{
  "type": "Feature",
  "properties": {
    "iso:country":"DE",
    "sg:address":"Neustr. 21",
    "sg:city":"Hechingen",
    "sg:phone":"+49 7471/3428",
    "sg:postcode":"72379",
    "sg:province":"Baden-W\u00fcrttemberg",
    "wof:name":"Star-kebap",
    "wof:placetype":"venue"
},
  "geometry": {"coordinates":[8.9627952576,48.3555145264],"type":"Point"}
}