{
  "type": "Feature",
  "properties": {
    "iso:country":"DE",
    "sg:address":"Prassekstr. 21",
    "sg:city":"L\u00fcbeck",
    "sg:phone":"+49 451/67776",
    "sg:postcode":"23566",
    "sg:province":"Schleswig-Holstein",
    "wof:name":"Herbert Linke",
    "wof:placetype":"venue"
},
  "geometry": {"coordinates":[10.729456,53.872555],"type":"Point"}
}