{
  "type": "Feature",
  "properties": {
    "iso:country":"DE",
    "sg:address":"Mozartstr. 37",
    "sg:city":"Gotha",
    "sg:phone":"+49 3621/82320",
    "sg:postcode":"99867",
    "sg:province":"Th\u00fcringen",
    "wof:name":"J\u00fcrgen Kurz Unternehmens- Beratungsgesellschaft Mbh",
    "wof:placetype":"venue"
},
  "geometry": {"coordinates":[10.714857,50.940731],"type":"Point"}
}