{
  "type": "Feature",
  "properties": {
    "iso:country":"DE",
    "sg:address":"Kirchplatz 5",
    "sg:city":"\u00dcbach-Palenberg",
    "sg:phone":"+49 2451/900019",
    "sg:postcode":"52531",
    "sg:province":"Nordrhein-Westfalen",
    "wof:name":"Restaurant Haus Hagen",
    "wof:placetype":"venue"
},
  "geometry": {"coordinates":[6.1225647926,50.9180183411],"type":"Point"}
}