{
  "type": "Feature",
  "properties": {
    "iso:country":"DE",
    "sg:address":"Birkenriedstr. 35",
    "sg:city":"Peiting",
    "sg:phone":"+49 8861/5691",
    "sg:postcode":"86971",
    "sg:province":"Bayern",
    "wof:name":"Thomas Bock",
    "wof:placetype":"venue"
},
  "geometry": {"coordinates":[10.9331035614,47.8031082153],"type":"Point"}
}