{
  "type": "Feature",
  "properties": {
    "iso:country":"DE",
    "sg:address":"Viktoriastr. 56",
    "sg:city":"Velten",
    "sg:phone":"+49 3304/34122",
    "sg:postcode":"16727",
    "sg:province":"Brandenburg",
    "wof:name":"Gemeinn\u00fctzige Wohnungs- Genossenschaft Velten-",
    "wof:placetype":"venue"
},
  "geometry": {"coordinates":[13.1752700806,52.6881980896],"type":"Point"}
}