{
  "type": "Feature",
  "properties": {
    "iso:country":"DE",
    "sg:address":"Wasenstr. 9",
    "sg:city":"Villingen-Schwenningen",
    "sg:phone":"+49 7720/31193",
    "sg:postcode":"78054",
    "sg:province":"Baden-W\u00fcrttemberg",
    "wof:name":"Hans F\u00fcllemann",
    "wof:placetype":"venue"
},
  "geometry": {"coordinates":[8.5205841064,48.0621070862],"type":"Point"}
}