{
  "type": "Feature",
  "properties": {
    "iso:country":"DE",
    "sg:address":"Emmericher Str. 155",
    "sg:city":"Kleve",
    "sg:phone":"+49 2821/798686",
    "sg:postcode":"47533",
    "sg:province":"Nordrhein-Westfalen",
    "wof:name":"Bierklause",
    "wof:placetype":"venue"
},
  "geometry": {"coordinates":[6.1586318016,51.7987976074],"type":"Point"}
}