{
  "type": "Feature",
  "properties": {
    "iso:country":"DE",
    "sg:address":"Deversdonk 3",
    "sg:city":"Grefrath",
    "sg:phone":"+49 2158/8218",
    "sg:postcode":"47929",
    "sg:province":"Nordrhein-Westfalen",
    "wof:name":"M. Oomen",
    "wof:placetype":"venue"
},
  "geometry": {"coordinates":[6.342077,51.33712],"type":"Point"}
}