{
  "type": "Feature",
  "properties": {
    "iso:country":"DE",
    "sg:address":"Stemmering 20",
    "sg:city":"Essen",
    "sg:phone":"+49 201/2205190",
    "sg:postcode":"45259",
    "sg:province":"Nordrhein-Westfalen",
    "wof:name":"Evangelisches Altenwohnheim Essen-heisingen Ggmbh",
    "wof:placetype":"venue"
},
  "geometry": {"coordinates":[7.062349,51.400196],"type":"Point"}
}