{
  "type": "Feature",
  "properties": {
    "iso:country":"DE",
    "sg:address":"Hunteburger Str. 5",
    "sg:city":"Bohmte",
    "sg:phone":"+49 5473/640",
    "sg:postcode":"49163",
    "sg:province":"Niedersachsen",
    "wof:name":"Gottfried Bok\u00e4mper Innenarchitekt",
    "wof:placetype":"venue"
},
  "geometry": {"coordinates":[8.268592,52.363926],"type":"Point"}
}