{
  "type": "Feature",
  "properties": {
    "iso:country":"DE",
    "sg:address":"Gottlieb-Daimler-Str. 1",
    "sg:city":"Twistringen",
    "sg:phone":"+49 4243/2111",
    "sg:postcode":"27239",
    "sg:province":"Niedersachsen",
    "wof:name":"Fritz W\u00fcppenhorst",
    "wof:placetype":"venue"
},
  "geometry": {"coordinates":[8.637984,52.789261],"type":"Point"}
}