{
  "type": "Feature",
  "properties": {
    "iso:country":"DE",
    "sg:address":"Waldstrasse 24::",
    "sg:city":"Aichwald",
    "sg:phone":"+49 4971/1369060",
    "sg:postcode":"73773",
    "sg:province":"Baden-W\u00fcrttemberg",
    "wof:name":"Karl Klein Ventilatorenbau Gmbh",
    "wof:placetype":"venue"
},
  "geometry": {"coordinates":[9.380052,48.749428],"type":"Point"}
}