{
  "type": "Feature",
  "properties": {
    "iso:country":"DE",
    "sg:address":"H\u00fcgelstr 4",
    "sg:city":"Stemwede",
    "sg:phone":"+49 5745/92070",
    "sg:postcode":"32351",
    "sg:province":"Nordrhein-Westfalen",
    "wof:name":"Redecker Fleischwaren Gmbh",
    "wof:placetype":"venue"
},
  "geometry": {"coordinates":[8.451165,52.376213],"type":"Point"}
}