{
  "type": "Feature",
  "properties": {
    "iso:country":"DE",
    "sg:address":"Frommerner Str. 51",
    "sg:city":"Balingen",
    "sg:phone":"+49 7433/3263",
    "sg:postcode":"72336",
    "sg:province":"Baden-W\u00fcrttemberg",
    "wof:name":"W. Kipp",
    "wof:placetype":"venue"
},
  "geometry": {"coordinates":[8.865462,48.244869],"type":"Point"}
}