{
  "type": "Feature",
  "properties": {
    "iso:country":"DE",
    "sg:address":"Mariahilfer Str. 3a",
    "sg:city":"F\u00fcssen",
    "sg:phone":"+49 8362/37111",
    "sg:postcode":"87629",
    "sg:province":"Bayern",
    "wof:name":"D. Haas",
    "wof:placetype":"venue"
},
  "geometry": {"coordinates":[10.6899471283,47.572883606],"type":"Point"}
}