{
  "type": "Feature",
  "properties": {
    "iso:country":"DE",
    "sg:address":"Am Kl\u00f6\u00dfberg 7",
    "sg:city":"Neuhof",
    "sg:phone":"+49 661/44972",
    "sg:postcode":"36119",
    "sg:province":"Hessen",
    "wof:name":"U. Kl\u00fch",
    "wof:placetype":"venue"
},
  "geometry": {"coordinates":[9.5678701401,50.5047531128],"type":"Point"}
}