{
  "type": "Feature",
  "properties": {
    "iso:country":"DE",
    "sg:address":"Vinckeufer 3",
    "sg:city":"Duisburg",
    "sg:postcode":"47119",
    "sg:province":"Nordrhein-Westfalen",
    "wof:name":"Dsu Gesellschaft F\u00fcr Industrierohstoffe Mbh",
    "wof:placetype":"venue"
},
  "geometry": {"coordinates":[6.7419891357,51.4480667114],"type":"Point"}
}