{
  "type": "Feature",
  "properties": {
    "iso:country":"DE",
    "sg:address":"61184",
    "sg:city":"Karben",
    "sg:phone":"+49 6039/3510",
    "sg:postcode":"61184",
    "sg:province":"Hessen",
    "wof:name":"Deutsche Bahn Ag",
    "wof:placetype":"venue"
},
  "geometry": {"coordinates":[8.7575502396,50.2312889099],"type":"Point"}
}