{
  "type": "Feature",
  "properties": {
    "iso:country":"DE",
    "sg:address":"Landwehrstr. 1",
    "sg:city":"Vechta",
    "sg:phone":"+49 4441/81068",
    "sg:postcode":"49377",
    "sg:province":"Niedersachsen",
    "wof:name":"St. Hedwig-stift",
    "wof:placetype":"venue"
},
  "geometry": {"coordinates":[8.284533,52.708866],"type":"Point"}
}