{
  "type": "Feature",
  "properties": {
    "iso:country":"DE",
    "sg:address":"Friedberger Landstr. 63",
    "sg:city":"Frankfurt",
    "sg:phone":"+49 69/5978940",
    "sg:postcode":"60316",
    "sg:province":"Hessen",
    "wof:name":"Tango",
    "wof:placetype":"venue"
},
  "geometry": {"coordinates":[8.691192627,50.1227798462],"type":"Point"}
}