{
  "type": "Feature",
  "properties": {
    "iso:country":"DE",
    "sg:address":"Spichernstr. 52",
    "sg:city":"Solingen",
    "sg:phone":"+49 212/320734",
    "sg:postcode":"42699",
    "sg:province":"Nordrhein-Westfalen",
    "wof:name":"Christiane Gerold-tenbuhs Architekt",
    "wof:placetype":"venue"
},
  "geometry": {"coordinates":[7.03116,51.172272],"type":"Point"}
}