{
  "type": "Feature",
  "properties": {
    "iso:country":"DE",
    "sg:address":"B\u00fcrgelsche Str. 41",
    "sg:city":"Dorndorf-Steudnitz",
    "sg:phone":"+49 36427/22569",
    "sg:postcode":"07778",
    "sg:province":"Th\u00fcringen",
    "wof:name":"Uwe Feukert",
    "wof:placetype":"venue"
},
  "geometry": {"coordinates":[11.674746,51.003967],"type":"Point"}
}