{
  "type": "Feature",
  "properties": {
    "iso:country":"DE",
    "sg:address":"Gr\u00fcner Weg 55",
    "sg:city":"L\u00fcbeck",
    "sg:phone":"+49 451/38389",
    "sg:postcode":"23566",
    "sg:province":"Schleswig-Holstein",
    "wof:name":"Christa Maria Brennan-gutsche Rechtsanw\u00e4ltin",
    "wof:placetype":"venue"
},
  "geometry": {"coordinates":[10.7114620209,53.8831481934],"type":"Point"}
}