{
  "type": "Feature",
  "properties": {
    "iso:country":"DE",
    "sg:address":"Mayener Str. 18",
    "sg:city":"Kelberg",
    "sg:phone":"+49 2692/87080",
    "sg:postcode":"53539",
    "sg:province":"Rheinland-Pfalz",
    "wof:name":"M\u00fcller-holz Gmbh",
    "wof:placetype":"venue"
},
  "geometry": {"coordinates":[6.9239168167,50.2854881287],"type":"Point"}
}