{
  "type": "Feature",
  "properties": {
    "iso:country":"DE",
    "sg:address":"Neckarstr. 18",
    "sg:city":"Ilvesheim",
    "sg:phone":"+49 621/492718",
    "sg:postcode":"68549",
    "sg:province":"Baden-W\u00fcrttemberg",
    "wof:name":"Bruno Kohs",
    "wof:placetype":"venue"
},
  "geometry": {"coordinates":[8.564803,49.475861],"type":"Point"}
}