{
  "type": "Feature",
  "properties": {
    "iso:country":"DE",
    "sg:address":"Am Freisch\u00fctz 16",
    "sg:city":"Duisburg",
    "sg:postcode":"47058",
    "sg:province":"Nordrhein-Westfalen",
    "wof:name":"Grundst\u00fccksgesellschaft Hermann Kleine-moellhoff Mbh",
    "wof:placetype":"venue"
},
  "geometry": {"coordinates":[6.798785,51.435307],"type":"Point"}
}