{
  "type": "Feature",
  "properties": {
    "iso:country":"DE",
    "sg:address":"Neustr. 24",
    "sg:city":"Emmendingen",
    "sg:phone":"+49 7641/42247",
    "sg:postcode":"79312",
    "sg:province":"Baden-W\u00fcrttemberg",
    "wof:name":"Lanz",
    "wof:placetype":"venue"
},
  "geometry": {"coordinates":[7.83977,48.123188],"type":"Point"}
}