{
  "type": "Feature",
  "properties": {
    "iso:country":"DE",
    "sg:address":"Bahnhofstr. 53",
    "sg:city":"Hamminkeln",
    "sg:phone":"+49 2857/2228",
    "sg:postcode":"46499",
    "sg:province":"Nordrhein-Westfalen",
    "wof:name":"Erwin Boland",
    "wof:placetype":"venue"
},
  "geometry": {"coordinates":[6.52885,51.742001],"type":"Point"}
}