{
  "type": "Feature",
  "properties": {
    "iso:country":"DE",
    "sg:address":"Kolpingstr. 32",
    "sg:city":"Euskirchen",
    "sg:phone":"+49 2251/3250",
    "sg:postcode":"53879",
    "sg:province":"Nordrhein-Westfalen",
    "wof:name":"K\u00fcmpel Inh. Herbert Lanzrath Volksblatt-druckerei U.verlag",
    "wof:placetype":"venue"
},
  "geometry": {"coordinates":[6.786159,50.663055],"type":"Point"}
}