{
  "type": "Feature",
  "properties": {
    "iso:country":"DE",
    "sg:address":"Ihlendiek 2",
    "sg:city":"Braak",
    "sg:postcode":"22145",
    "sg:province":"Hamburg",
    "wof:name":"Braak-city",
    "wof:placetype":"venue"
},
  "geometry": {"coordinates":[-79.016075,38.922325],"type":"Point"}
}