{
  "type": "Feature",
  "properties": {
    "iso:country":"DE",
    "sg:address":"Blumenstr. 48",
    "sg:city":"Leipzig",
    "sg:postcode":"04155",
    "sg:province":"Sachsen",
    "wof:name":"Max Woog",
    "wof:placetype":"venue"
},
  "geometry": {"coordinates":[12.374662,51.36158],"type":"Point"}
}