{
  "type": "Feature",
  "properties": {
    "iso:country":"DE",
    "sg:address":"Wulfspark 3",
    "sg:city":"Hannover",
    "sg:phone":"+49 511/9524365",
    "sg:postcode":"30559",
    "sg:province":"Niedersachsen",
    "wof:name":"S. Laxgang",
    "wof:placetype":"venue"
},
  "geometry": {"coordinates":[9.8236236572,52.3614311218],"type":"Point"}
}