{
  "type": "Feature",
  "properties": {
    "iso:country":"DE",
    "sg:address":"Gruener Weg 3a",
    "sg:city":"Barchfeld",
    "sg:phone":"+49 36961",
    "sg:postcode":"36456",
    "sg:province":"Th\u00fcringen",
    "wof:name":"X-tra Tours, Ihr Partner F\u00fcr Erholung Und Kultur.",
    "wof:placetype":"venue"
},
  "geometry": {"coordinates":[10.301725,50.796577],"type":"Point"}
}