{
  "type": "Feature",
  "properties": {
    "iso:country":"DE",
    "sg:address":"Wenauer Strasse 21a",
    "sg:city":"Stolberg",
    "sg:phone":"+49 2409/702940",
    "sg:postcode":"52224",
    "sg:province":"Nordrhein-Westfalen",
    "wof:name":"Fliesen - Marmor - Braun Gmbh",
    "wof:placetype":"venue"
},
  "geometry": {"coordinates":[6.3077301979,50.7734527588],"type":"Point"}
}