{
  "type": "Feature",
  "properties": {
    "iso:country":"DE",
    "sg:address":"Radlerstr. 12",
    "sg:city":"Hildesheim",
    "sg:phone":"+49 5121/57028",
    "sg:postcode":"31135",
    "sg:province":"Niedersachsen",
    "wof:name":"Bakeberg & L\u00f6hner",
    "wof:placetype":"venue"
},
  "geometry": {"coordinates":[9.99245,52.16782],"type":"Point"}
}