{
  "type": "Feature",
  "properties": {
    "iso:country":"DE",
    "sg:address":"M\u00fchlfeldweg 13",
    "sg:city":"Altenbuch",
    "sg:phone":"+49 9392/93986",
    "sg:postcode":"97901",
    "sg:province":"Bayern",
    "wof:name":"W. K. Haus-bautr\u00e4ger Gmbh",
    "wof:placetype":"venue"
},
  "geometry": {"coordinates":[9.408577,49.821957],"type":"Point"}
}