{
  "type": "Feature",
  "properties": {
    "iso:country":"DE",
    "sg:address":"Hallgartener Str. 13",
    "sg:city":"Oestrich-Winkel",
    "sg:phone":"+49 6723/3924",
    "sg:postcode":"65375",
    "sg:province":"Hessen",
    "wof:name":"Jakob Nikolai",
    "wof:placetype":"venue"
},
  "geometry": {"coordinates":[8.0323867798,50.0086898804],"type":"Point"}
}