{
  "type": "Feature",
  "properties": {
    "iso:country":"DE",
    "sg:address":"Burgstr. 25",
    "sg:city":"Ruppichteroth",
    "sg:phone":"+49 2295/5250",
    "sg:postcode":"53809",
    "sg:province":"Nordrhein-Westfalen",
    "wof:name":"Ristorante Da Franco",
    "wof:placetype":"venue"
},
  "geometry": {"coordinates":[7.4824061394,50.8448410034],"type":"Point"}
}