{
  "type": "Feature",
  "properties": {
    "iso:country":"DE",
    "sg:address":"Fuggerstr. 8 a",
    "sg:city":"Schwindegg",
    "sg:phone":"+49 8082/94424",
    "sg:postcode":"84419",
    "sg:province":"Bayern",
    "wof:name":"Anton Westenthanner Arzt F\u00fcr Allgemeinmedizin",
    "wof:placetype":"venue"
},
  "geometry": {"coordinates":[12.2611598969,48.2713699341],"type":"Point"}
}