{
  "type": "Feature",
  "properties": {
    "iso:country":"DE",
    "sg:address":"Neue Str. 13",
    "sg:city":"Fuldabr\u00fcck",
    "sg:phone":"+49 561/582300",
    "sg:postcode":"34277",
    "sg:province":"Hessen",
    "wof:name":"W\u00e4scherei-schneewei\u00df Manfred Birkenstock",
    "wof:placetype":"venue"
},
  "geometry": {"coordinates":[9.499710083,51.2645454407],"type":"Point"}
}