{
  "type": "Feature",
  "properties": {
    "iso:country":"DE",
    "sg:address":"Am Stillhof 6",
    "sg:city":"Gedern",
    "sg:phone":"+49 6045/96080",
    "sg:postcode":"63688",
    "sg:province":"Hessen",
    "wof:name":"Poly-clip System Gmbh",
    "wof:placetype":"venue"
},
  "geometry": {"coordinates":[9.195479,50.418839],"type":"Point"}
}