{
  "type": "Feature",
  "properties": {
    "iso:country":"DE",
    "sg:address":"Br\u00fcckenstr. 77",
    "sg:city":"Weilburg",
    "sg:phone":"+49 6471/51211",
    "sg:postcode":"35781",
    "sg:province":"Hessen",
    "wof:name":"Erich W\u00fcst",
    "wof:placetype":"venue"
},
  "geometry": {"coordinates":[8.2015695572,50.4651298523],"type":"Point"}
}