{
  "type": "Feature",
  "properties": {
    "iso:country":"DE",
    "sg:address":"Hindenburgstr. 26",
    "sg:city":"P\u00f6cking",
    "sg:phone":"+49 8157/93410",
    "sg:postcode":"82343",
    "sg:province":"Bayern",
    "wof:name":"Lhi Cb Leasing Gmbh",
    "wof:placetype":"venue"
},
  "geometry": {"coordinates":[11.304967,47.964485],"type":"Point"}
}