{
  "type": "Feature",
  "properties": {
    "iso:country":"DE",
    "sg:address":"Rechte Bachgasse 17",
    "sg:city":"Ochsenfurt",
    "sg:phone":"+49 9331/1053",
    "sg:postcode":"97199",
    "sg:province":"Bayern",
    "wof:name":"Heinrich Gernet",
    "wof:placetype":"venue"
},
  "geometry": {"coordinates":[10.0289640427,49.6804199219],"type":"Point"}
}