{
  "type": "Feature",
  "properties": {
    "iso:country":"DE",
    "sg:address":"Vincentiusstr. 9",
    "sg:city":"Karlsruhe",
    "sg:phone":"+49 721/815880",
    "sg:postcode":"76137",
    "sg:province":"Baden-W\u00fcrttemberg",
    "wof:name":"Kurt Widmer",
    "wof:placetype":"venue"
},
  "geometry": {"coordinates":[8.3897838593,48.997543335],"type":"Point"}
}