{
  "type": "Feature",
  "properties": {
    "iso:country":"DE",
    "sg:address":"Furtmayrstr. 10",
    "sg:city":"Regensburg",
    "sg:phone":"+49 941/709700",
    "sg:postcode":"93053",
    "sg:province":"Bayern",
    "wof:name":"Maharadscha",
    "wof:placetype":"venue"
},
  "geometry": {"coordinates":[12.1039218903,49.0095787048],"type":"Point"}
}