{
  "type": "Feature",
  "properties": {
    "iso:country":"DE",
    "sg:address":"Hauptstr. 11",
    "sg:city":"Ehrenburg",
    "sg:phone":"+49 4275/383",
    "sg:postcode":"27248",
    "sg:province":"Niedersachsen",
    "wof:name":"Edwin Mohrl\u00fcder",
    "wof:placetype":"venue"
},
  "geometry": {"coordinates":[8.704446,52.748257],"type":"Point"}
}