{
  "type": "Feature",
  "properties": {
    "iso:country":"DE",
    "sg:address":"Sprakener Str. 1",
    "sg:city":"Schwarme",
    "sg:phone":"+49 4258/528",
    "sg:postcode":"27327",
    "sg:province":"Niedersachsen",
    "wof:name":"Johann H. Masemann Omnibus- Verkehr Gmbh & Co. Kg",
    "wof:placetype":"venue"
},
  "geometry": {"coordinates":[9.0067358017,52.8848953247],"type":"Point"}
}