{
  "type": "Feature",
  "properties": {
    "iso:country":"DE",
    "sg:address":"Am Kirchkamp 1 +3",
    "sg:city":"Rosche",
    "sg:phone":"+49 5803/566",
    "sg:postcode":"29571",
    "sg:province":"Niedersachsen",
    "wof:name":"Schulz",
    "wof:placetype":"venue"
},
  "geometry": {"coordinates":[10.76188,52.986538],"type":"Point"}
}