{
  "type": "Feature",
  "properties": {
    "iso:country":"DE",
    "sg:address":"Hallerstr. 2",
    "sg:city":"Hamburg",
    "sg:phone":"+49 40/459578",
    "sg:postcode":"20146",
    "sg:province":"Hamburg",
    "wof:name":"Haller-stube",
    "wof:placetype":"venue"
},
  "geometry": {"coordinates":[9.9791173935,53.5723266602],"type":"Point"}
}