{
  "type": "Feature",
  "properties": {
    "iso:country":"DE",
    "sg:address":"Bunsenstr. 3",
    "sg:city":"Straubenhardt",
    "sg:postcode":"75334",
    "sg:province":"Baden-W\u00fcrttemberg",
    "wof:name":"Gdp Verzahnungstechnik Gmbh",
    "wof:placetype":"venue"
},
  "geometry": {"coordinates":[8.520871,48.850143],"type":"Point"}
}