{
  "type": "Feature",
  "properties": {
    "iso:country":"DE",
    "sg:address":"Feldgarten 2 b",
    "sg:city":"Hamm",
    "sg:postcode":"59063",
    "sg:province":"Nordrhein-Westfalen",
    "wof:name":"But Gmbh",
    "wof:placetype":"venue"
},
  "geometry": {"coordinates":[7.851973,51.667801],"type":"Point"}
}