{
  "type": "Feature",
  "properties": {
    "iso:country":"DE",
    "sg:address":"Rosentalstr. 6",
    "sg:city":"Remscheid",
    "sg:phone":"+49 2191/50000",
    "sg:postcode":"42899",
    "sg:province":"Nordrhein-Westfalen",
    "wof:name":"Stracke & Co. Verwaltungs-gmbh",
    "wof:placetype":"venue"
},
  "geometry": {"coordinates":[7.246711,51.216637],"type":"Point"}
}