{
  "type": "Feature",
  "properties": {
    "iso:country":"DE",
    "sg:address":"Linderner Str. 10",
    "sg:city":"Lastrup",
    "sg:phone":"+49 4472/920092",
    "sg:postcode":"49688",
    "sg:province":"Niedersachsen",
    "wof:name":"Saalfeld-kosmetik A. Saalfeld",
    "wof:placetype":"venue"
},
  "geometry": {"coordinates":[7.859363,52.796711],"type":"Point"}
}