{
  "type": "Feature",
  "properties": {
    "iso:country":"DE",
    "sg:address":"Zu den Gr\u00fcnden 19",
    "sg:city":"Ahrensb\u00f6k",
    "sg:phone":"+49 4505/446",
    "sg:postcode":"23623",
    "sg:province":"Schleswig-Holstein",
    "wof:name":"Hans M\u00f6ller & S\u00f6hne Gmbh",
    "wof:placetype":"venue"
},
  "geometry": {"coordinates":[10.587544,53.953991],"type":"Point"}
}