{
  "type": "Feature",
  "properties": {
    "iso:country":"DE",
    "sg:address":"Vlothoer Str. 65a",
    "sg:city":"Herford",
    "sg:phone":"+49 5221/86798",
    "sg:postcode":"32049",
    "sg:province":"Nordrhein-Westfalen",
    "wof:name":"Software-service Rethemeier Inh. Klaus Rethemeier",
    "wof:placetype":"venue"
},
  "geometry": {"coordinates":[8.699215889,52.1155166626],"type":"Point"}
}