{
  "type": "Feature",
  "properties": {
    "iso:country":"DE",
    "sg:address":"Bahrenfelder Str. 192",
    "sg:city":"Hamburg",
    "sg:phone":"+49 40/8663939",
    "sg:postcode":"22765",
    "sg:province":"Hamburg",
    "wof:name":"Wasch Center Technik Www- Gmbh",
    "wof:placetype":"venue"
},
  "geometry": {"coordinates":[9.928838,53.555031],"type":"Point"}
}