{
  "type": "Feature",
  "properties": {
    "iso:country":"DE",
    "sg:address":"Am Kirchenberg 1",
    "sg:city":"Hellenthal",
    "sg:phone":"+49 2482/2287",
    "sg:postcode":"53940",
    "sg:province":"Nordrhein-Westfalen",
    "wof:name":"Kath. Pfarramt St. Brigida",
    "wof:placetype":"venue"
},
  "geometry": {"coordinates":[6.4570088387,50.4948768616],"type":"Point"}
}