{
  "type": "Feature",
  "properties": {
    "iso:country":"DE",
    "sg:address":"Harsewinkelweg 5",
    "sg:city":"Rheda-Wiedenbr\u00fcck",
    "sg:phone":"+49 5242/5198",
    "sg:postcode":"33378",
    "sg:province":"Nordrhein-Westfalen",
    "wof:name":"Dietmar Werner",
    "wof:placetype":"venue"
},
  "geometry": {"coordinates":[8.3196811676,51.8396568298],"type":"Point"}
}