{
  "type": "Feature",
  "properties": {
    "iso:country":"DE",
    "sg:address":"Wiedaustr. 112",
    "sg:city":"M\u00fcnster",
    "sg:phone":"+49 2501/5568",
    "sg:postcode":"48163",
    "sg:province":"Nordrhein-Westfalen",
    "wof:name":"An De Wiedau",
    "wof:placetype":"venue"
},
  "geometry": {"coordinates":[7.5793499947,51.8939704895],"type":"Point"}
}