{
  "type": "Feature",
  "properties": {
    "iso:country":"DE",
    "sg:address":"Oststr. 7",
    "sg:city":"Oberstdorf",
    "sg:phone":"+49 8322/4897",
    "sg:postcode":"87561",
    "sg:province":"Bayern",
    "wof:name":"Allg\u00e4uer Volksbank Eg",
    "wof:placetype":"venue"
},
  "geometry": {"coordinates":[10.279809,47.406582],"type":"Point"}
}