{
  "type": "Feature",
  "properties": {
    "iso:country":"DE",
    "sg:address":"Lenaustr. 80",
    "sg:city":"Frankfurt",
    "sg:phone":"+49 69/555776",
    "sg:postcode":"60318",
    "sg:province":"Hessen",
    "wof:name":"Hagen Und Scharnberger Architekten",
    "wof:placetype":"venue"
},
  "geometry": {"coordinates":[8.689085,50.128628],"type":"Point"}
}