{
  "type": "Feature",
  "properties": {
    "iso:country":"DE",
    "sg:address":"In der Wehrhecke 30",
    "sg:city":"Bonn",
    "sg:phone":"+49 228/258003",
    "sg:postcode":"53125",
    "sg:province":"Nordrhein-Westfalen",
    "wof:name":"Meyer Zu K\u00fcddesen Multi-service Inh. Margret",
    "wof:placetype":"venue"
},
  "geometry": {"coordinates":[7.0693411827,50.6759719849],"type":"Point"}
}