{
  "type": "Feature",
  "properties": {
    "iso:country":"DE",
    "sg:address":"Frielicker Weg 41",
    "sg:city":"Hamm",
    "sg:postcode":"59073",
    "sg:province":"Nordrhein-Westfalen",
    "wof:name":"Baden Stahlexport Und Engineering E. Kfm.",
    "wof:placetype":"venue"
},
  "geometry": {"coordinates":[7.83138,51.718109],"type":"Point"}
}