{
  "type": "Feature",
  "properties": {
    "iso:country":"DE",
    "sg:address":"Espachstr. 15",
    "sg:city":"Balingen",
    "sg:postcode":"72336",
    "sg:province":"Baden-W\u00fcrttemberg",
    "wof:name":"Kom Tec Verwaltungs-gmbh",
    "wof:placetype":"venue"
},
  "geometry": {"coordinates":[8.8637695312,48.234085083],"type":"Point"}
}