{
  "type": "Feature",
  "properties": {
    "iso:country":"DE",
    "sg:address":"Eichendorffstr. 2",
    "sg:city":"Neckargem\u00fcnd",
    "sg:phone":"+49 6223/7088",
    "sg:postcode":"69151",
    "sg:province":"Baden-W\u00fcrttemberg",
    "wof:name":"Katholisches Pfarramt St. Franziskus",
    "wof:placetype":"venue"
},
  "geometry": {"coordinates":[8.8031520844,49.3848648071],"type":"Point"}
}