{
  "type": "Feature",
  "properties": {
    "iso:country":"DE",
    "sg:address":"M\u00f6llingerstr. 1",
    "sg:city":"H\u00f6xter",
    "sg:phone":"+49 4952/716830",
    "sg:postcode":"37671",
    "sg:province":"Nordrhein-Westfalen",
    "wof:name":"Volksbank H\u00f6xter-beverungen Eg",
    "wof:placetype":"venue"
},
  "geometry": {"coordinates":[9.380973,51.775272],"type":"Point"}
}