{
  "type": "Feature",
  "properties": {
    "iso:country":"DE",
    "sg:address":"Dr.-Paul-M\u00fcller-Str. 70",
    "sg:city":"Lennestadt",
    "sg:postcode":"57368",
    "sg:province":"Nordrhein-Westfalen",
    "wof:name":"Prokon Alu-tec Gmbh",
    "wof:placetype":"venue"
},
  "geometry": {"coordinates":[8.0144300461,51.118019104],"type":"Point"}
}