{
  "type": "Feature",
  "properties": {
    "iso:country":"DE",
    "sg:address":"Dr.-Kurt-Steim-Str. 18",
    "sg:city":"Schramberg",
    "sg:postcode":"78713",
    "sg:province":"Baden-W\u00fcrttemberg",
    "wof:name":"Armbruster Fliesen Und Natursteine Gmbh",
    "wof:placetype":"venue"
},
  "geometry": {"coordinates":[8.4216270447,48.234752655],"type":"Point"}
}