{
  "type": "Feature",
  "properties": {
    "iso:country":"DE",
    "sg:address":"Wilhelmstr. 2",
    "sg:city":"Angelbachtal",
    "sg:phone":"+49 7265/1644",
    "sg:postcode":"74918",
    "sg:province":"Baden-W\u00fcrttemberg",
    "wof:name":"Peter Beck",
    "wof:placetype":"venue"
},
  "geometry": {"coordinates":[8.7810125351,49.2268676758],"type":"Point"}
}