{
  "type": "Feature",
  "properties": {
    "iso:country":"DE",
    "sg:address":"Wilhelmstr. 19",
    "sg:city":"Coesfeld",
    "sg:postcode":"48653",
    "sg:province":"Nordrhein-Westfalen",
    "wof:name":"Www.meis-family.de",
    "wof:placetype":"venue"
},
  "geometry": {"coordinates":[7.159848,51.937744],"type":"Point"}
}