{
  "type": "Feature",
  "properties": {
    "iso:country":"DE",
    "sg:address":"Ellmendinger Str. 23",
    "sg:city":"Karlsruhe",
    "sg:phone":"+49 721/492400",
    "sg:postcode":"76227",
    "sg:province":"Baden-W\u00fcrttemberg",
    "wof:name":"J\u00fcrgen Goldschmidt Masseur",
    "wof:placetype":"venue"
},
  "geometry": {"coordinates":[8.458516,48.993877],"type":"Point"}
}