{
  "type": "Feature",
  "properties": {
    "iso:country":"DE",
    "sg:address":"R\u00e4uschstr. 18-20",
    "sg:city":"Berlin",
    "sg:phone":"+49 30/4338051",
    "sg:postcode":"13509",
    "sg:province":"Berlin",
    "wof:name":"Katholisches Pfarramt Allerheiligen",
    "wof:placetype":"venue"
},
  "geometry": {"coordinates":[13.3012180328,52.5840377808],"type":"Point"}
}