{
  "type": "Feature",
  "properties": {
    "iso:country":"DE",
    "sg:address":"R\u00f6merstr. 3",
    "sg:city":"M\u00fcnchen",
    "sg:phone":"+49 89/336274",
    "sg:postcode":"80801",
    "sg:province":"Bayern",
    "wof:name":"Karl Knospe",
    "wof:placetype":"venue"
},
  "geometry": {"coordinates":[11.576849,48.158276],"type":"Point"}
}