{
  "type": "Feature",
  "properties": {
    "iso:country":"DE",
    "sg:address":"Hildesheimer Str. 35",
    "sg:city":"Bad Gandersheim",
    "sg:phone":"+49 5382/7010",
    "sg:postcode":"37581",
    "sg:province":"Niedersachsen",
    "wof:name":"Schott Auer Gmbh",
    "wof:placetype":"venue"
},
  "geometry": {"coordinates":[10.0298957825,51.8810882568],"type":"Point"}
}