{
  "type": "Feature",
  "properties": {
    "iso:country":"DE",
    "sg:address":"Josefinenstr. 7",
    "sg:city":"Sigmaringen",
    "sg:phone":"+49 7571/52227",
    "sg:postcode":"72488",
    "sg:province":"Baden-W\u00fcrttemberg",
    "wof:name":"Erwin A. Rettich Und Partner",
    "wof:placetype":"venue"
},
  "geometry": {"coordinates":[9.2188463211,48.0854034424],"type":"Point"}
}