{
  "type": "Feature",
  "properties": {
    "iso:country":"DE",
    "sg:address":"Klaus-Groth-Str. 29",
    "sg:city":"Neu Wulmstorf",
    "sg:phone":"+49 40/7008973",
    "sg:postcode":"21629",
    "sg:province":"Niedersachsen",
    "wof:name":"Andrea Und Ralf Dammann",
    "wof:placetype":"venue"
},
  "geometry": {"coordinates":[9.779317,53.458447],"type":"Point"}
}