{
  "type": "Feature",
  "properties": {
    "iso:country":"DE",
    "sg:address":"Clausewitzstr 36",
    "sg:city":"Wuppertal",
    "sg:phone":"+49 202/260710",
    "sg:postcode":"42389",
    "sg:province":"Nordrhein-Westfalen",
    "wof:name":"Rahmann Gmbh",
    "wof:placetype":"venue"
},
  "geometry": {"coordinates":[7.256718,51.278801],"type":"Point"}
}