{
  "type": "Feature",
  "properties": {
    "iso:country":"DE",
    "sg:address":"Klarastr. 1",
    "sg:city":"Freiburg",
    "sg:postcode":"79106",
    "sg:province":"Baden-W\u00fcrttemberg",
    "wof:name":"Christian Schmukle Gmbh",
    "wof:placetype":"venue"
},
  "geometry": {"coordinates":[7.840549,48.000008],"type":"Point"}
}