{
  "type": "Feature",
  "properties": {
    "iso:country":"DE",
    "sg:address":"Hauffweg 17",
    "sg:city":"Neuenstein",
    "sg:postcode":"74632",
    "sg:province":"Baden-W\u00fcrttemberg",
    "wof:name":"Koch Gmbh",
    "wof:placetype":"venue"
},
  "geometry": {"coordinates":[9.576246,49.209164],"type":"Point"}
}