{
  "type": "Feature",
  "properties": {
    "iso:country":"DE",
    "sg:address":"Markt 7",
    "sg:city":"Sondershausen",
    "sg:phone":"+49 3632/5220",
    "sg:postcode":"99706",
    "sg:province":"Th\u00fcringen",
    "wof:name":"Stadtarchiv",
    "wof:placetype":"venue"
},
  "geometry": {"coordinates":[10.872404,51.371284],"type":"Point"}
}