{
  "type": "Feature",
  "properties": {
    "iso:country":"DE",
    "sg:address":"An den Brauwiesen 20",
    "sg:city":"J\u00fcchsen",
    "sg:phone":"+49 36947/50110",
    "sg:postcode":"98631",
    "sg:province":"Th\u00fcringen",
    "wof:name":"H. Zimmermann",
    "wof:placetype":"venue"
},
  "geometry": {"coordinates":[10.507214,50.480328],"type":"Point"}
}