{
  "type": "Feature",
  "properties": {
    "iso:country":"DE",
    "sg:address":"Georgenstr. 23",
    "sg:city":"Berlin",
    "sg:phone":"+49 30/254313",
    "sg:postcode":"10117",
    "sg:province":"Berlin",
    "wof:name":"Cti-capital Treuhand Und Anlageges. F\u00fcr Immobilien Ag",
    "wof:placetype":"venue"
},
  "geometry": {"coordinates":[13.3864679337,52.5195999146],"type":"Point"}
}