{
  "type": "Feature",
  "properties": {
    "iso:country":"DE",
    "sg:address":"Kirchspiel 13",
    "sg:city":"D\u00fclmen",
    "sg:phone":"+49 2548/297",
    "sg:postcode":"48249",
    "sg:province":"Nordrhein-Westfalen",
    "wof:name":"Alfons Wermeling",
    "wof:placetype":"venue"
},
  "geometry": {"coordinates":[7.279348,51.828785],"type":"Point"}
}