{
  "type": "Feature",
  "properties": {
    "iso:country":"DE",
    "sg:address":"Peter-Swyn-Str. 47a",
    "sg:city":"Lehe",
    "sg:phone":"+49 4882/425",
    "sg:postcode":"25774",
    "sg:province":"Schleswig-Holstein",
    "wof:name":"E. Und J. Postel",
    "wof:placetype":"venue"
},
  "geometry": {"coordinates":[9.024638,54.341339],"type":"Point"}
}