{
  "type": "Feature",
  "properties": {
    "iso:country":"DE",
    "sg:address":"Rodauer Str. 20",
    "sg:city":"Alsbach-H\u00e4hnlein",
    "sg:phone":"+49 6257/3704",
    "sg:postcode":"64665",
    "sg:province":"Hessen",
    "wof:name":"H. Nickel",
    "wof:placetype":"venue"
},
  "geometry": {"coordinates":[8.574965,49.735256],"type":"Point"}
}