{
  "type": "Feature",
  "properties": {
    "iso:country":"DE",
    "sg:address":"Eifelstr. 29",
    "sg:city":"Bonn",
    "sg:postcode":"53119",
    "sg:province":"Nordrhein-Westfalen",
    "wof:name":"Bwa Bonner Wirtschaftsakademie Gmbh",
    "wof:placetype":"venue"
},
  "geometry": {"coordinates":[7.0834088326,50.7369308472],"type":"Point"}
}