{
  "type": "Feature",
  "properties": {
    "iso:country":"DE",
    "sg:address":"K\u00fcckelheim",
    "sg:city":"Schmallenberg",
    "sg:phone":"+49 2971/86961",
    "sg:postcode":"57392",
    "sg:province":"Nordrhein-Westfalen",
    "wof:name":"Pension Josef Hengesbach",
    "wof:placetype":"venue"
},
  "geometry": {"coordinates":[8.1947498322,51.1771659851],"type":"Point"}
}