{
  "type": "Feature",
  "properties": {
    "iso:country":"DE",
    "sg:address":"Wilhelm-Hamacher-Pl",
    "sg:city":"Troisdorf",
    "sg:phone":"+49 2241/79557",
    "sg:postcode":"53844",
    "sg:province":"Nordrhein-Westfalen",
    "wof:name":"Raiffeisenbank Rhein-sieg Eg",
    "wof:placetype":"venue"
},
  "geometry": {"coordinates":[7.094024,50.772327],"type":"Point"}
}