{
  "type": "Feature",
  "properties": {
    "iso:country":"DE",
    "sg:address":"Helenenstr 85",
    "sg:city":"Viersen",
    "sg:phone":"+49 2162/933810",
    "sg:postcode":"41748",
    "sg:province":"Nordrhein-Westfalen",
    "wof:name":"Mardis Gmbh",
    "wof:placetype":"venue"
},
  "geometry": {"coordinates":[6.418705,51.226948],"type":"Point"}
}