{
  "type": "Feature",
  "properties": {
    "iso:country":"DE",
    "sg:address":"Frankfurter Str. 22",
    "sg:city":"W\u00fcrzburg",
    "sg:postcode":"97082",
    "sg:province":"Bayern",
    "wof:name":"Mimiworld-kl\u00fcgelein Ohg",
    "wof:placetype":"venue"
},
  "geometry": {"coordinates":[9.9141607285,49.7947311401],"type":"Point"}
}