{
  "type": "Feature",
  "properties": {
    "iso:country":"DE",
    "sg:address":"Reetzstr. 58",
    "sg:city":"Pfinztal",
    "sg:phone":"+49 7240/942066",
    "sg:postcode":"76327",
    "sg:province":"Baden-W\u00fcrttemberg",
    "wof:name":"Nemko Verwaltungs Gmbh",
    "wof:placetype":"venue"
},
  "geometry": {"coordinates":[8.5379390717,48.9962463379],"type":"Point"}
}