{
  "type": "Feature",
  "properties": {
    "iso:country":"DE",
    "sg:address":"Alte Reihe 23",
    "sg:city":"D\u00f6rverden",
    "sg:phone":"+49 4234/555",
    "sg:postcode":"27313",
    "sg:province":"Niedersachsen",
    "wof:name":"Willi Grupe",
    "wof:placetype":"venue"
},
  "geometry": {"coordinates":[9.241375,52.858315],"type":"Point"}
}