{
  "type": "Feature",
  "properties": {
    "iso:country":"DE",
    "sg:address":"Rotteckring 4",
    "sg:city":"Freiburg",
    "sg:phone":"+49 761/34500",
    "sg:postcode":"79098",
    "sg:province":"Baden-W\u00fcrttemberg",
    "wof:name":"Hubertus-apotheke",
    "wof:placetype":"venue"
},
  "geometry": {"coordinates":[7.846524,47.995686],"type":"Point"}
}