{
  "type": "Feature",
  "properties": {
    "iso:country":"DE",
    "sg:address":"Ollenhauerstr. 118",
    "sg:city":"Berlin",
    "sg:phone":"+49 30/4122422",
    "sg:postcode":"13403",
    "sg:province":"Berlin",
    "wof:name":"Imbi\u00df Gerhard Schillinger",
    "wof:placetype":"venue"
},
  "geometry": {"coordinates":[13.3291950226,52.5682220459],"type":"Point"}
}