{
  "type": "Feature",
  "properties": {
    "iso:country":"DE",
    "sg:address":"Ostenfeldmark 25",
    "sg:city":"Lippstadt",
    "sg:phone":"+49 2941/4034",
    "sg:postcode":"59557",
    "sg:province":"Nordrhein-Westfalen",
    "wof:name":"M\u00f6rtenk\u00f6tter + S\u00f6bke Dental-technik Gmbh",
    "wof:placetype":"venue"
},
  "geometry": {"coordinates":[8.373111,51.678677],"type":"Point"}
}