{
  "type": "Feature",
  "properties": {
    "iso:country":"DE",
    "sg:address":"Andreaskloster 12",
    "sg:city":"K\u00f6ln",
    "sg:phone":"+49 221/134727",
    "sg:postcode":"50667",
    "sg:province":"Nordrhein-Westfalen",
    "wof:name":"Bankers",
    "wof:placetype":"venue"
},
  "geometry": {"coordinates":[6.9552078247,50.9423408508],"type":"Point"}
}