{
  "type": "Feature",
  "properties": {
    "iso:country":"DE",
    "sg:address":"Okertal 13-17",
    "sg:city":"Goslar",
    "sg:phone":"+49 4953/2133740",
    "sg:postcode":"38642",
    "sg:province":"Niedersachsen",
    "wof:name":"Vivares Getr\u00c4nke Gmbh & Co. Kg Betriebsst. Okertaler",
    "wof:placetype":"venue"
},
  "geometry": {"coordinates":[10.472899,51.885075],"type":"Point"}
}