{
  "type": "Feature",
  "properties": {
    "iso:country":"DE",
    "sg:address":"Wolfratshauser Str. 3",
    "sg:city":"Egling",
    "sg:phone":"+49 8176/7147",
    "sg:postcode":"82544",
    "sg:province":"Bayern",
    "wof:name":"Sebastian Spiegl",
    "wof:placetype":"venue"
},
  "geometry": {"coordinates":[11.5047559738,47.9228134155],"type":"Point"}
}