{
  "type": "Feature",
  "properties": {
    "iso:country":"DE",
    "sg:address":"Joseph-Rupp-Weg 7-9",
    "sg:city":"L\u00f6rrach",
    "sg:phone":"+49 7621/93220",
    "sg:postcode":"79540",
    "sg:province":"Baden-W\u00fcrttemberg",
    "wof:name":"Kath. Pflegeheim St. Fridolin",
    "wof:placetype":"venue"
},
  "geometry": {"coordinates":[7.666557,47.599846],"type":"Point"}
}