{
  "type": "Feature",
  "properties": {
    "iso:country":"DE",
    "sg:address":"Duume 2",
    "sg:city":"Fulda",
    "sg:phone":"+49 661/75933",
    "sg:postcode":"36043",
    "sg:province":"Hessen",
    "wof:name":"Eintracht",
    "wof:placetype":"venue"
},
  "geometry": {"coordinates":[9.6801300049,50.5485687256],"type":"Point"}
}