{
  "type": "Feature",
  "properties": {
    "iso:country":"DE",
    "sg:address":"Wilhelmstr. 12",
    "sg:city":"Reutlingen",
    "sg:phone":"+49 7121/320597",
    "sg:postcode":"72764",
    "sg:province":"Baden-W\u00fcrttemberg",
    "wof:name":"M\u00fcller Gmbh & Co. Grundst\u00fccksverwaltungs Kg",
    "wof:placetype":"venue"
},
  "geometry": {"coordinates":[9.2101364136,48.4937133789],"type":"Point"}
}