{
  "type": "Feature",
  "properties": {
    "iso:country":"DE",
    "sg:address":"Schulstr. 1",
    "sg:city":"Haselbach",
    "sg:phone":"+49 9961/6408",
    "sg:postcode":"94354",
    "sg:province":"Bayern",
    "wof:name":"Kawa Kachelofenbau Gmbh",
    "wof:placetype":"venue"
},
  "geometry": {"coordinates":[12.692196846,49.0032424927],"type":"Point"}
}