{
  "type": "Feature",
  "properties": {
    "iso:country":"DE",
    "sg:address":"T\u00f6pferstr 9a",
    "sg:city":"Schwabm\u00fcnchen",
    "sg:phone":"+49 8232/959760",
    "sg:postcode":"86830",
    "sg:province":"Bayern",
    "wof:name":"Sipa + Stross Gmbh Batterietechnik - Ladetechnik",
    "wof:placetype":"venue"
},
  "geometry": {"coordinates":[10.758456,48.19162],"type":"Point"}
}