{
  "type": "Feature",
  "properties": {
    "iso:country":"DE",
    "sg:address":"Geraer Str. 27",
    "sg:city":"Zeitz",
    "sg:postcode":"06712",
    "sg:province":"Sachsen-Anhalt",
    "wof:name":"Alfred Gelewski",
    "wof:placetype":"venue"
},
  "geometry": {"coordinates":[12.13607,51.035019],"type":"Point"}
}