{
  "type": "Feature",
  "properties": {
    "iso:country":"DE",
    "sg:address":"Im Dorf 28",
    "sg:city":"Nordrach",
    "sg:phone":"+49 7838/202",
    "sg:postcode":"77787",
    "sg:province":"Baden-W\u00fcrttemberg",
    "wof:name":"Stube Fam. Haas",
    "wof:placetype":"venue"
},
  "geometry": {"coordinates":[8.0798101425,48.3979110718],"type":"Point"}
}