{
  "type": "Feature",
  "properties": {
    "iso:country":"DE",
    "sg:address":"Bremer Str. 5",
    "sg:city":"Ostercappeln",
    "sg:phone":"+49 5473/1877",
    "sg:postcode":"49179",
    "sg:province":"Niedersachsen",
    "wof:name":"Heinrich Erdwien",
    "wof:placetype":"venue"
},
  "geometry": {"coordinates":[8.22249,52.343014],"type":"Point"}
}