{
  "type": "Feature",
  "properties": {
    "iso:country":"DE",
    "sg:address":"Schermcker Str. 14b",
    "sg:city":"Ampfurth",
    "sg:phone":"+49 39407/5823",
    "sg:postcode":"39387",
    "sg:province":"Sachsen-Anhalt",
    "wof:name":"Kindertagesst\u00e4tte",
    "wof:placetype":"venue"
},
  "geometry": {"coordinates":[11.3129396439,52.0628204346],"type":"Point"}
}