{
  "type": "Feature",
  "properties": {
    "iso:country":"DE",
    "sg:address":"S\u00fcdstr. 148",
    "sg:city":"Herzogenrath",
    "sg:phone":"+49 2407/8290",
    "sg:postcode":"52134",
    "sg:province":"Nordrhein-Westfalen",
    "wof:name":"Jansen",
    "wof:placetype":"venue"
},
  "geometry": {"coordinates":[6.0921640396,50.829284668],"type":"Point"}
}