{
  "type": "Feature",
  "properties": {
    "iso:country":"DE",
    "sg:address":"S\u00fcdring 6",
    "sg:city":"Bissersheim",
    "sg:phone":"+49 6359/5388",
    "sg:postcode":"67281",
    "sg:province":"Rheinland-Pfalz",
    "wof:name":"Hans Bischoff",
    "wof:placetype":"venue"
},
  "geometry": {"coordinates":[8.199016571,49.5356292725],"type":"Point"}
}