{
  "type": "Feature",
  "properties": {
    "iso:country":"DE",
    "sg:address":"Antoniusstr. 1a",
    "sg:city":"Bad M\u00fcnstereifel",
    "sg:phone":"+49 2257/7521",
    "sg:postcode":"53902",
    "sg:province":"Nordrhein-Westfalen",
    "wof:name":"Mauel Baugesellschaft Mbh",
    "wof:placetype":"venue"
},
  "geometry": {"coordinates":[6.8794131279,50.5398292542],"type":"Point"}
}