{
  "type": "Feature",
  "properties": {
    "iso:country":"DE",
    "sg:address":"Simon-Bolivar-Str. 51",
    "sg:city":"Berlin",
    "sg:postcode":"13055",
    "sg:province":"Berlin",
    "wof:name":"Systemhaus Balzer Gmbh",
    "wof:placetype":"venue"
},
  "geometry": {"coordinates":[13.4847421646,52.539516449],"type":"Point"}
}