{
  "type": "Feature",
  "properties": {
    "iso:country":"DE",
    "sg:address":"Neustadt 7",
    "sg:city":"Spangenberg",
    "sg:postcode":"34286",
    "sg:province":"Hessen",
    "wof:name":"Mister Holiday Reisen U. Ticketservice",
    "wof:placetype":"venue"
},
  "geometry": {"coordinates":[9.6636209488,51.1166229248],"type":"Point"}
}