{
  "type": "Feature",
  "properties": {
    "iso:country":"DE",
    "sg:address":"Emslandstr. 4",
    "sg:city":"Bremen",
    "sg:postcode":"28259",
    "sg:province":"Bremen",
    "wof:name":"Ejb Bauobjekt Verwaltungs Gmbh",
    "wof:placetype":"venue"
},
  "geometry": {"coordinates":[8.7665166855,53.0610618591],"type":"Point"}
}