{
  "type": "Feature",
  "properties": {
    "iso:country":"DE",
    "sg:address":"Am Steinr\u00fcck 5",
    "sg:city":"Schmalkalden",
    "sg:phone":"+49 3683/783567",
    "sg:postcode":"98574",
    "sg:province":"Th\u00fcringen",
    "wof:name":"Hasta Werkzeuge",
    "wof:placetype":"venue"
},
  "geometry": {"coordinates":[10.4536237717,50.7205810547],"type":"Point"}
}