{
  "type": "Feature",
  "properties": {
    "iso:country":"DE",
    "sg:address":"Schulstr. 10",
    "sg:city":"Achslach",
    "sg:phone":"+49 9929/903912",
    "sg:postcode":"94250",
    "sg:province":"Bayern",
    "wof:name":"Spedition Gruber Gmbh",
    "wof:placetype":"venue"
},
  "geometry": {"coordinates":[12.937865,48.968868],"type":"Point"}
}