{
  "type": "Feature",
  "properties": {
    "iso:country":"DE",
    "sg:address":"Herzogstr. 21",
    "sg:city":"Leverkusen",
    "sg:phone":"+49 2171/43606",
    "sg:postcode":"51379",
    "sg:province":"Nordrhein-Westfalen",
    "wof:name":"Ursel Kanzok",
    "wof:placetype":"venue"
},
  "geometry": {"coordinates":[7.001396,51.061687],"type":"Point"}
}