{
  "type": "Feature",
  "properties": {
    "iso:country":"DE",
    "sg:city":"Veitsbronn",
    "sg:phone":"+49 171 4521127",
    "sg:postcode":"90587",
    "sg:province":"Bayern",
    "wof:name":"Monika Hahn",
    "wof:placetype":"venue"
},
  "geometry": {"coordinates":[10.883379,49.511639],"type":"Point"}
}