{
  "type": "Feature",
  "properties": {
    "iso:country":"DE",
    "sg:address":"Hochfeldstr. 2",
    "sg:city":"Bad Heilbrunn",
    "sg:phone":"+49 8046/1233",
    "sg:postcode":"83670",
    "sg:province":"Bayern",
    "wof:name":"G. In. Ser Ges. F\u00fcr Chemische Produkte Mbh & Co. Kg",
    "wof:placetype":"venue"
},
  "geometry": {"coordinates":[11.435304,47.742027],"type":"Point"}
}