{
  "type": "Feature",
  "properties": {
    "iso:country":"DE",
    "sg:address":"Bahnhofstr. 7",
    "sg:city":"Hamm",
    "sg:phone":"+49 2381/25747",
    "sg:postcode":"59065",
    "sg:province":"Nordrhein-Westfalen",
    "wof:name":"Restaurant Isenbeck Deele Gmbh",
    "wof:placetype":"venue"
},
  "geometry": {"coordinates":[7.8125991821,51.6794281006],"type":"Point"}
}