{
  "type": "Feature",
  "properties": {
    "iso:country":"DE",
    "sg:address":"Gartenstr. 25",
    "sg:city":"Gro\u00dftreben-Zwethau",
    "sg:phone":"+49 3421/73270",
    "sg:postcode":"04886",
    "sg:province":"Sachsen",
    "wof:name":"Gramer Gmbh",
    "wof:placetype":"venue"
},
  "geometry": {"coordinates":[13.0460510254,51.5804290771],"type":"Point"}
}