{
  "type": "Feature",
  "properties": {
    "iso:country":"DE",
    "sg:address":"Sickinger Str. 52",
    "sg:city":"Kaiserslautern",
    "sg:phone":"+49 631/3503320",
    "sg:postcode":"67663",
    "sg:province":"Rheinland-Pfalz",
    "wof:name":"Sachverst\u00e4ndigenb\u00fcro Bormann Inh. Siegmar Winter",
    "wof:placetype":"venue"
},
  "geometry": {"coordinates":[7.7324438095,49.4348983765],"type":"Point"}
}