{
  "type": "Feature",
  "properties": {
    "iso:country":"DE",
    "sg:address":"Mergentheimer Str. 162",
    "sg:city":"W\u00fcrzburg",
    "sg:phone":"+49 931/61510",
    "sg:postcode":"97084",
    "sg:province":"Bayern",
    "wof:name":"Hotel-restaurant Post-hotel",
    "wof:placetype":"venue"
},
  "geometry": {"coordinates":[9.9416980743,49.7670326233],"type":"Point"}
}