{
  "type": "Feature",
  "properties": {
    "iso:country":"DE",
    "sg:address":"Thietmarstr. 3",
    "sg:city":"Leipzig",
    "sg:phone":"+49 341/4805184",
    "sg:postcode":"04179",
    "sg:province":"Sachsen",
    "wof:name":"K. K\u00e4ssner",
    "wof:placetype":"venue"
},
  "geometry": {"coordinates":[12.314885,51.329704],"type":"Point"}
}