{
  "type": "Feature",
  "properties": {
    "iso:country":"DE",
    "sg:address":"Dorfst\u00e4dter Str. 121f",
    "sg:city":"Falkenstein",
    "sg:phone":"+49 3745/5290",
    "sg:postcode":"08223",
    "sg:province":"Sachsen",
    "wof:name":"Falkensteiner Spedition Gmbh",
    "wof:placetype":"venue"
},
  "geometry": {"coordinates":[12.3618059158,50.4804039001],"type":"Point"}
}