{
  "type": "Feature",
  "properties": {
    "iso:country":"DE",
    "sg:address":"Enzianweg 4",
    "sg:city":"Barbing",
    "sg:phone":"+49 9401/3142",
    "sg:postcode":"93092",
    "sg:province":"Bayern",
    "wof:name":"Otto Zimmer",
    "wof:placetype":"venue"
},
  "geometry": {"coordinates":[12.1931428909,49.0041465759],"type":"Point"}
}