{
  "type": "Feature",
  "properties": {
    "iso:country":"DE",
    "sg:address":"Wendenstr. 15",
    "sg:city":"Neum\u00fcnster",
    "sg:phone":"+49 4321/77032",
    "sg:postcode":"24539",
    "sg:province":"Schleswig-Holstein",
    "wof:name":"Wilhelm Wohldorf & Sohn",
    "wof:placetype":"venue"
},
  "geometry": {"coordinates":[9.9907302856,54.059551239],"type":"Point"}
}