{
  "type": "Feature",
  "properties": {
    "iso:country":"DE",
    "sg:address":"M\u00fchlenweg 40",
    "sg:city":"Neuwied",
    "sg:phone":"+49 2631/973320",
    "sg:postcode":"56567",
    "sg:province":"Rheinland-Pfalz",
    "wof:name":"Beul - Klatt Steuerberatungsges. Mbh",
    "wof:placetype":"venue"
},
  "geometry": {"coordinates":[7.4175081253,50.4483337402],"type":"Point"}
}