{
  "type": "Feature",
  "properties": {
    "iso:country":"DE",
    "sg:address":"Schlo\u00dfbergstr. 5",
    "sg:city":"Bad Saulgau",
    "sg:phone":"+49 7581/3131",
    "sg:postcode":"88348",
    "sg:province":"Baden-W\u00fcrttemberg",
    "wof:name":"Neurocon Beteiligungs-gmbh",
    "wof:placetype":"venue"
},
  "geometry": {"coordinates":[9.509777,48.013229],"type":"Point"}
}