{
  "type": "Feature",
  "properties": {
    "iso:country":"DE",
    "sg:address":"K\u00f6nigstr. 5",
    "sg:city":"Lehrte",
    "sg:phone":"+49 5132/2423",
    "sg:postcode":"31275",
    "sg:province":"Niedersachsen",
    "wof:name":"Zerbe-kosmetik",
    "wof:placetype":"venue"
},
  "geometry": {"coordinates":[9.976363,52.371899],"type":"Point"}
}