{
  "type": "Feature",
  "properties": {
    "iso:country":"DE",
    "sg:address":"Anzengruberstr. 9",
    "sg:city":"Stockdorf",
    "sg:phone":"+49 89/8573214",
    "sg:postcode":"82131",
    "sg:province":"Bayern",
    "wof:name":"Brigitte Behrendt Steuerberater",
    "wof:placetype":"venue"
},
  "geometry": {"coordinates":[11.4070072174,48.0872154236],"type":"Point"}
}