{
  "type": "Feature",
  "properties": {
    "iso:country":"DE",
    "sg:address":"Deutschherrenstr. 146",
    "sg:city":"Bonn",
    "sg:phone":"+49 228/334430",
    "sg:postcode":"53179",
    "sg:province":"Nordrhein-Westfalen",
    "wof:name":"Grande Vermittlungsges. Mbh",
    "wof:placetype":"venue"
},
  "geometry": {"coordinates":[7.167593956,50.6677093506],"type":"Point"}
}