{
  "type": "Feature",
  "properties": {
    "iso:country":"DE",
    "sg:address":"Am Stollen 49",
    "sg:city":"Ilmenau",
    "sg:phone":"+49 3677/884681",
    "sg:postcode":"98693",
    "sg:province":"Th\u00fcringen",
    "wof:name":"Jugendherberge Ilmenau",
    "wof:placetype":"venue"
},
  "geometry": {"coordinates":[10.9276618958,50.6776313782],"type":"Point"}
}