{
  "type": "Feature",
  "properties": {
    "iso:country":"DE",
    "sg:address":"Im Z\u00f6llischen Sieke 38",
    "sg:city":"Bad Gandersheim",
    "sg:phone":"+49 5382/2279",
    "sg:postcode":"37581",
    "sg:province":"Niedersachsen",
    "wof:name":"Therese K\u00fchn Steuerberaterin",
    "wof:placetype":"venue"
},
  "geometry": {"coordinates":[10.0287857056,51.8634872437],"type":"Point"}
}