{
  "type": "Feature",
  "properties": {
    "iso:country":"DE",
    "sg:address":"Uelzener Str. 15",
    "sg:city":"Melbeck",
    "sg:phone":"+49 4134/8244",
    "sg:postcode":"21406",
    "sg:province":"Niedersachsen",
    "wof:name":"Apotheke Am Bach",
    "wof:placetype":"venue"
},
  "geometry": {"coordinates":[10.410368,53.179493],"type":"Point"}
}