{
  "type": "Feature",
  "properties": {
    "iso:country":"DE",
    "sg:address":"Stader Str. 334",
    "sg:city":"Wischhafen",
    "sg:phone":"+49 4770/224",
    "sg:postcode":"21737",
    "sg:province":"Niedersachsen",
    "wof:name":"W. Hottendorf",
    "wof:placetype":"venue"
},
  "geometry": {"coordinates":[9.3221817017,53.7979507446],"type":"Point"}
}