{
  "type": "Feature",
  "properties": {
    "iso:country":"DE",
    "sg:address":"Hauptstr. 28",
    "sg:city":"Hausach",
    "sg:phone":"+49 7831/1052",
    "sg:postcode":"77756",
    "sg:province":"Baden-W\u00fcrttemberg",
    "wof:name":"Triangel Billardcaf\u00e9",
    "wof:placetype":"venue"
},
  "geometry": {"coordinates":[8.171549,48.284275],"type":"Point"}
}