{
  "type": "Feature",
  "properties": {
    "iso:country":"DE",
    "sg:address":"Bahnhofstr. 7",
    "sg:city":"Dettingen",
    "sg:phone":"+49 7021/53304",
    "sg:postcode":"73265",
    "sg:province":"Baden-W\u00fcrttemberg",
    "wof:name":"Bernd Ofterdinger Architekt",
    "wof:placetype":"venue"
},
  "geometry": {"coordinates":[9.453995,48.616253],"type":"Point"}
}