{
  "type": "Feature",
  "properties": {
    "iso:country":"DE",
    "sg:address":"We\u00dfnitzer Weg 3",
    "sg:city":"Gro\u00dfenhain OT Zschauitz",
    "sg:phone":"+49 3522",
    "sg:postcode":"01558",
    "sg:province":"Sachsen",
    "wof:name":"Pension Susie",
    "wof:placetype":"venue"
},
  "geometry": {"coordinates":[13.543694,51.26931],"type":"Point"}
}