{
  "type": "Feature",
  "properties": {
    "iso:country":"DE",
    "sg:address":"Fr\u00fchlingstr. 6 A",
    "sg:city":"Bad Kissingen",
    "sg:postcode":"97688",
    "sg:province":"Bayern",
    "wof:name":"Parksanatorium Bad Bocklet Gmbh",
    "wof:placetype":"venue"
},
  "geometry": {"coordinates":[10.083007,50.199619],"type":"Point"}
}