{
  "type": "Feature",
  "properties": {
    "iso:country":"DE",
    "sg:address":"Flutstr. 137",
    "sg:city":"Recklinghausen",
    "sg:phone":"+49 2361/25805",
    "sg:postcode":"45659",
    "sg:province":"Nordrhein-Westfalen",
    "wof:name":"Hans-joachim M\u00fcller Holz-kaufmann",
    "wof:placetype":"venue"
},
  "geometry": {"coordinates":[7.1898570061,51.6440048218],"type":"Point"}
}