{
  "type": "Feature",
  "properties": {
    "iso:country":"DE",
    "sg:address":"Paulinstr. 123",
    "sg:city":"Trier",
    "sg:phone":"+49 651/9910990",
    "sg:postcode":"54292",
    "sg:province":"Rheinland-Pfalz",
    "wof:name":"Thomas Michael Thelen",
    "wof:placetype":"venue"
},
  "geometry": {"coordinates":[6.6528348923,49.7645759583],"type":"Point"}
}