{
  "type": "Feature",
  "properties": {
    "iso:country":"DE",
    "sg:address":"W\u00fcrzbacher Str. 20",
    "sg:city":"Blieskastel",
    "sg:phone":"+49 6803/534",
    "sg:postcode":"66440",
    "sg:province":"Saarland",
    "wof:name":"Wilhelm K\u00f6zle",
    "wof:placetype":"venue"
},
  "geometry": {"coordinates":[7.202296,49.221951],"type":"Point"}
}