{
  "type": "Feature",
  "properties": {
    "iso:country":"DE",
    "sg:address":"Blanke Str. 45",
    "sg:city":"Gronau",
    "sg:phone":"+49 5182/2302",
    "sg:postcode":"31028",
    "sg:province":"Niedersachsen",
    "wof:name":"E. Reimann",
    "wof:placetype":"venue"
},
  "geometry": {"coordinates":[9.7724046707,52.0849494934],"type":"Point"}
}