{
  "type": "Feature",
  "properties": {
    "iso:country":"DE",
    "sg:address":"Limburgstr. 14",
    "sg:city":"Bad D\u00fcrkheim",
    "sg:phone":"+49 6322/65862",
    "sg:postcode":"67098",
    "sg:province":"Rheinland-Pfalz",
    "wof:name":"Lang Gmbh",
    "wof:placetype":"venue"
},
  "geometry": {"coordinates":[8.163576,49.458637],"type":"Point"}
}