{
  "type": "Feature",
  "properties": {
    "iso:country":"DE",
    "sg:address":"Kopernikusstr. 5a",
    "sg:city":"Karlsdorf-Neuthard",
    "sg:postcode":"76689",
    "sg:province":"Baden-W\u00fcrttemberg",
    "wof:name":"Immoflexx Gmbh",
    "wof:placetype":"venue"
},
  "geometry": {"coordinates":[8.53825,49.142509],"type":"Point"}
}