{
  "type": "Feature",
  "properties": {
    "iso:country":"DE",
    "sg:address":"Haus Ungarn/ Karl- Liebknecht Stra\u00dfe 9",
    "sg:city":"Berlin",
    "sg:phone":"+49 30/2415715",
    "sg:postcode":"10178",
    "sg:province":"Berlin",
    "wof:name":"Cafe Zsolnay, Berlin",
    "wof:placetype":"venue"
},
  "geometry": {"coordinates":[13.4241552353,52.5212135315],"type":"Point"}
}