{
  "type": "Feature",
  "properties": {
    "iso:country":"DE",
    "sg:address":"Baldurstr. 52",
    "sg:city":"Dorsten",
    "sg:phone":"+49 2362/945511",
    "sg:postcode":"46284",
    "sg:province":"Nordrhein-Westfalen",
    "wof:name":"Klaus Berger",
    "wof:placetype":"venue"
},
  "geometry": {"coordinates":[6.9503598213,51.671913147],"type":"Point"}
}