{
  "type": "Feature",
  "properties": {
    "iso:country":"DE",
    "sg:address":"Malscher Str. 23",
    "sg:city":"Muggensturm",
    "sg:phone":"+49 7222/53945",
    "sg:postcode":"76461",
    "sg:province":"Baden-W\u00fcrttemberg",
    "wof:name":"Dolczik",
    "wof:placetype":"venue"
},
  "geometry": {"coordinates":[8.28504,48.868809],"type":"Point"}
}