{
  "type": "Feature",
  "properties": {
    "iso:country":"DE",
    "sg:address":"Altendeich 9",
    "sg:city":"Raa-Besenbek",
    "sg:postcode":"25335",
    "sg:province":"Schleswig-Holstein",
    "wof:name":"Nord-tools Gmbh",
    "wof:placetype":"venue"
},
  "geometry": {"coordinates":[9.610914,53.744102],"type":"Point"}
}