{
  "type": "Feature",
  "properties": {
    "iso:country":"DE",
    "sg:address":"Bahnhofstr. 18",
    "sg:city":"Schee\u00dfel",
    "sg:phone":"+49 4263/34303",
    "sg:postcode":"27383",
    "sg:province":"Niedersachsen",
    "wof:name":"W\u00fcmme-baubedarf Gmbh",
    "wof:placetype":"venue"
},
  "geometry": {"coordinates":[9.485215,53.167835],"type":"Point"}
}