{
  "type": "Feature",
  "properties": {
    "iso:country":"DE",
    "sg:address":"Dortmunder Str. 43",
    "sg:city":"M\u00fcnster",
    "sg:phone":"+49 251/662675",
    "sg:postcode":"48155",
    "sg:province":"Nordrhein-Westfalen",
    "wof:name":"Gastst\u00e4tte Dornsch\u00e4nke",
    "wof:placetype":"venue"
},
  "geometry": {"coordinates":[7.6417222023,51.9529724121],"type":"Point"}
}