{
  "type": "Feature",
  "properties": {
    "iso:country":"DE",
    "sg:address":"Zum Upland 38",
    "sg:city":"Diemelsee",
    "sg:phone":"+49 4956/3398980",
    "sg:postcode":"34519",
    "sg:province":"Hessen",
    "wof:name":"Fieseler Bauunternehmen Gmbh & Co Kg",
    "wof:placetype":"venue"
},
  "geometry": {"coordinates":[8.69557,51.328522],"type":"Point"}
}