{
  "type": "Feature",
  "properties": {
    "iso:country":"DE",
    "sg:address":"Abt-Ulrich-Str. 18",
    "sg:city":"Osterhofen",
    "sg:phone":"+49 9932/95070",
    "sg:postcode":"94486",
    "sg:province":"Bayern",
    "wof:name":"C. Und Manuela Bruckmeier",
    "wof:placetype":"venue"
},
  "geometry": {"coordinates":[13.018151,48.689415],"type":"Point"}
}