{
  "type": "Feature",
  "properties": {
    "iso:country":"DE",
    "sg:address":"Rieckestr. 26",
    "sg:city":"Stuttgart",
    "sg:phone":"+49 711/261002",
    "sg:postcode":"70190",
    "sg:province":"Baden-W\u00fcrttemberg",
    "wof:name":"Wilhelm Lang Inh. Franz Weik",
    "wof:placetype":"venue"
},
  "geometry": {"coordinates":[9.197716713,48.7897872925],"type":"Point"}
}