{
  "type": "Feature",
  "properties": {
    "iso:country":"DE",
    "sg:address":"Elisenstr. 1",
    "sg:city":"Schleiz",
    "sg:phone":"+49 3663/422838",
    "sg:postcode":"07907",
    "sg:province":"Th\u00fcringen",
    "wof:name":"E. Jauch",
    "wof:placetype":"venue"
},
  "geometry": {"coordinates":[11.811856,50.57822],"type":"Point"}
}