{
  "type": "Feature",
  "properties": {
    "iso:country":"DE",
    "sg:address":"Konrad-Adenauer-Str. 81",
    "sg:city":"Geilenkirchen",
    "sg:phone":"+49 2451/5929",
    "sg:postcode":"52511",
    "sg:province":"Nordrhein-Westfalen",
    "wof:name":"Kirchner",
    "wof:placetype":"venue"
},
  "geometry": {"coordinates":[6.1255722046,50.9629821777],"type":"Point"}
}