{
  "type": "Feature",
  "properties": {
    "iso:country":"DE",
    "sg:address":"Urbanusstr. 29",
    "sg:city":"Bochum",
    "sg:phone":"+49 234/288907",
    "sg:postcode":"44892",
    "sg:province":"Nordrhein-Westfalen",
    "wof:name":"Klaus Schr\u00f6der Heilpraktiker",
    "wof:placetype":"venue"
},
  "geometry": {"coordinates":[7.304456234,51.458770752],"type":"Point"}
}