{
  "type": "Feature",
  "properties": {
    "iso:country":"DE",
    "sg:address":"K\u00f6nig-Karl-Str. 27",
    "sg:city":"Stuttgart",
    "sg:phone":"+49 711/9546550",
    "sg:postcode":"70372",
    "sg:province":"Baden-W\u00fcrttemberg",
    "wof:name":"Vogel Und Partner Rechtsanw\u00e4lte",
    "wof:placetype":"venue"
},
  "geometry": {"coordinates":[9.2200212479,48.8058815002],"type":"Point"}
}