{
  "type": "Feature",
  "properties": {
    "iso:country":"DE",
    "sg:address":"An der Hasenkaule 13",
    "sg:city":"H\u00fcrth",
    "sg:phone":"+49 2233/974040",
    "sg:postcode":"50354",
    "sg:province":"Nordrhein-Westfalen",
    "wof:name":"Hardy Remagen Gmbh & Co. Kg",
    "wof:placetype":"venue"
},
  "geometry": {"coordinates":[6.9071397781,50.8807373047],"type":"Point"}
}