{
  "type": "Feature",
  "properties": {
    "iso:country":"DE",
    "sg:address":"Postfach",
    "sg:city":"Goslar",
    "sg:phone":"+49 5321/43550",
    "sg:postcode":"38601",
    "sg:province":"Niedersachsen",
    "wof:name":"Freibad Osterfeld",
    "wof:placetype":"venue"
},
  "geometry": {"coordinates":[10.4278297424,51.9044914246],"type":"Point"}
}