{
  "type": "Feature",
  "properties": {
    "iso:country":"DE",
    "sg:address":"Hauptstr. 42",
    "sg:city":"Weil am Rhein",
    "sg:phone":"+49 7621/71209",
    "sg:postcode":"79576",
    "sg:province":"Baden-W\u00fcrttemberg",
    "wof:name":"Eugen Keller",
    "wof:placetype":"venue"
},
  "geometry": {"coordinates":[7.637127,47.592026],"type":"Point"}
}