{
  "type": "Feature",
  "properties": {
    "iso:country":"DE",
    "sg:address":"Kirchstr. 22",
    "sg:city":"Dillingen",
    "sg:postcode":"89407",
    "sg:province":"Bayern",
    "wof:name":"Josef Knaus",
    "wof:placetype":"venue"
},
  "geometry": {"coordinates":[10.537945,48.597668],"type":"Point"}
}