{
  "type": "Feature",
  "properties": {
    "iso:country":"DE",
    "sg:address":"Marktstr. 21",
    "sg:city":"Trochtelfingen",
    "sg:phone":"+49 7124/2200",
    "sg:postcode":"72818",
    "sg:province":"Baden-W\u00fcrttemberg",
    "wof:name":"Restaurant Zum Ochsen",
    "wof:placetype":"venue"
},
  "geometry": {"coordinates":[9.2442216873,48.3077468872],"type":"Point"}
}