{
  "type": "Feature",
  "properties": {
    "iso:country":"DE",
    "sg:address":"Feldstr. 11",
    "sg:city":"Tucheim",
    "sg:phone":"+49 39346/358",
    "sg:postcode":"39307",
    "sg:province":"Sachsen-Anhalt",
    "wof:name":"Karl-heinz Steinel",
    "wof:placetype":"venue"
},
  "geometry": {"coordinates":[12.197005,52.289822],"type":"Point"}
}