{
  "type": "Feature",
  "properties": {
    "iso:country":"DE",
    "sg:address":"Raschauer Weg 24 a",
    "sg:city":"Schwarzenberg",
    "sg:phone":"+49 3774/23156",
    "sg:postcode":"08340",
    "sg:province":"Sachsen",
    "wof:name":"Wohnberatung Neuwelt Gmbh",
    "wof:placetype":"venue"
},
  "geometry": {"coordinates":[12.801808,50.537945],"type":"Point"}
}