{
  "type": "Feature",
  "properties": {
    "iso:country":"DE",
    "sg:address":"Klauberger Str. 3",
    "sg:city":"Solingen",
    "sg:phone":"+49 212/204298",
    "sg:postcode":"42651",
    "sg:province":"Nordrhein-Westfalen",
    "wof:name":"G. B\u00f6hme Kfz-verwertungsuntern.",
    "wof:placetype":"venue"
},
  "geometry": {"coordinates":[7.0897359848,51.1771087646],"type":"Point"}
}