{
  "type": "Feature",
  "properties": {
    "iso:country":"DE",
    "sg:address":"Raerener Str./Autobahn E5",
    "sg:city":"Aachen",
    "sg:phone":"+49 2408/1820",
    "sg:postcode":"52076",
    "sg:province":"Nordrhein-Westfalen",
    "wof:name":"Dresdner Bank",
    "wof:placetype":"venue"
},
  "geometry": {"coordinates":[6.180575,50.707874],"type":"Point"}
}