{
  "type": "Feature",
  "properties": {
    "iso:country":"DE",
    "sg:address":"Untere Industriestr. 1",
    "sg:city":"Netphen",
    "sg:postcode":"57250",
    "sg:province":"Nordrhein-Westfalen",
    "wof:name":"Zdh Zustelldienst Verwaltungs Gmbh",
    "wof:placetype":"venue"
},
  "geometry": {"coordinates":[8.0687704086,50.9101409912],"type":"Point"}
}