{
  "type": "Feature",
  "properties": {
    "iso:country":"DE",
    "sg:address":"Klingelstr. 20",
    "sg:city":"Salzkotten",
    "sg:phone":"+49 5258/6358",
    "sg:postcode":"33154",
    "sg:province":"Nordrhein-Westfalen",
    "wof:name":"Cafe Schulte Inh. R. S\u00f6the",
    "wof:placetype":"venue"
},
  "geometry": {"coordinates":[8.607481,51.672333],"type":"Point"}
}