{
  "type": "Feature",
  "properties": {
    "iso:country":"DE",
    "sg:address":"Siemensstr. 10",
    "sg:city":"Garbsen",
    "sg:phone":"+49 5131/6051",
    "sg:postcode":"30827",
    "sg:province":"Niedersachsen",
    "wof:name":"Kfk Grundst\u00fccksver- Waltungs-gesellschaft",
    "wof:placetype":"venue"
},
  "geometry": {"coordinates":[9.6100416183,52.4451446533],"type":"Point"}
}