{
  "type": "Feature",
  "properties": {
    "iso:country":"DE",
    "sg:address":"Spessartstr. 30",
    "sg:city":"Triefenstein",
    "sg:phone":"+49 9395/1079",
    "sg:postcode":"97855",
    "sg:province":"Bayern",
    "wof:name":"Camping-gastst\u00e4tte",
    "wof:placetype":"venue"
},
  "geometry": {"coordinates":[9.5933103561,49.8156814575],"type":"Point"}
}