{
  "type": "Feature",
  "properties": {
    "iso:country":"DE",
    "sg:address":"Am Schacht 12",
    "sg:city":"Grenzach-Wyhlen",
    "sg:phone":"+49 7624/30090",
    "sg:postcode":"79639",
    "sg:province":"Baden-W\u00fcrttemberg",
    "wof:name":"Wilhelm M\u00f6nch Bauunternehmung Gmbh & Co. Kg",
    "wof:placetype":"venue"
},
  "geometry": {"coordinates":[7.6784801483,47.5363883972],"type":"Point"}
}