{
  "type": "Feature",
  "properties": {
    "iso:country":"DE",
    "sg:address":"Lichtenklinger Str. 3",
    "sg:city":"Wald-Michelbach",
    "sg:phone":"+49 4962/071679",
    "sg:postcode":"69483",
    "sg:province":"Hessen",
    "wof:name":"Gert-roland Kohl",
    "wof:placetype":"venue"
},
  "geometry": {"coordinates":[8.807009697,49.5480918884],"type":"Point"}
}