{
  "type": "Feature",
  "properties": {
    "iso:country":"DE",
    "sg:address":"Rheinstr. 11",
    "sg:city":"Dienheim",
    "sg:phone":"+49 6133/2887",
    "sg:postcode":"55276",
    "sg:province":"Rheinland-Pfalz",
    "wof:name":"A. L. Sch\u00e4fer Weinanbau",
    "wof:placetype":"venue"
},
  "geometry": {"coordinates":[8.3496761322,49.8358573914],"type":"Point"}
}