{
  "type": "Feature",
  "properties": {
    "iso:country":"DE",
    "sg:address":"Max-Planck-Str. 1",
    "sg:city":"Kitzingen",
    "sg:phone":"+49 9321/93640",
    "sg:postcode":"97318",
    "sg:province":"Bayern",
    "wof:name":"Bono",
    "wof:placetype":"venue"
},
  "geometry": {"coordinates":[10.19444,49.730259],"type":"Point"}
}