{
  "type": "Feature",
  "properties": {
    "iso:country":"DE",
    "sg:address":"Dochturowweg 25",
    "sg:city":"Leipzig",
    "sg:phone":"+49 341/8610848",
    "sg:postcode":"04289",
    "sg:province":"Sachsen",
    "wof:name":"Dieter Berthold",
    "wof:placetype":"venue"
},
  "geometry": {"coordinates":[12.4378004074,51.2842826843],"type":"Point"}
}