{
  "type": "Feature",
  "properties": {
    "iso:country":"DE",
    "sg:address":"Altm\u00e4rker Str. 8",
    "sg:city":"H\u00f6xter",
    "sg:phone":"+49 5271/8145",
    "sg:postcode":"37671",
    "sg:province":"Nordrhein-Westfalen",
    "wof:name":"Hans Lunghard",
    "wof:placetype":"venue"
},
  "geometry": {"coordinates":[9.378198,51.77578],"type":"Point"}
}