{
  "type": "Feature",
  "properties": {
    "iso:country":"DE",
    "sg:address":"H\u00f6henstr. 11",
    "sg:city":"Laufach",
    "sg:phone":"+49 6093/8010",
    "sg:postcode":"63846",
    "sg:province":"Bayern",
    "wof:name":"Matrade Karin Zierau",
    "wof:placetype":"venue"
},
  "geometry": {"coordinates":[9.2900209427,50.0154457092],"type":"Point"}
}