{
  "type": "Feature",
  "properties": {
    "iso:country":"DE",
    "sg:address":"Fischmarkt 13",
    "sg:city":"Erfurt",
    "sg:postcode":"99084",
    "sg:province":"Th\u00fcringen",
    "wof:name":"Handwerksf\u00f6rderungsges. Th\u00fcringen Mbh",
    "wof:placetype":"venue"
},
  "geometry": {"coordinates":[11.028649,50.978165],"type":"Point"}
}