{
  "type": "Feature",
  "properties": {
    "iso:country":"DE",
    "sg:address":"Wilhelmstr. 2",
    "sg:city":"B\u00fcren",
    "sg:phone":"+49 2951/2443",
    "sg:postcode":"33142",
    "sg:province":"Nordrhein-Westfalen",
    "wof:name":"Hotel Kretzer Inh. U. Kretzer-menke E. K.",
    "wof:placetype":"venue"
},
  "geometry": {"coordinates":[8.5539197922,51.5566215515],"type":"Point"}
}