{
  "type": "Feature",
  "properties": {
    "iso:country":"DE",
    "sg:address":"Augustenhofweg 2b",
    "sg:city":"Bad Laasphe",
    "sg:phone":"+49 2754/8772",
    "sg:postcode":"57334",
    "sg:province":"Nordrhein-Westfalen",
    "wof:name":"Herbert Wunderlich Jun.",
    "wof:placetype":"venue"
},
  "geometry": {"coordinates":[8.276971817,50.9342765808],"type":"Point"}
}