{
  "type": "Feature",
  "properties": {
    "iso:country":"DE",
    "sg:address":"Meisenweg 6",
    "sg:city":"Freren",
    "sg:phone":"+49 5902/891",
    "sg:postcode":"49832",
    "sg:province":"Niedersachsen",
    "wof:name":"Bernhard Thelen Architekt",
    "wof:placetype":"venue"
},
  "geometry": {"coordinates":[7.538612,52.483494],"type":"Point"}
}