{
  "type": "Feature",
  "properties": {
    "iso:country":"DE",
    "sg:address":"Pater-Delp-Str. 12",
    "sg:city":"Obertshausen",
    "sg:phone":"+49 6104/797505",
    "sg:postcode":"63179",
    "sg:province":"Hessen",
    "wof:name":"Franz Fischer Gmbh",
    "wof:placetype":"venue"
},
  "geometry": {"coordinates":[8.8682432175,50.0744247437],"type":"Point"}
}