{
  "type": "Feature",
  "properties": {
    "iso:country":"DE",
    "sg:address":"Reichenhainer Str. 183",
    "sg:city":"Chemnitz",
    "sg:phone":"+49 371/512210",
    "sg:postcode":"09125",
    "sg:province":"Sachsen",
    "wof:name":"Alfred Seifert",
    "wof:placetype":"venue"
},
  "geometry": {"coordinates":[12.941694,50.799812],"type":"Point"}
}