{
  "type": "Feature",
  "properties": {
    "iso:country":"DE",
    "sg:address":"Trogenau 25",
    "sg:city":"Regnitzlosau",
    "sg:phone":"+49 9294/1713",
    "sg:postcode":"95194",
    "sg:province":"Bayern",
    "wof:name":"H. Und . Sommermann",
    "wof:placetype":"venue"
},
  "geometry": {"coordinates":[12.04637,50.318718],"type":"Point"}
}