{
  "type": "Feature",
  "properties": {
    "iso:country":"DE",
    "sg:address":"Aroser Allee 88",
    "sg:city":"Berlin",
    "sg:postcode":"13407",
    "sg:province":"Berlin",
    "wof:name":"Eurolimousine",
    "wof:placetype":"venue"
},
  "geometry": {"coordinates":[13.3529558182,52.5647964478],"type":"Point"}
}