{
  "type": "Feature",
  "properties": {
    "iso:country":"DE",
    "sg:address":"Am Marktplatz 4",
    "sg:city":"Twist",
    "sg:phone":"+49 5936/2394",
    "sg:postcode":"49767",
    "sg:province":"Niedersachsen",
    "wof:name":"Haus St.anna",
    "wof:placetype":"venue"
},
  "geometry": {"coordinates":[7.059731,52.635017],"type":"Point"}
}