{
  "type": "Feature",
  "properties": {
    "iso:country":"DE",
    "sg:address":"Fichtenstr. 17",
    "sg:city":"Dietramszell",
    "sg:phone":"+49 8171/28404",
    "sg:postcode":"83623",
    "sg:province":"Bayern",
    "wof:name":"Dr. Georg Unterholzner Tierarzt",
    "wof:placetype":"venue"
},
  "geometry": {"coordinates":[11.5001268387,47.8899307251],"type":"Point"}
}