{
  "type": "Feature",
  "properties": {
    "iso:country":"DE",
    "sg:address":"Kettelerstr. 4",
    "sg:city":"Viernheim",
    "sg:phone":"+49 6204/8882",
    "sg:postcode":"68519",
    "sg:province":"Hessen",
    "wof:name":"Optik Sauer Gmbh",
    "wof:placetype":"venue"
},
  "geometry": {"coordinates":[8.5773544312,49.5381584167],"type":"Point"}
}