{
  "type": "Feature",
  "properties": {
    "iso:country":"DE",
    "sg:address":"Am Kreuzweiher 23",
    "sg:city":"Hirschau",
    "sg:phone":"+49 9622/6145",
    "sg:postcode":"92242",
    "sg:province":"Bayern",
    "wof:name":"Neubauer Software Gmbh",
    "wof:placetype":"venue"
},
  "geometry": {"coordinates":[11.930144,49.538235],"type":"Point"}
}