{
  "type": "Feature",
  "properties": {
    "iso:country":"DE",
    "sg:address":"Goldbergstr. 4",
    "sg:city":"Gensingen",
    "sg:phone":"+49 6727/95999",
    "sg:postcode":"55457",
    "sg:province":"Rheinland-Pfalz",
    "wof:name":"Jutta Rumpf",
    "wof:placetype":"venue"
},
  "geometry": {"coordinates":[7.9280090332,49.8974914551],"type":"Point"}
}