{
  "type": "Feature",
  "properties": {
    "iso:country":"DE",
    "sg:address":"Untere Schwemmbach 13",
    "sg:city":"Oestrich-Winkel",
    "sg:phone":"+49 6723/3394",
    "sg:postcode":"65375",
    "sg:province":"Hessen",
    "wof:name":"Edmund Graf",
    "wof:placetype":"venue"
},
  "geometry": {"coordinates":[8.012137,49.998737],"type":"Point"}
}