{
  "type": "Feature",
  "properties": {
    "iso:country":"DE",
    "sg:address":"Granstedter Str. 16",
    "sg:city":"Selsingen",
    "sg:phone":"+49 4284/644",
    "sg:postcode":"27446",
    "sg:province":"Niedersachsen",
    "wof:name":"Johann Brandtjen",
    "wof:placetype":"venue"
},
  "geometry": {"coordinates":[9.204307,53.368816],"type":"Point"}
}