{
  "type": "Feature",
  "properties": {
    "iso:country":"DE",
    "sg:address":"Rosenstr. 112",
    "sg:city":"Filderstadt",
    "sg:phone":"+49 4971/1704076",
    "sg:postcode":"70794",
    "sg:province":"Baden-W\u00fcrttemberg",
    "wof:name":"Gerhard H\u00dclsemann Maschinen-u. Fahrzeugbau Gmbh",
    "wof:placetype":"venue"
},
  "geometry": {"coordinates":[9.204574,48.680515],"type":"Point"}
}