{
  "type": "Feature",
  "properties": {
    "iso:country":"DE",
    "sg:address":"Am Postplatz 10::",
    "sg:city":"Titisee-Neustadt",
    "sg:phone":"+49 4976/519000",
    "sg:postcode":"79822",
    "sg:province":"Baden-W\u00fcrttemberg",
    "wof:name":"Sparkasse Hochschwarzwald",
    "wof:placetype":"venue"
},
  "geometry": {"coordinates":[8.211843,47.910206],"type":"Point"}
}