{
  "type": "Feature",
  "properties": {
    "iso:country":"DE",
    "sg:address":"Postfach",
    "sg:city":"Weinsberg",
    "sg:postcode":"74189",
    "sg:province":"Baden-W\u00fcrttemberg",
    "wof:name":"Karosseriewerke Weinsberg Gmbh",
    "wof:placetype":"venue"
},
  "geometry": {"coordinates":[9.284283,49.149151],"type":"Point"}
}