{
  "type": "Feature",
  "properties": {
    "iso:country":"DE",
    "sg:address":"Auf der Heckenbrede 8",
    "sg:city":"Erwitte",
    "sg:phone":"+49 2945/2260",
    "sg:postcode":"59597",
    "sg:province":"Nordrhein-Westfalen",
    "wof:name":"F. M\u00e4hler",
    "wof:placetype":"venue"
},
  "geometry": {"coordinates":[8.243159,51.61277],"type":"Point"}
}