{
  "type": "Feature",
  "properties": {
    "iso:country":"DE",
    "sg:address":"Schl\u00fcskamp 14",
    "sg:city":"Bad Bramstedt",
    "sg:phone":"+49 4192/1420",
    "sg:postcode":"24576",
    "sg:province":"Schleswig-Holstein",
    "wof:name":"Matthias Hamann & Co. Gmbh",
    "wof:placetype":"venue"
},
  "geometry": {"coordinates":[9.8854513168,53.919708252],"type":"Point"}
}