{
  "type": "Feature",
  "properties": {
    "iso:country":"DE",
    "sg:address":"Eichborndamm 146",
    "sg:city":"Berlin",
    "sg:phone":"+49 30/4144069",
    "sg:postcode":"13403",
    "sg:province":"Berlin",
    "wof:name":"Christel R\u00fcckert",
    "wof:placetype":"venue"
},
  "geometry": {"coordinates":[13.3192281723,52.5817451477],"type":"Point"}
}