{
  "type": "Feature",
  "properties": {
    "iso:country":"DE",
    "sg:address":"Aprikosenweg 21",
    "sg:city":"Halle",
    "sg:phone":"+49 345/5603007",
    "sg:postcode":"06112",
    "sg:province":"Sachsen-Anhalt",
    "wof:name":"Ulrich Karl Bohrungen Gmbh",
    "wof:placetype":"venue"
},
  "geometry": {"coordinates":[12.0072031021,51.4599075317],"type":"Point"}
}