{
  "type": "Feature",
  "properties": {
    "iso:country":"DE",
    "sg:address":"Marktstr. 2",
    "sg:city":"Eschweiler",
    "sg:phone":"+49 2403/4910",
    "sg:postcode":"52249",
    "sg:province":"Nordrhein-Westfalen",
    "wof:name":"Moden Koslowski Gmbh",
    "wof:placetype":"venue"
},
  "geometry": {"coordinates":[6.2689208984,50.8191642761],"type":"Point"}
}