{
  "type": "Feature",
  "properties": {
    "iso:country":"DE",
    "sg:address":"Beim Schlump 16",
    "sg:city":"Hamburg",
    "sg:phone":"+49 40/4501720",
    "sg:postcode":"20144",
    "sg:province":"Hamburg",
    "wof:name":"Dening Hair Company Gmbh",
    "wof:placetype":"venue"
},
  "geometry": {"coordinates":[9.9764795303,53.5708465576],"type":"Point"}
}