{
  "type": "Feature",
  "properties": {
    "iso:country":"DE",
    "sg:address":"Obere Vorstadtstr. 12",
    "sg:city":"Leutkirch",
    "sg:phone":"+49 7561/914387",
    "sg:postcode":"88299",
    "sg:province":"Baden-W\u00fcrttemberg",
    "wof:name":"Gerlinde Maier",
    "wof:placetype":"venue"
},
  "geometry": {"coordinates":[10.0252819061,47.8240280151],"type":"Point"}
}