{
  "type": "Feature",
  "properties": {
    "iso:country":"DE",
    "sg:address":"Schwarze-B\u00e4ren-Str. 8",
    "sg:city":"Regensburg",
    "sg:phone":"+49 941/55264",
    "sg:postcode":"93047",
    "sg:province":"Bayern",
    "wof:name":"City Konditorei",
    "wof:placetype":"venue"
},
  "geometry": {"coordinates":[12.0991592407,49.0176811218],"type":"Point"}
}