{
  "type": "Feature",
  "properties": {
    "iso:country":"DE",
    "sg:address":"Poststr. 52",
    "sg:city":"Albstadt",
    "sg:phone":"+49 7431/590085",
    "sg:postcode":"72458",
    "sg:province":"Baden-W\u00fcrttemberg",
    "wof:name":"Neumann Und Walter Rechtsanw\u00e4lte",
    "wof:placetype":"venue"
},
  "geometry": {"coordinates":[9.0242061615,48.2109947205],"type":"Point"}
}