{
  "type": "Feature",
  "properties": {
    "iso:country":"DE",
    "sg:address":"Carl-Miele-Str. 29",
    "sg:city":"G\u00fctersloh",
    "sg:phone":"+49 5241/890",
    "sg:postcode":"33332",
    "sg:province":"Nordrhein-Westfalen",
    "wof:name":"Geschwister Miele Beteiligungs- Gmbh",
    "wof:placetype":"venue"
},
  "geometry": {"coordinates":[8.3938760757,51.9121131897],"type":"Point"}
}