{
  "type": "Feature",
  "properties": {
    "iso:country":"DE",
    "sg:address":"Hauptstr. 9",
    "sg:city":"Denkendorf",
    "sg:phone":"+49 8466/312",
    "sg:postcode":"85095",
    "sg:province":"Bayern",
    "wof:name":"Cafe Jura",
    "wof:placetype":"venue"
},
  "geometry": {"coordinates":[11.459169,48.928837],"type":"Point"}
}