{
  "type": "Feature",
  "properties": {
    "iso:country":"DE",
    "sg:address":"Franz-Schubert-Str. 24",
    "sg:city":"Reutlingen",
    "sg:phone":"+49 7121/45244",
    "sg:postcode":"72766",
    "sg:province":"Baden-W\u00fcrttemberg",
    "wof:name":"C. Und H. Rapp Immobilienmakler",
    "wof:placetype":"venue"
},
  "geometry": {"coordinates":[9.2217082977,48.5001754761],"type":"Point"}
}