{
  "type": "Feature",
  "properties": {
    "iso:country":"DE",
    "sg:address":"Hermeskeiler Str. 37",
    "sg:city":"Trier",
    "sg:phone":"+49 651/958180",
    "sg:postcode":"54292",
    "sg:province":"Rheinland-Pfalz",
    "wof:name":"Werner Becker Steuerberater",
    "wof:placetype":"venue"
},
  "geometry": {"coordinates":[6.708591938,49.7887535095],"type":"Point"}
}