{
  "type": "Feature",
  "properties": {
    "iso:country":"DE",
    "sg:address":"Bilholtstr. 8",
    "sg:city":"Olfen",
    "sg:phone":"+49 2595/208",
    "sg:postcode":"59399",
    "sg:province":"Nordrhein-Westfalen",
    "wof:name":"Stadt-apotheke",
    "wof:placetype":"venue"
},
  "geometry": {"coordinates":[7.378771,51.708969],"type":"Point"}
}