{
  "type": "Feature",
  "properties": {
    "iso:country":"DE",
    "sg:address":"Wirthstr. 2",
    "sg:city":"Bayreuth",
    "sg:phone":"+49 921/12770",
    "sg:postcode":"95445",
    "sg:province":"Bayern",
    "wof:name":"Wolfgang Zeisel Ingenieur",
    "wof:placetype":"venue"
},
  "geometry": {"coordinates":[11.5690860748,49.9491233826],"type":"Point"}
}