{
  "type": "Feature",
  "properties": {
    "iso:country":"DE",
    "sg:address":"Norbertstr. 11",
    "sg:city":"M\u00fcnster",
    "sg:phone":"+49 251/527488",
    "sg:postcode":"48151",
    "sg:province":"Nordrhein-Westfalen",
    "wof:name":"Br\u00fcggemann Und Partner Software Berater",
    "wof:placetype":"venue"
},
  "geometry": {"coordinates":[7.6211271286,51.9538574219],"type":"Point"}
}