{
  "type": "Feature",
  "properties": {
    "iso:country":"DE",
    "sg:address":"Berliner Str. 15",
    "sg:city":"Ruhland",
    "sg:phone":"+49 35752/2367",
    "sg:postcode":"01945",
    "sg:province":"Brandenburg",
    "wof:name":"Paul Pohling",
    "wof:placetype":"venue"
},
  "geometry": {"coordinates":[13.8668804169,51.4595146179],"type":"Point"}
}