{
  "type": "Feature",
  "properties": {
    "iso:country":"DE",
    "sg:address":"Ginsterweg 60",
    "sg:city":"Bremerhaven",
    "sg:phone":"+49 471/60414",
    "sg:postcode":"27578",
    "sg:province":"Bremen",
    "wof:name":"Mabeg M\u00fcll-u. Schuttabfuhr-untern.",
    "wof:placetype":"venue"
},
  "geometry": {"coordinates":[8.633793,53.598442],"type":"Point"}
}