{
  "type": "Feature",
  "properties": {
    "iso:country":"DE",
    "sg:address":"Am Nymphenbad 9",
    "sg:city":"M\u00fcnchen",
    "sg:phone":"+49 89/8888450",
    "sg:postcode":"81245",
    "sg:province":"Bayern",
    "wof:name":"A. Hubert",
    "wof:placetype":"venue"
},
  "geometry": {"coordinates":[11.4793891907,48.1569061279],"type":"Point"}
}