{
  "type": "Feature",
  "properties": {
    "iso:country":"DE",
    "sg:address":"Kottenbrede 21",
    "sg:city":"Bad Salzuflen",
    "sg:phone":"+49 5222/7416",
    "sg:postcode":"32107",
    "sg:province":"Nordrhein-Westfalen",
    "wof:name":"Wilhelm Bentrup Verwaltungsgesellschaft Mbh",
    "wof:placetype":"venue"
},
  "geometry": {"coordinates":[8.6699342728,52.073009491],"type":"Point"}
}