{
  "type": "Feature",
  "properties": {
    "iso:country":"DE",
    "sg:address":"Ludwig-Erhard-Str. 3",
    "sg:city":"Pattensen",
    "sg:phone":"+49 5101/916435",
    "sg:postcode":"30982",
    "sg:province":"Niedersachsen",
    "wof:name":"H. Schottmann",
    "wof:placetype":"venue"
},
  "geometry": {"coordinates":[9.777212,52.268387],"type":"Point"}
}