{
  "type": "Feature",
  "properties": {
    "iso:country":"DE",
    "sg:address":"H\u00fctte 4-6",
    "sg:city":"Altena",
    "sg:phone":"+49 2352/97910",
    "sg:postcode":"58762",
    "sg:province":"Nordrhein-Westfalen",
    "wof:name":"W. Ossenberg & Cie. Verwaltungs Gmbh",
    "wof:placetype":"venue"
},
  "geometry": {"coordinates":[7.7234368324,51.2989196777],"type":"Point"}
}