{
  "type": "Feature",
  "properties": {
    "iso:country":"DE",
    "sg:address":"Freyunger Str. 2",
    "sg:city":"Grafenau",
    "sg:phone":"+49 8552/96000",
    "sg:postcode":"94481",
    "sg:province":"Bayern",
    "wof:name":"Nationalparkverwaltung Bayerischer Wald",
    "wof:placetype":"venue"
},
  "geometry": {"coordinates":[13.3974304199,48.8561248779],"type":"Point"}
}