{
  "type": "Feature",
  "properties": {
    "iso:country":"DE",
    "sg:address":"Amselweg 10",
    "sg:city":"Ebersbach",
    "sg:phone":"+49 7163/3697",
    "sg:postcode":"73061",
    "sg:province":"Baden-W\u00fcrttemberg",
    "wof:name":"Frank Industrie- Ausr\u00fcstungen Gmbh",
    "wof:placetype":"venue"
},
  "geometry": {"coordinates":[9.507242,48.695393],"type":"Point"}
}