{
  "type": "Feature",
  "properties": {
    "iso:country":"DE",
    "sg:address":"Kaiserstr. 28",
    "sg:city":"Lohnsfeld",
    "sg:phone":"+49 4963/023246",
    "sg:postcode":"67727",
    "sg:province":"Rheinland-Pfalz",
    "wof:name":"Kreissparkasse Rockenhausen",
    "wof:placetype":"venue"
},
  "geometry": {"coordinates":[7.853476,49.551064],"type":"Point"}
}