{
  "type": "Feature",
  "properties": {
    "iso:country":"DE",
    "sg:address":"Rudolf-Diesel-Ring 12",
    "sg:city":"Sauerlach",
    "sg:phone":"+49 8104/1011",
    "sg:postcode":"82054",
    "sg:province":"Bayern",
    "wof:name":"Dekora-malereibetrieb Und Bautendienst Gmbh",
    "wof:placetype":"venue"
},
  "geometry": {"coordinates":[11.660915,47.970032],"type":"Point"}
}