{
  "type": "Feature",
  "properties": {
    "iso:country":"DE",
    "sg:address":"Nordwalder Str. 160",
    "sg:city":"Greven",
    "sg:phone":"+49 2571/9270",
    "sg:postcode":"48268",
    "sg:province":"Nordrhein-Westfalen",
    "wof:name":"Hotel Wermelt",
    "wof:placetype":"venue"
},
  "geometry": {"coordinates":[7.5597829819,52.0955352783],"type":"Point"}
}