{
  "type": "Feature",
  "properties": {
    "iso:country":"DE",
    "sg:address":"Lorenzweg 24",
    "sg:city":"Magdeburg",
    "sg:postcode":"39106",
    "sg:province":"Sachsen-Anhalt",
    "wof:name":"Inkoba Commerz Gmbh",
    "wof:placetype":"venue"
},
  "geometry": {"coordinates":[11.635518074,52.1428565979],"type":"Point"}
}