{
  "type": "Feature",
  "properties": {
    "iso:country":"DE",
    "sg:address":"Wasserstr. 11",
    "sg:city":"Steinfurt",
    "sg:phone":"+49 2551/837070",
    "sg:postcode":"48565",
    "sg:province":"Nordrhein-Westfalen",
    "wof:name":"Daldrop Gro\u00dfe-siestrup U. Pott Rechtsanw\u00e4lte",
    "wof:placetype":"venue"
},
  "geometry": {"coordinates":[7.3395137787,52.1485519409],"type":"Point"}
}