{
  "type": "Feature",
  "properties": {
    "iso:country":"DE",
    "sg:address":"Im Grund 3",
    "sg:city":"Eckernf\u00f6rde",
    "sg:phone":"+49 4351/81806",
    "sg:postcode":"24340",
    "sg:province":"Schleswig-Holstein",
    "wof:name":"Wilhelm Simanski Architekt",
    "wof:placetype":"venue"
},
  "geometry": {"coordinates":[9.838106,54.479507],"type":"Point"}
}