{
  "type": "Feature",
  "properties": {
    "iso:country":"DE",
    "sg:address":"M\u00fcnsterstr. 90",
    "sg:city":"Ahlen",
    "sg:phone":"+49 2528/1858",
    "sg:postcode":"59227",
    "sg:province":"Nordrhein-Westfalen",
    "wof:name":"Trottenberg Industrie- Und",
    "wof:placetype":"venue"
},
  "geometry": {"coordinates":[7.9088659286,51.8211936951],"type":"Point"}
}