{
  "type": "Feature",
  "properties": {
    "iso:country":"DE",
    "sg:address":"Hehn 291",
    "sg:city":"M\u00f6nchengladbach",
    "sg:postcode":"41069",
    "sg:province":"Nordrhein-Westfalen",
    "wof:name":"Ernst Westermann",
    "wof:placetype":"venue"
},
  "geometry": {"coordinates":[6.3691601753,51.1848297119],"type":"Point"}
}