{
  "type": "Feature",
  "properties": {
    "iso:country":"DE",
    "sg:address":"Friedrich-List-Str 5",
    "sg:city":"Ki\u00dflegg",
    "sg:phone":"+49 7563/91000",
    "sg:postcode":"88353",
    "sg:province":"Baden-W\u00fcrttemberg",
    "wof:name":"Kerler Gmbh",
    "wof:placetype":"venue"
},
  "geometry": {"coordinates":[9.89197,47.769745],"type":"Point"}
}