{
  "type": "Feature",
  "properties": {
    "iso:country":"DE",
    "sg:address":"Uzstr. 37",
    "sg:city":"Ansbach",
    "sg:phone":"+49 981/15041",
    "sg:postcode":"91522",
    "sg:province":"Bayern",
    "wof:name":"Abr Amtliches Bayerisches Reiseb\u00fcro Gmbh",
    "wof:placetype":"venue"
},
  "geometry": {"coordinates":[10.5716199875,49.3013534546],"type":"Point"}
}