{
  "type": "Feature",
  "properties": {
    "iso:country":"DE",
    "sg:address":"Im Tiefen See 56",
    "sg:city":"Darmstadt",
    "sg:phone":"+49 6151/893720",
    "sg:postcode":"64293",
    "sg:province":"Hessen",
    "wof:name":"Displaytechnik Darmstadt Gmbh",
    "wof:placetype":"venue"
},
  "geometry": {"coordinates":[8.641355,49.88591],"type":"Point"}
}