{
  "type": "Feature",
  "properties": {
    "iso:country":"DE",
    "sg:address":"Kavarinerstr. 33",
    "sg:city":"Kleve",
    "sg:phone":"+49 2821/84302",
    "sg:postcode":"47533",
    "sg:province":"Nordrhein-Westfalen",
    "wof:name":"St\u00e4dt. Museum Haus Koekkoek",
    "wof:placetype":"venue"
},
  "geometry": {"coordinates":[6.137936,51.78997],"type":"Point"}
}