{
  "type": "Feature",
  "properties": {
    "iso:country":"DE",
    "sg:address":"Schulstr. 37",
    "sg:city":"Bretleben",
    "sg:phone":"+49 34673/97065",
    "sg:postcode":"06556",
    "sg:province":"Th\u00fcringen",
    "wof:name":"Heinz Sattler",
    "wof:placetype":"venue"
},
  "geometry": {"coordinates":[11.228942,51.334278],"type":"Point"}
}