{
  "type": "Feature",
  "properties": {
    "iso:country":"DE",
    "sg:address":"Liebigstr. 56",
    "sg:city":"Gie\u00dfen",
    "sg:phone":"+49 641/73589",
    "sg:postcode":"35392",
    "sg:province":"Hessen",
    "wof:name":"Ev. Pfarramt Lukasgemeinde S\u00fcd 1",
    "wof:placetype":"venue"
},
  "geometry": {"coordinates":[8.6724739075,50.5778465271],"type":"Point"}
}