{
  "type": "Feature",
  "properties": {
    "iso:country":"DE",
    "sg:address":"Hellkamp 1",
    "sg:city":"Rheda-Wiedenbr\u00fcck",
    "sg:phone":"+49 5242/577760",
    "sg:postcode":"33378",
    "sg:province":"Nordrhein-Westfalen",
    "wof:name":"Peter Mischke Finanzberater",
    "wof:placetype":"venue"
},
  "geometry": {"coordinates":[8.3163070679,51.8167648315],"type":"Point"}
}