{
  "type": "Feature",
  "properties": {
    "iso:country":"DE",
    "sg:address":"Lilienweg 2a",
    "sg:city":"Br\u00fchl",
    "sg:phone":"+49 6202/702636",
    "sg:postcode":"68782",
    "sg:province":"Baden-W\u00fcrttemberg",
    "wof:name":"W. Schneider",
    "wof:placetype":"venue"
},
  "geometry": {"coordinates":[8.5394001007,49.3976745605],"type":"Point"}
}