{
  "type": "Feature",
  "properties": {
    "iso:country":"DE",
    "sg:address":"Rebenring 11",
    "sg:city":"Braunschweig",
    "sg:phone":"+49 531/345468",
    "sg:postcode":"38106",
    "sg:province":"Niedersachsen",
    "wof:name":"Andreas Brunn",
    "wof:placetype":"venue"
},
  "geometry": {"coordinates":[10.524636,52.275482],"type":"Point"}
}