{
  "type": "Feature",
  "properties": {
    "iso:country":"DE",
    "sg:address":"Kirchgasse 230",
    "sg:city":"Landshut",
    "sg:phone":"+49 871/26491",
    "sg:postcode":"84028",
    "sg:province":"Bayern",
    "wof:name":"Lig L\u00fcftungstechnische Ingenieur- Gmbh",
    "wof:placetype":"venue"
},
  "geometry": {"coordinates":[12.152821,48.534351],"type":"Point"}
}