{
  "type": "Feature",
  "properties": {
    "iso:country":"DE",
    "sg:address":"Frieslandstr. 14",
    "sg:city":"Friedeburg",
    "sg:phone":"+49 4468/237",
    "sg:postcode":"26446",
    "sg:province":"Niedersachsen",
    "wof:name":"Richard Arends",
    "wof:placetype":"venue"
},
  "geometry": {"coordinates":[7.870945,53.492447],"type":"Point"}
}