{
  "type": "Feature",
  "properties": {
    "iso:country":"DE",
    "sg:address":"Bergstr. 128",
    "sg:city":"Marl",
    "sg:phone":"+49 2365/37660",
    "sg:postcode":"45770",
    "sg:province":"Nordrhein-Westfalen",
    "wof:name":"Elli Magnusson Immobilienmaklerin",
    "wof:placetype":"venue"
},
  "geometry": {"coordinates":[7.1156392097,51.6619682312],"type":"Point"}
}