{
  "type": "Feature",
  "properties": {
    "iso:country":"DE",
    "sg:address":"Oststr. 3",
    "sg:city":"Friedewald",
    "sg:phone":"+49 6629/567",
    "sg:postcode":"36289",
    "sg:province":"Hessen",
    "wof:name":"Heinrich Scheer",
    "wof:placetype":"venue"
},
  "geometry": {"coordinates":[9.859719,50.850315],"type":"Point"}
}