{
  "type": "Feature",
  "properties": {
    "iso:country":"DE",
    "sg:address":"Drechslerstr. 13a",
    "sg:city":"Herford",
    "sg:phone":"+49 5221/57010",
    "sg:postcode":"32051",
    "sg:province":"Nordrhein-Westfalen",
    "wof:name":"Theo Lenz",
    "wof:placetype":"venue"
},
  "geometry": {"coordinates":[8.650929,52.111782],"type":"Point"}
}