{
  "type": "Feature",
  "properties": {
    "iso:country":"DE",
    "sg:address":"Von-M\u00fcller-Str. 5",
    "sg:city":"Furth im Wald",
    "sg:phone":"+49 9973/84440",
    "sg:postcode":"93437",
    "sg:province":"Bayern",
    "wof:name":"Klaus Bauer",
    "wof:placetype":"venue"
},
  "geometry": {"coordinates":[12.841883,49.30772],"type":"Point"}
}