{
  "type": "Feature",
  "properties": {
    "iso:country":"DE",
    "sg:address":"Stottoff 22",
    "sg:city":"L\u00fcbbenau",
    "sg:phone":"+49 3542/46085",
    "sg:postcode":"03222",
    "sg:province":"Brandenburg",
    "wof:name":"Spree Apotheke Inh. Sylke Zabel",
    "wof:placetype":"venue"
},
  "geometry": {"coordinates":[13.956886,51.866055],"type":"Point"}
}