{
  "type": "Feature",
  "properties": {
    "iso:country":"DE",
    "sg:address":"Lutherstr. 10",
    "sg:city":"Rosche",
    "sg:phone":"+49 5803/291",
    "sg:postcode":"29571",
    "sg:province":"Niedersachsen",
    "wof:name":"Dipl.-ing. Heikoschulz Roscher Hausbau Gmbh",
    "wof:placetype":"venue"
},
  "geometry": {"coordinates":[10.7491941452,52.9847297668],"type":"Point"}
}