{
  "type": "Feature",
  "properties": {
    "iso:country":"DE",
    "sg:address":"Welzheimer Str. 31",
    "sg:city":"Rudersberg",
    "sg:phone":"+49 7183/930102",
    "sg:postcode":"73635",
    "sg:province":"Baden-W\u00fcrttemberg",
    "wof:name":"Restaurant Kytaro",
    "wof:placetype":"venue"
},
  "geometry": {"coordinates":[9.5322179794,48.8869361877],"type":"Point"}
}