{
  "type": "Feature",
  "properties": {
    "iso:country":"DE",
    "sg:address":"Ewaldstr. 35",
    "sg:city":"Berlin",
    "sg:phone":"+49 30/6729400",
    "sg:postcode":"12524",
    "sg:province":"Berlin",
    "wof:name":"Siegfried Pawlowski Bauausf\u00fchrungen Gmbh",
    "wof:placetype":"venue"
},
  "geometry": {"coordinates":[13.558444,52.407913],"type":"Point"}
}