{
  "type": "Feature",
  "properties": {
    "iso:country":"DE",
    "sg:address":"Schuckertstr. 33-35",
    "sg:city":"Gescher",
    "sg:phone":"+49 4925/422741",
    "sg:postcode":"48712",
    "sg:province":"Nordrhein-Westfalen",
    "wof:name":"P-h-w Gmbh",
    "wof:placetype":"venue"
},
  "geometry": {"coordinates":[7.031975,51.941559],"type":"Point"}
}