{
  "type": "Feature",
  "properties": {
    "iso:country":"DE",
    "sg:address":"Burgstr. 19",
    "sg:city":"Rodewisch",
    "sg:phone":"+49 3744/48274",
    "sg:postcode":"08228",
    "sg:province":"Sachsen",
    "wof:name":"Joachim Sch\u00e4dlich",
    "wof:placetype":"venue"
},
  "geometry": {"coordinates":[12.411655,50.534233],"type":"Point"}
}