{
  "type": "Feature",
  "properties": {
    "iso:country":"DE",
    "sg:address":"Fasanenallee 80",
    "sg:city":"Bergfelde",
    "sg:phone":"+49 3303/3075",
    "sg:postcode":"16562",
    "sg:province":"Brandenburg",
    "wof:name":"H. M\u00fcller",
    "wof:placetype":"venue"
},
  "geometry": {"coordinates":[13.3246641159,52.6696815491],"type":"Point"}
}