{
  "type": "Feature",
  "properties": {
    "iso:country":"DE",
    "sg:address":"Rainbachstr. 28",
    "sg:city":"Haag",
    "sg:phone":"+49 8072/1061",
    "sg:postcode":"83527",
    "sg:province":"Bayern",
    "wof:name":"Edeka Sb-warenhaus- Gesellschaft S\u00fcdbayern Mbh",
    "wof:placetype":"venue"
},
  "geometry": {"coordinates":[12.1767597198,48.1649475098],"type":"Point"}
}