{
  "type": "Feature",
  "properties": {
    "iso:country":"DE",
    "sg:address":"Neue Str. 76",
    "sg:city":"Salzgitter",
    "sg:postcode":"38259",
    "sg:province":"Niedersachsen",
    "wof:name":"Sim-industrietechnik Gmbh",
    "wof:placetype":"venue"
},
  "geometry": {"coordinates":[10.4477920532,52.0787963867],"type":"Point"}
}