{
  "type": "Feature",
  "properties": {
    "iso:country":"DE",
    "sg:address":"Nr. 50",
    "sg:city":"Grie\u00dfen",
    "sg:postcode":"03172",
    "sg:province":"Brandenburg",
    "wof:name":"Kinderheim Grie\u00dfen",
    "wof:placetype":"venue"
},
  "geometry": {"coordinates":[14.6419296265,51.9538383484],"type":"Point"}
}