{
  "type": "Feature",
  "properties": {
    "iso:country":"DE",
    "sg:address":"Goethestr. 25",
    "sg:city":"Weinb\u00f6hla",
    "sg:phone":"+49 35243/36257",
    "sg:postcode":"01689",
    "sg:province":"Sachsen",
    "wof:name":"Wilhelm Krause Ingenieur",
    "wof:placetype":"venue"
},
  "geometry": {"coordinates":[13.5719690323,51.16822052],"type":"Point"}
}