{
  "type": "Feature",
  "properties": {
    "iso:country":"DE",
    "sg:address":"Kirchplatz 3",
    "sg:city":"Stra\u00dfkirchen",
    "sg:phone":"+49 9424/8698",
    "sg:postcode":"94342",
    "sg:province":"Bayern",
    "wof:name":"Pizzeria Mimos",
    "wof:placetype":"venue"
},
  "geometry": {"coordinates":[12.7235298157,48.8302230835],"type":"Point"}
}