{
  "type": "Feature",
  "properties": {
    "iso:country":"DE",
    "sg:address":"Hauptstr. 17",
    "sg:city":"Gondorf",
    "sg:phone":"+49 6565/2855",
    "sg:postcode":"54647",
    "sg:province":"Rheinland-Pfalz",
    "wof:name":"Nikolaus Busch",
    "wof:placetype":"venue"
},
  "geometry": {"coordinates":[6.61677,49.969913],"type":"Point"}
}