{
  "type": "Feature",
  "properties": {
    "iso:country":"DE",
    "sg:address":"Hauptstr. 11",
    "sg:city":"Wilnsdorf",
    "sg:phone":"+49 2739/1804",
    "sg:postcode":"57234",
    "sg:province":"Nordrhein-Westfalen",
    "wof:name":"E. Und J. Thomas",
    "wof:placetype":"venue"
},
  "geometry": {"coordinates":[8.1422328949,50.8146820068],"type":"Point"}
}