{
  "type": "Feature",
  "properties": {
    "iso:country":"DE",
    "sg:address":"Forststr. 1",
    "sg:city":"Obertshausen",
    "sg:phone":"+49 6104/71776",
    "sg:postcode":"63179",
    "sg:province":"Hessen",
    "wof:name":"Otto Sonnabend",
    "wof:placetype":"venue"
},
  "geometry": {"coordinates":[8.8593921661,50.0787277222],"type":"Point"}
}