{
  "type": "Feature",
  "properties": {
    "iso:country":"DE",
    "sg:address":"Wilhelmstr. 21",
    "sg:city":"Crailsheim",
    "sg:phone":"+49 7951/94020",
    "sg:postcode":"74564",
    "sg:province":"Baden-W\u00fcrttemberg",
    "wof:name":"Photo-kino-schlosser Gmbh",
    "wof:placetype":"venue"
},
  "geometry": {"coordinates":[10.0702295303,49.138420105],"type":"Point"}
}