{
  "type": "Feature",
  "properties": {
    "iso:country":"DE",
    "sg:address":"T\u00f6pferstr. 17",
    "sg:city":"Bautzen",
    "sg:phone":"+49 3591/44394",
    "sg:postcode":"02625",
    "sg:province":"Sachsen",
    "wof:name":"Dr. Med. Eva Bulang \u00c4rztin F\u00fcr Innere Medizin",
    "wof:placetype":"venue"
},
  "geometry": {"coordinates":[14.4294548035,51.1824645996],"type":"Point"}
}