{
  "type": "Feature",
  "properties": {
    "iso:country":"DE",
    "sg:address":"Ludwigstr. 27a",
    "sg:city":"Paderborn",
    "sg:phone":"+49 5251/24761",
    "sg:postcode":"33098",
    "sg:province":"Nordrhein-Westfalen",
    "wof:name":"Thomas Auinger Postspiele",
    "wof:placetype":"venue"
},
  "geometry": {"coordinates":[8.7485055923,51.7126655579],"type":"Point"}
}