{
  "type": "Feature",
  "properties": {
    "iso:country":"DE",
    "sg:address":"Auf dem Molzberg 4",
    "sg:city":"Kirchen",
    "sg:phone":"+49 2741/62077",
    "sg:postcode":"57548",
    "sg:province":"Rheinland-Pfalz",
    "wof:name":"Monte Mare Freizeitbad Gmbh",
    "wof:placetype":"venue"
},
  "geometry": {"coordinates":[7.8722548485,50.8007164001],"type":"Point"}
}