{
  "type": "Feature",
  "properties": {
    "iso:country":"DE",
    "sg:address":"S\u00f6bendieken 5",
    "sg:city":"Hamburg",
    "sg:phone":"+49 40/823557",
    "sg:postcode":"22609",
    "sg:province":"Hamburg",
    "wof:name":"H. E. Kurt Dancker Kg",
    "wof:placetype":"venue"
},
  "geometry": {"coordinates":[9.847571,53.555977],"type":"Point"}
}