{
  "type": "Feature",
  "properties": {
    "iso:country":"DE",
    "sg:address":"Grabenstr. 5",
    "sg:city":"Wiesbaden",
    "sg:phone":"+49 611/303553",
    "sg:postcode":"65183",
    "sg:province":"Hessen",
    "wof:name":"Claus Demke Rechtsanwalt",
    "wof:placetype":"venue"
},
  "geometry": {"coordinates":[8.2406616211,50.0829925537],"type":"Point"}
}