{
  "type": "Feature",
  "properties": {
    "iso:country":"DE",
    "sg:address":"Veldensteiner Str. 8-10",
    "sg:city":"Pegnitz",
    "sg:phone":"+49 9241/6162",
    "sg:postcode":"91257",
    "sg:province":"Bayern",
    "wof:name":"Gerhard Bauer",
    "wof:placetype":"venue"
},
  "geometry": {"coordinates":[11.5293207169,49.7364196777],"type":"Point"}
}