{
  "type": "Feature",
  "properties": {
    "iso:country":"DE",
    "sg:address":"Niederurseler Landstr. 18",
    "sg:city":"Frankfurt",
    "sg:phone":"+49 69/94592068",
    "sg:postcode":"60439",
    "sg:province":"Hessen",
    "wof:name":"Friedrich Houzer Rechtsanwalt",
    "wof:placetype":"venue"
},
  "geometry": {"coordinates":[8.6331663132,50.16431427],"type":"Point"}
}