{
  "type": "Feature",
  "properties": {
    "iso:country":"DE",
    "sg:address":"Am Bahnhof 7",
    "sg:city":"Rosendahl",
    "sg:phone":"+49 2545/93020",
    "sg:postcode":"48720",
    "sg:province":"Nordrhein-Westfalen",
    "wof:name":"P\u00f6ssiger Gmbh Textilrohstoffe",
    "wof:placetype":"venue"
},
  "geometry": {"coordinates":[7.2773637772,52.0246925354],"type":"Point"}
}