{
  "type": "Feature",
  "properties": {
    "iso:country":"DE",
    "sg:address":"Sch\u00f6nwerthstr. 1-3",
    "sg:city":"Weiden",
    "sg:postcode":"92637",
    "sg:province":"Bayern",
    "wof:name":"Ipera M\u00f6bel Gmbh",
    "wof:placetype":"venue"
},
  "geometry": {"coordinates":[12.1557006836,49.6697006226],"type":"Point"}
}