{
  "type": "Feature",
  "properties": {
    "iso:country":"DE",
    "sg:address":"Bei der Alten Ziegelei 14",
    "sg:city":"Gundelfingen",
    "sg:postcode":"89423",
    "sg:province":"Bayern",
    "wof:name":"Csu Ortsverband Gundelfingen",
    "wof:placetype":"venue"
},
  "geometry": {"coordinates":[10.3715696335,48.558139801],"type":"Point"}
}