{
  "type": "Feature",
  "properties": {
    "iso:country":"DE",
    "sg:address":"Mariannenstr. 14",
    "sg:city":"Dessau",
    "sg:phone":"+49 340/215210",
    "sg:postcode":"06844",
    "sg:province":"Sachsen-Anhalt",
    "wof:name":"Ingenieurgesellschaft Dr. Eugen Macke Mbh",
    "wof:placetype":"venue"
},
  "geometry": {"coordinates":[12.2330684662,51.8315162659],"type":"Point"}
}