{
  "type": "Feature",
  "properties": {
    "iso:country":"DE",
    "sg:address":"Am Haslach 1",
    "sg:city":"Deuerling",
    "sg:phone":"+49 9498/94020",
    "sg:postcode":"93180",
    "sg:province":"Bayern",
    "wof:name":"Manfred Rullmann",
    "wof:placetype":"venue"
},
  "geometry": {"coordinates":[11.911774,49.040119],"type":"Point"}
}