{
  "type": "Feature",
  "properties": {
    "iso:country":"DE",
    "sg:address":"Mannsdorfer Str. 27 c",
    "sg:city":"Ebersbach",
    "sg:postcode":"04720",
    "sg:province":"Sachsen",
    "wof:name":"D\u00f6belner Sport Und Freizeit Gmbh & Co. Kg",
    "wof:placetype":"venue"
},
  "geometry": {"coordinates":[13.0904846191,51.1077919006],"type":"Point"}
}