{
  "type": "Feature",
  "properties": {
    "iso:country":"DE",
    "sg:address":"Witteringstr. 4",
    "sg:city":"Essen",
    "sg:postcode":"45130",
    "sg:province":"Nordrhein-Westfalen",
    "wof:name":"Peters Verwaltungs Gmbh",
    "wof:placetype":"venue"
},
  "geometry": {"coordinates":[7.0067801476,51.4402885437],"type":"Point"}
}