{
  "type": "Feature",
  "properties": {
    "iso:country":"DE",
    "sg:address":"Stieglitzhof 16",
    "sg:city":"Solingen",
    "sg:phone":"+49 212/248490",
    "sg:postcode":"42657",
    "sg:province":"Nordrhein-Westfalen",
    "wof:name":"Manfred Krause Architekt",
    "wof:placetype":"venue"
},
  "geometry": {"coordinates":[7.075461,51.146664],"type":"Point"}
}