{
  "type": "Feature",
  "properties": {
    "iso:country":"DE",
    "sg:address":"Schulstr. 5",
    "sg:city":"Engstingen",
    "sg:phone":"+49 7385/660",
    "sg:postcode":"72829",
    "sg:province":"Baden-W\u00fcrttemberg",
    "wof:name":"R\u00f6cker Kg",
    "wof:placetype":"venue"
},
  "geometry": {"coordinates":[9.330179,48.404171],"type":"Point"}
}