{
  "type": "Feature",
  "properties": {
    "iso:country":"DE",
    "sg:address":"Schulstr. 14",
    "sg:city":"\u00d6tigheim",
    "sg:phone":"+49 7222/24093",
    "sg:postcode":"76470",
    "sg:province":"Baden-W\u00fcrttemberg",
    "wof:name":"F. Kleinkopf",
    "wof:placetype":"venue"
},
  "geometry": {"coordinates":[8.2351522446,48.8892936707],"type":"Point"}
}