{
  "type": "Feature",
  "properties": {
    "iso:country":"DE",
    "sg:address":"Karmeliterweg 48",
    "sg:city":"Berlin",
    "sg:phone":"+49 30/40100736",
    "sg:postcode":"13465",
    "sg:province":"Berlin",
    "wof:name":"Bernhard Pohl Finanzberater",
    "wof:placetype":"venue"
},
  "geometry": {"coordinates":[13.280913353,52.6280784607],"type":"Point"}
}