{
  "type": "Feature",
  "properties": {
    "iso:country":"DE",
    "sg:address":"Janssenstr. 5 a",
    "sg:city":"Kleve",
    "sg:phone":"+49 2821/30879",
    "sg:postcode":"47533",
    "sg:province":"Nordrhein-Westfalen",
    "wof:name":"Miroslaw Klunder",
    "wof:placetype":"venue"
},
  "geometry": {"coordinates":[6.125833,51.810452],"type":"Point"}
}