{
  "type": "Feature",
  "properties": {
    "iso:country":"DE",
    "sg:address":"Kirchgasse 13",
    "sg:city":"Walluf",
    "sg:postcode":"65396",
    "sg:province":"Hessen",
    "wof:name":"G\u00f6pfert Wohn- Und Gewerbe- Bau Gmbh",
    "wof:placetype":"venue"
},
  "geometry": {"coordinates":[8.160646,50.034485],"type":"Point"}
}