{
  "type": "Feature",
  "properties": {
    "iso:country":"DE",
    "sg:address":"Huntestr. 5",
    "sg:city":"Oldenburg",
    "sg:postcode":"26135",
    "sg:province":"Niedersachsen",
    "wof:name":"Raiffeisen Wohnungsbau- Genossenschaft Oldenburg Eg",
    "wof:placetype":"venue"
},
  "geometry": {"coordinates":[8.2186088562,53.137096405],"type":"Point"}
}