{
  "type": "Feature",
  "properties": {
    "iso:country":"DE",
    "sg:address":"S\u00fclzg\u00fcrtel 94",
    "sg:city":"K\u00f6ln",
    "sg:phone":"+49 221/441476",
    "sg:postcode":"50937",
    "sg:province":"Nordrhein-Westfalen",
    "wof:name":"Eiscafe Massimo Defedilta",
    "wof:placetype":"venue"
},
  "geometry": {"coordinates":[6.915786,50.920052],"type":"Point"}
}