{
  "type": "Feature",
  "properties": {
    "iso:country":"DE",
    "sg:address":"Bielefelder Str. 39",
    "sg:city":"Bad Laer",
    "sg:phone":"+49 5424/9234",
    "sg:postcode":"49196",
    "sg:province":"Niedersachsen",
    "wof:name":"Bernhard Niebr\u00fcgge",
    "wof:placetype":"venue"
},
  "geometry": {"coordinates":[8.0980377197,52.1014900208],"type":"Point"}
}