{
  "type": "Feature",
  "properties": {
    "iso:country":"DE",
    "sg:address":"Hauptstr. 31",
    "sg:city":"Ottersheim",
    "sg:phone":"+49 6355/441",
    "sg:postcode":"67308",
    "sg:province":"Rheinland-Pfalz",
    "wof:name":"Erwin W\u00fcrz",
    "wof:placetype":"venue"
},
  "geometry": {"coordinates":[8.110047,49.625206],"type":"Point"}
}