{
  "type": "Feature",
  "properties": {
    "iso:country":"DE",
    "sg:address":"Geislohe 21",
    "sg:city":"Pappenheim",
    "sg:phone":"+49 9149/1224",
    "sg:postcode":"91788",
    "sg:province":"Bayern",
    "wof:name":"F. U. I. H\u00fcttinger",
    "wof:placetype":"venue"
},
  "geometry": {"coordinates":[10.984664,48.965267],"type":"Point"}
}