{
  "type": "Feature",
  "properties": {
    "iso:country":"DE",
    "sg:address":"Am Sandberg 4",
    "sg:city":"Weyhe",
    "sg:postcode":"28844",
    "sg:province":"Niedersachsen",
    "wof:name":"Kwb Construction Gmbh",
    "wof:placetype":"venue"
},
  "geometry": {"coordinates":[8.792258,52.992123],"type":"Point"}
}