{
  "type": "Feature",
  "properties": {
    "iso:country":"DE",
    "sg:address":"Wohlhaupterstr. 6",
    "sg:city":"Eichenzell",
    "sg:postcode":"36124",
    "sg:province":"Hessen",
    "wof:name":"Paul Kl\u00fcber Gmbh",
    "wof:placetype":"venue"
},
  "geometry": {"coordinates":[9.7029409409,50.4983596802],"type":"Point"}
}