{
  "type": "Feature",
  "properties": {
    "iso:country":"DE",
    "sg:address":"Breite Str. 59",
    "sg:city":"Vehlefanz",
    "sg:phone":"+49 3304/253228",
    "sg:postcode":"16727",
    "sg:province":"Brandenburg",
    "wof:name":"Wanderreiten Im Havelland",
    "wof:placetype":"venue"
},
  "geometry": {"coordinates":[13.11175,52.69635],"type":"Point"}
}