{
  "type": "Feature",
  "properties": {
    "iso:country":"DE",
    "sg:address":"Hauptstr. 51",
    "sg:city":"Dittelbrunn",
    "sg:phone":"+49 9721/44310",
    "sg:postcode":"97456",
    "sg:province":"Bayern",
    "wof:name":"Raiffeisenbank Sennfeld Und Umgeb., Eg",
    "wof:placetype":"venue"
},
  "geometry": {"coordinates":[10.22143,50.07431],"type":"Point"}
}