{
  "type": "Feature",
  "properties": {
    "iso:country":"DE",
    "sg:address":"Chamonixstr. 14",
    "sg:city":"Garmisch-Partenkirchen",
    "sg:phone":"+49 8821/1633",
    "sg:postcode":"82467",
    "sg:province":"Bayern",
    "wof:name":"Kreisboten-reisedienst",
    "wof:placetype":"venue"
},
  "geometry": {"coordinates":[11.0946893692,47.4943695068],"type":"Point"}
}