{
  "type": "Feature",
  "properties": {
    "iso:country":"DE",
    "sg:address":"Heilswannenweg 56",
    "sg:city":"Elze",
    "sg:phone":"+49 5068/2100",
    "sg:postcode":"31008",
    "sg:province":"Niedersachsen",
    "wof:name":"Gnc-verfahrenstechnik W. Schierbaum-planungs-",
    "wof:placetype":"venue"
},
  "geometry": {"coordinates":[9.731422,52.111702],"type":"Point"}
}