{
  "type": "Feature",
  "properties": {
    "iso:country":"DE",
    "sg:address":"Buchholzer Landstr. 62",
    "sg:city":"Buchholz",
    "sg:phone":"+49 4187/7791",
    "sg:postcode":"21244",
    "sg:province":"Niedersachsen",
    "wof:name":"Bert Lorenz",
    "wof:placetype":"venue"
},
  "geometry": {"coordinates":[9.870726,53.2873],"type":"Point"}
}