{
  "type": "Feature",
  "properties": {
    "iso:country":"DE",
    "sg:address":"Donauw\u00f6rther Str. 62",
    "sg:city":"Neuburg",
    "sg:phone":"+49 8431/40690",
    "sg:postcode":"86633",
    "sg:province":"Bayern",
    "wof:name":"Nachtcafe",
    "wof:placetype":"venue"
},
  "geometry": {"coordinates":[11.16756,48.733738],"type":"Point"}
}