{
  "type": "Feature",
  "properties": {
    "iso:country":"DE",
    "sg:address":"Gr\u00f6pelinger Str. 82",
    "sg:city":"Bad Bederkesa",
    "sg:phone":"+49 4745/5034",
    "sg:postcode":"27624",
    "sg:province":"Niedersachsen",
    "wof:name":"Heinz G. Behling",
    "wof:placetype":"venue"
},
  "geometry": {"coordinates":[8.846228,53.617344],"type":"Point"}
}