{
  "type": "Feature",
  "properties": {
    "iso:country":"DE",
    "sg:address":"An der Schmiede 37",
    "sg:city":"Rheine",
    "sg:phone":"+49 5975/93472",
    "sg:postcode":"48432",
    "sg:province":"Nordrhein-Westfalen",
    "wof:name":"Abc-nachf\u00fclltinte",
    "wof:placetype":"venue"
},
  "geometry": {"coordinates":[7.4805178642,52.2207527161],"type":"Point"}
}