{
  "type": "Feature",
  "properties": {
    "iso:country":"DE",
    "sg:address":"Bahnhofstr. 17",
    "sg:city":"Penzlin",
    "sg:phone":"+49 3962/210501",
    "sg:postcode":"17217",
    "sg:province":"Mecklenburg-Vorpommern",
    "wof:name":"Heinrich Hertz Eg",
    "wof:placetype":"venue"
},
  "geometry": {"coordinates":[13.0837450027,53.5056495667],"type":"Point"}
}