{
  "type": "Feature",
  "properties": {
    "iso:country":"DE",
    "sg:address":"Langgewann 49",
    "sg:city":"Heidelberg",
    "sg:phone":"+49 6221/401246",
    "sg:postcode":"69121",
    "sg:province":"Baden-W\u00fcrttemberg",
    "wof:name":"Anton Kartak Rechtsanwalt",
    "wof:placetype":"venue"
},
  "geometry": {"coordinates":[8.6789417267,49.4209403992],"type":"Point"}
}