{
  "type": "Feature",
  "properties": {
    "iso:country":"DE",
    "sg:address":"Oberstr. 21",
    "sg:city":"Neuss",
    "sg:phone":"+49 2131/21067",
    "sg:postcode":"41460",
    "sg:province":"Nordrhein-Westfalen",
    "wof:name":"Prokom Pharm. Ges. F\u00fcr Pharmamarketing Und",
    "wof:placetype":"venue"
},
  "geometry": {"coordinates":[6.697335,51.195312],"type":"Point"}
}