{
  "type": "Feature",
  "properties": {
    "iso:country":"DE",
    "sg:address":"Pfalzring 21",
    "sg:city":"Bobenheim-Roxheim",
    "sg:phone":"+49 6239/929126",
    "sg:postcode":"67240",
    "sg:province":"Rheinland-Pfalz",
    "wof:name":"Apotheke Am Pfalzring",
    "wof:placetype":"venue"
},
  "geometry": {"coordinates":[8.358158,49.581852],"type":"Point"}
}