{
  "type": "Feature",
  "properties": {
    "iso:country":"DE",
    "sg:address":"Viktoriastrasse 14 a",
    "sg:city":"Coburg",
    "sg:phone":"+49 9561/94669",
    "sg:postcode":"96450",
    "sg:province":"Bayern",
    "wof:name":"Antiquitaeten Andreas Lenz",
    "wof:placetype":"venue"
},
  "geometry": {"coordinates":[10.9607906342,50.2583808899],"type":"Point"}
}