{
  "type": "Feature",
  "properties": {
    "iso:country":"DE",
    "sg:address":"Friedrichstr. 7",
    "sg:city":"Wardenburg",
    "sg:phone":"+49 4407/2236",
    "sg:postcode":"26203",
    "sg:province":"Niedersachsen",
    "wof:name":"Naturladen S. Grotel\u00fcschen",
    "wof:placetype":"venue"
},
  "geometry": {"coordinates":[8.1956453323,53.0625648499],"type":"Point"}
}