{
  "type": "Feature",
  "properties": {
    "iso:country":"DE",
    "sg:address":"Kloster Banz",
    "sg:city":"Staffelstein",
    "sg:phone":"+49 9573/53744",
    "sg:postcode":"96231",
    "sg:province":"Bayern",
    "wof:name":"Petrefaktensammlung",
    "wof:placetype":"venue"
},
  "geometry": {"coordinates":[10.999785,50.134281],"type":"Point"}
}