{
  "type": "Feature",
  "properties": {
    "iso:country":"DE",
    "sg:address":"Elisabethstr. 10",
    "sg:city":"Remscheid",
    "sg:phone":"+49 2191/387823",
    "sg:postcode":"42859",
    "sg:province":"Nordrhein-Westfalen",
    "wof:name":"Bosch Telecom Gmbh",
    "wof:placetype":"venue"
},
  "geometry": {"coordinates":[7.201540947,51.1721382141],"type":"Point"}
}