{
  "type": "Feature",
  "properties": {
    "iso:country":"DE",
    "sg:address":"Burggasse",
    "sg:city":"Bergheim",
    "sg:phone":"+49 2271/596412",
    "sg:postcode":"50126",
    "sg:province":"Nordrhein-Westfalen",
    "wof:name":"Archiv Der Rheinbraun Ag",
    "wof:placetype":"venue"
},
  "geometry": {"coordinates":[6.608335,50.963772],"type":"Point"}
}