{
  "type": "Feature",
  "properties": {
    "iso:country":"DE",
    "sg:address":"M\u00f6llendorffstr. 50 A",
    "sg:city":"Berlin",
    "sg:phone":"+49 30/5542240",
    "sg:postcode":"10367",
    "sg:province":"Berlin",
    "wof:name":"Frank Schwedler",
    "wof:placetype":"venue"
},
  "geometry": {"coordinates":[13.4799499512,52.5245628357],"type":"Point"}
}