{
  "type": "Feature",
  "properties": {
    "iso:country":"DE",
    "sg:address":"Stadtplatz 11",
    "sg:city":"Velburg",
    "sg:phone":"+49 9182/2230",
    "sg:postcode":"92355",
    "sg:province":"Bayern",
    "wof:name":"Frankfurter Versicherungs Ag",
    "wof:placetype":"venue"
},
  "geometry": {"coordinates":[11.6709470749,49.2332038879],"type":"Point"}
}