{
  "type": "Feature",
  "properties": {
    "iso:country":"DE",
    "sg:address":"Schulstr. 4",
    "sg:city":"Berlin",
    "sg:phone":"+49 30/4948188",
    "sg:postcode":"13187",
    "sg:province":"Berlin",
    "wof:name":"Ludwig Frank & Frank Meyer Gbr",
    "wof:placetype":"venue"
},
  "geometry": {"coordinates":[13.4097852707,52.569393158],"type":"Point"}
}