{
  "type": "Feature",
  "properties": {
    "iso:country":"DE",
    "sg:address":"Holtenauer Str. 94",
    "sg:city":"Kiel",
    "sg:phone":"+49 431/567367",
    "sg:postcode":"24105",
    "sg:province":"Schleswig-Holstein",
    "wof:name":"Horst Walter Architekt",
    "wof:placetype":"venue"
},
  "geometry": {"coordinates":[10.133469,54.334461],"type":"Point"}
}