{
  "type": "Feature",
  "properties": {
    "iso:country":"DE",
    "sg:address":"Pflanzgartenstr. 57",
    "sg:city":"Berlin",
    "sg:postcode":"12555",
    "sg:province":"Berlin",
    "wof:name":"Dr. Med. Elvire R\u00f6sler",
    "wof:placetype":"venue"
},
  "geometry": {"coordinates":[13.586788,52.469887],"type":"Point"}
}