{
  "type": "Feature",
  "properties": {
    "iso:country":"DE",
    "sg:address":"Wallstr. 76",
    "sg:city":"B\u00fcckeburg",
    "sg:phone":"+49 5722/22876",
    "sg:postcode":"31675",
    "sg:province":"Niedersachsen",
    "wof:name":"La Palma",
    "wof:placetype":"venue"
},
  "geometry": {"coordinates":[9.0527429581,52.2613143921],"type":"Point"}
}