{
  "type": "Feature",
  "properties": {
    "iso:country":"DE",
    "sg:address":"Kaulbachplatz 5",
    "sg:city":"N\u00fcrnberg",
    "sg:phone":"+49 911/352080",
    "sg:postcode":"90408",
    "sg:province":"Bayern",
    "wof:name":"Dipl.ing. Vural Cokbudak Architekt",
    "wof:placetype":"venue"
},
  "geometry": {"coordinates":[11.076795,49.463562],"type":"Point"}
}