{
  "type": "Feature",
  "properties": {
    "iso:country":"DE",
    "sg:address":"Kriegsbergstr. 11",
    "sg:city":"Stuttgart",
    "sg:phone":"+49 4971/1229960",
    "sg:postcode":"70174",
    "sg:province":"Baden-W\u00fcrttemberg",
    "wof:name":"Cc-bank Ag",
    "wof:placetype":"venue"
},
  "geometry": {"coordinates":[9.17835,48.784142],"type":"Point"}
}