{
  "type": "Feature",
  "properties": {
    "iso:country":"DE",
    "sg:address":"Wiesenweg 3",
    "sg:city":"Maselheim",
    "sg:phone":"+49 7356/2209",
    "sg:postcode":"88437",
    "sg:province":"Baden-W\u00fcrttemberg",
    "wof:name":"Alois Rodi",
    "wof:placetype":"venue"
},
  "geometry": {"coordinates":[9.8706092834,48.1494216919],"type":"Point"}
}