{
  "type": "Feature",
  "properties": {
    "iso:country":"DE",
    "sg:address":"Am Birkfeld 18",
    "sg:city":"Dasing",
    "sg:phone":"+49 8205/96000",
    "sg:postcode":"86453",
    "sg:province":"Bayern",
    "wof:name":"Fila Boutique Gmbh",
    "wof:placetype":"venue"
},
  "geometry": {"coordinates":[11.085447,48.391747],"type":"Point"}
}