{
  "type": "Feature",
  "properties": {
    "iso:country":"DE",
    "sg:address":"Steinweg 18",
    "sg:city":"Wuppertal",
    "sg:phone":"+49 202/553390",
    "sg:postcode":"42275",
    "sg:province":"Nordrhein-Westfalen",
    "wof:name":"Heinr. Ramien",
    "wof:placetype":"venue"
},
  "geometry": {"coordinates":[7.195137,51.271774],"type":"Point"}
}