{
  "type": "Feature",
  "properties": {
    "iso:country":"DE",
    "sg:address":"Fredericiastr. 9 a",
    "sg:city":"Berlin",
    "sg:phone":"+49 30/3021292",
    "sg:postcode":"14050",
    "sg:province":"Berlin",
    "wof:name":"Josephski",
    "wof:placetype":"venue"
},
  "geometry": {"coordinates":[13.280327,52.511002],"type":"Point"}
}