{
  "type": "Feature",
  "properties": {
    "iso:country":"DE",
    "sg:address":"Hauptstr. 81",
    "sg:city":"Neu-Ulm",
    "sg:phone":"+49 731/719965",
    "sg:postcode":"89233",
    "sg:province":"Bayern",
    "wof:name":"Krone",
    "wof:placetype":"venue"
},
  "geometry": {"coordinates":[10.0402555466,48.4105682373],"type":"Point"}
}