{
  "type": "Feature",
  "properties": {
    "iso:country":"DE",
    "sg:address":"Im \u00d6schle 5",
    "sg:city":"Sigmaringen",
    "sg:phone":"+49 7571/51239",
    "sg:postcode":"72488",
    "sg:province":"Baden-W\u00fcrttemberg",
    "wof:name":"Schiller Bau",
    "wof:placetype":"venue"
},
  "geometry": {"coordinates":[9.15308,48.093636],"type":"Point"}
}