{
  "type": "Feature",
  "properties": {
    "iso:country":"DE",
    "sg:address":"Alter Steinweg 42",
    "sg:city":"M\u00fcnster",
    "sg:phone":"+49 251/482440",
    "sg:postcode":"48143",
    "sg:province":"Nordrhein-Westfalen",
    "wof:name":"Csr Jura Intensiv Repetitorium",
    "wof:placetype":"venue"
},
  "geometry": {"coordinates":[7.6316027641,51.9617996216],"type":"Point"}
}