{
  "type": "Feature",
  "properties": {
    "iso:country":"DE",
    "sg:address":"Weimesstr. 19",
    "sg:city":"Neuhof",
    "sg:phone":"+49 6655/919025",
    "sg:postcode":"36119",
    "sg:province":"Hessen",
    "wof:name":"Gerhard Walter Zeltverleih",
    "wof:placetype":"venue"
},
  "geometry": {"coordinates":[9.6710395813,50.4698410034],"type":"Point"}
}