{
  "type": "Feature",
  "properties": {
    "iso:country":"DE",
    "sg:address":"Hauptstr. 2",
    "sg:city":"B\u00f6tzingen",
    "sg:phone":"+49 7663/940095",
    "sg:postcode":"79268",
    "sg:province":"Baden-W\u00fcrttemberg",
    "wof:name":"Franz Barleon Weinanbau Und Rebveredlung",
    "wof:placetype":"venue"
},
  "geometry": {"coordinates":[7.7195000648,48.0719909668],"type":"Point"}
}