{
  "type": "Feature",
  "properties": {
    "iso:country":"DE",
    "sg:address":"Rheinh\u00e4user Str. 25",
    "sg:city":"Altlu\u00dfheim",
    "sg:phone":"+49 6205/33875",
    "sg:postcode":"68804",
    "sg:province":"Baden-W\u00fcrttemberg",
    "wof:name":"E. Dengler",
    "wof:placetype":"venue"
},
  "geometry": {"coordinates":[8.49726,49.299271],"type":"Point"}
}