{
  "type": "Feature",
  "properties": {
    "iso:country":"DE",
    "sg:address":"Wodanstr. 85",
    "sg:city":"K\u00f6ln",
    "sg:phone":"+49 221/866296",
    "sg:postcode":"51107",
    "sg:province":"Nordrhein-Westfalen",
    "wof:name":"S. Wolf Rechtsanwalt",
    "wof:placetype":"venue"
},
  "geometry": {"coordinates":[7.0971431732,50.9270553589],"type":"Point"}
}