{
  "type": "Feature",
  "properties": {
    "iso:country":"DE",
    "sg:address":"Breitestr. 2",
    "sg:city":"Simmerath",
    "sg:phone":"+49 2473/7358",
    "sg:postcode":"52152",
    "sg:province":"Nordrhein-Westfalen",
    "wof:name":"Paul Fink Architekt",
    "wof:placetype":"venue"
},
  "geometry": {"coordinates":[6.303811,50.577621],"type":"Point"}
}