{
  "type": "Feature",
  "properties": {
    "iso:country":"DE",
    "sg:address":"Ruhrstra\u00dfe 13",
    "sg:city":"Winterberg - Niedersfeld",
    "sg:phone":"+49 2985",
    "sg:postcode":"59955",
    "sg:province":"Nordrhein-Westfalen",
    "wof:name":"Honig Loechelt",
    "wof:placetype":"venue"
},
  "geometry": {"coordinates":[8.5261287689,51.262752533],"type":"Point"}
}