{
  "type": "Feature",
  "properties": {
    "iso:country":"DE",
    "sg:address":"Hinter der Kirche 4",
    "sg:city":"Neuental",
    "sg:phone":"+49 6693/617",
    "sg:postcode":"34599",
    "sg:province":"Hessen",
    "wof:name":"Ev. Pfarramt Zimmersrode",
    "wof:placetype":"venue"
},
  "geometry": {"coordinates":[9.2313718796,51.0060691833],"type":"Point"}
}