{
  "type": "Feature",
  "properties": {
    "iso:country":"DE",
    "sg:address":"Hindenburgstr. 13",
    "sg:city":"Altenstadt",
    "sg:postcode":"89281",
    "sg:province":"Bayern",
    "wof:name":"Raiffeisenbank Illereichen-altenstadt Eg",
    "wof:placetype":"venue"
},
  "geometry": {"coordinates":[10.13549,48.164539],"type":"Point"}
}