{
  "type": "Feature",
  "properties": {
    "iso:country":"DE",
    "sg:address":"Forststr. 4",
    "sg:city":"Gladenbach",
    "sg:phone":"+49 6462/8748",
    "sg:postcode":"35075",
    "sg:province":"Hessen",
    "wof:name":"Heinrich Sch\u00e4fer",
    "wof:placetype":"venue"
},
  "geometry": {"coordinates":[8.57649,50.799103],"type":"Point"}
}