{
  "type": "Feature",
  "properties": {
    "iso:country":"DE",
    "sg:address":"Kirchstr. 14",
    "sg:city":"Aschau",
    "sg:phone":"+49 8052/2446",
    "sg:postcode":"83229",
    "sg:province":"Bayern",
    "wof:name":"Peppis W\u00fcrstl Handels Gmbh",
    "wof:placetype":"venue"
},
  "geometry": {"coordinates":[12.2604093552,47.6834716797],"type":"Point"}
}