{
  "type": "Feature",
  "properties": {
    "iso:country":"DE",
    "sg:address":"Walter-Geerdes-Str. 14",
    "sg:city":"Bremen",
    "sg:postcode":"28307",
    "sg:province":"Bremen",
    "wof:name":"Fft Gmbh Industrievertretung",
    "wof:placetype":"venue"
},
  "geometry": {"coordinates":[8.9616518021,53.0475234985],"type":"Point"}
}