{
  "type": "Feature",
  "properties": {
    "iso:country":"DE",
    "sg:address":"Kleiner Sch\u00e4ferkamp 14",
    "sg:city":"Hamburg",
    "sg:phone":"+49 40/4102956",
    "sg:postcode":"20357",
    "sg:province":"Hamburg",
    "wof:name":"G\u00fcnaydin",
    "wof:placetype":"venue"
},
  "geometry": {"coordinates":[9.9692287445,53.5673217773],"type":"Point"}
}