{
  "type": "Feature",
  "properties": {
    "iso:country":"DE",
    "sg:address":"Cuxhavener Str. 65",
    "sg:city":"Nordleda",
    "sg:phone":"+49 4758/424",
    "sg:postcode":"21765",
    "sg:province":"Niedersachsen",
    "wof:name":"Hans Pape",
    "wof:placetype":"venue"
},
  "geometry": {"coordinates":[8.810891,53.771706],"type":"Point"}
}