{
  "type": "Feature",
  "properties": {
    "iso:country":"DE",
    "sg:address":"Bahnhofstr. 1 a",
    "sg:city":"Loburg",
    "sg:phone":"+49 39245/2513",
    "sg:postcode":"39279",
    "sg:province":"Sachsen-Anhalt",
    "wof:name":"Kleine Oase",
    "wof:placetype":"venue"
},
  "geometry": {"coordinates":[12.0883026123,52.1155204773],"type":"Point"}
}