{
  "type": "Feature",
  "properties": {
    "iso:country":"DE",
    "sg:address":"Sonnenstr. 4",
    "sg:city":"Bad F\u00fcssing",
    "sg:phone":"+49 8531/29717",
    "sg:postcode":"94072",
    "sg:province":"Bayern",
    "wof:name":"Manfred Graw Architekt",
    "wof:placetype":"venue"
},
  "geometry": {"coordinates":[13.30975,48.354603],"type":"Point"}
}