{
  "type": "Feature",
  "properties": {
    "iso:country":"DE",
    "sg:address":"Weimarer Str. 31 b",
    "sg:city":"Hanau",
    "sg:phone":"+49 6181/20479",
    "sg:postcode":"63454",
    "sg:province":"Hessen",
    "wof:name":"Intercomputer",
    "wof:placetype":"venue"
},
  "geometry": {"coordinates":[8.8857088089,50.1356201172],"type":"Point"}
}