{
  "type": "Feature",
  "properties": {
    "iso:country":"DE",
    "sg:address":"Im Dorfe 36",
    "sg:city":"Oettern",
    "sg:phone":"+49 36453/81440",
    "sg:postcode":"99438",
    "sg:province":"Th\u00fcringen",
    "wof:name":"N. Ungeth\u00fcm",
    "wof:placetype":"venue"
},
  "geometry": {"coordinates":[11.356861,50.922005],"type":"Point"}
}