{
  "type": "Feature",
  "properties": {
    "iso:country":"DE",
    "sg:address":"Unnerstr. 3",
    "sg:city":"Heimbach",
    "sg:phone":"+49 6789/94006",
    "sg:postcode":"55779",
    "sg:province":"Rheinland-Pfalz",
    "wof:name":"Stefan Riehm",
    "wof:placetype":"venue"
},
  "geometry": {"coordinates":[7.2485251427,49.6137161255],"type":"Point"}
}