{
  "type": "Feature",
  "properties": {
    "iso:country":"DE",
    "sg:address":"Goethestr. 14",
    "sg:city":"Linden",
    "sg:phone":"+49 6403/92350",
    "sg:postcode":"35440",
    "sg:province":"Hessen",
    "wof:name":"Goethe-apotheke",
    "wof:placetype":"venue"
},
  "geometry": {"coordinates":[8.6573,50.525631],"type":"Point"}
}