{
  "type": "Feature",
  "properties": {
    "iso:country":"DE",
    "sg:address":"Sudetensiedlung 5",
    "sg:city":"Mainhausen",
    "sg:phone":"+49 6182/21688",
    "sg:postcode":"63533",
    "sg:province":"Hessen",
    "wof:name":"B. Friedrich",
    "wof:placetype":"venue"
},
  "geometry": {"coordinates":[9.0052099228,50.0103645325],"type":"Point"}
}