{
  "type": "Feature",
  "properties": {
    "iso:country":"DE",
    "sg:address":"Balkenkamp 11",
    "sg:city":"Uchte",
    "sg:phone":"+49 5763/555",
    "sg:postcode":"31600",
    "sg:province":"Niedersachsen",
    "wof:name":"Linden-apotheke",
    "wof:placetype":"venue"
},
  "geometry": {"coordinates":[8.908006,52.498219],"type":"Point"}
}