{
  "type": "Feature",
  "properties": {
    "iso:country":"DE",
    "sg:address":"Hollener Landstr. 28",
    "sg:city":"Uplengen",
    "sg:phone":"+49 4489/1413",
    "sg:postcode":"26670",
    "sg:province":"Niedersachsen",
    "wof:name":"Hinrich Plagge Gmbh",
    "wof:placetype":"venue"
},
  "geometry": {"coordinates":[7.6996507645,53.2502632141],"type":"Point"}
}