{
  "type": "Feature",
  "properties": {
    "iso:country":"DE",
    "sg:address":"Einfelder Str. 27",
    "sg:city":"Neum\u00fcnster",
    "sg:phone":"+49 4321/529232",
    "sg:postcode":"24536",
    "sg:province":"Schleswig-Holstein",
    "wof:name":"Terence Wood Rechtsanwalt",
    "wof:placetype":"venue"
},
  "geometry": {"coordinates":[9.9930973053,54.1277923584],"type":"Point"}
}