{
  "type": "Feature",
  "properties": {
    "iso:country":"DE",
    "sg:address":"Am Dobben 98",
    "sg:city":"Bremen",
    "sg:phone":"+49 421/700065",
    "sg:postcode":"28203",
    "sg:province":"Bremen",
    "wof:name":"Einhorn-humboldt-apotheke",
    "wof:placetype":"venue"
},
  "geometry": {"coordinates":[8.82287,53.075344],"type":"Point"}
}