{
  "type": "Feature",
  "properties": {
    "iso:country":"DE",
    "sg:address":"D\u00fcppenweilerstr. 81 a",
    "sg:city":"Schmelz",
    "sg:phone":"+49 6887/2852",
    "sg:postcode":"66839",
    "sg:province":"Saarland",
    "wof:name":"Irma Szygulla",
    "wof:placetype":"venue"
},
  "geometry": {"coordinates":[6.831304,49.422424],"type":"Point"}
}