{
  "type": "Feature",
  "properties": {
    "iso:country":"DE",
    "sg:address":"Juchostr. 20",
    "sg:city":"Dortmund",
    "sg:postcode":"44143",
    "sg:province":"Nordrhein-Westfalen",
    "wof:name":"Holstein & Kappert Gmbh",
    "wof:placetype":"venue"
},
  "geometry": {"coordinates":[7.513098,51.520119],"type":"Point"}
}