{
  "type": "Feature",
  "properties": {
    "iso:country":"DE",
    "sg:address":"Langer Schemm 61",
    "sg:city":"Rietberg",
    "sg:phone":"+49 5244/932220",
    "sg:postcode":"33397",
    "sg:province":"Nordrhein-Westfalen",
    "wof:name":"Ncs Netzwerk & Computer & Service Gmbh",
    "wof:placetype":"venue"
},
  "geometry": {"coordinates":[8.4521160126,51.8421478271],"type":"Point"}
}