{
  "type": "Feature",
  "properties": {
    "iso:country":"DE",
    "sg:address":"Hauptstr. 16 a",
    "sg:city":"Bad Honnef",
    "sg:phone":"+49 2224/79296",
    "sg:postcode":"53604",
    "sg:province":"Nordrhein-Westfalen",
    "wof:name":"G & T Weinimport Georg Pfirrmann E. K.",
    "wof:placetype":"venue"
},
  "geometry": {"coordinates":[7.2220311165,50.6484680176],"type":"Point"}
}