{
  "type": "Feature",
  "properties": {
    "iso:country":"DE",
    "sg:city":"Bad Hersfeld",
    "sg:postcode":"36251",
    "sg:province":"Hessen",
    "wof:name":"Selma\u00b4s Haartraum - Biosthetik Beauty Coiffeur",
    "wof:placetype":"venue"
},
  "geometry": {"coordinates":[9.712997,50.869339],"type":"Point"}
}