{
  "type": "Feature",
  "properties": {
    "iso:country":"DE",
    "sg:address":"Carstennstr. 1",
    "sg:city":"Berlin",
    "sg:phone":"+49 30/8479120",
    "sg:postcode":"12205",
    "sg:province":"Berlin",
    "wof:name":"Marten Metallbau Charlotte Marten Kg",
    "wof:placetype":"venue"
},
  "geometry": {"coordinates":[13.286981,52.432377],"type":"Point"}
}