{
  "type": "Feature",
  "properties": {
    "iso:country":"DE",
    "sg:address":"Belchenstr. 16",
    "sg:city":"Sch\u00f6nenberg",
    "sg:phone":"+49 7673/542",
    "sg:postcode":"79677",
    "sg:province":"Baden-W\u00fcrttemberg",
    "wof:name":"Beckerhof",
    "wof:placetype":"venue"
},
  "geometry": {"coordinates":[7.8806900978,47.7940483093],"type":"Point"}
}