{
  "type": "Feature",
  "properties": {
    "iso:country":"DE",
    "sg:address":"Von-der-Mark-Str. 94",
    "sg:city":"Duisburg",
    "sg:phone":"+49 203/434401",
    "sg:postcode":"47137",
    "sg:province":"Nordrhein-Westfalen",
    "wof:name":"Kuchler",
    "wof:placetype":"venue"
},
  "geometry": {"coordinates":[6.770568,51.46735],"type":"Point"}
}