{
  "type": "Feature",
  "properties": {
    "iso:country":"DE",
    "sg:address":"Altendorfer Str. 313",
    "sg:city":"Essen",
    "sg:phone":"+49 201/626333",
    "sg:postcode":"45143",
    "sg:province":"Nordrhein-Westfalen",
    "wof:name":"Manfred M\u00e4nnig Rechtsanwalt Und Notar",
    "wof:placetype":"venue"
},
  "geometry": {"coordinates":[6.9782061577,51.4610328674],"type":"Point"}
}