{
  "type": "Feature",
  "properties": {
    "iso:country":"DE",
    "sg:address":"Rektor-Gieles-Str. 20",
    "sg:city":"Hanau",
    "sg:phone":"+49 6181/60459",
    "sg:postcode":"63456",
    "sg:province":"Hessen",
    "wof:name":"Helmut Scheurich",
    "wof:placetype":"venue"
},
  "geometry": {"coordinates":[8.9319572449,50.1003074646],"type":"Point"}
}