{
  "type": "Feature",
  "properties": {
    "iso:country":"DE",
    "sg:address":"Neust\u00e4dter Str. 1",
    "sg:city":"Sebnitz",
    "sg:phone":"+49 35971/57469",
    "sg:postcode":"01855",
    "sg:province":"Sachsen",
    "wof:name":"Kotte & Hoyer Gbr",
    "wof:placetype":"venue"
},
  "geometry": {"coordinates":[14.270157814,50.9726829529],"type":"Point"}
}