{
  "type": "Feature",
  "properties": {
    "iso:country":"DE",
    "sg:address":"Buschweg 37",
    "sg:city":"Norderstedt",
    "sg:phone":"+49 40/5217915",
    "sg:postcode":"22850",
    "sg:province":"Schleswig-Holstein",
    "wof:name":"R. Borchert",
    "wof:placetype":"venue"
},
  "geometry": {"coordinates":[9.985792,53.695148],"type":"Point"}
}