{
  "type": "Feature",
  "properties": {
    "iso:country":"DE",
    "sg:address":"Steinaer Str. 14",
    "sg:city":"Ohorn",
    "sg:phone":"+49 35955/3694",
    "sg:postcode":"01896",
    "sg:province":"Sachsen",
    "wof:name":"Linden",
    "wof:placetype":"venue"
},
  "geometry": {"coordinates":[14.055658,51.187378],"type":"Point"}
}