{
  "type": "Feature",
  "properties": {
    "iso:country":"DE",
    "sg:address":"Berliner Platz 19",
    "sg:city":"Neuss",
    "sg:phone":"+49 2131/50825",
    "sg:postcode":"41462",
    "sg:province":"Nordrhein-Westfalen",
    "wof:name":"Manfred Hass Masseur",
    "wof:placetype":"venue"
},
  "geometry": {"coordinates":[6.674334,51.209629],"type":"Point"}
}