{
  "type": "Feature",
  "properties": {
    "iso:country":"DE",
    "sg:address":"Saarbr\u00fccker Str. 10",
    "sg:city":"Kleinblittersdorf",
    "sg:postcode":"66271",
    "sg:province":"Saarland",
    "wof:name":"Wolfgang Bur Gesch\u00e4fts- F\u00fchrungsgesellschaft Mbh",
    "wof:placetype":"venue"
},
  "geometry": {"coordinates":[7.0344147682,49.1578636169],"type":"Point"}
}