{
  "type": "Feature",
  "properties": {
    "iso:country":"DE",
    "sg:address":"Korbacher Str. 20",
    "sg:city":"Willingen",
    "sg:phone":"+49 5632/5229",
    "sg:postcode":"34508",
    "sg:province":"Hessen",
    "wof:name":"Karl Saure",
    "wof:placetype":"venue"
},
  "geometry": {"coordinates":[8.6684865952,51.2817687988],"type":"Point"}
}