{
  "type": "Feature",
  "properties": {
    "iso:country":"DE",
    "sg:address":"Sch\u00fctzenstr. 14",
    "sg:city":"G\u00f6ppingen",
    "sg:phone":"+49 7161/960660",
    "sg:postcode":"73033",
    "sg:province":"Baden-W\u00fcrttemberg",
    "wof:name":"Dr. Carl Hagedorn Ingenieur",
    "wof:placetype":"venue"
},
  "geometry": {"coordinates":[9.6554412842,48.7022705078],"type":"Point"}
}