{
  "type": "Feature",
  "properties": {
    "iso:country":"DE",
    "sg:address":"Eisenbahnstr. 19 - 23",
    "sg:city":"Achern",
    "sg:postcode":"77855",
    "sg:province":"Baden-W\u00fcrttemberg",
    "wof:name":"Immobilienverwaltung Schwab- Stra\u00dfe Gesch\u00e4ftsf\u00fchrungs-",
    "wof:placetype":"venue"
},
  "geometry": {"coordinates":[8.067728,48.631134],"type":"Point"}
}