{
  "type": "Feature",
  "properties": {
    "iso:country":"DE",
    "sg:address":"Am See 32",
    "sg:city":"Parthenstein",
    "sg:phone":"+49 34293/29643",
    "sg:postcode":"04668",
    "sg:province":"Sachsen",
    "wof:name":"Steffen Kayser Architekt",
    "wof:placetype":"venue"
},
  "geometry": {"coordinates":[12.621676,51.268051],"type":"Point"}
}