{
  "type": "Feature",
  "properties": {
    "iso:country":"DE",
    "sg:address":"Wilhelmstr. 5",
    "sg:city":"W\u00fcrzburg",
    "sg:phone":"+49 931/54139",
    "sg:postcode":"97070",
    "sg:province":"Bayern",
    "wof:name":"Gerhard Hickl",
    "wof:placetype":"venue"
},
  "geometry": {"coordinates":[9.9318227768,49.7953948975],"type":"Point"}
}