{
  "type": "Feature",
  "properties": {
    "iso:country":"DE",
    "sg:address":"Lorsbacher Str. 48",
    "sg:city":"Eppstein",
    "sg:phone":"+49 6198/7718",
    "sg:postcode":"65817",
    "sg:province":"Hessen",
    "wof:name":"Restaurant Le Chateau",
    "wof:placetype":"venue"
},
  "geometry": {"coordinates":[8.4100265503,50.1301879883],"type":"Point"}
}