{
  "type": "Feature",
  "properties": {
    "iso:country":"DE",
    "sg:address":"Hahnerberger Str. 137/139",
    "sg:city":"Wuppertal",
    "sg:phone":"+49 4920/2408660",
    "sg:postcode":"42349",
    "sg:province":"Nordrhein-Westfalen",
    "wof:name":"Gustav Weber Kg",
    "wof:placetype":"venue"
},
  "geometry": {"coordinates":[7.152278,51.2225],"type":"Point"}
}