{
  "type": "Feature",
  "properties": {
    "iso:country":"DE",
    "sg:address":"Ahornweg 15",
    "sg:city":"Tuntenhausen",
    "sg:phone":"+49 8065/90350",
    "sg:postcode":"83104",
    "sg:province":"Bayern",
    "wof:name":"Innocom Gmbh",
    "wof:placetype":"venue"
},
  "geometry": {"coordinates":[11.970082283,47.9513702393],"type":"Point"}
}