{
  "type": "Feature",
  "properties": {
    "iso:country":"DE",
    "sg:address":"Einsiedelweg 6",
    "sg:city":"Murnau",
    "sg:phone":"+49 8841/3123",
    "sg:postcode":"82418",
    "sg:province":"Bayern",
    "wof:name":"Michael Meier Gmbh",
    "wof:placetype":"venue"
},
  "geometry": {"coordinates":[11.206276,47.679028],"type":"Point"}
}