{
  "type": "Feature",
  "properties": {
    "iso:country":"DE",
    "sg:address":"Messe-Turm",
    "sg:city":"Frankfurt",
    "sg:phone":"+49 69/71290",
    "sg:postcode":"60308",
    "sg:province":"Hessen",
    "wof:name":"Korea Exchange Bank (deutschland) Ag",
    "wof:placetype":"venue"
},
  "geometry": {"coordinates":[8.664363,50.117439],"type":"Point"}
}