{
  "type": "Feature",
  "properties": {
    "iso:country":"DE",
    "sg:address":"Meller Str. 15",
    "sg:city":"Osnabr\u00fcck",
    "sg:phone":"+49 541/57929",
    "sg:postcode":"49082",
    "sg:province":"Niedersachsen",
    "wof:name":"Arthur Schulte",
    "wof:placetype":"venue"
},
  "geometry": {"coordinates":[8.0558385849,52.2657661438],"type":"Point"}
}