{
  "type": "Feature",
  "properties": {
    "iso:country":"DE",
    "sg:address":"Nordfeldstr. 34",
    "sg:city":"Bergkamen",
    "sg:phone":"+49 2307/87066",
    "sg:postcode":"59192",
    "sg:province":"Nordrhein-Westfalen",
    "wof:name":"H-d Linkamp Gmbh & Co. Kg",
    "wof:placetype":"venue"
},
  "geometry": {"coordinates":[7.6496191025,51.6050682068],"type":"Point"}
}