{
  "type": "Feature",
  "properties": {
    "iso:country":"DE",
    "sg:address":"Iglinger Str. 3 a",
    "sg:city":"Kaufering",
    "sg:phone":"+49 8191/64290",
    "sg:postcode":"86916",
    "sg:province":"Bayern",
    "wof:name":"Dr. Med. T. Schultz-wittner Arzt F\u00fcr Allgemeinmedizin",
    "wof:placetype":"venue"
},
  "geometry": {"coordinates":[10.8586940765,48.0839691162],"type":"Point"}
}