{
  "type": "Feature",
  "properties": {
    "iso:country":"DE",
    "sg:address":"Sachsendorfer Str. 20",
    "sg:city":"Cottbus",
    "sg:phone":"+49 355/795956",
    "sg:postcode":"03046",
    "sg:province":"Brandenburg",
    "wof:name":"V. Ziegner Anlageberater",
    "wof:placetype":"venue"
},
  "geometry": {"coordinates":[14.3044452667,51.7523880005],"type":"Point"}
}