{
  "type": "Feature",
  "properties": {
    "iso:country":"DE",
    "sg:address":"Fuchsweg 1",
    "sg:city":"Beilngries",
    "sg:phone":"+49 8461/423",
    "sg:postcode":"92339",
    "sg:province":"Bayern",
    "wof:name":"Bernhard Schr\u00f6der",
    "wof:placetype":"venue"
},
  "geometry": {"coordinates":[11.485637,49.039883],"type":"Point"}
}