{
  "type": "Feature",
  "properties": {
    "iso:country":"DE",
    "sg:address":"Bahnhofstr. 20",
    "sg:city":"Grebenstein",
    "sg:postcode":"34393",
    "sg:province":"Hessen",
    "wof:name":"Immobilien Eg Der Raiffeisenbanken",
    "wof:placetype":"venue"
},
  "geometry": {"coordinates":[9.4183254242,51.4468688965],"type":"Point"}
}