{
  "type": "Feature",
  "properties": {
    "iso:country":"DE",
    "sg:address":"Lindenstra\u00dfe 11",
    "sg:city":"Bad Elster",
    "sg:phone":"+49 37437/3379",
    "sg:postcode":"08645",
    "sg:province":"Sachsen",
    "wof:name":"Gerhard Benker Steuerberater",
    "wof:placetype":"venue"
},
  "geometry": {"coordinates":[12.2358064651,50.2817955017],"type":"Point"}
}