{
  "type": "Feature",
  "properties": {
    "iso:country":"DE",
    "sg:address":"Gro\u00dfe Steinstr. 63",
    "sg:city":"Halle",
    "sg:postcode":"06108",
    "sg:province":"Sachsen-Anhalt",
    "wof:name":"Msx Gesch\u00e4ftsraum Vermietungs Gmbh",
    "wof:placetype":"venue"
},
  "geometry": {"coordinates":[11.9750442505,51.4861869812],"type":"Point"}
}