{
  "type": "Feature",
  "properties": {
    "iso:country":"DE",
    "sg:address":"Detmolder Str. 32",
    "sg:city":"Paderborn",
    "sg:phone":"+49 5251/15960",
    "sg:postcode":"33102",
    "sg:province":"Nordrhein-Westfalen",
    "wof:name":"Taxi E.-m. Glowienka",
    "wof:placetype":"venue"
},
  "geometry": {"coordinates":[8.7611789703,51.7258605957],"type":"Point"}
}