{
  "type": "Feature",
  "properties": {
    "iso:country":"DE",
    "sg:address":"Liebensteiner Str. 3",
    "sg:city":"Winterstein",
    "sg:phone":"+49 36259/5230",
    "sg:postcode":"99891",
    "sg:province":"Th\u00fcringen",
    "wof:name":"Wintersteiner Schwimmbadtechnik Gmbh",
    "wof:placetype":"venue"
},
  "geometry": {"coordinates":[10.4569225311,50.8849258423],"type":"Point"}
}