{
  "type": "Feature",
  "properties": {
    "iso:country":"DE",
    "sg:address":"Mittelstr. 1",
    "sg:city":"Wilnsdorf",
    "sg:phone":"+49 271/392824",
    "sg:postcode":"57234",
    "sg:province":"Nordrhein-Westfalen",
    "wof:name":"Flora Frisch 3000 Gmbh",
    "wof:placetype":"venue"
},
  "geometry": {"coordinates":[8.091445,50.851978],"type":"Point"}
}