{
  "type": "Feature",
  "properties": {
    "iso:country":"DE",
    "sg:address":"Bismarckstr. 33",
    "sg:city":"Bremen",
    "sg:phone":"+49 421/4985938",
    "sg:postcode":"28203",
    "sg:province":"Bremen",
    "wof:name":"Dr. J. Wegner Rechtsanwalt",
    "wof:placetype":"venue"
},
  "geometry": {"coordinates":[8.8283548355,53.0780181885],"type":"Point"}
}