{
  "type": "Feature",
  "properties": {
    "iso:country":"DE",
    "sg:address":"Von-der-Recke-Str. 7",
    "sg:city":"Bochum",
    "sg:phone":"+49 234/522050",
    "sg:postcode":"44809",
    "sg:province":"Nordrhein-Westfalen",
    "wof:name":"Wahine",
    "wof:placetype":"venue"
},
  "geometry": {"coordinates":[7.1927042007,51.4926528931],"type":"Point"}
}