{
  "type": "Feature",
  "properties": {
    "iso:country":"DE",
    "sg:address":"Bauerndoktor-Gros-Str. 6",
    "sg:city":"Neustadt",
    "sg:phone":"+49 6327/626",
    "sg:postcode":"67435",
    "sg:province":"Rheinland-Pfalz",
    "wof:name":"Roland Hamann",
    "wof:placetype":"venue"
},
  "geometry": {"coordinates":[8.1964845657,49.3221168518],"type":"Point"}
}