{
  "type": "Feature",
  "properties": {
    "iso:country":"DE",
    "sg:address":"Lipschitzallee 70",
    "sg:city":"Berlin",
    "sg:phone":"+49 30/6032098",
    "sg:postcode":"12353",
    "sg:province":"Berlin",
    "wof:name":"J\u00fcrgen Thiele Gmbh",
    "wof:placetype":"venue"
},
  "geometry": {"coordinates":[13.463051,52.424526],"type":"Point"}
}