{
  "type": "Feature",
  "properties": {
    "iso:country":"DE",
    "sg:address":"Oberstr. 63",
    "sg:city":"Dormagen",
    "sg:phone":"+49 2133/71713",
    "sg:postcode":"41541",
    "sg:province":"Nordrhein-Westfalen",
    "wof:name":"Niederrheinisch-bergisches Gemeinschaftswasserwerk Gmbh",
    "wof:placetype":"venue"
},
  "geometry": {"coordinates":[6.8322658539,51.1381454468],"type":"Point"}
}