{
  "type": "Feature",
  "properties": {
    "iso:country":"DE",
    "sg:address":"Schoppenbergweg 14",
    "sg:city":"Kaufungen",
    "sg:phone":"+49 5605/2033",
    "sg:postcode":"34260",
    "sg:province":"Hessen",
    "wof:name":"Tsi Gmbh & Co Kg",
    "wof:placetype":"venue"
},
  "geometry": {"coordinates":[9.632913,51.288403],"type":"Point"}
}