{
  "type": "Feature",
  "properties": {
    "iso:country":"DE",
    "sg:address":"M\u00fchlenstr. 52",
    "sg:city":"Pinneberg",
    "sg:phone":"+49 4101/27081",
    "sg:postcode":"25421",
    "sg:province":"Schleswig-Holstein",
    "wof:name":"Keros-bau Gmbh",
    "wof:placetype":"venue"
},
  "geometry": {"coordinates":[9.780859,53.657597],"type":"Point"}
}