{
  "type": "Feature",
  "properties": {
    "iso:country":"DE",
    "sg:address":"An Den Reesenbetten 14",
    "sg:city":"B\u00fcdelsdorf",
    "sg:phone":"+49 4943/3130266",
    "sg:postcode":"24782",
    "sg:province":"Schleswig-Holstein",
    "wof:name":"Armin Nielsen",
    "wof:placetype":"venue"
},
  "geometry": {"coordinates":[9.6960411072,54.3225669861],"type":"Point"}
}