{
  "type": "Feature",
  "properties": {
    "iso:country":"DE",
    "sg:address":"Stockhausenstr. 10",
    "sg:city":"Neustadt",
    "sg:phone":"+49 5032/2614",
    "sg:postcode":"31535",
    "sg:province":"Niedersachsen",
    "wof:name":"A. Neumann",
    "wof:placetype":"venue"
},
  "geometry": {"coordinates":[9.4573497772,52.5008506775],"type":"Point"}
}