{
  "type": "Feature",
  "properties": {
    "iso:country":"DE",
    "sg:address":"Saseler Chaussee 128",
    "sg:city":"Hamburg",
    "sg:phone":"+49 40/6016796",
    "sg:postcode":"22393",
    "sg:province":"Hamburg",
    "wof:name":"N\u00fcrnberger Bund Grosseinkauf Eg",
    "wof:placetype":"venue"
},
  "geometry": {"coordinates":[10.1025705338,53.6475410461],"type":"Point"}
}