{
  "type": "Feature",
  "properties": {
    "iso:country":"DE",
    "sg:address":"Wiestorstr. 23",
    "sg:city":"\u00dcberlingen",
    "sg:phone":"+49 7551/970748",
    "sg:postcode":"88662",
    "sg:province":"Baden-W\u00fcrttemberg",
    "wof:name":"Raben",
    "wof:placetype":"venue"
},
  "geometry": {"coordinates":[9.1615180969,47.7687644958],"type":"Point"}
}