{
  "type": "Feature",
  "properties": {
    "iso:country":"DE",
    "sg:address":"Aktienstr. 277",
    "sg:city":"M\u00fclheim",
    "sg:phone":"+49 208/763212",
    "sg:postcode":"45473",
    "sg:province":"Nordrhein-Westfalen",
    "wof:name":"Barbara-apotheke",
    "wof:placetype":"venue"
},
  "geometry": {"coordinates":[6.910073,51.447487],"type":"Point"}
}