{
  "type": "Feature",
  "properties": {
    "iso:country":"DE",
    "sg:address":"Nahtweg 58",
    "sg:city":"Netphen",
    "sg:phone":"+49 2737/592311",
    "sg:postcode":"57250",
    "sg:province":"Nordrhein-Westfalen",
    "wof:name":"Picosoft Automatisierungs Gmbh",
    "wof:placetype":"venue"
},
  "geometry": {"coordinates":[8.1397104263,50.8883361816],"type":"Point"}
}