{
  "type": "Feature",
  "properties": {
    "iso:country":"DE",
    "sg:address":"Obernhainer Weg 28",
    "sg:city":"Wehrheim",
    "sg:phone":"+49 6081/981086",
    "sg:postcode":"61273",
    "sg:province":"Hessen",
    "wof:name":"Findata Financial Data Service Gmbh",
    "wof:placetype":"venue"
},
  "geometry": {"coordinates":[8.5650157928,50.2988548279],"type":"Point"}
}