{
  "type": "Feature",
  "properties": {
    "iso:country":"DE",
    "sg:address":"N\u00fcrnberger Str. 24/26",
    "sg:city":"Erlangen",
    "sg:postcode":"91052",
    "sg:province":"Bayern",
    "wof:name":"Safin E. K.",
    "wof:placetype":"venue"
},
  "geometry": {"coordinates":[11.0059461594,49.5924224854],"type":"Point"}
}