{
  "type": "Feature",
  "properties": {
    "iso:country":"DE",
    "sg:address":"Dorfstr. 10",
    "sg:city":"Neu Bartelshagen",
    "sg:phone":"+49 38321/369",
    "sg:postcode":"18442",
    "sg:province":"Mecklenburg-Vorpommern",
    "wof:name":"Gastst\u00e4tte Girod",
    "wof:placetype":"venue"
},
  "geometry": {"coordinates":[12.866645813,54.3440933228],"type":"Point"}
}