{
  "type": "Feature",
  "properties": {
    "iso:country":"DE",
    "sg:address":"Die L\u00e4chner 5",
    "sg:city":"B\u00fcrstadt",
    "sg:postcode":"68642",
    "sg:province":"Hessen",
    "wof:name":"Aldi Gmbh & Co. Kg",
    "wof:placetype":"venue"
},
  "geometry": {"coordinates":[8.4497938156,49.6392707825],"type":"Point"}
}