{
  "type": "Feature",
  "properties": {
    "iso:country":"DE",
    "sg:address":"Marbacher Str. 80",
    "sg:city":"Stuttgart",
    "sg:phone":"+49 711/871312",
    "sg:postcode":"70435",
    "sg:province":"Baden-W\u00fcrttemberg",
    "wof:name":"Blumen Wenz Ohg",
    "wof:placetype":"venue"
},
  "geometry": {"coordinates":[9.176241,48.8358],"type":"Point"}
}