{
  "type": "Feature",
  "properties": {
    "iso:country":"DE",
    "sg:address":"Seligenweg 10",
    "sg:city":"Hof",
    "sg:phone":"+49 9281/83020",
    "sg:postcode":"95028",
    "sg:province":"Bayern",
    "wof:name":"Christian Dalloz Holding Deutschland Gmbh & Co Kg",
    "wof:placetype":"venue"
},
  "geometry": {"coordinates":[11.9093637466,50.3250999451],"type":"Point"}
}