{
  "type": "Feature",
  "properties": {
    "iso:country":"DE",
    "sg:address":"Breite Str. 33",
    "sg:city":"Ludwigslust",
    "sg:phone":"+49 3874/21718",
    "sg:postcode":"19288",
    "sg:province":"Mecklenburg-Vorpommern",
    "wof:name":"Karl Metzner",
    "wof:placetype":"venue"
},
  "geometry": {"coordinates":[11.501868,53.325951],"type":"Point"}
}