{
  "type": "Feature",
  "properties": {
    "iso:country":"DE",
    "sg:address":"Winsbergring 38",
    "sg:city":"Hamburg",
    "sg:phone":"+49 40/85308502",
    "sg:postcode":"22525",
    "sg:province":"Hamburg",
    "wof:name":"Birkner Gmbh & Co Kg",
    "wof:placetype":"venue"
},
  "geometry": {"coordinates":[9.916519165,53.5764923096],"type":"Point"}
}