{
  "type": "Feature",
  "properties": {
    "iso:country":"DE",
    "sg:address":"Am Stra\u00dfbach 2",
    "sg:city":"Friedberg",
    "sg:phone":"+49 6031/61304",
    "sg:postcode":"61169",
    "sg:province":"Hessen",
    "wof:name":"Treffpunkt",
    "wof:placetype":"venue"
},
  "geometry": {"coordinates":[8.7467813492,50.3174247742],"type":"Point"}
}