{
  "type": "Feature",
  "properties": {
    "iso:country":"DE",
    "sg:address":"Bachstr. 16",
    "sg:city":"Selm",
    "sg:phone":"+49 2592/20555",
    "sg:postcode":"59379",
    "sg:province":"Nordrhein-Westfalen",
    "wof:name":"Thomas Kraft",
    "wof:placetype":"venue"
},
  "geometry": {"coordinates":[7.472329,51.689354],"type":"Point"}
}