{
  "type": "Feature",
  "properties": {
    "iso:country":"DE",
    "sg:address":"Heimgartenstr. 37",
    "sg:city":"Herrsching",
    "sg:phone":"+49 8152/1836",
    "sg:postcode":"82211",
    "sg:province":"Bayern",
    "wof:name":"Franz Sommersberger Architekt",
    "wof:placetype":"venue"
},
  "geometry": {"coordinates":[11.13771,48.041401],"type":"Point"}
}