{
  "type": "Feature",
  "properties": {
    "iso:country":"DE",
    "sg:address":"Gewerbering Nord 10",
    "sg:city":"Bretnig-Hauswalde",
    "sg:phone":"+49 35955/8210",
    "sg:postcode":"01900",
    "sg:province":"Sachsen",
    "wof:name":"G\u00e4bler Stahlhandel Gmbh",
    "wof:placetype":"venue"
},
  "geometry": {"coordinates":[14.050939,51.161694],"type":"Point"}
}