{
  "type": "Feature",
  "properties": {
    "iso:country":"DE",
    "sg:address":"Eckernweg 2",
    "sg:city":"Epenw\u00f6hrden",
    "sg:phone":"+49 4832/1851",
    "sg:postcode":"25704",
    "sg:province":"Schleswig-Holstein",
    "wof:name":"Ferdinand Bubbers",
    "wof:placetype":"venue"
},
  "geometry": {"coordinates":[9.07693,54.112972],"type":"Point"}
}