{
  "type": "Feature",
  "properties": {
    "iso:country":"DE",
    "sg:address":"Dr.-Caspary-Weg 1",
    "sg:city":"Elze",
    "sg:phone":"+49 5068/5000",
    "sg:postcode":"31008",
    "sg:province":"Niedersachsen",
    "wof:name":"Axel Reinecke Finanzberater",
    "wof:placetype":"venue"
},
  "geometry": {"coordinates":[9.7428627014,52.1312446594],"type":"Point"}
}