{
  "type": "Feature",
  "properties": {
    "iso:country":"DE",
    "sg:address":"Altheimer Str. 11",
    "sg:city":"Heiligenberg",
    "sg:phone":"+49 7552/6174",
    "sg:postcode":"88633",
    "sg:province":"Baden-W\u00fcrttemberg",
    "wof:name":"Anton Biller",
    "wof:placetype":"venue"
},
  "geometry": {"coordinates":[9.277034,47.859871],"type":"Point"}
}