{
  "type": "Feature",
  "properties": {
    "iso:country":"DE",
    "sg:address":"Kuseler Str. 5",
    "sg:city":"Blaubach",
    "sg:phone":"+49 6381/923800",
    "sg:postcode":"66869",
    "sg:province":"Rheinland-Pfalz",
    "wof:name":"Hotel Zum Reweschnier",
    "wof:placetype":"venue"
},
  "geometry": {"coordinates":[7.3977799416,49.5578346252],"type":"Point"}
}