{
  "type": "Feature",
  "properties": {
    "iso:country":"DE",
    "sg:address":"Robert-Bosch-Str. 53",
    "sg:city":"Walldorf",
    "sg:phone":"+49 6227/9145",
    "sg:postcode":"69190",
    "sg:province":"Baden-W\u00fcrttemberg",
    "wof:name":"Kunststoff-gro\u00dfhandel Stier Gmbh",
    "wof:placetype":"venue"
},
  "geometry": {"coordinates":[8.6486911774,49.2906112671],"type":"Point"}
}