{
  "type": "Feature",
  "properties": {
    "iso:country":"DE",
    "sg:address":"An der Betmauer 10",
    "sg:city":"Isny",
    "sg:phone":"+49 7562/2602",
    "sg:postcode":"88316",
    "sg:province":"Baden-W\u00fcrttemberg",
    "wof:name":"Heinz Schadt Gmbh",
    "wof:placetype":"venue"
},
  "geometry": {"coordinates":[10.06047,47.696842],"type":"Point"}
}