{
  "type": "Feature",
  "properties": {
    "iso:country":"DE",
    "sg:address":"Dorfstr. 14",
    "sg:city":"Bippen",
    "sg:phone":"+49 5909/358",
    "sg:postcode":"49626",
    "sg:province":"Niedersachsen",
    "wof:name":"Gustav T\u00f6bben",
    "wof:placetype":"venue"
},
  "geometry": {"coordinates":[7.632963,52.566475],"type":"Point"}
}