{
  "type": "Feature",
  "properties": {
    "iso:country":"DE",
    "sg:address":"St\u00fcvvenweg 9",
    "sg:city":"Metelen",
    "sg:phone":"+49 2556/576",
    "sg:postcode":"48629",
    "sg:province":"Nordrhein-Westfalen",
    "wof:name":"Sm-versorgungstechnik Gmbh",
    "wof:placetype":"venue"
},
  "geometry": {"coordinates":[7.209773,52.144917],"type":"Point"}
}