{
  "type": "Feature",
  "properties": {
    "iso:country":"DE",
    "sg:address":"Unterseite 22",
    "sg:city":"Waldsolms",
    "sg:phone":"+49 6085/797",
    "sg:postcode":"35647",
    "sg:province":"Hessen",
    "wof:name":"Peter Ludwig",
    "wof:placetype":"venue"
},
  "geometry": {"coordinates":[8.4970388412,50.4331855774],"type":"Point"}
}