{
  "type": "Feature",
  "properties": {
    "iso:country":"DE",
    "sg:address":"H\u00fcnstein 62",
    "sg:city":"Nohra",
    "sg:phone":"+49 36334/50703",
    "sg:postcode":"99735",
    "sg:province":"Th\u00fcringen",
    "wof:name":"Fachzentrum F\u00fcr Innenwirtschaft Ffi Gmbh",
    "wof:placetype":"venue"
},
  "geometry": {"coordinates":[10.718459,51.428135],"type":"Point"}
}