{
  "type": "Feature",
  "properties": {
    "iso:country":"DE",
    "sg:address":"Draisstr. 19a",
    "sg:city":"Muggensturm",
    "sg:phone":"+49 7222/52129",
    "sg:postcode":"76461",
    "sg:province":"Baden-W\u00fcrttemberg",
    "wof:name":"B.e.z. Bischoff Verwaltungsgesellschaft Mbh",
    "wof:placetype":"venue"
},
  "geometry": {"coordinates":[8.274705,48.881069],"type":"Point"}
}