{
  "type": "Feature",
  "properties": {
    "iso:country":"DE",
    "sg:address":"Messeallee 2",
    "sg:city":"Leipzig",
    "sg:phone":"+49 341/6095280",
    "sg:postcode":"04356",
    "sg:province":"Sachsen",
    "wof:name":"Kabel-fernsehen Leipzig Verwaltungs Gmbh",
    "wof:placetype":"venue"
},
  "geometry": {"coordinates":[12.395957,51.394341],"type":"Point"}
}