{
  "type": "Feature",
  "properties": {
    "iso:country":"DE",
    "sg:address":"Zum Roppertsborn 37",
    "sg:city":"Marpingen",
    "sg:phone":"+49 6827/630",
    "sg:postcode":"66646",
    "sg:province":"Saarland",
    "wof:name":"Bernhard Becker",
    "wof:placetype":"venue"
},
  "geometry": {"coordinates":[7.077723,49.437038],"type":"Point"}
}