{
  "type": "Feature",
  "properties": {
    "iso:country":"DE",
    "sg:address":"Sch\u00fcsselmarkt 6",
    "sg:city":"Bad Windsheim",
    "sg:phone":"+49 9841/1638",
    "sg:postcode":"91438",
    "sg:province":"Bayern",
    "wof:name":"W. Strebel",
    "wof:placetype":"venue"
},
  "geometry": {"coordinates":[10.418431282,49.5034255981],"type":"Point"}
}