{
  "type": "Feature",
  "properties": {
    "iso:country":"DE",
    "sg:address":"Heidelberger Str. 51",
    "sg:city":"Viernheim",
    "sg:phone":"+49 6204/78683",
    "sg:postcode":"68519",
    "sg:province":"Hessen",
    "wof:name":"Auto-elektrik Lierke Gmbh",
    "wof:placetype":"venue"
},
  "geometry": {"coordinates":[8.58721,49.534794],"type":"Point"}
}