{
  "type": "Feature",
  "properties": {
    "iso:country":"DE",
    "sg:address":"Bizetstr. 101",
    "sg:city":"Berlin",
    "sg:phone":"+49 30/92378589",
    "sg:postcode":"13088",
    "sg:province":"Berlin",
    "wof:name":"Vitalis Ergo Praxis F Ergotherapie",
    "wof:placetype":"venue"
},
  "geometry": {"coordinates":[13.460096,52.549297],"type":"Point"}
}