{
  "type": "Feature",
  "properties": {
    "iso:country":"DE",
    "sg:address":"Dettelbacher Str. 8a",
    "sg:city":"Schwarzach",
    "sg:phone":"+49 9324/903639",
    "sg:postcode":"97359",
    "sg:province":"Bayern",
    "wof:name":"Cad-technologie M\u00f6slein Gmbh",
    "wof:placetype":"venue"
},
  "geometry": {"coordinates":[10.2159385681,49.8059463501],"type":"Point"}
}