{
  "type": "Feature",
  "properties": {
    "iso:country":"DE",
    "sg:address":"Bergstr.",
    "sg:city":"Weilm\u00fcnster",
    "sg:phone":"+49 6472/1532",
    "sg:postcode":"35789",
    "sg:province":"Hessen",
    "wof:name":"Manfred Velten",
    "wof:placetype":"venue"
},
  "geometry": {"coordinates":[8.374483,50.43063],"type":"Point"}
}