{
  "type": "Feature",
  "properties": {
    "iso:country":"DE",
    "sg:address":"Langer Segen 15",
    "sg:city":"Kiel",
    "sg:phone":"+49 431/567395",
    "sg:postcode":"24105",
    "sg:province":"Schleswig-Holstein",
    "wof:name":"Peter Graichen Papiergro\u00dfhandlung E. K.",
    "wof:placetype":"venue"
},
  "geometry": {"coordinates":[10.136842,54.329983],"type":"Point"}
}