{
  "type": "Feature",
  "properties": {
    "iso:country":"DE",
    "sg:address":"B\u00fcsdorfer Str. 2b",
    "sg:city":"Bergheim",
    "sg:phone":"+49 2271/51841",
    "sg:postcode":"50129",
    "sg:province":"Nordrhein-Westfalen",
    "wof:name":"G. Kurth",
    "wof:placetype":"venue"
},
  "geometry": {"coordinates":[6.6785640717,50.973449707],"type":"Point"}
}