{
  "type": "Feature",
  "properties": {
    "iso:country":"DE",
    "sg:address":"Hauptstr. 33",
    "sg:city":"L\u00fcbbenau",
    "sg:phone":"+49 3542/42441",
    "sg:postcode":"03222",
    "sg:province":"Brandenburg",
    "wof:name":"Garni-hotel Behrendt Gmbh",
    "wof:placetype":"venue"
},
  "geometry": {"coordinates":[13.9332590103,51.8607177734],"type":"Point"}
}