{
  "type": "Feature",
  "properties": {
    "iso:country":"DE",
    "sg:address":"Kreisstr. 30",
    "sg:city":"Hannover",
    "sg:phone":"+49 511/95900",
    "sg:postcode":"30629",
    "sg:province":"Niedersachsen",
    "wof:name":"Pape Verwaltungs-gmbh",
    "wof:placetype":"venue"
},
  "geometry": {"coordinates":[9.850757,52.380016],"type":"Point"}
}