{
  "type": "Feature",
  "properties": {
    "iso:country":"DE",
    "sg:address":"Rathausstr. 9",
    "sg:city":"Michelau",
    "sg:phone":"+49 9574/4388",
    "sg:postcode":"96247",
    "sg:province":"Bayern",
    "wof:name":"Weber-moden Inh. Klaus Weber E. K.",
    "wof:placetype":"venue"
},
  "geometry": {"coordinates":[11.1507902145,50.168056488],"type":"Point"}
}