{
  "type": "Feature",
  "properties": {
    "iso:country":"DE",
    "sg:address":"Mistelweg 5",
    "sg:city":"Lichtenfels",
    "sg:phone":"+49 9571/5253",
    "sg:postcode":"96215",
    "sg:province":"Bayern",
    "wof:name":"H. Schuberth",
    "wof:placetype":"venue"
},
  "geometry": {"coordinates":[11.0965871811,50.1256561279],"type":"Point"}
}