{
  "type": "Feature",
  "properties": {
    "iso:country":"DE",
    "sg:address":"Leipziger Str. 29",
    "sg:city":"Saarbr\u00fccken",
    "sg:phone":"+49 681/75094",
    "sg:postcode":"66113",
    "sg:province":"Saarland",
    "wof:name":"P. Kreis",
    "wof:placetype":"venue"
},
  "geometry": {"coordinates":[6.966421,49.243767],"type":"Point"}
}