{
  "type": "Feature",
  "properties": {
    "iso:country":"DE",
    "sg:address":"K\u00e4the-Kollwitz-Str. 30a",
    "sg:city":"Ruhla",
    "sg:phone":"+49 36929/63037",
    "sg:postcode":"99842",
    "sg:province":"Th\u00fcringen",
    "wof:name":"Adk Hoch- Und Tiefbau Gmbh",
    "wof:placetype":"venue"
},
  "geometry": {"coordinates":[10.387328,50.881516],"type":"Point"}
}