{
  "type": "Feature",
  "properties": {
    "iso:country":"DE",
    "sg:address":"Annenstr. 38",
    "sg:city":"Plauen",
    "sg:postcode":"08523",
    "sg:province":"Sachsen",
    "wof:name":"Apis-immobilien-gmbh",
    "wof:placetype":"venue"
},
  "geometry": {"coordinates":[12.1408529282,50.4988822937],"type":"Point"}
}