{
  "type": "Feature",
  "properties": {
    "iso:country":"DE",
    "sg:address":"Berliner Str. 7",
    "sg:city":"Alsheim",
    "sg:phone":"+49 6249/6386",
    "sg:postcode":"67577",
    "sg:province":"Rheinland-Pfalz",
    "wof:name":"W. Heid",
    "wof:placetype":"venue"
},
  "geometry": {"coordinates":[8.345125,49.765366],"type":"Point"}
}