{
  "type": "Feature",
  "properties": {
    "iso:country":"DE",
    "sg:address":"Schalker Str. 76",
    "sg:city":"Gelsenkirchen",
    "sg:phone":"+49 209/378016",
    "sg:postcode":"45881",
    "sg:province":"Nordrhein-Westfalen",
    "wof:name":"Ursula Ruhland Heilpraktikerin",
    "wof:placetype":"venue"
},
  "geometry": {"coordinates":[7.09207201,51.5162010193],"type":"Point"}
}