{
  "type": "Feature",
  "properties": {
    "iso:country":"DE",
    "sg:address":"Normannshauser Weg 199",
    "sg:city":"Martfeld",
    "sg:phone":"+49 4255/391",
    "sg:postcode":"27327",
    "sg:province":"Niedersachsen",
    "wof:name":"Johann K\u00f6nig",
    "wof:placetype":"venue"
},
  "geometry": {"coordinates":[9.048592,52.868847],"type":"Point"}
}