{
  "type": "Feature",
  "properties": {
    "iso:country":"DE",
    "sg:address":"G\u00fcterfelder Str. 2",
    "sg:city":"Schenkenhorst",
    "sg:postcode":"14532",
    "sg:province":"Brandenburg",
    "wof:name":"Sicherheitsdienst Christian Engel Gmbh",
    "wof:placetype":"venue"
},
  "geometry": {"coordinates":[13.2001037598,52.3416137695],"type":"Point"}
}