{
  "type": "Feature",
  "properties": {
    "iso:country":"DE",
    "sg:address":"Adersheimer Str. 25",
    "sg:city":"Wolfenb\u00fcttel",
    "sg:phone":"+49 5331/4738",
    "sg:postcode":"38304",
    "sg:province":"Niedersachsen",
    "wof:name":"Aral Tankstelle",
    "wof:placetype":"venue"
},
  "geometry": {"coordinates":[10.5180177689,52.1614112854],"type":"Point"}
}