{
  "type": "Feature",
  "properties": {
    "iso:country":"DE",
    "sg:address":"Im Sch\u00fctzengrund 78",
    "sg:city":"Neuwied",
    "sg:phone":"+49 2622/92790",
    "sg:postcode":"56566",
    "sg:province":"Rheinland-Pfalz",
    "wof:name":"Wjs Waco Jonab Systeme Vertriebs-gmbh",
    "wof:placetype":"venue"
},
  "geometry": {"coordinates":[7.526321888,50.4288101196],"type":"Point"}
}