{
  "type": "Feature",
  "properties": {
    "iso:country":"DE",
    "sg:address":"Am Sonnenberg 39",
    "sg:city":"W\u00fcrzburg",
    "sg:phone":"+49 931/25938",
    "sg:postcode":"97078",
    "sg:province":"Bayern",
    "wof:name":"Prof.dr.-ing. Gert Wiechert",
    "wof:placetype":"venue"
},
  "geometry": {"coordinates":[9.9624004364,49.826839447],"type":"Point"}
}