{
  "type": "Feature",
  "properties": {
    "iso:country":"DE",
    "sg:address":"Prinzenstr. 1",
    "sg:city":"Duisburg",
    "sg:phone":"+49 203/480470",
    "sg:postcode":"47179",
    "sg:province":"Nordrhein-Westfalen",
    "wof:name":"W. Borkes",
    "wof:placetype":"venue"
},
  "geometry": {"coordinates":[6.742501,51.524918],"type":"Point"}
}