{
  "type": "Feature",
  "properties": {
    "iso:country":"DE",
    "sg:address":"Carl-Giesecke-Str. 1",
    "sg:city":"Braunschweig",
    "sg:phone":"+49 531/21110",
    "sg:postcode":"38112",
    "sg:province":"Niedersachsen",
    "wof:name":"Bmg (braunschweiger Metallverpackungsgesellschaft Mbh)",
    "wof:placetype":"venue"
},
  "geometry": {"coordinates":[10.4733247757,52.3210983276],"type":"Point"}
}