{
  "type": "Feature",
  "properties": {
    "iso:country":"DE",
    "sg:address":"Buchweg 4",
    "sg:city":"Denklingen",
    "sg:phone":"+49 8243/90115",
    "sg:postcode":"86920",
    "sg:province":"Bayern",
    "wof:name":"Molkereigenossenschaft Epfach Eg",
    "wof:placetype":"venue"
},
  "geometry": {"coordinates":[10.8504629135,47.9132652283],"type":"Point"}
}