{
  "type": "Feature",
  "properties": {
    "iso:country":"DE",
    "sg:address":"Winterstr. 20 a",
    "sg:city":"Bobingen",
    "sg:phone":"+49 8234/1736",
    "sg:postcode":"86399",
    "sg:province":"Bayern",
    "wof:name":"Norbert Fleisch",
    "wof:placetype":"venue"
},
  "geometry": {"coordinates":[10.799368,48.27319],"type":"Point"}
}