{
  "type": "Feature",
  "properties": {
    "iso:country":"DE",
    "sg:address":"Rotermundstr. 14",
    "sg:city":"Hannover",
    "sg:phone":"+49 511/3502035",
    "sg:postcode":"30165",
    "sg:province":"Niedersachsen",
    "wof:name":"Wolf-derek Adamiec",
    "wof:placetype":"venue"
},
  "geometry": {"coordinates":[9.7352542877,52.4011383057],"type":"Point"}
}