{
  "type": "Feature",
  "properties": {
    "iso:country":"DE",
    "sg:address":"Untere Marktstr. 4",
    "sg:city":"Bad Sulza",
    "sg:phone":"+49 36461/21638",
    "sg:postcode":"99518",
    "sg:province":"Th\u00fcringen",
    "wof:name":"C. Und Armin Eggert Versicherung Ag",
    "wof:placetype":"venue"
},
  "geometry": {"coordinates":[11.6232156754,51.0870895386],"type":"Point"}
}