{
  "type": "Feature",
  "properties": {
    "iso:country":"DE",
    "sg:address":"Benzstr. 17",
    "sg:city":"Geisenhausen",
    "sg:phone":"+49 8743/96860",
    "sg:postcode":"84144",
    "sg:province":"Bayern",
    "wof:name":"Arcom B\u00e4der Und Bauen Gmbh & Co. Vertriebs Kg",
    "wof:placetype":"venue"
},
  "geometry": {"coordinates":[12.2464866638,48.4816360474],"type":"Point"}
}