{
  "type": "Feature",
  "properties": {
    "iso:country":"DE",
    "sg:address":"Westring 40",
    "sg:city":"Kassel",
    "sg:phone":"+49 561/83063",
    "sg:postcode":"34127",
    "sg:province":"Hessen",
    "wof:name":"Friedrich Schwaab",
    "wof:placetype":"venue"
},
  "geometry": {"coordinates":[9.4990386963,51.3249015808],"type":"Point"}
}