{
  "type": "Feature",
  "properties": {
    "iso:country":"DE",
    "sg:address":"Wiesenstr. 6",
    "sg:city":"Burghausen",
    "sg:phone":"+49 341/4420210",
    "sg:postcode":"04430",
    "sg:province":"Bayern",
    "wof:name":"C. Winkler",
    "wof:placetype":"venue"
},
  "geometry": {"coordinates":[12.2660198212,51.3559989929],"type":"Point"}
}