{
  "type": "Feature",
  "properties": {
    "iso:country":"DE",
    "sg:address":"Bruchhausener Str. 13",
    "sg:city":"\u00dcbach-Palenberg",
    "sg:phone":"+49 2451/47376",
    "sg:postcode":"52531",
    "sg:province":"Nordrhein-Westfalen",
    "wof:name":"P. Pelster",
    "wof:placetype":"venue"
},
  "geometry": {"coordinates":[6.094952,50.916809],"type":"Point"}
}