{
  "type": "Feature",
  "properties": {
    "iso:country":"DE",
    "sg:address":"Hagenburger Str. 20",
    "sg:city":"Wunstorf",
    "sg:phone":"+49 5031/2617",
    "sg:postcode":"31515",
    "sg:province":"Niedersachsen",
    "wof:name":"K. Schubert",
    "wof:placetype":"venue"
},
  "geometry": {"coordinates":[9.419121,52.429394],"type":"Point"}
}