{
  "type": "Feature",
  "properties": {
    "iso:country":"DE",
    "sg:address":"Steinweg",
    "sg:city":"Bad Kreuznach",
    "sg:phone":"+49 671/32589",
    "sg:postcode":"55545",
    "sg:province":"Rheinland-Pfalz",
    "wof:name":"Thomas Anheuser",
    "wof:placetype":"venue"
},
  "geometry": {"coordinates":[7.8504748344,49.850189209],"type":"Point"}
}