{
  "type": "Feature",
  "properties": {
    "iso:country":"DE",
    "sg:address":"Kronsheider Str. 41",
    "sg:city":"Wahlstedt",
    "sg:phone":"+49 4554/2806",
    "sg:postcode":"23812",
    "sg:province":"Schleswig-Holstein",
    "wof:name":"Okal-cafe",
    "wof:placetype":"venue"
},
  "geometry": {"coordinates":[10.201027,53.947052],"type":"Point"}
}