{
  "type": "Feature",
  "properties": {
    "iso:country":"DE",
    "sg:address":"H\u00f6rdener Str. 39",
    "sg:city":"Gaggenau",
    "sg:phone":"+49 7224/3587",
    "sg:postcode":"76571",
    "sg:province":"Baden-W\u00fcrttemberg",
    "wof:name":"Rahner Maler Und Lackierer Gmbh",
    "wof:placetype":"venue"
},
  "geometry": {"coordinates":[8.347192,48.78236],"type":"Point"}
}