{
  "type": "Feature",
  "properties": {
    "iso:country":"DE",
    "sg:address":"Friedrichstr. 238",
    "sg:city":"Velbert",
    "sg:phone":"+49 2051/253975",
    "sg:postcode":"42551",
    "sg:province":"Nordrhein-Westfalen",
    "wof:name":"C. Doerfer",
    "wof:placetype":"venue"
},
  "geometry": {"coordinates":[7.0491337776,51.3372421265],"type":"Point"}
}