{
  "type": "Feature",
  "properties": {
    "iso:country":"DE",
    "sg:address":"Hinter dem Dom 6",
    "sg:city":"Trier",
    "sg:phone":"+49 651/7105233",
    "sg:postcode":"54290",
    "sg:province":"Rheinland-Pfalz",
    "wof:name":"Domschatz",
    "wof:placetype":"venue"
},
  "geometry": {"coordinates":[6.644554,49.755798],"type":"Point"}
}