{
  "type": "Feature",
  "properties": {
    "iso:country":"DE",
    "sg:address":"Hartstr. 10 c",
    "sg:city":"Germering",
    "sg:phone":"+49 89/845000",
    "sg:postcode":"82110",
    "sg:province":"Bayern",
    "wof:name":"Hans Haller",
    "wof:placetype":"venue"
},
  "geometry": {"coordinates":[11.378364563,48.1287231445],"type":"Point"}
}