{
  "type": "Feature",
  "properties": {
    "iso:country":"DE",
    "sg:address":"Hauptstr. 37",
    "sg:city":"Olching",
    "sg:phone":"+49 8142/12311",
    "sg:postcode":"82140",
    "sg:province":"Bayern",
    "wof:name":"Kaisers Drugstore",
    "wof:placetype":"venue"
},
  "geometry": {"coordinates":[11.3285446167,48.2077941895],"type":"Point"}
}