{
  "type": "Feature",
  "properties": {
    "iso:country":"DE",
    "sg:address":"Marktplatz 4",
    "sg:city":"Eschwege",
    "sg:phone":"+49 5651/6433",
    "sg:postcode":"37269",
    "sg:province":"Hessen",
    "wof:name":"J. Knauf",
    "wof:placetype":"venue"
},
  "geometry": {"coordinates":[10.058193,51.186722],"type":"Point"}
}