{
  "type": "Feature",
  "properties": {
    "iso:country":"DE",
    "sg:address":"Hauptstr. 16",
    "sg:city":"Gro\u00dfberndten",
    "sg:phone":"+49 36330/65347",
    "sg:postcode":"99713",
    "sg:province":"Th\u00fcringen",
    "wof:name":"Gastst\u00e4tte Gro\u00dfberndten",
    "wof:placetype":"venue"
},
  "geometry": {"coordinates":[10.7018718719,51.359752655],"type":"Point"}
}