{
  "type": "Feature",
  "properties": {
    "iso:country":"DE",
    "sg:address":"Klotzbergstr. 18",
    "sg:city":"B\u00fchl",
    "sg:phone":"+49 7223/21208",
    "sg:postcode":"77815",
    "sg:province":"Baden-W\u00fcrttemberg",
    "wof:name":"Weinberg",
    "wof:placetype":"venue"
},
  "geometry": {"coordinates":[8.1492185593,48.6916160583],"type":"Point"}
}