{
  "type": "Feature",
  "properties": {
    "iso:country":"DE",
    "sg:address":"Steifensandstr. 28",
    "sg:city":"Bedburg",
    "sg:phone":"+49 2272/7505",
    "sg:postcode":"50181",
    "sg:province":"Nordrhein-Westfalen",
    "wof:name":"Hans Griesche",
    "wof:placetype":"venue"
},
  "geometry": {"coordinates":[6.5583429337,51.0005226135],"type":"Point"}
}