{
  "type": "Feature",
  "properties": {
    "iso:country":"DE",
    "sg:address":"Druckerweg 2",
    "sg:city":"Lindlar",
    "sg:phone":"+49 2266/1277",
    "sg:postcode":"51789",
    "sg:province":"Nordrhein-Westfalen",
    "wof:name":"F. H\u00f6her",
    "wof:placetype":"venue"
},
  "geometry": {"coordinates":[7.407502,51.029617],"type":"Point"}
}