{
  "type": "Feature",
  "properties": {
    "iso:country":"DE",
    "sg:address":"Engelsbyer Str. 55",
    "sg:city":"Flensburg",
    "sg:phone":"+49 461/65378",
    "sg:postcode":"24943",
    "sg:province":"Schleswig-Holstein",
    "wof:name":"China Restaurant Jap Gmbh",
    "wof:placetype":"venue"
},
  "geometry": {"coordinates":[9.4723043442,54.7946434021],"type":"Point"}
}