{
  "type": "Feature",
  "properties": {
    "iso:country":"DE",
    "sg:address":"Am Bahnhof 4",
    "sg:city":"Friedrichsthal",
    "sg:phone":"+49 6897/8053",
    "sg:postcode":"66299",
    "sg:province":"Saarland",
    "wof:name":"Schwendler & Co. Kg",
    "wof:placetype":"venue"
},
  "geometry": {"coordinates":[7.0901417732,49.3199386597],"type":"Point"}
}