{
  "type": "Feature",
  "properties": {
    "iso:country":"DE",
    "sg:address":"Am L\u00fcnink 48",
    "sg:city":"Essen",
    "sg:phone":"+49 201/403008",
    "sg:postcode":"45239",
    "sg:province":"Nordrhein-Westfalen",
    "wof:name":"Hans-j\u00fcrgen Tils",
    "wof:placetype":"venue"
},
  "geometry": {"coordinates":[7.0311818123,51.3874931335],"type":"Point"}
}