{
  "type": "Feature",
  "properties": {
    "iso:country":"DE",
    "sg:address":"Siebengebirgsstr. 4",
    "sg:city":"Wachtberg",
    "sg:phone":"+49 228/342105",
    "sg:postcode":"53343",
    "sg:province":"Nordrhein-Westfalen",
    "wof:name":"Katharina Fa\u00dfbender",
    "wof:placetype":"venue"
},
  "geometry": {"coordinates":[7.1618719101,50.6489906311],"type":"Point"}
}