{
  "type": "Feature",
  "properties": {
    "iso:country":"DE",
    "sg:address":"Am Bergblick 20",
    "sg:city":"Marktoberdorf",
    "sg:postcode":"87616",
    "sg:province":"Bayern",
    "wof:name":"Orunt Organisations- Und Unternehmensberatungsges. Mbh",
    "wof:placetype":"venue"
},
  "geometry": {"coordinates":[10.6209154129,47.7723426819],"type":"Point"}
}