{
  "type": "Feature",
  "properties": {
    "iso:country":"DE",
    "sg:address":"D\u00fcmmerstr. 9",
    "sg:city":"Cloppenburg",
    "sg:phone":"+49 4471/4454",
    "sg:postcode":"49661",
    "sg:province":"Niedersachsen",
    "wof:name":"Hans-hermann Brand Heilpraktiker",
    "wof:placetype":"venue"
},
  "geometry": {"coordinates":[8.007352829,52.8376541138],"type":"Point"}
}