{
  "type": "Feature",
  "properties": {
    "iso:country":"DE",
    "sg:address":"Geisinger Str. 10",
    "sg:city":"Donaueschingen",
    "sg:phone":"+49 771/2422",
    "sg:postcode":"78166",
    "sg:province":"Baden-W\u00fcrttemberg",
    "wof:name":"J. Raible",
    "wof:placetype":"venue"
},
  "geometry": {"coordinates":[8.553902626,47.9389610291],"type":"Point"}
}