{
  "type": "Feature",
  "properties": {
    "iso:country":"DE",
    "sg:address":"Zypressenweg 3",
    "sg:city":"Flensburg",
    "sg:phone":"+49 461/32333",
    "sg:postcode":"24944",
    "sg:province":"Schleswig-Holstein",
    "wof:name":"Dieter Fels",
    "wof:placetype":"venue"
},
  "geometry": {"coordinates":[9.482933,54.806759],"type":"Point"}
}