{
  "type": "Feature",
  "properties": {
    "iso:country":"DE",
    "sg:address":"\u00d6hningen",
    "sg:city":"\u00d6hningen",
    "sg:phone":"+49 4977/358572",
    "sg:postcode":"78337",
    "sg:province":"Baden-W\u00fcrttemberg",
    "wof:name":"Volksbank Eg Zw. \u00d6hningen",
    "wof:placetype":"venue"
},
  "geometry": {"coordinates":[8.90442,47.67688],"type":"Point"}
}