{
  "type": "Feature",
  "properties": {
    "iso:country":"DE",
    "sg:address":"St.-Albans-Gasse 2",
    "sg:city":"Regensburg",
    "sg:phone":"+49 941/567976",
    "sg:postcode":"93047",
    "sg:province":"Bayern",
    "wof:name":"Music-in",
    "wof:placetype":"venue"
},
  "geometry": {"coordinates":[12.0922222137,49.0213508606],"type":"Point"}
}