{
  "type": "Feature",
  "properties": {
    "iso:country":"DE",
    "sg:address":"Alte Kelterstrasse 7",
    "sg:city":"Saarbr\u00fccken",
    "sg:phone":"+49 6893",
    "sg:postcode":"66130",
    "sg:province":"Saarland",
    "wof:name":"Dk-elektronik Gmbh",
    "wof:placetype":"venue"
},
  "geometry": {"coordinates":[7.0646710396,49.1979598999],"type":"Point"}
}