{
  "type": "Feature",
  "properties": {
    "iso:country":"DE",
    "sg:address":"Kuglerstr. 2",
    "sg:city":"M\u00fcnchen",
    "sg:phone":"+49 89/4702879",
    "sg:postcode":"81675",
    "sg:province":"Bayern",
    "wof:name":"Melanie Stachl",
    "wof:placetype":"venue"
},
  "geometry": {"coordinates":[11.605513,48.135845],"type":"Point"}
}