{
  "type": "Feature",
  "properties": {
    "iso:country":"DE",
    "sg:address":"Heldburger Str. 14",
    "sg:city":"Bad Rodach",
    "sg:phone":"+49 9564/4022",
    "sg:postcode":"96476",
    "sg:province":"Bayern",
    "wof:name":"Thomas Kreisler Arzt F\u00fcr Allgemeinmedizin",
    "wof:placetype":"venue"
},
  "geometry": {"coordinates":[10.7775268555,50.3396720886],"type":"Point"}
}