{
  "type": "Feature",
  "properties": {
    "iso:country":"DE",
    "sg:address":"Dorfstr. 5",
    "sg:city":"Bierstedt",
    "sg:phone":"+49 39007/752",
    "sg:postcode":"29416",
    "sg:province":"Sachsen-Anhalt",
    "wof:name":"Heidi Stowitschek",
    "wof:placetype":"venue"
},
  "geometry": {"coordinates":[11.0152759552,52.7231826782],"type":"Point"}
}