{
  "type": "Feature",
  "properties": {
    "iso:country":"DE",
    "sg:address":"Waffenstr. 13",
    "sg:city":"Landau",
    "sg:phone":"+49 6341/80918",
    "sg:postcode":"76829",
    "sg:province":"Rheinland-Pfalz",
    "wof:name":"Mannheimer Versicherungen Ehrenpreis",
    "wof:placetype":"venue"
},
  "geometry": {"coordinates":[8.1110486984,49.1974525452],"type":"Point"}
}