{
  "type": "Feature",
  "properties": {
    "iso:country":"DE",
    "sg:address":"Stiglmaierplatz 2",
    "sg:city":"M\u00fcnchen",
    "sg:phone":"+49 89/522845",
    "sg:postcode":"80333",
    "sg:province":"Bayern",
    "wof:name":"Mgm Pfand Und Wert Gmbh",
    "wof:placetype":"venue"
},
  "geometry": {"coordinates":[11.559154,48.147972],"type":"Point"}
}