{
  "type": "Feature",
  "properties": {
    "iso:country":"DE",
    "sg:address":"Neckarvorlandstr. 45",
    "sg:city":"Mannheim",
    "sg:phone":"+49 621/28381",
    "sg:postcode":"68159",
    "sg:province":"Baden-W\u00fcrttemberg",
    "wof:name":"Ludwig Und Jakob G\u00f6tz Gmbh & Co. Kg",
    "wof:placetype":"venue"
},
  "geometry": {"coordinates":[8.4616718292,49.4962844849],"type":"Point"}
}