{
  "type": "Feature",
  "properties": {
    "iso:country":"DE",
    "sg:address":"Schlo\u00dfberg 3",
    "sg:city":"Osterfeld",
    "sg:phone":"+49 34422/21525",
    "sg:postcode":"06721",
    "sg:province":"Sachsen-Anhalt",
    "wof:name":"Sch\u00fctzenhaus",
    "wof:placetype":"venue"
},
  "geometry": {"coordinates":[11.9341402054,51.0784797668],"type":"Point"}
}