{
  "type": "Feature",
  "properties": {
    "iso:country":"DE",
    "sg:address":"Gebeseer Str. 9",
    "sg:city":"Tonna",
    "sg:phone":"+49 36042/74347",
    "sg:postcode":"99958",
    "sg:province":"Th\u00fcringen",
    "wof:name":"Dr. H. Schmidt Tierarzt",
    "wof:placetype":"venue"
},
  "geometry": {"coordinates":[10.7363071442,51.0932846069],"type":"Point"}
}