{
  "type": "Feature",
  "properties": {
    "iso:country":"DE",
    "sg:address":"Oberammergau",
    "sg:city":"Oberammergau",
    "sg:phone":"+49 8822/4012",
    "sg:postcode":"82487",
    "sg:province":"Bayern",
    "wof:name":"Raiffeisenbank Ammertal Eg",
    "wof:placetype":"venue"
},
  "geometry": {"coordinates":[11.05617,47.600368],"type":"Point"}
}