{
  "type": "Feature",
  "properties": {
    "iso:country":"DE",
    "sg:address":"Bayerwaldstra\u00dfe 1",
    "sg:city":"M\u00fcnchen",
    "sg:phone":"+49 89/679030",
    "sg:postcode":"81737",
    "sg:province":"Bayern",
    "wof:name":"Skl - S\u00fcddeutsche Klassenlotterie",
    "wof:placetype":"venue"
},
  "geometry": {"coordinates":[11.6295433044,48.0929031372],"type":"Point"}
}