{
  "type": "Feature",
  "properties": {
    "iso:country":"DE",
    "sg:address":"Palisadenstr. 37a",
    "sg:city":"Berlin",
    "sg:postcode":"10243",
    "sg:province":"Berlin",
    "wof:name":"Dr. Med. Klaus Kunz",
    "wof:placetype":"venue"
},
  "geometry": {"coordinates":[13.436426,52.519032],"type":"Point"}
}