{
  "type": "Feature",
  "properties": {
    "iso:country":"DE",
    "sg:address":"Hauptstr. 92",
    "sg:city":"B\u00fchlertal",
    "sg:phone":"+49 7223/73395",
    "sg:postcode":"77830",
    "sg:province":"Baden-W\u00fcrttemberg",
    "wof:name":"Gemeinde-leihb\u00fccherei",
    "wof:placetype":"venue"
},
  "geometry": {"coordinates":[8.187415,48.686749],"type":"Point"}
}