{
  "type": "Feature",
  "properties": {
    "iso:country":"DE",
    "sg:address":"Kaiserstr. 27",
    "sg:city":"Reutlingen",
    "sg:phone":"+49 7121/45989",
    "sg:postcode":"72764",
    "sg:province":"Baden-W\u00fcrttemberg",
    "wof:name":"P. Giagounidis \u00c4rztebedarf",
    "wof:placetype":"venue"
},
  "geometry": {"coordinates":[9.213473,48.495193],"type":"Point"}
}