{
  "type": "Feature",
  "properties": {
    "iso:country":"DE",
    "sg:address":"Plantagenplatz 6",
    "sg:city":"Werder",
    "sg:phone":"+49 3327/42425",
    "sg:postcode":"14542",
    "sg:province":"Brandenburg",
    "wof:name":"Gutschmidt",
    "wof:placetype":"venue"
},
  "geometry": {"coordinates":[13.356991,53.714333],"type":"Point"}
}