{
  "type": "Feature",
  "properties": {
    "iso:country":"DE",
    "sg:address":"B\u00e4dergasse 7",
    "sg:city":"M\u00f6ssingen",
    "sg:phone":"+49 7473/6414",
    "sg:postcode":"72116",
    "sg:province":"Baden-W\u00fcrttemberg",
    "wof:name":"Ev. Method. Pfarramt",
    "wof:placetype":"venue"
},
  "geometry": {"coordinates":[9.0602407455,48.4078063965],"type":"Point"}
}