{
  "type": "Feature",
  "properties": {
    "iso:country":"DE",
    "sg:address":"H\u00fclser Str. 5 B",
    "sg:city":"Krefeld",
    "sg:phone":"+49 2151/647500",
    "sg:postcode":"47798",
    "sg:province":"Nordrhein-Westfalen",
    "wof:name":"Restaurant Sukhothai",
    "wof:placetype":"venue"
},
  "geometry": {"coordinates":[6.5583930016,51.3407325745],"type":"Point"}
}