{
  "type": "Feature",
  "properties": {
    "iso:country":"DE",
    "sg:address":"Ottostr 24",
    "sg:city":"Karlsruhe",
    "sg:phone":"+49 5152/94240",
    "sg:postcode":"76227",
    "sg:province":"Baden-W\u00fcrttemberg",
    "wof:name":"Dreluso Pharmazeutika Dr. Elten Und Sohn Gmbh",
    "wof:placetype":"venue"
},
  "geometry": {"coordinates":[9.2498941422,52.1681060791],"type":"Point"}
}