{
  "type": "Feature",
  "properties": {
    "iso:country":"DE",
    "sg:address":"G\u00f6ttinger Str. 26",
    "sg:city":"Northeim",
    "sg:phone":"+49 5551/62044",
    "sg:postcode":"37154",
    "sg:province":"Niedersachsen",
    "wof:name":"Udo Anders Bedachungen",
    "wof:placetype":"venue"
},
  "geometry": {"coordinates":[9.99226,51.702877],"type":"Point"}
}