{
  "type": "Feature",
  "properties": {
    "iso:country":"DE",
    "sg:address":"St.-Johannes-Str. 7",
    "sg:city":"Vechelde",
    "sg:postcode":"38159",
    "sg:province":"Niedersachsen",
    "wof:name":"Ev. Pfarramt Gem. Denstorf",
    "wof:placetype":"venue"
},
  "geometry": {"coordinates":[10.412311554,52.2555503845],"type":"Point"}
}