{
  "type": "Feature",
  "properties": {
    "iso:country":"DE",
    "sg:address":"Uelzener Str. 2",
    "sg:city":"Melbeck",
    "sg:phone":"+49 4134/909223",
    "sg:postcode":"21406",
    "sg:province":"Niedersachsen",
    "wof:name":"Jens-peter Fuhrhop Anlageberater",
    "wof:placetype":"venue"
},
  "geometry": {"coordinates":[10.4066257477,53.1812782288],"type":"Point"}
}