{
  "type": "Feature",
  "properties": {
    "iso:country":"DE",
    "sg:address":"Lindenstr. 7",
    "sg:city":"P\u00fcttlingen",
    "sg:phone":"+49 6898/67504",
    "sg:postcode":"66346",
    "sg:province":"Saarland",
    "wof:name":"Hartmut Warken",
    "wof:placetype":"venue"
},
  "geometry": {"coordinates":[6.8934311867,49.2837753296],"type":"Point"}
}