{
  "type": "Feature",
  "properties": {
    "iso:country":"DE",
    "sg:address":"Engelern Mitte",
    "sg:city":"Merzen",
    "sg:postcode":"49586",
    "sg:province":"Niedersachsen",
    "wof:name":"Schlichthorst Wohnheim W. Hasemann Kg",
    "wof:placetype":"venue"
},
  "geometry": {"coordinates":[7.7608351707,52.48985672],"type":"Point"}
}