{
  "type": "Feature",
  "properties": {
    "iso:country":"DE",
    "sg:address":"Dorfstr. 123",
    "sg:city":"Gompertshausen",
    "sg:phone":"+49 36875/69844",
    "sg:postcode":"98663",
    "sg:province":"Th\u00fcringen",
    "wof:name":"Arno Siebensohn",
    "wof:placetype":"venue"
},
  "geometry": {"coordinates":[10.622574,50.298149],"type":"Point"}
}