{
  "type": "Feature",
  "properties": {
    "iso:country":"DE",
    "sg:address":"Kapellenstr. 18",
    "sg:city":"Iserlohn",
    "sg:phone":"+49 2371/41226",
    "sg:postcode":"58640",
    "sg:province":"Nordrhein-Westfalen",
    "wof:name":"Dr. Gisbert Bohle Tierarzt",
    "wof:placetype":"venue"
},
  "geometry": {"coordinates":[7.715610981,51.4164962769],"type":"Point"}
}