{
  "type": "Feature",
  "properties": {
    "iso:country":"DE",
    "sg:address":"Windh\u00e4user Str. 11",
    "sg:city":"Schwalmtal",
    "sg:phone":"+49 6630/919340",
    "sg:postcode":"36318",
    "sg:province":"Hessen",
    "wof:name":"Hans Dieter Mank",
    "wof:placetype":"venue"
},
  "geometry": {"coordinates":[9.2612104416,50.6557655334],"type":"Point"}
}