{
  "type": "Feature",
  "properties": {
    "iso:country":"DE",
    "sg:address":"Bahnhofstr. 21",
    "sg:city":"Strausberg",
    "sg:phone":"+49 3341/421015",
    "sg:postcode":"15344",
    "sg:province":"Brandenburg",
    "wof:name":"Bahnhof-apotheke",
    "wof:placetype":"venue"
},
  "geometry": {"coordinates":[13.841879,52.532021],"type":"Point"}
}