{
  "type": "Feature",
  "properties": {
    "iso:country":"DE",
    "sg:address":"Sophienstr. 57",
    "sg:city":"Karlsruhe",
    "sg:phone":"+49 7203/1476",
    "sg:postcode":"76133",
    "sg:province":"Baden-W\u00fcrttemberg",
    "wof:name":"Herwig Kr\u00e4tschmer Fertigbauelemente E. K.",
    "wof:placetype":"venue"
},
  "geometry": {"coordinates":[8.388329,49.007446],"type":"Point"}
}