{
  "type": "Feature",
  "properties": {
    "iso:country":"DE",
    "sg:address":"Filchnerweg 27",
    "sg:city":"Stuttgart",
    "sg:phone":"+49 711/8262349",
    "sg:postcode":"70439",
    "sg:province":"Baden-W\u00fcrttemberg",
    "wof:name":"H.-j. Ammon",
    "wof:placetype":"venue"
},
  "geometry": {"coordinates":[9.1558828354,48.8414344788],"type":"Point"}
}