{
  "type": "Feature",
  "properties": {
    "iso:country":"DE",
    "sg:address":"Duisburger Str. 368",
    "sg:city":"M\u00fclheim",
    "sg:phone":"+49 208/54048",
    "sg:postcode":"45478",
    "sg:province":"Nordrhein-Westfalen",
    "wof:name":"R. Leske Und W. L\u00f6rks",
    "wof:placetype":"venue"
},
  "geometry": {"coordinates":[6.8329367638,51.4315032959],"type":"Point"}
}