{
  "type": "Feature",
  "properties": {
    "iso:country":"DE",
    "sg:address":"Rheinblickstra\u00dfe 35",
    "sg:city":"Rheinbreitbach",
    "sg:phone":"+49 2224/931059",
    "sg:postcode":"53619",
    "sg:province":"Rheinland-Pfalz",
    "wof:name":"Breitbach Unternehmensberatung",
    "wof:placetype":"venue"
},
  "geometry": {"coordinates":[7.23362,50.623539],"type":"Point"}
}