{
  "type": "Feature",
  "properties": {
    "iso:country":"DE",
    "sg:address":"Ringstr. 8",
    "sg:city":"Mackenrodt",
    "sg:phone":"+49 6781/33481",
    "sg:postcode":"55758",
    "sg:province":"Rheinland-Pfalz",
    "wof:name":"Helmut Alt",
    "wof:placetype":"venue"
},
  "geometry": {"coordinates":[7.2556710243,49.7243232727],"type":"Point"}
}