{
  "type": "Feature",
  "properties": {
    "iso:country":"DE",
    "sg:address":"Westernmauer 38 a",
    "sg:city":"Paderborn",
    "sg:phone":"+49 5251/25343",
    "sg:postcode":"33098",
    "sg:province":"Nordrhein-Westfalen",
    "wof:name":"Maria Arnold",
    "wof:placetype":"venue"
},
  "geometry": {"coordinates":[8.747536,51.718864],"type":"Point"}
}