{
  "type": "Feature",
  "properties": {
    "iso:country":"DE",
    "sg:address":"Buchholzer Str. 32",
    "sg:city":"Berlin",
    "sg:phone":"+49 30/4760950",
    "sg:postcode":"13156",
    "sg:province":"Berlin",
    "wof:name":"Frisch & Faust Tiefbau Gmbh",
    "wof:placetype":"venue"
},
  "geometry": {"coordinates":[13.4159107208,52.5901145935],"type":"Point"}
}