{
  "type": "Feature",
  "properties": {
    "iso:country":"DE",
    "sg:address":"Hauptstr. 9",
    "sg:city":"St. Georgen",
    "sg:phone":"+49 7724/87261",
    "sg:postcode":"78112",
    "sg:province":"Baden-W\u00fcrttemberg",
    "wof:name":"Stadtwerke St. Georgen",
    "wof:placetype":"venue"
},
  "geometry": {"coordinates":[8.332154,48.12571],"type":"Point"}
}