{
  "type": "Feature",
  "properties": {
    "iso:country":"DE",
    "sg:address":"F\u00fcnfh\u00f6festr. 11",
    "sg:city":"Essen",
    "sg:postcode":"45329",
    "sg:province":"Nordrhein-Westfalen",
    "wof:name":"Wega Sicherheits Und Spezial- Armaturen H\u00fcsselmann Ohg",
    "wof:placetype":"venue"
},
  "geometry": {"coordinates":[6.999081,51.493427],"type":"Point"}
}