{
  "type": "Feature",
  "properties": {
    "iso:country":"DE",
    "sg:address":"M\u00f6rikestr. 36",
    "sg:city":"Denkendorf",
    "sg:phone":"+49 711/3464538",
    "sg:postcode":"73770",
    "sg:province":"Baden-W\u00fcrttemberg",
    "wof:name":"Uwe Kupka Anlageberater",
    "wof:placetype":"venue"
},
  "geometry": {"coordinates":[9.3187608719,48.7002677917],"type":"Point"}
}