{
  "type": "Feature",
  "properties": {
    "iso:country":"DE",
    "sg:address":"Calwer Str. 15",
    "sg:city":"Wildberg",
    "sg:phone":"+49 7054/92760",
    "sg:postcode":"72218",
    "sg:province":"Baden-W\u00fcrttemberg",
    "wof:name":"Vorrichtungs- Und Lehrenbau M\u00fcller Gmbh",
    "wof:placetype":"venue"
},
  "geometry": {"coordinates":[8.7445449829,48.6279182434],"type":"Point"}
}