{
  "type": "Feature",
  "properties": {
    "iso:country":"DE",
    "sg:address":"Uhlandstr. 2",
    "sg:city":"H\u00f6chst\u00e4dt",
    "sg:phone":"+49 9074/4811",
    "sg:postcode":"89420",
    "sg:province":"Bayern",
    "wof:name":"Kathi Gr\u00f6mer",
    "wof:placetype":"venue"
},
  "geometry": {"coordinates":[10.5760726929,48.6211395264],"type":"Point"}
}