{
  "type": "Feature",
  "properties": {
    "iso:country":"DE",
    "sg:address":"Br\u00fcckenstr. 3",
    "sg:city":"Ebersburg",
    "sg:phone":"+49 6656/919270",
    "sg:postcode":"36157",
    "sg:province":"Hessen",
    "wof:name":"Okay-kauf",
    "wof:placetype":"venue"
},
  "geometry": {"coordinates":[9.790848732,50.4553184509],"type":"Point"}
}