{
  "type": "Feature",
  "properties": {
    "iso:country":"DE",
    "sg:address":"Klinkebachstr. 21",
    "sg:city":"Magdeburg",
    "sg:phone":"+49 391/6345470",
    "sg:postcode":"39116",
    "sg:province":"Sachsen-Anhalt",
    "wof:name":"Dr. Med. Ulrike Dietrich",
    "wof:placetype":"venue"
},
  "geometry": {"coordinates":[11.58693,52.100151],"type":"Point"}
}