{
  "type": "Feature",
  "properties": {
    "iso:country":"DE",
    "sg:address":"Fichtenweg 23",
    "sg:city":"Hoyerswerda",
    "sg:phone":"+49 3571/417733",
    "sg:postcode":"02977",
    "sg:province":"Sachsen",
    "wof:name":"H.-g. Holder",
    "wof:placetype":"venue"
},
  "geometry": {"coordinates":[14.282155,51.444],"type":"Point"}
}