{
  "type": "Feature",
  "properties": {
    "iso:country":"DE",
    "sg:address":"Stettiner Str. 5",
    "sg:city":"Berlin",
    "sg:phone":"+49 30/4938745",
    "sg:postcode":"13357",
    "sg:province":"Berlin",
    "wof:name":"Ilse Lehmann Masseurin",
    "wof:placetype":"venue"
},
  "geometry": {"coordinates":[13.384888,52.55209],"type":"Point"}
}