{
  "type": "Feature",
  "properties": {
    "iso:country":"DE",
    "sg:address":"Rainerstr. 3",
    "sg:city":"Herne",
    "sg:phone":"+49 2325/33933",
    "sg:postcode":"44651",
    "sg:province":"Nordrhein-Westfalen",
    "wof:name":"Helma Kaiser",
    "wof:placetype":"venue"
},
  "geometry": {"coordinates":[7.178768158,51.513458252],"type":"Point"}
}