{
  "type": "Feature",
  "properties": {
    "iso:country":"DE",
    "sg:address":"An der Hasel 9",
    "sg:city":"Suhl",
    "sg:phone":"+49 3681/303253",
    "sg:postcode":"98527",
    "sg:province":"Th\u00fcringen",
    "wof:name":"D. Heydenbluth Ingenieur",
    "wof:placetype":"venue"
},
  "geometry": {"coordinates":[10.6814985275,50.6026573181],"type":"Point"}
}