{
  "type": "Feature",
  "properties": {
    "iso:country":"DE",
    "sg:address":"Weiherhausweg 2",
    "sg:city":"Winkelhaid",
    "sg:phone":"+49 9187/5728",
    "sg:postcode":"90610",
    "sg:province":"Bayern",
    "wof:name":"Christa Zink Eisenwaren",
    "wof:placetype":"venue"
},
  "geometry": {"coordinates":[11.290774,49.388908],"type":"Point"}
}