{
  "type": "Feature",
  "properties": {
    "iso:country":"DE",
    "sg:address":"Dorfstr. 49",
    "sg:city":"Wulfersdorf",
    "sg:phone":"+49 33963/40207",
    "sg:postcode":"16909",
    "sg:province":"Brandenburg",
    "wof:name":"Kurschat-reisen",
    "wof:placetype":"venue"
},
  "geometry": {"coordinates":[12.4259061813,53.241973877],"type":"Point"}
}