{
  "type": "Feature",
  "properties": {
    "iso:country":"DE",
    "sg:address":"Bocholder Str. 259",
    "sg:city":"Essen",
    "sg:phone":"+49 201/86120",
    "sg:postcode":"45356",
    "sg:province":"Nordrhein-Westfalen",
    "wof:name":"Hans Soldan Druck Gmbh",
    "wof:placetype":"venue"
},
  "geometry": {"coordinates":[6.9742188454,51.475856781],"type":"Point"}
}