{
  "type": "Feature",
  "properties": {
    "iso:country":"DE",
    "sg:address":"Alt-Heiligensee 45 - 47",
    "sg:city":"Berlin",
    "sg:phone":"+49 30/4311909",
    "sg:postcode":"13503",
    "sg:province":"Berlin",
    "wof:name":"Ev. Pfarramt Dorfgemeinde Heiligensee",
    "wof:placetype":"venue"
},
  "geometry": {"coordinates":[13.2140378952,52.6080741882],"type":"Point"}
}