{
  "type": "Feature",
  "properties": {
    "iso:country":"DE",
    "sg:address":"Werderstr. 6",
    "sg:city":"M\u00fcllheim",
    "sg:phone":"+49 7631/10447",
    "sg:postcode":"79379",
    "sg:province":"Baden-W\u00fcrttemberg",
    "wof:name":"Eiscafe Paradieso",
    "wof:placetype":"venue"
},
  "geometry": {"coordinates":[7.62121,47.809238],"type":"Point"}
}