{
  "type": "Feature",
  "properties": {
    "iso:country":"DE",
    "sg:address":"Formerstr. 3",
    "sg:city":"Siegen",
    "sg:phone":"+49 271/72760",
    "sg:postcode":"57076",
    "sg:province":"Nordrhein-Westfalen",
    "wof:name":"Jacques` Wein-depot Wein-einzelhandel Gmbh",
    "wof:placetype":"venue"
},
  "geometry": {"coordinates":[8.0313558578,50.899230957],"type":"Point"}
}