{
  "type": "Feature",
  "properties": {
    "iso:country":"DE",
    "sg:address":"Hergenhahnstr. 8",
    "sg:city":"Wiesbaden",
    "sg:phone":"+49 611/520623",
    "sg:postcode":"65193",
    "sg:province":"Hessen",
    "wof:name":"Susanne Von Rothkirch Praxis F\u00fcr Krankengymnastik",
    "wof:placetype":"venue"
},
  "geometry": {"coordinates":[8.247141,50.088436],"type":"Point"}
}