{
  "type": "Feature",
  "properties": {
    "iso:country":"DE",
    "sg:address":"Im Zollgarten 2",
    "sg:city":"Gundelfingen",
    "sg:phone":"+49 761/584255",
    "sg:postcode":"79194",
    "sg:province":"Baden-W\u00fcrttemberg",
    "wof:name":"Obermattenbad",
    "wof:placetype":"venue"
},
  "geometry": {"coordinates":[7.8703670502,48.0351104736],"type":"Point"}
}