{
  "type": "Feature",
  "properties": {
    "iso:country":"DE",
    "sg:address":"Heidesheimer Str. 79b",
    "sg:city":"Budenheim",
    "sg:phone":"+49 6139/2111",
    "sg:postcode":"55257",
    "sg:province":"Rheinland-Pfalz",
    "wof:name":"Hans Kremer",
    "wof:placetype":"venue"
},
  "geometry": {"coordinates":[8.167596,50.023037],"type":"Point"}
}