{
  "type": "Feature",
  "properties": {
    "iso:country":"DE",
    "sg:address":"Am Heilbrunnen 47",
    "sg:city":"Reutlingen",
    "sg:phone":"+49 7121/94330",
    "sg:postcode":"72766",
    "sg:province":"Baden-W\u00fcrttemberg",
    "wof:name":"Jentz Dienstleitung Im Baugewerbe",
    "wof:placetype":"venue"
},
  "geometry": {"coordinates":[9.21489,48.501209],"type":"Point"}
}