{
  "type": "Feature",
  "properties": {
    "iso:country":"DE",
    "sg:address":"Alois-Schie\u00dfl-Pl 4",
    "sg:city":"Erding",
    "sg:phone":"+49 8122/55212",
    "sg:postcode":"85435",
    "sg:province":"Bayern",
    "wof:name":"Kreis- & Stadtsparkasse",
    "wof:placetype":"venue"
},
  "geometry": {"coordinates":[11.905915,48.30814],"type":"Point"}
}