{
  "type": "Feature",
  "properties": {
    "iso:country":"DE",
    "sg:address":"Tibusstr. 3",
    "sg:city":"M\u00fcnster",
    "sg:phone":"+49 251/45856",
    "sg:postcode":"48143",
    "sg:province":"Nordrhein-Westfalen",
    "wof:name":"Hergem\u00f6ller",
    "wof:placetype":"venue"
},
  "geometry": {"coordinates":[7.6261868477,51.9654541016],"type":"Point"}
}