{
  "type": "Feature",
  "properties": {
    "iso:country":"DE",
    "sg:address":"L\u00fcbecker Str. 87",
    "sg:city":"Magdeburg",
    "sg:phone":"+49 391/2527509",
    "sg:postcode":"39124",
    "sg:province":"Sachsen-Anhalt",
    "wof:name":"Maler-palette Eg",
    "wof:placetype":"venue"
},
  "geometry": {"coordinates":[11.634233,52.163364],"type":"Point"}
}