{
  "type": "Feature",
  "properties": {
    "iso:country":"DE",
    "sg:address":"Am Rotlauber 2",
    "sg:city":"Waldeck",
    "sg:phone":"+49 5623/5236",
    "sg:postcode":"34513",
    "sg:province":"Hessen",
    "wof:name":"Erwin Germeroth Bootsvermietungen",
    "wof:placetype":"venue"
},
  "geometry": {"coordinates":[9.0581617355,51.2076683044],"type":"Point"}
}