{
  "type": "Feature",
  "properties": {
    "iso:country":"DE",
    "sg:address":"Weidenstr. 17",
    "sg:city":"D\u00fclmen",
    "sg:phone":"+49 2594/4782",
    "sg:postcode":"48249",
    "sg:province":"Nordrhein-Westfalen",
    "wof:name":"Siegfried Schultz Ingenieur Und Architekt",
    "wof:placetype":"venue"
},
  "geometry": {"coordinates":[7.295575,51.821941],"type":"Point"}
}