{
  "type": "Feature",
  "properties": {
    "iso:country":"DE",
    "sg:address":"Brook 2",
    "sg:city":"Schmalfeld",
    "sg:phone":"+49 4191/88638",
    "sg:postcode":"24640",
    "sg:province":"Schleswig-Holstein",
    "wof:name":"Jens Instandhaltungs-gmbh",
    "wof:placetype":"venue"
},
  "geometry": {"coordinates":[10.021716,53.871777],"type":"Point"}
}