{
  "type": "Feature",
  "properties": {
    "iso:country":"DE",
    "sg:address":"Stephanusstr. 27",
    "sg:city":"Hannover",
    "sg:phone":"+49 511/451112",
    "sg:postcode":"30449",
    "sg:province":"Niedersachsen",
    "wof:name":"D. Sporkhorst Ergotherapeutsche Praxis",
    "wof:placetype":"venue"
},
  "geometry": {"coordinates":[9.714186,52.369987],"type":"Point"}
}