{
  "type": "Feature",
  "properties": {
    "iso:country":"DE",
    "sg:address":"Am Hirschberg 7a",
    "sg:city":"Neunkirchen",
    "sg:phone":"+49 6821/33290",
    "sg:postcode":"66539",
    "sg:province":"Saarland",
    "wof:name":"Bambach Bau Gmbh",
    "wof:placetype":"venue"
},
  "geometry": {"coordinates":[7.24583,49.323242],"type":"Point"}
}