{
  "type": "Feature",
  "properties": {
    "iso:country":"DE",
    "sg:address":"Kasernstr. 3",
    "sg:city":"Amberg",
    "sg:phone":"+49 9621/12964",
    "sg:postcode":"92224",
    "sg:province":"Bayern",
    "wof:name":"Paul Selig",
    "wof:placetype":"venue"
},
  "geometry": {"coordinates":[11.8581123352,49.4470863342],"type":"Point"}
}