{
  "type": "Feature",
  "properties": {
    "iso:country":"DE",
    "sg:address":"Am Schulberg 3",
    "sg:city":"Seevetal",
    "sg:phone":"+49 4185/792677",
    "sg:postcode":"21220",
    "sg:province":"Niedersachsen",
    "wof:name":"Imex-electronics",
    "wof:placetype":"venue"
},
  "geometry": {"coordinates":[10.0377454758,53.3843307495],"type":"Point"}
}