{
  "type": "Feature",
  "properties": {
    "iso:country":"DE",
    "sg:address":"Sterpersdorf 33",
    "sg:city":"H\u00f6chstadt",
    "sg:phone":"+49 9193/507777",
    "sg:postcode":"91315",
    "sg:province":"Bayern",
    "wof:name":"Pizzeria La Vita E Bella",
    "wof:placetype":"venue"
},
  "geometry": {"coordinates":[10.7704877853,49.6876296997],"type":"Point"}
}