{
  "type": "Feature",
  "properties": {
    "iso:country":"DE",
    "sg:address":"Kreuznacher Str. 31",
    "sg:city":"Stadecken-Elsheim",
    "sg:phone":"+49 6136/2241",
    "sg:postcode":"55271",
    "sg:province":"Rheinland-Pfalz",
    "wof:name":"Cornelia Schlenker",
    "wof:placetype":"venue"
},
  "geometry": {"coordinates":[8.1316995621,49.9096221924],"type":"Point"}
}