{
  "type": "Feature",
  "properties": {
    "iso:country":"DE",
    "sg:address":"Blaihofstr. 59",
    "sg:city":"T\u00fcbingen",
    "sg:phone":"+49 7071/81575",
    "sg:postcode":"72074",
    "sg:province":"Baden-W\u00fcrttemberg",
    "wof:name":"Herbort Single",
    "wof:placetype":"venue"
},
  "geometry": {"coordinates":[9.1120567322,48.551109314],"type":"Point"}
}