{
  "type": "Feature",
  "properties": {
    "iso:country":"DE",
    "sg:address":"Pastorenweg 177",
    "sg:city":"Bremen",
    "sg:postcode":"28237",
    "sg:province":"Bremen",
    "wof:name":"Cantimur Bau Gmbh",
    "wof:placetype":"venue"
},
  "geometry": {"coordinates":[8.7603359222,53.1134147644],"type":"Point"}
}