{
  "type": "Feature",
  "properties": {
    "iso:country":"DE",
    "sg:address":"Saturnweg 35",
    "sg:city":"Hamburg",
    "sg:phone":"+49 40/501141",
    "sg:postcode":"22391",
    "sg:province":"Hamburg",
    "wof:name":"Uwe Meinke",
    "wof:placetype":"venue"
},
  "geometry": {"coordinates":[10.0630512238,53.6299667358],"type":"Point"}
}