{
  "type": "Feature",
  "properties": {
    "iso:country":"DE",
    "sg:address":"Untere Burachstr. 30",
    "sg:city":"Ravensburg",
    "sg:phone":"+49 751/2918",
    "sg:postcode":"88212",
    "sg:province":"Baden-W\u00fcrttemberg",
    "wof:name":"Schaltop Gmbh",
    "wof:placetype":"venue"
},
  "geometry": {"coordinates":[9.6228885651,47.7903594971],"type":"Point"}
}