{
  "type": "Feature",
  "properties": {
    "iso:country":"DE",
    "sg:address":"Ahler Grenzweg 21",
    "sg:city":"B\u00fcnde",
    "sg:phone":"+49 5223/63784",
    "sg:postcode":"32257",
    "sg:province":"Nordrhein-Westfalen",
    "wof:name":"R. Olschewski",
    "wof:placetype":"venue"
},
  "geometry": {"coordinates":[8.5160703659,52.1972084045],"type":"Point"}
}