{
  "type": "Feature",
  "properties": {
    "iso:country":"DE",
    "sg:address":"Triftstr. 78",
    "sg:city":"Berlin",
    "sg:phone":"+49 30/4112118",
    "sg:postcode":"13437",
    "sg:province":"Berlin",
    "wof:name":"Ernst Poppe",
    "wof:placetype":"venue"
},
  "geometry": {"coordinates":[13.320677,52.591984],"type":"Point"}
}