{
  "type": "Feature",
  "properties": {
    "iso:country":"DE",
    "sg:address":"Postfach 11 20",
    "sg:city":"Poing",
    "sg:postcode":"85580",
    "wof:name":"Kathreiner Vertriebsges. Ost Mbh Reichenbach",
    "wof:placetype":"venue"
},
  "geometry": {"coordinates":[11.8154840469,48.1709365845],"type":"Point"}
}