{
  "type": "Feature",
  "properties": {
    "iso:country":"DE",
    "sg:address":"Hermann-L\u00f6ns-Weg 2",
    "sg:city":"Sibbesse",
    "sg:phone":"+49 5065/8295",
    "sg:postcode":"31079",
    "sg:province":"Niedersachsen",
    "wof:name":"Werner Hu\u00dfmann",
    "wof:placetype":"venue"
},
  "geometry": {"coordinates":[9.9070043564,52.0551300049],"type":"Point"}
}