{
  "type": "Feature",
  "properties": {
    "iso:country":"DE",
    "sg:address":"Weinsberger Str. 25",
    "sg:city":"Heilbronn",
    "sg:phone":"+49 7131/163200",
    "sg:postcode":"74072",
    "sg:province":"Baden-W\u00fcrttemberg",
    "wof:name":"Winfried Droll Architekt",
    "wof:placetype":"venue"
},
  "geometry": {"coordinates":[9.224706,49.146309],"type":"Point"}
}