{
  "type": "Feature",
  "properties": {
    "iso:country":"DE",
    "sg:address":"Oldauer Heuweg 66",
    "sg:city":"Hamb\u00fchren",
    "sg:phone":"+49 5084/93020",
    "sg:postcode":"29313",
    "sg:province":"Niedersachsen",
    "wof:name":"Pension Haus Simms",
    "wof:placetype":"venue"
},
  "geometry": {"coordinates":[9.9505023956,52.6292266846],"type":"Point"}
}