{
  "type": "Feature",
  "properties": {
    "iso:country":"DE",
    "sg:address":"Utbremer Str. 67",
    "sg:city":"Bremen",
    "sg:postcode":"28217",
    "sg:province":"Bremen",
    "wof:name":"Nordwestdeutsche Transport- Beteiligungsgesellschaft Mbh",
    "wof:placetype":"venue"
},
  "geometry": {"coordinates":[8.793161,53.093506],"type":"Point"}
}