{
  "type": "Feature",
  "properties": {
    "iso:country":"DE",
    "sg:address":"K\u00fcmmelgasse 6",
    "sg:city":"Klingenthal",
    "sg:phone":"+49 37467/23196",
    "sg:postcode":"08248",
    "sg:province":"Sachsen",
    "wof:name":"Eduard Dingfeld",
    "wof:placetype":"venue"
},
  "geometry": {"coordinates":[12.467115,50.355488],"type":"Point"}
}