{
  "type": "Feature",
  "properties": {
    "iso:country":"DE",
    "sg:address":"Kochstr. 74",
    "sg:city":"Leipzig",
    "sg:postcode":"04275",
    "sg:province":"Sachsen",
    "wof:name":"Hans-joachim Bischoff",
    "wof:placetype":"venue"
},
  "geometry": {"coordinates":[12.371171,51.316051],"type":"Point"}
}