{
  "type": "Feature",
  "properties": {
    "iso:country":"DE",
    "sg:address":"M\u00fchlental 8",
    "sg:city":"Elbingerode",
    "sg:phone":"+49 39454/42245",
    "sg:postcode":"38875",
    "sg:province":"Sachsen-Anhalt",
    "wof:name":"Klaus Lierath",
    "wof:placetype":"venue"
},
  "geometry": {"coordinates":[10.8092565536,51.7691764832],"type":"Point"}
}