{
  "type": "Feature",
  "properties": {
    "iso:country":"DE",
    "sg:address":"Modaustr. 22",
    "sg:city":"Lautertal",
    "sg:phone":"+49 6254/951370",
    "sg:postcode":"64686",
    "sg:province":"Hessen",
    "wof:name":"Redaktion Diabetes Aktuell Hallo-du Auch",
    "wof:placetype":"venue"
},
  "geometry": {"coordinates":[8.7102298737,49.7353858948],"type":"Point"}
}