{
  "type": "Feature",
  "properties": {
    "iso:country":"DE",
    "sg:address":"Zeppelinstr. 13",
    "sg:city":"Erlangen",
    "sg:phone":"+49 9131/24991",
    "sg:postcode":"91052",
    "sg:province":"Bayern",
    "wof:name":"Freiwald Und Scholz Rechtsanw\u00e4lte",
    "wof:placetype":"venue"
},
  "geometry": {"coordinates":[11.0126829147,49.5887184143],"type":"Point"}
}