{
  "type": "Feature",
  "properties": {
    "iso:country":"DE",
    "sg:address":"Seidelstr. 2",
    "sg:city":"G\u00fcstrow",
    "sg:phone":"+49 3843/682671",
    "sg:postcode":"18273",
    "sg:province":"Mecklenburg-Vorpommern",
    "wof:name":"Detlef Peters",
    "wof:placetype":"venue"
},
  "geometry": {"coordinates":[12.1600093842,53.7940788269],"type":"Point"}
}