{
  "type": "Feature",
  "properties": {
    "iso:country":"DE",
    "sg:address":"Ginsterweg 41",
    "sg:city":"Ludwigshafen",
    "sg:phone":"+49 621/552530",
    "sg:postcode":"67067",
    "sg:province":"Rheinland-Pfalz",
    "wof:name":"Lothar Eggert",
    "wof:placetype":"venue"
},
  "geometry": {"coordinates":[8.401389,49.463455],"type":"Point"}
}