{
  "type": "Feature",
  "properties": {
    "iso:country":"DE",
    "sg:address":"T\u00f6ngesgasse 44",
    "sg:city":"Frankfurt",
    "sg:phone":"+49 69/21996343",
    "sg:postcode":"60311",
    "sg:province":"Hessen",
    "wof:name":"Udo Listmann Rechtsanwalt",
    "wof:placetype":"venue"
},
  "geometry": {"coordinates":[8.6824579239,50.113319397],"type":"Point"}
}