{
  "type": "Feature",
  "properties": {
    "iso:country":"DE",
    "sg:address":"Maximilianplatz 33a",
    "sg:city":"Tirschenreuth",
    "sg:phone":"+49 9631/5690",
    "sg:postcode":"95643",
    "sg:province":"Bayern",
    "wof:name":"Brunner",
    "wof:placetype":"venue"
},
  "geometry": {"coordinates":[12.336796,49.877895],"type":"Point"}
}