{
  "type": "Feature",
  "properties": {
    "iso:country":"DE",
    "sg:address":"S\u00e4gem\u00fchlenstr. 50",
    "sg:city":"Leer",
    "sg:phone":"+49 491/4312",
    "sg:postcode":"26789",
    "sg:province":"Niedersachsen",
    "wof:name":"D\u00f6nneweg & Janssen Gmbh & Co. Kg",
    "wof:placetype":"venue"
},
  "geometry": {"coordinates":[7.4615240097,53.2231216431],"type":"Point"}
}