{
  "type": "Feature",
  "properties": {
    "iso:country":"DE",
    "sg:address":"Bregstr. 32",
    "sg:city":"Donaueschingen",
    "sg:postcode":"78166",
    "sg:province":"Baden-W\u00fcrttemberg",
    "wof:name":"E. Schaub Gmbh",
    "wof:placetype":"venue"
},
  "geometry": {"coordinates":[8.499987,47.935528],"type":"Point"}
}