{
  "type": "Feature",
  "properties": {
    "iso:country":"DE",
    "sg:address":"Sandhohl 11",
    "sg:city":"Neupotz",
    "sg:phone":"+49 7272/73974",
    "sg:postcode":"76777",
    "sg:province":"Rheinland-Pfalz",
    "wof:name":"Patricia Gehrlein Masseurin",
    "wof:placetype":"venue"
},
  "geometry": {"coordinates":[8.313753,49.12262],"type":"Point"}
}