{
  "type": "Feature",
  "properties": {
    "iso:country":"DE",
    "sg:address":"Knollenstr. 10 a",
    "sg:city":"Stadtsteinach",
    "sg:phone":"+49 9225/425",
    "sg:postcode":"95346",
    "sg:province":"Bayern",
    "wof:name":"F. Schw\u00e4bisch",
    "wof:placetype":"venue"
},
  "geometry": {"coordinates":[11.502574,50.161709],"type":"Point"}
}