{
  "type": "Feature",
  "properties": {
    "iso:country":"DE",
    "sg:address":"Hauptstr. 43n",
    "sg:city":"Maulburg",
    "sg:phone":"+49 7622/666870",
    "sg:postcode":"79689",
    "sg:province":"Baden-W\u00fcrttemberg",
    "wof:name":"Ursula Frey Und M. M\u00e4nner Architekten",
    "wof:placetype":"venue"
},
  "geometry": {"coordinates":[7.777378,47.64584],"type":"Point"}
}