{
  "type": "Feature",
  "properties": {
    "iso:country":"DE",
    "sg:address":"Pfarrer-W\u00fcst-Str. 4",
    "sg:city":"Eggst\u00e4tt",
    "sg:phone":"+49 8056/1335",
    "sg:postcode":"83125",
    "sg:province":"Bayern",
    "wof:name":"Herbert Hackelsperger Architekt",
    "wof:placetype":"venue"
},
  "geometry": {"coordinates":[12.38212,47.92614],"type":"Point"}
}