{
  "type": "Feature",
  "properties": {
    "iso:country":"DE",
    "sg:address":"Postfach 140",
    "sg:city":"Baltrum",
    "sg:phone":"+49 4939/515",
    "sg:postcode":"26572",
    "sg:province":"Niedersachsen",
    "wof:name":"Heinz-j\u00fcrgen K\u00fcper",
    "wof:placetype":"venue"
},
  "geometry": {"coordinates":[7.3705811501,53.7275314331],"type":"Point"}
}