{
  "type": "Feature",
  "properties": {
    "iso:country":"DE",
    "sg:address":"Augustinerstr. 2",
    "sg:city":"W\u00fcrzburg",
    "sg:phone":"+49 931/17393",
    "sg:postcode":"97070",
    "sg:province":"Bayern",
    "wof:name":"Shoshana Beck",
    "wof:placetype":"venue"
},
  "geometry": {"coordinates":[9.928472,49.79269],"type":"Point"}
}