{
  "type": "Feature",
  "properties": {
    "iso:country":"DE",
    "sg:address":"Richard-Willst\u00e4tter-Allee",
    "sg:city":"Karlsruhe",
    "sg:postcode":"76131",
    "sg:province":"Baden-W\u00fcrttemberg",
    "wof:name":"Instiut F\u00fcr Bodenmechanik U. Felsmechanik Der Uni",
    "wof:placetype":"venue"
},
  "geometry": {"coordinates":[8.411115,49.013748],"type":"Point"}
}