{
  "type": "Feature",
  "properties": {
    "iso:country":"DE",
    "sg:address":"Marktstr. 4",
    "sg:city":"Clenze",
    "sg:phone":"+49 5844/306",
    "sg:postcode":"29459",
    "sg:province":"Niedersachsen",
    "wof:name":"Anneliese Lindeke",
    "wof:placetype":"venue"
},
  "geometry": {"coordinates":[10.957579,52.934673],"type":"Point"}
}