{
  "type": "Feature",
  "properties": {
    "iso:country":"DE",
    "sg:address":"Davidstr. 2",
    "sg:city":"Hamburg",
    "sg:phone":"+49 40/310897",
    "sg:postcode":"20359",
    "sg:province":"Hamburg",
    "wof:name":"Gastst\u00e4tte Abadi",
    "wof:placetype":"venue"
},
  "geometry": {"coordinates":[9.9626379013,53.5472717285],"type":"Point"}
}