{
  "type": "Feature",
  "properties": {
    "iso:country":"DE",
    "sg:address":"In der Berten 16",
    "sg:city":"F\u00fcrth",
    "sg:phone":"+49 911/739359",
    "sg:postcode":"90766",
    "sg:province":"Bayern",
    "wof:name":"Wolfgang Loebermann Architekt",
    "wof:placetype":"venue"
},
  "geometry": {"coordinates":[10.973829,49.473362],"type":"Point"}
}