{
  "type": "Feature",
  "properties": {
    "iso:country":"DE",
    "sg:address":"Bahnhofstr. 34",
    "sg:city":"Worms",
    "sg:phone":"+49 6241/45217",
    "sg:postcode":"67547",
    "sg:province":"Rheinland-Pfalz",
    "wof:name":"M. Schmidt-rossin Dolmetscherin",
    "wof:placetype":"venue"
},
  "geometry": {"coordinates":[8.357599,49.63546],"type":"Point"}
}