{
  "type": "Feature",
  "properties": {
    "iso:country":"DE",
    "sg:address":"Hochstr. 13",
    "sg:city":"Gelsenkirchen",
    "sg:phone":"+49 209/394316",
    "sg:postcode":"45894",
    "sg:province":"Nordrhein-Westfalen",
    "wof:name":"Bathen Backts Gmbh",
    "wof:placetype":"venue"
},
  "geometry": {"coordinates":[7.05395,51.578579],"type":"Point"}
}