{
  "type": "Feature",
  "properties": {
    "iso:country":"DE",
    "sg:address":"Hoher Hof 30",
    "sg:city":"Wendeburg",
    "sg:phone":"+49 5303/1312",
    "sg:postcode":"38176",
    "sg:province":"Niedersachsen",
    "wof:name":"Walter Heine Architekt",
    "wof:placetype":"venue"
},
  "geometry": {"coordinates":[10.395195,52.330582],"type":"Point"}
}