{
  "type": "Feature",
  "properties": {
    "iso:country":"DE",
    "sg:address":"Mauggen 1",
    "sg:city":"Bockhorn",
    "sg:phone":"+49 8122/892359",
    "sg:postcode":"85461",
    "sg:province":"Bayern",
    "wof:name":"Holzbau Anton Schlehhuber Gmbh",
    "wof:placetype":"venue"
},
  "geometry": {"coordinates":[11.98602,48.302559],"type":"Point"}
}