{
  "type": "Feature",
  "properties": {
    "iso:country":"DE",
    "sg:address":"Kahlhorststr. 29",
    "sg:city":"L\u00fcbeck",
    "sg:phone":"+49 451/583130",
    "sg:postcode":"23562",
    "sg:province":"Schleswig-Holstein",
    "wof:name":"A. Wittmer Und K. Schr\u00f6der Steuerberater",
    "wof:placetype":"venue"
},
  "geometry": {"coordinates":[10.6933317184,53.8502311707],"type":"Point"}
}