{
  "type": "Feature",
  "properties": {
    "iso:country":"DE",
    "sg:address":"Eggesiner Str. 9c",
    "sg:city":"Torgelow",
    "sg:phone":"+49 3976/4340",
    "sg:postcode":"17358",
    "sg:province":"Mecklenburg-Vorpommern",
    "wof:name":"Me-le Bautr\u00e4ger Und Sanierungs Verwaltungs Gmbh",
    "wof:placetype":"venue"
},
  "geometry": {"coordinates":[14.0281448364,53.6361160278],"type":"Point"}
}