{
  "type": "Feature",
  "properties": {
    "iso:country":"DE",
    "sg:address":"Kleine Str. 11",
    "sg:city":"Biere",
    "sg:phone":"+49 39297/21028",
    "sg:postcode":"39221",
    "sg:province":"Sachsen-Anhalt",
    "wof:name":"W. Rink",
    "wof:placetype":"venue"
},
  "geometry": {"coordinates":[11.6576776505,51.9730567932],"type":"Point"}
}