{
  "type": "Feature",
  "properties": {
    "iso:country":"DE",
    "sg:address":"Richard-Rentsch-Str. 30",
    "sg:city":"Oederan",
    "sg:phone":"+49 37292/4175",
    "sg:postcode":"09569",
    "sg:province":"Sachsen",
    "wof:name":"Blb Steuerberatungs Gmbh",
    "wof:placetype":"venue"
},
  "geometry": {"coordinates":[13.1804409027,50.8567237854],"type":"Point"}
}