{
  "type": "Feature",
  "properties": {
    "iso:country":"DE",
    "sg:address":"Oderweg 8",
    "sg:city":"G\u00fctersloh",
    "sg:phone":"+49 5241/961333",
    "sg:postcode":"33330",
    "sg:province":"Nordrhein-Westfalen",
    "wof:name":"F. Neumann",
    "wof:placetype":"venue"
},
  "geometry": {"coordinates":[8.3878383636,51.9293670654],"type":"Point"}
}