{
  "type": "Feature",
  "properties": {
    "iso:country":"DE",
    "sg:address":"Flotowstr. 21",
    "sg:city":"M\u00fcnchen",
    "sg:phone":"+49 89/562539",
    "sg:postcode":"80686",
    "sg:province":"Bayern",
    "wof:name":"G. Schoof Kunststoffwaren-eh.",
    "wof:placetype":"venue"
},
  "geometry": {"coordinates":[11.5049905777,48.1336555481],"type":"Point"}
}