{
  "type": "Feature",
  "properties": {
    "iso:country":"DE",
    "sg:address":"Ismaninger Str. 74",
    "sg:city":"M\u00fcnchen",
    "sg:phone":"+49 89/99894316",
    "sg:postcode":"81675",
    "sg:province":"Bayern",
    "wof:name":"Richard Beer",
    "wof:placetype":"venue"
},
  "geometry": {"coordinates":[11.6015405655,48.1433982849],"type":"Point"}
}