{
  "type": "Feature",
  "properties": {
    "iso:country":"DE",
    "sg:address":"Hannoversche Str. 60",
    "sg:city":"Leipzig",
    "sg:phone":"+49 341/9119379",
    "sg:postcode":"04157",
    "sg:province":"Sachsen",
    "wof:name":"Hans-georg Distler",
    "wof:placetype":"venue"
},
  "geometry": {"coordinates":[12.3746547699,51.3749427795],"type":"Point"}
}