{
  "type": "Feature",
  "properties": {
    "iso:country":"DE",
    "sg:address":"Am Erlenbach 3",
    "sg:city":"Neu-Isenburg",
    "sg:phone":"+49 69/33757",
    "sg:postcode":"63263",
    "sg:province":"Hessen",
    "wof:name":"Wolfgang Warnke",
    "wof:placetype":"venue"
},
  "geometry": {"coordinates":[8.701839447,50.0550918579],"type":"Point"}
}