{
  "type": "Feature",
  "properties": {
    "iso:country":"DE",
    "sg:address":"Bahnhofsplatz",
    "sg:city":"Frankfurt",
    "sg:phone":"+49 335/324313",
    "sg:postcode":"15230",
    "sg:province":"Brandenburg",
    "wof:name":"Burger King Gmbh",
    "wof:placetype":"venue"
},
  "geometry": {"coordinates":[14.5466327667,52.3374176025],"type":"Point"}
}