{
  "type": "Feature",
  "properties": {
    "iso:country":"DE",
    "sg:address":"Dachsweg 11",
    "sg:city":"K\u00f6ln",
    "sg:phone":"+49 221/984810",
    "sg:postcode":"51109",
    "sg:province":"Nordrhein-Westfalen",
    "wof:name":"Ingeborg Keil Steuerberaterin",
    "wof:placetype":"venue"
},
  "geometry": {"coordinates":[7.0877981186,50.9425239563],"type":"Point"}
}