{
  "type": "Feature",
  "properties": {
    "iso:country":"DE",
    "sg:address":"Zum Ludwigstal 19",
    "sg:city":"Hattingen",
    "sg:phone":"+49 2324/60275",
    "sg:postcode":"45527",
    "sg:province":"Nordrhein-Westfalen",
    "wof:name":"Sos Computerunterst\u00fctzung Gmbh",
    "wof:placetype":"venue"
},
  "geometry": {"coordinates":[7.2090182304,51.4008598328],"type":"Point"}
}