{
  "type": "Feature",
  "properties": {
    "iso:country":"DE",
    "sg:address":"Karlsruher Str. 25",
    "sg:city":"Dresden",
    "sg:phone":"+49 351/4707266",
    "sg:postcode":"01189",
    "sg:province":"Sachsen",
    "wof:name":"J\u00f6rg Altwein",
    "wof:placetype":"venue"
},
  "geometry": {"coordinates":[13.70217,51.016903],"type":"Point"}
}