{
  "type": "Feature",
  "properties": {
    "iso:country":"DE",
    "sg:address":"Gebr\u00fcder-Lang-Str. 23a",
    "sg:city":"Friedberg",
    "sg:postcode":"61169",
    "sg:province":"Hessen",
    "wof:name":"Ralf Lochm\u00fcller Verm\u00f6gensverwaltung Gmbh",
    "wof:placetype":"venue"
},
  "geometry": {"coordinates":[8.7630157471,50.3380088806],"type":"Point"}
}