{
  "type": "Feature",
  "properties": {
    "iso:country":"DE",
    "sg:address":"Birkenstr. 2",
    "sg:city":"Dotternhausen",
    "sg:phone":"+49 7427/8682",
    "sg:postcode":"72359",
    "sg:province":"Baden-W\u00fcrttemberg",
    "wof:name":"Harald Uttenweiler",
    "wof:placetype":"venue"
},
  "geometry": {"coordinates":[8.787455,48.225948],"type":"Point"}
}