{
  "type": "Feature",
  "properties": {
    "iso:country":"DE",
    "sg:address":"Goethestr. 14",
    "sg:city":"Germering",
    "sg:phone":"+49 89/848890",
    "sg:postcode":"82110",
    "sg:province":"Bayern",
    "wof:name":"Peter Schmidt",
    "wof:placetype":"venue"
},
  "geometry": {"coordinates":[11.3620948792,48.132774353],"type":"Point"}
}