{
  "type": "Feature",
  "properties": {
    "iso:country":"DE",
    "sg:address":"Peiner Str. 6",
    "sg:city":"Vechelde",
    "sg:phone":"+49 5302/7118",
    "sg:postcode":"38159",
    "sg:province":"Niedersachsen",
    "wof:name":"Landb\u00e4ckerei Heinrich Sander Gmbh",
    "wof:placetype":"venue"
},
  "geometry": {"coordinates":[10.371948,52.262108],"type":"Point"}
}