{
  "type": "Feature",
  "properties": {
    "iso:country":"DE",
    "sg:address":"Sch\u00fctzenstr. 1",
    "sg:city":"Geseke",
    "sg:phone":"+49 2942/3400",
    "sg:postcode":"59590",
    "sg:province":"Nordrhein-Westfalen",
    "wof:name":"Viehverkaufsgenossenschaft Geseke Eg",
    "wof:placetype":"venue"
},
  "geometry": {"coordinates":[8.443526,51.635563],"type":"Point"}
}