{
  "type": "Feature",
  "properties": {
    "iso:country":"DE",
    "sg:address":"Kolberger Weg 9",
    "sg:city":"Bad Homburg",
    "sg:postcode":"61348",
    "sg:province":"Hessen",
    "wof:name":"Img Immobilien- Management Gmbh",
    "wof:placetype":"venue"
},
  "geometry": {"coordinates":[8.5969581604,50.2253417969],"type":"Point"}
}