{
  "type": "Feature",
  "properties": {
    "iso:country":"DE",
    "sg:address":"Bachstr. 61/2",
    "sg:city":"Bessenbach",
    "sg:phone":"+49 6095/1680",
    "sg:postcode":"63856",
    "sg:province":"Bayern",
    "wof:name":"R. Schmitt",
    "wof:placetype":"venue"
},
  "geometry": {"coordinates":[9.23941,49.959999],"type":"Point"}
}