{
  "type": "Feature",
  "properties": {
    "iso:country":"DE",
    "sg:address":"Robert-Bosch-Str. 6",
    "sg:city":"Weilerswist",
    "sg:postcode":"53919",
    "sg:province":"Nordrhein-Westfalen",
    "wof:name":"Nor-reg Engineering Gmbh",
    "wof:placetype":"venue"
},
  "geometry": {"coordinates":[6.851892,50.750175],"type":"Point"}
}