{
  "type": "Feature",
  "properties": {
    "iso:country":"DE",
    "sg:address":"Konrad-Adenauer-Ring 13 c",
    "sg:city":"Duisburg",
    "sg:postcode":"47167",
    "sg:province":"Nordrhein-Westfalen",
    "wof:name":"Dentalbau Karl Heinz Leleux",
    "wof:placetype":"venue"
},
  "geometry": {"coordinates":[6.805444,51.493126],"type":"Point"}
}