{
  "type": "Feature",
  "properties": {
    "iso:country":"DE",
    "sg:address":"Oberlangau 5",
    "sg:city":"Oberviechtach",
    "sg:phone":"+49 9677/378",
    "sg:postcode":"92526",
    "sg:province":"Bayern",
    "wof:name":"Karl Brenner Anlageberater",
    "wof:placetype":"venue"
},
  "geometry": {"coordinates":[12.501124382,49.5384178162],"type":"Point"}
}