{
  "type": "Feature",
  "properties": {
    "iso:country":"DE",
    "sg:address":"Lindenstr. 12",
    "sg:city":"Bergwitz",
    "sg:phone":"+49 34921/28586",
    "sg:postcode":"06773",
    "sg:province":"Sachsen-Anhalt",
    "wof:name":"Beratende Gesellschaft F\u00fcr Geotechnische Ingenieur-",
    "wof:placetype":"venue"
},
  "geometry": {"coordinates":[12.5916633606,51.7943115234],"type":"Point"}
}