{
  "type": "Feature",
  "properties": {
    "iso:country":"DE",
    "sg:address":"Hauptstr. 16",
    "sg:city":"Zarrentin",
    "sg:postcode":"19246",
    "sg:province":"Mecklenburg-Vorpommern",
    "wof:name":"Rsp Projekt- Und Entwicklungsgesellschaft Mbh",
    "wof:placetype":"venue"
},
  "geometry": {"coordinates":[10.9159116745,53.5504608154],"type":"Point"}
}