{
  "type": "Feature",
  "properties": {
    "iso:country":"DE",
    "sg:address":"Mariendorfer Damm 338",
    "sg:city":"Berlin",
    "sg:phone":"+49 30/7412433",
    "sg:postcode":"12107",
    "sg:province":"Berlin",
    "wof:name":"Peter T\u00f6lle",
    "wof:placetype":"venue"
},
  "geometry": {"coordinates":[13.3957567215,52.4234695435],"type":"Point"}
}