{
  "type": "Feature",
  "properties": {
    "iso:country":"DE",
    "sg:address":"Mixdorfer Str. 1",
    "sg:city":"M\u00fcllrose",
    "sg:postcode":"15299",
    "sg:province":"Brandenburg",
    "wof:name":"Kofferfabrik M\u00fcllrose Gmbh",
    "wof:placetype":"venue"
},
  "geometry": {"coordinates":[14.41365,52.241707],"type":"Point"}
}