{
  "type": "Feature",
  "properties": {
    "iso:country":"DE",
    "sg:address":"Kornhausgasse 10",
    "sg:city":"Weingarten",
    "sg:phone":"+49 751/54579",
    "sg:postcode":"88250",
    "sg:province":"Baden-W\u00fcrttemberg",
    "wof:name":"Betten-zwerger Gmbh",
    "wof:placetype":"venue"
},
  "geometry": {"coordinates":[9.6409902573,47.8066253662],"type":"Point"}
}