{
  "type": "Feature",
  "properties": {
    "iso:country":"DE",
    "sg:address":"Angerweg 15",
    "sg:city":"Lich",
    "sg:phone":"+49 6404/950463",
    "sg:postcode":"35423",
    "sg:province":"Hessen",
    "wof:name":"G. Daubert",
    "wof:placetype":"venue"
},
  "geometry": {"coordinates":[8.882146,50.540188],"type":"Point"}
}