{
  "type": "Feature",
  "properties": {
    "iso:country":"DE",
    "sg:address":"Lindenplatz 16",
    "sg:city":"Niederdorfelden",
    "sg:phone":"+49 6101/531303",
    "sg:postcode":"61138",
    "sg:province":"Hessen",
    "wof:name":"Horst Weisbecker",
    "wof:placetype":"venue"
},
  "geometry": {"coordinates":[8.79526,50.195332],"type":"Point"}
}