{
  "type": "Feature",
  "properties": {
    "iso:country":"DE",
    "sg:address":"Baderberg 1",
    "sg:city":"Frankenberg",
    "sg:phone":"+49 37206/3665",
    "sg:postcode":"09669",
    "sg:province":"Sachsen",
    "wof:name":"Blumen Freud Und Leid Thomas Erhard",
    "wof:placetype":"venue"
},
  "geometry": {"coordinates":[13.032209,50.911575],"type":"Point"}
}