{
  "type": "Feature",
  "properties": {
    "iso:country":"DE",
    "sg:address":"Weiherstr. 11-1",
    "sg:city":"Villingen-Schwenningen",
    "sg:phone":"+49 7721/33334",
    "sg:postcode":"78050",
    "sg:province":"Baden-W\u00fcrttemberg",
    "wof:name":"Handelsvertretung Wolfgang Steinfeldt",
    "wof:placetype":"venue"
},
  "geometry": {"coordinates":[8.4549398422,48.0520591736],"type":"Point"}
}