{
  "type": "Feature",
  "properties": {
    "iso:country":"DE",
    "sg:address":"Greifstr. 78a",
    "sg:city":"Neubrandenburg",
    "sg:phone":"+49 395/4691817",
    "sg:postcode":"17034",
    "sg:province":"Mecklenburg-Vorpommern",
    "wof:name":"Joker Gastst\u00e4tten Und Automatenbetriebs Gmbh",
    "wof:placetype":"venue"
},
  "geometry": {"coordinates":[13.261133194,53.5637130737],"type":"Point"}
}