{
  "type": "Feature",
  "properties": {
    "iso:country":"DE",
    "sg:address":"S\u00fcdallee 15",
    "sg:city":"M\u00fcnchen-Flughafen",
    "sg:phone":"+49 89/9775453",
    "sg:postcode":"85356",
    "sg:province":"Bayern",
    "wof:name":"Sp\u00f6hrer Und Partner",
    "wof:placetype":"venue"
},
  "geometry": {"coordinates":[11.7748699188,48.379535675],"type":"Point"}
}