{
  "type": "Feature",
  "properties": {
    "iso:country":"DE",
    "sg:address":"Stedinger Str. 126",
    "sg:city":"Oldenburg",
    "sg:postcode":"26135",
    "sg:province":"Niedersachsen",
    "wof:name":"Plan L Wohnbau Gmbh",
    "wof:placetype":"venue"
},
  "geometry": {"coordinates":[8.2350673676,53.1371917725],"type":"Point"}
}