{
  "type": "Feature",
  "properties": {
    "iso:country":"DE",
    "sg:address":"Hubertusstr. 28",
    "sg:city":"Baden-Baden",
    "sg:phone":"+49 7221/60343",
    "sg:postcode":"76532",
    "sg:province":"Baden-W\u00fcrttemberg",
    "wof:name":"Mad Reboux",
    "wof:placetype":"venue"
},
  "geometry": {"coordinates":[8.202666,48.780342],"type":"Point"}
}