{
  "type": "Feature",
  "properties": {
    "iso:country":"DE",
    "sg:address":"Uhlandweg 4",
    "sg:city":"Dornstadt",
    "sg:postcode":"89160",
    "sg:province":"Baden-W\u00fcrttemberg",
    "wof:name":"Blw Bildungs-& Lernwelt",
    "wof:placetype":"venue"
},
  "geometry": {"coordinates":[9.945709,48.468845],"type":"Point"}
}