{
  "type": "Feature",
  "properties": {
    "iso:country":"DE",
    "sg:address":"Richard-Wagner-Str. 37",
    "sg:city":"Berlin",
    "sg:phone":"+49 30/3414537",
    "sg:postcode":"10585",
    "sg:province":"Berlin",
    "wof:name":"Walter Steckel Ohg Nachfolger Holger Koch",
    "wof:placetype":"venue"
},
  "geometry": {"coordinates":[13.3064727783,52.5153846741],"type":"Point"}
}