{
  "type": "Feature",
  "properties": {
    "iso:country":"DE",
    "sg:address":"Eschelsweg 4",
    "sg:city":"Hamburg",
    "sg:phone":"+49 40/3898905",
    "sg:postcode":"22767",
    "sg:province":"Hamburg",
    "wof:name":"G. Dannowski Werbeberater",
    "wof:placetype":"venue"
},
  "geometry": {"coordinates":[9.946398735,53.5497055054],"type":"Point"}
}