{
  "type": "Feature",
  "properties": {
    "iso:country":"DE",
    "sg:address":"Dinklager Weg 2",
    "sg:city":"Stuhr",
    "sg:phone":"+49 421/560552",
    "sg:postcode":"28816",
    "sg:province":"Niedersachsen",
    "wof:name":"Werner Schmiedel",
    "wof:placetype":"venue"
},
  "geometry": {"coordinates":[8.737255,53.032024],"type":"Point"}
}