{
  "type": "Feature",
  "properties": {
    "iso:country":"DE",
    "sg:address":"Schelztorstr. 52-56",
    "sg:city":"Esslingen",
    "sg:phone":"+49 711/3513839",
    "sg:postcode":"73728",
    "sg:province":"Baden-W\u00fcrttemberg",
    "wof:name":"In Vitro Biotec Gmbh Ivb",
    "wof:placetype":"venue"
},
  "geometry": {"coordinates":[9.2968864441,48.7425804138],"type":"Point"}
}