{
  "type": "Feature",
  "properties": {
    "iso:country":"DE",
    "sg:address":"Lingnerallee 3",
    "sg:city":"Dresden",
    "sg:phone":"+49 351/4906844",
    "sg:postcode":"01069",
    "sg:province":"Sachsen",
    "wof:name":"Sv Saxonia Verlag F\u00fcr Recht Wirtschaft Und Kultur Gmbh",
    "wof:placetype":"venue"
},
  "geometry": {"coordinates":[13.7465677261,51.0465812683],"type":"Point"}
}