{
  "type": "Feature",
  "properties": {
    "iso:country":"DE",
    "sg:address":"Brucker Str. 20c",
    "sg:city":"Dachau",
    "sg:phone":"+49 8131/83444",
    "sg:postcode":"85221",
    "sg:province":"Bayern",
    "wof:name":"B\u00f6ck Kg",
    "wof:placetype":"venue"
},
  "geometry": {"coordinates":[11.4288082123,48.2609710693],"type":"Point"}
}