{
  "type": "Feature",
  "properties": {
    "iso:country":"DE",
    "sg:address":"Bollmannsweg 23 a",
    "sg:city":"Oldenburg",
    "sg:postcode":"26125",
    "sg:province":"Niedersachsen",
    "wof:name":"Asim Gmbh",
    "wof:placetype":"venue"
},
  "geometry": {"coordinates":[8.2221670151,53.1875228882],"type":"Point"}
}