{
  "type": "Feature",
  "properties": {
    "iso:country":"DE",
    "sg:address":"Am Barkhof 5",
    "sg:city":"Osterholz-Scharmbeck",
    "sg:phone":"+49 4791",
    "sg:postcode":"27711",
    "sg:province":"Niedersachsen",
    "wof:name":"Dlrg Og Osterholz-scharmbeck",
    "wof:placetype":"venue"
},
  "geometry": {"coordinates":[8.788104,53.225311],"type":"Point"}
}