{
  "type": "Feature",
  "properties": {
    "iso:country":"DE",
    "sg:address":"Nienhagener Weg 1a",
    "sg:city":"Gr\u00f6mitz",
    "sg:phone":"+49 4562/266356",
    "sg:postcode":"23743",
    "sg:province":"Schleswig-Holstein",
    "wof:name":"Prof. J\u00fcrgen Lettner",
    "wof:placetype":"venue"
},
  "geometry": {"coordinates":[10.9537096024,54.1527061462],"type":"Point"}
}