{
  "type": "Feature",
  "properties": {
    "iso:country":"DE",
    "sg:address":"Dorfstr. 13",
    "sg:city":"Neuendorf",
    "sg:postcode":"37339",
    "sg:province":"Th\u00fcringen",
    "wof:name":"Katholisches Pfarramt Neuendorf",
    "wof:placetype":"venue"
},
  "geometry": {"coordinates":[10.1941518784,51.4549636841],"type":"Point"}
}