{
  "type": "Feature",
  "properties": {
    "iso:country":"DE",
    "sg:address":"August-Thyssen-Str. 45",
    "sg:city":"Duisburg",
    "sg:phone":"+49 203/781773",
    "sg:postcode":"47166",
    "sg:province":"Nordrhein-Westfalen",
    "wof:name":"Bergberufsschule Mit Fachoberschule F\u00fcr",
    "wof:placetype":"venue"
},
  "geometry": {"coordinates":[6.7701640129,51.498790741],"type":"Point"}
}