{
  "type": "Feature",
  "properties": {
    "iso:country":"DE",
    "sg:address":"Bienger Str. 6",
    "sg:city":"Ehrenkirchen",
    "sg:phone":"+49 7633/12667",
    "sg:postcode":"79238",
    "sg:province":"Baden-W\u00fcrttemberg",
    "wof:name":"H. Heitzler Immobilienmakler",
    "wof:placetype":"venue"
},
  "geometry": {"coordinates":[7.7155928612,47.930896759],"type":"Point"}
}