{
  "type": "Feature",
  "properties": {
    "iso:country":"DE",
    "sg:address":"Industriestr. 30",
    "sg:city":"Stockach",
    "sg:phone":"+49 7771/4035",
    "sg:postcode":"78333",
    "sg:province":"Baden-W\u00fcrttemberg",
    "wof:name":"Lutz Gmbh",
    "wof:placetype":"venue"
},
  "geometry": {"coordinates":[9.0016403198,47.8424682617],"type":"Point"}
}