{
  "type": "Feature",
  "properties": {
    "iso:country":"DE",
    "sg:address":"Sch\u00f6nbornstr 33",
    "sg:city":"Bruchsal",
    "sg:phone":"+49 7251/387211",
    "sg:postcode":"76646",
    "sg:province":"Baden-W\u00fcrttemberg",
    "wof:name":"Solid System Team Gmbh Niederlassung Holzgerlingen",
    "wof:placetype":"venue"
},
  "geometry": {"coordinates":[8.60104,49.130901],"type":"Point"}
}