{
  "type": "Feature",
  "properties": {
    "iso:country":"DE",
    "sg:address":"Am Heidhagen 4",
    "sg:city":"Seevetal",
    "sg:phone":"+49 4105/669294",
    "sg:postcode":"21217",
    "sg:province":"Niedersachsen",
    "wof:name":"Henry Drewes",
    "wof:placetype":"venue"
},
  "geometry": {"coordinates":[10.058724,53.414646],"type":"Point"}
}