{
  "type": "Feature",
  "properties": {
    "iso:country":"DE",
    "sg:address":"Walther-Rathenau-Str. 18",
    "sg:city":"Zwickau",
    "sg:phone":"+49 375",
    "sg:postcode":"08060",
    "sg:province":"Sachsen",
    "wof:name":"Institut F\u00fcr Schulung Und Beruf (isb)",
    "wof:placetype":"venue"
},
  "geometry": {"coordinates":[12.444194,50.722675],"type":"Point"}
}