{
  "type": "Feature",
  "properties": {
    "iso:country":"DE",
    "sg:address":"Gro\u00dfe Str. 77",
    "sg:city":"Rotenburg",
    "sg:phone":"+49 4261/2965",
    "sg:postcode":"27356",
    "sg:province":"Niedersachsen",
    "wof:name":"Zweirad-sch\u00fctz",
    "wof:placetype":"venue"
},
  "geometry": {"coordinates":[9.40813,53.111454],"type":"Point"}
}