{
  "type": "Feature",
  "properties": {
    "iso:country":"DE",
    "sg:address":"Auf der Eierwiese 26",
    "sg:city":"Gr\u00fcnwald",
    "sg:phone":"+49 89/641450",
    "sg:postcode":"82031",
    "sg:province":"Bayern",
    "wof:name":"Schwesternaltenheim",
    "wof:placetype":"venue"
},
  "geometry": {"coordinates":[11.518349,48.03698],"type":"Point"}
}