{
  "type": "Feature",
  "properties": {
    "iso:country":"DE",
    "sg:address":"Mozartstr. 15",
    "sg:city":"Ansbach",
    "sg:phone":"+49 172",
    "sg:postcode":"91522",
    "sg:province":"Bayern",
    "wof:name":"Bau-und Tragwerksplanung",
    "wof:placetype":"venue"
},
  "geometry": {"coordinates":[10.5859451294,49.3057632446],"type":"Point"}
}