{
  "type": "Feature",
  "properties": {
    "iso:country":"DE",
    "sg:address":"Weserstr. 12",
    "sg:city":"Bodenwerder",
    "sg:phone":"+49 5533/934834",
    "sg:postcode":"37619",
    "sg:province":"Niedersachsen",
    "wof:name":"Restaurant Altes F\u00e4hrhaus",
    "wof:placetype":"venue"
},
  "geometry": {"coordinates":[9.5152702332,51.9755706787],"type":"Point"}
}