{
  "type": "Feature",
  "properties": {
    "iso:country":"DE",
    "sg:address":"Breslauer Str. 2",
    "sg:city":"Mariental",
    "sg:postcode":"38368",
    "sg:province":"Niedersachsen",
    "wof:name":"Dataplan Gmbh",
    "wof:placetype":"venue"
},
  "geometry": {"coordinates":[10.9931735992,52.2883644104],"type":"Point"}
}