{
  "type": "Feature",
  "properties": {
    "iso:country":"DE",
    "sg:address":"Herdecker Str. 9",
    "sg:city":"Hagen",
    "sg:phone":"+49 2331/302232",
    "sg:postcode":"58089",
    "sg:province":"Nordrhein-Westfalen",
    "wof:name":"Maxi Mumm Fitness",
    "wof:placetype":"venue"
},
  "geometry": {"coordinates":[7.4473729134,51.3852767944],"type":"Point"}
}