{
  "type": "Feature",
  "properties": {
    "iso:country":"DE",
    "sg:address":"Gleviner Str. 37",
    "sg:city":"G\u00fcstrow",
    "sg:postcode":"18273",
    "sg:province":"Mecklenburg-Vorpommern",
    "wof:name":"Kohlehandel Schwerin Gmbh",
    "wof:placetype":"venue"
},
  "geometry": {"coordinates":[12.177055,53.792938],"type":"Point"}
}