{
  "type": "Feature",
  "properties": {
    "iso:country":"DE",
    "sg:address":"Hopfenstr. 26",
    "sg:city":"Wuppertal",
    "sg:phone":"+49 202/422976",
    "sg:postcode":"42119",
    "sg:province":"Nordrhein-Westfalen",
    "wof:name":"Hans-peter Kleinschmidt",
    "wof:placetype":"venue"
},
  "geometry": {"coordinates":[7.149984,51.251347],"type":"Point"}
}