{
  "type": "Feature",
  "properties": {
    "iso:country":"DE",
    "sg:address":"Karolingerstr. 48",
    "sg:city":"Nordhausen",
    "sg:phone":"+49 3631/61790",
    "sg:postcode":"99734",
    "sg:province":"Th\u00fcringen",
    "wof:name":"Rolf Pichler",
    "wof:placetype":"venue"
},
  "geometry": {"coordinates":[10.807731,51.506989],"type":"Point"}
}