{
  "type": "Feature",
  "properties": {
    "iso:country":"DE",
    "sg:address":"Borsigstr. 14",
    "sg:city":"Gronau",
    "sg:phone":"+49 4925/6293400",
    "sg:postcode":"48599",
    "sg:province":"Nordrhein-Westfalen",
    "wof:name":"Gronauer Stahlhandel Gmbh",
    "wof:placetype":"venue"
},
  "geometry": {"coordinates":[7.055999,52.209557],"type":"Point"}
}