{
  "type": "Feature",
  "properties": {
    "iso:country":"DE",
    "sg:address":"Neuburger Str. 123",
    "sg:city":"Augsburg",
    "sg:phone":"+49 821/703030",
    "sg:postcode":"86167",
    "sg:province":"Bayern",
    "wof:name":"Gloria Feuer- Und Pflanzenschutz Wilhelm Ohg",
    "wof:placetype":"venue"
},
  "geometry": {"coordinates":[10.916109,48.387375],"type":"Point"}
}