{
  "type": "Feature",
  "properties": {
    "iso:country":"DE",
    "sg:address":"Ebersbacher Str. 3",
    "sg:city":"Friedersdorf",
    "sg:phone":"+49 35872/32758",
    "sg:postcode":"02742",
    "sg:province":"Sachsen",
    "wof:name":"Gerd Grosser",
    "wof:placetype":"venue"
},
  "geometry": {"coordinates":[14.569593,51.019577],"type":"Point"}
}