{
  "type": "Feature",
  "properties": {
    "iso:country":"DE",
    "sg:address":"Elmshorner Str. 28",
    "sg:city":"Pinneberg",
    "sg:phone":"+49 4101/24553",
    "sg:postcode":"25421",
    "sg:province":"Schleswig-Holstein",
    "wof:name":"Orthop\u00e4die-schuhtechnik Peter Wiese",
    "wof:placetype":"venue"
},
  "geometry": {"coordinates":[9.7938318253,53.6661758423],"type":"Point"}
}