{
  "type": "Feature",
  "properties": {
    "iso:country":"DE",
    "sg:address":"Dorfstr. 41",
    "sg:city":"Holzdorf",
    "sg:phone":"+49 4352/2352",
    "sg:postcode":"24364",
    "sg:province":"Schleswig-Holstein",
    "wof:name":"K. Meyer",
    "wof:placetype":"venue"
},
  "geometry": {"coordinates":[9.89566,54.558456],"type":"Point"}
}