{
  "type": "Feature",
  "properties": {
    "iso:country":"DE",
    "sg:address":"Moltkestr. 4",
    "sg:city":"Badenweiler",
    "sg:phone":"+49 7632/75080",
    "sg:postcode":"79410",
    "sg:province":"Baden-W\u00fcrttemberg",
    "wof:name":"Romantik Hotel Zur Sonne",
    "wof:placetype":"venue"
},
  "geometry": {"coordinates":[7.6726198196,47.8011512756],"type":"Point"}
}