{
  "type": "Feature",
  "properties": {
    "iso:country":"DE",
    "sg:address":"K\u00f6nigstr. 9-11",
    "sg:city":"N\u00fcrnberg",
    "sg:phone":"+49 911/24545",
    "sg:postcode":"90402",
    "sg:province":"Bayern",
    "wof:name":"Admiral-palast Gmbh",
    "wof:placetype":"venue"
},
  "geometry": {"coordinates":[11.07794,49.451691],"type":"Point"}
}