{
  "type": "Feature",
  "properties": {
    "iso:country":"DE",
    "sg:address":"Berliner Str. 2",
    "sg:city":"Dabendorf",
    "sg:phone":"+49 3377/334547",
    "sg:postcode":"15806",
    "sg:province":"Brandenburg",
    "wof:name":"H. G\u00fcnther",
    "wof:placetype":"venue"
},
  "geometry": {"coordinates":[13.4506635666,52.2461433411],"type":"Point"}
}