{
  "type": "Feature",
  "properties": {
    "iso:country":"DE",
    "sg:address":"An der Fischeraue 10",
    "sg:city":"Eilenburg",
    "sg:phone":"+49 3423/600410",
    "sg:postcode":"04838",
    "sg:province":"Sachsen",
    "wof:name":"Anton Krebs",
    "wof:placetype":"venue"
},
  "geometry": {"coordinates":[12.6268777847,51.455619812],"type":"Point"}
}