{
  "type": "Feature",
  "properties": {
    "iso:country":"DE",
    "sg:address":"Hadersbach 41",
    "sg:city":"Geiselh\u00f6ring",
    "sg:phone":"+49 9423/1240",
    "sg:postcode":"94333",
    "sg:province":"Bayern",
    "wof:name":"Richard Fuchs",
    "wof:placetype":"venue"
},
  "geometry": {"coordinates":[12.372031,48.792992],"type":"Point"}
}