{
  "type": "Feature",
  "properties": {
    "iso:country":"DE",
    "sg:address":"Schleih\u00f6he 2",
    "sg:city":"Fahrdorf",
    "sg:phone":"+49 4621/33451",
    "sg:postcode":"24857",
    "sg:province":"Schleswig-Holstein",
    "wof:name":"Reinhard K\u00fchn",
    "wof:placetype":"venue"
},
  "geometry": {"coordinates":[9.602347,54.502159],"type":"Point"}
}