{
  "type": "Feature",
  "properties": {
    "iso:country":"DE",
    "sg:address":"Bruno-Walter-Ring 8",
    "sg:city":"M\u00fcnchen",
    "sg:phone":"+49 89/935835",
    "sg:postcode":"81927",
    "sg:province":"Bayern",
    "wof:name":"Franz Bock",
    "wof:placetype":"venue"
},
  "geometry": {"coordinates":[11.6413173676,48.1607093811],"type":"Point"}
}