{
  "type": "Feature",
  "properties": {
    "iso:country":"DE",
    "sg:address":"Zollhofstr. 6",
    "sg:city":"Ludwigshafen",
    "sg:phone":"+49 621/518266",
    "sg:postcode":"67061",
    "sg:province":"Rheinland-Pfalz",
    "wof:name":"Andre Urban",
    "wof:placetype":"venue"
},
  "geometry": {"coordinates":[8.4495725632,49.4835700989],"type":"Point"}
}