{
  "type": "Feature",
  "properties": {
    "iso:country":"DE",
    "sg:address":"Bahrensdorfer Str. 27",
    "sg:city":"Beeskow",
    "sg:phone":"+49 3366/26122",
    "sg:postcode":"15848",
    "sg:province":"Brandenburg",
    "wof:name":"Dr. Med. Klaus Mecklenburg",
    "wof:placetype":"venue"
},
  "geometry": {"coordinates":[14.252647,52.163826],"type":"Point"}
}