{
  "type": "Feature",
  "properties": {
    "iso:country":"DE",
    "sg:address":"Adolfstr. 26",
    "sg:city":"\u00dcbach-Palenberg",
    "sg:phone":"+49 2451/41474",
    "sg:postcode":"52531",
    "sg:province":"Nordrhein-Westfalen",
    "wof:name":"Franz-josef J\u00e4ger",
    "wof:placetype":"venue"
},
  "geometry": {"coordinates":[6.121834,50.915131],"type":"Point"}
}