{
  "type": "Feature",
  "properties": {
    "iso:country":"DE",
    "sg:address":"Rotter Bruch 26b",
    "sg:city":"Aachen",
    "sg:phone":"+49 241/4703610",
    "sg:postcode":"52068",
    "sg:province":"Nordrhein-Westfalen",
    "wof:name":"R. S. A. K\u00e4lte-klima-aachen R. Schreiber & Cie. Gmbh",
    "wof:placetype":"venue"
},
  "geometry": {"coordinates":[6.129098,50.78035],"type":"Point"}
}