{
  "type": "Feature",
  "properties": {
    "iso:country":"DE",
    "sg:address":"Treitschkestr. 2",
    "sg:city":"M\u00fcnchen",
    "sg:phone":"+49 89/1412754",
    "sg:postcode":"80992",
    "sg:province":"Bayern",
    "wof:name":"Josef Gr\u00fcnwald",
    "wof:placetype":"venue"
},
  "geometry": {"coordinates":[11.5213661194,48.1769638062],"type":"Point"}
}