{
  "type": "Feature",
  "properties": {
    "iso:country":"DE",
    "sg:address":"Kamperlingsweg 9 a",
    "sg:city":"Kempen",
    "sg:phone":"+49 2152/52932",
    "sg:postcode":"47906",
    "sg:province":"Nordrhein-Westfalen",
    "wof:name":"Helmut Jentjens Steuerberater",
    "wof:placetype":"venue"
},
  "geometry": {"coordinates":[6.416041851,51.3545303345],"type":"Point"}
}