{
  "type": "Feature",
  "properties": {
    "iso:country":"DE",
    "sg:address":"Hauptstr. 6",
    "sg:city":"Umkirch",
    "sg:phone":"+49 7665/7836",
    "sg:postcode":"79224",
    "sg:province":"Baden-W\u00fcrttemberg",
    "wof:name":"Doris Winsi",
    "wof:placetype":"venue"
},
  "geometry": {"coordinates":[7.761872,48.031914],"type":"Point"}
}