{
  "type": "Feature",
  "properties": {
    "iso:country":"DE",
    "sg:address":"An der Schinderlohe 3",
    "sg:city":"Aystetten",
    "sg:phone":"+49 821/485914",
    "sg:postcode":"86482",
    "sg:province":"Bayern",
    "wof:name":"St\u00f6tter Immobilien Gmbh",
    "wof:placetype":"venue"
},
  "geometry": {"coordinates":[10.7753543854,48.4081077576],"type":"Point"}
}