{
  "type": "Feature",
  "properties": {
    "iso:country":"DE",
    "sg:address":"DieStrasse.92",
    "sg:city":"D\u00fcsseldorf",
    "sg:phone":"+49 4443/33",
    "sg:postcode":"40225",
    "sg:province":"Nordrhein-Westfalen",
    "wof:name":"Webfilmstudio Internetseiten & E-commerce",
    "wof:placetype":"venue"
},
  "geometry": {"coordinates":[6.79283,51.194618],"type":"Point"}
}