{
  "type": "Feature",
  "properties": {
    "iso:country":"DE",
    "sg:address":"Kohlensiepen 94",
    "sg:city":"Witten",
    "sg:phone":"+49 2302/63712",
    "sg:postcode":"58453",
    "sg:province":"Nordrhein-Westfalen",
    "wof:name":"Nikolaus Krieg",
    "wof:placetype":"venue"
},
  "geometry": {"coordinates":[7.3762841225,51.4320602417],"type":"Point"}
}