{
  "type": "Feature",
  "properties": {
    "iso:country":"DE",
    "sg:address":"Rodergasse 12",
    "sg:city":"Idstein",
    "sg:phone":"+49 6126/91556",
    "sg:postcode":"65510",
    "sg:province":"Hessen",
    "wof:name":"Parf\u00fcmerie Sch\u00e4fer Gmbh",
    "wof:placetype":"venue"
},
  "geometry": {"coordinates":[8.268489,50.22097],"type":"Point"}
}