{
  "type": "Feature",
  "properties": {
    "iso:country":"DE",
    "sg:address":"Matthias-Klotz-Str. 39",
    "sg:city":"Mittenwald",
    "sg:phone":"+49 8823/1614",
    "sg:postcode":"82481",
    "sg:province":"Bayern",
    "wof:name":"Hans Heigl",
    "wof:placetype":"venue"
},
  "geometry": {"coordinates":[11.2592411041,47.4433784485],"type":"Point"}
}