{
  "type": "Feature",
  "properties": {
    "iso:country":"DE",
    "sg:address":"Parscheider Str. 31",
    "sg:city":"Asbach",
    "sg:phone":"+49 2683/42429",
    "sg:postcode":"53567",
    "sg:province":"Rheinland-Pfalz",
    "wof:name":"J. Und P. Dahlhausen",
    "wof:placetype":"venue"
},
  "geometry": {"coordinates":[7.43626,50.662224],"type":"Point"}
}