{
  "type": "Feature",
  "properties": {
    "iso:country":"DE",
    "sg:address":"Stolpener Landstr. 2 a",
    "sg:city":"Stolpen",
    "sg:phone":"+49 35973/2230",
    "sg:postcode":"01833",
    "sg:province":"Sachsen",
    "wof:name":"Tecto Gmbh",
    "wof:placetype":"venue"
},
  "geometry": {"coordinates":[14.062031,51.058784],"type":"Point"}
}