{
  "type": "Feature",
  "properties": {
    "iso:country":"DE",
    "sg:address":"Zenelliring 1",
    "sg:city":"Bodenkirchen",
    "sg:phone":"+49 8741/6732",
    "sg:postcode":"84155",
    "sg:province":"Bayern",
    "wof:name":"A. Hofmann",
    "wof:placetype":"venue"
},
  "geometry": {"coordinates":[12.4257249832,48.436920166],"type":"Point"}
}