{
  "type": "Feature",
  "properties": {
    "iso:country":"DE",
    "sg:address":"Splitting Links 156",
    "sg:city":"Papenburg",
    "sg:phone":"+49 4961/76796",
    "sg:postcode":"26871",
    "sg:province":"Niedersachsen",
    "wof:name":"Gerhard Bley",
    "wof:placetype":"venue"
},
  "geometry": {"coordinates":[7.461526,53.048641],"type":"Point"}
}