{
  "type": "Feature",
  "properties": {
    "iso:country":"DE",
    "sg:address":"Chemnitzer Str 13",
    "sg:city":"Stuttgart",
    "sg:phone":"+49 711/7220800",
    "sg:postcode":"70597",
    "sg:province":"Baden-W\u00fcrttemberg",
    "wof:name":"Hochland Kaffee Hunzelmann Gmbh & Co Kg",
    "wof:placetype":"venue"
},
  "geometry": {"coordinates":[9.166325,48.738766],"type":"Point"}
}