{
  "type": "Feature",
  "properties": {
    "iso:country":"DE",
    "sg:address":"Schulze-Delitzsch-Str. 3",
    "sg:city":"Meppen",
    "sg:phone":"+49 5931/13977",
    "sg:postcode":"49716",
    "sg:province":"Niedersachsen",
    "wof:name":"Sch\u00f6ning-fotodesign",
    "wof:placetype":"venue"
},
  "geometry": {"coordinates":[7.295522213,52.6675071716],"type":"Point"}
}