{
  "type": "Feature",
  "properties": {
    "iso:country":"DE",
    "sg:address":"Nibelungenstr. 64",
    "sg:city":"Bensheim",
    "sg:phone":"+49 6251/690291",
    "sg:postcode":"64625",
    "sg:province":"Hessen",
    "wof:name":"Finex Steuerberatungs Gmbh",
    "wof:placetype":"venue"
},
  "geometry": {"coordinates":[8.6323013306,49.6839332581],"type":"Point"}
}