{
  "type": "Feature",
  "properties": {
    "iso:country":"DE",
    "sg:address":"Obertaufkirchen",
    "sg:city":"Obertaufkirchen",
    "sg:phone":"+49 8082/224",
    "sg:postcode":"84419",
    "sg:province":"Bayern",
    "wof:name":"Raiffeisenbank Haag-maitenbeth Eg",
    "wof:placetype":"venue"
},
  "geometry": {"coordinates":[12.281003,48.260662],"type":"Point"}
}