{
  "type": "Feature",
  "properties": {
    "iso:country":"DE",
    "sg:address":"Maximilianstr. 18",
    "sg:city":"Traunstein",
    "sg:phone":"+49 861/986620",
    "sg:postcode":"83278",
    "sg:province":"Bayern",
    "wof:name":"Rt-reisen Gmbh",
    "wof:placetype":"venue"
},
  "geometry": {"coordinates":[12.6447582245,47.8677062988],"type":"Point"}
}