{
  "type": "Feature",
  "properties": {
    "iso:country":"DE",
    "sg:address":"Gerichtsstr. 19",
    "sg:city":"Dortmund",
    "sg:phone":"+49 231/182080",
    "sg:postcode":"44135",
    "sg:province":"Nordrhein-Westfalen",
    "wof:name":"Ulrich Bruhn Steuerberater",
    "wof:placetype":"venue"
},
  "geometry": {"coordinates":[7.4786348343,51.5151596069],"type":"Point"}
}