{
  "type": "Feature",
  "properties": {
    "iso:country":"DE",
    "sg:address":"Marktstr. 2-6",
    "sg:city":"Wiesbaden",
    "sg:phone":"+49 611/376361",
    "sg:postcode":"65183",
    "sg:province":"Hessen",
    "wof:name":"Manfred Knieriem Augenoptiker",
    "wof:placetype":"venue"
},
  "geometry": {"coordinates":[8.2418718338,50.080696106],"type":"Point"}
}