{
  "type": "Feature",
  "properties": {
    "iso:country":"DE",
    "sg:address":"Am Heidebruch 13b",
    "sg:city":"M\u00fcnchen",
    "sg:phone":"+49 89/74029555",
    "sg:postcode":"81375",
    "sg:province":"Bayern",
    "wof:name":"Distek",
    "wof:placetype":"venue"
},
  "geometry": {"coordinates":[11.475271225,48.1177101135],"type":"Point"}
}