{
  "type": "Feature",
  "properties": {
    "iso:country":"DE",
    "sg:address":"Postweg 4",
    "sg:city":"Bad M\u00fcnstereifel",
    "sg:phone":"+49 2253/6191",
    "sg:postcode":"53902",
    "sg:province":"Nordrhein-Westfalen",
    "wof:name":"U. Lemm Architekt",
    "wof:placetype":"venue"
},
  "geometry": {"coordinates":[6.778072,50.510799],"type":"Point"}
}