{
  "type": "Feature",
  "properties": {
    "iso:country":"DE",
    "sg:address":"Breite Str. 24",
    "sg:city":"Aschersleben",
    "sg:postcode":"06449",
    "sg:province":"Sachsen-Anhalt",
    "wof:name":"Dieter Mahnert & Sohn",
    "wof:placetype":"venue"
},
  "geometry": {"coordinates":[11.458726,51.753834],"type":"Point"}
}