{
  "type": "Feature",
  "properties": {
    "iso:country":"DE",
    "sg:address":"Kornbergstr. 42",
    "sg:city":"Lichtenstein",
    "sg:phone":"+49 4971/294287",
    "sg:postcode":"72805",
    "sg:province":"Baden-W\u00fcrttemberg",
    "wof:name":"Raiffeisenbank Holzelfingen Eg",
    "wof:placetype":"venue"
},
  "geometry": {"coordinates":[9.277403,48.423817],"type":"Point"}
}