{
  "type": "Feature",
  "properties": {
    "iso:country":"DE",
    "sg:address":"Heidk\u00f6ttersweg 16",
    "sg:city":"M\u00fcnster",
    "sg:phone":"+49 251/211151",
    "sg:postcode":"48159",
    "sg:province":"Nordrhein-Westfalen",
    "wof:name":"Heino Jagdt Gmbh",
    "wof:placetype":"venue"
},
  "geometry": {"coordinates":[7.5916280746,52.0015068054],"type":"Point"}
}