{
  "type": "Feature",
  "properties": {
    "iso:country":"DE",
    "sg:address":"Anton-Saefkow-Platz 11",
    "sg:city":"Berlin",
    "sg:phone":"+49 30/9751538",
    "sg:postcode":"10369",
    "sg:province":"Berlin",
    "wof:name":"Seifert",
    "wof:placetype":"venue"
},
  "geometry": {"coordinates":[13.470471,52.529491],"type":"Point"}
}