{
  "type": "Feature",
  "properties": {
    "iso:country":"DE",
    "sg:address":"Auf der Lieth 30",
    "sg:city":"G\u00f6ttingen",
    "sg:postcode":"37077",
    "sg:province":"Niedersachsen",
    "wof:name":"Zoo-schmidt",
    "wof:placetype":"venue"
},
  "geometry": {"coordinates":[9.986789,51.56089],"type":"Point"}
}