{
  "type": "Feature",
  "properties": {
    "iso:country":"DE",
    "sg:address":"D\u00fcsterstr. 46",
    "sg:city":"Dortmund",
    "sg:phone":"+49 231/597490",
    "sg:postcode":"44143",
    "sg:province":"Nordrhein-Westfalen",
    "wof:name":"Gastst\u00e4tte Libori-eck",
    "wof:placetype":"venue"
},
  "geometry": {"coordinates":[7.5107321739,51.5134429932],"type":"Point"}
}