{
  "type": "Feature",
  "properties": {
    "iso:country":"DE",
    "sg:address":"Dreibr\u00fcckenstr. 60",
    "sg:city":"Warendorf",
    "sg:phone":"+49 2581/7988",
    "sg:postcode":"48231",
    "sg:province":"Nordrhein-Westfalen",
    "wof:name":"Christel Kissing",
    "wof:placetype":"venue"
},
  "geometry": {"coordinates":[7.993929,51.960144],"type":"Point"}
}