{
  "type": "Feature",
  "properties": {
    "iso:country":"DE",
    "sg:address":"Schusterstr. 26",
    "sg:city":"Waldkirch",
    "sg:postcode":"79183",
    "sg:province":"Baden-W\u00fcrttemberg",
    "wof:name":"Reise-oase E. K.",
    "wof:placetype":"venue"
},
  "geometry": {"coordinates":[7.9624271393,48.0938301086],"type":"Point"}
}