{
  "type": "Feature",
  "properties": {
    "iso:country":"DE",
    "sg:address":"Kalkstr. 27",
    "sg:city":"Leverkusen",
    "sg:phone":"+49 214/74051",
    "sg:postcode":"51377",
    "sg:province":"Nordrhein-Westfalen",
    "wof:name":"Josef Traut Bauunternehmen Gmbh",
    "wof:placetype":"venue"
},
  "geometry": {"coordinates":[7.0241041183,51.0320739746],"type":"Point"}
}