{
  "type": "Feature",
  "properties": {
    "iso:country":"DE",
    "sg:address":"Raboisen 54",
    "sg:city":"Hamburg",
    "sg:phone":"+49 40/30393333",
    "sg:postcode":"20095",
    "sg:province":"Hamburg",
    "wof:name":"Hungerland Und K\u00f6sling Rechtsanw\u00e4lte",
    "wof:placetype":"venue"
},
  "geometry": {"coordinates":[9.9992408752,53.5529747009],"type":"Point"}
}