{
  "type": "Feature",
  "properties": {
    "iso:country":"DE",
    "sg:address":"Zierauer Str. 52",
    "sg:city":"Badel",
    "sg:postcode":"39624",
    "sg:province":"Sachsen-Anhalt",
    "wof:name":"Lager- Und Versorgungswirt- Schaft Badel Gmbh",
    "wof:placetype":"venue"
},
  "geometry": {"coordinates":[11.313617,52.731804],"type":"Point"}
}