{
  "type": "Feature",
  "properties": {
    "iso:country":"DE",
    "sg:address":"Bodenbacher Str. 143",
    "sg:city":"Dresden",
    "sg:phone":"+49 351/259010",
    "sg:postcode":"01277",
    "sg:province":"Sachsen",
    "wof:name":"Dt-steuerberatung",
    "wof:placetype":"venue"
},
  "geometry": {"coordinates":[13.808567,51.02383],"type":"Point"}
}