{
  "type": "Feature",
  "properties": {
    "iso:country":"DE",
    "sg:city":"Krefeld",
    "sg:postcode":"47829",
    "sg:province":"Nordrhein-Westfalen",
    "wof:name":"Cashkit\u00b4s Mediapool",
    "wof:placetype":"venue"
},
  "geometry": {"coordinates":[6.64993,51.353821],"type":"Point"}
}