{
  "type": "Feature",
  "properties": {
    "iso:country":"DE",
    "sg:address":"Karlsplatz 3",
    "sg:city":"Ansbach",
    "sg:phone":"+49 981/2349",
    "sg:postcode":"91522",
    "sg:province":"Bayern",
    "wof:name":"Kath. Beratungsstelle F. Ehe- Und Familienfragen",
    "wof:placetype":"venue"
},
  "geometry": {"coordinates":[10.575348,49.299881],"type":"Point"}
}