{
  "type": "Feature",
  "properties": {
    "iso:country":"DE",
    "sg:address":"Weidensees 90",
    "sg:city":"Betzenstein",
    "sg:phone":"+49 9244/306",
    "sg:postcode":"91282",
    "sg:province":"Bayern",
    "wof:name":"Elisabeth Martin",
    "wof:placetype":"venue"
},
  "geometry": {"coordinates":[11.4468336105,49.710559845],"type":"Point"}
}