{
  "type": "Feature",
  "properties": {
    "iso:country":"DE",
    "sg:address":"Kurzer Hagen 8-9",
    "sg:city":"Hildesheim",
    "sg:phone":"+49 5121/139950",
    "sg:postcode":"31134",
    "sg:province":"Niedersachsen",
    "wof:name":"Medicosma-institut F\u00fcr Medizinische Kosmetik Gmbh",
    "wof:placetype":"venue"
},
  "geometry": {"coordinates":[9.9490242004,52.1530532837],"type":"Point"}
}