{
  "type": "Feature",
  "properties": {
    "iso:country":"DE",
    "sg:address":"Lambertweg 13",
    "sg:city":"Lippstadt",
    "sg:phone":"+49 2941/81152",
    "sg:postcode":"59556",
    "sg:province":"Nordrhein-Westfalen",
    "wof:name":"Hubert L\u00f6ppenberg",
    "wof:placetype":"venue"
},
  "geometry": {"coordinates":[8.330827,51.702835],"type":"Point"}
}