{
  "type": "Feature",
  "properties": {
    "iso:country":"DE",
    "sg:address":"Ringweg 12",
    "sg:city":"Cottbus",
    "sg:phone":"+49 355/823008",
    "sg:postcode":"03053",
    "sg:province":"Brandenburg",
    "wof:name":"D. Zasowk",
    "wof:placetype":"venue"
},
  "geometry": {"coordinates":[14.380962,51.803436],"type":"Point"}
}