{
  "type": "Feature",
  "properties": {
    "iso:country":"DE",
    "sg:address":"Hecksbergstr. 22",
    "sg:city":"Braunfels",
    "sg:phone":"+49 6442/4368",
    "sg:postcode":"35619",
    "sg:province":"Hessen",
    "wof:name":"L. Dietz-unterberger Bildhauerei",
    "wof:placetype":"venue"
},
  "geometry": {"coordinates":[8.381301,50.521156],"type":"Point"}
}