{
  "type": "Feature",
  "properties": {
    "iso:country":"DE",
    "sg:address":"Turmhofstr. 20",
    "sg:city":"K\u00f6ln",
    "sg:phone":"+49 2203/81083",
    "sg:postcode":"51143",
    "sg:province":"Nordrhein-Westfalen",
    "wof:name":"H\u00f6finghoff Hausverwaltung Gmbh",
    "wof:placetype":"venue"
},
  "geometry": {"coordinates":[7.0478339195,50.8711357117],"type":"Point"}
}