{
  "type": "Feature",
  "properties": {
    "iso:country":"DE",
    "sg:address":"Breslauer Str. 19",
    "sg:city":"Hanau",
    "sg:phone":"+49 6181/91870",
    "sg:postcode":"63452",
    "sg:province":"Hessen",
    "wof:name":"Britas Recycling-anlagen Gmbh",
    "wof:placetype":"venue"
},
  "geometry": {"coordinates":[8.925314,50.146805],"type":"Point"}
}