{
  "type": "Feature",
  "properties": {
    "iso:country":"DE",
    "sg:address":"Im Hagenwinkel 51-1",
    "sg:city":"Schramberg",
    "sg:phone":"+49 7422/3604",
    "sg:postcode":"78713",
    "sg:province":"Baden-W\u00fcrttemberg",
    "wof:name":"Viktor Hettich",
    "wof:placetype":"venue"
},
  "geometry": {"coordinates":[8.393235,48.231796],"type":"Point"}
}