{
  "type": "Feature",
  "properties": {
    "iso:country":"DE",
    "sg:address":"Dominikanerweg 62",
    "sg:city":"Vechta",
    "sg:phone":"+49 4441/937212",
    "sg:postcode":"49377",
    "sg:province":"Niedersachsen",
    "wof:name":"Hanne Havertz Drogerie",
    "wof:placetype":"venue"
},
  "geometry": {"coordinates":[8.298573,52.728188],"type":"Point"}
}