{
  "type": "Feature",
  "properties": {
    "iso:country":"DE",
    "sg:address":"Bergstr. 5",
    "sg:city":"Wickerstedt",
    "sg:phone":"+49 3644/562990",
    "sg:postcode":"99510",
    "sg:province":"Th\u00fcringen",
    "wof:name":"Riko Milch Gmbh & Co. Kg",
    "wof:placetype":"venue"
},
  "geometry": {"coordinates":[11.536341,51.057819],"type":"Point"}
}