{
  "type": "Feature",
  "properties": {
    "iso:country":"DE",
    "sg:address":"Hugenottenstr. 98",
    "sg:city":"Friedrichsdorf",
    "sg:phone":"+49 6172/79898",
    "sg:postcode":"61381",
    "sg:province":"Hessen",
    "wof:name":"La Montanara",
    "wof:placetype":"venue"
},
  "geometry": {"coordinates":[8.6420583725,50.2572784424],"type":"Point"}
}