{
  "type": "Feature",
  "properties": {
    "iso:country":"DE",
    "sg:address":"Schwalbenweg 17",
    "sg:city":"K\u00f6nigsbronn",
    "sg:phone":"+49 7328/5011",
    "sg:postcode":"89551",
    "sg:province":"Baden-W\u00fcrttemberg",
    "wof:name":"Ulrich Kn\u00f6ller Ingenieur",
    "wof:placetype":"venue"
},
  "geometry": {"coordinates":[10.1055049896,48.7374076843],"type":"Point"}
}