{
  "type": "Feature",
  "properties": {
    "iso:country":"DE",
    "sg:address":"Schlo\u00dfstr. 6",
    "sg:city":"Jesberg",
    "sg:phone":"+49 6695/448",
    "sg:postcode":"34632",
    "sg:province":"Hessen",
    "wof:name":"Reinhard Becker Metzgerei",
    "wof:placetype":"venue"
},
  "geometry": {"coordinates":[9.1461334229,50.9959411621],"type":"Point"}
}