{
  "type": "Feature",
  "properties": {
    "iso:country":"DE",
    "sg:address":"Droneweg 19",
    "sg:city":"Deersheim",
    "sg:phone":"+49 39421/75568",
    "sg:postcode":"38835",
    "sg:province":"Sachsen-Anhalt",
    "wof:name":"Pbc - Partei Bibeltreuer Christen",
    "wof:placetype":"venue"
},
  "geometry": {"coordinates":[10.7148895264,51.9685745239],"type":"Point"}
}