{
  "type": "Feature",
  "properties": {
    "iso:country":"DE",
    "sg:address":"Nr. 34",
    "sg:city":"Linda",
    "sg:postcode":"06928",
    "sg:province":"Sachsen-Anhalt",
    "wof:name":"Ev. Kirche",
    "wof:placetype":"venue"
},
  "geometry": {"coordinates":[13.0309400558,51.8255004883],"type":"Point"}
}