{
  "type": "Feature",
  "properties": {
    "iso:country":"DE",
    "sg:address":"Wimpassing 24",
    "sg:city":"Vilsbiburg",
    "sg:phone":"+49 8741/924165",
    "sg:postcode":"84137",
    "sg:province":"Bayern",
    "wof:name":"Michael Holzner",
    "wof:placetype":"venue"
},
  "geometry": {"coordinates":[12.386445,48.444954],"type":"Point"}
}