{
  "type": "Feature",
  "properties": {
    "iso:country":"DE",
    "sg:address":"Lamstedter Str. 14",
    "sg:city":"Wingst",
    "sg:phone":"+49 4778/425",
    "sg:postcode":"21789",
    "sg:province":"Niedersachsen",
    "wof:name":"Werner L\u00fchrs",
    "wof:placetype":"venue"
},
  "geometry": {"coordinates":[9.071822,53.706085],"type":"Point"}
}