{
  "type": "Feature",
  "properties": {
    "iso:country":"DE",
    "sg:address":"Lindenstr. 6",
    "sg:city":"Gifhorn",
    "sg:phone":"+49 5371/14125",
    "sg:postcode":"38518",
    "sg:province":"Niedersachsen",
    "wof:name":"Ksh Gmbh",
    "wof:placetype":"venue"
},
  "geometry": {"coordinates":[10.5492897034,52.4849815369],"type":"Point"}
}