{
  "type": "Feature",
  "properties": {
    "iso:country":"DE",
    "sg:address":"Albert-Schweitzer-Str. 134",
    "sg:city":"Saalfeld",
    "sg:phone":"+49 3671/642808",
    "sg:postcode":"07318",
    "sg:province":"Th\u00fcringen",
    "wof:name":"Udo G\u00fcnther",
    "wof:placetype":"venue"
},
  "geometry": {"coordinates":[11.3979549408,50.6530990601],"type":"Point"}
}