{
  "type": "Feature",
  "properties": {
    "iso:country":"DE",
    "sg:address":"Alter Kreuzweg 21",
    "sg:city":"Borken",
    "sg:phone":"+49 2861/600810",
    "sg:postcode":"46325",
    "sg:province":"Nordrhein-Westfalen",
    "wof:name":"Ludwig Steverding Steuerberater",
    "wof:placetype":"venue"
},
  "geometry": {"coordinates":[6.8526687622,51.8350906372],"type":"Point"}
}