{
  "type": "Feature",
  "properties": {
    "iso:country":"DE",
    "sg:address":"Flurstr.",
    "sg:city":"Erding",
    "sg:postcode":"85435",
    "sg:province":"Bayern",
    "wof:name":"Flugb\u00f6rse M\u00fcnchen Am Flughafen Gmbh",
    "wof:placetype":"venue"
},
  "geometry": {"coordinates":[11.8954200745,48.3095588684],"type":"Point"}
}