{
  "type": "Feature",
  "properties": {
    "iso:country":"DE",
    "sg:address":"Ober-Mengelbach 12 a",
    "sg:city":"Wald-Michelbach",
    "sg:phone":"+49 6207/5267",
    "sg:postcode":"69483",
    "sg:province":"Hessen",
    "wof:name":"Horst-peter Vetter",
    "wof:placetype":"venue"
},
  "geometry": {"coordinates":[8.7939586639,49.5828361511],"type":"Point"}
}