{
  "type": "Feature",
  "properties": {
    "iso:country":"DE",
    "sg:address":"K\u00f6nigstr. 100",
    "sg:city":"Dietenheim",
    "sg:phone":"+49 7347/3334",
    "sg:postcode":"89165",
    "sg:province":"Baden-W\u00fcrttemberg",
    "wof:name":"Natterer & Heilig",
    "wof:placetype":"venue"
},
  "geometry": {"coordinates":[10.069399,48.214104],"type":"Point"}
}