{
  "type": "Feature",
  "properties": {
    "iso:country":"DE",
    "sg:address":"Dorfstr. 3",
    "sg:city":"Herrsching",
    "sg:phone":"+49 8152/7781",
    "sg:postcode":"82211",
    "sg:province":"Bayern",
    "wof:name":"M & W",
    "wof:placetype":"venue"
},
  "geometry": {"coordinates":[11.1992073059,48.0155830383],"type":"Point"}
}