{
  "type": "Feature",
  "properties": {
    "iso:country":"DE",
    "sg:address":"Saarstr. 1",
    "sg:city":"Guben",
    "sg:phone":"+49 3561/431504",
    "sg:postcode":"03172",
    "sg:province":"Brandenburg",
    "wof:name":"Hagen Schultke",
    "wof:placetype":"venue"
},
  "geometry": {"coordinates":[14.7020635605,51.9435501099],"type":"Point"}
}