{
  "type": "Feature",
  "properties": {
    "iso:country":"DE",
    "sg:address":"Blumenberger Str 143-145",
    "sg:city":"M\u00f6nchengladbach",
    "sg:phone":"+49 2161/6540",
    "sg:postcode":"41061",
    "sg:province":"Nordrhein-Westfalen",
    "wof:name":"Moenus Textilmaschinen Ag",
    "wof:placetype":"venue"
},
  "geometry": {"coordinates":[6.4219298363,51.1878814697],"type":"Point"}
}