{
  "type": "Feature",
  "properties": {
    "iso:country":"DE",
    "sg:address":"Wittestr. 30 K",
    "sg:city":"Berlin",
    "sg:postcode":"13509",
    "sg:province":"Berlin",
    "wof:name":"Farmakis Immobilien Gmbh",
    "wof:placetype":"venue"
},
  "geometry": {"coordinates":[13.3003,52.590519],"type":"Point"}
}