{
  "type": "Feature",
  "properties": {
    "iso:country":"DE",
    "sg:address":"Sandh\u00e4user Str. 10",
    "sg:city":"Heidelberg",
    "sg:phone":"+49 6221/784496",
    "sg:postcode":"69124",
    "sg:province":"Baden-W\u00fcrttemberg",
    "wof:name":"Sabine J\u00fclg",
    "wof:placetype":"venue"
},
  "geometry": {"coordinates":[8.665077,49.374992],"type":"Point"}
}