{
  "type": "Feature",
  "properties": {
    "iso:country":"DE",
    "sg:address":"Halberst\u00e4dter Str. 49",
    "sg:city":"Harsleben",
    "sg:phone":"+49 3941/443261",
    "sg:postcode":"38829",
    "sg:province":"Sachsen-Anhalt",
    "wof:name":"Barbara L\u00f6hr",
    "wof:placetype":"venue"
},
  "geometry": {"coordinates":[11.093509,51.871746],"type":"Point"}
}