{
  "type": "Feature",
  "properties": {
    "iso:country":"DE",
    "sg:address":"Bottroper Str. 8/1",
    "sg:city":"Stuttgart",
    "sg:postcode":"70376",
    "sg:province":"Baden-W\u00fcrttemberg",
    "wof:name":"Maltech Hebeb\u00fchnen Vermietung Gmbh",
    "wof:placetype":"venue"
},
  "geometry": {"coordinates":[9.2131872177,48.8175849915],"type":"Point"}
}