{
  "type": "Feature",
  "properties": {
    "iso:country":"DE",
    "sg:address":"Bucher Chaussee 1-3",
    "sg:city":"Berlin",
    "sg:phone":"+49 30/94380913",
    "sg:postcode":"13125",
    "sg:province":"Berlin",
    "wof:name":"Karow-apotheke",
    "wof:placetype":"venue"
},
  "geometry": {"coordinates":[13.485764,52.616112],"type":"Point"}
}