{
  "type": "Feature",
  "properties": {
    "iso:country":"DE",
    "sg:address":"Elbuferstr. 144",
    "sg:city":"Neu Darchau",
    "sg:phone":"+49 5853/510",
    "sg:postcode":"29490",
    "sg:province":"Niedersachsen",
    "wof:name":"Gastst\u00e4tte M\u00f6sch",
    "wof:placetype":"venue"
},
  "geometry": {"coordinates":[10.9221935272,53.2183837891],"type":"Point"}
}