{
  "type": "Feature",
  "properties": {
    "iso:country":"DE",
    "sg:address":"Hauptstr. 260",
    "sg:city":"Herne",
    "sg:phone":"+49 2325/77835",
    "sg:postcode":"44649",
    "sg:province":"Nordrhein-Westfalen",
    "wof:name":"Gregor Bruch Rechtsanwalt",
    "wof:placetype":"venue"
},
  "geometry": {"coordinates":[7.1582560539,51.5327453613],"type":"Point"}
}