{
  "type": "Feature",
  "properties": {
    "iso:country":"DE",
    "sg:address":"Meyerhofstr. 18",
    "sg:city":"Beverstedt",
    "sg:phone":"+49 4747/455",
    "sg:postcode":"27616",
    "sg:province":"Niedersachsen",
    "wof:name":"Hinrich Huxoll",
    "wof:placetype":"venue"
},
  "geometry": {"coordinates":[8.8247442245,53.4372024536],"type":"Point"}
}