{
  "type": "Feature",
  "properties": {
    "iso:country":"DE",
    "sg:address":"Rotenburger Str. 11",
    "sg:city":"Zeven",
    "sg:phone":"+49 4281/2290",
    "sg:postcode":"27404",
    "sg:province":"Niedersachsen",
    "wof:name":"Friedrich Martens",
    "wof:placetype":"venue"
},
  "geometry": {"coordinates":[9.280264,53.261173],"type":"Point"}
}