{
  "type": "Feature",
  "properties": {
    "iso:country":"DE",
    "sg:address":"Reisertstr. 12",
    "sg:city":"Hennef",
    "sg:phone":"+49 2242/5600",
    "sg:postcode":"53773",
    "sg:province":"Nordrhein-Westfalen",
    "wof:name":"Reifen Gr\u00e4ff Eine Zweignieder- Lassung Der Euromaster",
    "wof:placetype":"venue"
},
  "geometry": {"coordinates":[7.259849,50.783005],"type":"Point"}
}