{
  "type": "Feature",
  "properties": {
    "iso:country":"DE",
    "sg:address":"Badergasse 11",
    "sg:city":"Leisnig",
    "sg:phone":"+49 34321/12480",
    "sg:postcode":"04703",
    "sg:province":"Sachsen",
    "wof:name":"E. Junghanns",
    "wof:placetype":"venue"
},
  "geometry": {"coordinates":[12.9252920151,51.1607246399],"type":"Point"}
}