{
  "type": "Feature",
  "properties": {
    "iso:country":"DE",
    "sg:address":"Marienstr. 5",
    "sg:city":"Marpingen",
    "sg:phone":"+49 6853/3363",
    "sg:postcode":"66646",
    "sg:province":"Saarland",
    "wof:name":"Bistro",
    "wof:placetype":"venue"
},
  "geometry": {"coordinates":[7.0568699837,49.4513397217],"type":"Point"}
}