{
  "type": "Feature",
  "properties": {
    "iso:country":"DE",
    "sg:address":"Vastersstr. 14",
    "sg:city":"K\u00f6ln",
    "sg:phone":"+49 221/552536",
    "sg:postcode":"50825",
    "sg:province":"Nordrhein-Westfalen",
    "wof:name":"Udo Beyers",
    "wof:placetype":"venue"
},
  "geometry": {"coordinates":[6.9155039787,50.966758728],"type":"Point"}
}