{
  "type": "Feature",
  "properties": {
    "iso:country":"DE",
    "sg:address":"Parkstr. 55",
    "sg:city":"Esslingen",
    "sg:phone":"+49 711/381087",
    "sg:postcode":"73734",
    "sg:province":"Baden-W\u00fcrttemberg",
    "wof:name":"Max D\u00f6ring",
    "wof:placetype":"venue"
},
  "geometry": {"coordinates":[9.2933921814,48.7343635559],"type":"Point"}
}