{
  "type": "Feature",
  "properties": {
    "iso:country":"DE",
    "sg:address":"Gottschalkstr. 36",
    "sg:city":"Kassel",
    "sg:phone":"+49 561/8900430",
    "sg:postcode":"34127",
    "sg:province":"Hessen",
    "wof:name":"Casa Las Tapas",
    "wof:placetype":"venue"
},
  "geometry": {"coordinates":[9.5039949417,51.326423645],"type":"Point"}
}