{
  "type": "Feature",
  "properties": {
    "iso:country":"DE",
    "sg:address":"Weidacher Steige 69",
    "sg:city":"Leinfelden-Echterdingen",
    "sg:phone":"+49 711/7979998",
    "sg:postcode":"70771",
    "sg:province":"Baden-W\u00fcrttemberg",
    "wof:name":"D. \u00d6zdemir",
    "wof:placetype":"venue"
},
  "geometry": {"coordinates":[9.166266,48.669338],"type":"Point"}
}