{
  "type": "Feature",
  "properties": {
    "iso:country":"DE",
    "sg:address":"Moltkestr. 30",
    "sg:city":"G\u00fctersloh",
    "sg:phone":"+49 5241/27070",
    "sg:postcode":"33330",
    "sg:province":"Nordrhein-Westfalen",
    "wof:name":"Louis Augustin Ohg",
    "wof:placetype":"venue"
},
  "geometry": {"coordinates":[8.3764543533,51.91015625],"type":"Point"}
}