{
  "type": "Feature",
  "properties": {
    "iso:country":"DE",
    "sg:address":"Saarlandstr. 102",
    "sg:city":"Dortmund",
    "sg:phone":"+49 231/105880",
    "sg:postcode":"44139",
    "sg:province":"Nordrhein-Westfalen",
    "wof:name":"Shakspeare And Co. Inh. Hartmut Nolte",
    "wof:placetype":"venue"
},
  "geometry": {"coordinates":[7.4628810883,51.5046615601],"type":"Point"}
}