{
  "type": "Feature",
  "properties": {
    "iso:country":"DE",
    "sg:address":"Nalbacher Str. 175",
    "sg:city":"Dillingen",
    "sg:phone":"+49 6831/78299",
    "sg:postcode":"66763",
    "sg:province":"Saarland",
    "wof:name":"Jakob M. Kerber Architekt",
    "wof:placetype":"venue"
},
  "geometry": {"coordinates":[6.770914,49.37421],"type":"Point"}
}