{
  "type": "Feature",
  "properties": {
    "iso:country":"DE",
    "sg:address":"Wassergasse 22",
    "sg:city":"Flonheim",
    "sg:phone":"+49 6734/1648",
    "sg:postcode":"55237",
    "sg:province":"Rheinland-Pfalz",
    "wof:name":"Karl-heinz Dehos",
    "wof:placetype":"venue"
},
  "geometry": {"coordinates":[8.0343933105,49.7867393494],"type":"Point"}
}