{
  "type": "Feature",
  "properties": {
    "iso:country":"DE",
    "sg:address":"Winckelhoferstr. 69",
    "sg:city":"Ehingen",
    "sg:phone":"+49 7391/71801",
    "sg:postcode":"89584",
    "sg:province":"Baden-W\u00fcrttemberg",
    "wof:name":"Real Finanz Hans J\u00fcrgen Ewert",
    "wof:placetype":"venue"
},
  "geometry": {"coordinates":[9.7337617874,48.2818374634],"type":"Point"}
}