{
  "type": "Feature",
  "properties": {
    "iso:country":"DE",
    "sg:address":"Konrad-Adenauer-Allee 40",
    "sg:city":"Regensburg",
    "sg:phone":"+49 941/920670",
    "sg:postcode":"93051",
    "sg:province":"Bayern",
    "wof:name":"Josef Strobel Gmbh",
    "wof:placetype":"venue"
},
  "geometry": {"coordinates":[12.0681724548,48.9966812134],"type":"Point"}
}