{
  "type": "Feature",
  "properties": {
    "iso:country":"DE",
    "sg:address":"Nelkenweg 1",
    "sg:city":"Bietigheim-Bissingen",
    "sg:phone":"+49 7142/65679",
    "sg:postcode":"74321",
    "sg:province":"Baden-W\u00fcrttemberg",
    "wof:name":"Wolfgang H. Sibold G\u00fcnther Schubert",
    "wof:placetype":"venue"
},
  "geometry": {"coordinates":[9.1452560425,48.9480857849],"type":"Point"}
}