{
  "type": "Feature",
  "properties": {
    "iso:country":"DE",
    "sg:address":"Sonnenhalde 11",
    "sg:city":"Glatten",
    "sg:phone":"+49 7443/6868",
    "sg:postcode":"72293",
    "sg:province":"Baden-W\u00fcrttemberg",
    "wof:name":"Fritz Weigand",
    "wof:placetype":"venue"
},
  "geometry": {"coordinates":[8.5068817139,48.4432563782],"type":"Point"}
}