{
  "type": "Feature",
  "properties": {
    "iso:country":"DE",
    "sg:address":"Alte Jakobstr. 148",
    "sg:city":"Berlin",
    "sg:phone":"+49 30/2537140",
    "sg:postcode":"10969",
    "sg:province":"Berlin",
    "wof:name":"Hetzel Tor-westen & Partner Ingenieurgesellschaft Kg",
    "wof:placetype":"venue"
},
  "geometry": {"coordinates":[13.3966150284,52.4998664856],"type":"Point"}
}