{
  "type": "Feature",
  "properties": {
    "iso:country":"DE",
    "sg:address":"Alpenblickstr. 20",
    "sg:city":"Ebenhausen",
    "sg:phone":"+49 8178/3773",
    "sg:postcode":"82067",
    "sg:province":"Bayern",
    "wof:name":"R. Gr\u00fcbl Bildhauer",
    "wof:placetype":"venue"
},
  "geometry": {"coordinates":[11.447912,47.978134],"type":"Point"}
}