{
  "type": "Feature",
  "properties": {
    "iso:country":"DE",
    "sg:address":"Obere Gie\u00dfwiesen 17",
    "sg:city":"Hilzingen",
    "sg:phone":"+49 4977/3187250",
    "sg:postcode":"78247",
    "sg:province":"Baden-W\u00fcrttemberg",
    "wof:name":"Anrotec Tec Ohg",
    "wof:placetype":"venue"
},
  "geometry": {"coordinates":[8.785907,47.76136],"type":"Point"}
}