{
  "type": "Feature",
  "properties": {
    "iso:country":"DE",
    "sg:address":"Gr\u00fcninger Weg 26",
    "sg:city":"Pohlheim",
    "sg:phone":"+49 6404/8040",
    "sg:postcode":"35415",
    "sg:province":"Hessen",
    "wof:name":"Limes Werkstatt",
    "wof:placetype":"venue"
},
  "geometry": {"coordinates":[8.748262,50.530876],"type":"Point"}
}