{
  "type": "Feature",
  "properties": {
    "iso:country":"DE",
    "sg:address":"Hauptstr. 113-115",
    "sg:city":"Lobbach",
    "sg:phone":"+49 6226/95140",
    "sg:postcode":"74931",
    "sg:province":"Baden-W\u00fcrttemberg",
    "wof:name":"Karl Helmut Kre\u00df",
    "wof:placetype":"venue"
},
  "geometry": {"coordinates":[8.8955593109,49.3736114502],"type":"Point"}
}