{
  "type": "Feature",
  "properties": {
    "iso:country":"DE",
    "sg:address":"Toblacher Str 1",
    "sg:city":"Aichwald",
    "sg:phone":"+49 711/3108440",
    "sg:postcode":"73773",
    "sg:province":"Baden-W\u00fcrttemberg",
    "wof:name":"Presentationen Luzia Schneider",
    "wof:placetype":"venue"
},
  "geometry": {"coordinates":[9.393451,48.748131],"type":"Point"}
}