{
  "type": "Feature",
  "properties": {
    "iso:country":"DE",
    "sg:address":"Karl-Marx-Str. 73",
    "sg:city":"Neuruppin",
    "sg:phone":"+49 3391/3616",
    "sg:postcode":"16816",
    "sg:province":"Brandenburg",
    "wof:name":"W.-hartmut Knoblich",
    "wof:placetype":"venue"
},
  "geometry": {"coordinates":[12.8037290573,52.9234428406],"type":"Point"}
}