{
  "type": "Feature",
  "properties": {
    "iso:country":"DE",
    "sg:address":"Hubertusweg 3",
    "sg:city":"L\u00fcbben",
    "sg:phone":"+49 3546/186360",
    "sg:postcode":"15907",
    "sg:province":"Brandenburg",
    "wof:name":"F. Behrends Ingenieur",
    "wof:placetype":"venue"
},
  "geometry": {"coordinates":[13.8735151291,51.9383773804],"type":"Point"}
}