{
  "type": "Feature",
  "properties": {
    "iso:country":"DE",
    "sg:address":"Behrgasse 2",
    "sg:city":"Elsdorf",
    "sg:phone":"+49 2274/905743",
    "sg:postcode":"50189",
    "sg:province":"Nordrhein-Westfalen",
    "wof:name":"3 S Systemtechnik Gmbh",
    "wof:placetype":"venue"
},
  "geometry": {"coordinates":[6.566905,50.937363],"type":"Point"}
}