{
  "type": "Feature",
  "properties": {
    "iso:country":"DE",
    "sg:address":"Berggasse 11",
    "sg:city":"M\u00f6ssingen",
    "sg:phone":"+49 7473/940110",
    "sg:postcode":"72116",
    "sg:province":"Baden-W\u00fcrttemberg",
    "wof:name":"H. Metzger",
    "wof:placetype":"venue"
},
  "geometry": {"coordinates":[9.0582818985,48.4045066833],"type":"Point"}
}