{
  "type": "Feature",
  "properties": {
    "iso:country":"DE",
    "sg:address":"Etzwiesenstr. 21",
    "sg:city":"Rottenburg",
    "sg:phone":"+49 7457/7427",
    "sg:postcode":"72108",
    "sg:province":"Baden-W\u00fcrttemberg",
    "wof:name":"Manfred Hagmann Ingenieur",
    "wof:placetype":"venue"
},
  "geometry": {"coordinates":[8.8753633499,48.5283699036],"type":"Point"}
}