{
  "type": "Feature",
  "properties": {
    "iso:country":"DE",
    "sg:address":"Marktredwitzer Str. 1",
    "sg:city":"Pechbrunn",
    "sg:postcode":"95701",
    "sg:province":"Bayern",
    "wof:name":"J. P. K\u00fcsperth Fertigungs- Technik Gmbh & Co. Kg",
    "wof:placetype":"venue"
},
  "geometry": {"coordinates":[12.1488132477,49.9740219116],"type":"Point"}
}