{
  "type": "Feature",
  "properties": {
    "iso:country":"DE",
    "sg:address":"Waldstr. 22",
    "sg:city":"Bad Freienwalde",
    "sg:phone":"+49 3344/3521",
    "sg:postcode":"16259",
    "sg:province":"Brandenburg",
    "wof:name":"Dr. Med. Markus Markiewitz",
    "wof:placetype":"venue"
},
  "geometry": {"coordinates":[14.0427513123,52.7764396667],"type":"Point"}
}