{
  "type": "Feature",
  "properties": {
    "iso:country":"DE",
    "sg:address":"Im Hinteren Zeil 29",
    "sg:city":"Pforzheim",
    "sg:postcode":"75179",
    "sg:province":"Baden-W\u00fcrttemberg",
    "wof:name":"Wbr Rohr- Und Bau- Elemente Gmbh",
    "wof:placetype":"venue"
},
  "geometry": {"coordinates":[8.6583099365,48.8837471008],"type":"Point"}
}