{
  "type": "Feature",
  "properties": {
    "iso:country":"DE",
    "sg:address":"Graf-Zeppelin-Str. 116",
    "sg:city":"Essen",
    "sg:phone":"+49 2054/84481",
    "sg:postcode":"45219",
    "sg:province":"Nordrhein-Westfalen",
    "wof:name":"D.i.h. Bauentwicklung Und Bauprojektierung Gmbh",
    "wof:placetype":"venue"
},
  "geometry": {"coordinates":[6.935356,51.370247],"type":"Point"}
}