{
  "type": "Feature",
  "properties": {
    "iso:country":"DE",
    "sg:address":"Tannenweg 12",
    "sg:city":"Frankfurt",
    "sg:phone":"+49 69/5073093",
    "sg:postcode":"60437",
    "sg:province":"Hessen",
    "wof:name":"M. Wei\u00df Immobilienmakler",
    "wof:placetype":"venue"
},
  "geometry": {"coordinates":[8.6689548492,50.2032318115],"type":"Point"}
}