{
  "type": "Feature",
  "properties": {
    "iso:country":"DE",
    "sg:address":"Spenglerstr. 25",
    "sg:city":"Dreieich",
    "sg:phone":"+49 6103/61901",
    "sg:postcode":"63303",
    "sg:province":"Hessen",
    "wof:name":"W. Rabold",
    "wof:placetype":"venue"
},
  "geometry": {"coordinates":[8.6916666031,50.01587677],"type":"Point"}
}