{
  "type": "Feature",
  "properties": {
    "iso:country":"DE",
    "sg:address":"M\u00fchlstr. 5",
    "sg:city":"Raschau",
    "sg:postcode":"08352",
    "sg:province":"Sachsen",
    "wof:name":"C. S\u00fcss",
    "wof:placetype":"venue"
},
  "geometry": {"coordinates":[12.8312692642,50.5325317383],"type":"Point"}
}