{
  "type": "Feature",
  "properties": {
    "iso:country":"DE",
    "sg:city":"Einbeck",
    "sg:postcode":"37554",
    "sg:province":"Niedersachsen",
    "wof:name":"F. Hildebrandt Kommunikationselektronik",
    "wof:placetype":"venue"
},
  "geometry": {"coordinates":[9.86731,51.816479],"type":"Point"}
}