{
  "type": "Feature",
  "properties": {
    "iso:country":"DE",
    "sg:address":"Bahnhofstr. 72",
    "sg:city":"Neuenb\u00fcrg",
    "sg:phone":"+49 7082/92450",
    "sg:postcode":"75305",
    "sg:province":"Baden-W\u00fcrttemberg",
    "wof:name":"Nuding Verwaltungs-gmbh",
    "wof:placetype":"venue"
},
  "geometry": {"coordinates":[8.593778,48.849804],"type":"Point"}
}