{
  "type": "Feature",
  "properties": {
    "iso:country":"DE",
    "sg:address":"Teltower Str. 9",
    "sg:city":"Berlin",
    "sg:phone":"+49 30/3325491",
    "sg:postcode":"13597",
    "sg:province":"Berlin",
    "wof:name":"G\u00fcnter Gandow Gastst\u00e4tten Gmbh",
    "wof:placetype":"venue"
},
  "geometry": {"coordinates":[13.2172641754,52.5262145996],"type":"Point"}
}