{
  "type": "Feature",
  "properties": {
    "iso:country":"DE",
    "sg:address":"Angerstr. 2",
    "sg:city":"Ratingen",
    "sg:phone":"+49 2102/8774",
    "sg:postcode":"40878",
    "sg:province":"Nordrhein-Westfalen",
    "wof:name":"Seniorenanlage Marienhof",
    "wof:placetype":"venue"
},
  "geometry": {"coordinates":[6.853016,51.299187],"type":"Point"}
}