{
  "type": "Feature",
  "properties": {
    "iso:country":"DE",
    "sg:address":"Oranienburger Str. 43",
    "sg:city":"Berlin",
    "sg:phone":"+49 30/4927126",
    "sg:postcode":"13437",
    "sg:province":"Berlin",
    "wof:name":"Dr. Zoran Zimonjic",
    "wof:placetype":"venue"
},
  "geometry": {"coordinates":[13.3354387283,52.5857543945],"type":"Point"}
}