{
  "type": "Feature",
  "properties": {
    "iso:country":"DE",
    "sg:address":"Griesbadgasse 28",
    "sg:city":"Ulm",
    "sg:phone":"+49 731/22394",
    "sg:postcode":"89073",
    "sg:province":"Baden-W\u00fcrttemberg",
    "wof:name":"Gertrud Kern Massagepraxis",
    "wof:placetype":"venue"
},
  "geometry": {"coordinates":[9.999807,48.401173],"type":"Point"}
}