{
  "type": "Feature",
  "properties": {
    "iso:country":"DE",
    "sg:address":"Freiherr-von-Wallbrunn-Str. 13",
    "sg:city":"Partenheim",
    "sg:phone":"+49 6732/960070",
    "sg:postcode":"55288",
    "sg:province":"Rheinland-Pfalz",
    "wof:name":"Concept 2000 P. Cech",
    "wof:placetype":"venue"
},
  "geometry": {"coordinates":[8.0799398422,49.8867797852],"type":"Point"}
}