{
  "type": "Feature",
  "properties": {
    "iso:country":"DE",
    "sg:address":"Murhardstr. 4",
    "sg:city":"Kassel",
    "sg:phone":"+49 561/15388",
    "sg:postcode":"34119",
    "sg:province":"Hessen",
    "wof:name":"Dr. Med. Wolfgang Clau\u00df Arzt F\u00fcr Chirotherapie",
    "wof:placetype":"venue"
},
  "geometry": {"coordinates":[9.4750404358,51.3153419495],"type":"Point"}
}