{
  "type": "Feature",
  "properties": {
    "iso:country":"DE",
    "sg:address":"Vogelsbergstr. 212",
    "sg:city":"Schotten",
    "sg:phone":"+49 6044/60090",
    "sg:postcode":"63679",
    "sg:province":"Hessen",
    "wof:name":"Gemeinn. Schottener Reha- Und Betreuungseinricht. Der",
    "wof:placetype":"venue"
},
  "geometry": {"coordinates":[9.1356973648,50.5083885193],"type":"Point"}
}