{
  "type": "Feature",
  "properties": {
    "iso:country":"DE",
    "sg:address":"Josefstr. 56 a",
    "sg:city":"Baesweiler",
    "sg:phone":"+49 2401/97670",
    "sg:postcode":"52499",
    "sg:province":"Nordrhein-Westfalen",
    "wof:name":"Immobilien-palm",
    "wof:placetype":"venue"
},
  "geometry": {"coordinates":[6.1917219162,50.9278869629],"type":"Point"}
}