{
  "type": "Feature",
  "properties": {
    "iso:country":"DE",
    "sg:address":"Am Wiesengrund 7",
    "sg:city":"Idstein",
    "sg:phone":"+49 6126/990930",
    "sg:postcode":"65510",
    "sg:province":"Hessen",
    "wof:name":"Sch\u00f6n Und Pahnke",
    "wof:placetype":"venue"
},
  "geometry": {"coordinates":[8.242288,50.212734],"type":"Point"}
}