{
  "type": "Feature",
  "properties": {
    "iso:country":"DE",
    "sg:address":"Gewerbering 18",
    "sg:city":"R\u00f6ttenbach",
    "sg:phone":"+49 9195",
    "sg:postcode":"91341",
    "sg:province":"Bayern",
    "wof:name":"Davinci Computer",
    "wof:placetype":"venue"
},
  "geometry": {"coordinates":[10.914485,49.65855],"type":"Point"}
}