{
  "type": "Feature",
  "properties": {
    "iso:country":"DE",
    "sg:address":"Wacholderweg 10",
    "sg:city":"Kaiserslautern",
    "sg:phone":"+49 631/3504900",
    "sg:postcode":"67661",
    "sg:province":"Rheinland-Pfalz",
    "wof:name":"Andreas Theis Ingenieur",
    "wof:placetype":"venue"
},
  "geometry": {"coordinates":[7.6937861443,49.417137146],"type":"Point"}
}