{
  "type": "Feature",
  "properties": {
    "iso:country":"DE",
    "sg:address":"Parkstr. 6",
    "sg:city":"Stade",
    "sg:postcode":"21682",
    "sg:province":"Niedersachsen",
    "wof:name":"Elkes Tanzschule",
    "wof:placetype":"venue"
},
  "geometry": {"coordinates":[9.4743995667,53.605506897],"type":"Point"}
}