{
  "type": "Feature",
  "properties": {
    "iso:country":"DE",
    "sg:address":"Am Kieselhumes 33",
    "sg:city":"Saarbr\u00fccken",
    "sg:phone":"+49 681/968100",
    "sg:postcode":"66123",
    "sg:province":"Saarland",
    "wof:name":"Bernd Thewalt",
    "wof:placetype":"venue"
},
  "geometry": {"coordinates":[7.0207772255,49.2327728271],"type":"Point"}
}