{
  "type": "Feature",
  "properties": {
    "iso:country":"DE",
    "sg:address":"Kohlbuckweg 11",
    "sg:city":"N\u00fcrnberg",
    "sg:phone":"+49 911/599441",
    "sg:postcode":"90491",
    "sg:province":"Bayern",
    "wof:name":"Cawi Concept Gmbh",
    "wof:placetype":"venue"
},
  "geometry": {"coordinates":[11.1399011612,49.4734344482],"type":"Point"}
}