{
  "type": "Feature",
  "properties": {
    "iso:country":"DE",
    "sg:address":"Rosenstr. 3",
    "sg:city":"Haar",
    "sg:phone":"+49 89/463972",
    "sg:postcode":"85540",
    "sg:province":"Bayern",
    "wof:name":"Anneliese Uhlig Steuerberater",
    "wof:placetype":"venue"
},
  "geometry": {"coordinates":[11.7386760712,48.1074562073],"type":"Point"}
}