{
  "type": "Feature",
  "properties": {
    "iso:country":"DE",
    "sg:address":"Schmelzh\u00fcttenstr. 15",
    "sg:city":"Gera",
    "sg:phone":"+49 365/8326289",
    "sg:postcode":"07545",
    "sg:province":"Th\u00fcringen",
    "wof:name":"Redaktion Dpa-gera",
    "wof:placetype":"venue"
},
  "geometry": {"coordinates":[12.080696106,50.872543335],"type":"Point"}
}