{
  "type": "Feature",
  "properties": {
    "iso:country":"DE",
    "sg:address":"Hainbuchenring 10",
    "sg:city":"Rostock",
    "sg:phone":"+49 381/609820",
    "sg:postcode":"18147",
    "sg:province":"Mecklenburg-Vorpommern",
    "wof:name":"Neptun Engineering Gmbh",
    "wof:placetype":"venue"
},
  "geometry": {"coordinates":[12.1543312073,54.1195259094],"type":"Point"}
}