{
  "type": "Feature",
  "properties": {
    "iso:country":"DE",
    "sg:address":"Eichenweg 27",
    "sg:city":"Sonnefeld",
    "sg:postcode":"96242",
    "sg:province":"Bayern",
    "wof:name":"Osterroth",
    "wof:placetype":"venue"
},
  "geometry": {"coordinates":[11.1305885315,50.2299919128],"type":"Point"}
}