{
  "type": "Feature",
  "properties": {
    "iso:country":"DE",
    "sg:address":"Hauptstr 5",
    "sg:city":"Heckenbach",
    "sg:phone":"+49 2646/94130",
    "sg:postcode":"53506",
    "sg:province":"Rheinland-Pfalz",
    "wof:name":"Filox Filtertechnik Gmbh",
    "wof:placetype":"venue"
},
  "geometry": {"coordinates":[6.950456,50.469387],"type":"Point"}
}