{
  "type": "Feature",
  "properties": {
    "iso:country":"DE",
    "sg:address":"Benderstr. 69",
    "sg:city":"D\u00fcsseldorf",
    "sg:phone":"+49 211/294879",
    "sg:postcode":"40625",
    "sg:province":"Nordrhein-Westfalen",
    "wof:name":"Holger Und Markus Baatz",
    "wof:placetype":"venue"
},
  "geometry": {"coordinates":[6.853556,51.237667],"type":"Point"}
}