{
  "type": "Feature",
  "properties": {
    "iso:country":"DE",
    "sg:address":"Bonndorfer Str. 7",
    "sg:city":"L\u00f6ffingen",
    "sg:phone":"+49 7654/8541",
    "sg:postcode":"79843",
    "sg:province":"Baden-W\u00fcrttemberg",
    "wof:name":"Pension Haus Maria",
    "wof:placetype":"venue"
},
  "geometry": {"coordinates":[8.3453359604,47.8802909851],"type":"Point"}
}