{
  "type": "Feature",
  "properties": {
    "iso:country":"DE",
    "sg:address":"Kohlwaldstr. 7",
    "sg:city":"Schmelz",
    "sg:phone":"+49 6881/91308",
    "sg:postcode":"66839",
    "sg:province":"Saarland",
    "wof:name":"Helmut Werner",
    "wof:placetype":"venue"
},
  "geometry": {"coordinates":[6.8545498848,49.4133300781],"type":"Point"}
}