{
  "type": "Feature",
  "properties": {
    "iso:country":"DE",
    "sg:address":"Bernhardstr 12",
    "sg:city":"Nordenham",
    "sg:phone":"+49 4731/87140",
    "sg:postcode":"26954",
    "sg:province":"Niedersachsen",
    "wof:name":"Clap Tzu Massagetische",
    "wof:placetype":"venue"
},
  "geometry": {"coordinates":[8.478036,53.484371],"type":"Point"}
}