{
  "type": "Feature",
  "properties": {
    "iso:country":"DE",
    "sg:address":"Fanningerstr. 46",
    "sg:city":"Berlin",
    "sg:phone":"+49 30/5531627",
    "sg:postcode":"10365",
    "sg:province":"Berlin",
    "wof:name":"Aga Demir",
    "wof:placetype":"venue"
},
  "geometry": {"coordinates":[13.4977779388,52.5138893127],"type":"Point"}
}