{
  "type": "Feature",
  "properties": {
    "iso:country":"DE",
    "sg:address":"Albert-Ro\u00dfhaupter-Str. 106",
    "sg:city":"M\u00fcnchen",
    "sg:phone":"+49 89/7601609",
    "sg:postcode":"81369",
    "sg:province":"Bayern",
    "wof:name":"Hofer & Schurischuster",
    "wof:placetype":"venue"
},
  "geometry": {"coordinates":[11.5235834122,48.1155967712],"type":"Point"}
}