{
  "type": "Feature",
  "properties": {
    "iso:country":"DE",
    "sg:address":"Gr\u00fcneplan",
    "sg:city":"Delligsen",
    "sg:phone":"+49 5187/7261",
    "sg:postcode":"31073",
    "sg:province":"Niedersachsen",
    "wof:name":"Frei- Und Hallenbad",
    "wof:placetype":"venue"
},
  "geometry": {"coordinates":[9.7975187302,51.9425163269],"type":"Point"}
}