{
  "type": "Feature",
  "properties": {
    "iso:country":"DE",
    "sg:address":"Friedrich-Ebert-Str. 61",
    "sg:city":"Michelstadt",
    "sg:phone":"+49 6061/3452",
    "sg:postcode":"64720",
    "sg:province":"Hessen",
    "wof:name":"Ludwig Knierriem",
    "wof:placetype":"venue"
},
  "geometry": {"coordinates":[9.000402,49.672436],"type":"Point"}
}