{
  "type": "Feature",
  "properties": {
    "iso:country":"DE",
    "sg:address":"Hirschrott 11",
    "sg:city":"Simmerath",
    "sg:phone":"+49 2485/469",
    "sg:postcode":"52152",
    "sg:province":"Nordrhein-Westfalen",
    "wof:name":"Pension Zum Wei\u00dfen Stein",
    "wof:placetype":"venue"
},
  "geometry": {"coordinates":[6.3578958511,50.5571556091],"type":"Point"}
}