{
  "type": "Feature",
  "properties": {
    "iso:country":"DE",
    "sg:address":"W\u00fcrzburger Str. 29",
    "sg:city":"Rottendorf",
    "sg:phone":"+49 9302/1283",
    "sg:postcode":"97228",
    "sg:province":"Bayern",
    "wof:name":"E. Und W. Hart",
    "wof:placetype":"venue"
},
  "geometry": {"coordinates":[10.021076,49.790558],"type":"Point"}
}