{
  "type": "Feature",
  "properties": {
    "iso:country":"DE",
    "sg:address":"Kochstr. 7",
    "sg:city":"Lemf\u00f6rde",
    "sg:phone":"+49 5443/350",
    "sg:postcode":"49448",
    "sg:province":"Niedersachsen",
    "wof:name":"Werbegemeinschaft Lemf\u00f6rde Martin L\u00fccke",
    "wof:placetype":"venue"
},
  "geometry": {"coordinates":[8.3782110214,52.4677276611],"type":"Point"}
}