{
  "type": "Feature",
  "properties": {
    "iso:country":"DE",
    "sg:address":"Quellenstr. 2",
    "sg:city":"Reichelsheim",
    "sg:postcode":"64385",
    "sg:province":"Hessen",
    "wof:name":"I B S Immobilien",
    "wof:placetype":"venue"
},
  "geometry": {"coordinates":[8.8716077805,49.7280883789],"type":"Point"}
}