{
  "type": "Feature",
  "properties": {
    "iso:country":"DE",
    "sg:address":"Marktplatz 10",
    "sg:city":"Altmannstein",
    "sg:phone":"+49 9446/475",
    "sg:postcode":"93336",
    "sg:province":"Bayern",
    "wof:name":"Josef Forster",
    "wof:placetype":"venue"
},
  "geometry": {"coordinates":[11.650493,48.896393],"type":"Point"}
}