{
  "type": "Feature",
  "properties": {
    "iso:country":"DE",
    "sg:address":"Pfortenstr. 12b",
    "sg:city":"Gr\u00e4fenhainichen",
    "sg:phone":"+49 34953/21100",
    "sg:postcode":"06773",
    "sg:province":"Sachsen-Anhalt",
    "wof:name":"China-restaurat Wang Fu",
    "wof:placetype":"venue"
},
  "geometry": {"coordinates":[12.4566707611,51.7317886353],"type":"Point"}
}