{
  "type": "Feature",
  "properties": {
    "iso:country":"DE",
    "sg:address":"Bl\u00fccherstra\u00dfe 1",
    "sg:city":"Augsburg",
    "sg:phone":"+49 821/715412",
    "sg:postcode":"86165",
    "sg:province":"Bayern",
    "wof:name":"Rechtsanw\u00e4lte Metz-glogger, Herz, Musacchio",
    "wof:placetype":"venue"
},
  "geometry": {"coordinates":[10.91652,48.381241],"type":"Point"}
}