{
  "type": "Feature",
  "properties": {
    "iso:country":"DE",
    "sg:address":"Altm\u00f6llner Str 2",
    "sg:city":"M\u00f6lln",
    "sg:phone":"+49 4542/84590",
    "sg:postcode":"23879",
    "sg:province":"Schleswig-Holstein",
    "wof:name":"Ludwig Warncke Gmbh & Co Kg",
    "wof:placetype":"venue"
},
  "geometry": {"coordinates":[10.68169,53.625084],"type":"Point"}
}