{
  "type": "Feature",
  "properties": {
    "iso:country":"DE",
    "sg:address":"Ilmerweg 3",
    "sg:city":"Lippetal",
    "sg:phone":"+49 2527/284",
    "sg:postcode":"59510",
    "sg:province":"Nordrhein-Westfalen",
    "wof:name":"Paul Hagedorn Eisenwaren",
    "wof:placetype":"venue"
},
  "geometry": {"coordinates":[8.04376,51.672199],"type":"Point"}
}