{
  "type": "Feature",
  "properties": {
    "iso:country":"DE",
    "sg:address":"Lindener Str. 117-119",
    "sg:city":"Bochum",
    "sg:phone":"+49 234/491946",
    "sg:postcode":"44879",
    "sg:province":"Nordrhein-Westfalen",
    "wof:name":"Udo M\u00fcller Gmbh",
    "wof:placetype":"venue"
},
  "geometry": {"coordinates":[7.166894,51.426853],"type":"Point"}
}