{
  "type": "Feature",
  "properties": {
    "iso:country":"DE",
    "sg:address":"Talm\u00fchlenstr. 7",
    "sg:city":"Kurort Hartha",
    "sg:phone":"+49 35203/37129",
    "sg:postcode":"01737",
    "sg:province":"Sachsen",
    "wof:name":"Erhard Peuckert",
    "wof:placetype":"venue"
},
  "geometry": {"coordinates":[13.545692,50.980934],"type":"Point"}
}