{
  "type": "Feature",
  "properties": {
    "iso:country":"DE",
    "sg:address":"M\u00fcnsterstr 46",
    "sg:city":"Sendenhorst",
    "sg:phone":"+49 2535/9599111",
    "sg:postcode":"48324",
    "sg:province":"Nordrhein-Westfalen",
    "wof:name":"Mexs.de",
    "wof:placetype":"venue"
},
  "geometry": {"coordinates":[7.729518,51.871815],"type":"Point"}
}