{
  "type": "Feature",
  "properties": {
    "iso:country":"DE",
    "sg:address":"Badstr. 6",
    "sg:city":"Leiblfing",
    "sg:phone":"+49 9427/345",
    "sg:postcode":"94339",
    "sg:province":"Bayern",
    "wof:name":"F. Stuhlfelner Elektromeister",
    "wof:placetype":"venue"
},
  "geometry": {"coordinates":[12.55635,48.740173],"type":"Point"}
}