{
  "type": "Feature",
  "properties": {
    "iso:country":"DE",
    "sg:address":"Hubertusstr. 56",
    "sg:city":"Rheurdt",
    "sg:phone":"+49 2845/6668",
    "sg:postcode":"47509",
    "sg:province":"Nordrhein-Westfalen",
    "wof:name":"Ev. Pfarramt Schaephuysen",
    "wof:placetype":"venue"
},
  "geometry": {"coordinates":[6.4836578369,51.4384689331],"type":"Point"}
}