{
  "type": "Feature",
  "properties": {
    "iso:country":"DE",
    "sg:address":"Am Moselstausee 15",
    "sg:city":"Sankt Aldegund",
    "sg:phone":"+49 6542/2749",
    "sg:postcode":"56858",
    "sg:province":"Rheinland-Pfalz",
    "wof:name":"Treis-korneli",
    "wof:placetype":"venue"
},
  "geometry": {"coordinates":[7.1306838989,50.0817222595],"type":"Point"}
}