{
  "type": "Feature",
  "properties": {
    "iso:country":"DE",
    "sg:address":"Huyssenallee 44",
    "sg:city":"Essen",
    "sg:postcode":"45128",
    "sg:province":"Nordrhein-Westfalen",
    "wof:name":"Stiftung Mercator Gmbh",
    "wof:placetype":"venue"
},
  "geometry": {"coordinates":[7.0097241402,51.4472312927],"type":"Point"}
}