{
  "type": "Feature",
  "properties": {
    "iso:country":"DE",
    "sg:address":"Hof Talblick",
    "sg:city":"Netzbach",
    "sg:phone":"+49 6430/5003",
    "sg:postcode":"65623",
    "sg:province":"Rheinland-Pfalz",
    "wof:name":"Messebau Schild Inh. Wolfgang Zwiener E. K.",
    "wof:placetype":"venue"
},
  "geometry": {"coordinates":[8.084425,50.31459],"type":"Point"}
}