{
  "type": "Feature",
  "properties": {
    "iso:country":"DE",
    "sg:address":"Niederkirchnerstr. 7",
    "sg:city":"Leipzig",
    "sg:postcode":"04107",
    "sg:province":"Sachsen",
    "wof:name":"Kubens Ingenieurges. Mbh",
    "wof:placetype":"venue"
},
  "geometry": {"coordinates":[12.3687992096,51.3259429932],"type":"Point"}
}