{
  "type": "Feature",
  "properties": {
    "iso:country":"DE",
    "sg:address":"Schornstr. 23",
    "sg:city":"Garmisch-Partenkirchen",
    "sg:phone":"+49 8821/2157",
    "sg:postcode":"82467",
    "sg:province":"Bayern",
    "wof:name":"J. W\u00f6rndle Dolmetscher",
    "wof:placetype":"venue"
},
  "geometry": {"coordinates":[11.106401,47.490292],"type":"Point"}
}