{
  "type": "Feature",
  "properties": {
    "iso:country":"DE",
    "sg:address":"W.Brand 06",
    "sg:city":"Bebra",
    "sg:postcode":"36171",
    "sg:province":"Hessen",
    "wof:name":"Anton Greinert",
    "wof:placetype":"venue"
},
  "geometry": {"coordinates":[9.7943429947,50.9709854126],"type":"Point"}
}