{
  "type": "Feature",
  "properties": {
    "iso:country":"DE",
    "sg:address":"Burgweg 5",
    "sg:city":"Ibbenb\u00fcren",
    "sg:phone":"+49 5451/9968029",
    "sg:postcode":"49479",
    "sg:province":"Nordrhein-Westfalen",
    "wof:name":"Internetmarketing",
    "wof:placetype":"venue"
},
  "geometry": {"coordinates":[7.7863001823,52.2539291382],"type":"Point"}
}