{
  "type": "Feature",
  "properties": {
    "iso:country":"DE",
    "sg:address":"Beckumer Str. 34",
    "sg:city":"Ahlen",
    "sg:postcode":"59229",
    "sg:province":"Nordrhein-Westfalen",
    "wof:name":"Historeal Immobilien Christine Sch\u00e4per",
    "wof:placetype":"venue"
},
  "geometry": {"coordinates":[7.9028058052,51.763092041],"type":"Point"}
}