{
  "type": "Feature",
  "properties": {
    "iso:country":"DE",
    "sg:address":"Teestr. 36",
    "sg:city":"Aurich",
    "sg:phone":"+49 4941/80180",
    "sg:postcode":"26605",
    "sg:province":"Niedersachsen",
    "wof:name":"Enno Menken",
    "wof:placetype":"venue"
},
  "geometry": {"coordinates":[7.44634,53.464836],"type":"Point"}
}