{
  "type": "Feature",
  "properties": {
    "iso:country":"DE",
    "sg:address":"Max-Planck-Str. 6",
    "sg:city":"Telgte",
    "sg:phone":"+49 2504/3906",
    "sg:postcode":"48291",
    "sg:province":"Nordrhein-Westfalen",
    "wof:name":"Udo Kisk\u00e4mper",
    "wof:placetype":"venue"
},
  "geometry": {"coordinates":[7.7759618759,51.9781074524],"type":"Point"}
}