{
  "type": "Feature",
  "properties": {
    "iso:country":"DE",
    "sg:address":"Hohenlohestr. 23",
    "sg:city":"Ohrdruf",
    "sg:phone":"+49 3624/402400",
    "sg:postcode":"99885",
    "sg:province":"Th\u00fcringen",
    "wof:name":"G\u00f6rlachs Garten",
    "wof:placetype":"venue"
},
  "geometry": {"coordinates":[10.7316589355,50.8295097351],"type":"Point"}
}