{
  "type": "Feature",
  "properties": {
    "iso:country":"DE",
    "sg:address":"Graseweg 20",
    "sg:city":"Hann. M\u00fcnden",
    "sg:phone":"+49 5545/1035",
    "sg:postcode":"34346",
    "sg:province":"Niedersachsen",
    "wof:name":"Georg Fehrensen Kg",
    "wof:placetype":"venue"
},
  "geometry": {"coordinates":[9.7532949448,51.3939285278],"type":"Point"}
}