{
  "type": "Feature",
  "properties": {
    "iso:country":"DE",
    "sg:address":"Auf dem Amte 10",
    "sg:city":"Bad Laer",
    "sg:phone":"+49 5426/662",
    "sg:postcode":"49196",
    "sg:province":"Niedersachsen",
    "wof:name":"Heinrich Ossege",
    "wof:placetype":"venue"
},
  "geometry": {"coordinates":[8.067221,52.072906],"type":"Point"}
}