{
  "type": "Feature",
  "properties": {
    "iso:country":"DE",
    "sg:address":"Str\u00f6bing 1",
    "sg:city":"Bad Endorf",
    "sg:postcode":"83093",
    "sg:province":"Bayern",
    "wof:name":"Bgs-sportschule S\u00fcd",
    "wof:placetype":"venue"
},
  "geometry": {"coordinates":[12.3029708862,47.9027442932],"type":"Point"}
}