{
  "type": "Feature",
  "properties": {
    "iso:country":"DE",
    "sg:address":"D\u00f6rpfeldstr. 1",
    "sg:city":"Hamburg",
    "sg:postcode":"22609",
    "sg:province":"Hamburg",
    "wof:name":"Myfa Consulting Gmbh",
    "wof:placetype":"venue"
},
  "geometry": {"coordinates":[9.8427810669,53.5618553162],"type":"Point"}
}