{
  "type": "Feature",
  "properties": {
    "iso:country":"DE",
    "sg:address":"Rilkeweg 2",
    "sg:city":"Pl\u00fcderhausen",
    "sg:phone":"+49 7181/82773",
    "sg:postcode":"73655",
    "sg:province":"Baden-W\u00fcrttemberg",
    "wof:name":"Theinert",
    "wof:placetype":"venue"
},
  "geometry": {"coordinates":[9.6017723083,48.8028068542],"type":"Point"}
}