{
  "type": "Feature",
  "properties": {
    "iso:country":"DE",
    "sg:address":"Hauptstr. 60",
    "sg:city":"Dorfchemnitz",
    "sg:phone":"+49 37320/1651",
    "sg:postcode":"09619",
    "sg:province":"Sachsen",
    "wof:name":"Tischlermeister Werner",
    "wof:placetype":"venue"
},
  "geometry": {"coordinates":[13.447774,50.763985],"type":"Point"}
}