{
  "type": "Feature",
  "properties": {
    "iso:country":"DE",
    "sg:address":"Sulterkamp 70",
    "sg:city":"Essen",
    "sg:phone":"+49 201/663184",
    "sg:postcode":"45356",
    "sg:province":"Nordrhein-Westfalen",
    "wof:name":"Autokino Essen",
    "wof:placetype":"venue"
},
  "geometry": {"coordinates":[6.970701,51.486313],"type":"Point"}
}