{
  "type": "Feature",
  "properties": {
    "iso:country":"DE",
    "sg:address":"Kirchenstr. 18",
    "sg:city":"Westerstede",
    "sg:phone":"+49 4488/1856",
    "sg:postcode":"26655",
    "sg:province":"Niedersachsen",
    "wof:name":"Isermann H\u00f6rger\u00e4te Akustiker",
    "wof:placetype":"venue"
},
  "geometry": {"coordinates":[7.930314064,53.2588424683],"type":"Point"}
}