{
  "type": "Feature",
  "properties": {
    "iso:country":"DE",
    "sg:address":"Buchenweg 31",
    "sg:city":"Mainz",
    "sg:phone":"+49 6131/362620",
    "sg:postcode":"55128",
    "sg:province":"Rheinland-Pfalz",
    "wof:name":"Zvonimir Misanec",
    "wof:placetype":"venue"
},
  "geometry": {"coordinates":[8.23487,49.969879],"type":"Point"}
}