{
  "type": "Feature",
  "properties": {
    "iso:country":"DE",
    "sg:address":"Beindersheimer Str. 2",
    "sg:city":"Gro\u00dfniedesheim",
    "sg:phone":"+49 6239/6039",
    "sg:postcode":"67259",
    "sg:province":"Rheinland-Pfalz",
    "wof:name":"Rainer Schreiber",
    "wof:placetype":"venue"
},
  "geometry": {"coordinates":[8.313957,49.574986],"type":"Point"}
}