{
  "type": "Feature",
  "properties": {
    "iso:country":"DE",
    "sg:address":"Handelsweg 5",
    "sg:city":"Fulda",
    "sg:phone":"+49 661/58299",
    "sg:postcode":"36041",
    "sg:province":"Hessen",
    "wof:name":"Martin B\u00fcttner",
    "wof:placetype":"venue"
},
  "geometry": {"coordinates":[9.6383304596,50.6027832031],"type":"Point"}
}