{
  "type": "Feature",
  "properties": {
    "iso:country":"DE",
    "sg:address":"Diemstr. 2a",
    "sg:city":"Aachen",
    "sg:phone":"+49 241/65663",
    "sg:postcode":"52066",
    "sg:province":"Nordrhein-Westfalen",
    "wof:name":"Van Hout & Co. Gmbh",
    "wof:placetype":"venue"
},
  "geometry": {"coordinates":[6.101444,50.752956],"type":"Point"}
}