{
  "type": "Feature",
  "properties": {
    "iso:country":"DE",
    "sg:address":"Heigerding 1",
    "sg:city":"Ruhstorf",
    "sg:phone":"+49 8503/922157",
    "sg:postcode":"94099",
    "sg:province":"Bayern",
    "wof:name":"Privates Institut F\u00fcr Angewandte Kommunikation - Pifak",
    "wof:placetype":"venue"
},
  "geometry": {"coordinates":[13.346953,48.449486],"type":"Point"}
}