{
  "type": "Feature",
  "properties": {
    "iso:country":"DE",
    "sg:address":"Pettenkoferstr. 6",
    "sg:city":"Schrobenhausen",
    "sg:phone":"+49 8252/89660",
    "sg:postcode":"86529",
    "sg:province":"Bayern",
    "wof:name":"Schrobenhausener Treuhand Gmbh",
    "wof:placetype":"venue"
},
  "geometry": {"coordinates":[11.2599773407,48.562587738],"type":"Point"}
}