{
  "type": "Feature",
  "properties": {
    "iso:country":"DE",
    "sg:address":"Kronprinzenstr. 28",
    "sg:city":"Wiesbaden",
    "sg:phone":"+49 611/17000",
    "sg:postcode":"65185",
    "sg:province":"Hessen",
    "wof:name":"Gww Wiesbadener Wohn- Baugesellschaft Mbh",
    "wof:placetype":"venue"
},
  "geometry": {"coordinates":[8.243269,50.07457],"type":"Point"}
}