{
  "type": "Feature",
  "properties": {
    "iso:country":"DE",
    "sg:address":"Robert-Bosch-Str. 7",
    "sg:city":"Laudenbach",
    "sg:phone":"+49 6201/73295",
    "sg:postcode":"69514",
    "sg:province":"Baden-W\u00fcrttemberg",
    "wof:name":"C. Plotzki",
    "wof:placetype":"venue"
},
  "geometry": {"coordinates":[8.6396427155,49.6102142334],"type":"Point"}
}