{
  "type": "Feature",
  "properties": {
    "iso:country":"DE",
    "sg:address":"Wasenstr. 6",
    "sg:city":"G\u00f6ppingen",
    "sg:phone":"+49 711/8892431",
    "sg:postcode":"73035",
    "sg:province":"Baden-W\u00fcrttemberg",
    "wof:name":"Josef Baier Masseur",
    "wof:placetype":"venue"
},
  "geometry": {"coordinates":[9.632359,48.688549],"type":"Point"}
}