{
  "type": "Feature",
  "properties": {
    "iso:country":"DE",
    "sg:address":"Am Friedenstal 1",
    "sg:city":"Hannover",
    "sg:phone":"+49 511/571070",
    "sg:postcode":"30627",
    "sg:province":"Niedersachsen",
    "wof:name":"Schubert Ingenieurgemeinschaft",
    "wof:placetype":"venue"
},
  "geometry": {"coordinates":[9.8336000443,52.3864593506],"type":"Point"}
}