{
  "type": "Feature",
  "properties": {
    "iso:country":"DE",
    "sg:address":"SchwarzerWeg 30",
    "sg:city":"Darmstadt",
    "sg:phone":"+49 6151/735820",
    "sg:postcode":"64287",
    "sg:province":"Hessen",
    "wof:name":"Frank Seifert Photography",
    "wof:placetype":"venue"
},
  "geometry": {"coordinates":[8.672945,49.886074],"type":"Point"}
}