{
  "type": "Feature",
  "properties": {
    "iso:country":"DE",
    "sg:address":"Finkenweg 14",
    "sg:city":"Olsberg",
    "sg:phone":"+49 2962/6428",
    "sg:postcode":"59939",
    "sg:province":"Nordrhein-Westfalen",
    "wof:name":"J\u00fcrgen Peters",
    "wof:placetype":"venue"
},
  "geometry": {"coordinates":[8.493825,51.348572],"type":"Point"}
}