{
  "type": "Feature",
  "properties": {
    "iso:country":"DE",
    "sg:address":"Eschweilerstr. 59",
    "sg:city":"Baesweiler",
    "sg:phone":"+49 2401/2386",
    "sg:postcode":"52499",
    "sg:province":"Nordrhein-Westfalen",
    "wof:name":"Heinz-gerd Koch",
    "wof:placetype":"venue"
},
  "geometry": {"coordinates":[6.1832537651,50.8958435059],"type":"Point"}
}