{
  "type": "Feature",
  "properties": {
    "iso:country":"DE",
    "sg:address":"Holzhauser Str. 79",
    "sg:city":"B\u00fcnde",
    "sg:phone":"+49 5223/61161",
    "sg:postcode":"32257",
    "sg:province":"Nordrhein-Westfalen",
    "wof:name":"Dieter Garben",
    "wof:placetype":"venue"
},
  "geometry": {"coordinates":[8.5598773956,52.2073326111],"type":"Point"}
}