{
  "type": "Feature",
  "properties": {
    "iso:country":"DE",
    "sg:address":"Mittelweg 5",
    "sg:city":"Stuhr",
    "sg:phone":"+49 4206/41750",
    "sg:postcode":"28816",
    "sg:province":"Niedersachsen",
    "wof:name":"Deutsche Verm\u00f6gensberatung Ag",
    "wof:placetype":"venue"
},
  "geometry": {"coordinates":[8.6822795868,52.9936828613],"type":"Point"}
}