{
  "type": "Feature",
  "properties": {
    "iso:country":"DE",
    "sg:address":"Robert-Bosch-Str.",
    "sg:city":"Leutenbach",
    "sg:phone":"+49 7195/957078",
    "sg:postcode":"71397",
    "sg:province":"Baden-W\u00fcrttemberg",
    "wof:name":"Skr\u00fcgle Inh. Alic H. Robby",
    "wof:placetype":"venue"
},
  "geometry": {"coordinates":[9.4130620956,48.9041175842],"type":"Point"}
}