{
  "type": "Feature",
  "properties": {
    "iso:country":"DE",
    "sg:address":"Hildrizhauser Str. 5",
    "sg:city":"Herrenberg",
    "sg:phone":"+49 7032/952133",
    "sg:postcode":"71083",
    "sg:province":"Baden-W\u00fcrttemberg",
    "wof:name":"L. Mathyschok",
    "wof:placetype":"venue"
},
  "geometry": {"coordinates":[8.874536,48.59454],"type":"Point"}
}