{
  "type": "Feature",
  "properties": {
    "iso:country":"DE",
    "sg:address":"Wanheimer Str. 11",
    "sg:city":"Duisburg",
    "sg:phone":"+49 203/660687",
    "sg:postcode":"47053",
    "sg:province":"Nordrhein-Westfalen",
    "wof:name":"Behrens",
    "wof:placetype":"venue"
},
  "geometry": {"coordinates":[6.754468,51.422218],"type":"Point"}
}