{
  "type": "Feature",
  "properties": {
    "iso:country":"DE",
    "sg:address":"Donnstetter Str. 1",
    "sg:city":"Westerheim",
    "sg:phone":"+49 7333/6535",
    "sg:postcode":"72589",
    "sg:province":"Baden-W\u00fcrttemberg",
    "wof:name":"Alfons Stehle",
    "wof:placetype":"venue"
},
  "geometry": {"coordinates":[9.623627,48.514915],"type":"Point"}
}