{
  "type": "Feature",
  "properties": {
    "iso:country":"DE",
    "sg:address":"Am Wellenbach 35",
    "sg:city":"Hildesheim",
    "sg:phone":"+49 5121/62955",
    "sg:postcode":"31139",
    "sg:province":"Niedersachsen",
    "wof:name":"I. Bullach",
    "wof:placetype":"venue"
},
  "geometry": {"coordinates":[9.8821077347,52.1400985718],"type":"Point"}
}