{
  "type": "Feature",
  "properties": {
    "iso:country":"DE",
    "sg:address":"Bobenh\u00e4user Weg 11",
    "sg:city":"Borken",
    "sg:phone":"+49 5682/1818",
    "sg:postcode":"34582",
    "sg:province":"Hessen",
    "wof:name":"Borkener Sport- Und Festhalle Gmbh",
    "wof:placetype":"venue"
},
  "geometry": {"coordinates":[9.2740526199,51.0494499207],"type":"Point"}
}