{
  "type": "Feature",
  "properties": {
    "iso:country":"DE",
    "sg:address":"Am Schlo\u00dfpark 14",
    "sg:city":"M\u00f6nchengladbach",
    "sg:postcode":"41189",
    "sg:province":"Nordrhein-Westfalen",
    "wof:name":"Dipl.-ing. Viola Kluge-schulte Baubetreuungs- Gmbh",
    "wof:placetype":"venue"
},
  "geometry": {"coordinates":[6.419192,51.12632],"type":"Point"}
}