{
  "type": "Feature",
  "properties": {
    "iso:country":"DE",
    "sg:address":"Winkelberger H\u00f6he 15",
    "sg:city":"Bischweier",
    "sg:phone":"+49 7222/42123",
    "sg:postcode":"76476",
    "sg:province":"Baden-W\u00fcrttemberg",
    "wof:name":"Carmen Maurer Rechtsanw\u00e4ltin",
    "wof:placetype":"venue"
},
  "geometry": {"coordinates":[8.2936191559,48.8354530334],"type":"Point"}
}