{
  "type": "Feature",
  "properties": {
    "iso:country":"DE",
    "sg:address":"Sietwender Str. 7",
    "sg:city":"Drochtersen",
    "sg:phone":"+49 4143/9078",
    "sg:postcode":"21706",
    "sg:province":"Niedersachsen",
    "wof:name":"Gemeindeb\u00fccherei",
    "wof:placetype":"venue"
},
  "geometry": {"coordinates":[9.384467,53.709988],"type":"Point"}
}