{
  "type": "Feature",
  "properties": {
    "iso:country":"DE",
    "sg:address":"Burgweg 11",
    "sg:city":"G\u00fcglingen",
    "sg:phone":"+49 7135/15211",
    "sg:postcode":"74363",
    "sg:province":"Baden-W\u00fcrttemberg",
    "wof:name":"M\u00fcller",
    "wof:placetype":"venue"
},
  "geometry": {"coordinates":[8.9966497421,49.061580658],"type":"Point"}
}