{
  "type": "Feature",
  "properties": {
    "iso:country":"DE",
    "sg:address":"Langstr. 18",
    "sg:city":"Mannheim",
    "sg:phone":"+49 621/3392192",
    "sg:postcode":"68169",
    "sg:province":"Baden-W\u00fcrttemberg",
    "wof:name":"G. Ciatipitis",
    "wof:placetype":"venue"
},
  "geometry": {"coordinates":[8.470748,49.497181],"type":"Point"}
}