{
  "type": "Feature",
  "properties": {
    "iso:country":"DE",
    "sg:address":"Weg am K\u00f6tterberg 5",
    "sg:city":"Bochum",
    "sg:phone":"+49 234/502727",
    "sg:postcode":"44807",
    "sg:province":"Nordrhein-Westfalen",
    "wof:name":"Heinz Karwath Architekt",
    "wof:placetype":"venue"
},
  "geometry": {"coordinates":[7.242786,51.504189],"type":"Point"}
}