{
  "type": "Feature",
  "properties": {
    "iso:country":"DE",
    "sg:address":"Buschdorfer Str. 4",
    "sg:city":"Bonn",
    "sg:phone":"+49 228/674761",
    "sg:postcode":"53117",
    "sg:province":"Nordrhein-Westfalen",
    "wof:name":"Maschinenzentrale Des Verbandes Landwirtschaft-",
    "wof:placetype":"venue"
},
  "geometry": {"coordinates":[7.074629,50.761951],"type":"Point"}
}