{
  "type": "Feature",
  "properties": {
    "iso:country":"DE",
    "sg:address":"Spiegelburgring 31",
    "sg:city":"Bellheim",
    "sg:postcode":"76756",
    "sg:province":"Rheinland-Pfalz",
    "wof:name":"Vogelsang Transporte Gmbh",
    "wof:placetype":"venue"
},
  "geometry": {"coordinates":[8.280787468,49.1993789673],"type":"Point"}
}