{
  "type": "Feature",
  "properties": {
    "iso:country":"DE",
    "sg:address":"Martinusstr. 14",
    "sg:city":"Koblenz",
    "sg:phone":"+49 261/802280",
    "sg:postcode":"56070",
    "sg:province":"Rheinland-Pfalz",
    "wof:name":"Pai Otto Gmbh",
    "wof:placetype":"venue"
},
  "geometry": {"coordinates":[7.580906868,50.4003753662],"type":"Point"}
}