{
  "type": "Feature",
  "properties": {
    "iso:country":"DE",
    "sg:address":"An der Untertrave 69",
    "sg:city":"L\u00fcbeck",
    "sg:phone":"+49 451/6789901",
    "sg:postcode":"23552",
    "sg:province":"Schleswig-Holstein",
    "wof:name":"Otto Heineke Gmbh",
    "wof:placetype":"venue"
},
  "geometry": {"coordinates":[10.6817836761,53.8711585999],"type":"Point"}
}