{
  "type": "Feature",
  "properties": {
    "iso:country":"DE",
    "sg:address":"Gartenstr. 44",
    "sg:city":"D\u00fcsseldorf",
    "sg:phone":"+49 211/4931003",
    "sg:postcode":"40479",
    "sg:province":"Nordrhein-Westfalen",
    "wof:name":"Hbr Beteiligungs- Verwaltungs Gmbh",
    "wof:placetype":"venue"
},
  "geometry": {"coordinates":[6.784892,51.232014],"type":"Point"}
}