{
  "type": "Feature",
  "properties": {
    "iso:country":"DE",
    "sg:address":"Bahnhofstr. 74",
    "sg:city":"Wirges",
    "sg:phone":"+49 2602/6449",
    "sg:postcode":"56422",
    "sg:province":"Rheinland-Pfalz",
    "wof:name":"Norma Gmbh & Co. Kg",
    "wof:placetype":"venue"
},
  "geometry": {"coordinates":[7.7898468971,50.4694595337],"type":"Point"}
}