{
  "type": "Feature",
  "properties": {
    "iso:country":"DE",
    "sg:address":"Wanheimer Str. 607",
    "sg:city":"Duisburg",
    "sg:phone":"+49 203/701237",
    "sg:postcode":"47249",
    "sg:province":"Nordrhein-Westfalen",
    "wof:name":"Conrad Stolte",
    "wof:placetype":"venue"
},
  "geometry": {"coordinates":[6.7423081398,51.386516571],"type":"Point"}
}