{
  "type": "Feature",
  "properties": {
    "iso:country":"DE",
    "sg:address":"Holbeinstr.",
    "sg:city":"Heilbad Heiligenstadt",
    "sg:phone":"+49 3606/605054",
    "sg:postcode":"37308",
    "sg:province":"Th\u00fcringen",
    "wof:name":"Liethen-treffpunkt",
    "wof:placetype":"venue"
},
  "geometry": {"coordinates":[10.1402282715,51.3837623596],"type":"Point"}
}