{
  "type": "Feature",
  "properties": {
    "iso:country":"DE",
    "sg:address":"An den Sportpl\u00e4tzen 8-10",
    "sg:city":"M\u00f6rfelden-Walldorf",
    "sg:phone":"+49 6105/94000",
    "sg:postcode":"64546",
    "sg:province":"Hessen",
    "wof:name":"Verdi Vertriebs- Und Dienstleistungs Gmbh",
    "wof:placetype":"venue"
},
  "geometry": {"coordinates":[8.5663995743,50.0054855347],"type":"Point"}
}