{
  "type": "Feature",
  "properties": {
    "iso:country":"DE",
    "sg:address":"Tammer Str. 2",
    "sg:city":"Markgr\u00f6ningen",
    "sg:phone":"+49 7145/8926",
    "sg:postcode":"71706",
    "sg:province":"Baden-W\u00fcrttemberg",
    "wof:name":"Eiscafe Valentino",
    "wof:placetype":"venue"
},
  "geometry": {"coordinates":[9.083756,48.906342],"type":"Point"}
}