{
  "type": "Feature",
  "properties": {
    "iso:country":"DE",
    "sg:address":"Br\u00fcckenstr. 5",
    "sg:city":"Neustadt",
    "sg:phone":"+49 9568/5114",
    "sg:postcode":"96465",
    "sg:province":"Bayern",
    "wof:name":"Anton Schiel Kunststoff- U. Per\u00fccken- Gmbh",
    "wof:placetype":"venue"
},
  "geometry": {"coordinates":[9.031583,49.817333],"type":"Point"}
}