{
  "type": "Feature",
  "properties": {
    "iso:country":"DE",
    "sg:address":"Hinter der B\u00f6ck 75",
    "sg:city":"D\u00fcsseldorf",
    "sg:phone":"+49 211/394923",
    "sg:postcode":"40221",
    "sg:province":"Nordrhein-Westfalen",
    "wof:name":"G. Knell",
    "wof:placetype":"venue"
},
  "geometry": {"coordinates":[6.7383480072,51.2005462646],"type":"Point"}
}