{
  "type": "Feature",
  "properties": {
    "iso:country":"DE",
    "sg:address":"Stiftsgartenweg 3",
    "sg:city":"Kempten",
    "sg:phone":"+49 831/28452",
    "sg:postcode":"87439",
    "sg:province":"Bayern",
    "wof:name":"Josef Mildner",
    "wof:placetype":"venue"
},
  "geometry": {"coordinates":[10.30838871,47.7300834656],"type":"Point"}
}