{
  "type": "Feature",
  "properties": {
    "iso:country":"DE",
    "sg:address":"Tecklenburger Str. 12",
    "sg:city":"Lengerich",
    "sg:postcode":"49525",
    "sg:province":"Nordrhein-Westfalen",
    "wof:name":"Aldi Gmbh & Co. Kg",
    "wof:placetype":"venue"
},
  "geometry": {"coordinates":[7.8458352089,52.1920127869],"type":"Point"}
}