{
  "type": "Feature",
  "properties": {
    "iso:country":"DE",
    "sg:address":"Julius-Leber-Str. 28",
    "sg:city":"Aalen",
    "sg:phone":"+49 7361/961733",
    "sg:postcode":"73430",
    "sg:province":"Baden-W\u00fcrttemberg",
    "wof:name":"Michael Dietrich",
    "wof:placetype":"venue"
},
  "geometry": {"coordinates":[10.0914258957,48.8355293274],"type":"Point"}
}