{
  "type": "Feature",
  "properties": {
    "iso:country":"DE",
    "sg:address":"Heinrich-von-Berge-Weg 5",
    "sg:city":"Bornheim",
    "sg:phone":"+49 2227/82561",
    "sg:postcode":"53332",
    "sg:province":"Nordrhein-Westfalen",
    "wof:name":"Heinz-josef Schmitt",
    "wof:placetype":"venue"
},
  "geometry": {"coordinates":[6.915635,50.793205],"type":"Point"}
}