{
  "type": "Feature",
  "properties": {
    "iso:country":"DE",
    "sg:address":"Burgb\u00fchlstr. 7",
    "sg:city":"Lahr",
    "sg:phone":"+49 7821/37324",
    "sg:postcode":"77933",
    "sg:province":"Baden-W\u00fcrttemberg",
    "wof:name":"R. Haller",
    "wof:placetype":"venue"
},
  "geometry": {"coordinates":[7.881972,48.347649],"type":"Point"}
}