{
  "type": "Feature",
  "properties": {
    "iso:country":"DE",
    "sg:address":"Seesen",
    "sg:city":"Seesen",
    "sg:phone":"+49 5384/220",
    "sg:postcode":"38723",
    "sg:province":"Niedersachsen",
    "wof:name":"Raiffeisenbank Eg",
    "wof:placetype":"venue"
},
  "geometry": {"coordinates":[10.17358,51.877941],"type":"Point"}
}