{
  "type": "Feature",
  "properties": {
    "iso:country":"DE",
    "sg:address":"Baderallee 23",
    "sg:city":"Landau",
    "sg:phone":"+49 9951/2220",
    "sg:postcode":"94405",
    "sg:province":"Bayern",
    "wof:name":"Alois Huber Gmbh",
    "wof:placetype":"venue"
},
  "geometry": {"coordinates":[12.6954965591,48.6803398132],"type":"Point"}
}