{
  "type": "Feature",
  "properties": {
    "iso:country":"DE",
    "sg:address":"Meckelstr. 54",
    "sg:city":"Wuppertal",
    "sg:phone":"+49 202/597899",
    "sg:postcode":"42287",
    "sg:province":"Nordrhein-Westfalen",
    "wof:name":"Ev. Pfarramt Unterbarmer S\u00fcd Pfarr Bez. 2",
    "wof:placetype":"venue"
},
  "geometry": {"coordinates":[7.1872057915,51.2625579834],"type":"Point"}
}