{
  "type": "Feature",
  "properties": {
    "iso:country":"DE",
    "sg:address":"Uhlandstr 47",
    "sg:city":"Berlin",
    "sg:phone":"+49 30/8815138",
    "sg:postcode":"10719",
    "sg:province":"Berlin",
    "wof:name":"Pwi- Beratungs- Und Vertriebsgesellschaft F\u00fcr Produktionstechnik Mbh",
    "wof:placetype":"venue"
},
  "geometry": {"coordinates":[13.324151,52.497669],"type":"Point"}
}