{
  "type": "Feature",
  "properties": {
    "iso:country":"DE",
    "sg:address":"Weinbergstr. 33",
    "sg:city":"M\u00fchlhausen",
    "sg:phone":"+49 6222/64620",
    "sg:postcode":"69242",
    "sg:province":"Baden-W\u00fcrttemberg",
    "wof:name":"Vereinsgastst\u00e4tte 1. Fc M\u00fchlhausen",
    "wof:placetype":"venue"
},
  "geometry": {"coordinates":[8.7525463104,49.2660102844],"type":"Point"}
}