{
  "type": "Feature",
  "properties": {
    "iso:country":"DE",
    "sg:address":"Altl\u00e4nder Str. 23",
    "sg:city":"Dollern",
    "sg:phone":"+49 4163/2916",
    "sg:postcode":"21739",
    "sg:province":"Niedersachsen",
    "wof:name":"H. Michel Baumschule",
    "wof:placetype":"venue"
},
  "geometry": {"coordinates":[9.557962,53.545605],"type":"Point"}
}