{
  "type": "Feature",
  "properties": {
    "iso:country":"DE",
    "sg:address":"Dessauer Str. 48a",
    "sg:city":"Aken",
    "sg:phone":"+49 34909/82019",
    "sg:postcode":"06385",
    "sg:province":"Sachsen-Anhalt",
    "wof:name":"Dieter Zeibig Fleisch- Und Wurstwaren Gmbh",
    "wof:placetype":"venue"
},
  "geometry": {"coordinates":[12.0502882004,51.8546867371],"type":"Point"}
}