{
  "type": "Feature",
  "properties": {
    "iso:country":"DE",
    "sg:address":"Stadthausbr\u00fccke 1-3",
    "sg:city":"Hamburg",
    "sg:postcode":"20355",
    "sg:province":"Hamburg",
    "wof:name":"Cfpi Gmbh",
    "wof:placetype":"venue"
},
  "geometry": {"coordinates":[9.985699,53.550106],"type":"Point"}
}