{
  "type": "Feature",
  "properties": {
    "iso:country":"DE",
    "sg:address":"M\u00fchlstr. 7a",
    "sg:city":"Bechhofen",
    "sg:phone":"+49 6372/5847",
    "sg:postcode":"66894",
    "sg:province":"Rheinland-Pfalz",
    "wof:name":"C. Hennes",
    "wof:placetype":"venue"
},
  "geometry": {"coordinates":[7.4032959938,49.3518486023],"type":"Point"}
}