{
  "type": "Feature",
  "properties": {
    "iso:country":"DE",
    "sg:address":"Breustian",
    "sg:city":"Jameln",
    "sg:phone":"+49 5864/577",
    "sg:postcode":"29479",
    "sg:province":"Niedersachsen",
    "wof:name":"M. Kuhnle & M. Klaiber",
    "wof:placetype":"venue"
},
  "geometry": {"coordinates":[11.0335006714,53.0346260071],"type":"Point"}
}