{
  "type": "Feature",
  "properties": {
    "iso:country":"DE",
    "sg:address":"Nieder-Rosbacher-Str. 17",
    "sg:city":"Rosbach",
    "sg:postcode":"61191",
    "sg:province":"Hessen",
    "wof:name":"Limes Apotheke Robach E. K.",
    "wof:placetype":"venue"
},
  "geometry": {"coordinates":[8.692039,50.301044],"type":"Point"}
}