{
  "type": "Feature",
  "properties": {
    "iso:country":"DE",
    "sg:address":"Brandenburger Weg 27",
    "sg:city":"Wildflecken",
    "sg:phone":"+49 9745/2163",
    "sg:postcode":"97772",
    "sg:province":"Bayern",
    "wof:name":"Erich Reder",
    "wof:placetype":"venue"
},
  "geometry": {"coordinates":[9.94247,50.378761],"type":"Point"}
}