{
  "type": "Feature",
  "properties": {
    "iso:country":"DE",
    "sg:address":"Mittelweg 1",
    "sg:city":"Bad Essen",
    "sg:phone":"+49 5472/2084",
    "sg:postcode":"49152",
    "sg:province":"Niedersachsen",
    "wof:name":"Hans-georg Nimz",
    "wof:placetype":"venue"
},
  "geometry": {"coordinates":[8.3548822403,52.3278999329],"type":"Point"}
}