{
  "type": "Feature",
  "properties": {
    "iso:country":"DE",
    "sg:address":"Hauptstr. 279",
    "sg:city":"Adenau",
    "sg:phone":"+49 2691/92290",
    "sg:postcode":"53518",
    "sg:province":"Rheinland-Pfalz",
    "wof:name":"Seniorenzentrum Villa Am Buttermarkt",
    "wof:placetype":"venue"
},
  "geometry": {"coordinates":[6.944394,50.381863],"type":"Point"}
}