{
  "type": "Feature",
  "properties": {
    "iso:country":"DE",
    "sg:address":"Wiesenweg 31",
    "sg:city":"K\u00f6ln",
    "sg:phone":"+49 2203/27262",
    "sg:postcode":"51147",
    "sg:province":"Nordrhein-Westfalen",
    "wof:name":"Jakob Inger Architekt",
    "wof:placetype":"venue"
},
  "geometry": {"coordinates":[7.099711,50.875076],"type":"Point"}
}