{
  "type": "Feature",
  "properties": {
    "iso:country":"DE",
    "sg:address":"Hanauer Landstr 20",
    "sg:city":"Kahl",
    "sg:phone":"+49 6188/901140",
    "sg:postcode":"63796",
    "sg:province":"Bayern",
    "wof:name":"Geo-technik",
    "wof:placetype":"venue"
},
  "geometry": {"coordinates":[9.004702,50.071068],"type":"Point"}
}