{
  "type": "Feature",
  "properties": {
    "iso:country":"DE",
    "sg:address":"Ewaldstr. 18",
    "sg:city":"G\u00f6ttingen",
    "sg:postcode":"37085",
    "sg:province":"Niedersachsen",
    "wof:name":"G\u00f6rcke Gmbh",
    "wof:placetype":"venue"
},
  "geometry": {"coordinates":[9.9567661285,51.5398712158],"type":"Point"}
}