{
  "type": "Feature",
  "properties": {
    "iso:country":"DE",
    "sg:address":"Flugplatz 140",
    "sg:city":"Lahr",
    "sg:phone":"+49 7821/959692",
    "sg:postcode":"77933",
    "sg:province":"Baden-W\u00fcrttemberg",
    "wof:name":"Ellen Schiller Dienstleistungen E. K.",
    "wof:placetype":"venue"
},
  "geometry": {"coordinates":[7.8352651596,48.3570785522],"type":"Point"}
}