{
  "type": "Feature",
  "properties": {
    "iso:country":"DE",
    "sg:address":"Tannenleite 29",
    "sg:city":"Passau",
    "sg:postcode":"94034",
    "sg:province":"Bayern",
    "wof:name":"Pa-projects Gmbh",
    "wof:placetype":"venue"
},
  "geometry": {"coordinates":[13.4233760834,48.5977363586],"type":"Point"}
}