{
  "type": "Feature",
  "properties": {
    "iso:country":"DE",
    "sg:address":"Poststr. 6",
    "sg:city":"Zehdenick",
    "sg:phone":"+49 3307/2862",
    "sg:postcode":"16792",
    "sg:province":"Brandenburg",
    "wof:name":"Artur G\u00fcnther Rechtsanwalt",
    "wof:placetype":"venue"
},
  "geometry": {"coordinates":[13.3319387436,52.980381012],"type":"Point"}
}