{
  "type": "Feature",
  "properties": {
    "iso:country":"DE",
    "sg:address":"Schulstr. 9",
    "sg:city":"Lastrup",
    "sg:phone":"+49 4472/260",
    "sg:postcode":"49688",
    "sg:province":"Niedersachsen",
    "wof:name":"Foto Rensen Gmbh",
    "wof:placetype":"venue"
},
  "geometry": {"coordinates":[7.8632259369,52.7962226868],"type":"Point"}
}