{
  "type": "Feature",
  "properties": {
    "iso:country":"DE",
    "sg:address":"Ziegelstr. 7",
    "sg:city":"Halle/Westf.",
    "sg:phone":"+49 5201",
    "sg:postcode":"33790",
    "sg:province":"Nordrhein-Westfalen",
    "wof:name":"Hoffmann & Kaup Gbr",
    "wof:placetype":"venue"
},
  "geometry": {"coordinates":[8.328399,52.031658],"type":"Point"}
}