{
  "type": "Feature",
  "properties": {
    "iso:country":"DE",
    "sg:address":"Markt 14",
    "sg:city":"Hasel\u00fcnne",
    "sg:phone":"+49 5961/5967",
    "sg:postcode":"49740",
    "sg:province":"Niedersachsen",
    "wof:name":"Blumen-boutique",
    "wof:placetype":"venue"
},
  "geometry": {"coordinates":[7.477114,52.680111],"type":"Point"}
}