{
  "type": "Feature",
  "properties": {
    "iso:country":"DE",
    "sg:address":"Friesenstr. 13",
    "sg:city":"Berlin",
    "sg:phone":"+49 30/69816130",
    "sg:postcode":"10965",
    "sg:province":"Berlin",
    "wof:name":"Michael Zimmermann",
    "wof:placetype":"venue"
},
  "geometry": {"coordinates":[13.3941726685,52.4863166809],"type":"Point"}
}