{
  "type": "Feature",
  "properties": {
    "iso:country":"DE",
    "sg:address":"Am Stockfeld 11",
    "sg:city":"Barsinghausen",
    "sg:phone":"+49 5105/81077",
    "sg:postcode":"30890",
    "sg:province":"Niedersachsen",
    "wof:name":"Detewe-deutsche Telephonwerke Ag & Co.",
    "wof:placetype":"venue"
},
  "geometry": {"coordinates":[9.5073518753,52.2882652283],"type":"Point"}
}