{
  "type": "Feature",
  "properties": {
    "iso:country":"DE",
    "sg:address":"Peiner Heerstr. 13",
    "sg:city":"Lehrte",
    "sg:phone":"+49 5132/2396",
    "sg:postcode":"31275",
    "sg:province":"Niedersachsen",
    "wof:name":"Uwe Schmidt",
    "wof:placetype":"venue"
},
  "geometry": {"coordinates":[9.9785051346,52.4024620056],"type":"Point"}
}