{
  "type": "Feature",
  "properties": {
    "iso:country":"DE",
    "sg:address":"Heiligenstr. 53",
    "sg:city":"Hilden",
    "sg:phone":"+49 2103/8109",
    "sg:postcode":"40721",
    "sg:province":"Nordrhein-Westfalen",
    "wof:name":"H. Otto Schreiner",
    "wof:placetype":"venue"
},
  "geometry": {"coordinates":[6.938213,51.166161],"type":"Point"}
}