{
  "type": "Feature",
  "properties": {
    "iso:country":"DE",
    "sg:address":"Sagebiels Weg 3",
    "sg:city":"Hamburg",
    "sg:phone":"+49 40/867901",
    "sg:postcode":"22587",
    "sg:province":"Hamburg",
    "wof:name":"Anita Schiefelbein Immobilienmaklerin",
    "wof:placetype":"venue"
},
  "geometry": {"coordinates":[9.8047170639,53.5574150085],"type":"Point"}
}