{
  "type": "Feature",
  "properties": {
    "iso:country":"DE",
    "sg:address":"Sch\u00fctzenhausstr. 4",
    "sg:city":"Stolpen",
    "sg:postcode":"01833",
    "sg:province":"Sachsen",
    "wof:name":"Katholisches Pfarramt Stolpen",
    "wof:placetype":"venue"
},
  "geometry": {"coordinates":[14.0799427032,51.0503120422],"type":"Point"}
}