{
  "type": "Feature",
  "properties": {
    "iso:country":"DE",
    "sg:address":"Nord-West-Rg. 38",
    "sg:city":"Augustdorf",
    "sg:phone":"+49 4952/3798090",
    "sg:postcode":"32832",
    "sg:province":"Nordrhein-Westfalen",
    "wof:name":"Tnt Maschinenbau Gmbh",
    "wof:placetype":"venue"
},
  "geometry": {"coordinates":[8.70758,51.905399],"type":"Point"}
}