{
  "type": "Feature",
  "properties": {
    "iso:country":"DE",
    "sg:address":"Drosselweg 12",
    "sg:city":"Aschaffenburg",
    "sg:phone":"+49 6021/413775",
    "sg:postcode":"63741",
    "sg:province":"Bayern",
    "wof:name":"Otwin Kornherr",
    "wof:placetype":"venue"
},
  "geometry": {"coordinates":[9.1215219498,49.9898872375],"type":"Point"}
}