{
  "type": "Feature",
  "properties": {
    "iso:country":"DE",
    "sg:address":"Oberer Teckelsberg 14",
    "sg:city":"Sundern",
    "sg:phone":"+49 2933/4715",
    "sg:postcode":"59846",
    "sg:province":"Nordrhein-Westfalen",
    "wof:name":"Johannes Hoffmann",
    "wof:placetype":"venue"
},
  "geometry": {"coordinates":[7.99686,51.317165],"type":"Point"}
}