{
  "type": "Feature",
  "properties": {
    "iso:country":"DE",
    "sg:address":"Forststr. 31",
    "sg:city":"Finsterwalde",
    "sg:phone":"+49 3531/3398",
    "sg:postcode":"03238",
    "sg:province":"Brandenburg",
    "wof:name":"Dieter Eknigk",
    "wof:placetype":"venue"
},
  "geometry": {"coordinates":[13.69846,51.633492],"type":"Point"}
}