{
  "type": "Feature",
  "properties": {
    "iso:country":"DE",
    "sg:address":"Bergmannstr. 170",
    "sg:city":"Gelsenkirchen",
    "sg:postcode":"45886",
    "sg:province":"Nordrhein-Westfalen",
    "wof:name":"Gff Grundst\u00fccks- Verwaltungsges. Mbh",
    "wof:placetype":"venue"
},
  "geometry": {"coordinates":[7.1323509216,51.5051231384],"type":"Point"}
}