{
  "type": "Feature",
  "properties": {
    "iso:country":"DE",
    "sg:address":"Am Finther Wald",
    "sg:city":"Mainz",
    "sg:postcode":"55126",
    "sg:province":"Rheinland-Pfalz",
    "wof:name":"Layenhof Sport Consulting Gmbh",
    "wof:placetype":"venue"
},
  "geometry": {"coordinates":[8.148883,49.974659],"type":"Point"}
}