{
  "type": "Feature",
  "properties": {
    "iso:country":"DE",
    "sg:address":"Arndtstr. 33",
    "sg:city":"Osnabr\u00fcck",
    "sg:phone":"+49 541/963870",
    "sg:postcode":"49078",
    "sg:province":"Niedersachsen",
    "wof:name":"Erhard Pause Und Werner Fl\u00fcssmeyer",
    "wof:placetype":"venue"
},
  "geometry": {"coordinates":[8.0380086899,52.2723693848],"type":"Point"}
}