{
  "type": "Feature",
  "properties": {
    "iso:country":"DE",
    "sg:address":"Klever Str. 12",
    "sg:city":"Dorsten",
    "sg:phone":"+49 2866/189038",
    "sg:postcode":"46286",
    "sg:province":"Nordrhein-Westfalen",
    "wof:name":"Transporte Mechlinski Gmbh",
    "wof:placetype":"venue"
},
  "geometry": {"coordinates":[6.9346880913,51.7499008179],"type":"Point"}
}