{
  "type": "Feature",
  "properties": {
    "iso:country":"DE",
    "sg:address":"Ledererzeile 48",
    "sg:city":"Wasserburg",
    "sg:phone":"+49 8071/1648",
    "sg:postcode":"83512",
    "sg:province":"Bayern",
    "wof:name":"H. Schwer Augenoptik",
    "wof:placetype":"venue"
},
  "geometry": {"coordinates":[12.2296218872,48.0616607666],"type":"Point"}
}