{
  "type": "Feature",
  "properties": {
    "iso:country":"DE",
    "sg:address":"J\u00e4gerhausstr. 3",
    "sg:city":"Heilbronn",
    "sg:phone":"+49 7131/164663",
    "sg:postcode":"74074",
    "sg:province":"Baden-W\u00fcrttemberg",
    "wof:name":"Magnus Loring",
    "wof:placetype":"venue"
},
  "geometry": {"coordinates":[9.2399568558,49.1407356262],"type":"Point"}
}