{
  "type": "Feature",
  "properties": {
    "iso:country":"DE",
    "sg:address":"Oberkasseler Str. 88",
    "sg:city":"D\u00fcsseldorf",
    "sg:phone":"+49 211/575437",
    "sg:postcode":"40545",
    "sg:province":"Nordrhein-Westfalen",
    "wof:name":"Wrba-wilms",
    "wof:placetype":"venue"
},
  "geometry": {"coordinates":[6.756264,51.232185],"type":"Point"}
}