{
  "type": "Feature",
  "properties": {
    "iso:country":"DE",
    "sg:address":"Birkenkamp 7",
    "sg:city":"Gelsenkirchen",
    "sg:phone":"+49 209/76937",
    "sg:postcode":"45891",
    "sg:province":"Nordrhein-Westfalen",
    "wof:name":"Destino Betonsteine Gmbh",
    "wof:placetype":"venue"
},
  "geometry": {"coordinates":[7.0895819664,51.5700378418],"type":"Point"}
}