{
  "type": "Feature",
  "properties": {
    "iso:country":"DE",
    "sg:address":"Am Goldberg 1",
    "sg:city":"Bad Oldesloe",
    "sg:phone":"+49 4531/81293",
    "sg:postcode":"23843",
    "sg:province":"Schleswig-Holstein",
    "wof:name":"Rolf Weber Architekt",
    "wof:placetype":"venue"
},
  "geometry": {"coordinates":[10.36299,53.79847],"type":"Point"}
}