{
  "type": "Feature",
  "properties": {
    "iso:country":"DE",
    "sg:address":"Rosenstr 14",
    "sg:city":"Nordheim",
    "sg:phone":"+49 7135/15530",
    "sg:postcode":"74226",
    "sg:province":"Baden-W\u00fcrttemberg",
    "wof:name":"Hmb-management Beratung Dierk Heinkelein",
    "wof:placetype":"venue"
},
  "geometry": {"coordinates":[9.103645,49.104134],"type":"Point"}
}