{
  "type": "Feature",
  "properties": {
    "iso:country":"DE",
    "sg:address":"Bahnhofstr. 10",
    "sg:city":"Glaubitz",
    "sg:postcode":"01612",
    "sg:province":"Sachsen",
    "wof:name":"Dr. Med. Lotar Klemm",
    "wof:placetype":"venue"
},
  "geometry": {"coordinates":[13.375394,51.323433],"type":"Point"}
}