{
  "type": "Feature",
  "properties": {
    "iso:country":"DE",
    "sg:address":"Hauptstr. 67",
    "sg:city":"Bad Neuenahr-Ahrweiler",
    "sg:phone":"+49 2641/25216",
    "sg:postcode":"53474",
    "sg:province":"Rheinland-Pfalz",
    "wof:name":"Gert D. Pflaumbaum Ingenieur",
    "wof:placetype":"venue"
},
  "geometry": {"coordinates":[7.142414093,50.5467720032],"type":"Point"}
}