{
  "type": "Feature",
  "properties": {
    "iso:country":"DE",
    "sg:address":"Hauptstr.",
    "sg:city":"Silz",
    "sg:postcode":"76857",
    "sg:province":"Rheinland-Pfalz",
    "wof:name":"Wild- Und Wanderpark S\u00fcdliche Weinstrasse Gmbh",
    "wof:placetype":"venue"
},
  "geometry": {"coordinates":[7.9496221542,49.1472320557],"type":"Point"}
}