{
  "type": "Feature",
  "properties": {
    "iso:country":"DE",
    "sg:address":"Hattenhofer Str. 14",
    "sg:city":"G\u00f6ppingen",
    "sg:phone":"+49 7161/41249",
    "sg:postcode":"73035",
    "sg:province":"Baden-W\u00fcrttemberg",
    "wof:name":"Fr. Melzer Mech. Werkstatt",
    "wof:placetype":"venue"
},
  "geometry": {"coordinates":[9.614612,48.668255],"type":"Point"}
}