{
  "type": "Feature",
  "properties": {
    "iso:country":"DE",
    "sg:address":"Nassaustr. 37",
    "sg:city":"Hofheim",
    "sg:phone":"+49 6122/8792",
    "sg:postcode":"65719",
    "sg:province":"Hessen",
    "wof:name":"Pfister & Co. Gmbh",
    "wof:placetype":"venue"
},
  "geometry": {"coordinates":[8.38197,50.071171],"type":"Point"}
}