{
  "type": "Feature",
  "properties": {
    "iso:country":"DE",
    "sg:address":"Hauptstr. 80",
    "sg:city":"Oestrich-Winkel",
    "sg:phone":"+49 6723/2078",
    "sg:postcode":"65375",
    "sg:province":"Hessen",
    "wof:name":"Germontsches Weingut Weinanbau",
    "wof:placetype":"venue"
},
  "geometry": {"coordinates":[8.0059890747,49.9978904724],"type":"Point"}
}