{
  "type": "Feature",
  "properties": {
    "iso:country":"DE",
    "sg:address":"Hannoversche Str. 30a",
    "sg:city":"Celle",
    "sg:phone":"+49 5141/992940",
    "sg:postcode":"29221",
    "sg:province":"Niedersachsen",
    "wof:name":"Goldex Handels- Und Consulting Gmbh",
    "wof:placetype":"venue"
},
  "geometry": {"coordinates":[10.079202652,52.615272522],"type":"Point"}
}