{
  "type": "Feature",
  "properties": {
    "iso:country":"DE",
    "sg:address":"Steinhausstr. 21",
    "sg:city":"Hagen",
    "sg:phone":"+49 2331/64367",
    "sg:postcode":"58099",
    "sg:province":"Nordrhein-Westfalen",
    "wof:name":"Kraftfahrzeug-sachverst\u00e4ndigen B\u00fcro Hugo Feldberg Gmbh",
    "wof:placetype":"venue"
},
  "geometry": {"coordinates":[7.4722862244,51.4017372131],"type":"Point"}
}