{
  "type": "Feature",
  "properties": {
    "iso:country":"DE",
    "sg:address":"Egelhaafstr. 20",
    "sg:city":"Stuttgart",
    "sg:phone":"+49 711/742545",
    "sg:postcode":"70565",
    "sg:province":"Baden-W\u00fcrttemberg",
    "wof:name":"F. Riehm",
    "wof:placetype":"venue"
},
  "geometry": {"coordinates":[9.1082487106,48.716835022],"type":"Point"}
}