{
  "type": "Feature",
  "properties": {
    "iso:country":"DE",
    "sg:address":"Trifelsstr. 7",
    "sg:city":"Germersheim",
    "sg:phone":"+49 7274/1330",
    "sg:postcode":"76726",
    "sg:province":"Rheinland-Pfalz",
    "wof:name":"Wolfgang Pirron Architekt",
    "wof:placetype":"venue"
},
  "geometry": {"coordinates":[8.358888,49.211811],"type":"Point"}
}