{
  "type": "Feature",
  "properties": {
    "iso:country":"DE",
    "sg:address":"St\u00fcbeweg 64",
    "sg:city":"Freiburg",
    "sg:phone":"+49 761/5596560",
    "sg:postcode":"79108",
    "sg:province":"Baden-W\u00fcrttemberg",
    "wof:name":"G. Konzmann & Co Kg",
    "wof:placetype":"venue"
},
  "geometry": {"coordinates":[7.8503241539,48.0277748108],"type":"Point"}
}