{
  "type": "Feature",
  "properties": {
    "iso:country":"DE",
    "sg:address":"Tiefer Weg 31",
    "sg:city":"Delmenhorst",
    "sg:phone":"+49 4221/72309",
    "sg:postcode":"27749",
    "sg:province":"Niedersachsen",
    "wof:name":"Arwed Hampel",
    "wof:placetype":"venue"
},
  "geometry": {"coordinates":[8.6491413116,53.0454330444],"type":"Point"}
}