{
  "type": "Feature",
  "properties": {
    "iso:country":"DE",
    "sg:address":"Emsstr. 15",
    "sg:city":"Emsdetten",
    "sg:phone":"+49 2572/7370",
    "sg:postcode":"48282",
    "sg:province":"Nordrhein-Westfalen",
    "wof:name":"J. Telger Augenoptiker",
    "wof:placetype":"venue"
},
  "geometry": {"coordinates":[7.5298171043,52.1758270264],"type":"Point"}
}