{
  "type": "Feature",
  "properties": {
    "iso:country":"DE",
    "sg:address":"Bollwerkstr. 32",
    "sg:city":"Emden",
    "sg:phone":"+49 4921/25612",
    "sg:postcode":"26725",
    "sg:province":"Niedersachsen",
    "wof:name":"B. Scharf Steinmetz",
    "wof:placetype":"venue"
},
  "geometry": {"coordinates":[7.2100729942,53.368850708],"type":"Point"}
}