{
  "type": "Feature",
  "properties": {
    "iso:country":"DE",
    "sg:address":"N\u00fcrnberger Str. 2a",
    "sg:city":"Hanau",
    "sg:phone":"+49 6181/20144",
    "sg:postcode":"63450",
    "sg:province":"Hessen",
    "wof:name":"Verband Deutscher Volks- B\u00fchnenvereine E. V.",
    "wof:placetype":"venue"
},
  "geometry": {"coordinates":[8.9228544235,50.1313552856],"type":"Point"}
}