{
  "type": "Feature",
  "properties": {
    "iso:country":"DE",
    "sg:address":"Siedlerstr. 2",
    "sg:city":"K\u00f6tz",
    "sg:phone":"+49 8221/6415",
    "sg:postcode":"89359",
    "sg:province":"Bayern",
    "wof:name":"Erna Gro\u00dfmann",
    "wof:placetype":"venue"
},
  "geometry": {"coordinates":[10.2941551208,48.417678833],"type":"Point"}
}