{
  "type": "Feature",
  "properties": {
    "iso:country":"DE",
    "sg:address":"Nuesslerkamp 74",
    "sg:city":"Hamburg",
    "sg:phone":"+49 40/64221984",
    "sg:postcode":"22175",
    "sg:province":"Hamburg",
    "wof:name":"Die Griechischen Inseln",
    "wof:placetype":"venue"
},
  "geometry": {"coordinates":[10.093446,53.622742],"type":"Point"}
}