{
  "type": "Feature",
  "properties": {
    "iso:country":"DE",
    "sg:address":"Kolpingstr. 11",
    "sg:city":"Oberhausen-Rheinhausen",
    "sg:phone":"+49 7254/2104",
    "sg:postcode":"68794",
    "sg:province":"Baden-W\u00fcrttemberg",
    "wof:name":"Kath. \u00f6ffentliche Bibliothek St. Philippus Und Jakobus",
    "wof:placetype":"venue"
},
  "geometry": {"coordinates":[8.475407,49.270309],"type":"Point"}
}