{
  "type": "Feature",
  "properties": {
    "iso:country":"DE",
    "sg:address":"Engelsholt 157",
    "sg:city":"M\u00f6nchengladbach",
    "sg:phone":"+49 2161/592679",
    "sg:postcode":"41069",
    "sg:province":"Nordrhein-Westfalen",
    "wof:name":"Grimm",
    "wof:placetype":"venue"
},
  "geometry": {"coordinates":[6.40562,51.174511],"type":"Point"}
}