{
  "type": "Feature",
  "properties": {
    "iso:country":"DE",
    "sg:address":"Schulstr. 2",
    "sg:city":"Stuttgart",
    "sg:phone":"+49 711/229810",
    "sg:postcode":"70173",
    "sg:province":"Baden-W\u00fcrttemberg",
    "wof:name":"Korb-mayer Gmbh",
    "wof:placetype":"venue"
},
  "geometry": {"coordinates":[9.1777944565,48.7755699158],"type":"Point"}
}