{
  "type": "Feature",
  "properties": {
    "iso:country":"DE",
    "sg:address":"Stuttgarter Str. 28",
    "sg:city":"Ditzingen",
    "sg:phone":"+49 7156/33988",
    "sg:postcode":"71254",
    "sg:province":"Baden-W\u00fcrttemberg",
    "wof:name":"Hermann Reuter Immobilienberater",
    "wof:placetype":"venue"
},
  "geometry": {"coordinates":[9.067905,48.824329],"type":"Point"}
}