{
  "type": "Feature",
  "properties": {
    "iso:country":"DE",
    "sg:address":"Vorwerk 7b",
    "sg:city":"Lengefeld",
    "sg:phone":"+49 37367/3020",
    "sg:postcode":"09514",
    "sg:province":"Sachsen",
    "wof:name":"Florian Br\u00e4uer",
    "wof:placetype":"venue"
},
  "geometry": {"coordinates":[13.1730289459,50.7119827271],"type":"Point"}
}