{
  "type": "Feature",
  "properties": {
    "iso:country":"DE",
    "sg:address":"Ro\u00dfbergstr. 34",
    "sg:city":"Stuttgart",
    "sg:phone":"+49 711/261977",
    "sg:postcode":"70188",
    "sg:province":"Baden-W\u00fcrttemberg",
    "wof:name":"Maurice Aouchta Architekt",
    "wof:placetype":"venue"
},
  "geometry": {"coordinates":[9.206054,48.784462],"type":"Point"}
}