{
  "type": "Feature",
  "properties": {
    "iso:country":"DE",
    "sg:address":"Schnelth\u00f6rn 28",
    "sg:city":"Werlte",
    "sg:postcode":"49757",
    "sg:province":"Niedersachsen",
    "wof:name":"Ilotec Kg",
    "wof:placetype":"venue"
},
  "geometry": {"coordinates":[7.67448,52.832199],"type":"Point"}
}