{
  "type": "Feature",
  "properties": {
    "iso:country":"DE",
    "sg:address":"Kantorie 89",
    "sg:city":"Essen",
    "sg:phone":"+49 201/471202",
    "sg:postcode":"45134",
    "sg:province":"Nordrhein-Westfalen",
    "wof:name":"Dr. Eike Dieter Benke Rechtsanwalt",
    "wof:placetype":"venue"
},
  "geometry": {"coordinates":[7.0475029945,51.4180755615],"type":"Point"}
}