{
  "type": "Feature",
  "properties": {
    "iso:country":"DE",
    "sg:address":"Riehler Str. 225",
    "sg:city":"K\u00f6ln",
    "sg:phone":"+49 221/7607861",
    "sg:postcode":"50735",
    "sg:province":"Nordrhein-Westfalen",
    "wof:name":"F. Zinke",
    "wof:placetype":"venue"
},
  "geometry": {"coordinates":[6.980349,50.962414],"type":"Point"}
}