{
  "type": "Feature",
  "properties": {
    "iso:country":"DE",
    "sg:address":"Neuer Weg 29",
    "sg:city":"Norden",
    "sg:phone":"+49 4931/2112",
    "sg:postcode":"26506",
    "sg:province":"Niedersachsen",
    "wof:name":"K. Weissig",
    "wof:placetype":"venue"
},
  "geometry": {"coordinates":[7.2103729248,53.5941123962],"type":"Point"}
}