{
  "type": "Feature",
  "properties": {
    "iso:country":"DE",
    "sg:address":"Luisenstr. 28",
    "sg:city":"Viernheim",
    "sg:phone":"+49 6204/74114",
    "sg:postcode":"68519",
    "sg:province":"Hessen",
    "wof:name":"Josef Martin",
    "wof:placetype":"venue"
},
  "geometry": {"coordinates":[8.578576,49.539516],"type":"Point"}
}