{
  "type": "Feature",
  "properties": {
    "iso:country":"DE",
    "sg:address":"Bo\u00dflerstr. 25",
    "sg:city":"Wendlingen",
    "sg:phone":"+49 7024/2728",
    "sg:postcode":"73240",
    "sg:province":"Baden-W\u00fcrttemberg",
    "wof:name":"Helmut Kaiser",
    "wof:placetype":"venue"
},
  "geometry": {"coordinates":[9.392829,48.667244],"type":"Point"}
}