{
  "type": "Feature",
  "properties": {
    "iso:country":"DE",
    "sg:address":"Am Steinwerk 4",
    "sg:city":"Dorsten",
    "sg:phone":"+49 2362/63215",
    "sg:postcode":"46284",
    "sg:province":"Nordrhein-Westfalen",
    "wof:name":"Karl-heinz Funke Architekt",
    "wof:placetype":"venue"
},
  "geometry": {"coordinates":[6.934625,51.68684],"type":"Point"}
}