{
  "type": "Feature",
  "properties": {
    "iso:country":"DE",
    "sg:address":"Margarethenstr. 11",
    "sg:city":"Sulzbach",
    "sg:phone":"+49 6028/8670",
    "sg:postcode":"63834",
    "sg:province":"Bayern",
    "wof:name":"Bernd Klettke",
    "wof:placetype":"venue"
},
  "geometry": {"coordinates":[9.1530590057,49.9148139954],"type":"Point"}
}