{
  "type": "Feature",
  "properties": {
    "iso:country":"DE",
    "sg:address":"Kortumstr. 59",
    "sg:city":"Bochum",
    "sg:phone":"+49 234/13448",
    "sg:postcode":"44787",
    "sg:province":"Nordrhein-Westfalen",
    "wof:name":"Wmf Verk.-filiale",
    "wof:placetype":"venue"
},
  "geometry": {"coordinates":[7.2170228958,51.4804153442],"type":"Point"}
}