{
  "type": "Feature",
  "properties": {
    "iso:country":"DE",
    "sg:address":"Oberlinder Str. 62",
    "sg:city":"Sonneberg",
    "sg:phone":"+49 3675/706614",
    "sg:postcode":"96515",
    "sg:province":"Th\u00fcringen",
    "wof:name":"Hubert Scheler",
    "wof:placetype":"venue"
},
  "geometry": {"coordinates":[11.176502,50.349293],"type":"Point"}
}