{
  "type": "Feature",
  "properties": {
    "iso:country":"DE",
    "sg:address":"Oberer Dallenbergweg 14a",
    "sg:city":"W\u00fcrzburg",
    "sg:phone":"+49 931/77701",
    "sg:postcode":"97082",
    "sg:province":"Bayern",
    "wof:name":"Erwin Englert Sen. Verwaltungs-gmbh",
    "wof:placetype":"venue"
},
  "geometry": {"coordinates":[9.926002,49.770683],"type":"Point"}
}