{
  "type": "Feature",
  "properties": {
    "iso:country":"DE",
    "sg:address":"Kuhgasse 11",
    "sg:city":"Obrigheim",
    "sg:phone":"+49 6359/5660",
    "sg:postcode":"67283",
    "sg:province":"Rheinland-Pfalz",
    "wof:name":"Helmut Bl\u00fcm",
    "wof:placetype":"venue"
},
  "geometry": {"coordinates":[8.1826810837,49.5829696655],"type":"Point"}
}