{
  "type": "Feature",
  "properties": {
    "iso:country":"DE",
    "sg:address":"Niederwaldstr. 18",
    "sg:city":"R\u00fcdesheim am Rhein",
    "sg:phone":"+49 6722/2332",
    "sg:postcode":"65385",
    "sg:province":"Hessen",
    "wof:name":"Konrad Berg K\u00fcchenchef",
    "wof:placetype":"venue"
},
  "geometry": {"coordinates":[7.8668560982,49.9881591797],"type":"Point"}
}