{
  "type": "Feature",
  "properties": {
    "iso:country":"DE",
    "sg:address":"Neutscher Weg 7",
    "sg:city":"Ober-Ramstadt",
    "sg:phone":"+49 6167/381",
    "sg:postcode":"64372",
    "sg:province":"Hessen",
    "wof:name":"Karl Bauer Architekt",
    "wof:placetype":"venue"
},
  "geometry": {"coordinates":[8.7379,49.78566],"type":"Point"}
}