{
  "type": "Feature",
  "properties": {
    "iso:country":"DE",
    "sg:address":"Am Zollstock 10",
    "sg:city":"Schieder-Schwalenberg",
    "sg:phone":"+49 5284/261",
    "sg:postcode":"32816",
    "sg:province":"Nordrhein-Westfalen",
    "wof:name":"Reinhard Rieger",
    "wof:placetype":"venue"
},
  "geometry": {"coordinates":[9.166265,51.894138],"type":"Point"}
}