{
  "type": "Feature",
  "properties": {
    "iso:country":"DE",
    "sg:address":"Darmst\u00e4dter Landstrasse 185",
    "sg:city":"Frankfurt",
    "sg:phone":"+49 4969/60650",
    "sg:postcode":"60598",
    "sg:province":"Hessen",
    "wof:name":"Binding-brauerei Ag",
    "wof:placetype":"venue"
},
  "geometry": {"coordinates":[8.6910295486,50.0946311951],"type":"Point"}
}