{
  "type": "Feature",
  "properties": {
    "iso:country":"DE",
    "sg:address":"Burgstr. 2-4",
    "sg:city":"Wiesbaden",
    "sg:phone":"+49 611/1470",
    "sg:postcode":"65183",
    "sg:province":"Hessen",
    "wof:name":"Fl-mobilien Leasing Gmbh",
    "wof:placetype":"venue"
},
  "geometry": {"coordinates":[8.244314,50.083599],"type":"Point"}
}