{
  "type": "Feature",
  "properties": {
    "iso:country":"DE",
    "sg:address":"Rudolf-Diesel-Str 25",
    "sg:city":"Maisach",
    "sg:phone":"+49 8142/14418",
    "sg:postcode":"82216",
    "sg:province":"Bayern",
    "wof:name":"Kunstgie\u00dferei Karl Herbich Kg",
    "wof:placetype":"venue"
},
  "geometry": {"coordinates":[11.290152,48.213734],"type":"Point"}
}