{
  "type": "Feature",
  "properties": {
    "iso:country":"DE",
    "sg:address":"Lange Str. 12",
    "sg:city":"Wangerland",
    "sg:phone":"+49 4425/1268",
    "sg:postcode":"26434",
    "sg:province":"Niedersachsen",
    "wof:name":"S. Schenk",
    "wof:placetype":"venue"
},
  "geometry": {"coordinates":[7.868368,53.59708],"type":"Point"}
}