{
  "type": "Feature",
  "properties": {
    "iso:country":"DE",
    "sg:address":"Weinstr. 93",
    "sg:city":"Edenkoben",
    "sg:phone":"+49 6323/2306",
    "sg:postcode":"67480",
    "sg:province":"Rheinland-Pfalz",
    "wof:name":"Ignaz G\u00f6ser Inh. Klaus G\u00f6ser",
    "wof:placetype":"venue"
},
  "geometry": {"coordinates":[8.1270217896,49.2825126648],"type":"Point"}
}