{
  "type": "Feature",
  "properties": {
    "iso:country":"DE",
    "sg:address":"Drachenkopf 9",
    "sg:city":"Kirchberg",
    "sg:phone":"+49 37602/64128",
    "sg:postcode":"08107",
    "sg:province":"Sachsen",
    "wof:name":"Gerolf Scheibe",
    "wof:placetype":"venue"
},
  "geometry": {"coordinates":[12.528855,50.619457],"type":"Point"}
}