{
  "type": "Feature",
  "properties": {
    "iso:country":"DE",
    "sg:address":"Am Bogen 33",
    "sg:city":"Ottobrunn",
    "sg:phone":"+49 89/6083710",
    "sg:postcode":"85521",
    "sg:province":"Bayern",
    "wof:name":"Subway Tanzbar",
    "wof:placetype":"venue"
},
  "geometry": {"coordinates":[11.666098,48.064945],"type":"Point"}
}