{
  "type": "Feature",
  "properties": {
    "iso:country":"DE",
    "sg:address":"Max-Eyth-Str. 1",
    "sg:city":"Rielasingen-Worblingen",
    "sg:phone":"+49 7731/9290",
    "sg:postcode":"78239",
    "sg:province":"Baden-W\u00fcrttemberg",
    "wof:name":"Gericke Gmbh",
    "wof:placetype":"venue"
},
  "geometry": {"coordinates":[8.845662117,47.7347984314],"type":"Point"}
}