{
  "type": "Feature",
  "properties": {
    "iso:country":"DE",
    "sg:address":"Schleuseninsel 6",
    "sg:city":"Kiel",
    "sg:postcode":"24159",
    "sg:province":"Schleswig-Holstein",
    "wof:name":"F\u00f6rdergesellschaft Lgv Knurrhahn Mbh",
    "wof:placetype":"venue"
},
  "geometry": {"coordinates":[10.1425561905,54.369720459],"type":"Point"}
}