{
  "type": "Feature",
  "properties": {
    "iso:country":"DE",
    "sg:address":"Gutenbergstr. 1",
    "sg:city":"Alzenau",
    "sg:phone":"+49 6023/2393",
    "sg:postcode":"63755",
    "sg:province":"Bayern",
    "wof:name":"Gerhard Berger Gmbh",
    "wof:placetype":"venue"
},
  "geometry": {"coordinates":[9.0607862473,50.0926704407],"type":"Point"}
}