{
  "type": "Feature",
  "properties": {
    "iso:country":"DE",
    "sg:address":"Schlo\u00dfstr. 22",
    "sg:city":"Nienburg",
    "sg:phone":"+49 34721/22478",
    "sg:postcode":"06429",
    "sg:province":"Sachsen-Anhalt",
    "wof:name":"Arthur Endl",
    "wof:placetype":"venue"
},
  "geometry": {"coordinates":[11.7699251175,51.83751297],"type":"Point"}
}