{
  "type": "Feature",
  "properties": {
    "iso:country":"DE",
    "sg:address":"Bahnhofstr. 7",
    "sg:city":"Albersdorf",
    "sg:postcode":"25767",
    "sg:province":"Schleswig-Holstein",
    "wof:name":"Itzehoer Versicherungen",
    "wof:placetype":"venue"
},
  "geometry": {"coordinates":[9.2855567932,54.1467132568],"type":"Point"}
}