{
  "type": "Feature",
  "properties": {
    "iso:country":"DE",
    "sg:address":"Kronenstr. 14",
    "sg:city":"Hannover",
    "sg:phone":"+49 511/348760",
    "sg:postcode":"30161",
    "sg:province":"Niedersachsen",
    "wof:name":"Planungsgruppe \u00d6kologie U. Umwelt Gmbh",
    "wof:placetype":"venue"
},
  "geometry": {"coordinates":[9.7437038422,52.3818283081],"type":"Point"}
}