{
  "type": "Feature",
  "properties": {
    "iso:country":"DE",
    "sg:address":"Karl-Theodor-Str. 5",
    "sg:city":"Rottach-Egern",
    "sg:phone":"+49 8022/24324",
    "sg:postcode":"83700",
    "sg:province":"Bayern",
    "wof:name":"Harry Kuchenbecker",
    "wof:placetype":"venue"
},
  "geometry": {"coordinates":[11.766536,47.68763],"type":"Point"}
}