{
  "type": "Feature",
  "properties": {
    "iso:country":"DE",
    "sg:address":"Siebenbr\u00fcckleinsgasse 6",
    "sg:city":"Schweinfurt",
    "sg:phone":"+49 9721/22270",
    "sg:postcode":"97421",
    "sg:province":"Bayern",
    "wof:name":"Albrecht-d\u00fcrer-apotheke",
    "wof:placetype":"venue"
},
  "geometry": {"coordinates":[10.231049,50.043472],"type":"Point"}
}