{
  "type": "Feature",
  "properties": {
    "iso:country":"DE",
    "sg:address":"Nohlstr. 87",
    "sg:city":"Oberhausen",
    "sg:phone":"+49 208/851313",
    "sg:postcode":"46045",
    "sg:province":"Nordrhein-Westfalen",
    "wof:name":"Advice Werbeagentur",
    "wof:placetype":"venue"
},
  "geometry": {"coordinates":[6.8570418358,51.467540741],"type":"Point"}
}