{
  "type": "Feature",
  "properties": {
    "iso:country":"DE",
    "sg:address":"Ohrenfeld 16",
    "sg:city":"Oberhausen",
    "sg:phone":"+49 208/803474",
    "sg:postcode":"46049",
    "sg:province":"Nordrhein-Westfalen",
    "wof:name":"Verm\u00f6gensverwaltung Castillo Gmbh",
    "wof:placetype":"venue"
},
  "geometry": {"coordinates":[6.8324432373,51.455657959],"type":"Point"}
}