{
  "type": "Feature",
  "properties": {
    "iso:country":"DE",
    "sg:address":"Landstr. 80",
    "sg:city":"Schwanewede",
    "sg:postcode":"28790",
    "sg:province":"Niedersachsen",
    "wof:name":"Gemeindeb\u00fccherei",
    "wof:placetype":"venue"
},
  "geometry": {"coordinates":[8.517265,53.234482],"type":"Point"}
}