{
  "type": "Feature",
  "properties": {
    "iso:country":"DE",
    "sg:address":"L\u00fcbbecker Str. 1",
    "sg:city":"Rahden",
    "sg:phone":"+49 5771/3699",
    "sg:postcode":"32369",
    "sg:province":"Nordrhein-Westfalen",
    "wof:name":"Brozio-heizungsbau",
    "wof:placetype":"venue"
},
  "geometry": {"coordinates":[8.6175413132,52.4290733337],"type":"Point"}
}