{
  "type": "Feature",
  "properties": {
    "iso:country":"DE",
    "sg:address":"Scheidtbachstr. 23 - 31",
    "sg:city":"Bergisch Gladbach",
    "sg:phone":"+49 2202/1210",
    "sg:postcode":"51469",
    "sg:province":"Nordrhein-Westfalen",
    "wof:name":"L\u00fcbbe-verwaltungs-gmbh",
    "wof:placetype":"venue"
},
  "geometry": {"coordinates":[7.131794,50.979092],"type":"Point"}
}