{
  "type": "Feature",
  "properties": {
    "iso:country":"DE",
    "sg:address":"Gro\u00df-Berliner Damm 73 E",
    "sg:city":"Berlin",
    "sg:phone":"+49 30/6399860",
    "sg:postcode":"12487",
    "sg:province":"Berlin",
    "wof:name":"Telefonbau Schneider",
    "wof:placetype":"venue"
},
  "geometry": {"coordinates":[13.5027198792,52.4432945251],"type":"Point"}
}