{
  "type": "Feature",
  "properties": {
    "iso:country":"DE",
    "sg:address":"Ferdinand-Wallbrecht-Str. 9",
    "sg:city":"Hannover",
    "sg:phone":"+49 511/629813",
    "sg:postcode":"30163",
    "sg:province":"Niedersachsen",
    "wof:name":"Gogi P\u00e4dagogisches Spielzeug",
    "wof:placetype":"venue"
},
  "geometry": {"coordinates":[9.7492389679,52.3897323608],"type":"Point"}
}