{
  "type": "Feature",
  "properties": {
    "iso:country":"DE",
    "sg:address":"Untere Torstr. 5",
    "sg:city":"Neubulach",
    "sg:phone":"+49 7053/3010",
    "sg:postcode":"75387",
    "sg:province":"Baden-W\u00fcrttemberg",
    "wof:name":"Raiffeisenbank Calw Eg",
    "wof:placetype":"venue"
},
  "geometry": {"coordinates":[8.6964683533,48.6608161926],"type":"Point"}
}