{
  "type": "Feature",
  "properties": {
    "iso:country":"DE",
    "sg:address":"Altenholzerstr.3a",
    "sg:city":"Altenholz",
    "sg:postcode":"24161",
    "sg:province":"Schleswig-Holstein",
    "wof:name":"Pissfreundlich",
    "wof:placetype":"venue"
},
  "geometry": {"coordinates":[10.134262,54.39246],"type":"Point"}
}