{
  "type": "Feature",
  "properties": {
    "iso:country":"DE",
    "sg:address":"Am Zehnthof 23",
    "sg:city":"Pulheim",
    "sg:phone":"+49 2238/969698",
    "sg:postcode":"50259",
    "sg:province":"Nordrhein-Westfalen",
    "wof:name":"Restaurant \u00c4g\u00e4is Inh. Tanju Karota",
    "wof:placetype":"venue"
},
  "geometry": {"coordinates":[6.8241510391,51.0242843628],"type":"Point"}
}