{
  "type": "Feature",
  "properties": {
    "iso:country":"DE",
    "sg:address":"Drau\u00dfgartenstr. 3",
    "sg:city":"Lutherstadt Wittenberg",
    "sg:phone":"+49 3491/611326",
    "sg:postcode":"06886",
    "sg:province":"Sachsen-Anhalt",
    "wof:name":"Pension Lilly Kretschmar",
    "wof:placetype":"venue"
},
  "geometry": {"coordinates":[12.598115921,51.8726005554],"type":"Point"}
}