{
  "type": "Feature",
  "properties": {
    "iso:country":"DE",
    "sg:address":"Am Schaafredder 8",
    "sg:city":"Kaltenkirchen",
    "sg:phone":"+49 4191/91700",
    "sg:postcode":"24568",
    "sg:province":"Schleswig-Holstein",
    "wof:name":"Werner Und Nils Feldsien Architekten",
    "wof:placetype":"venue"
},
  "geometry": {"coordinates":[9.94893,53.834084],"type":"Point"}
}