{
  "type": "Feature",
  "properties": {
    "iso:country":"DE",
    "sg:address":"Hauptstr. 26",
    "sg:city":"Iggensbach",
    "sg:phone":"+49 9903/8406",
    "sg:postcode":"94547",
    "sg:province":"Bayern",
    "wof:name":"Erich Beer",
    "wof:placetype":"venue"
},
  "geometry": {"coordinates":[13.142402,48.7299],"type":"Point"}
}