{
  "type": "Feature",
  "properties": {
    "iso:country":"DE",
    "sg:address":"Briloner Landstr. 3",
    "sg:city":"Korbach",
    "sg:phone":"+49 5631/914858",
    "sg:postcode":"34497",
    "sg:province":"Hessen",
    "wof:name":"Hans-ulrich Seppi E. K.",
    "wof:placetype":"venue"
},
  "geometry": {"coordinates":[8.870032,51.276222],"type":"Point"}
}