{
  "type": "Feature",
  "properties": {
    "iso:country":"DE",
    "sg:address":"Rosenthalstr. 6",
    "sg:city":"Saarlouis",
    "sg:phone":"+49 6831/1313",
    "sg:postcode":"66740",
    "sg:province":"Saarland",
    "wof:name":"Zitt Qattan Und Wohlauf",
    "wof:placetype":"venue"
},
  "geometry": {"coordinates":[6.754997,49.294975],"type":"Point"}
}