{
  "type": "Feature",
  "properties": {
    "iso:country":"DE",
    "sg:address":"S\u00fcdring 163 a",
    "sg:city":"Datteln",
    "sg:phone":"+49 2363/2011",
    "sg:postcode":"45711",
    "sg:province":"Nordrhein-Westfalen",
    "wof:name":"Malerbetrieb Schlierkamp E. K.",
    "wof:placetype":"venue"
},
  "geometry": {"coordinates":[7.339686,51.64901],"type":"Point"}
}