{
  "type": "Feature",
  "properties": {
    "iso:country":"DE",
    "sg:address":"Lichtenberger Str. 35",
    "sg:city":"Oberstenfeld",
    "sg:phone":"+49 7062/21040",
    "sg:postcode":"71720",
    "sg:province":"Baden-W\u00fcrttemberg",
    "wof:name":"Mms Fotostudio",
    "wof:placetype":"venue"
},
  "geometry": {"coordinates":[9.3244161606,49.0238189697],"type":"Point"}
}