{
  "type": "Feature",
  "properties": {
    "iso:country":"DE",
    "sg:address":"Alte M\u00fcnze 21",
    "sg:city":"Osnabr\u00fcck",
    "sg:phone":"+49 541/24205",
    "sg:postcode":"49074",
    "sg:province":"Niedersachsen",
    "wof:name":"Peter Berning",
    "wof:placetype":"venue"
},
  "geometry": {"coordinates":[8.0444107056,52.2732086182],"type":"Point"}
}