{
  "type": "Feature",
  "properties": {
    "iso:country":"DE",
    "sg:address":"Bergheimer Str. 81",
    "sg:city":"Heidelberg",
    "sg:phone":"+49 6221/22107",
    "sg:postcode":"69115",
    "sg:province":"Baden-W\u00fcrttemberg",
    "wof:name":"Heinrich L\u00fcder",
    "wof:placetype":"venue"
},
  "geometry": {"coordinates":[8.684782,49.407726],"type":"Point"}
}