{
  "type": "Feature",
  "properties": {
    "iso:country":"DE",
    "sg:address":"Hauptstr. 131",
    "sg:city":"Bielefeld",
    "sg:phone":"+49 521/443179",
    "sg:postcode":"33647",
    "sg:province":"Nordrhein-Westfalen",
    "wof:name":"Sam Barlak",
    "wof:placetype":"venue"
},
  "geometry": {"coordinates":[8.5074157715,51.9932136536],"type":"Point"}
}