{
  "type": "Feature",
  "properties": {
    "iso:country":"DE",
    "sg:address":"Lehmberg 9",
    "sg:city":"Kiel",
    "sg:phone":"+49 431/554737",
    "sg:postcode":"24103",
    "sg:province":"Schleswig-Holstein",
    "wof:name":"J\u00fcrgen Schnack",
    "wof:placetype":"venue"
},
  "geometry": {"coordinates":[10.1302433014,54.3301086426],"type":"Point"}
}