{
  "type": "Feature",
  "properties": {
    "iso:country":"DE",
    "sg:address":"Johannistr. 29",
    "sg:city":"Nienburg",
    "sg:phone":"+49 34721/22390",
    "sg:postcode":"06429",
    "sg:province":"Sachsen-Anhalt",
    "wof:name":"Laumer Immobilien",
    "wof:placetype":"venue"
},
  "geometry": {"coordinates":[11.7684135437,51.837474823],"type":"Point"}
}