{
  "type": "Feature",
  "properties": {
    "iso:country":"DE",
    "sg:address":"Jahnstr. 16",
    "sg:city":"Lampertheim",
    "sg:postcode":"68623",
    "sg:province":"Hessen",
    "wof:name":"Eduard Krahe Tennislehrer",
    "wof:placetype":"venue"
},
  "geometry": {"coordinates":[8.4719743729,49.6013259888],"type":"Point"}
}