{
  "type": "Feature",
  "properties": {
    "iso:country":"DE",
    "sg:address":"Geheimrat-Schott-Str. 80",
    "sg:city":"Leimen",
    "sg:phone":"+49 6224/71669",
    "sg:postcode":"69181",
    "sg:province":"Baden-W\u00fcrttemberg",
    "wof:name":"N. Bartocha",
    "wof:placetype":"venue"
},
  "geometry": {"coordinates":[8.6903085709,49.3560752869],"type":"Point"}
}