{
  "type": "Feature",
  "properties": {
    "iso:country":"DE",
    "sg:address":"Ritterstr. 20",
    "sg:city":"D\u00f6beln",
    "sg:phone":"+49 3431/710162",
    "sg:postcode":"04720",
    "sg:province":"Sachsen",
    "wof:name":"Apotheke An Der Oberbr\u00fccke Inh. G\u00fcnther",
    "wof:placetype":"venue"
},
  "geometry": {"coordinates":[13.124101,51.123489],"type":"Point"}
}