{
  "type": "Feature",
  "properties": {
    "iso:country":"DE",
    "sg:address":"Eisenhammerweg 35",
    "sg:city":"Hindelang",
    "sg:phone":"+49 8324/2592",
    "sg:postcode":"87541",
    "sg:province":"Bayern",
    "wof:name":"Gemeindearchiv",
    "wof:placetype":"venue"
},
  "geometry": {"coordinates":[10.375677,47.499321],"type":"Point"}
}