{
  "type": "Feature",
  "properties": {
    "iso:country":"DE",
    "sg:address":"Stuttgarter Str. 120",
    "sg:city":"Fellbach",
    "sg:phone":"+49 711/5209218",
    "sg:postcode":"70736",
    "sg:province":"Baden-W\u00fcrttemberg",
    "wof:name":"Redaktion Herion Aktuell Herion-werke",
    "wof:placetype":"venue"
},
  "geometry": {"coordinates":[9.2593927383,48.8115615845],"type":"Point"}
}