{
  "type": "Feature",
  "properties": {
    "iso:country":"DE",
    "sg:address":"Pritzwalker Str. 12",
    "sg:city":"Wittstock",
    "sg:phone":"+49 3394/3582",
    "sg:postcode":"16909",
    "sg:province":"Brandenburg",
    "wof:name":"Fenster Und T\u00fcren Wittstock Gmbh",
    "wof:placetype":"venue"
},
  "geometry": {"coordinates":[12.472806,53.160797],"type":"Point"}
}