{
  "type": "Feature",
  "properties": {
    "iso:country":"DE",
    "sg:address":"M\u00fchlenweg 24",
    "sg:city":"Ziethen",
    "sg:phone":"+49 4541/6575",
    "sg:postcode":"23911",
    "sg:province":"Schleswig-Holstein",
    "wof:name":"R\u00fcdiger Sch\u00f6n",
    "wof:placetype":"venue"
},
  "geometry": {"coordinates":[10.804453,53.695721],"type":"Point"}
}