{
  "type": "Feature",
  "properties": {
    "iso:country":"DE",
    "sg:address":"Antonienstr. 62",
    "sg:city":"Berlin",
    "sg:phone":"+49 30/41783116",
    "sg:postcode":"13403",
    "sg:province":"Berlin",
    "wof:name":"Poliglas Gmbh",
    "wof:placetype":"venue"
},
  "geometry": {"coordinates":[13.3108348846,52.5692825317],"type":"Point"}
}