{
  "type": "Feature",
  "properties": {
    "iso:country":"DE",
    "sg:address":"Pappelallee 11",
    "sg:city":"M\u00fcnchen",
    "sg:phone":"+49 89/1504393",
    "sg:postcode":"80995",
    "sg:province":"Bayern",
    "wof:name":"H. Herchenbach",
    "wof:placetype":"venue"
},
  "geometry": {"coordinates":[11.5119228363,48.1985397339],"type":"Point"}
}