{
  "type": "Feature",
  "properties": {
    "iso:country":"DE",
    "sg:address":"In der Brunnenwiese 22",
    "sg:city":"St. Ingbert",
    "sg:phone":"+49 6894/888121",
    "sg:postcode":"66386",
    "sg:province":"Saarland",
    "wof:name":"Freenet Kommunikations- Systeme Gmbh",
    "wof:placetype":"venue"
},
  "geometry": {"coordinates":[7.1294560432,49.2536201477],"type":"Point"}
}