{
  "type": "Feature",
  "properties": {
    "iso:country":"DE",
    "sg:address":"Tschaikowskistr. 4",
    "sg:city":"Leipzig",
    "sg:phone":"+49 341/2122141",
    "sg:postcode":"04105",
    "sg:province":"Sachsen",
    "wof:name":"Karin Hopfe",
    "wof:placetype":"venue"
},
  "geometry": {"coordinates":[12.3621177673,51.3430480957],"type":"Point"}
}