{
  "type": "Feature",
  "properties": {
    "iso:country":"DE",
    "sg:address":"Bertolt-Brecht-Str. 17",
    "sg:city":"Rostock",
    "sg:phone":"+49 381/7699166",
    "sg:postcode":"18106",
    "sg:province":"Mecklenburg-Vorpommern",
    "wof:name":"Dorothea Thurm",
    "wof:placetype":"venue"
},
  "geometry": {"coordinates":[12.0582103729,54.1223983765],"type":"Point"}
}