{
  "type": "Feature",
  "properties": {
    "iso:country":"DE",
    "sg:address":"Am Pfalzbach 26",
    "sg:city":"Heppenheim",
    "sg:phone":"+49 6253/5121",
    "sg:postcode":"64646",
    "sg:province":"Hessen",
    "wof:name":"Barbara Bitsch",
    "wof:placetype":"venue"
},
  "geometry": {"coordinates":[8.7140817642,49.6572608948],"type":"Point"}
}