{
  "type": "Feature",
  "properties": {
    "iso:country":"DE",
    "sg:address":"Kirchsteige 1",
    "sg:city":"Immenstadt",
    "sg:phone":"+49 8323/9130",
    "sg:postcode":"87509",
    "sg:province":"Bayern",
    "wof:name":"Klinik St. Michael",
    "wof:placetype":"venue"
},
  "geometry": {"coordinates":[10.1908712387,47.5683784485],"type":"Point"}
}