{
  "type": "Feature",
  "properties": {
    "iso:country":"DE",
    "sg:address":"Spandauer Damm 23",
    "sg:city":"Berlin",
    "sg:phone":"+49 30/3215392",
    "sg:postcode":"14059",
    "sg:province":"Berlin",
    "wof:name":"Casa Mediterranea",
    "wof:placetype":"venue"
},
  "geometry": {"coordinates":[13.2936639786,52.5190734863],"type":"Point"}
}