{
  "type": "Feature",
  "properties": {
    "iso:country":"DE",
    "sg:address":"Kirchstr. 24",
    "sg:city":"Borchen",
    "sg:phone":"+49 5292/603",
    "sg:postcode":"33178",
    "sg:province":"Nordrhein-Westfalen",
    "wof:name":"Meinolf T\u00f6lle",
    "wof:placetype":"venue"
},
  "geometry": {"coordinates":[8.761702,51.629311],"type":"Point"}
}