{
  "type": "Feature",
  "properties": {
    "iso:country":"DE",
    "sg:address":"Richard-Schirrmann-Weg 6",
    "sg:city":"M\u00fcnster",
    "sg:phone":"+49 251/523058",
    "sg:postcode":"48151",
    "sg:province":"Nordrhein-Westfalen",
    "wof:name":"Tier\u00e4rztliche Verrechnungs- Stelle Nordrhein-westfalen",
    "wof:placetype":"venue"
},
  "geometry": {"coordinates":[7.6146287918,51.9541969299],"type":"Point"}
}