{
  "type": "Feature",
  "properties": {
    "iso:country":"DE",
    "sg:address":"Prignitzer Str. 2",
    "sg:city":"Wittstock",
    "sg:phone":"+49 3394/443661",
    "sg:postcode":"16909",
    "sg:province":"Brandenburg",
    "wof:name":"Bornemann Verwaltungs- Und Beteiligungs-gmbh",
    "wof:placetype":"venue"
},
  "geometry": {"coordinates":[12.457079,53.163567],"type":"Point"}
}