{
  "type": "Feature",
  "properties": {
    "iso:country":"DE",
    "sg:address":"Industriestr. 3",
    "sg:city":"Drolshagen",
    "sg:phone":"+49 34322/43486",
    "sg:postcode":"57489",
    "sg:province":"Nordrhein-Westfalen",
    "wof:name":"Elektrotherm Gleisberg Gmbh",
    "wof:placetype":"venue"
},
  "geometry": {"coordinates":[13.176552,51.076424],"type":"Point"}
}