{
  "type": "Feature",
  "properties": {
    "iso:country":"DE",
    "sg:address":"Egger Str. 60",
    "sg:city":"Metten",
    "sg:phone":"+49 991/9302",
    "sg:postcode":"94526",
    "sg:province":"Bayern",
    "wof:name":"Emil Oeler",
    "wof:placetype":"venue"
},
  "geometry": {"coordinates":[12.9214601517,48.8583183289],"type":"Point"}
}