{
  "type": "Feature",
  "properties": {
    "iso:country":"DE",
    "sg:address":"Gro\u00dfe Str. 42",
    "sg:city":"Rotenburg",
    "sg:phone":"+49 4261/3493",
    "sg:postcode":"27356",
    "sg:province":"Niedersachsen",
    "wof:name":"P\u00f6ppel & Co. Spieleladen Gmbh",
    "wof:placetype":"venue"
},
  "geometry": {"coordinates":[9.4053201675,53.1106071472],"type":"Point"}
}