{
  "type": "Feature",
  "properties": {
    "iso:country":"DE",
    "sg:address":"Hanauer Str. 73",
    "sg:city":"Rheinau",
    "sg:phone":"+49 7844/530",
    "sg:postcode":"77866",
    "sg:province":"Baden-W\u00fcrttemberg",
    "wof:name":"Willi Hauss",
    "wof:placetype":"venue"
},
  "geometry": {"coordinates":[7.8837909698,48.6435852051],"type":"Point"}
}