{
  "type": "Feature",
  "properties": {
    "iso:country":"DE",
    "sg:address":"Schilkseer Str. 179",
    "sg:city":"Kiel",
    "sg:phone":"+49 431/373395",
    "sg:postcode":"24159",
    "sg:province":"Schleswig-Holstein",
    "wof:name":"Giesela Zeiske",
    "wof:placetype":"venue"
},
  "geometry": {"coordinates":[10.16754,54.42289],"type":"Point"}
}