{
  "type": "Feature",
  "properties": {
    "iso:country":"DE",
    "sg:address":"Steinstr. 38",
    "sg:city":"Kleve",
    "sg:phone":"+49 2821/9009",
    "sg:postcode":"47533",
    "sg:province":"Nordrhein-Westfalen",
    "wof:name":"Renova Gmbh",
    "wof:placetype":"venue"
},
  "geometry": {"coordinates":[6.1502599716,51.7971954346],"type":"Point"}
}