{
  "type": "Feature",
  "properties": {
    "iso:country":"DE",
    "sg:address":"Dr.-Eugen-Sch\u00f6n-Str. 14",
    "sg:city":"Volkach",
    "sg:phone":"+49 9381/9848",
    "sg:postcode":"97332",
    "sg:province":"Bayern",
    "wof:name":"Ewb Einbauk\u00fcchen Werner B\u00e4uerlein Gmbh",
    "wof:placetype":"venue"
},
  "geometry": {"coordinates":[10.2310590744,49.8636703491],"type":"Point"}
}