{
  "type": "Feature",
  "properties": {
    "iso:country":"DE",
    "sg:address":"Rathausstr. 56",
    "sg:city":"Winsen",
    "sg:phone":"+49 4171/2382",
    "sg:postcode":"21423",
    "sg:province":"Niedersachsen",
    "wof:name":"F. J. H. Wegener E. K.",
    "wof:placetype":"venue"
},
  "geometry": {"coordinates":[10.2064352036,53.3607635498],"type":"Point"}
}