{
  "type": "Feature",
  "properties": {
    "iso:country":"DE",
    "sg:address":"Steubenstr. 61",
    "sg:city":"Essen",
    "sg:phone":"+49 201/286121",
    "sg:postcode":"45138",
    "sg:province":"Nordrhein-Westfalen",
    "wof:name":"Dirk Grefer Steuerberater",
    "wof:placetype":"venue"
},
  "geometry": {"coordinates":[7.0286989212,51.4488792419],"type":"Point"}
}