{
  "type": "Feature",
  "properties": {
    "iso:country":"DE",
    "sg:address":"Dorfstr. 44",
    "sg:city":"Niedertrebra",
    "sg:phone":"+49 36461/20937",
    "sg:postcode":"99518",
    "sg:province":"Th\u00fcringen",
    "wof:name":"Tdc-gmbh",
    "wof:placetype":"venue"
},
  "geometry": {"coordinates":[11.5848913193,51.0712852478],"type":"Point"}
}