{
  "type": "Feature",
  "properties": {
    "iso:country":"DE",
    "sg:address":"Egerstr. 78",
    "sg:city":"M\u00f6nchengladbach",
    "sg:phone":"+49 2166/619635",
    "sg:postcode":"41236",
    "sg:province":"Nordrhein-Westfalen",
    "wof:name":"Melitha",
    "wof:placetype":"venue"
},
  "geometry": {"coordinates":[6.4430160522,51.1585998535],"type":"Point"}
}