{
  "type": "Feature",
  "properties": {
    "iso:country":"DE",
    "sg:address":"Arnimstr. 16",
    "sg:city":"Peine",
    "sg:phone":"+49 5171/16560",
    "sg:postcode":"31224",
    "sg:province":"Niedersachsen",
    "wof:name":"Datentechnik Vollmer Beteiligungs Gmbh",
    "wof:placetype":"venue"
},
  "geometry": {"coordinates":[10.249624,52.329742],"type":"Point"}
}