{
  "type": "Feature",
  "properties": {
    "iso:country":"DE",
    "sg:address":"Finkenweg 8",
    "sg:city":"Warendorf",
    "sg:phone":"+49 2581/4167",
    "sg:postcode":"48231",
    "sg:province":"Nordrhein-Westfalen",
    "wof:name":"Rainer H\u00f6velmann Und Busmann Architekten",
    "wof:placetype":"venue"
},
  "geometry": {"coordinates":[7.953127,51.920361],"type":"Point"}
}