{
  "type": "Feature",
  "properties": {
    "iso:country":"DE",
    "sg:address":"Am Buchenberg 1",
    "sg:city":"Staufenberg",
    "sg:phone":"+49 6406/4777",
    "sg:postcode":"35460",
    "sg:province":"Hessen",
    "wof:name":"Waldsch\u00e4nke",
    "wof:placetype":"venue"
},
  "geometry": {"coordinates":[8.745054245,50.6462135315],"type":"Point"}
}