{
  "type": "Feature",
  "properties": {
    "iso:country":"DE",
    "sg:address":"Carl-Zeiss-Str. 2-4 POSTFACH 100145",
    "sg:city":"Heiligenhaus",
    "sg:phone":"+49 4920/5698380",
    "sg:postcode":"42566",
    "sg:province":"Nordrhein-Westfalen",
    "wof:name":"Diag Diesner Aluminium-gie\u00dferei Gmbh & Co. Kg",
    "wof:placetype":"venue"
},
  "geometry": {"coordinates":[6.97172,51.32653],"type":"Point"}
}