{
  "type": "Feature",
  "properties": {
    "iso:country":"DE",
    "sg:address":"J\u00e4gerstr. 21",
    "sg:city":"D\u00fcsseldorf",
    "sg:phone":"+49 211/219331",
    "sg:postcode":"40231",
    "sg:province":"Nordrhein-Westfalen",
    "wof:name":"Druckerei Pesch",
    "wof:placetype":"venue"
},
  "geometry": {"coordinates":[6.837481,51.2038],"type":"Point"}
}