{
  "type": "Feature",
  "properties": {
    "iso:country":"DE",
    "sg:address":"Werner-Von-Siemens-Str. 1::",
    "sg:city":"Augsburg",
    "sg:phone":"+49 821/59030",
    "sg:postcode":"86159",
    "sg:province":"Bayern",
    "wof:name":"Wanderer Werke Ag",
    "wof:placetype":"venue"
},
  "geometry": {"coordinates":[10.906253,48.339912],"type":"Point"}
}