{
  "type": "Feature",
  "properties": {
    "iso:country":"DE",
    "sg:address":"Leipziger Str. 60",
    "sg:city":"Magdeburg",
    "sg:phone":"+49 391/6226665",
    "sg:postcode":"39112",
    "sg:province":"Sachsen-Anhalt",
    "wof:name":"Stephan Heidel Praxis F\u00fcr Ergotherapie",
    "wof:placetype":"venue"
},
  "geometry": {"coordinates":[11.619736,52.114983],"type":"Point"}
}