{
  "type": "Feature",
  "properties": {
    "iso:country":"DE",
    "sg:address":"Marktplatz 1",
    "sg:city":"Engen",
    "sg:phone":"+49 7733/7500",
    "sg:postcode":"78234",
    "sg:province":"Baden-W\u00fcrttemberg",
    "wof:name":"J. Krug",
    "wof:placetype":"venue"
},
  "geometry": {"coordinates":[8.7707920074,47.8523712158],"type":"Point"}
}