{
  "type": "Feature",
  "properties": {
    "iso:country":"DE",
    "sg:address":"L\u00fcckingstr. 2",
    "sg:city":"Bonn",
    "sg:phone":"+49 228/281281",
    "sg:postcode":"53127",
    "sg:province":"Nordrhein-Westfalen",
    "wof:name":"Beim Mahler",
    "wof:placetype":"venue"
},
  "geometry": {"coordinates":[7.0807452202,50.7012748718],"type":"Point"}
}