{
  "type": "Feature",
  "properties": {
    "iso:country":"DE",
    "sg:address":"Am Buchauer Berg 8-10",
    "sg:city":"Pegnitz",
    "sg:phone":"+49 9241/2019",
    "sg:postcode":"91257",
    "sg:province":"Bayern",
    "wof:name":"Jura-br\u00e4u Inh. Wilhelm Knopf",
    "wof:placetype":"venue"
},
  "geometry": {"coordinates":[11.540547,49.758469],"type":"Point"}
}