{
  "type": "Feature",
  "properties": {
    "iso:country":"DE",
    "sg:address":"Martinusstr. 30",
    "sg:city":"Kaarst",
    "sg:phone":"+49 2131/602331",
    "sg:postcode":"41564",
    "sg:province":"Nordrhein-Westfalen",
    "wof:name":"Raum-klima Dieter W. Odendahl Gmbh",
    "wof:placetype":"venue"
},
  "geometry": {"coordinates":[6.613101,51.228382],"type":"Point"}
}