{
  "type": "Feature",
  "properties": {
    "iso:country":"DE",
    "sg:address":"Kirgelweg 8",
    "sg:city":"Gaildorf",
    "sg:phone":"+49 7971/23222",
    "sg:postcode":"74405",
    "sg:province":"Baden-W\u00fcrttemberg",
    "wof:name":"Walter Rieg",
    "wof:placetype":"venue"
},
  "geometry": {"coordinates":[9.7661895752,48.9949188232],"type":"Point"}
}