{
  "type": "Feature",
  "properties": {
    "iso:country":"DE",
    "sg:address":"Moltkestr. 5",
    "sg:city":"Neuss",
    "sg:phone":"+49 2131/858905",
    "sg:postcode":"41464",
    "sg:province":"Nordrhein-Westfalen",
    "wof:name":"L. Ewald Gravieranstalt",
    "wof:placetype":"venue"
},
  "geometry": {"coordinates":[6.6770992279,51.1969299316],"type":"Point"}
}