{
  "type": "Feature",
  "properties": {
    "iso:country":"DE",
    "sg:address":"Bahnhofstr 25",
    "sg:city":"Nordhausen",
    "sg:phone":"+49 3631/6360",
    "sg:postcode":"99734",
    "sg:province":"Th\u00fcringen",
    "wof:name":"Nordbrand Nordhausen Gmbh",
    "wof:placetype":"venue"
},
  "geometry": {"coordinates":[10.78902,51.493992],"type":"Point"}
}