{
  "type": "Feature",
  "properties": {
    "iso:country":"DE",
    "sg:address":"Hindenburgstr. 38",
    "sg:city":"Garmisch-Partenkirchen",
    "sg:phone":"+49 8821/51733",
    "sg:postcode":"82467",
    "sg:province":"Bayern",
    "wof:name":"Musikschule Garm.-partenkirchen E.v.",
    "wof:placetype":"venue"
},
  "geometry": {"coordinates":[11.099360466,47.4971008301],"type":"Point"}
}