{
  "type": "Feature",
  "properties": {
    "iso:country":"DE",
    "sg:address":"Schwalbacher Stra\u00dfe 101",
    "sg:city":"Eltville am Rhein",
    "sg:phone":"+49 6123",
    "sg:postcode":"65343",
    "sg:province":"Hessen",
    "wof:name":"Jonas - Das Weingut",
    "wof:placetype":"venue"
},
  "geometry": {"coordinates":[8.1172533035,50.0369338989],"type":"Point"}
}