{
  "type": "Feature",
  "properties": {
    "iso:country":"DE",
    "sg:address":"Eisenbahnstr. 8",
    "sg:city":"Fl\u00f6rsheim-Dalsheim",
    "sg:phone":"+49 6243/8650",
    "sg:postcode":"67592",
    "sg:province":"Rheinland-Pfalz",
    "wof:name":"K. H. Merkel Weinanbau",
    "wof:placetype":"venue"
},
  "geometry": {"coordinates":[8.2089958191,49.6632194519],"type":"Point"}
}