{
  "type": "Feature",
  "properties": {
    "iso:country":"DE",
    "sg:address":"Wittener Str. 142",
    "sg:city":"Witten",
    "sg:phone":"+49 2302/73041",
    "sg:postcode":"58456",
    "sg:province":"Nordrhein-Westfalen",
    "wof:name":"Rudolf Damm",
    "wof:placetype":"venue"
},
  "geometry": {"coordinates":[7.2663612366,51.4130821228],"type":"Point"}
}