{
  "type": "Feature",
  "properties": {
    "iso:country":"DE",
    "sg:address":"Westerwischweg 18",
    "sg:city":"Cuxhaven",
    "sg:phone":"+49 4721/53964",
    "sg:postcode":"27474",
    "sg:province":"Niedersachsen",
    "wof:name":"Dirk Saul",
    "wof:placetype":"venue"
},
  "geometry": {"coordinates":[8.6933259964,53.8592071533],"type":"Point"}
}