{
  "type": "Feature",
  "properties": {
    "iso:country":"DE",
    "sg:address":"Gro\u00df D\u00f6rgen 3",
    "sg:city":"Hasel\u00fcnne",
    "sg:phone":"+49 5931/6675",
    "sg:postcode":"49740",
    "sg:province":"Niedersachsen",
    "wof:name":"Paul Wulf",
    "wof:placetype":"venue"
},
  "geometry": {"coordinates":[7.383122,52.690769],"type":"Point"}
}