{
  "type": "Feature",
  "properties": {
    "iso:country":"DE",
    "sg:address":"Ludwigsplatz 13 - 15",
    "sg:city":"Giessen",
    "sg:postcode":"35390",
    "sg:province":"Hessen",
    "wof:name":"Westpruefung",
    "wof:placetype":"venue"
},
  "geometry": {"coordinates":[8.680074,50.582844],"type":"Point"}
}