{
  "type": "Feature",
  "properties": {
    "iso:country":"DE",
    "sg:address":"Die Meine 16",
    "sg:city":"Langelsheim",
    "sg:phone":"+49 5326/7115",
    "sg:postcode":"38685",
    "sg:province":"Niedersachsen",
    "wof:name":"Altes Backhaus M. Windisch",
    "wof:placetype":"venue"
},
  "geometry": {"coordinates":[10.3205919266,51.9084892273],"type":"Point"}
}