{
  "type": "Feature",
  "properties": {
    "iso:country":"DE",
    "sg:address":"Ernst-Th\u00e4lmann-Str. 28",
    "sg:city":"Viernau",
    "sg:phone":"+49 36847/30134",
    "sg:postcode":"98547",
    "sg:province":"Th\u00fcringen",
    "wof:name":"Horst Albrecht",
    "wof:placetype":"venue"
},
  "geometry": {"coordinates":[10.5573863983,50.6629676819],"type":"Point"}
}