{
  "type": "Feature",
  "properties": {
    "iso:country":"DE",
    "sg:address":"Clamorstr. 3",
    "sg:city":"Bohmte",
    "sg:phone":"+49 5471/2931",
    "sg:postcode":"49163",
    "sg:province":"Niedersachsen",
    "wof:name":"T. Arslan",
    "wof:placetype":"venue"
},
  "geometry": {"coordinates":[8.3082132339,52.3571395874],"type":"Point"}
}