{
  "type": "Feature",
  "properties": {
    "iso:country":"DE",
    "sg:address":"B\u00f6dingerstr. 13",
    "sg:city":"K\u00f6ln",
    "sg:phone":"+49 2232/68496",
    "sg:postcode":"50997",
    "sg:province":"Nordrhein-Westfalen",
    "wof:name":"Bertram Effer",
    "wof:placetype":"venue"
},
  "geometry": {"coordinates":[6.930065,50.862347],"type":"Point"}
}