{
  "type": "Feature",
  "properties": {
    "iso:country":"DE",
    "sg:address":"Hochweg 38",
    "sg:city":"Thierhaupten",
    "sg:phone":"+49 8271/7759",
    "sg:postcode":"86672",
    "sg:province":"Bayern",
    "wof:name":"Herbert Hawuda Architekt",
    "wof:placetype":"venue"
},
  "geometry": {"coordinates":[10.918252,48.568409],"type":"Point"}
}