{
  "type": "Feature",
  "properties": {
    "iso:country":"DE",
    "sg:address":"Kurf\u00fcrstenstr. 132",
    "sg:city":"Berlin",
    "sg:postcode":"10785",
    "sg:province":"Berlin",
    "wof:name":"Gsw Verwaltungs- Und Betriebs- Ges. Mbh & Co. Grundst\u00fccksges.",
    "wof:placetype":"venue"
},
  "geometry": {"coordinates":[13.354673,52.501755],"type":"Point"}
}