{
  "type": "Feature",
  "properties": {
    "iso:country":"DE",
    "sg:address":"Rudolf-Breitscheid-Str. 46",
    "sg:city":"Schwanebeck",
    "sg:phone":"+49 39424/7056",
    "sg:postcode":"39397",
    "sg:province":"Sachsen-Anhalt",
    "wof:name":"S. Thomas Ingenieur",
    "wof:placetype":"venue"
},
  "geometry": {"coordinates":[11.127204895,51.9646034241],"type":"Point"}
}