{
  "type": "Feature",
  "properties": {
    "iso:country":"DE",
    "sg:address":"Am Feldrain 15",
    "sg:city":"Fuldatal",
    "sg:phone":"+49 561/811448",
    "sg:postcode":"34233",
    "sg:province":"Hessen",
    "wof:name":"Karl-heinz Siebert",
    "wof:placetype":"venue"
},
  "geometry": {"coordinates":[9.5337,51.350822],"type":"Point"}
}