{
  "type": "Feature",
  "properties": {
    "iso:country":"DE",
    "sg:address":"Laurentiusstr. 3",
    "sg:city":"Ansbach",
    "sg:phone":"+49 981/61288",
    "sg:postcode":"91522",
    "sg:province":"Bayern",
    "wof:name":"Ev. Luth. Pfarramt",
    "wof:placetype":"venue"
},
  "geometry": {"coordinates":[10.5161628723,49.2784156799],"type":"Point"}
}