{
  "type": "Feature",
  "properties": {
    "iso:country":"DE",
    "sg:address":"Berenbrock",
    "sg:city":"L\u00fcdinghausen",
    "sg:phone":"+49 2591/3343",
    "sg:postcode":"59348",
    "sg:province":"Nordrhein-Westfalen",
    "wof:name":"Christoph Joerges",
    "wof:placetype":"venue"
},
  "geometry": {"coordinates":[7.425728,51.789719],"type":"Point"}
}