{
  "type": "Feature",
  "properties": {
    "iso:country":"DE",
    "sg:address":"Dammbecker Str. 15",
    "sg:city":"Bobitz",
    "sg:phone":"+49 38424/20253",
    "sg:postcode":"23996",
    "sg:province":"Mecklenburg-Vorpommern",
    "wof:name":"Landhof Bobitz Eg",
    "wof:placetype":"venue"
},
  "geometry": {"coordinates":[11.360015,53.796368],"type":"Point"}
}