{
  "type": "Feature",
  "properties": {
    "iso:country":"DE",
    "sg:address":"Am M\u00fcggelsee 4",
    "sg:city":"Hildesheim",
    "sg:phone":"+49 5121/53151",
    "sg:postcode":"31135",
    "sg:province":"Niedersachsen",
    "wof:name":"Freibad M\u00fcggelsee",
    "wof:placetype":"venue"
},
  "geometry": {"coordinates":[9.9647951126,52.1662559509],"type":"Point"}
}