{
  "type": "Feature",
  "properties": {
    "iso:country":"DE",
    "sg:address":"Abteistr. 11",
    "sg:city":"M\u00f6nchengladbach",
    "sg:phone":"+49 2161/14528",
    "sg:postcode":"41061",
    "sg:province":"Nordrhein-Westfalen",
    "wof:name":"M. R. Consulting Gmbh",
    "wof:placetype":"venue"
},
  "geometry": {"coordinates":[6.4348740578,51.1931381226],"type":"Point"}
}