{
  "type": "Feature",
  "properties": {
    "iso:country":"DE",
    "sg:address":"Eisenbahnstr. 26",
    "sg:city":"Rottweil",
    "sg:phone":"+49 741/18040",
    "sg:postcode":"78628",
    "sg:province":"Baden-W\u00fcrttemberg",
    "wof:name":"Jens Oetting Gmbh",
    "wof:placetype":"venue"
},
  "geometry": {"coordinates":[8.639016,48.164413],"type":"Point"}
}