{
  "type": "Feature",
  "properties": {
    "iso:country":"DE",
    "sg:address":"Duisburger Str. 15",
    "sg:city":"Dinslaken",
    "sg:phone":"+49 2064/59144",
    "sg:postcode":"46535",
    "sg:province":"Nordrhein-Westfalen",
    "wof:name":"Baedeker Buch- Und Kunsthandlung",
    "wof:placetype":"venue"
},
  "geometry": {"coordinates":[6.7339601517,51.5615272522],"type":"Point"}
}