{
  "type": "Feature",
  "properties": {
    "iso:country":"DE",
    "sg:address":"Obergasse 8",
    "sg:city":"Penig",
    "sg:phone":"+49 37381/82230",
    "sg:postcode":"09322",
    "sg:province":"Sachsen",
    "wof:name":"U. Schmidt Immobilienmakler",
    "wof:placetype":"venue"
},
  "geometry": {"coordinates":[12.7071208954,50.9326171875],"type":"Point"}
}