{
  "type": "Feature",
  "properties": {
    "iso:country":"DE",
    "sg:address":"Bahnhofstr. 31",
    "sg:city":"Gernrode",
    "sg:phone":"+49 39485/365",
    "sg:postcode":"06507",
    "sg:province":"Sachsen-Anhalt",
    "wof:name":"Foto Gregor",
    "wof:placetype":"venue"
},
  "geometry": {"coordinates":[11.1441488266,51.7253112793],"type":"Point"}
}