{
  "type": "Feature",
  "properties": {
    "iso:country":"DE",
    "sg:address":"Uhde-Bernays-Weg 7",
    "sg:city":"Starnberg",
    "sg:phone":"+49 8151/2380",
    "sg:postcode":"82319",
    "sg:province":"Bayern",
    "wof:name":"Klaus Pickert Steuerberater",
    "wof:placetype":"venue"
},
  "geometry": {"coordinates":[11.3269577026,47.9863586426],"type":"Point"}
}