{
  "type": "Feature",
  "properties": {
    "iso:country":"DE",
    "sg:address":"Kirchtalstr. 11",
    "sg:city":"Stuttgart",
    "sg:phone":"+49 711/875191",
    "sg:postcode":"70435",
    "sg:province":"Baden-W\u00fcrttemberg",
    "wof:name":"Karl Belschner Farben Und Lacke",
    "wof:placetype":"venue"
},
  "geometry": {"coordinates":[9.169801,48.833195],"type":"Point"}
}