{
  "type": "Feature",
  "properties": {
    "iso:country":"DE",
    "sg:address":"Eversumer Str. 61",
    "sg:city":"Olfen",
    "sg:phone":"+49 2595/98317",
    "sg:postcode":"59399",
    "sg:province":"Nordrhein-Westfalen",
    "wof:name":"Holzbau Vennemann & Strauch Gmbh",
    "wof:placetype":"venue"
},
  "geometry": {"coordinates":[7.3312158585,51.6994972229],"type":"Point"}
}