{
  "type": "Feature",
  "properties": {
    "iso:country":"DE",
    "sg:address":"Emmastr. 13",
    "sg:city":"Cuxhaven",
    "sg:phone":"+49 4721/201881",
    "sg:postcode":"27476",
    "sg:province":"Niedersachsen",
    "wof:name":"Brigitte Hupfer",
    "wof:placetype":"venue"
},
  "geometry": {"coordinates":[8.6831521988,53.8800735474],"type":"Point"}
}