{
  "type": "Feature",
  "properties": {
    "iso:country":"DE",
    "sg:address":"Fellbacher Str. 54",
    "sg:city":"Fellbach",
    "sg:phone":"+49 711/513973",
    "sg:postcode":"70736",
    "sg:province":"Baden-W\u00fcrttemberg",
    "wof:name":"Kurt Frick",
    "wof:placetype":"venue"
},
  "geometry": {"coordinates":[9.2650108337,48.8295707703],"type":"Point"}
}