{
  "type": "Feature",
  "properties": {
    "iso:country":"DE",
    "sg:address":"Am Waldacker 8",
    "sg:city":"Frankfurt",
    "sg:phone":"+49 6109/31031",
    "sg:postcode":"60388",
    "sg:province":"Hessen",
    "wof:name":"Fuss & Tr\u00f6gel",
    "wof:placetype":"venue"
},
  "geometry": {"coordinates":[8.75187,50.142605],"type":"Point"}
}