{
  "type": "Feature",
  "properties": {
    "iso:country":"DE",
    "sg:address":"Bahnhofstr. 1",
    "sg:city":"Malsfeld",
    "sg:phone":"+49 5664/7369",
    "sg:postcode":"34323",
    "sg:province":"Hessen",
    "wof:name":"Edeka-markt",
    "wof:placetype":"venue"
},
  "geometry": {"coordinates":[9.5470104218,51.0798187256],"type":"Point"}
}