{
  "type": "Feature",
  "properties": {
    "iso:country":"DE",
    "sg:address":"Lorenz-Zierl-Str. 10",
    "sg:city":"Furth im Wald",
    "sg:phone":"+49 9973/1039",
    "sg:postcode":"93437",
    "sg:province":"Bayern",
    "wof:name":"Diskothek Lido",
    "wof:placetype":"venue"
},
  "geometry": {"coordinates":[12.842906,49.307449],"type":"Point"}
}