{
  "type": "Feature",
  "properties": {
    "iso:country":"DE",
    "sg:address":"Friedrich-Ebert-Str. 13",
    "sg:city":"Obernkirchen",
    "sg:phone":"+49 5724/98474",
    "sg:postcode":"31683",
    "sg:province":"Niedersachsen",
    "wof:name":"Franz Hunstiger",
    "wof:placetype":"venue"
},
  "geometry": {"coordinates":[9.1290998459,52.271194458],"type":"Point"}
}