{
  "type": "Feature",
  "properties": {
    "iso:country":"DE",
    "sg:address":"Ungerather Kirchweg 8b",
    "sg:city":"Schwalmtal",
    "sg:phone":"+49 2163/47489",
    "sg:postcode":"41366",
    "sg:province":"Nordrhein-Westfalen",
    "wof:name":"Wilhelm Maa\u00dfen",
    "wof:placetype":"venue"
},
  "geometry": {"coordinates":[6.277596,51.2085],"type":"Point"}
}