{
  "type": "Feature",
  "properties": {
    "iso:country":"DE",
    "sg:address":"Bahnhofstr.9",
    "sg:city":"Oberkirch",
    "sg:phone":"+49 4978/028050",
    "sg:postcode":"77704",
    "sg:province":"Baden-W\u00fcrttemberg",
    "wof:name":"Volksbank Offenburg Eg",
    "wof:placetype":"venue"
},
  "geometry": {"coordinates":[8.077724,48.529648],"type":"Point"}
}