{
  "type": "Feature",
  "properties": {
    "iso:country":"DE",
    "sg:address":"Breitensteinstr. 18",
    "sg:city":"Bad Feilnbach",
    "sg:phone":"+49 8066/630",
    "sg:postcode":"83075",
    "sg:province":"Bayern",
    "wof:name":"Hans Mertzbach",
    "wof:placetype":"venue"
},
  "geometry": {"coordinates":[12.003769,47.773003],"type":"Point"}
}