{
  "type": "Feature",
  "properties": {
    "iso:country":"DE",
    "sg:address":"Stockacher Str. 34",
    "sg:city":"Radolfzell",
    "sg:phone":"+49 7732/10233",
    "sg:postcode":"78315",
    "sg:province":"Baden-W\u00fcrttemberg",
    "wof:name":"Andreas Siebold",
    "wof:placetype":"venue"
},
  "geometry": {"coordinates":[8.9761447906,47.7524185181],"type":"Point"}
}