{
  "type": "Feature",
  "properties": {
    "iso:country":"DE",
    "sg:address":"Hochstr. 14",
    "sg:city":"Traunstein",
    "sg:phone":"+49 861/988870",
    "sg:postcode":"83278",
    "sg:province":"Bayern",
    "wof:name":"Vertriebsgemeinschaft Werlin F\u00e4rber Autohaus",
    "wof:placetype":"venue"
},
  "geometry": {"coordinates":[12.62871,47.859409],"type":"Point"}
}