{
  "type": "Feature",
  "properties": {
    "iso:country":"DE",
    "sg:address":"Dorfstr. 10",
    "sg:city":"Frammersbach",
    "sg:phone":"+49 6020/1393",
    "sg:postcode":"97833",
    "sg:province":"Bayern",
    "wof:name":"Restaurant-pension Zur Frischen Quelle",
    "wof:placetype":"venue"
},
  "geometry": {"coordinates":[9.4047679901,50.0598068237],"type":"Point"}
}