{
  "type": "Feature",
  "properties": {
    "iso:country":"DE",
    "sg:address":"Dorfstrasse 13",
    "sg:city":"Seehausen am Staffelsee",
    "sg:postcode":"82418",
    "sg:province":"Bayern",
    "wof:name":"Ferienwohnungen Am Staffelsee In Oberbayern, Nahe Garmisch,",
    "wof:placetype":"venue"
},
  "geometry": {"coordinates":[11.182964325,47.6887245178],"type":"Point"}
}