{
  "type": "Feature",
  "properties": {
    "iso:country":"DE",
    "sg:address":"Harrlallee 3",
    "sg:city":"Bad Eilsen",
    "sg:phone":"+49 5722/981971",
    "sg:postcode":"31707",
    "sg:province":"Niedersachsen",
    "wof:name":"Pension Wilhelm Lahmann",
    "wof:placetype":"venue"
},
  "geometry": {"coordinates":[9.0947713852,52.2415313721],"type":"Point"}
}