{
  "type": "Feature",
  "properties": {
    "iso:country":"DE",
    "sg:address":"Heinz-R\u00fchmann-Platz 1",
    "sg:city":"Herne",
    "sg:phone":"+49 2325/791188",
    "sg:postcode":"44649",
    "sg:province":"Nordrhein-Westfalen",
    "wof:name":"Taxi Kohlmann Gmbh",
    "wof:placetype":"venue"
},
  "geometry": {"coordinates":[7.1658468246,51.5319061279],"type":"Point"}
}