{
  "type": "Feature",
  "properties": {
    "iso:country":"DE",
    "sg:address":"Wollseifener Str. 36",
    "sg:city":"Schleiden",
    "sg:phone":"+49 2485/1449",
    "sg:postcode":"53937",
    "sg:province":"Nordrhein-Westfalen",
    "wof:name":"Josef Siever",
    "wof:placetype":"venue"
},
  "geometry": {"coordinates":[6.411989,50.54747],"type":"Point"}
}