{
  "type": "Feature",
  "properties": {
    "iso:country":"DE",
    "sg:address":"Platz der Jugend",
    "sg:city":"Burg",
    "sg:postcode":"39288",
    "sg:province":"Sachsen-Anhalt",
    "wof:name":"Pharmazie Und Medizintechnik Versorgungszentrum Gmbh",
    "wof:placetype":"venue"
},
  "geometry": {"coordinates":[11.856802,52.270451],"type":"Point"}
}