{
  "type": "Feature",
  "properties": {
    "iso:country":"DE",
    "sg:address":"Toyota-Allee 99",
    "sg:city":"K\u00f6ln",
    "sg:phone":"+49 221/94970",
    "sg:postcode":"50858",
    "sg:province":"Nordrhein-Westfalen",
    "wof:name":"Mecklenburgische Versicherungs-gesellschaft Ag",
    "wof:placetype":"venue"
},
  "geometry": {"coordinates":[6.8530321121,50.9137649536],"type":"Point"}
}