{
  "type": "Feature",
  "properties": {
    "iso:country":"DE",
    "sg:address":"Alte Str. 6",
    "sg:city":"Dobra",
    "sg:phone":"+49 35026/91237",
    "sg:postcode":"01833",
    "sg:province":"Sachsen",
    "wof:name":"Landwirtschaftliche Agrargenossenschaft Dorma - Helmsdorf",
    "wof:placetype":"venue"
},
  "geometry": {"coordinates":[14.04016,51.03688],"type":"Point"}
}