{
  "type": "Feature",
  "properties": {
    "iso:country":"DE",
    "sg:address":"Engelsstr. 32",
    "sg:city":"Aschersleben",
    "sg:phone":"+49 3473/801062",
    "sg:postcode":"06449",
    "sg:province":"Sachsen-Anhalt",
    "wof:name":"E. Kujawa",
    "wof:placetype":"venue"
},
  "geometry": {"coordinates":[11.459954,51.77039],"type":"Point"}
}