{
  "type": "Feature",
  "properties": {
    "iso:country":"DE",
    "sg:address":"Egelsbacher Str. 19",
    "sg:city":"Langen",
    "sg:phone":"+49 6103/54179",
    "sg:postcode":"63225",
    "sg:province":"Hessen",
    "wof:name":"Herbert Knechtel",
    "wof:placetype":"venue"
},
  "geometry": {"coordinates":[8.6766166687,49.9827575684],"type":"Point"}
}