{
  "type": "Feature",
  "properties": {
    "iso:country":"DE",
    "sg:address":"Ostring 11",
    "sg:city":"Rottendorf",
    "sg:phone":"+49 9302/3090",
    "sg:postcode":"97228",
    "sg:province":"Bayern",
    "wof:name":"S. Oliver Bernd Freier Gmbh & Co. Kg",
    "wof:placetype":"venue"
},
  "geometry": {"coordinates":[10.0364093781,49.7925491333],"type":"Point"}
}