{
  "type": "Feature",
  "properties": {
    "iso:country":"DE",
    "sg:address":"Friedrichstr. 1 a",
    "sg:city":"M\u00fcnchen",
    "sg:postcode":"80801",
    "sg:province":"Bayern",
    "wof:name":"Von Zezschwitz Kunst Und Design E. K.",
    "wof:placetype":"venue"
},
  "geometry": {"coordinates":[11.5792179108,48.1549987793],"type":"Point"}
}