{
  "type": "Feature",
  "properties": {
    "iso:country":"DE",
    "sg:address":"Horststr. 31-33",
    "sg:city":"Landau",
    "sg:postcode":"76829",
    "sg:province":"Rheinland-Pfalz",
    "wof:name":"Toom-baumarkt",
    "wof:placetype":"venue"
},
  "geometry": {"coordinates":[8.120598793,49.2036552429],"type":"Point"}
}