{
  "type": "Feature",
  "properties": {
    "iso:country":"DE",
    "sg:address":"Markt 5",
    "sg:city":"Haltern",
    "sg:phone":"+49 2364/93104",
    "sg:postcode":"45721",
    "sg:province":"Nordrhein-Westfalen",
    "wof:name":"Reinhold Saldow Heilpraktiker",
    "wof:placetype":"venue"
},
  "geometry": {"coordinates":[7.1875700951,51.7428894043],"type":"Point"}
}