{
  "type": "Feature",
  "properties": {
    "iso:country":"DE",
    "sg:address":"Alsumer Str. 5",
    "sg:city":"Dorum",
    "sg:phone":"+49 4742/2033",
    "sg:postcode":"27632",
    "sg:province":"Niedersachsen",
    "wof:name":"Fr. Fitter",
    "wof:placetype":"venue"
},
  "geometry": {"coordinates":[8.567988,53.689137],"type":"Point"}
}