{
  "type": "Feature",
  "properties": {
    "iso:country":"DE",
    "sg:address":"Hauptstr. 52",
    "sg:city":"Pfedelbach",
    "sg:phone":"+49 7941/8377",
    "sg:postcode":"74629",
    "sg:province":"Baden-W\u00fcrttemberg",
    "wof:name":"Bernhard Schott",
    "wof:placetype":"venue"
},
  "geometry": {"coordinates":[9.5048732758,49.1754150391],"type":"Point"}
}