{
  "type": "Feature",
  "properties": {
    "iso:country":"DE",
    "sg:address":"R\u00f6merstr. 34",
    "sg:city":"Ulm",
    "sg:phone":"+49 731/31641",
    "sg:postcode":"89077",
    "sg:province":"Baden-W\u00fcrttemberg",
    "wof:name":"H. Grathwohl Immobilienmakler",
    "wof:placetype":"venue"
},
  "geometry": {"coordinates":[9.9744577408,48.3903961182],"type":"Point"}
}