{
  "type": "Feature",
  "properties": {
    "iso:country":"DE",
    "sg:address":"Adelheid-Steinmann-Str. 3",
    "sg:city":"Freiburg",
    "sg:postcode":"79111",
    "sg:province":"Baden-W\u00fcrttemberg",
    "wof:name":"Csh Informations- Technologie Gmbh",
    "wof:placetype":"venue"
},
  "geometry": {"coordinates":[7.7961997986,47.9984092712],"type":"Point"}
}