{
  "type": "Feature",
  "properties": {
    "iso:country":"DE",
    "sg:address":"Uhlandstr. 1",
    "sg:city":"Erfurt",
    "sg:phone":"+49 361/3735118",
    "sg:postcode":"99096",
    "sg:province":"Th\u00fcringen",
    "wof:name":"Gabriele Wegfra\u00df",
    "wof:placetype":"venue"
},
  "geometry": {"coordinates":[11.027631,50.964153],"type":"Point"}
}