{
  "type": "Feature",
  "properties": {
    "iso:country":"DE",
    "sg:address":"Deichstr. 207A",
    "sg:city":"Berne",
    "sg:phone":"+49 421/671033",
    "sg:postcode":"27804",
    "sg:province":"Niedersachsen",
    "wof:name":"Dirk Deters",
    "wof:placetype":"venue"
},
  "geometry": {"coordinates":[8.4674749374,53.2214050293],"type":"Point"}
}