{
  "type": "Feature",
  "properties": {
    "iso:country":"DE",
    "sg:address":"Nachtweideweg 1-7",
    "sg:city":"Frankenthal",
    "sg:phone":"+49 6233/810",
    "sg:postcode":"67227",
    "sg:province":"Rheinland-Pfalz",
    "wof:name":"Tarkett Sommer Ag",
    "wof:placetype":"venue"
},
  "geometry": {"coordinates":[8.361265,49.537766],"type":"Point"}
}