{
  "type": "Feature",
  "properties": {
    "iso:country":"DE",
    "sg:address":"Lenbachstr. 68",
    "sg:city":"Schrobenhausen",
    "sg:phone":"+49 8252/7337",
    "sg:postcode":"86529",
    "sg:province":"Bayern",
    "wof:name":"Marlene Lauterbach",
    "wof:placetype":"venue"
},
  "geometry": {"coordinates":[11.264536,48.559212],"type":"Point"}
}