{
  "type": "Feature",
  "properties": {
    "iso:country":"DE",
    "sg:address":"Liegnitzer Str. 1",
    "sg:city":"Oldenburg",
    "sg:phone":"+49 441/63900",
    "sg:postcode":"26127",
    "sg:province":"Niedersachsen",
    "wof:name":"Salon Thie",
    "wof:placetype":"venue"
},
  "geometry": {"coordinates":[8.1972780228,53.1689682007],"type":"Point"}
}