{
  "type": "Feature",
  "properties": {
    "iso:country":"DE",
    "sg:address":"Au\u00dfer der Schleifm\u00fchle 27",
    "sg:city":"Bremen",
    "sg:phone":"+49 421/326599",
    "sg:postcode":"28203",
    "sg:province":"Bremen",
    "wof:name":"Reiner M. Kreutzmann",
    "wof:placetype":"venue"
},
  "geometry": {"coordinates":[8.820715,53.079952],"type":"Point"}
}