{
  "type": "Feature",
  "properties": {
    "iso:country":"DE",
    "sg:address":"Am Bleichanger 16",
    "sg:city":"Kaufbeuren",
    "sg:phone":"+49 8341/41420",
    "sg:postcode":"87600",
    "sg:province":"Bayern",
    "wof:name":"Barbara Preller Masseurin",
    "wof:placetype":"venue"
},
  "geometry": {"coordinates":[10.62157,47.885204],"type":"Point"}
}