{
  "type": "Feature",
  "properties": {
    "iso:country":"DE",
    "sg:address":"Str der Jugend 16",
    "sg:city":"Drebkau-Schorbus",
    "sg:phone":"+49 35602/20671",
    "sg:postcode":"03116",
    "sg:province":"Brandenburg",
    "wof:name":"Grande U. Pujo Heizger\u00e4tevermietung",
    "wof:placetype":"venue"
},
  "geometry": {"coordinates":[14.27863,51.68988],"type":"Point"}
}