{
  "type": "Feature",
  "properties": {
    "iso:country":"DE",
    "sg:address":"Mispelweg 22",
    "sg:city":"Marl",
    "sg:phone":"+49 2365/84391",
    "sg:postcode":"45770",
    "sg:province":"Nordrhein-Westfalen",
    "wof:name":"Yacht-schule-marl",
    "wof:placetype":"venue"
},
  "geometry": {"coordinates":[7.184723,51.667614],"type":"Point"}
}