{
  "type": "Feature",
  "properties": {
    "iso:country":"DE",
    "sg:address":"Holtenauer Str. 112",
    "sg:city":"Kiel",
    "sg:phone":"+49 431/568686",
    "sg:postcode":"24105",
    "sg:province":"Schleswig-Holstein",
    "wof:name":"Gottfried Paul Optik",
    "wof:placetype":"venue"
},
  "geometry": {"coordinates":[10.1336402893,54.3360557556],"type":"Point"}
}