{
  "type": "Feature",
  "properties": {
    "iso:country":"DE",
    "sg:address":"Anliegerweg 4",
    "sg:city":"Tr\u00f6bitz",
    "sg:phone":"+49 35326/90601",
    "sg:postcode":"03253",
    "sg:province":"Brandenburg",
    "wof:name":"Dvb-shop24.de Antennen & Satanlagenbau R. Schulz",
    "wof:placetype":"venue"
},
  "geometry": {"coordinates":[13.430605,51.595409],"type":"Point"}
}