{
  "type": "Feature",
  "properties": {
    "iso:country":"DE",
    "sg:address":"Bartholom\u00e4usplatz 1",
    "sg:city":"Neupotz",
    "sg:phone":"+49 7272/4570",
    "sg:postcode":"76777",
    "sg:province":"Rheinland-Pfalz",
    "wof:name":"Werner Gehrlein",
    "wof:placetype":"venue"
},
  "geometry": {"coordinates":[8.321746,49.118511],"type":"Point"}
}