{
  "type": "Feature",
  "properties": {
    "iso:country":"DE",
    "sg:address":"Bargst\u00fccken 2",
    "sg:city":"Appen",
    "sg:phone":"+49 4101/513573",
    "sg:postcode":"25482",
    "sg:province":"Schleswig-Holstein",
    "wof:name":"Wellhausen Systemtechnik Gmbh",
    "wof:placetype":"venue"
},
  "geometry": {"coordinates":[9.736822,53.662193],"type":"Point"}
}