{
  "type": "Feature",
  "properties": {
    "iso:country":"DE",
    "sg:address":"Eichendorffstr. 12",
    "sg:city":"Weiden",
    "sg:phone":"+49 961/33883",
    "sg:postcode":"92637",
    "sg:province":"Bayern",
    "wof:name":"Max Schell",
    "wof:placetype":"venue"
},
  "geometry": {"coordinates":[12.1733694077,49.6957054138],"type":"Point"}
}