{
  "type": "Feature",
  "properties": {
    "iso:country":"DE",
    "sg:address":"H\u00fchnerstr. 11",
    "sg:city":"Emmerich",
    "sg:phone":"+49 2822/92733",
    "sg:postcode":"46446",
    "sg:province":"Nordrhein-Westfalen",
    "wof:name":"D-tours Gabriele Debiel Emmerich Gmbh",
    "wof:placetype":"venue"
},
  "geometry": {"coordinates":[6.2482380867,51.8335227966],"type":"Point"}
}