{
  "type": "Feature",
  "properties": {
    "iso:country":"DE",
    "sg:address":"Ostpreu\u00dfenstr. 26",
    "sg:city":"Bad Windsheim",
    "sg:phone":"+49 9841/2548",
    "sg:postcode":"91438",
    "sg:province":"Bayern",
    "wof:name":"Bayerischer Lehrerinnen- Und Lehrerverein",
    "wof:placetype":"venue"
},
  "geometry": {"coordinates":[10.4040622711,49.5042800903],"type":"Point"}
}