{
  "type": "Feature",
  "properties": {
    "iso:country":"DE",
    "sg:address":"Neue Str. 2",
    "sg:city":"L\u00fcnne",
    "sg:phone":"+49 5906/593",
    "sg:postcode":"48480",
    "sg:province":"Niedersachsen",
    "wof:name":"Franz Schr\u00f6er",
    "wof:placetype":"venue"
},
  "geometry": {"coordinates":[7.4730801582,52.3642539978],"type":"Point"}
}