{
  "type": "Feature",
  "properties": {
    "iso:country":"DE",
    "sg:address":"Altenberger-Dom-Str. 175",
    "sg:city":"Bergisch Gladbach",
    "sg:phone":"+49 2202/84508",
    "sg:postcode":"51467",
    "sg:province":"Nordrhein-Westfalen",
    "wof:name":"Ludwig Bonitz Masseur",
    "wof:placetype":"venue"
},
  "geometry": {"coordinates":[7.082436,51.018433],"type":"Point"}
}