{
  "type": "Feature",
  "properties": {
    "iso:country":"DE",
    "sg:address":"Jungmannstr. 11a",
    "sg:city":"Hamburg",
    "sg:phone":"+49 40/8801264",
    "sg:postcode":"22605",
    "sg:province":"Hamburg",
    "wof:name":"U. L\u00fcbke",
    "wof:placetype":"venue"
},
  "geometry": {"coordinates":[9.884182,53.557568],"type":"Point"}
}