{
  "type": "Feature",
  "properties": {
    "iso:country":"DE",
    "sg:address":"Krankenhausstr. 10",
    "sg:city":"Oberg\u00fcnzburg",
    "sg:phone":"+49 8372/2205",
    "sg:postcode":"87634",
    "sg:province":"Bayern",
    "wof:name":"Claudia Ro\u00dfmann",
    "wof:placetype":"venue"
},
  "geometry": {"coordinates":[10.416287,47.847439],"type":"Point"}
}