{
  "type": "Feature",
  "properties": {
    "iso:country":"DE",
    "sg:address":"Lange Str. 70",
    "sg:city":"Lage",
    "sg:phone":"+49 5232/3281",
    "sg:postcode":"32791",
    "sg:province":"Nordrhein-Westfalen",
    "wof:name":"Ev. Pfarramt Gemeindeb\u00fcro Der Ev.-ref.",
    "wof:placetype":"venue"
},
  "geometry": {"coordinates":[8.7925291061,51.9904251099],"type":"Point"}
}