{
  "type": "Feature",
  "properties": {
    "iso:country":"DE",
    "sg:address":"Tuttlinger Str. 30",
    "sg:city":"Emmingen-Liptingen",
    "sg:phone":"+49 4976/1458401",
    "sg:postcode":"78576",
    "sg:province":"Baden-W\u00fcrttemberg",
    "wof:name":"Centerpulse Germany Gmbh",
    "wof:placetype":"venue"
},
  "geometry": {"coordinates":[7.8306279182,47.9786987305],"type":"Point"}
}