{
  "type": "Feature",
  "properties": {
    "iso:country":"DE",
    "sg:address":"Holzstr 5",
    "sg:city":"D\u00fcsseldorf",
    "sg:phone":"+49 211/901800",
    "sg:postcode":"40221",
    "sg:province":"Nordrhein-Westfalen",
    "wof:name":"Rhenus Ag & Co Kg",
    "wof:placetype":"venue"
},
  "geometry": {"coordinates":[6.7467479706,51.2130050659],"type":"Point"}
}