{
  "type": "Feature",
  "properties": {
    "iso:country":"DE",
    "sg:address":"Auf dem Ruppels 9",
    "sg:city":"Eppertshausen",
    "sg:phone":"+49 6071/33227",
    "sg:postcode":"64859",
    "sg:province":"Hessen",
    "wof:name":"Heinz Schledt",
    "wof:placetype":"venue"
},
  "geometry": {"coordinates":[8.839482,49.944523],"type":"Point"}
}