{
  "type": "Feature",
  "properties": {
    "iso:country":"DE",
    "sg:address":"Bergiusstr. 4",
    "sg:city":"Bonn",
    "sg:phone":"+49 228/662066",
    "sg:postcode":"53121",
    "sg:province":"Nordrhein-Westfalen",
    "wof:name":"Coduan & Hess Kg",
    "wof:placetype":"venue"
},
  "geometry": {"coordinates":[7.0604419708,50.739074707],"type":"Point"}
}