{
  "type": "Feature",
  "properties": {
    "iso:country":"DE",
    "sg:address":"Hessenstr 124",
    "sg:city":"Herbstein",
    "sg:phone":"+49 6643/96260",
    "sg:postcode":"36358",
    "sg:province":"Hessen",
    "wof:name":"Betonwerk Josef Anton Wiegand Gmbh",
    "wof:placetype":"venue"
},
  "geometry": {"coordinates":[9.3523378372,50.5532112122],"type":"Point"}
}