{
  "type": "Feature",
  "properties": {
    "iso:country":"DE",
    "sg:address":"Zingelstr. 15",
    "sg:city":"Meldorf",
    "sg:phone":"+49 4832/2242",
    "sg:postcode":"25704",
    "sg:province":"Schleswig-Holstein",
    "wof:name":"Eiscafe M. Ongaro",
    "wof:placetype":"venue"
},
  "geometry": {"coordinates":[9.074984,54.089706],"type":"Point"}
}