{
  "type": "Feature",
  "properties": {
    "iso:country":"DE",
    "sg:address":"Friedhofstr. 20",
    "sg:city":"R\u00f6dermark",
    "sg:phone":"+49 6074/861445",
    "sg:postcode":"63322",
    "sg:province":"Hessen",
    "wof:name":"Cad-zeichenb\u00fcro Fantur",
    "wof:placetype":"venue"
},
  "geometry": {"coordinates":[8.792876,49.970024],"type":"Point"}
}