{
  "type": "Feature",
  "properties": {
    "iso:country":"DE",
    "sg:address":"Im Schiffelland 19",
    "sg:city":"St. Ingbert",
    "sg:phone":"+49 6894/9989930",
    "sg:postcode":"66386",
    "sg:province":"Saarland",
    "wof:name":"Isopor Gmbh",
    "wof:placetype":"venue"
},
  "geometry": {"coordinates":[7.1318411827,49.2684516907],"type":"Point"}
}