{
  "type": "Feature",
  "properties": {
    "iso:country":"DE",
    "sg:address":"Am Anger 3",
    "sg:city":"Zirzow",
    "sg:phone":"+49 395/5823328",
    "sg:postcode":"17039",
    "sg:province":"Mecklenburg-Vorpommern",
    "wof:name":"Adv Abbruch Demontage Und Verwertung Gmbh",
    "wof:placetype":"venue"
},
  "geometry": {"coordinates":[13.1991567612,53.5858650208],"type":"Point"}
}