{
  "type": "Feature",
  "properties": {
    "iso:country":"DE",
    "sg:address":"Geisenheimer Str. 81",
    "sg:city":"R\u00fcdesheim am Rhein",
    "sg:phone":"+49 6722/1062",
    "sg:postcode":"65385",
    "sg:province":"Hessen",
    "wof:name":"Reiseb\u00fcro Bernhardt",
    "wof:placetype":"venue"
},
  "geometry": {"coordinates":[7.9394202232,49.9817008972],"type":"Point"}
}