{
  "type": "Feature",
  "properties": {
    "iso:country":"DE",
    "sg:address":"Karl-Sonnenschein-Str. 2",
    "sg:city":"Heinsberg",
    "sg:phone":"+49 2452/5757",
    "sg:postcode":"52525",
    "sg:province":"Nordrhein-Westfalen",
    "wof:name":"Marika Und K. H. Beuer Masseure",
    "wof:placetype":"venue"
},
  "geometry": {"coordinates":[6.093474,51.07082],"type":"Point"}
}