{
  "type": "Feature",
  "properties": {
    "iso:country":"DE",
    "sg:address":"St.-Hubertus-Str. 38",
    "sg:city":"Geretsried",
    "sg:phone":"+49 8171/31835",
    "sg:postcode":"82538",
    "sg:province":"Bayern",
    "wof:name":"Siegfried Herrmann",
    "wof:placetype":"venue"
},
  "geometry": {"coordinates":[11.481049,47.86525],"type":"Point"}
}