{
  "type": "Feature",
  "properties": {
    "iso:country":"DE",
    "sg:address":"Bahnhofstr. 107",
    "sg:city":"Schortens",
    "sg:phone":"+49 4461/8543",
    "sg:postcode":"26419",
    "sg:province":"Niedersachsen",
    "wof:name":"Hotel Deutscher Brunnen",
    "wof:placetype":"venue"
},
  "geometry": {"coordinates":[7.9685750008,53.5510940552],"type":"Point"}
}