{
  "type": "Feature",
  "properties": {
    "iso:country":"DE",
    "sg:address":"Walderseestr. 23",
    "sg:city":"Hannover",
    "sg:postcode":"30177",
    "sg:province":"Niedersachsen",
    "wof:name":"Nord Kb Beteiligungsges. Mbh",
    "wof:placetype":"venue"
},
  "geometry": {"coordinates":[9.762373,52.392982],"type":"Point"}
}