{
  "type": "Feature",
  "properties": {
    "iso:country":"DE",
    "sg:address":"Barmbeker Markt 7-8",
    "sg:city":"Hamburg",
    "sg:postcode":"22081",
    "sg:province":"Hamburg",
    "wof:name":"Hans Schaffhausen Gmbh",
    "wof:placetype":"venue"
},
  "geometry": {"coordinates":[10.0418777466,53.5808677673],"type":"Point"}
}