{
  "type": "Feature",
  "properties": {
    "iso:country":"DE",
    "sg:address":"Libellenweg 10",
    "sg:city":"Freiburg",
    "sg:phone":"+49 761/84530",
    "sg:postcode":"79110",
    "sg:province":"Baden-W\u00fcrttemberg",
    "wof:name":"J\u00fcrgen Bachmann",
    "wof:placetype":"venue"
},
  "geometry": {"coordinates":[7.8175349236,48.0174026489],"type":"Point"}
}