{
  "type": "Feature",
  "properties": {
    "iso:country":"DE",
    "sg:address":"Kranichstr. 15",
    "sg:city":"Neukirchen-Vluyn",
    "sg:phone":"+49 2845/5050",
    "sg:postcode":"47506",
    "sg:province":"Nordrhein-Westfalen",
    "wof:name":"G\u00fcnter Lehnhardt Elektroinstallation",
    "wof:placetype":"venue"
},
  "geometry": {"coordinates":[6.582776,51.455349],"type":"Point"}
}