{
  "type": "Feature",
  "properties": {
    "iso:country":"DE",
    "sg:address":"Hauptstr. 11",
    "sg:city":"Wertingen",
    "sg:phone":"+49 8272/2329",
    "sg:postcode":"86637",
    "sg:province":"Bayern",
    "wof:name":"Cafe Madlon Gmbh",
    "wof:placetype":"venue"
},
  "geometry": {"coordinates":[10.682595,48.561245],"type":"Point"}
}