{
  "type": "Feature",
  "properties": {
    "iso:country":"DE",
    "sg:address":"Auf den Geisten 8",
    "sg:city":"D\u00fcsseldorf",
    "sg:phone":"+49 211/4201550",
    "sg:postcode":"40468",
    "sg:province":"Nordrhein-Westfalen",
    "wof:name":"G. Pauly",
    "wof:placetype":"venue"
},
  "geometry": {"coordinates":[6.774643,51.271271],"type":"Point"}
}