{
  "type": "Feature",
  "properties": {
    "iso:country":"DE",
    "sg:address":"Siebet-Attena-Str. 18",
    "sg:city":"Esens",
    "sg:phone":"+49 4971/595",
    "sg:postcode":"26427",
    "sg:province":"Niedersachsen",
    "wof:name":"Vertrauens\u00e4rztlicher-dienst D. Lva Oldenburg-bremen",
    "wof:placetype":"venue"
},
  "geometry": {"coordinates":[7.608716011,53.6445770264],"type":"Point"}
}