{
  "type": "Feature",
  "properties": {
    "iso:country":"DE",
    "sg:address":"Fraunhoferstr. 23",
    "sg:city":"M\u00fcnchen",
    "sg:phone":"+49 89/2016665",
    "sg:postcode":"80469",
    "sg:province":"Bayern",
    "wof:name":"W. Bombelaj",
    "wof:placetype":"venue"
},
  "geometry": {"coordinates":[11.5740671158,48.1296653748],"type":"Point"}
}