{
  "type": "Feature",
  "properties": {
    "iso:country":"DE",
    "sg:address":"Alter Markt 18",
    "sg:city":"Arnsberg",
    "sg:phone":"+49 2931/89020",
    "sg:postcode":"59821",
    "sg:province":"Nordrhein-Westfalen",
    "wof:name":"Hotel-restaur. Landsberger Hof",
    "wof:placetype":"venue"
},
  "geometry": {"coordinates":[8.064324379,51.3964996338],"type":"Point"}
}