{
  "type": "Feature",
  "properties": {
    "iso:country":"DE",
    "sg:address":"Bahnstrasse 3 B",
    "sg:city":"Bedburg-Hau",
    "sg:postcode":"47551",
    "sg:province":"Nordrhein-Westfalen",
    "wof:name":"Explore Africa - S\u00fcdafrika Reise Service Center",
    "wof:placetype":"venue"
},
  "geometry": {"coordinates":[6.1769862175,51.7635917664],"type":"Point"}
}