{
  "type": "Feature",
  "properties": {
    "iso:country":"DE",
    "sg:address":"Reuterstr. 222",
    "sg:city":"Goch",
    "sg:phone":"+49 2823/3220",
    "sg:postcode":"47574",
    "sg:province":"Nordrhein-Westfalen",
    "wof:name":"Behaton Gmbh & Co. Kg",
    "wof:placetype":"venue"
},
  "geometry": {"coordinates":[6.1887612343,51.6898880005],"type":"Point"}
}