{
  "type": "Feature",
  "properties": {
    "iso:country":"DE",
    "sg:address":"Schweinheimer Str. 59",
    "sg:city":"Aschaffenburg",
    "sg:phone":"+49 6021/96997",
    "sg:postcode":"63743",
    "sg:province":"Bayern",
    "wof:name":"Media - Agentur Peter Schneider Gmbh",
    "wof:placetype":"venue"
},
  "geometry": {"coordinates":[9.1590337753,49.9642715454],"type":"Point"}
}