{
  "type": "Feature",
  "properties": {
    "iso:country":"DE",
    "sg:address":"L\u00e4rchenweg 30",
    "sg:city":"Kappelrodeck",
    "sg:phone":"+49 7842/2593",
    "sg:postcode":"77876",
    "sg:province":"Baden-W\u00fcrttemberg",
    "wof:name":"Joachim Ehret Ingenieur",
    "wof:placetype":"venue"
},
  "geometry": {"coordinates":[8.1107378006,48.585308075],"type":"Point"}
}