{
  "type": "Feature",
  "properties": {
    "iso:country":"DE",
    "sg:address":"Kappenstr. 81",
    "sg:city":"M\u00fclheim",
    "sg:phone":"+49 208/761834",
    "sg:postcode":"45475",
    "sg:province":"Nordrhein-Westfalen",
    "wof:name":"Aloys Amshoff",
    "wof:placetype":"venue"
},
  "geometry": {"coordinates":[6.905887,51.448799],"type":"Point"}
}