{
  "type": "Feature",
  "properties": {
    "iso:country":"DE",
    "sg:address":"Breitenstein",
    "sg:city":"Overath",
    "sg:phone":"+49 2206/2201",
    "sg:postcode":"51491",
    "sg:province":"Nordrhein-Westfalen",
    "wof:name":"Autobahntankstelle Aggertal S\u00fcd",
    "wof:placetype":"venue"
},
  "geometry": {"coordinates":[7.3562197685,50.9244117737],"type":"Point"}
}