{
  "type": "Feature",
  "properties": {
    "iso:country":"DE",
    "sg:address":"Antonius-Beermann-Weg 7",
    "sg:city":"Soest",
    "sg:phone":"+49 2921/15931",
    "sg:postcode":"59494",
    "sg:province":"Nordrhein-Westfalen",
    "wof:name":"Peter Dieckhoff Architekt",
    "wof:placetype":"venue"
},
  "geometry": {"coordinates":[8.099414,51.574467],"type":"Point"}
}