{
  "type": "Feature",
  "properties": {
    "iso:country":"DE",
    "sg:address":"Kieler Str. 208-212",
    "sg:city":"Hamburg",
    "sg:phone":"+49 40/8533300",
    "sg:postcode":"22525",
    "sg:province":"Hamburg",
    "wof:name":"A Prico All-time Digital Print And Communikation Ag",
    "wof:placetype":"venue"
},
  "geometry": {"coordinates":[9.930425,53.590721],"type":"Point"}
}