{
  "type": "Feature",
  "properties": {
    "iso:country":"DE",
    "sg:address":"Alter Berner Weg 33",
    "sg:city":"Hamburg",
    "sg:phone":"+49 40/5002060",
    "sg:postcode":"22393",
    "sg:province":"Hamburg",
    "wof:name":"Dietmar Hatje",
    "wof:placetype":"venue"
},
  "geometry": {"coordinates":[10.1216564178,53.6433677673],"type":"Point"}
}