{
  "type": "Feature",
  "properties": {
    "iso:country":"DE",
    "sg:address":"Marktstr. 12",
    "sg:city":"Winterberg",
    "sg:phone":"+49 2981/6345",
    "sg:postcode":"59955",
    "sg:province":"Nordrhein-Westfalen",
    "wof:name":"Beratungsstelle D. Caritas- Verbandes Brilon",
    "wof:placetype":"venue"
},
  "geometry": {"coordinates":[8.535286,51.194954],"type":"Point"}
}