{
  "type": "Feature",
  "properties": {
    "iso:country":"DE",
    "sg:address":"Rathausstr. 43",
    "sg:city":"Bexbach",
    "sg:phone":"+49 6826/51578",
    "sg:postcode":"66450",
    "sg:province":"Saarland",
    "wof:name":"V. Bauer",
    "wof:placetype":"venue"
},
  "geometry": {"coordinates":[7.257248,49.348019],"type":"Point"}
}