{
  "type": "Feature",
  "properties": {
    "iso:country":"DE",
    "sg:address":"Gr\u00f6tschenm\u00fchle",
    "sg:city":"Tr\u00f6stau",
    "sg:phone":"+49 9232/2280",
    "sg:postcode":"95709",
    "sg:province":"Bayern",
    "wof:name":"Franz Weisser Gmbh",
    "wof:placetype":"venue"
},
  "geometry": {"coordinates":[11.9555883408,50.0169334412],"type":"Point"}
}