{
  "type": "Feature",
  "properties": {
    "iso:country":"DE",
    "sg:address":"Air-Terminal-Str. 9",
    "sg:city":"Wiedemar",
    "sg:phone":"+49 34207/6350",
    "sg:postcode":"04509",
    "sg:province":"Sachsen",
    "wof:name":"Exato K\u00fcchenvertriebs Gmbh",
    "wof:placetype":"venue"
},
  "geometry": {"coordinates":[12.2111644745,51.4678916931],"type":"Point"}
}