{
  "type": "Feature",
  "properties": {
    "iso:country":"DE",
    "sg:address":"Leipziger Str. 22",
    "sg:city":"Pegau",
    "sg:phone":"+49 34296/72808",
    "sg:postcode":"04523",
    "sg:province":"Sachsen",
    "wof:name":"Mandy Haslinger",
    "wof:placetype":"venue"
},
  "geometry": {"coordinates":[12.25932,51.16539],"type":"Point"}
}