{
  "type": "Feature",
  "properties": {
    "iso:country":"DE",
    "sg:address":"Ernst-Schneider-Pl 1",
    "sg:city":"D\u00fcsseldorf",
    "sg:postcode":"40212",
    "sg:province":"Nordrhein-Westfalen",
    "wof:name":"Bankhaus Schliep & Co",
    "wof:placetype":"venue"
},
  "geometry": {"coordinates":[6.781088,51.226315],"type":"Point"}
}