{
  "type": "Feature",
  "properties": {
    "iso:country":"DE",
    "sg:address":"Birkheckenstr. 18",
    "sg:city":"Stuttgart",
    "sg:phone":"+49 711/454875",
    "sg:postcode":"70599",
    "sg:province":"Baden-W\u00fcrttemberg",
    "wof:name":"Zaunbau Fritz Koch Gmbh",
    "wof:placetype":"venue"
},
  "geometry": {"coordinates":[9.2081546783,48.7230377197],"type":"Point"}
}