{
  "type": "Feature",
  "properties": {
    "iso:country":"DE",
    "sg:address":"Bahnhofstr. 62",
    "sg:city":"Nordenham",
    "sg:phone":"+49 4731/22702",
    "sg:postcode":"26954",
    "sg:province":"Niedersachsen",
    "wof:name":"Aral-tankstelle",
    "wof:placetype":"venue"
},
  "geometry": {"coordinates":[8.4754962921,53.4866676331],"type":"Point"}
}