{
  "type": "Feature",
  "properties": {
    "iso:country":"DE",
    "sg:address":"Kritenbarg 7",
    "sg:city":"Hamburg",
    "sg:phone":"+49 40/6066036",
    "sg:postcode":"22391",
    "sg:province":"Hamburg",
    "wof:name":"Crutex Import-export Gmbh",
    "wof:placetype":"venue"
},
  "geometry": {"coordinates":[10.091002,53.652706],"type":"Point"}
}