{
  "type": "Feature",
  "properties": {
    "iso:country":"DE",
    "sg:address":"Bertrand-Russell-Str 5",
    "sg:city":"Hamburg",
    "sg:phone":"+49 40/2361120",
    "sg:postcode":"22761",
    "sg:province":"Hamburg",
    "wof:name":"Deutsche Bp Gesch\u00e4ftsbereich Bp Solar Ag",
    "wof:placetype":"venue"
},
  "geometry": {"coordinates":[9.8870334625,53.5756607056],"type":"Point"}
}