{
  "type": "Feature",
  "properties": {
    "iso:country":"DE",
    "sg:address":"Brandweg 6",
    "sg:city":"Passau",
    "sg:phone":"+49 851/36214",
    "sg:postcode":"94036",
    "sg:province":"Bayern",
    "wof:name":"V. M. Reischl Detektivb\u00fcro",
    "wof:placetype":"venue"
},
  "geometry": {"coordinates":[13.390134,48.564468],"type":"Point"}
}