{
  "type": "Feature",
  "properties": {
    "iso:country":"DE",
    "sg:address":"Waldebene Ost 231",
    "sg:city":"Stuttgart",
    "sg:phone":"+49 711/465831",
    "sg:postcode":"70186",
    "sg:province":"Baden-W\u00fcrttemberg",
    "wof:name":"Wangener Zigeunerle",
    "wof:placetype":"venue"
},
  "geometry": {"coordinates":[9.2223205566,48.7717056274],"type":"Point"}
}