{
  "type": "Feature",
  "properties": {
    "iso:country":"DE",
    "sg:address":"Katharinenstr. 11",
    "sg:city":"Hamburg",
    "sg:phone":"+49 40/363166",
    "sg:postcode":"20457",
    "sg:province":"Hamburg",
    "wof:name":"Heinrich Hauschildt Kg Seeschiffahrt-unternehmen",
    "wof:placetype":"venue"
},
  "geometry": {"coordinates":[9.990612,53.546139],"type":"Point"}
}