{
  "type": "Feature",
  "properties": {
    "iso:country":"DE",
    "sg:address":"Heinrich-Wobst-Str.",
    "sg:city":"Langenwolschendorf",
    "sg:phone":"+49 36628/62488",
    "sg:postcode":"07937",
    "sg:province":"Th\u00fcringen",
    "wof:name":"M. Kasperowski",
    "wof:placetype":"venue"
},
  "geometry": {"coordinates":[11.9690351486,50.6427116394],"type":"Point"}
}