{
  "type": "Feature",
  "properties": {
    "iso:country":"DE",
    "sg:address":"Neugasse 2",
    "sg:city":"Heidelberg",
    "sg:phone":"+49 6221/29035",
    "sg:postcode":"69117",
    "sg:province":"Baden-W\u00fcrttemberg",
    "wof:name":"Schmitt S Mode- Boutique Gmbh",
    "wof:placetype":"venue"
},
  "geometry": {"coordinates":[8.6949949265,49.4098930359],"type":"Point"}
}