{
  "type": "Feature",
  "properties": {
    "iso:country":"DE",
    "sg:address":"Hauptstr. 37",
    "sg:city":"Schauren",
    "sg:phone":"+49 6786/950130",
    "sg:postcode":"55758",
    "sg:province":"Rheinland-Pfalz",
    "wof:name":"Arthur Brusius Ohg",
    "wof:placetype":"venue"
},
  "geometry": {"coordinates":[7.2363929749,49.8089332581],"type":"Point"}
}