{
  "type": "Feature",
  "properties": {
    "iso:country":"DE",
    "sg:address":"Hauptstr. 120",
    "sg:city":"Achim",
    "sg:phone":"+49 4202/82384",
    "sg:postcode":"28832",
    "sg:province":"Niedersachsen",
    "wof:name":"Eickhorst Industrie- Elektronik Gmbh",
    "wof:placetype":"venue"
},
  "geometry": {"coordinates":[9.03506,53.046646],"type":"Point"}
}