{
  "type": "Feature",
  "properties": {
    "iso:country":"DE",
    "sg:address":"Hauptstr. 53",
    "sg:city":"Sch\u00f6nheide",
    "sg:phone":"+49 37755/55700",
    "sg:postcode":"08304",
    "sg:province":"Sachsen",
    "wof:name":"Schalom-apotheke Sch\u00f6nheide Apoth. Marlies D\u00f6llefeld E. K.",
    "wof:placetype":"venue"
},
  "geometry": {"coordinates":[12.533716,50.503239],"type":"Point"}
}