{
  "type": "Feature",
  "properties": {
    "iso:country":"DE",
    "sg:address":"Hauptstr. 100",
    "sg:city":"G\u00f6cklingen",
    "sg:phone":"+49 6349/8608",
    "sg:postcode":"76831",
    "sg:province":"Rheinland-Pfalz",
    "wof:name":"F. Lauth",
    "wof:placetype":"venue"
},
  "geometry": {"coordinates":[8.03258,49.163208],"type":"Point"}
}