{
  "type": "Feature",
  "properties": {
    "iso:country":"DE",
    "sg:address":"Amselplatz 2",
    "sg:city":"Herford",
    "sg:phone":"+49 5221/25444",
    "sg:postcode":"32049",
    "sg:province":"Nordrhein-Westfalen",
    "wof:name":"Pizzeria Bei Pablo",
    "wof:placetype":"venue"
},
  "geometry": {"coordinates":[8.6973981857,52.1301383972],"type":"Point"}
}