{
  "type": "Feature",
  "properties": {
    "iso:country":"DE",
    "sg:address":"Ostwall 211",
    "sg:city":"Krefeld",
    "sg:phone":"+49 2151/23405",
    "sg:postcode":"47798",
    "sg:province":"Nordrhein-Westfalen",
    "wof:name":"Peter Beckers Heilpraktiker",
    "wof:placetype":"venue"
},
  "geometry": {"coordinates":[6.5650458336,51.3358612061],"type":"Point"}
}