{
  "type": "Feature",
  "properties": {
    "iso:country":"DE",
    "sg:address":"Am Hafen 2",
    "sg:city":"Braunschweig",
    "sg:phone":"+49 531/2115161",
    "sg:postcode":"38112",
    "sg:province":"Niedersachsen",
    "wof:name":"Rent For Fair B Und D Mietmesseservice Gmbh",
    "wof:placetype":"venue"
},
  "geometry": {"coordinates":[10.4859352112,52.3104171753],"type":"Point"}
}