{
  "type": "Feature",
  "properties": {
    "iso:country":"DE",
    "sg:address":"Kilianst\u00e4dter Str. 30 a",
    "sg:city":"Sch\u00f6neck",
    "sg:phone":"+49 6187/910442",
    "sg:postcode":"61137",
    "sg:province":"Hessen",
    "wof:name":"Helmut Haug Gmbh",
    "wof:placetype":"venue"
},
  "geometry": {"coordinates":[8.8414707184,50.2122116089],"type":"Point"}
}