{
  "type": "Feature",
  "properties": {
    "iso:country":"DE",
    "sg:address":"Kathreinerstr. 1",
    "sg:city":"Bad W\u00f6rishofen",
    "sg:phone":"+49 8247/2347",
    "sg:postcode":"86825",
    "sg:province":"Bayern",
    "wof:name":"Ingrid Theis",
    "wof:placetype":"venue"
},
  "geometry": {"coordinates":[10.59399,48.006882],"type":"Point"}
}