{
  "type": "Feature",
  "properties": {
    "iso:country":"DE",
    "sg:address":"Erlngasse 2",
    "sg:city":"Ebsdorfergrund",
    "sg:phone":"+49 6424/1651",
    "sg:postcode":"35085",
    "sg:province":"Hessen",
    "wof:name":"J. Lorch",
    "wof:placetype":"venue"
},
  "geometry": {"coordinates":[8.857536,50.727547],"type":"Point"}
}