{
  "type": "Feature",
  "properties": {
    "iso:country":"DE",
    "sg:address":"Am Wiesengrund 36",
    "sg:city":"Neu Degtow",
    "sg:phone":"+49 3881/713857",
    "sg:postcode":"23936",
    "sg:province":"Mecklenburg-Vorpommern",
    "wof:name":"Kcu Unternehmensberatung Gmbh",
    "wof:placetype":"venue"
},
  "geometry": {"coordinates":[11.2231779099,53.8641815186],"type":"Point"}
}