{
  "type": "Feature",
  "properties": {
    "iso:country":"DE",
    "sg:address":"Ottobrunner Str. 15 b",
    "sg:city":"M\u00fcnchen",
    "sg:postcode":"81737",
    "sg:province":"Bayern",
    "wof:name":"Sta-bau Wohn Und Gewerbebau Bautr\u00e4ger Gmbh",
    "wof:placetype":"venue"
},
  "geometry": {"coordinates":[11.617888,48.111679],"type":"Point"}
}