{
  "type": "Feature",
  "properties": {
    "iso:country":"DE",
    "sg:address":"Provinzial-Allee 1",
    "sg:city":"M\u00fcnster",
    "sg:phone":"+49 251/2190",
    "sg:postcode":"48159",
    "sg:province":"Nordrhein-Westfalen",
    "wof:name":"Westf\u00e4lische Provinzial Versicherung Der Sparkassen",
    "wof:placetype":"venue"
},
  "geometry": {"coordinates":[7.6204800606,51.9914169312],"type":"Point"}
}