{
  "type": "Feature",
  "properties": {
    "iso:country":"DE",
    "sg:address":"Lerchenweg 1",
    "sg:city":"Elsdorf",
    "sg:postcode":"50189",
    "sg:province":"Nordrhein-Westfalen",
    "wof:name":"Optacon Limburg B.v.",
    "wof:placetype":"venue"
},
  "geometry": {"coordinates":[6.5524330139,50.9428443909],"type":"Point"}
}