{
  "type": "Feature",
  "properties": {
    "iso:country":"DE",
    "sg:address":"Leuste 4",
    "sg:city":"D\u00fclmen",
    "sg:phone":"+49 2594/4066",
    "sg:postcode":"48249",
    "sg:province":"Nordrhein-Westfalen",
    "wof:name":"Heinrich Ruhoff",
    "wof:placetype":"venue"
},
  "geometry": {"coordinates":[7.285637,51.863049],"type":"Point"}
}