{
  "type": "Feature",
  "properties": {
    "iso:country":"DE",
    "sg:address":"Syker Str. 17A",
    "sg:city":"Weyhe",
    "sg:phone":"+49 421/3365292",
    "sg:postcode":"28844",
    "sg:province":"Niedersachsen",
    "wof:name":"Heider Wohnbau",
    "wof:placetype":"venue"
},
  "geometry": {"coordinates":[8.789936,52.976868],"type":"Point"}
}