{
  "type": "Feature",
  "properties": {
    "iso:country":"DE",
    "sg:address":"Unterschellhart 4",
    "sg:city":"Moosthenning",
    "sg:phone":"+49 8733/346",
    "sg:postcode":"84164",
    "sg:province":"Bayern",
    "wof:name":"Willi Lanner",
    "wof:placetype":"venue"
},
  "geometry": {"coordinates":[12.461295,48.689461],"type":"Point"}
}