{
  "type": "Feature",
  "properties": {
    "iso:country":"DE",
    "sg:address":"Bahnhofstr. 16",
    "sg:city":"Dillenburg",
    "sg:phone":"+49 2771/6277",
    "sg:postcode":"35683",
    "sg:province":"Hessen",
    "wof:name":"Gwh Gmbh",
    "wof:placetype":"venue"
},
  "geometry": {"coordinates":[8.2931938171,50.7362365723],"type":"Point"}
}