{
  "type": "Feature",
  "properties": {
    "iso:country":"DE",
    "sg:address":"R\u00fcbenkamp 315",
    "sg:city":"Hamburg",
    "sg:phone":"+49 40/6304996",
    "sg:postcode":"22337",
    "sg:province":"Hamburg",
    "wof:name":"Dr. Marianne Kluge Ingenieurin",
    "wof:placetype":"venue"
},
  "geometry": {"coordinates":[10.0321855545,53.6132965088],"type":"Point"}
}