{
  "type": "Feature",
  "properties": {
    "iso:country":"DE",
    "sg:address":"Badstr. 27",
    "sg:city":"Bayreuth",
    "sg:phone":"+49 921/5169005",
    "sg:postcode":"95444",
    "sg:province":"Bayern",
    "wof:name":"Martin B\u00f6hmer Rechtsanwalt",
    "wof:placetype":"venue"
},
  "geometry": {"coordinates":[11.5815143585,49.9440765381],"type":"Point"}
}