{
  "type": "Feature",
  "properties": {
    "iso:country":"DE",
    "sg:address":"Trautenauer Str. 8",
    "sg:city":"M\u00fcnster",
    "sg:phone":"+49 6071/31817",
    "sg:postcode":"64839",
    "sg:province":"Hessen",
    "wof:name":"Rudolf Hoch",
    "wof:placetype":"venue"
},
  "geometry": {"coordinates":[8.8639316559,49.916267395],"type":"Point"}
}