{
  "type": "Feature",
  "properties": {
    "iso:country":"DE",
    "sg:address":"Vorburg 33",
    "sg:city":"Petershagen",
    "sg:phone":"+49 5761/2187",
    "sg:postcode":"32469",
    "sg:province":"Nordrhein-Westfalen",
    "wof:name":"Ev. Pfarramt Ev. Luth. Kirchengemeinde",
    "wof:placetype":"venue"
},
  "geometry": {"coordinates":[9.0696105957,52.4846725464],"type":"Point"}
}