{
  "type": "Feature",
  "properties": {
    "iso:country":"DE",
    "sg:address":"Martin-Kuen-Str. 5",
    "sg:city":"Wei\u00dfenhorn",
    "sg:phone":"+49 7309/96500",
    "sg:postcode":"89264",
    "sg:province":"Bayern",
    "wof:name":"Gasthof Zum L\u00f6wen",
    "wof:placetype":"venue"
},
  "geometry": {"coordinates":[10.1573648453,48.304485321],"type":"Point"}
}