{
  "type": "Feature",
  "properties": {
    "iso:country":"DE",
    "sg:address":"Kreuzflur 11",
    "sg:city":"Trier",
    "sg:phone":"+49 651/16235",
    "sg:postcode":"54296",
    "sg:province":"Rheinland-Pfalz",
    "wof:name":"Birgit Sperling Steuerberater",
    "wof:placetype":"venue"
},
  "geometry": {"coordinates":[6.6878380775,49.7418251038],"type":"Point"}
}