{
  "type": "Feature",
  "properties": {
    "iso:country":"DE",
    "sg:address":"Rommelsgasse 2",
    "sg:city":"Aachen",
    "sg:phone":"+49 241/405159",
    "sg:postcode":"52062",
    "sg:province":"Nordrhein-Westfalen",
    "wof:name":"Couven-stube",
    "wof:placetype":"venue"
},
  "geometry": {"coordinates":[6.0850529671,50.7756690979],"type":"Point"}
}