{
  "type": "Feature",
  "properties": {
    "iso:country":"DE",
    "sg:address":"Eisenbahnstr. 38",
    "sg:city":"Eberswalde",
    "sg:phone":"+49 3334/24072",
    "sg:postcode":"16225",
    "sg:province":"Brandenburg",
    "wof:name":"Druckerei Scholz Inh. Werner Scholz",
    "wof:placetype":"venue"
},
  "geometry": {"coordinates":[13.798589,52.834385],"type":"Point"}
}