{
  "type": "Feature",
  "properties": {
    "iso:country":"DE",
    "sg:address":"Heinrich-Lorenz-Str. 15-19",
    "sg:city":"Chemnitz",
    "sg:phone":"+49 371/523050",
    "sg:postcode":"09120",
    "sg:province":"Sachsen",
    "wof:name":"Taz Technisches Ausbildungszentrum Gmbh",
    "wof:placetype":"venue"
},
  "geometry": {"coordinates":[12.9080705643,50.8148994446],"type":"Point"}
}