{
  "type": "Feature",
  "properties": {
    "iso:country":"DE",
    "sg:address":"Steubenweg 13",
    "sg:city":"Hamm",
    "sg:phone":"+49 2385/2203",
    "sg:postcode":"59069",
    "sg:province":"Nordrhein-Westfalen",
    "wof:name":"Schreiber",
    "wof:placetype":"venue"
},
  "geometry": {"coordinates":[7.83332,51.599648],"type":"Point"}
}