{
  "type": "Feature",
  "properties": {
    "iso:country":"DE",
    "sg:address":"Taunusstr. 12",
    "sg:city":"Usingen",
    "sg:phone":"+49 6081/66879",
    "sg:postcode":"61250",
    "sg:province":"Hessen",
    "wof:name":"Josef Zalud Architekt",
    "wof:placetype":"venue"
},
  "geometry": {"coordinates":[8.53086,50.33987],"type":"Point"}
}