{
  "type": "Feature",
  "properties": {
    "iso:country":"DE",
    "sg:address":"Schillerstr. 54",
    "sg:city":"Zeuthen",
    "sg:phone":"+49 33762/93663",
    "sg:postcode":"15738",
    "sg:province":"Brandenburg",
    "wof:name":"Pro Aktiv Bau Gmbh",
    "wof:placetype":"venue"
},
  "geometry": {"coordinates":[13.624204,52.361473],"type":"Point"}
}