{
  "type": "Feature",
  "properties": {
    "iso:country":"DE",
    "sg:address":"Lindenweg 11",
    "sg:city":"Ratekau",
    "sg:phone":"+49 4503/2563",
    "sg:postcode":"23626",
    "sg:province":"Schleswig-Holstein",
    "wof:name":"Horst Sch\u00fctt",
    "wof:placetype":"venue"
},
  "geometry": {"coordinates":[10.7343101501,53.94972229],"type":"Point"}
}