{
  "type": "Feature",
  "properties": {
    "iso:country":"DE",
    "sg:address":"Ravensburger Str. 12",
    "sg:city":"Bad Waldsee",
    "sg:phone":"+49 7524/1443",
    "sg:postcode":"88339",
    "sg:province":"Baden-W\u00fcrttemberg",
    "wof:name":"Hasen",
    "wof:placetype":"venue"
},
  "geometry": {"coordinates":[9.7545280457,47.9201011658],"type":"Point"}
}