{
  "type": "Feature",
  "properties": {
    "iso:country":"DE",
    "sg:address":"Kluser Str. 35",
    "sg:city":"L\u00fcdenscheid",
    "sg:phone":"+49 2351/860622",
    "sg:postcode":"58511",
    "sg:province":"Nordrhein-Westfalen",
    "wof:name":"Verkehrswacht L\u00fcdenscheid-stadt",
    "wof:placetype":"venue"
},
  "geometry": {"coordinates":[7.6401901245,51.2197113037],"type":"Point"}
}