{
  "type": "Feature",
  "properties": {
    "iso:country":"DE",
    "sg:address":"K\u00f6nigsberger Str. 260",
    "sg:city":"M\u00fcnster",
    "sg:phone":"+49 251/14310",
    "sg:postcode":"48157",
    "sg:province":"Nordrhein-Westfalen",
    "wof:name":"Edv-beratung Stein Gmbh",
    "wof:placetype":"venue"
},
  "geometry": {"coordinates":[7.66341,51.994194],"type":"Point"}
}