{
  "type": "Feature",
  "properties": {
    "iso:country":"DE",
    "sg:address":"Oststr. 1 a",
    "sg:city":"Bebra",
    "sg:phone":"+49 6622/7501",
    "sg:postcode":"36179",
    "sg:province":"Hessen",
    "wof:name":"Bestattungsunternehmen Ke\u00dfler Gmbh",
    "wof:placetype":"venue"
},
  "geometry": {"coordinates":[9.800614,50.968552],"type":"Point"}
}