{
  "type": "Feature",
  "properties": {
    "iso:country":"DE",
    "sg:address":"Borsteler Stra\u00dfe 42",
    "sg:city":"Bispingen",
    "sg:phone":"+49 5194",
    "sg:postcode":"29646",
    "sg:province":"Niedersachsen",
    "wof:name":"Down-market",
    "wof:placetype":"venue"
},
  "geometry": {"coordinates":[9.998532,53.093227],"type":"Point"}
}