{
  "type": "Feature",
  "properties": {
    "iso:country":"DE",
    "sg:address":"K\u00f6pfchenstr. 3",
    "sg:city":"Kreuztal",
    "sg:phone":"+49 2732/3923",
    "sg:postcode":"57223",
    "sg:province":"Nordrhein-Westfalen",
    "wof:name":"Peter Hirsch",
    "wof:placetype":"venue"
},
  "geometry": {"coordinates":[7.987986,50.966885],"type":"Point"}
}