{
  "type": "Feature",
  "properties": {
    "iso:country":"DE",
    "sg:address":"Beethovenstr. 67",
    "sg:city":"Frankfurt",
    "sg:phone":"+49 69/751997",
    "sg:postcode":"60325",
    "sg:province":"Hessen",
    "wof:name":"G. G\u00f6pfert Architekt",
    "wof:placetype":"venue"
},
  "geometry": {"coordinates":[8.656426,50.119209],"type":"Point"}
}