{
  "type": "Feature",
  "properties": {
    "iso:country":"DE",
    "sg:address":"Berliner Str. 87",
    "sg:city":"F\u00fcrstenberg",
    "sg:phone":"+49 33093/32525",
    "sg:postcode":"16798",
    "sg:province":"Brandenburg",
    "wof:name":"Georg Struzina",
    "wof:placetype":"venue"
},
  "geometry": {"coordinates":[13.143828,53.179482],"type":"Point"}
}