{
  "type": "Feature",
  "properties": {
    "iso:country":"DE",
    "sg:address":"Alte Bergstr. 2",
    "sg:city":"Puchheim",
    "sg:postcode":"82178",
    "sg:province":"Bayern",
    "wof:name":"G.i.g. Gesellschaft F\u00fcr Innovative Gastronomie Mbh",
    "wof:placetype":"venue"
},
  "geometry": {"coordinates":[11.349856,48.146172],"type":"Point"}
}