{
  "type": "Feature",
  "properties": {
    "iso:country":"DE",
    "sg:address":"Labiaustr. 14",
    "sg:city":"Verden",
    "sg:phone":"+49 4231/81931",
    "sg:postcode":"27283",
    "sg:province":"Niedersachsen",
    "wof:name":"Jochen Gerling",
    "wof:placetype":"venue"
},
  "geometry": {"coordinates":[9.2132673264,52.9191703796],"type":"Point"}
}