{
  "type": "Feature",
  "properties": {
    "iso:country":"DE",
    "sg:address":"Susanna-Haunsch\u00fctz-Str 1",
    "sg:city":"Buxtehude",
    "sg:phone":"+49 4161/713420",
    "sg:postcode":"21614",
    "sg:province":"Niedersachsen",
    "wof:name":"Betriebsberatung & Management Auf Zeit Ernst E. Nill",
    "wof:placetype":"venue"
},
  "geometry": {"coordinates":[9.681369,53.461128],"type":"Point"}
}