{
  "type": "Feature",
  "properties": {
    "iso:country":"DE",
    "sg:address":"Almker Str. 6",
    "sg:city":"Wolfsburg",
    "sg:phone":"+49 5363/1375",
    "sg:postcode":"38446",
    "sg:province":"Niedersachsen",
    "wof:name":"Planungsgruppe Benes & Partner Gmbh",
    "wof:placetype":"venue"
},
  "geometry": {"coordinates":[10.853144,52.388706],"type":"Point"}
}