{
  "type": "Feature",
  "properties": {
    "iso:country":"DE",
    "sg:address":"Kelterstr. 3",
    "sg:city":"Karlsruhe",
    "sg:phone":"+49 721/492374",
    "sg:postcode":"76227",
    "sg:province":"Baden-W\u00fcrttemberg",
    "wof:name":"Hermann Schaffner",
    "wof:placetype":"venue"
},
  "geometry": {"coordinates":[8.468654,48.999096],"type":"Point"}
}