{
  "type": "Feature",
  "properties": {
    "iso:country":"DE",
    "sg:address":"Riesstr. 3",
    "sg:city":"Ritterhude",
    "sg:phone":"+49 4292/3255",
    "sg:postcode":"27721",
    "sg:province":"Niedersachsen",
    "wof:name":"Herbert Ahrens Rechtsanwalt",
    "wof:placetype":"venue"
},
  "geometry": {"coordinates":[8.7458124161,53.178188324],"type":"Point"}
}