{
  "type": "Feature",
  "properties": {
    "iso:country":"DE",
    "sg:address":"Giselherstr. 11",
    "sg:city":"Dortmund",
    "sg:phone":"+49 231/21860",
    "sg:postcode":"44319",
    "sg:province":"Nordrhein-Westfalen",
    "wof:name":"Givaudan Roure Beteiligungs Gmbh",
    "wof:placetype":"venue"
},
  "geometry": {"coordinates":[7.625246048,51.5274124146],"type":"Point"}
}