{
  "type": "Feature",
  "properties": {
    "iso:country":"DE",
    "sg:address":"Steinmetzstr.32",
    "sg:city":"Essen",
    "sg:phone":"+49 201",
    "sg:postcode":"45139",
    "sg:province":"Nordrhein-Westfalen",
    "wof:name":"Herzkind E. V. Wuppertal",
    "wof:placetype":"venue"
},
  "geometry": {"coordinates":[7.0284352303,51.4524345398],"type":"Point"}
}