{
  "type": "Feature",
  "properties": {
    "iso:country":"DE",
    "sg:address":"Stra\u00dfe der Jugend 6",
    "sg:city":"Ronneburg",
    "sg:phone":"+49 36602/36616",
    "sg:postcode":"07580",
    "sg:province":"Th\u00fcringen",
    "wof:name":"Ronneburger Beratungs- Vermittlungs- Und Bau Gmbh",
    "wof:placetype":"venue"
},
  "geometry": {"coordinates":[12.189745903,50.8695259094],"type":"Point"}
}