{
  "type": "Feature",
  "properties": {
    "iso:country":"DE",
    "sg:address":"Steinstra\u00dfe 31",
    "sg:city":"Worms",
    "sg:phone":"+49 6241/413320",
    "sg:postcode":"67547",
    "sg:province":"Rheinland-Pfalz",
    "wof:name":"Klickverhalten",
    "wof:placetype":"venue"
},
  "geometry": {"coordinates":[8.3607788086,49.6375656128],"type":"Point"}
}