{
  "type": "Feature",
  "properties": {
    "iso:country":"DE",
    "sg:address":"B\u00f6ttcherkamp 28",
    "sg:city":"Hamburg",
    "sg:phone":"+49 40/8323612",
    "sg:postcode":"22549",
    "sg:province":"Hamburg",
    "wof:name":"G\u00fcnter Kirsch Abschleppdienst",
    "wof:placetype":"venue"
},
  "geometry": {"coordinates":[9.8746213913,53.5868759155],"type":"Point"}
}