{
  "type": "Feature",
  "properties": {
    "iso:country":"DE",
    "sg:address":"Schulstr. 26",
    "sg:city":"Bergen",
    "sg:phone":"+49 5051/2063",
    "sg:postcode":"29303",
    "sg:province":"Niedersachsen",
    "wof:name":"Gerhard Borchers",
    "wof:placetype":"venue"
},
  "geometry": {"coordinates":[9.9577,52.81057],"type":"Point"}
}