{
  "type": "Feature",
  "properties": {
    "iso:country":"DE",
    "sg:address":"Marienborner Str. 205",
    "sg:city":"Siegen",
    "sg:phone":"+49 271/62974",
    "sg:postcode":"57074",
    "sg:province":"Nordrhein-Westfalen",
    "wof:name":"Friedrich Uebach Werner M\u00fcnch",
    "wof:placetype":"venue"
},
  "geometry": {"coordinates":[8.0397891998,50.877040863],"type":"Point"}
}