{
  "type": "Feature",
  "properties": {
    "iso:country":"DE",
    "sg:address":"Beethovenweg 14",
    "sg:city":"Herdecke",
    "sg:postcode":"58313",
    "sg:province":"Nordrhein-Westfalen",
    "wof:name":"Willkommen Auf Www.mottl.org",
    "wof:placetype":"venue"
},
  "geometry": {"coordinates":[7.428703,51.40905],"type":"Point"}
}