{
  "type": "Feature",
  "properties": {
    "iso:country":"DE",
    "sg:address":"D\u00f6rfelstr 14",
    "sg:city":"Olbernhau",
    "sg:phone":"+49 37360/45170",
    "sg:postcode":"09526",
    "sg:province":"Sachsen",
    "wof:name":"Laser - Tech Olbernhau Gmbh",
    "wof:placetype":"venue"
},
  "geometry": {"coordinates":[13.34975,50.649071],"type":"Point"}
}