{
  "type": "Feature",
  "properties": {
    "iso:country":"DE",
    "sg:address":"Br\u00fctingsweg 19",
    "sg:city":"Dortmund",
    "sg:phone":"+49 231/213374",
    "sg:postcode":"44319",
    "sg:province":"Nordrhein-Westfalen",
    "wof:name":"Hermann J. Multmeier Hochbauingenieur",
    "wof:placetype":"venue"
},
  "geometry": {"coordinates":[7.6050882339,51.5342674255],"type":"Point"}
}