{
  "type": "Feature",
  "properties": {
    "iso:country":"DE",
    "sg:address":"L\u00f6hrstr. 78",
    "sg:city":"Koblenz",
    "sg:phone":"+49 261/139010",
    "sg:postcode":"56068",
    "sg:province":"Rheinland-Pfalz",
    "wof:name":"Signal Unfallversicherung Ag",
    "wof:placetype":"venue"
},
  "geometry": {"coordinates":[7.5906581879,50.3557395935],"type":"Point"}
}