{
  "type": "Feature",
  "properties": {
    "iso:country":"DE",
    "sg:address":"Ludwig-Roselius-Allee 89",
    "sg:city":"Bremen",
    "sg:phone":"+49 421/473311",
    "sg:postcode":"28329",
    "sg:province":"Bremen",
    "wof:name":"Ipas Steuerungstechnik Gmbh",
    "wof:placetype":"venue"
},
  "geometry": {"coordinates":[8.9020996094,53.0714607239],"type":"Point"}
}