{
  "type": "Feature",
  "properties": {
    "iso:country":"DE",
    "sg:address":"Erlenstr. 1",
    "sg:city":"Obersontheim",
    "sg:phone":"+49 7973/886",
    "sg:postcode":"74423",
    "sg:province":"Baden-W\u00fcrttemberg",
    "wof:name":"B. Diez",
    "wof:placetype":"venue"
},
  "geometry": {"coordinates":[9.8612709045,49.0656166077],"type":"Point"}
}