{
  "type": "Feature",
  "properties": {
    "iso:country":"DE",
    "sg:address":"Am Sportplatz",
    "sg:city":"Limeshain",
    "sg:phone":"+49 6048/3155",
    "sg:postcode":"63694",
    "sg:province":"Hessen",
    "wof:name":"Mehrzweckhalle Hainchen",
    "wof:placetype":"venue"
},
  "geometry": {"coordinates":[8.997019,50.258644],"type":"Point"}
}