{
  "type": "Feature",
  "properties": {
    "iso:country":"DE",
    "sg:address":"Nelkenstr. 4",
    "sg:city":"Du\u00dflingen",
    "sg:phone":"+49 7072/7839",
    "sg:postcode":"72144",
    "sg:province":"Baden-W\u00fcrttemberg",
    "wof:name":"Eugen Gruber",
    "wof:placetype":"venue"
},
  "geometry": {"coordinates":[9.0602245331,48.4494247437],"type":"Point"}
}