{
  "type": "Feature",
  "properties": {
    "iso:country":"DE",
    "sg:address":"Braugasse 10-12",
    "sg:city":"Lich",
    "sg:phone":"+49 6404/666564",
    "sg:postcode":"35423",
    "sg:province":"Hessen",
    "wof:name":"Designhaus Roland Viehl",
    "wof:placetype":"venue"
},
  "geometry": {"coordinates":[8.818737,50.519642],"type":"Point"}
}