{
  "type": "Feature",
  "properties": {
    "iso:country":"DE",
    "sg:address":"M\u00fclh\u00f6fe 4",
    "sg:city":"M\u00f6hnesee",
    "sg:phone":"+49 2925/3007",
    "sg:postcode":"59519",
    "sg:province":"Nordrhein-Westfalen",
    "wof:name":"Rauschlicht",
    "wof:placetype":"venue"
},
  "geometry": {"coordinates":[8.2039899826,51.4780311584],"type":"Point"}
}