{
  "type": "Feature",
  "properties": {
    "iso:country":"DE",
    "sg:address":"Steinstr. 9",
    "sg:city":"Elsfleth",
    "sg:phone":"+49 4404/1578",
    "sg:postcode":"26931",
    "sg:province":"Niedersachsen",
    "wof:name":"Al Canari",
    "wof:placetype":"venue"
},
  "geometry": {"coordinates":[8.4627990723,53.2358016968],"type":"Point"}
}