{
  "type": "Feature",
  "properties": {
    "iso:country":"DE",
    "sg:address":"M\u00fchlholz 2",
    "sg:city":"Iggensbach",
    "sg:phone":"+49 9903/397",
    "sg:postcode":"94547",
    "sg:province":"Bayern",
    "wof:name":"Josef Zitzelsberger Lohndrusch-unternehmen",
    "wof:placetype":"venue"
},
  "geometry": {"coordinates":[13.159303,48.72541],"type":"Point"}
}