{
  "type": "Feature",
  "properties": {
    "iso:country":"DE",
    "sg:address":"Issumer Str. 68",
    "sg:city":"Geldern",
    "sg:phone":"+49 2831/3625",
    "sg:postcode":"47608",
    "sg:province":"Nordrhein-Westfalen",
    "wof:name":"Spielkisten Automaten- Aufstellungsges. Mbh & Co. Kg",
    "wof:placetype":"venue"
},
  "geometry": {"coordinates":[6.3258419037,51.5186157227],"type":"Point"}
}