{
  "type": "Feature",
  "properties": {
    "iso:country":"DE",
    "sg:address":"Clemens-August-Str. 31",
    "sg:city":"Arnsberg",
    "sg:phone":"+49 2931/10661",
    "sg:postcode":"59821",
    "sg:province":"Nordrhein-Westfalen",
    "wof:name":"Clemens Gieseke",
    "wof:placetype":"venue"
},
  "geometry": {"coordinates":[8.069277,51.398529],"type":"Point"}
}