{
  "type": "Feature",
  "properties": {
    "iso:country":"DE",
    "sg:address":"Rosengasse 6",
    "sg:city":"Ilshofen",
    "sg:phone":"+49 7904/370",
    "sg:postcode":"74532",
    "sg:province":"Baden-W\u00fcrttemberg",
    "wof:name":"Gasthaus Felix M\u00fcller",
    "wof:placetype":"venue"
},
  "geometry": {"coordinates":[9.9235506058,49.1437187195],"type":"Point"}
}