{
  "type": "Feature",
  "properties": {
    "iso:country":"DE",
    "sg:address":"Konrad-Adenauer-Str. 3",
    "sg:city":"Rinteln",
    "sg:phone":"+49 5751/5625",
    "sg:postcode":"31737",
    "sg:province":"Niedersachsen",
    "wof:name":"Weser-lichtspiele",
    "wof:placetype":"venue"
},
  "geometry": {"coordinates":[9.0824079514,52.1938934326],"type":"Point"}
}