{
  "type": "Feature",
  "properties": {
    "iso:country":"DE",
    "sg:address":"Varenner Str. 16",
    "sg:city":"Petershausen",
    "sg:phone":"+49 8137/1522",
    "sg:postcode":"85238",
    "sg:province":"Bayern",
    "wof:name":"Herbert St\u00f6ger Elektroinstallation",
    "wof:placetype":"venue"
},
  "geometry": {"coordinates":[11.471998,48.409061],"type":"Point"}
}