{
  "type": "Feature",
  "properties": {
    "iso:country":"DE",
    "sg:address":"Bergheimer Str. 17",
    "sg:city":"Heidelberg",
    "sg:postcode":"69115",
    "sg:province":"Baden-W\u00fcrttemberg",
    "wof:name":"Lenticon Contactlinsen Anpassung Sigrid Neumann E. K.",
    "wof:placetype":"venue"
},
  "geometry": {"coordinates":[8.6905488968,49.4086494446],"type":"Point"}
}