{
  "type": "Feature",
  "properties": {
    "iso:country":"DE",
    "sg:address":"Renchtalstr. 14",
    "sg:city":"Renchen",
    "sg:phone":"+49 7843/9490",
    "sg:postcode":"77871",
    "sg:province":"Baden-W\u00fcrttemberg",
    "wof:name":"Fachklinik Haus Renchtal",
    "wof:placetype":"venue"
},
  "geometry": {"coordinates":[8.0148801804,48.5875205994],"type":"Point"}
}