{
  "type": "Feature",
  "properties": {
    "iso:country":"DE",
    "sg:address":"Bremer Str. 5",
    "sg:city":"Stuhr",
    "sg:phone":"+49 421/891581",
    "sg:postcode":"28816",
    "sg:province":"Niedersachsen",
    "wof:name":"Willy Liepe & Co.",
    "wof:placetype":"venue"
},
  "geometry": {"coordinates":[8.689949,52.978249],"type":"Point"}
}