{
  "type": "Feature",
  "properties": {
    "iso:country":"DE",
    "sg:address":"Br\u00fcsseler Ring 47",
    "sg:city":"Aachen",
    "sg:phone":"+49 241/72021",
    "sg:postcode":"52074",
    "sg:province":"Nordrhein-Westfalen",
    "wof:name":"Jochem Schaps Steuerberater",
    "wof:placetype":"venue"
},
  "geometry": {"coordinates":[6.0696377754,50.7531204224],"type":"Point"}
}