{
  "type": "Feature",
  "properties": {
    "iso:country":"DE",
    "sg:address":"Maubacher Str. 79",
    "sg:city":"Backnang",
    "sg:phone":"+49 7191/60066",
    "sg:postcode":"71522",
    "sg:province":"Baden-W\u00fcrttemberg",
    "wof:name":"Ralf Kleinpeter Rechtsanwalt",
    "wof:placetype":"venue"
},
  "geometry": {"coordinates":[9.4302349091,48.9405097961],"type":"Point"}
}