{
  "type": "Feature",
  "properties": {
    "iso:country":"DE",
    "sg:address":"Meister-St\u00fctting-Str. 6",
    "sg:city":"M\u00f6hnesee",
    "sg:phone":"+49 2924/393",
    "sg:postcode":"59519",
    "sg:province":"Nordrhein-Westfalen",
    "wof:name":"Helmut Ke\u00dfler",
    "wof:placetype":"venue"
},
  "geometry": {"coordinates":[8.129951,51.497066],"type":"Point"}
}