{
  "type": "Feature",
  "properties": {
    "iso:country":"DE",
    "sg:address":"Frasenweg 2",
    "sg:city":"Kassel",
    "sg:phone":"+49 561/880090",
    "sg:postcode":"34128",
    "sg:province":"Hessen",
    "wof:name":"Heydens Backhaus Inh. Helmut Heyden",
    "wof:placetype":"venue"
},
  "geometry": {"coordinates":[9.461894,51.327511],"type":"Point"}
}