{
  "type": "Feature",
  "properties": {
    "iso:country":"DE",
    "sg:address":"Bergstr. 1",
    "sg:city":"Dormitz",
    "sg:phone":"+49 9134/9239",
    "sg:postcode":"91077",
    "sg:province":"Bayern",
    "wof:name":"Georg M\u00e4nnlein",
    "wof:placetype":"venue"
},
  "geometry": {"coordinates":[11.115092,49.600117],"type":"Point"}
}