{
  "type": "Feature",
  "properties": {
    "iso:country":"DE",
    "sg:address":"Meiendorfer M\u00fchlenweg 21",
    "sg:city":"Hamburg",
    "sg:postcode":"22393",
    "sg:province":"Hamburg",
    "wof:name":"Beteiligungsges. Medikal Med. San. Sonderanf.-gmbh",
    "wof:placetype":"venue"
},
  "geometry": {"coordinates":[10.124819,53.643822],"type":"Point"}
}