{
  "type": "Feature",
  "properties": {
    "iso:country":"DE",
    "sg:address":"Dieselstr. 5",
    "sg:city":"Winsen",
    "sg:phone":"+49 4171/88240",
    "sg:postcode":"21423",
    "sg:province":"Niedersachsen",
    "wof:name":"Baumarkt Behr Gmbh & Co. Kg",
    "wof:placetype":"venue"
},
  "geometry": {"coordinates":[10.2287464142,53.3742866516],"type":"Point"}
}