{
  "type": "Feature",
  "properties": {
    "iso:country":"DE",
    "sg:address":"Ritterstr. 18",
    "sg:city":"Giengen",
    "sg:phone":"+49 7322/7528",
    "sg:postcode":"89537",
    "sg:province":"Baden-W\u00fcrttemberg",
    "wof:name":"Rudi Kl\u00f6ble",
    "wof:placetype":"venue"
},
  "geometry": {"coordinates":[10.231898,48.581074],"type":"Point"}
}