{
  "type": "Feature",
  "properties": {
    "iso:country":"DE",
    "sg:address":"Am Sch\u00f6pfbrunnen 3",
    "sg:city":"\u00dcchtelhausen",
    "sg:phone":"+49 9720/270",
    "sg:postcode":"97532",
    "sg:province":"Bayern",
    "wof:name":"Werner Grebner",
    "wof:placetype":"venue"
},
  "geometry": {"coordinates":[10.2500038147,50.0949363708],"type":"Point"}
}