{
  "type": "Feature",
  "properties": {
    "iso:country":"DE",
    "sg:address":"Stra\u00dfe der Jugend 17",
    "sg:city":"Dobbertin",
    "sg:phone":"+49 38736/42404",
    "sg:postcode":"19399",
    "sg:province":"Mecklenburg-Vorpommern",
    "wof:name":"Monika Heim",
    "wof:placetype":"venue"
},
  "geometry": {"coordinates":[12.077178,53.62212],"type":"Point"}
}