{
  "type": "Feature",
  "properties": {
    "iso:country":"DE",
    "sg:address":"Prinzregentenplatz 14",
    "sg:city":"M\u00fcnchen",
    "sg:phone":"+49 89/471081",
    "sg:postcode":"81675",
    "sg:province":"Bayern",
    "wof:name":"J\u00fcrgen Geyer Immobilienmakler",
    "wof:placetype":"venue"
},
  "geometry": {"coordinates":[11.6070213318,48.1391029358],"type":"Point"}
}