{
  "type": "Feature",
  "properties": {
    "iso:country":"DE",
    "sg:address":"St\u00fcheweg 33",
    "sg:city":"Bad Oeynhausen",
    "sg:phone":"+49 5731/757550",
    "sg:postcode":"32549",
    "sg:province":"Nordrhein-Westfalen",
    "wof:name":"Meinberg & Partner Unternehmensberatungs Gmbh",
    "wof:placetype":"venue"
},
  "geometry": {"coordinates":[8.790689,52.227901],"type":"Point"}
}