{
  "type": "Feature",
  "properties": {
    "iso:country":"DE",
    "sg:address":"Obere Stadt 48",
    "sg:city":"Weilheim",
    "sg:phone":"+49 881/64791",
    "sg:postcode":"82362",
    "sg:province":"Bayern",
    "wof:name":"Maria Und Roland H\u00f6rmann",
    "wof:placetype":"venue"
},
  "geometry": {"coordinates":[11.148166,47.838127],"type":"Point"}
}