{
  "type": "Feature",
  "properties": {
    "iso:country":"DE",
    "sg:address":"Westenhellweg 16",
    "sg:city":"Dortmund",
    "sg:phone":"+49 231/571851",
    "sg:postcode":"44137",
    "sg:province":"Nordrhein-Westfalen",
    "wof:name":"W\u00fcrttembergische Versicherung Aktiengesellschaft",
    "wof:placetype":"venue"
},
  "geometry": {"coordinates":[7.465596199,51.5142364502],"type":"Point"}
}