{
  "type": "Feature",
  "properties": {
    "iso:country":"DE",
    "sg:address":"Hauptstr. 8",
    "sg:city":"Schneverdingen",
    "sg:phone":"+49 5193/6087",
    "sg:postcode":"29640",
    "sg:province":"Niedersachsen",
    "wof:name":"G. Schmidt",
    "wof:placetype":"venue"
},
  "geometry": {"coordinates":[9.762023,53.144451],"type":"Point"}
}