{
  "type": "Feature",
  "properties": {
    "iso:country":"DE",
    "sg:address":"Hintermeilingerstr. 15",
    "sg:city":"Waldbrunn - Ellar",
    "sg:phone":"+49 6479/9490149",
    "sg:postcode":"65620",
    "sg:province":"Hessen",
    "wof:name":"Ihr Schneller Einkaufs- Und Lieferdienst Packesel",
    "wof:placetype":"venue"
},
  "geometry": {"coordinates":[8.094497,50.507175],"type":"Point"}
}