{
  "type": "Feature",
  "properties": {
    "iso:country":"DE",
    "sg:address":"Schr\u00e4ger Weg 24",
    "sg:city":"Berlin",
    "sg:postcode":"13125",
    "sg:province":"Berlin",
    "wof:name":"Dr. Matthias Rumpelhardt Gmbh",
    "wof:placetype":"venue"
},
  "geometry": {"coordinates":[13.478169,52.609596],"type":"Point"}
}