{
  "type": "Feature",
  "properties": {
    "iso:country":"DE",
    "sg:address":"Westerwaldstr. 30",
    "sg:city":"Ehringshausen",
    "sg:phone":"+49 6449/471",
    "sg:postcode":"35630",
    "sg:province":"Hessen",
    "wof:name":"Pension Greifenthaler Hof Inh. Paul Preller",
    "wof:placetype":"venue"
},
  "geometry": {"coordinates":[8.3240308762,50.6085853577],"type":"Point"}
}