{
  "type": "Feature",
  "properties": {
    "iso:country":"DE",
    "sg:address":"Wurmtal 43",
    "sg:city":"Stecklenberg",
    "sg:phone":"+49 3947/62602",
    "sg:postcode":"06507",
    "sg:province":"Sachsen-Anhalt",
    "wof:name":"Malerservice Polifka Gmbh",
    "wof:placetype":"venue"
},
  "geometry": {"coordinates":[11.082292,51.73],"type":"Point"}
}