{
  "type": "Feature",
  "properties": {
    "iso:country":"DE",
    "sg:address":"Herrlinghausen 22",
    "sg:city":"Wermelskirchen",
    "sg:phone":"+49 2196/2589",
    "sg:postcode":"42929",
    "sg:province":"Nordrhein-Westfalen",
    "wof:name":"Olga Und P. Sprenga",
    "wof:placetype":"venue"
},
  "geometry": {"coordinates":[7.1978840828,51.1203918457],"type":"Point"}
}