{
  "type": "Feature",
  "properties": {
    "iso:country":"DE",
    "sg:address":"Wilhelmsh\u00f6he 35",
    "sg:city":"Solingen",
    "sg:phone":"+49 212/204541",
    "sg:postcode":"42655",
    "sg:province":"Nordrhein-Westfalen",
    "wof:name":"Georg Gronewold",
    "wof:placetype":"venue"
},
  "geometry": {"coordinates":[7.0725631714,51.1724319458],"type":"Point"}
}