{
  "type": "Feature",
  "properties": {
    "iso:country":"DE",
    "sg:address":"Poststr. 37",
    "sg:city":"Zweibr\u00fccken",
    "sg:postcode":"66482",
    "sg:province":"Rheinland-Pfalz",
    "wof:name":"Sonja Blinn Gmbh",
    "wof:placetype":"venue"
},
  "geometry": {"coordinates":[7.358117,49.247471],"type":"Point"}
}