{
  "type": "Feature",
  "properties": {
    "iso:country":"DE",
    "sg:address":"Chemnitzer Str. 21",
    "sg:city":"Neuendettelsau",
    "sg:phone":"+49 9874/5890",
    "sg:postcode":"91564",
    "sg:province":"Bayern",
    "wof:name":"Dieter Beil",
    "wof:placetype":"venue"
},
  "geometry": {"coordinates":[10.774806,49.2864],"type":"Point"}
}