{
  "type": "Feature",
  "properties": {
    "iso:country":"DE",
    "sg:address":"Haseng\u00e4rtlestr. 2",
    "sg:city":"Aulendorf",
    "sg:phone":"+49 7525/585",
    "sg:postcode":"88326",
    "sg:province":"Baden-W\u00fcrttemberg",
    "wof:name":"Blaser & Sohn Gmbh",
    "wof:placetype":"venue"
},
  "geometry": {"coordinates":[9.6399021149,47.9473800659],"type":"Point"}
}