{
  "type": "Feature",
  "properties": {
    "iso:country":"DE",
    "sg:address":"Bognerhofweg 6",
    "sg:city":"M\u00fcnchen",
    "sg:phone":"+49 89/421337",
    "sg:postcode":"81825",
    "sg:province":"Bayern",
    "wof:name":"Max Jungmetallbau Gmbh",
    "wof:placetype":"venue"
},
  "geometry": {"coordinates":[11.6697292328,48.1225662231],"type":"Point"}
}