{
  "type": "Feature",
  "properties": {
    "iso:country":"DE",
    "sg:address":"Bahnhofstr. 4",
    "sg:city":"Rheinau",
    "sg:phone":"+49 7844/813",
    "sg:postcode":"77866",
    "sg:province":"Baden-W\u00fcrttemberg",
    "wof:name":"Heinz Lehmann",
    "wof:placetype":"venue"
},
  "geometry": {"coordinates":[7.941322,48.668724],"type":"Point"}
}