{
  "type": "Feature",
  "properties": {
    "iso:country":"DE",
    "sg:address":"M\u00fchlhauser Str. 6",
    "sg:city":"M\u00fchlhausen-Ehingen",
    "sg:phone":"+49 7733/7227",
    "sg:postcode":"78259",
    "sg:province":"Baden-W\u00fcrttemberg",
    "wof:name":"Otmar J\u00e4ger",
    "wof:placetype":"venue"
},
  "geometry": {"coordinates":[8.800354,47.822033],"type":"Point"}
}