{
  "type": "Feature",
  "properties": {
    "iso:country":"DE",
    "sg:address":"Postillionseck 6",
    "sg:city":"Hanstedt",
    "sg:phone":"+49 4184/7729",
    "sg:postcode":"21271",
    "sg:province":"Niedersachsen",
    "wof:name":"Tls Terminal Und Logistik Service Gmbh",
    "wof:placetype":"venue"
},
  "geometry": {"coordinates":[10.0107908249,53.2493629456],"type":"Point"}
}