{
  "type": "Feature",
  "properties": {
    "iso:country":"DE",
    "sg:address":"Gartenstr. 3",
    "sg:city":"Fensterbach",
    "sg:phone":"+49 9438",
    "sg:postcode":"92269",
    "sg:province":"Bayern",
    "wof:name":"Kleinteilmontage Und Lohnverpackung",
    "wof:placetype":"venue"
},
  "geometry": {"coordinates":[12.06837,49.400845],"type":"Point"}
}