{
  "type": "Feature",
  "properties": {
    "iso:country":"DE",
    "sg:address":"Gartenstr. 30",
    "sg:city":"Wittgendorf",
    "sg:phone":"+49 34423/21332",
    "sg:postcode":"06712",
    "sg:province":"Sachsen-Anhalt",
    "wof:name":"Erholung",
    "wof:placetype":"venue"
},
  "geometry": {"coordinates":[12.1981401443,50.975605011],"type":"Point"}
}