{
  "type": "Feature",
  "properties": {
    "iso:country":"DE",
    "sg:address":"Birkenweg 4",
    "sg:city":"Bad Salzdetfurth",
    "sg:phone":"+49 5063/960468",
    "sg:postcode":"31162",
    "sg:province":"Niedersachsen",
    "wof:name":"Der Versicherungs-fuchs Inh. Sandra Pramann E. K.",
    "wof:placetype":"venue"
},
  "geometry": {"coordinates":[10.0152387619,52.0667266846],"type":"Point"}
}