{
  "type": "Feature",
  "properties": {
    "iso:country":"DE",
    "sg:address":"Im Schilling 18",
    "sg:city":"Leimen",
    "sg:phone":"+49 6224/72558",
    "sg:postcode":"69181",
    "sg:province":"Baden-W\u00fcrttemberg",
    "wof:name":"Ingeborg Kelpin Immobilienmaklerin",
    "wof:placetype":"venue"
},
  "geometry": {"coordinates":[8.7000980377,49.3487091064],"type":"Point"}
}