{
  "type": "Feature",
  "properties": {
    "iso:country":"DE",
    "sg:address":"An der Welle 4",
    "sg:city":"Frankfurt",
    "sg:postcode":"60322",
    "sg:province":"Hessen",
    "wof:name":"Patsystems Gmbh",
    "wof:placetype":"venue"
},
  "geometry": {"coordinates":[8.6721029282,50.1173553467],"type":"Point"}
}