{
  "type": "Feature",
  "properties": {
    "iso:country":"DE",
    "sg:address":"Dorfstr. 1",
    "sg:city":"Freisen",
    "sg:phone":"+49 6855/232",
    "sg:postcode":"66629",
    "sg:province":"Saarland",
    "wof:name":"Gerhard Sommer",
    "wof:placetype":"venue"
},
  "geometry": {"coordinates":[7.2606568336,49.5248794556],"type":"Point"}
}