{
  "type": "Feature",
  "properties": {
    "iso:country":"DE",
    "sg:address":"Forststr. 6",
    "sg:city":"Ingersheim",
    "sg:phone":"+49 7142/51831",
    "sg:postcode":"74379",
    "sg:province":"Baden-W\u00fcrttemberg",
    "wof:name":"Willi Leibbrand Mech. Werkstatt",
    "wof:placetype":"venue"
},
  "geometry": {"coordinates":[9.181699,48.963844],"type":"Point"}
}