{
  "type": "Feature",
  "properties": {
    "iso:country":"DE",
    "sg:address":"Oberstr. 57",
    "sg:city":"Spiesheim",
    "sg:phone":"+49 6732/1466",
    "sg:postcode":"55288",
    "sg:province":"Rheinland-Pfalz",
    "wof:name":"Rks-ruth Kleinknecht Nachf. Birgit Kleinknecht-wocker",
    "wof:placetype":"venue"
},
  "geometry": {"coordinates":[8.1279201508,49.8120727539],"type":"Point"}
}