{
  "type": "Feature",
  "properties": {
    "iso:country":"DE",
    "sg:address":"Von-Humboldt-Str. 11",
    "sg:city":"Gro\u00dfenl\u00fcder",
    "sg:phone":"+49 6648/95050",
    "sg:postcode":"36137",
    "sg:province":"Hessen",
    "wof:name":"G\u00fcnther Otterbein Steuerberater",
    "wof:placetype":"venue"
},
  "geometry": {"coordinates":[9.5431442261,50.5857887268],"type":"Point"}
}