{
  "type": "Feature",
  "properties": {
    "iso:country":"DE",
    "sg:address":"Lerchenberger Str. 22",
    "sg:city":"G\u00f6ppingen",
    "sg:phone":"+49 7161/26342",
    "sg:postcode":"73035",
    "sg:province":"Baden-W\u00fcrttemberg",
    "wof:name":"W. Zeller B\u00e4ckerei",
    "wof:placetype":"venue"
},
  "geometry": {"coordinates":[9.666298,48.723347],"type":"Point"}
}