{
  "type": "Feature",
  "properties": {
    "iso:country":"DE",
    "sg:address":"Darmst\u00e4dter Str. 97a",
    "sg:city":"Pfungstadt",
    "sg:phone":"+49 6157/5052",
    "sg:postcode":"64319",
    "sg:province":"Hessen",
    "wof:name":"Herwig Schindler",
    "wof:placetype":"venue"
},
  "geometry": {"coordinates":[8.569803,49.817764],"type":"Point"}
}