{
  "type": "Feature",
  "properties": {
    "iso:country":"DE",
    "sg:address":"Bahnhofstr. 26",
    "sg:city":"Borken",
    "sg:phone":"+49 5682/5193",
    "sg:postcode":"34582",
    "sg:province":"Hessen",
    "wof:name":"Beate Festor-m\u00fcller Krankengymnastin",
    "wof:placetype":"venue"
},
  "geometry": {"coordinates":[6.864002,51.849003],"type":"Point"}
}