{
  "type": "Feature",
  "properties": {
    "iso:country":"DE",
    "sg:address":"Marktstr. 28",
    "sg:city":"Saerbeck",
    "sg:phone":"+49 2574/1049",
    "sg:postcode":"48369",
    "sg:province":"Nordrhein-Westfalen",
    "wof:name":"C. Greiling",
    "wof:placetype":"venue"
},
  "geometry": {"coordinates":[7.633125782,52.174118042],"type":"Point"}
}