{
  "type": "Feature",
  "properties": {
    "iso:country":"DE",
    "sg:address":"Gutenbergplatz 1",
    "sg:city":"Leipzig",
    "sg:phone":"+49 341/12930",
    "sg:postcode":"04103",
    "sg:province":"Sachsen",
    "wof:name":"Ramada Hotel Garni Gmbh & Co. Kg",
    "wof:placetype":"venue"
},
  "geometry": {"coordinates":[12.3928728104,51.3367576599],"type":"Point"}
}