{
  "type": "Feature",
  "properties": {
    "iso:country":"DE",
    "sg:address":"Ostpromenade 54",
    "sg:city":"Heinsberg",
    "sg:postcode":"52525",
    "sg:province":"Nordrhein-Westfalen",
    "wof:name":"Kineo Verwaltungs Gmbh",
    "wof:placetype":"venue"
},
  "geometry": {"coordinates":[6.0973072052,51.0625190735],"type":"Point"}
}