{
  "type": "Feature",
  "properties": {
    "iso:country":"DE",
    "sg:address":"Gaistalstr. 1",
    "sg:city":"Bad Herrenalb",
    "sg:phone":"+49 7083/7796",
    "sg:postcode":"76332",
    "sg:province":"Baden-W\u00fcrttemberg",
    "wof:name":"H. K\u00f6pke Und G. Mangler",
    "wof:placetype":"venue"
},
  "geometry": {"coordinates":[8.4387903214,48.7954978943],"type":"Point"}
}