{
  "type": "Feature",
  "properties": {
    "iso:country":"DE",
    "sg:address":"Schulstr. 18",
    "sg:city":"Anr\u00f6chte",
    "sg:phone":"+49 2947/629",
    "sg:postcode":"59609",
    "sg:province":"Nordrhein-Westfalen",
    "wof:name":"Matthias Lehnen",
    "wof:placetype":"venue"
},
  "geometry": {"coordinates":[8.295683,51.541065],"type":"Point"}
}