{
  "type": "Feature",
  "properties": {
    "iso:country":"DE",
    "sg:address":"Bayreuther Str. 3",
    "sg:city":"Schnaittach",
    "sg:phone":"+49 8841/1268",
    "sg:postcode":"91220",
    "sg:province":"Bayern",
    "wof:name":"Brauerei Karg Gmbh & Co. Kg",
    "wof:placetype":"venue"
},
  "geometry": {"coordinates":[11.201112,47.676655],"type":"Point"}
}