{
  "type": "Feature",
  "properties": {
    "iso:country":"DE",
    "sg:address":"Berliner Platz 13",
    "sg:city":"Oer-Erkenschwick",
    "sg:phone":"+49 2368/6205",
    "sg:postcode":"45739",
    "sg:province":"Nordrhein-Westfalen",
    "wof:name":"Erhard Lerch",
    "wof:placetype":"venue"
},
  "geometry": {"coordinates":[7.259298,51.63987],"type":"Point"}
}