{
  "type": "Feature",
  "properties": {
    "iso:country":"DE",
    "sg:address":"Ulrichstr. 90",
    "sg:city":"Frechen",
    "sg:phone":"+49 2234/17306",
    "sg:postcode":"50226",
    "sg:province":"Nordrhein-Westfalen",
    "wof:name":"Manfred Timm",
    "wof:placetype":"venue"
},
  "geometry": {"coordinates":[6.79747,50.926334],"type":"Point"}
}