{
  "type": "Feature",
  "properties": {
    "iso:country":"DE",
    "sg:address":"Schulweg 24",
    "sg:city":"Marktrodach",
    "sg:phone":"+49 9261/94633",
    "sg:postcode":"96364",
    "sg:province":"Bayern",
    "wof:name":"Michael Kestel Architekt",
    "wof:placetype":"venue"
},
  "geometry": {"coordinates":[11.380096,50.254044],"type":"Point"}
}