{
  "type": "Feature",
  "properties": {
    "iso:country":"DE",
    "sg:address":"Rechtis 40",
    "sg:city":"Weitnau",
    "sg:postcode":"87480",
    "sg:province":"Bayern",
    "wof:name":"Creativ Maler Gmbh",
    "wof:placetype":"venue"
},
  "geometry": {"coordinates":[10.20101,47.67448],"type":"Point"}
}