{
  "type": "Feature",
  "properties": {
    "iso:country":"DE",
    "sg:address":"Schlossbereich",
    "sg:city":"Flehingen",
    "sg:phone":"+49 7258",
    "sg:postcode":"75038",
    "sg:province":"Baden-W\u00fcrttemberg",
    "wof:name":"Hifi Garage - Car Audio Online Shop -",
    "wof:placetype":"venue"
},
  "geometry": {"coordinates":[8.801774025,49.0622673035],"type":"Point"}
}