{
  "type": "Feature",
  "properties": {
    "iso:country":"DE",
    "sg:address":"Anzengruberstr. 13",
    "sg:city":"Berlin",
    "sg:phone":"+49 30/6877050",
    "sg:postcode":"12043",
    "sg:province":"Berlin",
    "wof:name":"Sargmagazin Neuk\u00f6lln Georg Hannow Gmbh",
    "wof:placetype":"venue"
},
  "geometry": {"coordinates":[13.4412937164,52.4806289673],"type":"Point"}
}