{
  "type": "Feature",
  "properties": {
    "iso:country":"DE",
    "sg:address":"Friedhofstr. 19",
    "sg:city":"Stei\u00dflingen",
    "sg:phone":"+49 7738/5900",
    "sg:postcode":"78256",
    "sg:province":"Baden-W\u00fcrttemberg",
    "wof:name":"Ev. Pfarramt",
    "wof:placetype":"venue"
},
  "geometry": {"coordinates":[8.9227218628,47.8033866882],"type":"Point"}
}