{
  "type": "Feature",
  "properties": {
    "iso:country":"DE",
    "sg:address":"Schlo\u00dfweg 8",
    "sg:city":"Hof",
    "sg:phone":"+49 9281/71540",
    "sg:postcode":"95028",
    "sg:province":"Bayern",
    "wof:name":"Handrich Kg",
    "wof:placetype":"venue"
},
  "geometry": {"coordinates":[11.903768,50.328499],"type":"Point"}
}