{
  "type": "Feature",
  "properties": {
    "iso:country":"DE",
    "sg:address":"Am Wasserturm 4",
    "sg:city":"Peine",
    "sg:phone":"+49 5171/82990",
    "sg:postcode":"31224",
    "sg:province":"Niedersachsen",
    "wof:name":"Michael Hein",
    "wof:placetype":"venue"
},
  "geometry": {"coordinates":[10.3106088638,52.3071517944],"type":"Point"}
}