{
  "type": "Feature",
  "properties": {
    "iso:country":"DE",
    "sg:address":"Hauptstr. 26",
    "sg:city":"Westendorf",
    "sg:phone":"+49 8273/1066",
    "sg:postcode":"86707",
    "sg:province":"Bayern",
    "wof:name":"Xaver Geisenberger",
    "wof:placetype":"venue"
},
  "geometry": {"coordinates":[10.837254,48.573383],"type":"Point"}
}