{
  "type": "Feature",
  "properties": {
    "iso:country":"DE",
    "sg:address":"Friedrichrodaer Str. 29",
    "sg:city":"Waltershausen",
    "sg:phone":"+49 3622/66874",
    "sg:postcode":"99880",
    "sg:province":"Th\u00fcringen",
    "wof:name":"Gastst\u00e4tte Zur Schenke",
    "wof:placetype":"venue"
},
  "geometry": {"coordinates":[10.6027698517,50.900894165],"type":"Point"}
}