{
  "type": "Feature",
  "properties": {
    "iso:country":"DE",
    "sg:address":"Schweizerstr. 68 a",
    "sg:city":"Sennfeld",
    "sg:phone":"+49 9721/68116",
    "sg:postcode":"97526",
    "sg:province":"Bayern",
    "wof:name":"Uwe Kritzner",
    "wof:placetype":"venue"
},
  "geometry": {"coordinates":[10.2582950592,50.0424880981],"type":"Point"}
}