{
  "type": "Feature",
  "properties": {
    "iso:country":"DE",
    "sg:address":"Kieler Str. 124",
    "sg:city":"Neum\u00fcnster",
    "sg:phone":"+49 4321/31269",
    "sg:postcode":"24536",
    "sg:province":"Schleswig-Holstein",
    "wof:name":"Heinrich Hofmann",
    "wof:placetype":"venue"
},
  "geometry": {"coordinates":[9.985436,54.083717],"type":"Point"}
}