{
  "type": "Feature",
  "properties": {
    "iso:country":"DE",
    "sg:address":"Dorfstr. 15",
    "sg:city":"Liesten",
    "sg:phone":"+49 39032/622",
    "sg:postcode":"29416",
    "sg:province":"Sachsen-Anhalt",
    "wof:name":"Dieter Miehe",
    "wof:placetype":"venue"
},
  "geometry": {"coordinates":[11.29504776,52.7879447937],"type":"Point"}
}