{
  "type": "Feature",
  "properties": {
    "iso:country":"DE",
    "sg:address":"Br\u00fchlweg 5",
    "sg:city":"Schw\u00e4bisch Gm\u00fcnd",
    "sg:phone":"+49 7171/84010",
    "sg:postcode":"73527",
    "sg:province":"Baden-W\u00fcrttemberg",
    "wof:name":"Benno Butz Architekt",
    "wof:placetype":"venue"
},
  "geometry": {"coordinates":[9.868443,48.813496],"type":"Point"}
}