{
  "type": "Feature",
  "properties": {
    "iso:country":"DE",
    "sg:address":"Ahornstr. 19 b",
    "sg:city":"Salzgitter",
    "sg:phone":"+49 5341/26284",
    "sg:postcode":"38239",
    "sg:province":"Niedersachsen",
    "wof:name":"Hans Schmoldt",
    "wof:placetype":"venue"
},
  "geometry": {"coordinates":[10.4620513916,52.1930847168],"type":"Point"}
}