{
  "type": "Feature",
  "properties": {
    "iso:country":"DE",
    "sg:address":"Manchingerstr. 86",
    "sg:city":"Ingolstadt",
    "sg:phone":"+49 841/965030",
    "sg:postcode":"85053",
    "sg:province":"Bayern",
    "wof:name":"Gebr. Konrad",
    "wof:placetype":"venue"
},
  "geometry": {"coordinates":[11.4525184631,48.7527542114],"type":"Point"}
}