{
  "type": "Feature",
  "properties": {
    "iso:country":"DE",
    "sg:address":"Bahnhofstr. 32",
    "sg:city":"Passau",
    "sg:phone":"+49 851/70030",
    "sg:postcode":"94032",
    "sg:province":"Bayern",
    "wof:name":"Thuringia Versicherungs-ag",
    "wof:placetype":"venue"
},
  "geometry": {"coordinates":[13.4498615265,48.5744056702],"type":"Point"}
}