{
  "type": "Feature",
  "properties": {
    "iso:country":"DE",
    "sg:address":"Bussardweg 29",
    "sg:city":"L\u00f6chgau",
    "sg:postcode":"74369",
    "sg:province":"Baden-W\u00fcrttemberg",
    "wof:name":"Be Consult Ag",
    "wof:placetype":"venue"
},
  "geometry": {"coordinates":[9.114159584,49.0055503845],"type":"Point"}
}