{
  "type": "Feature",
  "properties": {
    "iso:country":"DE",
    "sg:address":"Radstr. 3",
    "sg:city":"Laupheim",
    "sg:phone":"+49 7392/2269",
    "sg:postcode":"88471",
    "sg:province":"Baden-W\u00fcrttemberg",
    "wof:name":"Paul Graf",
    "wof:placetype":"venue"
},
  "geometry": {"coordinates":[9.8828487396,48.2314758301],"type":"Point"}
}