{
  "type": "Feature",
  "properties": {
    "iso:country":"DE",
    "sg:address":"Rathausstr. 2a",
    "sg:city":"Neuenhagen bei Berlin",
    "sg:phone":"+49 3342/254732",
    "sg:postcode":"15366",
    "sg:province":"Brandenburg",
    "wof:name":"Kompetenzzentrum F\u00fcr Den Elektronischen Gesch\u00e4ftsverkehr Oderland",
    "wof:placetype":"venue"
},
  "geometry": {"coordinates":[13.6767501831,52.5179405212],"type":"Point"}
}