{
  "type": "Feature",
  "properties": {
    "iso:country":"DE",
    "sg:address":"Mainplatz 8",
    "sg:city":"Wertheim",
    "sg:phone":"+49 9342/92330",
    "sg:postcode":"97877",
    "sg:province":"Baden-W\u00fcrttemberg",
    "wof:name":"Rolf Wiessler Hotel Schwan",
    "wof:placetype":"venue"
},
  "geometry": {"coordinates":[9.5157289505,49.7611274719],"type":"Point"}
}