{
  "type": "Feature",
  "properties": {
    "iso:country":"DE",
    "sg:address":"Spielbergstr. 1",
    "sg:city":"Aschau",
    "sg:phone":"+49 8052/909340",
    "sg:postcode":"83229",
    "sg:province":"Bayern",
    "wof:name":"Tbk Technisches B\u00fcro Kuckuck Gmbh",
    "wof:placetype":"venue"
},
  "geometry": {"coordinates":[12.260409,47.683472],"type":"Point"}
}