{
  "type": "Feature",
  "properties": {
    "iso:country":"DE",
    "sg:address":"Aachener U. M\u00fcnchener Allee 1",
    "sg:city":"Aachen",
    "sg:phone":"+49 241/4096350",
    "sg:postcode":"52074",
    "sg:province":"Nordrhein-Westfalen",
    "wof:name":"Ks Shows Event Gmbh",
    "wof:placetype":"venue"
},
  "geometry": {"coordinates":[6.073951,50.761353],"type":"Point"}
}