{
  "type": "Feature",
  "properties": {
    "iso:country":"DE",
    "sg:address":"Penningshof",
    "sg:city":"T\u00f6nisvorst",
    "sg:phone":"+49 2152/2837",
    "sg:postcode":"47918",
    "sg:province":"Nordrhein-Westfalen",
    "wof:name":"Jakob Beumer",
    "wof:placetype":"venue"
},
  "geometry": {"coordinates":[6.4953598976,51.3206253052],"type":"Point"}
}