{
  "type": "Feature",
  "properties": {
    "iso:country":"DE",
    "sg:address":"Hauptstr. 69",
    "sg:city":"Sch\u00f6ppingen",
    "sg:phone":"+49 2555/8025",
    "sg:postcode":"48624",
    "sg:province":"Nordrhein-Westfalen",
    "wof:name":"Willy Krechting Gmbh",
    "wof:placetype":"venue"
},
  "geometry": {"coordinates":[7.23302,52.094147],"type":"Point"}
}