{
  "type": "Feature",
  "properties": {
    "iso:country":"DE",
    "sg:address":"Els\u00e4sser Str. 20",
    "sg:city":"M\u00fcnster",
    "sg:phone":"+49 251/792055",
    "sg:postcode":"48151",
    "sg:province":"Nordrhein-Westfalen",
    "wof:name":"Bernhard Reher",
    "wof:placetype":"venue"
},
  "geometry": {"coordinates":[7.620337,51.938957],"type":"Point"}
}