{
  "type": "Feature",
  "properties": {
    "iso:country":"DE",
    "sg:address":"Seestr. 4",
    "sg:city":"B\u00f6nnigheim",
    "sg:postcode":"74357",
    "sg:province":"Baden-W\u00fcrttemberg",
    "wof:name":"P. S. Immobilien Gmbh",
    "wof:placetype":"venue"
},
  "geometry": {"coordinates":[9.094633,49.039295],"type":"Point"}
}