{
  "type": "Feature",
  "properties": {
    "iso:country":"DE",
    "sg:address":"Jahnstr. 35",
    "sg:city":"Kaufering",
    "sg:phone":"+49 8191/966816",
    "sg:postcode":"86916",
    "sg:province":"Bayern",
    "wof:name":"Altos Handels Gmbh",
    "wof:placetype":"venue"
},
  "geometry": {"coordinates":[10.8641786575,48.0910949707],"type":"Point"}
}