{
  "type": "Feature",
  "properties": {
    "iso:country":"DE",
    "sg:address":"Forsterstr. 1b",
    "sg:city":"Friedrichsthal",
    "sg:phone":"+49 6897/84852",
    "sg:postcode":"66299",
    "sg:province":"Saarland",
    "wof:name":"E. Eyer Innenarchitekt",
    "wof:placetype":"venue"
},
  "geometry": {"coordinates":[7.095434,49.324203],"type":"Point"}
}