{
  "type": "Feature",
  "properties": {
    "iso:country":"DE",
    "sg:address":"Seeheimer Str. 2",
    "sg:city":"Darmstadt",
    "sg:phone":"+49 6151/56682",
    "sg:postcode":"64297",
    "sg:province":"Hessen",
    "wof:name":"Cheer In",
    "wof:placetype":"venue"
},
  "geometry": {"coordinates":[8.6452703476,49.8070602417],"type":"Point"}
}