{
  "type": "Feature",
  "properties": {
    "iso:country":"DE",
    "sg:address":"St.-Michael-Str 11",
    "sg:city":"Altenm\u00fcnster",
    "sg:phone":"+49 8295/888",
    "sg:postcode":"86450",
    "sg:province":"Bayern",
    "wof:name":"Wiehler Gmbh",
    "wof:placetype":"venue"
},
  "geometry": {"coordinates":[10.573411,48.450844],"type":"Point"}
}