{
  "type": "Feature",
  "properties": {
    "iso:country":"DE",
    "sg:address":"Jakobistr. 62",
    "sg:city":"Soest",
    "sg:phone":"+49 2921/33502",
    "sg:postcode":"59494",
    "sg:province":"Nordrhein-Westfalen",
    "wof:name":"Sonnen Immobilienmakler",
    "wof:placetype":"venue"
},
  "geometry": {"coordinates":[8.1020851135,51.5688896179],"type":"Point"}
}