{
  "type": "Feature",
  "properties": {
    "iso:country":"DE",
    "sg:address":"Siemensstr. 3",
    "sg:city":"Friedrichshafen",
    "sg:postcode":"88048",
    "sg:province":"Baden-W\u00fcrttemberg",
    "wof:name":"Ic Inter Consult Gmbh",
    "wof:placetype":"venue"
},
  "geometry": {"coordinates":[9.4795675278,47.6794319153],"type":"Point"}
}