{
  "type": "Feature",
  "properties": {
    "iso:country":"DE",
    "sg:address":"Lenzenstr. 18",
    "sg:city":"Asbach",
    "sg:phone":"+49 2683/42540",
    "sg:postcode":"53567",
    "sg:province":"Rheinland-Pfalz",
    "wof:name":"Manfred Tillmann",
    "wof:placetype":"venue"
},
  "geometry": {"coordinates":[7.46636,50.668739],"type":"Point"}
}