{
  "type": "Feature",
  "properties": {
    "iso:country":"DE",
    "sg:address":"Ringstr. 13",
    "sg:city":"Ahorn",
    "sg:phone":"+49 9561/82820",
    "sg:postcode":"96482",
    "sg:province":"Bayern",
    "wof:name":"Voit Verwaltungs- Gmbh",
    "wof:placetype":"venue"
},
  "geometry": {"coordinates":[10.9518089294,50.2370223999],"type":"Point"}
}