{
  "type": "Feature",
  "properties": {
    "iso:country":"DE",
    "sg:address":"Fichtackerstr. 1",
    "sg:city":"Garmisch-Partenkirchen",
    "sg:phone":"+49 8821/3183",
    "sg:postcode":"82467",
    "sg:province":"Bayern",
    "wof:name":"Martinsklause",
    "wof:placetype":"venue"
},
  "geometry": {"coordinates":[11.0725784302,47.4882164001],"type":"Point"}
}