{
  "type": "Feature",
  "properties": {
    "iso:country":"DE",
    "sg:address":"Karl-Z\u00f6rgiebel-Str. 13",
    "sg:city":"Mainz",
    "sg:postcode":"55128",
    "sg:province":"Rheinland-Pfalz",
    "wof:name":"Verm\u00f6genstreuhand- Und Wirtschaftsberatungs Gmbh",
    "wof:placetype":"venue"
},
  "geometry": {"coordinates":[8.2441358566,49.9757423401],"type":"Point"}
}