{
  "type": "Feature",
  "properties": {
    "iso:country":"DE",
    "sg:address":"Deisterstr. 26",
    "sg:city":"Hameln",
    "sg:phone":"+49 5151/95240",
    "sg:postcode":"31785",
    "sg:province":"Niedersachsen",
    "wof:name":"Quelle",
    "wof:placetype":"venue"
},
  "geometry": {"coordinates":[9.367128,52.104027],"type":"Point"}
}