{
  "type": "Feature",
  "properties": {
    "iso:country":"DE",
    "sg:address":"Industriestr. 1",
    "sg:city":"Sittensen",
    "sg:phone":"+49 4282/9420",
    "sg:postcode":"27419",
    "sg:province":"Niedersachsen",
    "wof:name":"Holz-haase-baustoffe Inh. Rudolf Haase",
    "wof:placetype":"venue"
},
  "geometry": {"coordinates":[9.4954,53.28067],"type":"Point"}
}