{
  "type": "Feature",
  "properties": {
    "iso:country":"DE",
    "sg:address":"Lenbachplatz 11",
    "sg:city":"Hannover",
    "sg:phone":"+49 511/695959",
    "sg:postcode":"30655",
    "sg:province":"Niedersachsen",
    "wof:name":"Ev. Pfarramt Messiaskirche",
    "wof:placetype":"venue"
},
  "geometry": {"coordinates":[9.7909908295,52.4007797241],"type":"Point"}
}