{
  "type": "Feature",
  "properties": {
    "iso:country":"DE",
    "sg:address":"Obere Dorfstr. 19",
    "sg:city":"N\u00f6rten-Hardenberg",
    "sg:phone":"+49 5503/2286",
    "sg:postcode":"37176",
    "sg:province":"Niedersachsen",
    "wof:name":"Ernst-august Hengst",
    "wof:placetype":"venue"
},
  "geometry": {"coordinates":[9.909847,51.631512],"type":"Point"}
}