{
  "type": "Feature",
  "properties": {
    "iso:country":"DE",
    "sg:address":"Maximilianstr. 35",
    "sg:city":"Ansbach",
    "sg:phone":"+49 981/15079",
    "sg:postcode":"91522",
    "sg:province":"Bayern",
    "wof:name":"Georg Einsiedler Steuerberater",
    "wof:placetype":"venue"
},
  "geometry": {"coordinates":[10.5724201202,49.2981262207],"type":"Point"}
}