{
  "type": "Feature",
  "properties": {
    "iso:country":"DE",
    "sg:address":"Am Schaar 18",
    "sg:city":"L\u00fcbeck",
    "sg:postcode":"23564",
    "sg:province":"Schleswig-Holstein",
    "wof:name":"Coachingb\u00fcro Huber Und Partner Diplom-psychologen",
    "wof:placetype":"venue"
},
  "geometry": {"coordinates":[10.7325181961,53.8511199951],"type":"Point"}
}