{
  "type": "Feature",
  "properties": {
    "iso:country":"DE",
    "sg:address":"Sch\u00f6nwalder Str. 3",
    "sg:city":"Selb",
    "sg:phone":"+49 9287/99220",
    "sg:postcode":"95100",
    "sg:province":"Bayern",
    "wof:name":"Grimm & Kanh\u00e4u\u00dfe Gmbh",
    "wof:placetype":"venue"
},
  "geometry": {"coordinates":[12.125403,50.179127],"type":"Point"}
}