{
  "type": "Feature",
  "properties": {
    "iso:country":"DE",
    "sg:address":"Adalbert-Stifter-Ring 5",
    "sg:city":"Hirschberg",
    "sg:phone":"+49 6201/592143",
    "sg:postcode":"69493",
    "sg:province":"Baden-W\u00fcrttemberg",
    "wof:name":"Rainer Wohlfahrt",
    "wof:placetype":"venue"
},
  "geometry": {"coordinates":[8.6602449417,49.5035476685],"type":"Point"}
}