{
  "type": "Feature",
  "properties": {
    "iso:country":"DE",
    "sg:address":"M\u00f6rikestra\u00dfe 15",
    "sg:city":"Polch",
    "sg:phone":"+49 2654",
    "sg:postcode":"56751",
    "sg:province":"Rheinland-Pfalz",
    "wof:name":"Bauunternehmen Scharrenbach Aus Polch",
    "wof:placetype":"venue"
},
  "geometry": {"coordinates":[7.311889,50.303547],"type":"Point"}
}