{
  "type": "Feature",
  "properties": {
    "iso:country":"DE",
    "sg:address":"Gartenstr. 13",
    "sg:city":"Aichwald",
    "sg:phone":"+49 711/361290",
    "sg:postcode":"73773",
    "sg:province":"Baden-W\u00fcrttemberg",
    "wof:name":"Siegfried Hailer",
    "wof:placetype":"venue"
},
  "geometry": {"coordinates":[9.3783073425,48.7585144043],"type":"Point"}
}