{
  "type": "Feature",
  "properties": {
    "iso:country":"DE",
    "sg:address":"Friedrich-Wilhelm-Weber-Str. 8",
    "sg:city":"Nieheim",
    "sg:phone":"+49 5274/341",
    "sg:postcode":"33039",
    "sg:province":"Nordrhein-Westfalen",
    "wof:name":"Rieks",
    "wof:placetype":"venue"
},
  "geometry": {"coordinates":[9.115651,51.803921],"type":"Point"}
}