{
  "type": "Feature",
  "properties": {
    "iso:country":"DE",
    "sg:address":"Hofgasse 1",
    "sg:city":"Oettingen",
    "sg:phone":"+49 9082/8656",
    "sg:postcode":"86732",
    "sg:province":"Bayern",
    "wof:name":"Norbert Fleck Masseur",
    "wof:placetype":"venue"
},
  "geometry": {"coordinates":[10.604331,48.953014],"type":"Point"}
}