{
  "type": "Feature",
  "properties": {
    "iso:country":"DE",
    "sg:address":"Aachener Str 122",
    "sg:city":"Alsdorf",
    "sg:phone":"+49 2404/98680",
    "sg:postcode":"52477",
    "sg:province":"Nordrhein-Westfalen",
    "wof:name":"Suzo International Deutschland Gmbh",
    "wof:placetype":"venue"
},
  "geometry": {"coordinates":[6.1988592148,50.8519935608],"type":"Point"}
}