{
  "type": "Feature",
  "properties": {
    "iso:country":"DE",
    "sg:address":"Schliebenstr. 2",
    "sg:city":"Bautzen",
    "sg:phone":"+49 3591/303234",
    "sg:postcode":"02625",
    "sg:province":"Sachsen",
    "wof:name":"Apotheke Zur Br\u00fccke Inh. Stefan G\u00e4nsler E. K.",
    "wof:placetype":"venue"
},
  "geometry": {"coordinates":[14.416146,51.17939],"type":"Point"}
}