{
  "type": "Feature",
  "properties": {
    "iso:country":"DE",
    "sg:address":"Sudetenstr. 34",
    "sg:city":"Birstein",
    "sg:phone":"+49 6054/6241",
    "sg:postcode":"63633",
    "sg:province":"Hessen",
    "wof:name":"Kurt Kautz B\u00e4ckerei",
    "wof:placetype":"venue"
},
  "geometry": {"coordinates":[9.311795,50.359093],"type":"Point"}
}