{
  "type": "Feature",
  "properties": {
    "iso:country":"DE",
    "sg:address":"Am Streichen 13",
    "sg:city":"Bastheim",
    "sg:postcode":"97654",
    "sg:province":"Bayern",
    "wof:name":"Vs Bau Gmbh",
    "wof:placetype":"venue"
},
  "geometry": {"coordinates":[10.18504,50.426556],"type":"Point"}
}