{
  "type": "Feature",
  "properties": {
    "iso:country":"DE",
    "sg:address":"W\u00f6lkendorf 1",
    "sg:city":"Stadelhofen",
    "sg:postcode":"96187",
    "sg:province":"Bayern",
    "wof:name":"Multi System Gmbh",
    "wof:placetype":"venue"
},
  "geometry": {"coordinates":[11.176337,50.004433],"type":"Point"}
}