{
  "type": "Feature",
  "properties": {
    "iso:country":"DE",
    "sg:address":"Bergweg 11",
    "sg:city":"Petersberg",
    "sg:phone":"+49 34606/20409",
    "sg:postcode":"06193",
    "sg:province":"Sachsen-Anhalt",
    "wof:name":"\u00d6kumenischer Petersberg- Verein E. V.",
    "wof:placetype":"venue"
},
  "geometry": {"coordinates":[11.9582910538,51.5951728821],"type":"Point"}
}