{
  "type": "Feature",
  "properties": {
    "iso:country":"DE",
    "sg:address":"Bahnhofstr.",
    "sg:city":"Garmisch-Partenkirchen",
    "sg:phone":"+49 8821/4400",
    "sg:postcode":"82467",
    "sg:province":"Bayern",
    "wof:name":"Bahnhofsbuchhandlung Metius Gmbh",
    "wof:placetype":"venue"
},
  "geometry": {"coordinates":[11.0977249146,47.4915809631],"type":"Point"}
}