{
  "type": "Feature",
  "properties": {
    "iso:country":"DE",
    "sg:address":"Bulstener Str. 42",
    "sg:city":"Melle",
    "sg:phone":"+49 4954/2794140",
    "sg:postcode":"49328",
    "sg:province":"Niedersachsen",
    "wof:name":"Meyer Holzverarbeitung Gmbh",
    "wof:placetype":"venue"
},
  "geometry": {"coordinates":[8.4391813278,52.2308120728],"type":"Point"}
}