{
  "type": "Feature",
  "properties": {
    "iso:country":"DE",
    "sg:address":"Mittelweg 5",
    "sg:city":"Leuterod",
    "sg:postcode":"56244",
    "sg:province":"Rheinland-Pfalz",
    "wof:name":"Victoria Versicherung",
    "wof:placetype":"venue"
},
  "geometry": {"coordinates":[7.8259868622,50.4907035828],"type":"Point"}
}