{
  "type": "Feature",
  "properties": {
    "iso:country":"DE",
    "sg:address":"Tulpenweg 5",
    "sg:city":"Oldendorf",
    "sg:phone":"+49 4144/7399",
    "sg:postcode":"21726",
    "sg:province":"Niedersachsen",
    "wof:name":"Kopierservice Oldendorf",
    "wof:placetype":"venue"
},
  "geometry": {"coordinates":[9.2591533661,53.5945014954],"type":"Point"}
}