{
  "type": "Feature",
  "properties": {
    "iso:country":"DE",
    "sg:address":"Pottenstetten 1",
    "sg:city":"Burglengenfeld",
    "sg:phone":"+49 9471/1498",
    "sg:postcode":"93133",
    "sg:province":"Bayern",
    "wof:name":"Josef Hofmann",
    "wof:placetype":"venue"
},
  "geometry": {"coordinates":[12.0193214417,49.2397994995],"type":"Point"}
}