{
  "type": "Feature",
  "properties": {
    "iso:country":"DE",
    "sg:address":"Am Forsthaus 1",
    "sg:city":"Alfeld",
    "sg:phone":"+49 5181/845512",
    "sg:postcode":"31061",
    "sg:province":"Niedersachsen",
    "wof:name":"Awa&partner Qualit\u00e4tsmanagement- Und Umweltberatung Gmbh",
    "wof:placetype":"venue"
},
  "geometry": {"coordinates":[9.842369,51.991329],"type":"Point"}
}