{
  "type": "Feature",
  "properties": {
    "iso:country":"DE",
    "sg:address":"Herforder Str. 306",
    "sg:city":"Vlotho",
    "sg:phone":"+49 5228/7153",
    "sg:postcode":"32602",
    "sg:province":"Nordrhein-Westfalen",
    "wof:name":"Hermann Niemann",
    "wof:placetype":"venue"
},
  "geometry": {"coordinates":[8.803988,52.143681],"type":"Point"}
}