{
  "type": "Feature",
  "properties": {
    "iso:country":"DE",
    "sg:address":"Kreuzbreite 4 d",
    "sg:city":"Straubing",
    "sg:phone":"+49 9421/3744",
    "sg:postcode":"94315",
    "sg:province":"Bayern",
    "wof:name":"Alfons Haimerl",
    "wof:placetype":"venue"
},
  "geometry": {"coordinates":[12.5508260727,48.8709030151],"type":"Point"}
}