{
  "type": "Feature",
  "properties": {
    "iso:country":"DE",
    "sg:address":"Turnierstieg 19",
    "sg:city":"Hamburg",
    "sg:phone":"+49 40/2205730",
    "sg:postcode":"22179",
    "sg:province":"Hamburg",
    "wof:name":"Gerhard Klug",
    "wof:placetype":"venue"
},
  "geometry": {"coordinates":[10.0963048935,53.5998344421],"type":"Point"}
}