{
  "type": "Feature",
  "properties": {
    "iso:country":"DE",
    "sg:address":"Burmesterstr. 5",
    "sg:city":"Oldenburg",
    "sg:phone":"+49 441/218880",
    "sg:postcode":"26135",
    "sg:province":"Niedersachsen",
    "wof:name":"Cotton Island Herstellung Und Vertrieb Naturbelassener Tex-",
    "wof:placetype":"venue"
},
  "geometry": {"coordinates":[8.230625,53.125851],"type":"Point"}
}