{
  "type": "Feature",
  "properties": {
    "iso:country":"DE",
    "sg:address":"Willst\u00e4tterstr.15",
    "sg:city":"D\u00fcsseldorf",
    "sg:phone":"+49 211/594011",
    "sg:postcode":"40549",
    "sg:province":"Nordrhein-Westfalen",
    "wof:name":"Rabobank",
    "wof:placetype":"venue"
},
  "geometry": {"coordinates":[6.71658,51.240608],"type":"Point"}
}