{
  "type": "Feature",
  "properties": {
    "iso:country":"DE",
    "sg:address":"Gottlieb-Dunkel-Str. 19",
    "sg:city":"Berlin",
    "sg:phone":"+49 30/6074370",
    "sg:postcode":"12099",
    "sg:province":"Berlin",
    "wof:name":"Zur Rattenburg",
    "wof:placetype":"venue"
},
  "geometry": {"coordinates":[13.4133329391,52.4580612183],"type":"Point"}
}