{
  "type": "Feature",
  "properties": {
    "iso:country":"DE",
    "sg:address":"Lindenweg 9 b",
    "sg:city":"Schwante",
    "sg:phone":"+49 33055/70782",
    "sg:postcode":"16727",
    "sg:province":"Brandenburg",
    "wof:name":"Berliner Restaurants Gastronomie Suchmaschine",
    "wof:placetype":"venue"
},
  "geometry": {"coordinates":[13.082516,52.743622],"type":"Point"}
}