{
  "type": "Feature",
  "properties": {
    "iso:country":"DE",
    "sg:address":"Storzenbergstr. 27",
    "sg:city":"St. Georgen",
    "sg:phone":"+49 7724/4233",
    "sg:postcode":"78112",
    "sg:province":"Baden-W\u00fcrttemberg",
    "wof:name":"R. M. Friese Gmbh",
    "wof:placetype":"venue"
},
  "geometry": {"coordinates":[8.321455,48.123131],"type":"Point"}
}