{
  "type": "Feature",
  "properties": {
    "iso:country":"DE",
    "sg:address":"Baumstr. 36-38",
    "sg:city":"Solingen",
    "sg:phone":"+49 212/222860",
    "sg:postcode":"42651",
    "sg:province":"Nordrhein-Westfalen",
    "wof:name":"Giesen & Forsthoff Gmbh & Co. Kg",
    "wof:placetype":"venue"
},
  "geometry": {"coordinates":[7.094124,51.172436],"type":"Point"}
}