{
  "type": "Feature",
  "properties": {
    "iso:country":"DE",
    "sg:address":"M\u00f6nchfeldstr. 20",
    "sg:city":"Ludwigsburg",
    "sg:phone":"+49 7141/862219",
    "sg:postcode":"71640",
    "sg:province":"Baden-W\u00fcrttemberg",
    "wof:name":"G. Zwicker Immobilienmakler",
    "wof:placetype":"venue"
},
  "geometry": {"coordinates":[9.2216644287,48.8949737549],"type":"Point"}
}