{
  "type": "Feature",
  "properties": {
    "iso:country":"DE",
    "sg:address":"Ruchtastr. 24",
    "sg:city":"Ruderting",
    "sg:phone":"+49 8509/522",
    "sg:postcode":"94161",
    "sg:province":"Bayern",
    "wof:name":"Klavier Altmann R. Altmann",
    "wof:placetype":"venue"
},
  "geometry": {"coordinates":[13.4117851257,48.6468200684],"type":"Point"}
}