{
  "type": "Feature",
  "properties": {
    "iso:country":"DE",
    "sg:address":"Freiherr-vom-Stein-Str. 1",
    "sg:city":"Niedernhausen",
    "sg:phone":"+49 6127/8246",
    "sg:postcode":"65527",
    "sg:province":"Hessen",
    "wof:name":"Alexandra Sch\u00e4fer",
    "wof:placetype":"venue"
},
  "geometry": {"coordinates":[8.316492,50.162552],"type":"Point"}
}