{
  "type": "Feature",
  "properties": {
    "iso:country":"DE",
    "sg:address":"Mozartstr. 10",
    "sg:city":"Vogt",
    "sg:phone":"+49 7529/6200",
    "sg:postcode":"88267",
    "sg:province":"Baden-W\u00fcrttemberg",
    "wof:name":"Cico Pflegeservice",
    "wof:placetype":"venue"
},
  "geometry": {"coordinates":[9.765827,47.776108],"type":"Point"}
}