{
  "type": "Feature",
  "properties": {
    "iso:country":"DE",
    "sg:address":"Sudetenstr. 80",
    "sg:city":"Kaufbeuren",
    "sg:phone":"+49 8341/6333",
    "sg:postcode":"87600",
    "sg:province":"Bayern",
    "wof:name":"Auto Kettner Gmbh",
    "wof:placetype":"venue"
},
  "geometry": {"coordinates":[10.6462221146,47.8977890015],"type":"Point"}
}