{
  "type": "Feature",
  "properties": {
    "iso:country":"DE",
    "sg:address":"Eugen-Adolff-Str. 26",
    "sg:city":"Backnang",
    "sg:phone":"+49 7191/952280",
    "sg:postcode":"71522",
    "sg:province":"Baden-W\u00fcrttemberg",
    "wof:name":"Karl Schwarz",
    "wof:placetype":"venue"
},
  "geometry": {"coordinates":[9.436704,48.944725],"type":"Point"}
}