{
  "type": "Feature",
  "properties": {
    "iso:country":"DE",
    "sg:address":"Steinbachweg 1",
    "sg:city":"Harpstedt",
    "sg:phone":"+49 4244/682",
    "sg:postcode":"27243",
    "sg:province":"Niedersachsen",
    "wof:name":"Heinz Wittgr\u00e4fe",
    "wof:placetype":"venue"
},
  "geometry": {"coordinates":[8.583574,52.91021],"type":"Point"}
}