{
  "type": "Feature",
  "properties": {
    "iso:country":"DE",
    "sg:address":"Steinhof 41",
    "sg:city":"Erkrath",
    "sg:phone":"+49 211/243604",
    "sg:postcode":"40699",
    "sg:province":"Nordrhein-Westfalen",
    "wof:name":"Reinhold Brechtel",
    "wof:placetype":"venue"
},
  "geometry": {"coordinates":[6.898222,51.219521],"type":"Point"}
}