{
  "type": "Feature",
  "properties": {
    "iso:country":"DE",
    "sg:address":"Im Nordfeld 21",
    "sg:city":"Nienhagen",
    "sg:phone":"+49 5144/4848",
    "sg:postcode":"29336",
    "sg:province":"Niedersachsen",
    "wof:name":"Schmittdiel Gmbh",
    "wof:placetype":"venue"
},
  "geometry": {"coordinates":[10.106051,52.564468],"type":"Point"}
}