{
  "type": "Feature",
  "properties": {
    "iso:country":"DE",
    "sg:address":"Carl-Schurz-Str. 22",
    "sg:city":"N\u00fcrnberg",
    "sg:postcode":"90411",
    "sg:province":"Bayern",
    "wof:name":"Berger-immobilien",
    "wof:placetype":"venue"
},
  "geometry": {"coordinates":[11.10850811,49.4784660339],"type":"Point"}
}