{
  "type": "Feature",
  "properties": {
    "iso:country":"DE",
    "sg:city":"Swisttal",
    "sg:phone":"+49 2254",
    "sg:postcode":"53913",
    "sg:province":"Nordrhein-Westfalen",
    "wof:name":"Frankie\u00b4s Print Service",
    "wof:placetype":"venue"
},
  "geometry": {"coordinates":[6.915384,50.670712],"type":"Point"}
}