{
  "type": "Feature",
  "properties": {
    "iso:country":"DE",
    "sg:address":"Kriemhildstr. 8",
    "sg:city":"Bielefeld",
    "sg:phone":"+49 521/130311",
    "sg:postcode":"33615",
    "sg:province":"Nordrhein-Westfalen",
    "wof:name":"Wilfried Diekmann",
    "wof:placetype":"venue"
},
  "geometry": {"coordinates":[8.51876,52.02858],"type":"Point"}
}