{
  "type": "Feature",
  "properties": {
    "iso:country":"DE",
    "sg:address":"Im Schachen 28",
    "sg:city":"Waldmohr",
    "sg:phone":"+49 6373/4471",
    "sg:postcode":"66914",
    "sg:province":"Rheinland-Pfalz",
    "wof:name":"G\u00fcnther Kaiser",
    "wof:placetype":"venue"
},
  "geometry": {"coordinates":[7.340444,49.393574],"type":"Point"}
}