{
  "type": "Feature",
  "properties": {
    "iso:country":"DE",
    "sg:address":"Friedrichstr. 21/23",
    "sg:city":"Pforzheim",
    "sg:postcode":"75180",
    "sg:province":"Baden-W\u00fcrttemberg",
    "wof:name":"E.u.m. Gmbh",
    "wof:placetype":"venue"
},
  "geometry": {"coordinates":[8.6674690247,48.8753013611],"type":"Point"}
}