{
  "type": "Feature",
  "properties": {
    "iso:country":"DE",
    "sg:address":"Ludwig-Feuerbach-Weg 5",
    "sg:city":"Schwerte",
    "sg:phone":"+49 2304/83481",
    "sg:postcode":"58239",
    "sg:province":"Nordrhein-Westfalen",
    "wof:name":"Ak Typ Gmbh",
    "wof:placetype":"venue"
},
  "geometry": {"coordinates":[7.5484161377,51.4431724548],"type":"Point"}
}