{
  "type": "Feature",
  "properties": {
    "iso:country":"DE",
    "sg:address":"Oderfelder Str. 6",
    "sg:city":"Hamburg",
    "sg:postcode":"20149",
    "sg:province":"Hamburg",
    "wof:name":"E-bit Elektronik-beratungsges. F\u00fcr Alle Medien Mbh",
    "wof:placetype":"venue"
},
  "geometry": {"coordinates":[9.9887371063,53.5826454163],"type":"Point"}
}