{
  "type": "Feature",
  "properties": {
    "iso:country":"DE",
    "sg:address":"Bahnhofsplatz 2",
    "sg:city":"Gernsbach",
    "sg:phone":"+49 7224/2916",
    "sg:postcode":"76593",
    "sg:province":"Baden-W\u00fcrttemberg",
    "wof:name":"Deutsche Bahn Ag",
    "wof:placetype":"venue"
},
  "geometry": {"coordinates":[8.3359365463,48.7677688599],"type":"Point"}
}