{
  "type": "Feature",
  "properties": {
    "iso:country":"DE",
    "sg:address":"Tanner Str. 10",
    "sg:city":"Trautenstein",
    "sg:phone":"+49 39459/72240",
    "sg:postcode":"38899",
    "sg:province":"Sachsen-Anhalt",
    "wof:name":"Steinmetzbetrieb Unger Kg",
    "wof:placetype":"venue"
},
  "geometry": {"coordinates":[10.7797431946,51.6826896667],"type":"Point"}
}