{
  "type": "Feature",
  "properties": {
    "iso:country":"DE",
    "sg:address":"Allensteiner Str. 17",
    "sg:city":"Neuwied",
    "sg:phone":"+49 2631/83740",
    "sg:postcode":"56566",
    "sg:province":"Rheinland-Pfalz",
    "wof:name":"Bauhaus Gmbh & Co. Kg",
    "wof:placetype":"venue"
},
  "geometry": {"coordinates":[7.4922761917,50.4380226135],"type":"Point"}
}