{
  "type": "Feature",
  "properties": {
    "iso:country":"DE",
    "sg:address":"Geister Landweg 7-9",
    "sg:city":"M\u00fcnster",
    "sg:phone":"+49 4947/36213",
    "sg:postcode":"48153",
    "sg:province":"Nordrhein-Westfalen",
    "wof:name":"Ross Gmbh Sonderwerkzeuge",
    "wof:placetype":"venue"
},
  "geometry": {"coordinates":[8.27586,53.589119],"type":"Point"}
}