{
  "type": "Feature",
  "properties": {
    "iso:country":"DE",
    "sg:address":"Severinstr. 161",
    "sg:city":"K\u00f6ln",
    "sg:phone":"+49 221/321663",
    "sg:postcode":"50678",
    "sg:province":"Nordrhein-Westfalen",
    "wof:name":"Heinz M. M\u00fcller",
    "wof:placetype":"venue"
},
  "geometry": {"coordinates":[6.9574432373,50.9278259277],"type":"Point"}
}