{
  "type": "Feature",
  "properties": {
    "iso:country":"DE",
    "sg:address":"Waldenburger Str. 1a",
    "sg:city":"Kleinbernsdorf",
    "sg:phone":"+49 3763/4030",
    "sg:postcode":"08373",
    "sg:province":"Sachsen",
    "wof:name":"Bauring-tief- Und Stra\u00dfenbau Gmbh",
    "wof:placetype":"venue"
},
  "geometry": {"coordinates":[12.5642004013,50.8512992859],"type":"Point"}
}