{
  "type": "Feature",
  "properties": {
    "iso:country":"DE",
    "sg:address":"Rosa-Luxemburg-Str. 8",
    "sg:city":"Grimma",
    "sg:phone":"+49 3437/919260",
    "sg:postcode":"04668",
    "sg:province":"Sachsen",
    "wof:name":"Hannelore Rebentisch",
    "wof:placetype":"venue"
},
  "geometry": {"coordinates":[12.726957,51.248402],"type":"Point"}
}