{
  "type": "Feature",
  "properties": {
    "iso:country":"DE",
    "sg:address":"Am Weiher 3",
    "sg:city":"Gr\u00fcnberg",
    "sg:phone":"+49 6400/8769",
    "sg:postcode":"35305",
    "sg:province":"Hessen",
    "wof:name":"Helmut Berg",
    "wof:placetype":"venue"
},
  "geometry": {"coordinates":[9.016902,50.58136],"type":"Point"}
}