{
  "type": "Feature",
  "properties": {
    "iso:country":"DE",
    "sg:address":"Josephsplatz 8",
    "sg:city":"M\u00fcnchen",
    "sg:phone":"+49 89/2721570",
    "sg:postcode":"80798",
    "sg:province":"Bayern",
    "wof:name":"Eva M. Trappehl Rechtsanw\u00e4ltin",
    "wof:placetype":"venue"
},
  "geometry": {"coordinates":[11.5666313171,48.1559791565],"type":"Point"}
}