{
  "type": "Feature",
  "properties": {
    "iso:country":"DE",
    "sg:address":"Wildmoos 42",
    "sg:city":"Berchtesgaden",
    "sg:phone":"+49 8652/3991",
    "sg:postcode":"83471",
    "sg:province":"Bayern",
    "wof:name":"G\u00e4stehaus Neuh\u00e4usl",
    "wof:placetype":"venue"
},
  "geometry": {"coordinates":[13.0762500763,47.6613998413],"type":"Point"}
}