{
  "type": "Feature",
  "properties": {
    "iso:country":"DE",
    "sg:address":"Dieselstr. 7",
    "sg:city":"Gerlingen",
    "sg:phone":"+49 7156/29224",
    "sg:postcode":"70839",
    "sg:province":"Baden-W\u00fcrttemberg",
    "wof:name":"Wolff Walsrode Ag",
    "wof:placetype":"venue"
},
  "geometry": {"coordinates":[9.074519,48.803688],"type":"Point"}
}