{
  "type": "Feature",
  "properties": {
    "iso:country":"DE",
    "sg:address":"Sch\u00f6neb\u00fcrgstr. 7",
    "sg:city":"Crailsheim",
    "sg:phone":"+49 7951/7607",
    "sg:postcode":"74564",
    "sg:province":"Baden-W\u00fcrttemberg",
    "wof:name":"Fahrrad-grund Gmbh",
    "wof:placetype":"venue"
},
  "geometry": {"coordinates":[10.075271,49.137978],"type":"Point"}
}