{
  "type": "Feature",
  "properties": {
    "iso:country":"DE",
    "sg:address":"Hauptstr. 155",
    "sg:city":"Langenau",
    "sg:phone":"+49 37322/3709",
    "sg:postcode":"09636",
    "sg:province":"Baden-W\u00fcrttemberg",
    "wof:name":"R. Kotewitz Immobilienmakler",
    "wof:placetype":"venue"
},
  "geometry": {"coordinates":[13.2911500931,50.8437614441],"type":"Point"}
}