{
  "type": "Feature",
  "properties": {
    "iso:country":"DE",
    "sg:address":"Marktplatz 3",
    "sg:city":"K\u00f6\u00dflarn",
    "sg:phone":"+49 8536/335",
    "sg:postcode":"94149",
    "sg:province":"Bayern",
    "wof:name":"Martin Rauch",
    "wof:placetype":"venue"
},
  "geometry": {"coordinates":[13.1245002747,48.3712158203],"type":"Point"}
}