{
  "type": "Feature",
  "properties": {
    "iso:country":"DE",
    "sg:address":"Kirchstr. 154",
    "sg:city":"Herne",
    "sg:phone":"+49 2323/33861",
    "sg:postcode":"44628",
    "sg:province":"Nordrhein-Westfalen",
    "wof:name":"H.h. Knapp Elektroinstallation",
    "wof:placetype":"venue"
},
  "geometry": {"coordinates":[7.262969,51.549862],"type":"Point"}
}