{
  "type": "Feature",
  "properties": {
    "iso:country":"DE",
    "sg:address":"Liebknechtstr. 4",
    "sg:city":"Obertshausen",
    "sg:phone":"+49 6104/71086",
    "sg:postcode":"63179",
    "sg:province":"Hessen",
    "wof:name":"Christian Subtil",
    "wof:placetype":"venue"
},
  "geometry": {"coordinates":[8.864199,50.083378],"type":"Point"}
}