{
  "type": "Feature",
  "properties": {
    "iso:country":"DE",
    "sg:address":"Hauptstr. 61",
    "sg:city":"Engen",
    "sg:phone":"+49 7733/6099",
    "sg:postcode":"78234",
    "sg:province":"Baden-W\u00fcrttemberg",
    "wof:name":"Mina Lahmari Heilpraktikerin",
    "wof:placetype":"venue"
},
  "geometry": {"coordinates":[8.7712497711,47.8496284485],"type":"Point"}
}