{
  "type": "Feature",
  "properties": {
    "iso:country":"DE",
    "sg:address":"Halskesteig 4",
    "sg:city":"Berlin",
    "sg:phone":"+49 30/3814704",
    "sg:postcode":"13629",
    "sg:province":"Berlin",
    "wof:name":"Rudi H\u00f6ckert",
    "wof:placetype":"venue"
},
  "geometry": {"coordinates":[13.268631,52.537437],"type":"Point"}
}