{
  "type": "Feature",
  "properties": {
    "iso:country":"DE",
    "sg:address":"Johannisstr. 104",
    "sg:city":"N\u00fcrnberg",
    "sg:phone":"+49 911/933730",
    "sg:postcode":"90419",
    "sg:province":"Bayern",
    "wof:name":"Bestattungsinstitut B\u00e4rbel Brand Gmbh",
    "wof:placetype":"venue"
},
  "geometry": {"coordinates":[11.056512,49.460636],"type":"Point"}
}