{
  "type": "Feature",
  "properties": {
    "iso:country":"DE",
    "sg:address":"Heldelinger Str. 6",
    "sg:city":"Weil am Rhein",
    "sg:phone":"+49 7621/61514",
    "sg:postcode":"79576",
    "sg:province":"Baden-W\u00fcrttemberg",
    "wof:name":"Siegfried Segendorf Wettannahme",
    "wof:placetype":"venue"
},
  "geometry": {"coordinates":[7.610955,47.6134],"type":"Point"}
}