{
  "type": "Feature",
  "properties": {
    "iso:country":"DE",
    "sg:address":"B\u00fcrgerm-K\u00fcrten-Str 30-32",
    "sg:city":"Bremen",
    "sg:phone":"+49 421/6009582",
    "sg:postcode":"28779",
    "sg:province":"Bremen",
    "wof:name":"Parit\u00e4tische Pflegedienste Bremen",
    "wof:placetype":"venue"
},
  "geometry": {"coordinates":[8.578325,53.18589],"type":"Point"}
}