{
  "type": "Feature",
  "properties": {
    "iso:country":"DE",
    "sg:address":"Franz-Hitze-Str. 12",
    "sg:city":"Krefeld",
    "sg:phone":"+49 2151/398808",
    "sg:postcode":"47807",
    "sg:province":"Nordrhein-Westfalen",
    "wof:name":"Richter Und Schwiede",
    "wof:placetype":"venue"
},
  "geometry": {"coordinates":[6.585767,51.318172],"type":"Point"}
}