{
  "type": "Feature",
  "properties": {
    "iso:country":"DE",
    "sg:address":"Hauptst\u00e4tter Str. 116",
    "sg:city":"Stuttgart",
    "sg:phone":"+49 711/604160",
    "sg:postcode":"70178",
    "sg:province":"Baden-W\u00fcrttemberg",
    "wof:name":"Sportcenter Top-fit S. Stergios",
    "wof:placetype":"venue"
},
  "geometry": {"coordinates":[9.1717023849,48.7676849365],"type":"Point"}
}