{
  "type": "Feature",
  "properties": {
    "iso:country":"DE",
    "sg:address":"Eugenstr. 9",
    "sg:city":"Eningen",
    "sg:phone":"+49 7121/81410",
    "sg:postcode":"72800",
    "sg:province":"Baden-W\u00fcrttemberg",
    "wof:name":"Ernst Hummel",
    "wof:placetype":"venue"
},
  "geometry": {"coordinates":[9.256617,48.486603],"type":"Point"}
}