{
  "type": "Feature",
  "properties": {
    "iso:country":"DE",
    "sg:address":"Neubrunnenstr. 11",
    "sg:city":"Mainz",
    "sg:phone":"+49 6131/234418",
    "sg:postcode":"55116",
    "sg:province":"Rheinland-Pfalz",
    "wof:name":"Boogies",
    "wof:placetype":"venue"
},
  "geometry": {"coordinates":[8.2645616531,50.0024223328],"type":"Point"}
}