{
  "type": "Feature",
  "properties": {
    "iso:country":"DE",
    "sg:address":"Alte Dorfstr. 23",
    "sg:city":"Drensteinfurt",
    "sg:phone":"+49 2538/952310",
    "sg:postcode":"48317",
    "sg:province":"Nordrhein-Westfalen",
    "wof:name":"W. Bahrenberg",
    "wof:placetype":"venue"
},
  "geometry": {"coordinates":[7.67583,51.84539],"type":"Point"}
}