{
  "type": "Feature",
  "properties": {
    "iso:country":"DE",
    "sg:address":"Gr\u00fcner Weg 28",
    "sg:city":"Walddorfh\u00e4slach",
    "sg:phone":"+49 7127/33821",
    "sg:postcode":"72141",
    "sg:province":"Baden-W\u00fcrttemberg",
    "wof:name":"Uwe Werner",
    "wof:placetype":"venue"
},
  "geometry": {"coordinates":[9.179252,48.585869],"type":"Point"}
}