{
  "type": "Feature",
  "properties": {
    "iso:country":"DE",
    "sg:address":"Pescher Str. 75",
    "sg:city":"Korschenbroich",
    "sg:phone":"+49 2161/640402",
    "sg:postcode":"41352",
    "sg:province":"Nordrhein-Westfalen",
    "wof:name":"H. Thoren",
    "wof:placetype":"venue"
},
  "geometry": {"coordinates":[6.5222082138,51.1860923767],"type":"Point"}
}