{
  "type": "Feature",
  "properties": {
    "iso:country":"DE",
    "sg:address":"Augustaanlage 12",
    "sg:city":"Mannheim",
    "sg:phone":"+49 621/400040",
    "sg:postcode":"68165",
    "sg:province":"Baden-W\u00fcrttemberg",
    "wof:name":"Willmann & Monz Gmbh",
    "wof:placetype":"venue"
},
  "geometry": {"coordinates":[8.479754,49.48214],"type":"Point"}
}