{
  "type": "Feature",
  "properties": {
    "iso:country":"DE",
    "sg:address":"M\u00fchlweg 7",
    "sg:city":"Ehingen",
    "sg:phone":"+49 7391/6367",
    "sg:postcode":"89584",
    "sg:province":"Baden-W\u00fcrttemberg",
    "wof:name":"Alfons Buck",
    "wof:placetype":"venue"
},
  "geometry": {"coordinates":[9.717305,48.280846],"type":"Point"}
}