{
  "type": "Feature",
  "properties": {
    "iso:country":"DE",
    "sg:address":"R\u00fcgheim 10",
    "sg:city":"Hofheim",
    "sg:phone":"+49 9523/7458",
    "sg:postcode":"97461",
    "sg:province":"Bayern",
    "wof:name":"Diskothek Arena",
    "wof:placetype":"venue"
},
  "geometry": {"coordinates":[10.522491,50.133335],"type":"Point"}
}