{
  "type": "Feature",
  "properties": {
    "iso:country":"DE",
    "sg:address":"Stockweg 5",
    "sg:city":"Weil am Rhein",
    "sg:phone":"+49 7621/689788",
    "sg:postcode":"79576",
    "sg:province":"Baden-W\u00fcrttemberg",
    "wof:name":"Pes Privatisierungs-entwickl.- Und Sanierungs Gmbh",
    "wof:placetype":"venue"
},
  "geometry": {"coordinates":[7.621422,47.611088],"type":"Point"}
}