{
  "type": "Feature",
  "properties": {
    "iso:country":"DE",
    "sg:address":"Neudeker Str. 2",
    "sg:city":"Neutraubling",
    "sg:phone":"+49 9401/7739",
    "sg:postcode":"93073",
    "sg:province":"Bayern",
    "wof:name":"K. Markus & S\u00f6hne Steinmetzbetrieb Nachf.",
    "wof:placetype":"venue"
},
  "geometry": {"coordinates":[12.1987943649,48.9871749878],"type":"Point"}
}