{
  "type": "Feature",
  "properties": {
    "iso:country":"DE",
    "sg:address":"M\u00fchlangerstr. 4",
    "sg:city":"Horgau",
    "sg:phone":"+49 8294/2885",
    "sg:postcode":"86497",
    "sg:province":"Bayern",
    "wof:name":"H. Lange",
    "wof:placetype":"venue"
},
  "geometry": {"coordinates":[10.6544542313,48.3952903748],"type":"Point"}
}