{
  "type": "Feature",
  "properties": {
    "iso:country":"DE",
    "sg:address":"Dahlhauser Str. 167",
    "sg:city":"Essen",
    "sg:phone":"+49 201/534011",
    "sg:postcode":"45279",
    "sg:province":"Nordrhein-Westfalen",
    "wof:name":"Edgar Gorgas",
    "wof:placetype":"venue"
},
  "geometry": {"coordinates":[7.1040887833,51.4371376038],"type":"Point"}
}