{
  "type": "Feature",
  "properties": {
    "iso:country":"DE",
    "sg:address":"Lindenallee 2",
    "sg:city":"Seesen",
    "sg:phone":"+49 5381/47262",
    "sg:postcode":"38723",
    "sg:province":"Niedersachsen",
    "wof:name":"Fritz Willers",
    "wof:placetype":"venue"
},
  "geometry": {"coordinates":[10.125254631,51.8938179016],"type":"Point"}
}