{
  "type": "Feature",
  "properties": {
    "iso:country":"DE",
    "sg:address":"Bischwinder Str.",
    "sg:city":"Dingolshausen",
    "sg:phone":"+49 9382/7927",
    "sg:postcode":"97497",
    "sg:province":"Bayern",
    "wof:name":"Eberhard Reichert Architekt",
    "wof:placetype":"venue"
},
  "geometry": {"coordinates":[10.387489,49.906834],"type":"Point"}
}