{
  "type": "Feature",
  "properties": {
    "iso:country":"DE",
    "sg:address":"An der Sch\u00fctt 11",
    "sg:city":"Herzogenaurach",
    "sg:phone":"+49 9132/3888",
    "sg:postcode":"91074",
    "sg:province":"Bayern",
    "wof:name":"U. B\u00f6rgmann",
    "wof:placetype":"venue"
},
  "geometry": {"coordinates":[10.883228,49.567856],"type":"Point"}
}