{
  "type": "Feature",
  "properties": {
    "iso:country":"DE",
    "sg:address":"K\u00fchwasenstr. 34",
    "sg:city":"Balingen",
    "sg:phone":"+49 7433/4997",
    "sg:postcode":"72336",
    "sg:province":"Baden-W\u00fcrttemberg",
    "wof:name":"G. M\u00fcrdter",
    "wof:placetype":"venue"
},
  "geometry": {"coordinates":[8.8958263397,48.2403945923],"type":"Point"}
}