{
  "type": "Feature",
  "properties": {
    "iso:country":"DE",
    "sg:address":"Am Neumarkt 2-4 Schlo\u00dfpark",
    "sg:city":"Senftenberg",
    "sg:phone":"+49 3573/37410",
    "sg:postcode":"01968",
    "sg:province":"Brandenburg",
    "wof:name":"Khv-dienstleistungs- Und Service Gmbh",
    "wof:placetype":"venue"
},
  "geometry": {"coordinates":[14.00963,51.515202],"type":"Point"}
}