{
  "type": "Feature",
  "properties": {
    "iso:country":"DE",
    "sg:address":"Danziger Str. 71",
    "sg:city":"Berlin",
    "sg:phone":"+49 30/4427034",
    "sg:postcode":"10435",
    "sg:province":"Berlin",
    "wof:name":"Efs-bestattungen Gmbh",
    "wof:placetype":"venue"
},
  "geometry": {"coordinates":[13.423919,52.539471],"type":"Point"}
}