{
  "type": "Feature",
  "properties": {
    "iso:country":"DE",
    "sg:address":"Schulzendorfer Str. 16",
    "sg:city":"Berlin",
    "sg:phone":"+49 30/6766877",
    "sg:postcode":"12526",
    "sg:province":"Berlin",
    "wof:name":"Alfred Jakubowski",
    "wof:placetype":"venue"
},
  "geometry": {"coordinates":[13.577108,52.40242],"type":"Point"}
}