{
  "type": "Feature",
  "properties": {
    "iso:country":"DE",
    "sg:address":"Haferstr. 20e",
    "sg:city":"Augsburg",
    "sg:phone":"+49 821/881974",
    "sg:postcode":"86179",
    "sg:province":"Bayern",
    "wof:name":"Richard Birkner Haunstetter-immobilien",
    "wof:placetype":"venue"
},
  "geometry": {"coordinates":[10.8979892731,48.3034286499],"type":"Point"}
}