{
  "type": "Feature",
  "properties": {
    "iso:country":"DE",
    "sg:address":"Kurf\u00fcrstendamm 65",
    "sg:city":"Berlin",
    "sg:phone":"+49 30/8822096",
    "sg:postcode":"10707",
    "sg:province":"Berlin",
    "wof:name":"J\u00f6rg-dietrich Fockert Rechtsanwalt",
    "wof:placetype":"venue"
},
  "geometry": {"coordinates":[13.3101825714,52.5005455017],"type":"Point"}
}