{
  "type": "Feature",
  "properties": {
    "iso:country":"DE",
    "sg:address":"Gro\u00dfe D\u00fcwelstr. 48",
    "sg:city":"Hannover",
    "sg:phone":"+49 511/28869730",
    "sg:postcode":"30171",
    "sg:province":"Niedersachsen",
    "wof:name":"Dieter Streese Ingenieur",
    "wof:placetype":"venue"
},
  "geometry": {"coordinates":[9.7594623566,52.3650894165],"type":"Point"}
}