{
  "type": "Feature",
  "properties": {
    "iso:country":"DE",
    "sg:address":"Bruckwiesen 32",
    "sg:city":"Geislingen",
    "sg:postcode":"73312",
    "sg:province":"Baden-W\u00fcrttemberg",
    "wof:name":"Baugro Gmbh",
    "wof:placetype":"venue"
},
  "geometry": {"coordinates":[9.815899,48.62809],"type":"Point"}
}