{
  "type": "Feature",
  "properties": {
    "iso:country":"DE",
    "sg:address":"Gewerbestr. 2 a",
    "sg:city":"Nossen",
    "sg:phone":"+49 35242/64113",
    "sg:postcode":"01683",
    "sg:province":"Sachsen",
    "wof:name":"Autovermietung Hofmann Gmbh",
    "wof:placetype":"venue"
},
  "geometry": {"coordinates":[13.292273,51.048695],"type":"Point"}
}