{
  "type": "Feature",
  "properties": {
    "iso:country":"DE",
    "sg:address":"H\u00fclsberg 13",
    "sg:city":"Wuppertal",
    "sg:phone":"+49 202/471276",
    "sg:postcode":"42349",
    "sg:province":"Nordrhein-Westfalen",
    "wof:name":"Giovanni Schultz",
    "wof:placetype":"venue"
},
  "geometry": {"coordinates":[7.1278281212,51.19348526],"type":"Point"}
}