{
  "type": "Feature",
  "properties": {
    "iso:country":"DE",
    "sg:address":"Wallmodenweg 4",
    "sg:city":"Bad Salzdetfurth",
    "sg:phone":"+49 5064/639",
    "sg:postcode":"31162",
    "sg:province":"Niedersachsen",
    "wof:name":"Heinrich Stein",
    "wof:placetype":"venue"
},
  "geometry": {"coordinates":[10.033372,52.102612],"type":"Point"}
}