{
  "type": "Feature",
  "properties": {
    "iso:country":"DE",
    "sg:address":"Katharinenberg 13",
    "sg:city":"Gremsdorf",
    "sg:phone":"+49 9193/7731",
    "sg:postcode":"91350",
    "sg:province":"Bayern",
    "wof:name":"Gerhard Renner Masseur",
    "wof:placetype":"venue"
},
  "geometry": {"coordinates":[10.828347,49.69426],"type":"Point"}
}