{
  "type": "Feature",
  "properties": {
    "iso:country":"DE",
    "sg:address":"Freiligrathstr. 59",
    "sg:city":"K\u00f6ln",
    "sg:postcode":"50935",
    "sg:province":"Nordrhein-Westfalen",
    "wof:name":"Lma Gmbh",
    "wof:placetype":"venue"
},
  "geometry": {"coordinates":[6.902477,50.923161],"type":"Point"}
}