{
  "type": "Feature",
  "properties": {
    "iso:country":"DE",
    "sg:address":"Stegemannstr. 33-41",
    "sg:city":"Koblenz",
    "sg:phone":"+49 261/915600",
    "sg:postcode":"56068",
    "sg:province":"Rheinland-Pfalz",
    "wof:name":"Engel Und Dr. Stein Rechtsanw\u00e4lte",
    "wof:placetype":"venue"
},
  "geometry": {"coordinates":[7.5937209129,50.3562088013],"type":"Point"}
}