{
  "type": "Feature",
  "properties": {
    "iso:country":"DE",
    "sg:address":"Brandstr. 60",
    "sg:city":"Bad Sachsa",
    "sg:phone":"+49 5523/3776",
    "sg:postcode":"37441",
    "sg:province":"Niedersachsen",
    "wof:name":"Cafe Elfi",
    "wof:placetype":"venue"
},
  "geometry": {"coordinates":[10.537571,51.59988],"type":"Point"}
}