{
  "type": "Feature",
  "properties": {
    "iso:country":"DE",
    "sg:address":"Bahnhofstr. 1",
    "sg:city":"L\u00f6rrach",
    "sg:postcode":"79539",
    "sg:province":"Baden-W\u00fcrttemberg",
    "wof:name":"Alfred Planer",
    "wof:placetype":"venue"
},
  "geometry": {"coordinates":[7.66543,47.614956],"type":"Point"}
}