{
  "type": "Feature",
  "properties": {
    "iso:country":"DE",
    "sg:address":"Kuckucksweg 10",
    "sg:city":"K\u00f6nigstein",
    "sg:postcode":"61462",
    "sg:province":"Hessen",
    "wof:name":"Grundst\u00fccksverwaltung W. Hohloch Kg",
    "wof:placetype":"venue"
},
  "geometry": {"coordinates":[8.461693,50.169128],"type":"Point"}
}