{
  "type": "Feature",
  "properties": {
    "iso:country":"DE",
    "sg:address":"An der Wuhle 101",
    "sg:city":"Berlin",
    "sg:phone":"+49 30/5664340",
    "sg:postcode":"12621",
    "sg:province":"Berlin",
    "wof:name":"Advanced-electronic Technic Gmbh",
    "wof:placetype":"venue"
},
  "geometry": {"coordinates":[13.563806,52.481373],"type":"Point"}
}