{
  "type": "Feature",
  "properties": {
    "iso:country":"DE",
    "sg:address":"Holtenauer Str. 174",
    "sg:city":"Kiel",
    "sg:phone":"+49 431/87646",
    "sg:postcode":"24105",
    "sg:province":"Schleswig-Holstein",
    "wof:name":"Hans Nommensen",
    "wof:placetype":"venue"
},
  "geometry": {"coordinates":[10.133879,54.3409],"type":"Point"}
}