{
  "type": "Feature",
  "properties": {
    "iso:country":"DE",
    "sg:address":"Kortumstr. 36",
    "sg:city":"Bochum",
    "sg:phone":"+49 234/459880",
    "sg:postcode":"44787",
    "sg:province":"Nordrhein-Westfalen",
    "wof:name":"It Lizenzsystem Gmbh & Co. Dienstleistungen Kg",
    "wof:placetype":"venue"
},
  "geometry": {"coordinates":[7.217083931,51.4781074524],"type":"Point"}
}