{
  "type": "Feature",
  "properties": {
    "iso:country":"DE",
    "sg:address":"Hauptstr. 15",
    "sg:city":"Winterberg",
    "sg:phone":"+49 2981/1712",
    "sg:postcode":"59955",
    "sg:province":"Nordrhein-Westfalen",
    "wof:name":"Robert Wahle",
    "wof:placetype":"venue"
},
  "geometry": {"coordinates":[8.53571,51.194141],"type":"Point"}
}