{
  "type": "Feature",
  "properties": {
    "iso:country":"DE",
    "sg:address":"Winkelmanns Graft 12",
    "sg:city":"Celle",
    "sg:phone":"+49 5141/82137",
    "sg:postcode":"29227",
    "sg:province":"Niedersachsen",
    "wof:name":"Michael B\u00e4tje Dentaltechnik Gmbh",
    "wof:placetype":"venue"
},
  "geometry": {"coordinates":[10.059454,52.585766],"type":"Point"}
}