{
  "type": "Feature",
  "properties": {
    "iso:country":"DE",
    "sg:address":"Postfach 1244",
    "sg:city":"Lauda-K\u00f6nigshofen",
    "sg:phone":"+49 7931/41793",
    "sg:postcode":"97912",
    "sg:province":"Baden-W\u00fcrttemberg",
    "wof:name":"Richard Kablitz & Mitthof Gmbh",
    "wof:placetype":"venue"
},
  "geometry": {"coordinates":[9.7028799057,49.5675010681],"type":"Point"}
}