{
  "type": "Feature",
  "properties": {
    "iso:country":"DE",
    "sg:address":"Am Mondschein 26",
    "sg:city":"Lippstadt",
    "sg:phone":"+49 2941/7025",
    "sg:postcode":"59557",
    "sg:province":"Nordrhein-Westfalen",
    "wof:name":"Praktiker Bau- Und Heimwerkermarkt",
    "wof:placetype":"venue"
},
  "geometry": {"coordinates":[8.3709201813,51.6768684387],"type":"Point"}
}