{
  "type": "Feature",
  "properties": {
    "iso:country":"DE",
    "sg:address":"G\u00fcntherstr. 4",
    "sg:city":"Fulda",
    "sg:postcode":"36043",
    "sg:province":"Hessen",
    "wof:name":"Baker Ton- Und Lichttechnik E. K.",
    "wof:placetype":"venue"
},
  "geometry": {"coordinates":[9.682225,50.531574],"type":"Point"}
}