{
  "type": "Feature",
  "properties": {
    "iso:country":"DE",
    "sg:address":"Chemnitzer Str. 38",
    "sg:city":"Leisnig",
    "sg:phone":"+49 34321/12201",
    "sg:postcode":"04703",
    "sg:province":"Sachsen",
    "wof:name":"Cafe Gitt",
    "wof:placetype":"venue"
},
  "geometry": {"coordinates":[12.927352,51.155136],"type":"Point"}
}