{
  "type": "Feature",
  "properties": {
    "iso:country":"DE",
    "sg:address":"Quitzowstr. 107",
    "sg:city":"Berlin",
    "sg:phone":"+49 30/3955081",
    "sg:postcode":"10551",
    "sg:province":"Berlin",
    "wof:name":"Jonschel & Co. Gmbh",
    "wof:placetype":"venue"
},
  "geometry": {"coordinates":[13.342467308,52.5341529846],"type":"Point"}
}