{
  "type": "Feature",
  "properties": {
    "iso:country":"DE",
    "sg:address":"Industrieweg 20",
    "sg:city":"Hille",
    "sg:phone":"+49 5703/2382",
    "sg:postcode":"32479",
    "sg:province":"Nordrhein-Westfalen",
    "wof:name":"Gerhard Wiese Hille",
    "wof:placetype":"venue"
},
  "geometry": {"coordinates":[8.8087701797,52.3420448303],"type":"Point"}
}