{
  "type": "Feature",
  "properties": {
    "iso:country":"DE",
    "sg:address":"Ebersberger Str. 74",
    "sg:city":"Bad Aibling",
    "sg:phone":"+49 8061/2556",
    "sg:postcode":"83043",
    "sg:province":"Bayern",
    "wof:name":"Ludwig Englmeier",
    "wof:placetype":"venue"
},
  "geometry": {"coordinates":[11.99353,47.879719],"type":"Point"}
}