{
  "type": "Feature",
  "properties": {
    "iso:country":"DE",
    "sg:address":"Marktplatz 4",
    "sg:city":"Villingen-Schwenningen",
    "sg:phone":"+49 7720/35788",
    "sg:postcode":"78054",
    "sg:province":"Baden-W\u00fcrttemberg",
    "wof:name":"E. Schlenker Gmbh",
    "wof:placetype":"venue"
},
  "geometry": {"coordinates":[8.535659,48.06559],"type":"Point"}
}