{
  "type": "Feature",
  "properties": {
    "iso:country":"DE",
    "sg:address":"Markt 5",
    "sg:city":"Neustrelitz",
    "sg:postcode":"17235",
    "sg:province":"Mecklenburg-Vorpommern",
    "wof:name":"Pharmazeutisches Zentrum",
    "wof:placetype":"venue"
},
  "geometry": {"coordinates":[13.0628623962,53.3629493713],"type":"Point"}
}