{
  "type": "Feature",
  "properties": {
    "iso:country":"DE",
    "sg:address":"M\u00fchlenweg 10",
    "sg:city":"Fischbachau",
    "sg:phone":"+49 8028/1773",
    "sg:postcode":"83730",
    "sg:province":"Bayern",
    "wof:name":"Bernhard Obliers Architekt",
    "wof:placetype":"venue"
},
  "geometry": {"coordinates":[11.957742,47.716106],"type":"Point"}
}