{
  "type": "Feature",
  "properties": {
    "iso:country":"DE",
    "sg:address":"Rathmann-Benecke-Str. 3",
    "sg:city":"Bardowick",
    "sg:phone":"+49 4131/128887",
    "sg:postcode":"21357",
    "sg:province":"Niedersachsen",
    "wof:name":"A-z Musikkartei G. Oberdieck",
    "wof:placetype":"venue"
},
  "geometry": {"coordinates":[10.3856115341,53.2916183472],"type":"Point"}
}