{
  "type": "Feature",
  "properties": {
    "iso:country":"DE",
    "sg:address":"Kaiserstr. 32",
    "sg:city":"Mainz",
    "sg:phone":"+49 4961/3124123",
    "sg:postcode":"55116",
    "sg:province":"Rheinland-Pfalz",
    "wof:name":"Bank F\u00fcr Gemeinwirtschaft",
    "wof:placetype":"venue"
},
  "geometry": {"coordinates":[8.264201,50.00436],"type":"Point"}
}