{
  "type": "Feature",
  "properties": {
    "iso:country":"DE",
    "sg:address":"Pyrmonter Str. 152",
    "sg:city":"Horn-Bad Meinberg",
    "sg:phone":"+49 5233/3376",
    "sg:postcode":"32805",
    "sg:province":"Nordrhein-Westfalen",
    "wof:name":"Bike Scheune Motorr\u00e4der Beteiligungs Gmbh",
    "wof:placetype":"venue"
},
  "geometry": {"coordinates":[9.0571975708,51.8968505859],"type":"Point"}
}