{
  "type": "Feature",
  "properties": {
    "iso:country":"DE",
    "sg:address":"Arminstr. 55",
    "sg:city":"Bensheim",
    "sg:postcode":"64625",
    "sg:province":"Hessen",
    "wof:name":"Fiwi Handelsvertretungs- Und Dienstleistungs Gmbh",
    "wof:placetype":"venue"
},
  "geometry": {"coordinates":[8.6328039169,49.6683044434],"type":"Point"}
}