{
  "type": "Feature",
  "properties": {
    "iso:country":"DE",
    "sg:address":"Bergheimer Str. 53",
    "sg:city":"Essen",
    "sg:phone":"+49 201/601111",
    "sg:postcode":"45359",
    "sg:province":"Nordrhein-Westfalen",
    "wof:name":"Alfred Lingnau",
    "wof:placetype":"venue"
},
  "geometry": {"coordinates":[6.9273309708,51.4697341919],"type":"Point"}
}