{
  "type": "Feature",
  "properties": {
    "iso:country":"DE",
    "sg:address":"Industriegebiet S\u00fcd",
    "sg:city":"F\u00f6rderstedt",
    "sg:phone":"+49 39266/7600",
    "sg:postcode":"39443",
    "sg:province":"Sachsen-Anhalt",
    "wof:name":"Metec Gmbh",
    "wof:placetype":"venue"
},
  "geometry": {"coordinates":[11.628915,51.891834],"type":"Point"}
}