{
  "type": "Feature",
  "properties": {
    "iso:country":"DE",
    "sg:address":"Stargarder Str. 72",
    "sg:city":"Berlin",
    "sg:phone":"+49 30/4458296",
    "sg:postcode":"10437",
    "sg:province":"Berlin",
    "wof:name":"Paris-berlin Specialites Francaises Karin Falkus",
    "wof:placetype":"venue"
},
  "geometry": {"coordinates":[13.417816,52.546837],"type":"Point"}
}