{
  "type": "Feature",
  "properties": {
    "iso:country":"DE",
    "sg:address":"Am Ritterhof 43",
    "sg:city":"Eschborn",
    "sg:phone":"+49 6196/41980",
    "sg:postcode":"65760",
    "sg:province":"Hessen",
    "wof:name":"Kr\u00fcger Beteiligungs- Und Beratungs Gmbh",
    "wof:placetype":"venue"
},
  "geometry": {"coordinates":[8.569847,50.145081],"type":"Point"}
}