{
  "type": "Feature",
  "properties": {
    "iso:country":"DE",
    "sg:address":"Bahnhofstr.",
    "sg:city":"Eppingen",
    "sg:phone":"+49 7262/4711",
    "sg:postcode":"75031",
    "sg:province":"Baden-W\u00fcrttemberg",
    "wof:name":"Margit Korth",
    "wof:placetype":"venue"
},
  "geometry": {"coordinates":[8.910964,49.135712],"type":"Point"}
}