{
  "type": "Feature",
  "properties": {
    "iso:country":"DE",
    "sg:address":"Amelsb\u00fcrener Str. 1",
    "sg:city":"Ascheberg",
    "sg:phone":"+49 2593/1629",
    "sg:postcode":"59387",
    "sg:province":"Nordrhein-Westfalen",
    "wof:name":"Glanemann Gmbh Technischer Gro\u00dfhandel",
    "wof:placetype":"venue"
},
  "geometry": {"coordinates":[7.5995678902,51.8146858215],"type":"Point"}
}