{
  "type": "Feature",
  "properties": {
    "iso:country":"DE",
    "sg:address":"Stra\u00dfburger Str. 253",
    "sg:city":"Oberhausen",
    "sg:phone":"+49 208/874949",
    "sg:postcode":"46045",
    "sg:province":"Nordrhein-Westfalen",
    "wof:name":"Adalbert Hofmann Steuerberater",
    "wof:placetype":"venue"
},
  "geometry": {"coordinates":[6.8666648865,51.4657745361],"type":"Point"}
}