{
  "type": "Feature",
  "properties": {
    "iso:country":"DE",
    "sg:address":"Otto-Quandt-Str. 12",
    "sg:city":"Landsberg",
    "sg:phone":"+49 34602/20845",
    "sg:postcode":"06188",
    "sg:province":"Sachsen-Anhalt",
    "wof:name":"R. Kottwitz",
    "wof:placetype":"venue"
},
  "geometry": {"coordinates":[12.1524438858,51.5277557373],"type":"Point"}
}