{
  "type": "Feature",
  "properties": {
    "iso:country":"DE",
    "sg:address":"Karlstrasse 15",
    "sg:city":"Augsburg",
    "sg:phone":"+49 821/502120",
    "sg:postcode":"86150",
    "sg:province":"Bayern",
    "wof:name":"Hotel Lochbrunner Im Herzen Von Augsburg",
    "wof:placetype":"venue"
},
  "geometry": {"coordinates":[10.896287,48.370071],"type":"Point"}
}