{
  "type": "Feature",
  "properties": {
    "iso:country":"DE",
    "sg:address":"Markt 29",
    "sg:city":"Hettstedt",
    "sg:phone":"+49 3476/81004",
    "sg:postcode":"06333",
    "sg:province":"Sachsen-Anhalt",
    "wof:name":"Schilderdienst Gmbh",
    "wof:placetype":"venue"
},
  "geometry": {"coordinates":[11.512475,51.645805],"type":"Point"}
}