{
  "type": "Feature",
  "properties": {
    "iso:country":"DE",
    "sg:address":"Neumarkt 13",
    "sg:city":"Schwelm",
    "sg:phone":"+49 2336/3431",
    "sg:postcode":"58332",
    "sg:province":"Nordrhein-Westfalen",
    "wof:name":"Kosmetikinstitut Weber Inh. Sandra K\u00f6hling-weber",
    "wof:placetype":"venue"
},
  "geometry": {"coordinates":[7.293272,51.286057],"type":"Point"}
}