{
  "type": "Feature",
  "properties": {
    "iso:country":"DE",
    "sg:address":"Streichet 12",
    "sg:city":"Lichtenwald",
    "sg:phone":"+49 4971/5342123",
    "sg:postcode":"73669",
    "sg:province":"Baden-W\u00fcrttemberg",
    "wof:name":"Weiler Gmbh",
    "wof:placetype":"venue"
},
  "geometry": {"coordinates":[9.4737672806,48.7306861877],"type":"Point"}
}