{
  "type": "Feature",
  "properties": {
    "iso:country":"DE",
    "sg:address":"Purrbachstr. 5",
    "sg:city":"Jetzendorf",
    "sg:postcode":"85305",
    "sg:province":"Bayern",
    "wof:name":"Professional-automation Gmbh",
    "wof:placetype":"venue"
},
  "geometry": {"coordinates":[11.436809,48.434437],"type":"Point"}
}