{
  "type": "Feature",
  "properties": {
    "iso:country":"DE",
    "sg:address":"Heckentalstr. 16",
    "sg:city":"Heidenheim",
    "sg:postcode":"89518",
    "sg:province":"Baden-W\u00fcrttemberg",
    "wof:name":"Blumen-pommerenke Klaus Pommerenke E. K.",
    "wof:placetype":"venue"
},
  "geometry": {"coordinates":[10.13891,48.681339],"type":"Point"}
}