{
  "type": "Feature",
  "properties": {
    "iso:country":"DE",
    "sg:address":"Meierhofstr. 6",
    "sg:city":"Oberweser",
    "sg:phone":"+49 5572/507",
    "sg:postcode":"34399",
    "sg:province":"Hessen",
    "wof:name":"W. D\u00f6rbaum",
    "wof:placetype":"venue"
},
  "geometry": {"coordinates":[9.5499296188,51.5974273682],"type":"Point"}
}