{
  "type": "Feature",
  "properties": {
    "iso:country":"DE",
    "sg:address":"Bahnhofstr. 28",
    "sg:city":"Piesport",
    "sg:phone":"+49 6507/2444",
    "sg:postcode":"54498",
    "sg:province":"Rheinland-Pfalz",
    "wof:name":"Hubert Kirsten Weinanbau",
    "wof:placetype":"venue"
},
  "geometry": {"coordinates":[6.9242329597,49.8804321289],"type":"Point"}
}