{
  "type": "Feature",
  "properties": {
    "iso:country":"DE",
    "sg:address":"Kirchstr. 15",
    "sg:city":"Blumberg",
    "sg:phone":"+49 7702/2908",
    "sg:postcode":"78176",
    "sg:province":"Baden-W\u00fcrttemberg",
    "wof:name":"Johann Holzner",
    "wof:placetype":"venue"
},
  "geometry": {"coordinates":[8.532779,47.837723],"type":"Point"}
}