{
  "type": "Feature",
  "properties": {
    "iso:country":"DE",
    "sg:address":"Br\u00fchlstr. 11",
    "sg:city":"Nast\u00e4tten",
    "sg:phone":"+49 6772/1489",
    "sg:postcode":"56355",
    "sg:province":"Rheinland-Pfalz",
    "wof:name":"Gerd Schr\u00f6der Masseur",
    "wof:placetype":"venue"
},
  "geometry": {"coordinates":[7.855005,50.199394],"type":"Point"}
}