{
  "type": "Feature",
  "properties": {
    "iso:country":"DE",
    "sg:address":"Wasserfuhr 47 a",
    "sg:city":"Bad Salzuflen",
    "sg:phone":"+49 5222/82457",
    "sg:postcode":"32108",
    "sg:province":"Nordrhein-Westfalen",
    "wof:name":"Eva Dettmeyer Krankengymnastin",
    "wof:placetype":"venue"
},
  "geometry": {"coordinates":[8.763811,52.073902],"type":"Point"}
}