{
  "type": "Feature",
  "properties": {
    "iso:country":"DE",
    "sg:address":"Konrad-Adenauer-Allee",
    "sg:city":"Dillingen",
    "sg:phone":"+49 6831/78939",
    "sg:postcode":"66763",
    "sg:province":"Saarland",
    "wof:name":"Anglerheim",
    "wof:placetype":"venue"
},
  "geometry": {"coordinates":[6.7140598297,49.3475532532],"type":"Point"}
}