{
  "type": "Feature",
  "properties": {
    "iso:country":"DE",
    "sg:address":"Kehlenweg 3",
    "sg:city":"Balgheim",
    "sg:phone":"+49 7424/3236",
    "sg:postcode":"78582",
    "sg:province":"Baden-W\u00fcrttemberg",
    "wof:name":"K. Distel Datenverarbeitung",
    "wof:placetype":"venue"
},
  "geometry": {"coordinates":[8.7655134201,48.069694519],"type":"Point"}
}