{
  "type": "Feature",
  "properties": {
    "iso:country":"DE",
    "sg:address":"Victor-Slotosch-Str. 17",
    "sg:city":"Frankfurt",
    "sg:phone":"+49 6109/32143",
    "sg:postcode":"60388",
    "sg:province":"Hessen",
    "wof:name":"Metallbau Hans M\u00fcller & Co Ohg",
    "wof:placetype":"venue"
},
  "geometry": {"coordinates":[8.745347,50.14349],"type":"Point"}
}