{
  "type": "Feature",
  "properties": {
    "iso:country":"DE",
    "sg:address":"In den Benten 13",
    "sg:city":"Detmold",
    "sg:phone":"+49 5232/98650",
    "sg:postcode":"32758",
    "sg:province":"Nordrhein-Westfalen",
    "wof:name":"Pfarramt Ii Ev. Ref. Kirche",
    "wof:placetype":"venue"
},
  "geometry": {"coordinates":[8.8091526031,51.9482917786],"type":"Point"}
}