{
  "type": "Feature",
  "properties": {
    "iso:country":"DE",
    "sg:address":"He\u00dfstr.66",
    "sg:city":"M\u00fcnchen",
    "sg:phone":"+49 89/527300",
    "sg:postcode":"80798",
    "sg:province":"Bayern",
    "wof:name":"Holzinger & Nanko Gmbh",
    "wof:placetype":"venue"
},
  "geometry": {"coordinates":[11.563656,48.152721],"type":"Point"}
}