{
  "type": "Feature",
  "properties": {
    "iso:country":"DE",
    "sg:address":"Bayerwaldstr. 31",
    "sg:city":"Hutthurm",
    "sg:phone":"+49 8505/922092",
    "sg:postcode":"94116",
    "sg:province":"Bayern",
    "wof:name":"T. Ehm",
    "wof:placetype":"venue"
},
  "geometry": {"coordinates":[13.4839134216,48.6695823669],"type":"Point"}
}