{
  "type": "Feature",
  "properties": {
    "iso:country":"DE",
    "sg:address":"Pleinfelder Str. 70",
    "sg:city":"Georgensgm\u00fcnd",
    "sg:phone":"+49 9172/67930",
    "sg:postcode":"91166",
    "sg:province":"Bayern",
    "wof:name":"R\u00f6hler Touristik Gmbh",
    "wof:placetype":"venue"
},
  "geometry": {"coordinates":[11.0126638412,49.1747665405],"type":"Point"}
}