{
  "type": "Feature",
  "properties": {
    "iso:country":"DE",
    "sg:address":"Bahnhofstr. 25",
    "sg:city":"L\u00fcbben",
    "sg:phone":"+49 3546/3564",
    "sg:postcode":"15907",
    "sg:province":"Brandenburg",
    "wof:name":"Norbert Stephan",
    "wof:placetype":"venue"
},
  "geometry": {"coordinates":[13.882275,51.93684],"type":"Point"}
}