{
  "type": "Feature",
  "properties": {
    "iso:country":"DE",
    "sg:address":"Hauptstr. 8",
    "sg:city":"Kirchheim",
    "sg:phone":"+49 7143/93731",
    "sg:postcode":"74366",
    "sg:province":"Baden-W\u00fcrttemberg",
    "wof:name":"S\u00fcddeutsche Kokillen- Gie\u00dferei Gmbh",
    "wof:placetype":"venue"
},
  "geometry": {"coordinates":[9.575412,50.836033],"type":"Point"}
}