{
  "type": "Feature",
  "properties": {
    "iso:country":"DE",
    "sg:address":"Finkenstr. 10",
    "sg:city":"Dautphetal",
    "sg:phone":"+49 6466/80104",
    "sg:postcode":"35232",
    "sg:province":"Hessen",
    "wof:name":"Martin Kr\u00fcger",
    "wof:placetype":"venue"
},
  "geometry": {"coordinates":[8.596881,50.87635],"type":"Point"}
}