{
  "type": "Feature",
  "properties": {
    "iso:country":"DE",
    "sg:address":"Wahmstr. 26",
    "sg:city":"L\u00fcbeck",
    "sg:phone":"+49 451/71448",
    "sg:postcode":"23552",
    "sg:province":"Schleswig-Holstein",
    "wof:name":"Escom Computer Ag",
    "wof:placetype":"venue"
},
  "geometry": {"coordinates":[10.6870670319,53.8652496338],"type":"Point"}
}