{
  "type": "Feature",
  "properties": {
    "iso:country":"DE",
    "sg:address":"K\u00f6nigsberger Str. 4",
    "sg:city":"Schneverdingen",
    "sg:phone":"+49 5193/7666",
    "sg:postcode":"29640",
    "sg:province":"Niedersachsen",
    "wof:name":"Gert Reitinger Grundst\u00fcck Gmbh",
    "wof:placetype":"venue"
},
  "geometry": {"coordinates":[9.8011703491,53.1084518433],"type":"Point"}
}