{
  "type": "Feature",
  "properties": {
    "iso:country":"DE",
    "sg:address":"Bahnhofstr. 147",
    "sg:city":"Gangelt",
    "sg:phone":"+49 2454/8272",
    "sg:postcode":"52538",
    "sg:province":"Nordrhein-Westfalen",
    "wof:name":"Josef Meiers Gmbh",
    "wof:placetype":"venue"
},
  "geometry": {"coordinates":[6.05619,51.009102],"type":"Point"}
}