{
  "type": "Feature",
  "properties": {
    "iso:country":"DE",
    "sg:address":"Neugasse 11",
    "sg:city":"Mainz",
    "sg:phone":"+49 6136/43264",
    "sg:postcode":"55129",
    "sg:province":"Rheinland-Pfalz",
    "wof:name":"V. Mayer",
    "wof:placetype":"venue"
},
  "geometry": {"coordinates":[8.246783,49.912827],"type":"Point"}
}