{
  "type": "Feature",
  "properties": {
    "iso:country":"DE",
    "sg:address":"Schwabenstr. 3",
    "sg:city":"Buchloe",
    "sg:postcode":"86807",
    "sg:province":"Bayern",
    "wof:name":"Schwabenhalle",
    "wof:placetype":"venue"
},
  "geometry": {"coordinates":[10.70687,48.029129],"type":"Point"}
}