{
  "type": "Feature",
  "properties": {
    "iso:country":"DE",
    "sg:address":"Kantstr. 32",
    "sg:city":"Berlin",
    "sg:phone":"+49 30/3138277",
    "sg:postcode":"10625",
    "sg:province":"Berlin",
    "wof:name":"Raffaela Moden",
    "wof:placetype":"venue"
},
  "geometry": {"coordinates":[13.316809,52.506329],"type":"Point"}
}