{
  "type": "Feature",
  "properties": {
    "iso:country":"DE",
    "sg:address":"Keldenicher Str. 52",
    "sg:city":"Kall",
    "sg:phone":"+49 2441/1774",
    "sg:postcode":"53925",
    "sg:province":"Nordrhein-Westfalen",
    "wof:name":"Adele P\u00fctz",
    "wof:placetype":"venue"
},
  "geometry": {"coordinates":[6.5694842339,50.5399894714],"type":"Point"}
}