{
  "type": "Feature",
  "properties": {
    "iso:country":"DE",
    "sg:address":"Kaiserin-Augusta-Str. 85",
    "sg:city":"Berlin",
    "sg:phone":"+49 30/7525285",
    "sg:postcode":"12099",
    "sg:province":"Berlin",
    "wof:name":"R.s. Elektrobau Gmbh",
    "wof:placetype":"venue"
},
  "geometry": {"coordinates":[13.3866443634,52.4590110779],"type":"Point"}
}