{
  "type": "Feature",
  "properties": {
    "iso:country":"DE",
    "sg:address":"Bergstr. 7",
    "sg:city":"R\u00fcckersdorf",
    "sg:phone":"+49 911/578434",
    "sg:postcode":"90607",
    "sg:province":"Bayern",
    "wof:name":"Hans-erich Reizammer Zentralheizungen",
    "wof:placetype":"venue"
},
  "geometry": {"coordinates":[11.2439079285,49.4950561523],"type":"Point"}
}