{
  "type": "Feature",
  "properties": {
    "iso:country":"DE",
    "sg:address":"John-Schehr-Str. 25",
    "sg:city":"Berlin",
    "sg:phone":"+49 30/4238058",
    "sg:postcode":"10407",
    "sg:province":"Berlin",
    "wof:name":"Frinab Metallhandels Gmbh",
    "wof:placetype":"venue"
},
  "geometry": {"coordinates":[13.437409,52.536404],"type":"Point"}
}