{
  "type": "Feature",
  "properties": {
    "iso:country":"DE",
    "sg:address":"Schalmeistr. 8",
    "sg:city":"G\u00f6ppingen",
    "sg:phone":"+49 7161/75424",
    "sg:postcode":"73033",
    "sg:province":"Baden-W\u00fcrttemberg",
    "wof:name":"Albert Keim Gmbh",
    "wof:placetype":"venue"
},
  "geometry": {"coordinates":[9.658222,48.708241],"type":"Point"}
}