{
  "type": "Feature",
  "properties": {
    "iso:country":"DE",
    "sg:address":"An der Bahn 1",
    "sg:city":"Apenburg",
    "sg:phone":"+49 39001/567",
    "sg:postcode":"38486",
    "sg:province":"Sachsen-Anhalt",
    "wof:name":"Ernst-otto Heinz",
    "wof:placetype":"venue"
},
  "geometry": {"coordinates":[11.204475,52.713726],"type":"Point"}
}