{
  "type": "Feature",
  "properties": {
    "iso:country":"DE",
    "sg:address":"Hannoversche Str. 56",
    "sg:city":"Isernhagen",
    "sg:phone":"+49 511/614444",
    "sg:postcode":"30916",
    "sg:province":"Niedersachsen",
    "wof:name":"Horst Schmidt Immobilienmakler",
    "wof:placetype":"venue"
},
  "geometry": {"coordinates":[9.8571977615,52.4327468872],"type":"Point"}
}