{
  "type": "Feature",
  "properties": {
    "iso:country":"DE",
    "sg:address":"Am Sportzentrum",
    "sg:city":"Sondershausen",
    "sg:phone":"+49 3632/782340",
    "sg:postcode":"99706",
    "sg:province":"Th\u00fcringen",
    "wof:name":"Am G\u00f6ldner",
    "wof:placetype":"venue"
},
  "geometry": {"coordinates":[10.8679618835,51.364616394],"type":"Point"}
}