{
  "type": "Feature",
  "properties": {
    "iso:country":"DE",
    "sg:address":"Oberes Daufeld 1",
    "sg:city":"Daun",
    "sg:phone":"+49 6592/2789",
    "sg:postcode":"54550",
    "sg:province":"Rheinland-Pfalz",
    "wof:name":"Adalbert Hommes Architekt",
    "wof:placetype":"venue"
},
  "geometry": {"coordinates":[6.830699,50.190578],"type":"Point"}
}