{
  "type": "Feature",
  "properties": {
    "iso:country":"DE",
    "sg:address":"Nelkenweg 16",
    "sg:city":"M\u00fchlheim",
    "sg:phone":"+49 6151/714687",
    "sg:postcode":"63165",
    "sg:province":"Hessen",
    "wof:name":"Inge Bukatschek",
    "wof:placetype":"venue"
},
  "geometry": {"coordinates":[8.832816124,50.11145401],"type":"Point"}
}