{
  "type": "Feature",
  "properties": {
    "iso:country":"DE",
    "sg:address":"Br\u00fcderstr. 54-56",
    "sg:city":"Soest",
    "sg:phone":"+49 2921/348888",
    "sg:postcode":"59494",
    "sg:province":"Nordrhein-Westfalen",
    "wof:name":"Becker It-komminikations- Gmbh",
    "wof:placetype":"venue"
},
  "geometry": {"coordinates":[8.1034450531,51.5761909485],"type":"Point"}
}