{
  "type": "Feature",
  "properties": {
    "iso:country":"DE",
    "sg:address":"Poststr. 2",
    "sg:city":"L\u00fcgde",
    "sg:phone":"+49 5283/647",
    "sg:postcode":"32676",
    "sg:province":"Nordrhein-Westfalen",
    "wof:name":"Blaschke",
    "wof:placetype":"venue"
},
  "geometry": {"coordinates":[9.2832927704,51.8792114258],"type":"Point"}
}