{
  "type": "Feature",
  "properties": {
    "iso:country":"DE",
    "sg:address":"Karl-Schurz-Str. 37",
    "sg:city":"Leipzig",
    "sg:phone":"+49 341/4412140",
    "sg:postcode":"04179",
    "sg:province":"Sachsen",
    "wof:name":"Rainer Kunze",
    "wof:placetype":"venue"
},
  "geometry": {"coordinates":[12.3069696426,51.3517112732],"type":"Point"}
}