{
  "type": "Feature",
  "properties": {
    "iso:country":"DE",
    "sg:address":"Im Koppelfeld 9",
    "sg:city":"Horstmar",
    "sg:phone":"+49 2558/661",
    "sg:postcode":"48612",
    "sg:province":"Nordrhein-Westfalen",
    "wof:name":"Restaurant Im Koppelfeld Inh. Peter Mett",
    "wof:placetype":"venue"
},
  "geometry": {"coordinates":[7.3118839264,52.0871429443],"type":"Point"}
}