{
  "type": "Feature",
  "properties": {
    "iso:country":"DE",
    "sg:address":"Humboldtstr. 27",
    "sg:city":"Simmerath",
    "sg:phone":"+49 2473/7878",
    "sg:postcode":"52152",
    "sg:province":"Nordrhein-Westfalen",
    "wof:name":"Horst Br\u00fcll",
    "wof:placetype":"venue"
},
  "geometry": {"coordinates":[6.306997,50.608795],"type":"Point"}
}