{
  "type": "Feature",
  "properties": {
    "iso:country":"DE",
    "sg:address":"Inselstr.",
    "sg:city":"Bad Abbach",
    "sg:phone":"+49 9405/5454",
    "sg:postcode":"93077",
    "sg:province":"Bayern",
    "wof:name":"Inselwirt",
    "wof:placetype":"venue"
},
  "geometry": {"coordinates":[12.0324306488,48.9373397827],"type":"Point"}
}