{
  "type": "Feature",
  "properties": {
    "iso:country":"DE",
    "sg:address":"Mariendorfer Damm 52",
    "sg:city":"Berlin",
    "sg:phone":"+49 30/7061495",
    "sg:postcode":"12109",
    "sg:province":"Berlin",
    "wof:name":"Linke Inh. Ute Israel",
    "wof:placetype":"venue"
},
  "geometry": {"coordinates":[13.384979,52.448254],"type":"Point"}
}