{
  "type": "Feature",
  "properties": {
    "iso:country":"DE",
    "sg:address":"Kurt-Schlosser-Str.",
    "sg:city":"Riesa",
    "sg:phone":"+49 3525/891031",
    "sg:postcode":"01591",
    "sg:province":"Sachsen",
    "wof:name":"Supermarkt Fischer Gmbh",
    "wof:placetype":"venue"
},
  "geometry": {"coordinates":[13.2619199753,51.3190193176],"type":"Point"}
}