{
  "type": "Feature",
  "properties": {
    "iso:country":"DE",
    "sg:address":"R\u00f6merstr. 21",
    "sg:city":"Hamminkeln",
    "sg:phone":"+49 2852/4777",
    "sg:postcode":"46499",
    "sg:province":"Nordrhein-Westfalen",
    "wof:name":"Peter Stark",
    "wof:placetype":"venue"
},
  "geometry": {"coordinates":[6.616714,51.776863],"type":"Point"}
}