{
  "type": "Feature",
  "properties": {
    "iso:country":"DE",
    "sg:address":"Koblenzer Str. 44",
    "sg:city":"Rheinbach",
    "sg:phone":"+49 4971/7166336",
    "sg:postcode":"53359",
    "sg:province":"Nordrhein-Westfalen",
    "wof:name":"Palme S\u00d6hne, Reinhold",
    "wof:placetype":"venue"
},
  "geometry": {"coordinates":[9.799268,48.796593],"type":"Point"}
}