{
  "type": "Feature",
  "properties": {
    "iso:country":"DE",
    "sg:city":"Wuppertal",
    "sg:phone":"+49 202/2501215",
    "sg:postcode":"42281",
    "sg:province":"Nordrhein-Westfalen",
    "wof:name":"Kerkmann Grafik-design-b\u00fcro Bdg",
    "wof:placetype":"venue"
},
  "geometry": {"coordinates":[7.19032,51.285889],"type":"Point"}
}