{
  "type": "Feature",
  "properties": {
    "iso:country":"DE",
    "sg:address":"L\u00fcneburger Schanze 21",
    "sg:city":"Buxtehude",
    "sg:phone":"+49 4161/81075",
    "sg:postcode":"21614",
    "sg:province":"Niedersachsen",
    "wof:name":"Elektro-rademacher Gmbh",
    "wof:placetype":"venue"
},
  "geometry": {"coordinates":[9.7016468048,53.4632072449],"type":"Point"}
}