{
  "type": "Feature",
  "properties": {
    "iso:country":"DE",
    "sg:address":"Maulkuppenstr. 2",
    "sg:city":"Eichenzell",
    "sg:phone":"+49 6659/919320",
    "sg:postcode":"36124",
    "sg:province":"Hessen",
    "wof:name":"K. Heurung Finanzberater",
    "wof:placetype":"venue"
},
  "geometry": {"coordinates":[9.7107868195,50.4647407532],"type":"Point"}
}