{
  "type": "Feature",
  "properties": {
    "iso:country":"DE",
    "sg:address":"Plauensche Str. 85",
    "sg:city":"Falkenstein",
    "sg:phone":"+49 3745/222226",
    "sg:postcode":"08223",
    "sg:province":"Sachsen",
    "wof:name":"Kai W\u00e4hner",
    "wof:placetype":"venue"
},
  "geometry": {"coordinates":[12.3538227081,50.4737167358],"type":"Point"}
}