{
  "type": "Feature",
  "properties": {
    "iso:country":"DE",
    "sg:address":"Rendeler Str. 37",
    "sg:city":"Frankfurt",
    "sg:phone":"+49 69/451271",
    "sg:postcode":"60385",
    "sg:province":"Hessen",
    "wof:name":"Georg Stark",
    "wof:placetype":"venue"
},
  "geometry": {"coordinates":[8.7095956802,50.1287994385],"type":"Point"}
}