{
  "type": "Feature",
  "properties": {
    "iso:country":"DE",
    "sg:address":"Kr\u00e4uterhausweg 35",
    "sg:city":"Traben-Trarbach",
    "sg:phone":"+49 6541/9979",
    "sg:postcode":"56841",
    "sg:province":"Rheinland-Pfalz",
    "wof:name":"Klaus Lieser",
    "wof:placetype":"venue"
},
  "geometry": {"coordinates":[7.105247,49.959805],"type":"Point"}
}