{
  "type": "Feature",
  "properties": {
    "iso:country":"DE",
    "sg:address":"Fleischstr. 55",
    "sg:city":"Trier",
    "sg:phone":"+49 651/74220",
    "sg:postcode":"54290",
    "sg:province":"Rheinland-Pfalz",
    "wof:name":"Cafe Mohr Inh. Claudia Regnery E. K.",
    "wof:placetype":"venue"
},
  "geometry": {"coordinates":[6.6377491951,49.7550582886],"type":"Point"}
}