{
  "type": "Feature",
  "properties": {
    "iso:country":"DE",
    "sg:address":"Reiserweg 22",
    "sg:city":"Duisburg",
    "sg:phone":"+49 203/766051",
    "sg:postcode":"47269",
    "sg:province":"Nordrhein-Westfalen",
    "wof:name":"Eisen-stahl- Und Gu\u00dftechnik Gesellschaft F\u00fcr Bergwerks-",
    "wof:placetype":"venue"
},
  "geometry": {"coordinates":[6.781652,51.359154],"type":"Point"}
}