{
  "type": "Feature",
  "properties": {
    "iso:country":"DE",
    "sg:address":"Worringer Str. 78",
    "sg:city":"D\u00fcsseldorf",
    "sg:postcode":"40211",
    "sg:province":"Nordrhein-Westfalen",
    "wof:name":"Immobilien Manager Redaktion D\u00fcsseldorf",
    "wof:placetype":"venue"
},
  "geometry": {"coordinates":[6.7965359688,51.2255096436],"type":"Point"}
}