{
  "type": "Feature",
  "properties": {
    "iso:country":"DE",
    "sg:address":"Am Sandberg 26",
    "sg:city":"Frankfurt",
    "sg:postcode":"60599",
    "sg:province":"Hessen",
    "wof:name":"Kalle",
    "wof:placetype":"venue"
},
  "geometry": {"coordinates":[8.697885,50.092777],"type":"Point"}
}