{
  "type": "Feature",
  "properties": {
    "iso:country":"DE",
    "sg:address":"Hamburger Landstr. 19 e",
    "sg:city":"Bardowick",
    "sg:postcode":"21357",
    "sg:province":"Niedersachsen",
    "wof:name":"Aldi Gmbh & Co. Kg",
    "wof:placetype":"venue"
},
  "geometry": {"coordinates":[10.3889369965,53.293258667],"type":"Point"}
}