{
  "type": "Feature",
  "properties": {
    "iso:country":"DE",
    "sg:address":"Ellenerbrokweg 17",
    "sg:city":"Bremen",
    "sg:phone":"+49 421/425036",
    "sg:postcode":"28325",
    "sg:province":"Bremen",
    "wof:name":"Manfred Wabbels",
    "wof:placetype":"venue"
},
  "geometry": {"coordinates":[8.945254,53.071297],"type":"Point"}
}