{
  "type": "Feature",
  "properties": {
    "iso:country":"DE",
    "sg:address":"Hoyeler Str. 51",
    "sg:city":"Melle",
    "sg:phone":"+49 5226/5631",
    "sg:postcode":"49328",
    "sg:province":"Niedersachsen",
    "wof:name":"H. W\u00e4lker",
    "wof:placetype":"venue"
},
  "geometry": {"coordinates":[8.472387,52.16563],"type":"Point"}
}