{
  "type": "Feature",
  "properties": {
    "iso:country":"DE",
    "sg:address":"Pestalozzistr. 88a",
    "sg:city":"Berlin",
    "sg:phone":"+49 30/3127217",
    "sg:postcode":"10625",
    "sg:province":"Berlin",
    "wof:name":"J\u00f6rg P. Bratz Antiquit\u00e4ten",
    "wof:placetype":"venue"
},
  "geometry": {"coordinates":[13.311778,52.50771],"type":"Point"}
}