{
  "type": "Feature",
  "properties": {
    "iso:country":"DE",
    "sg:address":"Norderstr. 43",
    "sg:city":"Flensburg",
    "sg:phone":"+49 461/28498",
    "sg:postcode":"24939",
    "sg:province":"Schleswig-Holstein",
    "wof:name":"Silberquell",
    "wof:placetype":"venue"
},
  "geometry": {"coordinates":[9.4311857224,54.7912559509],"type":"Point"}
}