{
  "type": "Feature",
  "properties": {
    "iso:country":"DE",
    "sg:address":"Plauener Str. 25",
    "sg:city":"Hof",
    "sg:phone":"+49 9281/2806",
    "sg:postcode":"95028",
    "sg:province":"Bayern",
    "wof:name":"Vereinsgastst\u00e4tte Naturheilverein",
    "wof:placetype":"venue"
},
  "geometry": {"coordinates":[11.9217338562,50.3309822083],"type":"Point"}
}