{
  "type": "Feature",
  "properties": {
    "iso:country":"DE",
    "sg:address":"Dorfstr. 6c",
    "sg:city":"Krummensee",
    "sg:phone":"+49 3375/950674",
    "sg:postcode":"15711",
    "sg:province":"Brandenburg",
    "wof:name":"K. G\u00f6rner",
    "wof:placetype":"venue"
},
  "geometry": {"coordinates":[13.6904687881,52.5973052979],"type":"Point"}
}