{
  "type": "Feature",
  "properties": {
    "iso:country":"DE",
    "sg:address":"Hiltruper Stra\u00dfe 7",
    "sg:city":"M\u00fcnster",
    "sg:phone":"+49 2506/302960",
    "sg:postcode":"48167",
    "sg:province":"Nordrhein-Westfalen",
    "wof:name":"Ergowolbeck.de",
    "wof:placetype":"venue"
},
  "geometry": {"coordinates":[7.71232,51.909229],"type":"Point"}
}