{
  "type": "Feature",
  "properties": {
    "iso:country":"DE",
    "sg:address":"Rammertstr. 12",
    "sg:city":"Hirrlingen",
    "sg:phone":"+49 7478/347",
    "sg:postcode":"72145",
    "sg:province":"Baden-W\u00fcrttemberg",
    "wof:name":"Wilhelm Baur E. K.",
    "wof:placetype":"venue"
},
  "geometry": {"coordinates":[8.8941755295,48.4119949341],"type":"Point"}
}