{
  "type": "Feature",
  "properties": {
    "iso:country":"DE",
    "sg:address":"Lindenweg 2",
    "sg:city":"Brilon",
    "sg:phone":"+49 2961/3902",
    "sg:postcode":"59929",
    "sg:province":"Nordrhein-Westfalen",
    "wof:name":"J\u00fcrgen Th\u00fcner",
    "wof:placetype":"venue"
},
  "geometry": {"coordinates":[8.568239212,51.3993186951],"type":"Point"}
}