{
  "type": "Feature",
  "properties": {
    "iso:country":"DE",
    "sg:address":"Hopfenseeweg 3",
    "sg:city":"Stuttgart",
    "sg:postcode":"70378",
    "sg:province":"Baden-W\u00fcrttemberg",
    "wof:name":"Leutenecker Kronenhof - Grundst\u00fccksgesellschaft",
    "wof:placetype":"venue"
},
  "geometry": {"coordinates":[9.217247963,48.8304138184],"type":"Point"}
}