{
  "type": "Feature",
  "properties": {
    "iso:country":"DE",
    "sg:address":"Robert-Bosch-Str. 6",
    "sg:city":"Dachau",
    "sg:phone":"+49 8131/15637",
    "sg:postcode":"85221",
    "sg:province":"Bayern",
    "wof:name":"Rowa Verpackungsmaschinen Gesch\u00e4ftsf\u00fchrungs Gmbh",
    "wof:placetype":"venue"
},
  "geometry": {"coordinates":[11.474849,48.264824],"type":"Point"}
}