{
  "type": "Feature",
  "properties": {
    "iso:country":"DE",
    "sg:address":"Friedensstr. 19a",
    "sg:city":"Leverkusen",
    "sg:phone":"+49 214/5000480",
    "sg:postcode":"51373",
    "sg:province":"Nordrhein-Westfalen",
    "wof:name":"Gebatec Mbh",
    "wof:placetype":"venue"
},
  "geometry": {"coordinates":[6.983157,51.029938],"type":"Point"}
}