{
  "type": "Feature",
  "properties": {
    "iso:country":"DE",
    "sg:address":"Rheinufer 16",
    "sg:city":"Bad Breisig",
    "sg:phone":"+49 2633/7431",
    "sg:postcode":"53498",
    "sg:province":"Rheinland-Pfalz",
    "wof:name":"Altes Zollhaus",
    "wof:placetype":"venue"
},
  "geometry": {"coordinates":[7.2997941971,50.5115966797],"type":"Point"}
}