{
  "type": "Feature",
  "properties": {
    "iso:country":"DE",
    "sg:address":"Dorfstr. 34",
    "sg:city":"Braderup",
    "sg:phone":"+49 4663/1456",
    "sg:postcode":"25923",
    "sg:province":"Schleswig-Holstein",
    "wof:name":"U. Hoffmann",
    "wof:placetype":"venue"
},
  "geometry": {"coordinates":[8.893266,54.835533],"type":"Point"}
}