{
  "type": "Feature",
  "properties": {
    "iso:country":"DE",
    "sg:address":"Hirschenstr. 33",
    "sg:city":"F\u00fcrth",
    "sg:phone":"+49 911/771730",
    "sg:postcode":"90762",
    "sg:province":"Bayern",
    "wof:name":"Karl Haberecker",
    "wof:placetype":"venue"
},
  "geometry": {"coordinates":[10.987021,49.474285],"type":"Point"}
}