{
  "type": "Feature",
  "properties": {
    "iso:country":"DE",
    "sg:address":"Herforder Str. 86",
    "sg:city":"Vlotho",
    "sg:phone":"+49 5733/18776",
    "sg:postcode":"32602",
    "sg:province":"Nordrhein-Westfalen",
    "wof:name":"Laternchen",
    "wof:placetype":"venue"
},
  "geometry": {"coordinates":[8.8440856934,52.157169342],"type":"Point"}
}