{
  "type": "Feature",
  "properties": {
    "iso:country":"DE",
    "sg:address":"Bahnhofstr. 58",
    "sg:city":"Gelsenkirchen",
    "sg:phone":"+49 209/17940",
    "sg:postcode":"45879",
    "sg:province":"Nordrhein-Westfalen",
    "wof:name":"C. & A.",
    "wof:placetype":"venue"
},
  "geometry": {"coordinates":[7.099172,51.507515],"type":"Point"}
}