{
  "type": "Feature",
  "properties": {
    "iso:country":"DE",
    "sg:address":"Weberstr. 118",
    "sg:city":"Bonn",
    "sg:phone":"+49 228/223071",
    "sg:postcode":"53113",
    "sg:province":"Nordrhein-Westfalen",
    "wof:name":"Redaktion Duz Verlag Dr. Josef Raabe",
    "wof:placetype":"venue"
},
  "geometry": {"coordinates":[7.1013650894,50.7258415222],"type":"Point"}
}