{
  "type": "Feature",
  "properties": {
    "iso:country":"DE",
    "sg:address":"Maximilian-Philipp-Str. 22",
    "sg:city":"T\u00fcrkheim",
    "sg:phone":"+49 8245/1603",
    "sg:postcode":"86842",
    "sg:province":"Bayern",
    "wof:name":"F. Eimannsberger & Rieger",
    "wof:placetype":"venue"
},
  "geometry": {"coordinates":[10.6399154663,48.0611572266],"type":"Point"}
}