{
  "type": "Feature",
  "properties": {
    "iso:country":"DE",
    "sg:address":"Bergweg 3",
    "sg:city":"Friedrichsdorf",
    "sg:phone":"+49 6175/930070",
    "sg:postcode":"61381",
    "sg:province":"Hessen",
    "wof:name":"Dev Systemtechnik Gmbh",
    "wof:placetype":"venue"
},
  "geometry": {"coordinates":[8.657369,50.272144],"type":"Point"}
}