{
  "type": "Feature",
  "properties": {
    "iso:country":"DE",
    "sg:address":"Tr\u00f6delmarkt 3",
    "sg:city":"N\u00fcrnberg",
    "sg:phone":"+49 911/232412",
    "sg:postcode":"90403",
    "sg:province":"Bayern",
    "wof:name":"Annette Rumbrecht",
    "wof:placetype":"venue"
},
  "geometry": {"coordinates":[11.0746250153,49.453037262],"type":"Point"}
}