{
  "type": "Feature",
  "properties": {
    "iso:country":"DE",
    "sg:address":"Langes S\u00e4chseng\u00e4\u00dfchen 9",
    "sg:city":"Augsburg",
    "sg:phone":"+49 821/30512",
    "sg:postcode":"86152",
    "sg:province":"Bayern",
    "wof:name":"Tabakwaren Gro\u00dfeinkauf Schaben Eg",
    "wof:placetype":"venue"
},
  "geometry": {"coordinates":[10.9032812119,48.3710250854],"type":"Point"}
}