{
  "type": "Feature",
  "properties": {
    "iso:country":"DE",
    "sg:address":"Kornb\u00fchlstr. 52",
    "sg:city":"Burladingen",
    "sg:phone":"+49 7126/1010",
    "sg:postcode":"72393",
    "sg:province":"Baden-W\u00fcrttemberg",
    "wof:name":"Lamm",
    "wof:placetype":"venue"
},
  "geometry": {"coordinates":[9.1141214371,48.3570594788],"type":"Point"}
}