{
  "type": "Feature",
  "properties": {
    "iso:country":"DE",
    "sg:address":"Jahnstr. 1",
    "sg:city":"Deizisau",
    "sg:phone":"+49 7153/24100",
    "sg:postcode":"73779",
    "sg:province":"Baden-W\u00fcrttemberg",
    "wof:name":"G. Und B. Walter Bauschlosserei",
    "wof:placetype":"venue"
},
  "geometry": {"coordinates":[9.384638,48.71204],"type":"Point"}
}