{
  "type": "Feature",
  "properties": {
    "iso:country":"DE",
    "sg:address":"Berliner Str. 55",
    "sg:city":"Lauchhammer",
    "sg:phone":"+49 3574/7044",
    "sg:postcode":"01979",
    "sg:province":"Brandenburg",
    "wof:name":"Dieter Georgi",
    "wof:placetype":"venue"
},
  "geometry": {"coordinates":[13.736991,51.473927],"type":"Point"}
}