{
  "type": "Feature",
  "properties": {
    "iso:country":"DE",
    "sg:address":"Klingenweg 10a",
    "sg:city":"Frankfurt",
    "sg:phone":"+49 6109/72540",
    "sg:postcode":"60388",
    "sg:province":"Hessen",
    "wof:name":"Karl-heinz Holzheimer Steuerberater",
    "wof:placetype":"venue"
},
  "geometry": {"coordinates":[8.7463693619,50.1552772522],"type":"Point"}
}