{
  "type": "Feature",
  "properties": {
    "iso:country":"DE",
    "sg:address":"Stiftsmarkt 12",
    "sg:city":"Warendorf",
    "sg:postcode":"48231",
    "sg:province":"Nordrhein-Westfalen",
    "wof:name":"Kath. \u00f6ffentl. Bibliothek St. Bonifatius",
    "wof:placetype":"venue"
},
  "geometry": {"coordinates":[7.967413,51.920879],"type":"Point"}
}