{
  "type": "Feature",
  "properties": {
    "iso:country":"DE",
    "sg:address":"Sandkamp 18",
    "sg:city":"Kiebitzreihe",
    "sg:postcode":"25368",
    "sg:province":"Schleswig-Holstein",
    "wof:name":"Hle Holger Littau Elektrotechnik Gmbh",
    "wof:placetype":"venue"
},
  "geometry": {"coordinates":[9.621495,53.784359],"type":"Point"}
}