{
  "type": "Feature",
  "properties": {
    "iso:country":"DE",
    "sg:address":"Zinshardter Str. 3",
    "sg:city":"Morsbach",
    "sg:phone":"+49 2294/6260",
    "sg:postcode":"51597",
    "sg:province":"Nordrhein-Westfalen",
    "wof:name":"Hans-reiner Reddig Gmbh",
    "wof:placetype":"venue"
},
  "geometry": {"coordinates":[7.681921,50.827446],"type":"Point"}
}