{
  "type": "Feature",
  "properties": {
    "iso:country":"DE",
    "sg:address":"Frankfurter Str. 8",
    "sg:city":"Dreieich",
    "sg:phone":"+49 6103/960304",
    "sg:postcode":"63303",
    "sg:province":"Hessen",
    "wof:name":"Ellermann U. Danka Ergotherapeutische Praxis",
    "wof:placetype":"venue"
},
  "geometry": {"coordinates":[8.695307,50.019199],"type":"Point"}
}