{
  "type": "Feature",
  "properties": {
    "iso:country":"DE",
    "sg:address":"Postfach 1720:: Markt 75::",
    "sg:city":"Heide",
    "sg:phone":"+49 481/85860",
    "sg:postcode":"25746",
    "sg:province":"Schleswig-Holstein",
    "wof:name":"Raiffeisenbank Eg Heide Holst",
    "wof:placetype":"venue"
},
  "geometry": {"coordinates":[9.09009,54.195545],"type":"Point"}
}