{
  "type": "Feature",
  "properties": {
    "iso:country":"DE",
    "sg:address":"Wilhelm-Raabe-Str. 20",
    "sg:city":"Osterode",
    "sg:phone":"+49 5522/2137",
    "sg:postcode":"37520",
    "sg:province":"Niedersachsen",
    "wof:name":"Gerhard Werner",
    "wof:placetype":"venue"
},
  "geometry": {"coordinates":[10.30898,51.676579],"type":"Point"}
}