{
  "type": "Feature",
  "properties": {
    "iso:country":"DE",
    "sg:address":"An der Laag 2",
    "sg:city":"Heimbach",
    "sg:phone":"+49 2446/805840",
    "sg:postcode":"52396",
    "sg:province":"Nordrhein-Westfalen",
    "wof:name":"Restaurant Rurtalklause",
    "wof:placetype":"venue"
},
  "geometry": {"coordinates":[6.4727878571,50.6371269226],"type":"Point"}
}