{
  "type": "Feature",
  "properties": {
    "iso:country":"DE",
    "sg:address":"Zu den Weinbergen 30",
    "sg:city":"Donnersdorf",
    "sg:phone":"+49 9528/1582",
    "sg:postcode":"97499",
    "sg:province":"Bayern",
    "wof:name":"Reiner Johannes",
    "wof:placetype":"venue"
},
  "geometry": {"coordinates":[10.4151706696,49.9420051575],"type":"Point"}
}