{
  "type": "Feature",
  "properties": {
    "iso:country":"DE",
    "sg:address":"Am Deich 1",
    "sg:city":"Kollmar",
    "sg:phone":"+49 4128/941874",
    "sg:postcode":"25377",
    "sg:province":"Schleswig-Holstein",
    "wof:name":"Ho Ga - Immobilien",
    "wof:placetype":"venue"
},
  "geometry": {"coordinates":[9.490509,53.726223],"type":"Point"}
}