{
  "type": "Feature",
  "properties": {
    "iso:country":"DE",
    "sg:address":"Haager Str. 56",
    "sg:city":"Obertaufkirchen",
    "sg:phone":"+49 8082/93050",
    "sg:postcode":"84419",
    "sg:province":"Bayern",
    "wof:name":"Uts Umwelt-technik-s\u00fcd Gmbh",
    "wof:placetype":"venue"
},
  "geometry": {"coordinates":[12.281191,48.260296],"type":"Point"}
}