{
  "type": "Feature",
  "properties": {
    "iso:country":"DE",
    "sg:address":"Landwehr 9",
    "sg:city":"Cloppenburg",
    "sg:phone":"+49 4471/942000",
    "sg:postcode":"49661",
    "sg:province":"Niedersachsen",
    "wof:name":"Hf Electronic Gmbh",
    "wof:placetype":"venue"
},
  "geometry": {"coordinates":[8.0440864563,52.8386077881],"type":"Point"}
}