{
  "type": "Feature",
  "properties": {
    "iso:country":"DE",
    "sg:address":"Mainzer Str.",
    "sg:city":"Montabaur",
    "sg:phone":"+49 2602/4726",
    "sg:postcode":"56410",
    "sg:province":"Rheinland-Pfalz",
    "wof:name":"G\u00fcnther Diedert Gmbh",
    "wof:placetype":"venue"
},
  "geometry": {"coordinates":[7.793925,50.431694],"type":"Point"}
}