{
  "type": "Feature",
  "properties": {
    "iso:country":"DE",
    "sg:address":"Wehlener Str. 9",
    "sg:city":"Dresden",
    "sg:phone":"+49 351/254444",
    "sg:postcode":"01279",
    "sg:province":"Sachsen",
    "wof:name":"M\u00fcller Bestattungen",
    "wof:placetype":"venue"
},
  "geometry": {"coordinates":[13.810405,51.037537],"type":"Point"}
}