{
  "type": "Feature",
  "properties": {
    "iso:country":"DE",
    "sg:address":"Birkenwaldstr. 18",
    "sg:city":"Obertshausen",
    "sg:postcode":"63179",
    "sg:province":"Hessen",
    "wof:name":"Gewerbegalerie Obertshausen Ohg",
    "wof:placetype":"venue"
},
  "geometry": {"coordinates":[8.8664045334,50.0763702393],"type":"Point"}
}