{
  "type": "Feature",
  "properties": {
    "iso:country":"DE",
    "sg:address":"Villacher Str. 6",
    "sg:city":"Stuttgart",
    "sg:phone":"+49 711/813834",
    "sg:postcode":"70469",
    "sg:province":"Baden-W\u00fcrttemberg",
    "wof:name":"Gudrun Widmann Masseurin",
    "wof:placetype":"venue"
},
  "geometry": {"coordinates":[9.157968,48.811489],"type":"Point"}
}