{
  "type": "Feature",
  "properties": {
    "iso:country":"DE",
    "sg:address":"Industriestr.",
    "sg:city":"Eschenburg",
    "sg:phone":"+49 2770/853",
    "sg:postcode":"35713",
    "sg:province":"Hessen",
    "wof:name":"G. M\u00fcller",
    "wof:placetype":"venue"
},
  "geometry": {"coordinates":[8.4065551758,50.7893295288],"type":"Point"}
}