{
  "type": "Feature",
  "properties": {
    "iso:country":"DE",
    "sg:address":"B\u00fcsdorfer Str. 5 a",
    "sg:city":"Bergheim",
    "sg:phone":"+49 2271/53061",
    "sg:postcode":"50129",
    "sg:province":"Nordrhein-Westfalen",
    "wof:name":"J. Grumann",
    "wof:placetype":"venue"
},
  "geometry": {"coordinates":[6.678941,50.974033],"type":"Point"}
}