{
  "type": "Feature",
  "properties": {
    "iso:country":"DE",
    "sg:address":"Bergstr. 215",
    "sg:city":"Marl",
    "sg:phone":"+49 2365/924940",
    "sg:postcode":"45770",
    "sg:province":"Nordrhein-Westfalen",
    "wof:name":"Busch Teufel Und Piechnick Rechtsanw\u00e4lte",
    "wof:placetype":"venue"
},
  "geometry": {"coordinates":[7.1026859283,51.6583137512],"type":"Point"}
}