{
  "type": "Feature",
  "properties": {
    "iso:country":"DE",
    "sg:address":"Wagnerstr. 20",
    "sg:city":"Ulm",
    "sg:phone":"+49 731/935020",
    "sg:postcode":"89077",
    "sg:province":"Baden-W\u00fcrttemberg",
    "wof:name":"Signal Unfallversicherung Ag",
    "wof:placetype":"venue"
},
  "geometry": {"coordinates":[9.9774084091,48.3940467834],"type":"Point"}
}