{
  "type": "Feature",
  "properties": {
    "iso:country":"DE",
    "sg:address":"Wolterstr. 10",
    "sg:city":"Neuenhagen",
    "sg:postcode":"15366",
    "sg:province":"Brandenburg",
    "wof:name":"Elektro-meisterbetrieb Lothar Fehlhaber",
    "wof:placetype":"venue"
},
  "geometry": {"coordinates":[13.6995697021,52.5219764709],"type":"Point"}
}