{
  "type": "Feature",
  "properties": {
    "iso:country":"DE",
    "sg:address":"Ahornweg 59",
    "sg:city":"R\u00f6srath",
    "sg:phone":"+49 2205/4062",
    "sg:postcode":"51503",
    "sg:province":"Nordrhein-Westfalen",
    "wof:name":"A. Vierk\u00f6tter",
    "wof:placetype":"venue"
},
  "geometry": {"coordinates":[7.1698660851,50.9014625549],"type":"Point"}
}