{
  "type": "Feature",
  "properties": {
    "iso:country":"DE",
    "sg:address":"Wilhelminenstr. 17",
    "sg:city":"M\u00fclheim",
    "sg:phone":"+49 208/424241",
    "sg:postcode":"45479",
    "sg:province":"Nordrhein-Westfalen",
    "wof:name":"Karl-heinz Behnke",
    "wof:placetype":"venue"
},
  "geometry": {"coordinates":[6.8706440926,51.4243049622],"type":"Point"}
}