{
  "type": "Feature",
  "properties": {
    "iso:country":"DE",
    "sg:address":"Hauptstr. 59-61",
    "sg:city":"M\u00fclsen",
    "sg:phone":"+49 37601/2484",
    "sg:postcode":"08132",
    "sg:province":"Sachsen",
    "wof:name":"S. Schmidt",
    "wof:placetype":"venue"
},
  "geometry": {"coordinates":[12.5718460083,50.7415084839],"type":"Point"}
}