{
  "type": "Feature",
  "properties": {
    "iso:country":"DE",
    "sg:address":"Thurower Str. 1",
    "sg:city":"Gro\u00df Molzahn",
    "sg:phone":"+49 38875/20073",
    "sg:postcode":"19217",
    "sg:province":"Mecklenburg-Vorpommern",
    "wof:name":"Holger Anspichler",
    "wof:placetype":"venue"
},
  "geometry": {"coordinates":[10.8584852219,53.7321662903],"type":"Point"}
}