{
  "type": "Feature",
  "properties": {
    "iso:country":"DE",
    "sg:address":"Steyler Str. 44",
    "sg:city":"Nettetal",
    "sg:phone":"+49 2157/6978",
    "sg:postcode":"41334",
    "sg:province":"Nordrhein-Westfalen",
    "wof:name":"Matthias Lankes",
    "wof:placetype":"venue"
},
  "geometry": {"coordinates":[6.17503,51.328289],"type":"Point"}
}