{
  "type": "Feature",
  "properties": {
    "iso:country":"DE",
    "sg:address":"Werkstr. 2A",
    "sg:city":"Montabaur",
    "sg:phone":"+49 2602/9995547",
    "sg:postcode":"56410",
    "sg:province":"Rheinland-Pfalz",
    "wof:name":"Serio Das Haus Gmbh",
    "wof:placetype":"venue"
},
  "geometry": {"coordinates":[7.823663,50.44109],"type":"Point"}
}