{
  "type": "Feature",
  "properties": {
    "iso:country":"DE",
    "sg:address":"Regentenstr. 5",
    "sg:city":"M\u00f6nchengladbach",
    "sg:postcode":"41061",
    "sg:province":"Nordrhein-Westfalen",
    "wof:name":"Com Con Ag",
    "wof:placetype":"venue"
},
  "geometry": {"coordinates":[6.433296,51.196594],"type":"Point"}
}