{
  "type": "Feature",
  "properties": {
    "iso:country":"DE",
    "sg:address":"An der Haardtsteige 6",
    "sg:city":"Steinsfeld",
    "sg:phone":"+49 9861/1528",
    "sg:postcode":"91628",
    "sg:province":"Bayern",
    "wof:name":"Gerda Sattler Kunstmalerin",
    "wof:placetype":"venue"
},
  "geometry": {"coordinates":[10.212303,49.420334],"type":"Point"}
}