{
  "type": "Feature",
  "properties": {
    "iso:country":"DE",
    "sg:address":"Pestalozzistr. 23",
    "sg:city":"Hamburg",
    "sg:phone":"+49 40/6917777",
    "sg:postcode":"22305",
    "sg:province":"Hamburg",
    "wof:name":"T. Boldt",
    "wof:placetype":"venue"
},
  "geometry": {"coordinates":[10.047667,53.587475],"type":"Point"}
}