{
  "type": "Feature",
  "properties": {
    "iso:country":"DE",
    "sg:address":"In den Hofwiesen 12",
    "sg:city":"N\u00fcrtingen",
    "sg:phone":"+49 7022/53533",
    "sg:postcode":"72622",
    "sg:province":"Baden-W\u00fcrttemberg",
    "wof:name":"Rolf Hauke Computerhandlungen",
    "wof:placetype":"venue"
},
  "geometry": {"coordinates":[9.3066129684,48.6184577942],"type":"Point"}
}