{
  "type": "Feature",
  "properties": {
    "iso:country":"DE",
    "sg:address":"Albert-Schweitzer-Str. 41",
    "sg:city":"Neuenb\u00fcrg",
    "sg:phone":"+49 7082/5604",
    "sg:postcode":"75305",
    "sg:province":"Baden-W\u00fcrttemberg",
    "wof:name":"Jacob Circuit Boards Gmbh",
    "wof:placetype":"venue"
},
  "geometry": {"coordinates":[8.5843009949,48.8526992798],"type":"Point"}
}