{
  "type": "Feature",
  "properties": {
    "iso:country":"DE",
    "sg:address":"Augsburger Str. 41",
    "sg:city":"P\u00f6ttmes",
    "sg:phone":"+49 8253/205",
    "sg:postcode":"86554",
    "sg:province":"Bayern",
    "wof:name":"Josef B\u00f6ck",
    "wof:placetype":"venue"
},
  "geometry": {"coordinates":[11.081077,48.579502],"type":"Point"}
}