{
  "type": "Feature",
  "properties": {
    "iso:country":"DE",
    "sg:address":"Waiblinger Str. 34",
    "sg:city":"Weinstadt",
    "sg:phone":"+49 7151/64069",
    "sg:postcode":"71384",
    "sg:province":"Baden-W\u00fcrttemberg",
    "wof:name":"Theodor Angelopoulos Ingenieur",
    "wof:placetype":"venue"
},
  "geometry": {"coordinates":[9.3606433868,48.8135948181],"type":"Point"}
}