{
  "type": "Feature",
  "properties": {
    "iso:country":"DE",
    "sg:address":"Gewerbestr 2",
    "sg:city":"Gerstetten",
    "sg:phone":"+49 7324/952179",
    "sg:postcode":"89547",
    "sg:province":"Baden-W\u00fcrttemberg",
    "wof:name":"Gardena Manufacturing Gmbh Gesch\u00e4ftsbereich Oem",
    "wof:placetype":"venue"
},
  "geometry": {"coordinates":[10.089945,48.59705],"type":"Point"}
}