{
  "type": "Feature",
  "properties": {
    "iso:country":"DE",
    "sg:address":"Rosenstra\u00dfe 18",
    "sg:city":"Rosenthal",
    "sg:phone":"+49 6458/1231",
    "sg:postcode":"35119",
    "sg:province":"Hessen",
    "wof:name":"Www.winter-haus.de",
    "wof:placetype":"venue"
},
  "geometry": {"coordinates":[8.870641,50.977337],"type":"Point"}
}