{
  "type": "Feature",
  "properties": {
    "iso:country":"DE",
    "sg:address":"Alte Plauener Str. 1",
    "sg:city":"Gro\u00dffriesen",
    "sg:phone":"+49 3741/444397",
    "sg:postcode":"08541",
    "sg:province":"Sachsen",
    "wof:name":"Otr Handels Gmbh",
    "wof:placetype":"venue"
},
  "geometry": {"coordinates":[12.1948451996,50.4897003174],"type":"Point"}
}