{
  "type": "Feature",
  "properties": {
    "iso:country":"DE",
    "sg:address":"Buchenweg 16",
    "sg:city":"Schapen",
    "sg:phone":"+49 5458/985049",
    "sg:postcode":"48480",
    "sg:province":"Niedersachsen",
    "wof:name":"Wolfgang Dirkes Bauunternehmung Gmbh",
    "wof:placetype":"venue"
},
  "geometry": {"coordinates":[7.537941,52.411705],"type":"Point"}
}