{
  "type": "Feature",
  "properties": {
    "iso:country":"DE",
    "sg:address":"Burgweintinger Str. 31",
    "sg:city":"Regensburg",
    "sg:postcode":"93055",
    "sg:province":"Bayern",
    "wof:name":"Birkart Globistics Ag Zwndl. Regensburg",
    "wof:placetype":"venue"
},
  "geometry": {"coordinates":[12.150839,48.989994],"type":"Point"}
}