{
  "type": "Feature",
  "properties": {
    "iso:country":"DE",
    "sg:address":"Rampenstr. 16",
    "sg:city":"Bochum",
    "sg:phone":"+49 234/294919",
    "sg:postcode":"44892",
    "sg:province":"Nordrhein-Westfalen",
    "wof:name":"Dr. M. Kolla Ingenieur",
    "wof:placetype":"venue"
},
  "geometry": {"coordinates":[7.3192358017,51.4669647217],"type":"Point"}
}