{
  "type": "Feature",
  "properties": {
    "iso:country":"DE",
    "sg:address":"Eisenh\u00fctten Weg 9 A",
    "sg:city":"Dortmund",
    "sg:phone":"+49 4923/1824950",
    "sg:postcode":"44145",
    "sg:province":"Nordrhein-Westfalen",
    "wof:name":"He-sie K\u00c4ltetechnik Gmbh",
    "wof:placetype":"venue"
},
  "geometry": {"coordinates":[7.47055,51.536789],"type":"Point"}
}