{
  "type": "Feature",
  "properties": {
    "iso:country":"DE",
    "sg:address":"Berliner Chaussee 17 b",
    "sg:city":"Kremmen",
    "sg:phone":"+49 33055/75994",
    "sg:postcode":"16766",
    "sg:province":"Brandenburg",
    "wof:name":"Bak Bauabfall- Und Altholz- Verwertung Kremmen Gmbh",
    "wof:placetype":"venue"
},
  "geometry": {"coordinates":[13.039802,52.752556],"type":"Point"}
}