{
  "type": "Feature",
  "properties": {
    "iso:country":"DE",
    "sg:address":"Friesenberg 1",
    "sg:city":"Heidelberg",
    "sg:postcode":"69117",
    "sg:province":"Baden-W\u00fcrttemberg",
    "wof:name":"Clickwaste Ag",
    "wof:placetype":"venue"
},
  "geometry": {"coordinates":[8.716215,49.412395],"type":"Point"}
}