{
  "type": "Feature",
  "properties": {
    "iso:country":"DE",
    "sg:address":"Postfach 1660:: 59401 Unna:: Germany.^^Bahnhofstr 37::",
    "sg:city":"Unna",
    "sg:phone":"+49 2303/1040",
    "sg:postcode":"59423",
    "sg:province":"Nordrhein-Westfalen",
    "wof:name":"Kreis-und Stadtsparkasse Unna",
    "wof:placetype":"venue"
},
  "geometry": {"coordinates":[7.68709,51.532413],"type":"Point"}
}