{
  "type": "Feature",
  "properties": {
    "iso:country":"DE",
    "sg:address":"Mellener Str. 49",
    "sg:city":"Berlin",
    "sg:phone":"+49 30/7446095",
    "sg:postcode":"12307",
    "sg:province":"Berlin",
    "wof:name":"Michael Echt",
    "wof:placetype":"venue"
},
  "geometry": {"coordinates":[13.4053535461,52.3848762512],"type":"Point"}
}