{
  "type": "Feature",
  "properties": {
    "iso:country":"DE",
    "sg:address":"Harzstr. 54",
    "sg:city":"Scharzfeld",
    "sg:phone":"+49 4955/213656",
    "sg:postcode":"37412",
    "sg:province":"Niedersachsen",
    "wof:name":"Sparkasse Im Kreis Osterode",
    "wof:placetype":"venue"
},
  "geometry": {"coordinates":[10.37782,51.628506],"type":"Point"}
}