{
  "type": "Feature",
  "properties": {
    "iso:country":"DE",
    "sg:address":"Weiherhausstr. 3",
    "sg:city":"Heppenheim",
    "sg:phone":"+49 6252/982155",
    "sg:postcode":"64646",
    "sg:province":"Hessen",
    "wof:name":"Fritz Renner Gmbh",
    "wof:placetype":"venue"
},
  "geometry": {"coordinates":[8.629784584,49.6434020996],"type":"Point"}
}