{
  "type": "Feature",
  "properties": {
    "iso:country":"DE",
    "sg:address":"Nicolaiplatz 1",
    "sg:city":"L\u00f6bau",
    "sg:phone":"+49 3585/404670",
    "sg:postcode":"02708",
    "sg:province":"Sachsen",
    "wof:name":"F. Und E. Atte",
    "wof:placetype":"venue"
},
  "geometry": {"coordinates":[14.66755,51.096352],"type":"Point"}
}