{
  "type": "Feature",
  "properties": {
    "iso:country":"DE",
    "sg:address":"H\u00f6ftkamp 2",
    "sg:city":"M\u00fchlenbarbek",
    "sg:phone":"+49 4822/1685",
    "sg:postcode":"25548",
    "sg:province":"Schleswig-Holstein",
    "wof:name":"J. Andresen",
    "wof:placetype":"venue"
},
  "geometry": {"coordinates":[9.6623182297,53.9555511475],"type":"Point"}
}