{
  "type": "Feature",
  "properties": {
    "iso:country":"DE",
    "sg:address":"Grolandstr. 61b",
    "sg:city":"N\u00fcrnberg",
    "sg:phone":"+49 911/3651849",
    "sg:postcode":"90408",
    "sg:province":"Bayern",
    "wof:name":"Georg Bingold Glasgrosshandlung",
    "wof:placetype":"venue"
},
  "geometry": {"coordinates":[11.07766819,49.4657936096],"type":"Point"}
}