{
  "type": "Feature",
  "properties": {
    "iso:country":"DE",
    "sg:address":"Harthauser Str. 81",
    "sg:city":"M\u00fcnchen",
    "sg:phone":"+49 89/643244",
    "sg:postcode":"81545",
    "sg:province":"Bayern",
    "wof:name":"Ruth Heisse Immobilien Gmbh",
    "wof:placetype":"venue"
},
  "geometry": {"coordinates":[11.5481920242,48.0832824707],"type":"Point"}
}