{
  "type": "Feature",
  "properties": {
    "iso:country":"DE",
    "sg:address":"Am Markt 23",
    "sg:city":"Luckau",
    "sg:phone":"+49 3544/3015",
    "sg:postcode":"15926",
    "sg:province":"Brandenburg",
    "wof:name":"Frank Winter",
    "wof:placetype":"venue"
},
  "geometry": {"coordinates":[13.715211,51.852329],"type":"Point"}
}