{
  "type": "Feature",
  "properties": {
    "iso:country":"DE",
    "sg:address":"Bauernwagnerstr. 2",
    "sg:city":"M\u00fcnchen",
    "sg:phone":"+49 89/504181",
    "sg:postcode":"81476",
    "sg:province":"Bayern",
    "wof:name":"Erwin Heidinger Elektroanlagen Gmbh",
    "wof:placetype":"venue"
},
  "geometry": {"coordinates":[11.496935,48.082336],"type":"Point"}
}