{
  "type": "Feature",
  "properties": {
    "iso:country":"DE",
    "sg:address":"Goerdelerstr. 59",
    "sg:city":"Delmenhorst",
    "sg:phone":"+49 4221/24607",
    "sg:postcode":"27755",
    "sg:province":"Niedersachsen",
    "wof:name":"W. Sch\u00f6n",
    "wof:placetype":"venue"
},
  "geometry": {"coordinates":[8.618687,53.028507],"type":"Point"}
}