{
  "type": "Feature",
  "properties": {
    "iso:country":"DE",
    "sg:address":"Marsstr. 12",
    "sg:city":"Halle",
    "sg:phone":"+49 345/5234763",
    "sg:postcode":"06118",
    "sg:province":"Sachsen-Anhalt",
    "wof:name":"Ulla G\u00fcnther",
    "wof:placetype":"venue"
},
  "geometry": {"coordinates":[11.96437,51.509735],"type":"Point"}
}