{
  "type": "Feature",
  "properties": {
    "iso:country":"DE",
    "sg:address":"Trierer Weg 8",
    "sg:city":"Wesseling",
    "sg:postcode":"50389",
    "sg:province":"Nordrhein-Westfalen",
    "wof:name":"A. Blenn Gmbh",
    "wof:placetype":"venue"
},
  "geometry": {"coordinates":[6.9713459015,50.8158416748],"type":"Point"}
}