{
  "type": "Feature",
  "properties": {
    "iso:country":"DE",
    "sg:address":"Ulhaus 34",
    "sg:city":"Langerwehe",
    "sg:phone":"+49 2423/94030",
    "sg:postcode":"52379",
    "sg:province":"Nordrhein-Westfalen",
    "wof:name":"T\u00f6pferei Langerwehe Kuckertz & Rennertz Gmbh",
    "wof:placetype":"venue"
},
  "geometry": {"coordinates":[6.3540449142,50.8188476562],"type":"Point"}
}