{
  "type": "Feature",
  "properties": {
    "iso:country":"DE",
    "sg:address":"Fabrikstr. 17 Bonlanden::",
    "sg:city":"Filderstadt",
    "sg:phone":"+49 4971/1770130",
    "sg:postcode":"70794",
    "sg:province":"Baden-W\u00fcrttemberg",
    "wof:name":"Sulzer Holding Gmbh",
    "wof:placetype":"venue"
},
  "geometry": {"coordinates":[9.21613,48.678261],"type":"Point"}
}