{
  "type": "Feature",
  "properties": {
    "iso:country":"DE",
    "sg:address":"Schie\u00dfmauer 7",
    "sg:city":"Wehrheim",
    "sg:phone":"+49 6081/57174",
    "sg:postcode":"61273",
    "sg:province":"Hessen",
    "wof:name":"Pit Reeh Dienstleistungen Gmbh",
    "wof:placetype":"venue"
},
  "geometry": {"coordinates":[8.572618,50.3055],"type":"Point"}
}