{
  "type": "Feature",
  "properties": {
    "iso:country":"DE",
    "sg:address":"Hauptstr. 11",
    "sg:city":"Sensweiler",
    "sg:phone":"+49 6786/2441",
    "sg:postcode":"55758",
    "sg:province":"Rheinland-Pfalz",
    "wof:name":"E. Schneider",
    "wof:placetype":"venue"
},
  "geometry": {"coordinates":[7.197293,49.774296],"type":"Point"}
}