{
  "type": "Feature",
  "properties": {
    "iso:country":"DE",
    "sg:address":"Schallershofer Str. 92",
    "sg:city":"Erlangen",
    "sg:phone":"+49 9131/44228",
    "sg:postcode":"91056",
    "sg:province":"Bayern",
    "wof:name":"Connys Petshop",
    "wof:placetype":"venue"
},
  "geometry": {"coordinates":[10.974008,49.584507],"type":"Point"}
}