{
  "type": "Feature",
  "properties": {
    "iso:country":"DE",
    "sg:address":"Traarer Str. 56",
    "sg:city":"Krefeld",
    "sg:phone":"+49 2151/471061",
    "sg:postcode":"47829",
    "sg:province":"Nordrhein-Westfalen",
    "wof:name":"La Barca",
    "wof:placetype":"venue"
},
  "geometry": {"coordinates":[6.6393198967,51.356010437],"type":"Point"}
}