{
  "type": "Feature",
  "properties": {
    "iso:country":"DE",
    "sg:address":"Bieberberg 6",
    "sg:city":"Menden",
    "sg:phone":"+49 2373/84232",
    "sg:postcode":"58710",
    "sg:province":"Nordrhein-Westfalen",
    "wof:name":"Hans Wiemann Und Eva-maria Tillmann",
    "wof:placetype":"venue"
},
  "geometry": {"coordinates":[7.832182,51.414845],"type":"Point"}
}