{
  "type": "Feature",
  "properties": {
    "iso:country":"DE",
    "sg:address":"Obertorstr. 6-8",
    "sg:city":"Marktheidenfeld",
    "sg:phone":"+49 9391/60040",
    "sg:postcode":"97828",
    "sg:province":"Bayern",
    "wof:name":"Hotel Anker Josef Deppisch Gmbh & Co. Kg",
    "wof:placetype":"venue"
},
  "geometry": {"coordinates":[9.6005191803,49.8453826904],"type":"Point"}
}