{
  "type": "Feature",
  "properties": {
    "iso:country":"DE",
    "sg:address":"Nadelstr. 2",
    "sg:city":"Rheda-Wiedenbr\u00fcck",
    "sg:phone":"+49 5242/44637",
    "sg:postcode":"33378",
    "sg:province":"Nordrhein-Westfalen",
    "wof:name":"Beckord",
    "wof:placetype":"venue"
},
  "geometry": {"coordinates":[8.290555,51.853081],"type":"Point"}
}