{
  "type": "Feature",
  "properties": {
    "iso:country":"DE",
    "sg:address":"Am Alten Markt 8-10",
    "sg:city":"Schotten",
    "sg:phone":"+49 6044/1384",
    "sg:postcode":"63679",
    "sg:province":"Hessen",
    "wof:name":"Johanna Linker",
    "wof:placetype":"venue"
},
  "geometry": {"coordinates":[9.122324,50.503899],"type":"Point"}
}