{
  "type": "Feature",
  "properties": {
    "iso:country":"DE",
    "sg:address":"Rachelstr. 22",
    "sg:city":"Osterhofen",
    "sg:phone":"+49 9932/1590",
    "sg:postcode":"94486",
    "sg:province":"Bayern",
    "wof:name":"Werner Drexler",
    "wof:placetype":"venue"
},
  "geometry": {"coordinates":[13.0293550491,48.7016372681],"type":"Point"}
}