{
  "type": "Feature",
  "properties": {
    "iso:country":"DE",
    "sg:address":"S\u00fcdstr. 26",
    "sg:city":"Wuppertal",
    "sg:phone":"+49 202/300589",
    "sg:postcode":"42103",
    "sg:province":"Nordrhein-Westfalen",
    "wof:name":"Pizzeria Taormina",
    "wof:placetype":"venue"
},
  "geometry": {"coordinates":[7.1403880119,51.2522850037],"type":"Point"}
}