{
  "type": "Feature",
  "properties": {
    "iso:country":"DE",
    "sg:address":"Schwanallee 22",
    "sg:city":"Marburg",
    "sg:phone":"+49 6421/25493",
    "sg:postcode":"35037",
    "sg:province":"Hessen",
    "wof:name":"Erhard Stein",
    "wof:placetype":"venue"
},
  "geometry": {"coordinates":[8.7593040466,50.8030433655],"type":"Point"}
}