{
  "type": "Feature",
  "properties": {
    "iso:country":"DE",
    "sg:address":"Hauptstr. 10",
    "sg:city":"Naila",
    "sg:phone":"+49 9282/1872",
    "sg:postcode":"95119",
    "sg:province":"Bayern",
    "wof:name":"Hildegard Weber",
    "wof:placetype":"venue"
},
  "geometry": {"coordinates":[11.709337,50.329418],"type":"Point"}
}