{
  "type": "Feature",
  "properties": {
    "iso:country":"DE",
    "sg:address":"Nordendstr. 45",
    "sg:city":"M\u00fcnchen",
    "sg:phone":"+49 89/2716290",
    "sg:postcode":"80801",
    "sg:province":"Bayern",
    "wof:name":"Dr. Gaiser & Sohn",
    "wof:placetype":"venue"
},
  "geometry": {"coordinates":[11.5746822357,48.158493042],"type":"Point"}
}