{
  "type": "Feature",
  "properties": {
    "iso:country":"DE",
    "sg:address":"Gerresheimer Stra\u00dfe 74",
    "sg:city":"Hilden",
    "sg:phone":"+49 2103/363201",
    "sg:postcode":"40721",
    "sg:province":"Nordrhein-Westfalen",
    "wof:name":"Wilhelmine-fliedner-realschule",
    "wof:placetype":"venue"
},
  "geometry": {"coordinates":[6.916368,51.164467],"type":"Point"}
}