{
  "type": "Feature",
  "properties": {
    "iso:country":"DE",
    "sg:address":"Fabrikstr. 17",
    "sg:city":"Herne",
    "sg:phone":"+49 2323/96680",
    "sg:postcode":"44629",
    "sg:province":"Nordrhein-Westfalen",
    "wof:name":"B & D Merchandising Gmbh",
    "wof:placetype":"venue"
},
  "geometry": {"coordinates":[7.2213759422,51.5449829102],"type":"Point"}
}