{
  "type": "Feature",
  "properties": {
    "iso:country":"DE",
    "sg:address":"Am Dausendbusch 20",
    "sg:city":"Wuppertal",
    "sg:phone":"+49 202/553054",
    "sg:postcode":"42285",
    "sg:province":"Nordrhein-Westfalen",
    "wof:name":"Pro Arte Gemeinn. Konzert- Und Schulungs Gmbh",
    "wof:placetype":"venue"
},
  "geometry": {"coordinates":[7.1759262085,51.2471733093],"type":"Point"}
}