{
  "type": "Feature",
  "properties": {
    "iso:country":"DE",
    "sg:address":"Friedhofsweg 3",
    "sg:city":"Rathenow",
    "sg:phone":"+49 3385/547020",
    "sg:postcode":"14712",
    "sg:province":"Brandenburg",
    "wof:name":"Rudolf Ei\u00dfer",
    "wof:placetype":"venue"
},
  "geometry": {"coordinates":[12.3347196579,52.6030082703],"type":"Point"}
}