{
  "type": "Feature",
  "properties": {
    "iso:country":"DE",
    "sg:address":"Heiglhofstr. 11",
    "sg:city":"M\u00fcnchen",
    "sg:phone":"+49 89/7144887",
    "sg:postcode":"81377",
    "sg:province":"Bayern",
    "wof:name":"Hans-albrecht Henkis Innenarchitekt",
    "wof:placetype":"venue"
},
  "geometry": {"coordinates":[11.478793,48.113453],"type":"Point"}
}