{
  "type": "Feature",
  "properties": {
    "iso:country":"DE",
    "sg:address":"Dorfstr. 31 a",
    "sg:city":"Webau",
    "sg:postcode":"06679",
    "sg:province":"Sachsen-Anhalt",
    "wof:name":"K\u00f6hler Gmbh",
    "wof:placetype":"venue"
},
  "geometry": {"coordinates":[12.08621,51.165951],"type":"Point"}
}