{
  "type": "Feature",
  "properties": {
    "iso:country":"DE",
    "sg:address":"K\u00fcllenhahner Str. 244",
    "sg:city":"Wuppertal",
    "sg:phone":"+49 202/400209",
    "sg:postcode":"42349",
    "sg:province":"Nordrhein-Westfalen",
    "wof:name":"Andrea Schlechter",
    "wof:placetype":"venue"
},
  "geometry": {"coordinates":[7.1326341629,51.2284431458],"type":"Point"}
}