{
  "type": "Feature",
  "properties": {
    "iso:country":"DE",
    "sg:address":"Eugen-Bolz-Str. 19",
    "sg:city":"Neckarsulm",
    "sg:phone":"+49 7132/980033",
    "sg:postcode":"74172",
    "sg:province":"Baden-W\u00fcrttemberg",
    "wof:name":"A & S Alarm- Und Sicherheit Kai M\u00fcller",
    "wof:placetype":"venue"
},
  "geometry": {"coordinates":[9.252165,49.212284],"type":"Point"}
}