{
  "type": "Feature",
  "properties": {
    "iso:country":"DE",
    "sg:address":"An der Bauschule 14 a",
    "sg:city":"Koblenz",
    "sg:postcode":"56075",
    "sg:province":"Rheinland-Pfalz",
    "wof:name":"Medizintechnik Reuther Gmbh & Co. Kg",
    "wof:placetype":"venue"
},
  "geometry": {"coordinates":[7.578888,50.34742],"type":"Point"}
}