{
  "type": "Feature",
  "properties": {
    "iso:country":"DE",
    "sg:address":"Gutenbergstr.",
    "sg:city":"Suhl",
    "sg:phone":"+49 3681/727077",
    "sg:postcode":"98527",
    "sg:province":"Th\u00fcringen",
    "wof:name":"Video-welt",
    "wof:placetype":"venue"
},
  "geometry": {"coordinates":[10.6869401932,50.608669281],"type":"Point"}
}