{
  "type": "Feature",
  "properties": {
    "iso:country":"DE",
    "sg:address":"Steeler Pfad 20",
    "sg:city":"Essen",
    "sg:phone":"+49 201/511260",
    "sg:postcode":"45307",
    "sg:province":"Nordrhein-Westfalen",
    "wof:name":"Friedhelm R\u00e4der Drogerie",
    "wof:placetype":"venue"
},
  "geometry": {"coordinates":[7.073826,51.4552],"type":"Point"}
}