{
  "type": "Feature",
  "properties": {
    "iso:country":"DE",
    "sg:address":"Friedrichstr. 19",
    "sg:city":"Furtwangen",
    "sg:postcode":"78120",
    "sg:province":"Baden-W\u00fcrttemberg",
    "wof:name":"Guckloch-kino",
    "wof:placetype":"venue"
},
  "geometry": {"coordinates":[8.204573,48.054283],"type":"Point"}
}