{
  "type": "Feature",
  "properties": {
    "iso:country":"DE",
    "sg:address":"Ebinger Str. 32",
    "sg:city":"Winterlingen",
    "sg:phone":"+49 4974/3427060",
    "sg:postcode":"72474",
    "sg:province":"Baden-W\u00fcrttemberg",
    "wof:name":"Eva B. Bitzer Gmbh",
    "wof:placetype":"venue"
},
  "geometry": {"coordinates":[9.115878,48.179665],"type":"Point"}
}