{
  "type": "Feature",
  "properties": {
    "iso:country":"DE",
    "sg:address":"D\u00fcvelsbrook 9",
    "sg:city":"Pl\u00f6n",
    "sg:phone":"+49 4522/7095",
    "sg:postcode":"24306",
    "sg:province":"Schleswig-Holstein",
    "wof:name":"G\u00f6tz-joachim Gottschalk Architekt",
    "wof:placetype":"venue"
},
  "geometry": {"coordinates":[10.42398,54.169861],"type":"Point"}
}