{
  "type": "Feature",
  "properties": {
    "iso:country":"DE",
    "sg:address":"Ulzburger Str. 567 a",
    "sg:city":"Norderstedt",
    "sg:phone":"+49 40/41925611",
    "sg:postcode":"22844",
    "sg:province":"Schleswig-Holstein",
    "wof:name":"Talk All In One Gmbh",
    "wof:placetype":"venue"
},
  "geometry": {"coordinates":[9.9969291687,53.7299003601],"type":"Point"}
}