{
  "type": "Feature",
  "properties": {
    "iso:country":"DE",
    "sg:address":"Im H\u00f6ferfeld 8",
    "sg:city":"Riedstadt",
    "sg:phone":"+49 6158/915392",
    "sg:postcode":"64560",
    "sg:province":"Hessen",
    "wof:name":"Cae Computeranwendungen Und Entwicklungstechniken",
    "wof:placetype":"venue"
},
  "geometry": {"coordinates":[8.49595,49.82864],"type":"Point"}
}