{
  "type": "Feature",
  "properties": {
    "iso:country":"DE",
    "sg:address":"Ehinger Stra\u00dfe 30",
    "sg:city":"Rottenacker",
    "sg:phone":"+49 7393/520",
    "sg:postcode":"89616",
    "sg:province":"Baden-W\u00fcrttemberg",
    "wof:name":"Bp Chemicals Plas Tec Gmbh Gesch\u00e4ftsbereich Techn. Teile",
    "wof:placetype":"venue"
},
  "geometry": {"coordinates":[9.700575,48.237957],"type":"Point"}
}