{
  "type": "Feature",
  "properties": {
    "iso:country":"DE",
    "sg:address":"Am Busbahnhof 12",
    "sg:city":"Westerr\u00f6nfeld",
    "sg:phone":"+49 4331/80733",
    "sg:postcode":"24784",
    "sg:province":"Schleswig-Holstein",
    "wof:name":"U. Timm",
    "wof:placetype":"venue"
},
  "geometry": {"coordinates":[9.654655,54.276169],"type":"Point"}
}