{
  "type": "Feature",
  "properties": {
    "iso:country":"DE",
    "sg:address":"Stuttgarter Str. 42",
    "sg:city":"Winnenden",
    "sg:phone":"+49 7195/2548",
    "sg:postcode":"71364",
    "sg:province":"Baden-W\u00fcrttemberg",
    "wof:name":"Ischinger Karosseriebau Gmbh",
    "wof:placetype":"venue"
},
  "geometry": {"coordinates":[9.422282,48.890018],"type":"Point"}
}