{
  "type": "Feature",
  "properties": {
    "iso:country":"DE",
    "sg:address":"Stenner Str. 19",
    "sg:city":"Zwickau",
    "sg:phone":"+49 375/213631",
    "sg:postcode":"08064",
    "sg:province":"Sachsen",
    "wof:name":"Christiane Und Heiko Oeser",
    "wof:placetype":"venue"
},
  "geometry": {"coordinates":[12.455745,50.685406],"type":"Point"}
}