{
  "type": "Feature",
  "properties": {
    "iso:country":"DE",
    "sg:address":"Im Eselsberg 106",
    "sg:city":"Schwaigern",
    "sg:phone":"+49 7138/920808",
    "sg:postcode":"74193",
    "sg:province":"Baden-W\u00fcrttemberg",
    "wof:name":"Werner Schukraft Architekt",
    "wof:placetype":"venue"
},
  "geometry": {"coordinates":[9.051583,49.148293],"type":"Point"}
}