{
  "type": "Feature",
  "properties": {
    "iso:country":"DE",
    "sg:address":"Dr.-Bachl-Str. 11 a",
    "sg:city":"Pfarrkirchen",
    "sg:phone":"+49 8561/6606",
    "sg:postcode":"84347",
    "sg:province":"Bayern",
    "wof:name":"Stadthalle",
    "wof:placetype":"venue"
},
  "geometry": {"coordinates":[12.933371,48.430008],"type":"Point"}
}