{
  "type": "Feature",
  "properties": {
    "iso:country":"DE",
    "sg:address":"Alter Holzweg 4 d",
    "sg:city":"Wolfenb\u00fcttel",
    "sg:phone":"+49 5331/65021",
    "sg:postcode":"38304",
    "sg:province":"Niedersachsen",
    "wof:name":"Baer Eisenbahnsignal- Technik Gmbh",
    "wof:placetype":"venue"
},
  "geometry": {"coordinates":[10.548247,52.141785],"type":"Point"}
}