{
  "type": "Feature",
  "properties": {
    "iso:country":"DE",
    "sg:address":"Br\u00fccker Landstr. 16",
    "sg:city":"Belzig",
    "sg:postcode":"14806",
    "sg:province":"Brandenburg",
    "wof:name":"Aldi Gmbh & Co. Kg",
    "wof:placetype":"venue"
},
  "geometry": {"coordinates":[12.6082420349,52.143951416],"type":"Point"}
}