{
  "type": "Feature",
  "properties": {
    "iso:country":"DE",
    "sg:address":"Untergasse 43",
    "sg:city":"Trebur",
    "sg:phone":"+49 6147/622",
    "sg:postcode":"65468",
    "sg:province":"Hessen",
    "wof:name":"Grimm Ohg",
    "wof:placetype":"venue"
},
  "geometry": {"coordinates":[8.391872,49.88567],"type":"Point"}
}