{
  "type": "Feature",
  "properties": {
    "iso:country":"DE",
    "sg:address":"Hummelsb\u00fctteler Landstr. 70",
    "sg:city":"Hamburg",
    "sg:phone":"+49 40/506633",
    "sg:postcode":"22335",
    "sg:province":"Hamburg",
    "wof:name":"A. Ludat",
    "wof:placetype":"venue"
},
  "geometry": {"coordinates":[10.0278892517,53.6315956116],"type":"Point"}
}