{
  "type": "Feature",
  "properties": {
    "iso:country":"DE",
    "sg:address":"Kiedricher Str. 34",
    "sg:city":"Eltville",
    "sg:phone":"+49 6123/5630",
    "sg:postcode":"65343",
    "sg:province":"Hessen",
    "wof:name":"Ludwig Sch\u00e4fer Stra\u00dfen- Und Tiefbau Gmbh",
    "wof:placetype":"venue"
},
  "geometry": {"coordinates":[8.1090106964,50.0286064148],"type":"Point"}
}