{
  "type": "Feature",
  "properties": {
    "iso:country":"DE",
    "sg:address":"Kurf\u00fcrstendamm 207-208",
    "sg:city":"Berlin",
    "sg:postcode":"10719",
    "sg:province":"Berlin",
    "wof:name":"Cyro-plan Industrieanlagen Ag",
    "wof:placetype":"venue"
},
  "geometry": {"coordinates":[13.323301,52.501991],"type":"Point"}
}