{
  "type": "Feature",
  "properties": {
    "iso:country":"DE",
    "sg:address":"Bruchstr. 39",
    "sg:city":"Wetzlar",
    "sg:phone":"+49 6441/72543",
    "sg:postcode":"35581",
    "sg:province":"Hessen",
    "wof:name":"A. Gertz Heissmangel",
    "wof:placetype":"venue"
},
  "geometry": {"coordinates":[8.572552681,50.5497016907],"type":"Point"}
}