{
  "type": "Feature",
  "properties": {
    "iso:country":"DE",
    "sg:address":"Im Paridam 4a",
    "sg:city":"Wittingen",
    "sg:phone":"+49 5831/645",
    "sg:postcode":"29378",
    "sg:province":"Niedersachsen",
    "wof:name":"Sylvia Meinecke Hebamme",
    "wof:placetype":"venue"
},
  "geometry": {"coordinates":[10.745773,52.723564],"type":"Point"}
}