{
  "type": "Feature",
  "properties": {
    "iso:country":"DE",
    "sg:address":"Barlachstr. 8",
    "sg:city":"M\u00fcnchen",
    "sg:phone":"+49 89/30001405",
    "sg:postcode":"80804",
    "sg:province":"Bayern",
    "wof:name":"Bj\u00f6rn Gerken Rechtsanwalt",
    "wof:placetype":"venue"
},
  "geometry": {"coordinates":[11.5739393234,48.1774139404],"type":"Point"}
}