{
  "type": "Feature",
  "properties": {
    "iso:country":"DE",
    "sg:address":"Obere K\u00f6nigstr. 12",
    "sg:city":"M\u00fchlacker",
    "sg:phone":"+49 7041/41737",
    "sg:postcode":"75417",
    "sg:province":"Baden-W\u00fcrttemberg",
    "wof:name":"Prof. Dr. O. Maier Architekt",
    "wof:placetype":"venue"
},
  "geometry": {"coordinates":[8.838425,48.938797],"type":"Point"}
}