{
  "type": "Feature",
  "properties": {
    "iso:country":"DE",
    "sg:address":"Zum Alten Wasserwerk",
    "sg:city":"Overath",
    "sg:postcode":"51491",
    "sg:province":"Nordrhein-Westfalen",
    "wof:name":"M\u00dcnzer Und Diehl Gmbh Computersysteme-",
    "wof:placetype":"venue"
},
  "geometry": {"coordinates":[7.2495498657,50.9622955322],"type":"Point"}
}