{
  "type": "Feature",
  "properties": {
    "iso:country":"DE",
    "sg:address":"M\u00fchlenhagen 16",
    "sg:city":"Burgwedel",
    "sg:phone":"+49 5139/3705",
    "sg:postcode":"30938",
    "sg:province":"Niedersachsen",
    "wof:name":"Rolf Kr\u00fcger",
    "wof:placetype":"venue"
},
  "geometry": {"coordinates":[9.850771,52.489517],"type":"Point"}
}