{
  "type": "Feature",
  "properties": {
    "iso:country":"DE",
    "sg:address":"Hauptstr. 41",
    "sg:city":"Lindenberg",
    "sg:phone":"+49 8381/3944",
    "sg:postcode":"88161",
    "sg:province":"Bayern",
    "wof:name":"Raphael-apotheke",
    "wof:placetype":"venue"
},
  "geometry": {"coordinates":[8.095149,49.37516],"type":"Point"}
}