{
  "type": "Feature",
  "properties": {
    "iso:country":"DE",
    "sg:address":"Schmidtstr. 12",
    "sg:city":"Frankfurt",
    "sg:phone":"+49 69/47892519",
    "sg:postcode":"60326",
    "sg:province":"Hessen",
    "wof:name":"Net 2 Man Gmbh",
    "wof:placetype":"venue"
},
  "geometry": {"coordinates":[8.6183481216,50.103729248],"type":"Point"}
}