{
  "type": "Feature",
  "properties": {
    "iso:country":"DE",
    "sg:address":"Schifferstadter Str. 4",
    "sg:city":"Hochdorf-Assenheim",
    "sg:postcode":"67126",
    "sg:province":"Rheinland-Pfalz",
    "wof:name":"Lingua-serv Gmbh",
    "wof:placetype":"venue"
},
  "geometry": {"coordinates":[8.2819681168,49.4179954529],"type":"Point"}
}