{
  "type": "Feature",
  "properties": {
    "iso:country":"DE",
    "sg:address":"Blumenring 35",
    "sg:city":"Ochsenfurt",
    "sg:phone":"+49 9331/3401",
    "sg:postcode":"97199",
    "sg:province":"Bayern",
    "wof:name":"Awr Flugvermittlung Dr. Wolfgang Rees",
    "wof:placetype":"venue"
},
  "geometry": {"coordinates":[10.039027,49.659939],"type":"Point"}
}