{
  "type": "Feature",
  "properties": {
    "iso:country":"DE",
    "sg:address":"Heuss-Str. 9",
    "sg:city":"Fulda",
    "sg:phone":"+49 661/402000",
    "sg:postcode":"36043",
    "sg:province":"Hessen",
    "wof:name":"R. Neu",
    "wof:placetype":"venue"
},
  "geometry": {"coordinates":[9.7070207596,50.527923584],"type":"Point"}
}