{
  "type": "Feature",
  "properties": {
    "iso:country":"DE",
    "sg:address":"Rieslingweg 7",
    "sg:city":"Pfedelbach",
    "sg:phone":"+49 7949/524",
    "sg:postcode":"74629",
    "sg:province":"Baden-W\u00fcrttemberg",
    "wof:name":"Karl-heinz Feucht",
    "wof:placetype":"venue"
},
  "geometry": {"coordinates":[9.539949,49.156384],"type":"Point"}
}