{
  "type": "Feature",
  "properties": {
    "iso:country":"DE",
    "sg:address":"Lissenstr. 6",
    "sg:city":"Karlsruhe",
    "sg:phone":"+49 721/42356",
    "sg:postcode":"76227",
    "sg:province":"Baden-W\u00fcrttemberg",
    "wof:name":"R-kauf",
    "wof:placetype":"venue"
},
  "geometry": {"coordinates":[8.454328537,48.9954719543],"type":"Point"}
}