{
  "type": "Feature",
  "properties": {
    "iso:country":"DE",
    "sg:address":"Solitudestr. 49",
    "sg:city":"Ludwigsburg",
    "sg:phone":"+49 7141/93660",
    "sg:postcode":"71638",
    "sg:province":"Baden-W\u00fcrttemberg",
    "wof:name":"Pflugfelder Baubetreuungs Gmbh",
    "wof:placetype":"venue"
},
  "geometry": {"coordinates":[9.188854,48.890518],"type":"Point"}
}