{
  "type": "Feature",
  "properties": {
    "iso:country":"DE",
    "sg:address":"Friedrich-Ebert-Str. 4",
    "sg:city":"Nidderau",
    "sg:phone":"+49 6187/3592",
    "sg:postcode":"61130",
    "sg:province":"Hessen",
    "wof:name":"Karlheinz Sch\u00fcler",
    "wof:placetype":"venue"
},
  "geometry": {"coordinates":[8.8800964355,50.2226486206],"type":"Point"}
}