{
  "type": "Feature",
  "properties": {
    "iso:country":"DE",
    "sg:address":"Bochstr. 20",
    "sg:city":"Dahme",
    "sg:phone":"+49 35451/474",
    "sg:postcode":"15936",
    "sg:province":"Brandenburg",
    "wof:name":"Goldener Stern Pension Inh. Ellen Burghardt",
    "wof:placetype":"venue"
},
  "geometry": {"coordinates":[13.430232048,51.8693161011],"type":"Point"}
}