{
  "type": "Feature",
  "properties": {
    "iso:country":"DE",
    "sg:address":"Sinstorfer Weg 35",
    "sg:city":"Hamburg",
    "sg:phone":"+49 40/7603764",
    "sg:postcode":"21077",
    "sg:province":"Hamburg",
    "wof:name":"H. Liegandt",
    "wof:placetype":"venue"
},
  "geometry": {"coordinates":[9.971639,53.430218],"type":"Point"}
}