{
  "type": "Feature",
  "properties": {
    "iso:country":"DE",
    "sg:address":"Schillerstr. 69",
    "sg:city":"Heusweiler",
    "sg:postcode":"66265",
    "sg:province":"Saarland",
    "wof:name":"Berthold Rau Verpachtungs- Und Beratungs Gmbh & Co. Kg",
    "wof:placetype":"venue"
},
  "geometry": {"coordinates":[6.9191570282,49.3336257935],"type":"Point"}
}