{
  "type": "Feature",
  "properties": {
    "iso:country":"DE",
    "sg:address":"Am Anger 37",
    "sg:city":"Hamb\u00fchren",
    "sg:phone":"+49 5084/6129",
    "sg:postcode":"29313",
    "sg:province":"Niedersachsen",
    "wof:name":"Hans-dieter Sievers",
    "wof:placetype":"venue"
},
  "geometry": {"coordinates":[9.9317932129,52.6407318115],"type":"Point"}
}