{
  "type": "Feature",
  "properties": {
    "iso:country":"DE",
    "sg:address":"Am Hulsberg 136",
    "sg:city":"Bremen",
    "sg:phone":"+49 421/324002",
    "sg:postcode":"28205",
    "sg:province":"Bremen",
    "wof:name":"Bund Deutscher Pfadfinder Im Bund Demokratischer Jugend",
    "wof:placetype":"venue"
},
  "geometry": {"coordinates":[8.8502874374,53.071346283],"type":"Point"}
}