{
  "type": "Feature",
  "properties": {
    "iso:country":"DE",
    "sg:address":"Leihaer Str. 15",
    "sg:city":"Gr\u00f6st",
    "sg:phone":"+49 34633/29000",
    "sg:postcode":"06632",
    "sg:province":"Sachsen-Anhalt",
    "wof:name":"Tm Marketing Und Consulting Gmbh",
    "wof:placetype":"venue"
},
  "geometry": {"coordinates":[11.768330574,51.2381973267],"type":"Point"}
}