{
  "type": "Feature",
  "properties": {
    "iso:country":"DE",
    "sg:address":"Sch\u00fctzenstr. 79",
    "sg:city":"Bad Neuenahr-Ahrweiler",
    "sg:phone":"+49 2641/35224",
    "sg:postcode":"53474",
    "sg:province":"Rheinland-Pfalz",
    "wof:name":"Hermann-josef Kr\u00e4mer Masseur",
    "wof:placetype":"venue"
},
  "geometry": {"coordinates":[7.108706,50.542282],"type":"Point"}
}