{
  "type": "Feature",
  "properties": {
    "iso:country":"DE",
    "sg:address":"Alter Markt 10",
    "sg:city":"Wuppertal",
    "sg:phone":"+49 202/4087133",
    "sg:postcode":"42275",
    "sg:province":"Nordrhein-Westfalen",
    "wof:name":"Immobilien Und Baubetreuung",
    "wof:placetype":"venue"
},
  "geometry": {"coordinates":[7.197655,51.270241],"type":"Point"}
}