{
  "type": "Feature",
  "properties": {
    "iso:country":"DE",
    "sg:address":"Am Zwergberg 10",
    "sg:city":"Schmachtenhagen",
    "sg:phone":"+49 3301/803578",
    "sg:postcode":"16515",
    "sg:province":"Brandenburg",
    "wof:name":"Marten Gmbh",
    "wof:placetype":"venue"
},
  "geometry": {"coordinates":[13.318614006,52.7673950195],"type":"Point"}
}