{
  "type": "Feature",
  "properties": {
    "iso:country":"DE",
    "sg:address":"D\u00f6rntelsberg 6",
    "sg:city":"Sinsheim",
    "sg:postcode":"74889",
    "sg:province":"Baden-W\u00fcrttemberg",
    "wof:name":"Labomatic Vertriebs-gmbh",
    "wof:placetype":"venue"
},
  "geometry": {"coordinates":[8.8735704422,49.253868103],"type":"Point"}
}