{
  "type": "Feature",
  "properties": {
    "iso:country":"DE",
    "sg:address":"An der Elbe 189",
    "sg:city":"Beuster",
    "sg:postcode":"39615",
    "sg:province":"Sachsen-Anhalt",
    "wof:name":"Verwaltungsgesellschaft Happy- Beton Gmbh",
    "wof:placetype":"venue"
},
  "geometry": {"coordinates":[11.8288879395,52.93699646],"type":"Point"}
}