{
  "type": "Feature",
  "properties": {
    "iso:country":"DE",
    "sg:address":"Austr. 61",
    "sg:city":"Stuttgart",
    "sg:phone":"+49 711/591818",
    "sg:postcode":"70376",
    "sg:province":"Baden-W\u00fcrttemberg",
    "wof:name":"Deutscher Hausbau Painhofer Und Co.",
    "wof:placetype":"venue"
},
  "geometry": {"coordinates":[9.223837,48.822491],"type":"Point"}
}