{
  "type": "Feature",
  "properties": {
    "iso:country":"DE",
    "sg:address":"Kirchenallee 56",
    "sg:city":"Hamburg",
    "sg:phone":"+49 40/55288670",
    "sg:postcode":"20099",
    "sg:province":"Hamburg",
    "wof:name":"Khaled Siddig Export Import Transparente E. K.",
    "wof:placetype":"venue"
},
  "geometry": {"coordinates":[10.008961,53.55267],"type":"Point"}
}