{
  "type": "Feature",
  "properties": {
    "iso:country":"DE",
    "sg:address":"Am Walde 4",
    "sg:city":"Porta Westfalica",
    "sg:phone":"+49 571/70215",
    "sg:postcode":"32457",
    "sg:province":"Nordrhein-Westfalen",
    "wof:name":"Alfred Dreyer",
    "wof:placetype":"venue"
},
  "geometry": {"coordinates":[8.990449,52.25729],"type":"Point"}
}