{
  "type": "Feature",
  "properties": {
    "iso:country":"DE",
    "sg:address":"Teichweg 6",
    "sg:city":"Freiberg",
    "sg:phone":"+49 3731/24247",
    "sg:postcode":"09599",
    "sg:province":"Sachsen",
    "wof:name":"Camping-tex Gmbh",
    "wof:placetype":"venue"
},
  "geometry": {"coordinates":[13.3358373642,50.9107322693],"type":"Point"}
}