{
  "type": "Feature",
  "properties": {
    "iso:country":"DE",
    "sg:address":"Leuchtturmweg 3",
    "sg:city":"Kellenhusen",
    "sg:phone":"+49 4364/9396",
    "sg:postcode":"23746",
    "sg:province":"Schleswig-Holstein",
    "wof:name":"Klaus Peters",
    "wof:placetype":"venue"
},
  "geometry": {"coordinates":[11.0659418106,54.1927528381],"type":"Point"}
}