{
  "type": "Feature",
  "properties": {
    "iso:country":"DE",
    "sg:address":"Schulstr. 13",
    "sg:city":"Velden",
    "sg:phone":"+49 8742/8989",
    "sg:postcode":"84149",
    "sg:province":"Bayern",
    "wof:name":"Franz Heckel",
    "wof:placetype":"venue"
},
  "geometry": {"coordinates":[12.257535,48.367973],"type":"Point"}
}