{
  "type": "Feature",
  "properties": {
    "iso:country":"DE",
    "sg:address":"Flehenberg 52",
    "sg:city":"W\u00fclfrath",
    "sg:phone":"+49 2058/3245",
    "sg:postcode":"42489",
    "sg:province":"Nordrhein-Westfalen",
    "wof:name":"Harry Kinder",
    "wof:placetype":"venue"
},
  "geometry": {"coordinates":[7.052621,51.28091],"type":"Point"}
}