{
  "type": "Feature",
  "properties": {
    "iso:country":"DE",
    "sg:address":"Werner Str. 98",
    "sg:city":"Selm",
    "sg:phone":"+49 2592/5314",
    "sg:postcode":"59379",
    "sg:province":"Nordrhein-Westfalen",
    "wof:name":"Josef Marian",
    "wof:placetype":"venue"
},
  "geometry": {"coordinates":[7.4829292297,51.6946372986],"type":"Point"}
}