{
  "type": "Feature",
  "properties": {
    "iso:country":"DE",
    "sg:address":"Bahnhofstr. 70",
    "sg:city":"Wrestedt",
    "sg:phone":"+49 4958/02277",
    "sg:postcode":"29559",
    "sg:province":"Niedersachsen",
    "wof:name":"Dietmar Wilke Konservenfabrik",
    "wof:placetype":"venue"
},
  "geometry": {"coordinates":[10.5907793045,52.9070472717],"type":"Point"}
}