{
  "type": "Feature",
  "properties": {
    "iso:country":"DE",
    "sg:address":"Horbeller Str. 200",
    "sg:city":"H\u00fcrth",
    "sg:phone":"+49 4922/3333870",
    "sg:postcode":"50354",
    "sg:province":"Nordrhein-Westfalen",
    "wof:name":"Mathias Sponer Gmbh",
    "wof:placetype":"venue"
},
  "geometry": {"coordinates":[6.865551,50.903992],"type":"Point"}
}