{
  "type": "Feature",
  "properties": {
    "iso:country":"DE",
    "sg:address":"Trinkbornstr. 6",
    "sg:city":"D\u00f6rth",
    "sg:phone":"+49 6747/93900",
    "sg:postcode":"56281",
    "sg:province":"Rheinland-Pfalz",
    "wof:name":"Morschh\u00e4user Verwaltungs Gmbh",
    "wof:placetype":"venue"
},
  "geometry": {"coordinates":[7.58792,50.159775],"type":"Point"}
}