{
  "type": "Feature",
  "properties": {
    "iso:country":"DE",
    "sg:address":"Reichenhainer Str. 55",
    "sg:city":"Chemnitz",
    "sg:postcode":"09126",
    "sg:province":"Sachsen",
    "wof:name":"D & B Kulturgesellschaft Mbh",
    "wof:placetype":"venue"
},
  "geometry": {"coordinates":[12.930295,50.814899],"type":"Point"}
}