{
  "type": "Feature",
  "properties": {
    "iso:country":"DE",
    "sg:address":"Seffenter Berg 13",
    "sg:city":"Aachen",
    "sg:postcode":"52074",
    "sg:province":"Nordrhein-Westfalen",
    "wof:name":"Tetra Gmbh",
    "wof:placetype":"venue"
},
  "geometry": {"coordinates":[6.0404229164,50.7900619507],"type":"Point"}
}