{
  "type": "Feature",
  "properties": {
    "iso:country":"DE",
    "sg:address":"Bahnweg 5",
    "sg:city":"Schwarzenfeld",
    "sg:phone":"+49 9435/2390",
    "sg:postcode":"92521",
    "sg:province":"Bayern",
    "wof:name":"H. Vier Heissmangel",
    "wof:placetype":"venue"
},
  "geometry": {"coordinates":[12.1329345703,49.3937835693],"type":"Point"}
}