{
  "type": "Feature",
  "properties": {
    "iso:country":"DE",
    "sg:address":"In der Lesehalle",
    "sg:city":"Bodenfelde",
    "sg:postcode":"37194",
    "sg:province":"Hessen",
    "wof:name":"B\u00fccherei Bodenfelde",
    "wof:placetype":"venue"
},
  "geometry": {"coordinates":[9.554917,51.639236],"type":"Point"}
}