{
  "type": "Feature",
  "properties": {
    "iso:country":"DE",
    "sg:address":"Untere Dorfstr. 20",
    "sg:city":"Boffzen",
    "sg:phone":"+49 5271/5346",
    "sg:postcode":"37691",
    "sg:province":"Niedersachsen",
    "wof:name":"Edith Hinze",
    "wof:placetype":"venue"
},
  "geometry": {"coordinates":[9.387174,51.75172],"type":"Point"}
}