{
  "type": "Feature",
  "properties": {
    "iso:country":"DE",
    "sg:address":"Wertinger Str. 30",
    "sg:city":"H\u00f6chst\u00e4dt",
    "sg:phone":"+49 9074/1660",
    "sg:postcode":"89420",
    "sg:province":"Bayern",
    "wof:name":"Friedrich Ludwig",
    "wof:placetype":"venue"
},
  "geometry": {"coordinates":[10.589961,48.601131],"type":"Point"}
}