{
  "type": "Feature",
  "properties": {
    "iso:country":"DE",
    "sg:address":"Dorotheastr. 8",
    "sg:city":"Berlin",
    "sg:postcode":"10318",
    "sg:province":"Berlin",
    "wof:name":"Holoeye Gmbh",
    "wof:placetype":"venue"
},
  "geometry": {"coordinates":[13.5224437714,52.4851036072],"type":"Point"}
}