{
  "type": "Feature",
  "properties": {
    "iso:country":"DE",
    "sg:address":"Max-Planck-Str. 12",
    "sg:city":"Vreden",
    "sg:phone":"+49 2564/98620",
    "sg:postcode":"48691",
    "sg:province":"Nordrhein-Westfalen",
    "wof:name":"Kruse Reproduktionen Gmbh",
    "wof:placetype":"venue"
},
  "geometry": {"coordinates":[6.79554,52.020683],"type":"Point"}
}