{
  "type": "Feature",
  "properties": {
    "iso:country":"DE",
    "sg:address":"Kleinneusch\u00f6nberger Str. 122",
    "sg:city":"Olbernhau",
    "sg:phone":"+49 37360/75000",
    "sg:postcode":"09526",
    "sg:province":"Sachsen",
    "wof:name":"Az Industriebedarfs Gmbh",
    "wof:placetype":"venue"
},
  "geometry": {"coordinates":[13.302421,50.677086],"type":"Point"}
}