{
  "type": "Feature",
  "properties": {
    "iso:country":"DE",
    "sg:address":"Distelweg 37",
    "sg:city":"R\u00f6dental",
    "sg:phone":"+49 9563/6523",
    "sg:postcode":"96472",
    "sg:province":"Bayern",
    "wof:name":"Werner Krug",
    "wof:placetype":"venue"
},
  "geometry": {"coordinates":[11.0390996933,50.2976608276],"type":"Point"}
}