{
  "type": "Feature",
  "properties": {
    "iso:country":"DE",
    "sg:address":"Marktstr. 5",
    "sg:city":"B\u00fchl",
    "sg:phone":"+49 7223/24140",
    "sg:postcode":"77815",
    "sg:province":"Baden-W\u00fcrttemberg",
    "wof:name":"Apollon",
    "wof:placetype":"venue"
},
  "geometry": {"coordinates":[8.1344623566,48.6974372864],"type":"Point"}
}