{
  "type": "Feature",
  "properties": {
    "iso:country":"DE",
    "sg:address":"Heidsiekstr. 8",
    "sg:city":"Bielefeld",
    "sg:phone":"+49 521/2702141",
    "sg:postcode":"33607",
    "sg:province":"Nordrhein-Westfalen",
    "wof:name":"Friedrich R\u00fcter Gmbh",
    "wof:placetype":"venue"
},
  "geometry": {"coordinates":[8.5787620544,52.0245094299],"type":"Point"}
}