{
  "type": "Feature",
  "properties": {
    "iso:country":"DE",
    "sg:address":"Postfach 911365",
    "sg:city":"Hannover",
    "sg:postcode":"30433",
    "sg:province":"Niedersachsen",
    "wof:name":"Vaw Leichtmetall Gmbh",
    "wof:placetype":"venue"
},
  "geometry": {"coordinates":[9.73573,52.37199],"type":"Point"}
}