{
  "type": "Feature",
  "properties": {
    "iso:country":"DE",
    "sg:address":"Kreisstr. 11",
    "sg:city":"Kleinblittersdorf",
    "sg:phone":"+49 6805/8528",
    "sg:postcode":"66271",
    "sg:province":"Saarland",
    "wof:name":"Schmitt Schreinerei Gmbh",
    "wof:placetype":"venue"
},
  "geometry": {"coordinates":[7.045715,49.1465],"type":"Point"}
}