{
  "type": "Feature",
  "properties": {
    "iso:country":"DE",
    "sg:address":"Grabower Landstr. 39",
    "sg:city":"Burg",
    "sg:phone":"+49 3921/984525",
    "sg:postcode":"39288",
    "sg:province":"Sachsen-Anhalt",
    "wof:name":"Borchers & Speer Baumaschinen-bauger\u00e4te",
    "wof:placetype":"venue"
},
  "geometry": {"coordinates":[11.87652,52.266647],"type":"Point"}
}