{
  "type": "Feature",
  "properties": {
    "iso:country":"DE",
    "sg:address":"Eckenbacher Hardt 48",
    "sg:city":"N\u00fcmbrecht",
    "sg:phone":"+49 2293/7794",
    "sg:postcode":"51588",
    "sg:province":"Nordrhein-Westfalen",
    "wof:name":"Hans Ohm",
    "wof:placetype":"venue"
},
  "geometry": {"coordinates":[7.5338292122,50.9088630676],"type":"Point"}
}