{
  "type": "Feature",
  "properties": {
    "iso:country":"DE",
    "sg:address":"Werraweg 3",
    "sg:city":"Landshut",
    "sg:phone":"+49 871/5758",
    "sg:postcode":"84036",
    "sg:province":"Bayern",
    "wof:name":"Peter Bosch",
    "wof:placetype":"venue"
},
  "geometry": {"coordinates":[12.2042293549,48.5661201477],"type":"Point"}
}