{
  "type": "Feature",
  "properties": {
    "iso:country":"DE",
    "sg:address":"Mottenburger Str. 5",
    "sg:city":"Hamburg",
    "sg:phone":"+49 40/39902030",
    "sg:postcode":"22765",
    "sg:province":"Hamburg",
    "wof:name":"Basi X It Ges. F\u00fcr Informationstechnologie Mbh",
    "wof:placetype":"venue"
},
  "geometry": {"coordinates":[9.928206,53.550743],"type":"Point"}
}