{
  "type": "Feature",
  "properties": {
    "iso:country":"DE",
    "sg:address":"Postfach 100431",
    "sg:city":"Wolfsburg",
    "sg:phone":"+49 5361/881399",
    "sg:postcode":"38404",
    "sg:province":"Niedersachsen",
    "wof:name":"Motocross Wolfsburg",
    "wof:placetype":"venue"
},
  "geometry": {"coordinates":[10.78497,52.42181],"type":"Point"}
}