{
  "type": "Feature",
  "properties": {
    "iso:country":"DE",
    "sg:address":"Hasselbrocker Str. 11",
    "sg:city":"Walchum",
    "sg:phone":"+49 5939/674",
    "sg:postcode":"26907",
    "sg:province":"Niedersachsen",
    "wof:name":"Bernhard Sandmann",
    "wof:placetype":"venue"
},
  "geometry": {"coordinates":[7.279463,52.930336],"type":"Point"}
}