{
  "type": "Feature",
  "properties": {
    "iso:country":"DE",
    "sg:address":"F\u00f6rsterweg 1",
    "sg:city":"Quickborn",
    "sg:phone":"+49 4106/626662",
    "sg:postcode":"25451",
    "sg:province":"Schleswig-Holstein",
    "wof:name":"Fashion Sport Agentur Peter-vincent Schulz",
    "wof:placetype":"venue"
},
  "geometry": {"coordinates":[9.9027118683,53.7181549072],"type":"Point"}
}