{
  "type": "Feature",
  "properties": {
    "iso:country":"DE",
    "sg:address":"Bachstr. 5",
    "sg:city":"Oberstdorf",
    "sg:phone":"+49 8322/1616",
    "sg:postcode":"87561",
    "sg:province":"Bayern",
    "wof:name":"Christian Omonsky",
    "wof:placetype":"venue"
},
  "geometry": {"coordinates":[10.2797222137,47.4079551697],"type":"Point"}
}