{
  "type": "Feature",
  "properties": {
    "iso:country":"DE",
    "sg:address":"Friedenstr. 9",
    "sg:city":"Ottobrunn",
    "sg:phone":"+49 89/60811830",
    "sg:postcode":"85521",
    "sg:province":"Bayern",
    "wof:name":"Rack & Sohn Bau Gmbh",
    "wof:placetype":"venue"
},
  "geometry": {"coordinates":[11.6619853973,48.0683555603],"type":"Point"}
}