{
  "type": "Feature",
  "properties": {
    "iso:country":"DE",
    "sg:address":"Markt 23",
    "sg:city":"Altenburg",
    "sg:phone":"+49 3447/311431",
    "sg:postcode":"04600",
    "sg:province":"Th\u00fcringen",
    "wof:name":"Apotheke Am Markt Inh. Renate H\u00f6nig",
    "wof:placetype":"venue"
},
  "geometry": {"coordinates":[12.433429,50.985382],"type":"Point"}
}