{
  "type": "Feature",
  "properties": {
    "iso:country":"DE",
    "sg:address":"Leipziger Str. 17",
    "sg:city":"Crimmitschau",
    "sg:phone":"+49 3762/49498",
    "sg:postcode":"08451",
    "sg:province":"Sachsen",
    "wof:name":"W. K\u00fchn Steuerberater",
    "wof:placetype":"venue"
},
  "geometry": {"coordinates":[12.3857402802,50.8181190491],"type":"Point"}
}