{
  "type": "Feature",
  "properties": {
    "iso:country":"DE",
    "sg:address":"Stephensonstrasse 12-14",
    "sg:city":"Dresden",
    "sg:phone":"+49 351/2091411",
    "sg:postcode":"01275",
    "sg:province":"Sachsen",
    "wof:name":"Die Johanniter In Sachsen - Juh E.v.",
    "wof:placetype":"venue"
},
  "geometry": {"coordinates":[13.827114,51.005196],"type":"Point"}
}