{
  "type": "Feature",
  "properties": {
    "iso:country":"DE",
    "sg:address":"Diegelsberger Str. 33",
    "sg:city":"Ebersbach",
    "sg:phone":"+49 7163/8919",
    "sg:postcode":"73061",
    "sg:province":"Baden-W\u00fcrttemberg",
    "wof:name":"Anton Tauber",
    "wof:placetype":"venue"
},
  "geometry": {"coordinates":[9.5388698578,48.7224960327],"type":"Point"}
}