{
  "type": "Feature",
  "properties": {
    "iso:country":"DE",
    "sg:address":"Haselnu\u00dfweg 13",
    "sg:city":"Siegburg",
    "sg:phone":"+49 2241/387171",
    "sg:postcode":"53721",
    "sg:province":"Nordrhein-Westfalen",
    "wof:name":"Kofa Gmbh",
    "wof:placetype":"venue"
},
  "geometry": {"coordinates":[7.2567448616,50.8060913086],"type":"Point"}
}