{
  "type": "Feature",
  "properties": {
    "iso:country":"DE",
    "sg:address":"Am Str\u00e4\u00dfel 16",
    "sg:city":"Lustadt",
    "sg:phone":"+49 6347/8316",
    "sg:postcode":"67363",
    "sg:province":"Rheinland-Pfalz",
    "wof:name":"Rudolf Klohe",
    "wof:placetype":"venue"
},
  "geometry": {"coordinates":[8.2813386917,49.2460823059],"type":"Point"}
}