{
  "type": "Feature",
  "properties": {
    "iso:country":"DE",
    "sg:address":"Steinbrechstr.11",
    "sg:city":"Magstadt",
    "sg:phone":"+49 7159/94520",
    "sg:postcode":"71106",
    "sg:province":"Baden-W\u00fcrttemberg",
    "wof:name":"Braun Gmbh Kunststoffe",
    "wof:placetype":"venue"
},
  "geometry": {"coordinates":[8.973780632,48.7459945679],"type":"Point"}
}