{
  "type": "Feature",
  "properties": {
    "iso:country":"DE",
    "sg:address":"Heuenkamp 2",
    "sg:city":"M\u00fcnster",
    "sg:postcode":"48163",
    "sg:province":"Nordrhein-Westfalen",
    "wof:name":"Cht Ges. F\u00fcr Bauprojekte Mbh",
    "wof:placetype":"venue"
},
  "geometry": {"coordinates":[7.5763239861,51.9181442261],"type":"Point"}
}