{
  "type": "Feature",
  "properties": {
    "iso:country":"DE",
    "sg:address":"Arndtstr. 8",
    "sg:city":"Zwickau",
    "sg:phone":"+49 375/301163",
    "sg:postcode":"08058",
    "sg:province":"Sachsen",
    "wof:name":"M. Da\u00dfler Immobilienmakler",
    "wof:placetype":"venue"
},
  "geometry": {"coordinates":[12.4937992096,50.7284736633],"type":"Point"}
}