{
  "type": "Feature",
  "properties": {
    "iso:country":"DE",
    "sg:address":"Frankenstr. 3",
    "sg:city":"Bechhofen",
    "sg:phone":"+49 9822/83511",
    "sg:postcode":"91572",
    "sg:province":"Bayern",
    "wof:name":"Compair Mahle Gmbh Werksb\u00fcro Dietmar Liebig",
    "wof:placetype":"venue"
},
  "geometry": {"coordinates":[10.561569,49.165714],"type":"Point"}
}