{
  "type": "Feature",
  "properties": {
    "iso:country":"DE",
    "sg:address":"Hoverstr. 7",
    "sg:city":"Straelen",
    "sg:phone":"+49 2839/1340",
    "sg:postcode":"47638",
    "sg:province":"Nordrhein-Westfalen",
    "wof:name":"Ti\u00dfen Gmbh & Co. Kg",
    "wof:placetype":"venue"
},
  "geometry": {"coordinates":[6.2444748878,51.385471344],"type":"Point"}
}