{
  "type": "Feature",
  "properties": {
    "iso:country":"DE",
    "sg:address":"Sophienstr. 9",
    "sg:city":"Hof",
    "sg:phone":"+49 9281/84580",
    "sg:postcode":"95028",
    "sg:province":"Bayern",
    "wof:name":"Pizzeria Neustadt",
    "wof:placetype":"venue"
},
  "geometry": {"coordinates":[11.9159832001,50.3133277893],"type":"Point"}
}