{
  "type": "Feature",
  "properties": {
    "iso:country":"DE",
    "sg:address":"K\u00f6lner Str. 55",
    "sg:city":"Engelskirchen",
    "sg:phone":"+49 2262/2541",
    "sg:postcode":"51766",
    "sg:province":"Nordrhein-Westfalen",
    "wof:name":"Gustav Schmidt",
    "wof:placetype":"venue"
},
  "geometry": {"coordinates":[7.4941291809,50.9951972961],"type":"Point"}
}