{
  "type": "Feature",
  "properties": {
    "iso:country":"DE",
    "sg:address":"Verresberger Str. 54",
    "sg:city":"Monheim",
    "sg:phone":"+49 2173/61414",
    "sg:postcode":"40789",
    "sg:province":"Nordrhein-Westfalen",
    "wof:name":"Hans Willi Hilger",
    "wof:placetype":"venue"
},
  "geometry": {"coordinates":[6.886046,51.119797],"type":"Point"}
}