{
  "type": "Feature",
  "properties": {
    "iso:country":"DE",
    "sg:address":"Schwedter Str. 48",
    "sg:city":"Berlin",
    "sg:phone":"+49 30/44053976",
    "sg:postcode":"10435",
    "sg:province":"Berlin",
    "wof:name":"Cvu Ihr Kreatives B\u00fcro Gmbh",
    "wof:placetype":"venue"
},
  "geometry": {"coordinates":[13.404995,52.539574],"type":"Point"}
}