{
  "type": "Feature",
  "properties": {
    "iso:country":"DE",
    "sg:address":"Nienhagener Str. 20",
    "sg:city":"Berlin",
    "sg:phone":"+49 30/9299194",
    "sg:postcode":"13051",
    "sg:province":"Berlin",
    "wof:name":"Karl-heinz Prochaska",
    "wof:placetype":"venue"
},
  "geometry": {"coordinates":[13.4938268661,52.5699081421],"type":"Point"}
}