{
  "type": "Feature",
  "properties": {
    "iso:country":"DE",
    "sg:address":"Piccoloministr. 435",
    "sg:city":"K\u00f6ln",
    "sg:phone":"+49 221/683828",
    "sg:postcode":"51067",
    "sg:province":"Nordrhein-Westfalen",
    "wof:name":"Grund Und Boden Gmbh",
    "wof:placetype":"venue"
},
  "geometry": {"coordinates":[7.0490279198,50.9729537964],"type":"Point"}
}