{
  "type": "Feature",
  "properties": {
    "iso:country":"DE",
    "sg:address":"Obert\u00fcrkheimer Str. 10",
    "sg:city":"Esslingen",
    "sg:phone":"+49 711/325872",
    "sg:postcode":"73733",
    "sg:province":"Baden-W\u00fcrttemberg",
    "wof:name":"W\u00fcrttembergische Versicherung A. Dobler",
    "wof:placetype":"venue"
},
  "geometry": {"coordinates":[9.2763214111,48.7492485046],"type":"Point"}
}