{
  "type": "Feature",
  "properties": {
    "iso:country":"DE",
    "sg:address":"Grasbrunner Str. 18",
    "sg:city":"Putzbrunn",
    "sg:phone":"+49 89/466746",
    "sg:postcode":"85640",
    "sg:province":"Bayern",
    "wof:name":"Restaurant Florian",
    "wof:placetype":"venue"
},
  "geometry": {"coordinates":[11.7198419571,48.0786247253],"type":"Point"}
}