{
  "type": "Feature",
  "properties": {
    "iso:country":"DE",
    "sg:address":"Heinrich-Beck-Str. 17 a",
    "sg:city":"Chemnitz",
    "sg:phone":"+49 371/301427",
    "sg:postcode":"09112",
    "sg:province":"Sachsen",
    "wof:name":"Gerold Wei\u00dfbach",
    "wof:placetype":"venue"
},
  "geometry": {"coordinates":[12.907915,50.828671],"type":"Point"}
}