{
  "type": "Feature",
  "properties": {
    "iso:country":"DE",
    "sg:address":"Hauptstr. 8",
    "sg:city":"Je\u00dfnitz",
    "sg:postcode":"06800",
    "sg:province":"Sachsen-Anhalt",
    "wof:name":"Je\u00dfnitzer Haustechnik Gmbh",
    "wof:placetype":"venue"
},
  "geometry": {"coordinates":[12.2998933792,51.6843223572],"type":"Point"}
}