{
  "type": "Feature",
  "properties": {
    "iso:country":"DE",
    "sg:address":"Egerlandstr. 4",
    "sg:city":"Amberg",
    "sg:phone":"+49 9621/85018",
    "sg:postcode":"92224",
    "sg:province":"Bayern",
    "wof:name":"Richard Benoist",
    "wof:placetype":"venue"
},
  "geometry": {"coordinates":[11.882662,49.427502],"type":"Point"}
}