{
  "type": "Feature",
  "properties": {
    "iso:country":"DE",
    "sg:address":"Beethovenstr. 59",
    "sg:city":"Lorch",
    "sg:phone":"+49 7172/5377",
    "sg:postcode":"73547",
    "sg:province":"Baden-W\u00fcrttemberg",
    "wof:name":"Erich Eipperle",
    "wof:placetype":"venue"
},
  "geometry": {"coordinates":[9.6759300232,48.802444458],"type":"Point"}
}