{
  "type": "Feature",
  "properties": {
    "iso:country":"DE",
    "sg:address":"Humboldtstr. 110",
    "sg:city":"Hamburg",
    "sg:phone":"+49 40/2795102",
    "sg:postcode":"22083",
    "sg:province":"Hamburg",
    "wof:name":"Polo Reisen Postrach & Lo\u00df Gmbh",
    "wof:placetype":"venue"
},
  "geometry": {"coordinates":[10.0214319229,53.5776596069],"type":"Point"}
}