{
  "type": "Feature",
  "properties": {
    "iso:country":"DE",
    "sg:address":"Zum Ukleisee 3",
    "sg:city":"Eutin - Sielbeck",
    "sg:phone":"+49 4521/9000",
    "sg:postcode":"23701",
    "sg:province":"Schleswig-Holstein",
    "wof:name":"Pension & Cafe Zur Post",
    "wof:placetype":"venue"
},
  "geometry": {"coordinates":[10.6248111725,54.1800384521],"type":"Point"}
}