{
  "type": "Feature",
  "properties": {
    "iso:country":"DE",
    "sg:address":"Neuwiesenweg 6",
    "sg:city":"Aidlingen",
    "sg:phone":"+49 7056/2888",
    "sg:postcode":"71134",
    "sg:province":"Baden-W\u00fcrttemberg",
    "wof:name":"Heinz Hartel",
    "wof:placetype":"venue"
},
  "geometry": {"coordinates":[8.8739299774,48.6760520935],"type":"Point"}
}