{
  "type": "Feature",
  "properties": {
    "iso:country":"DE",
    "sg:address":"Krautheimstr. 3",
    "sg:city":"M\u00fcnchen",
    "sg:phone":"+49 89/89220722",
    "sg:postcode":"80997",
    "sg:province":"Bayern",
    "wof:name":"Stephan Sandh\u00f6fer Steuerberater",
    "wof:placetype":"venue"
},
  "geometry": {"coordinates":[11.476808548,48.1784324646],"type":"Point"}
}