{
  "type": "Feature",
  "properties": {
    "iso:country":"DE",
    "sg:address":"St.-Vither-Str. 19",
    "sg:city":"Aachen",
    "sg:phone":"+49 241/61821",
    "sg:postcode":"52066",
    "sg:province":"Nordrhein-Westfalen",
    "wof:name":"Gerd Baltes",
    "wof:placetype":"venue"
},
  "geometry": {"coordinates":[6.0902447701,50.7512283325],"type":"Point"}
}