{
  "type": "Feature",
  "properties": {
    "iso:country":"DE",
    "sg:address":"An der Kirche 12",
    "sg:city":"Burgwedel",
    "sg:phone":"+49 5135/1221",
    "sg:postcode":"30938",
    "sg:province":"Niedersachsen",
    "wof:name":"Dr. Doris Offeney Tier\u00e4rztin",
    "wof:placetype":"venue"
},
  "geometry": {"coordinates":[9.8450155258,52.5663452148],"type":"Point"}
}