{
  "type": "Feature",
  "properties": {
    "iso:country":"DE",
    "sg:address":"Kirchstr. 2",
    "sg:city":"G\u00fctenbach",
    "sg:phone":"+49 7723/7445",
    "sg:postcode":"78148",
    "sg:province":"Baden-W\u00fcrttemberg",
    "wof:name":"G. Weis",
    "wof:placetype":"venue"
},
  "geometry": {"coordinates":[8.1376714706,48.0440216064],"type":"Point"}
}