{
  "type": "Feature",
  "properties": {
    "iso:country":"DE",
    "sg:address":"Maschbruchstr. 3",
    "sg:city":"B\u00fcnde",
    "sg:phone":"+49 5223/60269",
    "sg:postcode":"32257",
    "sg:province":"Nordrhein-Westfalen",
    "wof:name":"Dr. Tuminski Umwelttechnik Gmbh",
    "wof:placetype":"venue"
},
  "geometry": {"coordinates":[8.5444078445,52.2036705017],"type":"Point"}
}