{
  "type": "Feature",
  "properties": {
    "iso:country":"DE",
    "sg:address":"Am Graspl. 3",
    "sg:city":"Braunschweig",
    "sg:phone":"+49 4953/1511316",
    "sg:postcode":"38112",
    "sg:province":"Niedersachsen",
    "wof:name":"Volksbank Wendeburg E.g.",
    "wof:placetype":"venue"
},
  "geometry": {"coordinates":[10.466661,52.305813],"type":"Point"}
}