{
  "type": "Feature",
  "properties": {
    "iso:country":"DE",
    "sg:address":"Waldwinkel 7",
    "sg:city":"Jesteburg",
    "sg:postcode":"21266",
    "sg:province":"Niedersachsen",
    "wof:name":"Wahrmann-immobilien- Management E. K.",
    "wof:placetype":"venue"
},
  "geometry": {"coordinates":[9.9430522919,53.3000297546],"type":"Point"}
}