{
  "type": "Feature",
  "properties": {
    "iso:country":"DE",
    "sg:address":"Wei\u00dfenburger Str. 19",
    "sg:city":"M\u00fcnchen",
    "sg:phone":"+49 89/4480409",
    "sg:postcode":"81667",
    "sg:province":"Bayern",
    "wof:name":"Gastronomie Report Verlags Gmbh",
    "wof:placetype":"venue"
},
  "geometry": {"coordinates":[11.597949028,48.1286201477],"type":"Point"}
}