{
  "type": "Feature",
  "properties": {
    "iso:country":"DE",
    "sg:address":"Haspeler Strasse 25",
    "sg:city":"Wuppertal",
    "sg:phone":"+49 202/5636516",
    "sg:postcode":"42285",
    "sg:province":"Nordrhein-Westfalen",
    "wof:name":"Gewerbliche Schulen I Wuppertal",
    "wof:placetype":"venue"
},
  "geometry": {"coordinates":[7.165215,51.258678],"type":"Point"}
}