{
  "type": "Feature",
  "properties": {
    "iso:country":"DE",
    "sg:address":"Im Gewerbegebiet 16",
    "sg:city":"Hahnbach",
    "sg:postcode":"92256",
    "sg:province":"Bayern",
    "wof:name":"Gg-papier-b\u00f6rse Gmbh",
    "wof:placetype":"venue"
},
  "geometry": {"coordinates":[11.7872400284,49.5316810608],"type":"Point"}
}