{
  "type": "Feature",
  "properties": {
    "iso:country":"DE",
    "sg:address":"Fichtenstr. 6",
    "sg:city":"Berngau",
    "sg:phone":"+49 9181/69651",
    "sg:postcode":"92361",
    "sg:province":"Bayern",
    "wof:name":"Rehtec-gmbh",
    "wof:placetype":"venue"
},
  "geometry": {"coordinates":[11.4005231857,49.2559890747],"type":"Point"}
}