{
  "type": "Feature",
  "properties": {
    "iso:country":"DE",
    "sg:address":"Stra\u00dfe der Befreiung 141",
    "sg:city":"Reinsdorf",
    "sg:phone":"+49 375/294032",
    "sg:postcode":"08141",
    "sg:province":"Sachsen",
    "wof:name":"B. Nawrath",
    "wof:placetype":"venue"
},
  "geometry": {"coordinates":[12.5576267242,50.6994857788],"type":"Point"}
}