{
  "type": "Feature",
  "properties": {
    "iso:country":"DE",
    "sg:address":"Vilsendorfer Str. 20",
    "sg:city":"Bielefeld",
    "sg:phone":"+49 5206/3060",
    "sg:postcode":"33739",
    "sg:province":"Nordrhein-Westfalen",
    "wof:name":"H. Wortmeier Gmbh",
    "wof:placetype":"venue"
},
  "geometry": {"coordinates":[8.522190094,52.0942420959],"type":"Point"}
}