{
  "type": "Feature",
  "properties": {
    "iso:country":"DE",
    "sg:address":"Wichernstr. 29",
    "sg:city":"Lutherstadt Wittenberg",
    "sg:phone":"+49 3491/406776",
    "sg:postcode":"06886",
    "sg:province":"Sachsen-Anhalt",
    "wof:name":"Michael Jurk",
    "wof:placetype":"venue"
},
  "geometry": {"coordinates":[12.6544036865,51.8722801208],"type":"Point"}
}