{
  "type": "Feature",
  "properties": {
    "iso:country":"DE",
    "sg:address":"Mittelstendorf 18",
    "sg:city":"Soltau",
    "sg:phone":"+49 5191/4317",
    "sg:postcode":"29614",
    "sg:province":"Niedersachsen",
    "wof:name":"Walter Tillot",
    "wof:placetype":"venue"
},
  "geometry": {"coordinates":[9.7864198685,52.9488105774],"type":"Point"}
}