{
  "type": "Feature",
  "properties": {
    "iso:country":"DE",
    "sg:address":"Kathi-Kobus-Str. 11",
    "sg:city":"M\u00fcnchen",
    "sg:phone":"+49 89/180071",
    "sg:postcode":"80797",
    "sg:province":"Bayern",
    "wof:name":"Hans Erras Kg",
    "wof:placetype":"venue"
},
  "geometry": {"coordinates":[11.5570030212,48.1596488953],"type":"Point"}
}