{
  "type": "Feature",
  "properties": {
    "iso:country":"DE",
    "sg:address":"Borsigstr. 3",
    "sg:city":"Ingolstadt",
    "sg:phone":"+49 841/966850",
    "sg:postcode":"85053",
    "sg:province":"Bayern",
    "wof:name":"Floramobil M\u00f6belvertrieb Gmbh",
    "wof:placetype":"venue"
},
  "geometry": {"coordinates":[11.439061,48.75016],"type":"Point"}
}