{
  "type": "Feature",
  "properties": {
    "iso:country":"DE",
    "sg:address":"Gartenstra\u00dfe 3",
    "sg:city":"Hochheim-Massenheim",
    "sg:phone":"+49 6145",
    "sg:postcode":"65239",
    "sg:province":"Hessen",
    "wof:name":"Articon Musikproduktion",
    "wof:placetype":"venue"
},
  "geometry": {"coordinates":[8.387103,50.040894],"type":"Point"}
}