{
  "type": "Feature",
  "properties": {
    "iso:country":"DE",
    "sg:address":"Postweg 11",
    "sg:city":"Lenningen",
    "sg:phone":"+49 7026/7977",
    "sg:postcode":"73252",
    "sg:province":"Baden-W\u00fcrttemberg",
    "wof:name":"Diakoniestation Brucken",
    "wof:placetype":"venue"
},
  "geometry": {"coordinates":[9.457047,48.573826],"type":"Point"}
}