{
  "type": "Feature",
  "properties": {
    "iso:country":"DE",
    "sg:address":"Feldblumenweg 26",
    "sg:city":"K\u00f6ln",
    "sg:phone":"+49 221/9486430",
    "sg:postcode":"50858",
    "sg:province":"Nordrhein-Westfalen",
    "wof:name":"Curasoft Gmbh",
    "wof:placetype":"venue"
},
  "geometry": {"coordinates":[6.8557248116,50.9370536804],"type":"Point"}
}