{
  "type": "Feature",
  "properties": {
    "iso:country":"DE",
    "sg:address":"Heidebergenstr. 51",
    "sg:city":"Bonn",
    "sg:postcode":"53229",
    "sg:province":"Nordrhein-Westfalen",
    "wof:name":"Gegege Bautr\u00e4gerges. Mbh",
    "wof:placetype":"venue"
},
  "geometry": {"coordinates":[7.18901,50.747341],"type":"Point"}
}