{
  "type": "Feature",
  "properties": {
    "iso:country":"DE",
    "sg:address":"B\u00fclowstr. 78",
    "sg:city":"Berlin",
    "sg:phone":"+49 30/2614270",
    "sg:postcode":"10783",
    "sg:province":"Berlin",
    "wof:name":"Joachim Schreiner",
    "wof:placetype":"venue"
},
  "geometry": {"coordinates":[13.364189,52.49765],"type":"Point"}
}