{
  "type": "Feature",
  "properties": {
    "iso:country":"DE",
    "sg:address":"Am Fehrbelliner Tor",
    "sg:city":"Neuruppin",
    "sg:phone":"+49 3391/503808",
    "sg:postcode":"16816",
    "sg:province":"Brandenburg",
    "wof:name":"U. Dau",
    "wof:placetype":"venue"
},
  "geometry": {"coordinates":[12.8087558746,52.9124603271],"type":"Point"}
}