{
  "type": "Feature",
  "properties": {
    "iso:country":"DE",
    "sg:address":"An der Gr\u00e4fte 7",
    "sg:city":"Herten",
    "sg:phone":"+49 209/619590",
    "sg:postcode":"45701",
    "sg:province":"Nordrhein-Westfalen",
    "wof:name":"Art Hoc Design Gmbh",
    "wof:placetype":"venue"
},
  "geometry": {"coordinates":[7.093046,51.598522],"type":"Point"}
}