{
  "type": "Feature",
  "properties": {
    "iso:country":"DE",
    "sg:address":"Waldstr. 44 - 46",
    "sg:city":"Offenbach",
    "sg:postcode":"63065",
    "sg:province":"Hessen",
    "wof:name":"Yimpas Holding Verwaltungs Ag",
    "wof:placetype":"venue"
},
  "geometry": {"coordinates":[8.765583,50.101276],"type":"Point"}
}