{
  "type": "Feature",
  "properties": {
    "iso:country":"DE",
    "sg:address":"Am Hohengeren 1",
    "sg:city":"Stuttgart",
    "sg:phone":"+49 711/4800454",
    "sg:postcode":"70188",
    "sg:province":"Baden-W\u00fcrttemberg",
    "wof:name":"Ulrich Schmidt-hieber Architekt",
    "wof:placetype":"venue"
},
  "geometry": {"coordinates":[9.194275,48.779564],"type":"Point"}
}