{
  "type": "Feature",
  "properties": {
    "iso:country":"DE",
    "sg:address":"Kapellenstr. 48",
    "sg:city":"Wiesbaden",
    "sg:phone":"+49 611/520588",
    "sg:postcode":"65193",
    "sg:province":"Hessen",
    "wof:name":"P. C. Tschira Fotograf Und Fotoatelierbetr.",
    "wof:placetype":"venue"
},
  "geometry": {"coordinates":[8.2384967804,50.0914726257],"type":"Point"}
}