{
  "type": "Feature",
  "properties": {
    "iso:country":"DE",
    "sg:address":"Am Hauptbahnhof 12",
    "sg:city":"Frankfurt",
    "sg:postcode":"60329",
    "sg:province":"Hessen",
    "wof:name":"T. B. D. Sanit\u00e4r- Und Heizungssysteme Gmbh",
    "wof:placetype":"venue"
},
  "geometry": {"coordinates":[8.6645889282,50.1080970764],"type":"Point"}
}