{
  "type": "Feature",
  "properties": {
    "iso:country":"DE",
    "sg:address":"Balthasar-Neumann-Str. 18",
    "sg:city":"Waldkraiburg",
    "sg:phone":"+49 8638/881980",
    "sg:postcode":"84478",
    "sg:province":"Bayern",
    "wof:name":"Harald Mitterstrasser",
    "wof:placetype":"venue"
},
  "geometry": {"coordinates":[12.4148597717,48.1989707947],"type":"Point"}
}