{
  "type": "Feature",
  "properties": {
    "iso:country":"DE",
    "sg:address":"Bahnhofstr. 3",
    "sg:city":"Neunkirchen",
    "sg:phone":"+49 6821/13925",
    "sg:postcode":"66538",
    "sg:province":"Saarland",
    "wof:name":"Affenbaum",
    "wof:placetype":"venue"
},
  "geometry": {"coordinates":[7.176986,49.351841],"type":"Point"}
}