{
  "type": "Feature",
  "properties": {
    "iso:country":"DE",
    "sg:address":"Paul-Gerhardt-Platz 7",
    "sg:city":"R\u00fcdenhausen",
    "sg:phone":"+49 9383/440",
    "sg:postcode":"97355",
    "sg:province":"Bayern",
    "wof:name":"Brauerei Wolf",
    "wof:placetype":"venue"
},
  "geometry": {"coordinates":[10.3431158066,49.764289856],"type":"Point"}
}