{
  "type": "Feature",
  "properties": {
    "iso:country":"DE",
    "sg:address":"Im Barke 4",
    "sg:city":"Lage",
    "sg:phone":"+49 5232/71245",
    "sg:postcode":"32791",
    "sg:province":"Nordrhein-Westfalen",
    "wof:name":"Wilfried Efert",
    "wof:placetype":"venue"
},
  "geometry": {"coordinates":[8.775323,51.959747],"type":"Point"}
}