{
  "type": "Feature",
  "properties": {
    "iso:country":"DE",
    "sg:address":"Eckermannstr 124",
    "sg:city":"Berlin",
    "sg:phone":"+49 30/54398111",
    "sg:postcode":"12683",
    "sg:province":"Berlin",
    "wof:name":"Blo B\u00f6hnstedt Lackier- Und Oberfl\u00e4chentechnik Gmbh",
    "wof:placetype":"venue"
},
  "geometry": {"coordinates":[13.555109024,52.5245742798],"type":"Point"}
}