{
  "type": "Feature",
  "properties": {
    "iso:country":"DE",
    "sg:address":"Schlackenbergstr. 20",
    "sg:city":"St. Ingbert",
    "sg:phone":"+49 6894/91502",
    "sg:postcode":"66386",
    "sg:province":"Saarland",
    "wof:name":"Plato Versicherungs- Verwaltungsgesellschaft Mbh",
    "wof:placetype":"venue"
},
  "geometry": {"coordinates":[7.0964751244,49.2782554626],"type":"Point"}
}