{
  "type": "Feature",
  "properties": {
    "iso:country":"DE",
    "sg:address":"Ernst-Th\u00e4lmann-Str. 101",
    "sg:city":"Beilrode",
    "sg:phone":"+49 3421/713232",
    "sg:postcode":"04886",
    "sg:province":"Sachsen",
    "wof:name":"W. Hofmann & Sohn",
    "wof:placetype":"venue"
},
  "geometry": {"coordinates":[13.068215,51.566898],"type":"Point"}
}