{
  "type": "Feature",
  "properties": {
    "iso:country":"DE",
    "sg:address":"Koloniestr. 110",
    "sg:city":"Duisburg",
    "sg:phone":"+49 203/936970",
    "sg:postcode":"47057",
    "sg:province":"Nordrhein-Westfalen",
    "wof:name":"Walter He\u00dfling",
    "wof:placetype":"venue"
},
  "geometry": {"coordinates":[6.783589,51.421169],"type":"Point"}
}