{
  "type": "Feature",
  "properties": {
    "iso:country":"DE",
    "sg:address":"Herrenlettenstr. 12",
    "sg:city":"Ingolstadt",
    "sg:phone":"+49 841/72252",
    "sg:postcode":"85051",
    "sg:province":"Bayern",
    "wof:name":"Dipl.-ing. J. Kronthaler Gmbh",
    "wof:placetype":"venue"
},
  "geometry": {"coordinates":[11.4006223679,48.731502533],"type":"Point"}
}