{
  "type": "Feature",
  "properties": {
    "iso:country":"DE",
    "sg:address":"Bahnhofstr. 1",
    "sg:city":"Bad Driburg",
    "sg:phone":"+49 5253/9860",
    "sg:postcode":"33014",
    "sg:province":"Nordrhein-Westfalen",
    "wof:name":"Eggeland-klinik",
    "wof:placetype":"venue"
},
  "geometry": {"coordinates":[9.0282640457,51.732711792],"type":"Point"}
}