{
  "type": "Feature",
  "properties": {
    "iso:country":"DE",
    "sg:address":"Badegasse 8219",
    "sg:city":"Baumholder",
    "sg:phone":"+49 6783/5211",
    "sg:postcode":"55774",
    "sg:province":"Rheinland-Pfalz",
    "wof:name":"Anthony's Pizza",
    "wof:placetype":"venue"
},
  "geometry": {"coordinates":[7.3394727707,49.6159706116],"type":"Point"}
}