{
  "type": "Feature",
  "properties": {
    "iso:country":"DE",
    "sg:address":"Godenwind 42",
    "sg:city":"Hamburg",
    "sg:phone":"+49 40/7154445",
    "sg:postcode":"22115",
    "sg:province":"Hamburg",
    "wof:name":"G. Goosmann Jun.",
    "wof:placetype":"venue"
},
  "geometry": {"coordinates":[10.142492,53.525024],"type":"Point"}
}