{
  "type": "Feature",
  "properties": {
    "iso:country":"DE",
    "sg:address":"Hinter den G\u00e4rten 9",
    "sg:city":"Schwabhausen",
    "sg:phone":"+49 36256/21792",
    "sg:postcode":"99869",
    "sg:province":"Th\u00fcringen",
    "wof:name":"Hbk Fliesenverlegungs Gmbh",
    "wof:placetype":"venue"
},
  "geometry": {"coordinates":[10.7292995453,50.8919639587],"type":"Point"}
}