{
  "type": "Feature",
  "properties": {
    "iso:country":"DE",
    "sg:address":"Ebenungstr. 6",
    "sg:city":"Haibach",
    "sg:phone":"+49 6021/68891",
    "sg:postcode":"63808",
    "sg:province":"Bayern",
    "wof:name":"Heinz Blatt",
    "wof:placetype":"venue"
},
  "geometry": {"coordinates":[9.208851,49.960487],"type":"Point"}
}