{
  "type": "Feature",
  "properties": {
    "iso:country":"DE",
    "sg:address":"Alte Reihe 26",
    "sg:city":"Lilienthal",
    "sg:phone":"+49 4298/4718",
    "sg:postcode":"28865",
    "sg:province":"Niedersachsen",
    "wof:name":"Helmut M\u00fcller",
    "wof:placetype":"venue"
},
  "geometry": {"coordinates":[8.907968,53.141422],"type":"Point"}
}