{
  "type": "Feature",
  "properties": {
    "iso:country":"DE",
    "sg:address":"Waldstr. 8",
    "sg:city":"Dudenhofen",
    "sg:postcode":"67373",
    "sg:province":"Rheinland-Pfalz",
    "wof:name":"Roland Behrmann Kg",
    "wof:placetype":"venue"
},
  "geometry": {"coordinates":[8.398393631,49.320400238],"type":"Point"}
}