{
  "type": "Feature",
  "properties": {
    "iso:country":"DE",
    "sg:address":"Unterri\u00df 1",
    "sg:city":"Schliersee",
    "sg:phone":"+49 8026/4768",
    "sg:postcode":"83727",
    "sg:province":"Bayern",
    "wof:name":"Markus Bucher",
    "wof:placetype":"venue"
},
  "geometry": {"coordinates":[11.861131,47.741562],"type":"Point"}
}