{
  "type": "Feature",
  "properties": {
    "iso:country":"DE",
    "sg:address":"Finkenweg 8",
    "sg:city":"Breiteng\u00fc\u00dfbach",
    "sg:phone":"+49 9544/950145",
    "sg:postcode":"96149",
    "sg:province":"Bayern",
    "wof:name":"J\u00fcrgen Krause",
    "wof:placetype":"venue"
},
  "geometry": {"coordinates":[10.8913097382,49.9774589539],"type":"Point"}
}