{
  "type": "Feature",
  "properties": {
    "iso:country":"DE",
    "sg:address":"Gelbenholzener Str. 6",
    "sg:city":"F\u00fcrstenfeldbruck",
    "sg:postcode":"82256",
    "sg:province":"Bayern",
    "wof:name":"Kreisjugendring",
    "wof:placetype":"venue"
},
  "geometry": {"coordinates":[11.2512559891,48.1636962891],"type":"Point"}
}