{
  "type": "Feature",
  "properties": {
    "iso:country":"DE",
    "sg:address":"Mariahilfstr. 24",
    "sg:city":"M\u00fcnchen",
    "sg:postcode":"81541",
    "sg:province":"Bayern",
    "wof:name":"Schubert Gastronomiebetriebs- Und Consulting Gmbh",
    "wof:placetype":"venue"
},
  "geometry": {"coordinates":[11.5823135376,48.125831604],"type":"Point"}
}