{
  "type": "Feature",
  "properties": {
    "iso:country":"DE",
    "sg:address":"Klever Str. 362",
    "sg:city":"Goch",
    "sg:phone":"+49 2823/3761",
    "sg:postcode":"47574",
    "sg:province":"Nordrhein-Westfalen",
    "wof:name":"Hiltrud Schoonhoven Rechtsanw\u00e4ltin",
    "wof:placetype":"venue"
},
  "geometry": {"coordinates":[6.1576499939,51.7103500366],"type":"Point"}
}