{
  "type": "Feature",
  "properties": {
    "iso:country":"DE",
    "sg:address":"Teinacher Str. 34",
    "sg:city":"Ludwigsburg",
    "sg:phone":"+49 7141/22310",
    "sg:postcode":"71634",
    "sg:province":"Baden-W\u00fcrttemberg",
    "wof:name":"Redaktion Dhf Deutsche Hebe- Und F\u00f6rdertechnik",
    "wof:placetype":"venue"
},
  "geometry": {"coordinates":[9.1712942123,48.9035835266],"type":"Point"}
}