{
  "type": "Feature",
  "properties": {
    "iso:country":"DE",
    "sg:address":"Christian-Seltmann-Str. 90",
    "sg:city":"Weiden",
    "sg:phone":"+49 961/670140",
    "sg:postcode":"92637",
    "sg:province":"Bayern",
    "wof:name":"Bek Bodenmeier Gmbh",
    "wof:placetype":"venue"
},
  "geometry": {"coordinates":[12.1417274475,49.6815414429],"type":"Point"}
}