{
  "type": "Feature",
  "properties": {
    "iso:country":"DE",
    "sg:address":"Moosb\u00fcrger Str. 15",
    "sg:city":"Weiden",
    "sg:phone":"+49 961/47200",
    "sg:postcode":"92637",
    "sg:province":"Bayern",
    "wof:name":"E.on Bayern Ag",
    "wof:placetype":"venue"
},
  "geometry": {"coordinates":[12.153601,49.659889],"type":"Point"}
}