{
  "type": "Feature",
  "properties": {
    "iso:country":"DE",
    "sg:address":"Friedrich-R\u00fcckert-Ring 5",
    "sg:city":"Maroldsweisach",
    "sg:phone":"+49 9532/8010",
    "sg:postcode":"96126",
    "sg:province":"Bayern",
    "wof:name":"Wilhelm M\u00e4rz",
    "wof:placetype":"venue"
},
  "geometry": {"coordinates":[10.655912,50.198467],"type":"Point"}
}