{
  "type": "Feature",
  "properties": {
    "iso:country":"DE",
    "sg:city":"Bad Oeynhausen",
    "sg:phone":"+49 5734/1395",
    "sg:postcode":"32549",
    "sg:province":"Nordrhein-Westfalen",
    "wof:name":"Der Hammer",
    "wof:placetype":"venue"
},
  "geometry": {"coordinates":[8.743722,52.253635],"type":"Point"}
}