{
  "type": "Feature",
  "properties": {
    "iso:country":"DE",
    "sg:address":"Hauptstr. 42",
    "sg:city":"Gro\u00dflangheim",
    "sg:phone":"+49 9325/204",
    "sg:postcode":"97320",
    "sg:province":"Bayern",
    "wof:name":"Gemeindeb\u00fccherei",
    "wof:placetype":"venue"
},
  "geometry": {"coordinates":[10.241127,49.754787],"type":"Point"}
}