{
  "type": "Feature",
  "properties": {
    "iso:country":"DE",
    "sg:address":"Theodor-Heuss-Ring 36",
    "sg:city":"K\u00f6ln",
    "sg:phone":"+49 221/9128250",
    "sg:postcode":"50668",
    "sg:province":"Nordrhein-Westfalen",
    "wof:name":"Mil Research Group Gmbh",
    "wof:placetype":"venue"
},
  "geometry": {"coordinates":[6.962864,50.949879],"type":"Point"}
}