{
  "type": "Feature",
  "properties": {
    "iso:country":"DE",
    "sg:address":"Iserstr. 13d",
    "sg:city":"Teltow",
    "sg:phone":"+49 3328/471407",
    "sg:postcode":"14513",
    "sg:province":"Brandenburg",
    "wof:name":"G. Naumann",
    "wof:placetype":"venue"
},
  "geometry": {"coordinates":[13.2444915771,52.395362854],"type":"Point"}
}