{
  "type": "Feature",
  "properties": {
    "iso:country":"DE",
    "sg:address":"Hessenring 34",
    "sg:city":"Eschwege",
    "sg:postcode":"37269",
    "sg:province":"Hessen",
    "wof:name":"K\u00f6nig Gmbh",
    "wof:placetype":"venue"
},
  "geometry": {"coordinates":[10.027368,51.178291],"type":"Point"}
}