{
  "type": "Feature",
  "properties": {
    "iso:country":"DE",
    "sg:address":"Lindentorstr. 18",
    "sg:city":"Memmingen",
    "sg:phone":"+49 8331/87375",
    "sg:postcode":"87700",
    "sg:province":"Bayern",
    "wof:name":"Karl-heinz M\u00fcller",
    "wof:placetype":"venue"
},
  "geometry": {"coordinates":[10.1843061447,47.9833145142],"type":"Point"}
}