{
  "type": "Feature",
  "properties": {
    "iso:country":"DE",
    "sg:address":"Danckwerthstr. 6",
    "sg:city":"Husum",
    "sg:phone":"+49 4841/6991",
    "sg:postcode":"25813",
    "sg:province":"Schleswig-Holstein",
    "wof:name":"Deutsche Bahn Ag",
    "wof:placetype":"venue"
},
  "geometry": {"coordinates":[9.052816391,54.4754104614],"type":"Point"}
}