{
  "type": "Feature",
  "properties": {
    "iso:country":"DE",
    "sg:address":"Stiftsstr. 9",
    "sg:city":"Dietmannsried",
    "sg:phone":"+49 8374/25508",
    "sg:postcode":"87463",
    "sg:province":"Bayern",
    "wof:name":"R. Markmiller",
    "wof:placetype":"venue"
},
  "geometry": {"coordinates":[10.285962,47.813786],"type":"Point"}
}