{
  "type": "Feature",
  "properties": {
    "iso:country":"DE",
    "sg:address":"Ludwigstr. 9",
    "sg:city":"Ingolstadt",
    "sg:phone":"+49 841/17017",
    "sg:postcode":"85049",
    "sg:province":"Bayern",
    "wof:name":"N\u00fc\u00dflein S\u00e4ttler Und Kollegen Rechtsanw\u00e4lte",
    "wof:placetype":"venue"
},
  "geometry": {"coordinates":[11.4253807068,48.7643585205],"type":"Point"}
}