{
  "type": "Feature",
  "properties": {
    "iso:country":"DE",
    "sg:address":"Ohrb\u00fclt 11",
    "sg:city":"Zetel",
    "sg:phone":"+49 4453/4072",
    "sg:postcode":"26340",
    "sg:province":"Niedersachsen",
    "wof:name":"Apotheke Emil Duffhau\u00df Inh. Dr. Rolf Bruns",
    "wof:placetype":"venue"
},
  "geometry": {"coordinates":[7.973429,53.418064],"type":"Point"}
}