{
  "type": "Feature",
  "properties": {
    "iso:country":"DE",
    "sg:address":"Lorettoplatz 26",
    "sg:city":"T\u00fcbingen",
    "sg:phone":"+49 700 9393 7000",
    "sg:postcode":"72072",
    "sg:province":"Baden-W\u00fcrttemberg",
    "wof:name":"Projector Software Gmbh",
    "wof:placetype":"venue"
},
  "geometry": {"coordinates":[9.0639610291,48.5109634399],"type":"Point"}
}