{
  "type": "Feature",
  "properties": {
    "iso:country":"DE",
    "sg:address":"Jahnstr. 40",
    "sg:city":"D\u00fcsseldorf",
    "sg:phone":"+49 211/374242",
    "sg:postcode":"40215",
    "sg:province":"Nordrhein-Westfalen",
    "wof:name":"Schumacher Friedrichstadt",
    "wof:placetype":"venue"
},
  "geometry": {"coordinates":[6.7809419632,51.2148971558],"type":"Point"}
}