{
  "type": "Feature",
  "properties": {
    "iso:country":"DE",
    "sg:address":"Oberer Markt 10",
    "sg:city":"Weiden",
    "sg:phone":"+49 961/46371",
    "sg:postcode":"92637",
    "sg:province":"Bayern",
    "wof:name":"Rosemarie K\u00f6hler",
    "wof:placetype":"venue"
},
  "geometry": {"coordinates":[12.162876,49.675419],"type":"Point"}
}