{
  "type": "Feature",
  "properties": {
    "iso:country":"DE",
    "sg:address":"Igelsdorf 18",
    "sg:city":"Rednitzhembach",
    "sg:phone":"+49 9122/62566",
    "sg:postcode":"91126",
    "sg:province":"Bayern",
    "wof:name":"Thomas Bauer",
    "wof:placetype":"venue"
},
  "geometry": {"coordinates":[11.0499153137,49.3084793091],"type":"Point"}
}