{
  "type": "Feature",
  "properties": {
    "iso:country":"DE",
    "sg:address":"Neue Kirchstr.",
    "sg:city":"Neef",
    "sg:postcode":"56858",
    "sg:province":"Rheinland-Pfalz",
    "wof:name":"Pfarrb\u00fccherei Neef",
    "wof:placetype":"venue"
},
  "geometry": {"coordinates":[7.13835,50.090561],"type":"Point"}
}