{
  "type": "Feature",
  "properties": {
    "iso:country":"DE",
    "sg:address":"Unterh\u00f6lterfelder Str. 36a",
    "sg:city":"Remscheid",
    "sg:phone":"+49 2191/83663",
    "sg:postcode":"42857",
    "sg:province":"Nordrhein-Westfalen",
    "wof:name":"Mile Biljan",
    "wof:placetype":"venue"
},
  "geometry": {"coordinates":[7.159238,51.188747],"type":"Point"}
}