{
  "type": "Feature",
  "properties": {
    "iso:country":"DE",
    "sg:address":"Kurzes Ende 15",
    "sg:city":"M\u00fcnchhausen",
    "sg:phone":"+49 35323/6350",
    "sg:postcode":"03238",
    "sg:province":"Brandenburg",
    "wof:name":"Naturhaus-manufaktur Gmbh",
    "wof:placetype":"venue"
},
  "geometry": {"coordinates":[13.640933,51.666733],"type":"Point"}
}