{
  "type": "Feature",
  "properties": {
    "iso:country":"DE",
    "sg:address":"Friedrichshainstr. 11a",
    "sg:city":"Hamburg",
    "sg:phone":"+49 40",
    "sg:postcode":"22149",
    "sg:province":"Hamburg",
    "wof:name":"Whisky Depot",
    "wof:placetype":"venue"
},
  "geometry": {"coordinates":[10.1513967514,53.5889892578],"type":"Point"}
}