{
  "type": "Feature",
  "properties": {
    "iso:country":"DE",
    "sg:address":"Mainstr. 5",
    "sg:city":"Bayreuth",
    "sg:phone":"+49 921/81055",
    "sg:postcode":"95444",
    "sg:province":"Bayern",
    "wof:name":"R & T Fischer Steuerberatungsges. Mbh",
    "wof:placetype":"venue"
},
  "geometry": {"coordinates":[11.5754041672,49.9478759766],"type":"Point"}
}