{
  "type": "Feature",
  "properties": {
    "iso:country":"DE",
    "sg:address":"Alter Hafen Nord 234",
    "sg:city":"Rostock",
    "sg:postcode":"18069",
    "sg:province":"Mecklenburg-Vorpommern",
    "wof:name":"Ftw Gmbh",
    "wof:placetype":"venue"
},
  "geometry": {"coordinates":[12.084725,54.11097],"type":"Point"}
}