{
  "type": "Feature",
  "properties": {
    "iso:country":"DE",
    "sg:address":"Hauptstr. 47",
    "sg:city":"Karlsdorf-Neuthard",
    "sg:phone":"+49 7251",
    "sg:postcode":"76689",
    "sg:province":"Baden-W\u00fcrttemberg",
    "wof:name":"Edv Vertrieb Gerhard Dutzi",
    "wof:placetype":"venue"
},
  "geometry": {"coordinates":[8.519266,49.126984],"type":"Point"}
}