{
  "type": "Feature",
  "properties": {
    "iso:country":"DE",
    "sg:address":"Marburger Str. 275",
    "sg:city":"Gie\u00dfen",
    "sg:phone":"+49 641/53461",
    "sg:postcode":"35396",
    "sg:province":"Hessen",
    "wof:name":"Heinz Lacroix Innenausbau",
    "wof:placetype":"venue"
},
  "geometry": {"coordinates":[8.69206,50.611992],"type":"Point"}
}