{
  "type": "Feature",
  "properties": {
    "iso:country":"DE",
    "sg:address":"Im Gewerbepark 20",
    "sg:city":"Regensburg",
    "sg:postcode":"93059",
    "sg:province":"Bayern",
    "wof:name":"Antax Steuerberatungsges. Mbh",
    "wof:placetype":"venue"
},
  "geometry": {"coordinates":[12.1258859634,49.0299682617],"type":"Point"}
}