{
  "type": "Feature",
  "properties": {
    "iso:country":"DE",
    "sg:address":"Goltsteinstr. 76 a",
    "sg:city":"K\u00f6ln",
    "sg:phone":"+49 221/387903",
    "sg:postcode":"50968",
    "sg:province":"Nordrhein-Westfalen",
    "wof:name":"Peter Simon Rechtsanwalt",
    "wof:placetype":"venue"
},
  "geometry": {"coordinates":[6.969203949,50.9098129272],"type":"Point"}
}