{
  "type": "Feature",
  "properties": {
    "iso:country":"DE",
    "sg:address":"Springer Str. 2",
    "sg:city":"Hannover",
    "sg:phone":"+49 511/231814",
    "sg:postcode":"30459",
    "sg:province":"Niedersachsen",
    "wof:name":"Verena Arendt",
    "wof:placetype":"venue"
},
  "geometry": {"coordinates":[9.703186,52.341553],"type":"Point"}
}