{
  "type": "Feature",
  "properties": {
    "iso:country":"DE",
    "sg:address":"Moltkestr. 6",
    "sg:city":"Ahlen",
    "sg:phone":"+49 2382/2218",
    "sg:postcode":"59229",
    "sg:province":"Nordrhein-Westfalen",
    "wof:name":"Ev. Pfarramt Pauluskirche",
    "wof:placetype":"venue"
},
  "geometry": {"coordinates":[7.8966169357,51.766204834],"type":"Point"}
}