{
  "type": "Feature",
  "properties": {
    "iso:country":"DE",
    "sg:address":"H\u00e4usern 10",
    "sg:city":"Benediktbeuern",
    "sg:phone":"+49 8857/1453",
    "sg:postcode":"83671",
    "sg:province":"Bayern",
    "wof:name":"Huber & H\u00f6ck",
    "wof:placetype":"venue"
},
  "geometry": {"coordinates":[11.418476,47.705601],"type":"Point"}
}