{
  "type": "Feature",
  "properties": {
    "iso:country":"DE",
    "sg:address":"Paracelsusweg 14",
    "sg:city":"Neustadt",
    "sg:phone":"+49 5032/62029",
    "sg:postcode":"31535",
    "sg:province":"Niedersachsen",
    "wof:name":"Bewab Sicherheits Gmbh",
    "wof:placetype":"venue"
},
  "geometry": {"coordinates":[14.2566509247,51.4497146606],"type":"Point"}
}