{
  "type": "Feature",
  "properties": {
    "iso:country":"DE",
    "sg:address":"Moerser Str. 26 a",
    "sg:city":"Duisburg",
    "sg:phone":"+49 2065/61057",
    "sg:postcode":"47228",
    "sg:province":"Nordrhein-Westfalen",
    "wof:name":"Hans N\u00fchlen Gmbh & Co. Kg",
    "wof:placetype":"venue"
},
  "geometry": {"coordinates":[6.706048,51.415043],"type":"Point"}
}