{
  "type": "Feature",
  "properties": {
    "iso:country":"DE",
    "sg:address":"Deworastr. 1",
    "sg:city":"Trier",
    "sg:phone":"+49 651/975980",
    "sg:postcode":"54290",
    "sg:province":"Rheinland-Pfalz",
    "wof:name":"Weinbaudom\u00e4nen Trier",
    "wof:placetype":"venue"
},
  "geometry": {"coordinates":[6.6477718353,49.7573623657],"type":"Point"}
}