{
  "type": "Feature",
  "properties": {
    "iso:country":"DE",
    "sg:address":"Holzstr. 7",
    "sg:city":"Mainleus",
    "sg:phone":"+49 9229/974240",
    "sg:postcode":"95336",
    "sg:province":"Bayern",
    "wof:name":"Wata Waschen Und Tanken Clean Park-wasch-center E. K.",
    "wof:placetype":"venue"
},
  "geometry": {"coordinates":[11.3857221603,50.1025733948],"type":"Point"}
}