{
  "type": "Feature",
  "properties": {
    "iso:country":"DE",
    "sg:address":"Lange Str. 64",
    "sg:city":"Ottersheim",
    "sg:phone":"+49 6348/8503",
    "sg:postcode":"76879",
    "sg:province":"Rheinland-Pfalz",
    "wof:name":"Annette Morell-w\u00fcnschel Ergotherapiepraxis",
    "wof:placetype":"venue"
},
  "geometry": {"coordinates":[8.174248,49.236568],"type":"Point"}
}