{
  "type": "Feature",
  "properties": {
    "iso:country":"DE",
    "sg:address":"Velken 2",
    "sg:city":"Ruppichteroth",
    "sg:phone":"+49 2295/6086",
    "sg:postcode":"53809",
    "sg:province":"Nordrhein-Westfalen",
    "wof:name":"Hermann Schmidt",
    "wof:placetype":"venue"
},
  "geometry": {"coordinates":[7.5032901764,50.8471794128],"type":"Point"}
}