{
  "type": "Feature",
  "properties": {
    "iso:country":"DE",
    "sg:address":"Auenweg 13",
    "sg:city":"Kubsch\u00fctz",
    "sg:phone":"+49 3591/602609",
    "sg:postcode":"02627",
    "sg:province":"Sachsen",
    "wof:name":"Franz Klinger Gmbh",
    "wof:placetype":"venue"
},
  "geometry": {"coordinates":[14.48298,51.172279],"type":"Point"}
}