{
  "type": "Feature",
  "properties": {
    "iso:country":"DE",
    "sg:address":"Ravenestr. 67",
    "sg:city":"Cochem",
    "sg:phone":"+49 2671/7027",
    "sg:postcode":"56812",
    "sg:province":"Rheinland-Pfalz",
    "wof:name":"Deutsche Bahn Ag",
    "wof:placetype":"venue"
},
  "geometry": {"coordinates":[7.1669330597,50.1526603699],"type":"Point"}
}