{
  "type": "Feature",
  "properties": {
    "iso:country":"DE",
    "sg:address":"Limbergstr. 42",
    "sg:city":"Gifhorn",
    "sg:phone":"+49 5371/4368",
    "sg:postcode":"38518",
    "sg:province":"Niedersachsen",
    "wof:name":"H. M\u00f6hle",
    "wof:placetype":"venue"
},
  "geometry": {"coordinates":[10.54646492,52.4713363647],"type":"Point"}
}