{
  "type": "Feature",
  "properties": {
    "iso:country":"DE",
    "sg:address":"Reyerstr. 44",
    "sg:city":"M\u00f6nchengladbach",
    "sg:phone":"+49 2161/493920",
    "sg:postcode":"41065",
    "sg:province":"Nordrhein-Westfalen",
    "wof:name":"Peter Und Walter Pies",
    "wof:placetype":"venue"
},
  "geometry": {"coordinates":[6.4617319107,51.1957702637],"type":"Point"}
}