{
  "type": "Feature",
  "properties": {
    "iso:country":"DE",
    "sg:address":"Hohemarkstr. 73",
    "sg:city":"Oberursel",
    "sg:phone":"+49 6171/23842",
    "sg:postcode":"61440",
    "sg:province":"Hessen",
    "wof:name":"P. Beck",
    "wof:placetype":"venue"
},
  "geometry": {"coordinates":[8.566984,50.212059],"type":"Point"}
}