{
  "type": "Feature",
  "properties": {
    "iso:country":"DE",
    "sg:address":"Braugasse 12",
    "sg:city":"K\u00f6ln",
    "sg:phone":"+49 2234/48818",
    "sg:postcode":"50859",
    "sg:province":"Nordrhein-Westfalen",
    "wof:name":"Doris R\u00f6hrig",
    "wof:placetype":"venue"
},
  "geometry": {"coordinates":[6.8276219368,50.9447021484],"type":"Point"}
}