{
  "type": "Feature",
  "properties": {
    "iso:country":"DE",
    "sg:address":"Professor-K\u00fcmmell-Str. 8 A",
    "sg:city":"Korbach",
    "sg:phone":"+49 5631/915736",
    "sg:postcode":"34497",
    "sg:province":"Hessen",
    "wof:name":"Pizzeria Avanti",
    "wof:placetype":"venue"
},
  "geometry": {"coordinates":[8.8713541031,51.2732200623],"type":"Point"}
}