{
  "type": "Feature",
  "properties": {
    "iso:country":"DE",
    "sg:address":"Loebstr. 18",
    "sg:city":"Trier",
    "sg:phone":"+49 651/146470",
    "sg:postcode":"54292",
    "sg:province":"Rheinland-Pfalz",
    "wof:name":"Signal Unfallversicherung Ag",
    "wof:placetype":"venue"
},
  "geometry": {"coordinates":[6.68126297,49.7756614685],"type":"Point"}
}