{
  "type": "Feature",
  "properties": {
    "iso:country":"DE",
    "sg:address":"Springhof 2",
    "sg:city":"Bad Laer",
    "sg:phone":"+49 5424/9281",
    "sg:postcode":"49196",
    "sg:province":"Niedersachsen",
    "wof:name":"Wilhelm Tepe Heilpraktiker",
    "wof:placetype":"venue"
},
  "geometry": {"coordinates":[8.0927438736,52.1067466736],"type":"Point"}
}