{
  "type": "Feature",
  "properties": {
    "iso:country":"DE",
    "sg:address":"Sieberweg 11",
    "sg:city":"Seeg",
    "sg:postcode":"87637",
    "sg:province":"Bayern",
    "wof:name":"Hipp Gmbh Wohnbau",
    "wof:placetype":"venue"
},
  "geometry": {"coordinates":[10.6201181412,47.6602897644],"type":"Point"}
}