{
  "type": "Feature",
  "properties": {
    "iso:country":"DE",
    "sg:address":"Kellers Ziegelei 4",
    "sg:city":"Gera",
    "sg:phone":"+49 365/4212262",
    "sg:postcode":"07554",
    "sg:province":"Th\u00fcringen",
    "wof:name":"Gbu Geraer Bau Union Gmbh",
    "wof:placetype":"venue"
},
  "geometry": {"coordinates":[-83.7384643555,43.3833198547],"type":"Point"}
}