{
  "type": "Feature",
  "properties": {
    "iso:country":"DE",
    "sg:address":"Hindenburgstr 40",
    "sg:city":"Ludwigsburg",
    "sg:phone":"+49 7141/94480",
    "sg:postcode":"71638",
    "sg:province":"Baden-W\u00fcrttemberg",
    "wof:name":"Abfallverwertungsgesellschaft Des Landkreises Ludwigsburg Mbh",
    "wof:placetype":"venue"
},
  "geometry": {"coordinates":[9.200754,48.890877],"type":"Point"}
}