{
  "type": "Feature",
  "properties": {
    "iso:country":"DE",
    "sg:address":"Bergstra\u00dfe 13",
    "sg:city":"Billerbeck",
    "sg:phone":"+49 2543/932433",
    "sg:postcode":"48727",
    "sg:province":"Nordrhein-Westfalen",
    "wof:name":"Mensing Abbruch & Tiefbau Gmbh & Co. Kg",
    "wof:placetype":"venue"
},
  "geometry": {"coordinates":[7.3010201454,51.9762382507],"type":"Point"}
}