{
  "type": "Feature",
  "properties": {
    "iso:country":"DE",
    "sg:address":"Genholter Str. 99",
    "sg:city":"Br\u00fcggen",
    "sg:phone":"+49 2163/500544",
    "sg:postcode":"41379",
    "sg:province":"Nordrhein-Westfalen",
    "wof:name":"Leo Meyer Elektroinstallation",
    "wof:placetype":"venue"
},
  "geometry": {"coordinates":[6.197227,51.258766],"type":"Point"}
}