{
  "type": "Feature",
  "properties": {
    "iso:country":"DE",
    "sg:address":"Blumenstr. 7",
    "sg:city":"Hatten",
    "sg:phone":"+49 4481/928001",
    "sg:postcode":"26209",
    "sg:province":"Niedersachsen",
    "wof:name":"Axel Meier",
    "wof:placetype":"venue"
},
  "geometry": {"coordinates":[8.268136,53.056396],"type":"Point"}
}