{
  "type": "Feature",
  "properties": {
    "iso:country":"DE",
    "sg:address":"Lindenweg 23",
    "sg:city":"Seelow",
    "sg:phone":"+49 3346/80621",
    "sg:postcode":"15306",
    "sg:province":"Brandenburg",
    "wof:name":"Norbert Kositz Ingenieur",
    "wof:placetype":"venue"
},
  "geometry": {"coordinates":[14.3814086914,52.5389862061],"type":"Point"}
}