{
  "type": "Feature",
  "properties": {
    "iso:country":"DE",
    "sg:address":"Teichrohrweg 18 a",
    "sg:city":"Berlin",
    "sg:phone":"+49 30/67897170",
    "sg:postcode":"12524",
    "sg:province":"Berlin",
    "wof:name":"K. Im Kanada Import Gmbh",
    "wof:placetype":"venue"
},
  "geometry": {"coordinates":[13.5267744064,52.4205131531],"type":"Point"}
}