{
  "type": "Feature",
  "properties": {
    "iso:country":"DE",
    "sg:address":"Ostlandstr. 28",
    "sg:city":"Schwanewede",
    "sg:phone":"+49 4209/5676",
    "sg:postcode":"28790",
    "sg:province":"Niedersachsen",
    "wof:name":"Diedrich Brau",
    "wof:placetype":"venue"
},
  "geometry": {"coordinates":[8.589383,53.226345],"type":"Point"}
}