{
  "type": "Feature",
  "properties": {
    "iso:country":"DE",
    "sg:address":"Schl\u00fcterstr. 38",
    "sg:city":"Berlin",
    "sg:phone":"+49 30/8817770",
    "sg:postcode":"10629",
    "sg:province":"Berlin",
    "wof:name":"Pelzhaus Schrank",
    "wof:placetype":"venue"
},
  "geometry": {"coordinates":[13.31671,52.502182],"type":"Point"}
}