{
  "type": "Feature",
  "properties": {
    "iso:country":"DE",
    "sg:address":"Donauweg 1",
    "sg:city":"Hamburg",
    "sg:phone":"+49 40/6401031",
    "sg:postcode":"22393",
    "sg:province":"Hamburg",
    "wof:name":"Eberhard B\u00fcker Gmbh",
    "wof:placetype":"venue"
},
  "geometry": {"coordinates":[10.1069364548,53.6388511658],"type":"Point"}
}