{
  "type": "Feature",
  "properties": {
    "iso:country":"DE",
    "sg:address":"Remigiusstr. 22",
    "sg:city":"Wassenach",
    "sg:phone":"+49 2636/2368",
    "sg:postcode":"56653",
    "sg:province":"Rheinland-Pfalz",
    "wof:name":"Josef Renn",
    "wof:placetype":"venue"
},
  "geometry": {"coordinates":[7.283351,50.433643],"type":"Point"}
}