{
  "type": "Feature",
  "properties": {
    "iso:country":"DE",
    "sg:address":"K\u00fcnkelstr. 59",
    "sg:city":"M\u00f6nchengladbach",
    "sg:phone":"+49 2161/16557",
    "sg:postcode":"41063",
    "sg:province":"Nordrhein-Westfalen",
    "wof:name":"Josef Jan\u00dfen Kg",
    "wof:placetype":"venue"
},
  "geometry": {"coordinates":[6.452032,51.210815],"type":"Point"}
}