{
  "type": "Feature",
  "properties": {
    "iso:country":"DE",
    "sg:address":"Bauernstr. 2",
    "sg:city":"Rehlingen",
    "sg:phone":"+49 4132/8432",
    "sg:postcode":"21385",
    "sg:province":"Niedersachsen",
    "wof:name":"Bernd Weidmann Immobilienmakler",
    "wof:placetype":"venue"
},
  "geometry": {"coordinates":[10.2195529938,53.1038093567],"type":"Point"}
}