{
  "type": "Feature",
  "properties": {
    "iso:country":"DE",
    "sg:address":"Heidkoppel",
    "sg:city":"K\u00f6lln-Reisiek",
    "sg:phone":"+49 4121/74103",
    "sg:postcode":"25337",
    "sg:province":"Schleswig-Holstein",
    "wof:name":"Badv Datenverarbeitung Computer-hard- Und Software",
    "wof:placetype":"venue"
},
  "geometry": {"coordinates":[9.6861753464,53.7570343018],"type":"Point"}
}