{
  "type": "Feature",
  "properties": {
    "iso:country":"DE",
    "sg:address":"Schulstr. 1",
    "sg:city":"Recklinghausen",
    "sg:phone":"+49 2361/81381",
    "sg:postcode":"45665",
    "sg:province":"Nordrhein-Westfalen",
    "wof:name":"J. Sch\u00e4per",
    "wof:placetype":"venue"
},
  "geometry": {"coordinates":[7.260239,51.611542],"type":"Point"}
}