{
  "type": "Feature",
  "properties": {
    "iso:country":"DE",
    "sg:address":"Harderweg 2",
    "sg:city":"Hamburg",
    "sg:phone":"+49 40/804018",
    "sg:postcode":"22549",
    "sg:province":"Hamburg",
    "wof:name":"Lothar Jacobi Elektromechan. Werkst\u00e4tte",
    "wof:placetype":"venue"
},
  "geometry": {"coordinates":[9.854739,53.572567],"type":"Point"}
}