{
  "type": "Feature",
  "properties": {
    "iso:country":"DE",
    "sg:address":"Friedrich-Ebert-Str. 305",
    "sg:city":"Duisburg",
    "sg:phone":"+49 203/468577",
    "sg:postcode":"47139",
    "sg:province":"Nordrhein-Westfalen",
    "wof:name":"H. Eberhard",
    "wof:placetype":"venue"
},
  "geometry": {"coordinates":[6.7337360382,51.4770507812],"type":"Point"}
}