{
  "type": "Feature",
  "properties": {
    "iso:country":"DE",
    "sg:address":"Kalterer Str. 31",
    "sg:city":"Heppenheim",
    "sg:postcode":"64646",
    "sg:province":"Hessen",
    "wof:name":"Amm Agentur F\u00fcr Media Und Mittlung",
    "wof:placetype":"venue"
},
  "geometry": {"coordinates":[8.6312417984,49.6481323242],"type":"Point"}
}