{
  "type": "Feature",
  "properties": {
    "iso:country":"DE",
    "sg:address":"K\u00f6nigstr. 35",
    "sg:city":"Ehningen",
    "sg:phone":"+49 7034/93160",
    "sg:postcode":"71139",
    "sg:province":"Baden-W\u00fcrttemberg",
    "wof:name":"B\u00f6ttinger Versicherungs- Makler Gmbh",
    "wof:placetype":"venue"
},
  "geometry": {"coordinates":[8.9419574738,48.6595802307],"type":"Point"}
}