{
  "type": "Feature",
  "properties": {
    "iso:country":"DE",
    "sg:address":"Marktplatz 8",
    "sg:city":"Braunsbach",
    "sg:phone":"+49 7906/8664",
    "sg:postcode":"74542",
    "sg:province":"Baden-W\u00fcrttemberg",
    "wof:name":"Werner Kretzschmar",
    "wof:placetype":"venue"
},
  "geometry": {"coordinates":[9.791758,49.19931],"type":"Point"}
}