{
  "type": "Feature",
  "properties": {
    "iso:country":"DE",
    "sg:address":"Wilhelm-Str. 34",
    "sg:city":"Lampertheim",
    "sg:phone":"+49 4962/064253",
    "sg:postcode":"68623",
    "sg:province":"Hessen",
    "wof:name":"Raiffeisenbank Ried Eg",
    "wof:placetype":"venue"
},
  "geometry": {"coordinates":[8.469982,49.594074],"type":"Point"}
}