{
  "type": "Feature",
  "properties": {
    "iso:country":"DE",
    "sg:address":"Eduard-Pfeiffer-Str. 27",
    "sg:city":"Stuttgart",
    "sg:phone":"+49 711/2265063",
    "sg:postcode":"70192",
    "sg:province":"Baden-W\u00fcrttemberg",
    "wof:name":"Scherzer & Bengs Gmbh",
    "wof:placetype":"venue"
},
  "geometry": {"coordinates":[9.1658172607,48.7892074585],"type":"Point"}
}