{
  "type": "Feature",
  "properties": {
    "iso:country":"DE",
    "sg:address":"Leberberg 10",
    "sg:city":"Wiesbaden",
    "sg:phone":"+49 611/950400",
    "sg:postcode":"65193",
    "sg:province":"Hessen",
    "wof:name":"Ruske & P\u00fchretmaier Edutainment Gmbh",
    "wof:placetype":"venue"
},
  "geometry": {"coordinates":[8.2515182495,50.0865478516],"type":"Point"}
}