{
  "type": "Feature",
  "properties": {
    "iso:country":"DE",
    "sg:address":"Vossweg 27",
    "sg:city":"L\u00fcdinghausen",
    "sg:phone":"+49 2591/1200",
    "sg:postcode":"59348",
    "sg:province":"Nordrhein-Westfalen",
    "wof:name":"Gesine Welters Rechtsanw\u00e4ltin",
    "wof:placetype":"venue"
},
  "geometry": {"coordinates":[7.4470801353,51.7639007568],"type":"Point"}
}