{
  "type": "Feature",
  "properties": {
    "iso:country":"DE",
    "sg:address":"Am Markt 1",
    "sg:city":"Bremen",
    "sg:phone":"+49 421/339620",
    "sg:postcode":"28195",
    "sg:province":"Bremen",
    "wof:name":"E. H. Harms Automobile- Logistics Beteiligungs-gmbh",
    "wof:placetype":"venue"
},
  "geometry": {"coordinates":[8.807597,53.076023],"type":"Point"}
}