{
  "type": "Feature",
  "properties": {
    "iso:country":"DE",
    "sg:address":"Mittelweg 82",
    "sg:city":"Hamburg",
    "sg:postcode":"20149",
    "sg:province":"Hamburg",
    "wof:name":"Ari Consulting Gmbh",
    "wof:placetype":"venue"
},
  "geometry": {"coordinates":[9.9940824509,53.5795936584],"type":"Point"}
}