{
  "type": "Feature",
  "properties": {
    "iso:country":"DE",
    "sg:address":"Unterm Brink 3",
    "sg:city":"Wulften",
    "sg:phone":"+49 5556/4624",
    "sg:postcode":"37199",
    "sg:province":"Niedersachsen",
    "wof:name":"Gustav Thiele",
    "wof:placetype":"venue"
},
  "geometry": {"coordinates":[10.174206,51.662525],"type":"Point"}
}