{
  "type": "Feature",
  "properties": {
    "iso:country":"DE",
    "sg:address":"K\u00f6nigstr. 53",
    "sg:city":"Bad Bergzabern",
    "sg:phone":"+49 6343/1089",
    "sg:postcode":"76887",
    "sg:province":"Rheinland-Pfalz",
    "wof:name":"August Klein Eisenwaren",
    "wof:placetype":"venue"
},
  "geometry": {"coordinates":[7.9982,49.102528],"type":"Point"}
}