{
  "type": "Feature",
  "properties": {
    "iso:country":"DE",
    "sg:address":"Hoher Berg 17",
    "sg:city":"Steinbach-Hallenberg",
    "sg:phone":"+49 36847/48367",
    "sg:postcode":"98587",
    "sg:province":"Th\u00fcringen",
    "wof:name":"Fritz Bickel",
    "wof:placetype":"venue"
},
  "geometry": {"coordinates":[10.5724201202,50.7125549316],"type":"Point"}
}