{
  "type": "Feature",
  "properties": {
    "iso:country":"DE",
    "sg:address":"Mittlere Eckenbergstr. 11",
    "sg:city":"Adelsheim",
    "sg:phone":"+49 6291/7874",
    "sg:postcode":"74740",
    "sg:province":"Baden-W\u00fcrttemberg",
    "wof:name":"Wilfried Meyer Ingenieur",
    "wof:placetype":"venue"
},
  "geometry": {"coordinates":[9.3945198059,49.4072303772],"type":"Point"}
}