{
  "type": "Feature",
  "properties": {
    "iso:country":"DE",
    "sg:address":"Industriering Ost 72",
    "sg:city":"Kempen",
    "sg:phone":"+49 2152/510070",
    "sg:postcode":"47906",
    "sg:province":"Nordrhein-Westfalen",
    "wof:name":"Plaid Deutschland Gmbh",
    "wof:placetype":"venue"
},
  "geometry": {"coordinates":[6.433783,51.372726],"type":"Point"}
}