{
  "type": "Feature",
  "properties": {
    "iso:country":"DE",
    "sg:address":"Neubertstr. 36",
    "sg:city":"Hamburg",
    "sg:phone":"+49 40/2530570",
    "sg:postcode":"22087",
    "sg:province":"Hamburg",
    "wof:name":"Gerhard Loy & Partner Gmbh",
    "wof:placetype":"venue"
},
  "geometry": {"coordinates":[10.0298366547,53.5629653931],"type":"Point"}
}