{
  "type": "Feature",
  "properties": {
    "iso:country":"DE",
    "sg:address":"Kirchstr. 12",
    "sg:city":"Emden",
    "sg:phone":"+49 4921/32233",
    "sg:postcode":"26721",
    "sg:province":"Niedersachsen",
    "wof:name":"Floraly",
    "wof:placetype":"venue"
},
  "geometry": {"coordinates":[7.202565,53.366516],"type":"Point"}
}