{
  "type": "Feature",
  "properties": {
    "iso:country":"DE",
    "sg:address":"Bollwerk 9",
    "sg:city":"Kamen",
    "sg:phone":"+49 2307/912210",
    "sg:postcode":"59174",
    "sg:province":"Nordrhein-Westfalen",
    "wof:name":"Beratungsstelle F\u00fcr Jugendliche Zuwanderer",
    "wof:placetype":"venue"
},
  "geometry": {"coordinates":[7.659559,51.590797],"type":"Point"}
}