{
  "type": "Feature",
  "properties": {
    "iso:country":"DE",
    "sg:address":"Havelchaussee 66",
    "sg:city":"Berlin",
    "sg:phone":"+49 30/3040595",
    "sg:postcode":"14193",
    "sg:province":"Berlin",
    "wof:name":"Cafe Und Restaurant Waldhaus",
    "wof:placetype":"venue"
},
  "geometry": {"coordinates":[13.197769165,52.4793663025],"type":"Point"}
}