{
  "type": "Feature",
  "properties": {
    "iso:country":"DE",
    "sg:address":"Clara-Zetkin-Str. 10",
    "sg:city":"Neuhaus",
    "sg:phone":"+49 3679/722770",
    "sg:postcode":"98724",
    "sg:province":"Th\u00fcringen",
    "wof:name":"E. Greiner-adam",
    "wof:placetype":"venue"
},
  "geometry": {"coordinates":[11.149676,50.503365],"type":"Point"}
}