{
  "type": "Feature",
  "properties": {
    "iso:country":"DE",
    "sg:address":"Sternenburgstr. 51",
    "sg:city":"Bonn",
    "sg:phone":"+49 228/219273",
    "sg:postcode":"53115",
    "sg:province":"Nordrhein-Westfalen",
    "wof:name":"Restaurant Zur Sternenburg",
    "wof:placetype":"venue"
},
  "geometry": {"coordinates":[7.0929870605,50.7203674316],"type":"Point"}
}