{
  "type": "Feature",
  "properties": {
    "iso:country":"DE",
    "sg:address":"Altostr. 32",
    "sg:city":"M\u00fcnchen",
    "sg:phone":"+49 89/8632090",
    "sg:postcode":"81245",
    "sg:province":"Bayern",
    "wof:name":"Ernst Preis Gmbh & Co. Kg",
    "wof:placetype":"venue"
},
  "geometry": {"coordinates":[11.4153900146,48.1594696045],"type":"Point"}
}