{
  "type": "Feature",
  "properties": {
    "iso:country":"DE",
    "sg:address":"Am Rauschenbrunnen 20",
    "sg:city":"Pirmasens",
    "sg:phone":"+49 6331/70662",
    "sg:postcode":"66953",
    "sg:province":"Rheinland-Pfalz",
    "wof:name":"F. Wagner Gmbh",
    "wof:placetype":"venue"
},
  "geometry": {"coordinates":[7.62274,49.198399],"type":"Point"}
}