{
  "type": "Feature",
  "properties": {
    "iso:country":"DE",
    "sg:address":"Bersenbr\u00fccker Str. 103",
    "sg:city":"Alfhausen",
    "sg:phone":"+49 5464/1626",
    "sg:postcode":"49594",
    "sg:province":"Niedersachsen",
    "wof:name":"Hans Gerwin Gmbh & Co. Kg",
    "wof:placetype":"venue"
},
  "geometry": {"coordinates":[7.952323,52.504688],"type":"Point"}
}