{
  "type": "Feature",
  "properties": {
    "iso:country":"DE",
    "sg:address":"Stendaler Str. 4",
    "sg:city":"Berlin",
    "sg:phone":"+49 30/3966043",
    "sg:postcode":"10559",
    "sg:province":"Berlin",
    "wof:name":"Lothar Br\u00fcning",
    "wof:placetype":"venue"
},
  "geometry": {"coordinates":[13.349235,52.53289],"type":"Point"}
}