{
  "type": "Feature",
  "properties": {
    "iso:country":"DE",
    "sg:address":"Hirschstr. 24-26",
    "sg:city":"Stutensee - Fr.",
    "sg:phone":"+49 7249",
    "sg:postcode":"76297",
    "sg:province":"Baden-W\u00fcrttemberg",
    "wof:name":"Party-saal",
    "wof:placetype":"venue"
},
  "geometry": {"coordinates":[8.481949,49.10614],"type":"Point"}
}