{
  "type": "Feature",
  "properties": {
    "iso:country":"DE",
    "sg:address":"Gro\u00dfe Str. 58",
    "sg:city":"Osnabr\u00fcck",
    "sg:phone":"+49 541/24917",
    "sg:postcode":"49074",
    "sg:province":"Niedersachsen",
    "wof:name":"Nordsee Gmbh",
    "wof:placetype":"venue"
},
  "geometry": {"coordinates":[8.0455522537,52.2748985291],"type":"Point"}
}