{
  "type": "Feature",
  "properties": {
    "iso:country":"DE",
    "sg:address":"Kiefernstr. 20",
    "sg:city":"Langenhagen",
    "sg:phone":"+49 511/7850320",
    "sg:postcode":"30855",
    "sg:province":"Niedersachsen",
    "wof:name":"Df Folientechnik Inh. Regina M\u00f6ller E. K.",
    "wof:placetype":"venue"
},
  "geometry": {"coordinates":[9.676132,52.433468],"type":"Point"}
}