{
  "type": "Feature",
  "properties": {
    "iso:country":"DE",
    "sg:address":"Eisenbahnstr. 14",
    "sg:city":"Aue",
    "sg:phone":"+49 3771/26196",
    "sg:postcode":"08280",
    "sg:province":"Sachsen",
    "wof:name":"Heike Schlosser",
    "wof:placetype":"venue"
},
  "geometry": {"coordinates":[12.7023220062,50.583732605],"type":"Point"}
}