{
  "type": "Feature",
  "properties": {
    "iso:country":"DE",
    "sg:address":"Obere W\u00f6rthstr. 5",
    "sg:city":"N\u00fcrnberg",
    "sg:phone":"+49 911/222384",
    "sg:postcode":"90403",
    "sg:province":"Bayern",
    "wof:name":"G. Erlinger Antiquit\u00e4ten",
    "wof:placetype":"venue"
},
  "geometry": {"coordinates":[11.073776,49.452213],"type":"Point"}
}