{
  "type": "Feature",
  "properties": {
    "iso:country":"DE",
    "sg:address":"Sonnenstr. 9",
    "sg:city":"Biberach",
    "sg:phone":"+49 7351/22412",
    "sg:postcode":"88400",
    "sg:province":"Baden-W\u00fcrttemberg",
    "wof:name":"Peter H\u00f6rmle",
    "wof:placetype":"venue"
},
  "geometry": {"coordinates":[9.807934761,48.0755310059],"type":"Point"}
}