{
  "type": "Feature",
  "properties": {
    "iso:country":"DE",
    "sg:address":"Liebfrauenstrasse 1",
    "sg:city":"Mainz",
    "sg:phone":"+49 6131",
    "sg:postcode":"55116",
    "sg:province":"Rheinland-Pfalz",
    "wof:name":"Wolfgang Jakob Metzner Gmbh",
    "wof:placetype":"venue"
},
  "geometry": {"coordinates":[8.275535,49.998856],"type":"Point"}
}