{
  "type": "Feature",
  "properties": {
    "iso:country":"DE",
    "sg:address":"Brunnenstr. 18 b",
    "sg:city":"Marxzell",
    "sg:phone":"+49 7248/932119",
    "sg:postcode":"76359",
    "sg:province":"Baden-W\u00fcrttemberg",
    "wof:name":"E. M\u00f6ller",
    "wof:placetype":"venue"
},
  "geometry": {"coordinates":[8.438874,48.868786],"type":"Point"}
}