{
  "type": "Feature",
  "properties": {
    "iso:country":"DE",
    "sg:address":"Poststr. 7",
    "sg:city":"Neuerburg",
    "sg:phone":"+49 6564/96990",
    "sg:postcode":"54673",
    "sg:province":"Rheinland-Pfalz",
    "wof:name":"E. Roth Steuerberater",
    "wof:placetype":"venue"
},
  "geometry": {"coordinates":[6.2917981148,50.0137443542],"type":"Point"}
}