{
  "type": "Feature",
  "properties": {
    "iso:country":"DE",
    "sg:address":"Sommerfelder Weg 76",
    "sg:city":"Leipzig",
    "sg:postcode":"04329",
    "sg:province":"Sachsen",
    "wof:name":"Dr. Med. Adelheid J\u00e4ger",
    "wof:placetype":"venue"
},
  "geometry": {"coordinates":[12.479656,51.34745],"type":"Point"}
}