{
  "type": "Feature",
  "properties": {
    "iso:country":"DE",
    "sg:address":"Stra\u00dfe der MTS 1",
    "sg:city":"Braunsdorf",
    "sg:phone":"+49 35203/3910",
    "sg:postcode":"01737",
    "sg:province":"Sachsen",
    "wof:name":"Schneider Fahrkomfort Gmbh",
    "wof:placetype":"venue"
},
  "geometry": {"coordinates":[13.571126,51.016224],"type":"Point"}
}