{
  "type": "Feature",
  "properties": {
    "iso:country":"DE",
    "sg:address":"Langener Str. 5",
    "sg:city":"Dreieich",
    "sg:phone":"+49 6103/87108",
    "sg:postcode":"63303",
    "sg:province":"Hessen",
    "wof:name":"Johann Unger Rechtsanwalt",
    "wof:placetype":"venue"
},
  "geometry": {"coordinates":[8.7329549789,49.9977378845],"type":"Point"}
}