{
  "type": "Feature",
  "properties": {
    "iso:country":"DE",
    "sg:address":"Uerdinger Str. 224",
    "sg:city":"Krefeld",
    "sg:phone":"+49 2151/590171",
    "sg:postcode":"47800",
    "sg:province":"Nordrhein-Westfalen",
    "wof:name":"Paddy Murphys Irish Pub",
    "wof:placetype":"venue"
},
  "geometry": {"coordinates":[6.5866560936,51.3386039734],"type":"Point"}
}