{
  "type": "Feature",
  "properties": {
    "iso:country":"DE",
    "sg:address":"Sagbergstr. 7",
    "sg:city":"Frasdorf",
    "sg:phone":"+49 8052/2250",
    "sg:postcode":"83112",
    "sg:province":"Bayern",
    "wof:name":"Maximilian Butscher Architekt",
    "wof:placetype":"venue"
},
  "geometry": {"coordinates":[12.288212,47.801991],"type":"Point"}
}