{
  "type": "Feature",
  "properties": {
    "iso:country":"DE",
    "sg:address":"Altpoderschauer Weg 2",
    "sg:city":"Meuselwitz",
    "sg:phone":"+49 3448/44130",
    "sg:postcode":"04610",
    "sg:province":"Th\u00fcringen",
    "wof:name":"Schirach Gmbh",
    "wof:placetype":"venue"
},
  "geometry": {"coordinates":[12.3008537292,51.0357704163],"type":"Point"}
}