{
  "type": "Feature",
  "properties": {
    "iso:country":"DE",
    "sg:address":"B\u00fcddenstedter Str. 12",
    "sg:city":"Sch\u00f6ningen",
    "sg:phone":"+49 5352/1853",
    "sg:postcode":"38364",
    "sg:province":"Niedersachsen",
    "wof:name":"Hans-joachim Thiede Kg",
    "wof:placetype":"venue"
},
  "geometry": {"coordinates":[10.9748630524,52.1413993835],"type":"Point"}
}