{
  "type": "Feature",
  "properties": {
    "iso:country":"DE",
    "sg:address":"Gro\u00df Breesener Str. 79",
    "sg:city":"Guben",
    "sg:phone":"+49 3561/2937",
    "sg:postcode":"03172",
    "sg:province":"Brandenburg",
    "wof:name":"Josef Brandl",
    "wof:placetype":"venue"
},
  "geometry": {"coordinates":[14.701417,51.984314],"type":"Point"}
}