{
  "type": "Feature",
  "properties": {
    "iso:country":"DE",
    "sg:address":"Kapellstr. 21",
    "sg:city":"Donauw\u00f6rth",
    "sg:phone":"+49 906/3432",
    "sg:postcode":"86609",
    "sg:province":"Bayern",
    "wof:name":"Johann Schenkenhofer",
    "wof:placetype":"venue"
},
  "geometry": {"coordinates":[10.7827100754,48.71667099],"type":"Point"}
}