{
  "type": "Feature",
  "properties": {
    "iso:country":"DE",
    "sg:address":"Am Michaelshof 4 a",
    "sg:city":"Bonn",
    "sg:phone":"+49 228/957530",
    "sg:postcode":"53177",
    "sg:province":"Nordrhein-Westfalen",
    "wof:name":"Kersting Damenmoden",
    "wof:placetype":"venue"
},
  "geometry": {"coordinates":[7.152557,50.683735],"type":"Point"}
}