{
  "type": "Feature",
  "properties": {
    "iso:country":"DE",
    "sg:address":"Ferrariweg 37",
    "sg:city":"Paderborn",
    "sg:phone":"+49 5251/33408",
    "sg:postcode":"33102",
    "sg:province":"Nordrhein-Westfalen",
    "wof:name":"M. Kraus Architekt",
    "wof:placetype":"venue"
},
  "geometry": {"coordinates":[8.745396,51.732655],"type":"Point"}
}