{
  "type": "Feature",
  "properties": {
    "iso:country":"DE",
    "sg:address":"Leonberger Str. 32",
    "sg:city":"Ditzingen",
    "sg:phone":"+49 7156/32422",
    "sg:postcode":"71254",
    "sg:province":"Baden-W\u00fcrttemberg",
    "wof:name":"Karl Schall",
    "wof:placetype":"venue"
},
  "geometry": {"coordinates":[9.064218,48.824883],"type":"Point"}
}