{
  "type": "Feature",
  "properties": {
    "iso:country":"DE",
    "sg:address":"Oststr. 41",
    "sg:city":"Beckum",
    "sg:phone":"+49 2525/2216",
    "sg:postcode":"59269",
    "sg:province":"Nordrhein-Westfalen",
    "wof:name":"Beckumer Wohnungsges. Mbh",
    "wof:placetype":"venue"
},
  "geometry": {"coordinates":[8.0456542969,51.7544288635],"type":"Point"}
}