{
  "type": "Feature",
  "properties": {
    "iso:country":"DE",
    "sg:address":"Schaftrift 55",
    "sg:city":"Twist",
    "sg:phone":"+49 5936/2304",
    "sg:postcode":"49767",
    "sg:province":"Niedersachsen",
    "wof:name":"G. Gorny",
    "wof:placetype":"venue"
},
  "geometry": {"coordinates":[7.0693678856,52.6405677795],"type":"Point"}
}