{
  "type": "Feature",
  "properties": {
    "iso:country":"DE",
    "sg:address":"Stralsunder Str. 19",
    "sg:city":"Altentreptow",
    "sg:phone":"+49 3961/214480",
    "sg:postcode":"17087",
    "sg:province":"Mecklenburg-Vorpommern",
    "wof:name":"K.-d. Lindner",
    "wof:placetype":"venue"
},
  "geometry": {"coordinates":[13.248782,53.700165],"type":"Point"}
}