{
  "type": "Feature",
  "properties": {
    "iso:country":"DE",
    "sg:address":"Brunnenweg 22",
    "sg:city":"Ilvesheim",
    "sg:phone":"+49 621/494596",
    "sg:postcode":"68549",
    "sg:province":"Baden-W\u00fcrttemberg",
    "wof:name":"Hans-j\u00fcrgen Werner Augenoptiker",
    "wof:placetype":"venue"
},
  "geometry": {"coordinates":[8.5665893555,49.4761505127],"type":"Point"}
}