{
  "type": "Feature",
  "properties": {
    "iso:country":"DE",
    "sg:address":"Mittelweg 1",
    "sg:city":"Otterndorf",
    "sg:postcode":"21762",
    "sg:province":"Niedersachsen",
    "wof:name":"Medem-g\u00e4stehaus",
    "wof:placetype":"venue"
},
  "geometry": {"coordinates":[8.8929233551,53.8117637634],"type":"Point"}
}