{
  "type": "Feature",
  "properties": {
    "iso:country":"DE",
    "sg:address":"Kattowitzer Zeile 1",
    "sg:city":"Mannheim",
    "sg:phone":"+49 621/785938",
    "sg:postcode":"68307",
    "sg:province":"Baden-W\u00fcrttemberg",
    "wof:name":"Lorenz Scheerer",
    "wof:placetype":"venue"
},
  "geometry": {"coordinates":[8.472521,49.536907],"type":"Point"}
}