{
  "type": "Feature",
  "properties": {
    "iso:country":"DE",
    "sg:address":"Westenhellweg 86 - 88",
    "sg:city":"Dortmund",
    "sg:phone":"+49 231/18461",
    "sg:postcode":"44137",
    "sg:province":"Nordrhein-Westfalen",
    "wof:name":"Redaktion Vab Aktuell Gebr\u00fcder Lesing",
    "wof:placetype":"venue"
},
  "geometry": {"coordinates":[7.4602999687,51.5141334534],"type":"Point"}
}