{
  "type": "Feature",
  "properties": {
    "iso:country":"DE",
    "sg:address":"Logabirumer Str. 10A",
    "sg:city":"Leer",
    "sg:phone":"+49 180 5 237776",
    "sg:postcode":"26789",
    "sg:province":"Niedersachsen",
    "wof:name":"Bedarf F\u00fcr Das Fussballtraining",
    "wof:placetype":"venue"
},
  "geometry": {"coordinates":[7.510408,53.243576],"type":"Point"}
}