{
  "type": "Feature",
  "properties": {
    "iso:country":"DE",
    "sg:address":"Bad 14",
    "sg:city":"Recke",
    "sg:phone":"+49 5453/8280",
    "sg:postcode":"49509",
    "sg:province":"Nordrhein-Westfalen",
    "wof:name":"Landgasthaus Bad Steinbeck",
    "wof:placetype":"venue"
},
  "geometry": {"coordinates":[7.6727352142,52.3534584045],"type":"Point"}
}