{
  "type": "Feature",
  "properties": {
    "iso:country":"DE",
    "sg:address":"Schilbach 30 a",
    "sg:city":"Tanna",
    "sg:phone":"+49 36646/21433",
    "sg:postcode":"07922",
    "sg:province":"Th\u00fcringen",
    "wof:name":"B. Fuhrmann",
    "wof:placetype":"venue"
},
  "geometry": {"coordinates":[11.821037,50.488422],"type":"Point"}
}