{
  "type": "Feature",
  "properties": {
    "iso:country":"DE",
    "sg:address":"Vockenhauser Str. 15",
    "sg:city":"Villingen-Schwenningen",
    "sg:phone":"+49 7721/56001",
    "sg:postcode":"78048",
    "sg:province":"Baden-W\u00fcrttemberg",
    "wof:name":"E-center",
    "wof:placetype":"venue"
},
  "geometry": {"coordinates":[8.4568767548,48.0707359314],"type":"Point"}
}