{
  "type": "Feature",
  "properties": {
    "iso:country":"DE",
    "sg:address":"Schlo\u00dfgasse 51",
    "sg:city":"Grenzach-Wyhlen",
    "sg:phone":"+49 7624/1077",
    "sg:postcode":"79639",
    "sg:province":"Baden-W\u00fcrttemberg",
    "wof:name":"Theo Dietrich",
    "wof:placetype":"venue"
},
  "geometry": {"coordinates":[7.651627,47.555168],"type":"Point"}
}