{
  "type": "Feature",
  "properties": {
    "iso:country":"DE",
    "sg:address":"Am Landpflegeheim 64",
    "sg:city":"Hamburg",
    "sg:phone":"+49 40/8003404",
    "sg:postcode":"22549",
    "sg:province":"Hamburg",
    "wof:name":"A. Und E. Nowak",
    "wof:placetype":"venue"
},
  "geometry": {"coordinates":[9.859112,53.576488],"type":"Point"}
}