{
  "type": "Feature",
  "properties": {
    "iso:country":"DE",
    "sg:address":"Sch\u00f6ner-Berg-Weg 34",
    "sg:city":"Ulm",
    "sg:phone":"+49 731/262773",
    "sg:postcode":"89075",
    "sg:province":"Baden-W\u00fcrttemberg",
    "wof:name":"Dogan",
    "wof:placetype":"venue"
},
  "geometry": {"coordinates":[10.0150966644,48.4287452698],"type":"Point"}
}