{
  "type": "Feature",
  "properties": {
    "iso:country":"DE",
    "sg:address":"Nieskyer Str. 31",
    "sg:city":"Waldhufen",
    "sg:phone":"+49 3588/201936",
    "sg:postcode":"02906",
    "sg:province":"Sachsen",
    "wof:name":"Petra M\u00f6hle",
    "wof:placetype":"venue"
},
  "geometry": {"coordinates":[14.8109960556,51.252746582],"type":"Point"}
}