{
  "type": "Feature",
  "properties": {
    "iso:country":"DE",
    "sg:address":"Frankfurter Str. 14",
    "sg:city":"Ober-M\u00f6rlen",
    "sg:phone":"+49 6002/450",
    "sg:postcode":"61239",
    "sg:province":"Hessen",
    "wof:name":"Goldener Hirsch",
    "wof:placetype":"venue"
},
  "geometry": {"coordinates":[8.6935930252,50.3738670349],"type":"Point"}
}