{
  "type": "Feature",
  "properties": {
    "iso:country":"DE",
    "sg:address":"Kanalufer 14",
    "sg:city":"Rendsburg",
    "sg:postcode":"24768",
    "sg:province":"Schleswig-Holstein",
    "wof:name":"Verwaltung Ms Ute Schiff- Fahrtsgesellschaft Mbh",
    "wof:placetype":"venue"
},
  "geometry": {"coordinates":[9.6595087051,54.2907295227],"type":"Point"}
}