{
  "type": "Feature",
  "properties": {
    "iso:country":"DE",
    "sg:address":"Sommerstr. 13",
    "sg:city":"Erfweiler",
    "sg:phone":"+49 6391/859",
    "sg:postcode":"66996",
    "sg:province":"Rheinland-Pfalz",
    "wof:name":"Wolfgang Weis",
    "wof:placetype":"venue"
},
  "geometry": {"coordinates":[7.8095998764,49.1584587097],"type":"Point"}
}