{
  "type": "Feature",
  "properties": {
    "iso:country":"DE",
    "sg:address":"Bornstr. 30",
    "sg:city":"Essen",
    "sg:phone":"+49 201/225507",
    "sg:postcode":"45127",
    "sg:province":"Nordrhein-Westfalen",
    "wof:name":"Fred Wichmann",
    "wof:placetype":"venue"
},
  "geometry": {"coordinates":[7.017406,51.460499],"type":"Point"}
}