{
  "type": "Feature",
  "properties": {
    "iso:country":"DE",
    "sg:address":"Steller Str 26b",
    "sg:city":"Delmenhorst",
    "sg:phone":"+49 4221/97710",
    "sg:postcode":"27755",
    "sg:province":"Niedersachsen",
    "wof:name":"Palacz Kammeier K\u00e4lte-klimatechnik Gmbh",
    "wof:placetype":"venue"
},
  "geometry": {"coordinates":[8.6515846252,53.0190811157],"type":"Point"}
}