{
  "type": "Feature",
  "properties": {
    "iso:country":"DE",
    "sg:address":"Michelsdorf 17",
    "sg:city":"Cham",
    "sg:phone":"+49 9971/30763",
    "sg:postcode":"93413",
    "sg:province":"Bayern",
    "wof:name":"E. Wei\u00df",
    "wof:placetype":"venue"
},
  "geometry": {"coordinates":[12.6353225708,49.2152023315],"type":"Point"}
}