{
  "type": "Feature",
  "properties": {
    "iso:country":"DE",
    "sg:address":"Martin-Meyer-Weg 6",
    "sg:city":"Gro\u00dfhansdorf",
    "sg:phone":"+49 4102/60010",
    "sg:postcode":"22927",
    "sg:province":"Schleswig-Holstein",
    "wof:name":"Ulrich Mergardt Ingenieur",
    "wof:placetype":"venue"
},
  "geometry": {"coordinates":[10.2780828476,53.6473312378],"type":"Point"}
}