{
  "type": "Feature",
  "properties": {
    "iso:country":"DE",
    "sg:address":"Bahnhofplatz 7",
    "sg:city":"Ulm",
    "sg:phone":"+49 731/67018",
    "sg:postcode":"89073",
    "sg:province":"Baden-W\u00fcrttemberg",
    "wof:name":"Friseur Befurt Gmbh",
    "wof:placetype":"venue"
},
  "geometry": {"coordinates":[9.984417,48.399067],"type":"Point"}
}