{
  "type": "Feature",
  "properties": {
    "iso:country":"DE",
    "sg:address":"Gro\u00dfe Str. 18",
    "sg:city":"S\u00fcderbrarup",
    "sg:phone":"+49 4641/988014",
    "sg:postcode":"24392",
    "sg:province":"Schleswig-Holstein",
    "wof:name":"Friedrich Grefe Rechtsanwalt",
    "wof:placetype":"venue"
},
  "geometry": {"coordinates":[9.7742271423,54.6352119446],"type":"Point"}
}