{
  "type": "Feature",
  "properties": {
    "iso:country":"DE",
    "sg:address":"Dietzhof",
    "sg:city":"Kunreuth",
    "sg:phone":"+49 9199/267",
    "sg:postcode":"91358",
    "sg:province":"Bayern",
    "wof:name":"Gastst\u00e4tte Alt",
    "wof:placetype":"venue"
},
  "geometry": {"coordinates":[11.1434679031,49.682346344],"type":"Point"}
}