{
  "type": "Feature",
  "properties": {
    "iso:country":"DE",
    "sg:address":"Karl-Marx-Str. 2",
    "sg:city":"Grimma",
    "sg:postcode":"04668",
    "sg:province":"Sachsen",
    "wof:name":"H. Einbock",
    "wof:placetype":"venue"
},
  "geometry": {"coordinates":[12.72215,51.232243],"type":"Point"}
}