{
  "type": "Feature",
  "properties": {
    "iso:country":"DE",
    "sg:address":"Seegefelder Str. 126 c",
    "sg:city":"Berlin",
    "sg:phone":"+49 30/3712999",
    "sg:postcode":"13583",
    "sg:province":"Berlin",
    "wof:name":"H\u00f6pfner & Kaempff Gmbh",
    "wof:placetype":"venue"
},
  "geometry": {"coordinates":[13.180463,52.538879],"type":"Point"}
}