{
  "type": "Feature",
  "properties": {
    "iso:country":"DE",
    "sg:address":"Erlenstr. 2",
    "sg:city":"Worms",
    "sg:phone":"+49 6241/44814",
    "sg:postcode":"67547",
    "sg:province":"Rheinland-Pfalz",
    "wof:name":"U. Wilhelm",
    "wof:placetype":"venue"
},
  "geometry": {"coordinates":[8.3616065979,49.644733429],"type":"Point"}
}