{
  "type": "Feature",
  "properties": {
    "iso:country":"DE",
    "sg:address":"Mittelstr. 51",
    "sg:city":"Gevelsberg",
    "sg:phone":"+49 2332/2286",
    "sg:postcode":"58285",
    "sg:province":"Nordrhein-Westfalen",
    "wof:name":"Happ M\u00f6belhaus",
    "wof:placetype":"venue"
},
  "geometry": {"coordinates":[7.3365459442,51.3186340332],"type":"Point"}
}