{
  "type": "Feature",
  "properties": {
    "iso:country":"DE",
    "sg:address":"Lokstedter Weg 50",
    "sg:city":"Hamburg",
    "sg:phone":"+49 40/489821",
    "sg:postcode":"20251",
    "sg:province":"Hamburg",
    "wof:name":"T. Andrae",
    "wof:placetype":"venue"
},
  "geometry": {"coordinates":[9.984454,53.595654],"type":"Point"}
}