{
  "type": "Feature",
  "properties": {
    "iso:country":"DE",
    "sg:address":"Harscheidweg 23",
    "sg:city":"Essen",
    "sg:phone":"+49 9761/91070",
    "sg:postcode":"45149",
    "sg:province":"Nordrhein-Westfalen",
    "wof:name":"Viktor Haschke Gmbh",
    "wof:placetype":"venue"
},
  "geometry": {"coordinates":[10.472177,50.292767],"type":"Point"}
}