{
  "type": "Feature",
  "properties": {
    "iso:country":"DE",
    "sg:address":"Sattlertorstr. 2",
    "sg:city":"Forchheim",
    "sg:phone":"+49 9191/2234",
    "sg:postcode":"91301",
    "sg:province":"Bayern",
    "wof:name":"Kath. Pfarramt St. Martin",
    "wof:placetype":"venue"
},
  "geometry": {"coordinates":[11.0577669144,49.7202262878],"type":"Point"}
}