{
  "type": "Feature",
  "properties": {
    "iso:country":"DE",
    "sg:address":"Altenessener Str.405",
    "sg:city":"Essen",
    "sg:phone":"+49 201/341042",
    "sg:postcode":"45326",
    "sg:province":"Nordrhein-Westfalen",
    "wof:name":"Dresdner Bank",
    "wof:placetype":"venue"
},
  "geometry": {"coordinates":[7.007988,51.496094],"type":"Point"}
}