{
  "type": "Feature",
  "properties": {
    "iso:country":"DE",
    "sg:address":"Clayallee 242",
    "sg:city":"Berlin",
    "sg:phone":"+49 30/8328957",
    "sg:postcode":"14169",
    "sg:province":"Berlin",
    "wof:name":"Hinka Gmbh",
    "wof:placetype":"venue"
},
  "geometry": {"coordinates":[13.26807,52.445747],"type":"Point"}
}