{
  "type": "Feature",
  "properties": {
    "iso:country":"DE",
    "sg:address":"Rosenheimer Str. 25",
    "sg:city":"Kolbermoor",
    "sg:phone":"+49 8031/97943",
    "sg:postcode":"83059",
    "sg:province":"Bayern",
    "wof:name":"Ihr Foto-shop Strasser Gmbh",
    "wof:placetype":"venue"
},
  "geometry": {"coordinates":[12.0676259995,47.8499984741],"type":"Point"}
}