{
  "type": "Feature",
  "properties": {
    "iso:country":"DE",
    "sg:address":"Am Salzbach 6",
    "sg:city":"Kn\u00fcllwald",
    "sg:phone":"+49 5685/342",
    "sg:postcode":"34593",
    "sg:province":"Hessen",
    "wof:name":"Gerhard Kr\u00fcger",
    "wof:placetype":"venue"
},
  "geometry": {"coordinates":[9.533745,50.991467],"type":"Point"}
}