{
  "type": "Feature",
  "properties": {
    "iso:country":"DE",
    "sg:address":"Lauchst\u00e4dter Str. 1",
    "sg:city":"Halle",
    "sg:phone":"+49 345/1205100",
    "sg:postcode":"06110",
    "sg:province":"Sachsen-Anhalt",
    "wof:name":"A. Lange",
    "wof:placetype":"venue"
},
  "geometry": {"coordinates":[11.9832458496,51.4654083252],"type":"Point"}
}