{
  "type": "Feature",
  "properties": {
    "iso:country":"DE",
    "sg:address":"Radestr. 9",
    "sg:city":"Salzwedel",
    "sg:phone":"+49 3901/38085",
    "sg:postcode":"29410",
    "sg:province":"Sachsen-Anhalt",
    "wof:name":"Carsten Br\u00fcckner Ing.-b\u00fcro Hochbau",
    "wof:placetype":"venue"
},
  "geometry": {"coordinates":[11.1503334045,52.8493232727],"type":"Point"}
}