{
  "type": "Feature",
  "properties": {
    "iso:country":"DE",
    "sg:address":"Langemarckstr. 20",
    "sg:city":"Bedburg",
    "sg:phone":"+49 2272/2568",
    "sg:postcode":"50181",
    "sg:province":"Nordrhein-Westfalen",
    "wof:name":"Ev. Pfarramt Bedburg",
    "wof:placetype":"venue"
},
  "geometry": {"coordinates":[6.5733947754,50.9906311035],"type":"Point"}
}