{
  "type": "Feature",
  "properties": {
    "iso:country":"DE",
    "sg:address":"G\u00fcterhallenstr. 5",
    "sg:city":"Achern",
    "sg:phone":"+49 7841/25427",
    "sg:postcode":"77855",
    "sg:province":"Baden-W\u00fcrttemberg",
    "wof:name":"Arthur Und Erwin Weinhardt Inh. Erwin Weinhardt",
    "wof:placetype":"venue"
},
  "geometry": {"coordinates":[8.061106,48.629116],"type":"Point"}
}