{
  "type": "Feature",
  "properties": {
    "iso:country":"DE",
    "sg:address":"Marktstr. 6",
    "sg:city":"Billigheim-Ingenheim",
    "sg:phone":"+49 6349/6271",
    "sg:postcode":"76831",
    "sg:province":"Rheinland-Pfalz",
    "wof:name":"K. M\u00fcller",
    "wof:placetype":"venue"
},
  "geometry": {"coordinates":[8.0996828079,49.1371459961],"type":"Point"}
}