{
  "type": "Feature",
  "properties": {
    "iso:country":"DE",
    "sg:address":"Dauner Str. 2 a",
    "sg:city":"Bitburg",
    "sg:phone":"+49 6561/95880",
    "sg:postcode":"54634",
    "sg:province":"Rheinland-Pfalz",
    "wof:name":"Beda-gesellschaft F\u00fcr Multikult. Ausbildung Private",
    "wof:placetype":"venue"
},
  "geometry": {"coordinates":[6.5252070427,49.9757766724],"type":"Point"}
}