{
  "type": "Feature",
  "properties": {
    "iso:country":"DE",
    "sg:address":"Steinkuhle 4",
    "sg:city":"Woltershausen",
    "sg:phone":"+49 5183/768",
    "sg:postcode":"31099",
    "sg:province":"Niedersachsen",
    "wof:name":"Hans-dieter Und Liese. Koch",
    "wof:placetype":"venue"
},
  "geometry": {"coordinates":[9.9542369843,51.9710159302],"type":"Point"}
}