{
  "type": "Feature",
  "properties": {
    "iso:country":"DE",
    "sg:address":"Berliner Str. 15",
    "sg:city":"Waldkraiburg",
    "sg:phone":"+49 8638/880320",
    "sg:postcode":"84478",
    "sg:province":"Bayern",
    "wof:name":"Ecw-hausbau- Gmbh",
    "wof:placetype":"venue"
},
  "geometry": {"coordinates":[12.402891,48.207249],"type":"Point"}
}