{
  "type": "Feature",
  "properties": {
    "iso:country":"DE",
    "sg:address":"Tacitusstr. 10",
    "sg:city":"Neuss",
    "sg:phone":"+49 2131/103210",
    "sg:postcode":"41468",
    "sg:province":"Nordrhein-Westfalen",
    "wof:name":"Dahlmann Gmbh",
    "wof:placetype":"venue"
},
  "geometry": {"coordinates":[6.7267241478,51.1797027588],"type":"Point"}
}