{
  "type": "Feature",
  "properties": {
    "iso:country":"DE",
    "sg:address":"Seebergstr. 16",
    "sg:city":"Kassel",
    "sg:phone":"+49 561/62435",
    "sg:postcode":"34128",
    "sg:province":"Hessen",
    "wof:name":"Claus Schmidt Ingenieur",
    "wof:placetype":"venue"
},
  "geometry": {"coordinates":[9.4193887711,51.3325653076],"type":"Point"}
}