{
  "type": "Feature",
  "properties": {
    "iso:country":"DE",
    "sg:address":"Boschweg 4",
    "sg:city":"Berlin",
    "sg:postcode":"12057",
    "sg:province":"Berlin",
    "wof:name":"Ekasit Verwaltungs Gmbh",
    "wof:placetype":"venue"
},
  "geometry": {"coordinates":[13.464465,52.462845],"type":"Point"}
}