{
  "type": "Feature",
  "properties": {
    "iso:country":"DE",
    "sg:address":"Reuschstr. 16",
    "sg:city":"Siegen",
    "sg:phone":"+49 271/45127",
    "sg:postcode":"57072",
    "sg:province":"Nordrhein-Westfalen",
    "wof:name":"L. Gerhard & Co. Holzwaren-handels Gmbh",
    "wof:placetype":"venue"
},
  "geometry": {"coordinates":[8.032607,50.882145],"type":"Point"}
}