{
  "type": "Feature",
  "properties": {
    "iso:country":"DE",
    "sg:address":"B\u00fcttnerstr. 10",
    "sg:city":"Leipzig",
    "sg:phone":"+49 341/2111072",
    "sg:postcode":"04103",
    "sg:province":"Sachsen",
    "wof:name":"Sch\u00e4ferhof Projekt- Gesellschaft Mbh",
    "wof:placetype":"venue"
},
  "geometry": {"coordinates":[12.387446,51.342735],"type":"Point"}
}