{
  "type": "Feature",
  "properties": {
    "iso:country":"DE",
    "sg:address":"Johannisberger Str. 42",
    "sg:city":"Oestrich-Winkel",
    "sg:phone":"+49 6723/889316",
    "sg:postcode":"65375",
    "sg:province":"Hessen",
    "wof:name":"Ludwig Andreas Krehling Rechtsanwalt",
    "wof:placetype":"venue"
},
  "geometry": {"coordinates":[8.0005264282,49.9992103577],"type":"Point"}
}