{
  "type": "Feature",
  "properties": {
    "iso:country":"DE",
    "sg:address":"Koblenz-Olper-Str. 177",
    "sg:city":"Bendorf",
    "sg:phone":"+49 2622/14433",
    "sg:postcode":"56170",
    "sg:province":"Rheinland-Pfalz",
    "wof:name":"Roman H\u00f6rter",
    "wof:placetype":"venue"
},
  "geometry": {"coordinates":[7.5777587891,50.4406089783],"type":"Point"}
}