{
  "type": "Feature",
  "properties": {
    "iso:country":"DE",
    "sg:address":"Hofgraben 42",
    "sg:city":"Gersdorf",
    "sg:phone":"+49 37203/4369",
    "sg:postcode":"09355",
    "sg:province":"Sachsen",
    "wof:name":"C. F. Kretzschmar Inh. Ch. Stadler",
    "wof:placetype":"venue"
},
  "geometry": {"coordinates":[12.6959428787,50.7553520203],"type":"Point"}
}