{
  "type": "Feature",
  "properties": {
    "iso:country":"DE",
    "sg:address":"Sofienstr. 39",
    "sg:city":"Detmold",
    "sg:phone":"+49 5231/762400",
    "sg:postcode":"32756",
    "sg:province":"Nordrhein-Westfalen",
    "wof:name":"Haus Birke Ev. Diakonissenhaus",
    "wof:placetype":"venue"
},
  "geometry": {"coordinates":[8.881903,51.941341],"type":"Point"}
}