{
  "type": "Feature",
  "properties": {
    "iso:country":"DE",
    "sg:address":"Roggenstrasse",
    "sg:city":"Euskirchen",
    "sg:phone":"+49 2251/9291891",
    "sg:postcode":"53893",
    "sg:province":"Nordrhein-Westfalen",
    "wof:name":"Eds Euskirchen Gmbh",
    "wof:placetype":"venue"
},
  "geometry": {"coordinates":[6.77318,50.62801],"type":"Point"}
}