{
  "type": "Feature",
  "properties": {
    "iso:country":"DE",
    "sg:address":"Mittelweg 15",
    "sg:city":"Hamburg",
    "sg:phone":"+49 40/453772",
    "sg:postcode":"20148",
    "sg:province":"Hamburg",
    "wof:name":"Act Service Gmbh",
    "wof:placetype":"venue"
},
  "geometry": {"coordinates":[9.995394,53.56641],"type":"Point"}
}