{
  "type": "Feature",
  "properties": {
    "iso:country":"DE",
    "sg:address":"Fangdieckstr. 59",
    "sg:city":"Hamburg",
    "sg:postcode":"22547",
    "sg:province":"Hamburg",
    "wof:name":"Verwaltungsges. Theel Mbh",
    "wof:placetype":"venue"
},
  "geometry": {"coordinates":[9.9011392593,53.5971450806],"type":"Point"}
}