{
  "type": "Feature",
  "properties": {
    "iso:country":"DE",
    "sg:address":"Sch\u00e4fflerstr. 18",
    "sg:city":"Erding",
    "sg:phone":"+49 8122/42585",
    "sg:postcode":"85435",
    "sg:province":"Bayern",
    "wof:name":"Huber Datenservice Gmbh",
    "wof:placetype":"venue"
},
  "geometry": {"coordinates":[11.9306306839,48.3061904907],"type":"Point"}
}