{
  "type": "Feature",
  "properties": {
    "iso:country":"DE",
    "sg:address":"Schlo\u00dfstr. 16",
    "sg:city":"Pirmasens",
    "sg:phone":"+49 6331/76096",
    "sg:postcode":"66953",
    "sg:province":"Rheinland-Pfalz",
    "wof:name":"Reiseb\u00fcro Am Winzler Tor Gmbh",
    "wof:placetype":"venue"
},
  "geometry": {"coordinates":[7.6044769287,49.203956604],"type":"Point"}
}