{
  "type": "Feature",
  "properties": {
    "iso:country":"DE",
    "sg:address":"Rehauer Str. 47",
    "sg:city":"Sch\u00f6nwald",
    "sg:phone":"+49 9287/50999",
    "sg:postcode":"95173",
    "sg:province":"Bayern",
    "wof:name":"Norma Lebensmittelfilial- Betrieb Gmbh & Co. Kg",
    "wof:placetype":"venue"
},
  "geometry": {"coordinates":[12.0944623947,50.202835083],"type":"Point"}
}