{
  "type": "Feature",
  "properties": {
    "iso:country":"DE",
    "sg:address":"Unter den Ulmen 96-98",
    "sg:city":"K\u00f6ln",
    "sg:postcode":"50968",
    "sg:province":"Nordrhein-Westfalen",
    "wof:name":"Avs Anwalt Versicherungs- Service Gmbh & Co. Kg",
    "wof:placetype":"venue"
},
  "geometry": {"coordinates":[6.9734687805,50.9047737122],"type":"Point"}
}