{
  "type": "Feature",
  "properties": {
    "iso:country":"DE",
    "sg:address":"Stuttgarter Str. 88",
    "sg:city":"Bietigheim-Bissingen",
    "sg:phone":"+49 7142/222466",
    "sg:postcode":"74321",
    "sg:province":"Baden-W\u00fcrttemberg",
    "wof:name":"D2 Shop Phony Gmbh",
    "wof:placetype":"venue"
},
  "geometry": {"coordinates":[9.1264696121,48.9616203308],"type":"Point"}
}