{
  "type": "Feature",
  "properties": {
    "iso:country":"DE",
    "sg:address":"Katharinenstr. 88",
    "sg:city":"Ludwigsburg",
    "sg:phone":"+49 7141/374272",
    "sg:postcode":"71634",
    "sg:province":"Baden-W\u00fcrttemberg",
    "wof:name":"Inova Vertriebsges. F. Technische Ger\u00e4te Mbh",
    "wof:placetype":"venue"
},
  "geometry": {"coordinates":[9.1680812836,48.9056968689],"type":"Point"}
}