{
  "type": "Feature",
  "properties": {
    "iso:country":"DE",
    "sg:address":"Markt 2",
    "sg:city":"F\u00fcrstenberg",
    "sg:phone":"+49 33093/38308",
    "sg:postcode":"16798",
    "sg:province":"Brandenburg",
    "wof:name":"T. Burmann",
    "wof:placetype":"venue"
},
  "geometry": {"coordinates":[13.145278,53.185757],"type":"Point"}
}