{
  "type": "Feature",
  "properties": {
    "iso:country":"DE",
    "sg:address":"Erfurter Str. 15",
    "sg:city":"Gro\u00dfrudestedt",
    "sg:postcode":"99195",
    "sg:province":"Th\u00fcringen",
    "wof:name":"Ls Dachbau Gmbh",
    "wof:placetype":"venue"
},
  "geometry": {"coordinates":[11.0787286758,51.1202049255],"type":"Point"}
}