{
  "type": "Feature",
  "properties": {
    "iso:country":"DE",
    "sg:address":"Dedenser Str. 1",
    "sg:city":"Barsinghausen",
    "sg:phone":"+49 5035/526",
    "sg:postcode":"30890",
    "sg:province":"Niedersachsen",
    "wof:name":"Gerhard Kauke",
    "wof:placetype":"venue"
},
  "geometry": {"coordinates":[9.504682,52.368279],"type":"Point"}
}