{
  "type": "Feature",
  "properties": {
    "iso:country":"DE",
    "sg:address":"Claudiusstr. 84",
    "sg:city":"Hamburg",
    "sg:phone":"+49 40/684602",
    "sg:postcode":"22043",
    "sg:province":"Hamburg",
    "wof:name":"D. Schlimper Steuerberater",
    "wof:placetype":"venue"
},
  "geometry": {"coordinates":[10.0694541931,53.5653305054],"type":"Point"}
}