{
  "type": "Feature",
  "properties": {
    "iso:country":"DE",
    "sg:address":"Konrad-Hornschuch-Str 57",
    "sg:city":"Urbach",
    "sg:phone":"+49 7181/999040",
    "sg:postcode":"73660",
    "sg:province":"Baden-W\u00fcrttemberg",
    "wof:name":"Raum-reinigung-rems Gmbh",
    "wof:placetype":"venue"
},
  "geometry": {"coordinates":[9.575712,48.806355],"type":"Point"}
}