{
  "type": "Feature",
  "properties": {
    "iso:country":"DE",
    "sg:address":"Zur Lehnern 10",
    "sg:city":"H\u00e4usern",
    "sg:phone":"+49 7672/1500",
    "sg:postcode":"79837",
    "sg:province":"Baden-W\u00fcrttemberg",
    "wof:name":"Rainer Und Ulrike Weber",
    "wof:placetype":"venue"
},
  "geometry": {"coordinates":[8.159791,47.752705],"type":"Point"}
}