{
  "type": "Feature",
  "properties": {
    "iso:country":"DE",
    "sg:address":"Bachstr. 14",
    "sg:city":"Aichtal",
    "sg:postcode":"72631",
    "sg:province":"Baden-W\u00fcrttemberg",
    "wof:name":"Golenko Verwaltungs-gmbh",
    "wof:placetype":"venue"
},
  "geometry": {"coordinates":[9.2067804337,48.6249504089],"type":"Point"}
}