{
  "type": "Feature",
  "properties": {
    "iso:country":"DE",
    "sg:address":"Hubertusstr. 77",
    "sg:city":"Wesseling",
    "sg:phone":"+49 2236",
    "sg:postcode":"50389",
    "sg:province":"Nordrhein-Westfalen",
    "wof:name":"Grabmale, Brunnen, Natursteine",
    "wof:placetype":"venue"
},
  "geometry": {"coordinates":[6.9678812027,50.8263320923],"type":"Point"}
}