{
  "type": "Feature",
  "properties": {
    "iso:country":"DE",
    "sg:address":"Tiefenbachweg 7",
    "sg:city":"Ederm\u00fcnde",
    "sg:phone":"+49 5603/1479",
    "sg:postcode":"34295",
    "sg:province":"Hessen",
    "wof:name":"Caroline F\u00fchrer-caros Reiterwelt Gmbh",
    "wof:placetype":"venue"
},
  "geometry": {"coordinates":[9.385592,51.229382],"type":"Point"}
}