{
  "type": "Feature",
  "properties": {
    "iso:country":"DE",
    "sg:address":"Kirchstr. 10",
    "sg:city":"Altena",
    "sg:phone":"+49 2352/22282",
    "sg:postcode":"58762",
    "sg:province":"Nordrhein-Westfalen",
    "wof:name":"Friedrich Katerl\u00f6h Inh. Dorothea Renfordt",
    "wof:placetype":"venue"
},
  "geometry": {"coordinates":[7.6735172272,51.2962036133],"type":"Point"}
}