{
  "type": "Feature",
  "properties": {
    "iso:country":"DE",
    "sg:address":"Florianstr. 5",
    "sg:city":"H\u00f6chenschwand",
    "sg:phone":"+49 7672/4613",
    "sg:postcode":"79862",
    "sg:province":"Baden-W\u00fcrttemberg",
    "wof:name":"Franz Vogelbacher E. K.",
    "wof:placetype":"venue"
},
  "geometry": {"coordinates":[8.174847,47.730919],"type":"Point"}
}