{
  "type": "Feature",
  "properties": {
    "iso:country":"DE",
    "sg:address":"K\u00f6nigsh\u00fctte 31",
    "sg:city":"Leonberg",
    "sg:phone":"+49 9633/2306",
    "sg:postcode":"95666",
    "sg:province":"Bayern",
    "wof:name":"K. Eisner",
    "wof:placetype":"venue"
},
  "geometry": {"coordinates":[12.2869405746,49.9677886963],"type":"Point"}
}