{
  "type": "Feature",
  "properties": {
    "iso:country":"DE",
    "sg:address":"Im Hain 38",
    "sg:city":"Frankfurt",
    "sg:phone":"+49 69/504725",
    "sg:postcode":"60437",
    "sg:province":"Hessen",
    "wof:name":"Hans-peter J\u00e4ger Ingenieur",
    "wof:placetype":"venue"
},
  "geometry": {"coordinates":[8.6456365585,50.1883621216],"type":"Point"}
}