{
  "type": "Feature",
  "properties": {
    "iso:country":"DE",
    "sg:address":"Dorfstr. 71",
    "sg:city":"Zettlitz",
    "sg:phone":"+49 3737/47558",
    "sg:postcode":"09306",
    "sg:province":"Sachsen",
    "wof:name":"Gerd Diesterheft",
    "wof:placetype":"venue"
},
  "geometry": {"coordinates":[12.8378429413,51.0730438232],"type":"Point"}
}