{
  "type": "Feature",
  "properties": {
    "iso:country":"DE",
    "sg:address":"Hohenwedeler Weg 1",
    "sg:city":"Stade",
    "sg:phone":"+49 4141/85500",
    "sg:postcode":"21682",
    "sg:province":"Niedersachsen",
    "wof:name":"Brigitte Ebeling",
    "wof:placetype":"venue"
},
  "geometry": {"coordinates":[9.4628143311,53.6057739258],"type":"Point"}
}