{
  "type": "Feature",
  "properties": {
    "iso:country":"DE",
    "sg:address":"Holzweg 1",
    "sg:city":"Heilbad Heiligenstadt",
    "sg:phone":"+49 3606/612910",
    "sg:postcode":"37308",
    "sg:province":"Th\u00fcringen",
    "wof:name":"Gottfried Unselt Tankstelle",
    "wof:placetype":"venue"
},
  "geometry": {"coordinates":[10.1305303574,51.3754005432],"type":"Point"}
}