{
  "type": "Feature",
  "properties": {
    "iso:country":"DE",
    "sg:address":"Zu den Erlen 72",
    "sg:city":"Duisburg",
    "sg:phone":"+49 203/764642",
    "sg:postcode":"47269",
    "sg:province":"Nordrhein-Westfalen",
    "wof:name":"Tebarts Bauunternehmung Gmbh",
    "wof:placetype":"venue"
},
  "geometry": {"coordinates":[6.783077,51.366318],"type":"Point"}
}