{
  "type": "Feature",
  "properties": {
    "iso:country":"DE",
    "sg:address":"Hohlweg 3",
    "sg:city":"Neulu\u00dfheim",
    "sg:phone":"+49 6205/31494",
    "sg:postcode":"68809",
    "sg:province":"Baden-W\u00fcrttemberg",
    "wof:name":"Ewald Scheibel",
    "wof:placetype":"venue"
},
  "geometry": {"coordinates":[8.5251197815,49.29662323],"type":"Point"}
}