{
  "type": "Feature",
  "properties": {
    "iso:country":"DE",
    "sg:address":"Schleusenstr. 39a",
    "sg:city":"Wilhelmshaven",
    "sg:phone":"+49 4421/94750",
    "sg:postcode":"26382",
    "sg:province":"Niedersachsen",
    "wof:name":"Senckenberg-institut Seeschiffahrt-u.",
    "wof:placetype":"venue"
},
  "geometry": {"coordinates":[8.151848,53.518646],"type":"Point"}
}