{
  "type": "Feature",
  "properties": {
    "iso:country":"DE",
    "sg:address":"Erlenstr. 31",
    "sg:city":"Sinzheim",
    "sg:phone":"+49 7221/8436",
    "sg:postcode":"76547",
    "sg:province":"Baden-W\u00fcrttemberg",
    "wof:name":"K. Klein",
    "wof:placetype":"venue"
},
  "geometry": {"coordinates":[8.167481,48.762413],"type":"Point"}
}