{
  "type": "Feature",
  "properties": {
    "iso:country":"DE",
    "sg:address":"Kirchenweg 15",
    "sg:city":"Hausen",
    "sg:postcode":"63840",
    "sg:province":"Bayern",
    "wof:name":"T. E. M. Techn. Entwicklungen Und Management Gmbh",
    "wof:placetype":"venue"
},
  "geometry": {"coordinates":[9.2075929642,49.8695983887],"type":"Point"}
}