{
  "type": "Feature",
  "properties": {
    "iso:country":"DE",
    "sg:address":"Nansenstr. 14",
    "sg:city":"Wiesbaden",
    "sg:phone":"+49 611/607575",
    "sg:postcode":"65203",
    "sg:province":"Hessen",
    "wof:name":"Hans-joachim Scherry Architekt",
    "wof:placetype":"venue"
},
  "geometry": {"coordinates":[8.228805,50.041664],"type":"Point"}
}