{
  "type": "Feature",
  "properties": {
    "iso:country":"DE",
    "sg:address":"Bruchstr. 7",
    "sg:city":"Hilchenbach",
    "sg:phone":"+49 2733/4476",
    "sg:postcode":"57271",
    "sg:province":"Nordrhein-Westfalen",
    "wof:name":"Helmut Schneider Obst- Und Gem\u00fcsezentrale",
    "wof:placetype":"venue"
},
  "geometry": {"coordinates":[8.1069698334,50.9953918457],"type":"Point"}
}