{
  "type": "Feature",
  "properties": {
    "iso:country":"DE",
    "sg:address":"Hauptstr. 54",
    "sg:city":"Marsberg",
    "sg:phone":"+49 2992/5051",
    "sg:postcode":"34431",
    "sg:province":"Nordrhein-Westfalen",
    "wof:name":"N\u00e4hparadies Sylvia T\u00f6nsmeyer E. Kfr.",
    "wof:placetype":"venue"
},
  "geometry": {"coordinates":[8.857415,51.458832],"type":"Point"}
}