{
  "type": "Feature",
  "properties": {
    "iso:country":"DE",
    "sg:address":"Aachener Str. 419",
    "sg:city":"M\u00f6nchengladbach",
    "sg:phone":"+49 2161/593288",
    "sg:postcode":"41069",
    "sg:province":"Nordrhein-Westfalen",
    "wof:name":"U. Kleuser",
    "wof:placetype":"venue"
},
  "geometry": {"coordinates":[6.4104471207,51.1825218201],"type":"Point"}
}