{
  "type": "Feature",
  "properties": {
    "iso:country":"DE",
    "sg:address":"Syker Str. 52",
    "sg:city":"Bremen",
    "sg:phone":"+49 421/894466",
    "sg:postcode":"28307",
    "sg:province":"Bremen",
    "wof:name":"Blanke Herker Und Oetjens Rechtsanw\u00e4lte",
    "wof:placetype":"venue"
},
  "geometry": {"coordinates":[8.9472398758,53.0382614136],"type":"Point"}
}