{
  "type": "Feature",
  "properties": {
    "iso:country":"DE",
    "sg:address":"Bundeskanzlerplatz 2-10",
    "sg:city":"Bonn",
    "sg:classifiers":[
        {
            "category":"Professional",
            "subcategory":"Management & Consulting",
            "type":"Services"
        }
    ],
    "sg:postcode":"53113",
    "sg:tags":[
        "consulting",
        "online-marketing",
        "business-development"
    ],
    "sg:website":"http://www.saphiron.de",
    "wof:name":"Saphiron Management & Technology Consultants",
    "wof:placetype":"venue"
},
  "geometry": {"coordinates":[7.1161169,50.7191348],"type":"Point"}
}