{
  "type": "Feature",
  "properties": {
    "iso:country":"DE",
    "sg:address":"Stammheimer Str. 73",
    "sg:city":"K\u00f6ln",
    "sg:phone":"+49 221/7605100",
    "sg:postcode":"50735",
    "sg:province":"Nordrhein-Westfalen",
    "wof:name":"Tivoli-apotheke Inh. Gerd Schw\u00e4rtzel E. K.",
    "wof:placetype":"venue"
},
  "geometry": {"coordinates":[6.974713,50.963097],"type":"Point"}
}