{
  "type": "Feature",
  "properties": {
    "iso:country":"DE",
    "sg:address":"Am Rosengarten 10",
    "sg:city":"Tosterglope",
    "sg:phone":"+49 5853/511",
    "sg:postcode":"21371",
    "sg:province":"Niedersachsen",
    "wof:name":"Dagmar Sebon \u00c4rztin F\u00fcr Allgemeinmedizin",
    "wof:placetype":"venue"
},
  "geometry": {"coordinates":[10.8554039001,53.1999130249],"type":"Point"}
}