{
  "type": "Feature",
  "properties": {
    "iso:country":"DE",
    "sg:address":"Reimer-Hansen-Str. 12",
    "sg:city":"Bad Oldesloe",
    "sg:phone":"+49 4531/83221",
    "sg:postcode":"23843",
    "sg:province":"Schleswig-Holstein",
    "wof:name":"Horst-r. Klinck Heizungsbedarfs-hdl.",
    "wof:placetype":"venue"
},
  "geometry": {"coordinates":[10.380944252,53.8070487976],"type":"Point"}
}