{
  "type": "Feature",
  "properties": {
    "iso:country":"DE",
    "sg:address":"Kelterstr. 111",
    "sg:city":"Dettingen",
    "sg:phone":"+49 7021/987188",
    "sg:postcode":"73265",
    "sg:province":"Baden-W\u00fcrttemberg",
    "wof:name":"Bwd Betonwerk Dettingen Gmbh & Co.",
    "wof:placetype":"venue"
},
  "geometry": {"coordinates":[9.451279,48.627411],"type":"Point"}
}