{
  "type": "Feature",
  "properties": {
    "iso:country":"DE",
    "sg:address":"Endenicher Str. 185",
    "sg:city":"Bonn",
    "sg:phone":"+49 228/651285",
    "sg:postcode":"53115",
    "sg:province":"Nordrhein-Westfalen",
    "wof:name":"Sebastian Sarcher Detektei",
    "wof:placetype":"venue"
},
  "geometry": {"coordinates":[7.078329,50.72966],"type":"Point"}
}