{
  "type": "Feature",
  "properties": {
    "iso:country":"DE",
    "sg:address":"Erlenweg 12",
    "sg:city":"Reichenau",
    "sg:phone":"+49 7531/78456",
    "sg:postcode":"78479",
    "sg:province":"Baden-W\u00fcrttemberg",
    "wof:name":"Helmut Lieb Architekt",
    "wof:placetype":"venue"
},
  "geometry": {"coordinates":[9.117614,47.697693],"type":"Point"}
}