{
  "type": "Feature",
  "properties": {
    "iso:country":"DE",
    "sg:address":"Lotter Str. 63",
    "sg:city":"Osnabr\u00fcck",
    "sg:phone":"+49 541/41659",
    "sg:postcode":"49078",
    "sg:province":"Niedersachsen",
    "wof:name":"August Brockfeld",
    "wof:placetype":"venue"
},
  "geometry": {"coordinates":[8.02318573,52.2744293213],"type":"Point"}
}