{
  "type": "Feature",
  "properties": {
    "iso:country":"DE",
    "sg:address":"Saarlandstr. 87-89",
    "sg:city":"Oranienburg",
    "sg:phone":"+49 3301",
    "sg:postcode":"16515",
    "sg:province":"Brandenburg",
    "wof:name":"Tauber Automobile",
    "wof:placetype":"venue"
},
  "geometry": {"coordinates":[13.2544803619,52.7395896912],"type":"Point"}
}