{
  "type": "Feature",
  "properties": {
    "iso:country":"DE",
    "sg:address":"Zuckerbergstr. 82",
    "sg:city":"Stuttgart",
    "sg:phone":"+49 711/5380874",
    "sg:postcode":"70378",
    "sg:province":"Baden-W\u00fcrttemberg",
    "wof:name":"Tommaso Italia Vertriebs Kg",
    "wof:placetype":"venue"
},
  "geometry": {"coordinates":[9.2272529602,48.8253250122],"type":"Point"}
}