{
  "type": "Feature",
  "properties": {
    "iso:country":"DE",
    "sg:address":"Eibenweg 15",
    "sg:city":"N\u00fcrnberg",
    "sg:phone":"+49 911/646473",
    "sg:postcode":"90451",
    "sg:province":"Bayern",
    "wof:name":"B. Weindorf",
    "wof:placetype":"venue"
},
  "geometry": {"coordinates":[11.037657,49.408794],"type":"Point"}
}