{
  "type": "Feature",
  "properties": {
    "iso:country":"DE",
    "sg:address":"Roeckstr. 16",
    "sg:city":"L\u00fcbeck",
    "sg:phone":"+49 451/31338",
    "sg:postcode":"23568",
    "sg:province":"Schleswig-Holstein",
    "wof:name":"Kaspien",
    "wof:placetype":"venue"
},
  "geometry": {"coordinates":[10.6989059448,53.8756332397],"type":"Point"}
}