{
  "type": "Feature",
  "properties": {
    "iso:country":"DE",
    "sg:address":"Friedlandstr 23",
    "sg:city":"Bruchk\u00f6bel",
    "sg:phone":"+49 6181/976767",
    "sg:postcode":"63486",
    "sg:province":"Hessen",
    "wof:name":"Rts Schmierstoff-technik Vertriebsgesellschaft Mbh",
    "wof:placetype":"venue"
},
  "geometry": {"coordinates":[8.915408,50.186562],"type":"Point"}
}