{
  "type": "Feature",
  "properties": {
    "iso:country":"DE",
    "sg:address":"Oberstr. 98",
    "sg:city":"Boppard",
    "sg:phone":"+49 6742/1590",
    "sg:postcode":"56154",
    "sg:province":"Rheinland-Pfalz",
    "wof:name":"Cornelia Nebe Heilpraktikerin",
    "wof:placetype":"venue"
},
  "geometry": {"coordinates":[7.5930857658,50.2317504883],"type":"Point"}
}