{
  "type": "Feature",
  "properties": {
    "iso:country":"DE",
    "sg:address":"Am Wasserturm 15",
    "sg:city":"Graal-M\u00fcritz",
    "sg:postcode":"18181",
    "sg:province":"Mecklenburg-Vorpommern",
    "wof:name":"P. Reuter",
    "wof:placetype":"venue"
},
  "geometry": {"coordinates":[12.250261,54.251656],"type":"Point"}
}