{
  "type": "Feature",
  "properties": {
    "iso:country":"DE",
    "sg:address":"Wiesenenaer Str.",
    "sg:city":"Wiedemar",
    "sg:phone":"+49 34207/41030",
    "sg:postcode":"04509",
    "sg:province":"Sachsen",
    "wof:name":"K\u00fcper Kg",
    "wof:placetype":"venue"
},
  "geometry": {"coordinates":[12.2067899704,51.4636154175],"type":"Point"}
}