{
  "type": "Feature",
  "properties": {
    "iso:country":"DE",
    "sg:address":"Gartenstr. 44",
    "sg:city":"Nellingen",
    "sg:phone":"+49 7337/412",
    "sg:postcode":"89191",
    "sg:province":"Baden-W\u00fcrttemberg",
    "wof:name":"C. Schneller",
    "wof:placetype":"venue"
},
  "geometry": {"coordinates":[9.796286,48.541962],"type":"Point"}
}