{
  "type": "Feature",
  "properties": {
    "iso:country":"DE",
    "sg:address":"Kaiserstr. 107",
    "sg:city":"M\u00f6nchengladbach",
    "sg:postcode":"41061",
    "sg:province":"Nordrhein-Westfalen",
    "wof:name":"Formazell Ges. F\u00fcr Ek Und Vertrieb Von",
    "wof:placetype":"venue"
},
  "geometry": {"coordinates":[6.4417557716,51.1992378235],"type":"Point"}
}