{
  "type": "Feature",
  "properties": {
    "iso:country":"DE",
    "sg:address":"Hauptstr. 39",
    "sg:city":"P\u00fcttlingen",
    "sg:phone":"+49 6806/490861",
    "sg:postcode":"66346",
    "sg:province":"Saarland",
    "wof:name":"G. Wolmeringer Immobilienmakler",
    "wof:placetype":"venue"
},
  "geometry": {"coordinates":[6.8997941017,49.3035392761],"type":"Point"}
}