{
  "type": "Feature",
  "properties": {
    "iso:country":"DE",
    "sg:address":"K\u00e4the-Kollwitz-Str. 9",
    "sg:city":"Schkeuditz",
    "sg:postcode":"04435",
    "sg:province":"Sachsen",
    "wof:name":"Pms Graphischer Service Gmbh",
    "wof:placetype":"venue"
},
  "geometry": {"coordinates":[12.224798,51.397392],"type":"Point"}
}