{
  "type": "Feature",
  "properties": {
    "iso:country":"DE",
    "sg:address":"Am Weiler Hof 18",
    "sg:city":"Meerbusch",
    "sg:phone":"+49 2159/81092",
    "sg:postcode":"40668",
    "sg:province":"Nordrhein-Westfalen",
    "wof:name":"Use Messeteam Gmbh",
    "wof:placetype":"venue"
},
  "geometry": {"coordinates":[6.628745079,51.2947044373],"type":"Point"}
}