{
  "type": "Feature",
  "properties": {
    "iso:country":"DE",
    "sg:address":"Wilhelmstr. 110",
    "sg:city":"Hanau",
    "sg:postcode":"63450",
    "sg:province":"Hessen",
    "wof:name":"Dr. Bernhard Braun Gmbh",
    "wof:placetype":"venue"
},
  "geometry": {"coordinates":[8.923075,50.14032],"type":"Point"}
}