{
  "type": "Feature",
  "properties": {
    "iso:country":"DE",
    "sg:address":"dreichlingerstrasse 21",
    "sg:city":"neumarkt",
    "sg:phone":"+49 9181/9984",
    "sg:postcode":"92318",
    "sg:province":"Bayern",
    "wof:name":"Reha Vitalcenter Sossau",
    "wof:placetype":"venue"
},
  "geometry": {"coordinates":[11.45645,49.270897],"type":"Point"}
}