{
  "type": "Feature",
  "properties": {
    "iso:country":"DE",
    "sg:address":"Schulweg 47",
    "sg:city":"Hatten",
    "sg:phone":"+49 4481/8772",
    "sg:postcode":"26209",
    "sg:province":"Niedersachsen",
    "wof:name":"D\u00fc\u00dfmann Wohnausstattung Gmbh",
    "wof:placetype":"venue"
},
  "geometry": {"coordinates":[8.27545,53.065315],"type":"Point"}
}