{
  "type": "Feature",
  "properties": {
    "iso:country":"DE",
    "sg:address":"Zollplatz 15",
    "sg:city":"Lorch",
    "sg:phone":"+49 7172/8764",
    "sg:postcode":"73547",
    "sg:province":"Baden-W\u00fcrttemberg",
    "wof:name":"Wolfgang Witossek",
    "wof:placetype":"venue"
},
  "geometry": {"coordinates":[9.6921749115,48.797668457],"type":"Point"}
}