{
  "type": "Feature",
  "properties": {
    "iso:country":"DE",
    "sg:address":"Industriestr 32",
    "sg:city":"Stendal",
    "sg:phone":"+49 3931/213090",
    "sg:postcode":"39576",
    "sg:province":"Sachsen-Anhalt",
    "wof:name":"Wellco-drill Bohrausr\u00fcstungen Gmbh",
    "wof:placetype":"venue"
},
  "geometry": {"coordinates":[11.88677,52.584435],"type":"Point"}
}