{
  "type": "Feature",
  "properties": {
    "iso:country":"DE",
    "sg:address":"Pf\u00e4lzer Str. 13",
    "sg:city":"Brombachtal",
    "sg:phone":"+49 6063/2313",
    "sg:postcode":"64753",
    "sg:province":"Hessen",
    "wof:name":"Otto Muhn",
    "wof:placetype":"venue"
},
  "geometry": {"coordinates":[8.9423046112,49.752822876],"type":"Point"}
}