{
  "type": "Feature",
  "properties": {
    "iso:country":"DE",
    "sg:address":"Gro\u00dfe Str. 16",
    "sg:city":"Vechta",
    "sg:phone":"+49 4441/852233",
    "sg:postcode":"49377",
    "sg:province":"Niedersachsen",
    "wof:name":"Stadtgespr\u00e4ch",
    "wof:placetype":"venue"
},
  "geometry": {"coordinates":[8.2848176956,52.7267303467],"type":"Point"}
}