{
  "type": "Feature",
  "properties": {
    "iso:country":"DE",
    "sg:address":"Dieselstr. 5",
    "sg:city":"Gaimersheim",
    "sg:phone":"+49 8458/30306",
    "sg:postcode":"85080",
    "sg:province":"Bayern",
    "wof:name":"Khw Konstruktionen Gmbh",
    "wof:placetype":"venue"
},
  "geometry": {"coordinates":[11.377857,48.787281],"type":"Point"}
}