{
  "type": "Feature",
  "properties": {
    "iso:country":"DE",
    "sg:address":"Obere Hauptstr. 9",
    "sg:city":"Freising",
    "sg:phone":"+49 8161/92063",
    "sg:postcode":"85354",
    "sg:province":"Bayern",
    "wof:name":"Kaisers Tengelmann Ag",
    "wof:placetype":"venue"
},
  "geometry": {"coordinates":[11.7431564331,48.4001045227],"type":"Point"}
}