{
  "type": "Feature",
  "properties": {
    "iso:country":"DE",
    "sg:address":"Ersbergweg 28",
    "sg:city":"Reutlingen",
    "sg:phone":"+49 7121/550580",
    "sg:postcode":"72770",
    "sg:province":"Baden-W\u00fcrttemberg",
    "wof:name":"H. Mayer Reprografie",
    "wof:placetype":"venue"
},
  "geometry": {"coordinates":[9.1712598801,48.5042152405],"type":"Point"}
}