{
  "type": "Feature",
  "properties": {
    "iso:country":"DE",
    "sg:address":"Melanchthonweg 20",
    "sg:city":"Osnabr\u00fcck",
    "sg:phone":"+49 541/83717",
    "sg:postcode":"49080",
    "sg:province":"Niedersachsen",
    "wof:name":"Diter Sprengelmeyer Architekt",
    "wof:placetype":"venue"
},
  "geometry": {"coordinates":[8.043572,52.25246],"type":"Point"}
}