{
  "type": "Feature",
  "properties": {
    "iso:country":"DE",
    "sg:address":"Grimmelallee 44",
    "sg:city":"Nordhausen",
    "sg:phone":"+49 3631/694810",
    "sg:postcode":"99734",
    "sg:province":"Th\u00fcringen",
    "wof:name":"Haus Der Gesundheit Am Grimmel Gmbh",
    "wof:placetype":"venue"
},
  "geometry": {"coordinates":[10.784208,51.506294],"type":"Point"}
}