{
  "type": "Feature",
  "properties": {
    "iso:country":"DE",
    "sg:address":"Abtsg\u00e4\u00dfchen 11",
    "sg:city":"Frankfurt",
    "sg:phone":"+49 69/628114",
    "sg:postcode":"60594",
    "sg:province":"Hessen",
    "wof:name":"Werner Engineering",
    "wof:placetype":"venue"
},
  "geometry": {"coordinates":[8.6886901855,50.1039924622],"type":"Point"}
}