{
  "type": "Feature",
  "properties": {
    "iso:country":"DE",
    "sg:address":"Riemeisterstr. 148",
    "sg:city":"Berlin",
    "sg:phone":"+49 30/8135926",
    "sg:postcode":"14169",
    "sg:province":"Berlin",
    "wof:name":"Wolfgang Arndt Architekt",
    "wof:placetype":"venue"
},
  "geometry": {"coordinates":[13.252756,52.451988],"type":"Point"}
}