{
  "type": "Feature",
  "properties": {
    "iso:country":"DE",
    "sg:address":"Godenstedter Str. 26",
    "sg:city":"Zeven",
    "sg:phone":"+49 4281/8444",
    "sg:postcode":"27404",
    "sg:province":"Niedersachsen",
    "wof:name":"Hans-wilh. Michaelis",
    "wof:placetype":"venue"
},
  "geometry": {"coordinates":[9.2698888779,53.3002853394],"type":"Point"}
}