{
  "type": "Feature",
  "properties": {
    "iso:country":"DE",
    "sg:address":"K\u00f6nigstor 3-13",
    "sg:city":"Kassel",
    "sg:phone":"+49 4956/17820",
    "sg:postcode":"34117",
    "sg:province":"Hessen",
    "wof:name":"St\u00c4dtische Werke Ag",
    "wof:placetype":"venue"
},
  "geometry": {"coordinates":[9.488092,51.312664],"type":"Point"}
}