{
  "type": "Feature",
  "properties": {
    "iso:country":"DE",
    "sg:address":"Kindelsbergstr. 20",
    "sg:city":"Kreuztal",
    "sg:phone":"+49 2732/26581",
    "sg:postcode":"57223",
    "sg:province":"Nordrhein-Westfalen",
    "wof:name":"Ivg Sa\u00dfmannshausen Gmbh",
    "wof:placetype":"venue"
},
  "geometry": {"coordinates":[8.0085058212,50.9643783569],"type":"Point"}
}