{
  "type": "Feature",
  "properties": {
    "iso:country":"DE",
    "sg:address":"Neumarkt 26",
    "sg:city":"Leipzig",
    "sg:phone":"+49 341/9610210",
    "sg:postcode":"04109",
    "sg:province":"Sachsen",
    "wof:name":"Bausa Gmbh",
    "wof:placetype":"venue"
},
  "geometry": {"coordinates":[12.376152,51.338428],"type":"Point"}
}