{
  "type": "Feature",
  "properties": {
    "iso:country":"DE",
    "sg:address":"Carl-Rei\u00df-Platz 1",
    "sg:city":"Mannheim",
    "sg:phone":"+49 621/410920",
    "sg:postcode":"68165",
    "sg:province":"Baden-W\u00fcrttemberg",
    "wof:name":"Bilfinger Berger Umweltbau Gmbh",
    "wof:placetype":"venue"
},
  "geometry": {"coordinates":[8.4881000519,49.4793701172],"type":"Point"}
}