{
  "type": "Feature",
  "properties": {
    "iso:country":"DE",
    "sg:address":"Dr.-Gessler-Str. 45",
    "sg:city":"Regensburg",
    "sg:phone":"+49 941/998859",
    "sg:postcode":"93051",
    "sg:province":"Bayern",
    "wof:name":"Studio Le Pas",
    "wof:placetype":"venue"
},
  "geometry": {"coordinates":[12.063061,49.006748],"type":"Point"}
}