{
  "type": "Feature",
  "properties": {
    "iso:country":"DE",
    "sg:address":"39264",
    "sg:city":"Walternienburg",
    "sg:postcode":"39264",
    "sg:province":"Sachsen-Anhalt",
    "wof:name":"Evangelisches Pfarramt",
    "wof:placetype":"venue"
},
  "geometry": {"coordinates":[11.938794136,51.9651298523],"type":"Point"}
}