{
  "type": "Feature",
  "properties": {
    "iso:country":"DE",
    "sg:address":"Starenweg 64",
    "sg:city":"Pulheim",
    "sg:phone":"+49 2238/841060",
    "sg:postcode":"50259",
    "sg:province":"Nordrhein-Westfalen",
    "wof:name":"A. Dwornig-becker Rechtsanwalt",
    "wof:placetype":"venue"
},
  "geometry": {"coordinates":[6.8067059517,51.0028686523],"type":"Point"}
}