{
  "type": "Feature",
  "properties": {
    "iso:country":"DE",
    "sg:address":"Hauptstr. 165",
    "sg:city":"H\u00fctschenhausen",
    "sg:phone":"+49 6372/3121",
    "sg:postcode":"66882",
    "sg:province":"Rheinland-Pfalz",
    "wof:name":"Oskar Kurz",
    "wof:placetype":"venue"
},
  "geometry": {"coordinates":[7.4673171043,49.4175491333],"type":"Point"}
}