{
  "type": "Feature",
  "properties": {
    "iso:country":"DE",
    "sg:address":"Diepholzer Str. 6-8",
    "sg:city":"Delmenhorst",
    "sg:postcode":"27751",
    "sg:province":"Niedersachsen",
    "wof:name":"Daso Datenverarbeitung Gmbh \u00fcber Lettershop Wagemann Rolf",
    "wof:placetype":"venue"
},
  "geometry": {"coordinates":[8.6680698395,53.0387916565],"type":"Point"}
}