{
  "type": "Feature",
  "properties": {
    "iso:country":"DE",
    "sg:address":"Welsleber Str. 9",
    "sg:city":"Sch\u00f6nebeck",
    "sg:phone":"+49 3928/65590",
    "sg:postcode":"39218",
    "sg:province":"Sachsen-Anhalt",
    "wof:name":"Boutique Sylvi",
    "wof:placetype":"venue"
},
  "geometry": {"coordinates":[11.724836,52.020283],"type":"Point"}
}