{
  "type": "Feature",
  "properties": {
    "iso:country":"DE",
    "sg:address":"Friedrich-Ebert-Str. 44",
    "sg:city":"D\u00fcsseldorf",
    "sg:phone":"+49 211/354540",
    "sg:postcode":"40210",
    "sg:province":"Nordrhein-Westfalen",
    "wof:name":"Jet-reinigung",
    "wof:placetype":"venue"
},
  "geometry": {"coordinates":[6.790465,51.221428],"type":"Point"}
}