{
  "type": "Feature",
  "properties": {
    "iso:country":"DE",
    "sg:address":"Robert-Bosch-Str. 9",
    "sg:city":"Ostrach",
    "sg:phone":"+49 7585/93240",
    "sg:postcode":"88356",
    "sg:province":"Baden-W\u00fcrttemberg",
    "wof:name":"Helmut Senn Gmbh & Co.",
    "wof:placetype":"venue"
},
  "geometry": {"coordinates":[9.3739690781,47.9427947998],"type":"Point"}
}