{
  "type": "Feature",
  "properties": {
    "iso:country":"DE",
    "sg:address":"Kurhausstr. 6",
    "sg:city":"Bad Kreuznach",
    "sg:phone":"+49 671/31782",
    "sg:postcode":"55543",
    "sg:province":"Rheinland-Pfalz",
    "wof:name":"Sozialberatung F. Werdende M\u00fctter-diak. Werk",
    "wof:placetype":"venue"
},
  "geometry": {"coordinates":[7.856881,49.844196],"type":"Point"}
}