{
  "type": "Feature",
  "properties": {
    "iso:country":"DE",
    "sg:address":"Fr\u00fchgasse 3",
    "sg:city":"Insingen",
    "sg:phone":"+49 9869/266",
    "sg:postcode":"91610",
    "sg:province":"Bayern",
    "wof:name":"Friedrich Brand",
    "wof:placetype":"venue"
},
  "geometry": {"coordinates":[10.165346,49.303417],"type":"Point"}
}