{
  "type": "Feature",
  "properties": {
    "iso:country":"DE",
    "sg:address":"Raiserstr 7",
    "sg:city":"G\u00fcnzburg",
    "sg:phone":"+49 8221/8055",
    "sg:postcode":"89312",
    "sg:province":"Bayern",
    "wof:name":"Elwatronic Inh. Franz Josef Wagner",
    "wof:placetype":"venue"
},
  "geometry": {"coordinates":[10.261521,48.453915],"type":"Point"}
}