{
  "type": "Feature",
  "properties": {
    "iso:country":"DE",
    "sg:address":"Gewerbering.6",
    "sg:city":"Pocking",
    "sg:phone":"+49 8531/41875",
    "sg:postcode":"94060",
    "sg:province":"Bayern",
    "wof:name":"G\u00dcnther Sommer",
    "wof:placetype":"venue"
},
  "geometry": {"coordinates":[13.3027639389,48.4067649841],"type":"Point"}
}