{
  "type": "Feature",
  "properties": {
    "iso:country":"DE",
    "sg:address":"Am Mittelfeld 28",
    "sg:city":"Dahlenburg",
    "sg:phone":"+49 5851/979799",
    "sg:postcode":"21368",
    "sg:province":"Niedersachsen",
    "wof:name":"Thorsten Pagel",
    "wof:placetype":"venue"
},
  "geometry": {"coordinates":[10.7215900421,53.1901817322],"type":"Point"}
}