{
  "type": "Feature",
  "properties": {
    "iso:country":"DE",
    "sg:address":"G\u00f6ttinger Str. 33",
    "sg:city":"Northeim",
    "sg:phone":"+49 5551/97330",
    "sg:postcode":"37154",
    "sg:province":"Niedersachsen",
    "wof:name":"Icn-instruments Gmbh",
    "wof:placetype":"venue"
},
  "geometry": {"coordinates":[9.992185,51.700397],"type":"Point"}
}