{
  "type": "Feature",
  "properties": {
    "iso:country":"DE",
    "sg:address":"Maubacher Str. 1",
    "sg:city":"Kreuzau",
    "sg:phone":"+49 2422/901216",
    "sg:postcode":"52372",
    "sg:province":"Nordrhein-Westfalen",
    "wof:name":"Pf Teppichdiscount Gmbh",
    "wof:placetype":"venue"
},
  "geometry": {"coordinates":[6.4813699722,50.7400512695],"type":"Point"}
}