{
  "type": "Feature",
  "properties": {
    "iso:country":"DE",
    "sg:address":"St.-Georgs-Str. 19",
    "sg:city":"Buttenwiesen",
    "sg:phone":"+49 8274/388",
    "sg:postcode":"86647",
    "sg:province":"Bayern",
    "wof:name":"Matthias M\u00fcller",
    "wof:placetype":"venue"
},
  "geometry": {"coordinates":[10.746585,48.58762],"type":"Point"}
}