{
  "type": "Feature",
  "properties": {
    "iso:country":"DE",
    "sg:address":"Friedhofstr. 23",
    "sg:city":"Wilkau-Ha\u00dflau",
    "sg:postcode":"08112",
    "sg:province":"Sachsen",
    "wof:name":"W. Schwalbe",
    "wof:placetype":"venue"
},
  "geometry": {"coordinates":[12.5201587677,50.6784591675],"type":"Point"}
}