{
  "type": "Feature",
  "properties": {
    "iso:country":"DE",
    "sg:address":"Hedelfinger Str. 32",
    "sg:city":"Esslingen",
    "sg:phone":"+49 711/381031",
    "sg:postcode":"73734",
    "sg:province":"Baden-W\u00fcrttemberg",
    "wof:name":"Martin Gerecke",
    "wof:placetype":"venue"
},
  "geometry": {"coordinates":[9.29572,48.737957],"type":"Point"}
}