{
  "type": "Feature",
  "properties": {
    "iso:country":"DE",
    "sg:address":"Wilhelm-Hurtz-Str. 3",
    "sg:city":"Gummersbach",
    "sg:phone":"+49 2261/67427",
    "sg:postcode":"51643",
    "sg:province":"Nordrhein-Westfalen",
    "wof:name":"Chemfiber Faser Im- Und Export",
    "wof:placetype":"venue"
},
  "geometry": {"coordinates":[7.5671281815,51.0184707642],"type":"Point"}
}