{
  "type": "Feature",
  "properties": {
    "iso:country":"DE",
    "sg:address":"S\u00f6llingstr. 3",
    "sg:city":"Essen",
    "sg:phone":"+49 201/223437",
    "sg:postcode":"45127",
    "sg:province":"Nordrhein-Westfalen",
    "wof:name":"Letter Press Beschriftungen Vertriebs Gmbh",
    "wof:placetype":"venue"
},
  "geometry": {"coordinates":[7.020333,51.455334],"type":"Point"}
}