{
  "type": "Feature",
  "properties": {
    "iso:country":"DE",
    "sg:address":"Oschatzer Str. 16",
    "sg:city":"D\u00f6beln",
    "sg:phone":"+49 3431/571797",
    "sg:postcode":"04720",
    "sg:province":"Sachsen",
    "wof:name":"Karl-heinz Liers",
    "wof:placetype":"venue"
},
  "geometry": {"coordinates":[13.128660202,51.1262817383],"type":"Point"}
}