{
  "type": "Feature",
  "properties": {
    "iso:country":"DE",
    "sg:address":"Alte Landstr. 2",
    "sg:city":"Kosel",
    "sg:phone":"+49 4354/1320",
    "sg:postcode":"24354",
    "sg:province":"Schleswig-Holstein",
    "wof:name":"Landgasthaus Koseler Hof",
    "wof:placetype":"venue"
},
  "geometry": {"coordinates":[9.7548694611,54.5054397583],"type":"Point"}
}