{
  "type": "Feature",
  "properties": {
    "iso:country":"DE",
    "sg:address":"Basaltweg 33",
    "sg:city":"Hamburg",
    "sg:phone":"+49 40/6024332",
    "sg:postcode":"22395",
    "sg:province":"Hamburg",
    "wof:name":"Bernd Clasen Gmbh",
    "wof:placetype":"venue"
},
  "geometry": {"coordinates":[10.092171669,53.6571960449],"type":"Point"}
}