{
  "type": "Feature",
  "properties": {
    "iso:country":"DE",
    "sg:address":"Torgauer Str. 66",
    "sg:city":"Uebigau",
    "sg:phone":"+49 35365/87468",
    "sg:postcode":"04938",
    "sg:province":"Brandenburg",
    "wof:name":"Lutze Bau",
    "wof:placetype":"venue"
},
  "geometry": {"coordinates":[13.2857904434,51.5909118652],"type":"Point"}
}