{
  "type": "Feature",
  "properties": {
    "iso:country":"DE",
    "sg:address":"Menzelstr. 19",
    "sg:city":"Bielefeld",
    "sg:phone":"+49 521/882362",
    "sg:postcode":"33613",
    "sg:province":"Nordrhein-Westfalen",
    "wof:name":"M. Schorn",
    "wof:placetype":"venue"
},
  "geometry": {"coordinates":[8.506479,52.057972],"type":"Point"}
}