{
  "type": "Feature",
  "properties": {
    "iso:country":"DE",
    "sg:address":"Bahnhofstr. 24",
    "sg:city":"Rees",
    "sg:phone":"+49 2850/7730",
    "sg:postcode":"46459",
    "sg:province":"Nordrhein-Westfalen",
    "wof:name":"A. Krasenbrink",
    "wof:placetype":"venue"
},
  "geometry": {"coordinates":[6.4582858086,51.7737121582],"type":"Point"}
}