{
  "type": "Feature",
  "properties": {
    "iso:country":"DE",
    "sg:address":"Lange Laube 29",
    "sg:city":"Hannover",
    "sg:phone":"+49 511/1238278",
    "sg:postcode":"30159",
    "sg:province":"Niedersachsen",
    "wof:name":"Wedel Und Klasmeier Rechtsanwalt",
    "wof:placetype":"venue"
},
  "geometry": {"coordinates":[9.7271814346,52.37682724],"type":"Point"}
}