{
  "type": "Feature",
  "properties": {
    "iso:country":"DE",
    "sg:address":"Kolpingstr. 29",
    "sg:city":"Kaufering",
    "sg:phone":"+49 8191/64151",
    "sg:postcode":"86916",
    "sg:province":"Bayern",
    "wof:name":"Ralph G\u00f6thel",
    "wof:placetype":"venue"
},
  "geometry": {"coordinates":[10.855531,48.090919],"type":"Point"}
}