{
  "type": "Feature",
  "properties": {
    "iso:country":"DE",
    "sg:address":"Westallee 5",
    "sg:city":"Mogendorf",
    "sg:phone":"+49 2623/7645",
    "sg:postcode":"56424",
    "sg:province":"Rheinland-Pfalz",
    "wof:name":"Dirk M\u00fcller",
    "wof:placetype":"venue"
},
  "geometry": {"coordinates":[7.7553339005,50.49376297],"type":"Point"}
}