{
  "type": "Feature",
  "properties": {
    "iso:country":"DE",
    "sg:address":"Mercedesstr. 61",
    "sg:city":"Stuttgart",
    "sg:phone":"+49 711/2571023",
    "sg:postcode":"70372",
    "sg:province":"Baden-W\u00fcrttemberg",
    "wof:name":"Hans Mayr Gmbh",
    "wof:placetype":"venue"
},
  "geometry": {"coordinates":[9.2296047211,48.7951812744],"type":"Point"}
}