{
  "type": "Feature",
  "properties": {
    "iso:country":"DE",
    "sg:address":"Am Haslenbach 15",
    "sg:city":"Schlierbach",
    "sg:phone":"+49 7021/49944",
    "sg:postcode":"73278",
    "sg:province":"Baden-W\u00fcrttemberg",
    "wof:name":"Scaffidi Gmbh",
    "wof:placetype":"venue"
},
  "geometry": {"coordinates":[9.531268,48.671741],"type":"Point"}
}