{
  "type": "Feature",
  "properties": {
    "iso:country":"DE",
    "sg:address":"Wolfsstr. 3",
    "sg:city":"Schleiden",
    "sg:phone":"+49 2485/1330",
    "sg:postcode":"53937",
    "sg:province":"Nordrhein-Westfalen",
    "wof:name":"Gottfried Wolter Elektroinstallation",
    "wof:placetype":"venue"
},
  "geometry": {"coordinates":[6.407659,50.546085],"type":"Point"}
}