{
  "type": "Feature",
  "properties": {
    "iso:country":"DE",
    "sg:address":"Forststr. 14",
    "sg:city":"M\u00fcnnerstadt",
    "sg:postcode":"97702",
    "sg:province":"Bayern",
    "wof:name":"Rumagidealis Kompostierungs Gmbh",
    "wof:placetype":"venue"
},
  "geometry": {"coordinates":[10.1945400238,50.2490768433],"type":"Point"}
}