{
  "type": "Feature",
  "properties": {
    "iso:country":"DE",
    "sg:address":"Silvanerstr. 2",
    "sg:city":"M\u00f6rstadt",
    "sg:phone":"+49 6247/905375",
    "sg:postcode":"67591",
    "sg:province":"Rheinland-Pfalz",
    "wof:name":"Miller Bauunternehmen Gmbh",
    "wof:placetype":"venue"
},
  "geometry": {"coordinates":[8.258116,49.660423],"type":"Point"}
}