{
  "type": "Feature",
  "properties": {
    "iso:country":"DE",
    "sg:address":"Linderhauser Str. 122",
    "sg:city":"Wuppertal",
    "sg:phone":"+49 202/647001",
    "sg:postcode":"42279",
    "sg:province":"Nordrhein-Westfalen",
    "wof:name":"Haarhaus Getr\u00e4nke Zweigniederlassung Der",
    "wof:placetype":"venue"
},
  "geometry": {"coordinates":[7.250733,51.296997],"type":"Point"}
}