{
  "type": "Feature",
  "properties": {
    "iso:country":"DE",
    "sg:address":"Wiesenstr. 19",
    "sg:city":"Dissen",
    "sg:phone":"+49 5421/613",
    "sg:postcode":"49201",
    "sg:province":"Niedersachsen",
    "wof:name":"Bbs Von Bar Braatz Und Schriever Steuerberatungs-",
    "wof:placetype":"venue"
},
  "geometry": {"coordinates":[8.2042160034,52.1200942993],"type":"Point"}
}