{
  "type": "Feature",
  "properties": {
    "iso:country":"DE",
    "sg:address":"Dresdner Str. 99",
    "sg:city":"G\u00fctersloh",
    "sg:phone":"+49 5241/36137",
    "sg:postcode":"33330",
    "sg:province":"Nordrhein-Westfalen",
    "wof:name":"Ev. Pfarramt Blankenhagen",
    "wof:placetype":"venue"
},
  "geometry": {"coordinates":[8.380979538,51.9093055725],"type":"Point"}
}