{
  "type": "Feature",
  "properties": {
    "iso:country":"DE",
    "sg:address":"Unterberge 122",
    "sg:city":"Jessen",
    "sg:phone":"+49 3537/215623",
    "sg:postcode":"06917",
    "sg:province":"Sachsen-Anhalt",
    "wof:name":"Bernd Hopfchen",
    "wof:placetype":"venue"
},
  "geometry": {"coordinates":[12.8246116638,51.7881736755],"type":"Point"}
}