{
  "type": "Feature",
  "properties": {
    "iso:country":"DE",
    "sg:address":"Hofstattstr. 17",
    "sg:city":"Reutlingen",
    "sg:phone":"+49 4962/5276744",
    "sg:postcode":"72764",
    "sg:province":"Baden-W\u00fcrttemberg",
    "wof:name":"Koberg Gbr.",
    "wof:placetype":"venue"
},
  "geometry": {"coordinates":[8.6163988113,49.6440734863],"type":"Point"}
}