{
  "type": "Feature",
  "properties": {
    "iso:country":"DE",
    "sg:address":"S\u00fcdendstr. 1",
    "sg:city":"Kronau",
    "sg:postcode":"76709",
    "sg:province":"Baden-W\u00fcrttemberg",
    "wof:name":"Hagendorn & Celec Holzbau Gmbh",
    "wof:placetype":"venue"
},
  "geometry": {"coordinates":[8.6292591095,49.210559845],"type":"Point"}
}