{
  "type": "Feature",
  "properties": {
    "iso:country":"DE",
    "sg:address":"Theo-Neubauer-Str. 10",
    "sg:city":"Oberhof",
    "sg:phone":"+49 36842/20659",
    "sg:postcode":"98559",
    "sg:province":"Th\u00fcringen",
    "wof:name":"H. Kraus",
    "wof:placetype":"venue"
},
  "geometry": {"coordinates":[10.724345,50.706387],"type":"Point"}
}