{
  "type": "Feature",
  "properties": {
    "iso:country":"DE",
    "sg:address":"Uferallee 17",
    "sg:city":"Zeltingen-Rachtig",
    "sg:phone":"+49 6534/940145",
    "sg:postcode":"54492",
    "sg:province":"Rheinland-Pfalz",
    "wof:name":"M-tec Inh. Ralf Und Jens Sch\u00fcler",
    "wof:placetype":"venue"
},
  "geometry": {"coordinates":[7.0150461197,49.9529762268],"type":"Point"}
}