{
  "type": "Feature",
  "properties": {
    "iso:country":"DE",
    "sg:address":"Rottmayrstr. 2",
    "sg:city":"Laufen",
    "sg:phone":"+49 8682/371",
    "sg:postcode":"83410",
    "sg:province":"Bayern",
    "wof:name":"Greimel",
    "wof:placetype":"venue"
},
  "geometry": {"coordinates":[12.9366197586,47.9401473999],"type":"Point"}
}