{
  "type": "Feature",
  "properties": {
    "iso:country":"DE",
    "sg:address":"Bahnhofstr.",
    "sg:city":"Gessertshausen",
    "sg:phone":"+49 8238/2225",
    "sg:postcode":"86459",
    "sg:province":"Bayern",
    "wof:name":"Deutsche Bahn Ag",
    "wof:placetype":"venue"
},
  "geometry": {"coordinates":[10.7337017059,48.3316841125],"type":"Point"}
}