{
  "type": "Feature",
  "properties": {
    "iso:country":"DE",
    "sg:address":"Ostpreu\u00dfendamm 132A",
    "sg:city":"Berlin",
    "sg:phone":"+49 30/8458860",
    "sg:postcode":"12207",
    "sg:province":"Berlin",
    "wof:name":"Dedimax Gesch\u00e4fts- F\u00fchrungsgesellschaft Mbh",
    "wof:placetype":"venue"
},
  "geometry": {"coordinates":[13.3114976883,52.4215126038],"type":"Point"}
}