{
  "type": "Feature",
  "properties": {
    "iso:country":"DE",
    "sg:address":"26486",
    "sg:city":"Wangerooge",
    "sg:phone":"+49 4469/1377",
    "sg:postcode":"26486",
    "sg:province":"Niedersachsen",
    "wof:name":"Eiscafe Venezia",
    "wof:placetype":"venue"
},
  "geometry": {"coordinates":[7.90876,53.784351],"type":"Point"}
}