{
  "type": "Feature",
  "properties": {
    "iso:country":"DE",
    "sg:address":"Gewerbestr. 1",
    "sg:city":"Bernau",
    "sg:phone":"+49 7675/922030",
    "sg:postcode":"79872",
    "sg:province":"Baden-W\u00fcrttemberg",
    "wof:name":"Leonhard Lais",
    "wof:placetype":"venue"
},
  "geometry": {"coordinates":[8.069443,47.793705],"type":"Point"}
}