{
  "type": "Feature",
  "properties": {
    "iso:country":"DE",
    "sg:address":"Vorbecker Str. 2",
    "sg:city":"Gneven",
    "sg:phone":"+49 3860/8210",
    "sg:postcode":"19065",
    "sg:province":"Mecklenburg-Vorpommern",
    "wof:name":"Geologisches B\u00fcro Dr. Klaus Groth Gmbh",
    "wof:placetype":"venue"
},
  "geometry": {"coordinates":[11.5672512054,53.6383857727],"type":"Point"}
}