{
  "type": "Feature",
  "properties": {
    "iso:country":"DE",
    "sg:address":"Markt 5",
    "sg:city":"Zw\u00f6nitz",
    "sg:phone":"+49 37754/77011",
    "sg:postcode":"08297",
    "sg:province":"Sachsen",
    "wof:name":"H. Junghans",
    "wof:placetype":"venue"
},
  "geometry": {"coordinates":[12.813628,50.63047],"type":"Point"}
}