{
  "type": "Feature",
  "properties": {
    "iso:country":"DE",
    "sg:address":"Flurscheideweg 36",
    "sg:city":"Frankfurt",
    "sg:phone":"+49 69/341510",
    "sg:postcode":"65936",
    "sg:province":"Hessen",
    "wof:name":"Rud. Bier\u00e4ugel",
    "wof:placetype":"venue"
},
  "geometry": {"coordinates":[8.576165,50.123867],"type":"Point"}
}