{
  "type": "Feature",
  "properties": {
    "iso:country":"DE",
    "sg:address":"Borchener Str. 29",
    "sg:city":"Paderborn",
    "sg:postcode":"33098",
    "sg:province":"Nordrhein-Westfalen",
    "wof:name":"Ct Marketing Und Service Gmbh",
    "wof:placetype":"venue"
},
  "geometry": {"coordinates":[8.746591568,51.7117919922],"type":"Point"}
}