{
  "type": "Feature",
  "properties": {
    "iso:country":"DE",
    "sg:address":"Bahnhofstr. 30",
    "sg:city":"Bondorf",
    "sg:phone":"+49 7457/93920",
    "sg:postcode":"71149",
    "sg:province":"Baden-W\u00fcrttemberg",
    "wof:name":"Binder Gmbh & Co.",
    "wof:placetype":"venue"
},
  "geometry": {"coordinates":[8.828578,48.523331],"type":"Point"}
}