{
  "type": "Feature",
  "properties": {
    "iso:country":"DE",
    "sg:address":"F\u00f6rgstr. 24",
    "sg:city":"Buchdorf",
    "sg:postcode":"86675",
    "sg:province":"Bayern",
    "wof:name":"Max Neumeier",
    "wof:placetype":"venue"
},
  "geometry": {"coordinates":[10.821067,48.783875],"type":"Point"}
}