{
  "type": "Feature",
  "properties": {
    "iso:country":"DE",
    "sg:address":"Wangener Str. 168",
    "sg:city":"Ravensburg",
    "sg:phone":"+49 751/22594",
    "sg:postcode":"88212",
    "sg:province":"Baden-W\u00fcrttemberg",
    "wof:name":"Lothar Kamps",
    "wof:placetype":"venue"
},
  "geometry": {"coordinates":[9.624306,47.763206],"type":"Point"}
}