{
  "type": "Feature",
  "properties": {
    "iso:country":"DE",
    "sg:address":"Blumenstr. 11",
    "sg:city":"Tauberbischofsheim",
    "sg:postcode":"97941",
    "sg:province":"Baden-W\u00fcrttemberg",
    "wof:name":"Bauernverband Main-tauber-kreis E. V.",
    "wof:placetype":"venue"
},
  "geometry": {"coordinates":[9.6619663239,49.6243553162],"type":"Point"}
}