{
  "type": "Feature",
  "properties": {
    "iso:country":"DE",
    "sg:address":"Eickwisch 4",
    "sg:city":"Buchholz",
    "sg:phone":"+49 4181/33547",
    "sg:postcode":"21244",
    "sg:province":"Niedersachsen",
    "wof:name":"Rolf-dieter F\u00fcllgraf Ingenieur",
    "wof:placetype":"venue"
},
  "geometry": {"coordinates":[9.8682537079,53.3445587158],"type":"Point"}
}