{
  "type": "Feature",
  "properties": {
    "iso:country":"DE",
    "sg:address":"Mergenthalerallee 55",
    "sg:city":"Eschborn",
    "sg:postcode":"65760",
    "sg:province":"Hessen",
    "wof:name":"Andersen Luther Rechtsavwaltsgesellschaft Mbh",
    "wof:placetype":"venue"
},
  "geometry": {"coordinates":[8.5677471161,50.1351852417],"type":"Point"}
}