{
  "type": "Feature",
  "properties": {
    "iso:country":"DE",
    "sg:address":"Vinkenbergstr. 12",
    "sg:city":"Herdecke",
    "sg:postcode":"58313",
    "sg:province":"Nordrhein-Westfalen",
    "wof:name":"Consequence-audio, High-end-audio",
    "wof:placetype":"venue"
},
  "geometry": {"coordinates":[7.440269,51.400024],"type":"Point"}
}