{
  "type": "Feature",
  "properties": {
    "iso:country":"DE",
    "sg:address":"Tramplerstr. 73",
    "sg:city":"Lahr",
    "sg:phone":"+49 7821/3305",
    "sg:postcode":"77933",
    "sg:province":"Baden-W\u00fcrttemberg",
    "wof:name":"Baria Gmbh",
    "wof:placetype":"venue"
},
  "geometry": {"coordinates":[7.854502,48.334358],"type":"Point"}
}