{
  "type": "Feature",
  "properties": {
    "iso:country":"DE",
    "sg:address":"B\u00f6gelstr. 8",
    "sg:city":"L\u00fcneburg",
    "sg:phone":"+49 4131/407777",
    "sg:postcode":"21339",
    "sg:province":"Niedersachsen",
    "wof:name":"Amerika",
    "wof:placetype":"venue"
},
  "geometry": {"coordinates":[10.3993215561,53.2407951355],"type":"Point"}
}