{
  "type": "Feature",
  "properties": {
    "iso:country":"DE",
    "sg:address":"Friedenstr. 7",
    "sg:city":"Halle",
    "sg:phone":"+49 345/5226695",
    "sg:postcode":"06114",
    "sg:province":"Sachsen-Anhalt",
    "wof:name":"Christian Knauer Ergotherapiepraxis",
    "wof:placetype":"venue"
},
  "geometry": {"coordinates":[11.963089,51.50296],"type":"Point"}
}