{
  "type": "Feature",
  "properties": {
    "iso:country":"DE",
    "sg:address":"Oberstr. 96",
    "sg:city":"Hamburg",
    "sg:phone":"+49 40/440693",
    "sg:postcode":"20149",
    "sg:province":"Hamburg",
    "wof:name":"Krau\u00df Und B\u00f6ling Architekten",
    "wof:placetype":"venue"
},
  "geometry": {"coordinates":[9.988299,53.577522],"type":"Point"}
}