{
  "type": "Feature",
  "properties": {
    "iso:country":"DE",
    "sg:address":"Annastr. 28",
    "sg:city":"Aachen",
    "sg:phone":"+49 241/156088",
    "sg:postcode":"52062",
    "sg:province":"Nordrhein-Westfalen",
    "wof:name":"Axa Hauptvertretung Winfried Braun E. K.",
    "wof:placetype":"venue"
},
  "geometry": {"coordinates":[6.0814380646,50.7739257812],"type":"Point"}
}