{
  "type": "Feature",
  "properties": {
    "iso:country":"DE",
    "sg:address":"Aschaffenburger Str. 36",
    "sg:city":"Offenbach",
    "sg:phone":"+49 69/891016",
    "sg:postcode":"63073",
    "sg:province":"Hessen",
    "wof:name":"Erich Kipper",
    "wof:placetype":"venue"
},
  "geometry": {"coordinates":[8.805569,50.089081],"type":"Point"}
}