{
  "type": "Feature",
  "properties": {
    "iso:country":"DE",
    "sg:address":"Marktstr.12",
    "sg:city":"Buttenheim",
    "sg:phone":"+49 9545/44660",
    "sg:postcode":"96155",
    "sg:province":"Bayern",
    "wof:name":"St. Georgenbr\u00e4u Buttenheim",
    "wof:placetype":"venue"
},
  "geometry": {"coordinates":[11.0320329666,49.801902771],"type":"Point"}
}