{
  "type": "Feature",
  "properties": {
    "iso:country":"DE",
    "sg:address":"Paulinenstr. 8",
    "sg:city":"Minden",
    "sg:phone":"+49 571/24060",
    "sg:postcode":"32427",
    "sg:province":"Nordrhein-Westfalen",
    "wof:name":"E. Bernard-berlet Steuerberater",
    "wof:placetype":"venue"
},
  "geometry": {"coordinates":[8.9136552811,52.2948722839],"type":"Point"}
}