{
  "type": "Feature",
  "properties": {
    "iso:country":"DE",
    "sg:address":"Horstring 14",
    "sg:city":"Kandel",
    "sg:phone":"+49 7275/61601",
    "sg:postcode":"76870",
    "sg:province":"Rheinland-Pfalz",
    "wof:name":"Dmk Dachdeckerei Mindum Gmbh",
    "wof:placetype":"venue"
},
  "geometry": {"coordinates":[8.1708297729,49.0970344543],"type":"Point"}
}