{
  "type": "Feature",
  "properties": {
    "iso:country":"DE",
    "sg:address":"Marktplatz 10",
    "sg:city":"Nienburg",
    "sg:phone":"+49 34721/22435",
    "sg:postcode":"06429",
    "sg:province":"Sachsen-Anhalt",
    "wof:name":"Elektro-planungs-b\u00fcro",
    "wof:placetype":"venue"
},
  "geometry": {"coordinates":[11.7677116394,51.8367271423],"type":"Point"}
}