{
  "type": "Feature",
  "properties": {
    "iso:country":"DE",
    "sg:address":"Dr.-Zimmermann-Str. 20",
    "sg:city":"Meersburg",
    "sg:phone":"+49 7532/6509",
    "sg:postcode":"88709",
    "sg:province":"Baden-W\u00fcrttemberg",
    "wof:name":"Leopold Holzer",
    "wof:placetype":"venue"
},
  "geometry": {"coordinates":[9.2645435333,47.7025413513],"type":"Point"}
}