{
  "type": "Feature",
  "properties": {
    "iso:country":"DE",
    "sg:address":"Fichtenstr. 6",
    "sg:city":"Fridolfing",
    "sg:phone":"+49 8684/326",
    "sg:postcode":"83413",
    "sg:province":"Bayern",
    "wof:name":"Martha Wolf",
    "wof:placetype":"venue"
},
  "geometry": {"coordinates":[12.818963,47.999645],"type":"Point"}
}