{
  "type": "Feature",
  "properties": {
    "iso:country":"DE",
    "sg:address":"Kapellenberg 18",
    "sg:city":"Bayerbach",
    "sg:phone":"+49 8774/758",
    "sg:postcode":"84092",
    "sg:province":"Bayern",
    "wof:name":"Ludwig Bindhammer Architekt",
    "wof:placetype":"venue"
},
  "geometry": {"coordinates":[12.303007,48.700298],"type":"Point"}
}