{
  "type": "Feature",
  "properties": {
    "iso:country":"DE",
    "sg:address":"Rathausstr. 2",
    "sg:city":"Altentreptow",
    "sg:phone":"+49 3961/212488",
    "sg:postcode":"17087",
    "sg:province":"Mecklenburg-Vorpommern",
    "wof:name":"D. Daniel",
    "wof:placetype":"venue"
},
  "geometry": {"coordinates":[13.2514686584,53.6927108765],"type":"Point"}
}