{
  "type": "Feature",
  "properties": {
    "iso:country":"DE",
    "sg:address":"Rheinstr. 1b",
    "sg:city":"Rheinbreitbach",
    "sg:phone":"+49 2224/4924",
    "sg:postcode":"53619",
    "sg:province":"Rheinland-Pfalz",
    "wof:name":"Helmut Und Karina Lustinger",
    "wof:placetype":"venue"
},
  "geometry": {"coordinates":[7.2281131744,50.6179695129],"type":"Point"}
}