{
  "type": "Feature",
  "properties": {
    "iso:country":"DE",
    "sg:address":"Ludwigstr. 11a",
    "sg:city":"Eggenstein-Leopoldshafen",
    "sg:phone":"+49 721/787878",
    "sg:postcode":"76344",
    "sg:province":"Baden-W\u00fcrttemberg",
    "wof:name":"J\u00fcrgen Kling",
    "wof:placetype":"venue"
},
  "geometry": {"coordinates":[8.392306,49.099331],"type":"Point"}
}