{
  "type": "Feature",
  "properties": {
    "iso:country":"DE",
    "sg:address":"Bahnhofstr. 68",
    "sg:city":"Helpsen",
    "sg:phone":"+49 5724/2886",
    "sg:postcode":"31691",
    "sg:province":"Niedersachsen",
    "wof:name":"Wilfried Wecke E. K.",
    "wof:placetype":"venue"
},
  "geometry": {"coordinates":[9.1194581985,52.3097343445],"type":"Point"}
}