{
  "type": "Feature",
  "properties": {
    "iso:country":"DE",
    "sg:address":"Tulpenweg 4",
    "sg:city":"Brannenburg",
    "sg:phone":"+49 8034/2311",
    "sg:postcode":"83098",
    "sg:province":"Bayern",
    "wof:name":"Josef Siebler",
    "wof:placetype":"venue"
},
  "geometry": {"coordinates":[12.099439,47.74366],"type":"Point"}
}