{
  "type": "Feature",
  "properties": {
    "iso:country":"DE",
    "sg:address":"Wei\u00dfdornweg 8",
    "sg:city":"Ratingen",
    "sg:phone":"+49 2102/474411",
    "sg:postcode":"40880",
    "sg:province":"Nordrhein-Westfalen",
    "wof:name":"Klaus Dings",
    "wof:placetype":"venue"
},
  "geometry": {"coordinates":[6.820305,51.289074],"type":"Point"}
}