{
  "type": "Feature",
  "properties": {
    "iso:country":"DE",
    "sg:address":"Beesenstedter Str. 4",
    "sg:city":"Schwittersdorf",
    "sg:phone":"+49 34773/20259",
    "sg:postcode":"06295",
    "sg:province":"Sachsen-Anhalt",
    "wof:name":"Wolfgang Krost",
    "wof:placetype":"venue"
},
  "geometry": {"coordinates":[11.7104597092,51.5627555847],"type":"Point"}
}