{
  "type": "Feature",
  "properties": {
    "iso:country":"DE",
    "sg:address":"Luitpoldstr. 31",
    "sg:city":"Erlangen",
    "sg:phone":"+49 9131/28282",
    "sg:postcode":"91052",
    "sg:province":"Bayern",
    "wof:name":"Puma-profi-shop R\u00fchl",
    "wof:placetype":"venue"
},
  "geometry": {"coordinates":[11.016917,49.596764],"type":"Point"}
}