{
  "type": "Feature",
  "properties": {
    "iso:country":"DE",
    "sg:address":"Elbchaussee 580",
    "sg:city":"Hamburg",
    "sg:phone":"+49 40/861954",
    "sg:postcode":"22587",
    "sg:province":"Hamburg",
    "wof:name":"Johannes Jungclaus Rechtsanwalt",
    "wof:placetype":"venue"
},
  "geometry": {"coordinates":[9.8125190735,53.5589370728],"type":"Point"}
}