{
  "type": "Feature",
  "properties": {
    "iso:country":"DE",
    "sg:address":"Erler Str. 131",
    "sg:city":"Schermbeck",
    "sg:phone":"+49 2853/957747",
    "sg:postcode":"46514",
    "sg:province":"Nordrhein-Westfalen",
    "wof:name":"Kapselfertigung Herbert Meier Inh. Guido He\u00dfbr\u00fcggen E. K.",
    "wof:placetype":"venue"
},
  "geometry": {"coordinates":[6.8738760948,51.7080459595],"type":"Point"}
}