{
  "type": "Feature",
  "properties": {
    "iso:country":"DE",
    "sg:address":"Uferstr. 36",
    "sg:city":"Dortmund",
    "sg:phone":"+49 231/714770",
    "sg:postcode":"44227",
    "sg:province":"Nordrhein-Westfalen",
    "wof:name":"Dr. Karl-heinz Mertens Steuerberater",
    "wof:placetype":"venue"
},
  "geometry": {"coordinates":[7.4356818199,51.4925231934],"type":"Point"}
}