{
  "type": "Feature",
  "properties": {
    "iso:country":"DE",
    "sg:address":"Roonstr. 73",
    "sg:city":"Oberhausen",
    "sg:phone":"+49 4920/8841013",
    "sg:postcode":"46049",
    "sg:province":"Nordrhein-Westfalen",
    "wof:name":"H.m. Kerff",
    "wof:placetype":"venue"
},
  "geometry": {"coordinates":[6.838724,51.468098],"type":"Point"}
}