{
  "type": "Feature",
  "properties": {
    "iso:country":"DE",
    "sg:address":"Bertkower Str. 9",
    "sg:city":"Goldbeck",
    "sg:phone":"+49 39388/28366",
    "sg:postcode":"39596",
    "sg:province":"Sachsen-Anhalt",
    "wof:name":"Kurt Wohlfahrt",
    "wof:placetype":"venue"
},
  "geometry": {"coordinates":[11.8609333038,52.7170715332],"type":"Point"}
}