{
  "type": "Feature",
  "properties": {
    "iso:country":"DE",
    "sg:address":"Colberger Str. 127",
    "sg:city":"Ummerstadt",
    "sg:phone":"+49 36871/21851",
    "sg:postcode":"98663",
    "sg:province":"Th\u00fcringen",
    "wof:name":"Helmut Vetter",
    "wof:placetype":"venue"
},
  "geometry": {"coordinates":[10.810751,50.260056],"type":"Point"}
}