{
  "type": "Feature",
  "properties": {
    "iso:country":"DE",
    "sg:address":"Leubsdorfer Str. 1",
    "sg:city":"Borstendorf",
    "sg:phone":"+49 37294/1420",
    "sg:postcode":"09579",
    "sg:province":"Sachsen",
    "wof:name":"Ria Haustein",
    "wof:placetype":"venue"
},
  "geometry": {"coordinates":[13.1776208878,50.7729110718],"type":"Point"}
}