{
  "type": "Feature",
  "properties": {
    "iso:country":"DE",
    "sg:address":"Rembrandtweg 14",
    "sg:city":"Norderstedt",
    "sg:postcode":"22846",
    "sg:province":"Schleswig-Holstein",
    "wof:name":"Fachverband Der Handelsvertreter E. V.",
    "wof:placetype":"venue"
},
  "geometry": {"coordinates":[9.9835176468,53.71459198],"type":"Point"}
}