{
  "type": "Feature",
  "properties": {
    "iso:country":"DE",
    "sg:address":"Am Alten Sportplatz 1",
    "sg:city":"Montabaur",
    "sg:postcode":"56410",
    "sg:province":"Rheinland-Pfalz",
    "wof:name":"G. Franz",
    "wof:placetype":"venue"
},
  "geometry": {"coordinates":[7.826491,50.42989],"type":"Point"}
}