{
  "type": "Feature",
  "properties": {
    "iso:country":"DE",
    "sg:address":"Bredowstr. 35",
    "sg:city":"Berlin",
    "sg:phone":"+49 30/3969623",
    "sg:postcode":"10551",
    "sg:province":"Berlin",
    "wof:name":"Karl Thomas Pickert Rechtsanwalt Und Notar",
    "wof:placetype":"venue"
},
  "geometry": {"coordinates":[13.3397636414,52.5297775269],"type":"Point"}
}