{
  "type": "Feature",
  "properties": {
    "iso:country":"DE",
    "sg:address":"Wiener Str. 15",
    "sg:city":"Bornheim",
    "sg:phone":"+49 2227/91630",
    "sg:postcode":"53332",
    "sg:province":"Nordrhein-Westfalen",
    "wof:name":"Peter Kossmann Fachwerkerneuerung Zimmerei",
    "wof:placetype":"venue"
},
  "geometry": {"coordinates":[6.949958,50.7887],"type":"Point"}
}