{
  "type": "Feature",
  "properties": {
    "iso:country":"DE",
    "sg:address":"Cottbuser Str. 26",
    "sg:city":"Tschernitz",
    "sg:phone":"+49 35600/7041",
    "sg:postcode":"03130",
    "sg:province":"Brandenburg",
    "wof:name":"Raiffeisen-handels- Und Dienstleistungsgenossen-",
    "wof:placetype":"venue"
},
  "geometry": {"coordinates":[14.616579,51.579685],"type":"Point"}
}