{
  "type": "Feature",
  "properties": {
    "iso:country":"DE",
    "sg:address":"Untere K\u00e4ferbeinstr. 13",
    "sg:city":"Essenheim",
    "sg:phone":"+49 6136/85510",
    "sg:postcode":"55270",
    "sg:province":"Rheinland-Pfalz",
    "wof:name":"E. Lipp",
    "wof:placetype":"venue"
},
  "geometry": {"coordinates":[8.1554,49.929371],"type":"Point"}
}