{
  "type": "Feature",
  "properties": {
    "iso:country":"DE",
    "sg:address":"Gro\u00dfe Str. 82 - 84",
    "sg:city":"Ibbenb\u00fcren",
    "sg:phone":"+49 5451/17139",
    "sg:postcode":"49477",
    "sg:province":"Nordrhein-Westfalen",
    "wof:name":"Manfred Otto E. K.",
    "wof:placetype":"venue"
},
  "geometry": {"coordinates":[7.71006,52.280323],"type":"Point"}
}