{
  "type": "Feature",
  "properties": {
    "iso:country":"DE",
    "sg:address":"St\u00e4tzlinger Str. 103",
    "sg:city":"Augsburg",
    "sg:phone":"+49 821/723803",
    "sg:postcode":"86165",
    "sg:province":"Bayern",
    "wof:name":"Georg Braun Gmbh",
    "wof:placetype":"venue"
},
  "geometry": {"coordinates":[10.9444541931,48.3795089722],"type":"Point"}
}