{
  "type": "Feature",
  "properties": {
    "iso:country":"DE",
    "sg:address":"Karlstr. 8",
    "sg:city":"Eisenach",
    "sg:phone":"+49 3691/625330",
    "sg:postcode":"99817",
    "sg:province":"Th\u00fcringen",
    "wof:name":"Hypo-bank",
    "wof:placetype":"venue"
},
  "geometry": {"coordinates":[10.321188,50.974903],"type":"Point"}
}