{
  "type": "Feature",
  "properties": {
    "iso:country":"DE",
    "sg:address":"Max-Planck-Str. 12",
    "sg:city":"Spaichingen",
    "sg:phone":"+49 7424/93340",
    "sg:postcode":"78549",
    "sg:province":"Baden-W\u00fcrttemberg",
    "wof:name":"W. Klaiber",
    "wof:placetype":"venue"
},
  "geometry": {"coordinates":[8.7373075485,48.0677032471],"type":"Point"}
}