{
  "type": "Feature",
  "properties": {
    "iso:country":"DE",
    "sg:address":"Schulstr. 10 a",
    "sg:city":"Wiesmoor",
    "sg:phone":"+49 4944/1083",
    "sg:postcode":"26639",
    "sg:province":"Niedersachsen",
    "wof:name":"Gerhard Bengen",
    "wof:placetype":"venue"
},
  "geometry": {"coordinates":[7.733232,53.416496],"type":"Point"}
}