{
  "type": "Feature",
  "properties": {
    "iso:country":"DE",
    "sg:address":"Am Kurpark 29",
    "sg:city":"Garmisch-Partenkirchen",
    "sg:phone":"+49 8821/55749",
    "sg:postcode":"82467",
    "sg:province":"Bayern",
    "wof:name":"Anton Ostler",
    "wof:placetype":"venue"
},
  "geometry": {"coordinates":[11.088114,47.493324],"type":"Point"}
}