{
  "type": "Feature",
  "properties": {
    "iso:country":"DE",
    "sg:address":"Martinsfeld 42",
    "sg:city":"K\u00f6ln",
    "sg:phone":"+49 221/9318930",
    "sg:postcode":"50676",
    "sg:province":"Nordrhein-Westfalen",
    "wof:name":"Erlen & Partner Architekten",
    "wof:placetype":"venue"
},
  "geometry": {"coordinates":[6.950567,50.928864],"type":"Point"}
}