{
  "type": "Feature",
  "properties": {
    "iso:country":"DE",
    "sg:address":"Bachstr. 9",
    "sg:city":"Jena",
    "sg:phone":"+49 3641/24292",
    "sg:postcode":"07743",
    "sg:province":"Th\u00fcringen",
    "wof:name":"Brise",
    "wof:placetype":"venue"
},
  "geometry": {"coordinates":[11.581104,50.929581],"type":"Point"}
}