{
  "type": "Feature",
  "properties": {
    "iso:country":"DE",
    "sg:address":"Streekenweg 12",
    "sg:city":"Hessisch Oldendorf",
    "sg:phone":"+49 5152/1283",
    "sg:postcode":"31840",
    "sg:province":"Niedersachsen",
    "wof:name":"W. Klemme",
    "wof:placetype":"venue"
},
  "geometry": {"coordinates":[9.2399139404,52.1534194946],"type":"Point"}
}