{
  "type": "Feature",
  "properties": {
    "iso:country":"DE",
    "sg:address":"K\u00f6nigstr. 55",
    "sg:city":"Paderborn",
    "sg:phone":"+49 5251/22146",
    "sg:postcode":"33098",
    "sg:province":"Nordrhein-Westfalen",
    "wof:name":"F.-w. Brauns",
    "wof:placetype":"venue"
},
  "geometry": {"coordinates":[8.7491970062,51.719997406],"type":"Point"}
}