{
  "type": "Feature",
  "properties": {
    "iso:country":"DE",
    "sg:address":"Hans-von-Wolzogen-Str. 14",
    "sg:city":"Bayreuth",
    "sg:phone":"+49 921/26867",
    "sg:postcode":"95445",
    "sg:province":"Bayern",
    "wof:name":"Josef Lammel Ingenieur",
    "wof:placetype":"venue"
},
  "geometry": {"coordinates":[11.5721511841,49.9568824768],"type":"Point"}
}