{
  "type": "Feature",
  "properties": {
    "iso:country":"DE",
    "sg:address":"Reiner-Reineccius-Str. 8",
    "sg:city":"Steinheim",
    "sg:phone":"+49 5233/1391",
    "sg:postcode":"32839",
    "sg:province":"Nordrhein-Westfalen",
    "wof:name":"Buchfeld-kosmetik",
    "wof:placetype":"venue"
},
  "geometry": {"coordinates":[9.0970640182,51.8722305298],"type":"Point"}
}