{
  "type": "Feature",
  "properties": {
    "iso:country":"DE",
    "sg:address":"Forststr. 5",
    "sg:city":"Weilheim",
    "sg:phone":"+49 7023/5778",
    "sg:postcode":"73235",
    "sg:province":"Baden-W\u00fcrttemberg",
    "wof:name":"Bernd M\u00fcller Gmbh",
    "wof:placetype":"venue"
},
  "geometry": {"coordinates":[9.5387401581,48.6194114685],"type":"Point"}
}