{
  "type": "Feature",
  "properties": {
    "iso:country":"DE",
    "sg:address":"Friedrichsteiner Str. 10",
    "sg:city":"Berlin",
    "sg:phone":"+49 30/5086093",
    "sg:postcode":"10318",
    "sg:province":"Berlin",
    "wof:name":"Yvonne Herbert",
    "wof:placetype":"venue"
},
  "geometry": {"coordinates":[13.5193328857,52.4855499268],"type":"Point"}
}