{
  "type": "Feature",
  "properties": {
    "iso:country":"DE",
    "sg:address":"Hubertusdamm 41",
    "sg:city":"Berlin",
    "sg:postcode":"13125",
    "sg:province":"Berlin",
    "wof:name":"Heinrich Cornelius",
    "wof:placetype":"venue"
},
  "geometry": {"coordinates":[13.474877,52.618996],"type":"Point"}
}