{
  "type": "Feature",
  "properties": {
    "iso:country":"DE",
    "sg:address":"Gartenstr. 4",
    "sg:city":"Kaltennordheim",
    "sg:phone":"+49 36966/7146",
    "sg:postcode":"36452",
    "sg:province":"Th\u00fcringen",
    "wof:name":"Franko B\u00fcttner",
    "wof:placetype":"venue"
},
  "geometry": {"coordinates":[10.1607351303,50.6281433105],"type":"Point"}
}