{
  "type": "Feature",
  "properties": {
    "iso:country":"DE",
    "sg:address":"Brunnenstr. 17 a",
    "sg:city":"H\u00fctschenhausen",
    "sg:phone":"+49 6371/17581",
    "sg:postcode":"66882",
    "sg:province":"Rheinland-Pfalz",
    "wof:name":"Marianne Scheerer",
    "wof:placetype":"venue"
},
  "geometry": {"coordinates":[7.4982089996,49.4330978394],"type":"Point"}
}