{
  "type": "Feature",
  "properties": {
    "iso:country":"DE",
    "sg:address":"Bahnhofstr. 24",
    "sg:city":"Giengen",
    "sg:phone":"+49 7322/7286",
    "sg:postcode":"89537",
    "sg:province":"Baden-W\u00fcrttemberg",
    "wof:name":"Bierkr\u00fcgle",
    "wof:placetype":"venue"
},
  "geometry": {"coordinates":[10.2393217087,48.6198120117],"type":"Point"}
}