{
  "type": "Feature",
  "properties": {
    "iso:country":"DE",
    "sg:address":"Amthausstr. 15",
    "sg:city":"Langenargen",
    "sg:phone":"+49 7543/499401",
    "sg:postcode":"88085",
    "sg:province":"Baden-W\u00fcrttemberg",
    "wof:name":"Pion Unternehmensberatung F\u00fcr Softwareentwicklung Und",
    "wof:placetype":"venue"
},
  "geometry": {"coordinates":[9.545508,47.595341],"type":"Point"}
}