{
  "type": "Feature",
  "properties": {
    "iso:country":"DE",
    "sg:address":"Hof Wildstruth",
    "sg:city":"Singhofen",
    "sg:phone":"+49 2604/7300",
    "sg:postcode":"56379",
    "sg:province":"Rheinland-Pfalz",
    "wof:name":"Gerhard Kaiser",
    "wof:placetype":"venue"
},
  "geometry": {"coordinates":[7.834546,50.290642],"type":"Point"}
}