{
  "type": "Feature",
  "properties": {
    "iso:country":"DE",
    "sg:address":"G\u00e4nsberg 4",
    "sg:city":"Obersch\u00f6negg",
    "sg:phone":"+49 8333/3128",
    "sg:postcode":"87770",
    "sg:province":"Bayern",
    "wof:name":"Maurus Sch\u00e4fer",
    "wof:placetype":"venue"
},
  "geometry": {"coordinates":[10.272265,48.13216],"type":"Point"}
}