{
  "type": "Feature",
  "properties": {
    "iso:country":"DE",
    "sg:address":"Osterberg 8",
    "sg:city":"Bad Bentheim",
    "sg:phone":"+49 5922/7780",
    "sg:postcode":"48455",
    "sg:province":"Niedersachsen",
    "wof:name":"Deilmann-montan Gmbh",
    "wof:placetype":"venue"
},
  "geometry": {"coordinates":[7.176649,52.301575],"type":"Point"}
}