{
  "type": "Feature",
  "properties": {
    "iso:country":"DE",
    "sg:address":"Ludwigstr. 21",
    "sg:city":"Hof",
    "sg:phone":"+49 9281/3099",
    "sg:postcode":"95028",
    "sg:province":"Bayern",
    "wof:name":"Klaus Michael",
    "wof:placetype":"venue"
},
  "geometry": {"coordinates":[11.9191579819,50.3222160339],"type":"Point"}
}