{
  "type": "Feature",
  "properties": {
    "iso:country":"DE",
    "sg:address":"Theodor-Heuss-Str. 9",
    "sg:city":"Stuttgart",
    "sg:phone":"+49 711/162101",
    "sg:postcode":"70174",
    "sg:province":"Baden-W\u00fcrttemberg",
    "wof:name":"Victoria Lebensversicherung Ag",
    "wof:placetype":"venue"
},
  "geometry": {"coordinates":[9.1744909286,48.7773246765],"type":"Point"}
}