{
  "type": "Feature",
  "properties": {
    "iso:country":"DE",
    "sg:address":"G\u00fcterhallenstr. 37h",
    "sg:city":"Worms",
    "sg:phone":"+49 6241/51821",
    "sg:postcode":"67549",
    "sg:province":"Rheinland-Pfalz",
    "wof:name":"Klaus K\u00f6hler",
    "wof:placetype":"venue"
},
  "geometry": {"coordinates":[8.3551092148,49.6377372742],"type":"Point"}
}