{
  "type": "Feature",
  "properties": {
    "iso:country":"DE",
    "sg:address":"F\u00fcrstenstr. 14",
    "sg:city":"Mintraching",
    "sg:phone":"+49 9406/450",
    "sg:postcode":"93098",
    "sg:province":"Bayern",
    "wof:name":"Josef Weinzierl",
    "wof:placetype":"venue"
},
  "geometry": {"coordinates":[12.288591,48.92276],"type":"Point"}
}