{
  "type": "Feature",
  "properties": {
    "iso:country":"DE",
    "sg:address":"Buddestr. 103",
    "sg:city":"Krefeld",
    "sg:phone":"+49 2151/541120",
    "sg:postcode":"47809",
    "sg:province":"Nordrhein-Westfalen",
    "wof:name":"Hildegardis-apotheke",
    "wof:placetype":"venue"
},
  "geometry": {"coordinates":[6.611361,51.332905],"type":"Point"}
}