{
  "type": "Feature",
  "properties": {
    "iso:country":"DE",
    "sg:address":"Bauhausstr. 46",
    "sg:city":"Ludwigshafen",
    "sg:phone":"+49 621/654242",
    "sg:postcode":"67069",
    "sg:province":"Rheinland-Pfalz",
    "wof:name":"Culinex Becker Gmbh",
    "wof:placetype":"venue"
},
  "geometry": {"coordinates":[8.3956260681,49.5201797485],"type":"Point"}
}