{
  "type": "Feature",
  "properties": {
    "iso:country":"DE",
    "sg:address":"Blumenstr. 19",
    "sg:city":"Stutensee",
    "sg:phone":"+49 7244/92253",
    "sg:postcode":"76297",
    "sg:province":"Baden-W\u00fcrttemberg",
    "wof:name":"Stefan Kutscher",
    "wof:placetype":"venue"
},
  "geometry": {"coordinates":[8.466586113,49.0617446899],"type":"Point"}
}