{
  "type": "Feature",
  "properties": {
    "iso:country":"DE",
    "sg:address":"K\u00e4the-Kollwitz-Str. 9",
    "sg:city":"Springe",
    "sg:phone":"+49 5041/94190",
    "sg:postcode":"31832",
    "sg:province":"Niedersachsen",
    "wof:name":"Gustav Schlichting Steuerbevollm\u00e4chtigter",
    "wof:placetype":"venue"
},
  "geometry": {"coordinates":[9.5666790009,52.2135772705],"type":"Point"}
}