{
  "type": "Feature",
  "properties": {
    "iso:country":"DE",
    "sg:address":"Bahnhofstr. 34",
    "sg:city":"Bad Endorf",
    "sg:phone":"+49 8053/49948",
    "sg:postcode":"83093",
    "sg:province":"Bayern",
    "wof:name":"M\u00f6bel Feil Gmbh",
    "wof:placetype":"venue"
},
  "geometry": {"coordinates":[12.3007535934,47.90574646],"type":"Point"}
}