{
  "type": "Feature",
  "properties": {
    "iso:country":"DE",
    "sg:address":"Kronstadter Str. 50",
    "sg:city":"M\u00fcnchen",
    "sg:phone":"+49 89/1281",
    "sg:postcode":"81677",
    "sg:province":"Bayern",
    "wof:name":"Deutsche Bahn Ag",
    "wof:placetype":"venue"
},
  "geometry": {"coordinates":[11.648150444,48.138759613],"type":"Point"}
}