{
  "type": "Feature",
  "properties": {
    "iso:country":"DE",
    "sg:address":"Diezer Str. 63",
    "sg:city":"Limburg",
    "sg:phone":"+49 6431/22494",
    "sg:postcode":"65549",
    "sg:province":"Hessen",
    "wof:name":"Balkanrestaurant Dubrovnik",
    "wof:placetype":"venue"
},
  "geometry": {"coordinates":[8.0526609421,50.3839225769],"type":"Point"}
}