{
  "type": "Feature",
  "properties": {
    "iso:country":"DE",
    "sg:address":"K\u00f6ppelsdorfer Str. 18",
    "sg:city":"Sonneberg",
    "sg:phone":"+49 3675/81981",
    "sg:postcode":"96515",
    "sg:province":"Th\u00fcringen",
    "wof:name":"Ep Stein Inh. Detlef Stein",
    "wof:placetype":"venue"
},
  "geometry": {"coordinates":[11.1711359024,50.3589706421],"type":"Point"}
}