{
  "type": "Feature",
  "properties": {
    "iso:country":"DE",
    "sg:address":"St.-Barbara-Str.",
    "sg:city":"P\u00fcttlingen",
    "sg:postcode":"66346",
    "sg:province":"Saarland",
    "wof:name":"Mehrzweckhalle St. Barbara",
    "wof:placetype":"venue"
},
  "geometry": {"coordinates":[6.911102,49.278248],"type":"Point"}
}