{
  "type": "Feature",
  "properties": {
    "iso:country":"DE",
    "sg:address":"Am Seigen 17",
    "sg:city":"Roding",
    "sg:phone":"+49 9461/2720",
    "sg:postcode":"93426",
    "sg:province":"Bayern",
    "wof:name":"Anton Heindl",
    "wof:placetype":"venue"
},
  "geometry": {"coordinates":[12.524309,49.195499],"type":"Point"}
}