{
  "type": "Feature",
  "properties": {
    "iso:country":"DE",
    "sg:address":"An der Trift 40",
    "sg:city":"Z\u00fclpich",
    "sg:postcode":"53909",
    "sg:province":"Nordrhein-Westfalen",
    "wof:name":"Mauel & Wolff Bauunternehmung Gmbh",
    "wof:placetype":"venue"
},
  "geometry": {"coordinates":[6.6939349174,50.6573944092],"type":"Point"}
}