{
  "type": "Feature",
  "properties": {
    "iso:country":"DE",
    "sg:address":"Fraunhoferstr. 8",
    "sg:city":"Martinsried",
    "sg:phone":"+49 89/899190",
    "sg:postcode":"82152",
    "sg:province":"Bayern",
    "wof:name":"Sportive Werbeagentur Gmbh & Co Absatz Idee Kg",
    "wof:placetype":"venue"
},
  "geometry": {"coordinates":[11.448147,48.109818],"type":"Point"}
}