{
  "type": "Feature",
  "properties": {
    "iso:country":"DE",
    "sg:address":"Marie-Curie-Str. 6",
    "sg:city":"Fellbach",
    "sg:postcode":"70736",
    "sg:province":"Baden-W\u00fcrttemberg",
    "wof:name":"Gesellschaft F\u00fcr Schall- Und Schwingungstechnik Mbh",
    "wof:placetype":"venue"
},
  "geometry": {"coordinates":[9.283285,48.82098],"type":"Point"}
}