{
  "type": "Feature",
  "properties": {
    "iso:country":"DE",
    "sg:address":"Wetterburger Str. 15",
    "sg:city":"Bad Arolsen",
    "sg:phone":"+49 5691/3744",
    "sg:postcode":"34454",
    "sg:province":"Hessen",
    "wof:name":"Pension Josef Robitsch",
    "wof:placetype":"venue"
},
  "geometry": {"coordinates":[9.0252370834,51.3783912659],"type":"Point"}
}