{
  "type": "Feature",
  "properties": {
    "iso:country":"DE",
    "sg:address":"Scheelenkamp 19",
    "sg:city":"Garbsen",
    "sg:phone":"+49 5131/6607",
    "sg:postcode":"30827",
    "sg:province":"Niedersachsen",
    "wof:name":"Heinz Fabian Gmbh",
    "wof:placetype":"venue"
},
  "geometry": {"coordinates":[9.618278,52.432262],"type":"Point"}
}