{
  "type": "Feature",
  "properties": {
    "iso:country":"DE",
    "sg:address":"Heiligengeiststr. 9",
    "sg:city":"Oldenburg",
    "sg:phone":"+49 441/14060",
    "sg:postcode":"26121",
    "sg:province":"Niedersachsen",
    "wof:name":"Lbs Immobilien Gmbh",
    "wof:placetype":"venue"
},
  "geometry": {"coordinates":[8.2134914398,53.144733429],"type":"Point"}
}