{
  "type": "Feature",
  "properties": {
    "iso:country":"DE",
    "sg:address":"Th\u00fcringer Weg 72",
    "sg:city":"Paderborn",
    "sg:phone":"+49 5251/4619",
    "sg:postcode":"33102",
    "sg:province":"Nordrhein-Westfalen",
    "wof:name":"Dres Pape Verwaltungs- Und Beteiligungs-gmbh",
    "wof:placetype":"venue"
},
  "geometry": {"coordinates":[8.7626867294,51.7406616211],"type":"Point"}
}