{
  "type": "Feature",
  "properties": {
    "iso:country":"DE",
    "sg:address":"Kreuznacher Str. 43c",
    "sg:city":"Stuttgart",
    "sg:phone":"+49 711/560068",
    "sg:postcode":"70372",
    "sg:province":"Baden-W\u00fcrttemberg",
    "wof:name":"Redaktion Der Weg Zum Ziel S\u00fcddeutscher Verein F. Evan-",
    "wof:placetype":"venue"
},
  "geometry": {"coordinates":[9.221950531,48.8036499023],"type":"Point"}
}