{
  "type": "Feature",
  "properties": {
    "iso:country":"DE",
    "sg:address":"Kirchplatz 9",
    "sg:city":"Gera",
    "sg:phone":"+49 365/413597",
    "sg:postcode":"07552",
    "sg:province":"Th\u00fcringen",
    "wof:name":"Bernd Mo\u00dfner",
    "wof:placetype":"venue"
},
  "geometry": {"coordinates":[12.081221,50.908916],"type":"Point"}
}