{
  "type": "Feature",
  "properties": {
    "iso:country":"DE",
    "sg:address":"Kiefholzstr. 4",
    "sg:city":"Haldensleben",
    "sg:phone":"+49 3904/42098",
    "sg:postcode":"39340",
    "sg:province":"Sachsen-Anhalt",
    "wof:name":"Apotheke Am Wald",
    "wof:placetype":"venue"
},
  "geometry": {"coordinates":[11.37155,52.283936],"type":"Point"}
}