{
  "type": "Feature",
  "properties": {
    "iso:country":"DE",
    "sg:address":"Burgstr. 19",
    "sg:city":"Gelnhausen",
    "sg:phone":"+49 6051/2915",
    "sg:postcode":"63571",
    "sg:province":"Hessen",
    "wof:name":"Hotel Burgsch\u00e4nke",
    "wof:placetype":"venue"
},
  "geometry": {"coordinates":[9.1943941116,50.2002067566],"type":"Point"}
}