{
  "type": "Feature",
  "properties": {
    "iso:country":"DE",
    "sg:address":"Kurze Str. 1",
    "sg:city":"Naila",
    "sg:phone":"+49 9282/5859",
    "sg:postcode":"95119",
    "sg:province":"Bayern",
    "wof:name":"Schmidt Inh. Wilfried Schmidt",
    "wof:placetype":"venue"
},
  "geometry": {"coordinates":[11.7085952759,50.3295936584],"type":"Point"}
}