{
  "type": "Feature",
  "properties": {
    "iso:country":"DE",
    "sg:address":"Antersdorfer Str. 3",
    "sg:city":"Zell",
    "sg:phone":"+49 9468/251",
    "sg:postcode":"93199",
    "sg:province":"Bayern",
    "wof:name":"Alfred Schweiger",
    "wof:placetype":"venue"
},
  "geometry": {"coordinates":[12.432328,49.142189],"type":"Point"}
}