{
  "type": "Feature",
  "properties": {
    "iso:country":"DE",
    "sg:address":"Kreuzstr. 57",
    "sg:city":"Hauptstuhl",
    "sg:phone":"+49 6372/3222",
    "sg:postcode":"66851",
    "sg:province":"Rheinland-Pfalz",
    "wof:name":"H. Und . Bosch",
    "wof:placetype":"venue"
},
  "geometry": {"coordinates":[7.490672,49.403194],"type":"Point"}
}