{
  "type": "Feature",
  "properties": {
    "iso:country":"DE",
    "sg:address":"Ebinger Str. 95",
    "sg:city":"Me\u00dfstetten",
    "sg:phone":"+49 7431/6559",
    "sg:postcode":"72469",
    "sg:province":"Baden-W\u00fcrttemberg",
    "wof:name":"Friedrich Roth",
    "wof:placetype":"venue"
},
  "geometry": {"coordinates":[8.9669876099,48.1853866577],"type":"Point"}
}