{
  "type": "Feature",
  "properties": {
    "iso:country":"DE",
    "sg:address":"Obertsroter Str. 3",
    "sg:city":"Gernsbach",
    "sg:phone":"+49 7224/652274",
    "sg:postcode":"76593",
    "sg:province":"Baden-W\u00fcrttemberg",
    "wof:name":"Blume",
    "wof:placetype":"venue"
},
  "geometry": {"coordinates":[8.3469295502,48.7443885803],"type":"Point"}
}