{
  "type": "Feature",
  "properties": {
    "iso:country":"DE",
    "sg:address":"Rosenheimerstr. 71",
    "sg:city":"Brannenburg",
    "sg:phone":"+49 8034",
    "sg:postcode":"83098",
    "sg:province":"Bayern",
    "wof:name":"Us Waren Brannenburg",
    "wof:placetype":"venue"
},
  "geometry": {"coordinates":[12.1030092239,47.7411003113],"type":"Point"}
}