{
  "type": "Feature",
  "properties": {
    "iso:country":"DE",
    "sg:address":"Balbiererstr. 10",
    "sg:city":"F\u00fcrth",
    "sg:phone":"+49 911/705874",
    "sg:postcode":"90763",
    "sg:province":"Bayern",
    "wof:name":"Alex Melnik",
    "wof:placetype":"venue"
},
  "geometry": {"coordinates":[11.0037899017,49.4633140564],"type":"Point"}
}