{
  "type": "Feature",
  "properties": {
    "iso:country":"DE",
    "sg:address":"Blohnstr. 11",
    "sg:city":"Hemmingen",
    "sg:phone":"+49 7150/6374",
    "sg:postcode":"71282",
    "sg:province":"Baden-W\u00fcrttemberg",
    "wof:name":"Hermann Arnold",
    "wof:placetype":"venue"
},
  "geometry": {"coordinates":[9.03242,48.864216],"type":"Point"}
}