{
  "type": "Feature",
  "properties": {
    "iso:country":"DE",
    "sg:address":"Wallstr. 1",
    "sg:city":"Rehau",
    "sg:phone":"+49 9283/1782",
    "sg:postcode":"95111",
    "sg:province":"Bayern",
    "wof:name":"B\u00e4ckerei Am Maxplatz Gmbh",
    "wof:placetype":"venue"
},
  "geometry": {"coordinates":[12.035678,50.248806],"type":"Point"}
}