{
  "type": "Feature",
  "properties": {
    "iso:country":"DE",
    "sg:address":"Markt 11",
    "sg:city":"Hohenm\u00f6lsen",
    "sg:phone":"+49 34441/33093",
    "sg:postcode":"06679",
    "sg:province":"Sachsen-Anhalt",
    "wof:name":"Heike Augustin Drogerie",
    "wof:placetype":"venue"
},
  "geometry": {"coordinates":[12.098179,51.157253],"type":"Point"}
}