{
  "type": "Feature",
  "properties": {
    "iso:country":"DE",
    "sg:address":"Moltkeplatz 34",
    "sg:city":"Essen",
    "sg:phone":"+49 201/8950060",
    "sg:postcode":"45128",
    "sg:province":"Nordrhein-Westfalen",
    "wof:name":"Anderson & Tilch Werbeagentur Gmbh",
    "wof:placetype":"venue"
},
  "geometry": {"coordinates":[7.0230798721,51.4457054138],"type":"Point"}
}