{
  "type": "Feature",
  "properties": {
    "iso:country":"DE",
    "sg:address":"Nikolaus-Knopp-Platz 30",
    "sg:city":"D\u00fcsseldorf",
    "sg:postcode":"40549",
    "sg:province":"Nordrhein-Westfalen",
    "wof:name":"Przediebiorstow Uslug Technic- Mych Alkor Spolka Z Organi-",
    "wof:placetype":"venue"
},
  "geometry": {"coordinates":[6.72117,51.232445],"type":"Point"}
}