{
  "type": "Feature",
  "properties": {
    "iso:country":"DE",
    "sg:address":"Pfeffinger Str. 16",
    "sg:city":"Albstadt",
    "sg:phone":"+49 7432/5712",
    "sg:postcode":"72461",
    "sg:province":"Baden-W\u00fcrttemberg",
    "wof:name":"Helene Conzelmann Beteiligungs Gmbh",
    "wof:placetype":"venue"
},
  "geometry": {"coordinates":[9.011206,48.254219],"type":"Point"}
}