{
  "type": "Feature",
  "properties": {
    "iso:country":"DE",
    "sg:address":"Hagenmarkt 25",
    "sg:city":"Peine",
    "sg:phone":"+49 5171/73275",
    "sg:postcode":"31224",
    "sg:province":"Niedersachsen",
    "wof:name":"Owl Town",
    "wof:placetype":"venue"
},
  "geometry": {"coordinates":[10.2294950485,52.3241996765],"type":"Point"}
}