{
  "type": "Feature",
  "properties": {
    "iso:country":"DE",
    "sg:address":"Manhagener Allee 7",
    "sg:city":"Ahrensburg",
    "sg:phone":"+49 4102/50210",
    "sg:postcode":"22926",
    "sg:province":"Schleswig-Holstein",
    "wof:name":"Logware-logistik-software Gmbh",
    "wof:placetype":"venue"
},
  "geometry": {"coordinates":[10.2401447296,53.6724319458],"type":"Point"}
}