{
  "type": "Feature",
  "properties": {
    "iso:country":"DE",
    "sg:address":"Lachswehrallee 15b",
    "sg:city":"L\u00fcbeck",
    "sg:phone":"+49 451/85682",
    "sg:postcode":"23558",
    "sg:province":"Schleswig-Holstein",
    "wof:name":"Prodomo Bau Gmbh",
    "wof:placetype":"venue"
},
  "geometry": {"coordinates":[10.6750707626,53.8600006104],"type":"Point"}
}