{
  "type": "Feature",
  "properties": {
    "iso:country":"DE",
    "sg:address":"Lakomaer Str. 12",
    "sg:city":"Cottbus",
    "sg:phone":"+49 355/861112",
    "sg:postcode":"03044",
    "sg:province":"Brandenburg",
    "wof:name":"Siegfried Pschuskel",
    "wof:placetype":"venue"
},
  "geometry": {"coordinates":[14.357188,51.790257],"type":"Point"}
}