{
  "type": "Feature",
  "properties": {
    "iso:country":"DE",
    "sg:address":"Obertorstr. 4",
    "sg:city":"Schl\u00fcchtern",
    "sg:phone":"+49 6661/5649",
    "sg:postcode":"36381",
    "sg:province":"Hessen",
    "wof:name":"Eiscafe Ca D Oro",
    "wof:placetype":"venue"
},
  "geometry": {"coordinates":[9.524655,50.347378],"type":"Point"}
}