{
  "type": "Feature",
  "properties": {
    "iso:country":"DE",
    "sg:address":"Werneckestr. 22",
    "sg:city":"Holzminden",
    "sg:phone":"+49 5531/2411",
    "sg:postcode":"37603",
    "sg:province":"Niedersachsen",
    "wof:name":"Klaus-g\u00fcnther Horn",
    "wof:placetype":"venue"
},
  "geometry": {"coordinates":[9.486858,51.829643],"type":"Point"}
}