{
  "type": "Feature",
  "properties": {
    "iso:country":"DE",
    "sg:address":"Domplatz 4",
    "sg:city":"Fritzlar",
    "sg:phone":"+49 5622/1374",
    "sg:postcode":"34560",
    "sg:province":"Hessen",
    "wof:name":"Kosmetik Am Dom Eveline Busch-methner",
    "wof:placetype":"venue"
},
  "geometry": {"coordinates":[9.272891,51.130981],"type":"Point"}
}