{
  "type": "Feature",
  "properties": {
    "iso:country":"DE",
    "sg:address":"Hauptstr. 7",
    "sg:city":"Recke",
    "sg:phone":"+49 5453/96218",
    "sg:postcode":"49509",
    "sg:province":"Nordrhein-Westfalen",
    "wof:name":"S. Schenk Rechtsanwalt",
    "wof:placetype":"venue"
},
  "geometry": {"coordinates":[7.7195940018,52.369430542],"type":"Point"}
}