{
  "type": "Feature",
  "properties": {
    "iso:country":"DE",
    "sg:address":"Mayener Str. 10",
    "sg:city":"Bassenheim",
    "sg:phone":"+49 2625/4596",
    "sg:postcode":"56220",
    "sg:province":"Rheinland-Pfalz",
    "wof:name":"Lindenhof",
    "wof:placetype":"venue"
},
  "geometry": {"coordinates":[7.4566178322,50.3586387634],"type":"Point"}
}