{
  "type": "Feature",
  "properties": {
    "iso:country":"DE",
    "sg:address":"Hermann-Steinh\u00e4user-Str. 4",
    "sg:city":"Offenbach",
    "sg:phone":"+49 69/822094",
    "sg:postcode":"63065",
    "sg:province":"Hessen",
    "wof:name":"Shoja Bazargani Idee Gmbh",
    "wof:placetype":"venue"
},
  "geometry": {"coordinates":[8.7698631287,50.1057281494],"type":"Point"}
}