{
  "type": "Feature",
  "properties": {
    "iso:country":"DE",
    "sg:address":"Lindenstr. 26",
    "sg:city":"Lohra",
    "sg:phone":"+49 6462/8429",
    "sg:postcode":"35102",
    "sg:province":"Hessen",
    "wof:name":"Heinrich D\u00f6rr",
    "wof:placetype":"venue"
},
  "geometry": {"coordinates":[8.6337842941,50.7371177673],"type":"Point"}
}