{
  "type": "Feature",
  "properties": {
    "iso:country":"DE",
    "sg:address":"Max-Becher-Str. 13",
    "sg:city":"Steinberg",
    "sg:phone":"+49 37462/7745",
    "sg:postcode":"08237",
    "sg:province":"Sachsen",
    "wof:name":"Wildenauer Tiefbau Gmbh",
    "wof:placetype":"venue"
},
  "geometry": {"coordinates":[12.4818992615,50.5416374207],"type":"Point"}
}