{
  "type": "Feature",
  "properties": {
    "iso:country":"DE",
    "sg:address":"Kaltenbronner Str. 600",
    "sg:city":"Gernsbach",
    "sg:phone":"+49 7224/93390",
    "sg:postcode":"76593",
    "sg:province":"Baden-W\u00fcrttemberg",
    "wof:name":"Hotel Sarbacher Gmbh",
    "wof:placetype":"venue"
},
  "geometry": {"coordinates":[8.4316682816,48.7066001892],"type":"Point"}
}