{
  "type": "Feature",
  "properties": {
    "iso:country":"DE",
    "sg:address":"Birkenallee 3",
    "sg:city":"Wolfegg",
    "sg:phone":"+49 7527/4161",
    "sg:postcode":"88364",
    "sg:province":"Baden-W\u00fcrttemberg",
    "wof:name":"Hans Kranz",
    "wof:placetype":"venue"
},
  "geometry": {"coordinates":[9.7909812927,47.8412628174],"type":"Point"}
}