{
  "type": "Feature",
  "properties": {
    "iso:country":"DE",
    "sg:address":"Waldfeuchter Str. 165",
    "sg:city":"Heinsberg",
    "sg:phone":"+49 2452/7114",
    "sg:postcode":"52525",
    "sg:province":"Nordrhein-Westfalen",
    "wof:name":"Hubert Stepprath",
    "wof:placetype":"venue"
},
  "geometry": {"coordinates":[6.075111866,51.0731124878],"type":"Point"}
}