{
  "type": "Feature",
  "properties": {
    "iso:country":"DE",
    "sg:address":"Hauptstr. 16",
    "sg:city":"Visbek",
    "sg:phone":"+49 4445/2716",
    "sg:postcode":"49429",
    "sg:province":"Niedersachsen",
    "wof:name":"Traugott Landskron",
    "wof:placetype":"venue"
},
  "geometry": {"coordinates":[8.310317,52.836094],"type":"Point"}
}