{
  "type": "Feature",
  "properties": {
    "iso:country":"DE",
    "sg:address":"Juliusplate 6",
    "sg:city":"Berne",
    "sg:phone":"+49 4406/214",
    "sg:postcode":"27804",
    "sg:province":"Niedersachsen",
    "wof:name":"Gastst\u00e4tte J. Habben",
    "wof:placetype":"venue"
},
  "geometry": {"coordinates":[8.5138092041,53.1965789795],"type":"Point"}
}