{
  "type": "Feature",
  "properties": {
    "iso:country":"DE",
    "sg:address":"Bamberger Str. 64a",
    "sg:city":"Bayreuth",
    "sg:phone":"+49 921/31190",
    "sg:postcode":"95445",
    "sg:province":"Bayern",
    "wof:name":"N. B\u00f6hner",
    "wof:placetype":"venue"
},
  "geometry": {"coordinates":[11.54498,49.936531],"type":"Point"}
}