{
  "type": "Feature",
  "properties": {
    "iso:country":"DE",
    "sg:address":"M\u00fchlenstr. 3",
    "sg:city":"L\u00fcbz",
    "sg:phone":"+49 38731/5110",
    "sg:postcode":"19386",
    "sg:province":"Mecklenburg-Vorpommern",
    "wof:name":"Elde-apotheke Wolfgang Zimmermann",
    "wof:placetype":"venue"
},
  "geometry": {"coordinates":[12.027657,53.462208],"type":"Point"}
}