{
  "type": "Feature",
  "properties": {
    "iso:country":"DE",
    "sg:address":"Westenmauer 39",
    "sg:city":"Kamen",
    "sg:phone":"+49 2307/18410",
    "sg:postcode":"59174",
    "sg:province":"Nordrhein-Westfalen",
    "wof:name":"Creativ-treff Handelsgesell- Schaft Hobby Und Basteln Mbh",
    "wof:placetype":"venue"
},
  "geometry": {"coordinates":[7.657843,51.593727],"type":"Point"}
}