{
  "type": "Feature",
  "properties": {
    "iso:country":"DE",
    "sg:address":"Parkstr 77",
    "sg:city":"Esslingen",
    "sg:phone":"+49 711/382935",
    "sg:postcode":"73734",
    "sg:province":"Baden-W\u00fcrttemberg",
    "wof:name":"Inspiration Designs",
    "wof:placetype":"venue"
},
  "geometry": {"coordinates":[9.2927007675,48.7342147827],"type":"Point"}
}