{
  "type": "Feature",
  "properties": {
    "iso:country":"DE",
    "sg:address":"Borkshagenstr. 9",
    "sg:city":"Arnsberg",
    "sg:phone":"+49 2932/96740",
    "sg:postcode":"59757",
    "sg:province":"Nordrhein-Westfalen",
    "wof:name":"Ssw Stahl-service Westhoff Gmbh",
    "wof:placetype":"venue"
},
  "geometry": {"coordinates":[7.953329,51.428471],"type":"Point"}
}