{
  "type": "Feature",
  "properties": {
    "iso:country":"DE",
    "sg:address":"Brunostr. 16",
    "sg:city":"Ratingen",
    "sg:phone":"+49 2102/702759",
    "sg:postcode":"40878",
    "sg:province":"Nordrhein-Westfalen",
    "wof:name":"Baugesellschaft Welker Mbh",
    "wof:placetype":"venue"
},
  "geometry": {"coordinates":[6.8540968895,51.2968521118],"type":"Point"}
}