{
  "type": "Feature",
  "properties": {
    "iso:country":"DE",
    "sg:address":"Zum Tollberg 11",
    "sg:city":"Hamminkeln",
    "sg:phone":"+49 2852/7190",
    "sg:postcode":"46499",
    "sg:province":"Nordrhein-Westfalen",
    "wof:name":"H. Und W. Schm\u00e4nk Gmbh & Co. Kg",
    "wof:placetype":"venue"
},
  "geometry": {"coordinates":[6.6062521935,51.7658615112],"type":"Point"}
}