{
  "type": "Feature",
  "properties": {
    "iso:country":"DE",
    "sg:address":"Elvirastr. 25",
    "sg:city":"M\u00fcnchen",
    "sg:phone":"+49 89/18703907",
    "sg:postcode":"80636",
    "sg:province":"Bayern",
    "wof:name":"G. Fabbri Deutschland Gmbh",
    "wof:placetype":"venue"
},
  "geometry": {"coordinates":[11.5437469482,48.1479759216],"type":"Point"}
}