{
  "type": "Feature",
  "properties": {
    "iso:country":"DE",
    "sg:address":"Ernsthof 14",
    "sg:city":"Wertheim",
    "sg:phone":"+49 9345/95848",
    "sg:postcode":"97877",
    "sg:province":"Baden-W\u00fcrttemberg",
    "wof:name":"Wert Heim Holzbau Gmbh",
    "wof:placetype":"venue"
},
  "geometry": {"coordinates":[9.4851732254,49.706035614],"type":"Point"}
}