{
  "type": "Feature",
  "properties": {
    "iso:country":"DE",
    "sg:address":"Gasanstaltstr 12",
    "sg:city":"Dresden",
    "sg:phone":"+49 6621/1750",
    "sg:postcode":"01237",
    "sg:province":"Sachsen",
    "wof:name":"Georg B\u00f6rner Chemisches Werk F\u00fcr Dach- Und Bautenschutz Gmbh & Co Kg",
    "wof:placetype":"venue"
},
  "geometry": {"coordinates":[9.743666,50.897663],"type":"Point"}
}