{
  "type": "Feature",
  "properties": {
    "iso:country":"DE",
    "sg:address":"Leckerhorstweg 21",
    "sg:city":"Iserlohn",
    "sg:phone":"+49 2374/2412",
    "sg:postcode":"58642",
    "sg:province":"Nordrhein-Westfalen",
    "wof:name":"Wilhelm B\u00fcrger",
    "wof:placetype":"venue"
},
  "geometry": {"coordinates":[7.640325,51.378632],"type":"Point"}
}