{
  "type": "Feature",
  "properties": {
    "iso:country":"DE",
    "sg:address":"Mittelstr. 30",
    "sg:city":"Lindow",
    "sg:phone":"+49 33933/71553",
    "sg:postcode":"16835",
    "sg:province":"Brandenburg",
    "wof:name":"Restaurant Kircheneck",
    "wof:placetype":"venue"
},
  "geometry": {"coordinates":[12.985912323,52.9696426392],"type":"Point"}
}