{
  "type": "Feature",
  "properties": {
    "iso:country":"DE",
    "sg:address":"Husumer Str. 28",
    "sg:city":"Heide",
    "sg:phone":"+49 481/78710",
    "sg:postcode":"25746",
    "sg:province":"Schleswig-Holstein",
    "wof:name":"Dr. Heino Witt Tierarzt",
    "wof:placetype":"venue"
},
  "geometry": {"coordinates":[9.0904655457,54.1989097595],"type":"Point"}
}