{
  "type": "Feature",
  "properties": {
    "iso:country":"DE",
    "sg:address":"Gerberweg 5",
    "sg:city":"Herford",
    "sg:phone":"+49 5221/58138",
    "sg:postcode":"32051",
    "sg:province":"Nordrhein-Westfalen",
    "wof:name":"Pommernwurst Handelsgesellschaft Mbh",
    "wof:placetype":"venue"
},
  "geometry": {"coordinates":[8.646727562,52.1117401123],"type":"Point"}
}