{
  "type": "Feature",
  "properties": {
    "iso:country":"DE",
    "sg:address":"K\u00e4the-Kollwitz-Str. 11",
    "sg:city":"Lauchhammer",
    "sg:phone":"+49 3574/7165",
    "sg:postcode":"01979",
    "sg:province":"Brandenburg",
    "wof:name":"Michael Flache",
    "wof:placetype":"venue"
},
  "geometry": {"coordinates":[13.751243,51.470181],"type":"Point"}
}