{
  "type": "Feature",
  "properties": {
    "iso:country":"DE",
    "sg:address":"In den Stauden\u00e4ckern 10",
    "sg:city":"Filderstadt",
    "sg:phone":"+49 711/7778864",
    "sg:postcode":"70794",
    "sg:province":"Baden-W\u00fcrttemberg",
    "wof:name":"Gottlob H\u00f6rz",
    "wof:placetype":"venue"
},
  "geometry": {"coordinates":[9.2176198959,48.6455497742],"type":"Point"}
}