{
  "type": "Feature",
  "properties": {
    "iso:country":"DE",
    "sg:address":"Br\u00fcckenstr. 6",
    "sg:city":"Himmelstadt",
    "sg:phone":"+49 9364/1410",
    "sg:postcode":"97267",
    "sg:province":"Bayern",
    "wof:name":"Raiffeisenbank Zellingen Und Um-, Gebung Eg",
    "wof:placetype":"venue"
},
  "geometry": {"coordinates":[9.800718,49.924107],"type":"Point"}
}