{
  "type": "Feature",
  "properties": {
    "iso:country":"DE",
    "sg:address":"Bachstr. 6",
    "sg:city":"Gilserberg",
    "sg:phone":"+49 6696/291",
    "sg:postcode":"34630",
    "sg:province":"Hessen",
    "wof:name":"Gerhard Sch\u00f6mann",
    "wof:placetype":"venue"
},
  "geometry": {"coordinates":[9.0998897552,50.9626731873],"type":"Point"}
}