{
  "type": "Feature",
  "properties": {
    "iso:country":"DE",
    "sg:address":"Hauptstr. 4",
    "sg:city":"Waldenburg",
    "sg:phone":"+49 7942/2165",
    "sg:postcode":"74638",
    "sg:province":"Baden-W\u00fcrttemberg",
    "wof:name":"Pizzeria La Pietra",
    "wof:placetype":"venue"
},
  "geometry": {"coordinates":[9.6423358917,49.1902885437],"type":"Point"}
}