{
  "type": "Feature",
  "properties": {
    "iso:country":"DE",
    "sg:address":"Hinterstr. 19",
    "sg:city":"Duderstadt",
    "sg:phone":"+49 5527/3269",
    "sg:postcode":"37115",
    "sg:province":"Niedersachsen",
    "wof:name":"E. G\u00f6llnitz",
    "wof:placetype":"venue"
},
  "geometry": {"coordinates":[10.257628,51.513237],"type":"Point"}
}