{
  "type": "Feature",
  "properties": {
    "iso:country":"DE",
    "sg:address":"Fasanenweg 18",
    "sg:city":"Leinfelden-Echterdingen",
    "sg:postcode":"70771",
    "sg:province":"Baden-W\u00fcrttemberg",
    "wof:name":"Gesellschaft F\u00fcr Knowhow Transfer In Architektur",
    "wof:placetype":"venue"
},
  "geometry": {"coordinates":[9.1482744217,48.7072677612],"type":"Point"}
}