{
  "type": "Feature",
  "properties": {
    "iso:country":"DE",
    "sg:address":"Bahnhofplatz 4",
    "sg:city":"Herrsching",
    "sg:phone":"+49 8152/3710",
    "sg:postcode":"82211",
    "sg:province":"Bayern",
    "wof:name":"Vr-bank Starnberg-landsberg-herrsching Eg",
    "wof:placetype":"venue"
},
  "geometry": {"coordinates":[11.171386,47.99815],"type":"Point"}
}