{
  "type": "Feature",
  "properties": {
    "iso:country":"DE",
    "sg:address":"Victor-Kretz-Str.2",
    "sg:city":"Gengenbach",
    "sg:phone":"+49 7803",
    "sg:postcode":"77723",
    "sg:province":"Baden-W\u00fcrttemberg",
    "wof:name":"Stadt Gengenbach",
    "wof:placetype":"venue"
},
  "geometry": {"coordinates":[8.015622139,48.4043159485],"type":"Point"}
}