{
  "type": "Feature",
  "properties": {
    "iso:country":"DE",
    "sg:address":"M\u00fchlgrund 1",
    "sg:city":"Backnang",
    "sg:phone":"+49 7191/953700",
    "sg:postcode":"71522",
    "sg:province":"Baden-W\u00fcrttemberg",
    "wof:name":"Haag Verwaltung Und Beteiligung Gmbh",
    "wof:placetype":"venue"
},
  "geometry": {"coordinates":[9.4429998398,48.9301528931],"type":"Point"}
}