{
  "type": "Feature",
  "properties": {
    "iso:country":"DE",
    "sg:address":"Vlothenstr. 12",
    "sg:city":"\u00dcbach-Palenberg",
    "sg:phone":"+49 2451/41513",
    "sg:postcode":"52531",
    "sg:province":"Nordrhein-Westfalen",
    "wof:name":"Alfred Janssen Architekt",
    "wof:placetype":"venue"
},
  "geometry": {"coordinates":[6.126189,50.917889],"type":"Point"}
}