{
  "type": "Feature",
  "properties": {
    "iso:country":"DE",
    "sg:address":"Bentheimer Str. 14",
    "sg:city":"Sch\u00fcttorf",
    "sg:phone":"+49 5923/4500",
    "sg:postcode":"48465",
    "sg:province":"Niedersachsen",
    "wof:name":"Bernhard Wenning Elektro Mstr.",
    "wof:placetype":"venue"
},
  "geometry": {"coordinates":[7.217439,52.315826],"type":"Point"}
}