{
  "type": "Feature",
  "properties": {
    "iso:country":"DE",
    "sg:address":"Alte Hellersdorfer Str. 142",
    "sg:city":"Berlin",
    "sg:phone":"+49 30/9983523",
    "sg:postcode":"12629",
    "sg:province":"Berlin",
    "wof:name":"M\u00e4rkische-apotheke",
    "wof:placetype":"venue"
},
  "geometry": {"coordinates":[13.592743,52.546581],"type":"Point"}
}