{
  "type": "Feature",
  "properties": {
    "iso:country":"DE",
    "sg:address":"Zum Huchtinger Bahnhof 27",
    "sg:city":"Bremen",
    "sg:phone":"+49 421/5704050",
    "sg:postcode":"28259",
    "sg:province":"Bremen",
    "wof:name":"Diedr. Kieselhorst",
    "wof:placetype":"venue"
},
  "geometry": {"coordinates":[8.737022,53.061722],"type":"Point"}
}