{
  "type": "Feature",
  "properties": {
    "iso:country":"DE",
    "sg:address":"Tutzing",
    "sg:city":"Tutzing",
    "sg:phone":"+49 8158/8041",
    "sg:postcode":"82327",
    "sg:province":"Bayern",
    "wof:name":"Raiffeisenbank M\u00fcnchen Eg",
    "wof:placetype":"venue"
},
  "geometry": {"coordinates":[11.2479,47.91597],"type":"Point"}
}