{
  "type": "Feature",
  "properties": {
    "iso:country":"DE",
    "sg:address":"Am Solperts-Garten 46",
    "sg:city":"Langenfeld",
    "sg:phone":"+49 2173/977910",
    "sg:postcode":"40764",
    "sg:province":"Nordrhein-Westfalen",
    "wof:name":"Fachberater F\u00fcr Logistik, Lager, Personal, Stapler",
    "wof:placetype":"venue"
},
  "geometry": {"coordinates":[6.922779,51.115627],"type":"Point"}
}