{
  "type": "Feature",
  "properties": {
    "iso:country":"DE",
    "sg:address":"Schmalkalder Str. 110",
    "sg:city":"Tambach-Dietharz",
    "sg:phone":"+49 36252/36169",
    "sg:postcode":"99897",
    "sg:province":"Th\u00fcringen",
    "wof:name":"R. Krau\u00dfer",
    "wof:placetype":"venue"
},
  "geometry": {"coordinates":[10.6079177856,50.7866477966],"type":"Point"}
}