{
  "type": "Feature",
  "properties": {
    "iso:country":"DE",
    "sg:address":"An der Dorfeiche 30",
    "sg:city":"Minden",
    "sg:phone":"+49 571/55670",
    "sg:postcode":"32429",
    "sg:province":"Nordrhein-Westfalen",
    "wof:name":"Heiner Otto Architekt",
    "wof:placetype":"venue"
},
  "geometry": {"coordinates":[8.889297,52.267738],"type":"Point"}
}