{
  "type": "Feature",
  "properties": {
    "iso:country":"DE",
    "sg:address":"D\u00fcneberger Str. 119",
    "sg:city":"Geesthacht",
    "sg:phone":"+49 4152/70041",
    "sg:postcode":"21502",
    "sg:province":"Schleswig-Holstein",
    "wof:name":"Elbe-leasing Gmbh",
    "wof:placetype":"venue"
},
  "geometry": {"coordinates":[10.3540916443,53.4333343506],"type":"Point"}
}