{
  "type": "Feature",
  "properties": {
    "iso:country":"DE",
    "sg:address":"Elsem\u00fchlenweg 101b",
    "sg:city":"B\u00fcnde",
    "sg:phone":"+49 5223/13640",
    "sg:postcode":"32257",
    "sg:province":"Nordrhein-Westfalen",
    "wof:name":"E. Sippel Gmbh",
    "wof:placetype":"venue"
},
  "geometry": {"coordinates":[8.6037549973,52.1897087097],"type":"Point"}
}