{
  "type": "Feature",
  "properties": {
    "iso:country":"DE",
    "sg:address":"Stifelweg 14",
    "sg:city":"Hirschhorn",
    "sg:postcode":"69434",
    "sg:province":"Baden-W\u00fcrttemberg",
    "wof:name":"Grapefruit-samen-extrakt",
    "wof:placetype":"venue"
},
  "geometry": {"coordinates":[8.8953266144,49.4441566467],"type":"Point"}
}