{
  "type": "Feature",
  "properties": {
    "iso:country":"DE",
    "sg:address":"Friesenstr. 6",
    "sg:city":"M\u00fclheim",
    "sg:phone":"+49 208/400367",
    "sg:postcode":"45476",
    "sg:province":"Nordrhein-Westfalen",
    "wof:name":"Antennentechnik Albert Becker Gmbh & Co. Kg",
    "wof:placetype":"venue"
},
  "geometry": {"coordinates":[6.848122,51.446751],"type":"Point"}
}