{
  "type": "Feature",
  "properties": {
    "iso:country":"DE",
    "sg:address":"Dresdener Str. 8",
    "sg:city":"Colditz",
    "sg:phone":"+49 34381/42190",
    "sg:postcode":"04680",
    "sg:province":"Sachsen",
    "wof:name":"Regina T\u00f6pke",
    "wof:placetype":"venue"
},
  "geometry": {"coordinates":[12.808764,51.126423],"type":"Point"}
}