{
  "type": "Feature",
  "properties": {
    "iso:country":"DE",
    "sg:address":"Lechstr. 5 Waldrems",
    "sg:city":"Backnang",
    "sg:phone":"+49 4971/9132200",
    "sg:postcode":"71522",
    "sg:province":"Baden-W\u00fcrttemberg",
    "wof:name":"Idler Fleischwaren Gmbh",
    "wof:placetype":"venue"
},
  "geometry": {"coordinates":[9.4325151443,48.9483757019],"type":"Point"}
}