{
  "type": "Feature",
  "properties": {
    "iso:country":"DE",
    "sg:address":"Br\u00fcckenstr. 65",
    "sg:city":"M\u00fchldorf",
    "sg:postcode":"84453",
    "sg:province":"Bayern",
    "wof:name":"E. & M. Marx Gmbh",
    "wof:placetype":"venue"
},
  "geometry": {"coordinates":[12.5331325531,48.237537384],"type":"Point"}
}