{
  "type": "Feature",
  "properties": {
    "iso:country":"DE",
    "sg:address":"R\u00f6thestr. 8",
    "sg:city":"Kirchhain",
    "sg:phone":"+49 6422/7166",
    "sg:postcode":"35274",
    "sg:province":"Hessen",
    "wof:name":"K. Und L. Bergmann",
    "wof:placetype":"venue"
},
  "geometry": {"coordinates":[8.922353,50.825535],"type":"Point"}
}