{
  "type": "Feature",
  "properties": {
    "iso:country":"DE",
    "sg:address":"Rudolf-Breitscheid-Str. 4",
    "sg:city":"Kahla",
    "sg:phone":"+49 36424/22408",
    "sg:postcode":"07768",
    "sg:province":"Th\u00fcringen",
    "wof:name":"Dieter Wagner",
    "wof:placetype":"venue"
},
  "geometry": {"coordinates":[11.589183,50.803482],"type":"Point"}
}