{
  "type": "Feature",
  "properties": {
    "iso:country":"DE",
    "sg:address":"Boykengang",
    "sg:city":"Oldenburg",
    "sg:phone":"+49 441/26432",
    "sg:postcode":"26122",
    "sg:province":"Niedersachsen",
    "wof:name":"China Restaurant Sammy Inn",
    "wof:placetype":"venue"
},
  "geometry": {"coordinates":[8.2104654312,53.1408538818],"type":"Point"}
}