{
  "type": "Feature",
  "properties": {
    "iso:country":"DE",
    "sg:address":"Suhler Str. 1",
    "sg:city":"Schleusingen",
    "sg:phone":"+49 36841/41348",
    "sg:postcode":"98553",
    "sg:province":"Th\u00fcringen",
    "wof:name":"Finanzdienstleistungsinstitut Thomas K\u00fchner E. K.",
    "wof:placetype":"venue"
},
  "geometry": {"coordinates":[10.7484226227,50.5090446472],"type":"Point"}
}