{
  "type": "Feature",
  "properties": {
    "iso:country":"DE",
    "sg:address":"Arnold-Sommerfeld-Ring 2",
    "sg:city":"Baesweiler",
    "sg:postcode":"52499",
    "sg:province":"Nordrhein-Westfalen",
    "wof:name":"Chemagen Biopolymer- Technologie- Ag",
    "wof:placetype":"venue"
},
  "geometry": {"coordinates":[6.1737298965,50.918510437],"type":"Point"}
}