{
  "type": "Feature",
  "properties": {
    "iso:country":"DE",
    "sg:address":"Lundenerkoog",
    "sg:city":"Lehe",
    "sg:phone":"+49 4882/5084",
    "sg:postcode":"25774",
    "sg:province":"Schleswig-Holstein",
    "wof:name":"Haus Am Deich",
    "wof:placetype":"venue"
},
  "geometry": {"coordinates":[9.021355629,54.3502655029],"type":"Point"}
}