{
  "type": "Feature",
  "properties": {
    "iso:country":"DE",
    "sg:address":"Bahnhofstr. 6",
    "sg:city":"Gerolstein",
    "sg:phone":"+49 6591/3164",
    "sg:postcode":"54568",
    "sg:province":"Rheinland-Pfalz",
    "wof:name":"Arnold Frantzen",
    "wof:placetype":"venue"
},
  "geometry": {"coordinates":[6.658743,50.223251],"type":"Point"}
}