{
  "type": "Feature",
  "properties": {
    "iso:country":"DE",
    "sg:address":"Fellwiesenweg 8",
    "sg:city":"Langenhagen",
    "sg:phone":"+49 511/741329",
    "sg:postcode":"30855",
    "sg:province":"Niedersachsen",
    "wof:name":"Fritz Leiseberg",
    "wof:placetype":"venue"
},
  "geometry": {"coordinates":[9.666583,52.449398],"type":"Point"}
}