{
  "type": "Feature",
  "properties": {
    "iso:country":"DE",
    "sg:address":"Ottostr. 60",
    "sg:city":"Wuppertal",
    "sg:phone":"+49 202/663415",
    "sg:postcode":"42289",
    "sg:province":"Nordrhein-Westfalen",
    "wof:name":"Ev. Pfarramt Immanuelskirche",
    "wof:placetype":"venue"
},
  "geometry": {"coordinates":[7.2083997726,51.2681846619],"type":"Point"}
}