{
  "type": "Feature",
  "properties": {
    "iso:country":"DE",
    "sg:address":"Hauptstr. 46",
    "sg:city":"Neunkirchen-Seelscheid",
    "sg:phone":"+49 2247/2217",
    "sg:postcode":"53819",
    "sg:province":"Nordrhein-Westfalen",
    "wof:name":"Kaufhaus J. Kurtenbach",
    "wof:placetype":"venue"
},
  "geometry": {"coordinates":[7.3339190483,50.8407478333],"type":"Point"}
}