{
  "type": "Feature",
  "properties": {
    "iso:country":"DE",
    "sg:address":"Hauptstr. 14",
    "sg:city":"Kampen",
    "sg:phone":"+49 4651/41626",
    "sg:postcode":"25999",
    "sg:province":"Schleswig-Holstein",
    "wof:name":"Haus Seepferdchen",
    "wof:placetype":"venue"
},
  "geometry": {"coordinates":[8.3426189423,54.9545555115],"type":"Point"}
}