{
  "type": "Feature",
  "properties": {
    "iso:country":"DE",
    "sg:address":"Gartenstr. 43",
    "sg:city":"Kassel",
    "sg:phone":"+49 561/8700404",
    "sg:postcode":"34125",
    "sg:province":"Hessen",
    "wof:name":"Mega-posten Teppichb\u00f6den",
    "wof:placetype":"venue"
},
  "geometry": {"coordinates":[9.5183172226,51.3238067627],"type":"Point"}
}