{
  "type": "Feature",
  "properties": {
    "iso:country":"DE",
    "sg:address":"Gaehtjestr. 27",
    "sg:city":"Eckernf\u00f6rde",
    "sg:phone":"+49 4351/2087",
    "sg:postcode":"24340",
    "sg:province":"Schleswig-Holstein",
    "wof:name":"Heinz Vetter Videothek",
    "wof:placetype":"venue"
},
  "geometry": {"coordinates":[9.8328609467,54.4743919373],"type":"Point"}
}