{
  "type": "Feature",
  "properties": {
    "iso:country":"DE",
    "sg:address":"Niederrheinallee 100",
    "sg:city":"Neukirchen-Vluyn",
    "sg:phone":"+49 2845/5956",
    "sg:postcode":"47506",
    "sg:province":"Nordrhein-Westfalen",
    "wof:name":"Nk-hotel Mondial-gmbh",
    "wof:placetype":"venue"
},
  "geometry": {"coordinates":[6.5717329979,51.4463768005],"type":"Point"}
}