{
  "type": "Feature",
  "properties": {
    "iso:country":"DE",
    "sg:address":"Bachweg 3",
    "sg:city":"G\u00fcntersleben",
    "sg:phone":"+49 9365/5295",
    "sg:postcode":"97261",
    "sg:province":"Bayern",
    "wof:name":"Holz Und Design Schmitt",
    "wof:placetype":"venue"
},
  "geometry": {"coordinates":[9.903986,49.866413],"type":"Point"}
}