{
  "type": "Feature",
  "properties": {
    "iso:country":"DE",
    "sg:address":"Rothenbaumchaussee 5",
    "sg:city":"Hamburg",
    "sg:phone":"+49 40/41910224",
    "sg:postcode":"20148",
    "sg:province":"Hamburg",
    "wof:name":"Shg Systemhallen Vertriebsgesellschaft Mbh",
    "wof:placetype":"venue"
},
  "geometry": {"coordinates":[9.989009,53.564442],"type":"Point"}
}