{
  "type": "Feature",
  "properties": {
    "iso:country":"DE",
    "sg:address":"Schumannstr. 7",
    "sg:city":"Radebeul",
    "sg:phone":"+49 351/8302663",
    "sg:postcode":"01445",
    "sg:province":"Sachsen",
    "wof:name":"G\u00e4stehaus D\u00f6hnert",
    "wof:placetype":"venue"
},
  "geometry": {"coordinates":[13.6711244583,51.1031570435],"type":"Point"}
}