{
  "type": "Feature",
  "properties": {
    "iso:country":"DE",
    "sg:address":"Rathausstr. 92",
    "sg:city":"Wiesbaden",
    "sg:phone":"+49 611/609054",
    "sg:postcode":"65203",
    "sg:province":"Hessen",
    "wof:name":"Reiseb\u00fcro Wagenseil Gmbh",
    "wof:placetype":"venue"
},
  "geometry": {"coordinates":[8.2407808304,50.0445861816],"type":"Point"}
}