{
  "type": "Feature",
  "properties": {
    "iso:country":"DE",
    "sg:address":"Stigemannstr. 5-7",
    "sg:city":"Koblenz",
    "sg:phone":"+49 4926/1309789",
    "sg:postcode":"56068",
    "sg:province":"Rheinland-Pfalz",
    "wof:name":"Cps Copy Print Service Gmbh",
    "wof:placetype":"venue"
},
  "geometry": {"coordinates":[7.5961060524,50.3557701111],"type":"Point"}
}