{
  "type": "Feature",
  "properties": {
    "iso:country":"DE",
    "sg:address":"Vorwerk 13b",
    "sg:city":"Lassan",
    "sg:postcode":"17440",
    "sg:province":"Mecklenburg-Vorpommern",
    "wof:name":"G. Harenberg Ingenieur",
    "wof:placetype":"venue"
},
  "geometry": {"coordinates":[13.8450098038,53.9525108337],"type":"Point"}
}