{
  "type": "Feature",
  "properties": {
    "iso:country":"DE",
    "sg:address":"Kanalstr. 104",
    "sg:city":"Viersen",
    "sg:phone":"+49 2162/10892",
    "sg:postcode":"41748",
    "sg:province":"Nordrhein-Westfalen",
    "wof:name":"St. Martinsverein Rahser-s\u00fcd Ulrich Heyer",
    "wof:placetype":"venue"
},
  "geometry": {"coordinates":[6.4022531509,51.2626037598],"type":"Point"}
}