{
  "type": "Feature",
  "properties": {
    "iso:country":"DE",
    "sg:address":"Rheinbacher Str. 29",
    "sg:city":"Meckenheim",
    "sg:phone":"+49 2225/706177",
    "sg:postcode":"53340",
    "sg:province":"Nordrhein-Westfalen",
    "wof:name":"Schug Gmbh",
    "wof:placetype":"venue"
},
  "geometry": {"coordinates":[7.006461,50.594234],"type":"Point"}
}