{
  "type": "Feature",
  "properties": {
    "iso:country":"DE",
    "sg:address":"Cirksenastr. 17a",
    "sg:city":"Emden",
    "sg:phone":"+49 4921/89348",
    "sg:postcode":"26723",
    "sg:province":"Niedersachsen",
    "wof:name":"Oldenb. Landesbank Ag Zwst. Cirksenastrasse",
    "wof:placetype":"venue"
},
  "geometry": {"coordinates":[7.195953846,53.3628997803],"type":"Point"}
}