{
  "type": "Feature",
  "properties": {
    "iso:country":"DE",
    "sg:address":"Fliederstr. 21",
    "sg:city":"Ganderkesee",
    "sg:postcode":"27777",
    "sg:province":"Niedersachsen",
    "wof:name":"Vp Unternehmens- Beratung Gmbh",
    "wof:placetype":"venue"
},
  "geometry": {"coordinates":[8.5341482162,53.1021575928],"type":"Point"}
}