{
  "type": "Feature",
  "properties": {
    "iso:country":"DE",
    "sg:address":"Herrenstr. 1",
    "sg:city":"Freiburg",
    "sg:phone":"+49 761/33729",
    "sg:postcode":"79098",
    "sg:province":"Baden-W\u00fcrttemberg",
    "wof:name":"Village",
    "wof:placetype":"venue"
},
  "geometry": {"coordinates":[7.854223,47.996632],"type":"Point"}
}