{
  "type": "Feature",
  "properties": {
    "iso:country":"DE",
    "sg:address":"Am Lindenberg 7",
    "sg:city":"Braunschweig",
    "sg:phone":"+49 531/2361111",
    "sg:postcode":"38104",
    "sg:province":"Niedersachsen",
    "wof:name":"Martin Schade",
    "wof:placetype":"venue"
},
  "geometry": {"coordinates":[10.6058759689,52.2781066895],"type":"Point"}
}