{
  "type": "Feature",
  "properties": {
    "iso:country":"DE",
    "sg:address":"Regensburger Str. 82",
    "sg:city":"Passau",
    "sg:phone":"+49 851/81183",
    "sg:postcode":"94036",
    "sg:province":"Bayern",
    "wof:name":"Jacob Bachl",
    "wof:placetype":"venue"
},
  "geometry": {"coordinates":[13.412902832,48.5755271912],"type":"Point"}
}