{
  "type": "Feature",
  "properties": {
    "iso:country":"DE",
    "sg:address":"Wurmbenden 14",
    "sg:city":"Aachen",
    "sg:phone":"+49 241/166080",
    "sg:postcode":"52070",
    "sg:province":"Nordrhein-Westfalen",
    "wof:name":"Tfb Transport- Und Frisch- Beton Betriebsgesell-",
    "wof:placetype":"venue"
},
  "geometry": {"coordinates":[6.1194682121,50.7951850891],"type":"Point"}
}