{
  "type": "Feature",
  "properties": {
    "iso:country":"DE",
    "sg:address":"Mittelstr. 2",
    "sg:city":"Dannenfels",
    "sg:phone":"+49 6357/454",
    "sg:postcode":"67814",
    "sg:province":"Rheinland-Pfalz",
    "wof:name":"Gerhard Baab Obstanbau",
    "wof:placetype":"venue"
},
  "geometry": {"coordinates":[7.9423360825,49.6296730042],"type":"Point"}
}