{
  "type": "Feature",
  "properties": {
    "iso:country":"DE",
    "sg:address":"Bahnhofstr. 27",
    "sg:city":"Heidelberg",
    "sg:phone":"+49 6221/20185",
    "sg:postcode":"69115",
    "sg:province":"Baden-W\u00fcrttemberg",
    "wof:name":"Image Gastst\u00e4ttenbetriebs Gmbh",
    "wof:placetype":"venue"
},
  "geometry": {"coordinates":[8.689332962,49.4056854248],"type":"Point"}
}