{
  "type": "Feature",
  "properties": {
    "iso:country":"DE",
    "sg:address":"Ganerb 6",
    "sg:city":"Ha\u00dfloch",
    "sg:phone":"+49 6324/59930",
    "sg:postcode":"67454",
    "sg:province":"Rheinland-Pfalz",
    "wof:name":"Holiday-park Gmbh",
    "wof:placetype":"venue"
},
  "geometry": {"coordinates":[8.295696,49.320576],"type":"Point"}
}