{
  "type": "Feature",
  "properties": {
    "iso:country":"DE",
    "sg:address":"Badstr. 5",
    "sg:city":"N\u00fcrnberg",
    "sg:postcode":"90402",
    "sg:province":"Bayern",
    "wof:name":"3 Wbox Gmbh",
    "wof:placetype":"venue"
},
  "geometry": {"coordinates":[11.087506,49.449291],"type":"Point"}
}