{
  "type": "Feature",
  "properties": {
    "iso:country":"DE",
    "sg:address":"Gro\u00dfe Milower Str. 83",
    "sg:city":"Rathenow",
    "sg:phone":"+49 3385/513291",
    "sg:postcode":"14712",
    "sg:province":"Brandenburg",
    "wof:name":"Erhard Wegner",
    "wof:placetype":"venue"
},
  "geometry": {"coordinates":[12.337659,52.60305],"type":"Point"}
}