{
  "type": "Feature",
  "properties": {
    "iso:country":"DE",
    "sg:address":"Sonnental",
    "sg:city":"Engen",
    "sg:phone":"+49 7733/7529",
    "sg:postcode":"78234",
    "sg:province":"Baden-W\u00fcrttemberg",
    "wof:name":"Camping Sonnental",
    "wof:placetype":"venue"
},
  "geometry": {"coordinates":[8.781074,47.857407],"type":"Point"}
}