{
  "type": "Feature",
  "properties": {
    "iso:country":"DE",
    "sg:address":"Brackenweg 24",
    "sg:city":"Eslohe",
    "sg:phone":"+49 2973/97070",
    "sg:postcode":"59889",
    "sg:province":"Nordrhein-Westfalen",
    "wof:name":"Magdalene K\u00f6nig",
    "wof:placetype":"venue"
},
  "geometry": {"coordinates":[8.1768226624,51.2549552917],"type":"Point"}
}