{
  "type": "Feature",
  "properties": {
    "iso:country":"DE",
    "sg:address":"Breitenbachstr. 15",
    "sg:city":"Bad Oeynhausen",
    "sg:phone":"+49 5731/260629",
    "sg:postcode":"32547",
    "sg:province":"Nordrhein-Westfalen",
    "wof:name":"Hofmann Beteiligungs- Und Verwaltungs- Gmbh",
    "wof:placetype":"venue"
},
  "geometry": {"coordinates":[8.8083972931,52.2072868347],"type":"Point"}
}