{
  "type": "Feature",
  "properties": {
    "iso:country":"DE",
    "sg:address":"Schulterblatt 73",
    "sg:city":"Hamburg",
    "sg:postcode":"20357",
    "sg:province":"Hamburg",
    "wof:name":"Fotostudio Michael Zibold",
    "wof:placetype":"venue"
},
  "geometry": {"coordinates":[9.9614610672,53.5620803833],"type":"Point"}
}