{
  "type": "Feature",
  "properties": {
    "iso:country":"DE",
    "sg:address":"Nr. 62",
    "sg:city":"Paitzdorf",
    "sg:phone":"+49 36602/22887",
    "sg:postcode":"07580",
    "sg:province":"Th\u00fcringen",
    "wof:name":"Container-service Fritzenwenger Gmbh",
    "wof:placetype":"venue"
},
  "geometry": {"coordinates":[12.2076711655,50.8359146118],"type":"Point"}
}