{
  "type": "Feature",
  "properties": {
    "iso:country":"DE",
    "sg:address":"Max-Eyth-Str. 1",
    "sg:city":"Bad Teinach-Zavelstein",
    "sg:phone":"+49 7053/920117",
    "sg:postcode":"75385",
    "sg:province":"Baden-W\u00fcrttemberg",
    "wof:name":"Frank Schr\u00f6ter",
    "wof:placetype":"venue"
},
  "geometry": {"coordinates":[8.6639604568,48.7138442993],"type":"Point"}
}