{
  "type": "Feature",
  "properties": {
    "iso:country":"DE",
    "sg:address":"K\u00f6tztinger Str. 16",
    "sg:city":"Blaibach",
    "sg:phone":"+49 9941/8301",
    "sg:postcode":"93476",
    "sg:province":"Bayern",
    "wof:name":"Wenimex Handels Und Service Gmbh",
    "wof:placetype":"venue"
},
  "geometry": {"coordinates":[12.8065137863,49.1597747803],"type":"Point"}
}