{
  "type": "Feature",
  "properties": {
    "iso:country":"DE",
    "sg:address":"Ringstr. 33",
    "sg:city":"K\u00fcps",
    "sg:phone":"+49 9264/530",
    "sg:postcode":"96328",
    "sg:province":"Bayern",
    "wof:name":"Ewald Hartfil",
    "wof:placetype":"venue"
},
  "geometry": {"coordinates":[11.2804470062,50.1868782043],"type":"Point"}
}