{
  "type": "Feature",
  "properties": {
    "iso:country":"DE",
    "sg:address":"Goethestr. 17",
    "sg:city":"Apolda",
    "sg:phone":"+49 3644/651090",
    "sg:postcode":"99510",
    "sg:province":"Th\u00fcringen",
    "wof:name":"Treucolleg Steuerberatungs- Gesellschaft Mbh",
    "wof:placetype":"venue"
},
  "geometry": {"coordinates":[11.482126236,51.01927948],"type":"Point"}
}