{
  "type": "Feature",
  "properties": {
    "iso:country":"DE",
    "sg:address":"Dr.-Schl\u00f6gl-Str. 3",
    "sg:city":"Krumbach",
    "sg:phone":"+49 8282/4031",
    "sg:postcode":"86381",
    "sg:province":"Bayern",
    "wof:name":"Dr. R. Faist",
    "wof:placetype":"venue"
},
  "geometry": {"coordinates":[10.3606233597,48.2436103821],"type":"Point"}
}