{
  "type": "Feature",
  "properties": {
    "iso:country":"DE",
    "sg:address":"Irisstr. 10",
    "sg:city":"Kressbronn",
    "sg:phone":"+49 7543/6763",
    "sg:postcode":"88079",
    "sg:province":"Baden-W\u00fcrttemberg",
    "wof:name":"Manfred Ullrich Gmbh",
    "wof:placetype":"venue"
},
  "geometry": {"coordinates":[9.5933380127,47.5898208618],"type":"Point"}
}