{
  "type": "Feature",
  "properties": {
    "iso:country":"DE",
    "sg:address":"Laufgraben 31",
    "sg:city":"Hamburg",
    "sg:phone":"+49 40/4105799",
    "sg:postcode":"20146",
    "sg:province":"Hamburg",
    "wof:name":"Frame Tv",
    "wof:placetype":"venue"
},
  "geometry": {"coordinates":[9.975110054,53.5668907166],"type":"Point"}
}