{
  "type": "Feature",
  "properties": {
    "iso:country":"DE",
    "sg:address":"Tannfeld 48",
    "sg:city":"Thurnau",
    "sg:phone":"+49 9271/634",
    "sg:postcode":"95349",
    "sg:province":"Bayern",
    "wof:name":"Manfred Stief",
    "wof:placetype":"venue"
},
  "geometry": {"coordinates":[11.403509,49.982098],"type":"Point"}
}