{
  "type": "Feature",
  "properties": {
    "iso:country":"DE",
    "sg:address":"Sonnige Lehne 16",
    "sg:city":"Kaufbeuren",
    "sg:phone":"+49 8341/61040",
    "sg:postcode":"87600",
    "sg:province":"Bayern",
    "wof:name":"Dental-technik Gmbh",
    "wof:placetype":"venue"
},
  "geometry": {"coordinates":[10.6291809082,47.9093704224],"type":"Point"}
}