{
  "type": "Feature",
  "properties": {
    "iso:country":"DE",
    "sg:address":"Mittelsdorfer Str. 13",
    "sg:city":"Kaltensundheim",
    "sg:phone":"+49 36946/20864",
    "sg:postcode":"98634",
    "sg:province":"Th\u00fcringen",
    "wof:name":"Matthias Weigand",
    "wof:placetype":"venue"
},
  "geometry": {"coordinates":[10.1571798325,50.6064567566],"type":"Point"}
}