{
  "type": "Feature",
  "properties": {
    "iso:country":"DE",
    "sg:address":"Martin-Luther-Str. 6",
    "sg:city":"Hagen",
    "sg:phone":"+49 2331/182999",
    "sg:postcode":"58095",
    "sg:province":"Nordrhein-Westfalen",
    "wof:name":"Cafe Bistro Greece",
    "wof:placetype":"venue"
},
  "geometry": {"coordinates":[7.463198,51.362171],"type":"Point"}
}