{
  "type": "Feature",
  "properties": {
    "iso:country":"DE",
    "sg:address":"Birkenhof",
    "sg:city":"Osterr\u00f6nfeld",
    "sg:phone":"+49 4331/89740",
    "sg:postcode":"24783",
    "sg:province":"Schleswig-Holstein",
    "wof:name":"Peter H\u00f6hling",
    "wof:placetype":"venue"
},
  "geometry": {"coordinates":[9.683047,54.280327],"type":"Point"}
}