{
  "type": "Feature",
  "properties": {
    "iso:country":"DE",
    "sg:address":"Schillerstr. 15",
    "sg:city":"Wetzlar",
    "sg:postcode":"35582",
    "sg:province":"Hessen",
    "wof:name":"Agel Kg",
    "wof:placetype":"venue"
},
  "geometry": {"coordinates":[8.5907526016,50.5584182739],"type":"Point"}
}