{
  "type": "Feature",
  "properties": {
    "iso:country":"DE",
    "sg:address":"Am Bahnhof 1",
    "sg:city":"Friedrichsthal",
    "sg:phone":"+49 6897/88500",
    "sg:postcode":"66299",
    "sg:province":"Saarland",
    "wof:name":"Bbm Bergbaumaschinen Gmbh",
    "wof:placetype":"venue"
},
  "geometry": {"coordinates":[7.090412,49.319778],"type":"Point"}
}