{
  "type": "Feature",
  "properties": {
    "iso:country":"DE",
    "sg:address":"Deichstr. 8",
    "sg:city":"Nordenham",
    "sg:phone":"+49 4731/38337",
    "sg:postcode":"26954",
    "sg:province":"Niedersachsen",
    "wof:name":"Peter Koch Gmbh",
    "wof:placetype":"venue"
},
  "geometry": {"coordinates":[8.52264,53.536758],"type":"Point"}
}