{
  "type": "Feature",
  "properties": {
    "iso:country":"DE",
    "sg:address":"Dominikanerstr 19",
    "sg:city":"D\u00fcsseldorf",
    "sg:phone":"+49 211/588712",
    "sg:postcode":"40545",
    "sg:province":"Nordrhein-Westfalen",
    "wof:name":"Rottke Werbung Gmbh",
    "wof:placetype":"venue"
},
  "geometry": {"coordinates":[6.750901,51.229897],"type":"Point"}
}