{
  "type": "Feature",
  "properties": {
    "iso:country":"DE",
    "sg:address":"S\u00fcdallee 37 e",
    "sg:city":"Trier",
    "sg:phone":"+49 651/75740",
    "sg:postcode":"54290",
    "sg:province":"Rheinland-Pfalz",
    "wof:name":"Dagmar Abdalla Masseurin",
    "wof:placetype":"venue"
},
  "geometry": {"coordinates":[6.636521,49.757256],"type":"Point"}
}