{
  "type": "Feature",
  "properties": {
    "iso:country":"DE",
    "sg:address":"Hauptstr. 13",
    "sg:city":"Elsterwerda",
    "sg:phone":"+49 3533/489898",
    "sg:postcode":"04910",
    "sg:province":"Brandenburg",
    "wof:name":"Bischof Unf Kollegen Rechtsanw\u00e4lte",
    "wof:placetype":"venue"
},
  "geometry": {"coordinates":[13.5230436325,51.4571304321],"type":"Point"}
}