{
  "type": "Feature",
  "properties": {
    "iso:country":"DE",
    "sg:address":"Untermainkai 30",
    "sg:city":"Frankfurt",
    "sg:postcode":"60329",
    "sg:province":"Hessen",
    "wof:name":"Bsm Banking Systeme Und Managementberatung",
    "wof:placetype":"venue"
},
  "geometry": {"coordinates":[8.670986,50.105225],"type":"Point"}
}