{
  "type": "Feature",
  "properties": {
    "iso:country":"DE",
    "sg:address":"Gewerbestr 6",
    "sg:city":"Horst",
    "sg:phone":"+49 4126/1472",
    "sg:postcode":"25358",
    "sg:province":"Schleswig-Holstein",
    "wof:name":"Affeldt F\u00f6rdertechnik Gmbh",
    "wof:placetype":"venue"
},
  "geometry": {"coordinates":[9.617765,53.843719],"type":"Point"}
}