{
  "type": "Feature",
  "properties": {
    "iso:country":"DE",
    "sg:address":"Kurzgewannstr. 26",
    "sg:city":"Ladenburg",
    "sg:phone":"+49 6203/3526",
    "sg:postcode":"68526",
    "sg:province":"Baden-W\u00fcrttemberg",
    "wof:name":"K. Christ",
    "wof:placetype":"venue"
},
  "geometry": {"coordinates":[8.612008,49.47691],"type":"Point"}
}