{
  "type": "Feature",
  "properties": {
    "iso:country":"DE",
    "sg:address":"Reichenstr. 4",
    "sg:city":"Bautzen",
    "sg:phone":"+49 3591/481293",
    "sg:postcode":"02625",
    "sg:province":"Sachsen",
    "wof:name":"Ihr Platz Drogeriemarkt",
    "wof:placetype":"venue"
},
  "geometry": {"coordinates":[14.425343,51.181061],"type":"Point"}
}