{
  "type": "Feature",
  "properties": {
    "iso:country":"DE",
    "sg:address":"weg13",
    "sg:city":"Sexten",
    "sg:phone":"+49 123456",
    "sg:postcode":"39038",
    "wof:name":"Hotel Garni Reider",
    "wof:placetype":"venue"
},
  "geometry": {"coordinates":[-90.49788665769999,33.2063713074],"type":"Point"}
}