{
  "type": "Feature",
  "properties": {
    "iso:country":"DE",
    "sg:address":"Westerholmer Str. 4",
    "sg:city":"Steinbergkirche",
    "sg:phone":"+49 4632/1240",
    "sg:postcode":"24972",
    "sg:province":"Schleswig-Holstein",
    "wof:name":"Paspirgilis Glaserei- Und Fensterbau Gmbh",
    "wof:placetype":"venue"
},
  "geometry": {"coordinates":[9.76002,54.753719],"type":"Point"}
}