{
  "type": "Feature",
  "properties": {
    "iso:country":"DE",
    "sg:address":"Torgauer Str. 20",
    "sg:city":"Bad Nauheim",
    "sg:phone":"+49 6032/81816",
    "sg:postcode":"61231",
    "sg:province":"Hessen",
    "wof:name":"Dwd Pr\u00e4zisionswerkzeuge Klaus Dettke",
    "wof:placetype":"venue"
},
  "geometry": {"coordinates":[8.7362232208,50.3807373047],"type":"Point"}
}