{
  "type": "Feature",
  "properties": {
    "iso:country":"DE",
    "sg:address":"Kressenanger 8",
    "sg:city":"Krebeck",
    "sg:phone":"+49 5507/1244",
    "sg:postcode":"37434",
    "sg:province":"Niedersachsen",
    "wof:name":"Albert Rieck Gmbh Universal-ausbau",
    "wof:placetype":"venue"
},
  "geometry": {"coordinates":[10.101163,51.60014],"type":"Point"}
}