{
  "type": "Feature",
  "properties": {
    "iso:country":"DE",
    "sg:address":"Gabelsbergerstr. 1",
    "sg:city":"Aschaffenburg",
    "sg:phone":"+49 6021/21710",
    "sg:postcode":"63739",
    "sg:province":"Bayern",
    "wof:name":"Reinhold Heim Anlageberater",
    "wof:placetype":"venue"
},
  "geometry": {"coordinates":[9.1492614746,49.9702186584],"type":"Point"}
}