{
  "type": "Feature",
  "properties": {
    "iso:country":"DE",
    "sg:address":"Am Heidering 5",
    "sg:city":"Oranienburg",
    "sg:phone":"+49 3301/59870",
    "sg:postcode":"16515",
    "sg:province":"Brandenburg",
    "wof:name":"Hkl Baumaschinen",
    "wof:placetype":"venue"
},
  "geometry": {"coordinates":[13.389594,52.754543],"type":"Point"}
}