{
  "type": "Feature",
  "properties": {
    "iso:country":"DE",
    "sg:address":"Weserm\u00fcnder Str. 53",
    "sg:city":"Heerstedt",
    "sg:phone":"+49 4703/766",
    "sg:postcode":"27616",
    "sg:province":"Niedersachsen",
    "wof:name":"Gastst\u00e4tte Alte M\u00fchle",
    "wof:placetype":"venue"
},
  "geometry": {"coordinates":[8.742395401,53.4676017761],"type":"Point"}
}