{
  "type": "Feature",
  "properties": {
    "iso:country":"DE",
    "sg:address":"Moselstr. 21",
    "sg:city":"Burgen",
    "sg:phone":"+49 2605/793",
    "sg:postcode":"56332",
    "sg:province":"Rheinland-Pfalz",
    "wof:name":"Hotel Wunder",
    "wof:placetype":"venue"
},
  "geometry": {"coordinates":[7.3851299286,50.2090110779],"type":"Point"}
}