{
  "type": "Feature",
  "properties": {
    "iso:country":"DE",
    "sg:address":"Am Packhof 8",
    "sg:city":"Schwerin",
    "sg:postcode":"19053",
    "sg:province":"Mecklenburg-Vorpommern",
    "wof:name":"Evangelisch-lutherische St. Paul-kirche",
    "wof:placetype":"venue"
},
  "geometry": {"coordinates":[11.4084129333,53.6320800781],"type":"Point"}
}