{
  "type": "Feature",
  "properties": {
    "iso:country":"DE",
    "sg:address":"Mauerstr. 30",
    "sg:city":"F\u00fcrth",
    "sg:phone":"+49 911/7909582",
    "sg:postcode":"90765",
    "sg:province":"Bayern",
    "wof:name":"Paul K\u00f6hler",
    "wof:placetype":"venue"
},
  "geometry": {"coordinates":[10.998703,49.485321],"type":"Point"}
}