{
  "type": "Feature",
  "properties": {
    "iso:country":"DE",
    "sg:address":"Sandstr. 173",
    "sg:city":"Siegen",
    "sg:postcode":"57072",
    "sg:province":"Nordrhein-Westfalen",
    "wof:name":"Teppich-haus Am Kaisergarten Lankarani E. Kfr.",
    "wof:placetype":"venue"
},
  "geometry": {"coordinates":[8.0291099548,50.8819236755],"type":"Point"}
}