{
  "type": "Feature",
  "properties": {
    "iso:country":"DE",
    "sg:address":"Weddeln 10",
    "sg:city":"Bosau",
    "sg:phone":"+49 4521/2805",
    "sg:postcode":"23715",
    "sg:province":"Schleswig-Holstein",
    "wof:name":"K. Und E. Reimann",
    "wof:placetype":"venue"
},
  "geometry": {"coordinates":[10.57174,54.118652],"type":"Point"}
}