{
  "type": "Feature",
  "properties": {
    "iso:country":"DE",
    "sg:address":"Wigeystr. 28",
    "sg:city":"Lennestadt",
    "sg:phone":"+49 2723/60045",
    "sg:postcode":"57368",
    "sg:province":"Nordrhein-Westfalen",
    "wof:name":"Werner Winterhoff E. K.",
    "wof:placetype":"venue"
},
  "geometry": {"coordinates":[8.0728931427,51.1096305847],"type":"Point"}
}