{
  "type": "Feature",
  "properties": {
    "iso:country":"DE",
    "sg:address":"Am Brixener Hof 7",
    "sg:city":"Regensburg",
    "sg:phone":"+49 941/54420",
    "sg:postcode":"93047",
    "sg:province":"Bayern",
    "wof:name":"I. Sch\u00fctz Und Chr. Inkofer",
    "wof:placetype":"venue"
},
  "geometry": {"coordinates":[12.099908,49.01712],"type":"Point"}
}