{
  "type": "Feature",
  "properties": {
    "iso:country":"DE",
    "sg:address":"M\u00fcnchener Str. 84",
    "sg:city":"Forstinning",
    "sg:phone":"+49 8121/5562",
    "sg:postcode":"85661",
    "sg:province":"Bayern",
    "wof:name":"Gastst\u00e4tte Zum Vaas",
    "wof:placetype":"venue"
},
  "geometry": {"coordinates":[11.8994140625,48.1599273682],"type":"Point"}
}