{
  "type": "Feature",
  "properties": {
    "iso:country":"DE",
    "sg:address":"Bezirksstr. 1",
    "sg:city":"Blieskastel",
    "sg:phone":"+49 6842/7200",
    "sg:postcode":"66440",
    "sg:province":"Saarland",
    "wof:name":"Edmund Leyhe",
    "wof:placetype":"venue"
},
  "geometry": {"coordinates":[7.1916341782,49.2444343567],"type":"Point"}
}