{
  "type": "Feature",
  "properties": {
    "iso:country":"DE",
    "sg:address":"M\u00fchlenbachstr. 2",
    "sg:city":"L\u00fcnen",
    "sg:phone":"+49 231/870449",
    "sg:postcode":"44536",
    "sg:province":"Nordrhein-Westfalen",
    "wof:name":"Katholisches Pfarramt",
    "wof:placetype":"venue"
},
  "geometry": {"coordinates":[7.4525961876,51.5977058411],"type":"Point"}
}