{
  "type": "Feature",
  "properties": {
    "iso:country":"DE",
    "sg:address":"Aurach 15",
    "sg:city":"Oettingen",
    "sg:phone":"+49 9082/2834",
    "sg:postcode":"86732",
    "sg:province":"Bayern",
    "wof:name":"Erwin Sing",
    "wof:placetype":"venue"
},
  "geometry": {"coordinates":[10.6056547165,48.950252533],"type":"Point"}
}