{
  "type": "Feature",
  "properties": {
    "iso:country":"DE",
    "sg:address":"Graf-Zeppelin-Str. 5",
    "sg:city":"Erlangen",
    "sg:phone":"+49 9131/99930",
    "sg:postcode":"91056",
    "sg:province":"Bayern",
    "wof:name":"Zeppelin-metallwerke Gmbh Hd.- Und Servicebereich",
    "wof:placetype":"venue"
},
  "geometry": {"coordinates":[10.965124,49.562195],"type":"Point"}
}