{
  "type": "Feature",
  "properties": {
    "iso:country":"DE",
    "sg:address":"Bodnegger Str 19",
    "sg:city":"Gr\u00fcnkraut",
    "sg:phone":"+49 751/7690722",
    "sg:postcode":"88287",
    "sg:province":"Baden-W\u00fcrttemberg",
    "wof:name":"Raiffeisenbank Eg",
    "wof:placetype":"venue"
},
  "geometry": {"coordinates":[9.654279,47.741829],"type":"Point"}
}