{
  "type": "Feature",
  "properties": {
    "iso:country":"DE",
    "sg:address":"Aichingerstr. 19",
    "sg:city":"Weiden",
    "sg:phone":"+49 961/23587",
    "sg:postcode":"92637",
    "sg:province":"Bayern",
    "wof:name":"G. G\u00f6tz",
    "wof:placetype":"venue"
},
  "geometry": {"coordinates":[12.138716,49.684181],"type":"Point"}
}