{
  "type": "Feature",
  "properties": {
    "iso:country":"DE",
    "sg:address":"Zavelsteinstr. 47A",
    "sg:city":"Stuttgart",
    "sg:postcode":"70469",
    "sg:province":"Baden-W\u00fcrttemberg",
    "wof:name":"Med Consult Gesellschaft F\u00fcr Medizinische Beratung Mbh",
    "wof:placetype":"venue"
},
  "geometry": {"coordinates":[9.1536865234,48.8044204712],"type":"Point"}
}