{
  "type": "Feature",
  "properties": {
    "iso:country":"DE",
    "sg:address":"Kurze Str. 12",
    "sg:city":"Wilhelmshaven",
    "sg:phone":"+49 4421/201281",
    "sg:postcode":"26382",
    "sg:province":"Niedersachsen",
    "wof:name":"Diakonisches Werk",
    "wof:placetype":"venue"
},
  "geometry": {"coordinates":[8.110353,53.516182],"type":"Point"}
}