{
  "type": "Feature",
  "properties": {
    "iso:country":"DE",
    "sg:address":"K\u00f6rnerstr. 6",
    "sg:city":"Oberursel",
    "sg:phone":"+49 6171/4874",
    "sg:postcode":"61440",
    "sg:province":"Hessen",
    "wof:name":"Geveko Industrie Gmbh",
    "wof:placetype":"venue"
},
  "geometry": {"coordinates":[8.577977,50.200348],"type":"Point"}
}