{
  "type": "Feature",
  "properties": {
    "iso:country":"DE",
    "sg:address":"Im Bachfeld 17",
    "sg:city":"Bonn",
    "sg:phone":"+49 228/344473",
    "sg:postcode":"53179",
    "sg:province":"Nordrhein-Westfalen",
    "wof:name":"Gottfried Bertram",
    "wof:placetype":"venue"
},
  "geometry": {"coordinates":[7.182836,50.661682],"type":"Point"}
}