{
  "type": "Feature",
  "properties": {
    "iso:country":"DE",
    "sg:address":"Loruper Str. 9",
    "sg:city":"Werlte",
    "sg:phone":"+49 5951/4524",
    "sg:postcode":"49757",
    "sg:province":"Niedersachsen",
    "wof:name":"M\u00f6bel Bley Inh. Nicolaus Bley",
    "wof:placetype":"venue"
},
  "geometry": {"coordinates":[7.67431,52.852505],"type":"Point"}
}