{
  "type": "Feature",
  "properties": {
    "iso:country":"DE",
    "sg:address":"Florastr. 102",
    "sg:city":"Velbert",
    "sg:phone":"+49 2053/40912",
    "sg:postcode":"42553",
    "sg:province":"Nordrhein-Westfalen",
    "wof:name":"Herbert Gumz",
    "wof:placetype":"venue"
},
  "geometry": {"coordinates":[7.100465,51.300484],"type":"Point"}
}