{
  "type": "Feature",
  "properties": {
    "iso:country":"DE",
    "sg:address":"Dorfstr. 4",
    "sg:city":"Wennigsen",
    "sg:phone":"+49 5109/52217",
    "sg:postcode":"30974",
    "sg:province":"Niedersachsen",
    "wof:name":"Helmuth Roderhoff",
    "wof:placetype":"venue"
},
  "geometry": {"coordinates":[9.6104450226,52.2792053223],"type":"Point"}
}