{
  "type": "Feature",
  "properties": {
    "iso:country":"DE",
    "sg:address":"Mattsieserstr. 29",
    "sg:city":"Salgen-Hausen",
    "sg:phone":"+49 8265/96970",
    "sg:postcode":"87775",
    "sg:province":"Bayern",
    "wof:name":"Jungpflanzen Rampp Gmbh",
    "wof:placetype":"venue"
},
  "geometry": {"coordinates":[10.47879,48.129311],"type":"Point"}
}