{
  "type": "Feature",
  "properties": {
    "iso:country":"DE",
    "sg:address":"Gr\u00e4tzelstr. 9",
    "sg:city":"G\u00f6ttingen",
    "sg:postcode":"37079",
    "sg:province":"Niedersachsen",
    "wof:name":"Deutsche Bahn Ag",
    "wof:placetype":"venue"
},
  "geometry": {"coordinates":[9.9058160782,51.5420341492],"type":"Point"}
}