{
  "type": "Feature",
  "properties": {
    "iso:country":"DE",
    "sg:address":"Luperkusstr. 12",
    "sg:city":"Worms",
    "sg:phone":"+49 6241/55578",
    "sg:postcode":"67549",
    "sg:province":"Rheinland-Pfalz",
    "wof:name":"Werner Uhlig",
    "wof:placetype":"venue"
},
  "geometry": {"coordinates":[8.3531265259,49.6425323486],"type":"Point"}
}