{
  "type": "Feature",
  "properties": {
    "iso:country":"DE",
    "sg:address":"Otto-Schott-Str. 8",
    "sg:city":"Kempen",
    "sg:phone":"+49 2152/5560",
    "sg:postcode":"47906",
    "sg:province":"Nordrhein-Westfalen",
    "wof:name":"Self Heim Und Garten Gmbh",
    "wof:placetype":"venue"
},
  "geometry": {"coordinates":[6.417379,51.377296],"type":"Point"}
}