{
  "type": "Feature",
  "properties": {
    "iso:country":"DE",
    "sg:address":"Am Hockenborn 3",
    "sg:city":"Rheinb\u00f6llen",
    "sg:phone":"+49 6764/92280",
    "sg:postcode":"55494",
    "sg:province":"Rheinland-Pfalz",
    "wof:name":"Werner M\u00fcller Gmbh",
    "wof:placetype":"venue"
},
  "geometry": {"coordinates":[7.668874,50.012779],"type":"Point"}
}