{
  "type": "Feature",
  "properties": {
    "iso:country":"DE",
    "sg:address":"Wilhelmstr. 5",
    "sg:city":"Trebbin",
    "sg:phone":"+49 4933/731740",
    "sg:postcode":"14959",
    "sg:province":"Brandenburg",
    "wof:name":"Evangelisches Verlagswerk Gmbh",
    "wof:placetype":"venue"
},
  "geometry": {"coordinates":[13.2007398605,52.2180862427],"type":"Point"}
}