{
  "type": "Feature",
  "properties": {
    "iso:country":"DE",
    "sg:address":"Am Galgenfeld 1",
    "sg:city":"Gelnhausen",
    "sg:phone":"+49 6051/92940",
    "sg:postcode":"63571",
    "sg:province":"Hessen",
    "wof:name":"Minimal",
    "wof:placetype":"venue"
},
  "geometry": {"coordinates":[9.1726503372,50.2023277283],"type":"Point"}
}