{
  "type": "Feature",
  "properties": {
    "iso:country":"DE",
    "sg:address":"Ludwigstr. 2",
    "sg:city":"Worms",
    "sg:phone":"+49 6241/412896",
    "sg:postcode":"67547",
    "sg:province":"Rheinland-Pfalz",
    "wof:name":"Shell Station",
    "wof:placetype":"venue"
},
  "geometry": {"coordinates":[8.3689050674,49.6313705444],"type":"Point"}
}