{
  "type": "Feature",
  "properties": {
    "iso:country":"DE",
    "sg:address":"Pfalz-Grona-Breite 22",
    "sg:city":"G\u00f6ttingen",
    "sg:phone":"+49 551/68326",
    "sg:postcode":"37081",
    "sg:province":"Niedersachsen",
    "wof:name":"I. Schmuck",
    "wof:placetype":"venue"
},
  "geometry": {"coordinates":[9.915886879,51.5443572998],"type":"Point"}
}