{
  "type": "Feature",
  "properties": {
    "iso:country":"DE",
    "sg:address":"Poetenweg 36",
    "sg:city":"Leipzig",
    "sg:postcode":"04155",
    "sg:province":"Sachsen",
    "wof:name":"Kronos Beteiligungs- Gesellschaft Mbh",
    "wof:placetype":"venue"
},
  "geometry": {"coordinates":[12.360477,51.358036],"type":"Point"}
}