{
  "type": "Feature",
  "properties": {
    "iso:country":"DE",
    "sg:address":"Nohlstr. 77",
    "sg:city":"Oberhausen",
    "sg:phone":"+49 208/802185",
    "sg:postcode":"46045",
    "sg:province":"Nordrhein-Westfalen",
    "wof:name":"Uphoff Gmbh",
    "wof:placetype":"venue"
},
  "geometry": {"coordinates":[6.8570961952,51.4678878784],"type":"Point"}
}