{
  "type": "Feature",
  "properties": {
    "iso:country":"DE",
    "sg:address":"Leopoldstr. 82",
    "sg:city":"M\u00fcnchen",
    "sg:postcode":"80802",
    "sg:province":"Bayern",
    "wof:name":"Real Estate Essen Projektgesellschaft Mbh",
    "wof:placetype":"venue"
},
  "geometry": {"coordinates":[11.586459,48.161087],"type":"Point"}
}