{
  "type": "Feature",
  "properties": {
    "iso:country":"DE",
    "sg:address":"Brunnenstr. 1",
    "sg:city":"Ochsenfurt",
    "sg:phone":"+49 9331/2538",
    "sg:postcode":"97199",
    "sg:province":"Bayern",
    "wof:name":"Kupsch Gmbh",
    "wof:placetype":"venue"
},
  "geometry": {"coordinates":[10.0607852936,49.664806366],"type":"Point"}
}