{
  "type": "Feature",
  "properties": {
    "iso:country":"DE",
    "sg:address":"Stuttgarter Str. 132",
    "sg:city":"Uhingen",
    "sg:phone":"+49 7161/37127",
    "sg:postcode":"73066",
    "sg:province":"Baden-W\u00fcrttemberg",
    "wof:name":"Karlheinz Zwicker",
    "wof:placetype":"venue"
},
  "geometry": {"coordinates":[9.573152,48.711304],"type":"Point"}
}