{
  "type": "Feature",
  "properties": {
    "iso:country":"DE",
    "sg:address":"Steinstr. 56",
    "sg:city":"Essen",
    "sg:phone":"+49 201/230939",
    "sg:postcode":"45128",
    "sg:province":"Nordrhein-Westfalen",
    "wof:name":"Musik-shop Axel Dr. A. Geerling Gmbh",
    "wof:placetype":"venue"
},
  "geometry": {"coordinates":[7.0195760727,51.447681427],"type":"Point"}
}