{
  "type": "Feature",
  "properties": {
    "iso:country":"DE",
    "sg:address":"Eisenbahnstr. 207",
    "sg:city":"Werder",
    "sg:phone":"+49 3327/44449",
    "sg:postcode":"14542",
    "sg:province":"Brandenburg",
    "wof:name":"Bestattungsinstitut K\u00fcken Gmbh",
    "wof:placetype":"venue"
},
  "geometry": {"coordinates":[12.925414,52.389938],"type":"Point"}
}