{
  "type": "Feature",
  "properties": {
    "iso:country":"DE",
    "sg:address":"D\u00fcrnauer Weg 13",
    "sg:city":"Heiningen",
    "sg:phone":"+49 7161/41465",
    "sg:postcode":"73092",
    "sg:province":"Baden-W\u00fcrttemberg",
    "wof:name":"Vereinsgastst\u00e4tte 1. Fc Heiningen",
    "wof:placetype":"venue"
},
  "geometry": {"coordinates":[9.6432304382,48.6581497192],"type":"Point"}
}