{
  "type": "Feature",
  "properties": {
    "iso:country":"DE",
    "sg:address":"Berliner Str 130",
    "sg:city":"Potsdam",
    "sg:phone":"+49 331/2800167",
    "sg:postcode":"14467",
    "sg:province":"Brandenburg",
    "wof:name":"Landeszentralbank",
    "wof:placetype":"venue"
},
  "geometry": {"coordinates":[13.073374,52.406052],"type":"Point"}
}