{
  "type": "Feature",
  "properties": {
    "iso:country":"DE",
    "sg:address":"Von-der-Heydt-Str. 16-18",
    "sg:city":"Berlin",
    "sg:phone":"+49 30/254630",
    "sg:postcode":"10785",
    "sg:province":"Berlin",
    "wof:name":"Stiftung Preu\u00dfischer Kulturbesitz",
    "wof:placetype":"venue"
},
  "geometry": {"coordinates":[13.3540811539,52.5067062378],"type":"Point"}
}