{
  "type": "Feature",
  "properties": {
    "iso:country":"DE",
    "sg:address":"Dorfstr. 14",
    "sg:city":"Kartlow",
    "sg:postcode":"17129",
    "sg:province":"Mecklenburg-Vorpommern",
    "wof:name":"Evangelisch-lutherische Kirche",
    "wof:placetype":"venue"
},
  "geometry": {"coordinates":[13.2622709274,53.8898048401],"type":"Point"}
}