{
  "type": "Feature",
  "properties": {
    "iso:country":"DE",
    "sg:address":"Kroneng\u00e4\u00dfle 24",
    "sg:city":"V\u00f6hrenbach",
    "sg:phone":"+49 7727/7567",
    "sg:postcode":"78147",
    "sg:province":"Baden-W\u00fcrttemberg",
    "wof:name":"Hermann Spiegelhalder",
    "wof:placetype":"venue"
},
  "geometry": {"coordinates":[8.305553,48.046261],"type":"Point"}
}