{
  "type": "Feature",
  "properties": {
    "iso:country":"DE",
    "sg:address":"K\u00f6lner Str. 1",
    "sg:city":"Bitburg",
    "sg:phone":"+49 6561/2071",
    "sg:postcode":"54634",
    "sg:province":"Rheinland-Pfalz",
    "wof:name":"A. Wallenborn Immobilienmakler",
    "wof:placetype":"venue"
},
  "geometry": {"coordinates":[6.5252280235,49.9758071899],"type":"Point"}
}