{
  "type": "Feature",
  "properties": {
    "iso:country":"DE",
    "sg:address":"Leichtmetallstr. 26-30",
    "sg:city":"Haan",
    "sg:phone":"+49 4921/0469190",
    "sg:postcode":"42781",
    "sg:province":"Nordrhein-Westfalen",
    "wof:name":"Anlagenbau Stampfer Gmbh",
    "wof:placetype":"venue"
},
  "geometry": {"coordinates":[7.0072917938,51.2165908813],"type":"Point"}
}