{
  "type": "Feature",
  "properties": {
    "iso:country":"DE",
    "sg:address":"Beutlerstr. 5",
    "sg:city":"Freiberg",
    "sg:postcode":"09599",
    "sg:province":"Sachsen",
    "wof:name":"Ev.-luth. Christopherus Kirche",
    "wof:placetype":"venue"
},
  "geometry": {"coordinates":[13.3507022858,50.9026641846],"type":"Point"}
}