{
  "type": "Feature",
  "properties": {
    "iso:country":"DE",
    "sg:address":"Franz-Liszt-Str. 3",
    "sg:city":"B\u00f6hl-Iggelheim",
    "sg:phone":"+49 6324/64000",
    "sg:postcode":"67459",
    "sg:province":"Rheinland-Pfalz",
    "wof:name":"Gerhard Staab",
    "wof:placetype":"venue"
},
  "geometry": {"coordinates":[8.3190412521,49.3580856323],"type":"Point"}
}