{
  "type": "Feature",
  "properties": {
    "iso:country":"DE",
    "sg:address":"Neuenhauser Str. 25",
    "sg:city":"Nordhorn",
    "sg:phone":"+49 5921/36317",
    "sg:postcode":"48529",
    "sg:province":"Niedersachsen",
    "wof:name":"Rainer Lemke",
    "wof:placetype":"venue"
},
  "geometry": {"coordinates":[7.0671629906,52.4392280579],"type":"Point"}
}