{
  "type": "Feature",
  "properties": {
    "iso:country":"DE",
    "sg:address":"Bartholom\u00e4usstr. 45",
    "sg:city":"Warendorf",
    "sg:phone":"+49 2584/1681",
    "sg:postcode":"48231",
    "sg:province":"Nordrhein-Westfalen",
    "wof:name":"Herbert Pohlkamp Ingenieur",
    "wof:placetype":"venue"
},
  "geometry": {"coordinates":[7.8915472031,51.9737968445],"type":"Point"}
}