{
  "type": "Feature",
  "properties": {
    "iso:country":"DE",
    "sg:address":"Maisacher Str. 8",
    "sg:city":"F\u00fcrstenfeldbruck",
    "sg:phone":"+49 8141/41751",
    "sg:postcode":"82256",
    "sg:province":"Bayern",
    "wof:name":"S. Stollenwerk",
    "wof:placetype":"venue"
},
  "geometry": {"coordinates":[11.254764,48.181244],"type":"Point"}
}