{
  "type": "Feature",
  "properties": {
    "iso:country":"DE",
    "sg:address":"Reitbahn 6",
    "sg:city":"Wolfsburg",
    "sg:phone":"+49 5308/2405",
    "sg:postcode":"38444",
    "sg:province":"Niedersachsen",
    "wof:name":"C. Werthmann",
    "wof:placetype":"venue"
},
  "geometry": {"coordinates":[10.7485237122,52.3605766296],"type":"Point"}
}