{
  "type": "Feature",
  "properties": {
    "iso:country":"DE",
    "sg:address":"Dorfstr. 21 a",
    "sg:city":"Kerkau",
    "sg:phone":"+49 39034/720",
    "sg:postcode":"29416",
    "sg:province":"Sachsen-Anhalt",
    "wof:name":"Agrargesellschaft Kerkau Mbh",
    "wof:placetype":"venue"
},
  "geometry": {"coordinates":[11.431555,52.779446],"type":"Point"}
}