{
  "type": "Feature",
  "properties": {
    "iso:country":"DE",
    "sg:address":"Petersstr. 20a",
    "sg:city":"Freiberg",
    "sg:phone":"+49 3731/355832",
    "sg:postcode":"09599",
    "sg:province":"Sachsen",
    "wof:name":"Optiker H\u00f6sel",
    "wof:placetype":"venue"
},
  "geometry": {"coordinates":[13.3414297104,50.9161338806],"type":"Point"}
}