{
  "type": "Feature",
  "properties": {
    "iso:country":"DE",
    "sg:address":"Obertsroter Str. 10",
    "sg:city":"Gernsbach",
    "sg:phone":"+49 7224/3206",
    "sg:postcode":"76593",
    "sg:province":"Baden-W\u00fcrttemberg",
    "wof:name":"Strau\u00df",
    "wof:placetype":"venue"
},
  "geometry": {"coordinates":[8.3462839127,48.7451248169],"type":"Point"}
}