{
  "type": "Feature",
  "properties": {
    "iso:country":"DE",
    "sg:address":"Theaterstr. 15",
    "sg:city":"Aachen",
    "sg:phone":"+49 241/28765",
    "sg:postcode":"52062",
    "sg:province":"Nordrhein-Westfalen",
    "wof:name":"Berg",
    "wof:placetype":"venue"
},
  "geometry": {"coordinates":[6.089677,50.771694],"type":"Point"}
}