{
  "type": "Feature",
  "properties": {
    "iso:country":"DE",
    "sg:address":"Einsiedelstr.17",
    "sg:city":"D\u00fcsseldorf",
    "sg:phone":"+49 211",
    "sg:postcode":"40597",
    "sg:province":"Nordrhein-Westfalen",
    "wof:name":"Der Kundendienstprofi",
    "wof:placetype":"venue"
},
  "geometry": {"coordinates":[6.885305,51.162861],"type":"Point"}
}