{
  "type": "Feature",
  "properties": {
    "iso:country":"DE",
    "sg:address":"Eschstr. 36",
    "sg:city":"B\u00fcnde",
    "sg:phone":"+49 5223/2869",
    "sg:postcode":"32257",
    "sg:province":"Nordrhein-Westfalen",
    "wof:name":"Liberty Damenmoden Gmbh",
    "wof:placetype":"venue"
},
  "geometry": {"coordinates":[8.585418,52.198471],"type":"Point"}
}