{
  "type": "Feature",
  "properties": {
    "iso:country":"DE",
    "sg:address":"Erzgebirgsstr. 22",
    "sg:city":"Waldkraiburg",
    "sg:phone":"+49 8638/4890",
    "sg:postcode":"84478",
    "sg:province":"Bayern",
    "wof:name":"Friedel M\u00f6ller",
    "wof:placetype":"venue"
},
  "geometry": {"coordinates":[12.396692276,48.1988182068],"type":"Point"}
}