{
  "type": "Feature",
  "properties": {
    "iso:country":"DE",
    "sg:address":"Alt Breinig 59",
    "sg:city":"Stolberg",
    "sg:phone":"+49 2402/30881",
    "sg:postcode":"52223",
    "sg:province":"Nordrhein-Westfalen",
    "wof:name":"Zur Treppe",
    "wof:placetype":"venue"
},
  "geometry": {"coordinates":[6.2210168839,50.7297897339],"type":"Point"}
}