{
  "type": "Feature",
  "properties": {
    "iso:country":"DE",
    "sg:address":"Kattegattweg 6",
    "sg:city":"Emmerich",
    "sg:phone":"+49 4928/2891460",
    "sg:postcode":"46446",
    "sg:province":"Nordrhein-Westfalen",
    "wof:name":"Alwit Gmbh",
    "wof:placetype":"venue"
},
  "geometry": {"coordinates":[6.173154,51.879936],"type":"Point"}
}