{
  "type": "Feature",
  "properties": {
    "iso:country":"DE",
    "sg:address":"Hofgasse 23",
    "sg:city":"G\u00fcnzburg",
    "sg:phone":"+49 8221/31553",
    "sg:postcode":"89312",
    "sg:province":"Bayern",
    "wof:name":"Backstube",
    "wof:placetype":"venue"
},
  "geometry": {"coordinates":[10.2765741348,48.45470047],"type":"Point"}
}