{
  "type": "Feature",
  "properties": {
    "iso:country":"DE",
    "sg:address":"Karl-Marx-Allee 124",
    "sg:city":"Berlin",
    "sg:phone":"+49 30/2947863",
    "sg:postcode":"10243",
    "sg:province":"Berlin",
    "wof:name":"Kurt Heinen Dipl.-ingenieur",
    "wof:placetype":"venue"
},
  "geometry": {"coordinates":[13.449399,52.516094],"type":"Point"}
}