{
  "type": "Feature",
  "properties": {
    "iso:country":"DE",
    "sg:address":"Zinzendorfstr. 13",
    "sg:city":"Radebeul",
    "sg:phone":"+49 351/837050",
    "sg:postcode":"01445",
    "sg:province":"Sachsen",
    "wof:name":"Turbo Bautr\u00e4ger Gmbh",
    "wof:placetype":"venue"
},
  "geometry": {"coordinates":[13.684095,51.100304],"type":"Point"}
}