{
  "type": "Feature",
  "properties": {
    "iso:country":"DE",
    "sg:address":"Am Gelskamp 16 a",
    "sg:city":"Detmold",
    "sg:phone":"+49 5231/68783",
    "sg:postcode":"32758",
    "sg:province":"Nordrhein-Westfalen",
    "wof:name":"Wewokord Winterg\u00e4rten Und Bauelemente Gmbh",
    "wof:placetype":"venue"
},
  "geometry": {"coordinates":[8.857013,51.949062],"type":"Point"}
}