{
  "type": "Feature",
  "properties": {
    "iso:country":"DE",
    "sg:address":"Buschstr. 60",
    "sg:city":"Tarthun",
    "sg:phone":"+49 39268/98573",
    "sg:postcode":"39435",
    "sg:province":"Sachsen-Anhalt",
    "wof:name":"Jobangebot F\u00fcr Internetdienste In Sachsen-anhalt",
    "wof:placetype":"venue"
},
  "geometry": {"coordinates":[11.471413,51.930923],"type":"Point"}
}