{
  "type": "Feature",
  "properties": {
    "iso:country":"DE",
    "sg:address":"Hahnenbachstr. 21",
    "sg:city":"Hahnenbach",
    "sg:postcode":"55606",
    "sg:province":"Rheinland-Pfalz",
    "wof:name":"Strau\u00df & Rohr",
    "wof:placetype":"venue"
},
  "geometry": {"coordinates":[7.420235157,49.8073425293],"type":"Point"}
}