{
  "type": "Feature",
  "properties": {
    "iso:country":"DE",
    "sg:address":"Hellmundstr. 37",
    "sg:city":"Wiesbaden",
    "sg:phone":"+49 611",
    "sg:postcode":"65183",
    "sg:province":"Hessen",
    "wof:name":"Au-pair",
    "wof:placetype":"venue"
},
  "geometry": {"coordinates":[8.232996,50.08197],"type":"Point"}
}