{
  "type": "Feature",
  "properties": {
    "iso:country":"DE",
    "sg:address":"Markersdorfer Str. 89",
    "sg:city":"Chemnitz",
    "sg:phone":"+49 371/227301",
    "sg:postcode":"09123",
    "sg:province":"Sachsen",
    "wof:name":"Peter Uhlig Zoohandlung Aquaria",
    "wof:placetype":"venue"
},
  "geometry": {"coordinates":[12.897198,50.791695],"type":"Point"}
}