{
  "type": "Feature",
  "properties": {
    "iso:country":"DE",
    "sg:address":"Ludwigstr.1",
    "sg:city":"Bad Nauheim",
    "sg:phone":"+49 4960/326036",
    "sg:postcode":"61231",
    "sg:province":"Hessen",
    "wof:name":"Dresdner Bank",
    "wof:placetype":"venue"
},
  "geometry": {"coordinates":[8.74397,50.365459],"type":"Point"}
}