{
  "type": "Feature",
  "properties": {
    "iso:country":"DE",
    "sg:address":"Goethestra\u00dfe 44",
    "sg:city":"Elze",
    "sg:phone":"+49 5068",
    "sg:postcode":"31008",
    "sg:province":"Niedersachsen",
    "wof:name":"Weikert Ingenieurb\u00fcro",
    "wof:placetype":"venue"
},
  "geometry": {"coordinates":[9.746244,52.128902],"type":"Point"}
}