{
  "type": "Feature",
  "properties": {
    "iso:country":"DE",
    "sg:address":"Peter-Loer-Str. 24",
    "sg:city":"Neuss",
    "sg:phone":"+49 2131/542844",
    "sg:postcode":"41462",
    "sg:province":"Nordrhein-Westfalen",
    "wof:name":"A & O",
    "wof:placetype":"venue"
},
  "geometry": {"coordinates":[6.6691670418,51.2106361389],"type":"Point"}
}