{
  "type": "Feature",
  "properties": {
    "iso:country":"DE",
    "sg:address":"Mozartstr. 20",
    "sg:city":"Bremen",
    "sg:phone":"+49 421/3379933",
    "sg:postcode":"28203",
    "sg:province":"Bremen",
    "wof:name":"Massagepraxis Kammann",
    "wof:placetype":"venue"
},
  "geometry": {"coordinates":[8.816619,53.071152],"type":"Point"}
}