{
  "type": "Feature",
  "properties": {
    "iso:country":"DE",
    "sg:address":"Paulusstr. 9",
    "sg:city":"Ediger-Eller",
    "sg:phone":"+49 2675/481",
    "sg:postcode":"56814",
    "sg:province":"Rheinland-Pfalz",
    "wof:name":"Arnold Equit Weinanbau",
    "wof:placetype":"venue"
},
  "geometry": {"coordinates":[7.1559081078,50.0962524414],"type":"Point"}
}