{
  "type": "Feature",
  "properties": {
    "iso:country":"DE",
    "sg:city":"Kiefersfelden",
    "sg:phone":"+49 8033/7061",
    "sg:postcode":"83088",
    "sg:province":"Bayern",
    "wof:name":"Raiffeisenbank Oberaudorf Eg",
    "wof:placetype":"venue"
},
  "geometry": {"coordinates":[12.18826,47.615543],"type":"Point"}
}