{
  "type": "Feature",
  "properties": {
    "iso:country":"DE",
    "sg:address":"Nordhorner Str. 22",
    "sg:city":"Lingen",
    "sg:phone":"+49 591/3054",
    "sg:postcode":"49808",
    "sg:province":"Niedersachsen",
    "wof:name":"Hermann Krone",
    "wof:placetype":"venue"
},
  "geometry": {"coordinates":[7.292754,52.508587],"type":"Point"}
}