{
  "type": "Feature",
  "properties": {
    "iso:country":"DE",
    "sg:address":"Rippes Padd 4",
    "sg:city":"Syke",
    "sg:postcode":"28857",
    "sg:province":"Niedersachsen",
    "wof:name":"Fl Gruppen-reisen Gmbh",
    "wof:placetype":"venue"
},
  "geometry": {"coordinates":[8.8155956268,52.9164428711],"type":"Point"}
}