{
  "type": "Feature",
  "properties": {
    "iso:country":"DE",
    "sg:address":"Salzstr. 14",
    "sg:city":"Bingen",
    "sg:phone":"+49 6721/990876",
    "sg:postcode":"55411",
    "sg:province":"Rheinland-Pfalz",
    "wof:name":"Tchibo Frisch-r\u00f6st-kaffee Gmbh",
    "wof:placetype":"venue"
},
  "geometry": {"coordinates":[7.8950538635,49.9683494568],"type":"Point"}
}