{
  "type": "Feature",
  "properties": {
    "iso:country":"DE",
    "sg:address":"Alte Poststr. 59 A",
    "sg:city":"Passau",
    "sg:phone":"+49 851/89452",
    "sg:postcode":"94036",
    "sg:province":"Bayern",
    "wof:name":"Richard Weidinger",
    "wof:placetype":"venue"
},
  "geometry": {"coordinates":[13.380106,48.574455],"type":"Point"}
}