{
  "type": "Feature",
  "properties": {
    "iso:country":"DE",
    "sg:address":"Schulstr. 33",
    "sg:city":"Freilassing",
    "sg:postcode":"83395",
    "sg:province":"Bayern",
    "wof:name":"The Weeds",
    "wof:placetype":"venue"
},
  "geometry": {"coordinates":[12.9761,47.843971],"type":"Point"}
}