{
  "type": "Feature",
  "properties": {
    "iso:country":"DE",
    "sg:address":"Schwieberdingerstr.8",
    "sg:city":"M\u00f6glingen",
    "sg:phone":"+49 7141/481415",
    "sg:postcode":"71696",
    "sg:province":"Baden-W\u00fcrttemberg",
    "wof:name":"K\u00fcchen Und Elektroger\u00e4te In M\u00f6glingen",
    "wof:placetype":"venue"
},
  "geometry": {"coordinates":[9.125422,48.887207],"type":"Point"}
}