{
  "type": "Feature",
  "properties": {
    "iso:country":"DE",
    "sg:address":"Gartenstr. 3",
    "sg:city":"Perleberg",
    "sg:phone":"+49 3876/613427",
    "sg:postcode":"19348",
    "sg:province":"Brandenburg",
    "wof:name":"Ulrich Thiede",
    "wof:placetype":"venue"
},
  "geometry": {"coordinates":[11.858767,53.07473],"type":"Point"}
}