{
  "type": "Feature",
  "properties": {
    "iso:country":"DE",
    "sg:address":"Frankfurter Str. 53",
    "sg:city":"Hennef",
    "sg:phone":"+49 2242/4007",
    "sg:postcode":"53773",
    "sg:province":"Nordrhein-Westfalen",
    "wof:name":"Strohhut Reiseshop Gmbh",
    "wof:placetype":"venue"
},
  "geometry": {"coordinates":[7.2895641327,50.7734336853],"type":"Point"}
}