{
  "type": "Feature",
  "properties": {
    "iso:country":"DE",
    "sg:address":"Finkenweg 12",
    "sg:city":"Potsdam",
    "sg:postcode":"14473",
    "sg:province":"Brandenburg",
    "wof:name":"Dr. E.-g. Metz",
    "wof:placetype":"venue"
},
  "geometry": {"coordinates":[13.057483,52.385063],"type":"Point"}
}