{
  "type": "Feature",
  "properties": {
    "iso:country":"DE",
    "sg:address":"Hauptstr. 6",
    "sg:city":"Petersberg",
    "sg:phone":"+49 661/62484",
    "sg:postcode":"36100",
    "sg:province":"Hessen",
    "wof:name":"Schuhhaus-orthop\u00e4die- Krankenpflegeartikel",
    "wof:placetype":"venue"
},
  "geometry": {"coordinates":[9.7337188721,50.5912666321],"type":"Point"}
}