{
  "type": "Feature",
  "properties": {
    "iso:country":"DE",
    "sg:address":"Karl-Beck-Weg 13",
    "sg:city":"Vilshofen",
    "sg:postcode":"94474",
    "sg:province":"Bayern",
    "wof:name":"Aktiv Hochbau Gmbh",
    "wof:placetype":"venue"
},
  "geometry": {"coordinates":[13.1946763992,48.593547821],"type":"Point"}
}