{
  "type": "Feature",
  "properties": {
    "iso:country":"DE",
    "sg:address":"Krumbeckstr. 31",
    "sg:city":"Velbert",
    "sg:phone":"+49 2053/923122",
    "sg:postcode":"42553",
    "sg:province":"Nordrhein-Westfalen",
    "wof:name":"H. Schwarz Steuerberater",
    "wof:placetype":"venue"
},
  "geometry": {"coordinates":[7.0850429535,51.2997245789],"type":"Point"}
}