{
  "type": "Feature",
  "properties": {
    "iso:country":"DE",
    "sg:address":"Gildehauser Str. 210",
    "sg:city":"Gronau",
    "sg:phone":"+49 2562/5729",
    "sg:postcode":"48599",
    "sg:province":"Nordrhein-Westfalen",
    "wof:name":"H. Rundmund Herde Und \u00d6fen",
    "wof:placetype":"venue"
},
  "geometry": {"coordinates":[7.0486450195,52.2258987427],"type":"Point"}
}