{
  "type": "Feature",
  "properties": {
    "iso:country":"DE",
    "sg:address":"Ulfaer Str. 1",
    "sg:city":"Hungen",
    "sg:postcode":"35410",
    "sg:province":"Hessen",
    "wof:name":"Sss Service Team Gmbh",
    "wof:placetype":"venue"
},
  "geometry": {"coordinates":[8.98036,50.460522],"type":"Point"}
}