{
  "type": "Feature",
  "properties": {
    "iso:country":"DE",
    "sg:address":"Folzstr. 3",
    "sg:city":"Worms",
    "sg:phone":"+49 6241/28433",
    "sg:postcode":"67547",
    "sg:province":"Rheinland-Pfalz",
    "wof:name":"Karl-heinrich H\u00f6nig",
    "wof:placetype":"venue"
},
  "geometry": {"coordinates":[8.363673,49.630913],"type":"Point"}
}