{
  "type": "Feature",
  "properties": {
    "iso:country":"DE",
    "sg:address":"Dorfanger 10-12",
    "sg:city":"Altenm\u00fcnster",
    "sg:phone":"+49 8295/530",
    "sg:postcode":"86450",
    "sg:province":"Bayern",
    "wof:name":"Wiedemann Erdbewegungen Gmbh",
    "wof:placetype":"venue"
},
  "geometry": {"coordinates":[10.558351,48.458015],"type":"Point"}
}