{
  "type": "Feature",
  "properties": {
    "iso:country":"DE",
    "sg:address":"Rosenstr. 18",
    "sg:city":"B\u00f6hl-Iggelheim",
    "sg:phone":"+49 6324/78506",
    "sg:postcode":"67459",
    "sg:province":"Rheinland-Pfalz",
    "wof:name":"Hannebohm Transporte Gmbh",
    "wof:placetype":"venue"
},
  "geometry": {"coordinates":[8.3147192001,49.3638381958],"type":"Point"}
}