{
  "type": "Feature",
  "properties": {
    "iso:country":"DE",
    "sg:address":"D\u00fcrrenseestr. 44",
    "sg:city":"Ingolstadt",
    "sg:phone":"+49 841/84926",
    "sg:postcode":"85049",
    "sg:province":"Bayern",
    "wof:name":"Hermann Birzl Ingenieur",
    "wof:placetype":"venue"
},
  "geometry": {"coordinates":[11.3509588242,48.7515602112],"type":"Point"}
}