{
  "type": "Feature",
  "properties": {
    "iso:country":"DE",
    "sg:address":"An der G\u00fcmpgesbr\u00fccke 22",
    "sg:city":"Kaarst",
    "sg:phone":"+49 2131/793900",
    "sg:postcode":"41564",
    "sg:province":"Nordrhein-Westfalen",
    "wof:name":"Thieka Werbeversand Gmbh",
    "wof:placetype":"venue"
},
  "geometry": {"coordinates":[6.6359229088,51.2154808044],"type":"Point"}
}