{
  "type": "Feature",
  "properties": {
    "iso:country":"DE",
    "sg:address":"Am Heidorn 1",
    "sg:city":"Erndtebr\u00fcck",
    "sg:phone":"+49 2753/2182",
    "sg:postcode":"57339",
    "sg:province":"Nordrhein-Westfalen",
    "wof:name":"Richard Herling",
    "wof:placetype":"venue"
},
  "geometry": {"coordinates":[8.259379,51.016792],"type":"Point"}
}