{
  "type": "Feature",
  "properties": {
    "iso:country":"DE",
    "sg:address":"Suppengasse 17",
    "sg:city":"Oberndorf",
    "sg:postcode":"78727",
    "sg:province":"Baden-W\u00fcrttemberg",
    "wof:name":"W. Diez De Ulzurrun Martinez Verwaltungs Gmbh",
    "wof:placetype":"venue"
},
  "geometry": {"coordinates":[8.5675144196,48.3181648254],"type":"Point"}
}