{
  "type": "Feature",
  "properties": {
    "iso:country":"DE",
    "sg:address":"Schillingsstr. 243",
    "sg:city":"D\u00fcren",
    "sg:phone":"+49 2421/968030",
    "sg:postcode":"52355",
    "sg:province":"Nordrhein-Westfalen",
    "wof:name":"P. Und B. Harscheidt Steuerberater",
    "wof:placetype":"venue"
},
  "geometry": {"coordinates":[6.4389362335,50.7878074646],"type":"Point"}
}