{
  "type": "Feature",
  "properties": {
    "iso:country":"DE",
    "sg:address":"Alter Postweg 107",
    "sg:city":"Wittmund",
    "sg:phone":"+49 4462/7636",
    "sg:postcode":"26409",
    "sg:province":"Niedersachsen",
    "wof:name":"Reinhard Harms",
    "wof:placetype":"venue"
},
  "geometry": {"coordinates":[7.717106,53.557201],"type":"Point"}
}