{
  "type": "Feature",
  "properties": {
    "iso:country":"DE",
    "sg:address":"Auf der Heide",
    "sg:city":"Staudt",
    "sg:phone":"+49 2602/60003",
    "sg:postcode":"56424",
    "sg:province":"Rheinland-Pfalz",
    "wof:name":"Ramb Gmbh",
    "wof:placetype":"venue"
},
  "geometry": {"coordinates":[7.84395504,50.4613189697],"type":"Point"}
}