{
  "type": "Feature",
  "properties": {
    "iso:country":"DE",
    "sg:address":"Mittelgasse 23a",
    "sg:city":"Gr\u00e4finau-Angstedt",
    "sg:phone":"+49 36785/50670",
    "sg:postcode":"98704",
    "sg:province":"Th\u00fcringen",
    "wof:name":"Omnibusbetrieb Holger Zentgraf",
    "wof:placetype":"venue"
},
  "geometry": {"coordinates":[11.0264978409,50.7000694275],"type":"Point"}
}