{
  "type": "Feature",
  "properties": {
    "iso:country":"DE",
    "sg:address":"Grunewaldstr 59",
    "sg:city":"M\u00f6nchengladbach",
    "sg:phone":"+49 2161/6920",
    "sg:postcode":"41066",
    "sg:province":"Nordrhein-Westfalen",
    "wof:name":"Tiefdruck Schwann-bagel Gmbh & Co Kg",
    "wof:placetype":"venue"
},
  "geometry": {"coordinates":[6.4793748856,51.2310447693],"type":"Point"}
}