{
  "type": "Feature",
  "properties": {
    "iso:country":"DE",
    "sg:address":"Seilerstr. 24",
    "sg:city":"Ludwigshafen",
    "sg:phone":"+49 621/524655",
    "sg:postcode":"67063",
    "sg:province":"Rheinland-Pfalz",
    "wof:name":"Robert Lay",
    "wof:placetype":"venue"
},
  "geometry": {"coordinates":[8.4343833923,49.4882316589],"type":"Point"}
}