{
  "type": "Feature",
  "properties": {
    "iso:country":"DE",
    "sg:address":"Hoffenheimer Str. 8",
    "sg:city":"Sinsheim",
    "sg:phone":"+49 7265/384",
    "sg:postcode":"74889",
    "sg:province":"Baden-W\u00fcrttemberg",
    "wof:name":"W. Und W. Liebenstein",
    "wof:placetype":"venue"
},
  "geometry": {"coordinates":[8.7836589813,49.2519378662],"type":"Point"}
}