{
  "type": "Feature",
  "properties": {
    "iso:country":"DE",
    "sg:address":"Kurpfalzring 110",
    "sg:city":"Heidelberg",
    "sg:phone":"+49 6221/707608",
    "sg:postcode":"69123",
    "sg:province":"Baden-W\u00fcrttemberg",
    "wof:name":"Beck-leuchten Gmbh",
    "wof:placetype":"venue"
},
  "geometry": {"coordinates":[8.6401510239,49.4055328369],"type":"Point"}
}