{
  "type": "Feature",
  "properties": {
    "iso:country":"DE",
    "sg:address":"Kirchstr. 10",
    "sg:city":"Timmenrode",
    "sg:postcode":"06502",
    "sg:province":"Sachsen-Anhalt",
    "wof:name":"Evangelische Kirchengemeinde",
    "wof:placetype":"venue"
},
  "geometry": {"coordinates":[11.0066518784,51.7705383301],"type":"Point"}
}