{
  "type": "Feature",
  "properties": {
    "iso:country":"DE",
    "sg:address":"Bert-Brecht-Str. 15",
    "sg:city":"Wiesbaden",
    "sg:phone":"+49 611/25504",
    "sg:postcode":"65201",
    "sg:province":"Hessen",
    "wof:name":"Bernd Horcher Rechtsanwalt",
    "wof:placetype":"venue"
},
  "geometry": {"coordinates":[8.192735672,50.0571746826],"type":"Point"}
}