{
  "type": "Feature",
  "properties": {
    "iso:country":"DE",
    "sg:address":"Amtsstr. 23",
    "sg:city":"Bielefeld",
    "sg:phone":"+49 5206/2252",
    "sg:postcode":"33739",
    "sg:province":"Nordrhein-Westfalen",
    "wof:name":"Wilhelm Menke",
    "wof:placetype":"venue"
},
  "geometry": {"coordinates":[8.517106,52.095818],"type":"Point"}
}