{
  "type": "Feature",
  "properties": {
    "iso:country":"DE",
    "sg:address":"F\u00fcrther Str. 46",
    "sg:city":"Erlangen",
    "sg:phone":"+49 9131/63174",
    "sg:postcode":"91058",
    "sg:province":"Bayern",
    "wof:name":"Joachim Schneider",
    "wof:placetype":"venue"
},
  "geometry": {"coordinates":[10.985409,49.572701],"type":"Point"}
}