{
  "type": "Feature",
  "properties": {
    "iso:country":"DE",
    "sg:address":"Hardtstr. 37",
    "sg:city":"Karlsruhe",
    "sg:postcode":"76185",
    "sg:province":"Baden-W\u00fcrttemberg",
    "wof:name":"Seniorenresidenz Schlosspark Meerbusch Betriebsges. Mbh",
    "wof:placetype":"venue"
},
  "geometry": {"coordinates":[8.359011,49.013554],"type":"Point"}
}