{
  "type": "Feature",
  "properties": {
    "iso:country":"DE",
    "sg:address":"Siedlungsweg 3",
    "sg:city":"Lambrechtshagen",
    "sg:phone":"+49 381/8098801",
    "sg:postcode":"18069",
    "sg:province":"Mecklenburg-Vorpommern",
    "wof:name":"Vorsch Estrich-bau Gmbh",
    "wof:placetype":"venue"
},
  "geometry": {"coordinates":[12.016109,54.109024],"type":"Point"}
}