{
  "type": "Feature",
  "properties": {
    "iso:country":"DE",
    "sg:address":"Alte Heerstr. 20a",
    "sg:city":"Goslar",
    "sg:phone":"+49 5321/37370",
    "sg:postcode":"38644",
    "sg:province":"Niedersachsen",
    "wof:name":"Goos & Co.",
    "wof:placetype":"venue"
},
  "geometry": {"coordinates":[10.418683,51.937916],"type":"Point"}
}