{
  "type": "Feature",
  "properties": {
    "iso:country":"DE",
    "sg:address":"Kegelhofstr. 40",
    "sg:city":"Hamburg",
    "sg:postcode":"20251",
    "sg:province":"Hamburg",
    "wof:name":"Green Light E. K.",
    "wof:placetype":"venue"
},
  "geometry": {"coordinates":[9.9792928696,53.5952644348],"type":"Point"}
}