{
  "type": "Feature",
  "properties": {
    "iso:country":"DE",
    "sg:address":"Leonhard-Moll-Bogen 10::",
    "sg:city":"M\u00fcnchen",
    "sg:phone":"+49 4969/75771",
    "sg:postcode":"81373",
    "sg:province":"Bayern",
    "wof:name":"Axa Bank Ag",
    "wof:placetype":"venue"
},
  "geometry": {"coordinates":[8.658923,50.118019],"type":"Point"}
}