{
  "type": "Feature",
  "properties": {
    "iso:country":"DE",
    "sg:address":"Ostwall 20",
    "sg:city":"Dorsten",
    "sg:phone":"+49 4923/621288",
    "sg:postcode":"46282",
    "sg:province":"Nordrhein-Westfalen",
    "wof:name":"Rainer-hermann Beck Gmbh & Co.kg",
    "wof:placetype":"venue"
},
  "geometry": {"coordinates":[6.9735469818,51.6370925903],"type":"Point"}
}