{
  "type": "Feature",
  "properties": {
    "iso:country":"DE",
    "sg:address":"Nordring 40",
    "sg:city":"Bottrop",
    "sg:phone":"+49 2041/92048",
    "sg:postcode":"46240",
    "sg:province":"Nordrhein-Westfalen",
    "wof:name":"Haus H\u00f6lzemann",
    "wof:placetype":"venue"
},
  "geometry": {"coordinates":[6.925620079,51.541759491],"type":"Point"}
}