{
  "type": "Feature",
  "properties": {
    "iso:country":"DE",
    "sg:address":"Knaackstr. 43",
    "sg:city":"Berlin",
    "sg:phone":"+49 30/4416977",
    "sg:postcode":"10435",
    "sg:province":"Berlin",
    "wof:name":"Michael Kny Architekt",
    "wof:placetype":"venue"
},
  "geometry": {"coordinates":[13.416226,52.535881],"type":"Point"}
}