{
  "type": "Feature",
  "properties": {
    "iso:country":"DE",
    "sg:address":"Goslarsche Str. 25",
    "sg:city":"Salzgitter",
    "sg:phone":"+49 5341/331914",
    "sg:postcode":"38259",
    "sg:province":"Niedersachsen",
    "wof:name":"Hartmann",
    "wof:placetype":"venue"
},
  "geometry": {"coordinates":[10.324921608,52.0337219238],"type":"Point"}
}