{
  "type": "Feature",
  "properties": {
    "iso:country":"DE",
    "sg:address":"St\u00f6fsandkate 5",
    "sg:city":"Hamweddel",
    "sg:phone":"+49 4875/583",
    "sg:postcode":"24816",
    "sg:province":"Schleswig-Holstein",
    "wof:name":"Andreas Sievers",
    "wof:placetype":"venue"
},
  "geometry": {"coordinates":[9.611018,54.197742],"type":"Point"}
}