{
  "type": "Feature",
  "properties": {
    "iso:country":"DE",
    "sg:address":"Hauptstr. 168",
    "sg:city":"Stuhr",
    "sg:phone":"+49 421/893766",
    "sg:postcode":"28816",
    "sg:province":"Niedersachsen",
    "wof:name":"Heinrich Haberkamp",
    "wof:placetype":"venue"
},
  "geometry": {"coordinates":[8.725536,52.969269],"type":"Point"}
}