{
  "type": "Feature",
  "properties": {
    "iso:country":"DE",
    "sg:address":"Eduard-Weitsch-Weg 13",
    "sg:city":"Marl",
    "sg:postcode":"45768",
    "sg:province":"Nordrhein-Westfalen",
    "wof:name":"Jugendbibliothek T\u00fcrmchen",
    "wof:placetype":"venue"
},
  "geometry": {"coordinates":[7.094424,51.656864],"type":"Point"}
}