{
  "type": "Feature",
  "properties": {
    "iso:country":"DE",
    "sg:address":"Jacobigang 3",
    "sg:city":"Verden",
    "sg:phone":"+49 4231/82161",
    "sg:postcode":"27283",
    "sg:province":"Niedersachsen",
    "wof:name":"Anke Ringel",
    "wof:placetype":"venue"
},
  "geometry": {"coordinates":[9.229475,52.919804],"type":"Point"}
}