{
  "type": "Feature",
  "properties": {
    "iso:country":"DE",
    "sg:address":"Industriestr. 9 C",
    "sg:city":"Gadebusch",
    "sg:phone":"+49 3886/712454",
    "sg:postcode":"19205",
    "sg:province":"Mecklenburg-Vorpommern",
    "wof:name":"Kowol Bauelemente- Vertriebs Gmbh",
    "wof:placetype":"venue"
},
  "geometry": {"coordinates":[11.134036,53.686539],"type":"Point"}
}