{
  "type": "Feature",
  "properties": {
    "iso:country":"DE",
    "sg:address":"Nerotal 66",
    "sg:city":"Wiesbaden",
    "sg:phone":"+49 611/526066",
    "sg:postcode":"65193",
    "sg:province":"Hessen",
    "wof:name":"Beau Site",
    "wof:placetype":"venue"
},
  "geometry": {"coordinates":[8.2252311707,50.0949516296],"type":"Point"}
}