{
  "type": "Feature",
  "properties": {
    "iso:country":"DE",
    "sg:address":"Karlstr. 1",
    "sg:city":"Rastatt",
    "sg:phone":"+49 7222/34244",
    "sg:postcode":"76437",
    "sg:province":"Baden-W\u00fcrttemberg",
    "wof:name":"Wehrgeschichtliches Museum Rastatt Gmbh",
    "wof:placetype":"venue"
},
  "geometry": {"coordinates":[8.211138,48.855743],"type":"Point"}
}