{
  "type": "Feature",
  "properties": {
    "iso:country":"DE",
    "sg:address":"Schulstr. 10",
    "sg:city":"Luckau",
    "sg:phone":"+49 3544/12121",
    "sg:postcode":"15926",
    "sg:province":"Brandenburg",
    "wof:name":"Ralf John",
    "wof:placetype":"venue"
},
  "geometry": {"coordinates":[13.7124643326,51.8533744812],"type":"Point"}
}