{
  "type": "Feature",
  "properties": {
    "iso:country":"DE",
    "sg:address":"Bussardweg 8",
    "sg:city":"Dassendorf",
    "sg:postcode":"21521",
    "sg:province":"Schleswig-Holstein",
    "wof:name":"Exklusive Stickereien",
    "wof:placetype":"venue"
},
  "geometry": {"coordinates":[10.360558,53.489918],"type":"Point"}
}