{
  "type": "Feature",
  "properties": {
    "iso:country":"DE",
    "sg:address":"Kastanienweg 2",
    "sg:city":"Gnarrenburg",
    "sg:phone":"+49 4763/1621",
    "sg:postcode":"27442",
    "sg:province":"Niedersachsen",
    "wof:name":"Voigt",
    "wof:placetype":"venue"
},
  "geometry": {"coordinates":[9.011305,53.39299],"type":"Point"}
}