{
  "type": "Feature",
  "properties": {
    "iso:country":"DE",
    "sg:address":"In der Haydau",
    "sg:city":"Morschen",
    "sg:phone":"+49 5664/1870",
    "sg:postcode":"34326",
    "sg:province":"Hessen",
    "wof:name":"Willi Kurzrock",
    "wof:placetype":"venue"
},
  "geometry": {"coordinates":[9.617443,51.066692],"type":"Point"}
}