{
  "type": "Feature",
  "properties": {
    "iso:country":"DE",
    "sg:address":"Pasewalker Str. 9",
    "sg:city":"Neubrandenburg",
    "sg:phone":"+49 395/4226339",
    "sg:postcode":"17034",
    "sg:province":"Mecklenburg-Vorpommern",
    "wof:name":"Burkhard Sa\u00df",
    "wof:placetype":"venue"
},
  "geometry": {"coordinates":[13.2727422714,53.5674438477],"type":"Point"}
}