{
  "type": "Feature",
  "properties": {
    "iso:country":"DE",
    "sg:address":"Rundsm\u00fchlhof",
    "sg:city":"Rundsm\u00fchlhof",
    "sg:postcode":"71729",
    "sg:province":"Baden-W\u00fcrttemberg",
    "wof:name":"R. Trautwein",
    "wof:placetype":"venue"
},
  "geometry": {"coordinates":[9.294986,48.939915],"type":"Point"}
}