{
  "type": "Feature",
  "properties": {
    "iso:country":"DE",
    "sg:address":"Lerchenhof 3",
    "sg:city":"Ditzingen",
    "sg:phone":"+49 7156/8171",
    "sg:postcode":"71254",
    "sg:province":"Baden-W\u00fcrttemberg",
    "wof:name":"Karl Siegle",
    "wof:placetype":"venue"
},
  "geometry": {"coordinates":[8.9811,48.840473],"type":"Point"}
}