{
  "type": "Feature",
  "properties": {
    "iso:country":"DE",
    "sg:address":"Hinterbrack 4",
    "sg:city":"Jork",
    "sg:phone":"+49 40/7458434",
    "sg:postcode":"21635",
    "sg:province":"Niedersachsen",
    "wof:name":"E. Pagel",
    "wof:placetype":"venue"
},
  "geometry": {"coordinates":[9.7661123276,53.5455284119],"type":"Point"}
}