{
  "type": "Feature",
  "properties": {
    "iso:country":"DE",
    "sg:address":"Hohentwielstr. 169",
    "sg:city":"Stuttgart",
    "sg:phone":"+49 711/609607",
    "sg:postcode":"70199",
    "sg:province":"Baden-W\u00fcrttemberg",
    "wof:name":"Bernd E. Kr\u00e4mer Architekt",
    "wof:placetype":"venue"
},
  "geometry": {"coordinates":[9.147013,48.7575],"type":"Point"}
}