{
  "type": "Feature",
  "properties": {
    "iso:country":"DE",
    "sg:address":"Schwarzer Weg 32",
    "sg:city":"Hamburg",
    "sg:phone":"+49 40/6312422",
    "sg:postcode":"22309",
    "sg:province":"Hamburg",
    "wof:name":"M & G Sebek Ohg Inh. G. Sebek E. K.",
    "wof:placetype":"venue"
},
  "geometry": {"coordinates":[10.051183,53.607872],"type":"Point"}
}