{
  "type": "Feature",
  "properties": {
    "iso:country":"DE",
    "sg:address":"Dreilindenstr. 64",
    "sg:city":"Berlin",
    "sg:phone":"+49 30/80584590",
    "sg:postcode":"14109",
    "sg:province":"Berlin",
    "wof:name":"Bmeg Medien-entwicklungs- Gmbh",
    "wof:placetype":"venue"
},
  "geometry": {"coordinates":[13.1849813461,52.4207115173],"type":"Point"}
}