{
  "type": "Feature",
  "properties": {
    "iso:country":"DE",
    "sg:address":"Erich-Steinfurth-Str. 1",
    "sg:city":"Teltow",
    "sg:phone":"+49 3328/474625",
    "sg:postcode":"14513",
    "sg:province":"Brandenburg",
    "wof:name":"A. Kiesow",
    "wof:placetype":"venue"
},
  "geometry": {"coordinates":[13.2769489288,52.3984184265],"type":"Point"}
}