{
  "type": "Feature",
  "properties": {
    "iso:country":"DE",
    "sg:address":"Keltenstr. 3",
    "sg:city":"K\u00f6ln",
    "sg:phone":"+49 221/354783",
    "sg:postcode":"50996",
    "sg:province":"Nordrhein-Westfalen",
    "wof:name":"R. Sta\u00dfen",
    "wof:placetype":"venue"
},
  "geometry": {"coordinates":[6.9902949333,50.8880271912],"type":"Point"}
}