{
  "type": "Feature",
  "properties": {
    "iso:country":"DE",
    "sg:address":"Frankenstr. 43",
    "sg:city":"Gro\u00dfrinderfeld",
    "sg:phone":"+49 9349/1389",
    "sg:postcode":"97950",
    "sg:province":"Baden-W\u00fcrttemberg",
    "wof:name":"H & S Software-systeme Gmbh",
    "wof:placetype":"venue"
},
  "geometry": {"coordinates":[9.734960556,49.6623077393],"type":"Point"}
}