{
  "type": "Feature",
  "properties": {
    "iso:country":"DE",
    "sg:address":"Peter-Kl\u00f6ckner-Str. 8",
    "sg:city":"Herschbach",
    "sg:postcode":"56249",
    "sg:province":"Rheinland-Pfalz",
    "wof:name":"Bartels Immobilienservice",
    "wof:placetype":"venue"
},
  "geometry": {"coordinates":[7.7359099388,50.5771217346],"type":"Point"}
}