{
  "type": "Feature",
  "properties": {
    "iso:country":"DE",
    "sg:address":"Am S\u00f6ldnermoos 10",
    "sg:city":"Hallbergmoos",
    "sg:phone":"+49 811/55980",
    "sg:postcode":"85399",
    "sg:province":"Bayern",
    "wof:name":"Base Ten Systems Electronics Gmbh",
    "wof:placetype":"venue"
},
  "geometry": {"coordinates":[11.740079,48.33017],"type":"Point"}
}