{
  "type": "Feature",
  "properties": {
    "iso:country":"DE",
    "sg:address":"Rengelr\u00f6der Weg 17",
    "sg:city":"Heilbad Heiligenstadt",
    "sg:phone":"+49 3606/613856",
    "sg:postcode":"37308",
    "sg:province":"Th\u00fcringen",
    "wof:name":"M. Anna Metze Masseurin",
    "wof:placetype":"venue"
},
  "geometry": {"coordinates":[10.120447,51.375183],"type":"Point"}
}