{
  "type": "Feature",
  "properties": {
    "iso:country":"DE",
    "sg:address":"Martin-K\u00e4rcher-Str. 72",
    "sg:city":"Lampertheim",
    "sg:phone":"+49 6206/911141",
    "sg:postcode":"68623",
    "sg:province":"Hessen",
    "wof:name":"Telefonladen Lampertheim",
    "wof:placetype":"venue"
},
  "geometry": {"coordinates":[8.4724693298,49.598941803],"type":"Point"}
}