{
  "type": "Feature",
  "properties": {
    "iso:country":"DE",
    "sg:address":"L\u00e4rchenstr. 14",
    "sg:city":"Hannover",
    "sg:phone":"+49 511/3180873",
    "sg:postcode":"30161",
    "sg:province":"Niedersachsen",
    "wof:name":"M. Bauer-thunich",
    "wof:placetype":"venue"
},
  "geometry": {"coordinates":[9.755386,52.381256],"type":"Point"}
}