{
  "type": "Feature",
  "properties": {
    "iso:country":"DE",
    "sg:address":"Westfalenring 12",
    "sg:city":"Berlin",
    "sg:phone":"+49 30/7129647",
    "sg:postcode":"12207",
    "sg:province":"Berlin",
    "wof:name":"Carl-friefrich Brumm Ingenieur",
    "wof:placetype":"venue"
},
  "geometry": {"coordinates":[13.3072271347,52.4094390869],"type":"Point"}
}