{
  "type": "Feature",
  "properties": {
    "iso:country":"DE",
    "sg:address":"Aibweg 9",
    "sg:city":"Poxdorf",
    "sg:phone":"+49 9133/2548",
    "sg:postcode":"91099",
    "sg:province":"Bayern",
    "wof:name":"Robert Werner",
    "wof:placetype":"venue"
},
  "geometry": {"coordinates":[11.067909,49.667267],"type":"Point"}
}