{
  "type": "Feature",
  "properties": {
    "iso:country":"DE",
    "sg:address":"Schillerstr. 71",
    "sg:city":"Cottbus",
    "sg:phone":"+49 355/22658",
    "sg:postcode":"03046",
    "sg:province":"Brandenburg",
    "wof:name":"Unternehmerverband Brandenburg E. V.",
    "wof:placetype":"venue"
},
  "geometry": {"coordinates":[14.3239612579,51.7599525452],"type":"Point"}
}