{
  "type": "Feature",
  "properties": {
    "iso:country":"DE",
    "sg:address":"Haller Str. 116",
    "sg:city":"\u00d6hringen",
    "sg:phone":"+49 7941/63178",
    "sg:postcode":"74613",
    "sg:province":"Baden-W\u00fcrttemberg",
    "wof:name":"Ninos Piccola Pizzeria",
    "wof:placetype":"venue"
},
  "geometry": {"coordinates":[9.5165882111,49.1994972229],"type":"Point"}
}