{
  "type": "Feature",
  "properties": {
    "iso:country":"DE",
    "sg:address":"Rh\u00f6nstr. 6",
    "sg:city":"Philippsthal",
    "sg:phone":"+49 6620/456",
    "sg:postcode":"36269",
    "sg:province":"Hessen",
    "wof:name":"Fritz Limburg",
    "wof:placetype":"venue"
},
  "geometry": {"coordinates":[9.9536561966,50.8509902954],"type":"Point"}
}