{
  "type": "Feature",
  "properties": {
    "iso:country":"DE",
    "sg:address":"Behaimring 18",
    "sg:city":"L\u00fcbeck",
    "sg:phone":"+49 451/604801",
    "sg:postcode":"23564",
    "sg:province":"Schleswig-Holstein",
    "wof:name":"Manfred Kasprzak",
    "wof:placetype":"venue"
},
  "geometry": {"coordinates":[10.749487,53.848789],"type":"Point"}
}