{
  "type": "Feature",
  "properties": {
    "iso:country":"DE",
    "sg:address":"Pfarrweg 1",
    "sg:city":"Taufkirchen",
    "sg:phone":"+49 8084/722",
    "sg:postcode":"84416",
    "sg:province":"Bayern",
    "wof:name":"Katholisches Pfarramt",
    "wof:placetype":"venue"
},
  "geometry": {"coordinates":[12.1300582886,48.3467826843],"type":"Point"}
}