{
  "type": "Feature",
  "properties": {
    "iso:country":"DE",
    "sg:address":"Lerchenweg 2",
    "sg:city":"Allmersbach",
    "sg:phone":"+49 7191/59019",
    "sg:postcode":"71573",
    "sg:province":"Baden-W\u00fcrttemberg",
    "wof:name":"Waldemar K\u00fcbler Kohlenhandlung",
    "wof:placetype":"venue"
},
  "geometry": {"coordinates":[9.475567,48.90826],"type":"Point"}
}