{
  "type": "Feature",
  "properties": {
    "iso:country":"DE",
    "sg:address":"Hoher Weg 149",
    "sg:city":"Emmerich",
    "sg:phone":"+49 2822/92927",
    "sg:postcode":"46446",
    "sg:province":"Nordrhein-Westfalen",
    "wof:name":"Ferdinand Gr\u00f6ne",
    "wof:placetype":"venue"
},
  "geometry": {"coordinates":[6.2150020599,51.8528251648],"type":"Point"}
}