{
  "type": "Feature",
  "properties": {
    "iso:country":"DE",
    "sg:address":"Markt 5",
    "sg:city":"Altenburg",
    "sg:phone":"+49 3447/501779",
    "sg:postcode":"04600",
    "sg:province":"Th\u00fcringen",
    "wof:name":"Andreas Vogel",
    "wof:placetype":"venue"
},
  "geometry": {"coordinates":[12.4335851669,50.9851150513],"type":"Point"}
}