{
  "type": "Feature",
  "properties": {
    "iso:country":"DE",
    "sg:address":"Lilienthalstr. 6",
    "sg:city":"Gilching",
    "sg:phone":"+49 8105/9060",
    "sg:postcode":"82205",
    "sg:province":"Bayern",
    "wof:name":"Vfv Verlag F\u00fcr Foto Film Und Video-christian Sauer",
    "wof:placetype":"venue"
},
  "geometry": {"coordinates":[11.2851896286,48.1092948914],"type":"Point"}
}