{
  "type": "Feature",
  "properties": {
    "iso:country":"DE",
    "sg:address":"Cusanusstr. 12",
    "sg:city":"K\u00f6ln",
    "sg:phone":"+49 221/625552",
    "sg:postcode":"51065",
    "sg:province":"Nordrhein-Westfalen",
    "wof:name":"Trude Hakelberg",
    "wof:placetype":"venue"
},
  "geometry": {"coordinates":[7.0063109398,50.9509429932],"type":"Point"}
}