{
  "type": "Feature",
  "properties": {
    "iso:country":"DE",
    "sg:address":"Vogelsang 7",
    "sg:city":"Potsdam",
    "sg:phone":"+49 331/872937",
    "sg:postcode":"14478",
    "sg:province":"Brandenburg",
    "wof:name":"Dr. Walter Schmidt Rechtsanwalt",
    "wof:placetype":"venue"
},
  "geometry": {"coordinates":[13.0806446075,52.3740234375],"type":"Point"}
}