{
  "type": "Feature",
  "properties": {
    "iso:country":"DE",
    "sg:address":"Krugstr. 12",
    "sg:city":"N\u00fcrnberg",
    "sg:phone":"+49 911/3938133",
    "sg:postcode":"90419",
    "sg:province":"Bayern",
    "wof:name":"Pflaumer & Friends Studio Gmbh",
    "wof:placetype":"venue"
},
  "geometry": {"coordinates":[11.0579566956,49.4582977295],"type":"Point"}
}