{
  "type": "Feature",
  "properties": {
    "iso:country":"DE",
    "sg:address":"K\u00f6slinstr. 1",
    "sg:city":"Bonn",
    "sg:phone":"+49 228/9783474",
    "sg:postcode":"53123",
    "sg:province":"Nordrhein-Westfalen",
    "wof:name":"Tour Contact Reiseb\u00fcro Cooperation Gmbh & Co. Kg",
    "wof:placetype":"venue"
},
  "geometry": {"coordinates":[7.0534582138,50.7152557373],"type":"Point"}
}