{
  "type": "Feature",
  "properties": {
    "iso:country":"DE",
    "sg:address":"Oranienburger Stra\u00dfe",
    "sg:city":"Bredow",
    "sg:phone":"+49 3321/48664",
    "sg:postcode":"14641",
    "sg:province":"Brandenburg",
    "wof:name":"Versicherungsagentur Frank Otto - 14641 Bredow",
    "wof:placetype":"venue"
},
  "geometry": {"coordinates":[12.928622,52.588989],"type":"Point"}
}