{
  "type": "Feature",
  "properties": {
    "iso:country":"DE",
    "sg:address":"Euskirchener Str. 66",
    "sg:city":"K\u00f6ln",
    "sg:phone":"+49 221/283980",
    "sg:postcode":"50935",
    "sg:province":"Nordrhein-Westfalen",
    "wof:name":"Gemeinn. Wohnungsgenossen- Schaft Am Vorgebirgspark Eg",
    "wof:placetype":"venue"
},
  "geometry": {"coordinates":[6.9135789871,50.9165306091],"type":"Point"}
}