{
  "type": "Feature",
  "properties": {
    "iso:country":"DE",
    "sg:address":"Kohlengasse 1",
    "sg:city":"Heroldsberg",
    "sg:phone":"+49 911/5187266",
    "sg:postcode":"90562",
    "sg:province":"Bayern",
    "wof:name":"Andreas Heinz Bock",
    "wof:placetype":"venue"
},
  "geometry": {"coordinates":[11.152213,49.532917],"type":"Point"}
}