{
  "type": "Feature",
  "properties": {
    "iso:country":"DE",
    "sg:address":"Westfaelische Str. 251 Brackel",
    "sg:city":"Dortmund",
    "sg:phone":"+49 4923/125060",
    "sg:postcode":"44309",
    "sg:province":"Nordrhein-Westfalen",
    "wof:name":"Tremonis Gmbh",
    "wof:placetype":"venue"
},
  "geometry": {"coordinates":[7.551245,51.524025],"type":"Point"}
}