{
  "type": "Feature",
  "properties": {
    "iso:country":"DE",
    "sg:address":"Haagstr. 63",
    "sg:city":"Moers",
    "sg:phone":"+49 2841/23623",
    "sg:postcode":"47441",
    "sg:province":"Nordrhein-Westfalen",
    "wof:name":"Axel Burk Architekt",
    "wof:placetype":"venue"
},
  "geometry": {"coordinates":[6.623053,51.451599],"type":"Point"}
}