{
  "type": "Feature",
  "properties": {
    "iso:country":"DE",
    "sg:address":"Eckendorfer Str. 70",
    "sg:city":"Bielefeld",
    "sg:phone":"+49 521/3059741",
    "sg:postcode":"33609",
    "sg:province":"Nordrhein-Westfalen",
    "wof:name":"Sekmann Pkw Und Lkw Aufbereitung Gmbh",
    "wof:placetype":"venue"
},
  "geometry": {"coordinates":[8.568235,52.035553],"type":"Point"}
}