{
  "type": "Feature",
  "properties": {
    "iso:country":"DE",
    "sg:address":"Albert-Schweitzer-Str. 76",
    "sg:city":"Celle",
    "sg:phone":"+49 4421/51911",
    "sg:postcode":"29223",
    "sg:province":"Niedersachsen",
    "wof:name":"Dr. Med. Peter Schaps",
    "wof:placetype":"venue"
},
  "geometry": {"coordinates":[10.0978908539,52.6290969849],"type":"Point"}
}