{
  "type": "Feature",
  "properties": {
    "iso:country":"DE",
    "sg:address":"Bahnhofstr. 11",
    "sg:city":"Suhl",
    "sg:phone":"+49 3681/722515",
    "sg:postcode":"98527",
    "sg:province":"Th\u00fcringen",
    "wof:name":"M\u00fcnchener Verein Versicherungsgruppe",
    "wof:placetype":"venue"
},
  "geometry": {"coordinates":[10.6876888275,50.6075935364],"type":"Point"}
}