{
  "type": "Feature",
  "properties": {
    "iso:country":"DE",
    "sg:address":"Langemarckstr. 128",
    "sg:city":"Bremen",
    "sg:phone":"+49 421/592404",
    "sg:postcode":"28199",
    "sg:province":"Bremen",
    "wof:name":"Jan's Brutzelbude",
    "wof:placetype":"venue"
},
  "geometry": {"coordinates":[8.7899055481,53.071308136],"type":"Point"}
}