{
  "type": "Feature",
  "properties": {
    "iso:country":"DE",
    "sg:address":"Sportallee 2",
    "sg:city":"Hamburg",
    "sg:phone":"+49 40/5111448",
    "sg:postcode":"22335",
    "sg:province":"Hamburg",
    "wof:name":"F. Arnold Bank E. K.",
    "wof:placetype":"venue"
},
  "geometry": {"coordinates":[9.9997329712,53.6144752502],"type":"Point"}
}