{
  "type": "Feature",
  "properties": {
    "iso:country":"DE",
    "sg:address":"Moselstr. 4",
    "sg:city":"Falkensee",
    "sg:phone":"+49 3322/209233",
    "sg:postcode":"14612",
    "sg:province":"Brandenburg",
    "wof:name":"Manfred Fuhl",
    "wof:placetype":"venue"
},
  "geometry": {"coordinates":[13.067889,52.584808],"type":"Point"}
}