{
  "type": "Feature",
  "properties": {
    "iso:country":"DE",
    "sg:address":"Ludwigring 10",
    "sg:city":"Rastatt",
    "sg:postcode":"76437",
    "sg:province":"Baden-W\u00fcrttemberg",
    "wof:name":"Maschu Gmbh",
    "wof:placetype":"venue"
},
  "geometry": {"coordinates":[8.212171,48.854797],"type":"Point"}
}