{
  "type": "Feature",
  "properties": {
    "iso:country":"DE",
    "sg:address":"Henleinstr. 1",
    "sg:city":"Stuhr",
    "sg:phone":"+49 421/86360",
    "sg:postcode":"28816",
    "sg:province":"Niedersachsen",
    "wof:name":"Ratio-reisen",
    "wof:placetype":"venue"
},
  "geometry": {"coordinates":[8.8004083633,53.0269088745],"type":"Point"}
}