{
  "type": "Feature",
  "properties": {
    "iso:country":"DE",
    "sg:address":"Baumreute 11",
    "sg:city":"Stuttgart",
    "sg:phone":"+49 711/6406960",
    "sg:postcode":"70199",
    "sg:province":"Baden-W\u00fcrttemberg",
    "wof:name":"Richard Kasen Ingenieur",
    "wof:placetype":"venue"
},
  "geometry": {"coordinates":[9.1469764709,48.7611351013],"type":"Point"}
}