{
  "type": "Feature",
  "properties": {
    "iso:country":"DE",
    "sg:address":"Madlower Hauptstr. 10",
    "sg:city":"Cottbus",
    "sg:phone":"+49 355/522342",
    "sg:postcode":"03050",
    "sg:province":"Brandenburg",
    "wof:name":"Dr. Horst Fehler Tierarzt",
    "wof:placetype":"venue"
},
  "geometry": {"coordinates":[14.3398199081,51.7300720215],"type":"Point"}
}