{
  "type": "Feature",
  "properties": {
    "iso:country":"DE",
    "sg:address":"Gibitzenhofstr. 186",
    "sg:city":"N\u00fcrnberg",
    "sg:phone":"+49 911/416604",
    "sg:postcode":"90443",
    "sg:province":"Bayern",
    "wof:name":"R. Stark",
    "wof:placetype":"venue"
},
  "geometry": {"coordinates":[11.0650157928,49.4291152954],"type":"Point"}
}