{
  "type": "Feature",
  "properties": {
    "iso:country":"DE",
    "sg:address":"Ernst-Th\u00e4lmann-Str. 13",
    "sg:city":"Hohenm\u00f6lsen",
    "sg:postcode":"06679",
    "sg:province":"Sachsen-Anhalt",
    "wof:name":"Wasserversorgung Und Abwasserbehandlung Halle Gmbh",
    "wof:placetype":"venue"
},
  "geometry": {"coordinates":[12.1024837494,51.1553421021],"type":"Point"}
}