{
  "type": "Feature",
  "properties": {
    "iso:country":"DE",
    "sg:address":"Stuckenborsteler Str. 21",
    "sg:city":"Sottrum",
    "sg:phone":"+49 4264/1456",
    "sg:postcode":"27367",
    "sg:province":"Niedersachsen",
    "wof:name":"Helmut Wahlers",
    "wof:placetype":"venue"
},
  "geometry": {"coordinates":[9.175114,53.105629],"type":"Point"}
}