{
  "type": "Feature",
  "properties": {
    "iso:country":"DE",
    "sg:address":"Mausestr. 1",
    "sg:city":"Salzgitter",
    "sg:phone":"+49 5341/27688",
    "sg:postcode":"38239",
    "sg:province":"Niedersachsen",
    "wof:name":"Reginas Trink- Und Imbi\u00dfst\u00fcbchen",
    "wof:placetype":"venue"
},
  "geometry": {"coordinates":[10.4054203033,52.147518158],"type":"Point"}
}