{
  "type": "Feature",
  "properties": {
    "iso:country":"DE",
    "sg:address":"Kirchstr. 2",
    "sg:city":"Rheinsberg",
    "sg:phone":"+49 33931/2138",
    "sg:postcode":"16831",
    "sg:province":"Brandenburg",
    "wof:name":"H. Und J. Aertel",
    "wof:placetype":"venue"
},
  "geometry": {"coordinates":[12.8929691315,53.1003952026],"type":"Point"}
}