{
  "type": "Feature",
  "properties": {
    "iso:country":"DE",
    "sg:address":"Saidelsteig 3",
    "sg:city":"Erlangen",
    "sg:postcode":"91058",
    "sg:province":"Bayern",
    "wof:name":"Windkraftanlage Raitersaich Gmbh & Co. Kg",
    "wof:placetype":"venue"
},
  "geometry": {"coordinates":[11.023493,49.552784],"type":"Point"}
}