{
  "type": "Feature",
  "properties": {
    "iso:country":"DE",
    "sg:address":"Bochumer Landstr. 146",
    "sg:city":"Essen",
    "sg:phone":"+49 201/530035",
    "sg:postcode":"45276",
    "sg:province":"Nordrhein-Westfalen",
    "wof:name":"Karl Epler Gmbh",
    "wof:placetype":"venue"
},
  "geometry": {"coordinates":[7.091116,51.444759],"type":"Point"}
}