{
  "type": "Feature",
  "properties": {
    "iso:country":"DE",
    "sg:address":"Dormagener Str. 43",
    "sg:city":"Bergheim",
    "sg:phone":"+49 2271/52473",
    "sg:postcode":"50129",
    "sg:province":"Nordrhein-Westfalen",
    "wof:name":"E. Werner",
    "wof:placetype":"venue"
},
  "geometry": {"coordinates":[6.671369,50.98254],"type":"Point"}
}