{
  "type": "Feature",
  "properties": {
    "iso:country":"DE",
    "sg:address":"Stuttgarter Str. 15",
    "sg:city":"Eislingen",
    "sg:phone":"+49 7161/83743",
    "sg:postcode":"73054",
    "sg:province":"Baden-W\u00fcrttemberg",
    "wof:name":"Kreuzinger",
    "wof:placetype":"venue"
},
  "geometry": {"coordinates":[9.704313,48.694237],"type":"Point"}
}