{
  "type": "Feature",
  "properties": {
    "iso:country":"DE",
    "sg:address":"Am Wiesenhof 24",
    "sg:city":"Wilhelmshaven",
    "sg:phone":"+49 4421/82722",
    "sg:postcode":"26389",
    "sg:province":"Niedersachsen",
    "wof:name":"Dieter Borsch Architekt",
    "wof:placetype":"venue"
},
  "geometry": {"coordinates":[8.08888,53.536095],"type":"Point"}
}