{
  "type": "Feature",
  "properties": {
    "iso:country":"DE",
    "sg:address":"Pfarrgasse 98",
    "sg:city":"Helmershausen",
    "sg:phone":"+49 36943/60019",
    "sg:postcode":"98617",
    "sg:province":"Th\u00fcringen",
    "wof:name":"R. Bloh",
    "wof:placetype":"venue"
},
  "geometry": {"coordinates":[10.237638,50.562843],"type":"Point"}
}