{
  "type": "Feature",
  "properties": {
    "iso:country":"DE",
    "sg:address":"Lichtensteinstr. 45",
    "sg:city":"Pliezhausen",
    "sg:phone":"+49 7127/9750",
    "sg:postcode":"72124",
    "sg:province":"Baden-W\u00fcrttemberg",
    "wof:name":"Hotel Sch\u00f6nbuch",
    "wof:placetype":"venue"
},
  "geometry": {"coordinates":[9.1979999542,48.5619773865],"type":"Point"}
}