{
  "type": "Feature",
  "properties": {
    "iso:country":"DE",
    "sg:address":"Herner Str. 243",
    "sg:city":"Recklinghausen",
    "sg:phone":"+49 2361/34630",
    "sg:postcode":"45659",
    "sg:province":"Nordrhein-Westfalen",
    "wof:name":"M. Herdrich",
    "wof:placetype":"venue"
},
  "geometry": {"coordinates":[7.212373,51.583782],"type":"Point"}
}