{
  "type": "Feature",
  "properties": {
    "iso:country":"DE",
    "sg:address":"Watzenweg 1",
    "sg:city":"Hamburg",
    "sg:phone":"+49 40/7302809",
    "sg:postcode":"21033",
    "sg:province":"Hamburg",
    "wof:name":"C. K\u00fcbler-marten",
    "wof:placetype":"venue"
},
  "geometry": {"coordinates":[10.19213,53.502232],"type":"Point"}
}