{
  "type": "Feature",
  "properties": {
    "iso:country":"DE",
    "sg:address":"Jagstheimer Hauptstr. 67",
    "sg:city":"Crailsheim",
    "sg:phone":"+49 7951/5872",
    "sg:postcode":"74564",
    "sg:province":"Baden-W\u00fcrttemberg",
    "wof:name":"Volker Pr\u00e4g",
    "wof:placetype":"venue"
},
  "geometry": {"coordinates":[10.066228,49.098217],"type":"Point"}
}