{
  "type": "Feature",
  "properties": {
    "iso:country":"DE",
    "sg:address":"Wettersteinstr. 5 a",
    "sg:city":"Gr\u00f6benzell",
    "sg:phone":"+49 8142/540344",
    "sg:postcode":"82194",
    "sg:province":"Bayern",
    "wof:name":"Hermann Schultz",
    "wof:placetype":"venue"
},
  "geometry": {"coordinates":[11.370508,48.187141],"type":"Point"}
}