{
  "type": "Feature",
  "properties": {
    "iso:country":"DE",
    "sg:address":"Alter Postweg 2",
    "sg:city":"Emskirchen",
    "sg:phone":"+49 9104/2593",
    "sg:postcode":"91448",
    "sg:province":"Bayern",
    "wof:name":"Dipl.ing. Paul Wezel Architekt Und Architekt",
    "wof:placetype":"venue"
},
  "geometry": {"coordinates":[10.72167,49.546658],"type":"Point"}
}