{
  "type": "Feature",
  "properties": {
    "iso:country":"DE",
    "sg:address":"Kottwitzstr. 16",
    "sg:city":"L\u00fcbeck",
    "sg:phone":"+49 451/63996",
    "sg:postcode":"23566",
    "sg:province":"Schleswig-Holstein",
    "wof:name":"Alt Marli",
    "wof:placetype":"venue"
},
  "geometry": {"coordinates":[10.7138166428,53.8707008362],"type":"Point"}
}