{
  "type": "Feature",
  "properties": {
    "iso:country":"DE",
    "sg:address":"An der Bahn 11",
    "sg:city":"Adendorf",
    "sg:phone":"+49 4131/990586",
    "sg:postcode":"21365",
    "sg:province":"Niedersachsen",
    "wof:name":"Goom Music",
    "wof:placetype":"venue"
},
  "geometry": {"coordinates":[10.4532012939,53.2810287476],"type":"Point"}
}