{
  "type": "Feature",
  "properties": {
    "iso:country":"DE",
    "sg:address":"Bahnhofstr. 3",
    "sg:city":"Fulda",
    "sg:phone":"+49 661/72624",
    "sg:postcode":"36037",
    "sg:province":"Hessen",
    "wof:name":"Jahn Grundst\u00fccks- Verwaltung Gmbh",
    "wof:placetype":"venue"
},
  "geometry": {"coordinates":[9.6796979904,50.5526542664],"type":"Point"}
}