{
  "type": "Feature",
  "properties": {
    "iso:country":"DE",
    "sg:address":"Hauptstr. 51",
    "sg:city":"Seefeld",
    "sg:phone":"+49 8152/7378",
    "sg:postcode":"82229",
    "sg:province":"Bayern",
    "wof:name":"Kath. Pfarramt St. Michael",
    "wof:placetype":"venue"
},
  "geometry": {"coordinates":[11.1867723465,48.0337677002],"type":"Point"}
}