{
  "type": "Feature",
  "properties": {
    "iso:country":"DE",
    "sg:address":"Konrad-Adenauer-Str. 7",
    "sg:city":"Datteln",
    "sg:phone":"+49 2363/34745",
    "sg:postcode":"45711",
    "sg:province":"Nordrhein-Westfalen",
    "wof:name":"A. Krause",
    "wof:placetype":"venue"
},
  "geometry": {"coordinates":[7.3249092102,51.6525917053],"type":"Point"}
}