{
  "type": "Feature",
  "properties": {
    "iso:country":"DE",
    "sg:address":"Siegfriedstr. 3",
    "sg:city":"Neus\u00e4\u00df",
    "sg:phone":"+49 821/463666",
    "sg:postcode":"86356",
    "sg:province":"Bayern",
    "wof:name":"Evelyn Kraus",
    "wof:placetype":"venue"
},
  "geometry": {"coordinates":[10.82975,48.397663],"type":"Point"}
}