{
  "type": "Feature",
  "properties": {
    "iso:country":"DE",
    "sg:address":"Akazienring 60",
    "sg:city":"Hochheim",
    "sg:phone":"+49 6145/6576",
    "sg:postcode":"65239",
    "sg:province":"Hessen",
    "wof:name":"Horst Eckert Architekt",
    "wof:placetype":"venue"
},
  "geometry": {"coordinates":[8.375507,50.035015],"type":"Point"}
}