{
  "type": "Feature",
  "properties": {
    "iso:country":"DE",
    "sg:address":"Arndtstr. 2",
    "sg:city":"Markkleeberg",
    "sg:phone":"+49 341/3380320",
    "sg:postcode":"04416",
    "sg:province":"Sachsen",
    "wof:name":"Blumenfreund Feindt",
    "wof:placetype":"venue"
},
  "geometry": {"coordinates":[12.397794,51.27747],"type":"Point"}
}