{
  "type": "Feature",
  "properties": {
    "iso:country":"DE",
    "sg:address":"Frankenwaldstr. 1",
    "sg:city":"Wallenfels",
    "sg:phone":"+49 9262/1313",
    "sg:postcode":"96346",
    "sg:province":"Bayern",
    "wof:name":"I. Guillemaille",
    "wof:placetype":"venue"
},
  "geometry": {"coordinates":[11.4736633301,50.2677116394],"type":"Point"}
}