{
  "type": "Feature",
  "properties": {
    "iso:country":"DE",
    "sg:address":"Bergstr. 1",
    "sg:city":"Bad Wildbad",
    "sg:phone":"+49 7081/6492",
    "sg:postcode":"75323",
    "sg:province":"Baden-W\u00fcrttemberg",
    "wof:name":"Museum",
    "wof:placetype":"venue"
},
  "geometry": {"coordinates":[8.5821647644,48.7748374939],"type":"Point"}
}