{
  "type": "Feature",
  "properties": {
    "iso:country":"DE",
    "sg:address":"Jahnstr. 1",
    "sg:city":"Sankt Augustin",
    "sg:phone":"+49 2241/316886",
    "sg:postcode":"53757",
    "sg:province":"Nordrhein-Westfalen",
    "wof:name":"Hotel Jahnstuben",
    "wof:placetype":"venue"
},
  "geometry": {"coordinates":[7.1709890366,50.7894592285],"type":"Point"}
}