{
  "type": "Feature",
  "properties": {
    "iso:country":"DE",
    "sg:address":"Hauptstr. 38",
    "sg:city":"Missen-Wilhams",
    "sg:phone":"+49 8320/210",
    "sg:postcode":"87547",
    "sg:province":"Bayern",
    "wof:name":"Schwarz Holzbau E. K.",
    "wof:placetype":"venue"
},
  "geometry": {"coordinates":[10.1216564178,47.5988922119],"type":"Point"}
}