{
  "type": "Feature",
  "properties": {
    "iso:country":"DE",
    "sg:address":"D\u00fcsseldorfer Str. 192",
    "sg:city":"D\u00fcsseldorf",
    "sg:phone":"+49 211/5772420",
    "sg:postcode":"40545",
    "sg:province":"Nordrhein-Westfalen",
    "wof:name":"Hamburg-mannheimer Versicherungsgesellschaften",
    "wof:placetype":"venue"
},
  "geometry": {"coordinates":[6.7407531738,51.2306671143],"type":"Point"}
}