{
  "type": "Feature",
  "properties": {
    "iso:country":"DE",
    "sg:address":"Hauptstr. 241",
    "sg:city":"Bergisch Gladbach",
    "sg:phone":"+49 2202/33807",
    "sg:postcode":"51465",
    "sg:province":"Nordrhein-Westfalen",
    "wof:name":"Franz Fischer",
    "wof:placetype":"venue"
},
  "geometry": {"coordinates":[7.133806,50.991817],"type":"Point"}
}