{
  "type": "Feature",
  "properties": {
    "iso:country":"DE",
    "sg:address":"Kreuzstr. 7",
    "sg:city":"Elzach",
    "sg:phone":"+49 7682/1815",
    "sg:postcode":"79215",
    "sg:province":"Baden-W\u00fcrttemberg",
    "wof:name":"W. Burger",
    "wof:placetype":"venue"
},
  "geometry": {"coordinates":[8.069826,48.172394],"type":"Point"}
}