{
  "type": "Feature",
  "properties": {
    "iso:country":"DE",
    "sg:address":"Stralsunder Ring 3",
    "sg:city":"Leimen",
    "sg:postcode":"69181",
    "sg:province":"Baden-W\u00fcrttemberg",
    "wof:name":"Emmel Verwaltungs- Gmbh",
    "wof:placetype":"venue"
},
  "geometry": {"coordinates":[8.686811,49.355877],"type":"Point"}
}