{
  "type": "Feature",
  "properties": {
    "iso:country":"DE",
    "sg:address":"Hofgartenstr. 29",
    "sg:city":"Troisdorf",
    "sg:phone":"+49 2241/809636",
    "sg:postcode":"53840",
    "sg:province":"Nordrhein-Westfalen",
    "wof:name":"Thielcke Und Waldbrunn Ergotherapeutische Praxis",
    "wof:placetype":"venue"
},
  "geometry": {"coordinates":[7.163833,50.811584],"type":"Point"}
}