{
  "type": "Feature",
  "properties": {
    "iso:country":"DE",
    "sg:address":"Eichendorffstr. 30",
    "sg:city":"Bad Sch\u00f6nborn",
    "sg:phone":"+49 7253/4640",
    "sg:postcode":"76669",
    "sg:province":"Baden-W\u00fcrttemberg",
    "wof:name":"G\u00fcnter Zabler Elektro-install.",
    "wof:placetype":"venue"
},
  "geometry": {"coordinates":[8.649632,49.225353],"type":"Point"}
}