{
  "type": "Feature",
  "properties": {
    "iso:country":"DE",
    "sg:address":"Hirschgasse 1",
    "sg:city":"Memmingen",
    "sg:phone":"+49 8331/4032",
    "sg:postcode":"87700",
    "sg:province":"Bayern",
    "wof:name":"Radio Prima 1 Memmingen Und Unterallg\u00e4u Gmbh",
    "wof:placetype":"venue"
},
  "geometry": {"coordinates":[10.182762146,47.9829750061],"type":"Point"}
}