{
  "type": "Feature",
  "properties": {
    "iso:country":"DE",
    "sg:address":"Schlachthausgasse 1",
    "sg:city":"Deggendorf",
    "sg:phone":"+49 991/6744",
    "sg:postcode":"94469",
    "sg:province":"Bayern",
    "wof:name":"Tele Und Com Professionelle Communications Systeme Gmbh",
    "wof:placetype":"venue"
},
  "geometry": {"coordinates":[12.9614362717,48.834564209],"type":"Point"}
}