{
  "type": "Feature",
  "properties": {
    "iso:country":"DE",
    "sg:address":"Moosbachstr. 10",
    "sg:city":"Bretzfeld",
    "sg:phone":"+49 7946/1095",
    "sg:postcode":"74626",
    "sg:province":"Baden-W\u00fcrttemberg",
    "wof:name":"Sm Strukturmetall Gmbh",
    "wof:placetype":"venue"
},
  "geometry": {"coordinates":[9.41035,49.18317],"type":"Point"}
}