{
  "type": "Feature",
  "properties": {
    "iso:country":"DE",
    "sg:address":"Im Pappelhof 1",
    "sg:city":"Singen",
    "sg:phone":"+49 7731/26464",
    "sg:postcode":"78224",
    "sg:province":"Baden-W\u00fcrttemberg",
    "wof:name":"Th. Relling Baustatik Gmbh",
    "wof:placetype":"venue"
},
  "geometry": {"coordinates":[8.8340997696,47.7567405701],"type":"Point"}
}