{
  "type": "Feature",
  "properties": {
    "iso:country":"DE",
    "sg:address":"Kaufbeurer Str. 89",
    "sg:city":"Kempten",
    "sg:phone":"+49 831/574570",
    "sg:postcode":"87437",
    "sg:province":"Bayern",
    "wof:name":"Bosch Telecom Gmbh",
    "wof:placetype":"venue"
},
  "geometry": {"coordinates":[10.3231525421,47.7363853455],"type":"Point"}
}