{
  "type": "Feature",
  "properties": {
    "iso:country":"DE",
    "sg:address":"Salzpf\u00e4nnerstr. 1",
    "sg:city":"Bad Salzdetfurth",
    "sg:phone":"+49 5063/4129",
    "sg:postcode":"31162",
    "sg:province":"Niedersachsen",
    "wof:name":"Restaurant Zur Altstadt",
    "wof:placetype":"venue"
},
  "geometry": {"coordinates":[10.0091362,52.0643539429],"type":"Point"}
}