{
  "type": "Feature",
  "properties": {
    "iso:country":"DE",
    "sg:address":"Rathenaustra\u00dfe 48",
    "sg:city":"Erfurt",
    "sg:phone":"+49 361/5402204",
    "sg:postcode":"99085",
    "sg:province":"Th\u00fcringen",
    "wof:name":"Malermeister Klaus Tittmann",
    "wof:placetype":"venue"
},
  "geometry": {"coordinates":[11.044932,50.981346],"type":"Point"}
}