{
  "type": "Feature",
  "properties": {
    "iso:country":"DE",
    "sg:address":"Wilhelm-Hoffmann-Str. 23",
    "sg:city":"Bechtolsheim",
    "sg:phone":"+49 6733/7439",
    "sg:postcode":"55234",
    "sg:province":"Rheinland-Pfalz",
    "wof:name":"Bernhard Breivogel",
    "wof:placetype":"venue"
},
  "geometry": {"coordinates":[8.19834,49.803711],"type":"Point"}
}