{
  "type": "Feature",
  "properties": {
    "iso:country":"DE",
    "sg:address":"Hohenecker Str. 26",
    "sg:city":"Kaiserslautern",
    "sg:postcode":"67663",
    "sg:province":"Rheinland-Pfalz",
    "wof:name":"E-center",
    "wof:placetype":"venue"
},
  "geometry": {"coordinates":[7.7407360077,49.4322547913],"type":"Point"}
}