{
  "type": "Feature",
  "properties": {
    "iso:country":"DE",
    "sg:address":"Templiner Str. 5",
    "sg:city":"Gransee",
    "sg:phone":"+49 3306/2602",
    "sg:postcode":"16775",
    "sg:province":"Brandenburg",
    "wof:name":"Stadt Gransee",
    "wof:placetype":"venue"
},
  "geometry": {"coordinates":[13.164431572,53.005607605],"type":"Point"}
}