{
  "type": "Feature",
  "properties": {
    "iso:country":"DE",
    "sg:address":"Lauenburger Str. 65-67",
    "sg:city":"Geesthacht",
    "sg:postcode":"21502",
    "sg:province":"Schleswig-Holstein",
    "wof:name":"Quintas-analytische Verfahren- Verwaltungsgesellschaft Mbh",
    "wof:placetype":"venue"
},
  "geometry": {"coordinates":[10.38304,53.43465],"type":"Point"}
}