{
  "type": "Feature",
  "properties": {
    "iso:country":"DE",
    "sg:address":"Friedensstr. 21",
    "sg:city":"Haidem\u00fchl",
    "sg:postcode":"03130",
    "sg:province":"Brandenburg",
    "wof:name":"Sid Spremberger- Industrie-dienst Gmbh",
    "wof:placetype":"venue"
},
  "geometry": {"coordinates":[14.42307,51.578732],"type":"Point"}
}