{
  "type": "Feature",
  "properties": {
    "iso:country":"DE",
    "sg:address":"Kasseler Str. 41",
    "sg:city":"Witzenhausen",
    "sg:phone":"+49 5542/910213",
    "sg:postcode":"37215",
    "sg:province":"Hessen",
    "wof:name":"Bernhard Morth & Birgitt Simon",
    "wof:placetype":"venue"
},
  "geometry": {"coordinates":[9.8475093842,51.2942276001],"type":"Point"}
}