{
  "type": "Feature",
  "properties": {
    "iso:country":"DE",
    "sg:address":"Gro\u00dfe Str. 1",
    "sg:city":"Verden",
    "sg:phone":"+49 4231/8010",
    "sg:postcode":"27283",
    "sg:province":"Niedersachsen",
    "wof:name":"Kreiszeitung Verlags- Gesellschaft Mbh",
    "wof:placetype":"venue"
},
  "geometry": {"coordinates":[9.2281608582,52.9242553711],"type":"Point"}
}