{
  "type": "Feature",
  "properties": {
    "iso:country":"DE",
    "sg:address":"Am Kielsgraben 2-4",
    "sg:city":"Monheim",
    "sg:phone":"+49 2173/5950",
    "sg:postcode":"40789",
    "sg:province":"Nordrhein-Westfalen",
    "wof:name":"Odermath Stahl- Werkstechnik Gmbh",
    "wof:placetype":"venue"
},
  "geometry": {"coordinates":[6.8875198364,51.1065254211],"type":"Point"}
}