{
  "type": "Feature",
  "properties": {
    "iso:country":"DE",
    "sg:address":"Hindenburgstr. 22",
    "sg:city":"\u00d6lbronn-D\u00fcrrn",
    "sg:phone":"+49 7043/6836",
    "sg:postcode":"75248",
    "sg:province":"Baden-W\u00fcrttemberg",
    "wof:name":"Eberhard Hagmann",
    "wof:placetype":"venue"
},
  "geometry": {"coordinates":[8.750912,48.98381],"type":"Point"}
}