{
  "type": "Feature",
  "properties": {
    "iso:country":"DE",
    "sg:address":"Detmolder Str. 13",
    "sg:city":"Schlangen",
    "sg:phone":"+49 5252/985555",
    "sg:postcode":"33189",
    "sg:province":"Nordrhein-Westfalen",
    "wof:name":"Auto-deckers Service-team Gmbh",
    "wof:placetype":"venue"
},
  "geometry": {"coordinates":[8.8450584412,51.8110771179],"type":"Point"}
}