{
  "type": "Feature",
  "properties": {
    "iso:country":"DE",
    "sg:address":"Zur Hellwies 8",
    "sg:city":"Beckingen",
    "sg:phone":"+49 6835/4041",
    "sg:postcode":"66701",
    "sg:province":"Saarland",
    "wof:name":"Sporthotel Honzrath Gmbh",
    "wof:placetype":"venue"
},
  "geometry": {"coordinates":[6.740708828,49.430431366],"type":"Point"}
}