{
  "type": "Feature",
  "properties": {
    "iso:country":"DE",
    "sg:address":"Minkwitzweg 1",
    "sg:city":"Ortrand",
    "sg:phone":"+49 35755/50816",
    "sg:postcode":"01990",
    "sg:province":"Brandenburg",
    "wof:name":"Ingrid Weigel",
    "wof:placetype":"venue"
},
  "geometry": {"coordinates":[13.768609,51.370888],"type":"Point"}
}