{
  "type": "Feature",
  "properties": {
    "iso:country":"DE",
    "sg:address":"Adenauerallee 9",
    "sg:city":"Wallenhorst",
    "sg:phone":"+49 5407/5833",
    "sg:postcode":"49134",
    "sg:province":"Niedersachsen",
    "wof:name":"Ahpart Ges. F\u00fcr Patent-vertrieb Mbh",
    "wof:placetype":"venue"
},
  "geometry": {"coordinates":[7.9733200073,52.3467521667],"type":"Point"}
}