{
  "type": "Feature",
  "properties": {
    "iso:country":"DE",
    "sg:address":"Berliner Chaussee 29a",
    "sg:city":"Genthin",
    "sg:phone":"+49 3933/91204",
    "sg:postcode":"39307",
    "sg:province":"Sachsen-Anhalt",
    "wof:name":"Heran Gmbh",
    "wof:placetype":"venue"
},
  "geometry": {"coordinates":[12.1748180389,52.4080276489],"type":"Point"}
}