{
  "type": "Feature",
  "properties": {
    "iso:country":"DE",
    "sg:address":"Hauptstr. 54",
    "sg:city":"Baden-Baden",
    "sg:phone":"+49 7221/75286",
    "sg:postcode":"76534",
    "sg:province":"Baden-W\u00fcrttemberg",
    "wof:name":"K\u00f6ninger",
    "wof:placetype":"venue"
},
  "geometry": {"coordinates":[8.258573,48.744759],"type":"Point"}
}