{
  "type": "Feature",
  "properties": {
    "iso:country":"DE",
    "sg:address":"Ohmstr. 19",
    "sg:city":"Wiesbaden",
    "sg:phone":"+49 611/460053",
    "sg:postcode":"65199",
    "sg:province":"Hessen",
    "wof:name":"Dorit Schwalbach-khayyer Rechtsanw\u00e4ltin",
    "wof:placetype":"venue"
},
  "geometry": {"coordinates":[8.1952209473,50.0793380737],"type":"Point"}
}