{
  "type": "Feature",
  "properties": {
    "iso:country":"DE",
    "sg:address":"Rodstr. 6",
    "sg:city":"K\u00f6ln",
    "sg:phone":"+49 221/635163",
    "sg:postcode":"51067",
    "sg:province":"Nordrhein-Westfalen",
    "wof:name":"Hans-jochen Baudach Architekt",
    "wof:placetype":"venue"
},
  "geometry": {"coordinates":[7.0496,50.970444],"type":"Point"}
}