{
  "type": "Feature",
  "properties": {
    "iso:country":"DE",
    "sg:address":"Unnaer Str. 33 a",
    "sg:city":"Kamen",
    "sg:phone":"+49 2307/73956",
    "sg:postcode":"59174",
    "sg:province":"Nordrhein-Westfalen",
    "wof:name":"Franz Josef Kr\u00e4mer",
    "wof:placetype":"venue"
},
  "geometry": {"coordinates":[7.6651558876,51.5829467773],"type":"Point"}
}