{
  "type": "Feature",
  "properties": {
    "iso:country":"DE",
    "sg:address":"Kloppbergstr. 21",
    "sg:city":"Dittelsheim-He\u00dfloch",
    "sg:phone":"+49 6244/7050",
    "sg:postcode":"67596",
    "sg:province":"Rheinland-Pfalz",
    "wof:name":"H.-p. Taube",
    "wof:placetype":"venue"
},
  "geometry": {"coordinates":[8.2248792648,49.7434272766],"type":"Point"}
}