{
  "type": "Feature",
  "properties": {
    "iso:country":"DE",
    "sg:address":"Lange Geismarstr. 42",
    "sg:city":"G\u00f6ttingen",
    "sg:phone":"+49 551/57272",
    "sg:postcode":"37073",
    "sg:province":"Niedersachsen",
    "wof:name":"Woll Tex",
    "wof:placetype":"venue"
},
  "geometry": {"coordinates":[9.935451,51.531807],"type":"Point"}
}