{
  "type": "Feature",
  "properties": {
    "iso:country":"DE",
    "sg:address":"Kirchenstr. 14",
    "sg:city":"M\u00fcnchen",
    "sg:phone":"+49 89/4484454",
    "sg:postcode":"81675",
    "sg:province":"Bayern",
    "wof:name":"Lorenz Hagl",
    "wof:placetype":"venue"
},
  "geometry": {"coordinates":[11.600563,48.133945],"type":"Point"}
}