{
  "type": "Feature",
  "properties": {
    "iso:country":"DE",
    "sg:address":"Geretsrieder Str. 26",
    "sg:city":"Waldkraiburg",
    "sg:phone":"+49 8638/2077",
    "sg:postcode":"84478",
    "sg:province":"Bayern",
    "wof:name":"Markus Bernhard",
    "wof:placetype":"venue"
},
  "geometry": {"coordinates":[12.412056,48.212612],"type":"Point"}
}