{
  "type": "Feature",
  "properties": {
    "iso:country":"DE",
    "sg:address":"Finkenstr. 12",
    "sg:city":"Ottersweier",
    "sg:phone":"+49 7223/26458",
    "sg:postcode":"77833",
    "sg:province":"Baden-W\u00fcrttemberg",
    "wof:name":"Marlene K\u00f6nig",
    "wof:placetype":"venue"
},
  "geometry": {"coordinates":[8.109277,48.679932],"type":"Point"}
}