{
  "type": "Feature",
  "properties": {
    "iso:country":"DE",
    "sg:address":"An der Brake 107",
    "sg:city":"Weyhe",
    "sg:postcode":"28844",
    "sg:province":"Niedersachsen",
    "wof:name":"Home : Die Schule Mit Der Kuh",
    "wof:placetype":"venue"
},
  "geometry": {"coordinates":[8.828402,52.963722],"type":"Point"}
}