{
  "type": "Feature",
  "properties": {
    "iso:country":"DE",
    "sg:address":"An der Hasenjagd 8",
    "sg:city":"Remscheid",
    "sg:phone":"+49 2191/99890",
    "sg:postcode":"42897",
    "sg:province":"Nordrhein-Westfalen",
    "wof:name":"Hartmut Th\u00f6ne Steuerberater",
    "wof:placetype":"venue"
},
  "geometry": {"coordinates":[7.2440347672,51.1834182739],"type":"Point"}
}