{
  "type": "Feature",
  "properties": {
    "iso:country":"DE",
    "sg:address":"Stefan-George-Str. 20",
    "sg:city":"Bingen",
    "sg:phone":"+49 6721/1880",
    "sg:postcode":"55411",
    "sg:province":"Rheinland-Pfalz",
    "wof:name":"Pott-racke-dujardin Verwaltungsgesellschaft Mbh",
    "wof:placetype":"venue"
},
  "geometry": {"coordinates":[7.892863,49.962215],"type":"Point"}
}