{
  "type": "Feature",
  "properties": {
    "iso:country":"DE",
    "sg:address":"Friedensstr. 4",
    "sg:city":"Perleberg",
    "sg:phone":"+49 3876/613265",
    "sg:postcode":"19348",
    "sg:province":"Brandenburg",
    "wof:name":"Klaus-dieter Hartung",
    "wof:placetype":"venue"
},
  "geometry": {"coordinates":[11.866741,53.070129],"type":"Point"}
}