{
  "type": "Feature",
  "properties": {
    "iso:country":"DE",
    "sg:address":"Weringhauser Str. 17",
    "sg:city":"Erwitte",
    "sg:phone":"+49 2943/809161",
    "sg:postcode":"59597",
    "sg:province":"Nordrhein-Westfalen",
    "wof:name":"Hellweg-sole-thermen",
    "wof:placetype":"venue"
},
  "geometry": {"coordinates":[8.347057,51.632778],"type":"Point"}
}