{
  "type": "Feature",
  "properties": {
    "iso:country":"DE",
    "sg:address":"Postfach 1261:: 48303 Senden:: Germany.^^Eintrachtstr 5::",
    "sg:city":"Senden",
    "sg:phone":"+49 2597/9110",
    "sg:postcode":"48308",
    "sg:province":"Nordrhein-Westfalen",
    "wof:name":"Volksbank Senden Eg",
    "wof:placetype":"venue"
},
  "geometry": {"coordinates":[7.483098,51.857323],"type":"Point"}
}