{
  "type": "Feature",
  "properties": {
    "iso:country":"DE",
    "sg:address":"Reifferscheidstr. 3",
    "sg:city":"H\u00fcrth",
    "sg:phone":"+49 2233/74831",
    "sg:postcode":"50354",
    "sg:province":"Nordrhein-Westfalen",
    "wof:name":"W. Hennecke Architekt",
    "wof:placetype":"venue"
},
  "geometry": {"coordinates":[6.889119,50.883106],"type":"Point"}
}