{
  "type": "Feature",
  "properties": {
    "iso:country":"DE",
    "sg:address":"Kissinger Str. 34",
    "sg:city":"Steingaden",
    "sg:phone":"+49 8862/376",
    "sg:postcode":"86989",
    "sg:province":"Bayern",
    "wof:name":"Roman Fischer",
    "wof:placetype":"venue"
},
  "geometry": {"coordinates":[10.868518,47.702366],"type":"Point"}
}