{
  "type": "Feature",
  "properties": {
    "iso:country":"DE",
    "sg:address":"St.-Lukas-Str. 7",
    "sg:city":"Oberammergau",
    "sg:phone":"+49 8822/6883",
    "sg:postcode":"82487",
    "sg:province":"Bayern",
    "wof:name":"Georg H\u00f6ldrich Immobilienmakler",
    "wof:placetype":"venue"
},
  "geometry": {"coordinates":[11.0655927658,47.5988311768],"type":"Point"}
}