{
  "type": "Feature",
  "properties": {
    "iso:country":"DE",
    "sg:address":"Auf der Heide 44",
    "sg:city":"Stolberg",
    "sg:phone":"+49 2402/3280",
    "sg:postcode":"52223",
    "sg:province":"Nordrhein-Westfalen",
    "wof:name":"Joy",
    "wof:placetype":"venue"
},
  "geometry": {"coordinates":[6.213873,50.731266],"type":"Point"}
}