{
  "type": "Feature",
  "properties": {
    "iso:country":"DE",
    "sg:address":"Kaiserstr. 7",
    "sg:city":"Hildesheim",
    "sg:phone":"+49 5121/14430",
    "sg:postcode":"31134",
    "sg:province":"Niedersachsen",
    "wof:name":"Senioren-notruf Hildesheim Mobiler Hilfs- Und",
    "wof:placetype":"venue"
},
  "geometry": {"coordinates":[9.950159,52.155678],"type":"Point"}
}