{
  "type": "Feature",
  "properties": {
    "iso:country":"DE",
    "sg:address":"Opelstr. 2",
    "sg:city":"Konstanz",
    "sg:phone":"+49 8247/39070",
    "sg:postcode":"78467",
    "sg:province":"Baden-W\u00fcrttemberg",
    "wof:name":"Dronania Gmbh",
    "wof:placetype":"venue"
},
  "geometry": {"coordinates":[10.601422,48.025257],"type":"Point"}
}