{
  "type": "Feature",
  "properties": {
    "iso:country":"DE",
    "sg:address":"Bismarckring 67",
    "sg:city":"Biberach",
    "sg:phone":"+49 7351/74146",
    "sg:postcode":"88400",
    "sg:province":"Baden-W\u00fcrttemberg",
    "wof:name":"Koch Und Rubitschon Ergotherapeutische Praxis",
    "wof:placetype":"venue"
},
  "geometry": {"coordinates":[9.79261,48.100224],"type":"Point"}
}