{
  "type": "Feature",
  "properties": {
    "iso:country":"DE",
    "sg:address":"Gummersbacher Str. 47",
    "sg:city":"Gummersbach",
    "sg:phone":"+49 2261/910051",
    "sg:postcode":"51645",
    "sg:province":"Nordrhein-Westfalen",
    "wof:name":"Frick Gmbh",
    "wof:placetype":"venue"
},
  "geometry": {"coordinates":[7.5715370178,51.00963974],"type":"Point"}
}