{
  "type": "Feature",
  "properties": {
    "iso:country":"DE",
    "sg:address":"Mozartstr. 8",
    "sg:city":"Hagenbach",
    "sg:phone":"+49 7273/2348",
    "sg:postcode":"76767",
    "sg:province":"Rheinland-Pfalz",
    "wof:name":"Karl Kn\u00f6ll Ingenieur",
    "wof:placetype":"venue"
},
  "geometry": {"coordinates":[8.2467241287,49.0223007202],"type":"Point"}
}