{
  "type": "Feature",
  "properties": {
    "iso:country":"DE",
    "sg:address":"Paul-Ehrlich-Weg 6",
    "sg:city":"Bad Homburg",
    "sg:phone":"+49 6172/269595",
    "sg:postcode":"61348",
    "sg:province":"Hessen",
    "wof:name":"Fj-immobilien E. Kfm.",
    "wof:placetype":"venue"
},
  "geometry": {"coordinates":[8.6257610321,50.2301635742],"type":"Point"}
}