{
  "type": "Feature",
  "properties": {
    "iso:country":"DE",
    "sg:address":"Henkestr. 26",
    "sg:city":"Erlangen",
    "sg:phone":"+49 9131/19410",
    "sg:postcode":"91054",
    "sg:province":"Bayern",
    "wof:name":"Taxi Erlangen Eg",
    "wof:placetype":"venue"
},
  "geometry": {"coordinates":[11.0086917877,49.5938682556],"type":"Point"}
}