{
  "type": "Feature",
  "properties": {
    "iso:country":"DE",
    "sg:address":"Berlinstrasse 103",
    "sg:city":"Bingen am Rhein / B\u00fcdesheim",
    "sg:phone":"+49 6721/402262",
    "sg:postcode":"55411",
    "sg:province":"Rheinland-Pfalz",
    "wof:name":"Andreas Stein\u00b4s Dienstleistungsunternehmen",
    "wof:placetype":"venue"
},
  "geometry": {"coordinates":[7.92194,49.953068],"type":"Point"}
}