{
  "type": "Feature",
  "properties": {
    "iso:country":"DE",
    "sg:address":"Untere Burgbergstr. 24",
    "sg:city":"Lichtenfels",
    "sg:phone":"+49 9571/72132",
    "sg:postcode":"96215",
    "sg:province":"Bayern",
    "wof:name":"Margit Morhard",
    "wof:placetype":"venue"
},
  "geometry": {"coordinates":[11.06542,50.140339],"type":"Point"}
}