{
  "type": "Feature",
  "properties": {
    "iso:country":"DE",
    "sg:address":"Eckstr. 15",
    "sg:city":"Babenhausen",
    "sg:phone":"+49 6073/2354",
    "sg:postcode":"64832",
    "sg:province":"Hessen",
    "wof:name":"Gottfried Kolb",
    "wof:placetype":"venue"
},
  "geometry": {"coordinates":[8.908038,49.941013],"type":"Point"}
}