{
  "type": "Feature",
  "properties": {
    "iso:country":"DE",
    "sg:address":"Im Unterdorf 10",
    "sg:city":"Erden",
    "sg:phone":"+49 6532/3452",
    "sg:postcode":"54492",
    "sg:province":"Rheinland-Pfalz",
    "wof:name":"Hermann-josef Schwaab-scherr",
    "wof:placetype":"venue"
},
  "geometry": {"coordinates":[7.0253720284,49.9788627625],"type":"Point"}
}