{
  "type": "Feature",
  "properties": {
    "iso:country":"DE",
    "sg:address":"An der Alster 57-63",
    "sg:city":"Hamburg",
    "sg:phone":"+49 40/344311",
    "sg:postcode":"20099",
    "sg:province":"Hamburg",
    "wof:name":"Alster-finanz Beratung F\u00fcr Betriebliche",
    "wof:placetype":"venue"
},
  "geometry": {"coordinates":[10.00717,53.558247],"type":"Point"}
}