{
  "type": "Feature",
  "properties": {
    "iso:country":"DE",
    "sg:address":"Walkm\u00fchlstr. 25a",
    "sg:city":"Wiesbaden",
    "sg:phone":"+49 611/402860",
    "sg:postcode":"65195",
    "sg:province":"Hessen",
    "wof:name":"Rudolf Sch\u00fcrmann Architekt",
    "wof:placetype":"venue"
},
  "geometry": {"coordinates":[8.225151,50.086926],"type":"Point"}
}