{
  "type": "Feature",
  "properties": {
    "iso:country":"DE",
    "sg:address":"Bennstr. 8",
    "sg:city":"Deidesheim",
    "sg:phone":"+49 6326/6654",
    "sg:postcode":"67146",
    "sg:province":"Rheinland-Pfalz",
    "wof:name":"Werner Fischer",
    "wof:placetype":"venue"
},
  "geometry": {"coordinates":[8.1837282181,49.4077377319],"type":"Point"}
}