{
  "type": "Feature",
  "properties": {
    "iso:country":"DE",
    "sg:address":"Tirschenreuther Ring 68",
    "sg:city":"Berlin",
    "sg:phone":"+49 30/7218683",
    "sg:postcode":"12279",
    "sg:province":"Berlin",
    "wof:name":"Dirk Kaya",
    "wof:placetype":"venue"
},
  "geometry": {"coordinates":[13.355323,52.409901],"type":"Point"}
}