{
  "type": "Feature",
  "properties": {
    "iso:country":"DE",
    "sg:address":"Seestr. 36",
    "sg:city":"Gaildorf",
    "sg:phone":"+49 7971/4370",
    "sg:postcode":"74405",
    "sg:province":"Baden-W\u00fcrttemberg",
    "wof:name":"A. Und K. Braun",
    "wof:placetype":"venue"
},
  "geometry": {"coordinates":[9.7597408295,49.0010948181],"type":"Point"}
}