{
  "type": "Feature",
  "properties": {
    "iso:country":"DE",
    "sg:address":"Am Lausitzpark",
    "sg:city":"Gro\u00df Gaglow",
    "sg:postcode":"03058",
    "sg:province":"Brandenburg",
    "wof:name":"Jeans Fritz",
    "wof:placetype":"venue"
},
  "geometry": {"coordinates":[14.321517,51.71505],"type":"Point"}
}