{
  "type": "Feature",
  "properties": {
    "iso:country":"DE",
    "sg:address":"Steinerstr. 48",
    "sg:city":"Werl",
    "sg:postcode":"59457",
    "sg:province":"Nordrhein-Westfalen",
    "wof:name":"Plan Bautr\u00e4ger Gmbh",
    "wof:placetype":"venue"
},
  "geometry": {"coordinates":[7.914976,51.54966],"type":"Point"}
}