{
  "type": "Feature",
  "properties": {
    "iso:country":"DE",
    "sg:address":"Schuhstr. 31",
    "sg:city":"Erlangen",
    "sg:postcode":"91052",
    "sg:province":"Bayern",
    "wof:name":"Eck Beteiligungs- Gmbh",
    "wof:placetype":"venue"
},
  "geometry": {"coordinates":[11.008553,49.593246],"type":"Point"}
}