{
  "type": "Feature",
  "properties": {
    "iso:country":"DE",
    "sg:address":"Lingelmannstr. 3",
    "sg:city":"Dinslaken",
    "sg:phone":"+49 4920/6480314",
    "sg:postcode":"46539",
    "sg:province":"Nordrhein-Westfalen",
    "wof:name":"B & D Holzbau Fassaden Ausholz + Kunststoff Sowietreppenbau Gmbh",
    "wof:placetype":"venue"
},
  "geometry": {"coordinates":[6.7935099602,51.5631980896],"type":"Point"}
}