{
  "type": "Feature",
  "properties": {
    "iso:country":"DE",
    "sg:address":"Bavariaring 2",
    "sg:city":"M\u00fcnchen",
    "sg:phone":"+49 89/514550",
    "sg:postcode":"80336",
    "sg:province":"Bayern",
    "wof:name":"Allfood Lebensmittel- Handels Gmbh",
    "wof:placetype":"venue"
},
  "geometry": {"coordinates":[11.5497837067,48.1368751526],"type":"Point"}
}