{
  "type": "Feature",
  "properties": {
    "iso:country":"DE",
    "sg:address":"Gartenstr. 28",
    "sg:city":"Zellingen",
    "sg:phone":"+49 9364/1304",
    "sg:postcode":"97225",
    "sg:province":"Bayern",
    "wof:name":"Gerd Endrich",
    "wof:placetype":"venue"
},
  "geometry": {"coordinates":[9.816339,49.894821],"type":"Point"}
}