{
  "type": "Feature",
  "properties": {
    "iso:country":"DE",
    "sg:address":"Bisten 6",
    "sg:city":"Hinterzarten",
    "sg:phone":"+49 7652/1665",
    "sg:postcode":"79856",
    "sg:province":"Baden-W\u00fcrttemberg",
    "wof:name":"G\u00e4stehaus Georg Thoma",
    "wof:placetype":"venue"
},
  "geometry": {"coordinates":[8.0769939423,47.9087409973],"type":"Point"}
}