{
  "type": "Feature",
  "properties": {
    "iso:country":"DE",
    "sg:address":"Bahnstr. 19",
    "sg:city":"Mendig",
    "sg:phone":"+49 2652/51294",
    "sg:postcode":"56743",
    "sg:province":"Rheinland-Pfalz",
    "wof:name":"J. Lohner",
    "wof:placetype":"venue"
},
  "geometry": {"coordinates":[7.283264,50.371082],"type":"Point"}
}