{
  "type": "Feature",
  "properties": {
    "iso:country":"DE",
    "sg:address":"Allinger Strasse 30",
    "sg:city":"Eichenau",
    "sg:phone":"+49 8141/328602",
    "sg:postcode":"82223",
    "sg:province":"Bayern",
    "wof:name":"Flechsig & Walter (fuw)",
    "wof:placetype":"venue"
},
  "geometry": {"coordinates":[11.3290958405,48.1721343994],"type":"Point"}
}