{
  "type": "Feature",
  "properties": {
    "iso:country":"DE",
    "sg:address":"Servatiusweg 25",
    "sg:city":"Bornheim",
    "sg:phone":"+49 2222/2476",
    "sg:postcode":"53332",
    "sg:province":"Nordrhein-Westfalen",
    "wof:name":"Kath. Pfarramt St. Servatius",
    "wof:placetype":"venue"
},
  "geometry": {"coordinates":[6.9903497696,50.7617416382],"type":"Point"}
}