{
  "type": "Feature",
  "properties": {
    "iso:country":"DE",
    "sg:address":"Creidlitzer Str. 61",
    "sg:city":"Coburg",
    "sg:phone":"+49 9561/18000",
    "sg:postcode":"96450",
    "sg:province":"Bayern",
    "wof:name":"Werner Bauersachs",
    "wof:placetype":"venue"
},
  "geometry": {"coordinates":[10.9793453217,50.2344169617],"type":"Point"}
}