{
  "type": "Feature",
  "properties": {
    "iso:country":"DE",
    "sg:address":"Hannebach 30",
    "sg:city":"Gro\u00dfheirath",
    "sg:phone":"+49 9565/7660",
    "sg:postcode":"96269",
    "sg:province":"Bayern",
    "wof:name":"Fahrenholz Luft- Und Klimatechnik Gmbh",
    "wof:placetype":"venue"
},
  "geometry": {"coordinates":[10.943545,50.16674],"type":"Point"}
}