{
  "type": "Feature",
  "properties": {
    "iso:country":"DE",
    "sg:address":"Frommannstr. 12",
    "sg:city":"N\u00fcrnberg",
    "sg:phone":"+49 911/332520",
    "sg:postcode":"90419",
    "sg:province":"Bayern",
    "wof:name":"Richard Und Rud. Loock",
    "wof:placetype":"venue"
},
  "geometry": {"coordinates":[11.0722551346,49.4586143494],"type":"Point"}
}