{
  "type": "Feature",
  "properties": {
    "iso:country":"DE",
    "sg:address":"Zwirnerstr. 35",
    "sg:city":"K\u00f6ln",
    "sg:phone":"+49 221/313770",
    "sg:postcode":"50678",
    "sg:province":"Nordrhein-Westfalen",
    "wof:name":"Anton Schlee",
    "wof:placetype":"venue"
},
  "geometry": {"coordinates":[6.961712,50.926441],"type":"Point"}
}