{
  "type": "Feature",
  "properties": {
    "iso:country":"DE",
    "sg:address":"Lange Str. 3",
    "sg:city":"L\u00fcnen",
    "sg:phone":"+49 2306/14722",
    "sg:postcode":"44532",
    "sg:province":"Nordrhein-Westfalen",
    "wof:name":"H. Will Zahn\u00e4rztebedarf",
    "wof:placetype":"venue"
},
  "geometry": {"coordinates":[7.52782,51.587921],"type":"Point"}
}