{
  "type": "Feature",
  "properties": {
    "iso:country":"DE",
    "sg:address":"Haunw\u00f6hrer Str. 11",
    "sg:city":"Ingolstadt",
    "sg:phone":"+49 841/85089",
    "sg:postcode":"85051",
    "sg:province":"Bayern",
    "wof:name":"Restaurant Betrieb Zellner Gmbh",
    "wof:placetype":"venue"
},
  "geometry": {"coordinates":[11.4297552109,48.7530860901],"type":"Point"}
}