{
  "type": "Feature",
  "properties": {
    "iso:country":"DE",
    "sg:address":"Huteweg 4 b",
    "sg:city":"Marburg",
    "sg:phone":"+49 6421/83285",
    "sg:postcode":"35041",
    "sg:province":"Hessen",
    "wof:name":"St. Elisabeth-apotheke Inh. Barbara G\u00f6tz-schwarze",
    "wof:placetype":"venue"
},
  "geometry": {"coordinates":[8.755935,50.836063],"type":"Point"}
}