{
  "type": "Feature",
  "properties": {
    "iso:country":"DE",
    "sg:address":"Rheinstr. 13",
    "sg:city":"Wagh\u00e4usel",
    "sg:phone":"+49 7254/73077",
    "sg:postcode":"68753",
    "sg:province":"Baden-W\u00fcrttemberg",
    "wof:name":"Beckmann Immobilienmakler",
    "wof:placetype":"venue"
},
  "geometry": {"coordinates":[8.5563430786,49.2443084717],"type":"Point"}
}