{
  "type": "Feature",
  "properties": {
    "iso:country":"DE",
    "sg:address":"Alte Potsdamer Landstr. 43",
    "sg:city":"Stahnsdorf",
    "sg:phone":"+49 3329/62280",
    "sg:postcode":"14532",
    "sg:province":"Brandenburg",
    "wof:name":"Fook Lam Mun",
    "wof:placetype":"venue"
},
  "geometry": {"coordinates":[13.2014408112,52.392906189],"type":"Point"}
}