{
  "type": "Feature",
  "properties": {
    "iso:country":"DE",
    "sg:address":"M\u00fchlgrundweg 11",
    "sg:city":"Freudenberg",
    "sg:phone":"+49 9375/668",
    "sg:postcode":"97896",
    "sg:province":"Baden-W\u00fcrttemberg",
    "wof:name":"Schwimmbad",
    "wof:placetype":"venue"
},
  "geometry": {"coordinates":[9.3222646713,49.7571601868],"type":"Point"}
}