{
  "type": "Feature",
  "properties": {
    "iso:country":"DE",
    "sg:address":"Kiebitzweg 2",
    "sg:city":"Schenefeld",
    "sg:phone":"+49 40/83931010",
    "sg:postcode":"22869",
    "sg:province":"Schleswig-Holstein",
    "wof:name":"Rudolf Schramm Steuerberater",
    "wof:placetype":"venue"
},
  "geometry": {"coordinates":[9.8361644745,53.6024703979],"type":"Point"}
}