{
  "type": "Feature",
  "properties": {
    "iso:country":"DE",
    "sg:address":"Sachsenring 77",
    "sg:city":"K\u00f6ln",
    "sg:phone":"+49 221/327045",
    "sg:postcode":"50677",
    "sg:province":"Nordrhein-Westfalen",
    "wof:name":"Institut Francais Centre De Documentation Etd",
    "wof:placetype":"venue"
},
  "geometry": {"coordinates":[6.948981,50.925098],"type":"Point"}
}