{
  "type": "Feature",
  "properties": {
    "iso:country":"DE",
    "sg:address":"An der Gro\u00dfen Mauer 34",
    "sg:city":"Blomberg",
    "sg:phone":"+49 5235/7352",
    "sg:postcode":"32825",
    "sg:province":"Nordrhein-Westfalen",
    "wof:name":"Bernd Potthast",
    "wof:placetype":"venue"
},
  "geometry": {"coordinates":[9.091456,51.944839],"type":"Point"}
}