{
  "type": "Feature",
  "properties": {
    "iso:country":"DE",
    "sg:address":"Teutschenthaler Landstr.",
    "sg:city":"Halle",
    "sg:postcode":"06126",
    "sg:province":"Sachsen-Anhalt",
    "wof:name":"K\u00f6ppe-verwaltungs Gmbh",
    "wof:placetype":"venue"
},
  "geometry": {"coordinates":[11.88428,51.478825],"type":"Point"}
}