{
  "type": "Feature",
  "properties": {
    "iso:country":"DE",
    "sg:address":"Basler Str. 82",
    "sg:city":"Schallstadt",
    "sg:phone":"+49 7664/60180",
    "sg:postcode":"79227",
    "sg:province":"Baden-W\u00fcrttemberg",
    "wof:name":"Batzenberg-apotheke",
    "wof:placetype":"venue"
},
  "geometry": {"coordinates":[7.755834,47.95657],"type":"Point"}
}