{
  "type": "Feature",
  "properties": {
    "iso:country":"DE",
    "sg:address":"Stadtg. 1-2 Marktplatz",
    "sg:city":"Biedenkopf",
    "sg:phone":"+49 4964/612194",
    "sg:postcode":"35216",
    "sg:province":"Hessen",
    "wof:name":"Druckerei Unverzagt",
    "wof:placetype":"venue"
},
  "geometry": {"coordinates":[8.5247526169,50.9131469727],"type":"Point"}
}