{
  "type": "Feature",
  "properties": {
    "iso:country":"DE",
    "sg:address":"Am Vogelsang 27",
    "sg:city":"Schneverdingen",
    "sg:phone":"+49 5193/2402",
    "sg:postcode":"29640",
    "sg:province":"Niedersachsen",
    "wof:name":"Hm Fliesenverlegung Gmbh",
    "wof:placetype":"venue"
},
  "geometry": {"coordinates":[9.791879,53.108158],"type":"Point"}
}