{
  "type": "Feature",
  "properties": {
    "iso:country":"DE",
    "sg:address":"R\u00f6merstr. 32",
    "sg:city":"Bornheim",
    "sg:phone":"+49 2236/5150",
    "sg:postcode":"53332",
    "sg:province":"Nordrhein-Westfalen",
    "wof:name":"Josef Kuhl",
    "wof:placetype":"venue"
},
  "geometry": {"coordinates":[7.023822,50.794376],"type":"Point"}
}