{
  "type": "Feature",
  "properties": {
    "iso:country":"DE",
    "sg:address":"Wettelsheimer Str. 73",
    "sg:city":"Treuchtlingen",
    "sg:phone":"+49 9142/5957",
    "sg:postcode":"91757",
    "sg:province":"Bayern",
    "wof:name":"Erwin Ortner",
    "wof:placetype":"venue"
},
  "geometry": {"coordinates":[10.9062623978,48.9614524841],"type":"Point"}
}