{
  "type": "Feature",
  "properties": {
    "iso:country":"DE",
    "sg:address":"Hauptstr. 61",
    "sg:city":"Saalstadt",
    "sg:phone":"+49 6375/5815",
    "sg:postcode":"66919",
    "sg:province":"Rheinland-Pfalz",
    "wof:name":"Willi Weis",
    "wof:placetype":"venue"
},
  "geometry": {"coordinates":[7.546109,49.324223],"type":"Point"}
}