{
  "type": "Feature",
  "properties": {
    "iso:country":"DE",
    "sg:address":"Wippert 27",
    "sg:city":"Steinfurt",
    "sg:phone":"+49 2551/82433",
    "sg:postcode":"48565",
    "sg:province":"Nordrhein-Westfalen",
    "wof:name":"Ludger Holling",
    "wof:placetype":"venue"
},
  "geometry": {"coordinates":[7.3380908966,52.1492042542],"type":"Point"}
}