{
  "type": "Feature",
  "properties": {
    "iso:country":"DE",
    "sg:address":"Nordstr. 24",
    "sg:city":"J\u00fclich",
    "sg:phone":"+49 2461/8097",
    "sg:postcode":"52428",
    "sg:province":"Nordrhein-Westfalen",
    "wof:name":"Horst Merres Ingenieur",
    "wof:placetype":"venue"
},
  "geometry": {"coordinates":[6.3578138351,50.9329566956],"type":"Point"}
}