{
  "type": "Feature",
  "properties": {
    "iso:country":"DE",
    "sg:address":"Habichtstr. 15",
    "sg:city":"Vohburg",
    "sg:phone":"+49 8457/1373",
    "sg:postcode":"85088",
    "sg:province":"Bayern",
    "wof:name":"Johann Schr\u00f6dl",
    "wof:placetype":"venue"
},
  "geometry": {"coordinates":[11.6111,48.767319],"type":"Point"}
}