{
  "type": "Feature",
  "properties": {
    "iso:country":"DE",
    "sg:address":"Limbacher Str. 32",
    "sg:city":"Homburg",
    "sg:phone":"+49 4968/486399",
    "sg:postcode":"66424",
    "sg:province":"Saarland",
    "wof:name":"Karl Preis Gmbh",
    "wof:placetype":"venue"
},
  "geometry": {"coordinates":[7.3114438057,49.285194397],"type":"Point"}
}