{
  "type": "Feature",
  "properties": {
    "iso:country":"DE",
    "sg:address":"Mittorpstr. 43",
    "sg:city":"Gelsenkirchen",
    "sg:phone":"+49 209/47408",
    "sg:postcode":"45883",
    "sg:province":"Nordrhein-Westfalen",
    "wof:name":"Volker Keldenich Rechtsanwalt",
    "wof:placetype":"venue"
},
  "geometry": {"coordinates":[7.0575780869,51.5259094238],"type":"Point"}
}