{
  "type": "Feature",
  "properties": {
    "iso:country":"DE",
    "sg:address":"Dorheimer Str. 18",
    "sg:city":"Friedberg",
    "sg:phone":"+49 6031/5016",
    "sg:postcode":"61169",
    "sg:province":"Hessen",
    "wof:name":"Adolf Jost",
    "wof:placetype":"venue"
},
  "geometry": {"coordinates":[8.771913,50.330517],"type":"Point"}
}