{
  "type": "Feature",
  "properties": {
    "iso:country":"DE",
    "sg:address":"Altehofgasse 2",
    "sg:city":"Dittelsheim-He\u00dfloch",
    "sg:phone":"+49 6244/7437",
    "sg:postcode":"67596",
    "sg:province":"Rheinland-Pfalz",
    "wof:name":"Helmut Metzler",
    "wof:placetype":"venue"
},
  "geometry": {"coordinates":[8.2273206711,49.7459259033],"type":"Point"}
}