{
  "type": "Feature",
  "properties": {
    "iso:country":"DE",
    "sg:address":"Heidenschanze 6-8",
    "sg:city":"Dresden",
    "sg:phone":"+49 351/430590",
    "sg:postcode":"01189",
    "sg:province":"Sachsen",
    "wof:name":"Dresdner Sprengschule Gmbh",
    "wof:placetype":"venue"
},
  "geometry": {"coordinates":[13.6861486435,51.0189361572],"type":"Point"}
}