{
  "type": "Feature",
  "properties": {
    "iso:country":"DE",
    "sg:address":"Johann-Usener-Str. 3",
    "sg:city":"Frankfurt",
    "sg:phone":"+49 6109/33033",
    "sg:postcode":"60388",
    "sg:province":"Hessen",
    "wof:name":"Reinhard R. Mican Gmbh",
    "wof:placetype":"venue"
},
  "geometry": {"coordinates":[8.760587,50.154274],"type":"Point"}
}