{
  "type": "Feature",
  "properties": {
    "iso:country":"DE",
    "sg:address":"Maubisstr. 8",
    "sg:city":"Kaarst",
    "sg:phone":"+49 2131/794600",
    "sg:postcode":"41564",
    "sg:province":"Nordrhein-Westfalen",
    "wof:name":"Rudolf Und Wolfgang Winne Steuerberater",
    "wof:placetype":"venue"
},
  "geometry": {"coordinates":[6.6185832024,51.2312202454],"type":"Point"}
}