{
  "type": "Feature",
  "properties": {
    "iso:country":"DE",
    "sg:address":"Gro\u00dfg\u00f6rschenstr. 2",
    "sg:city":"Berlin",
    "sg:postcode":"10827",
    "sg:province":"Berlin",
    "wof:name":"Drehbuchautor",
    "wof:placetype":"venue"
},
  "geometry": {"coordinates":[13.361532,52.491154],"type":"Point"}
}