{
  "type": "Feature",
  "properties": {
    "iso:country":"DE",
    "sg:address":"Ginsterweg 1",
    "sg:city":"Laar",
    "sg:postcode":"49824",
    "sg:province":"Niedersachsen",
    "wof:name":"Fonville Gmbh",
    "wof:placetype":"venue"
},
  "geometry": {"coordinates":[6.7592377663,52.6251602173],"type":"Point"}
}