{
  "type": "Feature",
  "properties": {
    "iso:country":"DE",
    "sg:address":"Katzenbacher Str. 2",
    "sg:city":"Niedermohr",
    "sg:phone":"+49 6383/458",
    "sg:postcode":"66879",
    "sg:province":"Rheinland-Pfalz",
    "wof:name":"Restaurant Il Pirata",
    "wof:placetype":"venue"
},
  "geometry": {"coordinates":[7.4815320969,49.4569778442],"type":"Point"}
}