{
  "type": "Feature",
  "properties": {
    "iso:country":"DE",
    "sg:address":"Alois-Gall-Str. 5",
    "sg:city":"Maxh\u00fctte-Haidhof",
    "sg:phone":"+49 9471/2288",
    "sg:postcode":"93142",
    "sg:province":"Bayern",
    "wof:name":"Gabriele Sch\u00fcler Hebamme",
    "wof:placetype":"venue"
},
  "geometry": {"coordinates":[12.103438,49.197403],"type":"Point"}
}