{
  "type": "Feature",
  "properties": {
    "iso:country":"DE",
    "sg:address":"Friedenstr. 13",
    "sg:city":"Oedheim",
    "sg:phone":"+49 7136/21520",
    "sg:postcode":"74229",
    "sg:province":"Baden-W\u00fcrttemberg",
    "wof:name":"Karl Robert Leist Architekt",
    "wof:placetype":"venue"
},
  "geometry": {"coordinates":[9.251994,49.243847],"type":"Point"}
}