{
  "type": "Feature",
  "properties": {
    "iso:country":"DE",
    "sg:address":"Harzburger Weg 9c",
    "sg:city":"Hamburg",
    "sg:postcode":"22459",
    "sg:province":"Hamburg",
    "wof:name":"The Artist Network Company Gesellschaft Zur Produktion V.",
    "wof:placetype":"venue"
},
  "geometry": {"coordinates":[9.9454393387,53.6303405762],"type":"Point"}
}