{
  "type": "Feature",
  "properties": {
    "iso:country":"DE",
    "sg:address":"Herrnstr. 80",
    "sg:city":"Offenbach",
    "sg:postcode":"63065",
    "sg:province":"Hessen",
    "wof:name":"Wilhelm Und Lotte Neufeld- Stiftung",
    "wof:placetype":"venue"
},
  "geometry": {"coordinates":[8.7613306046,50.1074905396],"type":"Point"}
}