{
  "type": "Feature",
  "properties": {
    "iso:country":"DE",
    "sg:address":"Gaxel 122",
    "sg:city":"Vreden",
    "sg:phone":"+49 2564/390994",
    "sg:postcode":"48691",
    "sg:province":"Nordrhein-Westfalen",
    "wof:name":"Mvw Kamintechnik",
    "wof:placetype":"venue"
},
  "geometry": {"coordinates":[6.8149051666,52.0213508606],"type":"Point"}
}