{
  "type": "Feature",
  "properties": {
    "iso:country":"DE",
    "sg:address":"Arnhofener Str. 43",
    "sg:city":"Aindling",
    "sg:phone":"+49 8237/961630",
    "sg:postcode":"86447",
    "sg:province":"Bayern",
    "wof:name":"Hfm Technologie Gmbh",
    "wof:placetype":"venue"
},
  "geometry": {"coordinates":[10.9666614532,48.5113983154],"type":"Point"}
}