{
  "type": "Feature",
  "properties": {
    "iso:country":"DE",
    "sg:address":"Hauptstr. 12a",
    "sg:city":"Jeber-Bergfrieden",
    "sg:phone":"+49 34907/20459",
    "sg:postcode":"06862",
    "sg:province":"Sachsen-Anhalt",
    "wof:name":"Brigitte Mattke",
    "wof:placetype":"venue"
},
  "geometry": {"coordinates":[12.3493795395,51.9817123413],"type":"Point"}
}