{
  "type": "Feature",
  "properties": {
    "iso:country":"DE",
    "sg:address":"Spitalgasse 25",
    "sg:city":"Bad Windsheim",
    "sg:phone":"+49 9841/2723",
    "sg:postcode":"91438",
    "sg:province":"Bayern",
    "wof:name":"Orgelbauverein St. Kilian Bad Windsheim E. V.",
    "wof:placetype":"venue"
},
  "geometry": {"coordinates":[10.4138259888,49.5030670166],"type":"Point"}
}