{
  "type": "Feature",
  "properties": {
    "iso:country":"DE",
    "sg:address":"Rudolf-Breitscheid-Str. 57",
    "sg:city":"Delitzsch",
    "sg:phone":"+49 34202/21687",
    "sg:postcode":"04509",
    "sg:province":"Sachsen",
    "wof:name":"Matthias M\u00f6rstedt",
    "wof:placetype":"venue"
},
  "geometry": {"coordinates":[12.330121994,51.5343475342],"type":"Point"}
}