{
  "type": "Feature",
  "properties": {
    "iso:country":"DE",
    "sg:address":"Gartenstr. 1",
    "sg:city":"Sommerach",
    "sg:phone":"+49 9381/2380",
    "sg:postcode":"97334",
    "sg:province":"Bayern",
    "wof:name":"Wilhelm Heinlein Kg",
    "wof:placetype":"venue"
},
  "geometry": {"coordinates":[10.2087182999,49.8247299194],"type":"Point"}
}