{
  "type": "Feature",
  "properties": {
    "iso:country":"DE",
    "sg:address":"An der Promenade 1",
    "sg:city":"Dassow",
    "sg:phone":"+49 38826/80460",
    "sg:postcode":"23942",
    "sg:province":"Mecklenburg-Vorpommern",
    "wof:name":"Wasserversorgung Und Abwasserbehandlung",
    "wof:placetype":"venue"
},
  "geometry": {"coordinates":[10.9830522537,53.9096984863],"type":"Point"}
}