{
  "type": "Feature",
  "properties": {
    "iso:country":"DE",
    "sg:address":"Brachtenbecker Weg 39",
    "sg:city":"Altena",
    "sg:phone":"+49 2352/22688",
    "sg:postcode":"58762",
    "sg:province":"Nordrhein-Westfalen",
    "wof:name":"August Breidenbach Gmbh & Co. Kg",
    "wof:placetype":"venue"
},
  "geometry": {"coordinates":[7.6525731087,51.3017272949],"type":"Point"}
}