{
  "type": "Feature",
  "properties": {
    "iso:country":"DE",
    "sg:address":"Torsholter Hauptstr. 11",
    "sg:city":"Westerstede",
    "sg:phone":"+49 4488/76200",
    "sg:postcode":"26655",
    "sg:province":"Niedersachsen",
    "wof:name":"Trans M- Logistik Gmbh",
    "wof:placetype":"venue"
},
  "geometry": {"coordinates":[7.9537878036,53.2253990173],"type":"Point"}
}