{
  "type": "Feature",
  "properties": {
    "iso:country":"DE",
    "sg:address":"Boegeholdstr. 17",
    "sg:city":"Jena",
    "sg:phone":"+49 3641/600407",
    "sg:postcode":"07745",
    "sg:province":"Th\u00fcringen",
    "wof:name":"J. Lehmann",
    "wof:placetype":"venue"
},
  "geometry": {"coordinates":[11.57457,50.897518],"type":"Point"}
}