{
  "type": "Feature",
  "properties": {
    "iso:country":"DE",
    "sg:address":"Fehmarnwinkel 45",
    "sg:city":"Kiel",
    "sg:postcode":"24107",
    "sg:province":"Schleswig-Holstein",
    "wof:name":"Flugdienstleistung Nord Gmbh",
    "wof:placetype":"venue"
},
  "geometry": {"coordinates":[10.0753059387,54.3662338257],"type":"Point"}
}