{
  "type": "Feature",
  "properties": {
    "iso:country":"DE",
    "sg:address":"Hugenottenstr. 8",
    "sg:city":"Friedrichsdorf",
    "sg:phone":"+49 6172/778229",
    "sg:postcode":"61381",
    "sg:province":"Hessen",
    "wof:name":"Darbi Gesellschaft F\u00fcr Deutsch-arabische Wirtschaft-",
    "wof:placetype":"venue"
},
  "geometry": {"coordinates":[8.6341533661,50.253490448],"type":"Point"}
}