{
  "type": "Feature",
  "properties": {
    "iso:country":"DE",
    "sg:address":"Weinstr. 31",
    "sg:city":"Bad D\u00fcrkheim",
    "sg:phone":"+49 6322/1765",
    "sg:postcode":"67098",
    "sg:province":"Rheinland-Pfalz",
    "wof:name":"Druckerei Kaltenh\u00e4user Inh. R. Nagel",
    "wof:placetype":"venue"
},
  "geometry": {"coordinates":[8.17606,49.469437],"type":"Point"}
}