{
  "type": "Feature",
  "properties": {
    "iso:country":"DE",
    "sg:address":"Waldstr. 26",
    "sg:city":"Langenwei\u00dfbach",
    "sg:phone":"+49 375/617478",
    "sg:postcode":"08134",
    "sg:province":"Sachsen",
    "wof:name":"Josef Ga\u00dfler Architekt",
    "wof:placetype":"venue"
},
  "geometry": {"coordinates":[12.60955,50.637051],"type":"Point"}
}