{
  "type": "Feature",
  "properties": {
    "iso:country":"DE",
    "sg:address":"Rethelstr. 162",
    "sg:city":"D\u00fcsseldorf",
    "sg:phone":"+49 211/623156",
    "sg:postcode":"40237",
    "sg:province":"Nordrhein-Westfalen",
    "wof:name":"Kaisers Tengelmann Ag",
    "wof:placetype":"venue"
},
  "geometry": {"coordinates":[6.8006939888,51.2386169434],"type":"Point"}
}