{
  "type": "Feature",
  "properties": {
    "iso:country":"DE",
    "sg:address":"Wichelwisch 44",
    "sg:city":"Hamburg",
    "sg:phone":"+49 40/663317",
    "sg:postcode":"22045",
    "sg:province":"Hamburg",
    "wof:name":"Rolf Meyer Bauingenieur Architekt",
    "wof:placetype":"venue"
},
  "geometry": {"coordinates":[10.129138,53.593475],"type":"Point"}
}