{
  "type": "Feature",
  "properties": {
    "iso:country":"DE",
    "sg:address":"Gut Lindenhof",
    "sg:city":"Ahrensburg",
    "sg:postcode":"22926",
    "sg:province":"Schleswig-Holstein",
    "wof:name":"Altenheim Haus Bredenbek",
    "wof:placetype":"venue"
},
  "geometry": {"coordinates":[10.19636,53.671253],"type":"Point"}
}