{
  "type": "Feature",
  "properties": {
    "iso:country":"DE",
    "sg:address":"Weidenhausen 44",
    "sg:city":"Stadtallendorf",
    "sg:phone":"+49 6429/1448",
    "sg:postcode":"35260",
    "sg:province":"Hessen",
    "wof:name":"V. Otto",
    "wof:placetype":"venue"
},
  "geometry": {"coordinates":[8.9697113037,50.7702026367],"type":"Point"}
}