{
  "type": "Feature",
  "properties": {
    "iso:country":"DE",
    "sg:address":"Felix-Klipstein-Weg 24",
    "sg:city":"Laubach",
    "sg:phone":"+49 6405/7672",
    "sg:postcode":"35321",
    "sg:province":"Hessen",
    "wof:name":"Laubacher Sportler Klause",
    "wof:placetype":"venue"
},
  "geometry": {"coordinates":[8.9870834351,50.5485458374],"type":"Point"}
}