{
  "type": "Feature",
  "properties": {
    "iso:country":"DE",
    "sg:address":"Griesbacher Str. 2",
    "sg:city":"Rotthalm\u00fcnster",
    "sg:phone":"+49 8533/2313",
    "sg:postcode":"94094",
    "sg:province":"Bayern",
    "wof:name":"Restaurant-pizzeria La Gondula",
    "wof:placetype":"venue"
},
  "geometry": {"coordinates":[13.2025346756,48.3597488403],"type":"Point"}
}