{
  "type": "Feature",
  "properties": {
    "iso:country":"DE",
    "sg:address":"Ferdinand-Schmitz-Str. 34",
    "sg:city":"K\u00f6nigswinter",
    "sg:phone":"+49 2223/1429",
    "sg:postcode":"53639",
    "sg:province":"Nordrhein-Westfalen",
    "wof:name":"J\u00fcrgen Welbrink",
    "wof:placetype":"venue"
},
  "geometry": {"coordinates":[7.189127,50.696526],"type":"Point"}
}