{
  "type": "Feature",
  "properties": {
    "iso:country":"DE",
    "sg:address":"Lange Str. 30",
    "sg:city":"Beverungen",
    "sg:phone":"+49 5273/89051",
    "sg:postcode":"37688",
    "sg:province":"Nordrhein-Westfalen",
    "wof:name":"Pizzeria Zur Post",
    "wof:placetype":"venue"
},
  "geometry": {"coordinates":[9.3737249374,51.6645393372],"type":"Point"}
}