{
  "type": "Feature",
  "properties": {
    "iso:country":"DE",
    "sg:address":"Hauptstr. 59",
    "sg:city":"Friedrichsbrunn",
    "sg:phone":"+49 39487/342",
    "sg:postcode":"06507",
    "sg:province":"Sachsen-Anhalt",
    "wof:name":"Zur Unterklippe",
    "wof:placetype":"venue"
},
  "geometry": {"coordinates":[11.0321512222,51.6861114502],"type":"Point"}
}