{
  "type": "Feature",
  "properties": {
    "iso:country":"DE",
    "sg:address":"Untergasse 14",
    "sg:city":"Gau-Weinheim",
    "sg:phone":"+49 6732/3469",
    "sg:postcode":"55578",
    "sg:province":"Rheinland-Pfalz",
    "wof:name":"Erich Glass",
    "wof:placetype":"venue"
},
  "geometry": {"coordinates":[8.0495090485,49.8460922241],"type":"Point"}
}