{
  "type": "Feature",
  "properties": {
    "iso:country":"DE",
    "sg:address":"Am Alten Handelsplatz 5",
    "sg:city":"Ihlow",
    "sg:phone":"+49 4928/339",
    "sg:postcode":"26632",
    "sg:province":"Niedersachsen",
    "wof:name":"Wilm Rase",
    "wof:placetype":"venue"
},
  "geometry": {"coordinates":[7.343307972,53.3948669434],"type":"Point"}
}