{
  "type": "Feature",
  "properties": {
    "iso:country":"DE",
    "sg:address":"Papestr. 42",
    "sg:city":"Essen",
    "sg:postcode":"45147",
    "sg:province":"Nordrhein-Westfalen",
    "wof:name":"Aldi Gmbh & Co. Kg",
    "wof:placetype":"venue"
},
  "geometry": {"coordinates":[6.9955821037,51.4433097839],"type":"Point"}
}