{
  "type": "Feature",
  "properties": {
    "iso:country":"DE",
    "sg:address":"Kirchenstr. 25",
    "sg:city":"Anger",
    "sg:phone":"+49 8656/518",
    "sg:postcode":"83454",
    "sg:province":"Bayern",
    "wof:name":"Katholisches Pfarramt St. Jakob",
    "wof:placetype":"venue"
},
  "geometry": {"coordinates":[12.8673267365,47.781703949],"type":"Point"}
}