{
  "type": "Feature",
  "properties": {
    "iso:country":"DE",
    "sg:address":"Julius-Bamberger-Str. 4",
    "sg:city":"Bremen",
    "sg:phone":"+49 421/83900",
    "sg:postcode":"28279",
    "sg:province":"Bremen",
    "wof:name":"Alcatel Sel Ag",
    "wof:placetype":"venue"
},
  "geometry": {"coordinates":[8.835313797,53.0492134094],"type":"Point"}
}