{
  "type": "Feature",
  "properties": {
    "iso:country":"DE",
    "sg:address":"\u00d6dmiesbach 29",
    "sg:city":"Teunz",
    "sg:phone":"+49 9655/1474",
    "sg:postcode":"92552",
    "sg:province":"Bayern",
    "wof:name":"Helmut Ruhland",
    "wof:placetype":"venue"
},
  "geometry": {"coordinates":[12.368350029,49.5051460266],"type":"Point"}
}