{
  "type": "Feature",
  "properties": {
    "iso:country":"DE",
    "sg:address":"Waldeck 25",
    "sg:city":"Dinkelsb\u00fchl",
    "sg:phone":"+49 9857/590",
    "sg:postcode":"91550",
    "sg:province":"Bayern",
    "wof:name":"Freitag Holz- Und Spielwarenfabrik Gmbh",
    "wof:placetype":"venue"
},
  "geometry": {"coordinates":[10.2506361008,49.1035575867],"type":"Point"}
}