{
  "type": "Feature",
  "properties": {
    "iso:country":"DE",
    "sg:address":"Kaulbachstr. 1 a",
    "sg:city":"M\u00fcnchen",
    "sg:phone":"+49 89/2109900",
    "sg:postcode":"80539",
    "sg:province":"Bayern",
    "wof:name":"Khg Treuhand Gmbh",
    "wof:placetype":"venue"
},
  "geometry": {"coordinates":[11.5824861526,48.1459617615],"type":"Point"}
}