{
  "type": "Feature",
  "properties": {
    "iso:country":"DE",
    "sg:address":"Magnolienweg 3",
    "sg:city":"Aschaffenburg",
    "sg:phone":"+49 6021/86470",
    "sg:postcode":"63741",
    "sg:province":"Bayern",
    "wof:name":"M\u00fcller-dekor Gmbh",
    "wof:placetype":"venue"
},
  "geometry": {"coordinates":[9.1303091049,49.964717865],"type":"Point"}
}