{
  "type": "Feature",
  "properties": {
    "iso:country":"DE",
    "sg:address":"Bronnwiesenweg 12",
    "sg:city":"Rudersberg",
    "sg:phone":"+49 7183/37419",
    "sg:postcode":"73635",
    "sg:province":"Baden-W\u00fcrttemberg",
    "wof:name":"Gemeindehalle",
    "wof:placetype":"venue"
},
  "geometry": {"coordinates":[9.5279541016,48.882068634],"type":"Point"}
}