{
  "type": "Feature",
  "properties": {
    "iso:country":"DE",
    "sg:address":"Osnabr\u00fccker Str. 82",
    "sg:city":"L\u00fcbbecke",
    "sg:phone":"+49 5741/8470",
    "sg:postcode":"32312",
    "sg:province":"Nordrhein-Westfalen",
    "wof:name":"Deutsche Bp Gmbh",
    "wof:placetype":"venue"
},
  "geometry": {"coordinates":[8.59719944,52.3020706177],"type":"Point"}
}