{
  "type": "Feature",
  "properties": {
    "iso:country":"DE",
    "sg:address":"Emser Str. 392",
    "sg:city":"Koblenz",
    "sg:phone":"+49 261/70020",
    "sg:postcode":"56076",
    "sg:province":"Rheinland-Pfalz",
    "wof:name":"Kloster St. Josef",
    "wof:placetype":"venue"
},
  "geometry": {"coordinates":[7.595573,50.326469],"type":"Point"}
}