{
  "type": "Feature",
  "properties": {
    "iso:country":"DE",
    "sg:address":"Ludgeristr. 34",
    "sg:city":"M\u00fcnster",
    "sg:phone":"+49 251/511019",
    "sg:postcode":"48143",
    "sg:province":"Nordrhein-Westfalen",
    "wof:name":"Erdmann-kleidung Georg Erdmann Kg",
    "wof:placetype":"venue"
},
  "geometry": {"coordinates":[7.6274728775,51.9588050842],"type":"Point"}
}