{
  "type": "Feature",
  "properties": {
    "iso:country":"DE",
    "sg:address":"Bismarckstr. 3",
    "sg:city":"Bad Salzuflen",
    "sg:phone":"+49 5222/62910",
    "sg:postcode":"32105",
    "sg:province":"Nordrhein-Westfalen",
    "wof:name":"G\u00e4stehaus Haus Mecklenburg",
    "wof:placetype":"venue"
},
  "geometry": {"coordinates":[8.7452917099,52.0872802734],"type":"Point"}
}