{
  "type": "Feature",
  "properties": {
    "iso:country":"DE",
    "sg:address":"Auf dem Praun 14",
    "sg:city":"Zeven",
    "sg:phone":"+49 4281/2683",
    "sg:postcode":"27404",
    "sg:province":"Niedersachsen",
    "wof:name":"Malereigesch\u00e4ft G\u00fcnther Eggers Gmbh",
    "wof:placetype":"venue"
},
  "geometry": {"coordinates":[9.287045,53.286469],"type":"Point"}
}