{
  "type": "Feature",
  "properties": {
    "iso:country":"DE",
    "sg:address":"Edgar-Bennert-Str 44",
    "sg:city":"Schwerin",
    "sg:phone":"+49 385/4868882",
    "sg:postcode":"19057",
    "sg:province":"Mecklenburg-Vorpommern",
    "wof:name":"Fvg Folienverwertungsgesellschaft Mbh",
    "wof:placetype":"venue"
},
  "geometry": {"coordinates":[11.3704767227,53.651424408],"type":"Point"}
}