{
  "type": "Feature",
  "properties": {
    "iso:country":"DE",
    "sg:address":"Steingasse 11",
    "sg:city":"Aschaffenburg",
    "sg:phone":"+49 6021/15444",
    "sg:postcode":"63739",
    "sg:province":"Bayern",
    "wof:name":"Focal Ringfoto Gmbh",
    "wof:placetype":"venue"
},
  "geometry": {"coordinates":[9.1456222534,49.9754219055],"type":"Point"}
}