{
  "type": "Feature",
  "properties": {
    "iso:country":"DE",
    "sg:address":"Marktstr. 12",
    "sg:city":"Markdorf",
    "sg:phone":"+49 7544/5809",
    "sg:postcode":"88677",
    "sg:province":"Baden-W\u00fcrttemberg",
    "wof:name":"B. Procopio",
    "wof:placetype":"venue"
},
  "geometry": {"coordinates":[9.3902692795,47.7209358215],"type":"Point"}
}