{
  "type": "Feature",
  "properties": {
    "iso:country":"DE",
    "sg:address":"Aalborgring 38",
    "sg:city":"Kiel",
    "sg:phone":"+49 431/525201",
    "sg:postcode":"24109",
    "sg:province":"Schleswig-Holstein",
    "wof:name":"Christina Sattar Krankengymnastin",
    "wof:placetype":"venue"
},
  "geometry": {"coordinates":[10.046495,54.317902],"type":"Point"}
}