{
  "type": "Feature",
  "properties": {
    "iso:country":"DE",
    "sg:address":"Kronenstr. 38",
    "sg:city":"Rheinau",
    "sg:phone":"+49 7844/1418",
    "sg:postcode":"77866",
    "sg:province":"Baden-W\u00fcrttemberg",
    "wof:name":"Cafe Kaltschmitt",
    "wof:placetype":"venue"
},
  "geometry": {"coordinates":[7.940834,48.675819],"type":"Point"}
}