{
  "type": "Feature",
  "properties": {
    "iso:country":"DE",
    "sg:address":"Obererweg 52",
    "sg:city":"Cochem",
    "sg:phone":"+49 2671/3336",
    "sg:postcode":"56812",
    "sg:province":"Rheinland-Pfalz",
    "wof:name":"G\u00e4stehaus Bongers",
    "wof:placetype":"venue"
},
  "geometry": {"coordinates":[7.1719899178,50.1390914917],"type":"Point"}
}