{
  "type": "Feature",
  "properties": {
    "iso:country":"DE",
    "sg:address":"Sundische Str. 10",
    "sg:city":"Grimmen",
    "sg:phone":"+49 38326/4189",
    "sg:postcode":"18507",
    "sg:province":"Mecklenburg-Vorpommern",
    "wof:name":"M. Clasen",
    "wof:placetype":"venue"
},
  "geometry": {"coordinates":[13.042915,54.113926],"type":"Point"}
}