{
  "type": "Feature",
  "properties": {
    "iso:country":"DE",
    "sg:address":"Wettringener Str. 5",
    "sg:city":"Metelen",
    "sg:phone":"+49 2556/7888",
    "sg:postcode":"48629",
    "sg:province":"Nordrhein-Westfalen",
    "wof:name":"Texaco-tankstelle",
    "wof:placetype":"venue"
},
  "geometry": {"coordinates":[7.2202839851,52.1453590393],"type":"Point"}
}