{
  "type": "Feature",
  "properties": {
    "iso:country":"DE",
    "sg:address":"Teichstr. 9",
    "sg:city":"Schmalkalden",
    "sg:phone":"+49 3683/402451",
    "sg:postcode":"98574",
    "sg:province":"Th\u00fcringen",
    "wof:name":"Kurt Paul",
    "wof:placetype":"venue"
},
  "geometry": {"coordinates":[10.451414,50.726929],"type":"Point"}
}