{
  "type": "Feature",
  "properties": {
    "iso:country":"DE",
    "sg:address":"Am Trieb 12",
    "sg:city":"Esselbach",
    "sg:phone":"+49 9394/1250",
    "sg:postcode":"97839",
    "sg:province":"Bayern",
    "wof:name":"Josef V\u00e4th",
    "wof:placetype":"venue"
},
  "geometry": {"coordinates":[9.5211982727,49.8560562134],"type":"Point"}
}