{
  "type": "Feature",
  "properties": {
    "iso:country":"DE",
    "sg:address":"Kaulbachstr. 5",
    "sg:city":"Essen",
    "sg:phone":"+49 201/702233",
    "sg:postcode":"45147",
    "sg:province":"Nordrhein-Westfalen",
    "wof:name":"Evelyn Duerschlag",
    "wof:placetype":"venue"
},
  "geometry": {"coordinates":[6.987057,51.436962],"type":"Point"}
}