{
  "type": "Feature",
  "properties": {
    "iso:country":"DE",
    "sg:address":"Comeniusstr. 42",
    "sg:city":"Braunschweig",
    "sg:phone":"+49 531/7999820",
    "sg:postcode":"38102",
    "sg:province":"Niedersachsen",
    "wof:name":"Spa\u00df Und Erfolg Pur ! Bssv Von 1999 E.v.",
    "wof:placetype":"venue"
},
  "geometry": {"coordinates":[10.543937,52.26479],"type":"Point"}
}