{
  "type": "Feature",
  "properties": {
    "iso:country":"DE",
    "sg:address":"Freigebiet 1",
    "sg:city":"Bremerhaven",
    "sg:phone":"+49 471/65448",
    "sg:postcode":"27568",
    "sg:province":"Bremen",
    "wof:name":"U. Kurtz Autovermietung",
    "wof:placetype":"venue"
},
  "geometry": {"coordinates":[8.579515,53.549114],"type":"Point"}
}