{
  "type": "Feature",
  "properties": {
    "iso:country":"DE",
    "sg:address":"Kapersburgstr. 18",
    "sg:city":"Oberursel",
    "sg:phone":"+49 6171/4577",
    "sg:postcode":"61440",
    "sg:province":"Hessen",
    "wof:name":"M & M Software Gmbh",
    "wof:placetype":"venue"
},
  "geometry": {"coordinates":[8.5848350525,50.2057723999],"type":"Point"}
}