{
  "type": "Feature",
  "properties": {
    "iso:country":"DE",
    "sg:address":"Sch\u00f6nblickstr. 32",
    "sg:city":"Straubenhardt",
    "sg:postcode":"75334",
    "sg:province":"Baden-W\u00fcrttemberg",
    "wof:name":"Noni-saft - Der Kraftsaft Aus Der Frucht Morinda Citrifolia!",
    "wof:placetype":"venue"
},
  "geometry": {"coordinates":[8.5557670593,48.8447227478],"type":"Point"}
}