{
  "type": "Feature",
  "properties": {
    "iso:country":"DE",
    "sg:address":"Jahnstr. 27",
    "sg:city":"Bietigheim-Bissingen",
    "sg:phone":"+49 7142/30665",
    "sg:postcode":"74321",
    "sg:province":"Baden-W\u00fcrttemberg",
    "wof:name":"G\u00fcnter Weidenbach Steuerberater",
    "wof:placetype":"venue"
},
  "geometry": {"coordinates":[9.0850954056,48.9419631958],"type":"Point"}
}