{
  "type": "Feature",
  "properties": {
    "iso:country":"DE",
    "sg:address":"Warsteiner Str. 12",
    "sg:city":"Meschede",
    "sg:phone":"+49 291/1413",
    "sg:postcode":"59872",
    "sg:province":"Nordrhein-Westfalen",
    "wof:name":"Josef Menke",
    "wof:placetype":"venue"
},
  "geometry": {"coordinates":[8.2812309265,51.3499259949],"type":"Point"}
}