{
  "type": "Feature",
  "properties": {
    "iso:country":"DE",
    "sg:address":"Jahnstr. 17",
    "sg:city":"Neustadt",
    "sg:phone":"+49 6321/929392",
    "sg:postcode":"67434",
    "sg:province":"Rheinland-Pfalz",
    "wof:name":"Labrenz Gmbh",
    "wof:placetype":"venue"
},
  "geometry": {"coordinates":[8.131725,49.351185],"type":"Point"}
}