{
  "type": "Feature",
  "properties": {
    "iso:country":"DE",
    "sg:address":"Biebelrieder Str. 36",
    "sg:city":"Theilheim",
    "sg:phone":"+49 9303/2281",
    "sg:postcode":"97288",
    "sg:province":"Bayern",
    "wof:name":"Walter Lutz Inh. J\u00fcrgen Hammer",
    "wof:placetype":"venue"
},
  "geometry": {"coordinates":[10.0436134338,49.754863739],"type":"Point"}
}