{
  "type": "Feature",
  "properties": {
    "iso:country":"DE",
    "sg:address":"Rupperather Ring 38",
    "sg:city":"Bad M\u00fcnstereifel",
    "sg:phone":"+49 2257/1325",
    "sg:postcode":"53902",
    "sg:province":"Nordrhein-Westfalen",
    "wof:name":"Gerhard Ohlert",
    "wof:placetype":"venue"
},
  "geometry": {"coordinates":[6.877399,50.469364],"type":"Point"}
}