{
  "type": "Feature",
  "properties": {
    "iso:country":"DE",
    "sg:address":"Berliner Str. 10",
    "sg:city":"B\u00fcttelborn",
    "sg:phone":"+49 6152/55048",
    "sg:postcode":"64572",
    "sg:province":"Hessen",
    "wof:name":"E. Bott Und L. Hans Immobilienmakler",
    "wof:placetype":"venue"
},
  "geometry": {"coordinates":[8.5087490082,49.8989028931],"type":"Point"}
}