{
  "type": "Feature",
  "properties": {
    "iso:country":"DE",
    "sg:address":"Am Stadtgraben 48",
    "sg:city":"M\u00fcnster",
    "sg:phone":"+49 251/830",
    "sg:postcode":"48143",
    "sg:province":"Nordrhein-Westfalen",
    "wof:name":"Studentenwerk M\u00fcnster",
    "wof:placetype":"venue"
},
  "geometry": {"coordinates":[7.6196208,51.9580307007],"type":"Point"}
}