{
  "type": "Feature",
  "properties": {
    "iso:country":"DE",
    "sg:address":"Wermsdorfer Str. 10",
    "sg:city":"M\u00fcgeln",
    "sg:phone":"+49 34362/32311",
    "sg:postcode":"04769",
    "sg:province":"Sachsen",
    "wof:name":"Vollrath Thierbach",
    "wof:placetype":"venue"
},
  "geometry": {"coordinates":[13.041806221,51.236946106],"type":"Point"}
}