{
  "type": "Feature",
  "properties": {
    "iso:country":"DE",
    "sg:address":"Zeppelinstr. 4",
    "sg:city":"D\u00fcrnau",
    "sg:postcode":"73105",
    "sg:province":"Baden-W\u00fcrttemberg",
    "wof:name":"Cobits Gmbh Competence Center F\u00fcr Business",
    "wof:placetype":"venue"
},
  "geometry": {"coordinates":[9.64084,48.645351],"type":"Point"}
}