{
  "type": "Feature",
  "properties": {
    "iso:country":"DE",
    "sg:address":"M\u00fchlenstr. 51",
    "sg:city":"Euskirchen",
    "sg:phone":"+49 2251/53544",
    "sg:postcode":"53879",
    "sg:province":"Nordrhein-Westfalen",
    "wof:name":"H. Schichterich",
    "wof:placetype":"venue"
},
  "geometry": {"coordinates":[6.7926959991,50.6629066467],"type":"Point"}
}