{
  "type": "Feature",
  "properties": {
    "iso:country":"DE",
    "sg:address":"Radeberger Str. 45",
    "sg:city":"Dresden",
    "sg:phone":"+49 351/829300",
    "sg:postcode":"01099",
    "sg:province":"Sachsen",
    "wof:name":"Buhmann Und Ahlers Rechtsanw\u00e4lte",
    "wof:placetype":"venue"
},
  "geometry": {"coordinates":[13.7713880539,51.0684585571],"type":"Point"}
}