{
  "type": "Feature",
  "properties": {
    "iso:country":"DE",
    "sg:address":"Herforder Str. 26",
    "sg:city":"Bad Oeynhausen",
    "sg:phone":"+49 5731/27858",
    "sg:postcode":"32545",
    "sg:province":"Nordrhein-Westfalen",
    "wof:name":"Grillrestaurant Zur Feurigen Bratwurst",
    "wof:placetype":"venue"
},
  "geometry": {"coordinates":[8.788110733,52.2016716003],"type":"Point"}
}