{
  "type": "Feature",
  "properties": {
    "iso:country":"DE",
    "sg:address":"S\u00fcdmauer 15",
    "sg:city":"B\u00fcren",
    "sg:phone":"+49 2951/3976",
    "sg:postcode":"33142",
    "sg:province":"Nordrhein-Westfalen",
    "wof:name":"M\u00fchlenhof",
    "wof:placetype":"venue"
},
  "geometry": {"coordinates":[8.5599298477,51.5511474609],"type":"Point"}
}