{
  "type": "Feature",
  "properties": {
    "iso:country":"DE",
    "sg:address":"Hohmannstr. 28",
    "sg:city":"Schweinfurt",
    "sg:phone":"+49 9721/82463",
    "sg:postcode":"97421",
    "sg:province":"Bayern",
    "wof:name":"E. Neder",
    "wof:placetype":"venue"
},
  "geometry": {"coordinates":[10.2048158646,50.0485572815],"type":"Point"}
}