{
  "type": "Feature",
  "properties": {
    "iso:country":"DE",
    "sg:address":"Fiesteler Str. 48",
    "sg:city":"L\u00fcbbecke",
    "sg:phone":"+49 5743/1362",
    "sg:postcode":"32312",
    "sg:province":"Nordrhein-Westfalen",
    "wof:name":"Fritz Haseloh",
    "wof:placetype":"venue"
},
  "geometry": {"coordinates":[8.55822,52.336349],"type":"Point"}
}