{
  "type": "Feature",
  "properties": {
    "iso:country":"DE",
    "sg:address":"Adlerstr. 17 a",
    "sg:city":"Straubing",
    "sg:postcode":"94315",
    "sg:province":"Bayern",
    "wof:name":"Ciaramella & Co. Bau Gmbh",
    "wof:placetype":"venue"
},
  "geometry": {"coordinates":[12.597991,48.881104],"type":"Point"}
}