{
  "type": "Feature",
  "properties": {
    "iso:country":"DE",
    "sg:address":"Kornmarkt 19",
    "sg:city":"Altenburg",
    "sg:phone":"+49 3447/502668",
    "sg:postcode":"04600",
    "sg:province":"Th\u00fcringen",
    "wof:name":"J. Bensch Ingenieur",
    "wof:placetype":"venue"
},
  "geometry": {"coordinates":[12.43318367,50.98462677],"type":"Point"}
}