{
  "type": "Feature",
  "properties": {
    "iso:country":"DE",
    "sg:address":"Lutherstr.",
    "sg:city":"Wei\u00dfwasser",
    "sg:phone":"+49 3576/41193",
    "sg:postcode":"02943",
    "sg:province":"Sachsen",
    "wof:name":"R. Mahnke",
    "wof:placetype":"venue"
},
  "geometry": {"coordinates":[14.6431646347,51.5002365112],"type":"Point"}
}