{
  "type": "Feature",
  "properties": {
    "iso:country":"DE",
    "sg:address":"Ringstr 63A",
    "sg:city":"Remscheid",
    "sg:phone":"+49 2191/780771",
    "sg:postcode":"42897",
    "sg:province":"Nordrhein-Westfalen",
    "wof:name":"Hmr Elektrotechnik Gmbh",
    "wof:placetype":"venue"
},
  "geometry": {"coordinates":[7.26167,51.185959],"type":"Point"}
}