{
  "type": "Feature",
  "properties": {
    "iso:country":"DE",
    "sg:address":"Br\u00e4hlesgasse 15",
    "sg:city":"Stuttgart",
    "sg:phone":"+49 711/5594531",
    "sg:postcode":"70372",
    "sg:province":"Baden-W\u00fcrttemberg",
    "wof:name":"Karl Hahn",
    "wof:placetype":"venue"
},
  "geometry": {"coordinates":[9.212947,48.804955],"type":"Point"}
}