{
  "type": "Feature",
  "properties": {
    "iso:country":"DE",
    "sg:address":"Menglinghauser Str. 274",
    "sg:city":"Dortmund",
    "sg:phone":"+49 231/770053",
    "sg:postcode":"44227",
    "sg:province":"Nordrhein-Westfalen",
    "wof:name":"Michael Hentrich Gmbh",
    "wof:placetype":"venue"
},
  "geometry": {"coordinates":[7.410329,51.462204],"type":"Point"}
}