{
  "type": "Feature",
  "properties": {
    "iso:country":"DE",
    "sg:address":"Bahnhofstr. 19",
    "sg:city":"Lau\u00dfig",
    "sg:phone":"+49 34243/23237",
    "sg:postcode":"04838",
    "sg:province":"Sachsen",
    "wof:name":"Andreas Sombrowski",
    "wof:placetype":"venue"
},
  "geometry": {"coordinates":[12.635794,51.542946],"type":"Point"}
}