{
  "type": "Feature",
  "properties": {
    "iso:country":"DE",
    "sg:address":"Osterdeich 47",
    "sg:city":"Bremen",
    "sg:phone":"+49 421/78225",
    "sg:postcode":"28203",
    "sg:province":"Bremen",
    "wof:name":"Streng",
    "wof:placetype":"venue"
},
  "geometry": {"coordinates":[8.8233537674,53.0690574646],"type":"Point"}
}