{
  "type": "Feature",
  "properties": {
    "iso:country":"DE",
    "sg:address":"Theodor-Neubauer-Str. 2",
    "sg:city":"Gro\u00dfenhain",
    "sg:phone":"+49 3522/505330",
    "sg:postcode":"01558",
    "sg:province":"Sachsen",
    "wof:name":"Anett Englowski",
    "wof:placetype":"venue"
},
  "geometry": {"coordinates":[13.5405025482,51.2837944031],"type":"Point"}
}