{
  "type": "Feature",
  "properties": {
    "iso:country":"DE",
    "sg:address":"B\u00f6cklerstr. 4",
    "sg:city":"Hameln",
    "sg:phone":"+49 5151/60810",
    "sg:postcode":"31789",
    "sg:province":"Niedersachsen",
    "wof:name":"Valentin Klein Elektro Fachgro\u00dfhandlung Gmbh",
    "wof:placetype":"venue"
},
  "geometry": {"coordinates":[9.3436040878,52.0837097168],"type":"Point"}
}