{
  "type": "Feature",
  "properties": {
    "iso:country":"DE",
    "sg:address":"Kornmarkt 29",
    "sg:city":"Herborn",
    "sg:phone":"+49 2772/3536",
    "sg:postcode":"35745",
    "sg:province":"Hessen",
    "wof:name":"Bernd Nickel",
    "wof:placetype":"venue"
},
  "geometry": {"coordinates":[8.303649,50.682285],"type":"Point"}
}