{
  "type": "Feature",
  "properties": {
    "iso:country":"DE",
    "sg:address":"Igelweg 6",
    "sg:city":"Schnaittach-Osternohe",
    "sg:phone":"+49 9153",
    "sg:postcode":"91220",
    "sg:province":"Bayern",
    "wof:name":"Berggasthof Igelwirt",
    "wof:placetype":"venue"
},
  "geometry": {"coordinates":[11.3771429062,49.5869560242],"type":"Point"}
}