{
  "type": "Feature",
  "properties": {
    "iso:country":"DE",
    "sg:address":"Blumenweg 08",
    "sg:city":"Eisenh\u00fcttenstadt",
    "sg:phone":"+49 3364/44365",
    "sg:postcode":"15890",
    "sg:province":"Brandenburg",
    "wof:name":"Korff-autoservice",
    "wof:placetype":"venue"
},
  "geometry": {"coordinates":[14.615664,52.153137],"type":"Point"}
}