{
  "type": "Feature",
  "properties": {
    "iso:country":"DE",
    "sg:address":"Scherkhofenstr. 1",
    "sg:city":"Ihringen",
    "sg:phone":"+49 7668/5803",
    "sg:postcode":"79241",
    "sg:province":"Baden-W\u00fcrttemberg",
    "wof:name":"Ewald Konstanzer",
    "wof:placetype":"venue"
},
  "geometry": {"coordinates":[7.6506700516,48.046459198],"type":"Point"}
}