{
  "type": "Feature",
  "properties": {
    "iso:country":"DE",
    "sg:address":"Werftstr. 37",
    "sg:city":"D\u00fcsseldorf",
    "sg:phone":"+49 211/9900",
    "sg:postcode":"40549",
    "sg:province":"Nordrhein-Westfalen",
    "wof:name":"Rank Xerox Leasing Gmbh",
    "wof:placetype":"venue"
},
  "geometry": {"coordinates":[6.7153930664,51.2291145325],"type":"Point"}
}