{
  "type": "Feature",
  "properties": {
    "iso:country":"DE",
    "sg:address":"Schauinslandstr. 1",
    "sg:city":"Maulburg",
    "sg:phone":"+49 7622/6810",
    "sg:postcode":"79689",
    "sg:province":"Baden-W\u00fcrttemberg",
    "wof:name":"Busch-holding Gmbh",
    "wof:placetype":"venue"
},
  "geometry": {"coordinates":[7.788814,47.647087],"type":"Point"}
}