{
  "type": "Feature",
  "properties": {
    "iso:country":"DE",
    "sg:address":"Schulstr. 12",
    "sg:city":"Halstenbek",
    "sg:phone":"+49 4101/41049",
    "sg:postcode":"25469",
    "sg:province":"Schleswig-Holstein",
    "wof:name":"H. Mohr",
    "wof:placetype":"venue"
},
  "geometry": {"coordinates":[9.842007637,53.6356315613],"type":"Point"}
}