{
  "type": "Feature",
  "properties": {
    "iso:country":"DE",
    "sg:address":"Kleinfeldstrasse 3",
    "sg:city":"Sinsheim",
    "sg:phone":"+49 7261",
    "sg:postcode":"74889",
    "sg:province":"Baden-W\u00fcrttemberg",
    "wof:name":"Hom\u00f6otherapie F\u00fcr Tiere",
    "wof:placetype":"venue"
},
  "geometry": {"coordinates":[8.904971,49.254166],"type":"Point"}
}