{
  "type": "Feature",
  "properties": {
    "iso:country":"DE",
    "sg:address":"Aischer Str. 21",
    "sg:city":"Adelsdorf",
    "sg:phone":"+49 9195/2461",
    "sg:postcode":"91325",
    "sg:province":"Bayern",
    "wof:name":"H\u00f6rrlein",
    "wof:placetype":"venue"
},
  "geometry": {"coordinates":[10.891152,49.71629],"type":"Point"}
}