{
  "type": "Feature",
  "properties": {
    "iso:country":"DE",
    "sg:address":"F.-L.-Jahn-Str. 32",
    "sg:city":"Sarstedt",
    "sg:postcode":"31157",
    "sg:province":"Niedersachsen",
    "wof:name":"Inga And Thommy Online",
    "wof:placetype":"venue"
},
  "geometry": {"coordinates":[9.853415,52.234474],"type":"Point"}
}