{
  "type": "Feature",
  "properties": {
    "iso:country":"DE",
    "sg:address":"Gutenbergstr. 3",
    "sg:city":"Marburg",
    "sg:postcode":"35037",
    "sg:province":"Hessen",
    "wof:name":"Gerina German Internet Ag",
    "wof:placetype":"venue"
},
  "geometry": {"coordinates":[8.76854,50.806786],"type":"Point"}
}