{
  "type": "Feature",
  "properties": {
    "iso:country":"DE",
    "sg:address":"Kleinh\u00fclsen 41",
    "sg:city":"Hilden",
    "sg:phone":"+49 2103/58760",
    "sg:postcode":"40721",
    "sg:province":"Nordrhein-Westfalen",
    "wof:name":"Die Reha Gruppe Gmbh & Co. Kg",
    "wof:placetype":"venue"
},
  "geometry": {"coordinates":[6.9017019272,51.1686515808],"type":"Point"}
}