{
  "type": "Feature",
  "properties": {
    "iso:country":"DE",
    "sg:address":"Heidelbachweg 1",
    "sg:city":"Hinterhermsdorf",
    "sg:phone":"+49 35974/50320",
    "sg:postcode":"01855",
    "sg:province":"Sachsen",
    "wof:name":"Waldpension Obere M\u00fchle",
    "wof:placetype":"venue"
},
  "geometry": {"coordinates":[14.2828598022,50.9553565979],"type":"Point"}
}