{
  "type": "Feature",
  "properties": {
    "iso:country":"DE",
    "sg:address":"Walther-Rathenau-Str. 39",
    "sg:city":"Bitterfeld",
    "sg:phone":"+49 3493/23600",
    "sg:postcode":"06749",
    "sg:province":"Sachsen-Anhalt",
    "wof:name":"Rainer Rasym",
    "wof:placetype":"venue"
},
  "geometry": {"coordinates":[12.3187084198,51.6214141846],"type":"Point"}
}