{
  "type": "Feature",
  "properties": {
    "iso:country":"DE",
    "sg:address":"Almsstr. 30",
    "sg:city":"Hildesheim",
    "sg:phone":"+49 4951/2116910",
    "sg:postcode":"31134",
    "sg:province":"Niedersachsen",
    "wof:name":"Commerzbank Ag",
    "wof:placetype":"venue"
},
  "geometry": {"coordinates":[9.952528,52.155884],"type":"Point"}
}