{
  "type": "Feature",
  "properties": {
    "iso:country":"DE",
    "sg:address":"Weidenauer Str. 165",
    "sg:city":"Siegen",
    "sg:phone":"+49 271/71070",
    "sg:postcode":"57076",
    "sg:province":"Nordrhein-Westfalen",
    "wof:name":"Piano-kaiser Gmbh & Co.",
    "wof:placetype":"venue"
},
  "geometry": {"coordinates":[8.0275745392,50.8980484009],"type":"Point"}
}