{
  "type": "Feature",
  "properties": {
    "iso:country":"DE",
    "sg:address":"Durmersheimer Str. 6",
    "sg:city":"Karlsruhe",
    "sg:phone":"+49 721/590707",
    "sg:postcode":"76185",
    "sg:province":"Baden-W\u00fcrttemberg",
    "wof:name":"Engel",
    "wof:placetype":"venue"
},
  "geometry": {"coordinates":[8.3561210632,49.0082321167],"type":"Point"}
}