{
  "type": "Feature",
  "properties": {
    "iso:country":"DE",
    "sg:address":"Boddenstr. 63",
    "sg:city":"Lietzow",
    "sg:phone":"+49 38302/2066",
    "sg:postcode":"18528",
    "sg:province":"Mecklenburg-Vorpommern",
    "wof:name":"Strandcafe Essente",
    "wof:placetype":"venue"
},
  "geometry": {"coordinates":[13.506529,54.485493],"type":"Point"}
}