{
  "type": "Feature",
  "properties": {
    "iso:country":"DE",
    "sg:address":"Vorjurastr. 180",
    "sg:city":"N\u00fcrnberg",
    "sg:phone":"+49 911/637878",
    "sg:postcode":"90453",
    "sg:province":"Bayern",
    "wof:name":"Agip Deutschland Ag",
    "wof:placetype":"venue"
},
  "geometry": {"coordinates":[11.0451383591,49.3688163757],"type":"Point"}
}