{
  "type": "Feature",
  "properties": {
    "iso:country":"DE",
    "sg:address":"Gerhart-Hauptmann-Str. 47",
    "sg:city":"M\u00fchlheim",
    "sg:postcode":"63165",
    "sg:province":"Hessen",
    "wof:name":"Dv-consult Beteiligungsgesellschaft Mbh",
    "wof:placetype":"venue"
},
  "geometry": {"coordinates":[8.848135,50.122536],"type":"Point"}
}