{
  "type": "Feature",
  "properties": {
    "iso:country":"DE",
    "sg:address":"Neue Hochstr. 48",
    "sg:city":"Berlin",
    "sg:phone":"+49 30/46600139",
    "sg:postcode":"13347",
    "sg:province":"Berlin",
    "wof:name":"Hindi Malerei Gmbh",
    "wof:placetype":"venue"
},
  "geometry": {"coordinates":[13.375418,52.539284],"type":"Point"}
}