{
  "type": "Feature",
  "properties": {
    "iso:country":"DE",
    "sg:address":"Woltmershauser Str. 252",
    "sg:city":"Bremen",
    "sg:postcode":"28197",
    "sg:province":"Bremen",
    "wof:name":"Kranverleiher.de",
    "wof:placetype":"venue"
},
  "geometry": {"coordinates":[8.7742671967,53.0803985596],"type":"Point"}
}