{
  "type": "Feature",
  "properties": {
    "iso:country":"DE",
    "sg:address":"In den Eschen 45",
    "sg:city":"Wuelfrath",
    "sg:phone":"+49 2058",
    "sg:postcode":"42489",
    "sg:province":"Nordrhein-Westfalen",
    "wof:name":"Foto-reporter",
    "wof:placetype":"venue"
},
  "geometry": {"coordinates":[7.031924,51.271969],"type":"Point"}
}