{
  "type": "Feature",
  "properties": {
    "iso:country":"DE",
    "sg:address":"S\u00fcdendstr. 52",
    "sg:city":"Karlsruhe",
    "sg:phone":"+49 721/811089",
    "sg:postcode":"76135",
    "sg:province":"Baden-W\u00fcrttemberg",
    "wof:name":"Emil Becker",
    "wof:placetype":"venue"
},
  "geometry": {"coordinates":[8.382136,48.999012],"type":"Point"}
}