{
  "type": "Feature",
  "properties": {
    "iso:country":"DE",
    "sg:address":"Auf der Heide 4",
    "sg:city":"Trippstadt",
    "sg:phone":"+49 6306/1333",
    "sg:postcode":"67705",
    "sg:province":"Rheinland-Pfalz",
    "wof:name":"Kur-apotheke Inh. Annette Klinck E. K.",
    "wof:placetype":"venue"
},
  "geometry": {"coordinates":[7.772137,49.359798],"type":"Point"}
}