{
  "type": "Feature",
  "properties": {
    "iso:country":"DE",
    "sg:address":"Hauptstr. 19",
    "sg:city":"Stuttgart",
    "sg:postcode":"70563",
    "sg:province":"Baden-W\u00fcrttemberg",
    "wof:name":"Mpc Networks Gmbh",
    "wof:placetype":"venue"
},
  "geometry": {"coordinates":[9.110462,48.72974],"type":"Point"}
}