{
  "type": "Feature",
  "properties": {
    "iso:country":"DE",
    "sg:address":"Taubenweg 4",
    "sg:city":"Nesse",
    "sg:phone":"+49 4933/511",
    "sg:postcode":"26553",
    "sg:province":"Niedersachsen",
    "wof:name":"K. - H. Gronewold",
    "wof:placetype":"venue"
},
  "geometry": {"coordinates":[7.429926,53.645676],"type":"Point"}
}