{
  "type": "Feature",
  "properties": {
    "iso:country":"DE",
    "sg:address":"Dreschersreuth 20",
    "sg:city":"Helmbrechts",
    "sg:phone":"+49 9252/225",
    "sg:postcode":"95233",
    "sg:province":"Bayern",
    "wof:name":"Gastst\u00e4tte M. S\u00f6llner",
    "wof:placetype":"venue"
},
  "geometry": {"coordinates":[11.6710157394,50.2046966553],"type":"Point"}
}