{
  "type": "Feature",
  "properties": {
    "iso:country":"DE",
    "sg:address":"Parkallee 80",
    "sg:city":"Hamburg",
    "sg:postcode":"20144",
    "sg:province":"Hamburg",
    "wof:name":"Pa Textilvertriebs- Gmbh",
    "wof:placetype":"venue"
},
  "geometry": {"coordinates":[9.9841766357,53.5799751282],"type":"Point"}
}