{
  "type": "Feature",
  "properties": {
    "iso:country":"DE",
    "sg:address":"Breslauer Str. 65",
    "sg:city":"Leipzig",
    "sg:phone":"+49 341/8620584",
    "sg:postcode":"04299",
    "sg:province":"Sachsen",
    "wof:name":"Ralph Kluttig Rechtsanwalt",
    "wof:placetype":"venue"
},
  "geometry": {"coordinates":[12.4147796631,51.3151626587],"type":"Point"}
}