{
  "type": "Feature",
  "properties": {
    "iso:country":"DE",
    "sg:address":"Reuchlinstr. 9",
    "sg:city":"Ditzingen",
    "sg:phone":"+49 7156/39053",
    "sg:postcode":"71254",
    "sg:province":"Baden-W\u00fcrttemberg",
    "wof:name":"B. Sigle",
    "wof:placetype":"venue"
},
  "geometry": {"coordinates":[9.0728750229,48.8315734863],"type":"Point"}
}