{
  "type": "Feature",
  "properties": {
    "iso:country":"DE",
    "sg:address":"Eisenberger Str. 55",
    "sg:city":"Gera",
    "sg:phone":"+49 365/4229656",
    "sg:postcode":"07552",
    "sg:province":"Th\u00fcringen",
    "wof:name":"I. Hofmann",
    "wof:placetype":"venue"
},
  "geometry": {"coordinates":[12.044639,50.923252],"type":"Point"}
}