{
  "type": "Feature",
  "properties": {
    "iso:country":"DE",
    "sg:address":"Lange Str. 17",
    "sg:city":"Waiblingen",
    "sg:phone":"+49 7151/54631",
    "sg:postcode":"71332",
    "sg:province":"Baden-W\u00fcrttemberg",
    "wof:name":"U. Kuppinger",
    "wof:placetype":"venue"
},
  "geometry": {"coordinates":[9.3169870377,48.8332443237],"type":"Point"}
}