{
  "type": "Feature",
  "properties": {
    "iso:country":"DE",
    "sg:address":"Vachenlueger Str. 15",
    "sg:city":"Anger",
    "sg:phone":"+49 8656/478",
    "sg:postcode":"83454",
    "sg:province":"Bayern",
    "wof:name":"Andreas Stumpfegger",
    "wof:placetype":"venue"
},
  "geometry": {"coordinates":[12.863677,47.816502],"type":"Point"}
}