{
  "type": "Feature",
  "properties": {
    "iso:country":"DE",
    "sg:address":"R\u00fcskenkamp 44",
    "sg:city":"Ahaus",
    "sg:phone":"+49 2561/98470",
    "sg:postcode":"48683",
    "sg:province":"Nordrhein-Westfalen",
    "wof:name":"Josef Terweh Ingenieur",
    "wof:placetype":"venue"
},
  "geometry": {"coordinates":[6.9137282372,52.0672225952],"type":"Point"}
}