{
  "type": "Feature",
  "properties": {
    "iso:country":"DE",
    "sg:address":"Almsstr. 27",
    "sg:city":"Hildesheim",
    "sg:phone":"+49 4951/211040",
    "sg:postcode":"31134",
    "sg:province":"Niedersachsen",
    "wof:name":"Kreissparkasse Hildesheim",
    "wof:placetype":"venue"
},
  "geometry": {"coordinates":[9.951953,52.155739],"type":"Point"}
}