{
  "type": "Feature",
  "properties": {
    "iso:country":"DE",
    "sg:address":"K\u00f6lner Str. 6",
    "sg:city":"Bremen",
    "sg:postcode":"28327",
    "sg:province":"Bremen",
    "wof:name":"Fsb",
    "wof:placetype":"venue"
},
  "geometry": {"coordinates":[8.92563,53.07082],"type":"Point"}
}