{
  "type": "Feature",
  "properties": {
    "iso:country":"DE",
    "sg:address":"Freudenbergstr. 41",
    "sg:city":"Bochum",
    "sg:phone":"+49 234/512283",
    "sg:postcode":"44809",
    "sg:province":"Nordrhein-Westfalen",
    "wof:name":"Manfred Hu\u00dfmann Gro\u00dfschlachterei",
    "wof:placetype":"venue"
},
  "geometry": {"coordinates":[7.1967978477,51.4968719482],"type":"Point"}
}