{
  "type": "Feature",
  "properties": {
    "iso:country":"DE",
    "sg:address":"Neubeckumer Str. 47",
    "sg:city":"Beckum",
    "sg:postcode":"59269",
    "sg:province":"Nordrhein-Westfalen",
    "wof:name":"Offroad Center Mertens Gmbh & Co. Kg",
    "wof:placetype":"venue"
},
  "geometry": {"coordinates":[8.0428323746,51.7640457153],"type":"Point"}
}