{
  "type": "Feature",
  "properties": {
    "iso:country":"DE",
    "sg:address":"Steinacker 22",
    "sg:city":"Hamburg",
    "sg:phone":"+49 40/578161",
    "sg:postcode":"22523",
    "sg:province":"Hamburg",
    "wof:name":"Patrick Baucke Rechtsanwalt",
    "wof:placetype":"venue"
},
  "geometry": {"coordinates":[9.8925466537,53.6177330017],"type":"Point"}
}