{
  "type": "Feature",
  "properties": {
    "iso:country":"DE",
    "sg:address":"Glaitstr. 29 POSTFACH 80",
    "sg:city":"Maulbronn",
    "sg:phone":"+49 7043/900044",
    "sg:postcode":"75430",
    "sg:province":"Baden-W\u00fcrttemberg",
    "wof:name":"Protech Gmbh",
    "wof:placetype":"venue"
},
  "geometry": {"coordinates":[8.8273258209,48.9853897095],"type":"Point"}
}