{
  "type": "Feature",
  "properties": {
    "iso:country":"DE",
    "sg:address":"Louisenstra\u00dfe 15",
    "sg:city":"Dresden",
    "sg:phone":"+49 351",
    "sg:postcode":"01099",
    "sg:province":"Sachsen",
    "wof:name":"Mont Klamott - Secondhand Gro\u00dfhhandel - Dresden",
    "wof:placetype":"venue"
},
  "geometry": {"coordinates":[13.7495765686,51.0676078796],"type":"Point"}
}