{
  "type": "Feature",
  "properties": {
    "iso:country":"DE",
    "sg:address":"Gubener Str. 40",
    "sg:city":"Berlin",
    "sg:postcode":"10243",
    "sg:province":"Berlin",
    "wof:name":"Omnimedia Integrated Media Services Gmbh",
    "wof:placetype":"venue"
},
  "geometry": {"coordinates":[13.449697,52.510715],"type":"Point"}
}