{
  "type": "Feature",
  "properties": {
    "iso:country":"DE",
    "sg:address":"Sollbach",
    "sg:city":"Bruck",
    "sg:phone":"+49 9434/1501",
    "sg:postcode":"92436",
    "sg:province":"Bayern",
    "wof:name":"Wolfgang Spandl",
    "wof:placetype":"venue"
},
  "geometry": {"coordinates":[12.3237895966,49.2365112305],"type":"Point"}
}