{
  "type": "Feature",
  "properties": {
    "iso:country":"DE",
    "sg:address":"Marspfortengasse 6",
    "sg:city":"K\u00f6ln",
    "sg:postcode":"50667",
    "sg:province":"Nordrhein-Westfalen",
    "wof:name":"Patcom Mediengestaltung Inh. Petra Brings E. K.",
    "wof:placetype":"venue"
},
  "geometry": {"coordinates":[6.957013,50.937927],"type":"Point"}
}