{
  "type": "Feature",
  "properties": {
    "iso:country":"DE",
    "sg:address":"Freie Reichsstr. 81",
    "sg:city":"Dreis",
    "sg:phone":"+49 6578/385",
    "sg:postcode":"54518",
    "sg:province":"Rheinland-Pfalz",
    "wof:name":"Paul Kranz Haus- Und K\u00fcchenger\u00e4te",
    "wof:placetype":"venue"
},
  "geometry": {"coordinates":[6.8153100014,49.9407157898],"type":"Point"}
}