{
  "type": "Feature",
  "properties": {
    "iso:country":"DE",
    "sg:address":"Ostrampe 8",
    "sg:city":"Bremerhaven",
    "sg:phone":"+49 471/31031",
    "sg:postcode":"27572",
    "sg:province":"Bremen",
    "wof:name":"B\u00e4ckerei Br\u00fcser Gmbh",
    "wof:placetype":"venue"
},
  "geometry": {"coordinates":[8.5855836868,53.5238571167],"type":"Point"}
}