{
  "type": "Feature",
  "properties": {
    "iso:country":"DE",
    "sg:address":"Augustastr. 5",
    "sg:city":"Aachen",
    "sg:phone":"+49 241/507410",
    "sg:postcode":"52070",
    "sg:province":"Nordrhein-Westfalen",
    "wof:name":"M. Hassler-jabs Dipl. Designer",
    "wof:placetype":"venue"
},
  "geometry": {"coordinates":[6.096205,50.772858],"type":"Point"}
}