{
  "type": "Feature",
  "properties": {
    "iso:country":"DE",
    "sg:address":"Peeneblick 4",
    "sg:city":"G\u00fctzkow",
    "sg:phone":"+49 38353/50883",
    "sg:postcode":"17506",
    "sg:province":"Mecklenburg-Vorpommern",
    "wof:name":"Hatb Hafermanns Trockenbau E. Kfm.",
    "wof:placetype":"venue"
},
  "geometry": {"coordinates":[13.417769,53.929665],"type":"Point"}
}