{
  "type": "Feature",
  "properties": {
    "iso:country":"DE",
    "sg:address":"Ramsdorfer Str. 19",
    "sg:city":"Velen",
    "sg:phone":"+49 2863/926219",
    "sg:postcode":"46342",
    "sg:province":"Nordrhein-Westfalen",
    "wof:name":"Velen Ramsdorf E. V. Verkehrsverein",
    "wof:placetype":"venue"
},
  "geometry": {"coordinates":[6.9839849472,51.8943023682],"type":"Point"}
}