{
  "type": "Feature",
  "properties": {
    "iso:country":"DE",
    "sg:address":"Heinrich-Heine-Ring 120 c",
    "sg:city":"Stralsund",
    "sg:phone":"+49 3831/390322",
    "sg:postcode":"18435",
    "sg:province":"Mecklenburg-Vorpommern",
    "wof:name":"Sund-apotheke Phr Gitta Bockwitz E. Kfr.",
    "wof:placetype":"venue"
},
  "geometry": {"coordinates":[13.058785,54.326267],"type":"Point"}
}