{
  "type": "Feature",
  "properties": {
    "iso:country":"DE",
    "sg:address":"Brenscheder Str. 41",
    "sg:city":"Bochum",
    "sg:postcode":"44799",
    "sg:province":"Nordrhein-Westfalen",
    "wof:name":"Brenscheder Bauern E. V. Wolfgang Striepeke",
    "wof:placetype":"venue"
},
  "geometry": {"coordinates":[7.2325768471,51.4530181885],"type":"Point"}
}