{
  "type": "Feature",
  "properties": {
    "iso:country":"DE",
    "sg:address":"Bruchstr. 300",
    "sg:city":"Duisburg",
    "sg:phone":"+49 2066/30722",
    "sg:postcode":"47198",
    "sg:province":"Nordrhein-Westfalen",
    "wof:name":"K. Van Meegen",
    "wof:placetype":"venue"
},
  "geometry": {"coordinates":[6.682706,51.442169],"type":"Point"}
}