{
  "type": "Feature",
  "properties": {
    "iso:country":"DE",
    "sg:address":"Klingenderstr. 8",
    "sg:city":"Paderborn",
    "sg:phone":"+49 5251/528500",
    "sg:postcode":"33100",
    "sg:province":"Nordrhein-Westfalen",
    "wof:name":"P.-c. Kirchherr",
    "wof:placetype":"venue"
},
  "geometry": {"coordinates":[8.7782011032,51.7292366028],"type":"Point"}
}