{
  "type": "Feature",
  "properties": {
    "iso:country":"DE",
    "sg:address":"Jakobstr. 9-12",
    "sg:city":"G\u00f6rlitz",
    "sg:phone":"+49 3581/48440",
    "sg:postcode":"02826",
    "sg:province":"Sachsen",
    "wof:name":"Auto-centrale G\u00f6rlitz Paul Tesch Kg",
    "wof:placetype":"venue"
},
  "geometry": {"coordinates":[14.984046936,51.1488456726],"type":"Point"}
}