{
  "type": "Feature",
  "properties": {
    "iso:country":"DE",
    "sg:address":"Schmogrower Str. 16",
    "sg:city":"Burg",
    "sg:phone":"+49 35603/60789",
    "sg:postcode":"03096",
    "sg:province":"Brandenburg",
    "wof:name":"Pension Waltraud D\u00fcck",
    "wof:placetype":"venue"
},
  "geometry": {"coordinates":[14.1866645813,51.8391914368],"type":"Point"}
}