{
  "type": "Feature",
  "properties": {
    "iso:country":"DE",
    "sg:address":"Sonnenhalde 19",
    "sg:city":"Moos",
    "sg:phone":"+49 7732/54420",
    "sg:postcode":"78345",
    "sg:province":"Baden-W\u00fcrttemberg",
    "wof:name":"Gfk Wohnbau H\u00f6ri Gmbh",
    "wof:placetype":"venue"
},
  "geometry": {"coordinates":[8.955087,47.709942],"type":"Point"}
}