{
  "type": "Feature",
  "properties": {
    "iso:country":"DE",
    "sg:address":"Badberger Str. 18",
    "sg:city":"Quakenbr\u00fcck",
    "sg:phone":"+49 5431/3554",
    "sg:postcode":"49610",
    "sg:province":"Niedersachsen",
    "wof:name":"Zimmerei Bernhard B\u00e4ker Gmbh",
    "wof:placetype":"venue"
},
  "geometry": {"coordinates":[7.9616680145,52.6709403992],"type":"Point"}
}