{
  "type": "Feature",
  "properties": {
    "iso:country":"DE",
    "sg:address":"Alte Bahnhofstr. 9",
    "sg:city":"Bonn",
    "sg:phone":"+49 228/9563838",
    "sg:postcode":"53173",
    "sg:province":"Nordrhein-Westfalen",
    "wof:name":"Jackson Und Siemann Rechtsanw\u00e4lte",
    "wof:placetype":"venue"
},
  "geometry": {"coordinates":[7.1559681892,50.684715271],"type":"Point"}
}