{
  "type": "Feature",
  "properties": {
    "iso:country":"DE",
    "sg:address":"Etzenbach 16",
    "sg:city":"Staufen",
    "sg:phone":"+49 7636/208",
    "sg:postcode":"79219",
    "sg:province":"Baden-W\u00fcrttemberg",
    "wof:name":"Cat M. Zipperer Gmbh",
    "wof:placetype":"venue"
},
  "geometry": {"coordinates":[7.7571558952,47.864440918],"type":"Point"}
}