{
  "type": "Feature",
  "properties": {
    "iso:country":"DE",
    "sg:address":"Poststr. 73",
    "sg:city":"Merzig",
    "sg:postcode":"66663",
    "sg:province":"Saarland",
    "wof:name":"Vie Exclusive Merzig Gmbh",
    "wof:placetype":"venue"
},
  "geometry": {"coordinates":[6.640460968,49.4440574646],"type":"Point"}
}