{
  "type": "Feature",
  "properties": {
    "iso:country":"DE",
    "sg:address":"Asemisser Allee 3 a",
    "sg:city":"Leopoldsh\u00f6he",
    "sg:phone":"+49 5202/81089",
    "sg:postcode":"33818",
    "sg:province":"Nordrhein-Westfalen",
    "wof:name":"Egon Lau",
    "wof:placetype":"venue"
},
  "geometry": {"coordinates":[8.668761,51.978642],"type":"Point"}
}