{
  "type": "Feature",
  "properties": {
    "iso:country":"DE",
    "sg:address":"Strandstr. 63",
    "sg:city":"Wyk",
    "sg:phone":"+49 4681/2123",
    "sg:postcode":"25938",
    "sg:province":"Schleswig-Holstein",
    "wof:name":"M\u00f6bel-schulz Gmbh",
    "wof:placetype":"venue"
},
  "geometry": {"coordinates":[8.550876,54.687542],"type":"Point"}
}