{
  "type": "Feature",
  "properties": {
    "iso:country":"DE",
    "sg:address":"Bahnhofstr. 33a",
    "sg:city":"Fahrenbach",
    "sg:phone":"+49 6267/6300",
    "sg:postcode":"74864",
    "sg:province":"Baden-W\u00fcrttemberg",
    "wof:name":"Gem\u00fctlich",
    "wof:placetype":"venue"
},
  "geometry": {"coordinates":[9.156955719,49.431476593],"type":"Point"}
}