{
  "type": "Feature",
  "properties": {
    "iso:country":"DE",
    "sg:address":"Busshook 9",
    "sg:city":"Legden",
    "sg:phone":"+49 2566/972500",
    "sg:postcode":"48739",
    "sg:province":"Nordrhein-Westfalen",
    "wof:name":"Von Ingersleben Gesellschaft F\u00fcr Standortentwicklung In",
    "wof:placetype":"venue"
},
  "geometry": {"coordinates":[7.1066,52.02948],"type":"Point"}
}