{
  "type": "Feature",
  "properties": {
    "iso:country":"DE",
    "sg:address":"August-Eckardt-Str. 13",
    "sg:city":"Friedrichroda",
    "sg:phone":"+49 3623/304844",
    "sg:postcode":"99894",
    "sg:province":"Th\u00fcringen",
    "wof:name":"Heinz Merrbach",
    "wof:placetype":"venue"
},
  "geometry": {"coordinates":[10.567789,50.858288],"type":"Point"}
}