{
  "type": "Feature",
  "properties": {
    "iso:country":"DE",
    "sg:address":"Am Schlo\u00dfberg 5",
    "sg:city":"Stegaurach",
    "sg:phone":"+49 951/290611",
    "sg:postcode":"96135",
    "sg:province":"Bayern",
    "wof:name":"Admiral Objekt W\u00e4sche Und Arbeitskleidung Gmbh & Co.",
    "wof:placetype":"venue"
},
  "geometry": {"coordinates":[10.8461360931,49.8640556335],"type":"Point"}
}