{
  "type": "Feature",
  "properties": {
    "iso:country":"DE",
    "sg:address":"D\u00f6hrbruch 66",
    "sg:city":"Hannover",
    "sg:phone":"+49 511/957990",
    "sg:postcode":"30559",
    "sg:province":"Niedersachsen",
    "wof:name":"Zimmermann + Collegen",
    "wof:placetype":"venue"
},
  "geometry": {"coordinates":[9.8131799698,52.3499984741],"type":"Point"}
}