{
  "type": "Feature",
  "properties": {
    "iso:country":"DE",
    "sg:address":"Magdeburger Chaussee",
    "sg:city":"Halle",
    "sg:postcode":"06118",
    "sg:province":"Sachsen-Anhalt",
    "wof:name":"Hildebrandt",
    "wof:placetype":"venue"
},
  "geometry": {"coordinates":[11.9478502274,51.5267448425],"type":"Point"}
}