{
  "type": "Feature",
  "properties": {
    "iso:country":"DE",
    "sg:address":"Feuerbachstr. 16",
    "sg:city":"Berlin",
    "sg:phone":"+49 30/7922845",
    "sg:postcode":"12163",
    "sg:province":"Berlin",
    "wof:name":"Thai Restaurant Bali",
    "wof:placetype":"venue"
},
  "geometry": {"coordinates":[13.3291625977,52.4631958008],"type":"Point"}
}