{
  "type": "Feature",
  "properties": {
    "iso:country":"DE",
    "sg:address":"H\u00f6henweg 2",
    "sg:city":"Gro\u00dfburschla",
    "sg:phone":"+49 36923/88206",
    "sg:postcode":"99830",
    "sg:province":"Th\u00fcringen",
    "wof:name":"Torsten Ruhlandt Polsterm\u00f6bel Und Raumausstattung",
    "wof:placetype":"venue"
},
  "geometry": {"coordinates":[10.171806,51.13459],"type":"Point"}
}