{
  "type": "Feature",
  "properties": {
    "iso:country":"DE",
    "sg:address":"Bahnhofstr. 1",
    "sg:city":"Pfaffenhausen",
    "sg:phone":"+49 8265/252",
    "sg:postcode":"87772",
    "sg:province":"Bayern",
    "wof:name":"F. Schwankhart",
    "wof:placetype":"venue"
},
  "geometry": {"coordinates":[10.4522037506,48.1183700562],"type":"Point"}
}