{
  "type": "Feature",
  "properties": {
    "iso:country":"DE",
    "sg:address":"Schmaler Weg 23",
    "sg:city":"Dortmund",
    "sg:phone":"+49 231/441297",
    "sg:postcode":"44287",
    "sg:province":"Nordrhein-Westfalen",
    "wof:name":"Th. Schmitz",
    "wof:placetype":"venue"
},
  "geometry": {"coordinates":[7.56486,51.485043],"type":"Point"}
}