{
  "type": "Feature",
  "properties": {
    "iso:country":"DE",
    "sg:address":"Rosenweg 42",
    "sg:city":"Wurzen",
    "sg:phone":"+49 3425/926691",
    "sg:postcode":"04808",
    "sg:province":"Sachsen",
    "wof:name":"Waldemar Staffe",
    "wof:placetype":"venue"
},
  "geometry": {"coordinates":[12.727605,51.381275],"type":"Point"}
}