{
  "type": "Feature",
  "properties": {
    "iso:country":"DE",
    "sg:address":"Gau\u00dfstr. 7",
    "sg:city":"Herne",
    "sg:phone":"+49 2325/44731",
    "sg:postcode":"44625",
    "sg:province":"Nordrhein-Westfalen",
    "wof:name":"Sonne Mond Und Sterne E. V. Herr Anklam",
    "wof:placetype":"venue"
},
  "geometry": {"coordinates":[7.1956100464,51.5308265686],"type":"Point"}
}