{
  "type": "Feature",
  "properties": {
    "iso:country":"DE",
    "sg:address":"Harald Friedrich Stra\u00dfe 2-8",
    "sg:city":"Altenmarkt",
    "sg:phone":"+49 4908/621880",
    "sg:postcode":"83352",
    "sg:province":"Bayern",
    "wof:name":"Alzetall",
    "wof:placetype":"venue"
},
  "geometry": {"coordinates":[12.535836,47.999947],"type":"Point"}
}