{
  "type": "Feature",
  "properties": {
    "iso:country":"DE",
    "sg:address":"Untersch\u00fcpfer Str. 55",
    "sg:city":"Boxberg",
    "sg:postcode":"97944",
    "sg:province":"Baden-W\u00fcrttemberg",
    "wof:name":"H. Egetemeier Gmbh",
    "wof:placetype":"venue"
},
  "geometry": {"coordinates":[9.692886,49.513729],"type":"Point"}
}