{
  "type": "Feature",
  "properties": {
    "iso:country":"DE",
    "sg:address":"Waldhofstr. 6c",
    "sg:city":"Freiburg",
    "sg:phone":"+49 761/67337",
    "sg:postcode":"79117",
    "sg:province":"Baden-W\u00fcrttemberg",
    "wof:name":"Dr. K. Und A. Krimmel Steuerberater",
    "wof:placetype":"venue"
},
  "geometry": {"coordinates":[7.8972020149,47.9765853882],"type":"Point"}
}