{
  "type": "Feature",
  "properties": {
    "iso:country":"DE",
    "sg:address":"Seebr\u00fcckle 4",
    "sg:city":"G\u00fcglingen",
    "sg:phone":"+49 7135/97577",
    "sg:postcode":"74363",
    "sg:province":"Baden-W\u00fcrttemberg",
    "wof:name":"Taxi Gebr. Gabriel Gmbh",
    "wof:placetype":"venue"
},
  "geometry": {"coordinates":[9.0160560608,49.065662384],"type":"Point"}
}