{
  "type": "Feature",
  "properties": {
    "iso:country":"DE",
    "sg:address":"Am Theuspfad 72",
    "sg:city":"Pulheim",
    "sg:phone":"+49 2238/83477",
    "sg:postcode":"50259",
    "sg:province":"Nordrhein-Westfalen",
    "wof:name":"Petra Und Hans-heinr. Klingen",
    "wof:placetype":"venue"
},
  "geometry": {"coordinates":[6.8234138489,51.0256690979],"type":"Point"}
}