{
  "type": "Feature",
  "properties": {
    "iso:country":"DE",
    "sg:address":"Lohbr\u00fcgger Landstr. 171",
    "sg:city":"Hamburg",
    "sg:phone":"+49 40/7399948",
    "sg:postcode":"21031",
    "sg:province":"Hamburg",
    "wof:name":"Burg-drogerie Kurt Frenzen",
    "wof:placetype":"venue"
},
  "geometry": {"coordinates":[10.186671,53.505291],"type":"Point"}
}