{
  "type": "Feature",
  "properties": {
    "iso:country":"DE",
    "sg:address":"Am Plessen 1",
    "sg:city":"Hasbergen",
    "sg:phone":"+49 5405/5879",
    "sg:postcode":"49205",
    "sg:province":"Niedersachsen",
    "wof:name":"Restaurant Gausenest",
    "wof:placetype":"venue"
},
  "geometry": {"coordinates":[7.9484820366,52.2252922058],"type":"Point"}
}