{
  "type": "Feature",
  "properties": {
    "iso:country":"DE",
    "sg:address":"Sch\u00f6nbornsluster Str. 35",
    "sg:city":"Koblenz",
    "sg:phone":"+49 261/81035",
    "sg:postcode":"56070",
    "sg:province":"Rheinland-Pfalz",
    "wof:name":"Hm Moskopp Elektromotoren Gmbh & Co. Kg",
    "wof:placetype":"venue"
},
  "geometry": {"coordinates":[7.5923352242,50.3789176941],"type":"Point"}
}