{
  "type": "Feature",
  "properties": {
    "iso:country":"DE",
    "sg:address":"Kueser Plateau 7",
    "sg:city":"Bernkastel-Kues",
    "sg:phone":"+49 6531/2091",
    "sg:postcode":"54470",
    "sg:province":"Rheinland-Pfalz",
    "wof:name":"Mosellandtouristik",
    "wof:placetype":"venue"
},
  "geometry": {"coordinates":[7.0500769615,49.9203605652],"type":"Point"}
}