{
  "type": "Feature",
  "properties": {
    "iso:country":"DE",
    "sg:address":"Sportplatz 8",
    "sg:city":"Weil am Rhein",
    "sg:phone":"+49 7621/71346",
    "sg:postcode":"79576",
    "sg:province":"Baden-W\u00fcrttemberg",
    "wof:name":"Vereinsgastst\u00e4tte Esv Sportlerklause",
    "wof:placetype":"venue"
},
  "geometry": {"coordinates":[7.6135668755,47.5877151489],"type":"Point"}
}