{
  "type": "Feature",
  "properties": {
    "iso:country":"DE",
    "sg:address":"Kirchstr. 16",
    "sg:city":"Ihringen",
    "sg:phone":"+49 7668/237",
    "sg:postcode":"79241",
    "sg:province":"Baden-W\u00fcrttemberg",
    "wof:name":"Helmut Hohwieler",
    "wof:placetype":"venue"
},
  "geometry": {"coordinates":[7.6495461464,48.0460777283],"type":"Point"}
}