{
  "type": "Feature",
  "properties": {
    "iso:country":"DE",
    "sg:address":"Lindenstr. 3",
    "sg:city":"Rodewisch",
    "sg:phone":"+49 3744/48388",
    "sg:postcode":"08228",
    "sg:province":"Sachsen",
    "wof:name":"Schortmann & Sohn Gmbh",
    "wof:placetype":"venue"
},
  "geometry": {"coordinates":[12.401408,50.528515],"type":"Point"}
}