{
  "type": "Feature",
  "properties": {
    "iso:country":"DE",
    "sg:address":"Fellbacher Str. 29",
    "sg:city":"Berlin",
    "sg:phone":"+49 30/4048801",
    "sg:postcode":"13467",
    "sg:province":"Berlin",
    "wof:name":"Avance Damenmode & Mehr Inh. Renate Ostrominski E.kfr.",
    "wof:placetype":"venue"
},
  "geometry": {"coordinates":[13.307353,52.61573],"type":"Point"}
}