{
  "type": "Feature",
  "properties": {
    "iso:country":"DE",
    "sg:address":"Reu\u00dfensteinstr. 49",
    "sg:city":"B\u00f6blingen",
    "sg:postcode":"71032",
    "sg:province":"Baden-W\u00fcrttemberg",
    "wof:name":"Hep Genu\u00dfmittelvertriebs- Gmbh",
    "wof:placetype":"venue"
},
  "geometry": {"coordinates":[9.0265674591,48.6814193726],"type":"Point"}
}