{
  "type": "Feature",
  "properties": {
    "iso:country":"DE",
    "sg:address":"Kaiserau 2",
    "sg:city":"Lindlar",
    "sg:postcode":"51789",
    "sg:province":"Nordrhein-Westfalen",
    "wof:name":"D\u00f6pper & Schmitz Tischlerei Gmbh",
    "wof:placetype":"venue"
},
  "geometry": {"coordinates":[7.436845,51.035801],"type":"Point"}
}