{
  "type": "Feature",
  "properties": {
    "iso:country":"DE",
    "sg:address":"Gustav-Heinemann-Ufer 84-88",
    "sg:city":"Koeln",
    "sg:phone":"+49 221",
    "sg:postcode":"50968",
    "sg:province":"Nordrhein-Westfalen",
    "wof:name":"Deutschland Innovativ",
    "wof:placetype":"venue"
},
  "geometry": {"coordinates":[6.972756,50.912182],"type":"Point"}
}