{
  "type": "Feature",
  "properties": {
    "iso:country":"DE",
    "sg:address":"Gastenfelden 6",
    "sg:city":"Buch a. Wald",
    "sg:postcode":"91592",
    "sg:province":"Bayern",
    "wof:name":"Fritz Klaus",
    "wof:placetype":"venue"
},
  "geometry": {"coordinates":[10.296215,49.314472],"type":"Point"}
}