{
  "type": "Feature",
  "properties": {
    "iso:country":"DE",
    "sg:address":"Borker Str. 281",
    "sg:city":"L\u00fcnen",
    "sg:phone":"+49 2306/757500",
    "sg:postcode":"44534",
    "sg:province":"Nordrhein-Westfalen",
    "wof:name":"Hotel Wilhelm Bielefeld",
    "wof:placetype":"venue"
},
  "geometry": {"coordinates":[7.5058298111,51.646068573],"type":"Point"}
}