{
  "type": "Feature",
  "properties": {
    "iso:country":"DE",
    "sg:address":"Hauptmannsgreut 11",
    "sg:city":"Betzigau",
    "sg:phone":"+49 8304/287",
    "sg:postcode":"87488",
    "sg:province":"Bayern",
    "wof:name":"Mittelallg\u00e4u",
    "wof:placetype":"venue"
},
  "geometry": {"coordinates":[10.4434108734,47.7402572632],"type":"Point"}
}