{
  "type": "Feature",
  "properties": {
    "iso:country":"DE",
    "sg:address":"Olpener Str. 61",
    "sg:city":"K\u00f6ln",
    "sg:phone":"+49 221/871613",
    "sg:postcode":"51103",
    "sg:province":"Nordrhein-Westfalen",
    "wof:name":"H\u00f6henberg-apotheke",
    "wof:placetype":"venue"
},
  "geometry": {"coordinates":[7.03279,50.940338],"type":"Point"}
}