{
  "type": "Feature",
  "properties": {
    "iso:country":"DE",
    "sg:address":"Mittlere Ortsstr. 102",
    "sg:city":"R\u00fclzheim",
    "sg:phone":"+49 7272/6999",
    "sg:postcode":"76761",
    "sg:province":"Rheinland-Pfalz",
    "wof:name":"Margarethe Schmiedebach",
    "wof:placetype":"venue"
},
  "geometry": {"coordinates":[8.289389,49.156147],"type":"Point"}
}