{
  "type": "Feature",
  "properties": {
    "iso:country":"DE",
    "sg:address":"Riedler Str. 10",
    "sg:city":"Untergriesbach",
    "sg:phone":"+49 8593/716",
    "sg:postcode":"94107",
    "sg:province":"Bayern",
    "wof:name":"W. Rosenberger",
    "wof:placetype":"venue"
},
  "geometry": {"coordinates":[13.7296733856,48.5315666199],"type":"Point"}
}