{
  "type": "Feature",
  "properties": {
    "iso:country":"DE",
    "sg:address":"Am Schwarzen Sch\u00f6ps 22",
    "sg:city":"Quitzdorf am See",
    "sg:phone":"+49 3588/201134",
    "sg:postcode":"02906",
    "sg:province":"Sachsen",
    "wof:name":"Heiderose Silbe",
    "wof:placetype":"venue"
},
  "geometry": {"coordinates":[14.7430887222,51.2930717468],"type":"Point"}
}