{
  "type": "Feature",
  "properties": {
    "iso:country":"DE",
    "sg:address":"Moosstr. 3",
    "sg:city":"Langenbach",
    "sg:phone":"+49 8761/62614",
    "sg:postcode":"85416",
    "sg:province":"Bayern",
    "wof:name":"Gl\u00e4ser Design Uwe Gl\u00e4ser",
    "wof:placetype":"venue"
},
  "geometry": {"coordinates":[11.85324,48.44331],"type":"Point"}
}