{
  "type": "Feature",
  "properties": {
    "iso:country":"DE",
    "sg:address":"Freisinger Str. 15a",
    "sg:city":"Oberding",
    "sg:phone":"+49 8122/42758",
    "sg:postcode":"85445",
    "sg:province":"Bayern",
    "wof:name":"Hans Winkler",
    "wof:placetype":"venue"
},
  "geometry": {"coordinates":[11.8430814743,48.3362998962],"type":"Point"}
}