{
  "type": "Feature",
  "properties": {
    "iso:country":"DE",
    "sg:address":"Bleicherufer 11",
    "sg:city":"Schwerin",
    "sg:phone":"+49 385/558780",
    "sg:postcode":"19053",
    "sg:province":"Mecklenburg-Vorpommern",
    "wof:name":"Bbb Ingenieurb\u00fcro F\u00fcr Bauwerksdiagnose Bauphysik",
    "wof:placetype":"venue"
},
  "geometry": {"coordinates":[11.4008808136,53.6212882996],"type":"Point"}
}