{
  "type": "Feature",
  "properties": {
    "iso:country":"DE",
    "sg:address":"Tarpenbekstr. 48",
    "sg:city":"Hamburg",
    "sg:postcode":"20251",
    "sg:province":"Hamburg",
    "wof:name":"Lok Operations Agentur F\u00fcr Events Und Marketing Gmbh",
    "wof:placetype":"venue"
},
  "geometry": {"coordinates":[9.9840936661,53.5935897827],"type":"Point"}
}