{
  "type": "Feature",
  "properties": {
    "iso:country":"DE",
    "sg:address":"Mussumer Kirchweg 4- 6",
    "sg:city":"Bocholt",
    "sg:phone":"+49 2871/281600",
    "sg:postcode":"46395",
    "sg:province":"Nordrhein-Westfalen",
    "wof:name":"Grenzlandf\u00e4rberei Geuting Gmbh",
    "wof:placetype":"venue"
},
  "geometry": {"coordinates":[6.6120901108,51.8282089233],"type":"Point"}
}