{
  "type": "Feature",
  "properties": {
    "iso:country":"DE",
    "sg:address":"Oberstr. 44",
    "sg:city":"Spiesheim",
    "sg:phone":"+49 6732/7629",
    "sg:postcode":"55288",
    "sg:province":"Rheinland-Pfalz",
    "wof:name":"Horst Becker",
    "wof:placetype":"venue"
},
  "geometry": {"coordinates":[8.1266002655,49.8102760315],"type":"Point"}
}