{
  "type": "Feature",
  "properties": {
    "iso:country":"DE",
    "sg:address":"Wiesenstr. 11",
    "sg:city":"Pfungstadt",
    "sg:postcode":"64319",
    "sg:province":"Hessen",
    "wof:name":"Steelite International Deutschland Gmbh",
    "wof:placetype":"venue"
},
  "geometry": {"coordinates":[8.560453,49.803406],"type":"Point"}
}