{
  "type": "Feature",
  "properties": {
    "iso:country":"DE",
    "sg:address":"Rupert-Mayer-Str. 74",
    "sg:city":"Neuhausen",
    "sg:phone":"+49 7158/6695",
    "sg:postcode":"73765",
    "sg:province":"Baden-W\u00fcrttemberg",
    "wof:name":"Egelsee-festhalle",
    "wof:placetype":"venue"
},
  "geometry": {"coordinates":[9.2812900543,48.6798782349],"type":"Point"}
}