{
  "type": "Feature",
  "properties": {
    "iso:country":"DE",
    "sg:address":"T\u00fcskenheide 36",
    "sg:city":"G\u00fctersloh",
    "sg:phone":"+49 5241/79608",
    "sg:postcode":"33332",
    "sg:province":"Nordrhein-Westfalen",
    "wof:name":"R. Neuhaus",
    "wof:placetype":"venue"
},
  "geometry": {"coordinates":[8.4121198654,51.904209137],"type":"Point"}
}