{
  "type": "Feature",
  "properties": {
    "iso:country":"DE",
    "sg:address":"Feldstr. 63",
    "sg:city":"Oberhausen",
    "sg:phone":"+49 8651/3820",
    "sg:postcode":"46149",
    "sg:province":"Nordrhein-Westfalen",
    "wof:name":"Fritz Mayer",
    "wof:placetype":"venue"
},
  "geometry": {"coordinates":[12.8926267624,47.741809845],"type":"Point"}
}