{
  "type": "Feature",
  "properties": {
    "iso:country":"DE",
    "sg:address":"Gr\u00e4finthaler Str. 12",
    "sg:city":"Saarbr\u00fccken",
    "sg:phone":"+49 6893/3408",
    "sg:postcode":"66130",
    "sg:province":"Saarland",
    "wof:name":"Christian Duwe",
    "wof:placetype":"venue"
},
  "geometry": {"coordinates":[7.10339,49.188984],"type":"Point"}
}