{
  "type": "Feature",
  "properties": {
    "iso:country":"DE",
    "sg:address":"Schwarzbuchenweg 22a",
    "sg:city":"Hamburg",
    "sg:phone":"+49 40/5362488",
    "sg:postcode":"22391",
    "sg:province":"Hamburg",
    "wof:name":"Horst Lange",
    "wof:placetype":"venue"
},
  "geometry": {"coordinates":[10.0756196976,53.636516571],"type":"Point"}
}