{
  "type": "Feature",
  "properties": {
    "iso:country":"DE",
    "sg:address":"Kieselstr. 3",
    "sg:city":"Leverkusen",
    "sg:phone":"+49 2173/94410",
    "sg:postcode":"51371",
    "sg:province":"Nordrhein-Westfalen",
    "wof:name":"Droesser Gesch\u00e4ftsf\u00fchrungs-gmbh",
    "wof:placetype":"venue"
},
  "geometry": {"coordinates":[6.9262242317,51.0646781921],"type":"Point"}
}