{
  "type": "Feature",
  "properties": {
    "iso:country":"DE",
    "sg:address":"Reichsstr. 7",
    "sg:city":"Kempten",
    "sg:phone":"+49 831/28841",
    "sg:postcode":"87435",
    "sg:province":"Bayern",
    "wof:name":"Erhan Taghanli",
    "wof:placetype":"venue"
},
  "geometry": {"coordinates":[10.3186903,47.7255134583],"type":"Point"}
}