{
  "type": "Feature",
  "properties": {
    "iso:country":"DE",
    "sg:address":"Rodigallee 8",
    "sg:city":"Hamburg",
    "sg:phone":"+49 40/65720086",
    "sg:postcode":"22043",
    "sg:province":"Hamburg",
    "wof:name":"Abic Andreas Budde",
    "wof:placetype":"venue"
},
  "geometry": {"coordinates":[10.093547821,53.5684967041],"type":"Point"}
}