{
  "type": "Feature",
  "properties": {
    "iso:country":"DE",
    "sg:address":"Krumme Fohre 85",
    "sg:city":"Kasendorf",
    "sg:phone":"+49 9228/303",
    "sg:postcode":"95359",
    "sg:province":"Bayern",
    "wof:name":"Peter Ellner Ohg",
    "wof:placetype":"venue"
},
  "geometry": {"coordinates":[11.3862581253,50.0568885803],"type":"Point"}
}