{
  "type": "Feature",
  "properties": {
    "iso:country":"DE",
    "sg:address":"Laubrother Str. 2",
    "sg:city":"Bad Berleburg",
    "sg:phone":"+49 2751/5543",
    "sg:postcode":"57319",
    "sg:province":"Nordrhein-Westfalen",
    "wof:name":"Ludwig Grebe",
    "wof:placetype":"venue"
},
  "geometry": {"coordinates":[8.411889,51.016029],"type":"Point"}
}