{
  "type": "Feature",
  "properties": {
    "iso:country":"DE",
    "sg:address":"Eschenweg 44",
    "sg:city":"Zwickau",
    "sg:phone":"+49 375/525275",
    "sg:postcode":"08060",
    "sg:province":"Sachsen",
    "wof:name":"Lutz Gerischer Ingenieur",
    "wof:placetype":"venue"
},
  "geometry": {"coordinates":[12.4469947815,50.7256622314],"type":"Point"}
}