{
  "type": "Feature",
  "properties": {
    "iso:country":"DE",
    "sg:address":"Selliner Str. 15",
    "sg:city":"Dresden",
    "sg:phone":"+49 351/8806935",
    "sg:postcode":"01109",
    "sg:province":"Sachsen",
    "wof:name":"Malermeister Michael F\u00f6rster",
    "wof:placetype":"venue"
},
  "geometry": {"coordinates":[13.786461,51.120174],"type":"Point"}
}