{
  "type": "Feature",
  "properties": {
    "iso:country":"DE",
    "sg:address":"Weihergasse 16",
    "sg:city":"Niederbreitbach",
    "sg:phone":"+49 2638/1015",
    "sg:postcode":"56589",
    "sg:province":"Rheinland-Pfalz",
    "wof:name":"Hotel Wiedperle",
    "wof:placetype":"venue"
},
  "geometry": {"coordinates":[7.4149222374,50.5305938721],"type":"Point"}
}