{
  "type": "Feature",
  "properties": {
    "iso:country":"DE",
    "sg:address":"Braugasse 2",
    "sg:city":"Zwota",
    "sg:phone":"+49 37467/26581",
    "sg:postcode":"08267",
    "sg:province":"Sachsen",
    "wof:name":"E. Schmidt",
    "wof:placetype":"venue"
},
  "geometry": {"coordinates":[12.4321269989,50.3539924622],"type":"Point"}
}