{
  "type": "Feature",
  "properties": {
    "iso:country":"DE",
    "sg:address":"Sonnenstr. 32",
    "sg:city":"Gunzenhausen",
    "sg:phone":"+49 9831/9980",
    "sg:postcode":"91710",
    "sg:province":"Bayern",
    "wof:name":"Barbara Formann",
    "wof:placetype":"venue"
},
  "geometry": {"coordinates":[10.7592458725,49.1133041382],"type":"Point"}
}