{
  "type": "Feature",
  "properties": {
    "iso:country":"DE",
    "sg:address":"Katharinenstr. 25",
    "sg:city":"Esslingen",
    "sg:phone":"+49 711/355426",
    "sg:postcode":"73728",
    "sg:province":"Baden-W\u00fcrttemberg",
    "wof:name":"W. H\u00fcttl",
    "wof:placetype":"venue"
},
  "geometry": {"coordinates":[9.3136167526,48.7372398376],"type":"Point"}
}