{
  "type": "Feature",
  "properties": {
    "iso:country":"DE",
    "sg:address":"Gabelsbergerstr. 14",
    "sg:city":"Chemnitz",
    "sg:phone":"+49 371/858146",
    "sg:postcode":"09117",
    "sg:province":"Sachsen",
    "wof:name":"Georg Hahn Nachf. Gmbh",
    "wof:placetype":"venue"
},
  "geometry": {"coordinates":[12.830538,50.814678],"type":"Point"}
}