{
  "type": "Feature",
  "properties": {
    "iso:country":"DE",
    "sg:address":"Grader Weg 18",
    "sg:city":"Papenburg",
    "sg:phone":"+49 4961/916916",
    "sg:postcode":"26871",
    "sg:province":"Niedersachsen",
    "wof:name":"Ambulanter Alten- Und Krankenpflegedienst",
    "wof:placetype":"venue"
},
  "geometry": {"coordinates":[7.414384,53.074272],"type":"Point"}
}