{
  "type": "Feature",
  "properties": {
    "iso:country":"DE",
    "sg:address":"Stra\u00dfberger Str. 1",
    "sg:city":"Plauen",
    "sg:phone":"+49 3741/15690",
    "sg:postcode":"08527",
    "sg:province":"Sachsen",
    "wof:name":"Hpm Bautr\u00e4ger Und Immobilien Gmbh",
    "wof:placetype":"venue"
},
  "geometry": {"coordinates":[12.135621,50.493298],"type":"Point"}
}