{
  "type": "Feature",
  "properties": {
    "iso:country":"DE",
    "sg:address":"Holzhausen 21",
    "sg:city":"Stolzenau",
    "sg:phone":"+49 5761/1533",
    "sg:postcode":"31592",
    "sg:province":"Niedersachsen",
    "wof:name":"G\u00fcnther Curt",
    "wof:placetype":"venue"
},
  "geometry": {"coordinates":[9.06966,52.511822],"type":"Point"}
}