{
  "type": "Feature",
  "properties": {
    "iso:country":"DE",
    "sg:address":"Loit",
    "sg:city":"Loit",
    "sg:phone":"+49 4641/2649",
    "sg:postcode":"24888",
    "sg:province":"Schleswig-Holstein",
    "wof:name":"G. Kr\u00e4tzer",
    "wof:placetype":"venue"
},
  "geometry": {"coordinates":[9.7462596893,54.5984344482],"type":"Point"}
}