{
  "type": "Feature",
  "properties": {
    "iso:country":"DE",
    "sg:address":"Mendelssohnstr. 1",
    "sg:city":"Hannover",
    "sg:phone":"+49 511/8091191",
    "sg:postcode":"30173",
    "sg:province":"Niedersachsen",
    "wof:name":"Adolf Zoch",
    "wof:placetype":"venue"
},
  "geometry": {"coordinates":[9.755234,52.360142],"type":"Point"}
}