{
  "type": "Feature",
  "properties": {
    "iso:country":"DE",
    "sg:address":"Untergasse 10a",
    "sg:city":"Gie\u00dfen",
    "sg:phone":"+49 6403/8318",
    "sg:postcode":"35398",
    "sg:province":"Hessen",
    "wof:name":"R. Volk",
    "wof:placetype":"venue"
},
  "geometry": {"coordinates":[8.6169319153,50.5505332947],"type":"Point"}
}