{
  "type": "Feature",
  "properties": {
    "iso:country":"DE",
    "sg:address":"Schillerstr. 82",
    "sg:city":"Zepernick",
    "sg:phone":"+49 30/9415172",
    "sg:postcode":"16341",
    "sg:province":"Brandenburg",
    "wof:name":"Schilder & Licht Elektro-bachnick Gmbh",
    "wof:placetype":"venue"
},
  "geometry": {"coordinates":[13.52136,52.64922],"type":"Point"}
}