{
  "type": "Feature",
  "properties": {
    "iso:country":"DE",
    "sg:address":"Wilsdruffer Str. 170",
    "sg:city":"Freital",
    "sg:phone":"+49 351/658030",
    "sg:postcode":"01705",
    "sg:province":"Sachsen",
    "wof:name":"Bombastus-werke Ag",
    "wof:placetype":"venue"
},
  "geometry": {"coordinates":[13.6299791336,51.0211715698],"type":"Point"}
}