{
  "type": "Feature",
  "properties": {
    "iso:country":"DE",
    "sg:address":"Havelstr. 92",
    "sg:city":"Birkenwerder",
    "sg:phone":"+49 3303/503880",
    "sg:postcode":"16547",
    "sg:province":"Brandenburg",
    "wof:name":"Der Telefonladen Inh. Helga Buge",
    "wof:placetype":"venue"
},
  "geometry": {"coordinates":[13.2657489777,52.6885719299],"type":"Point"}
}