{
  "type": "Feature",
  "properties": {
    "iso:country":"DE",
    "sg:address":"Pankratiusstr. 1",
    "sg:city":"Offenburg",
    "sg:phone":"+49 781/25808",
    "sg:postcode":"77652",
    "sg:province":"Baden-W\u00fcrttemberg",
    "wof:name":"Karl Burger",
    "wof:placetype":"venue"
},
  "geometry": {"coordinates":[7.9558739662,48.5148735046],"type":"Point"}
}