{
  "type": "Feature",
  "properties": {
    "iso:country":"DE",
    "sg:address":"Lorcher Str. 9",
    "sg:city":"Alfdorf",
    "sg:phone":"+49 7172/31381",
    "sg:postcode":"73553",
    "sg:province":"Baden-W\u00fcrttemberg",
    "wof:name":"G. H\u00e4gele",
    "wof:placetype":"venue"
},
  "geometry": {"coordinates":[9.6828670502,48.8395996094],"type":"Point"}
}