{
  "type": "Feature",
  "properties": {
    "iso:country":"DE",
    "sg:address":"Schuckenteichweg 25",
    "sg:city":"Leopoldsh\u00f6he",
    "sg:phone":"+49 5208/91180",
    "sg:postcode":"33818",
    "sg:province":"Nordrhein-Westfalen",
    "wof:name":"Yestel Dial & Services S. Jacek Gmbh",
    "wof:placetype":"venue"
},
  "geometry": {"coordinates":[8.6916532516,52.0083427429],"type":"Point"}
}