{
  "type": "Feature",
  "properties": {
    "iso:country":"DE",
    "sg:address":"Haus-Biringer-Str. 6",
    "sg:city":"Perl",
    "sg:phone":"+49 6867/5343",
    "sg:postcode":"66706",
    "sg:province":"Saarland",
    "wof:name":"E. Bertel",
    "wof:placetype":"venue"
},
  "geometry": {"coordinates":[6.3931260109,49.4754447937],"type":"Point"}
}