{
  "type": "Feature",
  "properties": {
    "iso:country":"DE",
    "sg:address":"Postfach 1101",
    "sg:city":"Salzkotten",
    "sg:phone":"+49 5251/32900",
    "sg:postcode":"33143",
    "sg:province":"Nordrhein-Westfalen",
    "wof:name":"Wortmann-transporte Gmbh",
    "wof:placetype":"venue"
},
  "geometry": {"coordinates":[8.6090402603,51.6737098694],"type":"Point"}
}