{
  "type": "Feature",
  "properties": {
    "iso:country":"DE",
    "sg:address":"Rheinbr\u00fcckstr. 19",
    "sg:city":"Bad S\u00e4ckingen",
    "sg:phone":"+49 7761/6011",
    "sg:postcode":"79713",
    "sg:province":"Baden-W\u00fcrttemberg",
    "wof:name":"Reiseb\u00fcro Bad S\u00e4ckingen Gmbh",
    "wof:placetype":"venue"
},
  "geometry": {"coordinates":[7.9490280151,47.5523376465],"type":"Point"}
}