{
  "type": "Feature",
  "properties": {
    "iso:country":"DE",
    "sg:address":"Astfelder Str. 9",
    "sg:city":"Goslar",
    "sg:phone":"+49 5321/42888",
    "sg:postcode":"38640",
    "sg:province":"Niedersachsen",
    "wof:name":"R. Von Schachtmeyer",
    "wof:placetype":"venue"
},
  "geometry": {"coordinates":[10.4198102951,51.9096412659],"type":"Point"}
}