{
  "type": "Feature",
  "properties": {
    "iso:country":"DE",
    "sg:address":"Dingst\u00e4tte 20",
    "sg:city":"Pinneberg",
    "sg:phone":"+49 4101/25738",
    "sg:postcode":"25421",
    "sg:province":"Schleswig-Holstein",
    "wof:name":"Karl Krysik Architekt",
    "wof:placetype":"venue"
},
  "geometry": {"coordinates":[9.797953,53.661274],"type":"Point"}
}