{
  "type": "Feature",
  "properties": {
    "iso:country":"DE",
    "sg:address":"Marienstr. 5",
    "sg:city":"Bottrop",
    "sg:phone":"+49 2045/82581",
    "sg:postcode":"46244",
    "sg:province":"Nordrhein-Westfalen",
    "wof:name":"Sfb Schl\u00fcssel-fertig-bau Lippe-emscher Gmbh",
    "wof:placetype":"venue"
},
  "geometry": {"coordinates":[6.9735097885,51.6101417542],"type":"Point"}
}