{
  "type": "Feature",
  "properties": {
    "iso:country":"DE",
    "sg:address":"Obere Bergstr. 47",
    "sg:city":"Radebeul",
    "sg:phone":"+49 351/8307698",
    "sg:postcode":"01445",
    "sg:province":"Sachsen",
    "wof:name":"Manfred Spiering",
    "wof:placetype":"venue"
},
  "geometry": {"coordinates":[13.637298584,51.1139717102],"type":"Point"}
}