{
  "type": "Feature",
  "properties": {
    "iso:country":"DE",
    "sg:address":"Balkenst\u00fccken 2",
    "sg:city":"Hamburg",
    "sg:phone":"+49 40/6445329",
    "sg:postcode":"22159",
    "sg:province":"Hamburg",
    "wof:name":"Kay Tombers",
    "wof:placetype":"venue"
},
  "geometry": {"coordinates":[10.1269664764,53.6264648438],"type":"Point"}
}