{
  "type": "Feature",
  "properties": {
    "iso:country":"DE",
    "sg:address":"Bismarckstr. 90",
    "sg:city":"Remscheid",
    "sg:phone":"+49 2191/340380",
    "sg:postcode":"42859",
    "sg:province":"Nordrhein-Westfalen",
    "wof:name":"Elke Wolf Masseurin",
    "wof:placetype":"venue"
},
  "geometry": {"coordinates":[7.205136,51.177036],"type":"Point"}
}