{
  "type": "Feature",
  "properties": {
    "iso:country":"DE",
    "sg:address":"Am Wiesengrund 14",
    "sg:city":"M\u00fchl Rosin",
    "sg:phone":"+49 3843/843692",
    "sg:postcode":"18276",
    "sg:province":"Mecklenburg-Vorpommern",
    "wof:name":"G. Wolff",
    "wof:placetype":"venue"
},
  "geometry": {"coordinates":[12.2082834244,53.763053894],"type":"Point"}
}