{
  "type": "Feature",
  "properties": {
    "iso:country":"DE",
    "sg:address":"Maikstr. 14",
    "sg:city":"Hamburg",
    "sg:phone":"+49 40/7219964",
    "sg:postcode":"21031",
    "sg:province":"Hamburg",
    "wof:name":"Ritter & Peter",
    "wof:placetype":"venue"
},
  "geometry": {"coordinates":[10.204992,53.498489],"type":"Point"}
}