{
  "type": "Feature",
  "properties": {
    "iso:country":"DE",
    "sg:address":"Friedrich-Naumann-Str. 15",
    "sg:city":"Weimar",
    "sg:phone":"+49 3643/516811",
    "sg:postcode":"99423",
    "sg:province":"Th\u00fcringen",
    "wof:name":"Badelt",
    "wof:placetype":"venue"
},
  "geometry": {"coordinates":[11.322431,50.985687],"type":"Point"}
}