{
  "type": "Feature",
  "properties": {
    "iso:country":"DE",
    "sg:address":"Schartauer Str. 55/56",
    "sg:city":"Burg",
    "sg:postcode":"39288",
    "sg:province":"Sachsen-Anhalt",
    "wof:name":"Der Ossi-verlag",
    "wof:placetype":"venue"
},
  "geometry": {"coordinates":[11.8537731171,52.2707633972],"type":"Point"}
}