{
  "type": "Feature",
  "properties": {
    "iso:country":"DE",
    "sg:address":"Schleifweg 46",
    "sg:city":"Heidelberg",
    "sg:phone":"+49 6221/303820",
    "sg:postcode":"69126",
    "sg:province":"Baden-W\u00fcrttemberg",
    "wof:name":"Dr. Albrecht Braun Tierarzt",
    "wof:placetype":"venue"
},
  "geometry": {"coordinates":[8.6903562546,49.3721084595],"type":"Point"}
}