{
  "type": "Feature",
  "properties": {
    "iso:country":"DE",
    "sg:address":"Vogelruth 9",
    "sg:city":"Bielefeld",
    "sg:phone":"+49 521/443996",
    "sg:postcode":"33647",
    "sg:province":"Nordrhein-Westfalen",
    "wof:name":"Adelheid Ricke-mester",
    "wof:placetype":"venue"
},
  "geometry": {"coordinates":[8.5114297867,51.9881057739],"type":"Point"}
}