{
  "type": "Feature",
  "properties": {
    "iso:country":"DE",
    "sg:address":"Louisenstr. 13",
    "sg:city":"Bad Homburg",
    "sg:phone":"+49 6172/21619",
    "sg:postcode":"61348",
    "sg:province":"Hessen",
    "wof:name":"Marianne Kaspar-hill",
    "wof:placetype":"venue"
},
  "geometry": {"coordinates":[8.6131086349,50.2282867432],"type":"Point"}
}