{
  "type": "Feature",
  "properties": {
    "iso:country":"DE",
    "sg:address":"Ulrichstr. 35",
    "sg:city":"Abensberg",
    "sg:phone":"+49 9443/6381",
    "sg:postcode":"93326",
    "sg:province":"Bayern",
    "wof:name":"R. Ro\u00dfbauer",
    "wof:placetype":"venue"
},
  "geometry": {"coordinates":[11.8474206924,48.8158683777],"type":"Point"}
}