{
  "type": "Feature",
  "properties": {
    "iso:country":"DE",
    "sg:address":"Tonhallenstr. 4",
    "sg:city":"Duisburg",
    "sg:phone":"+49 203/287430",
    "sg:postcode":"47051",
    "sg:province":"Nordrhein-Westfalen",
    "wof:name":"Willi Winkelmann Rechtsanwalt",
    "wof:placetype":"venue"
},
  "geometry": {"coordinates":[6.7694759369,51.4317245483],"type":"Point"}
}