{
  "type": "Feature",
  "properties": {
    "iso:country":"DE",
    "sg:address":"Goethestr. 1",
    "sg:city":"Marl",
    "sg:phone":"+49 2365/67629",
    "sg:postcode":"45768",
    "sg:province":"Nordrhein-Westfalen",
    "wof:name":"A. Musetti",
    "wof:placetype":"venue"
},
  "geometry": {"coordinates":[7.082487,51.654762],"type":"Point"}
}