{
  "type": "Feature",
  "properties": {
    "iso:country":"DE",
    "sg:address":"Friedrichstr. 8",
    "sg:city":"Bamberg",
    "sg:phone":"+49 951/202100",
    "sg:postcode":"96047",
    "sg:province":"Bayern",
    "wof:name":"Pixxelplace Digitale Bild- Verarbeitung E. K.",
    "wof:placetype":"venue"
},
  "geometry": {"coordinates":[10.895382,49.891335],"type":"Point"}
}