{
  "type": "Feature",
  "properties": {
    "iso:country":"DE",
    "sg:address":"Bahnhofstr. 4",
    "sg:city":"Westoverledingen",
    "sg:phone":"+49 4955/9230",
    "sg:postcode":"26810",
    "sg:province":"Niedersachsen",
    "wof:name":"Korte Verwaltungs Gmbh",
    "wof:placetype":"venue"
},
  "geometry": {"coordinates":[7.449535,53.16571],"type":"Point"}
}