{
  "type": "Feature",
  "properties": {
    "iso:country":"DE",
    "sg:address":"Am Kamp 2 a",
    "sg:city":"Bremerv\u00f6rde",
    "sg:phone":"+49 4761/2007",
    "sg:postcode":"27432",
    "sg:province":"Niedersachsen",
    "wof:name":"Eismann Gastronomie Service Gmbh",
    "wof:placetype":"venue"
},
  "geometry": {"coordinates":[9.138397,53.481091],"type":"Point"}
}