{
  "type": "Feature",
  "properties": {
    "iso:country":"DE",
    "sg:address":"Ringstr. 5",
    "sg:city":"Heidenheim",
    "sg:phone":"+49 9833/472",
    "sg:postcode":"91719",
    "sg:province":"Bayern",
    "wof:name":"H. Und Anneliese Sch\u00e4fer",
    "wof:placetype":"venue"
},
  "geometry": {"coordinates":[10.7420663834,49.0179862976],"type":"Point"}
}