{
  "type": "Feature",
  "properties": {
    "iso:country":"DE",
    "sg:address":"Hauptstr. 88",
    "sg:city":"Stein",
    "sg:phone":"+49 911/6886660",
    "sg:postcode":"90547",
    "sg:province":"Bayern",
    "wof:name":"Schnell Und Kollegen Rechtsanw\u00e4lte",
    "wof:placetype":"venue"
},
  "geometry": {"coordinates":[11.0079612732,49.4119491577],"type":"Point"}
}