{
  "type": "Feature",
  "properties": {
    "iso:country":"DE",
    "sg:address":"Neuer Wall 72",
    "sg:city":"Hamburg",
    "sg:phone":"+49 40/360040",
    "sg:postcode":"20354",
    "sg:province":"Hamburg",
    "wof:name":"Vasa Kraftwerke Gmbh & Co. Neubrandenburg Kg",
    "wof:placetype":"venue"
},
  "geometry": {"coordinates":[9.987455,53.550495],"type":"Point"}
}