{
  "type": "Feature",
  "properties": {
    "iso:country":"DE",
    "sg:address":"Kaiserin-Augusta-Allee 108",
    "sg:city":"Berlin",
    "sg:postcode":"10553",
    "sg:province":"Berlin",
    "wof:name":"Tondachziegel-werk Friedland Gmbh",
    "wof:placetype":"venue"
},
  "geometry": {"coordinates":[13.3217773438,52.5256118774],"type":"Point"}
}