{
  "type": "Feature",
  "properties": {
    "iso:country":"DE",
    "sg:address":"Am Waldring 27",
    "sg:city":"Rechtmehring",
    "sg:phone":"+49 8076/1382",
    "sg:postcode":"83562",
    "sg:province":"Bayern",
    "wof:name":"K\u00f6ck Gmbh",
    "wof:placetype":"venue"
},
  "geometry": {"coordinates":[12.151399,48.125244],"type":"Point"}
}