{
  "type": "Feature",
  "properties": {
    "iso:country":"DE",
    "sg:address":"Bahnhofstr. 83",
    "sg:city":"Domb\u00fchl",
    "sg:phone":"+49 4933/7082320",
    "sg:postcode":"91601",
    "sg:province":"Bayern",
    "wof:name":"Askem Anlagen-u.stahlbau Gmbh",
    "wof:placetype":"venue"
},
  "geometry": {"coordinates":[13.44803,52.215515],"type":"Point"}
}