{
  "type": "Feature",
  "properties": {
    "iso:country":"DE",
    "sg:address":"Lanstroper Str. 46",
    "sg:city":"L\u00fcnen",
    "sg:phone":"+49 2306/44889",
    "sg:postcode":"44532",
    "sg:province":"Nordrhein-Westfalen",
    "wof:name":"Ilse Kieseheuer",
    "wof:placetype":"venue"
},
  "geometry": {"coordinates":[7.5529699326,51.5888290405],"type":"Point"}
}