{
  "type": "Feature",
  "properties": {
    "iso:country":"DE",
    "sg:address":"Am W\u00fcrmsee 26",
    "sg:city":"Burgwedel",
    "sg:phone":"+49 5139/7270",
    "sg:postcode":"30938",
    "sg:province":"Niedersachsen",
    "wof:name":"Heinz Maass",
    "wof:placetype":"venue"
},
  "geometry": {"coordinates":[9.848247,52.528576],"type":"Point"}
}