{
  "type": "Feature",
  "properties": {
    "iso:country":"DE",
    "sg:address":"Stuttgarter Str. 19",
    "sg:city":"Wendlingen",
    "sg:phone":"+49 7024/3399",
    "sg:postcode":"73240",
    "sg:province":"Baden-W\u00fcrttemberg",
    "wof:name":"Imbi\u00df Balkangrill Der Grieche",
    "wof:placetype":"venue"
},
  "geometry": {"coordinates":[9.3768606186,48.6732635498],"type":"Point"}
}