{
  "type": "Feature",
  "properties": {
    "iso:country":"DE",
    "sg:address":"Vietenheide 14",
    "sg:city":"M\u00f6nchengladbach",
    "sg:phone":"+49 2166/942050",
    "sg:postcode":"41239",
    "sg:province":"Nordrhein-Westfalen",
    "wof:name":"R & V Versicherungen Volker Gold",
    "wof:placetype":"venue"
},
  "geometry": {"coordinates":[6.4350361824,51.1717033386],"type":"Point"}
}