{
  "type": "Feature",
  "properties": {
    "iso:country":"DE",
    "sg:address":"Eltviller Landstr. 2",
    "sg:city":"Eltville",
    "sg:phone":"+49 6123/63395",
    "sg:postcode":"65346",
    "sg:province":"Hessen",
    "wof:name":"Haus Wilhelmine",
    "wof:placetype":"venue"
},
  "geometry": {"coordinates":[8.102551,50.02322],"type":"Point"}
}