{
  "type": "Feature",
  "properties": {
    "iso:country":"DE",
    "sg:address":"Fasanenstr. 49",
    "sg:city":"Vaterstetten",
    "sg:phone":"+49 8106/304755",
    "sg:postcode":"85591",
    "sg:province":"Bayern",
    "wof:name":"G\u00fcnther Erb Rechtsanwalt",
    "wof:placetype":"venue"
},
  "geometry": {"coordinates":[11.7660427094,48.1084518433],"type":"Point"}
}