{
  "type": "Feature",
  "properties": {
    "iso:country":"DE",
    "sg:address":"Alte Heerstr. 52",
    "sg:city":"L\u00f6ningen",
    "sg:phone":"+49 5432/2703",
    "sg:postcode":"49624",
    "sg:province":"Niedersachsen",
    "wof:name":"M. Heimbrock",
    "wof:placetype":"venue"
},
  "geometry": {"coordinates":[7.790135,52.774406],"type":"Point"}
}