{
  "type": "Feature",
  "properties": {
    "iso:country":"DE",
    "sg:address":"Leithenstr. 13",
    "sg:city":"Marloffstein",
    "sg:phone":"+49 9131/52150",
    "sg:postcode":"91080",
    "sg:province":"Bayern",
    "wof:name":"Dr. Peter Pierer Von Esch",
    "wof:placetype":"venue"
},
  "geometry": {"coordinates":[11.0588750839,49.6202278137],"type":"Point"}
}