{
  "type": "Feature",
  "properties": {
    "iso:country":"DE",
    "sg:address":"Simsseestr. 12",
    "sg:city":"Rohrdorf",
    "sg:phone":"+49 8034/1558",
    "sg:postcode":"83101",
    "sg:province":"Bayern",
    "wof:name":"Mitter Gmbh",
    "wof:placetype":"venue"
},
  "geometry": {"coordinates":[12.1975002289,47.8155822754],"type":"Point"}
}