{
  "type": "Feature",
  "properties": {
    "iso:country":"DE",
    "sg:address":"An der Lauter",
    "sg:city":"Laubach",
    "sg:postcode":"35321",
    "sg:province":"Hessen",
    "wof:name":"Mehrzweckhalle Lauter",
    "wof:placetype":"venue"
},
  "geometry": {"coordinates":[8.970517,50.569],"type":"Point"}
}