{
  "type": "Feature",
  "properties": {
    "iso:country":"DE",
    "sg:address":"Essener Str. 255",
    "sg:city":"Bottrop",
    "sg:phone":"+49 2041/66088",
    "sg:postcode":"46242",
    "sg:province":"Nordrhein-Westfalen",
    "wof:name":"M. Riedel",
    "wof:placetype":"venue"
},
  "geometry": {"coordinates":[6.935511,51.49963],"type":"Point"}
}