{
  "type": "Feature",
  "properties": {
    "iso:country":"DE",
    "sg:address":"Bahnhofstr. 14",
    "sg:city":"Arolsen",
    "sg:phone":"+49 4956/912091",
    "sg:postcode":"34454",
    "sg:province":"Hessen",
    "wof:name":"Waldecker Bank Eg",
    "wof:placetype":"venue"
},
  "geometry": {"coordinates":[9.013421,51.380688],"type":"Point"}
}