{
  "type": "Feature",
  "properties": {
    "iso:country":"DE",
    "sg:address":"Bollweg 19",
    "sg:city":"Buxtehude",
    "sg:phone":"+49 4161/61378",
    "sg:postcode":"21614",
    "sg:province":"Niedersachsen",
    "wof:name":"Metz Hoch- Und Tiefbau Gmbh",
    "wof:placetype":"venue"
},
  "geometry": {"coordinates":[9.71152,53.477882],"type":"Point"}
}