{
  "type": "Feature",
  "properties": {
    "iso:country":"DE",
    "sg:address":"Schulstr. 27",
    "sg:city":"Wolfschlugen",
    "sg:phone":"+49 7022/59407",
    "sg:postcode":"72649",
    "sg:province":"Baden-W\u00fcrttemberg",
    "wof:name":"Siegfried Schumann Steuerberater",
    "wof:placetype":"venue"
},
  "geometry": {"coordinates":[9.292096138,48.6494293213],"type":"Point"}
}