{
  "type": "Feature",
  "properties": {
    "iso:country":"DE",
    "sg:address":"Eiserfelder Str. 294",
    "sg:city":"Siegen",
    "sg:phone":"+49 271/359480",
    "sg:postcode":"57080",
    "sg:province":"Nordrhein-Westfalen",
    "wof:name":"H. Bottenberg Gmbh",
    "wof:placetype":"venue"
},
  "geometry": {"coordinates":[7.9870948792,50.8459892273],"type":"Point"}
}