{
  "type": "Feature",
  "properties": {
    "iso:country":"DE",
    "sg:address":"Kister Str. 10",
    "sg:city":"H\u00f6chberg",
    "sg:phone":"+49 931/48620",
    "sg:postcode":"97204",
    "sg:province":"Bayern",
    "wof:name":"Martin Ruppert",
    "wof:placetype":"venue"
},
  "geometry": {"coordinates":[9.874985,49.778446],"type":"Point"}
}