{
  "type": "Feature",
  "properties": {
    "iso:country":"DE",
    "sg:address":"Hein-Hoyer-Str. 40",
    "sg:city":"Hamburg",
    "sg:phone":"+49 40/3192537",
    "sg:postcode":"20359",
    "sg:province":"Hamburg",
    "wof:name":"Taverna Sokratis",
    "wof:placetype":"venue"
},
  "geometry": {"coordinates":[9.9627895355,53.5518035889],"type":"Point"}
}