{
  "type": "Feature",
  "properties": {
    "iso:country":"DE",
    "sg:address":"Ismertstr 1a",
    "sg:city":"P\u00fcttlingen",
    "sg:phone":"+49 6898/63920",
    "sg:postcode":"66346",
    "sg:province":"Saarland",
    "wof:name":"Del Fabro Informatik Gmbh",
    "wof:placetype":"venue"
},
  "geometry": {"coordinates":[6.885235,49.288029],"type":"Point"}
}