{
  "type": "Feature",
  "properties": {
    "iso:country":"DE",
    "sg:address":"Feldhusstr. 18",
    "sg:city":"Delmenhorst",
    "sg:phone":"+49 4221/982210",
    "sg:postcode":"27753",
    "sg:province":"Niedersachsen",
    "wof:name":"Geb\u00c4udereinigung & K\u00dcster Gmbh",
    "wof:placetype":"venue"
},
  "geometry": {"coordinates":[8.64984,53.017197],"type":"Point"}
}