{
  "type": "Feature",
  "properties": {
    "iso:country":"DE",
    "sg:address":"Kastanienstr. 8",
    "sg:city":"Winnenden",
    "sg:phone":"+49 7195/8424",
    "sg:postcode":"71364",
    "sg:province":"Baden-W\u00fcrttemberg",
    "wof:name":"M. St\u00f6ssinger",
    "wof:placetype":"venue"
},
  "geometry": {"coordinates":[9.3861379623,48.8640403748],"type":"Point"}
}