{
  "type": "Feature",
  "properties": {
    "iso:country":"DE",
    "sg:address":"Schlichterstr. 6",
    "sg:city":"Wiesbaden",
    "sg:phone":"+49 611/374708",
    "sg:postcode":"65185",
    "sg:province":"Hessen",
    "wof:name":"Friedrich Zehm Komponist",
    "wof:placetype":"venue"
},
  "geometry": {"coordinates":[8.2425308228,50.0737457275],"type":"Point"}
}