{
  "type": "Feature",
  "properties": {
    "iso:country":"DE",
    "sg:address":"Dreifertstr. 10",
    "sg:city":"Cottbus",
    "sg:phone":"+49 355/381350",
    "sg:postcode":"03044",
    "sg:province":"Brandenburg",
    "wof:name":"Ulrich Klein Notar",
    "wof:placetype":"venue"
},
  "geometry": {"coordinates":[14.3334245682,51.7646331787],"type":"Point"}
}