{
  "type": "Feature",
  "properties": {
    "iso:country":"DE",
    "sg:address":"Breite Str. 26",
    "sg:city":"Allstedt",
    "sg:phone":"+49 34652/712",
    "sg:postcode":"06542",
    "sg:province":"Sachsen-Anhalt",
    "wof:name":"Agria-rein",
    "wof:placetype":"venue"
},
  "geometry": {"coordinates":[11.384727,51.404999],"type":"Point"}
}