{
  "type": "Feature",
  "properties": {
    "iso:country":"DE",
    "sg:address":"Westerhaar 3",
    "sg:city":"Wickede",
    "sg:phone":"+49 2377/3600",
    "sg:postcode":"58739",
    "sg:province":"Nordrhein-Westfalen",
    "wof:name":"H. Hoberg",
    "wof:placetype":"venue"
},
  "geometry": {"coordinates":[7.872596,51.507622],"type":"Point"}
}