{
  "type": "Feature",
  "properties": {
    "iso:country":"DE",
    "sg:address":"Bremer Str. 25",
    "sg:city":"Stuhr",
    "sg:phone":"+49 421/894614",
    "sg:postcode":"28816",
    "sg:province":"Niedersachsen",
    "wof:name":"Biohof Michael Bode-kirchhoff Und Gebke",
    "wof:placetype":"venue"
},
  "geometry": {"coordinates":[8.788944,53.014439],"type":"Point"}
}