{
  "type": "Feature",
  "properties": {
    "iso:country":"DE",
    "sg:address":"Jossastr. 17",
    "sg:city":"Bad Soden-Salm\u00fcnster",
    "sg:phone":"+49 6660/375",
    "sg:postcode":"63628",
    "sg:province":"Hessen",
    "wof:name":"Ludwig Harnischfeger",
    "wof:placetype":"venue"
},
  "geometry": {"coordinates":[9.47704,50.241138],"type":"Point"}
}