{
  "type": "Feature",
  "properties": {
    "iso:country":"DE",
    "sg:address":"Reutweg 4",
    "sg:city":"Pfinztal",
    "sg:phone":"+49 7240/8034",
    "sg:postcode":"76327",
    "sg:province":"Baden-W\u00fcrttemberg",
    "wof:name":"W. Krauss K\u00fcferei",
    "wof:placetype":"venue"
},
  "geometry": {"coordinates":[8.55326,48.965282],"type":"Point"}
}