{
  "type": "Feature",
  "properties": {
    "iso:country":"DE",
    "sg:address":"Ferdinand-Lassalle-Str. 26",
    "sg:city":"Reutlingen",
    "sg:phone":"+49 7121/52250",
    "sg:postcode":"72770",
    "sg:province":"Baden-W\u00fcrttemberg",
    "wof:name":"W\u00f6rner & Hirsch Motorrad-service",
    "wof:placetype":"venue"
},
  "geometry": {"coordinates":[9.156882,48.491283],"type":"Point"}
}