{
  "type": "Feature",
  "properties": {
    "iso:country":"DE",
    "sg:address":"Langestr. 50",
    "sg:city":"Benningen",
    "sg:phone":"+49 7144/14333",
    "sg:postcode":"71726",
    "sg:province":"Baden-W\u00fcrttemberg",
    "wof:name":"Gastst\u00e4tte Gemeindehalle Inh. Eberhard Lenz",
    "wof:placetype":"venue"
},
  "geometry": {"coordinates":[9.2347278595,48.9445381165],"type":"Point"}
}