{
  "type": "Feature",
  "properties": {
    "iso:country":"DE",
    "sg:address":"In der Kleinen Au 3",
    "sg:city":"Germersheim",
    "sg:phone":"+49 7274/778234",
    "sg:postcode":"76726",
    "sg:province":"Rheinland-Pfalz",
    "wof:name":"Mas F\u00f6rder-hebetechnik Gmbh",
    "wof:placetype":"venue"
},
  "geometry": {"coordinates":[8.3751239777,49.2213592529],"type":"Point"}
}