{
  "type": "Feature",
  "properties": {
    "iso:country":"DE",
    "sg:address":"B\u00fchlstr. 4",
    "sg:city":"Bahlingen",
    "sg:phone":"+49 7663/747",
    "sg:postcode":"79353",
    "sg:province":"Baden-W\u00fcrttemberg",
    "wof:name":"Wolfgang Hi\u00df",
    "wof:placetype":"venue"
},
  "geometry": {"coordinates":[7.738833,48.12138],"type":"Point"}
}