{
  "type": "Feature",
  "properties": {
    "iso:country":"DE",
    "sg:address":"Am Eichenrain 34",
    "sg:city":"Schw\u00e4bisch Gm\u00fcnd",
    "sg:phone":"+49 7171/76062",
    "sg:postcode":"73527",
    "sg:province":"Baden-W\u00fcrttemberg",
    "wof:name":"Heinz Schmid Architekt",
    "wof:placetype":"venue"
},
  "geometry": {"coordinates":[9.823897,48.829319],"type":"Point"}
}