{
  "type": "Feature",
  "properties": {
    "iso:country":"DE",
    "sg:address":"Aegdidiusplatz 6",
    "sg:city":"Bad Honnef",
    "sg:phone":"+49 2224/973131",
    "sg:postcode":"53604",
    "sg:province":"Nordrhein-Westfalen",
    "wof:name":"Spar- & Darlehnskasse Aegidienberg",
    "wof:placetype":"venue"
},
  "geometry": {"coordinates":[7.302995,50.662487],"type":"Point"}
}