{
  "type": "Feature",
  "properties": {
    "iso:country":"DE",
    "sg:address":"Am Forstanger 29",
    "sg:city":"Oberhaching",
    "sg:phone":"+49 89/6133769",
    "sg:postcode":"82041",
    "sg:province":"Bayern",
    "wof:name":"Thomas Wille Rechtsanwalt",
    "wof:placetype":"venue"
},
  "geometry": {"coordinates":[11.5778150558,48.0246696472],"type":"Point"}
}