{
  "type": "Feature",
  "properties": {
    "iso:country":"DE",
    "sg:address":"Ellmendinger Str. 16",
    "sg:city":"Birkenfeld",
    "sg:phone":"+49 7082/93900",
    "sg:postcode":"75217",
    "sg:province":"Baden-W\u00fcrttemberg",
    "wof:name":"Alfred Stepper Finanzberater",
    "wof:placetype":"venue"
},
  "geometry": {"coordinates":[8.582821846,48.8739814758],"type":"Point"}
}