{
  "type": "Feature",
  "properties": {
    "iso:country":"DE",
    "sg:address":"Schulstr. 5",
    "sg:city":"Arnsberg",
    "sg:phone":"+49 2932/24081",
    "sg:postcode":"59755",
    "sg:province":"Nordrhein-Westfalen",
    "wof:name":"U. -o. Augustini Immobilienmakler",
    "wof:placetype":"venue"
},
  "geometry": {"coordinates":[7.9685702324,51.4504966736],"type":"Point"}
}