{
  "type": "Feature",
  "properties": {
    "iso:country":"DE",
    "sg:address":"Zevener Str. 8",
    "sg:city":"Ahlerstedt",
    "sg:phone":"+49 4166/7205",
    "sg:postcode":"21702",
    "sg:province":"Niedersachsen",
    "wof:name":"M & K Systembau Gmbh",
    "wof:placetype":"venue"
},
  "geometry": {"coordinates":[9.449437,53.402451],"type":"Point"}
}