{
  "type": "Feature",
  "properties": {
    "iso:country":"DE",
    "sg:address":"Unterer Kapellberg 58",
    "sg:city":"Hallstadt",
    "sg:phone":"+49 951/75454",
    "sg:postcode":"96103",
    "sg:province":"Bayern",
    "wof:name":"Konrad Dinkel",
    "wof:placetype":"venue"
},
  "geometry": {"coordinates":[10.8602848053,49.9331016541],"type":"Point"}
}