{
  "type": "Feature",
  "properties": {
    "iso:country":"DE",
    "sg:address":"S\u00fcdstr. 2",
    "sg:city":"Meerbusch",
    "sg:phone":"+49 2159/3037",
    "sg:postcode":"40670",
    "sg:province":"Nordrhein-Westfalen",
    "wof:name":"Heinrich Wolf Masseur",
    "wof:placetype":"venue"
},
  "geometry": {"coordinates":[6.620926,51.264851],"type":"Point"}
}