{
  "type": "Feature",
  "properties": {
    "iso:country":"DE",
    "sg:address":"Bahnhofsplatz 8",
    "sg:city":"Trier",
    "sg:phone":"+49 651/12012",
    "sg:postcode":"54292",
    "sg:province":"Rheinland-Pfalz",
    "wof:name":"Taxi-funk-zentrale Tfz Eg",
    "wof:placetype":"venue"
},
  "geometry": {"coordinates":[6.6513252258,49.7574386597],"type":"Point"}
}