{
  "type": "Feature",
  "properties": {
    "iso:country":"DE",
    "sg:address":"Karl-Zink-Str. 6",
    "sg:city":"Ilmenau",
    "sg:phone":"+49 3677/841019",
    "sg:postcode":"98693",
    "sg:province":"Th\u00fcringen",
    "wof:name":"Elektro-f\u00fcchse Gmbh",
    "wof:placetype":"venue"
},
  "geometry": {"coordinates":[10.9133939743,50.6855545044],"type":"Point"}
}