{
  "type": "Feature",
  "properties": {
    "iso:country":"DE",
    "sg:address":"Kirchenweg 22",
    "sg:city":"N\u00fcrnberg",
    "sg:phone":"+49 911/374287",
    "sg:postcode":"90419",
    "sg:province":"Bayern",
    "wof:name":"China-restaurant Loon-fung",
    "wof:placetype":"venue"
},
  "geometry": {"coordinates":[11.0665121078,49.4620170593],"type":"Point"}
}