{
  "type": "Feature",
  "properties": {
    "iso:country":"DE",
    "sg:address":"J\u00e4gersweg 1",
    "sg:city":"Leidersbach",
    "sg:phone":"+49 6092/494",
    "sg:postcode":"63849",
    "sg:province":"Bayern",
    "wof:name":"Alfons Brand",
    "wof:placetype":"venue"
},
  "geometry": {"coordinates":[9.2682619095,49.897190094],"type":"Point"}
}