{
  "type": "Feature",
  "properties": {
    "iso:country":"DE",
    "sg:address":"Hohlstr. 26",
    "sg:city":"Olsbr\u00fccken",
    "sg:phone":"+49 6308/7794",
    "sg:postcode":"67737",
    "sg:province":"Rheinland-Pfalz",
    "wof:name":"B. Und P. Wendel",
    "wof:placetype":"venue"
},
  "geometry": {"coordinates":[7.6625528336,49.5365867615],"type":"Point"}
}