{
  "type": "Feature",
  "properties": {
    "iso:country":"DE",
    "sg:address":"Stadionweg 3",
    "sg:city":"Aalen",
    "sg:phone":"+49 7361/460100",
    "sg:postcode":"73430",
    "sg:province":"Baden-W\u00fcrttemberg",
    "wof:name":"Vereinsgastst\u00e4tte Verein F\u00fcr Rasenspiele E. V.",
    "wof:placetype":"venue"
},
  "geometry": {"coordinates":[10.0732793808,48.8398475647],"type":"Point"}
}