{
  "type": "Feature",
  "properties": {
    "iso:country":"DE",
    "sg:address":"Grandweg 8",
    "sg:city":"Ludwigslust",
    "sg:phone":"+49 3874/20694",
    "sg:postcode":"19288",
    "sg:province":"Mecklenburg-Vorpommern",
    "wof:name":"Mbd Metall, Bau Und Dienstleistungs Gmbh",
    "wof:placetype":"venue"
},
  "geometry": {"coordinates":[11.49965,53.333149],"type":"Point"}
}