{
  "type": "Feature",
  "properties": {
    "iso:country":"DE",
    "sg:address":"Rheingutstr. 25",
    "sg:city":"Konstanz",
    "sg:phone":"+49 7531/25293",
    "sg:postcode":"78462",
    "sg:province":"Baden-W\u00fcrttemberg",
    "wof:name":"Friedemann Reh Heilpraktiker",
    "wof:placetype":"venue"
},
  "geometry": {"coordinates":[9.1679401398,47.6669540405],"type":"Point"}
}