{
  "type": "Feature",
  "properties": {
    "iso:country":"DE",
    "sg:address":"Friedensstr. 47",
    "sg:city":"Reichenbach",
    "sg:phone":"+49 3765/12287",
    "sg:postcode":"08468",
    "sg:province":"Sachsen",
    "wof:name":"F. Goy",
    "wof:placetype":"venue"
},
  "geometry": {"coordinates":[12.659074,50.836285],"type":"Point"}
}