{
  "type": "Feature",
  "properties": {
    "iso:country":"DE",
    "sg:address":"Kaltenbach 5",
    "sg:city":"Traunstein",
    "sg:phone":"+49 861/4568",
    "sg:postcode":"83278",
    "sg:province":"Bayern",
    "wof:name":"Winkler Kg",
    "wof:placetype":"venue"
},
  "geometry": {"coordinates":[12.626924,47.916878],"type":"Point"}
}