{
  "type": "Feature",
  "properties": {
    "iso:country":"DE",
    "sg:address":"Frohmestr. 16",
    "sg:city":"Hamburg",
    "sg:phone":"+49 40/5503031",
    "sg:postcode":"22457",
    "sg:province":"Hamburg",
    "wof:name":"Stehrs Brillenstudio E. K.",
    "wof:placetype":"venue"
},
  "geometry": {"coordinates":[9.9189891815,53.6344909668],"type":"Point"}
}