{
  "type": "Feature",
  "properties": {
    "iso:country":"DE",
    "sg:address":"Scharmbecker Dorfstr. 48",
    "sg:city":"Winsen",
    "sg:phone":"+49 4171/5183",
    "sg:postcode":"21423",
    "sg:province":"Niedersachsen",
    "wof:name":"Hermann Sander",
    "wof:placetype":"venue"
},
  "geometry": {"coordinates":[10.1481742859,53.3441162109],"type":"Point"}
}