{
  "type": "Feature",
  "properties": {
    "iso:country":"DE",
    "sg:address":"Kitzinger Str. 33",
    "sg:city":"Schwarzach",
    "sg:phone":"+49 9324/99550",
    "sg:postcode":"97359",
    "sg:province":"Bayern",
    "wof:name":"Uta Knobloch U. Karsten Herchenhan Gbr",
    "wof:placetype":"venue"
},
  "geometry": {"coordinates":[10.218884,49.791439],"type":"Point"}
}