{
  "type": "Feature",
  "properties": {
    "iso:country":"DE",
    "sg:address":"Vorjurastr. 54a",
    "sg:city":"N\u00fcrnberg",
    "sg:phone":"+49 911/635748",
    "sg:postcode":"90453",
    "sg:province":"Bayern",
    "wof:name":"Hans Braun",
    "wof:placetype":"venue"
},
  "geometry": {"coordinates":[11.039316,49.37751],"type":"Point"}
}