{
  "type": "Feature",
  "properties": {
    "iso:country":"DE",
    "sg:address":"Gilsingstr. 14",
    "sg:city":"Bochum",
    "sg:phone":"+49 234/791106",
    "sg:postcode":"44789",
    "sg:province":"Nordrhein-Westfalen",
    "wof:name":"Apotheke Der Berufsgen. Krankenanstalten Bergmannsheil",
    "wof:placetype":"venue"
},
  "geometry": {"coordinates":[7.21222,51.469994],"type":"Point"}
}