{
  "type": "Feature",
  "properties": {
    "iso:country":"DE",
    "sg:address":"Am Hafen 57",
    "sg:city":"Varel",
    "sg:phone":"+49 4451/3114",
    "sg:postcode":"26316",
    "sg:province":"Niedersachsen",
    "wof:name":"H. Wilters",
    "wof:placetype":"venue"
},
  "geometry": {"coordinates":[8.176525116,53.4077033997],"type":"Point"}
}