{
  "type": "Feature",
  "properties": {
    "iso:country":"DE",
    "sg:address":"Frankfurter Str. 35",
    "sg:city":"Heusenstamm",
    "sg:phone":"+49 6104/67482",
    "sg:postcode":"63150",
    "sg:province":"Hessen",
    "wof:name":"M. Berg",
    "wof:placetype":"venue"
},
  "geometry": {"coordinates":[8.80552,50.059326],"type":"Point"}
}