{
  "type": "Feature",
  "properties": {
    "iso:country":"DE",
    "sg:address":"Breitlenstr.",
    "sg:city":"Dollnstein",
    "sg:phone":"+49 8422/874",
    "sg:postcode":"91795",
    "sg:province":"Bayern",
    "wof:name":"Freibad",
    "wof:placetype":"venue"
},
  "geometry": {"coordinates":[11.1029748917,48.8756942749],"type":"Point"}
}