{
  "type": "Feature",
  "properties": {
    "iso:country":"DE",
    "sg:address":"Ingolst\u00e4dter Str. 26",
    "sg:city":"Manching",
    "sg:phone":"+49 8459/2704",
    "sg:postcode":"85077",
    "sg:province":"Bayern",
    "wof:name":"Minimal",
    "wof:placetype":"venue"
},
  "geometry": {"coordinates":[11.4899663925,48.7171974182],"type":"Point"}
}