{
  "type": "Feature",
  "properties": {
    "iso:country":"DE",
    "sg:address":"Gro\u00dfe Hinterlohne 3",
    "sg:city":"Norden",
    "sg:phone":"+49 4931/6033",
    "sg:postcode":"26506",
    "sg:province":"Niedersachsen",
    "wof:name":"Taxi Und Mietwagenzentrale Norden E. K.",
    "wof:placetype":"venue"
},
  "geometry": {"coordinates":[7.2107439041,53.5959434509],"type":"Point"}
}