{
  "type": "Feature",
  "properties": {
    "iso:country":"DE",
    "sg:address":"Am Boeselagerhof 5",
    "sg:city":"Bonn",
    "sg:phone":"+49 228/654689",
    "sg:postcode":"53111",
    "sg:province":"Nordrhein-Westfalen",
    "wof:name":"Dieter Schr\u00f6der Architekt",
    "wof:placetype":"venue"
},
  "geometry": {"coordinates":[7.105806,50.736256],"type":"Point"}
}