{
  "type": "Feature",
  "properties": {
    "iso:country":"DE",
    "sg:address":"Fuhrenk\u00e4mpe 16",
    "sg:city":"Suderburg",
    "sg:phone":"+49 5826/327",
    "sg:postcode":"29556",
    "sg:province":"Niedersachsen",
    "wof:name":"Werner Stachorra",
    "wof:placetype":"venue"
},
  "geometry": {"coordinates":[10.44382,52.884571],"type":"Point"}
}