{
  "type": "Feature",
  "properties": {
    "iso:country":"DE",
    "sg:address":"Im Lindhof 2",
    "sg:city":"Syke",
    "sg:postcode":"28857",
    "sg:province":"Niedersachsen",
    "wof:name":"Syker-tennis-center Beteiligungs Gmbh",
    "wof:placetype":"venue"
},
  "geometry": {"coordinates":[8.820678,52.899506],"type":"Point"}
}