{
  "type": "Feature",
  "properties": {
    "iso:country":"DE",
    "sg:address":"Salmstr. 12",
    "sg:city":"Kl\u00fcsserath",
    "sg:phone":"+49 6507/4658",
    "sg:postcode":"54340",
    "sg:province":"Rheinland-Pfalz",
    "wof:name":"A. Briesch Weinanbau",
    "wof:placetype":"venue"
},
  "geometry": {"coordinates":[6.8448190689,49.8418273926],"type":"Point"}
}