{
  "type": "Feature",
  "properties": {
    "iso:country":"DE",
    "sg:address":"Am Eichkamp 5",
    "sg:city":"Haste",
    "sg:phone":"+49 5723/8578",
    "sg:postcode":"31559",
    "sg:province":"Niedersachsen",
    "wof:name":"E. Bruns",
    "wof:placetype":"venue"
},
  "geometry": {"coordinates":[9.399043,52.384365],"type":"Point"}
}