{
  "type": "Feature",
  "properties": {
    "iso:country":"DE",
    "sg:address":"S\u00fcderende 3b",
    "sg:city":"Langballig",
    "sg:phone":"+49 4636/1507",
    "sg:postcode":"24977",
    "sg:province":"Schleswig-Holstein",
    "wof:name":"Amts-apotheke",
    "wof:placetype":"venue"
},
  "geometry": {"coordinates":[9.635723,54.798843],"type":"Point"}
}