{
  "type": "Feature",
  "properties": {
    "iso:country":"DE",
    "sg:address":"Redenstr. 9",
    "sg:city":"Hannover",
    "sg:phone":"+49 511/2831414",
    "sg:postcode":"30171",
    "sg:province":"Niedersachsen",
    "wof:name":"Rene Glembotzky",
    "wof:placetype":"venue"
},
  "geometry": {"coordinates":[9.7601337433,52.364112854],"type":"Point"}
}