{
  "type": "Feature",
  "properties": {
    "iso:country":"DE",
    "sg:address":"Havkamp 5",
    "sg:city":"Bad Segeberg",
    "sg:phone":"+49 4551/4994",
    "sg:postcode":"23795",
    "sg:province":"Schleswig-Holstein",
    "wof:name":"Architekturb\u00fcro Meier Und Moss E. Meier Und W. Moss",
    "wof:placetype":"venue"
},
  "geometry": {"coordinates":[10.330303,53.930984],"type":"Point"}
}