{
  "type": "Feature",
  "properties": {
    "iso:country":"DE",
    "sg:address":"Kustrenaer Str. 62",
    "sg:city":"Bernburg",
    "sg:phone":"+49 3471/312386",
    "sg:postcode":"06406",
    "sg:province":"Sachsen-Anhalt",
    "wof:name":"B Und S Gbr",
    "wof:placetype":"venue"
},
  "geometry": {"coordinates":[11.7355394363,51.7815971375],"type":"Point"}
}