{
  "type": "Feature",
  "properties": {
    "iso:country":"DE",
    "sg:address":"Sonnenstr. 81",
    "sg:city":"Albstadt",
    "sg:postcode":"72458",
    "sg:province":"Baden-W\u00fcrttemberg",
    "wof:name":"Beck & Norz H\u00f6rger\u00e4teakustik Gmbh",
    "wof:placetype":"venue"
},
  "geometry": {"coordinates":[9.016722,48.212559],"type":"Point"}
}