{
  "type": "Feature",
  "properties": {
    "iso:country":"DE",
    "sg:address":"Lessingstr. 17",
    "sg:city":"Limburgerhof",
    "sg:phone":"+49 6236/61022",
    "sg:postcode":"67117",
    "sg:province":"Rheinland-Pfalz",
    "wof:name":"Scheele & Mark",
    "wof:placetype":"venue"
},
  "geometry": {"coordinates":[8.3847484589,49.4240913391],"type":"Point"}
}