{
  "type": "Feature",
  "properties": {
    "iso:country":"DE",
    "sg:address":"Stiftstr. 14",
    "sg:city":"Frankfurt",
    "sg:phone":"+49 69/237680",
    "sg:postcode":"60313",
    "sg:province":"Hessen",
    "wof:name":"Foki Handels Gmbh",
    "wof:placetype":"venue"
},
  "geometry": {"coordinates":[8.6826763153,50.1156654358],"type":"Point"}
}