{
  "type": "Feature",
  "properties": {
    "iso:country":"DE",
    "sg:address":"Lessingstr. 9",
    "sg:city":"M\u00fchlheim",
    "sg:phone":"+49 6108/798292",
    "sg:postcode":"63165",
    "sg:province":"Hessen",
    "wof:name":"Transportservice Halm E. K.",
    "wof:placetype":"venue"
},
  "geometry": {"coordinates":[8.8372049332,50.120513916],"type":"Point"}
}