{
  "type": "Feature",
  "properties": {
    "iso:country":"DE",
    "sg:address":"Hauptstr. 42",
    "sg:city":"Ebersbach",
    "sg:phone":"+49 7163/52421",
    "sg:postcode":"73061",
    "sg:province":"Baden-W\u00fcrttemberg",
    "wof:name":"Scherr Gmbh",
    "wof:placetype":"venue"
},
  "geometry": {"coordinates":[13.1036300659,51.1007423401],"type":"Point"}
}