{
  "type": "Feature",
  "properties": {
    "iso:country":"DE",
    "sg:address":"Heinrich-Hertz-Str. 7",
    "sg:city":"Eberswalde",
    "sg:phone":"+49 3334/20680",
    "sg:postcode":"16225",
    "sg:province":"Brandenburg",
    "wof:name":"Agro Treppen Gmbh",
    "wof:placetype":"venue"
},
  "geometry": {"coordinates":[13.78814,52.858253],"type":"Point"}
}