{
  "type": "Feature",
  "properties": {
    "iso:country":"DE",
    "sg:address":"Herrenstr. 2",
    "sg:city":"Siegenburg",
    "sg:phone":"+49 9444/97085",
    "sg:postcode":"93354",
    "sg:province":"Bayern",
    "wof:name":"Karl Present",
    "wof:placetype":"venue"
},
  "geometry": {"coordinates":[11.8499536514,48.7551956177],"type":"Point"}
}