{
  "type": "Feature",
  "properties": {
    "iso:country":"DE",
    "sg:address":"Alte Landstr. 5",
    "sg:city":"Bad Salzuflen",
    "sg:phone":"+49 5222/22204",
    "sg:postcode":"32108",
    "sg:province":"Nordrhein-Westfalen",
    "wof:name":"Abbeiz-zentrale Heyde Stickdorn Gmbh",
    "wof:placetype":"venue"
},
  "geometry": {"coordinates":[8.7944202423,52.0501594543],"type":"Point"}
}