{
  "type": "Feature",
  "properties": {
    "iso:country":"DE",
    "sg:address":"Bahnstr",
    "sg:city":"Langen",
    "sg:phone":"+49 4961/032040",
    "sg:postcode":"63225",
    "sg:province":"Hessen",
    "wof:name":"Langener Volksbank Eg",
    "wof:placetype":"venue"
},
  "geometry": {"coordinates":[8.673425,49.989677],"type":"Point"}
}