{
  "type": "Feature",
  "properties": {
    "iso:country":"DE",
    "sg:address":"Fischerstr. 17",
    "sg:city":"Wolfenb\u00fcttel",
    "sg:phone":"+49 5331/5408",
    "sg:postcode":"38300",
    "sg:province":"Niedersachsen",
    "wof:name":"Emil Sopka",
    "wof:placetype":"venue"
},
  "geometry": {"coordinates":[10.5393886566,52.16198349],"type":"Point"}
}