{
  "type": "Feature",
  "properties": {
    "iso:country":"DE",
    "sg:address":"Hochturmgasse 3",
    "sg:city":"Rottweil",
    "sg:phone":"+49 741/7206",
    "sg:postcode":"78628",
    "sg:province":"Baden-W\u00fcrttemberg",
    "wof:name":"Stuttgarter Lebens- Versicherung Ag",
    "wof:placetype":"venue"
},
  "geometry": {"coordinates":[8.6229858398,48.1674880981],"type":"Point"}
}