{
  "type": "Feature",
  "properties": {
    "iso:country":"DE",
    "sg:address":"Altr\u00e4cknitz 8",
    "sg:city":"Dresden",
    "sg:phone":"+49 351/4724064",
    "sg:postcode":"01217",
    "sg:province":"Sachsen",
    "wof:name":"Freiraumplanung Mit System",
    "wof:placetype":"venue"
},
  "geometry": {"coordinates":[13.733358,51.024708],"type":"Point"}
}