{
  "type": "Feature",
  "properties": {
    "iso:country":"DE",
    "sg:address":"Humboldtstr.",
    "sg:city":"Glinde",
    "sg:phone":"+49 40/3233450",
    "sg:postcode":"21509",
    "sg:province":"Schleswig-Holstein",
    "wof:name":"Century Expert Ges. F. Timesharing Und Touristik Mbh",
    "wof:placetype":"venue"
},
  "geometry": {"coordinates":[10.2317762375,53.5295333862],"type":"Point"}
}