{
  "type": "Feature",
  "properties": {
    "iso:country":"DE",
    "sg:address":"Schulstr. 14-16",
    "sg:city":"Much",
    "sg:postcode":"53804",
    "sg:province":"Nordrhein-Westfalen",
    "wof:name":"Realschule Mit Internat",
    "wof:placetype":"venue"
},
  "geometry": {"coordinates":[7.4020171165,50.9036445618],"type":"Point"}
}