{
  "type": "Feature",
  "properties": {
    "iso:country":"DE",
    "sg:address":"Gottlieb-Daimler-Str. 35",
    "sg:city":"Ludwigsfelde",
    "sg:phone":"+49 3378/541766",
    "sg:postcode":"14974",
    "sg:province":"Brandenburg",
    "wof:name":"Biopur Vertriebs Und Service Gmbh",
    "wof:placetype":"venue"
},
  "geometry": {"coordinates":[13.27088,52.329891],"type":"Point"}
}