{
  "type": "Feature",
  "properties": {
    "iso:country":"DE",
    "sg:address":"Vordere Str. 49",
    "sg:city":"Bissingen",
    "sg:phone":"+49 7023/6201",
    "sg:postcode":"73266",
    "sg:province":"Baden-W\u00fcrttemberg",
    "wof:name":"Ochsen",
    "wof:placetype":"venue"
},
  "geometry": {"coordinates":[9.4910984039,48.6004867554],"type":"Point"}
}