{
  "type": "Feature",
  "properties": {
    "iso:country":"DE",
    "sg:address":"Josef-Schnuch-Str. 25",
    "sg:city":"Wellen",
    "sg:phone":"+49 6584/236",
    "sg:postcode":"54441",
    "sg:province":"Rheinland-Pfalz",
    "wof:name":"Casino",
    "wof:placetype":"venue"
},
  "geometry": {"coordinates":[6.4403920174,49.6713829041],"type":"Point"}
}