{
  "type": "Feature",
  "properties": {
    "iso:country":"DE",
    "sg:address":"Hachenburger Str. 14",
    "sg:city":"Daaden",
    "sg:phone":"+49 2743/2225",
    "sg:postcode":"57567",
    "sg:province":"Rheinland-Pfalz",
    "wof:name":"Schweitzer Verwaltungs- Und Beteiligungs-gmbh",
    "wof:placetype":"venue"
},
  "geometry": {"coordinates":[7.966882,50.73822],"type":"Point"}
}