{
  "type": "Feature",
  "properties": {
    "iso:country":"DE",
    "sg:address":"Hauptstr. 6",
    "sg:city":"Bisingen",
    "sg:phone":"+49 7476/1391",
    "sg:postcode":"72406",
    "sg:province":"Baden-W\u00fcrttemberg",
    "wof:name":"Karl Sauter",
    "wof:placetype":"venue"
},
  "geometry": {"coordinates":[8.916782,48.311073],"type":"Point"}
}