{
  "type": "Feature",
  "properties": {
    "iso:country":"DE",
    "sg:address":"Gutleutstr. 167",
    "sg:city":"Frankfurt",
    "sg:postcode":"60327",
    "sg:province":"Hessen",
    "wof:name":"Gvf Grundst\u00fccksverwaltungsges. F. Immobilien In",
    "wof:placetype":"venue"
},
  "geometry": {"coordinates":[8.65899086,50.1012382507],"type":"Point"}
}