{
  "type": "Feature",
  "properties": {
    "iso:country":"DE",
    "sg:address":"M\u00fchlweg 90",
    "sg:city":"Engelsbrand",
    "sg:phone":"+49 7082/7900",
    "sg:postcode":"75331",
    "sg:province":"Baden-W\u00fcrttemberg",
    "wof:name":"Seiz Reisen Gmbh",
    "wof:placetype":"venue"
},
  "geometry": {"coordinates":[8.656167984,48.8300209045],"type":"Point"}
}