{
  "type": "Feature",
  "properties": {
    "iso:country":"DE",
    "sg:address":"Nu\u00dfgarten 13",
    "sg:city":"H\u00fcttenberg",
    "sg:phone":"+49 6445/7299",
    "sg:postcode":"35625",
    "sg:province":"Hessen",
    "wof:name":"Koch & Eichenauer Seit 1862 Inh. Hans-peter Koch",
    "wof:placetype":"venue"
},
  "geometry": {"coordinates":[8.515384,50.504959],"type":"Point"}
}