{
  "type": "Feature",
  "properties": {
    "iso:country":"DE",
    "sg:address":"Hebelstr. 10",
    "sg:city":"Tennenbronn",
    "sg:phone":"+49 7729/1679",
    "sg:postcode":"78144",
    "sg:province":"Baden-W\u00fcrttemberg",
    "wof:name":"Rudolf Allgeier",
    "wof:placetype":"venue"
},
  "geometry": {"coordinates":[8.3389139175,48.1922836304],"type":"Point"}
}