{
  "type": "Feature",
  "properties": {
    "iso:country":"DE",
    "sg:address":"Mozartstr. 8",
    "sg:city":"Bernburg",
    "sg:postcode":"06406",
    "sg:province":"Sachsen-Anhalt",
    "wof:name":"Gesellschaft F\u00fcr Immobilien- Service-bernburg Gmbh",
    "wof:placetype":"venue"
},
  "geometry": {"coordinates":[11.7421760559,51.7975502014],"type":"Point"}
}