{
  "type": "Feature",
  "properties": {
    "iso:country":"DE",
    "sg:address":"Renthofstr. 29",
    "sg:city":"Schmalkalden",
    "sg:phone":"+49 3683/69330",
    "sg:postcode":"98574",
    "sg:province":"Th\u00fcringen",
    "wof:name":"Bau-haus Projekt Schmalkalden Gmbh",
    "wof:placetype":"venue"
},
  "geometry": {"coordinates":[10.45988,50.721676],"type":"Point"}
}