{
  "type": "Feature",
  "properties": {
    "iso:country":"DE",
    "sg:address":"K\u00f6lner Str. 60 a",
    "sg:city":"M\u00fclheim",
    "sg:phone":"+49 208/460401",
    "sg:postcode":"45481",
    "sg:province":"Nordrhein-Westfalen",
    "wof:name":"Fangmann Kouril & Partner Marketing Gmbh",
    "wof:placetype":"venue"
},
  "geometry": {"coordinates":[6.8754148483,51.3984146118],"type":"Point"}
}