{
  "type": "Feature",
  "properties": {
    "iso:country":"DE",
    "sg:address":"S\u00fc\u00dfbachweg 60",
    "sg:city":"Neunkirchen",
    "sg:phone":"+49 6821/57334",
    "sg:postcode":"66540",
    "sg:province":"Saarland",
    "wof:name":"J. Rossek Gmbh",
    "wof:placetype":"venue"
},
  "geometry": {"coordinates":[7.2098259926,49.3862266541],"type":"Point"}
}