{
  "type": "Feature",
  "properties": {
    "iso:country":"DE",
    "sg:address":"Kometenweg 7",
    "sg:city":"Magdeburg",
    "sg:postcode":"39118",
    "sg:province":"Sachsen-Anhalt",
    "wof:name":"Narkus",
    "wof:placetype":"venue"
},
  "geometry": {"coordinates":[11.618835,52.081913],"type":"Point"}
}