{
  "type": "Feature",
  "properties": {
    "iso:country":"DE",
    "sg:address":"Bremer Str. 35",
    "sg:city":"Hamburg",
    "sg:phone":"+49 40/76751400",
    "sg:postcode":"21073",
    "sg:province":"Hamburg",
    "wof:name":"Reinhard Bracker",
    "wof:placetype":"venue"
},
  "geometry": {"coordinates":[9.9785661697,53.4563407898],"type":"Point"}
}