{
  "type": "Feature",
  "properties": {
    "iso:country":"DE",
    "sg:address":"Am M\u00fchlentor 1",
    "sg:city":"R\u00f6bel",
    "sg:phone":"+49 39931/50883",
    "sg:postcode":"17207",
    "sg:province":"Mecklenburg-Vorpommern",
    "wof:name":"Torsten M\u00f6ller / Versicherungsmakler",
    "wof:placetype":"venue"
},
  "geometry": {"coordinates":[12.6659202576,53.3776741028],"type":"Point"}
}