{
  "type": "Feature",
  "properties": {
    "iso:country":"DE",
    "sg:address":"Puschkinstr. 14",
    "sg:city":"Schkopau",
    "sg:postcode":"06258",
    "sg:province":"Sachsen-Anhalt",
    "wof:name":"Garagengemeinschaft Merseburg- Schkopau E. V.",
    "wof:placetype":"venue"
},
  "geometry": {"coordinates":[11.9824237823,51.3877716064],"type":"Point"}
}