{
  "type": "Feature",
  "properties": {
    "iso:country":"DE",
    "sg:address":"Westf\u00e4lische Str. 18",
    "sg:city":"Olpe",
    "sg:postcode":"57462",
    "sg:province":"Nordrhein-Westfalen",
    "wof:name":"Trend Moden",
    "wof:placetype":"venue"
},
  "geometry": {"coordinates":[7.846029,51.030724],"type":"Point"}
}