{
  "type": "Feature",
  "properties": {
    "iso:country":"DE",
    "sg:address":"Kelterplatz 7",
    "sg:city":"Vaihingen",
    "sg:phone":"+49 4970/422860",
    "sg:postcode":"71665",
    "sg:province":"Baden-W\u00fcrttemberg",
    "wof:name":"Raiffeisenbank Ro\u00dfwag-m\u00fchlacker Eg",
    "wof:placetype":"venue"
},
  "geometry": {"coordinates":[8.91916,48.938095],"type":"Point"}
}