{
  "type": "Feature",
  "properties": {
    "iso:country":"DE",
    "sg:address":"Hauptstr. 59",
    "sg:city":"Offenburg",
    "sg:phone":"+49 781/24289",
    "sg:postcode":"77652",
    "sg:province":"Baden-W\u00fcrttemberg",
    "wof:name":"Blumen Schweiger Inh. Inge Killius-schweiger",
    "wof:placetype":"venue"
},
  "geometry": {"coordinates":[7.943055,48.470249],"type":"Point"}
}