{
  "type": "Feature",
  "properties": {
    "iso:country":"DE",
    "sg:address":"L\u00fcdersfelder Str. 10",
    "sg:city":"Stadthagen",
    "sg:phone":"+49 5721/72786",
    "sg:postcode":"31655",
    "sg:province":"Niedersachsen",
    "wof:name":"Spfk Wohnen Und Arbeit Gemeinn\u00fctzige Gmbh",
    "wof:placetype":"venue"
},
  "geometry": {"coordinates":[9.226029,52.339054],"type":"Point"}
}