{
  "type": "Feature",
  "properties": {
    "iso:country":"DE",
    "sg:address":"K\u00f6nigsallee 6",
    "sg:city":"Bayreuth",
    "sg:phone":"+49 921/94699",
    "sg:postcode":"95448",
    "sg:province":"Bayern",
    "wof:name":"Klaus Dombek",
    "wof:placetype":"venue"
},
  "geometry": {"coordinates":[11.5884847641,49.9393501282],"type":"Point"}
}