{
  "type": "Feature",
  "properties": {
    "iso:country":"DE",
    "sg:address":"Berghof",
    "sg:city":"Meckenheim",
    "sg:postcode":"67149",
    "sg:province":"Rheinland-Pfalz",
    "wof:name":"Delta Productions Ges. F\u00fcr Medienproduktion Mbh",
    "wof:placetype":"venue"
},
  "geometry": {"coordinates":[8.2308149338,49.4012298584],"type":"Point"}
}