{
  "type": "Feature",
  "properties": {
    "iso:country":"DE",
    "sg:address":"T\u00f6nninger Weg 26",
    "sg:city":"Hamburg",
    "sg:phone":"+49 40/802796",
    "sg:postcode":"22609",
    "sg:province":"Hamburg",
    "wof:name":"Harald Kr\u00f6ger",
    "wof:placetype":"venue"
},
  "geometry": {"coordinates":[9.847554,53.569035],"type":"Point"}
}