{
  "type": "Feature",
  "properties": {
    "iso:country":"DE",
    "sg:address":"Sandstr 116",
    "sg:city":"Chemnitz",
    "sg:phone":"+49 371/91300",
    "sg:postcode":"09114",
    "sg:province":"Sachsen",
    "wof:name":"Bhg Guss- Und Verschleisstechnik Gmbh",
    "wof:placetype":"venue"
},
  "geometry": {"coordinates":[12.9005594254,50.8627166748],"type":"Point"}
}