{
  "type": "Feature",
  "properties": {
    "iso:country":"DE",
    "sg:address":"Am Hoppenhof 33",
    "sg:city":"Paderborn",
    "sg:phone":"+49 4952/518890",
    "sg:postcode":"33104",
    "sg:province":"Nordrhein-Westfalen",
    "wof:name":"Orga Kartensysteme Gmbh",
    "wof:placetype":"venue"
},
  "geometry": {"coordinates":[8.72142,51.732491],"type":"Point"}
}