{
  "type": "Feature",
  "properties": {
    "iso:country":"DE",
    "sg:address":"Adolfstr. 13",
    "sg:city":"Kassel",
    "sg:phone":"+49 561/700120",
    "sg:postcode":"34121",
    "sg:province":"Hessen",
    "wof:name":"F. W. Breithaupt & Sohn Gmbh & Co. Kg",
    "wof:placetype":"venue"
},
  "geometry": {"coordinates":[9.4757900238,51.3107223511],"type":"Point"}
}