{
  "type": "Feature",
  "properties": {
    "iso:country":"DE",
    "sg:address":"Gro\u00dfe Forststr. 59",
    "sg:city":"Niederzier",
    "sg:phone":"+49 2428/901176",
    "sg:postcode":"52382",
    "sg:province":"Nordrhein-Westfalen",
    "wof:name":"I. Braun",
    "wof:placetype":"venue"
},
  "geometry": {"coordinates":[6.4445171356,50.9009971619],"type":"Point"}
}