{
  "type": "Feature",
  "properties": {
    "iso:country":"DE",
    "sg:address":"Felderhauser Str. 27",
    "sg:city":"Hennef",
    "sg:phone":"+49 2242/86050",
    "sg:postcode":"53773",
    "sg:province":"Nordrhein-Westfalen",
    "wof:name":"H & L Foto Gmbh",
    "wof:placetype":"venue"
},
  "geometry": {"coordinates":[7.281416893,50.75207901],"type":"Point"}
}