{
  "type": "Feature",
  "properties": {
    "iso:country":"DE",
    "sg:address":"F\u00fcssinger Str. 1",
    "sg:city":"Pocking",
    "sg:phone":"+49 8531/12585",
    "sg:postcode":"94060",
    "sg:province":"Bayern",
    "wof:name":"Batavia Fitness",
    "wof:placetype":"venue"
},
  "geometry": {"coordinates":[13.3096885681,48.3943901062],"type":"Point"}
}