{
  "type": "Feature",
  "properties": {
    "iso:country":"DE",
    "sg:address":"Oberer Graben 28",
    "sg:city":"Freising",
    "sg:phone":"+49 8161/5939",
    "sg:postcode":"85354",
    "sg:province":"Bayern",
    "wof:name":"Franz F. Kirmaier",
    "wof:placetype":"venue"
},
  "geometry": {"coordinates":[11.7403039932,48.400718689],"type":"Point"}
}