{
  "type": "Feature",
  "properties": {
    "iso:country":"DE",
    "sg:address":"Im Stadtfelde 43",
    "sg:city":"Wunstorf",
    "sg:phone":"+49 5031/912590",
    "sg:postcode":"31515",
    "sg:province":"Niedersachsen",
    "wof:name":"Ekamed Ohg",
    "wof:placetype":"venue"
},
  "geometry": {"coordinates":[9.463086,52.421875],"type":"Point"}
}