{
  "type": "Feature",
  "properties": {
    "iso:country":"DE",
    "sg:address":"Marktplatz 11",
    "sg:city":"Laatzen",
    "sg:phone":"+49 511/826282",
    "sg:postcode":"30880",
    "sg:province":"Niedersachsen",
    "wof:name":"Leine-apotheke Jakob Herzog",
    "wof:placetype":"venue"
},
  "geometry": {"coordinates":[9.812674,52.309216],"type":"Point"}
}