{
  "type": "Feature",
  "properties": {
    "iso:country":"DE",
    "sg:address":"Gertrudenstr. 9",
    "sg:city":"Rostock",
    "sg:postcode":"18057",
    "sg:province":"Mecklenburg-Vorpommern",
    "wof:name":"Institut F\u00fcr Anatomie",
    "wof:placetype":"venue"
},
  "geometry": {"coordinates":[12.12605,54.089493],"type":"Point"}
}