{
  "type": "Feature",
  "properties": {
    "iso:country":"DE",
    "sg:address":"Gut Prieschka 63",
    "sg:city":"Prieschka",
    "sg:phone":"+49 35341/6130",
    "sg:postcode":"04924",
    "sg:province":"Brandenburg",
    "wof:name":"Osterhuber Agrar Gmbh",
    "wof:placetype":"venue"
},
  "geometry": {"coordinates":[13.3912134171,51.5224494934],"type":"Point"}
}