{
  "type": "Feature",
  "properties": {
    "iso:country":"DE",
    "sg:address":"Zum Bierloch 1",
    "sg:city":"Winterberg",
    "sg:phone":"+49 2758/272",
    "sg:postcode":"59955",
    "sg:province":"Nordrhein-Westfalen",
    "wof:name":"Pension Karl-heinz Hoffmann",
    "wof:placetype":"venue"
},
  "geometry": {"coordinates":[8.4632835388,51.1503829956],"type":"Point"}
}