{
  "type": "Feature",
  "properties": {
    "iso:country":"DE",
    "sg:address":"Grevinghof 71",
    "sg:city":"Werne",
    "sg:phone":"+49 2389/6925",
    "sg:postcode":"59368",
    "sg:province":"Nordrhein-Westfalen",
    "wof:name":"Paul W\u00f6rdemann",
    "wof:placetype":"venue"
},
  "geometry": {"coordinates":[7.627384,51.675434],"type":"Point"}
}