{
  "type": "Feature",
  "properties": {
    "iso:country":"DE",
    "sg:address":"Ehinger Str 12",
    "sg:city":"\u00d6pfingen",
    "sg:phone":"+49 7391/70160",
    "sg:postcode":"89614",
    "sg:province":"Baden-W\u00fcrttemberg",
    "wof:name":"Gapp Gmbh",
    "wof:placetype":"venue"
},
  "geometry": {"coordinates":[9.800052,48.290878],"type":"Point"}
}