{
  "type": "Feature",
  "properties": {
    "iso:country":"DE",
    "sg:address":"Naunynstr. 40",
    "sg:city":"Berlin",
    "sg:phone":"+49 30/6152034",
    "sg:postcode":"10999",
    "sg:province":"Berlin",
    "wof:name":"Carsten H\u00f6land Elektrotechnik Gmbh",
    "wof:placetype":"venue"
},
  "geometry": {"coordinates":[13.418604,52.502937],"type":"Point"}
}