{
  "type": "Feature",
  "properties": {
    "iso:country":"DE",
    "sg:address":"Solitudeallee 109",
    "sg:city":"Kornwestheim",
    "sg:phone":"+49 7154/83230",
    "sg:postcode":"70806",
    "sg:province":"Baden-W\u00fcrttemberg",
    "wof:name":"Rometsch Textilvertriebs Gmbh",
    "wof:placetype":"venue"
},
  "geometry": {"coordinates":[9.1789741516,48.879611969],"type":"Point"}
}