{
  "type": "Feature",
  "properties": {
    "iso:country":"DE",
    "sg:address":"Malderitzstr. 12",
    "sg:city":"Halle",
    "sg:phone":"+49 345/7705009",
    "sg:postcode":"06132",
    "sg:province":"Sachsen-Anhalt",
    "wof:name":"Dd Dachsanierungs Gmbh",
    "wof:placetype":"venue"
},
  "geometry": {"coordinates":[11.961058,51.431263],"type":"Point"}
}