{
  "type": "Feature",
  "properties": {
    "iso:country":"DE",
    "sg:address":"Don-Bosco-Str. 4",
    "sg:city":"Forchheim",
    "sg:phone":"+49 9191/979154",
    "sg:postcode":"91301",
    "sg:province":"Bayern",
    "wof:name":"Don-bosco-heim Der Salesianer",
    "wof:placetype":"venue"
},
  "geometry": {"coordinates":[11.0783138275,49.7182731628],"type":"Point"}
}