{
  "type": "Feature",
  "properties": {
    "iso:country":"DE",
    "sg:address":"Charlie-Mills-Str. 15",
    "sg:city":"Hamburg",
    "sg:phone":"+49 40/6938568",
    "sg:postcode":"22159",
    "sg:province":"Hamburg",
    "wof:name":"Convest Versicherungs- Makler Gmbh",
    "wof:placetype":"venue"
},
  "geometry": {"coordinates":[10.1047954559,53.5931930542],"type":"Point"}
}