{
  "type": "Feature",
  "properties": {
    "iso:country":"DE",
    "sg:address":"Wilhelm-Segerath-Str. 93",
    "sg:city":"Essen",
    "sg:phone":"+49 201/605112",
    "sg:postcode":"45359",
    "sg:province":"Nordrhein-Westfalen",
    "wof:name":"Arbeiterwohlfahrt Kreisverband Essen E. V.",
    "wof:placetype":"venue"
},
  "geometry": {"coordinates":[6.907879,51.475796],"type":"Point"}
}