{
  "type": "Feature",
  "properties": {
    "iso:country":"DE",
    "sg:address":"In der Mutte 13",
    "sg:city":"Witten",
    "sg:phone":"+49 2302/73404",
    "sg:postcode":"58456",
    "sg:province":"Nordrhein-Westfalen",
    "wof:name":"Karl-heinz Poth",
    "wof:placetype":"venue"
},
  "geometry": {"coordinates":[7.290935,51.383369],"type":"Point"}
}