{
  "type": "Feature",
  "properties": {
    "iso:country":"DE",
    "sg:address":"Im Sonneneck 2",
    "sg:city":"Barsinghausen",
    "sg:phone":"+49 5105/52360",
    "sg:postcode":"30890",
    "sg:province":"Niedersachsen",
    "wof:name":"Axel Buhl",
    "wof:placetype":"venue"
},
  "geometry": {"coordinates":[9.5008869171,52.3336791992],"type":"Point"}
}