{
  "type": "Feature",
  "properties": {
    "iso:country":"DE",
    "sg:address":"Mozartweg 3",
    "sg:city":"Bad Muskau",
    "sg:phone":"+49 35771/60227",
    "sg:postcode":"02953",
    "sg:province":"Sachsen",
    "wof:name":"Helmut Fiebig",
    "wof:placetype":"venue"
},
  "geometry": {"coordinates":[14.710598,51.544285],"type":"Point"}
}