{
  "type": "Feature",
  "properties": {
    "iso:country":"DE",
    "sg:address":"Welfenstr. 11 POSTFACH 1840",
    "sg:city":"Fellbach",
    "sg:phone":"+49 4963/4151080",
    "sg:postcode":"70708",
    "sg:province":"Baden-W\u00fcrttemberg",
    "wof:name":"Ronal Gmbh",
    "wof:placetype":"venue"
},
  "geometry": {"coordinates":[8.1637992859,49.2048339844],"type":"Point"}
}