{
  "type": "Feature",
  "properties": {
    "iso:country":"DE",
    "sg:address":"Salinweg 87",
    "sg:city":"Stephanskirchen",
    "sg:phone":"+49 8031/71629",
    "sg:postcode":"83071",
    "sg:province":"Bayern",
    "wof:name":"Hans Bullwein Elektroinstallation",
    "wof:placetype":"venue"
},
  "geometry": {"coordinates":[12.156032,47.855362],"type":"Point"}
}