{
  "type": "Feature",
  "properties": {
    "iso:country":"DE",
    "sg:address":"Waldsiedlung 2",
    "sg:city":"T\u00fcrkheim",
    "sg:phone":"+49 8245/740",
    "sg:postcode":"86842",
    "sg:province":"Bayern",
    "wof:name":"Discothek Pilsbar Waldfrieden",
    "wof:placetype":"venue"
},
  "geometry": {"coordinates":[10.61228,48.048294],"type":"Point"}
}