{
  "type": "Feature",
  "properties": {
    "iso:country":"DE",
    "sg:address":"Kotzinger Str. 21",
    "sg:city":"Traunstein",
    "sg:phone":"+49 861/4090",
    "sg:postcode":"83278",
    "sg:province":"Bayern",
    "wof:name":"Werbeagentur Bock",
    "wof:placetype":"venue"
},
  "geometry": {"coordinates":[12.629355,47.883568],"type":"Point"}
}