{
  "type": "Feature",
  "properties": {
    "iso:country":"DE",
    "sg:address":"Mettackerweg 12",
    "sg:city":"Freiburg",
    "sg:phone":"+49 761/443303",
    "sg:postcode":"79111",
    "sg:province":"Baden-W\u00fcrttemberg",
    "wof:name":"Werner Liebetruth Architekt",
    "wof:placetype":"venue"
},
  "geometry": {"coordinates":[7.808328,47.980621],"type":"Point"}
}