{
  "type": "Feature",
  "properties": {
    "iso:country":"DE",
    "sg:address":"Badener Str. 18-20",
    "sg:city":"Rastatt",
    "sg:phone":"+49 4972/2232035",
    "sg:postcode":"76437",
    "sg:province":"Baden-W\u00fcrttemberg",
    "wof:name":"M\u00d6bel K\u00dchn Gmbh",
    "wof:placetype":"venue"
},
  "geometry": {"coordinates":[8.2019166946,48.8450469971],"type":"Point"}
}