{
  "type": "Feature",
  "properties": {
    "iso:country":"DE",
    "sg:address":"Ha\u00dflerstr. 22",
    "sg:city":"Aachen",
    "sg:phone":"+49 241/501963",
    "sg:postcode":"52066",
    "sg:province":"Nordrhein-Westfalen",
    "wof:name":"Dr. Wilhelm Hogrebe Ingenieur",
    "wof:placetype":"venue"
},
  "geometry": {"coordinates":[6.1050400734,50.7695999146],"type":"Point"}
}