{
  "type": "Feature",
  "properties": {
    "iso:country":"DE",
    "sg:address":"Am Schmeding 5",
    "sg:city":"Berlin",
    "sg:phone":"+49 30/5455168",
    "sg:postcode":"12685",
    "sg:province":"Berlin",
    "wof:name":"Restaurant-cafe Regina",
    "wof:placetype":"venue"
},
  "geometry": {"coordinates":[13.544798851,52.5365066528],"type":"Point"}
}