{
  "type": "Feature",
  "properties": {
    "iso:country":"DE",
    "sg:address":"Karl-Schneider-Str. 12 b",
    "sg:city":"Gladbeck",
    "sg:phone":"+49 2043/478097",
    "sg:postcode":"45966",
    "sg:province":"Nordrhein-Westfalen",
    "wof:name":"H. D. Dondrup Gmbh",
    "wof:placetype":"venue"
},
  "geometry": {"coordinates":[6.967556,51.572044],"type":"Point"}
}