{
  "type": "Feature",
  "properties": {
    "iso:country":"DE",
    "sg:address":"Wiesenstr.",
    "sg:city":"Egeln",
    "sg:phone":"+49 39268/32271",
    "sg:postcode":"39435",
    "sg:province":"Sachsen-Anhalt",
    "wof:name":"Egelner Tischlerei Gmbh",
    "wof:placetype":"venue"
},
  "geometry": {"coordinates":[11.432307,51.948612],"type":"Point"}
}