{
  "type": "Feature",
  "properties": {
    "iso:country":"DE",
    "sg:address":"Allendestr. 68",
    "sg:city":"Schmalkalden",
    "sg:postcode":"98574",
    "sg:province":"Th\u00fcringen",
    "wof:name":"Geon Gesellschaft F\u00fcr Energieoptimierte Nutzung Mbh",
    "wof:placetype":"venue"
},
  "geometry": {"coordinates":[10.4731302261,50.724445343],"type":"Point"}
}