{
  "type": "Feature",
  "properties": {
    "iso:country":"DE",
    "sg:address":"Twentestr. 3",
    "sg:city":"Nordhorn",
    "sg:phone":"+49 5921/88170",
    "sg:postcode":"48527",
    "sg:province":"Niedersachsen",
    "wof:name":"Stylex Schreibwaren Gmbh",
    "wof:placetype":"venue"
},
  "geometry": {"coordinates":[7.033826,52.419582],"type":"Point"}
}