{
  "type": "Feature",
  "properties": {
    "iso:country":"DE",
    "sg:address":"Benzstr. 10",
    "sg:city":"Reutlingen",
    "sg:phone":"+49 7121/93060",
    "sg:postcode":"72762",
    "sg:province":"Baden-W\u00fcrttemberg",
    "wof:name":"Ivt Ingenieurb\u00fcro F\u00fcr Versorgungstechnik Gmbh",
    "wof:placetype":"venue"
},
  "geometry": {"coordinates":[9.203704,48.497025],"type":"Point"}
}