{
  "type": "Feature",
  "properties": {
    "iso:country":"DE",
    "sg:address":"Annastr. 21",
    "sg:city":"Dinslaken",
    "sg:phone":"+49 2064/2077",
    "sg:postcode":"46537",
    "sg:province":"Nordrhein-Westfalen",
    "wof:name":"Werner Heise",
    "wof:placetype":"venue"
},
  "geometry": {"coordinates":[6.7171320915,51.5771865845],"type":"Point"}
}