{
  "type": "Feature",
  "properties": {
    "iso:country":"DE",
    "sg:address":"Breitenkamp 46",
    "sg:city":"Oerlinghausen",
    "sg:phone":"+49 5202/2556",
    "sg:postcode":"33813",
    "sg:province":"Nordrhein-Westfalen",
    "wof:name":"Bohle-heintze",
    "wof:placetype":"venue"
},
  "geometry": {"coordinates":[8.663118,51.954464],"type":"Point"}
}