{
  "type": "Feature",
  "properties": {
    "iso:country":"DE",
    "sg:address":"Oulustr. 7",
    "sg:city":"Leverkusen",
    "sg:phone":"+49 214/8505311",
    "sg:postcode":"51375",
    "sg:province":"Nordrhein-Westfalen",
    "wof:name":"Enak Energie-anlagen",
    "wof:placetype":"venue"
},
  "geometry": {"coordinates":[7.048036,51.034302],"type":"Point"}
}