{
  "type": "Feature",
  "properties": {
    "iso:country":"DE",
    "sg:address":"H\u00fcbel 2",
    "sg:city":"Kleinkarlbach",
    "sg:phone":"+49 6359/3682",
    "sg:postcode":"67271",
    "sg:province":"Rheinland-Pfalz",
    "wof:name":"Karl Speckert Weinanbau",
    "wof:placetype":"venue"
},
  "geometry": {"coordinates":[8.1601161957,49.5407867432],"type":"Point"}
}