{
  "type": "Feature",
  "properties": {
    "iso:country":"DE",
    "sg:address":"Heinrich-Koehl-Str. 58",
    "sg:city":"Saarbr\u00fccken",
    "sg:phone":"+49 681/48767",
    "sg:postcode":"66113",
    "sg:province":"Saarland",
    "wof:name":"In Lebensmittel-filiale Gmbh",
    "wof:placetype":"venue"
},
  "geometry": {"coordinates":[6.9912810326,49.2489776611],"type":"Point"}
}