{
  "type": "Feature",
  "properties": {
    "iso:country":"DE",
    "sg:address":"Raiffeisenstr. 2",
    "sg:city":"Triftern",
    "sg:phone":"+49 8562/912216",
    "sg:postcode":"84371",
    "sg:province":"Bayern",
    "wof:name":"Thomas Broda",
    "wof:placetype":"venue"
},
  "geometry": {"coordinates":[13.0061073303,48.3899917603],"type":"Point"}
}