{
  "type": "Feature",
  "properties": {
    "iso:country":"DE",
    "sg:address":"Rheinstr. 38",
    "sg:city":"M\u00fchltal",
    "sg:phone":"+49 4961/5150980",
    "sg:postcode":"64367",
    "sg:province":"Hessen",
    "wof:name":"Cordier Spezialpapier Gmbh",
    "wof:placetype":"venue"
},
  "geometry": {"coordinates":[8.6843795776,49.819190979],"type":"Point"}
}