{
  "type": "Feature",
  "properties": {
    "iso:country":"DE",
    "sg:address":"Goethestr. 2",
    "sg:city":"Du\u00dflingen",
    "sg:phone":"+49 7072/6820",
    "sg:postcode":"72144",
    "sg:province":"Baden-W\u00fcrttemberg",
    "wof:name":"Heinz Fauser",
    "wof:placetype":"venue"
},
  "geometry": {"coordinates":[9.0553569794,48.4465370178],"type":"Point"}
}