{
  "type": "Feature",
  "properties": {
    "iso:country":"DE",
    "sg:address":"Ebertallee 207",
    "sg:city":"Hamburg",
    "sg:phone":"+49 40/891540",
    "sg:postcode":"22607",
    "sg:province":"Hamburg",
    "wof:name":"Manfred Lewerenz",
    "wof:placetype":"venue"
},
  "geometry": {"coordinates":[9.8910837173,53.573299408],"type":"Point"}
}