{
  "type": "Feature",
  "properties": {
    "iso:country":"DE",
    "sg:address":"Liedstr. 5",
    "sg:city":"Hagen",
    "sg:phone":"+49 5401/9357",
    "sg:postcode":"49170",
    "sg:province":"Niedersachsen",
    "wof:name":"F. Kriege",
    "wof:placetype":"venue"
},
  "geometry": {"coordinates":[7.997658,52.207996],"type":"Point"}
}