{
  "type": "Feature",
  "properties": {
    "iso:country":"DE",
    "sg:address":"Provinzialstr. 48",
    "sg:city":"Saarlouis",
    "sg:phone":"+49 6831/122525",
    "sg:postcode":"66740",
    "sg:province":"Saarland",
    "wof:name":"Creativ Light Design Robin Schindera",
    "wof:placetype":"venue"
},
  "geometry": {"coordinates":[6.757517,49.304787],"type":"Point"}
}