{
  "type": "Feature",
  "properties": {
    "iso:country":"DE",
    "sg:address":"Wielandstr. 8",
    "sg:city":"Uttenweiler",
    "sg:phone":"+49 7374/91103",
    "sg:postcode":"88524",
    "sg:province":"Baden-W\u00fcrttemberg",
    "wof:name":"Dr. Hartmut Pfrommer Tierarzt",
    "wof:placetype":"venue"
},
  "geometry": {"coordinates":[9.6176357269,48.1510353088],"type":"Point"}
}