{
  "type": "Feature",
  "properties": {
    "iso:country":"DE",
    "sg:address":"Lohweg 20",
    "sg:city":"Bad Sassendorf",
    "sg:phone":"+49 2921/5686",
    "sg:postcode":"59505",
    "sg:province":"Nordrhein-Westfalen",
    "wof:name":"Pension U. Dunkel",
    "wof:placetype":"venue"
},
  "geometry": {"coordinates":[8.173377037,51.5856323242],"type":"Point"}
}