{
  "type": "Feature",
  "properties": {
    "iso:country":"DE",
    "sg:address":"Ginsheimer Str. 1",
    "sg:city":"Ginsheim-Gustavsburg",
    "sg:postcode":"65462",
    "sg:province":"Hessen",
    "wof:name":"Vier Sale It-service Gmbh",
    "wof:placetype":"venue"
},
  "geometry": {"coordinates":[8.319694,49.992847],"type":"Point"}
}