{
  "type": "Feature",
  "properties": {
    "iso:country":"DE",
    "sg:address":"Danziger Str. 10",
    "sg:city":"Babenhausen",
    "sg:phone":"+49 6073/5822",
    "sg:postcode":"64832",
    "sg:province":"Hessen",
    "wof:name":"E. C. Denkena Ingenieur",
    "wof:placetype":"venue"
},
  "geometry": {"coordinates":[8.9590177536,49.9683418274],"type":"Point"}
}