{
  "type": "Feature",
  "properties": {
    "iso:country":"DE",
    "sg:address":"Hauptmarkt 10",
    "sg:city":"Gotha",
    "sg:phone":"+49 3621/28424",
    "sg:postcode":"99867",
    "sg:province":"Th\u00fcringen",
    "wof:name":"B. Noth",
    "wof:placetype":"venue"
},
  "geometry": {"coordinates":[10.7019166946,50.948802948],"type":"Point"}
}