{
  "type": "Feature",
  "properties": {
    "iso:country":"DE",
    "sg:address":"Hauptstr. 25-27",
    "sg:city":"Wuppertal",
    "sg:phone":"+49 202/473725",
    "sg:postcode":"42349",
    "sg:province":"Nordrhein-Westfalen",
    "wof:name":"Kaufhaus Josef K\u00fchle",
    "wof:placetype":"venue"
},
  "geometry": {"coordinates":[7.131026,51.206024],"type":"Point"}
}