{
  "type": "Feature",
  "properties": {
    "iso:country":"DE",
    "sg:address":"Stra\u00dfe des Friedens 23",
    "sg:city":"Bad Klosterlausnitz",
    "sg:phone":"+49 36601/83587",
    "sg:postcode":"07639",
    "sg:province":"Th\u00fcringen",
    "wof:name":"Gerhard L\u00fcders",
    "wof:placetype":"venue"
},
  "geometry": {"coordinates":[11.8654737473,50.9186820984],"type":"Point"}
}