{
  "type": "Feature",
  "properties": {
    "iso:country":"DE",
    "sg:address":"Asberger Str. 33",
    "sg:city":"Moers",
    "sg:phone":"+49 2841/3718",
    "sg:postcode":"47441",
    "sg:province":"Nordrhein-Westfalen",
    "wof:name":"Friedhelm Kempe",
    "wof:placetype":"venue"
},
  "geometry": {"coordinates":[6.644053,51.445923],"type":"Point"}
}