{
  "type": "Feature",
  "properties": {
    "iso:country":"DE",
    "sg:address":"Rellinghauser Str. 1-11",
    "sg:city":"Essen",
    "sg:postcode":"45128",
    "sg:province":"Nordrhein-Westfalen",
    "wof:name":"Preussag Handel Gmbh",
    "wof:placetype":"venue"
},
  "geometry": {"coordinates":[7.015712,51.448933],"type":"Point"}
}