{
  "type": "Feature",
  "properties": {
    "iso:country":"DE",
    "sg:address":"Die Waide 8",
    "sg:city":"Schutterwald",
    "sg:phone":"+49 781/51356",
    "sg:postcode":"77746",
    "sg:province":"Baden-W\u00fcrttemberg",
    "wof:name":"Erna Viziotidis Heilpraktikerin",
    "wof:placetype":"venue"
},
  "geometry": {"coordinates":[7.8795118332,48.4616966248],"type":"Point"}
}