{
  "type": "Feature",
  "properties": {
    "iso:country":"DE",
    "sg:address":"Adlerstra\u00dfe 4",
    "sg:city":"Heidelberg",
    "sg:phone":"+49 6221/830450",
    "sg:postcode":"69123",
    "sg:province":"Baden-W\u00fcrttemberg",
    "wof:name":"Aljoscha Remelius",
    "wof:placetype":"venue"
},
  "geometry": {"coordinates":[8.6469106674,49.4227752686],"type":"Point"}
}