{
  "type": "Feature",
  "properties": {
    "iso:country":"DE",
    "sg:address":"S\u00fcdfelder Dorfstr. 6",
    "sg:city":"Petershagen",
    "sg:phone":"+49 5704/643",
    "sg:postcode":"32469",
    "sg:province":"Nordrhein-Westfalen",
    "wof:name":"Hotel Landhaus Sch\u00e4ferbarthold",
    "wof:placetype":"venue"
},
  "geometry": {"coordinates":[8.902340889,52.3656387329],"type":"Point"}
}