{
  "type": "Feature",
  "properties": {
    "iso:country":"DE",
    "sg:address":"Bahnhofstr. 31",
    "sg:city":"V\u00f6hringen",
    "sg:phone":"+49 7306/5593",
    "sg:postcode":"89269",
    "sg:province":"Bayern",
    "wof:name":"Restaurant Bierkrug",
    "wof:placetype":"venue"
},
  "geometry": {"coordinates":[10.0829963684,48.2791595459],"type":"Point"}
}