{
  "type": "Feature",
  "properties": {
    "iso:country":"DE",
    "sg:address":"Hafenstr. 3",
    "sg:city":"Bremerhaven",
    "sg:phone":"+49 471/45558",
    "sg:postcode":"27576",
    "sg:province":"Bremen",
    "wof:name":"Hanke Br\u00fcning",
    "wof:placetype":"venue"
},
  "geometry": {"coordinates":[8.5796823502,53.5497741699],"type":"Point"}
}