{
  "type": "Feature",
  "properties": {
    "iso:country":"DE",
    "sg:address":"Silcherstr. 12",
    "sg:city":"Filderstadt",
    "sg:phone":"+49 7158/8578",
    "sg:postcode":"70794",
    "sg:province":"Baden-W\u00fcrttemberg",
    "wof:name":"J\u00f6rg Schweizer",
    "wof:placetype":"venue"
},
  "geometry": {"coordinates":[9.238756,48.679897],"type":"Point"}
}