{
  "type": "Feature",
  "properties": {
    "iso:country":"DE",
    "sg:address":"Industriestr. 7",
    "sg:city":"Jesberg",
    "sg:phone":"+49 6695/7312",
    "sg:postcode":"34632",
    "sg:province":"Hessen",
    "wof:name":"Hawe Gokart-sport Gmbh",
    "wof:placetype":"venue"
},
  "geometry": {"coordinates":[9.148572,50.999123],"type":"Point"}
}