{
  "type": "Feature",
  "properties": {
    "iso:country":"DE",
    "sg:address":"Am Posthof 7",
    "sg:city":"Gudensberg",
    "sg:phone":"+49 4956/0393340",
    "sg:postcode":"34281",
    "sg:province":"Hessen",
    "wof:name":"Tis Banze Gmbh",
    "wof:placetype":"venue"
},
  "geometry": {"coordinates":[9.411043,51.194298],"type":"Point"}
}