{
  "type": "Feature",
  "properties": {
    "iso:country":"DE",
    "sg:address":"Ernst-Th\u00e4lmann-Str. 52",
    "sg:city":"Reitzenhain",
    "sg:phone":"+49 37364/8257",
    "sg:postcode":"09496",
    "sg:province":"Sachsen",
    "wof:name":"Christian Rie\u00df",
    "wof:placetype":"venue"
},
  "geometry": {"coordinates":[13.2192296982,50.5585021973],"type":"Point"}
}