{
  "type": "Feature",
  "properties": {
    "iso:country":"DE",
    "sg:address":"Erfurter Str. 5",
    "sg:city":"Gotha",
    "sg:phone":"+49 3621/301191",
    "sg:postcode":"99867",
    "sg:province":"Th\u00fcringen",
    "wof:name":"Essanelle Frisiersalons Gmbh & Co. Ohg",
    "wof:placetype":"venue"
},
  "geometry": {"coordinates":[10.7060871124,50.9502296448],"type":"Point"}
}