{
  "type": "Feature",
  "properties": {
    "iso:country":"DE",
    "sg:address":"Rosentalstr. 3",
    "sg:city":"Minden",
    "sg:phone":"+49 571/828760",
    "sg:postcode":"32423",
    "sg:province":"Nordrhein-Westfalen",
    "wof:name":"Schulpsychologische Beratungsstelle",
    "wof:placetype":"venue"
},
  "geometry": {"coordinates":[8.916435,52.294228],"type":"Point"}
}