{
  "type": "Feature",
  "properties": {
    "iso:country":"DE",
    "sg:address":"Industriestr. 11 d",
    "sg:city":"Kaufungen",
    "sg:phone":"+49 5605/94450",
    "sg:postcode":"34260",
    "sg:province":"Hessen",
    "wof:name":"Spedition C. Werthmann & K\u00f6ster Gmbh",
    "wof:placetype":"venue"
},
  "geometry": {"coordinates":[9.5760059357,51.2858085632],"type":"Point"}
}