{
  "type": "Feature",
  "properties": {
    "iso:country":"DE",
    "sg:address":"Fuldische Aue 7",
    "sg:city":"Heringen",
    "sg:phone":"+49 6624/919330",
    "sg:postcode":"36266",
    "sg:province":"Hessen",
    "wof:name":"Pension Alt Heringen",
    "wof:placetype":"venue"
},
  "geometry": {"coordinates":[10.0098686218,50.8900184631],"type":"Point"}
}