{
  "type": "Feature",
  "properties": {
    "iso:country":"DE",
    "sg:address":"Leimenstr. 20",
    "sg:city":"Hanau",
    "sg:phone":"+49 6181/2960",
    "sg:postcode":"63450",
    "sg:province":"Hessen",
    "wof:name":"Krankenhausvollapotheke Des St\u00e4dt. Krankenhauses",
    "wof:placetype":"venue"
},
  "geometry": {"coordinates":[8.922425,50.133579],"type":"Point"}
}