{
  "type": "Feature",
  "properties": {
    "iso:country":"DE",
    "sg:address":"Gelber Weg 15",
    "sg:city":"Enger",
    "sg:phone":"+49 5224/6262",
    "sg:postcode":"32130",
    "sg:province":"Nordrhein-Westfalen",
    "wof:name":"Dr. Hans-j\u00fcrgen Zechel Tierarzt",
    "wof:placetype":"venue"
},
  "geometry": {"coordinates":[8.5399551392,52.1112365723],"type":"Point"}
}