{
  "type": "Feature",
  "properties": {
    "iso:country":"DE",
    "sg:address":"Bergfriedstr. 19",
    "sg:city":"Berlin",
    "sg:phone":"+49 30/6152022",
    "sg:postcode":"10969",
    "sg:province":"Berlin",
    "wof:name":"\u00d6z-g\u00f6z Gmbh",
    "wof:placetype":"venue"
},
  "geometry": {"coordinates":[13.4108181,52.4997749329],"type":"Point"}
}