{
  "type": "Feature",
  "properties": {
    "iso:country":"DE",
    "sg:address":"Berliner Str. 44",
    "sg:city":"Berlin",
    "sg:postcode":"10713",
    "sg:province":"Berlin",
    "wof:name":"Idbg- Immobilien Dienst- Leistungs- Und",
    "wof:placetype":"venue"
},
  "geometry": {"coordinates":[13.318715,52.486656],"type":"Point"}
}