{
  "type": "Feature",
  "properties": {
    "iso:country":"DE",
    "sg:address":"Wenstrup 19",
    "sg:city":"Neuenkirchen-V\u00f6rden",
    "sg:postcode":"49434",
    "sg:province":"Niedersachsen",
    "wof:name":"Bio-anbau Gisela Mustermann-fiedler",
    "wof:placetype":"venue"
},
  "geometry": {"coordinates":[8.042139,52.585033],"type":"Point"}
}