{
  "type": "Feature",
  "properties": {
    "iso:country":"DE",
    "sg:address":"Kirchheimer Str. 53",
    "sg:city":"N\u00fcrtingen",
    "sg:phone":"+49 7022/8238",
    "sg:postcode":"72622",
    "sg:province":"Baden-W\u00fcrttemberg",
    "wof:name":"Edeka Aktiv Markt",
    "wof:placetype":"venue"
},
  "geometry": {"coordinates":[9.3488883972,48.6251296997],"type":"Point"}
}