{
  "type": "Feature",
  "properties": {
    "iso:country":"DE",
    "sg:address":"Hauptstr. 43",
    "sg:city":"Pirmasens",
    "sg:phone":"+49 6331/43582",
    "sg:postcode":"66953",
    "sg:province":"Rheinland-Pfalz",
    "wof:name":"Manfred Steigerwald",
    "wof:placetype":"venue"
},
  "geometry": {"coordinates":[7.60516119,49.1984367371],"type":"Point"}
}