{
  "type": "Feature",
  "properties": {
    "iso:country":"DE",
    "sg:address":"Fehlheimer Str. 5",
    "sg:city":"Einhausen",
    "sg:phone":"+49 6251/587764",
    "sg:postcode":"64683",
    "sg:province":"Hessen",
    "wof:name":"P. Kassner",
    "wof:placetype":"venue"
},
  "geometry": {"coordinates":[8.552484,49.673466],"type":"Point"}
}