{
  "type": "Feature",
  "properties": {
    "iso:country":"DE",
    "sg:address":"Borchersstr. 19",
    "sg:city":"Hannover",
    "sg:phone":"+49 511/517741",
    "sg:postcode":"30559",
    "sg:province":"Niedersachsen",
    "wof:name":"Witte-service Gesellschaft F. Verwalt. V. Immobilien Sow.",
    "wof:placetype":"venue"
},
  "geometry": {"coordinates":[9.830142,52.359234],"type":"Point"}
}