{
  "type": "Feature",
  "properties": {
    "iso:country":"DE",
    "sg:address":"Blumenthalstr. 24",
    "sg:city":"Wustrow",
    "sg:phone":"+49 5843/986300",
    "sg:postcode":"29462",
    "sg:province":"Niedersachsen",
    "wof:name":"Alexander Wolfrath",
    "wof:placetype":"venue"
},
  "geometry": {"coordinates":[11.1289920807,52.9260101318],"type":"Point"}
}