{
  "type": "Feature",
  "properties": {
    "iso:country":"DE",
    "sg:address":"Waldenburger Str. 8",
    "sg:city":"Schmallenberg",
    "sg:phone":"+49 2974/1631",
    "sg:postcode":"57392",
    "sg:province":"Nordrhein-Westfalen",
    "wof:name":"Fredeburger",
    "wof:placetype":"venue"
},
  "geometry": {"coordinates":[8.291719,51.16206],"type":"Point"}
}