{
  "type": "Feature",
  "properties": {
    "iso:country":"DE",
    "sg:address":"Neuwiesenstr. 57",
    "sg:city":"Frankfurt",
    "sg:phone":"+49 69/672390",
    "sg:postcode":"60528",
    "sg:province":"Hessen",
    "wof:name":"Kinne & Papsdorf Gmbh & Co.",
    "wof:placetype":"venue"
},
  "geometry": {"coordinates":[8.649692,50.078308],"type":"Point"}
}