{
  "type": "Feature",
  "properties": {
    "iso:country":"DE",
    "sg:address":"Gr\u00fcntenstr. 22",
    "sg:city":"M\u00fcnchen",
    "sg:phone":"+49 89/5701163",
    "sg:postcode":"80686",
    "sg:province":"Bayern",
    "wof:name":"Gernot Dettweiler Architekt",
    "wof:placetype":"venue"
},
  "geometry": {"coordinates":[11.518493,48.12653],"type":"Point"}
}