{
  "type": "Feature",
  "properties": {
    "iso:country":"DE",
    "sg:address":"Rosental 37",
    "sg:city":"Bonn",
    "sg:phone":"+49 228/635560",
    "sg:postcode":"53111",
    "sg:province":"Nordrhein-Westfalen",
    "wof:name":"Schell Gmbh",
    "wof:placetype":"venue"
},
  "geometry": {"coordinates":[7.100388,50.742584],"type":"Point"}
}