{
  "type": "Feature",
  "properties": {
    "iso:country":"DE",
    "sg:address":"Karlsbader Str. 287",
    "sg:city":"Sehmatal-Neudorf",
    "sg:phone":"+49 37342/8281",
    "sg:postcode":"09465",
    "sg:province":"Sachsen",
    "wof:name":"Winfried Otto",
    "wof:placetype":"venue"
},
  "geometry": {"coordinates":[12.970715,50.472076],"type":"Point"}
}