{
  "type": "Feature",
  "properties": {
    "iso:country":"DE",
    "sg:address":"Kirchplatz 182",
    "sg:city":"Gro\u00dfneuhausen",
    "sg:phone":"+49 36372/90578",
    "sg:postcode":"99625",
    "sg:province":"Th\u00fcringen",
    "wof:name":"B. Wenzowski",
    "wof:placetype":"venue"
},
  "geometry": {"coordinates":[11.2822360992,51.1604347229],"type":"Point"}
}