{
  "type": "Feature",
  "properties": {
    "iso:country":"DE",
    "sg:address":"Hospitalstr. 2",
    "sg:city":"Asbach",
    "sg:phone":"+49 2683/949775",
    "sg:postcode":"53567",
    "sg:province":"Rheinland-Pfalz",
    "wof:name":"M. Limbach",
    "wof:placetype":"venue"
},
  "geometry": {"coordinates":[7.425024,50.666218],"type":"Point"}
}