{
  "type": "Feature",
  "properties": {
    "iso:country":"DE",
    "sg:address":"An den Graften 1",
    "sg:city":"Delmenhorst",
    "sg:postcode":"27753",
    "sg:province":"Niedersachsen",
    "wof:name":"Saalbau Am Stadtpark Gmbh",
    "wof:placetype":"venue"
},
  "geometry": {"coordinates":[8.625749,53.047447],"type":"Point"}
}