{
  "type": "Feature",
  "properties": {
    "iso:country":"DE",
    "sg:address":"Daimlerstr 33",
    "sg:city":"Herrenberg",
    "sg:phone":"+49 6751/93660",
    "sg:postcode":"71083",
    "sg:province":"Baden-W\u00fcrttemberg",
    "wof:name":"Wehner",
    "wof:placetype":"venue"
},
  "geometry": {"coordinates":[7.6289582253,49.7856483459],"type":"Point"}
}