{
  "type": "Feature",
  "properties": {
    "iso:country":"DE",
    "sg:address":"Kirchstr. 22",
    "sg:city":"Eberswalde",
    "sg:phone":"+49 3334/22265",
    "sg:postcode":"16225",
    "sg:province":"Brandenburg",
    "wof:name":"Musahl Gmbh",
    "wof:placetype":"venue"
},
  "geometry": {"coordinates":[13.82002,52.832279],"type":"Point"}
}