{
  "type": "Feature",
  "properties": {
    "iso:country":"DE",
    "sg:address":"Storkower Str. 115 a",
    "sg:city":"Berlin",
    "sg:phone":"+49 30/42188440",
    "sg:postcode":"10407",
    "sg:province":"Berlin",
    "wof:name":"Aucoteam Ingenieurgesellschaft F\u00fcr Automatisierungs- Und",
    "wof:placetype":"venue"
},
  "geometry": {"coordinates":[13.4535417557,52.5356445312],"type":"Point"}
}