{
  "type": "Feature",
  "properties": {
    "iso:country":"DE",
    "sg:address":"Orleansstr. 55",
    "sg:city":"M\u00fcnchen",
    "sg:phone":"+49 89/4483032",
    "sg:postcode":"81667",
    "sg:province":"Bayern",
    "wof:name":"Alfred Florian",
    "wof:placetype":"venue"
},
  "geometry": {"coordinates":[11.605069,48.12933],"type":"Point"}
}