{
  "type": "Feature",
  "properties": {
    "iso:country":"DE",
    "sg:address":"Alexanderplatz 6",
    "sg:city":"Berlin",
    "sg:postcode":"10178",
    "sg:province":"Berlin",
    "wof:name":"Impuls Electronic Gmbh",
    "wof:placetype":"venue"
},
  "geometry": {"coordinates":[13.413509,52.521305],"type":"Point"}
}