{
  "type": "Feature",
  "properties": {
    "iso:country":"DE",
    "sg:address":"Markgrafenstr. 8",
    "sg:city":"Baden-Baden",
    "sg:postcode":"76530",
    "sg:province":"Baden-W\u00fcrttemberg",
    "wof:name":"Capital Corporation Gmbh",
    "wof:placetype":"venue"
},
  "geometry": {"coordinates":[8.2477245331,48.7594985962],"type":"Point"}
}