{
  "type": "Feature",
  "properties": {
    "iso:country":"DE",
    "sg:address":"Marktstr. 1",
    "sg:city":"Marienm\u00fcnster",
    "sg:phone":"+49 5276/8083",
    "sg:postcode":"37696",
    "sg:province":"Nordrhein-Westfalen",
    "wof:name":"Provinzial Versicherung Hans Reifer",
    "wof:placetype":"venue"
},
  "geometry": {"coordinates":[9.2280349731,51.8184242249],"type":"Point"}
}