{
  "type": "Feature",
  "properties": {
    "iso:country":"DE",
    "sg:address":"Gilbertstr. 67a",
    "sg:city":"Trier",
    "sg:phone":"+49 651/9759599",
    "sg:postcode":"54290",
    "sg:province":"Rheinland-Pfalz",
    "wof:name":"Konzept Gesellschaft F\u00fcr Immobilien-recycling Und",
    "wof:placetype":"venue"
},
  "geometry": {"coordinates":[6.6294908524,49.7491836548],"type":"Point"}
}