{
  "type": "Feature",
  "properties": {
    "iso:country":"DE",
    "sg:address":"Barkhausenstr. 49",
    "sg:city":"Falkensee",
    "sg:phone":"+49 3322/209223",
    "sg:postcode":"14612",
    "sg:province":"Brandenburg",
    "wof:name":"Berlin-brandenburg Immobilien",
    "wof:placetype":"venue"
},
  "geometry": {"coordinates":[13.0880708694,52.5553588867],"type":"Point"}
}