{
  "type": "Feature",
  "properties": {
    "iso:country":"DE",
    "sg:address":"Frankenweg 30",
    "sg:city":"Eschborn",
    "sg:phone":"+49 69/447714",
    "sg:postcode":"65760",
    "sg:province":"Hessen",
    "wof:name":"Christian Rieck Verlag",
    "wof:placetype":"venue"
},
  "geometry": {"coordinates":[8.549137,50.15295],"type":"Point"}
}