{
  "type": "Feature",
  "properties": {
    "iso:country":"DE",
    "sg:address":"Schwaaner Landstr. 15",
    "sg:city":"Rostock",
    "sg:phone":"+49 381/4001515",
    "sg:postcode":"18059",
    "sg:province":"Mecklenburg-Vorpommern",
    "wof:name":"Richard Harder Pretty-t\u00fcren-fachbetrieb Gmbh",
    "wof:placetype":"venue"
},
  "geometry": {"coordinates":[12.1368141174,54.0712432861],"type":"Point"}
}