{
  "type": "Feature",
  "properties": {
    "iso:country":"DE",
    "sg:address":"Heinrich-von-Stephan-Platz 5",
    "sg:city":"Naumburg",
    "sg:phone":"+49 3445/703002",
    "sg:postcode":"06618",
    "sg:province":"Sachsen-Anhalt",
    "wof:name":"Naumburger Stra\u00dfenbahn Gmbh",
    "wof:placetype":"venue"
},
  "geometry": {"coordinates":[11.8136672974,51.1553497314],"type":"Point"}
}