{
  "type": "Feature",
  "properties": {
    "iso:country":"DE",
    "sg:address":"Gro\u00dfer Sand 80",
    "sg:city":"Uetersen",
    "sg:phone":"+49 4122/1414",
    "sg:postcode":"25436",
    "sg:province":"Schleswig-Holstein",
    "wof:name":"H\u00fcsniye \u00d6ncan",
    "wof:placetype":"venue"
},
  "geometry": {"coordinates":[9.6728572845,53.6812858582],"type":"Point"}
}