{
  "type": "Feature",
  "properties": {
    "iso:country":"DE",
    "sg:address":"Leipziger Str. 36",
    "sg:city":"Pohlheim",
    "sg:phone":"+49 6403/974921",
    "sg:postcode":"35415",
    "sg:province":"Hessen",
    "wof:name":"Schmitt Und Saller Rechtsanw\u00e4lte",
    "wof:placetype":"venue"
},
  "geometry": {"coordinates":[8.7030477524,50.538356781],"type":"Point"}
}