{
  "type": "Feature",
  "properties": {
    "iso:country":"DE",
    "sg:address":"Auf der Steig 33",
    "sg:city":"Stuttgart",
    "sg:phone":"+49 711/545855",
    "sg:postcode":"70376",
    "sg:province":"Baden-W\u00fcrttemberg",
    "wof:name":"Wilhelm Bauer",
    "wof:placetype":"venue"
},
  "geometry": {"coordinates":[9.2056035995,48.8143310547],"type":"Point"}
}