{
  "type": "Feature",
  "properties": {
    "iso:country":"DE",
    "sg:address":"Diekmoorweg 15",
    "sg:city":"Hamburg",
    "sg:phone":"+49 40/53035710",
    "sg:postcode":"22419",
    "sg:province":"Hamburg",
    "wof:name":"Ronald Sperling Rechtsanwalt",
    "wof:placetype":"venue"
},
  "geometry": {"coordinates":[10.0163459778,53.6597976685],"type":"Point"}
}