{
  "type": "Feature",
  "properties": {
    "iso:country":"DE",
    "sg:address":"Schippertstr. 13",
    "sg:city":"Murrhardt",
    "sg:phone":"+49 7192/6064",
    "sg:postcode":"71540",
    "sg:province":"Baden-W\u00fcrttemberg",
    "wof:name":"Rainer Hirzel",
    "wof:placetype":"venue"
},
  "geometry": {"coordinates":[9.575235,48.981503],"type":"Point"}
}