{
  "type": "Feature",
  "properties": {
    "iso:country":"DE",
    "sg:address":"In der Twiete 3",
    "sg:city":"Fr\u00f6ndenberg",
    "sg:phone":"+49 2378/2774",
    "sg:postcode":"58730",
    "sg:province":"Nordrhein-Westfalen",
    "wof:name":"Brigitte Und Heinz-d. Klemp",
    "wof:placetype":"venue"
},
  "geometry": {"coordinates":[7.7431,51.501862],"type":"Point"}
}