{
  "type": "Feature",
  "properties": {
    "iso:country":"DE",
    "sg:address":"Ludwigsfelder Str. 5",
    "sg:city":"R\u00f6slau",
    "sg:phone":"+49 9238/348",
    "sg:postcode":"95195",
    "sg:province":"Bayern",
    "wof:name":"Erika Barnickel",
    "wof:placetype":"venue"
},
  "geometry": {"coordinates":[11.972533226,50.0839729309],"type":"Point"}
}