{
  "type": "Feature",
  "properties": {
    "iso:country":"DE",
    "sg:address":"Allee der Kosmonauten 115",
    "sg:city":"Berlin",
    "sg:phone":"+49 30/5419815",
    "sg:postcode":"12681",
    "sg:province":"Berlin",
    "wof:name":"Dr. Med. Gisela G\u00f6hlert",
    "wof:placetype":"venue"
},
  "geometry": {"coordinates":[13.546824,52.528893],"type":"Point"}
}