{
  "type": "Feature",
  "properties": {
    "iso:country":"DE",
    "sg:address":"Karlumer Str. 4",
    "sg:city":"Achtrup",
    "sg:phone":"+49 4662/2436",
    "sg:postcode":"25917",
    "sg:province":"Schleswig-Holstein",
    "wof:name":"Lorenz Boyschau",
    "wof:placetype":"venue"
},
  "geometry": {"coordinates":[9.024443,54.790592],"type":"Point"}
}