{
  "type": "Feature",
  "properties": {
    "iso:country":"DE",
    "sg:address":"Steindamm 87",
    "sg:city":"Hamburg",
    "sg:phone":"+49 40/2840640",
    "sg:postcode":"20099",
    "sg:province":"Hamburg",
    "wof:name":"Ic & C Immobilien Consulting Und Conception Gmbh",
    "wof:placetype":"venue"
},
  "geometry": {"coordinates":[10.0183773041,53.5564575195],"type":"Point"}
}