{
  "type": "Feature",
  "properties": {
    "iso:country":"DE",
    "sg:address":"Sommeracher Str. 33",
    "sg:city":"Volkach",
    "sg:phone":"+49 9381/84820",
    "sg:postcode":"97332",
    "sg:province":"Bayern",
    "wof:name":"Stephan Leuxner Architekt",
    "wof:placetype":"venue"
},
  "geometry": {"coordinates":[10.227369,49.860416],"type":"Point"}
}