{
  "type": "Feature",
  "properties": {
    "iso:country":"DE",
    "sg:address":"Obere Frauenstr. 9-17",
    "sg:city":"Bad Hersfeld",
    "sg:phone":"+49 6621/3035",
    "sg:postcode":"36251",
    "sg:province":"Hessen",
    "wof:name":"Karl Koch Gmbh",
    "wof:placetype":"venue"
},
  "geometry": {"coordinates":[9.7050886154,50.8693313599],"type":"Point"}
}