{
  "type": "Feature",
  "properties": {
    "iso:country":"DE",
    "sg:address":"Maarstr. 25",
    "sg:city":"Troisdorf",
    "sg:phone":"+49 2241/42714",
    "sg:postcode":"53842",
    "sg:province":"Nordrhein-Westfalen",
    "wof:name":"Josef Schn\u00fcttgen Gmbh & Co. Kg",
    "wof:placetype":"venue"
},
  "geometry": {"coordinates":[7.11075,50.83519],"type":"Point"}
}