{
  "type": "Feature",
  "properties": {
    "iso:country":"DE",
    "sg:address":"H\u00f6seler Str. 23",
    "sg:city":"Heiligenhaus",
    "sg:phone":"+49 2056/3330",
    "sg:postcode":"42579",
    "sg:province":"Nordrhein-Westfalen",
    "wof:name":"Dachdeckerei Andreas Lilienthal Gmbh",
    "wof:placetype":"venue"
},
  "geometry": {"coordinates":[6.951392,51.325413],"type":"Point"}
}