{
  "type": "Feature",
  "properties": {
    "iso:country":"DE",
    "sg:address":"Jabacher Str. 125",
    "sg:city":"Lebach",
    "sg:phone":"+49 4968/812031",
    "sg:postcode":"66822",
    "sg:province":"Saarland",
    "wof:name":"Bauer Handels Gmbh",
    "wof:placetype":"venue"
},
  "geometry": {"coordinates":[6.891077,49.405579],"type":"Point"}
}