{
  "type": "Feature",
  "properties": {
    "iso:country":"DE",
    "sg:address":"Karither Str. 29",
    "sg:city":"Gommern",
    "sg:phone":"+49 39200/52081",
    "sg:postcode":"39245",
    "sg:province":"Sachsen-Anhalt",
    "wof:name":"Floristik 99 Gmbh",
    "wof:placetype":"venue"
},
  "geometry": {"coordinates":[11.829428,52.074333],"type":"Point"}
}