{
  "type": "Feature",
  "properties": {
    "iso:country":"DE",
    "sg:address":"Bismarckstr. 5",
    "sg:city":"Bebra",
    "sg:phone":"+49 6622/919575",
    "sg:postcode":"36179",
    "sg:province":"Hessen",
    "wof:name":"Heinrich Funk Gmbh",
    "wof:placetype":"venue"
},
  "geometry": {"coordinates":[9.7942733765,50.9701042175],"type":"Point"}
}