{
  "type": "Feature",
  "properties": {
    "iso:country":"DE",
    "sg:address":"Luisenstr. 19",
    "sg:city":"Frankfurt",
    "sg:phone":"+49 69/495683",
    "sg:postcode":"60316",
    "sg:province":"Hessen",
    "wof:name":"Hans Koster",
    "wof:placetype":"venue"
},
  "geometry": {"coordinates":[8.6962213516,50.1218414307],"type":"Point"}
}