{
  "type": "Feature",
  "properties": {
    "iso:country":"DE",
    "sg:address":"Martener Hellweg 35",
    "sg:city":"Dortmund",
    "sg:phone":"+49 231/171110",
    "sg:postcode":"44379",
    "sg:province":"Nordrhein-Westfalen",
    "wof:name":"Alfa M\u00f6bel Vertriebs Gmbh",
    "wof:placetype":"venue"
},
  "geometry": {"coordinates":[7.399383,51.504776],"type":"Point"}
}