{
  "type": "Feature",
  "properties": {
    "iso:country":"DE",
    "sg:address":"Hallwanger Weg",
    "sg:city":"Dornstetten",
    "sg:phone":"+49 7443/6730",
    "sg:postcode":"72280",
    "sg:province":"Baden-W\u00fcrttemberg",
    "wof:name":"H\u00f6hencamping K\u00f6nigskanzel",
    "wof:placetype":"venue"
},
  "geometry": {"coordinates":[8.499525,48.472946],"type":"Point"}
}