{
  "type": "Feature",
  "properties": {
    "iso:country":"DE",
    "sg:address":"Ebersbach 8",
    "sg:city":"Kleinschmalkalden",
    "sg:phone":"+49 36849/20668",
    "sg:postcode":"98593",
    "sg:province":"Th\u00fcringen",
    "wof:name":"Horst Sch\u00fcssler",
    "wof:placetype":"venue"
},
  "geometry": {"coordinates":[10.47725,50.799068],"type":"Point"}
}