{
  "type": "Feature",
  "properties": {
    "iso:country":"DE",
    "sg:address":"Passauer Str. 9",
    "sg:city":"Bad Birnbach",
    "sg:phone":"+49 8563/871",
    "sg:postcode":"84364",
    "sg:province":"Bayern",
    "wof:name":"Gasthof Wasner",
    "wof:placetype":"venue"
},
  "geometry": {"coordinates":[13.0943470001,48.4419975281],"type":"Point"}
}