{
  "type": "Feature",
  "properties": {
    "iso:country":"DE",
    "sg:address":"Hauptstr. 22",
    "sg:city":"Hochstadt",
    "sg:phone":"+49 9574/80366",
    "sg:postcode":"96272",
    "sg:province":"Bayern",
    "wof:name":"A. S\u00fcnkel",
    "wof:placetype":"venue"
},
  "geometry": {"coordinates":[11.172668457,50.1503677368],"type":"Point"}
}