{
  "type": "Feature",
  "properties": {
    "iso:country":"DE",
    "sg:address":"Veit-Sto\u00df-Str. 20",
    "sg:city":"M\u00fcnnerstadt",
    "sg:phone":"+49 9733/4370",
    "sg:postcode":"97702",
    "sg:province":"Bayern",
    "wof:name":"Fritz Matschiowalli",
    "wof:placetype":"venue"
},
  "geometry": {"coordinates":[10.1938762665,50.2475471497],"type":"Point"}
}