{
  "type": "Feature",
  "properties": {
    "iso:country":"DE",
    "sg:address":"Neue Str. 2",
    "sg:city":"Wehretal",
    "sg:phone":"+49 5658/8315",
    "sg:postcode":"37287",
    "sg:province":"Hessen",
    "wof:name":"S. Schmidt Hochbau Gmbh",
    "wof:placetype":"venue"
},
  "geometry": {"coordinates":[9.997326,51.151993],"type":"Point"}
}