{
  "type": "Feature",
  "properties": {
    "iso:country":"DE",
    "sg:address":"Schlo\u00dfstr. 6",
    "sg:city":"J\u00f6\u00dfnitz",
    "sg:phone":"+49 3741/521695",
    "sg:postcode":"08547",
    "sg:province":"Sachsen",
    "wof:name":"J\u00f6rg Schmidt",
    "wof:placetype":"venue"
},
  "geometry": {"coordinates":[12.1368713379,50.5432853699],"type":"Point"}
}