{
  "type": "Feature",
  "properties": {
    "iso:country":"DE",
    "sg:address":"Neudorfer Str. 113",
    "sg:city":"Duisburg",
    "sg:phone":"+49 4920/3359039",
    "sg:postcode":"47057",
    "sg:province":"Nordrhein-Westfalen",
    "wof:name":"Heiko Kraftfahrzeugzubeh\u00d6r Gmbh",
    "wof:placetype":"venue"
},
  "geometry": {"coordinates":[6.7794761658,51.4266777039],"type":"Point"}
}