{
  "type": "Feature",
  "properties": {
    "iso:country":"DE",
    "sg:address":"Eichelh\u00e4herweg 17",
    "sg:city":"Hamm",
    "sg:phone":"+49 2381/983820",
    "sg:postcode":"59071",
    "sg:province":"Nordrhein-Westfalen",
    "wof:name":"Kaha Systemtechnik Hanczewski",
    "wof:placetype":"venue"
},
  "geometry": {"coordinates":[7.8659582138,51.6891975403],"type":"Point"}
}