{
  "type": "Feature",
  "properties": {
    "iso:country":"DE",
    "sg:address":"Poststr. 59",
    "sg:city":"Velbert",
    "sg:phone":"+49 2051/52569",
    "sg:postcode":"42549",
    "sg:province":"Nordrhein-Westfalen",
    "wof:name":"E. Hasselbeck",
    "wof:placetype":"venue"
},
  "geometry": {"coordinates":[7.0390729904,51.3384590149],"type":"Point"}
}