{
  "type": "Feature",
  "properties": {
    "iso:country":"DE",
    "sg:address":"Am Kurgarten",
    "sg:city":"M\u00f6lln",
    "sg:phone":"+49 4542/3930",
    "sg:postcode":"23879",
    "sg:province":"Schleswig-Holstein",
    "wof:name":"Parkhotel",
    "wof:placetype":"venue"
},
  "geometry": {"coordinates":[10.6894607544,53.6252975464],"type":"Point"}
}