{
  "type": "Feature",
  "properties": {
    "iso:country":"DE",
    "sg:address":"Welpe 5",
    "sg:city":"Vechta",
    "sg:phone":"+49 4441/910078",
    "sg:postcode":"49377",
    "sg:province":"Niedersachsen",
    "wof:name":"Active Golfer Handels Gmbh",
    "wof:placetype":"venue"
},
  "geometry": {"coordinates":[8.3018884659,52.7139587402],"type":"Point"}
}