{
  "type": "Feature",
  "properties": {
    "iso:country":"DE",
    "sg:address":"Wildhagen 7",
    "sg:city":"Bielefeld",
    "sg:phone":"+49 521/102988",
    "sg:postcode":"33619",
    "sg:province":"Nordrhein-Westfalen",
    "wof:name":"Dietzel & Hoff Gmbh",
    "wof:placetype":"venue"
},
  "geometry": {"coordinates":[8.4800720215,52.0555839539],"type":"Point"}
}