{
  "type": "Feature",
  "properties": {
    "iso:country":"DE",
    "sg:address":"Feldstr. 41",
    "sg:city":"Wei\u00dfwasser",
    "sg:phone":"+49 3576/241107",
    "sg:postcode":"02943",
    "sg:province":"Sachsen",
    "wof:name":"Konietzky Verwaltungs Gmbh",
    "wof:placetype":"venue"
},
  "geometry": {"coordinates":[14.610409,51.509892],"type":"Point"}
}