{
  "type": "Feature",
  "properties": {
    "iso:country":"DE",
    "sg:address":"Am Bahndamm 2",
    "sg:city":"Seligenstadt",
    "sg:phone":"+49 6182/89040",
    "sg:postcode":"63500",
    "sg:province":"Hessen",
    "wof:name":"Zweckverband Wasserversorgung Stadt Und Kreis Offenbach",
    "wof:placetype":"venue"
},
  "geometry": {"coordinates":[8.9676961899,50.0434150696],"type":"Point"}
}