{
  "type": "Feature",
  "properties": {
    "iso:country":"DE",
    "sg:address":"Bahnhofstr. 4",
    "sg:city":"Welden",
    "sg:phone":"+49 8293/6449",
    "sg:postcode":"86465",
    "sg:province":"Bayern",
    "wof:name":"Veros Optik Und Schmuck Verwaltungs- Gmbh",
    "wof:placetype":"venue"
},
  "geometry": {"coordinates":[10.659108,48.456779],"type":"Point"}
}