{
  "type": "Feature",
  "properties": {
    "iso:country":"DE",
    "sg:address":"Eduard-Mann-Str. 7",
    "sg:city":"Ebertsheim",
    "sg:phone":"+49 6359/82542",
    "sg:postcode":"67280",
    "sg:province":"Rheinland-Pfalz",
    "wof:name":"Technologie Und \u00d6kologiebetr. Ebertsheim Grundst\u00fccks-",
    "wof:placetype":"venue"
},
  "geometry": {"coordinates":[8.1100978851,49.5663375854],"type":"Point"}
}