{
  "type": "Feature",
  "properties": {
    "iso:country":"DE",
    "sg:address":"Holl\u00e4ndische Str. 142",
    "sg:city":"Kassel",
    "sg:phone":"+49 561/9893813",
    "sg:postcode":"34127",
    "sg:province":"Hessen",
    "wof:name":"Aral-tankstelle",
    "wof:placetype":"venue"
},
  "geometry": {"coordinates":[9.4954252243,51.3339157104],"type":"Point"}
}