{
  "type": "Feature",
  "properties": {
    "iso:country":"DE",
    "sg:address":"Berliner Str. 113",
    "sg:city":"Clausthal-Zellerfeld",
    "sg:phone":"+49 5323/3234",
    "sg:postcode":"38678",
    "sg:province":"Niedersachsen",
    "wof:name":"G. Und K. Kuhfu\u00df",
    "wof:placetype":"venue"
},
  "geometry": {"coordinates":[10.3283119202,51.8064880371],"type":"Point"}
}