{
  "type": "Feature",
  "properties": {
    "iso:country":"DE",
    "sg:address":"Schweriner Str. 25",
    "sg:city":"Hamburg",
    "sg:phone":"+49 40/6774429",
    "sg:postcode":"22143",
    "sg:province":"Hamburg",
    "wof:name":"Paul Rosenbaum Gmbh",
    "wof:placetype":"venue"
},
  "geometry": {"coordinates":[10.1608228683,53.6051368713],"type":"Point"}
}