{
  "type": "Feature",
  "properties": {
    "iso:country":"DE",
    "sg:address":"Donnerstedter Weg 4",
    "sg:city":"Bremen",
    "sg:postcode":"28277",
    "sg:province":"Bremen",
    "wof:name":"Truck & Pack Dienstleistungsges. Mbh",
    "wof:placetype":"venue"
},
  "geometry": {"coordinates":[8.8205814362,53.0272293091],"type":"Point"}
}