{
  "type": "Feature",
  "properties": {
    "iso:country":"DE",
    "sg:address":"Bahnhofstr. 15",
    "sg:city":"Geislingen",
    "sg:phone":"+49 7331/43412",
    "sg:postcode":"73312",
    "sg:province":"Baden-W\u00fcrttemberg",
    "wof:name":"Hans G. Buck",
    "wof:placetype":"venue"
},
  "geometry": {"coordinates":[9.8423986435,48.6168899536],"type":"Point"}
}