{
  "type": "Feature",
  "properties": {
    "iso:country":"DE",
    "sg:address":"Erlenstr. 21",
    "sg:city":"Obersontheim",
    "sg:phone":"+49 7973/5192",
    "sg:postcode":"74423",
    "sg:province":"Baden-W\u00fcrttemberg",
    "wof:name":"Karl Lehnert",
    "wof:placetype":"venue"
},
  "geometry": {"coordinates":[9.861271,49.065617],"type":"Point"}
}