{
  "type": "Feature",
  "properties": {
    "iso:country":"DE",
    "sg:address":"Oelgartenstr. 18",
    "sg:city":"Sankt Augustin",
    "sg:phone":"+49 2241/332056",
    "sg:postcode":"53757",
    "sg:province":"Nordrhein-Westfalen",
    "wof:name":"Hubert Kramer Gmbh",
    "wof:placetype":"venue"
},
  "geometry": {"coordinates":[7.2250509262,50.7701721191],"type":"Point"}
}