{
  "type": "Feature",
  "properties": {
    "iso:country":"DE",
    "sg:address":"Am Massenberger Kamp 42",
    "sg:city":"D\u00fcsseldorf",
    "sg:phone":"+49 211/7597973",
    "sg:postcode":"40589",
    "sg:province":"Nordrhein-Westfalen",
    "wof:name":"Eugen Trockel Steuerberater",
    "wof:placetype":"venue"
},
  "geometry": {"coordinates":[6.8213038445,51.1811676025],"type":"Point"}
}