{
  "type": "Feature",
  "properties": {
    "iso:country":"DE",
    "sg:address":"Philipp-Reis-Str. 7",
    "sg:city":"Dreieich",
    "sg:postcode":"63303",
    "sg:province":"Hessen",
    "wof:name":"Enterprise Computer Technology Gmbh",
    "wof:placetype":"venue"
},
  "geometry": {"coordinates":[8.7080955505,50.031162262],"type":"Point"}
}