{
  "type": "Feature",
  "properties": {
    "iso:country":"DE",
    "sg:address":"S\u00fcderstr. 199",
    "sg:city":"Hamburg",
    "sg:postcode":"20537",
    "sg:province":"Hamburg",
    "wof:name":"Exporient Hamburg Gmbh",
    "wof:placetype":"venue"
},
  "geometry": {"coordinates":[10.044732,53.548515],"type":"Point"}
}