{
  "type": "Feature",
  "properties": {
    "iso:country":"DE",
    "sg:address":"Fahreschweg 38",
    "sg:city":"B\u00fcnde",
    "sg:postcode":"32257",
    "sg:province":"Nordrhein-Westfalen",
    "wof:name":"Mobil Guard Gmbh",
    "wof:placetype":"venue"
},
  "geometry": {"coordinates":[8.5863132477,52.229839325],"type":"Point"}
}