{
  "type": "Feature",
  "properties": {
    "iso:country":"DE",
    "sg:address":"Weiherstr. 3",
    "sg:city":"Monschau",
    "sg:phone":"+49 4924/722305",
    "sg:postcode":"52156",
    "sg:province":"Nordrhein-Westfalen",
    "wof:name":"Erich Und Renate Braun",
    "wof:placetype":"venue"
},
  "geometry": {"coordinates":[6.253693,50.534412],"type":"Point"}
}