{
  "type": "Feature",
  "properties": {
    "iso:country":"DE",
    "sg:address":"Bahnhofstr. 4",
    "sg:city":"Wenzenbach",
    "sg:phone":"+49 9407/2885",
    "sg:postcode":"93173",
    "sg:province":"Bayern",
    "wof:name":"Aktiv-markt Dirnberger",
    "wof:placetype":"venue"
},
  "geometry": {"coordinates":[12.1954374313,49.0754585266],"type":"Point"}
}