{
  "type": "Feature",
  "properties": {
    "iso:country":"DE",
    "sg:address":"Zedernstr. 49",
    "sg:city":"Lorsch",
    "sg:phone":"+49 6251/588970",
    "sg:postcode":"64653",
    "sg:province":"Hessen",
    "wof:name":"Christa Kumpf",
    "wof:placetype":"venue"
},
  "geometry": {"coordinates":[8.5615758896,49.6420516968],"type":"Point"}
}