{
  "type": "Feature",
  "properties": {
    "iso:country":"DE",
    "sg:address":"Orankestr.88",
    "sg:city":"Berlin",
    "sg:phone":"+49 30",
    "sg:postcode":"13053",
    "sg:province":"Berlin",
    "wof:name":"Begede",
    "wof:placetype":"venue"
},
  "geometry": {"coordinates":[13.489061,52.544758],"type":"Point"}
}