{
  "type": "Feature",
  "properties": {
    "iso:country":"DE",
    "sg:address":"Nordh\u00e4user Str. 72",
    "sg:city":"Bleicherode",
    "sg:postcode":"99752",
    "sg:province":"Th\u00fcringen",
    "wof:name":"Aldi Gmbh & Co. Kg",
    "wof:placetype":"venue"
},
  "geometry": {"coordinates":[10.5894927979,51.4491386414],"type":"Point"}
}