{
  "type": "Feature",
  "properties": {
    "iso:country":"DE",
    "sg:address":"Salzmatten 12",
    "sg:city":"Sulzburg",
    "sg:phone":"+49 7634/2959",
    "sg:postcode":"79295",
    "sg:province":"Baden-W\u00fcrttemberg",
    "wof:name":"Hans Werner Hetzel Handelsvertretung",
    "wof:placetype":"venue"
},
  "geometry": {"coordinates":[7.7046480179,47.845413208],"type":"Point"}
}