{
  "type": "Feature",
  "properties": {
    "iso:country":"DE",
    "sg:address":"Gr\u00fcner Weg 14",
    "sg:city":"Rosbach",
    "sg:phone":"+49 6003/464",
    "sg:postcode":"61191",
    "sg:province":"Hessen",
    "wof:name":"H. J. Lausche Rechtsanwalt Und Notar",
    "wof:placetype":"venue"
},
  "geometry": {"coordinates":[8.6848506927,50.3072090149],"type":"Point"}
}