{
  "type": "Feature",
  "properties": {
    "iso:country":"DE",
    "sg:address":"Vorfeldweg 16",
    "sg:city":"Meinersen",
    "sg:phone":"+49 5372/7710",
    "sg:postcode":"38536",
    "sg:province":"Niedersachsen",
    "wof:name":"H. Und B. Ulbrich",
    "wof:placetype":"venue"
},
  "geometry": {"coordinates":[10.3568067551,52.4702606201],"type":"Point"}
}