{
  "type": "Feature",
  "properties": {
    "iso:country":"DE",
    "sg:address":"Luisenstr. 6",
    "sg:city":"Badenweiler",
    "sg:phone":"+49 7632/254",
    "sg:postcode":"79410",
    "sg:province":"Baden-W\u00fcrttemberg",
    "wof:name":"Markgr\u00e4fler Winzerstube",
    "wof:placetype":"venue"
},
  "geometry": {"coordinates":[7.6734728813,47.8017120361],"type":"Point"}
}