{
  "type": "Feature",
  "properties": {
    "iso:country":"DE",
    "sg:address":"Thomas-M\u00fcntzer-Str. 33",
    "sg:city":"Schkeuditz",
    "sg:phone":"+49 34204/60381",
    "sg:postcode":"04435",
    "sg:province":"Sachsen",
    "wof:name":"Kurt Schlange",
    "wof:placetype":"venue"
},
  "geometry": {"coordinates":[12.189651,51.393772],"type":"Point"}
}