{
  "type": "Feature",
  "properties": {
    "iso:country":"DE",
    "sg:address":"Hauptstr. 106",
    "sg:city":"Auerbach",
    "sg:phone":"+49 3721/30966",
    "sg:postcode":"09392",
    "sg:province":"Sachsen",
    "wof:name":"Gerhard Mehlhorn",
    "wof:placetype":"venue"
},
  "geometry": {"coordinates":[12.9144525528,50.6858863831],"type":"Point"}
}