{
  "type": "Feature",
  "properties": {
    "iso:country":"DE",
    "sg:address":"Haydnstr. 39",
    "sg:city":"Salzgitter",
    "sg:phone":"+49 5341/61339",
    "sg:postcode":"38226",
    "sg:province":"Niedersachsen",
    "wof:name":"Hans-joachim Gr\u00fcttner",
    "wof:placetype":"venue"
},
  "geometry": {"coordinates":[10.3249874115,52.1660804749],"type":"Point"}
}