{
  "type": "Feature",
  "properties": {
    "iso:country":"DE",
    "sg:address":"Hauptstr. 150",
    "sg:city":"Bendorf",
    "sg:phone":"+49 2622/2145",
    "sg:postcode":"56170",
    "sg:province":"Rheinland-Pfalz",
    "wof:name":"Grubs Imbi\u00df",
    "wof:placetype":"venue"
},
  "geometry": {"coordinates":[7.5721101761,50.425819397],"type":"Point"}
}