{
  "type": "Feature",
  "properties": {
    "iso:country":"DE",
    "sg:address":"Pfarrweg 11",
    "sg:city":"Bruckm\u00fchl",
    "sg:phone":"+49 8062/6841",
    "sg:postcode":"83052",
    "sg:province":"Bayern",
    "wof:name":"Brigitte Huber",
    "wof:placetype":"venue"
},
  "geometry": {"coordinates":[11.917584,47.883385],"type":"Point"}
}