{
  "type": "Feature",
  "properties": {
    "iso:country":"DE",
    "sg:address":"Im Langreh 14",
    "sg:city":"Bodenheim",
    "sg:phone":"+49 6135/4409",
    "sg:postcode":"55294",
    "sg:province":"Rheinland-Pfalz",
    "wof:name":"Horst Koch",
    "wof:placetype":"venue"
},
  "geometry": {"coordinates":[8.302756,49.92675],"type":"Point"}
}