{
  "type": "Feature",
  "properties": {
    "iso:country":"DE",
    "sg:address":"Heinrich-Heine-Str. 16",
    "sg:city":"Weiterstadt",
    "sg:phone":"+49 6150/51920",
    "sg:postcode":"64331",
    "sg:province":"Hessen",
    "wof:name":"Wilfried Kunz",
    "wof:placetype":"venue"
},
  "geometry": {"coordinates":[8.581501,49.927368],"type":"Point"}
}