{
  "type": "Feature",
  "properties": {
    "iso:country":"DE",
    "sg:address":"Gebr\u00fcder-Grimm-Str. 11",
    "sg:city":"Rheinbreitbach",
    "sg:phone":"+49 2224/4632",
    "sg:postcode":"53619",
    "sg:province":"Rheinland-Pfalz",
    "wof:name":"Chr. Rechmann Heissmangel",
    "wof:placetype":"venue"
},
  "geometry": {"coordinates":[7.2335448265,50.6220436096],"type":"Point"}
}