{
  "type": "Feature",
  "properties": {
    "iso:country":"DE",
    "sg:address":"Hauptstr. 36-40",
    "sg:city":"K\u00fcnzelsau",
    "sg:phone":"+49 7940/91660",
    "sg:postcode":"74653",
    "sg:province":"Baden-W\u00fcrttemberg",
    "wof:name":"Elektro-stein Inh. R\u00fcdiger Stein",
    "wof:placetype":"venue"
},
  "geometry": {"coordinates":[9.6896247864,49.2791404724],"type":"Point"}
}