{
  "type": "Feature",
  "properties": {
    "iso:country":"DE",
    "sg:address":"Rader Heide 4",
    "sg:city":"Schwanewede",
    "sg:phone":"+49 421/682615",
    "sg:postcode":"28790",
    "sg:province":"Niedersachsen",
    "wof:name":"Harald Lilienthal Transporte Gmbh",
    "wof:placetype":"venue"
},
  "geometry": {"coordinates":[8.5425634384,53.2313613892],"type":"Point"}
}