{
  "type": "Feature",
  "properties": {
    "iso:country":"DE",
    "sg:address":"K\u00fcstergasse 1",
    "sg:city":"Solingen",
    "sg:phone":"+49 212/10220",
    "sg:postcode":"42651",
    "sg:province":"Nordrhein-Westfalen",
    "wof:name":"Valentino Speisecafe Gmbh",
    "wof:placetype":"venue"
},
  "geometry": {"coordinates":[7.084123,51.171417],"type":"Point"}
}