{
  "type": "Feature",
  "properties": {
    "iso:country":"DE",
    "sg:address":"Kolpingstr. 21",
    "sg:city":"Baesweiler",
    "sg:phone":"+49 2401/96061",
    "sg:postcode":"52499",
    "sg:province":"Nordrhein-Westfalen",
    "wof:name":"Wolfgang Scheen Immobilienmakler",
    "wof:placetype":"venue"
},
  "geometry": {"coordinates":[6.1891560555,50.9283828735],"type":"Point"}
}