{
  "type": "Feature",
  "properties": {
    "iso:country":"DE",
    "sg:address":"Taunusstr. 42",
    "sg:city":"N\u00fcrtingen",
    "sg:phone":"+49 7022/50856",
    "sg:postcode":"72622",
    "sg:province":"Baden-W\u00fcrttemberg",
    "wof:name":"W. M\u00fcller",
    "wof:placetype":"venue"
},
  "geometry": {"coordinates":[9.300169,48.620605],"type":"Point"}
}