{
  "type": "Feature",
  "properties": {
    "iso:country":"DE",
    "sg:address":"Louisenstr. 68",
    "sg:city":"Bad Homburg",
    "sg:phone":"+49 6172/683470",
    "sg:postcode":"61348",
    "sg:province":"Hessen",
    "wof:name":"Dr. Carola Ensslen Rechtsanw\u00e4ltin",
    "wof:placetype":"venue"
},
  "geometry": {"coordinates":[8.616484642,50.2270698547],"type":"Point"}
}