{
  "type": "Feature",
  "properties": {
    "iso:country":"DE",
    "sg:address":"Alsterdorfer Str. 40",
    "sg:city":"Hamburg",
    "sg:phone":"+49 40/5142300",
    "sg:postcode":"22299",
    "sg:province":"Hamburg",
    "wof:name":"Volker Rathje Architekt",
    "wof:placetype":"venue"
},
  "geometry": {"coordinates":[9.997347,53.596691],"type":"Point"}
}