{
  "type": "Feature",
  "properties": {
    "iso:country":"DE",
    "sg:address":"Mutzenb\u00fchlstr. 21",
    "sg:city":"Villingen-Schwenningen",
    "sg:phone":"+49 7720/31167",
    "sg:postcode":"78054",
    "sg:province":"Baden-W\u00fcrttemberg",
    "wof:name":"W. Und H. Z\u00f6hrlaut Schlo\u00dfbrauerei Haigerloch",
    "wof:placetype":"venue"
},
  "geometry": {"coordinates":[8.53473,48.067936],"type":"Point"}
}