{
  "type": "Feature",
  "properties": {
    "iso:country":"DE",
    "sg:address":"Ludwigstr. 52",
    "sg:city":"L\u00fcbbecke",
    "sg:phone":"+49 5741/9311",
    "sg:postcode":"32312",
    "sg:province":"Nordrhein-Westfalen",
    "wof:name":"Werner Schwab",
    "wof:placetype":"venue"
},
  "geometry": {"coordinates":[8.6058425903,52.3158340454],"type":"Point"}
}