{
  "type": "Feature",
  "properties": {
    "iso:country":"DE",
    "sg:address":"R\u00f6chlingstr. 12",
    "sg:city":"Haren",
    "sg:phone":"+49 5934/93210",
    "sg:postcode":"49733",
    "sg:province":"Niedersachsen",
    "wof:name":"Abbundzentrum Emsland Beteiligungs Gmbh",
    "wof:placetype":"venue"
},
  "geometry": {"coordinates":[7.131463,52.83411],"type":"Point"}
}