{
  "type": "Feature",
  "properties": {
    "iso:country":"DE",
    "sg:address":"Ketschendorfer Str. 102",
    "sg:city":"Coburg",
    "sg:phone":"+49 9561/10682",
    "sg:postcode":"96450",
    "sg:province":"Bayern",
    "wof:name":"Rudolf Wolf",
    "wof:placetype":"venue"
},
  "geometry": {"coordinates":[10.9719381332,50.2458381653],"type":"Point"}
}