{
  "type": "Feature",
  "properties": {
    "iso:country":"DE",
    "sg:address":"Burgstr. 19-25",
    "sg:city":"Leipzig",
    "sg:phone":"+49 341/9604507",
    "sg:postcode":"04109",
    "sg:province":"Sachsen",
    "wof:name":"Jack Wolfskin Shop",
    "wof:placetype":"venue"
},
  "geometry": {"coordinates":[12.373488,51.338028],"type":"Point"}
}