{
  "type": "Feature",
  "properties": {
    "iso:country":"DE",
    "sg:address":"Freiherr-vom-Stein-Str. 14",
    "sg:city":"Ginsheim-Gustavsburg",
    "sg:phone":"+49 6134/54353",
    "sg:postcode":"65462",
    "sg:province":"Hessen",
    "wof:name":"Willi Wallm\u00fcller",
    "wof:placetype":"venue"
},
  "geometry": {"coordinates":[8.3341159821,49.9975662231],"type":"Point"}
}