{
  "type": "Feature",
  "properties": {
    "iso:country":"DE",
    "sg:address":"Wedehorn 35",
    "sg:city":"Bassum",
    "sg:phone":"+49 4245/324",
    "sg:postcode":"27211",
    "sg:province":"Niedersachsen",
    "wof:name":"August Wiechmann",
    "wof:placetype":"venue"
},
  "geometry": {"coordinates":[8.718799,52.796436],"type":"Point"}
}