{
  "type": "Feature",
  "properties": {
    "iso:country":"DE",
    "sg:address":"Am Bu\u00dfnerberg 8",
    "sg:city":"Eschlkam",
    "sg:phone":"+49 9948/1674",
    "sg:postcode":"93458",
    "sg:province":"Bayern",
    "wof:name":"Augustin",
    "wof:placetype":"venue"
},
  "geometry": {"coordinates":[12.9377975464,49.3076782227],"type":"Point"}
}