{
  "type": "Feature",
  "properties": {
    "iso:country":"DE",
    "sg:address":"Im Bungert 13",
    "sg:city":"Wachtberg",
    "sg:phone":"+49 228/344826",
    "sg:postcode":"53343",
    "sg:province":"Nordrhein-Westfalen",
    "wof:name":"Bode Bedachungen Gmbh",
    "wof:placetype":"venue"
},
  "geometry": {"coordinates":[7.177807,50.643616],"type":"Point"}
}