{
  "type": "Feature",
  "properties": {
    "iso:country":"DE",
    "sg:address":"Hanseatenweg 10",
    "sg:city":"Hanstedt",
    "sg:phone":"+49 4184/1026",
    "sg:postcode":"21271",
    "sg:province":"Niedersachsen",
    "wof:name":"Anneliese Schultze Heilpraktikerin",
    "wof:placetype":"venue"
},
  "geometry": {"coordinates":[10.0117349625,53.2502288818],"type":"Point"}
}