{
  "type": "Feature",
  "properties": {
    "iso:country":"DE",
    "sg:address":"Thomas-M\u00fcntzer-Str. 5",
    "sg:city":"Weidenhain",
    "sg:phone":"+49 3421/711230",
    "sg:postcode":"04860",
    "sg:province":"Sachsen",
    "wof:name":"Innenausbau Akustik Kracht Gmbh",
    "wof:placetype":"venue"
},
  "geometry": {"coordinates":[12.849955,51.567188],"type":"Point"}
}