{
  "type": "Feature",
  "properties": {
    "iso:country":"DE",
    "sg:address":"Sigiswang 29",
    "sg:city":"Ofterschwang/Allg\u00e4u",
    "sg:phone":"+49 8321/81317",
    "sg:postcode":"87527",
    "sg:province":"Bayern",
    "wof:name":"Allg\u00e4u-alpen-ferienwohnungen, Landhaus Edelweiss",
    "wof:placetype":"venue"
},
  "geometry": {"coordinates":[10.2831296921,47.5125579834],"type":"Point"}
}