{
  "type": "Feature",
  "properties": {
    "iso:country":"DE",
    "sg:address":"Kantstr. 40",
    "sg:city":"W\u00fcrzburg",
    "sg:postcode":"97074",
    "sg:province":"Bayern",
    "wof:name":"Zigarrenkontor E. K.",
    "wof:placetype":"venue"
},
  "geometry": {"coordinates":[9.9435682297,49.7752075195],"type":"Point"}
}