{
  "type": "Feature",
  "properties": {
    "iso:country":"DE",
    "sg:address":"Giesensdorfer Str. 24",
    "sg:city":"Harmsdorf",
    "sg:phone":"+49 4541/3969",
    "sg:postcode":"23911",
    "sg:province":"Schleswig-Holstein",
    "wof:name":"Peter Wiesener",
    "wof:placetype":"venue"
},
  "geometry": {"coordinates":[10.722514,53.696545],"type":"Point"}
}