{
  "type": "Feature",
  "properties": {
    "iso:country":"DE",
    "sg:address":"Bergstr. 51",
    "sg:city":"Bottrop",
    "sg:phone":"+49 2041/686633",
    "sg:postcode":"46236",
    "sg:province":"Nordrhein-Westfalen",
    "wof:name":"I. Herrlich",
    "wof:placetype":"venue"
},
  "geometry": {"coordinates":[6.924571,51.514942],"type":"Point"}
}