{
  "type": "Feature",
  "properties": {
    "iso:country":"DE",
    "sg:address":"Roseggerstr. 50a",
    "sg:city":"Neuenhagen",
    "sg:postcode":"15366",
    "sg:province":"Brandenburg",
    "wof:name":"Icg Consulting Gmbh",
    "wof:placetype":"venue"
},
  "geometry": {"coordinates":[13.6820735931,52.5199241638],"type":"Point"}
}