{
  "type": "Feature",
  "properties": {
    "iso:country":"DE",
    "sg:address":"Am Vogelherd 2-4",
    "sg:city":"Berlin",
    "sg:postcode":"14055",
    "sg:province":"Berlin",
    "wof:name":"Twenty Five Gastronomie Und Handels Gmbh",
    "wof:placetype":"venue"
},
  "geometry": {"coordinates":[13.2680015564,52.498046875],"type":"Point"}
}