{
  "type": "Feature",
  "properties": {
    "iso:country":"DE",
    "sg:address":"Bahnhofstr. 23",
    "sg:city":"Warstein",
    "sg:phone":"+49 2902/7246",
    "sg:postcode":"59581",
    "sg:province":"Nordrhein-Westfalen",
    "wof:name":"Bernhard Heimann Elektroinst.",
    "wof:placetype":"venue"
},
  "geometry": {"coordinates":[8.337193,51.487061],"type":"Point"}
}