{
  "type": "Feature",
  "properties": {
    "iso:country":"DE",
    "sg:address":"Stra\u00dfe der Einheit 15",
    "sg:city":"Ortrand",
    "sg:phone":"+49 35755/51965",
    "sg:postcode":"01990",
    "sg:province":"Brandenburg",
    "wof:name":"N. Neunert",
    "wof:placetype":"venue"
},
  "geometry": {"coordinates":[13.7573060989,51.3772315979],"type":"Point"}
}