{
  "type": "Feature",
  "properties": {
    "iso:country":"DE",
    "sg:address":"Methweg 2",
    "sg:city":"K\u00f6ln",
    "sg:phone":"+49 221/174077",
    "sg:postcode":"50823",
    "sg:province":"Nordrhein-Westfalen",
    "wof:name":"E. Krupp Gmbh",
    "wof:placetype":"venue"
},
  "geometry": {"coordinates":[6.935919,50.95747],"type":"Point"}
}