{
  "type": "Feature",
  "properties": {
    "iso:country":"DE",
    "sg:address":"Friedrichstr. 32",
    "sg:city":"Friedrichshafen",
    "sg:phone":"+49 7541/38550",
    "sg:postcode":"88045",
    "sg:province":"Baden-W\u00fcrttemberg",
    "wof:name":"Hotel Schwanen",
    "wof:placetype":"venue"
},
  "geometry": {"coordinates":[9.4786882401,47.6518211365],"type":"Point"}
}