{
  "type": "Feature",
  "properties": {
    "iso:country":"DE",
    "sg:address":"Untere K\u00f6nigstr. 35",
    "sg:city":"Bamberg",
    "sg:phone":"+49 951/26371",
    "sg:postcode":"96052",
    "sg:province":"Bayern",
    "wof:name":"Bauer & Barbian",
    "wof:placetype":"venue"
},
  "geometry": {"coordinates":[10.8894300461,49.8976821899],"type":"Point"}
}