{
  "type": "Feature",
  "properties": {
    "iso:country":"DE",
    "sg:address":"Heinrich-Sch\u00fctz-Str 8",
    "sg:city":"Sindelfingen",
    "sg:phone":"+49 7031/93930",
    "sg:postcode":"71065",
    "sg:province":"Baden-W\u00fcrttemberg",
    "wof:name":"Dipl.-ing. H. Baumann Software Gmbh",
    "wof:placetype":"venue"
},
  "geometry": {"coordinates":[9.0182723999,48.7100219727],"type":"Point"}
}