{
  "type": "Feature",
  "properties": {
    "iso:country":"DE",
    "sg:address":"Queichstr. 4",
    "sg:city":"Siebeldingen",
    "sg:phone":"+49 6345/1564",
    "sg:postcode":"76833",
    "sg:province":"Rheinland-Pfalz",
    "wof:name":"G\u00fcnter Bollinger",
    "wof:placetype":"venue"
},
  "geometry": {"coordinates":[8.0518302917,49.2089385986],"type":"Point"}
}