{
  "type": "Feature",
  "properties": {
    "iso:country":"DE",
    "sg:address":"S\u00fcdmauer 54",
    "sg:city":"Bocholt",
    "sg:postcode":"46397",
    "sg:province":"Nordrhein-Westfalen",
    "wof:name":"M\u00fcller Vermietungs- Und",
    "wof:placetype":"venue"
},
  "geometry": {"coordinates":[6.6199297905,51.8385314941],"type":"Point"}
}