{
  "type": "Feature",
  "properties": {
    "iso:country":"DE",
    "sg:address":"Borngasse 8",
    "sg:city":"Kirtorf",
    "sg:phone":"+49 6635/461",
    "sg:postcode":"36320",
    "sg:province":"Hessen",
    "wof:name":"Karl Felsing",
    "wof:placetype":"venue"
},
  "geometry": {"coordinates":[9.132783,50.756607],"type":"Point"}
}