{
  "type": "Feature",
  "properties": {
    "iso:country":"DE",
    "sg:address":"Paulinenstr. 55",
    "sg:city":"Detmold",
    "sg:phone":"+49 5231/24431",
    "sg:postcode":"32756",
    "sg:province":"Nordrhein-Westfalen",
    "wof:name":"B\u00f6llinghaus Augenoptiker",
    "wof:placetype":"venue"
},
  "geometry": {"coordinates":[8.8752326965,51.9385986328],"type":"Point"}
}