{
  "type": "Feature",
  "properties": {
    "iso:country":"DE",
    "sg:address":"Dammstr. 4",
    "sg:city":"Merseburg",
    "sg:phone":"+49 3461/213421",
    "sg:postcode":"06217",
    "sg:province":"Sachsen-Anhalt",
    "wof:name":"Geigenm\u00fcller",
    "wof:placetype":"venue"
},
  "geometry": {"coordinates":[11.995171,51.357304],"type":"Point"}
}