{
  "type": "Feature",
  "properties": {
    "iso:country":"DE",
    "sg:address":"Unterer Markt 6 a",
    "sg:city":"Nabburg",
    "sg:phone":"+49 9433/312",
    "sg:postcode":"92507",
    "sg:province":"Bayern",
    "wof:name":"Reinhard H\u00f6sl Rechtsanwalt",
    "wof:placetype":"venue"
},
  "geometry": {"coordinates":[12.1808986664,49.4530143738],"type":"Point"}
}