{
  "type": "Feature",
  "properties": {
    "iso:country":"DE",
    "sg:address":"Furth Poststr. 10",
    "sg:city":"Dietersburg",
    "sg:phone":"+49 8726/96030",
    "sg:postcode":"84378",
    "sg:province":"Bayern",
    "wof:name":"Reiter Agrartechnik",
    "wof:placetype":"venue"
},
  "geometry": {"coordinates":[12.928496,48.493813],"type":"Point"}
}