{
  "type": "Feature",
  "properties": {
    "iso:country":"DE",
    "sg:address":"Berliner Chaussee 5",
    "sg:city":"Genthin",
    "sg:phone":"+49 3933/3805",
    "sg:postcode":"39307",
    "sg:province":"Sachsen-Anhalt",
    "wof:name":"W. Und E. Titze",
    "wof:placetype":"venue"
},
  "geometry": {"coordinates":[12.164198,52.406055],"type":"Point"}
}