{
  "type": "Feature",
  "properties": {
    "iso:country":"DE",
    "sg:address":"Z\u00e4hringer Str. 12",
    "sg:city":"St. Peter",
    "sg:phone":"+49 7660/1555",
    "sg:postcode":"79271",
    "sg:province":"Baden-W\u00fcrttemberg",
    "wof:name":"Z\u00e4hringer-apotheke",
    "wof:placetype":"venue"
},
  "geometry": {"coordinates":[8.0342,48.015709],"type":"Point"}
}