{
  "type": "Feature",
  "properties": {
    "iso:country":"DE",
    "sg:address":"Vor dem Hummelsholz 19",
    "sg:city":"Villingen-Schwenningen",
    "sg:postcode":"78056",
    "sg:province":"Baden-W\u00fcrttemberg",
    "wof:name":"I. Schachtmann",
    "wof:placetype":"venue"
},
  "geometry": {"coordinates":[8.5394430161,48.0755882263],"type":"Point"}
}