{
  "type": "Feature",
  "properties": {
    "iso:country":"DE",
    "sg:address":"Hauptstr. 33",
    "sg:city":"Werneck",
    "sg:phone":"+49 9722/2576",
    "sg:postcode":"97440",
    "sg:province":"Bayern",
    "wof:name":"Georg G\u00f6b",
    "wof:placetype":"venue"
},
  "geometry": {"coordinates":[10.079518,49.942642],"type":"Point"}
}