{
  "type": "Feature",
  "properties": {
    "iso:country":"DE",
    "sg:address":"Rie\u00dferseestr. 51",
    "sg:city":"Garmisch-Partenkirchen",
    "sg:phone":"+49 8821/57495",
    "sg:postcode":"82467",
    "sg:province":"Bayern",
    "wof:name":"Hans Und Klementia Langmatz Stiftung",
    "wof:placetype":"venue"
},
  "geometry": {"coordinates":[11.0767593384,47.4842643738],"type":"Point"}
}