{
  "type": "Feature",
  "properties": {
    "iso:country":"DE",
    "sg:address":"Pfingstweide 2",
    "sg:city":"Friedberg",
    "sg:phone":"+49 6031/18549",
    "sg:postcode":"61169",
    "sg:province":"Hessen",
    "wof:name":"Pizzeria La Rosa",
    "wof:placetype":"venue"
},
  "geometry": {"coordinates":[8.7485294342,50.3170051575],"type":"Point"}
}