{
  "type": "Feature",
  "properties": {
    "iso:country":"DE",
    "sg:address":"Ulmer Str. 2",
    "sg:city":"Diedorf",
    "sg:phone":"+49 821/483031",
    "sg:postcode":"86420",
    "sg:province":"Bayern",
    "wof:name":"Lorenz Nu\u00dfbaum",
    "wof:placetype":"venue"
},
  "geometry": {"coordinates":[10.776432991,48.3537635803],"type":"Point"}
}