{
  "type": "Feature",
  "properties": {
    "iso:country":"DE",
    "sg:address":"Gerhart-Hauptmann-Str. 13",
    "sg:city":"Erfurt",
    "sg:phone":"+49 361/3460132",
    "sg:postcode":"99096",
    "sg:province":"Th\u00fcringen",
    "wof:name":"Prof. Dr. Med. Martin Spr\u00f6\u00dfig",
    "wof:placetype":"venue"
},
  "geometry": {"coordinates":[11.025886,50.963123],"type":"Point"}
}