{
  "type": "Feature",
  "properties": {
    "iso:country":"DE",
    "sg:address":"Bismarckstr. 4",
    "sg:city":"Jockgrim",
    "sg:phone":"+49 7271/52835",
    "sg:postcode":"76751",
    "sg:province":"Rheinland-Pfalz",
    "wof:name":"Uwe Fischer",
    "wof:placetype":"venue"
},
  "geometry": {"coordinates":[8.270742,49.092361],"type":"Point"}
}