{
  "type": "Feature",
  "properties": {
    "iso:country":"DE",
    "sg:address":"Gertigstr. 22",
    "sg:city":"Hamburg",
    "sg:postcode":"22303",
    "sg:province":"Hamburg",
    "wof:name":"Mol-tex Norbert Tiedemann Ohg",
    "wof:placetype":"venue"
},
  "geometry": {"coordinates":[10.0144100189,53.5817108154],"type":"Point"}
}