{
  "type": "Feature",
  "properties": {
    "iso:country":"DE",
    "sg:address":"Zschochersche Str. 97",
    "sg:city":"Leipzig",
    "sg:phone":"+49 341/4250425",
    "sg:postcode":"04229",
    "sg:province":"Sachsen",
    "wof:name":"Foto-rechtnitz Gmbh",
    "wof:placetype":"venue"
},
  "geometry": {"coordinates":[12.3309745789,51.3208808899],"type":"Point"}
}