{
  "type": "Feature",
  "properties": {
    "iso:country":"DE",
    "sg:address":"Am Stock 20",
    "sg:city":"Reiskirchen",
    "sg:phone":"+49 6408/96120",
    "sg:postcode":"35447",
    "sg:province":"Hessen",
    "wof:name":"Biomedico Gmbh",
    "wof:placetype":"venue"
},
  "geometry": {"coordinates":[8.830859,50.601948],"type":"Point"}
}