{
  "type": "Feature",
  "properties": {
    "iso:country":"DE",
    "sg:address":"Frauenstr. 9",
    "sg:city":"M\u00fcnchen",
    "sg:phone":"+49 89/2919550",
    "sg:postcode":"80469",
    "sg:province":"Bayern",
    "wof:name":"Buxs",
    "wof:placetype":"venue"
},
  "geometry": {"coordinates":[11.5778875351,48.1345672607],"type":"Point"}
}