{
  "type": "Feature",
  "properties": {
    "iso:country":"DE",
    "sg:address":"Provinzialstra\u00dfe 59",
    "sg:city":"Saarbr\u00fccken",
    "sg:phone":"+49 6893",
    "sg:postcode":"66130",
    "sg:province":"Saarland",
    "wof:name":"Homepage Der Fa. Parkett- Studio",
    "wof:placetype":"venue"
},
  "geometry": {"coordinates":[7.064607,49.19957],"type":"Point"}
}