{
  "type": "Feature",
  "properties": {
    "iso:country":"DE",
    "sg:address":"In der Burgweid 30",
    "sg:city":"Alsdorf",
    "sg:phone":"+49 2404/1703",
    "sg:postcode":"52477",
    "sg:province":"Nordrhein-Westfalen",
    "wof:name":"Helmut Neu",
    "wof:placetype":"venue"
},
  "geometry": {"coordinates":[6.165143,50.880501],"type":"Point"}
}