{
  "type": "Feature",
  "properties": {
    "iso:country":"DE",
    "sg:address":"Diedrichstrasse 7",
    "sg:city":"Kiel",
    "sg:postcode":"24143",
    "sg:province":"Schleswig-Holstein",
    "wof:name":"Nord-ostsee-bahn Gmbh",
    "wof:placetype":"venue"
},
  "geometry": {"coordinates":[10.1379957199,54.3008575439],"type":"Point"}
}