{
  "type": "Feature",
  "properties": {
    "iso:country":"DE",
    "sg:address":"G\u00fctbach",
    "sg:city":"Schrozberg",
    "sg:phone":"+49 7936/278",
    "sg:postcode":"74575",
    "sg:province":"Baden-W\u00fcrttemberg",
    "wof:name":"E. Ziegler",
    "wof:placetype":"venue"
},
  "geometry": {"coordinates":[9.896528244,49.3643417358],"type":"Point"}
}