{
  "type": "Feature",
  "properties": {
    "iso:country":"DE",
    "sg:address":"Mauerstr. 13",
    "sg:city":"Bielefeld",
    "sg:phone":"+49 521/173753",
    "sg:postcode":"33602",
    "sg:province":"Nordrhein-Westfalen",
    "wof:name":"Ristorante Pizzeria Da Donato",
    "wof:placetype":"venue"
},
  "geometry": {"coordinates":[8.5294008255,52.0221252441],"type":"Point"}
}