{
  "type": "Feature",
  "properties": {
    "iso:country":"DE",
    "sg:address":"Dorfstr. 18",
    "sg:city":"Sustrum",
    "sg:phone":"+49 5939/545",
    "sg:postcode":"49762",
    "sg:province":"Niedersachsen",
    "wof:name":"Hermann Hoppe",
    "wof:placetype":"venue"
},
  "geometry": {"coordinates":[7.21512,52.882801],"type":"Point"}
}