{
  "type": "Feature",
  "properties": {
    "iso:country":"DE",
    "sg:address":"Mittelstr. 59",
    "sg:city":"Barntrup",
    "sg:phone":"+49 5263/2154",
    "sg:postcode":"32683",
    "sg:province":"Nordrhein-Westfalen",
    "wof:name":"L. Jacob Sb-markt",
    "wof:placetype":"venue"
},
  "geometry": {"coordinates":[9.1087722778,51.9908370972],"type":"Point"}
}