{
  "type": "Feature",
  "properties": {
    "iso:country":"DE",
    "sg:address":"Dorfstr. 16",
    "sg:city":"Mehltheuer",
    "sg:phone":"+49 37431/3421",
    "sg:postcode":"08539",
    "sg:province":"Sachsen",
    "wof:name":"Dr. F. Jacob Tierarzt",
    "wof:placetype":"venue"
},
  "geometry": {"coordinates":[12.0307836533,50.5323295593],"type":"Point"}
}