{
  "type": "Feature",
  "properties": {
    "iso:country":"DE",
    "sg:address":"Kolpingstr. 11",
    "sg:city":"Hasel\u00fcnne",
    "sg:phone":"+49 5961/4051",
    "sg:postcode":"49740",
    "sg:province":"Niedersachsen",
    "wof:name":"Gastst\u00e4tte Kolpinghaus",
    "wof:placetype":"venue"
},
  "geometry": {"coordinates":[7.4884190559,52.6763534546],"type":"Point"}
}