{
  "type": "Feature",
  "properties": {
    "iso:country":"DE",
    "sg:address":"Born 22",
    "sg:city":"Br\u00fcggen",
    "sg:phone":"+49 2163/6076",
    "sg:postcode":"41379",
    "sg:province":"Nordrhein-Westfalen",
    "wof:name":"Am Transporte U. Speditions-gmbh",
    "wof:placetype":"venue"
},
  "geometry": {"coordinates":[6.2093148232,51.2440567017],"type":"Point"}
}