{
  "type": "Feature",
  "properties": {
    "iso:country":"DE",
    "sg:address":"Albrechtstr. 7",
    "sg:city":"Plattling",
    "sg:phone":"+49 9931/2242",
    "sg:postcode":"94447",
    "sg:province":"Bayern",
    "wof:name":"Franz Ernst",
    "wof:placetype":"venue"
},
  "geometry": {"coordinates":[12.8578090668,48.7852363586],"type":"Point"}
}