{
  "type": "Feature",
  "properties": {
    "iso:country":"DE",
    "sg:address":"Am Clarenhof 2",
    "sg:city":"K\u00f6ln",
    "sg:phone":"+49 2234/75421",
    "sg:postcode":"50859",
    "sg:province":"Nordrhein-Westfalen",
    "wof:name":"H. G\u00fcnther Buss",
    "wof:placetype":"venue"
},
  "geometry": {"coordinates":[6.8288049698,50.9373054504],"type":"Point"}
}