{
  "type": "Feature",
  "properties": {
    "iso:country":"DE",
    "sg:address":"Herkener Weg 8",
    "sg:city":"Rees",
    "sg:phone":"+49 2850/7624",
    "sg:postcode":"46459",
    "sg:province":"Nordrhein-Westfalen",
    "wof:name":"Franz Bontrup",
    "wof:placetype":"venue"
},
  "geometry": {"coordinates":[6.451572,51.789547],"type":"Point"}
}