{
  "type": "Feature",
  "properties": {
    "iso:country":"DE",
    "sg:address":"Gewerbestr. 1",
    "sg:city":"Dieburg",
    "sg:phone":"+49 6071/24130",
    "sg:postcode":"64807",
    "sg:province":"Hessen",
    "wof:name":"Players Inn",
    "wof:placetype":"venue"
},
  "geometry": {"coordinates":[8.8500556946,49.9089202881],"type":"Point"}
}