{
  "type": "Feature",
  "properties": {
    "iso:country":"DE",
    "sg:address":"H\u00f6ltenweg 105",
    "sg:city":"M\u00fcnster",
    "sg:phone":"+49 251/627370",
    "sg:postcode":"48155",
    "sg:province":"Nordrhein-Westfalen",
    "wof:name":"Ism-industrieservice Zweigniederlassung Der Firma",
    "wof:placetype":"venue"
},
  "geometry": {"coordinates":[7.651508,51.924271],"type":"Point"}
}