{
  "type": "Feature",
  "properties": {
    "iso:country":"DE",
    "sg:address":"Schlo\u00dfstr. 15",
    "sg:city":"Ludwigslust",
    "sg:phone":"+49 3874/4180",
    "sg:postcode":"19288",
    "sg:province":"Mecklenburg-Vorpommern",
    "wof:name":"Landhotel De Weimar Ludwiglust Wiesehahn Ohg",
    "wof:placetype":"venue"
},
  "geometry": {"coordinates":[11.4918441772,53.324256897],"type":"Point"}
}