{
  "type": "Feature",
  "properties": {
    "iso:country":"DE",
    "sg:address":"Am Kirchplatz 12",
    "sg:city":"B\u00f6sel",
    "sg:postcode":"26219",
    "sg:province":"Niedersachsen",
    "wof:name":"Vb Sachwert Gmbh",
    "wof:placetype":"venue"
},
  "geometry": {"coordinates":[7.953985,53.004765],"type":"Point"}
}