{
  "type": "Feature",
  "properties": {
    "iso:country":"DE",
    "sg:address":"Zietenstr. 6",
    "sg:city":"Oldenburg",
    "sg:phone":"+49 441/507032",
    "sg:postcode":"26131",
    "sg:province":"Niedersachsen",
    "wof:name":"Ev. Pfarramt Eversten-mitte",
    "wof:placetype":"venue"
},
  "geometry": {"coordinates":[8.1759853363,53.1311988831],"type":"Point"}
}