{
  "type": "Feature",
  "properties": {
    "iso:country":"DE",
    "sg:address":"Beethovenstr. 16",
    "sg:city":"St. Wendel",
    "sg:phone":"+49 6851/4066",
    "sg:postcode":"66606",
    "sg:province":"Saarland",
    "wof:name":"Staub Und Goergen Rechtsanw\u00e4lte",
    "wof:placetype":"venue"
},
  "geometry": {"coordinates":[7.1702690125,49.4646453857],"type":"Point"}
}