{
  "type": "Feature",
  "properties": {
    "iso:country":"DE",
    "sg:address":"Moosstr. 15",
    "sg:city":"Ismaning",
    "sg:phone":"+49 89/965877",
    "sg:postcode":"85737",
    "sg:province":"Bayern",
    "wof:name":"Gerhard Eigner",
    "wof:placetype":"venue"
},
  "geometry": {"coordinates":[11.721391,48.243103],"type":"Point"}
}