{
  "type": "Feature",
  "properties": {
    "iso:country":"DE",
    "sg:address":"Schliemannstr. 8",
    "sg:city":"Admannshagen-Bargeshagen",
    "sg:postcode":"18211",
    "sg:province":"Mecklenburg-Vorpommern",
    "wof:name":"Malerbetrieb H.-j. Meier Gmbh",
    "wof:placetype":"venue"
},
  "geometry": {"coordinates":[11.99834,54.113895],"type":"Point"}
}