{
  "type": "Feature",
  "properties": {
    "iso:country":"DE",
    "sg:address":"Schulstr. 17",
    "sg:city":"Bad W\u00f6rishofen",
    "sg:phone":"+49 8247/2766",
    "sg:postcode":"86825",
    "sg:province":"Bayern",
    "wof:name":"H. Scharpf",
    "wof:placetype":"venue"
},
  "geometry": {"coordinates":[10.5953912735,48.0029373169],"type":"Point"}
}