{
  "type": "Feature",
  "properties": {
    "iso:country":"DE",
    "sg:address":"Stuttgarter Str. 3",
    "sg:city":"Knittlingen",
    "sg:phone":"+49 7043/32258",
    "sg:postcode":"75438",
    "sg:province":"Baden-W\u00fcrttemberg",
    "wof:name":"W. Backfisch",
    "wof:placetype":"venue"
},
  "geometry": {"coordinates":[8.7609844208,49.0242462158],"type":"Point"}
}