{
  "type": "Feature",
  "properties": {
    "iso:country":"DE",
    "sg:address":"Kirchenstr. 5",
    "sg:city":"Loxstedt",
    "sg:phone":"+49 4744/2667",
    "sg:postcode":"27612",
    "sg:province":"Niedersachsen",
    "wof:name":"Ev. Pfarramt Ii Loxstedt",
    "wof:placetype":"venue"
},
  "geometry": {"coordinates":[8.646282196,53.4703483582],"type":"Point"}
}