{
  "type": "Feature",
  "properties": {
    "iso:country":"DE",
    "sg:address":"Hauptstr. 4",
    "sg:city":"Wiesau",
    "sg:phone":"+49 9634/461",
    "sg:postcode":"95676",
    "sg:province":"Bayern",
    "wof:name":"Hotel-pension Hans Kormann",
    "wof:placetype":"venue"
},
  "geometry": {"coordinates":[12.1805887222,49.9096183777],"type":"Point"}
}