{
  "type": "Feature",
  "properties": {
    "iso:country":"DE",
    "sg:address":"Georgenstr. 39",
    "sg:city":"Spremberg",
    "sg:phone":"+49 3563/2736",
    "sg:postcode":"03130",
    "sg:province":"Brandenburg",
    "wof:name":"Martin Kie\u00dfig",
    "wof:placetype":"venue"
},
  "geometry": {"coordinates":[14.37886,51.572475],"type":"Point"}
}