{
  "type": "Feature",
  "properties": {
    "iso:country":"DE",
    "sg:address":"Am F\u00fcnfminutenweg 7",
    "sg:city":"Windischleuba",
    "sg:phone":"+49 4934/4785160",
    "sg:postcode":"04603",
    "sg:province":"Th\u00fcringen",
    "wof:name":"M\u00d6bel Schr\u00d6ter",
    "wof:placetype":"venue"
},
  "geometry": {"coordinates":[12.458990097,51.0104675293],"type":"Point"}
}