{
  "type": "Feature",
  "properties": {
    "iso:country":"DE",
    "sg:address":"Im T\u00e4nnig 14",
    "sg:city":"Mainstockheim",
    "sg:phone":"+49 9321/920595",
    "sg:postcode":"97320",
    "sg:province":"Bayern",
    "wof:name":"Heinz-\u00d6l Energie- Und Service-gmbh",
    "wof:placetype":"venue"
},
  "geometry": {"coordinates":[10.1469078064,49.7711906433],"type":"Point"}
}