{
  "type": "Feature",
  "properties": {
    "iso:country":"DE",
    "sg:address":"Enzianweg 7",
    "sg:city":"Winnenden",
    "sg:phone":"+49 7195/983136",
    "sg:postcode":"71364",
    "sg:province":"Baden-W\u00fcrttemberg",
    "wof:name":"Hh Beck",
    "wof:placetype":"venue"
},
  "geometry": {"coordinates":[9.4234552383,48.8729476929],"type":"Point"}
}