{
  "type": "Feature",
  "properties": {
    "iso:country":"DE",
    "sg:address":"Bauamtsgasse 7",
    "sg:city":"Heidelberg",
    "sg:phone":"+49 6221/21189",
    "sg:postcode":"69117",
    "sg:province":"Baden-W\u00fcrttemberg",
    "wof:name":"Weinstube Schnitzelbank",
    "wof:placetype":"venue"
},
  "geometry": {"coordinates":[8.7024478912,49.4118041992],"type":"Point"}
}