{
  "type": "Feature",
  "properties": {
    "iso:country":"DE",
    "sg:address":"Kupfer 3 a",
    "sg:city":"Unterm\u00fcnkheim",
    "sg:phone":"+49 7944/459",
    "sg:postcode":"74547",
    "sg:province":"Baden-W\u00fcrttemberg",
    "wof:name":"Gastst\u00e4tte Hermann Sch\u00e4fer",
    "wof:placetype":"venue"
},
  "geometry": {"coordinates":[9.7332019806,49.1531257629],"type":"Point"}
}