{
  "type": "Feature",
  "properties": {
    "iso:country":"DE",
    "sg:address":"Affalterthal 6",
    "sg:city":"Egloffstein",
    "sg:phone":"+49 9197/369",
    "sg:postcode":"91349",
    "sg:province":"Bayern",
    "wof:name":"Georg Trautner",
    "wof:placetype":"venue"
},
  "geometry": {"coordinates":[11.2779941559,49.7057723999],"type":"Point"}
}