{
  "type": "Feature",
  "properties": {
    "iso:country":"DE",
    "sg:address":"Europaallee 30 A",
    "sg:city":"Bremen",
    "sg:phone":"+49 421/395053",
    "sg:postcode":"28309",
    "sg:province":"Bremen",
    "wof:name":"Perantara Makelar Tembakau Indonesia Tabak Maklerges. Mbh",
    "wof:placetype":"venue"
},
  "geometry": {"coordinates":[8.8794279099,53.0333061218],"type":"Point"}
}