{
  "type": "Feature",
  "properties": {
    "iso:country":"DE",
    "sg:address":"Sudetenstr. 10",
    "sg:city":"Gro\u00df-Gerau",
    "sg:phone":"+49 6152/82147",
    "sg:postcode":"64521",
    "sg:province":"Hessen",
    "wof:name":"Volker Schuricht",
    "wof:placetype":"venue"
},
  "geometry": {"coordinates":[8.4920158386,49.916557312],"type":"Point"}
}