{
  "type": "Feature",
  "properties": {
    "iso:country":"DE",
    "sg:address":"Im Tiergarten 6",
    "sg:city":"Kurtscheid",
    "sg:phone":"+49 2634/8598",
    "sg:postcode":"56581",
    "sg:province":"Rheinland-Pfalz",
    "wof:name":"Indukran Gmbh",
    "wof:placetype":"venue"
},
  "geometry": {"coordinates":[7.4630680084,50.5333404541],"type":"Point"}
}