{
  "type": "Feature",
  "properties": {
    "iso:country":"DE",
    "sg:address":"Riemker Str. 1",
    "sg:city":"Bochum",
    "sg:phone":"+49 234/534793",
    "sg:postcode":"44809",
    "sg:province":"Nordrhein-Westfalen",
    "wof:name":"Jet-tankstelle",
    "wof:placetype":"venue"
},
  "geometry": {"coordinates":[7.1869330406,51.5077018738],"type":"Point"}
}