{
  "type": "Feature",
  "properties": {
    "iso:country":"DE",
    "sg:address":"Grassistr. 12",
    "sg:city":"Leipzig",
    "sg:phone":"+49 341/216210",
    "sg:postcode":"04107",
    "sg:province":"Sachsen",
    "wof:name":"Talanx Ag",
    "wof:placetype":"venue"
},
  "geometry": {"coordinates":[12.367275238,51.3316764832],"type":"Point"}
}