{
  "type": "Feature",
  "properties": {
    "iso:country":"DE",
    "sg:address":"Fassensteg 3",
    "sg:city":"Kalletal",
    "sg:phone":"+49 5264/5888",
    "sg:postcode":"32689",
    "sg:province":"Nordrhein-Westfalen",
    "wof:name":"Karl Preu\u00df Gmbh & Co.",
    "wof:placetype":"venue"
},
  "geometry": {"coordinates":[8.934088707,52.1039619446],"type":"Point"}
}