{
  "type": "Feature",
  "properties": {
    "iso:country":"DE",
    "sg:address":"Schollerwiese 1",
    "sg:city":"Langenzenn",
    "sg:phone":"+49 9101/5780",
    "sg:postcode":"90579",
    "sg:province":"Bayern",
    "wof:name":"H.-j. Metter",
    "wof:placetype":"venue"
},
  "geometry": {"coordinates":[10.79805,49.49593],"type":"Point"}
}