{
  "type": "Feature",
  "properties": {
    "iso:country":"DE",
    "sg:address":"Auf'm Bruch 4",
    "sg:city":"Warstein",
    "sg:phone":"+49 2902/97200",
    "sg:postcode":"59581",
    "sg:province":"Nordrhein-Westfalen",
    "wof:name":"J. Schr\u00f6der Sanit\u00e4tshaus",
    "wof:placetype":"venue"
},
  "geometry": {"coordinates":[8.275536,51.482674],"type":"Point"}
}