{
  "type": "Feature",
  "properties": {
    "iso:country":"DE",
    "sg:address":"Aroser Allee 72",
    "sg:city":"Berlin",
    "sg:phone":"+49 30/498820",
    "sg:postcode":"13407",
    "sg:province":"Berlin",
    "wof:name":"Senioren-betreuungs- Gesellschaft Medico",
    "wof:placetype":"venue"
},
  "geometry": {"coordinates":[13.353632,52.563362],"type":"Point"}
}