{
  "type": "Feature",
  "properties": {
    "iso:country":"DE",
    "sg:address":"Hauptstr. 89",
    "sg:city":"Mossautal",
    "sg:phone":"+49 6061/7020",
    "sg:postcode":"64756",
    "sg:province":"Hessen",
    "wof:name":"Privat-brauerei Schmucker Ober-mossau Kg",
    "wof:placetype":"venue"
},
  "geometry": {"coordinates":[8.92227,49.675621],"type":"Point"}
}