{
  "type": "Feature",
  "properties": {
    "iso:country":"DE",
    "sg:address":"Bahnhofstr. 23b",
    "sg:city":"Hofgeismar",
    "sg:phone":"+49 5671/2081",
    "sg:postcode":"34369",
    "sg:province":"Hessen",
    "wof:name":"Gustav Nolte",
    "wof:placetype":"venue"
},
  "geometry": {"coordinates":[9.3899021149,51.4951438904],"type":"Point"}
}