{
  "type": "Feature",
  "properties": {
    "iso:country":"DE",
    "sg:address":"Brinksweg 7 a",
    "sg:city":"Wittmund",
    "sg:postcode":"26409",
    "sg:province":"Niedersachsen",
    "wof:name":"Fritz Tell",
    "wof:placetype":"venue"
},
  "geometry": {"coordinates":[7.7617301941,53.5705490112],"type":"Point"}
}