{
  "type": "Feature",
  "properties": {
    "iso:country":"DE",
    "sg:address":"Obere Bachgasse 7",
    "sg:city":"Memmingen",
    "sg:phone":"+49 8331/81102",
    "sg:postcode":"87700",
    "sg:province":"Bayern",
    "wof:name":"Weinstube Eiche",
    "wof:placetype":"venue"
},
  "geometry": {"coordinates":[10.1809234619,47.9835128784],"type":"Point"}
}