{
  "type": "Feature",
  "properties": {
    "iso:country":"DE",
    "sg:address":"Breitenbacher Str. 32",
    "sg:city":"Leinefelde",
    "sg:phone":"+49 3605/54303",
    "sg:postcode":"37327",
    "sg:province":"Th\u00fcringen",
    "wof:name":"Autohaus Hanuschke Gmbh",
    "wof:placetype":"venue"
},
  "geometry": {"coordinates":[10.326232,51.392929],"type":"Point"}
}