{
  "type": "Feature",
  "properties": {
    "iso:country":"DE",
    "sg:address":"Professor-Willkomm-Str.",
    "sg:city":"Limbach-Oberfrohna",
    "sg:phone":"+49 3722/95152",
    "sg:postcode":"09212",
    "sg:province":"Sachsen",
    "wof:name":"Bad Gro\u00dfer Teich",
    "wof:placetype":"venue"
},
  "geometry": {"coordinates":[12.7643270493,50.8555297852],"type":"Point"}
}