{
  "type": "Feature",
  "properties": {
    "iso:country":"DE",
    "sg:address":"Schusterstr. 35",
    "sg:city":"M\u00fcnchen",
    "sg:phone":"+49 89/7901567",
    "sg:postcode":"81477",
    "sg:province":"Bayern",
    "wof:name":"Verena Knott",
    "wof:placetype":"venue"
},
  "geometry": {"coordinates":[11.50982,48.083118],"type":"Point"}
}