{
  "type": "Feature",
  "properties": {
    "iso:country":"DE",
    "sg:address":"Schopfgraben 31",
    "sg:city":"Miesbach",
    "sg:phone":"+49 8025/3324",
    "sg:postcode":"83714",
    "sg:province":"Bayern",
    "wof:name":"Heinrich Friedl",
    "wof:placetype":"venue"
},
  "geometry": {"coordinates":[11.825215,47.796917],"type":"Point"}
}