{
  "type": "Feature",
  "properties": {
    "iso:country":"DE",
    "sg:address":"Hans-Staden-Str 1",
    "sg:city":"Wolfhagen",
    "sg:phone":"+49 5692/1695",
    "sg:postcode":"34466",
    "sg:province":"Hessen",
    "wof:name":"Geru-pack Gmbh",
    "wof:placetype":"venue"
},
  "geometry": {"coordinates":[9.173645,51.324921],"type":"Point"}
}