{
  "type": "Feature",
  "properties": {
    "iso:country":"DE",
    "sg:address":"Ahornstr. 17",
    "sg:city":"Hohenbrunn",
    "sg:postcode":"85662",
    "sg:province":"Bayern",
    "wof:name":"Cigaretten Ostermeier Kg",
    "wof:placetype":"venue"
},
  "geometry": {"coordinates":[11.710021019,48.0347862244],"type":"Point"}
}