{
  "type": "Feature",
  "properties": {
    "iso:country":"DE",
    "sg:address":"Max-Reger-Str.71",
    "sg:city":"Hof",
    "sg:postcode":"95030",
    "sg:province":"Bayern",
    "wof:name":"Staatliche Realschule Hof",
    "wof:placetype":"venue"
},
  "geometry": {"coordinates":[11.899071,50.30759],"type":"Point"}
}