{
  "type": "Feature",
  "properties": {
    "iso:country":"DE",
    "sg:address":"H\u00f6fgen 3",
    "sg:city":"H\u00f6fgen",
    "sg:phone":"+49 35246/50308",
    "sg:postcode":"01623",
    "sg:province":"Sachsen",
    "wof:name":"D. Sch\u00fcller",
    "wof:placetype":"venue"
},
  "geometry": {"coordinates":[13.290071,51.124035],"type":"Point"}
}