{
  "type": "Feature",
  "properties": {
    "iso:country":"DE",
    "sg:address":"Robert-Bosch-Str. 25",
    "sg:city":"Horb",
    "sg:phone":"+49 7451/7021",
    "sg:postcode":"72160",
    "sg:province":"Baden-W\u00fcrttemberg",
    "wof:name":"Manfred Volz",
    "wof:placetype":"venue"
},
  "geometry": {"coordinates":[8.712262,48.46188],"type":"Point"}
}