{
  "type": "Feature",
  "properties": {
    "iso:country":"DE",
    "sg:address":"Gerlachstr. 36",
    "sg:city":"Frankfurt",
    "sg:phone":"+49 69/306434",
    "sg:postcode":"65929",
    "sg:province":"Hessen",
    "wof:name":"Richard Meder Rechtsanwalt",
    "wof:placetype":"venue"
},
  "geometry": {"coordinates":[8.5455989838,50.1050071716],"type":"Point"}
}