{
  "type": "Feature",
  "properties": {
    "iso:country":"DE",
    "sg:address":"Weiherer Str. 2",
    "sg:city":"Lisberg",
    "sg:phone":"+49 9549/7940",
    "sg:postcode":"96170",
    "sg:province":"Bayern",
    "wof:name":"Erwin Und Helga Pickel",
    "wof:placetype":"venue"
},
  "geometry": {"coordinates":[10.7269973755,49.8954086304],"type":"Point"}
}