{
  "type": "Feature",
  "properties": {
    "iso:country":"DE",
    "sg:address":"Warendorfer Str. 511",
    "sg:city":"M\u00fcnster",
    "sg:phone":"+49 251/326656",
    "sg:postcode":"48157",
    "sg:province":"Nordrhein-Westfalen",
    "wof:name":"Ralf Wendland Wohnen Gmbh",
    "wof:placetype":"venue"
},
  "geometry": {"coordinates":[7.699018,51.988331],"type":"Point"}
}