{
  "type": "Feature",
  "properties": {
    "iso:country":"DE",
    "sg:address":"Eschersheimer Landstr. 540",
    "sg:city":"Frankfurt",
    "sg:phone":"+49 69/522247",
    "sg:postcode":"60433",
    "sg:province":"Hessen",
    "wof:name":"Zorbach Finanzberater",
    "wof:placetype":"venue"
},
  "geometry": {"coordinates":[8.6573963165,50.156627655],"type":"Point"}
}