{
  "type": "Feature",
  "properties": {
    "iso:country":"DE",
    "sg:address":"Poststr. 28",
    "sg:city":"Nortorf",
    "sg:phone":"+49 4392/4437",
    "sg:postcode":"24589",
    "sg:province":"Schleswig-Holstein",
    "wof:name":"Carl Maass Gmbh",
    "wof:placetype":"venue"
},
  "geometry": {"coordinates":[9.8562784195,54.1655235291],"type":"Point"}
}