{
  "type": "Feature",
  "properties": {
    "iso:country":"DE",
    "sg:address":"St\u00fchlingerweg 1",
    "sg:city":"Hinterzarten",
    "sg:phone":"+49 7652/5580",
    "sg:postcode":"79856",
    "sg:province":"Baden-W\u00fcrttemberg",
    "wof:name":"Hotel Zartenbach",
    "wof:placetype":"venue"
},
  "geometry": {"coordinates":[8.100111,47.910202],"type":"Point"}
}