{
  "type": "Feature",
  "properties": {
    "iso:country":"DE",
    "sg:address":"Baustr. 43",
    "sg:city":"Duisburg",
    "sg:phone":"+49 203/4556670",
    "sg:postcode":"47179",
    "sg:province":"Nordrhein-Westfalen",
    "wof:name":"Meike Conrads Rechtsanw\u00e4ltin",
    "wof:placetype":"venue"
},
  "geometry": {"coordinates":[6.7383260727,51.5291557312],"type":"Point"}
}