{
  "type": "Feature",
  "properties": {
    "iso:country":"DE",
    "sg:address":"Rosental 46",
    "sg:city":"Nettetal",
    "sg:postcode":"41334",
    "sg:province":"Nordrhein-Westfalen",
    "wof:name":"Meisterbau Nettetal Gmbh",
    "wof:placetype":"venue"
},
  "geometry": {"coordinates":[6.268301,51.316841],"type":"Point"}
}