{
  "type": "Feature",
  "properties": {
    "iso:country":"DE",
    "sg:address":"Varenholzer Str. 30",
    "sg:city":"Kalletal",
    "sg:phone":"+49 5755/329",
    "sg:postcode":"32689",
    "sg:province":"Nordrhein-Westfalen",
    "wof:name":"Ev. Pfarramt Ev. Ref. Kirche",
    "wof:placetype":"venue"
},
  "geometry": {"coordinates":[8.9900531769,52.1710777283],"type":"Point"}
}