{
  "type": "Feature",
  "properties": {
    "iso:country":"DE",
    "sg:address":"Diepoltshofen 8",
    "sg:city":"Maisach",
    "sg:phone":"+49 8141/94707",
    "sg:postcode":"82216",
    "sg:province":"Bayern",
    "wof:name":"Rudolf Fischer Architekt",
    "wof:placetype":"venue"
},
  "geometry": {"coordinates":[11.24964,48.225994],"type":"Point"}
}