{
  "type": "Feature",
  "properties": {
    "iso:country":"DE",
    "sg:address":"Hans-Sachs-Str. 25",
    "sg:city":"Bottrop",
    "sg:phone":"+49 2041/22919",
    "sg:postcode":"46236",
    "sg:province":"Nordrhein-Westfalen",
    "wof:name":"G. Van Dyck",
    "wof:placetype":"venue"
},
  "geometry": {"coordinates":[6.926158905,51.5274391174],"type":"Point"}
}