{
  "type": "Feature",
  "properties": {
    "iso:country":"DE",
    "sg:address":"Langensaal 8",
    "sg:city":"Hamburg",
    "sg:phone":"+49 40/810622",
    "sg:postcode":"22559",
    "sg:province":"Hamburg",
    "wof:name":"Sybronn Verm\u00f6gens- Verwaltung Gmbh",
    "wof:placetype":"venue"
},
  "geometry": {"coordinates":[9.7688026428,53.5854187012],"type":"Point"}
}