{
  "type": "Feature",
  "properties": {
    "iso:country":"DE",
    "sg:address":"Finkenweg 10",
    "sg:city":"Blankenburg",
    "sg:phone":"+49 3944/64847",
    "sg:postcode":"38889",
    "sg:province":"Sachsen-Anhalt",
    "wof:name":"Klaus Lindner",
    "wof:placetype":"venue"
},
  "geometry": {"coordinates":[10.9815664291,51.7984352112],"type":"Point"}
}