{
  "type": "Feature",
  "properties": {
    "iso:country":"DE",
    "sg:address":"Creuzburger Str. 65",
    "sg:city":"Hastrungsfeld-Burla",
    "sg:postcode":"99848",
    "sg:province":"Th\u00fcringen",
    "wof:name":"Fleisch- Und Wurstwaren H\u00f6rseltal Gmbh",
    "wof:placetype":"venue"
},
  "geometry": {"coordinates":[10.4999704361,50.9550209045],"type":"Point"}
}