{
  "type": "Feature",
  "properties": {
    "iso:country":"DE",
    "sg:address":"Spitzbergstr. 7",
    "sg:city":"Kreischa",
    "sg:phone":"+49 35206/22056",
    "sg:postcode":"01731",
    "sg:province":"Sachsen",
    "wof:name":"Werunia Gmbh Werner Rudnik",
    "wof:placetype":"venue"
},
  "geometry": {"coordinates":[13.774515152,50.9329452515],"type":"Point"}
}