{
  "type": "Feature",
  "properties": {
    "iso:country":"DE",
    "sg:address":"Waldburgstr. 104",
    "sg:city":"Stuttgart",
    "sg:postcode":"70563",
    "sg:province":"Baden-W\u00fcrttemberg",
    "wof:name":"Ips Beschaffung Und Services Gmbh",
    "wof:placetype":"venue"
},
  "geometry": {"coordinates":[9.0986728668,48.7249755859],"type":"Point"}
}