{
  "type": "Feature",
  "properties": {
    "iso:country":"DE",
    "sg:address":"Kilvertzhof 1",
    "sg:city":"Hilden",
    "sg:phone":"+49 2103/62122",
    "sg:postcode":"40724",
    "sg:province":"Nordrhein-Westfalen",
    "wof:name":"Cremona Gmbh",
    "wof:placetype":"venue"
},
  "geometry": {"coordinates":[6.9543361664,51.1656837463],"type":"Point"}
}