{
  "type": "Feature",
  "properties": {
    "iso:country":"DE",
    "sg:address":"Preysingstr. 7",
    "sg:city":"Wolnzach",
    "sg:phone":"+49 8442/3401",
    "sg:postcode":"85283",
    "sg:province":"Bayern",
    "wof:name":"Restaurant Haimmerl",
    "wof:placetype":"venue"
},
  "geometry": {"coordinates":[11.628027916,48.6024436951],"type":"Point"}
}