{
  "type": "Feature",
  "properties": {
    "iso:country":"DE",
    "sg:address":"Hohnsteinerstr.",
    "sg:city":"Ilfeld",
    "sg:phone":"+49 36331/6381",
    "sg:postcode":"99768",
    "sg:province":"Th\u00fcringen",
    "wof:name":"R. Heinicke",
    "wof:placetype":"venue"
},
  "geometry": {"coordinates":[10.794938,51.575794],"type":"Point"}
}