{
  "type": "Feature",
  "properties": {
    "iso:country":"DE",
    "sg:address":"Pribbenow 60",
    "sg:city":"Stavenhagen",
    "sg:phone":"+49 39955/20461",
    "sg:postcode":"17153",
    "sg:province":"Mecklenburg-Vorpommern",
    "wof:name":"S. Schulz",
    "wof:placetype":"venue"
},
  "geometry": {"coordinates":[12.9704303741,53.7102355957],"type":"Point"}
}