{
  "type": "Feature",
  "properties": {
    "iso:country":"DE",
    "sg:address":"Heerweg 154",
    "sg:city":"Gronau",
    "sg:phone":"+49 2562/98900",
    "sg:postcode":"48599",
    "sg:province":"Nordrhein-Westfalen",
    "wof:name":"Hans Rosellen",
    "wof:placetype":"venue"
},
  "geometry": {"coordinates":[7.0539569855,52.2110595703],"type":"Point"}
}