{
  "type": "Feature",
  "properties": {
    "iso:country":"DE",
    "sg:address":"Dorfstr. 111",
    "sg:city":"Appenweier",
    "sg:phone":"+49 7805/97426",
    "sg:postcode":"77767",
    "sg:province":"Baden-W\u00fcrttemberg",
    "wof:name":"Wolfgang Wegel Ing.-b\u00fcro F\u00fcr Gr\u00fcn- Und",
    "wof:placetype":"venue"
},
  "geometry": {"coordinates":[8.0150299072,48.5156173706],"type":"Point"}
}