{
  "type": "Feature",
  "properties": {
    "iso:country":"DE",
    "sg:address":"Beckmarhau 44",
    "sg:city":"Obernkirchen",
    "sg:phone":"+49 5724/8980",
    "sg:postcode":"31683",
    "sg:province":"Niedersachsen",
    "wof:name":"G. Patterson",
    "wof:placetype":"venue"
},
  "geometry": {"coordinates":[9.1332597733,52.2534408569],"type":"Point"}
}