{
  "type": "Feature",
  "properties": {
    "iso:country":"DE",
    "sg:address":"Eisinger Str. 2",
    "sg:city":"Kist",
    "sg:phone":"+49 9306/1267",
    "sg:postcode":"97270",
    "sg:province":"Bayern",
    "wof:name":"Leo Thomas Raimund Copyshop Buchbinderarbeiten",
    "wof:placetype":"venue"
},
  "geometry": {"coordinates":[9.8387813568,49.7448158264],"type":"Point"}
}