{
  "type": "Feature",
  "properties": {
    "iso:country":"DE",
    "sg:address":"Scherfeder Str. 24",
    "sg:city":"Warburg",
    "sg:phone":"+49 5642/5730",
    "sg:postcode":"34414",
    "sg:province":"Nordrhein-Westfalen",
    "wof:name":"Wilfried Bunse",
    "wof:placetype":"venue"
},
  "geometry": {"coordinates":[9.045340538,51.5264358521],"type":"Point"}
}