{
  "type": "Feature",
  "properties": {
    "iso:country":"DE",
    "sg:address":"Mont-Cenis-Str. 346",
    "sg:city":"Herne",
    "sg:phone":"+49 2323/961223",
    "sg:postcode":"44627",
    "sg:province":"Nordrhein-Westfalen",
    "wof:name":"Dr, Hans-joachim Bu\u00dfmann Rechtsanwalt",
    "wof:placetype":"venue"
},
  "geometry": {"coordinates":[7.2661061287,51.5409545898],"type":"Point"}
}