{
  "type": "Feature",
  "properties": {
    "iso:country":"DE",
    "sg:address":"Winterstr. 9",
    "sg:city":"M\u00fcnchen",
    "sg:phone":"+49 89/663941",
    "sg:postcode":"81543",
    "sg:province":"Bayern",
    "wof:name":"Dieter Zimmermann Architekt",
    "wof:placetype":"venue"
},
  "geometry": {"coordinates":[11.571252,48.115498],"type":"Point"}
}