{
  "type": "Feature",
  "properties": {
    "iso:country":"DE",
    "sg:address":"M\u00fchlbachstr. 59",
    "sg:city":"\u00dcberlingen",
    "sg:postcode":"88662",
    "sg:province":"Baden-W\u00fcrttemberg",
    "wof:name":"Riedm\u00fcller Und St\u00f6rr",
    "wof:placetype":"venue"
},
  "geometry": {"coordinates":[9.1778869629,47.761680603],"type":"Point"}
}