{
  "type": "Feature",
  "properties": {
    "iso:country":"DE",
    "sg:address":"Schleifweg 5",
    "sg:city":"Renchen",
    "sg:phone":"+49 7843/541",
    "sg:postcode":"77871",
    "sg:province":"Baden-W\u00fcrttemberg",
    "wof:name":"Ultra Werk",
    "wof:placetype":"venue"
},
  "geometry": {"coordinates":[8.00527668,48.591960907],"type":"Point"}
}