{
  "type": "Feature",
  "properties": {
    "iso:country":"DE",
    "sg:address":"Leinzeller Str. 2",
    "sg:city":"T\u00e4ferrot",
    "sg:phone":"+49 7175/6793",
    "sg:postcode":"73527",
    "sg:province":"Baden-W\u00fcrttemberg",
    "wof:name":"G. L. Kunz",
    "wof:placetype":"venue"
},
  "geometry": {"coordinates":[9.835399,48.852146],"type":"Point"}
}