{
  "type": "Feature",
  "properties": {
    "iso:country":"DE",
    "sg:address":"Gehrn 1",
    "sg:city":"Wacken",
    "sg:phone":"+49 4827/2462",
    "sg:postcode":"25596",
    "sg:province":"Schleswig-Holstein",
    "wof:name":"Axel Ramm Bedachungs Gmbh",
    "wof:placetype":"venue"
},
  "geometry": {"coordinates":[9.3832168579,54.0203857422],"type":"Point"}
}