{
  "type": "Feature",
  "properties": {
    "iso:country":"DE",
    "sg:address":"Biesenkamp 5",
    "sg:city":"Castrop-Rauxel",
    "sg:phone":"+49 2305/22249",
    "sg:postcode":"44575",
    "sg:province":"Nordrhein-Westfalen",
    "wof:name":"Prott-modique Inh. Christa Prott E. Kfr.",
    "wof:placetype":"venue"
},
  "geometry": {"coordinates":[7.31181,51.548706],"type":"Point"}
}