{
  "type": "Feature",
  "properties": {
    "iso:country":"DE",
    "sg:address":"B\u00f6hmerstr. 5",
    "sg:city":"Waldm\u00fcnchen",
    "sg:phone":"+49 9972/902776",
    "sg:postcode":"93449",
    "sg:province":"Bayern",
    "wof:name":"Helmut Windmei\u00dfer",
    "wof:placetype":"venue"
},
  "geometry": {"coordinates":[12.7076473236,49.3786468506],"type":"Point"}
}