{
  "type": "Feature",
  "properties": {
    "iso:country":"DE",
    "sg:address":"Volmestr. 13",
    "sg:city":"Recklinghausen",
    "sg:phone":"+49 2361/63209",
    "sg:postcode":"45663",
    "sg:province":"Nordrhein-Westfalen",
    "wof:name":"Wilfried Hilberg",
    "wof:placetype":"venue"
},
  "geometry": {"coordinates":[7.2221050262,51.5715026855],"type":"Point"}
}