{
  "type": "Feature",
  "properties": {
    "iso:country":"DE",
    "sg:address":"Pferdekoppel 26",
    "sg:city":"Neuenkirchen",
    "sg:postcode":"29643",
    "sg:province":"Niedersachsen",
    "wof:name":"Gloustique Management Service Gmbh",
    "wof:placetype":"venue"
},
  "geometry": {"coordinates":[9.6877508163,53.0274848938],"type":"Point"}
}