{
  "type": "Feature",
  "properties": {
    "iso:country":"DE",
    "sg:address":"Gesellensteig 29",
    "sg:city":"Salzgitter",
    "sg:phone":"+49 5341/64752",
    "sg:postcode":"38229",
    "sg:province":"Niedersachsen",
    "wof:name":"Ihos Darginidis Gmbh",
    "wof:placetype":"venue"
},
  "geometry": {"coordinates":[10.349647,52.166641],"type":"Point"}
}