{
  "type": "Feature",
  "properties": {
    "iso:country":"DE",
    "sg:address":"Postfach 11 69",
    "sg:city":"Rotenburg",
    "sg:postcode":"36187",
    "sg:province":"Hessen",
    "wof:name":"Kurt G\u00fcnther Gmbh",
    "wof:placetype":"venue"
},
  "geometry": {"coordinates":[9.7268800735,50.9951705933],"type":"Point"}
}