{
  "type": "Feature",
  "properties": {
    "iso:country":"DE",
    "sg:address":"Schlo\u00dfhof 5",
    "sg:city":"Mespelbrunn",
    "sg:phone":"+49 6092/1698",
    "sg:postcode":"63875",
    "sg:province":"Bayern",
    "wof:name":"Pferdestall",
    "wof:placetype":"venue"
},
  "geometry": {"coordinates":[9.2892999649,49.9170036316],"type":"Point"}
}