{
  "type": "Feature",
  "properties": {
    "iso:country":"DE",
    "sg:address":"Hardtweg 7/1",
    "sg:city":"Dobel",
    "sg:postcode":"75335",
    "sg:province":"Baden-W\u00fcrttemberg",
    "wof:name":"Axel Cramer Gmbh",
    "wof:placetype":"venue"
},
  "geometry": {"coordinates":[8.497027,48.799366],"type":"Point"}
}