{
  "type": "Feature",
  "properties": {
    "iso:country":"DE",
    "sg:address":"Fuistingstr. 16",
    "sg:city":"Ahaus",
    "sg:postcode":"48683",
    "sg:province":"Nordrhein-Westfalen",
    "wof:name":"Kath. \u00f6ffentliche Bibliothek St. Josef",
    "wof:placetype":"venue"
},
  "geometry": {"coordinates":[7.010639,52.083912],"type":"Point"}
}