{
  "type": "Feature",
  "properties": {
    "iso:country":"DE",
    "sg:address":"Klematisweg 8",
    "sg:city":"Detmold",
    "sg:phone":"+49 5231/48327",
    "sg:postcode":"32760",
    "sg:province":"Nordrhein-Westfalen",
    "wof:name":"Herbert K\u00f6nig",
    "wof:placetype":"venue"
},
  "geometry": {"coordinates":[8.873163,51.905861],"type":"Point"}
}