{
  "type": "Feature",
  "properties": {
    "iso:country":"DE",
    "sg:address":"An der Bergkette 41",
    "sg:city":"Stadthagen",
    "sg:phone":"+49 5721/79480",
    "sg:postcode":"31655",
    "sg:province":"Niedersachsen",
    "wof:name":"Hans-gerd Abs",
    "wof:placetype":"venue"
},
  "geometry": {"coordinates":[9.2658472061,52.3072624207],"type":"Point"}
}