{
  "type": "Feature",
  "properties": {
    "iso:country":"DE",
    "sg:address":"Hauptstr. 119",
    "sg:city":"Saarbr\u00fccken",
    "sg:phone":"+49 681/70132",
    "sg:postcode":"66128",
    "sg:province":"Saarland",
    "wof:name":"Manfred Bernardi Architekt",
    "wof:placetype":"venue"
},
  "geometry": {"coordinates":[6.924609,49.237305],"type":"Point"}
}