{
  "type": "Feature",
  "properties": {
    "iso:country":"DE",
    "sg:address":"H\u00fclsebrockstr. 62",
    "sg:city":"M\u00fcnster",
    "sg:phone":"+49 2501/25600",
    "sg:postcode":"48165",
    "sg:province":"Nordrhein-Westfalen",
    "wof:name":"Herbert F. Schuler",
    "wof:placetype":"venue"
},
  "geometry": {"coordinates":[7.645871,51.908272],"type":"Point"}
}