{
  "type": "Feature",
  "properties": {
    "iso:country":"DE",
    "sg:address":"Steinstr. 28",
    "sg:city":"Kaiserslautern",
    "sg:phone":"+49 631/3605316",
    "sg:postcode":"67657",
    "sg:province":"Rheinland-Pfalz",
    "wof:name":"J. Schneider Finanzberater",
    "wof:placetype":"venue"
},
  "geometry": {"coordinates":[7.7735600471,49.4467086792],"type":"Point"}
}