{
  "type": "Feature",
  "properties": {
    "iso:country":"DE",
    "sg:address":"Lookenstr. 17",
    "sg:city":"Lingen",
    "sg:postcode":"49808",
    "sg:province":"Niedersachsen",
    "wof:name":"Mensing Verwaltungs Gmbh",
    "wof:placetype":"venue"
},
  "geometry": {"coordinates":[7.3164491653,52.5209312439],"type":"Point"}
}