{
  "type": "Feature",
  "properties": {
    "iso:country":"DE",
    "sg:address":"Uelzener Str 34a",
    "sg:city":"Salzwedel",
    "sg:phone":"+49 3901/306945",
    "sg:postcode":"29410",
    "sg:province":"Sachsen-Anhalt",
    "wof:name":"Gesellschaft F\u00fcr Analysentechnik Hls",
    "wof:placetype":"venue"
},
  "geometry": {"coordinates":[11.136895,52.858044],"type":"Point"}
}