{
  "type": "Feature",
  "properties": {
    "iso:country":"DE",
    "sg:address":"Possendorfer Str. 9",
    "sg:city":"Dresden",
    "sg:postcode":"01217",
    "sg:province":"Sachsen",
    "wof:name":"Ct Bauplanungs- Und Bau- Betreuungsges. Mbh",
    "wof:placetype":"venue"
},
  "geometry": {"coordinates":[13.72944,51.016209],"type":"Point"}
}