{
  "type": "Feature",
  "properties": {
    "iso:country":"DE",
    "sg:address":"Bauerngasse 18",
    "sg:city":"Syrgenstein",
    "sg:phone":"+49 9077/708477",
    "sg:postcode":"89428",
    "sg:province":"Bayern",
    "wof:name":"K. Rettenberger",
    "wof:placetype":"venue"
},
  "geometry": {"coordinates":[10.284236908,48.6608047485],"type":"Point"}
}