{
  "type": "Feature",
  "properties": {
    "iso:country":"DE",
    "sg:address":"Dornierstr. 4",
    "sg:city":"Sindelfingen",
    "sg:phone":"+49 7031/76800",
    "sg:postcode":"71069",
    "sg:province":"Baden-W\u00fcrttemberg",
    "wof:name":"Sanit\u00e4r Mundle Gmbh",
    "wof:placetype":"venue"
},
  "geometry": {"coordinates":[8.941812,48.690422],"type":"Point"}
}