{
  "type": "Feature",
  "properties": {
    "iso:country":"DE",
    "sg:address":"Hainh\u00e4user Str. 61",
    "sg:city":"Rodgau",
    "sg:phone":"+49 6106/15972",
    "sg:postcode":"63110",
    "sg:province":"Hessen",
    "wof:name":"Stickl Werkzeugbau Gmbh",
    "wof:placetype":"venue"
},
  "geometry": {"coordinates":[8.8855829239,50.0475311279],"type":"Point"}
}