{
  "type": "Feature",
  "properties": {
    "iso:country":"DE",
    "sg:address":"Buchendorfer Str. 2",
    "sg:city":"Gauting",
    "sg:phone":"+49 89/8505235",
    "sg:postcode":"82131",
    "sg:province":"Bayern",
    "wof:name":"A. Von Richthofen",
    "wof:placetype":"venue"
},
  "geometry": {"coordinates":[11.383194,48.065613],"type":"Point"}
}