{
  "type": "Feature",
  "properties": {
    "iso:country":"DE",
    "sg:address":"Schillerstr. 68",
    "sg:city":"Zittau",
    "sg:phone":"+49 4935/8357320",
    "sg:postcode":"02763",
    "sg:province":"Sachsen",
    "wof:name":"Osamatic System Gmbh",
    "wof:placetype":"venue"
},
  "geometry": {"coordinates":[14.812787056,50.9071235657],"type":"Point"}
}