{
  "type": "Feature",
  "properties": {
    "iso:country":"DE",
    "sg:address":"Birkacher Str 33",
    "sg:city":"Steinenbronn",
    "sg:phone":"+49 7157/20064",
    "sg:postcode":"71144",
    "sg:province":"Baden-W\u00fcrttemberg",
    "wof:name":"Manfred Gienger L\u00f6tzinn",
    "wof:placetype":"venue"
},
  "geometry": {"coordinates":[9.1189851761,48.6666107178],"type":"Point"}
}