{
  "type": "Feature",
  "properties": {
    "iso:country":"DE",
    "sg:address":"W\u00fcrzburger Str. 6",
    "sg:city":"Rothenburg",
    "sg:phone":"+49 9861/3484",
    "sg:postcode":"91541",
    "sg:province":"Bayern",
    "wof:name":"Ziegler Kg",
    "wof:placetype":"venue"
},
  "geometry": {"coordinates":[10.1858062744,49.3809585571],"type":"Point"}
}