{
  "type": "Feature",
  "properties": {
    "iso:country":"DE",
    "sg:address":"Bonhoefferstr. 31",
    "sg:city":"Aachen",
    "sg:phone":"+49 241/527340",
    "sg:postcode":"52078",
    "sg:province":"Nordrhein-Westfalen",
    "wof:name":"Robert Fahrb\u00fcchel",
    "wof:placetype":"venue"
},
  "geometry": {"coordinates":[6.166583,50.755726],"type":"Point"}
}