{
  "type": "Feature",
  "properties": {
    "iso:country":"DE",
    "sg:address":"Schlo\u00dfstr. 12a",
    "sg:city":"Allstedt",
    "sg:phone":"+49 34652/708",
    "sg:postcode":"06542",
    "sg:province":"Sachsen-Anhalt",
    "wof:name":"Hans-dieter Gr\u00fctzner",
    "wof:placetype":"venue"
},
  "geometry": {"coordinates":[11.3936071396,51.404258728],"type":"Point"}
}