{
  "type": "Feature",
  "properties": {
    "iso:country":"DE",
    "sg:address":"Obere Bleiche 2",
    "sg:city":"Ulm",
    "sg:phone":"+49 731/39790",
    "sg:postcode":"89077",
    "sg:province":"Baden-W\u00fcrttemberg",
    "wof:name":"Fricker Kg",
    "wof:placetype":"venue"
},
  "geometry": {"coordinates":[9.975654,48.400921],"type":"Point"}
}