{
  "type": "Feature",
  "properties": {
    "iso:country":"DE",
    "sg:address":"An der Knippenburg 38",
    "sg:city":"Bottrop",
    "sg:phone":"+49 2041/18380",
    "sg:postcode":"46238",
    "sg:province":"Nordrhein-Westfalen",
    "wof:name":"Ikewa Industriekesselwagen- Reinigung Gmbh",
    "wof:placetype":"venue"
},
  "geometry": {"coordinates":[6.9479351044,51.5125083923],"type":"Point"}
}