{
  "type": "Feature",
  "properties": {
    "iso:country":"DE",
    "sg:address":"Schmuzerstr. 1",
    "sg:city":"M\u00fcnchen",
    "sg:phone":"+49 89/716571",
    "sg:postcode":"81373",
    "sg:province":"Bayern",
    "wof:name":"Manfred L. Gramminger Heilpraktiker",
    "wof:placetype":"venue"
},
  "geometry": {"coordinates":[11.5221691132,48.1149406433],"type":"Point"}
}