{
  "type": "Feature",
  "properties": {
    "iso:country":"DE",
    "sg:address":"Carl-Still-Str. 21",
    "sg:city":"Recklinghausen",
    "sg:phone":"+49 2361/900390",
    "sg:postcode":"45659",
    "sg:province":"Nordrhein-Westfalen",
    "wof:name":"Politt & Feldmann Gmbh & Co. Kg",
    "wof:placetype":"venue"
},
  "geometry": {"coordinates":[7.201011,51.58778],"type":"Point"}
}