{
  "type": "Feature",
  "properties": {
    "iso:country":"DE",
    "sg:address":"Deven 17a",
    "sg:city":"Demmin",
    "sg:phone":"+49 4939/9827030",
    "sg:postcode":"17109",
    "sg:province":"Mecklenburg-Vorpommern",
    "wof:name":"Silke Klinkberg Gmbh",
    "wof:placetype":"venue"
},
  "geometry": {"coordinates":[12.995854,53.901512],"type":"Point"}
}