{
  "type": "Feature",
  "properties": {
    "iso:country":"DE",
    "sg:address":"Nelkenstr. 46",
    "sg:city":"Unterschlei\u00dfheim",
    "sg:phone":"+49 89/2725565",
    "sg:postcode":"85716",
    "sg:province":"Bayern",
    "wof:name":"Franz Pilzweger Steuerberater",
    "wof:placetype":"venue"
},
  "geometry": {"coordinates":[11.5793533325,48.2763328552],"type":"Point"}
}