{
  "type": "Feature",
  "properties": {
    "iso:country":"DE",
    "sg:address":"Weingartenstr. 2",
    "sg:city":"Worms",
    "sg:phone":"+49 6242/7098",
    "sg:postcode":"67550",
    "sg:province":"Rheinland-Pfalz",
    "wof:name":"T. Brunn",
    "wof:placetype":"venue"
},
  "geometry": {"coordinates":[8.281782,49.67963],"type":"Point"}
}