{
  "type": "Feature",
  "properties": {
    "iso:country":"DE",
    "sg:address":"Rebweg 4",
    "sg:city":"Bodolz",
    "sg:phone":"+49 8382/942125",
    "sg:postcode":"88131",
    "sg:province":"Bayern",
    "wof:name":"J. & P. Drechsel Speditions Gmbh",
    "wof:placetype":"venue"
},
  "geometry": {"coordinates":[9.6679134369,47.5669059753],"type":"Point"}
}