{
  "type": "Feature",
  "properties": {
    "iso:country":"DE",
    "sg:address":"Schenkenburgstr. 7",
    "sg:city":"Karlsruhe",
    "sg:phone":"+49 721/986500",
    "sg:postcode":"76135",
    "sg:province":"Baden-W\u00fcrttemberg",
    "wof:name":"Winkler Gmbh",
    "wof:placetype":"venue"
},
  "geometry": {"coordinates":[8.3721561432,48.9933929443],"type":"Point"}
}