{
  "type": "Feature",
  "properties": {
    "iso:country":"DE",
    "sg:address":"B\u00e4ckergasse 2",
    "sg:city":"D\u00fcsseldorf",
    "sg:phone":"+49 211/320486",
    "sg:postcode":"40213",
    "sg:province":"Nordrhein-Westfalen",
    "wof:name":"H.-t. Hahn Steuerberater",
    "wof:placetype":"venue"
},
  "geometry": {"coordinates":[6.77039814,51.2224731445],"type":"Point"}
}