{
  "type": "Feature",
  "properties": {
    "iso:country":"DE",
    "sg:address":"Kugelb\u00fchlstr. 3",
    "sg:city":"Roth",
    "sg:phone":"+49 9171/2027",
    "sg:postcode":"91154",
    "sg:province":"Bayern",
    "wof:name":"Hypo-bank Ag",
    "wof:placetype":"venue"
},
  "geometry": {"coordinates":[11.091303,49.245472],"type":"Point"}
}