{
  "type": "Feature",
  "properties": {
    "iso:country":"DE",
    "sg:address":"Hauptstr. 23",
    "sg:city":"Partenstein",
    "sg:phone":"+49 9355/557",
    "sg:postcode":"97846",
    "sg:province":"Bayern",
    "wof:name":"Fritz Amend Architekt Und Ingenieur",
    "wof:placetype":"venue"
},
  "geometry": {"coordinates":[9.518728,50.040516],"type":"Point"}
}