{
  "type": "Feature",
  "properties": {
    "iso:country":"DE",
    "sg:address":"Am Markt 6",
    "sg:city":"L\u00fcbz",
    "sg:phone":"+49 38731/25999",
    "sg:postcode":"19386",
    "sg:province":"Mecklenburg-Vorpommern",
    "wof:name":"D. Stubbe",
    "wof:placetype":"venue"
},
  "geometry": {"coordinates":[12.0303153992,53.4623260498],"type":"Point"}
}