{
  "type": "Feature",
  "properties": {
    "iso:country":"DE",
    "sg:address":"Carl-vom-Hagen-Str. 11",
    "sg:city":"Schwelm",
    "sg:postcode":"58332",
    "sg:province":"Nordrhein-Westfalen",
    "wof:name":"Euteneuer Schmidt Und Burghardt Kg",
    "wof:placetype":"venue"
},
  "geometry": {"coordinates":[7.282445,51.288891],"type":"Point"}
}