{
  "type": "Feature",
  "properties": {
    "iso:country":"DE",
    "sg:address":"Grafenberger Allee 100",
    "sg:city":"D\u00fcsseldorf",
    "sg:phone":"+49 211/9682215",
    "sg:postcode":"40237",
    "sg:province":"Nordrhein-Westfalen",
    "wof:name":"Karl Rauch Verlag Kg",
    "wof:placetype":"venue"
},
  "geometry": {"coordinates":[6.8040571213,51.2311210632],"type":"Point"}
}