{
  "type": "Feature",
  "properties": {
    "iso:country":"DE",
    "sg:address":"Panr\u00f6der Stra\u00dfe 21",
    "sg:city":"Burgschwalbach",
    "sg:phone":"+49 6430",
    "sg:postcode":"65558",
    "sg:province":"Rheinland-Pfalz",
    "wof:name":"Elektro-assmann",
    "wof:placetype":"venue"
},
  "geometry": {"coordinates":[8.083035,50.283272],"type":"Point"}
}