{
  "type": "Feature",
  "properties": {
    "iso:country":"DE",
    "sg:address":"Xantener Str. 10",
    "sg:city":"D\u00fcsseldorf",
    "sg:phone":"+49 211",
    "sg:postcode":"40474",
    "sg:province":"Nordrhein-Westfalen",
    "wof:name":"Hfu Hermann Fuchslocher Unternehmensberatung Gmbh (bdu)",
    "wof:placetype":"venue"
},
  "geometry": {"coordinates":[6.7637338638,51.2489624023],"type":"Point"}
}