{
  "type": "Feature",
  "properties": {
    "iso:country":"DE",
    "sg:address":"Wilhelmstr. 19",
    "sg:city":"Soltau",
    "sg:phone":"+49 5191/2120",
    "sg:postcode":"29614",
    "sg:province":"Niedersachsen",
    "wof:name":"Spielzeug Eilitz Ohg",
    "wof:placetype":"venue"
},
  "geometry": {"coordinates":[9.8432950974,52.9869422913],"type":"Point"}
}