{
  "type": "Feature",
  "properties": {
    "iso:country":"DE",
    "sg:address":"Cainsdorfer Str. 9",
    "sg:city":"Wilkau-Ha\u00dflau",
    "sg:phone":"+49 375/671673",
    "sg:postcode":"08112",
    "sg:province":"Sachsen",
    "wof:name":"Wolfgang Rauch",
    "wof:placetype":"venue"
},
  "geometry": {"coordinates":[12.513920784,50.6735115051],"type":"Point"}
}