{
  "type": "Feature",
  "properties": {
    "iso:country":"DE",
    "sg:address":"K\u00f6nigsfahrt 2",
    "sg:city":"Ahnatal",
    "sg:phone":"+49 5609/302",
    "sg:postcode":"34292",
    "sg:province":"Hessen",
    "wof:name":"U. Steube",
    "wof:placetype":"venue"
},
  "geometry": {"coordinates":[9.3921670914,51.3658409119],"type":"Point"}
}