{
  "type": "Feature",
  "properties": {
    "iso:country":"DE",
    "sg:address":"Friesenstr. 45",
    "sg:city":"Neuwied",
    "sg:phone":"+49 2631/75755",
    "sg:postcode":"56567",
    "sg:province":"Rheinland-Pfalz",
    "wof:name":"Waltraud Schneider Heilpraktikerin",
    "wof:placetype":"venue"
},
  "geometry": {"coordinates":[7.4418430328,50.4508094788],"type":"Point"}
}