{
  "type": "Feature",
  "properties": {
    "iso:country":"DE",
    "sg:address":"Silberhauckstr. 9",
    "sg:city":"Hilders",
    "sg:phone":"+49 6681/238",
    "sg:postcode":"36115",
    "sg:province":"Hessen",
    "wof:name":"Franz Ernst",
    "wof:placetype":"venue"
},
  "geometry": {"coordinates":[9.95067,50.566486],"type":"Point"}
}