{
  "type": "Feature",
  "properties": {
    "iso:country":"DE",
    "sg:address":"Wiemecker Feld 9",
    "sg:city":"Bestwig",
    "sg:phone":"+49 2904/1258",
    "sg:postcode":"59909",
    "sg:province":"Nordrhein-Westfalen",
    "wof:name":"Stemper Gmbh",
    "wof:placetype":"venue"
},
  "geometry": {"coordinates":[8.368097,51.35545],"type":"Point"}
}