{
  "type": "Feature",
  "properties": {
    "iso:country":"DE",
    "sg:address":"Bienenweg 4",
    "sg:city":"K\u00f6nigsfeld",
    "sg:phone":"+49 9207/237",
    "sg:postcode":"96167",
    "sg:province":"Bayern",
    "wof:name":"B\u00f6hlein Treppenbau Schreinerei Verwaltungs Gmbh",
    "wof:placetype":"venue"
},
  "geometry": {"coordinates":[11.172203064,49.9466056824],"type":"Point"}
}