{
  "type": "Feature",
  "properties": {
    "iso:country":"DE",
    "sg:address":"Niedieckstr. 47-49",
    "sg:city":"Nettetal",
    "sg:phone":"+49 2153/91830",
    "sg:postcode":"41334",
    "sg:province":"Nordrhein-Westfalen",
    "wof:name":"Longlife Teppichboden Bernd Cleven Gmbh & Co.",
    "wof:placetype":"venue"
},
  "geometry": {"coordinates":[6.2772688866,51.310459137],"type":"Point"}
}