{
  "type": "Feature",
  "properties": {
    "iso:country":"DE",
    "sg:address":"Ringstr. 24",
    "sg:city":"Eiterfeld",
    "sg:phone":"+49 6672/400",
    "sg:postcode":"36132",
    "sg:province":"Hessen",
    "wof:name":"Werner Lutz",
    "wof:placetype":"venue"
},
  "geometry": {"coordinates":[9.8038330078,50.762840271],"type":"Point"}
}