{
  "type": "Feature",
  "properties": {
    "iso:country":"DE",
    "sg:address":"Heidenheimer Str. 41",
    "sg:city":"Oberkochen",
    "sg:phone":"+49 7364/41201",
    "sg:postcode":"73447",
    "sg:province":"Baden-W\u00fcrttemberg",
    "wof:name":"Graffiti",
    "wof:placetype":"venue"
},
  "geometry": {"coordinates":[10.1042098999,48.7818145752],"type":"Point"}
}