{
  "type": "Feature",
  "properties": {
    "iso:country":"DE",
    "sg:address":"Wilhelmstr. 23",
    "sg:city":"Bad Urach",
    "sg:phone":"+49 7125/14508",
    "sg:postcode":"72574",
    "sg:province":"Baden-W\u00fcrttemberg",
    "wof:name":"A. Kazantzidis",
    "wof:placetype":"venue"
},
  "geometry": {"coordinates":[9.4007310867,48.4919052124],"type":"Point"}
}