{
  "type": "Feature",
  "properties": {
    "iso:country":"DE",
    "sg:address":"Kaiser-Wilhelm-Ring 82",
    "sg:city":"Mainz",
    "sg:phone":"+49 6131/613767",
    "sg:postcode":"55118",
    "sg:province":"Rheinland-Pfalz",
    "wof:name":"Einstein",
    "wof:placetype":"venue"
},
  "geometry": {"coordinates":[8.2533693314,50.0080947876],"type":"Point"}
}