{
  "type": "Feature",
  "properties": {
    "iso:country":"DE",
    "sg:address":"Wasastr. 13",
    "sg:city":"Radebeul",
    "sg:phone":"+49 351/8384713",
    "sg:postcode":"01445",
    "sg:province":"Sachsen",
    "wof:name":"Klaus Papendick",
    "wof:placetype":"venue"
},
  "geometry": {"coordinates":[13.665444,51.098621],"type":"Point"}
}