{
  "type": "Feature",
  "properties": {
    "iso:country":"DE",
    "sg:address":"Hauptstr. 1a",
    "sg:city":"Isernhagen",
    "sg:phone":"+49 5139/5599",
    "sg:postcode":"30916",
    "sg:province":"Niedersachsen",
    "wof:name":"Valentines Exclusive Car Rent",
    "wof:placetype":"venue"
},
  "geometry": {"coordinates":[9.8339605331,52.4679260254],"type":"Point"}
}