{
  "type": "Feature",
  "properties": {
    "iso:country":"DE",
    "sg:address":"Im Grunde 59",
    "sg:city":"Unterl\u00fc\u00df",
    "sg:phone":"+49 9761/91400",
    "sg:postcode":"29345",
    "sg:province":"Niedersachsen",
    "wof:name":"Dipl.-ing. Erdmann Nenninger Nachfolger Gmbh",
    "wof:placetype":"venue"
},
  "geometry": {"coordinates":[10.46766,50.29932],"type":"Point"}
}