{
  "type": "Feature",
  "properties": {
    "iso:country":"DE",
    "sg:address":"Eibenstocker Str. 17",
    "sg:city":"Sch\u00f6nheide",
    "sg:phone":"+49 37755/4233",
    "sg:postcode":"08304",
    "sg:province":"Sachsen",
    "wof:name":"Hirsch Pinsel Gmbh",
    "wof:placetype":"venue"
},
  "geometry": {"coordinates":[12.5446119308,50.5064735413],"type":"Point"}
}