{
  "type": "Feature",
  "properties": {
    "iso:country":"DE",
    "sg:address":"B\u00fcrkleinstr. 20",
    "sg:city":"M\u00fcnchen",
    "sg:postcode":"80538",
    "sg:province":"Bayern",
    "wof:name":"Praxisverbund Gmbh",
    "wof:placetype":"venue"
},
  "geometry": {"coordinates":[11.586730957,48.1392059326],"type":"Point"}
}