{
  "type": "Feature",
  "properties": {
    "iso:country":"DE",
    "sg:address":"Mooswaldstr. 99",
    "sg:city":"Freiburg",
    "sg:postcode":"79108",
    "sg:province":"Baden-W\u00fcrttemberg",
    "wof:name":"Hochdorf-automaten Gmbh",
    "wof:placetype":"venue"
},
  "geometry": {"coordinates":[7.8110718727,48.0455513],"type":"Point"}
}