{
  "type": "Feature",
  "properties": {
    "iso:country":"DE",
    "sg:address":"Gr\u00f6ninger Str. 23",
    "sg:city":"Ditzingen",
    "sg:phone":"+49 7156/330510",
    "sg:postcode":"71254",
    "sg:province":"Baden-W\u00fcrttemberg",
    "wof:name":"Hoffmann & Moser Innenausbau Gmbh",
    "wof:placetype":"venue"
},
  "geometry": {"coordinates":[9.069589,48.830116],"type":"Point"}
}