{
  "type": "Feature",
  "properties": {
    "iso:country":"DE",
    "sg:address":"Talamtstr. 5",
    "sg:city":"Halle",
    "sg:phone":"+49 345/501924",
    "sg:postcode":"06108",
    "sg:province":"Sachsen-Anhalt",
    "wof:name":"E. Und R. Sch\u00f6ne",
    "wof:placetype":"venue"
},
  "geometry": {"coordinates":[11.9671535492,51.4825973511],"type":"Point"}
}