{
  "type": "Feature",
  "properties": {
    "iso:country":"DE",
    "sg:address":"Kornmarktstr. 12a",
    "sg:city":"Preist",
    "sg:phone":"+49 6562/3093",
    "sg:postcode":"54664",
    "sg:province":"Rheinland-Pfalz",
    "wof:name":"Dr. Med. Ludwig Grobe",
    "wof:placetype":"venue"
},
  "geometry": {"coordinates":[6.632123,49.907658],"type":"Point"}
}