{
  "type": "Feature",
  "properties": {
    "iso:country":"DE",
    "sg:address":"Burchardstr. 14",
    "sg:city":"Hamburg",
    "sg:postcode":"20095",
    "sg:province":"Hamburg",
    "wof:name":"Grundst\u00fccksgesellschaft Billstra\u00dfe 82-84 Mbh",
    "wof:placetype":"venue"
},
  "geometry": {"coordinates":[10.002657,53.548779],"type":"Point"}
}