{
  "type": "Feature",
  "properties": {
    "iso:country":"DE",
    "sg:address":"Neustr.2",
    "sg:city":"Westerburg",
    "sg:phone":"+49 2663/4750",
    "sg:postcode":"56457",
    "sg:province":"Rheinland-Pfalz",
    "wof:name":"Schluessel Zum Herzen - Alles Rund Ums Herz",
    "wof:placetype":"venue"
},
  "geometry": {"coordinates":[7.969392,50.562607],"type":"Point"}
}