{
  "type": "Feature",
  "properties": {
    "iso:country":"DE",
    "sg:address":"Huestr. 135",
    "sg:city":"Essen",
    "sg:phone":"+49 201/211416",
    "sg:postcode":"45309",
    "sg:province":"Nordrhein-Westfalen",
    "wof:name":"E. Balzer",
    "wof:placetype":"venue"
},
  "geometry": {"coordinates":[7.0639610291,51.4862861633],"type":"Point"}
}