{
  "type": "Feature",
  "properties": {
    "iso:country":"DE",
    "sg:address":"Allmannshausen 13",
    "sg:city":"Montabaur",
    "sg:phone":"+49 3491/41710",
    "sg:postcode":"56410",
    "sg:province":"Rheinland-Pfalz",
    "wof:name":"Wimetec Wittenberger Metallbau Gmbh",
    "wof:placetype":"venue"
},
  "geometry": {"coordinates":[12.651135,51.86599],"type":"Point"}
}