{
  "type": "Feature",
  "properties": {
    "iso:country":"DE",
    "sg:address":"Dangast",
    "sg:city":"Varel",
    "sg:phone":"+49 4451/4951",
    "sg:postcode":"26316",
    "sg:province":"Niedersachsen",
    "wof:name":"G\u00e4stehaus Udo Carstens",
    "wof:placetype":"venue"
},
  "geometry": {"coordinates":[8.1180095673,53.4424095154],"type":"Point"}
}