{
  "type": "Feature",
  "properties": {
    "iso:country":"DE",
    "sg:address":"Finkenstr. 3",
    "sg:city":"Langenbach",
    "sg:phone":"+49 8761/5333",
    "sg:postcode":"85416",
    "sg:province":"Bayern",
    "wof:name":"Lichtenauer & Schober Gmbh",
    "wof:placetype":"venue"
},
  "geometry": {"coordinates":[11.8545227051,48.4375953674],"type":"Point"}
}