{
  "type": "Feature",
  "properties": {
    "iso:country":"DE",
    "sg:address":"Verdistr. 4",
    "sg:city":"Worms",
    "sg:phone":"+49 6241/938410",
    "sg:postcode":"67551",
    "sg:province":"Rheinland-Pfalz",
    "wof:name":"Topware Teachware Gmbh",
    "wof:placetype":"venue"
},
  "geometry": {"coordinates":[8.257352829,49.6029396057],"type":"Point"}
}