{
  "type": "Feature",
  "properties": {
    "iso:country":"DE",
    "sg:address":"Karrystr. 1",
    "sg:city":"Fulda",
    "sg:postcode":"36041",
    "sg:province":"Hessen",
    "wof:name":"Gedis Gesellschaft F\u00fcr Elektronische Daten Und",
    "wof:placetype":"venue"
},
  "geometry": {"coordinates":[9.60418,50.554111],"type":"Point"}
}