{
  "type": "Feature",
  "properties": {
    "iso:country":"DE",
    "sg:address":"Greifswalder Chaussee 61",
    "sg:city":"Stralsund",
    "sg:postcode":"18439",
    "sg:province":"Mecklenburg-Vorpommern",
    "wof:name":"Gpg",
    "wof:placetype":"venue"
},
  "geometry": {"coordinates":[13.099795,54.282581],"type":"Point"}
}