{
  "type": "Feature",
  "properties": {
    "iso:country":"DE",
    "sg:address":"Ortrander Str. 18",
    "sg:city":"Lauchhammer",
    "sg:phone":"+49 3574/2828",
    "sg:postcode":"01979",
    "sg:province":"Brandenburg",
    "wof:name":"H. Nicklisch",
    "wof:placetype":"venue"
},
  "geometry": {"coordinates":[13.764557,51.492561],"type":"Point"}
}