{
  "type": "Feature",
  "properties": {
    "iso:country":"DE",
    "sg:address":"Nebenstr. 28",
    "sg:city":"M\u00fclsen",
    "sg:phone":"+49 37601/58622",
    "sg:postcode":"08132",
    "sg:province":"Sachsen",
    "wof:name":"H\u00f6lzel & O\u00dfmann Gmbh",
    "wof:placetype":"venue"
},
  "geometry": {"coordinates":[12.5375137329,50.7722511292],"type":"Point"}
}