{
  "type": "Feature",
  "properties": {
    "iso:country":"DE",
    "sg:address":"Im Gleisbogen 10",
    "sg:city":"Marl",
    "sg:phone":"+49 2365/888990",
    "sg:postcode":"45770",
    "sg:province":"Nordrhein-Westfalen",
    "wof:name":"Var Gmbh",
    "wof:placetype":"venue"
},
  "geometry": {"coordinates":[7.15831,51.673943],"type":"Point"}
}