{
  "type": "Feature",
  "properties": {
    "iso:country":"DE",
    "sg:address":"Maximilianstr. 99",
    "sg:city":"Speyer",
    "sg:phone":"+49 6232/6610",
    "sg:postcode":"67346",
    "sg:province":"Rheinland-Pfalz",
    "wof:name":"Abwasser-entsorgungs Gmbh",
    "wof:placetype":"venue"
},
  "geometry": {"coordinates":[8.440222,49.317417],"type":"Point"}
}