{
  "type": "Feature",
  "properties": {
    "iso:country":"DE",
    "sg:address":"Hauptstr. 56",
    "sg:city":"Tannhausen",
    "sg:phone":"+49 4979/641414",
    "sg:postcode":"73497",
    "sg:province":"Baden-W\u00fcrttemberg",
    "wof:name":"Kreissparkasse Ostalb",
    "wof:placetype":"venue"
},
  "geometry": {"coordinates":[10.364484,48.979652],"type":"Point"}
}