{
  "type": "Feature",
  "properties": {
    "iso:country":"DE",
    "sg:address":"Deutsche Str. 131",
    "sg:city":"Dortmund",
    "sg:phone":"+49 231/852930",
    "sg:postcode":"44339",
    "sg:province":"Nordrhein-Westfalen",
    "wof:name":"Wolfram Schulte-r\u00f6dding Rechtsanwalt",
    "wof:placetype":"venue"
},
  "geometry": {"coordinates":[7.4732050896,51.5543937683],"type":"Point"}
}