{
  "type": "Feature",
  "properties": {
    "iso:country":"DE",
    "sg:address":"Alfelder Str. 20",
    "sg:city":"Freden",
    "sg:phone":"+49 5184/200",
    "sg:postcode":"31084",
    "sg:province":"Niedersachsen",
    "wof:name":"Tacan Gmbh",
    "wof:placetype":"venue"
},
  "geometry": {"coordinates":[9.89926,51.92952],"type":"Point"}
}