{
  "type": "Feature",
  "properties": {
    "iso:country":"DE",
    "sg:address":"Querstr. 2",
    "sg:city":"Gotha",
    "sg:phone":"+49 3621/853670",
    "sg:postcode":"99867",
    "sg:province":"Th\u00fcringen",
    "wof:name":"Benkert & Kaulen-optik Gmbh",
    "wof:placetype":"venue"
},
  "geometry": {"coordinates":[10.703576088,50.9497871399],"type":"Point"}
}