{
  "type": "Feature",
  "properties": {
    "iso:country":"DE",
    "sg:address":"Im Eisfeld 3",
    "sg:city":"Grebenau",
    "sg:phone":"+49 6646/919120",
    "sg:postcode":"36323",
    "sg:province":"Hessen",
    "wof:name":"Remo-bau Gmbh",
    "wof:placetype":"venue"
},
  "geometry": {"coordinates":[9.424781,50.722965],"type":"Point"}
}