{
  "type": "Feature",
  "properties": {
    "iso:country":"DE",
    "sg:address":"Bahnhofstr. 11",
    "sg:city":"Herscheid",
    "sg:postcode":"58849",
    "sg:province":"Nordrhein-Westfalen",
    "wof:name":"Westmark Haushaltswaren- Fabrik Gmbh & Co. Kg",
    "wof:placetype":"venue"
},
  "geometry": {"coordinates":[7.7483911514,51.1769485474],"type":"Point"}
}