{
  "type": "Feature",
  "properties": {
    "iso:country":"DE",
    "sg:address":"Alsterdorfer Str. 254",
    "sg:city":"Hamburg",
    "sg:phone":"+49 40/5116610",
    "sg:postcode":"22297",
    "sg:province":"Hamburg",
    "wof:name":"Cpt-hamburg Handels Gmbh",
    "wof:placetype":"venue"
},
  "geometry": {"coordinates":[10.0056371689,53.6072502136],"type":"Point"}
}