{
  "type": "Feature",
  "properties": {
    "iso:country":"DE",
    "sg:address":"Rollo\u00dfweg 29",
    "sg:city":"Heidelberg",
    "sg:phone":"+49 6221/470980",
    "sg:postcode":"69121",
    "sg:province":"Baden-W\u00fcrttemberg",
    "wof:name":"P. Depre Rechtsanwalt",
    "wof:placetype":"venue"
},
  "geometry": {"coordinates":[8.6901035309,49.4302940369],"type":"Point"}
}