{
  "type": "Feature",
  "properties": {
    "iso:country":"DE",
    "sg:address":"Martin-Luther-Str. 3",
    "sg:city":"Freudenstadt",
    "sg:phone":"+49 7441/869961",
    "sg:postcode":"72250",
    "sg:province":"Baden-W\u00fcrttemberg",
    "wof:name":"Hotel-restaurant Drei K\u00f6nig",
    "wof:placetype":"venue"
},
  "geometry": {"coordinates":[8.4103765488,48.4649124146],"type":"Point"}
}