{
  "type": "Feature",
  "properties": {
    "iso:country":"DE",
    "sg:address":"Kirchenstr. 10",
    "sg:city":"Schifferstadt",
    "sg:phone":"+49 6235/3850",
    "sg:postcode":"67105",
    "sg:province":"Rheinland-Pfalz",
    "wof:name":"Kath. Pfarramt St. Jakobus",
    "wof:placetype":"venue"
},
  "geometry": {"coordinates":[8.3725671768,49.3873329163],"type":"Point"}
}