{
  "type": "Feature",
  "properties": {
    "iso:country":"DE",
    "sg:address":"Am See 27",
    "sg:city":"Bebensee",
    "sg:phone":"+49 4552/9528",
    "sg:postcode":"23816",
    "sg:province":"Schleswig-Holstein",
    "wof:name":"Hermann Schreyer Ingenieur",
    "wof:placetype":"venue"
},
  "geometry": {"coordinates":[10.2937793732,53.8734970093],"type":"Point"}
}