{
  "type": "Feature",
  "properties": {
    "iso:country":"DE",
    "sg:address":"Cottbuser Str. 52",
    "sg:city":"K\u00f6nigs Wusterhausen",
    "sg:phone":"+49 3375/293445",
    "sg:postcode":"15711",
    "sg:province":"Brandenburg",
    "wof:name":"Werner Paustian",
    "wof:placetype":"venue"
},
  "geometry": {"coordinates":[13.6251735687,52.2955322266],"type":"Point"}
}