{
  "type": "Feature",
  "properties": {
    "iso:country":"DE",
    "sg:address":"Eichendorffstr. 47",
    "sg:city":"Wesseling",
    "sg:phone":"+49 2236/48798",
    "sg:postcode":"50389",
    "sg:province":"Nordrhein-Westfalen",
    "wof:name":"F. Marx Tapeten",
    "wof:placetype":"venue"
},
  "geometry": {"coordinates":[6.9763908386,50.814453125],"type":"Point"}
}