{
  "type": "Feature",
  "properties": {
    "iso:country":"DE",
    "sg:address":"Walddorfer Str. 79",
    "sg:city":"Altenriet",
    "sg:phone":"+49 7127/93270",
    "sg:postcode":"72657",
    "sg:province":"Baden-W\u00fcrttemberg",
    "wof:name":"Fenchel Wohnfaszination Gmbh",
    "wof:placetype":"venue"
},
  "geometry": {"coordinates":[9.215333,48.590504],"type":"Point"}
}