{
  "type": "Feature",
  "properties": {
    "iso:country":"DE",
    "sg:address":"Ganghoferstr. 10",
    "sg:city":"Welden",
    "sg:phone":"+49 8293/6353",
    "sg:postcode":"86465",
    "sg:province":"Bayern",
    "wof:name":"Alfred Gamperling",
    "wof:placetype":"venue"
},
  "geometry": {"coordinates":[10.659848,48.458023],"type":"Point"}
}