{
  "type": "Feature",
  "properties": {
    "iso:country":"DE",
    "sg:address":"Poppenreuther Str. 64",
    "sg:city":"F\u00fcrth",
    "sg:phone":"+49 911/7906181",
    "sg:postcode":"90765",
    "sg:province":"Bayern",
    "wof:name":"B. Thaler",
    "wof:placetype":"venue"
},
  "geometry": {"coordinates":[11.006656,49.481647],"type":"Point"}
}