{
  "type": "Feature",
  "properties": {
    "iso:country":"DE",
    "sg:address":"Leipziger Ring 203",
    "sg:city":"Rodgau",
    "sg:phone":"+49 6106/75535",
    "sg:postcode":"63110",
    "sg:province":"Hessen",
    "wof:name":"Inpro Planungsgesell- Schaft Mbh & Co.",
    "wof:placetype":"venue"
},
  "geometry": {"coordinates":[8.87858,50.004539],"type":"Point"}
}