{
  "type": "Feature",
  "properties": {
    "iso:country":"DE",
    "sg:address":"Auf der Hohl 3",
    "sg:city":"Niederwambach",
    "sg:phone":"+49 2681/989230",
    "sg:postcode":"57614",
    "sg:province":"Rheinland-Pfalz",
    "wof:name":"H. Wurst",
    "wof:placetype":"venue"
},
  "geometry": {"coordinates":[7.591864,50.649967],"type":"Point"}
}