{
  "type": "Feature",
  "properties": {
    "iso:country":"DE",
    "sg:address":"Osnabr\u00fccker Str 7",
    "sg:city":"Westerkappeln",
    "sg:phone":"+49 5404/2060",
    "sg:postcode":"49492",
    "sg:province":"Nordrhein-Westfalen",
    "wof:name":"Tischlerei & Innenausbau T\u00fcpker",
    "wof:placetype":"venue"
},
  "geometry": {"coordinates":[7.8800978661,52.3131370544],"type":"Point"}
}