{
  "type": "Feature",
  "properties": {
    "iso:country":"DE",
    "sg:address":"Untere Schulstr. 11",
    "sg:city":"Lo\u00dfburg",
    "sg:phone":"+49 7446/579",
    "sg:postcode":"72290",
    "sg:province":"Baden-W\u00fcrttemberg",
    "wof:name":"Siegfried Silzle",
    "wof:placetype":"venue"
},
  "geometry": {"coordinates":[8.446949,48.414066],"type":"Point"}
}