{
  "type": "Feature",
  "properties": {
    "iso:country":"DE",
    "sg:address":"Annenallee 13",
    "sg:city":"Berlin",
    "sg:phone":"+49 30/6572036",
    "sg:postcode":"12555",
    "sg:province":"Berlin",
    "wof:name":"Dr. Med. Eberhard Otto",
    "wof:placetype":"venue"
},
  "geometry": {"coordinates":[13.571738,52.455055],"type":"Point"}
}