{
  "type": "Feature",
  "properties": {
    "iso:country":"DE",
    "sg:address":"Dachauer Str. 511",
    "sg:city":"M\u00fcnchen",
    "sg:phone":"+49 89/991134",
    "sg:postcode":"80993",
    "sg:province":"Bayern",
    "wof:name":"Minimax Gmbh",
    "wof:placetype":"venue"
},
  "geometry": {"coordinates":[11.503063,48.188614],"type":"Point"}
}