{
  "type": "Feature",
  "properties": {
    "iso:country":"DE",
    "sg:address":"Jahnstr. 30",
    "sg:city":"Plankstadt",
    "sg:phone":"+49 6202/26325",
    "sg:postcode":"68723",
    "sg:province":"Baden-W\u00fcrttemberg",
    "wof:name":"Tenniszentrum Wintergarten",
    "wof:placetype":"venue"
},
  "geometry": {"coordinates":[8.5898590088,49.3961982727],"type":"Point"}
}