{
  "type": "Feature",
  "properties": {
    "iso:country":"DE",
    "sg:address":"Kirchstr. 5",
    "sg:city":"Wut\u00f6schingen",
    "sg:phone":"+49 7746/8520",
    "sg:postcode":"79793",
    "sg:province":"Baden-W\u00fcrttemberg",
    "wof:name":"Kommunalbau Wut\u00f6schingen Gmbh",
    "wof:placetype":"venue"
},
  "geometry": {"coordinates":[8.3648662567,47.6597175598],"type":"Point"}
}