{
  "type": "Feature",
  "properties": {
    "iso:country":"DE",
    "sg:address":"Feldstr. 45",
    "sg:city":"Dietzenbach",
    "sg:phone":"+49 6074/42110",
    "sg:postcode":"63128",
    "sg:province":"Hessen",
    "wof:name":"Ricophon Tontr\u00e4ger Vertriebs Gmbh",
    "wof:placetype":"venue"
},
  "geometry": {"coordinates":[8.7702236176,50.0100898743],"type":"Point"}
}