{
  "type": "Feature",
  "properties": {
    "iso:country":"DE",
    "sg:address":"Am Kirchfeld 6",
    "sg:city":"Hille",
    "sg:phone":"+49 571/44695",
    "sg:postcode":"32479",
    "sg:province":"Nordrhein-Westfalen",
    "wof:name":"Harald Von Der Ahe Ingenieur",
    "wof:placetype":"venue"
},
  "geometry": {"coordinates":[8.8258066177,52.313835144],"type":"Point"}
}