{
  "type": "Feature",
  "properties": {
    "iso:country":"DE",
    "sg:address":"Bahnhofplatz 2",
    "sg:city":"Lenggries",
    "sg:phone":"+49 8042/8711",
    "sg:postcode":"83661",
    "sg:province":"Bayern",
    "wof:name":"Deutsche Bahn Ag",
    "wof:placetype":"venue"
},
  "geometry": {"coordinates":[11.5739526749,47.6797370911],"type":"Point"}
}