{
  "type": "Feature",
  "properties": {
    "iso:country":"DE",
    "sg:address":"Hamburger Str. 76",
    "sg:city":"Ahrensburg",
    "sg:phone":"+49 4102/54938",
    "sg:postcode":"22926",
    "sg:province":"Schleswig-Holstein",
    "wof:name":"W. Rughase",
    "wof:placetype":"venue"
},
  "geometry": {"coordinates":[10.2287549973,53.6680488586],"type":"Point"}
}