{
  "type": "Feature",
  "properties": {
    "iso:country":"DE",
    "sg:address":"Rosenstr. 6-9::",
    "sg:city":"Wiesbaden",
    "sg:phone":"+49 4961/136120",
    "sg:postcode":"65189",
    "sg:province":"Hessen",
    "wof:name":"Lotterie-treuhand Gmbh",
    "wof:placetype":"venue"
},
  "geometry": {"coordinates":[8.24931,50.081387],"type":"Point"}
}