{
  "type": "Feature",
  "properties": {
    "iso:country":"DE",
    "sg:address":"Hattinger Str. 334",
    "sg:city":"Bochum",
    "sg:phone":"+49 234/431421",
    "sg:postcode":"44795",
    "sg:province":"Nordrhein-Westfalen",
    "wof:name":"Alte Apotheke",
    "wof:placetype":"venue"
},
  "geometry": {"coordinates":[7.192516,51.451775],"type":"Point"}
}