{
  "type": "Feature",
  "properties": {
    "iso:country":"DE",
    "sg:address":"M\u00fcnsterstra\u00dfe 50",
    "sg:city":"Lengerich",
    "sg:phone":"+49 5481/140",
    "sg:postcode":"49525",
    "sg:province":"Nordrhein-Westfalen",
    "wof:name":"Windm\u00d6ller & H\u00d6lscher",
    "wof:placetype":"venue"
},
  "geometry": {"coordinates":[7.8489580154,52.1846046448],"type":"Point"}
}