{
  "type": "Feature",
  "properties": {
    "iso:country":"DE",
    "sg:address":"D\u00f6rffurtstr. 8",
    "sg:city":"Lutherstadt Wittenberg",
    "sg:phone":"+49 3491/407164",
    "sg:postcode":"06886",
    "sg:province":"Sachsen-Anhalt",
    "wof:name":"Primus Projektentwicklungsges. Mbh",
    "wof:placetype":"venue"
},
  "geometry": {"coordinates":[12.6395406723,51.8740310669],"type":"Point"}
}