{
  "type": "Feature",
  "properties": {
    "iso:country":"DE",
    "sg:address":"Freudenbergstr. 2",
    "sg:city":"Neuenburg",
    "sg:phone":"+49 7631/7593",
    "sg:postcode":"79395",
    "sg:province":"Baden-W\u00fcrttemberg",
    "wof:name":"Otto Kuhn",
    "wof:placetype":"venue"
},
  "geometry": {"coordinates":[7.5536088943,47.8069343567],"type":"Point"}
}