{
  "type": "Feature",
  "properties": {
    "iso:country":"DE",
    "sg:address":"Alemannenstr. 8",
    "sg:city":"Augsburg",
    "sg:phone":"+49 821/991820",
    "sg:postcode":"86199",
    "sg:province":"Bayern",
    "wof:name":"Proha Handels Gmbh",
    "wof:placetype":"venue"
},
  "geometry": {"coordinates":[10.872344017,48.3386611938],"type":"Point"}
}