{
  "type": "Feature",
  "properties": {
    "iso:country":"DE",
    "sg:address":"Hemsothstr. 28",
    "sg:city":"Lamstedt",
    "sg:phone":"+49 4773/892091",
    "sg:postcode":"21769",
    "sg:province":"Niedersachsen",
    "wof:name":"Lamstedter Musik Shop",
    "wof:placetype":"venue"
},
  "geometry": {"coordinates":[9.1035928726,53.6360588074],"type":"Point"}
}