{
  "type": "Feature",
  "properties": {
    "iso:country":"DE",
    "sg:address":"Lothringer Str. 22",
    "sg:city":"Duisburg",
    "sg:phone":"+49 2066/56051",
    "sg:postcode":"47198",
    "sg:province":"Nordrhein-Westfalen",
    "wof:name":"Rhein Und See Speditions- Gesellschaft Mbh & Co",
    "wof:placetype":"venue"
},
  "geometry": {"coordinates":[6.7030930519,51.4571647644],"type":"Point"}
}