{
  "type": "Feature",
  "properties": {
    "iso:country":"DE",
    "sg:address":"Feldbergring 64",
    "sg:city":"Langenselbold",
    "sg:phone":"+49 6184/7423",
    "sg:postcode":"63505",
    "sg:province":"Hessen",
    "wof:name":"Mematic Gmbh",
    "wof:placetype":"venue"
},
  "geometry": {"coordinates":[9.0262556076,50.1836738586],"type":"Point"}
}