{
  "type": "Feature",
  "properties": {
    "iso:country":"DE",
    "sg:address":"Ostermeedlandsweg 27/29",
    "sg:city":"Leer",
    "sg:phone":"+49 4967/990189",
    "sg:postcode":"26789",
    "sg:province":"Niedersachsen",
    "wof:name":"Special-service Matthias Mitzlaff",
    "wof:placetype":"venue"
},
  "geometry": {"coordinates":[7.471016,53.224876],"type":"Point"}
}