{
  "type": "Feature",
  "properties": {
    "iso:country":"DE",
    "sg:address":"Lange Str. 48",
    "sg:city":"Ahaus",
    "sg:phone":"+49 2561/987025",
    "sg:postcode":"48683",
    "sg:province":"Nordrhein-Westfalen",
    "wof:name":"H. Ostendorf Malerfachbetrieb",
    "wof:placetype":"venue"
},
  "geometry": {"coordinates":[6.9887609482,52.0798149109],"type":"Point"}
}