{
  "type": "Feature",
  "properties": {
    "iso:country":"DE",
    "sg:address":"Habichthorst 34-36",
    "sg:city":"Hamburg",
    "sg:phone":"+49 40/5558970",
    "sg:postcode":"22459",
    "sg:province":"Hamburg",
    "wof:name":"Technokom Service Gmbh",
    "wof:placetype":"venue"
},
  "geometry": {"coordinates":[9.957381,53.631084],"type":"Point"}
}