{
  "type": "Feature",
  "properties": {
    "iso:country":"DE",
    "sg:address":"Klein-Winternheimer-Weg 6",
    "sg:city":"Mainz",
    "sg:phone":"+49 6131/59678",
    "sg:postcode":"55129",
    "sg:province":"Rheinland-Pfalz",
    "wof:name":"Adam Schneider",
    "wof:placetype":"venue"
},
  "geometry": {"coordinates":[8.277699,49.957756],"type":"Point"}
}