{
  "type": "Feature",
  "properties": {
    "iso:country":"DE",
    "sg:address":"Steinergraben 3",
    "sg:city":"Werl",
    "sg:phone":"+49 2922/867730",
    "sg:postcode":"59457",
    "sg:province":"Nordrhein-Westfalen",
    "wof:name":"Fon & Fun",
    "wof:placetype":"venue"
},
  "geometry": {"coordinates":[7.9149451256,51.5526924133],"type":"Point"}
}