{
  "type": "Feature",
  "properties": {
    "iso:country":"DE",
    "sg:address":"Spittaplatz 3",
    "sg:city":"Burgdorf",
    "sg:postcode":"31303",
    "sg:province":"Niedersachsen",
    "wof:name":"Sozialberatung F. Werdende M\u00fctter-diak. Werk",
    "wof:placetype":"venue"
},
  "geometry": {"coordinates":[10.007086,52.445976],"type":"Point"}
}