{
  "type": "Feature",
  "properties": {
    "iso:country":"DE",
    "sg:address":"Fischerstr. 10",
    "sg:city":"Herbrechtingen",
    "sg:phone":"+49 7324/96480",
    "sg:postcode":"89542",
    "sg:province":"Baden-W\u00fcrttemberg",
    "wof:name":"Gerhard Benz Inh. Eva Christa Benz",
    "wof:placetype":"venue"
},
  "geometry": {"coordinates":[10.16261,48.631622],"type":"Point"}
}