{
  "type": "Feature",
  "properties": {
    "iso:country":"DE",
    "sg:address":"Hauptstr. 95",
    "sg:city":"Dittmannsdorf",
    "sg:phone":"+49 3725/5156",
    "sg:postcode":"09573",
    "sg:province":"Sachsen",
    "wof:name":"H. H\u00e4nel",
    "wof:placetype":"venue"
},
  "geometry": {"coordinates":[13.0410966873,50.7743263245],"type":"Point"}
}