{
  "type": "Feature",
  "properties": {
    "iso:country":"DE",
    "sg:city":"Unna",
    "sg:phone":"+49 2364/105794",
    "sg:postcode":"59423",
    "sg:province":"Nordrhein-Westfalen",
    "wof:name":"Solar-spirit",
    "wof:placetype":"venue"
},
  "geometry": {"coordinates":[7.68709,51.532413],"type":"Point"}
}