{
  "type": "Feature",
  "properties": {
    "iso:country":"DE",
    "sg:address":"Westring 29",
    "sg:city":"Worms",
    "sg:phone":"+49 6242/2279",
    "sg:postcode":"67550",
    "sg:province":"Rheinland-Pfalz",
    "wof:name":"F. Wennesheimer",
    "wof:placetype":"venue"
},
  "geometry": {"coordinates":[8.27738,49.675091],"type":"Point"}
}