{
  "type": "Feature",
  "properties": {
    "iso:country":"DE",
    "sg:address":"Taubenheimstr. 97A",
    "sg:city":"Stuttgart",
    "sg:phone":"+49 711/567333",
    "sg:postcode":"70372",
    "sg:province":"Baden-W\u00fcrttemberg",
    "wof:name":"Lauser & Gmelin Gmbh",
    "wof:placetype":"venue"
},
  "geometry": {"coordinates":[9.232625,48.799595],"type":"Point"}
}