{
  "type": "Feature",
  "properties": {
    "iso:country":"DE",
    "sg:address":"Heideweg 11",
    "sg:city":"Dissen",
    "sg:phone":"+49 5424/4570",
    "sg:postcode":"49201",
    "sg:province":"Niedersachsen",
    "wof:name":"Bauunternehmung Hermann Kr\u00fcger",
    "wof:placetype":"venue"
},
  "geometry": {"coordinates":[8.190581,52.077065],"type":"Point"}
}