{
  "type": "Feature",
  "properties": {
    "iso:country":"DE",
    "sg:address":"Trippsteinstr. 60",
    "sg:city":"Berlin",
    "sg:postcode":"12249",
    "sg:province":"Berlin",
    "wof:name":"Heinrich D\u00f6rh\u00f6fer Architekt",
    "wof:placetype":"venue"
},
  "geometry": {"coordinates":[13.347317,52.417351],"type":"Point"}
}