{
  "type": "Feature",
  "properties": {
    "iso:country":"DE",
    "sg:address":"Amselweg 2",
    "sg:city":"Pei\u00dfenberg",
    "sg:phone":"+49 8803/1441",
    "sg:postcode":"82380",
    "sg:province":"Bayern",
    "wof:name":"Peter Guggenmoos",
    "wof:placetype":"venue"
},
  "geometry": {"coordinates":[11.0600385666,47.8029632568],"type":"Point"}
}