{
  "type": "Feature",
  "properties": {
    "iso:country":"DE",
    "sg:address":"Rathenaustr 12",
    "sg:city":"Hamm",
    "sg:phone":"+49 2381/943020",
    "sg:postcode":"59067",
    "sg:province":"Nordrhein-Westfalen",
    "wof:name":"Hamm Krananlagen Gmbh",
    "wof:placetype":"venue"
},
  "geometry": {"coordinates":[7.790841,51.656071],"type":"Point"}
}