{
  "type": "Feature",
  "properties": {
    "iso:country":"DE",
    "sg:address":"Br\u00fcckenstr. 33",
    "sg:city":"K\u00f6nigsbronn",
    "sg:phone":"+49 7328/5627",
    "sg:postcode":"89551",
    "sg:province":"Baden-W\u00fcrttemberg",
    "wof:name":"Friedrich H\u00e4rlin",
    "wof:placetype":"venue"
},
  "geometry": {"coordinates":[10.137391,48.733391],"type":"Point"}
}