{
  "type": "Feature",
  "properties": {
    "iso:country":"DE",
    "sg:address":"Walter-Neuberger-Str. 3",
    "sg:city":"Bockelwitz",
    "sg:phone":"+49 34321/12293",
    "sg:postcode":"04703",
    "sg:province":"Sachsen",
    "wof:name":"Pkt Polkenberger K\u00fcchen- Technik Gmbh & Co.",
    "wof:placetype":"venue"
},
  "geometry": {"coordinates":[12.874432,51.170238],"type":"Point"}
}