{
  "type": "Feature",
  "properties": {
    "iso:country":"DE",
    "sg:address":"Postfach 58291",
    "sg:city":"Wetter",
    "sg:postcode":"58291",
    "sg:province":"Hessen",
    "wof:name":"Pfleging",
    "wof:placetype":"venue"
},
  "geometry": {"coordinates":[7.39512,51.387611],"type":"Point"}
}