{
  "type": "Feature",
  "properties": {
    "iso:country":"DE",
    "sg:address":"Kirchweg 7",
    "sg:city":"Hallenberg",
    "sg:phone":"+49 2984/8154",
    "sg:postcode":"59969",
    "sg:province":"Nordrhein-Westfalen",
    "wof:name":"Katholisches Pfarramt St. Goar",
    "wof:placetype":"venue"
},
  "geometry": {"coordinates":[8.6213588715,51.1111717224],"type":"Point"}
}