{
  "type": "Feature",
  "properties": {
    "iso:country":"DE",
    "sg:address":"Rodenberger Str. 18",
    "sg:city":"Stadthagen",
    "sg:phone":"+49 5721/5494",
    "sg:postcode":"31655",
    "sg:province":"Niedersachsen",
    "wof:name":"Hans-heinrich Langhorst",
    "wof:placetype":"venue"
},
  "geometry": {"coordinates":[9.25526,52.31649],"type":"Point"}
}