{
  "type": "Feature",
  "properties": {
    "iso:country":"DE",
    "sg:address":"Alter Schulweg 2-4",
    "sg:city":"Gl\u00fccksburg",
    "sg:phone":"+49 4631/8624",
    "sg:postcode":"24960",
    "sg:province":"Schleswig-Holstein",
    "wof:name":"Alfred Grages",
    "wof:placetype":"venue"
},
  "geometry": {"coordinates":[9.587265,54.846668],"type":"Point"}
}