{
  "type": "Feature",
  "properties": {
    "iso:country":"DE",
    "sg:address":"Kreuzherrenpfad 16",
    "sg:city":"Erkelenz",
    "sg:phone":"+49 2431/73810",
    "sg:postcode":"41812",
    "sg:province":"Nordrhein-Westfalen",
    "wof:name":"Maria Meurer Steuerberaterin",
    "wof:placetype":"venue"
},
  "geometry": {"coordinates":[6.3242230415,51.0651016235],"type":"Point"}
}