{
  "type": "Feature",
  "properties": {
    "iso:country":"DE",
    "sg:address":"Eltinger Str. 13",
    "sg:city":"Leonberg",
    "sg:phone":"+49 7152/25757",
    "sg:postcode":"71229",
    "sg:province":"Baden-W\u00fcrttemberg",
    "wof:name":"B\u00e4ren-apotheke",
    "wof:placetype":"venue"
},
  "geometry": {"coordinates":[9.0169,48.798992],"type":"Point"}
}