{
  "type": "Feature",
  "properties": {
    "iso:country":"DE",
    "sg:address":"Lyoner Str. 18",
    "sg:city":"Frankfurt",
    "sg:phone":"+49 69/66031451",
    "sg:postcode":"60528",
    "sg:province":"Hessen",
    "wof:name":"Dr. Ing. E. H. Hubert H. A. Sternberg Stiftung",
    "wof:placetype":"venue"
},
  "geometry": {"coordinates":[8.6269683838,50.0822372437],"type":"Point"}
}