{
  "type": "Feature",
  "properties": {
    "iso:country":"DE",
    "sg:address":"Hauptstr. 51",
    "sg:city":"Klinken",
    "sg:phone":"+49 38722/20231",
    "sg:postcode":"19374",
    "sg:province":"Mecklenburg-Vorpommern",
    "wof:name":"A. Schwartz",
    "wof:placetype":"venue"
},
  "geometry": {"coordinates":[11.670475,53.501049],"type":"Point"}
}