{
  "type": "Feature",
  "properties": {
    "iso:country":"DE",
    "sg:address":"Eninger Str. 11",
    "sg:city":"Metzingen",
    "sg:phone":"+49 7123/20881",
    "sg:postcode":"72555",
    "sg:province":"Baden-W\u00fcrttemberg",
    "wof:name":"Hirsch",
    "wof:placetype":"venue"
},
  "geometry": {"coordinates":[9.3049297333,48.5094184875],"type":"Point"}
}