{
  "type": "Feature",
  "properties": {
    "iso:country":"DE",
    "sg:address":"Thyssenstra\u00dfe 177",
    "sg:city":"Dinslaken",
    "sg:phone":"+49 2064",
    "sg:postcode":"46535",
    "sg:province":"Nordrhein-Westfalen",
    "wof:name":"Willkommen Bei Der Potera Gmbh !",
    "wof:placetype":"venue"
},
  "geometry": {"coordinates":[6.750153,51.557392],"type":"Point"}
}