{
  "type": "Feature",
  "properties": {
    "iso:country":"DE",
    "sg:address":"Am Bach 11",
    "sg:city":"Wildberg",
    "sg:phone":"+49 7054/5122",
    "sg:postcode":"72218",
    "sg:province":"Baden-W\u00fcrttemberg",
    "wof:name":"Gemeindehalle Sulz",
    "wof:placetype":"venue"
},
  "geometry": {"coordinates":[8.778999,48.616749],"type":"Point"}
}