{
  "type": "Feature",
  "properties": {
    "iso:country":"DE",
    "sg:address":"Breite Str. 1",
    "sg:city":"Peine",
    "sg:phone":"+49 5171/6826",
    "sg:postcode":"31224",
    "sg:province":"Niedersachsen",
    "wof:name":"C. Lehnert",
    "wof:placetype":"venue"
},
  "geometry": {"coordinates":[10.2257461548,52.3229408264],"type":"Point"}
}