{
  "type": "Feature",
  "properties": {
    "iso:country":"DE",
    "sg:address":"Altonaer Str. 390 a",
    "sg:city":"Halstenbek",
    "sg:phone":"+49 4101/34795",
    "sg:postcode":"25469",
    "sg:province":"Schleswig-Holstein",
    "wof:name":"Werner M\u00fcller Steuerberater",
    "wof:placetype":"venue"
},
  "geometry": {"coordinates":[9.8732099533,53.6268386841],"type":"Point"}
}