{
  "type": "Feature",
  "properties": {
    "iso:country":"DE",
    "sg:address":"Adenauerallee 115",
    "sg:city":"Bonn",
    "sg:phone":"+49 228/9121170",
    "sg:postcode":"53113",
    "sg:province":"Nordrhein-Westfalen",
    "wof:name":"Kirchliches Archiv Des Katholischen Milit\u00e4rbischofs",
    "wof:placetype":"venue"
},
  "geometry": {"coordinates":[7.112535,50.724476],"type":"Point"}
}