{
  "type": "Feature",
  "properties": {
    "iso:country":"DE",
    "sg:address":"Wilhelmstr. 63",
    "sg:city":"Euskirchen",
    "sg:phone":"+49 2251/75255",
    "sg:postcode":"53879",
    "sg:province":"Nordrhein-Westfalen",
    "wof:name":"Dohmganz",
    "wof:placetype":"venue"
},
  "geometry": {"coordinates":[6.7883481979,50.6581230164],"type":"Point"}
}