{
  "type": "Feature",
  "properties": {
    "iso:country":"DE",
    "sg:address":"Liebenberger Weg 12 C",
    "sg:city":"Bergsdorf",
    "sg:phone":"+49 33088/50247",
    "sg:postcode":"16775",
    "sg:province":"Brandenburg",
    "wof:name":"Agrar Gmbh Bergsdorf",
    "wof:placetype":"venue"
},
  "geometry": {"coordinates":[13.254904,52.923771],"type":"Point"}
}