{
  "type": "Feature",
  "properties": {
    "iso:country":"DE",
    "sg:address":"Petkuser Str. 2",
    "sg:city":"Nordhorn",
    "sg:phone":"+49 5921/34840",
    "sg:postcode":"48531",
    "sg:province":"Niedersachsen",
    "wof:name":"F. V. Lochow-petkus Samen- Und Saatgut",
    "wof:placetype":"venue"
},
  "geometry": {"coordinates":[7.129731,52.487392],"type":"Point"}
}