{
  "type": "Feature",
  "properties": {
    "iso:country":"DE",
    "sg:address":"B\u00f6ttgerstr. 6",
    "sg:city":"Braunschweig",
    "sg:phone":"+49 531/876080",
    "sg:postcode":"38122",
    "sg:province":"Niedersachsen",
    "wof:name":"Werner Ditzinger Gmbh",
    "wof:placetype":"venue"
},
  "geometry": {"coordinates":[10.49478,52.212135],"type":"Point"}
}