{
  "type": "Feature",
  "properties": {
    "iso:country":"DE",
    "sg:address":"Lange Str. 25",
    "sg:city":"Elsterberg",
    "sg:phone":"+49 36621/30604",
    "sg:postcode":"07985",
    "sg:province":"Th\u00fcringen",
    "wof:name":"U. S\u00e4nger",
    "wof:placetype":"venue"
},
  "geometry": {"coordinates":[12.1698436737,50.6082992554],"type":"Point"}
}