{
  "type": "Feature",
  "properties": {
    "iso:country":"DE",
    "sg:address":"Mainstr. 3-5",
    "sg:city":"Bayreuth",
    "sg:phone":"+49 921/84479",
    "sg:postcode":"95444",
    "sg:province":"Bayern",
    "wof:name":"Music Partner",
    "wof:placetype":"venue"
},
  "geometry": {"coordinates":[11.5756340027,49.9478111267],"type":"Point"}
}