{
  "type": "Feature",
  "properties": {
    "iso:country":"DE",
    "sg:address":"Zei\u00dfstr. 48",
    "sg:city":"Hannover",
    "sg:phone":"+49 511/8420628",
    "sg:postcode":"30519",
    "sg:province":"Niedersachsen",
    "wof:name":"\u00dcbergangswohnheim",
    "wof:placetype":"venue"
},
  "geometry": {"coordinates":[9.7752399445,52.3448295593],"type":"Point"}
}