{
  "type": "Feature",
  "properties": {
    "iso:country":"DE",
    "sg:address":"Industriering 20",
    "sg:city":"Breiteng\u00fc\u00dfbach",
    "sg:phone":"+49 9544/950330",
    "sg:postcode":"96149",
    "sg:province":"Bayern",
    "wof:name":"Olias Spaltband-service Ag",
    "wof:placetype":"venue"
},
  "geometry": {"coordinates":[10.8799619675,49.9737930298],"type":"Point"}
}