{
  "type": "Feature",
  "properties": {
    "iso:country":"DE",
    "sg:address":"Umstr. 34",
    "sg:city":"Stolberg",
    "sg:phone":"+49 2408/5770",
    "sg:postcode":"52224",
    "sg:province":"Nordrhein-Westfalen",
    "wof:name":"Prof. Dr. Helmut Strehl",
    "wof:placetype":"venue"
},
  "geometry": {"coordinates":[6.2169499397,50.7179718018],"type":"Point"}
}