{
  "type": "Feature",
  "properties": {
    "iso:country":"DE",
    "sg:address":"Katharinenstr. 14",
    "sg:city":"Ludwigsburg",
    "sg:phone":"+49 4971/4160800",
    "sg:postcode":"71634",
    "sg:province":"Baden-W\u00fcrttemberg",
    "wof:name":"Class Gmbh",
    "wof:placetype":"venue"
},
  "geometry": {"coordinates":[9.1717424393,48.907951355],"type":"Point"}
}