{
  "type": "Feature",
  "properties": {
    "iso:country":"DE",
    "sg:address":"Hammer Str. 17",
    "sg:city":"Beckum",
    "sg:phone":"+49 2521/874978",
    "sg:postcode":"59269",
    "sg:province":"Nordrhein-Westfalen",
    "wof:name":"Pizzeria Italia",
    "wof:placetype":"venue"
},
  "geometry": {"coordinates":[8.0303964615,51.7530059814],"type":"Point"}
}