{
  "type": "Feature",
  "properties": {
    "iso:country":"DE",
    "sg:address":"Steinlachstr. 2",
    "sg:city":"Schwaig",
    "sg:phone":"+49 911/505899",
    "sg:postcode":"90571",
    "sg:province":"Bayern",
    "wof:name":"Werner Dreykorn-lindner Patentanwalt",
    "wof:placetype":"venue"
},
  "geometry": {"coordinates":[11.2005434036,49.468120575],"type":"Point"}
}