{
  "type": "Feature",
  "properties": {
    "iso:country":"DE",
    "sg:address":"Vahrenwalder Str. 39",
    "sg:city":"Hannover",
    "sg:phone":"+49 511/3504020",
    "sg:postcode":"30165",
    "sg:province":"Niedersachsen",
    "wof:name":"R. Reschke Kg",
    "wof:placetype":"venue"
},
  "geometry": {"coordinates":[9.734044,52.388794],"type":"Point"}
}