{
  "type": "Feature",
  "properties": {
    "iso:country":"DE",
    "sg:address":"Herzog-Georg-Str. 13",
    "sg:city":"Lauingen",
    "sg:phone":"+49 9072/4672",
    "sg:postcode":"89415",
    "sg:province":"Bayern",
    "wof:name":"A. Schmid Jun.",
    "wof:placetype":"venue"
},
  "geometry": {"coordinates":[10.4309396744,48.5714797974],"type":"Point"}
}