{
  "type": "Feature",
  "properties": {
    "iso:country":"DE",
    "sg:address":"Waldhornstr. 23",
    "sg:city":"Stutensee",
    "sg:phone":"+49 7249/3446",
    "sg:postcode":"76297",
    "sg:province":"Baden-W\u00fcrttemberg",
    "wof:name":"B\u00e4ckerei-konditorei Rolf Daiss",
    "wof:placetype":"venue"
},
  "geometry": {"coordinates":[8.508196,49.115257],"type":"Point"}
}