{
  "type": "Feature",
  "properties": {
    "iso:country":"DE",
    "sg:address":"Lessingstr. 4",
    "sg:city":"Neuss",
    "sg:phone":"+49 2131/48888",
    "sg:postcode":"41464",
    "sg:province":"Nordrhein-Westfalen",
    "wof:name":"H. Sohn Ingenieur",
    "wof:placetype":"venue"
},
  "geometry": {"coordinates":[6.6976847649,51.182964325],"type":"Point"}
}