{
  "type": "Feature",
  "properties": {
    "iso:country":"DE",
    "sg:address":"Steinwaldstr. 20",
    "sg:city":"Neusorg",
    "sg:phone":"+49 9234/213",
    "sg:postcode":"95700",
    "sg:province":"Bayern",
    "wof:name":"Otto Reger",
    "wof:placetype":"venue"
},
  "geometry": {"coordinates":[11.975026,49.933769],"type":"Point"}
}