{
  "type": "Feature",
  "properties": {
    "iso:country":"DE",
    "sg:address":"Poststr. 9",
    "sg:city":"Rastatt",
    "sg:phone":"+49 7222/34126",
    "sg:postcode":"76437",
    "sg:province":"Baden-W\u00fcrttemberg",
    "wof:name":"Rolf Beck Parf\u00fcmerie Beck",
    "wof:placetype":"venue"
},
  "geometry": {"coordinates":[8.204569,48.857475],"type":"Point"}
}