{
  "type": "Feature",
  "properties": {
    "iso:country":"DE",
    "sg:address":"Kilianst\u00e4dter Str. 2",
    "sg:city":"Maintal",
    "sg:phone":"+49 6181/840593",
    "sg:postcode":"63477",
    "sg:province":"Hessen",
    "wof:name":"Volker Wissenbach Architekt",
    "wof:placetype":"venue"
},
  "geometry": {"coordinates":[8.859453,50.17205],"type":"Point"}
}