{
  "type": "Feature",
  "properties": {
    "iso:country":"DE",
    "sg:address":"Marktstr. 195c",
    "sg:city":"Pfullingen",
    "sg:phone":"+49 7121/239021",
    "sg:postcode":"72793",
    "sg:province":"Baden-W\u00fcrttemberg",
    "wof:name":"Hege Hekhorn & Gekeler Gmbh",
    "wof:placetype":"venue"
},
  "geometry": {"coordinates":[9.225154,48.483704],"type":"Point"}
}