{
  "type": "Feature",
  "properties": {
    "iso:country":"DE",
    "sg:address":"Zentbechhofener Str. 14a",
    "sg:city":"Frensdorf",
    "sg:phone":"+49 9502/8104",
    "sg:postcode":"96158",
    "sg:province":"Bayern",
    "wof:name":"Herrmann",
    "wof:placetype":"venue"
},
  "geometry": {"coordinates":[10.8862953186,49.7909240723],"type":"Point"}
}