{
  "type": "Feature",
  "properties": {
    "iso:country":"DE",
    "sg:address":"Postfach 1107",
    "sg:city":"Pleystein",
    "sg:phone":"+49 9654/462",
    "sg:postcode":"92714",
    "sg:province":"Bayern",
    "wof:name":"Stadtb\u00fccherei Kulturhaus",
    "wof:placetype":"venue"
},
  "geometry": {"coordinates":[12.407515,49.644615],"type":"Point"}
}