{
  "type": "Feature",
  "properties": {
    "iso:country":"DE",
    "sg:address":"Deufringer Str. 11",
    "sg:city":"Aidlingen",
    "sg:phone":"+49 7056/92475",
    "sg:postcode":"71134",
    "sg:province":"Baden-W\u00fcrttemberg",
    "wof:name":"R\u00f6ssle",
    "wof:placetype":"venue"
},
  "geometry": {"coordinates":[8.8589096069,48.678478241],"type":"Point"}
}