{
  "type": "Feature",
  "properties": {
    "iso:country":"DE",
    "sg:address":"Eberhardsb\u00fchler Str. 1",
    "sg:city":"Vilseck",
    "sg:phone":"+49 9662/41000",
    "sg:postcode":"92249",
    "sg:province":"Bayern",
    "wof:name":"Tsg Tankschutz Gmbh",
    "wof:placetype":"venue"
},
  "geometry": {"coordinates":[11.77553,49.571453],"type":"Point"}
}