{
  "type": "Feature",
  "properties": {
    "iso:country":"DE",
    "sg:address":"Oldenburger Str. 62",
    "sg:city":"Zetel",
    "sg:phone":"+49 4453/2184",
    "sg:postcode":"26340",
    "sg:province":"Niedersachsen",
    "wof:name":"Heinrich Czwikla",
    "wof:placetype":"venue"
},
  "geometry": {"coordinates":[7.9754681587,53.4081993103],"type":"Point"}
}