{
  "type": "Feature",
  "properties": {
    "iso:country":"DE",
    "sg:address":"Lindenstr. 39",
    "sg:city":"Fulda",
    "sg:postcode":"36037",
    "sg:province":"Hessen",
    "wof:name":"Norbert Fritz",
    "wof:placetype":"venue"
},
  "geometry": {"coordinates":[9.6835079193,50.5502929688],"type":"Point"}
}