{
  "type": "Feature",
  "properties": {
    "iso:country":"DE",
    "sg:address":"Turmstr. 3",
    "sg:city":"Deidesheim",
    "sg:phone":"+49 6326/981081",
    "sg:postcode":"67146",
    "sg:province":"Rheinland-Pfalz",
    "wof:name":"Turmst\u00fcb'l",
    "wof:placetype":"venue"
},
  "geometry": {"coordinates":[8.1878824234,49.4078941345],"type":"Point"}
}