{
  "type": "Feature",
  "properties": {
    "iso:country":"DE",
    "sg:address":"Hammoor 12",
    "sg:city":"Rietberg",
    "sg:phone":"+49 2944/7701",
    "sg:postcode":"33397",
    "sg:province":"Nordrhein-Westfalen",
    "wof:name":"Reinhard Kempkensteffen",
    "wof:placetype":"venue"
},
  "geometry": {"coordinates":[8.372994,51.776466],"type":"Point"}
}