{
  "type": "Feature",
  "properties": {
    "iso:country":"DE",
    "sg:address":"Jahnstr. 2",
    "sg:city":"Dorn-D\u00fcrkheim",
    "sg:phone":"+49 6733/6925",
    "sg:postcode":"67585",
    "sg:province":"Rheinland-Pfalz",
    "wof:name":"Philipp Korb",
    "wof:placetype":"venue"
},
  "geometry": {"coordinates":[8.265381813,49.7682037354],"type":"Point"}
}