{
  "type": "Feature",
  "properties": {
    "iso:country":"DE",
    "sg:address":"Bahnhofstr. 46",
    "sg:city":"Buxtehude",
    "sg:phone":"+49 4161/54516",
    "sg:postcode":"21614",
    "sg:province":"Niedersachsen",
    "wof:name":"Post-apotheke Christine Rau",
    "wof:placetype":"venue"
},
  "geometry": {"coordinates":[9.691236,53.471783],"type":"Point"}
}