{
  "type": "Feature",
  "properties": {
    "iso:country":"DE",
    "sg:address":"Altmarkt 1",
    "sg:city":"Ortrand",
    "sg:phone":"+49 35755/50201",
    "sg:postcode":"01990",
    "sg:province":"Brandenburg",
    "wof:name":"Altentagesst\u00e4tte Der Volkssolidarit\u00e4t",
    "wof:placetype":"venue"
},
  "geometry": {"coordinates":[13.757292,51.375938],"type":"Point"}
}