{
  "type": "Feature",
  "properties": {
    "iso:country":"DE",
    "sg:address":"Sch\u00f6nbornstr. 53-55",
    "sg:city":"Hanau",
    "sg:phone":"+49 6181/66550",
    "sg:postcode":"63456",
    "sg:province":"Hessen",
    "wof:name":"Dr. Hanno Freisen Tierarzt",
    "wof:placetype":"venue"
},
  "geometry": {"coordinates":[8.9061727524,50.106502533],"type":"Point"}
}