{
  "type": "Feature",
  "properties": {
    "iso:country":"DE",
    "sg:address":"Str\u00fcmpenbusch 7",
    "sg:city":"Dortmund",
    "sg:phone":"+49 231/357060",
    "sg:postcode":"44357",
    "sg:province":"Nordrhein-Westfalen",
    "wof:name":"Norbert Schuhmacher",
    "wof:placetype":"venue"
},
  "geometry": {"coordinates":[7.367474,51.560703],"type":"Point"}
}