{
  "type": "Feature",
  "properties": {
    "iso:country":"DE",
    "sg:address":"Mittelwendung 23",
    "sg:city":"Weyhe",
    "sg:phone":"+49 4203/720",
    "sg:postcode":"28844",
    "sg:province":"Niedersachsen",
    "wof:name":"Sb-fachgro\u00dfmarkt",
    "wof:placetype":"venue"
},
  "geometry": {"coordinates":[8.8735866547,53.015712738],"type":"Point"}
}