{
  "type": "Feature",
  "properties": {
    "iso:country":"DE",
    "sg:address":"Ernst-Th\u00e4lmann-Platz 21",
    "sg:city":"Dahlen",
    "sg:phone":"+49 34361/51813",
    "sg:postcode":"04774",
    "sg:province":"Sachsen",
    "wof:name":"R. K\u00fchne",
    "wof:placetype":"venue"
},
  "geometry": {"coordinates":[12.927446,51.379539],"type":"Point"}
}