{
  "type": "Feature",
  "properties": {
    "iso:country":"DE",
    "sg:address":"An der Spree 1",
    "sg:city":"Lohsa",
    "sg:phone":"+49 35724/50244",
    "sg:postcode":"02999",
    "sg:province":"Sachsen",
    "wof:name":"S. Sch\u00fctze",
    "wof:placetype":"venue"
},
  "geometry": {"coordinates":[14.400464,51.382496],"type":"Point"}
}