{
  "type": "Feature",
  "properties": {
    "iso:country":"DE",
    "sg:address":"Peterstr. 10",
    "sg:city":"Iserlohn",
    "sg:phone":"+49 2371/22917",
    "sg:postcode":"58636",
    "sg:province":"Nordrhein-Westfalen",
    "wof:name":"Gagfah",
    "wof:placetype":"venue"
},
  "geometry": {"coordinates":[7.7002339363,51.3721351624],"type":"Point"}
}