{
  "type": "Feature",
  "properties": {
    "iso:country":"DE",
    "sg:address":"Kapuzinergasse 7-9",
    "sg:city":"Aachen",
    "sg:postcode":"52068",
    "sg:province":"Nordrhein-Westfalen",
    "wof:name":"Aixtreme E. K.",
    "wof:placetype":"venue"
},
  "geometry": {"coordinates":[6.1039299965,50.7810440063],"type":"Point"}
}