{
  "type": "Feature",
  "properties": {
    "iso:country":"DE",
    "sg:address":"Grellstr. 54",
    "sg:city":"Berlin",
    "sg:phone":"+49 30/4244938",
    "sg:postcode":"10409",
    "sg:province":"Berlin",
    "wof:name":"Dr. Med. Christa Bottin",
    "wof:placetype":"venue"
},
  "geometry": {"coordinates":[13.434661,52.543098],"type":"Point"}
}