{
  "type": "Feature",
  "properties": {
    "iso:country":"DE",
    "sg:address":"Neupforte 5",
    "sg:city":"Saulheim",
    "sg:phone":"+49 6732/1644",
    "sg:postcode":"55291",
    "sg:province":"Rheinland-Pfalz",
    "wof:name":"A. W. Appenheimer",
    "wof:placetype":"venue"
},
  "geometry": {"coordinates":[8.148229599,49.8762588501],"type":"Point"}
}