{
  "type": "Feature",
  "properties": {
    "iso:country":"DE",
    "sg:address":"Nieper Str. 17",
    "sg:city":"Moers",
    "sg:phone":"+49 2841/61024",
    "sg:postcode":"47447",
    "sg:province":"Nordrhein-Westfalen",
    "wof:name":"Hoyer Druck & Service Gmbh",
    "wof:placetype":"venue"
},
  "geometry": {"coordinates":[6.58414,51.40699],"type":"Point"}
}