{
  "type": "Feature",
  "properties": {
    "iso:country":"DE",
    "sg:address":"Markt 28",
    "sg:city":"H\u00fcckelhoven",
    "sg:phone":"+49 2433/84268",
    "sg:postcode":"41836",
    "sg:province":"Nordrhein-Westfalen",
    "wof:name":"H. Gramzow",
    "wof:placetype":"venue"
},
  "geometry": {"coordinates":[6.228433,51.053268],"type":"Point"}
}