{
  "type": "Feature",
  "properties": {
    "iso:country":"DE",
    "sg:address":"Hammstr. 12",
    "sg:city":"Frankenthal",
    "sg:phone":"+49 6233/436209",
    "sg:postcode":"67227",
    "sg:province":"Rheinland-Pfalz",
    "wof:name":"Gardinenfabrik Flei\u00dfner E. K.",
    "wof:placetype":"venue"
},
  "geometry": {"coordinates":[8.3501024246,49.522693634],"type":"Point"}
}