{
  "type": "Feature",
  "properties": {
    "iso:country":"DE",
    "sg:address":"Gottlieb-Daimler-Str. 1",
    "sg:city":"Erdmannhausen",
    "sg:phone":"+49 7144/83540",
    "sg:postcode":"71729",
    "sg:province":"Baden-W\u00fcrttemberg",
    "wof:name":"B\u00e4ko Erdmannhausen B\u00e4cker- Und Konditoren-einkauf Eg",
    "wof:placetype":"venue"
},
  "geometry": {"coordinates":[9.28816,48.947533],"type":"Point"}
}