{
  "type": "Feature",
  "properties": {
    "iso:country":"DE",
    "sg:address":"Schimmelbuschstr. 17",
    "sg:city":"Erkrath",
    "sg:postcode":"40699",
    "sg:province":"Nordrhein-Westfalen",
    "wof:name":"Hengesbach Smt Gmbh",
    "wof:placetype":"venue"
},
  "geometry": {"coordinates":[6.946373,51.216274],"type":"Point"}
}