{
  "type": "Feature",
  "properties": {
    "iso:country":"DE",
    "sg:address":"Hessinggrabenweg 34",
    "sg:city":"Burgbernheim",
    "sg:phone":"+49 7171/929533",
    "sg:postcode":"91593",
    "sg:province":"Bayern",
    "wof:name":"Hof Werkzeug- Und Ger\u00e4tebau Gmbh",
    "wof:placetype":"venue"
},
  "geometry": {"coordinates":[9.7843446732,48.7931442261],"type":"Point"}
}