{
  "type": "Feature",
  "properties": {
    "iso:country":"DE",
    "sg:address":"\u00d6hringer Str. 24",
    "sg:city":"Gro\u00dfenhain",
    "sg:phone":"+49 3522/63261",
    "sg:postcode":"01558",
    "sg:province":"Sachsen",
    "wof:name":"Teppich - Center Torsten Kaiser",
    "wof:placetype":"venue"
},
  "geometry": {"coordinates":[13.5311727524,51.2809524536],"type":"Point"}
}