{
  "type": "Feature",
  "properties": {
    "iso:country":"DE",
    "sg:address":"Rodenbek 1",
    "sg:city":"M\u00f6nkhagen",
    "sg:phone":"+49 4506/250",
    "sg:postcode":"23619",
    "sg:province":"Schleswig-Holstein",
    "wof:name":"Karl-heinz Sch\u00fctt",
    "wof:placetype":"venue"
},
  "geometry": {"coordinates":[10.549515,53.901081],"type":"Point"}
}