{
  "type": "Feature",
  "properties": {
    "iso:country":"DE",
    "sg:address":"Seestr. 16",
    "sg:city":"Freudental",
    "sg:phone":"+49 7143/26511",
    "sg:postcode":"74392",
    "sg:province":"Baden-W\u00fcrttemberg",
    "wof:name":"Robert Wawczynika Gmbh",
    "wof:placetype":"venue"
},
  "geometry": {"coordinates":[9.061018,49.01062],"type":"Point"}
}