{
  "type": "Feature",
  "properties": {
    "iso:country":"DE",
    "sg:address":"Pankstr. 8-10",
    "sg:city":"Berlin",
    "sg:phone":"+49 30/5338791",
    "sg:postcode":"13127",
    "sg:province":"Berlin",
    "wof:name":"Antome Anlagen-ton- Und Me\u00dftechnik Gmbh",
    "wof:placetype":"venue"
},
  "geometry": {"coordinates":[13.4394731522,52.5934524536],"type":"Point"}
}