{
  "type": "Feature",
  "properties": {
    "iso:country":"DE",
    "sg:address":"Hauptstr. 4",
    "sg:city":"Bubsheim",
    "sg:phone":"+49 7429/3885",
    "sg:postcode":"78585",
    "sg:province":"Baden-W\u00fcrttemberg",
    "wof:name":"Traube",
    "wof:placetype":"venue"
},
  "geometry": {"coordinates":[8.831533432,48.1202430725],"type":"Point"}
}