{
  "type": "Feature",
  "properties": {
    "iso:country":"DE",
    "sg:address":"Gr\u00fcnauer Str. 27",
    "sg:city":"Neuburg",
    "sg:phone":"+49 8431/67140",
    "sg:postcode":"86633",
    "sg:province":"Bayern",
    "wof:name":"J. Friedrich Ammon",
    "wof:placetype":"venue"
},
  "geometry": {"coordinates":[11.2046298981,48.7456016541],"type":"Point"}
}