{
  "type": "Feature",
  "properties": {
    "iso:country":"DE",
    "sg:address":"Ascherslebener Str. 8 f",
    "sg:city":"Egeln",
    "sg:phone":"+49 39268/92832",
    "sg:postcode":"39435",
    "sg:province":"Sachsen-Anhalt",
    "wof:name":"Restaurant Finkenh\u00fctte",
    "wof:placetype":"venue"
},
  "geometry": {"coordinates":[11.4230594635,51.9402084351],"type":"Point"}
}