{
  "type": "Feature",
  "properties": {
    "iso:country":"DE",
    "sg:address":"Im Stummefeld 13",
    "sg:city":"Siegen",
    "sg:phone":"+49 271/51988",
    "sg:postcode":"57072",
    "sg:province":"Nordrhein-Westfalen",
    "wof:name":"Wolfgang Klein Innenarchitekt",
    "wof:placetype":"venue"
},
  "geometry": {"coordinates":[7.998232,50.884201],"type":"Point"}
}