{
  "type": "Feature",
  "properties": {
    "iso:country":"DE",
    "sg:address":"Fronhof 4",
    "sg:city":"Solingen",
    "sg:phone":"+49 212/205327",
    "sg:postcode":"42651",
    "sg:province":"Nordrhein-Westfalen",
    "wof:name":"Ev. Pfarramt Stadtkirchengemeinde",
    "wof:placetype":"venue"
},
  "geometry": {"coordinates":[7.0842299461,51.1720046997],"type":"Point"}
}