{
  "type": "Feature",
  "properties": {
    "iso:country":"DE",
    "sg:address":"Im Bannen 9",
    "sg:city":"Mayen",
    "sg:phone":"+49 2651/2514",
    "sg:postcode":"56727",
    "sg:province":"Rheinland-Pfalz",
    "wof:name":"Dieter Peters",
    "wof:placetype":"venue"
},
  "geometry": {"coordinates":[7.2284212112,50.3278846741],"type":"Point"}
}