{
  "type": "Feature",
  "properties": {
    "iso:country":"DE",
    "sg:address":"Gl\u00fcckst\u00e4dter Weg 1",
    "sg:city":"Hamburg",
    "sg:phone":"+49 40/8314222",
    "sg:postcode":"22549",
    "sg:province":"Hamburg",
    "wof:name":"J\u00fcrgen Schr\u00f6der",
    "wof:placetype":"venue"
},
  "geometry": {"coordinates":[9.866457,53.586243],"type":"Point"}
}