{
  "type": "Feature",
  "properties": {
    "iso:country":"DE",
    "sg:address":"Korbacher Str. 60",
    "sg:city":"Schauenburg",
    "sg:postcode":"34270",
    "sg:province":"Hessen",
    "wof:name":"\u00d6ko-fleischwaren Vertriebs Gmbh",
    "wof:placetype":"venue"
},
  "geometry": {"coordinates":[9.2968425751,51.2824249268],"type":"Point"}
}