{
  "type": "Feature",
  "properties": {
    "iso:country":"DE",
    "sg:address":"Dorfstr. 58",
    "sg:city":"Lichtenberg",
    "sg:phone":"+49 3964/210250",
    "sg:postcode":"17259",
    "sg:province":"Bayern",
    "wof:name":"Baugesch\u00e4ft Thomas Riedel Gmbh",
    "wof:placetype":"venue"
},
  "geometry": {"coordinates":[12.8767824173,52.8864097595],"type":"Point"}
}