{
  "type": "Feature",
  "properties": {
    "iso:country":"DE",
    "sg:address":"Ringstr. 16",
    "sg:city":"Siegburg",
    "sg:phone":"+49 2241/971840",
    "sg:postcode":"53721",
    "sg:province":"Nordrhein-Westfalen",
    "wof:name":"Inge Ettalbi Praxis F\u00fcr Ergotherapie",
    "wof:placetype":"venue"
},
  "geometry": {"coordinates":[7.204993,50.797234],"type":"Point"}
}