{
  "type": "Feature",
  "properties": {
    "iso:country":"DE",
    "sg:address":"Rudolph-Brandes-Allee 1",
    "sg:city":"Bad Salzuflen",
    "sg:postcode":"32105",
    "sg:province":"Nordrhein-Westfalen",
    "wof:name":"Aps Gmbh",
    "wof:placetype":"venue"
},
  "geometry": {"coordinates":[8.751689,52.080265],"type":"Point"}
}