{
  "type": "Feature",
  "properties": {
    "iso:country":"DE",
    "sg:address":"Oberstr. 8",
    "sg:city":"Niederkassel",
    "sg:phone":"+49 2208/6584",
    "sg:postcode":"53859",
    "sg:province":"Nordrhein-Westfalen",
    "wof:name":"Rolf Herzog",
    "wof:placetype":"venue"
},
  "geometry": {"coordinates":[7.0419158936,50.7903442383],"type":"Point"}
}