{
  "type": "Feature",
  "properties": {
    "iso:country":"DE",
    "sg:address":"Kronstr.9",
    "sg:city":"Landau",
    "sg:phone":"+49 4963/4186208",
    "sg:postcode":"76829",
    "sg:province":"Rheinland-Pfalz",
    "wof:name":"Dresdner Bank",
    "wof:placetype":"venue"
},
  "geometry": {"coordinates":[8.113107,49.198204],"type":"Point"}
}