{
  "type": "Feature",
  "properties": {
    "iso:country":"DE",
    "sg:address":"Morgenstr. 18",
    "sg:city":"Karlsruhe",
    "sg:postcode":"76137",
    "sg:province":"Baden-W\u00fcrttemberg",
    "wof:name":"L. U. W. A. Internet-agentur Ohg",
    "wof:placetype":"venue"
},
  "geometry": {"coordinates":[8.4129247665,49.0012893677],"type":"Point"}
}