{
  "type": "Feature",
  "properties": {
    "iso:country":"DE",
    "sg:address":"Am Hopfenberg 36",
    "sg:city":"Gr\u00e4fenroda",
    "sg:phone":"+49 36205/77233",
    "sg:postcode":"99330",
    "sg:province":"Th\u00fcringen",
    "wof:name":"Gbr \u00b4am Hopfenberg\u00b4",
    "wof:placetype":"venue"
},
  "geometry": {"coordinates":[10.8048295975,50.7505073547],"type":"Point"}
}