{
  "type": "Feature",
  "properties": {
    "iso:country":"DE",
    "sg:address":"Siemensstr. 12",
    "sg:city":"Eggenstein-Leopoldshafen",
    "sg:phone":"+49 721/787244",
    "sg:postcode":"76344",
    "sg:province":"Baden-W\u00fcrttemberg",
    "wof:name":"Friedrich Fuchs",
    "wof:placetype":"venue"
},
  "geometry": {"coordinates":[8.381841,49.073357],"type":"Point"}
}