{
  "type": "Feature",
  "properties": {
    "iso:country":"DE",
    "sg:address":"Kr\u00e4merstr. 46",
    "sg:city":"Karlsruhe",
    "sg:phone":"+49 721/9574030",
    "sg:postcode":"76189",
    "sg:province":"Baden-W\u00fcrttemberg",
    "wof:name":"Schr\u00f6der & Schr\u00f6der Consult Beratungsgesellschaft Mbh",
    "wof:placetype":"venue"
},
  "geometry": {"coordinates":[8.331325531,49.0034103394],"type":"Point"}
}