{
  "type": "Feature",
  "properties": {
    "iso:country":"DE",
    "sg:address":"Kirchweg 48",
    "sg:city":"K\u00f6ln",
    "sg:phone":"+49 221/4845571",
    "sg:postcode":"50858",
    "sg:province":"Nordrhein-Westfalen",
    "wof:name":"Armin Heger Architekt",
    "wof:placetype":"venue"
},
  "geometry": {"coordinates":[6.863018,50.935516],"type":"Point"}
}