{
  "type": "Feature",
  "properties": {
    "iso:country":"DE",
    "sg:address":"Industriestr. 7",
    "sg:city":"Hengersberg",
    "sg:phone":"+49 9901/901519",
    "sg:postcode":"94491",
    "sg:province":"Bayern",
    "wof:name":"Bistro Im Moz",
    "wof:placetype":"venue"
},
  "geometry": {"coordinates":[13.0537471771,48.7606315613],"type":"Point"}
}