{
  "type": "Feature",
  "properties": {
    "iso:country":"DE",
    "sg:address":"Kirchwehrener Ring 11",
    "sg:city":"Seelze",
    "sg:phone":"+49 5137/94873",
    "sg:postcode":"30926",
    "sg:province":"Niedersachsen",
    "wof:name":"Henning Narten",
    "wof:placetype":"venue"
},
  "geometry": {"coordinates":[9.566727,52.366123],"type":"Point"}
}