{
  "type": "Feature",
  "properties": {
    "iso:country":"DE",
    "sg:address":"Dorfplatz 17",
    "sg:city":"Stallwang",
    "sg:phone":"+49 9964/9980",
    "sg:postcode":"94375",
    "sg:province":"Bayern",
    "wof:name":"E. Rothammer",
    "wof:placetype":"venue"
},
  "geometry": {"coordinates":[12.65664,49.050102],"type":"Point"}
}