{
  "type": "Feature",
  "properties": {
    "iso:country":"DE",
    "sg:address":"Feldbergstr. 1",
    "sg:city":"Tiefenbronn",
    "sg:phone":"+49 7234/4287",
    "sg:postcode":"75233",
    "sg:province":"Baden-W\u00fcrttemberg",
    "wof:name":"K\u00e4the Schl\u00f6gl",
    "wof:placetype":"venue"
},
  "geometry": {"coordinates":[8.8017911911,48.8273544312],"type":"Point"}
}