{
  "type": "Feature",
  "properties": {
    "iso:country":"DE",
    "sg:address":"Balauerfohr 4",
    "sg:city":"L\u00fcbeck",
    "sg:phone":"+49 451/73693",
    "sg:postcode":"23552",
    "sg:province":"Schleswig-Holstein",
    "wof:name":"E. Berner",
    "wof:placetype":"venue"
},
  "geometry": {"coordinates":[10.690905571,53.8649635315],"type":"Point"}
}