{
  "type": "Feature",
  "properties": {
    "iso:country":"DE",
    "sg:address":"Ulmenweg 7",
    "sg:city":"Seesen",
    "sg:phone":"+49 5381/5586",
    "sg:postcode":"38723",
    "sg:province":"Niedersachsen",
    "wof:name":"Hannelore Zeise",
    "wof:placetype":"venue"
},
  "geometry": {"coordinates":[10.201007843,51.892364502],"type":"Point"}
}