{
  "type": "Feature",
  "properties": {
    "iso:country":"DE",
    "sg:address":"Bahnhofstr. 12-16",
    "sg:city":"Ungerhausen",
    "sg:phone":"+49 8393/92032",
    "sg:postcode":"87781",
    "sg:province":"Bayern",
    "wof:name":"Mawy More Than Business",
    "wof:placetype":"venue"
},
  "geometry": {"coordinates":[10.273305,48.016148],"type":"Point"}
}