{
  "type": "Feature",
  "properties": {
    "iso:country":"DE",
    "sg:address":"Zum Ottersberg 12",
    "sg:city":"Wertheim-Reicholzheim",
    "sg:phone":"+49 9342/3080",
    "sg:postcode":"97877",
    "sg:province":"Baden-W\u00fcrttemberg",
    "wof:name":"Tfa Ideen Zum Messen",
    "wof:placetype":"venue"
},
  "geometry": {"coordinates":[9.519072,49.731308],"type":"Point"}
}