{
  "type": "Feature",
  "properties": {
    "iso:country":"DE",
    "sg:address":"Alte Landstr. 28a",
    "sg:city":"Bad Berleburg",
    "sg:phone":"+49 2759/645",
    "sg:postcode":"57319",
    "sg:province":"Nordrhein-Westfalen",
    "wof:name":"Lothar Pritzel",
    "wof:placetype":"venue"
},
  "geometry": {"coordinates":[8.2878284454,51.0652770996],"type":"Point"}
}