{
  "type": "Feature",
  "properties": {
    "iso:country":"DE",
    "sg:address":"Renatastr. 63",
    "sg:city":"M\u00fcnchen",
    "sg:phone":"+49 89/1306810",
    "sg:postcode":"80639",
    "sg:province":"Bayern",
    "wof:name":"Dieter Gernhardt Werbegeschenk-hdl.",
    "wof:placetype":"venue"
},
  "geometry": {"coordinates":[11.5268468857,48.1551818848],"type":"Point"}
}