{
  "type": "Feature",
  "properties": {
    "iso:country":"DE",
    "sg:address":"Klarastr. 12",
    "sg:city":"Essen",
    "sg:phone":"+49 201/771008",
    "sg:postcode":"45130",
    "sg:province":"Nordrhein-Westfalen",
    "wof:name":"Bauhaus Gmbh & Co. Kg",
    "wof:placetype":"venue"
},
  "geometry": {"coordinates":[7.0069050789,51.4378814697],"type":"Point"}
}