{
  "type": "Feature",
  "properties": {
    "iso:country":"DE",
    "sg:address":"Funckenhausen 1",
    "sg:city":"Hagen",
    "sg:phone":"+49 2331/303823",
    "sg:postcode":"58089",
    "sg:province":"Nordrhein-Westfalen",
    "wof:name":"Bernhard Gr\u00e4we",
    "wof:placetype":"venue"
},
  "geometry": {"coordinates":[7.43568,51.378605],"type":"Point"}
}