{
  "type": "Feature",
  "properties": {
    "iso:country":"DE",
    "sg:address":"Gildestr. 11",
    "sg:city":"Roth",
    "sg:phone":"+49 9171",
    "sg:postcode":"91154",
    "sg:province":"Bayern",
    "wof:name":"Technisches Hilfswerk Ortsverband Roth",
    "wof:placetype":"venue"
},
  "geometry": {"coordinates":[11.1132354736,49.2472190857],"type":"Point"}
}