{
  "type": "Feature",
  "properties": {
    "iso:country":"DE",
    "sg:address":"Wilhelm-Conrad-R\u00f6ntgen-Str. 4",
    "sg:city":"Eberswalde",
    "sg:phone":"+49 3334/57530",
    "sg:postcode":"16225",
    "sg:province":"Brandenburg",
    "wof:name":"Fruchtservice Vertriebs Gmbh",
    "wof:placetype":"venue"
},
  "geometry": {"coordinates":[13.7850217819,52.8589897156],"type":"Point"}
}