{
  "type": "Feature",
  "properties": {
    "iso:country":"DE",
    "sg:address":"Am Getreidespeicher 29",
    "sg:city":"Mainz",
    "sg:phone":"+49 6131/611936",
    "sg:postcode":"55120",
    "sg:province":"Rheinland-Pfalz",
    "wof:name":"Josef Beaury & Co.",
    "wof:placetype":"venue"
},
  "geometry": {"coordinates":[8.2637033463,50.0134849548],"type":"Point"}
}