{
  "type": "Feature",
  "properties": {
    "iso:country":"DE",
    "sg:address":"Blumenower Str. 14",
    "sg:city":"Dannenwalde",
    "sg:phone":"+49 33085/70306",
    "sg:postcode":"16775",
    "sg:province":"Brandenburg",
    "wof:name":"Soma Sondermaschinenbau Dannenwalde Gmbh",
    "wof:placetype":"venue"
},
  "geometry": {"coordinates":[13.19122,53.082741],"type":"Point"}
}