{
  "type": "Feature",
  "properties": {
    "iso:country":"DE",
    "sg:address":"Thurasdorf",
    "sg:city":"Wiesenfelden",
    "sg:phone":"+49 9966/1038",
    "sg:postcode":"94344",
    "sg:province":"Bayern",
    "wof:name":"Gasthaus Tremmel",
    "wof:placetype":"venue"
},
  "geometry": {"coordinates":[12.5656604767,49.0141906738],"type":"Point"}
}