{
  "type": "Feature",
  "properties": {
    "iso:country":"DE",
    "sg:address":"Dorfstr. 67",
    "sg:city":"Neuk\u00fcstrinchen",
    "sg:postcode":"16259",
    "sg:province":"Brandenburg",
    "wof:name":"Evangelisches Pfarramt",
    "wof:placetype":"venue"
},
  "geometry": {"coordinates":[14.026684761,52.7821731567],"type":"Point"}
}