{
  "type": "Feature",
  "properties": {
    "iso:country":"DE",
    "sg:address":"In den Weywiesen 96",
    "sg:city":"Bottrop",
    "sg:postcode":"46240",
    "sg:province":"Nordrhein-Westfalen",
    "wof:name":"Paschke Bauelemente Gmbh",
    "wof:placetype":"venue"
},
  "geometry": {"coordinates":[6.925578,51.545967],"type":"Point"}
}