{
  "type": "Feature",
  "properties": {
    "iso:country":"DE",
    "sg:address":"Frankenstr. 28",
    "sg:city":"Erftstadt",
    "sg:postcode":"50374",
    "sg:province":"Nordrhein-Westfalen",
    "wof:name":"Kath. \u00d6ffentliche Bibliothek St. Lambertus",
    "wof:placetype":"venue"
},
  "geometry": {"coordinates":[6.817352,50.783909],"type":"Point"}
}