{
  "type": "Feature",
  "properties": {
    "iso:country":"DE",
    "sg:address":"Friedrich-Ebert-Str. 35",
    "sg:city":"Ottweiler",
    "sg:phone":"+49 6824/700949",
    "sg:postcode":"66564",
    "sg:province":"Saarland",
    "wof:name":"Vera Gemeinder-el\u00df",
    "wof:placetype":"venue"
},
  "geometry": {"coordinates":[7.1697378159,49.4135322571],"type":"Point"}
}