{
  "type": "Feature",
  "properties": {
    "iso:country":"DE",
    "sg:address":"Gussau 59b",
    "sg:city":"Hamburg",
    "sg:postcode":"22359",
    "sg:province":"Hamburg",
    "wof:name":"Afe Agentur F\u00fcr Einrichtung Gmbh",
    "wof:placetype":"venue"
},
  "geometry": {"coordinates":[10.1713552475,53.65883255],"type":"Point"}
}