{
  "type": "Feature",
  "properties": {
    "iso:country":"DE",
    "sg:address":"Neue Maastrichter Str. 12 -14",
    "sg:city":"K\u00f6ln",
    "sg:phone":"+49 221/516393",
    "sg:postcode":"50672",
    "sg:province":"Nordrhein-Westfalen",
    "wof:name":"Wallmeyer Gmbh",
    "wof:placetype":"venue"
},
  "geometry": {"coordinates":[6.933868,50.939556],"type":"Point"}
}