{
  "type": "Feature",
  "properties": {
    "iso:country":"DE",
    "sg:address":"Astruper Str. 19",
    "sg:city":"Visbek",
    "sg:phone":"+49 4445/96770",
    "sg:postcode":"49429",
    "sg:province":"Niedersachsen",
    "wof:name":"Hotel Garni W\u00fcbboldt",
    "wof:placetype":"venue"
},
  "geometry": {"coordinates":[8.3099737167,52.8333435059],"type":"Point"}
}