{
  "type": "Feature",
  "properties": {
    "iso:country":"DE",
    "sg:address":"Borsigstr. 28",
    "sg:city":"Rodgau",
    "sg:postcode":"63110",
    "sg:province":"Hessen",
    "wof:name":"Tl - Pr\u00e4zisionstechnik E. K.",
    "wof:placetype":"venue"
},
  "geometry": {"coordinates":[8.8648605347,49.9906425476],"type":"Point"}
}