{
  "type": "Feature",
  "properties": {
    "iso:country":"DE",
    "sg:address":"Agnes-Bernauer-Str. 65",
    "sg:city":"M\u00fcnchen",
    "sg:phone":"+49 89/581256",
    "sg:postcode":"80687",
    "sg:province":"Bayern",
    "wof:name":"Anna Svenda Krankengymnastin",
    "wof:placetype":"venue"
},
  "geometry": {"coordinates":[11.505737,48.139462],"type":"Point"}
}