{
  "type": "Feature",
  "properties": {
    "iso:country":"DE",
    "sg:address":"Augustdorfer Str. 67",
    "sg:city":"Detmold",
    "sg:phone":"+49 5232/88902",
    "sg:postcode":"32758",
    "sg:province":"Nordrhein-Westfalen",
    "wof:name":"Westfalen-tankstelle Inh. Ralf Bartling",
    "wof:placetype":"venue"
},
  "geometry": {"coordinates":[8.778459549,51.9368934631],"type":"Point"}
}