{
  "type": "Feature",
  "properties": {
    "iso:country":"DE",
    "sg:address":"Gm\u00fcnder Str. 2",
    "sg:city":"Schorndorf",
    "sg:phone":"+49 7181/929888",
    "sg:postcode":"73614",
    "sg:province":"Baden-W\u00fcrttemberg",
    "wof:name":"Cd-creativ Design",
    "wof:placetype":"venue"
},
  "geometry": {"coordinates":[9.532332,48.805367],"type":"Point"}
}