{
  "type": "Feature",
  "properties": {
    "iso:country":"DE",
    "sg:address":"Reiherweg 17",
    "sg:city":"K\u00f6ln",
    "sg:phone":"+49 221/9582174",
    "sg:postcode":"50829",
    "sg:province":"Nordrhein-Westfalen",
    "wof:name":"E. Momma",
    "wof:placetype":"venue"
},
  "geometry": {"coordinates":[6.881282,50.957191],"type":"Point"}
}