{
  "type": "Feature",
  "properties": {
    "iso:country":"DE",
    "sg:address":"Beethovenstr. 20",
    "sg:city":"Herford",
    "sg:phone":"+49 5221/81419",
    "sg:postcode":"32049",
    "sg:province":"Nordrhein-Westfalen",
    "wof:name":"B & M D\u00e4mmtechnik Gmbh",
    "wof:placetype":"venue"
},
  "geometry": {"coordinates":[8.700059,52.120068],"type":"Point"}
}