{
  "type": "Feature",
  "properties": {
    "iso:country":"DE",
    "sg:address":"Wilhelm-Sch\u00e4fer-Str. 3",
    "sg:city":"Heringen",
    "sg:phone":"+49 6624/8287",
    "sg:postcode":"36266",
    "sg:province":"Hessen",
    "wof:name":"Helmut Weyh",
    "wof:placetype":"venue"
},
  "geometry": {"coordinates":[10.0129146576,50.888961792],"type":"Point"}
}