{
  "type": "Feature",
  "properties": {
    "iso:country":"DE",
    "sg:address":"Walsener Str. 3",
    "sg:city":"Barnstorf",
    "sg:phone":"+49 5442/2827",
    "sg:postcode":"49406",
    "sg:province":"Niedersachsen",
    "wof:name":"Gasthaus Zur Pfefferm\u00fchle Inh. Gabriele Rohlfs",
    "wof:placetype":"venue"
},
  "geometry": {"coordinates":[8.4962415695,52.7166099548],"type":"Point"}
}