{
  "type": "Feature",
  "properties": {
    "iso:country":"DE",
    "sg:address":"Schwimmbadstr. 8",
    "sg:city":"Heuchelheim",
    "sg:phone":"+49 641/61289",
    "sg:postcode":"35452",
    "sg:province":"Hessen",
    "wof:name":"Ernst Rinn Architekt",
    "wof:placetype":"venue"
},
  "geometry": {"coordinates":[8.621665,50.581219],"type":"Point"}
}