{
  "type": "Feature",
  "properties": {
    "iso:country":"DE",
    "sg:address":"August-Bebel-Str. 7",
    "sg:city":"Bad K\u00f6sen",
    "sg:phone":"+49 34463/28531",
    "sg:postcode":"06628",
    "sg:province":"Sachsen-Anhalt",
    "wof:name":"F. R. Marten Ingenieur",
    "wof:placetype":"venue"
},
  "geometry": {"coordinates":[11.7252025604,51.1361923218],"type":"Point"}
}