{
  "type": "Feature",
  "properties": {
    "iso:country":"DE",
    "sg:address":"Weiherstra\u00dfe 35/3",
    "sg:city":"Esslingen",
    "sg:phone":"+49 711",
    "sg:postcode":"73730",
    "sg:province":"Baden-W\u00fcrttemberg",
    "wof:name":"Hildegard Landmesser",
    "wof:placetype":"venue"
},
  "geometry": {"coordinates":[9.3370666504,48.7296295166],"type":"Point"}
}