{
  "type": "Feature",
  "properties": {
    "iso:country":"DE",
    "sg:address":"Senner Str. 32",
    "sg:city":"G\u00fctersloh",
    "sg:postcode":"33335",
    "sg:province":"Nordrhein-Westfalen",
    "wof:name":"Fl\u00f6totto Gmbh",
    "wof:placetype":"venue"
},
  "geometry": {"coordinates":[8.4882202148,51.9413871765],"type":"Point"}
}