{
  "type": "Feature",
  "properties": {
    "iso:country":"DE",
    "sg:address":"Am Kirchb\u00fchl 13",
    "sg:city":"Schwarzenbruck",
    "sg:phone":"+49 9128/3003",
    "sg:postcode":"90592",
    "sg:province":"Bayern",
    "wof:name":"Irena Richter Innenarchitekt",
    "wof:placetype":"venue"
},
  "geometry": {"coordinates":[11.238584,49.358505],"type":"Point"}
}