{
  "type": "Feature",
  "properties": {
    "iso:country":"DE",
    "sg:address":"Borsigstr. 50",
    "sg:city":"Stuttgart",
    "sg:phone":"+49 4971/198130",
    "sg:postcode":"70469",
    "sg:province":"Baden-W\u00fcrttemberg",
    "wof:name":"Hahn & Kolb Werkzeuge Gmbh",
    "wof:placetype":"venue"
},
  "geometry": {"coordinates":[9.173924,48.818787],"type":"Point"}
}