{
  "type": "Feature",
  "properties": {
    "iso:country":"DE",
    "sg:address":"Am Laaker Bach 3",
    "sg:city":"Bocholt",
    "sg:phone":"+49 2871/7553",
    "sg:postcode":"46395",
    "sg:province":"Nordrhein-Westfalen",
    "wof:name":"Heinrich Krasenbrink",
    "wof:placetype":"venue"
},
  "geometry": {"coordinates":[6.572435,51.802685],"type":"Point"}
}