{
  "type": "Feature",
  "properties": {
    "iso:country":"DE",
    "sg:address":"Granastr. 38",
    "sg:city":"Konz",
    "sg:phone":"+49 6501/5615",
    "sg:postcode":"54329",
    "sg:province":"Rheinland-Pfalz",
    "wof:name":"Optik Kranz Gmbh",
    "wof:placetype":"venue"
},
  "geometry": {"coordinates":[6.5724449158,49.6990356445],"type":"Point"}
}