{
  "type": "Feature",
  "properties": {
    "iso:country":"DE",
    "sg:address":"Kruthorst 4d",
    "sg:city":"Bargteheide",
    "sg:postcode":"22941",
    "sg:province":"Schleswig-Holstein",
    "wof:name":"Lemsahler Grundst\u00fccks- Und Vermietungsges. Mbh",
    "wof:placetype":"venue"
},
  "geometry": {"coordinates":[10.2592506409,53.7329216003],"type":"Point"}
}