{
  "type": "Feature",
  "properties": {
    "iso:country":"DE",
    "sg:address":"Boschstr 3",
    "sg:city":"Haan",
    "sg:phone":"+49 212/96071",
    "sg:postcode":"42781",
    "sg:province":"Nordrhein-Westfalen",
    "wof:name":"Gebr. Pausch & Maurer Gmbh & Co Kg",
    "wof:placetype":"venue"
},
  "geometry": {"coordinates":[6.992336,51.18335],"type":"Point"}
}