{
  "type": "Feature",
  "properties": {
    "iso:country":"DE",
    "sg:address":"Von-Rosen-Str. 12",
    "sg:city":"Zweibr\u00fccken",
    "sg:phone":"+49 6332/92370",
    "sg:postcode":"66482",
    "sg:province":"Rheinland-Pfalz",
    "wof:name":"Praxis Fess Und Dr. Med. Forcher",
    "wof:placetype":"venue"
},
  "geometry": {"coordinates":[7.3631792068,49.2473831177],"type":"Point"}
}