{
  "type": "Feature",
  "properties": {
    "iso:country":"DE",
    "sg:address":"Elbchaussee 517",
    "sg:city":"Hamburg",
    "sg:phone":"+49 40/864535",
    "sg:postcode":"22587",
    "sg:province":"Hamburg",
    "wof:name":"Kati Of Sky Fine Engilish Country Wear",
    "wof:placetype":"venue"
},
  "geometry": {"coordinates":[9.8220272064,53.5608634949],"type":"Point"}
}