{
  "type": "Feature",
  "properties": {
    "iso:country":"DE",
    "sg:address":"Geiststr. 32",
    "sg:city":"Halle",
    "sg:phone":"+49 345/3881231",
    "sg:postcode":"06108",
    "sg:province":"Sachsen-Anhalt",
    "wof:name":"Graf Luckner",
    "wof:placetype":"venue"
},
  "geometry": {"coordinates":[11.9657440186,51.4915657043],"type":"Point"}
}