{
  "type": "Feature",
  "properties": {
    "iso:country":"DE",
    "sg:address":"Alpenstr. 24",
    "sg:city":"Baiern",
    "sg:phone":"+49 8093/794",
    "sg:postcode":"85625",
    "sg:province":"Bayern",
    "wof:name":"B. Hagenrainer",
    "wof:placetype":"venue"
},
  "geometry": {"coordinates":[11.90703,47.951027],"type":"Point"}
}