{
  "type": "Feature",
  "properties": {
    "iso:country":"DE",
    "sg:address":"Erlentiefenstr. 9",
    "sg:city":"Bergkamen",
    "sg:phone":"+49 2307/982810",
    "sg:postcode":"59192",
    "sg:province":"Nordrhein-Westfalen",
    "wof:name":"Sixt Ag",
    "wof:placetype":"venue"
},
  "geometry": {"coordinates":[7.659884,51.624313],"type":"Point"}
}