{
  "type": "Feature",
  "properties": {
    "iso:country":"DE",
    "sg:address":"Hahnweg 116",
    "sg:city":"Coburg",
    "sg:phone":"+49 9561/65260",
    "sg:postcode":"96450",
    "sg:province":"Bayern",
    "wof:name":"K. Leistner",
    "wof:placetype":"venue"
},
  "geometry": {"coordinates":[10.975449,50.268124],"type":"Point"}
}