{
  "type": "Feature",
  "properties": {
    "iso:country":"DE",
    "sg:address":"Weihersweg 16",
    "sg:city":"Fladungen",
    "sg:phone":"+49 9778/91460",
    "sg:postcode":"97650",
    "sg:province":"Bayern",
    "wof:name":"Hubert B\u00e4stlein Steuerberater",
    "wof:placetype":"venue"
},
  "geometry": {"coordinates":[10.1364603043,50.5228652954],"type":"Point"}
}