{
  "type": "Feature",
  "properties": {
    "iso:country":"DE",
    "sg:address":"Im Geeren 36",
    "sg:city":"Frankfurt am Main",
    "sg:phone":"+49 69/74308400",
    "sg:postcode":"60433",
    "sg:province":"Hessen",
    "wof:name":"Horvat Internationale Immobilienberatung",
    "wof:placetype":"venue"
},
  "geometry": {"coordinates":[8.6637792587,50.1610641479],"type":"Point"}
}