{
  "type": "Feature",
  "properties": {
    "iso:country":"DE",
    "sg:address":"Am Abdinghof 11",
    "sg:city":"Paderborn",
    "sg:phone":"+49 5251/206247",
    "sg:postcode":"33098",
    "sg:province":"Nordrhein-Westfalen",
    "wof:name":"St\u00e4dtische Galerie Im Stadthaus",
    "wof:placetype":"venue"
},
  "geometry": {"coordinates":[8.752303,51.718315],"type":"Point"}
}