{
  "type": "Feature",
  "properties": {
    "iso:country":"DE",
    "sg:address":"Stifterstr. 2",
    "sg:city":"Ludwigshafen",
    "sg:phone":"+49 621/584354",
    "sg:postcode":"67065",
    "sg:province":"Rheinland-Pfalz",
    "wof:name":"Linie 48",
    "wof:placetype":"venue"
},
  "geometry": {"coordinates":[8.434633255,49.4687004089],"type":"Point"}
}