{
  "type": "Feature",
  "properties": {
    "iso:country":"DE",
    "sg:address":"Tischbeinstr. 45",
    "sg:city":"Kassel",
    "sg:phone":"+49 561/284460",
    "sg:postcode":"34121",
    "sg:province":"Hessen",
    "wof:name":"W. A. Schaller",
    "wof:placetype":"venue"
},
  "geometry": {"coordinates":[9.4839477539,51.3077354431],"type":"Point"}
}