{
  "type": "Feature",
  "properties": {
    "iso:country":"DE",
    "sg:address":"Rosenstr. 66",
    "sg:city":"Esslingen",
    "sg:phone":"+49 711/322654",
    "sg:postcode":"73733",
    "sg:province":"Baden-W\u00fcrttemberg",
    "wof:name":"Helmut Siegle Zahn\u00e4rztebedarf",
    "wof:placetype":"venue"
},
  "geometry": {"coordinates":[9.277419,48.750511],"type":"Point"}
}