{
  "type": "Feature",
  "properties": {
    "iso:country":"DE",
    "sg:address":"J\u00fcthornstr. 33",
    "sg:city":"Hamburg",
    "sg:phone":"+49 40/687161",
    "sg:postcode":"22043",
    "sg:province":"Hamburg",
    "wof:name":"Institut F\u00fcr Weltkunde In Bildung Und Forschung Wbf",
    "wof:placetype":"venue"
},
  "geometry": {"coordinates":[10.0722513199,53.5652618408],"type":"Point"}
}