{
  "type": "Feature",
  "properties": {
    "iso:country":"DE",
    "sg:address":"Kirchenweg 14",
    "sg:city":"N\u00fcrnberg",
    "sg:phone":"+49 911/337828",
    "sg:postcode":"90419",
    "sg:province":"Bayern",
    "wof:name":"J. Bauer",
    "wof:placetype":"venue"
},
  "geometry": {"coordinates":[11.0678787231,49.4622116089],"type":"Point"}
}