{
  "type": "Feature",
  "properties": {
    "iso:country":"DE",
    "sg:address":"Sindlinger Bahnstr. 113",
    "sg:city":"Frankfurt",
    "sg:phone":"+49 69/374110",
    "sg:postcode":"65931",
    "sg:province":"Hessen",
    "wof:name":"Stephanische Apotheke",
    "wof:placetype":"venue"
},
  "geometry": {"coordinates":[8.51312,50.086494],"type":"Point"}
}