{
  "type": "Feature",
  "properties": {
    "iso:country":"DE",
    "sg:address":"M\u00e4uerlesstr. 30",
    "sg:city":"Magstadt",
    "sg:phone":"+49 7159/42440",
    "sg:postcode":"71106",
    "sg:province":"Baden-W\u00fcrttemberg",
    "wof:name":"Vincenzo Salemi",
    "wof:placetype":"venue"
},
  "geometry": {"coordinates":[8.960042,48.74604],"type":"Point"}
}