{
  "type": "Feature",
  "properties": {
    "iso:country":"DE",
    "sg:address":"Zur Haselburg",
    "sg:city":"H\u00f6chst",
    "sg:postcode":"64739",
    "sg:province":"Hessen",
    "wof:name":"Haselburg-halle Mehrzweckveranstaltungshalle",
    "wof:placetype":"venue"
},
  "geometry": {"coordinates":[8.943275,49.776024],"type":"Point"}
}