{
  "type": "Feature",
  "properties": {
    "iso:country":"DE",
    "sg:address":"Seebacherweg 22",
    "sg:city":"Stockach",
    "sg:postcode":"78333",
    "sg:province":"Baden-W\u00fcrttemberg",
    "wof:name":"The News Agency Angela Jung E. K.",
    "wof:placetype":"venue"
},
  "geometry": {"coordinates":[9.0191526413,47.8599662781],"type":"Point"}
}