{
  "type": "Feature",
  "properties": {
    "iso:country":"DE",
    "sg:address":"K\u00f6lner Str. 268",
    "sg:city":"D\u00fcsseldorf",
    "sg:phone":"+49 211/771199",
    "sg:postcode":"40227",
    "sg:province":"Nordrhein-Westfalen",
    "wof:name":"Rudis Reste Rampe",
    "wof:placetype":"venue"
},
  "geometry": {"coordinates":[6.806588,51.213005],"type":"Point"}
}