{
  "type": "Feature",
  "properties": {
    "iso:country":"DE",
    "sg:address":"Pflegerstr. 15 D",
    "sg:city":"M\u00fcnchen",
    "sg:phone":"+49 89/8113840",
    "sg:postcode":"81247",
    "sg:province":"Bayern",
    "wof:name":"Heinrich Schulte Ingenieur",
    "wof:placetype":"venue"
},
  "geometry": {"coordinates":[11.4813041687,48.1659545898],"type":"Point"}
}