{
  "type": "Feature",
  "properties": {
    "iso:country":"DE",
    "sg:address":"R\u00f6dersteinweg 4",
    "sg:city":"Hofheim",
    "sg:phone":"+49 6192/8023",
    "sg:postcode":"65719",
    "sg:province":"Hessen",
    "wof:name":"Gerd Salomon Steuerberater",
    "wof:placetype":"venue"
},
  "geometry": {"coordinates":[8.4386844635,50.0922698975],"type":"Point"}
}