{
  "type": "Feature",
  "properties": {
    "iso:country":"DE",
    "sg:address":"Br\u00fcckenstr. 65",
    "sg:city":"Langerwehe",
    "sg:phone":"+49 2423/90016",
    "sg:postcode":"52379",
    "sg:province":"Nordrhein-Westfalen",
    "wof:name":"H. Mertens",
    "wof:placetype":"venue"
},
  "geometry": {"coordinates":[6.3689851761,50.8295822144],"type":"Point"}
}