{
  "type": "Feature",
  "properties": {
    "iso:country":"DE",
    "sg:address":"Admiral-Klatt-Str. 1",
    "sg:city":"Wilhelmshaven",
    "sg:phone":"+49 4421/455144",
    "sg:postcode":"26382",
    "sg:province":"Niedersachsen",
    "wof:name":"P. Harms",
    "wof:placetype":"venue"
},
  "geometry": {"coordinates":[8.1102113724,53.5159454346],"type":"Point"}
}