{
  "type": "Feature",
  "properties": {
    "iso:country":"DE",
    "sg:address":"Hauptstr. 94",
    "sg:city":"Tambach-Dietharz",
    "sg:phone":"+49 36252/36576",
    "sg:postcode":"99897",
    "sg:province":"Th\u00fcringen",
    "wof:name":"Elli Seyfarth",
    "wof:placetype":"venue"
},
  "geometry": {"coordinates":[10.6083421707,50.7921867371],"type":"Point"}
}