{
  "type": "Feature",
  "properties": {
    "iso:country":"DE",
    "sg:address":"Hauptstr. 5",
    "sg:city":"R\u00fcthen",
    "sg:phone":"+49 2954/354",
    "sg:postcode":"59602",
    "sg:province":"Nordrhein-Westfalen",
    "wof:name":"Pieper",
    "wof:placetype":"venue"
},
  "geometry": {"coordinates":[8.4240474701,51.5649337769],"type":"Point"}
}