{
  "type": "Feature",
  "properties": {
    "iso:country":"DE",
    "sg:address":"Jordanstr. 6",
    "sg:city":"Zirndorf",
    "sg:phone":"+49 911/692964",
    "sg:postcode":"90513",
    "sg:province":"Bayern",
    "wof:name":"Teppichboden-r\u00f6per Lothar R\u00f6per",
    "wof:placetype":"venue"
},
  "geometry": {"coordinates":[10.951259,49.434204],"type":"Point"}
}