{
  "type": "Feature",
  "properties": {
    "iso:country":"DE",
    "sg:address":"Werler Str. 32",
    "sg:city":"Arnsberg",
    "sg:phone":"+49 2932/25617",
    "sg:postcode":"59755",
    "sg:province":"Nordrhein-Westfalen",
    "wof:name":"Weber Pokale Gmbh",
    "wof:placetype":"venue"
},
  "geometry": {"coordinates":[7.962054,51.458004],"type":"Point"}
}