{
  "type": "Feature",
  "properties": {
    "iso:country":"DE",
    "sg:address":"Bismarckstr. 2",
    "sg:city":"Traben-Trarbach",
    "sg:phone":"+49 6541/1050",
    "sg:postcode":"56841",
    "sg:province":"Rheinland-Pfalz",
    "wof:name":"Trend-m\u00f6bel-bauer Handels Gmbh",
    "wof:placetype":"venue"
},
  "geometry": {"coordinates":[7.1185369492,49.9515647888],"type":"Point"}
}