{
  "type": "Feature",
  "properties": {
    "iso:country":"DE",
    "sg:address":"Wormser Str. 119",
    "sg:city":"Frankenthal",
    "sg:phone":"+49 6233/65108",
    "sg:postcode":"67227",
    "sg:province":"Rheinland-Pfalz",
    "wof:name":"Disco Fun Und Lollipop",
    "wof:placetype":"venue"
},
  "geometry": {"coordinates":[8.35311,49.549294],"type":"Point"}
}