{
  "type": "Feature",
  "properties": {
    "iso:country":"DE",
    "sg:address":"Fontanestr. 10",
    "sg:city":"Hameln",
    "sg:phone":"+49 5151/41350",
    "sg:postcode":"31785",
    "sg:province":"Niedersachsen",
    "wof:name":"A. Hofe",
    "wof:placetype":"venue"
},
  "geometry": {"coordinates":[9.3494405746,52.1142883301],"type":"Point"}
}