{
  "type": "Feature",
  "properties": {
    "iso:country":"DE",
    "sg:address":"Burgwall 18",
    "sg:city":"Rostock",
    "sg:phone":"+49 36961/3680",
    "sg:postcode":"18055",
    "sg:province":"Mecklenburg-Vorpommern",
    "wof:name":"Reiner Labling Fernmeldeanlagenbau Gmbh",
    "wof:placetype":"venue"
},
  "geometry": {"coordinates":[10.357416,50.814236],"type":"Point"}
}