{
  "type": "Feature",
  "properties": {
    "iso:country":"DE",
    "sg:address":"Bindergasse 2",
    "sg:city":"Saaldorf-Surheim",
    "sg:phone":"+49 8654/9605",
    "sg:postcode":"83416",
    "sg:province":"Bayern",
    "wof:name":"Paul Rehrl",
    "wof:placetype":"venue"
},
  "geometry": {"coordinates":[12.929206,47.86879],"type":"Point"}
}