{
  "type": "Feature",
  "properties": {
    "iso:country":"DE",
    "sg:address":"Schaafenstr. 7",
    "sg:city":"K\u00f6ln",
    "sg:phone":"+49 221/2403546",
    "sg:postcode":"50676",
    "sg:province":"Nordrhein-Westfalen",
    "wof:name":"Rudis Brillenerlebnis Optik Gmbh",
    "wof:placetype":"venue"
},
  "geometry": {"coordinates":[6.9427909851,50.9349479675],"type":"Point"}
}