{
  "type": "Feature",
  "properties": {
    "iso:country":"DE",
    "sg:address":"Schulstr. 12",
    "sg:city":"Deensen",
    "sg:phone":"+49 5532/4412",
    "sg:postcode":"37627",
    "sg:province":"Niedersachsen",
    "wof:name":"Ulrike Seefeld-r\u00f6\u00dfler",
    "wof:placetype":"venue"
},
  "geometry": {"coordinates":[9.596032,51.85733],"type":"Point"}
}