{
  "type": "Feature",
  "properties": {
    "iso:country":"DE",
    "sg:address":"Bertholdstr. 31",
    "sg:city":"Stolberg",
    "sg:phone":"+49 2402/36197",
    "sg:postcode":"52223",
    "sg:province":"Nordrhein-Westfalen",
    "wof:name":"S. Rutz",
    "wof:placetype":"venue"
},
  "geometry": {"coordinates":[6.2132058144,50.7329025269],"type":"Point"}
}