{
  "type": "Feature",
  "properties": {
    "iso:country":"DE",
    "sg:address":"Mettinger Str. 101-105",
    "sg:city":"Esslingen",
    "sg:postcode":"73728",
    "sg:province":"Baden-W\u00fcrttemberg",
    "wof:name":"W & S Service Gmbh",
    "wof:placetype":"venue"
},
  "geometry": {"coordinates":[9.2928543091,48.7423362732],"type":"Point"}
}