{
  "type": "Feature",
  "properties": {
    "iso:country":"DE",
    "sg:address":"Im Lohr 14",
    "sg:city":"Mannheim",
    "sg:phone":"+49 621/8281030",
    "sg:postcode":"68199",
    "sg:province":"Baden-W\u00fcrttemberg",
    "wof:name":"W. Oswald",
    "wof:placetype":"venue"
},
  "geometry": {"coordinates":[8.477211,49.463924],"type":"Point"}
}