{
  "type": "Feature",
  "properties": {
    "iso:country":"DE",
    "sg:address":"Auguststra\u00dfe 49a",
    "sg:city":"Berlin",
    "sg:postcode":"10119",
    "sg:province":"Berlin",
    "wof:name":"Open Space Lab Gbr - Konferenzen, Events, Veranstaltungen",
    "wof:placetype":"venue"
},
  "geometry": {"coordinates":[13.4008998871,52.5278968811],"type":"Point"}
}