{
  "type": "Feature",
  "properties": {
    "iso:country":"DE",
    "sg:address":"Sandkrug 3 a",
    "sg:city":"Bandenitz",
    "sg:postcode":"19230",
    "sg:province":"Mecklenburg-Vorpommern",
    "wof:name":"Milchhof H\u00fclseburg Gmbh & Co. Kg",
    "wof:placetype":"venue"
},
  "geometry": {"coordinates":[11.2906122208,53.5124816895],"type":"Point"}
}