{
  "type": "Feature",
  "properties": {
    "iso:country":"DE",
    "sg:address":"Blumenstr. 6",
    "sg:city":"Wiesbaden",
    "sg:phone":"+49 611/334447",
    "sg:postcode":"65189",
    "sg:province":"Hessen",
    "wof:name":"Zibell Willner & Partner Ingenieurges. F\u00fcr Technische",
    "wof:placetype":"venue"
},
  "geometry": {"coordinates":[8.2506227493,50.0798454285],"type":"Point"}
}