{
  "type": "Feature",
  "properties": {
    "iso:country":"DE",
    "sg:address":"Pforzheimer Str. 244 A",
    "sg:city":"Stuttgart",
    "sg:phone":"+49 711/8893614",
    "sg:postcode":"70499",
    "sg:province":"Baden-W\u00fcrttemberg",
    "wof:name":"Erich Matti Bildhauer",
    "wof:placetype":"venue"
},
  "geometry": {"coordinates":[9.125349,48.814758],"type":"Point"}
}