{
  "type": "Feature",
  "properties": {
    "iso:country":"DE",
    "sg:address":"Neutorstr. 10",
    "sg:city":"Mainz",
    "sg:phone":"+49 6131/223849",
    "sg:postcode":"55116",
    "sg:province":"Rheinland-Pfalz",
    "wof:name":"Volkers Fitness-center",
    "wof:placetype":"venue"
},
  "geometry": {"coordinates":[8.2779979706,49.9950370789],"type":"Point"}
}