{
  "type": "Feature",
  "properties": {
    "iso:country":"DE",
    "sg:address":"Pfarrweg 7",
    "sg:city":"Scheidegg",
    "sg:postcode":"88175",
    "sg:province":"Bayern",
    "wof:name":"Kath. Pfarramt St. Gallus",
    "wof:placetype":"venue"
},
  "geometry": {"coordinates":[9.8503446579,47.5825424194],"type":"Point"}
}