{
  "type": "Feature",
  "properties": {
    "iso:country":"DE",
    "sg:address":"Windbergerstr. 2",
    "sg:city":"Ingolstadt",
    "sg:phone":"+49 841",
    "sg:postcode":"85053",
    "sg:province":"Bayern",
    "wof:name":"Morisch\u00d6berl",
    "wof:placetype":"venue"
},
  "geometry": {"coordinates":[11.4332275391,48.7512664795],"type":"Point"}
}