{
  "type": "Feature",
  "properties": {
    "iso:country":"DE",
    "sg:address":"Zimmerstr. 5",
    "sg:city":"Wittenberge",
    "sg:postcode":"19322",
    "sg:province":"Brandenburg",
    "wof:name":"Ev.-freikirchliche Gemeinde",
    "wof:placetype":"venue"
},
  "geometry": {"coordinates":[11.7570457458,52.9955062866],"type":"Point"}
}