{
  "type": "Feature",
  "properties": {
    "iso:country":"DE",
    "sg:address":"Rosenstr. 8",
    "sg:city":"Dransfeld",
    "sg:phone":"+49 5502/1216",
    "sg:postcode":"37127",
    "sg:province":"Niedersachsen",
    "wof:name":"E. Effnert",
    "wof:placetype":"venue"
},
  "geometry": {"coordinates":[9.7640838623,51.4966278076],"type":"Point"}
}