{
  "type": "Feature",
  "properties": {
    "iso:country":"DE",
    "sg:address":"Kurt-Schumacher-Str. 9",
    "sg:city":"Alzey",
    "sg:postcode":"55232",
    "sg:province":"Rheinland-Pfalz",
    "wof:name":"Lions Club Alzey Dr. Heinz-bernd Eppler",
    "wof:placetype":"venue"
},
  "geometry": {"coordinates":[8.1058549881,49.7371673584],"type":"Point"}
}