{
  "type": "Feature",
  "properties": {
    "iso:country":"DE",
    "sg:address":"Julienluster Weg 71",
    "sg:city":"Kiel",
    "sg:phone":"+49 431/521618",
    "sg:postcode":"24109",
    "sg:province":"Schleswig-Holstein",
    "wof:name":"Karl-heinz Graf Alt- Und Abfallstoffe",
    "wof:placetype":"venue"
},
  "geometry": {"coordinates":[10.078613,54.31805],"type":"Point"}
}