{
  "type": "Feature",
  "properties": {
    "iso:country":"DE",
    "sg:address":"Am Eichkamp 2",
    "sg:city":"Sottrum",
    "sg:postcode":"27367",
    "sg:province":"Niedersachsen",
    "wof:name":"Lothar Luckhans Gmbh",
    "wof:placetype":"venue"
},
  "geometry": {"coordinates":[9.2277202606,53.1139984131],"type":"Point"}
}