{
  "type": "Feature",
  "properties": {
    "iso:country":"DE",
    "sg:address":"Lintruper Str. 46",
    "sg:city":"Berlin",
    "sg:phone":"+49 30/7426103",
    "sg:postcode":"12305",
    "sg:province":"Berlin",
    "wof:name":"Hans Knauff Rechtsanwalt",
    "wof:placetype":"venue"
},
  "geometry": {"coordinates":[13.4016962051,52.4099121094],"type":"Point"}
}