{
  "type": "Feature",
  "properties": {
    "iso:country":"DE",
    "sg:address":"Peterstr. 13",
    "sg:city":"Hahnheim",
    "sg:phone":"+49 6737/760013",
    "sg:postcode":"55278",
    "sg:province":"Rheinland-Pfalz",
    "wof:name":"H. Schnoor Finanzberater",
    "wof:placetype":"venue"
},
  "geometry": {"coordinates":[8.2396326065,49.8622131348],"type":"Point"}
}