{
  "type": "Feature",
  "properties": {
    "iso:country":"DE",
    "sg:address":"Altenaustr. 6",
    "sg:city":"Bad Pyrmont",
    "sg:phone":"+49 5281/607788",
    "sg:postcode":"31812",
    "sg:province":"Niedersachsen",
    "wof:name":"Lvm Versicherungsb\u00fcro Hans-peter B\u00f6ke",
    "wof:placetype":"venue"
},
  "geometry": {"coordinates":[9.2553634644,51.9846191406],"type":"Point"}
}