{
  "type": "Feature",
  "properties": {
    "iso:country":"DE",
    "sg:address":"Roritzerstr. 37",
    "sg:city":"N\u00fcrnberg",
    "sg:phone":"+49 911/3746728",
    "sg:postcode":"90419",
    "sg:province":"Bayern",
    "wof:name":"Wfk K\u00e4lte- Und Klima- Technik E. K.",
    "wof:placetype":"venue"
},
  "geometry": {"coordinates":[11.069941,49.46109],"type":"Point"}
}