{
  "type": "Feature",
  "properties": {
    "iso:country":"DE",
    "sg:address":"Talstr. 19",
    "sg:city":"Lollar",
    "sg:phone":"+49 6406/71452",
    "sg:postcode":"35457",
    "sg:province":"Hessen",
    "wof:name":"Siegfried Barho Steuerberater",
    "wof:placetype":"venue"
},
  "geometry": {"coordinates":[8.6875677109,50.6817321777],"type":"Point"}
}