{
  "type": "Feature",
  "properties": {
    "iso:country":"DE",
    "sg:address":"Kirchstr. 98",
    "sg:city":"Papenburg",
    "sg:phone":"+49 4961/3026",
    "sg:postcode":"26871",
    "sg:province":"Niedersachsen",
    "wof:name":"C. De Wall Gmbh",
    "wof:placetype":"venue"
},
  "geometry": {"coordinates":[7.401263,53.086044],"type":"Point"}
}