{
  "type": "Feature",
  "properties": {
    "iso:country":"DE",
    "sg:address":"Hauptstr. 19",
    "sg:city":"Bruttig-Fankel",
    "sg:phone":"+49 2671/7138",
    "sg:postcode":"56814",
    "sg:province":"Rheinland-Pfalz",
    "wof:name":"Hotel Petrus Mosellanus",
    "wof:placetype":"venue"
},
  "geometry": {"coordinates":[7.2341661453,50.1329727173],"type":"Point"}
}