{
  "type": "Feature",
  "properties": {
    "iso:country":"DE",
    "sg:address":"Hausener Obergasse 49",
    "sg:city":"Frankfurt",
    "sg:phone":"+49 69/785680",
    "sg:postcode":"60488",
    "sg:province":"Hessen",
    "wof:name":"Restaurant Odysseus",
    "wof:placetype":"venue"
},
  "geometry": {"coordinates":[8.6252269745,50.131565094],"type":"Point"}
}