{
  "type": "Feature",
  "properties": {
    "iso:country":"DE",
    "sg:address":"Adenauerallee 45-49",
    "sg:city":"Bornheim",
    "sg:postcode":"53332",
    "sg:province":"Nordrhein-Westfalen",
    "wof:name":"Imagineon Ohg",
    "wof:placetype":"venue"
},
  "geometry": {"coordinates":[7.0039000511,50.7577667236],"type":"Point"}
}