{
  "type": "Feature",
  "properties": {
    "iso:country":"DE",
    "sg:address":"Joachimstr. 14",
    "sg:city":"Berlin",
    "sg:postcode":"10119",
    "sg:province":"Berlin",
    "wof:name":"Reflex Kommunikation Events Und Spezialreisen Gmbh",
    "wof:placetype":"venue"
},
  "geometry": {"coordinates":[13.4000530243,52.528339386],"type":"Point"}
}