{
  "type": "Feature",
  "properties": {
    "iso:country":"DE",
    "sg:address":"Carl-Lensch-Str. 5",
    "sg:city":"Borsfleth",
    "sg:phone":"+49 4824/762",
    "sg:postcode":"25376",
    "sg:province":"Schleswig-Holstein",
    "wof:name":"Ev. Pfarramt Borsfleth",
    "wof:placetype":"venue"
},
  "geometry": {"coordinates":[9.4299812317,53.82654953],"type":"Point"}
}