{
  "type": "Feature",
  "properties": {
    "iso:country":"DE",
    "sg:address":"H\u00f6henstr. 82",
    "sg:city":"Wendlingen",
    "sg:phone":"+49 7024/94160",
    "sg:postcode":"73240",
    "sg:province":"Baden-W\u00fcrttemberg",
    "wof:name":"Bruno Gro\u00dfmann Heiz\u00f6lhandlung",
    "wof:placetype":"venue"
},
  "geometry": {"coordinates":[9.3778438568,48.6654930115],"type":"Point"}
}