{
  "type": "Feature",
  "properties": {
    "iso:country":"DE",
    "sg:address":"Danielsberg 3",
    "sg:city":"Sch\u00f6necken",
    "sg:phone":"+49 6553/2495",
    "sg:postcode":"54614",
    "sg:province":"Rheinland-Pfalz",
    "wof:name":"D. Reicherts",
    "wof:placetype":"venue"
},
  "geometry": {"coordinates":[6.4671821594,50.152305603],"type":"Point"}
}