{
  "type": "Feature",
  "properties": {
    "iso:country":"DE",
    "sg:address":"Beethovenstr. 15",
    "sg:city":"Dornhan",
    "sg:phone":"+49 7455/1402",
    "sg:postcode":"72175",
    "sg:province":"Baden-W\u00fcrttemberg",
    "wof:name":"Hans Schwenk",
    "wof:placetype":"venue"
},
  "geometry": {"coordinates":[8.503928,48.347797],"type":"Point"}
}