{
  "type": "Feature",
  "properties": {
    "iso:country":"DE",
    "sg:address":"Im Sch\u00f6nortsfelde 8",
    "sg:city":"Loxstedt",
    "sg:phone":"+49 4744/2898",
    "sg:postcode":"27612",
    "sg:province":"Niedersachsen",
    "wof:name":"Ute Runge",
    "wof:placetype":"venue"
},
  "geometry": {"coordinates":[8.65276,53.466789],"type":"Point"}
}