{
  "type": "Feature",
  "properties": {
    "iso:country":"DE",
    "sg:address":"Moselstr. 1",
    "sg:city":"Wilhelmshaven",
    "sg:phone":"+49 4421/998203",
    "sg:postcode":"26382",
    "sg:province":"Niedersachsen",
    "wof:name":"Beteiligungsgesellschaft Der Stadt Wilhelmshaven Mbh",
    "wof:placetype":"venue"
},
  "geometry": {"coordinates":[8.1326637268,53.5144195557],"type":"Point"}
}