{
  "type": "Feature",
  "properties": {
    "iso:country":"DE",
    "sg:address":"Vor der H\u00f6he 2",
    "sg:city":"Messel",
    "sg:phone":"+49 6159/208",
    "sg:postcode":"64409",
    "sg:province":"Hessen",
    "wof:name":"Georg Berz Elektroinstallation",
    "wof:placetype":"venue"
},
  "geometry": {"coordinates":[8.738315,49.934433],"type":"Point"}
}