{
  "type": "Feature",
  "properties": {
    "iso:country":"DE",
    "sg:address":"K\u00f6nigsberger Str. 21",
    "sg:city":"Wennigsen",
    "sg:phone":"+49 5109/6672",
    "sg:postcode":"30974",
    "sg:province":"Niedersachsen",
    "wof:name":"Elke Weiss",
    "wof:placetype":"venue"
},
  "geometry": {"coordinates":[9.621391,52.258415],"type":"Point"}
}