{
  "type": "Feature",
  "properties": {
    "iso:country":"DE",
    "sg:address":"Ohrdrufer Str. 47",
    "sg:city":"Crawinkel",
    "sg:phone":"+49 3624/314926",
    "sg:postcode":"99330",
    "sg:province":"Th\u00fcringen",
    "wof:name":"Goldene Aue",
    "wof:placetype":"venue"
},
  "geometry": {"coordinates":[10.7838888168,50.7810897827],"type":"Point"}
}