{
  "type": "Feature",
  "properties": {
    "iso:country":"DE",
    "sg:address":"Bismarckstr. 4",
    "sg:city":"Memmingen",
    "sg:phone":"+49 8331/63048",
    "sg:postcode":"87700",
    "sg:province":"Bayern",
    "wof:name":"Vertrauens\u00e4rztlicher-dienst Der Lva Schwaben",
    "wof:placetype":"venue"
},
  "geometry": {"coordinates":[10.1728897095,47.9839477539],"type":"Point"}
}