{
  "type": "Feature",
  "properties": {
    "iso:country":"DE",
    "sg:address":"Kieler Str. 21",
    "sg:city":"Eckernf\u00f6rde",
    "sg:phone":"+49 4351/2673",
    "sg:postcode":"24340",
    "sg:province":"Schleswig-Holstein",
    "wof:name":"Vo\u00df",
    "wof:placetype":"venue"
},
  "geometry": {"coordinates":[9.8371553421,54.4714698792],"type":"Point"}
}