{
  "type": "Feature",
  "properties": {
    "iso:country":"DE",
    "sg:address":"Parlerstr. 9",
    "sg:city":"Schw\u00e4bisch Gm\u00fcnd",
    "sg:postcode":"73525",
    "sg:province":"Baden-W\u00fcrttemberg",
    "wof:name":"Gwf Mbh",
    "wof:placetype":"venue"
},
  "geometry": {"coordinates":[9.7936153412,48.7976036072],"type":"Point"}
}