{
  "type": "Feature",
  "properties": {
    "iso:country":"DE",
    "sg:address":"Von-Buttel-Str. 10",
    "sg:city":"Wangerland",
    "sg:postcode":"26434",
    "sg:province":"Niedersachsen",
    "wof:name":"Ghe Gewerbe- Und Hotelprojekt Entwicklungs Gmbh",
    "wof:placetype":"venue"
},
  "geometry": {"coordinates":[8.0213747025,53.6335754395],"type":"Point"}
}