{
  "type": "Feature",
  "properties": {
    "iso:country":"DE",
    "sg:address":"Mannesmannufer 2",
    "sg:city":"D\u00fcsseldorf",
    "sg:phone":"+49 211/8200",
    "sg:postcode":"40213",
    "sg:province":"Nordrhein-Westfalen",
    "wof:name":"Mannesmann Ag & Co. Ohg",
    "wof:placetype":"venue"
},
  "geometry": {"coordinates":[6.767758,51.220905],"type":"Point"}
}