{
  "type": "Feature",
  "properties": {
    "iso:country":"DE",
    "sg:address":"Obermarkt 1",
    "sg:city":"Waldheim",
    "sg:phone":"+49 34327/53223",
    "sg:postcode":"04736",
    "sg:province":"Sachsen",
    "wof:name":"Fessler Gernhardt Und Schuster Rechtsanw\u00e4lte",
    "wof:placetype":"venue"
},
  "geometry": {"coordinates":[13.0244903564,51.0731887817],"type":"Point"}
}