{
  "type": "Feature",
  "properties": {
    "iso:country":"DE",
    "sg:address":"L\u00fcttelbrachter Str. 102",
    "sg:city":"Br\u00fcggen",
    "sg:phone":"+49 2163/59233",
    "sg:postcode":"41379",
    "sg:province":"Nordrhein-Westfalen",
    "wof:name":"Landb\u00e4ckerei Stinges & S\u00f6hne Gmbh",
    "wof:placetype":"venue"
},
  "geometry": {"coordinates":[6.19761,51.261631],"type":"Point"}
}