{
  "type": "Feature",
  "properties": {
    "iso:country":"DE",
    "sg:address":"Dorfstr. 16 a",
    "sg:city":"G\u00fctergl\u00fcck",
    "sg:phone":"+49 39247/5074",
    "sg:postcode":"39264",
    "sg:province":"Sachsen-Anhalt",
    "wof:name":"Peter Schulze Rechtsanwalt",
    "wof:placetype":"venue"
},
  "geometry": {"coordinates":[11.9936571121,51.985534668],"type":"Point"}
}