{
  "type": "Feature",
  "properties": {
    "iso:country":"DE",
    "sg:address":"Burghauser Str. 4 a",
    "sg:city":"Alt\u00f6tting",
    "sg:postcode":"84503",
    "sg:province":"Bayern",
    "wof:name":"Immobilien Gmbh",
    "wof:placetype":"venue"
},
  "geometry": {"coordinates":[12.6778535843,48.2244644165],"type":"Point"}
}