{
  "type": "Feature",
  "properties": {
    "iso:country":"DE",
    "sg:address":"Teichh\u00fctter Weg",
    "sg:city":"Eisdorf",
    "sg:phone":"+49 5327/4575",
    "sg:postcode":"37534",
    "sg:province":"Niedersachsen",
    "wof:name":"Friedrich Br\u00fcnau",
    "wof:placetype":"venue"
},
  "geometry": {"coordinates":[10.1715698242,51.7788543701],"type":"Point"}
}