{
  "type": "Feature",
  "properties": {
    "iso:country":"DE",
    "sg:address":"Sprollstr. 93",
    "sg:city":"Stuttgart",
    "sg:phone":"+49 711/724779",
    "sg:postcode":"70597",
    "sg:province":"Baden-W\u00fcrttemberg",
    "wof:name":"J. Frljuzel \u00dcbersetzungsb\u00fcro",
    "wof:placetype":"venue"
},
  "geometry": {"coordinates":[9.182811,48.735107],"type":"Point"}
}