{
  "type": "Feature",
  "properties": {
    "iso:country":"DE",
    "sg:address":"Auf der Hard 9",
    "sg:city":"Grasellenbach",
    "sg:phone":"+49 6253/1466",
    "sg:postcode":"64689",
    "sg:province":"Hessen",
    "wof:name":"C. Rehse De Jesus \u00dcbersetzer Bd\u00dc",
    "wof:placetype":"venue"
},
  "geometry": {"coordinates":[8.835594,49.639053],"type":"Point"}
}