{
  "type": "Feature",
  "properties": {
    "iso:country":"DE",
    "sg:address":"Steeler Str. 174",
    "sg:city":"Essen",
    "sg:phone":"+49 201/898403",
    "sg:postcode":"45138",
    "sg:province":"Nordrhein-Westfalen",
    "wof:name":"Thomas Becker",
    "wof:placetype":"venue"
},
  "geometry": {"coordinates":[7.0292849541,51.4512557983],"type":"Point"}
}