{
  "type": "Feature",
  "properties": {
    "iso:country":"DE",
    "sg:address":"Unterdorf 17",
    "sg:city":"Adelberg",
    "sg:phone":"+49 7166/5754",
    "sg:postcode":"73099",
    "sg:province":"Baden-W\u00fcrttemberg",
    "wof:name":"Max Langer Architekt",
    "wof:placetype":"venue"
},
  "geometry": {"coordinates":[9.603664,48.764545],"type":"Point"}
}