{
  "type": "Feature",
  "properties": {
    "iso:country":"DE",
    "sg:address":"Tarvisstr. 2",
    "sg:city":"Bamberg",
    "sg:phone":"+49 951/68724",
    "sg:postcode":"96049",
    "sg:province":"Bayern",
    "wof:name":"Michael T\u00e4uber",
    "wof:placetype":"venue"
},
  "geometry": {"coordinates":[10.8582401276,49.9044036865],"type":"Point"}
}