{
  "type": "Feature",
  "properties": {
    "iso:country":"DE",
    "sg:address":"Kalterweg 71",
    "sg:city":"Stadtlohn",
    "sg:phone":"+49 2563/93540",
    "sg:postcode":"48703",
    "sg:province":"Nordrhein-Westfalen",
    "wof:name":"Hollweg Verwaltungs Gmbh",
    "wof:placetype":"venue"
},
  "geometry": {"coordinates":[6.9303622246,51.9969291687],"type":"Point"}
}