{
  "type": "Feature",
  "properties": {
    "iso:country":"DE",
    "sg:address":"Seehofstr. 32",
    "sg:city":"Memmelsdorf",
    "sg:phone":"+49 951/41456",
    "sg:postcode":"96117",
    "sg:province":"Bayern",
    "wof:name":"Reinhold Albert",
    "wof:placetype":"venue"
},
  "geometry": {"coordinates":[10.960657,49.926144],"type":"Point"}
}