{
  "type": "Feature",
  "properties": {
    "iso:country":"DE",
    "sg:address":"Lindenstr. 2",
    "sg:city":"Ludwigsburg",
    "sg:phone":"+49 7141/905555",
    "sg:postcode":"71634",
    "sg:province":"Baden-W\u00fcrttemberg",
    "wof:name":"Arte Moda",
    "wof:placetype":"venue"
},
  "geometry": {"coordinates":[9.1910133362,48.8987884521],"type":"Point"}
}