{
  "type": "Feature",
  "properties": {
    "iso:country":"DE",
    "sg:address":"Waldweg 6",
    "sg:city":"Niepars",
    "sg:phone":"+49 38321/60361",
    "sg:postcode":"18442",
    "sg:province":"Mecklenburg-Vorpommern",
    "wof:name":"Maschinen Handels- Und Service Gmbh",
    "wof:placetype":"venue"
},
  "geometry": {"coordinates":[12.926642,54.298397],"type":"Point"}
}