{
  "type": "Feature",
  "properties": {
    "iso:country":"DE",
    "sg:address":"Zur Schweiz 32",
    "sg:city":"Strohn",
    "sg:phone":"+49 6573/1250",
    "sg:postcode":"54558",
    "sg:province":"Rheinland-Pfalz",
    "wof:name":"P. Wagner Rechtsanwalt",
    "wof:placetype":"venue"
},
  "geometry": {"coordinates":[6.928044796,50.1074447632],"type":"Point"}
}