{
  "type": "Feature",
  "properties": {
    "iso:country":"DE",
    "sg:address":"Altenaer Str. 258",
    "sg:city":"L\u00fcdenscheid",
    "sg:phone":"+49 2351/997880",
    "sg:postcode":"58513",
    "sg:province":"Nordrhein-Westfalen",
    "wof:name":"Ernst Butz Gmbh",
    "wof:placetype":"venue"
},
  "geometry": {"coordinates":[7.6390919685,51.2544136047],"type":"Point"}
}