{
  "type": "Feature",
  "properties": {
    "iso:country":"DE",
    "sg:address":"Pf\u00e4lzerstr. 11",
    "sg:city":"Regenstauf",
    "sg:phone":"+49 9402/93180",
    "sg:postcode":"93128",
    "sg:province":"Bayern",
    "wof:name":"Schmalzl Bau Gmbh",
    "wof:placetype":"venue"
},
  "geometry": {"coordinates":[12.12672,49.114269],"type":"Point"}
}