{
  "type": "Feature",
  "properties": {
    "iso:country":"DE",
    "sg:address":"Kesselstr. 15",
    "sg:city":"R\u00f6blingen am See",
    "sg:phone":"+49 34774/20655",
    "sg:postcode":"06317",
    "sg:province":"Sachsen-Anhalt",
    "wof:name":"H. G. Luge",
    "wof:placetype":"venue"
},
  "geometry": {"coordinates":[11.665893,51.466331],"type":"Point"}
}