{
  "type": "Feature",
  "properties": {
    "iso:country":"DE",
    "sg:address":"Wentelstr. 4",
    "sg:city":"Sigmaringen",
    "sg:phone":"+49 7571/62313",
    "sg:postcode":"72488",
    "sg:province":"Baden-W\u00fcrttemberg",
    "wof:name":"P. Zeller",
    "wof:placetype":"venue"
},
  "geometry": {"coordinates":[9.21731,48.093037],"type":"Point"}
}