{
  "type": "Feature",
  "properties": {
    "iso:country":"DE",
    "sg:address":"Carl-Zeiss-Str. 11",
    "sg:city":"Offenburg",
    "sg:phone":"+49 781/969273",
    "sg:postcode":"77656",
    "sg:province":"Baden-W\u00fcrttemberg",
    "wof:name":"G\u00f6tz Und Moriz",
    "wof:placetype":"venue"
},
  "geometry": {"coordinates":[7.9286370277,48.4372596741],"type":"Point"}
}