{
  "type": "Feature",
  "properties": {
    "iso:country":"DE",
    "sg:address":"Am Wingert 16",
    "sg:city":"Langg\u00f6ns",
    "sg:phone":"+49 6403/5081",
    "sg:postcode":"35428",
    "sg:province":"Hessen",
    "wof:name":"Wolff & Meier Gesch\u00e4ftsf\u00fchrungs Gmbh",
    "wof:placetype":"venue"
},
  "geometry": {"coordinates":[8.6629962921,50.4931182861],"type":"Point"}
}