{
  "type": "Feature",
  "properties": {
    "iso:country":"DE",
    "sg:address":"R\u00f6tebuckweg 60",
    "sg:city":"Freiburg",
    "sg:postcode":"79104",
    "sg:province":"Baden-W\u00fcrttemberg",
    "wof:name":"Picco Bello Sortier- Dienst E. K.",
    "wof:placetype":"venue"
},
  "geometry": {"coordinates":[7.863911,48.017441],"type":"Point"}
}