{
  "type": "Feature",
  "properties": {
    "iso:country":"DE",
    "sg:address":"Bahnhofstr. 13",
    "sg:city":"Bad Sobernheim",
    "sg:phone":"+49 6751/1240",
    "sg:postcode":"55566",
    "sg:province":"Rheinland-Pfalz",
    "wof:name":"B. Frischauf",
    "wof:placetype":"venue"
},
  "geometry": {"coordinates":[7.6486721039,49.7839126587],"type":"Point"}
}