{
  "type": "Feature",
  "properties": {
    "iso:country":"DE",
    "sg:address":"Daimlerstr. 21",
    "sg:city":"Uhingen",
    "sg:phone":"+49 7163/33139",
    "sg:postcode":"73066",
    "sg:province":"Baden-W\u00fcrttemberg",
    "wof:name":"Ev. Pfarramt Iii",
    "wof:placetype":"venue"
},
  "geometry": {"coordinates":[9.5840654373,48.7123260498],"type":"Point"}
}