{
  "type": "Feature",
  "properties": {
    "iso:country":"DE",
    "sg:address":"Am Deich 19",
    "sg:city":"St.Peter-Ording",
    "sg:phone":"+49 2173/979944",
    "sg:postcode":"25826",
    "sg:province":"Schleswig-Holstein",
    "wof:name":"M. U. H.-d. Lemburg",
    "wof:placetype":"venue"
},
  "geometry": {"coordinates":[8.60709095,54.3303833008],"type":"Point"}
}