{
  "type": "Feature",
  "properties": {
    "iso:country":"DE",
    "sg:address":"Dr.-Gustav-Heinemann-Str. 1",
    "sg:city":"Schwabach",
    "sg:phone":"+49 9122/99210",
    "sg:postcode":"91126",
    "sg:province":"Bayern",
    "wof:name":"Rms-online Gmbh",
    "wof:placetype":"venue"
},
  "geometry": {"coordinates":[11.0269918442,49.3212966919],"type":"Point"}
}