{
  "type": "Feature",
  "properties": {
    "iso:country":"DE",
    "sg:address":"Hauptstr. 28",
    "sg:city":"Roth",
    "sg:phone":"+49 9171/96850",
    "sg:postcode":"91154",
    "sg:province":"Bayern",
    "wof:name":"J\u00fcrgen Fiegl Steuerberater",
    "wof:placetype":"venue"
},
  "geometry": {"coordinates":[11.091632843,49.2473869324],"type":"Point"}
}