{
  "type": "Feature",
  "properties": {
    "iso:country":"DE",
    "sg:address":"Schmittgasse 11",
    "sg:city":"M\u00f6rlenbach",
    "sg:phone":"+49 6209/3921",
    "sg:postcode":"69509",
    "sg:province":"Hessen",
    "wof:name":"Hans Taufertsh\u00f6fer Gmbh",
    "wof:placetype":"venue"
},
  "geometry": {"coordinates":[8.737455368,49.6005821228],"type":"Point"}
}