{
  "type": "Feature",
  "properties": {
    "iso:country":"DE",
    "sg:address":"Siedlungsstr. 20",
    "sg:city":"Dannenwalde",
    "sg:phone":"+49 33975/50266",
    "sg:postcode":"16866",
    "sg:province":"Brandenburg",
    "wof:name":"Arndt Bauunternehmen",
    "wof:placetype":"venue"
},
  "geometry": {"coordinates":[12.235768,53.028236],"type":"Point"}
}