{
  "type": "Feature",
  "properties": {
    "iso:country":"DE",
    "sg:address":"Kachelstr. 43",
    "sg:city":"Tauberbischofsheim",
    "sg:phone":"+49 9341/2571",
    "sg:postcode":"97941",
    "sg:province":"Baden-W\u00fcrttemberg",
    "wof:name":"Karl Stilla",
    "wof:placetype":"venue"
},
  "geometry": {"coordinates":[9.6698236465,49.6260108948],"type":"Point"}
}