{
  "type": "Feature",
  "properties": {
    "iso:country":"DE",
    "sg:address":"Gartenstr. 1",
    "sg:city":"Zwickau",
    "sg:phone":"+49 375/2047650",
    "sg:postcode":"08056",
    "sg:province":"Sachsen",
    "wof:name":"Drei Schw\u00e4ne Inh. Yannick Demange",
    "wof:placetype":"venue"
},
  "geometry": {"coordinates":[12.4507350922,50.6665916443],"type":"Point"}
}