{
  "type": "Feature",
  "properties": {
    "iso:country":"DE",
    "sg:address":"Br\u00fcckenstr. 94",
    "sg:city":"L\u00f6hne",
    "sg:phone":"+49 5731/74070",
    "sg:postcode":"32584",
    "sg:province":"Nordrhein-Westfalen",
    "wof:name":"Paul Henke Gmbh & Co. Kg",
    "wof:placetype":"venue"
},
  "geometry": {"coordinates":[8.7595682144,52.213924408],"type":"Point"}
}