{
  "type": "Feature",
  "properties": {
    "iso:country":"DE",
    "sg:address":"Maiergasse 15",
    "sg:city":"Aalen",
    "sg:phone":"+49 7361/91230",
    "sg:postcode":"73433",
    "sg:province":"Baden-W\u00fcrttemberg",
    "wof:name":"Nowinta Investmentservice Gmbh",
    "wof:placetype":"venue"
},
  "geometry": {"coordinates":[10.102052,48.864861],"type":"Point"}
}