{
  "type": "Feature",
  "properties": {
    "iso:country":"DE",
    "sg:address":"Junker-J\u00f6rg-Str. 24",
    "sg:city":"Berlin",
    "sg:phone":"+49 30/5084563",
    "sg:postcode":"10318",
    "sg:province":"Berlin",
    "wof:name":"Peter Kanwisch",
    "wof:placetype":"venue"
},
  "geometry": {"coordinates":[13.522608,52.488167],"type":"Point"}
}