{
  "type": "Feature",
  "properties": {
    "iso:country":"DE",
    "sg:address":"Illach 1",
    "sg:city":"Steingaden",
    "sg:phone":"+49 8862/516",
    "sg:postcode":"86989",
    "sg:province":"Bayern",
    "wof:name":"Hans Echtler",
    "wof:placetype":"venue"
},
  "geometry": {"coordinates":[10.833647,47.711514],"type":"Point"}
}