{
  "type": "Feature",
  "properties": {
    "iso:country":"DE",
    "sg:address":"Bredenhop 14",
    "sg:city":"H\u00fcllhorst",
    "sg:phone":"+49 4957/4493000",
    "sg:postcode":"32609",
    "sg:province":"Nordrhein-Westfalen",
    "wof:name":"Conal Metallbaugmbh",
    "wof:placetype":"venue"
},
  "geometry": {"coordinates":[8.708516,52.264847],"type":"Point"}
}