{
  "type": "Feature",
  "properties": {
    "iso:country":"DE",
    "sg:address":"Tondernstr. 42",
    "sg:city":"K\u00f6ln",
    "sg:phone":"+49 221/5503206",
    "sg:postcode":"50825",
    "sg:province":"Nordrhein-Westfalen",
    "wof:name":"Hawle Armaturen Gmbh",
    "wof:placetype":"venue"
},
  "geometry": {"coordinates":[6.91727,50.963085],"type":"Point"}
}