{
  "type": "Feature",
  "properties": {
    "iso:country":"DE",
    "sg:address":"Binger Str. 50b",
    "sg:city":"Ingelheim",
    "sg:phone":"+49 6132/73447",
    "sg:postcode":"55218",
    "sg:province":"Rheinland-Pfalz",
    "wof:name":"A. Bayat",
    "wof:placetype":"venue"
},
  "geometry": {"coordinates":[8.0582799911,49.9750518799],"type":"Point"}
}