{
  "type": "Feature",
  "properties": {
    "iso:country":"DE",
    "sg:address":"Friedlandstr. 9",
    "sg:city":"Bonn",
    "sg:phone":"+49 228/555820",
    "sg:postcode":"53117",
    "sg:province":"Nordrhein-Westfalen",
    "wof:name":"Buschdorfer-apotheke",
    "wof:placetype":"venue"
},
  "geometry": {"coordinates":[7.050574,50.760433],"type":"Point"}
}