{
  "type": "Feature",
  "properties": {
    "iso:country":"DE",
    "sg:address":"Alter Postweg 33",
    "sg:city":"Hamburg",
    "sg:phone":"+49 40/7656016",
    "sg:postcode":"21075",
    "sg:province":"Hamburg",
    "wof:name":"Y. Abul",
    "wof:placetype":"venue"
},
  "geometry": {"coordinates":[9.9639549255,53.4647979736],"type":"Point"}
}