{
  "type": "Feature",
  "properties": {
    "iso:country":"DE",
    "sg:address":"Markt 41",
    "sg:city":"Schm\u00f6lln",
    "sg:phone":"+49 34491/63828",
    "sg:postcode":"04626",
    "sg:province":"Th\u00fcringen",
    "wof:name":"Yvette Kruschwitz Rechtsanw\u00e4ltin",
    "wof:placetype":"venue"
},
  "geometry": {"coordinates":[12.3535995483,50.8957481384],"type":"Point"}
}