{
  "type": "Feature",
  "properties": {
    "iso:country":"DE",
    "sg:address":"Kraicherhohl",
    "sg:city":"Limburg/Lahn",
    "sg:phone":"+49 6431/932600",
    "sg:postcode":"65549",
    "sg:province":"Hessen",
    "wof:name":"Ds-verpackung Gmbh",
    "wof:placetype":"venue"
},
  "geometry": {"coordinates":[8.0618114471,50.3961868286],"type":"Point"}
}