{
  "type": "Feature",
  "properties": {
    "iso:country":"DE",
    "sg:address":"Trebbiner Str. 16",
    "sg:city":"Mahlow",
    "sg:phone":"+49 3379/372676",
    "sg:postcode":"15831",
    "sg:province":"Brandenburg",
    "wof:name":"Horst Wagenknecht",
    "wof:placetype":"venue"
},
  "geometry": {"coordinates":[13.410782,52.360901],"type":"Point"}
}