{
  "type": "Feature",
  "properties": {
    "iso:country":"DE",
    "sg:address":"An der K\u00e4lschbach 3",
    "sg:city":"Gorxheimertal",
    "sg:phone":"+49 6201/21650",
    "sg:postcode":"69517",
    "sg:province":"Hessen",
    "wof:name":"Franz G\u00f6lz Architekt",
    "wof:placetype":"venue"
},
  "geometry": {"coordinates":[8.711444,49.539261],"type":"Point"}
}