{
  "type": "Feature",
  "properties": {
    "iso:country":"DE",
    "sg:address":"Friedrichstr. 35",
    "sg:city":"Tornesch",
    "sg:phone":"+49 4122/53242",
    "sg:postcode":"25436",
    "sg:province":"Schleswig-Holstein",
    "wof:name":"Erhard Wasmann Rechtsanwalt Und Notar",
    "wof:placetype":"venue"
},
  "geometry": {"coordinates":[9.7092695236,53.6999549866],"type":"Point"}
}