{
  "type": "Feature",
  "properties": {
    "iso:country":"DE",
    "sg:address":"Chausseestr. 35",
    "sg:city":"K\u00f6nigs Wusterhausen",
    "sg:phone":"+49 3375/292797",
    "sg:postcode":"15711",
    "sg:province":"Brandenburg",
    "wof:name":"Rolf Seidel Rechtsanwalt",
    "wof:placetype":"venue"
},
  "geometry": {"coordinates":[13.594165802,52.2949104309],"type":"Point"}
}