{
  "type": "Feature",
  "properties": {
    "iso:country":"DE",
    "sg:address":"Neuenlander Str. 9",
    "sg:city":"Ganderkesee",
    "sg:phone":"+49 4223/489",
    "sg:postcode":"27777",
    "sg:province":"Niedersachsen",
    "wof:name":"Wilhelm Lange",
    "wof:placetype":"venue"
},
  "geometry": {"coordinates":[8.546288,53.116711],"type":"Point"}
}