{
  "type": "Feature",
  "properties": {
    "iso:country":"DE",
    "sg:address":"Alzeyer Str. 317",
    "sg:city":"Worms",
    "sg:phone":"+49 6241/75207",
    "sg:postcode":"67549",
    "sg:province":"Rheinland-Pfalz",
    "wof:name":"Johann Biebesheimer",
    "wof:placetype":"venue"
},
  "geometry": {"coordinates":[8.3178663254,49.6320800781],"type":"Point"}
}