{
  "type": "Feature",
  "properties": {
    "iso:country":"DE",
    "sg:address":"Schwetzinger Str. 28",
    "sg:city":"Mannheim",
    "sg:phone":"+49 621/444548",
    "sg:postcode":"68165",
    "sg:province":"Baden-W\u00fcrttemberg",
    "wof:name":"Iepg Institut F\u00fcr Med. Ethik Grundlagen U. Methoden Der",
    "wof:placetype":"venue"
},
  "geometry": {"coordinates":[8.4744386673,49.4807319641],"type":"Point"}
}