{
  "type": "Feature",
  "properties": {
    "iso:country":"DE",
    "sg:address":"Mainzer Str 77",
    "sg:city":"Kaiserslautern",
    "sg:phone":"+49 631/366130",
    "sg:postcode":"67657",
    "sg:province":"Rheinland-Pfalz",
    "wof:name":"Matricks Marketing Gmbh",
    "wof:placetype":"venue"
},
  "geometry": {"coordinates":[7.785924,49.452103],"type":"Point"}
}