{
  "type": "Feature",
  "properties": {
    "iso:country":"DE",
    "sg:address":"Weststr. 20",
    "sg:city":"Aachen",
    "sg:phone":"+49 241/870777",
    "sg:postcode":"52074",
    "sg:province":"Nordrhein-Westfalen",
    "wof:name":"Selection Fitness Center Vi Gmbh",
    "wof:placetype":"venue"
},
  "geometry": {"coordinates":[6.0620422363,50.7720680237],"type":"Point"}
}