{
  "type": "Feature",
  "properties": {
    "iso:country":"DE",
    "sg:address":"Bergstr. 113",
    "sg:city":"Dortmund",
    "sg:phone":"+49 231/853456",
    "sg:postcode":"44339",
    "sg:province":"Nordrhein-Westfalen",
    "wof:name":"Friedhelm Wolter",
    "wof:placetype":"venue"
},
  "geometry": {"coordinates":[7.449828,51.553036],"type":"Point"}
}