{
  "type": "Feature",
  "properties": {
    "iso:country":"DE",
    "sg:address":"Ringstr. 50",
    "sg:city":"Espelkamp",
    "sg:phone":"+49 5743/2482",
    "sg:postcode":"32339",
    "sg:province":"Nordrhein-Westfalen",
    "wof:name":"Buchholz Fast Food Betriebs Gmbh",
    "wof:placetype":"venue"
},
  "geometry": {"coordinates":[8.5623340607,52.3510246277],"type":"Point"}
}