{
  "type": "Feature",
  "properties": {
    "iso:country":"DE",
    "sg:address":"Kaiserstuhlstr. 2",
    "sg:city":"Herbolzheim",
    "sg:phone":"+49 4976/4391530",
    "sg:postcode":"79336",
    "sg:province":"Baden-W\u00fcrttemberg",
    "wof:name":"Huser Maschinenbau Gmbh",
    "wof:placetype":"venue"
},
  "geometry": {"coordinates":[7.776297,48.217747],"type":"Point"}
}