{
  "type": "Feature",
  "properties": {
    "iso:country":"DE",
    "sg:address":"Hallesche Str. 2",
    "sg:city":"Eilenburg",
    "sg:phone":"+49 3423/602661",
    "sg:postcode":"04838",
    "sg:province":"Sachsen",
    "wof:name":"Horst Stichel",
    "wof:placetype":"venue"
},
  "geometry": {"coordinates":[12.6191911697,51.4597892761],"type":"Point"}
}