{
  "type": "Feature",
  "properties": {
    "iso:country":"DE",
    "sg:address":"Zum Ehrw\u00e4ldchen 6",
    "sg:city":"Rehlingen-Siersburg",
    "sg:phone":"+49 6833/1277",
    "sg:postcode":"66780",
    "sg:province":"Saarland",
    "wof:name":"Jannys Treff",
    "wof:placetype":"venue"
},
  "geometry": {"coordinates":[6.6187877655,49.3519630432],"type":"Point"}
}