{
  "type": "Feature",
  "properties": {
    "iso:country":"DE",
    "sg:address":"L\u00e4rchenstr. 6",
    "sg:city":"Bad Urach",
    "sg:postcode":"72574",
    "sg:province":"Baden-W\u00fcrttemberg",
    "wof:name":"Astrans Gmbh",
    "wof:placetype":"venue"
},
  "geometry": {"coordinates":[9.4065666199,48.4624862671],"type":"Point"}
}