{
  "type": "Feature",
  "properties": {
    "iso:country":"DE",
    "sg:address":"Faurndauer Stra\u00dfe 64",
    "sg:city":"Goeppingen",
    "sg:phone":"+49 7161/683758",
    "sg:postcode":"73035",
    "sg:province":"Baden-W\u00fcrttemberg",
    "wof:name":"Naturfreunde Ortsgruppe G\u00f6ppingen",
    "wof:placetype":"venue"
},
  "geometry": {"coordinates":[9.6379585266,48.7037391663],"type":"Point"}
}