{
  "type": "Feature",
  "properties": {
    "iso:country":"DE",
    "sg:address":"Jakobistr. 31",
    "sg:city":"Hannover",
    "sg:phone":"+49 511/3940530",
    "sg:postcode":"30163",
    "sg:province":"Niedersachsen",
    "wof:name":"R. Kr\u00f6sing",
    "wof:placetype":"venue"
},
  "geometry": {"coordinates":[9.744201,52.390259],"type":"Point"}
}