{
  "type": "Feature",
  "properties": {
    "iso:country":"DE",
    "sg:address":"Dorflinde 9",
    "sg:city":"Windeck",
    "sg:phone":"+49 2295/902404",
    "sg:postcode":"51570",
    "sg:province":"Nordrhein-Westfalen",
    "wof:name":"Reno-bauelemente Service Gmbh",
    "wof:placetype":"venue"
},
  "geometry": {"coordinates":[7.5038299561,50.8223304749],"type":"Point"}
}