{
  "type": "Feature",
  "properties": {
    "iso:country":"DE",
    "sg:address":"Eichsfeldstr. 34",
    "sg:city":"Oberhausen",
    "sg:phone":"+49 208/673678",
    "sg:postcode":"46147",
    "sg:province":"Nordrhein-Westfalen",
    "wof:name":"Manfred Franzkowiak",
    "wof:placetype":"venue"
},
  "geometry": {"coordinates":[6.825671,51.547989],"type":"Point"}
}