{
  "type": "Feature",
  "properties": {
    "iso:country":"DE",
    "sg:address":"Hauptstr. 14",
    "sg:city":"Postbauer-Heng",
    "sg:phone":"+49 9188/748",
    "sg:postcode":"92353",
    "sg:province":"Bayern",
    "wof:name":"K. H. Hentschel",
    "wof:placetype":"venue"
},
  "geometry": {"coordinates":[11.3549871445,49.3124084473],"type":"Point"}
}