{
  "type": "Feature",
  "properties": {
    "iso:country":"DE",
    "sg:address":"Lange Str. 23",
    "sg:city":"Billerbeck",
    "sg:phone":"+49 2543/1631",
    "sg:postcode":"48727",
    "sg:province":"Nordrhein-Westfalen",
    "wof:name":"A. Frieling Haus- Und K\u00fcchenger\u00e4te",
    "wof:placetype":"venue"
},
  "geometry": {"coordinates":[7.3752760887,52.0029373169],"type":"Point"}
}