{
  "type": "Feature",
  "properties": {
    "iso:country":"DE",
    "sg:address":"Unter dem Nu\u00dfbaum 18",
    "sg:city":"Wetzlar",
    "sg:phone":"+49 6441/76589",
    "sg:postcode":"35578",
    "sg:province":"Hessen",
    "wof:name":"Peter Hildebrand",
    "wof:placetype":"venue"
},
  "geometry": {"coordinates":[8.5352067947,50.5446052551],"type":"Point"}
}