{
  "type": "Feature",
  "properties": {
    "iso:country":"DE",
    "sg:address":"Dahlienweg 40",
    "sg:city":"Kirchen",
    "sg:phone":"+49 2741/61854",
    "sg:postcode":"57548",
    "sg:province":"Rheinland-Pfalz",
    "wof:name":"Inge Gebauer",
    "wof:placetype":"venue"
},
  "geometry": {"coordinates":[7.8989210129,50.8186836243],"type":"Point"}
}