{
  "type": "Feature",
  "properties": {
    "iso:country":"DE",
    "sg:address":"Feuerbacher Weg 16",
    "sg:city":"Hildesheim",
    "sg:phone":"+49 5121/41333",
    "sg:postcode":"31139",
    "sg:province":"Niedersachsen",
    "wof:name":"Dietmar Nitsche",
    "wof:placetype":"venue"
},
  "geometry": {"coordinates":[9.903015,52.116798],"type":"Point"}
}