{
  "type": "Feature",
  "properties": {
    "iso:country":"DE",
    "sg:address":"Lindenstr. 74",
    "sg:city":"Lohne",
    "sg:phone":"+49 4442/6655",
    "sg:postcode":"49393",
    "sg:province":"Niedersachsen",
    "wof:name":"Mampf",
    "wof:placetype":"venue"
},
  "geometry": {"coordinates":[8.2460622787,52.6698684692],"type":"Point"}
}