{
  "type": "Feature",
  "properties": {
    "iso:country":"DE",
    "sg:address":"Kastanienallee 35",
    "sg:city":"Hannover",
    "sg:phone":"+49 511/83810",
    "sg:postcode":"30519",
    "sg:province":"Niedersachsen",
    "wof:name":"I V I Immobilien-verwaltungs- Und Investitionsgesellschaft",
    "wof:placetype":"venue"
},
  "geometry": {"coordinates":[9.7681598663,52.3326721191],"type":"Point"}
}