{
  "type": "Feature",
  "properties": {
    "iso:country":"DE",
    "sg:address":"Kreuzstr. 10",
    "sg:city":"Eltville",
    "sg:phone":"+49 6123/62225",
    "sg:postcode":"65346",
    "sg:province":"Hessen",
    "wof:name":"Helmut Zwilling Architekt",
    "wof:placetype":"venue"
},
  "geometry": {"coordinates":[8.098035,50.021076],"type":"Point"}
}