{
  "type": "Feature",
  "properties": {
    "iso:country":"DE",
    "sg:address":"Ottobrunner Str. 13",
    "sg:city":"M\u00fcnchen",
    "sg:phone":"+49 89/6803400",
    "sg:postcode":"81737",
    "sg:province":"Bayern",
    "wof:name":"Hund & Katz Haustiernahrungm\u00dcnchen Gmbh",
    "wof:placetype":"venue"
},
  "geometry": {"coordinates":[11.617788,48.111877],"type":"Point"}
}