{
  "type": "Feature",
  "properties": {
    "iso:country":"DE",
    "sg:address":"Geschwister-Scholl-Str. 19",
    "sg:city":"Potsdam",
    "sg:phone":"+49 331/970493",
    "sg:postcode":"14471",
    "sg:province":"Brandenburg",
    "wof:name":"Peter Zehm Rechtsanwalt",
    "wof:placetype":"venue"
},
  "geometry": {"coordinates":[13.0332899094,52.3937606812],"type":"Point"}
}