{
  "type": "Feature",
  "properties": {
    "iso:country":"DE",
    "sg:address":"Platzweg 1",
    "sg:city":"Wipperf\u00fcrth",
    "sg:phone":"+49 2267/5339",
    "sg:postcode":"51688",
    "sg:province":"Nordrhein-Westfalen",
    "wof:name":"Kunibert Ackerschott",
    "wof:placetype":"venue"
},
  "geometry": {"coordinates":[7.416137,51.158279],"type":"Point"}
}