{
  "type": "Feature",
  "properties": {
    "iso:country":"DE",
    "sg:address":"Adelheidstr. 20-22",
    "sg:city":"Friedrichshafen",
    "sg:phone":"+49 4975/4192140",
    "sg:postcode":"88046",
    "sg:province":"Baden-W\u00fcrttemberg",
    "wof:name":"Ender Gmbh",
    "wof:placetype":"venue"
},
  "geometry": {"coordinates":[9.501205,47.6618],"type":"Point"}
}