{
  "type": "Feature",
  "properties": {
    "iso:country":"DE",
    "sg:address":"Grottenau 2",
    "sg:city":"Augsburg",
    "sg:phone":"+49 171 2382264",
    "sg:postcode":"86150",
    "sg:province":"Bayern",
    "wof:name":"Ralf Sch\u00f6nauer Rechtsanwalt",
    "wof:placetype":"venue"
},
  "geometry": {"coordinates":[10.8942146301,48.3700675964],"type":"Point"}
}