{
  "type": "Feature",
  "properties": {
    "iso:country":"DE",
    "sg:address":"H\u00f6hmannstr. 7",
    "sg:city":"Berlin",
    "sg:phone":"+49 4930/8265490",
    "sg:postcode":"14193",
    "sg:province":"Berlin",
    "wof:name":"Luchnik Bau Gmbh",
    "wof:placetype":"venue"
},
  "geometry": {"coordinates":[13.263997,52.481297],"type":"Point"}
}