{
  "type": "Feature",
  "properties": {
    "iso:country":"DE",
    "sg:address":"Gartenstr. 5",
    "sg:city":"Oberhonnefeld-Gierend",
    "sg:phone":"+49 2631/47677",
    "sg:postcode":"56587",
    "sg:province":"Rheinland-Pfalz",
    "wof:name":"Maschinenputztuchhandel Thomas Keuter",
    "wof:placetype":"venue"
},
  "geometry": {"coordinates":[7.517319,50.553162],"type":"Point"}
}