{
  "type": "Feature",
  "properties": {
    "iso:country":"DE",
    "sg:address":"Eibseestr. 65",
    "sg:city":"Grainau",
    "sg:phone":"+49 8821/81977",
    "sg:postcode":"82491",
    "sg:province":"Bayern",
    "wof:name":"Tennis Und Squashzentrum J. R\u00f6sner",
    "wof:placetype":"venue"
},
  "geometry": {"coordinates":[11.0056524277,47.4635429382],"type":"Point"}
}