{
  "type": "Feature",
  "properties": {
    "iso:country":"DE",
    "sg:address":"Von-Klug-Str. 17",
    "sg:city":"Heilbronn",
    "sg:phone":"+49 7066/7608",
    "sg:postcode":"74078",
    "sg:province":"Baden-W\u00fcrttemberg",
    "wof:name":"G\u00fcnter Knobloch",
    "wof:placetype":"venue"
},
  "geometry": {"coordinates":[9.1456193924,49.1915092468],"type":"Point"}
}