{
  "type": "Feature",
  "properties": {
    "iso:country":"DE",
    "sg:address":"Grahlstr. 39",
    "sg:city":"Perleberg",
    "sg:phone":"+49 3876/784310",
    "sg:postcode":"19348",
    "sg:province":"Brandenburg",
    "wof:name":"Jannasch Gmbh",
    "wof:placetype":"venue"
},
  "geometry": {"coordinates":[11.855366,53.075596],"type":"Point"}
}