{
  "type": "Feature",
  "properties": {
    "iso:country":"DE",
    "sg:address":"H\u00e4ndelplatz 4",
    "sg:city":"Schwabach",
    "sg:phone":"+49 9122/2320",
    "sg:postcode":"91126",
    "sg:province":"Bayern",
    "wof:name":"Gasthaus Spachm\u00fcller",
    "wof:placetype":"venue"
},
  "geometry": {"coordinates":[10.9938354492,49.3285903931],"type":"Point"}
}