{
  "type": "Feature",
  "properties": {
    "iso:country":"DE",
    "sg:address":"Weidendamm 12",
    "sg:city":"Rehburg-Loccum",
    "sg:postcode":"31547",
    "sg:province":"Niedersachsen",
    "wof:name":"Fr. Gosewisch Gmbh",
    "wof:placetype":"venue"
},
  "geometry": {"coordinates":[9.225034,52.465809],"type":"Point"}
}