{
  "type": "Feature",
  "properties": {
    "iso:country":"DE",
    "sg:address":"Elisabethstr. 31",
    "sg:city":"Berlin",
    "sg:phone":"+49 30/7699690",
    "sg:postcode":"12247",
    "sg:province":"Berlin",
    "wof:name":"Arndt & Partner",
    "wof:placetype":"venue"
},
  "geometry": {"coordinates":[13.3359107971,52.4324455261],"type":"Point"}
}