{
  "type": "Feature",
  "properties": {
    "iso:country":"DE",
    "sg:address":"Rh\u00f6nstr. 8",
    "sg:city":"Mainhausen",
    "sg:phone":"+49 6182/3870",
    "sg:postcode":"63533",
    "sg:province":"Hessen",
    "wof:name":"Baudekoration Gerfelder Gmbh",
    "wof:placetype":"venue"
},
  "geometry": {"coordinates":[9.00016,50.012337],"type":"Point"}
}