{
  "type": "Feature",
  "properties": {
    "iso:country":"DE",
    "sg:address":"Gailinger Str. 8",
    "sg:city":"Gottmadingen",
    "sg:phone":"+49 7734/99865",
    "sg:postcode":"78244",
    "sg:province":"Baden-W\u00fcrttemberg",
    "wof:name":"R. Heisrath",
    "wof:placetype":"venue"
},
  "geometry": {"coordinates":[8.753033638,47.7136268616],"type":"Point"}
}