{
  "type": "Feature",
  "properties": {
    "iso:country":"DE",
    "sg:address":"Im S\u00fcdfeld 13",
    "sg:city":"Bielefeld",
    "sg:phone":"+49 521/410207",
    "sg:postcode":"33647",
    "sg:province":"Nordrhein-Westfalen",
    "wof:name":"Walls Verwaltungs Gmbh",
    "wof:placetype":"venue"
},
  "geometry": {"coordinates":[8.5124511719,51.9771232605],"type":"Point"}
}