{
  "type": "Feature",
  "properties": {
    "iso:country":"DE",
    "sg:address":"Weidenpesch 77",
    "sg:city":"D\u00fcren",
    "sg:phone":"+49 2421/84527",
    "sg:postcode":"52353",
    "sg:province":"Nordrhein-Westfalen",
    "wof:name":"Malerbetrieb Wuttke Gmbh",
    "wof:placetype":"venue"
},
  "geometry": {"coordinates":[6.464729,50.825558],"type":"Point"}
}