{
  "type": "Feature",
  "properties": {
    "iso:country":"DE",
    "sg:address":"Johann-Georg-Str. 5",
    "sg:city":"Berlin",
    "sg:phone":"+49 30/89094035",
    "sg:postcode":"10709",
    "sg:province":"Berlin",
    "wof:name":"Kerszberg Events : Hostessenservice, Veranstaltungsservice",
    "wof:placetype":"venue"
},
  "geometry": {"coordinates":[13.298339,52.496532],"type":"Point"}
}