{
  "type": "Feature",
  "properties": {
    "iso:country":"DE",
    "sg:address":"Rotbuchenstr. 32",
    "sg:city":"M\u00fcnchen",
    "sg:phone":"+49 89/6990660",
    "sg:postcode":"81547",
    "sg:province":"Bayern",
    "wof:name":"Alten- Und Servicezentrum Harlaching",
    "wof:placetype":"venue"
},
  "geometry": {"coordinates":[11.57809,48.101173],"type":"Point"}
}