{
  "type": "Feature",
  "properties": {
    "iso:country":"DE",
    "sg:address":"Ro\u00dffelder Str. 59",
    "sg:city":"Crailsheim",
    "sg:phone":"+49 7951/93620",
    "sg:postcode":"74564",
    "sg:province":"Baden-W\u00fcrttemberg",
    "wof:name":"B\u00fcrger Gmbh & Co. Kg",
    "wof:placetype":"venue"
},
  "geometry": {"coordinates":[10.0363826752,49.1288375854],"type":"Point"}
}