{
  "type": "Feature",
  "properties": {
    "iso:country":"DE",
    "sg:address":"L\u00f6rracher Str. 21",
    "sg:city":"Freiburg",
    "sg:phone":"+49 7665/2693",
    "sg:postcode":"79115",
    "sg:province":"Baden-W\u00fcrttemberg",
    "wof:name":"Frank Straube Architekt",
    "wof:placetype":"venue"
},
  "geometry": {"coordinates":[7.826539,47.982079],"type":"Point"}
}