{
  "type": "Feature",
  "properties": {
    "iso:country":"DE",
    "sg:address":"Schmiedberg 5",
    "sg:city":"Augsburg",
    "sg:phone":"+49 821/38170",
    "sg:postcode":"86152",
    "sg:province":"Bayern",
    "wof:name":"Lory Orthop\u00e4die- Schuhtechnik Gmbh",
    "wof:placetype":"venue"
},
  "geometry": {"coordinates":[10.8983297348,48.3711738586],"type":"Point"}
}