{
  "type": "Feature",
  "properties": {
    "iso:country":"DE",
    "sg:address":"Marktplatz 9",
    "sg:city":"Bad Kissingen",
    "sg:phone":"+49 971/2109",
    "sg:postcode":"97688",
    "sg:province":"Bayern",
    "wof:name":"Hans D. Englert Rechtsanwalt",
    "wof:placetype":"venue"
},
  "geometry": {"coordinates":[10.0765647888,50.2000579834],"type":"Point"}
}