{
  "type": "Feature",
  "properties": {
    "iso:country":"DE",
    "sg:address":"Hauptstr. 1",
    "sg:city":"Steinhorst",
    "sg:phone":"+49 5148/775",
    "sg:postcode":"29367",
    "sg:province":"Niedersachsen",
    "wof:name":"Gasthaus-pension Niemann",
    "wof:placetype":"venue"
},
  "geometry": {"coordinates":[10.4396839142,52.7260513306],"type":"Point"}
}