{
  "type": "Feature",
  "properties": {
    "iso:country":"DE",
    "sg:address":"Westring 431-451",
    "sg:city":"Kiel",
    "sg:phone":"+49 431/80020",
    "sg:postcode":"24118",
    "sg:province":"Schleswig-Holstein",
    "wof:name":"People2people.de Gmbh",
    "wof:placetype":"venue"
},
  "geometry": {"coordinates":[10.1260671616,54.3407745361],"type":"Point"}
}