{
  "type": "Feature",
  "properties": {
    "iso:country":"DE",
    "sg:address":"Am Karrenberg 45::",
    "sg:city":"Velbert-T\u00f6nisheide",
    "sg:postcode":"42553",
    "sg:province":"Nordrhein-Westfalen",
    "wof:name":"Fuji Bank (deutschland) Ag",
    "wof:placetype":"venue"
},
  "geometry": {"coordinates":[8.663898,50.110981],"type":"Point"}
}