{
  "type": "Feature",
  "properties": {
    "iso:country":"DE",
    "sg:address":"Bredelarer Str. 2",
    "sg:city":"Diemelsee",
    "sg:phone":"+49 5633/276",
    "sg:postcode":"34519",
    "sg:province":"Hessen",
    "wof:name":"F. Meier",
    "wof:placetype":"venue"
},
  "geometry": {"coordinates":[8.7988080978,51.3680915833],"type":"Point"}
}