{
  "type": "Feature",
  "properties": {
    "iso:country":"DE",
    "sg:address":"Schulstr. 2",
    "sg:city":"Bad Teinach-Zavelstein",
    "sg:phone":"+49 7053/8661",
    "sg:postcode":"75385",
    "sg:province":"Baden-W\u00fcrttemberg",
    "wof:name":"Karl Bohnenberger",
    "wof:placetype":"venue"
},
  "geometry": {"coordinates":[8.6895904541,48.694316864],"type":"Point"}
}