{
  "type": "Feature",
  "properties": {
    "iso:country":"DE",
    "sg:address":"Herrenbreite 17",
    "sg:city":"Aschersleben",
    "sg:phone":"+49 3473/87260",
    "sg:postcode":"06449",
    "sg:province":"Sachsen-Anhalt",
    "wof:name":"Hotel Stadt Aschersleben",
    "wof:placetype":"venue"
},
  "geometry": {"coordinates":[11.4612588882,51.7583084106],"type":"Point"}
}