{
  "type": "Feature",
  "properties": {
    "iso:country":"DE",
    "sg:address":"Residenzstr. 27",
    "sg:city":"Berlin",
    "sg:phone":"+49 30/4953475",
    "sg:postcode":"13409",
    "sg:province":"Berlin",
    "wof:name":"Anette Spielhallen Gmbh",
    "wof:placetype":"venue"
},
  "geometry": {"coordinates":[13.3613328934,52.568901062],"type":"Point"}
}