{
  "type": "Feature",
  "properties": {
    "iso:country":"DE",
    "sg:address":"In den Kreuzwiesen 21",
    "sg:city":"Sch\u00f6nau",
    "sg:phone":"+49 6228/8781",
    "sg:postcode":"69250",
    "sg:province":"Baden-W\u00fcrttemberg",
    "wof:name":"Ebru Gesellschaft F\u00fcr Industrielle Elektronik Mbh",
    "wof:placetype":"venue"
},
  "geometry": {"coordinates":[8.80756,49.423553],"type":"Point"}
}