{
  "type": "Feature",
  "properties": {
    "iso:country":"DE",
    "sg:address":"R\u00fcckertstr. 14",
    "sg:city":"Schweinfurt",
    "sg:phone":"+49 9721/21821",
    "sg:postcode":"97421",
    "sg:province":"Bayern",
    "wof:name":"Pilsstube Zur Stra\u00dfenbahn",
    "wof:placetype":"venue"
},
  "geometry": {"coordinates":[10.2357711792,50.045501709],"type":"Point"}
}