{
  "type": "Feature",
  "properties": {
    "iso:country":"DE",
    "sg:address":"Lange Herzogstr. 23",
    "sg:city":"Wolfenb\u00fcttel",
    "sg:phone":"+49 5331/1507",
    "sg:postcode":"38300",
    "sg:province":"Niedersachsen",
    "wof:name":"Leder Fischer",
    "wof:placetype":"venue"
},
  "geometry": {"coordinates":[10.538912,52.164005],"type":"Point"}
}