{
  "type": "Feature",
  "properties": {
    "iso:country":"DE",
    "sg:address":"Parkstr. 13",
    "sg:city":"Erding",
    "sg:phone":"+49 8122/14925",
    "sg:postcode":"85435",
    "sg:province":"Bayern",
    "wof:name":"Karl-heinz Hartmann Fliesenleger Gmbh",
    "wof:placetype":"venue"
},
  "geometry": {"coordinates":[11.9064359665,48.2945327759],"type":"Point"}
}