{
  "type": "Feature",
  "properties": {
    "iso:country":"DE",
    "sg:address":"Pariser Str. 7",
    "sg:city":"Berlin",
    "sg:phone":"+49 30/8833680",
    "sg:postcode":"10719",
    "sg:province":"Berlin",
    "wof:name":"Zenit-buchhandlung Inh. Dagmar Reimold Und",
    "wof:placetype":"venue"
},
  "geometry": {"coordinates":[13.3277006149,52.4964523315],"type":"Point"}
}