{
  "type": "Feature",
  "properties": {
    "iso:country":"DE",
    "sg:address":"Bornst\u00e4dter Str. 30",
    "sg:city":"Osterhausen",
    "sg:phone":"+49 34776/20400",
    "sg:postcode":"06295",
    "sg:province":"Sachsen-Anhalt",
    "wof:name":"Rothenschirmbacher Agrargenossenschaft Eg",
    "wof:placetype":"venue"
},
  "geometry": {"coordinates":[11.50126,51.457226],"type":"Point"}
}