{
  "type": "Feature",
  "properties": {
    "iso:country":"DE",
    "sg:address":"Kappeler Weg 4",
    "sg:city":"Reckershausen",
    "sg:phone":"+49 6763/1783",
    "sg:postcode":"55481",
    "sg:province":"Rheinland-Pfalz",
    "wof:name":"Gremer Gabelstapler Service Gmbh",
    "wof:placetype":"venue"
},
  "geometry": {"coordinates":[7.400712,49.98291],"type":"Point"}
}