{
  "type": "Feature",
  "properties": {
    "iso:country":"DE",
    "sg:address":"Dorfstr. 3",
    "sg:city":"Wolfenb\u00fcttel",
    "sg:phone":"+49 5331/44428",
    "sg:postcode":"38300",
    "sg:province":"Niedersachsen",
    "wof:name":"Malerbetrieb Horst Behrens Nachf. Inh. J\u00f6rg Borkowski",
    "wof:placetype":"venue"
},
  "geometry": {"coordinates":[10.588897,52.15432],"type":"Point"}
}