{
  "type": "Feature",
  "properties": {
    "iso:country":"DE",
    "sg:address":"Ruhrstr. 41",
    "sg:city":"Arnsberg",
    "sg:phone":"+49 2931/3402",
    "sg:postcode":"59821",
    "sg:province":"Nordrhein-Westfalen",
    "wof:name":"Hotel Zur Linde",
    "wof:placetype":"venue"
},
  "geometry": {"coordinates":[8.0646781921,51.4000091553],"type":"Point"}
}