{
  "type": "Feature",
  "properties": {
    "iso:country":"DE",
    "sg:address":"Alleestr. 51",
    "sg:city":"Duisburg",
    "sg:phone":"+49 203/5520544",
    "sg:postcode":"47166",
    "sg:province":"Nordrhein-Westfalen",
    "wof:name":"Ralf K\u00f6ppen Anlageberater",
    "wof:placetype":"venue"
},
  "geometry": {"coordinates":[6.7756872177,51.4898910522],"type":"Point"}
}