{
  "type": "Feature",
  "properties": {
    "iso:country":"DE",
    "sg:address":"Stra\u00dfe des Friedens 5",
    "sg:city":"Lauscha",
    "sg:postcode":"98724",
    "sg:province":"Th\u00fcringen",
    "wof:name":"Merkur-drogerie",
    "wof:placetype":"venue"
},
  "geometry": {"coordinates":[11.161177,50.477417],"type":"Point"}
}