{
  "type": "Feature",
  "properties": {
    "iso:country":"DE",
    "sg:address":"Hindenburgstr. 300",
    "sg:city":"M\u00f6nchengladbach",
    "sg:phone":"+49 2161/10079",
    "sg:postcode":"41061",
    "sg:province":"Nordrhein-Westfalen",
    "wof:name":"Reiner Herzmann",
    "wof:placetype":"venue"
},
  "geometry": {"coordinates":[6.4494771957,51.2006378174],"type":"Point"}
}