{
  "type": "Feature",
  "properties": {
    "iso:country":"DE",
    "sg:address":"Johannisplatz 4-1",
    "sg:city":"Limbach-Oberfrohna",
    "sg:phone":"+49 3722/896105",
    "sg:postcode":"09212",
    "sg:province":"Sachsen",
    "wof:name":"Vereinigte Versicherung",
    "wof:placetype":"venue"
},
  "geometry": {"coordinates":[12.7612257004,50.8588447571],"type":"Point"}
}