{
  "type": "Feature",
  "properties": {
    "iso:country":"DE",
    "sg:address":"Raiffeisenstr. 5",
    "sg:city":"Kirchhain",
    "sg:phone":"+49 6422/859980",
    "sg:postcode":"35274",
    "sg:province":"Hessen",
    "wof:name":"Ingenieurb\u00fcro Palme Gmbh",
    "wof:placetype":"venue"
},
  "geometry": {"coordinates":[8.9210062027,50.8218421936],"type":"Point"}
}