{
  "type": "Feature",
  "properties": {
    "iso:country":"DE",
    "sg:address":"Krokusstr. 64 A",
    "sg:city":"Berlin",
    "sg:phone":"+49 30/6626161",
    "sg:postcode":"12357",
    "sg:province":"Berlin",
    "wof:name":"Goldene Tasse",
    "wof:placetype":"venue"
},
  "geometry": {"coordinates":[13.4951086044,52.4235076904],"type":"Point"}
}