{
  "type": "Feature",
  "properties": {
    "iso:country":"DE",
    "sg:address":"Kernerstr. 33",
    "sg:city":"Stuttgart",
    "sg:postcode":"70182",
    "sg:province":"Baden-W\u00fcrttemberg",
    "wof:name":"Bauer Gmbh",
    "wof:placetype":"venue"
},
  "geometry": {"coordinates":[9.190392,48.782757],"type":"Point"}
}