{
  "type": "Feature",
  "properties": {
    "iso:country":"DE",
    "sg:address":"Albert-Schweitzer-Str. 11 a",
    "sg:city":"Kirchzarten",
    "sg:phone":"+49 7661/98680",
    "sg:postcode":"79199",
    "sg:province":"Baden-W\u00fcrttemberg",
    "wof:name":"Sozialstation Dreisamtal E. V.",
    "wof:placetype":"venue"
},
  "geometry": {"coordinates":[7.951175,47.967442],"type":"Point"}
}