{
  "type": "Feature",
  "properties": {
    "iso:country":"DE",
    "sg:address":"Rosa-Luxemburg-Str. 2",
    "sg:city":"Tautenhain",
    "sg:phone":"+49 34341/43930",
    "sg:postcode":"04643",
    "sg:province":"Sachsen",
    "wof:name":"M. Heine",
    "wof:placetype":"venue"
},
  "geometry": {"coordinates":[12.6835403442,51.0902137756],"type":"Point"}
}