{
  "type": "Feature",
  "properties": {
    "iso:country":"DE",
    "sg:address":"Kettelerstr. 10",
    "sg:city":"H\u00f6xter",
    "sg:phone":"+49 5271/92424",
    "sg:postcode":"37671",
    "sg:province":"Nordrhein-Westfalen",
    "wof:name":"Bruno Arens Gbr",
    "wof:placetype":"venue"
},
  "geometry": {"coordinates":[9.353617,51.808224],"type":"Point"}
}