{
  "type": "Feature",
  "properties": {
    "iso:country":"DE",
    "sg:address":"Hardt 6",
    "sg:city":"Sendenhorst",
    "sg:phone":"+49 2526/1272",
    "sg:postcode":"48324",
    "sg:province":"Nordrhein-Westfalen",
    "wof:name":"Restaurant Gasthaus Waldmutter M. Kogge",
    "wof:placetype":"venue"
},
  "geometry": {"coordinates":[7.8712158203,51.8301582336],"type":"Point"}
}