{
  "type": "Feature",
  "properties": {
    "iso:country":"DE",
    "sg:address":"Krefelder Str. 50",
    "sg:city":"Geldern",
    "sg:phone":"+49 2831/12933",
    "sg:postcode":"47608",
    "sg:province":"Nordrhein-Westfalen",
    "wof:name":"Beterams Gartencenter",
    "wof:placetype":"venue"
},
  "geometry": {"coordinates":[6.332043,51.509109],"type":"Point"}
}