{
  "type": "Feature",
  "properties": {
    "iso:country":"DE",
    "sg:address":"Ludwigstr. 95",
    "sg:city":"Offenbach",
    "sg:phone":"+49 69/812650",
    "sg:postcode":"63067",
    "sg:province":"Hessen",
    "wof:name":"Hotel L\u00f6wen",
    "wof:placetype":"venue"
},
  "geometry": {"coordinates":[8.7529993057,50.1049575806],"type":"Point"}
}