{
  "type": "Feature",
  "properties": {
    "iso:country":"DE",
    "sg:address":"Bielefelder Str. 57",
    "sg:city":"Herford",
    "sg:phone":"+49 5221/50375",
    "sg:postcode":"32051",
    "sg:province":"Nordrhein-Westfalen",
    "wof:name":"Otto Spilker",
    "wof:placetype":"venue"
},
  "geometry": {"coordinates":[8.657834053,52.109375],"type":"Point"}
}