{
  "type": "Feature",
  "properties": {
    "iso:country":"DE",
    "sg:address":"K\u00f6lnstr. 47",
    "sg:city":"Bonn",
    "sg:phone":"+49 228/654074",
    "sg:postcode":"53111",
    "sg:province":"Nordrhein-Westfalen",
    "wof:name":"Restaurant Anno Tubac",
    "wof:placetype":"venue"
},
  "geometry": {"coordinates":[7.0998969078,50.7394256592],"type":"Point"}
}