{
  "type": "Feature",
  "properties": {
    "iso:country":"DE",
    "sg:address":"Schiepziger Str. 29",
    "sg:city":"Halle",
    "sg:postcode":"06120",
    "sg:province":"Sachsen-Anhalt",
    "wof:name":"Forschungs- Und Untersuchungs- Anstalt Des Landes",
    "wof:placetype":"venue"
},
  "geometry": {"coordinates":[11.8624353409,51.5045318604],"type":"Point"}
}