{
  "type": "Feature",
  "properties": {
    "iso:country":"DE",
    "sg:address":"Hirschstr. 52",
    "sg:city":"Lorsch",
    "sg:phone":"+49 6251/52342",
    "sg:postcode":"64653",
    "sg:province":"Hessen",
    "wof:name":"Nikolaus Adrian",
    "wof:placetype":"venue"
},
  "geometry": {"coordinates":[8.567787,49.646912],"type":"Point"}
}