{
  "type": "Feature",
  "properties": {
    "iso:country":"DE",
    "sg:address":"Salzstr. 27",
    "sg:city":"Kempten",
    "sg:phone":"+49 831/521770",
    "sg:postcode":"87435",
    "sg:province":"Bayern",
    "wof:name":"Schw\u00e4bisches Ingeniurb\u00fcro F\u00fcr Wasserversorgung Und",
    "wof:placetype":"venue"
},
  "geometry": {"coordinates":[10.3104352951,47.726650238],"type":"Point"}
}