{
  "type": "Feature",
  "properties": {
    "iso:country":"DE",
    "sg:address":"Sonnenbachweg 69",
    "sg:city":"Augsburg",
    "sg:phone":"+49 821/705351",
    "sg:postcode":"86169",
    "sg:province":"Bayern",
    "wof:name":"Hans Bosch",
    "wof:placetype":"venue"
},
  "geometry": {"coordinates":[10.903509,48.402836],"type":"Point"}
}