{
  "type": "Feature",
  "properties": {
    "iso:country":"DE",
    "sg:address":"Steinbruchweg 4",
    "sg:city":"Dossenheim",
    "sg:phone":"+49 6221/87560",
    "sg:postcode":"69221",
    "sg:province":"Baden-W\u00fcrttemberg",
    "wof:name":"Hotel Am Kirchberg",
    "wof:placetype":"venue"
},
  "geometry": {"coordinates":[8.6786985397,49.4516067505],"type":"Point"}
}