{
  "type": "Feature",
  "properties": {
    "iso:country":"DE",
    "sg:address":"Kirchstr. 64",
    "sg:city":"M\u00fcnster",
    "sg:phone":"+49 6071/34436",
    "sg:postcode":"64839",
    "sg:province":"Hessen",
    "wof:name":"Reimar M\u00fcller",
    "wof:placetype":"venue"
},
  "geometry": {"coordinates":[8.8940029144,49.913433075],"type":"Point"}
}