{
  "type": "Feature",
  "properties": {
    "iso:country":"DE",
    "sg:address":"Mitteldorfstr. 10",
    "sg:city":"Hausen",
    "sg:phone":"+49 7622/2531",
    "sg:postcode":"79688",
    "sg:province":"Baden-W\u00fcrttemberg",
    "wof:name":"Dieter Greiner",
    "wof:placetype":"venue"
},
  "geometry": {"coordinates":[7.8401408195,47.6816711426],"type":"Point"}
}