{
  "type": "Feature",
  "properties": {
    "iso:country":"DE",
    "sg:address":"Jahnstr. 2",
    "sg:city":"Preu\u00dfisch Oldendorf",
    "sg:postcode":"32361",
    "sg:province":"Nordrhein-Westfalen",
    "wof:name":"Jack W. Bradley Masseur",
    "wof:placetype":"venue"
},
  "geometry": {"coordinates":[8.489131,52.302738],"type":"Point"}
}