{
  "type": "Feature",
  "properties": {
    "iso:country":"DE",
    "sg:address":"Normannenstr. 16",
    "sg:city":"M\u00fcnchen",
    "sg:phone":"+49 89/984845",
    "sg:postcode":"81925",
    "sg:province":"Bayern",
    "wof:name":"Albert Graf",
    "wof:placetype":"venue"
},
  "geometry": {"coordinates":[11.6177406311,48.1543655396],"type":"Point"}
}