{
  "type": "Feature",
  "properties": {
    "iso:country":"DE",
    "sg:address":"Quellenhofweg 5",
    "sg:city":"Bielefeld",
    "sg:phone":"+49 521/1438881",
    "sg:postcode":"33617",
    "sg:province":"Nordrhein-Westfalen",
    "wof:name":"B.s.g. Gmbh Bielefelder Sicherheitsglas",
    "wof:placetype":"venue"
},
  "geometry": {"coordinates":[8.5187005997,52.0100479126],"type":"Point"}
}