{
  "type": "Feature",
  "properties": {
    "iso:country":"DE",
    "sg:address":"Industriestr. 4-8",
    "sg:city":"Baiersdorf",
    "sg:phone":"+49 9133/2602",
    "sg:postcode":"91083",
    "sg:province":"Bayern",
    "wof:name":"Hocam Universal Spielwarenhandels Gmbh",
    "wof:placetype":"venue"
},
  "geometry": {"coordinates":[11.0387973785,49.6589279175],"type":"Point"}
}