{
  "type": "Feature",
  "properties": {
    "iso:country":"DE",
    "sg:address":"Benzstr. 4",
    "sg:city":"Marl",
    "sg:postcode":"45772",
    "sg:province":"Nordrhein-Westfalen",
    "wof:name":"Polycoat Gmbh",
    "wof:placetype":"venue"
},
  "geometry": {"coordinates":[7.162708,51.672146],"type":"Point"}
}