{
  "type": "Feature",
  "properties": {
    "iso:country":"DE",
    "sg:address":"Untere Bergstr. 11",
    "sg:city":"Langenau",
    "sg:phone":"+49 7345/5379",
    "sg:postcode":"89129",
    "sg:province":"Baden-W\u00fcrttemberg",
    "wof:name":"Kurt Baiker Architekt",
    "wof:placetype":"venue"
},
  "geometry": {"coordinates":[10.114828,48.49826],"type":"Point"}
}