{
  "type": "Feature",
  "properties": {
    "iso:country":"DE",
    "sg:address":"Ortsstr. 6",
    "sg:city":"Karlsruhe",
    "sg:phone":"+49 721/473651",
    "sg:postcode":"76228",
    "sg:province":"Baden-W\u00fcrttemberg",
    "wof:name":"Piston Gmbh",
    "wof:placetype":"venue"
},
  "geometry": {"coordinates":[8.5084581375,48.9537506104],"type":"Point"}
}