{
  "type": "Feature",
  "properties": {
    "iso:country":"DE",
    "sg:address":"\u00dcbelrodaer Str. 42",
    "sg:city":"Immelborn",
    "sg:phone":"+49 3695/871424",
    "sg:postcode":"36433",
    "sg:province":"Th\u00fcringen",
    "wof:name":"Gerhard Luck",
    "wof:placetype":"venue"
},
  "geometry": {"coordinates":[10.2733230591,50.790725708],"type":"Point"}
}