{
  "type": "Feature",
  "properties": {
    "iso:country":"DE",
    "sg:address":"Eichendorffstr. 11",
    "sg:city":"Osthofen",
    "sg:postcode":"67574",
    "sg:province":"Rheinland-Pfalz",
    "wof:name":"Gaubatz Fassaden Systeme Gmbh",
    "wof:placetype":"venue"
},
  "geometry": {"coordinates":[8.3199224472,49.6967277527],"type":"Point"}
}