{
  "type": "Feature",
  "properties": {
    "iso:country":"DE",
    "sg:address":"Vl\u00e4mische Str. 3",
    "sg:city":"Lastrup",
    "sg:phone":"+49 4472/8863",
    "sg:postcode":"49688",
    "sg:province":"Niedersachsen",
    "wof:name":"Frischgefl\u00fcgel B\u00fcnnemeyer Gmbh",
    "wof:placetype":"venue"
},
  "geometry": {"coordinates":[7.8599090576,52.7943305969],"type":"Point"}
}