{
  "type": "Feature",
  "properties": {
    "iso:country":"DE",
    "sg:address":"Zweinaundorfer Str. 11-13",
    "sg:city":"Leipzig",
    "sg:phone":"+49 341/6880575",
    "sg:postcode":"04318",
    "sg:province":"Sachsen",
    "wof:name":"Cafe Orient Inh. H. Engler",
    "wof:placetype":"venue"
},
  "geometry": {"coordinates":[12.409818,51.335262],"type":"Point"}
}