{
  "type": "Feature",
  "properties": {
    "iso:country":"DE",
    "sg:address":"Nikolaus-Fey-Str 17",
    "sg:city":"Gerolzhofen",
    "sg:phone":"+49 9382/97910",
    "sg:postcode":"97447",
    "sg:province":"Bayern",
    "wof:name":"Kirchner Gmbh",
    "wof:placetype":"venue"
},
  "geometry": {"coordinates":[10.3411159515,49.8985099792],"type":"Point"}
}