{
  "type": "Feature",
  "properties": {
    "iso:country":"DE",
    "sg:address":"Schmutterstr. 22",
    "sg:city":"Trossingen",
    "sg:phone":"+49 7425/27408",
    "sg:postcode":"78647",
    "sg:province":"Baden-W\u00fcrttemberg",
    "wof:name":"M. K\u00e4stner",
    "wof:placetype":"venue"
},
  "geometry": {"coordinates":[8.6400136948,48.0712089539],"type":"Point"}
}