{
  "type": "Feature",
  "properties": {
    "iso:country":"DE",
    "sg:address":"Neue Torstr. 1",
    "sg:city":"Schieder-Schwalenberg",
    "sg:phone":"+49 5284/98060",
    "sg:postcode":"32816",
    "sg:province":"Nordrhein-Westfalen",
    "wof:name":"Hotel-restaurant-cafe Schwalenberger Malkasten",
    "wof:placetype":"venue"
},
  "geometry": {"coordinates":[9.1982736588,51.8786354065],"type":"Point"}
}