{
  "type": "Feature",
  "properties": {
    "iso:country":"DE",
    "sg:address":"Rosengasse 342",
    "sg:city":"Landshut",
    "sg:phone":"+49 871/89308",
    "sg:postcode":"84028",
    "sg:province":"Bayern",
    "wof:name":"Otto Pa\u00dfberger",
    "wof:placetype":"venue"
},
  "geometry": {"coordinates":[12.1530656815,48.5367279053],"type":"Point"}
}