{
  "type": "Feature",
  "properties": {
    "iso:country":"DE",
    "sg:address":"Tulpenweg 4",
    "sg:city":"Kirchheim",
    "sg:phone":"+49 89/9032778",
    "sg:postcode":"85551",
    "sg:province":"Bayern",
    "wof:name":"Michael Friederichsen Bildhauer",
    "wof:placetype":"venue"
},
  "geometry": {"coordinates":[11.756339,48.16013],"type":"Point"}
}