{
  "type": "Feature",
  "properties": {
    "iso:country":"DE",
    "sg:address":"Iselerstr. 15",
    "sg:city":"Bremerv\u00f6rde",
    "sg:phone":"+49 4769/213",
    "sg:postcode":"27432",
    "sg:province":"Niedersachsen",
    "wof:name":"Hinrich Buck Seeschiffahrts-u.",
    "wof:placetype":"venue"
},
  "geometry": {"coordinates":[9.1333,53.579529],"type":"Point"}
}