{
  "type": "Feature",
  "properties": {
    "iso:country":"DE",
    "sg:address":"Denkmalstr. 20",
    "sg:city":"Bayreuth",
    "sg:phone":"+49 921/92502",
    "sg:postcode":"95448",
    "sg:province":"Bayern",
    "wof:name":"S. Freiberger",
    "wof:placetype":"venue"
},
  "geometry": {"coordinates":[11.6252880096,49.9603271484],"type":"Point"}
}