{
  "type": "Feature",
  "properties": {
    "iso:country":"DE",
    "sg:address":"Mouvauxstr. 40",
    "sg:city":"Neukirchen-Vluyn",
    "sg:postcode":"47506",
    "sg:province":"Nordrhein-Westfalen",
    "wof:name":"Planungsteam Maas- Van Schingen Gmbh",
    "wof:placetype":"venue"
},
  "geometry": {"coordinates":[6.540101,51.433495],"type":"Point"}
}