{
  "type": "Feature",
  "properties": {
    "iso:country":"DE",
    "sg:address":"Drosselstr. 21",
    "sg:city":"Kelheim",
    "sg:phone":"+49 9441/9603",
    "sg:postcode":"93309",
    "sg:province":"Bayern",
    "wof:name":"Franz Balk",
    "wof:placetype":"venue"
},
  "geometry": {"coordinates":[11.890309,48.916222],"type":"Point"}
}