{
  "type": "Feature",
  "properties": {
    "iso:country":"DE",
    "sg:address":"Dikwai 4",
    "sg:city":"Sylt-Ost",
    "sg:phone":"+49 4651/890755",
    "sg:postcode":"25980",
    "sg:province":"Schleswig-Holstein",
    "wof:name":"Karin Boernsen Kosmetiksalon",
    "wof:placetype":"venue"
},
  "geometry": {"coordinates":[8.414447,54.865555],"type":"Point"}
}