{
  "type": "Feature",
  "properties": {
    "iso:country":"DE",
    "sg:address":"Ludwigstr. 95",
    "sg:city":"Garmisch Partenkirchen",
    "sg:phone":"+49 8821/7330",
    "sg:postcode":"82467",
    "sg:province":"Bayern",
    "wof:name":"Raiffeisenbank Garmisch-partenkir.",
    "wof:placetype":"venue"
},
  "geometry": {"coordinates":[11.107663,47.494591],"type":"Point"}
}