{
  "type": "Feature",
  "properties": {
    "iso:country":"DE",
    "sg:address":"Steinh\u00f6ft",
    "sg:city":"Hamburg",
    "sg:phone":"+49 40/362501",
    "sg:postcode":"20459",
    "sg:province":"Hamburg",
    "wof:name":"C. Heinrich F. Meyer Assekuranz",
    "wof:placetype":"venue"
},
  "geometry": {"coordinates":[9.9827699661,53.5452919006],"type":"Point"}
}