{
  "type": "Feature",
  "properties": {
    "iso:country":"DE",
    "sg:address":"Gr\u00fcne Str. 24 a",
    "sg:city":"Oldenburg",
    "sg:postcode":"26121",
    "sg:province":"Niedersachsen",
    "wof:name":"E & B Gesellschaft F\u00fcr Wissenschaftliche Studien Mbh",
    "wof:placetype":"venue"
},
  "geometry": {"coordinates":[8.2101993561,53.1445541382],"type":"Point"}
}