{
  "type": "Feature",
  "properties": {
    "iso:country":"DE",
    "sg:address":"M\u00fcndener Str. 82",
    "sg:city":"Reinhardshagen",
    "sg:phone":"+49 5544/940007",
    "sg:postcode":"34359",
    "sg:province":"Hessen",
    "wof:name":"Taverne Despina",
    "wof:placetype":"venue"
},
  "geometry": {"coordinates":[9.6190500259,51.4786491394],"type":"Point"}
}