{
  "type": "Feature",
  "properties": {
    "iso:country":"DE",
    "sg:address":"Industriestr. 1",
    "sg:city":"Waldmohr",
    "sg:phone":"+49 6373/8230",
    "sg:postcode":"66914",
    "sg:province":"Rheinland-Pfalz",
    "wof:name":"Kampa-hausbau Waldmohr Gmbh",
    "wof:placetype":"venue"
},
  "geometry": {"coordinates":[7.347759,49.384308],"type":"Point"}
}