{
  "type": "Feature",
  "properties": {
    "iso:country":"DE",
    "sg:address":"Erles\u00e4ckerstr. 6",
    "sg:city":"Reutlingen",
    "sg:postcode":"72768",
    "sg:province":"Baden-W\u00fcrttemberg",
    "wof:name":"Creative Consulting Gmbh",
    "wof:placetype":"venue"
},
  "geometry": {"coordinates":[9.1702032089,48.5219841003],"type":"Point"}
}