{
  "type": "Feature",
  "properties": {
    "iso:country":"DE",
    "sg:address":"Kapellenstr.200",
    "sg:city":"Baesweiler",
    "sg:phone":"+49 2401/939138",
    "sg:postcode":"52499",
    "sg:province":"Nordrhein-Westfalen",
    "wof:name":"Irs-webdesign",
    "wof:placetype":"venue"
},
  "geometry": {"coordinates":[6.174105,50.907917],"type":"Point"}
}