{
  "type": "Feature",
  "properties": {
    "iso:country":"DE",
    "sg:address":"G\u00f6ckingstr.",
    "sg:city":"Ellrich",
    "sg:postcode":"99755",
    "sg:province":"Th\u00fcringen",
    "wof:name":"Elf-tankstelle",
    "wof:placetype":"venue"
},
  "geometry": {"coordinates":[10.6718130112,51.5805931091],"type":"Point"}
}