{
  "type": "Feature",
  "properties": {
    "iso:country":"DE",
    "sg:address":"Sommerdeich 41",
    "sg:city":"Kleve",
    "sg:phone":"+49 2821/24672",
    "sg:postcode":"47533",
    "sg:province":"Nordrhein-Westfalen",
    "wof:name":"R\u00fcbo-gas Handelsges. Mbh",
    "wof:placetype":"venue"
},
  "geometry": {"coordinates":[6.1437969208,51.7971496582],"type":"Point"}
}