{
  "type": "Feature",
  "properties": {
    "iso:country":"DE",
    "sg:address":"Klaus-Strick-Weg 25",
    "sg:city":"Osnabr\u00fcck",
    "sg:phone":"+49 541/56694",
    "sg:postcode":"49082",
    "sg:province":"Niedersachsen",
    "wof:name":"Tus Nahne",
    "wof:placetype":"venue"
},
  "geometry": {"coordinates":[8.0673503876,52.2501716614],"type":"Point"}
}