{
  "type": "Feature",
  "properties": {
    "iso:country":"DE",
    "sg:address":"Hardtstr. 6",
    "sg:city":"Eglfing",
    "sg:phone":"+49 8847/733",
    "sg:postcode":"82436",
    "sg:province":"Bayern",
    "wof:name":"Systembau Wolfgang Storf",
    "wof:placetype":"venue"
},
  "geometry": {"coordinates":[11.180527,47.74638],"type":"Point"}
}