{
  "type": "Feature",
  "properties": {
    "iso:country":"DE",
    "sg:address":"Untere Hauptstr. 9 b",
    "sg:city":"Eching",
    "sg:phone":"+49 89/3192353",
    "sg:postcode":"85386",
    "sg:province":"Bayern",
    "wof:name":"Regina Arndt Krankengymnastin",
    "wof:placetype":"venue"
},
  "geometry": {"coordinates":[11.625262,48.298187],"type":"Point"}
}