{
  "type": "Feature",
  "properties": {
    "iso:country":"DE",
    "sg:address":"Alte Poststr. 7",
    "sg:city":"Kleinostheim",
    "sg:phone":"+49 6027/99976",
    "sg:postcode":"63801",
    "sg:province":"Bayern",
    "wof:name":"G & S Buchhaltungs- Service Gmbh",
    "wof:placetype":"venue"
},
  "geometry": {"coordinates":[9.070431,50.00563],"type":"Point"}
}