{
  "type": "Feature",
  "properties": {
    "iso:country":"DE",
    "sg:address":"Rappenberghalde 61",
    "sg:city":"T\u00fcbingen",
    "sg:phone":"+49 7071/43145",
    "sg:postcode":"72070",
    "sg:province":"Baden-W\u00fcrttemberg",
    "wof:name":"Neckarcamping",
    "wof:placetype":"venue"
},
  "geometry": {"coordinates":[9.035319,48.510143],"type":"Point"}
}