{
  "type": "Feature",
  "properties": {
    "iso:country":"DE",
    "sg:address":"Ochsenkopf 6",
    "sg:city":"Eckernf\u00f6rde",
    "sg:phone":"+49 4351/2122",
    "sg:postcode":"24340",
    "sg:province":"Schleswig-Holstein",
    "wof:name":"Heidrich B\u00fcrobedarf",
    "wof:placetype":"venue"
},
  "geometry": {"coordinates":[9.8358449936,54.4732475281],"type":"Point"}
}