{
  "type": "Feature",
  "properties": {
    "iso:country":"DE",
    "sg:address":"Schifferheimstr. 13",
    "sg:city":"Duisburg",
    "sg:phone":"+49 4920/381855",
    "sg:postcode":"47119",
    "sg:province":"Nordrhein-Westfalen",
    "wof:name":"Bernhard Van De Spreng Gmbh",
    "wof:placetype":"venue"
},
  "geometry": {"coordinates":[6.730410099,51.4548721313],"type":"Point"}
}