{
  "type": "Feature",
  "properties": {
    "iso:country":"DE",
    "sg:address":"Bahnhofstr. 39",
    "sg:city":"Weingarten",
    "sg:phone":"+49 7244/1212",
    "sg:postcode":"76356",
    "sg:province":"Baden-W\u00fcrttemberg",
    "wof:name":"Henry \u00d6streicher Vereinigte Versicherung",
    "wof:placetype":"venue"
},
  "geometry": {"coordinates":[8.5282039642,49.052898407],"type":"Point"}
}