{
  "type": "Feature",
  "properties": {
    "iso:country":"DE",
    "sg:address":"Hartkirchweg 17",
    "sg:city":"Freiburg",
    "sg:phone":"+49 761",
    "sg:postcode":"79111",
    "sg:province":"Baden-W\u00fcrttemberg",
    "wof:name":"Shoes 4 U - Main Shop",
    "wof:placetype":"venue"
},
  "geometry": {"coordinates":[7.802518,47.980061],"type":"Point"}
}