{
  "type": "Feature",
  "properties": {
    "iso:country":"DE",
    "sg:address":"M\u00fchlendamm 34",
    "sg:city":"Solingen",
    "sg:phone":"+49 212/49394",
    "sg:postcode":"42659",
    "sg:province":"Nordrhein-Westfalen",
    "wof:name":"P. Waerder Steuerberater",
    "wof:placetype":"venue"
},
  "geometry": {"coordinates":[7.1501321793,51.141166687],"type":"Point"}
}