{
  "type": "Feature",
  "properties": {
    "iso:country":"DE",
    "sg:address":"Altnossener Str. 11a",
    "sg:city":"Gompitz",
    "sg:phone":"+49 351/4160563",
    "sg:postcode":"01462",
    "wof:name":"D. Bauer Gmbh",
    "wof:placetype":"venue"
},
  "geometry": {"coordinates":[13.639784,51.041866],"type":"Point"}
}