{
  "type": "Feature",
  "properties": {
    "iso:country":"DE",
    "sg:address":"Hans-Sachs-Str 6",
    "sg:city":"Hilden",
    "sg:phone":"+49 2103/42525",
    "sg:postcode":"40721",
    "sg:province":"Nordrhein-Westfalen",
    "wof:name":"Helmut Mack Blechverarbeitung Gmbh & Co Kg",
    "wof:placetype":"venue"
},
  "geometry": {"coordinates":[6.919863224,51.1741371155],"type":"Point"}
}