{
  "type": "Feature",
  "properties": {
    "iso:country":"DE",
    "sg:address":"Leipheimer Str. 78",
    "sg:city":"Neu-Ulm",
    "sg:phone":"+49 731/714544",
    "sg:postcode":"89233",
    "sg:province":"Bayern",
    "wof:name":"Nusser",
    "wof:placetype":"venue"
},
  "geometry": {"coordinates":[10.040971756,48.4059677124],"type":"Point"}
}