{
  "type": "Feature",
  "properties": {
    "iso:country":"DE",
    "sg:address":"Pl d Befreiung 12",
    "sg:city":"Glash\u00fctte",
    "sg:phone":"+49 35053/8236",
    "sg:postcode":"01768",
    "sg:province":"Sachsen",
    "wof:name":"Dresdner Spezialgetriebe Gmbh",
    "wof:placetype":"venue"
},
  "geometry": {"coordinates":[13.779904,50.851601],"type":"Point"}
}