{
  "type": "Feature",
  "properties": {
    "iso:country":"DE",
    "sg:address":"Steinbeck 3",
    "sg:city":"Stade",
    "sg:phone":"+49 4141/51870",
    "sg:postcode":"21684",
    "sg:province":"Niedersachsen",
    "wof:name":"Hadler Gmbh",
    "wof:placetype":"venue"
},
  "geometry": {"coordinates":[9.4713811874,53.5463905334],"type":"Point"}
}