{
  "type": "Feature",
  "properties": {
    "iso:country":"DE",
    "sg:address":"Germanenstr. 20",
    "sg:city":"Beckum",
    "sg:phone":"+49 2521/5546",
    "sg:postcode":"59269",
    "sg:province":"Nordrhein-Westfalen",
    "wof:name":"E. Proksch",
    "wof:placetype":"venue"
},
  "geometry": {"coordinates":[8.0245771408,51.751083374],"type":"Point"}
}