{
  "type": "Feature",
  "properties": {
    "iso:country":"DE",
    "sg:address":"Bredenscheider Str. 114",
    "sg:city":"Hattingen",
    "sg:phone":"+49 2324/24602",
    "sg:postcode":"45525",
    "sg:province":"Nordrhein-Westfalen",
    "wof:name":"Wilhelm Flieter",
    "wof:placetype":"venue"
},
  "geometry": {"coordinates":[7.191454,51.382923],"type":"Point"}
}