{
  "type": "Feature",
  "properties": {
    "iso:country":"DE",
    "sg:address":"Barbarossaweg 6",
    "sg:city":"Waldstetten",
    "sg:phone":"+49 7171/41061",
    "sg:postcode":"73550",
    "sg:province":"Baden-W\u00fcrttemberg",
    "wof:name":"Ingenieurb\u00fcro Weber E. K.",
    "wof:placetype":"venue"
},
  "geometry": {"coordinates":[9.814989,48.769337],"type":"Point"}
}