{
  "type": "Feature",
  "properties": {
    "iso:country":"DE",
    "sg:address":"Friedrich-Ebert-Str. 413",
    "sg:city":"Duisburg",
    "sg:phone":"+49 203/471120",
    "sg:postcode":"47178",
    "sg:province":"Nordrhein-Westfalen",
    "wof:name":"J\u00fcrgen Bendmann",
    "wof:placetype":"venue"
},
  "geometry": {"coordinates":[6.7377347946,51.5397186279],"type":"Point"}
}