{
  "type": "Feature",
  "properties": {
    "iso:country":"DE",
    "sg:address":"Hermann-Klammt-Str. 7",
    "sg:city":"Neuss",
    "sg:postcode":"41460",
    "sg:province":"Nordrhein-Westfalen",
    "wof:name":"Wayss & Freytag Schl\u00fcssel- Fertigbau Ag",
    "wof:placetype":"venue"
},
  "geometry": {"coordinates":[6.685837,51.225677],"type":"Point"}
}