{
  "type": "Feature",
  "properties": {
    "iso:country":"DE",
    "sg:address":"Friedberger Landstr. 296",
    "sg:city":"Frankfurt",
    "sg:phone":"+49 69/553103",
    "sg:postcode":"60389",
    "sg:province":"Hessen",
    "wof:name":"O. Frank Autolackiererei",
    "wof:placetype":"venue"
},
  "geometry": {"coordinates":[8.695468,50.132629],"type":"Point"}
}