{
  "type": "Feature",
  "properties": {
    "iso:country":"DE",
    "sg:address":"Rauchstr. 89",
    "sg:city":"Hamburg",
    "sg:phone":"+49 40/6560942",
    "sg:postcode":"22043",
    "sg:province":"Hamburg",
    "wof:name":"Ulrich Meyer Rechtsanwalt",
    "wof:placetype":"venue"
},
  "geometry": {"coordinates":[10.0972003937,53.5724868774],"type":"Point"}
}