{
  "type": "Feature",
  "properties": {
    "iso:country":"DE",
    "sg:address":"Eisenbahnstr. 4",
    "sg:city":"Forchheim",
    "sg:phone":"+49 9191/13144",
    "sg:postcode":"91301",
    "sg:province":"Bayern",
    "wof:name":"F. Hagen",
    "wof:placetype":"venue"
},
  "geometry": {"coordinates":[11.0657873154,49.7185401917],"type":"Point"}
}