{
  "type": "Feature",
  "properties": {
    "iso:country":"DE",
    "sg:address":"Friedrichshofener Str. 29",
    "sg:city":"Ingolstadt",
    "sg:phone":"+49 841/42683",
    "sg:postcode":"85049",
    "sg:province":"Bayern",
    "wof:name":"Eberhard Gleinich Weinhandels- Gmbh",
    "wof:placetype":"venue"
},
  "geometry": {"coordinates":[11.3735675812,48.7797660828],"type":"Point"}
}