{
  "type": "Feature",
  "properties": {
    "iso:country":"DE",
    "sg:address":"Querenburger Str 19-23",
    "sg:city":"Bochum",
    "sg:phone":"+49 234/937730",
    "sg:postcode":"44789",
    "sg:province":"Nordrhein-Westfalen",
    "wof:name":"Automaten-service Camatec Gmbh",
    "wof:placetype":"venue"
},
  "geometry": {"coordinates":[7.229225,51.469517],"type":"Point"}
}