{
  "type": "Feature",
  "properties": {
    "iso:country":"DE",
    "sg:address":"Ansbacher Str. 16",
    "sg:city":"Berlin",
    "sg:postcode":"10787",
    "sg:province":"Berlin",
    "wof:name":"Vdeb Verband Der Edv-berater E. V.",
    "wof:placetype":"venue"
},
  "geometry": {"coordinates":[13.342451,52.503395],"type":"Point"}
}