{
  "type": "Feature",
  "properties": {
    "iso:country":"DE",
    "sg:address":"Am Rathaus 9",
    "sg:city":"Ronnenberg",
    "sg:phone":"+49 511/432041",
    "sg:postcode":"30952",
    "sg:province":"Niedersachsen",
    "wof:name":"Dental-labor M\u00fcller E. Kfm.",
    "wof:placetype":"venue"
},
  "geometry": {"coordinates":[9.6643676758,52.3417701721],"type":"Point"}
}