{
  "type": "Feature",
  "properties": {
    "iso:country":"DE",
    "sg:address":"Markusstr. 21",
    "sg:city":"Dortmund",
    "sg:phone":"+49 231/774348",
    "sg:postcode":"44265",
    "sg:province":"Nordrhein-Westfalen",
    "wof:name":"Karl-heinz Thimm",
    "wof:placetype":"venue"
},
  "geometry": {"coordinates":[7.491494,51.426491],"type":"Point"}
}