{
  "type": "Feature",
  "properties": {
    "iso:country":"DE",
    "sg:address":"Karl-Liebknecht-Str. 94",
    "sg:city":"Cottbus",
    "sg:postcode":"03046",
    "sg:province":"Brandenburg",
    "wof:name":"L. Zimmermann",
    "wof:placetype":"venue"
},
  "geometry": {"coordinates":[14.3177585602,51.7566871643],"type":"Point"}
}