{
  "type": "Feature",
  "properties": {
    "iso:country":"DE",
    "sg:address":"M\u00fcllerstr. 9",
    "sg:city":"Apolda",
    "sg:phone":"+49 3644/619977",
    "sg:postcode":"99510",
    "sg:province":"Th\u00fcringen",
    "wof:name":"Frank Siebert",
    "wof:placetype":"venue"
},
  "geometry": {"coordinates":[11.5069084167,51.0208129883],"type":"Point"}
}