{
  "type": "Feature",
  "properties": {
    "iso:country":"DE",
    "sg:address":"Wellinghofer Str. 166",
    "sg:city":"Dortmund",
    "sg:postcode":"44263",
    "sg:province":"Nordrhein-Westfalen",
    "wof:name":"H & T Hoch & Tiefbau Gmbh",
    "wof:placetype":"venue"
},
  "geometry": {"coordinates":[7.4939808846,51.478012085],"type":"Point"}
}