{
  "type": "Feature",
  "properties": {
    "iso:country":"DE",
    "sg:address":"M\u00fchlbachstr. 17",
    "sg:city":"Freilassing",
    "sg:phone":"+49 8654/2595",
    "sg:postcode":"83395",
    "sg:province":"Bayern",
    "wof:name":"Rudolf Kaiser Holzwaren",
    "wof:placetype":"venue"
},
  "geometry": {"coordinates":[12.984943,47.837029],"type":"Point"}
}