{
  "type": "Feature",
  "properties": {
    "iso:country":"DE",
    "sg:address":"Ulmer Str. 18",
    "sg:city":"Leonberg",
    "sg:phone":"+49 7152/71198",
    "sg:postcode":"71229",
    "sg:province":"Baden-W\u00fcrttemberg",
    "wof:name":"Schweizer Fliesen Und Natursteine Gmbh",
    "wof:placetype":"venue"
},
  "geometry": {"coordinates":[9.0277576447,48.7876701355],"type":"Point"}
}