{
  "type": "Feature",
  "properties": {
    "iso:country":"DE",
    "sg:address":"Lange Str. 57",
    "sg:city":"B\u00fcckeburg",
    "sg:phone":"+49 5722/21431",
    "sg:postcode":"31675",
    "sg:province":"Niedersachsen",
    "wof:name":"Koulen",
    "wof:placetype":"venue"
},
  "geometry": {"coordinates":[9.048746,52.260536],"type":"Point"}
}