{
  "type": "Feature",
  "properties": {
    "iso:country":"DE",
    "sg:address":"Bachstr. 1",
    "sg:city":"Br\u00fccktal",
    "sg:phone":"+49 2692/205",
    "sg:postcode":"53539",
    "sg:province":"Rheinland-Pfalz",
    "wof:name":"Josef Theisen Gmbh & Co.",
    "wof:placetype":"venue"
},
  "geometry": {"coordinates":[6.9815349579,50.3170166016],"type":"Point"}
}