{
  "type": "Feature",
  "properties": {
    "iso:country":"DE",
    "sg:address":"St.-Leoner-Str. 38",
    "sg:city":"Neulu\u00dfheim",
    "sg:phone":"+49 6205/31516",
    "sg:postcode":"68809",
    "sg:province":"Baden-W\u00fcrttemberg",
    "wof:name":"W. Schwechheimer",
    "wof:placetype":"venue"
},
  "geometry": {"coordinates":[8.526604,49.29277],"type":"Point"}
}