{
  "type": "Feature",
  "properties": {
    "iso:country":"DE",
    "sg:address":"Neumarkter Str. 3",
    "sg:city":"Gangkofen",
    "sg:phone":"+49 8722/94970",
    "sg:postcode":"84140",
    "sg:province":"Bayern",
    "wof:name":"Bay Wa Ag",
    "wof:placetype":"venue"
},
  "geometry": {"coordinates":[12.563378,48.437107],"type":"Point"}
}