{
  "type": "Feature",
  "properties": {
    "iso:country":"DE",
    "sg:address":"Hopfenweg 7",
    "sg:city":"G\u00fctersloh",
    "sg:phone":"+49 5241/47554",
    "sg:postcode":"33334",
    "sg:province":"Nordrhein-Westfalen",
    "wof:name":"Kurt Br\u00f6del Inh. Karl L\u00f6seke",
    "wof:placetype":"venue"
},
  "geometry": {"coordinates":[8.429897,51.876633],"type":"Point"}
}