{
  "type": "Feature",
  "properties": {
    "iso:country":"DE",
    "sg:address":"Schulstr. 2",
    "sg:city":"Schwalbach",
    "sg:phone":"+49 6196/86085",
    "sg:postcode":"65824",
    "sg:province":"Hessen",
    "wof:name":"Historisches Rathaus",
    "wof:placetype":"venue"
},
  "geometry": {"coordinates":[6.811275959,49.2998275757],"type":"Point"}
}