{
  "type": "Feature",
  "properties": {
    "iso:country":"DE",
    "sg:address":"Poststr. 18",
    "sg:city":"Uhldingen-M\u00fchlhofen",
    "sg:phone":"+49 7556/6741",
    "sg:postcode":"88690",
    "sg:province":"Baden-W\u00fcrttemberg",
    "wof:name":"Pension Zimmermann",
    "wof:placetype":"venue"
},
  "geometry": {"coordinates":[9.233672142,47.7244873047],"type":"Point"}
}