{
  "type": "Feature",
  "properties": {
    "iso:country":"DE",
    "sg:address":"Klingenhagen 39",
    "sg:city":"Sassenberg",
    "sg:phone":"+49 2583/93300",
    "sg:postcode":"48336",
    "sg:province":"Nordrhein-Westfalen",
    "wof:name":"Druckhaus Krimphoff Verwaltungsgesellschaft Mbh",
    "wof:placetype":"venue"
},
  "geometry": {"coordinates":[8.044495,51.993755],"type":"Point"}
}