{
  "type": "Feature",
  "properties": {
    "iso:country":"DE",
    "sg:address":"Innstr. 36",
    "sg:city":"Mannheim",
    "sg:phone":"+49 621/859071",
    "sg:postcode":"68199",
    "sg:province":"Baden-W\u00fcrttemberg",
    "wof:name":"Max Erdmann & Schneider",
    "wof:placetype":"venue"
},
  "geometry": {"coordinates":[8.5093317032,49.4469985962],"type":"Point"}
}