{
  "type": "Feature",
  "properties": {
    "iso:country":"DE",
    "sg:address":"J\u00fcterboger Str. 16",
    "sg:city":"Dahme",
    "sg:phone":"+49 35451/405",
    "sg:postcode":"15936",
    "sg:province":"Brandenburg",
    "wof:name":"B. Fahr",
    "wof:placetype":"venue"
},
  "geometry": {"coordinates":[13.4204139709,51.868473053],"type":"Point"}
}