{
  "type": "Feature",
  "properties": {
    "iso:country":"DE",
    "sg:address":"Neu\u00f6ttinger Str. 68 B",
    "sg:city":"Alt\u00f6tting",
    "sg:phone":"+49 8671/71616",
    "sg:postcode":"84503",
    "sg:province":"Bayern",
    "wof:name":"Film-casino Kino 13",
    "wof:placetype":"venue"
},
  "geometry": {"coordinates":[12.687111,48.234402],"type":"Point"}
}