{
  "type": "Feature",
  "properties": {
    "iso:country":"DE",
    "sg:address":"Formesstr. 49",
    "sg:city":"K\u00f6ln",
    "sg:phone":"+49 221/622044",
    "sg:postcode":"51063",
    "sg:province":"Nordrhein-Westfalen",
    "wof:name":"Gebr\u00fcder Sartory Gmbh",
    "wof:placetype":"venue"
},
  "geometry": {"coordinates":[6.9992880821,50.9620475769],"type":"Point"}
}