{
  "type": "Feature",
  "properties": {
    "iso:country":"DE",
    "sg:address":"Barbyer Str. 8a",
    "sg:city":"Sch\u00f6nebeck",
    "sg:phone":"+49 3928/400625",
    "sg:postcode":"39218",
    "sg:province":"Sachsen-Anhalt",
    "wof:name":"Imbi\u00dfgastst\u00e4tte Zur Kegelbahn Inh. Helga Stracke",
    "wof:placetype":"venue"
},
  "geometry": {"coordinates":[11.7486057281,52.018081665],"type":"Point"}
}