{
  "type": "Feature",
  "properties": {
    "iso:country":"DE",
    "sg:address":"Elkan-Naumburg-Str. 37",
    "sg:city":"Treuchtlingen",
    "sg:phone":"+49 9142/8050",
    "sg:postcode":"91757",
    "sg:province":"Bayern",
    "wof:name":"Kb Kunststoffbeschichtung Gmbh",
    "wof:placetype":"venue"
},
  "geometry": {"coordinates":[10.911409,48.964741],"type":"Point"}
}