{
  "type": "Feature",
  "properties": {
    "iso:country":"DE",
    "sg:address":"Steinbachstr. 10",
    "sg:city":"Altom\u00fcnster",
    "sg:phone":"+49 8258/481",
    "sg:postcode":"85250",
    "sg:province":"Bayern",
    "wof:name":"Martin Asam",
    "wof:placetype":"venue"
},
  "geometry": {"coordinates":[11.187783,48.349998],"type":"Point"}
}