{
  "type": "Feature",
  "properties": {
    "iso:country":"DE",
    "sg:address":"Herbststr. 7",
    "sg:city":"K\u00f6nigsbrunn",
    "sg:phone":"+49 8231/605929",
    "sg:postcode":"86343",
    "sg:province":"Bayern",
    "wof:name":"Restaurant Paranha",
    "wof:placetype":"venue"
},
  "geometry": {"coordinates":[10.8925561905,48.274848938],"type":"Point"}
}