{
  "type": "Feature",
  "properties": {
    "iso:country":"DE",
    "sg:address":"R\u00f6ttenbacher Str. 6",
    "sg:city":"M\u00f6hrendorf",
    "sg:phone":"+49 9133/4688",
    "sg:postcode":"91096",
    "sg:province":"Bayern",
    "wof:name":"H. Polster",
    "wof:placetype":"venue"
},
  "geometry": {"coordinates":[11.0044336319,49.6515388489],"type":"Point"}
}