{
  "type": "Feature",
  "properties": {
    "iso:country":"DE",
    "sg:address":"Vordere Dorfstr. 48",
    "sg:city":"Breitenbach",
    "sg:phone":"+49 34658/21314",
    "sg:postcode":"06528",
    "sg:province":"Sachsen-Anhalt",
    "wof:name":"Deutsches Haus",
    "wof:placetype":"venue"
},
  "geometry": {"coordinates":[11.294839859,51.42237854],"type":"Point"}
}