{
  "type": "Feature",
  "properties": {
    "iso:country":"DE",
    "sg:address":"Georgstr. 8 A",
    "sg:city":"Hannover",
    "sg:phone":"+49 511/363471",
    "sg:postcode":"30159",
    "sg:province":"Niedersachsen",
    "wof:name":"J. H. Bencke-verm\u00f6gensver- Verwaltungs Kg",
    "wof:placetype":"venue"
},
  "geometry": {"coordinates":[9.7351179123,52.3750953674],"type":"Point"}
}