{
  "type": "Feature",
  "properties": {
    "iso:country":"DE",
    "sg:address":"Ratsm\u00fchlendamm 34",
    "sg:city":"Hamburg",
    "sg:phone":"+49 40/50022333",
    "sg:postcode":"22335",
    "sg:province":"Hamburg",
    "wof:name":"Schuster",
    "wof:placetype":"venue"
},
  "geometry": {"coordinates":[10.022397,53.626781],"type":"Point"}
}