{
  "type": "Feature",
  "properties": {
    "iso:country":"DE",
    "sg:address":"Beethovenstr. 31",
    "sg:city":"Keltern",
    "sg:phone":"+49 7236/8473",
    "sg:postcode":"75210",
    "sg:province":"Baden-W\u00fcrttemberg",
    "wof:name":"G. Knaack Dolmetscherin U. \u00dcbersetzerin",
    "wof:placetype":"venue"
},
  "geometry": {"coordinates":[8.605469,48.890091],"type":"Point"}
}