{
  "type": "Feature",
  "properties": {
    "iso:country":"DE",
    "sg:address":"Castroper Str. 164",
    "sg:city":"Datteln",
    "sg:phone":"+49 2363/62737",
    "sg:postcode":"45711",
    "sg:province":"Nordrhein-Westfalen",
    "wof:name":"Dea Tankstelle",
    "wof:placetype":"venue"
},
  "geometry": {"coordinates":[7.3335800171,51.6404266357],"type":"Point"}
}