{
  "type": "Feature",
  "properties": {
    "iso:country":"DE",
    "sg:address":"Nebraer Str. 17",
    "sg:city":"Querfurt",
    "sg:postcode":"06268",
    "sg:province":"Sachsen-Anhalt",
    "wof:name":"Global-bau Gmbh",
    "wof:placetype":"venue"
},
  "geometry": {"coordinates":[11.598067,51.376869],"type":"Point"}
}