{
  "type": "Feature",
  "properties": {
    "iso:country":"DE",
    "sg:address":"Wiesenweg 12",
    "sg:city":"Mesenich",
    "sg:phone":"+49 2673/4574",
    "sg:postcode":"56820",
    "sg:province":"Rheinland-Pfalz",
    "wof:name":"Franz Dernst Weinanbau",
    "wof:placetype":"venue"
},
  "geometry": {"coordinates":[7.1947689056,50.1019897461],"type":"Point"}
}