{
  "type": "Feature",
  "properties": {
    "iso:country":"DE",
    "sg:address":"Widenmayerstr. 52",
    "sg:city":"M\u00fcnchen",
    "sg:postcode":"80538",
    "sg:province":"Bayern",
    "wof:name":"Kiefer & Rauch Gastronomie Gmbh",
    "wof:placetype":"venue"
},
  "geometry": {"coordinates":[11.5970106125,48.1495666504],"type":"Point"}
}