{
  "type": "Feature",
  "properties": {
    "iso:country":"DE",
    "sg:address":"An der Mauer 7",
    "sg:city":"Warburg",
    "sg:phone":"+49 5641/8748",
    "sg:postcode":"34414",
    "sg:province":"Nordrhein-Westfalen",
    "wof:name":"Max Mutz",
    "wof:placetype":"venue"
},
  "geometry": {"coordinates":[9.150762558,51.4865074158],"type":"Point"}
}