{
  "type": "Feature",
  "properties": {
    "iso:country":"DE",
    "sg:address":"Rathausstr. 8",
    "sg:city":"Mainhardt",
    "sg:phone":"+49 7903/2379",
    "sg:postcode":"74535",
    "sg:province":"Baden-W\u00fcrttemberg",
    "wof:name":"Helmut Phillipp",
    "wof:placetype":"venue"
},
  "geometry": {"coordinates":[9.570291,49.102837],"type":"Point"}
}