{
  "type": "Feature",
  "properties": {
    "iso:country":"DE",
    "sg:address":"Bruchwitzstr. 30",
    "sg:city":"Berlin",
    "sg:phone":"+49 30/76680085",
    "sg:postcode":"12247",
    "sg:province":"Berlin",
    "wof:name":"Glaserei Maa\u00dfen Gmbh",
    "wof:placetype":"venue"
},
  "geometry": {"coordinates":[13.3496837616,52.436920166],"type":"Point"}
}