{
  "type": "Feature",
  "properties": {
    "iso:country":"DE",
    "sg:address":"Kleinstr. 3",
    "sg:city":"Karlskron",
    "sg:phone":"+49 8450/630",
    "sg:postcode":"85123",
    "sg:province":"Bayern",
    "wof:name":"Alois Stoll",
    "wof:placetype":"venue"
},
  "geometry": {"coordinates":[11.41131,48.677906],"type":"Point"}
}