{
  "type": "Feature",
  "properties": {
    "iso:country":"DE",
    "sg:address":"Leopoldstr. 208",
    "sg:city":"M\u00fcnchen",
    "sg:phone":"+49 89/3609020",
    "sg:postcode":"80804",
    "sg:province":"Bayern",
    "wof:name":"C. A. Lorenz",
    "wof:placetype":"venue"
},
  "geometry": {"coordinates":[11.585788,48.175644],"type":"Point"}
}