{
  "type": "Feature",
  "properties": {
    "iso:country":"DE",
    "sg:address":"Schanze 4",
    "sg:city":"Bornhagen",
    "sg:postcode":"37318",
    "sg:province":"Th\u00fcringen",
    "wof:name":"Imo-bau Immobilien Gmbh",
    "wof:placetype":"venue"
},
  "geometry": {"coordinates":[9.941399,51.342777],"type":"Point"}
}