{
  "type": "Feature",
  "properties": {
    "iso:country":"DE",
    "sg:address":"Staufenstr. 17a",
    "sg:city":"Kelkheim",
    "sg:phone":"+49 6195/6813",
    "sg:postcode":"65779",
    "sg:province":"Hessen",
    "wof:name":"Senex Export Und Import Handels Gmbh",
    "wof:placetype":"venue"
},
  "geometry": {"coordinates":[8.424785614,50.1459541321],"type":"Point"}
}