{
  "type": "Feature",
  "properties": {
    "iso:country":"DE",
    "sg:address":"Th\u00e4lmannstr. 2",
    "sg:city":"Bernsbach",
    "sg:phone":"+49 3774/62947",
    "sg:postcode":"08315",
    "sg:province":"Sachsen",
    "wof:name":"Matthias Fischer",
    "wof:placetype":"venue"
},
  "geometry": {"coordinates":[12.7697095871,50.5770797729],"type":"Point"}
}