{
  "type": "Feature",
  "properties": {
    "iso:country":"DE",
    "sg:address":"Lange Str. 9",
    "sg:city":"Finsterwalde",
    "sg:postcode":"03238",
    "sg:province":"Brandenburg",
    "wof:name":"E. Hoffmann",
    "wof:placetype":"venue"
},
  "geometry": {"coordinates":[13.716622,51.625801],"type":"Point"}
}