{
  "type": "Feature",
  "properties": {
    "iso:country":"DE",
    "sg:address":"Drosendorfer Str. 24",
    "sg:city":"Sche\u00dflitz",
    "sg:phone":"+49 9542/516",
    "sg:postcode":"96110",
    "sg:province":"Bayern",
    "wof:name":"Brauerei Georg Gerner",
    "wof:placetype":"venue"
},
  "geometry": {"coordinates":[11.000849,49.959499],"type":"Point"}
}