{
  "type": "Feature",
  "properties": {
    "iso:country":"DE",
    "sg:address":"Am Schaumberg",
    "sg:city":"Tholey",
    "sg:phone":"+49 6853/2271",
    "sg:postcode":"66636",
    "sg:province":"Saarland",
    "wof:name":"Jugendg\u00e4stehaus",
    "wof:placetype":"venue"
},
  "geometry": {"coordinates":[7.0363101959,49.4842529297],"type":"Point"}
}