{
  "type": "Feature",
  "properties": {
    "iso:country":"DE",
    "sg:address":"Weidenallee 12",
    "sg:city":"Hamburg",
    "sg:phone":"+49 40/53301840",
    "sg:postcode":"20357",
    "sg:province":"Hamburg",
    "wof:name":"W(x)m / Wosgien-cross-media",
    "wof:placetype":"venue"
},
  "geometry": {"coordinates":[9.9653453827,53.566783905],"type":"Point"}
}