{
  "type": "Feature",
  "properties": {
    "iso:country":"DE",
    "sg:address":"Dresdner Str. 301",
    "sg:city":"Freital",
    "sg:phone":"+49 351/648040",
    "sg:postcode":"01705",
    "sg:province":"Sachsen",
    "wof:name":"Wasserversorgung Wei\u00dferitzgruppe Gmbh",
    "wof:placetype":"venue"
},
  "geometry": {"coordinates":[13.6444826126,50.9893875122],"type":"Point"}
}