{
  "type": "Feature",
  "properties": {
    "iso:country":"DE",
    "sg:address":"August-Wolff-Str. 9",
    "sg:city":"Wiesbaden",
    "sg:phone":"+49 611/601957",
    "sg:postcode":"65203",
    "sg:province":"Hessen",
    "wof:name":"Rosemarie Beard",
    "wof:placetype":"venue"
},
  "geometry": {"coordinates":[8.24054,50.04583],"type":"Point"}
}