{
  "type": "Feature",
  "properties": {
    "iso:country":"DE",
    "sg:address":"Brucknerstr. 27",
    "sg:city":"Eisenberg",
    "sg:phone":"+49 6351/6970",
    "sg:postcode":"67304",
    "sg:province":"Rheinland-Pfalz",
    "wof:name":"T. Fl\u00f6rchinger",
    "wof:placetype":"venue"
},
  "geometry": {"coordinates":[8.0389766693,49.5516738892],"type":"Point"}
}