{
  "type": "Feature",
  "properties": {
    "iso:country":"DE",
    "sg:address":"Keltenweg 20",
    "sg:city":"Bonn",
    "sg:phone":"+49 228/670630",
    "sg:postcode":"53117",
    "sg:province":"Nordrhein-Westfalen",
    "wof:name":"C. Esch",
    "wof:placetype":"venue"
},
  "geometry": {"coordinates":[7.087806,50.755806],"type":"Point"}
}