{
  "type": "Feature",
  "properties": {
    "iso:country":"DE",
    "sg:address":"Kreuzgasse 12",
    "sg:city":"Haiger",
    "sg:phone":"+49 2773/1446",
    "sg:postcode":"35708",
    "sg:province":"Hessen",
    "wof:name":"Helmut Kirchner Masseur",
    "wof:placetype":"venue"
},
  "geometry": {"coordinates":[8.204829,50.742874],"type":"Point"}
}