{
  "type": "Feature",
  "properties": {
    "iso:country":"DE",
    "sg:address":"Braunser Hammerweg 19",
    "sg:city":"Bad Arolsen",
    "sg:postcode":"34454",
    "sg:province":"Hessen",
    "wof:name":"Erich Sch\u00e4fer",
    "wof:placetype":"venue"
},
  "geometry": {"coordinates":[9.03061,51.348358],"type":"Point"}
}