{
  "type": "Feature",
  "properties": {
    "iso:country":"DE",
    "sg:address":"Westiger Str. 34",
    "sg:city":"Altena",
    "sg:phone":"+49 2352/21799",
    "sg:postcode":"58762",
    "sg:province":"Nordrhein-Westfalen",
    "wof:name":"S. Schomann Praxis F\u00fcr Krankengymnastik",
    "wof:placetype":"venue"
},
  "geometry": {"coordinates":[7.690594,51.300278],"type":"Point"}
}