{
  "type": "Feature",
  "properties": {
    "iso:country":"DE",
    "sg:address":"M\u00fcnchener Str. 3",
    "sg:city":"Oberpframmern",
    "sg:phone":"+49 8093/5102",
    "sg:postcode":"85667",
    "sg:province":"Bayern",
    "wof:name":"Felix Suchanek",
    "wof:placetype":"venue"
},
  "geometry": {"coordinates":[11.812686,48.022038],"type":"Point"}
}