{
  "type": "Feature",
  "properties": {
    "iso:country":"DE",
    "sg:address":"Am G\u00fcterbahnhof",
    "sg:city":"Dillenburg",
    "sg:postcode":"35683",
    "sg:province":"Hessen",
    "wof:name":"Wendel Verwaltungs Gmbh",
    "wof:placetype":"venue"
},
  "geometry": {"coordinates":[8.29473,50.730873],"type":"Point"}
}