{
  "type": "Feature",
  "properties": {
    "iso:country":"DE",
    "sg:address":"Obere Langgasse 40",
    "sg:city":"Speyer",
    "sg:phone":"+49 6232/76026",
    "sg:postcode":"67346",
    "sg:province":"Rheinland-Pfalz",
    "wof:name":"Landwirtschaftliche Unter- Suchungs- Und Forschungs-",
    "wof:placetype":"venue"
},
  "geometry": {"coordinates":[8.4233140945,49.3184585571],"type":"Point"}
}