{
  "type": "Feature",
  "properties": {
    "iso:country":"DE",
    "sg:address":"Hansaring 30",
    "sg:city":"Wesel",
    "sg:phone":"+49 281/28686",
    "sg:postcode":"46483",
    "sg:province":"Nordrhein-Westfalen",
    "wof:name":"Warthuysen Und Otten Rechtsanw\u00e4lte",
    "wof:placetype":"venue"
},
  "geometry": {"coordinates":[6.6078038216,51.65782547],"type":"Point"}
}