{
  "type": "Feature",
  "properties": {
    "iso:country":"DE",
    "sg:address":"Am Lindchen 33",
    "sg:city":"K\u00fcrten",
    "sg:postcode":"51515",
    "sg:province":"Nordrhein-Westfalen",
    "wof:name":"E. Con Gesellschaft F\u00fcr Innovative Beratung Mbh",
    "wof:placetype":"venue"
},
  "geometry": {"coordinates":[7.2616558075,51.0567512512],"type":"Point"}
}