{
  "type": "Feature",
  "properties": {
    "iso:country":"DE",
    "sg:address":"Charlottenstr. 22",
    "sg:city":"Stuttgart",
    "sg:phone":"+49 711/239920",
    "sg:postcode":"70182",
    "sg:province":"Baden-W\u00fcrttemberg",
    "wof:name":"W\u00fcterich Und Breucker Rechtsanw\u00e4lte",
    "wof:placetype":"venue"
},
  "geometry": {"coordinates":[9.185749054,48.7739906311],"type":"Point"}
}