{
  "type": "Feature",
  "properties": {
    "iso:country":"DE",
    "sg:address":"Wiflingshauser Str. 83",
    "sg:city":"Esslingen",
    "sg:phone":"+49 711/371673",
    "sg:postcode":"73732",
    "sg:province":"Baden-W\u00fcrttemberg",
    "wof:name":"Paul Scholl Verlagsvertreter",
    "wof:placetype":"venue"
},
  "geometry": {"coordinates":[9.3311815262,48.755645752],"type":"Point"}
}