{
  "type": "Feature",
  "properties": {
    "iso:country":"DE",
    "sg:address":"Dorfstr. 17",
    "sg:city":"Enge-Sande",
    "sg:phone":"+49 4662/3892",
    "sg:postcode":"25917",
    "sg:province":"Schleswig-Holstein",
    "wof:name":"S\u00f6nke S\u00f6nksen",
    "wof:placetype":"venue"
},
  "geometry": {"coordinates":[8.976323,54.726692],"type":"Point"}
}