{
  "type": "Feature",
  "properties": {
    "iso:country":"DE",
    "sg:address":"Schlo\u00dfstr. 1",
    "sg:city":"Neustrelitz",
    "sg:phone":"+49 3981/205386",
    "sg:postcode":"17235",
    "sg:province":"Mecklenburg-Vorpommern",
    "wof:name":"Schlo\u00dfkeller",
    "wof:placetype":"venue"
},
  "geometry": {"coordinates":[13.0617818832,53.3627090454],"type":"Point"}
}