{
  "type": "Feature",
  "properties": {
    "iso:country":"DE",
    "sg:address":"Paul-Hessemer-Str. 2 1/10",
    "sg:city":"R\u00fcsselsheim",
    "sg:phone":"+49 6142/62673",
    "sg:postcode":"65428",
    "sg:province":"Hessen",
    "wof:name":"Katholisches Pfarramt St. Joseph",
    "wof:placetype":"venue"
},
  "geometry": {"coordinates":[8.4099397659,49.9800987244],"type":"Point"}
}