{
  "type": "Feature",
  "properties": {
    "iso:country":"DE",
    "sg:address":"Falkensteinstr. 7",
    "sg:city":"Glottertal",
    "sg:phone":"+49 7684/1097",
    "sg:postcode":"79286",
    "sg:province":"Baden-W\u00fcrttemberg",
    "wof:name":"Ms Holzvermittlung Gmbh",
    "wof:placetype":"venue"
},
  "geometry": {"coordinates":[7.946712,48.048367],"type":"Point"}
}