{
  "type": "Feature",
  "properties": {
    "iso:country":"DE",
    "sg:address":"Am Tiergarten 63",
    "sg:city":"Aurich",
    "sg:phone":"+49 4941/97970",
    "sg:postcode":"26603",
    "sg:province":"Niedersachsen",
    "wof:name":"Dirk Romanee\u00dfen E. K.",
    "wof:placetype":"venue"
},
  "geometry": {"coordinates":[7.4774270058,53.4823226929],"type":"Point"}
}