{
  "type": "Feature",
  "properties": {
    "iso:country":"DE",
    "sg:address":"Wermerichsh\u00e4user Str. 33",
    "sg:city":"M\u00fcnnerstadt",
    "sg:phone":"+49 9766/293",
    "sg:postcode":"97702",
    "sg:province":"Bayern",
    "wof:name":"Elmar Breunig",
    "wof:placetype":"venue"
},
  "geometry": {"coordinates":[10.29974,50.23534],"type":"Point"}
}