{
  "type": "Feature",
  "properties": {
    "iso:country":"DE",
    "sg:address":"Ludgeristr. 63",
    "sg:city":"Selm",
    "sg:phone":"+49 2592/9210",
    "sg:postcode":"59379",
    "sg:province":"Nordrhein-Westfalen",
    "wof:name":"Brigitte Lorscheider Steuerberaterin Und",
    "wof:placetype":"venue"
},
  "geometry": {"coordinates":[7.4666647911,51.702167511],"type":"Point"}
}