{
  "type": "Feature",
  "properties": {
    "iso:country":"DE",
    "sg:address":"Marktrichterstrasse 30",
    "sg:city":"Waldkirchen",
    "sg:phone":"+49 8581/3909",
    "sg:postcode":"94065",
    "sg:province":"Bayern",
    "wof:name":"Ferienwohnung In Waldkirchen/ Bayerischer Wald",
    "wof:placetype":"venue"
},
  "geometry": {"coordinates":[13.614267,48.725842],"type":"Point"}
}