{
  "type": "Feature",
  "properties": {
    "iso:country":"DE",
    "sg:address":"S\u00fcdstr. 4-6",
    "sg:city":"Wieda",
    "sg:phone":"+49 5586/8010",
    "sg:postcode":"37447",
    "sg:province":"Niedersachsen",
    "wof:name":"Sachsa Verpackung Gmbh",
    "wof:placetype":"venue"
},
  "geometry": {"coordinates":[10.5898523331,51.6135368347],"type":"Point"}
}