{
  "type": "Feature",
  "properties": {
    "iso:country":"DE",
    "sg:address":"Gleiwitzstr. 267",
    "sg:city":"Dortmund",
    "sg:phone":"+49 231/233060",
    "sg:postcode":"44328",
    "sg:province":"Nordrhein-Westfalen",
    "wof:name":"B. Rausch",
    "wof:placetype":"venue"
},
  "geometry": {"coordinates":[7.5415158272,51.5526123047],"type":"Point"}
}