{
  "type": "Feature",
  "properties": {
    "iso:country":"DE",
    "sg:address":"Hildesheimer Str. 36",
    "sg:city":"Laatzen",
    "sg:postcode":"30880",
    "sg:province":"Niedersachsen",
    "wof:name":"B & S Management Gmbh",
    "wof:placetype":"venue"
},
  "geometry": {"coordinates":[9.787966,52.31815],"type":"Point"}
}