{
  "type": "Feature",
  "properties": {
    "iso:country":"DE",
    "sg:address":"Krakower Str. 38",
    "sg:city":"Gro\u00df-Wokern",
    "sg:phone":"+49 39978/51296",
    "sg:postcode":"17166",
    "sg:province":"Mecklenburg-Vorpommern",
    "wof:name":"Ingrid Kolmorgen",
    "wof:placetype":"venue"
},
  "geometry": {"coordinates":[12.4934482574,53.7483901978],"type":"Point"}
}