{
  "type": "Feature",
  "properties": {
    "iso:country":"DE",
    "sg:address":"Albecker Steige 40",
    "sg:city":"Ulm",
    "sg:phone":"+49 731/9217075",
    "sg:postcode":"89075",
    "sg:province":"Baden-W\u00fcrttemberg",
    "wof:name":"Sunsystems Heinz Burkhardt",
    "wof:placetype":"venue"
},
  "geometry": {"coordinates":[10.002913475,48.4146614075],"type":"Point"}
}