{
  "type": "Feature",
  "properties": {
    "iso:country":"DE",
    "sg:address":"Rinderbacher Gasse 13",
    "sg:city":"Schw\u00e4bisch Gm\u00fcnd",
    "sg:phone":"+49 7171/64976",
    "sg:postcode":"73525",
    "sg:province":"Baden-W\u00fcrttemberg",
    "wof:name":"G\u00fcnter Thorwart",
    "wof:placetype":"venue"
},
  "geometry": {"coordinates":[9.799988,48.799931],"type":"Point"}
}