{
  "type": "Feature",
  "properties": {
    "iso:country":"DE",
    "sg:address":"Ortsstr. 34",
    "sg:city":"Dreba",
    "sg:phone":"+49 36484/22333",
    "sg:postcode":"07806",
    "sg:province":"Th\u00fcringen",
    "wof:name":"Frank Seidemann",
    "wof:placetype":"venue"
},
  "geometry": {"coordinates":[11.747051239,50.6652679443],"type":"Point"}
}