{
  "type": "Feature",
  "properties": {
    "iso:country":"DE",
    "sg:address":"Gro\u00dfe Diesdorfer Str. 52",
    "sg:city":"Magdeburg",
    "sg:phone":"+49 391/739770",
    "sg:postcode":"39110",
    "sg:province":"Sachsen-Anhalt",
    "wof:name":"Creditreform Magdeburg Harland Kg",
    "wof:placetype":"venue"
},
  "geometry": {"coordinates":[11.600661,52.129375],"type":"Point"}
}