{
  "type": "Feature",
  "properties": {
    "iso:country":"DE",
    "sg:address":"Hildesheimer Str. 27",
    "sg:city":"Hameln",
    "sg:phone":"+49 5151/13018",
    "sg:postcode":"31789",
    "sg:province":"Niedersachsen",
    "wof:name":"G\u00fcnther Meindl",
    "wof:placetype":"venue"
},
  "geometry": {"coordinates":[9.4137144089,52.1003456116],"type":"Point"}
}