{
  "type": "Feature",
  "properties": {
    "iso:country":"DE",
    "sg:address":"Rapunzelweg 33",
    "sg:city":"Ulm",
    "sg:phone":"+49 731/9386130",
    "sg:postcode":"89077",
    "sg:province":"Baden-W\u00fcrttemberg",
    "wof:name":"Dr. J\u00f6rg Hanisch Rechtsanwalt",
    "wof:placetype":"venue"
},
  "geometry": {"coordinates":[9.95911026,48.3882789612],"type":"Point"}
}