{
  "type": "Feature",
  "properties": {
    "iso:country":"DE",
    "sg:address":"Morgensternstr. 26",
    "sg:city":"Frankfurt",
    "sg:phone":"+49 69/623096",
    "sg:postcode":"60596",
    "sg:province":"Hessen",
    "wof:name":"Harald Kunze",
    "wof:placetype":"venue"
},
  "geometry": {"coordinates":[8.6783485413,50.1009674072],"type":"Point"}
}