{
  "type": "Feature",
  "properties": {
    "iso:country":"DE",
    "sg:address":"Wittmoor-S\u00fcd 102",
    "sg:city":"Rhauderfehn",
    "sg:phone":"+49 4955/1651",
    "sg:postcode":"26817",
    "sg:province":"Niedersachsen",
    "wof:name":"Welp",
    "wof:placetype":"venue"
},
  "geometry": {"coordinates":[7.500732,53.154335],"type":"Point"}
}