{
  "type": "Feature",
  "properties": {
    "iso:country":"DE",
    "sg:address":"Satower H\u00fctte",
    "sg:city":"Satow",
    "sg:postcode":"17209",
    "sg:province":"Mecklenburg-Vorpommern",
    "wof:name":"Windfeld B\u00fctow Zepkow Gmbh & Co. Erschlie\u00dfungs-",
    "wof:placetype":"venue"
},
  "geometry": {"coordinates":[12.4851,53.34623],"type":"Point"}
}