{
  "type": "Feature",
  "properties": {
    "iso:country":"DE",
    "sg:address":"Egelseestr. 5",
    "sg:city":"Ingolstadt",
    "sg:phone":"+49 841/33415",
    "sg:postcode":"85049",
    "sg:province":"Bayern",
    "wof:name":"Pr\u00f6sler Audit Ing. Gmbh",
    "wof:placetype":"venue"
},
  "geometry": {"coordinates":[11.4251117706,48.7602462769],"type":"Point"}
}