{
  "type": "Feature",
  "properties": {
    "iso:country":"DE",
    "sg:address":"Im Domstift 46 b",
    "sg:city":"Berlin",
    "sg:postcode":"12309",
    "sg:province":"Berlin",
    "wof:name":"Lci Labor Concept Ingenieur Gmbh",
    "wof:placetype":"venue"
},
  "geometry": {"coordinates":[13.41206,52.389645],"type":"Point"}
}