{
  "type": "Feature",
  "properties": {
    "iso:country":"DE",
    "sg:address":"Marktstr. 165",
    "sg:city":"Oberhausen",
    "sg:phone":"+49 208/24038",
    "sg:postcode":"46045",
    "sg:province":"Nordrhein-Westfalen",
    "wof:name":"G\u00fcnther Hirsch",
    "wof:placetype":"venue"
},
  "geometry": {"coordinates":[6.861361,51.468353],"type":"Point"}
}