{
  "type": "Feature",
  "properties": {
    "iso:country":"DE",
    "sg:address":"Buchweizenberg 30a",
    "sg:city":"Solingen",
    "sg:phone":"+49 4921/2262360",
    "sg:postcode":"42699",
    "sg:province":"Nordrhein-Westfalen",
    "wof:name":"Hallmann Werkzeugbau Gmbh",
    "wof:placetype":"venue"
},
  "geometry": {"coordinates":[7.001092,51.151779],"type":"Point"}
}