{
  "type": "Feature",
  "properties": {
    "iso:country":"DE",
    "sg:address":"Poserstr. 1",
    "sg:city":"Leipzig",
    "sg:phone":"+49 341/2313110",
    "sg:postcode":"04347",
    "sg:province":"Sachsen",
    "wof:name":"B. Riedel Und M. Schulz Gemeinschaftspraxis F\u00fcr",
    "wof:placetype":"venue"
},
  "geometry": {"coordinates":[12.422842,51.353195],"type":"Point"}
}