{
  "type": "Feature",
  "properties": {
    "iso:country":"DE",
    "sg:address":"Maria-Viktoria-Str. 15",
    "sg:city":"Baden-Baden",
    "sg:phone":"+49 7221/38182",
    "sg:postcode":"76530",
    "sg:province":"Baden-W\u00fcrttemberg",
    "wof:name":"Gilbert-versicherungsagentur",
    "wof:placetype":"venue"
},
  "geometry": {"coordinates":[8.2422885895,48.7561645508],"type":"Point"}
}