{
  "type": "Feature",
  "properties": {
    "iso:country":"DE",
    "sg:address":"Obere Vorstadt 7",
    "sg:city":"Auerbach",
    "sg:phone":"+49 9643/1382",
    "sg:postcode":"91275",
    "sg:province":"Bayern",
    "wof:name":"G\u00fcnther H. Speckner",
    "wof:placetype":"venue"
},
  "geometry": {"coordinates":[11.632585,49.69075],"type":"Point"}
}