{
  "type": "Feature",
  "properties": {
    "iso:country":"DE",
    "sg:address":"Tinnumer Str.",
    "sg:city":"Westerland",
    "sg:phone":"+49 4651/936359",
    "sg:postcode":"25980",
    "sg:province":"Schleswig-Holstein",
    "wof:name":"Haus Greth Scrabbel",
    "wof:placetype":"venue"
},
  "geometry": {"coordinates":[8.310128212,54.9030761719],"type":"Point"}
}