{
  "type": "Feature",
  "properties": {
    "iso:country":"DE",
    "sg:address":"Friedhofstr. 31",
    "sg:city":"Pfinztal",
    "sg:phone":"+49 721/469322",
    "sg:postcode":"76327",
    "sg:province":"Baden-W\u00fcrttemberg",
    "wof:name":"J\u00fcrgen Tilger",
    "wof:placetype":"venue"
},
  "geometry": {"coordinates":[8.52606,49.001366],"type":"Point"}
}