{
  "type": "Feature",
  "properties": {
    "iso:country":"DE",
    "sg:address":"Bajuwarenring 21",
    "sg:city":"Deisenhofen",
    "sg:phone":"+49 8042/4724",
    "sg:postcode":"82041",
    "sg:province":"Bayern",
    "wof:name":"Ttl Consult It Gmbh",
    "wof:placetype":"venue"
},
  "geometry": {"coordinates":[11.5959348679,48.0257911682],"type":"Point"}
}