{
  "type": "Feature",
  "properties": {
    "iso:country":"DE",
    "sg:address":"Vereinsstr. 24",
    "sg:city":"Bestwig",
    "sg:phone":"+49 2904/4333",
    "sg:postcode":"59909",
    "sg:province":"Nordrhein-Westfalen",
    "wof:name":"Manfred Burmann Masseur",
    "wof:placetype":"venue"
},
  "geometry": {"coordinates":[8.393239,51.359676],"type":"Point"}
}