{
  "type": "Feature",
  "properties": {
    "iso:country":"DE",
    "sg:address":"Lautensackstr. 33",
    "sg:city":"M\u00fcnchen",
    "sg:postcode":"80687",
    "sg:province":"Bayern",
    "wof:name":"Response Software Engieering Gmbh",
    "wof:placetype":"venue"
},
  "geometry": {"coordinates":[11.517572403,48.1365814209],"type":"Point"}
}