{
  "type": "Feature",
  "properties": {
    "iso:country":"DE",
    "sg:address":"Wiesenweg 65",
    "sg:city":"Oststeinbek",
    "sg:phone":"+49 40/7122665",
    "sg:postcode":"22113",
    "sg:province":"Schleswig-Holstein",
    "wof:name":"Friedrich Hei\u00df Architekt",
    "wof:placetype":"venue"
},
  "geometry": {"coordinates":[10.172263,53.547039],"type":"Point"}
}