{
  "type": "Feature",
  "properties": {
    "iso:country":"DE",
    "sg:address":"Ostra-Allee 10",
    "sg:city":"Dresden",
    "sg:phone":"+49 351/4919211",
    "sg:postcode":"01067",
    "sg:province":"Sachsen",
    "wof:name":"Dresden Tourist Board",
    "wof:placetype":"venue"
},
  "geometry": {"coordinates":[13.7298135757,51.0553398132],"type":"Point"}
}