{
  "type": "Feature",
  "properties": {
    "iso:country":"DE",
    "sg:address":"Ringstr. 74",
    "sg:city":"Bad Nauheim",
    "sg:phone":"+49 6032/35280",
    "sg:postcode":"61231",
    "sg:province":"Hessen",
    "wof:name":"Renate Kaczynski",
    "wof:placetype":"venue"
},
  "geometry": {"coordinates":[8.734497,50.357471],"type":"Point"}
}