{
  "type": "Feature",
  "properties": {
    "iso:country":"DE",
    "sg:address":"Kaulhausen 118",
    "sg:city":"Erkelenz",
    "sg:phone":"+49 2431/5318",
    "sg:postcode":"41812",
    "sg:province":"Nordrhein-Westfalen",
    "wof:name":"M. Zimmermann",
    "wof:placetype":"venue"
},
  "geometry": {"coordinates":[6.365989,51.082115],"type":"Point"}
}