{
  "type": "Feature",
  "properties": {
    "iso:country":"DE",
    "sg:address":"Unterzaunsbach",
    "sg:city":"Pretzfeld",
    "sg:phone":"+49 9194/76950",
    "sg:postcode":"91362",
    "sg:province":"Bayern",
    "wof:name":"Cafe Holweg",
    "wof:placetype":"venue"
},
  "geometry": {"coordinates":[11.22082901,49.7392539978],"type":"Point"}
}