{
  "type": "Feature",
  "properties": {
    "iso:country":"DE",
    "sg:address":"Rottmannsgasse 27",
    "sg:city":"Zellertal",
    "sg:phone":"+49 6355/2203",
    "sg:postcode":"67308",
    "sg:province":"Rheinland-Pfalz",
    "wof:name":"Walter Laible",
    "wof:placetype":"venue"
},
  "geometry": {"coordinates":[8.1502103806,49.6440315247],"type":"Point"}
}