{
  "type": "Feature",
  "properties": {
    "iso:country":"DE",
    "sg:address":"Horn Bad Meinberg",
    "sg:city":"Horn Bad Meinberg",
    "sg:phone":"+49 5234/3190",
    "sg:postcode":"32805",
    "sg:province":"Nordrhein-Westfalen",
    "wof:name":"Westdeutsche Landesbank Girozentr.",
    "wof:placetype":"venue"
},
  "geometry": {"coordinates":[8.98564,51.85817],"type":"Point"}
}