{
  "type": "Feature",
  "properties": {
    "iso:country":"DE",
    "sg:address":"Untere Hauptstr. 38",
    "sg:city":"Steinfeld",
    "sg:phone":"+49 6340/919240",
    "sg:postcode":"76889",
    "sg:province":"Rheinland-Pfalz",
    "wof:name":"Wolfgang M\u00fcller",
    "wof:placetype":"venue"
},
  "geometry": {"coordinates":[8.0384016037,49.0496101379],"type":"Point"}
}