{
  "type": "Feature",
  "properties": {
    "iso:country":"DE",
    "sg:address":"Lindenstr. 25",
    "sg:city":"Bremen",
    "sg:phone":"+49 421/6520505",
    "sg:postcode":"28755",
    "sg:province":"Bremen",
    "wof:name":"Petra Heitmann Ergotherapiepraxis",
    "wof:placetype":"venue"
},
  "geometry": {"coordinates":[8.607908,53.176174],"type":"Point"}
}