{
  "type": "Feature",
  "properties": {
    "iso:country":"DE",
    "sg:address":"Zobelstr. 5",
    "sg:city":"Frankfurt",
    "sg:phone":"+49 69/492899",
    "sg:postcode":"60316",
    "sg:province":"Hessen",
    "wof:name":"Frink & Hofmann",
    "wof:placetype":"venue"
},
  "geometry": {"coordinates":[8.700203,50.113258],"type":"Point"}
}