{
  "type": "Feature",
  "properties": {
    "iso:country":"DE",
    "sg:address":"Westfalenstr 96",
    "sg:city":"Essen",
    "sg:phone":"+49 201/513462",
    "sg:postcode":"45136",
    "sg:province":"Nordrhein-Westfalen",
    "wof:name":"Art Tec Plexiglas Design Westerhoff Und Fa\u00dfold Gbr",
    "wof:placetype":"venue"
},
  "geometry": {"coordinates":[7.0599589348,51.4382781982],"type":"Point"}
}