{
  "type": "Feature",
  "properties": {
    "iso:country":"DE",
    "sg:address":"Brunnengasse 2",
    "sg:city":"Bad Kissingen",
    "sg:phone":"+49 971/2357",
    "sg:postcode":"97688",
    "sg:province":"Bayern",
    "wof:name":"F. Kober",
    "wof:placetype":"venue"
},
  "geometry": {"coordinates":[10.0771360397,50.1997756958],"type":"Point"}
}