{
  "type": "Feature",
  "properties": {
    "iso:country":"DE",
    "sg:address":"Hauptstr. 39",
    "sg:city":"Bermbach",
    "sg:phone":"+49 36847/48228",
    "sg:postcode":"98587",
    "sg:province":"Th\u00fcringen",
    "wof:name":"Reiner Fleischmann",
    "wof:placetype":"venue"
},
  "geometry": {"coordinates":[10.596884,50.677322],"type":"Point"}
}