{
  "type": "Feature",
  "properties": {
    "iso:country":"DE",
    "sg:address":"Am Schlo\u00dfgraben 1",
    "sg:city":"Herzogenaurach",
    "sg:postcode":"91074",
    "sg:province":"Bayern",
    "wof:name":"Jumov Immobilien Gmbh & Co. Kg",
    "wof:placetype":"venue"
},
  "geometry": {"coordinates":[10.8809833527,49.5699424744],"type":"Point"}
}