{
  "type": "Feature",
  "properties": {
    "iso:country":"DE",
    "sg:address":"Spitalgasse 8",
    "sg:city":"W\u00fcrzburg",
    "sg:phone":"+49 931/42430",
    "sg:postcode":"97082",
    "sg:province":"Bayern",
    "wof:name":"E. Beck",
    "wof:placetype":"venue"
},
  "geometry": {"coordinates":[9.923441,49.792374],"type":"Point"}
}