{
  "type": "Feature",
  "properties": {
    "iso:country":"DE",
    "sg:address":"Solinger Str. 67",
    "sg:city":"Leverkusen",
    "sg:phone":"+49 214/21349",
    "sg:postcode":"51371",
    "sg:province":"Nordrhein-Westfalen",
    "wof:name":"Deutsche Bp Gmbh",
    "wof:placetype":"venue"
},
  "geometry": {"coordinates":[6.9536161423,51.0555801392],"type":"Point"}
}