{
  "type": "Feature",
  "properties": {
    "iso:country":"DE",
    "sg:address":"Meller Str. 197",
    "sg:city":"Osnabr\u00fcck",
    "sg:phone":"+49 541/588637",
    "sg:postcode":"49084",
    "sg:province":"Niedersachsen",
    "wof:name":"Bauernkate",
    "wof:placetype":"venue"
},
  "geometry": {"coordinates":[8.0845804214,52.256401062],"type":"Point"}
}