{
  "type": "Feature",
  "properties": {
    "iso:country":"DE",
    "sg:address":"Moorstr. 15",
    "sg:city":"Tecklenburg",
    "sg:phone":"+49 5455/1046",
    "sg:postcode":"49545",
    "sg:province":"Nordrhein-Westfalen",
    "wof:name":"Kath. \u00f6ffentliche Bibliothek St. Peter Und Paul",
    "wof:placetype":"venue"
},
  "geometry": {"coordinates":[7.746287,52.224873],"type":"Point"}
}