{
  "type": "Feature",
  "properties": {
    "iso:country":"DE",
    "sg:address":"W\u00fclfrather Str. 124",
    "sg:city":"Wuppertal",
    "sg:phone":"+49 202/309179",
    "sg:postcode":"42105",
    "sg:province":"Nordrhein-Westfalen",
    "wof:name":"Euva Gmbh",
    "wof:placetype":"venue"
},
  "geometry": {"coordinates":[7.13270998,51.2620506287],"type":"Point"}
}