{
  "type": "Feature",
  "properties": {
    "iso:country":"DE",
    "sg:address":"Am Kreuzkamp 5",
    "sg:city":"Adendorf",
    "sg:postcode":"21365",
    "sg:province":"Niedersachsen",
    "wof:name":"Golfanlage Adendorf Gary & Gail Birch Kg",
    "wof:placetype":"venue"
},
  "geometry": {"coordinates":[10.4348602295,53.2851753235],"type":"Point"}
}