{
  "type": "Feature",
  "properties": {
    "iso:country":"DE",
    "sg:address":"Gartzenweg 25",
    "sg:city":"Monheim",
    "sg:phone":"+49 2173/53783",
    "sg:postcode":"40789",
    "sg:province":"Nordrhein-Westfalen",
    "wof:name":"Erika Volkmann",
    "wof:placetype":"venue"
},
  "geometry": {"coordinates":[6.893176,51.091942],"type":"Point"}
}