{
  "type": "Feature",
  "properties": {
    "iso:country":"DE",
    "sg:address":"Kopernikusstr. 67",
    "sg:city":"Ludwigshafen",
    "sg:phone":"+49 621/697358",
    "sg:postcode":"67063",
    "sg:province":"Rheinland-Pfalz",
    "wof:name":"Chinarestaurant China-town",
    "wof:placetype":"venue"
},
  "geometry": {"coordinates":[8.4078464508,49.4923477173],"type":"Point"}
}