{
  "type": "Feature",
  "properties": {
    "iso:country":"DE",
    "sg:address":"Brunnengasse 6",
    "sg:city":"Aschaffenburg",
    "sg:phone":"+49 6021/87337",
    "sg:postcode":"63741",
    "sg:province":"Bayern",
    "wof:name":"A. Engelhard",
    "wof:placetype":"venue"
},
  "geometry": {"coordinates":[9.11307,49.974964],"type":"Point"}
}