{
  "type": "Feature",
  "properties": {
    "iso:country":"DE",
    "sg:address":"Ringstr. 12 a",
    "sg:city":"Ferschweiler",
    "sg:phone":"+49 6523/1022",
    "sg:postcode":"54668",
    "sg:province":"Rheinland-Pfalz",
    "wof:name":"W. Drees",
    "wof:placetype":"venue"
},
  "geometry": {"coordinates":[6.4043478966,49.8629684448],"type":"Point"}
}