{
  "type": "Feature",
  "properties": {
    "iso:country":"DE",
    "sg:address":"Friedrich-Ebert-Str. 102a",
    "sg:city":"Duisburg",
    "sg:phone":"+49 203/81423",
    "sg:postcode":"47119",
    "sg:province":"Nordrhein-Westfalen",
    "wof:name":"F. L\u00f6cken",
    "wof:placetype":"venue"
},
  "geometry": {"coordinates":[6.7355928421,51.4571418762],"type":"Point"}
}