{
  "type": "Feature",
  "properties": {
    "iso:country":"DE",
    "sg:address":"Pirnaer Str. 32",
    "sg:city":"Heidenau",
    "sg:phone":"+49 3529/517452",
    "sg:postcode":"01809",
    "sg:province":"Sachsen",
    "wof:name":"Eiscafe S\u00fcdpol",
    "wof:placetype":"venue"
},
  "geometry": {"coordinates":[13.874817,50.972366],"type":"Point"}
}