{
  "type": "Feature",
  "properties": {
    "iso:country":"DE",
    "sg:address":"Marlistr. 65",
    "sg:city":"L\u00fcbeck",
    "sg:phone":"+49 451/6101199",
    "sg:postcode":"23566",
    "sg:province":"Schleswig-Holstein",
    "wof:name":"Marli Leiser Ergotherapeutsche Praxis",
    "wof:placetype":"venue"
},
  "geometry": {"coordinates":[10.712787,53.868057],"type":"Point"}
}