{
  "type": "Feature",
  "properties": {
    "iso:country":"DE",
    "sg:address":"Weimarer Str. 176",
    "sg:city":"Gotha",
    "sg:postcode":"99867",
    "sg:province":"Th\u00fcringen",
    "wof:name":"Herzog Gmbh",
    "wof:placetype":"venue"
},
  "geometry": {"coordinates":[10.7525596619,50.9439544678],"type":"Point"}
}