{
  "type": "Feature",
  "properties": {
    "iso:country":"DE",
    "sg:address":"Marie-Juchacz-Str. 25",
    "sg:city":"Augsburg",
    "sg:phone":"+49 821/414895",
    "sg:postcode":"86154",
    "sg:province":"Bayern",
    "wof:name":"C. Nocon",
    "wof:placetype":"venue"
},
  "geometry": {"coordinates":[10.882604,48.401855],"type":"Point"}
}