{
  "type": "Feature",
  "properties": {
    "iso:country":"DE",
    "sg:address":"Karlsruher Str. 20",
    "sg:city":"Laatzen",
    "sg:postcode":"30880",
    "sg:province":"Niedersachsen",
    "wof:name":"Serviceland Gesellschaft F\u00fcr Computerdienstleistungen Mbh",
    "wof:placetype":"venue"
},
  "geometry": {"coordinates":[9.798653,52.313847],"type":"Point"}
}