{
  "type": "Feature",
  "properties": {
    "iso:country":"DE",
    "sg:address":"Newburystr. 3b",
    "sg:city":"Braunfels",
    "sg:phone":"+49 6442/4069",
    "sg:postcode":"35619",
    "sg:province":"Hessen",
    "wof:name":"Cb-funk Rettungsteam Licher Runde Braunfels",
    "wof:placetype":"venue"
},
  "geometry": {"coordinates":[8.3989839554,50.5169677734],"type":"Point"}
}