{
  "type": "Feature",
  "properties": {
    "iso:country":"DE",
    "sg:address":"Buchnerweg 10",
    "sg:city":"Hamburg",
    "sg:phone":"+49 40/6436572",
    "sg:postcode":"22159",
    "sg:province":"Hamburg",
    "wof:name":"G. Entrich",
    "wof:placetype":"venue"
},
  "geometry": {"coordinates":[10.116194,53.601234],"type":"Point"}
}