{
  "type": "Feature",
  "properties": {
    "iso:country":"DE",
    "sg:address":"D\u00fcsseldorfer Str. 9",
    "sg:city":"M\u00fclheim",
    "sg:phone":"+49 208/480336",
    "sg:postcode":"45481",
    "sg:province":"Nordrhein-Westfalen",
    "wof:name":"Quattelbaum Verwaltungs Ohg",
    "wof:placetype":"venue"
},
  "geometry": {"coordinates":[6.879293,51.402561],"type":"Point"}
}