{
  "type": "Feature",
  "properties": {
    "iso:country":"DE",
    "sg:address":"S\u00fcdstr. 11a",
    "sg:city":"Bad Pyrmont",
    "sg:postcode":"31812",
    "sg:province":"Niedersachsen",
    "wof:name":"Kur- Und Fremdenverkehrs- F\u00f6rderungsgesellschaft",
    "wof:placetype":"venue"
},
  "geometry": {"coordinates":[9.2544260025,51.9814491272],"type":"Point"}
}