{
  "type": "Feature",
  "properties": {
    "iso:country":"DE",
    "sg:address":"Alsheimer Str.",
    "sg:city":"Gimbsheim",
    "sg:phone":"+49 6249/5814",
    "sg:postcode":"67578",
    "sg:province":"Rheinland-Pfalz",
    "wof:name":"Obst- Und Gem\u00fcsezentrale Rhein-main Eg",
    "wof:placetype":"venue"
},
  "geometry": {"coordinates":[8.3657045364,49.7765617371],"type":"Point"}
}