{
  "type": "Feature",
  "properties": {
    "iso:country":"DE",
    "sg:address":"Kettelerstr. 6",
    "sg:city":"Hopsten",
    "sg:phone":"+49 5458/93210",
    "sg:postcode":"48496",
    "sg:province":"Nordrhein-Westfalen",
    "wof:name":"Annen-apotheke",
    "wof:placetype":"venue"
},
  "geometry": {"coordinates":[7.602181,52.383102],"type":"Point"}
}