{
  "type": "Feature",
  "properties": {
    "iso:country":"DE",
    "sg:address":"S\u00fcderende 15",
    "sg:city":"Norstedt",
    "sg:phone":"+49 4843/1286",
    "sg:postcode":"25884",
    "sg:province":"Schleswig-Holstein",
    "wof:name":"Motorradhandel",
    "wof:placetype":"venue"
},
  "geometry": {"coordinates":[9.1290493011,54.5866966248],"type":"Point"}
}