{
  "type": "Feature",
  "properties": {
    "iso:country":"DE",
    "sg:address":"Markt 21",
    "sg:city":"J\u00fcchen",
    "sg:phone":"+49 2165/911229",
    "sg:postcode":"41363",
    "sg:province":"Nordrhein-Westfalen",
    "wof:name":"Diakonisches Werk",
    "wof:placetype":"venue"
},
  "geometry": {"coordinates":[6.503607,51.100189],"type":"Point"}
}