{
  "type": "Feature",
  "properties": {
    "iso:country":"DE",
    "sg:address":"Marktstr. 1",
    "sg:city":"Schee\u00dfel",
    "sg:phone":"+49 4263/3376",
    "sg:postcode":"27383",
    "sg:province":"Niedersachsen",
    "wof:name":"G. M\u00fcller",
    "wof:placetype":"venue"
},
  "geometry": {"coordinates":[9.479867,53.169098],"type":"Point"}
}