{
  "type": "Feature",
  "properties": {
    "iso:country":"DE",
    "sg:address":"Bahnhofstr. 1b",
    "sg:city":"Ha\u00dfloch",
    "sg:postcode":"67454",
    "sg:province":"Rheinland-Pfalz",
    "wof:name":"Clg Concept Leasing Gmbh",
    "wof:placetype":"venue"
},
  "geometry": {"coordinates":[8.2556991577,49.3634605408],"type":"Point"}
}