{
  "type": "Feature",
  "properties": {
    "iso:country":"DE",
    "sg:address":"Industriestr. 45",
    "sg:city":"Leopoldsh\u00f6he",
    "sg:phone":"+49 5202/5148",
    "sg:postcode":"33818",
    "sg:province":"Nordrhein-Westfalen",
    "wof:name":"Adolf Bembenek",
    "wof:placetype":"venue"
},
  "geometry": {"coordinates":[8.7125864029,51.9785232544],"type":"Point"}
}