{
  "type": "Feature",
  "properties": {
    "iso:country":"DE",
    "sg:address":"Falkensteinstr. 147",
    "sg:city":"Oberhausen",
    "sg:phone":"+49 208/653389",
    "sg:postcode":"46047",
    "sg:province":"Nordrhein-Westfalen",
    "wof:name":"Gws Grafik Werbung Gmbh",
    "wof:placetype":"venue"
},
  "geometry": {"coordinates":[6.873093,51.475239],"type":"Point"}
}