{
  "type": "Feature",
  "properties": {
    "iso:country":"DE",
    "sg:address":"Karlstr. 189",
    "sg:city":"Essen",
    "sg:phone":"+49 201/344327",
    "sg:postcode":"45329",
    "sg:province":"Nordrhein-Westfalen",
    "wof:name":"Heide-apotheke Wolf-gerhard Reitz",
    "wof:placetype":"venue"
},
  "geometry": {"coordinates":[7.017836,51.508282],"type":"Point"}
}