{
  "type": "Feature",
  "properties": {
    "iso:country":"DE",
    "sg:address":"Dorfstr. 22",
    "sg:city":"Dohren",
    "sg:phone":"+49 5962/667",
    "sg:postcode":"49770",
    "sg:province":"Niedersachsen",
    "wof:name":"Gastst\u00e4tte Heinz Spieker",
    "wof:placetype":"venue"
},
  "geometry": {"coordinates":[7.5830688477,52.6448822021],"type":"Point"}
}