{
  "type": "Feature",
  "properties": {
    "iso:country":"DE",
    "sg:address":"Wingertstr. 70/1",
    "sg:city":"Neulu\u00dfheim",
    "sg:postcode":"68809",
    "sg:province":"Baden-W\u00fcrttemberg",
    "wof:name":"Network Engineering Gmbh",
    "wof:placetype":"venue"
},
  "geometry": {"coordinates":[8.51658535,49.2896537781],"type":"Point"}
}