{
  "type": "Feature",
  "properties": {
    "iso:country":"DE",
    "sg:address":"Bahnhofstr. 44",
    "sg:city":"Neuenb\u00fcrg",
    "sg:phone":"+49 7082/2333",
    "sg:postcode":"75305",
    "sg:province":"Baden-W\u00fcrttemberg",
    "wof:name":"Red. Kurzeitung Enzkl\u00f6sterle Druckhaus M\u00fcller",
    "wof:placetype":"venue"
},
  "geometry": {"coordinates":[8.5907049179,48.8490104675],"type":"Point"}
}