{
  "type": "Feature",
  "properties": {
    "iso:country":"DE",
    "sg:address":"L\u00fcderitzer Str. 101",
    "sg:city":"Stendal",
    "sg:phone":"+49 3931/219592",
    "sg:postcode":"39576",
    "sg:province":"Sachsen-Anhalt",
    "wof:name":"Altm\u00e4rkischer Eil- Und Kurierdienst Gmbh",
    "wof:placetype":"venue"
},
  "geometry": {"coordinates":[11.847661,52.591084],"type":"Point"}
}