{
  "type": "Feature",
  "properties": {
    "iso:country":"DE",
    "sg:address":"Reuschstr. 56",
    "sg:city":"Heiningen",
    "sg:phone":"+49 7161/49088",
    "sg:postcode":"73092",
    "sg:province":"Baden-W\u00fcrttemberg",
    "wof:name":"Fritz Sitzm\u00f6bel",
    "wof:placetype":"venue"
},
  "geometry": {"coordinates":[9.6432714462,48.6548576355],"type":"Point"}
}