{
  "type": "Feature",
  "properties": {
    "iso:country":"DE",
    "sg:address":"Marktplatz 5",
    "sg:city":"Hutthurm",
    "sg:phone":"+49 8505/9403",
    "sg:postcode":"94116",
    "sg:province":"Bayern",
    "wof:name":"Ballonteam Hutthurmer",
    "wof:placetype":"venue"
},
  "geometry": {"coordinates":[13.471906662,48.6722412109],"type":"Point"}
}