{
  "type": "Feature",
  "properties": {
    "iso:country":"DE",
    "sg:address":"Scheffoldstr. 53",
    "sg:city":"Schw\u00e4bisch Gm\u00fcnd",
    "sg:phone":"+49 7171/82093",
    "sg:postcode":"73529",
    "sg:province":"Baden-W\u00fcrttemberg",
    "wof:name":"Autohaus Baier Gmbh",
    "wof:placetype":"venue"
},
  "geometry": {"coordinates":[9.830693,48.784721],"type":"Point"}
}