{
  "type": "Feature",
  "properties": {
    "iso:country":"DE",
    "sg:address":"Am Kalkofen 13",
    "sg:city":"Speyer",
    "sg:phone":"+49 6232/621162",
    "sg:postcode":"67346",
    "sg:province":"Rheinland-Pfalz",
    "wof:name":"Taxi Weber Gmbh",
    "wof:placetype":"venue"
},
  "geometry": {"coordinates":[8.4425172806,49.3236236572],"type":"Point"}
}