{
  "type": "Feature",
  "properties": {
    "iso:country":"DE",
    "sg:address":"Innsbrucker Str. 20",
    "sg:city":"Berlin",
    "sg:phone":"+49 30/8575850",
    "sg:postcode":"10825",
    "sg:province":"Berlin",
    "wof:name":"Ulrich Reisert Architekt",
    "wof:placetype":"venue"
},
  "geometry": {"coordinates":[13.34211,52.481674],"type":"Point"}
}