{
  "type": "Feature",
  "properties": {
    "iso:country":"DE",
    "sg:address":"Moselstr. 17",
    "sg:city":"Sinzig",
    "sg:phone":"+49 2642/992520",
    "sg:postcode":"53489",
    "sg:province":"Rheinland-Pfalz",
    "wof:name":"Dachsystembau",
    "wof:placetype":"venue"
},
  "geometry": {"coordinates":[7.222443,50.555424],"type":"Point"}
}