{
  "type": "Feature",
  "properties": {
    "iso:country":"DE",
    "sg:address":"Wiedm\u00fchle",
    "sg:city":"Sulzbach-Laufen",
    "sg:phone":"+49 7976/202",
    "sg:postcode":"74429",
    "sg:province":"Baden-W\u00fcrttemberg",
    "wof:name":"Hirschbach Gmbh",
    "wof:placetype":"venue"
},
  "geometry": {"coordinates":[9.8560495377,48.9408149719],"type":"Point"}
}