{
  "type": "Feature",
  "properties": {
    "iso:country":"DE",
    "sg:address":"Im G\u00e4\u00dfchen 30",
    "sg:city":"Niederkassel",
    "sg:phone":"+49 2208/910300",
    "sg:postcode":"53859",
    "sg:province":"Nordrhein-Westfalen",
    "wof:name":"Ingo Bayer Gmbh",
    "wof:placetype":"venue"
},
  "geometry": {"coordinates":[7.0631427765,50.8202934265],"type":"Point"}
}