{
  "type": "Feature",
  "properties": {
    "iso:country":"DE",
    "sg:address":"Rigipsstr. 15",
    "sg:city":"Herrenberg",
    "sg:phone":"+49 7032/78090",
    "sg:postcode":"71083",
    "sg:province":"Baden-W\u00fcrttemberg",
    "wof:name":"Kwc Deutschland Gmbh",
    "wof:placetype":"venue"
},
  "geometry": {"coordinates":[8.885228,48.576694],"type":"Point"}
}