{
  "type": "Feature",
  "properties": {
    "iso:country":"DE",
    "sg:address":"Hofer Str. 26",
    "sg:city":"Wunsiedel",
    "sg:phone":"+49 9232/70907",
    "sg:postcode":"95632",
    "sg:province":"Bayern",
    "wof:name":"Fitness-treff Impuls",
    "wof:placetype":"venue"
},
  "geometry": {"coordinates":[11.9966392517,50.0416755676],"type":"Point"}
}