{
  "type": "Feature",
  "properties": {
    "iso:country":"DE",
    "sg:address":"Elsa\u00dfstr. 17",
    "sg:city":"Aachen",
    "sg:phone":"+49 241/500977",
    "sg:postcode":"52068",
    "sg:province":"Nordrhein-Westfalen",
    "wof:name":"Schlo\u00df-stube",
    "wof:placetype":"venue"
},
  "geometry": {"coordinates":[6.113670826,50.7726516724],"type":"Point"}
}