{
  "type": "Feature",
  "properties": {
    "iso:country":"DE",
    "sg:address":"Gerhart-Hauptmann-Str. 12",
    "sg:city":"Gro\u00df-Gerau",
    "sg:phone":"+49 6150/81036",
    "sg:postcode":"64521",
    "sg:province":"Hessen",
    "wof:name":"G. Maurer",
    "wof:placetype":"venue"
},
  "geometry": {"coordinates":[8.4903097153,49.8760681152],"type":"Point"}
}