{
  "type": "Feature",
  "properties": {
    "iso:country":"DE",
    "sg:address":"Marienplatz 2",
    "sg:city":"Wittislingen",
    "sg:phone":"+49 9076/2221",
    "sg:postcode":"89426",
    "sg:province":"Bayern",
    "wof:name":"E. Mayr Steinmetz",
    "wof:placetype":"venue"
},
  "geometry": {"coordinates":[10.4154043198,48.6183853149],"type":"Point"}
}