{
  "type": "Feature",
  "properties": {
    "iso:country":"DE",
    "sg:address":"Rathausmarkt 1",
    "sg:city":"Eckernf\u00f6rde",
    "sg:phone":"+49 4351/90080",
    "sg:postcode":"24340",
    "sg:province":"Schleswig-Holstein",
    "wof:name":"J. C. Schwensen Gmbh & Co. Kg",
    "wof:placetype":"venue"
},
  "geometry": {"coordinates":[9.836769104,54.4710998535],"type":"Point"}
}