{
  "type": "Feature",
  "properties": {
    "iso:country":"DE",
    "sg:address":"Strandweg 10 b",
    "sg:city":"Schashagen",
    "sg:phone":"+49 4562/4230",
    "sg:postcode":"23730",
    "sg:province":"Schleswig-Holstein",
    "wof:name":"Rolf Heiland",
    "wof:placetype":"venue"
},
  "geometry": {"coordinates":[10.913079,54.129944],"type":"Point"}
}