{
  "type": "Feature",
  "properties": {
    "iso:country":"DE",
    "sg:address":"Wielandstr. 11",
    "sg:city":"Calw",
    "sg:phone":"+49 7051/3836",
    "sg:postcode":"75365",
    "sg:province":"Baden-W\u00fcrttemberg",
    "wof:name":"Wilhelm Dengler",
    "wof:placetype":"venue"
},
  "geometry": {"coordinates":[8.7640342712,48.7132110596],"type":"Point"}
}