{
  "type": "Feature",
  "properties": {
    "iso:country":"DE",
    "sg:address":"Lange Str. 10",
    "sg:city":"Crailsheim",
    "sg:phone":"+49 7951/42018",
    "sg:postcode":"74564",
    "sg:province":"Baden-W\u00fcrttemberg",
    "wof:name":"Optik-g\u00f6tz Gmbh",
    "wof:placetype":"venue"
},
  "geometry": {"coordinates":[10.0714836121,49.1373405457],"type":"Point"}
}