{
  "type": "Feature",
  "properties": {
    "iso:country":"DE",
    "sg:address":"Ludwig-Thoma-Str. 1",
    "sg:city":"Geiselh\u00f6ring",
    "sg:phone":"+49 9423/2460",
    "sg:postcode":"94333",
    "sg:province":"Bayern",
    "wof:name":"G. Gebe\u00dfler Rechtsanwalt",
    "wof:placetype":"venue"
},
  "geometry": {"coordinates":[12.4027252197,48.8275718689],"type":"Point"}
}