{
  "type": "Feature",
  "properties": {
    "iso:country":"DE",
    "sg:address":"Poststr. 13",
    "sg:city":"Luckenwalde",
    "sg:phone":"+49 3371/610395",
    "sg:postcode":"14943",
    "sg:province":"Brandenburg",
    "wof:name":"B. Vogel",
    "wof:placetype":"venue"
},
  "geometry": {"coordinates":[13.1695318222,52.090423584],"type":"Point"}
}