{
  "type": "Feature",
  "properties": {
    "iso:country":"DE",
    "sg:address":"M\u00fchlbachstr. 19",
    "sg:city":"Oy-Mittelberg",
    "sg:phone":"+49 8366/269",
    "sg:postcode":"87466",
    "sg:province":"Bayern",
    "wof:name":"Michael Heim",
    "wof:placetype":"venue"
},
  "geometry": {"coordinates":[10.434623,47.638771],"type":"Point"}
}