{
  "type": "Feature",
  "properties": {
    "iso:country":"DE",
    "sg:address":"Ochtruper Str. 14",
    "sg:city":"Steinfurt",
    "sg:phone":"+49 2551/4174",
    "sg:postcode":"48565",
    "sg:province":"Nordrhein-Westfalen",
    "wof:name":"Hans-rudolf Pr\u00fcmers Wirtschaftspr\u00fcfer Und",
    "wof:placetype":"venue"
},
  "geometry": {"coordinates":[7.3356528282,52.150352478],"type":"Point"}
}