{
  "type": "Feature",
  "properties": {
    "iso:country":"DE",
    "sg:address":"Schwarzwaldstr. 62",
    "sg:city":"Offenburg",
    "sg:phone":"+49 781/37781",
    "sg:postcode":"77654",
    "sg:province":"Baden-W\u00fcrttemberg",
    "wof:name":"Wilhelm Kirchner Architekt",
    "wof:placetype":"venue"
},
  "geometry": {"coordinates":[7.96041,48.461639],"type":"Point"}
}