{
  "type": "Feature",
  "properties": {
    "iso:country":"DE",
    "sg:address":"Wildbachstr. 21",
    "sg:city":"Freudenberg",
    "sg:phone":"+49 9377/440",
    "sg:postcode":"97896",
    "sg:province":"Baden-W\u00fcrttemberg",
    "wof:name":"Ottmar H\u00e4fner",
    "wof:placetype":"venue"
},
  "geometry": {"coordinates":[9.401999,49.765915],"type":"Point"}
}