{
  "type": "Feature",
  "properties": {
    "iso:country":"DE",
    "sg:address":"Hintergasse 2",
    "sg:city":"Gr\u00fcnstadt",
    "sg:phone":"+49 6359/1381",
    "sg:postcode":"67269",
    "sg:province":"Rheinland-Pfalz",
    "wof:name":"Kurt Binder",
    "wof:placetype":"venue"
},
  "geometry": {"coordinates":[8.156786,49.547611],"type":"Point"}
}