{
  "type": "Feature",
  "properties": {
    "iso:country":"DE",
    "sg:address":"Entengasse 10",
    "sg:city":"Ettlingen",
    "sg:phone":"+49 7243/16877",
    "sg:postcode":"76275",
    "sg:province":"Baden-W\u00fcrttemberg",
    "wof:name":"Ulf D. Gaubatz Rechtsanwalt",
    "wof:placetype":"venue"
},
  "geometry": {"coordinates":[8.407790184,48.9407196045],"type":"Point"}
}