{
  "type": "Feature",
  "properties": {
    "iso:country":"DE",
    "sg:address":"Karolinenstr. 7",
    "sg:city":"Ansbach",
    "sg:postcode":"91522",
    "sg:province":"Bayern",
    "wof:name":"Dr. Schuhmann Und Partner Steuerberatungsgesellschaft",
    "wof:placetype":"venue"
},
  "geometry": {"coordinates":[10.5731525421,49.2992515564],"type":"Point"}
}