{
  "type": "Feature",
  "properties": {
    "iso:country":"DE",
    "sg:address":"Oberer Ahlenbergweg 46b",
    "sg:city":"Herdecke",
    "sg:postcode":"58313",
    "sg:province":"Nordrhein-Westfalen",
    "wof:name":"Krefelder Rennbahn Gastronomie Gmbh",
    "wof:placetype":"venue"
},
  "geometry": {"coordinates":[7.462031,51.432812],"type":"Point"}
}