{
  "type": "Feature",
  "properties": {
    "iso:country":"DE",
    "sg:address":"Harmenhausen",
    "sg:city":"Berne",
    "sg:phone":"+49 4406/6866",
    "sg:postcode":"27804",
    "sg:province":"Niedersachsen",
    "wof:name":"K. Sinn",
    "wof:placetype":"venue"
},
  "geometry": {"coordinates":[8.539903,53.140488],"type":"Point"}
}