{
  "type": "Feature",
  "properties": {
    "iso:country":"DE",
    "sg:address":"Obere Kaiserstr. 238",
    "sg:city":"St. Ingbert",
    "sg:phone":"+49 6894/57480",
    "sg:postcode":"66386",
    "sg:province":"Saarland",
    "wof:name":"Altes Forsthaus",
    "wof:placetype":"venue"
},
  "geometry": {"coordinates":[7.1332621574,49.2858581543],"type":"Point"}
}