{
  "type": "Feature",
  "properties": {
    "iso:country":"DE",
    "sg:address":"Gewerbestr. 5",
    "sg:city":"Hilzingen",
    "sg:phone":"+49 7731/947064",
    "sg:postcode":"78247",
    "sg:province":"Baden-W\u00fcrttemberg",
    "wof:name":"Helmut Grison W\u00e4rme-k\u00e4lte-schallschutz",
    "wof:placetype":"venue"
},
  "geometry": {"coordinates":[8.790685,47.758926],"type":"Point"}
}