{
  "type": "Feature",
  "properties": {
    "iso:country":"DE",
    "sg:address":"Pestalozzistr. 15",
    "sg:city":"Templin",
    "sg:phone":"+49 3987/2730",
    "sg:postcode":"17268",
    "sg:province":"Brandenburg",
    "wof:name":"Kurt Schneider",
    "wof:placetype":"venue"
},
  "geometry": {"coordinates":[13.501554,53.120659],"type":"Point"}
}