{
  "type": "Feature",
  "properties": {
    "iso:country":"DE",
    "sg:address":"F\u00f6rchenholzstr. 19",
    "sg:city":"Bad T\u00f6lz",
    "sg:phone":"+49 8041/71292",
    "sg:postcode":"83646",
    "sg:province":"Bayern",
    "wof:name":"Kantschuster K\u00e4ltetechnik Gmbh",
    "wof:placetype":"venue"
},
  "geometry": {"coordinates":[11.555122,47.776573],"type":"Point"}
}