{
  "type": "Feature",
  "properties": {
    "iso:country":"DE",
    "sg:address":"Filderhauptstr. 7",
    "sg:city":"Stuttgart",
    "sg:phone":"+49 711/4570192",
    "sg:postcode":"70599",
    "sg:province":"Baden-W\u00fcrttemberg",
    "wof:name":"Fotosatz Teichmann Gmbh",
    "wof:placetype":"venue"
},
  "geometry": {"coordinates":[9.1799850464,48.7216300964],"type":"Point"}
}