{
  "type": "Feature",
  "properties": {
    "iso:country":"DE",
    "sg:address":"Albert-Einstein-Str. 5",
    "sg:city":"Limbach-Oberfrohna",
    "sg:phone":"+49 3722/92217",
    "sg:postcode":"09212",
    "sg:province":"Sachsen",
    "wof:name":"A. Saupe & Co. Gmbh",
    "wof:placetype":"venue"
},
  "geometry": {"coordinates":[12.7625198364,50.8579330444],"type":"Point"}
}