{
  "type": "Feature",
  "properties": {
    "iso:country":"DE",
    "sg:address":"Unfinden 59",
    "sg:city":"K\u00f6nigsberg",
    "sg:phone":"+49 9525/207",
    "sg:postcode":"97486",
    "sg:province":"Bayern",
    "wof:name":"E. Biedermann Elektro Artikel",
    "wof:placetype":"venue"
},
  "geometry": {"coordinates":[10.568401,50.093647],"type":"Point"}
}