{
  "type": "Feature",
  "properties": {
    "iso:country":"DE",
    "sg:address":"Angerbreite 11",
    "sg:city":"M\u00fcnsing",
    "sg:phone":"+49 8171/10344",
    "sg:postcode":"82541",
    "sg:province":"Bayern",
    "wof:name":"Sch\u00d6fmann-steuerungs- Elektronik-gmbh",
    "wof:placetype":"venue"
},
  "geometry": {"coordinates":[11.3715772629,47.8824501038],"type":"Point"}
}