{
  "type": "Feature",
  "properties": {
    "iso:country":"DE",
    "sg:address":"Steinkreuzweg5",
    "sg:city":"Alzenau",
    "sg:phone":"+49 6023/2367",
    "sg:postcode":"63755",
    "sg:province":"Bayern",
    "wof:name":"Picadero Fuente Del Gallo",
    "wof:placetype":"venue"
},
  "geometry": {"coordinates":[9.073635,50.086327],"type":"Point"}
}