{
  "type": "Feature",
  "properties": {
    "iso:country":"DE",
    "sg:address":"Landsberger Str. 155",
    "sg:city":"M\u00fcnchen",
    "sg:postcode":"80687",
    "sg:province":"Bayern",
    "wof:name":"Exigen Deutschland Gmbh",
    "wof:placetype":"venue"
},
  "geometry": {"coordinates":[11.5267086029,48.1403121948],"type":"Point"}
}