{
  "type": "Feature",
  "properties": {
    "iso:country":"DE",
    "sg:address":"J\u00e4gerhaus 34",
    "sg:city":"Gl\u00f6the",
    "sg:postcode":"39240",
    "sg:province":"Sachsen-Anhalt",
    "wof:name":"Wach- Und Schlie\u00dfgesellschaft Hablowetz & Co.",
    "wof:placetype":"venue"
},
  "geometry": {"coordinates":[11.7712001801,51.8982048035],"type":"Point"}
}