{
  "type": "Feature",
  "properties": {
    "iso:country":"DE",
    "sg:address":"Auf dem Schilde 22",
    "sg:city":"Gummersbach",
    "sg:phone":"+49 2261/74319",
    "sg:postcode":"51645",
    "sg:province":"Nordrhein-Westfalen",
    "wof:name":"Herbert Noah",
    "wof:placetype":"venue"
},
  "geometry": {"coordinates":[7.538709,50.987831],"type":"Point"}
}