{
  "type": "Feature",
  "properties": {
    "iso:country":"DE",
    "sg:address":"Frankenstr. 14",
    "sg:city":"Felsberg",
    "sg:phone":"+49 5662/6712",
    "sg:postcode":"34587",
    "sg:province":"Hessen",
    "wof:name":"Kurmed Ges. F\u00fcr Handel Und Dienstleistungen Mit",
    "wof:placetype":"venue"
},
  "geometry": {"coordinates":[9.435945,51.12764],"type":"Point"}
}