{
  "type": "Feature",
  "properties": {
    "iso:country":"DE",
    "sg:address":"Schleptruper Strang 20",
    "sg:city":"Bramsche",
    "sg:phone":"+49 251/136116",
    "sg:postcode":"49565",
    "sg:province":"Niedersachsen",
    "wof:name":"G\u00fcnter Tappe Rechtsanwalt",
    "wof:placetype":"venue"
},
  "geometry": {"coordinates":[8.0071725845,52.4107322693],"type":"Point"}
}