{
  "type": "Feature",
  "properties": {
    "iso:country":"DE",
    "sg:address":"Presseweg 6",
    "sg:city":"Kneitlingen",
    "sg:phone":"+49 5332/3547",
    "sg:postcode":"38170",
    "sg:province":"Niedersachsen",
    "wof:name":"Lindenhof Brot Und Gem\u00fcse Gmbh",
    "wof:placetype":"venue"
},
  "geometry": {"coordinates":[10.726542,52.161461],"type":"Point"}
}