{
  "type": "Feature",
  "properties": {
    "iso:country":"DE",
    "sg:address":"Eckdorfer Str. 62",
    "sg:city":"Br\u00fchl",
    "sg:phone":"+49 2232/31913",
    "sg:postcode":"50321",
    "sg:province":"Nordrhein-Westfalen",
    "wof:name":"Gasthaus Alt Eckdorf",
    "wof:placetype":"venue"
},
  "geometry": {"coordinates":[6.8954048157,50.8030662537],"type":"Point"}
}