{
  "type": "Feature",
  "properties": {
    "iso:country":"DE",
    "sg:address":"Gretelweg 10",
    "sg:city":"Leipzig",
    "sg:phone":"+49 341/8774034",
    "sg:postcode":"04277",
    "sg:province":"Sachsen",
    "wof:name":"Peter Stummer",
    "wof:placetype":"venue"
},
  "geometry": {"coordinates":[12.399556,51.30735],"type":"Point"}
}