{
  "type": "Feature",
  "properties": {
    "iso:country":"DE",
    "sg:address":"Marienstr. 53",
    "sg:city":"Braunschweig",
    "sg:phone":"+49 531/7074822",
    "sg:postcode":"38102",
    "sg:province":"Niedersachsen",
    "wof:name":"Bildings - Visual Engineering",
    "wof:placetype":"venue"
},
  "geometry": {"coordinates":[10.544296,52.263958],"type":"Point"}
}