{
  "type": "Feature",
  "properties": {
    "iso:country":"DE",
    "sg:address":"Nykoppel 2",
    "sg:city":"Kappeln",
    "sg:phone":"+49 4642/82950",
    "sg:postcode":"24376",
    "sg:province":"Schleswig-Holstein",
    "wof:name":"Klaus B\u00fchsen",
    "wof:placetype":"venue"
},
  "geometry": {"coordinates":[9.964401,54.661301],"type":"Point"}
}