{
  "type": "Feature",
  "properties": {
    "iso:country":"DE",
    "sg:address":"Grafenberger Allee 37",
    "sg:city":"D\u00fcsseldorf",
    "sg:phone":"+49 211/6801043",
    "sg:postcode":"40237",
    "sg:province":"Nordrhein-Westfalen",
    "wof:name":"Hotel Industriehof Konnertz",
    "wof:placetype":"venue"
},
  "geometry": {"coordinates":[6.7984747887,51.2298126221],"type":"Point"}
}