{
  "type": "Feature",
  "properties": {
    "iso:country":"DE",
    "sg:address":"Meister-Erwin-Str. 57",
    "sg:city":"Baden-Baden",
    "sg:phone":"+49 7223/58023",
    "sg:postcode":"76534",
    "sg:province":"Baden-W\u00fcrttemberg",
    "wof:name":"Joachim Schr\u00f6mbgens",
    "wof:placetype":"venue"
},
  "geometry": {"coordinates":[8.1728658676,48.7275352478],"type":"Point"}
}