{
  "type": "Feature",
  "properties": {
    "iso:country":"DE",
    "sg:address":"Queichheimer Hauptstr. 184",
    "sg:city":"Landau",
    "sg:phone":"+49 6341/52689",
    "sg:postcode":"76829",
    "sg:province":"Rheinland-Pfalz",
    "wof:name":"M\u00f6bel-schad Gmbh",
    "wof:placetype":"venue"
},
  "geometry": {"coordinates":[8.146935463,49.195892334],"type":"Point"}
}