{
  "type": "Feature",
  "properties": {
    "iso:country":"DE",
    "sg:address":"Zum Berggarten 24",
    "sg:city":"Kassel",
    "sg:phone":"+49 561/67121",
    "sg:postcode":"34130",
    "sg:province":"Hessen",
    "wof:name":"Hans-reinhard Klein",
    "wof:placetype":"venue"
},
  "geometry": {"coordinates":[9.4397096634,51.3217086792],"type":"Point"}
}