{
  "type": "Feature",
  "properties": {
    "iso:country":"DE",
    "sg:address":"M\u00fchlenweg 35a",
    "sg:city":"Bremen",
    "sg:postcode":"28355",
    "sg:province":"Bremen",
    "wof:name":"Hgn-beteiligungsges. Mbh",
    "wof:placetype":"venue"
},
  "geometry": {"coordinates":[8.936957,53.086391],"type":"Point"}
}