{
  "type": "Feature",
  "properties": {
    "iso:country":"DE",
    "sg:address":"Oesterfeldweg 36",
    "sg:city":"Arnsberg",
    "sg:phone":"+49 2937/6334",
    "sg:postcode":"59823",
    "sg:province":"Nordrhein-Westfalen",
    "wof:name":"Johannes Wilmes",
    "wof:placetype":"venue"
},
  "geometry": {"coordinates":[8.140029,51.400848],"type":"Point"}
}