{
  "type": "Feature",
  "properties": {
    "iso:country":"DE",
    "sg:address":"Konzilstr. 3",
    "sg:city":"Konstanz",
    "sg:phone":"+49 7531/29329",
    "sg:postcode":"78462",
    "sg:province":"Baden-W\u00fcrttemberg",
    "wof:name":"Pro Velo Inh. Christoph Riedle",
    "wof:placetype":"venue"
},
  "geometry": {"coordinates":[9.177381,47.662098],"type":"Point"}
}