{
  "type": "Feature",
  "properties": {
    "iso:country":"DE",
    "sg:address":"Gartenstr. 1",
    "sg:city":"Waldbr\u00f6l",
    "sg:phone":"+49 2291/4255",
    "sg:postcode":"51545",
    "sg:province":"Nordrhein-Westfalen",
    "wof:name":"Inno Br\u00e4ckel",
    "wof:placetype":"venue"
},
  "geometry": {"coordinates":[7.6142630577,50.8756141663],"type":"Point"}
}