{
  "type": "Feature",
  "properties": {
    "iso:country":"DE",
    "sg:address":"Am Weinberg 24",
    "sg:city":"Reiskirchen",
    "sg:phone":"+49 6401/6834",
    "sg:postcode":"35447",
    "sg:province":"Hessen",
    "wof:name":"Dieter Blei Architekt",
    "wof:placetype":"venue"
},
  "geometry": {"coordinates":[8.91707,50.564301],"type":"Point"}
}