{
  "type": "Feature",
  "properties": {
    "iso:country":"DE",
    "sg:address":"Dorfstr. 7a",
    "sg:city":"Ohlsbach",
    "sg:phone":"+49 7803/980050",
    "sg:postcode":"77797",
    "sg:province":"Baden-W\u00fcrttemberg",
    "wof:name":"Siegbert Bischler",
    "wof:placetype":"venue"
},
  "geometry": {"coordinates":[7.99505,48.432354],"type":"Point"}
}