{
  "type": "Feature",
  "properties": {
    "iso:country":"DE",
    "sg:address":"Weiherer Str. 41",
    "sg:city":"Hambr\u00fccken",
    "sg:phone":"+49 4972/557150",
    "sg:postcode":"76707",
    "sg:province":"Baden-W\u00fcrttemberg",
    "wof:name":"Linhardt & Co. Gmbh",
    "wof:placetype":"venue"
},
  "geometry": {"coordinates":[8.5516357422,49.1863212585],"type":"Point"}
}