{
  "type": "Feature",
  "properties": {
    "iso:country":"DE",
    "sg:address":"Dorfstr.",
    "sg:city":"Nunsdorf",
    "sg:phone":"+49 33731/80187",
    "sg:postcode":"15806",
    "sg:province":"Brandenburg",
    "wof:name":"Ucan Remti",
    "wof:placetype":"venue"
},
  "geometry": {"coordinates":[13.3150911331,52.2319450378],"type":"Point"}
}