{
  "type": "Feature",
  "properties": {
    "iso:country":"DE",
    "sg:address":"Triftstr. 5",
    "sg:city":"Blankenfelde",
    "sg:postcode":"15827",
    "sg:province":"Brandenburg",
    "wof:name":"Dany-w\u00e4schetrans Blankenfelde Gmbh",
    "wof:placetype":"venue"
},
  "geometry": {"coordinates":[13.3915224075,52.328125],"type":"Point"}
}