{
  "type": "Feature",
  "properties": {
    "iso:country":"DE",
    "sg:address":"Huntloser Str. 25",
    "sg:city":"D\u00f6tlingen",
    "sg:phone":"+49 4432/558",
    "sg:postcode":"27801",
    "sg:province":"Niedersachsen",
    "wof:name":"Richard Feldhaus",
    "wof:placetype":"venue"
},
  "geometry": {"coordinates":[8.356395,52.977463],"type":"Point"}
}