{
  "type": "Feature",
  "properties": {
    "iso:country":"DE",
    "sg:address":"Brauhausstr. 46",
    "sg:city":"Raguhn",
    "sg:postcode":"06779",
    "sg:province":"Sachsen-Anhalt",
    "wof:name":"Horst Globig",
    "wof:placetype":"venue"
},
  "geometry": {"coordinates":[12.290299,51.710583],"type":"Point"}
}