{
  "type": "Feature",
  "properties": {
    "iso:country":"DE",
    "sg:address":"An der Ziegelei 3",
    "sg:city":"Seesen",
    "sg:phone":"+49 5381/47019",
    "sg:postcode":"38723",
    "sg:province":"Niedersachsen",
    "wof:name":"Norbert K\u00fchnel",
    "wof:placetype":"venue"
},
  "geometry": {"coordinates":[10.169874,51.895233],"type":"Point"}
}