{
  "type": "Feature",
  "properties": {
    "iso:country":"DE",
    "sg:address":"Nideggener Str. 139",
    "sg:city":"D\u00fcren",
    "sg:phone":"+49 2421/505996",
    "sg:postcode":"52349",
    "sg:province":"Nordrhein-Westfalen",
    "wof:name":"K\u00f6nigsbacher-stuben",
    "wof:placetype":"venue"
},
  "geometry": {"coordinates":[6.489841938,50.7903671265],"type":"Point"}
}