{
  "type": "Feature",
  "properties": {
    "iso:country":"DE",
    "sg:address":"Roggensteiner Str. 7",
    "sg:city":"Emmering",
    "sg:phone":"+49 8141/6508",
    "sg:postcode":"82275",
    "sg:province":"Bayern",
    "wof:name":"Benno Euler",
    "wof:placetype":"venue"
},
  "geometry": {"coordinates":[11.282424,48.180122],"type":"Point"}
}