{
  "type": "Feature",
  "properties": {
    "iso:country":"DE",
    "sg:address":"Neue Weinsteige 47-49",
    "sg:city":"Stuttgart",
    "sg:phone":"+49 711/24897860",
    "sg:postcode":"70180",
    "sg:province":"Baden-W\u00fcrttemberg",
    "wof:name":"Reinecke New Media - Marketing & Kommunikation",
    "wof:placetype":"venue"
},
  "geometry": {"coordinates":[9.181071,48.765167],"type":"Point"}
}