{
  "type": "Feature",
  "properties": {
    "iso:country":"DE",
    "sg:address":"Hemmersbacher Str. 62",
    "sg:city":"Kerpen",
    "sg:phone":"+49 2273/1616",
    "sg:postcode":"50169",
    "sg:province":"Nordrhein-Westfalen",
    "wof:name":"Christian G\u00fcnther Ingenieur",
    "wof:placetype":"venue"
},
  "geometry": {"coordinates":[6.7106552124,50.9048957825],"type":"Point"}
}