{
  "type": "Feature",
  "properties": {
    "iso:country":"DE",
    "sg:address":"M\u00fchle 1 Waldm\u00fchle",
    "sg:city":"M\u00fclheim-K\u00e4rlich",
    "sg:phone":"+49 2630/1642",
    "sg:postcode":"56218",
    "sg:province":"Rheinland-Pfalz",
    "wof:name":"Horst Oster",
    "wof:placetype":"venue"
},
  "geometry": {"coordinates":[7.4973640442,50.3865280151],"type":"Point"}
}