{
  "type": "Feature",
  "properties": {
    "iso:country":"DE",
    "sg:address":"Turmstr. 3 a",
    "sg:city":"Herborn",
    "sg:phone":"+49 2772/3687",
    "sg:postcode":"35745",
    "sg:province":"Hessen",
    "wof:name":"Karl D\u00f6ring",
    "wof:placetype":"venue"
},
  "geometry": {"coordinates":[8.303587,50.68399],"type":"Point"}
}