{
  "type": "Feature",
  "properties": {
    "iso:country":"DE",
    "sg:address":"Am Oxer 24",
    "sg:city":"Harrislee",
    "sg:phone":"+49 461/74447",
    "sg:postcode":"24955",
    "sg:province":"Schleswig-Holstein",
    "wof:name":"Container-dienst Rehmke Verwaltungs Gmbh",
    "wof:placetype":"venue"
},
  "geometry": {"coordinates":[9.3693418503,54.7976608276],"type":"Point"}
}