{
  "type": "Feature",
  "properties": {
    "iso:country":"DE",
    "sg:address":"Am Rennplatz 7a",
    "sg:city":"Nettetal",
    "sg:phone":"+49 2157/125832",
    "sg:postcode":"41334",
    "sg:province":"Nordrhein-Westfalen",
    "wof:name":"Handelsvertretung Projekt Limited Inh. Magdalena Kijak",
    "wof:placetype":"venue"
},
  "geometry": {"coordinates":[6.203545,51.339977],"type":"Point"}
}