{
  "type": "Feature",
  "properties": {
    "iso:country":"DE",
    "sg:address":"Moltkestr. 15",
    "sg:city":"G\u00fctersloh",
    "sg:phone":"+49 5241/14233",
    "sg:postcode":"33330",
    "sg:province":"Nordrhein-Westfalen",
    "wof:name":"Moltke-apotheke",
    "wof:placetype":"venue"
},
  "geometry": {"coordinates":[8.376896,51.908985],"type":"Point"}
}