{
  "type": "Feature",
  "properties": {
    "iso:country":"DE",
    "sg:address":"Immendorfer Hauptstr. 1",
    "sg:city":"K\u00f6ln",
    "sg:phone":"+49 2236/963360",
    "sg:postcode":"50997",
    "sg:province":"Nordrhein-Westfalen",
    "wof:name":"Gerd Spitz",
    "wof:placetype":"venue"
},
  "geometry": {"coordinates":[6.958345,50.858952],"type":"Point"}
}