{
  "type": "Feature",
  "properties": {
    "iso:country":"DE",
    "sg:address":"K\u00f6lner Str. 68",
    "sg:city":"K\u00f6ln",
    "sg:phone":"+49 2234/74542",
    "sg:postcode":"50859",
    "sg:province":"Nordrhein-Westfalen",
    "wof:name":"Peter Goeke Steuerberater",
    "wof:placetype":"venue"
},
  "geometry": {"coordinates":[6.8459830284,50.9473953247],"type":"Point"}
}