{
  "type": "Feature",
  "properties": {
    "iso:country":"DE",
    "sg:address":"Hauptstr. 89",
    "sg:city":"Miltenberg",
    "sg:phone":"+49 9371/3359",
    "sg:postcode":"63897",
    "sg:province":"Bayern",
    "wof:name":"Barbara Moden Gmbh Bekleidungs-einzelhandel",
    "wof:placetype":"venue"
},
  "geometry": {"coordinates":[9.256405,49.700684],"type":"Point"}
}