{
  "type": "Feature",
  "properties": {
    "iso:country":"DE",
    "sg:address":"Poststr. 8",
    "sg:city":"Eggstedt",
    "sg:phone":"+49 4830/759",
    "sg:postcode":"25721",
    "sg:province":"Schleswig-Holstein",
    "wof:name":"U. Karstens",
    "wof:placetype":"venue"
},
  "geometry": {"coordinates":[9.2628240585,54.0567626953],"type":"Point"}
}