{
  "type": "Feature",
  "properties": {
    "iso:country":"DE",
    "sg:address":"Maximilianstr. 58",
    "sg:city":"Augsburg",
    "sg:phone":"+49 821/33620",
    "sg:postcode":"86150",
    "sg:province":"Bayern",
    "wof:name":"Heinz Bosch",
    "wof:placetype":"venue"
},
  "geometry": {"coordinates":[10.8997411728,48.3639717102],"type":"Point"}
}