{
  "type": "Feature",
  "properties": {
    "iso:country":"DE",
    "sg:address":"Alte Poststr. 61",
    "sg:city":"Kleinostheim",
    "sg:phone":"+49 6027/8403",
    "sg:postcode":"63801",
    "sg:province":"Bayern",
    "wof:name":"Ludwig Stenger Architekt",
    "wof:placetype":"venue"
},
  "geometry": {"coordinates":[9.075841,50.001221],"type":"Point"}
}