{
  "type": "Feature",
  "properties": {
    "iso:country":"DE",
    "sg:address":"Berliner Str. 18",
    "sg:city":"Idstein",
    "sg:phone":"+49 6126/500506",
    "sg:postcode":"65510",
    "sg:province":"Hessen",
    "wof:name":"Ilanit Toys Marketing Gmbh",
    "wof:placetype":"venue"
},
  "geometry": {"coordinates":[8.2594556808,50.2218055725],"type":"Point"}
}