{
  "type": "Feature",
  "properties": {
    "iso:country":"DE",
    "sg:address":"Rosenstr. 16",
    "sg:city":"Marienhafe",
    "sg:phone":"+49 4934/4102",
    "sg:postcode":"26529",
    "sg:province":"Niedersachsen",
    "wof:name":"Textilhaus Ennenga E. K.",
    "wof:placetype":"venue"
},
  "geometry": {"coordinates":[7.2753238678,53.5211524963],"type":"Point"}
}