{
  "type": "Feature",
  "properties": {
    "iso:country":"DE",
    "sg:address":"Martin-Luther-Str. 67",
    "sg:city":"Burg",
    "sg:phone":"+49 3921/944033",
    "sg:postcode":"39288",
    "sg:province":"Sachsen-Anhalt",
    "wof:name":"Elli-markt",
    "wof:placetype":"venue"
},
  "geometry": {"coordinates":[11.8475236893,52.2712020874],"type":"Point"}
}