{
  "type": "Feature",
  "properties": {
    "iso:country":"DE",
    "sg:address":"Kirchstr. 12",
    "sg:city":"Kottenheim",
    "sg:phone":"+49 2651/43257",
    "sg:postcode":"56736",
    "sg:province":"Rheinland-Pfalz",
    "wof:name":"Gangolf Mohr",
    "wof:placetype":"venue"
},
  "geometry": {"coordinates":[7.2568898201,50.3494110107],"type":"Point"}
}