{
  "type": "Feature",
  "properties": {
    "iso:country":"DE",
    "sg:address":"Bregenzer Str. 3",
    "sg:city":"Berlin",
    "sg:phone":"+49 30/88683900",
    "sg:postcode":"10707",
    "sg:province":"Berlin",
    "wof:name":"Michael Reichenbach Architekt",
    "wof:placetype":"venue"
},
  "geometry": {"coordinates":[13.31313,52.497597],"type":"Point"}
}