{
  "type": "Feature",
  "properties": {
    "iso:country":"DE",
    "sg:address":"Bahnhofstr. 29",
    "sg:city":"Saal",
    "sg:phone":"+49 9441/8888",
    "sg:postcode":"93342",
    "sg:province":"Bayern",
    "wof:name":"Roka M\u00f6belgro\u00dfhandels- Gmbh",
    "wof:placetype":"venue"
},
  "geometry": {"coordinates":[11.9313335419,48.9016685486],"type":"Point"}
}