{
  "type": "Feature",
  "properties": {
    "iso:country":"DE",
    "sg:address":"Frankfurter Str. 57",
    "sg:city":"Bad Vilbel",
    "sg:phone":"+49 6101/84787",
    "sg:postcode":"61118",
    "sg:province":"Hessen",
    "wof:name":"Herge & Delazer",
    "wof:placetype":"venue"
},
  "geometry": {"coordinates":[8.741379,50.180943],"type":"Point"}
}