{
  "type": "Feature",
  "properties": {
    "iso:country":"DE",
    "sg:address":"Klemensplatz 7",
    "sg:city":"D\u00fcsseldorf",
    "sg:phone":"+49 211/327478",
    "sg:postcode":"40489",
    "sg:province":"Nordrhein-Westfalen",
    "wof:name":"Schr\u00f6der & Wader Catering Gmbh",
    "wof:placetype":"venue"
},
  "geometry": {"coordinates":[6.7387061119,51.3013725281],"type":"Point"}
}