{
  "type": "Feature",
  "properties": {
    "iso:country":"DE",
    "sg:address":"Berliner Str. 101",
    "sg:city":"Strausberg",
    "sg:phone":"+49 3341/314246",
    "sg:postcode":"15344",
    "sg:province":"Brandenburg",
    "wof:name":"K\u00e4fergaragen",
    "wof:placetype":"venue"
},
  "geometry": {"coordinates":[13.874129,52.570328],"type":"Point"}
}