{
  "type": "Feature",
  "properties": {
    "iso:country":"DE",
    "sg:address":"Beim Tivoli 2",
    "sg:city":"Jever",
    "sg:phone":"+49 4461/74231",
    "sg:postcode":"26441",
    "sg:province":"Niedersachsen",
    "wof:name":"R.g. Haus Und Grund Gmbh",
    "wof:placetype":"venue"
},
  "geometry": {"coordinates":[7.912151,53.566299],"type":"Point"}
}