{
  "type": "Feature",
  "properties": {
    "iso:country":"DE",
    "sg:address":"Herzlstr. 7",
    "sg:city":"Kirchheim",
    "sg:phone":"+49 89/9034850",
    "sg:postcode":"85551",
    "sg:province":"Bayern",
    "wof:name":"Georg Lehner Industrie- Vertrieb Kabel Und Leitungen",
    "wof:placetype":"venue"
},
  "geometry": {"coordinates":[11.757065773,48.1608657837],"type":"Point"}
}