{
  "type": "Feature",
  "properties": {
    "iso:country":"DE",
    "sg:address":"Sommerau 32",
    "sg:city":"Heilbronn",
    "sg:phone":"+49 7131/251142",
    "sg:postcode":"74081",
    "sg:province":"Baden-W\u00fcrttemberg",
    "wof:name":"Gerd Bauer",
    "wof:placetype":"venue"
},
  "geometry": {"coordinates":[9.1969709396,49.1172065735],"type":"Point"}
}