{
  "type": "Feature",
  "properties": {
    "iso:country":"DE",
    "sg:address":"K\u00f6nigstr. 103",
    "sg:city":"Minden",
    "sg:phone":"+49 571/25779",
    "sg:postcode":"32427",
    "sg:province":"Nordrhein-Westfalen",
    "wof:name":"Ein Charlotte Laden J\u00f6rg Herwig",
    "wof:placetype":"venue"
},
  "geometry": {"coordinates":[8.8970479965,52.2887573242],"type":"Point"}
}