{
  "type": "Feature",
  "properties": {
    "iso:country":"DE",
    "sg:address":"Peiner Str. 16",
    "sg:city":"Sehnde",
    "sg:phone":"+49 5138/1288",
    "sg:postcode":"31319",
    "sg:province":"Niedersachsen",
    "wof:name":"Apotheke Im Gro\u00dfen Freien",
    "wof:placetype":"venue"
},
  "geometry": {"coordinates":[9.965352,52.315563],"type":"Point"}
}