{
  "type": "Feature",
  "properties": {
    "iso:country":"DE",
    "sg:address":"Mainzer Str. 1-3",
    "sg:city":"Germersheim",
    "sg:phone":"+49 7274/3027",
    "sg:postcode":"76726",
    "sg:province":"Rheinland-Pfalz",
    "wof:name":"Hela-profizentrum",
    "wof:placetype":"venue"
},
  "geometry": {"coordinates":[8.3691101074,49.2272491455],"type":"Point"}
}