{
  "type": "Feature",
  "properties": {
    "iso:country":"DE",
    "sg:address":"Breite Str. 16",
    "sg:city":"Rinteln",
    "sg:postcode":"31737",
    "sg:province":"Niedersachsen",
    "wof:name":"Pm Service Schuhreparatur- Und Schl\u00fcsselbetriebe Gmbh",
    "wof:placetype":"venue"
},
  "geometry": {"coordinates":[9.0729389191,52.1959075928],"type":"Point"}
}