{
  "type": "Feature",
  "properties": {
    "iso:country":"DE",
    "sg:address":"In den Stubenweinbergen 5",
    "sg:city":"Stuttgart",
    "sg:phone":"+49 711/467481",
    "sg:postcode":"70327",
    "sg:province":"Baden-W\u00fcrttemberg",
    "wof:name":"Weinstube Onkel Otto",
    "wof:placetype":"venue"
},
  "geometry": {"coordinates":[9.2300615311,48.7707061768],"type":"Point"}
}