{
  "type": "Feature",
  "properties": {
    "iso:country":"DE",
    "sg:address":"Steffensrott 12",
    "sg:city":"J\u00fclich",
    "sg:postcode":"52428",
    "sg:province":"Nordrhein-Westfalen",
    "wof:name":"Ambition Travel Vliex E. K.",
    "wof:placetype":"venue"
},
  "geometry": {"coordinates":[6.3324360847,50.9250183105],"type":"Point"}
}