{
  "type": "Feature",
  "properties": {
    "iso:country":"DE",
    "sg:address":"Meinigstr. 43",
    "sg:city":"Bad Harzburg",
    "sg:phone":"+49 5322/81586",
    "sg:postcode":"38667",
    "sg:province":"Niedersachsen",
    "wof:name":"Ev. Pfarramt Harlingerode",
    "wof:placetype":"venue"
},
  "geometry": {"coordinates":[10.5194635391,51.9100112915],"type":"Point"}
}