{
  "type": "Feature",
  "properties": {
    "iso:country":"DE",
    "sg:address":"Kurzekampstr. 21",
    "sg:city":"Braunschweig",
    "sg:phone":"+49 531/373074",
    "sg:postcode":"38104",
    "sg:province":"Niedersachsen",
    "wof:name":"Petra Homann Krankengymnastin",
    "wof:placetype":"venue"
},
  "geometry": {"coordinates":[10.55341,52.278648],"type":"Point"}
}