{
  "type": "Feature",
  "properties": {
    "iso:country":"DE",
    "sg:address":"Heiligenstr. 8",
    "sg:city":"Hilden",
    "sg:phone":"+49 2103/55845",
    "sg:postcode":"40721",
    "sg:province":"Nordrhein-Westfalen",
    "wof:name":"Alice Moden",
    "wof:placetype":"venue"
},
  "geometry": {"coordinates":[6.935822,51.168694],"type":"Point"}
}