{
  "type": "Feature",
  "properties": {
    "iso:country":"DE",
    "sg:address":"Talstr. 38",
    "sg:city":"Kraichtal",
    "sg:phone":"+49 7250/7268",
    "sg:postcode":"76703",
    "sg:province":"Baden-W\u00fcrttemberg",
    "wof:name":"Abc Hoch- Und Tiefbau Gmbh",
    "wof:placetype":"venue"
},
  "geometry": {"coordinates":[8.719577,49.121323],"type":"Point"}
}