{
  "type": "Feature",
  "properties": {
    "iso:country":"DE",
    "sg:address":"Am Bahnhof",
    "sg:city":"Cuxhaven",
    "sg:postcode":"27472",
    "sg:province":"Niedersachsen",
    "wof:name":"Elli Koenig Blumenhaus",
    "wof:placetype":"venue"
},
  "geometry": {"coordinates":[8.70263,53.862301],"type":"Point"}
}