{
  "type": "Feature",
  "properties": {
    "iso:country":"DE",
    "sg:address":"meerweg 63",
    "sg:city":"rheda wiedenbr\u00fcck",
    "sg:postcode":"33378",
    "sg:province":"Nordrhein-Westfalen",
    "wof:name":"Bannex Submition Service",
    "wof:placetype":"venue"
},
  "geometry": {"coordinates":[8.2914133072,51.80311203],"type":"Point"}
}