{
  "type": "Feature",
  "properties": {
    "iso:country":"DE",
    "sg:address":"Stra\u00dfe zum Schlo\u00dfpark 10",
    "sg:city":"Oranienburg",
    "sg:phone":"+49 3301/582983",
    "sg:postcode":"16515",
    "sg:province":"Brandenburg",
    "wof:name":"U. Gesche",
    "wof:placetype":"venue"
},
  "geometry": {"coordinates":[13.230353,52.752823],"type":"Point"}
}