{
  "type": "Feature",
  "properties": {
    "iso:country":"DE",
    "sg:address":"Vornholzstr. 85b",
    "sg:city":"Passau",
    "sg:phone":"+49 851/53386",
    "sg:postcode":"94036",
    "sg:province":"Bayern",
    "wof:name":"G. Springer",
    "wof:placetype":"venue"
},
  "geometry": {"coordinates":[13.4114904404,48.5662612915],"type":"Point"}
}