{
  "type": "Feature",
  "properties": {
    "iso:country":"DE",
    "sg:address":"Bernwardstr. 13",
    "sg:city":"Hannover",
    "sg:phone":"+49 511/830458",
    "sg:postcode":"30519",
    "sg:province":"Niedersachsen",
    "wof:name":"Anna Fiedler",
    "wof:placetype":"venue"
},
  "geometry": {"coordinates":[9.7641582489,52.3401870728],"type":"Point"}
}