{
  "type": "Feature",
  "properties": {
    "iso:country":"DE",
    "sg:address":"Hagener Str. 49",
    "sg:city":"Kreuztal",
    "sg:phone":"+49 4927/324046",
    "sg:postcode":"57223",
    "sg:province":"Nordrhein-Westfalen",
    "wof:name":"Hirsch-sportger\u00c4te Ohg",
    "wof:placetype":"venue"
},
  "geometry": {"coordinates":[7.9862508774,50.963924408],"type":"Point"}
}