{
  "type": "Feature",
  "properties": {
    "iso:country":"DE",
    "sg:address":"Hugo-H\u00e4ring-Str. 13",
    "sg:city":"Biberach",
    "sg:phone":"+49 7351/6644",
    "sg:postcode":"88400",
    "sg:province":"Baden-W\u00fcrttemberg",
    "wof:name":"Inge Dangel",
    "wof:placetype":"venue"
},
  "geometry": {"coordinates":[9.8065471649,48.0954437256],"type":"Point"}
}