{
  "type": "Feature",
  "properties": {
    "iso:country":"DE",
    "sg:address":"Schafh\u00e4user Str. 45",
    "sg:city":"Alzey",
    "sg:postcode":"55232",
    "sg:province":"Rheinland-Pfalz",
    "wof:name":"W & R Grundst\u00fccksges. Mbh",
    "wof:placetype":"venue"
},
  "geometry": {"coordinates":[8.123525,49.751472],"type":"Point"}
}