{
  "type": "Feature",
  "properties": {
    "iso:country":"DE",
    "sg:address":"Zeppelinstr. 23",
    "sg:city":"S\u00fc\u00dfen",
    "sg:phone":"+49 7162/7170",
    "sg:postcode":"73079",
    "sg:province":"Baden-W\u00fcrttemberg",
    "wof:name":"Erich Gerstenbrand",
    "wof:placetype":"venue"
},
  "geometry": {"coordinates":[9.7648277283,48.684211731],"type":"Point"}
}