{
  "type": "Feature",
  "properties": {
    "iso:country":"DE",
    "sg:address":"Johann-Sebastian-Bach-Str. 16",
    "sg:city":"Ueckerm\u00fcnde",
    "sg:phone":"+49 39771/22891",
    "sg:postcode":"17373",
    "sg:province":"Mecklenburg-Vorpommern",
    "wof:name":"Manfred Behl",
    "wof:placetype":"venue"
},
  "geometry": {"coordinates":[14.06348,53.734421],"type":"Point"}
}