{
  "type": "Feature",
  "properties": {
    "iso:country":"DE",
    "sg:address":"Neum\u00fchle 1",
    "sg:city":"Altenbuch",
    "sg:phone":"+49 9392/8771",
    "sg:postcode":"97901",
    "sg:province":"Bayern",
    "wof:name":"Elisabeth Gollbach",
    "wof:placetype":"venue"
},
  "geometry": {"coordinates":[9.4298830032,49.8190841675],"type":"Point"}
}