{
  "type": "Feature",
  "properties": {
    "iso:country":"DE",
    "sg:address":"Schlo\u00dfstr. 5",
    "sg:city":"Obersulm",
    "sg:phone":"+49 7130/273",
    "sg:postcode":"74182",
    "sg:province":"Baden-W\u00fcrttemberg",
    "wof:name":"Ev. Pfarramt Affaltrach",
    "wof:placetype":"venue"
},
  "geometry": {"coordinates":[9.3830032349,49.1363983154],"type":"Point"}
}