{
  "type": "Feature",
  "properties": {
    "iso:country":"DE",
    "sg:address":"Gassenfleckl 6b",
    "sg:city":"Muenchen",
    "sg:phone":"+49 89/3133409",
    "sg:postcode":"80939",
    "sg:province":"Bayern",
    "wof:name":"Edv-beratung Und Aufbewahrungssysteme",
    "wof:placetype":"venue"
},
  "geometry": {"coordinates":[11.595099,48.204609],"type":"Point"}
}