{
  "type": "Feature",
  "properties": {
    "iso:country":"DE",
    "sg:address":"Goldschmiedstr. 3",
    "sg:city":"Friedrichshafen",
    "sg:phone":"+49 7541/23538",
    "sg:postcode":"88045",
    "sg:province":"Baden-W\u00fcrttemberg",
    "wof:name":"Ingrids Handarbeits-truhe Inh. Ingrid Blaser",
    "wof:placetype":"venue"
},
  "geometry": {"coordinates":[9.481036,47.650589],"type":"Point"}
}