{
  "type": "Feature",
  "properties": {
    "iso:country":"DE",
    "sg:address":"Im Wurmgarten 19",
    "sg:city":"Neukirchen",
    "sg:phone":"+49 6694/919115",
    "sg:postcode":"34626",
    "sg:province":"Hessen",
    "wof:name":"Metallveredelung Kahlmeyer Gmbh",
    "wof:placetype":"venue"
},
  "geometry": {"coordinates":[9.352683,50.858662],"type":"Point"}
}