{
  "type": "Feature",
  "properties": {
    "iso:country":"DE",
    "sg:address":"Waldh\u00e4usle",
    "sg:city":"Schenkenzell",
    "sg:phone":"+49 7836/2402",
    "sg:postcode":"77773",
    "sg:province":"Baden-W\u00fcrttemberg",
    "wof:name":"Naturfreundehaus",
    "wof:placetype":"venue"
},
  "geometry": {"coordinates":[8.3452653885,48.3249320984],"type":"Point"}
}