{
  "type": "Feature",
  "properties": {
    "iso:country":"DE",
    "sg:address":"Kaiserstr. 146",
    "sg:city":"W\u00fcrselen",
    "sg:phone":"+49 2405/2393",
    "sg:postcode":"52146",
    "sg:province":"Nordrhein-Westfalen",
    "wof:name":"Hermann Pfeifferling",
    "wof:placetype":"venue"
},
  "geometry": {"coordinates":[6.1284098625,50.8248100281],"type":"Point"}
}