{
  "type": "Feature",
  "properties": {
    "iso:country":"DE",
    "sg:address":"Gewerbeparkring 7",
    "sg:city":"M\u00fcllrose",
    "sg:phone":"+49 33606/4455",
    "sg:postcode":"15299",
    "sg:province":"Brandenburg",
    "wof:name":"W. Sauer Orgelbau Frankfurt Oder Gmbh",
    "wof:placetype":"venue"
},
  "geometry": {"coordinates":[14.430516243,52.256855011],"type":"Point"}
}