{
  "type": "Feature",
  "properties": {
    "iso:country":"DE",
    "sg:address":"Alexanderstr. 128",
    "sg:city":"Stuttgart",
    "sg:phone":"+49 711/6079444",
    "sg:postcode":"70180",
    "sg:province":"Baden-W\u00fcrttemberg",
    "wof:name":"R. Steidinger Kg",
    "wof:placetype":"venue"
},
  "geometry": {"coordinates":[9.18039608,48.7680473328],"type":"Point"}
}