{
  "type": "Feature",
  "properties": {
    "iso:country":"DE",
    "sg:address":"Stanleystr. 9",
    "sg:city":"Wiesbaden",
    "sg:phone":"+49 611/713571",
    "sg:postcode":"65189",
    "sg:province":"Hessen",
    "wof:name":"Sch\u00e4uffele",
    "wof:placetype":"venue"
},
  "geometry": {"coordinates":[8.261809,50.075325],"type":"Point"}
}