{
  "type": "Feature",
  "properties": {
    "iso:country":"DE",
    "sg:address":"Hohlstr. 3",
    "sg:city":"Neuerburg",
    "sg:phone":"+49 6564/2198",
    "sg:postcode":"54673",
    "sg:province":"Rheinland-Pfalz",
    "wof:name":"Schloss-apotheke",
    "wof:placetype":"venue"
},
  "geometry": {"coordinates":[6.29442,50.010956],"type":"Point"}
}