{
  "type": "Feature",
  "properties": {
    "iso:country":"DE",
    "sg:address":"Sittard 8c",
    "sg:city":"M\u00f6nchengladbach",
    "sg:phone":"+49 2161/958610",
    "sg:postcode":"41179",
    "sg:province":"Nordrhein-Westfalen",
    "wof:name":"Silvia Kirschstein S. K. A. R. T. E. K.",
    "wof:placetype":"venue"
},
  "geometry": {"coordinates":[6.3502159119,51.1361503601],"type":"Point"}
}