{
  "type": "Feature",
  "properties": {
    "iso:country":"DE",
    "sg:address":"Johannisstr. 41-44",
    "sg:city":"Osnabr\u00fcck",
    "sg:phone":"+49 541/35800",
    "sg:postcode":"49074",
    "sg:province":"Niedersachsen",
    "wof:name":"Leffers Gmbh & Co. Kg",
    "wof:placetype":"venue"
},
  "geometry": {"coordinates":[8.050721,52.27121],"type":"Point"}
}