{
  "type": "Feature",
  "properties": {
    "iso:country":"DE",
    "sg:address":"Neustr. 13",
    "sg:city":"Euskirchen",
    "sg:phone":"+49 2251/3236",
    "sg:postcode":"53879",
    "sg:province":"Nordrhein-Westfalen",
    "wof:name":"Kirchberger Gmbh",
    "wof:placetype":"venue"
},
  "geometry": {"coordinates":[6.7887601852,50.6607894897],"type":"Point"}
}