{
  "type": "Feature",
  "properties": {
    "iso:country":"DE",
    "sg:address":"Josefstr. 20",
    "sg:city":"K\u00f6ln",
    "sg:phone":"+49 2203/9558541",
    "sg:postcode":"51143",
    "sg:province":"Nordrhein-Westfalen",
    "wof:name":"Deutsche Post Ag",
    "wof:placetype":"venue"
},
  "geometry": {"coordinates":[7.0581431389,50.8864059448],"type":"Point"}
}