{
  "type": "Feature",
  "properties": {
    "iso:country":"DE",
    "sg:address":"Schlo\u00dfgasse 188",
    "sg:city":"Wallhausen",
    "sg:phone":"+49 34656/31048",
    "sg:postcode":"06528",
    "sg:province":"Sachsen-Anhalt",
    "wof:name":"Joachim Bohnstedt",
    "wof:placetype":"venue"
},
  "geometry": {"coordinates":[11.2076091766,51.4596748352],"type":"Point"}
}