{
  "type": "Feature",
  "properties": {
    "iso:country":"DE",
    "sg:address":"Grenzstr. 28",
    "sg:city":"Obertshausen",
    "sg:phone":"+49 6104/499313",
    "sg:postcode":"63179",
    "sg:province":"Hessen",
    "wof:name":"Analex Data Vertriebs Gmbh",
    "wof:placetype":"venue"
},
  "geometry": {"coordinates":[8.844976,50.075191],"type":"Point"}
}