{
  "type": "Feature",
  "properties": {
    "iso:country":"DE",
    "sg:address":"Luntenbuck 2",
    "sg:city":"N\u00f6rdlingen",
    "sg:phone":"+49 9081/29650",
    "sg:postcode":"86720",
    "sg:province":"Bayern",
    "wof:name":"Richard Ziegelm\u00fcller",
    "wof:placetype":"venue"
},
  "geometry": {"coordinates":[10.49345,48.856636],"type":"Point"}
}