{
  "type": "Feature",
  "properties": {
    "iso:country":"DE",
    "sg:address":"Bergwaldstr. 7",
    "sg:city":"Julbach",
    "sg:postcode":"84387",
    "sg:province":"Bayern",
    "wof:name":"Halo Gmbh",
    "wof:placetype":"venue"
},
  "geometry": {"coordinates":[12.9547328949,48.2576370239],"type":"Point"}
}