{
  "type": "Feature",
  "properties": {
    "iso:country":"DE",
    "sg:address":"Dornierstr 2",
    "sg:city":"Birkenfeld",
    "sg:phone":"+49 7231/489880",
    "sg:postcode":"75217",
    "sg:province":"Baden-W\u00fcrttemberg",
    "wof:name":"Hohl Gmbh Aluminium-veredelung",
    "wof:placetype":"venue"
},
  "geometry": {"coordinates":[8.640893,48.878017],"type":"Point"}
}