{
  "type": "Feature",
  "properties": {
    "iso:country":"DE",
    "sg:address":"Tulpenstr. 22",
    "sg:city":"Saarbr\u00fccken",
    "sg:phone":"+49 681/70662",
    "sg:postcode":"66128",
    "sg:province":"Saarland",
    "wof:name":"Gersweiler Anzeiger",
    "wof:placetype":"venue"
},
  "geometry": {"coordinates":[6.9086761475,49.2269744873],"type":"Point"}
}