{
  "type": "Feature",
  "properties": {
    "iso:country":"DE",
    "sg:address":"Hanauer Landstr. 360",
    "sg:city":"Frankfurt",
    "sg:postcode":"60386",
    "sg:province":"Hessen",
    "wof:name":"Fritz Berger Beteiligungs Gmbh",
    "wof:placetype":"venue"
},
  "geometry": {"coordinates":[8.750333,50.126244],"type":"Point"}
}