{
  "type": "Feature",
  "properties": {
    "iso:country":"DE",
    "sg:address":"Breite Str. 22",
    "sg:city":"Gro\u00dfostheim",
    "sg:phone":"+49 6026/995959",
    "sg:postcode":"63762",
    "sg:province":"Bayern",
    "wof:name":"Div Digitale Informationsver - Arbeitungssysteme Gmbh",
    "wof:placetype":"venue"
},
  "geometry": {"coordinates":[9.075176239,49.9180107117],"type":"Point"}
}