{
  "type": "Feature",
  "properties": {
    "iso:country":"DE",
    "sg:address":"S\u00fcdring 25",
    "sg:city":"Velen",
    "sg:phone":"+49 2863/95880",
    "sg:postcode":"46342",
    "sg:province":"Nordrhein-Westfalen",
    "wof:name":"G\u00fcnter Ebbing Elektroinstallation",
    "wof:placetype":"venue"
},
  "geometry": {"coordinates":[6.921114,51.879204],"type":"Point"}
}