{
  "type": "Feature",
  "properties": {
    "iso:country":"DE",
    "sg:address":"Landgrafenstr. 20",
    "sg:city":"Pfreimd",
    "sg:phone":"+49 9606/914156",
    "sg:postcode":"92536",
    "sg:province":"Bayern",
    "wof:name":"Renate Schaller",
    "wof:placetype":"venue"
},
  "geometry": {"coordinates":[12.177748,49.492664],"type":"Point"}
}