{
  "type": "Feature",
  "properties": {
    "iso:country":"DE",
    "sg:address":"Josefinenstr. 2",
    "sg:city":"Herne",
    "sg:postcode":"44628",
    "sg:province":"Nordrhein-Westfalen",
    "wof:name":"Heermann Der Partyservice.de",
    "wof:placetype":"venue"
},
  "geometry": {"coordinates":[7.2336349487,51.5505523682],"type":"Point"}
}