{
  "type": "Feature",
  "properties": {
    "iso:country":"DE",
    "sg:address":"Kelterstr. 1",
    "sg:city":"Altbach",
    "sg:postcode":"73776",
    "sg:province":"Baden-W\u00fcrttemberg",
    "wof:name":"Ortsb\u00fccherei Neues Schulhaus",
    "wof:placetype":"venue"
},
  "geometry": {"coordinates":[9.378808,48.724285],"type":"Point"}
}