{
  "type": "Feature",
  "properties": {
    "iso:country":"DE",
    "sg:address":"Birkenweg 5",
    "sg:city":"Reichenschwand",
    "sg:phone":"+49 9151/95908",
    "sg:postcode":"91244",
    "sg:province":"Bayern",
    "wof:name":"Hotel-pension Zipser",
    "wof:placetype":"venue"
},
  "geometry": {"coordinates":[11.3710021973,49.51304245],"type":"Point"}
}