{
  "type": "Feature",
  "properties": {
    "iso:country":"DE",
    "sg:address":"Fichtestr. 9",
    "sg:city":"Solingen",
    "sg:phone":"+49 212/52781",
    "sg:postcode":"42655",
    "sg:province":"Nordrhein-Westfalen",
    "wof:name":"Hellmann & Haarmann Gmbh",
    "wof:placetype":"venue"
},
  "geometry": {"coordinates":[7.0771188736,51.1802177429],"type":"Point"}
}