{
  "type": "Feature",
  "properties": {
    "iso:country":"DE",
    "sg:address":"Sommerstr. 20a",
    "sg:city":"Unterhaching",
    "sg:phone":"+49 89/663931",
    "sg:postcode":"82008",
    "sg:province":"Bayern",
    "wof:name":"August Kowatschitsch",
    "wof:placetype":"venue"
},
  "geometry": {"coordinates":[11.6076173782,48.075214386],"type":"Point"}
}