{
  "type": "Feature",
  "properties": {
    "iso:country":"DE",
    "sg:address":"Lungwitzer Str. 26",
    "sg:city":"Hohenstein-Ernstthal",
    "sg:phone":"+49 3723/46994",
    "sg:postcode":"09337",
    "sg:province":"Sachsen",
    "wof:name":"Orthop\u00e4die Technik Wolf Gmbh",
    "wof:placetype":"venue"
},
  "geometry": {"coordinates":[12.7132,50.800758],"type":"Point"}
}