{
  "type": "Feature",
  "properties": {
    "iso:country":"DE",
    "sg:address":"Hauptstr. 33",
    "sg:city":"Obrigheim",
    "sg:phone":"+49 6359/5674",
    "sg:postcode":"67283",
    "sg:province":"Rheinland-Pfalz",
    "wof:name":"Kurt Rentschler",
    "wof:placetype":"venue"
},
  "geometry": {"coordinates":[8.203874,49.59166],"type":"Point"}
}