{
  "type": "Feature",
  "properties": {
    "iso:country":"DE",
    "sg:address":"Schlo\u00dfstr. 13",
    "sg:city":"Meitingen",
    "sg:phone":"+49 8271/6906",
    "sg:postcode":"86405",
    "sg:province":"Bayern",
    "wof:name":"Alois Strobl",
    "wof:placetype":"venue"
},
  "geometry": {"coordinates":[10.8511610031,48.5412902832],"type":"Point"}
}