{
  "type": "Feature",
  "properties": {
    "iso:country":"DE",
    "sg:address":"Daimler-Benz-Str. 10",
    "sg:city":"Waibstadt",
    "sg:phone":"+49 7263/5678",
    "sg:postcode":"74915",
    "sg:province":"Baden-W\u00fcrttemberg",
    "wof:name":"Hauck Baugesellschaft Mbh",
    "wof:placetype":"venue"
},
  "geometry": {"coordinates":[8.899619,49.303482],"type":"Point"}
}