{
  "type": "Feature",
  "properties": {
    "iso:country":"DE",
    "sg:address":"Pirnaer Landstr. 239",
    "sg:city":"Dresden",
    "sg:phone":"+49 351/2031187",
    "sg:postcode":"01259",
    "sg:province":"Sachsen",
    "wof:name":"Dieter Sohrmann",
    "wof:placetype":"venue"
},
  "geometry": {"coordinates":[13.841955,51.002602],"type":"Point"}
}