{
  "type": "Feature",
  "properties": {
    "iso:country":"DE",
    "sg:address":"Klosterstr. 15",
    "sg:city":"Neuhaus",
    "sg:phone":"+49 8503/205",
    "sg:postcode":"94152",
    "sg:province":"Bayern",
    "wof:name":"Max Nebauer",
    "wof:placetype":"venue"
},
  "geometry": {"coordinates":[13.423478,48.460796],"type":"Point"}
}