{
  "type": "Feature",
  "properties": {
    "iso:country":"DE",
    "sg:address":"Blumenacker 30",
    "sg:city":"Inzlingen",
    "sg:postcode":"79594",
    "sg:province":"Baden-W\u00fcrttemberg",
    "wof:name":"Hildebrand Systeme Gmbh",
    "wof:placetype":"venue"
},
  "geometry": {"coordinates":[7.6835031509,47.58934021],"type":"Point"}
}