{
  "type": "Feature",
  "properties": {
    "iso:country":"DE",
    "sg:address":"Nordsehler Str. 47",
    "sg:city":"Stadthagen",
    "sg:phone":"+49 5721/97840",
    "sg:postcode":"31655",
    "sg:province":"Niedersachsen",
    "wof:name":"H & S Fahrzeugbau Gmbh & Co.",
    "wof:placetype":"venue"
},
  "geometry": {"coordinates":[9.178827,52.339348],"type":"Point"}
}