{
  "type": "Feature",
  "properties": {
    "iso:country":"DE",
    "sg:address":"Pieperstr 1-3",
    "sg:city":"Bremen",
    "sg:phone":"+49 421/175690",
    "sg:postcode":"28195",
    "sg:province":"Bremen",
    "wof:name":"Itg Gmbh",
    "wof:placetype":"venue"
},
  "geometry": {"coordinates":[8.804023,53.077705],"type":"Point"}
}