{
  "type": "Feature",
  "properties": {
    "iso:country":"DE",
    "sg:address":"Von-Weichs-Str. 2-4",
    "sg:city":"Bonn",
    "sg:phone":"+49 228/622000",
    "sg:postcode":"53121",
    "sg:province":"Nordrhein-Westfalen",
    "wof:name":"Heinz B\u00fcttner Gmbh",
    "wof:placetype":"venue"
},
  "geometry": {"coordinates":[7.06995821,50.7268638611],"type":"Point"}
}