{
  "type": "Feature",
  "properties": {
    "iso:country":"DE",
    "sg:address":"Luzernestr. 9",
    "sg:city":"Leinfelden-Echterdingen",
    "sg:phone":"+49 711/7542530",
    "sg:postcode":"70771",
    "sg:province":"Baden-W\u00fcrttemberg",
    "wof:name":"U. Wahl Immobilienmakler",
    "wof:placetype":"venue"
},
  "geometry": {"coordinates":[9.1266012192,48.6933708191],"type":"Point"}
}