{
  "type": "Feature",
  "properties": {
    "iso:country":"DE",
    "sg:address":"Gotenstr. 2",
    "sg:city":"Mannheim",
    "sg:postcode":"68259",
    "sg:province":"Baden-W\u00fcrttemberg",
    "wof:name":"Ekici Gmbh",
    "wof:placetype":"venue"
},
  "geometry": {"coordinates":[8.554515,49.49736],"type":"Point"}
}