{
  "type": "Feature",
  "properties": {
    "iso:country":"DE",
    "sg:address":"Sechsbaumweg 10",
    "sg:city":"Heimertingen",
    "sg:phone":"+49 8335/986372",
    "sg:postcode":"87751",
    "sg:province":"Bayern",
    "wof:name":"Berthold Mang Steuerberater",
    "wof:placetype":"venue"
},
  "geometry": {"coordinates":[10.156701088,48.042263031],"type":"Point"}
}