{
  "type": "Feature",
  "properties": {
    "iso:country":"DE",
    "sg:address":"Kleinbahnring 13",
    "sg:city":"Ense",
    "sg:postcode":"59469",
    "sg:province":"Nordrhein-Westfalen",
    "wof:name":"Pl\u00f6ger Beteiligungs Gmbh",
    "wof:placetype":"venue"
},
  "geometry": {"coordinates":[7.991085,51.497505],"type":"Point"}
}