{
  "type": "Feature",
  "properties": {
    "iso:country":"DE",
    "sg:address":"Leuschnerstr. 53",
    "sg:city":"Bayreuth",
    "sg:phone":"+49 921/757440",
    "sg:postcode":"95447",
    "sg:province":"Bayern",
    "wof:name":"Rospeg Bayreuth Gmbh",
    "wof:placetype":"venue"
},
  "geometry": {"coordinates":[11.5664434433,49.9325637817],"type":"Point"}
}