{
  "type": "Feature",
  "properties": {
    "iso:country":"DE",
    "sg:address":"Zum Leeborn 3",
    "sg:city":"Harmstorf",
    "sg:phone":"+49 4105/570501",
    "sg:postcode":"21228",
    "sg:province":"Niedersachsen",
    "wof:name":"Dqmd Drinkewitz Qualit\u00e4tsmanagement Dienstleistung",
    "wof:placetype":"venue"
},
  "geometry": {"coordinates":[9.993394,53.351452],"type":"Point"}
}