{
  "type": "Feature",
  "properties": {
    "iso:country":"DE",
    "sg:address":"Kronsforder Allee 35",
    "sg:city":"L\u00fcbeck",
    "sg:postcode":"23560",
    "sg:province":"Schleswig-Holstein",
    "wof:name":"Hanse Consult",
    "wof:placetype":"venue"
},
  "geometry": {"coordinates":[10.6883583069,53.8530158997],"type":"Point"}
}