{
  "type": "Feature",
  "properties": {
    "iso:country":"DE",
    "sg:address":"Gocher Str. 116",
    "sg:city":"Weeze",
    "sg:phone":"+49 2837/1366",
    "sg:postcode":"47652",
    "sg:province":"Nordrhein-Westfalen",
    "wof:name":"Discount-markt In Weeze E. K.",
    "wof:placetype":"venue"
},
  "geometry": {"coordinates":[6.193980217,51.6355819702],"type":"Point"}
}