{
  "type": "Feature",
  "properties": {
    "iso:country":"DE",
    "sg:address":"Viktor-Reuter-Str. 35",
    "sg:city":"Herne",
    "sg:phone":"+49 2323/50091",
    "sg:postcode":"44623",
    "sg:province":"Nordrhein-Westfalen",
    "wof:name":"Med. Techn. Krankenhaus Service-zentrum F\u00fcr",
    "wof:placetype":"venue"
},
  "geometry": {"coordinates":[7.226116,51.543068],"type":"Point"}
}