{
  "type": "Feature",
  "properties": {
    "iso:country":"DE",
    "sg:address":"Bismarckstr. 27",
    "sg:city":"Radolfzell",
    "sg:phone":"+49 7732/99920",
    "sg:postcode":"78315",
    "sg:province":"Baden-W\u00fcrttemberg",
    "wof:name":"Horst Joos Steuerberater",
    "wof:placetype":"venue"
},
  "geometry": {"coordinates":[8.9653196335,47.7402687073],"type":"Point"}
}