{
  "type": "Feature",
  "properties": {
    "iso:country":"DE",
    "sg:address":"Auestr. 26 a",
    "sg:city":"Speyer",
    "sg:phone":"+49 6232/41252",
    "sg:postcode":"67346",
    "sg:province":"Rheinland-Pfalz",
    "wof:name":"Siegbert Weickenmeier",
    "wof:placetype":"venue"
},
  "geometry": {"coordinates":[8.4406051636,49.3332519531],"type":"Point"}
}