{
  "type": "Feature",
  "properties": {
    "iso:country":"DE",
    "sg:address":"Ober-Eschbacher Str. 122",
    "sg:city":"Bad Homburg",
    "sg:phone":"+49 6172/450862",
    "sg:postcode":"61352",
    "sg:province":"Hessen",
    "wof:name":"K. Mohn",
    "wof:placetype":"venue"
},
  "geometry": {"coordinates":[8.654789,50.214252],"type":"Point"}
}