{
  "type": "Feature",
  "properties": {
    "iso:country":"DE",
    "sg:address":"Hugo-Herrmann-Str. 9",
    "sg:city":"Reutlingen",
    "sg:phone":"+49 7121/46151",
    "sg:postcode":"72766",
    "sg:province":"Baden-W\u00fcrttemberg",
    "wof:name":"Friedrich Gronbach Architekt",
    "wof:placetype":"venue"
},
  "geometry": {"coordinates":[9.230486,48.503498],"type":"Point"}
}