{
  "type": "Feature",
  "properties": {
    "iso:country":"DE",
    "sg:address":"Hauptstr. 2",
    "sg:city":"Hundsdorf",
    "sg:phone":"+49 2623/88020",
    "sg:postcode":"56235",
    "sg:province":"Rheinland-Pfalz",
    "wof:name":"Heide Gmbh",
    "wof:placetype":"venue"
},
  "geometry": {"coordinates":[7.709298,50.470753],"type":"Point"}
}