{
  "type": "Feature",
  "properties": {
    "iso:country":"DE",
    "sg:address":"Beverwijker Ring 2",
    "sg:city":"Neuwied",
    "sg:postcode":"56564",
    "sg:province":"Rheinland-Pfalz",
    "wof:name":"F\u00f6rder- Und Wohnst\u00e4tte F\u00fcr Schwerstbehinderte Gem. Gmbh",
    "wof:placetype":"venue"
},
  "geometry": {"coordinates":[7.470298,50.447739],"type":"Point"}
}