{
  "type": "Feature",
  "properties": {
    "iso:country":"DE",
    "sg:address":"Am Schlo\u00dfjockelskopf 13",
    "sg:city":"Kehl",
    "sg:phone":"+49 7851/3846",
    "sg:postcode":"77694",
    "sg:province":"Baden-W\u00fcrttemberg",
    "wof:name":"Gerd Krau\u00df",
    "wof:placetype":"venue"
},
  "geometry": {"coordinates":[7.814129,48.559906],"type":"Point"}
}