{
  "type": "Feature",
  "properties": {
    "iso:country":"DE",
    "sg:address":"Amalienhofstr. 21",
    "sg:city":"Berlin",
    "sg:phone":"+49 30/3328301",
    "sg:postcode":"13581",
    "sg:province":"Berlin",
    "wof:name":"Walter H\u00fcter Strassenbau Gmbh",
    "wof:placetype":"venue"
},
  "geometry": {"coordinates":[13.1784572601,52.5262756348],"type":"Point"}
}