{
  "type": "Feature",
  "properties": {
    "iso:country":"DE",
    "sg:address":"Hannoversche Str. 21",
    "sg:city":"B\u00fcckeburg",
    "sg:postcode":"31675",
    "sg:province":"Niedersachsen",
    "wof:name":"Kartsportcenter Tr Gmbh",
    "wof:placetype":"venue"
},
  "geometry": {"coordinates":[9.060099,52.26329],"type":"Point"}
}