{
  "type": "Feature",
  "properties": {
    "iso:country":"DE",
    "sg:address":"Johannes-Haag-Str. 13",
    "sg:city":"Kaufbeuren",
    "sg:phone":"+49 8341/82048",
    "sg:postcode":"87600",
    "sg:province":"Bayern",
    "wof:name":"Gastst\u00e4tte Aktienschenke",
    "wof:placetype":"venue"
},
  "geometry": {"coordinates":[10.6273546219,47.879535675],"type":"Point"}
}