{
  "type": "Feature",
  "properties": {
    "iso:country":"DE",
    "sg:address":"Untere Bahnhofstr 32",
    "sg:city":"Thalheim",
    "sg:phone":"+49 3721/26030",
    "sg:postcode":"09380",
    "sg:province":"Sachsen",
    "wof:name":"Elektro-anlagenbau Thalheim Gmbh",
    "wof:placetype":"venue"
},
  "geometry": {"coordinates":[12.850719,50.698814],"type":"Point"}
}