{
  "type": "Feature",
  "properties": {
    "iso:country":"DE",
    "sg:address":"Milit\u00e4rstr. 6",
    "sg:city":"Rastatt",
    "sg:phone":"+49 4972/2297590",
    "sg:postcode":"76437",
    "sg:province":"Baden-W\u00fcrttemberg",
    "wof:name":"Holz-hertel Gmbh",
    "wof:placetype":"venue"
},
  "geometry": {"coordinates":[8.2118387222,48.8491134644],"type":"Point"}
}