{
  "type": "Feature",
  "properties": {
    "iso:country":"DE",
    "sg:address":"Kammerstr. 130",
    "sg:city":"Duisburg",
    "sg:phone":"+49 203/356863",
    "sg:postcode":"47057",
    "sg:province":"Nordrhein-Westfalen",
    "wof:name":"Theis Gmbh",
    "wof:placetype":"venue"
},
  "geometry": {"coordinates":[6.7856631279,51.4252090454],"type":"Point"}
}