{
  "type": "Feature",
  "properties": {
    "iso:country":"DE",
    "sg:address":"Bad Kreuznacher Str 32",
    "sg:city":"Mannheim",
    "sg:phone":"+49 621/727550",
    "sg:postcode":"68309",
    "sg:province":"Baden-W\u00fcrttemberg",
    "wof:name":"Dr. Keller Maschinen Gmbh",
    "wof:placetype":"venue"
},
  "geometry": {"coordinates":[8.523507,49.506241],"type":"Point"}
}