{
  "type": "Feature",
  "properties": {
    "iso:country":"DE",
    "sg:address":"Schlo\u00dferstr. 6",
    "sg:city":"Manching",
    "sg:phone":"+49 8459/33380",
    "sg:postcode":"85077",
    "sg:province":"Bayern",
    "wof:name":"Cool Light Gmbh",
    "wof:placetype":"venue"
},
  "geometry": {"coordinates":[11.478632,48.713844],"type":"Point"}
}