{
  "type": "Feature",
  "properties": {
    "iso:country":"DE",
    "sg:address":"Marktstr. 5",
    "sg:city":"Ichenhausen",
    "sg:phone":"+49 8223/3456",
    "sg:postcode":"89335",
    "sg:province":"Bayern",
    "wof:name":"Johann Jordan",
    "wof:placetype":"venue"
},
  "geometry": {"coordinates":[10.3055953979,48.3720626831],"type":"Point"}
}