{
  "type": "Feature",
  "properties": {
    "iso:country":"DE",
    "sg:address":"Westfalenweg 90",
    "sg:city":"Wuppertal",
    "sg:phone":"+49 202/722599",
    "sg:postcode":"42111",
    "sg:province":"Nordrhein-Westfalen",
    "wof:name":"Im Fuchspark",
    "wof:placetype":"venue"
},
  "geometry": {"coordinates":[7.1339249611,51.2798805237],"type":"Point"}
}