{
  "type": "Feature",
  "properties": {
    "iso:country":"DE",
    "sg:address":"Hauptstr. 25",
    "sg:city":"Kettig",
    "sg:phone":"+49 2637/8158",
    "sg:postcode":"56220",
    "sg:province":"Rheinland-Pfalz",
    "wof:name":"H. H\u00f6fer",
    "wof:placetype":"venue"
},
  "geometry": {"coordinates":[7.4608569145,50.3966598511],"type":"Point"}
}