{
  "type": "Feature",
  "properties": {
    "iso:country":"DE",
    "sg:address":"Atzenberger Str. 2",
    "sg:city":"Bad Schussenried",
    "sg:phone":"+49 7525/8286",
    "sg:postcode":"88427",
    "sg:province":"Baden-W\u00fcrttemberg",
    "wof:name":"A. Pfarr",
    "wof:placetype":"venue"
},
  "geometry": {"coordinates":[9.641751,47.974979],"type":"Point"}
}