{
  "type": "Feature",
  "properties": {
    "iso:country":"DE",
    "sg:address":"Br\u00fchlweg 26",
    "sg:city":"Alfdorf",
    "sg:phone":"+49 7172/937700",
    "sg:postcode":"73553",
    "sg:province":"Baden-W\u00fcrttemberg",
    "wof:name":"Direkt Cnc-systeme Gmbh",
    "wof:placetype":"venue"
},
  "geometry": {"coordinates":[9.7379684448,48.8442420959],"type":"Point"}
}