{
  "type": "Feature",
  "properties": {
    "iso:country":"DE",
    "sg:address":"Harzblick 2",
    "sg:city":"Quedlinburg",
    "sg:phone":"+49 3946/704684",
    "sg:postcode":"06484",
    "sg:province":"Sachsen-Anhalt",
    "wof:name":"Adalbert Writte",
    "wof:placetype":"venue"
},
  "geometry": {"coordinates":[11.1608171463,51.7831268311],"type":"Point"}
}