{
  "type": "Feature",
  "properties": {
    "iso:country":"DE",
    "sg:address":"Marlener Str. 9",
    "sg:city":"Offenburg",
    "sg:phone":"+49 781/5040",
    "sg:postcode":"77656",
    "sg:province":"Baden-W\u00fcrttemberg",
    "wof:name":"Reiff Printservice Gmbh",
    "wof:placetype":"venue"
},
  "geometry": {"coordinates":[7.926291,48.470238],"type":"Point"}
}