{
  "type": "Feature",
  "properties": {
    "iso:country":"DE",
    "sg:address":"Lanzstr. 1",
    "sg:city":"St. Leon-Rot",
    "sg:phone":"+49 6227/52265",
    "sg:postcode":"68789",
    "sg:province":"Baden-W\u00fcrttemberg",
    "wof:name":"Siegrist Gmbh",
    "wof:placetype":"venue"
},
  "geometry": {"coordinates":[8.646957,49.245125],"type":"Point"}
}