{
  "type": "Feature",
  "properties": {
    "iso:country":"DE",
    "sg:address":"Hintergasse 22",
    "sg:city":"Niddatal",
    "sg:phone":"+49 6034/2081",
    "sg:postcode":"61194",
    "sg:province":"Hessen",
    "wof:name":"Arcaini & Co. Beteiligungs-gmbh",
    "wof:placetype":"venue"
},
  "geometry": {"coordinates":[8.813551,50.298698],"type":"Point"}
}