{
  "type": "Feature",
  "properties": {
    "iso:country":"DE",
    "sg:address":"Rheinstr. 9",
    "sg:city":"Merzig",
    "sg:phone":"+49 6861/2929",
    "sg:postcode":"66663",
    "sg:province":"Saarland",
    "wof:name":"Hans Kasper Steuerberater",
    "wof:placetype":"venue"
},
  "geometry": {"coordinates":[6.6102490425,49.4407348633],"type":"Point"}
}