{
  "type": "Feature",
  "properties": {
    "iso:country":"DE",
    "sg:address":"Bembergstr. 2",
    "sg:city":"Wuppertal",
    "sg:phone":"+49 4920/24900",
    "sg:postcode":"42103",
    "sg:province":"Nordrhein-Westfalen",
    "wof:name":"Jackst\u00c4dt Gmbh",
    "wof:placetype":"venue"
},
  "geometry": {"coordinates":[7.1545071602,51.257850647],"type":"Point"}
}