{
  "type": "Feature",
  "properties": {
    "iso:country":"DE",
    "sg:address":"Raindorfer Weg 13",
    "sg:city":"Langenzenn",
    "sg:phone":"+49 9101/6513",
    "sg:postcode":"90579",
    "sg:province":"Bayern",
    "wof:name":"Heiz\u00f6l Biegel Inh. Heinrich Maydt",
    "wof:placetype":"venue"
},
  "geometry": {"coordinates":[10.8079824448,49.4983444214],"type":"Point"}
}