{
  "type": "Feature",
  "properties": {
    "iso:country":"DE",
    "sg:address":"Beusselstr. 19-20",
    "sg:city":"Berlin",
    "sg:phone":"+49 30/3956269",
    "sg:postcode":"10553",
    "sg:province":"Berlin",
    "wof:name":"G\u00fcl Boutique Kahire Tatlici",
    "wof:placetype":"venue"
},
  "geometry": {"coordinates":[13.328878,52.528309],"type":"Point"}
}