{
  "type": "Feature",
  "properties": {
    "iso:country":"DE",
    "sg:address":"Hauptkanal Rechts 56",
    "sg:city":"Papenburg",
    "sg:phone":"+49 4961/5532",
    "sg:postcode":"26871",
    "sg:province":"Niedersachsen",
    "wof:name":"L\u00f6wen Play Gmbh",
    "wof:placetype":"venue"
},
  "geometry": {"coordinates":[7.3923082352,53.0793190002],"type":"Point"}
}