{
  "type": "Feature",
  "properties": {
    "iso:country":"DE",
    "sg:address":"Am Frauenberg",
    "sg:city":"Bad Waldsee",
    "sg:phone":"+49 7524/49782",
    "sg:postcode":"88339",
    "sg:province":"Baden-W\u00fcrttemberg",
    "wof:name":"Klingothek",
    "wof:placetype":"venue"
},
  "geometry": {"coordinates":[9.7468099594,47.9146881104],"type":"Point"}
}