{
  "type": "Feature",
  "properties": {
    "iso:country":"DE",
    "sg:address":"Auf der Schanze 16",
    "sg:city":"Kirn",
    "sg:phone":"+49 6752/6783",
    "sg:postcode":"55606",
    "sg:province":"Rheinland-Pfalz",
    "wof:name":"Asis-arbeitsschutz",
    "wof:placetype":"venue"
},
  "geometry": {"coordinates":[7.4516768456,49.7891998291],"type":"Point"}
}