{
  "type": "Feature",
  "properties": {
    "iso:country":"DE",
    "sg:address":"Romelstr. 14",
    "sg:city":"Gottmadingen",
    "sg:phone":"+49 7734/6200",
    "sg:postcode":"78244",
    "sg:province":"Baden-W\u00fcrttemberg",
    "wof:name":"Karl Mohr",
    "wof:placetype":"venue"
},
  "geometry": {"coordinates":[8.72879,47.738373],"type":"Point"}
}