{
  "type": "Feature",
  "properties": {
    "iso:country":"DE",
    "sg:address":"Strahlenbergerstra\u00dfe 11",
    "sg:city":"Offenbach",
    "sg:phone":"+49 69/91322905",
    "sg:postcode":"63067",
    "sg:province":"Hessen",
    "wof:name":"Int. Hessen-rundfahrt Der Rad-elite",
    "wof:placetype":"venue"
},
  "geometry": {"coordinates":[8.741522,50.107388],"type":"Point"}
}