{
  "type": "Feature",
  "properties": {
    "iso:country":"DE",
    "sg:address":"Carumer M\u00fchle",
    "sg:city":"Bakum",
    "sg:phone":"+49 4443/1011",
    "sg:postcode":"49456",
    "sg:province":"Niedersachsen",
    "wof:name":"Theodor Lammerding Inh. Regina Lammerding",
    "wof:placetype":"venue"
},
  "geometry": {"coordinates":[8.1909399033,52.7516326904],"type":"Point"}
}