{
  "type": "Feature",
  "properties": {
    "iso:country":"DE",
    "sg:address":"Humboldtstr. 90",
    "sg:city":"Frankfurt",
    "sg:phone":"+49 69/59796900",
    "sg:postcode":"60318",
    "sg:province":"Hessen",
    "wof:name":"Klaus Buchholz",
    "wof:placetype":"venue"
},
  "geometry": {"coordinates":[8.6843299866,50.1276321411],"type":"Point"}
}