{
  "type": "Feature",
  "properties": {
    "iso:country":"DE",
    "sg:address":"Falterstr. 5",
    "sg:city":"Kitzingen",
    "sg:phone":"+49 9321/23124",
    "sg:postcode":"97318",
    "sg:province":"Bayern",
    "wof:name":"Ihr Platz Drogeriemarkt",
    "wof:placetype":"venue"
},
  "geometry": {"coordinates":[10.160654,49.736595],"type":"Point"}
}