{
  "type": "Feature",
  "properties": {
    "iso:country":"DE",
    "sg:address":"R\u00f6ntgenstr. 5",
    "sg:city":"Villingen-Schwenningen",
    "sg:phone":"+49 7720/1484",
    "sg:postcode":"78054",
    "sg:province":"Baden-W\u00fcrttemberg",
    "wof:name":"Karl Altmann Gmbh",
    "wof:placetype":"venue"
},
  "geometry": {"coordinates":[8.5257377625,48.0698242188],"type":"Point"}
}