{
  "type": "Feature",
  "properties": {
    "iso:country":"DE",
    "sg:address":"Hartmattenstr. 15",
    "sg:city":"L\u00f6rrach",
    "sg:phone":"+49 7621/45568",
    "sg:postcode":"79539",
    "sg:province":"Baden-W\u00fcrttemberg",
    "wof:name":"Ev. Pfarramt Friedensgemeinde",
    "wof:placetype":"venue"
},
  "geometry": {"coordinates":[7.6740341187,47.6201210022],"type":"Point"}
}