{
  "type": "Feature",
  "properties": {
    "iso:country":"DE",
    "sg:address":"Babelsberger Str. 19",
    "sg:city":"Magdeburg",
    "sg:phone":"+49 391/857718",
    "sg:postcode":"39114",
    "sg:province":"Sachsen-Anhalt",
    "wof:name":"Pumpen Hollburg",
    "wof:placetype":"venue"
},
  "geometry": {"coordinates":[11.661053,52.116783],"type":"Point"}
}