{
  "type": "Feature",
  "properties": {
    "iso:country":"DE",
    "sg:address":"Hagenstr. 17",
    "sg:city":"Nottuln",
    "sg:phone":"+49 2502/9247",
    "sg:postcode":"48301",
    "sg:province":"Nordrhein-Westfalen",
    "wof:name":"G. H. Hidding",
    "wof:placetype":"venue"
},
  "geometry": {"coordinates":[7.353815,51.931572],"type":"Point"}
}