{
  "type": "Feature",
  "properties": {
    "iso:country":"DE",
    "sg:address":"Alte Poststr. 4",
    "sg:city":"Katzwinkel",
    "sg:phone":"+49 2741/63447",
    "sg:postcode":"57581",
    "sg:province":"Rheinland-Pfalz",
    "wof:name":"C. Reinhardt Heilpraktiker",
    "wof:placetype":"venue"
},
  "geometry": {"coordinates":[7.8054609299,50.8087921143],"type":"Point"}
}