{
  "type": "Feature",
  "properties": {
    "iso:country":"DE",
    "sg:address":"Beethovenstr. 3",
    "sg:city":"Menden",
    "sg:phone":"+49 2373/2787",
    "sg:postcode":"58706",
    "sg:province":"Nordrhein-Westfalen",
    "wof:name":"Keglerklause",
    "wof:placetype":"venue"
},
  "geometry": {"coordinates":[7.8061480522,51.4464073181],"type":"Point"}
}