{
  "type": "Feature",
  "properties": {
    "iso:country":"DE",
    "sg:address":"Pinneberger Chaussee 5",
    "sg:city":"Hamburg",
    "sg:phone":"+49 40/5703132",
    "sg:postcode":"22523",
    "sg:province":"Hamburg",
    "wof:name":"Christel Weper",
    "wof:placetype":"venue"
},
  "geometry": {"coordinates":[9.903198,53.609051],"type":"Point"}
}