{
  "type": "Feature",
  "properties": {
    "iso:country":"DE",
    "sg:address":"Marienstr. 20",
    "sg:city":"Dresden",
    "sg:phone":"+49 351/4900799",
    "sg:postcode":"01067",
    "sg:province":"Sachsen",
    "wof:name":"P. Breiter",
    "wof:placetype":"venue"
},
  "geometry": {"coordinates":[13.733377,51.047127],"type":"Point"}
}