{
  "type": "Feature",
  "properties": {
    "iso:country":"DE",
    "sg:address":"Dorfstr. 29",
    "sg:city":"Friedberg",
    "sg:phone":"+49 8208/406",
    "sg:postcode":"86316",
    "sg:province":"Bayern",
    "wof:name":"M. Huber",
    "wof:placetype":"venue"
},
  "geometry": {"coordinates":[11.056438446,48.321975708],"type":"Point"}
}