{
  "type": "Feature",
  "properties": {
    "iso:country":"DE",
    "sg:address":"Rudolf-Diesel-Ring 13",
    "sg:city":"Sauerlach",
    "sg:postcode":"82054",
    "sg:province":"Bayern",
    "wof:name":"Hps Vermittlungs- Und Handelsgesellschaft Mbh",
    "wof:placetype":"venue"
},
  "geometry": {"coordinates":[11.6627321243,47.9701271057],"type":"Point"}
}