{
  "type": "Feature",
  "properties": {
    "iso:country":"DE",
    "sg:address":"Am Kirchberg 2",
    "sg:city":"Ostheim",
    "sg:phone":"+49 9779/525",
    "sg:postcode":"97645",
    "sg:province":"Bayern",
    "wof:name":"Ev.-luth. Pfarramt Urspringen",
    "wof:placetype":"venue"
},
  "geometry": {"coordinates":[10.1365261078,50.4568405151],"type":"Point"}
}