{
  "type": "Feature",
  "properties": {
    "iso:country":"DE",
    "sg:address":"Waalwijker Str. 14",
    "sg:city":"Unna",
    "sg:phone":"+49 2303/65455",
    "sg:postcode":"59425",
    "sg:province":"Nordrhein-Westfalen",
    "wof:name":"Haaselop Steuerberatungs Gmbh",
    "wof:placetype":"venue"
},
  "geometry": {"coordinates":[7.694811821,51.5531349182],"type":"Point"}
}