{
  "type": "Feature",
  "properties": {
    "iso:country":"DE",
    "sg:address":"Nordstr. 9",
    "sg:city":"Saterland",
    "sg:phone":"+49 4498/919260",
    "sg:postcode":"26683",
    "sg:province":"Niedersachsen",
    "wof:name":"Meik R\u00f6bber",
    "wof:placetype":"venue"
},
  "geometry": {"coordinates":[7.701331,53.153835],"type":"Point"}
}