{
  "type": "Feature",
  "properties": {
    "iso:country":"DE",
    "sg:address":"Gie\u00dfener Str. 2",
    "sg:city":"Pohlheim",
    "sg:phone":"+49 6403/1009",
    "sg:postcode":"35415",
    "sg:province":"Hessen",
    "wof:name":"H. K\u00fcc\u00fckkaplan",
    "wof:placetype":"venue"
},
  "geometry": {"coordinates":[8.7085075378,50.5332069397],"type":"Point"}
}