{
  "type": "Feature",
  "properties": {
    "iso:country":"DE",
    "sg:address":"In den Erlen 4",
    "sg:city":"Kreuztal",
    "sg:phone":"+49 2732/80227",
    "sg:postcode":"57223",
    "sg:province":"Nordrhein-Westfalen",
    "wof:name":"Robert Bald Zimmerei Und S\u00e4gewerk",
    "wof:placetype":"venue"
},
  "geometry": {"coordinates":[7.9902648926,50.9593048096],"type":"Point"}
}