{
  "type": "Feature",
  "properties": {
    "iso:country":"DE",
    "sg:address":"Warener Str. 53",
    "sg:city":"Berlin",
    "sg:phone":"+49 30/56498825",
    "sg:postcode":"12683",
    "sg:province":"Berlin",
    "wof:name":"Krankentransport Lehmann Gmbh",
    "wof:placetype":"venue"
},
  "geometry": {"coordinates":[13.56515,52.515862],"type":"Point"}
}