{
  "type": "Feature",
  "properties": {
    "iso:country":"DE",
    "sg:address":"Breslauer Str. 6",
    "sg:city":"Hanau",
    "sg:phone":"+49 6181/13901",
    "sg:postcode":"63452",
    "sg:province":"Hessen",
    "wof:name":"Meier-bau Gmbh",
    "wof:placetype":"venue"
},
  "geometry": {"coordinates":[8.926363945,50.1447143555],"type":"Point"}
}