{
  "type": "Feature",
  "properties": {
    "iso:country":"DE",
    "sg:address":"F\u00e4rbergasse 5",
    "sg:city":"Bad Aibling",
    "sg:phone":"+49 8061/9369147",
    "sg:postcode":"83043",
    "sg:province":"Bayern",
    "wof:name":"Petra Keitz-dimpflmeier Rechtsanw\u00e4ltin",
    "wof:placetype":"venue"
},
  "geometry": {"coordinates":[12.0093078613,47.8647346497],"type":"Point"}
}