{
  "type": "Feature",
  "properties": {
    "iso:country":"DE",
    "sg:address":"Ludwig-Ganghofer-Str. 1",
    "sg:city":"Meitingen",
    "sg:phone":"+49 8271/2778",
    "sg:postcode":"86405",
    "sg:province":"Bayern",
    "wof:name":"Rosa Lebender",
    "wof:placetype":"venue"
},
  "geometry": {"coordinates":[10.850995,48.549309],"type":"Point"}
}