{
  "type": "Feature",
  "properties": {
    "iso:country":"DE",
    "sg:address":"Sprockhofer Str. 16",
    "sg:city":"Lindwedel",
    "sg:phone":"+49 5073/577",
    "sg:postcode":"29690",
    "sg:province":"Niedersachsen",
    "wof:name":"R\u00fcdiger Krull",
    "wof:placetype":"venue"
},
  "geometry": {"coordinates":[9.694508,52.610615],"type":"Point"}
}