{
  "type": "Feature",
  "properties": {
    "iso:country":"DE",
    "sg:address":"Meraner Weg 1",
    "sg:city":"Freiburg",
    "sg:phone":"+49 761/42436",
    "sg:postcode":"79111",
    "sg:province":"Baden-W\u00fcrttemberg",
    "wof:name":"Schlechtendahl Und Wopperer Partnerschaft",
    "wof:placetype":"venue"
},
  "geometry": {"coordinates":[7.815553,47.978382],"type":"Point"}
}