{
  "type": "Feature",
  "properties": {
    "iso:country":"DE",
    "sg:address":"Hauptstr. 37",
    "sg:city":"Walluf",
    "sg:phone":"+49 6123/72348",
    "sg:postcode":"65396",
    "sg:province":"Hessen",
    "wof:name":"Katholisches Pfarramt St. Johannes D. T.",
    "wof:placetype":"venue"
},
  "geometry": {"coordinates":[8.1593885422,50.0347175598],"type":"Point"}
}