{
  "type": "Feature",
  "properties": {
    "iso:country":"DE",
    "sg:address":"Bleichestr. 7",
    "sg:city":"Villingen-Schwenningen",
    "sg:phone":"+49 7721/903421",
    "sg:postcode":"78050",
    "sg:province":"Baden-W\u00fcrttemberg",
    "wof:name":"Michaela Maurer Rechtsanw\u00e4ltin",
    "wof:placetype":"venue"
},
  "geometry": {"coordinates":[8.4586582184,48.0543518066],"type":"Point"}
}