{
  "type": "Feature",
  "properties": {
    "iso:country":"DE",
    "sg:address":"Weg zum Roten See 24",
    "sg:city":"Br\u00fcel",
    "sg:phone":"+49 38483/20367",
    "sg:postcode":"19412",
    "sg:province":"Mecklenburg-Vorpommern",
    "wof:name":"Siegrid Zankow",
    "wof:placetype":"venue"
},
  "geometry": {"coordinates":[11.714093,53.729176],"type":"Point"}
}