{
  "type": "Feature",
  "properties": {
    "iso:country":"DE",
    "sg:address":"Goethestr. 9",
    "sg:city":"Schopfheim",
    "sg:phone":"+49 7622/7141",
    "sg:postcode":"79650",
    "sg:province":"Baden-W\u00fcrttemberg",
    "wof:name":"H. Schneegass Gmbh Bauschlosserei",
    "wof:placetype":"venue"
},
  "geometry": {"coordinates":[7.8276982307,47.647819519],"type":"Point"}
}