{
  "type": "Feature",
  "properties": {
    "iso:country":"DE",
    "sg:address":"Lamprechtstr. 58",
    "sg:city":"Daaden",
    "sg:phone":"+49 2743/727",
    "sg:postcode":"57567",
    "sg:province":"Rheinland-Pfalz",
    "wof:name":"Dig Immobilien Vertriebs Gmbh",
    "wof:placetype":"venue"
},
  "geometry": {"coordinates":[7.9665851593,50.7376403809],"type":"Point"}
}