{
  "type": "Feature",
  "properties": {
    "iso:country":"DE",
    "sg:address":"Bergfrieden 29",
    "sg:city":"Ostercappeln",
    "sg:phone":"+49 5473/1438",
    "sg:postcode":"49179",
    "sg:province":"Niedersachsen",
    "wof:name":"K. Mondry",
    "wof:placetype":"venue"
},
  "geometry": {"coordinates":[8.187788,52.337627],"type":"Point"}
}