{
  "type": "Feature",
  "properties": {
    "iso:country":"DE",
    "sg:address":"Mainstr. 14",
    "sg:city":"W\u00f6rth",
    "sg:phone":"+49 9372/5326",
    "sg:postcode":"63939",
    "sg:province":"Bayern",
    "wof:name":"Josef H\u00f6rnig Schiffer",
    "wof:placetype":"venue"
},
  "geometry": {"coordinates":[9.15693,49.798649],"type":"Point"}
}