{
  "type": "Feature",
  "properties": {
    "iso:country":"DE",
    "sg:address":"Drachenseestr. 18",
    "sg:city":"M\u00fcnchen",
    "sg:postcode":"81373",
    "sg:province":"Bayern",
    "wof:name":"Carl Max Prager",
    "wof:placetype":"venue"
},
  "geometry": {"coordinates":[11.5314035416,48.118522644],"type":"Point"}
}