{
  "type": "Feature",
  "properties": {
    "iso:country":"DE",
    "sg:address":"Strohg\u00e4ustr. 22",
    "sg:city":"Stuttgart",
    "sg:phone":"+49 711/8261636",
    "sg:postcode":"70435",
    "sg:province":"Baden-W\u00fcrttemberg",
    "wof:name":"F. Und W. Erbis Gmbh",
    "wof:placetype":"venue"
},
  "geometry": {"coordinates":[9.157637,48.836124],"type":"Point"}
}