{
  "type": "Feature",
  "properties": {
    "iso:country":"DE",
    "sg:address":"Daimlerstr. 16",
    "sg:city":"Korb",
    "sg:phone":"+49 7151/31460",
    "sg:postcode":"71404",
    "sg:province":"Baden-W\u00fcrttemberg",
    "wof:name":"Buhl & Nad Gmbh",
    "wof:placetype":"venue"
},
  "geometry": {"coordinates":[9.366069,48.83699],"type":"Point"}
}