{
  "type": "Feature",
  "properties": {
    "iso:country":"DE",
    "sg:address":"Im Felster 19",
    "sg:city":"Neuwied",
    "sg:phone":"+49 2631/97390",
    "sg:postcode":"56567",
    "sg:province":"Rheinland-Pfalz",
    "wof:name":"Baark Bau- Und Ingenieurges. Mbh",
    "wof:placetype":"venue"
},
  "geometry": {"coordinates":[7.411626,50.451931],"type":"Point"}
}