{
  "type": "Feature",
  "properties": {
    "iso:country":"DE",
    "sg:address":"Hilgen\u00e4cker 7",
    "sg:city":"Borken",
    "sg:phone":"+49 5682/1723",
    "sg:postcode":"34582",
    "sg:province":"Hessen",
    "wof:name":"Otto Rininsland",
    "wof:placetype":"venue"
},
  "geometry": {"coordinates":[9.3251791,51.0253601074],"type":"Point"}
}