{
  "type": "Feature",
  "properties": {
    "iso:country":"DE",
    "sg:address":"Ziegelfeld 7",
    "sg:city":"Mauern",
    "sg:postcode":"85419",
    "sg:province":"Bayern",
    "wof:name":"Informationstechnologie Alexander Schneeweis Gmbh",
    "wof:placetype":"venue"
},
  "geometry": {"coordinates":[11.898975,48.517193],"type":"Point"}
}