{
  "type": "Feature",
  "properties": {
    "iso:country":"DE",
    "sg:address":"Steinweg 2",
    "sg:city":"Stolberg",
    "sg:phone":"+49 2402/81529",
    "sg:postcode":"52222",
    "sg:province":"Nordrhein-Westfalen",
    "wof:name":"Ursula Graaf",
    "wof:placetype":"venue"
},
  "geometry": {"coordinates":[6.21756,50.782589],"type":"Point"}
}