{
  "type": "Feature",
  "properties": {
    "iso:country":"DE",
    "sg:address":"Alte Heerstr 1",
    "sg:city":"Georgsmarienh\u00fctte",
    "sg:phone":"+49 5401/86400",
    "sg:postcode":"49124",
    "sg:province":"Niedersachsen",
    "wof:name":"Gustav Berning Gmbh & Co Kg",
    "wof:placetype":"venue"
},
  "geometry": {"coordinates":[8.08324,52.221901],"type":"Point"}
}