{
  "type": "Feature",
  "properties": {
    "iso:country":"DE",
    "sg:address":"Graweland 103",
    "sg:city":"Enger",
    "sg:phone":"+49 5224/2701",
    "sg:postcode":"32130",
    "sg:province":"Nordrhein-Westfalen",
    "wof:name":"Helmut Tholen Ingenieur",
    "wof:placetype":"venue"
},
  "geometry": {"coordinates":[8.5242137909,52.1292533875],"type":"Point"}
}