{
  "type": "Feature",
  "properties": {
    "iso:country":"DE",
    "sg:address":"Kulturstr. 18",
    "sg:city":"Freising",
    "sg:phone":"+49 8161/82146",
    "sg:postcode":"85356",
    "sg:province":"Bayern",
    "wof:name":"S. Aul",
    "wof:placetype":"venue"
},
  "geometry": {"coordinates":[11.760998,48.396286],"type":"Point"}
}