{
  "type": "Feature",
  "properties": {
    "iso:country":"DE",
    "sg:address":"Schondorfer Str. 10",
    "sg:city":"M\u00fcnchen",
    "sg:phone":"+49 89/7144879",
    "sg:postcode":"81379",
    "sg:province":"Bayern",
    "wof:name":"Julius Grundl Ingenieur",
    "wof:placetype":"venue"
},
  "geometry": {"coordinates":[11.5158672333,48.1079673767],"type":"Point"}
}