{
  "type": "Feature",
  "properties": {
    "iso:country":"DE",
    "sg:address":"Minnholzweg 3 A",
    "sg:city":"Kronberg",
    "sg:postcode":"61476",
    "sg:province":"Hessen",
    "wof:name":"Bernhard Wulf Verlag",
    "wof:placetype":"venue"
},
  "geometry": {"coordinates":[8.5167007446,50.1789741516],"type":"Point"}
}