{
  "type": "Feature",
  "properties": {
    "iso:country":"DE",
    "sg:address":"Longericher Str. 538 a",
    "sg:city":"K\u00f6ln",
    "sg:phone":"+49 221/5995871",
    "sg:postcode":"50739",
    "sg:province":"Nordrhein-Westfalen",
    "wof:name":"Helmut Sch\u00e4fer",
    "wof:placetype":"venue"
},
  "geometry": {"coordinates":[6.913046,50.998337],"type":"Point"}
}