{
  "type": "Feature",
  "properties": {
    "iso:country":"DE",
    "sg:address":"Gremsdorf",
    "sg:city":"Gremsdorf",
    "sg:phone":"+49 9193/8853",
    "sg:postcode":"91350",
    "sg:province":"Bayern",
    "wof:name":"Kreissparkasse H\u00f6chstadt, A.d. Aisch",
    "wof:placetype":"venue"
},
  "geometry": {"coordinates":[10.834309,49.696651],"type":"Point"}
}