{
  "type": "Feature",
  "properties": {
    "iso:country":"DE",
    "sg:address":"Kasseler Str. 51",
    "sg:city":"C\u00f6lbe",
    "sg:phone":"+49 6421/85011",
    "sg:postcode":"35091",
    "sg:province":"Hessen",
    "wof:name":"Hein",
    "wof:placetype":"venue"
},
  "geometry": {"coordinates":[8.7818050385,50.8466491699],"type":"Point"}
}