{
  "type": "Feature",
  "properties": {
    "iso:country":"DE",
    "sg:address":"Industriestr. 8",
    "sg:city":"Gr\u00fcnsfeld",
    "sg:phone":"+49 9346/1772",
    "sg:postcode":"97947",
    "sg:province":"Baden-W\u00fcrttemberg",
    "wof:name":"Helmut Glaefcke Gmbh",
    "wof:placetype":"venue"
},
  "geometry": {"coordinates":[9.755346,49.606537],"type":"Point"}
}