{
  "type": "Feature",
  "properties": {
    "iso:country":"DE",
    "sg:address":"Sonnenberg 32",
    "sg:city":"Kuddew\u00f6rde",
    "sg:postcode":"22958",
    "sg:province":"Schleswig-Holstein",
    "wof:name":"Sms Sport Marketing Service Gmbh",
    "wof:placetype":"venue"
},
  "geometry": {"coordinates":[10.381035,53.572239],"type":"Point"}
}