{
  "type": "Feature",
  "properties": {
    "iso:country":"DE",
    "sg:address":"Waldstr. 6",
    "sg:city":"Bad Endbach",
    "sg:phone":"+49 6464/209",
    "sg:postcode":"35080",
    "sg:province":"Hessen",
    "wof:name":"G\u00e4stehaus Elisabeth Becker",
    "wof:placetype":"venue"
},
  "geometry": {"coordinates":[8.4736003876,50.7932891846],"type":"Point"}
}