{
  "type": "Feature",
  "properties": {
    "iso:country":"DE",
    "sg:address":"R\u00f6merstr. 41",
    "sg:city":"Obernburg",
    "sg:postcode":"63785",
    "sg:province":"Bayern",
    "wof:name":"Des Un Sell - Schenken Und Genie\u00dfen Gmbh",
    "wof:placetype":"venue"
},
  "geometry": {"coordinates":[9.1468858719,49.8412284851],"type":"Point"}
}