{
  "type": "Feature",
  "properties": {
    "iso:country":"DE",
    "sg:address":"Taruper Hauptstr. 85",
    "sg:city":"Flensburg",
    "sg:phone":"+49 461/61367",
    "sg:postcode":"24943",
    "sg:province":"Schleswig-Holstein",
    "wof:name":"Friedrich Hansen",
    "wof:placetype":"venue"
},
  "geometry": {"coordinates":[9.4946460724,54.7764511108],"type":"Point"}
}