{
  "type": "Feature",
  "properties": {
    "iso:country":"DE",
    "sg:address":"An der Talle 21",
    "sg:city":"Paderborn",
    "sg:phone":"+49 5251/881705",
    "sg:postcode":"33102",
    "sg:province":"Nordrhein-Westfalen",
    "wof:name":"Stadt Paderborn",
    "wof:placetype":"venue"
},
  "geometry": {"coordinates":[8.7641496658,51.7513198853],"type":"Point"}
}