{
  "type": "Feature",
  "properties": {
    "iso:country":"DE",
    "sg:address":"Reiherberg",
    "sg:city":"Celle",
    "sg:phone":"+49 5086/530",
    "sg:postcode":"29229",
    "sg:province":"Niedersachsen",
    "wof:name":"Herbert Schlag Bw-kantine",
    "wof:placetype":"venue"
},
  "geometry": {"coordinates":[10.0891275406,52.6785392761],"type":"Point"}
}