{
  "type": "Feature",
  "properties": {
    "iso:country":"DE",
    "sg:address":"Kattenvenner Str. 78",
    "sg:city":"Ladbergen",
    "sg:phone":"+49 5485/1511",
    "sg:postcode":"49549",
    "sg:province":"Nordrhein-Westfalen",
    "wof:name":"Friedrich Lepper",
    "wof:placetype":"venue"
},
  "geometry": {"coordinates":[7.758758,52.13472],"type":"Point"}
}