{
  "type": "Feature",
  "properties": {
    "iso:country":"DE",
    "sg:address":"Quierschieder Str. 25",
    "sg:city":"Quierschied",
    "sg:phone":"+49 6897/66200",
    "sg:postcode":"66287",
    "sg:province":"Saarland",
    "wof:name":"Dieter Schirra Masseur",
    "wof:placetype":"venue"
},
  "geometry": {"coordinates":[7.025512,49.305145],"type":"Point"}
}