{
  "type": "Feature",
  "properties": {
    "iso:country":"DE",
    "sg:address":"Kurt-Schumacher-Str. 18",
    "sg:city":"Braunschweig",
    "sg:phone":"+49 531/701050",
    "sg:postcode":"38102",
    "sg:province":"Niedersachsen",
    "wof:name":"Vereinte Kranken- Versicherung Ag",
    "wof:placetype":"venue"
},
  "geometry": {"coordinates":[10.5337905884,52.2561607361],"type":"Point"}
}