{
  "type": "Feature",
  "properties": {
    "iso:country":"DE",
    "sg:address":"Kirchplatz 5",
    "sg:city":"Bottrop",
    "sg:phone":"+49 2041/22035",
    "sg:postcode":"46236",
    "sg:province":"Nordrhein-Westfalen",
    "wof:name":"Fleischer Und Koch Rechtsanw\u00e4lte Und Notar",
    "wof:placetype":"venue"
},
  "geometry": {"coordinates":[6.9256930351,51.5212783813],"type":"Point"}
}