{
  "type": "Feature",
  "properties": {
    "iso:country":"DE",
    "sg:city":"Eberstadt",
    "sg:phone":"+49 4971/341631",
    "sg:postcode":"74246",
    "sg:province":"Baden-W\u00fcrttemberg",
    "wof:name":"Volksbank Ellhofen Eg",
    "wof:placetype":"venue"
},
  "geometry": {"coordinates":[9.320985,49.18008],"type":"Point"}
}