{
  "type": "Feature",
  "properties": {
    "iso:country":"DE",
    "sg:address":"Marktplatz 6",
    "sg:city":"K\u00f6nigsberg",
    "sg:phone":"+49 9525/92210",
    "sg:postcode":"97486",
    "sg:province":"Bayern",
    "wof:name":"Hotel-restaurant Goldner Stern",
    "wof:placetype":"venue"
},
  "geometry": {"coordinates":[10.570309639,50.081577301],"type":"Point"}
}