{
  "type": "Feature",
  "properties": {
    "iso:country":"DE",
    "sg:address":"Lange Gasse 10",
    "sg:city":"Spalt",
    "sg:phone":"+49 9175/380",
    "sg:postcode":"91174",
    "sg:province":"Bayern",
    "wof:name":"Karl Lutz Eisenwaren",
    "wof:placetype":"venue"
},
  "geometry": {"coordinates":[10.9234132767,49.1786193848],"type":"Point"}
}