{
  "type": "Feature",
  "properties": {
    "iso:country":"DE",
    "sg:address":"Sophienstr. 40",
    "sg:city":"Frankfurt",
    "sg:postcode":"15230",
    "sg:province":"Brandenburg",
    "wof:name":"Dr. Reimann Immobilien Ver- Waltungs- Und Vertriebs Gmbh",
    "wof:placetype":"venue"
},
  "geometry": {"coordinates":[14.5440864563,52.3479537964],"type":"Point"}
}