{
  "type": "Feature",
  "properties": {
    "iso:country":"DE",
    "sg:address":"Hoopter Str. 3",
    "sg:city":"Winsen",
    "sg:postcode":"21423",
    "sg:province":"Niedersachsen",
    "wof:name":"Holger Hoffmann Tankstellengesellschaft Mbh",
    "wof:placetype":"venue"
},
  "geometry": {"coordinates":[10.200961113,53.3666687012],"type":"Point"}
}