{
  "type": "Feature",
  "properties": {
    "iso:country":"DE",
    "sg:city":"Aubstadt",
    "sg:phone":"+49 9761/727",
    "sg:postcode":"97633",
    "sg:province":"Bayern",
    "wof:name":"Raiffeisenbank Aubstadt Eg",
    "wof:placetype":"venue"
},
  "geometry": {"coordinates":[10.43621,50.333164],"type":"Point"}
}