{
  "type": "Feature",
  "properties": {
    "iso:country":"DE",
    "sg:address":"Pottenstetten 18",
    "sg:city":"Burglengenfeld",
    "sg:phone":"+49 9471/6110",
    "sg:postcode":"93133",
    "sg:province":"Bayern",
    "wof:name":"Richard Steinbauer",
    "wof:placetype":"venue"
},
  "geometry": {"coordinates":[12.0198850632,49.2388038635],"type":"Point"}
}