{
  "type": "Feature",
  "properties": {
    "iso:country":"DE",
    "sg:address":"Im Sonnern 1",
    "sg:city":"St. Goarshausen",
    "sg:phone":"+49 6771/7220",
    "sg:postcode":"56346",
    "sg:province":"Rheinland-Pfalz",
    "wof:name":"Hotel Christian",
    "wof:placetype":"venue"
},
  "geometry": {"coordinates":[7.7347579002,50.1485443115],"type":"Point"}
}