{
  "type": "Feature",
  "properties": {
    "iso:country":"DE",
    "sg:address":"Nidderstr 10",
    "sg:city":"Hirzenhain",
    "sg:phone":"+49 6045/680",
    "sg:postcode":"63697",
    "sg:province":"Hessen",
    "wof:name":"Buderus Guss Gmbh",
    "wof:placetype":"venue"
},
  "geometry": {"coordinates":[9.134356,50.393196],"type":"Point"}
}