{
  "type": "Feature",
  "properties": {
    "iso:country":"DE",
    "sg:address":"Schachenaueler Str. 30",
    "sg:city":"Lohmar",
    "sg:phone":"+49 2206/2582",
    "sg:postcode":"53797",
    "sg:province":"Nordrhein-Westfalen",
    "wof:name":"Walter Clever",
    "wof:placetype":"venue"
},
  "geometry": {"coordinates":[7.274121,50.898167],"type":"Point"}
}