{
  "type": "Feature",
  "properties": {
    "iso:country":"DE",
    "sg:address":"Von-der-Gablentz-Str. 19",
    "sg:city":"Berlin",
    "sg:phone":"+49 30/417760",
    "sg:postcode":"13403",
    "sg:province":"Berlin",
    "wof:name":"Gse Ingenieurges. Mbh",
    "wof:placetype":"venue"
},
  "geometry": {"coordinates":[13.326335907,52.5655555725],"type":"Point"}
}