{
  "type": "Feature",
  "properties": {
    "iso:country":"DE",
    "sg:address":"Rudolf-Diesel-Str. 5",
    "sg:city":"Pei\u00dfenberg",
    "sg:phone":"+49 8803/5045",
    "sg:postcode":"82380",
    "sg:province":"Bayern",
    "wof:name":"F\u00fchrer U. Weingartner Tankstellenverpachtung",
    "wof:placetype":"venue"
},
  "geometry": {"coordinates":[11.053524971,47.7825508118],"type":"Point"}
}