{
  "type": "Feature",
  "properties": {
    "iso:country":"DE",
    "sg:address":"Wittgensteiner Str. 16",
    "sg:city":"Lahntal",
    "sg:phone":"+49 6420/6211",
    "sg:postcode":"35094",
    "sg:province":"Hessen",
    "wof:name":"Erwin Littig",
    "wof:placetype":"venue"
},
  "geometry": {"coordinates":[8.7025690079,50.8609542847],"type":"Point"}
}