{
  "type": "Feature",
  "properties": {
    "iso:country":"DE",
    "sg:address":"Kreuzstr. 70",
    "sg:city":"Bad Kreuznach",
    "sg:phone":"+49 671/32102",
    "sg:postcode":"55543",
    "sg:province":"Rheinland-Pfalz",
    "wof:name":"Freya",
    "wof:placetype":"venue"
},
  "geometry": {"coordinates":[7.8583660126,49.8425636292],"type":"Point"}
}