{
  "type": "Feature",
  "properties": {
    "iso:country":"DE",
    "sg:address":"Im Gewerbegebiet 2",
    "sg:city":"W\u00e4schenbeuren",
    "sg:phone":"+49 7172/5960",
    "sg:postcode":"73116",
    "sg:province":"Baden-W\u00fcrttemberg",
    "wof:name":"Alfred Heckenlaible",
    "wof:placetype":"venue"
},
  "geometry": {"coordinates":[9.6956596375,48.7602806091],"type":"Point"}
}