{
  "type": "Feature",
  "properties": {
    "iso:country":"DE",
    "sg:address":"Unter Den Linden 25",
    "sg:city":"Herford",
    "sg:phone":"+49 4952/2154013",
    "sg:postcode":"32052",
    "sg:province":"Nordrhein-Westfalen",
    "wof:name":"Ls-edv Datentechnik Gmbh",
    "wof:placetype":"venue"
},
  "geometry": {"coordinates":[8.6698579788,52.1125450134],"type":"Point"}
}