{
  "type": "Feature",
  "properties": {
    "iso:country":"DE",
    "sg:address":"Lanterstr. 105",
    "sg:city":"Oberhausen",
    "sg:phone":"+49 208/651506",
    "sg:postcode":"46149",
    "sg:province":"Nordrhein-Westfalen",
    "wof:name":"Wolfgang Mohr",
    "wof:placetype":"venue"
},
  "geometry": {"coordinates":[6.8246760368,51.5051612854],"type":"Point"}
}