{
  "type": "Feature",
  "properties": {
    "iso:country":"DE",
    "sg:address":"Tannenweg 12",
    "sg:city":"Ettlingen",
    "sg:phone":"+49 7243/4235",
    "sg:postcode":"76275",
    "sg:province":"Baden-W\u00fcrttemberg",
    "wof:name":"Schott Bauelemente Handel Und Montage Gmbh",
    "wof:placetype":"venue"
},
  "geometry": {"coordinates":[8.380435,48.950596],"type":"Point"}
}