{
  "type": "Feature",
  "properties": {
    "iso:country":"DE",
    "sg:address":"Am Felsenkeller 5",
    "sg:city":"Bovenden",
    "sg:phone":"+49 551/83605",
    "sg:postcode":"37120",
    "sg:province":"Niedersachsen",
    "wof:name":"Gaus Gesellschaft F\u00fcr Automa- Tisierte Systementwicklung Mbh",
    "wof:placetype":"venue"
},
  "geometry": {"coordinates":[9.9339962006,51.588508606],"type":"Point"}
}