{
  "type": "Feature",
  "properties": {
    "iso:country":"DE",
    "sg:address":"Postfach 2642",
    "sg:city":"Goslar",
    "sg:postcode":"38616",
    "sg:province":"Niedersachsen",
    "wof:name":"Stiftung Kehmstedt",
    "wof:placetype":"venue"
},
  "geometry": {"coordinates":[10.4278297424,51.9044914246],"type":"Point"}
}