{
  "type": "Feature",
  "properties": {
    "iso:country":"DE",
    "sg:address":"Richard-Strauss-Str. 70",
    "sg:city":"M\u00fcnchen",
    "sg:phone":"+49 89/91059850",
    "sg:postcode":"81679",
    "sg:province":"Bayern",
    "wof:name":"Moosheimer Gmbh",
    "wof:placetype":"venue"
},
  "geometry": {"coordinates":[11.6161298752,48.1455726624],"type":"Point"}
}