{
  "type": "Feature",
  "properties": {
    "iso:country":"DE",
    "sg:address":"Wilhelm-Lantermann-Str. 62",
    "sg:city":"Dinslaken",
    "sg:phone":"+49 2064/57693",
    "sg:postcode":"46535",
    "sg:province":"Nordrhein-Westfalen",
    "wof:name":"Pizzeria Isolbella",
    "wof:placetype":"venue"
},
  "geometry": {"coordinates":[6.7375020981,51.5662498474],"type":"Point"}
}