{
  "type": "Feature",
  "properties": {
    "iso:country":"DE",
    "sg:address":"Im H\u00f6rnchen 12",
    "sg:city":"Bergisch Gladbach",
    "sg:phone":"+49 2204",
    "sg:postcode":"51429",
    "sg:province":"Nordrhein-Westfalen",
    "wof:name":"Www.dr.goetzke.de",
    "wof:placetype":"venue"
},
  "geometry": {"coordinates":[7.204521,50.955238],"type":"Point"}
}