{
  "type": "Feature",
  "properties": {
    "iso:country":"DE",
    "sg:address":"Schiffergasse 24",
    "sg:city":"Wiesbaden",
    "sg:phone":"+49 611/21714",
    "sg:postcode":"65201",
    "sg:province":"Hessen",
    "wof:name":"Fritz Rossel",
    "wof:placetype":"venue"
},
  "geometry": {"coordinates":[8.197539,50.043159],"type":"Point"}
}