{
  "type": "Feature",
  "properties": {
    "iso:country":"DE",
    "sg:address":"Postgasse 18",
    "sg:city":"Elchingen",
    "sg:phone":"+49 7308/2444",
    "sg:postcode":"89275",
    "sg:province":"Bayern",
    "wof:name":"Joachim Stader",
    "wof:placetype":"venue"
},
  "geometry": {"coordinates":[10.0859718323,48.4486312866],"type":"Point"}
}