{
  "type": "Feature",
  "properties": {
    "iso:country":"DE",
    "sg:address":"Lilienthalstr. 41",
    "sg:city":"Flensburg",
    "sg:phone":"+49 461/570330",
    "sg:postcode":"24941",
    "sg:province":"Schleswig-Holstein",
    "wof:name":"Funkmietwagen Und Taxi Hansen Gmbh",
    "wof:placetype":"venue"
},
  "geometry": {"coordinates":[9.398853302,54.76820755],"type":"Point"}
}