{
  "type": "Feature",
  "properties": {
    "iso:country":"DE",
    "sg:address":"Neugasse 44",
    "sg:city":"Dillenburg",
    "sg:phone":"+49 2771/21340",
    "sg:postcode":"35687",
    "sg:province":"Hessen",
    "wof:name":"G. Breidenstein",
    "wof:placetype":"venue"
},
  "geometry": {"coordinates":[8.306956,50.720253],"type":"Point"}
}