{
  "type": "Feature",
  "properties": {
    "iso:country":"DE",
    "sg:address":"Werner-Sylten-Str. 8",
    "sg:city":"Gotha",
    "sg:phone":"+49 3621/751075",
    "sg:postcode":"99867",
    "sg:province":"Th\u00fcringen",
    "wof:name":"Glm Elektro-hausger\u00e4te Gmbh",
    "wof:placetype":"venue"
},
  "geometry": {"coordinates":[10.6769762039,50.9482460022],"type":"Point"}
}