{
  "type": "Feature",
  "properties": {
    "iso:country":"DE",
    "sg:address":"Bahnhofstr. 14",
    "sg:city":"Nottuln",
    "sg:phone":"+49 2509/228",
    "sg:postcode":"48301",
    "sg:province":"Nordrhein-Westfalen",
    "wof:name":"Willi Ge\u00dfmann",
    "wof:placetype":"venue"
},
  "geometry": {"coordinates":[7.4245939255,51.8967170715],"type":"Point"}
}