{
  "type": "Feature",
  "properties": {
    "iso:country":"DE",
    "sg:address":"Albstrasse 15",
    "sg:city":"Tuttlingen",
    "sg:phone":"+49 4974/6178223",
    "sg:postcode":"78532",
    "sg:province":"Baden-W\u00fcrttemberg",
    "wof:name":"Habitat Shirts",
    "wof:placetype":"venue"
},
  "geometry": {"coordinates":[8.861535,48.002201],"type":"Point"}
}