{
  "type": "Feature",
  "properties": {
    "iso:country":"DE",
    "sg:address":"Mooswinkel 16",
    "sg:city":"Bochum",
    "sg:phone":"+49 2327/71068",
    "sg:postcode":"44869",
    "sg:province":"Nordrhein-Westfalen",
    "wof:name":"Manfred G\u00f6rke",
    "wof:placetype":"venue"
},
  "geometry": {"coordinates":[7.170085907,51.4436950684],"type":"Point"}
}