{
  "type": "Feature",
  "properties": {
    "iso:country":"DE",
    "sg:address":"Niedersachsenring 26",
    "sg:city":"W\u00f6lpinghausen",
    "sg:phone":"+49 5037/98747",
    "sg:postcode":"31556",
    "sg:province":"Niedersachsen",
    "wof:name":"Dittmar Wach- Und Sicherheits- Dienste Hausverwaltungen Und",
    "wof:placetype":"venue"
},
  "geometry": {"coordinates":[9.256974,52.410606],"type":"Point"}
}