{
  "type": "Feature",
  "properties": {
    "iso:country":"DE",
    "sg:address":"Waldstr. 5",
    "sg:city":"Ebermannsdorf",
    "sg:phone":"+49 9624/485",
    "sg:postcode":"92263",
    "sg:province":"Bayern",
    "wof:name":"Hans Scharl Gmbh",
    "wof:placetype":"venue"
},
  "geometry": {"coordinates":[11.934913,49.394836],"type":"Point"}
}