{
  "type": "Feature",
  "properties": {
    "iso:country":"DE",
    "sg:address":"Hindenburgring 9",
    "sg:city":"Espelkamp",
    "sg:phone":"+49 4957/722090",
    "sg:postcode":"32339",
    "sg:province":"Nordrhein-Westfalen",
    "wof:name":"Rosenthal Ag",
    "wof:placetype":"venue"
},
  "geometry": {"coordinates":[8.6284399033,52.3711395264],"type":"Point"}
}