{
  "type": "Feature",
  "properties": {
    "iso:country":"DE",
    "sg:address":"Glattbacher Str. 6",
    "sg:city":"Aschaffenburg",
    "sg:phone":"+49 6021/421956",
    "sg:postcode":"63741",
    "sg:province":"Bayern",
    "wof:name":"M. Merbach",
    "wof:placetype":"venue"
},
  "geometry": {"coordinates":[9.148133,49.982437],"type":"Point"}
}