{
  "type": "Feature",
  "properties": {
    "iso:country":"DE",
    "sg:address":"Stuttgarter Str 22",
    "sg:city":"Weil",
    "sg:phone":"+49 7033/527011",
    "sg:postcode":"71263",
    "sg:province":"Baden-W\u00fcrttemberg",
    "wof:name":"Kreissparkasse B\u00f6blingen",
    "wof:placetype":"venue"
},
  "geometry": {"coordinates":[-91.410309,32.879776],"type":"Point"}
}