{
  "type": "Feature",
  "properties": {
    "iso:country":"DE",
    "sg:address":"Zehnthausstr. 20",
    "sg:city":"Cochem",
    "sg:phone":"+49 2671/8698",
    "sg:postcode":"56812",
    "sg:province":"Rheinland-Pfalz",
    "wof:name":"Joachim G\u00f6bel",
    "wof:placetype":"venue"
},
  "geometry": {"coordinates":[7.169907093,50.1462364197],"type":"Point"}
}