{
  "type": "Feature",
  "properties": {
    "iso:country":"DE",
    "sg:address":"Gai\u00dfacher Str. 7",
    "sg:city":"M\u00fcnchen",
    "sg:postcode":"81371",
    "sg:province":"Bayern",
    "wof:name":"Erotix Video Und Fashion Shop Gmbh",
    "wof:placetype":"venue"
},
  "geometry": {"coordinates":[11.549325,48.114479],"type":"Point"}
}