{
  "type": "Feature",
  "properties": {
    "iso:country":"DE",
    "sg:address":"M\u00fchlenweg 10",
    "sg:city":"Oyten",
    "sg:phone":"+49 4207/2558",
    "sg:postcode":"28876",
    "sg:province":"Niedersachsen",
    "wof:name":"Johann Duhn",
    "wof:placetype":"venue"
},
  "geometry": {"coordinates":[9.032598,53.059811],"type":"Point"}
}