{
  "type": "Feature",
  "properties": {
    "iso:country":"DE",
    "sg:address":"Ziegelstr. 21",
    "sg:city":"Fellbach",
    "sg:phone":"+49 711/584937",
    "sg:postcode":"70734",
    "sg:province":"Baden-W\u00fcrttemberg",
    "wof:name":"Monika Schindler Steuerberaterin",
    "wof:placetype":"venue"
},
  "geometry": {"coordinates":[9.2800245285,48.8067474365],"type":"Point"}
}