{
  "type": "Feature",
  "properties": {
    "iso:country":"DE",
    "sg:address":"Kyffh\u00e4userstr. 7",
    "sg:city":"D\u00fcsseldorf",
    "sg:phone":"+49 211/954999",
    "sg:postcode":"40545",
    "sg:province":"Nordrhein-Westfalen",
    "wof:name":"Prahl Recke Gesellschaft F\u00fcr Marken- Und",
    "wof:placetype":"venue"
},
  "geometry": {"coordinates":[6.754848,51.231888],"type":"Point"}
}