{
  "type": "Feature",
  "properties": {
    "iso:country":"DE",
    "sg:address":"Marienthal",
    "sg:city":"Schweina",
    "sg:postcode":"36448",
    "sg:province":"Th\u00fcringen",
    "wof:name":"K\u00f6nig",
    "wof:placetype":"venue"
},
  "geometry": {"coordinates":[10.331263,50.810406],"type":"Point"}
}