{
  "type": "Feature",
  "properties": {
    "iso:country":"DE",
    "sg:address":"F\u00fcrstenfelder Str. 7 Feldgeding",
    "sg:city":"Bergkirchen",
    "sg:phone":"+49 8131/361460",
    "sg:postcode":"85232",
    "sg:province":"Bayern",
    "wof:name":"Franz Sandmeier Mineral\u00d6l Gmbh",
    "wof:placetype":"venue"
},
  "geometry": {"coordinates":[11.364796,48.25901],"type":"Point"}
}