{
  "type": "Feature",
  "properties": {
    "iso:country":"DE",
    "sg:address":"Tulpenstr. 23",
    "sg:city":"Wuppertal",
    "sg:phone":"+49 202/599389",
    "sg:postcode":"42283",
    "sg:province":"Nordrhein-Westfalen",
    "wof:name":"Michael Kaiser",
    "wof:placetype":"venue"
},
  "geometry": {"coordinates":[7.1838140488,51.2694969177],"type":"Point"}
}