{
  "type": "Feature",
  "properties": {
    "iso:country":"DE",
    "sg:address":"Friedrich-Ebert-Str. 53",
    "sg:city":"Ingolstadt",
    "sg:postcode":"85055",
    "sg:province":"Bayern",
    "wof:name":"In-bau Gmbh & Co. Kg",
    "wof:placetype":"venue"
},
  "geometry": {"coordinates":[11.442487,48.773689],"type":"Point"}
}