{
  "type": "Feature",
  "properties": {
    "iso:country":"DE",
    "sg:address":"M\u00f6rikestr. 18",
    "sg:city":"Weil der Stadt",
    "sg:postcode":"71263",
    "sg:province":"Baden-W\u00fcrttemberg",
    "wof:name":"Zingg Gmbh",
    "wof:placetype":"venue"
},
  "geometry": {"coordinates":[8.850876,48.775913],"type":"Point"}
}