{
  "type": "Feature",
  "properties": {
    "iso:country":"DE",
    "sg:address":"M\u00fchlenstr. 1",
    "sg:city":"Rotenburg",
    "sg:phone":"+49 4261/93700",
    "sg:postcode":"27356",
    "sg:province":"Niedersachsen",
    "wof:name":"Holger Winkel Claus Buhrfeind Und Winkelvos",
    "wof:placetype":"venue"
},
  "geometry": {"coordinates":[9.3992500305,53.1079521179],"type":"Point"}
}