{
  "type": "Feature",
  "properties": {
    "iso:country":"DE",
    "sg:address":"Bredelarer Str. 5",
    "sg:city":"Diemelsee",
    "sg:phone":"+49 5633/827",
    "sg:postcode":"34519",
    "sg:province":"Hessen",
    "wof:name":"Waldecker Bank Eg",
    "wof:placetype":"venue"
},
  "geometry": {"coordinates":[8.798394,51.368019],"type":"Point"}
}