{
  "type": "Feature",
  "properties": {
    "iso:country":"DE",
    "sg:address":"Klosterkamp 7",
    "sg:city":"Magdeburg",
    "sg:phone":"+49 391/501078",
    "sg:postcode":"39126",
    "sg:province":"Sachsen-Anhalt",
    "wof:name":"Grv-zentralwerkstatt",
    "wof:placetype":"venue"
},
  "geometry": {"coordinates":[11.667989,52.158585],"type":"Point"}
}