{
  "type": "Feature",
  "properties": {
    "iso:country":"DE",
    "sg:address":"Heitkampweg 5",
    "sg:city":"Ibbenb\u00fcren",
    "sg:phone":"+49 5451/745597",
    "sg:postcode":"49479",
    "sg:province":"Nordrhein-Westfalen",
    "wof:name":"Jos. Sch\u00fcrmann",
    "wof:placetype":"venue"
},
  "geometry": {"coordinates":[7.6685328484,52.3136634827],"type":"Point"}
}