{
  "type": "Feature",
  "properties": {
    "iso:country":"DE",
    "sg:address":"Pelikanstr. 2",
    "sg:city":"Peine",
    "sg:phone":"+49 5171/22899",
    "sg:postcode":"31228",
    "sg:province":"Niedersachsen",
    "wof:name":"Vincenz Schoeler",
    "wof:placetype":"venue"
},
  "geometry": {"coordinates":[10.1911296844,52.3372764587],"type":"Point"}
}