{
  "type": "Feature",
  "properties": {
    "iso:country":"DE",
    "sg:address":"Ebertstr. 20",
    "sg:city":"Gelsenkirchen",
    "sg:phone":"+49 209/23180",
    "sg:postcode":"45879",
    "sg:province":"Nordrhein-Westfalen",
    "wof:name":"Harld Schuster Rechtsanwalt",
    "wof:placetype":"venue"
},
  "geometry": {"coordinates":[7.094066143,51.5107192993],"type":"Point"}
}