{
  "type": "Feature",
  "properties": {
    "iso:country":"DE",
    "sg:address":"Brahmsweg 1",
    "sg:city":"Freiberg",
    "sg:phone":"+49 7141/71183",
    "sg:postcode":"71691",
    "sg:province":"Baden-W\u00fcrttemberg",
    "wof:name":"Mayer Gmbh",
    "wof:placetype":"venue"
},
  "geometry": {"coordinates":[9.193262,48.925278],"type":"Point"}
}