{
  "type": "Feature",
  "properties": {
    "iso:country":"DE",
    "sg:address":"Hermann-Unger-Allee 26",
    "sg:city":"Meerbusch",
    "sg:phone":"+49 2132/4778",
    "sg:postcode":"40667",
    "sg:province":"Nordrhein-Westfalen",
    "wof:name":"Paul Rusche Architekt",
    "wof:placetype":"venue"
},
  "geometry": {"coordinates":[6.688252,51.253952],"type":"Point"}
}