{
  "type": "Feature",
  "properties": {
    "iso:country":"DE",
    "sg:address":"Grambartstr. 16",
    "sg:city":"Hannover",
    "sg:phone":"+49 511/3521367",
    "sg:postcode":"30165",
    "sg:province":"Niedersachsen",
    "wof:name":"Kommunalausr\u00fcstungen M. Holz Vertriebs- Und",
    "wof:placetype":"venue"
},
  "geometry": {"coordinates":[9.7061767578,52.406337738],"type":"Point"}
}