{
  "type": "Feature",
  "properties": {
    "iso:country":"DE",
    "sg:address":"Achtmorgenweg 20",
    "sg:city":"Wachtberg",
    "sg:phone":"+49 228/346366",
    "sg:postcode":"53343",
    "sg:province":"Nordrhein-Westfalen",
    "wof:name":"Dr. Gerhard Kothmann Tierarzt",
    "wof:placetype":"venue"
},
  "geometry": {"coordinates":[7.1349039078,50.6220588684],"type":"Point"}
}