{
  "type": "Feature",
  "properties": {
    "iso:country":"DE",
    "sg:address":"Allenfeldstr. 56",
    "sg:city":"Merchweiler",
    "sg:phone":"+49 6825/88758",
    "sg:postcode":"66589",
    "sg:province":"Saarland",
    "wof:name":"Felix R\u00f6hlinger Gmbh",
    "wof:placetype":"venue"
},
  "geometry": {"coordinates":[7.0624580383,49.3555374146],"type":"Point"}
}