{
  "type": "Feature",
  "properties": {
    "iso:country":"DE",
    "sg:address":"Zellaer Str. 101",
    "sg:city":"Suhl",
    "sg:phone":"+49 3681/461703",
    "sg:postcode":"98528",
    "sg:province":"Th\u00fcringen",
    "wof:name":"Th\u00fcringer Hof",
    "wof:placetype":"venue"
},
  "geometry": {"coordinates":[10.7348871231,50.6358718872],"type":"Point"}
}