{
  "type": "Feature",
  "properties": {
    "iso:country":"DE",
    "sg:address":"Siedlerweg 39",
    "sg:city":"Minden",
    "sg:phone":"+49 571/5800364",
    "sg:postcode":"32429",
    "sg:province":"Nordrhein-Westfalen",
    "wof:name":"American Megatech Company Inc., Germany",
    "wof:placetype":"venue"
},
  "geometry": {"coordinates":[8.8943300247,52.2720603943],"type":"Point"}
}