{
  "type": "Feature",
  "properties": {
    "iso:country":"DE",
    "sg:address":"Schwachhauser Heerstr. 71",
    "sg:city":"Bremen",
    "sg:phone":"+49 421/3479414",
    "sg:postcode":"28211",
    "sg:province":"Bremen",
    "wof:name":"Wolfgang Lehmann",
    "wof:placetype":"venue"
},
  "geometry": {"coordinates":[8.8366689682,53.0822372437],"type":"Point"}
}