{
  "type": "Feature",
  "properties": {
    "iso:country":"DE",
    "sg:address":"Glockenbrunnenstr. 4",
    "sg:city":"Konstanz",
    "sg:phone":"+49 7533/5186",
    "sg:postcode":"78465",
    "sg:province":"Baden-W\u00fcrttemberg",
    "wof:name":"Typo Kunze Fotosatz Gmbh",
    "wof:placetype":"venue"
},
  "geometry": {"coordinates":[9.119572,47.732155],"type":"Point"}
}