{
  "type": "Feature",
  "properties": {
    "iso:country":"DE",
    "sg:address":"Segelmacherweg",
    "sg:city":"Rostock",
    "sg:phone":"+49 381/1200083",
    "sg:postcode":"18109",
    "sg:province":"Mecklenburg-Vorpommern",
    "wof:name":"Baugenossenschaft Neptun Eg",
    "wof:placetype":"venue"
},
  "geometry": {"coordinates":[12.078040123,54.1451454163],"type":"Point"}
}