{
  "type": "Feature",
  "properties": {
    "iso:country":"DE",
    "sg:address":"Herforder Str. 2",
    "sg:city":"Bad Salzuflen",
    "sg:phone":"+49 5222/9530",
    "sg:postcode":"32105",
    "sg:province":"Nordrhein-Westfalen",
    "wof:name":"Ges. F. Verm\u00f6gensverwaltg. Mbh",
    "wof:placetype":"venue"
},
  "geometry": {"coordinates":[8.7415161133,52.0854797363],"type":"Point"}
}