{
  "type": "Feature",
  "properties": {
    "iso:country":"DE",
    "sg:address":"Krondorfer Str. 117",
    "sg:city":"Wolfen",
    "sg:phone":"+49 3494/21520",
    "sg:postcode":"06766",
    "sg:province":"Sachsen-Anhalt",
    "wof:name":"Hgp Hydro-geo-plan- Consult Gmbh",
    "wof:placetype":"venue"
},
  "geometry": {"coordinates":[12.2613143921,51.6664390564],"type":"Point"}
}