{
  "type": "Feature",
  "properties": {
    "iso:country":"DE",
    "sg:address":"Schillingstr. 30",
    "sg:city":"Berlin",
    "sg:phone":"+49 30/4122351",
    "sg:postcode":"13403",
    "sg:province":"Berlin",
    "wof:name":"Bauernst\u00fcbl",
    "wof:placetype":"venue"
},
  "geometry": {"coordinates":[13.3213014603,52.5692367554],"type":"Point"}
}