{
  "type": "Feature",
  "properties": {
    "iso:country":"DE",
    "sg:address":"Frankenstr. 7",
    "sg:city":"Eschau",
    "sg:phone":"+49 9374/8239",
    "sg:postcode":"63863",
    "sg:province":"Bayern",
    "wof:name":"P. Wierschen Anlageberater",
    "wof:placetype":"venue"
},
  "geometry": {"coordinates":[9.2553501129,49.8285903931],"type":"Point"}
}