{
  "type": "Feature",
  "properties": {
    "iso:country":"DE",
    "sg:address":"Bismarckstr. 8",
    "sg:city":"G\u00f6nnheim",
    "sg:phone":"+49 6322/63537",
    "sg:postcode":"67161",
    "sg:province":"Rheinland-Pfalz",
    "wof:name":"Heinz Walter Weinanbau",
    "wof:placetype":"venue"
},
  "geometry": {"coordinates":[8.2383985519,49.4490776062],"type":"Point"}
}