{
  "type": "Feature",
  "properties": {
    "iso:country":"DE",
    "sg:address":"Hauptstr. 65",
    "sg:city":"Heilbad Heiligenstadt",
    "sg:phone":"+49 3606/2604",
    "sg:postcode":"37308",
    "sg:province":"Th\u00fcringen",
    "wof:name":"J. Ga\u00dfmann",
    "wof:placetype":"venue"
},
  "geometry": {"coordinates":[10.185058,51.315998],"type":"Point"}
}