{
  "type": "Feature",
  "properties": {
    "iso:country":"DE",
    "sg:address":"Kiebitzmoor 1",
    "sg:city":"Preetz",
    "sg:phone":"+49 38323/71155",
    "sg:postcode":"18445",
    "sg:province":"Mecklenburg-Vorpommern",
    "wof:name":"A. G\u00e4rtner",
    "wof:placetype":"venue"
},
  "geometry": {"coordinates":[13.0138168335,54.3496627808],"type":"Point"}
}