{
  "type": "Feature",
  "properties": {
    "iso:country":"DE",
    "sg:address":"Burgstr. 14",
    "sg:city":"Ravensburg",
    "sg:phone":"+49 751/33456",
    "sg:postcode":"88212",
    "sg:province":"Baden-W\u00fcrttemberg",
    "wof:name":"R\u00e4uberh\u00f6hle",
    "wof:placetype":"venue"
},
  "geometry": {"coordinates":[9.6146202087,47.7799873352],"type":"Point"}
}