{
  "type": "Feature",
  "properties": {
    "iso:country":"DE",
    "sg:address":"Calenberger Str. 24",
    "sg:city":"Hannover",
    "sg:phone":"+49 511/911050",
    "sg:postcode":"30169",
    "sg:province":"Niedersachsen",
    "wof:name":"Insititut F\u00fcr \u00d6kologie Und Naturschutz Niedersachsen",
    "wof:placetype":"venue"
},
  "geometry": {"coordinates":[9.7264566422,52.3701591492],"type":"Point"}
}