{
  "type": "Feature",
  "properties": {
    "iso:country":"DE",
    "sg:address":"Klein S\u00fcstedter Str. 9",
    "sg:city":"Uelzen",
    "sg:phone":"+49 581/15106",
    "sg:postcode":"29525",
    "sg:province":"Niedersachsen",
    "wof:name":"Helmut Niebuhr",
    "wof:placetype":"venue"
},
  "geometry": {"coordinates":[10.489066,52.936123],"type":"Point"}
}