{
  "type": "Feature",
  "properties": {
    "iso:country":"DE",
    "sg:address":"Kurstr. 10",
    "sg:city":"Neustadt",
    "sg:phone":"+49 2683/31102",
    "sg:postcode":"53577",
    "sg:province":"Rheinland-Pfalz",
    "wof:name":"Hotel Westerw\u00e4lder Hof",
    "wof:placetype":"venue"
},
  "geometry": {"coordinates":[7.3974328041,50.5977363586],"type":"Point"}
}