{
  "type": "Feature",
  "properties": {
    "iso:country":"DE",
    "sg:address":"Diekstraat 7",
    "sg:city":"Norderfriedrichskoog",
    "sg:postcode":"25870",
    "sg:province":"Schleswig-Holstein",
    "wof:name":"Nfk Finanzcontor Gmbh & Co. Kg",
    "wof:placetype":"venue"
},
  "geometry": {"coordinates":[8.892755,54.403877],"type":"Point"}
}