{
  "type": "Feature",
  "properties": {
    "iso:country":"DE",
    "sg:address":"Josef-Wirmer-Str. 1",
    "sg:city":"Warburg",
    "sg:phone":"+49 5641/2922",
    "sg:postcode":"34414",
    "sg:province":"Nordrhein-Westfalen",
    "wof:name":"Warburger Grillst\u00fcbchen",
    "wof:placetype":"venue"
},
  "geometry": {"coordinates":[9.1475296021,51.488368988],"type":"Point"}
}