{
  "type": "Feature",
  "properties": {
    "iso:country":"DE",
    "sg:address":"Gompitzer H\u00f6he 2",
    "sg:city":"Pennrich",
    "sg:postcode":"01462",
    "wof:name":"Aldi Gmbh & Co. Kg",
    "wof:placetype":"venue"
},
  "geometry": {"coordinates":[13.6240196228,51.0432891846],"type":"Point"}
}