{
  "type": "Feature",
  "properties": {
    "iso:country":"DE",
    "sg:address":"Helenenstr. 2",
    "sg:city":"Dinslaken",
    "sg:phone":"+49 2064/57285",
    "sg:postcode":"46537",
    "sg:province":"Nordrhein-Westfalen",
    "wof:name":"H. Nix Wettannahme",
    "wof:placetype":"venue"
},
  "geometry": {"coordinates":[6.724143,51.568699],"type":"Point"}
}