{
  "type": "Feature",
  "properties": {
    "iso:country":"DE",
    "sg:address":"Madamenweg 173",
    "sg:city":"Braunschweig",
    "sg:phone":"+49 531/80080",
    "sg:postcode":"38118",
    "sg:province":"Niedersachsen",
    "wof:name":"H. M\u00fcller-becker",
    "wof:placetype":"venue"
},
  "geometry": {"coordinates":[10.508883,52.261494],"type":"Point"}
}