{
  "type": "Feature",
  "properties": {
    "iso:country":"DE",
    "sg:address":"Gro\u00dfthannensteig 3",
    "sg:city":"Hutthurm",
    "sg:postcode":"94116",
    "sg:province":"Bayern",
    "wof:name":"Novicap Immobilien- Und Kapitalanlagenvermittlung Gmbh",
    "wof:placetype":"venue"
},
  "geometry": {"coordinates":[13.5141925812,48.6963729858],"type":"Point"}
}