{
  "type": "Feature",
  "properties": {
    "iso:country":"DE",
    "sg:address":"Alfred-Delp-Str. 37",
    "sg:city":"Rodgau",
    "sg:phone":"+49 6106/602667",
    "sg:postcode":"63110",
    "sg:province":"Hessen",
    "wof:name":"Baucon Projektentwicklungs- Gesellschaft Mbh",
    "wof:placetype":"venue"
},
  "geometry": {"coordinates":[8.8817539215,50.0438156128],"type":"Point"}
}