{
  "type": "Feature",
  "properties": {
    "iso:country":"DE",
    "sg:address":"Ernst-Grube-Str. 1",
    "sg:city":"Bernburg",
    "sg:phone":"+49 3471/3255",
    "sg:postcode":"06406",
    "sg:province":"Sachsen-Anhalt",
    "wof:name":"Multiport Recycling Gmbh",
    "wof:placetype":"venue"
},
  "geometry": {"coordinates":[11.759118,51.790009],"type":"Point"}
}