{
  "type": "Feature",
  "properties": {
    "iso:country":"DE",
    "sg:address":"Brunecker Str. 27",
    "sg:city":"Herten",
    "sg:phone":"+49 2366/55955",
    "sg:postcode":"45701",
    "sg:province":"Nordrhein-Westfalen",
    "wof:name":"Meis Und Eichholz Gmbh",
    "wof:placetype":"venue"
},
  "geometry": {"coordinates":[7.1086678505,51.6167869568],"type":"Point"}
}