{
  "type": "Feature",
  "properties": {
    "iso:country":"DE",
    "sg:address":"Polenzstr. 43",
    "sg:city":"Lengenfeld",
    "sg:phone":"+49 37606/2892",
    "sg:postcode":"08485",
    "sg:province":"Sachsen",
    "wof:name":"Wolfgang Richter",
    "wof:placetype":"venue"
},
  "geometry": {"coordinates":[12.3789319992,50.5715332031],"type":"Point"}
}