{
  "type": "Feature",
  "properties": {
    "iso:country":"DE",
    "sg:address":"Bahnhofweg 28",
    "sg:city":"Lo\u00dfburg",
    "sg:phone":"+49 7446/1685",
    "sg:postcode":"72290",
    "sg:province":"Baden-W\u00fcrttemberg",
    "wof:name":"Karl Grieshaber",
    "wof:placetype":"venue"
},
  "geometry": {"coordinates":[8.453152,48.414314],"type":"Point"}
}