{
  "type": "Feature",
  "properties": {
    "iso:country":"DE",
    "sg:address":"Kermisdahlufer 1",
    "sg:city":"Kleve",
    "sg:phone":"+49 2821/23307",
    "sg:postcode":"47533",
    "sg:province":"Nordrhein-Westfalen",
    "wof:name":"Kleindorp Bauunternehmung Gmbh & Co. Kg",
    "wof:placetype":"venue"
},
  "geometry": {"coordinates":[6.140819,51.785084],"type":"Point"}
}