{
  "type": "Feature",
  "properties": {
    "iso:country":"DE",
    "sg:address":"Franzstr. 60",
    "sg:city":"Kamp-Lintfort",
    "sg:postcode":"47475",
    "sg:province":"Nordrhein-Westfalen",
    "wof:name":"Flughafen Weeze-laarbruch Finanzierungs- Und",
    "wof:placetype":"venue"
},
  "geometry": {"coordinates":[6.5645427704,51.4961395264],"type":"Point"}
}