{
  "type": "Feature",
  "properties": {
    "iso:country":"DE",
    "sg:address":"Plinganserstr. 5",
    "sg:city":"M\u00fcnchen",
    "sg:phone":"+49 89/74791400",
    "sg:postcode":"81369",
    "sg:province":"Bayern",
    "wof:name":"Heinrich Meyer Rechtsanwalt",
    "wof:placetype":"venue"
},
  "geometry": {"coordinates":[11.5413398743,48.1210632324],"type":"Point"}
}