{
  "type": "Feature",
  "properties": {
    "iso:country":"DE",
    "sg:address":"Ernststr. 25",
    "sg:city":"Berlin",
    "sg:phone":"+49 30/5328251",
    "sg:postcode":"12437",
    "sg:province":"Berlin",
    "wof:name":"Hausma Gmbh",
    "wof:placetype":"venue"
},
  "geometry": {"coordinates":[13.489543,52.465027],"type":"Point"}
}