{
  "type": "Feature",
  "properties": {
    "iso:country":"DE",
    "sg:address":"Ebinger Str. 47",
    "sg:city":"M\u00fchldorf",
    "sg:phone":"+49 8631/8590",
    "sg:postcode":"84453",
    "sg:province":"Bayern",
    "wof:name":"Klaus Laske",
    "wof:placetype":"venue"
},
  "geometry": {"coordinates":[12.470284,48.243217],"type":"Point"}
}