{
  "type": "Feature",
  "properties": {
    "iso:country":"DE",
    "sg:address":"Dittersdorfer Str. 40",
    "sg:city":"Amtsberg",
    "sg:phone":"+49 37209/2228",
    "sg:postcode":"09439",
    "sg:province":"Sachsen",
    "wof:name":"Eckhard Haase",
    "wof:placetype":"venue"
},
  "geometry": {"coordinates":[13.011478,50.75922],"type":"Point"}
}