{
  "type": "Feature",
  "properties": {
    "iso:country":"DE",
    "sg:address":"Grashoffstr. 11",
    "sg:city":"Bremerhaven",
    "sg:phone":"+49 471/9313303",
    "sg:postcode":"27570",
    "sg:province":"Bremen",
    "wof:name":"C. Fiedler Inh. Hans-dieter Lautenbach",
    "wof:placetype":"venue"
},
  "geometry": {"coordinates":[8.592139,53.532192],"type":"Point"}
}