{
  "type": "Feature",
  "properties": {
    "iso:country":"DE",
    "sg:address":"Hauptstr 2a",
    "sg:city":"Drochow",
    "sg:phone":"+49 35754/7490",
    "sg:postcode":"01994",
    "sg:province":"Brandenburg",
    "wof:name":"Europarts Drochow Gmbh",
    "wof:placetype":"venue"
},
  "geometry": {"coordinates":[13.923226,51.562611],"type":"Point"}
}