{
  "type": "Feature",
  "properties": {
    "iso:country":"DE",
    "sg:address":"Schillerstr. 49",
    "sg:city":"Bielefeld",
    "sg:phone":"+49 521/9828020",
    "sg:postcode":"33609",
    "sg:province":"Nordrhein-Westfalen",
    "wof:name":"Wsw Schmidt Werbung Und Promotion Gmbh",
    "wof:placetype":"venue"
},
  "geometry": {"coordinates":[8.5505781174,52.0415992737],"type":"Point"}
}