{
  "type": "Feature",
  "properties": {
    "iso:country":"DE",
    "sg:address":"Emmetstr. 24",
    "sg:city":"Olsberg",
    "sg:phone":"+49 2962/744",
    "sg:postcode":"59939",
    "sg:province":"Nordrhein-Westfalen",
    "wof:name":"Karl-josef Bathen",
    "wof:placetype":"venue"
},
  "geometry": {"coordinates":[8.4907159805,51.359172821],"type":"Point"}
}