{
  "type": "Feature",
  "properties": {
    "iso:country":"DE",
    "sg:address":"Feldtorstr. 1",
    "sg:city":"N\u00f6rten-Hardenberg",
    "sg:phone":"+49 5503/1221",
    "sg:postcode":"37176",
    "sg:province":"Niedersachsen",
    "wof:name":"Karl-h. Lambrecht",
    "wof:placetype":"venue"
},
  "geometry": {"coordinates":[9.966729,51.635296],"type":"Point"}
}