{
  "type": "Feature",
  "properties": {
    "iso:country":"DE",
    "sg:address":"Holzweg 14",
    "sg:city":"Oberursel",
    "sg:phone":"+49 6171/57014",
    "sg:postcode":"61440",
    "sg:province":"Hessen",
    "wof:name":"Bernhard Kempermann Rechtsanwalt",
    "wof:placetype":"venue"
},
  "geometry": {"coordinates":[8.5809001923,50.2025718689],"type":"Point"}
}