{
  "type": "Feature",
  "properties": {
    "iso:country":"DE",
    "sg:address":"Friedberger Landstr. 122",
    "sg:city":"Frankfurt am Main",
    "sg:phone":"+49 69/439331",
    "sg:postcode":"60316",
    "sg:province":"Hessen",
    "wof:name":"Reiseb\u00fcro Im Nordend Lufthansa City Center",
    "wof:placetype":"venue"
},
  "geometry": {"coordinates":[8.692312,50.127277],"type":"Point"}
}