{
  "type": "Feature",
  "properties": {
    "iso:country":"DE",
    "sg:address":"M\u00fcnsterstr. 21",
    "sg:city":"L\u00fcnen",
    "sg:phone":"+49 2306/73668",
    "sg:postcode":"44534",
    "sg:province":"Nordrhein-Westfalen",
    "wof:name":"H\u00e4nschen Angenehm",
    "wof:placetype":"venue"
},
  "geometry": {"coordinates":[7.5244832039,51.6168365479],"type":"Point"}
}