{
  "type": "Feature",
  "properties": {
    "iso:country":"DE",
    "sg:address":"Zeppelinstr. 9",
    "sg:city":"Ulm",
    "sg:phone":"+49 731/60974",
    "sg:postcode":"89075",
    "sg:province":"Baden-W\u00fcrttemberg",
    "wof:name":"Ulm Consult Planungsges. Mbh",
    "wof:placetype":"venue"
},
  "geometry": {"coordinates":[9.982853,48.406624],"type":"Point"}
}