{
  "type": "Feature",
  "properties": {
    "iso:country":"DE",
    "sg:address":"Maschweg 11",
    "sg:city":"Wienhausen",
    "sg:phone":"+49 5149/752",
    "sg:postcode":"29342",
    "sg:province":"Niedersachsen",
    "wof:name":"Sylvia Wiebe Reinigung 2000 E. K.",
    "wof:placetype":"venue"
},
  "geometry": {"coordinates":[10.155544281,52.5820655823],"type":"Point"}
}