{
  "type": "Feature",
  "properties": {
    "iso:country":"DE",
    "sg:address":"Landwehr 35B",
    "sg:city":"Oberhausen",
    "sg:phone":"+49 208/27723",
    "sg:postcode":"46049",
    "sg:province":"Nordrhein-Westfalen",
    "wof:name":"E. Knopp",
    "wof:placetype":"venue"
},
  "geometry": {"coordinates":[6.836702,51.459621],"type":"Point"}
}