{
  "type": "Feature",
  "properties": {
    "iso:country":"DE",
    "sg:address":"Gutenbergstr. 5-7",
    "sg:city":"Greven",
    "sg:phone":"+49 4925/7191920",
    "sg:postcode":"48268",
    "sg:province":"Nordrhein-Westfalen",
    "wof:name":"Wentker Druck Ek",
    "wof:placetype":"venue"
},
  "geometry": {"coordinates":[7.5980548859,52.0940551758],"type":"Point"}
}