{
  "type": "Feature",
  "properties": {
    "iso:country":"DE",
    "sg:address":"Emil-Beerli-Str. 20",
    "sg:city":"Mettmann",
    "sg:phone":"+49 2104/917900",
    "sg:postcode":"40822",
    "sg:province":"Nordrhein-Westfalen",
    "wof:name":"Burberg-eicker Technische Federn Gmbh",
    "wof:placetype":"venue"
},
  "geometry": {"coordinates":[6.9938521385,51.2498703003],"type":"Point"}
}