{
  "type": "Feature",
  "properties": {
    "iso:country":"DE",
    "sg:address":"Hannoversche Str. 86",
    "sg:city":"Giesen",
    "sg:phone":"+49 5121/770166",
    "sg:postcode":"31180",
    "sg:province":"Niedersachsen",
    "wof:name":"Werkzeug- Und Vorrichtungsbau Peter Van Kempen Gmbh",
    "wof:placetype":"venue"
},
  "geometry": {"coordinates":[9.917661,52.200771],"type":"Point"}
}