{
  "type": "Feature",
  "properties": {
    "iso:country":"DE",
    "sg:address":"Bischbergstr. 30 Schweinheim",
    "sg:city":"Aschaffenburg",
    "sg:phone":"+49 4960/2191047",
    "sg:postcode":"63743",
    "sg:province":"Bayern",
    "wof:name":"Heinrich Kunkel Gmbh & Co. Strassen- U. Tiefbau",
    "wof:placetype":"venue"
},
  "geometry": {"coordinates":[9.135922,49.932804],"type":"Point"}
}