{
  "type": "Feature",
  "properties": {
    "iso:country":"DE",
    "sg:address":"Georgengasse 7",
    "sg:city":"Fritzlar",
    "sg:postcode":"34560",
    "sg:province":"Hessen",
    "wof:name":"Range Gmbh",
    "wof:placetype":"venue"
},
  "geometry": {"coordinates":[9.279863,51.131199],"type":"Point"}
}