{
  "type": "Feature",
  "properties": {
    "iso:country":"DE",
    "sg:address":"Thanheimer Str. 50",
    "sg:city":"Bisingen",
    "sg:phone":"+49 7476/8330",
    "sg:postcode":"72406",
    "sg:province":"Baden-W\u00fcrttemberg",
    "wof:name":"Peter Rager",
    "wof:placetype":"venue"
},
  "geometry": {"coordinates":[8.927143,48.303452],"type":"Point"}
}