{
  "type": "Feature",
  "properties": {
    "iso:country":"DE",
    "sg:address":"Brahmsstr. 30",
    "sg:city":"Monheim",
    "sg:phone":"+49 2173/56171",
    "sg:postcode":"40789",
    "sg:province":"Nordrhein-Westfalen",
    "wof:name":"Eberhard Emmler Steuerberater",
    "wof:placetype":"venue"
},
  "geometry": {"coordinates":[6.903386116,51.0887031555],"type":"Point"}
}