{
  "type": "Feature",
  "properties": {
    "iso:country":"DE",
    "sg:address":"Otto-Hahn-Str. 25",
    "sg:city":"Sindelfingen",
    "sg:phone":"+49 7031/383096",
    "sg:postcode":"71069",
    "sg:province":"Baden-W\u00fcrttemberg",
    "wof:name":"A. Milla Rechtsanw\u00e4lte",
    "wof:placetype":"venue"
},
  "geometry": {"coordinates":[8.9775161743,48.7275924683],"type":"Point"}
}