{
  "type": "Feature",
  "properties": {
    "iso:country":"DE",
    "sg:address":"Siegsdorfer Str. 9 a",
    "sg:city":"M\u00fcnchen",
    "sg:phone":"+49 89/432945",
    "sg:postcode":"81825",
    "sg:province":"Bayern",
    "wof:name":"Manfred Landsmann",
    "wof:placetype":"venue"
},
  "geometry": {"coordinates":[11.652349,48.124191],"type":"Point"}
}