{
  "type": "Feature",
  "properties": {
    "iso:country":"DE",
    "sg:address":"Sudetenstr. 21",
    "sg:city":"Kirchheim",
    "sg:phone":"+49 7021/84747",
    "sg:postcode":"73230",
    "sg:province":"Baden-W\u00fcrttemberg",
    "wof:name":"Whg Immobilien",
    "wof:placetype":"venue"
},
  "geometry": {"coordinates":[9.470938,48.641483],"type":"Point"}
}