{
  "type": "Feature",
  "properties": {
    "iso:country":"DE",
    "sg:address":"Amselstr. 4",
    "sg:city":"Hille",
    "sg:phone":"+49 5734/7085",
    "sg:postcode":"32479",
    "sg:province":"Nordrhein-Westfalen",
    "wof:name":"Witting Gmbh",
    "wof:placetype":"venue"
},
  "geometry": {"coordinates":[8.7929677963,52.2750053406],"type":"Point"}
}