{
  "type": "Feature",
  "properties": {
    "iso:country":"DE",
    "sg:address":"Heimeranstr. 58",
    "sg:city":"M\u00fcnchen",
    "sg:phone":"+49 89/507136",
    "sg:postcode":"80339",
    "sg:province":"Bayern",
    "wof:name":"Michael Voltz Rechtsanwalt",
    "wof:placetype":"venue"
},
  "geometry": {"coordinates":[11.5365829468,48.1339874268],"type":"Point"}
}