{
  "type": "Feature",
  "properties": {
    "iso:country":"DE",
    "sg:address":"Hans-Pinsel-Str. 9 b",
    "sg:city":"Haar",
    "sg:postcode":"85540",
    "sg:province":"Bayern",
    "wof:name":"Domando Ag",
    "wof:placetype":"venue"
},
  "geometry": {"coordinates":[11.7153625488,48.1086883545],"type":"Point"}
}