{
  "type": "Feature",
  "properties": {
    "iso:country":"DE",
    "sg:address":"Bahnhofstr. 4",
    "sg:city":"Schwabach",
    "sg:phone":"+49 9122/93560",
    "sg:postcode":"91126",
    "sg:province":"Bayern",
    "wof:name":"Hans-dieter Molnar Steuerberater",
    "wof:placetype":"venue"
},
  "geometry": {"coordinates":[11.027132988,49.327999115],"type":"Point"}
}