{
  "type": "Feature",
  "properties": {
    "iso:country":"DE",
    "sg:address":"Am Br\u00fcchelsteg 2",
    "sg:city":"Gro\u00df-Umstadt",
    "sg:phone":"+49 6078/72642",
    "sg:postcode":"64823",
    "sg:province":"Hessen",
    "wof:name":"Karl-werner Jakob",
    "wof:placetype":"venue"
},
  "geometry": {"coordinates":[8.927073,49.873653],"type":"Point"}
}