{
  "type": "Feature",
  "properties": {
    "iso:country":"DE",
    "sg:address":"Heidenreichstr. 13",
    "sg:city":"Schwabach",
    "sg:phone":"+49 911/6327213",
    "sg:postcode":"91126",
    "sg:province":"Bayern",
    "wof:name":"W. Hetzler",
    "wof:placetype":"venue"
},
  "geometry": {"coordinates":[11.0203676224,49.3639144897],"type":"Point"}
}