{
  "type": "Feature",
  "properties": {
    "iso:country":"DE",
    "sg:address":"Am Alten Flugplatz 10",
    "sg:city":"Trier",
    "sg:phone":"+49 651/86097",
    "sg:postcode":"54294",
    "sg:province":"Rheinland-Pfalz",
    "wof:name":"Herresthal & Th\u00f6nnes Gmbh",
    "wof:placetype":"venue"
},
  "geometry": {"coordinates":[6.61186409,49.7296638489],"type":"Point"}
}