{
  "type": "Feature",
  "properties": {
    "iso:country":"DE",
    "sg:address":"Hopfenstr. 6",
    "sg:city":"Attenkirchen",
    "sg:phone":"+49 8168/210",
    "sg:postcode":"85395",
    "sg:province":"Bayern",
    "wof:name":"Johann Wurzer",
    "wof:placetype":"venue"
},
  "geometry": {"coordinates":[11.75707,48.507568],"type":"Point"}
}