{
  "type": "Feature",
  "properties": {
    "iso:country":"DE",
    "sg:address":"Reichsstr. 44",
    "sg:city":"Donauw\u00f6rth",
    "sg:phone":"+49 906/23365",
    "sg:postcode":"86609",
    "sg:province":"Bayern",
    "wof:name":"U. Singer",
    "wof:placetype":"venue"
},
  "geometry": {"coordinates":[10.777571,48.719433],"type":"Point"}
}