{
  "type": "Feature",
  "properties": {
    "iso:country":"DE",
    "sg:address":"Im Gr\u00fcnen Ring 25",
    "sg:city":"Windhagen",
    "sg:phone":"+49 2645/2688",
    "sg:postcode":"53578",
    "sg:province":"Rheinland-Pfalz",
    "wof:name":"Horst Litsch Verlagsvertreter",
    "wof:placetype":"venue"
},
  "geometry": {"coordinates":[7.327945,50.633968],"type":"Point"}
}