{
  "type": "Feature",
  "properties": {
    "iso:country":"DE",
    "sg:address":"Goerdelerstr. 12",
    "sg:city":"Apolda",
    "sg:phone":"+49 3644/555035",
    "sg:postcode":"99510",
    "sg:province":"Th\u00fcringen",
    "wof:name":"Krake-mode",
    "wof:placetype":"venue"
},
  "geometry": {"coordinates":[11.51434,51.024361],"type":"Point"}
}