{
  "type": "Feature",
  "properties": {
    "iso:country":"DE",
    "sg:address":"Steiner Weg 1",
    "sg:city":"Laboe",
    "sg:phone":"+49 4343/7662",
    "sg:postcode":"24235",
    "sg:province":"Schleswig-Holstein",
    "wof:name":"W. Faig Praxis F\u00fcr Krankengymnastik",
    "wof:placetype":"venue"
},
  "geometry": {"coordinates":[10.227945,54.405865],"type":"Point"}
}