{
  "type": "Feature",
  "properties": {
    "iso:country":"DE",
    "sg:address":"Sohler Weg 38",
    "sg:city":"Neuwied",
    "sg:postcode":"56564",
    "sg:province":"Rheinland-Pfalz",
    "wof:name":"Fl\u00fcssiggaslager Verwaltungs Gmbh",
    "wof:placetype":"venue"
},
  "geometry": {"coordinates":[7.4772830009,50.4354133606],"type":"Point"}
}