{
  "type": "Feature",
  "properties": {
    "iso:country":"DE",
    "sg:address":"Bahnhofstr. 94",
    "sg:city":"M\u00fchlacker",
    "sg:phone":"+49 7041/46077",
    "sg:postcode":"75417",
    "sg:province":"Baden-W\u00fcrttemberg",
    "wof:name":"City Terff",
    "wof:placetype":"venue"
},
  "geometry": {"coordinates":[8.8434085846,48.9516792297],"type":"Point"}
}