{
  "type": "Feature",
  "properties": {
    "iso:country":"DE",
    "sg:address":"Edesheimer Str. 42",
    "sg:city":"Edenkoben",
    "sg:phone":"+49 6323/4586",
    "sg:postcode":"67480",
    "sg:province":"Rheinland-Pfalz",
    "wof:name":"Johanna Husfeld Weinanbau",
    "wof:placetype":"venue"
},
  "geometry": {"coordinates":[8.1286754608,49.2751579285],"type":"Point"}
}