{
  "type": "Feature",
  "properties": {
    "iso:country":"DE",
    "sg:address":"Bergwerkstr. 18",
    "sg:city":"Hausen",
    "sg:phone":"+49 7622/2506",
    "sg:postcode":"79688",
    "sg:province":"Baden-W\u00fcrttemberg",
    "wof:name":"W. Hug",
    "wof:placetype":"venue"
},
  "geometry": {"coordinates":[7.8401060104,47.6822967529],"type":"Point"}
}