{
  "type": "Feature",
  "properties": {
    "iso:country":"DE",
    "sg:address":"Am Hohen Gstad 13",
    "sg:city":"G\u00fcnzburg",
    "sg:phone":"+49 8221/33398",
    "sg:postcode":"89312",
    "sg:province":"Bayern",
    "wof:name":"J\u00fcrgen Michalek Finanzberater",
    "wof:placetype":"venue"
},
  "geometry": {"coordinates":[10.2790794373,48.4477806091],"type":"Point"}
}