{
  "type": "Feature",
  "properties": {
    "iso:country":"DE",
    "sg:address":"K\u00f6nigseer Str. 7",
    "sg:city":"Bad Blankenburg",
    "sg:phone":"+49 36741/3423",
    "sg:postcode":"07422",
    "sg:province":"Th\u00fcringen",
    "wof:name":"Elektro-mann",
    "wof:placetype":"venue"
},
  "geometry": {"coordinates":[11.2588376999,50.6851081848],"type":"Point"}
}