{
  "type": "Feature",
  "properties": {
    "iso:country":"DE",
    "sg:address":"Ratoldusstr. 8",
    "sg:city":"Radolfzell",
    "sg:phone":"+49 7732/910150",
    "sg:postcode":"78315",
    "sg:province":"Baden-W\u00fcrttemberg",
    "wof:name":"Alfred Guduscheit",
    "wof:placetype":"venue"
},
  "geometry": {"coordinates":[8.9692516327,47.742767334],"type":"Point"}
}