{
  "type": "Feature",
  "properties": {
    "iso:country":"DE",
    "sg:address":"Hauptstr. 45",
    "sg:city":"Ingoldingen",
    "sg:phone":"+49 7355/7665",
    "sg:postcode":"88456",
    "sg:province":"Baden-W\u00fcrttemberg",
    "wof:name":"Dr. Helmut Feu\u00dfner Tierarzt",
    "wof:placetype":"venue"
},
  "geometry": {"coordinates":[9.7085399628,48.0350875854],"type":"Point"}
}