{
  "type": "Feature",
  "properties": {
    "iso:country":"DE",
    "sg:address":"Ried",
    "sg:city":"Obermaiselstein",
    "sg:phone":"+49 8326/7958",
    "sg:postcode":"87538",
    "sg:province":"Bayern",
    "wof:name":"M. & B. Sch\u00f6ll",
    "wof:placetype":"venue"
},
  "geometry": {"coordinates":[10.2445898056,47.439250946],"type":"Point"}
}