{
  "type": "Feature",
  "properties": {
    "iso:country":"DE",
    "sg:address":"M\u00fchlenstr. 68",
    "sg:city":"Korschenbroich",
    "sg:phone":"+49 2161/641435",
    "sg:postcode":"41352",
    "sg:province":"Nordrhein-Westfalen",
    "wof:name":"Johannes Thei\u00dfen Gmbh",
    "wof:placetype":"venue"
},
  "geometry": {"coordinates":[6.501771,51.195568],"type":"Point"}
}