{
  "type": "Feature",
  "properties": {
    "iso:country":"DE",
    "sg:address":"Halfmannstr. 61",
    "sg:city":"Duisburg",
    "sg:phone":"+49 203/580707",
    "sg:postcode":"47167",
    "sg:province":"Nordrhein-Westfalen",
    "wof:name":"Peter Paul",
    "wof:placetype":"venue"
},
  "geometry": {"coordinates":[6.792447,51.501717],"type":"Point"}
}