{
  "type": "Feature",
  "properties": {
    "iso:country":"DE",
    "sg:address":"Pagenhelle",
    "sg:city":"Lemgo",
    "sg:phone":"+49 5261/213318",
    "sg:postcode":"32657",
    "sg:province":"Nordrhein-Westfalen",
    "wof:name":"Hallenbad Pagenhelle",
    "wof:placetype":"venue"
},
  "geometry": {"coordinates":[8.9129085541,52.0257263184],"type":"Point"}
}