{
  "type": "Feature",
  "properties": {
    "iso:country":"DE",
    "sg:address":"Weinbergstr. 20",
    "sg:city":"Sta\u00dffurt",
    "sg:phone":"+49 3925/621715",
    "sg:postcode":"39418",
    "sg:province":"Sachsen-Anhalt",
    "wof:name":"Hans-joachim D\u00fcnkler",
    "wof:placetype":"venue"
},
  "geometry": {"coordinates":[11.5857772827,51.8554153442],"type":"Point"}
}