{
  "type": "Feature",
  "properties": {
    "iso:country":"DE",
    "sg:address":"Auf der Hofestatt 13",
    "sg:city":"Werl",
    "sg:phone":"+49 2922/83210",
    "sg:postcode":"59457",
    "sg:province":"Nordrhein-Westfalen",
    "wof:name":"Karl Scheiwe",
    "wof:placetype":"venue"
},
  "geometry": {"coordinates":[7.9770097733,51.566860199],"type":"Point"}
}