{
  "type": "Feature",
  "properties": {
    "iso:country":"DE",
    "sg:address":"Hinterheuweiler 28",
    "sg:city":"Heuweiler",
    "sg:phone":"+49 7666/8355",
    "sg:postcode":"79194",
    "sg:province":"Baden-W\u00fcrttemberg",
    "wof:name":"F. Klausmann",
    "wof:placetype":"venue"
},
  "geometry": {"coordinates":[7.9012570381,48.0491714478],"type":"Point"}
}