{
  "type": "Feature",
  "properties": {
    "iso:country":"DE",
    "sg:address":"In den Folgen 3",
    "sg:city":"Langewiesen",
    "sg:phone":"+49 3677/800051",
    "sg:postcode":"98704",
    "sg:province":"Th\u00fcringen",
    "wof:name":"I. Raesch Novo-quarz Gmbh",
    "wof:placetype":"venue"
},
  "geometry": {"coordinates":[10.9710855484,50.6748123169],"type":"Point"}
}