{
  "type": "Feature",
  "properties": {
    "iso:country":"DE",
    "sg:address":"Rother Str. 5",
    "sg:city":"Rednitzhembach",
    "sg:phone":"+49 9122/63640",
    "sg:postcode":"91126",
    "sg:province":"Bayern",
    "wof:name":"Backhaus Lederer Gmbh",
    "wof:placetype":"venue"
},
  "geometry": {"coordinates":[11.078894,49.302929],"type":"Point"}
}