{
  "type": "Feature",
  "properties": {
    "iso:country":"DE",
    "sg:address":"Friedrich-Ebert-Ring 76",
    "sg:city":"Weinheim",
    "sg:phone":"+49 6201/64476",
    "sg:postcode":"69469",
    "sg:province":"Baden-W\u00fcrttemberg",
    "wof:name":"Stockmann Vertriebs Gmbh",
    "wof:placetype":"venue"
},
  "geometry": {"coordinates":[8.6343307495,49.5416297913],"type":"Point"}
}