{
  "type": "Feature",
  "properties": {
    "iso:country":"DE",
    "sg:address":"Hunteburger Str. 1",
    "sg:city":"Damme",
    "sg:phone":"+49 4954/9196870",
    "sg:postcode":"49401",
    "sg:province":"Niedersachsen",
    "wof:name":"Kalkhoff Gmbh",
    "wof:placetype":"venue"
},
  "geometry": {"coordinates":[8.200315,52.520767],"type":"Point"}
}