{
  "type": "Feature",
  "properties": {
    "iso:country":"DE",
    "sg:address":"Wissmarerstr. 4",
    "sg:city":"Wettenberg",
    "sg:phone":"+49 641/8778371",
    "sg:postcode":"35435",
    "sg:province":"Hessen",
    "wof:name":"Humax Und Mehr",
    "wof:placetype":"venue"
},
  "geometry": {"coordinates":[8.636822,50.624996],"type":"Point"}
}