{
  "type": "Feature",
  "properties": {
    "iso:country":"DE",
    "sg:address":"Bellinger Tor 5",
    "sg:city":"Steinau",
    "sg:phone":"+49 6663/8205",
    "sg:postcode":"36396",
    "sg:province":"Hessen",
    "wof:name":"Blumenland Inh. Petra Wolf",
    "wof:placetype":"venue"
},
  "geometry": {"coordinates":[9.464869,50.313869],"type":"Point"}
}