{
  "type": "Feature",
  "properties": {
    "iso:country":"DE",
    "sg:address":"Lassallestr. 3",
    "sg:city":"M\u00fcnchen",
    "sg:postcode":"80995",
    "sg:province":"Bayern",
    "wof:name":"Genio Rent Fahrzeughandels- Und",
    "wof:placetype":"venue"
},
  "geometry": {"coordinates":[11.5335798264,48.1876525879],"type":"Point"}
}