{
  "type": "Feature",
  "properties": {
    "iso:country":"DE",
    "sg:address":"Bozener Str. 4",
    "sg:city":"Mindelheim",
    "sg:phone":"+49 8261/1374",
    "sg:postcode":"87719",
    "sg:province":"Bayern",
    "wof:name":"M. Schmidt",
    "wof:placetype":"venue"
},
  "geometry": {"coordinates":[10.500082016,48.0525169373],"type":"Point"}
}