{
  "type": "Feature",
  "properties": {
    "iso:country":"DE",
    "sg:address":"Max-Reger-Str. 45",
    "sg:city":"Marl",
    "sg:phone":"+49 2365/45111",
    "sg:postcode":"45772",
    "sg:province":"Nordrhein-Westfalen",
    "wof:name":"Reinhold Leese",
    "wof:placetype":"venue"
},
  "geometry": {"coordinates":[7.1442341805,51.6568336487],"type":"Point"}
}