{
  "type": "Feature",
  "properties": {
    "iso:country":"DE",
    "sg:address":"K\u00f6rkwitzer Weg 54a",
    "sg:city":"Ribnitz-Damgarten",
    "sg:phone":"+49 3821/813503",
    "sg:postcode":"18311",
    "sg:province":"Mecklenburg-Vorpommern",
    "wof:name":"H. Michalkowski",
    "wof:placetype":"venue"
},
  "geometry": {"coordinates":[12.40473,54.248119],"type":"Point"}
}