{
  "type": "Feature",
  "properties": {
    "iso:country":"DE",
    "sg:address":"Baldungstr. 9",
    "sg:city":"Schw\u00e4bisch Gm\u00fcnd",
    "sg:phone":"+49 7171/2970",
    "sg:postcode":"73525",
    "sg:province":"Baden-W\u00fcrttemberg",
    "wof:name":"Max Lehmann",
    "wof:placetype":"venue"
},
  "geometry": {"coordinates":[9.8030452728,48.8017578125],"type":"Point"}
}