{
  "type": "Feature",
  "properties": {
    "iso:country":"DE",
    "sg:address":"M\u00f6rikestr. 55",
    "sg:city":"Heiningen",
    "sg:phone":"+49 7161/44604",
    "sg:postcode":"73092",
    "sg:province":"Baden-W\u00fcrttemberg",
    "wof:name":"Haus In Der Breite",
    "wof:placetype":"venue"
},
  "geometry": {"coordinates":[9.642483,48.664169],"type":"Point"}
}