{
  "type": "Feature",
  "properties": {
    "iso:country":"DE",
    "sg:address":"Garmischer Str. 22",
    "sg:city":"Eschenlohe",
    "sg:phone":"+49 8824/345",
    "sg:postcode":"82438",
    "sg:province":"Bayern",
    "wof:name":"Jakob Mangold",
    "wof:placetype":"venue"
},
  "geometry": {"coordinates":[11.185435,47.59626],"type":"Point"}
}