{
  "type": "Feature",
  "properties": {
    "iso:country":"DE",
    "sg:address":"Kniebisweg 6",
    "sg:city":"Waldachtal",
    "sg:phone":"+49 7486/815",
    "sg:postcode":"72178",
    "sg:province":"Baden-W\u00fcrttemberg",
    "wof:name":"Ursula Beck Masseurin",
    "wof:placetype":"venue"
},
  "geometry": {"coordinates":[8.600198,48.488804],"type":"Point"}
}