{
  "type": "Feature",
  "properties": {
    "iso:country":"DE",
    "sg:address":"Hannoversche Str. 24",
    "sg:city":"Bad M\u00fcnder",
    "sg:postcode":"31848",
    "sg:province":"Niedersachsen",
    "wof:name":"Werner Gehring Lizenz\u00fcberlassungs Kg",
    "wof:placetype":"venue"
},
  "geometry": {"coordinates":[9.4736003876,52.1971206665],"type":"Point"}
}