{
  "type": "Feature",
  "properties": {
    "iso:country":"DE",
    "sg:address":"Hussenhofer Str. 35",
    "sg:city":"Schw\u00e4bisch Gm\u00fcnd",
    "sg:phone":"+49 7171/81609",
    "sg:postcode":"73529",
    "sg:province":"Baden-W\u00fcrttemberg",
    "wof:name":"Rita Ocker Hebamme",
    "wof:placetype":"venue"
},
  "geometry": {"coordinates":[9.848247,48.793514],"type":"Point"}
}