{
  "type": "Feature",
  "properties": {
    "iso:country":"DE",
    "sg:address":"Olbrichtstr 34",
    "sg:city":"Weinheim",
    "sg:phone":"+49 6201/875780",
    "sg:postcode":"69469",
    "sg:province":"Baden-W\u00fcrttemberg",
    "wof:name":"Kos Klima - Anlagenbau Projektierung Und Service Gmbh",
    "wof:placetype":"venue"
},
  "geometry": {"coordinates":[8.65837,49.541592],"type":"Point"}
}