{
  "type": "Feature",
  "properties": {
    "iso:country":"DE",
    "sg:address":"Venneweg 52",
    "sg:city":"Delbr\u00fcck",
    "sg:phone":"+49 5250/7915",
    "sg:postcode":"33129",
    "sg:province":"Nordrhein-Westfalen",
    "wof:name":"Josef Zipsewers Elektroinst.",
    "wof:placetype":"venue"
},
  "geometry": {"coordinates":[8.575622,51.797829],"type":"Point"}
}