{
  "type": "Feature",
  "properties": {
    "iso:country":"DE",
    "sg:address":"R\u00f6merstr. 19",
    "sg:city":"Kempten",
    "sg:phone":"+49 831/60262",
    "sg:postcode":"87437",
    "sg:province":"Bayern",
    "wof:name":"H. Kreitner",
    "wof:placetype":"venue"
},
  "geometry": {"coordinates":[10.3360843658,47.7108840942],"type":"Point"}
}