{
  "type": "Feature",
  "properties": {
    "iso:country":"DE",
    "sg:address":"Heiddiek 18",
    "sg:city":"Hamburg",
    "sg:phone":"+49 40/6049442",
    "sg:postcode":"22395",
    "sg:province":"Hamburg",
    "wof:name":"Michael Klawan",
    "wof:placetype":"venue"
},
  "geometry": {"coordinates":[10.1267700195,53.6784210205],"type":"Point"}
}