{
  "type": "Feature",
  "properties": {
    "iso:country":"DE",
    "sg:address":"Steing. 18",
    "sg:city":"Ulm",
    "sg:phone":"+49 4973/1920100",
    "sg:postcode":"89073",
    "sg:province":"Baden-W\u00fcrttemberg",
    "wof:name":"Elektro Unseld Gmbh & Co. Kg",
    "wof:placetype":"venue"
},
  "geometry": {"coordinates":[9.997778,48.39904],"type":"Point"}
}