{
  "type": "Feature",
  "properties": {
    "iso:country":"DE",
    "sg:address":"M\u00f6mpelgardstr. 4",
    "sg:city":"Ludwigsburg",
    "sg:phone":"+49 7141/977110",
    "sg:postcode":"71640",
    "sg:province":"Baden-W\u00fcrttemberg",
    "wof:name":"Psycho-soziale Beratungs- U. Ambulante Behandlungsstelle",
    "wof:placetype":"venue"
},
  "geometry": {"coordinates":[9.198082,48.896645],"type":"Point"}
}