{
  "type": "Feature",
  "properties": {
    "iso:country":"DE",
    "sg:address":"Nibelungenstr. 3",
    "sg:city":"Westhofen",
    "sg:phone":"+49 6244/5549",
    "sg:postcode":"67593",
    "sg:province":"Rheinland-Pfalz",
    "wof:name":"Senlog Schulungs- Und Beratungs Gmbh",
    "wof:placetype":"venue"
},
  "geometry": {"coordinates":[8.2571268082,49.6996421814],"type":"Point"}
}