{
  "type": "Feature",
  "properties": {
    "iso:country":"DE",
    "sg:address":"Nevenweg 1",
    "sg:city":"Geldern",
    "sg:phone":"+49 2831/2154",
    "sg:postcode":"47608",
    "sg:province":"Nordrhein-Westfalen",
    "wof:name":"Stammen Gmbh",
    "wof:placetype":"venue"
},
  "geometry": {"coordinates":[6.3847,51.483952],"type":"Point"}
}