{
  "type": "Feature",
  "properties": {
    "iso:country":"DE",
    "sg:address":"Uferallee 14",
    "sg:city":"Zeltingen-Rachtig",
    "sg:phone":"+49 6532/2402",
    "sg:postcode":"54492",
    "sg:province":"Rheinland-Pfalz",
    "wof:name":"Pension Hans-walter Beucher",
    "wof:placetype":"venue"
},
  "geometry": {"coordinates":[7.0155792236,49.9526634216],"type":"Point"}
}