{
  "type": "Feature",
  "properties": {
    "iso:country":"DE",
    "sg:address":"Marren 6",
    "sg:city":"Lindern",
    "sg:phone":"+49 5957/1875",
    "sg:postcode":"49699",
    "sg:province":"Niedersachsen",
    "wof:name":"Remmers Creativ In Holz Gmbh",
    "wof:placetype":"venue"
},
  "geometry": {"coordinates":[7.762878,52.824959],"type":"Point"}
}