{
  "type": "Feature",
  "properties": {
    "iso:country":"DE",
    "sg:address":"Klosterstr. 12",
    "sg:city":"Diemelsee",
    "sg:phone":"+49 5633/5663",
    "sg:postcode":"34519",
    "sg:province":"Hessen",
    "wof:name":"J\u00f6rg Schultze",
    "wof:placetype":"venue"
},
  "geometry": {"coordinates":[8.824599,51.326305],"type":"Point"}
}