{
  "type": "Feature",
  "properties": {
    "iso:country":"DE",
    "sg:address":"Monschauer Str. 106",
    "sg:city":"D\u00fcren",
    "sg:phone":"+49 2421/61468",
    "sg:postcode":"52355",
    "sg:province":"Nordrhein-Westfalen",
    "wof:name":"Heinz Kraemer",
    "wof:placetype":"venue"
},
  "geometry": {"coordinates":[6.457572,50.774677],"type":"Point"}
}