{
  "type": "Feature",
  "properties": {
    "iso:country":"DE",
    "sg:address":"Landstr. 7",
    "sg:city":"M\u00fcden",
    "sg:phone":"+49 5375/569",
    "sg:postcode":"38539",
    "sg:province":"Niedersachsen",
    "wof:name":"Wilhelm Meyer",
    "wof:placetype":"venue"
},
  "geometry": {"coordinates":[10.379912,52.508186],"type":"Point"}
}