{
  "type": "Feature",
  "properties": {
    "iso:country":"DE",
    "sg:address":"Kirchstr. 3",
    "sg:city":"Satzung",
    "sg:phone":"+49 37364/8263",
    "sg:postcode":"09496",
    "sg:province":"Sachsen",
    "wof:name":"Karlheinz Hesse",
    "wof:placetype":"venue"
},
  "geometry": {"coordinates":[13.192631,50.527115],"type":"Point"}
}