{
  "type": "Feature",
  "properties": {
    "iso:country":"DE",
    "sg:address":"Friedrich-Ebert-Str. 19b",
    "sg:city":"Markkleeberg",
    "sg:postcode":"04416",
    "sg:province":"Sachsen",
    "wof:name":"S\u00e4chsische Shk Beratungs- Und Vertriebs Gmbh",
    "wof:placetype":"venue"
},
  "geometry": {"coordinates":[12.370642662,51.285736084],"type":"Point"}
}