{
  "type": "Feature",
  "properties": {
    "iso:country":"DE",
    "sg:address":"M\u00fchlenbr\u00fccke 6 a",
    "sg:city":"L\u00fcbeck",
    "sg:phone":"+49 451/71858",
    "sg:postcode":"23552",
    "sg:province":"Schleswig-Holstein",
    "wof:name":"Brigit Barnstedt Steuerberaterin",
    "wof:placetype":"venue"
},
  "geometry": {"coordinates":[10.6896772385,53.8604736328],"type":"Point"}
}