{
  "type": "Feature",
  "properties": {
    "iso:country":"DE",
    "sg:address":"K\u00f6nigsweg 23",
    "sg:city":"Kiel",
    "sg:postcode":"24103",
    "sg:province":"Schleswig-Holstein",
    "wof:name":"Geburtshaus Kiel E. V.",
    "wof:placetype":"venue"
},
  "geometry": {"coordinates":[10.127415657,54.3162918091],"type":"Point"}
}