{
  "type": "Feature",
  "properties": {
    "iso:country":"DE",
    "sg:address":"Blinke 6",
    "sg:city":"Leer",
    "sg:phone":"+49 491/928340",
    "sg:postcode":"26789",
    "sg:province":"Niedersachsen",
    "wof:name":"Phoenix Reederei Gmbh",
    "wof:placetype":"venue"
},
  "geometry": {"coordinates":[7.4447197914,53.2259597778],"type":"Point"}
}