{
  "type": "Feature",
  "properties": {
    "iso:country":"DE",
    "sg:address":"Lorcher Str. 6",
    "sg:city":"W\u00e4schenbeuren",
    "sg:phone":"+49 7172/6863",
    "sg:postcode":"73116",
    "sg:province":"Baden-W\u00fcrttemberg",
    "wof:name":"Hildegard Kottmann B\u00e4ckerei",
    "wof:placetype":"venue"
},
  "geometry": {"coordinates":[9.686283,48.759575],"type":"Point"}
}