{
  "type": "Feature",
  "properties": {
    "iso:country":"DE",
    "sg:address":"Alte Mittelstr. 11",
    "sg:city":"Voerde",
    "sg:phone":"+49 281/41316",
    "sg:postcode":"46562",
    "sg:province":"Nordrhein-Westfalen",
    "wof:name":"Andrea Schmitz",
    "wof:placetype":"venue"
},
  "geometry": {"coordinates":[6.650416,51.621658],"type":"Point"}
}