{
  "type": "Feature",
  "properties": {
    "iso:country":"DE",
    "sg:address":"Daimlerstr. 27",
    "sg:city":"Frittlingen",
    "sg:phone":"+49 7426/1826",
    "sg:postcode":"78665",
    "sg:province":"Baden-W\u00fcrttemberg",
    "wof:name":"Gottfried Hauser",
    "wof:placetype":"venue"
},
  "geometry": {"coordinates":[8.6989889145,48.128818512],"type":"Point"}
}