{
  "type": "Feature",
  "properties": {
    "iso:country":"DE",
    "sg:address":"Bahnhofstr. 58",
    "sg:city":"Winsen",
    "sg:postcode":"21423",
    "sg:province":"Niedersachsen",
    "wof:name":"Al Cheikh",
    "wof:placetype":"venue"
},
  "geometry": {"coordinates":[10.206234,53.35714],"type":"Point"}
}