{
  "type": "Feature",
  "properties": {
    "iso:country":"DE",
    "sg:address":"Rotwasserstr. 1",
    "sg:city":"Aschaffenburg",
    "sg:phone":"+49 6021/960409",
    "sg:postcode":"63743",
    "sg:province":"Bayern",
    "wof:name":"A. Sistenich",
    "wof:placetype":"venue"
},
  "geometry": {"coordinates":[9.17029953,49.960067749],"type":"Point"}
}