{
  "type": "Feature",
  "properties": {
    "iso:country":"DE",
    "sg:address":"Wiesenweg 2",
    "sg:city":"W\u00fcrzburg",
    "sg:phone":"+49 931/64537",
    "sg:postcode":"97084",
    "sg:province":"Bayern",
    "wof:name":"Gastst\u00e4tte Fenu Gmbh",
    "wof:placetype":"venue"
},
  "geometry": {"coordinates":[9.9454479218,49.7672462463],"type":"Point"}
}