{
  "type": "Feature",
  "properties": {
    "iso:country":"DE",
    "sg:address":"Menzeler Str. 13",
    "sg:city":"R\u00fcthen",
    "sg:phone":"+49 2952/2772",
    "sg:postcode":"59602",
    "sg:province":"Nordrhein-Westfalen",
    "wof:name":"Johannes Prinz",
    "wof:placetype":"venue"
},
  "geometry": {"coordinates":[8.408717,51.523399],"type":"Point"}
}