{
  "type": "Feature",
  "properties": {
    "iso:country":"DE",
    "sg:address":"Z\u00fcndh\u00f6lzlberg 3",
    "sg:city":"Burghausen",
    "sg:phone":"+49 8677/3467",
    "sg:postcode":"84489",
    "sg:province":"Bayern",
    "wof:name":"Heinrich Kiefer Finanzdienst- Leistungen Gmbh",
    "wof:placetype":"venue"
},
  "geometry": {"coordinates":[12.8206348419,48.159122467],"type":"Point"}
}