{
  "type": "Feature",
  "properties": {
    "iso:country":"DE",
    "sg:address":"Beethovenweg 7",
    "sg:city":"Darmstadt",
    "sg:phone":"+49 6151/75970",
    "sg:postcode":"64287",
    "sg:province":"Hessen",
    "wof:name":"Alexandra Bormann-arndt Graphikerin",
    "wof:placetype":"venue"
},
  "geometry": {"coordinates":[8.6758232117,49.8829536438],"type":"Point"}
}