{
  "type": "Feature",
  "properties": {
    "iso:country":"DE",
    "sg:address":"Rothenbachstr. 41-47",
    "sg:city":"Berlin",
    "sg:postcode":"13089",
    "sg:province":"Berlin",
    "wof:name":"Rs-be Baugesellschaft Mbh",
    "wof:placetype":"venue"
},
  "geometry": {"coordinates":[13.433942,52.570637],"type":"Point"}
}