{
  "type": "Feature",
  "properties": {
    "iso:country":"DE",
    "sg:address":"Pfarrer-Schreyer-Str 6",
    "sg:city":"Wernberg-K\u00f6blitz",
    "sg:phone":"+49 9604/92100",
    "sg:postcode":"92533",
    "sg:province":"Bayern",
    "wof:name":"Wich Vertriebs Gmbh",
    "wof:placetype":"venue"
},
  "geometry": {"coordinates":[12.1457891464,49.5424346924],"type":"Point"}
}