{
  "type": "Feature",
  "properties": {
    "iso:country":"DE",
    "sg:address":"Bindergasse 2",
    "sg:city":"Bruckberg",
    "sg:phone":"+49 8765/608",
    "sg:postcode":"84079",
    "sg:province":"Bayern",
    "wof:name":"J. Nebauer",
    "wof:placetype":"venue"
},
  "geometry": {"coordinates":[12.0271606445,48.5336303711],"type":"Point"}
}