{
  "type": "Feature",
  "properties": {
    "iso:country":"DE",
    "sg:address":"Veltmannsweg 9",
    "sg:city":"Neuenkirchen",
    "sg:phone":"+49 5973/3430",
    "sg:postcode":"48485",
    "sg:province":"Nordrhein-Westfalen",
    "wof:name":"Heinz-dieter Zabel Dipl.-ing. Hochbau",
    "wof:placetype":"venue"
},
  "geometry": {"coordinates":[7.372679,52.247318],"type":"Point"}
}