{
  "type": "Feature",
  "properties": {
    "iso:country":"DE",
    "sg:city":"Hamburg",
    "sg:postcode":"22043",
    "sg:province":"Hamburg",
    "wof:name":"At Informationsvermittlung",
    "wof:placetype":"venue"
},
  "geometry": {"coordinates":[10.075455,53.566589],"type":"Point"}
}