{
  "type": "Feature",
  "properties": {
    "iso:country":"DE",
    "sg:address":"Potsdamer Str. 4",
    "sg:city":"Falkensee",
    "sg:phone":"+49 3322/239927",
    "sg:postcode":"14612",
    "sg:province":"Brandenburg",
    "wof:name":"Ala",
    "wof:placetype":"venue"
},
  "geometry": {"coordinates":[13.090585,52.558678],"type":"Point"}
}