{
  "type": "Feature",
  "properties": {
    "iso:country":"DE",
    "sg:address":"Alte Weinsteige 71",
    "sg:city":"Stuttgart",
    "sg:phone":"+49 711/6408848",
    "sg:postcode":"70597",
    "sg:province":"Baden-W\u00fcrttemberg",
    "wof:name":"Restaurant Wielandsh\u00f6he",
    "wof:placetype":"venue"
},
  "geometry": {"coordinates":[9.170797348,48.757144928],"type":"Point"}
}