{
  "type": "Feature",
  "properties": {
    "iso:country":"DE",
    "sg:address":"Dorfstr. 12",
    "sg:city":"Pfaffendorf",
    "sg:postcode":"15848",
    "sg:province":"Brandenburg",
    "wof:name":"Evangelisches Pfarramt",
    "wof:placetype":"venue"
},
  "geometry": {"coordinates":[14.1746101379,52.2288208008],"type":"Point"}
}