{
  "type": "Feature",
  "properties": {
    "iso:country":"DE",
    "sg:address":"F\u00fcnffensterstr. 9 a",
    "sg:city":"Kassel",
    "sg:phone":"+49 561/21018",
    "sg:postcode":"34117",
    "sg:province":"Hessen",
    "wof:name":"Heinrich Koch Eisenwaren- Fachgesch\u00e4ft Und Kasseler",
    "wof:placetype":"venue"
},
  "geometry": {"coordinates":[9.491568,51.312309],"type":"Point"}
}