{
  "type": "Feature",
  "properties": {
    "iso:country":"DE",
    "sg:address":"Marktstr. 27",
    "sg:city":"Steinheim",
    "sg:phone":"+49 5233/94110",
    "sg:postcode":"32839",
    "sg:province":"Nordrhein-Westfalen",
    "wof:name":"Reiseb\u00fcro Niggemann Verwaltungs Gmbh",
    "wof:placetype":"venue"
},
  "geometry": {"coordinates":[9.093069,51.866543],"type":"Point"}
}