{
  "type": "Feature",
  "properties": {
    "iso:country":"DE",
    "sg:address":"Friedrichstr. 18",
    "sg:city":"Wendlingen",
    "sg:phone":"+49 7024/2776",
    "sg:postcode":"73240",
    "sg:province":"Baden-W\u00fcrttemberg",
    "wof:name":"Anny Frey Immobilienmaklerin",
    "wof:placetype":"venue"
},
  "geometry": {"coordinates":[9.3851137161,48.6727409363],"type":"Point"}
}