{
  "type": "Feature",
  "properties": {
    "iso:country":"DE",
    "sg:address":"Kirchdorf 25",
    "sg:city":"Neuendorf",
    "sg:phone":"+49 4121/3739",
    "sg:postcode":"25335",
    "sg:province":"Schleswig-Holstein",
    "wof:name":"B\u00c4kus B\u00e4ckerei Konditorei Cafe Uwe Sass",
    "wof:placetype":"venue"
},
  "geometry": {"coordinates":[9.651304245,53.7543334961],"type":"Point"}
}