{
  "type": "Feature",
  "properties": {
    "iso:country":"DE",
    "sg:address":"Elisabethstr. 51",
    "sg:city":"M\u00fcnchen",
    "sg:phone":"+49 89/1292379",
    "sg:postcode":"80796",
    "sg:province":"Bayern",
    "wof:name":"Augenoptik Einwang Inh. Manfred Garrecht",
    "wof:placetype":"venue"
},
  "geometry": {"coordinates":[11.5641298294,48.1595573425],"type":"Point"}
}