{
  "type": "Feature",
  "properties": {
    "iso:country":"DE",
    "sg:address":"Wollseifener Str. 16",
    "sg:city":"Schleiden",
    "sg:phone":"+49 2485/1404",
    "sg:postcode":"53937",
    "sg:province":"Nordrhein-Westfalen",
    "wof:name":"W. Steffen",
    "wof:placetype":"venue"
},
  "geometry": {"coordinates":[6.4104800224,50.5466804504],"type":"Point"}
}