{
  "type": "Feature",
  "properties": {
    "iso:country":"DE",
    "sg:address":"Sperberstr. 12",
    "sg:city":"Duisburg",
    "sg:phone":"+49 203/779846",
    "sg:postcode":"47055",
    "sg:province":"Nordrhein-Westfalen",
    "wof:name":"Theo Jansen",
    "wof:placetype":"venue"
},
  "geometry": {"coordinates":[6.765209,51.400181],"type":"Point"}
}