{
  "type": "Feature",
  "properties": {
    "iso:country":"DE",
    "sg:address":"Gro\u00dfer Bauhof 14",
    "sg:city":"L\u00fcbeck",
    "sg:phone":"+49 451/1224342",
    "sg:postcode":"23552",
    "sg:province":"Schleswig-Holstein",
    "wof:name":"V\u00f6lkerkunde-sammlung Der Hansestadt L\u00fcbeck",
    "wof:placetype":"venue"
},
  "geometry": {"coordinates":[10.68435,53.861301],"type":"Point"}
}