{
  "type": "Feature",
  "properties": {
    "iso:country":"DE",
    "sg:address":"Chemnitzer Str. 14",
    "sg:city":"Neustadt",
    "sg:phone":"+49 6321/14844",
    "sg:postcode":"67433",
    "sg:province":"Rheinland-Pfalz",
    "wof:name":"R. Kaub",
    "wof:placetype":"venue"
},
  "geometry": {"coordinates":[8.157984,49.34306],"type":"Point"}
}