{
  "type": "Feature",
  "properties": {
    "iso:country":"DE",
    "sg:address":"Wasserstr. 3",
    "sg:city":"Donaueschingen",
    "sg:postcode":"78166",
    "sg:province":"Baden-W\u00fcrttemberg",
    "wof:name":"Lederwaren Fritz Obergfell Inh. Edelgard Lehmer E. K.",
    "wof:placetype":"venue"
},
  "geometry": {"coordinates":[8.496113,47.95134],"type":"Point"}
}