{
  "type": "Feature",
  "properties": {
    "iso:country":"DE",
    "sg:address":"Senefelderstr. 13",
    "sg:city":"Paderborn",
    "sg:phone":"+49 5251/500550",
    "sg:postcode":"33100",
    "sg:province":"Nordrhein-Westfalen",
    "wof:name":"J. L\u00fctkemeier Und S. Karch Steuerberater",
    "wof:placetype":"venue"
},
  "geometry": {"coordinates":[8.788602829,51.7345504761],"type":"Point"}
}