{
  "type": "Feature",
  "properties": {
    "iso:country":"DE",
    "sg:address":"Augustastr. 46",
    "sg:city":"Gelsenkirchen",
    "sg:phone":"+49 209/204381",
    "sg:postcode":"45888",
    "sg:province":"Nordrhein-Westfalen",
    "wof:name":"Bauunternehmung Friedrich Bielemeier Gmbh",
    "wof:placetype":"venue"
},
  "geometry": {"coordinates":[7.10553,51.508331],"type":"Point"}
}