{
  "type": "Feature",
  "properties": {
    "iso:country":"DE",
    "sg:address":"Pfinztalstr. 56 a",
    "sg:city":"Karlsruhe",
    "sg:postcode":"76227",
    "sg:province":"Baden-W\u00fcrttemberg",
    "wof:name":"Revanche Fashion And More Irmgard Kleiber E. K.",
    "wof:placetype":"venue"
},
  "geometry": {"coordinates":[8.471542,48.999317],"type":"Point"}
}