{
  "type": "Feature",
  "properties": {
    "iso:country":"DE",
    "sg:address":"Nottebohmstr. 4",
    "sg:city":"L\u00fcdenscheid",
    "sg:phone":"+49 2351/936850",
    "sg:postcode":"58511",
    "sg:province":"Nordrhein-Westfalen",
    "wof:name":"Rudolf Reinecke Mp-metallveredelung",
    "wof:placetype":"venue"
},
  "geometry": {"coordinates":[7.655166,51.21571],"type":"Point"}
}