{
  "type": "Feature",
  "properties": {
    "iso:country":"DE",
    "sg:address":"Am Zollhaus 2",
    "sg:city":"Philippsthal",
    "sg:phone":"+49 6620/918800",
    "sg:postcode":"36269",
    "sg:province":"Hessen",
    "wof:name":"Nani Kehm-bikoni Ergotherapiepraxis",
    "wof:placetype":"venue"
},
  "geometry": {"coordinates":[9.993379,50.839497],"type":"Point"}
}