{
  "type": "Feature",
  "properties": {
    "iso:country":"DE",
    "sg:address":"Ulmenstr. 18",
    "sg:city":"Sindelfingen",
    "sg:phone":"+49 7031/73910",
    "sg:postcode":"71069",
    "sg:province":"Baden-W\u00fcrttemberg",
    "wof:name":"Hero F\u00f6rdertechnik Verw. Gmbh",
    "wof:placetype":"venue"
},
  "geometry": {"coordinates":[8.970124,48.728027],"type":"Point"}
}