{
  "type": "Feature",
  "properties": {
    "iso:country":"DE",
    "sg:address":"Isarstr. 31",
    "sg:city":"Senden",
    "sg:phone":"+49 7307/23164",
    "sg:postcode":"89250",
    "sg:province":"Bayern",
    "wof:name":"Scheffold-electronic",
    "wof:placetype":"venue"
},
  "geometry": {"coordinates":[10.0537424088,48.3287277222],"type":"Point"}
}