{
  "type": "Feature",
  "properties": {
    "iso:country":"DE",
    "sg:address":"Gleiwitzer Str. 7",
    "sg:city":"\u00d6hringen",
    "sg:postcode":"74613",
    "sg:province":"Baden-W\u00fcrttemberg",
    "wof:name":"B + S Blechtechnik Gmbh",
    "wof:placetype":"venue"
},
  "geometry": {"coordinates":[9.493075,49.197113],"type":"Point"}
}