{
  "type": "Feature",
  "properties": {
    "iso:country":"DE",
    "sg:address":"Nonnengasse 14",
    "sg:city":"T\u00fcbingen",
    "sg:phone":"+49 7071/27480",
    "sg:postcode":"72070",
    "sg:province":"Baden-W\u00fcrttemberg",
    "wof:name":"Anton Brenner",
    "wof:placetype":"venue"
},
  "geometry": {"coordinates":[9.05616,48.522434],"type":"Point"}
}