{
  "type": "Feature",
  "properties": {
    "iso:country":"DE",
    "sg:address":"Schillerstr. 17",
    "sg:city":"Veitsbronn",
    "sg:phone":"+49 911/756474",
    "sg:postcode":"90587",
    "sg:province":"Bayern",
    "wof:name":"Hasenheim",
    "wof:placetype":"venue"
},
  "geometry": {"coordinates":[10.893034935,49.5144691467],"type":"Point"}
}