{
  "type": "Feature",
  "properties": {
    "iso:country":"DE",
    "sg:address":"Am Zellwald",
    "sg:city":"Siebenlehn",
    "sg:phone":"+49 4937/3248800",
    "sg:postcode":"09634",
    "sg:province":"Sachsen",
    "wof:name":"Skg K\u00dchlerfabrik Gmbh",
    "wof:placetype":"venue"
},
  "geometry": {"coordinates":[13.28631,51.01424],"type":"Point"}
}