{
  "type": "Feature",
  "properties": {
    "iso:country":"DE",
    "sg:address":"Hauptstr. 113-115",
    "sg:city":"Berlin",
    "sg:phone":"+49 30/7846565",
    "sg:postcode":"10827",
    "sg:province":"Berlin",
    "wof:name":"Dominicus Apotheke Inh. J\u00f6rg Wilkens",
    "wof:placetype":"venue"
},
  "geometry": {"coordinates":[13.348887,52.481895],"type":"Point"}
}