{
  "type": "Feature",
  "properties": {
    "iso:country":"DE",
    "sg:address":"Bahnhofstr. 18",
    "sg:city":"Aalen",
    "sg:phone":"+49 7361/95640",
    "sg:postcode":"73430",
    "sg:province":"Baden-W\u00fcrttemberg",
    "wof:name":"Voba-reiseb\u00fcro Rominger Gmbh",
    "wof:placetype":"venue"
},
  "geometry": {"coordinates":[10.0944957733,48.8397293091],"type":"Point"}
}