{
  "type": "Feature",
  "properties": {
    "iso:country":"DE",
    "sg:address":"Alt-Enginger-Weg 60",
    "sg:city":"Paderborn",
    "sg:phone":"+49 5254/5135",
    "sg:postcode":"33106",
    "sg:province":"Nordrhein-Westfalen",
    "wof:name":"Exakt Kiesaufbereitung Gmbh",
    "wof:placetype":"venue"
},
  "geometry": {"coordinates":[8.6837759018,51.7486419678],"type":"Point"}
}