{
  "type": "Feature",
  "properties": {
    "iso:country":"DE",
    "sg:address":"Elbestr 23",
    "sg:city":"Bocholt",
    "sg:phone":"+49 2871/185081",
    "sg:postcode":"46395",
    "sg:province":"Nordrhein-Westfalen",
    "wof:name":"Unispace Gmbh",
    "wof:placetype":"venue"
},
  "geometry": {"coordinates":[6.618657,51.823654],"type":"Point"}
}