{
  "type": "Feature",
  "properties": {
    "iso:country":"DE",
    "sg:address":"Brunnenstr. 28",
    "sg:city":"M\u00fcnsing",
    "sg:phone":"+49 8177/8549",
    "sg:postcode":"82541",
    "sg:province":"Bayern",
    "wof:name":"Johann Klostermeier",
    "wof:placetype":"venue"
},
  "geometry": {"coordinates":[11.356217,47.881882],"type":"Point"}
}