{
  "type": "Feature",
  "properties": {
    "iso:country":"DE",
    "sg:address":"Ravensburger Str. 16",
    "sg:city":"Schlier",
    "sg:phone":"+49 751/361950",
    "sg:postcode":"88281",
    "sg:province":"Baden-W\u00fcrttemberg",
    "wof:name":"Helmut Weber Beteiligungs- Gmbh",
    "wof:placetype":"venue"
},
  "geometry": {"coordinates":[9.655499,47.775143],"type":"Point"}
}