{
  "type": "Feature",
  "properties": {
    "iso:country":"DE",
    "sg:address":"Dechant-Wolter-Str. 8",
    "sg:city":"Waldbr\u00f6l",
    "sg:phone":"+49 2291/7330",
    "sg:postcode":"51545",
    "sg:province":"Nordrhein-Westfalen",
    "wof:name":"Klaumas Co Thomas Knura",
    "wof:placetype":"venue"
},
  "geometry": {"coordinates":[7.6132221222,50.8771629333],"type":"Point"}
}