{
  "type": "Feature",
  "properties": {
    "iso:country":"DE",
    "sg:address":"Kaiserdamm 12",
    "sg:city":"Berlin",
    "sg:phone":"+49 30/3269310",
    "sg:postcode":"14057",
    "sg:province":"Berlin",
    "wof:name":"B\u00e4rbel Werneburg Steuerberaterin",
    "wof:placetype":"venue"
},
  "geometry": {"coordinates":[13.2895584106,52.5107002258],"type":"Point"}
}