{
  "type": "Feature",
  "properties": {
    "iso:country":"DE",
    "sg:address":"Steigleweg 12",
    "sg:city":"Winterlingen",
    "sg:phone":"+49 7434/618",
    "sg:postcode":"72474",
    "sg:province":"Baden-W\u00fcrttemberg",
    "wof:name":"Ralf Unbescheiden Masseur",
    "wof:placetype":"venue"
},
  "geometry": {"coordinates":[9.117427,48.187546],"type":"Point"}
}