{
  "type": "Feature",
  "properties": {
    "iso:country":"DE",
    "sg:address":"Fuhlsb\u00fcttler Str. 139",
    "sg:city":"Hamburg",
    "sg:phone":"+49 40/614874",
    "sg:postcode":"22305",
    "sg:province":"Hamburg",
    "wof:name":"Hajo Automatenauf- Stellungs- Und Handels Gmbh",
    "wof:placetype":"venue"
},
  "geometry": {"coordinates":[10.0444984436,53.5909538269],"type":"Point"}
}