{
  "type": "Feature",
  "properties": {
    "iso:country":"DE",
    "sg:address":"Bahnhofstr. 11a",
    "sg:city":"Celle",
    "sg:phone":"+49 5141/6616",
    "sg:postcode":"29221",
    "sg:province":"Niedersachsen",
    "wof:name":"Anjas Lollypop",
    "wof:placetype":"venue"
},
  "geometry": {"coordinates":[10.0713262558,52.6214637756],"type":"Point"}
}