{
  "type": "Feature",
  "properties": {
    "iso:country":"DE",
    "sg:address":"Rothwind 6",
    "sg:city":"Mainleus",
    "sg:phone":"+49 9229/569",
    "sg:postcode":"95336",
    "sg:province":"Bayern",
    "wof:name":"Rudolf Vonbrunn",
    "wof:placetype":"venue"
},
  "geometry": {"coordinates":[11.3392505646,50.1173439026],"type":"Point"}
}