{
  "type": "Feature",
  "properties": {
    "iso:country":"DE",
    "sg:address":"Wechtern",
    "sg:city":"Krummendeich",
    "sg:phone":"+49 4753/333",
    "sg:postcode":"21732",
    "sg:province":"Niedersachsen",
    "wof:name":"Gastst\u00e4tte G. Und I. Gro\u00df",
    "wof:placetype":"venue"
},
  "geometry": {"coordinates":[9.2112426758,53.82264328],"type":"Point"}
}