{
  "type": "Feature",
  "properties": {
    "iso:country":"DE",
    "sg:address":"Erdinger Str. 11",
    "sg:city":"Dorfen",
    "sg:phone":"+49 8081/734",
    "sg:postcode":"84405",
    "sg:province":"Bayern",
    "wof:name":"Hans Kern",
    "wof:placetype":"venue"
},
  "geometry": {"coordinates":[12.150558,48.275471],"type":"Point"}
}