{
  "type": "Feature",
  "properties": {
    "iso:country":"DE",
    "sg:address":"Oberfrohnaer Str. 62",
    "sg:city":"Chemnitz",
    "sg:phone":"+49 371/8576947",
    "sg:postcode":"09117",
    "sg:province":"Sachsen",
    "wof:name":"Mgv Werbeagentur Felber Hartling & Co. Ohg",
    "wof:placetype":"venue"
},
  "geometry": {"coordinates":[12.8328380585,50.8256225586],"type":"Point"}
}