{
  "type": "Feature",
  "properties": {
    "iso:country":"DE",
    "sg:address":"Gurlittplatz 2",
    "sg:city":"Kiel",
    "sg:phone":"+49 431/338304",
    "sg:postcode":"24106",
    "sg:province":"Schleswig-Holstein",
    "wof:name":"Brigitte Rensch",
    "wof:placetype":"venue"
},
  "geometry": {"coordinates":[10.1159067154,54.3557815552],"type":"Point"}
}