{
  "type": "Feature",
  "properties": {
    "iso:country":"DE",
    "sg:address":"Ilbeckweg 1",
    "sg:city":"D\u00fcsseldorf",
    "sg:phone":"+49 2102/842234",
    "sg:postcode":"40629",
    "sg:province":"Nordrhein-Westfalen",
    "wof:name":"Gut Aue-markeneivertrieb Gmbh",
    "wof:placetype":"venue"
},
  "geometry": {"coordinates":[6.9142699242,51.2755584717],"type":"Point"}
}