{
  "type": "Feature",
  "properties": {
    "iso:country":"DE",
    "sg:address":"Franz-Vetter-Str. 12",
    "sg:city":"Kassel",
    "sg:phone":"+49 561/25782",
    "sg:postcode":"34121",
    "sg:province":"Hessen",
    "wof:name":"Hermann Krapp Steuerbevollm\u00e4chtigter",
    "wof:placetype":"venue"
},
  "geometry": {"coordinates":[9.4537343979,51.3070335388],"type":"Point"}
}