{
  "type": "Feature",
  "properties": {
    "iso:country":"DE",
    "sg:address":"Heidkopf 4",
    "sg:city":"Dortmund",
    "sg:phone":"+49 231",
    "sg:postcode":"44229",
    "sg:province":"Nordrhein-Westfalen",
    "wof:name":"Automobile Rogowski",
    "wof:placetype":"venue"
},
  "geometry": {"coordinates":[7.4715228081,51.4650001526],"type":"Point"}
}