{
  "type": "Feature",
  "properties": {
    "iso:country":"DE",
    "sg:address":"Dr.-Eckener-Str. 14",
    "sg:city":"Diepholz",
    "sg:phone":"+49 5441/8719",
    "sg:postcode":"49356",
    "sg:province":"Niedersachsen",
    "wof:name":"Trend-bau Gmbh",
    "wof:placetype":"venue"
},
  "geometry": {"coordinates":[8.362122,52.596813],"type":"Point"}
}