{
  "type": "Feature",
  "properties": {
    "iso:country":"DE",
    "sg:address":"Gewerbepark Mei\u00dfen 12",
    "sg:city":"Minden",
    "sg:phone":"+49 571/31088",
    "sg:postcode":"32423",
    "sg:province":"Nordrhein-Westfalen",
    "wof:name":"Betriebs-lager- Und Inneneinrichtung",
    "wof:placetype":"venue"
},
  "geometry": {"coordinates":[8.9562110901,52.2716674805],"type":"Point"}
}