{
  "type": "Feature",
  "properties": {
    "iso:country":"DE",
    "sg:address":"Am Deich 12",
    "sg:city":"Marschacht",
    "sg:phone":"+49 4176/9111019",
    "sg:postcode":"21436",
    "sg:province":"Niedersachsen",
    "wof:name":"Plambeck",
    "wof:placetype":"venue"
},
  "geometry": {"coordinates":[10.377145,53.415668],"type":"Point"}
}