{
  "type": "Feature",
  "properties": {
    "iso:country":"DE",
    "sg:address":"S\u00fcdstr. 28",
    "sg:city":"Lauenau",
    "sg:phone":"+49 5043/1659",
    "sg:postcode":"31867",
    "sg:province":"Niedersachsen",
    "wof:name":"Wilhelm Wehrhahn Architekt",
    "wof:placetype":"venue"
},
  "geometry": {"coordinates":[9.372961,52.268234],"type":"Point"}
}