{
  "type": "Feature",
  "properties": {
    "iso:country":"DE",
    "sg:address":"Lange Str. 42",
    "sg:city":"Crailsheim",
    "sg:phone":"+49 7951/43400",
    "sg:postcode":"74564",
    "sg:province":"Baden-W\u00fcrttemberg",
    "wof:name":"Ibs Immobilienb\u00f6rse F\u00fcr Haus- Und Grundbesitz Gmbh",
    "wof:placetype":"venue"
},
  "geometry": {"coordinates":[10.0713024139,49.1352844238],"type":"Point"}
}