{
  "type": "Feature",
  "properties": {
    "iso:country":"DE",
    "sg:address":"Beethovenstr. 14",
    "sg:city":"Weilerswist",
    "sg:phone":"+49 2254/7542",
    "sg:postcode":"53919",
    "sg:province":"Nordrhein-Westfalen",
    "wof:name":"Wok\u00f6ck Gmbh",
    "wof:placetype":"venue"
},
  "geometry": {"coordinates":[6.8430299759,50.749622345],"type":"Point"}
}