{
  "type": "Feature",
  "properties": {
    "iso:country":"DE",
    "sg:address":"Ludwigstr. 12 b",
    "sg:city":"Traunstein",
    "sg:phone":"+49 861/989430",
    "sg:postcode":"83278",
    "sg:province":"Bayern",
    "wof:name":"Bhw Bausparkasse Ag",
    "wof:placetype":"venue"
},
  "geometry": {"coordinates":[12.644973,47.870255],"type":"Point"}
}