{
  "type": "Feature",
  "properties": {
    "iso:country":"DE",
    "sg:address":"Handwerkerwall 74",
    "sg:city":"Gifhorn",
    "sg:phone":"+49 5371/98830",
    "sg:postcode":"38518",
    "sg:province":"Niedersachsen",
    "wof:name":"D. Weezel Errenz Immobilienmakler",
    "wof:placetype":"venue"
},
  "geometry": {"coordinates":[10.5675497055,52.4868888855],"type":"Point"}
}