{
  "type": "Feature",
  "properties": {
    "iso:country":"DE",
    "sg:address":"B\u00e4ckerstr. 35",
    "sg:city":"Hameln",
    "sg:phone":"+49 5151/27552",
    "sg:postcode":"31785",
    "sg:province":"Niedersachsen",
    "wof:name":"Brillen-galerie Inh. Klaus G\u00fcnter Sagebiel",
    "wof:placetype":"venue"
},
  "geometry": {"coordinates":[9.3558721542,52.1014213562],"type":"Point"}
}