{
  "type": "Feature",
  "properties": {
    "iso:country":"DE",
    "sg:address":"M\u00fchlenstr. 4",
    "sg:city":"Greifswald",
    "sg:postcode":"17489",
    "sg:province":"Mecklenburg-Vorpommern",
    "wof:name":"Gebr. Fobke Inh. Gudrun Freiwald",
    "wof:placetype":"venue"
},
  "geometry": {"coordinates":[13.384062767,54.0956192017],"type":"Point"}
}