{
  "type": "Feature",
  "properties": {
    "iso:country":"DE",
    "sg:address":"Resthauser Str. 22",
    "sg:city":"Cloppenburg",
    "sg:phone":"+49 4471/82470",
    "sg:postcode":"49661",
    "sg:province":"Niedersachsen",
    "wof:name":"Albert J\u00fcnemann",
    "wof:placetype":"venue"
},
  "geometry": {"coordinates":[8.033692,52.849117],"type":"Point"}
}