{
  "type": "Feature",
  "properties": {
    "iso:country":"DE",
    "sg:address":"Waldstr. 5",
    "sg:city":"Brechen",
    "sg:phone":"+49 6438/921818",
    "sg:postcode":"65611",
    "sg:province":"Hessen",
    "wof:name":"Ms-happy Tours",
    "wof:placetype":"venue"
},
  "geometry": {"coordinates":[8.1679887772,50.3440933228],"type":"Point"}
}