{
  "type": "Feature",
  "properties": {
    "iso:country":"DE",
    "sg:address":"Fischergasse 7",
    "sg:city":"Kulmbach",
    "sg:phone":"+49 9221/2505",
    "sg:postcode":"95326",
    "sg:province":"Bayern",
    "wof:name":"Wilhelm Hugel",
    "wof:placetype":"venue"
},
  "geometry": {"coordinates":[11.4590921402,50.1093978882],"type":"Point"}
}