{
  "type": "Feature",
  "properties": {
    "iso:country":"DE",
    "sg:address":"Kersbacher Str. 1",
    "sg:city":"Neunkirchen",
    "sg:phone":"+49 9153/97110",
    "sg:postcode":"91233",
    "sg:province":"Bayern",
    "wof:name":"Abs Architekturb\u00fcro Speikern Ganser Marschall Und",
    "wof:placetype":"venue"
},
  "geometry": {"coordinates":[11.318508,49.525982],"type":"Point"}
}