{
  "type": "Feature",
  "properties": {
    "iso:country":"DE",
    "sg:address":"Stift 24",
    "sg:city":"Tecklenburg",
    "sg:phone":"+49 5481/2491",
    "sg:postcode":"49545",
    "sg:province":"Nordrhein-Westfalen",
    "wof:name":"Gustav Wellemeyer",
    "wof:placetype":"venue"
},
  "geometry": {"coordinates":[7.8827772141,52.2118911743],"type":"Point"}
}