{
  "type": "Feature",
  "properties": {
    "iso:country":"DE",
    "sg:address":"Michelner Str. 2",
    "sg:city":"Lichtenstein",
    "sg:phone":"+49 37204/3960",
    "sg:postcode":"09350",
    "sg:province":"Sachsen",
    "wof:name":"Steffen Bachmann",
    "wof:placetype":"venue"
},
  "geometry": {"coordinates":[12.6229152679,50.7535018921],"type":"Point"}
}