{
  "type": "Feature",
  "properties": {
    "iso:country":"DE",
    "sg:address":"Am Bl\u00fctenanger 71",
    "sg:city":"M\u00fcnchen",
    "sg:phone":"+49 89/1581210",
    "sg:postcode":"80995",
    "sg:province":"Bayern",
    "wof:name":"Forschungsstelle F\u00fcr Energiewirtschaft",
    "wof:placetype":"venue"
},
  "geometry": {"coordinates":[11.510891,48.200691],"type":"Point"}
}