{
  "type": "Feature",
  "properties": {
    "iso:country":"DE",
    "sg:address":"Am Kl\u00f6terbusch 46",
    "sg:city":"Buxtehude",
    "sg:phone":"+49 4161/84823",
    "sg:postcode":"21614",
    "sg:province":"Niedersachsen",
    "wof:name":"G. Martens Und H. Garbe-emden",
    "wof:placetype":"venue"
},
  "geometry": {"coordinates":[9.6791172028,53.4585838318],"type":"Point"}
}