{
  "type": "Feature",
  "properties": {
    "iso:country":"DE",
    "sg:address":"Eugen-Kaiser-Str. 57",
    "sg:city":"Hanau",
    "sg:postcode":"63450",
    "sg:province":"Hessen",
    "wof:name":"Brass Versicherungsagentur Hanau Gmbh",
    "wof:placetype":"venue"
},
  "geometry": {"coordinates":[8.9207601547,50.1403617859],"type":"Point"}
}