{
  "type": "Feature",
  "properties": {
    "iso:country":"DE",
    "sg:address":"Am Sioniterhof 4",
    "sg:city":"Wesseling",
    "sg:postcode":"50389",
    "sg:province":"Nordrhein-Westfalen",
    "wof:name":"Ganser K\u00fcchen- Klima- Und L\u00fcftungsanlagen-",
    "wof:placetype":"venue"
},
  "geometry": {"coordinates":[6.9877018929,50.822353363],"type":"Point"}
}