{
  "type": "Feature",
  "properties": {
    "iso:country":"DE",
    "sg:address":"Friedrichstr. 22",
    "sg:city":"M\u00fcnchen",
    "sg:phone":"+49 89/332568",
    "sg:postcode":"80801",
    "sg:province":"Bayern",
    "wof:name":"Fmg Fachverlag F\u00fcr Druck Und Medien Gmbh",
    "wof:placetype":"venue"
},
  "geometry": {"coordinates":[11.5803050995,48.1591644287],"type":"Point"}
}