{
  "type": "Feature",
  "properties": {
    "iso:country":"DE",
    "sg:address":"Zentgrafenstr. 3",
    "sg:city":"Frankfurt",
    "sg:phone":"+49 69/479144",
    "sg:postcode":"60389",
    "sg:province":"Hessen",
    "wof:name":"Helmut Schneider",
    "wof:placetype":"venue"
},
  "geometry": {"coordinates":[8.726018,50.144585],"type":"Point"}
}