{
  "type": "Feature",
  "properties": {
    "iso:country":"DE",
    "sg:address":"Leienbergstr. 24",
    "sg:city":"Eitorf",
    "sg:phone":"+49 2243/6968",
    "sg:postcode":"53783",
    "sg:province":"Nordrhein-Westfalen",
    "wof:name":"Elke W\u00f6stendiek",
    "wof:placetype":"venue"
},
  "geometry": {"coordinates":[7.45063,50.768082],"type":"Point"}
}