{
  "type": "Feature",
  "properties": {
    "iso:country":"DE",
    "sg:address":"Alte Bahnhofstr. 16",
    "sg:city":"Bonn",
    "sg:phone":"+49 228/363601",
    "sg:postcode":"53173",
    "sg:province":"Nordrhein-Westfalen",
    "wof:name":"G. Kemp Und Sohn",
    "wof:placetype":"venue"
},
  "geometry": {"coordinates":[7.1561131477,50.6844520569],"type":"Point"}
}