{
  "type": "Feature",
  "properties": {
    "iso:country":"DE",
    "sg:address":"T\u00f6pfermarkt 2",
    "sg:city":"Hofgeismar",
    "sg:phone":"+49 5671/6686",
    "sg:postcode":"34369",
    "sg:province":"Hessen",
    "wof:name":"Waldecks Backstube Gmbh",
    "wof:placetype":"venue"
},
  "geometry": {"coordinates":[9.380906,51.494164],"type":"Point"}
}