{
  "type": "Feature",
  "properties": {
    "iso:country":"DE",
    "sg:address":"Halberst\u00e4dter Str. 83",
    "sg:city":"Magdeburg",
    "sg:phone":"+49 391/6228229",
    "sg:postcode":"39112",
    "sg:province":"Sachsen-Anhalt",
    "wof:name":"Em-be-allgemeine Verwaltungs Gmbh",
    "wof:placetype":"venue"
},
  "geometry": {"coordinates":[11.6057271957,52.1120834351],"type":"Point"}
}