{
  "type": "Feature",
  "properties": {
    "iso:country":"DE",
    "sg:address":"Prosperstr. 158",
    "sg:city":"Bottrop",
    "sg:phone":"+49 2041/64259",
    "sg:postcode":"46238",
    "sg:province":"Nordrhein-Westfalen",
    "wof:name":"Egon Dolzani",
    "wof:placetype":"venue"
},
  "geometry": {"coordinates":[6.94481,51.520222],"type":"Point"}
}