{
  "type": "Feature",
  "properties": {
    "iso:country":"DE",
    "sg:address":"Bismarckstr. 24",
    "sg:city":"Bitterfeld",
    "sg:postcode":"06749",
    "sg:province":"Sachsen-Anhalt",
    "wof:name":"J & J Service Gmbh",
    "wof:placetype":"venue"
},
  "geometry": {"coordinates":[12.32264328,51.6208267212],"type":"Point"}
}