{
  "type": "Feature",
  "properties": {
    "iso:country":"DE",
    "sg:address":"Postfach 400628",
    "sg:city":"K\u00f6ln",
    "sg:phone":"+49 700 6343 6783",
    "sg:postcode":"50836",
    "sg:province":"Nordrhein-Westfalen",
    "wof:name":"Rosa-sitzung",
    "wof:placetype":"venue"
},
  "geometry": {"coordinates":[6.95989,50.940552],"type":"Point"}
}