{
  "type": "Feature",
  "properties": {
    "iso:country":"DE",
    "sg:address":"R\u00fcckertstr. 36",
    "sg:city":"Frankfurt",
    "sg:phone":"+49 69/448566",
    "sg:postcode":"60314",
    "sg:province":"Hessen",
    "wof:name":"H. A. Rodeh\u00fcser",
    "wof:placetype":"venue"
},
  "geometry": {"coordinates":[8.699802,50.111244],"type":"Point"}
}