{
  "type": "Feature",
  "properties": {
    "iso:country":"DE",
    "sg:address":"Ebertsheimer Weg 1",
    "sg:city":"Tiefenthal",
    "sg:phone":"+49 6351/44513",
    "sg:postcode":"67311",
    "sg:province":"Rheinland-Pfalz",
    "wof:name":"Klaus Sch\u00f6neberger",
    "wof:placetype":"venue"
},
  "geometry": {"coordinates":[8.10562,49.542782],"type":"Point"}
}