{
  "type": "Feature",
  "properties": {
    "iso:country":"DE",
    "sg:address":"Lindh\u00f6fter Berg",
    "sg:city":"Noer",
    "sg:phone":"+49 4346/8491",
    "sg:postcode":"24214",
    "sg:province":"Schleswig-Holstein",
    "wof:name":"Pension Egon Und I. Schilling",
    "wof:placetype":"venue"
},
  "geometry": {"coordinates":[9.9634609222,54.4533348083],"type":"Point"}
}