{
  "type": "Feature",
  "properties": {
    "iso:country":"DE",
    "sg:address":"Gewerbestr. 42 Ot Gr\u00e4fenhausen",
    "sg:city":"Birkenfeld",
    "sg:phone":"+49 4970/8292540",
    "sg:postcode":"75217",
    "sg:province":"Baden-W\u00fcrttemberg",
    "wof:name":"Horst Karcher",
    "wof:placetype":"venue"
},
  "geometry": {"coordinates":[8.636127,48.870373],"type":"Point"}
}