{
  "type": "Feature",
  "properties": {
    "iso:country":"DE",
    "sg:address":"Oberdorf 14",
    "sg:city":"Frielendorf",
    "sg:phone":"+49 5684/7432",
    "sg:postcode":"34621",
    "sg:province":"Hessen",
    "wof:name":"Erich Viehmann",
    "wof:placetype":"venue"
},
  "geometry": {"coordinates":[9.320621,50.963245],"type":"Point"}
}