{
  "type": "Feature",
  "properties": {
    "iso:country":"DE",
    "sg:address":"Uhlandstr. 22",
    "sg:city":"Kerpen",
    "sg:phone":"+49 2237/3780",
    "sg:postcode":"50171",
    "sg:province":"Nordrhein-Westfalen",
    "wof:name":"H. Ackermann Drogerie",
    "wof:placetype":"venue"
},
  "geometry": {"coordinates":[6.699954,50.866009],"type":"Point"}
}