{
  "type": "Feature",
  "properties": {
    "iso:country":"DE",
    "sg:address":"In der Neckarhelle 23",
    "sg:city":"Heidelberg",
    "sg:phone":"+49 6221/800610",
    "sg:postcode":"69118",
    "sg:province":"Baden-W\u00fcrttemberg",
    "wof:name":"Karl Wetzel Gmbh",
    "wof:placetype":"venue"
},
  "geometry": {"coordinates":[8.7540187836,49.4175338745],"type":"Point"}
}