{
  "type": "Feature",
  "properties": {
    "iso:country":"DE",
    "sg:address":"Hauptstr. 47",
    "sg:city":"Spahnharrenst\u00e4tte",
    "sg:phone":"+49 5951/2745",
    "sg:postcode":"49751",
    "sg:province":"Niedersachsen",
    "wof:name":"Hubertus Lager",
    "wof:placetype":"venue"
},
  "geometry": {"coordinates":[7.5978331566,52.8679733276],"type":"Point"}
}