{
  "type": "Feature",
  "properties": {
    "iso:country":"DE",
    "sg:address":"Ruhesteinstr. 486",
    "sg:city":"Baiersbronn",
    "sg:phone":"+49 7449/393",
    "sg:postcode":"72270",
    "sg:province":"Baden-W\u00fcrttemberg",
    "wof:name":"Rudi Gaiser",
    "wof:placetype":"venue"
},
  "geometry": {"coordinates":[8.281889,48.537228],"type":"Point"}
}