{
  "type": "Feature",
  "properties": {
    "iso:country":"DE",
    "sg:address":"Robert-Bosch-Str. 5",
    "sg:city":"Kastl",
    "sg:phone":"+49 8671/6018",
    "sg:postcode":"84556",
    "sg:province":"Bayern",
    "wof:name":"Otto Doppelberger",
    "wof:placetype":"venue"
},
  "geometry": {"coordinates":[12.691416,48.194988],"type":"Point"}
}