{
  "type": "Feature",
  "properties": {
    "iso:country":"DE",
    "sg:address":"Basler Str. 34",
    "sg:city":"Bad Krozingen",
    "sg:phone":"+49 7633/3560",
    "sg:postcode":"79189",
    "sg:province":"Baden-W\u00fcrttemberg",
    "wof:name":"G\u00fcnther Stoll",
    "wof:placetype":"venue"
},
  "geometry": {"coordinates":[7.7001547813,47.9163246155],"type":"Point"}
}