{
  "type": "Feature",
  "properties": {
    "iso:country":"DE",
    "sg:address":"Marienring 20",
    "sg:city":"Landau",
    "sg:phone":"+49 6341/899999",
    "sg:postcode":"76829",
    "sg:province":"Rheinland-Pfalz",
    "wof:name":"Lzl Laser-zentrum Gmbh",
    "wof:placetype":"venue"
},
  "geometry": {"coordinates":[8.118332,49.194439],"type":"Point"}
}