{
  "type": "Feature",
  "properties": {
    "iso:country":"DE",
    "sg:address":"Bernkasteler Str. 13",
    "sg:city":"Morbach",
    "sg:phone":"+49 6533/93890",
    "sg:postcode":"54497",
    "sg:province":"Rheinland-Pfalz",
    "wof:name":"Emil Heinrich Steuerberater",
    "wof:placetype":"venue"
},
  "geometry": {"coordinates":[7.1213212013,49.8114738464],"type":"Point"}
}