{
  "type": "Feature",
  "properties": {
    "iso:country":"DE",
    "sg:address":"Esslinger Str. 11",
    "sg:city":"Wolfschlugen",
    "sg:phone":"+49 7022/59799",
    "sg:postcode":"72649",
    "sg:province":"Baden-W\u00fcrttemberg",
    "wof:name":"Jochen Wirth",
    "wof:placetype":"venue"
},
  "geometry": {"coordinates":[9.2867517471,48.6541175842],"type":"Point"}
}