{
  "type": "Feature",
  "properties": {
    "iso:country":"DE",
    "sg:address":"Julius-Pintsch-Ring 21",
    "sg:city":"F\u00fcrstenwalde",
    "sg:phone":"+49 3361/589321",
    "sg:postcode":"15517",
    "sg:province":"Brandenburg",
    "wof:name":"Geocon Ges. F\u00fcr Geotechnik Und Umweltschutz Mbh",
    "wof:placetype":"venue"
},
  "geometry": {"coordinates":[14.0557193756,52.3686180115],"type":"Point"}
}