{
  "type": "Feature",
  "properties": {
    "iso:country":"DE",
    "sg:address":"Z\u00e4hringer Str. 4",
    "sg:city":"St. Peter",
    "sg:phone":"+49 7660/220",
    "sg:postcode":"79271",
    "sg:province":"Baden-W\u00fcrttemberg",
    "wof:name":"H. Kn\u00f6pfle",
    "wof:placetype":"venue"
},
  "geometry": {"coordinates":[8.032372,48.015701],"type":"Point"}
}