{
  "type": "Feature",
  "properties": {
    "iso:country":"DE",
    "sg:address":"Im Alten Dorfe 24",
    "sg:city":"Hamburg",
    "sg:phone":"+49 40/6036699",
    "sg:postcode":"22359",
    "sg:province":"Hamburg",
    "wof:name":"Volksdorfer Markt",
    "wof:placetype":"venue"
},
  "geometry": {"coordinates":[10.1649188995,53.6485290527],"type":"Point"}
}