{
  "type": "Feature",
  "properties": {
    "iso:country":"DE",
    "sg:address":"Schulstr. 24",
    "sg:city":"Berlin",
    "sg:phone":"+49 30/4658022",
    "sg:postcode":"13347",
    "sg:province":"Berlin",
    "wof:name":"Passierscheineck",
    "wof:placetype":"venue"
},
  "geometry": {"coordinates":[13.3643856049,52.5493545532],"type":"Point"}
}