{
  "type": "Feature",
  "properties": {
    "iso:country":"DE",
    "sg:address":"Z\u00e4hringerplatz 15",
    "sg:city":"Konstanz",
    "sg:phone":"+49 7531/62580",
    "sg:postcode":"78464",
    "sg:province":"Baden-W\u00fcrttemberg",
    "wof:name":"Blumenhaus Fehrenbach Gmbh",
    "wof:placetype":"venue"
},
  "geometry": {"coordinates":[9.183543,47.673531],"type":"Point"}
}