{
  "type": "Feature",
  "properties": {
    "iso:country":"DE",
    "sg:address":"Neckarauer Str. 69",
    "sg:city":"Mannheim",
    "sg:phone":"+49 621/852190",
    "sg:postcode":"68199",
    "sg:province":"Baden-W\u00fcrttemberg",
    "wof:name":"Mario Sofia",
    "wof:placetype":"venue"
},
  "geometry": {"coordinates":[8.4925613403,49.4580078125],"type":"Point"}
}