{
  "type": "Feature",
  "properties": {
    "iso:country":"DE",
    "sg:address":"Liliencronstr. 3",
    "sg:city":"Hannover",
    "sg:phone":"+49 511/693929",
    "sg:postcode":"30177",
    "sg:province":"Niedersachsen",
    "wof:name":"Karsten Knott",
    "wof:placetype":"venue"
},
  "geometry": {"coordinates":[9.7737016678,52.4009590149],"type":"Point"}
}