{
  "type": "Feature",
  "properties": {
    "iso:country":"DE",
    "sg:address":"Finsingstr. 1",
    "sg:city":"M\u00fcnchen",
    "sg:phone":"+49 89/6891642",
    "sg:postcode":"81735",
    "sg:province":"Bayern",
    "wof:name":"G\u00fcnther Handel Rechtsanwalt",
    "wof:placetype":"venue"
},
  "geometry": {"coordinates":[11.61906147,48.1148986816],"type":"Point"}
}