{
  "type": "Feature",
  "properties": {
    "iso:country":"DE",
    "sg:address":"Rurtalstra\u00dfe 37",
    "sg:city":"Heinsberg",
    "sg:phone":"+49 2432/939321",
    "sg:postcode":"41849",
    "sg:province":"Nordrhein-Westfalen",
    "wof:name":"Sofa Direkt - Wassenberger Polster Werkst\u00e4tten",
    "wof:placetype":"venue"
},
  "geometry": {"coordinates":[6.172277,51.039207],"type":"Point"}
}