{
  "type": "Feature",
  "properties": {
    "iso:country":"DE",
    "sg:address":"Butendoor 25",
    "sg:city":"Bad Bramstedt",
    "sg:phone":"+49 4192/813344",
    "sg:postcode":"24576",
    "sg:province":"Schleswig-Holstein",
    "wof:name":"Ingenieurbuero Endom B\u00fcro F\u00fcr Boden-/georadar",
    "wof:placetype":"venue"
},
  "geometry": {"coordinates":[9.888126,53.91428],"type":"Point"}
}