{
  "type": "Feature",
  "properties": {
    "iso:country":"DE",
    "sg:address":"Piusallee 182",
    "sg:city":"M\u00fcnster",
    "sg:phone":"+49 251/2301652",
    "sg:postcode":"48147",
    "sg:province":"Nordrhein-Westfalen",
    "wof:name":"Friedr.-wilhelm We\u00dfel",
    "wof:placetype":"venue"
},
  "geometry": {"coordinates":[7.640532,51.97406],"type":"Point"}
}