{
  "type": "Feature",
  "properties": {
    "iso:country":"DE",
    "sg:address":"Meisenweg 14",
    "sg:city":"Krailling",
    "sg:phone":"+49 89/8574782",
    "sg:postcode":"82152",
    "sg:province":"Bayern",
    "wof:name":"Dirk Kabisch Steuerberater",
    "wof:placetype":"venue"
},
  "geometry": {"coordinates":[11.4015378952,48.1025009155],"type":"Point"}
}