{
  "type": "Feature",
  "properties": {
    "iso:country":"DE",
    "sg:address":"Industriestr. 22",
    "sg:city":"Melle",
    "sg:postcode":"49324",
    "sg:province":"Niedersachsen",
    "wof:name":"Pzm Parkett-zentrum Melle Gmbh",
    "wof:placetype":"venue"
},
  "geometry": {"coordinates":[8.3552274704,52.1907272339],"type":"Point"}
}