{
  "type": "Feature",
  "properties": {
    "iso:country":"DE",
    "sg:address":"Umschlagstr. 10",
    "sg:city":"M\u00fclheim",
    "sg:phone":"+49 208/58020",
    "sg:postcode":"45478",
    "sg:province":"Nordrhein-Westfalen",
    "wof:name":"Friedrich W. Markmann Gmbh",
    "wof:placetype":"venue"
},
  "geometry": {"coordinates":[6.836261,51.437435],"type":"Point"}
}