{
  "type": "Feature",
  "properties": {
    "iso:country":"DE",
    "sg:address":"Wormser Str. 21",
    "sg:city":"Westhofen",
    "sg:phone":"+49 6244/57131",
    "sg:postcode":"67593",
    "sg:province":"Rheinland-Pfalz",
    "wof:name":"Uniplay Automatenvertriebs- Gmbh",
    "wof:placetype":"venue"
},
  "geometry": {"coordinates":[8.24814,49.702248],"type":"Point"}
}