{
  "type": "Feature",
  "properties": {
    "iso:country":"DE",
    "sg:address":"Plettstr. 19",
    "sg:city":"M\u00fcnchen",
    "sg:phone":"+49 89/674829",
    "sg:postcode":"81735",
    "sg:province":"Bayern",
    "wof:name":"Ayinger Hof",
    "wof:placetype":"venue"
},
  "geometry": {"coordinates":[11.6433448792,48.1073455811],"type":"Point"}
}