{
  "type": "Feature",
  "properties": {
    "iso:country":"DE",
    "sg:address":"Goldene Aue 21",
    "sg:city":"Goslar",
    "sg:phone":"+49 5321/25139",
    "sg:postcode":"38640",
    "sg:province":"Niedersachsen",
    "wof:name":"Hans-joachim Bochdam Steuerbevollm.",
    "wof:placetype":"venue"
},
  "geometry": {"coordinates":[10.4243907928,51.918712616],"type":"Point"}
}