{
  "type": "Feature",
  "properties": {
    "iso:country":"DE",
    "sg:address":"Ochsengasse 5",
    "sg:city":"Weingarten",
    "sg:phone":"+49 751/561040",
    "sg:postcode":"88250",
    "sg:province":"Baden-W\u00fcrttemberg",
    "wof:name":"Hotel Alter Ochsen",
    "wof:placetype":"venue"
},
  "geometry": {"coordinates":[9.6426620483,47.8063926697],"type":"Point"}
}