{
  "type": "Feature",
  "properties": {
    "iso:country":"DE",
    "sg:city":"Miesbach",
    "sg:phone":"+49 8025/3031",
    "sg:postcode":"83714",
    "sg:province":"Bayern",
    "wof:name":"Hypo-bank Ag",
    "wof:placetype":"venue"
},
  "geometry": {"coordinates":[11.83342,47.789139],"type":"Point"}
}