{
  "type": "Feature",
  "properties": {
    "iso:country":"DE",
    "sg:address":"Arnsh\u00e4user Str. 41",
    "sg:city":"Bad Kissingen",
    "sg:phone":"+49 971/20800",
    "sg:postcode":"97688",
    "sg:province":"Bayern",
    "wof:name":"Schm\u00fcck Gmbh",
    "wof:placetype":"venue"
},
  "geometry": {"coordinates":[10.09537,50.180248],"type":"Point"}
}