{
  "type": "Feature",
  "properties": {
    "iso:country":"DE",
    "sg:address":"Dillinger Str. 14",
    "sg:city":"G\u00fcnzburg",
    "sg:phone":"+49 8221/4063",
    "sg:postcode":"89312",
    "sg:province":"Bayern",
    "wof:name":"Schwaben Echo",
    "wof:placetype":"venue"
},
  "geometry": {"coordinates":[10.2800731659,48.4577674866],"type":"Point"}
}