{
  "type": "Feature",
  "properties": {
    "iso:country":"DE",
    "sg:address":"Rathausplatz 1",
    "sg:city":"Gebhardshain",
    "sg:phone":"+49 2747/8090",
    "sg:postcode":"57580",
    "sg:province":"Rheinland-Pfalz",
    "wof:name":"Verbandsgemeindewerke",
    "wof:placetype":"venue"
},
  "geometry": {"coordinates":[7.81964,50.748035],"type":"Point"}
}