{
  "type": "Feature",
  "properties": {
    "iso:country":"DE",
    "sg:address":"S\u00fcderkirchenweg 1-3",
    "sg:city":"Hamburg",
    "sg:phone":"+49 40/7421880",
    "sg:postcode":"21129",
    "sg:province":"Hamburg",
    "wof:name":"Sigro Korrosions- Und Bautenschutz Gmbh",
    "wof:placetype":"venue"
},
  "geometry": {"coordinates":[9.8662557602,53.526714325],"type":"Point"}
}