{
  "type": "Feature",
  "properties": {
    "iso:country":"DE",
    "sg:address":"Weidenstr. 36a",
    "sg:city":"Oldenburg",
    "sg:phone":"+49 441/17427",
    "sg:postcode":"26135",
    "sg:province":"Niedersachsen",
    "wof:name":"Rolf B\u00fcker Gmbh",
    "wof:placetype":"venue"
},
  "geometry": {"coordinates":[8.22921,53.127621],"type":"Point"}
}