{
  "type": "Feature",
  "properties": {
    "iso:country":"DE",
    "sg:address":"Woninger Esch 14",
    "sg:city":"Gronau",
    "sg:phone":"+49 2565/3406",
    "sg:postcode":"48599",
    "sg:province":"Nordrhein-Westfalen",
    "wof:name":"Deutscher Verband F\u00fcr Gebrauchshunde",
    "wof:placetype":"venue"
},
  "geometry": {"coordinates":[7.0278701782,52.1829032898],"type":"Point"}
}