{
  "type": "Feature",
  "properties": {
    "iso:country":"DE",
    "sg:address":"Untere Alte Poststr. 1",
    "sg:city":"Warmensteinach",
    "sg:phone":"+49 9277/256",
    "sg:postcode":"95485",
    "sg:province":"Bayern",
    "wof:name":"Pension-cafe Pfeiferhaus",
    "wof:placetype":"venue"
},
  "geometry": {"coordinates":[11.7801704407,49.9900550842],"type":"Point"}
}