{
  "type": "Feature",
  "properties": {
    "iso:country":"DE",
    "sg:address":"Irlachinger Str. 3",
    "sg:city":"Schwandorf",
    "sg:phone":"+49 9431/21165",
    "sg:postcode":"92421",
    "sg:province":"Bayern",
    "wof:name":"Max Dietl",
    "wof:placetype":"venue"
},
  "geometry": {"coordinates":[12.108527,49.327663],"type":"Point"}
}