{
  "type": "Feature",
  "properties": {
    "iso:country":"DE",
    "sg:address":"Dorfstr. 61",
    "sg:city":"Sohland",
    "sg:postcode":"02894",
    "sg:province":"Sachsen",
    "wof:name":"H. M\u00e4ffert",
    "wof:placetype":"venue"
},
  "geometry": {"coordinates":[14.7688999176,51.1577033997],"type":"Point"}
}