{
  "type": "Feature",
  "properties": {
    "iso:country":"DE",
    "sg:address":"R\u00f6merstr. 75",
    "sg:city":"Pfullingen",
    "sg:phone":"+49 7121/754308",
    "sg:postcode":"72793",
    "sg:province":"Baden-W\u00fcrttemberg",
    "wof:name":"S. Czeschka-wetzel Immobilienmakler",
    "wof:placetype":"venue"
},
  "geometry": {"coordinates":[9.2205886841,48.4714927673],"type":"Point"}
}