{
  "type": "Feature",
  "properties": {
    "iso:country":"DE",
    "sg:address":"Tannenweg 3",
    "sg:city":"Weilm\u00fcnster",
    "sg:phone":"+49 6475/262",
    "sg:postcode":"35789",
    "sg:province":"Hessen",
    "wof:name":"Kramer Transport Gmbh",
    "wof:placetype":"venue"
},
  "geometry": {"coordinates":[8.3363637924,50.4022369385],"type":"Point"}
}