{
  "type": "Feature",
  "properties": {
    "iso:country":"DE",
    "sg:address":"Hochstr. 12",
    "sg:city":"Schmallenberg",
    "sg:phone":"+49 2974/317",
    "sg:postcode":"57392",
    "sg:province":"Nordrhein-Westfalen",
    "wof:name":"Dohl",
    "wof:placetype":"venue"
},
  "geometry": {"coordinates":[8.311016,51.192539],"type":"Point"}
}