{
  "type": "Feature",
  "properties": {
    "iso:country":"DE",
    "sg:address":"Niedereimerfeld 22",
    "sg:city":"Arnsberg",
    "sg:phone":"+49 2932/49080",
    "sg:postcode":"59823",
    "sg:province":"Nordrhein-Westfalen",
    "wof:name":"Stadtwerke Amsberg",
    "wof:placetype":"venue"
},
  "geometry": {"coordinates":[8.034249,51.422611],"type":"Point"}
}