{
  "type": "Feature",
  "properties": {
    "iso:country":"DE",
    "sg:address":"Rosenheimer Landstr. 113",
    "sg:city":"Riemerling",
    "sg:phone":"+49 89/6099070",
    "sg:postcode":"85521",
    "sg:province":"Bayern",
    "wof:name":"Papeterie Sigl Kg",
    "wof:placetype":"venue"
},
  "geometry": {"coordinates":[11.667656,48.056137],"type":"Point"}
}