{
  "type": "Feature",
  "properties": {
    "iso:country":"DE",
    "sg:address":"Leerer Landstr. 16",
    "sg:city":"Aurich",
    "sg:phone":"+49 4941/4254",
    "sg:postcode":"26603",
    "sg:province":"Niedersachsen",
    "wof:name":"Theessen Elktro Gmbh",
    "wof:placetype":"venue"
},
  "geometry": {"coordinates":[7.486065,53.466637],"type":"Point"}
}