{
  "type": "Feature",
  "properties": {
    "iso:country":"DE",
    "sg:address":"Pestalozzistr. 24",
    "sg:city":"Neustadt",
    "sg:phone":"+49 6327/4163",
    "sg:postcode":"67435",
    "sg:province":"Rheinland-Pfalz",
    "wof:name":"Fritz Schwarztrauber",
    "wof:placetype":"venue"
},
  "geometry": {"coordinates":[8.195489,49.327248],"type":"Point"}
}