{
  "type": "Feature",
  "properties": {
    "iso:country":"DE",
    "sg:address":"Neustr. 52",
    "sg:city":"Dinslaken",
    "sg:phone":"+49 2064/58696",
    "sg:postcode":"46535",
    "sg:province":"Nordrhein-Westfalen",
    "wof:name":"Ristorante Pizzeria Al Trullo",
    "wof:placetype":"venue"
},
  "geometry": {"coordinates":[6.7362418175,51.5626182556],"type":"Point"}
}