{
  "type": "Feature",
  "properties": {
    "iso:country":"DE",
    "sg:address":"Mendelssohnstr. 31",
    "sg:city":"Hannover",
    "sg:phone":"+49 511/888489",
    "sg:postcode":"30173",
    "sg:province":"Niedersachsen",
    "wof:name":"H. Butterwegge",
    "wof:placetype":"venue"
},
  "geometry": {"coordinates":[9.755978,52.356319],"type":"Point"}
}