{
  "type": "Feature",
  "properties": {
    "iso:country":"DE",
    "sg:address":"Werner-Sylten-Str. 15",
    "sg:city":"Bad K\u00f6stritz",
    "sg:phone":"+49 36605/2237",
    "sg:postcode":"07586",
    "sg:province":"Th\u00fcringen",
    "wof:name":"Manfred Gei\u00dfler",
    "wof:placetype":"venue"
},
  "geometry": {"coordinates":[12.007296,50.933346],"type":"Point"}
}