{
  "type": "Feature",
  "properties": {
    "iso:country":"DE",
    "sg:address":"Kurzer Kamp 11",
    "sg:city":"Denkte",
    "sg:phone":"+49 5331/906034",
    "sg:postcode":"38321",
    "sg:province":"Niedersachsen",
    "wof:name":"Kornelia Schubert",
    "wof:placetype":"venue"
},
  "geometry": {"coordinates":[10.6064071655,52.1465072632],"type":"Point"}
}