{
  "type": "Feature",
  "properties": {
    "iso:country":"DE",
    "sg:address":"K\u00fclsheim",
    "sg:city":"K\u00fclsheim",
    "sg:phone":"+49 9342/3000",
    "sg:postcode":"97900",
    "sg:province":"Baden-W\u00fcrttemberg",
    "wof:name":"Volksbank Wertheim Eg",
    "wof:placetype":"venue"
},
  "geometry": {"coordinates":[9.517351,49.758675],"type":"Point"}
}