{
  "type": "Feature",
  "properties": {
    "iso:country":"DE",
    "sg:address":"Ruhesteinstr. 18",
    "sg:city":"Seebach",
    "sg:phone":"+49 7842/1724",
    "sg:postcode":"77889",
    "sg:province":"Baden-W\u00fcrttemberg",
    "wof:name":"Udo Orlemann",
    "wof:placetype":"venue"
},
  "geometry": {"coordinates":[8.205678,48.580948],"type":"Point"}
}