{
  "type": "Feature",
  "properties": {
    "iso:country":"DE",
    "sg:address":"Am Holl 1",
    "sg:city":"Bergkamen",
    "sg:phone":"+49 2307/87086",
    "sg:postcode":"59192",
    "sg:province":"Nordrhein-Westfalen",
    "wof:name":"G\u00fcnter Schulze",
    "wof:placetype":"venue"
},
  "geometry": {"coordinates":[7.6587181091,51.6211776733],"type":"Point"}
}