{
  "type": "Feature",
  "properties": {
    "iso:country":"DE",
    "sg:address":"K\u00f6lner Str. 375",
    "sg:city":"D\u00fcsseldorf",
    "sg:phone":"+49 211/722450",
    "sg:postcode":"40227",
    "sg:province":"Nordrhein-Westfalen",
    "wof:name":"Gastst\u00e4tte Karla R\u00fcsche",
    "wof:placetype":"venue"
},
  "geometry": {"coordinates":[6.8103141785,51.2087593079],"type":"Point"}
}