{
  "type": "Feature",
  "properties": {
    "iso:country":"DE",
    "sg:address":"Rosenbergplatz 2",
    "sg:city":"Johanngeorgenstadt",
    "sg:phone":"+49 3773/883195",
    "sg:postcode":"08349",
    "sg:province":"Sachsen",
    "wof:name":"Wsk Gmbh",
    "wof:placetype":"venue"
},
  "geometry": {"coordinates":[12.6896934509,50.4424095154],"type":"Point"}
}