{
  "type": "Feature",
  "properties": {
    "iso:country":"DE",
    "sg:address":"Am B\u00fchl 2",
    "sg:city":"Heroldsberg",
    "sg:phone":"+49 911/5180479",
    "sg:postcode":"90562",
    "sg:province":"Bayern",
    "wof:name":"Horst Lemmen Gmbh",
    "wof:placetype":"venue"
},
  "geometry": {"coordinates":[11.148587,49.533131],"type":"Point"}
}