{
  "type": "Feature",
  "properties": {
    "iso:country":"DE",
    "sg:address":"Am Gewerbegebiet 1",
    "sg:city":"Gattendorf",
    "sg:phone":"+49 9281/734200",
    "sg:postcode":"95185",
    "sg:province":"Bayern",
    "wof:name":"Spacewall Gmbh",
    "wof:placetype":"venue"
},
  "geometry": {"coordinates":[11.9948263168,50.319355011],"type":"Point"}
}