{
  "type": "Feature",
  "properties": {
    "iso:country":"DE",
    "sg:address":"Zum Himmelreich 28",
    "sg:city":"N\u00fcrnberg",
    "sg:phone":"+49 911/305023",
    "sg:postcode":"90427",
    "sg:province":"Bayern",
    "wof:name":"Behindertenwerkstatt",
    "wof:placetype":"venue"
},
  "geometry": {"coordinates":[11.02454,49.520489],"type":"Point"}
}