{
  "type": "Feature",
  "properties": {
    "iso:country":"DE",
    "sg:address":"Klingenhofstr. 50",
    "sg:city":"N\u00fcrnberg",
    "sg:postcode":"90411",
    "sg:province":"Bayern",
    "wof:name":"H Records Overstock Vertriebs Gmbh",
    "wof:placetype":"venue"
},
  "geometry": {"coordinates":[11.112326,49.475143],"type":"Point"}
}