{
  "type": "Feature",
  "properties": {
    "iso:country":"DE",
    "sg:address":"Waldhausen 9",
    "sg:city":"T\u00fcbingen",
    "sg:phone":"+49 7071/64365",
    "sg:postcode":"72076",
    "sg:province":"Baden-W\u00fcrttemberg",
    "wof:name":"Waldh\u00e4userhof",
    "wof:placetype":"venue"
},
  "geometry": {"coordinates":[9.0529947281,48.5454559326],"type":"Point"}
}