{
  "type": "Feature",
  "properties": {
    "iso:country":"DE",
    "sg:address":"An der Surheide 34",
    "sg:city":"Ottersberg",
    "sg:phone":"+49 4293/880",
    "sg:postcode":"28870",
    "sg:province":"Niedersachsen",
    "wof:name":"Co-lo-trans Gmbh",
    "wof:placetype":"venue"
},
  "geometry": {"coordinates":[9.0724544525,53.1230735779],"type":"Point"}
}