{
  "type": "Feature",
  "properties": {
    "iso:country":"DE",
    "sg:address":"Am Graben 32",
    "sg:city":"Thum-Herold",
    "sg:postcode":"09419",
    "sg:province":"Sachsen",
    "wof:name":"J. Beck",
    "wof:placetype":"venue"
},
  "geometry": {"coordinates":[12.9497995377,50.6744308472],"type":"Point"}
}