{
  "type": "Feature",
  "properties": {
    "iso:country":"DE",
    "sg:address":"Im Wiesengrund 1",
    "sg:city":"H\u00f6rstel",
    "sg:phone":"+49 5454/7646",
    "sg:postcode":"48477",
    "sg:province":"Nordrhein-Westfalen",
    "wof:name":"S. Seifert",
    "wof:placetype":"venue"
},
  "geometry": {"coordinates":[7.6200671196,52.2585754395],"type":"Point"}
}