{
  "type": "Feature",
  "properties": {
    "iso:country":"DE",
    "sg:address":"Enscheder Str. 112",
    "sg:city":"Gronau",
    "sg:phone":"+49 2562/4484",
    "sg:postcode":"48599",
    "sg:province":"Nordrhein-Westfalen",
    "wof:name":"Theo L\u00fctke-wenning",
    "wof:placetype":"venue"
},
  "geometry": {"coordinates":[7.008135,52.21347],"type":"Point"}
}