{
  "type": "Feature",
  "properties": {
    "iso:country":"DE",
    "sg:address":"Kohlmeisenweg 6",
    "sg:city":"Torgau",
    "sg:phone":"+49 3421/710529",
    "sg:postcode":"04860",
    "sg:province":"Sachsen",
    "wof:name":"Frank-roland Franke",
    "wof:placetype":"venue"
},
  "geometry": {"coordinates":[12.9722204208,51.5684318542],"type":"Point"}
}