{
  "type": "Feature",
  "properties": {
    "iso:country":"DE",
    "sg:address":"Merseburger Str. 9",
    "sg:city":"Dresden",
    "sg:phone":"+49 351/3100020",
    "sg:postcode":"01309",
    "sg:province":"Sachsen",
    "wof:name":"Matthias Roch",
    "wof:placetype":"venue"
},
  "geometry": {"coordinates":[13.783204,51.046577],"type":"Point"}
}