{
  "type": "Feature",
  "properties": {
    "iso:country":"DE",
    "sg:address":"Trostfelde 3",
    "sg:city":"Altentreptow",
    "sg:phone":"+49 3961/212976",
    "sg:postcode":"17087",
    "sg:province":"Mecklenburg-Vorpommern",
    "wof:name":"Reinhard Korff",
    "wof:placetype":"venue"
},
  "geometry": {"coordinates":[13.238871,53.683453],"type":"Point"}
}