{
  "type": "Feature",
  "properties": {
    "iso:country":"DE",
    "sg:address":"Ritterstr. 26",
    "sg:city":"R\u00fcthen",
    "sg:phone":"+49 2952/1005",
    "sg:postcode":"59602",
    "sg:province":"Nordrhein-Westfalen",
    "wof:name":"Karl-josef Niggemann",
    "wof:placetype":"venue"
},
  "geometry": {"coordinates":[8.428387,51.493015],"type":"Point"}
}