{
  "type": "Feature",
  "properties": {
    "iso:country":"DE",
    "sg:address":"Robert-Bosch-Str. 32",
    "sg:city":"Dreieich",
    "sg:phone":"+49 6103/9160",
    "sg:postcode":"63303",
    "sg:province":"Hessen",
    "wof:name":"Nacamar Data Communications Gmbh",
    "wof:placetype":"venue"
},
  "geometry": {"coordinates":[8.7048311234,50.0319595337],"type":"Point"}
}