{
  "type": "Feature",
  "properties": {
    "iso:country":"DE",
    "sg:address":"Mainzer Str. 9",
    "sg:city":"Bingen",
    "sg:postcode":"55411",
    "sg:province":"Rheinland-Pfalz",
    "wof:name":"Cinema-lichtspiele",
    "wof:placetype":"venue"
},
  "geometry": {"coordinates":[7.898666,49.968334],"type":"Point"}
}