{
  "type": "Feature",
  "properties": {
    "iso:country":"DE",
    "sg:address":"Im Brunskroog 17",
    "sg:city":"L\u00fcbeck",
    "sg:phone":"+49 451/395590",
    "sg:postcode":"23569",
    "sg:province":"Schleswig-Holstein",
    "wof:name":"Planungsgruppe Kmo",
    "wof:placetype":"venue"
},
  "geometry": {"coordinates":[10.79529953,53.907787323],"type":"Point"}
}