{
  "type": "Feature",
  "properties": {
    "iso:country":"DE",
    "sg:address":"Turnstr. 1",
    "sg:city":"Spremberg",
    "sg:phone":"+49 3563/93068",
    "sg:postcode":"03130",
    "sg:province":"Brandenburg",
    "wof:name":"\u00d6kumenische Sozial- Station E. V.",
    "wof:placetype":"venue"
},
  "geometry": {"coordinates":[14.372315,51.566093],"type":"Point"}
}