{
  "type": "Feature",
  "properties": {
    "iso:country":"DE",
    "sg:address":"Frankfurter Ring 150",
    "sg:city":"M\u00fcnchen",
    "sg:phone":"+49 89/35653560",
    "sg:postcode":"80807",
    "sg:province":"Bayern",
    "wof:name":"Hg Trans Int. Spedition Und Handel Gmbh",
    "wof:placetype":"venue"
},
  "geometry": {"coordinates":[11.5869913101,48.1877326965],"type":"Point"}
}