{
  "type": "Feature",
  "properties": {
    "iso:country":"DE",
    "sg:address":"Zwischen den Br\u00fccken 7",
    "sg:city":"Buxtehude",
    "sg:phone":"+49 4161/512661",
    "sg:postcode":"21614",
    "sg:province":"Niedersachsen",
    "wof:name":"Br\u00fccken-apotheke Inh. Marion St\u00fcwe",
    "wof:placetype":"venue"
},
  "geometry": {"coordinates":[9.697228,53.475067],"type":"Point"}
}