{
  "type": "Feature",
  "properties": {
    "iso:country":"DE",
    "sg:address":"Grauwisch 13",
    "sg:city":"Heiligenhafen",
    "sg:phone":"+49 4362/6600",
    "sg:postcode":"23774",
    "sg:province":"Schleswig-Holstein",
    "wof:name":"Modellbaugruppe Heiligenhafen Karl-heinz Babbe",
    "wof:placetype":"venue"
},
  "geometry": {"coordinates":[10.9656991959,54.3671264648],"type":"Point"}
}