{
  "type": "Feature",
  "properties": {
    "iso:country":"DE",
    "sg:address":"Stra\u00dfe der Republik 41",
    "sg:city":"Wiesbaden",
    "sg:phone":"+49 611/691576",
    "sg:postcode":"65203",
    "sg:province":"Hessen",
    "wof:name":"Mr. Rib",
    "wof:placetype":"venue"
},
  "geometry": {"coordinates":[8.2413101196,50.0461654663],"type":"Point"}
}