{
  "type": "Feature",
  "properties": {
    "iso:country":"DE",
    "sg:address":"Sendlinger-Tor-Platz 10",
    "sg:city":"M\u00fcnchen",
    "sg:phone":"+49 89/592317",
    "sg:postcode":"80336",
    "sg:province":"Bayern",
    "wof:name":"Radsport Haase Inh. Axel Haase",
    "wof:placetype":"venue"
},
  "geometry": {"coordinates":[11.566608,48.134041],"type":"Point"}
}