{
  "type": "Feature",
  "properties": {
    "iso:country":"DE",
    "sg:address":"Schlo\u00df-Wolfsbrunnenweg 60",
    "sg:city":"Heidelberg",
    "sg:phone":"+49 6221/803600",
    "sg:postcode":"69118",
    "sg:province":"Baden-W\u00fcrttemberg",
    "wof:name":"Dorothea Weber Steuerberaterin",
    "wof:placetype":"venue"
},
  "geometry": {"coordinates":[8.7399587631,49.4132537842],"type":"Point"}
}