{
  "type": "Feature",
  "properties": {
    "iso:country":"DE",
    "sg:address":"Waldstr. 33",
    "sg:city":"Queidersbach",
    "sg:phone":"+49 6371/2288",
    "sg:postcode":"66851",
    "sg:province":"Rheinland-Pfalz",
    "wof:name":"Ludwig Lutz Architekt",
    "wof:placetype":"venue"
},
  "geometry": {"coordinates":[7.636212,49.373638],"type":"Point"}
}