{
  "type": "Feature",
  "properties": {
    "iso:country":"DE",
    "sg:address":"Alois-Lang-Str. 12",
    "sg:city":"Bad Waldsee",
    "sg:phone":"+49 7524/5746",
    "sg:postcode":"88339",
    "sg:province":"Baden-W\u00fcrttemberg",
    "wof:name":"Herbert Zettlert Ingenieur",
    "wof:placetype":"venue"
},
  "geometry": {"coordinates":[9.7630691528,47.9195289612],"type":"Point"}
}