{
  "type": "Feature",
  "properties": {
    "iso:country":"DE",
    "sg:address":"Badstubenstr. 37",
    "sg:city":"Wolgast",
    "sg:phone":"+49 3836/203366",
    "sg:postcode":"17438",
    "sg:province":"Mecklenburg-Vorpommern",
    "wof:name":"G\u00fcnter Bluhm",
    "wof:placetype":"venue"
},
  "geometry": {"coordinates":[13.7786436081,54.05493927],"type":"Point"}
}