{
  "type": "Feature",
  "properties": {
    "iso:country":"DE",
    "sg:address":"Hauptstr. 16",
    "sg:city":"Geslau",
    "sg:phone":"+49 9867/252",
    "sg:postcode":"91608",
    "sg:province":"Bayern",
    "wof:name":"Siegfried List",
    "wof:placetype":"venue"
},
  "geometry": {"coordinates":[10.308878,49.367977],"type":"Point"}
}