{
  "type": "Feature",
  "properties": {
    "iso:country":"DE",
    "sg:address":"Thomas-Mann-Str. 60",
    "sg:city":"N\u00fcrnberg",
    "sg:phone":"+49 911/5868855",
    "sg:postcode":"90471",
    "sg:province":"Bayern",
    "wof:name":"Symacma Matthias Koch Und Partner Ohg",
    "wof:placetype":"venue"
},
  "geometry": {"coordinates":[11.137659,49.414204],"type":"Point"}
}