{
  "type": "Feature",
  "properties": {
    "iso:country":"DE",
    "sg:address":"Kirchstr. 4",
    "sg:city":"Queidersbach",
    "sg:phone":"+49 6371/15750",
    "sg:postcode":"66851",
    "sg:province":"Rheinland-Pfalz",
    "wof:name":"G\u00fcnter M\u00fcller",
    "wof:placetype":"venue"
},
  "geometry": {"coordinates":[7.631919,49.373871],"type":"Point"}
}