{
  "type": "Feature",
  "properties": {
    "iso:country":"DE",
    "sg:address":"Sennhofgasse 7",
    "sg:city":"Biberach",
    "sg:phone":"+49 7351/13320",
    "sg:postcode":"88400",
    "sg:province":"Baden-W\u00fcrttemberg",
    "wof:name":"R. Wiedmann",
    "wof:placetype":"venue"
},
  "geometry": {"coordinates":[9.790233,48.096951],"type":"Point"}
}