{
  "type": "Feature",
  "properties": {
    "iso:country":"DE",
    "sg:address":"Zum Brinkberg 1",
    "sg:city":"Eggerm\u00fchlen",
    "sg:phone":"+49 5462/1232",
    "sg:postcode":"49577",
    "sg:province":"Niedersachsen",
    "wof:name":"Walter Kr\u00e4mer Ingenieur",
    "wof:placetype":"venue"
},
  "geometry": {"coordinates":[7.8128199577,52.5401077271],"type":"Point"}
}