{
  "type": "Feature",
  "properties": {
    "iso:country":"DE",
    "sg:address":"Oranienstr. 140-142",
    "sg:city":"Berlin",
    "sg:phone":"+49 30/25921405",
    "sg:postcode":"10969",
    "sg:province":"Berlin",
    "wof:name":"Arbeiterwohlfahrt Landesverband Berlin E. V.",
    "wof:placetype":"venue"
},
  "geometry": {"coordinates":[13.408741,52.504082],"type":"Point"}
}