{
  "type": "Feature",
  "properties": {
    "iso:country":"DE",
    "sg:address":"Saarstr. 39",
    "sg:city":"Trier",
    "sg:postcode":"54290",
    "sg:province":"Rheinland-Pfalz",
    "wof:name":"Gothaer U. Berlin-k\u00f6lnische Versicherungen",
    "wof:placetype":"venue"
},
  "geometry": {"coordinates":[6.6361179352,49.7473602295],"type":"Point"}
}