{
  "type": "Feature",
  "properties": {
    "iso:country":"DE",
    "sg:address":"Holunderweg 9",
    "sg:city":"Essen",
    "sg:phone":"+49 5434/3071",
    "sg:postcode":"49632",
    "sg:province":"Niedersachsen",
    "wof:name":"Wilhelm Plez",
    "wof:placetype":"venue"
},
  "geometry": {"coordinates":[6.9967718124,51.4199104309],"type":"Point"}
}