{
  "type": "Feature",
  "properties": {
    "iso:country":"DE",
    "sg:address":"Wallauer Weg 2B",
    "sg:city":"Wiesbaden",
    "sg:phone":"+49 6122/940222",
    "sg:postcode":"65205",
    "sg:province":"Hessen",
    "wof:name":"H. & H. Bautr\u00e4ger Gmbh",
    "wof:placetype":"venue"
},
  "geometry": {"coordinates":[8.34659,50.064243],"type":"Point"}
}