{
  "type": "Feature",
  "properties": {
    "iso:country":"DE",
    "sg:address":"Geschwister-Scholl-Str. 14",
    "sg:city":"Stendal",
    "sg:postcode":"39576",
    "sg:province":"Sachsen-Anhalt",
    "wof:name":"Apothekerverein Sachsen-anhalt Region Magdeburg E. V.",
    "wof:placetype":"venue"
},
  "geometry": {"coordinates":[11.860824585,52.6062316895],"type":"Point"}
}