{
  "type": "Feature",
  "properties": {
    "iso:country":"DE",
    "sg:address":"Karl-Ulrich-Str. 3",
    "sg:city":"Worms",
    "sg:phone":"+49 6241/93800",
    "sg:postcode":"67547",
    "sg:province":"Rheinland-Pfalz",
    "wof:name":"J\u00fcrgen M\u00f6thrath Rechtsanwalt",
    "wof:placetype":"venue"
},
  "geometry": {"coordinates":[8.3567800522,49.6147346497],"type":"Point"}
}