{
  "type": "Feature",
  "properties": {
    "iso:country":"DE",
    "sg:address":"Enthalb der Ach 7",
    "sg:city":"Wertach",
    "sg:phone":"+49 8365/234",
    "sg:postcode":"87497",
    "sg:province":"Bayern",
    "wof:name":"Konrad Gebhart",
    "wof:placetype":"venue"
},
  "geometry": {"coordinates":[10.418113,47.59634],"type":"Point"}
}