{
  "type": "Feature",
  "properties": {
    "iso:country":"DE",
    "sg:address":"Uphauser Weg 61",
    "sg:city":"Osnabr\u00fcck",
    "sg:phone":"+49 541/389689",
    "sg:postcode":"49086",
    "sg:province":"Niedersachsen",
    "wof:name":"Hubert Strickmann",
    "wof:placetype":"venue"
},
  "geometry": {"coordinates":[8.121469,52.237789],"type":"Point"}
}