{
  "type": "Feature",
  "properties": {
    "iso:country":"DE",
    "sg:address":"Camesallee 20",
    "sg:city":"Meerbusch",
    "sg:phone":"+49 2159/81111",
    "sg:postcode":"40670",
    "sg:province":"Nordrhein-Westfalen",
    "wof:name":"Alleest\u00fcbchen",
    "wof:placetype":"venue"
},
  "geometry": {"coordinates":[6.6621098518,51.2821159363],"type":"Point"}
}