{
  "type": "Feature",
  "properties": {
    "iso:country":"DE",
    "sg:address":"Ossecker Str. 174",
    "sg:city":"Hof",
    "sg:postcode":"95030",
    "sg:province":"Bayern",
    "wof:name":"Pro-videntia Rechtsanwalts Ag Zwndl. Hof",
    "wof:placetype":"venue"
},
  "geometry": {"coordinates":[11.8809652328,50.3101768494],"type":"Point"}
}