{
  "type": "Feature",
  "properties": {
    "iso:country":"DE",
    "sg:address":"Bokeler Str. 8",
    "sg:city":"Cappeln",
    "sg:postcode":"49692",
    "sg:province":"Niedersachsen",
    "wof:name":"Servcom Gmbh",
    "wof:placetype":"venue"
},
  "geometry": {"coordinates":[8.1122941971,52.8096237183],"type":"Point"}
}