{
  "type": "Feature",
  "properties": {
    "iso:country":"DE",
    "sg:address":"Berliner Str. 51",
    "sg:city":"Schkeuditz",
    "sg:phone":"+49 34204/62496",
    "sg:postcode":"04435",
    "sg:province":"Sachsen",
    "wof:name":"Sander Bauhandelsagentur Gmbh",
    "wof:placetype":"venue"
},
  "geometry": {"coordinates":[12.2206802368,51.4083900452],"type":"Point"}
}