{
  "type": "Feature",
  "properties": {
    "iso:country":"DE",
    "sg:address":"Blumenstr. 12",
    "sg:city":"Daun",
    "sg:phone":"+49 6592/2334",
    "sg:postcode":"54550",
    "sg:province":"Rheinland-Pfalz",
    "wof:name":"Klara R\u00f6mer",
    "wof:placetype":"venue"
},
  "geometry": {"coordinates":[6.8452811241,50.2230567932],"type":"Point"}
}