{
  "type": "Feature",
  "properties": {
    "iso:country":"DE",
    "sg:address":"Innere Zittauer Str. 2",
    "sg:city":"L\u00f6bau",
    "sg:phone":"+49 3585/402084",
    "sg:postcode":"02708",
    "sg:province":"Sachsen",
    "wof:name":"Annes Boutique Gmbh",
    "wof:placetype":"venue"
},
  "geometry": {"coordinates":[14.6663370132,51.0950050354],"type":"Point"}
}