{
  "type": "Feature",
  "properties": {
    "iso:country":"DE",
    "sg:address":"Hirschgasse 26",
    "sg:city":"Neckargem\u00fcnd",
    "sg:phone":"+49 6223/861860",
    "sg:postcode":"69151",
    "sg:province":"Baden-W\u00fcrttemberg",
    "wof:name":"Move Ya! Entertainment & Media - Agentur F\u00fcr Kommunikation",
    "wof:placetype":"venue"
},
  "geometry": {"coordinates":[8.796886,49.398769],"type":"Point"}
}