{
  "type": "Feature",
  "properties": {
    "iso:country":"DE",
    "sg:address":"Feldstr. 66",
    "sg:city":"Hamburg",
    "sg:phone":"+49 40/43178100",
    "sg:postcode":"20359",
    "sg:province":"Hamburg",
    "wof:name":"Pps Professional Photo Service",
    "wof:placetype":"venue"
},
  "geometry": {"coordinates":[9.970376,53.557163],"type":"Point"}
}