{
  "type": "Feature",
  "properties": {
    "iso:country":"DE",
    "sg:address":"Kropplenberg",
    "sg:city":"Meinerzhagen",
    "sg:phone":"+49 2354/4917",
    "sg:postcode":"58540",
    "sg:province":"Nordrhein-Westfalen",
    "wof:name":"Rudolf Baeger",
    "wof:placetype":"venue"
},
  "geometry": {"coordinates":[7.656107,51.078182],"type":"Point"}
}