{
  "type": "Feature",
  "properties": {
    "iso:country":"DE",
    "sg:address":"Zum Friedhof 12a",
    "sg:city":"Ebsdorfergrund",
    "sg:postcode":"35085",
    "sg:province":"Hessen",
    "wof:name":"A. Scheidt Hebamme",
    "wof:placetype":"venue"
},
  "geometry": {"coordinates":[8.852757,50.727879],"type":"Point"}
}