{
  "type": "Feature",
  "properties": {
    "iso:country":"DE",
    "sg:address":"Liebenaustr. 38",
    "sg:city":"Waldenbuch",
    "sg:phone":"+49 7157/20499",
    "sg:postcode":"71111",
    "sg:province":"Baden-W\u00fcrttemberg",
    "wof:name":"Wohnbau Waldenbuch Gmbh & Co.",
    "wof:placetype":"venue"
},
  "geometry": {"coordinates":[9.139053,48.639938],"type":"Point"}
}