{
  "type": "Feature",
  "properties": {
    "iso:country":"DE",
    "sg:address":"Leonberger Str. 35",
    "sg:city":"Leonberg",
    "sg:phone":"+49 7152/929753",
    "sg:postcode":"71229",
    "sg:province":"Baden-W\u00fcrttemberg",
    "wof:name":"Mc Immobilien Gmbh",
    "wof:placetype":"venue"
},
  "geometry": {"coordinates":[9.0104570389,48.7911529541],"type":"Point"}
}