{
  "type": "Feature",
  "properties": {
    "iso:country":"DE",
    "sg:address":"Celler Str. 7a",
    "sg:city":"Ebstorf",
    "sg:phone":"+49 5822/2427",
    "sg:postcode":"29574",
    "sg:province":"Niedersachsen",
    "wof:name":"Gerhard Pooch",
    "wof:placetype":"venue"
},
  "geometry": {"coordinates":[10.416505,53.028725],"type":"Point"}
}