{
  "type": "Feature",
  "properties": {
    "iso:country":"DE",
    "sg:address":"Gietlhausener Str. 47",
    "sg:city":"Neuburg",
    "sg:phone":"+49 8431/7512",
    "sg:postcode":"86633",
    "sg:province":"Bayern",
    "wof:name":"Dr. G\u00fcnther Schnitzer Rechtsanwalt",
    "wof:placetype":"venue"
},
  "geometry": {"coordinates":[11.2046298981,48.7456016541],"type":"Point"}
}