{
  "type": "Feature",
  "properties": {
    "iso:country":"DE",
    "sg:address":"S\u00f6llingstr. 17",
    "sg:city":"Kehl",
    "sg:postcode":"77694",
    "sg:province":"Baden-W\u00fcrttemberg",
    "wof:name":"Topline Handels Gmbh",
    "wof:placetype":"venue"
},
  "geometry": {"coordinates":[7.8331828117,48.5637741089],"type":"Point"}
}