{
  "type": "Feature",
  "properties": {
    "iso:country":"DE",
    "sg:address":"Darmst\u00e4dter Str. 1",
    "sg:city":"Bischofsheim",
    "sg:phone":"+49 6144/964504",
    "sg:postcode":"65474",
    "sg:province":"Hessen",
    "wof:name":"Billard Bistro Royal",
    "wof:placetype":"venue"
},
  "geometry": {"coordinates":[8.3551998138,49.9888687134],"type":"Point"}
}