{
  "type": "Feature",
  "properties": {
    "iso:country":"DE",
    "sg:address":"Hohenzollernring 22-24",
    "sg:city":"K\u00f6ln",
    "sg:phone":"+49 221/2578441",
    "sg:postcode":"50672",
    "sg:province":"Nordrhein-Westfalen",
    "wof:name":"Sabine Schmidt",
    "wof:placetype":"venue"
},
  "geometry": {"coordinates":[6.939502,50.937965],"type":"Point"}
}