{
  "type": "Feature",
  "properties": {
    "iso:country":"DE",
    "sg:address":"Kastengasse 2",
    "sg:city":"Neumarkt",
    "sg:phone":"+49 9181/69580",
    "sg:postcode":"92318",
    "sg:province":"Bayern",
    "wof:name":"Reiseb\u00fcro Maric",
    "wof:placetype":"venue"
},
  "geometry": {"coordinates":[11.4598312378,49.2802734375],"type":"Point"}
}