{
  "type": "Feature",
  "properties": {
    "iso:country":"DE",
    "sg:address":"S\u00fcdring 189",
    "sg:city":"Heiligenhaus",
    "sg:phone":"+49 2056/2953",
    "sg:postcode":"42579",
    "sg:province":"Nordrhein-Westfalen",
    "wof:name":"F. W. R\u00fccker",
    "wof:placetype":"venue"
},
  "geometry": {"coordinates":[6.960048,51.324215],"type":"Point"}
}