{
  "type": "Feature",
  "properties": {
    "iso:country":"DE",
    "sg:address":"Siddesser Str. 3",
    "sg:city":"Brakel",
    "sg:phone":"+49 5645/236",
    "sg:postcode":"33034",
    "sg:province":"Nordrhein-Westfalen",
    "wof:name":"Egon Barkhausen",
    "wof:placetype":"venue"
},
  "geometry": {"coordinates":[9.1820163727,51.6428947449],"type":"Point"}
}