{
  "type": "Feature",
  "properties": {
    "iso:country":"DE",
    "sg:address":"Prora",
    "sg:city":"Ostseebad Binz",
    "sg:phone":"+49 38393/32659",
    "sg:postcode":"18609",
    "sg:province":"Mecklenburg-Vorpommern",
    "wof:name":"Gfb Liegenschafts- Verwaltung Mbh",
    "wof:placetype":"venue"
},
  "geometry": {"coordinates":[13.6030893326,54.4026451111],"type":"Point"}
}