{
  "type": "Feature",
  "properties": {
    "iso:country":"DE",
    "sg:address":"Hollager Str 26a",
    "sg:city":"Wallenhorst",
    "sg:phone":"+49 5407/857951",
    "sg:postcode":"49134",
    "sg:province":"Niedersachsen",
    "wof:name":"Xtrasat Deutschland Gmbh",
    "wof:placetype":"venue"
},
  "geometry": {"coordinates":[8.006607,52.351776],"type":"Point"}
}