{
  "type": "Feature",
  "properties": {
    "iso:country":"DE",
    "sg:address":"Neuer Anbau 7",
    "sg:city":"Rosenthal",
    "sg:phone":"+49 35033/70410",
    "sg:postcode":"01824",
    "sg:province":"Sachsen",
    "wof:name":"Ferienwohnung Mergen",
    "wof:placetype":"venue"
},
  "geometry": {"coordinates":[14.063443,50.844158],"type":"Point"}
}