{
  "type": "Feature",
  "properties": {
    "iso:country":"DE",
    "sg:address":"Mittelweg 30",
    "sg:city":"Leegebruch",
    "sg:phone":"+49 3304/250897",
    "sg:postcode":"16767",
    "sg:province":"Brandenburg",
    "wof:name":"Bestattungsannahme Karin Pekrul",
    "wof:placetype":"venue"
},
  "geometry": {"coordinates":[13.191035,52.730911],"type":"Point"}
}