{
  "type": "Feature",
  "properties": {
    "iso:country":"DE",
    "sg:address":"Beethovenring 13",
    "sg:city":"Lehrte",
    "sg:phone":"+49 5132/57148",
    "sg:postcode":"31275",
    "sg:province":"Niedersachsen",
    "wof:name":"J. Und C. Hu\u00dfmann",
    "wof:placetype":"venue"
},
  "geometry": {"coordinates":[9.962112,52.366665],"type":"Point"}
}