{
  "type": "Feature",
  "properties": {
    "iso:country":"DE",
    "sg:address":"Mahlhaus 11",
    "sg:city":"Hamburg",
    "sg:phone":"+49 40/6436342",
    "sg:postcode":"22159",
    "sg:province":"Hamburg",
    "wof:name":"G\u00fcnter Heins",
    "wof:placetype":"venue"
},
  "geometry": {"coordinates":[10.113591,53.608402],"type":"Point"}
}