{
  "type": "Feature",
  "properties": {
    "iso:country":"DE",
    "sg:address":"Hardenbergstr. 16-18",
    "sg:city":"Berlin",
    "sg:postcode":"10623",
    "sg:province":"Berlin",
    "wof:name":"Jci Europakonferenz Wirtschaftsjunioren",
    "wof:placetype":"venue"
},
  "geometry": {"coordinates":[13.328414,52.507797],"type":"Point"}
}