{
  "type": "Feature",
  "properties": {
    "iso:country":"DE",
    "sg:address":"Hanauer Vorstadt 7",
    "sg:city":"Hanau",
    "sg:phone":"+49 6181/20809",
    "sg:postcode":"63450",
    "sg:province":"Hessen",
    "wof:name":"Hirsch-apotheke",
    "wof:placetype":"venue"
},
  "geometry": {"coordinates":[8.911792,50.137451],"type":"Point"}
}