{
  "type": "Feature",
  "properties": {
    "iso:country":"DE",
    "sg:address":"Marienterrasse 2",
    "sg:city":"Hamburg",
    "sg:postcode":"22085",
    "sg:province":"Hamburg",
    "wof:name":"Tkm Transport Kommunikation Und Marketing Gmbh",
    "wof:placetype":"venue"
},
  "geometry": {"coordinates":[10.0135087967,53.5760993958],"type":"Point"}
}