{
  "type": "Feature",
  "properties": {
    "iso:country":"DE",
    "sg:address":"Illerstr. 61",
    "sg:city":"Senden",
    "sg:phone":"+49 7307/32104",
    "sg:postcode":"89250",
    "sg:province":"Bayern",
    "wof:name":"Restaurant Meteora",
    "wof:placetype":"venue"
},
  "geometry": {"coordinates":[10.0397138596,48.3180847168],"type":"Point"}
}