{
  "type": "Feature",
  "properties": {
    "iso:country":"DE",
    "sg:address":"Kirchstr. 13",
    "sg:city":"Wustrow",
    "sg:phone":"+49 5843/1320",
    "sg:postcode":"29462",
    "sg:province":"Niedersachsen",
    "wof:name":"Friseursalon K. B\u00f6hnsch Gmbh",
    "wof:placetype":"venue"
},
  "geometry": {"coordinates":[11.118763,52.9245],"type":"Point"}
}