{
  "type": "Feature",
  "properties": {
    "iso:country":"DE",
    "sg:address":"Schnitzschulstr. 2",
    "sg:city":"Garmisch-Partenkirchen",
    "sg:phone":"+49 8821/2182",
    "sg:postcode":"82467",
    "sg:province":"Bayern",
    "wof:name":"Stefan Wolff",
    "wof:placetype":"venue"
},
  "geometry": {"coordinates":[11.1097698212,47.4945068359],"type":"Point"}
}