{
  "type": "Feature",
  "properties": {
    "iso:country":"DE",
    "sg:address":"Kalmsweg 8",
    "sg:city":"Bremen",
    "sg:phone":"+49 421/649100",
    "sg:postcode":"28239",
    "sg:province":"Bremen",
    "wof:name":"Backmann Verwaltungs- Gmbh",
    "wof:placetype":"venue"
},
  "geometry": {"coordinates":[8.7417135239,53.1362571716],"type":"Point"}
}