{
  "type": "Feature",
  "properties": {
    "iso:country":"DE",
    "sg:address":"Am Markt 5",
    "sg:city":"Osten",
    "sg:phone":"+49 4771/3682",
    "sg:postcode":"21756",
    "sg:province":"Niedersachsen",
    "wof:name":"Heimat- Und Budelmuseum",
    "wof:placetype":"venue"
},
  "geometry": {"coordinates":[9.18764,53.694084],"type":"Point"}
}