{
  "type": "Feature",
  "properties": {
    "iso:country":"DE",
    "sg:address":"Hochstr. 44",
    "sg:city":"Ingelheim",
    "sg:phone":"+49 6132/84750",
    "sg:postcode":"55218",
    "sg:province":"Rheinland-Pfalz",
    "wof:name":"Pool",
    "wof:placetype":"venue"
},
  "geometry": {"coordinates":[8.030336,49.988789],"type":"Point"}
}