{
  "type": "Feature",
  "properties": {
    "iso:country":"DE",
    "sg:address":"Reinsburgstr. 110",
    "sg:city":"Stuttgart",
    "sg:phone":"+49 711/6153140",
    "sg:postcode":"70197",
    "sg:province":"Baden-W\u00fcrttemberg",
    "wof:name":"Friedrich Rocker Architekt",
    "wof:placetype":"venue"
},
  "geometry": {"coordinates":[9.157051,48.768211],"type":"Point"}
}