{
  "type": "Feature",
  "properties": {
    "iso:country":"DE",
    "sg:address":"Veit-Sto\u00df-Str. 50",
    "sg:city":"M\u00fcnchen",
    "sg:phone":"+49 89/5800251",
    "sg:postcode":"80687",
    "sg:province":"Bayern",
    "wof:name":"Wolfgang Blanke Architekt",
    "wof:placetype":"venue"
},
  "geometry": {"coordinates":[11.506342,48.141277],"type":"Point"}
}