{
  "type": "Feature",
  "properties": {
    "iso:country":"DE",
    "sg:address":"Am Tower 3",
    "sg:city":"N\u00fcrnberg",
    "sg:phone":"+49 9128/726261",
    "sg:postcode":"90475",
    "sg:province":"Bayern",
    "wof:name":"B & B Merchandising Gmbh",
    "wof:placetype":"venue"
},
  "geometry": {"coordinates":[11.1771154404,49.3892211914],"type":"Point"}
}