{
  "type": "Feature",
  "properties": {
    "iso:country":"DE",
    "sg:address":"Gewerbestr. 12",
    "sg:city":"Kappel-Grafenhausen",
    "sg:phone":"+49 7822/76583",
    "sg:postcode":"77966",
    "sg:province":"Baden-W\u00fcrttemberg",
    "wof:name":"Christiane Debacher",
    "wof:placetype":"venue"
},
  "geometry": {"coordinates":[7.7749419212,48.2791976929],"type":"Point"}
}