{
  "type": "Feature",
  "properties": {
    "iso:country":"DE",
    "sg:address":"Johannisstr. 45",
    "sg:city":"Herford",
    "sg:phone":"+49 5221/55603",
    "sg:postcode":"32052",
    "sg:province":"Nordrhein-Westfalen",
    "wof:name":"Restaurant Altstadt",
    "wof:placetype":"venue"
},
  "geometry": {"coordinates":[8.6733980179,52.1130485535],"type":"Point"}
}