{
  "type": "Feature",
  "properties": {
    "iso:country":"DE",
    "sg:address":"Weddingstr. 38a",
    "sg:city":"Sassnitz",
    "sg:phone":"+49 38392/35291",
    "sg:postcode":"18546",
    "sg:province":"Mecklenburg-Vorpommern",
    "wof:name":"Hoffmann",
    "wof:placetype":"venue"
},
  "geometry": {"coordinates":[13.6634197235,54.5210266113],"type":"Point"}
}