{
  "type": "Feature",
  "properties": {
    "iso:country":"DE",
    "sg:address":"D\u00fcppenb\u00e4ckerweg 30",
    "sg:city":"M\u00fclheim",
    "sg:phone":"+49 208/422505",
    "sg:postcode":"45481",
    "sg:province":"Nordrhein-Westfalen",
    "wof:name":"Uwe Und Helmut Beierlorzer Ingenieure",
    "wof:placetype":"venue"
},
  "geometry": {"coordinates":[6.8600077629,51.4093894958],"type":"Point"}
}