{
  "type": "Feature",
  "properties": {
    "iso:country":"DE",
    "sg:address":"Am Wollhaus 14",
    "sg:city":"Heilbronn",
    "sg:postcode":"74072",
    "sg:province":"Baden-W\u00fcrttemberg",
    "wof:name":"Sparkassenbeteiligungsges. Heilbronn-franken Mbh & Co. Kg",
    "wof:placetype":"venue"
},
  "geometry": {"coordinates":[9.221268,49.139019],"type":"Point"}
}