{
  "type": "Feature",
  "properties": {
    "iso:country":"DE",
    "sg:address":"Luxemburger Str. 4",
    "sg:city":"Trier",
    "sg:phone":"+49 651/89969",
    "sg:postcode":"54294",
    "sg:province":"Rheinland-Pfalz",
    "wof:name":"Horst Langen",
    "wof:placetype":"venue"
},
  "geometry": {"coordinates":[6.6241660118,49.7508964539],"type":"Point"}
}