{
  "type": "Feature",
  "properties": {
    "iso:country":"DE",
    "sg:address":"Karl-Arnold-Str. 8",
    "sg:city":"Osnabr\u00fcck",
    "sg:phone":"+49 541/127706",
    "sg:postcode":"49090",
    "sg:province":"Niedersachsen",
    "wof:name":"Barbara Koch",
    "wof:placetype":"venue"
},
  "geometry": {"coordinates":[7.992456913,52.2926521301],"type":"Point"}
}