{
  "type": "Feature",
  "properties": {
    "iso:country":"DE",
    "sg:address":"Carl-Diem-Str. 10",
    "sg:city":"Reutlingen",
    "sg:phone":"+49 7121/330702",
    "sg:postcode":"72760",
    "sg:province":"Baden-W\u00fcrttemberg",
    "wof:name":"Minimal Handelsmarkt Gmbh",
    "wof:placetype":"venue"
},
  "geometry": {"coordinates":[9.2067480087,48.5064201355],"type":"Point"}
}