{
  "type": "Feature",
  "properties": {
    "iso:country":"DE",
    "sg:address":"Schellenberg",
    "sg:city":"Ottobeuren",
    "sg:postcode":"87724",
    "sg:province":"Bayern",
    "wof:name":"G\u00fcnther Pscheidl",
    "wof:placetype":"venue"
},
  "geometry": {"coordinates":[10.2982654572,47.9215965271],"type":"Point"}
}