{
  "type": "Feature",
  "properties": {
    "iso:country":"DE",
    "sg:address":"Mittelhegge 11",
    "sg:city":"Rheda-Wiedenbr\u00fcck",
    "sg:phone":"+49 5242/93010",
    "sg:postcode":"33378",
    "sg:province":"Nordrhein-Westfalen",
    "wof:name":"Flora Westfalia-fgs- F\u00f6rdergesellschaft Wirtschaft",
    "wof:placetype":"venue"
},
  "geometry": {"coordinates":[8.299315,51.843281],"type":"Point"}
}