{
  "type": "Feature",
  "properties": {
    "iso:country":"DE",
    "sg:address":"Hauptstra\u00dfe 102",
    "sg:city":"Lengenfeld/Stein",
    "sg:phone":"+49 36027",
    "sg:postcode":"99976",
    "sg:province":"Th\u00fcringen",
    "wof:name":"Design-, Schreib- Und Dienstleistungs - Service Hildebrand",
    "wof:placetype":"venue"
},
  "geometry": {"coordinates":[10.227772,51.212898],"type":"Point"}
}