{
  "type": "Feature",
  "properties": {
    "iso:country":"DE",
    "sg:address":"An der Hochheimer Str. 2",
    "sg:city":"Wiesbaden",
    "sg:phone":"+49 611/731843",
    "sg:postcode":"65205",
    "sg:province":"Hessen",
    "wof:name":"Heinz Michael Emmel",
    "wof:placetype":"venue"
},
  "geometry": {"coordinates":[8.33928,50.042374],"type":"Point"}
}