{
  "type": "Feature",
  "properties": {
    "iso:country":"DE",
    "sg:address":"Hahler Str. 28",
    "sg:city":"Minden",
    "sg:phone":"+49 571/28484",
    "sg:postcode":"32427",
    "sg:province":"Nordrhein-Westfalen",
    "wof:name":"Reinhold Wiegers Gmbh",
    "wof:placetype":"venue"
},
  "geometry": {"coordinates":[8.9087018967,52.2929916382],"type":"Point"}
}