{
  "type": "Feature",
  "properties": {
    "iso:country":"DE",
    "sg:address":"Breslauer Str. 8",
    "sg:city":"Leipzig",
    "sg:phone":"+49 341/8629015",
    "sg:postcode":"04299",
    "sg:province":"Sachsen",
    "wof:name":"Eckehardt Lehmann",
    "wof:placetype":"venue"
},
  "geometry": {"coordinates":[12.4144897461,51.3234786987],"type":"Point"}
}