{
  "type": "Feature",
  "properties": {
    "iso:country":"DE",
    "sg:address":"Obere Bachstr. 10",
    "sg:city":"Moos",
    "sg:phone":"+49 9938/1045",
    "sg:postcode":"94554",
    "sg:province":"Bayern",
    "wof:name":"Franz Schmatz",
    "wof:placetype":"venue"
},
  "geometry": {"coordinates":[12.96384,48.737751],"type":"Point"}
}