{
  "type": "Feature",
  "properties": {
    "iso:country":"DE",
    "sg:address":"Wagnerstr. 7",
    "sg:city":"Neuhof",
    "sg:phone":"+49 6655/918656",
    "sg:postcode":"36119",
    "sg:province":"Hessen",
    "wof:name":"F. G\u00f6rlich",
    "wof:placetype":"venue"
},
  "geometry": {"coordinates":[9.603458,50.454098],"type":"Point"}
}