{
  "type": "Feature",
  "properties": {
    "iso:country":"DE",
    "sg:address":"Willy-Brandt-Platz 4",
    "sg:city":"Oberhausen",
    "sg:phone":"+49 208/850750",
    "sg:postcode":"46045",
    "sg:province":"Nordrhein-Westfalen",
    "wof:name":"Oberhausener Reiseb\u00fcro Gmbh",
    "wof:placetype":"venue"
},
  "geometry": {"coordinates":[6.8544020653,51.4738311768],"type":"Point"}
}