{
  "type": "Feature",
  "properties": {
    "iso:country":"DE",
    "sg:address":"Holbeinweg 8",
    "sg:city":"Marktredwitz",
    "sg:phone":"+49 9231/81850",
    "sg:postcode":"95615",
    "sg:province":"Bayern",
    "wof:name":"Wolfgang F\u00fcrst Steuerberater",
    "wof:placetype":"venue"
},
  "geometry": {"coordinates":[12.072303772,50.0082168579],"type":"Point"}
}