{
  "type": "Feature",
  "properties": {
    "iso:country":"DE",
    "sg:address":"Erikastr. 178",
    "sg:city":"Hamburg",
    "sg:phone":"+49 40/488742",
    "sg:postcode":"20251",
    "sg:province":"Hamburg",
    "wof:name":"Residenz Grundst\u00fccks Gmbh",
    "wof:placetype":"venue"
},
  "geometry": {"coordinates":[9.9857263565,53.5997276306],"type":"Point"}
}