{
  "type": "Feature",
  "properties": {
    "iso:country":"DE",
    "sg:address":"Waltringer Weg 46",
    "sg:city":"Werl",
    "sg:phone":"+49 2922/865766",
    "sg:postcode":"59457",
    "sg:province":"Nordrhein-Westfalen",
    "wof:name":"Heinzelm\u00e4nnchen Gmbh",
    "wof:placetype":"venue"
},
  "geometry": {"coordinates":[7.916871,51.542557],"type":"Point"}
}