{
  "type": "Feature",
  "properties": {
    "iso:country":"DE",
    "sg:address":"Bamberger Str. 20",
    "sg:city":"Lichtenfels",
    "sg:phone":"+49 9571/14418",
    "sg:postcode":"96215",
    "sg:province":"Bayern",
    "wof:name":"Deutsche Post Ag",
    "wof:placetype":"venue"
},
  "geometry": {"coordinates":[11.0627317429,50.1459007263],"type":"Point"}
}