{
  "type": "Feature",
  "properties": {
    "iso:country":"DE",
    "sg:address":"Frohnlacher Str. 48",
    "sg:city":"Ebersdorf",
    "sg:phone":"+49 9562/1201",
    "sg:postcode":"96237",
    "sg:province":"Bayern",
    "wof:name":"Max Fischer",
    "wof:placetype":"venue"
},
  "geometry": {"coordinates":[11.0803289413,50.2173042297],"type":"Point"}
}