{
  "type": "Feature",
  "properties": {
    "iso:country":"DE",
    "sg:address":"Zum Knappsberg 5",
    "sg:city":"Steyerberg",
    "sg:phone":"+49 5764/96150",
    "sg:postcode":"31595",
    "sg:province":"Niedersachsen",
    "wof:name":"Hbt-holzhandel Gmbh",
    "wof:placetype":"venue"
},
  "geometry": {"coordinates":[9.0177717209,52.5725517273],"type":"Point"}
}