{
  "type": "Feature",
  "properties": {
    "iso:country":"DE",
    "sg:address":"Kapellstr. 12",
    "sg:city":"Donauw\u00f6rth",
    "sg:phone":"+49 906/22640",
    "sg:postcode":"86609",
    "sg:province":"Bayern",
    "wof:name":"J. A. Straulino Kg",
    "wof:placetype":"venue"
},
  "geometry": {"coordinates":[10.7816781998,48.7173461914],"type":"Point"}
}