{
  "type": "Feature",
  "properties": {
    "iso:country":"DE",
    "sg:address":"Hasberger Str. 13",
    "sg:city":"Kirchheim",
    "sg:phone":"+49 8266/2990",
    "sg:postcode":"87757",
    "sg:province":"Bayern",
    "wof:name":"Wanzl Gmbh",
    "wof:placetype":"venue"
},
  "geometry": {"coordinates":[10.463889,48.171944],"type":"Point"}
}