{
  "type": "Feature",
  "properties": {
    "iso:country":"DE",
    "sg:address":"Riederweg 5",
    "sg:city":"Weil am Rhein",
    "sg:phone":"+49 7621/64898",
    "sg:postcode":"79576",
    "sg:province":"Baden-W\u00fcrttemberg",
    "wof:name":"Reiterst\u00fcble",
    "wof:placetype":"venue"
},
  "geometry": {"coordinates":[7.5891108513,47.6189422607],"type":"Point"}
}