{
  "type": "Feature",
  "properties": {
    "iso:country":"DE",
    "sg:city":"W\u00f6rnitz",
    "sg:phone":"+49 9868/5041",
    "sg:postcode":"91637",
    "sg:province":"Bayern",
    "wof:name":"Autohof W\u00f6rnitz Gmbh & Co. Kg",
    "wof:placetype":"venue"
},
  "geometry": {"coordinates":[10.24396,49.25494],"type":"Point"}
}