{
  "type": "Feature",
  "properties": {
    "iso:country":"DE",
    "sg:address":"Niedersachsenstr. 27a-c",
    "sg:city":"Langenhagen",
    "sg:phone":"+49 511/725530",
    "sg:postcode":"30853",
    "sg:province":"Niedersachsen",
    "wof:name":"Raphael Kierey Gmbh",
    "wof:placetype":"venue"
},
  "geometry": {"coordinates":[9.73983,52.440605],"type":"Point"}
}