{
  "type": "Feature",
  "properties": {
    "iso:country":"DE",
    "sg:address":"Stefan-George-Weg 8",
    "sg:city":"Darmstadt",
    "sg:phone":"+49 6151/604010",
    "sg:postcode":"64285",
    "sg:province":"Hessen",
    "wof:name":"Helmut Dirigo Steuerberater",
    "wof:placetype":"venue"
},
  "geometry": {"coordinates":[8.6574401855,49.8559265137],"type":"Point"}
}