{
  "type": "Feature",
  "properties": {
    "iso:country":"DE",
    "sg:address":"Neuenlander Str. 13-15",
    "sg:city":"Bremen",
    "sg:phone":"+49 421/416327",
    "sg:postcode":"28199",
    "sg:province":"Bremen",
    "wof:name":"Trendwende Handel Mit Naturstoffen Gmbh",
    "wof:placetype":"venue"
},
  "geometry": {"coordinates":[8.781238,53.067375],"type":"Point"}
}