{
  "type": "Feature",
  "properties": {
    "iso:country":"DE",
    "sg:address":"Endestr. 21",
    "sg:city":"Berlin",
    "sg:phone":"+49 30/8053777",
    "sg:postcode":"14109",
    "sg:province":"Berlin",
    "wof:name":"Colloquim Verlag Otto H. Hess Gmbh",
    "wof:placetype":"venue"
},
  "geometry": {"coordinates":[13.159213,52.421791],"type":"Point"}
}