{
  "type": "Feature",
  "properties": {
    "iso:country":"DE",
    "sg:address":"Bauernwald 1",
    "sg:city":"Sulz",
    "sg:phone":"+49 7454/3094",
    "sg:postcode":"72172",
    "sg:province":"Baden-W\u00fcrttemberg",
    "wof:name":"Maschinen- Und Betriebs- Hilfsring E. V.",
    "wof:placetype":"venue"
},
  "geometry": {"coordinates":[8.6704244614,48.3687362671],"type":"Point"}
}