{
  "type": "Feature",
  "properties": {
    "iso:country":"DE",
    "sg:address":"Am Anger 3::",
    "sg:city":"Seebruck",
    "sg:phone":"+49 8667/7171",
    "sg:postcode":"83358",
    "sg:province":"Bayern",
    "wof:name":"Raiffeisenbank Chiemgau-nord-obing Eg",
    "wof:placetype":"venue"
},
  "geometry": {"coordinates":[12.474137,47.934559],"type":"Point"}
}