{
  "type": "Feature",
  "properties": {
    "iso:country":"DE",
    "sg:address":"Lindenufer 56",
    "sg:city":"Schwerte",
    "sg:phone":"+49 2304/72544",
    "sg:postcode":"58239",
    "sg:province":"Nordrhein-Westfalen",
    "wof:name":"Veronika Stock",
    "wof:placetype":"venue"
},
  "geometry": {"coordinates":[7.5684890747,51.418712616],"type":"Point"}
}