{
  "type": "Feature",
  "properties": {
    "iso:country":"DE",
    "sg:address":"Pl\u00fcschowstr. 8",
    "sg:city":"Kassel",
    "sg:phone":"+49 561/2888361",
    "sg:postcode":"34121",
    "sg:province":"Hessen",
    "wof:name":"Wilfried Asshoff Rechtsanwalt",
    "wof:placetype":"venue"
},
  "geometry": {"coordinates":[9.4710435867,51.302192688],"type":"Point"}
}