{
  "type": "Feature",
  "properties": {
    "iso:country":"DE",
    "sg:address":"Ulrich-von-Hutten-Str. 80",
    "sg:city":"Korntal-M\u00fcnchingen",
    "sg:postcode":"70825",
    "sg:province":"Baden-W\u00fcrttemberg",
    "wof:name":"Optiluv E. K.",
    "wof:placetype":"venue"
},
  "geometry": {"coordinates":[9.125268,48.835461],"type":"Point"}
}