{
  "type": "Feature",
  "properties": {
    "iso:country":"DE",
    "sg:address":"Georg-Schwarz-Str. 166",
    "sg:city":"Leipzig",
    "sg:phone":"+49 341/4410675",
    "sg:postcode":"04179",
    "sg:province":"Sachsen",
    "wof:name":"I. P\u00f6tzsch",
    "wof:placetype":"venue"
},
  "geometry": {"coordinates":[12.310389,51.349426],"type":"Point"}
}