{
  "type": "Feature",
  "properties": {
    "iso:country":"DE",
    "sg:address":"Waldensberger Str. 6",
    "sg:city":"W\u00e4chtersbach",
    "sg:phone":"+49 6053/5506",
    "sg:postcode":"63607",
    "sg:province":"Hessen",
    "wof:name":"Brm Brunnensanierung - Rhein-main-bodensee Gmbh",
    "wof:placetype":"venue"
},
  "geometry": {"coordinates":[9.264989,50.2803],"type":"Point"}
}