{
  "type": "Feature",
  "properties": {
    "iso:country":"DE",
    "sg:address":"Weinberg 5",
    "sg:city":"Obersontheim",
    "sg:phone":"+49 7973/96060",
    "sg:postcode":"74423",
    "sg:province":"Baden-W\u00fcrttemberg",
    "wof:name":"Beton R\u00f6ser Siegfried R\u00f6ser Kg",
    "wof:placetype":"venue"
},
  "geometry": {"coordinates":[9.863539,49.044785],"type":"Point"}
}