{
  "type": "Feature",
  "properties": {
    "iso:country":"DE",
    "sg:address":"Riedstr. 87",
    "sg:city":"Frankfurt",
    "sg:postcode":"60388",
    "sg:province":"Hessen",
    "wof:name":"Timbox International Gmbh Herstellung Und Vertrieb Von",
    "wof:placetype":"venue"
},
  "geometry": {"coordinates":[8.7607660294,50.1509132385],"type":"Point"}
}