{
  "type": "Feature",
  "properties": {
    "iso:country":"DE",
    "sg:address":"Kirschenweg 19 a",
    "sg:city":"Lindenfels",
    "sg:phone":"+49 6255/1069",
    "sg:postcode":"64678",
    "sg:province":"Hessen",
    "wof:name":"H. Spannhaus",
    "wof:placetype":"venue"
},
  "geometry": {"coordinates":[8.78309,49.690891],"type":"Point"}
}