{
  "type": "Feature",
  "properties": {
    "iso:country":"DE",
    "sg:address":"Juri-Gagarin-Str.",
    "sg:city":"F\u00fcrstenwalde",
    "sg:phone":"+49 3361/32114",
    "sg:postcode":"15517",
    "sg:province":"Brandenburg",
    "wof:name":"Saf Schrottaufbereitung Gmbh",
    "wof:placetype":"venue"
},
  "geometry": {"coordinates":[14.076905,52.375919],"type":"Point"}
}