{
  "type": "Feature",
  "properties": {
    "iso:country":"DE",
    "sg:address":"Konrad-Adenauer-Str. 37",
    "sg:city":"Geilenkirchen",
    "sg:phone":"+49 2451/2808",
    "sg:postcode":"52511",
    "sg:province":"Nordrhein-Westfalen",
    "wof:name":"Uwe Eggert",
    "wof:placetype":"venue"
},
  "geometry": {"coordinates":[6.128265,50.962898],"type":"Point"}
}