{
  "type": "Feature",
  "properties": {
    "iso:country":"DE",
    "sg:address":"Hauptstr. 40",
    "sg:city":"Much",
    "sg:phone":"+49 2245/912563",
    "sg:postcode":"53804",
    "sg:province":"Nordrhein-Westfalen",
    "wof:name":"Provinzial Versicherungen",
    "wof:placetype":"venue"
},
  "geometry": {"coordinates":[7.4046578407,50.9053039551],"type":"Point"}
}