{
  "type": "Feature",
  "properties": {
    "iso:country":"DE",
    "sg:address":"Leopold-von-Ranke-Str. 56",
    "sg:city":"Wiehe",
    "sg:phone":"+49 34672/83754",
    "sg:postcode":"06571",
    "sg:province":"Th\u00fcringen",
    "wof:name":"Panorama M\u00f6bel",
    "wof:placetype":"venue"
},
  "geometry": {"coordinates":[11.403906,51.298229],"type":"Point"}
}