{
  "type": "Feature",
  "properties": {
    "iso:country":"DE",
    "sg:address":"Graseckstr. 39",
    "sg:city":"Kochel",
    "sg:postcode":"82431",
    "sg:province":"Bayern",
    "wof:name":"Lamaqq Gmbh",
    "wof:placetype":"venue"
},
  "geometry": {"coordinates":[11.3628978729,47.6511993408],"type":"Point"}
}