{
  "type": "Feature",
  "properties": {
    "iso:country":"DE",
    "sg:address":"Am Schrebergarten 22",
    "sg:city":"Thum-Jahnsbach",
    "sg:phone":"+49 37297/89706",
    "sg:postcode":"09419",
    "sg:province":"Sachsen",
    "wof:name":"U. Sch\u00e4ffner",
    "wof:placetype":"venue"
},
  "geometry": {"coordinates":[12.9143400192,50.6675643921],"type":"Point"}
}