{
  "type": "Feature",
  "properties": {
    "iso:country":"DE",
    "sg:address":"Wolburgsweg 24 c",
    "sg:city":"Berlin",
    "sg:phone":"+49 30/3731914",
    "sg:postcode":"13589",
    "sg:province":"Berlin",
    "wof:name":"Hermann Steinhaus Ingenieur",
    "wof:placetype":"venue"
},
  "geometry": {"coordinates":[13.1689586639,52.5532913208],"type":"Point"}
}