{
  "type": "Feature",
  "properties": {
    "iso:country":"DE",
    "sg:address":"Chemnitzer Str. 33",
    "sg:city":"Penig",
    "sg:phone":"+49 37381/5328",
    "sg:postcode":"09322",
    "sg:province":"Sachsen",
    "wof:name":"Karin Swirbul",
    "wof:placetype":"venue"
},
  "geometry": {"coordinates":[12.705951,50.930897],"type":"Point"}
}