{
  "type": "Feature",
  "properties": {
    "iso:country":"DE",
    "sg:address":"Gleitsmannstr. 10",
    "sg:city":"Leipzig",
    "sg:phone":"+49 341/4250001",
    "sg:postcode":"04249",
    "sg:province":"Sachsen",
    "wof:name":"Ina J\u00fcschke",
    "wof:placetype":"venue"
},
  "geometry": {"coordinates":[12.310446,51.278309],"type":"Point"}
}