{
  "type": "Feature",
  "properties": {
    "iso:country":"DE",
    "sg:address":"Im Mohnfeld 1",
    "sg:city":"Rheinm\u00fcnster",
    "sg:phone":"+49 7227/2770",
    "sg:postcode":"77836",
    "sg:province":"Baden-W\u00fcrttemberg",
    "wof:name":"Wilfried Gro\u00dfer Gmbh",
    "wof:placetype":"venue"
},
  "geometry": {"coordinates":[8.058339119,48.7762947083],"type":"Point"}
}