{
  "type": "Feature",
  "properties": {
    "iso:country":"DE",
    "sg:address":"Schlachthofstr. 19-21",
    "sg:city":"Koblenz",
    "sg:phone":"+49 261/43051",
    "sg:postcode":"56073",
    "sg:province":"Rheinland-Pfalz",
    "wof:name":"Fliesen-b\u00e4der Heinrich Hermannn",
    "wof:placetype":"venue"
},
  "geometry": {"coordinates":[7.5836992264,50.363494873],"type":"Point"}
}