{
  "type": "Feature",
  "properties": {
    "iso:country":"DE",
    "sg:address":"Nagelgasse 11",
    "sg:city":"Neuwied",
    "sg:phone":"+49 2631/83720",
    "sg:postcode":"56564",
    "sg:province":"Rheinland-Pfalz",
    "wof:name":"Schell Gmbh",
    "wof:placetype":"venue"
},
  "geometry": {"coordinates":[7.4713320732,50.4407806396],"type":"Point"}
}