{
  "type": "Feature",
  "properties": {
    "iso:country":"DE",
    "sg:address":"Erdinger Str. 26",
    "sg:city":"Eitting",
    "sg:phone":"+49 8122/3418",
    "sg:postcode":"85462",
    "sg:province":"Bayern",
    "wof:name":"Anton Anzinger",
    "wof:placetype":"venue"
},
  "geometry": {"coordinates":[11.8942918777,48.3582420349],"type":"Point"}
}