{
  "type": "Feature",
  "properties": {
    "iso:country":"DE",
    "sg:address":"Rudolf-Breitscheid-Siedlung",
    "sg:city":"Lawalde",
    "sg:phone":"+49 3585/402148",
    "sg:postcode":"02708",
    "sg:province":"Sachsen",
    "wof:name":"Hannelore Kasper",
    "wof:placetype":"venue"
},
  "geometry": {"coordinates":[14.6011962891,51.0799255371],"type":"Point"}
}