{
  "type": "Feature",
  "properties": {
    "iso:country":"DE",
    "sg:address":"Klausenberg 2",
    "sg:city":"Laupheim",
    "sg:phone":"+49 7392/2450",
    "sg:postcode":"88471",
    "sg:province":"Baden-W\u00fcrttemberg",
    "wof:name":"E. Sauter",
    "wof:placetype":"venue"
},
  "geometry": {"coordinates":[9.869082,48.227913],"type":"Point"}
}