{
  "type": "Feature",
  "properties": {
    "iso:country":"DE",
    "sg:address":"Stadtgraben 20",
    "sg:city":"Landau",
    "sg:phone":"+49 9951/9550",
    "sg:postcode":"94405",
    "sg:province":"Bayern",
    "wof:name":"Stadwerke Landau A. D. Isar",
    "wof:placetype":"venue"
},
  "geometry": {"coordinates":[12.694079,48.669323],"type":"Point"}
}