{
  "type": "Feature",
  "properties": {
    "iso:country":"DE",
    "sg:address":"Heinrich-Heine-Str 12",
    "sg:city":"Borsdorf",
    "sg:phone":"+49 34291/86500",
    "sg:postcode":"04451",
    "sg:province":"Sachsen",
    "wof:name":"Dr. Olaf Schr\u00f6der",
    "wof:placetype":"venue"
},
  "geometry": {"coordinates":[12.5411682129,51.3443756104],"type":"Point"}
}