{
  "type": "Feature",
  "properties": {
    "iso:country":"DE",
    "sg:address":"Liebigstr. 10",
    "sg:city":"Leonberg",
    "sg:phone":"+49 7152/902944",
    "sg:postcode":"71229",
    "sg:province":"Baden-W\u00fcrttemberg",
    "wof:name":"Teppich Seifferth Christel Seifferth",
    "wof:placetype":"venue"
},
  "geometry": {"coordinates":[9.0295696259,48.8177680969],"type":"Point"}
}