{
  "type": "Feature",
  "properties": {
    "iso:country":"DE",
    "sg:address":"H\u00f6feweg 58",
    "sg:city":"Bielefeld",
    "sg:postcode":"33619",
    "sg:province":"Nordrhein-Westfalen",
    "wof:name":"Dornberg Auto Handelsgesellschaft",
    "wof:placetype":"venue"
},
  "geometry": {"coordinates":[8.466542244,52.0535049438],"type":"Point"}
}