{
  "type": "Feature",
  "properties": {
    "iso:country":"DE",
    "sg:address":"S\u00fcdstr. 17",
    "sg:city":"Delbr\u00fcck",
    "sg:phone":"+49 5250/53375",
    "sg:postcode":"33129",
    "sg:province":"Nordrhein-Westfalen",
    "wof:name":"Heinz Grundmeier",
    "wof:placetype":"venue"
},
  "geometry": {"coordinates":[8.564319,51.761028],"type":"Point"}
}