{
  "type": "Feature",
  "properties": {
    "iso:country":"DE",
    "sg:address":"Schlehenweg 21",
    "sg:city":"Niedereschach",
    "sg:phone":"+49 7728/464",
    "sg:postcode":"78078",
    "sg:province":"Baden-W\u00fcrttemberg",
    "wof:name":"K. D\u00f6llgast Edv-beratungs-gmbh",
    "wof:placetype":"venue"
},
  "geometry": {"coordinates":[8.5341434479,48.1294059753],"type":"Point"}
}