{
  "type": "Feature",
  "properties": {
    "iso:country":"DE",
    "sg:address":"Mittelstr. 4",
    "sg:city":"Bersenbr\u00fcck",
    "sg:phone":"+49 5439/2458",
    "sg:postcode":"49593",
    "sg:province":"Niedersachsen",
    "wof:name":"Heinrich Grewing",
    "wof:placetype":"venue"
},
  "geometry": {"coordinates":[7.943676,52.553806],"type":"Point"}
}