{
  "type": "Feature",
  "properties": {
    "iso:country":"DE",
    "sg:city":"Remagen",
    "sg:phone":"+49 2642/1417",
    "sg:postcode":"53424",
    "sg:province":"Rheinland-Pfalz",
    "wof:name":"Juliane Damenmode Gmbh",
    "wof:placetype":"venue"
},
  "geometry": {"coordinates":[7.225296,50.579334],"type":"Point"}
}