{
  "type": "Feature",
  "properties": {
    "iso:country":"DE",
    "sg:address":"R\u00f6merweg 6",
    "sg:city":"Sch\u00f6mberg",
    "sg:postcode":"75328",
    "sg:province":"Baden-W\u00fcrttemberg",
    "wof:name":"Zs Elektrotechnik Gmbh",
    "wof:placetype":"venue"
},
  "geometry": {"coordinates":[8.6479387283,48.7912635803],"type":"Point"}
}