{
  "type": "Feature",
  "properties": {
    "iso:country":"DE",
    "sg:address":"Ramskamp 49",
    "sg:city":"Elmshorn",
    "sg:postcode":"25337",
    "sg:province":"Schleswig-Holstein",
    "wof:name":"Edicom Warenhandels- Und Vermietungsgesellschaft Mbh",
    "wof:placetype":"venue"
},
  "geometry": {"coordinates":[9.6904754639,53.7419509888],"type":"Point"}
}