{
  "type": "Feature",
  "properties": {
    "iso:country":"DE",
    "sg:address":"Keltenring 6",
    "sg:city":"St. Wendel",
    "sg:phone":"+49 6851/3868",
    "sg:postcode":"66606",
    "sg:province":"Saarland",
    "wof:name":"Berg-und H\u00fcttenarbeiterverein Winterbach",
    "wof:placetype":"venue"
},
  "geometry": {"coordinates":[7.0974478722,49.4780082703],"type":"Point"}
}