{
  "type": "Feature",
  "properties": {
    "iso:country":"DE",
    "sg:address":"Brunnenstr. 10",
    "sg:city":"Obernheim",
    "sg:phone":"+49 7436/1668",
    "sg:postcode":"72364",
    "sg:province":"Baden-W\u00fcrttemberg",
    "wof:name":"Karosseriebau Essigbeck Gmbh",
    "wof:placetype":"venue"
},
  "geometry": {"coordinates":[8.863475,48.163467],"type":"Point"}
}