{
  "type": "Feature",
  "properties": {
    "iso:country":"DE",
    "sg:address":"Kernerplatz 10",
    "sg:city":"Stuttgart",
    "sg:phone":"+49 4907/111260",
    "sg:postcode":"70182",
    "sg:province":"Baden-W\u00fcrttemberg",
    "wof:name":"Ministerium F\u00fcr Ern\u00e4hrung Und L\u00e4ndlichen Raum Baden-w\u00fcrttemb",
    "wof:placetype":"venue"
},
  "geometry": {"coordinates":[9.1894989014,48.7834625244],"type":"Point"}
}