{
  "type": "Feature",
  "properties": {
    "iso:country":"DE",
    "sg:address":"Hauptstra\u00dfe 10",
    "sg:city":"Arnsdorf/Dresden",
    "sg:phone":"+49 35200",
    "sg:postcode":"01475",
    "wof:name":"Raumausstattung Schwarzmeier",
    "wof:placetype":"venue"
},
  "geometry": {"coordinates":[13.9861001968,51.0942611694],"type":"Point"}
}