{
  "type": "Feature",
  "properties": {
    "iso:country":"DE",
    "sg:address":"Bahnhofsplatz 3 A",
    "sg:city":"Bremen",
    "sg:phone":"+49 421/13345",
    "sg:postcode":"28195",
    "sg:province":"Bremen",
    "wof:name":"Seelke",
    "wof:placetype":"venue"
},
  "geometry": {"coordinates":[8.810933,53.080448],"type":"Point"}
}