{
  "type": "Feature",
  "properties": {
    "iso:country":"DE",
    "sg:address":"L\u00fcerweg 28",
    "sg:city":"Willingen",
    "sg:phone":"+49 5632/968045",
    "sg:postcode":"34508",
    "sg:province":"Hessen",
    "wof:name":"U. Donath",
    "wof:placetype":"venue"
},
  "geometry": {"coordinates":[8.630865,51.306633],"type":"Point"}
}