{
  "type": "Feature",
  "properties": {
    "iso:country":"DE",
    "sg:address":"Alzeyer Str. 60",
    "sg:city":"Worms",
    "sg:phone":"+49 6241/594500",
    "sg:postcode":"67549",
    "sg:province":"Rheinland-Pfalz",
    "wof:name":"Neukauf",
    "wof:placetype":"venue"
},
  "geometry": {"coordinates":[8.3466463089,49.6319274902],"type":"Point"}
}