{
  "type": "Feature",
  "properties": {
    "iso:country":"DE",
    "sg:address":"Hubertstr. 223",
    "sg:city":"Essen",
    "sg:postcode":"45307",
    "sg:province":"Nordrhein-Westfalen",
    "wof:name":"Osa Verpackungs- Gmbh",
    "wof:placetype":"venue"
},
  "geometry": {"coordinates":[7.069304,51.467587],"type":"Point"}
}