{
  "type": "Feature",
  "properties": {
    "iso:country":"DE",
    "sg:address":"Eschenstr. 6",
    "sg:city":"Ismaning",
    "sg:phone":"+49 89/96202386",
    "sg:postcode":"85737",
    "sg:province":"Bayern",
    "wof:name":"G & F Wohnbau Gmbh",
    "wof:placetype":"venue"
},
  "geometry": {"coordinates":[11.671601,48.229485],"type":"Point"}
}