{
  "type": "Feature",
  "properties": {
    "iso:country":"DE",
    "sg:address":"Fontaneallee 34",
    "sg:city":"Wildau",
    "sg:phone":"+49 3375/56530",
    "sg:postcode":"15745",
    "sg:province":"Brandenburg",
    "wof:name":"Classic Fertighaus-handel Ag",
    "wof:placetype":"venue"
},
  "geometry": {"coordinates":[13.638528,52.333347],"type":"Point"}
}