{
  "type": "Feature",
  "properties": {
    "iso:country":"DE",
    "sg:address":"Bernbacher Str. 9",
    "sg:city":"Freigericht",
    "sg:phone":"+49 6055/81630",
    "sg:postcode":"63579",
    "sg:province":"Hessen",
    "wof:name":"The Grill Company Gmbh",
    "wof:placetype":"venue"
},
  "geometry": {"coordinates":[9.1435270309,50.1469993591],"type":"Point"}
}