{
  "type": "Feature",
  "properties": {
    "iso:country":"DE",
    "sg:address":"Kirchplatz 7",
    "sg:city":"Alsfeld",
    "sg:phone":"+49 6631/3598",
    "sg:postcode":"36304",
    "sg:province":"Hessen",
    "wof:name":"H.-w. Popp",
    "wof:placetype":"venue"
},
  "geometry": {"coordinates":[9.271449,50.751701],"type":"Point"}
}