{
  "type": "Feature",
  "properties": {
    "iso:country":"DE",
    "sg:address":"An der Trift 31",
    "sg:city":"Neustrelitz",
    "sg:phone":"+49 3981/445296",
    "sg:postcode":"17235",
    "sg:province":"Mecklenburg-Vorpommern",
    "wof:name":"Georg Begert",
    "wof:placetype":"venue"
},
  "geometry": {"coordinates":[13.070043,53.335793],"type":"Point"}
}