{
  "type": "Feature",
  "properties": {
    "iso:country":"DE",
    "sg:address":"Schlo\u00dfbergstr. 35",
    "sg:city":"Sulz",
    "sg:postcode":"72172",
    "sg:province":"Baden-W\u00fcrttemberg",
    "wof:name":"Kath. \u00f6ffentliche B\u00fccherei Der Pfarrgemeinde Fischingen",
    "wof:placetype":"venue"
},
  "geometry": {"coordinates":[8.677146,48.389759],"type":"Point"}
}