{
  "type": "Feature",
  "properties": {
    "iso:country":"DE",
    "sg:address":"Alfred-Paulsen-Str 8",
    "sg:city":"Otterndorf",
    "sg:phone":"+49 4751/915791",
    "sg:postcode":"21762",
    "sg:province":"Niedersachsen",
    "wof:name":"Marschland Naturkost Gmbh",
    "wof:placetype":"venue"
},
  "geometry": {"coordinates":[8.8960056305,53.8113479614],"type":"Point"}
}