{
  "type": "Feature",
  "properties": {
    "iso:country":"DE",
    "sg:address":"\u00d6lm\u00fchlweg 35c",
    "sg:city":"K\u00f6nigstein",
    "sg:phone":"+49 6174/4835",
    "sg:postcode":"61462",
    "sg:province":"Hessen",
    "wof:name":"Fema Gesellschaft F\u00fcr Vertrieb Und Vermietung Von",
    "wof:placetype":"venue"
},
  "geometry": {"coordinates":[8.4533185959,50.18724823],"type":"Point"}
}