{
  "type": "Feature",
  "properties": {
    "iso:country":"DE",
    "sg:address":"Max-Planck-Str. 110",
    "sg:city":"Neustadt",
    "sg:phone":"+49 5032/2878",
    "sg:postcode":"31535",
    "sg:province":"Niedersachsen",
    "wof:name":"Sander Hebe- Und Sicherheits- Technik Gmbh",
    "wof:placetype":"venue"
},
  "geometry": {"coordinates":[9.524664,52.528793],"type":"Point"}
}