{
  "type": "Feature",
  "properties": {
    "iso:country":"DE",
    "sg:address":"Zusamweg 6",
    "sg:city":"Donauw\u00f6rth",
    "sg:phone":"+49 906/1000",
    "sg:postcode":"86609",
    "sg:province":"Bayern",
    "wof:name":"Bob-logistic & Consulting Gmbh",
    "wof:placetype":"venue"
},
  "geometry": {"coordinates":[10.7821893692,48.7121772766],"type":"Point"}
}