{
  "type": "Feature",
  "properties": {
    "iso:country":"DE",
    "sg:address":"Lindenstr. 7",
    "sg:city":"Tuttlingen",
    "sg:phone":"+49 7461/76794",
    "sg:postcode":"78532",
    "sg:province":"Baden-W\u00fcrttemberg",
    "wof:name":"Franz Sch\u00f6nle Architekt",
    "wof:placetype":"venue"
},
  "geometry": {"coordinates":[8.852148,48.008575],"type":"Point"}
}