{
  "type": "Feature",
  "properties": {
    "iso:country":"DE",
    "sg:address":"Dieselstr. 11-15",
    "sg:city":"Neu-Ulm",
    "sg:phone":"+49 731/966630",
    "sg:postcode":"89231",
    "sg:province":"Bayern",
    "wof:name":"F. Stamm Gmbh",
    "wof:placetype":"venue"
},
  "geometry": {"coordinates":[10.002123,48.383739],"type":"Point"}
}