{
  "type": "Feature",
  "properties": {
    "iso:country":"DE",
    "sg:address":"Bodanstr. 38",
    "sg:city":"Konstanz",
    "sg:phone":"+49 7531/15467",
    "sg:postcode":"78462",
    "sg:province":"Baden-W\u00fcrttemberg",
    "wof:name":"Herodek",
    "wof:placetype":"venue"
},
  "geometry": {"coordinates":[9.1714506149,47.6585540771],"type":"Point"}
}