{
  "type": "Feature",
  "properties": {
    "iso:country":"DE",
    "sg:address":"Holsterhauser Str. 160",
    "sg:city":"Essen",
    "sg:phone":"+49 201/702558",
    "sg:postcode":"45147",
    "sg:province":"Nordrhein-Westfalen",
    "wof:name":"Hugo Laws",
    "wof:placetype":"venue"
},
  "geometry": {"coordinates":[6.9867529869,51.4367599487],"type":"Point"}
}