{
  "type": "Feature",
  "properties": {
    "iso:country":"DE",
    "sg:address":"Authariplatz 15",
    "sg:city":"M\u00fcnchen",
    "sg:phone":"+49 89/647284",
    "sg:postcode":"81545",
    "sg:province":"Bayern",
    "wof:name":"Haus Waldeck Verwaltungsgesellschaft Mbh",
    "wof:placetype":"venue"
},
  "geometry": {"coordinates":[11.5624570847,48.0918464661],"type":"Point"}
}