{
  "type": "Feature",
  "properties": {
    "iso:country":"DE",
    "sg:address":"Bleicherstr. 32",
    "sg:city":"Ravensburg",
    "sg:phone":"+49 751/366860",
    "sg:postcode":"88212",
    "sg:province":"Baden-W\u00fcrttemberg",
    "wof:name":"Siemens-electroger\u00e4te Gmbh",
    "wof:placetype":"venue"
},
  "geometry": {"coordinates":[9.6116914749,47.7927513123],"type":"Point"}
}