{
  "type": "Feature",
  "properties": {
    "iso:country":"DE",
    "sg:address":"Stummstr. 40",
    "sg:city":"Dillingen",
    "sg:postcode":"66763",
    "sg:province":"Saarland",
    "wof:name":"Herresthal Touristik Gmbh Reiseb\u00fcro Ats Reisen",
    "wof:placetype":"venue"
},
  "geometry": {"coordinates":[6.7269868851,49.3534584045],"type":"Point"}
}