{
  "type": "Feature",
  "properties": {
    "iso:country":"DE",
    "sg:address":"Wallstr. 6",
    "sg:city":"Kleinwallstadt",
    "sg:phone":"+49 6022/66240",
    "sg:postcode":"63839",
    "sg:province":"Bayern",
    "wof:name":"St. Emile Josef Reis Gmbh & Co. Kg",
    "wof:placetype":"venue"
},
  "geometry": {"coordinates":[9.1671161652,49.8740348816],"type":"Point"}
}