{
  "type": "Feature",
  "properties": {
    "iso:country":"DE",
    "sg:city":"Leitzkau",
    "sg:phone":"+49 39241/4258",
    "sg:postcode":"39279",
    "sg:province":"Sachsen-Anhalt",
    "wof:name":"E. Schoch",
    "wof:placetype":"venue"
},
  "geometry": {"coordinates":[11.953582,52.056915],"type":"Point"}
}