{
  "type": "Feature",
  "properties": {
    "iso:country":"DE",
    "sg:address":"Gleiwitzer Str. 10",
    "sg:city":"Springe",
    "sg:phone":"+49 5045/6188",
    "sg:postcode":"31832",
    "sg:province":"Niedersachsen",
    "wof:name":"Freibad Bennigsen",
    "wof:placetype":"venue"
},
  "geometry": {"coordinates":[9.6536502838,52.2359352112],"type":"Point"}
}