{
  "type": "Feature",
  "properties": {
    "iso:country":"DE",
    "sg:address":"Knapper Weg 24",
    "sg:city":"Friesoythe",
    "sg:phone":"+49 4491/2788",
    "sg:postcode":"26169",
    "sg:province":"Niedersachsen",
    "wof:name":"Josef Rolfes",
    "wof:placetype":"venue"
},
  "geometry": {"coordinates":[7.822149,53.035397],"type":"Point"}
}