{
  "type": "Feature",
  "properties": {
    "iso:country":"DE",
    "sg:address":"Thomasburger Str. 1",
    "sg:city":"Thomasburg",
    "sg:phone":"+49 5859/699",
    "sg:postcode":"21401",
    "sg:province":"Niedersachsen",
    "wof:name":"Gerhard G\u00f6ttert",
    "wof:placetype":"venue"
},
  "geometry": {"coordinates":[10.6304216385,53.2238693237],"type":"Point"}
}