{
  "type": "Feature",
  "properties": {
    "iso:country":"DE",
    "sg:address":"Mittelweg",
    "sg:city":"Gr\u00f6mitz",
    "sg:phone":"+49 4562/8586",
    "sg:postcode":"23743",
    "sg:province":"Schleswig-Holstein",
    "wof:name":"Campingplatz Ahoi",
    "wof:placetype":"venue"
},
  "geometry": {"coordinates":[10.968985,54.152386],"type":"Point"}
}