{
  "type": "Feature",
  "properties": {
    "iso:country":"DE",
    "sg:address":"Seestr. 10",
    "sg:city":"Wadern-Noswendel",
    "sg:phone":"+49 6871/7737",
    "sg:postcode":"66687",
    "sg:province":"Saarland",
    "wof:name":"J. Kiefer",
    "wof:placetype":"venue"
},
  "geometry": {"coordinates":[6.8928661346,49.5401268005],"type":"Point"}
}