{
  "type": "Feature",
  "properties": {
    "iso:country":"DE",
    "sg:address":"Hauptstr. 28",
    "sg:city":"Tutzing",
    "sg:phone":"+49 8158/993117",
    "sg:postcode":"82327",
    "sg:province":"Bayern",
    "wof:name":"Aurel Parf\u00fcmerie",
    "wof:placetype":"venue"
},
  "geometry": {"coordinates":[11.280233,47.908302],"type":"Point"}
}