{
  "type": "Feature",
  "properties": {
    "iso:country":"DE",
    "sg:address":"Merscheider Str. 302 b",
    "sg:city":"Solingen",
    "sg:phone":"+49 212/336488",
    "sg:postcode":"42699",
    "sg:province":"Nordrhein-Westfalen",
    "wof:name":"Pflege Daheim J. P. Haubrich",
    "wof:placetype":"venue"
},
  "geometry": {"coordinates":[7.038054,51.171589],"type":"Point"}
}