{
  "type": "Feature",
  "properties": {
    "iso:country":"DE",
    "sg:address":"Zweibr\u00fccker Str.80",
    "sg:city":"Berlin",
    "sg:phone":"+49 30",
    "sg:postcode":"13583",
    "sg:province":"Berlin",
    "wof:name":"Lutzes Hompage",
    "wof:placetype":"venue"
},
  "geometry": {"coordinates":[13.189372,52.548416],"type":"Point"}
}