{
  "type": "Feature",
  "properties": {
    "iso:country":"DE",
    "sg:address":"August-Kayser-Str 35",
    "sg:city":"Pforzheim",
    "sg:phone":"+49 7231/64220",
    "sg:postcode":"75175",
    "sg:province":"Baden-W\u00fcrttemberg",
    "wof:name":"Druckerei B\u00f6hmler Gmbh",
    "wof:placetype":"venue"
},
  "geometry": {"coordinates":[8.7180528641,48.8799934387],"type":"Point"}
}