{
  "type": "Feature",
  "properties": {
    "iso:country":"DE",
    "sg:address":"Schaartor 1 PF 11",
    "sg:city":"Hamburg",
    "sg:phone":"+49 40/3785660",
    "sg:postcode":"20459",
    "sg:province":"Hamburg",
    "wof:name":"Han-sanit\u00c4r Trade Gmbh & Co",
    "wof:placetype":"venue"
},
  "geometry": {"coordinates":[9.9780597687,53.5465316772],"type":"Point"}
}