{
  "type": "Feature",
  "properties": {
    "iso:country":"DE",
    "sg:address":"Gro\u00dfer Busch 1",
    "sg:city":"Bergisch Gladbach",
    "sg:phone":"+49 2202/38079",
    "sg:postcode":"51467",
    "sg:province":"Nordrhein-Westfalen",
    "wof:name":"Another",
    "wof:placetype":"venue"
},
  "geometry": {"coordinates":[7.1481847763,51.000831604],"type":"Point"}
}