{
  "type": "Feature",
  "properties": {
    "iso:country":"DE",
    "sg:address":"Kirch\u00e4ckerstr. 27",
    "sg:city":"Steinenbronn",
    "sg:phone":"+49 7157/4256",
    "sg:postcode":"71144",
    "sg:province":"Baden-W\u00fcrttemberg",
    "wof:name":"Peter Wei\u00df Architekt",
    "wof:placetype":"venue"
},
  "geometry": {"coordinates":[9.120914,48.65884],"type":"Point"}
}