{
  "type": "Feature",
  "properties": {
    "iso:country":"DE",
    "sg:address":"Odenthaler Str. 184",
    "sg:city":"K\u00f6ln",
    "sg:phone":"+49 221/601097",
    "sg:postcode":"51069",
    "sg:province":"Nordrhein-Westfalen",
    "wof:name":"Schwahn Systems Gesellschaft F. Automatisierungstechnik Mbh",
    "wof:placetype":"venue"
},
  "geometry": {"coordinates":[7.0540089607,50.9994049072],"type":"Point"}
}