{
  "type": "Feature",
  "properties": {
    "iso:country":"DE",
    "sg:address":"Toblacher Str. 11",
    "sg:city":"Augsburg",
    "sg:phone":"+49 821/719688",
    "sg:postcode":"86165",
    "sg:province":"Bayern",
    "wof:name":"Kuno Els\u00e4\u00dfer Regelungs- Elektro-tontechnik Gmbh",
    "wof:placetype":"venue"
},
  "geometry": {"coordinates":[10.9484319687,48.3823738098],"type":"Point"}
}