{
  "type": "Feature",
  "properties": {
    "iso:country":"DE",
    "sg:address":"Retzstr. 2",
    "sg:city":"Vohenstrau\u00df",
    "sg:phone":"+49 9651/669",
    "sg:postcode":"92648",
    "sg:province":"Bayern",
    "wof:name":"Pizzeria Tulis Restaurant",
    "wof:placetype":"venue"
},
  "geometry": {"coordinates":[12.3359632492,49.6319046021],"type":"Point"}
}