{
  "type": "Feature",
  "properties": {
    "iso:country":"DE",
    "sg:address":"Oberdorfstr. 27",
    "sg:city":"Waldbrunn/Hintemeilingen",
    "sg:phone":"+49 6479/1285",
    "sg:postcode":"65620",
    "sg:province":"Hessen",
    "wof:name":"Service Rund Ums Haus Heinz Looben Waldbrunn/ww.",
    "wof:placetype":"venue"
},
  "geometry": {"coordinates":[8.118716,50.521919],"type":"Point"}
}