{
  "type": "Feature",
  "properties": {
    "iso:country":"DE",
    "sg:address":"Lindenallee 16",
    "sg:city":"Eisenh\u00fcttenstadt",
    "sg:phone":"+49 3364/46011",
    "sg:postcode":"15890",
    "sg:province":"Brandenburg",
    "wof:name":"Christian Poppitz",
    "wof:placetype":"venue"
},
  "geometry": {"coordinates":[14.630797,52.147675],"type":"Point"}
}