{
  "type": "Feature",
  "properties": {
    "iso:country":"DE",
    "sg:address":"Verbindungsstr. 7a",
    "sg:city":"Kempen",
    "sg:phone":"+49 2152/559940",
    "sg:postcode":"47906",
    "sg:province":"Nordrhein-Westfalen",
    "wof:name":"Bootswerft Sebastian Funger",
    "wof:placetype":"venue"
},
  "geometry": {"coordinates":[6.42953,51.36644],"type":"Point"}
}