{
  "type": "Feature",
  "properties": {
    "iso:country":"DE",
    "sg:address":"\u00d6lbergstr.86",
    "sg:city":"K\u00f6nigswinter",
    "sg:phone":"+49 2244",
    "sg:postcode":"53639",
    "sg:province":"Nordrhein-Westfalen",
    "wof:name":"Reisetagebuch Spanien",
    "wof:placetype":"venue"
},
  "geometry": {"coordinates":[7.233685,50.690037],"type":"Point"}
}