{
  "type": "Feature",
  "properties": {
    "iso:country":"DE",
    "sg:address":"Amalienstr. 46",
    "sg:city":"M\u00fcnchen",
    "sg:phone":"+49 89/284280",
    "sg:postcode":"80799",
    "sg:province":"Bayern",
    "wof:name":"Modern Art Gallery Hpm Kunsthandel Gmbh",
    "wof:placetype":"venue"
},
  "geometry": {"coordinates":[11.577898,48.149166],"type":"Point"}
}