{
  "type": "Feature",
  "properties": {
    "iso:country":"DE",
    "sg:address":"Wenzel-Verner-Str. 10",
    "sg:city":"Chemnitz",
    "sg:postcode":"09120",
    "sg:province":"Sachsen",
    "wof:name":"Siegried \u00d6lschlegele Gmbh Pelzhandlung",
    "wof:placetype":"venue"
},
  "geometry": {"coordinates":[12.897813,50.809406],"type":"Point"}
}