{
  "type": "Feature",
  "properties": {
    "iso:country":"DE",
    "sg:address":"Steinbrink 102",
    "sg:city":"Diepenau",
    "sg:phone":"+49 5777/201",
    "sg:postcode":"31603",
    "sg:province":"Niedersachsen",
    "wof:name":"Heinrich Ha\u00dffeld",
    "wof:placetype":"venue"
},
  "geometry": {"coordinates":[8.729263,52.49192],"type":"Point"}
}