{
  "type": "Feature",
  "properties": {
    "iso:country":"DE",
    "sg:address":"Goltzstr. 1",
    "sg:city":"Berlin",
    "sg:phone":"+49 30/21754555",
    "sg:postcode":"10781",
    "sg:province":"Berlin",
    "wof:name":"Ikonenhandel Gra\u00dfmann Gmbh",
    "wof:placetype":"venue"
},
  "geometry": {"coordinates":[13.3534145355,52.4901733398],"type":"Point"}
}