{
  "type": "Feature",
  "properties": {
    "iso:country":"DE",
    "sg:address":"Alte M\u00fcnsterstr. 18",
    "sg:city":"Werne",
    "sg:phone":"+49 2389/6293",
    "sg:postcode":"59368",
    "sg:province":"Nordrhein-Westfalen",
    "wof:name":"Mebra Vermittlungs Gmbh",
    "wof:placetype":"venue"
},
  "geometry": {"coordinates":[7.6377649307,51.6661605835],"type":"Point"}
}