{
  "type": "Feature",
  "properties": {
    "iso:country":"DE",
    "sg:address":"An der Pikardie 8",
    "sg:city":"Dresden",
    "sg:phone":"+49 351/285910",
    "sg:postcode":"01277",
    "sg:province":"Sachsen",
    "wof:name":"Strabag Stra\u00dfen- Und Tiefbau Ag",
    "wof:placetype":"venue"
},
  "geometry": {"coordinates":[13.775522,51.033375],"type":"Point"}
}