{
  "type": "Feature",
  "properties": {
    "iso:country":"DE",
    "sg:address":"Falkener Landstr.",
    "sg:city":"Treffurt",
    "sg:phone":"+49 36923/50356",
    "sg:postcode":"99830",
    "sg:province":"Th\u00fcringen",
    "wof:name":"Bistro Hahn Ernst",
    "wof:placetype":"venue"
},
  "geometry": {"coordinates":[10.2463912964,51.1320343018],"type":"Point"}
}