{
  "type": "Feature",
  "properties": {
    "iso:country":"DE",
    "sg:city":"Eimen",
    "sg:phone":"+49 5565/774",
    "sg:postcode":"37632",
    "sg:province":"Niedersachsen",
    "wof:name":"J. Zappe Antiquit\u00e4ten",
    "wof:placetype":"venue"
},
  "geometry": {"coordinates":[9.77762,51.876522],"type":"Point"}
}