{
  "type": "Feature",
  "properties": {
    "iso:country":"DE",
    "sg:address":"Fuggerstr. 32",
    "sg:city":"Bad Gr\u00f6nenbach",
    "sg:phone":"+49 8334/986227",
    "sg:postcode":"87730",
    "sg:province":"Bayern",
    "wof:name":"Gerhard Breher Gmbh",
    "wof:placetype":"venue"
},
  "geometry": {"coordinates":[10.2229824066,47.8803787231],"type":"Point"}
}