{
  "type": "Feature",
  "properties": {
    "iso:country":"DE",
    "sg:address":"Augustenstr. 39",
    "sg:city":"Kiel",
    "sg:phone":"+49 431/733888",
    "sg:postcode":"24143",
    "sg:province":"Schleswig-Holstein",
    "wof:name":"Uwe Und J\u00fcrgen Peter",
    "wof:placetype":"venue"
},
  "geometry": {"coordinates":[10.1474142075,54.3146133423],"type":"Point"}
}