{
  "type": "Feature",
  "properties": {
    "iso:country":"DE",
    "sg:address":"Fasanenweg 2",
    "sg:city":"Holzwickede",
    "sg:phone":"+49 2301/3036",
    "sg:postcode":"59439",
    "sg:province":"Nordrhein-Westfalen",
    "wof:name":"Reinhold Bendigs",
    "wof:placetype":"venue"
},
  "geometry": {"coordinates":[7.623006,51.494881],"type":"Point"}
}