{
  "type": "Feature",
  "properties": {
    "iso:country":"DE",
    "sg:address":"L\u00fcnener Str. 128",
    "sg:city":"Kamen",
    "sg:phone":"+49 2307/12381",
    "sg:postcode":"59174",
    "sg:province":"Nordrhein-Westfalen",
    "wof:name":"Heinrich Freund Inh. R. Stinka",
    "wof:placetype":"venue"
},
  "geometry": {"coordinates":[7.631499,51.588825],"type":"Point"}
}