{
  "type": "Feature",
  "properties": {
    "iso:country":"DE",
    "sg:address":"Bamberger Str. 16",
    "sg:city":"Uehlfeld",
    "sg:phone":"+49 9163/243",
    "sg:postcode":"91486",
    "sg:province":"Bayern",
    "wof:name":"Aro",
    "wof:placetype":"venue"
},
  "geometry": {"coordinates":[10.7239103317,49.6714706421],"type":"Point"}
}