{
  "type": "Feature",
  "properties": {
    "iso:country":"DE",
    "sg:address":"Am Sooren 25",
    "sg:city":"Hamburg",
    "sg:phone":"+49 40/6735945",
    "sg:postcode":"22149",
    "sg:province":"Hamburg",
    "wof:name":"System Kontor Andreas Feustel Unternehmensberatung E. K.",
    "wof:placetype":"venue"
},
  "geometry": {"coordinates":[10.1737480164,53.5948143005],"type":"Point"}
}