{
  "type": "Feature",
  "properties": {
    "iso:country":"DE",
    "sg:address":"Chausseestr. 1",
    "sg:city":"Wolgast",
    "sg:postcode":"17438",
    "sg:province":"Mecklenburg-Vorpommern",
    "wof:name":"Ad. Hibben Gmbh",
    "wof:placetype":"venue"
},
  "geometry": {"coordinates":[13.7736253738,54.0525016785],"type":"Point"}
}