{
  "type": "Feature",
  "properties": {
    "iso:country":"DE",
    "sg:address":"Gelnh\u00e4user Str 7",
    "sg:city":"Freigericht",
    "sg:phone":"+49 6055/5696",
    "sg:postcode":"63579",
    "sg:province":"Hessen",
    "wof:name":"Pnt Peter Nowak Team-bau",
    "wof:placetype":"venue"
},
  "geometry": {"coordinates":[9.114239,50.144398],"type":"Point"}
}