{
  "type": "Feature",
  "properties": {
    "iso:country":"DE",
    "sg:address":"Birkenstr. 32",
    "sg:city":"Friolzheim",
    "sg:phone":"+49 7044/940380",
    "sg:postcode":"71292",
    "sg:province":"Baden-W\u00fcrttemberg",
    "wof:name":"Manfred W. Foebus",
    "wof:placetype":"venue"
},
  "geometry": {"coordinates":[8.8359680176,48.8383407593],"type":"Point"}
}