{
  "type": "Feature",
  "properties": {
    "iso:country":"DE",
    "sg:address":"Oberkotzauer Str. 5",
    "sg:city":"Hof",
    "sg:phone":"+49 9281/51719",
    "sg:postcode":"95032",
    "sg:province":"Bayern",
    "wof:name":"Symos-h. Dillner Sandstrahlarbeiten",
    "wof:placetype":"venue"
},
  "geometry": {"coordinates":[11.932607,50.292698],"type":"Point"}
}