{
  "type": "Feature",
  "properties": {
    "iso:country":"DE",
    "sg:address":"Riehler Str. 12",
    "sg:city":"K\u00f6ln",
    "sg:phone":"+49 221/731883",
    "sg:postcode":"50668",
    "sg:province":"Nordrhein-Westfalen",
    "wof:name":"Aral Ag",
    "wof:placetype":"venue"
},
  "geometry": {"coordinates":[6.9610300064,50.9522171021],"type":"Point"}
}