{
  "type": "Feature",
  "properties": {
    "iso:country":"DE",
    "sg:address":"M\u00fchlenweg 8-10",
    "sg:city":"Bad Rothenfelde",
    "sg:postcode":"49214",
    "sg:province":"Niedersachsen",
    "wof:name":"Autolackiererei Steinbr\u00fcgge Gmbh & Co. Kg",
    "wof:placetype":"venue"
},
  "geometry": {"coordinates":[8.1457872391,52.0994186401],"type":"Point"}
}