{
  "type": "Feature",
  "properties": {
    "iso:country":"DE",
    "sg:address":"Gro\u00dfmachnower Str. 44",
    "sg:city":"Rangsdorf",
    "sg:phone":"+49 33708/20756",
    "sg:postcode":"15834",
    "sg:province":"Brandenburg",
    "wof:name":"Jahn",
    "wof:placetype":"venue"
},
  "geometry": {"coordinates":[13.439847,52.289467],"type":"Point"}
}