{
  "type": "Feature",
  "properties": {
    "iso:country":"DE",
    "sg:address":"Lothringer Str. 9 B",
    "sg:city":"Bremen",
    "sg:postcode":"28211",
    "sg:province":"Bremen",
    "wof:name":"A. Kempe Immobilien E. K.",
    "wof:placetype":"venue"
},
  "geometry": {"coordinates":[8.8349313736,53.0800056458],"type":"Point"}
}