{
  "type": "Feature",
  "properties": {
    "iso:country":"DE",
    "sg:address":"Munscheidstr. 14",
    "sg:city":"Gelsenkirchen",
    "sg:postcode":"45886",
    "sg:province":"Nordrhein-Westfalen",
    "wof:name":"Makros Ges. F\u00fcr Markt- Und Akzeptanzforschung",
    "wof:placetype":"venue"
},
  "geometry": {"coordinates":[7.108402,51.498589],"type":"Point"}
}