{
  "type": "Feature",
  "properties": {
    "iso:country":"DE",
    "sg:address":"Odenwaldring 21",
    "sg:city":"Freudenberg",
    "sg:postcode":"97896",
    "sg:province":"Baden-W\u00fcrttemberg",
    "wof:name":"Mayer-bau- Gmbh",
    "wof:placetype":"venue"
},
  "geometry": {"coordinates":[9.329285,49.756462],"type":"Point"}
}