{
  "type": "Feature",
  "properties": {
    "iso:country":"DE",
    "sg:address":"Markt 12",
    "sg:city":"Emsb\u00fcren",
    "sg:phone":"+49 5903/7813",
    "sg:postcode":"48488",
    "sg:province":"Niedersachsen",
    "wof:name":"Gutteck-spielst\u00e4tten Gmbh",
    "wof:placetype":"venue"
},
  "geometry": {"coordinates":[7.2939829826,52.3919219971],"type":"Point"}
}