{
  "type": "Feature",
  "properties": {
    "iso:country":"DE",
    "sg:address":"Gm\u00fcnder Str. 39",
    "sg:city":"Durlangen",
    "sg:phone":"+49 7176/6525",
    "sg:postcode":"73568",
    "sg:province":"Baden-W\u00fcrttemberg",
    "wof:name":"Manfred Baur Baugesch\u00e4ft Gmbh",
    "wof:placetype":"venue"
},
  "geometry": {"coordinates":[9.791769,48.855339],"type":"Point"}
}