{
  "type": "Feature",
  "properties": {
    "iso:country":"DE",
    "sg:address":"Agnes-Miegel-Str. 31",
    "sg:city":"Bremen",
    "sg:postcode":"28279",
    "sg:province":"Bremen",
    "wof:name":"Ebro Raum- Und Objekt- Ausstattung Handels Gmbh",
    "wof:placetype":"venue"
},
  "geometry": {"coordinates":[8.8440341949,53.0543327332],"type":"Point"}
}