{
  "type": "Feature",
  "properties": {
    "iso:country":"DE",
    "sg:address":"Deggendorfer Str. 45",
    "sg:city":"Essenbach",
    "sg:phone":"+49 8703/2509",
    "sg:postcode":"84051",
    "sg:province":"Bayern",
    "wof:name":"Kurt Urban Gmbh",
    "wof:placetype":"venue"
},
  "geometry": {"coordinates":[12.265944,48.606197],"type":"Point"}
}