{
  "type": "Feature",
  "properties": {
    "iso:country":"DE",
    "sg:address":"Kirchstr. 10",
    "sg:city":"Vilsbiburg",
    "sg:phone":"+49 8741/1222",
    "sg:postcode":"84137",
    "sg:province":"Bayern",
    "wof:name":"Deutsches Rotes Kreuz",
    "wof:placetype":"venue"
},
  "geometry": {"coordinates":[12.3576478958,48.4521865845],"type":"Point"}
}