{
  "type": "Feature",
  "properties": {
    "iso:country":"DE",
    "sg:address":"Am Langen Loh 4",
    "sg:city":"Lohra",
    "sg:phone":"+49 6426/204",
    "sg:postcode":"35102",
    "sg:province":"Hessen",
    "wof:name":"Johann Brusius",
    "wof:placetype":"venue"
},
  "geometry": {"coordinates":[8.60814,50.688011],"type":"Point"}
}