{
  "type": "Feature",
  "properties": {
    "iso:country":"DE",
    "sg:address":"Naheweinstr. 135",
    "sg:city":"Langenlonsheim",
    "sg:phone":"+49 6704/2242",
    "sg:postcode":"55450",
    "sg:province":"Rheinland-Pfalz",
    "wof:name":"Thomas Kappes",
    "wof:placetype":"venue"
},
  "geometry": {"coordinates":[7.8987851143,49.8974456787],"type":"Point"}
}