{
  "type": "Feature",
  "properties": {
    "iso:country":"DE",
    "sg:address":"Vallendarer Str. 67",
    "sg:city":"Bendorf",
    "sg:phone":"+49 2622/15043",
    "sg:postcode":"56170",
    "sg:province":"Rheinland-Pfalz",
    "wof:name":"Gta Fahrzeugvermietungs- Und Gro\u00dfhandels Gmbh",
    "wof:placetype":"venue"
},
  "geometry": {"coordinates":[7.5805740356,50.4180908203],"type":"Point"}
}