{
  "type": "Feature",
  "properties": {
    "iso:country":"DE",
    "sg:address":"Lortzingstr. 69",
    "sg:city":"Darmstadt",
    "sg:phone":"+49 6150/7390",
    "sg:postcode":"64291",
    "sg:province":"Hessen",
    "wof:name":"Manfred Wiedmann",
    "wof:placetype":"venue"
},
  "geometry": {"coordinates":[8.65265,49.92931],"type":"Point"}
}