{
  "type": "Feature",
  "properties": {
    "iso:country":"DE",
    "sg:address":"Behringstr. 15",
    "sg:city":"Potsdam",
    "sg:postcode":"14482",
    "sg:province":"Brandenburg",
    "wof:name":"Blank Ingenieurges. Mbh",
    "wof:placetype":"venue"
},
  "geometry": {"coordinates":[13.103518,52.397354],"type":"Point"}
}