{
  "type": "Feature",
  "properties": {
    "iso:country":"DE",
    "sg:address":"Walther-Rathenau-Str. 30",
    "sg:city":"Zwickau",
    "sg:phone":"+49 375/22657",
    "sg:postcode":"08058",
    "sg:province":"Sachsen",
    "wof:name":"Architekten Und Ingenieur Gbr",
    "wof:placetype":"venue"
},
  "geometry": {"coordinates":[12.488295,50.728573],"type":"Point"}
}