{
  "type": "Feature",
  "properties": {
    "iso:country":"DE",
    "sg:address":"Eichenstr. 1",
    "sg:city":"Burglengenfeld",
    "sg:phone":"+49 9471/807766",
    "sg:postcode":"93133",
    "sg:province":"Bayern",
    "wof:name":"Andreas Ollert",
    "wof:placetype":"venue"
},
  "geometry": {"coordinates":[12.053785,49.201447],"type":"Point"}
}