{
  "type": "Feature",
  "properties": {
    "iso:country":"DE",
    "sg:address":"Wieslauftalstr. 139",
    "sg:city":"Schorndorf",
    "sg:phone":"+49 7181/92850",
    "sg:postcode":"73614",
    "sg:province":"Baden-W\u00fcrttemberg",
    "wof:name":"B\u00fcro-schlang Kg",
    "wof:placetype":"venue"
},
  "geometry": {"coordinates":[9.5476036072,48.8197822571],"type":"Point"}
}