{
  "type": "Feature",
  "properties": {
    "iso:country":"DE",
    "sg:address":"Baumschulenweg 18",
    "sg:city":"Potsdam",
    "sg:phone":"+49 331/5054860",
    "sg:postcode":"14469",
    "sg:province":"Brandenburg",
    "wof:name":"Mbt Montage Bau Tornow",
    "wof:placetype":"venue"
},
  "geometry": {"coordinates":[12.9903106689,52.4053192139],"type":"Point"}
}