{
  "type": "Feature",
  "properties": {
    "iso:country":"DE",
    "sg:address":"Meininger Str. 1",
    "sg:city":"Themar",
    "sg:phone":"+49 36873/67421",
    "sg:postcode":"98660",
    "sg:province":"Th\u00fcringen",
    "wof:name":"Ingolf B\u00f6ttger",
    "wof:placetype":"venue"
},
  "geometry": {"coordinates":[10.6158447266,50.5055541992],"type":"Point"}
}