{
  "type": "Feature",
  "properties": {
    "iso:country":"DE",
    "sg:address":"Postfach 211161",
    "sg:city":"Salzgitter",
    "sg:postcode":"38213",
    "sg:province":"Niedersachsen",
    "wof:name":"Microfalt Asphaltbel\u00e4ge Gmbh",
    "wof:placetype":"venue"
},
  "geometry": {"coordinates":[10.3249101639,52.1485214233],"type":"Point"}
}