{
  "type": "Feature",
  "properties": {
    "iso:country":"DE",
    "sg:address":"Wertherstr. 9",
    "sg:city":"M\u00fcnchen",
    "sg:phone":"+49 89/30002611",
    "sg:postcode":"80809",
    "sg:province":"Bayern",
    "wof:name":"M S Webconsulting",
    "wof:placetype":"venue"
},
  "geometry": {"coordinates":[11.5642948151,48.1734046936],"type":"Point"}
}