{
  "type": "Feature",
  "properties": {
    "iso:country":"DE",
    "sg:address":"Ellernbruch 2",
    "sg:city":"Kavelstorf",
    "sg:phone":"+49 38208/60667",
    "sg:postcode":"18196",
    "sg:province":"Mecklenburg-Vorpommern",
    "wof:name":"Esser Bau Gmbh",
    "wof:placetype":"venue"
},
  "geometry": {"coordinates":[12.209965,54.01379],"type":"Point"}
}