{
  "type": "Feature",
  "properties": {
    "iso:country":"DE",
    "sg:address":"Ebersberger Str 28",
    "sg:city":"Alth\u00fctte",
    "sg:phone":"+49 7183/41144",
    "sg:postcode":"71566",
    "sg:province":"Baden-W\u00fcrttemberg",
    "wof:name":"Roland G\u00fcnther",
    "wof:placetype":"venue"
},
  "geometry": {"coordinates":[9.559318,48.932045],"type":"Point"}
}