{
  "type": "Feature",
  "properties": {
    "iso:country":"DE",
    "sg:address":"Otawistr. 13",
    "sg:city":"Berlin",
    "sg:phone":"+49 30/4515056",
    "sg:postcode":"13351",
    "sg:province":"Berlin",
    "wof:name":"Otto Mehler",
    "wof:placetype":"venue"
},
  "geometry": {"coordinates":[13.3407001495,52.5547676086],"type":"Point"}
}