{
  "type": "Feature",
  "properties": {
    "iso:country":"DE",
    "sg:address":"Starkenbrook 10",
    "sg:city":"Gettorf",
    "sg:phone":"+49 4346/4861",
    "sg:postcode":"24214",
    "sg:province":"Schleswig-Holstein",
    "wof:name":"Carl Ingwersen",
    "wof:placetype":"venue"
},
  "geometry": {"coordinates":[9.9719800949,54.4153747559],"type":"Point"}
}