{
  "type": "Feature",
  "properties": {
    "iso:country":"DE",
    "sg:address":"Wulkower Chaussee",
    "sg:city":"Alt Ruppin",
    "sg:phone":"+49 3391/7115",
    "sg:postcode":"16827",
    "sg:province":"Brandenburg",
    "wof:name":"Altruppiner Landservice Gmbh",
    "wof:placetype":"venue"
},
  "geometry": {"coordinates":[12.850934,52.944695],"type":"Point"}
}