{
  "type": "Feature",
  "properties": {
    "iso:country":"DE",
    "sg:address":"Gro\u00dfe Burgstr. 19",
    "sg:city":"L\u00fcbeck",
    "sg:phone":"+49 451/7026410",
    "sg:postcode":"23552",
    "sg:province":"Schleswig-Holstein",
    "wof:name":"Axel Franz Rechtsanwalt",
    "wof:placetype":"venue"
},
  "geometry": {"coordinates":[10.6910495758,53.8731994629],"type":"Point"}
}