{
  "type": "Feature",
  "properties": {
    "iso:country":"DE",
    "sg:address":"Panoramaweg 22",
    "sg:city":"Oberaula",
    "sg:phone":"+49 6628/327",
    "sg:postcode":"36280",
    "sg:province":"Hessen",
    "wof:name":"Hans Thamer",
    "wof:placetype":"venue"
},
  "geometry": {"coordinates":[9.494308,50.823631],"type":"Point"}
}