{
  "type": "Feature",
  "properties": {
    "iso:country":"DE",
    "sg:address":"Remstalstr. 29",
    "sg:city":"Remseck",
    "sg:phone":"+49 7146/6013",
    "sg:postcode":"71686",
    "sg:province":"Baden-W\u00fcrttemberg",
    "wof:name":"Hotel-restaurant Hirsch",
    "wof:placetype":"venue"
},
  "geometry": {"coordinates":[9.2741765976,48.8700714111],"type":"Point"}
}