{
  "type": "Feature",
  "properties": {
    "iso:country":"DE",
    "sg:address":"Vogt-Ramcke-Str. 8",
    "sg:city":"Pinneberg",
    "sg:phone":"+49 4101/65763",
    "sg:postcode":"25421",
    "sg:province":"Schleswig-Holstein",
    "wof:name":"Rudi Schulz Ingenieur",
    "wof:placetype":"venue"
},
  "geometry": {"coordinates":[9.8091745377,53.6443061829],"type":"Point"}
}