{
  "type": "Feature",
  "properties": {
    "iso:country":"DE",
    "sg:address":"Morianstr. 32",
    "sg:city":"Wuppertal",
    "sg:phone":"+49 4920/2245380",
    "sg:postcode":"42103",
    "sg:province":"Nordrhein-Westfalen",
    "wof:name":"Lonza Gmbh",
    "wof:placetype":"venue"
},
  "geometry": {"coordinates":[7.149958,51.256645],"type":"Point"}
}