{
  "type": "Feature",
  "properties": {
    "iso:country":"DE",
    "sg:address":"Mauerstr. 3",
    "sg:city":"Aachen",
    "sg:phone":"+49 241/27818",
    "sg:postcode":"52064",
    "sg:province":"Nordrhein-Westfalen",
    "wof:name":"Plum Bau- Und M\u00f6belschreinerei Gmbh",
    "wof:placetype":"venue"
},
  "geometry": {"coordinates":[6.074996,50.774902],"type":"Point"}
}