{
  "type": "Feature",
  "properties": {
    "iso:country":"DE",
    "sg:address":"L\u00f6ffelstr. 8",
    "sg:city":"Stuttgart",
    "sg:phone":"+49 711/760093",
    "sg:postcode":"70597",
    "sg:province":"Baden-W\u00fcrttemberg",
    "wof:name":"Erich Hiller Bauunternehmung Gmbh",
    "wof:placetype":"venue"
},
  "geometry": {"coordinates":[9.16878,48.749149],"type":"Point"}
}