{
  "type": "Feature",
  "properties": {
    "iso:country":"DE",
    "sg:address":"Lindenberg 7",
    "sg:city":"M\u00fcnchhausen",
    "sg:phone":"+49 6457/473",
    "sg:postcode":"35117",
    "sg:province":"Hessen",
    "wof:name":"Gastst\u00e4tte Heinrich Freiling",
    "wof:placetype":"venue"
},
  "geometry": {"coordinates":[8.6823272705,50.97215271],"type":"Point"}
}