{
  "type": "Feature",
  "properties": {
    "iso:country":"DE",
    "sg:address":"Marktstr. 59",
    "sg:city":"Krefeld",
    "sg:phone":"+49 2151/66657",
    "sg:postcode":"47798",
    "sg:province":"Nordrhein-Westfalen",
    "wof:name":"G. Wedekind",
    "wof:placetype":"venue"
},
  "geometry": {"coordinates":[6.5609197617,51.3303146362],"type":"Point"}
}