{
  "type": "Feature",
  "properties": {
    "iso:country":"DE",
    "sg:address":"Detmolder Str. 50",
    "sg:city":"Bad Oeynhausen",
    "sg:phone":"+49 5731/94430",
    "sg:postcode":"32545",
    "sg:province":"Nordrhein-Westfalen",
    "wof:name":"Neust\u00e4dter Eck",
    "wof:placetype":"venue"
},
  "geometry": {"coordinates":[8.8014373779,52.1925926208],"type":"Point"}
}