{
  "type": "Feature",
  "properties": {
    "iso:country":"DE",
    "sg:address":"Am Otterrohr 7a",
    "sg:city":"Oberstdorf",
    "sg:phone":"+49 8322/3675",
    "sg:postcode":"87561",
    "sg:province":"Bayern",
    "wof:name":"Fremdenheim Manfred Luxenhofer",
    "wof:placetype":"venue"
},
  "geometry": {"coordinates":[10.27110672,47.4123344421],"type":"Point"}
}