{
  "type": "Feature",
  "properties": {
    "iso:country":"DE",
    "sg:address":"Oldesloer Str. 113 A",
    "sg:city":"Hamburg",
    "sg:phone":"+49 40/5502763",
    "sg:postcode":"22457",
    "sg:province":"Hamburg",
    "wof:name":"Zerkleinerungstechnik Wiechers Gmbh",
    "wof:placetype":"venue"
},
  "geometry": {"coordinates":[9.9359502792,53.6473503113],"type":"Point"}
}