{
  "type": "Feature",
  "properties": {
    "iso:country":"DE",
    "sg:address":"Industriestr. 6A",
    "sg:city":"Henstedt-Ulzburg",
    "sg:phone":"+49 4193/892587",
    "sg:postcode":"24558",
    "sg:province":"Schleswig-Holstein",
    "wof:name":"Wein U. Getr\u00e4nkefachmarkt Inh. L. Butemann",
    "wof:placetype":"venue"
},
  "geometry": {"coordinates":[9.9828367233,53.7623329163],"type":"Point"}
}