{
  "type": "Feature",
  "properties": {
    "iso:country":"DE",
    "sg:address":"Dachauer Str. 215",
    "sg:city":"M\u00fcnchen",
    "sg:postcode":"80637",
    "sg:province":"Bayern",
    "wof:name":"Doca M\u00fcnchen S. R. L. Timisoara",
    "wof:placetype":"venue"
},
  "geometry": {"coordinates":[11.5430297852,48.1620788574],"type":"Point"}
}