{
  "type": "Feature",
  "properties": {
    "iso:country":"DE",
    "sg:address":"H\u00f6llengasse 2",
    "sg:city":"Gengenbach",
    "sg:postcode":"77723",
    "sg:province":"Baden-W\u00fcrttemberg",
    "wof:name":"Gegenbach Kultur- Und Tourismus Gmbh",
    "wof:placetype":"venue"
},
  "geometry": {"coordinates":[8.0142946243,48.404083252],"type":"Point"}
}