{
  "type": "Feature",
  "properties": {
    "iso:country":"DE",
    "sg:address":"Kalckreuthweg 4",
    "sg:city":"Stuttgart",
    "sg:phone":"+49 711/251845",
    "sg:postcode":"70192",
    "sg:province":"Baden-W\u00fcrttemberg",
    "wof:name":"Ulfert Weber Architekt",
    "wof:placetype":"venue"
},
  "geometry": {"coordinates":[9.168047,48.799374],"type":"Point"}
}