{
  "type": "Feature",
  "properties": {
    "iso:country":"DE",
    "sg:address":"Falkenseer Str. 21",
    "sg:city":"Hennigsdorf",
    "sg:postcode":"16761",
    "sg:province":"Brandenburg",
    "wof:name":"Alpin Massivhaus Marketing Gmbh",
    "wof:placetype":"venue"
},
  "geometry": {"coordinates":[13.1954603195,52.6246833801],"type":"Point"}
}