{
  "type": "Feature",
  "properties": {
    "iso:country":"DE",
    "sg:address":"Warburgstr. 37",
    "sg:city":"Hamburg",
    "sg:phone":"+49 40/413243",
    "sg:postcode":"20354",
    "sg:province":"Hamburg",
    "wof:name":"Matthias Ocker Architekt",
    "wof:placetype":"venue"
},
  "geometry": {"coordinates":[9.995649,53.562279],"type":"Point"}
}