{
  "type": "Feature",
  "properties": {
    "iso:country":"DE",
    "sg:address":"Starenweg 10",
    "sg:city":"Ditzingen",
    "sg:phone":"+49 7156/5711",
    "sg:postcode":"71254",
    "sg:province":"Baden-W\u00fcrttemberg",
    "wof:name":"Schwarz",
    "wof:placetype":"venue"
},
  "geometry": {"coordinates":[9.04662323,48.8361434937],"type":"Point"}
}