{
  "type": "Feature",
  "properties": {
    "iso:country":"DE",
    "sg:address":"Eschenschlag 7",
    "sg:city":"Northeim",
    "sg:postcode":"37154",
    "sg:province":"Niedersachsen",
    "wof:name":"Sanit\u00e4tshaus Leinetal Gmbh",
    "wof:placetype":"venue"
},
  "geometry": {"coordinates":[9.9904909134,51.7063674927],"type":"Point"}
}