{
  "type": "Feature",
  "properties": {
    "iso:country":"DE",
    "sg:address":"Hauptstr. 46",
    "sg:city":"Bad Wimpfen",
    "sg:phone":"+49 7063/233",
    "sg:postcode":"74206",
    "sg:province":"Baden-W\u00fcrttemberg",
    "wof:name":"Egon Maisenh\u00e4lder",
    "wof:placetype":"venue"
},
  "geometry": {"coordinates":[9.162691,49.229542],"type":"Point"}
}