{
  "type": "Feature",
  "properties": {
    "iso:country":"DE",
    "sg:address":"Am Tempelberg 8",
    "sg:city":"Eberswalde",
    "sg:phone":"+49 3334/235700",
    "sg:postcode":"16225",
    "sg:province":"Brandenburg",
    "wof:name":"Lothar Kulike",
    "wof:placetype":"venue"
},
  "geometry": {"coordinates":[13.8447713852,52.8333206177],"type":"Point"}
}