{
  "type": "Feature",
  "properties": {
    "iso:country":"DE",
    "sg:address":"Ehrenpfortensteig 6",
    "sg:city":"Berlin",
    "sg:phone":"+49 30/4047075",
    "sg:postcode":"13467",
    "sg:province":"Berlin",
    "wof:name":"Aceb Bau-planungs-betreu- Ungs Und Vermittlungsges. Mbh",
    "wof:placetype":"venue"
},
  "geometry": {"coordinates":[13.2887268066,52.6112861633],"type":"Point"}
}