{
  "type": "Feature",
  "properties": {
    "iso:country":"DE",
    "sg:address":"Ludwigshohl 11",
    "sg:city":"Enkenbach-Alsenborn",
    "sg:phone":"+49 6303/2131",
    "sg:postcode":"67677",
    "sg:province":"Rheinland-Pfalz",
    "wof:name":"M. Kaiser",
    "wof:placetype":"venue"
},
  "geometry": {"coordinates":[7.895604,49.485661],"type":"Point"}
}