{
  "type": "Feature",
  "properties": {
    "iso:country":"DE",
    "sg:address":"Eisenbahnstr. 1",
    "sg:city":"D\u00f6beln",
    "sg:phone":"+49 3431/611714",
    "sg:postcode":"04720",
    "sg:province":"Sachsen",
    "wof:name":"Hotel Wei\u00dfe Taube",
    "wof:placetype":"venue"
},
  "geometry": {"coordinates":[13.0961418152,51.1281051636],"type":"Point"}
}