{
  "type": "Feature",
  "properties": {
    "iso:country":"DE",
    "sg:address":"Dornenkamp 11",
    "sg:city":"Sendenhorst",
    "sg:phone":"+49 2526/950000",
    "sg:postcode":"48324",
    "sg:province":"Nordrhein-Westfalen",
    "wof:name":"Hans-joachim Bialek",
    "wof:placetype":"venue"
},
  "geometry": {"coordinates":[7.826934,51.836605],"type":"Point"}
}