{
  "type": "Feature",
  "properties": {
    "iso:country":"DE",
    "sg:address":"Stra\u00dfe des Friedens",
    "sg:city":"Hohenthurm",
    "sg:phone":"+49 34602/51043",
    "sg:postcode":"06188",
    "sg:province":"Sachsen-Anhalt",
    "wof:name":"Liane Schlemmer",
    "wof:placetype":"venue"
},
  "geometry": {"coordinates":[12.099215,51.515266],"type":"Point"}
}