{
  "type": "Feature",
  "properties": {
    "iso:country":"DE",
    "sg:address":"Lerchenpfad",
    "sg:city":"Mechernich",
    "sg:phone":"+49 2443/6965",
    "sg:postcode":"53894",
    "sg:province":"Nordrhein-Westfalen",
    "wof:name":"U. Besecke Masseur",
    "wof:placetype":"venue"
},
  "geometry": {"coordinates":[6.713133,50.604347],"type":"Point"}
}