{
  "type": "Feature",
  "properties": {
    "iso:country":"DE",
    "sg:address":"Lossenweg 4",
    "sg:city":"Darmstadt",
    "sg:phone":"+49 6151/64304",
    "sg:postcode":"64285",
    "sg:province":"Hessen",
    "wof:name":"G\u00fcnter Wetzel",
    "wof:placetype":"venue"
},
  "geometry": {"coordinates":[8.6585597992,49.8524208069],"type":"Point"}
}