{
  "type": "Feature",
  "properties": {
    "iso:country":"DE",
    "sg:address":"Stresemannstr. 20",
    "sg:city":"Plauen",
    "sg:phone":"+49 3741/220621",
    "sg:postcode":"08523",
    "sg:province":"Sachsen",
    "wof:name":"Camp Markt Ohg Schadler & Schneider",
    "wof:placetype":"venue"
},
  "geometry": {"coordinates":[12.1385068893,50.4982223511],"type":"Point"}
}