{
  "type": "Feature",
  "properties": {
    "iso:country":"DE",
    "sg:address":"Papendiek 27",
    "sg:city":"G\u00f6ttingen",
    "sg:phone":"+49 551/58788",
    "sg:postcode":"37073",
    "sg:province":"Niedersachsen",
    "wof:name":"Alphei-optik Gmbh Augenoptiker",
    "wof:placetype":"venue"
},
  "geometry": {"coordinates":[9.9312458038,51.5328559875],"type":"Point"}
}