{
  "type": "Feature",
  "properties": {
    "iso:country":"DE",
    "sg:address":"Delsterner Str. 102",
    "sg:city":"Hagen",
    "sg:phone":"+49 2331/75758",
    "sg:postcode":"58091",
    "sg:province":"Nordrhein-Westfalen",
    "wof:name":"Bernd Lange Mineral\u00f6l-handel",
    "wof:placetype":"venue"
},
  "geometry": {"coordinates":[7.5110311508,51.3407936096],"type":"Point"}
}