{
  "type": "Feature",
  "properties": {
    "iso:country":"DE",
    "sg:address":"M\u00fclheimer Str. 306",
    "sg:city":"Oberhausen",
    "sg:postcode":"46045",
    "sg:province":"Nordrhein-Westfalen",
    "wof:name":"Holzbau Wendt Gmbh",
    "wof:placetype":"venue"
},
  "geometry": {"coordinates":[6.8643422127,51.4656944275],"type":"Point"}
}