{
  "type": "Feature",
  "properties": {
    "iso:country":"DE",
    "sg:address":"Burgstr. 17",
    "sg:city":"Lahnstein",
    "sg:phone":"+49 2621/3778",
    "sg:postcode":"56112",
    "sg:province":"Rheinland-Pfalz",
    "wof:name":"Karo-schl\u00fcsseldienst",
    "wof:placetype":"venue"
},
  "geometry": {"coordinates":[7.6063809395,50.3003883362],"type":"Point"}
}