{
  "type": "Feature",
  "properties": {
    "iso:country":"DE",
    "sg:address":"Karlsgraben 8",
    "sg:city":"Aachen",
    "sg:phone":"+49 241/37364",
    "sg:postcode":"52064",
    "sg:province":"Nordrhein-Westfalen",
    "wof:name":"Scharzard",
    "wof:placetype":"venue"
},
  "geometry": {"coordinates":[6.077026,50.773026],"type":"Point"}
}