{
  "type": "Feature",
  "properties": {
    "iso:country":"DE",
    "sg:address":"Odenthaler Str. 44",
    "sg:city":"Odenthal",
    "sg:phone":"+49 2202/70255",
    "sg:postcode":"51519",
    "sg:province":"Nordrhein-Westfalen",
    "wof:name":"La Fornace Inh. Salvatore Greco",
    "wof:placetype":"venue"
},
  "geometry": {"coordinates":[7.1238751411,51.0179862976],"type":"Point"}
}