{
  "type": "Feature",
  "properties": {
    "iso:country":"DE",
    "sg:address":"Mengstr. 1",
    "sg:city":"L\u00fcbeck",
    "sg:phone":"+49 451/705955",
    "sg:postcode":"23552",
    "sg:province":"Schleswig-Holstein",
    "wof:name":"Werner Hass",
    "wof:placetype":"venue"
},
  "geometry": {"coordinates":[10.6839761734,53.8682899475],"type":"Point"}
}