{
  "type": "Feature",
  "properties": {
    "iso:country":"DE",
    "sg:address":"Bachstr. 9 a",
    "sg:city":"Fr\u00f6ndenberg",
    "sg:phone":"+49 2378/3411",
    "sg:postcode":"58730",
    "sg:province":"Nordrhein-Westfalen",
    "wof:name":"Bss B\u00fcrosysteme- Simon- Gmbh",
    "wof:placetype":"venue"
},
  "geometry": {"coordinates":[7.6921257973,51.4764976501],"type":"Point"}
}