{
  "type": "Feature",
  "properties": {
    "iso:country":"DE",
    "sg:address":"Wasserm\u00fchlenstr. 14",
    "sg:city":"Vreden",
    "sg:phone":"+49 2564/32672",
    "sg:postcode":"48691",
    "sg:province":"Nordrhein-Westfalen",
    "wof:name":"Ingrid S",
    "wof:placetype":"venue"
},
  "geometry": {"coordinates":[6.823911,52.034981],"type":"Point"}
}