{
  "type": "Feature",
  "properties": {
    "iso:country":"DE",
    "sg:address":"Rottstr. 9",
    "sg:city":"Essen",
    "sg:phone":"+49 201/2205323",
    "sg:postcode":"45127",
    "sg:province":"Nordrhein-Westfalen",
    "wof:name":"Beratungsstelle D. Diakon. Werkes",
    "wof:placetype":"venue"
},
  "geometry": {"coordinates":[7.011988,51.459518],"type":"Point"}
}