{
  "type": "Feature",
  "properties": {
    "iso:country":"DE",
    "sg:address":"Liethwisch 5a",
    "sg:city":"Hamburg",
    "sg:phone":"+49 40/5893840",
    "sg:postcode":"22529",
    "sg:province":"Hamburg",
    "wof:name":"Rainulf Mende Rechtsanwalt",
    "wof:placetype":"venue"
},
  "geometry": {"coordinates":[9.944196701,53.6038017273],"type":"Point"}
}