{
  "type": "Feature",
  "properties": {
    "iso:country":"DE",
    "sg:address":"Frankenforster Str. 27-29",
    "sg:city":"Bergisch Gladbach",
    "sg:phone":"+49 2204/92810",
    "sg:postcode":"51427",
    "sg:province":"Nordrhein-Westfalen",
    "wof:name":"Bocchi Fruit Trade Germany Gmbh",
    "wof:placetype":"venue"
},
  "geometry": {"coordinates":[7.1386179924,50.9559593201],"type":"Point"}
}