{
  "type": "Feature",
  "properties": {
    "iso:country":"DE",
    "sg:address":"Lerchesflurweg 61",
    "sg:city":"Saarbr\u00fccken",
    "sg:phone":"+49 681/5849200",
    "sg:postcode":"66119",
    "sg:province":"Saarland",
    "wof:name":"Gabriele Und G\u00fcnther Kiefer",
    "wof:placetype":"venue"
},
  "geometry": {"coordinates":[6.983383,49.224533],"type":"Point"}
}