{
  "type": "Feature",
  "properties": {
    "iso:country":"DE",
    "sg:address":"Carl-Zeiss-Str. 2",
    "sg:city":"Alzenau",
    "sg:postcode":"63755",
    "sg:province":"Bayern",
    "wof:name":"Gobera Management Gmbh",
    "wof:placetype":"venue"
},
  "geometry": {"coordinates":[9.0437850952,50.0905685425],"type":"Point"}
}