{
  "type": "Feature",
  "properties": {
    "iso:country":"DE",
    "sg:address":"L\u00fcnkenberg 5",
    "sg:city":"Hamburg",
    "sg:postcode":"22609",
    "sg:province":"Hamburg",
    "wof:name":"Euro Progress Real Estate Development And",
    "wof:placetype":"venue"
},
  "geometry": {"coordinates":[9.8628997803,53.5483207703],"type":"Point"}
}