{
  "type": "Feature",
  "properties": {
    "iso:country":"DE",
    "sg:address":"Kolpingstr. 10",
    "sg:city":"Billerbeck",
    "sg:phone":"+49 2543/4495",
    "sg:postcode":"48727",
    "sg:province":"Nordrhein-Westfalen",
    "wof:name":"A. Klemmt Heissmangel",
    "wof:placetype":"venue"
},
  "geometry": {"coordinates":[7.2858428955,51.9834747314],"type":"Point"}
}