{
  "type": "Feature",
  "properties": {
    "iso:country":"DE",
    "sg:address":"Rodderweg 38",
    "sg:city":"Br\u00fchl",
    "sg:phone":"+49 2232/27678",
    "sg:postcode":"50321",
    "sg:province":"Nordrhein-Westfalen",
    "wof:name":"Kreisch",
    "wof:placetype":"venue"
},
  "geometry": {"coordinates":[6.893075943,50.8282585144],"type":"Point"}
}