{
  "type": "Feature",
  "properties": {
    "iso:country":"DE",
    "sg:address":"Turmstr. 53",
    "sg:city":"Sulzdorf",
    "sg:phone":"+49 9763/265",
    "sg:postcode":"97528",
    "sg:province":"Bayern",
    "wof:name":"Berggasthof",
    "wof:placetype":"venue"
},
  "geometry": {"coordinates":[10.583237648,50.266242981],"type":"Point"}
}