{
  "type": "Feature",
  "properties": {
    "iso:country":"DE",
    "sg:address":"Poststr. 19",
    "sg:city":"Hagenow",
    "sg:phone":"+49 3883/510251",
    "sg:postcode":"19230",
    "sg:province":"Mecklenburg-Vorpommern",
    "wof:name":"Horst-dieter Vo\u00df",
    "wof:placetype":"venue"
},
  "geometry": {"coordinates":[11.188392,53.43082],"type":"Point"}
}