{
  "type": "Feature",
  "properties": {
    "iso:country":"DE",
    "sg:address":"Sinsheimer Str. 15",
    "sg:city":"Mauer",
    "sg:phone":"+49 6226/1370",
    "sg:postcode":"69256",
    "sg:province":"Baden-W\u00fcrttemberg",
    "wof:name":"Werner Gutruf",
    "wof:placetype":"venue"
},
  "geometry": {"coordinates":[8.801423,49.338612],"type":"Point"}
}