{
  "type": "Feature",
  "properties": {
    "iso:country":"DE",
    "sg:address":"Staufenbergstr. 2",
    "sg:city":"Zorge",
    "sg:phone":"+49 5586/593",
    "sg:postcode":"37449",
    "sg:province":"Niedersachsen",
    "wof:name":"Pension Rieche",
    "wof:placetype":"venue"
},
  "geometry": {"coordinates":[10.6265201569,51.6212806702],"type":"Point"}
}