{
  "type": "Feature",
  "properties": {
    "iso:country":"DE",
    "sg:address":"Neukircher Str. 5",
    "sg:city":"Putzkau",
    "sg:phone":"+49 3594/706139",
    "sg:postcode":"01877",
    "sg:province":"Sachsen",
    "wof:name":"Erhard Winkler",
    "wof:placetype":"venue"
},
  "geometry": {"coordinates":[14.236787,51.097614],"type":"Point"}
}