{
  "type": "Feature",
  "properties": {
    "iso:country":"DE",
    "sg:address":"Am Weidiggraben 11",
    "sg:city":"F\u00fcrth",
    "sg:phone":"+49 911/970850",
    "sg:postcode":"90763",
    "sg:province":"Bayern",
    "wof:name":"Japp Schlosserei",
    "wof:placetype":"venue"
},
  "geometry": {"coordinates":[11.0055351257,49.4550056458],"type":"Point"}
}