{
  "type": "Feature",
  "properties": {
    "iso:country":"DE",
    "sg:address":"Ledenweg 31",
    "sg:city":"Radebeul",
    "sg:phone":"+49 351/8307515",
    "sg:postcode":"01445",
    "sg:province":"Sachsen",
    "wof:name":"F. Mehnert Architekt",
    "wof:placetype":"venue"
},
  "geometry": {"coordinates":[13.638893,51.111244],"type":"Point"}
}