{
  "type": "Feature",
  "properties": {
    "iso:country":"DE",
    "sg:address":"Landwehr 3",
    "sg:city":"Hanau",
    "sg:phone":"+49 6181/33770",
    "sg:postcode":"63450",
    "sg:province":"Hessen",
    "wof:name":"Bki Baukeramik Import- Und Handels Gmbh",
    "wof:placetype":"venue"
},
  "geometry": {"coordinates":[8.9321203232,50.128238678],"type":"Point"}
}