{
  "type": "Feature",
  "properties": {
    "iso:country":"DE",
    "sg:address":"Missundestr. 47",
    "sg:city":"Dortmund",
    "sg:phone":"+49 231/811435",
    "sg:postcode":"44145",
    "sg:province":"Nordrhein-Westfalen",
    "wof:name":"Herbert Kordt",
    "wof:placetype":"venue"
},
  "geometry": {"coordinates":[7.471082,51.524334],"type":"Point"}
}