{
  "type": "Feature",
  "properties": {
    "iso:country":"DE",
    "sg:address":"Sch\u00e4ferweg 14",
    "sg:city":"Flensburg",
    "sg:phone":"+49 461/50400",
    "sg:postcode":"24941",
    "sg:province":"Schleswig-Holstein",
    "wof:name":"Orion Versand Gmbh & Co. Kg",
    "wof:placetype":"venue"
},
  "geometry": {"coordinates":[9.3893604279,54.7759132385],"type":"Point"}
}