{
  "type": "Feature",
  "properties": {
    "iso:country":"DE",
    "sg:address":"Herbststr. 2",
    "sg:city":"Oberasbach",
    "sg:postcode":"90522",
    "sg:province":"Bayern",
    "wof:name":"B\u00f6den B\u00e4der Baden Gmbh",
    "wof:placetype":"venue"
},
  "geometry": {"coordinates":[10.9795017242,49.4192008972],"type":"Point"}
}