{
  "type": "Feature",
  "properties": {
    "iso:country":"DE",
    "sg:address":"Nassaustr. 35",
    "sg:city":"Hofheim",
    "sg:phone":"+49 6122/2054",
    "sg:postcode":"65719",
    "sg:province":"Hessen",
    "wof:name":"Pier-electronic Gmbh",
    "wof:placetype":"venue"
},
  "geometry": {"coordinates":[8.38197,50.071171],"type":"Point"}
}