{
  "type": "Feature",
  "properties": {
    "iso:country":"DE",
    "sg:address":"Planckstr. 24",
    "sg:city":"Herford",
    "sg:phone":"+49 5221/9760",
    "sg:postcode":"32052",
    "sg:province":"Nordrhein-Westfalen",
    "wof:name":"Dr.-ing. F. Prekwinkel Gmbh",
    "wof:placetype":"venue"
},
  "geometry": {"coordinates":[8.68117,52.095139],"type":"Point"}
}