{
  "type": "Feature",
  "properties": {
    "iso:country":"DE",
    "sg:address":"Ottensooser Weg 5",
    "sg:city":"Lauf",
    "sg:phone":"+49 9123/188122",
    "sg:postcode":"91207",
    "sg:province":"Bayern",
    "wof:name":"Tennis-squash Lauf",
    "wof:placetype":"venue"
},
  "geometry": {"coordinates":[11.2922277451,49.5091552734],"type":"Point"}
}