{
  "type": "Feature",
  "properties": {
    "iso:country":"DE",
    "sg:address":"Birkenweg 9",
    "sg:city":"Putzbrunn",
    "sg:postcode":"85640",
    "sg:province":"Bayern",
    "wof:name":"Wb Gmbh",
    "wof:placetype":"venue"
},
  "geometry": {"coordinates":[11.6975593567,48.073802948],"type":"Point"}
}