{
  "type": "Feature",
  "properties": {
    "iso:country":"DE",
    "sg:address":"Pestalozzistr. 3",
    "sg:city":"Kulmbach",
    "sg:postcode":"95326",
    "sg:province":"Bayern",
    "wof:name":"Reste Ecke",
    "wof:placetype":"venue"
},
  "geometry": {"coordinates":[11.4512910843,50.1068687439],"type":"Point"}
}