{
  "type": "Feature",
  "properties": {
    "iso:country":"DE",
    "sg:address":"Marktplatz 4",
    "sg:city":"Luhe-Wildenau",
    "sg:phone":"+49 9607/209",
    "sg:postcode":"92706",
    "sg:province":"Bayern",
    "wof:name":"K. Tretter",
    "wof:placetype":"venue"
},
  "geometry": {"coordinates":[12.1490764618,49.5825538635],"type":"Point"}
}