{
  "type": "Feature",
  "properties": {
    "iso:country":"DE",
    "sg:address":"Hermann-L\u00f6ns-Str. 55",
    "sg:city":"Hildesheim",
    "sg:phone":"+49 5121/44993",
    "sg:postcode":"31137",
    "sg:province":"Niedersachsen",
    "wof:name":"Dieter H\u00f6rschelmann Architekt",
    "wof:placetype":"venue"
},
  "geometry": {"coordinates":[9.903151,52.165558],"type":"Point"}
}