{
  "type": "Feature",
  "properties": {
    "iso:country":"DE",
    "sg:address":"Nedderndorfer Weg 11",
    "sg:city":"Hamburg",
    "sg:phone":"+49 40/6511796",
    "sg:postcode":"22111",
    "sg:province":"Hamburg",
    "wof:name":"Ganzalez Ballettschule",
    "wof:placetype":"venue"
},
  "geometry": {"coordinates":[10.0832300186,53.5488433838],"type":"Point"}
}