{
  "type": "Feature",
  "properties": {
    "iso:country":"DE",
    "sg:address":"Bahnhofstr. 12",
    "sg:city":"Lindenthal",
    "sg:phone":"+49 341/4615828",
    "sg:postcode":"04466",
    "wof:name":"Karl Gbr",
    "wof:placetype":"venue"
},
  "geometry": {"coordinates":[12.3313999176,51.4003791809],"type":"Point"}
}