{
  "type": "Feature",
  "properties": {
    "iso:country":"DE",
    "sg:address":"Eichendorffstr. 1",
    "sg:city":"Donzdorf",
    "sg:phone":"+49 7162/24712",
    "sg:postcode":"73072",
    "sg:province":"Baden-W\u00fcrttemberg",
    "wof:name":"K. Und B. Str\u00e4hle",
    "wof:placetype":"venue"
},
  "geometry": {"coordinates":[9.794284,48.704926],"type":"Point"}
}