{
  "type": "Feature",
  "properties": {
    "iso:country":"DE",
    "sg:address":"Klaus-Groth-Str. 56",
    "sg:city":"Hamburg",
    "sg:postcode":"20535",
    "sg:province":"Hamburg",
    "wof:name":"Mgm Management Verwaltungs Gmbh",
    "wof:placetype":"venue"
},
  "geometry": {"coordinates":[10.0316400528,53.5553283691],"type":"Point"}
}