{
  "type": "Feature",
  "properties": {
    "iso:country":"DE",
    "sg:address":"Klosterstr. 1",
    "sg:city":"Hof",
    "sg:phone":"+49 9281/815232",
    "sg:postcode":"95028",
    "sg:province":"Bayern",
    "wof:name":"Freiheitshalle Hof",
    "wof:placetype":"venue"
},
  "geometry": {"coordinates":[11.918491,50.321918],"type":"Point"}
}