{
  "type": "Feature",
  "properties": {
    "iso:country":"DE",
    "sg:address":"Schlachthofstr. 27",
    "sg:city":"Bochum",
    "sg:phone":"+49 2327/61131",
    "sg:postcode":"44866",
    "sg:province":"Nordrhein-Westfalen",
    "wof:name":"Gerhard Kaltwasser Innenarchitekt",
    "wof:placetype":"venue"
},
  "geometry": {"coordinates":[7.132183,51.486946],"type":"Point"}
}