{
  "type": "Feature",
  "properties": {
    "iso:country":"DE",
    "sg:address":"G\u00e4rtnerstr. 16",
    "sg:city":"Freudenstadt",
    "sg:phone":"+49 7441/4008",
    "sg:postcode":"72250",
    "sg:province":"Baden-W\u00fcrttemberg",
    "wof:name":"Gisela Anton Immobilienmakler",
    "wof:placetype":"venue"
},
  "geometry": {"coordinates":[8.4086198807,48.4638595581],"type":"Point"}
}