{
  "type": "Feature",
  "properties": {
    "iso:country":"DE",
    "sg:address":"Zum Niederntor 26",
    "sg:city":"Springe",
    "sg:phone":"+49 5041/77740",
    "sg:postcode":"31832",
    "sg:province":"Niedersachsen",
    "wof:name":"Sozialstation",
    "wof:placetype":"venue"
},
  "geometry": {"coordinates":[9.555185,52.209091],"type":"Point"}
}