{
  "type": "Feature",
  "properties": {
    "iso:country":"DE",
    "sg:address":"Schulstr. 19",
    "sg:city":"Hennef",
    "sg:phone":"+49 2242/2880",
    "sg:postcode":"53773",
    "sg:province":"Nordrhein-Westfalen",
    "wof:name":"Grabmale Nigg Gmbh",
    "wof:placetype":"venue"
},
  "geometry": {"coordinates":[7.2666730881,50.7710571289],"type":"Point"}
}