{
  "type": "Feature",
  "properties": {
    "iso:country":"DE",
    "sg:address":"Im Auelsgarten 4",
    "sg:city":"Bad Neuenahr-Ahrweiler",
    "sg:phone":"+49 2641/7254",
    "sg:postcode":"53474",
    "sg:province":"Rheinland-Pfalz",
    "wof:name":"Udo Heimermann Architekt",
    "wof:placetype":"venue"
},
  "geometry": {"coordinates":[7.194795,50.543301],"type":"Point"}
}