{
  "type": "Feature",
  "properties": {
    "iso:country":"DE",
    "sg:address":"Riegelstr. 6",
    "sg:city":"Lehrte",
    "sg:phone":"+49 5132/4733",
    "sg:postcode":"31275",
    "sg:province":"Niedersachsen",
    "wof:name":"Heinz Ollmetzer Heilpraktiker",
    "wof:placetype":"venue"
},
  "geometry": {"coordinates":[9.9702787399,52.3849868774],"type":"Point"}
}