{
  "type": "Feature",
  "properties": {
    "iso:country":"DE",
    "sg:address":"L\u00fcbecker Str. 32",
    "sg:city":"Eutin",
    "sg:phone":"+49 4521/2186",
    "sg:postcode":"23701",
    "sg:province":"Schleswig-Holstein",
    "wof:name":"Dietrich Kermer Rechtsanwalt Und Notar",
    "wof:placetype":"venue"
},
  "geometry": {"coordinates":[10.6173868179,54.1337585449],"type":"Point"}
}