{
  "type": "Feature",
  "properties": {
    "iso:country":"DE",
    "sg:address":"Robert-Bosch-Str. 91",
    "sg:city":"Aalen",
    "sg:phone":"+49 7361/94860",
    "sg:postcode":"73431",
    "sg:province":"Baden-W\u00fcrttemberg",
    "wof:name":"Brabandt Grundbesitz Verwaltungs- Gmbh",
    "wof:placetype":"venue"
},
  "geometry": {"coordinates":[10.0589132309,48.8217887878],"type":"Point"}
}