{
  "type": "Feature",
  "properties": {
    "iso:country":"DE",
    "sg:address":"Wikingerstr. 27",
    "sg:city":"Bielefeld",
    "sg:phone":"+49 521/441098",
    "sg:postcode":"33647",
    "sg:province":"Nordrhein-Westfalen",
    "wof:name":"K. Wermuth Gmbh",
    "wof:placetype":"venue"
},
  "geometry": {"coordinates":[8.5095615387,51.9884338379],"type":"Point"}
}