{
  "type": "Feature",
  "properties": {
    "iso:country":"DE",
    "sg:address":"Eckhardtstr. 23",
    "sg:city":"Duingen",
    "sg:phone":"+49 5185/511",
    "sg:postcode":"31089",
    "sg:province":"Niedersachsen",
    "wof:name":"Thomas Bei\u00dfner",
    "wof:placetype":"venue"
},
  "geometry": {"coordinates":[9.6947832108,52.0078697205],"type":"Point"}
}