{
  "type": "Feature",
  "properties": {
    "iso:country":"DE",
    "sg:address":"Kurt-Blaum-Platz 2",
    "sg:city":"Hanau",
    "sg:phone":"+49 6181/22754",
    "sg:postcode":"63450",
    "sg:province":"Hessen",
    "wof:name":"Medizinischer Dienst Der Krankenversicherung",
    "wof:placetype":"venue"
},
  "geometry": {"coordinates":[8.9232711792,50.1301498413],"type":"Point"}
}