{
  "type": "Feature",
  "properties": {
    "iso:country":"DE",
    "sg:address":"Niederlanggasse 5",
    "sg:city":"Leisnig",
    "sg:phone":"+49 34321/12710",
    "sg:postcode":"04703",
    "sg:province":"Sachsen",
    "wof:name":"Manfred Hingst",
    "wof:placetype":"venue"
},
  "geometry": {"coordinates":[12.9248,51.161011],"type":"Point"}
}