{
  "type": "Feature",
  "properties": {
    "iso:country":"DE",
    "sg:address":"Brandenburger Weg 19",
    "sg:city":"Ingolstadt",
    "sg:phone":"+49 841/940143",
    "sg:postcode":"85053",
    "sg:province":"Bayern",
    "wof:name":"W. Und Gisela Dollt",
    "wof:placetype":"venue"
},
  "geometry": {"coordinates":[11.448927,48.760368],"type":"Point"}
}