{
  "type": "Feature",
  "properties": {
    "iso:country":"DE",
    "sg:address":"Ru\u00dflandweg 34",
    "sg:city":"Friedeburg",
    "sg:phone":"+49 4465/8778",
    "sg:postcode":"26446",
    "sg:province":"Niedersachsen",
    "wof:name":"Zentralheizung- Und L\u00fcftungs- Bau Jan\u00dfen Gmbh",
    "wof:placetype":"venue"
},
  "geometry": {"coordinates":[7.81328,53.45039],"type":"Point"}
}