{
  "type": "Feature",
  "properties": {
    "iso:country":"DE",
    "sg:address":"Dorfstr. 14",
    "sg:city":"Vilsbiburg",
    "sg:postcode":"84137",
    "sg:province":"Bayern",
    "wof:name":"Katholisches Pfarramt",
    "wof:placetype":"venue"
},
  "geometry": {"coordinates":[12.3404350281,48.4809989929],"type":"Point"}
}