{
  "type": "Feature",
  "properties": {
    "iso:country":"DE",
    "sg:address":"H\u00fcgelstr. 6",
    "sg:city":"Ro\u00dftal",
    "sg:phone":"+49 9127/7814",
    "sg:postcode":"90574",
    "sg:province":"Bayern",
    "wof:name":"Fritz B\u00e4r",
    "wof:placetype":"venue"
},
  "geometry": {"coordinates":[10.856232,49.405632],"type":"Point"}
}