{
  "type": "Feature",
  "properties": {
    "iso:country":"DE",
    "sg:address":"S\u00fclldorfer Str 17",
    "sg:city":"Osterweddingen",
    "sg:phone":"+49 39205/69176",
    "sg:postcode":"39171",
    "sg:province":"Sachsen-Anhalt",
    "wof:name":"Elektro Tempelhagen Gmbh",
    "wof:placetype":"venue"
},
  "geometry": {"coordinates":[11.577017,52.038784],"type":"Point"}
}