{
  "type": "Feature",
  "properties": {
    "iso:country":"DE",
    "sg:address":"Florastr. 61",
    "sg:city":"Krefeld",
    "sg:phone":"+49 2151/857777",
    "sg:postcode":"47799",
    "sg:province":"Nordrhein-Westfalen",
    "wof:name":"Dianas Reisen",
    "wof:placetype":"venue"
},
  "geometry": {"coordinates":[6.5810441971,51.335018158],"type":"Point"}
}