{
  "type": "Feature",
  "properties": {
    "iso:country":"DE",
    "sg:address":"Schenkendorfstr. 14",
    "sg:city":"Duisburg",
    "sg:phone":"+49 203/352279",
    "sg:postcode":"47057",
    "sg:province":"Nordrhein-Westfalen",
    "wof:name":"Heinz Dreyer",
    "wof:placetype":"venue"
},
  "geometry": {"coordinates":[6.7906599045,51.423248291],"type":"Point"}
}