{
  "type": "Feature",
  "properties": {
    "iso:country":"DE",
    "sg:address":"Parkstrasse::",
    "sg:city":"Premnitz",
    "sg:phone":"+49 3386/242888",
    "sg:postcode":"14727",
    "sg:province":"Brandenburg",
    "wof:name":"Markische Faser Ag",
    "wof:placetype":"venue"
},
  "geometry": {"coordinates":[12.348125,52.532814],"type":"Point"}
}