{
  "type": "Feature",
  "properties": {
    "iso:country":"DE",
    "sg:address":"Hauptstr. 28",
    "sg:city":"Dahme",
    "sg:phone":"+49 35451/8340",
    "sg:postcode":"15936",
    "sg:province":"Brandenburg",
    "wof:name":"Lutz Van Hal",
    "wof:placetype":"venue"
},
  "geometry": {"coordinates":[13.4295186996,51.8691253662],"type":"Point"}
}