{
  "type": "Feature",
  "properties": {
    "iso:country":"DE",
    "sg:address":"Alte Raiffeisenstr. 1",
    "sg:city":"Passau",
    "sg:phone":"+49 851/83854",
    "sg:postcode":"94036",
    "sg:province":"Bayern",
    "wof:name":"Schmidt Handelsges. Mbh",
    "wof:placetype":"venue"
},
  "geometry": {"coordinates":[13.395707,48.584568],"type":"Point"}
}