{
  "type": "Feature",
  "properties": {
    "iso:country":"DE",
    "sg:address":"Marktplatz 1",
    "sg:city":"Grabenst\u00e4tt",
    "sg:phone":"+49 8661/263",
    "sg:postcode":"83355",
    "sg:province":"Bayern",
    "wof:name":"Ranft",
    "wof:placetype":"venue"
},
  "geometry": {"coordinates":[12.542409,47.843315],"type":"Point"}
}