{
  "type": "Feature",
  "properties": {
    "iso:country":"DE",
    "sg:address":"Magdeburger Str. 54",
    "sg:city":"Haldensleben",
    "sg:phone":"+49 3904/3320",
    "sg:postcode":"39340",
    "sg:province":"Sachsen-Anhalt",
    "wof:name":"Uwe Michael",
    "wof:placetype":"venue"
},
  "geometry": {"coordinates":[11.4172525406,52.2877731323],"type":"Point"}
}