{
  "type": "Feature",
  "properties": {
    "iso:country":"DE",
    "sg:address":"Rosengasse 3",
    "sg:city":"Westerheim",
    "sg:phone":"+49 7333/6427",
    "sg:postcode":"72589",
    "sg:province":"Baden-W\u00fcrttemberg",
    "wof:name":"Goerke",
    "wof:placetype":"venue"
},
  "geometry": {"coordinates":[9.631703,48.512642],"type":"Point"}
}