{
  "type": "Feature",
  "properties": {
    "iso:country":"DE",
    "sg:address":"Walter Werning Str. 9",
    "sg:city":"Bielefeld",
    "sg:phone":"+49 521/926170",
    "sg:postcode":"33699",
    "sg:province":"Nordrhein-Westfalen",
    "wof:name":"Werbeplanen",
    "wof:placetype":"venue"
},
  "geometry": {"coordinates":[8.621366,51.992676],"type":"Point"}
}