{
  "type": "Feature",
  "properties": {
    "iso:country":"DE",
    "sg:address":"N\u00fcrtinger Str. 35",
    "sg:city":"Wolfschlugen",
    "sg:phone":"+49 7022/51480",
    "sg:postcode":"72649",
    "sg:province":"Baden-W\u00fcrttemberg",
    "wof:name":"Klaus Schaal Rechtsanwalt",
    "wof:placetype":"venue"
},
  "geometry": {"coordinates":[9.2936677933,48.6520004272],"type":"Point"}
}