{
  "type": "Feature",
  "properties": {
    "iso:country":"DE",
    "sg:address":"Neue Torstr. 54",
    "sg:city":"Blomberg",
    "sg:phone":"+49 5235/97962",
    "sg:postcode":"32825",
    "sg:province":"Nordrhein-Westfalen",
    "wof:name":"Schuh- Und Sporthaus Meier Inh. Frank Meier E. Kfm.",
    "wof:placetype":"venue"
},
  "geometry": {"coordinates":[9.0920181274,51.9466285706],"type":"Point"}
}