{
  "type": "Feature",
  "properties": {
    "iso:country":"DE",
    "sg:address":"Bremer Str. 13",
    "sg:city":"Vechta",
    "sg:phone":"+49 4441/921880",
    "sg:postcode":"49377",
    "sg:province":"Niedersachsen",
    "wof:name":"Pro Vita",
    "wof:placetype":"venue"
},
  "geometry": {"coordinates":[8.290438,52.732433],"type":"Point"}
}