{
  "type": "Feature",
  "properties": {
    "iso:country":"DE",
    "sg:address":"Hafenstr. 22",
    "sg:city":"Wei\u00dfenthurm",
    "sg:phone":"+49 2637/7029",
    "sg:postcode":"56575",
    "sg:province":"Rheinland-Pfalz",
    "wof:name":"Matousek Gmbh",
    "wof:placetype":"venue"
},
  "geometry": {"coordinates":[7.473279953,50.4107093811],"type":"Point"}
}