{
  "type": "Feature",
  "properties": {
    "iso:country":"DE",
    "sg:address":"Lager Damm 89",
    "sg:city":"H\u00f6rstel",
    "sg:phone":"+49 5454/355",
    "sg:postcode":"48477",
    "sg:province":"Nordrhein-Westfalen",
    "wof:name":"Heinrich Helmig",
    "wof:placetype":"venue"
},
  "geometry": {"coordinates":[7.628381,52.250706],"type":"Point"}
}