{
  "type": "Feature",
  "properties": {
    "iso:country":"DE",
    "sg:address":"R\u00f6merstr. 7",
    "sg:city":"Marktheidenfeld",
    "sg:phone":"+49 9391/2490",
    "sg:postcode":"97828",
    "sg:province":"Bayern",
    "wof:name":"Dipl.-ing. K. Freudenberger Ingenieur Und Architekt",
    "wof:placetype":"venue"
},
  "geometry": {"coordinates":[9.553439,49.82972],"type":"Point"}
}