{
  "type": "Feature",
  "properties": {
    "iso:country":"DE",
    "sg:address":"Kr\u00e4uterbergstr. 15",
    "sg:city":"G\u00fcntersleben",
    "sg:phone":"+49 9365/1025",
    "sg:postcode":"97261",
    "sg:province":"Bayern",
    "wof:name":"Kolb Stieber Und Partner",
    "wof:placetype":"venue"
},
  "geometry": {"coordinates":[9.910687,49.865292],"type":"Point"}
}