{
  "type": "Feature",
  "properties": {
    "iso:country":"DE",
    "sg:address":"Dorfstr. 1",
    "sg:city":"Bochow",
    "sg:phone":"+49 3372/404209",
    "sg:postcode":"14913",
    "sg:province":"Brandenburg",
    "wof:name":"G\u00fcnter Schulze",
    "wof:placetype":"venue"
},
  "geometry": {"coordinates":[13.075406,51.990162],"type":"Point"}
}