{
  "type": "Feature",
  "properties": {
    "iso:country":"DE",
    "sg:address":"Ostenhellweg 35",
    "sg:city":"Dortmund",
    "sg:phone":"+49 231/524461",
    "sg:postcode":"44135",
    "sg:province":"Nordrhein-Westfalen",
    "wof:name":"Dm-drogerie Markt Gmbh & Co. Kg",
    "wof:placetype":"venue"
},
  "geometry": {"coordinates":[7.470425,51.514198],"type":"Point"}
}