{
  "type": "Feature",
  "properties": {
    "iso:country":"DE",
    "sg:address":"Oberstr. 60",
    "sg:city":"Niederzier",
    "sg:phone":"+49 2428/3559",
    "sg:postcode":"52382",
    "sg:province":"Nordrhein-Westfalen",
    "wof:name":"Wilfried Esser",
    "wof:placetype":"venue"
},
  "geometry": {"coordinates":[6.469456,50.885685],"type":"Point"}
}