{
  "type": "Feature",
  "properties": {
    "iso:country":"DE",
    "sg:address":"Hauptstr. 4",
    "sg:city":"Unterpleichfeld",
    "sg:phone":"+49 9367/8602",
    "sg:postcode":"97294",
    "sg:province":"Bayern",
    "wof:name":"Unterpleichfelder Sauerkrautfabrik",
    "wof:placetype":"venue"
},
  "geometry": {"coordinates":[10.0446863174,49.8663825989],"type":"Point"}
}