{
  "type": "Feature",
  "properties": {
    "iso:country":"DE",
    "sg:address":"G\u00f6rlitzer Str. 12",
    "sg:city":"Freilassing",
    "sg:phone":"+49 8654/69060",
    "sg:postcode":"83395",
    "sg:province":"Bayern",
    "wof:name":"Towe Leuchten Gmbh",
    "wof:placetype":"venue"
},
  "geometry": {"coordinates":[12.9605407715,47.8540878296],"type":"Point"}
}