{
  "type": "Feature",
  "properties": {
    "iso:country":"DE",
    "sg:address":"Im Mediapark 2",
    "sg:city":"K\u00f6ln",
    "sg:phone":"+49 221/51006",
    "sg:postcode":"50670",
    "sg:province":"Nordrhein-Westfalen",
    "wof:name":"Bcc Brain Centre Cologne Gmbh",
    "wof:placetype":"venue"
},
  "geometry": {"coordinates":[6.9469261169,50.9483108521],"type":"Point"}
}