{
  "type": "Feature",
  "properties": {
    "iso:country":"DE",
    "sg:address":"Hagenstr. 5",
    "sg:city":"Karlsruhe",
    "sg:phone":"+49 721/845280",
    "sg:postcode":"76185",
    "sg:province":"Baden-W\u00fcrttemberg",
    "wof:name":"Ev. \u00d6ffentliche Bibliothek Der Lukaspfarrei",
    "wof:placetype":"venue"
},
  "geometry": {"coordinates":[8.370869,49.014664],"type":"Point"}
}