{
  "type": "Feature",
  "properties": {
    "iso:country":"DE",
    "sg:address":"Puchower Chaussee 29",
    "sg:city":"Penzlin",
    "sg:phone":"+49 3962/210342",
    "sg:postcode":"17217",
    "sg:province":"Mecklenburg-Vorpommern",
    "wof:name":"Ebert Gmbh",
    "wof:placetype":"venue"
},
  "geometry": {"coordinates":[13.078787,53.508656],"type":"Point"}
}