{
  "type": "Feature",
  "properties": {
    "iso:country":"DE",
    "sg:address":"Am Schroffen 1",
    "sg:city":"Bad Reichenhall",
    "sg:phone":"+49 8651/61521",
    "sg:postcode":"83435",
    "sg:province":"Bayern",
    "wof:name":"Dr. Norbert Hillebrand Wirtschaftspr\u00fcfer Und",
    "wof:placetype":"venue"
},
  "geometry": {"coordinates":[12.8690519333,47.7149963379],"type":"Point"}
}