{
  "type": "Feature",
  "properties": {
    "iso:country":"DE",
    "sg:address":"Eisenberg 5",
    "sg:city":"Wernigerode",
    "sg:phone":"+49 3943/604035",
    "sg:postcode":"38855",
    "sg:province":"Sachsen-Anhalt",
    "wof:name":"P. Schilling",
    "wof:placetype":"venue"
},
  "geometry": {"coordinates":[10.7658452988,51.8322486877],"type":"Point"}
}