{
  "type": "Feature",
  "properties": {
    "iso:country":"DE",
    "sg:address":"Innstr. 20",
    "sg:city":"Simbach",
    "sg:phone":"+49 8571/2486",
    "sg:postcode":"84359",
    "sg:province":"Bayern",
    "wof:name":"Restaurant Oberkrainerst\u00fcberl",
    "wof:placetype":"venue"
},
  "geometry": {"coordinates":[13.0287981033,48.2658233643],"type":"Point"}
}