{
  "type": "Feature",
  "properties": {
    "iso:country":"DE",
    "sg:address":"Sch\u00f6mberger Str. 69",
    "sg:city":"Balingen",
    "sg:phone":"+49 7433/9370",
    "sg:postcode":"72336",
    "sg:province":"Baden-W\u00fcrttemberg",
    "wof:name":"Framatome Connectors Schmid Gmbh",
    "wof:placetype":"venue"
},
  "geometry": {"coordinates":[8.834821701,48.2542877197],"type":"Point"}
}