{
  "type": "Feature",
  "properties": {
    "iso:country":"DE",
    "sg:address":"Roxeler Str. 1",
    "sg:city":"Havixbeck",
    "sg:phone":"+49 2507/1289",
    "sg:postcode":"48329",
    "sg:province":"Nordrhein-Westfalen",
    "wof:name":"Else Annegarn Pension",
    "wof:placetype":"venue"
},
  "geometry": {"coordinates":[7.4692130089,51.995803833],"type":"Point"}
}