{
  "type": "Feature",
  "properties": {
    "iso:country":"DE",
    "sg:address":"Simon-Hoffmann-Str. 3",
    "sg:city":"Merseburg",
    "sg:postcode":"06217",
    "sg:province":"Sachsen-Anhalt",
    "wof:name":"Kramer Gmbh & Co. Kg",
    "wof:placetype":"venue"
},
  "geometry": {"coordinates":[11.9733686447,51.3750572205],"type":"Point"}
}