{
  "type": "Feature",
  "properties": {
    "iso:country":"DE",
    "sg:address":"Amtsstr. 29",
    "sg:city":"Hamburg",
    "sg:phone":"+49 40/6759570",
    "sg:postcode":"22143",
    "sg:province":"Hamburg",
    "wof:name":"F\u00fcrstenberg Institut Gmbh",
    "wof:placetype":"venue"
},
  "geometry": {"coordinates":[10.1597967148,53.6020317078],"type":"Point"}
}