{
  "type": "Feature",
  "properties": {
    "iso:country":"DE",
    "sg:city":"Hamburg",
    "sg:postcode":"21077",
    "sg:province":"Hamburg",
    "wof:name":"Knights-diary",
    "wof:placetype":"venue"
},
  "geometry": {"coordinates":[9.961024,53.439655],"type":"Point"}
}