{
  "type": "Feature",
  "properties": {
    "iso:country":"DE",
    "sg:address":"Cosimastr. 2",
    "sg:city":"M\u00fcnchen",
    "sg:phone":"+49 89/917730",
    "sg:postcode":"81927",
    "sg:province":"Bayern",
    "wof:name":"Christoph Haller Architekt",
    "wof:placetype":"venue"
},
  "geometry": {"coordinates":[11.62983,48.153851],"type":"Point"}
}