{
  "type": "Feature",
  "properties": {
    "iso:country":"DE",
    "sg:address":"Kirchheimer Str. 65",
    "sg:city":"Dettingen",
    "sg:phone":"+49 7021/59821",
    "sg:postcode":"73265",
    "sg:province":"Baden-W\u00fcrttemberg",
    "wof:name":"Bernd G\u00f6tz",
    "wof:placetype":"venue"
},
  "geometry": {"coordinates":[9.4519338608,48.6159553528],"type":"Point"}
}