{
  "type": "Feature",
  "properties": {
    "iso:country":"DE",
    "sg:address":"Fichtenstr. 6",
    "sg:city":"Lachendorf",
    "sg:phone":"+49 5145/2380",
    "sg:postcode":"29331",
    "sg:province":"Niedersachsen",
    "wof:name":"Michael Spohr",
    "wof:placetype":"venue"
},
  "geometry": {"coordinates":[10.2351980209,52.6202316284],"type":"Point"}
}