{
  "type": "Feature",
  "properties": {
    "iso:country":"DE",
    "sg:address":"Wittorfer Ecke 112b",
    "sg:city":"Wittorf",
    "sg:phone":"+49 4133/7221",
    "sg:postcode":"21357",
    "sg:province":"Niedersachsen",
    "wof:name":"Meyers Blumenparadies W. Meyer",
    "wof:placetype":"venue"
},
  "geometry": {"coordinates":[10.355383,53.327652],"type":"Point"}
}