{
  "type": "Feature",
  "properties": {
    "iso:country":"DE",
    "sg:address":"Siemensstr. 8",
    "sg:city":"B\u00fchl",
    "sg:phone":"+49 7223/80930",
    "sg:postcode":"77815",
    "sg:province":"Baden-W\u00fcrttemberg",
    "wof:name":"Dieter Wurm Architekt",
    "wof:placetype":"venue"
},
  "geometry": {"coordinates":[8.123884,48.695404],"type":"Point"}
}