{
  "type": "Feature",
  "properties": {
    "iso:country":"DE",
    "sg:address":"Sc hulstr. 16",
    "sg:city":"Landstuhl",
    "sg:phone":"+49 6371/912260",
    "sg:postcode":"66849",
    "sg:province":"Rheinland-Pfalz",
    "wof:name":"Alt-montagebau",
    "wof:placetype":"venue"
},
  "geometry": {"coordinates":[7.568212986,49.4090881348],"type":"Point"}
}