{
  "type": "Feature",
  "properties": {
    "iso:country":"DE",
    "sg:address":"Grube-Karl-Str. 6",
    "sg:city":"Geislingen",
    "sg:phone":"+49 7331/63133",
    "sg:postcode":"73312",
    "sg:province":"Baden-W\u00fcrttemberg",
    "wof:name":"Sportgastst\u00e4tte Gl\u00fcck Auf",
    "wof:placetype":"venue"
},
  "geometry": {"coordinates":[9.8291196823,48.6244392395],"type":"Point"}
}