{
  "type": "Feature",
  "properties": {
    "iso:country":"DE",
    "sg:address":"Auf der H\u00f6rn 38",
    "sg:city":"Aachen",
    "sg:phone":"+49 241/8793652",
    "sg:postcode":"52074",
    "sg:province":"Nordrhein-Westfalen",
    "wof:name":"Pumatec Gmbh & Co. Kg",
    "wof:placetype":"venue"
},
  "geometry": {"coordinates":[6.05465,50.779655],"type":"Point"}
}