{
  "type": "Feature",
  "properties": {
    "iso:country":"DE",
    "sg:address":"S\u00fcdendstr. 6",
    "sg:city":"Klettgau",
    "sg:phone":"+49 7742/4151",
    "sg:postcode":"79771",
    "sg:province":"Baden-W\u00fcrttemberg",
    "wof:name":"V. Herz",
    "wof:placetype":"venue"
},
  "geometry": {"coordinates":[8.4157390594,47.6222877502],"type":"Point"}
}