{
  "type": "Feature",
  "properties": {
    "iso:country":"DE",
    "sg:address":"Lisa-Tetzner-Str. 22",
    "sg:city":"Zittau",
    "sg:phone":"+49 3583/683063",
    "sg:postcode":"02763",
    "sg:province":"Sachsen",
    "wof:name":"Schwimmhalle",
    "wof:placetype":"venue"
},
  "geometry": {"coordinates":[14.8027009964,50.8858947754],"type":"Point"}
}