{
  "type": "Feature",
  "properties": {
    "iso:country":"DE",
    "sg:address":"Nei\u00dfestr. 4",
    "sg:city":"Scharbeutz",
    "sg:postcode":"23683",
    "sg:province":"Schleswig-Holstein",
    "wof:name":"Delago-vertriebs Gmbh",
    "wof:placetype":"venue"
},
  "geometry": {"coordinates":[10.736812,54.021721],"type":"Point"}
}