{
  "type": "Feature",
  "properties": {
    "iso:country":"DE",
    "sg:address":"Fleyer Str. 101",
    "sg:city":"Hagen",
    "sg:phone":"+49 2331/870744",
    "sg:postcode":"58097",
    "sg:province":"Nordrhein-Westfalen",
    "wof:name":"Rainer Teichert",
    "wof:placetype":"venue"
},
  "geometry": {"coordinates":[7.4806661606,51.3672447205],"type":"Point"}
}