{
  "type": "Feature",
  "properties": {
    "iso:country":"DE",
    "sg:address":"Robert-Koch-Str 43",
    "sg:city":"Mainz",
    "sg:phone":"+49 6131/958590",
    "sg:postcode":"55129",
    "sg:province":"Rheinland-Pfalz",
    "wof:name":"Nta Mainz Gmbh",
    "wof:placetype":"venue"
},
  "geometry": {"coordinates":[8.2579603195,49.957447052],"type":"Point"}
}