{
  "type": "Feature",
  "properties": {
    "iso:country":"DE",
    "sg:address":"Zum Eulenberg 1",
    "sg:city":"Ahorn",
    "sg:phone":"+49 7930/6498",
    "sg:postcode":"74744",
    "sg:province":"Baden-W\u00fcrttemberg",
    "wof:name":"Hilde Czasch",
    "wof:placetype":"venue"
},
  "geometry": {"coordinates":[9.573974,49.460449],"type":"Point"}
}