{
  "type": "Feature",
  "properties": {
    "iso:country":"DE",
    "sg:address":"Bielefelder Str. 3",
    "sg:city":"Hilter",
    "sg:phone":"+49 5424/23200",
    "sg:postcode":"49176",
    "sg:province":"Niedersachsen",
    "wof:name":"Tepe",
    "wof:placetype":"venue"
},
  "geometry": {"coordinates":[8.146821022,52.1385536194],"type":"Point"}
}