{
  "type": "Feature",
  "properties": {
    "iso:country":"DE",
    "sg:address":"Schlehenkamp 11",
    "sg:city":"Kiel",
    "sg:phone":"+49 431/782675",
    "sg:postcode":"24146",
    "sg:province":"Schleswig-Holstein",
    "wof:name":"Michael Hofmann",
    "wof:placetype":"venue"
},
  "geometry": {"coordinates":[10.170879364,54.2940063477],"type":"Point"}
}