{
  "type": "Feature",
  "properties": {
    "iso:country":"DE",
    "sg:address":"Am Wasserturm 11 a",
    "sg:city":"Halle",
    "sg:phone":"+49 345/2028790",
    "sg:postcode":"06114",
    "sg:province":"Sachsen-Anhalt",
    "wof:name":"Christina K\u00e4mpf",
    "wof:placetype":"venue"
},
  "geometry": {"coordinates":[11.982835,51.492977],"type":"Point"}
}