{
  "type": "Feature",
  "properties": {
    "iso:country":"DE",
    "sg:address":"Hauptstr. 54",
    "sg:city":"Meckenheim",
    "sg:phone":"+49 6326/5959",
    "sg:postcode":"67149",
    "sg:province":"Rheinland-Pfalz",
    "wof:name":"Cafe Pub Geheimrat",
    "wof:placetype":"venue"
},
  "geometry": {"coordinates":[8.23851,49.404583],"type":"Point"}
}