{
  "type": "Feature",
  "properties": {
    "iso:country":"DE",
    "sg:address":"Gerhart-Hauptmann-Weg 22",
    "sg:city":"Schw\u00e4bisch Gm\u00fcnd",
    "sg:postcode":"73525",
    "sg:province":"Baden-W\u00fcrttemberg",
    "wof:name":"Ssw Schwimmbad-sauna- Und Wellnessbedarf Gmbh",
    "wof:placetype":"venue"
},
  "geometry": {"coordinates":[9.7707300186,48.7849311829],"type":"Point"}
}