{
  "type": "Feature",
  "properties": {
    "iso:country":"DE",
    "sg:address":"Jungfernstieg 30",
    "sg:city":"Hamburg",
    "sg:postcode":"20354",
    "sg:province":"Hamburg",
    "wof:name":"Jungfernstieg 30 Erste Verwaltungsges. Mbh",
    "wof:placetype":"venue"
},
  "geometry": {"coordinates":[9.9911661148,53.5540618896],"type":"Point"}
}