{
  "type": "Feature",
  "properties": {
    "iso:country":"DE",
    "sg:address":"Gottlieb-Daimler-Str. 6",
    "sg:city":"Sulz",
    "sg:phone":"+49 7454/96800",
    "sg:postcode":"72172",
    "sg:province":"Baden-W\u00fcrttemberg",
    "wof:name":"Edelstahlservice Ges. Mbh",
    "wof:placetype":"venue"
},
  "geometry": {"coordinates":[8.635249,48.351231],"type":"Point"}
}