{
  "type": "Feature",
  "properties": {
    "iso:country":"DE",
    "sg:address":"Paulinenstr. 10",
    "sg:city":"Friedrichshafen",
    "sg:phone":"+49 7541/22380",
    "sg:postcode":"88046",
    "sg:province":"Baden-W\u00fcrttemberg",
    "wof:name":"Kino-center Erwin Lohner Verwaltungs-gmbh",
    "wof:placetype":"venue"
},
  "geometry": {"coordinates":[9.482523,47.653557],"type":"Point"}
}