{
  "type": "Feature",
  "properties": {
    "iso:country":"DE",
    "sg:address":"Berliner Str. 18 d",
    "sg:city":"Herdecke",
    "sg:phone":"+49 2330/2409",
    "sg:postcode":"58313",
    "sg:province":"Nordrhein-Westfalen",
    "wof:name":"Bauunternehmung Sch\u00f6ne Gmbh",
    "wof:placetype":"venue"
},
  "geometry": {"coordinates":[7.4280848503,51.4111328125],"type":"Point"}
}