{
  "type": "Feature",
  "properties": {
    "iso:country":"DE",
    "sg:address":"Henry-Dunant-Str 7",
    "sg:city":"Greven",
    "sg:phone":"+49 2571/952323",
    "sg:postcode":"48268",
    "sg:province":"Nordrhein-Westfalen",
    "wof:name":"K\u00e4mmerling Gmbh",
    "wof:placetype":"venue"
},
  "geometry": {"coordinates":[7.617168,52.103878],"type":"Point"}
}