{
  "type": "Feature",
  "properties": {
    "iso:country":"DE",
    "sg:address":"Kirchdorfer Str. 2",
    "sg:city":"Bruckm\u00fchl",
    "sg:phone":"+49 8062/78388",
    "sg:postcode":"83052",
    "sg:province":"Bayern",
    "wof:name":"Edeka-markt",
    "wof:placetype":"venue"
},
  "geometry": {"coordinates":[11.9154834747,47.8826751709],"type":"Point"}
}