{
  "type": "Feature",
  "properties": {
    "iso:country":"DE",
    "sg:address":"Poppenstr. 3",
    "sg:city":"Ingolstadt",
    "sg:phone":"+49 841/34682",
    "sg:postcode":"85049",
    "sg:province":"Bayern",
    "wof:name":"Orgel-paradies Vertriebs-gmbh",
    "wof:placetype":"venue"
},
  "geometry": {"coordinates":[11.4206209183,48.7635612488],"type":"Point"}
}