{
  "type": "Feature",
  "properties": {
    "iso:country":"DE",
    "sg:address":"An der Stadtkirche 2",
    "sg:city":"Aalen",
    "sg:phone":"+49 7361/68299",
    "sg:postcode":"73430",
    "sg:province":"Baden-W\u00fcrttemberg",
    "wof:name":"Inge Drabeck",
    "wof:placetype":"venue"
},
  "geometry": {"coordinates":[10.093648,48.837772],"type":"Point"}
}