{
  "type": "Feature",
  "properties": {
    "iso:country":"DE",
    "sg:address":"An der Fahrt 8-10",
    "sg:city":"Eschweiler",
    "sg:phone":"+49 2403/78780",
    "sg:postcode":"52249",
    "sg:province":"Nordrhein-Westfalen",
    "wof:name":"Jc Goskowitz Alten- Und Pflegeheim Gmbh",
    "wof:placetype":"venue"
},
  "geometry": {"coordinates":[6.228355,50.841949],"type":"Point"}
}