{
  "type": "Feature",
  "properties": {
    "iso:country":"DE",
    "sg:address":"Gro\u00df Lessen 24",
    "sg:city":"Sulingen",
    "sg:phone":"+49 4271/4685",
    "sg:postcode":"27232",
    "sg:province":"Niedersachsen",
    "wof:name":"Manfred Cohrs",
    "wof:placetype":"venue"
},
  "geometry": {"coordinates":[8.700081,52.684025],"type":"Point"}
}