{
  "type": "Feature",
  "properties": {
    "iso:country":"DE",
    "sg:address":"Gartenstr. 82-84",
    "sg:city":"Karlsruhe",
    "sg:phone":"+49 721/840020",
    "sg:postcode":"76135",
    "sg:province":"Baden-W\u00fcrttemberg",
    "wof:name":"C & L Deutsche Revision Ag",
    "wof:placetype":"venue"
},
  "geometry": {"coordinates":[8.3825588226,49.0045852661],"type":"Point"}
}