{
  "type": "Feature",
  "properties": {
    "iso:country":"DE",
    "sg:address":"Danziger Str. 3",
    "sg:city":"Bad K\u00f6nig",
    "sg:phone":"+49 6063/577790",
    "sg:postcode":"64732",
    "sg:province":"Hessen",
    "wof:name":"Kunkelmann Grundst\u00fccks- Verwaltungsges. Mbh & Co. Kg",
    "wof:placetype":"venue"
},
  "geometry": {"coordinates":[9.001953125,49.7503318787],"type":"Point"}
}