{
  "type": "Feature",
  "properties": {
    "iso:country":"DE",
    "sg:address":"Kirchdorfer Str. 5",
    "sg:city":"Barsinghausen",
    "sg:phone":"+49 5105/64860",
    "sg:postcode":"30890",
    "sg:province":"Niedersachsen",
    "wof:name":"Karsten D\u00fcnte Ingenieur",
    "wof:placetype":"venue"
},
  "geometry": {"coordinates":[9.48133564,52.3005485535],"type":"Point"}
}