{
  "type": "Feature",
  "properties": {
    "iso:country":"DE",
    "sg:address":"M\u00fchlschlag",
    "sg:city":"Kallm\u00fcnz",
    "sg:phone":"+49 9473/8737",
    "sg:postcode":"93183",
    "sg:province":"Bayern",
    "wof:name":"Bergst\u00fcberl",
    "wof:placetype":"venue"
},
  "geometry": {"coordinates":[11.9661102295,49.1320381165],"type":"Point"}
}