{
  "type": "Feature",
  "properties": {
    "iso:country":"DE",
    "sg:address":"Vogelsangstr. 18",
    "sg:city":"Weil im Sch\u00f6nbuch",
    "sg:phone":"+49 7157/62962",
    "sg:postcode":"71093",
    "sg:province":"Baden-W\u00fcrttemberg",
    "wof:name":"Verm\u00f6gensverwaltungsges. Philipp Scheuermann Mbh",
    "wof:placetype":"venue"
},
  "geometry": {"coordinates":[9.0602359772,48.6264533997],"type":"Point"}
}