{
  "type": "Feature",
  "properties": {
    "iso:country":"DE",
    "sg:address":"Blumenstr. 36",
    "sg:city":"Offenbach",
    "sg:phone":"+49 69/831196",
    "sg:postcode":"63069",
    "sg:province":"Hessen",
    "wof:name":"J. Salzer Ingenieur",
    "wof:placetype":"venue"
},
  "geometry": {"coordinates":[8.7471380234,50.0912017822],"type":"Point"}
}