{
  "type": "Feature",
  "properties": {
    "iso:country":"DE",
    "sg:address":"Stettiner Str. 21",
    "sg:city":"Bad Windsheim",
    "sg:phone":"+49 9841/66000",
    "sg:postcode":"91438",
    "sg:province":"Bayern",
    "wof:name":"Tbg Transportbeton Gesellschaft Eck-beton",
    "wof:placetype":"venue"
},
  "geometry": {"coordinates":[10.405508,49.501709],"type":"Point"}
}