{
  "type": "Feature",
  "properties": {
    "iso:country":"DE",
    "sg:address":"Belzbuckel",
    "sg:city":"Hirschberg",
    "sg:phone":"+49 6201/56646",
    "sg:postcode":"69493",
    "sg:province":"Baden-W\u00fcrttemberg",
    "wof:name":"Joachim Neumann",
    "wof:placetype":"venue"
},
  "geometry": {"coordinates":[8.672158,49.511047],"type":"Point"}
}