{
  "type": "Feature",
  "properties": {
    "iso:country":"DE",
    "sg:address":"Sperberh\u00f6he 23",
    "sg:city":"Arnsberg",
    "sg:phone":"+49 2932/33665",
    "sg:postcode":"59759",
    "sg:province":"Nordrhein-Westfalen",
    "wof:name":"Friedhelm Schirp",
    "wof:placetype":"venue"
},
  "geometry": {"coordinates":[7.9795069695,51.430683136],"type":"Point"}
}