{
  "type": "Feature",
  "properties": {
    "iso:country":"DE",
    "sg:address":"Wolfs\u00e4gerweg 31",
    "sg:city":"Fischbach",
    "sg:phone":"+49 6393/1738",
    "sg:postcode":"66996",
    "sg:province":"Rheinland-Pfalz",
    "wof:name":"Stefanie Vavriniak",
    "wof:placetype":"venue"
},
  "geometry": {"coordinates":[7.708175,49.091541],"type":"Point"}
}