{
  "type": "Feature",
  "properties": {
    "iso:country":"DE",
    "sg:address":"Mittelh\u00e4user Str. 41",
    "sg:city":"Erfurt",
    "sg:phone":"+49 361/7396200",
    "sg:postcode":"99091",
    "sg:province":"Th\u00fcringen",
    "wof:name":"Kraftverkehrsgesellschaft Erfurt Mbh",
    "wof:placetype":"venue"
},
  "geometry": {"coordinates":[11.005964,51.031849],"type":"Point"}
}