{
  "type": "Feature",
  "properties": {
    "iso:country":"DE",
    "sg:address":"Kerstingstr. 14",
    "sg:city":"Hannover",
    "sg:phone":"+49 511/814141",
    "sg:postcode":"30173",
    "sg:province":"Niedersachsen",
    "wof:name":"Dieter Illgen",
    "wof:placetype":"venue"
},
  "geometry": {"coordinates":[9.771021,52.36414],"type":"Point"}
}