{
  "type": "Feature",
  "properties": {
    "iso:country":"DE",
    "sg:address":"Harnischweg 10",
    "sg:city":"Berlin",
    "sg:phone":"+49 30/6518445",
    "sg:postcode":"12555",
    "sg:province":"Berlin",
    "wof:name":"H\u00e4mmerling-zimmerei Gmbh",
    "wof:placetype":"venue"
},
  "geometry": {"coordinates":[13.5621976852,52.4522247314],"type":"Point"}
}