{
  "type": "Feature",
  "properties": {
    "iso:country":"DE",
    "sg:address":"Haller Str. 30",
    "sg:city":"Schw\u00e4bisch Hall",
    "sg:postcode":"74523",
    "sg:province":"Baden-W\u00fcrttemberg",
    "wof:name":"Hem Systemhaus Ag",
    "wof:placetype":"venue"
},
  "geometry": {"coordinates":[9.7460603714,49.1133117676],"type":"Point"}
}