{
  "type": "Feature",
  "properties": {
    "iso:country":"DE",
    "sg:address":"Ladestr. 3-3a",
    "sg:city":"Bremen",
    "sg:postcode":"28197",
    "sg:province":"Bremen",
    "wof:name":"Asi Automation F\u00fcr Schiff Und Industrie Gmbh",
    "wof:placetype":"venue"
},
  "geometry": {"coordinates":[8.780354,53.078651],"type":"Point"}
}