{
  "type": "Feature",
  "properties": {
    "iso:country":"DE",
    "sg:address":"Hauptstr. 138",
    "sg:city":"Waldfischbach-Burgalben",
    "sg:phone":"+49 6333/5040",
    "sg:postcode":"67714",
    "sg:province":"Rheinland-Pfalz",
    "wof:name":"Gerhard Palm",
    "wof:placetype":"venue"
},
  "geometry": {"coordinates":[7.643874,49.281406],"type":"Point"}
}