{
  "type": "Feature",
  "properties": {
    "iso:country":"DE",
    "sg:address":"Kirchstr. 8",
    "sg:city":"Forst",
    "sg:phone":"+49 7251/300896",
    "sg:postcode":"76694",
    "sg:province":"Baden-W\u00fcrttemberg",
    "wof:name":"Gasthaus L\u00f6wen",
    "wof:placetype":"venue"
},
  "geometry": {"coordinates":[8.5864543915,49.1529846191],"type":"Point"}
}