{
  "type": "Feature",
  "properties": {
    "iso:country":"DE",
    "sg:address":"Fahrenberg 27",
    "sg:city":"Barsb\u00fcttel",
    "sg:postcode":"22885",
    "sg:province":"Schleswig-Holstein",
    "wof:name":"Graphik & Satztechnik Giesecke",
    "wof:placetype":"venue"
},
  "geometry": {"coordinates":[10.190679,53.574856],"type":"Point"}
}