{
  "type": "Feature",
  "properties": {
    "iso:country":"DE",
    "sg:address":"Meboldstr. 10",
    "sg:city":"Sulz",
    "sg:phone":"+49 7454/96010",
    "sg:postcode":"72172",
    "sg:province":"Baden-W\u00fcrttemberg",
    "wof:name":"Kitzlinger Gmbh",
    "wof:placetype":"venue"
},
  "geometry": {"coordinates":[8.631633,48.350407],"type":"Point"}
}