{
  "type": "Feature",
  "properties": {
    "iso:country":"DE",
    "sg:address":"Bahnhofstr. 19",
    "sg:city":"Althengstett",
    "sg:phone":"+49 7051/6886",
    "sg:postcode":"75382",
    "sg:province":"Baden-W\u00fcrttemberg",
    "wof:name":"Sch\u00f6nheitsinsel Jasmin Eisele",
    "wof:placetype":"venue"
},
  "geometry": {"coordinates":[8.797815,48.725269],"type":"Point"}
}