{
  "type": "Feature",
  "properties": {
    "iso:country":"DE",
    "sg:address":"Boenster Str. 16",
    "sg:city":"Bunde",
    "sg:phone":"+49 4953/493",
    "sg:postcode":"26831",
    "sg:province":"Niedersachsen",
    "wof:name":"Wolf-dietrich Sass Architekt Und",
    "wof:placetype":"venue"
},
  "geometry": {"coordinates":[7.2659797668,53.1806983948],"type":"Point"}
}