{
  "type": "Feature",
  "properties": {
    "iso:country":"DE",
    "sg:address":"Pirmasenser Str. 54",
    "sg:city":"Dahn",
    "sg:postcode":"66994",
    "sg:province":"Rheinland-Pfalz",
    "wof:name":"Eurospar",
    "wof:placetype":"venue"
},
  "geometry": {"coordinates":[7.7730231285,49.1541900635],"type":"Point"}
}