{
  "type": "Feature",
  "properties": {
    "iso:country":"DE",
    "sg:address":"Krakauer Str. 9",
    "sg:city":"Markranst\u00e4dt",
    "sg:phone":"+49 34205/88574",
    "sg:postcode":"04420",
    "sg:province":"Sachsen",
    "wof:name":"Buchdruckerei K\u00f6hler",
    "wof:placetype":"venue"
},
  "geometry": {"coordinates":[12.219093,51.299507],"type":"Point"}
}