{
  "type": "Feature",
  "properties": {
    "iso:country":"DE",
    "sg:address":"Latzower Str. 1",
    "sg:city":"Rubenow",
    "sg:postcode":"17509",
    "sg:province":"Mecklenburg-Vorpommern",
    "wof:name":"Zln Zwischenlager Nord Gmbh",
    "wof:placetype":"venue"
},
  "geometry": {"coordinates":[13.61007,54.134483],"type":"Point"}
}