{
  "type": "Feature",
  "properties": {
    "iso:country":"DE",
    "sg:address":"Kirchstr. 22",
    "sg:city":"Bad Bertrich",
    "sg:phone":"+49 2674/264",
    "sg:postcode":"56864",
    "sg:province":"Rheinland-Pfalz",
    "wof:name":"Herm. Reinhard",
    "wof:placetype":"venue"
},
  "geometry": {"coordinates":[7.036929,50.072678],"type":"Point"}
}