{
  "type": "Feature",
  "properties": {
    "iso:country":"DE",
    "sg:address":"Keltenring 17",
    "sg:city":"Oberhaching",
    "sg:postcode":"82041",
    "sg:province":"Bayern",
    "wof:name":"Bfi Vermittlungsges. F. Bank- Produkte U. Finanzdienstleist.",
    "wof:placetype":"venue"
},
  "geometry": {"coordinates":[11.5891227722,48.0336608887],"type":"Point"}
}