{
  "type": "Feature",
  "properties": {
    "iso:country":"DE",
    "sg:address":"Heinder Str. 11",
    "sg:city":"Bad Salzdetfurth",
    "sg:phone":"+49 5064/1617",
    "sg:postcode":"31162",
    "sg:province":"Niedersachsen",
    "wof:name":"Mbv Metallbau- Und -verarbeitungs Gmbh",
    "wof:placetype":"venue"
},
  "geometry": {"coordinates":[10.025422,52.097897],"type":"Point"}
}