{
  "type": "Feature",
  "properties": {
    "iso:country":"DE",
    "sg:address":"Hauptstr. 44",
    "sg:city":"Hofheim",
    "sg:phone":"+49 6192/5646",
    "sg:postcode":"65719",
    "sg:province":"Hessen",
    "wof:name":"Ursula Weissm\u00fcller",
    "wof:placetype":"venue"
},
  "geometry": {"coordinates":[8.444415,50.087475],"type":"Point"}
}