{
  "type": "Feature",
  "properties": {
    "iso:country":"DE",
    "sg:address":"Dorfstra\u00dfe 51",
    "sg:city":"Gr\u00e4fensteinberg",
    "sg:phone":"+49 9837/96827",
    "sg:postcode":"91729",
    "sg:province":"Bayern",
    "wof:name":"Job Fit Training Peter Froeba",
    "wof:placetype":"venue"
},
  "geometry": {"coordinates":[10.8111000061,49.1518440247],"type":"Point"}
}