{
  "type": "Feature",
  "properties": {
    "iso:country":"DE",
    "sg:address":"Breslauer Str. 1",
    "sg:city":"Geiselh\u00f6ring",
    "sg:phone":"+49 9423/902111",
    "sg:postcode":"94333",
    "sg:province":"Bayern",
    "wof:name":"Penny-markt",
    "wof:placetype":"venue"
},
  "geometry": {"coordinates":[12.4005441666,48.8304977417],"type":"Point"}
}