{
  "type": "Feature",
  "properties": {
    "iso:country":"DE",
    "sg:address":"Karl-Marx-Str. 34",
    "sg:city":"Leipzig",
    "sg:phone":"+49 341/5213851",
    "sg:postcode":"04158",
    "sg:province":"Sachsen",
    "wof:name":"Kurt Wolf",
    "wof:placetype":"venue"
},
  "geometry": {"coordinates":[12.378218,51.396339],"type":"Point"}
}