{
  "type": "Feature",
  "properties": {
    "iso:country":"DE",
    "sg:address":"Wichernstr. 16",
    "sg:city":"Neuhofen",
    "sg:phone":"+49 6236/55619",
    "sg:postcode":"67141",
    "sg:province":"Rheinland-Pfalz",
    "wof:name":"Walter Fischer",
    "wof:placetype":"venue"
},
  "geometry": {"coordinates":[8.431644,49.416576],"type":"Point"}
}