{
  "type": "Feature",
  "properties": {
    "iso:country":"DE",
    "sg:address":"Altk\u00f6nigstr. 41",
    "sg:city":"K\u00f6nigstein",
    "sg:postcode":"61462",
    "sg:province":"Hessen",
    "wof:name":"Akv Altk\u00f6nig-verwaltungs Gmbh",
    "wof:placetype":"venue"
},
  "geometry": {"coordinates":[8.467116,50.194107],"type":"Point"}
}