{
  "type": "Feature",
  "properties": {
    "iso:country":"DE",
    "sg:address":"Lindenstr. 10",
    "sg:city":"Hartheim",
    "sg:phone":"+49 4976/333472",
    "sg:postcode":"79258",
    "sg:province":"Baden-W\u00fcrttemberg",
    "wof:name":"Hubert Scherer",
    "wof:placetype":"venue"
},
  "geometry": {"coordinates":[7.622551,47.924679],"type":"Point"}
}