{
  "type": "Feature",
  "properties": {
    "iso:country":"DE",
    "sg:address":"Jungfrauenthal 53",
    "sg:city":"Hamburg",
    "sg:phone":"+49 40/418742",
    "sg:postcode":"20149",
    "sg:province":"Hamburg",
    "wof:name":"Silver Cine Filmverleih Th. Bronner",
    "wof:placetype":"venue"
},
  "geometry": {"coordinates":[9.9825201035,53.5811653137],"type":"Point"}
}