{
  "type": "Feature",
  "properties": {
    "iso:country":"DE",
    "sg:address":"Oldenfelder Str. 62a",
    "sg:city":"Hamburg",
    "sg:phone":"+49 40/6782897",
    "sg:postcode":"22143",
    "sg:province":"Hamburg",
    "wof:name":"Paco Paschelke & Co.",
    "wof:placetype":"venue"
},
  "geometry": {"coordinates":[10.1563262939,53.6135292053],"type":"Point"}
}