{
  "type": "Feature",
  "properties": {
    "iso:country":"DE",
    "sg:address":"W\u00fcrzburger Str. 18",
    "sg:city":"Rottendorf",
    "sg:phone":"+49 9302/90950",
    "sg:postcode":"97228",
    "sg:province":"Bayern",
    "wof:name":"Ida Hoeller",
    "wof:placetype":"venue"
},
  "geometry": {"coordinates":[10.0240459442,49.7905235291],"type":"Point"}
}