{
  "type": "Feature",
  "properties": {
    "iso:country":"DE",
    "sg:address":"Lederergasse 15",
    "sg:city":"Passau",
    "sg:phone":"+49 851/35187",
    "sg:postcode":"94032",
    "sg:province":"Bayern",
    "wof:name":"Klaus Bock Ingenieurb\u00fcro",
    "wof:placetype":"venue"
},
  "geometry": {"coordinates":[13.4643659592,48.5706100464],"type":"Point"}
}