{
  "type": "Feature",
  "properties": {
    "iso:country":"DE",
    "sg:address":"Ehinger Str. 14",
    "sg:city":"Schemmerhofen",
    "sg:phone":"+49 7356/689",
    "sg:postcode":"88433",
    "sg:province":"Baden-W\u00fcrttemberg",
    "wof:name":"Karl Funk",
    "wof:placetype":"venue"
},
  "geometry": {"coordinates":[9.7720327377,48.2002868652],"type":"Point"}
}