{
  "type": "Feature",
  "properties": {
    "iso:country":"DE",
    "sg:address":"Bahnhofsallee 13",
    "sg:city":"Hildesheim",
    "sg:phone":"+49 5121/35679",
    "sg:postcode":"31134",
    "sg:province":"Niedersachsen",
    "wof:name":"Schwetje",
    "wof:placetype":"venue"
},
  "geometry": {"coordinates":[9.954377,52.157185],"type":"Point"}
}