{
  "type": "Feature",
  "properties": {
    "iso:country":"DE",
    "sg:address":"Immenweg 2",
    "sg:city":"Rietberg",
    "sg:phone":"+49 2944/58061",
    "sg:postcode":"33397",
    "sg:province":"Nordrhein-Westfalen",
    "wof:name":"Kaba Gallensch\u00fctz Gmbh",
    "wof:placetype":"venue"
},
  "geometry": {"coordinates":[8.393864,51.756428],"type":"Point"}
}