{
  "type": "Feature",
  "properties": {
    "iso:country":"DE",
    "sg:address":"Beckumer Str. 124",
    "sg:city":"Ahlen",
    "sg:postcode":"59229",
    "sg:province":"Nordrhein-Westfalen",
    "wof:name":"Iut Industrie- Und Umwelt- Technik Gmbh",
    "wof:placetype":"venue"
},
  "geometry": {"coordinates":[7.913286,51.764694],"type":"Point"}
}