{
  "type": "Feature",
  "properties": {
    "iso:country":"DE",
    "sg:address":"Markt 25",
    "sg:city":"Schwaan",
    "sg:phone":"+49 3844/1484",
    "sg:postcode":"18258",
    "sg:province":"Mecklenburg-Vorpommern",
    "wof:name":"Warnow-cafe Gastst\u00e4tte Cafe",
    "wof:placetype":"venue"
},
  "geometry": {"coordinates":[12.107408,53.939472],"type":"Point"}
}