{
  "type": "Feature",
  "properties": {
    "iso:country":"DE",
    "sg:address":"Steeler Str. 149",
    "sg:city":"Essen",
    "sg:phone":"+49 201/284346",
    "sg:postcode":"45138",
    "sg:province":"Nordrhein-Westfalen",
    "wof:name":"Gr\u00fcne's Leihh\u00e4user",
    "wof:placetype":"venue"
},
  "geometry": {"coordinates":[7.031399,51.450741],"type":"Point"}
}