{
  "type": "Feature",
  "properties": {
    "iso:country":"DE",
    "sg:address":"Kellereistra\u00dfe 12",
    "sg:city":"Osterburken",
    "sg:postcode":"74706",
    "sg:province":"Baden-W\u00fcrttemberg",
    "wof:name":"Jobs Bei Robert Zipf - Haupt- Oder Nebenberuflich:",
    "wof:placetype":"venue"
},
  "geometry": {"coordinates":[9.426763,49.429901],"type":"Point"}
}