{
  "type": "Feature",
  "properties": {
    "iso:country":"DE",
    "sg:address":"M\u00fcllerstr. 13-15",
    "sg:city":"Schwerin",
    "sg:phone":"+49 385/712149",
    "sg:postcode":"19053",
    "sg:province":"Mecklenburg-Vorpommern",
    "wof:name":"Apotheke M\u00fcllerstra\u00dfe Inh. Thomas Hindelang",
    "wof:placetype":"venue"
},
  "geometry": {"coordinates":[11.401331,53.628132],"type":"Point"}
}