{
  "type": "Feature",
  "properties": {
    "iso:country":"DE",
    "sg:address":"Hesselteicher Str. 72",
    "sg:city":"Harsewinkel",
    "sg:phone":"+49 5247/5171",
    "sg:postcode":"33428",
    "sg:province":"Nordrhein-Westfalen",
    "wof:name":"Omniform Ludwig Verwaltungs-gmbh",
    "wof:placetype":"venue"
},
  "geometry": {"coordinates":[8.228105,51.971603],"type":"Point"}
}