{
  "type": "Feature",
  "properties": {
    "iso:country":"DE",
    "sg:address":"Wielandstr. 22",
    "sg:city":"Neumarkt",
    "sg:phone":"+49 9181/42247",
    "sg:postcode":"92318",
    "sg:province":"Bayern",
    "wof:name":"Karl Grasruck Ingenieur",
    "wof:placetype":"venue"
},
  "geometry": {"coordinates":[11.4832696915,49.2881965637],"type":"Point"}
}