{
  "type": "Feature",
  "properties": {
    "iso:country":"DE",
    "sg:address":"Ringstr. 26",
    "sg:city":"Oberndorf",
    "sg:phone":"+49 7423/2407",
    "sg:postcode":"78727",
    "sg:province":"Baden-W\u00fcrttemberg",
    "wof:name":"Gastst\u00e4tte Albblick",
    "wof:placetype":"venue"
},
  "geometry": {"coordinates":[8.5535984039,48.2937583923],"type":"Point"}
}