{
  "type": "Feature",
  "properties": {
    "iso:country":"DE",
    "sg:address":"Gr\u00fcner J\u00e4ger 29",
    "sg:city":"Hassel",
    "sg:phone":"+49 4254/93210",
    "sg:postcode":"27324",
    "sg:province":"Niedersachsen",
    "wof:name":"Manfred Blind Gmbh",
    "wof:placetype":"venue"
},
  "geometry": {"coordinates":[9.1951770782,52.8062934875],"type":"Point"}
}