{
  "type": "Feature",
  "properties": {
    "iso:country":"DE",
    "sg:address":"Elisabethstr. 20",
    "sg:city":"T\u00fc\u00dfling",
    "sg:phone":"+49 8633/351",
    "sg:postcode":"84577",
    "sg:province":"Bayern",
    "wof:name":"Hans Sewald Elektroinstallation",
    "wof:placetype":"venue"
},
  "geometry": {"coordinates":[12.59763,48.211151],"type":"Point"}
}