{
  "type": "Feature",
  "properties": {
    "iso:country":"DE",
    "sg:address":"Jahnstr. 26",
    "sg:city":"Pforzheim",
    "sg:phone":"+49 7231/27518",
    "sg:postcode":"75173",
    "sg:province":"Baden-W\u00fcrttemberg",
    "wof:name":"Cafe Conditorei B\u00e4ckerei Leibbrand Gmbh",
    "wof:placetype":"venue"
},
  "geometry": {"coordinates":[8.695767,48.887699],"type":"Point"}
}