{
  "type": "Feature",
  "properties": {
    "iso:country":"DE",
    "sg:address":"Beilsteiner Str. 11",
    "sg:city":"Berlin",
    "sg:phone":"+49 30/5456632",
    "sg:postcode":"12681",
    "sg:province":"Berlin",
    "wof:name":"Uwe Siebenh\u00fchner",
    "wof:placetype":"venue"
},
  "geometry": {"coordinates":[13.52696,52.516994],"type":"Point"}
}