{
  "type": "Feature",
  "properties": {
    "iso:country":"DE",
    "sg:address":"Leopoldring 18",
    "sg:city":"Rastatt",
    "sg:phone":"+49 7222/33733",
    "sg:postcode":"76437",
    "sg:province":"Baden-W\u00fcrttemberg",
    "wof:name":"Jugoslawischer Arbeiterverein Domovina Rastatt E. V.",
    "wof:placetype":"venue"
},
  "geometry": {"coordinates":[8.2010993958,48.8524703979],"type":"Point"}
}