{
  "type": "Feature",
  "properties": {
    "iso:country":"DE",
    "sg:address":"Nr. 16",
    "sg:city":"Obersch\u00f6na",
    "sg:postcode":"09600",
    "sg:province":"Sachsen",
    "wof:name":"Ev.-luth. Kirche Obersch\u00f6na",
    "wof:placetype":"venue"
},
  "geometry": {"coordinates":[13.2972984314,50.9073295593],"type":"Point"}
}