{
  "type": "Feature",
  "properties": {
    "iso:country":"DE",
    "sg:address":"Im Lauer 53",
    "sg:city":"Bad Soden",
    "sg:phone":"+49 6196/659829",
    "sg:postcode":"65812",
    "sg:province":"Hessen",
    "wof:name":"Inka Koch",
    "wof:placetype":"venue"
},
  "geometry": {"coordinates":[8.4870471954,50.155960083],"type":"Point"}
}