{
  "type": "Feature",
  "properties": {
    "iso:country":"DE",
    "sg:address":"M\u00fchlsteige 39",
    "sg:city":"Neubulach",
    "sg:phone":"+49 7053/7476",
    "sg:postcode":"75387",
    "sg:province":"Baden-W\u00fcrttemberg",
    "wof:name":"Niethammer",
    "wof:placetype":"venue"
},
  "geometry": {"coordinates":[8.701426,48.658733],"type":"Point"}
}