{
  "type": "Feature",
  "properties": {
    "iso:country":"DE",
    "sg:address":"Wittelsbacherallee 60",
    "sg:city":"Minden",
    "sg:phone":"+49 571/505250",
    "sg:postcode":"32427",
    "sg:province":"Nordrhein-Westfalen",
    "wof:name":"M\u00fcller Minden Maschinenhandels Gmbh",
    "wof:placetype":"venue"
},
  "geometry": {"coordinates":[8.8807897568,52.2949562073],"type":"Point"}
}