{
  "type": "Feature",
  "properties": {
    "iso:country":"DE",
    "sg:address":"Am Wehrgang 9",
    "sg:city":"Gundelfingen",
    "sg:phone":"+49 9073/3941",
    "sg:postcode":"89423",
    "sg:province":"Bayern",
    "wof:name":"Peter Wagner Heilpraktiker",
    "wof:placetype":"venue"
},
  "geometry": {"coordinates":[10.3649101257,48.5539627075],"type":"Point"}
}