{
  "type": "Feature",
  "properties": {
    "iso:country":"DE",
    "sg:address":"L\u00fcttgenfeldstr. 28 b",
    "sg:city":"Wernigerode",
    "sg:phone":"+49 3943/632265",
    "sg:postcode":"38855",
    "sg:province":"Sachsen-Anhalt",
    "wof:name":"H.-reiner Schimang",
    "wof:placetype":"venue"
},
  "geometry": {"coordinates":[10.773182869,51.8303794861],"type":"Point"}
}