{
  "type": "Feature",
  "properties": {
    "iso:country":"DE",
    "sg:address":"Spie\u00dfgasse 39",
    "sg:city":"Alzey",
    "sg:phone":"+49 6731/993470",
    "sg:postcode":"55232",
    "sg:province":"Rheinland-Pfalz",
    "wof:name":"Alzeyer Wochenblatt",
    "wof:placetype":"venue"
},
  "geometry": {"coordinates":[8.1106853485,49.7449188232],"type":"Point"}
}