{
  "type": "Feature",
  "properties": {
    "iso:country":"DE",
    "sg:address":"Lange Str. 16",
    "sg:city":"Roitzsch",
    "sg:phone":"+49 34954/21456",
    "sg:postcode":"06809",
    "sg:province":"Sachsen-Anhalt",
    "wof:name":"Alfred Meinhardt",
    "wof:placetype":"venue"
},
  "geometry": {"coordinates":[12.260086,51.573563],"type":"Point"}
}