{
  "type": "Feature",
  "properties": {
    "iso:country":"DE",
    "sg:address":"Druseltalstr. 135",
    "sg:city":"Kassel",
    "sg:phone":"+49 561/311341",
    "sg:postcode":"34131",
    "sg:province":"Hessen",
    "wof:name":"Hans-ulrich Von Klitzing",
    "wof:placetype":"venue"
},
  "geometry": {"coordinates":[9.4236383438,51.3034706116],"type":"Point"}
}