{
  "type": "Feature",
  "properties": {
    "iso:country":"DE",
    "sg:address":"Robert-Bosch-Str. 3",
    "sg:city":"Straelen",
    "sg:phone":"+49 2834/93550",
    "sg:postcode":"47638",
    "sg:province":"Nordrhein-Westfalen",
    "wof:name":"Adrem Tor- Und Zaunprojekte Gmbh",
    "wof:placetype":"venue"
},
  "geometry": {"coordinates":[6.2702050209,51.4372253418],"type":"Point"}
}