{
  "type": "Feature",
  "properties": {
    "iso:country":"DE",
    "sg:address":"Reism\u00fchler Str. 28",
    "sg:city":"Gauting",
    "sg:phone":"+49 89/8504435",
    "sg:postcode":"82131",
    "sg:province":"Bayern",
    "wof:name":"Hilmar Schneider Architekt",
    "wof:placetype":"venue"
},
  "geometry": {"coordinates":[11.376104,48.06028],"type":"Point"}
}