{
  "type": "Feature",
  "properties": {
    "iso:country":"DE",
    "sg:address":"Mozartstr. 5",
    "sg:city":"Mainaschaff",
    "sg:phone":"+49 6021/780306",
    "sg:postcode":"63814",
    "sg:province":"Bayern",
    "wof:name":"W. H. Ettel Ingenieur",
    "wof:placetype":"venue"
},
  "geometry": {"coordinates":[9.0932645798,49.9787483215],"type":"Point"}
}