{
  "type": "Feature",
  "properties": {
    "iso:country":"DE",
    "sg:address":"Eulenstr. 51",
    "sg:city":"Fr\u00f6ndenberg",
    "sg:phone":"+49 2373/72016",
    "sg:postcode":"58730",
    "sg:province":"Nordrhein-Westfalen",
    "wof:name":"Wilhelm Dieckmann",
    "wof:placetype":"venue"
},
  "geometry": {"coordinates":[7.756599,51.488834],"type":"Point"}
}