{
  "type": "Feature",
  "properties": {
    "iso:country":"DE",
    "sg:address":"Aubernweg 2 A",
    "sg:city":"Wettenberg",
    "sg:phone":"+49 641/82338",
    "sg:postcode":"35435",
    "sg:province":"Hessen",
    "wof:name":"Leib Handels-dienstleistungs- Und Verwaltungsges. Mbh",
    "wof:placetype":"venue"
},
  "geometry": {"coordinates":[8.638166,50.61911],"type":"Point"}
}