{
  "type": "Feature",
  "properties": {
    "iso:country":"DE",
    "sg:address":"Asbacher Str. 16",
    "sg:city":"Vierkirchen",
    "sg:phone":"+49 8139/92242",
    "sg:postcode":"85256",
    "sg:province":"Bayern",
    "wof:name":"Thomas Karsten",
    "wof:placetype":"venue"
},
  "geometry": {"coordinates":[11.4569263458,48.3655929565],"type":"Point"}
}