{
  "type": "Feature",
  "properties": {
    "iso:country":"DE",
    "sg:address":"Ehestetter Str. 10",
    "sg:city":"Hayingen",
    "sg:phone":"+49 7386/250",
    "sg:postcode":"72534",
    "sg:province":"Baden-W\u00fcrttemberg",
    "wof:name":"Albert Herter",
    "wof:placetype":"venue"
},
  "geometry": {"coordinates":[9.4736433029,48.2776527405],"type":"Point"}
}