{
  "type": "Feature",
  "properties": {
    "iso:country":"DE",
    "sg:address":"Karl-Hermann-Flach-Str 15b",
    "sg:city":"Oberursel",
    "sg:phone":"+49 6171/59090",
    "sg:postcode":"61440",
    "sg:province":"Hessen",
    "wof:name":"Wohlleben Gmbh",
    "wof:placetype":"venue"
},
  "geometry": {"coordinates":[8.595734,50.204453],"type":"Point"}
}