{
  "type": "Feature",
  "properties": {
    "iso:country":"DE",
    "sg:address":"Hirschplan 4",
    "sg:city":"Herrenberg",
    "sg:phone":"+49 7032/6389",
    "sg:postcode":"71083",
    "sg:province":"Baden-W\u00fcrttemberg",
    "wof:name":"R. Sch\u00f6ll",
    "wof:placetype":"venue"
},
  "geometry": {"coordinates":[8.86902,48.596214],"type":"Point"}
}