{
  "type": "Feature",
  "properties": {
    "iso:country":"DE",
    "sg:address":"Chemnitzer Str. 4",
    "sg:city":"Thum",
    "sg:phone":"+49 37297/4476",
    "sg:postcode":"09419",
    "sg:province":"Sachsen",
    "wof:name":"M. Pojda",
    "wof:placetype":"venue"
},
  "geometry": {"coordinates":[12.950667,50.671429],"type":"Point"}
}