{
  "type": "Feature",
  "properties": {
    "iso:country":"DE",
    "sg:address":"Husarenstr. 35",
    "sg:city":"Heidelberg",
    "sg:phone":"+49 6221/165789",
    "sg:postcode":"69121",
    "sg:province":"Baden-W\u00fcrttemberg",
    "wof:name":"Elpis Verlag Gmbh",
    "wof:placetype":"venue"
},
  "geometry": {"coordinates":[8.6783246994,49.4300727844],"type":"Point"}
}