{
  "type": "Feature",
  "properties": {
    "iso:country":"DE",
    "sg:address":"Auchtertstr. 14",
    "sg:city":"Reutlingen",
    "sg:phone":"+49 4971/2156790",
    "sg:postcode":"72770",
    "sg:province":"Baden-W\u00fcrttemberg",
    "wof:name":"Druckerei Raisch Gmbh & Co Kg",
    "wof:placetype":"venue"
},
  "geometry": {"coordinates":[9.1640882492,48.4940452576],"type":"Point"}
}