{
  "type": "Feature",
  "properties": {
    "iso:country":"DE",
    "sg:address":"Siedlung 3",
    "sg:city":"Dolle",
    "sg:phone":"+49 39364/319",
    "sg:postcode":"39517",
    "sg:province":"Sachsen-Anhalt",
    "wof:name":"Automaten Aufstellung Kramann Gmbh",
    "wof:placetype":"venue"
},
  "geometry": {"coordinates":[11.6170568466,52.404045105],"type":"Point"}
}