{
  "type": "Feature",
  "properties": {
    "iso:country":"DE",
    "sg:address":"Gie\u00dfener Stra\u00dfe 6",
    "sg:city":"Fernwald",
    "sg:phone":"+49 641",
    "sg:postcode":"35463",
    "sg:province":"Hessen",
    "wof:name":"A Cappella Blind-date-agentur",
    "wof:placetype":"venue"
},
  "geometry": {"coordinates":[8.7543907166,50.580329895],"type":"Point"}
}