{
  "type": "Feature",
  "properties": {
    "iso:country":"DE",
    "sg:address":"K\u00f6nigsheidering 109",
    "sg:city":"Weidenberg",
    "sg:phone":"+49 9278/1850",
    "sg:postcode":"95466",
    "sg:province":"Bayern",
    "wof:name":"Bettina Und Uwe Will",
    "wof:placetype":"venue"
},
  "geometry": {"coordinates":[11.7300720215,49.9473114014],"type":"Point"}
}