{
  "type": "Feature",
  "properties": {
    "iso:country":"DE",
    "sg:address":"Hohenzollernstr. 53",
    "sg:city":"Hannover",
    "sg:phone":"+49 511/961640",
    "sg:postcode":"30161",
    "sg:province":"Niedersachsen",
    "wof:name":"Mam Verm\u00f6gensverwaltungs- Gesellschaft Mbh & Co. Kg",
    "wof:placetype":"venue"
},
  "geometry": {"coordinates":[9.752921,52.387108],"type":"Point"}
}