{
  "type": "Feature",
  "properties": {
    "iso:country":"DE",
    "sg:address":"Germanenstr. 45",
    "sg:city":"Bielefeld",
    "sg:phone":"+49 521/442122",
    "sg:postcode":"33647",
    "sg:province":"Nordrhein-Westfalen",
    "wof:name":"Asglas Kalkbrenner Gmbh",
    "wof:placetype":"venue"
},
  "geometry": {"coordinates":[8.50479,51.988968],"type":"Point"}
}