{
  "type": "Feature",
  "properties": {
    "iso:country":"DE",
    "sg:address":"H\u00e4userner Str. 1",
    "sg:city":"Ummendorf",
    "sg:phone":"+49 4973/5122200",
    "sg:postcode":"88444",
    "sg:province":"Baden-W\u00fcrttemberg",
    "wof:name":"Kreissparkasse",
    "wof:placetype":"venue"
},
  "geometry": {"coordinates":[9.830955,48.063438],"type":"Point"}
}