{
  "type": "Feature",
  "properties": {
    "iso:country":"DE",
    "sg:address":"Daimlerstr. 21",
    "sg:city":"Bodelshausen",
    "sg:phone":"+49 7471/71277",
    "sg:postcode":"72411",
    "sg:province":"Baden-W\u00fcrttemberg",
    "wof:name":"Obstk\u00f6rble K.-h. Behnle",
    "wof:placetype":"venue"
},
  "geometry": {"coordinates":[8.9792757034,48.3845214844],"type":"Point"}
}