{
  "type": "Feature",
  "properties": {
    "iso:country":"DE",
    "sg:address":"Denkendorfer Str. 21",
    "sg:city":"Ostfildern",
    "sg:phone":"+49 711/3411383",
    "sg:postcode":"73760",
    "sg:province":"Baden-W\u00fcrttemberg",
    "wof:name":"G\u00fcnter Maier Architekt",
    "wof:placetype":"venue"
},
  "geometry": {"coordinates":[9.302279,48.710701],"type":"Point"}
}