{
  "type": "Feature",
  "properties": {
    "iso:country":"DE",
    "sg:address":"Hauptstr. 46 c",
    "sg:city":"Braunschweig",
    "sg:phone":"+49 5307/92120",
    "sg:postcode":"38110",
    "sg:province":"Niedersachsen",
    "wof:name":"Wenden Hallenbad",
    "wof:placetype":"venue"
},
  "geometry": {"coordinates":[10.5199165344,52.3330879211],"type":"Point"}
}