{
  "type": "Feature",
  "properties": {
    "iso:country":"DE",
    "sg:address":"Neufirreler Str. 86",
    "sg:city":"Uplengen",
    "sg:phone":"+49 4956/637",
    "sg:postcode":"26670",
    "sg:province":"Niedersachsen",
    "wof:name":"Wilhelm Diener",
    "wof:placetype":"venue"
},
  "geometry": {"coordinates":[7.683656,53.343987],"type":"Point"}
}