{
  "type": "Feature",
  "properties": {
    "iso:country":"DE",
    "sg:address":"Tegernbach 13",
    "sg:city":"Egglkofen",
    "sg:phone":"+49 8639/428",
    "sg:postcode":"84546",
    "sg:province":"Bayern",
    "wof:name":"Hans Plinninger",
    "wof:placetype":"venue"
},
  "geometry": {"coordinates":[12.4606409073,48.3856925964],"type":"Point"}
}