{
  "type": "Feature",
  "properties": {
    "iso:country":"DE",
    "sg:address":"Alte L\u00fcbecker Chaussee 27 a",
    "sg:city":"Kiel",
    "sg:phone":"+49 431/688830",
    "sg:postcode":"24113",
    "sg:province":"Schleswig-Holstein",
    "wof:name":"Brockers",
    "wof:placetype":"venue"
},
  "geometry": {"coordinates":[10.1253070831,54.3058280945],"type":"Point"}
}