{
  "type": "Feature",
  "properties": {
    "iso:country":"DE",
    "sg:address":"Rellinghauser Str. 162",
    "sg:city":"Essen",
    "sg:phone":"+49 201/260830",
    "sg:postcode":"45128",
    "sg:province":"Nordrhein-Westfalen",
    "wof:name":"Krombacher Novelle",
    "wof:placetype":"venue"
},
  "geometry": {"coordinates":[7.0215959549,51.4402618408],"type":"Point"}
}