{
  "type": "Feature",
  "properties": {
    "iso:country":"DE",
    "sg:address":"Reichsstr. 15a",
    "sg:city":"Plauen",
    "sg:phone":"+49 3741/222628",
    "sg:postcode":"08523",
    "sg:province":"Sachsen",
    "wof:name":"Einrichtung Lothar Michel",
    "wof:placetype":"venue"
},
  "geometry": {"coordinates":[12.1344,50.499172],"type":"Point"}
}