{
  "type": "Feature",
  "properties": {
    "iso:country":"DE",
    "sg:address":"Heidlerchenstr. 8 b",
    "sg:city":"Bremen",
    "sg:phone":"+49 421/6007080",
    "sg:postcode":"28777",
    "sg:province":"Bremen",
    "wof:name":"Olaf Rath Gmbh",
    "wof:placetype":"venue"
},
  "geometry": {"coordinates":[8.555494,53.191845],"type":"Point"}
}