{
  "type": "Feature",
  "properties": {
    "iso:country":"DE",
    "sg:address":"M\u00f6rikestr. 3",
    "sg:city":"Gerlingen",
    "sg:phone":"+49 7156/433470",
    "sg:postcode":"70839",
    "sg:province":"Baden-W\u00fcrttemberg",
    "wof:name":"A.r. Informatik",
    "wof:placetype":"venue"
},
  "geometry": {"coordinates":[9.064228,48.802902],"type":"Point"}
}