{
  "type": "Feature",
  "properties": {
    "iso:country":"DE",
    "sg:address":"Erbstal 14",
    "sg:city":"Steinbach-Hallenberg",
    "sg:phone":"+49 36847/42370",
    "sg:postcode":"98587",
    "sg:province":"Th\u00fcringen",
    "wof:name":"Lindenhof",
    "wof:placetype":"venue"
},
  "geometry": {"coordinates":[10.5710630417,50.6985397339],"type":"Point"}
}