{
  "type": "Feature",
  "properties": {
    "iso:country":"DE",
    "sg:address":"Lange Str. 40",
    "sg:city":"Malchow",
    "sg:phone":"+49 39932/14533",
    "sg:postcode":"17213",
    "sg:province":"Mecklenburg-Vorpommern",
    "wof:name":"H. Schimmel",
    "wof:placetype":"venue"
},
  "geometry": {"coordinates":[12.430086,53.475094],"type":"Point"}
}