{
  "type": "Feature",
  "properties": {
    "iso:country":"DE",
    "sg:address":"Osterholzallee 7",
    "sg:city":"Ludwigsburg",
    "sg:phone":"+49 7141/927591",
    "sg:postcode":"71636",
    "sg:province":"Baden-W\u00fcrttemberg",
    "wof:name":"Bronner Gmbh",
    "wof:placetype":"venue"
},
  "geometry": {"coordinates":[9.17855,48.897057],"type":"Point"}
}