{
  "type": "Feature",
  "properties": {
    "iso:country":"DE",
    "sg:address":"Hauptstr. 70",
    "sg:city":"Nieb\u00fcll",
    "sg:phone":"+49 4661/8740",
    "sg:postcode":"25899",
    "sg:province":"Schleswig-Holstein",
    "wof:name":"Hubert Dahmen",
    "wof:placetype":"venue"
},
  "geometry": {"coordinates":[8.8250799179,54.7841796875],"type":"Point"}
}