{
  "type": "Feature",
  "properties": {
    "iso:country":"DE",
    "sg:address":"Industriestr. 18",
    "sg:city":"Landau",
    "sg:postcode":"76829",
    "sg:province":"Rheinland-Pfalz",
    "wof:name":"Energie S\u00fcdwest Ag",
    "wof:placetype":"venue"
},
  "geometry": {"coordinates":[8.123307,49.200031],"type":"Point"}
}