{
  "type": "Feature",
  "properties": {
    "iso:country":"DE",
    "sg:address":"Bayreuther Str. 2",
    "sg:city":"Trebgast",
    "sg:phone":"+49 9227/5456",
    "sg:postcode":"95367",
    "sg:province":"Bayern",
    "wof:name":"Erika Lauterbach",
    "wof:placetype":"venue"
},
  "geometry": {"coordinates":[11.5512542725,50.0683517456],"type":"Point"}
}