{
  "type": "Feature",
  "properties": {
    "iso:country":"DE",
    "sg:address":"Edelwei\u00dfstr. 112",
    "sg:city":"Kaarst",
    "sg:phone":"+49 2131/766616",
    "sg:postcode":"41564",
    "sg:province":"Nordrhein-Westfalen",
    "wof:name":"Mirage Vertriebs Gmbh",
    "wof:placetype":"venue"
},
  "geometry": {"coordinates":[6.6121897697,51.2203102112],"type":"Point"}
}