{
  "type": "Feature",
  "properties": {
    "iso:country":"DE",
    "sg:address":"Waldstr. 2",
    "sg:city":"Germering",
    "sg:postcode":"82110",
    "sg:province":"Bayern",
    "wof:name":"Sss Audit Team Gesellschaft F. Medizinische Forschung Mbh",
    "wof:placetype":"venue"
},
  "geometry": {"coordinates":[11.3797330856,48.125579834],"type":"Point"}
}