{
  "type": "Feature",
  "properties": {
    "iso:country":"DE",
    "sg:address":"Wurzer Str. 14",
    "sg:city":"Windischeschenbach",
    "sg:phone":"+49 9681/1332",
    "sg:postcode":"92670",
    "sg:province":"Bayern",
    "wof:name":"Bernhard Riebl Gmbh",
    "wof:placetype":"venue"
},
  "geometry": {"coordinates":[12.16944,49.79916],"type":"Point"}
}