{
  "type": "Feature",
  "properties": {
    "iso:country":"DE",
    "sg:address":"Naumannstr. 1",
    "sg:city":"Dresden",
    "sg:phone":"+49 351/340800",
    "sg:postcode":"01309",
    "sg:province":"Sachsen",
    "wof:name":"Schmidt & Partner Gmbh",
    "wof:placetype":"venue"
},
  "geometry": {"coordinates":[13.8045835495,51.0532951355],"type":"Point"}
}