{
  "type": "Feature",
  "properties": {
    "iso:country":"DE",
    "sg:address":"Michelbacher Str. 1",
    "sg:city":"Wettringen",
    "sg:phone":"+49 9869/698",
    "sg:postcode":"91631",
    "sg:province":"Bayern",
    "wof:name":"E. Haberecker",
    "wof:placetype":"venue"
},
  "geometry": {"coordinates":[10.156285,49.25824],"type":"Point"}
}