{
  "type": "Feature",
  "properties": {
    "iso:country":"DE",
    "sg:address":"Keno-tom-Brook-Str. 9d",
    "sg:city":"Upgant-Schott",
    "sg:phone":"+49 4934/914267",
    "sg:postcode":"26529",
    "sg:province":"Niedersachsen",
    "wof:name":"Saathoff & Woldenga Ohg",
    "wof:placetype":"venue"
},
  "geometry": {"coordinates":[7.283853054,53.5232543945],"type":"Point"}
}