{
  "type": "Feature",
  "properties": {
    "iso:country":"DE",
    "sg:address":"Gr\u00fcne Str. 16",
    "sg:city":"Horn-Bad Meinberg",
    "sg:phone":"+49 5234/824242",
    "sg:postcode":"32805",
    "sg:province":"Nordrhein-Westfalen",
    "wof:name":"Ursula Garnjost",
    "wof:placetype":"venue"
},
  "geometry": {"coordinates":[8.945225,51.873196],"type":"Point"}
}