{
  "type": "Feature",
  "properties": {
    "iso:country":"DE",
    "sg:address":"Leerer Str. 27",
    "sg:city":"Steinfurt",
    "sg:phone":"+49 2551/2544",
    "sg:postcode":"48565",
    "sg:province":"Nordrhein-Westfalen",
    "wof:name":"Restaurant Akropolis",
    "wof:placetype":"venue"
},
  "geometry": {"coordinates":[7.3356499672,52.1466026306],"type":"Point"}
}