{
  "type": "Feature",
  "properties": {
    "iso:country":"DE",
    "sg:address":"F\u00fcrstenbergstr. 54",
    "sg:city":"Konstanz",
    "sg:phone":"+49 7531/78672",
    "sg:postcode":"78467",
    "sg:province":"Baden-W\u00fcrttemberg",
    "wof:name":"H. Lanz Versicherung",
    "wof:placetype":"venue"
},
  "geometry": {"coordinates":[9.1544189453,47.6850242615],"type":"Point"}
}