{
  "type": "Feature",
  "properties": {
    "iso:country":"DE",
    "sg:address":"Otto-Nuschke-Str. 7",
    "sg:city":"Seehausen",
    "sg:phone":"+49 39386/54496",
    "sg:postcode":"39615",
    "sg:province":"Sachsen-Anhalt",
    "wof:name":"Seeh\u00e4user Wachschutz- Und Geb\u00e4udereinigungs Gmbh",
    "wof:placetype":"venue"
},
  "geometry": {"coordinates":[11.7455644608,52.8839912415],"type":"Point"}
}