{
  "type": "Feature",
  "properties": {
    "iso:country":"DE",
    "sg:address":"Ditmar-Koel-Str. 1",
    "sg:city":"Hamburg",
    "sg:phone":"+49 40/37503177",
    "sg:postcode":"20459",
    "sg:province":"Hamburg",
    "wof:name":"Flg Fischmarkt L\u00fchr Gmbh",
    "wof:placetype":"venue"
},
  "geometry": {"coordinates":[9.9775018692,53.5462188721],"type":"Point"}
}