{
  "type": "Feature",
  "properties": {
    "iso:country":"DE",
    "sg:address":"Hirschau",
    "sg:city":"Grabenst\u00e4tt",
    "sg:phone":"+49 8661/470",
    "sg:postcode":"83355",
    "sg:province":"Bayern",
    "wof:name":"Josef Wiesholler",
    "wof:placetype":"venue"
},
  "geometry": {"coordinates":[12.538356781,47.854763031],"type":"Point"}
}