{
  "type": "Feature",
  "properties": {
    "iso:country":"DE",
    "sg:address":"Frankfurter Str. 10",
    "sg:city":"Gedern",
    "sg:phone":"+49 6045/5855",
    "sg:postcode":"63688",
    "sg:province":"Hessen",
    "wof:name":"Spar Markt",
    "wof:placetype":"venue"
},
  "geometry": {"coordinates":[9.1977453232,50.4230155945],"type":"Point"}
}