{
  "type": "Feature",
  "properties": {
    "iso:country":"DE",
    "sg:address":"Zeppelinstr. 7",
    "sg:city":"Insheim",
    "sg:phone":"+49 6341/83814",
    "sg:postcode":"76865",
    "sg:province":"Rheinland-Pfalz",
    "wof:name":"Klaus L\u00f6sch",
    "wof:placetype":"venue"
},
  "geometry": {"coordinates":[8.1459980011,49.1571922302],"type":"Point"}
}