{
  "type": "Feature",
  "properties": {
    "iso:country":"DE",
    "sg:address":"Tillystrasse 33",
    "sg:city":"Bad Wimpfen",
    "sg:phone":"+49 7063/760",
    "sg:postcode":"74206",
    "sg:province":"Baden-W\u00fcrttemberg",
    "wof:name":"Januz Kunstkarten-verlag",
    "wof:placetype":"venue"
},
  "geometry": {"coordinates":[9.162557,49.222786],"type":"Point"}
}