{
  "type": "Feature",
  "properties": {
    "iso:country":"DE",
    "sg:address":"August-Ullrich-Str. 42",
    "sg:city":"Elfershausen",
    "sg:postcode":"97725",
    "sg:province":"Bayern",
    "wof:name":"Brs Baustoffrecycling Saaletal Gmbh",
    "wof:placetype":"venue"
},
  "geometry": {"coordinates":[9.965869,50.143417],"type":"Point"}
}