{
  "type": "Feature",
  "properties": {
    "iso:country":"DE",
    "sg:address":"Margaretenstr. 4",
    "sg:city":"Regensburg",
    "sg:phone":"+49 941/2070",
    "sg:postcode":"93047",
    "sg:province":"Bayern",
    "wof:name":"Zeitungs-zustellung Gmbh",
    "wof:placetype":"venue"
},
  "geometry": {"coordinates":[12.0896072388,49.0133934021],"type":"Point"}
}