{
  "type": "Feature",
  "properties": {
    "iso:country":"DE",
    "sg:address":"An der Schleife 13",
    "sg:city":"Stavenhagen",
    "sg:phone":"+49 39954/31587",
    "sg:postcode":"17153",
    "sg:province":"Mecklenburg-Vorpommern",
    "wof:name":"Schuster Dachbau Gmbh",
    "wof:placetype":"venue"
},
  "geometry": {"coordinates":[12.97043,53.710236],"type":"Point"}
}