{
  "type": "Feature",
  "properties": {
    "iso:country":"DE",
    "sg:address":"Steinbergstr. 46",
    "sg:city":"Burkardroth",
    "sg:phone":"+49 9701/641",
    "sg:postcode":"97705",
    "sg:province":"Bayern",
    "wof:name":"Walter Krapf",
    "wof:placetype":"venue"
},
  "geometry": {"coordinates":[10.018037796,50.3022117615],"type":"Point"}
}