{
  "type": "Feature",
  "properties": {
    "iso:country":"DE",
    "sg:address":"Hangstr. 5",
    "sg:city":"Bruckberg",
    "sg:phone":"+49 8765/541",
    "sg:postcode":"84079",
    "sg:province":"Bayern",
    "wof:name":"Hans Matzner",
    "wof:placetype":"venue"
},
  "geometry": {"coordinates":[12.0252065659,48.5362014771],"type":"Point"}
}