{
  "type": "Feature",
  "properties": {
    "iso:country":"DE",
    "sg:address":"Waldstr 2",
    "sg:city":"Sondershausen",
    "sg:phone":"+49 3632/623136",
    "sg:postcode":"99706",
    "sg:province":"Th\u00fcringen",
    "wof:name":"Multimedia & Internet-service",
    "wof:placetype":"venue"
},
  "geometry": {"coordinates":[10.9045171738,51.3560638428],"type":"Point"}
}