{
  "type": "Feature",
  "properties": {
    "iso:country":"DE",
    "sg:address":"Nordstr. 10",
    "sg:city":"Gronau",
    "sg:phone":"+49 5182/2118",
    "sg:postcode":"31028",
    "sg:province":"Niedersachsen",
    "wof:name":"Paul B\u00fcschel",
    "wof:placetype":"venue"
},
  "geometry": {"coordinates":[9.772366,52.085178],"type":"Point"}
}