{
  "type": "Feature",
  "properties": {
    "iso:country":"DE",
    "sg:address":"Wiesenbachstr. 2",
    "sg:city":"Brackenheim",
    "sg:phone":"+49 7135/12274",
    "sg:postcode":"74336",
    "sg:province":"Baden-W\u00fcrttemberg",
    "wof:name":"Ernst-hermann Schmidt",
    "wof:placetype":"venue"
},
  "geometry": {"coordinates":[9.068498,49.066265],"type":"Point"}
}