{
  "type": "Feature",
  "properties": {
    "iso:country":"DE",
    "sg:address":"Potsdamer Str 10",
    "sg:city":"Teltow",
    "sg:phone":"+49 3328/447980",
    "sg:postcode":"14513",
    "sg:province":"Brandenburg",
    "wof:name":"Werbetechnik Teltow",
    "wof:placetype":"venue"
},
  "geometry": {"coordinates":[13.2445907593,52.3976593018],"type":"Point"}
}