{
  "type": "Feature",
  "properties": {
    "iso:country":"DE",
    "sg:address":"Fuhlsb\u00fcttler Str. 779 a",
    "sg:city":"Hamburg",
    "sg:phone":"+49 40/597598",
    "sg:postcode":"22337",
    "sg:province":"Hamburg",
    "wof:name":"Karl Weiss Inh. Martin M\u00fcller",
    "wof:placetype":"venue"
},
  "geometry": {"coordinates":[10.0326423645,53.6223945618],"type":"Point"}
}