{
  "type": "Feature",
  "properties": {
    "iso:country":"DE",
    "sg:address":"F\u00fcrstenwalder Allee 79",
    "sg:city":"Berlin",
    "sg:phone":"+49 30/6484010",
    "sg:postcode":"12589",
    "sg:province":"Berlin",
    "wof:name":"Pension Fobbe",
    "wof:placetype":"venue"
},
  "geometry": {"coordinates":[13.6860580444,52.4428062439],"type":"Point"}
}