{
  "type": "Feature",
  "properties": {
    "iso:country":"DE",
    "sg:address":"Kirchstr. 5",
    "sg:city":"Bockhorn",
    "sg:phone":"+49 8122/15060",
    "sg:postcode":"85461",
    "sg:province":"Bayern",
    "wof:name":"Lorenz Schaberl",
    "wof:placetype":"venue"
},
  "geometry": {"coordinates":[11.9996242523,48.2883796692],"type":"Point"}
}