{
  "type": "Feature",
  "properties": {
    "iso:country":"DE",
    "sg:address":"Danziger Str. 42 - 44",
    "sg:city":"Passau",
    "sg:phone":"+49 851/72040",
    "sg:postcode":"94036",
    "sg:province":"Bayern",
    "wof:name":"Hotel-restaurant Dreifl\u00fcssehof",
    "wof:placetype":"venue"
},
  "geometry": {"coordinates":[13.4244527817,48.5631866455],"type":"Point"}
}