{
  "type": "Feature",
  "properties": {
    "iso:country":"DE",
    "sg:address":"Lorbeerstr. 20",
    "sg:city":"Neuss",
    "sg:phone":"+49 2131/464035",
    "sg:postcode":"41466",
    "sg:province":"Nordrhein-Westfalen",
    "wof:name":"U. Welzel",
    "wof:placetype":"venue"
},
  "geometry": {"coordinates":[6.692866,51.169258],"type":"Point"}
}