{
  "type": "Feature",
  "properties": {
    "iso:country":"DE",
    "sg:address":"Hohe-Acht-Str. 4",
    "sg:city":"Siebenbach",
    "sg:phone":"+49 2656/8666",
    "sg:postcode":"56729",
    "sg:province":"Rheinland-Pfalz",
    "wof:name":"Km Bau Gmbh",
    "wof:placetype":"venue"
},
  "geometry": {"coordinates":[7.03398,50.379215],"type":"Point"}
}