{
  "type": "Feature",
  "properties": {
    "iso:country":"DE",
    "sg:address":"Stettiner Str. 4",
    "sg:city":"Paderborn",
    "sg:phone":"+49 5251/777210",
    "sg:postcode":"33106",
    "sg:province":"Nordrhein-Westfalen",
    "wof:name":"Josef Thiel",
    "wof:placetype":"venue"
},
  "geometry": {"coordinates":[8.684877,51.733929],"type":"Point"}
}