{
  "type": "Feature",
  "properties": {
    "iso:country":"DE",
    "sg:address":"Helenenbergweg 10",
    "sg:city":"Witten",
    "sg:postcode":"58453",
    "sg:province":"Nordrhein-Westfalen",
    "wof:name":"Behindertenwerkstatt",
    "wof:placetype":"venue"
},
  "geometry": {"coordinates":[7.342877,51.431248],"type":"Point"}
}