{
  "type": "Feature",
  "properties": {
    "iso:country":"DE",
    "sg:address":"Grottenstr. 18",
    "sg:city":"Hamburg",
    "sg:phone":"+49 40/828253",
    "sg:postcode":"22605",
    "sg:province":"Hamburg",
    "wof:name":"Handels- Und Beteiligungsges. Martin M\u00fcller Mbh",
    "wof:placetype":"venue"
},
  "geometry": {"coordinates":[9.880005,53.556694],"type":"Point"}
}