{
  "type": "Feature",
  "properties": {
    "iso:country":"DE",
    "sg:address":"Ostbezirk 35",
    "sg:city":"Warendorf",
    "sg:phone":"+49 2581/8325",
    "sg:postcode":"48231",
    "sg:province":"Nordrhein-Westfalen",
    "wof:name":"Johannes Jungemann",
    "wof:placetype":"venue"
},
  "geometry": {"coordinates":[8.017439,51.946918],"type":"Point"}
}