{
  "type": "Feature",
  "properties": {
    "iso:country":"DE",
    "sg:address":"Leingrubstr. 8",
    "sg:city":"Ingelheim",
    "sg:phone":"+49 6132/40911",
    "sg:postcode":"55218",
    "sg:province":"Rheinland-Pfalz",
    "wof:name":"Tecturana Bautr\u00e4ger Gmbh",
    "wof:placetype":"venue"
},
  "geometry": {"coordinates":[8.078722,49.98053],"type":"Point"}
}