{
  "type": "Feature",
  "properties": {
    "iso:country":"DE",
    "sg:address":"Abensberger Str. 9",
    "sg:city":"Neustadt",
    "sg:phone":"+49 9445/391",
    "sg:postcode":"93333",
    "sg:province":"Bayern",
    "wof:name":"Luitpold Adam Kunstmaler",
    "wof:placetype":"venue"
},
  "geometry": {"coordinates":[11.809082,48.801708],"type":"Point"}
}