{
  "type": "Feature",
  "properties": {
    "iso:country":"DE",
    "sg:address":"Kirchstr 3a",
    "sg:city":"Korbach",
    "sg:phone":"+49 5631/97570",
    "sg:postcode":"34497",
    "sg:province":"Hessen",
    "wof:name":"Pc Computer-studio Schrey Gmbh",
    "wof:placetype":"venue"
},
  "geometry": {"coordinates":[8.871072,51.274647],"type":"Point"}
}