{
  "type": "Feature",
  "properties": {
    "iso:country":"DE",
    "sg:address":"Rodigallee 239",
    "sg:city":"Hamburg",
    "sg:phone":"+49 40/6546777",
    "sg:postcode":"22043",
    "sg:province":"Hamburg",
    "wof:name":"Weddige",
    "wof:placetype":"venue"
},
  "geometry": {"coordinates":[10.126099,53.571178],"type":"Point"}
}