{
  "type": "Feature",
  "properties": {
    "iso:country":"DE",
    "sg:address":"Wickingstr. 5",
    "sg:city":"Essen",
    "sg:phone":"+49 201/835570",
    "sg:postcode":"45326",
    "sg:province":"Nordrhein-Westfalen",
    "wof:name":"Westhoff & Frie Ag",
    "wof:placetype":"venue"
},
  "geometry": {"coordinates":[7.0025000572,51.4787483215],"type":"Point"}
}