{
  "type": "Feature",
  "properties": {
    "iso:country":"DE",
    "sg:address":"Niewark 3",
    "sg:city":"Eckernf\u00f6rde",
    "sg:phone":"+49 4351/4790",
    "sg:postcode":"24340",
    "sg:province":"Schleswig-Holstein",
    "wof:name":"Waldemar Behn Gmbh & Co Kg",
    "wof:placetype":"venue"
},
  "geometry": {"coordinates":[9.8322219849,54.4530906677],"type":"Point"}
}