{
  "type": "Feature",
  "properties": {
    "iso:country":"DE",
    "sg:address":"Wehme 10",
    "sg:city":"Paderborn",
    "sg:phone":"+49 5251/91530",
    "sg:postcode":"33106",
    "sg:province":"Nordrhein-Westfalen",
    "wof:name":"Petra Nowak Architektin",
    "wof:placetype":"venue"
},
  "geometry": {"coordinates":[8.685795,51.689243],"type":"Point"}
}