{
  "type": "Feature",
  "properties": {
    "iso:country":"DE",
    "sg:address":"Oberzielenbach 16",
    "sg:city":"Morsbach",
    "sg:phone":"+49 2291/7067",
    "sg:postcode":"51597",
    "sg:province":"Nordrhein-Westfalen",
    "wof:name":"Horst Schumacher",
    "wof:placetype":"venue"
},
  "geometry": {"coordinates":[7.678063,50.886147],"type":"Point"}
}