{
  "type": "Feature",
  "properties": {
    "iso:country":"DE",
    "sg:address":"Wellseedamm 5",
    "sg:city":"Kiel",
    "sg:phone":"+49 431/716899",
    "sg:postcode":"24145",
    "sg:province":"Schleswig-Holstein",
    "wof:name":"Hinz Kunststoffverarbeitung Und Formenbau Gmbh",
    "wof:placetype":"venue"
},
  "geometry": {"coordinates":[10.147707,54.280144],"type":"Point"}
}