{
  "type": "Feature",
  "properties": {
    "iso:country":"DE",
    "sg:address":"Gleichenstr. 28",
    "sg:city":"Gotha",
    "sg:phone":"+49 361/7450535",
    "sg:postcode":"99867",
    "sg:province":"Th\u00fcringen",
    "wof:name":"Fbt-fertigbeton Verwaltungsges. Mbh",
    "wof:placetype":"venue"
},
  "geometry": {"coordinates":[10.727503,50.95163],"type":"Point"}
}