{
  "type": "Feature",
  "properties": {
    "iso:country":"DE",
    "sg:address":"Sundahlstr. 2",
    "sg:city":"Zweibr\u00fccken",
    "sg:phone":"+49 6332/43578",
    "sg:postcode":"66482",
    "sg:province":"Rheinland-Pfalz",
    "wof:name":"Siegrun Keller Heilpraktikerin",
    "wof:placetype":"venue"
},
  "geometry": {"coordinates":[7.3717479706,49.2566375732],"type":"Point"}
}