{
  "type": "Feature",
  "properties": {
    "iso:country":"DE",
    "sg:address":"Bahnhofstr. 17",
    "sg:city":"Kurort Seiffen",
    "sg:phone":"+49 37362/8368",
    "sg:postcode":"09548",
    "sg:province":"Sachsen",
    "wof:name":"G\u00fcnther Harzer",
    "wof:placetype":"venue"
},
  "geometry": {"coordinates":[13.4495000839,50.636390686],"type":"Point"}
}