{
  "type": "Feature",
  "properties": {
    "iso:country":"DE",
    "sg:address":"Kulmbacher Str. 6",
    "sg:city":"Kronach",
    "sg:phone":"+49 9261/62400",
    "sg:postcode":"96317",
    "sg:province":"Bayern",
    "wof:name":"Kmb Kronacher Massivbau Gmbh",
    "wof:placetype":"venue"
},
  "geometry": {"coordinates":[11.324015,50.237347],"type":"Point"}
}