{
  "type": "Feature",
  "properties": {
    "iso:country":"DE",
    "sg:address":"Strandallee 138",
    "sg:city":"Scharbeutz",
    "sg:phone":"+49 4503/700123",
    "sg:postcode":"23683",
    "sg:province":"Schleswig-Holstein",
    "wof:name":"Restaurant Zum Krabbenfischer",
    "wof:placetype":"venue"
},
  "geometry": {"coordinates":[10.757727623,54.0261116028],"type":"Point"}
}