{
  "type": "Feature",
  "properties": {
    "iso:country":"DE",
    "sg:address":"Bremer Str. 127",
    "sg:city":"Hamburg",
    "sg:phone":"+49 40/7664546",
    "sg:postcode":"21073",
    "sg:province":"Hamburg",
    "wof:name":"Karl-heinz Kr\u00fcger",
    "wof:placetype":"venue"
},
  "geometry": {"coordinates":[9.970684,53.451107],"type":"Point"}
}