{
  "type": "Feature",
  "properties": {
    "iso:country":"DE",
    "sg:address":"Marktplatz 2",
    "sg:city":"Erbendorf",
    "sg:phone":"+49 9682/209",
    "sg:postcode":"92681",
    "sg:province":"Bayern",
    "wof:name":"Stadtapotheke W. Tretter E. K.",
    "wof:placetype":"venue"
},
  "geometry": {"coordinates":[12.048346,49.838253],"type":"Point"}
}