{
  "type": "Feature",
  "properties": {
    "iso:country":"DE",
    "sg:address":"Neuer Weg 2",
    "sg:city":"Bad Sassendorf",
    "sg:phone":"+49 2921/8644",
    "sg:postcode":"59505",
    "sg:province":"Nordrhein-Westfalen",
    "wof:name":"Ernst-otto Keining Kinderunterhaltungsger\u00e4te-",
    "wof:placetype":"venue"
},
  "geometry": {"coordinates":[8.1816701889,51.584980011],"type":"Point"}
}