{
  "type": "Feature",
  "properties": {
    "iso:country":"DE",
    "sg:address":"Schramberger Winkel 6",
    "sg:city":"Mannheim",
    "sg:phone":"+49 621/478413",
    "sg:postcode":"68239",
    "sg:province":"Baden-W\u00fcrttemberg",
    "wof:name":"Rainer Wentz",
    "wof:placetype":"venue"
},
  "geometry": {"coordinates":[8.552435,49.468601],"type":"Point"}
}