{
  "type": "Feature",
  "properties": {
    "iso:country":"DE",
    "sg:address":"Rheinstr. 9A",
    "sg:city":"Worms",
    "sg:phone":"+49 6241/25567",
    "sg:postcode":"67547",
    "sg:province":"Rheinland-Pfalz",
    "wof:name":"Z. Bulut",
    "wof:placetype":"venue"
},
  "geometry": {"coordinates":[8.367026329,49.6322479248],"type":"Point"}
}