{
  "type": "Feature",
  "properties": {
    "iso:country":"DE",
    "sg:address":"Badstr. 6",
    "sg:city":"Freiburg",
    "sg:phone":"+49 761/67562",
    "sg:postcode":"79117",
    "sg:province":"Baden-W\u00fcrttemberg",
    "wof:name":"Gertraud Niemeier Heilpraktikerin",
    "wof:placetype":"venue"
},
  "geometry": {"coordinates":[7.8948807716,47.9792785645],"type":"Point"}
}