{
  "type": "Feature",
  "properties": {
    "iso:country":"DE",
    "sg:address":"Solitudestr. 30",
    "sg:city":"Ludwigsburg",
    "sg:phone":"+49 7141/924664",
    "sg:postcode":"71638",
    "sg:province":"Baden-W\u00fcrttemberg",
    "wof:name":"Kreutzer Per\u00fccken",
    "wof:placetype":"venue"
},
  "geometry": {"coordinates":[9.188325882,48.8919487],"type":"Point"}
}