{
  "type": "Feature",
  "properties": {
    "iso:country":"DE",
    "sg:address":"Forststr. 168",
    "sg:city":"Stuttgart",
    "sg:phone":"+49 711/6366469",
    "sg:postcode":"70193",
    "sg:province":"Baden-W\u00fcrttemberg",
    "wof:name":"A. Schiemann Praxis F\u00fcr Ergotherapie",
    "wof:placetype":"venue"
},
  "geometry": {"coordinates":[9.149473,48.775692],"type":"Point"}
}