{
  "type": "Feature",
  "properties": {
    "iso:country":"DE",
    "sg:address":"Sebastianstr. 123",
    "sg:city":"K\u00f6ln",
    "sg:phone":"+49 221/714266",
    "sg:postcode":"50735",
    "sg:province":"Nordrhein-Westfalen",
    "wof:name":"Sebastian-apotheke",
    "wof:placetype":"venue"
},
  "geometry": {"coordinates":[6.961121,50.987946],"type":"Point"}
}