{
  "type": "Feature",
  "properties": {
    "iso:country":"DE",
    "sg:address":"Bahnstr. 104",
    "sg:city":"D\u00fcren",
    "sg:phone":"+49 2421/65784",
    "sg:postcode":"52355",
    "sg:province":"Nordrhein-Westfalen",
    "wof:name":"Ingeb. Seel-wagner Hebamme",
    "wof:placetype":"venue"
},
  "geometry": {"coordinates":[6.463317,50.794708],"type":"Point"}
}