{
  "type": "Feature",
  "properties": {
    "iso:country":"DE",
    "sg:address":"F\u00fcrst-zu-Salm-Horstmar-Str. 5",
    "sg:city":"S\u00fcdlohn",
    "sg:phone":"+49 2862/6247",
    "sg:postcode":"46354",
    "sg:province":"Nordrhein-Westfalen",
    "wof:name":"Reinhold Fellerhoff",
    "wof:placetype":"venue"
},
  "geometry": {"coordinates":[6.808042,51.935753],"type":"Point"}
}