{
  "type": "Feature",
  "properties": {
    "iso:country":"DE",
    "sg:address":"Teutonenstr. 10",
    "sg:city":"Bocholt",
    "sg:postcode":"46395",
    "sg:province":"Nordrhein-Westfalen",
    "wof:name":"Unterst\u00fctzungskasse Der Firma Herbert Olbrich",
    "wof:placetype":"venue"
},
  "geometry": {"coordinates":[6.6099028587,51.8295402527],"type":"Point"}
}