{
  "type": "Feature",
  "properties": {
    "iso:country":"DE",
    "sg:address":"Ailinger Str. 30",
    "sg:city":"Friedrichshafen",
    "sg:phone":"+49 4975/4170050",
    "sg:postcode":"88046",
    "sg:province":"Baden-W\u00fcrttemberg",
    "wof:name":"Volksbank Friedrichshafen",
    "wof:placetype":"venue"
},
  "geometry": {"coordinates":[9.482246,47.657135],"type":"Point"}
}