{
  "type": "Feature",
  "properties": {
    "iso:country":"DE",
    "sg:address":"Borsigstr. 17",
    "sg:city":"Isernhagen",
    "sg:phone":"+49 4951/1902150",
    "sg:postcode":"30916",
    "sg:province":"Niedersachsen",
    "wof:name":"Hans Landmann & Co. Gmbh",
    "wof:placetype":"venue"
},
  "geometry": {"coordinates":[9.8360271454,52.4321365356],"type":"Point"}
}