{
  "type": "Feature",
  "properties": {
    "iso:country":"DE",
    "sg:address":"Markt 24",
    "sg:city":"Erftstadt",
    "sg:phone":"+49 2235/74148",
    "sg:postcode":"50374",
    "sg:province":"Nordrhein-Westfalen",
    "wof:name":"Birgit Paashaus",
    "wof:placetype":"venue"
},
  "geometry": {"coordinates":[6.7659401894,50.7998275757],"type":"Point"}
}