{
  "type": "Feature",
  "properties": {
    "iso:country":"DE",
    "sg:address":"Hertinger Weg 10",
    "sg:city":"Nesselwang",
    "sg:phone":"+49 8361/1353",
    "sg:postcode":"87484",
    "sg:province":"Bayern",
    "wof:name":"Martin Lotter Mechanische Fertigung Und",
    "wof:placetype":"venue"
},
  "geometry": {"coordinates":[10.5104675293,47.6197280884],"type":"Point"}
}