{
  "type": "Feature",
  "properties": {
    "iso:country":"DE",
    "sg:address":"B\u00fcchig 1",
    "sg:city":"Friedrichroda",
    "sg:phone":"+49 3623/304386",
    "sg:postcode":"99894",
    "sg:province":"Th\u00fcringen",
    "wof:name":"Pension Feierabend",
    "wof:placetype":"venue"
},
  "geometry": {"coordinates":[10.5579299927,50.8579101562],"type":"Point"}
}