{
  "type": "Feature",
  "properties": {
    "iso:country":"DE",
    "sg:address":"Bahnhofstrasse 27",
    "sg:city":"Calw",
    "sg:phone":"+49 7051/953250",
    "sg:postcode":"75365",
    "sg:province":"Baden-W\u00fcrttemberg",
    "wof:name":"Rotomedia Webservice & More",
    "wof:placetype":"venue"
},
  "geometry": {"coordinates":[8.7425060272,48.7120819092],"type":"Point"}
}