{
  "type": "Feature",
  "properties": {
    "iso:country":"DE",
    "sg:address":"Hof Altona",
    "sg:city":"Sierksdorf",
    "sg:phone":"+49 4945/638103",
    "sg:postcode":"23730",
    "sg:province":"Schleswig-Holstein",
    "wof:name":"Holsteinische Hagelgilde Vvag",
    "wof:placetype":"venue"
},
  "geometry": {"coordinates":[10.741505,54.072384],"type":"Point"}
}