{
  "type": "Feature",
  "properties": {
    "iso:country":"DE",
    "sg:address":"Martinstra\u00dfe 27",
    "sg:city":"Darmstadt",
    "sg:phone":"+49 6151",
    "sg:postcode":"64285",
    "sg:province":"Hessen",
    "wof:name":"Piano-berg Gmbh",
    "wof:placetype":"venue"
},
  "geometry": {"coordinates":[8.6571626663,49.8645782471],"type":"Point"}
}