{
  "type": "Feature",
  "properties": {
    "iso:country":"DE",
    "sg:address":"Richmodstr. 1",
    "sg:city":"K\u00f6ln",
    "sg:phone":"+49 221/253046",
    "sg:postcode":"50667",
    "sg:province":"Nordrhein-Westfalen",
    "wof:name":"Gummi Gr\u00fcn Gummi-handelshaus",
    "wof:placetype":"venue"
},
  "geometry": {"coordinates":[6.94756,50.93663],"type":"Point"}
}