{
  "type": "Feature",
  "properties": {
    "iso:country":"DE",
    "sg:address":"Mathildenstr. 17",
    "sg:city":"Dresden",
    "sg:phone":"+49 351/4426117",
    "sg:postcode":"01069",
    "sg:province":"Sachsen",
    "wof:name":"Familienzentrum Dresden E. V. Frau Schreiber",
    "wof:placetype":"venue"
},
  "geometry": {"coordinates":[13.752573967,51.0494270325],"type":"Point"}
}