{
  "type": "Feature",
  "properties": {
    "iso:country":"DE",
    "sg:address":"Dorfstr. 3",
    "sg:city":"Feilsdorf",
    "sg:phone":"+49 6527/593",
    "sg:postcode":"54636",
    "sg:province":"Rheinland-Pfalz",
    "wof:name":"Rudolf Ries",
    "wof:placetype":"venue"
},
  "geometry": {"coordinates":[6.4088587761,49.9894676208],"type":"Point"}
}