{
  "type": "Feature",
  "properties": {
    "iso:country":"DE",
    "sg:address":"Fr\u00fchlingstr. 3",
    "sg:city":"Gaggenau",
    "sg:phone":"+49 7224/1419",
    "sg:postcode":"76571",
    "sg:province":"Baden-W\u00fcrttemberg",
    "wof:name":"Maria Koch",
    "wof:placetype":"venue"
},
  "geometry": {"coordinates":[8.347327,48.783379],"type":"Point"}
}