{
  "type": "Feature",
  "properties": {
    "iso:country":"DE",
    "sg:address":"Hauptstr. 58",
    "sg:city":"Oyten",
    "sg:phone":"+49 4207/5966",
    "sg:postcode":"28876",
    "sg:province":"Niedersachsen",
    "wof:name":"Motel H\u00f6per Gmbh",
    "wof:placetype":"venue"
},
  "geometry": {"coordinates":[9.0211429596,53.0606956482],"type":"Point"}
}