{
  "type": "Feature",
  "properties": {
    "iso:country":"DE",
    "sg:address":"Alte Poststr. 6",
    "sg:city":"Kronach",
    "sg:phone":"+49 9261/2149",
    "sg:postcode":"96317",
    "sg:province":"Bayern",
    "wof:name":"A. Bauer",
    "wof:placetype":"venue"
},
  "geometry": {"coordinates":[11.309829,50.214504],"type":"Point"}
}