{
  "type": "Feature",
  "properties": {
    "iso:country":"DE",
    "sg:address":"Mauthstr. 9",
    "sg:city":"Ingolstadt",
    "sg:phone":"+49 841/9312233",
    "sg:postcode":"85049",
    "sg:province":"Bayern",
    "wof:name":"Kolinsky Und Pietsch Rechtsanw\u00e4lte",
    "wof:placetype":"venue"
},
  "geometry": {"coordinates":[11.4265489578,48.7635498047],"type":"Point"}
}