{
  "type": "Feature",
  "properties": {
    "iso:country":"DE",
    "sg:address":"Unterer Wingertweg 3",
    "sg:city":"Pforzheim",
    "sg:postcode":"75177",
    "sg:province":"Baden-W\u00fcrttemberg",
    "wof:name":"Delos Ag",
    "wof:placetype":"venue"
},
  "geometry": {"coordinates":[8.711318,48.901459],"type":"Point"}
}