{
  "type": "Feature",
  "properties": {
    "iso:country":"DE",
    "sg:address":"Heilwigstr. 88",
    "sg:city":"Hamburg",
    "sg:phone":"+49 40/4686510",
    "sg:postcode":"20249",
    "sg:province":"Hamburg",
    "wof:name":"Dr. Ingolf Kl\u00fcssendorf Rechtsanwalt",
    "wof:placetype":"venue"
},
  "geometry": {"coordinates":[9.9951181412,53.5863685608],"type":"Point"}
}