{
  "type": "Feature",
  "properties": {
    "iso:country":"DE",
    "sg:address":"G\u00f6ckelsweg 77",
    "sg:city":"M\u00f6nchengladbach",
    "sg:phone":"+49 2161/530443",
    "sg:postcode":"41068",
    "sg:province":"Nordrhein-Westfalen",
    "wof:name":"Hermann-martin Klein Rechtsanwalt",
    "wof:placetype":"venue"
},
  "geometry": {"coordinates":[6.3962421417,51.2041893005],"type":"Point"}
}