{
  "type": "Feature",
  "properties": {
    "iso:country":"DE",
    "sg:address":"Bachwiesenstr. 70",
    "sg:city":"Bad Steben",
    "sg:phone":"+49 9288/97420",
    "sg:postcode":"95138",
    "sg:province":"Bayern",
    "wof:name":"G\u00e4stehaus Frankenwaldhof",
    "wof:placetype":"venue"
},
  "geometry": {"coordinates":[11.6177778244,50.3646125793],"type":"Point"}
}