{
  "type": "Feature",
  "properties": {
    "iso:country":"DE",
    "sg:address":"Dr. Karl-Storz-Str. 16",
    "sg:city":"Tuttlingen",
    "sg:phone":"+49 7461/4054",
    "sg:postcode":"78532",
    "sg:province":"Baden-W\u00fcrttemberg",
    "wof:name":"Peter Bandle",
    "wof:placetype":"venue"
},
  "geometry": {"coordinates":[8.82362,47.993656],"type":"Point"}
}