{
  "type": "Feature",
  "properties": {
    "iso:country":"DE",
    "sg:address":"Zechenstr. 2",
    "sg:city":"K\u00f6ln",
    "sg:phone":"+49 221/8702255",
    "sg:postcode":"51103",
    "sg:province":"Nordrhein-Westfalen",
    "wof:name":"China-restaurant Lung-wah",
    "wof:placetype":"venue"
},
  "geometry": {"coordinates":[7.0128951073,50.9393424988],"type":"Point"}
}