{
  "type": "Feature",
  "properties": {
    "iso:country":"DE",
    "sg:address":"Leimenstr. 3",
    "sg:city":"Hanau",
    "sg:phone":"+49 6181/33300",
    "sg:postcode":"63450",
    "sg:province":"Hessen",
    "wof:name":"Herrmann",
    "wof:placetype":"venue"
},
  "geometry": {"coordinates":[8.92146,50.132435],"type":"Point"}
}