{
  "type": "Feature",
  "properties": {
    "iso:country":"DE",
    "sg:address":"Am Augraben 8",
    "sg:city":"G\u00fcstrow",
    "sg:phone":"+49 3843/214193",
    "sg:postcode":"18273",
    "sg:province":"Mecklenburg-Vorpommern",
    "wof:name":"Pollmann Pumpen Gmbh",
    "wof:placetype":"venue"
},
  "geometry": {"coordinates":[12.243168,53.805523],"type":"Point"}
}