{
  "type": "Feature",
  "properties": {
    "iso:country":"DE",
    "sg:address":"Nelkenweg 5",
    "sg:city":"Ruhstorf",
    "sg:phone":"+49 8531/31364",
    "sg:postcode":"94099",
    "sg:province":"Bayern",
    "wof:name":"Bekleidungs-e H",
    "wof:placetype":"venue"
},
  "geometry": {"coordinates":[13.329841,48.432575],"type":"Point"}
}