{
  "type": "Feature",
  "properties": {
    "iso:country":"DE",
    "sg:address":"Heisterbusch 4",
    "sg:city":"Salzgitter",
    "sg:phone":"+49 5341/52689",
    "sg:postcode":"38228",
    "sg:province":"Niedersachsen",
    "wof:name":"Klaus Weikamp",
    "wof:placetype":"venue"
},
  "geometry": {"coordinates":[10.2899,52.125961],"type":"Point"}
}