{
  "type": "Feature",
  "properties": {
    "iso:country":"DE",
    "sg:address":"Hammerbergweg 10",
    "sg:city":"Maitenbeth",
    "sg:phone":"+49 8076/9395",
    "sg:postcode":"83558",
    "sg:province":"Bayern",
    "wof:name":"Heide Von Berg-staib Immobilienmaklerin",
    "wof:placetype":"venue"
},
  "geometry": {"coordinates":[12.0963153839,48.148815155],"type":"Point"}
}