{
  "type": "Feature",
  "properties": {
    "iso:country":"DE",
    "sg:address":"Dornierstr. 17",
    "sg:city":"Stuttgart",
    "sg:phone":"+49 711/81040",
    "sg:postcode":"70469",
    "sg:province":"Baden-W\u00fcrttemberg",
    "wof:name":"Rud. Otto Mayer",
    "wof:placetype":"venue"
},
  "geometry": {"coordinates":[9.175639,48.812424],"type":"Point"}
}