{
  "type": "Feature",
  "properties": {
    "iso:country":"DE",
    "sg:address":"Lindenweg 5 d",
    "sg:city":"Bad Nauheim",
    "sg:phone":"+49 6032/84641",
    "sg:postcode":"61231",
    "sg:province":"Hessen",
    "wof:name":"Ingeborg Und Ulrich Grote Architekten",
    "wof:placetype":"venue"
},
  "geometry": {"coordinates":[8.746186,50.36499],"type":"Point"}
}