{
  "type": "Feature",
  "properties": {
    "iso:country":"DE",
    "sg:address":"Wipperf\u00fcrther Str. 389",
    "sg:city":"K\u00fcrten",
    "sg:phone":"+49 2268/6331",
    "sg:postcode":"51515",
    "sg:province":"Nordrhein-Westfalen",
    "wof:name":"Hans-josef Herzhoff",
    "wof:placetype":"venue"
},
  "geometry": {"coordinates":[7.268419,51.053596],"type":"Point"}
}