{
  "type": "Feature",
  "properties": {
    "iso:country":"DE",
    "sg:address":"Bahnhofstr. 3",
    "sg:city":"Grimma",
    "sg:postcode":"04668",
    "sg:province":"Sachsen",
    "wof:name":"Ipcv Institut F\u00fcr Physikalisch Chemische",
    "wof:placetype":"venue"
},
  "geometry": {"coordinates":[12.7155351639,51.2258148193],"type":"Point"}
}