{
  "type": "Feature",
  "properties": {
    "iso:country":"DE",
    "sg:address":"Ganderhofstr. 4",
    "sg:city":"Ludwigshafen",
    "sg:phone":"+49 621/5292294",
    "sg:postcode":"67063",
    "sg:province":"Rheinland-Pfalz",
    "wof:name":"Globetrotter",
    "wof:placetype":"venue"
},
  "geometry": {"coordinates":[8.4370622635,49.4902992249],"type":"Point"}
}