{
  "type": "Feature",
  "properties": {
    "iso:country":"DE",
    "sg:address":"Royberg 8",
    "sg:city":"Hanstedt",
    "sg:phone":"+49 4187/321647",
    "sg:postcode":"21271",
    "sg:province":"Niedersachsen",
    "wof:name":"Frank Reucher Architekt",
    "wof:placetype":"venue"
},
  "geometry": {"coordinates":[9.907334,53.2677],"type":"Point"}
}