{
  "type": "Feature",
  "properties": {
    "iso:country":"DE",
    "sg:address":"In der D\u00f6nne 50",
    "sg:city":"L\u00fcdenscheid",
    "sg:phone":"+49 2351/952566",
    "sg:postcode":"58513",
    "sg:province":"Nordrhein-Westfalen",
    "wof:name":"K. W. D\u00f6nneweg Architekt",
    "wof:placetype":"venue"
},
  "geometry": {"coordinates":[7.590001,51.246685],"type":"Point"}
}