{
  "type": "Feature",
  "properties": {
    "iso:country":"DE",
    "sg:address":"Hauptstr. 23",
    "sg:city":"Dernbach",
    "sg:phone":"+49 2689/1252",
    "sg:postcode":"56307",
    "sg:province":"Rheinland-Pfalz",
    "wof:name":"Sparkasse Neuwied",
    "wof:placetype":"venue"
},
  "geometry": {"coordinates":[7.598877,50.545311],"type":"Point"}
}