{
  "type": "Feature",
  "properties": {
    "iso:country":"DE",
    "sg:address":"Scharpenberg 72",
    "sg:city":"M\u00fclheim",
    "sg:phone":"+49 208/35539",
    "sg:postcode":"45468",
    "sg:province":"Nordrhein-Westfalen",
    "wof:name":"Hans-bernhard Heucken",
    "wof:placetype":"venue"
},
  "geometry": {"coordinates":[6.8808932304,51.4176139832],"type":"Point"}
}