{
  "type": "Feature",
  "properties": {
    "iso:country":"DE",
    "sg:address":"Bismarckstr. 53",
    "sg:city":"Bietigheim-Bissingen",
    "sg:phone":"+49 7142/21727",
    "sg:postcode":"74321",
    "sg:province":"Baden-W\u00fcrttemberg",
    "wof:name":"Dr. Med. Tanja Engels",
    "wof:placetype":"venue"
},
  "geometry": {"coordinates":[9.1370697021,48.9593505859],"type":"Point"}
}