{
  "type": "Feature",
  "properties": {
    "iso:country":"DE",
    "sg:address":"Sedanstr. 17",
    "sg:city":"Hagen",
    "sg:postcode":"58089",
    "sg:province":"Nordrhein-Westfalen",
    "wof:name":"Goldau Kg",
    "wof:placetype":"venue"
},
  "geometry": {"coordinates":[7.4554700851,51.3691825867],"type":"Point"}
}