{
  "type": "Feature",
  "properties": {
    "iso:country":"DE",
    "sg:address":"Wannen 99",
    "sg:city":"Witten",
    "sg:phone":"+49 2302/59460",
    "sg:postcode":"58455",
    "sg:province":"Nordrhein-Westfalen",
    "wof:name":"Johann Nowak",
    "wof:placetype":"venue"
},
  "geometry": {"coordinates":[7.314781189,51.4417076111],"type":"Point"}
}