{
  "type": "Feature",
  "properties": {
    "iso:country":"DE",
    "sg:address":"Zum Stein\u00e4scher 5",
    "sg:city":"Algermissen",
    "sg:phone":"+49 5126/1212",
    "sg:postcode":"31191",
    "sg:province":"Niedersachsen",
    "wof:name":"Helmut K\u00f6rner",
    "wof:placetype":"venue"
},
  "geometry": {"coordinates":[9.979461,52.283367],"type":"Point"}
}