{
  "type": "Feature",
  "properties": {
    "iso:country":"DE",
    "sg:address":"Marbachweg 234",
    "sg:city":"Frankfurt",
    "sg:phone":"+49 69/564641",
    "sg:postcode":"60320",
    "sg:province":"Hessen",
    "wof:name":"H. Und H. Eifert",
    "wof:placetype":"venue"
},
  "geometry": {"coordinates":[8.6826686859,50.1419372559],"type":"Point"}
}