{
  "type": "Feature",
  "properties": {
    "iso:country":"DE",
    "sg:address":"L\u00f6wenberger Str. 1-5",
    "sg:city":"Emmerich",
    "sg:phone":"+49 2822/5560",
    "sg:postcode":"46446",
    "sg:province":"Nordrhein-Westfalen",
    "wof:name":"Gebr. Van Beek Gmbh",
    "wof:placetype":"venue"
},
  "geometry": {"coordinates":[6.249154,51.835854],"type":"Point"}
}