{
  "type": "Feature",
  "properties": {
    "iso:country":"DE",
    "sg:address":"Hauptstr. 4",
    "sg:city":"Schmidgaden",
    "sg:phone":"+49 9435/3101",
    "sg:postcode":"92546",
    "sg:province":"Bayern",
    "wof:name":"C. Hofrichter",
    "wof:placetype":"venue"
},
  "geometry": {"coordinates":[12.0981721878,49.4236755371],"type":"Point"}
}