{
  "type": "Feature",
  "properties": {
    "iso:country":"DE",
    "sg:address":"Mathias-Hess-Str. 26",
    "sg:city":"Walldorf",
    "sg:phone":"+49 6227/63100",
    "sg:postcode":"69190",
    "sg:province":"Baden-W\u00fcrttemberg",
    "wof:name":"Kurt Horn Ingenieur",
    "wof:placetype":"venue"
},
  "geometry": {"coordinates":[8.6347770691,49.3058357239],"type":"Point"}
}