{
  "type": "Feature",
  "properties": {
    "iso:country":"DE",
    "sg:address":"Krugstr. 18",
    "sg:city":"Wingerode",
    "sg:phone":"+49 3605/502821",
    "sg:postcode":"37327",
    "sg:province":"Th\u00fcringen",
    "wof:name":"Dr. Erich Kny Zahnarzt",
    "wof:placetype":"venue"
},
  "geometry": {"coordinates":[10.245984,51.392147],"type":"Point"}
}