{
  "type": "Feature",
  "properties": {
    "iso:country":"DE",
    "sg:address":"Teplitzer Str. 7",
    "sg:city":"Berlin",
    "sg:phone":"+49 30/8255146",
    "sg:postcode":"14193",
    "sg:province":"Berlin",
    "wof:name":"Mabe Immobilien Gmbh",
    "wof:placetype":"venue"
},
  "geometry": {"coordinates":[13.2809238434,52.4810714722],"type":"Point"}
}