{
  "type": "Feature",
  "properties": {
    "iso:country":"DE",
    "sg:address":"Ringstr. 8",
    "sg:city":"Hannover",
    "sg:phone":"+49 511/434111",
    "sg:postcode":"30457",
    "sg:province":"Niedersachsen",
    "wof:name":"Arnhorlds Gmbh",
    "wof:placetype":"venue"
},
  "geometry": {"coordinates":[9.6905355453,52.324886322],"type":"Point"}
}