{
  "type": "Feature",
  "properties": {
    "iso:country":"DE",
    "sg:address":"Damaschkestr. 31",
    "sg:city":"Rog\u00e4tz",
    "sg:phone":"+49 39208/50131",
    "sg:postcode":"39326",
    "sg:province":"Sachsen-Anhalt",
    "wof:name":"Schwerlast - Trans - Gmbh",
    "wof:placetype":"venue"
},
  "geometry": {"coordinates":[11.75516,52.322319],"type":"Point"}
}