{
  "type": "Feature",
  "properties": {
    "iso:country":"DE",
    "sg:address":"Leharstra\u00dfe 7/1",
    "sg:city":"Ditzingen",
    "sg:phone":"+49 7156/5755",
    "sg:postcode":"71254",
    "sg:province":"Baden-W\u00fcrttemberg",
    "wof:name":"Edition Musica Rinata - Musikverlag Und Notenversa",
    "wof:placetype":"venue"
},
  "geometry": {"coordinates":[9.058444,48.825668],"type":"Point"}
}