{
  "type": "Feature",
  "properties": {
    "iso:country":"DE",
    "sg:address":"Schneidm\u00fchle 1",
    "sg:city":"Sinntal",
    "sg:phone":"+49 6664/8547",
    "sg:postcode":"36391",
    "sg:province":"Hessen",
    "wof:name":"Heinrich Ochs",
    "wof:placetype":"venue"
},
  "geometry": {"coordinates":[9.7066202164,50.3354568481],"type":"Point"}
}