{
  "type": "Feature",
  "properties": {
    "iso:country":"DE",
    "sg:address":"Krummenweger Str. 161",
    "sg:city":"Ratingen",
    "sg:phone":"+49 2102/17007",
    "sg:postcode":"40885",
    "sg:province":"Nordrhein-Westfalen",
    "wof:name":"F. Raudszus",
    "wof:placetype":"venue"
},
  "geometry": {"coordinates":[6.8501200676,51.3361244202],"type":"Point"}
}