{
  "type": "Feature",
  "properties": {
    "iso:country":"DE",
    "sg:address":"Waldweg 1",
    "sg:city":"Lohberg",
    "sg:phone":"+49 9943/8560",
    "sg:postcode":"93470",
    "sg:province":"Bayern",
    "wof:name":"Pension Alfons Loderbauer",
    "wof:placetype":"venue"
},
  "geometry": {"coordinates":[13.0908622742,49.1643218994],"type":"Point"}
}