{
  "type": "Feature",
  "properties": {
    "iso:country":"DE",
    "sg:address":"Domstr. 2",
    "sg:city":"Minden",
    "sg:phone":"+49 571/8290659",
    "sg:postcode":"32423",
    "sg:province":"Nordrhein-Westfalen",
    "wof:name":"Minden-marketing Gmbh",
    "wof:placetype":"venue"
},
  "geometry": {"coordinates":[8.91837883,52.2879562378],"type":"Point"}
}