{
  "type": "Feature",
  "properties": {
    "iso:country":"DE",
    "sg:address":"Hans-Lohnert-Str. 7",
    "sg:city":"F\u00fcrth",
    "sg:phone":"+49 911/711926",
    "sg:postcode":"90763",
    "sg:province":"Bayern",
    "wof:name":"Friedrich Heid Steuerberater",
    "wof:placetype":"venue"
},
  "geometry": {"coordinates":[10.9908246994,49.46068573],"type":"Point"}
}