{
  "type": "Feature",
  "properties": {
    "iso:country":"DE",
    "sg:address":"Am G\u00f6hrenanger 5",
    "sg:city":"Schm\u00f6lln",
    "sg:phone":"+49 34491/82543",
    "sg:postcode":"04626",
    "sg:province":"Th\u00fcringen",
    "wof:name":"U. Geithel",
    "wof:placetype":"venue"
},
  "geometry": {"coordinates":[12.3519487381,50.8905334473],"type":"Point"}
}