{
  "type": "Feature",
  "properties": {
    "iso:country":"DE",
    "sg:address":"Preetzer Str. 14",
    "sg:city":"Nettelsee",
    "sg:phone":"+49 4302/661",
    "sg:postcode":"24250",
    "sg:province":"Schleswig-Holstein",
    "wof:name":"Peter Kistenmacher",
    "wof:placetype":"venue"
},
  "geometry": {"coordinates":[10.199745,54.183334],"type":"Point"}
}