{
  "type": "Feature",
  "properties": {
    "iso:country":"DE",
    "sg:address":"Herrlichkeit 35",
    "sg:city":"Syke",
    "sg:phone":"+49 4242/4055",
    "sg:postcode":"28857",
    "sg:province":"Niedersachsen",
    "wof:name":"Sylvia Kastner",
    "wof:placetype":"venue"
},
  "geometry": {"coordinates":[8.828387,52.916626],"type":"Point"}
}