{
  "type": "Feature",
  "properties": {
    "iso:country":"DE",
    "sg:address":"Kaiserstr. 45",
    "sg:city":"W\u00fcrselen",
    "sg:phone":"+49 2405/14379",
    "sg:postcode":"52146",
    "sg:province":"Nordrhein-Westfalen",
    "wof:name":"Franz Schnorrenberg",
    "wof:placetype":"venue"
},
  "geometry": {"coordinates":[6.131009,50.820274],"type":"Point"}
}