{
  "type": "Feature",
  "properties": {
    "iso:country":"DE",
    "sg:address":"Dorfstr. 2",
    "sg:city":"Ismaning",
    "sg:phone":"+49 89/965826",
    "sg:postcode":"85737",
    "sg:province":"Bayern",
    "wof:name":"Korbinian Zacherl",
    "wof:placetype":"venue"
},
  "geometry": {"coordinates":[11.673969,48.224621],"type":"Point"}
}