{
  "type": "Feature",
  "properties": {
    "iso:country":"DE",
    "sg:address":"August-Schanz-Str. 24",
    "sg:city":"Frankfurt",
    "sg:phone":"+49 69/5482448",
    "sg:postcode":"60433",
    "sg:province":"Hessen",
    "wof:name":"Tus Makkabi Frankfurt",
    "wof:placetype":"venue"
},
  "geometry": {"coordinates":[8.687789917,50.1634483337],"type":"Point"}
}