{
  "type": "Feature",
  "properties": {
    "iso:country":"DE",
    "sg:address":"An der Ziegelei 1",
    "sg:city":"Eschwege",
    "sg:phone":"+49 5652/2136",
    "sg:postcode":"37269",
    "sg:province":"Hessen",
    "wof:name":"Hesse Gmbh",
    "wof:placetype":"venue"
},
  "geometry": {"coordinates":[9.98644,51.234928],"type":"Point"}
}