{
  "type": "Feature",
  "properties": {
    "iso:country":"DE",
    "sg:address":"Endenicher Str. 343",
    "sg:city":"Bonn",
    "sg:phone":"+49 228/625542",
    "sg:postcode":"53121",
    "sg:province":"Nordrhein-Westfalen",
    "wof:name":"Klaus Herrmann Masseur",
    "wof:placetype":"venue"
},
  "geometry": {"coordinates":[7.071495,50.726143],"type":"Point"}
}