{
  "type": "Feature",
  "properties": {
    "iso:country":"DE",
    "sg:address":"Friedrichstr. 14a",
    "sg:city":"Hennickendorf",
    "sg:phone":"+49 33434/45721",
    "sg:postcode":"15378",
    "sg:province":"Brandenburg",
    "wof:name":"P\u00f6schel & Partner Gmbh & Co. Kg",
    "wof:placetype":"venue"
},
  "geometry": {"coordinates":[13.844298,52.504704],"type":"Point"}
}