{
  "type": "Feature",
  "properties": {
    "iso:country":"DE",
    "sg:address":"Georgsheiler Weg",
    "sg:city":"S\u00fcdbrookmerland",
    "sg:phone":"+49 4942/1581",
    "sg:postcode":"26624",
    "sg:province":"Niedersachsen",
    "wof:name":"Dr. Gerhard Pfl\u00fcger Tierarzt",
    "wof:placetype":"venue"
},
  "geometry": {"coordinates":[7.3231310844,53.4767112732],"type":"Point"}
}