{
  "type": "Feature",
  "properties": {
    "iso:country":"DE",
    "sg:address":"Bahnhofstr. 2",
    "sg:city":"Kerpen",
    "sg:phone":"+49 2273/4509",
    "sg:postcode":"50169",
    "sg:province":"Nordrhein-Westfalen",
    "wof:name":"Dackweiler",
    "wof:placetype":"venue"
},
  "geometry": {"coordinates":[6.710248,50.914566],"type":"Point"}
}