{
  "type": "Feature",
  "properties": {
    "iso:country":"DE",
    "sg:address":"Sudetenstr. 29",
    "sg:city":"Feldkirchen",
    "sg:postcode":"85622",
    "sg:province":"Bayern",
    "wof:name":"Wolfsburger Deutschland Gmbh",
    "wof:placetype":"venue"
},
  "geometry": {"coordinates":[11.7179813385,48.1482696533],"type":"Point"}
}