{
  "type": "Feature",
  "properties": {
    "iso:country":"DE",
    "sg:address":"Auguststr. 7",
    "sg:city":"Bad Salzuflen",
    "sg:phone":"+49 5222/83111",
    "sg:postcode":"32108",
    "sg:province":"Nordrhein-Westfalen",
    "wof:name":"H. Epke",
    "wof:placetype":"venue"
},
  "geometry": {"coordinates":[8.751883,52.070435],"type":"Point"}
}