{
  "type": "Feature",
  "properties": {
    "iso:country":"DE",
    "sg:address":"Altenhofer Str. 57",
    "sg:city":"Solingen",
    "sg:phone":"+49 212/315863",
    "sg:postcode":"42719",
    "sg:province":"Nordrhein-Westfalen",
    "wof:name":"K. L\u00fcddecke",
    "wof:placetype":"venue"
},
  "geometry": {"coordinates":[7.0342020988,51.1820220947],"type":"Point"}
}