{
  "type": "Feature",
  "properties": {
    "iso:country":"DE",
    "sg:address":"Kleekamp 1",
    "sg:city":"Hamburg",
    "sg:phone":"+49 40/590655",
    "sg:postcode":"22339",
    "sg:province":"Hamburg",
    "wof:name":"S. J. Pabst Textil",
    "wof:placetype":"venue"
},
  "geometry": {"coordinates":[10.025793,53.632496],"type":"Point"}
}