{
  "type": "Feature",
  "properties": {
    "iso:country":"DE",
    "sg:address":"Hauptstr. 448",
    "sg:city":"Saterland",
    "sg:phone":"+49 4498/2575",
    "sg:postcode":"26683",
    "sg:province":"Niedersachsen",
    "wof:name":"Johannes Oltmanns Gmbh",
    "wof:placetype":"venue"
},
  "geometry": {"coordinates":[7.69306,53.094681],"type":"Point"}
}