{
  "type": "Feature",
  "properties": {
    "iso:country":"DE",
    "sg:address":"Zum Merschbach 21",
    "sg:city":"Ennigerloh",
    "sg:phone":"+49 2524/1685",
    "sg:postcode":"59320",
    "sg:province":"Nordrhein-Westfalen",
    "wof:name":"H. Picken\u00e4cker Gmbh",
    "wof:placetype":"venue"
},
  "geometry": {"coordinates":[8.041322,51.832111],"type":"Point"}
}