{
  "type": "Feature",
  "properties": {
    "iso:country":"DE",
    "sg:address":"Kappellenstr. 4",
    "sg:city":"Beedenbostel",
    "sg:phone":"+49 4951/4122297",
    "sg:postcode":"29355",
    "sg:province":"Niedersachsen",
    "wof:name":"Denecke",
    "wof:placetype":"venue"
},
  "geometry": {"coordinates":[10.262606,52.6422],"type":"Point"}
}