{
  "type": "Feature",
  "properties": {
    "iso:country":"DE",
    "sg:address":"86704",
    "sg:city":"Tagmersheim",
    "sg:postcode":"86704",
    "sg:province":"Bayern",
    "wof:name":"Raiffeisenbank Tagmersheim Eg",
    "wof:placetype":"venue"
},
  "geometry": {"coordinates":[10.97204,48.822063],"type":"Point"}
}