{
  "type": "Feature",
  "properties": {
    "iso:country":"DE",
    "sg:address":"Ruhlsdorfer Weg 7",
    "sg:city":"Nuthe-Urstromtal",
    "sg:phone":"+49 33732/40305",
    "sg:postcode":"14947",
    "sg:province":"Brandenburg",
    "wof:name":"Pension Kastner",
    "wof:placetype":"venue"
},
  "geometry": {"coordinates":[13.1202297211,52.1396789551],"type":"Point"}
}