{
  "type": "Feature",
  "properties": {
    "iso:country":"DE",
    "sg:address":"Buschstr. 96",
    "sg:city":"Krefeld",
    "sg:phone":"+49 2151/592546",
    "sg:postcode":"47800",
    "sg:province":"Nordrhein-Westfalen",
    "wof:name":"Christel Th\u00f6ne Lebensmittel",
    "wof:placetype":"venue"
},
  "geometry": {"coordinates":[6.6005787849,51.351272583],"type":"Point"}
}