{
  "type": "Feature",
  "properties": {
    "iso:country":"DE",
    "sg:address":"Lindenweg 17",
    "sg:city":"Pfreimd",
    "sg:phone":"+49 9606/361",
    "sg:postcode":"92536",
    "sg:province":"Bayern",
    "wof:name":"Georg Sch\u00f6nberger Ingenieur",
    "wof:placetype":"venue"
},
  "geometry": {"coordinates":[12.1899518967,49.4993667603],"type":"Point"}
}