{
  "type": "Feature",
  "properties": {
    "iso:country":"DE",
    "sg:address":"Zeppelinstr. 115",
    "sg:city":"Frankfurt",
    "sg:phone":"+49 69",
    "sg:postcode":"60487",
    "sg:province":"Hessen",
    "wof:name":"Ballettschule Hanno Hassloch",
    "wof:placetype":"venue"
},
  "geometry": {"coordinates":[8.64563,50.12883],"type":"Point"}
}