{
  "type": "Feature",
  "properties": {
    "iso:country":"DE",
    "sg:address":"Stra\u00dfe des Friedens 38",
    "sg:city":"Leinefelde",
    "sg:phone":"+49 3605/2346",
    "sg:postcode":"37327",
    "sg:province":"Th\u00fcringen",
    "wof:name":"C. Beykirch",
    "wof:placetype":"venue"
},
  "geometry": {"coordinates":[10.3324298859,51.3862342834],"type":"Point"}
}