{
  "type": "Feature",
  "properties": {
    "iso:country":"DE",
    "sg:address":"Rothschwaiger Str. 8",
    "sg:city":"Sch\u00f6ngeising",
    "sg:phone":"+49 8141/23140",
    "sg:postcode":"82296",
    "sg:province":"Bayern",
    "wof:name":"Probasys Software Gmbh",
    "wof:placetype":"venue"
},
  "geometry": {"coordinates":[11.2003192902,48.1451377869],"type":"Point"}
}