{
  "type": "Feature",
  "properties": {
    "iso:country":"DE",
    "sg:address":"Holl\u00e4ndische Str. 2",
    "sg:city":"Breuna",
    "sg:phone":"+49 5676/925050",
    "sg:postcode":"34479",
    "sg:province":"Hessen",
    "wof:name":"Ingenieurb\u00fcro F\u00fcr Fahrzeug- Und Maschinentechnik",
    "wof:placetype":"venue"
},
  "geometry": {"coordinates":[9.2451667786,51.4497032166],"type":"Point"}
}