{
  "type": "Feature",
  "properties": {
    "iso:country":"DE",
    "sg:address":"Barstr. 32",
    "sg:city":"Berlin",
    "sg:phone":"+49 30/8235050",
    "sg:postcode":"10713",
    "sg:province":"Berlin",
    "wof:name":"T & S Taxi Und Service Gmbh",
    "wof:placetype":"venue"
},
  "geometry": {"coordinates":[13.3132867813,52.4812583923],"type":"Point"}
}