{
  "type": "Feature",
  "properties": {
    "iso:country":"DE",
    "sg:address":"Dalbergstr. 8",
    "sg:city":"Frankfurt",
    "sg:phone":"+49 69/302018",
    "sg:postcode":"65929",
    "sg:province":"Hessen",
    "wof:name":"Bernard Und Baumg\u00e4rtner Rechtsanw\u00e4lte",
    "wof:placetype":"venue"
},
  "geometry": {"coordinates":[8.5437278748,50.1018829346],"type":"Point"}
}