{
  "type": "Feature",
  "properties": {
    "iso:country":"DE",
    "sg:address":"Robert-Koch-Str. 3",
    "sg:city":"Konstanz",
    "sg:phone":"+49 7531/699515",
    "sg:postcode":"78464",
    "sg:province":"Baden-W\u00fcrttemberg",
    "wof:name":"Alois Kern Architekt",
    "wof:placetype":"venue"
},
  "geometry": {"coordinates":[9.192344,47.679382],"type":"Point"}
}