{
  "type": "Feature",
  "properties": {
    "iso:country":"DE",
    "sg:address":"Schwabhauser Str. 22",
    "sg:city":"Penzing",
    "sg:phone":"+49 8191/989105",
    "sg:postcode":"86929",
    "sg:province":"Bayern",
    "wof:name":"Alfred Rief",
    "wof:placetype":"venue"
},
  "geometry": {"coordinates":[10.934314,48.076927],"type":"Point"}
}