{
  "type": "Feature",
  "properties": {
    "iso:country":"DE",
    "sg:address":"Flemminger Weg",
    "sg:city":"Naumburg",
    "sg:phone":"+49 3445/776466",
    "sg:postcode":"06618",
    "sg:province":"Sachsen-Anhalt",
    "wof:name":"Gartenlokal Sch\u00f6ne Aussicht",
    "wof:placetype":"venue"
},
  "geometry": {"coordinates":[11.7838106155,51.1438827515],"type":"Point"}
}