{
  "type": "Feature",
  "properties": {
    "iso:country":"DE",
    "sg:address":"Bei der Kirche 3",
    "sg:city":"B\u00fcdingen",
    "sg:phone":"+49 6041/1540",
    "sg:postcode":"63654",
    "sg:province":"Hessen",
    "wof:name":"Ev. Pfarramt D\u00fcdelsheim",
    "wof:placetype":"venue"
},
  "geometry": {"coordinates":[9.0286531448,50.2943725586],"type":"Point"}
}