{
  "type": "Feature",
  "properties": {
    "iso:country":"DE",
    "sg:address":"Philipp-Reis-Str. 3",
    "sg:city":"Butzbach",
    "sg:phone":"+49 6033/6942",
    "sg:postcode":"35510",
    "sg:province":"Hessen",
    "wof:name":"Toom-baumarkt",
    "wof:placetype":"venue"
},
  "geometry": {"coordinates":[8.6832008362,50.4350280762],"type":"Point"}
}