{
  "type": "Feature",
  "properties": {
    "iso:country":"DE",
    "sg:address":"Begonienstr. 20",
    "sg:city":"D\u00fcsseldorf",
    "sg:postcode":"40474",
    "sg:province":"Nordrhein-Westfalen",
    "wof:name":"Oberschulte-beckmann Architekt",
    "wof:placetype":"venue"
},
  "geometry": {"coordinates":[6.75217,51.262203],"type":"Point"}
}