{
  "type": "Feature",
  "properties": {
    "iso:country":"DE",
    "sg:city":"frechen",
    "sg:phone":"+49 2234/24289",
    "sg:postcode":"50226",
    "sg:province":"Nordrhein-Westfalen",
    "wof:name":"A Abflusshilfe Atn - Dieter Alfes",
    "wof:placetype":"venue"
},
  "geometry": {"coordinates":[6.8093,50.910751],"type":"Point"}
}