{
  "type": "Feature",
  "properties": {
    "iso:country":"DE",
    "sg:address":"Erich-Weinert-Str. 11",
    "sg:city":"Hohenleuben",
    "sg:postcode":"07958",
    "sg:province":"Th\u00fcringen",
    "wof:name":"Kinderheim Erich Weinert",
    "wof:placetype":"venue"
},
  "geometry": {"coordinates":[12.0529203415,50.7090682983],"type":"Point"}
}