{
  "type": "Feature",
  "properties": {
    "iso:country":"DE",
    "sg:address":"Garstedter Feldstr. 3",
    "sg:city":"Norderstedt",
    "sg:phone":"+49 40/5235723",
    "sg:postcode":"22850",
    "sg:province":"Schleswig-Holstein",
    "wof:name":"J\u00fcrgen Albrecht Ingenieur Architekt",
    "wof:placetype":"venue"
},
  "geometry": {"coordinates":[9.983222,53.686787],"type":"Point"}
}