{
  "type": "Feature",
  "properties": {
    "iso:country":"DE",
    "sg:address":"Kirchberger Str. 28",
    "sg:city":"Gerabronn",
    "sg:phone":"+49 7952/6272",
    "sg:postcode":"74582",
    "sg:province":"Baden-W\u00fcrttemberg",
    "wof:name":"Backstube Vollkornb\u00e4ckerei Gmbh",
    "wof:placetype":"venue"
},
  "geometry": {"coordinates":[9.886397,49.211136],"type":"Point"}
}