{
  "type": "Feature",
  "properties": {
    "iso:country":"DE",
    "sg:address":"M\u00fcnchener Str. 37",
    "sg:city":"Wiesbaden",
    "sg:phone":"+49 6122/51968",
    "sg:postcode":"65205",
    "sg:province":"Hessen",
    "wof:name":"Kurt Herrgen Alt- Und Abfallstoffe",
    "wof:placetype":"venue"
},
  "geometry": {"coordinates":[8.363614,50.040398],"type":"Point"}
}