{
  "type": "Feature",
  "properties": {
    "iso:country":"DE",
    "sg:address":"Gladbacher Str. 51",
    "sg:city":"Langenfeld",
    "sg:phone":"+49 2173/907480",
    "sg:postcode":"40764",
    "sg:province":"Nordrhein-Westfalen",
    "wof:name":"Niggemann Gmbh",
    "wof:placetype":"venue"
},
  "geometry": {"coordinates":[6.973311,51.115788],"type":"Point"}
}