{
  "type": "Feature",
  "properties": {
    "iso:country":"DE",
    "sg:address":"Im Sand 3",
    "sg:city":"Kirchberg",
    "sg:phone":"+49 7954/432",
    "sg:postcode":"74592",
    "sg:province":"Baden-W\u00fcrttemberg",
    "wof:name":"Emil Roth",
    "wof:placetype":"venue"
},
  "geometry": {"coordinates":[9.965392,49.204746],"type":"Point"}
}