{
  "type": "Feature",
  "properties": {
    "iso:country":"DE",
    "sg:address":"Bildstr. 76",
    "sg:city":"Flein",
    "sg:phone":"+49 7131/255343",
    "sg:postcode":"74223",
    "sg:province":"Baden-W\u00fcrttemberg",
    "wof:name":"Elektro Haller Gmbh",
    "wof:placetype":"venue"
},
  "geometry": {"coordinates":[9.214266,49.109474],"type":"Point"}
}