{
  "type": "Feature",
  "properties": {
    "iso:country":"DE",
    "sg:address":"Gerresheimer Str. 275",
    "sg:city":"Hilden",
    "sg:phone":"+49 2103/43857",
    "sg:postcode":"40721",
    "sg:province":"Nordrhein-Westfalen",
    "wof:name":"Josef Tondorf",
    "wof:placetype":"venue"
},
  "geometry": {"coordinates":[6.924102,51.186058],"type":"Point"}
}