{
  "type": "Feature",
  "properties": {
    "iso:country":"DE",
    "sg:address":"Baldingerstr.",
    "sg:city":"Marburg",
    "sg:phone":"+49 6421/27488",
    "sg:postcode":"35043",
    "sg:province":"Hessen",
    "wof:name":"M. Schneider",
    "wof:placetype":"venue"
},
  "geometry": {"coordinates":[8.808536,50.817364],"type":"Point"}
}