{
  "type": "Feature",
  "properties": {
    "iso:country":"DE",
    "sg:address":"Bahnhofstr. 10",
    "sg:city":"Montabaur",
    "sg:phone":"+49 2602/3446",
    "sg:postcode":"56410",
    "sg:province":"Rheinland-Pfalz",
    "wof:name":"Gastst\u00e4tte K.-h. Fries",
    "wof:placetype":"venue"
},
  "geometry": {"coordinates":[7.8295178413,50.4371643066],"type":"Point"}
}