{
  "type": "Feature",
  "properties": {
    "iso:country":"DE",
    "sg:address":"Seelhorststr. 4",
    "sg:city":"Hannover",
    "sg:postcode":"30175",
    "sg:province":"Niedersachsen",
    "wof:name":"Milchwirtschaftliche Verwer- Tungsgemeinschaft Eg",
    "wof:placetype":"venue"
},
  "geometry": {"coordinates":[9.754904,52.37606],"type":"Point"}
}