{
  "type": "Feature",
  "properties": {
    "iso:country":"DE",
    "sg:address":"Orlam\u00fcnder Str. 14",
    "sg:city":"Ludwigsstadt",
    "sg:phone":"+49 9263/1751",
    "sg:postcode":"96337",
    "sg:province":"Bayern",
    "wof:name":"Horst Opel",
    "wof:placetype":"venue"
},
  "geometry": {"coordinates":[11.370207,50.509701],"type":"Point"}
}