{
  "type": "Feature",
  "properties": {
    "iso:country":"DE",
    "sg:address":"Fuhrberger Landstr. 28",
    "sg:city":"Celle",
    "sg:phone":"+49 5141/940514",
    "sg:postcode":"29225",
    "sg:province":"Niedersachsen",
    "wof:name":"M. Martin",
    "wof:placetype":"venue"
},
  "geometry": {"coordinates":[10.0211439133,52.6052856445],"type":"Point"}
}