{
  "type": "Feature",
  "properties": {
    "iso:country":"DE",
    "sg:address":"Badener Str. 30",
    "sg:city":"Gaggenau",
    "sg:phone":"+49 7225/2326",
    "sg:postcode":"76571",
    "sg:province":"Baden-W\u00fcrttemberg",
    "wof:name":"Martin Schulz Architekt",
    "wof:placetype":"venue"
},
  "geometry": {"coordinates":[8.313317,48.781239],"type":"Point"}
}