{
  "type": "Feature",
  "properties": {
    "iso:country":"DE",
    "sg:address":"Danziger Str. 39",
    "sg:city":"Altdorf",
    "sg:phone":"+49 9187/2647",
    "sg:postcode":"90518",
    "sg:province":"Bayern",
    "wof:name":"Werner Mailer",
    "wof:placetype":"venue"
},
  "geometry": {"coordinates":[11.3662233353,49.3830375671],"type":"Point"}
}