{
  "type": "Feature",
  "properties": {
    "iso:country":"DE",
    "sg:city":"Sch\u00f6ntal",
    "sg:phone":"+49 4979/432234",
    "sg:postcode":"74214",
    "sg:province":"Baden-W\u00fcrttemberg",
    "wof:name":"Volksbank K\u00fcnzelsau Eg",
    "wof:placetype":"venue"
},
  "geometry": {"coordinates":[9.561353,49.341682],"type":"Point"}
}