{
  "type": "Feature",
  "properties": {
    "iso:country":"DE",
    "sg:address":"Riemenschneiderstr 2",
    "sg:city":"Th\u00fcngersheim",
    "sg:phone":"+49 9364/7145",
    "sg:postcode":"97291",
    "sg:province":"Bayern",
    "wof:name":"Zb 19 Kugellagerservice",
    "wof:placetype":"venue"
},
  "geometry": {"coordinates":[9.845273,49.884739],"type":"Point"}
}