{
  "type": "Feature",
  "properties": {
    "iso:country":"DE",
    "sg:address":"Iburger Str. 32",
    "sg:city":"Hilter",
    "sg:phone":"+49 5409/254",
    "sg:postcode":"49176",
    "sg:province":"Niedersachsen",
    "wof:name":"Matthias Overschmidt",
    "wof:placetype":"venue"
},
  "geometry": {"coordinates":[8.154173851,52.1874809265],"type":"Point"}
}