{
  "type": "Feature",
  "properties": {
    "iso:country":"DE",
    "sg:address":"Weinbergstr. 20",
    "sg:city":"Hohenroth",
    "sg:phone":"+49 9771/4071",
    "sg:postcode":"97618",
    "sg:province":"Bayern",
    "wof:name":"Du-wi Disco Gmbh",
    "wof:placetype":"venue"
},
  "geometry": {"coordinates":[10.145584,50.336823],"type":"Point"}
}