{
  "type": "Feature",
  "properties": {
    "iso:country":"DE",
    "sg:address":"Riedstr. 8",
    "sg:city":"Herbolzheim",
    "sg:phone":"+49 7643/6300",
    "sg:postcode":"79336",
    "sg:province":"Baden-W\u00fcrttemberg",
    "wof:name":"Heinz Kehnel",
    "wof:placetype":"venue"
},
  "geometry": {"coordinates":[7.8278532028,48.2192878723],"type":"Point"}
}