{
  "type": "Feature",
  "properties": {
    "iso:country":"DE",
    "sg:address":"Anzinger Str. 4",
    "sg:city":"M\u00fcnchen",
    "sg:phone":"+49 89/492235",
    "sg:postcode":"81671",
    "sg:province":"Bayern",
    "wof:name":"Doris M\u00fcller",
    "wof:placetype":"venue"
},
  "geometry": {"coordinates":[11.606809,48.120667],"type":"Point"}
}