{
  "type": "Feature",
  "properties": {
    "iso:country":"DE",
    "sg:address":"Marktredwitzer Str. 32",
    "sg:city":"Waldershof",
    "sg:phone":"+49 9231/71454",
    "sg:postcode":"95679",
    "sg:province":"Bayern",
    "wof:name":"Siegfried Imelauer",
    "wof:placetype":"venue"
},
  "geometry": {"coordinates":[12.068335,49.982517],"type":"Point"}
}