{
  "type": "Feature",
  "properties": {
    "iso:country":"DE",
    "sg:address":"M\u00f6nchsbergstr. 21",
    "sg:city":"Brackenheim",
    "sg:phone":"+49 7135/4344",
    "sg:postcode":"74336",
    "sg:province":"Baden-W\u00fcrttemberg",
    "wof:name":"Zur Traube",
    "wof:placetype":"venue"
},
  "geometry": {"coordinates":[9.0778408051,49.0875663757],"type":"Point"}
}