{
  "type": "Feature",
  "properties": {
    "iso:country":"DE",
    "sg:address":"Dorfstr. 23",
    "sg:city":"Borstel-Hohenraden",
    "sg:phone":"+49 4101/75489",
    "sg:postcode":"25494",
    "sg:province":"Schleswig-Holstein",
    "wof:name":"H.-h. Meyer",
    "wof:placetype":"venue"
},
  "geometry": {"coordinates":[9.807079,53.69239],"type":"Point"}
}