{
  "type": "Feature",
  "properties": {
    "iso:country":"DE",
    "sg:address":"Sinsheim",
    "sg:city":"Sinsheim",
    "sg:phone":"+49 7266/451",
    "sg:postcode":"74889",
    "sg:province":"Baden-W\u00fcrttemberg",
    "wof:name":"Volksbank Sinsheim Eg",
    "wof:placetype":"venue"
},
  "geometry": {"coordinates":[8.88717,49.2346],"type":"Point"}
}