{
  "type": "Feature",
  "properties": {
    "iso:country":"DE",
    "sg:address":"Charlottenstr. 9",
    "sg:city":"Ravensburg",
    "sg:phone":"+49 751/25457",
    "sg:postcode":"88212",
    "sg:province":"Baden-W\u00fcrttemberg",
    "wof:name":"J\u00e4gerst\u00fcble",
    "wof:placetype":"venue"
},
  "geometry": {"coordinates":[9.6125497818,47.7835197449],"type":"Point"}
}