{
  "type": "Feature",
  "properties": {
    "iso:country":"DE",
    "sg:address":"Frohlinder Str. 35",
    "sg:city":"Dortmund",
    "sg:phone":"+49 231/677749",
    "sg:postcode":"44379",
    "sg:province":"Nordrhein-Westfalen",
    "wof:name":"Haus Leffler",
    "wof:placetype":"venue"
},
  "geometry": {"coordinates":[7.3683381081,51.5248756409],"type":"Point"}
}