{
  "type": "Feature",
  "properties": {
    "iso:country":"DE",
    "sg:address":"Tiergartenstr. 5",
    "sg:city":"Hannover",
    "sg:phone":"+49 511/520630",
    "sg:postcode":"30559",
    "sg:province":"Niedersachsen",
    "wof:name":"Werner Meyer",
    "wof:placetype":"venue"
},
  "geometry": {"coordinates":[9.813159,52.365948],"type":"Point"}
}