{
  "type": "Feature",
  "properties": {
    "iso:country":"DE",
    "sg:address":"Alpspitzstr. 34",
    "sg:city":"Garmisch-Partenkirchen",
    "sg:phone":"+49 8821/57386",
    "sg:postcode":"82467",
    "sg:province":"Bayern",
    "wof:name":"Christian Sporer Tennislehrer",
    "wof:placetype":"venue"
},
  "geometry": {"coordinates":[11.0894346237,47.4866943359],"type":"Point"}
}