{
  "type": "Feature",
  "properties": {
    "iso:country":"DE",
    "sg:address":"Haldenweg 6",
    "sg:city":"Bergkamen",
    "sg:phone":"+49 2307/6336",
    "sg:postcode":"59192",
    "sg:province":"Nordrhein-Westfalen",
    "wof:name":"Taxi Dohrmann Gmbh",
    "wof:placetype":"venue"
},
  "geometry": {"coordinates":[7.6278219223,51.6188011169],"type":"Point"}
}