{
  "type": "Feature",
  "properties": {
    "iso:country":"DE",
    "sg:address":"Kattreppeln 2",
    "sg:city":"K\u00f6nigslutter",
    "sg:phone":"+49 5353/1266",
    "sg:postcode":"38154",
    "sg:province":"Niedersachsen",
    "wof:name":"Jochen Erbacher",
    "wof:placetype":"venue"
},
  "geometry": {"coordinates":[10.8175086975,52.2490348816],"type":"Point"}
}