{
  "type": "Feature",
  "properties": {
    "iso:country":"DE",
    "sg:address":"Schanzenstr. 37",
    "sg:city":"K\u00f6ln",
    "sg:postcode":"51063",
    "sg:province":"Nordrhein-Westfalen",
    "wof:name":"Dirk Becker Entertainment Gmbh",
    "wof:placetype":"venue"
},
  "geometry": {"coordinates":[7.017646,50.9697],"type":"Point"}
}