{
  "type": "Feature",
  "properties": {
    "iso:country":"DE",
    "sg:address":"Heidelberger Str. 179",
    "sg:city":"Heilbronn",
    "sg:phone":"+49 7131/41111",
    "sg:postcode":"74080",
    "sg:province":"Baden-W\u00fcrttemberg",
    "wof:name":"Erwin R\u00f6der",
    "wof:placetype":"venue"
},
  "geometry": {"coordinates":[9.180321,49.149143],"type":"Point"}
}