{
  "type": "Feature",
  "properties": {
    "iso:country":"DE",
    "sg:address":"Salzstr. 26",
    "sg:city":"Niedernhall",
    "sg:phone":"+49 4979/404065",
    "sg:postcode":"74676",
    "sg:province":"Baden-W\u00fcrttemberg",
    "wof:name":"Chr. Knapp Gmbh",
    "wof:placetype":"venue"
},
  "geometry": {"coordinates":[9.6220216751,49.3035087585],"type":"Point"}
}