{
  "type": "Feature",
  "properties": {
    "iso:country":"DE",
    "sg:address":"Eisensteiner Kopf",
    "sg:city":"Kirchheimbolanden",
    "sg:phone":"+49 6352/5698",
    "sg:postcode":"67292",
    "sg:province":"Rheinland-Pfalz",
    "wof:name":"Amk Asphalt - Mischwerk Kirchheimbolanden",
    "wof:placetype":"venue"
},
  "geometry": {"coordinates":[7.9517388344,49.6676139832],"type":"Point"}
}