{
  "type": "Feature",
  "properties": {
    "iso:country":"DE",
    "sg:address":"Lindenstr. 34",
    "sg:city":"Pr\u00f6del",
    "sg:phone":"+49 39242/236",
    "sg:postcode":"39264",
    "sg:province":"Sachsen-Anhalt",
    "wof:name":"Johannes Paasch",
    "wof:placetype":"venue"
},
  "geometry": {"coordinates":[11.916601,52.038361],"type":"Point"}
}