{
  "type": "Feature",
  "properties": {
    "iso:country":"DE",
    "sg:address":"rathenaustr. 37",
    "sg:city":"Maintal",
    "sg:postcode":"63477",
    "sg:province":"Hessen",
    "wof:name":"Dieter Gring",
    "wof:placetype":"venue"
},
  "geometry": {"coordinates":[8.835813,50.136913],"type":"Point"}
}