{
  "type": "Feature",
  "properties": {
    "iso:country":"DE",
    "sg:address":"Van-der-Smissen-Str. 2",
    "sg:city":"Hamburg",
    "sg:postcode":"22767",
    "sg:province":"Hamburg",
    "wof:name":"Cad Datenverarbeitung Spangenberg Gmbh",
    "wof:placetype":"venue"
},
  "geometry": {"coordinates":[9.94148,53.543465],"type":"Point"}
}