{
  "type": "Feature",
  "properties": {
    "iso:country":"DE",
    "sg:address":"Spitzenstr. 1",
    "sg:city":"Wuppertal",
    "sg:phone":"+49 202/602300",
    "sg:postcode":"42389",
    "sg:province":"Nordrhein-Westfalen",
    "wof:name":"Dr. Med. Ralf Wopersnow",
    "wof:placetype":"venue"
},
  "geometry": {"coordinates":[7.2434840202,51.2743339539],"type":"Point"}
}