{
  "type": "Feature",
  "properties": {
    "iso:country":"DE",
    "sg:address":"Langenfelder Str. 59",
    "sg:city":"Hamburg",
    "sg:phone":"+49 40/435557",
    "sg:postcode":"22769",
    "sg:province":"Hamburg",
    "wof:name":"Willy R\u00fcth",
    "wof:placetype":"venue"
},
  "geometry": {"coordinates":[9.9540996552,53.5648612976],"type":"Point"}
}