{
  "type": "Feature",
  "properties": {
    "iso:country":"DE",
    "sg:address":"Seestr. 3",
    "sg:city":"Bad Zwischenahn",
    "sg:phone":"+49 4403/979220",
    "sg:postcode":"26160",
    "sg:province":"Niedersachsen",
    "wof:name":"Kts Stolper Gmbh",
    "wof:placetype":"venue"
},
  "geometry": {"coordinates":[7.9869761467,53.1922416687],"type":"Point"}
}