{
  "type": "Feature",
  "properties": {
    "iso:country":"DE",
    "sg:address":"Hochstr. 74",
    "sg:city":"Sonsbeck",
    "sg:phone":"+49 2838/2362",
    "sg:postcode":"47665",
    "sg:province":"Nordrhein-Westfalen",
    "wof:name":"Heinrich Hegger",
    "wof:placetype":"venue"
},
  "geometry": {"coordinates":[6.3762178421,51.607875824],"type":"Point"}
}