{
  "type": "Feature",
  "properties": {
    "iso:country":"DE",
    "sg:address":"Ellenstr. 8",
    "sg:city":"Kempen",
    "sg:phone":"+49 2152/51269",
    "sg:postcode":"47906",
    "sg:province":"Nordrhein-Westfalen",
    "wof:name":"U. Siegers",
    "wof:placetype":"venue"
},
  "geometry": {"coordinates":[6.417377,51.363522],"type":"Point"}
}