{
  "type": "Feature",
  "properties": {
    "iso:country":"DE",
    "sg:address":"Heilbronner Str. 11",
    "sg:city":"H\u00f6chst",
    "sg:phone":"+49 6163/3695",
    "sg:postcode":"64739",
    "sg:province":"Hessen",
    "wof:name":"Horst Und Willi Heckmann",
    "wof:placetype":"venue"
},
  "geometry": {"coordinates":[8.9919633865,49.7712287903],"type":"Point"}
}