{
  "type": "Feature",
  "properties": {
    "iso:country":"DE",
    "sg:address":"Markneukirchner Str. 53",
    "sg:city":"Zwota",
    "sg:phone":"+49 37467/23006",
    "sg:postcode":"08267",
    "sg:province":"Sachsen",
    "wof:name":"Robert Tho\u00df",
    "wof:placetype":"venue"
},
  "geometry": {"coordinates":[12.418438,50.349331],"type":"Point"}
}