{
  "type": "Feature",
  "properties": {
    "iso:country":"DE",
    "sg:address":"Lindenstr. 36",
    "sg:city":"Kaisersbach",
    "sg:phone":"+49 7184/546",
    "sg:postcode":"73667",
    "sg:province":"Baden-W\u00fcrttemberg",
    "wof:name":"Willi Schneidereit",
    "wof:placetype":"venue"
},
  "geometry": {"coordinates":[9.64173,48.928982],"type":"Point"}
}