{
  "type": "Feature",
  "properties": {
    "iso:country":"DE",
    "sg:address":"Sachsendorf 14",
    "sg:city":"G\u00f6\u00dfweinstein",
    "sg:phone":"+49 9242/441",
    "sg:postcode":"91327",
    "sg:province":"Bayern",
    "wof:name":"Georg Gr\u00fcner",
    "wof:placetype":"venue"
},
  "geometry": {"coordinates":[11.3367443085,49.7702026367],"type":"Point"}
}