{
  "type": "Feature",
  "properties": {
    "iso:country":"DE",
    "sg:address":"Herrnhuter Allee 21",
    "sg:city":"Neuwied",
    "sg:phone":"+49 2631/20842",
    "sg:postcode":"56564",
    "sg:province":"Rheinland-Pfalz",
    "wof:name":"Fensterseifer Elektrotechnik Gmbh",
    "wof:placetype":"venue"
},
  "geometry": {"coordinates":[7.468017,50.424259],"type":"Point"}
}