{
  "type": "Feature",
  "properties": {
    "iso:country":"DE",
    "sg:address":"Am Stadtpark 6 b",
    "sg:city":"Erfurt",
    "sg:phone":"+49 361/3459554",
    "sg:postcode":"99096",
    "sg:province":"Th\u00fcringen",
    "wof:name":"J\u00f6rg Hober\u00fcck Rechtsanwalt",
    "wof:placetype":"venue"
},
  "geometry": {"coordinates":[11.0380582809,50.9679756165],"type":"Point"}
}