{
  "type": "Feature",
  "properties": {
    "iso:country":"DE",
    "sg:address":"Ernst-Th\u00e4lmann-Str. 30",
    "sg:city":"Heidenau",
    "sg:phone":"+49 3529/521780",
    "sg:postcode":"01809",
    "sg:province":"Sachsen",
    "wof:name":"Cordamed Gmbh",
    "wof:placetype":"venue"
},
  "geometry": {"coordinates":[13.8694820404,50.9760856628],"type":"Point"}
}