{
  "type": "Feature",
  "properties": {
    "iso:country":"DE",
    "sg:address":"Mittelgasse 1",
    "sg:city":"Feldatal",
    "sg:phone":"+49 6645/454",
    "sg:postcode":"36325",
    "sg:province":"Hessen",
    "wof:name":"Karl D\u00f6rr",
    "wof:placetype":"venue"
},
  "geometry": {"coordinates":[9.181042,50.61591],"type":"Point"}
}