{
  "type": "Feature",
  "properties": {
    "iso:country":"DE",
    "sg:address":"Schulstr. 5",
    "sg:city":"Sterup",
    "sg:phone":"+49 4637/1806",
    "sg:postcode":"24996",
    "sg:province":"Schleswig-Holstein",
    "wof:name":"Odefey & Sohn",
    "wof:placetype":"venue"
},
  "geometry": {"coordinates":[9.7411470413,54.7298965454],"type":"Point"}
}