{
  "type": "Feature",
  "properties": {
    "iso:country":"DE",
    "sg:address":"Wildrosenweg 32",
    "sg:city":"Kirchheim",
    "sg:phone":"+49 89/9046516",
    "sg:postcode":"85551",
    "sg:province":"Bayern",
    "wof:name":"Presoft Planung Realisierung Und Einf\u00fchrung Von Edv-",
    "wof:placetype":"venue"
},
  "geometry": {"coordinates":[11.7609472275,48.1691093445],"type":"Point"}
}