{
  "type": "Feature",
  "properties": {
    "iso:country":"DE",
    "sg:address":"Mozartweg 1",
    "sg:city":"Michelau",
    "sg:phone":"+49 9571/97770",
    "sg:postcode":"96247",
    "sg:province":"Bayern",
    "wof:name":"Dr. Klaus Grund Heilpraktiker Und Tierarzt",
    "wof:placetype":"venue"
},
  "geometry": {"coordinates":[11.1100673676,50.1630477905],"type":"Point"}
}