{
  "type": "Feature",
  "properties": {
    "iso:country":"DE",
    "sg:address":"Rosenweide 5",
    "sg:city":"Stelle",
    "sg:phone":"+49 4174/2918",
    "sg:postcode":"21435",
    "sg:province":"Niedersachsen",
    "wof:name":"Walter Rieckmann",
    "wof:placetype":"venue"
},
  "geometry": {"coordinates":[10.12214,53.420952],"type":"Point"}
}