{
  "type": "Feature",
  "properties": {
    "iso:country":"DE",
    "sg:address":"Dresdner Str. 339",
    "sg:city":"Freital",
    "sg:phone":"+49 351/648890",
    "sg:postcode":"01705",
    "sg:province":"Sachsen",
    "wof:name":"Fdg-sozialdienstleistungs Gmbh",
    "wof:placetype":"venue"
},
  "geometry": {"coordinates":[13.6369762421,50.9862365723],"type":"Point"}
}