{
  "type": "Feature",
  "properties": {
    "iso:country":"DE",
    "sg:address":"Beethovenstr. 1",
    "sg:city":"K\u00f6ngen",
    "sg:postcode":"73257",
    "sg:province":"Baden-W\u00fcrttemberg",
    "wof:name":"Yeda.de",
    "wof:placetype":"venue"
},
  "geometry": {"coordinates":[9.358934,48.67691],"type":"Point"}
}