{
  "type": "Feature",
  "properties": {
    "iso:country":"DE",
    "sg:address":"Konsulstr. 1",
    "sg:city":"G\u00f6rlitz",
    "sg:phone":"+49 3581/405064",
    "sg:postcode":"02826",
    "sg:province":"Sachsen",
    "wof:name":"Kreuzbube",
    "wof:placetype":"venue"
},
  "geometry": {"coordinates":[14.9878864288,51.1512031555],"type":"Point"}
}