{
  "type": "Feature",
  "properties": {
    "iso:country":"DE",
    "sg:address":"Fleckstr. 39",
    "sg:city":"Wippra",
    "sg:postcode":"06543",
    "sg:province":"Sachsen-Anhalt",
    "wof:name":"Tischlerei Herold",
    "wof:placetype":"venue"
},
  "geometry": {"coordinates":[11.276971,51.573715],"type":"Point"}
}