{
  "type": "Feature",
  "properties": {
    "iso:country":"DE",
    "sg:address":"Rablstr. 47",
    "sg:city":"M\u00fcnchen",
    "sg:phone":"+49 6104/5386",
    "sg:postcode":"81669",
    "sg:province":"Bayern",
    "wof:name":"Henner Lehfeld Architekt",
    "wof:placetype":"venue"
},
  "geometry": {"coordinates":[11.59462,48.12677],"type":"Point"}
}