{
  "type": "Feature",
  "properties": {
    "iso:country":"DE",
    "sg:address":"J\u00e4gerh\u00f6lzlstr. 27",
    "sg:city":"Lalling",
    "sg:phone":"+49 9904/84135",
    "sg:postcode":"94551",
    "sg:province":"Bayern",
    "wof:name":"Robert Schengili",
    "wof:placetype":"venue"
},
  "geometry": {"coordinates":[13.1335687637,48.8424797058],"type":"Point"}
}