{
  "type": "Feature",
  "properties": {
    "iso:country":"DE",
    "sg:address":"Zienkener Str. 5",
    "sg:city":"M\u00fcllheim",
    "sg:phone":"+49 7631/14211",
    "sg:postcode":"79379",
    "sg:province":"Baden-W\u00fcrttemberg",
    "wof:name":"Sportgastst\u00e4tte H\u00fcgelheim",
    "wof:placetype":"venue"
},
  "geometry": {"coordinates":[7.6173000336,47.8311195374],"type":"Point"}
}