{
  "type": "Feature",
  "properties": {
    "iso:country":"DE",
    "sg:address":"Altinger Str. 55",
    "sg:city":"Herrenberg",
    "sg:phone":"+49 7032/73927",
    "sg:postcode":"71083",
    "sg:province":"Baden-W\u00fcrttemberg",
    "wof:name":"Top Service",
    "wof:placetype":"venue"
},
  "geometry": {"coordinates":[8.883249,48.573116],"type":"Point"}
}