{
  "type": "Feature",
  "properties": {
    "iso:country":"DE",
    "sg:address":"Friedrich-Bach-Str. 29",
    "sg:city":"B\u00fcckeburg",
    "sg:phone":"+49 5722/3325",
    "sg:postcode":"31675",
    "sg:province":"Niedersachsen",
    "wof:name":"Engel & Engelke",
    "wof:placetype":"venue"
},
  "geometry": {"coordinates":[9.042192,52.262291],"type":"Point"}
}