{
  "type": "Feature",
  "properties": {
    "iso:country":"DE",
    "sg:address":"Am Hipperich 26",
    "sg:city":"Mainz",
    "sg:phone":"+49 6131/625480",
    "sg:postcode":"55120",
    "sg:province":"Rheinland-Pfalz",
    "wof:name":"Erwin Liesert Steuerberater",
    "wof:placetype":"venue"
},
  "geometry": {"coordinates":[8.2140455246,50.0196266174],"type":"Point"}
}