{
  "type": "Feature",
  "properties": {
    "iso:country":"DE",
    "sg:address":"Denisstr. 43",
    "sg:city":"N\u00fcrnberg",
    "sg:phone":"+49 911/288821",
    "sg:postcode":"90429",
    "sg:province":"Bayern",
    "wof:name":"Gisela Borowski",
    "wof:placetype":"venue"
},
  "geometry": {"coordinates":[11.0482463837,49.4508132935],"type":"Point"}
}