{
  "type": "Feature",
  "properties": {
    "iso:country":"DE",
    "sg:address":"S\u00fcdring 1",
    "sg:city":"Mudau",
    "sg:phone":"+49 6284/95250",
    "sg:postcode":"69427",
    "sg:province":"Baden-W\u00fcrttemberg",
    "wof:name":"Braun Communication Gmbh",
    "wof:placetype":"venue"
},
  "geometry": {"coordinates":[9.199603,49.52916],"type":"Point"}
}