{
  "type": "Feature",
  "properties": {
    "iso:country":"DE",
    "sg:address":"Kilianstr. 6",
    "sg:city":"Heilbronn",
    "sg:phone":"+49 7131/888620",
    "sg:postcode":"74072",
    "sg:province":"Baden-W\u00fcrttemberg",
    "wof:name":"Neckermann Reiseb\u00fcro",
    "wof:placetype":"venue"
},
  "geometry": {"coordinates":[9.2197904587,49.1410140991],"type":"Point"}
}