{
  "type": "Feature",
  "properties": {
    "iso:country":"DE",
    "sg:address":"D\u00fcppheider Weg 11",
    "sg:city":"Korschenbroich",
    "sg:postcode":"41352",
    "sg:province":"Nordrhein-Westfalen",
    "wof:name":"Rjp Vertriebs-gmbh",
    "wof:placetype":"venue"
},
  "geometry": {"coordinates":[6.564223,51.209412],"type":"Point"}
}