{
  "type": "Feature",
  "properties": {
    "iso:country":"DE",
    "sg:address":"Am Diehlengarten 1",
    "sg:city":"H\u00fcnstetten",
    "sg:phone":"+49 6126/55577",
    "sg:postcode":"65510",
    "sg:province":"Hessen",
    "wof:name":"U. M\u00fcller",
    "wof:placetype":"venue"
},
  "geometry": {"coordinates":[8.176729,50.245083],"type":"Point"}
}