{
  "type": "Feature",
  "properties": {
    "iso:country":"DE",
    "sg:address":"Heinestr. 8",
    "sg:city":"Reinsdorf",
    "sg:phone":"+49 375/617547",
    "sg:postcode":"08141",
    "sg:province":"Sachsen",
    "wof:name":"Gasthaus Gl\u00fcck Auf",
    "wof:placetype":"venue"
},
  "geometry": {"coordinates":[12.5612287521,50.6842193604],"type":"Point"}
}