{
  "type": "Feature",
  "properties": {
    "iso:country":"DE",
    "sg:address":"Goethestr. 11",
    "sg:city":"Stuttgart",
    "sg:postcode":"70174",
    "sg:province":"Baden-W\u00fcrttemberg",
    "wof:name":"Wlsb-service-gmbh",
    "wof:placetype":"venue"
},
  "geometry": {"coordinates":[9.1760616302,48.7846565247],"type":"Point"}
}