{
  "type": "Feature",
  "properties": {
    "iso:country":"DE",
    "sg:address":"\u00c4u\u00dfere N\u00fcrnberger Str. 21 a",
    "sg:city":"Forchheim",
    "sg:phone":"+49 9191/80421",
    "sg:postcode":"91301",
    "sg:province":"Bayern",
    "wof:name":"Pizzeria Mille Lire",
    "wof:placetype":"venue"
},
  "geometry": {"coordinates":[11.0619049072,49.7116928101],"type":"Point"}
}