{
  "type": "Feature",
  "properties": {
    "iso:country":"DE",
    "sg:address":"Heinkstr. 15",
    "sg:city":"Leipzig",
    "sg:postcode":"04347",
    "sg:province":"Sachsen",
    "wof:name":"Grafema Maschinen Und Anlagen Vertriebs-gmbh",
    "wof:placetype":"venue"
},
  "geometry": {"coordinates":[12.409987,51.354588],"type":"Point"}
}