{
  "type": "Feature",
  "properties": {
    "iso:country":"DE",
    "sg:address":"G\u00f6ttinger Str. 28",
    "sg:city":"Wadersloh",
    "sg:phone":"+49 2945/5689",
    "sg:postcode":"59329",
    "sg:province":"Nordrhein-Westfalen",
    "wof:name":"Gerhard Samuel",
    "wof:placetype":"venue"
},
  "geometry": {"coordinates":[8.2359657288,51.669254303],"type":"Point"}
}