{
  "type": "Feature",
  "properties": {
    "iso:country":"DE",
    "sg:address":"Kirchweg 22",
    "sg:city":"Idstein",
    "sg:phone":"+49 6126/1085",
    "sg:postcode":"65510",
    "sg:province":"Hessen",
    "wof:name":"Hans-albrecht Oehmke Ingenieur",
    "wof:placetype":"venue"
},
  "geometry": {"coordinates":[8.2372112274,50.2119216919],"type":"Point"}
}