{
  "type": "Feature",
  "properties": {
    "iso:country":"DE",
    "sg:address":"Auf der Alten Burg 40",
    "sg:city":"Aschersleben",
    "sg:phone":"+49 3473/3324",
    "sg:postcode":"06449",
    "sg:province":"Sachsen-Anhalt",
    "wof:name":"Tierpark Aschersleben",
    "wof:placetype":"venue"
},
  "geometry": {"coordinates":[11.4398612976,51.7528877258],"type":"Point"}
}