{
  "type": "Feature",
  "properties": {
    "iso:country":"DE",
    "sg:address":"Brestenberg 5",
    "sg:city":"Villingen-Schwenningen",
    "sg:phone":"+49 7721/22500",
    "sg:postcode":"78052",
    "sg:province":"Baden-W\u00fcrttemberg",
    "wof:name":"Fernmeldemontage Gmbh",
    "wof:placetype":"venue"
},
  "geometry": {"coordinates":[8.417095,48.030773],"type":"Point"}
}