{
  "type": "Feature",
  "properties": {
    "iso:country":"DE",
    "sg:address":"Freisinger Str. 93",
    "sg:city":"Ismaning",
    "sg:phone":"+49 89/968249",
    "sg:postcode":"85737",
    "sg:province":"Bayern",
    "wof:name":"Gr\u00fcnbeck Gmbh",
    "wof:placetype":"venue"
},
  "geometry": {"coordinates":[11.69626,48.256821],"type":"Point"}
}