{
  "type": "Feature",
  "properties": {
    "iso:country":"DE",
    "sg:address":"Untere Marktstr. 7",
    "sg:city":"Gehren",
    "sg:phone":"+49 36783/81100",
    "sg:postcode":"98708",
    "sg:province":"Th\u00fcringen",
    "wof:name":"Evangelisch-lutherische Kirche",
    "wof:placetype":"venue"
},
  "geometry": {"coordinates":[11.0040426254,50.6488800049],"type":"Point"}
}