{
  "type": "Feature",
  "properties": {
    "iso:country":"DE",
    "sg:address":"Erdweg 15",
    "sg:city":"P\u00f6ttmes",
    "sg:phone":"+49 8253/327",
    "sg:postcode":"86554",
    "sg:province":"Bayern",
    "wof:name":"Maria Schiffelholz",
    "wof:placetype":"venue"
},
  "geometry": {"coordinates":[11.0893707275,48.5834236145],"type":"Point"}
}