{
  "type": "Feature",
  "properties": {
    "iso:country":"DE",
    "sg:address":"Am Krusenick 16",
    "sg:city":"Berlin",
    "sg:phone":"+49 30/6626420",
    "sg:postcode":"12555",
    "sg:province":"Berlin",
    "wof:name":"Manfred Lorch",
    "wof:placetype":"venue"
},
  "geometry": {"coordinates":[13.5834102631,52.448299408],"type":"Point"}
}