{
  "type": "Feature",
  "properties": {
    "iso:country":"DE",
    "sg:address":"Friedrich-Hebbel-Str. 2",
    "sg:city":"Sankt Peter-Ording",
    "sg:phone":"+49 4863/7010",
    "sg:postcode":"25826",
    "sg:province":"Schleswig-Holstein",
    "wof:name":"Vier Jahreszeiten Familie L\u00fcders Ohg",
    "wof:placetype":"venue"
},
  "geometry": {"coordinates":[8.6225452423,54.3114356995],"type":"Point"}
}