{
  "type": "Feature",
  "properties": {
    "iso:country":"DE",
    "sg:address":"Brachter Str. 42",
    "sg:city":"Lennestadt",
    "sg:phone":"+49 2725/467",
    "sg:postcode":"57368",
    "sg:province":"Nordrhein-Westfalen",
    "wof:name":"Wolfgang Stratmann",
    "wof:placetype":"venue"
},
  "geometry": {"coordinates":[8.12572,51.172878],"type":"Point"}
}