{
  "type": "Feature",
  "properties": {
    "iso:country":"DE",
    "sg:address":"Harzstr. 4",
    "sg:city":"Katlenburg-Lindau",
    "sg:phone":"+49 5552/206",
    "sg:postcode":"37191",
    "sg:province":"Niedersachsen",
    "wof:name":"Hans-g\u00fcnter Hesse",
    "wof:placetype":"venue"
},
  "geometry": {"coordinates":[10.105178,51.680344],"type":"Point"}
}