{
  "type": "Feature",
  "properties": {
    "iso:country":"DE",
    "sg:address":"August-Horch-Str. 28",
    "sg:city":"Koblenz",
    "sg:phone":"+49 261/89202",
    "sg:postcode":"56070",
    "sg:province":"Rheinland-Pfalz",
    "wof:name":"Rz-markt & Medien Gmbh & Co. Kg",
    "wof:placetype":"venue"
},
  "geometry": {"coordinates":[7.5823740959,50.3902893066],"type":"Point"}
}