{
  "type": "Feature",
  "properties": {
    "iso:country":"DE",
    "sg:address":"Faberweg 10",
    "sg:city":"Kirchheim",
    "sg:phone":"+49 7021/570387",
    "sg:postcode":"73230",
    "sg:province":"Baden-W\u00fcrttemberg",
    "wof:name":"Rb 22 Kirchheimer Tipp- Kick-spieler",
    "wof:placetype":"venue"
},
  "geometry": {"coordinates":[9.4545269012,48.6369514465],"type":"Point"}
}