{
  "type": "Feature",
  "properties": {
    "iso:country":"DE",
    "sg:address":"Mainzer Str. 36",
    "sg:city":"R\u00fcsselsheim",
    "sg:phone":"+49 6142/12980",
    "sg:postcode":"65428",
    "sg:province":"Hessen",
    "wof:name":"Hotel Pension Tur",
    "wof:placetype":"venue"
},
  "geometry": {"coordinates":[8.4080657959,49.9941444397],"type":"Point"}
}