{
  "type": "Feature",
  "properties": {
    "iso:country":"DE",
    "sg:address":"Von-der-Gablentz-Str. 13",
    "sg:city":"Berlin",
    "sg:phone":"+49 30/4122310",
    "sg:postcode":"13403",
    "sg:province":"Berlin",
    "wof:name":"Pilsner St\u00fcbchen",
    "wof:placetype":"venue"
},
  "geometry": {"coordinates":[13.3268938065,52.5654792786],"type":"Point"}
}