{
  "type": "Feature",
  "properties": {
    "iso:country":"DE",
    "sg:address":"Buchhoferstr. 26",
    "sg:city":"Olching",
    "sg:phone":"+49 8142/13058",
    "sg:postcode":"82140",
    "sg:province":"Bayern",
    "wof:name":"G\u00fcnter Bamberg",
    "wof:placetype":"venue"
},
  "geometry": {"coordinates":[11.341794,48.210915],"type":"Point"}
}