{
  "type": "Feature",
  "properties": {
    "iso:country":"DE",
    "sg:address":"Wickrather Str. 76",
    "sg:city":"M\u00f6nchengladbach",
    "sg:phone":"+49 2166/48201",
    "sg:postcode":"41236",
    "sg:province":"Nordrhein-Westfalen",
    "wof:name":"Bei Marlies",
    "wof:placetype":"venue"
},
  "geometry": {"coordinates":[6.439622879,51.1595115662],"type":"Point"}
}