{
  "type": "Feature",
  "properties": {
    "iso:country":"DE",
    "sg:address":"Sanderglacisstr. 7",
    "sg:city":"W\u00fcrzburg",
    "sg:postcode":"97072",
    "sg:province":"Bayern",
    "wof:name":"A & O Concept Gmbh",
    "wof:placetype":"venue"
},
  "geometry": {"coordinates":[9.93015,49.78545],"type":"Point"}
}