{
  "type": "Feature",
  "properties": {
    "iso:country":"DE",
    "sg:address":"An der Koppel 3d",
    "sg:city":"Celle",
    "sg:phone":"+49 5141/88900",
    "sg:postcode":"29227",
    "sg:province":"Niedersachsen",
    "wof:name":"Draht & Schutz Sicherheitstechnik Gmbh",
    "wof:placetype":"venue"
},
  "geometry": {"coordinates":[10.065839,52.590923],"type":"Point"}
}