{
  "type": "Feature",
  "properties": {
    "iso:country":"DE",
    "sg:address":"Posener Str. 44",
    "sg:city":"D\u00fcsseldorf",
    "sg:phone":"+49 211/484484",
    "sg:postcode":"40231",
    "sg:province":"Nordrhein-Westfalen",
    "wof:name":"Tinas Billardst\u00fcbchen",
    "wof:placetype":"venue"
},
  "geometry": {"coordinates":[6.8329467773,51.2099533081],"type":"Point"}
}