{
  "type": "Feature",
  "properties": {
    "iso:country":"DE",
    "sg:address":"Illerstr. 34",
    "sg:city":"Bellenberg",
    "sg:phone":"+49 7306/919797",
    "sg:postcode":"89287",
    "sg:province":"Bayern",
    "wof:name":"C. Fischer",
    "wof:placetype":"venue"
},
  "geometry": {"coordinates":[10.081825,48.260338],"type":"Point"}
}