{
  "type": "Feature",
  "properties": {
    "iso:country":"DE",
    "sg:address":"Hinter der Bahn 8",
    "sg:city":"Drentwede",
    "sg:phone":"+49 4246/473",
    "sg:postcode":"49406",
    "sg:province":"Niedersachsen",
    "wof:name":"Heinrich Hoffmeyer",
    "wof:placetype":"venue"
},
  "geometry": {"coordinates":[8.563553,52.734032],"type":"Point"}
}