{
  "type": "Feature",
  "properties": {
    "iso:country":"DE",
    "sg:address":"Am Hauplatz 4",
    "sg:city":"Oberkirn",
    "sg:phone":"+49 6544/99770",
    "sg:postcode":"55624",
    "sg:province":"Rheinland-Pfalz",
    "wof:name":"Alfons Klingels Steuerberater",
    "wof:placetype":"venue"
},
  "geometry": {"coordinates":[7.3696699142,49.88331604],"type":"Point"}
}