{
  "type": "Feature",
  "properties": {
    "iso:country":"DE",
    "sg:city":"Birkholz",
    "sg:phone":"+49 3366/23633",
    "sg:postcode":"15848",
    "sg:province":"Brandenburg",
    "wof:name":"Kauartikel F\u00fcr Den Hund",
    "wof:placetype":"venue"
},
  "geometry": {"coordinates":[14.19537,52.190769],"type":"Point"}
}