{
  "type": "Feature",
  "properties": {
    "iso:country":"DE",
    "sg:address":"M\u00fchlweg 3",
    "sg:city":"Braunfels",
    "sg:phone":"+49 6445/7206",
    "sg:postcode":"35619",
    "sg:province":"Hessen",
    "wof:name":"Amend Kg",
    "wof:placetype":"venue"
},
  "geometry": {"coordinates":[8.435300827,50.4790267944],"type":"Point"}
}