{
  "type": "Feature",
  "properties": {
    "iso:country":"DE",
    "sg:address":"Algenrodter Str. 6",
    "sg:city":"Idar-Oberstein",
    "sg:phone":"+49 6781/43604",
    "sg:postcode":"55743",
    "sg:province":"Rheinland-Pfalz",
    "wof:name":"Alfred Barth",
    "wof:placetype":"venue"
},
  "geometry": {"coordinates":[7.2885861397,49.7157211304],"type":"Point"}
}