{
  "type": "Feature",
  "properties": {
    "iso:country":"DE",
    "sg:address":"Wismarsche Str.",
    "sg:city":"Insel Poel",
    "sg:phone":"+49 38425/20276",
    "sg:postcode":"23999",
    "sg:province":"Mecklenburg-Vorpommern",
    "wof:name":"Poeler Bau Gmbh",
    "wof:placetype":"venue"
},
  "geometry": {"coordinates":[11.4480552673,53.9945487976],"type":"Point"}
}