{
  "type": "Feature",
  "properties": {
    "iso:country":"DE",
    "sg:address":"Waldweg 73",
    "sg:city":"Hamburg",
    "sg:phone":"+49 40/6017611",
    "sg:postcode":"22393",
    "sg:province":"Hamburg",
    "wof:name":"Product Film Und Video Wolfgang Schmidt",
    "wof:placetype":"venue"
},
  "geometry": {"coordinates":[10.1238269806,53.6553611755],"type":"Point"}
}