{
  "type": "Feature",
  "properties": {
    "iso:country":"DE",
    "sg:address":"Gartenstr. 51",
    "sg:city":"Drebkau",
    "sg:postcode":"03116",
    "sg:province":"Brandenburg",
    "wof:name":"Wohngestaltung 2000 Gmbh",
    "wof:placetype":"venue"
},
  "geometry": {"coordinates":[14.2161130905,51.6582832336],"type":"Point"}
}