{
  "type": "Feature",
  "properties": {
    "iso:country":"DE",
    "sg:address":"Am Sch\u00e4ferfeld 5",
    "sg:city":"Seesen",
    "sg:phone":"+49 5384/1608",
    "sg:postcode":"38723",
    "sg:province":"Niedersachsen",
    "wof:name":"J. Beyes Immobilienmakler",
    "wof:placetype":"venue"
},
  "geometry": {"coordinates":[10.1080636978,51.9162712097],"type":"Point"}
}