{
  "type": "Feature",
  "properties": {
    "iso:country":"DE",
    "sg:address":"Hauptstr. 10",
    "sg:city":"Profen",
    "sg:phone":"+49 34424/21314",
    "sg:postcode":"06725",
    "sg:province":"Sachsen-Anhalt",
    "wof:name":"G\u00fcnter Peil",
    "wof:placetype":"venue"
},
  "geometry": {"coordinates":[12.215204,51.125435],"type":"Point"}
}