{
  "type": "Feature",
  "properties": {
    "iso:country":"DE",
    "sg:address":"Bahnhofstr. 11",
    "sg:city":"Burgsinn",
    "sg:phone":"+49 9356/2168",
    "sg:postcode":"97775",
    "sg:province":"Bayern",
    "wof:name":"Herbert Weininger",
    "wof:placetype":"venue"
},
  "geometry": {"coordinates":[9.65501,50.150299],"type":"Point"}
}