{
  "type": "Feature",
  "properties": {
    "iso:country":"DE",
    "sg:address":"Hauptstr. 141",
    "sg:city":"Schwalbach",
    "sg:phone":"+49 6834/51717",
    "sg:postcode":"66773",
    "sg:province":"Saarland",
    "wof:name":"R. Ruppert Heissmangel",
    "wof:placetype":"venue"
},
  "geometry": {"coordinates":[6.8112311363,49.3019332886],"type":"Point"}
}