{
  "type": "Feature",
  "properties": {
    "iso:country":"DE",
    "sg:address":"An der Rackst\u00e4dt 10",
    "sg:city":"Wittstock",
    "sg:phone":"+49 3394/442025",
    "sg:postcode":"16909",
    "sg:province":"Brandenburg",
    "wof:name":"Rackst\u00e4dtklause",
    "wof:placetype":"venue"
},
  "geometry": {"coordinates":[12.500494957,53.1701889038],"type":"Point"}
}