{
  "type": "Feature",
  "properties": {
    "iso:country":"DE",
    "sg:address":"Eichwiese 4 a",
    "sg:city":"Montabaur",
    "sg:phone":"+49 2602/4581",
    "sg:postcode":"56410",
    "sg:province":"Rheinland-Pfalz",
    "wof:name":"Josef R\u00f6ssel",
    "wof:placetype":"venue"
},
  "geometry": {"coordinates":[7.832693,50.436752],"type":"Point"}
}