{
  "type": "Feature",
  "properties": {
    "iso:country":"DE",
    "sg:address":"Birkenstr. 141",
    "sg:city":"D\u00fcsseldorf",
    "sg:phone":"+49 211/666743",
    "sg:postcode":"40233",
    "sg:province":"Nordrhein-Westfalen",
    "wof:name":"D. Lassine",
    "wof:placetype":"venue"
},
  "geometry": {"coordinates":[6.810389,51.226955],"type":"Point"}
}