{
  "type": "Feature",
  "properties": {
    "iso:country":"DE",
    "sg:address":"Kronthaler Str. 53",
    "sg:city":"K\u00f6nigstein",
    "sg:phone":"+49 6173/940990",
    "sg:postcode":"61462",
    "sg:province":"Hessen",
    "wof:name":"Willy Steffens Steinmetz",
    "wof:placetype":"venue"
},
  "geometry": {"coordinates":[8.5021324158,50.1719017029],"type":"Point"}
}