{
  "type": "Feature",
  "properties": {
    "iso:country":"DE",
    "sg:address":"R\u00f6merstr. 511",
    "sg:city":"Moers",
    "sg:postcode":"47443",
    "sg:province":"Nordrhein-Westfalen",
    "wof:name":"Medien Park Ag",
    "wof:placetype":"venue"
},
  "geometry": {"coordinates":[6.658983,51.447765],"type":"Point"}
}