{
  "type": "Feature",
  "properties": {
    "iso:country":"DE",
    "sg:address":"V\u00f6lklinger Weg 64",
    "sg:city":"Frankfurt",
    "sg:phone":"+49 69/350673",
    "sg:postcode":"60529",
    "sg:province":"Hessen",
    "wof:name":"Bernd Hoffmann Ingenieur",
    "wof:placetype":"venue"
},
  "geometry": {"coordinates":[8.5729513168,50.0848045349],"type":"Point"}
}