{
  "type": "Feature",
  "properties": {
    "iso:country":"DE",
    "sg:address":"Sengenholzer Weg 39",
    "sg:city":"Heiligenhaus",
    "sg:phone":"+49 2054/6607",
    "sg:postcode":"42579",
    "sg:province":"Nordrhein-Westfalen",
    "wof:name":"Georg Katterle Architekt",
    "wof:placetype":"venue"
},
  "geometry": {"coordinates":[6.940805,51.34919],"type":"Point"}
}