{
  "type": "Feature",
  "properties": {
    "iso:country":"DE",
    "sg:address":"Lerchenweg 16",
    "sg:city":"Dortmund",
    "sg:phone":"+49 231/676816",
    "sg:postcode":"44388",
    "sg:province":"Nordrhein-Westfalen",
    "wof:name":"Ilija Efendic",
    "wof:placetype":"venue"
},
  "geometry": {"coordinates":[7.3537478447,51.5178604126],"type":"Point"}
}