{
  "type": "Feature",
  "properties": {
    "iso:country":"DE",
    "sg:address":"Grabenstr. 44",
    "sg:city":"A\u00dflar",
    "sg:phone":"+49 6443/3520",
    "sg:postcode":"35614",
    "sg:province":"Hessen",
    "wof:name":"H. Dietz",
    "wof:placetype":"venue"
},
  "geometry": {"coordinates":[8.47387,50.588539],"type":"Point"}
}