{
  "type": "Feature",
  "properties": {
    "iso:country":"DE",
    "sg:address":"Max-Planck-Stra\u00dfe 8",
    "sg:city":"Saarburg",
    "sg:phone":"+49 6581",
    "sg:postcode":"54439",
    "sg:province":"Rheinland-Pfalz",
    "wof:name":"Heinrich Kind Gmbh",
    "wof:placetype":"venue"
},
  "geometry": {"coordinates":[6.5780081749,49.6060600281],"type":"Point"}
}