{
  "type": "Feature",
  "properties": {
    "iso:country":"DE",
    "sg:address":"Sternwartestr. 20b",
    "sg:city":"Sonneberg",
    "sg:phone":"+49 3675/805332",
    "sg:postcode":"96515",
    "sg:province":"Th\u00fcringen",
    "wof:name":"Heinz Bausanierung Gmbh",
    "wof:placetype":"venue"
},
  "geometry": {"coordinates":[11.1910600662,50.3760681152],"type":"Point"}
}