{
  "type": "Feature",
  "properties": {
    "iso:country":"DE",
    "sg:address":"Casumer Str. 42",
    "sg:city":"Versmold",
    "sg:phone":"+49 5423/49449",
    "sg:postcode":"33775",
    "sg:province":"Nordrhein-Westfalen",
    "wof:name":"Thomas H\u00fcgel",
    "wof:placetype":"venue"
},
  "geometry": {"coordinates":[8.2472391129,52.0437507629],"type":"Point"}
}