{
  "type": "Feature",
  "properties": {
    "iso:country":"DE",
    "sg:address":"Regensburger Str. 41",
    "sg:city":"Teublitz",
    "sg:phone":"+49 9471/9602",
    "sg:postcode":"93158",
    "sg:province":"Bayern",
    "wof:name":"Rosen-apotheke",
    "wof:placetype":"venue"
},
  "geometry": {"coordinates":[12.087004,49.223431],"type":"Point"}
}