{
  "type": "Feature",
  "properties": {
    "iso:country":"DE",
    "sg:address":"Kirchgasse 4",
    "sg:city":"Karben",
    "sg:phone":"+49 6039/5878",
    "sg:postcode":"61184",
    "sg:province":"Hessen",
    "wof:name":"Riesling-stube",
    "wof:placetype":"venue"
},
  "geometry": {"coordinates":[8.7736883163,50.2241096497],"type":"Point"}
}