{
  "type": "Feature",
  "properties": {
    "iso:country":"DE",
    "sg:address":"Rivesellstr. 2",
    "sg:city":"Flensburg",
    "sg:phone":"+49 461/25229",
    "sg:postcode":"24943",
    "sg:province":"Schleswig-Holstein",
    "wof:name":"Horst Petersen",
    "wof:placetype":"venue"
},
  "geometry": {"coordinates":[9.4442491531,54.7870445251],"type":"Point"}
}