{
  "type": "Feature",
  "properties": {
    "iso:country":"DE",
    "sg:address":"Marktstr. 9",
    "sg:city":"N\u00fcrtingen",
    "sg:phone":"+49 7022/39645",
    "sg:postcode":"72622",
    "sg:province":"Baden-W\u00fcrttemberg",
    "wof:name":"Kantelberg",
    "wof:placetype":"venue"
},
  "geometry": {"coordinates":[9.336672,48.626076],"type":"Point"}
}