{
  "type": "Feature",
  "properties": {
    "iso:country":"DE",
    "sg:address":"Dorfstr. 25",
    "sg:city":"Frauwalde",
    "sg:phone":"+49 35755/50314",
    "sg:postcode":"01990",
    "sg:province":"Brandenburg",
    "wof:name":"I. G\u00f6tze",
    "wof:placetype":"venue"
},
  "geometry": {"coordinates":[13.7111091614,51.3865280151],"type":"Point"}
}