{
  "type": "Feature",
  "properties": {
    "iso:country":"DE",
    "sg:address":"Siegfried-von-Vegesack-Str. 1",
    "sg:city":"Regen",
    "sg:phone":"+49 9921/1086",
    "sg:postcode":"94209",
    "sg:province":"Bayern",
    "wof:name":"Hotel Wei\u00dfenstein",
    "wof:placetype":"venue"
},
  "geometry": {"coordinates":[13.1215696335,48.9590148926],"type":"Point"}
}