{
  "type": "Feature",
  "properties": {
    "iso:country":"DE",
    "sg:address":"Untere Nu\u00dfbreite 48",
    "sg:city":"Beverungen",
    "sg:phone":"+49 5273/5506",
    "sg:postcode":"37688",
    "sg:province":"Nordrhein-Westfalen",
    "wof:name":"Else V\u00f6ssing",
    "wof:placetype":"venue"
},
  "geometry": {"coordinates":[9.371671,51.667557],"type":"Point"}
}