{
  "type": "Feature",
  "properties": {
    "iso:country":"DE",
    "sg:address":"patanenalle 23",
    "sg:city":"unna",
    "sg:postcode":"59423",
    "sg:province":"Nordrhein-Westfalen",
    "wof:name":"Firstseite Die Besten Seiten Im Internet",
    "wof:placetype":"venue"
},
  "geometry": {"coordinates":[7.68709,51.532413],"type":"Point"}
}