{
  "type": "Feature",
  "properties": {
    "iso:country":"DE",
    "sg:address":"Birkenbergstr. 30",
    "sg:city":"Leverkusen",
    "sg:phone":"+49 2171/1812",
    "sg:postcode":"51379",
    "sg:province":"Nordrhein-Westfalen",
    "wof:name":"Heinz Und Lydia Vierk\u00f6tter Fachgesch\u00e4ft Mutter Und",
    "wof:placetype":"venue"
},
  "geometry": {"coordinates":[7.001133,51.065159],"type":"Point"}
}