{
  "type": "Feature",
  "properties": {
    "iso:country":"DE",
    "sg:address":"Am Anger 7",
    "sg:city":"Zw\u00f6nitz",
    "sg:postcode":"08297",
    "sg:province":"Sachsen",
    "wof:name":"W. Neubauer",
    "wof:placetype":"venue"
},
  "geometry": {"coordinates":[12.83762,50.66671],"type":"Point"}
}