{
  "type": "Feature",
  "properties": {
    "iso:country":"DE",
    "sg:address":"Lauser Str. 1",
    "sg:city":"Feldkirchen-Westerham",
    "sg:phone":"+49 8063/9740",
    "sg:postcode":"83620",
    "sg:province":"Bayern",
    "wof:name":"Goldi Gefl\u00fcgel Gmbh",
    "wof:placetype":"venue"
},
  "geometry": {"coordinates":[11.8951873779,47.927772522],"type":"Point"}
}