{
  "type": "Feature",
  "properties": {
    "iso:country":"DE",
    "sg:address":"Breslauer Str. 7",
    "sg:city":"Dinkelsb\u00fchl",
    "sg:phone":"+49 8053/9507",
    "sg:postcode":"91550",
    "sg:province":"Bayern",
    "wof:name":"Wenninger Druck",
    "wof:placetype":"venue"
},
  "geometry": {"coordinates":[12.3042068481,47.9032287598],"type":"Point"}
}