{
  "type": "Feature",
  "properties": {
    "iso:country":"DE",
    "sg:address":"Steinhardter Str. 53",
    "sg:city":"Bad Sobernheim",
    "sg:phone":"+49 6751/2368",
    "sg:postcode":"55566",
    "sg:province":"Rheinland-Pfalz",
    "wof:name":"Sobernheimer Ziegeleigesellschaft Mbh",
    "wof:placetype":"venue"
},
  "geometry": {"coordinates":[7.656687,49.788807],"type":"Point"}
}