{
  "type": "Feature",
  "properties": {
    "iso:country":"DE",
    "sg:address":"Hohlweg 3",
    "sg:city":"Neuhaus",
    "sg:phone":"+49 3679/722073",
    "sg:postcode":"98724",
    "sg:province":"Th\u00fcringen",
    "wof:name":"Hubert Koch",
    "wof:placetype":"venue"
},
  "geometry": {"coordinates":[11.1405630112,50.5113220215],"type":"Point"}
}