{
  "type": "Feature",
  "properties": {
    "iso:country":"DE",
    "sg:address":"Zum Langenberg 18",
    "sg:city":"Willingen",
    "sg:postcode":"34508",
    "sg:province":"Hessen",
    "wof:name":"Aqua-technologie Ingenieur- Gesellschaft Mbh",
    "wof:placetype":"venue"
},
  "geometry": {"coordinates":[8.5880460739,51.2907295227],"type":"Point"}
}