{
  "type": "Feature",
  "properties": {
    "iso:country":"DE",
    "sg:address":"Postfach 13 55",
    "sg:city":"M\u00fcllheim",
    "sg:postcode":"79373",
    "sg:province":"Baden-W\u00fcrttemberg",
    "wof:name":"Neckermann Versand Gtf M\u00fcllheim Gmbh",
    "wof:placetype":"venue"
},
  "geometry": {"coordinates":[7.628349781,47.80834198],"type":"Point"}
}