{
  "type": "Feature",
  "properties": {
    "iso:country":"DE",
    "sg:address":"L\u00f6ricker Str. 9",
    "sg:city":"D\u00fcsseldorf",
    "sg:phone":"+49 211/591029",
    "sg:postcode":"40547",
    "sg:province":"Nordrhein-Westfalen",
    "wof:name":"Konrad Willecke Eisen- Und R\u00f6hrengrosshdl.",
    "wof:placetype":"venue"
},
  "geometry": {"coordinates":[6.7220950127,51.243057251],"type":"Point"}
}