{
  "type": "Feature",
  "properties": {
    "iso:country":"DE",
    "sg:address":"Alte Bismarckstr. 17",
    "sg:city":"Remscheid",
    "sg:phone":"+49 2191/23600",
    "sg:postcode":"42853",
    "sg:province":"Nordrhein-Westfalen",
    "wof:name":"S. Sezen",
    "wof:placetype":"venue"
},
  "geometry": {"coordinates":[7.1969451904,51.1791191101],"type":"Point"}
}