{
  "type": "Feature",
  "properties": {
    "iso:country":"DE",
    "sg:address":"Finkenweg 1",
    "sg:city":"Volkach",
    "sg:phone":"+49 9381/802245",
    "sg:postcode":"97332",
    "sg:province":"Bayern",
    "wof:name":"Roman Seck U. Thomas Leuxner",
    "wof:placetype":"venue"
},
  "geometry": {"coordinates":[10.237583,49.862946],"type":"Point"}
}