{
  "type": "Feature",
  "properties": {
    "iso:country":"DE",
    "sg:address":"Ludwig-Eberle-Str. 5",
    "sg:city":"Bad Gr\u00f6nenbach",
    "sg:phone":"+49 8334/7128",
    "sg:postcode":"87730",
    "sg:province":"Bayern",
    "wof:name":"Carmen Lindwor-keitel Rechtsanw\u00e4ltin",
    "wof:placetype":"venue"
},
  "geometry": {"coordinates":[10.2138462067,47.8770637512],"type":"Point"}
}