{
  "type": "Feature",
  "properties": {
    "iso:country":"DE",
    "sg:address":"Am Brink 54",
    "sg:city":"Lemgo",
    "sg:phone":"+49 5261/8177",
    "sg:postcode":"32657",
    "sg:province":"Nordrhein-Westfalen",
    "wof:name":"Friedrich Meierjohann",
    "wof:placetype":"venue"
},
  "geometry": {"coordinates":[8.962105,52.021515],"type":"Point"}
}