{
  "type": "Feature",
  "properties": {
    "iso:country":"DE",
    "sg:address":"Finkenweg 33",
    "sg:city":"Kaisersesch",
    "sg:phone":"+49 2653/6661",
    "sg:postcode":"56759",
    "sg:province":"Rheinland-Pfalz",
    "wof:name":"Skanditex Bekleidungsparadies Gmbh",
    "wof:placetype":"venue"
},
  "geometry": {"coordinates":[7.1342959404,50.2365112305],"type":"Point"}
}