{
  "type": "Feature",
  "properties": {
    "iso:country":"DE",
    "sg:address":"Haselnu\u00dfweg 62",
    "sg:city":"Weinheim",
    "sg:phone":"+49 6201/12489",
    "sg:postcode":"69469",
    "sg:province":"Baden-W\u00fcrttemberg",
    "wof:name":"Erwin Schumacher Und Sohn Bootsbaugesellschaft Mbh",
    "wof:placetype":"venue"
},
  "geometry": {"coordinates":[8.636369,49.547356],"type":"Point"}
}