{
  "type": "Feature",
  "properties": {
    "iso:country":"DE",
    "sg:address":"Kurf\u00fcrstenstr. 2-4",
    "sg:city":"Kassel",
    "sg:postcode":"34117",
    "sg:province":"Hessen",
    "wof:name":"Jeans-place Inh. Karl Oberm\u00fcller",
    "wof:placetype":"venue"
},
  "geometry": {"coordinates":[9.4925041199,51.3168754578],"type":"Point"}
}