{
  "type": "Feature",
  "properties": {
    "iso:country":"DE",
    "sg:address":"Papierm\u00fchlenweg 18",
    "sg:city":"Greiz",
    "sg:phone":"+49 3661/2662",
    "sg:postcode":"07973",
    "sg:province":"Th\u00fcringen",
    "wof:name":"G\u00f6ltzschtal",
    "wof:placetype":"venue"
},
  "geometry": {"coordinates":[12.1986694336,50.6445045471],"type":"Point"}
}