{
  "type": "Feature",
  "properties": {
    "iso:country":"DE",
    "sg:address":"Passauer Str. 23",
    "sg:city":"Neuhaus",
    "sg:phone":"+49 8503/922937",
    "sg:postcode":"94152",
    "sg:province":"Bayern",
    "wof:name":"Fischer Gmbh & Co. Kg",
    "wof:placetype":"venue"
},
  "geometry": {"coordinates":[13.419508934,48.4595832825],"type":"Point"}
}