{
  "type": "Feature",
  "properties": {
    "iso:country":"DE",
    "sg:address":"Im Grund 3 - 5",
    "sg:city":"Friedrichroda",
    "sg:phone":"+49 3623/4583",
    "sg:postcode":"99894",
    "sg:province":"Th\u00fcringen",
    "wof:name":"Im Grund",
    "wof:placetype":"venue"
},
  "geometry": {"coordinates":[10.5585947037,50.8450775146],"type":"Point"}
}