{
  "type": "Feature",
  "properties": {
    "iso:country":"DE",
    "sg:address":"Hessentorstr. 83",
    "sg:city":"Rottenburg",
    "sg:phone":"+49 7478/8015",
    "sg:postcode":"72108",
    "sg:province":"Baden-W\u00fcrttemberg",
    "wof:name":"Horst Paepke Gmbh",
    "wof:placetype":"venue"
},
  "geometry": {"coordinates":[8.938245,48.475811],"type":"Point"}
}