{
  "type": "Feature",
  "properties": {
    "iso:country":"DE",
    "sg:address":"Holzschuhmacherstr. 4",
    "sg:city":"Wilstedt",
    "sg:phone":"+49 4283/956101",
    "sg:postcode":"27412",
    "sg:province":"Niedersachsen",
    "wof:name":"Hugo Hinz",
    "wof:placetype":"venue"
},
  "geometry": {"coordinates":[9.09457,53.192963],"type":"Point"}
}