{
  "type": "Feature",
  "properties": {
    "iso:country":"DE",
    "sg:address":"Charvieu-Chavagneux-Platz 16",
    "sg:city":"Nauheim",
    "sg:phone":"+49 6152/965650",
    "sg:postcode":"64569",
    "sg:province":"Hessen",
    "wof:name":"Denk & Dachte Software Gmbh",
    "wof:placetype":"venue"
},
  "geometry": {"coordinates":[8.4586000443,49.9505958557],"type":"Point"}
}