{
  "type": "Feature",
  "properties": {
    "iso:country":"DE",
    "sg:address":"Kaltofen 18",
    "sg:city":"Striegistal",
    "sg:phone":"+49 37207/2315",
    "sg:postcode":"09661",
    "sg:province":"Sachsen",
    "wof:name":"Waldhaus Kalkbr\u00fcche",
    "wof:placetype":"venue"
},
  "geometry": {"coordinates":[13.1553697586,50.9908294678],"type":"Point"}
}