{
  "type": "Feature",
  "properties": {
    "iso:country":"DE",
    "sg:address":"Genieler Str. 92",
    "sg:city":"Geldern",
    "sg:phone":"+49 2831/3169",
    "sg:postcode":"47608",
    "sg:province":"Nordrhein-Westfalen",
    "wof:name":"Blumenhandel De Klus Import Und Export Gmbh",
    "wof:placetype":"venue"
},
  "geometry": {"coordinates":[6.271411,51.520184],"type":"Point"}
}