{
  "type": "Feature",
  "properties": {
    "iso:country":"DE",
    "sg:address":"Lange Morgen 12",
    "sg:city":"Kirchheim",
    "sg:phone":"+49 7021/81577",
    "sg:postcode":"73230",
    "sg:province":"Baden-W\u00fcrttemberg",
    "wof:name":"Friedrich Blum Ingenieur",
    "wof:placetype":"venue"
},
  "geometry": {"coordinates":[9.4468889236,48.6396408081],"type":"Point"}
}