{
  "type": "Feature",
  "properties": {
    "iso:country":"DE",
    "sg:address":"\u00dcbern Braken 12",
    "sg:city":"Pennigsehl",
    "sg:phone":"+49 5028/378",
    "sg:postcode":"31621",
    "sg:province":"Niedersachsen",
    "wof:name":"Heinrich G\u00fcnnemann",
    "wof:placetype":"venue"
},
  "geometry": {"coordinates":[9.040305,52.63681],"type":"Point"}
}