{
  "type": "Feature",
  "properties": {
    "iso:country":"DE",
    "sg:address":"Am Gehege 17",
    "sg:city":"Guben",
    "sg:phone":"+49 3561/550550",
    "sg:postcode":"03172",
    "sg:province":"Brandenburg",
    "wof:name":"Bossan",
    "wof:placetype":"venue"
},
  "geometry": {"coordinates":[14.6821250916,51.9527778625],"type":"Point"}
}