{
  "type": "Feature",
  "properties": {
    "iso:country":"DE",
    "sg:address":"Zweigstr. 4",
    "sg:city":"Inning",
    "sg:phone":"+49 8143/1632",
    "sg:postcode":"82266",
    "sg:province":"Bayern",
    "wof:name":"Josef M\u00fcller Gmbh",
    "wof:placetype":"venue"
},
  "geometry": {"coordinates":[11.1485233307,48.0804176331],"type":"Point"}
}