{
  "type": "Feature",
  "properties": {
    "iso:country":"DE",
    "sg:address":"Schlauden 2",
    "sg:city":"Bielefeld",
    "sg:phone":"+49 521/335600",
    "sg:postcode":"33719",
    "sg:province":"Nordrhein-Westfalen",
    "wof:name":"Eugen Gracka",
    "wof:placetype":"venue"
},
  "geometry": {"coordinates":[8.598902,52.029572],"type":"Point"}
}