{
  "type": "Feature",
  "properties": {
    "iso:country":"DE",
    "sg:address":"Schorf 60",
    "sg:city":"Bremen",
    "sg:phone":"+49 421/8728923",
    "sg:postcode":"28357",
    "sg:province":"Bremen",
    "wof:name":"B\u00fcro Leasing Vogt Gmbh",
    "wof:placetype":"venue"
},
  "geometry": {"coordinates":[8.8924102783,53.0973587036],"type":"Point"}
}