{
  "type": "Feature",
  "properties": {
    "iso:country":"DE",
    "sg:address":"Alter Postweg 173h",
    "sg:city":"Bremen",
    "sg:phone":"+49 421/415438",
    "sg:postcode":"28207",
    "sg:province":"Bremen",
    "wof:name":"Bremer-curier-dienst Gmbh",
    "wof:placetype":"venue"
},
  "geometry": {"coordinates":[8.881166,53.060932],"type":"Point"}
}