{
  "type": "Feature",
  "properties": {
    "iso:country":"DE",
    "sg:address":"Nicklheimer Str. 66",
    "sg:city":"Raubling",
    "sg:phone":"+49 8035/3185",
    "sg:postcode":"83064",
    "sg:province":"Bayern",
    "wof:name":"Helmut Danner",
    "wof:placetype":"venue"
},
  "geometry": {"coordinates":[12.0969696045,47.7867660522],"type":"Point"}
}