{
  "type": "Feature",
  "properties": {
    "iso:country":"DE",
    "sg:address":"Schneiderstr. 87",
    "sg:city":"Krefeld",
    "sg:phone":"+49 2151/804240",
    "sg:postcode":"47798",
    "sg:province":"Nordrhein-Westfalen",
    "wof:name":"Tipico Ohg",
    "wof:placetype":"venue"
},
  "geometry": {"coordinates":[6.5580658913,51.3371124268],"type":"Point"}
}