{
  "type": "Feature",
  "properties": {
    "iso:country":"DE",
    "sg:address":"Hainstr. 11",
    "sg:city":"Thum",
    "sg:phone":"+49 37297/3322",
    "sg:postcode":"09419",
    "sg:province":"Sachsen",
    "wof:name":"Sabine Viertel",
    "wof:placetype":"venue"
},
  "geometry": {"coordinates":[12.953803,50.673981],"type":"Point"}
}