{
  "type": "Feature",
  "properties": {
    "iso:country":"DE",
    "sg:address":"Kressenberg 1",
    "sg:city":"Hattingen",
    "sg:postcode":"45529",
    "sg:province":"Nordrhein-Westfalen",
    "wof:name":"Kath. \u00f6ffentliche Bibliothek St. Engelbert",
    "wof:placetype":"venue"
},
  "geometry": {"coordinates":[7.122981,51.381943],"type":"Point"}
}