{
  "type": "Feature",
  "properties": {
    "iso:country":"DE",
    "sg:address":"Bonhoefferstr. 15",
    "sg:city":"Oldenburg",
    "sg:phone":"+49 441/51810",
    "sg:postcode":"26129",
    "sg:province":"Niedersachsen",
    "wof:name":"Trios Me\u00df- Und Datentechnik Gmbh",
    "wof:placetype":"venue"
},
  "geometry": {"coordinates":[8.157492,53.137653],"type":"Point"}
}