{
  "type": "Feature",
  "properties": {
    "iso:country":"DE",
    "sg:address":"M\u00f6sle 37",
    "sg:city":"G\u00fcnzburg",
    "sg:phone":"+49 8221/399494",
    "sg:postcode":"89312",
    "sg:province":"Bayern",
    "wof:name":"Dr. Med. J\u00fcrgen Meyer",
    "wof:placetype":"venue"
},
  "geometry": {"coordinates":[10.3112344742,48.4614906311],"type":"Point"}
}