{
  "type": "Feature",
  "properties": {
    "iso:country":"DE",
    "sg:address":"Marienstr. 113",
    "sg:city":"Offenbach",
    "sg:phone":"+49 69/888536",
    "sg:postcode":"63069",
    "sg:province":"Hessen",
    "wof:name":"Martin Schulz Rechtsanwalt",
    "wof:placetype":"venue"
},
  "geometry": {"coordinates":[8.7536420822,50.0976867676],"type":"Point"}
}