{
  "type": "Feature",
  "properties": {
    "iso:country":"DE",
    "sg:address":"Bruckstr. 13",
    "sg:city":"Dingolfing",
    "sg:phone":"+49 8731/1395",
    "sg:postcode":"84130",
    "sg:province":"Bayern",
    "wof:name":"Franz Stadler",
    "wof:placetype":"venue"
},
  "geometry": {"coordinates":[12.4964008331,48.6294593811],"type":"Point"}
}