{
  "type": "Feature",
  "properties": {
    "iso:country":"DE",
    "sg:address":"Pauluszell",
    "sg:city":"Wurmsham",
    "sg:phone":"+49 8742/8101",
    "sg:postcode":"84189",
    "sg:province":"Bayern",
    "wof:name":"Walter F\u00f6ckersperger Gmbh",
    "wof:placetype":"venue"
},
  "geometry": {"coordinates":[12.30528,48.365868],"type":"Point"}
}