{
  "type": "Feature",
  "properties": {
    "iso:country":"DE",
    "sg:address":"An der Buchhalde 12",
    "sg:city":"Brigachtal",
    "sg:phone":"+49 7721/90013",
    "sg:postcode":"78086",
    "sg:province":"Baden-W\u00fcrttemberg",
    "wof:name":"Mezger Ingenieur",
    "wof:placetype":"venue"
},
  "geometry": {"coordinates":[8.4781579971,48.0196876526],"type":"Point"}
}