{
  "type": "Feature",
  "properties": {
    "iso:country":"DE",
    "sg:address":"Mascowstr. 12",
    "sg:city":"G\u00fctzkow",
    "sg:phone":"+49 38353/51524",
    "sg:postcode":"17506",
    "sg:province":"Mecklenburg-Vorpommern",
    "wof:name":"E. Kunte Und K. Bernstein",
    "wof:placetype":"venue"
},
  "geometry": {"coordinates":[13.4155693054,53.9335021973],"type":"Point"}
}