{
  "type": "Feature",
  "properties": {
    "iso:country":"DE",
    "sg:address":"Schlo\u00dfstr. 2",
    "sg:city":"Pirmasens",
    "sg:phone":"+49 6331/62385",
    "sg:postcode":"66953",
    "sg:province":"Rheinland-Pfalz",
    "wof:name":"Leonberger Immobilien Gmbh",
    "wof:placetype":"venue"
},
  "geometry": {"coordinates":[7.6042189598,49.2048492432],"type":"Point"}
}