{
  "type": "Feature",
  "properties": {
    "iso:country":"DE",
    "sg:address":"Stolper Str. 49",
    "sg:city":"Bremen",
    "sg:phone":"+49 421/631201",
    "sg:postcode":"28717",
    "sg:province":"Bremen",
    "wof:name":"Claus-arco K\u00f6rner Haus-und Grundst\u00fccksmakler",
    "wof:placetype":"venue"
},
  "geometry": {"coordinates":[8.7120027542,53.1760101318],"type":"Point"}
}