{
  "type": "Feature",
  "properties": {
    "iso:country":"DE",
    "sg:address":"Dresdener Str. 26",
    "sg:city":"Bernsdorf",
    "sg:phone":"+49 35723/20409",
    "sg:postcode":"02994",
    "sg:province":"Sachsen",
    "wof:name":"Harold Mehlhose",
    "wof:placetype":"venue"
},
  "geometry": {"coordinates":[14.0629873276,51.3672943115],"type":"Point"}
}