{
  "type": "Feature",
  "properties": {
    "iso:country":"DE",
    "sg:address":"Marktstr. 6",
    "sg:city":"Schneverdingen",
    "sg:postcode":"29640",
    "sg:province":"Niedersachsen",
    "wof:name":"Supermarkt Ahrens- Isermann Gmbh",
    "wof:placetype":"venue"
},
  "geometry": {"coordinates":[9.7853002548,53.1193656921],"type":"Point"}
}