{
  "type": "Feature",
  "properties": {
    "iso:country":"DE",
    "sg:address":"Haarer Weg 3",
    "sg:city":"Grasbrunn",
    "sg:phone":"+49 89/4609090",
    "sg:postcode":"85630",
    "sg:province":"Bayern",
    "wof:name":"F\u00fcrtsch Ohg",
    "wof:placetype":"venue"
},
  "geometry": {"coordinates":[11.7439079285,48.0808029175],"type":"Point"}
}