{
  "type": "Feature",
  "properties": {
    "iso:country":"DE",
    "sg:address":"Kirchplatz 8",
    "sg:city":"Eggst\u00e4tt",
    "sg:postcode":"83125",
    "sg:province":"Bayern",
    "wof:name":"Gasthof-pension-unterwirt",
    "wof:placetype":"venue"
},
  "geometry": {"coordinates":[12.3804779053,47.9272460938],"type":"Point"}
}