{
  "type": "Feature",
  "properties": {
    "iso:country":"DE",
    "sg:address":"Montebruchstr. 2",
    "sg:city":"Essen",
    "sg:phone":"+49 2054/9240",
    "sg:postcode":"45219",
    "sg:province":"Nordrhein-Westfalen",
    "wof:name":"Redaktion Der Anschnitt Gl\u00fcckauf Verlag",
    "wof:placetype":"venue"
},
  "geometry": {"coordinates":[6.9337048531,51.3572921753],"type":"Point"}
}