{
  "type": "Feature",
  "properties": {
    "iso:country":"DE",
    "sg:address":"Grafenheider Str 12",
    "sg:city":"Bielefeld",
    "sg:phone":"+49 521/770820",
    "sg:postcode":"33729",
    "sg:province":"Nordrhein-Westfalen",
    "wof:name":"Sirius Direktmarketing Gmbh",
    "wof:placetype":"venue"
},
  "geometry": {"coordinates":[8.606006,52.065399],"type":"Point"}
}