{
  "type": "Feature",
  "properties": {
    "iso:country":"DE",
    "sg:address":"Waldzeller Str. 14",
    "sg:city":"Roden",
    "sg:postcode":"97849",
    "sg:province":"Bayern",
    "wof:name":"Fischer Agrar Verwaltungs Gmbh",
    "wof:placetype":"venue"
},
  "geometry": {"coordinates":[9.6227684021,49.9201164246],"type":"Point"}
}