{
  "type": "Feature",
  "properties": {
    "iso:country":"DE",
    "sg:address":"Sarstedt",
    "sg:city":"Pattensen",
    "sg:phone":"+49 5101/2266",
    "sg:postcode":"30982",
    "sg:province":"Niedersachsen",
    "wof:name":"Bestattungsinstitut Gieseke",
    "wof:placetype":"venue"
},
  "geometry": {"coordinates":[9.765352,52.263512],"type":"Point"}
}