{
  "type": "Feature",
  "properties": {
    "iso:country":"DE",
    "sg:address":"Am Laubberg 19",
    "sg:city":"Bergneustadt",
    "sg:phone":"+49 2261/43393",
    "sg:postcode":"51702",
    "sg:province":"Nordrhein-Westfalen",
    "wof:name":"Wolfgang Kammerer",
    "wof:placetype":"venue"
},
  "geometry": {"coordinates":[7.6918039322,51.028465271],"type":"Point"}
}