{
  "type": "Feature",
  "properties": {
    "iso:country":"DE",
    "sg:address":"Im Alten Holz 171",
    "sg:city":"Hagen",
    "sg:phone":"+49 2331/57453",
    "sg:postcode":"58093",
    "sg:province":"Nordrhein-Westfalen",
    "wof:name":"Ricarda Benner",
    "wof:placetype":"venue"
},
  "geometry": {"coordinates":[7.51093,51.37727],"type":"Point"}
}