{
  "type": "Feature",
  "properties": {
    "iso:country":"DE",
    "sg:address":"Georgstr. 27",
    "sg:city":"Bienenb\u00fcttel",
    "sg:phone":"+49 5823/257",
    "sg:postcode":"29553",
    "sg:province":"Niedersachsen",
    "wof:name":"Ilka D\u00fcmmel",
    "wof:placetype":"venue"
},
  "geometry": {"coordinates":[10.484664917,53.1415252686],"type":"Point"}
}