{
  "type": "Feature",
  "properties": {
    "iso:country":"DE",
    "sg:address":"Johann-H\u00e4ck-Str. 14",
    "sg:city":"Odenthal",
    "sg:phone":"+49 2174/743968",
    "sg:postcode":"51519",
    "sg:province":"Nordrhein-Westfalen",
    "wof:name":"A. Berger",
    "wof:placetype":"venue"
},
  "geometry": {"coordinates":[7.1166129112,51.0325622559],"type":"Point"}
}