{
  "type": "Feature",
  "properties": {
    "iso:country":"DE",
    "sg:address":"Eleonorenweg 2",
    "sg:city":"Hamburg",
    "sg:postcode":"21109",
    "sg:province":"Hamburg",
    "wof:name":"Anb-bau Bauunternehmung Gmbh",
    "wof:placetype":"venue"
},
  "geometry": {"coordinates":[10.010991,53.486797],"type":"Point"}
}