{
  "type": "Feature",
  "properties": {
    "iso:country":"DE",
    "sg:address":"Schlo\u00dffeld 86 a",
    "sg:city":"Senden",
    "sg:postcode":"48308",
    "sg:province":"Nordrhein-Westfalen",
    "wof:name":"Kako Gmbh",
    "wof:placetype":"venue"
},
  "geometry": {"coordinates":[7.465327,51.852158],"type":"Point"}
}