{
  "type": "Feature",
  "properties": {
    "iso:country":"DE",
    "sg:address":"Beim Pfaffenkeller 10 A",
    "sg:city":"Augsburg",
    "sg:phone":"+49 821/509540",
    "sg:postcode":"86152",
    "sg:province":"Bayern",
    "wof:name":"Alfred Kosebach Architekt",
    "wof:placetype":"venue"
},
  "geometry": {"coordinates":[10.900006,48.373486],"type":"Point"}
}