{
  "type": "Feature",
  "properties": {
    "iso:country":"DE",
    "sg:address":"Kronenstr. 5",
    "sg:city":"Winterlingen",
    "sg:phone":"+49 7434/2443",
    "sg:postcode":"72474",
    "sg:province":"Baden-W\u00fcrttemberg",
    "wof:name":"O. Koch",
    "wof:placetype":"venue"
},
  "geometry": {"coordinates":[9.118225,48.178967],"type":"Point"}
}