{
  "type": "Feature",
  "properties": {
    "iso:country":"DE",
    "sg:address":"Jungbergerstr. 17",
    "sg:city":"K\u00f6ln",
    "sg:phone":"+49 221/983700",
    "sg:postcode":"51105",
    "sg:province":"Nordrhein-Westfalen",
    "wof:name":"Cokonzept Consulting & Management Gmbh",
    "wof:placetype":"venue"
},
  "geometry": {"coordinates":[6.989251,50.911377],"type":"Point"}
}