{
  "type": "Feature",
  "properties": {
    "iso:country":"DE",
    "sg:address":"Kaiserstr. 52",
    "sg:city":"Waldbr\u00f6l",
    "sg:phone":"+49 2291/4927",
    "sg:postcode":"51545",
    "sg:province":"Nordrhein-Westfalen",
    "wof:name":"Sanit\u00e4tshaus Braun Inh. Wolfgang Boos",
    "wof:placetype":"venue"
},
  "geometry": {"coordinates":[7.6191048622,50.877456665],"type":"Point"}
}