{
  "type": "Feature",
  "properties": {
    "iso:country":"DE",
    "sg:address":"Emil-Ott-Str. 9",
    "sg:city":"Kelheim",
    "sg:phone":"+49 9441/3614",
    "sg:postcode":"93309",
    "sg:province":"Bayern",
    "wof:name":"Josef Pletl",
    "wof:placetype":"venue"
},
  "geometry": {"coordinates":[11.8705,48.916145],"type":"Point"}
}