{
  "type": "Feature",
  "properties": {
    "iso:country":"DE",
    "sg:address":"Heerstr. 3",
    "sg:city":"Selfkant",
    "sg:phone":"+49 2456/1224",
    "sg:postcode":"52538",
    "sg:province":"Nordrhein-Westfalen",
    "wof:name":"J. Backhaus Gmbh",
    "wof:placetype":"venue"
},
  "geometry": {"coordinates":[5.935772,51.026108],"type":"Point"}
}