{
  "type": "Feature",
  "properties": {
    "iso:country":"DE",
    "sg:address":"Friesenweg 34",
    "sg:city":"S\u00fcdbrookmerland",
    "sg:phone":"+49 4941/87123",
    "sg:postcode":"26624",
    "sg:province":"Niedersachsen",
    "wof:name":"Siegmund Fahnster",
    "wof:placetype":"venue"
},
  "geometry": {"coordinates":[7.395602,53.482662],"type":"Point"}
}