{
  "type": "Feature",
  "properties": {
    "iso:country":"DE",
    "sg:address":"Rittersbacher Str. 74",
    "sg:city":"Schwabach",
    "sg:phone":"+49 9122/2318",
    "sg:postcode":"91126",
    "sg:province":"Bayern",
    "wof:name":"Felsenkeller",
    "wof:placetype":"venue"
},
  "geometry": {"coordinates":[11.0182523727,49.3190841675],"type":"Point"}
}