{
  "type": "Feature",
  "properties": {
    "iso:country":"DE",
    "sg:address":"Friedrich-Ebert-Str. 18",
    "sg:city":"Kassel",
    "sg:phone":"+49 561/711469",
    "sg:postcode":"34117",
    "sg:province":"Hessen",
    "wof:name":"Prigogine",
    "wof:placetype":"venue"
},
  "geometry": {"coordinates":[9.486956,51.314625],"type":"Point"}
}