{
  "type": "Feature",
  "properties": {
    "iso:country":"DE",
    "sg:address":"Schlo\u00dfweg 2",
    "sg:city":"Reichenschwand",
    "sg:phone":"+49 9151/6071",
    "sg:postcode":"91244",
    "sg:province":"Bayern",
    "wof:name":"K\u00fcstroh-metallbau Verwaltungs-gmbh",
    "wof:placetype":"venue"
},
  "geometry": {"coordinates":[11.3754739761,49.5108833313],"type":"Point"}
}