{
  "type": "Feature",
  "properties": {
    "iso:country":"DE",
    "sg:address":"Mainzer Str. 6",
    "sg:city":"Kaiserslautern",
    "sg:phone":"+49 631/66931",
    "sg:postcode":"67657",
    "sg:province":"Rheinland-Pfalz",
    "wof:name":"Kulisse",
    "wof:placetype":"venue"
},
  "geometry": {"coordinates":[7.7806777954,49.4496040344],"type":"Point"}
}