{
  "type": "Feature",
  "properties": {
    "iso:country":"DE",
    "sg:address":"Vordere Karlstr. 41",
    "sg:city":"G\u00f6ppingen",
    "sg:phone":"+49 7161/78610",
    "sg:postcode":"73033",
    "sg:province":"Baden-W\u00fcrttemberg",
    "wof:name":"D. Hahn",
    "wof:placetype":"venue"
},
  "geometry": {"coordinates":[9.660719,48.700672],"type":"Point"}
}