{
  "type": "Feature",
  "properties": {
    "iso:country":"DE",
    "sg:address":"Beieringsweg 12",
    "sg:city":"Borken",
    "sg:phone":"+49 2862/910713",
    "sg:postcode":"46325",
    "sg:province":"Nordrhein-Westfalen",
    "wof:name":"Modeladen Hillenbach Gmbh",
    "wof:placetype":"venue"
},
  "geometry": {"coordinates":[6.864386,51.908901],"type":"Point"}
}