{
  "type": "Feature",
  "properties": {
    "iso:country":"DE",
    "sg:address":"Siemensstr. 1",
    "sg:city":"Essenbach",
    "sg:postcode":"84051",
    "sg:province":"Bayern",
    "wof:name":"Fodig Handelsgesellschaft Mbh",
    "wof:placetype":"venue"
},
  "geometry": {"coordinates":[12.2057991028,48.5859260559],"type":"Point"}
}