{
  "type": "Feature",
  "properties": {
    "iso:country":"DE",
    "sg:address":"Professor-Pl\u00fccker-Str. 5",
    "sg:city":"Wolfenb\u00fcttel",
    "sg:phone":"+49 5331/32099",
    "sg:postcode":"38302",
    "sg:province":"Niedersachsen",
    "wof:name":"G. St\u00fctzer Immobilienmakler",
    "wof:placetype":"venue"
},
  "geometry": {"coordinates":[10.5429916382,52.1670722961],"type":"Point"}
}