{
  "type": "Feature",
  "properties": {
    "iso:country":"DE",
    "sg:address":"\u00dcckendorfer Str. 95",
    "sg:city":"Gelsenkirchen",
    "sg:phone":"+49 209/200418",
    "sg:postcode":"45886",
    "sg:province":"Nordrhein-Westfalen",
    "wof:name":"Wacker",
    "wof:placetype":"venue"
},
  "geometry": {"coordinates":[7.1190900803,51.5010795593],"type":"Point"}
}