{
  "type": "Feature",
  "properties": {
    "iso:country":"DE",
    "sg:address":"N\u00f6rdliche Waldstr. 32",
    "sg:city":"Wagh\u00e4usel",
    "sg:phone":"+49 7254/71308",
    "sg:postcode":"68753",
    "sg:province":"Baden-W\u00fcrttemberg",
    "wof:name":"M\u00fcller Edelbert Handelsagentur Gmbh",
    "wof:placetype":"venue"
},
  "geometry": {"coordinates":[8.5385303497,49.2475242615],"type":"Point"}
}