{
  "type": "Feature",
  "properties": {
    "iso:country":"DE",
    "sg:address":"Wildparkstr. 27",
    "sg:city":"Neuweiler",
    "sg:phone":"+49 7055/2272",
    "sg:postcode":"75389",
    "sg:province":"Baden-W\u00fcrttemberg",
    "wof:name":"\u00d6fele",
    "wof:placetype":"venue"
},
  "geometry": {"coordinates":[8.6181373596,48.629322052],"type":"Point"}
}