{
  "type": "Feature",
  "properties": {
    "iso:country":"DE",
    "sg:address":"Lemgoer Str. 69",
    "sg:city":"Barntrup",
    "sg:phone":"+49 171 5010654",
    "sg:postcode":"32683",
    "sg:province":"Nordrhein-Westfalen",
    "wof:name":"Karl-fred Altrogge",
    "wof:placetype":"venue"
},
  "geometry": {"coordinates":[9.098941,51.993847],"type":"Point"}
}