{
  "type": "Feature",
  "properties": {
    "iso:country":"DE",
    "sg:address":"Auerbacher Str. 5",
    "sg:city":"Frankfurt",
    "sg:postcode":"60388",
    "sg:province":"Hessen",
    "wof:name":"Lehning Gmbh",
    "wof:placetype":"venue"
},
  "geometry": {"coordinates":[8.758652,50.142361],"type":"Point"}
}