{
  "type": "Feature",
  "properties": {
    "iso:country":"DE",
    "sg:address":"Am S\u00e4gewerk 2",
    "sg:city":"Riesweiler",
    "sg:phone":"+49 6761/7755",
    "sg:postcode":"55499",
    "sg:province":"Rheinland-Pfalz",
    "wof:name":"Holzbau Sch\u00f6n Gmbh",
    "wof:placetype":"venue"
},
  "geometry": {"coordinates":[7.5509967804,49.9574813843],"type":"Point"}
}