{
  "type": "Feature",
  "properties": {
    "iso:country":"DE",
    "sg:address":"Fuhrmannstr. 3",
    "sg:city":"Cham",
    "sg:phone":"+49 9971/4840",
    "sg:postcode":"93413",
    "sg:province":"Bayern",
    "wof:name":"Schmidt Bank",
    "wof:placetype":"venue"
},
  "geometry": {"coordinates":[12.66728,49.218807],"type":"Point"}
}