{
  "type": "Feature",
  "properties": {
    "iso:country":"DE",
    "sg:address":"Hauptstr. 3",
    "sg:city":"Hanau",
    "sg:phone":"+49 6181/54350",
    "sg:postcode":"63457",
    "sg:province":"Hessen",
    "wof:name":"Hans Rayher",
    "wof:placetype":"venue"
},
  "geometry": {"coordinates":[8.944803,50.103916],"type":"Point"}
}