{
  "type": "Feature",
  "properties": {
    "iso:country":"DE",
    "sg:address":"Gewerbering 1",
    "sg:city":"Oberndorf",
    "sg:postcode":"86698",
    "sg:province":"Bayern",
    "wof:name":"Autohaus Rainer Wernitz",
    "wof:placetype":"venue"
},
  "geometry": {"coordinates":[10.8681316376,48.6777992249],"type":"Point"}
}