{
  "type": "Feature",
  "properties": {
    "iso:country":"DE",
    "sg:address":"Bramscher Str. 5",
    "sg:city":"Alfhausen",
    "sg:phone":"+49 5464/1222",
    "sg:postcode":"49594",
    "sg:province":"Niedersachsen",
    "wof:name":"Dr. Reinhold Heil Tierarzt",
    "wof:placetype":"venue"
},
  "geometry": {"coordinates":[7.9552159309,52.498249054],"type":"Point"}
}