{
  "type": "Feature",
  "properties": {
    "iso:country":"DE",
    "sg:address":"Emscherstr. 6",
    "sg:city":"Minden",
    "sg:postcode":"32427",
    "sg:province":"Nordrhein-Westfalen",
    "wof:name":"Frisia Steuerungen Gmbh",
    "wof:placetype":"venue"
},
  "geometry": {"coordinates":[8.871881,52.29623],"type":"Point"}
}