{
  "type": "Feature",
  "properties": {
    "iso:country":"DE",
    "sg:address":"Viktoriaallee 5a",
    "sg:city":"Bad Ems",
    "sg:phone":"+49 2603/4417",
    "sg:postcode":"56130",
    "sg:province":"Rheinland-Pfalz",
    "wof:name":"Pension Josef Und Aenne Wirz",
    "wof:placetype":"venue"
},
  "geometry": {"coordinates":[7.7169427872,50.3324394226],"type":"Point"}
}