{
  "type": "Feature",
  "properties": {
    "iso:country":"DE",
    "sg:address":"Lauxweg 24",
    "sg:city":"Berlin",
    "sg:phone":"+49 30/7058469",
    "sg:postcode":"12107",
    "sg:province":"Berlin",
    "wof:name":"Tsb Travel Und Shuttle Gmbh",
    "wof:placetype":"venue"
},
  "geometry": {"coordinates":[13.379573822,52.4351158142],"type":"Point"}
}