{
  "type": "Feature",
  "properties": {
    "iso:country":"DE",
    "sg:address":"Neub\u00f6rger Str. 15",
    "sg:city":"Neulehe",
    "sg:phone":"+49 4968/298",
    "sg:postcode":"26909",
    "sg:province":"Niedersachsen",
    "wof:name":"Eduard Kaufhold",
    "wof:placetype":"venue"
},
  "geometry": {"coordinates":[7.443962,52.998993],"type":"Point"}
}