{
  "type": "Feature",
  "properties": {
    "iso:country":"DE",
    "sg:address":"Pfortefeldstr. 19",
    "sg:city":"Gro\u00df-Gerau",
    "sg:phone":"+49 6152/950007",
    "sg:postcode":"64521",
    "sg:province":"Hessen",
    "wof:name":"Scherer Gmbh",
    "wof:placetype":"venue"
},
  "geometry": {"coordinates":[8.455377,49.906944],"type":"Point"}
}