{
  "type": "Feature",
  "properties": {
    "iso:country":"DE",
    "sg:address":"Zeller Str. 29",
    "sg:city":"W\u00fcrzburg",
    "sg:phone":"+49 931/44651",
    "sg:postcode":"97082",
    "sg:province":"Bayern",
    "wof:name":"Erich Sebald",
    "wof:placetype":"venue"
},
  "geometry": {"coordinates":[9.922912,49.793831],"type":"Point"}
}