{
  "type": "Feature",
  "properties": {
    "iso:country":"DE",
    "sg:address":"Hasenstr. 4",
    "sg:city":"Merzig",
    "sg:phone":"+49 6861/6056",
    "sg:postcode":"66663",
    "sg:province":"Saarland",
    "wof:name":"Reiseb\u00fcro Saargru\u00df Dillschneider & Sohn Gmbh",
    "wof:placetype":"venue"
},
  "geometry": {"coordinates":[6.6133751869,49.4403762817],"type":"Point"}
}