{
  "type": "Feature",
  "properties": {
    "iso:country":"DE",
    "sg:address":"Hans-Bunte-Str. 43",
    "sg:city":"N\u00fcrnberg",
    "sg:phone":"+49 911/327166",
    "sg:postcode":"90431",
    "sg:province":"Bayern",
    "wof:name":"Cre Apro Werbemittel Gmbh",
    "wof:placetype":"venue"
},
  "geometry": {"coordinates":[11.042445,49.448639],"type":"Point"}
}