{
  "type": "Feature",
  "properties": {
    "iso:country":"DE",
    "sg:address":"Cantadorstr. 18",
    "sg:city":"D\u00fcsseldorf",
    "sg:phone":"+49 211/915070",
    "sg:postcode":"40211",
    "sg:province":"Nordrhein-Westfalen",
    "wof:name":"Beeckens Agentur F\u00fcr Unter- Nehmens-kommunikation Gmbh",
    "wof:placetype":"venue"
},
  "geometry": {"coordinates":[6.7915410995,51.2271957397],"type":"Point"}
}