{
  "type": "Feature",
  "properties": {
    "iso:country":"DE",
    "sg:address":"Platz der Ermahnung 4",
    "sg:city":"M\u00fchlau",
    "sg:postcode":"09241",
    "sg:province":"Sachsen",
    "wof:name":"Evangelisch-lutherische Kirche",
    "wof:placetype":"venue"
},
  "geometry": {"coordinates":[12.7639055252,50.9049682617],"type":"Point"}
}