{
  "type": "Feature",
  "properties": {
    "iso:country":"DE",
    "sg:address":"Stuttgarter Str. 13",
    "sg:city":"Frankfurt",
    "sg:phone":"+49 69/232138",
    "sg:postcode":"60329",
    "sg:province":"Hessen",
    "wof:name":"Karl Denz",
    "wof:placetype":"venue"
},
  "geometry": {"coordinates":[8.6636810303,50.1029052734],"type":"Point"}
}