{
  "type": "Feature",
  "properties": {
    "iso:country":"DE",
    "sg:address":"Im Avelertal 71",
    "sg:city":"Trier",
    "sg:phone":"+49 651/25098",
    "sg:postcode":"54295",
    "sg:province":"Rheinland-Pfalz",
    "wof:name":"Gebr. Welter Ohg",
    "wof:placetype":"venue"
},
  "geometry": {"coordinates":[6.67164,49.761318],"type":"Point"}
}