{
  "type": "Feature",
  "properties": {
    "iso:country":"DE",
    "sg:address":"St.-Johannes-Str. 6",
    "sg:city":"Meitingen",
    "sg:phone":"+49 8271/2025",
    "sg:postcode":"86405",
    "sg:province":"Bayern",
    "wof:name":"Ev. Luth. Pfarramt",
    "wof:placetype":"venue"
},
  "geometry": {"coordinates":[10.8557348251,48.5452384949],"type":"Point"}
}