{
  "type": "Feature",
  "properties": {
    "iso:country":"DE",
    "sg:address":"Aachener Str. 14",
    "sg:city":"Hillesheim",
    "sg:phone":"+49 6593/989010",
    "sg:postcode":"54576",
    "sg:province":"Rheinland-Pfalz",
    "wof:name":"Bauunternehmung Bauer Gmbh",
    "wof:placetype":"venue"
},
  "geometry": {"coordinates":[6.665831,50.292316],"type":"Point"}
}