{
  "type": "Feature",
  "properties": {
    "iso:country":"DE",
    "sg:address":"Gerhart-Hauptmann-Str. 13",
    "sg:city":"Wunstorf",
    "sg:phone":"+49 5031/912797",
    "sg:postcode":"31515",
    "sg:province":"Niedersachsen",
    "wof:name":"Krock Malerfachbetrieb Gmbh",
    "wof:placetype":"venue"
},
  "geometry": {"coordinates":[9.430924,52.431824],"type":"Point"}
}