{
  "type": "Feature",
  "properties": {
    "iso:country":"DE",
    "sg:address":"Josef-Schneider-Str. 8",
    "sg:city":"W\u00fcrzburg",
    "sg:phone":"+49 931/2011",
    "sg:postcode":"97080",
    "sg:province":"Bayern",
    "wof:name":"Universit\u00e4ts-kliniken",
    "wof:placetype":"venue"
},
  "geometry": {"coordinates":[9.956659,49.803024],"type":"Point"}
}