{
  "type": "Feature",
  "properties": {
    "iso:country":"DE",
    "sg:address":"Mozartstr. 20a",
    "sg:city":"Stuttgart",
    "sg:phone":"+49 711/6071070",
    "sg:postcode":"70180",
    "sg:province":"Baden-W\u00fcrttemberg",
    "wof:name":"Maglock",
    "wof:placetype":"venue"
},
  "geometry": {"coordinates":[9.1787452698,48.7689056396],"type":"Point"}
}