{
  "type": "Feature",
  "properties": {
    "iso:country":"DE",
    "sg:address":"Oppertsweg 6",
    "sg:city":"Erbach",
    "sg:postcode":"64711",
    "sg:province":"Hessen",
    "wof:name":"Sebo Gmbh",
    "wof:placetype":"venue"
},
  "geometry": {"coordinates":[9.0099163055,49.6468353271],"type":"Point"}
}