{
  "type": "Feature",
  "properties": {
    "iso:country":"DE",
    "sg:address":"Badstr. 4",
    "sg:city":"Frauenau",
    "sg:phone":"+49 9926/789",
    "sg:postcode":"94258",
    "sg:province":"Bayern",
    "wof:name":"B\u00fcrgerhalle",
    "wof:placetype":"venue"
},
  "geometry": {"coordinates":[13.3034563065,48.9919052124],"type":"Point"}
}