{
  "type": "Feature",
  "properties": {
    "iso:country":"DE",
    "sg:address":"Prinzenstr. 96",
    "sg:city":"Voerde",
    "sg:phone":"+49 2855/15548",
    "sg:postcode":"46562",
    "sg:province":"Nordrhein-Westfalen",
    "wof:name":"J. Und Gabriele Scheffler",
    "wof:placetype":"venue"
},
  "geometry": {"coordinates":[6.705648,51.597893],"type":"Point"}
}