{
  "type": "Feature",
  "properties": {
    "iso:country":"DE",
    "sg:address":"Stargarder Str. 11",
    "sg:city":"Berlin",
    "sg:postcode":"10437",
    "sg:province":"Berlin",
    "wof:name":"Doc Future Financial Service Gmbh",
    "wof:placetype":"venue"
},
  "geometry": {"coordinates":[13.4170875549,52.5467758179],"type":"Point"}
}