{
  "type": "Feature",
  "properties": {
    "iso:country":"DE",
    "sg:address":"Am Wehlbach 1",
    "sg:city":"Hameln",
    "sg:phone":"+49 5151/28709",
    "sg:postcode":"31787",
    "sg:province":"Niedersachsen",
    "wof:name":"Forsthaus Wehl",
    "wof:placetype":"venue"
},
  "geometry": {"coordinates":[9.3402280807,52.1256446838],"type":"Point"}
}