{
  "type": "Feature",
  "properties": {
    "iso:country":"DE",
    "sg:address":"Hasenwinkel 3",
    "sg:city":"Braunschweig",
    "sg:phone":"+49 531/331212",
    "sg:postcode":"38114",
    "sg:province":"Niedersachsen",
    "wof:name":"Ev. Pfarramt Ii St. Andreaskirche",
    "wof:placetype":"venue"
},
  "geometry": {"coordinates":[10.5197124481,52.2753677368],"type":"Point"}
}