{
  "type": "Feature",
  "properties": {
    "iso:country":"DE",
    "sg:address":"Im Lipperfeld 38",
    "sg:city":"Oberhausen",
    "sg:postcode":"46047",
    "sg:province":"Nordrhein-Westfalen",
    "wof:name":"Plugged Media Gmbh",
    "wof:placetype":"venue"
},
  "geometry": {"coordinates":[6.8675141335,51.4870948792],"type":"Point"}
}