{
  "type": "Feature",
  "properties": {
    "iso:country":"DE",
    "sg:city":"Felsberg",
    "sg:phone":"+49 4956/62802",
    "sg:postcode":"34587",
    "sg:province":"Hessen",
    "wof:name":"Kreissparkasse Schwalm-eder",
    "wof:placetype":"venue"
},
  "geometry": {"coordinates":[9.421669,51.134609],"type":"Point"}
}