{
  "type": "Feature",
  "properties": {
    "iso:country":"DE",
    "sg:address":"Takustr. 97",
    "sg:city":"K\u00f6ln",
    "sg:phone":"+49 221/558800",
    "sg:postcode":"50825",
    "sg:province":"Nordrhein-Westfalen",
    "wof:name":"A. Und E. Lehnen",
    "wof:placetype":"venue"
},
  "geometry": {"coordinates":[6.91538,50.961399],"type":"Point"}
}