{
  "type": "Feature",
  "properties": {
    "iso:country":"DE",
    "sg:address":"Me\u00dfberg 1",
    "sg:city":"Hamburg",
    "sg:phone":"+49 40/321020",
    "sg:postcode":"20095",
    "sg:province":"Hamburg",
    "wof:name":"Flemming Holding Gesch\u00e4ftsf\u00fchrung Gmbh",
    "wof:placetype":"venue"
},
  "geometry": {"coordinates":[10.0018415451,53.5476951599],"type":"Point"}
}