{
  "type": "Feature",
  "properties": {
    "iso:country":"DE",
    "sg:address":"Hauptstr. 13",
    "sg:city":"Singen",
    "sg:phone":"+49 7731/799963",
    "sg:postcode":"78224",
    "sg:province":"Baden-W\u00fcrttemberg",
    "wof:name":"Caf\u00e9 Cappuccino",
    "wof:placetype":"venue"
},
  "geometry": {"coordinates":[9.886915,50.25351],"type":"Point"}
}