{
  "type": "Feature",
  "properties": {
    "iso:country":"DE",
    "sg:address":"Dr.-Seeling-Str. 19a",
    "sg:city":"Weiden",
    "sg:phone":"+49 961/41270",
    "sg:postcode":"92637",
    "sg:province":"Bayern",
    "wof:name":"Kontur-k\u00fcchen Gmbh",
    "wof:placetype":"venue"
},
  "geometry": {"coordinates":[12.1536846161,49.6645774841],"type":"Point"}
}