{
  "type": "Feature",
  "properties": {
    "iso:country":"DE",
    "sg:address":"Wehrweg 2",
    "sg:city":"Bad Nenndorf",
    "sg:phone":"+49 5725/6343",
    "sg:postcode":"31542",
    "sg:province":"Niedersachsen",
    "wof:name":"Heinrich Pfingsten",
    "wof:placetype":"venue"
},
  "geometry": {"coordinates":[9.334152,52.346043],"type":"Point"}
}