{
  "type": "Feature",
  "properties": {
    "iso:country":"DE",
    "sg:address":"Jaminstr. 9",
    "sg:city":"Erlangen",
    "sg:postcode":"91052",
    "sg:province":"Bayern",
    "wof:name":"Rinke Beteiligungs- Gmbh",
    "wof:placetype":"venue"
},
  "geometry": {"coordinates":[11.010302,49.577507],"type":"Point"}
}