{
  "type": "Feature",
  "properties": {
    "iso:country":"DE",
    "sg:address":"Wilhelmstr. 87 a",
    "sg:city":"Berlin",
    "sg:phone":"+49 30/36282190",
    "sg:postcode":"13593",
    "sg:province":"Berlin",
    "wof:name":"Hse Gesellschaft F\u00fcr Steuerungs- Und Daten-",
    "wof:placetype":"venue"
},
  "geometry": {"coordinates":[13.1705760956,52.5098457336],"type":"Point"}
}