{
  "type": "Feature",
  "properties": {
    "iso:country":"DE",
    "sg:address":"Ahornstr. 6b",
    "sg:city":"Hattersheim",
    "sg:phone":"+49 6190/930193",
    "sg:postcode":"65795",
    "sg:province":"Hessen",
    "wof:name":"C. O. L. A. Cost Of Living Analysen Gmbh",
    "wof:placetype":"venue"
},
  "geometry": {"coordinates":[8.491641,50.052414],"type":"Point"}
}