{
  "type": "Feature",
  "properties": {
    "iso:country":"DE",
    "sg:address":"Friedrichstr. 34",
    "sg:city":"Heppenheim",
    "sg:phone":"+49 6252/2654",
    "sg:postcode":"64646",
    "sg:province":"Hessen",
    "wof:name":"Rudi Ludwig Augenoptiker",
    "wof:placetype":"venue"
},
  "geometry": {"coordinates":[8.6396389008,49.6423721313],"type":"Point"}
}