{
  "type": "Feature",
  "properties": {
    "iso:country":"DE",
    "sg:address":"Robert-Koch-Str. 116",
    "sg:city":"Kelkheim",
    "sg:phone":"+49 6174/93480",
    "sg:postcode":"65779",
    "sg:province":"Hessen",
    "wof:name":"Wzr Gmbh",
    "wof:placetype":"venue"
},
  "geometry": {"coordinates":[8.4038000107,50.176864624],"type":"Point"}
}