{
  "type": "Feature",
  "properties": {
    "iso:country":"DE",
    "sg:address":"Stra\u00dfe des Friedens 3a",
    "sg:city":"Angerm\u00fcnde",
    "sg:phone":"+49 3331/26650",
    "sg:postcode":"16278",
    "sg:province":"Brandenburg",
    "wof:name":"Van Ghemen Dentallabor Angerm\u00fcnde Ohg",
    "wof:placetype":"venue"
},
  "geometry": {"coordinates":[14.0002174377,53.014465332],"type":"Point"}
}