{
  "type": "Feature",
  "properties": {
    "iso:country":"DE",
    "sg:address":"Kapellenstr. 8",
    "sg:city":"Sankt Augustin",
    "sg:phone":"+49 2241/29798",
    "sg:postcode":"53757",
    "sg:province":"Nordrhein-Westfalen",
    "wof:name":"Gerd Jonen",
    "wof:placetype":"venue"
},
  "geometry": {"coordinates":[7.1685900688,50.7588157654],"type":"Point"}
}