{
  "type": "Feature",
  "properties": {
    "iso:country":"DE",
    "sg:address":"Breisacher Str. 117",
    "sg:city":"Freiburg",
    "sg:phone":"+49 761/283757",
    "sg:postcode":"79106",
    "sg:province":"Baden-W\u00fcrttemberg",
    "wof:name":"Cafeteria In Der Tumorbiolog. Klinik",
    "wof:placetype":"venue"
},
  "geometry": {"coordinates":[7.83359,48.006008],"type":"Point"}
}