{
  "type": "Feature",
  "properties": {
    "iso:country":"DE",
    "sg:city":"St. Ingbert",
    "sg:postcode":"66386",
    "sg:province":"Saarland",
    "wof:name":"Evangelische Kantorei St. Ingbert (e.v.)",
    "wof:placetype":"venue"
},
  "geometry": {"coordinates":[7.111905,49.278954],"type":"Point"}
}