{
  "type": "Feature",
  "properties": {
    "iso:country":"DE",
    "sg:address":"Dewitzer Str. 18",
    "sg:city":"Taucha",
    "sg:phone":"+49 34298/30083",
    "sg:postcode":"04425",
    "sg:province":"Sachsen",
    "wof:name":"Happyreisen",
    "wof:placetype":"venue"
},
  "geometry": {"coordinates":[12.5029878616,51.3819122314],"type":"Point"}
}