{
  "type": "Feature",
  "properties": {
    "iso:country":"DE",
    "sg:address":"Westpreu\u00dfenstr. 67",
    "sg:city":"M\u00fcnchen",
    "sg:postcode":"81927",
    "sg:province":"Bayern",
    "wof:name":"Pvp Pietzak & Vollmann Gmbh",
    "wof:placetype":"venue"
},
  "geometry": {"coordinates":[11.6373519897,48.1543617249],"type":"Point"}
}