{
  "type": "Feature",
  "properties": {
    "iso:country":"DE",
    "sg:address":"Gartenstr. 6",
    "sg:city":"Wawern",
    "sg:phone":"+49 6501/16835",
    "sg:postcode":"54441",
    "sg:province":"Rheinland-Pfalz",
    "wof:name":"Paul Carl",
    "wof:placetype":"venue"
},
  "geometry": {"coordinates":[6.5487771034,49.6533508301],"type":"Point"}
}