{
  "type": "Feature",
  "properties": {
    "iso:country":"DE",
    "sg:address":"L\u00fcttelforst 350",
    "sg:city":"Schwalmtal",
    "sg:phone":"+49 2163/459563",
    "sg:postcode":"41366",
    "sg:province":"Nordrhein-Westfalen",
    "wof:name":"Heinz-willi Lehnen Steuerberater",
    "wof:placetype":"venue"
},
  "geometry": {"coordinates":[6.2354121208,51.2012252808],"type":"Point"}
}