{
  "type": "Feature",
  "properties": {
    "iso:country":"DE",
    "sg:address":"Kanalstr 4",
    "sg:city":"Kaiserslautern",
    "sg:phone":"+49 4963/1855116",
    "sg:postcode":"67655",
    "sg:province":"Rheinland-Pfalz",
    "wof:name":"Volksbank Kaiserslautern Eg",
    "wof:placetype":"venue"
},
  "geometry": {"coordinates":[7.773693,49.445145],"type":"Point"}
}