{
  "type": "Feature",
  "properties": {
    "iso:country":"DE",
    "sg:address":"Marktstr. 7",
    "sg:city":"Neuwied",
    "sg:phone":"+49 2631/23062",
    "sg:postcode":"56564",
    "sg:province":"Rheinland-Pfalz",
    "wof:name":"Hans-hermann Walter",
    "wof:placetype":"venue"
},
  "geometry": {"coordinates":[7.45682621,50.4268684387],"type":"Point"}
}