{
  "type": "Feature",
  "properties": {
    "iso:country":"DE",
    "sg:address":"Tannenwaldstr. 30a",
    "sg:city":"Wassenberg",
    "sg:postcode":"41849",
    "sg:province":"Nordrhein-Westfalen",
    "wof:name":"Elmo-massivhaus Bautr\u00e4ger Gmbh",
    "wof:placetype":"venue"
},
  "geometry": {"coordinates":[6.164232,51.104572],"type":"Point"}
}