{
  "type": "Feature",
  "properties": {
    "iso:country":"DE",
    "sg:address":"Podbielskistr. 164",
    "sg:city":"Hannover",
    "sg:phone":"+49 511/696350",
    "sg:postcode":"30177",
    "sg:province":"Niedersachsen",
    "wof:name":"Thomas Beil Rechtsanwalt",
    "wof:placetype":"venue"
},
  "geometry": {"coordinates":[9.7737073898,52.3979225159],"type":"Point"}
}