{
  "type": "Feature",
  "properties": {
    "iso:country":"DE",
    "sg:address":"Max-Planck-Str. 19",
    "sg:city":"Dreieich",
    "sg:phone":"+49 6103/58495",
    "sg:postcode":"63303",
    "sg:province":"Hessen",
    "wof:name":"Cotex Textil Import-export Gmbh",
    "wof:placetype":"venue"
},
  "geometry": {"coordinates":[8.7070865631,50.0267753601],"type":"Point"}
}