{
  "type": "Feature",
  "properties": {
    "iso:country":"DE",
    "sg:address":"Haferlandstrasse 16",
    "sg:city":"Muenster",
    "sg:phone":"+49 251/6744453",
    "sg:postcode":"48155",
    "sg:province":"Nordrhein-Westfalen",
    "wof:name":"Eassun Germany",
    "wof:placetype":"venue"
},
  "geometry": {"coordinates":[7.658764,51.937469],"type":"Point"}
}