{
  "type": "Feature",
  "properties": {
    "iso:country":"DE",
    "sg:address":"Schafhausener Str. 104",
    "sg:city":"Heinsberg",
    "sg:phone":"+49 2452/62227",
    "sg:postcode":"52525",
    "sg:province":"Nordrhein-Westfalen",
    "wof:name":"H. Hilgers",
    "wof:placetype":"venue"
},
  "geometry": {"coordinates":[6.120611,51.054932],"type":"Point"}
}