{
  "type": "Feature",
  "properties": {
    "iso:country":"DE",
    "sg:address":"S\u00fcdring 60",
    "sg:city":"Parchim",
    "sg:phone":"+49 3871/265248",
    "sg:postcode":"19370",
    "sg:province":"Mecklenburg-Vorpommern",
    "wof:name":"Annette Wandschneider",
    "wof:placetype":"venue"
},
  "geometry": {"coordinates":[11.841153,53.416302],"type":"Point"}
}