{
  "type": "Feature",
  "properties": {
    "iso:country":"DE",
    "sg:address":"Zum Hansa Center 1",
    "sg:city":"Holdorf",
    "sg:phone":"+49 5494/8899",
    "sg:postcode":"49451",
    "sg:province":"Niedersachsen",
    "wof:name":"Mcdonalds Restaurant",
    "wof:placetype":"venue"
},
  "geometry": {"coordinates":[8.115477562,52.5972709656],"type":"Point"}
}