{
  "type": "Feature",
  "properties": {
    "iso:country":"DE",
    "sg:address":"Bahnhofsplatz 6",
    "sg:city":"L\u00f6rrach",
    "sg:phone":"+49 7621/2435",
    "sg:postcode":"79539",
    "sg:province":"Baden-W\u00fcrttemberg",
    "wof:name":"Benneton",
    "wof:placetype":"venue"
},
  "geometry": {"coordinates":[7.664440155,47.6137275696],"type":"Point"}
}