{
  "type": "Feature",
  "properties": {
    "iso:country":"DE",
    "sg:address":"Paulinenweg 4",
    "sg:city":"Hofheim",
    "sg:phone":"+49 6192/8595",
    "sg:postcode":"65719",
    "sg:province":"Hessen",
    "wof:name":"Heinrich Capelle",
    "wof:placetype":"venue"
},
  "geometry": {"coordinates":[8.400435,50.100567],"type":"Point"}
}