{
  "type": "Feature",
  "properties": {
    "iso:country":"DE",
    "sg:address":"M\u00fchlenstr. 120",
    "sg:city":"Greven",
    "sg:phone":"+49 2571/6838",
    "sg:postcode":"48268",
    "sg:province":"Nordrhein-Westfalen",
    "wof:name":"Wilhelm Stegemann Wanningmann",
    "wof:placetype":"venue"
},
  "geometry": {"coordinates":[7.601344,52.079788],"type":"Point"}
}