{
  "type": "Feature",
  "properties": {
    "iso:country":"DE",
    "sg:address":"Wilskistr. 2",
    "sg:city":"Berlin",
    "sg:phone":"+49 30/8135996",
    "sg:postcode":"14169",
    "sg:province":"Berlin",
    "wof:name":"Regina Liedtke Heilpraktikerin",
    "wof:placetype":"venue"
},
  "geometry": {"coordinates":[13.2616958618,52.4502067566],"type":"Point"}
}