{
  "type": "Feature",
  "properties": {
    "iso:country":"DE",
    "sg:address":"Steinstr. 38",
    "sg:city":"Wehingen",
    "sg:phone":"+49 7426/1223",
    "sg:postcode":"78564",
    "sg:province":"Baden-W\u00fcrttemberg",
    "wof:name":"Fischinger Verwaltungs Gmbh",
    "wof:placetype":"venue"
},
  "geometry": {"coordinates":[8.797785,48.142567],"type":"Point"}
}