{
  "type": "Feature",
  "properties": {
    "iso:country":"DE",
    "sg:address":"Nordstr 4",
    "sg:city":"Haan",
    "sg:phone":"+49 212/9344603",
    "sg:postcode":"42781",
    "sg:province":"Nordrhein-Westfalen",
    "wof:name":"G\u00f6rtler",
    "wof:placetype":"venue"
},
  "geometry": {"coordinates":[7.0094909668,51.1969985962],"type":"Point"}
}