{
  "type": "Feature",
  "properties": {
    "iso:country":"DE",
    "sg:address":"Achtern H\u00f6ben 4",
    "sg:city":"Syke",
    "sg:phone":"+49 4242/60784",
    "sg:postcode":"28857",
    "sg:province":"Niedersachsen",
    "wof:name":"G\u00fcnther Gl\u00fcsenkamp Ingenieur",
    "wof:placetype":"venue"
},
  "geometry": {"coordinates":[8.8175392151,52.9164237976],"type":"Point"}
}