{
  "type": "Feature",
  "properties": {
    "iso:country":"DE",
    "sg:address":"Hauptstr. 108",
    "sg:city":"M\u00f6mlingen",
    "sg:phone":"+49 6022/3208",
    "sg:postcode":"63853",
    "sg:province":"Bayern",
    "wof:name":"Adler",
    "wof:placetype":"venue"
},
  "geometry": {"coordinates":[9.081911087,49.8602676392],"type":"Point"}
}