{
  "type": "Feature",
  "properties": {
    "iso:country":"DE",
    "sg:address":"Erlenkamp 11",
    "sg:city":"L\u00fcbeck",
    "sg:phone":"+49 451/394727",
    "sg:postcode":"23568",
    "sg:province":"Schleswig-Holstein",
    "wof:name":"Wolfgang Achenbach",
    "wof:placetype":"venue"
},
  "geometry": {"coordinates":[10.7398347855,53.901889801],"type":"Point"}
}