{
  "type": "Feature",
  "properties": {
    "iso:country":"DE",
    "sg:address":"Walter-Flex-Str. 88",
    "sg:city":"R\u00fcsselsheim",
    "sg:phone":"+49 6142/51841",
    "sg:postcode":"65428",
    "sg:province":"Hessen",
    "wof:name":"M. Und W. Althaus",
    "wof:placetype":"venue"
},
  "geometry": {"coordinates":[8.4300861359,49.9951896667],"type":"Point"}
}