{
  "type": "Feature",
  "properties": {
    "iso:country":"DE",
    "sg:address":"Mehrener Str. 31 a",
    "sg:city":"Daun",
    "sg:phone":"+49 6592/95100",
    "sg:postcode":"54550",
    "sg:province":"Rheinland-Pfalz",
    "wof:name":"Top-markt Gesellschaft F\u00fcr Baum\u00e4rkte Mbh",
    "wof:placetype":"venue"
},
  "geometry": {"coordinates":[6.8389678001,50.1946678162],"type":"Point"}
}