{
  "type": "Feature",
  "properties": {
    "iso:country":"DE",
    "sg:address":"Hauptstr. 22",
    "sg:city":"Rosendahl",
    "sg:phone":"+49 2547/291",
    "sg:postcode":"48720",
    "sg:province":"Nordrhein-Westfalen",
    "wof:name":"Ingrid Roters Gmbh",
    "wof:placetype":"venue"
},
  "geometry": {"coordinates":[7.210124,52.017113],"type":"Point"}
}