{
  "type": "Feature",
  "properties": {
    "iso:country":"DE",
    "sg:address":"Auengrund 1",
    "sg:city":"Mittweida",
    "sg:phone":"+49 3727/91647",
    "sg:postcode":"09648",
    "sg:province":"Sachsen",
    "wof:name":"Gastst\u00fcbl Alte Fuchsfarm",
    "wof:placetype":"venue"
},
  "geometry": {"coordinates":[12.9781303406,50.9995422363],"type":"Point"}
}