{
  "type": "Feature",
  "properties": {
    "iso:country":"DE",
    "sg:address":"Metzinger Str. 20",
    "sg:city":"Dettingen",
    "sg:phone":"+49 7123/71286",
    "sg:postcode":"72581",
    "sg:province":"Baden-W\u00fcrttemberg",
    "wof:name":"Fremdenzimmer L\u00f6wen",
    "wof:placetype":"venue"
},
  "geometry": {"coordinates":[9.3450717926,48.5294685364],"type":"Point"}
}