{
  "type": "Feature",
  "properties": {
    "iso:country":"DE",
    "sg:address":"Rosa-Luxemburg-Str. 59",
    "sg:city":"Greiz",
    "sg:phone":"+49 3661/2602",
    "sg:postcode":"07973",
    "sg:province":"Th\u00fcringen",
    "wof:name":"Richard Lorenz",
    "wof:placetype":"venue"
},
  "geometry": {"coordinates":[12.1979875565,50.6478462219],"type":"Point"}
}