{
  "type": "Feature",
  "properties": {
    "iso:country":"DE",
    "sg:address":"Leipziger Str. 10",
    "sg:city":"M\u00fchlau",
    "sg:phone":"+49 3722/96894",
    "sg:postcode":"09241",
    "sg:province":"Sachsen",
    "wof:name":"Christian Schaile",
    "wof:placetype":"venue"
},
  "geometry": {"coordinates":[12.7583751678,50.9017410278],"type":"Point"}
}