{
  "type": "Feature",
  "properties": {
    "iso:country":"DE",
    "sg:address":"Jahnring 17",
    "sg:city":"Magdeburg",
    "sg:phone":"+49 391/5436826",
    "sg:postcode":"39104",
    "sg:province":"Sachsen-Anhalt",
    "wof:name":"Richter Rupertus & Co. B\u00fcro F\u00fcr Baumanagement Gmbh",
    "wof:placetype":"venue"
},
  "geometry": {"coordinates":[11.629334,52.112339],"type":"Point"}
}