{
  "type": "Feature",
  "properties": {
    "iso:country":"DE",
    "sg:address":"Gr\u00fcner Markt 31",
    "sg:city":"Bamberg",
    "sg:phone":"+49 951/1337033",
    "sg:postcode":"96047",
    "sg:province":"Bayern",
    "wof:name":"Udo Ostermann Rechtsanwalt",
    "wof:placetype":"venue"
},
  "geometry": {"coordinates":[10.8894109726,49.8940582275],"type":"Point"}
}