{
  "type": "Feature",
  "properties": {
    "iso:country":"DE",
    "sg:address":"Rathausstr. 16",
    "sg:city":"Neustadt",
    "sg:phone":"+49 6321/84023",
    "sg:postcode":"67433",
    "sg:province":"Rheinland-Pfalz",
    "wof:name":"F. Ludwig",
    "wof:placetype":"venue"
},
  "geometry": {"coordinates":[8.134531,49.354225],"type":"Point"}
}