{
  "type": "Feature",
  "properties": {
    "iso:country":"DE",
    "sg:address":"Hattinger Str. 799",
    "sg:city":"Bochum",
    "sg:phone":"+49 234/941920",
    "sg:postcode":"44879",
    "sg:province":"Nordrhein-Westfalen",
    "wof:name":"Reiseb\u00fcro Linden",
    "wof:placetype":"venue"
},
  "geometry": {"coordinates":[7.1641387939,51.4280471802],"type":"Point"}
}