{
  "type": "Feature",
  "properties": {
    "iso:country":"DE",
    "sg:address":"Georgstr. 9",
    "sg:city":"Halle",
    "sg:phone":"+49 345/3881915",
    "sg:postcode":"06108",
    "sg:province":"Sachsen-Anhalt",
    "wof:name":"W. H\u00fcndorf",
    "wof:placetype":"venue"
},
  "geometry": {"coordinates":[11.9685745239,51.4909057617],"type":"Point"}
}