{
  "type": "Feature",
  "properties": {
    "iso:country":"DE",
    "sg:address":"Dorfstr. 34",
    "sg:city":"M\u00f6nkhagen",
    "sg:phone":"+49 4506/380",
    "sg:postcode":"23619",
    "sg:province":"Schleswig-Holstein",
    "wof:name":"Otto Fraede Architekt",
    "wof:placetype":"venue"
},
  "geometry": {"coordinates":[10.558977,53.900387],"type":"Point"}
}