{
  "type": "Feature",
  "properties": {
    "iso:country":"DE",
    "sg:address":"Waldstr. 116",
    "sg:city":"Offenbach",
    "sg:phone":"+49 69/858188",
    "sg:postcode":"63071",
    "sg:province":"Hessen",
    "wof:name":"Angela Klink Krankengymnastin",
    "wof:placetype":"venue"
},
  "geometry": {"coordinates":[8.767949,50.095928],"type":"Point"}
}