{
  "type": "Feature",
  "properties": {
    "iso:country":"DE",
    "sg:address":"Rilkestr. 5",
    "sg:city":"Augsburg",
    "sg:phone":"+49 821/571088",
    "sg:postcode":"86199",
    "sg:province":"Bayern",
    "wof:name":"Arwe Gmbh",
    "wof:placetype":"venue"
},
  "geometry": {"coordinates":[10.879215,48.34745],"type":"Point"}
}