{
  "type": "Feature",
  "properties": {
    "iso:country":"DE",
    "sg:address":"Am Oxer 25",
    "sg:city":"Harrislee",
    "sg:postcode":"24955",
    "sg:province":"Schleswig-Holstein",
    "wof:name":"Tmx Autocamper Gmbh",
    "wof:placetype":"venue"
},
  "geometry": {"coordinates":[9.3696260452,54.7989311218],"type":"Point"}
}