{
  "type": "Feature",
  "properties": {
    "iso:country":"DE",
    "sg:address":"Bernd-Rosemeyer-Str 11",
    "sg:city":"Laatzen",
    "sg:phone":"+49 5102/91980",
    "sg:postcode":"30880",
    "sg:province":"Niedersachsen",
    "wof:name":"Case Institut Gmbh",
    "wof:placetype":"venue"
},
  "geometry": {"coordinates":[9.8209180832,52.2921447754],"type":"Point"}
}