{
  "type": "Feature",
  "properties": {
    "iso:country":"DE",
    "sg:address":"Wundtstra\u00dfe 14a",
    "sg:city":"Heidelberg",
    "sg:phone":"+49 6221/834899",
    "sg:postcode":"69123",
    "sg:province":"Baden-W\u00fcrttemberg",
    "wof:name":"Isconlab - Labor F\u00fcr Umweltanalytik: Nitrosamine",
    "wof:placetype":"venue"
},
  "geometry": {"coordinates":[8.650809,49.424],"type":"Point"}
}