{
  "type": "Feature",
  "properties": {
    "iso:country":"DE",
    "sg:address":"Hauptstr. 50 a",
    "sg:city":"Lebendorf",
    "sg:phone":"+49 34691/28440",
    "sg:postcode":"06420",
    "sg:province":"Sachsen-Anhalt",
    "wof:name":"Bestehorns Markt",
    "wof:placetype":"venue"
},
  "geometry": {"coordinates":[11.786485,51.716824],"type":"Point"}
}