{
  "type": "Feature",
  "properties": {
    "iso:country":"DE",
    "sg:address":"R\u00f6merstr. 4",
    "sg:city":"Kissing",
    "sg:postcode":"86438",
    "sg:province":"Bayern",
    "wof:name":"Verlag Recht Und Praxis",
    "wof:placetype":"venue"
},
  "geometry": {"coordinates":[10.964379,48.293995],"type":"Point"}
}