{
  "type": "Feature",
  "properties": {
    "iso:country":"DE",
    "sg:address":"Blasiusstr. 47",
    "sg:city":"D\u00fcsseldorf",
    "sg:phone":"+49 211/9179936",
    "sg:postcode":"40221",
    "sg:province":"Nordrhein-Westfalen",
    "wof:name":"G. K\u00fcpper",
    "wof:placetype":"venue"
},
  "geometry": {"coordinates":[6.7359662056,51.2073173523],"type":"Point"}
}