{
  "type": "Feature",
  "properties": {
    "iso:country":"DE",
    "sg:address":"Marie-Elisabeth-L\u00fcders-Str. 7",
    "sg:city":"Berlin",
    "sg:phone":"+49 30/3414292",
    "sg:postcode":"10625",
    "sg:province":"Berlin",
    "wof:name":"Arthur Bayer Kg",
    "wof:placetype":"venue"
},
  "geometry": {"coordinates":[13.3169231415,52.513671875],"type":"Point"}
}