{
  "type": "Feature",
  "properties": {
    "iso:country":"DE",
    "sg:address":"Nikolaus-Otto-Str. 3 a",
    "sg:city":"Grevenbroich",
    "sg:phone":"+49 2181/61933",
    "sg:postcode":"41515",
    "sg:province":"Nordrhein-Westfalen",
    "wof:name":"Br\u00fcgger Metallbau Gmbh",
    "wof:placetype":"venue"
},
  "geometry": {"coordinates":[6.617605,51.083759],"type":"Point"}
}