{
  "type": "Feature",
  "properties": {
    "iso:country":"DE",
    "sg:address":"Zenettistr. 47",
    "sg:city":"M\u00fcnchen",
    "sg:phone":"+49 89/7473450",
    "sg:postcode":"80337",
    "sg:province":"Bayern",
    "wof:name":"Kirschner Und Mersi Architekten",
    "wof:placetype":"venue"
},
  "geometry": {"coordinates":[11.553006,48.126293],"type":"Point"}
}