{
  "type": "Feature",
  "properties": {
    "iso:country":"DE",
    "sg:address":"Dellborner Str. 17",
    "sg:city":"Losheim",
    "sg:postcode":"66679",
    "sg:province":"Saarland",
    "wof:name":"Jost Gmbh",
    "wof:placetype":"venue"
},
  "geometry": {"coordinates":[6.7838802338,49.4893989563],"type":"Point"}
}