{
  "type": "Feature",
  "properties": {
    "iso:country":"DE",
    "sg:address":"Dresdener Str. 84",
    "sg:city":"Bernsdorf",
    "sg:phone":"+49 35723/21125",
    "sg:postcode":"02994",
    "sg:province":"Sachsen",
    "wof:name":"J. Reppe",
    "wof:placetype":"venue"
},
  "geometry": {"coordinates":[14.0491819382,51.3627815247],"type":"Point"}
}