{
  "type": "Feature",
  "properties": {
    "iso:country":"DE",
    "sg:address":"Lange Str. 39",
    "sg:city":"Zschopau",
    "sg:phone":"+49 3725/22067",
    "sg:postcode":"09405",
    "sg:province":"Sachsen",
    "wof:name":"Elektro-anlagenbau Zschopau Gmbh",
    "wof:placetype":"venue"
},
  "geometry": {"coordinates":[13.0694169998,50.7486991882],"type":"Point"}
}