{
  "type": "Feature",
  "properties": {
    "iso:country":"DE",
    "sg:address":"Arnold-Sommerfeld-Ring 18",
    "sg:city":"Baesweiler",
    "sg:phone":"+49 2401/91560",
    "sg:postcode":"52499",
    "sg:province":"Nordrhein-Westfalen",
    "wof:name":"Smw Schaltschrankbau Montage Wartung Gmbh",
    "wof:placetype":"venue"
},
  "geometry": {"coordinates":[6.1717200279,50.9174194336],"type":"Point"}
}