{
  "type": "Feature",
  "properties": {
    "iso:country":"DE",
    "sg:address":"Kirchstr. 25",
    "sg:city":"Ilshofen",
    "sg:phone":"+49 7904/8719",
    "sg:postcode":"74532",
    "sg:province":"Baden-W\u00fcrttemberg",
    "wof:name":"Alfons Schmitt",
    "wof:placetype":"venue"
},
  "geometry": {"coordinates":[9.94662,49.173695],"type":"Point"}
}