{
  "type": "Feature",
  "properties": {
    "iso:country":"DE",
    "sg:address":"Nerobergstr. 13",
    "sg:city":"Wiesbaden",
    "sg:phone":"+49 611/523001",
    "sg:postcode":"65193",
    "sg:province":"Hessen",
    "wof:name":"Prof. Lothar G. Voigtmann Rechtsanwalt Und Notar",
    "wof:placetype":"venue"
},
  "geometry": {"coordinates":[8.234954834,50.0951042175],"type":"Point"}
}