{
  "type": "Feature",
  "properties": {
    "iso:country":"DE",
    "sg:address":"Kieferstr. 30",
    "sg:city":"Dortmund",
    "sg:phone":"+49 231/717070",
    "sg:postcode":"44225",
    "sg:province":"Nordrhein-Westfalen",
    "wof:name":"Albert Fl\u00f6ssner Inh. B. Fl\u00f6ssner",
    "wof:placetype":"venue"
},
  "geometry": {"coordinates":[7.43272,51.471218],"type":"Point"}
}