{
  "type": "Feature",
  "properties": {
    "iso:country":"DE",
    "sg:address":"Strandweg 8",
    "sg:city":"M\u00f6nkeberg",
    "sg:postcode":"24248",
    "sg:province":"Schleswig-Holstein",
    "wof:name":"Dynastie Gmbh",
    "wof:placetype":"venue"
},
  "geometry": {"coordinates":[10.1783742905,54.3527984619],"type":"Point"}
}