{
  "type": "Feature",
  "properties": {
    "iso:country":"DE",
    "sg:address":"Stockacher Str. 162 /3",
    "sg:city":"Tuttlingen",
    "sg:phone":"+49 7461/3651",
    "sg:postcode":"78532",
    "sg:province":"Baden-W\u00fcrttemberg",
    "wof:name":"Agip Deutschland Ag",
    "wof:placetype":"venue"
},
  "geometry": {"coordinates":[8.8295917511,47.9739227295],"type":"Point"}
}