{
  "type": "Feature",
  "properties": {
    "iso:country":"DE",
    "sg:address":"Mosbacher Str. 55",
    "sg:city":"Wiesbaden",
    "sg:postcode":"65187",
    "sg:province":"Hessen",
    "wof:name":"Historische Kommission F\u00fcr Nassau",
    "wof:placetype":"venue"
},
  "geometry": {"coordinates":[8.2398805618,50.063331604],"type":"Point"}
}