{
  "type": "Feature",
  "properties": {
    "iso:country":"DE",
    "sg:address":"Hamburger Allee 36",
    "sg:city":"Hannover",
    "sg:phone":"+49 511/318791",
    "sg:postcode":"30161",
    "sg:province":"Niedersachsen",
    "wof:name":"Circulo Familar Espanol Hannover E. V.",
    "wof:placetype":"venue"
},
  "geometry": {"coordinates":[9.7385320663,52.3819923401],"type":"Point"}
}