{
  "type": "Feature",
  "properties": {
    "iso:country":"DE",
    "sg:address":"Zossener Str. 18",
    "sg:city":"Glienick",
    "sg:phone":"+49 3377/302264",
    "sg:postcode":"15806",
    "sg:province":"Brandenburg",
    "wof:name":"Saste Handels- Und Transport- Gesellschaft Mbh",
    "wof:placetype":"venue"
},
  "geometry": {"coordinates":[13.38373,52.246033],"type":"Point"}
}