{
  "type": "Feature",
  "properties": {
    "iso:country":"DE",
    "sg:address":"Industriestr. 4",
    "sg:city":"Ringe",
    "sg:phone":"+49 5944/990220",
    "sg:postcode":"49824",
    "sg:province":"Niedersachsen",
    "wof:name":"Franz Rohe Transporte E. K.",
    "wof:placetype":"venue"
},
  "geometry": {"coordinates":[6.9543800354,52.6101989746],"type":"Point"}
}