{
  "type": "Feature",
  "properties": {
    "iso:country":"DE",
    "sg:address":"Hauptstr. 12",
    "sg:city":"Birkenfeld",
    "sg:phone":"+49 6782/5823",
    "sg:postcode":"55765",
    "sg:province":"Rheinland-Pfalz",
    "wof:name":"W. Kreis",
    "wof:placetype":"venue"
},
  "geometry": {"coordinates":[7.1688,49.647404],"type":"Point"}
}