{
  "type": "Feature",
  "properties": {
    "iso:country":"DE",
    "sg:address":"Kronprinzenstra\u00dfe 3",
    "sg:city":"L\u00fcdenscheid",
    "sg:postcode":"58511",
    "sg:province":"Nordrhein-Westfalen",
    "wof:name":"Mach Was Aktive Freizeitgestaltung E.v.",
    "wof:placetype":"venue"
},
  "geometry": {"coordinates":[7.6406822205,51.2180862427],"type":"Point"}
}