{
  "type": "Feature",
  "properties": {
    "iso:country":"DE",
    "sg:address":"Rainer Str. 35",
    "sg:city":"Donauw\u00f6rth",
    "sg:phone":"+49 906/241378",
    "sg:postcode":"86609",
    "sg:province":"Bayern",
    "wof:name":"J. Rebele",
    "wof:placetype":"venue"
},
  "geometry": {"coordinates":[10.795753,48.702766],"type":"Point"}
}