{
  "type": "Feature",
  "properties": {
    "iso:country":"DE",
    "sg:address":"Weidenstr. 12",
    "sg:city":"Pinneberg",
    "sg:phone":"+49 4101/200460",
    "sg:postcode":"25421",
    "sg:province":"Schleswig-Holstein",
    "wof:name":"Hergen & K\u00f6ppl Ohg",
    "wof:placetype":"venue"
},
  "geometry": {"coordinates":[9.810051918,53.6577415466],"type":"Point"}
}