{
  "type": "Feature",
  "properties": {
    "iso:country":"DE",
    "sg:address":"Gebbertstr. 52 a",
    "sg:city":"Erlangen",
    "sg:phone":"+49 9131/206300",
    "sg:postcode":"91052",
    "sg:province":"Bayern",
    "wof:name":"Casa Tecta Bautr\u00e4ger Gmbh",
    "wof:placetype":"venue"
},
  "geometry": {"coordinates":[11.017145,49.591881],"type":"Point"}
}