{
  "type": "Feature",
  "properties": {
    "iso:country":"DE",
    "sg:address":"Leipziger Str. 2",
    "sg:city":"Gr\u00fcnberg",
    "sg:phone":"+49 6401/7180",
    "sg:postcode":"35305",
    "sg:province":"Hessen",
    "wof:name":"Inge Schmiedel",
    "wof:placetype":"venue"
},
  "geometry": {"coordinates":[8.974723,50.593651],"type":"Point"}
}