{
  "type": "Feature",
  "properties": {
    "iso:country":"DE",
    "sg:address":"Hauptstr. 27",
    "sg:city":"Wernberg-K\u00f6blitz",
    "sg:postcode":"92533",
    "sg:province":"Bayern",
    "wof:name":"Elektrotechnik Unger Gmbh",
    "wof:placetype":"venue"
},
  "geometry": {"coordinates":[12.1518783569,49.5483665466],"type":"Point"}
}