{
  "type": "Feature",
  "properties": {
    "iso:country":"DE",
    "sg:address":"Neue Str. 22",
    "sg:city":"Bad Urach",
    "sg:phone":"+49 7125/70321",
    "sg:postcode":"72574",
    "sg:province":"Baden-W\u00fcrttemberg",
    "wof:name":"Ernst Burgemeister Gmbh",
    "wof:placetype":"venue"
},
  "geometry": {"coordinates":[9.402242,48.492535],"type":"Point"}
}