{
  "type": "Feature",
  "properties": {
    "iso:country":"DE",
    "sg:address":"T\u00f6pfers Weg 24",
    "sg:city":"Cuxhaven",
    "sg:phone":"+49 4723/3535",
    "sg:postcode":"27474",
    "sg:province":"Niedersachsen",
    "wof:name":"Klaus Gerhardt Architekt",
    "wof:placetype":"venue"
},
  "geometry": {"coordinates":[8.687708,53.846672],"type":"Point"}
}