{
  "type": "Feature",
  "properties": {
    "iso:country":"DE",
    "sg:address":"Herrenh\u00e4user Str. 8",
    "sg:city":"Hannover",
    "sg:postcode":"30419",
    "sg:province":"Niedersachsen",
    "wof:name":"Institut F\u00fcr Ausl\u00e4ndische Fachhochschulbewerber",
    "wof:placetype":"venue"
},
  "geometry": {"coordinates":[9.6959972382,52.392250061],"type":"Point"}
}