{
  "type": "Feature",
  "properties": {
    "iso:country":"DE",
    "sg:address":"Am Wellsee 58",
    "sg:city":"Kiel",
    "sg:phone":"+49 431/783424",
    "sg:postcode":"24146",
    "sg:province":"Schleswig-Holstein",
    "wof:name":"Karl-heinz Timm",
    "wof:placetype":"venue"
},
  "geometry": {"coordinates":[10.1879577637,54.2820320129],"type":"Point"}
}