{
  "type": "Feature",
  "properties": {
    "iso:country":"DE",
    "sg:address":"Steuernagelstr.10",
    "sg:city":"Frankfurt",
    "sg:postcode":"60326",
    "sg:province":"Hessen",
    "wof:name":"Pattaya Live, Thailand Webcameras",
    "wof:placetype":"venue"
},
  "geometry": {"coordinates":[8.626644,50.097492],"type":"Point"}
}