{
  "type": "Feature",
  "properties": {
    "iso:country":"DE",
    "sg:address":"Wilzenberger Str. 4",
    "sg:city":"Wilzenberg-Hu\u00dfweiler",
    "sg:phone":"+49 6787/8139",
    "sg:postcode":"55767",
    "sg:province":"Rheinland-Pfalz",
    "wof:name":"Willi Kemmer",
    "wof:placetype":"venue"
},
  "geometry": {"coordinates":[7.222259,49.70517],"type":"Point"}
}