{
  "type": "Feature",
  "properties": {
    "iso:country":"DE",
    "sg:address":"Hans-Weigel-Str. 10",
    "sg:city":"Leipzig",
    "sg:postcode":"04319",
    "sg:province":"Sachsen",
    "wof:name":"Dietmar Mogk",
    "wof:placetype":"venue"
},
  "geometry": {"coordinates":[12.473941803,51.3386001587],"type":"Point"}
}