{
  "type": "Feature",
  "properties": {
    "iso:country":"DE",
    "sg:address":"Markt 6",
    "sg:city":"Apolda",
    "sg:phone":"+49 3644/555122",
    "sg:postcode":"99510",
    "sg:province":"Th\u00fcringen",
    "wof:name":"Partner Optik Gmbh",
    "wof:placetype":"venue"
},
  "geometry": {"coordinates":[11.512423,51.022533],"type":"Point"}
}