{
  "type": "Feature",
  "properties": {
    "iso:country":"DE",
    "sg:address":"Klein-Zimmerner-Str. 20",
    "sg:city":"Gro\u00df-Zimmern",
    "sg:phone":"+49 6071/4605",
    "sg:postcode":"64846",
    "sg:province":"Hessen",
    "wof:name":"Johannes K\u00f6bel Architekt",
    "wof:placetype":"venue"
},
  "geometry": {"coordinates":[8.837202,49.870579],"type":"Point"}
}