{
  "type": "Feature",
  "properties": {
    "iso:country":"DE",
    "sg:address":"Am Butterh\u00fcgel 4",
    "sg:city":"Bexbach",
    "sg:phone":"+49 6826/4572",
    "sg:postcode":"66450",
    "sg:province":"Saarland",
    "wof:name":"Bauunternehmung Henze Gmbh",
    "wof:placetype":"venue"
},
  "geometry": {"coordinates":[7.28165,49.345284],"type":"Point"}
}