{
  "type": "Feature",
  "properties": {
    "iso:country":"DE",
    "sg:city":"Hannover",
    "sg:postcode":"30451",
    "sg:province":"Niedersachsen",
    "wof:name":"Weiss-dachreinigung",
    "wof:placetype":"venue"
},
  "geometry": {"coordinates":[9.704995,52.374035],"type":"Point"}
}