{
  "type": "Feature",
  "properties": {
    "iso:country":"DE",
    "sg:address":"Am Park 7",
    "sg:city":"Fraureuth",
    "sg:phone":"+49 3761/3481",
    "sg:postcode":"08427",
    "sg:province":"Sachsen",
    "wof:name":"Horst G\u00fcnnel",
    "wof:placetype":"venue"
},
  "geometry": {"coordinates":[12.356584,50.703213],"type":"Point"}
}