{
  "type": "Feature",
  "properties": {
    "iso:country":"DE",
    "sg:address":"Karl-Marx-Str. 9b",
    "sg:city":"L\u00fcttchendorf",
    "sg:phone":"+49 3475/715907",
    "sg:postcode":"06317",
    "sg:province":"Sachsen-Anhalt",
    "wof:name":"Petra Beinert",
    "wof:placetype":"venue"
},
  "geometry": {"coordinates":[11.626229,51.50182],"type":"Point"}
}