{
  "type": "Feature",
  "properties": {
    "iso:country":"DE",
    "sg:address":"H\u00e4gentwiete 5",
    "sg:city":"Alveslohe",
    "sg:postcode":"25486",
    "sg:province":"Schleswig-Holstein",
    "wof:name":"Arkon Metallbau E. K.",
    "wof:placetype":"venue"
},
  "geometry": {"coordinates":[9.8896188736,53.7885284424],"type":"Point"}
}