{
  "type": "Feature",
  "properties": {
    "iso:country":"DE",
    "sg:address":"Flachsmarktstr. 42 a",
    "sg:city":"Blomberg",
    "sg:postcode":"32825",
    "sg:province":"Nordrhein-Westfalen",
    "wof:name":"Pro-inova M\u00f6bel Vertriebsgesellschaft Mbh",
    "wof:placetype":"venue"
},
  "geometry": {"coordinates":[9.1057167053,51.9322776794],"type":"Point"}
}