{
  "type": "Feature",
  "properties": {
    "iso:country":"DE",
    "sg:address":"Unter den Linden 46",
    "sg:city":"Schl\u00fcchtern",
    "sg:phone":"+49 6661/8026",
    "sg:postcode":"36381",
    "sg:province":"Hessen",
    "wof:name":"M\u00f6belfabrik Fr. Rudolf & Sohn Gmbh & Co. Kg",
    "wof:placetype":"venue"
},
  "geometry": {"coordinates":[9.5243053436,50.3457450867],"type":"Point"}
}