{
  "type": "Feature",
  "properties": {
    "iso:country":"DE",
    "sg:address":"Hauptstr. 24",
    "sg:city":"Kodersdorf",
    "sg:phone":"+49 35825/5321",
    "sg:postcode":"02923",
    "sg:province":"Sachsen",
    "wof:name":"J\u00fcrgen Laske",
    "wof:placetype":"venue"
},
  "geometry": {"coordinates":[14.8592596054,51.2265586853],"type":"Point"}
}