{
  "type": "Feature",
  "properties": {
    "iso:country":"DE",
    "sg:address":"Robert-Koch-Str. 22",
    "sg:city":"Heilbad Heiligenstadt",
    "sg:phone":"+49 3606/612570",
    "sg:postcode":"37308",
    "sg:province":"Th\u00fcringen",
    "wof:name":"H.-georg Sander",
    "wof:placetype":"venue"
},
  "geometry": {"coordinates":[10.1376438141,51.3756752014],"type":"Point"}
}