{
  "type": "Feature",
  "properties": {
    "iso:country":"DE",
    "sg:address":"Tumblingerstr. 19",
    "sg:city":"M\u00fcnchen",
    "sg:phone":"+49 89/534618",
    "sg:postcode":"80337",
    "sg:province":"Bayern",
    "wof:name":"Veronika Meisinger",
    "wof:placetype":"venue"
},
  "geometry": {"coordinates":[11.559835,48.12693],"type":"Point"}
}