{
  "type": "Feature",
  "properties": {
    "iso:country":"DE",
    "sg:address":"Industriestr 17",
    "sg:city":"Nauheim",
    "sg:phone":"+49 6152/97580",
    "sg:postcode":"64569",
    "sg:province":"Hessen",
    "wof:name":"W. Schreiber & S\u00f6hne Gmbh",
    "wof:placetype":"venue"
},
  "geometry": {"coordinates":[8.444394,49.949356],"type":"Point"}
}