{
  "type": "Feature",
  "properties": {
    "iso:country":"DE",
    "sg:address":"Industriestr. 2",
    "sg:city":"Neuhaus-Schierschnitz",
    "sg:phone":"+49 36764/72675",
    "sg:postcode":"96524",
    "sg:province":"Th\u00fcringen",
    "wof:name":"Delbrouck Kunststoff- Verarbeitung Gmbh & Co. Kg",
    "wof:placetype":"venue"
},
  "geometry": {"coordinates":[11.250029,50.300838],"type":"Point"}
}