{
  "type": "Feature",
  "properties": {
    "iso:country":"DE",
    "sg:address":"Ahnepaule",
    "sg:city":"Bad Salzdetfurth",
    "sg:postcode":"31162",
    "sg:province":"Niedersachsen",
    "wof:name":"Suk-lammetal",
    "wof:placetype":"venue"
},
  "geometry": {"coordinates":[10.007314,52.047611],"type":"Point"}
}