{
  "type": "Feature",
  "properties": {
    "iso:country":"DE",
    "sg:address":"Breite Str. 4",
    "sg:city":"Sehnde",
    "sg:phone":"+49 5138/1629",
    "sg:postcode":"31319",
    "sg:province":"Niedersachsen",
    "wof:name":"G\u00fcnter G\u00f6rlitz",
    "wof:placetype":"venue"
},
  "geometry": {"coordinates":[9.968384,52.314846],"type":"Point"}
}