{
  "type": "Feature",
  "properties": {
    "iso:country":"DE",
    "sg:address":"Stiepeler Str. 161",
    "sg:city":"Bochum",
    "sg:postcode":"44801",
    "sg:province":"Nordrhein-Westfalen",
    "wof:name":"Terraline Kommunikations- Und Informationst. Gmbh & Co. Kg",
    "wof:placetype":"venue"
},
  "geometry": {"coordinates":[7.244809,51.444366],"type":"Point"}
}