{
  "type": "Feature",
  "properties": {
    "iso:country":"DE",
    "sg:address":"Sch\u00f6ne Aussicht 15",
    "sg:city":"Kronberg",
    "sg:phone":"+49 6173/64680",
    "sg:postcode":"61476",
    "sg:province":"Hessen",
    "wof:name":"Ema Grundst\u00fccksges. Mbh",
    "wof:placetype":"venue"
},
  "geometry": {"coordinates":[8.5439586639,50.1842575073],"type":"Point"}
}