{
  "type": "Feature",
  "properties": {
    "iso:country":"DE",
    "sg:address":"Stielerstr.",
    "sg:city":"Erfurt",
    "sg:postcode":"99099",
    "sg:province":"Th\u00fcringen",
    "wof:name":"Ha-we-ge-center",
    "wof:placetype":"venue"
},
  "geometry": {"coordinates":[11.0702266693,50.9558448792],"type":"Point"}
}