{
  "type": "Feature",
  "properties": {
    "iso:country":"DE",
    "sg:address":"Lutterstr. 15",
    "sg:city":"Bielefeld",
    "sg:phone":"+49 521/1550",
    "sg:postcode":"33617",
    "sg:province":"Nordrhein-Westfalen",
    "wof:name":"Dr. Oetker Tiefk\u00fchlkost Gmbh",
    "wof:placetype":"venue"
},
  "geometry": {"coordinates":[8.520573616,52.01512146],"type":"Point"}
}