{
  "type": "Feature",
  "properties": {
    "iso:country":"DE",
    "sg:address":"Bahnhofstr. 13",
    "sg:city":"B\u00fcrstadt",
    "sg:phone":"+49 6206/6465",
    "sg:postcode":"68642",
    "sg:province":"Hessen",
    "wof:name":"Jost",
    "wof:placetype":"venue"
},
  "geometry": {"coordinates":[8.4955863953,49.6480674744],"type":"Point"}
}