{
  "type": "Feature",
  "properties": {
    "iso:country":"DE",
    "sg:address":"Luttinger Str. 33",
    "sg:city":"Laufenburg",
    "sg:phone":"+49 7763/7762",
    "sg:postcode":"79725",
    "sg:province":"Baden-W\u00fcrttemberg",
    "wof:name":"Josef Eckert",
    "wof:placetype":"venue"
},
  "geometry": {"coordinates":[8.060817,47.565128],"type":"Point"}
}