{
  "type": "Feature",
  "properties": {
    "iso:country":"DE",
    "sg:address":"Hubertusstr. 11",
    "sg:city":"Bonn",
    "sg:phone":"+49 228/251466",
    "sg:postcode":"53125",
    "sg:province":"Nordrhein-Westfalen",
    "wof:name":"Dr. H.-u. Lang Steuerberater",
    "wof:placetype":"venue"
},
  "geometry": {"coordinates":[7.0697369576,50.694152832],"type":"Point"}
}