{
  "type": "Feature",
  "properties": {
    "iso:country":"DE",
    "sg:address":"Am Westhang 51",
    "sg:city":"Iserlohn",
    "sg:postcode":"58640",
    "sg:province":"Nordrhein-Westfalen",
    "wof:name":"Geschenke,lampen,wohnaccessoires",
    "wof:placetype":"venue"
},
  "geometry": {"coordinates":[7.693956852,51.4124984741],"type":"Point"}
}