{
  "type": "Feature",
  "properties": {
    "iso:country":"DE",
    "sg:address":"Nahestr. 3",
    "sg:city":"Boos",
    "sg:phone":"+49 6758/8879",
    "sg:postcode":"55595",
    "sg:province":"Rheinland-Pfalz",
    "wof:name":"Leibrock",
    "wof:placetype":"venue"
},
  "geometry": {"coordinates":[7.719429,49.795616],"type":"Point"}
}