{
  "type": "Feature",
  "properties": {
    "iso:country":"DE",
    "sg:address":"Aufkirchner Str.",
    "sg:city":"Berg",
    "sg:phone":"+49 8151/5469",
    "sg:postcode":"82335",
    "sg:province":"Bayern",
    "wof:name":"Heinz Br\u00fchl Architekt",
    "wof:placetype":"venue"
},
  "geometry": {"coordinates":[11.356255,47.966389],"type":"Point"}
}