{
  "type": "Feature",
  "properties": {
    "iso:country":"DE",
    "sg:address":"Ulzburger Str. 4",
    "sg:city":"Norderstedt",
    "sg:phone":"+49 40/52950774",
    "sg:postcode":"22850",
    "sg:province":"Schleswig-Holstein",
    "wof:name":"Murats D\u00f6ner Treff",
    "wof:placetype":"venue"
},
  "geometry": {"coordinates":[9.9984779358,53.6828804016],"type":"Point"}
}