{
  "type": "Feature",
  "properties": {
    "iso:country":"DE",
    "sg:address":"Bahnhofstr. 8",
    "sg:city":"N\u00f6rvenich",
    "sg:phone":"+49 2426/5701",
    "sg:postcode":"52388",
    "sg:province":"Nordrhein-Westfalen",
    "wof:name":"Reinhard Schiffer E. K.",
    "wof:placetype":"venue"
},
  "geometry": {"coordinates":[6.636054039,50.8097229004],"type":"Point"}
}