{
  "type": "Feature",
  "properties": {
    "iso:country":"DE",
    "sg:address":"K\u00f6nigstr. 76a",
    "sg:city":"Wetter",
    "sg:phone":"+49 2335/2604",
    "sg:postcode":"58300",
    "sg:province":"Nordrhein-Westfalen",
    "wof:name":"Norbert Reifer Heilpraktiker",
    "wof:placetype":"venue"
},
  "geometry": {"coordinates":[7.3900699615,51.3876075745],"type":"Point"}
}