{
  "type": "Feature",
  "properties": {
    "iso:country":"DE",
    "sg:address":"Malteserstr. 5",
    "sg:city":"Obertshausen",
    "sg:postcode":"63179",
    "sg:province":"Hessen",
    "wof:name":"M\u00fcnch Hausen Gmbh",
    "wof:placetype":"venue"
},
  "geometry": {"coordinates":[8.840703,50.06509],"type":"Point"}
}