{
  "type": "Feature",
  "properties": {
    "iso:country":"DE",
    "sg:address":"Auf der Langen Wiese 4",
    "sg:city":"Haunetal",
    "sg:phone":"+49 6673/368",
    "sg:postcode":"36166",
    "sg:province":"Hessen",
    "wof:name":"Ev. Pfarramt Wehrda",
    "wof:placetype":"venue"
},
  "geometry": {"coordinates":[9.6632833481,50.7393684387],"type":"Point"}
}