{
  "type": "Feature",
  "properties": {
    "iso:country":"DE",
    "sg:address":"Am Fuchsberg 6",
    "sg:city":"Ottersberg",
    "sg:phone":"+49 4293/917345",
    "sg:postcode":"28870",
    "sg:province":"Niedersachsen",
    "wof:name":"Twindata Edv-systemservice Andreas Ziegenhirt Kg",
    "wof:placetype":"venue"
},
  "geometry": {"coordinates":[9.0390338898,53.1192855835],"type":"Point"}
}