{
  "type": "Feature",
  "properties": {
    "iso:country":"DE",
    "sg:address":"Bahnhofstr. 11",
    "sg:city":"Deggendorf",
    "sg:phone":"+49 991/7643",
    "sg:postcode":"94469",
    "sg:province":"Bayern",
    "wof:name":"Franz Seidl",
    "wof:placetype":"venue"
},
  "geometry": {"coordinates":[12.960743,48.8335],"type":"Point"}
}