{
  "type": "Feature",
  "properties": {
    "iso:country":"DE",
    "sg:address":"Pipinstr. 20",
    "sg:city":"Paderborn",
    "sg:phone":"+49 5251/207421",
    "sg:postcode":"33098",
    "sg:province":"Nordrhein-Westfalen",
    "wof:name":"Tropenwelt Rolf Kalytta Kg",
    "wof:placetype":"venue"
},
  "geometry": {"coordinates":[8.7481107712,51.7139129639],"type":"Point"}
}