{
  "type": "Feature",
  "properties": {
    "iso:country":"DE",
    "sg:address":"Wolfg-Amad-Mozart-Str 34",
    "sg:city":"Marktheidenfeld",
    "sg:phone":"+49 9391/3969",
    "sg:postcode":"97828",
    "sg:province":"Bayern",
    "wof:name":"Dieter Ruhland Ingenieur",
    "wof:placetype":"venue"
},
  "geometry": {"coordinates":[9.6134128571,49.8412437439],"type":"Point"}
}