{
  "type": "Feature",
  "properties": {
    "iso:country":"DE",
    "sg:address":"Ernst-August-Str. 9",
    "sg:city":"Hilter",
    "sg:phone":"+49 5409/4940",
    "sg:postcode":"49176",
    "sg:province":"Niedersachsen",
    "wof:name":"K. Hornig",
    "wof:placetype":"venue"
},
  "geometry": {"coordinates":[8.143978,52.181831],"type":"Point"}
}