{
  "type": "Feature",
  "properties": {
    "iso:country":"DE",
    "sg:address":"Postfach 380:: 32123 Enger:: Germany.^^Burgstr 2::",
    "sg:city":"Enger",
    "sg:phone":"+49 5224/6920",
    "sg:postcode":"32130",
    "sg:province":"Nordrhein-Westfalen",
    "wof:name":"Volksbank Enger-spenge Eg",
    "wof:placetype":"venue"
},
  "geometry": {"coordinates":[8.555879,52.137482],"type":"Point"}
}