{
  "type": "Feature",
  "properties": {
    "iso:country":"DE",
    "sg:address":"Platenstr 46",
    "sg:city":"N\u00fcrnberg",
    "sg:phone":"+49 911/652626",
    "sg:postcode":"90441",
    "sg:province":"Bayern",
    "wof:name":"Wnetpartner Ag",
    "wof:placetype":"venue"
},
  "geometry": {"coordinates":[11.0683546066,49.4259033203],"type":"Point"}
}