{
  "type": "Feature",
  "properties": {
    "iso:country":"DE",
    "sg:address":"Spatzenlohweg 16",
    "sg:city":"Sauerlach",
    "sg:phone":"+49 8104/1545",
    "sg:postcode":"82054",
    "sg:province":"Bayern",
    "wof:name":"Michael Gr\u00e4tz Grundbesitzverwaltungs Gmbh",
    "wof:placetype":"venue"
},
  "geometry": {"coordinates":[11.635449,47.970554],"type":"Point"}
}