{
  "type": "Feature",
  "properties": {
    "iso:country":"DE",
    "sg:address":"Am Langberg 91 f",
    "sg:city":"Hamburg",
    "sg:postcode":"21033",
    "sg:province":"Hamburg",
    "wof:name":"Ipc Industry & Private Consulting Verwaltungs-",
    "wof:placetype":"venue"
},
  "geometry": {"coordinates":[10.1400203705,53.5026397705],"type":"Point"}
}