{
  "type": "Feature",
  "properties": {
    "iso:country":"DE",
    "sg:address":"Feld-Forstmann-Str. 9",
    "sg:city":"Bendorf",
    "sg:postcode":"56170",
    "sg:province":"Rheinland-Pfalz",
    "wof:name":"Cerom Keramik Gmbh",
    "wof:placetype":"venue"
},
  "geometry": {"coordinates":[7.5676870346,50.4274787903],"type":"Point"}
}