{
  "type": "Feature",
  "properties": {
    "iso:country":"DE",
    "sg:address":"K\u00f6nigstr. 67",
    "sg:city":"Wetter",
    "sg:phone":"+49 2335/1555",
    "sg:postcode":"58300",
    "sg:province":"Nordrhein-Westfalen",
    "wof:name":"Provinzial Versicherung Der Sparkassen",
    "wof:placetype":"venue"
},
  "geometry": {"coordinates":[7.3901958466,51.387348175],"type":"Point"}
}