{
  "type": "Feature",
  "properties": {
    "iso:country":"DE",
    "sg:address":"Iggelheimer Str. 30",
    "sg:city":"Dudenhofen",
    "sg:phone":"+49 6232/94783",
    "sg:postcode":"67373",
    "sg:province":"Rheinland-Pfalz",
    "wof:name":"S. Und W. Wingerter Gmbh",
    "wof:placetype":"venue"
},
  "geometry": {"coordinates":[8.3881502151,49.3199653625],"type":"Point"}
}