{
  "type": "Feature",
  "properties": {
    "iso:country":"DE",
    "sg:address":"Goethestr. 23",
    "sg:city":"Falkenstein",
    "sg:phone":"+49 3745/77446",
    "sg:postcode":"08223",
    "sg:province":"Sachsen",
    "wof:name":"O. Meisel",
    "wof:placetype":"venue"
},
  "geometry": {"coordinates":[12.3749647141,50.4787025452],"type":"Point"}
}