{
  "type": "Feature",
  "properties": {
    "iso:country":"DE",
    "sg:address":"Bahnhofstr. 27",
    "sg:city":"Lauffen",
    "sg:phone":"+49 7133/16345",
    "sg:postcode":"74348",
    "sg:province":"Baden-W\u00fcrttemberg",
    "wof:name":"I. De Virgilio",
    "wof:placetype":"venue"
},
  "geometry": {"coordinates":[9.148904,49.075695],"type":"Point"}
}