{
  "type": "Feature",
  "properties": {
    "iso:country":"DE",
    "sg:address":"Albert-Einstein-Str. 65",
    "sg:city":"Aachen",
    "sg:phone":"+49 2408/989016",
    "sg:postcode":"52076",
    "sg:province":"Nordrhein-Westfalen",
    "wof:name":"Georg Tournay",
    "wof:placetype":"venue"
},
  "geometry": {"coordinates":[6.176403,50.70903],"type":"Point"}
}