{
  "type": "Feature",
  "properties": {
    "iso:country":"DE",
    "sg:address":"G\u00fcterstr. 22",
    "sg:city":"Maxh\u00fctte-Haidhof",
    "sg:postcode":"93142",
    "sg:province":"Bayern",
    "wof:name":"Halbritter Gmbh",
    "wof:placetype":"venue"
},
  "geometry": {"coordinates":[12.1062726974,49.2022819519],"type":"Point"}
}