{
  "type": "Feature",
  "properties": {
    "iso:country":"DE",
    "sg:address":"Marienstr. 42",
    "sg:city":"Schmelz",
    "sg:phone":"+49 6887/92071",
    "sg:postcode":"66839",
    "sg:province":"Saarland",
    "wof:name":"Klaus M\u00fcller",
    "wof:placetype":"venue"
},
  "geometry": {"coordinates":[6.8483462334,49.4461975098],"type":"Point"}
}