{
  "type": "Feature",
  "properties": {
    "iso:country":"DE",
    "sg:address":"Berliner Str 43",
    "sg:city":"A\u00dflar",
    "sg:phone":"+49 6441/8020",
    "sg:postcode":"35614",
    "sg:province":"Hessen",
    "wof:name":"Pfeiffer Vacuum Gmbh",
    "wof:placetype":"venue"
},
  "geometry": {"coordinates":[8.464112,50.589664],"type":"Point"}
}