{
  "type": "Feature",
  "properties": {
    "iso:country":"DE",
    "sg:address":"Herzog-Heinrich-Str. 33",
    "sg:city":"M\u00fcnchen",
    "sg:postcode":"80336",
    "sg:province":"Bayern",
    "wof:name":"One X Two Franchise Gmbh",
    "wof:placetype":"venue"
},
  "geometry": {"coordinates":[11.5559597015,48.1292266846],"type":"Point"}
}