{
  "type": "Feature",
  "properties": {
    "iso:country":"DE",
    "sg:address":"Dagobertstr. 36",
    "sg:city":"K\u00f6ln",
    "sg:phone":"+49 221/123566",
    "sg:postcode":"50668",
    "sg:province":"Nordrhein-Westfalen",
    "wof:name":"Heinz Micheel Architekt",
    "wof:placetype":"venue"
},
  "geometry": {"coordinates":[6.960235,50.9482],"type":"Point"}
}