{
  "type": "Feature",
  "properties": {
    "iso:country":"DE",
    "sg:address":"Goethestr. 7",
    "sg:city":"Kassel",
    "sg:phone":"+49 800 9998888",
    "sg:postcode":"34119",
    "sg:province":"Hessen",
    "wof:name":"Fair Play Versicherungs- Makler Gmbh",
    "wof:placetype":"venue"
},
  "geometry": {"coordinates":[9.4770069122,51.3149642944],"type":"Point"}
}