{
  "type": "Feature",
  "properties": {
    "iso:country":"DE",
    "sg:address":"Wittener Str. 103",
    "sg:city":"Bochum",
    "sg:phone":"+49 234/9379910",
    "sg:postcode":"44803",
    "sg:province":"Nordrhein-Westfalen",
    "wof:name":"R\u00fcdiger Weinrich",
    "wof:placetype":"venue"
},
  "geometry": {"coordinates":[7.2810130119,51.4637908936],"type":"Point"}
}