{
  "type": "Feature",
  "properties": {
    "iso:country":"DE",
    "sg:address":"Rosenstr. 15",
    "sg:city":"Oberteuringen",
    "sg:phone":"+49 7546/5695",
    "sg:postcode":"88094",
    "sg:province":"Baden-W\u00fcrttemberg",
    "wof:name":"K. Fitzko",
    "wof:placetype":"venue"
},
  "geometry": {"coordinates":[9.484167,47.742882],"type":"Point"}
}