{
  "type": "Feature",
  "properties": {
    "iso:country":"DE",
    "sg:address":"Wilhelmstr. 139",
    "sg:city":"W\u00fclfrath",
    "sg:phone":"+49 2058/3113",
    "sg:postcode":"42489",
    "sg:province":"Nordrhein-Westfalen",
    "wof:name":"Blumen Busse E. K.",
    "wof:placetype":"venue"
},
  "geometry": {"coordinates":[7.036508,51.281857],"type":"Point"}
}