{
  "type": "Feature",
  "properties": {
    "iso:country":"DE",
    "sg:address":"Pastoratsstr. 7",
    "sg:city":"Marienheide",
    "sg:phone":"+49 2264/8498",
    "sg:postcode":"51709",
    "sg:province":"Nordrhein-Westfalen",
    "wof:name":"Katholisches Pfarramt St. Johannes Baptist",
    "wof:placetype":"venue"
},
  "geometry": {"coordinates":[7.4739489555,51.0599746704],"type":"Point"}
}