{
  "type": "Feature",
  "properties": {
    "iso:country":"DE",
    "sg:address":"Bahnhofstr. 23a",
    "sg:city":"Neumarkt-Sankt Veit",
    "sg:phone":"+49 8639/411",
    "sg:postcode":"84494",
    "sg:province":"Bayern",
    "wof:name":"B. Gro\u00df",
    "wof:placetype":"venue"
},
  "geometry": {"coordinates":[12.5046186447,48.3615341187],"type":"Point"}
}