{
  "type": "Feature",
  "properties": {
    "iso:country":"DE",
    "sg:address":"Greutterstr. 30",
    "sg:city":"Stuttgart",
    "sg:phone":"+49 711/834795",
    "sg:postcode":"70499",
    "sg:province":"Baden-W\u00fcrttemberg",
    "wof:name":"K. E. Riedlinger Ingenieur",
    "wof:placetype":"venue"
},
  "geometry": {"coordinates":[9.1218709946,48.822807312],"type":"Point"}
}