{
  "type": "Feature",
  "properties": {
    "iso:country":"DE",
    "sg:address":"Schneeberger Str. 21",
    "sg:city":"Aue",
    "sg:phone":"+49 3771/22193",
    "sg:postcode":"08280",
    "sg:province":"Sachsen",
    "wof:name":"U. Matthes",
    "wof:placetype":"venue"
},
  "geometry": {"coordinates":[12.699246,50.587635],"type":"Point"}
}