{
  "type": "Feature",
  "properties": {
    "iso:country":"DE",
    "sg:address":"Mollenbachstr. 2",
    "sg:city":"Leonberg",
    "sg:postcode":"71229",
    "sg:province":"Baden-W\u00fcrttemberg",
    "wof:name":"Euroteam Zentralregulierungs- U. Dienstleistungspartner F.",
    "wof:placetype":"venue"
},
  "geometry": {"coordinates":[9.003839,48.785015],"type":"Point"}
}