{
  "type": "Feature",
  "properties": {
    "iso:country":"DE",
    "sg:address":"Wendersbachweg 31",
    "sg:city":"Essen",
    "sg:phone":"+49 201/606087",
    "sg:postcode":"45359",
    "sg:province":"Nordrhein-Westfalen",
    "wof:name":"Gerhard Klein",
    "wof:placetype":"venue"
},
  "geometry": {"coordinates":[6.922985,51.465401],"type":"Point"}
}