{
  "type": "Feature",
  "properties": {
    "iso:country":"DE",
    "sg:address":"Tettnanger Str. 345/1",
    "sg:city":"Ravensburg",
    "sg:phone":"+49 751/61459",
    "sg:postcode":"88214",
    "sg:province":"Baden-W\u00fcrttemberg",
    "wof:name":"Doris Natterer",
    "wof:placetype":"venue"
},
  "geometry": {"coordinates":[9.6024780273,47.739074707],"type":"Point"}
}