{
  "type": "Feature",
  "properties": {
    "iso:country":"DE",
    "sg:address":"PF 104015",
    "sg:city":"Merzig",
    "sg:phone":"+49 6861",
    "sg:postcode":"66663",
    "sg:province":"Saarland",
    "wof:name":"Windpark Saar Gmbh&co.kg",
    "wof:placetype":"venue"
},
  "geometry": {"coordinates":[6.63651,49.442039],"type":"Point"}
}