{
  "type": "Feature",
  "properties": {
    "iso:country":"DE",
    "sg:address":"Dr.-G\u00fcnther-Bodeck-Str. 7",
    "sg:city":"Grambin",
    "sg:postcode":"17375",
    "sg:province":"Mecklenburg-Vorpommern",
    "wof:name":"Dr. Med. Klaus Stolz",
    "wof:placetype":"venue"
},
  "geometry": {"coordinates":[14.164754,53.706383],"type":"Point"}
}