{
  "type": "Feature",
  "properties": {
    "iso:country":"DE",
    "sg:address":"F\u00f6hrendamm 2",
    "sg:city":"Emsdetten",
    "sg:phone":"+49 2572/7866",
    "sg:postcode":"48282",
    "sg:province":"Nordrhein-Westfalen",
    "wof:name":"Hubert Wesselmeier",
    "wof:placetype":"venue"
},
  "geometry": {"coordinates":[7.526862,52.161999],"type":"Point"}
}