{
  "type": "Feature",
  "properties": {
    "iso:country":"DE",
    "sg:address":"Hammerbrookstr. 47",
    "sg:city":"Hamburg",
    "sg:phone":"+49 40/327087",
    "sg:postcode":"20097",
    "sg:province":"Hamburg",
    "wof:name":"Peter Wegner Verwaltungs- Gesellschaft Mbh",
    "wof:placetype":"venue"
},
  "geometry": {"coordinates":[10.0227012634,53.5483779907],"type":"Point"}
}