{
  "type": "Feature",
  "properties": {
    "iso:country":"DE",
    "sg:address":"Raiffeisenstr. 26",
    "sg:city":"Pfaffenhofen",
    "sg:phone":"+49 8441/89820",
    "sg:postcode":"85276",
    "sg:province":"Bayern",
    "wof:name":"Endress M\u00fcnchen Gmbh & Co. Verwaltungs-kg",
    "wof:placetype":"venue"
},
  "geometry": {"coordinates":[11.51629,48.537724],"type":"Point"}
}