{
  "type": "Feature",
  "properties": {
    "iso:country":"DE",
    "sg:address":"Hauptstr. 80",
    "sg:city":"Stuttgart",
    "sg:phone":"+49 711/133560",
    "sg:postcode":"70563",
    "sg:province":"Baden-W\u00fcrttemberg",
    "wof:name":"Kreder Gmbh",
    "wof:placetype":"venue"
},
  "geometry": {"coordinates":[9.10368,48.730087],"type":"Point"}
}