{
  "type": "Feature",
  "properties": {
    "iso:country":"DE",
    "sg:address":"Eberbacher Str. 22",
    "sg:city":"Sch\u00f6nbrunn",
    "sg:phone":"+49 6262/3814",
    "sg:postcode":"69436",
    "sg:province":"Baden-W\u00fcrttemberg",
    "wof:name":"Alten- Und Pflegeheim Haus M\u00fctzel",
    "wof:placetype":"venue"
},
  "geometry": {"coordinates":[8.975128,49.401421],"type":"Point"}
}