{
  "type": "Feature",
  "properties": {
    "iso:country":"DE",
    "sg:address":"Lindenberg 8",
    "sg:city":"Babenhausen",
    "sg:phone":"+49 8333/93194",
    "sg:postcode":"87727",
    "sg:province":"Bayern",
    "wof:name":"Dr. Med. Georg Hipp Arzt F\u00fcr Allgemeinmedizin",
    "wof:placetype":"venue"
},
  "geometry": {"coordinates":[10.2550897598,48.1408996582],"type":"Point"}
}