{
  "type": "Feature",
  "properties": {
    "iso:country":"DE",
    "sg:address":"Hamburger Str. 196",
    "sg:city":"Ahrensburg",
    "sg:phone":"+49 4102/1233",
    "sg:postcode":"22926",
    "sg:province":"Schleswig-Holstein",
    "wof:name":"Rolf",
    "wof:placetype":"venue"
},
  "geometry": {"coordinates":[10.2110176086,53.6570549011],"type":"Point"}
}