{
  "type": "Feature",
  "properties": {
    "iso:country":"DE",
    "sg:address":"Kieler Str. 18",
    "sg:city":"Bredenbek",
    "sg:phone":"+49 4334/330",
    "sg:postcode":"24796",
    "sg:province":"Schleswig-Holstein",
    "wof:name":"Kreys Gasthof",
    "wof:placetype":"venue"
},
  "geometry": {"coordinates":[9.8753080368,54.3243255615],"type":"Point"}
}