{
  "type": "Feature",
  "properties": {
    "iso:country":"DE",
    "sg:address":"Werner-Hartmann-Str 5",
    "sg:city":"Dresden",
    "sg:phone":"+49 351/8074460",
    "sg:postcode":"01099",
    "sg:province":"Sachsen",
    "wof:name":"Pps Gmbh",
    "wof:placetype":"venue"
},
  "geometry": {"coordinates":[13.763671,51.085888],"type":"Point"}
}