{
  "type": "Feature",
  "properties": {
    "iso:country":"DE",
    "sg:address":"Ramminger Str. 4",
    "sg:city":"\u00d6llingen",
    "sg:phone":"+49 7345/7504",
    "sg:postcode":"89129",
    "sg:province":"Baden-W\u00fcrttemberg",
    "wof:name":"Frisch",
    "wof:placetype":"venue"
},
  "geometry": {"coordinates":[10.149288,48.52747],"type":"Point"}
}