{
  "type": "Feature",
  "properties": {
    "iso:country":"DE",
    "sg:address":"Wiedenhofstr. 1-3",
    "sg:city":"Remscheid",
    "sg:phone":"+49 2191/926990",
    "sg:postcode":"42853",
    "sg:province":"Nordrhein-Westfalen",
    "wof:name":"Otto Wevelsiep Kg Farben-lacke-tapeten",
    "wof:placetype":"venue"
},
  "geometry": {"coordinates":[7.189344883,51.1803245544],"type":"Point"}
}