{
  "type": "Feature",
  "properties": {
    "iso:country":"DE",
    "sg:address":"Borkener Str. 203",
    "sg:city":"Borken",
    "sg:phone":"+49 2861/62955",
    "sg:postcode":"46325",
    "sg:province":"Nordrhein-Westfalen",
    "wof:name":"Paul Becker",
    "wof:placetype":"venue"
},
  "geometry": {"coordinates":[6.806422,51.866051],"type":"Point"}
}