{
  "type": "Feature",
  "properties": {
    "iso:country":"DE",
    "sg:address":"Wesselheideweg 101",
    "sg:city":"Bonn",
    "sg:phone":"+49 228/746095",
    "sg:postcode":"53123",
    "sg:province":"Nordrhein-Westfalen",
    "wof:name":"Reitanlage Wesselheide Gmbh",
    "wof:placetype":"venue"
},
  "geometry": {"coordinates":[7.034119,50.703583],"type":"Point"}
}