{
  "type": "Feature",
  "properties": {
    "iso:country":"DE",
    "sg:address":"Striewitzweg 55",
    "sg:city":"Teltow",
    "sg:phone":"+49 3328/473689",
    "sg:postcode":"14513",
    "sg:province":"Brandenburg",
    "wof:name":"Pension Schulze",
    "wof:placetype":"venue"
},
  "geometry": {"coordinates":[13.2532949448,52.3975219727],"type":"Point"}
}