{
  "type": "Feature",
  "properties": {
    "iso:country":"DE",
    "sg:address":"Reitling",
    "sg:city":"Evessen",
    "sg:phone":"+49 5305/447",
    "sg:postcode":"38173",
    "sg:province":"Niedersachsen",
    "wof:name":"Gastst\u00e4tte Reitling Im Elm",
    "wof:placetype":"venue"
},
  "geometry": {"coordinates":[10.7546396255,52.2076187134],"type":"Point"}
}