{
  "type": "Feature",
  "properties": {
    "iso:country":"DE",
    "sg:address":"Ringweg 9",
    "sg:city":"B\u00fchlertann",
    "sg:phone":"+49 7973/16490",
    "sg:postcode":"74424",
    "sg:province":"Baden-W\u00fcrttemberg",
    "wof:name":"Kellerberg",
    "wof:placetype":"venue"
},
  "geometry": {"coordinates":[9.9153547287,49.0404434204],"type":"Point"}
}