{
  "type": "Feature",
  "properties": {
    "iso:country":"DE",
    "sg:address":"W\u00fcllener Str. 74",
    "sg:city":"Vreden",
    "sg:phone":"+49 2564/97123",
    "sg:postcode":"48691",
    "sg:province":"Nordrhein-Westfalen",
    "wof:name":"Concept-haus Bautr\u00e4ger Verwaltungs Gmbh",
    "wof:placetype":"venue"
},
  "geometry": {"coordinates":[6.8346509933,52.0350189209],"type":"Point"}
}