{
  "type": "Feature",
  "properties": {
    "iso:country":"DE",
    "sg:address":"Die Boene 4",
    "sg:city":"Ebsdorfergrund",
    "sg:phone":"+49 6424/70006",
    "sg:postcode":"35085",
    "sg:province":"Hessen",
    "wof:name":"Dieter Gr\u00fcn",
    "wof:placetype":"venue"
},
  "geometry": {"coordinates":[8.885905,50.756886],"type":"Point"}
}