{
  "type": "Feature",
  "properties": {
    "iso:country":"DE",
    "sg:address":"Frankenstr. 72",
    "sg:city":"Essen",
    "sg:phone":"+49 201/596922",
    "sg:postcode":"45134",
    "sg:province":"Nordrhein-Westfalen",
    "wof:name":"Pro Audio Gmbh",
    "wof:placetype":"venue"
},
  "geometry": {"coordinates":[7.0474882126,51.4273757935],"type":"Point"}
}