{
  "type": "Feature",
  "properties": {
    "iso:country":"DE",
    "sg:address":"Schlo\u00dfstr. 7",
    "sg:city":"Oberstaufen",
    "sg:phone":"+49 8386/7757",
    "sg:postcode":"87534",
    "sg:province":"Bayern",
    "wof:name":"Adolf F\u00e4\u00dfler Architekt",
    "wof:placetype":"venue"
},
  "geometry": {"coordinates":[10.020535,47.55336],"type":"Point"}
}