{
  "type": "Feature",
  "properties": {
    "iso:country":"DE",
    "sg:address":"Schwerter Str. 3",
    "sg:city":"Holzwickede",
    "sg:phone":"+49 2301/12012",
    "sg:postcode":"59439",
    "sg:province":"Nordrhein-Westfalen",
    "wof:name":"Isdo Tendler Gmbh",
    "wof:placetype":"venue"
},
  "geometry": {"coordinates":[7.629187,51.482407],"type":"Point"}
}