{
  "type": "Feature",
  "properties": {
    "iso:country":"DE",
    "sg:address":"Weidenweg 12",
    "sg:city":"Laage",
    "sg:phone":"+49 38459/32502",
    "sg:postcode":"18299",
    "sg:province":"Mecklenburg-Vorpommern",
    "wof:name":"W. Gerullat",
    "wof:placetype":"venue"
},
  "geometry": {"coordinates":[12.353097,53.922161],"type":"Point"}
}