{
  "type": "Feature",
  "properties": {
    "iso:country":"DE",
    "sg:address":"Ginsterweg",
    "sg:city":"Billigheim",
    "sg:phone":"+49 6265/8085",
    "sg:postcode":"74842",
    "sg:province":"Baden-W\u00fcrttemberg",
    "wof:name":"Floristenbedarf Und Korbwaren",
    "wof:placetype":"venue"
},
  "geometry": {"coordinates":[9.225598,49.35498],"type":"Point"}
}