{
  "type": "Feature",
  "properties": {
    "iso:country":"DE",
    "sg:address":"Oldenburger Str. 37",
    "sg:city":"Vechta",
    "sg:phone":"+49 4441/84777",
    "sg:postcode":"49377",
    "sg:province":"Niedersachsen",
    "wof:name":"Hongkong City",
    "wof:placetype":"venue"
},
  "geometry": {"coordinates":[8.2878055573,52.7336120605],"type":"Point"}
}