{
  "type": "Feature",
  "properties": {
    "iso:country":"DE",
    "sg:address":"Nardter Weg 11",
    "sg:city":"Hoyerswerda",
    "sg:phone":"+49 3571/406203",
    "sg:postcode":"02977",
    "sg:province":"Sachsen",
    "wof:name":"H & K Baustoffe Gmbh",
    "wof:placetype":"venue"
},
  "geometry": {"coordinates":[14.2232589722,51.4478340149],"type":"Point"}
}