{
  "type": "Feature",
  "properties": {
    "iso:country":"DE",
    "sg:address":"Im Fladder 2",
    "sg:city":"Siedenburg",
    "sg:postcode":"27254",
    "sg:province":"Niedersachsen",
    "wof:name":"Tischlerei Schlemermeyer Inh. Thomas Humke Und",
    "wof:placetype":"venue"
},
  "geometry": {"coordinates":[8.937016,52.694241],"type":"Point"}
}