{
  "type": "Feature",
  "properties": {
    "iso:country":"DE",
    "sg:address":"Glockenanger 3",
    "sg:city":"Hessisch Oldendorf",
    "sg:postcode":"31840",
    "sg:province":"Niedersachsen",
    "wof:name":"Merseburger Fach- Gro\u00dfhandel Gmbh",
    "wof:placetype":"venue"
},
  "geometry": {"coordinates":[9.255108,52.167801],"type":"Point"}
}