{
  "type": "Feature",
  "properties": {
    "iso:country":"DE",
    "sg:address":"Hatzper Str. 104",
    "sg:city":"Essen",
    "sg:phone":"+49 201/718141",
    "sg:postcode":"45149",
    "sg:province":"Nordrhein-Westfalen",
    "wof:name":"Hans Hermann Unterschemmann",
    "wof:placetype":"venue"
},
  "geometry": {"coordinates":[6.973964,51.417912],"type":"Point"}
}