{
  "type": "Feature",
  "properties": {
    "iso:country":"DE",
    "sg:address":"Dorfstr. 16",
    "sg:city":"Pahlsdorf",
    "sg:phone":"+49 35323/61019",
    "sg:postcode":"03249",
    "sg:province":"Brandenburg",
    "wof:name":"Seco Bau Gmbh",
    "wof:placetype":"venue"
},
  "geometry": {"coordinates":[13.646672,51.696777],"type":"Point"}
}