{
  "type": "Feature",
  "properties": {
    "iso:country":"DE",
    "sg:address":"Zimmerplatzweg 14",
    "sg:city":"Marburg",
    "sg:phone":"+49 172 5603897",
    "sg:postcode":"35043",
    "sg:province":"Hessen",
    "wof:name":"Karl M\u00fcller",
    "wof:placetype":"venue"
},
  "geometry": {"coordinates":[8.761674,50.775459],"type":"Point"}
}