{
  "type": "Feature",
  "properties": {
    "iso:country":"DE",
    "sg:address":"Langenbielauer Weg 21",
    "sg:city":"D\u00fcsseldorf",
    "sg:phone":"+49 211/272222",
    "sg:postcode":"40627",
    "sg:province":"Nordrhein-Westfalen",
    "wof:name":"Vpv Allgemeine Versicherungs- Ag",
    "wof:placetype":"venue"
},
  "geometry": {"coordinates":[6.8517241478,51.2124137878],"type":"Point"}
}