{
  "type": "Feature",
  "properties": {
    "iso:country":"DE",
    "sg:address":"Neue Chaussee 1a",
    "sg:city":"Hadamar",
    "sg:phone":"+49 6433/4664",
    "sg:postcode":"65589",
    "sg:province":"Hessen",
    "wof:name":"Arnold Jasinski",
    "wof:placetype":"venue"
},
  "geometry": {"coordinates":[8.044844,50.444569],"type":"Point"}
}