{
  "type": "Feature",
  "properties": {
    "iso:country":"DE",
    "sg:address":"Burgstr. 81",
    "sg:city":"Baesweiler",
    "sg:phone":"+49 2401/607550",
    "sg:postcode":"52499",
    "sg:province":"Nordrhein-Westfalen",
    "wof:name":"M. Wackertapp",
    "wof:placetype":"venue"
},
  "geometry": {"coordinates":[6.1810998917,50.9111785889],"type":"Point"}
}