{
  "type": "Feature",
  "properties": {
    "iso:country":"DE",
    "sg:address":"Spitalm\u00fchlenstr. 20",
    "sg:city":"Schw\u00e4bisch Hall",
    "sg:phone":"+49 791/71991",
    "sg:postcode":"74523",
    "sg:province":"Baden-W\u00fcrttemberg",
    "wof:name":"Auwiesen Freizeit- Und Sportanlagen Gmbh",
    "wof:placetype":"venue"
},
  "geometry": {"coordinates":[9.7351160049,49.1221504211],"type":"Point"}
}