{
  "type": "Feature",
  "properties": {
    "iso:country":"DE",
    "sg:address":"Kurt-Schumacher-Str. 16",
    "sg:city":"Niddatal",
    "sg:phone":"+49 6034/8880",
    "sg:postcode":"61194",
    "sg:province":"Hessen",
    "wof:name":"Thomas L\u00f6ffler",
    "wof:placetype":"venue"
},
  "geometry": {"coordinates":[8.8404779434,50.286781311],"type":"Point"}
}