{
  "type": "Feature",
  "properties": {
    "iso:country":"DE",
    "sg:address":"Auf Sprung 12",
    "sg:city":"Trier",
    "sg:phone":"+49 651/52390",
    "sg:postcode":"54292",
    "sg:province":"Rheinland-Pfalz",
    "wof:name":"Volker Niemann Rechtsanwalt",
    "wof:placetype":"venue"
},
  "geometry": {"coordinates":[6.7101221085,49.7897987366],"type":"Point"}
}