{
  "type": "Feature",
  "properties": {
    "iso:country":"DE",
    "sg:address":"Talstr. 28",
    "sg:city":"Siegen",
    "sg:phone":"+49 271/4852705",
    "sg:postcode":"57076",
    "sg:province":"Nordrhein-Westfalen",
    "wof:name":"Aktiver Pflegedienst",
    "wof:placetype":"venue"
},
  "geometry": {"coordinates":[8.037765,50.89407],"type":"Point"}
}