{
  "type": "Feature",
  "properties": {
    "iso:country":"DE",
    "sg:address":"Lundener Str 12-14",
    "sg:city":"Rendsburg",
    "sg:phone":"+49 4331/590921",
    "sg:postcode":"24768",
    "sg:province":"Schleswig-Holstein",
    "wof:name":"Rzr Rechenzentrum Rendsburg Gmbh & Co Kg",
    "wof:placetype":"venue"
},
  "geometry": {"coordinates":[9.6282539368,54.3164253235],"type":"Point"}
}