{
  "type": "Feature",
  "properties": {
    "iso:country":"DE",
    "sg:address":"Hauptstr. 36",
    "sg:city":"Gessertshausen",
    "sg:phone":"+49 8238/4011",
    "sg:postcode":"86459",
    "sg:province":"Bayern",
    "wof:name":"Raiffeisenbank Gessertshausen Eg",
    "wof:placetype":"venue"
},
  "geometry": {"coordinates":[10.72994,48.329071],"type":"Point"}
}