{
  "type": "Feature",
  "properties": {
    "iso:country":"DE",
    "sg:address":"Burg Grona 29",
    "sg:city":"G\u00f6ttingen",
    "sg:postcode":"37079",
    "sg:province":"Niedersachsen",
    "wof:name":"Von Bismarck-briestsche Familienstiftung",
    "wof:placetype":"venue"
},
  "geometry": {"coordinates":[9.9110422134,51.5529975891],"type":"Point"}
}