{
  "type": "Feature",
  "properties": {
    "iso:country":"DE",
    "sg:address":"Buchenstr. 21",
    "sg:city":"Alveslohe",
    "sg:phone":"+49 4193/1862",
    "sg:postcode":"25486",
    "sg:province":"Schleswig-Holstein",
    "wof:name":"Kr\u00fcger & Wiegmann Ohg Fleischwaren",
    "wof:placetype":"venue"
},
  "geometry": {"coordinates":[9.9194555283,53.7879486084],"type":"Point"}
}