{
  "type": "Feature",
  "properties": {
    "iso:country":"DE",
    "sg:address":"Heinrich-Winter-Str. 12a",
    "sg:city":"Kronberg",
    "sg:phone":"+49 6173/4537",
    "sg:postcode":"61476",
    "sg:province":"Hessen",
    "wof:name":"Hanspeter Borsch Architekt",
    "wof:placetype":"venue"
},
  "geometry": {"coordinates":[8.512239,50.177567],"type":"Point"}
}