{
  "type": "Feature",
  "properties": {
    "iso:country":"DE",
    "sg:address":"Hauptstr. 27",
    "sg:city":"Gie\u00df\u00fcbel",
    "sg:postcode":"98667",
    "sg:province":"Th\u00fcringen",
    "wof:name":"Prof. Dr. Liniger Engineering Gmbh",
    "wof:placetype":"venue"
},
  "geometry": {"coordinates":[10.8765535355,50.5221061707],"type":"Point"}
}