{
  "type": "Feature",
  "properties": {
    "iso:country":"DE",
    "sg:address":"Hebbelstr. 4",
    "sg:city":"Berlin",
    "sg:phone":"+49 30/3418636",
    "sg:postcode":"10585",
    "sg:province":"Berlin",
    "wof:name":"Thomas Wetzel",
    "wof:placetype":"venue"
},
  "geometry": {"coordinates":[13.299595,52.515625],"type":"Point"}
}