{
  "type": "Feature",
  "properties": {
    "iso:country":"DE",
    "sg:address":"Markhauser Str. 40",
    "sg:city":"Peheim",
    "sg:phone":"+49 4479/1331",
    "sg:postcode":"49696",
    "sg:province":"Niedersachsen",
    "wof:name":"Aloys Koopmann",
    "wof:placetype":"venue"
},
  "geometry": {"coordinates":[7.83922,52.890129],"type":"Point"}
}