{
  "type": "Feature",
  "properties": {
    "iso:country":"DE",
    "sg:address":"Weizenstr. 3",
    "sg:city":"Eching",
    "sg:phone":"+49 8709/262091",
    "sg:postcode":"84174",
    "sg:province":"Bayern",
    "wof:name":"Btb Gmbh",
    "wof:placetype":"venue"
},
  "geometry": {"coordinates":[12.028451,48.494671],"type":"Point"}
}