{
  "type": "Feature",
  "properties": {
    "iso:country":"DE",
    "sg:address":"Industriestr. 15",
    "sg:city":"Springe",
    "sg:phone":"+49 5041/2273",
    "sg:postcode":"31832",
    "sg:province":"Niedersachsen",
    "wof:name":"Eschenhof Friedrich Bartels",
    "wof:placetype":"venue"
},
  "geometry": {"coordinates":[9.558792,52.215687],"type":"Point"}
}