{
  "type": "Feature",
  "properties": {
    "iso:country":"DE",
    "sg:address":"Kabeler Str. 4",
    "sg:city":"Hagen",
    "sg:postcode":"58099",
    "sg:province":"Nordrhein-Westfalen",
    "wof:name":"Hww Immobilien- Beteiligungs Gmbh & Co. Kg",
    "wof:placetype":"venue"
},
  "geometry": {"coordinates":[7.479754,51.407833],"type":"Point"}
}