{
  "type": "Feature",
  "properties": {
    "iso:country":"DE",
    "sg:address":"Morawitzkystr. 1",
    "sg:city":"M\u00fcnchen",
    "sg:phone":"+49 89/331824",
    "sg:postcode":"80803",
    "sg:province":"Bayern",
    "wof:name":"Dr. Gerhard Beisenherz Rechtsanwalt",
    "wof:placetype":"venue"
},
  "geometry": {"coordinates":[11.5848798752,48.1635665894],"type":"Point"}
}