{
  "type": "Feature",
  "properties": {
    "iso:country":"DE",
    "sg:address":"Seehausener Str. 5",
    "sg:city":"Leipzig",
    "sg:phone":"+49 341/524030",
    "sg:postcode":"04158",
    "sg:province":"Sachsen",
    "wof:name":"Bhs Leipzig-wiederitzsch Grundst\u00fccksverwaltungs-gmbh",
    "wof:placetype":"venue"
},
  "geometry": {"coordinates":[12.3801555634,51.3944969177],"type":"Point"}
}