{
  "type": "Feature",
  "properties": {
    "iso:country":"DE",
    "sg:address":"Forsthausenstr. 47",
    "sg:city":"Kirchzell",
    "sg:phone":"+49 9373/8617",
    "sg:postcode":"63931",
    "sg:province":"Bayern",
    "wof:name":"Erich Henn",
    "wof:placetype":"venue"
},
  "geometry": {"coordinates":[9.179158,49.617588],"type":"Point"}
}