{
  "type": "Feature",
  "properties": {
    "iso:country":"DE",
    "sg:address":"Heiligenh\u00f6fe 7",
    "sg:city":"Uslar",
    "sg:phone":"+49 5573/342",
    "sg:postcode":"37170",
    "sg:province":"Niedersachsen",
    "wof:name":"Heinrich Teske Gmbh",
    "wof:placetype":"venue"
},
  "geometry": {"coordinates":[9.6348495483,51.6596336365],"type":"Point"}
}