{
  "type": "Feature",
  "properties": {
    "iso:country":"DE",
    "sg:address":"Culemeyerstr. 2",
    "sg:city":"Berlin",
    "sg:phone":"+49 30/74962107",
    "sg:postcode":"12277",
    "sg:province":"Berlin",
    "wof:name":"Daimler Chrysler Aerospace Ag",
    "wof:placetype":"venue"
},
  "geometry": {"coordinates":[13.3912696838,52.4171066284],"type":"Point"}
}