{
  "type": "Feature",
  "properties": {
    "iso:country":"DE",
    "sg:address":"Hohe Heide 2",
    "sg:city":"Emmerich",
    "sg:phone":"+49 2828/2363",
    "sg:postcode":"46446",
    "sg:province":"Nordrhein-Westfalen",
    "wof:name":"Theo Kerkhof",
    "wof:placetype":"venue"
},
  "geometry": {"coordinates":[6.180936,51.877399],"type":"Point"}
}