{
  "type": "Feature",
  "properties": {
    "iso:country":"DE",
    "sg:address":"Rempartstr. 5",
    "sg:city":"Freiburg",
    "sg:phone":"+49 761/26126",
    "sg:postcode":"79098",
    "sg:province":"Baden-W\u00fcrttemberg",
    "wof:name":"V. Elsenhans Antiquit\u00e4ten",
    "wof:placetype":"venue"
},
  "geometry": {"coordinates":[7.847997,47.992767],"type":"Point"}
}