{
  "type": "Feature",
  "properties": {
    "iso:country":"DE",
    "sg:address":"Postfach",
    "sg:city":"Lautersheim",
    "sg:postcode":"67308",
    "sg:province":"Rheinland-Pfalz",
    "wof:name":"Gemeindeb\u00fccherei Lautersheim",
    "wof:placetype":"venue"
},
  "geometry": {"coordinates":[8.139891,49.649078],"type":"Point"}
}