{
  "type": "Feature",
  "properties": {
    "iso:country":"DE",
    "sg:address":"Festplatzstr. 8",
    "sg:city":"Neustadt",
    "sg:phone":"+49 6321/92420",
    "sg:postcode":"67433",
    "sg:province":"Rheinland-Pfalz",
    "wof:name":"Redaktion Ehv Aktuell Wirtschaftsf\u00f6rderungsges.",
    "wof:placetype":"venue"
},
  "geometry": {"coordinates":[8.134447,49.353928],"type":"Point"}
}