{
  "type": "Feature",
  "properties": {
    "iso:country":"DE",
    "sg:address":"L\u00f6wengasse 9",
    "sg:city":"Bad Homburg",
    "sg:phone":"+49 6172/25821",
    "sg:postcode":"61348",
    "sg:province":"Hessen",
    "wof:name":"C. Knoll",
    "wof:placetype":"venue"
},
  "geometry": {"coordinates":[8.6123762131,50.2275848389],"type":"Point"}
}