{
  "type": "Feature",
  "properties": {
    "iso:country":"DE",
    "sg:address":"Ortenaustr. 26",
    "sg:city":"Oberkirch",
    "sg:postcode":"77704",
    "sg:province":"Baden-W\u00fcrttemberg",
    "wof:name":"Kath. Pfarramt St. Wendelin",
    "wof:placetype":"venue"
},
  "geometry": {"coordinates":[8.0358181,48.5593147278],"type":"Point"}
}