{
  "type": "Feature",
  "properties": {
    "iso:country":"DE",
    "sg:address":"Gelsenkircher Str. 15",
    "sg:city":"Herne",
    "sg:phone":"+49 2325/9820",
    "sg:postcode":"44649",
    "sg:province":"Nordrhein-Westfalen",
    "wof:name":"Lucke Miet- Und Leasing Gmbh",
    "wof:placetype":"venue"
},
  "geometry": {"coordinates":[7.1586470604,51.5267829895],"type":"Point"}
}