{
  "type": "Feature",
  "properties": {
    "iso:country":"DE",
    "sg:address":"Kupferdreher Str. 196",
    "sg:city":"Essen",
    "sg:phone":"+49 201/487815",
    "sg:postcode":"45257",
    "sg:province":"Nordrhein-Westfalen",
    "wof:name":"Kanu - Trekking - Autodachtr\u00e4ger - Boote - Seekaja",
    "wof:placetype":"venue"
},
  "geometry": {"coordinates":[7.083353,51.388519],"type":"Point"}
}