{
  "type": "Feature",
  "properties": {
    "iso:country":"DE",
    "sg:address":"Stefansbecke 35",
    "sg:city":"Sprockh\u00f6vel",
    "sg:phone":"+49 2339/6021",
    "sg:postcode":"45549",
    "sg:province":"Nordrhein-Westfalen",
    "wof:name":"Ph Industriehydraulik- Und Verwaltungs Gmbh",
    "wof:placetype":"venue"
},
  "geometry": {"coordinates":[7.280338,51.320263],"type":"Point"}
}