{
  "type": "Feature",
  "properties": {
    "iso:country":"DE",
    "sg:address":"Lenaustr. 35",
    "sg:city":"Kassel",
    "sg:phone":"+49 561/878448",
    "sg:postcode":"34125",
    "sg:province":"Hessen",
    "wof:name":"G\u00fcnter Diekmann Bau Gmbh",
    "wof:placetype":"venue"
},
  "geometry": {"coordinates":[9.504411,51.333733],"type":"Point"}
}