{
  "type": "Feature",
  "properties": {
    "iso:country":"DE",
    "sg:address":"Schulstr. 21",
    "sg:city":"Ebernhahn",
    "sg:phone":"+49 2623/96400",
    "sg:postcode":"56424",
    "sg:province":"Rheinland-Pfalz",
    "wof:name":"Robert Lieser",
    "wof:placetype":"venue"
},
  "geometry": {"coordinates":[7.7733278275,50.4729881287],"type":"Point"}
}