{
  "type": "Feature",
  "properties": {
    "iso:country":"DE",
    "sg:address":"Ackerstr. 9",
    "sg:city":"Wesel",
    "sg:phone":"+49 281/64346",
    "sg:postcode":"46483",
    "sg:province":"Nordrhein-Westfalen",
    "wof:name":"E. Scholten Heissmangel",
    "wof:placetype":"venue"
},
  "geometry": {"coordinates":[6.6081671715,51.6763916016],"type":"Point"}
}