{
  "type": "Feature",
  "properties": {
    "iso:country":"DE",
    "sg:address":"Besser Str. 6",
    "sg:city":"Gudensberg",
    "sg:phone":"+49 5603/3137",
    "sg:postcode":"34281",
    "sg:province":"Hessen",
    "wof:name":"Kurt Koch",
    "wof:placetype":"venue"
},
  "geometry": {"coordinates":[9.36619,51.179104],"type":"Point"}
}