{
  "type": "Feature",
  "properties": {
    "iso:country":"DE",
    "sg:address":"Uhlandstr. 1",
    "sg:city":"Kirchheimbolanden",
    "sg:phone":"+49 4963/525061",
    "sg:postcode":"67292",
    "sg:province":"Rheinland-Pfalz",
    "wof:name":"Raiffeisenbank Kirchheimbolanden",
    "wof:placetype":"venue"
},
  "geometry": {"coordinates":[8.016006,49.665382],"type":"Point"}
}