{
  "type": "Feature",
  "properties": {
    "iso:country":"DE",
    "sg:address":"Hiesfelder Str. 173",
    "sg:city":"Oberhausen",
    "sg:phone":"+49 208/687770",
    "sg:postcode":"46147",
    "sg:province":"Nordrhein-Westfalen",
    "wof:name":"Bross Und Verbist Malerfachbetrieb Gmbh",
    "wof:placetype":"venue"
},
  "geometry": {"coordinates":[6.82251,51.537472],"type":"Point"}
}