{
  "type": "Feature",
  "properties": {
    "iso:country":"DE",
    "sg:address":"Hauptstr. 31",
    "sg:city":"Lambrecht",
    "sg:phone":"+49 6325/95440",
    "sg:postcode":"67466",
    "sg:province":"Rheinland-Pfalz",
    "wof:name":"Ph. Welker Gmbh",
    "wof:placetype":"venue"
},
  "geometry": {"coordinates":[8.076906,49.372768],"type":"Point"}
}