{
  "type": "Feature",
  "properties": {
    "iso:country":"DE",
    "sg:address":"Annastr. 2",
    "sg:city":"Wietmarschen",
    "sg:phone":"+49 5925/265",
    "sg:postcode":"49835",
    "sg:province":"Niedersachsen",
    "wof:name":"Hermann Brinkers",
    "wof:placetype":"venue"
},
  "geometry": {"coordinates":[7.1184082031,52.5218086243],"type":"Point"}
}