{
  "type": "Feature",
  "properties": {
    "iso:country":"DE",
    "sg:address":"Altm\u00fchlstr. 3",
    "sg:city":"Wiesbaden",
    "sg:phone":"+49 6122/8666",
    "sg:postcode":"65207",
    "sg:province":"Hessen",
    "wof:name":"Imowa Immobilien Gmbh",
    "wof:placetype":"venue"
},
  "geometry": {"coordinates":[8.3741788864,50.0830116272],"type":"Point"}
}