{
  "type": "Feature",
  "properties": {
    "iso:country":"DE",
    "sg:address":"Rentzelstr. 1",
    "sg:city":"Hamburg",
    "sg:phone":"+49 40/456018",
    "sg:postcode":"20146",
    "sg:province":"Hamburg",
    "wof:name":"Redaktion Forum Kritische Psychologie",
    "wof:placetype":"venue"
},
  "geometry": {"coordinates":[9.9808883667,53.5668296814],"type":"Point"}
}