{
  "type": "Feature",
  "properties": {
    "iso:country":"DE",
    "sg:address":"Wilhelm-Schreiber-Str. 18",
    "sg:city":"K\u00f6ln",
    "sg:phone":"+49 221/592766",
    "sg:postcode":"50827",
    "sg:province":"Nordrhein-Westfalen",
    "wof:name":"Rheingold-zug Betriebs Gmbh",
    "wof:placetype":"venue"
},
  "geometry": {"coordinates":[6.900124073,50.9687347412],"type":"Point"}
}