{
  "type": "Feature",
  "properties": {
    "iso:country":"DE",
    "sg:address":"Industriestr. 24",
    "sg:city":"Datteln",
    "sg:phone":"+49 2363/2360",
    "sg:postcode":"45711",
    "sg:province":"Nordrhein-Westfalen",
    "wof:name":"Wirtz Buch- Und Offsetdruck Inh. Ernst Schmidt",
    "wof:placetype":"venue"
},
  "geometry": {"coordinates":[7.3517589569,51.6682472229],"type":"Point"}
}