{
  "type": "Feature",
  "properties": {
    "iso:country":"DE",
    "sg:address":"Haugerpfarrgasse 9",
    "sg:city":"W\u00fcrzburg",
    "sg:phone":"+49 931/30805",
    "sg:postcode":"97070",
    "sg:province":"Bayern",
    "wof:name":"Bank Schilling & Co",
    "wof:placetype":"venue"
},
  "geometry": {"coordinates":[9.934951,49.797794],"type":"Point"}
}