{
  "type": "Feature",
  "properties": {
    "iso:country":"DE",
    "sg:address":"Peiffersweg 18",
    "sg:city":"Hamburg",
    "sg:phone":"+49 40/615963",
    "sg:postcode":"22307",
    "sg:province":"Hamburg",
    "wof:name":"Richard Hirrschoff Ofenbaumeister",
    "wof:placetype":"venue"
},
  "geometry": {"coordinates":[10.049779892,53.5930252075],"type":"Point"}
}