{
  "type": "Feature",
  "properties": {
    "iso:country":"DE",
    "sg:address":"Rosenweg 16",
    "sg:city":"Magdeburg",
    "sg:phone":"+49 391/6227064",
    "sg:postcode":"39120",
    "sg:province":"Sachsen-Anhalt",
    "wof:name":"Dr. Med. Friedr.-w. Onnasch",
    "wof:placetype":"venue"
},
  "geometry": {"coordinates":[11.628072,52.093319],"type":"Point"}
}