{
  "type": "Feature",
  "properties": {
    "iso:country":"DE",
    "sg:address":"Zum Schelderhoff 34",
    "sg:city":"Raesfeld",
    "sg:phone":"+49 2865/422",
    "sg:postcode":"46348",
    "sg:province":"Nordrhein-Westfalen",
    "wof:name":"Johannes Loker",
    "wof:placetype":"venue"
},
  "geometry": {"coordinates":[6.828322,51.75843],"type":"Point"}
}