{
  "type": "Feature",
  "properties": {
    "iso:country":"DE",
    "sg:address":"Reutenen 12",
    "sg:city":"Tettnang",
    "sg:phone":"+49 7542/7270",
    "sg:postcode":"88069",
    "sg:province":"Baden-W\u00fcrttemberg",
    "wof:name":"Herbert Kn\u00f6dler Elektroinstallation",
    "wof:placetype":"venue"
},
  "geometry": {"coordinates":[9.595286,47.652134],"type":"Point"}
}