{
  "type": "Feature",
  "properties": {
    "iso:country":"DE",
    "sg:address":"Keltenring 25",
    "sg:city":"Euskirchen",
    "sg:phone":"+49 2251/4023",
    "sg:postcode":"53879",
    "sg:province":"Nordrhein-Westfalen",
    "wof:name":"Marlene Filz Masseurin",
    "wof:placetype":"venue"
},
  "geometry": {"coordinates":[6.801008,50.663559],"type":"Point"}
}