{
  "type": "Feature",
  "properties": {
    "iso:country":"DE",
    "sg:address":"Im Graben",
    "sg:city":"Hohenfurch",
    "sg:postcode":"86978",
    "sg:province":"Bayern",
    "wof:name":"Sdh Schwedisch-deutsche Handels Gmbh",
    "wof:placetype":"venue"
},
  "geometry": {"coordinates":[10.919072,47.853687],"type":"Point"}
}