{
  "type": "Feature",
  "properties": {
    "iso:country":"DE",
    "sg:address":"Bergstr. 2",
    "sg:city":"K\u00fcnzelsau",
    "sg:phone":"+49 7940/170",
    "sg:postcode":"74653",
    "sg:province":"Baden-W\u00fcrttemberg",
    "wof:name":"R. Stahl Ag",
    "wof:placetype":"venue"
},
  "geometry": {"coordinates":[9.6847019196,49.2773780823],"type":"Point"}
}