{
  "type": "Feature",
  "properties": {
    "iso:country":"DE",
    "sg:address":"Lohengrinstr. 23",
    "sg:city":"N\u00fcrnberg",
    "sg:phone":"+49 911/492025",
    "sg:postcode":"90461",
    "sg:province":"Bayern",
    "wof:name":"G. Tausend",
    "wof:placetype":"venue"
},
  "geometry": {"coordinates":[11.100938,49.436268],"type":"Point"}
}