{
  "type": "Feature",
  "properties": {
    "iso:country":"DE",
    "sg:address":"Obere Burghalde 6",
    "sg:city":"Leonberg",
    "sg:phone":"+49 7152/25622",
    "sg:postcode":"71229",
    "sg:province":"Baden-W\u00fcrttemberg",
    "wof:name":"Karl Pluciak Steuerberater",
    "wof:placetype":"venue"
},
  "geometry": {"coordinates":[9.0209980011,48.8031997681],"type":"Point"}
}