{
  "type": "Feature",
  "properties": {
    "iso:country":"DE",
    "sg:address":"Martinstr. 8",
    "sg:city":"Bessenbach",
    "sg:phone":"+49 6095/559",
    "sg:postcode":"63856",
    "sg:province":"Bayern",
    "wof:name":"Helmut Hesbacher",
    "wof:placetype":"venue"
},
  "geometry": {"coordinates":[9.2497253418,49.963306427],"type":"Point"}
}