{
  "type": "Feature",
  "properties": {
    "iso:country":"DE",
    "sg:address":"Rudolf-Diesel-Str. 21",
    "sg:city":"M\u00fclheim-K\u00e4rlich",
    "sg:phone":"+49 2630/6032",
    "sg:postcode":"56218",
    "sg:province":"Rheinland-Pfalz",
    "wof:name":"Baugesellschaft M\u00fcller Gmbh",
    "wof:placetype":"venue"
},
  "geometry": {"coordinates":[7.518475,50.399822],"type":"Point"}
}