{
  "type": "Feature",
  "properties": {
    "iso:country":"DE",
    "sg:address":"Aukenberg 2",
    "sg:city":"Falkenstein",
    "sg:phone":"+49 9462/323",
    "sg:postcode":"93167",
    "sg:province":"Bayern",
    "wof:name":"Alois Spandel",
    "wof:placetype":"venue"
},
  "geometry": {"coordinates":[12.51786,49.077175],"type":"Point"}
}