{
  "type": "Feature",
  "properties": {
    "iso:country":"DE",
    "sg:address":"Am Kirchberg 61",
    "sg:city":"Karlsruhe",
    "sg:phone":"+49 721/468790",
    "sg:postcode":"76229",
    "sg:province":"Baden-W\u00fcrttemberg",
    "wof:name":"Sigrid Paulus Heilpraktiker",
    "wof:placetype":"venue"
},
  "geometry": {"coordinates":[8.5013246536,49.0019111633],"type":"Point"}
}