{
  "type": "Feature",
  "properties": {
    "iso:country":"DE",
    "sg:address":"Neuburger Str. 1",
    "sg:city":"Karlshuld",
    "sg:phone":"+49 8454/8247",
    "sg:postcode":"86668",
    "sg:province":"Bayern",
    "wof:name":"Da Treff",
    "wof:placetype":"venue"
},
  "geometry": {"coordinates":[11.2864627838,48.6824264526],"type":"Point"}
}