{
  "type": "Feature",
  "properties": {
    "iso:country":"DE",
    "sg:address":"Franz-Hartl-Str.",
    "sg:city":"Regensburg",
    "sg:phone":"+49 941/787800",
    "sg:postcode":"93053",
    "sg:province":"Bayern",
    "wof:name":"Hin & Mit",
    "wof:placetype":"venue"
},
  "geometry": {"coordinates":[12.1116104126,48.993888855],"type":"Point"}
}