{
  "type": "Feature",
  "properties": {
    "iso:country":"DE",
    "sg:address":"Altmarkt 2",
    "sg:city":"Ortrand",
    "sg:phone":"+49 35755/51416",
    "sg:postcode":"01990",
    "sg:province":"Brandenburg",
    "wof:name":"H\u00f6tzel",
    "wof:placetype":"venue"
},
  "geometry": {"coordinates":[13.7575054169,51.375919342],"type":"Point"}
}