{
  "type": "Feature",
  "properties": {
    "iso:country":"DE",
    "sg:address":"Frankenh\u00e4user Str. 6",
    "sg:city":"Ringleben",
    "sg:phone":"+49 3466/322274",
    "sg:postcode":"06556",
    "sg:province":"Th\u00fcringen",
    "wof:name":"Heidrun Allendorf",
    "wof:placetype":"venue"
},
  "geometry": {"coordinates":[11.2233028412,51.3670463562],"type":"Point"}
}