{
  "type": "Feature",
  "properties": {
    "iso:country":"DE",
    "sg:address":"Konrad-Adenauer-Allee",
    "sg:city":"Reichelsheim",
    "sg:phone":"+49 6164/54387",
    "sg:postcode":"64385",
    "sg:province":"Hessen",
    "wof:name":"Schwimmbad Reichelsheim",
    "wof:placetype":"venue"
},
  "geometry": {"coordinates":[8.8412675858,49.7133903503],"type":"Point"}
}