{
  "type": "Feature",
  "properties": {
    "iso:country":"DE",
    "sg:address":"Herrnstr. 1",
    "sg:city":"Reiskirchen",
    "sg:phone":"+49 6408/965787",
    "sg:postcode":"35447",
    "sg:province":"Hessen",
    "wof:name":"P. Fa\u00dfbender",
    "wof:placetype":"venue"
},
  "geometry": {"coordinates":[8.8491344452,50.5748786926],"type":"Point"}
}