{
  "type": "Feature",
  "properties": {
    "iso:country":"DE",
    "sg:address":"Vaihinger Str. 78",
    "sg:city":"Illingen",
    "sg:phone":"+49 7042/8888",
    "sg:postcode":"75428",
    "sg:province":"Baden-W\u00fcrttemberg",
    "wof:name":"Otto Ezel Gmbh Hausbau Und Immobilien",
    "wof:placetype":"venue"
},
  "geometry": {"coordinates":[8.926142,48.951496],"type":"Point"}
}