{
  "type": "Feature",
  "properties": {
    "iso:country":"DE",
    "sg:address":"Hauptstr. 13",
    "sg:city":"Kisselbach",
    "sg:phone":"+49 6766/960069",
    "sg:postcode":"56291",
    "sg:province":"Rheinland-Pfalz",
    "wof:name":"Michael Kessler",
    "wof:placetype":"venue"
},
  "geometry": {"coordinates":[7.61299,50.051147],"type":"Point"}
}