{
  "type": "Feature",
  "properties": {
    "iso:country":"DE",
    "sg:address":"Rathausplatz 9",
    "sg:city":"Esslingen",
    "sg:phone":"+49 711/357056",
    "sg:postcode":"73728",
    "sg:province":"Baden-W\u00fcrttemberg",
    "wof:name":"Rats-apotheke",
    "wof:placetype":"venue"
},
  "geometry": {"coordinates":[9.307982,48.742317],"type":"Point"}
}