{
  "type": "Feature",
  "properties": {
    "iso:country":"DE",
    "sg:address":"Putzbrunner Str. 47",
    "sg:city":"M\u00fcnchen",
    "sg:phone":"+49 89/6372942",
    "sg:postcode":"81739",
    "sg:province":"Bayern",
    "wof:name":"Winfried Haller",
    "wof:placetype":"venue"
},
  "geometry": {"coordinates":[11.6390924454,48.0984687805],"type":"Point"}
}