{
  "type": "Feature",
  "properties": {
    "iso:country":"DE",
    "sg:address":"Alt-Engelbostel 11",
    "sg:city":"Langenhagen",
    "sg:phone":"+49 511/743872",
    "sg:postcode":"30855",
    "sg:province":"Niedersachsen",
    "wof:name":"Dea-tankstelle",
    "wof:placetype":"venue"
},
  "geometry": {"coordinates":[9.6499500275,52.446811676],"type":"Point"}
}