{
  "type": "Feature",
  "properties": {
    "iso:country":"DE",
    "sg:address":"Alleestr. 95",
    "sg:city":"Oberhausen",
    "sg:phone":"+49 208/842838",
    "sg:postcode":"46049",
    "sg:province":"Nordrhein-Westfalen",
    "wof:name":"Elke T\u00f6gel",
    "wof:placetype":"venue"
},
  "geometry": {"coordinates":[6.8334021568,51.4702224731],"type":"Point"}
}