{
  "type": "Feature",
  "properties": {
    "iso:country":"DE",
    "sg:address":"Eichenstr. 120",
    "sg:city":"Hilden",
    "sg:phone":"+49 2103/55512",
    "sg:postcode":"40721",
    "sg:province":"Nordrhein-Westfalen",
    "wof:name":"Hans-dieter G\u00f6thling",
    "wof:placetype":"venue"
},
  "geometry": {"coordinates":[6.9068341255,51.1637382507],"type":"Point"}
}