{
  "type": "Feature",
  "properties": {
    "iso:country":"DE",
    "sg:address":"Bergerstr. 45",
    "sg:city":"Wesseling",
    "sg:phone":"+49 2232/51972",
    "sg:postcode":"50389",
    "sg:province":"Nordrhein-Westfalen",
    "wof:name":"G. Spichala Ingenieur",
    "wof:placetype":"venue"
},
  "geometry": {"coordinates":[6.9449081421,50.8263473511],"type":"Point"}
}