{
  "type": "Feature",
  "properties": {
    "iso:country":"DE",
    "sg:address":"Kiefernweg 11",
    "sg:city":"Ostbevern",
    "sg:phone":"+49 2532/90510",
    "sg:postcode":"48346",
    "sg:province":"Nordrhein-Westfalen",
    "wof:name":"Hubert Schmack Steuerberater",
    "wof:placetype":"venue"
},
  "geometry": {"coordinates":[7.8446860313,52.0407485962],"type":"Point"}
}