{
  "type": "Feature",
  "properties": {
    "iso:country":"DE",
    "sg:address":"Hochweg 13a",
    "sg:city":"Regensburg",
    "sg:phone":"+49 941/27443",
    "sg:postcode":"93049",
    "sg:province":"Bayern",
    "wof:name":"Dr. Theo Popp Rechtsanwalt",
    "wof:placetype":"venue"
},
  "geometry": {"coordinates":[12.0768661499,49.0206642151],"type":"Point"}
}