{
  "type": "Feature",
  "properties": {
    "iso:country":"DE",
    "sg:address":"H\u00f6cklingser Weg 3",
    "sg:city":"Hemer",
    "sg:phone":"+49 2372/12679",
    "sg:postcode":"58675",
    "sg:province":"Nordrhein-Westfalen",
    "wof:name":"Akropolis",
    "wof:placetype":"venue"
},
  "geometry": {"coordinates":[7.7686271667,51.3918266296],"type":"Point"}
}