{
  "type": "Feature",
  "properties": {
    "iso:country":"DE",
    "sg:address":"Hammer Str. 28",
    "sg:city":"D\u00fcsseldorf",
    "sg:phone":"+49 211/305400",
    "sg:postcode":"40219",
    "sg:province":"Nordrhein-Westfalen",
    "wof:name":"Karl-josef Kuhn",
    "wof:placetype":"venue"
},
  "geometry": {"coordinates":[6.756563,51.214741],"type":"Point"}
}