{
  "type": "Feature",
  "properties": {
    "iso:country":"DE",
    "sg:address":"Hagenstr. 1",
    "sg:city":"Cloppenburg",
    "sg:phone":"+49 4471/3213",
    "sg:postcode":"49661",
    "sg:province":"Niedersachsen",
    "wof:name":"Bernhard L\u00fcbbe Rechtsanwalt",
    "wof:placetype":"venue"
},
  "geometry": {"coordinates":[8.0478658676,52.846157074],"type":"Point"}
}