{
  "type": "Feature",
  "properties": {
    "iso:country":"DE",
    "sg:address":"Jungfernstieg",
    "sg:city":"Hamburg",
    "sg:phone":"+49 40/346736",
    "sg:postcode":"20095",
    "sg:province":"Hamburg",
    "wof:name":"Bistro",
    "wof:placetype":"venue"
},
  "geometry": {"coordinates":[9.9944095612,53.5520439148],"type":"Point"}
}