{
  "type": "Feature",
  "properties": {
    "iso:country":"DE",
    "sg:address":"Burtscheider Markt 14-16",
    "sg:city":"Aachen",
    "sg:phone":"+49 241/600000",
    "sg:postcode":"52066",
    "sg:province":"Nordrhein-Westfalen",
    "wof:name":"Hotel Burtscheider Markt",
    "wof:placetype":"venue"
},
  "geometry": {"coordinates":[6.0920948982,50.7631759644],"type":"Point"}
}