{
  "type": "Feature",
  "properties": {
    "iso:country":"DE",
    "sg:address":"Merscheider Busch 49",
    "sg:city":"Solingen",
    "sg:phone":"+49 212/333443",
    "sg:postcode":"42699",
    "sg:province":"Nordrhein-Westfalen",
    "wof:name":"Scherenh\u00e4rterei L\u00f6hr Gmbh",
    "wof:placetype":"venue"
},
  "geometry": {"coordinates":[7.0252418518,51.1637191772],"type":"Point"}
}