{
  "type": "Feature",
  "properties": {
    "iso:country":"DE",
    "sg:address":"Kaiserstr. 71",
    "sg:city":"Gummersbach",
    "sg:postcode":"51643",
    "sg:province":"Nordrhein-Westfalen",
    "wof:name":"Do It Uessem Gmbh",
    "wof:placetype":"venue"
},
  "geometry": {"coordinates":[7.5601887703,51.0284347534],"type":"Point"}
}