{
  "type": "Feature",
  "properties": {
    "iso:country":"DE",
    "sg:address":"Comburgstr. 31/1",
    "sg:city":"Bad Friedrichshall",
    "sg:postcode":"74177",
    "sg:province":"Baden-W\u00fcrttemberg",
    "wof:name":"Reiserschnittgarten Weinsberg Gmbh",
    "wof:placetype":"venue"
},
  "geometry": {"coordinates":[9.222593,49.266701],"type":"Point"}
}