{
  "type": "Feature",
  "properties": {
    "iso:country":"DE",
    "sg:address":"Michaelisstr. 2",
    "sg:city":"Bad Salzungen",
    "sg:postcode":"36433",
    "sg:province":"Th\u00fcringen",
    "wof:name":"Auslese-bild-verlag Inh. G\u00fcnter Burghard",
    "wof:placetype":"venue"
},
  "geometry": {"coordinates":[10.2357521057,50.8134002686],"type":"Point"}
}