{
  "type": "Feature",
  "properties": {
    "iso:country":"DE",
    "sg:address":"Vaihinger Str. 43",
    "sg:city":"Stuttgart",
    "sg:postcode":"70567",
    "sg:province":"Baden-W\u00fcrttemberg",
    "wof:name":"Panta Rhei Ag",
    "wof:placetype":"venue"
},
  "geometry": {"coordinates":[9.1471948624,48.7281303406],"type":"Point"}
}