{
  "type": "Feature",
  "properties": {
    "iso:country":"DE",
    "sg:address":"Reuterstr. 241",
    "sg:city":"Bonn",
    "sg:phone":"+49 228/214265",
    "sg:postcode":"53113",
    "sg:province":"Nordrhein-Westfalen",
    "wof:name":"Center-apotheke",
    "wof:placetype":"venue"
},
  "geometry": {"coordinates":[7.116449,50.719276],"type":"Point"}
}