{
  "type": "Feature",
  "properties": {
    "iso:country":"DE",
    "sg:address":"Biewerer Str. 193",
    "sg:city":"Trier",
    "sg:phone":"+49 651/968070",
    "sg:postcode":"54293",
    "sg:province":"Rheinland-Pfalz",
    "wof:name":"W. Schwind Und H. Krajewski",
    "wof:placetype":"venue"
},
  "geometry": {"coordinates":[6.6707348824,49.7829551697],"type":"Point"}
}