{
  "type": "Feature",
  "properties": {
    "iso:country":"DE",
    "sg:address":"Berliner Str. 21",
    "sg:city":"Zehlendorf",
    "sg:phone":"+49 172 3225299",
    "sg:postcode":"16515",
    "sg:province":"Brandenburg",
    "wof:name":"Olaf Jarnack",
    "wof:placetype":"venue"
},
  "geometry": {"coordinates":[13.24443,52.756378],"type":"Point"}
}