{
  "type": "Feature",
  "properties": {
    "iso:country":"DE",
    "sg:address":"Langestr. 2",
    "sg:city":"B\u00fctzow",
    "sg:phone":"+49 38461/2871",
    "sg:postcode":"18246",
    "sg:province":"Mecklenburg-Vorpommern",
    "wof:name":"Eiscafe Gisela Frahm",
    "wof:placetype":"venue"
},
  "geometry": {"coordinates":[11.986566,53.847504],"type":"Point"}
}