{
  "type": "Feature",
  "properties": {
    "iso:country":"DE",
    "sg:address":"Sch\u00fctzenhofstr. 91",
    "sg:city":"Jena",
    "sg:phone":"+49 3641/823111",
    "sg:postcode":"07743",
    "sg:province":"Th\u00fcringen",
    "wof:name":"Rolf-gerd Pfeiffer Patentanwalt",
    "wof:placetype":"venue"
},
  "geometry": {"coordinates":[11.601773262,50.9508323669],"type":"Point"}
}