{
  "type": "Feature",
  "properties": {
    "iso:country":"DE",
    "sg:address":"R\u00f6tlen",
    "sg:city":"Ellwangen",
    "sg:phone":"+49 7965/477",
    "sg:postcode":"73479",
    "sg:province":"Baden-W\u00fcrttemberg",
    "wof:name":"Otto Gruber",
    "wof:placetype":"venue"
},
  "geometry": {"coordinates":[10.218335,48.944408],"type":"Point"}
}