{
  "type": "Feature",
  "properties": {
    "iso:country":"DE",
    "sg:address":"Altkirchener Str. 8",
    "sg:city":"Schm\u00f6lln",
    "sg:phone":"+49 34491/22252",
    "sg:postcode":"04626",
    "sg:province":"Th\u00fcringen",
    "wof:name":"Thomas Elektrow\u00e4rme Gmbh",
    "wof:placetype":"venue"
},
  "geometry": {"coordinates":[12.3499994278,50.911403656],"type":"Point"}
}