{
  "type": "Feature",
  "properties": {
    "iso:country":"DE",
    "sg:address":"Bergstr. 3",
    "sg:city":"Beckedorf",
    "sg:phone":"+49 5725/913356",
    "sg:postcode":"31699",
    "sg:province":"Niedersachsen",
    "wof:name":"Gaus",
    "wof:placetype":"venue"
},
  "geometry": {"coordinates":[9.316645,52.338966],"type":"Point"}
}