{
  "type": "Feature",
  "properties": {
    "iso:country":"DE",
    "sg:address":"M\u00e4rkische Strasse",
    "sg:city":"Dabendorf",
    "sg:phone":"+49 3377/300127",
    "sg:postcode":"15806",
    "sg:province":"Brandenburg",
    "wof:name":"Daweba Dabendorfer Werkzeugbau Gmbh",
    "wof:placetype":"venue"
},
  "geometry": {"coordinates":[13.42486,52.245785],"type":"Point"}
}