{
  "type": "Feature",
  "properties": {
    "iso:country":"DE",
    "sg:address":"Ulmenstr. 8",
    "sg:city":"Germersheim",
    "sg:phone":"+49 7274/4183",
    "sg:postcode":"76726",
    "sg:province":"Rheinland-Pfalz",
    "wof:name":"D. Und P. Richter",
    "wof:placetype":"venue"
},
  "geometry": {"coordinates":[8.352369,49.199333],"type":"Point"}
}