{
  "type": "Feature",
  "properties": {
    "iso:country":"DE",
    "sg:address":"Sch\u00f6ne Aussicht 10",
    "sg:city":"Winterborn",
    "sg:postcode":"67822",
    "sg:province":"Rheinland-Pfalz",
    "wof:name":"B & M Gestaltungs Gmbh Design Planung Und Ausf\u00fchrung",
    "wof:placetype":"venue"
},
  "geometry": {"coordinates":[7.8613128662,49.7450561523],"type":"Point"}
}