{
  "type": "Feature",
  "properties": {
    "iso:country":"DE",
    "sg:address":"Karlstr. 2-4",
    "sg:city":"Tettnang",
    "sg:phone":"+49 7542/530200",
    "sg:postcode":"88069",
    "sg:province":"Baden-W\u00fcrttemberg",
    "wof:name":"Hotel-restaurant Ritter",
    "wof:placetype":"venue"
},
  "geometry": {"coordinates":[9.5876760483,47.6692085266],"type":"Point"}
}