{
  "type": "Feature",
  "properties": {
    "iso:country":"DE",
    "sg:address":"Elsestr. 179",
    "sg:city":"Kirchlengern",
    "sg:phone":"+49 5223/84047",
    "sg:postcode":"32278",
    "sg:province":"Nordrhein-Westfalen",
    "wof:name":"S. L\u00fclf",
    "wof:placetype":"venue"
},
  "geometry": {"coordinates":[8.644409,52.191906],"type":"Point"}
}