{
  "type": "Feature",
  "properties": {
    "iso:country":"DE",
    "sg:address":"Schillerstr. 22",
    "sg:city":"Norderstedt",
    "sg:phone":"+49 40/5235389",
    "sg:postcode":"22848",
    "sg:province":"Schleswig-Holstein",
    "wof:name":"Manfred Niese",
    "wof:placetype":"venue"
},
  "geometry": {"coordinates":[9.980957,53.679398],"type":"Point"}
}