{
  "type": "Feature",
  "properties": {
    "iso:country":"DE",
    "sg:address":"K\u00f6nigstr. 50",
    "sg:city":"Br\u00fcggen",
    "sg:phone":"+49 2157/7666",
    "sg:postcode":"41379",
    "sg:province":"Nordrhein-Westfalen",
    "wof:name":"O. Becker",
    "wof:placetype":"venue"
},
  "geometry": {"coordinates":[6.1946759224,51.283531189],"type":"Point"}
}