{
  "type": "Feature",
  "properties": {
    "iso:country":"DE",
    "sg:address":"Am Steenblenk 1 a",
    "sg:city":"J\u00fcchen",
    "sg:phone":"+49 2181/43238",
    "sg:postcode":"41363",
    "sg:province":"Nordrhein-Westfalen",
    "wof:name":"Brigitte Schmitt Steuerbevollm\u00e4chtigte",
    "wof:placetype":"venue"
},
  "geometry": {"coordinates":[6.5486531258,51.1046943665],"type":"Point"}
}