{
  "type": "Feature",
  "properties": {
    "iso:country":"DE",
    "sg:address":"Dorneystr. 64",
    "sg:city":"Dortmund",
    "sg:phone":"+49 231/651678",
    "sg:postcode":"44149",
    "sg:province":"Nordrhein-Westfalen",
    "wof:name":"Gastst\u00e4tte Dorney-stuben",
    "wof:placetype":"venue"
},
  "geometry": {"coordinates":[7.3689818382,51.4838294983],"type":"Point"}
}