{
  "type": "Feature",
  "properties": {
    "iso:country":"DE",
    "sg:address":"Borchtitz",
    "sg:city":"Lietzow",
    "sg:phone":"+49 38392/23750",
    "sg:postcode":"18528",
    "sg:province":"Mecklenburg-Vorpommern",
    "wof:name":"R\u00fcgener Ladenbau Gmbh",
    "wof:placetype":"venue"
},
  "geometry": {"coordinates":[13.530025,54.50346],"type":"Point"}
}