{
  "type": "Feature",
  "properties": {
    "iso:country":"DE",
    "sg:address":"Obere Marktstr. 12",
    "sg:city":"Bad Sulza",
    "sg:phone":"+49 36461/20201",
    "sg:postcode":"99518",
    "sg:province":"Th\u00fcringen",
    "wof:name":"Apotheke Im Heylandhaus",
    "wof:placetype":"venue"
},
  "geometry": {"coordinates":[11.622938,51.088078],"type":"Point"}
}