{
  "type": "Feature",
  "properties": {
    "iso:country":"DE",
    "sg:address":"Flurstr. 18a",
    "sg:city":"Aurachtal",
    "sg:phone":"+49 9132/62909",
    "sg:postcode":"91086",
    "sg:province":"Bayern",
    "wof:name":"Max Telorack",
    "wof:placetype":"venue"
},
  "geometry": {"coordinates":[10.849523,49.57822],"type":"Point"}
}