{
  "type": "Feature",
  "properties": {
    "iso:country":"DE",
    "sg:address":"Schlei\u00dfheimer Str. 263",
    "sg:city":"M\u00fcnchen",
    "sg:phone":"+49 89/352315",
    "sg:postcode":"80809",
    "sg:province":"Bayern",
    "wof:name":"Bayerische Vereinsbank Ag",
    "wof:placetype":"venue"
},
  "geometry": {"coordinates":[11.566986,48.179504],"type":"Point"}
}