{
  "type": "Feature",
  "properties": {
    "iso:country":"DE",
    "sg:address":"Gr\u00fcnberger Str. 14",
    "sg:city":"Gie\u00dfen",
    "sg:postcode":"35390",
    "sg:province":"Hessen",
    "wof:name":"Gispo-sportmarketing Gesellschaft Gie\u00dfen Mbh",
    "wof:placetype":"venue"
},
  "geometry": {"coordinates":[8.6832056046,50.5833053589],"type":"Point"}
}