{
  "type": "Feature",
  "properties": {
    "iso:country":"DE",
    "sg:address":"Gartenstr. 45",
    "sg:city":"Asbach-B\u00e4umenheim",
    "sg:phone":"+49 906/91892",
    "sg:postcode":"86663",
    "sg:province":"Bayern",
    "wof:name":"Ambos Gmbh",
    "wof:placetype":"venue"
},
  "geometry": {"coordinates":[10.815397,48.684765],"type":"Point"}
}