{
  "type": "Feature",
  "properties": {
    "iso:country":"DE",
    "sg:address":"An den Vier Ruten 24a",
    "sg:city":"Blankenfelde",
    "sg:phone":"+49 3379/371076",
    "sg:postcode":"15827",
    "sg:province":"Brandenburg",
    "wof:name":"Licht- Und Kraftanlagen Hc Gmbh",
    "wof:placetype":"venue"
},
  "geometry": {"coordinates":[13.403743,52.333271],"type":"Point"}
}