{
  "type": "Feature",
  "properties": {
    "iso:country":"DE",
    "sg:address":"Schankstr. 23",
    "sg:city":"Merzig",
    "sg:phone":"+49 6861/88585",
    "sg:postcode":"66663",
    "sg:province":"Saarland",
    "wof:name":"Schlo\u00df-apotheke",
    "wof:placetype":"venue"
},
  "geometry": {"coordinates":[6.636206,49.441441],"type":"Point"}
}