{
  "type": "Feature",
  "properties": {
    "iso:country":"DE",
    "sg:address":"B\u00fcrgermeister-Keller-Str. 1",
    "sg:city":"Buchen",
    "sg:phone":"+49 6281/4563",
    "sg:postcode":"74722",
    "sg:province":"Baden-W\u00fcrttemberg",
    "wof:name":"Emil Sch\u00fcssler Gmbh",
    "wof:placetype":"venue"
},
  "geometry": {"coordinates":[9.3272399902,49.5231895447],"type":"Point"}
}