{
  "type": "Feature",
  "properties": {
    "iso:country":"DE",
    "sg:address":"Roskaul 12",
    "sg:city":"Baesweiler",
    "sg:phone":"+49 2401/4224",
    "sg:postcode":"52499",
    "sg:province":"Nordrhein-Westfalen",
    "wof:name":"Norbert Gerhards Steuerberater",
    "wof:placetype":"venue"
},
  "geometry": {"coordinates":[6.1806287766,50.9063453674],"type":"Point"}
}