{
  "type": "Feature",
  "properties": {
    "iso:country":"DE",
    "sg:address":"Ludgeristr. 88",
    "sg:city":"M\u00fcnster",
    "sg:postcode":"48143",
    "sg:province":"Nordrhein-Westfalen",
    "wof:name":"S Consult Gesellschaft F\u00fcr Management Und",
    "wof:placetype":"venue"
},
  "geometry": {"coordinates":[7.6272931099,51.9597434998],"type":"Point"}
}