{
  "type": "Feature",
  "properties": {
    "iso:country":"DE",
    "sg:address":"August-Bebel-Str. 26",
    "sg:city":"Geyer",
    "sg:phone":"+49 37346/1497",
    "sg:postcode":"09468",
    "sg:province":"Sachsen",
    "wof:name":"Edelwei\u00df Blumen Und Handels Gmbh",
    "wof:placetype":"venue"
},
  "geometry": {"coordinates":[12.921148,50.625942],"type":"Point"}
}