{
  "type": "Feature",
  "properties": {
    "iso:country":"DE",
    "sg:address":"Bahnhofstr. 14",
    "sg:city":"Bad Camberg",
    "sg:phone":"+49 6434/8545",
    "sg:postcode":"65520",
    "sg:province":"Hessen",
    "wof:name":"H. Hunkeler",
    "wof:placetype":"venue"
},
  "geometry": {"coordinates":[8.264449,50.29763],"type":"Point"}
}