{
  "type": "Feature",
  "properties": {
    "iso:country":"DE",
    "sg:address":"Pfleggasse 19",
    "sg:city":"Deggendorf",
    "sg:phone":"+49 991/6269",
    "sg:postcode":"94469",
    "sg:province":"Bayern",
    "wof:name":"K\u00e4the Eiter Inh. Mathilde Hastreiter",
    "wof:placetype":"venue"
},
  "geometry": {"coordinates":[12.9638738632,48.8336753845],"type":"Point"}
}