{
  "type": "Feature",
  "properties": {
    "iso:country":"DE",
    "sg:address":"Zittelstr. 4",
    "sg:city":"M\u00fcnchen",
    "sg:phone":"+49 89/3006630",
    "sg:postcode":"80796",
    "sg:province":"Bayern",
    "wof:name":"Gaby Bzdega Kameraassistentin",
    "wof:placetype":"venue"
},
  "geometry": {"coordinates":[11.5724868774,48.1617889404],"type":"Point"}
}