{
  "type": "Feature",
  "properties": {
    "iso:country":"DE",
    "sg:address":"B\u00f6rderstich 3f",
    "sg:city":"Kampen",
    "sg:phone":"+49 4651/42411",
    "sg:postcode":"25999",
    "sg:province":"Schleswig-Holstein",
    "wof:name":"Klaus Schneider",
    "wof:placetype":"venue"
},
  "geometry": {"coordinates":[8.344417572,54.9491348267],"type":"Point"}
}