{
  "type": "Feature",
  "properties": {
    "iso:country":"DE",
    "sg:address":"Heusenstammer Weg",
    "sg:city":"Rodgau",
    "sg:phone":"+49 6106/71108",
    "sg:postcode":"63110",
    "sg:province":"Hessen",
    "wof:name":"Sch\u00fcttler Gmbh & Co Kg",
    "wof:placetype":"venue"
},
  "geometry": {"coordinates":[8.8303604126,50.0333595276],"type":"Point"}
}