{
  "type": "Feature",
  "properties": {
    "iso:country":"DE",
    "sg:address":"Tesdorpfstr. 16",
    "sg:city":"Hamburg",
    "sg:phone":"+49 40",
    "sg:postcode":"20148",
    "sg:province":"Hamburg",
    "wof:name":"Jagd Schloss Bellin - Apartmenthotel Events",
    "wof:placetype":"venue"
},
  "geometry": {"coordinates":[9.993726,53.564587],"type":"Point"}
}