{
  "type": "Feature",
  "properties": {
    "iso:country":"DE",
    "sg:address":"Rennstr. 1",
    "sg:city":"Westerngrund",
    "sg:phone":"+49 6024/2969",
    "sg:postcode":"63825",
    "sg:province":"Bayern",
    "wof:name":"H. M\u00fcller",
    "wof:placetype":"venue"
},
  "geometry": {"coordinates":[9.23837,50.115131],"type":"Point"}
}