{
  "type": "Feature",
  "properties": {
    "iso:country":"DE",
    "sg:address":"La-Villedieu-Ring 30",
    "sg:city":"Wachtberg",
    "sg:phone":"+49 228/9343431",
    "sg:postcode":"53343",
    "sg:province":"Nordrhein-Westfalen",
    "wof:name":"A. Gendziorra",
    "wof:placetype":"venue"
},
  "geometry": {"coordinates":[7.1302452087,50.6206970215],"type":"Point"}
}