{
  "type": "Feature",
  "properties": {
    "iso:country":"DE",
    "sg:address":"Havelstr. 3",
    "sg:city":"Oranienburg",
    "sg:phone":"+49 3301/3544",
    "sg:postcode":"16515",
    "sg:province":"Brandenburg",
    "wof:name":"Havelst\u00fcbchen",
    "wof:placetype":"venue"
},
  "geometry": {"coordinates":[13.237695694,52.7520332336],"type":"Point"}
}