{
  "type": "Feature",
  "properties": {
    "iso:country":"DE",
    "sg:address":"Graftstr. 1",
    "sg:city":"Langenberg",
    "sg:postcode":"33449",
    "sg:province":"Nordrhein-Westfalen",
    "wof:name":"Franz Unkr\u00f6er",
    "wof:placetype":"venue"
},
  "geometry": {"coordinates":[8.347105,51.745506],"type":"Point"}
}