{
  "type": "Feature",
  "properties": {
    "iso:country":"DE",
    "sg:address":"Grengeler Mauspfad 59",
    "sg:city":"K\u00f6ln",
    "sg:phone":"+49 2203/64681",
    "sg:postcode":"51147",
    "sg:province":"Nordrhein-Westfalen",
    "wof:name":"Wilhelm Becker",
    "wof:placetype":"venue"
},
  "geometry": {"coordinates":[7.10617,50.880371],"type":"Point"}
}