{
  "type": "Feature",
  "properties": {
    "iso:country":"DE",
    "sg:address":"Meisenstr. 23",
    "sg:city":"N\u00fcrnberg",
    "sg:phone":"+49 911/412813",
    "sg:postcode":"90443",
    "sg:province":"Bayern",
    "wof:name":"Heinrich Hartl Ingenieur",
    "wof:placetype":"venue"
},
  "geometry": {"coordinates":[11.0640878677,49.4301109314],"type":"Point"}
}