{
  "type": "Feature",
  "properties": {
    "iso:country":"DE",
    "sg:address":"Paulinerstr. 1",
    "sg:city":"Erden",
    "sg:phone":"+49 6532/2227",
    "sg:postcode":"54492",
    "sg:province":"Rheinland-Pfalz",
    "wof:name":"Georg Hanio Hotel",
    "wof:placetype":"venue"
},
  "geometry": {"coordinates":[7.0254349709,49.9793281555],"type":"Point"}
}