{
  "type": "Feature",
  "properties": {
    "iso:country":"DE",
    "sg:address":"Fichtenstr. 4",
    "sg:city":"Fridolfing",
    "sg:phone":"+49 8684/9138",
    "sg:postcode":"83413",
    "sg:province":"Bayern",
    "wof:name":"Hopf",
    "wof:placetype":"venue"
},
  "geometry": {"coordinates":[12.819205,47.99979],"type":"Point"}
}