{
  "type": "Feature",
  "properties": {
    "iso:country":"DE",
    "sg:address":"Erbacher Str. 31",
    "sg:city":"Beerfelden",
    "sg:phone":"+49 6068/1350",
    "sg:postcode":"64743",
    "sg:province":"Hessen",
    "wof:name":"Otto Daum",
    "wof:placetype":"venue"
},
  "geometry": {"coordinates":[8.9757099152,49.5663261414],"type":"Point"}
}