{
  "type": "Feature",
  "properties": {
    "iso:country":"DE",
    "sg:address":"Bruno-B\u00fcrgel-Weg 122-140",
    "sg:city":"Berlin",
    "sg:postcode":"12439",
    "sg:province":"Berlin",
    "wof:name":"Zeta Druckbeh\u00e4lter Gmbh",
    "wof:placetype":"venue"
},
  "geometry": {"coordinates":[13.546618,52.45377],"type":"Point"}
}