{
  "type": "Feature",
  "properties": {
    "iso:country":"DE",
    "sg:address":"Speicker Str. 13",
    "sg:city":"M\u00f6nchengladbach",
    "sg:phone":"+49 2161/936900",
    "sg:postcode":"41061",
    "sg:province":"Nordrhein-Westfalen",
    "wof:name":"Signal Unfallversicherung Ag",
    "wof:placetype":"venue"
},
  "geometry": {"coordinates":[6.4321942329,51.1904983521],"type":"Point"}
}