{
  "type": "Feature",
  "properties": {
    "iso:country":"DE",
    "sg:address":"Moggaster Hauptstr. 8",
    "sg:city":"Ebermannstadt",
    "sg:postcode":"91320",
    "sg:province":"Bayern",
    "wof:name":"Ts Betriebs- Und Verlags Gmbh",
    "wof:placetype":"venue"
},
  "geometry": {"coordinates":[11.2605018616,49.7688293457],"type":"Point"}
}