{
  "type": "Feature",
  "properties": {
    "iso:country":"DE",
    "sg:address":"Bogenstr. 2",
    "sg:city":"Siegen",
    "sg:phone":"+49 271/351502",
    "sg:postcode":"57080",
    "sg:province":"Nordrhein-Westfalen",
    "wof:name":"Manfred Gotthardt",
    "wof:placetype":"venue"
},
  "geometry": {"coordinates":[7.9746007919,50.8458976746],"type":"Point"}
}