{
  "type": "Feature",
  "properties": {
    "iso:country":"DE",
    "sg:address":"Niederbornstr. 42",
    "sg:city":"Frankfurt",
    "sg:phone":"+49 69/549506",
    "sg:postcode":"60435",
    "sg:province":"Hessen",
    "wof:name":"K\u00f6hler Hoch- Tief- Und Wasserbau Gmbh",
    "wof:placetype":"venue"
},
  "geometry": {"coordinates":[8.680535,50.153187],"type":"Point"}
}