{
  "type": "Feature",
  "properties": {
    "iso:country":"DE",
    "sg:address":"Bergweg 11",
    "sg:city":"Bonn",
    "sg:phone":"+49 228/4797747",
    "sg:postcode":"53225",
    "sg:province":"Nordrhein-Westfalen",
    "wof:name":"Kundalini-yoga",
    "wof:placetype":"venue"
},
  "geometry": {"coordinates":[7.120748,50.733265],"type":"Point"}
}