{
  "type": "Feature",
  "properties": {
    "iso:country":"DE",
    "sg:address":"Burgstr. 4",
    "sg:city":"Freudenburg",
    "sg:phone":"+49 6582/257",
    "sg:postcode":"54450",
    "sg:province":"Rheinland-Pfalz",
    "wof:name":"Zum K\u00f6nig Johann",
    "wof:placetype":"venue"
},
  "geometry": {"coordinates":[6.5330147743,49.5415649414],"type":"Point"}
}