{
  "type": "Feature",
  "properties": {
    "iso:country":"DE",
    "sg:address":"Astruper Str. 6",
    "sg:city":"Visbek",
    "sg:phone":"+49 4445/96600",
    "sg:postcode":"49429",
    "sg:province":"Niedersachsen",
    "wof:name":"Krogmann Und Partner",
    "wof:placetype":"venue"
},
  "geometry": {"coordinates":[8.3097991943,52.8346786499],"type":"Point"}
}