{
  "type": "Feature",
  "properties": {
    "iso:country":"DE",
    "sg:address":"Niederlosheimer Weg 5",
    "sg:city":"Weiskirchen",
    "sg:phone":"+49 6872/1785",
    "sg:postcode":"66709",
    "sg:province":"Saarland",
    "wof:name":"M. Barbian Wettannahme",
    "wof:placetype":"venue"
},
  "geometry": {"coordinates":[6.796852,49.538708],"type":"Point"}
}