{
  "type": "Feature",
  "properties": {
    "iso:country":"DE",
    "sg:address":"Chemnitzer Str. 5",
    "sg:city":"Meerane",
    "sg:phone":"+49 3764/4655",
    "sg:postcode":"08393",
    "sg:province":"Sachsen",
    "wof:name":"R. M\u00fcller",
    "wof:placetype":"venue"
},
  "geometry": {"coordinates":[12.471176,50.847801],"type":"Point"}
}