{
  "type": "Feature",
  "properties": {
    "iso:country":"DE",
    "sg:address":"Laubacherstr. 7",
    "sg:city":"Mindelheim",
    "sg:phone":"+49 8261/76410",
    "sg:postcode":"87719",
    "sg:province":"Bayern",
    "wof:name":"Sicor Gmbh",
    "wof:placetype":"venue"
},
  "geometry": {"coordinates":[10.4903297424,48.0450668335],"type":"Point"}
}