{
  "type": "Feature",
  "properties": {
    "iso:country":"DE",
    "sg:address":"Teichvorstadt 3",
    "sg:city":"Altenburg",
    "sg:phone":"+49 3447/314006",
    "sg:postcode":"04600",
    "sg:province":"Th\u00fcringen",
    "wof:name":"Gerhard Vontra",
    "wof:placetype":"venue"
},
  "geometry": {"coordinates":[12.43724,50.982368],"type":"Point"}
}