{
  "type": "Feature",
  "properties": {
    "iso:country":"DE",
    "sg:address":"Im Neuenb\u00fchl 12",
    "sg:city":"Weissach",
    "sg:phone":"+49 7044/93130",
    "sg:postcode":"71287",
    "sg:province":"Baden-W\u00fcrttemberg",
    "wof:name":"Kmc Management Consulting Gmbh",
    "wof:placetype":"venue"
},
  "geometry": {"coordinates":[8.91037,48.823086],"type":"Point"}
}