{
  "type": "Feature",
  "properties": {
    "iso:country":"DE",
    "sg:address":"K\u00f6lner Str. 16",
    "sg:city":"Altenkirchen",
    "sg:phone":"+49 2681/70595",
    "sg:postcode":"57610",
    "sg:province":"Rheinland-Pfalz",
    "wof:name":"Ursula Sch\u00e4fer",
    "wof:placetype":"venue"
},
  "geometry": {"coordinates":[7.64014,50.686626],"type":"Point"}
}