{
  "type": "Feature",
  "properties": {
    "iso:country":"DE",
    "sg:address":"Am Haarstrang Nordseite",
    "sg:city":"Werl",
    "sg:postcode":"59457",
    "sg:province":"Nordrhein-Westfalen",
    "wof:name":"Rainer Schmaler Bundesautobahntankstelle",
    "wof:placetype":"venue"
},
  "geometry": {"coordinates":[7.9123048782,51.5568847656],"type":"Point"}
}