{
  "type": "Feature",
  "properties": {
    "iso:country":"DE",
    "sg:address":"Frankstr. 141",
    "sg:city":"Pforzheim",
    "sg:phone":"+49 7231/440188",
    "sg:postcode":"75172",
    "sg:province":"Baden-W\u00fcrttemberg",
    "wof:name":"Schwarzwalds\u00e4ngerhalle",
    "wof:placetype":"venue"
},
  "geometry": {"coordinates":[8.6713142395,48.891368866],"type":"Point"}
}