{
  "type": "Feature",
  "properties": {
    "iso:country":"DE",
    "sg:address":"Nordkanalstr. 58",
    "sg:city":"Hamburg",
    "sg:postcode":"20097",
    "sg:province":"Hamburg",
    "wof:name":"Zietz Consulting Gmbh",
    "wof:placetype":"venue"
},
  "geometry": {"coordinates":[10.0248889923,53.5507545471],"type":"Point"}
}