{
  "type": "Feature",
  "properties": {
    "iso:country":"DE",
    "sg:address":"Gartenstr. 7a",
    "sg:city":"Kemberg",
    "sg:phone":"+49 34921/20486",
    "sg:postcode":"06901",
    "sg:province":"Sachsen-Anhalt",
    "wof:name":"Ernst Stahl",
    "wof:placetype":"venue"
},
  "geometry": {"coordinates":[12.6326198578,51.7689170837],"type":"Point"}
}