{
  "type": "Feature",
  "properties": {
    "iso:country":"DE",
    "sg:address":"Rosenhardtstr. 10",
    "sg:city":"Bad Liebenzell",
    "sg:phone":"+49 7084/92720",
    "sg:postcode":"75378",
    "sg:province":"Baden-W\u00fcrttemberg",
    "wof:name":"Nothacker & Schwemmle Gmbh",
    "wof:placetype":"venue"
},
  "geometry": {"coordinates":[8.6818027496,48.769405365],"type":"Point"}
}