{
  "type": "Feature",
  "properties": {
    "iso:country":"DE",
    "sg:address":"Marienstr. 2",
    "sg:city":"Eching",
    "sg:phone":"+49 89/3105001",
    "sg:postcode":"85386",
    "sg:province":"Bayern",
    "wof:name":"Nagu-lager-gmbh",
    "wof:placetype":"venue"
},
  "geometry": {"coordinates":[11.6227779388,48.2967758179],"type":"Point"}
}