{
  "type": "Feature",
  "properties": {
    "iso:country":"DE",
    "sg:address":"Potsdamer Str. 33",
    "sg:city":"Brandenburg",
    "sg:phone":"+49 3381/2710",
    "sg:postcode":"14776",
    "sg:province":"Brandenburg",
    "wof:name":"Allkauf Sb-warenhaus Gmbh & Co. Kg",
    "wof:placetype":"venue"
},
  "geometry": {"coordinates":[12.5755386353,52.4074478149],"type":"Point"}
}