{
  "type": "Feature",
  "properties": {
    "iso:country":"DE",
    "sg:address":"Osterrade 46",
    "sg:city":"Hamburg",
    "sg:phone":"+49 40/7386015",
    "sg:postcode":"21031",
    "sg:province":"Hamburg",
    "wof:name":"Hartmann Tischlerei Gmbh",
    "wof:placetype":"venue"
},
  "geometry": {"coordinates":[10.182693,53.510883],"type":"Point"}
}