{
  "type": "Feature",
  "properties": {
    "iso:country":"DE",
    "sg:address":"Riemelsbeck 20",
    "sg:city":"M\u00fclheim",
    "sg:phone":"+49 208/373383",
    "sg:postcode":"45470",
    "sg:province":"Nordrhein-Westfalen",
    "wof:name":"Dieter Geldermann",
    "wof:placetype":"venue"
},
  "geometry": {"coordinates":[6.91464,51.40749],"type":"Point"}
}