{
  "type": "Feature",
  "properties": {
    "iso:country":"DE",
    "sg:address":"Bach",
    "sg:city":"Aschau",
    "sg:phone":"+49 8052/755",
    "sg:postcode":"83229",
    "sg:province":"Bayern",
    "wof:name":"Christel Korkisch",
    "wof:placetype":"venue"
},
  "geometry": {"coordinates":[12.3121500015,47.7573890686],"type":"Point"}
}