{
  "type": "Feature",
  "properties": {
    "iso:country":"DE",
    "sg:address":"Tucherbachstr. 2",
    "sg:city":"Wadgassen",
    "sg:phone":"+49 6834/47271",
    "sg:postcode":"66787",
    "sg:province":"Saarland",
    "wof:name":"W. K\u00f6nig",
    "wof:placetype":"venue"
},
  "geometry": {"coordinates":[6.8129210472,49.257183075],"type":"Point"}
}