{
  "type": "Feature",
  "properties": {
    "iso:country":"DE",
    "sg:address":"Hauptstr. 22",
    "sg:city":"Neunburg",
    "sg:phone":"+49 9672/2142",
    "sg:postcode":"92431",
    "sg:province":"Bayern",
    "wof:name":"Taverne Mikonos",
    "wof:placetype":"venue"
},
  "geometry": {"coordinates":[12.3862524033,49.3485412598],"type":"Point"}
}