{
  "type": "Feature",
  "properties": {
    "iso:country":"DE",
    "sg:address":"Tannenstr. 60",
    "sg:city":"R\u00fcsselsheim",
    "sg:phone":"+49 6142/51761",
    "sg:postcode":"65428",
    "sg:province":"Hessen",
    "wof:name":"Ullmann Transporte Gmbh",
    "wof:placetype":"venue"
},
  "geometry": {"coordinates":[8.4342651367,49.9958076477],"type":"Point"}
}