{
  "type": "Feature",
  "properties": {
    "iso:country":"DE",
    "sg:address":"Am Markt 1",
    "sg:city":"B\u00fcrgel",
    "sg:phone":"+49 36692/300",
    "sg:postcode":"07616",
    "sg:province":"Th\u00fcringen",
    "wof:name":"Kreissparkasse Eisenberg",
    "wof:placetype":"venue"
},
  "geometry": {"coordinates":[11.754589,50.941673],"type":"Point"}
}