{
  "type": "Feature",
  "properties": {
    "iso:country":"DE",
    "sg:address":"Straubinger Str. 61",
    "sg:city":"Regensburg",
    "sg:phone":"+49 941/603660",
    "sg:postcode":"93055",
    "sg:province":"Bayern",
    "wof:name":"Sanit\u00e4ts-fachhaus Reiss Gmbh",
    "wof:placetype":"venue"
},
  "geometry": {"coordinates":[12.131591,49.013527],"type":"Point"}
}