{
  "type": "Feature",
  "properties": {
    "iso:country":"DE",
    "sg:address":"Marktplatz 33",
    "sg:city":"Gangkofen",
    "sg:phone":"+49 8722/910005",
    "sg:postcode":"84140",
    "sg:province":"Bayern",
    "wof:name":"Josef Pavenzinger",
    "wof:placetype":"venue"
},
  "geometry": {"coordinates":[12.56369,48.43779],"type":"Point"}
}