{
  "type": "Feature",
  "properties": {
    "iso:country":"DE",
    "sg:address":"Kasseler Str. 10",
    "sg:city":"M\u00fchlhausen",
    "sg:phone":"+49 36014/40255",
    "sg:postcode":"99974",
    "sg:province":"Th\u00fcringen",
    "wof:name":"Sachverst\u00e4ndigenb\u00fcro Nagel & Bolze Gmbh",
    "wof:placetype":"venue"
},
  "geometry": {"coordinates":[10.4566164017,51.2364654541],"type":"Point"}
}