{
  "type": "Feature",
  "properties": {
    "iso:country":"DE",
    "sg:address":"Am Steffelberg 8",
    "sg:city":"Bernhardswald",
    "sg:phone":"+49 9407/3152",
    "sg:postcode":"93170",
    "sg:province":"Bayern",
    "wof:name":"Dieter Pramsch\u00fcfer",
    "wof:placetype":"venue"
},
  "geometry": {"coordinates":[12.253714,49.116703],"type":"Point"}
}