{
  "type": "Feature",
  "properties": {
    "iso:country":"DE",
    "sg:address":"Bayreuther Berg 3",
    "sg:city":"Pottenstein",
    "sg:phone":"+49 9243/314",
    "sg:postcode":"91278",
    "sg:province":"Bayern",
    "wof:name":"Josef Schlesinger",
    "wof:placetype":"venue"
},
  "geometry": {"coordinates":[11.4069442749,49.7727966309],"type":"Point"}
}