{
  "type": "Feature",
  "properties": {
    "iso:country":"DE",
    "sg:address":"Budersandstr. 26",
    "sg:city":"H\u00f6rnum",
    "sg:phone":"+49 4651/881753",
    "sg:postcode":"25997",
    "sg:province":"Schleswig-Holstein",
    "wof:name":"Offermann & Koch Gmbh",
    "wof:placetype":"venue"
},
  "geometry": {"coordinates":[8.289440155,54.7588043213],"type":"Point"}
}