{
  "type": "Feature",
  "properties": {
    "iso:country":"DE",
    "sg:address":"Schacksdorfer Str. 2",
    "sg:city":"Finsterwalde",
    "sg:phone":"+49 4935/3165020",
    "sg:postcode":"03238",
    "sg:province":"Brandenburg",
    "wof:name":"Autohaus Meyer & Ziegler Gmbh",
    "wof:placetype":"venue"
},
  "geometry": {"coordinates":[13.7175378799,51.6243515015],"type":"Point"}
}