{
  "type": "Feature",
  "properties": {
    "iso:country":"DE",
    "sg:address":"Gro\u00dfsch\u00f6nauer Str. 24",
    "sg:city":"Kurort Jonsdorf",
    "sg:phone":"+49 35844/70513",
    "sg:postcode":"02796",
    "sg:province":"Sachsen",
    "wof:name":"Thomas Richter",
    "wof:placetype":"venue"
},
  "geometry": {"coordinates":[14.6894321442,50.852268219],"type":"Point"}
}