{
  "type": "Feature",
  "properties": {
    "iso:country":"DE",
    "sg:address":"Friesenweg 22",
    "sg:city":"Wenningstedt",
    "sg:phone":"+49 4651/41199",
    "sg:postcode":"25996",
    "sg:province":"Schleswig-Holstein",
    "wof:name":"Uwe Krull",
    "wof:placetype":"venue"
},
  "geometry": {"coordinates":[8.3241939545,54.9352493286],"type":"Point"}
}