{
  "type": "Feature",
  "properties": {
    "iso:country":"DE",
    "sg:address":"Wilhelmstr. 46",
    "sg:city":"Heuchelheim",
    "sg:phone":"+49 641/63349",
    "sg:postcode":"35452",
    "sg:province":"Hessen",
    "wof:name":"Turnhalle Heuchelheim",
    "wof:placetype":"venue"
},
  "geometry": {"coordinates":[8.6364612579,50.5857505798],"type":"Point"}
}