{
  "type": "Feature",
  "properties": {
    "iso:country":"DE",
    "sg:address":"K\u00f6penicker Landstr. 177",
    "sg:city":"Berlin",
    "sg:postcode":"12437",
    "sg:province":"Berlin",
    "wof:name":"Evelyne Lange",
    "wof:placetype":"venue"
},
  "geometry": {"coordinates":[13.4863233566,52.4727783203],"type":"Point"}
}