{
  "type": "Feature",
  "properties": {
    "iso:country":"DE",
    "sg:address":"Hauptstr. 62",
    "sg:city":"Obers\u00fclzen",
    "sg:phone":"+49 6359/2278",
    "sg:postcode":"67271",
    "sg:province":"Rheinland-Pfalz",
    "wof:name":"Helmut Barth",
    "wof:placetype":"venue"
},
  "geometry": {"coordinates":[8.2132749557,49.5685844421],"type":"Point"}
}