{
  "type": "Feature",
  "properties": {
    "iso:country":"DE",
    "sg:address":"Bahnhofstr. 18-20",
    "sg:city":"Brackel",
    "sg:postcode":"21438",
    "sg:province":"Niedersachsen",
    "wof:name":"Koch Tankstellen Gmbh",
    "wof:placetype":"venue"
},
  "geometry": {"coordinates":[10.048518,53.301849],"type":"Point"}
}