{
  "type": "Feature",
  "properties": {
    "iso:country":"DE",
    "sg:address":"Alsstr. 236",
    "sg:city":"M\u00f6nchengladbach",
    "sg:phone":"+49 2161/182356",
    "sg:postcode":"41063",
    "sg:province":"Nordrhein-Westfalen",
    "wof:name":"M. N\u00f6ver",
    "wof:placetype":"venue"
},
  "geometry": {"coordinates":[6.4594249725,51.2092018127],"type":"Point"}
}