{
  "type": "Feature",
  "properties": {
    "iso:country":"DE",
    "sg:address":"Dorstener Str. 137",
    "sg:city":"Haltern",
    "sg:phone":"+49 2364/168666",
    "sg:postcode":"45721",
    "sg:province":"Nordrhein-Westfalen",
    "wof:name":"Waldhotel Bienh\u00fcls Gmbh",
    "wof:placetype":"venue"
},
  "geometry": {"coordinates":[7.15980196,51.7283706665],"type":"Point"}
}