{
  "type": "Feature",
  "properties": {
    "iso:country":"DE",
    "sg:address":"K\u00f6lner Str. 466 a",
    "sg:city":"K\u00fcrten",
    "sg:phone":"+49 2207/1306",
    "sg:postcode":"51515",
    "sg:province":"Nordrhein-Westfalen",
    "wof:name":"Helmut Koll Elektroinstallation",
    "wof:placetype":"venue"
},
  "geometry": {"coordinates":[7.206556,51.028778],"type":"Point"}
}