{
  "type": "Feature",
  "properties": {
    "iso:country":"DE",
    "sg:address":"Steinenbolstr. 14",
    "sg:city":"Pfullingen",
    "sg:phone":"+49 7121/71254",
    "sg:postcode":"72793",
    "sg:province":"Baden-W\u00fcrttemberg",
    "wof:name":"Wilfried Wolf",
    "wof:placetype":"venue"
},
  "geometry": {"coordinates":[9.2351341248,48.4667663574],"type":"Point"}
}