{
  "type": "Feature",
  "properties": {
    "iso:country":"DE",
    "sg:address":"Waldburgstr. 133a",
    "sg:city":"Stuttgart",
    "sg:phone":"+49 711/732512",
    "sg:postcode":"70563",
    "sg:province":"Baden-W\u00fcrttemberg",
    "wof:name":"Willi Harter Architekt",
    "wof:placetype":"venue"
},
  "geometry": {"coordinates":[9.095549,48.723942],"type":"Point"}
}