{
  "type": "Feature",
  "properties": {
    "iso:country":"DE",
    "sg:address":"Postfach 1210",
    "sg:city":"Emmelshausen",
    "sg:phone":"+49 6747/8655",
    "sg:postcode":"56278",
    "sg:province":"Rheinland-Pfalz",
    "wof:name":"Standard-versicherungen Fritz Bartels",
    "wof:placetype":"venue"
},
  "geometry": {"coordinates":[7.55383,50.155769],"type":"Point"}
}