{
  "type": "Feature",
  "properties": {
    "iso:country":"DE",
    "sg:address":"An der Strusbek 46",
    "sg:city":"Ahrensburg",
    "sg:phone":"+49 4102/44651",
    "sg:postcode":"22926",
    "sg:province":"Schleswig-Holstein",
    "wof:name":"Theodor Speckb\u00f6tel Gmbh",
    "wof:placetype":"venue"
},
  "geometry": {"coordinates":[10.265626,53.691364],"type":"Point"}
}