{
  "type": "Feature",
  "properties": {
    "iso:country":"DE",
    "sg:address":"Weinstr. 66",
    "sg:city":"Klingenm\u00fcnster",
    "sg:phone":"+49 6349/1786",
    "sg:postcode":"76889",
    "sg:province":"Rheinland-Pfalz",
    "wof:name":"Kristof Mathis",
    "wof:placetype":"venue"
},
  "geometry": {"coordinates":[8.0197677612,49.1417503357],"type":"Point"}
}