{
  "type": "Feature",
  "properties": {
    "iso:country":"DE",
    "sg:address":"Zobeltitzstr. 117",
    "sg:city":"Berlin",
    "sg:phone":"+49 30/4128817",
    "sg:postcode":"13403",
    "sg:province":"Berlin",
    "wof:name":"Seniorenwohnheim Der Stadt Berlin",
    "wof:placetype":"venue"
},
  "geometry": {"coordinates":[13.30702,52.572098],"type":"Point"}
}