{
  "type": "Feature",
  "properties": {
    "iso:country":"DE",
    "sg:address":"Georg-Hoffmann-Str. 38",
    "sg:city":"Syke",
    "sg:phone":"+49 4242/933793",
    "sg:postcode":"28857",
    "sg:province":"Niedersachsen",
    "wof:name":"Arbeiterwohlfahrt Ambulanter Pflegedienst",
    "wof:placetype":"venue"
},
  "geometry": {"coordinates":[8.817969,52.913563],"type":"Point"}
}