{
  "type": "Feature",
  "properties": {
    "iso:country":"DE",
    "sg:address":"Donastr. 8",
    "sg:city":"Wendelsheim",
    "sg:phone":"+49 6734/8607",
    "sg:postcode":"55234",
    "sg:province":"Rheinland-Pfalz",
    "wof:name":"Erwin Krieger Steuerberater",
    "wof:placetype":"venue"
},
  "geometry": {"coordinates":[7.9965810776,49.7678947449],"type":"Point"}
}