{
  "type": "Feature",
  "properties": {
    "iso:country":"DE",
    "sg:address":"Lindenstr. 47",
    "sg:city":"Oelde",
    "sg:phone":"+49 2522/4124",
    "sg:postcode":"59302",
    "sg:province":"Nordrhein-Westfalen",
    "wof:name":"Speckmann",
    "wof:placetype":"venue"
},
  "geometry": {"coordinates":[8.150001,51.829453],"type":"Point"}
}