{
  "type": "Feature",
  "properties": {
    "iso:country":"DE",
    "sg:address":"Berliner Str. 31",
    "sg:city":"Kloster Zinna",
    "sg:phone":"+49 3372/400072",
    "sg:postcode":"14913",
    "sg:province":"Brandenburg",
    "wof:name":"M. Sponholz",
    "wof:placetype":"venue"
},
  "geometry": {"coordinates":[13.104262352,52.0233764648],"type":"Point"}
}