{
  "type": "Feature",
  "properties": {
    "iso:country":"DE",
    "sg:address":"Rindelbacher Str. 10",
    "sg:city":"Ellwangen",
    "sg:postcode":"73479",
    "sg:province":"Baden-W\u00fcrttemberg",
    "wof:name":"Aldi Gmbh & Co. Kg",
    "wof:placetype":"venue"
},
  "geometry": {"coordinates":[10.1247215271,48.9690093994],"type":"Point"}
}