{
  "type": "Feature",
  "properties": {
    "iso:country":"DE",
    "sg:address":"Gr\u00e4tzelstr. 13 - 15",
    "sg:city":"G\u00f6ttingen",
    "sg:postcode":"37079",
    "sg:province":"Niedersachsen",
    "wof:name":"G\u00fcnther Grundst\u00fccks- Verwaltungsgesellschaft",
    "wof:placetype":"venue"
},
  "geometry": {"coordinates":[9.9043941498,51.541683197],"type":"Point"}
}