{
  "type": "Feature",
  "properties": {
    "iso:country":"DE",
    "sg:address":"Ackerstr. 6",
    "sg:city":"Meerbusch",
    "sg:phone":"+49 2159/3296",
    "sg:postcode":"40670",
    "sg:province":"Nordrhein-Westfalen",
    "wof:name":"Norman K\u00f6ser Architekt",
    "wof:placetype":"venue"
},
  "geometry": {"coordinates":[6.633935,51.268658],"type":"Point"}
}