{
  "type": "Feature",
  "properties": {
    "iso:country":"DE",
    "sg:address":"Wolfenb\u00fctteler Str 39",
    "sg:city":"Braunschweig",
    "sg:phone":"+49 531/27180",
    "sg:postcode":"38102",
    "sg:province":"Niedersachsen",
    "wof:name":"Hofbrauhaus Wolters Ag",
    "wof:placetype":"venue"
},
  "geometry": {"coordinates":[10.529197,52.246296],"type":"Point"}
}