{
  "type": "Feature",
  "properties": {
    "iso:country":"DE",
    "sg:address":"Johann-Sebastian-Bach-Str. 19",
    "sg:city":"Forchheim",
    "sg:phone":"+49 9191/13639",
    "sg:postcode":"91301",
    "sg:province":"Bayern",
    "wof:name":"Erna Wieg\u00e4rtner",
    "wof:placetype":"venue"
},
  "geometry": {"coordinates":[11.0741262436,49.7207107544],"type":"Point"}
}