{
  "type": "Feature",
  "properties": {
    "iso:country":"DE",
    "sg:address":"Wesselinger Str. 17",
    "sg:city":"Br\u00fchl",
    "sg:phone":"+49 2232/44017",
    "sg:postcode":"50321",
    "sg:province":"Nordrhein-Westfalen",
    "wof:name":"Thrum & Michalowski Gmbh",
    "wof:placetype":"venue"
},
  "geometry": {"coordinates":[6.9247789383,50.8323402405],"type":"Point"}
}