{
  "type": "Feature",
  "properties": {
    "iso:country":"DE",
    "sg:address":"Paul-Keller-Str. 17",
    "sg:city":"Pocking",
    "sg:phone":"+49 8531/8180",
    "sg:postcode":"94060",
    "sg:province":"Bayern",
    "wof:name":"Adolf Hofeichner",
    "wof:placetype":"venue"
},
  "geometry": {"coordinates":[13.3299856186,48.408000946],"type":"Point"}
}