{
  "type": "Feature",
  "properties": {
    "iso:country":"DE",
    "sg:address":"Austr. 87",
    "sg:city":"Stuttgart",
    "sg:phone":"+49 711/592658",
    "sg:postcode":"70376",
    "sg:province":"Baden-W\u00fcrttemberg",
    "wof:name":"Wolfgang May",
    "wof:placetype":"venue"
},
  "geometry": {"coordinates":[9.221914,48.823341],"type":"Point"}
}