{
  "type": "Feature",
  "properties": {
    "iso:country":"DE",
    "sg:address":"Georgstr. 15",
    "sg:city":"Eisfeld",
    "sg:phone":"+49 3686/39400",
    "sg:postcode":"98673",
    "sg:province":"Th\u00fcringen",
    "wof:name":"Elektro-schramm Gmbh",
    "wof:placetype":"venue"
},
  "geometry": {"coordinates":[10.9071025848,50.4240875244],"type":"Point"}
}