{
  "type": "Feature",
  "properties": {
    "iso:country":"DE",
    "sg:address":"Beulenhof 8",
    "sg:city":"Essen",
    "sg:phone":"+49 201/531212",
    "sg:postcode":"45279",
    "sg:province":"Nordrhein-Westfalen",
    "wof:name":"Hans-georg Berlau Architekt",
    "wof:placetype":"venue"
},
  "geometry": {"coordinates":[7.100539,51.430813],"type":"Point"}
}