{
  "type": "Feature",
  "properties": {
    "iso:country":"DE",
    "sg:address":"Ulrich-Fai\u00dft-Str. 11",
    "sg:city":"Horb",
    "sg:phone":"+49 7451/7424",
    "sg:postcode":"72160",
    "sg:province":"Baden-W\u00fcrttemberg",
    "wof:name":"Helmut M\u00fcller",
    "wof:placetype":"venue"
},
  "geometry": {"coordinates":[8.661791,48.433315],"type":"Point"}
}