{
  "type": "Feature",
  "properties": {
    "iso:country":"DE",
    "sg:address":"Werderplatz 4",
    "sg:city":"Lahr",
    "sg:phone":"+49 7821/22063",
    "sg:postcode":"77933",
    "sg:province":"Baden-W\u00fcrttemberg",
    "wof:name":"Josef Vauderwange",
    "wof:placetype":"venue"
},
  "geometry": {"coordinates":[7.873770237,48.3370475769],"type":"Point"}
}