{
  "type": "Feature",
  "properties": {
    "iso:country":"DE",
    "sg:address":"Naunheimer Str. 36",
    "sg:city":"Wetzlar",
    "sg:phone":"+49 6441/93346",
    "sg:postcode":"35576",
    "sg:province":"Hessen",
    "wof:name":"Harig & Jochum Maklerb\u00fcro Gmbh",
    "wof:placetype":"venue"
},
  "geometry": {"coordinates":[8.5078048706,50.5763053894],"type":"Point"}
}