{
  "type": "Feature",
  "properties": {
    "iso:country":"DE",
    "sg:address":"Nassauische Str. 30",
    "sg:city":"Berlin",
    "sg:postcode":"10717",
    "sg:province":"Berlin",
    "wof:name":"Romanisches Cafe Verwaltungsges. Mbh",
    "wof:placetype":"venue"
},
  "geometry": {"coordinates":[13.326323,52.488613],"type":"Point"}
}