{
  "type": "Feature",
  "properties": {
    "iso:country":"DE",
    "sg:address":"Annastr. 27",
    "sg:city":"Bochum",
    "sg:phone":"+49 234/681020",
    "sg:postcode":"44793",
    "sg:province":"Nordrhein-Westfalen",
    "wof:name":"Selbsthilfegruppe F. Krebsbetroffene",
    "wof:placetype":"venue"
},
  "geometry": {"coordinates":[7.209407,51.478539],"type":"Point"}
}