{
  "type": "Feature",
  "properties": {
    "iso:country":"DE",
    "sg:address":"Sternheckenweg 15",
    "sg:city":"Rieneck",
    "sg:phone":"+49 9354/1695",
    "sg:postcode":"97794",
    "sg:province":"Bayern",
    "wof:name":"T. Ullrich",
    "wof:placetype":"venue"
},
  "geometry": {"coordinates":[9.635621,50.095802],"type":"Point"}
}