{
  "type": "Feature",
  "properties": {
    "iso:country":"DE",
    "sg:address":"Neukirchener Weg 10",
    "sg:city":"Dollerup",
    "sg:phone":"+49 4636/210",
    "sg:postcode":"24989",
    "sg:province":"Schleswig-Holstein",
    "wof:name":"Ewald Ma\u00df",
    "wof:placetype":"venue"
},
  "geometry": {"coordinates":[9.679706,54.782894],"type":"Point"}
}