{
  "type": "Feature",
  "properties": {
    "iso:country":"DE",
    "sg:address":"Gerbishofen",
    "sg:city":"Kaltental",
    "sg:phone":"+49 8344/276",
    "sg:postcode":"87662",
    "sg:province":"Bayern",
    "wof:name":"Andreas Besel",
    "wof:placetype":"venue"
},
  "geometry": {"coordinates":[10.7624044418,47.929977417],"type":"Point"}
}