{
  "type": "Feature",
  "properties": {
    "iso:country":"DE",
    "sg:address":"Poststr. 18",
    "sg:city":"Heidelberg",
    "sg:phone":"+49 6221/22070",
    "sg:postcode":"69115",
    "sg:province":"Baden-W\u00fcrttemberg",
    "wof:name":"Praxis Dr. Eckhardt Zahn\u00e4rzte F\u00fcr Mund- Und",
    "wof:placetype":"venue"
},
  "geometry": {"coordinates":[8.6905012131,49.4080848694],"type":"Point"}
}