{
  "type": "Feature",
  "properties": {
    "iso:country":"DE",
    "sg:address":"Hermannstr. 6",
    "sg:city":"Neuwied",
    "sg:phone":"+49 2631/28495",
    "sg:postcode":"56564",
    "sg:province":"Rheinland-Pfalz",
    "wof:name":"Dieter Neurath",
    "wof:placetype":"venue"
},
  "geometry": {"coordinates":[7.4613280296,50.4310798645],"type":"Point"}
}