{
  "type": "Feature",
  "properties": {
    "iso:country":"DE",
    "sg:address":"Wallster Weg",
    "sg:city":"Aurich",
    "sg:phone":"+49 4941/4139",
    "sg:postcode":"26603",
    "sg:province":"Niedersachsen",
    "wof:name":"Raiffeisen-warengen. Nordh\u00d6rn-aurich E.g.",
    "wof:placetype":"venue"
},
  "geometry": {"coordinates":[7.4693551064,53.471786499],"type":"Point"}
}