{
  "type": "Feature",
  "properties": {
    "iso:country":"DE",
    "sg:address":"Martinistr. 10 a",
    "sg:city":"Wesel",
    "sg:phone":"+49 281/21146",
    "sg:postcode":"46483",
    "sg:province":"Nordrhein-Westfalen",
    "wof:name":"Kath. Pfarramt St. Martini",
    "wof:placetype":"venue"
},
  "geometry": {"coordinates":[6.6132621765,51.6598777771],"type":"Point"}
}