{
  "type": "Feature",
  "properties": {
    "iso:country":"DE",
    "sg:address":"Bahnhofstr. 7",
    "sg:city":"Roth",
    "sg:phone":"+49 9171/61200",
    "sg:postcode":"91154",
    "sg:province":"Bayern",
    "wof:name":"Bestattungsinstitut Denk Gmbh & Co. Kg",
    "wof:placetype":"venue"
},
  "geometry": {"coordinates":[11.089958,49.247822],"type":"Point"}
}