{
  "type": "Feature",
  "properties": {
    "iso:country":"DE",
    "sg:address":"Wormser Str. 13",
    "sg:city":"Heilbronn",
    "sg:phone":"+49 7066/4676",
    "sg:postcode":"74078",
    "sg:province":"Baden-W\u00fcrttemberg",
    "wof:name":"Andrea Miltenberger",
    "wof:placetype":"venue"
},
  "geometry": {"coordinates":[9.113645,49.179985],"type":"Point"}
}