{
  "type": "Feature",
  "properties": {
    "iso:country":"DE",
    "sg:address":"Rathausstr. 10",
    "sg:city":"Wiesbaden",
    "sg:phone":"+49 611/967210",
    "sg:postcode":"65203",
    "sg:province":"Hessen",
    "wof:name":"Nachbarschaftshaus Wiesbaden E. V.",
    "wof:placetype":"venue"
},
  "geometry": {"coordinates":[8.2373828888,50.0372695923],"type":"Point"}
}