{
  "type": "Feature",
  "properties": {
    "iso:country":"DE",
    "sg:address":"Lindauer Str. 107",
    "sg:city":"Kempten",
    "sg:phone":"+49 831/87455",
    "sg:postcode":"87435",
    "sg:province":"Bayern",
    "wof:name":"Jet-tankstelle",
    "wof:placetype":"venue"
},
  "geometry": {"coordinates":[10.2983646393,47.7174301147],"type":"Point"}
}