{
  "type": "Feature",
  "properties": {
    "iso:country":"DE",
    "sg:address":"R\u00f6ntgenstr. 4",
    "sg:city":"Brunsb\u00fcttel",
    "sg:phone":"+49 4852/51550",
    "sg:postcode":"25541",
    "sg:province":"Schleswig-Holstein",
    "wof:name":"R. Wolter",
    "wof:placetype":"venue"
},
  "geometry": {"coordinates":[9.126085,53.898483],"type":"Point"}
}