{
  "type": "Feature",
  "properties": {
    "iso:country":"DE",
    "sg:address":"Fahrhauerstr. 44",
    "sg:city":"Essen",
    "sg:phone":"+49 201/368398",
    "sg:postcode":"45329",
    "sg:province":"Nordrhein-Westfalen",
    "wof:name":"Guido Piepiora",
    "wof:placetype":"venue"
},
  "geometry": {"coordinates":[7.0136919022,51.5003700256],"type":"Point"}
}