{
  "type": "Feature",
  "properties": {
    "iso:country":"DE",
    "sg:address":"Hevener Str. 309",
    "sg:city":"Bochum",
    "sg:phone":"+49 234/7090180",
    "sg:postcode":"44801",
    "sg:province":"Nordrhein-Westfalen",
    "wof:name":"H\u00fcggenberg",
    "wof:placetype":"venue"
},
  "geometry": {"coordinates":[7.2799158096,51.4388542175],"type":"Point"}
}