{
  "type": "Feature",
  "properties": {
    "iso:country":"DE",
    "sg:address":"Cheruskerstr. 8",
    "sg:city":"Paderborn",
    "sg:phone":"+49 5251/154900",
    "sg:postcode":"33102",
    "sg:province":"Nordrhein-Westfalen",
    "wof:name":"Josef Proppe Innenarchitekt",
    "wof:placetype":"venue"
},
  "geometry": {"coordinates":[8.762974,51.726505],"type":"Point"}
}