{
  "type": "Feature",
  "properties": {
    "iso:country":"DE",
    "sg:address":"Wolfsberg",
    "sg:city":"Neumarkt-Sankt Veit",
    "sg:phone":"+49 8639/1587",
    "sg:postcode":"84494",
    "sg:province":"Bayern",
    "wof:name":"Johann Langm\u00fcller Lohndrescherei",
    "wof:placetype":"venue"
},
  "geometry": {"coordinates":[12.47755,48.344688],"type":"Point"}
}