{
  "type": "Feature",
  "properties": {
    "iso:country":"DE",
    "sg:address":"Hauptstr. 16",
    "sg:city":"Sch\u00f6ppenstedt",
    "sg:phone":"+49 5332/801",
    "sg:postcode":"38170",
    "sg:province":"Niedersachsen",
    "wof:name":"Hugo Lotholz",
    "wof:placetype":"venue"
},
  "geometry": {"coordinates":[10.813768,52.154324],"type":"Point"}
}