{
  "type": "Feature",
  "properties": {
    "iso:country":"DE",
    "sg:address":"Hamburger Str. 38",
    "sg:city":"Rosengarten",
    "sg:phone":"+49 4108/40404",
    "sg:postcode":"21224",
    "sg:province":"Niedersachsen",
    "wof:name":"Hennies Elektrik Gmbh",
    "wof:placetype":"venue"
},
  "geometry": {"coordinates":[9.89059,53.384113],"type":"Point"}
}