{
  "type": "Feature",
  "properties": {
    "iso:country":"DE",
    "sg:address":"Am Torfstich 11",
    "sg:city":"Edemissen",
    "sg:postcode":"31234",
    "sg:province":"Niedersachsen",
    "wof:name":"Wind Strom Nord Gmbh",
    "wof:placetype":"venue"
},
  "geometry": {"coordinates":[10.32234,52.399937],"type":"Point"}
}