{
  "type": "Feature",
  "properties": {
    "iso:country":"DE",
    "sg:address":"Kastorstr. 45",
    "sg:city":"Heidenheim",
    "sg:phone":"+49 7321/43784",
    "sg:postcode":"89518",
    "sg:province":"Baden-W\u00fcrttemberg",
    "wof:name":"M. Walz Bauschlosserei",
    "wof:placetype":"venue"
},
  "geometry": {"coordinates":[10.144198,48.679504],"type":"Point"}
}