{
  "type": "Feature",
  "properties": {
    "iso:country":"DE",
    "sg:address":"Martinsplatz 2a",
    "sg:city":"Bonn",
    "sg:postcode":"53113",
    "sg:province":"Nordrhein-Westfalen",
    "wof:name":"Cms Beteiligungs Gmbh",
    "wof:placetype":"venue"
},
  "geometry": {"coordinates":[7.100234,50.732891],"type":"Point"}
}