{
  "type": "Feature",
  "properties": {
    "iso:country":"DE",
    "sg:address":"Klarenbergstr. 54",
    "sg:city":"Schw\u00e4bisch Gm\u00fcnd",
    "sg:phone":"+49 7171/2561",
    "sg:postcode":"73525",
    "sg:province":"Baden-W\u00fcrttemberg",
    "wof:name":"Klarenberg",
    "wof:placetype":"venue"
},
  "geometry": {"coordinates":[9.8044967651,48.7945785522],"type":"Point"}
}