{
  "type": "Feature",
  "properties": {
    "iso:country":"DE",
    "sg:address":"Zum L\u00f6werholz 2a",
    "sg:city":"M\u00f6hnesee",
    "sg:phone":"+49 2925/82010",
    "sg:postcode":"59519",
    "sg:province":"Nordrhein-Westfalen",
    "wof:name":"Akg Andreas Kaleja Gie\u00dferei Engineering E. K.",
    "wof:placetype":"venue"
},
  "geometry": {"coordinates":[8.198759079,51.4811973572],"type":"Point"}
}