{
  "type": "Feature",
  "properties": {
    "iso:country":"DE",
    "sg:address":"Reventlouallee 14-16",
    "sg:city":"Kiel",
    "sg:phone":"+49 431/566561",
    "sg:postcode":"24105",
    "sg:province":"Schleswig-Holstein",
    "wof:name":"Ev. Pfarramt I Heiligengeist-gemeinde",
    "wof:placetype":"venue"
},
  "geometry": {"coordinates":[10.147851944,54.3351287842],"type":"Point"}
}