{
  "type": "Feature",
  "properties": {
    "iso:country":"DE",
    "sg:address":"Im Katzenforst 1",
    "sg:city":"Kronberg",
    "sg:phone":"+49 6173/607960",
    "sg:postcode":"61476",
    "sg:province":"Hessen",
    "wof:name":"Verano Messebau Jakob F. Wintzer Messebau",
    "wof:placetype":"venue"
},
  "geometry": {"coordinates":[8.546539,50.175636],"type":"Point"}
}