{
  "type": "Feature",
  "properties": {
    "iso:country":"DE",
    "sg:address":"Paderborner Str. 23",
    "sg:city":"Schlangen",
    "sg:phone":"+49 5252/7217",
    "sg:postcode":"33189",
    "sg:province":"Nordrhein-Westfalen",
    "wof:name":"Katholisches Pfarramt St. Marien",
    "wof:placetype":"venue"
},
  "geometry": {"coordinates":[8.8414354324,51.8064537048],"type":"Point"}
}