{
  "type": "Feature",
  "properties": {
    "iso:country":"DE",
    "sg:address":"Dorfstr. 17",
    "sg:city":"Altenmedingen",
    "sg:phone":"+49 5807/98710",
    "sg:postcode":"29575",
    "sg:province":"Niedersachsen",
    "wof:name":"A. Seegel Kunststofftechnik Handels- Und Produktions-",
    "wof:placetype":"venue"
},
  "geometry": {"coordinates":[10.60036,53.106228],"type":"Point"}
}