{
  "type": "Feature",
  "properties": {
    "iso:country":"DE",
    "sg:address":"Anton-Aulke-Weg 11",
    "sg:city":"Ostbevern",
    "sg:phone":"+49 2532/1596",
    "sg:postcode":"48346",
    "sg:province":"Nordrhein-Westfalen",
    "wof:name":"Lust Und Laune Reisen",
    "wof:placetype":"venue"
},
  "geometry": {"coordinates":[7.8406200409,52.0437889099],"type":"Point"}
}