{
  "type": "Feature",
  "properties": {
    "iso:country":"DE",
    "sg:address":"Gartenstr. 32",
    "sg:city":"Gotha",
    "sg:phone":"+49 3621/853360",
    "sg:postcode":"99867",
    "sg:province":"Th\u00fcringen",
    "wof:name":"Tatjana Sch\u00f6ppe Notarin",
    "wof:placetype":"venue"
},
  "geometry": {"coordinates":[10.7035522461,50.9510421753],"type":"Point"}
}