{
  "type": "Feature",
  "properties": {
    "iso:country":"DE",
    "sg:address":"Hochstr. 8",
    "sg:city":"Lahnstein",
    "sg:phone":"+49 2621/2490",
    "sg:postcode":"56112",
    "sg:province":"Rheinland-Pfalz",
    "wof:name":"Josef Neusser",
    "wof:placetype":"venue"
},
  "geometry": {"coordinates":[7.6043171883,50.3016929626],"type":"Point"}
}