{
  "type": "Feature",
  "properties": {
    "iso:country":"DE",
    "sg:address":"Herriedener Str. 95",
    "sg:city":"N\u00fcrnberg",
    "sg:phone":"+49 911/4467538",
    "sg:postcode":"90449",
    "sg:province":"Bayern",
    "wof:name":"Modell-bau-club N\u00fcrnberg E. V. Rudolf Greissl",
    "wof:placetype":"venue"
},
  "geometry": {"coordinates":[11.0293502808,49.4221611023],"type":"Point"}
}