{
  "type": "Feature",
  "properties": {
    "iso:country":"DE",
    "sg:address":"Am Bahnhof 6",
    "sg:city":"Steinhagen",
    "sg:phone":"+49 5204/8639",
    "sg:postcode":"33803",
    "sg:province":"Nordrhein-Westfalen",
    "wof:name":"Anne Henkel",
    "wof:placetype":"venue"
},
  "geometry": {"coordinates":[8.422191,52.016094],"type":"Point"}
}