{
  "type": "Feature",
  "properties": {
    "iso:country":"DE",
    "sg:address":"Schrevenwiesen 5",
    "sg:city":"Goslar",
    "sg:phone":"+49 5321/33500",
    "sg:postcode":"38642",
    "sg:province":"Niedersachsen",
    "wof:name":"Feet Oker Computer Gmbh",
    "wof:placetype":"venue"
},
  "geometry": {"coordinates":[10.4966430664,51.897151947],"type":"Point"}
}