{
  "type": "Feature",
  "properties": {
    "iso:country":"DE",
    "sg:address":"Ossietzkystr. 37",
    "sg:city":"Hamburg",
    "sg:phone":"+49 40/6546412",
    "sg:postcode":"22043",
    "sg:province":"Hamburg",
    "wof:name":"Inca Industrielle Computersysteme Gmbh",
    "wof:placetype":"venue"
},
  "geometry": {"coordinates":[10.1128377914,53.5720596313],"type":"Point"}
}