{
  "type": "Feature",
  "properties": {
    "iso:country":"DE",
    "sg:address":"Schmaler Weg 2",
    "sg:city":"Porta Westfalica",
    "sg:phone":"+49 5706/3707",
    "sg:postcode":"32457",
    "sg:province":"Nordrhein-Westfalen",
    "wof:name":"F. Und M. Mohme",
    "wof:placetype":"venue"
},
  "geometry": {"coordinates":[8.9253406525,52.2060432434],"type":"Point"}
}