{
  "type": "Feature",
  "properties": {
    "iso:country":"DE",
    "sg:address":"Bruckmairstr. 15",
    "sg:city":"Ismaning",
    "sg:phone":"+49 89/966741",
    "sg:postcode":"85737",
    "sg:province":"Bayern",
    "wof:name":"Josef Lupperger",
    "wof:placetype":"venue"
},
  "geometry": {"coordinates":[11.715259,48.234589],"type":"Point"}
}