{
  "type": "Feature",
  "properties": {
    "iso:country":"DE",
    "sg:address":"St.-Annen-Weg 9",
    "sg:city":"Werl",
    "sg:phone":"+49 2922/3651",
    "sg:postcode":"59457",
    "sg:province":"Nordrhein-Westfalen",
    "wof:name":"Johannes Rossa",
    "wof:placetype":"venue"
},
  "geometry": {"coordinates":[7.8781299591,51.5471496582],"type":"Point"}
}