{
  "type": "Feature",
  "properties": {
    "iso:country":"DE",
    "sg:address":"Ha\u00dflinghauser Str. 35",
    "sg:city":"Schwelm",
    "sg:phone":"+49 2336/16301",
    "sg:postcode":"58332",
    "sg:province":"Nordrhein-Westfalen",
    "wof:name":"Gustav Adolf Wilkesmann Mineral\u00f6l",
    "wof:placetype":"venue"
},
  "geometry": {"coordinates":[7.2949471474,51.3012695312],"type":"Point"}
}