{
  "type": "Feature",
  "properties": {
    "iso:country":"DE",
    "sg:address":"Vo\u00dfhagen 92-98",
    "sg:city":"Wedel",
    "sg:phone":"+49 4103/17938",
    "sg:postcode":"22880",
    "sg:province":"Schleswig-Holstein",
    "wof:name":"Rudolf Schlee Gmbh",
    "wof:placetype":"venue"
},
  "geometry": {"coordinates":[9.721275,53.584778],"type":"Point"}
}