{
  "type": "Feature",
  "properties": {
    "iso:country":"DE",
    "sg:address":"Hauptstr. 130-134",
    "sg:city":"Markkleeberg",
    "sg:phone":"+49 34299/77062",
    "sg:postcode":"04416",
    "sg:province":"Sachsen",
    "wof:name":"G. Christoph",
    "wof:placetype":"venue"
},
  "geometry": {"coordinates":[12.3779296875,51.2671699524],"type":"Point"}
}