{
  "type": "Feature",
  "properties": {
    "iso:country":"DE",
    "sg:address":"Steinachstr. 11",
    "sg:city":"Balingen",
    "sg:phone":"+49 7433/99140",
    "sg:postcode":"72336",
    "sg:province":"Baden-W\u00fcrttemberg",
    "wof:name":"Geb\u00e4udeversicherung Baden W\u00fcrttemberg",
    "wof:placetype":"venue"
},
  "geometry": {"coordinates":[8.8492956161,48.2664451599],"type":"Point"}
}