{
  "type": "Feature",
  "properties": {
    "iso:country":"DE",
    "sg:address":"Jungfernstieg 7a",
    "sg:city":"Berlin",
    "sg:phone":"+49 30/7723027",
    "sg:postcode":"12207",
    "sg:province":"Berlin",
    "wof:name":"Hotel Jungfernstieg",
    "wof:placetype":"venue"
},
  "geometry": {"coordinates":[13.3280353546,52.4308433533],"type":"Point"}
}