{
  "type": "Feature",
  "properties": {
    "iso:country":"DE",
    "sg:address":"Schieringerstr. 15",
    "sg:city":"Bietigheim-Bissingen",
    "sg:phone":"+49 7142/43207",
    "sg:postcode":"74321",
    "sg:province":"Baden-W\u00fcrttemberg",
    "wof:name":"Gastst\u00e4tte Riff",
    "wof:placetype":"venue"
},
  "geometry": {"coordinates":[9.1271066666,48.9604988098],"type":"Point"}
}