{
  "type": "Feature",
  "properties": {
    "iso:country":"DE",
    "sg:address":"Wilhelm-Leuschner-Str. 55",
    "sg:city":"Neu-Isenburg",
    "sg:phone":"+49 6102/22188",
    "sg:postcode":"63263",
    "sg:province":"Hessen",
    "wof:name":"Schumacher Und K\u00f6rner Architekten",
    "wof:placetype":"venue"
},
  "geometry": {"coordinates":[8.682896,50.054188],"type":"Point"}
}