{
  "type": "Feature",
  "properties": {
    "iso:country":"DE",
    "sg:address":"Lohenstr. 11",
    "sg:city":"Gr\u00e4felfing",
    "sg:phone":"+49 89/8589660",
    "sg:postcode":"82166",
    "sg:province":"Bayern",
    "wof:name":"Bavaria Dachbau Ag",
    "wof:placetype":"venue"
},
  "geometry": {"coordinates":[11.4494543076,48.1206588745],"type":"Point"}
}