{
  "type": "Feature",
  "properties": {
    "iso:country":"DE",
    "sg:address":"Karl-Stieler-Str. 8",
    "sg:city":"Ottobrunn",
    "sg:phone":"+49 89/6888609",
    "sg:postcode":"85521",
    "sg:province":"Bayern",
    "wof:name":"Gelateria Coccinella",
    "wof:placetype":"venue"
},
  "geometry": {"coordinates":[11.68041,48.063507],"type":"Point"}
}