{
  "type": "Feature",
  "properties": {
    "iso:country":"DE",
    "sg:address":"Lamnitzer Str. 1",
    "sg:city":"Auerbach",
    "sg:phone":"+49 3744/214251",
    "sg:postcode":"08209",
    "sg:province":"Sachsen",
    "wof:name":"Walpurg",
    "wof:placetype":"venue"
},
  "geometry": {"coordinates":[12.4032268524,50.5105056763],"type":"Point"}
}