{
  "type": "Feature",
  "properties": {
    "iso:country":"DE",
    "sg:address":"Siedlerweg 2",
    "sg:city":"Kurort Hartha",
    "sg:phone":"+49 35203/2479",
    "sg:postcode":"01737",
    "sg:province":"Sachsen",
    "wof:name":"Karsten Hermisson",
    "wof:placetype":"venue"
},
  "geometry": {"coordinates":[13.547301,50.982521],"type":"Point"}
}