{
  "type": "Feature",
  "properties": {
    "iso:country":"DE",
    "sg:address":"Bollstedter Gasse 4",
    "sg:city":"M\u00fchlhausen",
    "sg:postcode":"99974",
    "sg:province":"Th\u00fcringen",
    "wof:name":"Ev.-luth. Kirche Thomas-muentzer",
    "wof:placetype":"venue"
},
  "geometry": {"coordinates":[10.457567215,51.2113494873],"type":"Point"}
}