{
  "type": "Feature",
  "properties": {
    "iso:country":"DE",
    "sg:address":"Kirmesauer Str. 17",
    "sg:city":"Bad Bayersoien",
    "sg:phone":"+49 8845/1816",
    "sg:postcode":"82435",
    "sg:province":"Bayern",
    "wof:name":"Kurcafe",
    "wof:placetype":"venue"
},
  "geometry": {"coordinates":[11.002043,47.694138],"type":"Point"}
}