{
  "type": "Feature",
  "properties": {
    "iso:country":"DE",
    "sg:address":"Kreuzgrundweg 1",
    "sg:city":"Petersberg",
    "sg:phone":"+49 661/969550",
    "sg:postcode":"36100",
    "sg:province":"Hessen",
    "wof:name":"Sauermilch Design & Handels-gmbh",
    "wof:placetype":"venue"
},
  "geometry": {"coordinates":[9.7240400314,50.5556716919],"type":"Point"}
}