{
  "type": "Feature",
  "properties": {
    "iso:country":"DE",
    "sg:address":"Max-Josefs-Platz 5",
    "sg:city":"Rosenheim",
    "sg:phone":"+49 8031/396914",
    "sg:postcode":"83022",
    "sg:province":"Bayern",
    "wof:name":"Fielmann Ag & Co. Ohg",
    "wof:placetype":"venue"
},
  "geometry": {"coordinates":[12.126376152,47.8553390503],"type":"Point"}
}