{
  "type": "Feature",
  "properties": {
    "iso:country":"DE",
    "sg:address":"L\u00fcbecker Str. 22 A",
    "sg:city":"Magdeburg",
    "sg:phone":"+49 391/2523535",
    "sg:postcode":"39124",
    "sg:province":"Sachsen-Anhalt",
    "wof:name":"Konditorei-cafe Todzi",
    "wof:placetype":"venue"
},
  "geometry": {"coordinates":[11.636369,52.156055],"type":"Point"}
}