{
  "type": "Feature",
  "properties": {
    "iso:country":"DE",
    "sg:address":"D\u00fcsseldorfer Str. 20",
    "sg:city":"Krefeld",
    "sg:phone":"+49 2151/49150",
    "sg:postcode":"47829",
    "sg:province":"Nordrhein-Westfalen",
    "wof:name":"Willy Hagemus Steuerberater",
    "wof:placetype":"venue"
},
  "geometry": {"coordinates":[6.6514320374,51.3506965637],"type":"Point"}
}