{
  "type": "Feature",
  "properties": {
    "iso:country":"DE",
    "sg:address":"Jungfernstieg 30",
    "sg:city":"Hamburg",
    "sg:phone":"+49 40/3574720",
    "sg:postcode":"20354",
    "sg:province":"Hamburg",
    "wof:name":"Schneider Stein Und Partner Rechtsanw\u00e4lte",
    "wof:placetype":"venue"
},
  "geometry": {"coordinates":[9.9911661148,53.5540618896],"type":"Point"}
}