{
  "type": "Feature",
  "properties": {
    "iso:country":"DE",
    "sg:address":"Holweider Str. 13-15",
    "sg:city":"K\u00f6ln",
    "sg:phone":"+49 221/612041",
    "sg:postcode":"51065",
    "sg:province":"Nordrhein-Westfalen",
    "wof:name":"Bundesverband Information Und Beratung F. Ns-verfolgte E. V.",
    "wof:placetype":"venue"
},
  "geometry": {"coordinates":[7.0080871582,50.9637298584],"type":"Point"}
}