{
  "type": "Feature",
  "properties": {
    "iso:country":"DE",
    "sg:address":"Baldesgraben 1",
    "sg:city":"Traben-Trarbach",
    "sg:phone":"+49 6541/9105",
    "sg:postcode":"56841",
    "sg:province":"Rheinland-Pfalz",
    "wof:name":"Pension Ferdinand Riemer",
    "wof:placetype":"venue"
},
  "geometry": {"coordinates":[7.1053462029,49.9784240723],"type":"Point"}
}