{
  "type": "Feature",
  "properties": {
    "iso:country":"DE",
    "sg:address":"Vogelbeerenweg 20",
    "sg:city":"Kirchheim",
    "sg:phone":"+49 89/9037204",
    "sg:postcode":"85551",
    "sg:province":"Bayern",
    "wof:name":"Masters Sports Gmbh",
    "wof:placetype":"venue"
},
  "geometry": {"coordinates":[11.7563705444,48.1702384949],"type":"Point"}
}