{
  "type": "Feature",
  "properties": {
    "iso:country":"DE",
    "sg:address":"K\u00f6nigstr. 1",
    "sg:city":"Meppen",
    "sg:phone":"+49 5931/6515",
    "sg:postcode":"49716",
    "sg:province":"Niedersachsen",
    "wof:name":"Exactadent Dentallabor Gmbh",
    "wof:placetype":"venue"
},
  "geometry": {"coordinates":[7.2954359055,52.6978302002],"type":"Point"}
}