{
  "type": "Feature",
  "properties": {
    "iso:country":"DE",
    "sg:address":"Gie\u00dfener Str. 40",
    "sg:city":"Heuchelheim",
    "sg:postcode":"35452",
    "sg:province":"Hessen",
    "wof:name":"Aybau Gmbh",
    "wof:placetype":"venue"
},
  "geometry": {"coordinates":[8.634264,50.58337],"type":"Point"}
}