{
  "type": "Feature",
  "properties": {
    "iso:country":"DE",
    "sg:address":"Vacher Str. 62 a",
    "sg:city":"F\u00fcrth",
    "sg:phone":"+49 911/732534",
    "sg:postcode":"90766",
    "sg:province":"Bayern",
    "wof:name":"Karl Sulzer",
    "wof:placetype":"venue"
},
  "geometry": {"coordinates":[10.9793949127,49.4858970642],"type":"Point"}
}