{
  "type": "Feature",
  "properties": {
    "iso:country":"DE",
    "sg:address":"Kaiserstr. 28",
    "sg:city":"Ostfildern",
    "sg:phone":"+49 711/7949993",
    "sg:postcode":"73760",
    "sg:province":"Baden-W\u00fcrttemberg",
    "wof:name":"K\u00dchlanlagenbaud\u00d6rfel & Fr\u00d6schle Gmbh",
    "wof:placetype":"venue"
},
  "geometry": {"coordinates":[9.297327,48.712875],"type":"Point"}
}