{
  "type": "Feature",
  "properties": {
    "iso:country":"DE",
    "sg:address":"Zur Femelinde 52",
    "sg:city":"Melle",
    "sg:phone":"+49 5422/44881",
    "sg:postcode":"49326",
    "sg:province":"Niedersachsen",
    "wof:name":"Horst Rudolf",
    "wof:placetype":"venue"
},
  "geometry": {"coordinates":[8.271358,52.214481],"type":"Point"}
}