{
  "type": "Feature",
  "properties": {
    "iso:country":"DE",
    "sg:address":"Erfenschlager Str. 23",
    "sg:city":"Chemnitz",
    "sg:phone":"+49 371/510165",
    "sg:postcode":"09125",
    "sg:province":"Sachsen",
    "wof:name":"Mm Modemaus Gmbh",
    "wof:placetype":"venue"
},
  "geometry": {"coordinates":[12.9282655716,50.7929763794],"type":"Point"}
}