{
  "type": "Feature",
  "properties": {
    "iso:country":"DE",
    "sg:address":"Kaiserstr. 57",
    "sg:city":"St. Ingbert",
    "sg:phone":"+49 6894/2614",
    "sg:postcode":"66386",
    "sg:province":"Saarland",
    "wof:name":"L. Jung Inh. Christel Braun",
    "wof:placetype":"venue"
},
  "geometry": {"coordinates":[7.11657,49.27882],"type":"Point"}
}