{
  "type": "Feature",
  "properties": {
    "iso:country":"DE",
    "sg:address":"K\u00f6lnstr. 175",
    "sg:city":"Bonn",
    "sg:phone":"+49 228/690515",
    "sg:postcode":"53111",
    "sg:province":"Nordrhein-Westfalen",
    "wof:name":"Provinzial Versicherungen Frank Dietrich",
    "wof:placetype":"venue"
},
  "geometry": {"coordinates":[7.0916719437,50.7429618835],"type":"Point"}
}