{
  "type": "Feature",
  "properties": {
    "iso:country":"DE",
    "sg:address":"Balderstr. 64",
    "sg:city":"Leipzig",
    "sg:phone":"+49 341/9214045",
    "sg:postcode":"04349",
    "sg:province":"Sachsen",
    "wof:name":"Jochen Krause",
    "wof:placetype":"venue"
},
  "geometry": {"coordinates":[12.451396,51.379864],"type":"Point"}
}