{
  "type": "Feature",
  "properties": {
    "iso:country":"DE",
    "sg:address":"Hoffeldring 4",
    "sg:city":"Oberaudorf",
    "sg:phone":"+49 8033/1591",
    "sg:postcode":"83080",
    "sg:province":"Bayern",
    "wof:name":"Werner Reidl Immobilien Alpenland",
    "wof:placetype":"venue"
},
  "geometry": {"coordinates":[12.1743755341,47.6582107544],"type":"Point"}
}