{
  "type": "Feature",
  "properties": {
    "iso:country":"DE",
    "sg:address":"Niederf\u00e4hrer Str. 45",
    "sg:city":"Mei\u00dfen",
    "sg:phone":"+49 3521/733053",
    "sg:postcode":"01662",
    "sg:province":"Sachsen",
    "wof:name":"Unabh\u00e4ngige Finanz- Und Wirtschaftsberatung Gmbh",
    "wof:placetype":"venue"
},
  "geometry": {"coordinates":[13.4833517075,51.1666259766],"type":"Point"}
}