{
  "type": "Feature",
  "properties": {
    "iso:country":"DE",
    "sg:address":"Bahnhofstr. 25",
    "sg:city":"Strehla",
    "sg:phone":"+49 35264/90675",
    "sg:postcode":"01616",
    "sg:province":"Sachsen",
    "wof:name":"Rolf K\u00fchne",
    "wof:placetype":"venue"
},
  "geometry": {"coordinates":[13.233764,51.349289],"type":"Point"}
}