{
  "type": "Feature",
  "properties": {
    "iso:country":"DE",
    "sg:address":"Jesenwang",
    "sg:city":"Jesenwang",
    "sg:phone":"+49 8146/408",
    "sg:postcode":"82287",
    "sg:province":"Bayern",
    "wof:name":"Volksbank F\u00fcrstenfeldbruck Eg",
    "wof:placetype":"venue"
},
  "geometry": {"coordinates":[11.132233,48.166492],"type":"Point"}
}