{
  "type": "Feature",
  "properties": {
    "iso:country":"DE",
    "sg:address":"Zimmerstr.",
    "sg:city":"Eberswalde",
    "sg:postcode":"16225",
    "sg:province":"Brandenburg",
    "wof:name":"Computer Service Zubeh\u00f6r",
    "wof:placetype":"venue"
},
  "geometry": {"coordinates":[13.8119907379,52.8347320557],"type":"Point"}
}