{
  "type": "Feature",
  "properties": {
    "iso:country":"DE",
    "sg:address":"Binzwangen 20",
    "sg:city":"Colmberg",
    "sg:phone":"+49 9803/581",
    "sg:postcode":"91598",
    "sg:province":"Bayern",
    "wof:name":"Dr. Karla P\u00fcllmann-heller Tier\u00e4rztin",
    "wof:placetype":"venue"
},
  "geometry": {"coordinates":[10.3703012466,49.385383606],"type":"Point"}
}