{
  "type": "Feature",
  "properties": {
    "iso:country":"DE",
    "sg:address":"Schulstr. 4",
    "sg:city":"R\u00f6hl",
    "sg:phone":"+49 6562/2386",
    "sg:postcode":"54636",
    "sg:province":"Rheinland-Pfalz",
    "wof:name":"Alfred Engel",
    "wof:placetype":"venue"
},
  "geometry": {"coordinates":[6.57873106,49.9393119812],"type":"Point"}
}