{
  "type": "Feature",
  "properties": {
    "iso:country":"DE",
    "sg:address":"Wulffstr. 12",
    "sg:city":"Berlin",
    "sg:phone":"+49 30/7913061",
    "sg:postcode":"12165",
    "sg:province":"Berlin",
    "wof:name":"Peter Arnold Kameramann",
    "wof:placetype":"venue"
},
  "geometry": {"coordinates":[13.3155679703,52.454410553],"type":"Point"}
}