{
  "type": "Feature",
  "properties": {
    "iso:country":"DE",
    "sg:address":"Naheweg 16",
    "sg:city":"Oberbrombach",
    "sg:phone":"+49 6787/8103",
    "sg:postcode":"55767",
    "sg:province":"Rheinland-Pfalz",
    "wof:name":"Lothar Heiderich",
    "wof:placetype":"venue"
},
  "geometry": {"coordinates":[7.2635622025,49.698135376],"type":"Point"}
}