{
  "type": "Feature",
  "properties": {
    "iso:country":"DE",
    "sg:address":"Rathausstr 1",
    "sg:city":"Miesbach",
    "sg:phone":"+49 8025/1335",
    "sg:postcode":"83714",
    "sg:province":"Bayern",
    "wof:name":"Raiffeisenbank Miesbach Eg",
    "wof:placetype":"venue"
},
  "geometry": {"coordinates":[11.830698,47.788818],"type":"Point"}
}