{
  "type": "Feature",
  "properties": {
    "iso:country":"DE",
    "sg:address":"Friedrich-Ebert-Str. 52",
    "sg:city":"Taucha",
    "sg:phone":"+49 34298/65105",
    "sg:postcode":"04425",
    "sg:province":"Sachsen",
    "wof:name":"Dieter Hohenstein",
    "wof:placetype":"venue"
},
  "geometry": {"coordinates":[12.486938,51.385788],"type":"Point"}
}