{
  "type": "Feature",
  "properties": {
    "iso:country":"DE",
    "sg:address":"Wei\u00dfdornstr. 32",
    "sg:city":"Georgsmarienh\u00fctte",
    "sg:phone":"+49 5401/44597",
    "sg:postcode":"49124",
    "sg:province":"Niedersachsen",
    "wof:name":"Sigrid Schmidt",
    "wof:placetype":"venue"
},
  "geometry": {"coordinates":[8.074372,52.214901],"type":"Point"}
}