{
  "type": "Feature",
  "properties": {
    "iso:country":"DE",
    "sg:address":"Thumseestr. 9",
    "sg:city":"Bad Reichenhall",
    "sg:phone":"+49 8651/95610",
    "sg:postcode":"83435",
    "sg:province":"Bayern",
    "wof:name":"Kirchberg Altenheim",
    "wof:placetype":"venue"
},
  "geometry": {"coordinates":[12.868431,47.718887],"type":"Point"}
}