{
  "type": "Feature",
  "properties": {
    "iso:country":"DE",
    "sg:address":"Postweg 8 a",
    "sg:city":"Celle",
    "sg:phone":"+49 5141/85175",
    "sg:postcode":"29227",
    "sg:province":"Niedersachsen",
    "wof:name":"R. M\u00fcller",
    "wof:placetype":"venue"
},
  "geometry": {"coordinates":[10.0793600082,52.6020431519],"type":"Point"}
}