{
  "type": "Feature",
  "properties": {
    "iso:country":"DE",
    "sg:address":"Hassel 2",
    "sg:city":"Welle",
    "sg:phone":"+49 4188/7266",
    "sg:postcode":"21261",
    "sg:province":"Niedersachsen",
    "wof:name":"Edava Daten-erfassungs- Verarbeitungs Gmbh",
    "wof:placetype":"venue"
},
  "geometry": {"coordinates":[9.7760982513,53.2419128418],"type":"Point"}
}