{
  "type": "Feature",
  "properties": {
    "iso:country":"DE",
    "sg:address":"Gro\u00dfe Bleiche 34",
    "sg:city":"Mainz",
    "sg:phone":"+49 6131/224512",
    "sg:postcode":"55116",
    "sg:province":"Rheinland-Pfalz",
    "wof:name":"Girasole",
    "wof:placetype":"venue"
},
  "geometry": {"coordinates":[8.2664356232,50.0021133423],"type":"Point"}
}