{
  "type": "Feature",
  "properties": {
    "iso:country":"DE",
    "sg:address":"Am Hauberg 28a",
    "sg:city":"Sipplingen",
    "sg:phone":"+49 7551/5925",
    "sg:postcode":"78354",
    "sg:province":"Baden-W\u00fcrttemberg",
    "wof:name":"Beirer Stuckateur- Fachbetrieb Gmbh",
    "wof:placetype":"venue"
},
  "geometry": {"coordinates":[9.106508255,47.7956924438],"type":"Point"}
}