{
  "type": "Feature",
  "properties": {
    "iso:country":"DE",
    "sg:address":"Maistr. 63",
    "sg:city":"M\u00fcnchen",
    "sg:phone":"+49 89/5439944",
    "sg:postcode":"80337",
    "sg:province":"Bayern",
    "wof:name":"Mike Gl\u00fcckstein Rechtsanwalt",
    "wof:placetype":"venue"
},
  "geometry": {"coordinates":[11.5614118576,48.1263656616],"type":"Point"}
}