{
  "type": "Feature",
  "properties": {
    "iso:country":"DE",
    "sg:address":"Hohe Str. 5",
    "sg:city":"Wermelskirchen",
    "sg:phone":"+49 2196/4952",
    "sg:postcode":"42929",
    "sg:province":"Nordrhein-Westfalen",
    "wof:name":"Ernst Fastenrath Jun.",
    "wof:placetype":"venue"
},
  "geometry": {"coordinates":[7.208202,51.135284],"type":"Point"}
}