{
  "type": "Feature",
  "properties": {
    "iso:country":"DE",
    "sg:address":"Gl\u00f6singer Str. 96",
    "sg:city":"Arnsberg",
    "sg:phone":"+49 2937/6755",
    "sg:postcode":"59823",
    "sg:province":"Nordrhein-Westfalen",
    "wof:name":"Josef Hanses",
    "wof:placetype":"venue"
},
  "geometry": {"coordinates":[8.1487350464,51.3971481323],"type":"Point"}
}