{
  "type": "Feature",
  "properties": {
    "iso:country":"DE",
    "sg:address":"Rudolf-Diesel-Str. 2",
    "sg:city":"Saterland",
    "sg:phone":"+49 4498/921279",
    "sg:postcode":"26683",
    "sg:province":"Niedersachsen",
    "wof:name":"Saterl\u00e4nder Glasveredelungs Gmbh",
    "wof:placetype":"venue"
},
  "geometry": {"coordinates":[7.6830711365,53.1317062378],"type":"Point"}
}