{
  "type": "Feature",
  "properties": {
    "iso:country":"DE",
    "sg:address":"Talstr. 28",
    "sg:city":"Schriesheim",
    "sg:phone":"+49 6203/65615",
    "sg:postcode":"69198",
    "sg:province":"Baden-W\u00fcrttemberg",
    "wof:name":"Restaurant Linde",
    "wof:placetype":"venue"
},
  "geometry": {"coordinates":[8.6624927521,49.4757957458],"type":"Point"}
}