{
  "type": "Feature",
  "properties": {
    "iso:country":"DE",
    "sg:address":"Faulenbachstr 15",
    "sg:city":"Wurmlingen",
    "sg:phone":"+49 7461/966290",
    "sg:postcode":"78573",
    "sg:province":"Baden-W\u00fcrttemberg",
    "wof:name":"Buchmann",
    "wof:placetype":"venue"
},
  "geometry": {"coordinates":[8.778765,48.008362],"type":"Point"}
}