{
  "type": "Feature",
  "properties": {
    "iso:country":"DE",
    "sg:address":"Killinger Str. 2",
    "sg:city":"Westhausen",
    "sg:phone":"+49 7363/3839",
    "sg:postcode":"73463",
    "sg:province":"Baden-W\u00fcrttemberg",
    "wof:name":"E. Wenzel",
    "wof:placetype":"venue"
},
  "geometry": {"coordinates":[10.252691,48.898563],"type":"Point"}
}