{
  "type": "Feature",
  "properties": {
    "iso:country":"DE",
    "sg:address":"Siegesstr. 148",
    "sg:city":"Oberhausen",
    "sg:phone":"+49 208/686974",
    "sg:postcode":"46147",
    "sg:province":"Nordrhein-Westfalen",
    "wof:name":"P. Zagorny",
    "wof:placetype":"venue"
},
  "geometry": {"coordinates":[6.787982,51.522118],"type":"Point"}
}