{
  "type": "Feature",
  "properties": {
    "iso:country":"DE",
    "sg:address":"Schlehenweg 3",
    "sg:city":"Uelzen",
    "sg:phone":"+49 581/43584",
    "sg:postcode":"29525",
    "sg:province":"Niedersachsen",
    "wof:name":"Dietrich Smolla",
    "wof:placetype":"venue"
},
  "geometry": {"coordinates":[7.7228589058,51.5405158997],"type":"Point"}
}