{
  "type": "Feature",
  "properties": {
    "iso:country":"DE",
    "sg:address":"Hauptstr. 35",
    "sg:city":"Rellingen",
    "sg:phone":"+49 4101/200110",
    "sg:postcode":"25462",
    "sg:province":"Schleswig-Holstein",
    "wof:name":"Post-apotheke",
    "wof:placetype":"venue"
},
  "geometry": {"coordinates":[9.829661,53.64994],"type":"Point"}
}