{
  "type": "Feature",
  "properties": {
    "iso:country":"DE",
    "sg:address":"Kaarster Str. 51-53",
    "sg:city":"Kaarst",
    "sg:phone":"+49 2131/67168",
    "sg:postcode":"41564",
    "sg:province":"Nordrhein-Westfalen",
    "wof:name":"Pc-tronic Computer-handelsges. Mbh",
    "wof:placetype":"venue"
},
  "geometry": {"coordinates":[6.6076231003,51.2219848633],"type":"Point"}
}