{
  "type": "Feature",
  "properties": {
    "iso:country":"DE",
    "sg:address":"Lilienthalstr. 2",
    "sg:city":"Iserlohn",
    "sg:postcode":"58638",
    "sg:province":"Nordrhein-Westfalen",
    "wof:name":"Grabmale Friedrich Inh. Ludger Pempeit E. K.",
    "wof:placetype":"venue"
},
  "geometry": {"coordinates":[7.6802282333,51.3809623718],"type":"Point"}
}