{
  "type": "Feature",
  "properties": {
    "iso:country":"DE",
    "sg:address":"Weberplatz 3",
    "sg:city":"Essen",
    "sg:phone":"+49 201/202138",
    "sg:postcode":"45127",
    "sg:province":"Nordrhein-Westfalen",
    "wof:name":"Restaurant Rhodos",
    "wof:placetype":"venue"
},
  "geometry": {"coordinates":[7.0096421242,51.4594764709],"type":"Point"}
}