{
  "type": "Feature",
  "properties": {
    "iso:country":"DE",
    "sg:address":"Poller Kirchweg 63",
    "sg:city":"K\u00f6ln",
    "sg:phone":"+49 221/836236",
    "sg:postcode":"51105",
    "sg:province":"Nordrhein-Westfalen",
    "wof:name":"Clemens Metallbau Gmbh",
    "wof:placetype":"venue"
},
  "geometry": {"coordinates":[6.984237,50.918472],"type":"Point"}
}