{
  "type": "Feature",
  "properties": {
    "iso:country":"DE",
    "sg:address":"Hof Neuborn",
    "sg:city":"Dachsenhausen",
    "sg:phone":"+49 6776/589",
    "sg:postcode":"56340",
    "sg:province":"Rheinland-Pfalz",
    "wof:name":"Fritz Hof",
    "wof:placetype":"venue"
},
  "geometry": {"coordinates":[7.689816,50.243587],"type":"Point"}
}