{
  "type": "Feature",
  "properties": {
    "iso:country":"DE",
    "sg:address":"Ringstr. 3",
    "sg:city":"Diemelsee",
    "sg:phone":"+49 5633/5147",
    "sg:postcode":"34519",
    "sg:province":"Hessen",
    "wof:name":"H. J. Schwarzbach",
    "wof:placetype":"venue"
},
  "geometry": {"coordinates":[8.6977643967,51.3476066589],"type":"Point"}
}