{
  "type": "Feature",
  "properties": {
    "iso:country":"DE",
    "sg:address":"Kauffahrtei 25",
    "sg:city":"Chemnitz",
    "sg:phone":"+49 371/2804217",
    "sg:postcode":"09120",
    "sg:province":"Sachsen",
    "wof:name":"Karl-heinz Kandler Rechtsanwalt",
    "wof:placetype":"venue"
},
  "geometry": {"coordinates":[12.9048490524,50.8106460571],"type":"Point"}
}