{
  "type": "Feature",
  "properties": {
    "iso:country":"DE",
    "sg:address":"Hamf\u00e4hrer Weg 4",
    "sg:city":"Schwanewede",
    "sg:phone":"+49 4209/915831",
    "sg:postcode":"28790",
    "sg:province":"Niedersachsen",
    "wof:name":"Envi-tech Gmbh",
    "wof:placetype":"venue"
},
  "geometry": {"coordinates":[8.597102,53.248924],"type":"Point"}
}