{
  "type": "Feature",
  "properties": {
    "iso:country":"DE",
    "sg:address":"Zur Rehlbieke 37",
    "sg:city":"L\u00f6hne",
    "sg:phone":"+49 5732/71887",
    "sg:postcode":"32584",
    "sg:province":"Nordrhein-Westfalen",
    "wof:name":"Willi H\u00fcske",
    "wof:placetype":"venue"
},
  "geometry": {"coordinates":[8.746268,52.221733],"type":"Point"}
}