{
  "type": "Feature",
  "properties": {
    "iso:country":"DE",
    "sg:address":"E\u00dflinger Str. 1",
    "sg:city":"Tuttlingen",
    "sg:phone":"+49 7462/6263",
    "sg:postcode":"78532",
    "sg:province":"Baden-W\u00fcrttemberg",
    "wof:name":"A. Erath",
    "wof:placetype":"venue"
},
  "geometry": {"coordinates":[8.7675924301,47.9612770081],"type":"Point"}
}