{
  "type": "Feature",
  "properties": {
    "iso:country":"DE",
    "sg:address":"Siemensstr. 2",
    "sg:city":"Garbsen",
    "sg:phone":"+49 5131/6032",
    "sg:postcode":"30827",
    "sg:province":"Niedersachsen",
    "wof:name":"K\u00f6llner Motoren Import Ingrid Wegner",
    "wof:placetype":"venue"
},
  "geometry": {"coordinates":[9.61048,52.443077],"type":"Point"}
}