{
  "type": "Feature",
  "properties": {
    "iso:country":"DE",
    "sg:address":"Dietrichstal 7",
    "sg:city":"Bad Lauterberg",
    "sg:phone":"+49 5524/92260",
    "sg:postcode":"37431",
    "sg:province":"Niedersachsen",
    "wof:name":"Hotel Waldcafe Dietrichstal",
    "wof:placetype":"venue"
},
  "geometry": {"coordinates":[10.4928159714,51.6393013],"type":"Point"}
}