{
  "type": "Feature",
  "properties": {
    "iso:country":"DE",
    "sg:address":"Marktstr. 32",
    "sg:city":"Neuenb\u00fcrg",
    "sg:phone":"+49 7082/940229",
    "sg:postcode":"75305",
    "sg:province":"Baden-W\u00fcrttemberg",
    "wof:name":"Heckmeck",
    "wof:placetype":"venue"
},
  "geometry": {"coordinates":[8.5877771378,48.8467178345],"type":"Point"}
}