{
  "type": "Feature",
  "properties": {
    "iso:country":"DE",
    "sg:address":"Hauptstr. 3",
    "sg:city":"R\u00fchen",
    "sg:phone":"+49 5367/1831",
    "sg:postcode":"38471",
    "sg:province":"Niedersachsen",
    "wof:name":"H. Werner",
    "wof:placetype":"venue"
},
  "geometry": {"coordinates":[10.883527,52.48307],"type":"Point"}
}