{
  "type": "Feature",
  "properties": {
    "iso:country":"DE",
    "sg:address":"Carl-Schurz-Str. 12",
    "sg:city":"Berlin",
    "sg:phone":"+49 30/3333076",
    "sg:postcode":"13597",
    "sg:province":"Berlin",
    "wof:name":"C & A",
    "wof:placetype":"venue"
},
  "geometry": {"coordinates":[13.2016477585,52.5358695984],"type":"Point"}
}