{
  "type": "Feature",
  "properties": {
    "iso:country":"DE",
    "sg:address":"S\u00fcchtelner Str. 83",
    "sg:city":"Viersen",
    "sg:phone":"+49 2162/12220",
    "sg:postcode":"41747",
    "sg:province":"Nordrhein-Westfalen",
    "wof:name":"Neetix Gmbh",
    "wof:placetype":"venue"
},
  "geometry": {"coordinates":[6.384831,51.263676],"type":"Point"}
}