{
  "type": "Feature",
  "properties": {
    "iso:country":"DE",
    "sg:address":"Karst\u00e4dter Str. 9",
    "sg:city":"Rambow a See",
    "sg:phone":"+49 38781/40242",
    "sg:postcode":"19309",
    "sg:province":"Brandenburg",
    "wof:name":"J\u00f6rg Antes",
    "wof:placetype":"venue"
},
  "geometry": {"coordinates":[11.474708,53.090591],"type":"Point"}
}