{
  "type": "Feature",
  "properties": {
    "iso:country":"DE",
    "sg:address":"Hauptstr. 41",
    "sg:city":"Buxheim",
    "sg:phone":"+49 8331/72280",
    "sg:postcode":"87740",
    "sg:province":"Bayern",
    "wof:name":"Kartausen-apotheke",
    "wof:placetype":"venue"
},
  "geometry": {"coordinates":[10.131654,48.000282],"type":"Point"}
}