{
  "type": "Feature",
  "properties": {
    "iso:country":"DE",
    "sg:address":"Winkelsmaar 56",
    "sg:city":"K\u00f6ln",
    "sg:phone":"+49 2203/62266",
    "sg:postcode":"51147",
    "sg:province":"Nordrhein-Westfalen",
    "wof:name":"Profi-blinker Angelger\u00e4te Gmbh",
    "wof:placetype":"venue"
},
  "geometry": {"coordinates":[7.0940561295,50.8517990112],"type":"Point"}
}