{
  "type": "Feature",
  "properties": {
    "iso:country":"DE",
    "sg:address":"Am Sportplatz 1",
    "sg:city":"Langdorf",
    "sg:phone":"+49 9921/7332",
    "sg:postcode":"94264",
    "sg:province":"Bayern",
    "wof:name":"Karl-heinz Achatz Tennisanlage",
    "wof:placetype":"venue"
},
  "geometry": {"coordinates":[13.1486625671,49.0078735352],"type":"Point"}
}