{
  "type": "Feature",
  "properties": {
    "iso:country":"DE",
    "sg:address":"Overbeckstr. 9",
    "sg:city":"Hamburg",
    "sg:phone":"+49 40/2296793",
    "sg:postcode":"22085",
    "sg:province":"Hamburg",
    "wof:name":"D. Bernstorff Immobilienmakler",
    "wof:placetype":"venue"
},
  "geometry": {"coordinates":[10.0194501877,53.5695304871],"type":"Point"}
}