{
  "type": "Feature",
  "properties": {
    "iso:country":"DE",
    "sg:address":"M\u00fchlh\u00e4user Chaussee 11",
    "sg:city":"Eisenach",
    "sg:phone":"+49 3691/858585",
    "sg:postcode":"99817",
    "sg:province":"Th\u00fcringen",
    "wof:name":"Manfred Bender",
    "wof:placetype":"venue"
},
  "geometry": {"coordinates":[10.3140392303,50.9810066223],"type":"Point"}
}