{
  "type": "Feature",
  "properties": {
    "iso:country":"DE",
    "sg:address":"Otto-Behaghel-Str. 10 G",
    "sg:city":"Gie\u00dfen",
    "sg:phone":"+49 641/7025615",
    "sg:postcode":"35394",
    "sg:province":"Hessen",
    "wof:name":"Universit\u00e4t Gie\u00dfen Vergleichende Sprach-",
    "wof:placetype":"venue"
},
  "geometry": {"coordinates":[8.75076,50.600487],"type":"Point"}
}