{
  "type": "Feature",
  "properties": {
    "iso:country":"DE",
    "sg:address":"Freiligrathstr. 46",
    "sg:city":"Zeitz",
    "sg:phone":"+49 3441/250951",
    "sg:postcode":"06712",
    "sg:province":"Sachsen-Anhalt",
    "wof:name":"G\u00fcnther Ebenhoch",
    "wof:placetype":"venue"
},
  "geometry": {"coordinates":[12.1412534714,51.0540962219],"type":"Point"}
}