{
  "type": "Feature",
  "properties": {
    "iso:country":"DE",
    "sg:address":"Kirschbl\u00fctenstr. 13",
    "sg:city":"Wiesbaden",
    "sg:phone":"+49 611/421115",
    "sg:postcode":"65201",
    "sg:province":"Hessen",
    "wof:name":"Horst Huhn",
    "wof:placetype":"venue"
},
  "geometry": {"coordinates":[8.16789,50.067039],"type":"Point"}
}