{
  "type": "Feature",
  "properties": {
    "iso:country":"DE",
    "sg:address":"Dorfstr. 13",
    "sg:city":"Steinau",
    "sg:phone":"+49 6667/733",
    "sg:postcode":"36396",
    "sg:province":"Hessen",
    "wof:name":"Mister Wonder Magic F. Joustra",
    "wof:placetype":"venue"
},
  "geometry": {"coordinates":[9.43428,50.39217],"type":"Point"}
}