{
  "type": "Feature",
  "properties": {
    "iso:country":"DE",
    "sg:address":"Bahnhofsallee 20",
    "sg:city":"Solms",
    "sg:phone":"+49 6442/94120",
    "sg:postcode":"35606",
    "sg:province":"Hessen",
    "wof:name":"Klaus Lemper",
    "wof:placetype":"venue"
},
  "geometry": {"coordinates":[8.406794,50.543346],"type":"Point"}
}