{
  "type": "Feature",
  "properties": {
    "iso:country":"DE",
    "sg:address":"Hauptstr. 31",
    "sg:city":"Toppenstedt",
    "sg:phone":"+49 4173/7997",
    "sg:postcode":"21442",
    "sg:province":"Niedersachsen",
    "wof:name":"Horst Kasparek",
    "wof:placetype":"venue"
},
  "geometry": {"coordinates":[10.10969,53.263432],"type":"Point"}
}