{
  "type": "Feature",
  "properties": {
    "iso:country":"DE",
    "sg:address":"G\u00fcrtlerstr. 17",
    "sg:city":"Kaufbeuren",
    "sg:phone":"+49 8341/989969",
    "sg:postcode":"87600",
    "sg:province":"Bayern",
    "wof:name":"G\u00fcnter Zasche",
    "wof:placetype":"venue"
},
  "geometry": {"coordinates":[10.638474,47.915855],"type":"Point"}
}