{
  "type": "Feature",
  "properties": {
    "iso:country":"DE",
    "sg:address":"Willaringen 17",
    "sg:city":"Rickenbach",
    "sg:phone":"+49 7765/96673",
    "sg:postcode":"79736",
    "sg:province":"Baden-W\u00fcrttemberg",
    "wof:name":"Gerd Baumann",
    "wof:placetype":"venue"
},
  "geometry": {"coordinates":[7.9735407829,47.6060333252],"type":"Point"}
}