{
  "type": "Feature",
  "properties": {
    "iso:country":"DE",
    "sg:address":"M\u00fchlheimer Str. 211-213",
    "sg:city":"Offenbach",
    "sg:phone":"+49 69/861341",
    "sg:postcode":"63075",
    "sg:province":"Hessen",
    "wof:name":"Ricker Marmor-natursteine A. Martin Kg",
    "wof:placetype":"venue"
},
  "geometry": {"coordinates":[8.7954273224,50.1092948914],"type":"Point"}
}