{
  "type": "Feature",
  "properties": {
    "iso:country":"DE",
    "sg:address":"Bismarckstr. 23",
    "sg:city":"Bocholt",
    "sg:phone":"+49 2871/232630",
    "sg:postcode":"46397",
    "sg:province":"Nordrhein-Westfalen",
    "wof:name":"Makra Consulting Gmbh",
    "wof:placetype":"venue"
},
  "geometry": {"coordinates":[6.6224241257,51.8373718262],"type":"Point"}
}