{
  "type": "Feature",
  "properties": {
    "iso:country":"DE",
    "sg:address":"Otto-Hahn-Str. 10",
    "sg:city":"Herrenberg",
    "sg:phone":"+49 7032/31019",
    "sg:postcode":"71083",
    "sg:province":"Baden-W\u00fcrttemberg",
    "wof:name":"Eufa Fasteners Gmbh",
    "wof:placetype":"venue"
},
  "geometry": {"coordinates":[8.848793,48.613464],"type":"Point"}
}