{
  "type": "Feature",
  "properties": {
    "iso:country":"DE",
    "sg:address":"Hauptstr. 26",
    "sg:city":"Zapfendorf",
    "sg:phone":"+49 9547/323",
    "sg:postcode":"96199",
    "sg:province":"Bayern",
    "wof:name":"Volksbank Ebensfeld Eg",
    "wof:placetype":"venue"
},
  "geometry": {"coordinates":[10.933293,50.020451],"type":"Point"}
}