{
  "type": "Feature",
  "properties": {
    "iso:country":"DE",
    "sg:address":"Bleichstr. 2 b",
    "sg:city":"Bielefeld",
    "sg:phone":"+49 521/61613",
    "sg:postcode":"33607",
    "sg:province":"Nordrhein-Westfalen",
    "wof:name":"Hechelei",
    "wof:placetype":"venue"
},
  "geometry": {"coordinates":[8.5444850922,52.0228691101],"type":"Point"}
}