{
  "type": "Feature",
  "properties": {
    "iso:country":"DE",
    "sg:address":"Lohrhaupter Str. 18",
    "sg:city":"Jossgrund",
    "sg:phone":"+49 6059/364",
    "sg:postcode":"63637",
    "sg:province":"Hessen",
    "wof:name":"Ewald Hagemann",
    "wof:placetype":"venue"
},
  "geometry": {"coordinates":[9.472331,50.165459],"type":"Point"}
}