{
  "type": "Feature",
  "properties": {
    "iso:country":"DE",
    "sg:address":"Markt",
    "sg:city":"Kemberg",
    "sg:phone":"+49 34921/20272",
    "sg:postcode":"06901",
    "sg:province":"Sachsen-Anhalt",
    "wof:name":"E. Herrmann",
    "wof:placetype":"venue"
},
  "geometry": {"coordinates":[12.6363353729,51.7738800049],"type":"Point"}
}