{
  "type": "Feature",
  "properties": {
    "iso:country":"DE",
    "sg:address":"R\u00f6ntgenstr. 13",
    "sg:city":"Wittlich",
    "sg:phone":"+49 6571/5039",
    "sg:postcode":"54516",
    "sg:province":"Rheinland-Pfalz",
    "wof:name":"Colosseum",
    "wof:placetype":"venue"
},
  "geometry": {"coordinates":[6.910163,49.975605],"type":"Point"}
}