{
  "type": "Feature",
  "properties": {
    "iso:country":"DE",
    "sg:address":"Heidestr. 175e",
    "sg:city":"Dessau",
    "sg:phone":"+49 340/8824339",
    "sg:postcode":"06849",
    "sg:province":"Sachsen-Anhalt",
    "wof:name":"S. & R. Stavenhagen",
    "wof:placetype":"venue"
},
  "geometry": {"coordinates":[12.2418041229,51.809135437],"type":"Point"}
}