{
  "type": "Feature",
  "properties": {
    "iso:country":"DE",
    "sg:address":"Hauptstr. 69",
    "sg:city":"Langerwehe",
    "sg:phone":"+49 2423/5665",
    "sg:postcode":"52379",
    "sg:province":"Nordrhein-Westfalen",
    "wof:name":"Monique Paukner",
    "wof:placetype":"venue"
},
  "geometry": {"coordinates":[6.359301,50.818077],"type":"Point"}
}