{
  "type": "Feature",
  "properties": {
    "iso:country":"DE",
    "sg:address":"Wilsdorf 25A",
    "sg:city":"Dornburg",
    "sg:phone":"+49 36427/70244",
    "sg:postcode":"07778",
    "sg:province":"Th\u00fcringen",
    "wof:name":"Michael Thieme",
    "wof:placetype":"venue"
},
  "geometry": {"coordinates":[11.6436071396,51.0188941956],"type":"Point"}
}