{
  "type": "Feature",
  "properties": {
    "iso:country":"DE",
    "sg:address":"Wemdinger Str. 29",
    "sg:city":"M\u00fcnchen",
    "sg:phone":"+49 89/49000382",
    "sg:postcode":"81671",
    "sg:province":"Bayern",
    "wof:name":"Ziegler Druckvorlagen Gmbh",
    "wof:placetype":"venue"
},
  "geometry": {"coordinates":[11.6225004196,48.1194953918],"type":"Point"}
}