{
  "type": "Feature",
  "properties": {
    "iso:country":"DE",
    "sg:address":"Heitzerstr. 10",
    "sg:city":"Regensburg",
    "sg:phone":"+49 941/26031",
    "sg:postcode":"93049",
    "sg:province":"Bayern",
    "wof:name":"C. Esprester Steuerberater",
    "wof:placetype":"venue"
},
  "geometry": {"coordinates":[12.0754823685,49.0160942078],"type":"Point"}
}