{
  "type": "Feature",
  "properties": {
    "iso:country":"DE",
    "sg:address":"Vilbeler Landstr. 45 a",
    "sg:city":"Frankfurt",
    "sg:phone":"+49 6109/377836",
    "sg:postcode":"60388",
    "sg:province":"Hessen",
    "wof:name":"Interseroh-trading Zweigndl. Frankfurt Der",
    "wof:placetype":"venue"
},
  "geometry": {"coordinates":[8.756242,50.141846],"type":"Point"}
}