{
  "type": "Feature",
  "properties": {
    "iso:country":"DE",
    "sg:address":"Bonner Str. 335",
    "sg:city":"K\u00f6ln",
    "sg:phone":"+49 221/3405395",
    "sg:postcode":"50968",
    "sg:province":"Nordrhein-Westfalen",
    "wof:name":"Gastst\u00e4tte \u00c4. Br\u00fcncker",
    "wof:placetype":"venue"
},
  "geometry": {"coordinates":[6.964468956,50.904876709],"type":"Point"}
}