{
  "type": "Feature",
  "properties": {
    "iso:country":"DE",
    "sg:address":"Mitteranger 18",
    "sg:city":"Murnau",
    "sg:phone":"+49 8841/620000",
    "sg:postcode":"82418",
    "sg:province":"Bayern",
    "wof:name":"Cura Treuhand Wirtschaftspr\u00fcfungs- Und",
    "wof:placetype":"venue"
},
  "geometry": {"coordinates":[11.2066450119,47.6820602417],"type":"Point"}
}