{
  "type": "Feature",
  "properties": {
    "iso:country":"DE",
    "sg:address":"Hintergasse 1",
    "sg:city":"Herleshausen",
    "sg:phone":"+49 5654/1344",
    "sg:postcode":"37293",
    "sg:province":"Hessen",
    "wof:name":"J. Deubener Praxis F\u00fcr Physiotherapie",
    "wof:placetype":"venue"
},
  "geometry": {"coordinates":[10.162467,51.005726],"type":"Point"}
}