{
  "type": "Feature",
  "properties": {
    "iso:country":"DE",
    "sg:address":"Spitzbergstr. 6",
    "sg:city":"Oderwitz",
    "sg:phone":"+49 35842/27990",
    "sg:postcode":"02791",
    "sg:province":"Sachsen",
    "wof:name":"Spitzbergbaude Inh. Jochen Kaminski",
    "wof:placetype":"venue"
},
  "geometry": {"coordinates":[14.7002229691,50.9654502869],"type":"Point"}
}