{
  "type": "Feature",
  "properties": {
    "iso:country":"DE",
    "sg:address":"Altlandsberger Str. 1",
    "sg:city":"R\u00fcdersdorf",
    "sg:phone":"+49 33638/4285",
    "sg:postcode":"15562",
    "sg:province":"Brandenburg",
    "wof:name":"S. Fink Baumaschinen Und Hebezeuge Gmbh & Co. Kg",
    "wof:placetype":"venue"
},
  "geometry": {"coordinates":[13.8137149811,52.4693031311],"type":"Point"}
}