{
  "type": "Feature",
  "properties": {
    "iso:country":"DE",
    "sg:address":"Aachener Str. 128",
    "sg:city":"Baesweiler",
    "sg:phone":"+49 2401/2406",
    "sg:postcode":"52499",
    "sg:province":"Nordrhein-Westfalen",
    "wof:name":"Dea-tankstelle",
    "wof:placetype":"venue"
},
  "geometry": {"coordinates":[6.1906671524,50.910068512],"type":"Point"}
}