{
  "type": "Feature",
  "properties": {
    "iso:country":"DE",
    "sg:address":"Deschinger Str. 15",
    "sg:city":"Ingolstadt",
    "sg:phone":"+49 841/58724",
    "sg:postcode":"85055",
    "sg:province":"Bayern",
    "wof:name":"Inge Sengl",
    "wof:placetype":"venue"
},
  "geometry": {"coordinates":[11.452733,48.787354],"type":"Point"}
}