{
  "type": "Feature",
  "properties": {
    "iso:country":"DE",
    "sg:address":"Hermann-L\u00f6ns-Str. 63",
    "sg:city":"Herne",
    "sg:phone":"+49 2323/12344",
    "sg:postcode":"44623",
    "sg:province":"Nordrhein-Westfalen",
    "wof:name":"Aydemir",
    "wof:placetype":"venue"
},
  "geometry": {"coordinates":[7.2247200012,51.5431556702],"type":"Point"}
}