{
  "type": "Feature",
  "properties": {
    "iso:country":"DE",
    "sg:address":"Meller Str. 254a",
    "sg:city":"Osnabr\u00fcck",
    "sg:phone":"+49 541/588208",
    "sg:postcode":"49082",
    "sg:province":"Niedersachsen",
    "wof:name":"Kreiswehrsch\u00e4nke",
    "wof:placetype":"venue"
},
  "geometry": {"coordinates":[8.0793027878,52.2575683594],"type":"Point"}
}