{
  "type": "Feature",
  "properties": {
    "iso:country":"DE",
    "sg:address":"Ostseeallee 40",
    "sg:city":"Rostock",
    "sg:phone":"+49 381/7767676",
    "sg:postcode":"18107",
    "sg:province":"Mecklenburg-Vorpommern",
    "wof:name":"Steuerberaterkammer Mecklenburg-vorpommern",
    "wof:placetype":"venue"
},
  "geometry": {"coordinates":[12.043434,54.141251],"type":"Point"}
}