{
  "type": "Feature",
  "properties": {
    "iso:country":"DE",
    "sg:address":"Arno-Assmann-Stra\u00dfe 9",
    "sg:city":"M\u00fcnchen",
    "sg:postcode":"81739",
    "sg:province":"Bayern",
    "wof:name":"Ingenieurb\u00fcro Kreft&tauschek Gbr",
    "wof:placetype":"venue"
},
  "geometry": {"coordinates":[11.637881279,48.0952644348],"type":"Point"}
}