{
  "type": "Feature",
  "properties": {
    "iso:country":"DE",
    "sg:address":"Mindener Landstr. 22",
    "sg:city":"Estorf",
    "sg:phone":"+49 5025/1025",
    "sg:postcode":"31629",
    "sg:province":"Niedersachsen",
    "wof:name":"Restaurant Sandkrug",
    "wof:placetype":"venue"
},
  "geometry": {"coordinates":[9.1422157288,52.5888824463],"type":"Point"}
}