{
  "type": "Feature",
  "properties": {
    "iso:country":"DE",
    "sg:address":"Piepenbreite 21",
    "sg:city":"Obernkirchen",
    "sg:phone":"+49 5724/8494",
    "sg:postcode":"31683",
    "sg:province":"Niedersachsen",
    "wof:name":"Rosel Rebatschek-otto",
    "wof:placetype":"venue"
},
  "geometry": {"coordinates":[9.136049,52.266582],"type":"Point"}
}