{
  "type": "Feature",
  "properties": {
    "iso:country":"DE",
    "sg:address":"Blocksbergstr.151",
    "sg:city":"Pirmasens",
    "sg:phone":"+49 4963/3126300",
    "sg:postcode":"66955",
    "sg:province":"Rheinland-Pfalz",
    "wof:name":"Afis International Schuhproduktion Gmbh",
    "wof:placetype":"venue"
},
  "geometry": {"coordinates":[7.58124,49.184097],"type":"Point"}
}