{
  "type": "Feature",
  "properties": {
    "iso:country":"DE",
    "sg:address":"Auf der Schmelz 10",
    "sg:city":"Sulzbach",
    "sg:phone":"+49 6897/51161",
    "sg:postcode":"66280",
    "sg:province":"Saarland",
    "wof:name":"G. Frank",
    "wof:placetype":"venue"
},
  "geometry": {"coordinates":[7.060683,49.297962],"type":"Point"}
}