{
  "type": "Feature",
  "properties": {
    "iso:country":"DE",
    "sg:address":"Gehringstr. 15",
    "sg:city":"Berlin",
    "sg:postcode":"13088",
    "sg:province":"Berlin",
    "wof:name":"M.c.f. Mobil-center Grundbesitzverwaltungs Gmbh",
    "wof:placetype":"venue"
},
  "geometry": {"coordinates":[13.462049,52.562546],"type":"Point"}
}