{
  "type": "Feature",
  "properties": {
    "iso:country":"DE",
    "sg:address":"Bahnhofstr. 31",
    "sg:city":"Treuen",
    "sg:phone":"+49 37468/2438",
    "sg:postcode":"08233",
    "sg:province":"Sachsen",
    "wof:name":"Eiscafe Rudi Pieschel",
    "wof:placetype":"venue"
},
  "geometry": {"coordinates":[12.300725,50.545353],"type":"Point"}
}