{
  "type": "Feature",
  "properties": {
    "iso:country":"DE",
    "sg:address":"Charlottenstr. 37",
    "sg:city":"T\u00fcbingen",
    "sg:phone":"+49 7071/408930",
    "sg:postcode":"72070",
    "sg:province":"Baden-W\u00fcrttemberg",
    "wof:name":"Bauer Immobilien Gmbh",
    "wof:placetype":"venue"
},
  "geometry": {"coordinates":[9.0440568924,48.5249671936],"type":"Point"}
}