{
  "type": "Feature",
  "properties": {
    "iso:country":"DE",
    "sg:address":"Ilsenburger Str. 7",
    "sg:city":"Dr\u00fcbeck",
    "sg:phone":"+49 39452/2774",
    "sg:postcode":"38871",
    "sg:province":"Sachsen-Anhalt",
    "wof:name":"Rudolf Bartsch",
    "wof:placetype":"venue"
},
  "geometry": {"coordinates":[10.708831,51.856972],"type":"Point"}
}