{
  "type": "Feature",
  "properties": {
    "iso:country":"DE",
    "sg:address":"Dollendorfer Str. 259",
    "sg:city":"K\u00f6nigswinter",
    "sg:phone":"+49 2244/1685",
    "sg:postcode":"53639",
    "sg:province":"Nordrhein-Westfalen",
    "wof:name":"Dietmar Sakowitz Steuerberater",
    "wof:placetype":"venue"
},
  "geometry": {"coordinates":[7.2412462234,50.7028083801],"type":"Point"}
}