{
  "type": "Feature",
  "properties": {
    "iso:country":"DE",
    "sg:address":"Bahnhofstr. 52",
    "sg:city":"Unna",
    "sg:phone":"+49 2303/22277",
    "sg:postcode":"59423",
    "sg:province":"Nordrhein-Westfalen",
    "wof:name":"Trittbrett",
    "wof:placetype":"venue"
},
  "geometry": {"coordinates":[7.6911139488,51.5388298035],"type":"Point"}
}