{
  "type": "Feature",
  "properties": {
    "iso:country":"DE",
    "sg:address":"Eheweg 26",
    "sg:city":"Aurich",
    "sg:phone":"+49 4941/7816",
    "sg:postcode":"26607",
    "sg:province":"Niedersachsen",
    "wof:name":"Heye Wilts",
    "wof:placetype":"venue"
},
  "geometry": {"coordinates":[7.510846,53.494503],"type":"Point"}
}