{
  "type": "Feature",
  "properties": {
    "iso:country":"DE",
    "sg:address":"Flughafenstr. 120",
    "sg:city":"D\u00fcsseldorf",
    "sg:postcode":"40474",
    "sg:province":"Nordrhein-Westfalen",
    "wof:name":"Flughafen D\u00fcsseldorf Cargo Gmbh",
    "wof:placetype":"venue"
},
  "geometry": {"coordinates":[6.7663259506,51.2756996155],"type":"Point"}
}