{
  "type": "Feature",
  "properties": {
    "iso:country":"DE",
    "sg:address":"Rebenring 8",
    "sg:city":"Braunschweig",
    "sg:phone":"+49 531",
    "sg:postcode":"38106",
    "sg:province":"Niedersachsen",
    "wof:name":"Wyrwas Studiotechnik Gmbh",
    "wof:placetype":"venue"
},
  "geometry": {"coordinates":[10.523684,52.27544],"type":"Point"}
}