{
  "type": "Feature",
  "properties": {
    "iso:country":"DE",
    "sg:address":"Hauenriede 19",
    "sg:city":"Uelzen",
    "sg:phone":"+49 581/90330",
    "sg:postcode":"29525",
    "sg:province":"Niedersachsen",
    "wof:name":"Dr. Spils Ad Wilken Ra\u00dfmann & Partner Gmbh",
    "wof:placetype":"venue"
},
  "geometry": {"coordinates":[10.5469388962,52.9694404602],"type":"Point"}
}