{
  "type": "Feature",
  "properties": {
    "iso:country":"DE",
    "sg:address":"Stresemannstr. 21",
    "sg:city":"Berlin",
    "sg:phone":"+49 30/2510527",
    "sg:postcode":"10963",
    "sg:province":"Berlin",
    "wof:name":"Kalisch & Kreiseler Gmbh",
    "wof:placetype":"venue"
},
  "geometry": {"coordinates":[13.3875331879,52.4999275208],"type":"Point"}
}