{
  "type": "Feature",
  "properties": {
    "iso:country":"DE",
    "sg:address":"Postenweg 19 a",
    "sg:city":"Oldenburg",
    "sg:phone":"+49 441/73282",
    "sg:postcode":"26129",
    "sg:province":"Niedersachsen",
    "wof:name":"Postensch\u00e4nke",
    "wof:placetype":"venue"
},
  "geometry": {"coordinates":[8.1717128754,53.1435813904],"type":"Point"}
}