{
  "type": "Feature",
  "properties": {
    "iso:country":"DE",
    "sg:address":"Hans-B\u00f6ckler-Allee 29",
    "sg:city":"Aachen",
    "sg:phone":"+49 241/876133",
    "sg:postcode":"52074",
    "sg:province":"Nordrhein-Westfalen",
    "wof:name":"Gds-textil-gmbh",
    "wof:placetype":"venue"
},
  "geometry": {"coordinates":[6.0344882011,50.7742233276],"type":"Point"}
}