{
  "type": "Feature",
  "properties": {
    "iso:country":"DE",
    "sg:address":"Holtschneiderweg 27 A",
    "sg:city":"Br\u00fcggen",
    "sg:postcode":"41379",
    "sg:province":"Nordrhein-Westfalen",
    "wof:name":"T. S. P. Transporte Service Und Paketdienst Gmbh",
    "wof:placetype":"venue"
},
  "geometry": {"coordinates":[6.1855249405,51.2422637939],"type":"Point"}
}