{
  "type": "Feature",
  "properties": {
    "iso:country":"DE",
    "sg:address":"Steingau",
    "sg:city":"Otterfing",
    "sg:phone":"+49 8024/7493",
    "sg:postcode":"83624",
    "sg:province":"Bayern",
    "wof:name":"Katholisches Pfarramt St. Martin",
    "wof:placetype":"venue"
},
  "geometry": {"coordinates":[11.6754627228,47.9089012146],"type":"Point"}
}