{
  "type": "Feature",
  "properties": {
    "iso:country":"DE",
    "sg:address":"Martinrodaer Str 1",
    "sg:city":"Heyda",
    "sg:phone":"+49 3677/840944",
    "sg:postcode":"98693",
    "sg:province":"Th\u00fcringen",
    "wof:name":"Spedition Andreas Kirsten",
    "wof:placetype":"venue"
},
  "geometry": {"coordinates":[10.9348287582,50.734287262],"type":"Point"}
}