{
  "type": "Feature",
  "properties": {
    "iso:country":"DE",
    "sg:address":"Hirtenweg 14",
    "sg:city":"Lichtenwald",
    "sg:phone":"+49 7153/42952",
    "sg:postcode":"73669",
    "sg:province":"Baden-W\u00fcrttemberg",
    "wof:name":"Am",
    "wof:placetype":"venue"
},
  "geometry": {"coordinates":[9.47587,48.732258],"type":"Point"}
}