{
  "type": "Feature",
  "properties": {
    "iso:country":"DE",
    "sg:address":"Rudolf-Diesel-Str. 8",
    "sg:city":"Frechen",
    "sg:phone":"+49 2234/17695",
    "sg:postcode":"50226",
    "sg:province":"Nordrhein-Westfalen",
    "wof:name":"Df Datenverarbeitung Frechen Gmbh & Co. Kg",
    "wof:placetype":"venue"
},
  "geometry": {"coordinates":[6.821434021,50.9210777283],"type":"Point"}
}