{
  "type": "Feature",
  "properties": {
    "iso:country":"DE",
    "sg:address":"Hartlage 20",
    "sg:city":"Diepholz",
    "sg:phone":"+49 5441/1513",
    "sg:postcode":"49356",
    "sg:province":"Niedersachsen",
    "wof:name":"Berthold Sandmann",
    "wof:placetype":"venue"
},
  "geometry": {"coordinates":[8.380972,52.577251],"type":"Point"}
}