{
  "type": "Feature",
  "properties": {
    "iso:country":"DE",
    "sg:address":"Holzhauser Str. 16-18",
    "sg:city":"Berlin",
    "sg:phone":"+49 30/430090",
    "sg:postcode":"13509",
    "sg:province":"Berlin",
    "wof:name":"Efk Gesellschaft F\u00fcr Schl\u00fcsselfertiges Bauen Mbh",
    "wof:placetype":"venue"
},
  "geometry": {"coordinates":[13.2966327667,52.5770072937],"type":"Point"}
}