{
  "type": "Feature",
  "properties": {
    "iso:country":"DE",
    "sg:address":"Heckinghauser Str. 65",
    "sg:city":"Wuppertal",
    "sg:phone":"+49 202/624397",
    "sg:postcode":"42289",
    "sg:province":"Nordrhein-Westfalen",
    "wof:name":"Spielstube",
    "wof:placetype":"venue"
},
  "geometry": {"coordinates":[7.2107510567,51.2714309692],"type":"Point"}
}