{
  "type": "Feature",
  "properties": {
    "iso:country":"DE",
    "sg:address":"August-L\u00e4mmle-Str. 38",
    "sg:city":"Aspach",
    "sg:phone":"+49 4971/9120211",
    "sg:postcode":"71546",
    "sg:province":"Baden-W\u00fcrttemberg",
    "wof:name":"Jaroslav Dolak",
    "wof:placetype":"venue"
},
  "geometry": {"coordinates":[9.4060926437,48.9859390259],"type":"Point"}
}