{
  "type": "Feature",
  "properties": {
    "iso:country":"DE",
    "sg:address":"Sophienstr. 27",
    "sg:city":"Frankfurt",
    "sg:phone":"+49 69/70794890",
    "sg:postcode":"60487",
    "sg:province":"Hessen",
    "wof:name":"Schmitz-br\u00fcmmer",
    "wof:placetype":"venue"
},
  "geometry": {"coordinates":[8.6494283676,50.1234054565],"type":"Point"}
}