{
  "type": "Feature",
  "properties": {
    "iso:country":"DE",
    "sg:address":"Hauptstr. 48",
    "sg:city":"Neuss",
    "sg:phone":"+49 2131/460697",
    "sg:postcode":"41472",
    "sg:province":"Nordrhein-Westfalen",
    "wof:name":"Andreas Gabler",
    "wof:placetype":"venue"
},
  "geometry": {"coordinates":[6.668342,51.158779],"type":"Point"}
}