{
  "type": "Feature",
  "properties": {
    "iso:country":"DE",
    "sg:address":"Martinstr. 95",
    "sg:city":"Krefeld",
    "sg:phone":"+49 2151/311788",
    "sg:postcode":"47805",
    "sg:province":"Nordrhein-Westfalen",
    "wof:name":"Waltraud Wendorf",
    "wof:placetype":"venue"
},
  "geometry": {"coordinates":[6.556166172,51.3194046021],"type":"Point"}
}