{
  "type": "Feature",
  "properties": {
    "iso:country":"DE",
    "sg:address":"Erdinger Str 45",
    "sg:city":"Freising",
    "sg:phone":"+49 8161/99130",
    "sg:postcode":"85356",
    "sg:province":"Bayern",
    "wof:name":"Intertec Components Gmbh",
    "wof:placetype":"venue"
},
  "geometry": {"coordinates":[11.7576036453,48.3952980042],"type":"Point"}
}