{
  "type": "Feature",
  "properties": {
    "iso:country":"DE",
    "sg:address":"Bruchstr. 3",
    "sg:city":"Rietberg",
    "sg:phone":"+49 5244/78479",
    "sg:postcode":"33397",
    "sg:province":"Nordrhein-Westfalen",
    "wof:name":"Nordgerling",
    "wof:placetype":"venue"
},
  "geometry": {"coordinates":[8.426294,51.805573],"type":"Point"}
}