{
  "type": "Feature",
  "properties": {
    "iso:country":"DE",
    "sg:address":"Am Graben 2-6",
    "sg:city":"Radevormwald",
    "sg:phone":"+49 2191/463300",
    "sg:postcode":"42477",
    "sg:province":"Nordrhein-Westfalen",
    "wof:name":"Winterhoff Zerspanungstechnik E.k.",
    "wof:placetype":"venue"
},
  "geometry": {"coordinates":[7.316303,51.22147],"type":"Point"}
}