{
  "type": "Feature",
  "properties": {
    "iso:country":"DE",
    "sg:address":"Bartelskamp 30",
    "sg:city":"Velbert",
    "sg:phone":"+49 2051/66878",
    "sg:postcode":"42549",
    "sg:province":"Nordrhein-Westfalen",
    "wof:name":"M. Zemke Architekt",
    "wof:placetype":"venue"
},
  "geometry": {"coordinates":[7.036975,51.327457],"type":"Point"}
}