{
  "type": "Feature",
  "properties": {
    "iso:country":"DE",
    "sg:address":"Giesestr. 22",
    "sg:city":"Iserlohn",
    "sg:phone":"+49 2371/40007",
    "sg:postcode":"58636",
    "sg:province":"Nordrhein-Westfalen",
    "wof:name":"Wigra Offsetdruck Gmbh",
    "wof:placetype":"venue"
},
  "geometry": {"coordinates":[7.699709,51.399879],"type":"Point"}
}