{
  "type": "Feature",
  "properties": {
    "iso:country":"DE",
    "sg:address":"Hochstr. 61",
    "sg:city":"Saarbr\u00fccken",
    "sg:phone":"+49 681/99200",
    "sg:postcode":"66115",
    "sg:province":"Saarland",
    "wof:name":"Ingo Wunderlich",
    "wof:placetype":"venue"
},
  "geometry": {"coordinates":[6.9588179588,49.2411956787],"type":"Point"}
}