{
  "type": "Feature",
  "properties": {
    "iso:country":"DE",
    "sg:address":"Ronheider Berg 221",
    "sg:city":"Aachen",
    "sg:phone":"+49 241/709523",
    "sg:postcode":"52076",
    "sg:province":"Nordrhein-Westfalen",
    "wof:name":"Ronheide",
    "wof:placetype":"venue"
},
  "geometry": {"coordinates":[6.0687122345,50.7487602234],"type":"Point"}
}