{
  "type": "Feature",
  "properties": {
    "iso:country":"DE",
    "sg:address":"Raiffeisenstr. 3",
    "sg:city":"Wiesbaden",
    "sg:postcode":"65191",
    "sg:province":"Hessen",
    "wof:name":"Marion Engelmann",
    "wof:placetype":"venue"
},
  "geometry": {"coordinates":[8.284296,50.082676],"type":"Point"}
}