{
  "type": "Feature",
  "properties": {
    "iso:country":"DE",
    "sg:address":"Hauptstr. 69",
    "sg:city":"Reckendorf",
    "sg:phone":"+49 9544/1590",
    "sg:postcode":"96182",
    "sg:province":"Bayern",
    "wof:name":"H. Schug",
    "wof:placetype":"venue"
},
  "geometry": {"coordinates":[10.8267612457,50.0212287903],"type":"Point"}
}