{
  "type": "Feature",
  "properties": {
    "iso:country":"DE",
    "sg:address":"Oberbruchstr. 133",
    "sg:city":"Krefeld",
    "sg:phone":"+49 2151/305814",
    "sg:postcode":"47807",
    "sg:province":"Nordrhein-Westfalen",
    "wof:name":"Egon Hover",
    "wof:placetype":"venue"
},
  "geometry": {"coordinates":[6.5956501961,51.3105392456],"type":"Point"}
}