{
  "type": "Feature",
  "properties": {
    "iso:country":"DE",
    "sg:address":"Daimlerstr. 6",
    "sg:city":"Maintal",
    "sg:phone":"+49 6181/491833",
    "sg:postcode":"63477",
    "sg:province":"Hessen",
    "wof:name":"Edwin Hoffmann Architekt",
    "wof:placetype":"venue"
},
  "geometry": {"coordinates":[8.847631,50.141052],"type":"Point"}
}