{
  "type": "Feature",
  "properties": {
    "iso:country":"DE",
    "sg:address":"Karpfengasse 8",
    "sg:city":"Biberach",
    "sg:postcode":"88400",
    "sg:province":"Baden-W\u00fcrttemberg",
    "wof:name":"Blumenk\u00f6rble",
    "wof:placetype":"venue"
},
  "geometry": {"coordinates":[9.788584,48.097176],"type":"Point"}
}