{
  "type": "Feature",
  "properties": {
    "iso:country":"DE",
    "sg:address":"Oberhofer Str. 3",
    "sg:city":"Tambach-Dietharz",
    "sg:phone":"+49 36252/36149",
    "sg:postcode":"99897",
    "sg:province":"Th\u00fcringen",
    "wof:name":"Jugendherberge Tambach-dietharz",
    "wof:placetype":"venue"
},
  "geometry": {"coordinates":[10.6178970337,50.7955436707],"type":"Point"}
}