{
  "type": "Feature",
  "properties": {
    "iso:country":"DE",
    "sg:address":"Semmelweisstra\u00dfe 2",
    "sg:city":"Havelberg",
    "sg:phone":"+49 39382/8215",
    "sg:postcode":"39539",
    "sg:province":"Sachsen-Anhalt",
    "wof:name":"Kreissparkasse",
    "wof:placetype":"venue"
},
  "geometry": {"coordinates":[12.078919,52.830353],"type":"Point"}
}