{
  "type": "Feature",
  "properties": {
    "iso:country":"DE",
    "sg:address":"Karlstr. 135-139",
    "sg:city":"Essen",
    "sg:phone":"+49 201/356226",
    "sg:postcode":"45329",
    "sg:province":"Nordrhein-Westfalen",
    "wof:name":"Ariana Reifen Gmbh",
    "wof:placetype":"venue"
},
  "geometry": {"coordinates":[7.015416,51.505898],"type":"Point"}
}