{
  "type": "Feature",
  "properties": {
    "iso:country":"DE",
    "sg:address":"Frankenfelder Str. 10",
    "sg:city":"Nuthe-Urstromtal",
    "sg:postcode":"14947",
    "sg:province":"Brandenburg",
    "wof:name":"Meding Gmbh",
    "wof:placetype":"venue"
},
  "geometry": {"coordinates":[13.1620740891,52.1248626709],"type":"Point"}
}