{
  "type": "Feature",
  "properties": {
    "iso:country":"DE",
    "sg:address":"Grenzstra\u00dfe 65",
    "sg:city":"Wilhelmshaven",
    "sg:phone":"+49 4421/81886",
    "sg:postcode":"26382",
    "sg:province":"Niedersachsen",
    "wof:name":"Fahrschule Hermann Und Jens Ahlers",
    "wof:placetype":"venue"
},
  "geometry": {"coordinates":[8.1125946045,53.5263214111],"type":"Point"}
}