{
  "type": "Feature",
  "properties": {
    "iso:country":"DE",
    "sg:address":"Ottendorfer Str. 12",
    "sg:city":"Dresden",
    "sg:phone":"+49 351/800970",
    "sg:postcode":"01127",
    "sg:province":"Sachsen",
    "wof:name":"Ingenieurbau George B\u00e4hr Gmbh",
    "wof:placetype":"venue"
},
  "geometry": {"coordinates":[13.7441778183,51.080909729],"type":"Point"}
}