{
  "type": "Feature",
  "properties": {
    "iso:country":"DE",
    "sg:address":"Bitburger Str. 4",
    "sg:city":"Utscheid",
    "sg:phone":"+49 6564/480040",
    "sg:postcode":"54675",
    "sg:province":"Rheinland-Pfalz",
    "wof:name":"Gerd Lackas",
    "wof:placetype":"venue"
},
  "geometry": {"coordinates":[6.3565340042,49.9922485352],"type":"Point"}
}