{
  "type": "Feature",
  "properties": {
    "iso:country":"DE",
    "sg:address":"Grasweg 6",
    "sg:city":"Lemgo",
    "sg:phone":"+49 5261/89015",
    "sg:postcode":"32657",
    "sg:province":"Nordrhein-Westfalen",
    "wof:name":"Herbert Zimmermann",
    "wof:placetype":"venue"
},
  "geometry": {"coordinates":[8.924325943,52.0150032043],"type":"Point"}
}