{
  "type": "Feature",
  "properties": {
    "iso:country":"DE",
    "sg:address":"Hipperstr. 5",
    "sg:city":"Pl\u00f6n",
    "sg:phone":"+49 4522/9500",
    "sg:postcode":"24306",
    "sg:province":"Schleswig-Holstein",
    "wof:name":"J\u00fcrgen Bockelmann Ingenieur",
    "wof:placetype":"venue"
},
  "geometry": {"coordinates":[10.4400663376,54.1590881348],"type":"Point"}
}