{
  "type": "Feature",
  "properties": {
    "iso:country":"DE",
    "sg:address":"Hauptstr. 7",
    "sg:city":"Sankt Wolfgang",
    "sg:phone":"+49 8085/844",
    "sg:postcode":"84427",
    "sg:province":"Bayern",
    "wof:name":"Braust\u00fcberl",
    "wof:placetype":"venue"
},
  "geometry": {"coordinates":[12.1350708008,48.2187194824],"type":"Point"}
}