{
  "type": "Feature",
  "properties": {
    "iso:country":"DE",
    "sg:address":"Am Knill 71",
    "sg:city":"Hamburg",
    "sg:phone":"+49 40/6431561",
    "sg:postcode":"22147",
    "sg:province":"Hamburg",
    "wof:name":"Walter Berg",
    "wof:placetype":"venue"
},
  "geometry": {"coordinates":[10.1277475357,53.6107177734],"type":"Point"}
}