{
  "type": "Feature",
  "properties": {
    "iso:country":"DE",
    "sg:address":"Thingstr. 3",
    "sg:city":"Lippstadt",
    "sg:phone":"+49 2941/12334",
    "sg:postcode":"59558",
    "sg:province":"Nordrhein-Westfalen",
    "wof:name":"J.w. Hammer",
    "wof:placetype":"venue"
},
  "geometry": {"coordinates":[8.400032,51.667824],"type":"Point"}
}