{
  "type": "Feature",
  "properties": {
    "iso:country":"DE",
    "sg:address":"Mittelstr. 1",
    "sg:city":"Kreuzau",
    "sg:phone":"+49 2422/7129",
    "sg:postcode":"52372",
    "sg:province":"Nordrhein-Westfalen",
    "wof:name":"Lorenz Brings",
    "wof:placetype":"venue"
},
  "geometry": {"coordinates":[6.4879198074,50.7471923828],"type":"Point"}
}