{
  "type": "Feature",
  "properties": {
    "iso:country":"DE",
    "sg:address":"Bruchfeldstr. 80",
    "sg:city":"Frankfurt",
    "sg:phone":"+49 69/671390",
    "sg:postcode":"60528",
    "sg:province":"Hessen",
    "wof:name":"Reformhaus Niederrad S. Krause",
    "wof:placetype":"venue"
},
  "geometry": {"coordinates":[8.642332077,50.0864982605],"type":"Point"}
}