{
  "type": "Feature",
  "properties": {
    "iso:country":"DE",
    "sg:address":"Hohe Luft 6",
    "sg:city":"Heeslingen",
    "sg:postcode":"27404",
    "sg:province":"Niedersachsen",
    "wof:name":"West-pol Gmbh Zwndl. Heeslingen",
    "wof:placetype":"venue"
},
  "geometry": {"coordinates":[9.3428344727,53.3195533752],"type":"Point"}
}