{
  "type": "Feature",
  "properties": {
    "iso:country":"DE",
    "sg:address":"Raiffeisenstr. 8",
    "sg:city":"Friedberg",
    "sg:phone":"+49 6031/3051",
    "sg:postcode":"61169",
    "sg:province":"Hessen",
    "wof:name":"Knud Stenzel Rechtsanwalt",
    "wof:placetype":"venue"
},
  "geometry": {"coordinates":[8.764172554,50.325958252],"type":"Point"}
}