{
  "type": "Feature",
  "properties": {
    "iso:country":"DE",
    "sg:address":"Auf der Heide 11",
    "sg:city":"Langenfeld",
    "sg:phone":"+49 2655/1818",
    "sg:postcode":"56729",
    "sg:province":"Rheinland-Pfalz",
    "wof:name":"Dr. Jean Bausch Kg",
    "wof:placetype":"venue"
},
  "geometry": {"coordinates":[7.0876998901,50.3800697327],"type":"Point"}
}