{
  "type": "Feature",
  "properties": {
    "iso:country":"DE",
    "sg:address":"Beethovenstr. 44",
    "sg:city":"Wegberg",
    "sg:phone":"+49 2161/666636",
    "sg:postcode":"41844",
    "sg:province":"Nordrhein-Westfalen",
    "wof:name":"Rhein Ruhr Helicopter Reiner Zemke Gmbh & Co. Kg",
    "wof:placetype":"venue"
},
  "geometry": {"coordinates":[6.177947,51.153957],"type":"Point"}
}