{
  "type": "Feature",
  "properties": {
    "iso:country":"DE",
    "sg:address":"Eggeroder Str. 4",
    "sg:city":"Horstmar",
    "sg:postcode":"48612",
    "sg:province":"Nordrhein-Westfalen",
    "wof:name":"Reventa Kunststoffverarbeitung U. -vertriebsges. Mbh & Co. Kg",
    "wof:placetype":"venue"
},
  "geometry": {"coordinates":[7.298496,52.080109],"type":"Point"}
}