{
  "type": "Feature",
  "properties": {
    "iso:country":"DE",
    "sg:address":"Dorfstr. 32",
    "sg:city":"Nienb\u00fcttel",
    "sg:phone":"+49 4827/2234",
    "sg:postcode":"25596",
    "sg:province":"Schleswig-Holstein",
    "wof:name":"J\u00fcrgen H. E. Str\u00f6h Architekt",
    "wof:placetype":"venue"
},
  "geometry": {"coordinates":[9.417436,54.03281],"type":"Point"}
}