{
  "type": "Feature",
  "properties": {
    "iso:country":"DE",
    "sg:address":"Dorfstr. 18",
    "sg:city":"Wangels",
    "sg:postcode":"23758",
    "sg:province":"Schleswig-Holstein",
    "wof:name":"J.-p. Und M. Bohnsack Finanzberater",
    "wof:placetype":"venue"
},
  "geometry": {"coordinates":[10.7304201126,54.295124054],"type":"Point"}
}