{
  "type": "Feature",
  "properties": {
    "iso:country":"DE",
    "sg:address":"Am Stechersberg 10",
    "sg:city":"Bad Wildungen",
    "sg:phone":"+49 5621/73296",
    "sg:postcode":"34537",
    "sg:province":"Hessen",
    "wof:name":"B. Rudolph Anlageberater",
    "wof:placetype":"venue"
},
  "geometry": {"coordinates":[9.1077327728,51.119934082],"type":"Point"}
}