{
  "type": "Feature",
  "properties": {
    "iso:country":"DE",
    "sg:address":"Germaniastr. 28::",
    "sg:city":"Dortmund",
    "sg:phone":"+49 4957/3153050",
    "sg:postcode":"44379",
    "sg:province":"Nordrhein-Westfalen",
    "wof:name":"Georg Zopf Gmbh & Co",
    "wof:placetype":"venue"
},
  "geometry": {"coordinates":[8.777316,52.210194],"type":"Point"}
}