{
  "type": "Feature",
  "properties": {
    "iso:country":"DE",
    "sg:address":"Ravensburger Str. 3",
    "sg:city":"Bad Waldsee",
    "sg:phone":"+49 7524/5291",
    "sg:postcode":"88339",
    "sg:province":"Baden-W\u00fcrttemberg",
    "wof:name":"P. Schmid",
    "wof:placetype":"venue"
},
  "geometry": {"coordinates":[9.754745,47.920517],"type":"Point"}
}