{
  "type": "Feature",
  "properties": {
    "iso:country":"DE",
    "sg:address":"Hauptstr. 28",
    "sg:city":"Bestensee",
    "sg:phone":"+49 33763/9840",
    "sg:postcode":"15741",
    "sg:province":"Brandenburg",
    "wof:name":"W\u00e4rme- Und Umwelttechnik Gmbh",
    "wof:placetype":"venue"
},
  "geometry": {"coordinates":[13.639603,52.242214],"type":"Point"}
}