{
  "type": "Feature",
  "properties": {
    "iso:country":"DE",
    "sg:address":"Lutherstr. 4",
    "sg:city":"Nordenham",
    "sg:postcode":"26954",
    "sg:province":"Niedersachsen",
    "wof:name":"K\u00fchl & Eppler Gmbh",
    "wof:placetype":"venue"
},
  "geometry": {"coordinates":[8.4806,53.485092],"type":"Point"}
}