{
  "type": "Feature",
  "properties": {
    "iso:country":"DE",
    "sg:address":"Kr\u00e4merstr. 13",
    "sg:city":"Kusterdingen",
    "sg:phone":"+49 7071/34582",
    "sg:postcode":"72127",
    "sg:province":"Baden-W\u00fcrttemberg",
    "wof:name":"Otto Kuttler",
    "wof:placetype":"venue"
},
  "geometry": {"coordinates":[9.106758,48.485634],"type":"Point"}
}