{
  "type": "Feature",
  "properties": {
    "iso:country":"DE",
    "sg:address":"Welfengasse 8",
    "sg:city":"Oberammergau",
    "sg:phone":"+49 8822/1535",
    "sg:postcode":"82487",
    "sg:province":"Bayern",
    "wof:name":"G\u00e4stehaus Otto Huber",
    "wof:placetype":"venue"
},
  "geometry": {"coordinates":[11.0556402206,47.5982933044],"type":"Point"}
}