{
  "type": "Feature",
  "properties": {
    "iso:country":"DE",
    "sg:address":"Schnelter Str. 42",
    "sg:city":"Lastrup",
    "sg:phone":"+49 4472/8821",
    "sg:postcode":"49688",
    "sg:province":"Niedersachsen",
    "wof:name":"Witte-lastrup Beteiligungs Gmbh",
    "wof:placetype":"venue"
},
  "geometry": {"coordinates":[7.897556,52.798092],"type":"Point"}
}