{
  "type": "Feature",
  "properties": {
    "iso:country":"DE",
    "sg:address":"Tullastr. 8",
    "sg:city":"Ettenheim",
    "sg:phone":"+49 7822/44680",
    "sg:postcode":"77955",
    "sg:province":"Baden-W\u00fcrttemberg",
    "wof:name":"Dwf Handel & Systembau Gmbh",
    "wof:placetype":"venue"
},
  "geometry": {"coordinates":[7.806743,48.262733],"type":"Point"}
}