{
  "type": "Feature",
  "properties": {
    "iso:country":"DE",
    "sg:address":"Stadtweg 5",
    "sg:city":"Braunschweig",
    "sg:phone":"+49 5309/5022",
    "sg:postcode":"38108",
    "sg:province":"Niedersachsen",
    "wof:name":"Hondelager Baubetrieb D. Franke Gmbh",
    "wof:placetype":"venue"
},
  "geometry": {"coordinates":[10.6033210754,52.3116416931],"type":"Point"}
}