{
  "type": "Feature",
  "properties": {
    "iso:country":"DE",
    "sg:address":"Ziegetsdorfer Str. 118",
    "sg:city":"Regensburg",
    "sg:phone":"+49 941/35866",
    "sg:postcode":"93051",
    "sg:province":"Bayern",
    "wof:name":"Bistro Ramazzotti",
    "wof:placetype":"venue"
},
  "geometry": {"coordinates":[12.0593824387,49.0103874207],"type":"Point"}
}