{
  "type": "Feature",
  "properties": {
    "iso:country":"DE",
    "sg:address":"Hintere Dorfstr. 49",
    "sg:city":"Oderwitz",
    "sg:phone":"+49 35842/27435",
    "sg:postcode":"02791",
    "sg:province":"Sachsen",
    "wof:name":"G\u00fcnter Berndt",
    "wof:placetype":"venue"
},
  "geometry": {"coordinates":[14.713969,50.968536],"type":"Point"}
}