{
  "type": "Feature",
  "properties": {
    "iso:country":"DE",
    "sg:address":"Hubertusstr. 15",
    "sg:city":"Kerpen",
    "sg:phone":"+49 2237/972420",
    "sg:postcode":"50169",
    "sg:province":"Nordrhein-Westfalen",
    "wof:name":"Gl\u00fcckauf",
    "wof:placetype":"venue"
},
  "geometry": {"coordinates":[6.772315979,50.8471603394],"type":"Point"}
}