{
  "type": "Feature",
  "properties": {
    "iso:country":"DE",
    "sg:address":"Im Frauental 14",
    "sg:city":"Amberg",
    "sg:phone":"+49 9621/67710",
    "sg:postcode":"92224",
    "sg:province":"Bayern",
    "wof:name":"Ivs Industrievertretung Schweiger Gmbh",
    "wof:placetype":"venue"
},
  "geometry": {"coordinates":[11.8627538681,49.4468727112],"type":"Point"}
}