{
  "type": "Feature",
  "properties": {
    "iso:country":"DE",
    "sg:address":"Elsa-Br\u00e4ndstr\u00f6m-Str. 6",
    "sg:city":"Karlsruhe",
    "sg:postcode":"76228",
    "sg:province":"Baden-W\u00fcrttemberg",
    "wof:name":"Imp Innovative Medical- Producte Handelsges. Mbh",
    "wof:placetype":"venue"
},
  "geometry": {"coordinates":[8.468036,48.972061],"type":"Point"}
}