{
  "type": "Feature",
  "properties": {
    "iso:country":"DE",
    "sg:address":"Obere Hardt 34",
    "sg:city":"Breidenbach",
    "sg:phone":"+49 6465/597",
    "sg:postcode":"35236",
    "sg:province":"Hessen",
    "wof:name":"Peter Hillesheim",
    "wof:placetype":"venue"
},
  "geometry": {"coordinates":[8.430656,50.902111],"type":"Point"}
}