{
  "type": "Feature",
  "properties": {
    "iso:country":"DE",
    "sg:address":"Hirschengasse 3",
    "sg:city":"Nittenau",
    "sg:phone":"+49 9436/8152",
    "sg:postcode":"93149",
    "sg:province":"Bayern",
    "wof:name":"B. Raab",
    "wof:placetype":"venue"
},
  "geometry": {"coordinates":[12.2720403671,49.1968688965],"type":"Point"}
}