{
  "type": "Feature",
  "properties": {
    "iso:country":"DE",
    "sg:address":"Hindenburgstr. 2 a",
    "sg:city":"Wipperf\u00fcrth",
    "sg:phone":"+49 2267/80320",
    "sg:postcode":"51688",
    "sg:province":"Nordrhein-Westfalen",
    "wof:name":"Jens Schimmelpfennig Masseur",
    "wof:placetype":"venue"
},
  "geometry": {"coordinates":[7.400485,51.117802],"type":"Point"}
}