{
  "type": "Feature",
  "properties": {
    "iso:country":"DE",
    "sg:address":"Gradanger 3",
    "sg:city":"Dassel",
    "sg:phone":"+49 5564/8533",
    "sg:postcode":"37586",
    "sg:province":"Niedersachsen",
    "wof:name":"Helco",
    "wof:placetype":"venue"
},
  "geometry": {"coordinates":[9.6882276535,51.8005943298],"type":"Point"}
}