{
  "type": "Feature",
  "properties": {
    "iso:country":"DE",
    "sg:address":"Schulstr. 49",
    "sg:city":"Spiegelau",
    "sg:phone":"+49 8553/920389",
    "sg:postcode":"94518",
    "sg:province":"Bayern",
    "wof:name":"Peschl Und Keilhofer Gmbh",
    "wof:placetype":"venue"
},
  "geometry": {"coordinates":[13.353067,48.914394],"type":"Point"}
}