{
  "type": "Feature",
  "properties": {
    "iso:country":"DE",
    "sg:address":"Gr\u00fcne Aue 21",
    "sg:city":"Marsberg",
    "sg:phone":"+49 2992/202",
    "sg:postcode":"34431",
    "sg:province":"Nordrhein-Westfalen",
    "wof:name":"H. W\u00fcllner",
    "wof:placetype":"venue"
},
  "geometry": {"coordinates":[8.878636,51.508533],"type":"Point"}
}