{
  "type": "Feature",
  "properties": {
    "iso:country":"DE",
    "sg:address":"Paderborner Str. 99",
    "sg:city":"Detmold",
    "sg:phone":"+49 5231/48555",
    "sg:postcode":"32760",
    "sg:province":"Nordrhein-Westfalen",
    "wof:name":"C. Boussillot",
    "wof:placetype":"venue"
},
  "geometry": {"coordinates":[8.8794898987,51.9002227783],"type":"Point"}
}