{
  "type": "Feature",
  "properties": {
    "iso:country":"DE",
    "sg:address":"Waldstr. 4",
    "sg:city":"Schneeberg",
    "sg:phone":"+49 3772/28926",
    "sg:postcode":"08289",
    "sg:province":"Sachsen",
    "wof:name":"Bernd Locke",
    "wof:placetype":"venue"
},
  "geometry": {"coordinates":[12.605342,50.590122],"type":"Point"}
}