{
  "type": "Feature",
  "properties": {
    "iso:country":"DE",
    "sg:address":"Oskarstr. 3",
    "sg:city":"Wuppertal",
    "sg:phone":"+49 202/5850",
    "sg:postcode":"42283",
    "sg:province":"Nordrhein-Westfalen",
    "wof:name":"Stannol Verwaltungs- Gmbh",
    "wof:placetype":"venue"
},
  "geometry": {"coordinates":[7.183392,51.264397],"type":"Point"}
}