{
  "type": "Feature",
  "properties": {
    "iso:country":"DE",
    "sg:address":"Am alten Galgen 14",
    "sg:city":"Montabaur",
    "sg:phone":"+49 2602/92160",
    "sg:postcode":"56410",
    "sg:province":"Rheinland-Pfalz",
    "wof:name":"Ucm Ursa Chemie Gmbh",
    "wof:placetype":"venue"
},
  "geometry": {"coordinates":[7.8409881592,50.4505882263],"type":"Point"}
}