{
  "type": "Feature",
  "properties": {
    "iso:country":"DE",
    "sg:address":"Markwiesenstr. 45",
    "sg:city":"Reutlingen",
    "sg:phone":"+49 7121/953598",
    "sg:postcode":"72770",
    "sg:province":"Baden-W\u00fcrttemberg",
    "wof:name":"Heinz Schmidt",
    "wof:placetype":"venue"
},
  "geometry": {"coordinates":[9.1540203094,48.4953308105],"type":"Point"}
}