{
  "type": "Feature",
  "properties": {
    "iso:country":"DE",
    "sg:address":"Hocksteiner Weg 32",
    "sg:city":"M\u00f6nchengladbach",
    "sg:phone":"+49 2166/54130",
    "sg:postcode":"41189",
    "sg:province":"Nordrhein-Westfalen",
    "wof:name":"Platoon Modeteam Gmbh",
    "wof:placetype":"venue"
},
  "geometry": {"coordinates":[6.413636,51.137905],"type":"Point"}
}