{
  "type": "Feature",
  "properties": {
    "iso:country":"DE",
    "sg:address":"Dechenweg 46a",
    "sg:city":"D\u00fcsseldorf",
    "sg:phone":"+49 211/753984",
    "sg:postcode":"40591",
    "sg:province":"Nordrhein-Westfalen",
    "wof:name":"Adolf Kuttig",
    "wof:placetype":"venue"
},
  "geometry": {"coordinates":[6.813404,51.184784],"type":"Point"}
}