{
  "type": "Feature",
  "properties": {
    "iso:country":"DE",
    "sg:address":"J\u00e4gerstr. 90",
    "sg:city":"Delmenhorst",
    "sg:phone":"+49 4221/22710",
    "sg:postcode":"27755",
    "sg:province":"Niedersachsen",
    "wof:name":"Hildegard Meeuw",
    "wof:placetype":"venue"
},
  "geometry": {"coordinates":[8.6340322495,53.0297546387],"type":"Point"}
}