{
  "type": "Feature",
  "properties": {
    "iso:country":"DE",
    "sg:address":"S\u00fcdweg 2a",
    "sg:city":"Dassendorf",
    "sg:phone":"+49 4104/2034",
    "sg:postcode":"21521",
    "sg:province":"Schleswig-Holstein",
    "wof:name":"D. F. Objektverwaltungs-gmbh",
    "wof:placetype":"venue"
},
  "geometry": {"coordinates":[10.3508863449,53.4917259216],"type":"Point"}
}