{
  "type": "Feature",
  "properties": {
    "iso:country":"DE",
    "sg:address":"Obere-H\u00f6fe-Str. 2",
    "sg:city":"Emmendingen",
    "sg:phone":"+49 7641/7037",
    "sg:postcode":"79312",
    "sg:province":"Baden-W\u00fcrttemberg",
    "wof:name":"Bernhard Herrmann",
    "wof:placetype":"venue"
},
  "geometry": {"coordinates":[7.861283,48.094101],"type":"Point"}
}