{
  "type": "Feature",
  "properties": {
    "iso:country":"DE",
    "sg:address":"Wessumer Str. 17",
    "sg:city":"Ahaus",
    "sg:phone":"+49 2561/971181",
    "sg:postcode":"48683",
    "sg:province":"Nordrhein-Westfalen",
    "wof:name":"B\u00e4ckerei Und Konditorei Rawers Gmbh",
    "wof:placetype":"venue"
},
  "geometry": {"coordinates":[7.004253,52.07732],"type":"Point"}
}