{
  "type": "Feature",
  "properties": {
    "iso:country":"DE",
    "sg:address":"Ra\u00dfbach 1",
    "sg:city":"Thyrnau",
    "sg:phone":"+49 8501/1313",
    "sg:postcode":"94136",
    "sg:province":"Bayern",
    "wof:name":"Golf-hotel",
    "wof:placetype":"venue"
},
  "geometry": {"coordinates":[13.553768158,48.6086463928],"type":"Point"}
}