{
  "type": "Feature",
  "properties": {
    "iso:country":"DE",
    "sg:address":"Serkendorfer Str. 4",
    "sg:city":"Staffelstein",
    "sg:phone":"+49 9573/6410",
    "sg:postcode":"96231",
    "sg:province":"Bayern",
    "wof:name":"B\u00fcttner Und K\u00fcfner Uetzing",
    "wof:placetype":"venue"
},
  "geometry": {"coordinates":[11.069844,50.085789],"type":"Point"}
}