{
  "type": "Feature",
  "properties": {
    "iso:country":"DE",
    "sg:address":"Alte Schulstr. 12",
    "sg:city":"Monheim",
    "sg:phone":"+49 2173/51397",
    "sg:postcode":"40789",
    "sg:province":"Nordrhein-Westfalen",
    "wof:name":"Dirk Killian",
    "wof:placetype":"venue"
},
  "geometry": {"coordinates":[6.8855390549,51.0914764404],"type":"Point"}
}