{
  "type": "Feature",
  "properties": {
    "iso:country":"DE",
    "sg:address":"Riederstr. 9",
    "sg:city":"Baden-Baden",
    "sg:phone":"+49 7221/5045670",
    "sg:postcode":"76532",
    "sg:province":"Baden-W\u00fcrttemberg",
    "wof:name":"Kurt Sterk Ingenieur",
    "wof:placetype":"venue"
},
  "geometry": {"coordinates":[8.190911,48.81155],"type":"Point"}
}