{
  "type": "Feature",
  "properties": {
    "iso:country":"DE",
    "sg:address":"Ludwigstr. 1",
    "sg:city":"Neustadt",
    "sg:phone":"+49 9161/876565",
    "sg:postcode":"91413",
    "sg:province":"Bayern",
    "wof:name":"Reiseb\u00fcro Eckgold",
    "wof:placetype":"venue"
},
  "geometry": {"coordinates":[13.7341489792,51.0639915466],"type":"Point"}
}