{
  "type": "Feature",
  "properties": {
    "iso:country":"DE",
    "sg:address":"Mechtildenstr. 15",
    "sg:city":"Gr\u00fcnwald",
    "sg:phone":"+49 89/6411306",
    "sg:postcode":"82031",
    "sg:province":"Bayern",
    "wof:name":"St. Peter Und Paul",
    "wof:placetype":"venue"
},
  "geometry": {"coordinates":[11.524,48.043201],"type":"Point"}
}