{
  "type": "Feature",
  "properties": {
    "iso:country":"DE",
    "sg:address":"Oldenburger Str. 117",
    "sg:city":"Wardenburg",
    "sg:phone":"+49 4407/6809",
    "sg:postcode":"26203",
    "sg:province":"Niedersachsen",
    "wof:name":"G\u00fcnter Klusmann",
    "wof:placetype":"venue"
},
  "geometry": {"coordinates":[8.192943573,53.0809364319],"type":"Point"}
}