{
  "type": "Feature",
  "properties": {
    "iso:country":"DE",
    "sg:address":"Hinter der Bahn 4",
    "sg:city":"Neustadt-Glewe",
    "sg:phone":"+49 38757/22521",
    "sg:postcode":"19306",
    "sg:province":"Mecklenburg-Vorpommern",
    "wof:name":"Omnibusbetrieb Und Reiseb\u00fcro",
    "wof:placetype":"venue"
},
  "geometry": {"coordinates":[11.5968770981,53.3779258728],"type":"Point"}
}