{
  "type": "Feature",
  "properties": {
    "iso:country":"DE",
    "sg:address":"Zeller Str. 11",
    "sg:city":"Offenburg",
    "sg:phone":"+49 781/924240",
    "sg:postcode":"77654",
    "sg:province":"Baden-W\u00fcrttemberg",
    "wof:name":"Wallaston Gmbh",
    "wof:placetype":"venue"
},
  "geometry": {"coordinates":[7.947971,48.473793],"type":"Point"}
}