{
  "type": "Feature",
  "properties": {
    "iso:country":"DE",
    "sg:address":"Louis-Peter-Str. 24",
    "sg:city":"Korbach",
    "sg:phone":"+49 5631/8268",
    "sg:postcode":"34497",
    "sg:province":"Hessen",
    "wof:name":"F. Paulus",
    "wof:placetype":"venue"
},
  "geometry": {"coordinates":[8.862537384,51.2749290466],"type":"Point"}
}