{
  "type": "Feature",
  "properties": {
    "iso:country":"DE",
    "sg:address":"Sandwiesenstr.",
    "sg:city":"Pfullingen",
    "sg:phone":"+49 7121/707130",
    "sg:postcode":"72793",
    "sg:province":"Baden-W\u00fcrttemberg",
    "wof:name":"Gfp Gesellschaft F\u00fcr Parksysteme Gmbh",
    "wof:placetype":"venue"
},
  "geometry": {"coordinates":[9.22767,48.458977],"type":"Point"}
}