{
  "type": "Feature",
  "properties": {
    "iso:country":"DE",
    "sg:address":"Beckengasse 26",
    "sg:city":"Urbach",
    "sg:phone":"+49 7181/84967",
    "sg:postcode":"73660",
    "sg:province":"Baden-W\u00fcrttemberg",
    "wof:name":"Rudolf Standfest",
    "wof:placetype":"venue"
},
  "geometry": {"coordinates":[9.5745811462,48.8172798157],"type":"Point"}
}