{
  "type": "Feature",
  "properties": {
    "iso:country":"DE",
    "sg:address":"Wilhelmstr. 21",
    "sg:city":"D\u00fcren",
    "sg:phone":"+49 2421/10933",
    "sg:postcode":"52349",
    "sg:province":"Nordrhein-Westfalen",
    "wof:name":"Plaka-imbi\u00df",
    "wof:placetype":"venue"
},
  "geometry": {"coordinates":[6.4815039635,50.8031768799],"type":"Point"}
}