{
  "type": "Feature",
  "properties": {
    "iso:country":"DE",
    "sg:address":"Wischhof 33",
    "sg:city":"Postfeld",
    "sg:postcode":"24211",
    "sg:province":"Schleswig-Holstein",
    "wof:name":"Mephisto Theaterproduktion Gmbh",
    "wof:placetype":"venue"
},
  "geometry": {"coordinates":[10.217288,54.21199],"type":"Point"}
}