{
  "type": "Feature",
  "properties": {
    "iso:country":"DE",
    "sg:address":"Bahnhofstr. 42",
    "sg:city":"Wittingen",
    "sg:phone":"+49 5831/1661",
    "sg:postcode":"29378",
    "sg:province":"Niedersachsen",
    "wof:name":"T\u00dcv Hannover Sachsen-anhalt E. V.",
    "wof:placetype":"venue"
},
  "geometry": {"coordinates":[10.7280483246,52.7286987305],"type":"Point"}
}