{
  "type": "Feature",
  "properties": {
    "iso:country":"DE",
    "sg:address":"Segeberger Landstr. 68",
    "sg:city":"Kiel",
    "sg:phone":"+49 431/711380",
    "sg:postcode":"24145",
    "sg:province":"Schleswig-Holstein",
    "wof:name":"K\u00e4ptns St\u00fcbchen",
    "wof:placetype":"venue"
},
  "geometry": {"coordinates":[10.1623477936,54.2915802002],"type":"Point"}
}