{
  "type": "Feature",
  "properties": {
    "iso:country":"DE",
    "sg:address":"Wacholderweg 3",
    "sg:city":"Gechingen",
    "sg:phone":"+49 7056/1500",
    "sg:postcode":"75391",
    "sg:province":"Baden-W\u00fcrttemberg",
    "wof:name":"T. A. C.-gmbh Team F\u00fcr Audivisuelle",
    "wof:placetype":"venue"
},
  "geometry": {"coordinates":[8.8415584564,48.69140625],"type":"Point"}
}