{
  "type": "Feature",
  "properties": {
    "iso:country":"DE",
    "sg:address":"Auf Dem Kleinen Feld 5a",
    "sg:city":"Taunusstein",
    "sg:phone":"+49 4961/2885850",
    "sg:postcode":"65232",
    "sg:province":"Hessen",
    "wof:name":"N.tec Gmbh",
    "wof:placetype":"venue"
},
  "geometry": {"coordinates":[8.2199935913,50.1691398621],"type":"Point"}
}