{
  "type": "Feature",
  "properties": {
    "iso:country":"DE",
    "sg:address":"Schillingplatz 16",
    "sg:city":"Dresden",
    "sg:phone":"+49 351/423970",
    "sg:postcode":"01159",
    "sg:province":"Sachsen",
    "wof:name":"Seifert Immobilien",
    "wof:placetype":"venue"
},
  "geometry": {"coordinates":[13.6996097565,51.0426368713],"type":"Point"}
}