{
  "type": "Feature",
  "properties": {
    "iso:country":"DE",
    "sg:address":"Unterdigisheimer Str.",
    "sg:city":"Me\u00dfstetten",
    "sg:postcode":"72469",
    "sg:province":"Baden-W\u00fcrttemberg",
    "wof:name":"Kath. Pfarramt St. Maria",
    "wof:placetype":"venue"
},
  "geometry": {"coordinates":[8.9538011551,48.176864624],"type":"Point"}
}