{
  "type": "Feature",
  "properties": {
    "iso:country":"DE",
    "sg:address":"Carl-Friedrich-Gau\u00df-Str 5",
    "sg:city":"Neu-Isenburg",
    "sg:phone":"+49 6187/291619",
    "sg:postcode":"63263",
    "sg:province":"Hessen",
    "wof:name":"Gate Gmbh",
    "wof:placetype":"venue"
},
  "geometry": {"coordinates":[8.7160482407,50.0473518372],"type":"Point"}
}