{
  "type": "Feature",
  "properties": {
    "iso:country":"DE",
    "sg:address":"St.-J\u00fcrgen-Str.",
    "sg:city":"Bremen",
    "sg:phone":"+49 421/4975030",
    "sg:postcode":"28205",
    "sg:province":"Bremen",
    "wof:name":"Ev. Pfarramt Zentralkrankenhaus",
    "wof:placetype":"venue"
},
  "geometry": {"coordinates":[8.8369808197,53.0753746033],"type":"Point"}
}