{
  "type": "Feature",
  "properties": {
    "iso:country":"DE",
    "sg:address":"K\u00f6lner Str. 65",
    "sg:city":"J\u00fcnkerath",
    "sg:phone":"+49 6597/2231",
    "sg:postcode":"54584",
    "sg:province":"Rheinland-Pfalz",
    "wof:name":"Kath. Pfarramt St. Antonius V. Paderborn",
    "wof:placetype":"venue"
},
  "geometry": {"coordinates":[6.5812969208,50.3426933289],"type":"Point"}
}