{
  "type": "Feature",
  "properties": {
    "iso:country":"DE",
    "sg:address":"Am Ries 17",
    "sg:city":"Bocholt",
    "sg:phone":"+49 2871/225427",
    "sg:postcode":"46395",
    "sg:province":"Nordrhein-Westfalen",
    "wof:name":"Uebbing & Partner Stahlbau Gmbh",
    "wof:placetype":"venue"
},
  "geometry": {"coordinates":[6.5608139038,51.8147201538],"type":"Point"}
}