{
  "type": "Feature",
  "properties": {
    "iso:country":"DE",
    "sg:address":"Eisenhammer 3",
    "sg:city":"Laaber",
    "sg:phone":"+49 9498/8972",
    "sg:postcode":"93164",
    "sg:province":"Bayern",
    "wof:name":"M. Hofmeister",
    "wof:placetype":"venue"
},
  "geometry": {"coordinates":[11.8997831345,49.0597496033],"type":"Point"}
}