{
  "type": "Feature",
  "properties": {
    "iso:country":"DE",
    "sg:address":"Deutschherrnstr. 21",
    "sg:city":"M\u00fcnnerstadt",
    "sg:phone":"+49 9733/9761",
    "sg:postcode":"97702",
    "sg:province":"Bayern",
    "wof:name":"Dieter Peitsch",
    "wof:placetype":"venue"
},
  "geometry": {"coordinates":[10.196767807,50.2499351501],"type":"Point"}
}