{
  "type": "Feature",
  "properties": {
    "iso:country":"DE",
    "sg:address":"Oberfrohnaer Str. 7",
    "sg:city":"Chemnitz",
    "sg:phone":"+49 371/851193",
    "sg:postcode":"09117",
    "sg:province":"Sachsen",
    "wof:name":"Bau Consult Gmbh Bautr\u00e4ger- Und",
    "wof:placetype":"venue"
},
  "geometry": {"coordinates":[12.840389,50.817364],"type":"Point"}
}