{
  "type": "Feature",
  "properties": {
    "iso:country":"DE",
    "sg:address":"Berging",
    "sg:city":"Simbach",
    "sg:phone":"+49 8571/6389",
    "sg:postcode":"84359",
    "sg:province":"Bayern",
    "wof:name":"F. Stiglbrunner",
    "wof:placetype":"venue"
},
  "geometry": {"coordinates":[13.0489654541,48.3090171814],"type":"Point"}
}