{
  "type": "Feature",
  "properties": {
    "iso:country":"DE",
    "sg:address":"Hamelner Str. 53",
    "sg:city":"Bodenwerder",
    "sg:postcode":"37619",
    "sg:province":"Niedersachsen",
    "wof:name":"Neckermann Versand Ag",
    "wof:placetype":"venue"
},
  "geometry": {"coordinates":[9.5024528503,51.9835624695],"type":"Point"}
}