{
  "type": "Feature",
  "properties": {
    "iso:country":"DE",
    "sg:address":"Celler Str. 6",
    "sg:city":"Edemissen",
    "sg:phone":"+49 5373/7769",
    "sg:postcode":"31234",
    "sg:province":"Niedersachsen",
    "wof:name":"Heidkrug",
    "wof:placetype":"venue"
},
  "geometry": {"coordinates":[10.3706216812,52.3961677551],"type":"Point"}
}