{
  "type": "Feature",
  "properties": {
    "iso:country":"DE",
    "sg:address":"Hochstr. 40",
    "sg:city":"Willich",
    "sg:phone":"+49 2154/7719",
    "sg:postcode":"47877",
    "sg:province":"Nordrhein-Westfalen",
    "wof:name":"Siso Textil Gmbh",
    "wof:placetype":"venue"
},
  "geometry": {"coordinates":[6.535941,51.242542],"type":"Point"}
}