{
  "type": "Feature",
  "properties": {
    "iso:country":"DE",
    "sg:address":"Bahnhofstr. 5",
    "sg:city":"Bandau",
    "sg:postcode":"38486",
    "sg:province":"Sachsen-Anhalt",
    "wof:name":"Coiffeur Charmant Gmbh",
    "wof:placetype":"venue"
},
  "geometry": {"coordinates":[11.1231441498,52.6701507568],"type":"Point"}
}