{
  "type": "Feature",
  "properties": {
    "iso:country":"DE",
    "sg:address":"Geiselbach",
    "sg:city":"Geiselbach",
    "sg:phone":"+49 6024/1580",
    "sg:postcode":"63826",
    "sg:province":"Bayern",
    "wof:name":"Raiffeisenbank M\u00f6mbris Eg",
    "wof:placetype":"venue"
},
  "geometry": {"coordinates":[9.198498,50.12225],"type":"Point"}
}