{
  "type": "Feature",
  "properties": {
    "iso:country":"DE",
    "sg:address":"Forlenstr. 7",
    "sg:city":"B\u00fchl",
    "sg:phone":"+49 7223/83581",
    "sg:postcode":"77815",
    "sg:province":"Baden-W\u00fcrttemberg",
    "wof:name":"R. D\u00fcrr Schilder Und Lichtreklame",
    "wof:placetype":"venue"
},
  "geometry": {"coordinates":[8.108679,48.718716],"type":"Point"}
}