{
  "type": "Feature",
  "properties": {
    "iso:country":"DE",
    "sg:address":"Rudolf-Renner-Str. 55",
    "sg:city":"Dresden",
    "sg:phone":"+49 351/4215347",
    "sg:postcode":"01159",
    "sg:province":"Sachsen",
    "wof:name":"Stoffreste & Damenmoden",
    "wof:placetype":"venue"
},
  "geometry": {"coordinates":[13.694377,51.043324],"type":"Point"}
}