{
  "type": "Feature",
  "properties": {
    "iso:country":"DE",
    "sg:address":"Sch\u00f6nhauser Allee 109",
    "sg:city":"Berlin",
    "sg:phone":"+49 30/4477966",
    "sg:postcode":"10439",
    "sg:province":"Berlin",
    "wof:name":"R.-p. Rose Und R. Wunderlich Rechtsanw\u00e4lte",
    "wof:placetype":"venue"
},
  "geometry": {"coordinates":[13.4136695862,52.5513153076],"type":"Point"}
}