{
  "type": "Feature",
  "properties": {
    "iso:country":"DE",
    "sg:address":"Max-Beckmann-Str. 8",
    "sg:city":"Ohlstadt",
    "sg:phone":"+49 8841/7300",
    "sg:postcode":"82441",
    "sg:province":"Bayern",
    "wof:name":"Zenta Sanktjohanser Heissmangel",
    "wof:placetype":"venue"
},
  "geometry": {"coordinates":[11.2288370132,47.6335449219],"type":"Point"}
}