{
  "type": "Feature",
  "properties": {
    "iso:country":"DE",
    "sg:address":"Am Birkenhain 1",
    "sg:city":"Templin",
    "sg:phone":"+49 3987/52102",
    "sg:postcode":"17268",
    "sg:province":"Brandenburg",
    "wof:name":"Frank B\u00f6ttcher",
    "wof:placetype":"venue"
},
  "geometry": {"coordinates":[13.4886932373,53.1125488281],"type":"Point"}
}