{
  "type": "Feature",
  "properties": {
    "iso:country":"DE",
    "sg:address":"Lilienthaler Heerstr. 220",
    "sg:city":"Bremen",
    "sg:phone":"+49 421/272717",
    "sg:postcode":"28357",
    "sg:province":"Bremen",
    "wof:name":"Jehovas Zeugen Versammlung Bremen Horn E. V.",
    "wof:placetype":"venue"
},
  "geometry": {"coordinates":[8.8890800476,53.1108360291],"type":"Point"}
}