{
  "type": "Feature",
  "properties": {
    "iso:country":"DE",
    "sg:address":"Emmendinger Str. 14",
    "sg:city":"Denzlingen",
    "sg:phone":"+49 7666/3332",
    "sg:postcode":"79211",
    "sg:province":"Baden-W\u00fcrttemberg",
    "wof:name":"Hans Lay",
    "wof:placetype":"venue"
},
  "geometry": {"coordinates":[7.894865036,48.0726470947],"type":"Point"}
}