{
  "type": "Feature",
  "properties": {
    "iso:country":"DE",
    "sg:address":"Bismarckstr. 51a",
    "sg:city":"Darmstadt",
    "sg:phone":"+49 6151/293905",
    "sg:postcode":"64293",
    "sg:province":"Hessen",
    "wof:name":"Amog Architekt",
    "wof:placetype":"venue"
},
  "geometry": {"coordinates":[8.644348,49.875324],"type":"Point"}
}