{
  "type": "Feature",
  "properties": {
    "iso:country":"DE",
    "sg:address":"Braunstr. 6a",
    "sg:city":"Hannover",
    "sg:phone":"+49 511/342042",
    "sg:postcode":"30169",
    "sg:province":"Niedersachsen",
    "wof:name":"Stefan Wirz Ingenieur",
    "wof:placetype":"venue"
},
  "geometry": {"coordinates":[9.722285,52.373112],"type":"Point"}
}