{
  "type": "Feature",
  "properties": {
    "iso:country":"DE",
    "sg:address":"Hauptstra\u00dfe 38",
    "sg:city":"Lauf",
    "sg:phone":"+49 7841/24823",
    "sg:postcode":"77886",
    "sg:province":"Baden-W\u00fcrttemberg",
    "wof:name":"Fahrzeug Kist Ohg",
    "wof:placetype":"venue"
},
  "geometry": {"coordinates":[8.1294212341,48.6513404846],"type":"Point"}
}