{
  "type": "Feature",
  "properties": {
    "iso:country":"DE",
    "sg:address":"Kronwinkler Str. 47",
    "sg:city":"M\u00fcnchen",
    "sg:phone":"+49 89",
    "sg:postcode":"81245",
    "sg:province":"Bayern",
    "wof:name":"Voigt Engineering Gmbh",
    "wof:placetype":"venue"
},
  "geometry": {"coordinates":[11.4226064682,48.1617012024],"type":"Point"}
}