{
  "type": "Feature",
  "properties": {
    "iso:country":"DE",
    "sg:address":"Fischbacher Str. 6",
    "sg:city":"Kelkheim",
    "sg:postcode":"65779",
    "sg:province":"Hessen",
    "wof:name":"Davitec Gesellschaft F\u00fcr Datenverarbeitung Und",
    "wof:placetype":"venue"
},
  "geometry": {"coordinates":[8.4461183548,50.1390190125],"type":"Point"}
}