{
  "type": "Feature",
  "properties": {
    "iso:country":"DE",
    "sg:address":"Mei\u00dfner Gasse 17",
    "sg:city":"Freiberg",
    "sg:phone":"+49 3731/39510",
    "sg:postcode":"09599",
    "sg:province":"Sachsen",
    "wof:name":"Steyer Textilservice Gmbh",
    "wof:placetype":"venue"
},
  "geometry": {"coordinates":[13.346165657,50.9213752747],"type":"Point"}
}