{
  "type": "Feature",
  "properties": {
    "iso:country":"DE",
    "sg:address":"Im Dall 11",
    "sg:city":"L\u00f6hne",
    "sg:phone":"+49 5732/5373",
    "sg:postcode":"32584",
    "sg:province":"Nordrhein-Westfalen",
    "wof:name":"B\u00f6ka Futterstoff Und Textilvertriebs Gmbh",
    "wof:placetype":"venue"
},
  "geometry": {"coordinates":[8.718907,52.200432],"type":"Point"}
}