{
  "type": "Feature",
  "properties": {
    "iso:country":"DE",
    "sg:address":"Geisbergstr. 10",
    "sg:city":"Niederzissen",
    "sg:phone":"+49 2636/6547",
    "sg:postcode":"56651",
    "sg:province":"Rheinland-Pfalz",
    "wof:name":"Artur Adams E. K.",
    "wof:placetype":"venue"
},
  "geometry": {"coordinates":[7.2235059738,50.4618415833],"type":"Point"}
}