{
  "type": "Feature",
  "properties": {
    "iso:country":"DE",
    "sg:address":"K\u00f6nigsteinstr. 2",
    "sg:city":"Dresden",
    "sg:phone":"+49 351/2515614",
    "sg:postcode":"01277",
    "sg:province":"Sachsen",
    "wof:name":"Frank Ludolphy",
    "wof:placetype":"venue"
},
  "geometry": {"coordinates":[13.773597,51.031727],"type":"Point"}
}