{
  "type": "Feature",
  "properties": {
    "iso:country":"DE",
    "sg:address":"Vonsbach 6",
    "sg:city":"Rheinbreitbach",
    "sg:phone":"+49 2224/4917",
    "sg:postcode":"53619",
    "sg:province":"Rheinland-Pfalz",
    "wof:name":"M. Matzerath",
    "wof:placetype":"venue"
},
  "geometry": {"coordinates":[7.2323179245,50.6193580627],"type":"Point"}
}