{
  "type": "Feature",
  "properties": {
    "iso:country":"DE",
    "sg:address":"Wei\u00dfensteinweg 6",
    "sg:city":"St. Blasien",
    "sg:phone":"+49 7672/1313",
    "sg:postcode":"79837",
    "sg:province":"Baden-W\u00fcrttemberg",
    "wof:name":"Thomas Huber Masseur",
    "wof:placetype":"venue"
},
  "geometry": {"coordinates":[8.12378,47.75946],"type":"Point"}
}