{
  "type": "Feature",
  "properties": {
    "iso:country":"DE",
    "sg:address":"S\u00fcdstr. 16",
    "sg:city":"Rehlingen-Siersburg",
    "sg:phone":"+49 6835/93147",
    "sg:postcode":"66780",
    "sg:province":"Saarland",
    "wof:name":"Bew Blumhardt Engineering Service Gmbh",
    "wof:placetype":"venue"
},
  "geometry": {"coordinates":[6.6925067902,49.3670539856],"type":"Point"}
}