{
  "type": "Feature",
  "properties": {
    "iso:country":"DE",
    "sg:address":"Ludwigstr. 54",
    "sg:city":"N\u00fcrnberg",
    "sg:phone":"+49 911/232787",
    "sg:postcode":"90402",
    "sg:province":"Bayern",
    "wof:name":"Michele Angie Boutique",
    "wof:placetype":"venue"
},
  "geometry": {"coordinates":[11.068164,49.449158],"type":"Point"}
}