{
  "type": "Feature",
  "properties": {
    "iso:country":"DE",
    "sg:address":"Am Schwimmbad 9",
    "sg:city":"Dormagen",
    "sg:phone":"+49 2133/92580",
    "sg:postcode":"41542",
    "sg:province":"Nordrhein-Westfalen",
    "wof:name":"Saatherm Heiz- Und Regel- Technik Gmbh",
    "wof:placetype":"venue"
},
  "geometry": {"coordinates":[6.7781209946,51.120639801],"type":"Point"}
}