{
  "type": "Feature",
  "properties": {
    "iso:country":"DE",
    "sg:address":"Sandstr. 27",
    "sg:city":"Solingen",
    "sg:phone":"+49 212/202153",
    "sg:postcode":"42655",
    "sg:province":"Nordrhein-Westfalen",
    "wof:name":"Friedr. Baumann & S\u00f6hne",
    "wof:placetype":"venue"
},
  "geometry": {"coordinates":[7.07033,51.176842],"type":"Point"}
}