{
  "type": "Feature",
  "properties": {
    "iso:country":"DE",
    "sg:address":"Weiherhof",
    "sg:city":"Pohlheim",
    "sg:phone":"+49 6403/61127",
    "sg:postcode":"35415",
    "sg:province":"Hessen",
    "wof:name":"Werner Reitschmidt",
    "wof:placetype":"venue"
},
  "geometry": {"coordinates":[8.721045,50.528946],"type":"Point"}
}