{
  "type": "Feature",
  "properties": {
    "iso:country":"DE",
    "sg:address":"Vorster Str. 527",
    "sg:city":"M\u00f6nchengladbach",
    "sg:phone":"+49 2161/559940",
    "sg:postcode":"41169",
    "sg:province":"Nordrhein-Westfalen",
    "wof:name":"Eiscafe Cesarino De Bona",
    "wof:placetype":"venue"
},
  "geometry": {"coordinates":[6.341995,51.205376],"type":"Point"}
}