{
  "type": "Feature",
  "properties": {
    "iso:country":"DE",
    "sg:address":"B\u00fcltenweg 18",
    "sg:city":"Adendorf",
    "sg:phone":"+49 4131/18378",
    "sg:postcode":"21365",
    "sg:province":"Niedersachsen",
    "wof:name":"Ev. Pfarramt I",
    "wof:placetype":"venue"
},
  "geometry": {"coordinates":[10.435751915,53.2787361145],"type":"Point"}
}