{
  "type": "Feature",
  "properties": {
    "iso:country":"DE",
    "sg:address":"G\u00f6ttinger Chaussee 163",
    "sg:city":"Hannover",
    "sg:phone":"+49 511/429095",
    "sg:postcode":"30459",
    "sg:province":"Niedersachsen",
    "wof:name":"Restaurant Zur Alten Post",
    "wof:placetype":"venue"
},
  "geometry": {"coordinates":[9.7172021866,52.338470459],"type":"Point"}
}