{
  "type": "Feature",
  "properties": {
    "iso:country":"DE",
    "sg:address":"Alter Getreidespeicher",
    "sg:city":"Quermathen",
    "sg:phone":"+49 33239/70491",
    "sg:postcode":"14641",
    "sg:province":"Brandenburg",
    "wof:name":"Bauform Baubedarf Handels-gmbh",
    "wof:placetype":"venue"
},
  "geometry": {"coordinates":[12.879175,52.608898],"type":"Point"}
}