{
  "type": "Feature",
  "properties": {
    "iso:country":"DE",
    "sg:address":"Brunnenstr. 138",
    "sg:city":"L\u00fcnen",
    "sg:postcode":"44536",
    "sg:province":"Nordrhein-Westfalen",
    "wof:name":"Agrogas D Ag",
    "wof:placetype":"venue"
},
  "geometry": {"coordinates":[7.4653811455,51.6162834167],"type":"Point"}
}