{
  "type": "Feature",
  "properties": {
    "iso:country":"DE",
    "sg:address":"Am Strand 3",
    "sg:city":"Oelsnitz",
    "sg:phone":"+49 37421/23331",
    "sg:postcode":"08606",
    "sg:province":"Sachsen",
    "wof:name":"Am See",
    "wof:placetype":"venue"
},
  "geometry": {"coordinates":[12.1191301346,50.4304084778],"type":"Point"}
}