{
  "type": "Feature",
  "properties": {
    "iso:country":"DE",
    "sg:address":"Beiersdorfer Str. 14",
    "sg:city":"Neumark",
    "sg:phone":"+49 37600/2220",
    "sg:postcode":"08496",
    "sg:province":"Sachsen",
    "wof:name":"S. Seifert",
    "wof:placetype":"venue"
},
  "geometry": {"coordinates":[12.323293,50.672333],"type":"Point"}
}