{
  "type": "Feature",
  "properties": {
    "iso:country":"DE",
    "sg:address":"B\u00f6ttgerstr. 32",
    "sg:city":"Monheim",
    "sg:phone":"+49 2173/50609",
    "sg:postcode":"40789",
    "sg:province":"Nordrhein-Westfalen",
    "wof:name":"Cigula Gmbh",
    "wof:placetype":"venue"
},
  "geometry": {"coordinates":[6.8959980011,51.1026496887],"type":"Point"}
}