{
  "type": "Feature",
  "properties": {
    "iso:country":"DE",
    "sg:address":"Rheinlandstr. 70",
    "sg:city":"Frankfurt",
    "sg:phone":"+49 69/355694",
    "sg:postcode":"60529",
    "sg:province":"Hessen",
    "wof:name":"Horst Kirbach Papier- Und Schreibwaren",
    "wof:placetype":"venue"
},
  "geometry": {"coordinates":[8.581517,50.082649],"type":"Point"}
}