{
  "type": "Feature",
  "properties": {
    "iso:country":"DE",
    "sg:address":"Lochhamer Str. 76",
    "sg:city":"Gr\u00e4felfing",
    "sg:phone":"+49 89/853941",
    "sg:postcode":"82166",
    "sg:province":"Bayern",
    "wof:name":"Alten- Und Pflegeheim Rudolf Und Maria Gunst Haus",
    "wof:placetype":"venue"
},
  "geometry": {"coordinates":[11.434009,48.128513],"type":"Point"}
}