{
  "type": "Feature",
  "properties": {
    "iso:country":"DE",
    "sg:address":"Krummacherstr. 19",
    "sg:city":"Duisburg",
    "sg:phone":"+49 203/24937",
    "sg:postcode":"47051",
    "sg:province":"Nordrhein-Westfalen",
    "wof:name":"Eiscafe Kurt Graupner",
    "wof:placetype":"venue"
},
  "geometry": {"coordinates":[6.763348,51.428474],"type":"Point"}
}