{
  "type": "Feature",
  "properties": {
    "iso:country":"DE",
    "sg:address":"Bundesplatz 17",
    "sg:city":"Berlin",
    "sg:phone":"+49 30/8535921",
    "sg:postcode":"10715",
    "sg:province":"Berlin",
    "wof:name":"Joseph H. Lonas Bildhauer",
    "wof:placetype":"venue"
},
  "geometry": {"coordinates":[13.329247,52.479713],"type":"Point"}
}