{
  "type": "Feature",
  "properties": {
    "iso:country":"DE",
    "sg:address":"Dienstadter Str. 4",
    "sg:city":"K\u00f6nigheim",
    "sg:phone":"+49 9341/95066",
    "sg:postcode":"97953",
    "sg:province":"Baden-W\u00fcrttemberg",
    "wof:name":"Tiberius Gastro-service Gmbh & Co. Kg",
    "wof:placetype":"venue"
},
  "geometry": {"coordinates":[9.605612,49.620171],"type":"Point"}
}