{
  "type": "Feature",
  "properties": {
    "iso:country":"DE",
    "sg:address":"Forster Str. 75",
    "sg:city":"Forst",
    "sg:phone":"+49 3562/7682",
    "sg:postcode":"03149",
    "sg:province":"Brandenburg",
    "wof:name":"Gastst\u00e4tte Turnhalle",
    "wof:placetype":"venue"
},
  "geometry": {"coordinates":[14.6041049957,51.6906814575],"type":"Point"}
}