{
  "type": "Feature",
  "properties": {
    "iso:country":"DE",
    "sg:address":"Bahnhofstr. 3",
    "sg:city":"Neckargem\u00fcnd",
    "sg:phone":"+49 6223/2248",
    "sg:postcode":"69151",
    "sg:province":"Baden-W\u00fcrttemberg",
    "wof:name":"Hans H\u00fcnnerkopf",
    "wof:placetype":"venue"
},
  "geometry": {"coordinates":[8.79571,49.394691],"type":"Point"}
}