{
  "type": "Feature",
  "properties": {
    "iso:country":"DE",
    "sg:address":"Hauptstr. 80",
    "sg:city":"Ostrhauderfehn",
    "sg:phone":"+49 4952/61847",
    "sg:postcode":"26842",
    "sg:province":"Niedersachsen",
    "wof:name":"Liebel B\u00fcrosysteme Gmbh",
    "wof:placetype":"venue"
},
  "geometry": {"coordinates":[7.6140551567,53.1398124695],"type":"Point"}
}