{
  "type": "Feature",
  "properties": {
    "iso:country":"DE",
    "sg:address":"D\u00fclmener Str. 99",
    "sg:city":"Coesfeld",
    "sg:phone":"+49 2541/94220",
    "sg:postcode":"48653",
    "sg:province":"Nordrhein-Westfalen",
    "wof:name":"Stall Verwaltungs Gmbh",
    "wof:placetype":"venue"
},
  "geometry": {"coordinates":[7.171377182,51.9302558899],"type":"Point"}
}