{
  "type": "Feature",
  "properties": {
    "iso:country":"DE",
    "sg:address":"Donaustr. 2-6",
    "sg:city":"Kelheim",
    "sg:phone":"+49 9441/70050",
    "sg:postcode":"93309",
    "sg:province":"Bayern",
    "wof:name":"W. Weissm\u00fcller Eisenwaren",
    "wof:placetype":"venue"
},
  "geometry": {"coordinates":[11.8718967438,48.9183731079],"type":"Point"}
}