{
  "type": "Feature",
  "properties": {
    "iso:country":"DE",
    "sg:address":"Bahnhofstr. 11",
    "sg:city":"Herrsching",
    "sg:phone":"+49 8152/6242",
    "sg:postcode":"82211",
    "sg:province":"Bayern",
    "wof:name":"Hdv",
    "wof:placetype":"venue"
},
  "geometry": {"coordinates":[11.1747636795,47.998664856],"type":"Point"}
}