{
  "type": "Feature",
  "properties": {
    "iso:country":"DE",
    "sg:address":"Blumenstr. 4",
    "sg:city":"Tuttlingen",
    "sg:phone":"+49 7461/12829",
    "sg:postcode":"78532",
    "sg:province":"Baden-W\u00fcrttemberg",
    "wof:name":"Erich Hermann",
    "wof:placetype":"venue"
},
  "geometry": {"coordinates":[8.8257236481,47.9831886292],"type":"Point"}
}