{
  "type": "Feature",
  "properties": {
    "iso:country":"DE",
    "sg:address":"Fokko-Pannenborg-Str. 16",
    "sg:city":"Emden",
    "sg:phone":"+49 4921/22534",
    "sg:postcode":"26725",
    "sg:province":"Niedersachsen",
    "wof:name":"L. Hemken",
    "wof:placetype":"venue"
},
  "geometry": {"coordinates":[7.229307,53.37196],"type":"Point"}
}