{
  "type": "Feature",
  "properties": {
    "iso:country":"DE",
    "sg:address":"Untere Hauptstr. 82",
    "sg:city":"Worms",
    "sg:phone":"+49 6241/384423",
    "sg:postcode":"67551",
    "sg:province":"Rheinland-Pfalz",
    "wof:name":"Baumg\u00e4rtner",
    "wof:placetype":"venue"
},
  "geometry": {"coordinates":[8.320022583,49.6105461121],"type":"Point"}
}