{
  "type": "Feature",
  "properties": {
    "iso:country":"DE",
    "sg:address":"Gelderstr. 25",
    "sg:city":"Geldern",
    "sg:phone":"+49 2831/87060",
    "sg:postcode":"47608",
    "sg:province":"Nordrhein-Westfalen",
    "wof:name":"Herzog Theater",
    "wof:placetype":"venue"
},
  "geometry": {"coordinates":[6.326039,51.51582],"type":"Point"}
}