{
  "type": "Feature",
  "properties": {
    "iso:country":"DE",
    "sg:address":"Pappelweg 14",
    "sg:city":"Heilbronn",
    "sg:phone":"+49 7131/251486",
    "sg:postcode":"74081",
    "sg:province":"Baden-W\u00fcrttemberg",
    "wof:name":"Siegfried Leixner",
    "wof:placetype":"venue"
},
  "geometry": {"coordinates":[9.1772689819,49.1141662598],"type":"Point"}
}