{
  "type": "Feature",
  "properties": {
    "iso:country":"DE",
    "sg:address":"Curslacker Heerweg 34",
    "sg:city":"Hamburg",
    "sg:phone":"+49 40/7231469",
    "sg:postcode":"21039",
    "sg:province":"Hamburg",
    "wof:name":"Diskothek A. P\u00fclm",
    "wof:placetype":"venue"
},
  "geometry": {"coordinates":[10.23476,53.45993],"type":"Point"}
}