{
  "type": "Feature",
  "properties": {
    "iso:country":"DE",
    "sg:address":"Karlstr. 13",
    "sg:city":"Bernkastel-Kues",
    "sg:phone":"+49 6531/7476",
    "sg:postcode":"54470",
    "sg:province":"Rheinland-Pfalz",
    "wof:name":"Schmitz",
    "wof:placetype":"venue"
},
  "geometry": {"coordinates":[7.0758228302,49.9153060913],"type":"Point"}
}