{
  "type": "Feature",
  "properties": {
    "iso:country":"DE",
    "sg:address":"Hauptstr. 34",
    "sg:city":"Spahnharrenst\u00e4tte",
    "sg:phone":"+49 5951/4589",
    "sg:postcode":"49751",
    "sg:province":"Niedersachsen",
    "wof:name":"Wilhelm Meyer",
    "wof:placetype":"venue"
},
  "geometry": {"coordinates":[7.602966,52.870358],"type":"Point"}
}