{
  "type": "Feature",
  "properties": {
    "iso:country":"DE",
    "sg:address":"Rather Str. 27",
    "sg:city":"Nideggen",
    "sg:phone":"+49 2427/1226",
    "sg:postcode":"52385",
    "sg:province":"Nordrhein-Westfalen",
    "wof:name":"Jugendherberge Nideggen",
    "wof:placetype":"venue"
},
  "geometry": {"coordinates":[6.480861187,50.6945762634],"type":"Point"}
}