{
  "type": "Feature",
  "properties": {
    "iso:country":"DE",
    "sg:address":"Lotterbergstr. 16",
    "sg:city":"Stuttgart",
    "sg:phone":"+49 711/1399400",
    "sg:postcode":"70499",
    "sg:province":"Baden-W\u00fcrttemberg",
    "wof:name":"Kinderberg E. V.",
    "wof:placetype":"venue"
},
  "geometry": {"coordinates":[9.1056137085,48.8210792542],"type":"Point"}
}