{
  "type": "Feature",
  "properties": {
    "iso:country":"DE",
    "sg:address":"Am Rheinberg 6",
    "sg:city":"Kuhardt",
    "sg:phone":"+49 7272/8383",
    "sg:postcode":"76773",
    "sg:province":"Rheinland-Pfalz",
    "wof:name":"Marmor Ochsenreither Gmbh",
    "wof:placetype":"venue"
},
  "geometry": {"coordinates":[8.3206119537,49.1447982788],"type":"Point"}
}