{
  "type": "Feature",
  "properties": {
    "iso:country":"DE",
    "sg:address":"Haardtring 100",
    "sg:city":"Darmstadt",
    "sg:postcode":"64295",
    "sg:province":"Hessen",
    "wof:name":"Dugena Vertriebs- Gesellschaft Mbh",
    "wof:placetype":"venue"
},
  "geometry": {"coordinates":[8.6316576004,49.8661231995],"type":"Point"}
}