{
  "type": "Feature",
  "properties": {
    "iso:country":"DE",
    "sg:address":"Nordheimstr. 31",
    "sg:city":"Cuxhaven",
    "sg:phone":"+49 4721/29195",
    "sg:postcode":"27476",
    "sg:province":"Niedersachsen",
    "wof:name":"Ulrich Hempel Drogerie",
    "wof:placetype":"venue"
},
  "geometry": {"coordinates":[8.630898,53.861378],"type":"Point"}
}