{
  "type": "Feature",
  "properties": {
    "iso:country":"DE",
    "sg:address":"Bahnhofstr. 25/26",
    "sg:city":"Erfurt",
    "sg:postcode":"99084",
    "sg:province":"Th\u00fcringen",
    "wof:name":"Energis Erfurt Gmbh",
    "wof:placetype":"venue"
},
  "geometry": {"coordinates":[11.0364332199,50.9731559753],"type":"Point"}
}