{
  "type": "Feature",
  "properties": {
    "iso:country":"DE",
    "sg:address":"Weiler Weg 53",
    "sg:city":"Steinenbronn",
    "sg:phone":"+49 7157/21418",
    "sg:postcode":"71144",
    "sg:province":"Baden-W\u00fcrttemberg",
    "wof:name":"Paulinenpflege Stuttgart",
    "wof:placetype":"venue"
},
  "geometry": {"coordinates":[9.113327,48.655346],"type":"Point"}
}