{
  "type": "Feature",
  "properties": {
    "iso:country":"DE",
    "sg:address":"Rehgasse 42",
    "sg:city":"Mechernich",
    "sg:phone":"+49 2443/5808",
    "sg:postcode":"53894",
    "sg:province":"Nordrhein-Westfalen",
    "wof:name":"Johanna Oesterling",
    "wof:placetype":"venue"
},
  "geometry": {"coordinates":[6.653203,50.61451],"type":"Point"}
}