{
  "type": "Feature",
  "properties": {
    "iso:country":"DE",
    "sg:address":"Bogener Str. 1 a",
    "sg:city":"Neukirchen",
    "sg:phone":"+49 9961/7272",
    "sg:postcode":"94362",
    "sg:province":"Bayern",
    "wof:name":"Aktivmarkt Schroll E. K.",
    "wof:placetype":"venue"
},
  "geometry": {"coordinates":[12.7553071976,48.9726638794],"type":"Point"}
}