{
  "type": "Feature",
  "properties": {
    "iso:country":"DE",
    "sg:address":"Freisinger Str. 36",
    "sg:city":"Mainburg",
    "sg:phone":"+49 8751/1393",
    "sg:postcode":"84048",
    "sg:province":"Bayern",
    "wof:name":"Paul Buchinger",
    "wof:placetype":"venue"
},
  "geometry": {"coordinates":[11.778664,48.63699],"type":"Point"}
}