{
  "type": "Feature",
  "properties": {
    "iso:country":"DE",
    "sg:address":"Kirchstr. 223",
    "sg:city":"Duisburg",
    "sg:phone":"+49 2066/30125",
    "sg:postcode":"47198",
    "sg:province":"Nordrhein-Westfalen",
    "wof:name":"A. Gericke",
    "wof:placetype":"venue"
},
  "geometry": {"coordinates":[6.691527,51.4557],"type":"Point"}
}