{
  "type": "Feature",
  "properties": {
    "iso:country":"DE",
    "sg:address":"Konrad-Zuse-Str 3",
    "sg:city":"Nerdlen",
    "sg:phone":"+49 6592/98260",
    "sg:postcode":"54552",
    "sg:province":"Rheinland-Pfalz",
    "wof:name":"Hamannit Josef Hamann",
    "wof:placetype":"venue"
},
  "geometry": {"coordinates":[6.84059,50.24474],"type":"Point"}
}