{
  "type": "Feature",
  "properties": {
    "iso:country":"DE",
    "sg:address":"Ihlenfelder Str. 151",
    "sg:city":"Neubrandenburg",
    "sg:phone":"+49 395/4214676",
    "sg:postcode":"17034",
    "sg:province":"Mecklenburg-Vorpommern",
    "wof:name":"Fest Und Veranstaltungs Service Gmbh",
    "wof:placetype":"venue"
},
  "geometry": {"coordinates":[13.299971,53.577137],"type":"Point"}
}