{
  "type": "Feature",
  "properties": {
    "iso:country":"DE",
    "sg:address":"Hohe Weide 15",
    "sg:city":"Hamburg",
    "sg:phone":"+49 40/405823",
    "sg:postcode":"20259",
    "sg:province":"Hamburg",
    "wof:name":"Kaifu Hallen- Und Freibad",
    "wof:placetype":"venue"
},
  "geometry": {"coordinates":[9.9651842117,53.5708045959],"type":"Point"}
}