{
  "type": "Feature",
  "properties": {
    "iso:country":"DE",
    "sg:address":"In der Braike",
    "sg:city":"Owen",
    "sg:phone":"+49 7021/53350",
    "sg:postcode":"73277",
    "sg:province":"Baden-W\u00fcrttemberg",
    "wof:name":"Vereinsgastst\u00e4tte Tsv Owen-teck",
    "wof:placetype":"venue"
},
  "geometry": {"coordinates":[9.4459314346,48.5839881897],"type":"Point"}
}