{
  "type": "Feature",
  "properties": {
    "iso:country":"DE",
    "sg:address":"Altenderner Str. 6",
    "sg:city":"Dortmund",
    "sg:phone":"+49 231/890554",
    "sg:postcode":"44329",
    "sg:province":"Nordrhein-Westfalen",
    "wof:name":"Ernst Schr\u00f6der",
    "wof:placetype":"venue"
},
  "geometry": {"coordinates":[7.50789,51.572639],"type":"Point"}
}