{
  "type": "Feature",
  "properties": {
    "iso:country":"DE",
    "sg:address":"R\u00f6ntgenstr. 4 POSTFACH 1268",
    "sg:city":"Schwarzenbek",
    "sg:phone":"+49 4941/5181011",
    "sg:postcode":"21485",
    "sg:province":"Schleswig-Holstein",
    "wof:name":"Mgk - M. G. Kurth Gmbh",
    "wof:placetype":"venue"
},
  "geometry": {"coordinates":[10.5023374557,53.5050354004],"type":"Point"}
}