{
  "type": "Feature",
  "properties": {
    "iso:country":"DE",
    "sg:address":"Hafenstr. 4c",
    "sg:city":"Worms",
    "sg:phone":"+49 6241/425222",
    "sg:postcode":"67547",
    "sg:province":"Rheinland-Pfalz",
    "wof:name":"Horst Dinges Gmbh",
    "wof:placetype":"venue"
},
  "geometry": {"coordinates":[8.3714780807,49.6433792114],"type":"Point"}
}