{
  "type": "Feature",
  "properties": {
    "iso:country":"DE",
    "sg:address":"Sudetenstr. 46",
    "sg:city":"M\u00f6rfelden-Walldorf",
    "sg:phone":"+49 6105/25676",
    "sg:postcode":"64546",
    "sg:province":"Hessen",
    "wof:name":"Helmuth Schaffarczik",
    "wof:placetype":"venue"
},
  "geometry": {"coordinates":[8.554165,49.973854],"type":"Point"}
}