{
  "type": "Feature",
  "properties": {
    "iso:country":"DE",
    "sg:address":"Rochlitzer Str. 4",
    "sg:city":"Mittweida",
    "sg:phone":"+49 3727/612035",
    "sg:postcode":"09648",
    "sg:province":"Sachsen",
    "wof:name":"Rats-apotheke Inh. Knut Siling E. K.",
    "wof:placetype":"venue"
},
  "geometry": {"coordinates":[12.980192,50.985886],"type":"Point"}
}