{
  "type": "Feature",
  "properties": {
    "iso:country":"DE",
    "sg:address":"Kalkstr. 1a",
    "sg:city":"Iserlohn",
    "sg:phone":"+49 2371/4221463",
    "sg:postcode":"58644",
    "sg:province":"Nordrhein-Westfalen",
    "wof:name":"Heinz Middelmann",
    "wof:placetype":"venue"
},
  "geometry": {"coordinates":[7.6740717888,51.3692092896],"type":"Point"}
}