{
  "type": "Feature",
  "properties": {
    "iso:country":"DE",
    "sg:address":"Marktstr. 6",
    "sg:city":"Bad Wurzach",
    "sg:phone":"+49 4975/642018",
    "sg:postcode":"88410",
    "sg:province":"Baden-W\u00fcrttemberg",
    "wof:name":"Volksbank Bad Wurzach",
    "wof:placetype":"venue"
},
  "geometry": {"coordinates":[9.895263,47.908173],"type":"Point"}
}