{
  "type": "Feature",
  "properties": {
    "iso:country":"DE",
    "sg:address":"Auf dem Steinb\u00fcchel 2",
    "sg:city":"Meckenheim",
    "sg:phone":"+49 2225/4079",
    "sg:postcode":"53340",
    "sg:province":"Nordrhein-Westfalen",
    "wof:name":"Zaun Fliesen Gmbh",
    "wof:placetype":"venue"
},
  "geometry": {"coordinates":[7.048584938,50.6349601746],"type":"Point"}
}