{
  "type": "Feature",
  "properties": {
    "iso:country":"DE",
    "sg:address":"Koellikerstr. 13",
    "sg:city":"W\u00fcrzburg",
    "sg:phone":"+49 931/14352",
    "sg:postcode":"97070",
    "sg:province":"Bayern",
    "wof:name":"J\u00f6rg Schild",
    "wof:placetype":"venue"
},
  "geometry": {"coordinates":[9.92929,49.798641],"type":"Point"}
}