{
  "type": "Feature",
  "properties": {
    "iso:country":"DE",
    "sg:address":"Simonshofer Str. 42",
    "sg:city":"Schnaittach",
    "sg:postcode":"91220",
    "sg:province":"Bayern",
    "wof:name":"Titzmann & Co. Gmbh",
    "wof:placetype":"venue"
},
  "geometry": {"coordinates":[11.33113,49.55632],"type":"Point"}
}