{
  "type": "Feature",
  "properties": {
    "iso:country":"DE",
    "sg:address":"Schornreuteweg 80",
    "sg:city":"Ravensburg",
    "sg:postcode":"88212",
    "sg:province":"Baden-W\u00fcrttemberg",
    "wof:name":"Verm\u00f6gensmanagement Andreas Bernhardt Gmbh",
    "wof:placetype":"venue"
},
  "geometry": {"coordinates":[9.6206445694,47.7667121887],"type":"Point"}
}