{
  "type": "Feature",
  "properties": {
    "iso:country":"DE",
    "sg:address":"Auf Hambuch 5",
    "sg:city":"Morbach",
    "sg:phone":"+49 6533/3830",
    "sg:postcode":"54497",
    "sg:province":"Rheinland-Pfalz",
    "wof:name":"Clemens Und Rudolf Bohr Zimmerei Gmbh",
    "wof:placetype":"venue"
},
  "geometry": {"coordinates":[7.1328148842,49.8143081665],"type":"Point"}
}