{
  "type": "Feature",
  "properties": {
    "iso:country":"DE",
    "sg:address":"Alemannenstr. 10",
    "sg:city":"Stockach",
    "sg:phone":"+49 7771/919513",
    "sg:postcode":"78333",
    "sg:province":"Baden-W\u00fcrttemberg",
    "wof:name":"H & M M\u00f6belmarkt K\u00fcchen- Und M\u00f6belhandelsges. Mbh",
    "wof:placetype":"venue"
},
  "geometry": {"coordinates":[9.001831,47.844429],"type":"Point"}
}