{
  "type": "Feature",
  "properties": {
    "iso:country":"DE",
    "sg:address":"Freiherr-vom-Stein-Str. 12",
    "sg:city":"Hessisch Lichtenau",
    "sg:phone":"+49 5602/1314",
    "sg:postcode":"37235",
    "sg:province":"Hessen",
    "wof:name":"Hallenbad",
    "wof:placetype":"venue"
},
  "geometry": {"coordinates":[9.7260036469,51.2038764954],"type":"Point"}
}