{
  "type": "Feature",
  "properties": {
    "iso:country":"DE",
    "sg:address":"F\u00fcssener Str. 26",
    "sg:city":"Burggen",
    "sg:phone":"+49 8860/1449",
    "sg:postcode":"86977",
    "sg:province":"Bayern",
    "wof:name":"Alois Martin",
    "wof:placetype":"venue"
},
  "geometry": {"coordinates":[10.812262,47.774811],"type":"Point"}
}