{
  "type": "Feature",
  "properties": {
    "iso:country":"DE",
    "sg:address":"Stadtplatz 24",
    "sg:city":"Pfarrkirchen",
    "sg:phone":"+49 8561/1306",
    "sg:postcode":"84347",
    "sg:province":"Bayern",
    "wof:name":"Cafe Venezia",
    "wof:placetype":"venue"
},
  "geometry": {"coordinates":[12.939516,48.432137],"type":"Point"}
}