{
  "type": "Feature",
  "properties": {
    "iso:country":"DE",
    "sg:address":"Colmarer Str. 46",
    "sg:city":"Memmingen",
    "sg:phone":"+49 8331/87023",
    "sg:postcode":"87700",
    "sg:province":"Bayern",
    "wof:name":"Dieters Zoo Inh. Dieter Hassmann",
    "wof:placetype":"venue"
},
  "geometry": {"coordinates":[10.182332,47.995029],"type":"Point"}
}