{
  "type": "Feature",
  "properties": {
    "iso:country":"DE",
    "sg:address":"Kronenstr. 26",
    "sg:city":"Troisdorf",
    "sg:phone":"+49 2241/91310",
    "sg:postcode":"53840",
    "sg:province":"Nordrhein-Westfalen",
    "wof:name":"Zag Zahntechnische Abrechnungsstelle",
    "wof:placetype":"venue"
},
  "geometry": {"coordinates":[7.154922,50.817623],"type":"Point"}
}