{
  "type": "Feature",
  "properties": {
    "iso:country":"DE",
    "sg:address":"Lockhofstr. 13",
    "sg:city":"Gelsenkirchen",
    "sg:postcode":"45881",
    "sg:province":"Nordrhein-Westfalen",
    "wof:name":"K. & C. Grundbesitz Verwaltungs-gmbh",
    "wof:placetype":"venue"
},
  "geometry": {"coordinates":[7.0782628059,51.5224380493],"type":"Point"}
}