{
  "type": "Feature",
  "properties": {
    "iso:country":"DE",
    "sg:address":"Gro\u00dfer Sand 85",
    "sg:city":"Uetersen",
    "sg:phone":"+49 4122/489974",
    "sg:postcode":"25436",
    "sg:province":"Schleswig-Holstein",
    "wof:name":"Musikhaus Und Akkordionzentrum",
    "wof:placetype":"venue"
},
  "geometry": {"coordinates":[9.6732492447,53.6814689636],"type":"Point"}
}