{
  "type": "Feature",
  "properties": {
    "iso:country":"DE",
    "sg:address":"Bahnhofstr. 6",
    "sg:city":"K\u00f6ln",
    "sg:phone":"+49 2203/53075",
    "sg:postcode":"51143",
    "sg:province":"Nordrhein-Westfalen",
    "wof:name":"Redaktion K\u00f6lner Stadt-anzeiger",
    "wof:placetype":"venue"
},
  "geometry": {"coordinates":[7.0553689003,50.8838272095],"type":"Point"}
}