{
  "type": "Feature",
  "properties": {
    "iso:country":"DE",
    "sg:address":"Oelbecker Str. 4",
    "sg:city":"Volkmarsen",
    "sg:phone":"+49 5693/7147",
    "sg:postcode":"34471",
    "sg:province":"Hessen",
    "wof:name":"K. Schaake",
    "wof:placetype":"venue"
},
  "geometry": {"coordinates":[9.1203298569,51.3780593872],"type":"Point"}
}