{
  "type": "Feature",
  "properties": {
    "iso:country":"DE",
    "sg:address":"Ludwigshafener Str. 37",
    "sg:city":"D\u00fcsseldorf",
    "sg:phone":"+49 211/9216047",
    "sg:postcode":"40229",
    "sg:province":"Nordrhein-Westfalen",
    "wof:name":"Klaus Stiehler",
    "wof:placetype":"venue"
},
  "geometry": {"coordinates":[6.8318228722,51.2037734985],"type":"Point"}
}