{
  "type": "Feature",
  "properties": {
    "iso:country":"DE",
    "sg:address":"Ringstra\u00dfe 77",
    "sg:city":"Raunheim",
    "sg:phone":"+49 6142",
    "sg:postcode":"65479",
    "sg:province":"Hessen",
    "wof:name":"Pc-service, Hard & Software",
    "wof:placetype":"venue"
},
  "geometry": {"coordinates":[8.447299,50.006638],"type":"Point"}
}