{
  "type": "Feature",
  "properties": {
    "iso:country":"DE",
    "sg:address":"Geldersheimer Str. 66",
    "sg:city":"Schweinfurt",
    "sg:phone":"+49 9721/806152",
    "sg:postcode":"97424",
    "sg:province":"Bayern",
    "wof:name":"Josef M\u00fcller",
    "wof:placetype":"venue"
},
  "geometry": {"coordinates":[10.1930322647,50.0409431458],"type":"Point"}
}