{
  "type": "Feature",
  "properties": {
    "iso:country":"DE",
    "sg:address":"Zittauer Str.42",
    "sg:city":"Putzkau",
    "sg:postcode":"01877",
    "sg:province":"Sachsen",
    "wof:name":"Willkommen Bei Michael J\u00e4ger",
    "wof:placetype":"venue"
},
  "geometry": {"coordinates":[14.24316,51.099602],"type":"Point"}
}