{
  "type": "Feature",
  "properties": {
    "iso:country":"DE",
    "sg:address":"Lessingstr. 13",
    "sg:city":"Altenburg",
    "sg:phone":"+49 3447/831091",
    "sg:postcode":"04600",
    "sg:province":"Th\u00fcringen",
    "wof:name":"Holger Hammitzsch",
    "wof:placetype":"venue"
},
  "geometry": {"coordinates":[12.446596,50.983738],"type":"Point"}
}