{
  "type": "Feature",
  "properties": {
    "iso:country":"DE",
    "sg:address":"Sch\u00fctzenhofstr. 1a",
    "sg:city":"Brotterode",
    "sg:phone":"+49 36840/32404",
    "sg:postcode":"98599",
    "sg:province":"Th\u00fcringen",
    "wof:name":"Harry Steinbach",
    "wof:placetype":"venue"
},
  "geometry": {"coordinates":[10.4458427429,50.8233146667],"type":"Point"}
}