{
  "type": "Feature",
  "properties": {
    "iso:country":"DE",
    "sg:address":"Schlehdornweg 68",
    "sg:city":"Ibbenb\u00fcren",
    "sg:phone":"+49 5451/13818",
    "sg:postcode":"49479",
    "sg:province":"Nordrhein-Westfalen",
    "wof:name":"Horst G\u00f6vert",
    "wof:placetype":"venue"
},
  "geometry": {"coordinates":[7.6742978096,52.3097801208],"type":"Point"}
}