{
  "type": "Feature",
  "properties": {
    "iso:country":"DE",
    "sg:address":"Brunnenstr. 15",
    "sg:city":"Fleringen",
    "sg:phone":"+49 6558/8549",
    "sg:postcode":"54597",
    "sg:province":"Rheinland-Pfalz",
    "wof:name":"Georg Weinandy",
    "wof:placetype":"venue"
},
  "geometry": {"coordinates":[6.502281,50.206455],"type":"Point"}
}