{
  "type": "Feature",
  "properties": {
    "iso:country":"DE",
    "sg:address":"Bockenheimer Landstr. 67",
    "sg:city":"Frankfurt",
    "sg:phone":"+49 69/727912",
    "sg:postcode":"60325",
    "sg:province":"Hessen",
    "wof:name":"Cafe Laumer",
    "wof:placetype":"venue"
},
  "geometry": {"coordinates":[8.6624231339,50.1181983948],"type":"Point"}
}