{
  "type": "Feature",
  "properties": {
    "iso:country":"DE",
    "sg:address":"Am Wiesengrund 9 a",
    "sg:city":"Garlstorf",
    "sg:postcode":"21376",
    "sg:province":"Niedersachsen",
    "wof:name":"Rainer Henze Baubetreuung E.k.",
    "wof:placetype":"venue"
},
  "geometry": {"coordinates":[10.096779,53.239838],"type":"Point"}
}