{
  "type": "Feature",
  "properties": {
    "iso:country":"DE",
    "sg:address":"Knechtstedener Str. 10",
    "sg:city":"Dormagen",
    "sg:phone":"+49 2133/5696",
    "sg:postcode":"41540",
    "sg:province":"Nordrhein-Westfalen",
    "wof:name":"J\u00e4gersruh",
    "wof:placetype":"venue"
},
  "geometry": {"coordinates":[6.8149380684,51.0986938477],"type":"Point"}
}