{
  "type": "Feature",
  "properties": {
    "iso:country":"DE",
    "sg:address":"Warmbronner Str. 14",
    "sg:city":"Sindelfingen",
    "sg:phone":"+49 7031/801880",
    "sg:postcode":"71063",
    "sg:province":"Baden-W\u00fcrttemberg",
    "wof:name":"R. Sekinger",
    "wof:placetype":"venue"
},
  "geometry": {"coordinates":[9.0035810471,48.7203483582],"type":"Point"}
}