{
  "type": "Feature",
  "properties": {
    "iso:country":"DE",
    "sg:address":"177",
    "sg:city":"ILLKIRCH-GRAFFENSTADEN",
    "sg:phone":"+49 3886/72128",
    "sg:postcode":"67400",
    "wof:name":"Depannage 67",
    "wof:placetype":"venue"
},
  "geometry": {"coordinates":[7.711647,48.529846],"type":"Point"}
}