{
  "type": "Feature",
  "properties": {
    "iso:country":"DE",
    "sg:address":"Hagenstr. 34",
    "sg:city":"Northeim",
    "sg:phone":"+49 5551/8391",
    "sg:postcode":"37154",
    "sg:province":"Niedersachsen",
    "wof:name":"Johannes Fiebich",
    "wof:placetype":"venue"
},
  "geometry": {"coordinates":[10.00041,51.705006],"type":"Point"}
}