{
  "type": "Feature",
  "properties": {
    "iso:country":"DE",
    "sg:address":"Bezirksamtsstr. 49",
    "sg:city":"Rockenhausen",
    "sg:phone":"+49 6361/7385",
    "sg:postcode":"67806",
    "sg:province":"Rheinland-Pfalz",
    "wof:name":"Annenhof",
    "wof:placetype":"venue"
},
  "geometry": {"coordinates":[7.8213028908,49.6350364685],"type":"Point"}
}