{
  "type": "Feature",
  "properties": {
    "iso:country":"DE",
    "sg:address":"Untere Hauptstr. 21",
    "sg:city":"Kippenheim",
    "sg:phone":"+49 7825/1798",
    "sg:postcode":"77971",
    "sg:province":"Baden-W\u00fcrttemberg",
    "wof:name":"Rolf Bauer",
    "wof:placetype":"venue"
},
  "geometry": {"coordinates":[7.8243999481,48.2953643799],"type":"Point"}
}