{
  "type": "Feature",
  "properties": {
    "iso:country":"DE",
    "sg:address":"Paul-Gerhardt-Str. 27",
    "sg:city":"Harsum",
    "sg:phone":"+49 5127/1550",
    "sg:postcode":"31177",
    "sg:province":"Niedersachsen",
    "wof:name":"Hansotto Hohmann",
    "wof:placetype":"venue"
},
  "geometry": {"coordinates":[10.0028247833,52.2081451416],"type":"Point"}
}