{
  "type": "Feature",
  "properties": {
    "iso:country":"DE",
    "sg:address":"Daimlerstr. 14",
    "sg:city":"Neus\u00e4\u00df",
    "sg:phone":"+49 821/465658",
    "sg:postcode":"86356",
    "sg:province":"Bayern",
    "wof:name":"Norma Gmbh & Co. Kg Lebensmittelfilialbetrieb",
    "wof:placetype":"venue"
},
  "geometry": {"coordinates":[10.8261356354,48.3933258057],"type":"Point"}
}