{
  "type": "Feature",
  "properties": {
    "iso:country":"DE",
    "sg:address":"Dillinger Str. 18",
    "sg:city":"Burgau",
    "sg:phone":"+49 8222/7559",
    "sg:postcode":"89331",
    "sg:province":"Bayern",
    "wof:name":"Wml Markus Laudahn Gmbh",
    "wof:placetype":"venue"
},
  "geometry": {"coordinates":[10.411243,48.435764],"type":"Point"}
}