{
  "type": "Feature",
  "properties": {
    "iso:country":"DE",
    "sg:address":"Elhornstr. 4",
    "sg:city":"Stuhr",
    "sg:phone":"+49 421/895736",
    "sg:postcode":"28816",
    "sg:province":"Niedersachsen",
    "wof:name":"Cb-bau Gesellschaft F\u00fcr Familiengerechtes Wohnen Mbh",
    "wof:placetype":"venue"
},
  "geometry": {"coordinates":[8.792358,53.012272],"type":"Point"}
}