{
  "type": "Feature",
  "properties": {
    "iso:country":"DE",
    "sg:address":"Markt 6",
    "sg:city":"Celle",
    "sg:postcode":"29221",
    "sg:province":"Niedersachsen",
    "wof:name":"Tourismus Region Celle Gmbh",
    "wof:placetype":"venue"
},
  "geometry": {"coordinates":[10.0814151764,52.6247062683],"type":"Point"}
}