{
  "type": "Feature",
  "properties": {
    "iso:country":"DE",
    "sg:address":"In der Gr\u00fcnd 5",
    "sg:city":"Ortenberg",
    "sg:phone":"+49 781/34017",
    "sg:postcode":"77799",
    "sg:province":"Baden-W\u00fcrttemberg",
    "wof:name":"E. Und M. Rieder Steuerberater",
    "wof:placetype":"venue"
},
  "geometry": {"coordinates":[7.9738030434,48.4557228088],"type":"Point"}
}