{
  "type": "Feature",
  "properties": {
    "iso:country":"DE",
    "sg:address":"Bahnhofstr. 9",
    "sg:city":"Penzberg",
    "sg:phone":"+49 8856/3444",
    "sg:postcode":"82377",
    "sg:province":"Bayern",
    "wof:name":"Barbara C\u00f6llen",
    "wof:placetype":"venue"
},
  "geometry": {"coordinates":[11.3733034134,47.7496566772],"type":"Point"}
}