{
  "type": "Feature",
  "properties": {
    "iso:country":"DE",
    "sg:address":"Hofkoppelweg 16",
    "sg:city":"Hanerau-Hademarschen",
    "sg:phone":"+49 4872/96000",
    "sg:postcode":"25557",
    "sg:province":"Schleswig-Holstein",
    "wof:name":"Heinrich Tepker Verwaltungsgesellschaft Mbh",
    "wof:placetype":"venue"
},
  "geometry": {"coordinates":[9.424842,54.125187],"type":"Point"}
}