{
  "type": "Feature",
  "properties": {
    "iso:country":"DE",
    "sg:address":"Laufenbergstr. 1",
    "sg:city":"Bonn",
    "sg:phone":"+49 228/317466",
    "sg:postcode":"53173",
    "sg:province":"Nordrhein-Westfalen",
    "wof:name":"Alfred Wendlandt",
    "wof:placetype":"venue"
},
  "geometry": {"coordinates":[7.1485671997,50.6881637573],"type":"Point"}
}