{
  "type": "Feature",
  "properties": {
    "iso:country":"DE",
    "sg:address":"Bismarckstr. 87",
    "sg:city":"Remscheid",
    "sg:phone":"+49 2191/31890",
    "sg:postcode":"42859",
    "sg:province":"Nordrhein-Westfalen",
    "wof:name":"Discothek Bismarckplatz",
    "wof:placetype":"venue"
},
  "geometry": {"coordinates":[7.206421,51.176437],"type":"Point"}
}