{
  "type": "Feature",
  "properties": {
    "iso:country":"DE",
    "sg:address":"M\u00fcllerstr. 5",
    "sg:city":"Schweigen-Rechtenbach",
    "sg:phone":"+49 6342/919042",
    "sg:postcode":"76889",
    "sg:province":"Rheinland-Pfalz",
    "wof:name":"Hans Gn\u00e4gy Weinanbau",
    "wof:placetype":"venue"
},
  "geometry": {"coordinates":[7.9580597878,49.0538902283],"type":"Point"}
}