{
  "type": "Feature",
  "properties": {
    "iso:country":"DE",
    "sg:address":"Feuerbacher Str. 134",
    "sg:city":"Gerlingen",
    "sg:phone":"+49 7156/29645",
    "sg:postcode":"70839",
    "sg:province":"Baden-W\u00fcrttemberg",
    "wof:name":"Vokus Speiseeis-vertriebs Gmbh",
    "wof:placetype":"venue"
},
  "geometry": {"coordinates":[9.0849761963,48.8025360107],"type":"Point"}
}