{
  "type": "Feature",
  "properties": {
    "iso:country":"DE",
    "sg:address":"Willi-Graf-Str. 9",
    "sg:city":"Euskirchen",
    "sg:phone":"+49 2251/53328",
    "sg:postcode":"53881",
    "sg:province":"Nordrhein-Westfalen",
    "wof:name":"Walter Lehnert Steuerberater",
    "wof:placetype":"venue"
},
  "geometry": {"coordinates":[6.8298449516,50.6509017944],"type":"Point"}
}