{
  "type": "Feature",
  "properties": {
    "iso:country":"DE",
    "sg:address":"Am Weiher 12",
    "sg:city":"Kreuzwertheim",
    "sg:phone":"+49 9342/91880",
    "sg:postcode":"97892",
    "sg:province":"Bayern",
    "wof:name":"Gaby R\u00fcppel Steuerberaterin",
    "wof:placetype":"venue"
},
  "geometry": {"coordinates":[9.5246191025,49.8025779724],"type":"Point"}
}