{
  "type": "Feature",
  "properties": {
    "iso:country":"DE",
    "sg:address":"Urbanusstr 32",
    "sg:city":"Gelsenkirchen",
    "sg:phone":"+49 209/933310",
    "sg:postcode":"45894",
    "sg:province":"Nordrhein-Westfalen",
    "wof:name":"Alarm-zentrale Gmbh & Co Kg",
    "wof:placetype":"venue"
},
  "geometry": {"coordinates":[7.047515,51.576683],"type":"Point"}
}