{
  "type": "Feature",
  "properties": {
    "iso:country":"DE",
    "sg:address":"Gr\u00fcner Weg 2",
    "sg:city":"Straubing",
    "sg:phone":"+49 9421/4566",
    "sg:postcode":"94315",
    "sg:province":"Bayern",
    "wof:name":"H. Farmer",
    "wof:placetype":"venue"
},
  "geometry": {"coordinates":[12.59471035,48.8694458008],"type":"Point"}
}