{
  "type": "Feature",
  "properties": {
    "iso:country":"DE",
    "sg:address":"St\u00f6ckleinstr. 10",
    "sg:city":"Sonderhofen",
    "sg:phone":"+49 9337/526",
    "sg:postcode":"97255",
    "sg:province":"Bayern",
    "wof:name":"Oswald Knorr",
    "wof:placetype":"venue"
},
  "geometry": {"coordinates":[10.004583,49.59314],"type":"Point"}
}