{
  "type": "Feature",
  "properties": {
    "iso:country":"DE",
    "sg:address":"Andreas-Hermes-Str. 7",
    "sg:city":"Bonn",
    "sg:phone":"+49 228/959140",
    "sg:postcode":"53175",
    "sg:province":"Nordrhein-Westfalen",
    "wof:name":"Lutum & Tappert Ov-beratung Gmbh",
    "wof:placetype":"venue"
},
  "geometry": {"coordinates":[7.1469140053,50.7051239014],"type":"Point"}
}