{
  "type": "Feature",
  "properties": {
    "iso:country":"DE",
    "sg:address":"Haagstr. 19",
    "sg:city":"H\u00fcckelhoven",
    "sg:phone":"+49 2433/84888",
    "sg:postcode":"41836",
    "sg:province":"Nordrhein-Westfalen",
    "wof:name":"Arthur Babb Masseur",
    "wof:placetype":"venue"
},
  "geometry": {"coordinates":[6.224376,51.052422],"type":"Point"}
}