{
  "type": "Feature",
  "properties": {
    "iso:country":"DE",
    "sg:address":"Klever Str. 56",
    "sg:city":"Krefeld",
    "sg:phone":"+49 2151/730773",
    "sg:postcode":"47839",
    "sg:province":"Nordrhein-Westfalen",
    "wof:name":"Ludwig Kandzior Drogerie",
    "wof:placetype":"venue"
},
  "geometry": {"coordinates":[6.50016,51.390331],"type":"Point"}
}