{
  "type": "Feature",
  "properties": {
    "iso:country":"DE",
    "sg:address":"Schwammenaueler Str. 29",
    "sg:city":"Heimbach",
    "sg:phone":"+49 2446/495",
    "sg:postcode":"52396",
    "sg:province":"Nordrhein-Westfalen",
    "wof:name":"Pension Haus Fernblick",
    "wof:placetype":"venue"
},
  "geometry": {"coordinates":[6.4606618881,50.6359786987],"type":"Point"}
}