{
  "type": "Feature",
  "properties": {
    "iso:country":"DE",
    "sg:address":"An den Bergwiesen 7",
    "sg:city":"Gundelsheim",
    "sg:postcode":"96163",
    "sg:province":"Bayern",
    "wof:name":"Jan Kolbe Einbauger\u00e4te Gmbh",
    "wof:placetype":"venue"
},
  "geometry": {"coordinates":[10.932095,49.939816],"type":"Point"}
}