{
  "type": "Feature",
  "properties": {
    "iso:country":"DE",
    "sg:address":"Belziger Str. 23",
    "sg:city":"Kranepuhl",
    "sg:phone":"+49 33841/32103",
    "sg:postcode":"14806",
    "sg:province":"Brandenburg",
    "wof:name":"Bertold Mentzel",
    "wof:placetype":"venue"
},
  "geometry": {"coordinates":[12.613335,52.09959],"type":"Point"}
}