{
  "type": "Feature",
  "properties": {
    "iso:country":"DE",
    "sg:address":"Ottilienstr. 17",
    "sg:city":"Bad Homburg",
    "sg:postcode":"61348",
    "sg:province":"Hessen",
    "wof:name":"Nk Dr. Park Gmbh",
    "wof:placetype":"venue"
},
  "geometry": {"coordinates":[8.6162881851,50.2312545776],"type":"Point"}
}