{
  "type": "Feature",
  "properties": {
    "iso:country":"DE",
    "sg:address":"Am Storrenacker 4",
    "sg:city":"Karlsruhe",
    "sg:phone":"+49 721/62870",
    "sg:postcode":"76139",
    "sg:province":"Baden-W\u00fcrttemberg",
    "wof:name":"Thyssen Schulte Metallcenter Gmbh",
    "wof:placetype":"venue"
},
  "geometry": {"coordinates":[8.459586,49.019943],"type":"Point"}
}