{
  "type": "Feature",
  "properties": {
    "iso:country":"DE",
    "sg:address":"Richardplatz 16",
    "sg:city":"Berlin",
    "sg:phone":"+49 30/6372688",
    "sg:postcode":"12055",
    "sg:province":"Berlin",
    "wof:name":"Tews Pro Techno Gmbh",
    "wof:placetype":"venue"
},
  "geometry": {"coordinates":[13.445067,52.473763],"type":"Point"}
}