{
  "type": "Feature",
  "properties": {
    "iso:country":"DE",
    "sg:address":"R\u00f6llingheiderstr 6",
    "sg:city":"Gevelsberg",
    "sg:phone":"+49 2332/80444",
    "sg:postcode":"58285",
    "sg:province":"Nordrhein-Westfalen",
    "wof:name":"Armbrecht Matthes Verpackungstechnik",
    "wof:placetype":"venue"
},
  "geometry": {"coordinates":[7.329171,51.321968],"type":"Point"}
}