{
  "type": "Feature",
  "properties": {
    "iso:country":"DE",
    "sg:address":"Bornwiesstr. 12",
    "sg:city":"Nohfelden",
    "sg:phone":"+49 6857/799",
    "sg:postcode":"66625",
    "sg:province":"Saarland",
    "wof:name":"J\u00f6rg Schmidt",
    "wof:placetype":"venue"
},
  "geometry": {"coordinates":[7.158945,49.55735],"type":"Point"}
}