{
  "type": "Feature",
  "properties": {
    "iso:country":"DE",
    "sg:address":"An der Sandelm\u00fchle 13",
    "sg:city":"Frankfurt",
    "sg:phone":"+49 69/95403254",
    "sg:postcode":"60439",
    "sg:province":"Hessen",
    "wof:name":"Stb Paul Hahn Gesellschaft F\u00fcr Arbeits- Und Umweltschutz Mbh",
    "wof:placetype":"venue"
},
  "geometry": {"coordinates":[8.6461267471,50.1650123596],"type":"Point"}
}