{
  "type": "Feature",
  "properties": {
    "iso:country":"DE",
    "sg:address":"Regaweg 1",
    "sg:city":"Hannover",
    "sg:phone":"+49 511/517173",
    "sg:postcode":"30559",
    "sg:province":"Niedersachsen",
    "wof:name":"Maren Claussen Steuerberaterin",
    "wof:placetype":"venue"
},
  "geometry": {"coordinates":[9.852437973,52.3664855957],"type":"Point"}
}