{
  "type": "Feature",
  "properties": {
    "iso:country":"DE",
    "sg:address":"Westerholterweg 10",
    "sg:city":"Recklinghausen",
    "sg:phone":"+49 2361/27777",
    "sg:postcode":"45657",
    "sg:province":"Nordrhein-Westfalen",
    "wof:name":"Barth & Bothe Steuerberatungs Gmbh",
    "wof:placetype":"venue"
},
  "geometry": {"coordinates":[7.1912031174,51.6143875122],"type":"Point"}
}