{
  "type": "Feature",
  "properties": {
    "iso:country":"DE",
    "sg:address":"Laufamholzstrasse 114",
    "sg:city":"N\u00fcrnberg",
    "sg:phone":"+49 911/5460561",
    "sg:postcode":"90482",
    "sg:province":"Bayern",
    "wof:name":"Campus Sports & Reha Gmbh Fitness Kg N\u00fcrnberg",
    "wof:placetype":"venue"
},
  "geometry": {"coordinates":[11.146312,49.463726],"type":"Point"}
}