{
  "type": "Feature",
  "properties": {
    "iso:country":"DE",
    "sg:address":"Oestlestr. 8",
    "sg:city":"St\u00f6ttwang",
    "sg:phone":"+49 8345/1661",
    "sg:postcode":"87677",
    "sg:province":"Bayern",
    "wof:name":"H. Kl\u00f6ck",
    "wof:placetype":"venue"
},
  "geometry": {"coordinates":[10.7014541626,47.8980522156],"type":"Point"}
}