{
  "type": "Feature",
  "properties": {
    "iso:country":"DE",
    "sg:address":"Friedrich-Engels-Str. 93",
    "sg:city":"Hohenstein-Ernstthal",
    "sg:postcode":"09337",
    "sg:province":"Sachsen",
    "wof:name":"Ersatzteilfertigung Hohenstein-ernstthal Gmbh",
    "wof:placetype":"venue"
},
  "geometry": {"coordinates":[12.693919,50.795414],"type":"Point"}
}