{
  "type": "Feature",
  "properties": {
    "iso:country":"DE",
    "sg:address":"Kreuzmattenstr. 14",
    "sg:city":"Heidersheim",
    "sg:phone":"+49 4976/3450670",
    "sg:postcode":"79423",
    "sg:province":"Baden-W\u00fcrttemberg",
    "wof:name":"Pfefferle B\u00dcrsten Gmbh",
    "wof:placetype":"venue"
},
  "geometry": {"coordinates":[7.6436009407,47.8719024658],"type":"Point"}
}