{
  "type": "Feature",
  "properties": {
    "iso:country":"DE",
    "sg:address":"Reuther Str. 76",
    "sg:city":"Forchheim",
    "sg:phone":"+49 9191/60527",
    "sg:postcode":"91301",
    "sg:province":"Bayern",
    "wof:name":"Ingo Gro\u00dfkopf",
    "wof:placetype":"venue"
},
  "geometry": {"coordinates":[11.0967340469,49.715763092],"type":"Point"}
}