{
  "type": "Feature",
  "properties": {
    "iso:country":"DE",
    "sg:address":"Birkenwaldstr. 151",
    "sg:city":"Stuttgart",
    "sg:postcode":"70191",
    "sg:province":"Baden-W\u00fcrttemberg",
    "wof:name":"Ausland Glas Beteiligungen Gmbh",
    "wof:placetype":"venue"
},
  "geometry": {"coordinates":[9.173473,48.793262],"type":"Point"}
}