{
  "type": "Feature",
  "properties": {
    "iso:country":"DE",
    "sg:address":"Leonhardstr. 22",
    "sg:city":"Wolfersdorf",
    "sg:phone":"+49 8168/1833",
    "sg:postcode":"85395",
    "sg:province":"Bayern",
    "wof:name":"Gastst\u00e4tte Sebastian Schweiger",
    "wof:placetype":"venue"
},
  "geometry": {"coordinates":[11.6880235672,48.4795455933],"type":"Point"}
}