{
  "type": "Feature",
  "properties": {
    "iso:country":"DE",
    "sg:address":"Spanger Str. 2",
    "sg:city":"Cuxhaven",
    "sg:phone":"+49 4721/29035",
    "sg:postcode":"27476",
    "sg:province":"Niedersachsen",
    "wof:name":"H. M. Itjen Ohg",
    "wof:placetype":"venue"
},
  "geometry": {"coordinates":[8.635253,53.864033],"type":"Point"}
}