{
  "type": "Feature",
  "properties": {
    "iso:country":"DE",
    "sg:address":"Am Obereichholz 1-3",
    "sg:city":"Marktheidenfeld",
    "sg:phone":"+49 9391/1018",
    "sg:postcode":"97828",
    "sg:province":"Bayern",
    "wof:name":"Dartpoint Gmbh",
    "wof:placetype":"venue"
},
  "geometry": {"coordinates":[9.6073932648,49.8543395996],"type":"Point"}
}