{
  "type": "Feature",
  "properties": {
    "iso:country":"DE",
    "sg:address":"Lindenstr. 20",
    "sg:city":"Celle",
    "sg:phone":"+49 5141/33928",
    "sg:postcode":"29223",
    "sg:province":"Niedersachsen",
    "wof:name":"Kurt Hoffmeister",
    "wof:placetype":"venue"
},
  "geometry": {"coordinates":[10.069966,52.633179],"type":"Point"}
}