{
  "type": "Feature",
  "properties": {
    "iso:country":"DE",
    "sg:address":"Fichtenstr. 13",
    "sg:city":"Remchingen",
    "sg:phone":"+49 7232/734648",
    "sg:postcode":"75196",
    "sg:province":"Baden-W\u00fcrttemberg",
    "wof:name":"Techno Leasing Gmbh",
    "wof:placetype":"venue"
},
  "geometry": {"coordinates":[8.5648546219,48.9433021545],"type":"Point"}
}