{
  "type": "Feature",
  "properties": {
    "iso:country":"DE",
    "sg:address":"Herrenstr. 4",
    "sg:city":"Memmingen",
    "sg:phone":"+49 8331/495873",
    "sg:postcode":"87700",
    "sg:province":"Bayern",
    "wof:name":"As-friseurbedarf Gmbh",
    "wof:placetype":"venue"
},
  "geometry": {"coordinates":[10.1801300049,47.984664917],"type":"Point"}
}