{
  "type": "Feature",
  "properties": {
    "iso:country":"DE",
    "sg:address":"Dankwartstr. 14",
    "sg:city":"Wismar",
    "sg:phone":"+49 3841/212165",
    "sg:postcode":"23966",
    "sg:province":"Mecklenburg-Vorpommern",
    "wof:name":"C. Schaarschmidt Und Offermann",
    "wof:placetype":"venue"
},
  "geometry": {"coordinates":[11.464775,53.890377],"type":"Point"}
}