{
  "type": "Feature",
  "properties": {
    "iso:country":"DE",
    "sg:address":"Gehrenstr. 5",
    "sg:city":"Bad Kohlgrub",
    "sg:phone":"+49 8845/448",
    "sg:postcode":"82433",
    "sg:province":"Bayern",
    "wof:name":"Pension Kurbad Fortuna",
    "wof:placetype":"venue"
},
  "geometry": {"coordinates":[11.0543632507,47.6637496948],"type":"Point"}
}