{
  "type": "Feature",
  "properties": {
    "iso:country":"DE",
    "sg:address":"Rehfeld 36",
    "sg:city":"Pentling",
    "sg:phone":"+49 9405/3122",
    "sg:postcode":"93080",
    "sg:province":"Bayern",
    "wof:name":"Dr. Helmut Adam Ingenieur",
    "wof:placetype":"venue"
},
  "geometry": {"coordinates":[12.0673389435,48.9588127136],"type":"Point"}
}