{
  "type": "Feature",
  "properties": {
    "iso:country":"DE",
    "sg:address":"Lankwitzer Str. 17-18",
    "sg:city":"Berlin",
    "sg:phone":"+49 30/747040",
    "sg:postcode":"12107",
    "sg:province":"Berlin",
    "wof:name":"Hinz Fabrik Gmbh",
    "wof:placetype":"venue"
},
  "geometry": {"coordinates":[13.3764858246,52.4371681213],"type":"Point"}
}