{
  "type": "Feature",
  "properties": {
    "iso:country":"DE",
    "sg:address":"Pastor-Rentz-Str. 2",
    "sg:city":"Kamp-Bornhofen",
    "sg:phone":"+49 6773/509",
    "sg:postcode":"56341",
    "sg:province":"Rheinland-Pfalz",
    "wof:name":"J. A. Diesler",
    "wof:placetype":"venue"
},
  "geometry": {"coordinates":[7.6151680946,50.229057312],"type":"Point"}
}