{
  "type": "Feature",
  "properties": {
    "iso:country":"DE",
    "sg:address":"Irkutsker Str. 179",
    "sg:city":"Chemnitz",
    "sg:postcode":"09119",
    "sg:province":"Sachsen",
    "wof:name":"J. Mehrwald",
    "wof:placetype":"venue"
},
  "geometry": {"coordinates":[12.8931837082,50.8149299622],"type":"Point"}
}