{
  "type": "Feature",
  "properties": {
    "iso:country":"DE",
    "sg:address":"Panzerleite 24",
    "sg:city":"Bamberg",
    "sg:phone":"+49 951/952300",
    "sg:postcode":"96049",
    "sg:province":"Bayern",
    "wof:name":"Langlouis Gmbh",
    "wof:placetype":"venue"
},
  "geometry": {"coordinates":[10.8782987595,49.8862571716],"type":"Point"}
}