{
  "type": "Feature",
  "properties": {
    "iso:country":"DE",
    "sg:address":"Wallrabser Str. 30",
    "sg:city":"Hildburghausen",
    "sg:phone":"+49 3685/703267",
    "sg:postcode":"98646",
    "sg:province":"Th\u00fcringen",
    "wof:name":"Klaus Hartung",
    "wof:placetype":"venue"
},
  "geometry": {"coordinates":[10.71501,50.41893],"type":"Point"}
}