{
  "type": "Feature",
  "properties": {
    "iso:country":"DE",
    "sg:address":"Zum Hasengarten 9",
    "sg:city":"Bad Bederkesa",
    "sg:postcode":"27624",
    "sg:province":"Niedersachsen",
    "wof:name":"Bio-train Fitness- Und Freizeitpark",
    "wof:placetype":"venue"
},
  "geometry": {"coordinates":[8.839717865,53.6272697449],"type":"Point"}
}