{
  "type": "Feature",
  "properties": {
    "iso:country":"DE",
    "sg:address":"Haarenstr. 44",
    "sg:city":"Oldenburg",
    "sg:phone":"+49 441/2184420",
    "sg:postcode":"26122",
    "sg:province":"Niedersachsen",
    "wof:name":"Sch\u00fctte Gmbh & Co. Kg",
    "wof:placetype":"venue"
},
  "geometry": {"coordinates":[8.211412,53.140755],"type":"Point"}
}