{
  "type": "Feature",
  "properties": {
    "iso:country":"DE",
    "sg:address":"Parkstr. 8",
    "sg:city":"Gro\u00dftreben-Zwethau",
    "sg:postcode":"04886",
    "sg:province":"Sachsen",
    "wof:name":"Maschinenbau Handel Landtechnik Gmbh",
    "wof:placetype":"venue"
},
  "geometry": {"coordinates":[13.043471,51.579365],"type":"Point"}
}