{
  "type": "Feature",
  "properties": {
    "iso:country":"DE",
    "sg:address":"Lange Str. 57",
    "sg:city":"Grimma",
    "sg:phone":"+49 3437/917765",
    "sg:postcode":"04668",
    "sg:province":"Sachsen",
    "wof:name":"K. Thalheim",
    "wof:placetype":"venue"
},
  "geometry": {"coordinates":[12.728417,51.235886],"type":"Point"}
}