{
  "type": "Feature",
  "properties": {
    "iso:country":"DE",
    "sg:address":"Schrammsweg 25",
    "sg:city":"Hamburg",
    "sg:phone":"+49 40/484677",
    "sg:postcode":"20249",
    "sg:province":"Hamburg",
    "wof:name":"Ballons \u00fcber Hamburg Hei\u00dfluftballonfahrten Gmbh",
    "wof:placetype":"venue"
},
  "geometry": {"coordinates":[9.990309,53.590912],"type":"Point"}
}