{
  "type": "Feature",
  "properties": {
    "iso:country":"DE",
    "sg:address":"Unter Mengelbach 4",
    "sg:city":"Rimbach",
    "sg:phone":"+49 6207/1820",
    "sg:postcode":"64668",
    "sg:province":"Hessen",
    "wof:name":"Just For Fun Tours",
    "wof:placetype":"venue"
},
  "geometry": {"coordinates":[8.7878952026,49.5868453979],"type":"Point"}
}