{
  "type": "Feature",
  "properties": {
    "iso:country":"DE",
    "sg:address":"Schippelsweg 63f",
    "sg:city":"Hamburg",
    "sg:phone":"+49 40/5558610",
    "sg:postcode":"22455",
    "sg:province":"Hamburg",
    "wof:name":"Volker Mielke Steuerberater",
    "wof:placetype":"venue"
},
  "geometry": {"coordinates":[9.9532213211,53.6351699829],"type":"Point"}
}