{
  "type": "Feature",
  "properties": {
    "iso:country":"DE",
    "sg:address":"Kiesweg 6",
    "sg:city":"N\u00fcrtingen",
    "sg:phone":"+49 7022/61262",
    "sg:postcode":"72622",
    "sg:province":"Baden-W\u00fcrttemberg",
    "wof:name":"Anneliese Runge",
    "wof:placetype":"venue"
},
  "geometry": {"coordinates":[9.351933,48.639469],"type":"Point"}
}