{
  "type": "Feature",
  "properties": {
    "iso:country":"DE",
    "sg:address":"Hammerweg 23",
    "sg:city":"Dresden",
    "sg:postcode":"01127",
    "sg:province":"Sachsen",
    "wof:name":"Dresdner Abfallver- Wertungsges. Mbh",
    "wof:placetype":"venue"
},
  "geometry": {"coordinates":[13.742696,51.090034],"type":"Point"}
}