{
  "type": "Feature",
  "properties": {
    "iso:country":"DE",
    "sg:address":"Tratzigerstr. 21",
    "sg:city":"Hamburg",
    "sg:phone":"+49 40/6562842",
    "sg:postcode":"22043",
    "sg:province":"Hamburg",
    "wof:name":"Werner Lotterieeinnahme Kg",
    "wof:placetype":"venue"
},
  "geometry": {"coordinates":[10.086281,53.571693],"type":"Point"}
}