{
  "type": "Feature",
  "properties": {
    "iso:country":"DE",
    "sg:address":"Eichenkamp 49",
    "sg:city":"Hasbergen",
    "sg:phone":"+49 5405/2355",
    "sg:postcode":"49205",
    "sg:province":"Niedersachsen",
    "wof:name":"Albert Zietek Architekt",
    "wof:placetype":"venue"
},
  "geometry": {"coordinates":[7.953081,52.255783],"type":"Point"}
}