{
  "type": "Feature",
  "properties": {
    "iso:country":"DE",
    "sg:address":"Dorfstr. 9",
    "sg:city":"Buxtehude",
    "sg:postcode":"21614",
    "sg:province":"Niedersachsen",
    "wof:name":"Hedendorfer Agrarservice Gmbh",
    "wof:placetype":"venue"
},
  "geometry": {"coordinates":[9.618785,53.480167],"type":"Point"}
}