{
  "type": "Feature",
  "properties": {
    "iso:country":"DE",
    "sg:address":"Ohlauer Weg 9",
    "sg:city":"D\u00fcsseldorf",
    "sg:phone":"+49 211/279372",
    "sg:postcode":"40627",
    "sg:province":"Nordrhein-Westfalen",
    "wof:name":"F. Maassen",
    "wof:placetype":"venue"
},
  "geometry": {"coordinates":[6.850272,51.211571],"type":"Point"}
}