{
  "type": "Feature",
  "properties": {
    "iso:country":"DE",
    "sg:address":"Ballstr. 11",
    "sg:city":"Quedlinburg",
    "sg:phone":"+49 3946/3167",
    "sg:postcode":"06484",
    "sg:province":"Sachsen-Anhalt",
    "wof:name":"Rolf Ziegenbein",
    "wof:placetype":"venue"
},
  "geometry": {"coordinates":[11.150693,51.787727],"type":"Point"}
}