{
  "type": "Feature",
  "properties": {
    "iso:country":"DE",
    "sg:address":"August-Bebel-Str. 5",
    "sg:city":"Gera",
    "sg:phone":"+49 365/32082",
    "sg:postcode":"07551",
    "sg:province":"Th\u00fcringen",
    "wof:name":"Inixrent-autovermietung Domseifer Gmbh",
    "wof:placetype":"venue"
},
  "geometry": {"coordinates":[12.0859,50.848434],"type":"Point"}
}