{
  "type": "Feature",
  "properties": {
    "iso:country":"DE",
    "sg:address":"Selterser Str. 44",
    "sg:city":"Weilburg",
    "sg:phone":"+49 6471/7282",
    "sg:postcode":"35781",
    "sg:province":"Hessen",
    "wof:name":"Karl Maar Elektromeister",
    "wof:placetype":"venue"
},
  "geometry": {"coordinates":[8.271276,50.500538],"type":"Point"}
}