{
  "type": "Feature",
  "properties": {
    "iso:country":"DE",
    "sg:address":"Steiningergasse 10",
    "sg:city":"Passau",
    "sg:phone":"+49 851/33488",
    "sg:postcode":"94032",
    "sg:province":"Bayern",
    "wof:name":"Hans Schroth Architekt",
    "wof:placetype":"venue"
},
  "geometry": {"coordinates":[13.467116,48.574577],"type":"Point"}
}