{
  "type": "Feature",
  "properties": {
    "iso:country":"DE",
    "sg:address":"J\u00e4gersgrund 10",
    "sg:city":"Erndtebr\u00fcck",
    "sg:phone":"+49 2753/59450",
    "sg:postcode":"57339",
    "sg:province":"Nordrhein-Westfalen",
    "wof:name":"Rolf Kuhn Gmbh",
    "wof:placetype":"venue"
},
  "geometry": {"coordinates":[8.305994,50.994354],"type":"Point"}
}