{
  "type": "Feature",
  "properties": {
    "iso:country":"DE",
    "sg:address":"Dreichlingerstr. 2",
    "sg:city":"Neumarkt",
    "sg:phone":"+49 9181/6558",
    "sg:postcode":"92318",
    "sg:province":"Bayern",
    "wof:name":"Miele Center Ochsenk\u00fchn Gmbh",
    "wof:placetype":"venue"
},
  "geometry": {"coordinates":[11.452132225,49.2745018005],"type":"Point"}
}