{
  "type": "Feature",
  "properties": {
    "iso:country":"DE",
    "sg:address":"Wilhelmstr. 32",
    "sg:city":"Velten",
    "sg:postcode":"16727",
    "sg:province":"Brandenburg",
    "wof:name":"St\u00e4dtisches Heimat- Und Keramikmuseum",
    "wof:placetype":"venue"
},
  "geometry": {"coordinates":[13.17171,52.689133],"type":"Point"}
}