{
  "type": "Feature",
  "properties": {
    "iso:country":"DE",
    "sg:address":"Dorfstr.",
    "sg:city":"Sauen",
    "sg:phone":"+49 33672/231",
    "sg:postcode":"15848",
    "sg:province":"Brandenburg",
    "wof:name":"Agrarprodukte Sauen Eg",
    "wof:placetype":"venue"
},
  "geometry": {"coordinates":[14.1746101379,52.2288208008],"type":"Point"}
}