{
  "type": "Feature",
  "properties": {
    "iso:country":"DE",
    "sg:address":"Am K\u00f6ppel 31",
    "sg:city":"Breidenbach",
    "sg:phone":"+49 6465/4316",
    "sg:postcode":"35236",
    "sg:province":"Hessen",
    "wof:name":"Erich Papstein",
    "wof:placetype":"venue"
},
  "geometry": {"coordinates":[8.42226,50.900261],"type":"Point"}
}