{
  "type": "Feature",
  "properties": {
    "iso:country":"DE",
    "sg:address":"75392",
    "sg:city":"Deckenpfronn",
    "sg:phone":"+49 7056/3211",
    "sg:postcode":"75392",
    "sg:province":"Baden-W\u00fcrttemberg",
    "wof:name":"Gastst\u00e4tte Gemeindehalle",
    "wof:placetype":"venue"
},
  "geometry": {"coordinates":[8.8184700012,48.6495895386],"type":"Point"}
}