{
  "type": "Feature",
  "properties": {
    "iso:country":"DE",
    "sg:address":"Parkweg 5",
    "sg:city":"Ruhpolding",
    "sg:phone":"+49 8663/9271",
    "sg:postcode":"83324",
    "sg:province":"Bayern",
    "wof:name":"Beppo P\u00f6ttinger",
    "wof:placetype":"venue"
},
  "geometry": {"coordinates":[12.6551885605,47.7612800598],"type":"Point"}
}