{
  "type": "Feature",
  "properties": {
    "iso:country":"DE",
    "sg:address":"Adolfstr. 144",
    "sg:city":"Lahnstein",
    "sg:phone":"+49 2621/2873",
    "sg:postcode":"56112",
    "sg:province":"Rheinland-Pfalz",
    "wof:name":"Horst Wilhelm",
    "wof:placetype":"venue"
},
  "geometry": {"coordinates":[7.6018280983,50.3179855347],"type":"Point"}
}