{
  "type": "Feature",
  "properties": {
    "iso:country":"DE",
    "sg:address":"Erbsenrainweg 10",
    "sg:city":"Aschaffenburg",
    "sg:phone":"+49 6021/94666",
    "sg:postcode":"63743",
    "sg:province":"Bayern",
    "wof:name":"Leonhard Fertig & Sohn Gmbh",
    "wof:placetype":"venue"
},
  "geometry": {"coordinates":[9.1607208252,49.9555931091],"type":"Point"}
}