{
  "type": "Feature",
  "properties": {
    "iso:country":"DE",
    "sg:address":"Siemensstr. 34",
    "sg:city":"Haag",
    "sg:phone":"+49 8072/8572",
    "sg:postcode":"83527",
    "sg:province":"Bayern",
    "wof:name":"Franz X. Paul Ingenieur",
    "wof:placetype":"venue"
},
  "geometry": {"coordinates":[12.1715211868,48.1602516174],"type":"Point"}
}