{
  "type": "Feature",
  "properties": {
    "iso:country":"DE",
    "sg:address":"Am Jochartgraben 3",
    "sg:city":"Fischbachtal",
    "sg:phone":"+49 6166/8020",
    "sg:postcode":"64405",
    "sg:province":"Hessen",
    "wof:name":"Akw",
    "wof:placetype":"venue"
},
  "geometry": {"coordinates":[8.815451,49.772797],"type":"Point"}
}