{
  "type": "Feature",
  "properties": {
    "iso:country":"DE",
    "sg:address":"Dorfbauerschaft 102a",
    "sg:city":"Senden",
    "sg:phone":"+49 2597/8975",
    "sg:postcode":"48308",
    "sg:province":"Nordrhein-Westfalen",
    "wof:name":"Winfried Preusser",
    "wof:placetype":"venue"
},
  "geometry": {"coordinates":[7.511394,51.860218],"type":"Point"}
}