{
  "type": "Feature",
  "properties": {
    "iso:country":"DE",
    "sg:address":"Hubertusstr. 11",
    "sg:city":"Hohenbrunn",
    "sg:phone":"+49 8102/748889",
    "sg:postcode":"85662",
    "sg:province":"Bayern",
    "wof:name":"Silvia Kubiak-offergelt Rechtsanw\u00e4ltin",
    "wof:placetype":"venue"
},
  "geometry": {"coordinates":[11.7025470734,48.0516548157],"type":"Point"}
}