{
  "type": "Feature",
  "properties": {
    "iso:country":"DE",
    "sg:address":"Schulstr. 27",
    "sg:city":"S\u00f6rup",
    "sg:phone":"+49 4635/2546",
    "sg:postcode":"24966",
    "sg:province":"Schleswig-Holstein",
    "wof:name":"L. Hamann",
    "wof:placetype":"venue"
},
  "geometry": {"coordinates":[9.6552171707,54.7186393738],"type":"Point"}
}