{
  "type": "Feature",
  "properties": {
    "iso:country":"DE",
    "sg:address":"Marktplatz 4",
    "sg:city":"Esslingen",
    "sg:phone":"+49 711/354635",
    "sg:postcode":"73728",
    "sg:province":"Baden-W\u00fcrttemberg",
    "wof:name":"Weinstube \u00d6xle",
    "wof:placetype":"venue"
},
  "geometry": {"coordinates":[9.3053655624,48.7432823181],"type":"Point"}
}