{
  "type": "Feature",
  "properties": {
    "iso:country":"DE",
    "sg:address":"Lindenstr. 44",
    "sg:city":"Berga",
    "sg:phone":"+49 34651/53292",
    "sg:postcode":"06536",
    "sg:province":"Sachsen-Anhalt",
    "wof:name":"Steinemann",
    "wof:placetype":"venue"
},
  "geometry": {"coordinates":[11.004161,51.451969],"type":"Point"}
}