{
  "type": "Feature",
  "properties": {
    "iso:country":"DE",
    "sg:address":"D\u00fcsseldorfer Landstr. 294",
    "sg:city":"Duisburg",
    "sg:phone":"+49 203/751502",
    "sg:postcode":"47259",
    "sg:province":"Nordrhein-Westfalen",
    "wof:name":"Aqudreams",
    "wof:placetype":"venue"
},
  "geometry": {"coordinates":[6.7473797798,51.3602218628],"type":"Point"}
}