{
  "type": "Feature",
  "properties": {
    "iso:country":"DE",
    "sg:address":"Am Graben 7",
    "sg:city":"Neubulach",
    "sg:phone":"+49 7053/7844",
    "sg:postcode":"75387",
    "sg:province":"Baden-W\u00fcrttemberg",
    "wof:name":"Ruth Berner Hebamme",
    "wof:placetype":"venue"
},
  "geometry": {"coordinates":[8.676057,48.67305],"type":"Point"}
}