{
  "type": "Feature",
  "properties": {
    "iso:country":"DE",
    "sg:address":"Breidensteiner Str. 20",
    "sg:city":"Neuh\u00fctten",
    "sg:phone":"+49 6020/97320",
    "sg:postcode":"97843",
    "sg:province":"Bayern",
    "wof:name":"Franz Kunkel Gmbh",
    "wof:placetype":"venue"
},
  "geometry": {"coordinates":[9.41791,50.004639],"type":"Point"}
}