{
  "type": "Feature",
  "properties": {
    "iso:country":"DE",
    "sg:address":"Laufamholzstr. 49",
    "sg:city":"N\u00fcrnberg",
    "sg:phone":"+49 911/5441490",
    "sg:postcode":"90482",
    "sg:province":"Bayern",
    "wof:name":"Gerda Schlegl",
    "wof:placetype":"venue"
},
  "geometry": {"coordinates":[11.1373586655,49.4620628357],"type":"Point"}
}