{
  "type": "Feature",
  "properties": {
    "iso:country":"DE",
    "sg:address":"Stadtweg 22",
    "sg:city":"Borchen",
    "sg:phone":"+49 5251/38079",
    "sg:postcode":"33178",
    "sg:province":"Nordrhein-Westfalen",
    "wof:name":"Innova Werbe- Und Verlagsagentur Gmbh",
    "wof:placetype":"venue"
},
  "geometry": {"coordinates":[8.7293348312,51.6626358032],"type":"Point"}
}