{
  "type": "Feature",
  "properties": {
    "iso:country":"DE",
    "sg:address":"Erolzheim",
    "sg:city":"Erolzheim",
    "sg:phone":"+49 7354/1085",
    "sg:postcode":"88453",
    "sg:province":"Baden-W\u00fcrttemberg",
    "wof:name":"Raiffeisenbank Kirchberg Eg",
    "wof:placetype":"venue"
},
  "geometry": {"coordinates":[10.074075,48.09119],"type":"Point"}
}