{
  "type": "Feature",
  "properties": {
    "iso:country":"DE",
    "sg:address":"Vor dem Haveltor 1",
    "sg:city":"Rathenow",
    "sg:phone":"+49 3385/515758",
    "sg:postcode":"14712",
    "sg:province":"Brandenburg",
    "wof:name":"Haveltor Rathenow",
    "wof:placetype":"venue"
},
  "geometry": {"coordinates":[12.329382,52.608284],"type":"Point"}
}