{
  "type": "Feature",
  "properties": {
    "iso:country":"DE",
    "sg:address":"Weingartstr. 21",
    "sg:city":"Denkendorf",
    "sg:phone":"+49 711/3461719",
    "sg:postcode":"73770",
    "sg:province":"Baden-W\u00fcrttemberg",
    "wof:name":"N. Und F. Renz",
    "wof:placetype":"venue"
},
  "geometry": {"coordinates":[9.312281,48.696213],"type":"Point"}
}