{
  "type": "Feature",
  "properties": {
    "iso:country":"DE",
    "sg:address":"Marktstr. 12",
    "sg:city":"Berlin",
    "sg:phone":"+49 30/4558151",
    "sg:postcode":"10317",
    "sg:province":"Berlin",
    "wof:name":"Pup-virginia",
    "wof:placetype":"venue"
},
  "geometry": {"coordinates":[13.4722213745,52.5038642883],"type":"Point"}
}