{
  "type": "Feature",
  "properties": {
    "iso:country":"DE",
    "sg:address":"Heidestr. 42",
    "sg:city":"Boppard",
    "sg:phone":"+49 6742/921414",
    "sg:postcode":"56154",
    "sg:province":"Rheinland-Pfalz",
    "wof:name":"Ariane Schampera-edelmann Ergotherapiepraxis",
    "wof:placetype":"venue"
},
  "geometry": {"coordinates":[7.53549,50.211132],"type":"Point"}
}