{
  "type": "Feature",
  "properties": {
    "iso:country":"DE",
    "sg:address":"Brandenburger Platz 56",
    "sg:city":"Cottbus",
    "sg:phone":"+49 355/791152",
    "sg:postcode":"03046",
    "sg:province":"Brandenburg",
    "wof:name":"Klaus-dieter Bl\u00fcthner Steuerbevollm\u00e4chtigter",
    "wof:placetype":"venue"
},
  "geometry": {"coordinates":[14.3348722458,51.7577056885],"type":"Point"}
}