{
  "type": "Feature",
  "properties": {
    "iso:country":"DE",
    "sg:address":"Jahnstr. 10",
    "sg:city":"Hilgertshausen-Tandern",
    "sg:phone":"+49 8250/1818",
    "sg:postcode":"86567",
    "sg:province":"Bayern",
    "wof:name":"La Puglia",
    "wof:placetype":"venue"
},
  "geometry": {"coordinates":[11.2979211807,48.42603302],"type":"Point"}
}