{
  "type": "Feature",
  "properties": {
    "iso:country":"DE",
    "sg:address":"Vogt-Sanmann-Weg 8",
    "sg:city":"Gro\u00dfhansdorf",
    "sg:phone":"+49 4102/62821",
    "sg:postcode":"22927",
    "sg:province":"Schleswig-Holstein",
    "wof:name":"Ev. Pfarramt Grosshansdorf",
    "wof:placetype":"venue"
},
  "geometry": {"coordinates":[10.2801351547,53.6671943665],"type":"Point"}
}