{
  "type": "Feature",
  "properties": {
    "iso:country":"DE",
    "sg:address":"Z\u00fcttlinger Str. 3",
    "sg:city":"M\u00f6ckm\u00fchl",
    "sg:postcode":"74219",
    "sg:province":"Baden-W\u00fcrttemberg",
    "wof:name":"Tankstelle Josef Nietsch Shop Waschanlage Und",
    "wof:placetype":"venue"
},
  "geometry": {"coordinates":[9.364,49.321953],"type":"Point"}
}