{
  "type": "Feature",
  "properties": {
    "iso:country":"DE",
    "sg:address":"Mainzer Str. 38-38a",
    "sg:city":"Wiesbaden",
    "sg:phone":"+49 611/376621",
    "sg:postcode":"65185",
    "sg:province":"Hessen",
    "wof:name":"Iota Kontaktlinsen Gmbh",
    "wof:placetype":"venue"
},
  "geometry": {"coordinates":[8.248384,50.07568],"type":"Point"}
}