{
  "type": "Feature",
  "properties": {
    "iso:country":"DE",
    "sg:address":"Gerberstr. 132",
    "sg:city":"Viersen",
    "sg:phone":"+49 2162/31839",
    "sg:postcode":"41748",
    "sg:province":"Nordrhein-Westfalen",
    "wof:name":"Dekra",
    "wof:placetype":"venue"
},
  "geometry": {"coordinates":[6.4077401161,51.2642288208],"type":"Point"}
}