{
  "type": "Feature",
  "properties": {
    "iso:country":"DE",
    "sg:address":"Hinrichsdorfer Str.",
    "sg:city":"Rostock",
    "sg:postcode":"18146",
    "sg:province":"Mecklenburg-Vorpommern",
    "wof:name":"M. Gottwald",
    "wof:placetype":"venue"
},
  "geometry": {"coordinates":[12.16593,54.124565],"type":"Point"}
}