{
  "type": "Feature",
  "properties": {
    "iso:country":"DE",
    "sg:address":"Gutenbergstr. 10",
    "sg:city":"Hechingen",
    "sg:phone":"+49 7471/622331",
    "sg:postcode":"72379",
    "sg:province":"Baden-W\u00fcrttemberg",
    "wof:name":"Naturheilpraxis Spranger, 72379 Hechingen",
    "wof:placetype":"venue"
},
  "geometry": {"coordinates":[8.9646196365,48.3522262573],"type":"Point"}
}