{
  "type": "Feature",
  "properties": {
    "iso:country":"DE",
    "sg:address":"Neust\u00e4dter Str. 21",
    "sg:city":"H\u00fcnfeld",
    "sg:phone":"+49 6652/6480",
    "sg:postcode":"36088",
    "sg:province":"Hessen",
    "wof:name":"Kolibri",
    "wof:placetype":"venue"
},
  "geometry": {"coordinates":[9.767704,50.670662],"type":"Point"}
}