{
  "type": "Feature",
  "properties": {
    "iso:country":"DE",
    "sg:address":"Vennstr. 25",
    "sg:city":"Waldbr\u00f6l",
    "sg:phone":"+49 2291/4219",
    "sg:postcode":"51545",
    "sg:province":"Nordrhein-Westfalen",
    "wof:name":"Otto Sohnius Antiquit\u00e4ten",
    "wof:placetype":"venue"
},
  "geometry": {"coordinates":[7.610929,50.875755],"type":"Point"}
}