{
  "type": "Feature",
  "properties": {
    "iso:country":"DE",
    "sg:address":"Irmgardstr. 10",
    "sg:city":"D\u00fcsseldorf",
    "sg:phone":"+49 211/681012",
    "sg:postcode":"40235",
    "sg:province":"Nordrhein-Westfalen",
    "wof:name":"Kath. \u00f6ffentliche Bibliothek St. Ursula",
    "wof:placetype":"venue"
},
  "geometry": {"coordinates":[6.826541,51.24036],"type":"Point"}
}