{
  "type": "Feature",
  "properties": {
    "iso:country":"DE",
    "sg:address":"Schmidlgasse 3",
    "sg:city":"Straubing",
    "sg:phone":"+49 9421/831266",
    "sg:postcode":"94315",
    "sg:province":"Bayern",
    "wof:name":"Pilspub Fortuna",
    "wof:placetype":"venue"
},
  "geometry": {"coordinates":[12.5663232803,48.8807754517],"type":"Point"}
}