{
  "type": "Feature",
  "properties": {
    "iso:country":"DE",
    "sg:address":"Mehlsstr. 48",
    "sg:city":"Westhausen",
    "sg:phone":"+49 3606/601917",
    "sg:postcode":"37308",
    "sg:province":"Th\u00fcringen",
    "wof:name":"Arnold Schmerbauch",
    "wof:placetype":"venue"
},
  "geometry": {"coordinates":[10.194532,51.394432],"type":"Point"}
}