{
  "type": "Feature",
  "properties": {
    "iso:country":"DE",
    "sg:address":"Steinweg",
    "sg:city":"Br\u00fchl",
    "sg:phone":"+49 2232/68257",
    "sg:postcode":"50321",
    "sg:province":"Nordrhein-Westfalen",
    "wof:name":"Volksbank Br\u00fchl Eg",
    "wof:placetype":"venue"
},
  "geometry": {"coordinates":[6.903275,50.828159],"type":"Point"}
}