{
  "type": "Feature",
  "properties": {
    "iso:country":"DE",
    "sg:address":"K\u00f6nigstr. 114",
    "sg:city":"Krefeld",
    "sg:phone":"+49 2151/818990",
    "sg:postcode":"47798",
    "sg:province":"Nordrhein-Westfalen",
    "wof:name":"Industrie-reisedienst Gmbh",
    "wof:placetype":"venue"
},
  "geometry": {"coordinates":[6.563806057,51.3322792053],"type":"Point"}
}