{
  "type": "Feature",
  "properties": {
    "iso:country":"DE",
    "sg:address":"Hohenstaufenrg. 47-51",
    "sg:city":"K\u00f6ln",
    "sg:phone":"+49 4922/1211550",
    "sg:postcode":"50674",
    "sg:province":"Nordrhein-Westfalen",
    "wof:name":"Gleumes & Co Kg",
    "wof:placetype":"venue"
},
  "geometry": {"coordinates":[6.9397988319,50.932434082],"type":"Point"}
}