{
  "type": "Feature",
  "properties": {
    "iso:country":"DE",
    "sg:address":"Wundtstr. 38",
    "sg:city":"Berlin",
    "sg:phone":"+49 30/32102844",
    "sg:postcode":"14057",
    "sg:province":"Berlin",
    "wof:name":"Linda F. Mayes Dolmetscherin \u00dcbersetzerin",
    "wof:placetype":"venue"
},
  "geometry": {"coordinates":[13.288801,52.50935],"type":"Point"}
}