{
  "type": "Feature",
  "properties": {
    "iso:country":"DE",
    "sg:address":"Druxberger Weg 3-5",
    "sg:city":"Magdeburg",
    "sg:phone":"+49 391",
    "sg:postcode":"39110",
    "sg:province":"Sachsen-Anhalt",
    "wof:name":"Cbos B\u00fcrosysteme Gmbh",
    "wof:placetype":"venue"
},
  "geometry": {"coordinates":[11.5717630386,52.1179084778],"type":"Point"}
}