{
  "type": "Feature",
  "properties": {
    "iso:country":"DE",
    "sg:address":"Gernsbacher Str. 5",
    "sg:city":"Bad Herrenalb",
    "sg:phone":"+49 7083/2415",
    "sg:postcode":"76332",
    "sg:province":"Baden-W\u00fcrttemberg",
    "wof:name":"W\u00fcrttembergische Versicherung Wolfram M\u00f6hrmann",
    "wof:placetype":"venue"
},
  "geometry": {"coordinates":[8.4354295731,48.7969055176],"type":"Point"}
}