{
  "type": "Feature",
  "properties": {
    "iso:country":"DE",
    "sg:address":"Zur Aumundswiese 3-3a",
    "sg:city":"Bremen",
    "sg:phone":"+49 421/826312",
    "sg:postcode":"28279",
    "sg:province":"Bremen",
    "wof:name":"R. N\u00fcrnberg Gmbh",
    "wof:placetype":"venue"
},
  "geometry": {"coordinates":[8.8617086411,53.0244903564],"type":"Point"}
}