{
  "type": "Feature",
  "properties": {
    "iso:country":"DE",
    "sg:address":"Casparistr. 6",
    "sg:city":"Arnsberg",
    "sg:phone":"+49 2931/13108",
    "sg:postcode":"59823",
    "sg:province":"Nordrhein-Westfalen",
    "wof:name":"Hermann Br\u00fcggemann",
    "wof:placetype":"venue"
},
  "geometry": {"coordinates":[8.0912513733,51.3983955383],"type":"Point"}
}