{
  "type": "Feature",
  "properties": {
    "iso:country":"DE",
    "sg:address":"Altheimer Str. 43",
    "sg:city":"Horb",
    "sg:phone":"+49 7451/2557",
    "sg:postcode":"72160",
    "sg:province":"Baden-W\u00fcrttemberg",
    "wof:name":"Restaurant Germania",
    "wof:placetype":"venue"
},
  "geometry": {"coordinates":[8.6872005463,48.4458312988],"type":"Point"}
}