{
  "type": "Feature",
  "properties": {
    "iso:country":"DE",
    "sg:address":"Egertenweg 10",
    "sg:city":"Steinen",
    "sg:phone":"+49 7627/8831",
    "sg:postcode":"79585",
    "sg:province":"Baden-W\u00fcrttemberg",
    "wof:name":"Jassen Kunststoffzentrum",
    "wof:placetype":"venue"
},
  "geometry": {"coordinates":[7.733405,47.640404],"type":"Point"}
}