{
  "type": "Feature",
  "properties": {
    "iso:country":"DE",
    "sg:address":"Nordring 107",
    "sg:city":"N\u00fcrnberg",
    "sg:phone":"+49 911/359928",
    "sg:postcode":"90409",
    "sg:province":"Bayern",
    "wof:name":"W. K\u00fchnel",
    "wof:placetype":"venue"
},
  "geometry": {"coordinates":[11.086699,49.470055],"type":"Point"}
}