{
  "type": "Feature",
  "properties": {
    "iso:country":"DE",
    "sg:address":"Innsbrucker Str. 18",
    "sg:city":"Freiburg",
    "sg:phone":"+49 761/4763223",
    "sg:postcode":"79111",
    "sg:province":"Baden-W\u00fcrttemberg",
    "wof:name":"Chinafreunde",
    "wof:placetype":"venue"
},
  "geometry": {"coordinates":[7.815612,47.974041],"type":"Point"}
}