{
  "type": "Feature",
  "properties": {
    "iso:country":"DE",
    "sg:address":"Bergweg 8",
    "sg:city":"Kiefersfelden",
    "sg:phone":"+49 8033/1310",
    "sg:postcode":"83088",
    "sg:province":"Bayern",
    "wof:name":"Tiroler Weinstubn",
    "wof:placetype":"venue"
},
  "geometry": {"coordinates":[12.1695356369,47.6386756897],"type":"Point"}
}