{
  "type": "Feature",
  "properties": {
    "iso:country":"DE",
    "sg:address":"kantstr 83",
    "sg:city":"berlin",
    "sg:phone":"+49 32/301791",
    "sg:postcode":"60100",
    "sg:province":"Berlin",
    "wof:name":"Rentabild",
    "wof:placetype":"venue"
},
  "geometry": {"coordinates":[13.296601,52.507004],"type":"Point"}
}