{
  "type": "Feature",
  "properties": {
    "iso:country":"DE",
    "sg:address":"Am T\u00fcrleberg 12",
    "sg:city":"Ellingen",
    "sg:postcode":"91792",
    "sg:province":"Bayern",
    "wof:name":"Adlatus Vorsorge & Investment Gmbh",
    "wof:placetype":"venue"
},
  "geometry": {"coordinates":[10.9731349945,49.0594558716],"type":"Point"}
}