{
  "type": "Feature",
  "properties": {
    "iso:country":"DE",
    "sg:address":"B\u00f6tzower Landstr.",
    "sg:city":"Sch\u00f6nwalde",
    "sg:postcode":"14621",
    "sg:province":"Brandenburg",
    "wof:name":"Pro Baustoffe E. K.",
    "wof:placetype":"venue"
},
  "geometry": {"coordinates":[13.1304445267,52.619846344],"type":"Point"}
}