{
  "type": "Feature",
  "properties": {
    "iso:country":"DE",
    "sg:address":"Rudolf-Breitscheid-Str. 20",
    "sg:city":"Kahla",
    "sg:phone":"+49 36424/51735",
    "sg:postcode":"07768",
    "sg:province":"Th\u00fcringen",
    "wof:name":"Ilona Curth",
    "wof:placetype":"venue"
},
  "geometry": {"coordinates":[11.5889911652,50.8032302856],"type":"Point"}
}