{
  "type": "Feature",
  "properties": {
    "iso:country":"DE",
    "sg:address":"St.-Ingberter-Str. 28",
    "sg:city":"Spiesen-Elversberg",
    "sg:phone":"+49 6821/730111",
    "sg:postcode":"66583",
    "sg:province":"Saarland",
    "wof:name":"Alfons Graf Rechtsanwalt",
    "wof:placetype":"venue"
},
  "geometry": {"coordinates":[7.1240200996,49.3088417053],"type":"Point"}
}