{
  "type": "Feature",
  "properties": {
    "iso:country":"DE",
    "sg:address":"Bahnstr. 66",
    "sg:city":"Willich",
    "sg:phone":"+49 2154/429875",
    "sg:postcode":"47877",
    "sg:province":"Nordrhein-Westfalen",
    "wof:name":"Cornelia Wielgosch",
    "wof:placetype":"venue"
},
  "geometry": {"coordinates":[6.5403299332,51.2673072815],"type":"Point"}
}