{
  "type": "Feature",
  "properties": {
    "iso:country":"DE",
    "sg:address":"Dolomitstr. 15",
    "sg:city":"Bad Lauterberg",
    "sg:phone":"+49 5521/5014",
    "sg:postcode":"37431",
    "sg:province":"Niedersachsen",
    "wof:name":"Johannes Brehm",
    "wof:placetype":"venue"
},
  "geometry": {"coordinates":[10.4053030014,51.6204566956],"type":"Point"}
}