{
  "type": "Feature",
  "properties": {
    "iso:country":"DE",
    "sg:address":"Br\u00f6nninghauser Str. 40a",
    "sg:city":"Bielefeld",
    "sg:phone":"+49 521/391290",
    "sg:postcode":"33729",
    "sg:province":"Nordrhein-Westfalen",
    "wof:name":"Rudolf Schiche",
    "wof:placetype":"venue"
},
  "geometry": {"coordinates":[8.63549,52.045311],"type":"Point"}
}