{
  "type": "Feature",
  "properties": {
    "iso:country":"DE",
    "sg:address":"Birkenstr. 4",
    "sg:city":"Baierbrunn",
    "sg:phone":"+49 89/7930699",
    "sg:postcode":"82065",
    "sg:province":"Bayern",
    "wof:name":"Dr. Friedrich Kohl Ingenieur",
    "wof:placetype":"venue"
},
  "geometry": {"coordinates":[11.4932527542,48.0306854248],"type":"Point"}
}