{
  "type": "Feature",
  "properties": {
    "iso:country":"DE",
    "sg:address":"Hallerh\u00fcttenstr. 4",
    "sg:city":"N\u00fcrnberg",
    "sg:phone":"+49 911/473564",
    "sg:postcode":"90461",
    "sg:province":"Bayern",
    "wof:name":"Rafael Ostojic",
    "wof:placetype":"venue"
},
  "geometry": {"coordinates":[11.100899,49.44138],"type":"Point"}
}