{
  "type": "Feature",
  "properties": {
    "iso:country":"DE",
    "sg:address":"J\u00fclicher Str. 20",
    "sg:city":"Berlin",
    "sg:phone":"+49 30/4941548",
    "sg:postcode":"13357",
    "sg:province":"Berlin",
    "wof:name":"Wolfgang Grunewald Steuerberater",
    "wof:placetype":"venue"
},
  "geometry": {"coordinates":[13.3920049667,52.5527153015],"type":"Point"}
}