{
  "type": "Feature",
  "properties": {
    "iso:country":"DE",
    "sg:address":"Daiserstr. 6",
    "sg:city":"M\u00fcnchen",
    "sg:phone":"+49 89/7211163",
    "sg:postcode":"81371",
    "sg:province":"Bayern",
    "wof:name":"Hebensperger H\u00fcther Und R\u00f6ttig Architekten",
    "wof:placetype":"venue"
},
  "geometry": {"coordinates":[11.543807,48.121315],"type":"Point"}
}