{
  "type": "Feature",
  "properties": {
    "iso:country":"DE",
    "sg:address":"Grabowstr. 16",
    "sg:city":"Prenzlau",
    "sg:phone":"+49 3984/808775",
    "sg:postcode":"17291",
    "sg:province":"Brandenburg",
    "wof:name":"J. Labeau",
    "wof:placetype":"venue"
},
  "geometry": {"coordinates":[13.8668050766,53.312625885],"type":"Point"}
}