{
  "type": "Feature",
  "properties": {
    "iso:country":"DE",
    "sg:address":"Klingenthaler Str. 24 b",
    "sg:city":"Zwota",
    "sg:phone":"+49 37467/26135",
    "sg:postcode":"08267",
    "sg:province":"Sachsen",
    "wof:name":"Bernd Zimmermann",
    "wof:placetype":"venue"
},
  "geometry": {"coordinates":[12.4417438507,50.3564987183],"type":"Point"}
}