{
  "type": "Feature",
  "properties": {
    "iso:country":"DE",
    "sg:address":"Schulstr. 42",
    "sg:city":"Herne",
    "sg:phone":"+49 2323/13298",
    "sg:postcode":"44623",
    "sg:province":"Nordrhein-Westfalen",
    "wof:name":"Generalagentur R. Mic",
    "wof:placetype":"venue"
},
  "geometry": {"coordinates":[7.2243261337,51.5419654846],"type":"Point"}
}