{
  "type": "Feature",
  "properties": {
    "iso:country":"DE",
    "sg:address":"Ludwigstr. 37",
    "sg:city":"Kaufbeuren",
    "sg:phone":"+49 8341/40980",
    "sg:postcode":"87600",
    "sg:province":"Bayern",
    "wof:name":"K\u00e4sestube",
    "wof:placetype":"venue"
},
  "geometry": {"coordinates":[10.6205301285,47.8785552979],"type":"Point"}
}