{
  "type": "Feature",
  "properties": {
    "iso:country":"DE",
    "sg:address":"Feldmochinger Str. 83",
    "sg:city":"M\u00fcnchen",
    "sg:phone":"+49 89/1407382",
    "sg:postcode":"80993",
    "sg:province":"Bayern",
    "wof:name":"Max Wei\u00dfenberger",
    "wof:placetype":"venue"
},
  "geometry": {"coordinates":[11.518084,48.189857],"type":"Point"}
}