{
  "type": "Feature",
  "properties": {
    "iso:country":"DE",
    "sg:address":"D\u00fcrriweg 45",
    "sg:city":"Efringen-Kirchen",
    "sg:phone":"+49 7628/1750",
    "sg:postcode":"79588",
    "sg:province":"Baden-W\u00fcrttemberg",
    "wof:name":"S. Kamm\u00fcller",
    "wof:placetype":"venue"
},
  "geometry": {"coordinates":[7.6017990112,47.6813392639],"type":"Point"}
}