{
  "type": "Feature",
  "properties": {
    "iso:country":"DE",
    "sg:address":"Wendelsteinstr.",
    "sg:city":"Gr\u00fcnwald",
    "sg:postcode":"82031",
    "sg:province":"Bayern",
    "wof:name":"Erich Lettl Gmbh",
    "wof:placetype":"venue"
},
  "geometry": {"coordinates":[11.5214729309,48.0332717896],"type":"Point"}
}