{
  "type": "Feature",
  "properties": {
    "iso:country":"DE",
    "sg:address":"H\u00fcwel 15",
    "sg:city":"\u00dcrzig",
    "sg:phone":"+49 6532/2133",
    "sg:postcode":"54539",
    "sg:province":"Rheinland-Pfalz",
    "wof:name":"Carl Berres Gessinger Gmbh",
    "wof:placetype":"venue"
},
  "geometry": {"coordinates":[7.0036377907,49.9762535095],"type":"Point"}
}