{
  "type": "Feature",
  "properties": {
    "iso:country":"DE",
    "sg:address":"Storchengasse 2",
    "sg:city":"Bad Neustadt",
    "sg:phone":"+49 9771/7878",
    "sg:postcode":"97616",
    "sg:province":"Bayern",
    "wof:name":"Storchennest",
    "wof:placetype":"venue"
},
  "geometry": {"coordinates":[10.2148742676,50.3225708008],"type":"Point"}
}