{
  "type": "Feature",
  "properties": {
    "iso:country":"DE",
    "sg:address":"Schulstr. 6",
    "sg:city":"Bruchsal",
    "sg:phone":"+49 7257/4572",
    "sg:postcode":"76646",
    "sg:province":"Baden-W\u00fcrttemberg",
    "wof:name":"Hotel-restaurant Weisses Lamm",
    "wof:placetype":"venue"
},
  "geometry": {"coordinates":[8.5542621613,49.0849952698],"type":"Point"}
}