{
  "type": "Feature",
  "properties": {
    "iso:country":"DE",
    "sg:address":"Weiherhalde 1",
    "sg:city":"Ingoldingen",
    "sg:phone":"+49 7355/2352",
    "sg:postcode":"88456",
    "sg:province":"Baden-W\u00fcrttemberg",
    "wof:name":"Erwin M\u00fcller",
    "wof:placetype":"venue"
},
  "geometry": {"coordinates":[9.733455,48.004467],"type":"Point"}
}