{
  "type": "Feature",
  "properties": {
    "iso:country":"DE",
    "sg:address":"Hansestr. 1",
    "sg:city":"Bielefeld",
    "sg:phone":"+49 5205/6537",
    "sg:postcode":"33689",
    "sg:province":"Nordrhein-Westfalen",
    "wof:name":"M. Hollmann",
    "wof:placetype":"venue"
},
  "geometry": {"coordinates":[8.570967,51.950836],"type":"Point"}
}