{
  "type": "Feature",
  "properties": {
    "iso:country":"DE",
    "sg:address":"Dorfstr. 12",
    "sg:city":"Kusterdingen",
    "sg:phone":"+49 7071/31004",
    "sg:postcode":"72127",
    "sg:province":"Baden-W\u00fcrttemberg",
    "wof:name":"Gerhard Grauer",
    "wof:placetype":"venue"
},
  "geometry": {"coordinates":[9.126912117,48.5013847351],"type":"Point"}
}