{
  "type": "Feature",
  "properties": {
    "iso:country":"DE",
    "sg:address":"M\u00fcllerstr. 30",
    "sg:city":"Peiting",
    "sg:phone":"+49 8861/69645",
    "sg:postcode":"86971",
    "sg:province":"Bayern",
    "wof:name":"Josef A. Sepp",
    "wof:placetype":"venue"
},
  "geometry": {"coordinates":[10.926266,47.800308],"type":"Point"}
}