{
  "type": "Feature",
  "properties": {
    "iso:country":"DE",
    "sg:address":"Frohnauer Str. 106",
    "sg:city":"Berlin",
    "sg:phone":"+49 30/4048806",
    "sg:postcode":"13465",
    "sg:province":"Berlin",
    "wof:name":"Restaurant Sounion",
    "wof:placetype":"venue"
},
  "geometry": {"coordinates":[13.2915687561,52.6259422302],"type":"Point"}
}