{
  "type": "Feature",
  "properties": {
    "iso:country":"DE",
    "sg:address":"Sch\u00fcrmannshofstr. 13",
    "sg:city":"Kamp-Lintfort",
    "sg:phone":"+49 2842/10618",
    "sg:postcode":"47475",
    "sg:province":"Nordrhein-Westfalen",
    "wof:name":"Walter Dammert Fernsehen",
    "wof:placetype":"venue"
},
  "geometry": {"coordinates":[6.5682139397,51.4978485107],"type":"Point"}
}