{
  "type": "Feature",
  "properties": {
    "iso:country":"DE",
    "sg:address":"Birkenhof",
    "sg:city":"Herbstein",
    "sg:phone":"+49 6643/501",
    "sg:postcode":"36358",
    "sg:province":"Hessen",
    "wof:name":"Manfred Lipp",
    "wof:placetype":"venue"
},
  "geometry": {"coordinates":[9.308722,50.546253],"type":"Point"}
}