{
  "type": "Feature",
  "properties": {
    "iso:country":"DE",
    "sg:address":"Kegelhofstr. 57-59",
    "sg:city":"Hamburg",
    "sg:postcode":"20251",
    "sg:province":"Hamburg",
    "wof:name":"Verwaltungsges. B & G Flugzeugcharter Mbh",
    "wof:placetype":"venue"
},
  "geometry": {"coordinates":[9.977478,53.594963],"type":"Point"}
}