{
  "type": "Feature",
  "properties": {
    "iso:country":"DE",
    "sg:address":"Alte Zollstr. 24",
    "sg:city":"Wedemark",
    "sg:phone":"+49 5072/221",
    "sg:postcode":"30900",
    "sg:province":"Niedersachsen",
    "wof:name":"Hans-joachim Naumann",
    "wof:placetype":"venue"
},
  "geometry": {"coordinates":[9.620495,52.567047],"type":"Point"}
}