{
  "type": "Feature",
  "properties": {
    "iso:country":"DE",
    "sg:address":"Berliner Tor 27",
    "sg:city":"Angerm\u00fcnde",
    "sg:phone":"+49 3331/23511",
    "sg:postcode":"16278",
    "sg:province":"Brandenburg",
    "wof:name":"Fliesen- Und Baustoffcenter H\u00fctteroth Gmbh & Co. Kg",
    "wof:placetype":"venue"
},
  "geometry": {"coordinates":[13.9787387848,52.9902687073],"type":"Point"}
}