{
  "type": "Feature",
  "properties": {
    "iso:country":"DE",
    "sg:address":"Theaterwall 30",
    "sg:city":"Oldenburg",
    "sg:phone":"+49 441/924910",
    "sg:postcode":"26122",
    "sg:province":"Niedersachsen",
    "wof:name":"Iduna Nova",
    "wof:placetype":"venue"
},
  "geometry": {"coordinates":[8.2098560333,53.1399002075],"type":"Point"}
}