{
  "type": "Feature",
  "properties": {
    "iso:country":"DE",
    "sg:address":"Bodelschwinghstr. 104",
    "sg:city":"Krefeld",
    "sg:phone":"+49 2151/593184",
    "sg:postcode":"47800",
    "sg:province":"Nordrhein-Westfalen",
    "wof:name":"Heiner R\u00fctten Ingenieur",
    "wof:placetype":"venue"
},
  "geometry": {"coordinates":[6.624297142,51.3497390747],"type":"Point"}
}