{
  "type": "Feature",
  "properties": {
    "iso:country":"DE",
    "sg:address":"Gewerbestr. 5",
    "sg:city":"Heiligenhafen",
    "sg:postcode":"23774",
    "sg:province":"Schleswig-Holstein",
    "wof:name":"Compakt Gmbh",
    "wof:placetype":"venue"
},
  "geometry": {"coordinates":[11.0059537888,54.3644485474],"type":"Point"}
}