{
  "type": "Feature",
  "properties": {
    "iso:country":"DE",
    "sg:address":"Bahnhofstr. 2",
    "sg:city":"Muhr",
    "sg:phone":"+49 9831/7041",
    "sg:postcode":"91735",
    "sg:province":"Bayern",
    "wof:name":"Raiffeisenbank Altm\u00fchlsee Eg",
    "wof:placetype":"venue"
},
  "geometry": {"coordinates":[10.711892,49.155083],"type":"Point"}
}