{
  "type": "Feature",
  "properties": {
    "iso:country":"DE",
    "sg:address":"Keltenstr 12",
    "sg:city":"Bruchk\u00f6bel",
    "sg:phone":"+49 6181/976320",
    "sg:postcode":"63486",
    "sg:province":"Hessen",
    "wof:name":"Unitherm Messtechnik Gmbh",
    "wof:placetype":"venue"
},
  "geometry": {"coordinates":[8.90972,50.177258],"type":"Point"}
}