{
  "type": "Feature",
  "properties": {
    "iso:country":"DE",
    "sg:address":"Schmalzberg 6",
    "sg:city":"Talheim",
    "sg:phone":"+49 7133/974540",
    "sg:postcode":"74388",
    "sg:province":"Baden-W\u00fcrttemberg",
    "wof:name":"Hohn Kunststoff- Verarbeitung Gmbh",
    "wof:placetype":"venue"
},
  "geometry": {"coordinates":[9.1884737015,49.0964393616],"type":"Point"}
}