{
  "type": "Feature",
  "properties": {
    "iso:country":"DE",
    "sg:address":"Schillerplatz 16",
    "sg:city":"Mainz",
    "sg:phone":"+49 6131/222438",
    "sg:postcode":"55116",
    "sg:province":"Rheinland-Pfalz",
    "wof:name":"Optik Lehr",
    "wof:placetype":"venue"
},
  "geometry": {"coordinates":[8.2674875259,49.9986343384],"type":"Point"}
}