{
  "type": "Feature",
  "properties": {
    "iso:country":"DE",
    "sg:address":"Stuttgarter Str. 103",
    "sg:city":"Stuttgart",
    "sg:phone":"+49 711/817275",
    "sg:postcode":"70469",
    "sg:province":"Baden-W\u00fcrttemberg",
    "wof:name":"Optik Schuppin Gmbh",
    "wof:placetype":"venue"
},
  "geometry": {"coordinates":[9.1560440063,48.8087005615],"type":"Point"}
}