{
  "type": "Feature",
  "properties": {
    "iso:country":"DE",
    "sg:address":"Wei\u00dfenbach 6",
    "sg:city":"Sch\u00f6nwald",
    "sg:phone":"+49 7722/4848",
    "sg:postcode":"78141",
    "sg:province":"Baden-W\u00fcrttemberg",
    "wof:name":"R\u00f6ssle",
    "wof:placetype":"venue"
},
  "geometry": {"coordinates":[8.186580658,48.110206604],"type":"Point"}
}