{
  "type": "Feature",
  "properties": {
    "iso:country":"DE",
    "sg:address":"Gartenstr. 12",
    "sg:city":"Kirrweiler",
    "sg:phone":"+49 6321/5269",
    "sg:postcode":"67489",
    "sg:province":"Rheinland-Pfalz",
    "wof:name":"Rudi Jung",
    "wof:placetype":"venue"
},
  "geometry": {"coordinates":[8.159472,49.30183],"type":"Point"}
}