{
  "type": "Feature",
  "properties": {
    "iso:country":"DE",
    "sg:address":"Kapuzinerstr. 12",
    "sg:city":"M\u00fcnchen",
    "sg:phone":"+49 89/779098",
    "sg:postcode":"80337",
    "sg:province":"Bayern",
    "wof:name":"Georg Waldleitner Technischer Kundendienst",
    "wof:placetype":"venue"
},
  "geometry": {"coordinates":[11.5569896698,48.1272201538],"type":"Point"}
}