{
  "type": "Feature",
  "properties": {
    "iso:country":"DE",
    "sg:address":"Hanns-Eisler-Weg 14",
    "sg:city":"Schwedt",
    "sg:postcode":"16303",
    "sg:province":"Brandenburg",
    "wof:name":"Franz\u00f6sisch-reformierte",
    "wof:placetype":"venue"
},
  "geometry": {"coordinates":[14.2785215378,53.0594787598],"type":"Point"}
}