{
  "type": "Feature",
  "properties": {
    "iso:country":"DE",
    "sg:address":"Karl-Marx-Str. 29",
    "sg:city":"Unterma\u00dffeld",
    "sg:phone":"+49 36949/21218",
    "sg:postcode":"98617",
    "sg:province":"Th\u00fcringen",
    "wof:name":"Klaus Kuhles",
    "wof:placetype":"venue"
},
  "geometry": {"coordinates":[10.4129829407,50.5346488953],"type":"Point"}
}