{
  "type": "Feature",
  "properties": {
    "iso:country":"DE",
    "sg:address":"Dorfstr. 35",
    "sg:city":"Hausen",
    "sg:phone":"+49 9448/267",
    "sg:postcode":"93345",
    "sg:province":"Bayern",
    "wof:name":"Raiffeisenbank Herrnwahlthann Eg",
    "wof:placetype":"venue"
},
  "geometry": {"coordinates":[11.987777,48.842678],"type":"Point"}
}