{
  "type": "Feature",
  "properties": {
    "iso:country":"DE",
    "sg:address":"Adam-Opel-Str. 26a",
    "sg:city":"R\u00f6dermark",
    "sg:phone":"+49 4960/7484200",
    "sg:postcode":"63322",
    "sg:province":"Hessen",
    "wof:name":"Immucor Medizinische Diagnostik Gmbh",
    "wof:placetype":"venue"
},
  "geometry": {"coordinates":[8.7996912003,49.9834899902],"type":"Point"}
}