{
  "type": "Feature",
  "properties": {
    "iso:country":"DE",
    "sg:address":"Julius-Lucas-Weg 102",
    "sg:city":"Wuppertal",
    "sg:phone":"+49 202/308563",
    "sg:postcode":"42113",
    "sg:province":"Nordrhein-Westfalen",
    "wof:name":"Mammut Transport Gmbh",
    "wof:placetype":"venue"
},
  "geometry": {"coordinates":[7.115981102,51.2664489746],"type":"Point"}
}