{
  "type": "Feature",
  "properties": {
    "iso:country":"DE",
    "sg:address":"Enggasse 3 a",
    "sg:city":"K\u00f6ln",
    "sg:phone":"+49 221/160420",
    "sg:postcode":"50668",
    "sg:province":"Nordrhein-Westfalen",
    "wof:name":"Dr. L\u00fcbke Gmbh",
    "wof:placetype":"venue"
},
  "geometry": {"coordinates":[7.0448131561,50.8689346313],"type":"Point"}
}