{
  "type": "Feature",
  "properties": {
    "iso:country":"DE",
    "sg:address":"Leinstr. 3",
    "sg:city":"Abtsgm\u00fcnd",
    "sg:phone":"+49 7366/7394",
    "sg:postcode":"73453",
    "sg:province":"Baden-W\u00fcrttemberg",
    "wof:name":"Dieter Dussling",
    "wof:placetype":"venue"
},
  "geometry": {"coordinates":[10.0046319962,48.8941841125],"type":"Point"}
}