{
  "type": "Feature",
  "properties": {
    "iso:country":"DE",
    "sg:address":"Hauptstr 7::",
    "sg:city":"Hirschau",
    "sg:phone":"+49 9622/70000",
    "sg:postcode":"92242",
    "sg:province":"Bayern",
    "wof:name":"Raiffeisenbank Hirschau-schnaittenbach Eg",
    "wof:placetype":"venue"
},
  "geometry": {"coordinates":[11.94876,49.544621],"type":"Point"}
}