{
  "type": "Feature",
  "properties": {
    "iso:country":"DE",
    "sg:address":"Seedamm 2",
    "sg:city":"Walldorf",
    "sg:phone":"+49 3693/897242",
    "sg:postcode":"98639",
    "sg:province":"Th\u00fcringen",
    "wof:name":"Wolfgang Schlechtweg",
    "wof:placetype":"venue"
},
  "geometry": {"coordinates":[10.387275,50.609169],"type":"Point"}
}