{
  "type": "Feature",
  "properties": {
    "iso:country":"DE",
    "sg:address":"Bahnhofstr. 5",
    "sg:city":"St. Wendel",
    "sg:postcode":"66606",
    "sg:province":"Saarland",
    "wof:name":"Ms3 Textilhandel Gmbh",
    "wof:placetype":"venue"
},
  "geometry": {"coordinates":[7.1693630219,49.4666252136],"type":"Point"}
}