{
  "type": "Feature",
  "properties": {
    "iso:country":"DE",
    "sg:address":"Willmendinger Str. 25",
    "sg:city":"Wut\u00f6schingen",
    "sg:phone":"+49 7746/5331",
    "sg:postcode":"79793",
    "sg:province":"Baden-W\u00fcrttemberg",
    "wof:name":"Willi Billich",
    "wof:placetype":"venue"
},
  "geometry": {"coordinates":[8.366133,47.659184],"type":"Point"}
}