{
  "type": "Feature",
  "properties": {
    "iso:country":"DE",
    "sg:address":"Eiffestr. 490",
    "sg:city":"Hamburg",
    "sg:phone":"+49 177 2191466",
    "sg:postcode":"20537",
    "sg:province":"Hamburg",
    "wof:name":"H.s.h. - The House Sound From Hamburg",
    "wof:placetype":"venue"
},
  "geometry": {"coordinates":[10.049643,53.551914],"type":"Point"}
}