{
  "type": "Feature",
  "properties": {
    "iso:country":"DE",
    "sg:address":"Bergstr. 8",
    "sg:city":"Schiffweiler",
    "sg:phone":"+49 6821/635151",
    "sg:postcode":"66578",
    "sg:province":"Saarland",
    "wof:name":"Gasthaus Bergschenke",
    "wof:placetype":"venue"
},
  "geometry": {"coordinates":[7.1397042274,49.3736228943],"type":"Point"}
}