{
  "type": "Feature",
  "properties": {
    "iso:country":"DE",
    "sg:address":"Hamburger Berg",
    "sg:city":"Hamburg",
    "sg:phone":"+49 40/7600921",
    "sg:postcode":"20359",
    "sg:province":"Hamburg",
    "wof:name":"Avia Bundesautobahn",
    "wof:placetype":"venue"
},
  "geometry": {"coordinates":[9.9612846375,53.5509414673],"type":"Point"}
}