{
  "type": "Feature",
  "properties": {
    "iso:country":"DE",
    "sg:address":"Am Lenzenfleck 4",
    "sg:city":"Ismaning",
    "sg:phone":"+49 89/9624360",
    "sg:postcode":"85737",
    "sg:province":"Bayern",
    "wof:name":"Neoplan-omnibusvertrieb Beteiligungs-gmbh",
    "wof:placetype":"venue"
},
  "geometry": {"coordinates":[11.680693,48.238602],"type":"Point"}
}