{
  "type": "Feature",
  "properties": {
    "iso:country":"DE",
    "sg:address":"Weseler Str. 52",
    "sg:city":"Haltern",
    "sg:postcode":"45721",
    "sg:province":"Nordrhein-Westfalen",
    "wof:name":"Bauko Koordination F\u00fcr Wohn- Und Gewerbebauten Gmbh",
    "wof:placetype":"venue"
},
  "geometry": {"coordinates":[7.177258,51.741821],"type":"Point"}
}