{
  "type": "Feature",
  "properties": {
    "iso:country":"DE",
    "sg:address":"Ostertagstr. 20",
    "sg:city":"Leonberg",
    "sg:phone":"+49 7152/73334",
    "sg:postcode":"71229",
    "sg:province":"Baden-W\u00fcrttemberg",
    "wof:name":"Werkst\u00e4tte F\u00fcr Orgelbau M\u00fchleisen Gmbh",
    "wof:placetype":"venue"
},
  "geometry": {"coordinates":[9.0130434036,48.7906646729],"type":"Point"}
}