{
  "type": "Feature",
  "properties": {
    "iso:country":"DE",
    "sg:address":"Bgm.-Mahr-Str. 36",
    "sg:city":"Obertshausen",
    "sg:phone":"+49 4961/047070",
    "sg:postcode":"63179",
    "sg:province":"Hessen",
    "wof:name":"Bms Systems Gmbh",
    "wof:placetype":"venue"
},
  "geometry": {"coordinates":[8.846830368,50.0696563721],"type":"Point"}
}