{
  "type": "Feature",
  "properties": {
    "iso:country":"DE",
    "sg:address":"Merklinger Str. 7",
    "sg:city":"Renningen",
    "sg:phone":"+49 7159/92490",
    "sg:postcode":"71272",
    "sg:province":"Baden-W\u00fcrttemberg",
    "wof:name":"Gastst\u00e4tte Zur Taube",
    "wof:placetype":"venue"
},
  "geometry": {"coordinates":[8.8954296112,48.7785644531],"type":"Point"}
}