{
  "type": "Feature",
  "properties": {
    "iso:country":"DE",
    "sg:address":"Marnheimer Str. 68",
    "sg:city":"Kirchheimbolanden",
    "sg:phone":"+49 6352/789152",
    "sg:postcode":"67292",
    "sg:province":"Rheinland-Pfalz",
    "wof:name":"Zweiradhandels- Gmbh Kibo",
    "wof:placetype":"venue"
},
  "geometry": {"coordinates":[8.01552,49.659847],"type":"Point"}
}