{
  "type": "Feature",
  "properties": {
    "iso:country":"DE",
    "sg:address":"Holzweg 33",
    "sg:city":"W\u00fcrzburg",
    "sg:phone":"+49 931/64210",
    "sg:postcode":"97084",
    "sg:province":"Bayern",
    "wof:name":"M. Albert",
    "wof:placetype":"venue"
},
  "geometry": {"coordinates":[9.9402933121,49.7605628967],"type":"Point"}
}