{
  "type": "Feature",
  "properties": {
    "iso:country":"DE",
    "sg:address":"Graf-von-H\u00f6vel-Str. 14",
    "sg:city":"Hamm",
    "sg:postcode":"59075",
    "sg:province":"Nordrhein-Westfalen",
    "wof:name":"M. Seiffert",
    "wof:placetype":"venue"
},
  "geometry": {"coordinates":[7.7565460205,51.7093009949],"type":"Point"}
}