{
  "type": "Feature",
  "properties": {
    "iso:country":"DE",
    "sg:address":"Neum\u00fcnsterstr. 26",
    "sg:city":"Wahlstedt",
    "sg:phone":"+49 4554/4205",
    "sg:postcode":"23812",
    "sg:province":"Schleswig-Holstein",
    "wof:name":"W. Winckelmann",
    "wof:placetype":"venue"
},
  "geometry": {"coordinates":[10.204038,53.954762],"type":"Point"}
}