{
  "type": "Feature",
  "properties": {
    "iso:country":"DE",
    "sg:address":"Broichstr. 26",
    "sg:city":"Neuss",
    "sg:phone":"+49 2131/50071",
    "sg:postcode":"41462",
    "sg:province":"Nordrhein-Westfalen",
    "wof:name":"Lux Gmbh",
    "wof:placetype":"venue"
},
  "geometry": {"coordinates":[6.6628341675,51.2110862732],"type":"Point"}
}