{
  "type": "Feature",
  "properties": {
    "iso:country":"DE",
    "sg:address":"Buchenbichl 11",
    "sg:city":"Tutzing",
    "sg:phone":"+49 8157/8548",
    "sg:postcode":"82327",
    "sg:province":"Bayern",
    "wof:name":"Ludwig Kraus",
    "wof:placetype":"venue"
},
  "geometry": {"coordinates":[11.253618,47.945518],"type":"Point"}
}