{
  "type": "Feature",
  "properties": {
    "iso:country":"DE",
    "sg:address":"Rathergasse 24",
    "sg:city":"Mechernich",
    "sg:phone":"+49 2443/48874",
    "sg:postcode":"53894",
    "sg:province":"Nordrhein-Westfalen",
    "wof:name":"Em Gardest\u00fcffje",
    "wof:placetype":"venue"
},
  "geometry": {"coordinates":[6.6539740562,50.5884361267],"type":"Point"}
}