{
  "type": "Feature",
  "properties": {
    "iso:country":"DE",
    "sg:address":"Schwedenstr. 9",
    "sg:city":"Berlin",
    "sg:phone":"+49 30/4551878",
    "sg:postcode":"13359",
    "sg:province":"Berlin",
    "wof:name":"Geisel",
    "wof:placetype":"venue"
},
  "geometry": {"coordinates":[13.372028,52.557762],"type":"Point"}
}