{
  "type": "Feature",
  "properties": {
    "iso:country":"DE",
    "sg:address":"Mendelssohnstr. 7",
    "sg:city":"Berlin",
    "sg:phone":"+49 30/4424704",
    "sg:postcode":"10405",
    "sg:province":"Berlin",
    "wof:name":"Klaus-dieter Weber",
    "wof:placetype":"venue"
},
  "geometry": {"coordinates":[13.4190721512,52.5274276733],"type":"Point"}
}