{
  "type": "Feature",
  "properties": {
    "iso:country":"DE",
    "sg:address":"Lengeder Str 4",
    "sg:city":"Berlin",
    "sg:phone":"+49 30/41472444",
    "sg:postcode":"13407",
    "sg:province":"Berlin",
    "wof:name":"Udb Urban Design Berlin Gmbh",
    "wof:placetype":"venue"
},
  "geometry": {"coordinates":[13.346301,52.581543],"type":"Point"}
}