{
  "type": "Feature",
  "properties": {
    "iso:country":"DE",
    "sg:address":"Im Gewerbegebiet 10",
    "sg:city":"Hille",
    "sg:phone":"+49 571/646440",
    "sg:postcode":"32479",
    "sg:province":"Nordrhein-Westfalen",
    "wof:name":"Schulwitz Gmbh",
    "wof:placetype":"venue"
},
  "geometry": {"coordinates":[8.7468996048,52.3277702332],"type":"Point"}
}