{
  "type": "Feature",
  "properties": {
    "iso:country":"DE",
    "sg:address":"Marktgasse 20",
    "sg:city":"Eichst\u00e4tt",
    "sg:phone":"+49 8421/901303",
    "sg:postcode":"85072",
    "sg:province":"Bayern",
    "wof:name":"Optik Dickmann Foto Wolfgang Dickmann",
    "wof:placetype":"venue"
},
  "geometry": {"coordinates":[11.1854553223,48.8927955627],"type":"Point"}
}