{
  "type": "Feature",
  "properties": {
    "iso:country":"DE",
    "sg:address":"Windm\u00fchlenstr. 12",
    "sg:city":"Kaarst",
    "sg:phone":"+49 2131/65344",
    "sg:postcode":"41564",
    "sg:province":"Nordrhein-Westfalen",
    "wof:name":"Franz-josef Klein",
    "wof:placetype":"venue"
},
  "geometry": {"coordinates":[6.6240310669,51.233127594],"type":"Point"}
}