{
  "type": "Feature",
  "properties": {
    "iso:country":"DE",
    "sg:address":"Pfarrgasse 1",
    "sg:city":"Volkertshausen",
    "sg:phone":"+49 7774/424",
    "sg:postcode":"78269",
    "sg:province":"Baden-W\u00fcrttemberg",
    "wof:name":"R. Muffler",
    "wof:placetype":"venue"
},
  "geometry": {"coordinates":[8.867823,47.821461],"type":"Point"}
}