{
  "type": "Feature",
  "properties": {
    "iso:country":"DE",
    "sg:address":"Briesbach 31",
    "sg:city":"Idar-Oberstein",
    "sg:phone":"+49 6781/33893",
    "sg:postcode":"55743",
    "sg:province":"Rheinland-Pfalz",
    "wof:name":"Helmut G\u00fcnther",
    "wof:placetype":"venue"
},
  "geometry": {"coordinates":[7.2736902237,49.7371940613],"type":"Point"}
}