{
  "type": "Feature",
  "properties": {
    "iso:country":"DE",
    "sg:address":"Benndorfer Str. 3",
    "sg:city":"Gr\u00f6bers",
    "sg:phone":"+49 34605/20641",
    "sg:postcode":"06184",
    "sg:province":"Sachsen-Anhalt",
    "wof:name":"S. M\u00fcller",
    "wof:placetype":"venue"
},
  "geometry": {"coordinates":[12.0981149673,51.4363746643],"type":"Point"}
}