{
  "type": "Feature",
  "properties": {
    "iso:country":"DE",
    "sg:address":"Am Entenplatz 6",
    "sg:city":"Wagenfeld",
    "sg:phone":"+49 5444/5511",
    "sg:postcode":"49419",
    "sg:province":"Niedersachsen",
    "wof:name":"Ges\u00fcnder Leben Handels Gmbh",
    "wof:placetype":"venue"
},
  "geometry": {"coordinates":[8.5921850204,52.543586731],"type":"Point"}
}