{
  "type": "Feature",
  "properties": {
    "iso:country":"DE",
    "sg:address":"Hauptstr. 18",
    "sg:city":"Angelbachtal",
    "sg:phone":"+49 7265/91340",
    "sg:postcode":"74918",
    "sg:province":"Baden-W\u00fcrttemberg",
    "wof:name":"Ingeborg Rudolf",
    "wof:placetype":"venue"
},
  "geometry": {"coordinates":[8.7738189697,49.2362709045],"type":"Point"}
}