{
  "type": "Feature",
  "properties": {
    "iso:country":"DE",
    "sg:address":"Dr.-Fritz-Zimmermann-Str. 3",
    "sg:city":"Hagnau",
    "sg:phone":"+49 7532/7375",
    "sg:postcode":"88709",
    "sg:province":"Baden-W\u00fcrttemberg",
    "wof:name":"Paulis Keltenschenke",
    "wof:placetype":"venue"
},
  "geometry": {"coordinates":[9.3174562454,47.6740341187],"type":"Point"}
}