{
  "type": "Feature",
  "properties": {
    "iso:country":"DE",
    "sg:address":"Metzgergasse 24",
    "sg:city":"Bad Windsheim",
    "sg:phone":"+49 9841/5709",
    "sg:postcode":"91438",
    "sg:province":"Bayern",
    "wof:name":"Ditha Elektro- Fachgrosshandelshaus",
    "wof:placetype":"venue"
},
  "geometry": {"coordinates":[10.4203720093,49.5028343201],"type":"Point"}
}