{
  "type": "Feature",
  "properties": {
    "iso:country":"DE",
    "sg:address":"Flurstr. 3",
    "sg:city":"Gr\u00e4felfing",
    "sg:phone":"+49 89/8980600",
    "sg:postcode":"82166",
    "sg:province":"Bayern",
    "wof:name":"W.-d. Ehrl Und R. Mattern Steuerberater",
    "wof:placetype":"venue"
},
  "geometry": {"coordinates":[11.4287528992,48.1199569702],"type":"Point"}
}