{
  "type": "Feature",
  "properties": {
    "iso:country":"DE",
    "sg:address":"Schlehenstr. 39",
    "sg:city":"Hamm",
    "sg:phone":"+49 2381/21550",
    "sg:postcode":"59063",
    "sg:province":"Nordrhein-Westfalen",
    "wof:name":"F. Kl\u00f6pperpieper",
    "wof:placetype":"venue"
},
  "geometry": {"coordinates":[7.8413739204,51.6767158508],"type":"Point"}
}