{
  "type": "Feature",
  "properties": {
    "iso:country":"DE",
    "sg:address":"Benzstr. 9",
    "sg:city":"Bad Homburg",
    "sg:postcode":"61352",
    "sg:province":"Hessen",
    "wof:name":"Kaizen Teaching Ag Ndl. Deutschland",
    "wof:placetype":"venue"
},
  "geometry": {"coordinates":[8.61827,50.217609],"type":"Point"}
}