{
  "type": "Feature",
  "properties": {
    "iso:country":"DE",
    "sg:address":"Gorch-Fock-Str. 4",
    "sg:city":"Stade",
    "sg:phone":"+49 4141/62278",
    "sg:postcode":"21680",
    "sg:province":"Niedersachsen",
    "wof:name":"Hildegard Schr\u00f6der",
    "wof:placetype":"venue"
},
  "geometry": {"coordinates":[9.4806051254,53.592300415],"type":"Point"}
}