{
  "type": "Feature",
  "properties": {
    "iso:country":"DE",
    "sg:address":"Vennhauser Allee 251",
    "sg:city":"D\u00fcsseldorf",
    "sg:phone":"+49 211/9262620",
    "sg:postcode":"40627",
    "sg:province":"Nordrhein-Westfalen",
    "wof:name":"M\u00fcther Engineering Gmbh",
    "wof:placetype":"venue"
},
  "geometry": {"coordinates":[6.863985,51.213154],"type":"Point"}
}