{
  "type": "Feature",
  "properties": {
    "iso:country":"DE",
    "sg:address":"Moselstr. 15",
    "sg:city":"Trier",
    "sg:phone":"+49 651/74000",
    "sg:postcode":"54290",
    "sg:province":"Rheinland-Pfalz",
    "wof:name":"Ingobert Bach",
    "wof:placetype":"venue"
},
  "geometry": {"coordinates":[6.6409420967,49.758972168],"type":"Point"}
}