{
  "type": "Feature",
  "properties": {
    "iso:country":"DE",
    "sg:address":"Sandhook 40",
    "sg:city":"Nordhorn",
    "sg:phone":"+49 5921/307340",
    "sg:postcode":"48531",
    "sg:province":"Niedersachsen",
    "wof:name":"Dieter Hahne Automobile Gmbh",
    "wof:placetype":"venue"
},
  "geometry": {"coordinates":[7.0885047913,52.4428291321],"type":"Point"}
}