{
  "type": "Feature",
  "properties": {
    "iso:country":"DE",
    "sg:address":"Sielminger Str. 35",
    "sg:city":"Leinfelden-Echterdingen",
    "sg:phone":"+49 711/790940",
    "sg:postcode":"70771",
    "sg:province":"Baden-W\u00fcrttemberg",
    "wof:name":"Lutro Luft- Und Trockentechnik Gmbh",
    "wof:placetype":"venue"
},
  "geometry": {"coordinates":[9.17827,48.672447],"type":"Point"}
}