{
  "type": "Feature",
  "properties": {
    "iso:country":"DE",
    "sg:address":"Marienstr. 1",
    "sg:city":"Selb",
    "sg:phone":"+49 9287/4075",
    "sg:postcode":"95100",
    "sg:province":"Bayern",
    "wof:name":"Verein F\u00fcr Aquarienkunde E. V. Josef Guba",
    "wof:placetype":"venue"
},
  "geometry": {"coordinates":[12.1277599335,50.1697998047],"type":"Point"}
}