{
  "type": "Feature",
  "properties": {
    "iso:country":"DE",
    "sg:address":"Elbinger Str. 1",
    "sg:city":"Meerbusch",
    "sg:phone":"+49 2159/4900",
    "sg:postcode":"40670",
    "sg:province":"Nordrhein-Westfalen",
    "wof:name":"Paul Schumacher Gmbh Sand- U. Kiesvertrieb",
    "wof:placetype":"venue"
},
  "geometry": {"coordinates":[6.636825,51.264771],"type":"Point"}
}