{
  "type": "Feature",
  "properties": {
    "iso:country":"DE",
    "sg:address":"F\u00fcrstenberger Str. 18",
    "sg:city":"B\u00fcren",
    "sg:phone":"+49 2951/1326",
    "sg:postcode":"33142",
    "sg:province":"Nordrhein-Westfalen",
    "wof:name":"Foto-treff-b\u00fcren Inh. Althaus & Co.",
    "wof:placetype":"venue"
},
  "geometry": {"coordinates":[8.5640773773,51.5470123291],"type":"Point"}
}