{
  "type": "Feature",
  "properties": {
    "iso:country":"DE",
    "sg:address":"Basler Str. 70",
    "sg:city":"Freiburg",
    "sg:phone":"+49 761/408612",
    "sg:postcode":"79100",
    "sg:province":"Baden-W\u00fcrttemberg",
    "wof:name":"S. Woerner",
    "wof:placetype":"venue"
},
  "geometry": {"coordinates":[7.8365330696,47.986038208],"type":"Point"}
}