{
  "type": "Feature",
  "properties": {
    "iso:country":"DE",
    "sg:address":"Wilhelmstr. 1",
    "sg:city":"Rendsburg",
    "sg:phone":"+49 4331/23180",
    "sg:postcode":"24768",
    "sg:province":"Schleswig-Holstein",
    "wof:name":"Hans-j\u00fcrgen Pastor",
    "wof:placetype":"venue"
},
  "geometry": {"coordinates":[9.66456604,54.2932319641],"type":"Point"}
}