{
  "type": "Feature",
  "properties": {
    "iso:country":"DE",
    "sg:address":"Postfach 1517",
    "sg:city":"M\u00fchlacker",
    "sg:postcode":"75405",
    "sg:province":"Baden-W\u00fcrttemberg",
    "wof:name":"Uwe Hirschmann",
    "wof:placetype":"venue"
},
  "geometry": {"coordinates":[8.84001,48.94875],"type":"Point"}
}