{
  "type": "Feature",
  "properties": {
    "iso:country":"DE",
    "sg:address":"Ohefeldweg 1",
    "sg:city":"Hannover",
    "sg:phone":"+49 511/517037",
    "sg:postcode":"30559",
    "sg:province":"Niedersachsen",
    "wof:name":"Schr\u00f6der & Weise Gmbh",
    "wof:placetype":"venue"
},
  "geometry": {"coordinates":[9.848965,52.351994],"type":"Point"}
}