{
  "type": "Feature",
  "properties": {
    "iso:country":"DE",
    "sg:address":"Seilmattenstr. 11",
    "sg:city":"Waldkirch",
    "sg:phone":"+49 7681/7464",
    "sg:postcode":"79183",
    "sg:province":"Baden-W\u00fcrttemberg",
    "wof:name":"Martin Jauch",
    "wof:placetype":"venue"
},
  "geometry": {"coordinates":[7.9707369804,48.1071662903],"type":"Point"}
}