{
  "type": "Feature",
  "properties": {
    "iso:country":"DE",
    "sg:address":"Papenhuder Str. 10",
    "sg:city":"Hamburg",
    "sg:phone":"+49 40/2295154",
    "sg:postcode":"22087",
    "sg:province":"Hamburg",
    "wof:name":"Lsh Handelsgesellschaft Ohg",
    "wof:placetype":"venue"
},
  "geometry": {"coordinates":[10.0207080841,53.5644874573],"type":"Point"}
}