{
  "type": "Feature",
  "properties": {
    "iso:country":"DE",
    "sg:address":"Am Plan 5",
    "sg:city":"Bad Gandersheim",
    "sg:phone":"+49 5382/3419",
    "sg:postcode":"37581",
    "sg:province":"Niedersachsen",
    "wof:name":"R. Kolle",
    "wof:placetype":"venue"
},
  "geometry": {"coordinates":[10.026911,51.871853],"type":"Point"}
}