{
  "type": "Feature",
  "properties": {
    "iso:country":"DE",
    "sg:address":"Dr.-Lauter-Str. 1",
    "sg:city":"Memmingen",
    "sg:phone":"+49 8331/71056",
    "sg:postcode":"87700",
    "sg:province":"Bayern",
    "wof:name":"Eurekfrost K\u00fchl Und Handelsges. Mbh",
    "wof:placetype":"venue"
},
  "geometry": {"coordinates":[10.1594257355,47.9941253662],"type":"Point"}
}