{
  "type": "Feature",
  "properties": {
    "iso:country":"DE",
    "sg:address":"Winterhuder Weg 130",
    "sg:city":"Hamburg",
    "sg:phone":"+49 40/2205662",
    "sg:postcode":"22085",
    "sg:province":"Hamburg",
    "wof:name":"Ev. Pfarramt Ii Heilandskirche",
    "wof:placetype":"venue"
},
  "geometry": {"coordinates":[10.0180139542,53.5777587891],"type":"Point"}
}