{
  "type": "Feature",
  "properties": {
    "iso:country":"DE",
    "sg:address":"Horner Weg 197",
    "sg:city":"Hamburg",
    "sg:phone":"+49 40/6513838",
    "sg:postcode":"22111",
    "sg:province":"Hamburg",
    "wof:name":"J\u00fcrgen Kortylak",
    "wof:placetype":"venue"
},
  "geometry": {"coordinates":[10.0754489899,53.5550003052],"type":"Point"}
}