{
  "type": "Feature",
  "properties": {
    "iso:country":"DE",
    "sg:address":"Am Anger 14",
    "sg:city":"Zw\u00f6nitz",
    "sg:phone":"+49 37754/2815",
    "sg:postcode":"08297",
    "sg:province":"Sachsen",
    "wof:name":"Gebr. Roth Gmbh",
    "wof:placetype":"venue"
},
  "geometry": {"coordinates":[12.82165,50.648449],"type":"Point"}
}