{
  "type": "Feature",
  "properties": {
    "iso:country":"DE",
    "sg:address":"St.-Margareten-Weg 14",
    "sg:city":"Neufahrn",
    "sg:phone":"+49 8165/691804",
    "sg:postcode":"85375",
    "sg:province":"Bayern",
    "wof:name":"J. Haber Immobilienmakler",
    "wof:placetype":"venue"
},
  "geometry": {"coordinates":[11.6870212555,48.3174095154],"type":"Point"}
}