{
  "type": "Feature",
  "properties": {
    "iso:country":"DE",
    "sg:address":"Bauhofstr. 31",
    "sg:city":"Inzell",
    "sg:phone":"+49 8665/7084",
    "sg:postcode":"83334",
    "sg:province":"Bayern",
    "wof:name":"Herbert Funke",
    "wof:placetype":"venue"
},
  "geometry": {"coordinates":[12.74349,47.766449],"type":"Point"}
}