{
  "type": "Feature",
  "properties": {
    "iso:country":"DE",
    "sg:address":"Gewerbegebiet",
    "sg:city":"Haselbach",
    "sg:phone":"+49 34343/7070",
    "sg:postcode":"04617",
    "sg:province":"Th\u00fcringen",
    "wof:name":"Dr. Waldenburger Grundst\u00fcck Gmbh & Co.",
    "wof:placetype":"venue"
},
  "geometry": {"coordinates":[12.3722295761,51.0151290894],"type":"Point"}
}