{
  "type": "Feature",
  "properties": {
    "iso:country":"DE",
    "sg:address":"B\u00fcsnauer Str. 260",
    "sg:city":"Stuttgart",
    "sg:phone":"+49 711/681596",
    "sg:postcode":"70569",
    "sg:province":"Baden-W\u00fcrttemberg",
    "wof:name":"Kath. Pfarramt Maria K\u00f6nigin Des Friedens",
    "wof:placetype":"venue"
},
  "geometry": {"coordinates":[9.0838575363,48.7520561218],"type":"Point"}
}