{
  "type": "Feature",
  "properties": {
    "iso:country":"DE",
    "sg:address":"Am Neutor 30",
    "sg:city":"Dinslaken",
    "sg:phone":"+49 2064/15732",
    "sg:postcode":"46535",
    "sg:province":"Nordrhein-Westfalen",
    "wof:name":"W. Borkes",
    "wof:placetype":"venue"
},
  "geometry": {"coordinates":[6.741698,51.562717],"type":"Point"}
}