{
  "type": "Feature",
  "properties": {
    "iso:country":"DE",
    "sg:address":"Im Wiesengrund 16",
    "sg:city":"Hee\u00dfen",
    "sg:phone":"+49 5722/982404",
    "sg:postcode":"31707",
    "sg:province":"Niedersachsen",
    "wof:name":"Emporio Casa Bautr\u00e4ger Gmbh",
    "wof:placetype":"venue"
},
  "geometry": {"coordinates":[9.100808,52.232105],"type":"Point"}
}