{
  "type": "Feature",
  "properties": {
    "iso:country":"DE",
    "sg:address":"Stiftstr. 2",
    "sg:city":"Frankfurt",
    "sg:phone":"+49 69/28662",
    "sg:postcode":"60313",
    "sg:province":"Hessen",
    "wof:name":"Lexim Im- Und Export Gmbh",
    "wof:placetype":"venue"
},
  "geometry": {"coordinates":[8.6831178665,50.1151351929],"type":"Point"}
}