{
  "type": "Feature",
  "properties": {
    "iso:country":"DE",
    "sg:address":"Marktstr. 71",
    "sg:city":"Winterlingen",
    "sg:phone":"+49 7434/1547",
    "sg:postcode":"72474",
    "sg:province":"Baden-W\u00fcrttemberg",
    "wof:name":"K. Keinath",
    "wof:placetype":"venue"
},
  "geometry": {"coordinates":[9.1177511215,48.1756820679],"type":"Point"}
}