{
  "type": "Feature",
  "properties": {
    "iso:country":"DE",
    "sg:address":"Neusch\u00f6nau",
    "sg:city":"Neusch\u00f6nau",
    "sg:phone":"+49 8558/1084",
    "sg:postcode":"94556",
    "sg:province":"Bayern",
    "wof:name":"Raiffeisenbank Grafenau Eg",
    "wof:placetype":"venue"
},
  "geometry": {"coordinates":[13.475214,48.884121],"type":"Point"}
}