{
  "type": "Feature",
  "properties": {
    "iso:country":"DE",
    "sg:address":"Europaring 110",
    "sg:city":"Altena",
    "sg:phone":"+49 2352/77158",
    "sg:postcode":"58762",
    "sg:province":"Nordrhein-Westfalen",
    "wof:name":"E. Stodtko",
    "wof:placetype":"venue"
},
  "geometry": {"coordinates":[7.71833,51.292854],"type":"Point"}
}