{
  "type": "Feature",
  "properties": {
    "iso:country":"DE",
    "sg:address":"Oberhauser Str. 25a",
    "sg:city":"Essen",
    "sg:phone":"+49 201/696527",
    "sg:postcode":"45359",
    "sg:province":"Nordrhein-Westfalen",
    "wof:name":"K\u00fcpl\u00fcce",
    "wof:placetype":"venue"
},
  "geometry": {"coordinates":[6.9132127762,51.4729194641],"type":"Point"}
}