{
  "type": "Feature",
  "properties": {
    "iso:country":"DE",
    "sg:address":"Bahnhofstr. 12",
    "sg:city":"Eitorf",
    "sg:phone":"+49 2243/2116",
    "sg:postcode":"53783",
    "sg:province":"Nordrhein-Westfalen",
    "wof:name":"Walter Rogalla Steuerberater",
    "wof:placetype":"venue"
},
  "geometry": {"coordinates":[7.4488167763,50.7722587585],"type":"Point"}
}