{
  "type": "Feature",
  "properties": {
    "iso:country":"DE",
    "sg:address":"Paustweg 26",
    "sg:city":"H\u00fcllhorst",
    "sg:phone":"+49 5744/2159",
    "sg:postcode":"32609",
    "sg:province":"Nordrhein-Westfalen",
    "wof:name":"Wilhelm Kr\u00f6ger",
    "wof:placetype":"venue"
},
  "geometry": {"coordinates":[8.735225,52.266712],"type":"Point"}
}