{
  "type": "Feature",
  "properties": {
    "iso:country":"DE",
    "sg:city":"Varchentin",
    "sg:phone":"+49 39934/7579",
    "sg:postcode":"17192",
    "sg:province":"Mecklenburg-Vorpommern",
    "wof:name":"Bernd Mross",
    "wof:placetype":"venue"
},
  "geometry": {"coordinates":[12.859654,53.584736],"type":"Point"}
}