{
  "type": "Feature",
  "properties": {
    "iso:country":"DE",
    "sg:address":"Xantener Str. 17",
    "sg:city":"M\u00fclheim",
    "sg:postcode":"45479",
    "sg:province":"Nordrhein-Westfalen",
    "wof:name":"Hartmuth Recycling Gmbh",
    "wof:placetype":"venue"
},
  "geometry": {"coordinates":[6.8643131256,51.429813385],"type":"Point"}
}