{
  "type": "Feature",
  "properties": {
    "iso:country":"DE",
    "sg:address":"Osnabr\u00fccker Str. 4",
    "sg:city":"L\u00fcbbecke",
    "sg:phone":"+49 5741/30588",
    "sg:postcode":"32312",
    "sg:province":"Nordrhein-Westfalen",
    "wof:name":"G. Kruthoff",
    "wof:placetype":"venue"
},
  "geometry": {"coordinates":[8.6140527725,52.3031005859],"type":"Point"}
}