{
  "type": "Feature",
  "properties": {
    "iso:country":"DE",
    "sg:address":"Am Steinbrink 1",
    "sg:city":"Werdohl",
    "sg:phone":"+49 2392/2276",
    "sg:postcode":"58791",
    "sg:province":"Nordrhein-Westfalen",
    "wof:name":"D. Bruch",
    "wof:placetype":"venue"
},
  "geometry": {"coordinates":[7.7466602325,51.2529182434],"type":"Point"}
}