{
  "type": "Feature",
  "properties": {
    "iso:country":"DE",
    "sg:address":"Rainlesberg 16",
    "sg:city":"K\u00fcnzelsau",
    "sg:phone":"+49 7940/6208",
    "sg:postcode":"74653",
    "sg:province":"Baden-W\u00fcrttemberg",
    "wof:name":"Motech E. K.",
    "wof:placetype":"venue"
},
  "geometry": {"coordinates":[9.758562,49.269264],"type":"Point"}
}