{
  "type": "Feature",
  "properties": {
    "iso:country":"DE",
    "sg:address":"Ostwall 118-120",
    "sg:city":"Krefeld",
    "sg:phone":"+49 2151/618051",
    "sg:postcode":"47798",
    "sg:province":"Nordrhein-Westfalen",
    "wof:name":"Maximum Dressed Gmbh",
    "wof:placetype":"venue"
},
  "geometry": {"coordinates":[6.56646,51.331329],"type":"Point"}
}