{
  "type": "Feature",
  "properties": {
    "iso:country":"DE",
    "sg:address":"Alexanderstr. 37-39",
    "sg:city":"Darmstadt",
    "sg:phone":"+49 6151/22522",
    "sg:postcode":"64283",
    "sg:province":"Hessen",
    "wof:name":"Sta Travel",
    "wof:placetype":"venue"
},
  "geometry": {"coordinates":[8.6605262756,49.8755569458],"type":"Point"}
}