{
  "type": "Feature",
  "properties": {
    "iso:country":"DE",
    "sg:address":"Dessauerstr 6",
    "sg:city":"M\u00fcnchen",
    "sg:phone":"+49 89/14369710",
    "sg:postcode":"80992",
    "sg:province":"Bayern",
    "wof:name":"Polis Gesellschaft F\u00fcr Politik- Und Sozialforschung Mbh",
    "wof:placetype":"venue"
},
  "geometry": {"coordinates":[11.5305967331,48.1804389954],"type":"Point"}
}