{
  "type": "Feature",
  "properties": {
    "iso:country":"DE",
    "sg:address":"Julius-Konegen-Str. 21",
    "sg:city":"Braunschweig",
    "sg:phone":"+49 531/576920",
    "sg:postcode":"38114",
    "sg:province":"Niedersachsen",
    "wof:name":"Monika Kutter Steuerbevollm\u00e4chtigte",
    "wof:placetype":"venue"
},
  "geometry": {"coordinates":[10.5000190735,52.2749786377],"type":"Point"}
}