{
  "type": "Feature",
  "properties": {
    "iso:country":"DE",
    "sg:address":"Langenharmer Weg 93 b",
    "sg:city":"Norderstedt",
    "sg:postcode":"22844",
    "sg:province":"Schleswig-Holstein",
    "wof:name":"Albus Gmbh Allgemeine Buchf\u00fchrungs- Und",
    "wof:placetype":"venue"
},
  "geometry": {"coordinates":[10.01843,53.707279],"type":"Point"}
}