{
  "type": "Feature",
  "properties": {
    "iso:country":"DE",
    "sg:address":"M\u00fchlweg",
    "sg:city":"Gro\u00dfkorbetha",
    "sg:phone":"+49 34446/90501",
    "sg:postcode":"06688",
    "sg:province":"Sachsen-Anhalt",
    "wof:name":"J\u00f6rg B\u00f6hland",
    "wof:placetype":"venue"
},
  "geometry": {"coordinates":[12.029086,51.256683],"type":"Point"}
}