{
  "type": "Feature",
  "properties": {
    "iso:country":"DE",
    "sg:address":"Im Burgstock 2",
    "sg:city":"Steinhausen",
    "sg:phone":"+49 7352/1334",
    "sg:postcode":"88416",
    "sg:province":"Baden-W\u00fcrttemberg",
    "wof:name":"Paul Hagel",
    "wof:placetype":"venue"
},
  "geometry": {"coordinates":[9.974845,48.063354],"type":"Point"}
}