{
  "type": "Feature",
  "properties": {
    "iso:country":"DE",
    "sg:address":"Essentho",
    "sg:city":"Marsberg",
    "sg:phone":"+49 2992/3258",
    "sg:postcode":"34431",
    "sg:province":"Nordrhein-Westfalen",
    "wof:name":"Johann Wagner",
    "wof:placetype":"venue"
},
  "geometry": {"coordinates":[8.8322200775,51.4812698364],"type":"Point"}
}