{
  "type": "Feature",
  "properties": {
    "iso:country":"DE",
    "sg:address":"Hauptstr. 8",
    "sg:city":"Oberau",
    "sg:phone":"+49 8824/262",
    "sg:postcode":"82496",
    "sg:province":"Bayern",
    "wof:name":"Josef Neuner B\u00e4ckerei",
    "wof:placetype":"venue"
},
  "geometry": {"coordinates":[11.136899,47.560333],"type":"Point"}
}