{
  "type": "Feature",
  "properties": {
    "iso:country":"DE",
    "sg:address":"Porschestr 24a",
    "sg:city":"Braunschweig",
    "sg:phone":"+49 531/210790",
    "sg:postcode":"38112",
    "sg:province":"Niedersachsen",
    "wof:name":"Prowema Gmbh",
    "wof:placetype":"venue"
},
  "geometry": {"coordinates":[10.515276,52.301392],"type":"Point"}
}