{
  "type": "Feature",
  "properties": {
    "iso:country":"DE",
    "sg:address":"Geweckenhorst 12",
    "sg:city":"Rheda-Wiedenbr\u00fcck",
    "sg:phone":"+49 5242/402556",
    "sg:postcode":"33378",
    "sg:province":"Nordrhein-Westfalen",
    "wof:name":"F. Papenfort",
    "wof:placetype":"venue"
},
  "geometry": {"coordinates":[8.256029,51.836529],"type":"Point"}
}