{
  "type": "Feature",
  "properties": {
    "iso:country":"DE",
    "sg:address":"Heresbachstr. 11",
    "sg:city":"Rees",
    "sg:phone":"+49 2857/3541",
    "sg:postcode":"46459",
    "sg:province":"Nordrhein-Westfalen",
    "wof:name":"F. Michelbrink",
    "wof:placetype":"venue"
},
  "geometry": {"coordinates":[6.4734477997,51.73046875],"type":"Point"}
}