{
  "type": "Feature",
  "properties": {
    "iso:country":"DE",
    "sg:address":"Seestr. 1",
    "sg:city":"Herrsching",
    "sg:phone":"+49 8152/8972",
    "sg:postcode":"82211",
    "sg:province":"Bayern",
    "wof:name":"See-apotheke",
    "wof:placetype":"venue"
},
  "geometry": {"coordinates":[11.174807,47.995907],"type":"Point"}
}