{
  "type": "Feature",
  "properties": {
    "iso:country":"DE",
    "sg:address":"Oberhaardter Weg 12",
    "sg:city":"Berlin",
    "sg:phone":"+49 30/8255764",
    "sg:postcode":"14193",
    "sg:province":"Berlin",
    "wof:name":"Patrizia Di Stefano",
    "wof:placetype":"venue"
},
  "geometry": {"coordinates":[13.26565,52.481792],"type":"Point"}
}