{
  "type": "Feature",
  "properties": {
    "iso:country":"DE",
    "sg:address":"B\u00fcchel 51",
    "sg:city":"Neuss",
    "sg:phone":"+49 2131/21805",
    "sg:postcode":"41460",
    "sg:province":"Nordrhein-Westfalen",
    "wof:name":"E-plus Shop",
    "wof:placetype":"venue"
},
  "geometry": {"coordinates":[6.6904067993,51.1993560791],"type":"Point"}
}