{
  "type": "Feature",
  "properties": {
    "iso:country":"DE",
    "sg:address":"Landweg 4",
    "sg:city":"Bad Bramstedt",
    "sg:phone":"+49 4192/4682",
    "sg:postcode":"24576",
    "sg:province":"Schleswig-Holstein",
    "wof:name":"Werner Wohlgemuth",
    "wof:placetype":"venue"
},
  "geometry": {"coordinates":[9.8827934265,53.9209289551],"type":"Point"}
}