{
  "type": "Feature",
  "properties": {
    "iso:country":"DE",
    "sg:address":"Karlsplatz 18",
    "sg:city":"Eisenach",
    "sg:phone":"+49 3691/743320",
    "sg:postcode":"99817",
    "sg:province":"Th\u00fcringen",
    "wof:name":"Eiscafe Am Nikolaitor",
    "wof:placetype":"venue"
},
  "geometry": {"coordinates":[10.3256454468,50.9751548767],"type":"Point"}
}