{
  "type": "Feature",
  "properties": {
    "iso:country":"DE",
    "sg:address":"Friedhofstr. 90",
    "sg:city":"M\u00fclheim",
    "sg:postcode":"45478",
    "sg:province":"Nordrhein-Westfalen",
    "wof:name":"Courier-logistik Toth E. K.",
    "wof:placetype":"venue"
},
  "geometry": {"coordinates":[6.839846,51.422634],"type":"Point"}
}