{
  "type": "Feature",
  "properties": {
    "iso:country":"DE",
    "sg:address":"Paul-Frankfurth-Str. 10",
    "sg:city":"Morschen",
    "sg:phone":"+49 5664/254",
    "sg:postcode":"34326",
    "sg:province":"Hessen",
    "wof:name":"Betten Teichmann Inh. Ulrich Teichmann",
    "wof:placetype":"venue"
},
  "geometry": {"coordinates":[9.6194343567,51.070930481],"type":"Point"}
}