{
  "type": "Feature",
  "properties": {
    "iso:country":"DE",
    "sg:address":"Harburger Str. 8",
    "sg:city":"Stelle",
    "sg:phone":"+49 4174/2398",
    "sg:postcode":"21435",
    "sg:province":"Niedersachsen",
    "wof:name":"Rosen-apotheke E. K. Inh. Gisela Wilkens",
    "wof:placetype":"venue"
},
  "geometry": {"coordinates":[10.109228,53.384819],"type":"Point"}
}