{
  "type": "Feature",
  "properties": {
    "iso:country":"DE",
    "sg:address":"Hollertszug 10",
    "sg:city":"Herdorf",
    "sg:postcode":"57562",
    "sg:province":"Rheinland-Pfalz",
    "wof:name":"Sle-prodino Gmbh",
    "wof:placetype":"venue"
},
  "geometry": {"coordinates":[7.931748,50.779659],"type":"Point"}
}