{
  "type": "Feature",
  "properties": {
    "iso:country":"DE",
    "sg:address":"Hauptstr. 42",
    "sg:city":"Hage",
    "sg:phone":"+49 4931/76272",
    "sg:postcode":"26524",
    "sg:province":"Niedersachsen",
    "wof:name":"Ristorante Pizzeria Taverna",
    "wof:placetype":"venue"
},
  "geometry": {"coordinates":[7.2861680984,53.6032752991],"type":"Point"}
}