{
  "type": "Feature",
  "properties": {
    "iso:country":"DE",
    "sg:address":"Rahmedestr. 75-91",
    "sg:city":"Altena",
    "sg:phone":"+49 2352/95920",
    "sg:postcode":"58762",
    "sg:province":"Nordrhein-Westfalen",
    "wof:name":"Berg Verwaltungsges. Mbh",
    "wof:placetype":"venue"
},
  "geometry": {"coordinates":[7.67267,51.274078],"type":"Point"}
}