{
  "type": "Feature",
  "properties": {
    "iso:country":"DE",
    "sg:address":"B\u00f6blinger Str. 21",
    "sg:city":"Horb",
    "sg:phone":"+49 7486/9467",
    "sg:postcode":"72160",
    "sg:province":"Baden-W\u00fcrttemberg",
    "wof:name":"Erich Nafz",
    "wof:placetype":"venue"
},
  "geometry": {"coordinates":[8.63619,48.473637],"type":"Point"}
}