{
  "type": "Feature",
  "properties": {
    "iso:country":"DE",
    "sg:address":"Heidenauer Str. 17",
    "sg:city":"Berlin",
    "sg:phone":"+49 30/9986130",
    "sg:postcode":"12627",
    "sg:province":"Berlin",
    "wof:name":"Lippenstift",
    "wof:placetype":"venue"
},
  "geometry": {"coordinates":[13.6080875397,52.5350265503],"type":"Point"}
}