{
  "type": "Feature",
  "properties": {
    "iso:country":"DE",
    "sg:address":"Heinrich-Heine-Str. 21",
    "sg:city":"Wilkau-Ha\u00dflau",
    "sg:phone":"+49 375/2048210",
    "sg:postcode":"08112",
    "sg:province":"Sachsen",
    "wof:name":"Setbau Gmbh",
    "wof:placetype":"venue"
},
  "geometry": {"coordinates":[12.521785,50.67664],"type":"Point"}
}