{
  "type": "Feature",
  "properties": {
    "iso:country":"DE",
    "sg:address":"Marktplatz 16",
    "sg:city":"Hennef",
    "sg:phone":"+49 2242/80909",
    "sg:postcode":"53773",
    "sg:province":"Nordrhein-Westfalen",
    "wof:name":"Wolfgang J\u00fcnger Rechtsanwalt",
    "wof:placetype":"venue"
},
  "geometry": {"coordinates":[7.2840828896,50.7744483948],"type":"Point"}
}