{
  "type": "Feature",
  "properties": {
    "iso:country":"DE",
    "sg:address":"Parkallee 14",
    "sg:city":"Bremen",
    "sg:phone":"+49 421/3498745",
    "sg:postcode":"28209",
    "sg:province":"Bremen",
    "wof:name":"Bremer Verein Der Getreide- Futtermittel-impoteure Und",
    "wof:placetype":"venue"
},
  "geometry": {"coordinates":[8.8217477798,53.0823516846],"type":"Point"}
}