{
  "type": "Feature",
  "properties": {
    "iso:country":"DE",
    "sg:address":"Hauptstr. 66",
    "sg:city":"Leupoldsgr\u00fcn",
    "sg:phone":"+49 9292/1567",
    "sg:postcode":"95191",
    "sg:province":"Bayern",
    "wof:name":"Emil Schaller",
    "wof:placetype":"venue"
},
  "geometry": {"coordinates":[11.802825,50.298134],"type":"Point"}
}