{
  "type": "Feature",
  "properties": {
    "iso:country":"DE",
    "sg:address":"K\u00f6nigswall 4-6",
    "sg:city":"Dortmund",
    "sg:phone":"+49 231/57041",
    "sg:postcode":"44137",
    "sg:province":"Nordrhein-Westfalen",
    "wof:name":"Hotel K\u00f6nigshof Gmbh",
    "wof:placetype":"venue"
},
  "geometry": {"coordinates":[7.4642381668,51.5175094604],"type":"Point"}
}