{
  "type": "Feature",
  "properties": {
    "iso:country":"DE",
    "sg:address":"Am Exerzierplatz 3a",
    "sg:city":"Mannheim",
    "sg:postcode":"68167",
    "sg:province":"Baden-W\u00fcrttemberg",
    "wof:name":"Elektrokom Elektro- Und Kommunikationstechnik Gmbh",
    "wof:placetype":"venue"
},
  "geometry": {"coordinates":[8.494802,49.503296],"type":"Point"}
}