{
  "type": "Feature",
  "properties": {
    "iso:country":"DE",
    "sg:address":"Kleiberg",
    "sg:city":"Wiefelstede",
    "sg:postcode":"26215",
    "sg:province":"Niedersachsen",
    "wof:name":"A. El-hamidi Gmbh",
    "wof:placetype":"venue"
},
  "geometry": {"coordinates":[8.110025,53.255989],"type":"Point"}
}