{
  "type": "Feature",
  "properties": {
    "iso:country":"DE",
    "sg:address":"Salvatorweg 3",
    "sg:city":"Hohenwart",
    "sg:phone":"+49 8443/91117",
    "sg:postcode":"86558",
    "sg:province":"Bayern",
    "wof:name":"P & S Labormedien-handel Gmbh",
    "wof:placetype":"venue"
},
  "geometry": {"coordinates":[11.3939447403,48.6188354492],"type":"Point"}
}