{
  "type": "Feature",
  "properties": {
    "iso:country":"DE",
    "sg:address":"Gr\u00fcner Winkel 31",
    "sg:city":"Zingst",
    "sg:phone":"+49 38232/15474",
    "sg:postcode":"18374",
    "sg:province":"Mecklenburg-Vorpommern",
    "wof:name":"Versicherungsb\u00fcro Bezirksgeneralagentur",
    "wof:placetype":"venue"
},
  "geometry": {"coordinates":[12.6750898361,54.4331932068],"type":"Point"}
}