{
  "type": "Feature",
  "properties": {
    "iso:country":"DE",
    "sg:address":"Faulerstr. 3",
    "sg:city":"Freiburg",
    "sg:phone":"+49 761/2012370",
    "sg:postcode":"79098",
    "sg:province":"Baden-W\u00fcrttemberg",
    "wof:name":"Faulerbad",
    "wof:placetype":"venue"
},
  "geometry": {"coordinates":[7.8421339989,47.9918479919],"type":"Point"}
}