{
  "type": "Feature",
  "properties": {
    "iso:country":"DE",
    "sg:address":"Oranienstr. 144",
    "sg:city":"K\u00f6ln",
    "sg:phone":"+49 221/8700665",
    "sg:postcode":"51103",
    "sg:province":"Nordrhein-Westfalen",
    "wof:name":"Oranieneck",
    "wof:placetype":"venue"
},
  "geometry": {"coordinates":[7.0200519562,50.9385604858],"type":"Point"}
}