{
  "type": "Feature",
  "properties": {
    "iso:country":"DE",
    "sg:address":"Arnimstr. 4",
    "sg:city":"L\u00fcbeck",
    "sg:phone":"+49 451/625802",
    "sg:postcode":"23566",
    "sg:province":"Schleswig-Holstein",
    "wof:name":"Inlingua Mecklenburg Gmbh Zweigniederlassung L\u00fcbeck",
    "wof:placetype":"venue"
},
  "geometry": {"coordinates":[10.708464,53.874458],"type":"Point"}
}