{
  "type": "Feature",
  "properties": {
    "iso:country":"DE",
    "sg:address":"Erzbergerstr. 3",
    "sg:city":"Hamburg",
    "sg:phone":"+49 40/39901416",
    "sg:postcode":"22765",
    "sg:province":"Hamburg",
    "wof:name":"Art In Art - Martina Skopp-thalheim",
    "wof:placetype":"venue"
},
  "geometry": {"coordinates":[9.931271553,53.5515022278],"type":"Point"}
}