{
  "type": "Feature",
  "properties": {
    "iso:country":"DE",
    "sg:address":"Alt\u00f6ttinger Str. 19",
    "sg:city":"Trostberg",
    "sg:postcode":"83308",
    "sg:province":"Bayern",
    "wof:name":"Aldi Gmbh & Co. Kg",
    "wof:placetype":"venue"
},
  "geometry": {"coordinates":[12.5586366653,48.0339050293],"type":"Point"}
}