{
  "type": "Feature",
  "properties": {
    "iso:country":"DE",
    "sg:address":"Nr. 31",
    "sg:city":"Frie\u00dfnitz",
    "sg:phone":"+49 36603/2882",
    "sg:postcode":"07570",
    "sg:province":"Th\u00fcringen",
    "wof:name":"Eiscafe Sachse",
    "wof:placetype":"venue"
},
  "geometry": {"coordinates":[12.05217,50.768711],"type":"Point"}
}