{
  "type": "Feature",
  "properties": {
    "iso:country":"DE",
    "sg:address":"Obertor 2",
    "sg:city":"Niedenstein",
    "sg:phone":"+49 5624/724",
    "sg:postcode":"34305",
    "sg:province":"Hessen",
    "wof:name":"Keglerstube",
    "wof:placetype":"venue"
},
  "geometry": {"coordinates":[9.3122682571,51.2366676331],"type":"Point"}
}