{
  "type": "Feature",
  "properties": {
    "iso:country":"DE",
    "sg:address":"Wiesenweg 55",
    "sg:city":"Heidelberg",
    "sg:phone":"+49 6221/472777",
    "sg:postcode":"69121",
    "sg:province":"Baden-W\u00fcrttemberg",
    "wof:name":"W. Und W. Grieser",
    "wof:placetype":"venue"
},
  "geometry": {"coordinates":[8.67708,49.435169],"type":"Point"}
}