{
  "type": "Feature",
  "properties": {
    "iso:country":"DE",
    "sg:address":"Inleg 12",
    "sg:city":"Nordhastedt",
    "sg:phone":"+49 4804/420",
    "sg:postcode":"25785",
    "sg:province":"Schleswig-Holstein",
    "wof:name":"L\u00fcders Baugesellschaft Mbh",
    "wof:placetype":"venue"
},
  "geometry": {"coordinates":[9.171759,54.168427],"type":"Point"}
}