{
  "type": "Feature",
  "properties": {
    "iso:country":"DE",
    "sg:address":"Palmaille 35",
    "sg:city":"Hamburg",
    "sg:phone":"+49 40/382271",
    "sg:postcode":"22767",
    "sg:province":"Hamburg",
    "wof:name":"Dr. Harten & Partner Rechtsanw\u00e4lte",
    "wof:placetype":"venue"
},
  "geometry": {"coordinates":[9.941573143,53.5460510254],"type":"Point"}
}