{
  "type": "Feature",
  "properties": {
    "iso:country":"DE",
    "sg:address":"Gartenstr. 6",
    "sg:city":"Elsterberg",
    "sg:postcode":"07985",
    "sg:province":"Th\u00fcringen",
    "wof:name":"Madness-spezial",
    "wof:placetype":"venue"
},
  "geometry": {"coordinates":[12.1688,50.606796],"type":"Point"}
}