{
  "type": "Feature",
  "properties": {
    "iso:country":"DE",
    "sg:address":"Rudolf-Harbig-Str. 4",
    "sg:city":"Hoya",
    "sg:phone":"+49 4251/3591",
    "sg:postcode":"27318",
    "sg:province":"Niedersachsen",
    "wof:name":"Freibad",
    "wof:placetype":"venue"
},
  "geometry": {"coordinates":[9.1324882507,52.8123283386],"type":"Point"}
}