{
  "type": "Feature",
  "properties": {
    "iso:country":"DE",
    "sg:address":"Prezeller Weg 10",
    "sg:city":"Gartow",
    "sg:phone":"+49 5846/1325",
    "sg:postcode":"29471",
    "sg:province":"Niedersachsen",
    "wof:name":"G\u00fcnter Grote",
    "wof:placetype":"venue"
},
  "geometry": {"coordinates":[11.449411,53.021801],"type":"Point"}
}