{
  "type": "Feature",
  "properties": {
    "iso:country":"DE",
    "sg:address":"Schillerstr. 26",
    "sg:city":"Schwalbach",
    "sg:phone":"+49 4968/3455545",
    "sg:postcode":"66773",
    "sg:province":"Saarland",
    "wof:name":"Armin Sch\u00c4fer",
    "wof:placetype":"venue"
},
  "geometry": {"coordinates":[6.820393,49.299076],"type":"Point"}
}