{
  "type": "Feature",
  "properties": {
    "iso:country":"DE",
    "sg:address":"Wallbergstr. 10",
    "sg:city":"Mering",
    "sg:phone":"+49 8233/74010",
    "sg:postcode":"86415",
    "sg:province":"Bayern",
    "wof:name":"Cybermedia Verlags-gmbh",
    "wof:placetype":"venue"
},
  "geometry": {"coordinates":[10.9865484238,48.2563362122],"type":"Point"}
}