{
  "type": "Feature",
  "properties": {
    "iso:country":"DE",
    "sg:address":"Jungbauernhof 27",
    "sg:city":"Alpirsbach",
    "sg:postcode":"72275",
    "sg:province":"Baden-W\u00fcrttemberg",
    "wof:name":"Anndrag Gmbh",
    "wof:placetype":"venue"
},
  "geometry": {"coordinates":[8.3761138916,48.3821105957],"type":"Point"}
}