{
  "type": "Feature",
  "properties": {
    "iso:country":"DE",
    "sg:address":"Buntspechtweg 17",
    "sg:city":"Rheine",
    "sg:phone":"+49 5971/931837",
    "sg:postcode":"48432",
    "sg:province":"Nordrhein-Westfalen",
    "wof:name":"Stefan Kossak",
    "wof:placetype":"venue"
},
  "geometry": {"coordinates":[7.4526810646,52.2402153015],"type":"Point"}
}