{
  "type": "Feature",
  "properties": {
    "iso:country":"DE",
    "sg:address":"Koelnstra\u00dfe 107",
    "sg:city":"Bruehl",
    "sg:postcode":"50321",
    "sg:province":"Nordrhein-Westfalen",
    "wof:name":"Webdesign Welker",
    "wof:placetype":"venue"
},
  "geometry": {"coordinates":[6.907051,50.834534],"type":"Point"}
}