{
  "type": "Feature",
  "properties": {
    "iso:country":"DE",
    "sg:address":"Marktplatz 10",
    "sg:city":"Gr\u00e4finau-Angstedt",
    "sg:phone":"+49 36785/50385",
    "sg:postcode":"98704",
    "sg:province":"Th\u00fcringen",
    "wof:name":"Hotel Prinzenhof Inh. Michael Richter",
    "wof:placetype":"venue"
},
  "geometry": {"coordinates":[11.020690918,50.7029914856],"type":"Point"}
}