{
  "type": "Feature",
  "properties": {
    "iso:country":"DE",
    "sg:address":"Uedesheimer Str. 36",
    "sg:city":"D\u00fcsseldorf",
    "sg:phone":"+49 211/156447",
    "sg:postcode":"40221",
    "sg:province":"Nordrhein-Westfalen",
    "wof:name":"Paul-peter Koelzer Rechtsanwalt",
    "wof:placetype":"venue"
},
  "geometry": {"coordinates":[6.7650260925,51.1980667114],"type":"Point"}
}