{
  "type": "Feature",
  "properties": {
    "iso:country":"DE",
    "sg:address":"Fl\u00fcrener Weg 25",
    "sg:city":"Wesel",
    "sg:phone":"+49 281/70037",
    "sg:postcode":"46487",
    "sg:province":"Nordrhein-Westfalen",
    "wof:name":"Kath. Pfarramt St. Marien",
    "wof:placetype":"venue"
},
  "geometry": {"coordinates":[6.5750589371,51.681804657],"type":"Point"}
}