{
  "type": "Feature",
  "properties": {
    "iso:country":"DE",
    "sg:address":"Karlsbader Str. 250",
    "sg:city":"Sehmatal-Neudorf",
    "sg:phone":"+49 37342/8217",
    "sg:postcode":"09465",
    "sg:province":"Sachsen",
    "wof:name":"Tvs Gmbh",
    "wof:placetype":"venue"
},
  "geometry": {"coordinates":[12.9703035355,50.4712028503],"type":"Point"}
}