{
  "type": "Feature",
  "properties": {
    "iso:country":"DE",
    "sg:address":"Loosestr. 25",
    "sg:city":"Mei\u00dfen",
    "sg:phone":"+49 3521/732366",
    "sg:postcode":"01662",
    "sg:province":"Sachsen",
    "wof:name":"Baumeister Vogel Gmbh",
    "wof:placetype":"venue"
},
  "geometry": {"coordinates":[13.4877357483,51.1586914062],"type":"Point"}
}