{
  "type": "Feature",
  "properties": {
    "iso:country":"DE",
    "sg:address":"Schlo\u00dfstr. 20",
    "sg:city":"Gem\u00fcnden",
    "sg:phone":"+49 6765/9100",
    "sg:postcode":"55490",
    "sg:province":"Rheinland-Pfalz",
    "wof:name":"Archiv Des Freiherrn Von Salis-soglio",
    "wof:placetype":"venue"
},
  "geometry": {"coordinates":[7.477715,49.895699],"type":"Point"}
}