{
  "type": "Feature",
  "properties": {
    "iso:country":"DE",
    "sg:address":"Schiltacher Str. 5",
    "sg:city":"Wolfach",
    "sg:phone":"+49 4978/3483950",
    "sg:postcode":"77709",
    "sg:province":"Baden-W\u00fcrttemberg",
    "wof:name":"Carl Leipold Kg",
    "wof:placetype":"venue"
},
  "geometry": {"coordinates":[8.236269,48.297779],"type":"Point"}
}