{
  "type": "Feature",
  "properties": {
    "iso:country":"DE",
    "sg:address":"Im Bendchen 45",
    "sg:city":"Kerpen",
    "sg:phone":"+49 2273/4662",
    "sg:postcode":"50169",
    "sg:province":"Nordrhein-Westfalen",
    "wof:name":"Hans Neunzig Steuerberater",
    "wof:placetype":"venue"
},
  "geometry": {"coordinates":[6.7217679024,50.9103240967],"type":"Point"}
}