{
  "type": "Feature",
  "properties": {
    "iso:country":"DE",
    "sg:address":"Am Exer 3",
    "sg:city":"Eckernf\u00f6rde",
    "sg:phone":"+49 4351/6044",
    "sg:postcode":"24340",
    "sg:province":"Schleswig-Holstein",
    "wof:name":"Stadthotel Eckernf\u00f6rde",
    "wof:placetype":"venue"
},
  "geometry": {"coordinates":[9.8384380341,54.4680976868],"type":"Point"}
}