{
  "type": "Feature",
  "properties": {
    "iso:country":"DE",
    "sg:address":"Siegburger Weg 59",
    "sg:city":"Hennef",
    "sg:phone":"+49 2242/86396",
    "sg:postcode":"53773",
    "sg:province":"Nordrhein-Westfalen",
    "wof:name":"Apw Wirtschaftsberatungs- Und Warenhandelsgesellschaft Mbh",
    "wof:placetype":"venue"
},
  "geometry": {"coordinates":[7.2590699196,50.7739601135],"type":"Point"}
}