{
  "type": "Feature",
  "properties": {
    "iso:country":"DE",
    "sg:address":"\u00dcbern Berg 28",
    "sg:city":"Osterholz-Scharmbeck",
    "sg:postcode":"27711",
    "sg:province":"Niedersachsen",
    "wof:name":"Multi-design Projekt Gmbh",
    "wof:placetype":"venue"
},
  "geometry": {"coordinates":[8.695182,53.282883],"type":"Point"}
}