{
  "type": "Feature",
  "properties": {
    "iso:country":"DE",
    "sg:address":"Herrenfelder Str. 26",
    "sg:city":"Freudenstadt",
    "sg:phone":"+49 7441/88400",
    "sg:postcode":"72250",
    "sg:province":"Baden-W\u00fcrttemberg",
    "wof:name":"Diakonisches Werk Freudenstadt",
    "wof:placetype":"venue"
},
  "geometry": {"coordinates":[8.419176,48.460266],"type":"Point"}
}