{
  "type": "Feature",
  "properties": {
    "iso:country":"DE",
    "sg:address":"D\u00f6rrieweg 6",
    "sg:city":"Hemmingen",
    "sg:phone":"+49 511/415777",
    "sg:postcode":"30966",
    "sg:province":"Niedersachsen",
    "wof:name":"Gerhard Zilian Steuerberater",
    "wof:placetype":"venue"
},
  "geometry": {"coordinates":[9.752705574,52.3118972778],"type":"Point"}
}