{
  "type": "Feature",
  "properties": {
    "iso:country":"DE",
    "sg:address":"Am Edelsberg 2",
    "sg:city":"Hindelang",
    "sg:phone":"+49 8324/7603",
    "sg:postcode":"87541",
    "sg:province":"Bayern",
    "wof:name":"Pension J\u00f6rg",
    "wof:placetype":"venue"
},
  "geometry": {"coordinates":[10.4193754196,47.5436134338],"type":"Point"}
}