{
  "type": "Feature",
  "properties": {
    "iso:country":"DE",
    "sg:address":"Wirtsstr. 1",
    "sg:city":"Elfershausen",
    "sg:phone":"+49 9732/4926",
    "sg:postcode":"97725",
    "sg:province":"Bayern",
    "wof:name":"Erwin Vierengel",
    "wof:placetype":"venue"
},
  "geometry": {"coordinates":[9.9476003647,50.1230697632],"type":"Point"}
}