{
  "type": "Feature",
  "properties": {
    "iso:country":"DE",
    "sg:address":"M\u00fchlweg 1",
    "sg:city":"Wangen",
    "sg:phone":"+49 7528/2459",
    "sg:postcode":"88239",
    "sg:province":"Baden-W\u00fcrttemberg",
    "wof:name":"Max Buhmann S\u00e4gewerk",
    "wof:placetype":"venue"
},
  "geometry": {"coordinates":[11.3558797836,48.5920906067],"type":"Point"}
}