{
  "type": "Feature",
  "properties": {
    "iso:country":"DE",
    "sg:address":"Vo\u00dfstr. 195",
    "sg:city":"Gladbeck",
    "sg:phone":"+49 2043/62476",
    "sg:postcode":"45966",
    "sg:province":"Nordrhein-Westfalen",
    "wof:name":"Maria Weimann",
    "wof:placetype":"venue"
},
  "geometry": {"coordinates":[6.998779,51.58934],"type":"Point"}
}