{
  "type": "Feature",
  "properties": {
    "iso:country":"DE",
    "sg:address":"Unterwendelsheim 6",
    "sg:city":"Wendelsheim",
    "sg:phone":"+49 6734/304",
    "sg:postcode":"55234",
    "sg:province":"Rheinland-Pfalz",
    "wof:name":"Karl Gro\u00dfe",
    "wof:placetype":"venue"
},
  "geometry": {"coordinates":[7.9963459969,49.7667274475],"type":"Point"}
}