{
  "type": "Feature",
  "properties": {
    "iso:country":"DE",
    "sg:address":"Ringstr. 42",
    "sg:city":"Neckarwestheim",
    "sg:phone":"+49 7133/98200",
    "sg:postcode":"74382",
    "sg:province":"Baden-W\u00fcrttemberg",
    "wof:name":"C T W Computertechnik Gmbh",
    "wof:placetype":"venue"
},
  "geometry": {"coordinates":[9.1880836487,49.0509490967],"type":"Point"}
}