{
  "type": "Feature",
  "properties": {
    "iso:country":"DE",
    "sg:address":"M\u00fcnzmeisterstr. 31",
    "sg:city":"Dresden",
    "sg:phone":"+49 351/4033698",
    "sg:postcode":"01217",
    "sg:province":"Sachsen",
    "wof:name":"R. Ulbricht",
    "wof:placetype":"venue"
},
  "geometry": {"coordinates":[13.741433,51.016888],"type":"Point"}
}