{
  "type": "Feature",
  "properties": {
    "iso:country":"DE",
    "sg:address":"Siemensrg. 112",
    "sg:city":"Willich",
    "sg:phone":"+49 2154/499660",
    "sg:postcode":"47877",
    "sg:province":"Nordrhein-Westfalen",
    "wof:name":"El-o-matic Gmbh",
    "wof:placetype":"venue"
},
  "geometry": {"coordinates":[6.515509,51.266392],"type":"Point"}
}