{
  "type": "Feature",
  "properties": {
    "iso:country":"DE",
    "sg:address":"Friedhofstr. 7",
    "sg:city":"Wilsdruff",
    "sg:phone":"+49 35204/48639",
    "sg:postcode":"01723",
    "sg:province":"Sachsen",
    "wof:name":"Riedel Und Clausnitzer",
    "wof:placetype":"venue"
},
  "geometry": {"coordinates":[13.539806,51.049335],"type":"Point"}
}