{
  "type": "Feature",
  "properties": {
    "iso:country":"DE",
    "sg:address":"Herzbergstr 87-99",
    "sg:city":"Berlin",
    "sg:phone":"+49 30/55263071",
    "sg:postcode":"10365",
    "sg:province":"Berlin",
    "wof:name":"Berlinerluft Technik Gmbh",
    "wof:placetype":"venue"
},
  "geometry": {"coordinates":[13.502404,52.526447],"type":"Point"}
}