{
  "type": "Feature",
  "properties": {
    "iso:country":"DE",
    "sg:address":"Kreuzstr. 22",
    "sg:city":"Aachen",
    "sg:phone":"+49 241/163959",
    "sg:postcode":"52080",
    "sg:province":"Nordrhein-Westfalen",
    "wof:name":"K Und C Schmies Gmbh",
    "wof:placetype":"venue"
},
  "geometry": {"coordinates":[6.1304960251,50.7971496582],"type":"Point"}
}