{
  "type": "Feature",
  "properties": {
    "iso:country":"DE",
    "sg:address":"Bruckgasse 18",
    "sg:city":"Obersontheim",
    "sg:phone":"+49 7973/739",
    "sg:postcode":"74423",
    "sg:province":"Baden-W\u00fcrttemberg",
    "wof:name":"Roland Carle",
    "wof:placetype":"venue"
},
  "geometry": {"coordinates":[9.8632593155,49.0414085388],"type":"Point"}
}