{
  "type": "Feature",
  "properties": {
    "iso:country":"DE",
    "sg:address":"Lange Str. 72",
    "sg:city":"Naunhof",
    "sg:phone":"+49 34293/33294",
    "sg:postcode":"04683",
    "sg:province":"Sachsen",
    "wof:name":"Elisabeth He\u00dfler",
    "wof:placetype":"venue"
},
  "geometry": {"coordinates":[12.5908346176,51.2726974487],"type":"Point"}
}