{
  "type": "Feature",
  "properties": {
    "iso:country":"DE",
    "sg:address":"Rhenaniastr. 1",
    "sg:city":"Stolberg",
    "sg:phone":"+49 2402/22227",
    "sg:postcode":"52222",
    "sg:province":"Nordrhein-Westfalen",
    "wof:name":"W. F\u00e4hnrich",
    "wof:placetype":"venue"
},
  "geometry": {"coordinates":[6.2183761597,50.7926101685],"type":"Point"}
}