{
  "type": "Feature",
  "properties": {
    "iso:country":"DE",
    "sg:address":"M\u00fcnsterstr. 6",
    "sg:city":"Altenberge",
    "sg:postcode":"48341",
    "sg:province":"Nordrhein-Westfalen",
    "wof:name":"Sonnen Apotheke Susanne Stricker E. K.",
    "wof:placetype":"venue"
},
  "geometry": {"coordinates":[7.465574,52.044853],"type":"Point"}
}