{
  "type": "Feature",
  "properties": {
    "iso:country":"DE",
    "sg:address":"Von-Holte-Str. 11",
    "sg:city":"M\u00fcnster",
    "sg:phone":"+49 2506/2367",
    "sg:postcode":"48167",
    "sg:province":"Nordrhein-Westfalen",
    "wof:name":"Wilhelm Wessel-therhorn Steuerbevollm\u00e4chtigter",
    "wof:placetype":"venue"
},
  "geometry": {"coordinates":[7.7218551636,51.9128036499],"type":"Point"}
}