{
  "type": "Feature",
  "properties": {
    "iso:country":"DE",
    "sg:address":"Bamberger Str. 21",
    "sg:city":"Forchheim",
    "sg:phone":"+49 9191/15444",
    "sg:postcode":"91301",
    "sg:province":"Bayern",
    "wof:name":"G\u00fcnter Siegert",
    "wof:placetype":"venue"
},
  "geometry": {"coordinates":[11.0591745377,49.7226142883],"type":"Point"}
}