{
  "type": "Feature",
  "properties": {
    "iso:country":"DE",
    "sg:address":"Vilshofener Str. 76",
    "sg:city":"Passau",
    "sg:phone":"+49 851/51315",
    "sg:postcode":"94034",
    "sg:province":"Bayern",
    "wof:name":"Josef Franz",
    "wof:placetype":"venue"
},
  "geometry": {"coordinates":[13.43619,48.576023],"type":"Point"}
}