{
  "type": "Feature",
  "properties": {
    "iso:country":"DE",
    "sg:address":"Gro\u00dfe M\u00fchlenstr. 7",
    "sg:city":"Nortorf",
    "sg:phone":"+49 4392/4442",
    "sg:postcode":"24589",
    "sg:province":"Schleswig-Holstein",
    "wof:name":"K\u00f6niglich Priviligierte Apotheke",
    "wof:placetype":"venue"
},
  "geometry": {"coordinates":[9.853954,54.168812],"type":"Point"}
}