{
  "type": "Feature",
  "properties": {
    "iso:country":"DE",
    "sg:address":"Landsberger Str. 57 a",
    "sg:city":"K\u00f6nigsbrunn",
    "sg:phone":"+49 8231/4890",
    "sg:postcode":"86343",
    "sg:province":"Bayern",
    "wof:name":"Erwin Frisch",
    "wof:placetype":"venue"
},
  "geometry": {"coordinates":[10.881397,48.253895],"type":"Point"}
}