{
  "type": "Feature",
  "properties": {
    "iso:country":"DE",
    "sg:address":"Obere Tiefenbachstr. 15a",
    "sg:city":"Hausham",
    "sg:phone":"+49 8026/38529",
    "sg:postcode":"83734",
    "sg:province":"Bayern",
    "wof:name":"Trigema Gmbh",
    "wof:placetype":"venue"
},
  "geometry": {"coordinates":[11.830694,47.762352],"type":"Point"}
}