{
  "type": "Feature",
  "properties": {
    "iso:country":"DE",
    "sg:address":"Mauer 1",
    "sg:city":"Coburg",
    "sg:phone":"+49 9561/75313",
    "sg:postcode":"96450",
    "sg:province":"Bayern",
    "wof:name":"Augenoptik Keintzel Im Parkhaus",
    "wof:placetype":"venue"
},
  "geometry": {"coordinates":[10.9635601044,50.2594604492],"type":"Point"}
}