{
  "type": "Feature",
  "properties": {
    "iso:country":"DE",
    "sg:address":"Lessingstr. 6",
    "sg:city":"Neu-Ulm",
    "sg:phone":"+49 731/974080",
    "sg:postcode":"89231",
    "sg:province":"Bayern",
    "wof:name":"Gruschwitz Textilwerke Ag",
    "wof:placetype":"venue"
},
  "geometry": {"coordinates":[10.0272312164,48.3971138],"type":"Point"}
}