{
  "type": "Feature",
  "properties": {
    "iso:country":"DE",
    "sg:address":"Zum Langen See 59",
    "sg:city":"Berlin",
    "sg:postcode":"12557",
    "sg:province":"Berlin",
    "wof:name":"My Home Wohnbauten Gmbh",
    "wof:placetype":"venue"
},
  "geometry": {"coordinates":[13.59362,52.415482],"type":"Point"}
}