{
  "type": "Feature",
  "properties": {
    "iso:country":"DE",
    "sg:address":"Tauchenweiler Str. 13",
    "sg:city":"Essingen",
    "sg:phone":"+49 7365/5810",
    "sg:postcode":"73457",
    "sg:province":"Baden-W\u00fcrttemberg",
    "wof:name":"Hirsch",
    "wof:placetype":"venue"
},
  "geometry": {"coordinates":[10.0268335342,48.8049201965],"type":"Point"}
}