{
  "type": "Feature",
  "properties": {
    "iso:country":"DE",
    "sg:address":"Pfarrweg 2c",
    "sg:city":"M\u00fcnchen",
    "sg:postcode":"81541",
    "sg:province":"Bayern",
    "wof:name":"Sites Unlimited",
    "wof:placetype":"venue"
},
  "geometry": {"coordinates":[11.6002807617,48.110622406],"type":"Point"}
}