{
  "type": "Feature",
  "properties": {
    "iso:country":"DE",
    "sg:address":"Pritchardstr. 5/9",
    "sg:city":"Berlin",
    "sg:phone":"+49 30/7850589",
    "sg:postcode":"14169",
    "sg:province":"Berlin",
    "wof:name":"Irene Pfeifer",
    "wof:placetype":"venue"
},
  "geometry": {"coordinates":[13.2654600143,52.4529457092],"type":"Point"}
}