{
  "type": "Feature",
  "properties": {
    "iso:country":"DE",
    "sg:address":"Hasselbinnen 12",
    "sg:city":"Schenefeld",
    "sg:phone":"+49 40/875232",
    "sg:postcode":"22869",
    "sg:province":"Schleswig-Holstein",
    "wof:name":"Peter Sch\u00f6nherr Omnibusbetrieb",
    "wof:placetype":"venue"
},
  "geometry": {"coordinates":[9.832575798,53.5933227539],"type":"Point"}
}