{
  "type": "Feature",
  "properties": {
    "iso:country":"DE",
    "sg:address":"Teplitzer Str. 14",
    "sg:city":"Altenberg",
    "sg:phone":"+49 35056/5370",
    "sg:postcode":"01773",
    "sg:province":"Sachsen",
    "wof:name":"Edeka Markt",
    "wof:placetype":"venue"
},
  "geometry": {"coordinates":[13.7625932693,50.7364883423],"type":"Point"}
}