{
  "type": "Feature",
  "properties": {
    "iso:country":"DE",
    "sg:address":"Dissenchener Str. 50",
    "sg:city":"Cottbus",
    "sg:phone":"+49 355",
    "sg:postcode":"03042",
    "sg:province":"Brandenburg",
    "wof:name":"Autofit Kfz Werkstatt Senkel & Sch\u00f6nbrunn Gmbh",
    "wof:placetype":"venue"
},
  "geometry": {"coordinates":[14.3726520538,51.7636413574],"type":"Point"}
}