{
  "type": "Feature",
  "properties": {
    "iso:country":"DE",
    "sg:address":"Rissener Landstr. 177",
    "sg:city":"Hamburg",
    "sg:phone":"+49 40/810654",
    "sg:postcode":"22559",
    "sg:province":"Hamburg",
    "wof:name":"Kobialka Verwaltungs- Gmbh",
    "wof:placetype":"venue"
},
  "geometry": {"coordinates":[9.7745170593,53.5767059326],"type":"Point"}
}