{
  "type": "Feature",
  "properties": {
    "iso:country":"DE",
    "sg:address":"Gro\u00dfer L\u00f6we 4",
    "sg:city":"Emmerich",
    "sg:phone":"+49 2822/3457",
    "sg:postcode":"46446",
    "sg:province":"Nordrhein-Westfalen",
    "wof:name":"M. De Moll",
    "wof:placetype":"venue"
},
  "geometry": {"coordinates":[6.247461,51.834499],"type":"Point"}
}