{
  "type": "Feature",
  "properties": {
    "iso:country":"DE",
    "sg:address":"Br\u00f6kerei 5",
    "sg:city":"Oldenburg",
    "sg:phone":"+49 441/951970",
    "sg:postcode":"26129",
    "sg:province":"Niedersachsen",
    "wof:name":"Bourquin Rosenkranz & Partner",
    "wof:placetype":"venue"
},
  "geometry": {"coordinates":[8.1754150391,53.1422653198],"type":"Point"}
}