{
  "type": "Feature",
  "properties": {
    "iso:country":"DE",
    "sg:address":"Budenheimer Str. 25",
    "sg:city":"Mainz",
    "sg:phone":"+49 6131/41346",
    "sg:postcode":"55124",
    "sg:province":"Rheinland-Pfalz",
    "wof:name":"Roland Neuh\u00e4user Roland's Antiquit\u00e4ten",
    "wof:placetype":"venue"
},
  "geometry": {"coordinates":[8.206321,49.999401],"type":"Point"}
}