{
  "type": "Feature",
  "properties": {
    "iso:country":"DE",
    "sg:address":"Am Kirchplatz 4",
    "sg:city":"H\u00fcnxe",
    "sg:phone":"+49 2858/2665",
    "sg:postcode":"46569",
    "sg:province":"Nordrhein-Westfalen",
    "wof:name":"M. Hillenbach",
    "wof:placetype":"venue"
},
  "geometry": {"coordinates":[6.7476072311,51.660068512],"type":"Point"}
}