{
  "type": "Feature",
  "properties": {
    "iso:country":"DE",
    "sg:address":"Fr\u00f6belstr. 19",
    "sg:city":"Augsburg",
    "sg:phone":"+49 821/524702",
    "sg:postcode":"86157",
    "sg:province":"Bayern",
    "wof:name":"Pension Abba",
    "wof:placetype":"venue"
},
  "geometry": {"coordinates":[10.864919,48.361851],"type":"Point"}
}