{
  "type": "Feature",
  "properties": {
    "iso:country":"DE",
    "sg:address":"Berggarten 1",
    "sg:city":"Siershahn",
    "sg:phone":"+49 2623/600217",
    "sg:postcode":"56427",
    "sg:province":"Rheinland-Pfalz",
    "wof:name":"Hermann G\u00f6bel",
    "wof:placetype":"venue"
},
  "geometry": {"coordinates":[7.7699518204,50.4838066101],"type":"Point"}
}