{
  "type": "Feature",
  "properties": {
    "iso:country":"DE",
    "sg:address":"Genschmarer Str. 8",
    "sg:city":"Gorgast",
    "sg:phone":"+49 33472/546",
    "sg:postcode":"15328",
    "sg:province":"Brandenburg",
    "wof:name":"R. Wagner",
    "wof:placetype":"venue"
},
  "geometry": {"coordinates":[14.543346,52.572586],"type":"Point"}
}