{
  "type": "Feature",
  "properties": {
    "iso:country":"DE",
    "sg:address":"Langst\u00fccken 26",
    "sg:city":"Flintbek",
    "sg:phone":"+49 4347/8949",
    "sg:postcode":"24220",
    "sg:province":"Schleswig-Holstein",
    "wof:name":"Adalbert Zajadacz Gmbh & Co.",
    "wof:placetype":"venue"
},
  "geometry": {"coordinates":[10.0585155487,54.2531280518],"type":"Point"}
}