{
  "type": "Feature",
  "properties": {
    "iso:country":"DE",
    "sg:address":"Pappelweg 1",
    "sg:city":"Altenstadt",
    "sg:phone":"+49 6047/2445",
    "sg:postcode":"63674",
    "sg:province":"Hessen",
    "wof:name":"Herbert Volkening Architekt",
    "wof:placetype":"venue"
},
  "geometry": {"coordinates":[8.960888,50.270641],"type":"Point"}
}