{
  "type": "Feature",
  "properties": {
    "iso:country":"DE",
    "sg:address":"Friedrich-Ebert-Str. 19",
    "sg:city":"Babenhausen",
    "sg:phone":"+49 6073/64984",
    "sg:postcode":"64832",
    "sg:province":"Hessen",
    "wof:name":"Inge B\u00fchler",
    "wof:placetype":"venue"
},
  "geometry": {"coordinates":[8.9602422714,49.9571609497],"type":"Point"}
}