{
  "type": "Feature",
  "properties": {
    "iso:country":"DE",
    "sg:address":"Justus-von-Liebig-Str. 22",
    "sg:city":"Bonn",
    "sg:phone":"+49 228/9669530",
    "sg:postcode":"53121",
    "sg:province":"Nordrhein-Westfalen",
    "wof:name":"Zht Z\u00f6lfel Haustechnik Gmbh",
    "wof:placetype":"venue"
},
  "geometry": {"coordinates":[7.0559167862,50.7396583557],"type":"Point"}
}