{
  "type": "Feature",
  "properties": {
    "iso:country":"DE",
    "sg:address":"Kre\u00dfbacher Str. 5",
    "sg:city":"Neudenau",
    "sg:phone":"+49 6298/5353",
    "sg:postcode":"74861",
    "sg:province":"Baden-W\u00fcrttemberg",
    "wof:name":"Kleintierzuchtverein Siglingen Z\u00fcttlingen",
    "wof:placetype":"venue"
},
  "geometry": {"coordinates":[9.2613296509,49.2821960449],"type":"Point"}
}