{
  "type": "Feature",
  "properties": {
    "iso:country":"DE",
    "sg:address":"Turnhallestr. 16",
    "sg:city":"Freudenstadt",
    "sg:phone":"+49 7441/91180",
    "sg:postcode":"72250",
    "sg:province":"Baden-W\u00fcrttemberg",
    "wof:name":"Tiesenhausen Schwarz Und Duffner",
    "wof:placetype":"venue"
},
  "geometry": {"coordinates":[8.4188451767,48.4632873535],"type":"Point"}
}