{
  "type": "Feature",
  "properties": {
    "iso:country":"DE",
    "sg:address":"Stadtstr. 20",
    "sg:city":"Burgau",
    "sg:phone":"+49 8222/1867",
    "sg:postcode":"89331",
    "sg:province":"Bayern",
    "wof:name":"Erich Kraus",
    "wof:placetype":"venue"
},
  "geometry": {"coordinates":[10.40791,48.431225],"type":"Point"}
}