{
  "type": "Feature",
  "properties": {
    "iso:country":"DE",
    "sg:address":"S\u00fcdring 181",
    "sg:city":"Datteln",
    "sg:phone":"+49 2363/91900",
    "sg:postcode":"45711",
    "sg:province":"Nordrhein-Westfalen",
    "wof:name":"Stefan Koch-niehus",
    "wof:placetype":"venue"
},
  "geometry": {"coordinates":[7.3431382179,51.6502418518],"type":"Point"}
}