{
  "type": "Feature",
  "properties": {
    "iso:country":"DE",
    "sg:address":"Gauchachstr. 7",
    "sg:city":"Br\u00e4unlingen",
    "sg:phone":"+49 7707/223",
    "sg:postcode":"78199",
    "sg:province":"Baden-W\u00fcrttemberg",
    "wof:name":"Herbert Schorp",
    "wof:placetype":"venue"
},
  "geometry": {"coordinates":[8.434912,47.89119],"type":"Point"}
}