{
  "type": "Feature",
  "properties": {
    "iso:country":"DE",
    "sg:address":"Bahnhofstr. 99",
    "sg:city":"Wirges",
    "sg:postcode":"56422",
    "sg:province":"Rheinland-Pfalz",
    "wof:name":"E.-m. Gehringer",
    "wof:placetype":"venue"
},
  "geometry": {"coordinates":[7.786885,50.46814],"type":"Point"}
}