{
  "type": "Feature",
  "properties": {
    "iso:country":"DE",
    "sg:address":"Steindamm 101",
    "sg:city":"Hamburg",
    "sg:phone":"+49 40/2802222",
    "sg:postcode":"20099",
    "sg:province":"Hamburg",
    "wof:name":"Krause",
    "wof:placetype":"venue"
},
  "geometry": {"coordinates":[10.0190753937,53.5567245483],"type":"Point"}
}