{
  "type": "Feature",
  "properties": {
    "iso:country":"DE",
    "sg:address":"R\u00fchberg 10",
    "sg:city":"Soltau",
    "sg:phone":"+49 5191/17662",
    "sg:postcode":"29614",
    "sg:province":"Niedersachsen",
    "wof:name":"Willi Herzberg",
    "wof:placetype":"venue"
},
  "geometry": {"coordinates":[9.835884,52.985825],"type":"Point"}
}