{
  "type": "Feature",
  "properties": {
    "iso:country":"DE",
    "sg:address":"Ringstr. 24",
    "sg:city":"H\u00f6rstel",
    "sg:phone":"+49 5454/9515",
    "sg:postcode":"48477",
    "sg:province":"Nordrhein-Westfalen",
    "wof:name":"Gabriele M\u00f6hle Heilpraktikerin",
    "wof:placetype":"venue"
},
  "geometry": {"coordinates":[7.64392519,52.2459945679],"type":"Point"}
}