{
  "type": "Feature",
  "properties": {
    "iso:country":"DE",
    "sg:address":"Frankenwinheimer Str. 17",
    "sg:city":"Gerolzhofen",
    "sg:postcode":"97447",
    "sg:province":"Bayern",
    "wof:name":"M\u00fcller Landtechnik Kg",
    "wof:placetype":"venue"
},
  "geometry": {"coordinates":[10.33757,49.900688],"type":"Point"}
}