{
  "type": "Feature",
  "properties": {
    "iso:country":"DE",
    "sg:address":"Grafenreuth 5",
    "sg:city":"Flo\u00df",
    "sg:phone":"+49 9603/307",
    "sg:postcode":"92685",
    "sg:province":"Bayern",
    "wof:name":"Helmut Bock",
    "wof:placetype":"venue"
},
  "geometry": {"coordinates":[12.291291,49.692924],"type":"Point"}
}