{
  "type": "Feature",
  "properties": {
    "iso:country":"DE",
    "sg:address":"Heerstr. 13",
    "sg:city":"H\u00fcckelhoven",
    "sg:phone":"+49 2433/60811",
    "sg:postcode":"41836",
    "sg:province":"Nordrhein-Westfalen",
    "wof:name":"An Der Chaussee",
    "wof:placetype":"venue"
},
  "geometry": {"coordinates":[6.1880698204,51.0656242371],"type":"Point"}
}