{
  "type": "Feature",
  "properties": {
    "iso:country":"DE",
    "sg:address":"Hospitalstr. 1",
    "sg:city":"Schm\u00f6lln",
    "sg:phone":"+49 34491/61314",
    "sg:postcode":"04626",
    "sg:province":"Th\u00fcringen",
    "wof:name":"Weiske",
    "wof:placetype":"venue"
},
  "geometry": {"coordinates":[12.360775,50.896927],"type":"Point"}
}