{
  "type": "Feature",
  "properties": {
    "iso:country":"DE",
    "sg:address":"Technikstr. 5",
    "sg:city":"Wermelskirchen",
    "sg:phone":"+49 2196/72990",
    "sg:postcode":"42929",
    "sg:province":"Nordrhein-Westfalen",
    "wof:name":"Ising-steuerungstechnik Gmbh",
    "wof:placetype":"venue"
},
  "geometry": {"coordinates":[7.246213913,51.1440238953],"type":"Point"}
}