{
  "type": "Feature",
  "properties": {
    "iso:country":"DE",
    "sg:address":"Ruhesteinstr. 170",
    "sg:city":"Baiersbronn",
    "sg:phone":"+49 7442/84590",
    "sg:postcode":"72270",
    "sg:province":"Baden-W\u00fcrttemberg",
    "wof:name":"Braun Beton Gmbh",
    "wof:placetype":"venue"
},
  "geometry": {"coordinates":[8.3616,48.50956],"type":"Point"}
}