{
  "type": "Feature",
  "properties": {
    "iso:country":"DE",
    "sg:address":"Blarerstr 56",
    "sg:city":"Konstanz",
    "sg:phone":"+49 7531/9189101",
    "sg:postcode":"78462",
    "sg:province":"Baden-W\u00fcrttemberg",
    "wof:name":"Visiometrics Stephan Neser & Ralf Bubeck Gbr",
    "wof:placetype":"venue"
},
  "geometry": {"coordinates":[9.1664075851,47.6588478088],"type":"Point"}
}