{
  "type": "Feature",
  "properties": {
    "iso:country":"DE",
    "sg:address":"Neue Gasse 23",
    "sg:city":"Wernshausen",
    "sg:phone":"+49 36848/30642",
    "sg:postcode":"98590",
    "sg:province":"Th\u00fcringen",
    "wof:name":"Dr. Herbert Wolff Tierarzt",
    "wof:placetype":"venue"
},
  "geometry": {"coordinates":[10.3538713455,50.7245864868],"type":"Point"}
}