{
  "type": "Feature",
  "properties": {
    "iso:country":"DE",
    "sg:address":"Hauptstr. 4",
    "sg:city":"Buchholz",
    "sg:phone":"+49 3395/304090",
    "sg:postcode":"16928",
    "sg:province":"Brandenburg",
    "wof:name":"Prignitzer Hof",
    "wof:placetype":"venue"
},
  "geometry": {"coordinates":[11.7909488678,52.5423088074],"type":"Point"}
}