{
  "type": "Feature",
  "properties": {
    "iso:country":"DE",
    "sg:address":"Steinlestr. 4",
    "sg:city":"Neu-Isenburg",
    "sg:postcode":"63263",
    "sg:province":"Hessen",
    "wof:name":"Volta Park Kghp Gewerbe- Immobilien Gmbh & Co. Kg",
    "wof:placetype":"venue"
},
  "geometry": {"coordinates":[8.6951436996,50.0565185547],"type":"Point"}
}