{
  "type": "Feature",
  "properties": {
    "iso:country":"DE",
    "sg:address":"Ostendstr. 67-1",
    "sg:city":"Stuttgart",
    "sg:phone":"+49 711/2865903",
    "sg:postcode":"70188",
    "sg:province":"Baden-W\u00fcrttemberg",
    "wof:name":"Bistro Astoria",
    "wof:placetype":"venue"
},
  "geometry": {"coordinates":[9.2080993652,48.7855224609],"type":"Point"}
}