{
  "type": "Feature",
  "properties": {
    "iso:country":"DE",
    "sg:address":"Lange Zeile 10",
    "sg:city":"Erding",
    "sg:phone":"+49 8122/93219",
    "sg:postcode":"85435",
    "sg:province":"Bayern",
    "wof:name":"G. Und G.",
    "wof:placetype":"venue"
},
  "geometry": {"coordinates":[11.9073162079,48.3073005676],"type":"Point"}
}