{
  "type": "Feature",
  "properties": {
    "iso:country":"DE",
    "sg:address":"Kirchstr. 9",
    "sg:city":"Gechingen",
    "sg:phone":"+49 7056/2762",
    "sg:postcode":"75391",
    "sg:province":"Baden-W\u00fcrttemberg",
    "wof:name":"A. Sebald",
    "wof:placetype":"venue"
},
  "geometry": {"coordinates":[8.8278589249,48.6939506531],"type":"Point"}
}