{
  "type": "Feature",
  "properties": {
    "iso:country":"DE",
    "sg:address":"Robert-Koch-Str. 2",
    "sg:city":"Storkow",
    "sg:phone":"+49 33678/62121",
    "sg:postcode":"15859",
    "sg:province":"Brandenburg",
    "wof:name":"Theresienheim",
    "wof:placetype":"venue"
},
  "geometry": {"coordinates":[13.93133,52.255363],"type":"Point"}
}