{
  "type": "Feature",
  "properties": {
    "iso:country":"DE",
    "sg:address":"Dammstr. 7",
    "sg:city":"Breuberg",
    "sg:phone":"+49 6165/2592",
    "sg:postcode":"64747",
    "sg:province":"Hessen",
    "wof:name":"Wolf & S\u00f6hne Gmbh",
    "wof:placetype":"venue"
},
  "geometry": {"coordinates":[9.040389,49.832253],"type":"Point"}
}