{
  "type": "Feature",
  "properties": {
    "iso:country":"DE",
    "sg:address":"Graupfortstr. 3",
    "sg:city":"Limburg",
    "sg:phone":"+49 6431/8727",
    "sg:postcode":"65549",
    "sg:province":"Hessen",
    "wof:name":"Spielejo Jochem Holzh\u00e4user",
    "wof:placetype":"venue"
},
  "geometry": {"coordinates":[8.0648841858,50.386089325],"type":"Point"}
}