{
  "type": "Feature",
  "properties": {
    "iso:country":"DE",
    "sg:address":"Bahnhofstr. 8",
    "sg:city":"Kalbe",
    "sg:phone":"+49 39080/3727",
    "sg:postcode":"39624",
    "sg:province":"Sachsen-Anhalt",
    "wof:name":"E. Roese",
    "wof:placetype":"venue"
},
  "geometry": {"coordinates":[9.550326,53.29179],"type":"Point"}
}