{
  "type": "Feature",
  "properties": {
    "iso:country":"DE",
    "sg:address":"Tanzb\u00fchlweg 6",
    "sg:city":"Aichen",
    "sg:phone":"+49 8262/90079",
    "sg:postcode":"86479",
    "sg:province":"Bayern",
    "wof:name":"H. Wolf",
    "wof:placetype":"venue"
},
  "geometry": {"coordinates":[10.552222,48.211205],"type":"Point"}
}