{
  "type": "Feature",
  "properties": {
    "iso:country":"DE",
    "sg:address":"Am Sandfeld 6",
    "sg:city":"Karlsruhe",
    "sg:phone":"+49 721/556311",
    "sg:postcode":"76149",
    "sg:province":"Baden-W\u00fcrttemberg",
    "wof:name":"Vision Experts Gmbh",
    "wof:placetype":"venue"
},
  "geometry": {"coordinates":[8.3912773132,49.0437889099],"type":"Point"}
}