{
  "type": "Feature",
  "properties": {
    "iso:country":"DE",
    "sg:address":"Landwehr 130",
    "sg:city":"Schermbeck",
    "sg:phone":"+49 2853/914610",
    "sg:postcode":"46514",
    "sg:province":"Nordrhein-Westfalen",
    "wof:name":"Udo Huppers Gmbh",
    "wof:placetype":"venue"
},
  "geometry": {"coordinates":[6.874924,51.682121],"type":"Point"}
}