{
  "type": "Feature",
  "properties": {
    "iso:country":"DE",
    "sg:address":"Bachstr. 22",
    "sg:city":"Heidelberg",
    "sg:phone":"+49 6221/46048",
    "sg:postcode":"69121",
    "sg:province":"Baden-W\u00fcrttemberg",
    "wof:name":"Garrecht Immobilien- Gesellschaft Mbh",
    "wof:placetype":"venue"
},
  "geometry": {"coordinates":[8.684347,49.422333],"type":"Point"}
}