{
  "type": "Feature",
  "properties": {
    "iso:country":"DE",
    "sg:address":"Am Ladenzentrum 6",
    "sg:city":"Reinbek",
    "sg:phone":"+49 40/7222505",
    "sg:postcode":"21465",
    "sg:province":"Schleswig-Holstein",
    "wof:name":"Textilpflege Siewertsen",
    "wof:placetype":"venue"
},
  "geometry": {"coordinates":[10.23536,53.511036],"type":"Point"}
}