{
  "type": "Feature",
  "properties": {
    "iso:country":"DE",
    "sg:address":"Kulmbacher Str. 31-35",
    "sg:city":"Bad Berneck",
    "sg:phone":"+49 9273/92040",
    "sg:postcode":"95460",
    "sg:province":"Bayern",
    "wof:name":"Herzlieb Gmbh Kleeberg & Meyer",
    "wof:placetype":"venue"
},
  "geometry": {"coordinates":[11.6560726166,50.0419654846],"type":"Point"}
}