{
  "type": "Feature",
  "properties": {
    "iso:country":"DE",
    "sg:address":"Seulbitzer Str. 51",
    "sg:city":"Bayreuth",
    "sg:phone":"+49 921/970876",
    "sg:postcode":"95448",
    "sg:province":"Bayern",
    "wof:name":"Fischer Markisen",
    "wof:placetype":"venue"
},
  "geometry": {"coordinates":[11.64628,49.94347],"type":"Point"}
}