{
  "type": "Feature",
  "properties": {
    "iso:country":"DE",
    "sg:address":"Richterstr. 16",
    "sg:city":"Stuttgart",
    "sg:phone":"+49 711/713960",
    "sg:postcode":"70567",
    "sg:province":"Baden-W\u00fcrttemberg",
    "wof:name":"Biblische Missionsgemeinde Stuttgart E. V.",
    "wof:placetype":"venue"
},
  "geometry": {"coordinates":[9.1489973068,48.7272071838],"type":"Point"}
}