{
  "type": "Feature",
  "properties": {
    "iso:country":"DE",
    "sg:address":"Celsiusstr. 120",
    "sg:city":"Bonn",
    "sg:phone":"+49 228/257375",
    "sg:postcode":"53125",
    "sg:province":"Nordrhein-Westfalen",
    "wof:name":"Hamburg-mannheimer Versicherungen",
    "wof:placetype":"venue"
},
  "geometry": {"coordinates":[7.059073925,50.699508667],"type":"Point"}
}