{
  "type": "Feature",
  "properties": {
    "iso:country":"DE",
    "sg:address":"Bahnhofstr. 32",
    "sg:city":"Gersthofen",
    "sg:phone":"+49 821/473213",
    "sg:postcode":"86368",
    "sg:province":"Bayern",
    "wof:name":"Versicherungsb\u00fcro Siegfried Grob E. K.",
    "wof:placetype":"venue"
},
  "geometry": {"coordinates":[10.871720314,48.42552948],"type":"Point"}
}