{
  "type": "Feature",
  "properties": {
    "iso:country":"DE",
    "sg:address":"Kannenstieg 23",
    "sg:city":"Sch\u00f6ningen",
    "sg:phone":"+49 5352/94940",
    "sg:postcode":"38364",
    "sg:province":"Niedersachsen",
    "wof:name":"J\u00f6rg Dewitz Steuerberater",
    "wof:placetype":"venue"
},
  "geometry": {"coordinates":[10.9547452927,52.1359863281],"type":"Point"}
}