{
  "type": "Feature",
  "properties": {
    "iso:country":"DE",
    "sg:address":"Schafw\u00e4sche 4",
    "sg:city":"Heimsheim",
    "sg:phone":"+49 7033/53590",
    "sg:postcode":"71296",
    "sg:province":"Baden-W\u00fcrttemberg",
    "wof:name":"Backshop Fichtner Gmbh",
    "wof:placetype":"venue"
},
  "geometry": {"coordinates":[8.861359,48.818127],"type":"Point"}
}