{
  "type": "Feature",
  "properties": {
    "iso:country":"DE",
    "sg:address":"Alperbr\u00fcck",
    "sg:city":"Wiehl",
    "sg:phone":"+49 2262/5815",
    "sg:postcode":"51674",
    "sg:province":"Nordrhein-Westfalen",
    "wof:name":"Bergerhoff",
    "wof:placetype":"venue"
},
  "geometry": {"coordinates":[7.534446,50.961475],"type":"Point"}
}