{
  "type": "Feature",
  "properties": {
    "iso:country":"DE",
    "sg:address":"Hauptstr. 46a",
    "sg:city":"Sippersfeld",
    "sg:phone":"+49 4963/577325",
    "sg:postcode":"67729",
    "sg:province":"Rheinland-Pfalz",
    "wof:name":"Kreissparkasse Rockenhausen",
    "wof:placetype":"venue"
},
  "geometry": {"coordinates":[7.936729,49.553123],"type":"Point"}
}