{
  "type": "Feature",
  "properties": {
    "iso:country":"DE",
    "sg:address":"Mittelstr. 2",
    "sg:city":"Lausitz",
    "sg:phone":"+49 35341/2020",
    "sg:postcode":"04924",
    "sg:province":"Brandenburg",
    "wof:name":"G\u00fcnter Henze",
    "wof:placetype":"venue"
},
  "geometry": {"coordinates":[13.347725,51.513458],"type":"Point"}
}