{
  "type": "Feature",
  "properties": {
    "iso:country":"DE",
    "sg:address":"Weinbergstr. 13",
    "sg:city":"K\u00fcps",
    "sg:phone":"+49 9264/99110",
    "sg:postcode":"96328",
    "sg:province":"Bayern",
    "wof:name":"M. A. I. Verwaltungs Gmbh",
    "wof:placetype":"venue"
},
  "geometry": {"coordinates":[11.2737188339,50.1972312927],"type":"Point"}
}