{
  "type": "Feature",
  "properties": {
    "iso:country":"DE",
    "sg:address":"August Bebel Str. 8",
    "sg:city":"Ilmenau",
    "sg:phone":"+49 3677/3008",
    "sg:postcode":"98693",
    "sg:province":"Th\u00fcringen",
    "wof:name":"Deutsche Bank Ag",
    "wof:placetype":"venue"
},
  "geometry": {"coordinates":[10.918197,50.684135],"type":"Point"}
}