{
  "type": "Feature",
  "properties": {
    "iso:country":"DE",
    "sg:address":"Brederscheid 20",
    "sg:city":"Essen",
    "sg:phone":"+49 2054/4021",
    "sg:postcode":"45219",
    "sg:province":"Nordrhein-Westfalen",
    "wof:name":"R. Franke Kunstmaler",
    "wof:placetype":"venue"
},
  "geometry": {"coordinates":[6.946563,51.368176],"type":"Point"}
}