{
  "type": "Feature",
  "properties": {
    "iso:country":"DE",
    "sg:address":"Schollacker 23",
    "sg:city":"F\u00fcrth",
    "sg:phone":"+49 6253/932258",
    "sg:postcode":"64658",
    "sg:province":"Hessen",
    "wof:name":"Koczian Finanzberater",
    "wof:placetype":"venue"
},
  "geometry": {"coordinates":[8.8432130814,49.6586532593],"type":"Point"}
}