{
  "type": "Feature",
  "properties": {
    "iso:country":"DE",
    "sg:address":"M\u00f6nnigstr. 36",
    "sg:city":"K\u00f6ln",
    "sg:phone":"+49 221/5992492",
    "sg:postcode":"50737",
    "sg:province":"Nordrhein-Westfalen",
    "wof:name":"Hermann Klein",
    "wof:placetype":"venue"
},
  "geometry": {"coordinates":[6.917541,50.998142],"type":"Point"}
}