{
  "type": "Feature",
  "properties": {
    "iso:country":"DE",
    "sg:address":"Harvestehuder Weg 12",
    "sg:city":"Hamburg",
    "sg:phone":"+49 40/446121",
    "sg:postcode":"20148",
    "sg:province":"Hamburg",
    "wof:name":"Bistro",
    "wof:placetype":"venue"
},
  "geometry": {"coordinates":[9.9999456406,53.5703735352],"type":"Point"}
}