{
  "type": "Feature",
  "properties": {
    "iso:country":"DE",
    "sg:address":"M\u00fcnchener Str. 23",
    "sg:city":"Steinh\u00f6ring",
    "sg:phone":"+49 8094/1403",
    "sg:postcode":"85643",
    "sg:province":"Bayern",
    "wof:name":"C. Fischer",
    "wof:placetype":"venue"
},
  "geometry": {"coordinates":[12.0313911438,48.0865402222],"type":"Point"}
}