{
  "type": "Feature",
  "properties": {
    "iso:country":"DE",
    "sg:address":"Bruckstr. 32",
    "sg:city":"Dingolfing",
    "sg:phone":"+49 8731/2540",
    "sg:postcode":"84130",
    "sg:province":"Bayern",
    "wof:name":"S. Reicheneder",
    "wof:placetype":"venue"
},
  "geometry": {"coordinates":[12.495991,48.629803],"type":"Point"}
}