{
  "type": "Feature",
  "properties": {
    "iso:country":"DE",
    "sg:address":"In der Blankenau 14",
    "sg:city":"Husum",
    "sg:phone":"+49 5027/654",
    "sg:postcode":"31632",
    "sg:province":"Niedersachsen",
    "wof:name":"Albert Homeyer",
    "wof:placetype":"venue"
},
  "geometry": {"coordinates":[9.241557,52.59819],"type":"Point"}
}