{
  "type": "Feature",
  "properties": {
    "iso:country":"DE",
    "sg:address":"Odenwaldstr. 35",
    "sg:city":"Frankfurt",
    "sg:phone":"+49 69/674017",
    "sg:postcode":"60528",
    "sg:province":"Hessen",
    "wof:name":"H. Brodbeck",
    "wof:placetype":"venue"
},
  "geometry": {"coordinates":[8.642701149,50.0853347778],"type":"Point"}
}