{
  "type": "Feature",
  "properties": {
    "iso:country":"DE",
    "sg:address":"An der Jagst 1",
    "sg:city":"Ellwangen",
    "sg:phone":"+49 7961/6593",
    "sg:postcode":"73479",
    "sg:province":"Baden-W\u00fcrttemberg",
    "wof:name":"China Restaurant Changhai",
    "wof:placetype":"venue"
},
  "geometry": {"coordinates":[10.129529953,48.962562561],"type":"Point"}
}