{
  "type": "Feature",
  "properties": {
    "iso:country":"DE",
    "sg:address":"Froser Str. 32",
    "sg:city":"Aschersleben",
    "sg:phone":"+49 3473/817372",
    "sg:postcode":"06449",
    "sg:province":"Sachsen-Anhalt",
    "wof:name":"Ascania-maler Gmbh",
    "wof:placetype":"venue"
},
  "geometry": {"coordinates":[11.446743,51.761288],"type":"Point"}
}