{
  "type": "Feature",
  "properties": {
    "iso:country":"DE",
    "sg:address":"Bahnhofstr. 2",
    "sg:city":"Axstedt",
    "sg:phone":"+49 4793/2383",
    "sg:postcode":"27729",
    "sg:province":"Niedersachsen",
    "wof:name":"Ev. Pfarramt Hambergen",
    "wof:placetype":"venue"
},
  "geometry": {"coordinates":[8.7762556076,53.354888916],"type":"Point"}
}