{
  "type": "Feature",
  "properties": {
    "iso:country":"DE",
    "sg:address":"Biedenkopfer Str. 22",
    "sg:city":"Lahntal",
    "sg:phone":"+49 6423/6910",
    "sg:postcode":"35094",
    "sg:province":"Hessen",
    "wof:name":"Gesells.f.lagereibetr. Gmbh Getreidelager",
    "wof:placetype":"venue"
},
  "geometry": {"coordinates":[8.705693,50.862484],"type":"Point"}
}