{
  "type": "Feature",
  "properties": {
    "iso:country":"DE",
    "sg:address":"Racklstr. 2",
    "sg:city":"Prackenbach",
    "sg:phone":"+49 9944/459",
    "sg:postcode":"94267",
    "sg:province":"Bayern",
    "wof:name":"Gastst\u00e4tte Josef Freund",
    "wof:placetype":"venue"
},
  "geometry": {"coordinates":[12.8262424469,49.0935020447],"type":"Point"}
}