{
  "type": "Feature",
  "properties": {
    "iso:country":"DE",
    "sg:address":"Wilhelmstr. 5",
    "sg:city":"Riederich",
    "sg:phone":"+49 711/701995",
    "sg:postcode":"72585",
    "sg:province":"Baden-W\u00fcrttemberg",
    "wof:name":"Herbert Fellendorf Architekt",
    "wof:placetype":"venue"
},
  "geometry": {"coordinates":[9.269187,48.558006],"type":"Point"}
}