{
  "type": "Feature",
  "properties": {
    "iso:country":"DE",
    "sg:address":"Dreieichstr. 59",
    "sg:city":"Frankfurt",
    "sg:phone":"+49 69/68609050",
    "sg:postcode":"60594",
    "sg:province":"Hessen",
    "wof:name":"Rosewood Hotels & Resorts",
    "wof:placetype":"venue"
},
  "geometry": {"coordinates":[8.6914749146,50.1036071777],"type":"Point"}
}