{
  "type": "Feature",
  "properties": {
    "iso:country":"DE",
    "sg:address":"Kl\u00fctzer Str.",
    "sg:city":"Ostseebad Boltenhagen",
    "sg:postcode":"23946",
    "sg:province":"Mecklenburg-Vorpommern",
    "wof:name":"Aldi Gmbh & Co. Kg",
    "wof:placetype":"venue"
},
  "geometry": {"coordinates":[11.207734108,53.9454841614],"type":"Point"}
}