{
  "type": "Feature",
  "properties": {
    "iso:country":"DE",
    "sg:address":"Baumstr. 33",
    "sg:city":"Euskirchen",
    "sg:phone":"+49 2251/3074",
    "sg:postcode":"53879",
    "sg:province":"Nordrhein-Westfalen",
    "wof:name":"Josef Frenz",
    "wof:placetype":"venue"
},
  "geometry": {"coordinates":[6.787773,50.662235],"type":"Point"}
}