{
  "type": "Feature",
  "properties": {
    "iso:country":"DE",
    "sg:address":"Hauptstr. 14",
    "sg:city":"Friedrichshafen",
    "sg:phone":"+49 7541/52358",
    "sg:postcode":"88048",
    "sg:province":"Baden-W\u00fcrttemberg",
    "wof:name":"Pizzeria Pinocchio",
    "wof:placetype":"venue"
},
  "geometry": {"coordinates":[9.4872512817,47.6989822388],"type":"Point"}
}