{
  "type": "Feature",
  "properties": {
    "iso:country":"DE",
    "sg:address":"Buchenweg 11",
    "sg:city":"Illingen",
    "sg:phone":"+49 6825/498326",
    "sg:postcode":"66557",
    "sg:province":"Saarland",
    "wof:name":"Cybernet Professional",
    "wof:placetype":"venue"
},
  "geometry": {"coordinates":[7.0666770935,49.3883781433],"type":"Point"}
}