{
  "type": "Feature",
  "properties": {
    "iso:country":"DE",
    "sg:address":"Friedhofstr. 12",
    "sg:city":"Leibertingen",
    "sg:phone":"+49 7570/442",
    "sg:postcode":"88637",
    "sg:province":"Baden-W\u00fcrttemberg",
    "wof:name":"Hermann Maier Ingenieur",
    "wof:placetype":"venue"
},
  "geometry": {"coordinates":[9.0551462173,48.060131073],"type":"Point"}
}