{
  "type": "Feature",
  "properties": {
    "iso:country":"DE",
    "sg:address":"Marktplatz 16",
    "sg:city":"Ellwangen",
    "sg:phone":"+49 7961/2398",
    "sg:postcode":"73479",
    "sg:province":"Baden-W\u00fcrttemberg",
    "wof:name":"Theodor Richter",
    "wof:placetype":"venue"
},
  "geometry": {"coordinates":[10.131469,48.961369],"type":"Point"}
}