{
  "type": "Feature",
  "properties": {
    "iso:country":"DE",
    "sg:address":"Richard-Dehmel-Str 15",
    "sg:city":"Ahrensburg",
    "sg:phone":"+49 4102/823041",
    "sg:postcode":"22926",
    "sg:province":"Schleswig-Holstein",
    "wof:name":"M\u00f6ller Gmbh Handling- Und Transportsysteme",
    "wof:placetype":"venue"
},
  "geometry": {"coordinates":[10.226799,53.668957],"type":"Point"}
}