{
  "type": "Feature",
  "properties": {
    "iso:country":"DE",
    "sg:address":"H\u00fclzweilerstr. 53",
    "sg:city":"Schwalbach",
    "sg:phone":"+49 6834/56619",
    "sg:postcode":"66773",
    "sg:province":"Saarland",
    "wof:name":"Harald Ochmann",
    "wof:placetype":"venue"
},
  "geometry": {"coordinates":[6.821972847,49.3099060059],"type":"Point"}
}