{
  "type": "Feature",
  "properties": {
    "iso:country":"DE",
    "sg:address":"Borngasse",
    "sg:city":"Bergisch Gladbach",
    "sg:phone":"+49 2202/51462",
    "sg:postcode":"51469",
    "sg:province":"Nordrhein-Westfalen",
    "wof:name":"Stadtb\u00fccherei Paffrath",
    "wof:placetype":"venue"
},
  "geometry": {"coordinates":[7.09368,50.999226],"type":"Point"}
}