{
  "type": "Feature",
  "properties": {
    "iso:country":"DE",
    "sg:address":"Kirchgasse 6",
    "sg:city":"Alzey",
    "sg:phone":"+49 6731/41869",
    "sg:postcode":"55232",
    "sg:province":"Rheinland-Pfalz",
    "wof:name":"Katholisches Pfarramt St. Mauritius",
    "wof:placetype":"venue"
},
  "geometry": {"coordinates":[8.1135015488,49.7449111938],"type":"Point"}
}