{
  "type": "Feature",
  "properties": {
    "iso:country":"DE",
    "sg:address":"Marienthaler Str. 166",
    "sg:city":"Zwickau",
    "sg:phone":"+49 375/526518",
    "sg:postcode":"08060",
    "sg:province":"Sachsen",
    "wof:name":"M. Pirgl",
    "wof:placetype":"venue"
},
  "geometry": {"coordinates":[12.450399,50.719784],"type":"Point"}
}