{
  "type": "Feature",
  "properties": {
    "iso:country":"DE",
    "sg:address":"Dorotheenstr. 36",
    "sg:city":"Flensburg",
    "sg:phone":"+49 461/8161",
    "sg:postcode":"24939",
    "sg:province":"Schleswig-Holstein",
    "wof:name":"St. Franziskus-hospital",
    "wof:placetype":"venue"
},
  "geometry": {"coordinates":[9.41952,54.791523],"type":"Point"}
}