{
  "type": "Feature",
  "properties": {
    "iso:country":"DE",
    "sg:address":"Rietberger Str.42",
    "sg:city":"Rietberg",
    "sg:phone":"+49 2944/58400",
    "sg:postcode":"33397",
    "sg:province":"Nordrhein-Westfalen",
    "wof:name":"Euroblumen",
    "wof:placetype":"venue"
},
  "geometry": {"coordinates":[8.403935,51.763992],"type":"Point"}
}