{
  "type": "Feature",
  "properties": {
    "iso:country":"DE",
    "sg:address":"Buntzelstr. 133",
    "sg:city":"Berlin",
    "sg:phone":"+49 30/67809940",
    "sg:postcode":"12526",
    "sg:province":"Berlin",
    "wof:name":"Juliane Eickhoff Ergotherapiepraxis",
    "wof:placetype":"venue"
},
  "geometry": {"coordinates":[13.559632,52.400688],"type":"Point"}
}