{
  "type": "Feature",
  "properties": {
    "iso:country":"DE",
    "sg:address":"Drosselstr. 42",
    "sg:city":"Ottobrunn",
    "sg:phone":"+49 89/6084310",
    "sg:postcode":"85521",
    "sg:province":"Bayern",
    "wof:name":"Cornelia Schmitt",
    "wof:placetype":"venue"
},
  "geometry": {"coordinates":[11.6612024307,48.0557060242],"type":"Point"}
}