{
  "type": "Feature",
  "properties": {
    "iso:country":"DE",
    "sg:address":"Langwiesenweg 8",
    "sg:city":"Wehrheim",
    "sg:phone":"+49 6081/59476",
    "sg:postcode":"61273",
    "sg:province":"Hessen",
    "wof:name":"Karl-friedrich Keil",
    "wof:placetype":"venue"
},
  "geometry": {"coordinates":[8.5637207031,50.3037109375],"type":"Point"}
}