{
  "type": "Feature",
  "properties": {
    "iso:country":"DE",
    "sg:address":"Marktplatz 2",
    "sg:city":"Lahr",
    "sg:phone":"+49 7821/24932",
    "sg:postcode":"77933",
    "sg:province":"Baden-W\u00fcrttemberg",
    "wof:name":"Schellbach Ohg",
    "wof:placetype":"venue"
},
  "geometry": {"coordinates":[7.8716440201,48.3408432007],"type":"Point"}
}