{
  "type": "Feature",
  "properties": {
    "iso:country":"DE",
    "sg:address":"Amselweg 11",
    "sg:city":"Mayen",
    "sg:phone":"+49 2651/947046",
    "sg:postcode":"56727",
    "sg:province":"Rheinland-Pfalz",
    "wof:name":"Rotary-club Georg Grabkowsky",
    "wof:placetype":"venue"
},
  "geometry": {"coordinates":[7.2276802063,50.3329048157],"type":"Point"}
}