{
  "type": "Feature",
  "properties": {
    "iso:country":"DE",
    "sg:address":"Meierweg 3",
    "sg:city":"Bad Salzuflen",
    "sg:phone":"+49 5222/22669",
    "sg:postcode":"32108",
    "sg:province":"Nordrhein-Westfalen",
    "wof:name":"Herbert Overbeck Leasing",
    "wof:placetype":"venue"
},
  "geometry": {"coordinates":[8.761753,52.046848],"type":"Point"}
}