{
  "type": "Feature",
  "properties": {
    "iso:country":"DE",
    "sg:address":"Salzmannstr. 7",
    "sg:city":"Emmerting",
    "sg:postcode":"84547",
    "sg:province":"Bayern",
    "wof:name":"Creative Factory Of Design Gmbh",
    "wof:placetype":"venue"
},
  "geometry": {"coordinates":[12.7603,48.200092],"type":"Point"}
}