{
  "type": "Feature",
  "properties": {
    "iso:country":"DE",
    "sg:address":"Johann-Eilers-Weg 37",
    "sg:city":"Stuhr",
    "sg:phone":"+49 4221/30177",
    "sg:postcode":"28816",
    "sg:province":"Niedersachsen",
    "wof:name":"Elektro Mysegaes & Cordes Gmbh",
    "wof:placetype":"venue"
},
  "geometry": {"coordinates":[8.692166,53.037659],"type":"Point"}
}