{
  "type": "Feature",
  "properties": {
    "iso:country":"DE",
    "sg:address":"Oberstr. 2",
    "sg:city":"Wadern",
    "sg:phone":"+49 6871/8470",
    "sg:postcode":"66687",
    "sg:province":"Saarland",
    "wof:name":"Albayrat Grill Dagstuhler Hof",
    "wof:placetype":"venue"
},
  "geometry": {"coordinates":[6.8896207809,49.5403366089],"type":"Point"}
}