{
  "type": "Feature",
  "properties": {
    "iso:country":"DE",
    "sg:address":"Thalkirchner Str. 131",
    "sg:city":"M\u00fcnchen",
    "sg:phone":"+49 89/763410",
    "sg:postcode":"81371",
    "sg:province":"Bayern",
    "wof:name":"Irene Mayer",
    "wof:placetype":"venue"
},
  "geometry": {"coordinates":[11.549867,48.113293],"type":"Point"}
}