{
  "type": "Feature",
  "properties": {
    "iso:country":"DE",
    "sg:address":"Beeckstr. 1",
    "sg:city":"Aachen",
    "sg:phone":"+49 241/49475",
    "sg:postcode":"52062",
    "sg:province":"Nordrhein-Westfalen",
    "wof:name":"Wrede",
    "wof:placetype":"venue"
},
  "geometry": {"coordinates":[6.094798,50.774422],"type":"Point"}
}