{
  "type": "Feature",
  "properties": {
    "iso:country":"DE",
    "sg:address":"Marktstr. 22",
    "sg:city":"Gladenbach",
    "sg:phone":"+49 6462/6569",
    "sg:postcode":"35075",
    "sg:province":"Hessen",
    "wof:name":"Iss Was",
    "wof:placetype":"venue"
},
  "geometry": {"coordinates":[8.582775116,50.7681694031],"type":"Point"}
}