{
  "type": "Feature",
  "properties": {
    "iso:country":"DE",
    "sg:address":"Marburger Tor 23",
    "sg:city":"Siegen",
    "sg:postcode":"57072",
    "sg:province":"Nordrhein-Westfalen",
    "wof:name":"Erotische Schiffahrt Beverly 2001",
    "wof:placetype":"venue"
},
  "geometry": {"coordinates":[8.029371,50.876678],"type":"Point"}
}