{
  "type": "Feature",
  "properties": {
    "iso:country":"DE",
    "sg:address":"Dorfstr. 36",
    "sg:city":"Gro\u00df Gottschow",
    "sg:phone":"+49 38784/60328",
    "sg:postcode":"19348",
    "sg:province":"Brandenburg",
    "wof:name":"Landmaschinen-technik Gro\u00df-gottschow Gmbh",
    "wof:placetype":"venue"
},
  "geometry": {"coordinates":[11.993739,53.148968],"type":"Point"}
}