{
  "type": "Feature",
  "properties": {
    "iso:country":"DE",
    "sg:address":"Breite Str. 2",
    "sg:city":"Gittelde",
    "sg:phone":"+49 4953/274181",
    "sg:postcode":"37534",
    "sg:province":"Niedersachsen",
    "wof:name":"Sparkasse Im Kreis Osterode",
    "wof:placetype":"venue"
},
  "geometry": {"coordinates":[10.185869,51.797935],"type":"Point"}
}