{
  "type": "Feature",
  "properties": {
    "iso:country":"DE",
    "sg:address":"Schwarzburgstr. 69",
    "sg:city":"Frankfurt",
    "sg:phone":"+49 69/59796513",
    "sg:postcode":"60318",
    "sg:province":"Hessen",
    "wof:name":"Organisation & Personal Gmbh",
    "wof:placetype":"venue"
},
  "geometry": {"coordinates":[8.683612,50.127094],"type":"Point"}
}