{
  "type": "Feature",
  "properties": {
    "iso:country":"DE",
    "sg:address":"Stauffenbergring 23",
    "sg:city":"Olpe",
    "sg:phone":"+49 2761/62299",
    "sg:postcode":"57462",
    "sg:province":"Nordrhein-Westfalen",
    "wof:name":"Paul Hoberg",
    "wof:placetype":"venue"
},
  "geometry": {"coordinates":[7.857033,51.041077],"type":"Point"}
}