{
  "type": "Feature",
  "properties": {
    "iso:country":"DE",
    "sg:address":"Gabelsbergerstr. 11b-13",
    "sg:city":"Herne",
    "sg:phone":"+49 2325/3856",
    "sg:postcode":"44652",
    "sg:province":"Nordrhein-Westfalen",
    "wof:name":"Ebv Hartke Elektrohandels Beteiligungs- Und",
    "wof:placetype":"venue"
},
  "geometry": {"coordinates":[7.16417,51.522137],"type":"Point"}
}