{
  "type": "Feature",
  "properties": {
    "iso:country":"DE",
    "sg:address":"Eglhartinger Str. 304",
    "sg:city":"Kirchseeon",
    "sg:phone":"+49 8091/9739",
    "sg:postcode":"85614",
    "sg:province":"Bayern",
    "wof:name":"Jet-tankstelle",
    "wof:placetype":"venue"
},
  "geometry": {"coordinates":[11.8586835861,48.0818252563],"type":"Point"}
}