{
  "type": "Feature",
  "properties": {
    "iso:country":"DE",
    "sg:address":"gotmarstra\u00dfe 3",
    "sg:city":"g\u00f6ttingen",
    "sg:phone":"+49 551/5315989",
    "sg:postcode":"37073",
    "sg:province":"Niedersachsen",
    "wof:name":"Minimaxi Schuhe",
    "wof:placetype":"venue"
},
  "geometry": {"coordinates":[9.9337368011,51.5341110229],"type":"Point"}
}