{
  "type": "Feature",
  "properties": {
    "iso:country":"DE",
    "sg:address":"Hans-Sachs-Str. 4",
    "sg:city":"M\u00fcnchen",
    "sg:phone":"+49 89/2605257",
    "sg:postcode":"80469",
    "sg:province":"Bayern",
    "wof:name":"Kaltenegger Und Stettner Anlageberater",
    "wof:placetype":"venue"
},
  "geometry": {"coordinates":[11.5699710846,48.1305427551],"type":"Point"}
}