{
  "type": "Feature",
  "properties": {
    "iso:country":"DE",
    "sg:address":"Darwinstr. 12",
    "sg:city":"Hannover",
    "sg:postcode":"30165",
    "sg:province":"Niedersachsen",
    "wof:name":"Potato Point Mitte Gmbh",
    "wof:placetype":"venue"
},
  "geometry": {"coordinates":[9.7281036377,52.3914031982],"type":"Point"}
}