{
  "type": "Feature",
  "properties": {
    "iso:country":"DE",
    "sg:address":"Albert- Schlangenstr. 42",
    "sg:city":"Bedburg",
    "sg:phone":"+49 2272/938553",
    "sg:postcode":"50181",
    "sg:province":"Nordrhein-Westfalen",
    "wof:name":"Friedhelm Hunold",
    "wof:placetype":"venue"
},
  "geometry": {"coordinates":[6.5431470871,51.0031013489],"type":"Point"}
}