{
  "type": "Feature",
  "properties": {
    "iso:country":"DE",
    "sg:address":"Im Kirchbr\u00e4ndel 26",
    "sg:city":"Bad Sch\u00f6nborn",
    "sg:phone":"+49 7253/4740",
    "sg:postcode":"76669",
    "sg:province":"Baden-W\u00fcrttemberg",
    "wof:name":"Wolfgang Baumg\u00e4rtner Steuerberater",
    "wof:placetype":"venue"
},
  "geometry": {"coordinates":[8.6527309418,49.20753479],"type":"Point"}
}