{
  "type": "Feature",
  "properties": {
    "iso:country":"DE",
    "sg:address":"Furtgasse 4",
    "sg:city":"Vilshofen",
    "sg:phone":"+49 8541/910001",
    "sg:postcode":"94474",
    "sg:province":"Bayern",
    "wof:name":"Nkd Vertrieb",
    "wof:placetype":"venue"
},
  "geometry": {"coordinates":[13.1946763992,48.593547821],"type":"Point"}
}