{
  "type": "Feature",
  "properties": {
    "iso:country":"DE",
    "sg:address":"Schinkelring 10",
    "sg:city":"Norderstedt",
    "sg:phone":"+49 40/52630782",
    "sg:postcode":"22844",
    "sg:province":"Schleswig-Holstein",
    "wof:name":"Pfaffenberger & Steinbi\u00df Gmbh",
    "wof:placetype":"venue"
},
  "geometry": {"coordinates":[10.006064415,53.7115516663],"type":"Point"}
}