{
  "type": "Feature",
  "properties": {
    "iso:country":"DE",
    "sg:address":"Am S\u00fcdhang 41c",
    "sg:city":"Bielefeld",
    "sg:postcode":"33739",
    "sg:province":"Nordrhein-Westfalen",
    "wof:name":"Lautz-oberwelland Gmbh & Co. Kg",
    "wof:placetype":"venue"
},
  "geometry": {"coordinates":[8.5204124451,52.0668754578],"type":"Point"}
}