{
  "type": "Feature",
  "properties": {
    "iso:country":"DE",
    "sg:address":"Postfach 1225:: 22859 Schenefeld:: Germany.^^Blankeneser Chaussee 10::",
    "sg:city":"Schenefeld",
    "sg:phone":"+49 40/8393350",
    "sg:postcode":"22869",
    "sg:province":"Schleswig-Holstein",
    "wof:name":"Vr-bank Halstenbek-schenefeld Eg",
    "wof:placetype":"venue"
},
  "geometry": {"coordinates":[9.837515,53.600239],"type":"Point"}
}