{
  "type": "Feature",
  "properties": {
    "iso:country":"DE",
    "sg:address":"Goethestr. 10",
    "sg:city":"Helmstedt",
    "sg:phone":"+49 5351/2008",
    "sg:postcode":"38350",
    "sg:province":"Niedersachsen",
    "wof:name":"Dorothea Rybotycky Steuerberaterin",
    "wof:placetype":"venue"
},
  "geometry": {"coordinates":[11.0178699493,52.2284393311],"type":"Point"}
}