{
  "type": "Feature",
  "properties": {
    "iso:country":"DE",
    "sg:address":"Neuer Weg 41",
    "sg:city":"Wolfenb\u00fcttel",
    "sg:phone":"+49 5331/71519",
    "sg:postcode":"38302",
    "sg:province":"Niedersachsen",
    "wof:name":"Friedrich Linne",
    "wof:placetype":"venue"
},
  "geometry": {"coordinates":[10.537721,52.179092],"type":"Point"}
}