{
  "type": "Feature",
  "properties": {
    "iso:country":"DE",
    "sg:address":"M\u00f6nkhofer Weg 50",
    "sg:city":"L\u00fcbeck",
    "sg:phone":"+49 451/593700",
    "sg:postcode":"23562",
    "sg:province":"Schleswig-Holstein",
    "wof:name":"Goldrei Reinigung",
    "wof:placetype":"venue"
},
  "geometry": {"coordinates":[10.698609,53.849522],"type":"Point"}
}