{
  "type": "Feature",
  "properties": {
    "iso:country":"DE",
    "sg:address":"Lehnitzstr. 19",
    "sg:city":"Oranienburg",
    "sg:phone":"+49 3301/529824",
    "sg:postcode":"16515",
    "sg:province":"Brandenburg",
    "wof:name":"K. Gohlisch",
    "wof:placetype":"venue"
},
  "geometry": {"coordinates":[13.242718,52.754337],"type":"Point"}
}