{
  "type": "Feature",
  "properties": {
    "iso:country":"DE",
    "sg:address":"Georgstr. 34",
    "sg:city":"Hannover",
    "sg:postcode":"30159",
    "sg:province":"Niedersachsen",
    "wof:name":"Eicke Beteiligungsges. Mbh",
    "wof:placetype":"venue"
},
  "geometry": {"coordinates":[9.739287,52.373322],"type":"Point"}
}