{
  "type": "Feature",
  "properties": {
    "iso:country":"DE",
    "sg:address":"Ehrwalder Str. 85",
    "sg:city":"M\u00fcnchen",
    "sg:phone":"+49 89/7141011",
    "sg:postcode":"81377",
    "sg:province":"Bayern",
    "wof:name":"Thomas Obermiller Rechtsanwalt",
    "wof:placetype":"venue"
},
  "geometry": {"coordinates":[11.5038309097,48.1163406372],"type":"Point"}
}