{
  "type": "Feature",
  "properties": {
    "iso:country":"DE",
    "sg:address":"M\u00fcnchener Str. 15",
    "sg:city":"W\u00e4chtersbach",
    "sg:phone":"+49 6053/1393",
    "sg:postcode":"63607",
    "sg:province":"Hessen",
    "wof:name":"Ph\u00f6nix Gmbh",
    "wof:placetype":"venue"
},
  "geometry": {"coordinates":[9.3172082901,50.2496910095],"type":"Point"}
}