{
  "type": "Feature",
  "properties": {
    "iso:country":"DE",
    "sg:address":"Elgerter Str. 54",
    "sg:city":"Dierdorf",
    "sg:phone":"+49 2689/3527",
    "sg:postcode":"56269",
    "sg:province":"Rheinland-Pfalz",
    "wof:name":"Helmut Eyl",
    "wof:placetype":"venue"
},
  "geometry": {"coordinates":[7.6630210876,50.5528945923],"type":"Point"}
}