{
  "type": "Feature",
  "properties": {
    "iso:country":"DE",
    "sg:address":"Hauptstr. 11",
    "sg:city":"Meitingen",
    "sg:phone":"+49 8271/2336",
    "sg:postcode":"86405",
    "sg:province":"Bayern",
    "wof:name":"Josef Liepert",
    "wof:placetype":"venue"
},
  "geometry": {"coordinates":[10.851504,48.546169],"type":"Point"}
}