{
  "type": "Feature",
  "properties": {
    "iso:country":"DE",
    "sg:address":"Fuldastr. 9 a",
    "sg:city":"Baunatal",
    "sg:postcode":"34225",
    "sg:province":"Hessen",
    "wof:name":"Men\u00fc Bring-dienst Gmbh Essen Auf R\u00e4dern",
    "wof:placetype":"venue"
},
  "geometry": {"coordinates":[9.43069,51.228958],"type":"Point"}
}