{
  "type": "Feature",
  "properties": {
    "iso:country":"DE",
    "sg:address":"Halderstr 3",
    "sg:city":"Augsburg",
    "sg:phone":"+49 821/32551701",
    "sg:postcode":"86150",
    "sg:province":"Bayern",
    "wof:name":"Stadtsparkasse",
    "wof:placetype":"venue"
},
  "geometry": {"coordinates":[10.892236,48.364906],"type":"Point"}
}