{
  "type": "Feature",
  "properties": {
    "iso:country":"DE",
    "sg:address":"Goerdelerstr. 10",
    "sg:city":"Apolda",
    "sg:phone":"+49 3644/554346",
    "sg:postcode":"99510",
    "sg:province":"Th\u00fcringen",
    "wof:name":"J\u00fcrgen Koch",
    "wof:placetype":"venue"
},
  "geometry": {"coordinates":[11.5144920349,51.024307251],"type":"Point"}
}