{
  "type": "Feature",
  "properties": {
    "iso:country":"DE",
    "sg:address":"Klosterstr. 2",
    "sg:city":"Gransee",
    "sg:postcode":"16775",
    "sg:province":"Brandenburg",
    "wof:name":"Evangelisches Pfarramt Ii",
    "wof:placetype":"venue"
},
  "geometry": {"coordinates":[13.1578598022,53.0086288452],"type":"Point"}
}