{
  "type": "Feature",
  "properties": {
    "iso:country":"DE",
    "sg:address":"Marienwerderstr. 17",
    "sg:city":"Finowfurt",
    "sg:phone":"+49 3335/7128",
    "sg:postcode":"16244",
    "sg:province":"Brandenburg",
    "wof:name":"Lothar Kirchhoff",
    "wof:placetype":"venue"
},
  "geometry": {"coordinates":[13.6790752411,52.8502655029],"type":"Point"}
}