{
  "type": "Feature",
  "properties": {
    "iso:country":"DE",
    "sg:address":"Arvid-Harnack-Str. 13",
    "sg:city":"Jena",
    "sg:phone":"+49 3641/441143",
    "sg:postcode":"07743",
    "sg:province":"Th\u00fcringen",
    "wof:name":"F. Wohlleben",
    "wof:placetype":"venue"
},
  "geometry": {"coordinates":[11.5889358521,50.9328689575],"type":"Point"}
}