{
  "type": "Feature",
  "properties": {
    "iso:country":"DE",
    "sg:address":"Gustav-Ricker-Str. 63",
    "sg:city":"Magdeburg",
    "sg:phone":"+49 391/6262600",
    "sg:postcode":"39120",
    "sg:province":"Sachsen-Anhalt",
    "wof:name":"Maco Gmbh",
    "wof:placetype":"venue"
},
  "geometry": {"coordinates":[11.6359596252,52.0794334412],"type":"Point"}
}