{
  "type": "Feature",
  "properties": {
    "iso:country":"DE",
    "sg:address":"Am Grubenbahnhof 4",
    "sg:city":"Friedrichsthal",
    "sg:phone":"+49 6897/8207",
    "sg:postcode":"66299",
    "sg:province":"Saarland",
    "wof:name":"Peter Th\u00f6s Gmbh",
    "wof:placetype":"venue"
},
  "geometry": {"coordinates":[7.071115,49.322041],"type":"Point"}
}