{
  "type": "Feature",
  "properties": {
    "iso:country":"DE",
    "sg:address":"Ludwigsh\u00f6he 8",
    "sg:city":"F\u00fcrstenfeldbruck",
    "sg:phone":"+49 8141/92470",
    "sg:postcode":"82256",
    "sg:province":"Bayern",
    "wof:name":"Geophysikalisches Observatorium Der",
    "wof:placetype":"venue"
},
  "geometry": {"coordinates":[11.2507343292,48.1776847839],"type":"Point"}
}