{
  "type": "Feature",
  "properties": {
    "iso:country":"DE",
    "sg:address":"Guthrater Weg 7",
    "sg:city":"Schnaitsee",
    "sg:phone":"+49 8074/257",
    "sg:postcode":"83530",
    "sg:province":"Bayern",
    "wof:name":"Dr. Med. Hartmut Mandetzky Arzt F\u00fcr Allgemeinmedizin",
    "wof:placetype":"venue"
},
  "geometry": {"coordinates":[12.3665895462,48.0707588196],"type":"Point"}
}