{
  "type": "Feature",
  "properties": {
    "iso:country":"DE",
    "sg:address":"Alte Heerstr. 18",
    "sg:city":"Rosdorf",
    "sg:phone":"+49 5502/2360",
    "sg:postcode":"37124",
    "sg:province":"Niedersachsen",
    "wof:name":"Helmut Sucher",
    "wof:placetype":"venue"
},
  "geometry": {"coordinates":[9.84152,51.508862],"type":"Point"}
}