{
  "type": "Feature",
  "properties": {
    "iso:country":"DE",
    "sg:address":"Th\u00fcringer Str. 73",
    "sg:city":"Oberhausen",
    "sg:phone":"+49 208/653880",
    "sg:postcode":"46149",
    "sg:province":"Nordrhein-Westfalen",
    "wof:name":"Annemarie Altendorfer-muhra",
    "wof:placetype":"venue"
},
  "geometry": {"coordinates":[6.8242092133,51.5007972717],"type":"Point"}
}