{
  "type": "Feature",
  "properties": {
    "iso:country":"DE",
    "sg:address":"Schacktor",
    "sg:city":"Bad Langensalza",
    "sg:postcode":"99947",
    "sg:province":"Th\u00fcringen",
    "wof:name":"Kartoffelaufbereitungs- Und Lagerungs Gmbh",
    "wof:placetype":"venue"
},
  "geometry": {"coordinates":[10.6305751801,51.0468788147],"type":"Point"}
}