{
  "type": "Feature",
  "properties": {
    "iso:country":"DE",
    "sg:address":"Sonnenhalde 7",
    "sg:city":"Lichtenstein",
    "sg:phone":"+49 7129/4210",
    "sg:postcode":"72805",
    "sg:province":"Baden-W\u00fcrttemberg",
    "wof:name":"Felicitas Reiff",
    "wof:placetype":"venue"
},
  "geometry": {"coordinates":[9.2592401505,48.42918396],"type":"Point"}
}