{
  "type": "Feature",
  "properties": {
    "iso:country":"DE",
    "sg:address":"Crailsheimer Str. 32",
    "sg:city":"Ilshofen",
    "sg:phone":"+49 7904/237",
    "sg:postcode":"74532",
    "sg:province":"Baden-W\u00fcrttemberg",
    "wof:name":"O. Freim\u00fcller",
    "wof:placetype":"venue"
},
  "geometry": {"coordinates":[9.9264316559,49.1712379456],"type":"Point"}
}