{
  "type": "Feature",
  "properties": {
    "iso:country":"DE",
    "sg:address":"Spie\u00dfgasse 24",
    "sg:city":"Alzey",
    "sg:phone":"+49 6731/2352",
    "sg:postcode":"55232",
    "sg:province":"Rheinland-Pfalz",
    "wof:name":"Irmgard Hein",
    "wof:placetype":"venue"
},
  "geometry": {"coordinates":[8.1113681793,49.7454223633],"type":"Point"}
}