{
  "type": "Feature",
  "properties": {
    "iso:country":"DE",
    "sg:address":"Johanniterstr. 125",
    "sg:city":"Duisburg",
    "sg:phone":"+49 203/63562",
    "sg:postcode":"47053",
    "sg:province":"Nordrhein-Westfalen",
    "wof:name":"Ulrich Blankenburg",
    "wof:placetype":"venue"
},
  "geometry": {"coordinates":[6.76427,51.418068],"type":"Point"}
}