{
  "type": "Feature",
  "properties": {
    "iso:country":"DE",
    "sg:address":"Flutstr. 208",
    "sg:city":"Wilhelmshaven",
    "sg:phone":"+49 4421/504274",
    "sg:postcode":"26388",
    "sg:province":"Niedersachsen",
    "wof:name":"Restaurant La Terrazza",
    "wof:placetype":"venue"
},
  "geometry": {"coordinates":[8.103603363,53.5857315063],"type":"Point"}
}