{
  "type": "Feature",
  "properties": {
    "iso:country":"DE",
    "sg:address":"Bayernstr. 20",
    "sg:city":"Sulzbach",
    "sg:phone":"+49 6897/87300",
    "sg:postcode":"66280",
    "sg:province":"Saarland",
    "wof:name":"Bohrmann",
    "wof:placetype":"venue"
},
  "geometry": {"coordinates":[7.0813069344,49.3067169189],"type":"Point"}
}