{
  "type": "Feature",
  "properties": {
    "iso:country":"DE",
    "sg:address":"Hatzfelder Weg 13 c",
    "sg:city":"M\u00fcnchen",
    "sg:phone":"+49 89/7555418",
    "sg:postcode":"81476",
    "sg:province":"Bayern",
    "wof:name":"Prankl Gmbh Dach- Und Wandprofile",
    "wof:placetype":"venue"
},
  "geometry": {"coordinates":[11.504263,48.098305],"type":"Point"}
}