{
  "type": "Feature",
  "properties": {
    "iso:country":"DE",
    "sg:address":"Am Wehrbusch 19",
    "sg:city":"Laatzen",
    "sg:phone":"+49 511/221348",
    "sg:postcode":"30880",
    "sg:province":"Niedersachsen",
    "wof:name":"A. Keskin",
    "wof:placetype":"venue"
},
  "geometry": {"coordinates":[9.807595,52.306152],"type":"Point"}
}