{
  "type": "Feature",
  "properties": {
    "iso:country":"DE",
    "sg:address":"B\u00f6rnigeweg 15",
    "sg:city":"M\u00f6hnesee",
    "sg:phone":"+49 2924/1513",
    "sg:postcode":"59519",
    "sg:province":"Nordrhein-Westfalen",
    "wof:name":"K. Rocholl",
    "wof:placetype":"venue"
},
  "geometry": {"coordinates":[8.1287355423,51.4938011169],"type":"Point"}
}