{
  "type": "Feature",
  "properties": {
    "iso:country":"DE",
    "sg:address":"Diestedder Str. 48",
    "sg:city":"Lippetal",
    "sg:phone":"+49 2923/1054",
    "sg:postcode":"59510",
    "sg:province":"Nordrhein-Westfalen",
    "wof:name":"Bella Italia",
    "wof:placetype":"venue"
},
  "geometry": {"coordinates":[8.1520223618,51.6795845032],"type":"Point"}
}