{
  "type": "Feature",
  "properties": {
    "iso:country":"DE",
    "sg:address":"Schulte-Heuthaus-Str. 24",
    "sg:city":"Dortmund",
    "sg:phone":"+49 231/61286",
    "sg:postcode":"44379",
    "sg:province":"Nordrhein-Westfalen",
    "wof:name":"Dirk Ittner",
    "wof:placetype":"venue"
},
  "geometry": {"coordinates":[7.384839,51.508274],"type":"Point"}
}