{
  "type": "Feature",
  "properties": {
    "iso:country":"DE",
    "sg:address":"Parkstr. 26",
    "sg:city":"Riedlingen",
    "sg:phone":"+49 7371/2372",
    "sg:postcode":"88499",
    "sg:province":"Baden-W\u00fcrttemberg",
    "wof:name":"Fidel Gehweiler",
    "wof:placetype":"venue"
},
  "geometry": {"coordinates":[9.45011,48.16853],"type":"Point"}
}