{
  "type": "Feature",
  "properties": {
    "iso:country":"DE",
    "sg:address":"Teichstr. 30",
    "sg:city":"Bielefeld",
    "sg:phone":"+49 521/66685",
    "sg:postcode":"33615",
    "sg:province":"Nordrhein-Westfalen",
    "wof:name":"Heywinkel Gmbh",
    "wof:placetype":"venue"
},
  "geometry": {"coordinates":[8.5269641876,52.0289916992],"type":"Point"}
}