{
  "type": "Feature",
  "properties": {
    "iso:country":"DE",
    "sg:address":"Waldstr. 29",
    "sg:city":"Asbach",
    "sg:phone":"+49 2683/43438",
    "sg:postcode":"53567",
    "sg:province":"Rheinland-Pfalz",
    "wof:name":"Hans-werner Schumacher",
    "wof:placetype":"venue"
},
  "geometry": {"coordinates":[7.422287,50.673698],"type":"Point"}
}