{
  "type": "Feature",
  "properties": {
    "iso:country":"DE",
    "sg:address":"Hauptstr. 33",
    "sg:city":"Schiffweiler",
    "sg:phone":"+49 6821/6209",
    "sg:postcode":"66578",
    "sg:province":"Saarland",
    "wof:name":"Saalbau",
    "wof:placetype":"venue"
},
  "geometry": {"coordinates":[7.1314268112,49.3690948486],"type":"Point"}
}