{
  "type": "Feature",
  "properties": {
    "iso:country":"DE",
    "sg:address":"Konstantinstr. 83",
    "sg:city":"M\u00f6nchengladbach",
    "sg:phone":"+49 2166/81705",
    "sg:postcode":"41238",
    "sg:province":"Nordrhein-Westfalen",
    "wof:name":"Am Sternenfeld",
    "wof:placetype":"venue"
},
  "geometry": {"coordinates":[6.4834938049,51.1571960449],"type":"Point"}
}