{
  "type": "Feature",
  "properties": {
    "iso:country":"DE",
    "sg:address":"Am M\u00fchlenturm 2",
    "sg:city":"Alpen",
    "sg:phone":"+49 2802/70339",
    "sg:postcode":"46519",
    "sg:province":"Nordrhein-Westfalen",
    "wof:name":"I. Und B. Rochel",
    "wof:placetype":"venue"
},
  "geometry": {"coordinates":[6.5120811462,51.5727348328],"type":"Point"}
}