{
  "type": "Feature",
  "properties": {
    "iso:country":"DE",
    "sg:address":"Siemensstr. 2",
    "sg:city":"Friedrichshafen",
    "sg:phone":"+49 7541/53010",
    "sg:postcode":"88048",
    "sg:province":"Baden-W\u00fcrttemberg",
    "wof:name":"Bruno Pfaff Gmbh",
    "wof:placetype":"venue"
},
  "geometry": {"coordinates":[9.479501,47.679165],"type":"Point"}
}