{
  "type": "Feature",
  "properties": {
    "iso:country":"DE",
    "sg:address":"Wiclefstr. 17",
    "sg:city":"Berlin",
    "sg:phone":"+49 30/3973850",
    "sg:postcode":"10551",
    "sg:province":"Berlin",
    "wof:name":"Versorgungstechnik Ossege & Co. Gmbh",
    "wof:placetype":"venue"
},
  "geometry": {"coordinates":[13.335072,52.530632],"type":"Point"}
}