{
  "type": "Feature",
  "properties": {
    "iso:country":"DE",
    "sg:address":"Teckelstr. 2",
    "sg:city":"Preu\u00dfisch Oldendorf",
    "sg:phone":"+49 5743/8319",
    "sg:postcode":"32361",
    "sg:province":"Nordrhein-Westfalen",
    "wof:name":"H. Hafer Landhandel",
    "wof:placetype":"venue"
},
  "geometry": {"coordinates":[8.538337,52.339027],"type":"Point"}
}