{
  "type": "Feature",
  "properties": {
    "iso:country":"DE",
    "sg:address":"Hufelandstr. 10",
    "sg:city":"Bad K\u00f6sen",
    "sg:postcode":"06628",
    "sg:province":"Sachsen-Anhalt",
    "wof:name":"\u00d6ttner Transport Gmbh",
    "wof:placetype":"venue"
},
  "geometry": {"coordinates":[11.7268857956,51.128944397],"type":"Point"}
}