{
  "type": "Feature",
  "properties": {
    "iso:country":"DE",
    "sg:address":"Stiftstr. 17",
    "sg:city":"Minden",
    "sg:phone":"+49 571/29902",
    "sg:postcode":"32427",
    "sg:province":"Nordrhein-Westfalen",
    "wof:name":"Wiese Architekt",
    "wof:placetype":"venue"
},
  "geometry": {"coordinates":[8.913009,52.294029],"type":"Point"}
}