{
  "type": "Feature",
  "properties": {
    "iso:country":"DE",
    "sg:address":"Paderberg 1",
    "sg:city":"Paderborn",
    "sg:postcode":"33098",
    "sg:province":"Nordrhein-Westfalen",
    "wof:name":"Gestern Und Heute - Art-antik Handelsgesellschaft Mbh",
    "wof:placetype":"venue"
},
  "geometry": {"coordinates":[8.751326561,51.717792511],"type":"Point"}
}