{
  "type": "Feature",
  "properties": {
    "iso:country":"DE",
    "sg:address":"An der Falkschule 4",
    "sg:city":"Hamm",
    "sg:phone":"+49 2381/461655",
    "sg:postcode":"59077",
    "sg:province":"Nordrhein-Westfalen",
    "wof:name":"Ingrid Heimann",
    "wof:placetype":"venue"
},
  "geometry": {"coordinates":[7.7441267967,51.6602592468],"type":"Point"}
}