{
  "type": "Feature",
  "properties": {
    "iso:country":"DE",
    "sg:address":"R\u00f6mer 8",
    "sg:city":"Kleinwallstadt",
    "sg:phone":"+49 6022/21309",
    "sg:postcode":"63839",
    "sg:province":"Bayern",
    "wof:name":"Gerhard Labudda",
    "wof:placetype":"venue"
},
  "geometry": {"coordinates":[9.1649913788,49.8728103638],"type":"Point"}
}