{
  "type": "Feature",
  "properties": {
    "iso:country":"DE",
    "sg:address":"Dorfstr. 9",
    "sg:city":"R\u00fcdnitz",
    "sg:postcode":"16321",
    "sg:province":"Brandenburg",
    "wof:name":"Sandra Sanierungsges. Mbh",
    "wof:placetype":"venue"
},
  "geometry": {"coordinates":[13.6222753525,52.7218551636],"type":"Point"}
}