{
  "type": "Feature",
  "properties": {
    "iso:country":"DE",
    "sg:address":"Gli\u00dfmannweg 1",
    "sg:city":"Hamburg",
    "sg:postcode":"22457",
    "sg:province":"Hamburg",
    "wof:name":"Musikschule Schnelsen",
    "wof:placetype":"venue"
},
  "geometry": {"coordinates":[9.9188966751,53.6347007751],"type":"Point"}
}