{
  "type": "Feature",
  "properties": {
    "iso:country":"DE",
    "sg:address":"Uhlandstr 28",
    "sg:city":"Bietigheim-Bissingen",
    "sg:phone":"+49 7142/940476",
    "sg:postcode":"74321",
    "sg:province":"Baden-W\u00fcrttemberg",
    "wof:name":"Bhu Umwelttechnik Gmbh",
    "wof:placetype":"venue"
},
  "geometry": {"coordinates":[9.1340084076,48.9575424194],"type":"Point"}
}