{
  "type": "Feature",
  "properties": {
    "iso:country":"DE",
    "sg:address":"Am Brunkelsberg 1",
    "sg:city":"Guxhagen",
    "sg:phone":"+49 5665/1264",
    "sg:postcode":"34302",
    "sg:province":"Hessen",
    "wof:name":"Gerhard Dittmar",
    "wof:placetype":"venue"
},
  "geometry": {"coordinates":[9.461063,51.205765],"type":"Point"}
}