{
  "type": "Feature",
  "properties": {
    "iso:country":"DE",
    "sg:address":"Industriestr 8",
    "sg:city":"Trossingen",
    "sg:phone":"+49 7425/94990",
    "sg:postcode":"78647",
    "sg:province":"Baden-W\u00fcrttemberg",
    "wof:name":"Hans Koch Gmbh & Co",
    "wof:placetype":"venue"
},
  "geometry": {"coordinates":[8.617583,48.074341],"type":"Point"}
}