{
  "type": "Feature",
  "properties": {
    "iso:country":"DE",
    "sg:address":"Haiterbacher Str. 9",
    "sg:city":"Nagold",
    "sg:phone":"+49 7452/4854",
    "sg:postcode":"72202",
    "sg:province":"Baden-W\u00fcrttemberg",
    "wof:name":"Mac Kee-jeans Gmbh",
    "wof:placetype":"venue"
},
  "geometry": {"coordinates":[8.7273902893,48.5489120483],"type":"Point"}
}