{
  "type": "Feature",
  "properties": {
    "iso:country":"DE",
    "sg:address":"Rosenheimer Str. 4",
    "sg:city":"Bad Aibling",
    "sg:phone":"+49 8061/7258",
    "sg:postcode":"83043",
    "sg:province":"Bayern",
    "wof:name":"Rosen-apotheke",
    "wof:placetype":"venue"
},
  "geometry": {"coordinates":[12.01076,47.863106],"type":"Point"}
}