{
  "type": "Feature",
  "properties": {
    "iso:country":"DE",
    "sg:address":"Kr\u00e4henstr. 29",
    "sg:city":"L\u00fcbeck",
    "sg:phone":"+49 451/75230",
    "sg:postcode":"23552",
    "sg:province":"Schleswig-Holstein",
    "wof:name":"Fleischerei U. Kleinfeldt E.k.",
    "wof:placetype":"venue"
},
  "geometry": {"coordinates":[10.6928787231,53.8641738892],"type":"Point"}
}