{
  "type": "Feature",
  "properties": {
    "iso:country":"DE",
    "sg:address":"Gewerbegebiet Rommersch",
    "sg:city":"Lippetal",
    "sg:phone":"+49 2527/8717",
    "sg:postcode":"59510",
    "sg:province":"Nordrhein-Westfalen",
    "wof:name":"Holzbau Frigge",
    "wof:placetype":"venue"
},
  "geometry": {"coordinates":[8.050721,51.657673],"type":"Point"}
}