{
  "type": "Feature",
  "properties": {
    "iso:country":"DE",
    "sg:address":"Osterstr. 13",
    "sg:city":"Hameln",
    "sg:phone":"+49 5151/941220",
    "sg:postcode":"31785",
    "sg:province":"Niedersachsen",
    "wof:name":"New Yorker S. H. K. Jeans Gmbh",
    "wof:placetype":"venue"
},
  "geometry": {"coordinates":[9.359171,52.104618],"type":"Point"}
}