{
  "type": "Feature",
  "properties": {
    "iso:country":"DE",
    "sg:address":"Werkstr 1-5",
    "sg:city":"Bielefeld",
    "sg:phone":"+49 521/9773900",
    "sg:postcode":"33729",
    "sg:province":"Nordrhein-Westfalen",
    "wof:name":"Uffmann Lackierbetrieb Gmbh",
    "wof:placetype":"venue"
},
  "geometry": {"coordinates":[8.5822286606,52.066986084],"type":"Point"}
}