{
  "type": "Feature",
  "properties": {
    "iso:country":"DE",
    "sg:address":"Friedhofstr. 42",
    "sg:city":"Hattenhofen",
    "sg:phone":"+49 7164/3195",
    "sg:postcode":"73110",
    "sg:province":"Baden-W\u00fcrttemberg",
    "wof:name":"Sommerfeldt Eisenbahn Modelle Gmbh",
    "wof:placetype":"venue"
},
  "geometry": {"coordinates":[9.5571422577,48.6653137207],"type":"Point"}
}