{
  "type": "Feature",
  "properties": {
    "iso:country":"DE",
    "sg:address":"Neue Str. 35",
    "sg:city":"Hamburg",
    "sg:phone":"+49 40/7665971",
    "sg:postcode":"21073",
    "sg:province":"Hamburg",
    "wof:name":"Restaurant Mercarto",
    "wof:placetype":"venue"
},
  "geometry": {"coordinates":[9.9793310165,53.4608192444],"type":"Point"}
}