{
  "type": "Feature",
  "properties": {
    "iso:country":"DE",
    "sg:address":"Holbeinstr 2",
    "sg:city":"M\u00fcnchen",
    "sg:phone":"+49 89/45747430",
    "sg:postcode":"81679",
    "sg:province":"Bayern",
    "wof:name":"Up2date.it Gmbh",
    "wof:placetype":"venue"
},
  "geometry": {"coordinates":[11.601585,48.143009],"type":"Point"}
}