{
  "type": "Feature",
  "properties": {
    "iso:country":"DE",
    "sg:address":"K\u00fckenbrucher Str. 1",
    "sg:city":"Extertal",
    "sg:phone":"+49 5754/222",
    "sg:postcode":"32699",
    "sg:province":"Nordrhein-Westfalen",
    "wof:name":"Rohbraken Klinker Gmbh",
    "wof:placetype":"venue"
},
  "geometry": {"coordinates":[9.0834646225,52.1352539062],"type":"Point"}
}