{
  "type": "Feature",
  "properties": {
    "iso:country":"DE",
    "sg:address":"Oberdie\u00dfemer Str. 164",
    "sg:city":"Krefeld",
    "sg:phone":"+49 2151/391118",
    "sg:postcode":"47805",
    "sg:province":"Nordrhein-Westfalen",
    "wof:name":"Peter Kampendonk",
    "wof:placetype":"venue"
},
  "geometry": {"coordinates":[6.5848498344,51.3231086731],"type":"Point"}
}