{
  "type": "Feature",
  "properties": {
    "iso:country":"DE",
    "sg:address":"J\u00e4gersgrund",
    "sg:city":"Erndtebr\u00fcck",
    "sg:phone":"+49 2753/6070",
    "sg:postcode":"57339",
    "sg:province":"Nordrhein-Westfalen",
    "wof:name":"Steiner Gmbh & Co. Kg",
    "wof:placetype":"venue"
},
  "geometry": {"coordinates":[8.3108100891,50.9953956604],"type":"Point"}
}