{
  "type": "Feature",
  "properties": {
    "iso:country":"DE",
    "sg:address":"Schiffelsfelder Weg 10",
    "sg:city":"Boppard",
    "sg:phone":"+49 6742/81153",
    "sg:postcode":"56154",
    "sg:province":"Rheinland-Pfalz",
    "wof:name":"Heike M\u00fcller",
    "wof:placetype":"venue"
},
  "geometry": {"coordinates":[7.6039,50.218365],"type":"Point"}
}