{
  "type": "Feature",
  "properties": {
    "iso:country":"DE",
    "sg:address":"Ignatius-Blenninger-Str 6",
    "sg:city":"M\u00fcnchen",
    "sg:phone":"+49 89/3133515",
    "sg:postcode":"80995",
    "sg:province":"Bayern",
    "wof:name":"Heim & Haus Gmbh & Co Kg",
    "wof:placetype":"venue"
},
  "geometry": {"coordinates":[11.537129,48.21265],"type":"Point"}
}