{
  "type": "Feature",
  "properties": {
    "iso:country":"DE",
    "sg:address":"Dr.-Julius-Stinde-Str. 2",
    "sg:city":"Lensahn",
    "sg:phone":"+49 4363/817",
    "sg:postcode":"23738",
    "sg:province":"Schleswig-Holstein",
    "wof:name":"Gilde-stuben",
    "wof:placetype":"venue"
},
  "geometry": {"coordinates":[10.8877382278,54.2198486328],"type":"Point"}
}