{
  "type": "Feature",
  "properties": {
    "iso:country":"DE",
    "sg:address":"Sch\u00f6nhauser Allee 36-39",
    "sg:city":"Berlin",
    "sg:postcode":"10435",
    "sg:province":"Berlin",
    "wof:name":"Jugendklub D.stadtbezirkes Erich Franz",
    "wof:placetype":"venue"
},
  "geometry": {"coordinates":[13.4126605988,52.5382919312],"type":"Point"}
}