{
  "type": "Feature",
  "properties": {
    "iso:country":"DE",
    "sg:address":"Merkurstr. 3",
    "sg:city":"Rheinstetten",
    "sg:phone":"+49 7242/7332",
    "sg:postcode":"76287",
    "sg:province":"Baden-W\u00fcrttemberg",
    "wof:name":"Gindner E. K.",
    "wof:placetype":"venue"
},
  "geometry": {"coordinates":[8.292238,48.954151],"type":"Point"}
}