{
  "type": "Feature",
  "properties": {
    "iso:country":"DE",
    "sg:address":"Stettiner Str. 25",
    "sg:city":"Aachen",
    "sg:phone":"+49 241/527414",
    "sg:postcode":"52078",
    "sg:province":"Nordrhein-Westfalen",
    "wof:name":"Stettiner Stuben",
    "wof:placetype":"venue"
},
  "geometry": {"coordinates":[6.145401001,50.7536392212],"type":"Point"}
}