{
  "type": "Feature",
  "properties": {
    "iso:country":"DE",
    "sg:address":"Am Rosenplatz 1",
    "sg:city":"Reinbek",
    "sg:phone":"+49 40/7224159",
    "sg:postcode":"21465",
    "sg:province":"Schleswig-Holstein",
    "wof:name":"P. Cicekei",
    "wof:placetype":"venue"
},
  "geometry": {"coordinates":[10.2513904572,53.5115585327],"type":"Point"}
}