{
  "type": "Feature",
  "properties": {
    "iso:country":"DE",
    "sg:address":"Ringweg 2",
    "sg:city":"Kaufbeuren",
    "sg:phone":"+49 8341/994600",
    "sg:postcode":"87600",
    "sg:province":"Bayern",
    "wof:name":"Bauernj\u00f6rg",
    "wof:placetype":"venue"
},
  "geometry": {"coordinates":[10.622672081,47.8794746399],"type":"Point"}
}