{
  "type": "Feature",
  "properties": {
    "iso:country":"DE",
    "sg:address":"Am Gardumshof 15",
    "sg:city":"Ratingen",
    "sg:phone":"+49 2102/69471",
    "sg:postcode":"40883",
    "sg:province":"Nordrhein-Westfalen",
    "wof:name":"Dr. Burkhardt H\u00f6per Rechtsanwalt",
    "wof:placetype":"venue"
},
  "geometry": {"coordinates":[6.8873400688,51.3158683777],"type":"Point"}
}