{
  "type": "Feature",
  "properties": {
    "iso:country":"DE",
    "sg:address":"Heinrichstr. 24",
    "sg:city":"D\u00fcsseldorf",
    "sg:phone":"+49 4921/161030",
    "sg:postcode":"40239",
    "sg:province":"Nordrhein-Westfalen",
    "wof:name":"Springer-vdi-verlag Gmbh & Co. Kg",
    "wof:placetype":"venue"
},
  "geometry": {"coordinates":[6.8109669685,51.2446136475],"type":"Point"}
}