{
  "type": "Feature",
  "properties": {
    "iso:country":"DE",
    "sg:address":"Niederhofheimer Str. 27",
    "sg:city":"Hofheim",
    "sg:phone":"+49 6192/7743",
    "sg:postcode":"65719",
    "sg:province":"Hessen",
    "wof:name":"H. Fischer",
    "wof:placetype":"venue"
},
  "geometry": {"coordinates":[8.451859,50.090755],"type":"Point"}
}