{
  "type": "Feature",
  "properties": {
    "iso:country":"DE",
    "sg:address":"Warnetalstr. 19a",
    "sg:city":"Alfeld",
    "sg:phone":"+49 5181/26656",
    "sg:postcode":"31061",
    "sg:province":"Niedersachsen",
    "wof:name":"Hans-joachim Sliber",
    "wof:placetype":"venue"
},
  "geometry": {"coordinates":[9.851009,51.99535],"type":"Point"}
}