{
  "type": "Feature",
  "properties": {
    "iso:country":"DE",
    "sg:address":"Kapellenweg 21",
    "sg:city":"Immenstaad",
    "sg:phone":"+49 7545/1266",
    "sg:postcode":"88090",
    "sg:province":"Baden-W\u00fcrttemberg",
    "wof:name":"Angela Brose",
    "wof:placetype":"venue"
},
  "geometry": {"coordinates":[9.360706,47.663872],"type":"Point"}
}