{
  "type": "Feature",
  "properties": {
    "iso:country":"DE",
    "sg:address":"Schl\u00fcterdeich 15",
    "sg:city":"Berne",
    "sg:phone":"+49 4406/928936",
    "sg:postcode":"27804",
    "sg:province":"Niedersachsen",
    "wof:name":"Georg Skrypzak Restaurator",
    "wof:placetype":"venue"
},
  "geometry": {"coordinates":[8.4586458206,53.1981277466],"type":"Point"}
}