{
  "type": "Feature",
  "properties": {
    "iso:country":"DE",
    "sg:city":"Delmenhorst",
    "sg:postcode":"27753",
    "sg:province":"Niedersachsen",
    "wof:name":"Delmenhorster Tv - Karate Dojo",
    "wof:placetype":"venue"
},
  "geometry": {"coordinates":[8.6135,53.055641],"type":"Point"}
}