{
  "type": "Feature",
  "properties": {
    "iso:country":"DE",
    "sg:address":"Feldmark 4",
    "sg:city":"Dortmund",
    "sg:phone":"+49 2304/998040",
    "sg:postcode":"44267",
    "sg:province":"Nordrhein-Westfalen",
    "wof:name":"Bielemeyer Kran- Und F\u00f6rderanlagen Gmbh",
    "wof:placetype":"venue"
},
  "geometry": {"coordinates":[7.53381,51.44379],"type":"Point"}
}