{
  "type": "Feature",
  "properties": {
    "iso:country":"DE",
    "sg:address":"Oberlinweg 18",
    "sg:city":"Freudenstadt",
    "sg:phone":"+49 7441",
    "sg:postcode":"72250",
    "sg:province":"Baden-W\u00fcrttemberg",
    "wof:name":"Stengle - Webdesign",
    "wof:placetype":"venue"
},
  "geometry": {"coordinates":[8.4070291519,48.4711723328],"type":"Point"}
}