{
  "type": "Feature",
  "properties": {
    "iso:country":"DE",
    "sg:address":"Ludwigstr 5",
    "sg:city":"Zwickau",
    "sg:phone":"+49 375/274990",
    "sg:postcode":"08056",
    "sg:province":"Sachsen",
    "wof:name":"S\u00e4chsische Industrieofen Gmbh",
    "wof:placetype":"venue"
},
  "geometry": {"coordinates":[12.4736337662,50.712097168],"type":"Point"}
}