{
  "type": "Feature",
  "properties": {
    "iso:country":"DE",
    "sg:address":"Bachstr. 22",
    "sg:city":"Stettfeld",
    "sg:phone":"+49 9522/5156",
    "sg:postcode":"96188",
    "sg:province":"Bayern",
    "wof:name":"Fritz H\u00f6fler",
    "wof:placetype":"venue"
},
  "geometry": {"coordinates":[10.724216,49.970364],"type":"Point"}
}