{
  "type": "Feature",
  "properties": {
    "iso:country":"DE",
    "sg:address":"Ulzburger Str. 670 B",
    "sg:city":"Norderstedt",
    "sg:phone":"+49 40/52610385",
    "sg:postcode":"22844",
    "sg:province":"Schleswig-Holstein",
    "wof:name":"D.d.s. Warenhandels Gmbh",
    "wof:placetype":"venue"
},
  "geometry": {"coordinates":[10.0082054138,53.7045288086],"type":"Point"}
}