{
  "type": "Feature",
  "properties": {
    "iso:country":"DE",
    "sg:address":"Langenhainer Str. 59 a",
    "sg:city":"Tabarz",
    "sg:phone":"+49 36259/51243",
    "sg:postcode":"99891",
    "sg:province":"Th\u00fcringen",
    "wof:name":"Bbb Baumarkt Gmbh",
    "wof:placetype":"venue"
},
  "geometry": {"coordinates":[10.480024,50.884823],"type":"Point"}
}