{
  "type": "Feature",
  "properties": {
    "iso:country":"DE",
    "sg:address":"Kaiserberg 1",
    "sg:city":"Gudow",
    "sg:phone":"+49 4547/891289",
    "sg:postcode":"23899",
    "sg:province":"Schleswig-Holstein",
    "wof:name":"Hotel Landgasthaus Gudow",
    "wof:placetype":"venue"
},
  "geometry": {"coordinates":[10.7656803131,53.5558052063],"type":"Point"}
}