{
  "type": "Feature",
  "properties": {
    "iso:country":"DE",
    "sg:address":"Poststr. 26",
    "sg:city":"Wain",
    "sg:phone":"+49 7353/2494",
    "sg:postcode":"88489",
    "sg:province":"Baden-W\u00fcrttemberg",
    "wof:name":"Zuchtberatungsstelle Wain",
    "wof:placetype":"venue"
},
  "geometry": {"coordinates":[10.0166702271,48.1874313354],"type":"Point"}
}