{
  "type": "Feature",
  "properties": {
    "iso:country":"DE",
    "sg:address":"Sch\u00fctzenweg 5",
    "sg:city":"Wolfsburg",
    "sg:phone":"+49 5362/3969",
    "sg:postcode":"38442",
    "sg:province":"Niedersachsen",
    "wof:name":"Bruno Bozella",
    "wof:placetype":"venue"
},
  "geometry": {"coordinates":[10.716755,52.410801],"type":"Point"}
}