{
  "type": "Feature",
  "properties": {
    "iso:country":"DE",
    "sg:address":"Lebacher Str. 104",
    "sg:city":"Saarbr\u00fccken",
    "sg:phone":"+49 7624/6434",
    "sg:postcode":"66113",
    "sg:province":"Saarland",
    "wof:name":"A. Maurer Architekt",
    "wof:placetype":"venue"
},
  "geometry": {"coordinates":[6.967949,49.246796],"type":"Point"}
}