{
  "type": "Feature",
  "properties": {
    "iso:country":"DE",
    "sg:address":"Erich-Weinert-Str. 19",
    "sg:city":"Magdeburg",
    "sg:phone":"+49 391/628730",
    "sg:postcode":"39112",
    "sg:province":"Sachsen-Anhalt",
    "wof:name":"Thomas Krayl Architekt",
    "wof:placetype":"venue"
},
  "geometry": {"coordinates":[11.624472,52.113274],"type":"Point"}
}