{
  "type": "Feature",
  "properties": {
    "iso:country":"DE",
    "sg:address":"Kettelerstr. 14",
    "sg:city":"\u00dcbach-Palenberg",
    "sg:phone":"+49 2451/909364",
    "sg:postcode":"52531",
    "sg:province":"Nordrhein-Westfalen",
    "wof:name":"H.-p. Brendt",
    "wof:placetype":"venue"
},
  "geometry": {"coordinates":[6.1272058487,50.9179801941],"type":"Point"}
}