{
  "type": "Feature",
  "properties": {
    "iso:country":"DE",
    "sg:address":"Von-Bergmann-Str. 29",
    "sg:city":"Essen",
    "sg:phone":"+49 201/213022",
    "sg:postcode":"45141",
    "sg:province":"Nordrhein-Westfalen",
    "wof:name":"R. Ruttloff",
    "wof:placetype":"venue"
},
  "geometry": {"coordinates":[7.032277,51.476086],"type":"Point"}
}