{
  "type": "Feature",
  "properties": {
    "iso:country":"DE",
    "sg:address":"Zeitblomweg 12",
    "sg:city":"N\u00f6rdlingen",
    "sg:postcode":"86720",
    "sg:province":"Bayern",
    "wof:name":"Heidrun Roepke",
    "wof:placetype":"venue"
},
  "geometry": {"coordinates":[10.4918708801,48.8451004028],"type":"Point"}
}