{
  "type": "Feature",
  "properties": {
    "iso:country":"DE",
    "sg:address":"Fischers Allee 61",
    "sg:city":"Hamburg",
    "sg:phone":"+49 40/396969",
    "sg:postcode":"22763",
    "sg:province":"Hamburg",
    "wof:name":"J. Schniebel",
    "wof:placetype":"venue"
},
  "geometry": {"coordinates":[9.9220714569,53.550327301],"type":"Point"}
}