{
  "type": "Feature",
  "properties": {
    "iso:country":"DE",
    "sg:address":"Hirschberger Str. 2",
    "sg:city":"Isselbach",
    "sg:postcode":"65558",
    "sg:province":"Rheinland-Pfalz",
    "wof:name":"Milchlieferungsgenossenschaft Lahn-taunus Eg",
    "wof:placetype":"venue"
},
  "geometry": {"coordinates":[7.8900418282,50.388885498],"type":"Point"}
}