{
  "type": "Feature",
  "properties": {
    "iso:country":"DE",
    "sg:address":"Leibweg 7",
    "sg:city":"M\u00fcnchen",
    "sg:phone":"+49 89/6352033",
    "sg:postcode":"81679",
    "sg:province":"Bayern",
    "wof:name":"Beatrix Wiesner Architekt",
    "wof:placetype":"venue"
},
  "geometry": {"coordinates":[11.612832,48.149982],"type":"Point"}
}