{
  "type": "Feature",
  "properties": {
    "iso:country":"DE",
    "sg:address":"Bahnhofstr. 26",
    "sg:city":"Limburg",
    "sg:phone":"+49 6431/71024",
    "sg:postcode":"65552",
    "sg:province":"Hessen",
    "wof:name":"Paul Litzinger & Sohn Kg",
    "wof:placetype":"venue"
},
  "geometry": {"coordinates":[8.1041059494,50.3951416016],"type":"Point"}
}