{
  "type": "Feature",
  "properties": {
    "iso:country":"DE",
    "sg:address":"Freibergerstr. 8",
    "sg:city":"Dresden",
    "sg:phone":"+49 351/2881183",
    "sg:postcode":"01067",
    "sg:province":"Sachsen",
    "wof:name":"Zmo-k\u00fcnstlerkreis",
    "wof:placetype":"venue"
},
  "geometry": {"coordinates":[13.73365,51.05526],"type":"Point"}
}