{
  "type": "Feature",
  "properties": {
    "iso:country":"DE",
    "sg:address":"Gehrenberg 16",
    "sg:city":"Bielefeld",
    "sg:phone":"+49 521/170225",
    "sg:postcode":"33602",
    "sg:province":"Nordrhein-Westfalen",
    "wof:name":"Gabriele Frigo Mosca",
    "wof:placetype":"venue"
},
  "geometry": {"coordinates":[8.5325193405,52.0193862915],"type":"Point"}
}