{
  "type": "Feature",
  "properties": {
    "iso:country":"DE",
    "sg:address":"Am Rosengarten 1",
    "sg:city":"Sangerhausen",
    "sg:phone":"+49 3464/2460",
    "sg:postcode":"06526",
    "sg:province":"Sachsen-Anhalt",
    "wof:name":"Soziale Dienstleistungen Am Rosengarten Ggmbh",
    "wof:placetype":"venue"
},
  "geometry": {"coordinates":[11.3184652328,51.473651886],"type":"Point"}
}