{
  "type": "Feature",
  "properties": {
    "iso:country":"DE",
    "sg:address":"Limbecker Str. 62 - 64",
    "sg:city":"Essen",
    "sg:phone":"+49 201/827550",
    "sg:postcode":"45127",
    "sg:province":"Nordrhein-Westfalen",
    "wof:name":"Betten Saeger",
    "wof:placetype":"venue"
},
  "geometry": {"coordinates":[7.0085020065,51.4578781128],"type":"Point"}
}