{
  "type": "Feature",
  "properties": {
    "iso:country":"DE",
    "sg:address":"Mittelstr. 7",
    "sg:city":"Sibbesse",
    "sg:phone":"+49 5065/8751",
    "sg:postcode":"31079",
    "sg:province":"Niedersachsen",
    "wof:name":"Otto Brandes",
    "wof:placetype":"venue"
},
  "geometry": {"coordinates":[9.8900947571,52.0654716492],"type":"Point"}
}