{
  "type": "Feature",
  "properties": {
    "iso:country":"DE",
    "sg:address":"Karolinenstr. 4",
    "sg:city":"Detmold",
    "sg:phone":"+49 5231/390263",
    "sg:postcode":"32756",
    "sg:province":"Nordrhein-Westfalen",
    "wof:name":"Pfarramt Ii Ev. Ref. Kirche",
    "wof:placetype":"venue"
},
  "geometry": {"coordinates":[8.8733615875,51.9455490112],"type":"Point"}
}