{
  "type": "Feature",
  "properties": {
    "iso:country":"DE",
    "sg:address":"Endinger Weg 7",
    "sg:city":"Bahlingen",
    "sg:postcode":"79353",
    "sg:province":"Baden-W\u00fcrttemberg",
    "wof:name":"Gabriele Haas",
    "wof:placetype":"venue"
},
  "geometry": {"coordinates":[7.732117,48.121155],"type":"Point"}
}