{
  "type": "Feature",
  "properties": {
    "iso:country":"DE",
    "sg:address":"Am Waschteich 5",
    "sg:city":"Neumark",
    "sg:phone":"+49 37600/2300",
    "sg:postcode":"08496",
    "sg:province":"Sachsen",
    "wof:name":"Seniorenheim",
    "wof:placetype":"venue"
},
  "geometry": {"coordinates":[12.318893,50.670536],"type":"Point"}
}