{
  "type": "Feature",
  "properties": {
    "iso:country":"DE",
    "sg:address":"Frankfurter Str.17",
    "sg:city":"Giessen",
    "sg:phone":"+49 641/2500700",
    "sg:postcode":"35390",
    "sg:province":"Hessen",
    "wof:name":"Pc Spiele Chat\u00b4s Und Forum",
    "wof:placetype":"venue"
},
  "geometry": {"coordinates":[8.668303,50.580326],"type":"Point"}
}