{
  "type": "Feature",
  "properties": {
    "iso:country":"DE",
    "sg:address":"Bromberger Str. 21",
    "sg:city":"Nordenham",
    "sg:phone":"+49 4731/88637",
    "sg:postcode":"26954",
    "sg:province":"Niedersachsen",
    "wof:name":"Ev. Pfarramt Friedrich-august-h\u00fctte",
    "wof:placetype":"venue"
},
  "geometry": {"coordinates":[8.4916381836,53.5042762756],"type":"Point"}
}