{
  "type": "Feature",
  "properties": {
    "iso:country":"DE",
    "sg:address":"Sinnstr. 1",
    "sg:city":"Mittelsinn",
    "sg:phone":"+49 9356/6533",
    "sg:postcode":"97785",
    "sg:province":"Bayern",
    "wof:name":"Tanzcafe Charivari",
    "wof:placetype":"venue"
},
  "geometry": {"coordinates":[9.623493,50.189575],"type":"Point"}
}