{
  "type": "Feature",
  "properties": {
    "iso:country":"DE",
    "sg:address":"Eduard-Breuninger-Str. 3",
    "sg:city":"Backnang",
    "sg:phone":"+49 7191/65205",
    "sg:postcode":"71522",
    "sg:province":"Baden-W\u00fcrttemberg",
    "wof:name":"B. Paulus",
    "wof:placetype":"venue"
},
  "geometry": {"coordinates":[9.4297456741,48.9452362061],"type":"Point"}
}