{
  "type": "Feature",
  "properties": {
    "iso:country":"DE",
    "sg:address":"Beerenheide 14",
    "sg:city":"Ratingen",
    "sg:phone":"+49 2102/843911",
    "sg:postcode":"40882",
    "sg:province":"Nordrhein-Westfalen",
    "wof:name":"Norbert Pracht Architekt",
    "wof:placetype":"venue"
},
  "geometry": {"coordinates":[6.872293,51.292458],"type":"Point"}
}