{
  "type": "Feature",
  "properties": {
    "iso:country":"DE",
    "sg:address":"Einsteinstr. 38",
    "sg:city":"Planegg",
    "sg:postcode":"82152",
    "sg:province":"Bayern",
    "wof:name":"Jako-verputz Gmbh",
    "wof:placetype":"venue"
},
  "geometry": {"coordinates":[11.44518,48.104561],"type":"Point"}
}