{
  "type": "Feature",
  "properties": {
    "iso:country":"DE",
    "sg:address":"Bismarckstr. 4",
    "sg:city":"Kehl",
    "sg:phone":"+49 7851/94610",
    "sg:postcode":"77694",
    "sg:province":"Baden-W\u00fcrttemberg",
    "wof:name":"Elektro Sch\u00fctterle E. K.",
    "wof:placetype":"venue"
},
  "geometry": {"coordinates":[7.8278508186,48.5664634705],"type":"Point"}
}