{
  "type": "Feature",
  "properties": {
    "iso:country":"DE",
    "sg:address":"Hirtenstr. 17",
    "sg:city":"Hamburg",
    "sg:phone":"+49 40/2542677",
    "sg:postcode":"20535",
    "sg:province":"Hamburg",
    "wof:name":"H\u00fcbner",
    "wof:placetype":"venue"
},
  "geometry": {"coordinates":[10.0472640991,53.5564651489],"type":"Point"}
}