{
  "type": "Feature",
  "properties": {
    "iso:country":"DE",
    "sg:address":"Mauritiusstr. 16",
    "sg:city":"Bochum",
    "sg:phone":"+49 234/301728",
    "sg:postcode":"44789",
    "sg:province":"Nordrhein-Westfalen",
    "wof:name":"Willi Maukisch Ohg",
    "wof:placetype":"venue"
},
  "geometry": {"coordinates":[7.225334,51.476719],"type":"Point"}
}