{
  "type": "Feature",
  "properties": {
    "iso:country":"DE",
    "sg:address":"Erichstr. 1",
    "sg:city":"Hannover",
    "sg:phone":"+49 511/442998",
    "sg:postcode":"30449",
    "sg:province":"Niedersachsen",
    "wof:name":"Casadio Gmbh",
    "wof:placetype":"venue"
},
  "geometry": {"coordinates":[9.7066059113,52.3669433594],"type":"Point"}
}