{
  "type": "Feature",
  "properties": {
    "iso:country":"DE",
    "sg:address":"Dieselstr.",
    "sg:city":"Dillingen",
    "sg:phone":"+49 6831/768790",
    "sg:postcode":"66763",
    "sg:province":"Saarland",
    "wof:name":"Pink & Wagner Gmbh",
    "wof:placetype":"venue"
},
  "geometry": {"coordinates":[6.711617,49.369942],"type":"Point"}
}