{
  "type": "Feature",
  "properties": {
    "iso:country":"DE",
    "sg:address":"Wittelsbacherstr. 46",
    "sg:city":"Rosenheim",
    "sg:phone":"+49 8031/16154",
    "sg:postcode":"83022",
    "sg:province":"Bayern",
    "wof:name":"Erika Neumeier",
    "wof:placetype":"venue"
},
  "geometry": {"coordinates":[12.111782074,47.8549423218],"type":"Point"}
}