{
  "type": "Feature",
  "properties": {
    "iso:country":"DE",
    "sg:address":"Hauptstr. 70",
    "sg:city":"Langerwehe",
    "sg:phone":"+49 2423/3043",
    "sg:postcode":"52379",
    "sg:province":"Nordrhein-Westfalen",
    "wof:name":"Schmitz Moden Gmbh",
    "wof:placetype":"venue"
},
  "geometry": {"coordinates":[6.3596539497,50.8177833557],"type":"Point"}
}