{
  "type": "Feature",
  "properties": {
    "iso:country":"DE",
    "sg:address":"Aachener Str. 1158 a",
    "sg:city":"K\u00f6ln",
    "sg:postcode":"50858",
    "sg:province":"Nordrhein-Westfalen",
    "wof:name":"Funtime Promotion Gmbh",
    "wof:placetype":"venue"
},
  "geometry": {"coordinates":[6.8414092064,50.9384040833],"type":"Point"}
}