{
  "type": "Feature",
  "properties": {
    "iso:country":"DE",
    "sg:address":"Blaubeurer Weg 14",
    "sg:city":"Heroldstatt",
    "sg:phone":"+49 7389/685",
    "sg:postcode":"72535",
    "sg:province":"Baden-W\u00fcrttemberg",
    "wof:name":"Wolfgang Day",
    "wof:placetype":"venue"
},
  "geometry": {"coordinates":[9.673555,48.444172],"type":"Point"}
}