{
  "type": "Feature",
  "properties": {
    "iso:country":"DE",
    "sg:address":"Gentzkowstr. 35",
    "sg:city":"Stralsund",
    "sg:postcode":"18439",
    "sg:province":"Mecklenburg-Vorpommern",
    "wof:name":"Factum 2000 Gmbh & Co. Kg",
    "wof:placetype":"venue"
},
  "geometry": {"coordinates":[13.085869,54.302414],"type":"Point"}
}