{
  "type": "Feature",
  "properties": {
    "iso:country":"DE",
    "sg:address":"Wierlings Kamp 6",
    "sg:city":"D\u00fclmen",
    "sg:phone":"+49 2594/94190",
    "sg:postcode":"48249",
    "sg:province":"Nordrhein-Westfalen",
    "wof:name":"Atoll-handels Beteiligungs Gmbh",
    "wof:placetype":"venue"
},
  "geometry": {"coordinates":[7.3151459694,51.8225784302],"type":"Point"}
}