{
  "type": "Feature",
  "properties": {
    "iso:country":"DE",
    "sg:address":"Am Kiebitzpfuhl 1",
    "sg:city":"Magdeburg",
    "sg:phone":"+49 391/2528943",
    "sg:postcode":"39128",
    "sg:province":"Sachsen-Anhalt",
    "wof:name":"Renate Riemann",
    "wof:placetype":"venue"
},
  "geometry": {"coordinates":[11.6166543961,52.1496391296],"type":"Point"}
}