{
  "type": "Feature",
  "properties": {
    "iso:country":"DE",
    "sg:address":"Bahnhofstr. 8",
    "sg:city":"Fl\u00f6ha",
    "sg:postcode":"09557",
    "sg:province":"Sachsen",
    "wof:name":"Kreiskinderbibliothek",
    "wof:placetype":"venue"
},
  "geometry": {"coordinates":[13.076409,50.857033],"type":"Point"}
}