{
  "type": "Feature",
  "properties": {
    "iso:country":"DE",
    "sg:address":"Neustr. 46",
    "sg:city":"Westerburg",
    "sg:phone":"+49 2663/1531",
    "sg:postcode":"56457",
    "sg:province":"Rheinland-Pfalz",
    "wof:name":"Ernst Schmalzried Steuerberater",
    "wof:placetype":"venue"
},
  "geometry": {"coordinates":[7.9745631218,50.5662536621],"type":"Point"}
}