{
  "type": "Feature",
  "properties": {
    "iso:country":"DE",
    "sg:address":"Wilhelm-Raabe-Str. 10",
    "sg:city":"Markkleeberg",
    "sg:phone":"+49 341/3580714",
    "sg:postcode":"04416",
    "sg:province":"Sachsen",
    "wof:name":"Dr. Rolf Grohmann Ing.-b\u00fcro F.rechentechnik",
    "wof:placetype":"venue"
},
  "geometry": {"coordinates":[12.3694963455,51.2869377136],"type":"Point"}
}