{
  "type": "Feature",
  "properties": {
    "iso:country":"DE",
    "sg:address":"Berghofer Weg 16",
    "sg:city":"Berlin",
    "sg:phone":"+49 30/6486525",
    "sg:postcode":"12589",
    "sg:province":"Berlin",
    "wof:name":"Monika Romund",
    "wof:placetype":"venue"
},
  "geometry": {"coordinates":[13.701395,52.439842],"type":"Point"}
}