{
  "type": "Feature",
  "properties": {
    "iso:country":"DE",
    "sg:address":"An den Eichen 10",
    "sg:city":"M\u00f6nchberg",
    "sg:phone":"+49 9374/90011",
    "sg:postcode":"63933",
    "sg:province":"Bayern",
    "wof:name":"Thea Reus Verwaltungsges. Mbh",
    "wof:placetype":"venue"
},
  "geometry": {"coordinates":[9.273803,49.791985],"type":"Point"}
}