{
  "type": "Feature",
  "properties": {
    "iso:country":"DE",
    "sg:address":"Mittelweg 106",
    "sg:city":"Hamburg",
    "sg:phone":"+49 40/4101830",
    "sg:postcode":"20149",
    "sg:province":"Hamburg",
    "wof:name":"Altenheim St. Johannis- St. Nikolai Stiftung",
    "wof:placetype":"venue"
},
  "geometry": {"coordinates":[9.993381,53.575909],"type":"Point"}
}