{
  "type": "Feature",
  "properties": {
    "iso:country":"DE",
    "sg:address":"Halstenbeker Weg 96 b",
    "sg:city":"Rellingen",
    "sg:postcode":"25462",
    "sg:province":"Schleswig-Holstein",
    "wof:name":"Usf Vertriebs & Service Center Nord Zweigniederlassung Der",
    "wof:placetype":"venue"
},
  "geometry": {"coordinates":[9.840563,53.644249],"type":"Point"}
}