{
  "type": "Feature",
  "properties": {
    "iso:country":"DE",
    "sg:address":"Falltorstr. 8",
    "sg:city":"Bad Sch\u00f6nborn",
    "sg:phone":"+49 7253/4697",
    "sg:postcode":"76669",
    "sg:province":"Baden-W\u00fcrttemberg",
    "wof:name":"Cafe Zabler",
    "wof:placetype":"venue"
},
  "geometry": {"coordinates":[8.6620368958,49.2174873352],"type":"Point"}
}