{
  "type": "Feature",
  "properties": {
    "iso:country":"DE",
    "sg:address":"Wagh\u00e4useler Str. 93",
    "sg:city":"Wagh\u00e4usel",
    "sg:phone":"+49 7254/3722",
    "sg:postcode":"68753",
    "sg:province":"Baden-W\u00fcrttemberg",
    "wof:name":"Doris Schuhmacher",
    "wof:placetype":"venue"
},
  "geometry": {"coordinates":[8.5393648148,49.244468689],"type":"Point"}
}