{
  "type": "Feature",
  "properties": {
    "iso:country":"DE",
    "sg:address":"Stiefenhofer Platz 1",
    "sg:city":"Barsb\u00fcttel",
    "sg:phone":"+49 40/670720",
    "sg:postcode":"22885",
    "sg:province":"Schleswig-Holstein",
    "wof:name":"Barsb\u00fctteler W\u00e4rmedienst Gmbh",
    "wof:placetype":"venue"
},
  "geometry": {"coordinates":[10.16831,53.569183],"type":"Point"}
}