{
  "type": "Feature",
  "properties": {
    "iso:country":"DE",
    "sg:address":"Marktplatz 5",
    "sg:city":"Zell",
    "sg:phone":"+49 9257/366",
    "sg:postcode":"95239",
    "sg:province":"Bayern",
    "wof:name":"Richard Hoffmann",
    "wof:placetype":"venue"
},
  "geometry": {"coordinates":[11.8210248947,50.1336021423],"type":"Point"}
}