{
  "type": "Feature",
  "properties": {
    "iso:country":"DE",
    "sg:address":"Godensholter Str 10",
    "sg:city":"Westerstede",
    "sg:phone":"+49 4409/1455",
    "sg:postcode":"26655",
    "sg:province":"Niedersachsen",
    "wof:name":"G\u00fcnther Gmbh",
    "wof:placetype":"venue"
},
  "geometry": {"coordinates":[7.8839678764,53.200843811],"type":"Point"}
}