{
  "type": "Feature",
  "properties": {
    "iso:country":"DE",
    "sg:address":"Salmas",
    "sg:city":"Oberstaufen",
    "sg:phone":"+49 8325/265",
    "sg:postcode":"87534",
    "sg:province":"Bayern",
    "wof:name":"P. L\u00f6chle",
    "wof:placetype":"venue"
},
  "geometry": {"coordinates":[10.0720710754,47.5570907593],"type":"Point"}
}