{
  "type": "Feature",
  "properties": {
    "iso:country":"DE",
    "sg:address":"Beelener Str. 70",
    "sg:city":"Herzebrock-Clarholz",
    "sg:phone":"+49 5245/858511",
    "sg:postcode":"33442",
    "sg:province":"Nordrhein-Westfalen",
    "wof:name":"Antjes Reiseb\u00fcro",
    "wof:placetype":"venue"
},
  "geometry": {"coordinates":[8.1941156387,51.9019432068],"type":"Point"}
}