{
  "type": "Feature",
  "properties": {
    "iso:country":"DE",
    "sg:address":"Merseburger Str. 72",
    "sg:city":"Querfurt",
    "sg:phone":"+49 34771/24404",
    "sg:postcode":"06268",
    "sg:province":"Sachsen-Anhalt",
    "wof:name":"Freund Und Partner Steuerberatungs- Gmbh",
    "wof:placetype":"venue"
},
  "geometry": {"coordinates":[11.6117429733,51.3811531067],"type":"Point"}
}