{
  "type": "Feature",
  "properties": {
    "iso:country":"DE",
    "sg:address":"Oppenheimstr. 56",
    "sg:city":"Eisenach",
    "sg:phone":"+49 3691/213141",
    "sg:postcode":"99817",
    "sg:province":"Th\u00fcringen",
    "wof:name":"Sk Objektm\u00f6bel Vetriebs Gmbh",
    "wof:placetype":"venue"
},
  "geometry": {"coordinates":[10.309234,50.980659],"type":"Point"}
}