{
  "type": "Feature",
  "properties": {
    "iso:country":"DE",
    "sg:address":"Zur Teerhofsinsel 6",
    "sg:city":"L\u00fcbeck",
    "sg:phone":"+49 451/26162",
    "sg:postcode":"23554",
    "sg:province":"Schleswig-Holstein",
    "wof:name":"Nord-ost Service- Und Handels Gmbh",
    "wof:placetype":"venue"
},
  "geometry": {"coordinates":[10.695838,53.906227],"type":"Point"}
}