{
  "type": "Feature",
  "properties": {
    "iso:country":"DE",
    "sg:address":"Heiliggeistgasse 23",
    "sg:city":"Passau",
    "sg:phone":"+49 851/34445",
    "sg:postcode":"94032",
    "sg:province":"Bayern",
    "wof:name":"Club Inn",
    "wof:placetype":"venue"
},
  "geometry": {"coordinates":[13.4617338181,48.5723571777],"type":"Point"}
}