{
  "type": "Feature",
  "properties": {
    "iso:country":"DE",
    "sg:address":"Stedinger Weg 32",
    "sg:city":"D\u00f6tlingen-Brettorf",
    "sg:phone":"+49 4432",
    "sg:postcode":"27801",
    "sg:province":"Niedersachsen",
    "wof:name":"Dirksen Immobilien",
    "wof:placetype":"venue"
},
  "geometry": {"coordinates":[8.4450569153,52.965385437],"type":"Point"}
}