{
  "type": "Feature",
  "properties": {
    "iso:country":"DE",
    "sg:address":"Oberbuchen",
    "sg:city":"Bad Heilbrunn",
    "sg:phone":"+49 8046/587",
    "sg:postcode":"83670",
    "sg:province":"Bayern",
    "wof:name":"Thomas Mayr Gmbh",
    "wof:placetype":"venue"
},
  "geometry": {"coordinates":[11.48879,47.765728],"type":"Point"}
}