{
  "type": "Feature",
  "properties": {
    "iso:country":"DE",
    "sg:address":"Stillestr. 28",
    "sg:city":"L\u00fcbbecke",
    "sg:phone":"+49 5741/6844",
    "sg:postcode":"32312",
    "sg:province":"Nordrhein-Westfalen",
    "wof:name":"Ernst Brinkmann",
    "wof:placetype":"venue"
},
  "geometry": {"coordinates":[8.691938,52.305145],"type":"Point"}
}