{
  "type": "Feature",
  "properties": {
    "iso:country":"DE",
    "sg:address":"Fasanenhof",
    "sg:city":"Freisen",
    "sg:phone":"+49 6857/295",
    "sg:postcode":"66629",
    "sg:province":"Saarland",
    "wof:name":"Josef Fisahn",
    "wof:placetype":"venue"
},
  "geometry": {"coordinates":[7.230431,49.526772],"type":"Point"}
}