{
  "type": "Feature",
  "properties": {
    "iso:country":"DE",
    "sg:address":"Charlottenstr. 13",
    "sg:city":"Wangerooge",
    "sg:phone":"+49 4469/1656",
    "sg:postcode":"26486",
    "sg:province":"Niedersachsen",
    "wof:name":"V. Baines",
    "wof:placetype":"venue"
},
  "geometry": {"coordinates":[7.8987669945,53.79139328],"type":"Point"}
}