{
  "type": "Feature",
  "properties": {
    "iso:country":"DE",
    "sg:address":"Paderborner Str. 13",
    "sg:city":"Borchen",
    "sg:phone":"+49 5251/391900",
    "sg:postcode":"33178",
    "sg:province":"Nordrhein-Westfalen",
    "wof:name":"Eckhard Fastrich Rechtsanwalt Und Notar",
    "wof:placetype":"venue"
},
  "geometry": {"coordinates":[8.7239122391,51.6694641113],"type":"Point"}
}