{
  "type": "Feature",
  "properties": {
    "iso:country":"DE",
    "sg:address":"Ismaningerstr. 23",
    "sg:city":"Freising",
    "sg:phone":"+49 8161",
    "sg:postcode":"85356",
    "sg:province":"Bayern",
    "wof:name":"Jos.thalhammer Gmbh",
    "wof:placetype":"venue"
},
  "geometry": {"coordinates":[11.7537822723,48.3921928406],"type":"Point"}
}