{
  "type": "Feature",
  "properties": {
    "iso:country":"DE",
    "sg:address":"Hauptstr. 7",
    "sg:city":"Werlte",
    "sg:phone":"+49 5951/990088",
    "sg:postcode":"49757",
    "sg:province":"Niedersachsen",
    "wof:name":"China Restaurant Jade Garden",
    "wof:placetype":"venue"
},
  "geometry": {"coordinates":[7.6746149063,52.8511695862],"type":"Point"}
}