{
  "type": "Feature",
  "properties": {
    "iso:country":"DE",
    "sg:address":"Freysestr. 10",
    "sg:city":"Krefeld",
    "sg:postcode":"47802",
    "sg:province":"Nordrhein-Westfalen",
    "wof:name":"Seros Textilvertriebs Gmbh",
    "wof:placetype":"venue"
},
  "geometry": {"coordinates":[6.569729805,51.3660888672],"type":"Point"}
}