{
  "type": "Feature",
  "properties": {
    "iso:country":"DE",
    "sg:address":"Eschenweg 3",
    "sg:city":"Wiesloch",
    "sg:phone":"+49 6222/4949",
    "sg:postcode":"69168",
    "sg:province":"Baden-W\u00fcrttemberg",
    "wof:name":"Armin Soder Ingenieur",
    "wof:placetype":"venue"
},
  "geometry": {"coordinates":[8.7041416168,49.2920455933],"type":"Point"}
}