{
  "type": "Feature",
  "properties": {
    "iso:country":"DE",
    "sg:address":"Hauptstr. 179",
    "sg:city":"Bochum",
    "sg:phone":"+49 234/286665",
    "sg:postcode":"44892",
    "sg:province":"Nordrhein-Westfalen",
    "wof:name":"Gundor Katern",
    "wof:placetype":"venue"
},
  "geometry": {"coordinates":[7.3237509727,51.4750900269],"type":"Point"}
}