{
  "type": "Feature",
  "properties": {
    "iso:country":"DE",
    "sg:address":"Vorderdorfstr. 72",
    "sg:city":"St. Blasien",
    "sg:phone":"+49 7675/1800",
    "sg:postcode":"79837",
    "sg:province":"Baden-W\u00fcrttemberg",
    "wof:name":"Bier- U. Weinstube Treff 2000",
    "wof:placetype":"venue"
},
  "geometry": {"coordinates":[8.0711660385,47.8239364624],"type":"Point"}
}