{
  "type": "Feature",
  "properties": {
    "iso:country":"DE",
    "sg:address":"Zum Silberacker 18",
    "sg:city":"Elze",
    "sg:phone":"+49 5182/6751",
    "sg:postcode":"31008",
    "sg:province":"Niedersachsen",
    "wof:name":"Kurt Scheffler",
    "wof:placetype":"venue"
},
  "geometry": {"coordinates":[9.684004,52.081303],"type":"Point"}
}