{
  "type": "Feature",
  "properties": {
    "iso:country":"DE",
    "sg:address":"Herrenwiese 3",
    "sg:city":"Bad Berleburg",
    "sg:phone":"+49 2751/7514",
    "sg:postcode":"57319",
    "sg:province":"Nordrhein-Westfalen",
    "wof:name":"Adolf Kloos Fliesen- Und Sanit\u00e4rfachgesch\u00e4ft",
    "wof:placetype":"venue"
},
  "geometry": {"coordinates":[8.3971567154,51.060962677],"type":"Point"}
}