{
  "type": "Feature",
  "properties": {
    "iso:country":"DE",
    "sg:address":"Nymphenburger Str. 145",
    "sg:city":"M\u00fcnchen",
    "sg:phone":"+49 89/12789660",
    "sg:postcode":"80636",
    "sg:province":"Bayern",
    "wof:name":"Hervol Und R\u00fcll Rechtsanw\u00e4lte",
    "wof:placetype":"venue"
},
  "geometry": {"coordinates":[11.537311554,48.1515541077],"type":"Point"}
}