{
  "type": "Feature",
  "properties": {
    "iso:country":"DE",
    "sg:address":"Lengfelder Str. 38",
    "sg:city":"Teugn",
    "sg:phone":"+49 9405/3891",
    "sg:postcode":"93356",
    "sg:province":"Bayern",
    "wof:name":"N & Z Schwimmbadbau Gmbh",
    "wof:placetype":"venue"
},
  "geometry": {"coordinates":[12.008408,48.900333],"type":"Point"}
}