{
  "type": "Feature",
  "properties": {
    "iso:country":"DE",
    "sg:address":"Hauptstr. 342",
    "sg:city":"Herne",
    "sg:phone":"+49 2325/77901",
    "sg:postcode":"44649",
    "sg:province":"Nordrhein-Westfalen",
    "wof:name":"Weber Lederwaren",
    "wof:placetype":"venue"
},
  "geometry": {"coordinates":[7.156124,51.538948],"type":"Point"}
}