{
  "type": "Feature",
  "properties": {
    "iso:country":"DE",
    "sg:address":"Grabental 39",
    "sg:city":"Eisenach",
    "sg:postcode":"99817",
    "sg:province":"Th\u00fcringen",
    "wof:name":"Unigarant Eisenach Gmbh",
    "wof:placetype":"venue"
},
  "geometry": {"coordinates":[10.3323001862,50.9813690186],"type":"Point"}
}