{
  "type": "Feature",
  "properties": {
    "iso:country":"DE",
    "sg:address":"Flensburger Str. 2A",
    "sg:city":"Gl\u00fcckstadt",
    "sg:phone":"+49 4124/890506",
    "sg:postcode":"25348",
    "sg:province":"Schleswig-Holstein",
    "wof:name":"Autohalle Gl\u00fcckstadt Gmbh",
    "wof:placetype":"venue"
},
  "geometry": {"coordinates":[9.417731,53.800468],"type":"Point"}
}