{
  "type": "Feature",
  "properties": {
    "iso:country":"DE",
    "sg:address":"Schmittmannstr. 27",
    "sg:city":"Dernau",
    "sg:phone":"+49 2643/900003",
    "sg:postcode":"53507",
    "sg:province":"Rheinland-Pfalz",
    "wof:name":"Gillessen",
    "wof:placetype":"venue"
},
  "geometry": {"coordinates":[7.0450401306,50.5341567993],"type":"Point"}
}