{
  "type": "Feature",
  "properties": {
    "iso:country":"DE",
    "sg:address":"Rudolf-Bosse-Weg 13",
    "sg:city":"Goslar",
    "sg:postcode":"38642",
    "sg:province":"Niedersachsen",
    "wof:name":"Ats Schlemme Gmbh",
    "wof:placetype":"venue"
},
  "geometry": {"coordinates":[10.453823,51.921776],"type":"Point"}
}