{
  "type": "Feature",
  "properties": {
    "iso:country":"DE",
    "sg:address":"Rheinstr. 2",
    "sg:city":"Linz",
    "sg:phone":"+49 2644/2375",
    "sg:postcode":"53545",
    "sg:province":"Rheinland-Pfalz",
    "wof:name":"St\u00fcrs Moden Inh. Jutta Kr\u00e4ften",
    "wof:placetype":"venue"
},
  "geometry": {"coordinates":[7.2792568207,50.565776825],"type":"Point"}
}