{
  "type": "Feature",
  "properties": {
    "iso:country":"DE",
    "sg:address":"Bahnhofstr. 30",
    "sg:city":"Gie\u00dfen",
    "sg:phone":"+49 641/72877",
    "sg:postcode":"35390",
    "sg:province":"Hessen",
    "wof:name":"Pic Dame",
    "wof:placetype":"venue"
},
  "geometry": {"coordinates":[8.670689,50.584763],"type":"Point"}
}