{
  "type": "Feature",
  "properties": {
    "iso:country":"DE",
    "sg:address":"Rosenstr. 60",
    "sg:city":"Filderstadt",
    "sg:postcode":"70794",
    "sg:province":"Baden-W\u00fcrttemberg",
    "wof:name":"Manisha Moden",
    "wof:placetype":"venue"
},
  "geometry": {"coordinates":[9.209985,48.678108],"type":"Point"}
}