{
  "type": "Feature",
  "properties": {
    "iso:country":"DE",
    "sg:address":"Banzweg 8",
    "sg:city":"M\u00fcnchen",
    "sg:phone":"+49 89/8712176",
    "sg:postcode":"81243",
    "sg:province":"Bayern",
    "wof:name":"Ulrich Ott Architekt",
    "wof:placetype":"venue"
},
  "geometry": {"coordinates":[11.426974,48.151592],"type":"Point"}
}