{
  "type": "Feature",
  "properties": {
    "iso:country":"DE",
    "sg:address":"Albestr. 24",
    "sg:city":"Berlin",
    "sg:phone":"+49 30/8524375",
    "sg:postcode":"12159",
    "sg:province":"Berlin",
    "wof:name":"Sch\u00f6neberger Vorschul- Erziehung E. V.",
    "wof:placetype":"venue"
},
  "geometry": {"coordinates":[13.3311624527,52.4733123779],"type":"Point"}
}