{
  "type": "Feature",
  "properties": {
    "iso:country":"DE",
    "sg:address":"Drosselweg 14",
    "sg:city":"Bad Arolsen",
    "sg:phone":"+49 5691/3812",
    "sg:postcode":"34454",
    "sg:province":"Hessen",
    "wof:name":"Ute Rapp",
    "wof:placetype":"venue"
},
  "geometry": {"coordinates":[8.97678,51.3671],"type":"Point"}
}