{
  "type": "Feature",
  "properties": {
    "iso:country":"DE",
    "sg:address":"Feldgasse 9",
    "sg:city":"Schleiz",
    "sg:phone":"+49 3663/402720",
    "sg:postcode":"07907",
    "sg:province":"Th\u00fcringen",
    "wof:name":"Ingenieurb\u00fcro Bernd D\u00f6bling Gmbh",
    "wof:placetype":"venue"
},
  "geometry": {"coordinates":[11.8102531433,50.5736312866],"type":"Point"}
}