{
  "type": "Feature",
  "properties": {
    "iso:country":"DE",
    "sg:address":"Domhof 4",
    "sg:city":"Vreden",
    "sg:phone":"+49 2564/1372",
    "sg:postcode":"48691",
    "sg:province":"Nordrhein-Westfalen",
    "wof:name":"Kettelerhaus",
    "wof:placetype":"venue"
},
  "geometry": {"coordinates":[6.8248491287,52.0347290039],"type":"Point"}
}