{
  "type": "Feature",
  "properties": {
    "iso:country":"DE",
    "sg:address":"Heusweiler Str. 26",
    "sg:city":"Heusweiler",
    "sg:phone":"+49 6806/81487",
    "sg:postcode":"66265",
    "sg:province":"Saarland",
    "wof:name":"Sofie Gro\u00df",
    "wof:placetype":"venue"
},
  "geometry": {"coordinates":[6.9330649376,49.34973526],"type":"Point"}
}