{
  "type": "Feature",
  "properties": {
    "iso:country":"DE",
    "sg:address":"Baldstr. 6",
    "sg:city":"F\u00fcrth",
    "sg:postcode":"90762",
    "sg:province":"Bayern",
    "wof:name":"Casieri Stuck Gmbh",
    "wof:placetype":"venue"
},
  "geometry": {"coordinates":[10.9903497696,49.4787063599],"type":"Point"}
}