{
  "type": "Feature",
  "properties": {
    "iso:country":"DE",
    "sg:address":"N\u00fcrnberger Str.",
    "sg:city":"Barchfeld",
    "sg:phone":"+49 36961/4720",
    "sg:postcode":"36456",
    "sg:province":"Th\u00fcringen",
    "wof:name":"Bauzentrum",
    "wof:placetype":"venue"
},
  "geometry": {"coordinates":[10.296959877,50.8018913269],"type":"Point"}
}