{
  "type": "Feature",
  "properties": {
    "iso:country":"DE",
    "sg:address":"Hintergasse 2",
    "sg:city":"Brensbach",
    "sg:phone":"+49 6161/2288",
    "sg:postcode":"64395",
    "sg:province":"Hessen",
    "wof:name":"Gickelswirt",
    "wof:placetype":"venue"
},
  "geometry": {"coordinates":[8.8655223846,49.7760047913],"type":"Point"}
}