{
  "type": "Feature",
  "properties": {
    "iso:country":"DE",
    "sg:address":"Heerstr. 10",
    "sg:city":"Metzingen",
    "sg:phone":"+49 7123/15257",
    "sg:postcode":"72555",
    "sg:province":"Baden-W\u00fcrttemberg",
    "wof:name":"Dorothee Reiff Wollkorb",
    "wof:placetype":"venue"
},
  "geometry": {"coordinates":[9.291288,48.537132],"type":"Point"}
}