{
  "type": "Feature",
  "properties": {
    "iso:country":"DE",
    "sg:address":"Weidengasse 2",
    "sg:city":"Butzbach",
    "sg:phone":"+49 6033/2886",
    "sg:postcode":"35510",
    "sg:province":"Hessen",
    "wof:name":"Holzbearbeitungsbetrieb Werner Ohg",
    "wof:placetype":"venue"
},
  "geometry": {"coordinates":[8.6411514282,50.3901290894],"type":"Point"}
}