{
  "type": "Feature",
  "properties": {
    "iso:country":"DE",
    "sg:address":"Kreuzstr. 13",
    "sg:city":"Leipzig",
    "sg:phone":"+49 341/696860",
    "sg:postcode":"04103",
    "sg:province":"Sachsen",
    "wof:name":"Ds Druck-strom Gmbh",
    "wof:placetype":"venue"
},
  "geometry": {"coordinates":[12.392853,51.341263],"type":"Point"}
}