{
  "type": "Feature",
  "properties": {
    "iso:country":"DE",
    "sg:address":"Erlengarten 4",
    "sg:city":"Enger",
    "sg:phone":"+49 5224/45712",
    "sg:postcode":"32130",
    "sg:province":"Nordrhein-Westfalen",
    "wof:name":"Ev. Pfarramt S\u00fcd",
    "wof:placetype":"venue"
},
  "geometry": {"coordinates":[8.5575237274,52.1363601685],"type":"Point"}
}