{
  "type": "Feature",
  "properties": {
    "iso:country":"DE",
    "sg:address":"Handelsstr. 25",
    "sg:city":"Alpen",
    "sg:phone":"+49 2802/2491",
    "sg:postcode":"46519",
    "sg:province":"Nordrhein-Westfalen",
    "wof:name":"Peter Jordan",
    "wof:placetype":"venue"
},
  "geometry": {"coordinates":[6.461113,51.575542],"type":"Point"}
}