{
  "type": "Feature",
  "properties": {
    "iso:country":"DE",
    "sg:address":"Carl-Zeiss-Weg 6",
    "sg:city":"Salzgitter",
    "sg:phone":"+49 5341/189990",
    "sg:postcode":"38239",
    "sg:province":"Niedersachsen",
    "wof:name":"Bozankaya Gmbh",
    "wof:placetype":"venue"
},
  "geometry": {"coordinates":[10.4192142487,52.1481628418],"type":"Point"}
}