{
  "type": "Feature",
  "properties": {
    "iso:country":"DE",
    "sg:address":"Schulzenstr. 25",
    "sg:city":"Mannheim",
    "sg:phone":"+49 621/703733",
    "sg:postcode":"68259",
    "sg:province":"Baden-W\u00fcrttemberg",
    "wof:name":"Prinz Max",
    "wof:placetype":"venue"
},
  "geometry": {"coordinates":[8.5510454178,49.497756958],"type":"Point"}
}