{
  "type": "Feature",
  "properties": {
    "iso:country":"DE",
    "sg:address":"Am Lerchenschlag 5",
    "sg:city":"Erfurt",
    "sg:postcode":"99099",
    "sg:province":"Th\u00fcringen",
    "wof:name":"Deutsche Verm\u00f6gensberatung Ag",
    "wof:placetype":"venue"
},
  "geometry": {"coordinates":[11.0741434097,50.9668769836],"type":"Point"}
}