{
  "type": "Feature",
  "properties": {
    "iso:country":"DE",
    "sg:address":"Hauptstr. 85-87",
    "sg:city":"Sprockh\u00f6vel",
    "sg:postcode":"45549",
    "sg:province":"Nordrhein-Westfalen",
    "wof:name":"Bosselmann Handel Gmbh",
    "wof:placetype":"venue"
},
  "geometry": {"coordinates":[7.246615,51.363182],"type":"Point"}
}