{
  "type": "Feature",
  "properties": {
    "iso:country":"DE",
    "sg:address":"Hauptstr 30",
    "sg:city":"Wagenfeld",
    "sg:phone":"+49 5444/5501",
    "sg:postcode":"49419",
    "sg:province":"Niedersachsen",
    "wof:name":"Dehlfing Kg",
    "wof:placetype":"venue"
},
  "geometry": {"coordinates":[8.5852298737,52.5503349304],"type":"Point"}
}