{
  "type": "Feature",
  "properties": {
    "iso:country":"DE",
    "sg:address":"Holmmoorweg 60",
    "sg:city":"Quickborn",
    "sg:phone":"+49 4106/69290",
    "sg:postcode":"25451",
    "sg:province":"Schleswig-Holstein",
    "wof:name":"Bundesautobahnrastst\u00e4tte Holmmoor-westseite",
    "wof:placetype":"venue"
},
  "geometry": {"coordinates":[9.9383401871,53.7205505371],"type":"Point"}
}