{
  "type": "Feature",
  "properties": {
    "iso:country":"DE",
    "sg:address":"Neutorstr. 8",
    "sg:city":"Emden",
    "sg:phone":"+49 4921/24314",
    "sg:postcode":"26721",
    "sg:province":"Niedersachsen",
    "wof:name":"A. Engbers Gmbh & Co.",
    "wof:placetype":"venue"
},
  "geometry": {"coordinates":[7.206506,53.367016],"type":"Point"}
}