{
  "type": "Feature",
  "properties": {
    "iso:country":"DE",
    "sg:address":"Auf der Schanze 41",
    "sg:city":"Bad Homburg",
    "sg:phone":"+49 6172/450442",
    "sg:postcode":"61352",
    "sg:province":"Hessen",
    "wof:name":"C. Hischke",
    "wof:placetype":"venue"
},
  "geometry": {"coordinates":[8.6348686218,50.2171440125],"type":"Point"}
}