{
  "type": "Feature",
  "properties": {
    "iso:country":"DE",
    "sg:address":"Lindenbergstr. 5",
    "sg:city":"Breitenbach",
    "sg:phone":"+49 6675/337",
    "sg:postcode":"36287",
    "sg:province":"Hessen",
    "wof:name":"Ev. Pfarramt Breitenbach",
    "wof:placetype":"venue"
},
  "geometry": {"coordinates":[9.3135375977,51.2843742371],"type":"Point"}
}