{
  "type": "Feature",
  "properties": {
    "iso:country":"DE",
    "sg:address":"Hofplan 3",
    "sg:city":"Neumarkt",
    "sg:phone":"+49 9181/31778",
    "sg:postcode":"92318",
    "sg:province":"Bayern",
    "wof:name":"Kath. Pfarramt Zu Unserer Lieben Frau",
    "wof:placetype":"venue"
},
  "geometry": {"coordinates":[11.4612264633,49.2807693481],"type":"Point"}
}