{
  "type": "Feature",
  "properties": {
    "iso:country":"DE",
    "sg:address":"Siedlungsweg 24",
    "sg:city":"Blankenhagen",
    "sg:phone":"+49 38201/499",
    "sg:postcode":"18182",
    "sg:province":"Mecklenburg-Vorpommern",
    "wof:name":"Claus Krupke",
    "wof:placetype":"venue"
},
  "geometry": {"coordinates":[12.3442840576,54.165435791],"type":"Point"}
}