{
  "type": "Feature",
  "properties": {
    "iso:country":"DE",
    "sg:address":"Zur Bullenwiese 2",
    "sg:city":"Friedland",
    "sg:phone":"+49 39601/2860",
    "sg:postcode":"17098",
    "sg:province":"Mecklenburg-Vorpommern",
    "wof:name":"Keilberg & Kr\u00fcger Gmbh",
    "wof:placetype":"venue"
},
  "geometry": {"coordinates":[13.562325,53.679764],"type":"Point"}
}