{
  "type": "Feature",
  "properties": {
    "iso:country":"DE",
    "sg:address":"Gemeindehof 8",
    "sg:city":"Goslar",
    "sg:postcode":"38640",
    "sg:province":"Niedersachsen",
    "wof:name":"Ev.-luth. Kirchenverband",
    "wof:placetype":"venue"
},
  "geometry": {"coordinates":[10.4287052155,51.9050788879],"type":"Point"}
}