{
  "type": "Feature",
  "properties": {
    "iso:country":"DE",
    "sg:address":"Parkstr. 12",
    "sg:city":"Gr\u00f6benzell",
    "sg:phone":"+49 8142/8887",
    "sg:postcode":"82194",
    "sg:province":"Bayern",
    "wof:name":"Detlef Ballhorn Rechtsanwalt",
    "wof:placetype":"venue"
},
  "geometry": {"coordinates":[11.3665809631,48.1978111267],"type":"Point"}
}