{
  "type": "Feature",
  "properties": {
    "iso:country":"DE",
    "sg:address":"Am Druvendriesch 33",
    "sg:city":"H\u00fcrth",
    "sg:phone":"+49 2233/46691",
    "sg:postcode":"50354",
    "sg:province":"Nordrhein-Westfalen",
    "wof:name":"Jackpot Gmbh",
    "wof:placetype":"venue"
},
  "geometry": {"coordinates":[6.8925199509,50.8553009033],"type":"Point"}
}