{
  "type": "Feature",
  "properties": {
    "iso:country":"DE",
    "sg:address":"Dorfplatz 1",
    "sg:city":"S\u00f6chtenau",
    "sg:phone":"+49 8055/8720",
    "sg:postcode":"83139",
    "sg:province":"Bayern",
    "wof:name":"Praxis Dr. Med. Beushausen \u00c4rzte F\u00fcr Allgemeinmedizin",
    "wof:placetype":"venue"
},
  "geometry": {"coordinates":[12.2307405472,47.9317550659],"type":"Point"}
}