{
  "type": "Feature",
  "properties": {
    "iso:country":"DE",
    "sg:address":"Lutterweg 27",
    "sg:city":"Hermannsburg",
    "sg:phone":"+49 5052/978832",
    "sg:postcode":"29320",
    "sg:province":"Niedersachsen",
    "wof:name":"Restaurant May Flower",
    "wof:placetype":"venue"
},
  "geometry": {"coordinates":[10.0939235687,52.836971283],"type":"Point"}
}