{
  "type": "Feature",
  "properties": {
    "iso:country":"DE",
    "sg:address":"Steinstr. 1",
    "sg:city":"Rathenow",
    "sg:phone":"+49 3385/513445",
    "sg:postcode":"14712",
    "sg:province":"Brandenburg",
    "wof:name":"Altst\u00e4dtische Apotheke",
    "wof:placetype":"venue"
},
  "geometry": {"coordinates":[12.335098,52.607281],"type":"Point"}
}