{
  "type": "Feature",
  "properties": {
    "iso:country":"DE",
    "sg:address":"Wilhelmstr. 123",
    "sg:city":"Hamm",
    "sg:phone":"+49 2381/441750",
    "sg:postcode":"59067",
    "sg:province":"Nordrhein-Westfalen",
    "wof:name":"Aslan",
    "wof:placetype":"venue"
},
  "geometry": {"coordinates":[7.796131134,51.6694641113],"type":"Point"}
}