{
  "type": "Feature",
  "properties": {
    "iso:country":"DE",
    "sg:address":"K\u00f6tterberg 9",
    "sg:city":"Marsberg",
    "sg:phone":"+49 2991/254",
    "sg:postcode":"34431",
    "sg:province":"Nordrhein-Westfalen",
    "wof:name":"Katholisches Pfarramt St. Vitus",
    "wof:placetype":"venue"
},
  "geometry": {"coordinates":[8.766450882,51.402797699],"type":"Point"}
}