{
  "type": "Feature",
  "properties": {
    "iso:country":"DE",
    "sg:address":"Northeimer Str. 45",
    "sg:city":"Warburg",
    "sg:phone":"+49 5641/2892",
    "sg:postcode":"34414",
    "sg:province":"Nordrhein-Westfalen",
    "wof:name":"Karl Brenke",
    "wof:placetype":"venue"
},
  "geometry": {"coordinates":[9.131334,51.530884],"type":"Point"}
}