{
  "type": "Feature",
  "properties": {
    "iso:country":"DE",
    "sg:address":"M\u00f6hlenh\u00f6rn 20",
    "sg:city":"Krummh\u00f6rn",
    "sg:phone":"+49 4923/1219",
    "sg:postcode":"26736",
    "sg:province":"Niedersachsen",
    "wof:name":"M. Hombergs Masseur",
    "wof:placetype":"venue"
},
  "geometry": {"coordinates":[7.086853,53.4361],"type":"Point"}
}