{
  "type": "Feature",
  "properties": {
    "iso:country":"DE",
    "sg:address":"Naumannstr. 3",
    "sg:city":"Dresden",
    "sg:phone":"+49 351/3452255",
    "sg:postcode":"01309",
    "sg:province":"Sachsen",
    "wof:name":"Apotheke Am Blauen Wunder",
    "wof:placetype":"venue"
},
  "geometry": {"coordinates":[13.804936,51.053047],"type":"Point"}
}