{
  "type": "Feature",
  "properties": {
    "iso:country":"DE",
    "sg:address":"Am Hochwald 30g",
    "sg:city":"Kleinmachnow",
    "sg:phone":"+49 33203/78947",
    "sg:postcode":"14532",
    "sg:province":"Brandenburg",
    "wof:name":"Sds International Marketing Gbr",
    "wof:placetype":"venue"
},
  "geometry": {"coordinates":[13.216178894,52.4014968872],"type":"Point"}
}