{
  "type": "Feature",
  "properties": {
    "iso:country":"DE",
    "sg:address":"Kirchenstr.",
    "sg:city":"Kleinblittersdorf",
    "sg:postcode":"66271",
    "sg:province":"Saarland",
    "wof:name":"Kath. \u00d6ffentliche Bibliothek",
    "wof:placetype":"venue"
},
  "geometry": {"coordinates":[7.08811,49.167439],"type":"Point"}
}