{
  "type": "Feature",
  "properties": {
    "iso:country":"DE",
    "sg:address":"Paul-Junius-Str. 2",
    "sg:city":"Berlin",
    "sg:postcode":"10367",
    "sg:province":"Berlin",
    "wof:name":"Ohne Abseits Uwe Braden",
    "wof:placetype":"venue"
},
  "geometry": {"coordinates":[13.4736442566,52.5208892822],"type":"Point"}
}