{
  "type": "Feature",
  "properties": {
    "iso:country":"DE",
    "sg:address":"Industriestr. 21",
    "sg:city":"Kevelaer",
    "sg:postcode":"47623",
    "sg:province":"Nordrhein-Westfalen",
    "wof:name":"Webscreen Internetdesign Und -providing Gmbh",
    "wof:placetype":"venue"
},
  "geometry": {"coordinates":[6.2694120407,51.580783844],"type":"Point"}
}