{
  "type": "Feature",
  "properties": {
    "iso:country":"DE",
    "sg:address":"Im Bogen 25",
    "sg:city":"Westertimke",
    "sg:postcode":"27412",
    "sg:province":"Niedersachsen",
    "wof:name":"Blitzschnell-kurier Inh. Uwe Michael Daum E. K.",
    "wof:placetype":"venue"
},
  "geometry": {"coordinates":[9.133852,53.235664],"type":"Point"}
}