{
  "type": "Feature",
  "properties": {
    "iso:country":"DE",
    "sg:address":"Sch\u00f6nhauser Str. 26",
    "sg:city":"Berlin",
    "sg:phone":"+49 30/91209210",
    "sg:postcode":"13158",
    "sg:province":"Berlin",
    "wof:name":"Hans-helmut N\u00fcrnberg",
    "wof:placetype":"venue"
},
  "geometry": {"coordinates":[13.3924064636,52.5953216553],"type":"Point"}
}