{
  "type": "Feature",
  "properties": {
    "iso:country":"DE",
    "sg:address":"In Der Dehne 6",
    "sg:city":"Dransfeld",
    "sg:phone":"+49 4955/022574",
    "sg:postcode":"37127",
    "sg:province":"Niedersachsen",
    "wof:name":"Polyroof Karosserie- U. Fahrzeugbau Gebr. G\u00dcnther Ohg",
    "wof:placetype":"venue"
},
  "geometry": {"coordinates":[9.7657709122,51.5028076172],"type":"Point"}
}