{
  "type": "Feature",
  "properties": {
    "iso:country":"DE",
    "sg:address":"Weinbergstrasse 19",
    "sg:city":"Angelbachtal",
    "sg:phone":"+49 4972/657555",
    "sg:postcode":"74918",
    "sg:province":"Baden-W\u00fcrttemberg",
    "wof:name":"Ponick Invest",
    "wof:placetype":"venue"
},
  "geometry": {"coordinates":[8.777866,49.2374],"type":"Point"}
}