{
  "type": "Feature",
  "properties": {
    "iso:country":"DE",
    "sg:address":"Kleiner Ort 6",
    "sg:city":"Bremen",
    "sg:phone":"+49 421/207640",
    "sg:postcode":"28357",
    "sg:province":"Bremen",
    "wof:name":"J. Und G. Renzelmann Gmbh",
    "wof:placetype":"venue"
},
  "geometry": {"coordinates":[8.8808231354,53.1092987061],"type":"Point"}
}