{
  "type": "Feature",
  "properties": {
    "iso:country":"DE",
    "sg:address":"Dr.-Martin-Luther-King-Str. 34",
    "sg:city":"Schwerin",
    "sg:phone":"+49 385/3261475",
    "sg:postcode":"19061",
    "sg:province":"Mecklenburg-Vorpommern",
    "wof:name":"A. Budzien Immobilienmakler",
    "wof:placetype":"venue"
},
  "geometry": {"coordinates":[11.4274940491,53.6001815796],"type":"Point"}
}