{
  "type": "Feature",
  "properties": {
    "iso:country":"DE",
    "sg:address":"Helmstedter Str. 135",
    "sg:city":"Braunschweig",
    "sg:phone":"+49 531/796522",
    "sg:postcode":"38102",
    "sg:province":"Niedersachsen",
    "wof:name":"Restaurant Espana",
    "wof:placetype":"venue"
},
  "geometry": {"coordinates":[10.5440120697,52.2588500977],"type":"Point"}
}