{
  "type": "Feature",
  "properties": {
    "iso:country":"DE",
    "sg:address":"Hintere Dorfstr. 15a",
    "sg:city":"Obercunnersdorf",
    "sg:postcode":"02708",
    "sg:province":"Sachsen",
    "wof:name":"Berger Raumsysteme Gmbh",
    "wof:placetype":"venue"
},
  "geometry": {"coordinates":[14.670460701,51.0366668701],"type":"Point"}
}