{
  "type": "Feature",
  "properties": {
    "iso:country":"DE",
    "sg:address":"Burgwall 22",
    "sg:city":"Wusterhausen",
    "sg:phone":"+49 33979/14595",
    "sg:postcode":"16868",
    "sg:province":"Brandenburg",
    "wof:name":"Gellhorn Bau Gmbh",
    "wof:placetype":"venue"
},
  "geometry": {"coordinates":[12.462924,52.894302],"type":"Point"}
}