{
  "type": "Feature",
  "properties": {
    "iso:country":"DE",
    "sg:address":"Holl\u00e4ndische Str. 96-98",
    "sg:city":"Kassel",
    "sg:phone":"+49 5671/2236",
    "sg:postcode":"34127",
    "sg:province":"Hessen",
    "wof:name":"Friedrich A. Bank Kg",
    "wof:placetype":"venue"
},
  "geometry": {"coordinates":[9.499339,51.329575],"type":"Point"}
}