{
  "type": "Feature",
  "properties": {
    "iso:country":"DE",
    "sg:address":"Parkstrasse 28",
    "sg:city":"Jahnsdorf",
    "sg:phone":"+49 3721/29050",
    "sg:postcode":"09387",
    "sg:province":"Sachsen",
    "wof:name":"Kaps Elektronik",
    "wof:placetype":"venue"
},
  "geometry": {"coordinates":[12.8625164032,50.7504501343],"type":"Point"}
}