{
  "type": "Feature",
  "properties": {
    "iso:country":"DE",
    "sg:address":"Stettiner Str. 11",
    "sg:city":"Hungen",
    "sg:phone":"+49 6402/1299",
    "sg:postcode":"35410",
    "sg:province":"Hessen",
    "wof:name":"Bernd M\u00fcller Elektroinstallation",
    "wof:placetype":"venue"
},
  "geometry": {"coordinates":[8.887003,50.474976],"type":"Point"}
}