{
  "type": "Feature",
  "properties": {
    "iso:country":"DE",
    "sg:address":"Mittlethalstr. 60",
    "sg:city":"Waldaschaff",
    "sg:phone":"+49 6095/2945",
    "sg:postcode":"63857",
    "sg:province":"Bayern",
    "wof:name":"Kleiner B\u00e4r Gertrud Wild",
    "wof:placetype":"venue"
},
  "geometry": {"coordinates":[9.317975,49.965958],"type":"Point"}
}