{
  "type": "Feature",
  "properties": {
    "iso:country":"DE",
    "sg:address":"Hasenheide 54",
    "sg:city":"Berlin",
    "sg:postcode":"10967",
    "sg:province":"Berlin",
    "wof:name":"Umweltform Berlin Auferstehungskirche Gmbh",
    "wof:placetype":"venue"
},
  "geometry": {"coordinates":[13.4101266861,52.4889373779],"type":"Point"}
}