{
  "type": "Feature",
  "properties": {
    "iso:country":"DE",
    "sg:address":"Leibnizstr. 56",
    "sg:city":"Berlin",
    "sg:phone":"+49 30/8811641",
    "sg:postcode":"10629",
    "sg:province":"Berlin",
    "wof:name":"Buchmann Und St\u00f6cklein Rechtsanw\u00e4lte",
    "wof:placetype":"venue"
},
  "geometry": {"coordinates":[13.3129701614,52.5016021729],"type":"Point"}
}