{
  "type": "Feature",
  "properties": {
    "iso:country":"DE",
    "sg:address":"Gr\u00e4frather Str. 124",
    "sg:city":"Wuppertal",
    "sg:phone":"+49 202/73910",
    "sg:postcode":"42329",
    "sg:province":"Nordrhein-Westfalen",
    "wof:name":"Tesch Gmbh",
    "wof:placetype":"venue"
},
  "geometry": {"coordinates":[7.0715398788,51.2230911255],"type":"Point"}
}