{
  "type": "Feature",
  "properties": {
    "iso:country":"DE",
    "sg:address":"Gadebuscher Str. 10",
    "sg:city":"Passow",
    "sg:phone":"+49 3886/2270",
    "sg:postcode":"19205",
    "sg:province":"Mecklenburg-Vorpommern",
    "wof:name":"Gerhard Bockhold Tischlerei Gmbh",
    "wof:placetype":"venue"
},
  "geometry": {"coordinates":[11.14919,53.722309],"type":"Point"}
}