{
  "type": "Feature",
  "properties": {
    "iso:country":"DE",
    "sg:address":"Uelsener Str. 4",
    "sg:city":"Wilsum",
    "sg:phone":"+49 5945/316",
    "sg:postcode":"49849",
    "sg:province":"Niedersachsen",
    "wof:name":"L. V\u00f6lkering",
    "wof:placetype":"venue"
},
  "geometry": {"coordinates":[6.855427,52.528854],"type":"Point"}
}