{
  "type": "Feature",
  "properties": {
    "iso:country":"DE",
    "sg:address":"Krusemarker Str. 5",
    "sg:city":"Hindenburg",
    "sg:phone":"+49 39394/81450",
    "sg:postcode":"39596",
    "sg:province":"Sachsen-Anhalt",
    "wof:name":"Falke Bauunternehmen Gmbh",
    "wof:placetype":"venue"
},
  "geometry": {"coordinates":[11.932672,52.752556],"type":"Point"}
}