{
  "type": "Feature",
  "properties": {
    "iso:country":"DE",
    "sg:address":"Kropsburgstr. 35",
    "sg:city":"Limburgerhof",
    "sg:phone":"+49 6236/8523",
    "sg:postcode":"67117",
    "sg:province":"Rheinland-Pfalz",
    "wof:name":"Enno Reimer Ingenieur",
    "wof:placetype":"venue"
},
  "geometry": {"coordinates":[8.3887844086,49.4146995544],"type":"Point"}
}