{
  "type": "Feature",
  "properties": {
    "iso:country":"DE",
    "sg:address":"Steinweg 75",
    "sg:city":"Quedlinburg",
    "sg:phone":"+49 3946/2493",
    "sg:postcode":"06484",
    "sg:province":"Sachsen-Anhalt",
    "wof:name":"Thomas Haese",
    "wof:placetype":"venue"
},
  "geometry": {"coordinates":[11.1493339539,51.7900848389],"type":"Point"}
}