{
  "type": "Feature",
  "properties": {
    "iso:country":"DE",
    "sg:address":"Kiefernweg 6",
    "sg:city":"Rauenberg",
    "sg:phone":"+49 6222/660126",
    "sg:postcode":"69231",
    "sg:province":"Baden-W\u00fcrttemberg",
    "wof:name":"K. Sauer",
    "wof:placetype":"venue"
},
  "geometry": {"coordinates":[8.7029886246,49.2732391357],"type":"Point"}
}