{
  "type": "Feature",
  "properties": {
    "iso:country":"DE",
    "sg:address":"Wiesenweg 8",
    "sg:city":"Rosenheim",
    "sg:phone":"+49 8031/62805",
    "sg:postcode":"83026",
    "sg:province":"Bayern",
    "wof:name":"Planungs- Und Bauleitungsb\u00fcro Sandor & Schubert Gmbh",
    "wof:placetype":"venue"
},
  "geometry": {"coordinates":[12.1295003891,47.8283233643],"type":"Point"}
}