{
  "type": "Feature",
  "properties": {
    "iso:country":"DE",
    "sg:address":"Hochstr. 16",
    "sg:city":"Mittenwald",
    "sg:phone":"+49 8823/1569",
    "sg:postcode":"82481",
    "sg:province":"Bayern",
    "wof:name":"Cafe Konditorei B\u00e4ckerei Haller",
    "wof:placetype":"venue"
},
  "geometry": {"coordinates":[11.2613191605,47.4417610168],"type":"Point"}
}