{
  "type": "Feature",
  "properties": {
    "iso:country":"DE",
    "sg:address":"Zeiler Str. 41",
    "sg:city":"Ha\u00dffurt",
    "sg:phone":"+49 9521/1381",
    "sg:postcode":"97437",
    "sg:province":"Bayern",
    "wof:name":"Erik Walther Gmbh & Co.",
    "wof:placetype":"venue"
},
  "geometry": {"coordinates":[10.5226716995,50.0310134888],"type":"Point"}
}