{
  "type": "Feature",
  "properties": {
    "iso:country":"DE",
    "sg:address":"Brabanter Str. 5",
    "sg:city":"Weilerswist",
    "sg:phone":"+49 2251/3067",
    "sg:postcode":"53919",
    "sg:province":"Nordrhein-Westfalen",
    "wof:name":"F. Altmann",
    "wof:placetype":"venue"
},
  "geometry": {"coordinates":[6.798296,50.710735],"type":"Point"}
}