{
  "type": "Feature",
  "properties": {
    "iso:country":"DE",
    "sg:address":"Kramgasse 5",
    "sg:city":"Regensburg",
    "sg:phone":"+49 941/52992",
    "sg:postcode":"93047",
    "sg:province":"Bayern",
    "wof:name":"Karl Krammer Inh. Friedrich Hegenbart",
    "wof:placetype":"venue"
},
  "geometry": {"coordinates":[12.0965442657,49.0198287964],"type":"Point"}
}