{
  "type": "Feature",
  "properties": {
    "iso:country":"DE",
    "sg:address":"Dorfstr. 50",
    "sg:city":"Lage",
    "sg:phone":"+49 5941/4313",
    "sg:postcode":"49828",
    "sg:province":"Niedersachsen",
    "wof:name":"Jan Arends",
    "wof:placetype":"venue"
},
  "geometry": {"coordinates":[6.961755,52.467133],"type":"Point"}
}