{
  "type": "Feature",
  "properties": {
    "iso:country":"DE",
    "sg:address":"Winzlarer Str. 14",
    "sg:city":"Rehburg-Loccum",
    "sg:phone":"+49 5037/98713",
    "sg:postcode":"31547",
    "sg:province":"Niedersachsen",
    "wof:name":"B. Busche Gmbh",
    "wof:placetype":"venue"
},
  "geometry": {"coordinates":[9.2283658981,52.4628143311],"type":"Point"}
}