{
  "type": "Feature",
  "properties": {
    "iso:country":"DE",
    "sg:address":"M\u00f6nchshofstr. 35",
    "sg:city":"Viechtach",
    "sg:phone":"+49 9942/431",
    "sg:postcode":"94234",
    "sg:province":"Bayern",
    "wof:name":"Maschinen- Und Betriebs- Hilfsring K\u00f6tzing-viechtach",
    "wof:placetype":"venue"
},
  "geometry": {"coordinates":[12.889304,49.075993],"type":"Point"}
}