{
  "type": "Feature",
  "properties": {
    "iso:country":"DE",
    "sg:address":"Silzweg 26",
    "sg:city":"Hanhofen",
    "sg:phone":"+49 6344/8369",
    "sg:postcode":"67374",
    "sg:province":"Rheinland-Pfalz",
    "wof:name":"Kr\u00fcger Transport Gmbh",
    "wof:placetype":"venue"
},
  "geometry": {"coordinates":[8.3415460587,49.3113441467],"type":"Point"}
}