{
  "type": "Feature",
  "properties": {
    "iso:country":"DE",
    "sg:address":"Waldeckstr. 26",
    "sg:city":"Albershausen",
    "sg:phone":"+49 7161/939331",
    "sg:postcode":"73095",
    "sg:province":"Baden-W\u00fcrttemberg",
    "wof:name":"M. Schlotz",
    "wof:placetype":"venue"
},
  "geometry": {"coordinates":[9.569332,48.698936],"type":"Point"}
}