{
  "type": "Feature",
  "properties": {
    "iso:country":"DE",
    "sg:address":"Friedrichstr. 12",
    "sg:city":"Neuried",
    "sg:phone":"+49 7807/2339",
    "sg:postcode":"77743",
    "sg:province":"Baden-W\u00fcrttemberg",
    "wof:name":"Walter Reuter",
    "wof:placetype":"venue"
},
  "geometry": {"coordinates":[7.807484,48.464703],"type":"Point"}
}