{
  "type": "Feature",
  "properties": {
    "iso:country":"DE",
    "sg:address":"Br\u00e4uhausstr. 2",
    "sg:city":"M\u00fcnchen",
    "sg:phone":"+49 89/226441",
    "sg:postcode":"80331",
    "sg:province":"Bayern",
    "wof:name":"Redaktion Vorg\u00e4nge Verlag Vorg\u00e4nge E. V.",
    "wof:placetype":"venue"
},
  "geometry": {"coordinates":[11.5796785355,48.1373786926],"type":"Point"}
}