{
  "type": "Feature",
  "properties": {
    "iso:country":"DE",
    "sg:address":"Postplatz 5",
    "sg:city":"Bautzen",
    "sg:phone":"+49 3591/48170",
    "sg:postcode":"02625",
    "sg:province":"Sachsen",
    "wof:name":"Oberlausitzer Kurier/niederschlesischer Kurier",
    "wof:placetype":"venue"
},
  "geometry": {"coordinates":[14.428869,51.177727],"type":"Point"}
}