{
  "type": "Feature",
  "properties": {
    "iso:country":"DE",
    "sg:address":"Waldstr. 31",
    "sg:city":"Stuttgart",
    "sg:phone":"+49 711/762767",
    "sg:postcode":"70597",
    "sg:province":"Baden-W\u00fcrttemberg",
    "wof:name":"Walter Keller",
    "wof:placetype":"venue"
},
  "geometry": {"coordinates":[9.1790323257,48.7478141785],"type":"Point"}
}