{
  "type": "Feature",
  "properties": {
    "iso:country":"DE",
    "sg:address":"Birkenweg 2",
    "sg:city":"Kuhfelde",
    "sg:phone":"+49 39035/403",
    "sg:postcode":"29416",
    "sg:province":"Sachsen-Anhalt",
    "wof:name":"E. Mentzel",
    "wof:placetype":"venue"
},
  "geometry": {"coordinates":[11.109266,52.784309],"type":"Point"}
}