{
  "type": "Feature",
  "properties": {
    "iso:country":"DE",
    "sg:address":"Berliner Str. 921",
    "sg:city":"K\u00f6ln",
    "sg:phone":"+49 221/601113",
    "sg:postcode":"51069",
    "sg:province":"Nordrhein-Westfalen",
    "wof:name":"Speedy",
    "wof:placetype":"venue"
},
  "geometry": {"coordinates":[7.038577,51.000118],"type":"Point"}
}