{
  "type": "Feature",
  "properties": {
    "iso:country":"DE",
    "sg:address":"Markt 2",
    "sg:city":"Mettingen",
    "sg:phone":"+49 5452/97100",
    "sg:postcode":"49497",
    "sg:province":"Nordrhein-Westfalen",
    "wof:name":"E\u00dflage & Vo\u00df Gmbh",
    "wof:placetype":"venue"
},
  "geometry": {"coordinates":[7.7800130844,52.3154182434],"type":"Point"}
}