{
  "type": "Feature",
  "properties": {
    "iso:country":"DE",
    "sg:address":"Rodgaustr. 46",
    "sg:city":"Dietzenbach",
    "sg:phone":"+49 6074/29724",
    "sg:postcode":"63128",
    "sg:province":"Hessen",
    "wof:name":"Ls Bauunternehmen Gmbh",
    "wof:placetype":"venue"
},
  "geometry": {"coordinates":[8.783149,50.013172],"type":"Point"}
}