{
  "type": "Feature",
  "properties": {
    "iso:country":"DE",
    "sg:address":"Theaterstr 19",
    "sg:city":"W\u00fcrzburg",
    "sg:phone":"+49 931/3503441",
    "sg:postcode":"97070",
    "sg:province":"Bayern",
    "wof:name":"B\u00fcrgerspital-weingut",
    "wof:placetype":"venue"
},
  "geometry": {"coordinates":[9.9356307983,49.7953872681],"type":"Point"}
}