{
  "type": "Feature",
  "properties": {
    "iso:country":"DE",
    "sg:address":"Tumringer Str. 175-177",
    "sg:city":"L\u00f6rrach",
    "sg:phone":"+49 7621/10626",
    "sg:postcode":"79539",
    "sg:province":"Baden-W\u00fcrttemberg",
    "wof:name":"Casper Blue Inh. G. Regel",
    "wof:placetype":"venue"
},
  "geometry": {"coordinates":[7.660872,47.61235],"type":"Point"}
}