{
  "type": "Feature",
  "properties": {
    "iso:country":"DE",
    "sg:address":"Hauptstr. 21",
    "sg:city":"Beilngries",
    "sg:postcode":"92339",
    "sg:province":"Bayern",
    "wof:name":"Anton Ullermann",
    "wof:placetype":"venue"
},
  "geometry": {"coordinates":[11.4742240906,49.0345649719],"type":"Point"}
}