{
  "type": "Feature",
  "properties": {
    "iso:country":"DE",
    "sg:address":"Weixdorfer Str. 34",
    "sg:city":"Ottendorf-Okrilla",
    "sg:phone":"+49 35205/73080",
    "sg:postcode":"01458",
    "sg:province":"Sachsen",
    "wof:name":"Dietmar Chalmakoff",
    "wof:placetype":"venue"
},
  "geometry": {"coordinates":[13.788424,51.177032],"type":"Point"}
}