{
  "type": "Feature",
  "properties": {
    "iso:country":"DE",
    "sg:address":"Marienstr. 1",
    "sg:city":"Stuttgart",
    "sg:phone":"+49 711/221911",
    "sg:postcode":"70178",
    "sg:province":"Baden-W\u00fcrttemberg",
    "wof:name":"Sattler Und Partner Rechtsanw\u00e4lte Und Notare",
    "wof:placetype":"venue"
},
  "geometry": {"coordinates":[9.1738481522,48.7736091614],"type":"Point"}
}