{
  "type": "Feature",
  "properties": {
    "iso:country":"DE",
    "sg:address":"Alten-Busecker Str.",
    "sg:city":"Gie\u00dfen",
    "sg:phone":"+49 641/51979",
    "sg:postcode":"35396",
    "sg:province":"Hessen",
    "wof:name":"Waldfrieden",
    "wof:placetype":"venue"
},
  "geometry": {"coordinates":[8.7128143311,50.6088790894],"type":"Point"}
}