{
  "type": "Feature",
  "properties": {
    "iso:country":"DE",
    "sg:address":"Lindenstr. 12a",
    "sg:city":"Neustadt",
    "sg:phone":"+49 6344/936171",
    "sg:postcode":"67434",
    "sg:province":"Rheinland-Pfalz",
    "wof:name":"Pfalz-web Internetservice F\u00fcr Den Raum Pfalz.",
    "wof:placetype":"venue"
},
  "geometry": {"coordinates":[8.128789,49.335171],"type":"Point"}
}