{
  "type": "Feature",
  "properties": {
    "iso:country":"DE",
    "sg:address":"Klosterweg 35",
    "sg:city":"Wegberg",
    "sg:phone":"+49 2436/339011",
    "sg:postcode":"41844",
    "sg:province":"Nordrhein-Westfalen",
    "wof:name":"Hekatech Laborbedarf Gmbh",
    "wof:placetype":"venue"
},
  "geometry": {"coordinates":[6.170205,51.152679],"type":"Point"}
}