{
  "type": "Feature",
  "properties": {
    "iso:country":"DE",
    "sg:address":"Hauptstr. 24",
    "sg:city":"Mamming",
    "sg:phone":"+49 9955/241",
    "sg:postcode":"94437",
    "sg:province":"Bayern",
    "wof:name":"Kath. Pfarramt St. Margaretha",
    "wof:placetype":"venue"
},
  "geometry": {"coordinates":[12.6060113907,48.6498985291],"type":"Point"}
}