{
  "type": "Feature",
  "properties": {
    "iso:country":"DE",
    "sg:address":"Samenhandelstr. 41",
    "sg:city":"Reutlingen",
    "sg:phone":"+49 7072/4418",
    "sg:postcode":"72770",
    "sg:province":"Baden-W\u00fcrttemberg",
    "wof:name":"J. Rein",
    "wof:placetype":"venue"
},
  "geometry": {"coordinates":[9.147841,48.431911],"type":"Point"}
}