{
  "type": "Feature",
  "properties": {
    "iso:country":"DE",
    "sg:address":"Uracher Str. 10",
    "sg:city":"Dettingen",
    "sg:phone":"+49 4971/2371021",
    "sg:postcode":"72581",
    "sg:province":"Baden-W\u00fcrttemberg",
    "wof:name":"Kreissparkasse Reutlingen",
    "wof:placetype":"venue"
},
  "geometry": {"coordinates":[9.346816,48.529003],"type":"Point"}
}