{
  "type": "Feature",
  "properties": {
    "iso:country":"DE",
    "sg:address":"Rheinstr. 21",
    "sg:city":"Bad Bellingen",
    "sg:phone":"+49 7635/422",
    "sg:postcode":"79415",
    "sg:province":"Baden-W\u00fcrttemberg",
    "wof:name":"Bernhard",
    "wof:placetype":"venue"
},
  "geometry": {"coordinates":[7.5561089516,47.7310676575],"type":"Point"}
}