{
  "type": "Feature",
  "properties": {
    "iso:country":"DE",
    "sg:address":"Friedrichsthaler Str.",
    "sg:city":"Olpe",
    "sg:phone":"+49 2761/92610",
    "sg:postcode":"57462",
    "sg:province":"Nordrhein-Westfalen",
    "wof:name":"Fleischmarkt Olpe Gmbh",
    "wof:placetype":"venue"
},
  "geometry": {"coordinates":[7.840572834,51.0038146973],"type":"Point"}
}