{
  "type": "Feature",
  "properties": {
    "iso:country":"DE",
    "sg:address":"Tauentzienstr. 8",
    "sg:city":"Berlin",
    "sg:phone":"+49 30/2646464",
    "sg:postcode":"10789",
    "sg:province":"Berlin",
    "wof:name":"Shok Fashion Fts Gmbh",
    "wof:placetype":"venue"
},
  "geometry": {"coordinates":[13.338318,52.503777],"type":"Point"}
}