{
  "type": "Feature",
  "properties": {
    "iso:country":"DE",
    "sg:address":"G\u00e4rtnerstr. 4",
    "sg:city":"Sch\u00f6llnach",
    "sg:phone":"+49 9903/321",
    "sg:postcode":"94508",
    "sg:province":"Bayern",
    "wof:name":"Johann Eden Grabdenkm\u00e4ler",
    "wof:placetype":"venue"
},
  "geometry": {"coordinates":[13.1816959381,48.7547454834],"type":"Point"}
}