{
  "type": "Feature",
  "properties": {
    "iso:country":"DE",
    "sg:address":"Stiegstr 60",
    "sg:city":"Br\u00fcggen",
    "sg:phone":"+49 2157/14190",
    "sg:postcode":"41379",
    "sg:province":"Nordrhein-Westfalen",
    "wof:name":"Peter Van Eyk Gmbh & Co Kg",
    "wof:placetype":"venue"
},
  "geometry": {"coordinates":[6.1815671921,51.2819633484],"type":"Point"}
}