{
  "type": "Feature",
  "properties": {
    "iso:country":"DE",
    "sg:address":"Rosenstr. 94",
    "sg:city":"Oberhausen",
    "sg:phone":"+49 208/801312",
    "sg:postcode":"46049",
    "sg:province":"Nordrhein-Westfalen",
    "wof:name":"Imbi\u00df Marica Planinic",
    "wof:placetype":"venue"
},
  "geometry": {"coordinates":[6.8180999756,51.4792518616],"type":"Point"}
}