{
  "type": "Feature",
  "properties": {
    "iso:country":"DE",
    "sg:address":"Am Brichelberg 5",
    "sg:city":"Kleinblittersdorf",
    "sg:phone":"+49 6805/1674",
    "sg:postcode":"66271",
    "sg:province":"Saarland",
    "wof:name":"Magdalena Scholz",
    "wof:placetype":"venue"
},
  "geometry": {"coordinates":[7.031359,49.168526],"type":"Point"}
}