{
  "type": "Feature",
  "properties": {
    "iso:country":"DE",
    "sg:address":"Louise-Schr\u00f6der-Stra\u00dfe 20",
    "sg:city":"Bergkamen",
    "sg:phone":"+49 2307/6318",
    "sg:postcode":"59192",
    "sg:province":"Nordrhein-Westfalen",
    "wof:name":"Sonnen-apotheke Bergkamen",
    "wof:placetype":"venue"
},
  "geometry": {"coordinates":[7.629335,51.613613],"type":"Point"}
}