{
  "type": "Feature",
  "properties": {
    "iso:country":"DE",
    "sg:address":"Biesenthaler Str. 33",
    "sg:city":"Marienwerder",
    "sg:phone":"+49 3335/688",
    "sg:postcode":"16348",
    "sg:province":"Brandenburg",
    "wof:name":"Herbert Kuke",
    "wof:placetype":"venue"
},
  "geometry": {"coordinates":[13.5996780396,52.8408164978],"type":"Point"}
}