{
  "type": "Feature",
  "properties": {
    "iso:country":"DE",
    "sg:address":"Herrengasse 12",
    "sg:city":"Rudersdorf",
    "sg:postcode":"99628",
    "sg:province":"Th\u00fcringen",
    "wof:name":"Iweba-bauelemente Gmbh",
    "wof:placetype":"venue"
},
  "geometry": {"coordinates":[11.458006,51.106102],"type":"Point"}
}