{
  "type": "Feature",
  "properties": {
    "iso:country":"DE",
    "sg:address":"Moerser Str. 127",
    "sg:city":"Meerbusch",
    "sg:phone":"+49 2132/960668",
    "sg:postcode":"40667",
    "sg:province":"Nordrhein-Westfalen",
    "wof:name":"Vitos Restaurant",
    "wof:placetype":"venue"
},
  "geometry": {"coordinates":[6.678150177,51.2610816956],"type":"Point"}
}