{
  "type": "Feature",
  "properties": {
    "iso:country":"DE",
    "sg:address":"Gewerbehof Westring 57-61",
    "sg:city":"Recklinghausen",
    "sg:phone":"+49 2361/93220",
    "sg:postcode":"45659",
    "sg:province":"Nordrhein-Westfalen",
    "wof:name":"Sec-com Sicherheits- Und Kommunikationstechnik Gmbh",
    "wof:placetype":"venue"
},
  "geometry": {"coordinates":[7.17396,51.590889],"type":"Point"}
}