{
  "type": "Feature",
  "properties": {
    "iso:country":"DE",
    "sg:address":"Flurweg 11",
    "sg:city":"Neunkirchen",
    "sg:phone":"+49 6821/31452",
    "sg:postcode":"66539",
    "sg:province":"Saarland",
    "wof:name":"E. Skalei",
    "wof:placetype":"venue"
},
  "geometry": {"coordinates":[7.241306,49.324413],"type":"Point"}
}