{
  "type": "Feature",
  "properties": {
    "iso:country":"DE",
    "sg:address":"K\u00f6lner Str. 62",
    "sg:city":"K\u00f6ln",
    "sg:phone":"+49 2234/76094",
    "sg:postcode":"50859",
    "sg:province":"Nordrhein-Westfalen",
    "wof:name":"Ferber Gmbh",
    "wof:placetype":"venue"
},
  "geometry": {"coordinates":[6.843342,50.947174],"type":"Point"}
}