{
  "type": "Feature",
  "properties": {
    "iso:country":"DE",
    "sg:address":"Altenhagener Str. 2",
    "sg:city":"Hagen",
    "sg:phone":"+49 2331/24471",
    "sg:postcode":"58097",
    "sg:province":"Nordrhein-Westfalen",
    "wof:name":"Br\u00fcckensch\u00e4nke",
    "wof:placetype":"venue"
},
  "geometry": {"coordinates":[7.4633731842,51.3649864197],"type":"Point"}
}