{
  "type": "Feature",
  "properties": {
    "iso:country":"DE",
    "sg:address":"Oberf\u00f6hringer Str. 73",
    "sg:city":"M\u00fcnchen",
    "sg:phone":"+49 89/953202",
    "sg:postcode":"81925",
    "sg:province":"Bayern",
    "wof:name":"Dipl.ing. Michael Sepp Architekt",
    "wof:placetype":"venue"
},
  "geometry": {"coordinates":[11.621024,48.163242],"type":"Point"}
}