{
  "type": "Feature",
  "properties": {
    "iso:country":"DE",
    "sg:address":"Leuchtenberger Str. 11",
    "sg:city":"Pfreimd",
    "sg:phone":"+49 9606/463",
    "sg:postcode":"92536",
    "sg:province":"Bayern",
    "wof:name":"R. Ge\u00df",
    "wof:placetype":"venue"
},
  "geometry": {"coordinates":[12.181496,49.494198],"type":"Point"}
}