{
  "type": "Feature",
  "properties": {
    "iso:country":"DE",
    "sg:address":"Albersloher Weg 550",
    "sg:city":"M\u00fcnster",
    "sg:postcode":"48167",
    "sg:province":"Nordrhein-Westfalen",
    "wof:name":"Aldi Gmbh & Co. Kg",
    "wof:placetype":"venue"
},
  "geometry": {"coordinates":[7.6810808182,51.9152679443],"type":"Point"}
}