{
  "type": "Feature",
  "properties": {
    "iso:country":"DE",
    "sg:address":"Monhardt 25",
    "sg:city":"Altensteig",
    "sg:postcode":"72213",
    "sg:province":"Baden-W\u00fcrttemberg",
    "wof:name":"Transfer Logistik Gmbh",
    "wof:placetype":"venue"
},
  "geometry": {"coordinates":[8.644614,48.589687],"type":"Point"}
}