{
  "type": "Feature",
  "properties": {
    "iso:country":"DE",
    "sg:address":"Sonnenbergstr. 8",
    "sg:city":"Garmisch-Partenkirchen",
    "sg:postcode":"82467",
    "sg:province":"Bayern",
    "wof:name":"Aigner Gmbh",
    "wof:placetype":"venue"
},
  "geometry": {"coordinates":[11.111987114,47.494972229],"type":"Point"}
}