{
  "type": "Feature",
  "properties": {
    "iso:country":"DE",
    "sg:address":"Hansestr. 20",
    "sg:city":"Borken",
    "sg:phone":"+49 2861/2072",
    "sg:postcode":"46325",
    "sg:province":"Nordrhein-Westfalen",
    "wof:name":"Peinemann & B\u00f6rgers Gmbh",
    "wof:placetype":"venue"
},
  "geometry": {"coordinates":[6.882882,51.849876],"type":"Point"}
}