{
  "type": "Feature",
  "properties": {
    "iso:country":"DE",
    "sg:address":"An der Alsterschleife 27",
    "sg:city":"Hamburg",
    "sg:phone":"+49 40/6026112",
    "sg:postcode":"22399",
    "sg:province":"Hamburg",
    "wof:name":"Behrmann & Behrmann",
    "wof:placetype":"venue"
},
  "geometry": {"coordinates":[10.0904769897,53.6719779968],"type":"Point"}
}