{
  "type": "Feature",
  "properties": {
    "iso:country":"DE",
    "sg:address":"Edelhof 15",
    "sg:city":"Topfstedt",
    "sg:postcode":"99718",
    "sg:province":"Th\u00fcringen",
    "wof:name":"G. Hotze",
    "wof:placetype":"venue"
},
  "geometry": {"coordinates":[10.832319,51.247898],"type":"Point"}
}