{
  "type": "Feature",
  "properties": {
    "iso:country":"DE",
    "sg:address":"Dorfstr. 10",
    "sg:city":"Ingoldingen",
    "sg:phone":"+49 7355/2380",
    "sg:postcode":"88456",
    "sg:province":"Baden-W\u00fcrttemberg",
    "wof:name":"Josef M\u00fcller",
    "wof:placetype":"venue"
},
  "geometry": {"coordinates":[9.7394390106,47.9878883362],"type":"Point"}
}