{
  "type": "Feature",
  "properties": {
    "iso:country":"DE",
    "sg:address":"Boschstr.",
    "sg:city":"Kaltenkirchen",
    "sg:phone":"+49 4191/4014",
    "sg:postcode":"24568",
    "sg:province":"Schleswig-Holstein",
    "wof:name":"Gerhard Auf Der Heide",
    "wof:placetype":"venue"
},
  "geometry": {"coordinates":[9.97835,53.823029],"type":"Point"}
}