{
  "type": "Feature",
  "properties": {
    "iso:country":"DE",
    "sg:address":"Haylerstr. 31 A",
    "sg:city":"M\u00fcnchen",
    "sg:phone":"+49 89/1492490",
    "sg:postcode":"80993",
    "sg:province":"Bayern",
    "wof:name":"Horst-ferdinand Ernigkeit Architekt",
    "wof:placetype":"venue"
},
  "geometry": {"coordinates":[11.506574,48.188564],"type":"Point"}
}