{
  "type": "Feature",
  "properties": {
    "iso:country":"DE",
    "sg:address":"Wermingser Str. 6",
    "sg:city":"Iserlohn",
    "sg:postcode":"58636",
    "sg:province":"Nordrhein-Westfalen",
    "wof:name":"Deutsche Telekom T-punkt",
    "wof:placetype":"venue"
},
  "geometry": {"coordinates":[7.6983652115,51.3742408752],"type":"Point"}
}