{
  "type": "Feature",
  "properties": {
    "iso:country":"DE",
    "sg:address":"Frauenstr. 32",
    "sg:city":"Bamberg",
    "sg:phone":"+49 951/200123",
    "sg:postcode":"96047",
    "sg:province":"Bayern",
    "wof:name":"Bayerische Beamtenkrankenkasse Versicherungsdienste Bev Gmbh",
    "wof:placetype":"venue"
},
  "geometry": {"coordinates":[10.8890724182,49.8954925537],"type":"Point"}
}