{
  "type": "Feature",
  "properties": {
    "iso:country":"DE",
    "sg:address":"Holstenstr. 22",
    "sg:city":"Hamburg",
    "sg:phone":"+49 40/310345",
    "sg:postcode":"22767",
    "sg:province":"Hamburg",
    "wof:name":"Pizzeria Restaurante Piccoletto",
    "wof:placetype":"venue"
},
  "geometry": {"coordinates":[9.9544887543,53.5529785156],"type":"Point"}
}