{
  "type": "Feature",
  "properties": {
    "iso:country":"DE",
    "sg:address":"W\u00fcrmstr.",
    "sg:city":"Hildrizhausen",
    "sg:phone":"+49 7034/7990",
    "sg:postcode":"71157",
    "sg:province":"Baden-W\u00fcrttemberg",
    "wof:name":"Freibad Hildrizhausen",
    "wof:placetype":"venue"
},
  "geometry": {"coordinates":[8.9730396271,48.6233482361],"type":"Point"}
}