{
  "type": "Feature",
  "properties": {
    "iso:country":"DE",
    "sg:address":"Am Ulmenhof 33",
    "sg:city":"Bedburg",
    "sg:phone":"+49 2463/3766",
    "sg:postcode":"50181",
    "sg:province":"Nordrhein-Westfalen",
    "wof:name":"Wilhelm Frenger",
    "wof:placetype":"venue"
},
  "geometry": {"coordinates":[6.482776165,51.0044059753],"type":"Point"}
}