{
  "type": "Feature",
  "properties": {
    "iso:country":"DE",
    "sg:address":"Schl\u00f6p 10",
    "sg:city":"Nettetal",
    "sg:phone":"+49 2153/2956",
    "sg:postcode":"41334",
    "sg:province":"Nordrhein-Westfalen",
    "wof:name":"Secretis",
    "wof:placetype":"venue"
},
  "geometry": {"coordinates":[6.254556179,51.3350791931],"type":"Point"}
}