{
  "type": "Feature",
  "properties": {
    "iso:country":"DE",
    "sg:address":"Clemensstr 75",
    "sg:city":"M\u00fcnchen",
    "sg:phone":"+49 89/2011949",
    "sg:postcode":"80796",
    "sg:province":"Bayern",
    "wof:name":"Geweba D\u00f6rner Gmbh",
    "wof:placetype":"venue"
},
  "geometry": {"coordinates":[11.572805,48.163548],"type":"Point"}
}