{
  "type": "Feature",
  "properties": {
    "iso:country":"DE",
    "sg:address":"Lenauweg 28",
    "sg:city":"Eislingen",
    "sg:phone":"+49 7161/812518",
    "sg:postcode":"73054",
    "sg:province":"Baden-W\u00fcrttemberg",
    "wof:name":"Helmut Kauderer Architekt",
    "wof:placetype":"venue"
},
  "geometry": {"coordinates":[9.710359,48.688747],"type":"Point"}
}