{
  "type": "Feature",
  "properties": {
    "iso:country":"DE",
    "sg:address":"Hagenrg. 20",
    "sg:city":"Ammerbuch",
    "sg:phone":"+49 4970/3297900",
    "sg:postcode":"72119",
    "sg:province":"Baden-W\u00fcrttemberg",
    "wof:name":"Rmp Gmbh & Co. Kg",
    "wof:placetype":"venue"
},
  "geometry": {"coordinates":[8.905888,48.566586],"type":"Point"}
}