{
  "type": "Feature",
  "properties": {
    "iso:country":"DE",
    "sg:address":"Oberwaldstr. 19",
    "sg:city":"Karlsruhe",
    "sg:phone":"+49 721/404296",
    "sg:postcode":"76227",
    "sg:province":"Baden-W\u00fcrttemberg",
    "wof:name":"K\u00f6nig",
    "wof:placetype":"venue"
},
  "geometry": {"coordinates":[8.4601631165,48.9960746765],"type":"Point"}
}