{
  "type": "Feature",
  "properties": {
    "iso:country":"DE",
    "sg:address":"Scheffelstr.10",
    "sg:city":"Iserlohn",
    "sg:phone":"+49 2371/42114",
    "sg:postcode":"58636",
    "sg:province":"Nordrhein-Westfalen",
    "wof:name":"Schumacher",
    "wof:placetype":"venue"
},
  "geometry": {"coordinates":[7.7036418915,51.4001197815],"type":"Point"}
}