{
  "type": "Feature",
  "properties": {
    "iso:country":"DE",
    "sg:address":"Flachst\u00f6ckheimer Str. 34",
    "sg:city":"Salzgitter",
    "sg:phone":"+49 5341/9705",
    "sg:postcode":"38259",
    "sg:province":"Niedersachsen",
    "wof:name":"Heinrich Heitm\u00fcller",
    "wof:placetype":"venue"
},
  "geometry": {"coordinates":[10.430175,52.097164],"type":"Point"}
}