{
  "type": "Feature",
  "properties": {
    "iso:country":"DE",
    "sg:address":"Kirchgasse 9",
    "sg:city":"Dettelbach",
    "sg:phone":"+49 9324/857",
    "sg:postcode":"97337",
    "sg:province":"Bayern",
    "wof:name":"Karl M\u00fcller",
    "wof:placetype":"venue"
},
  "geometry": {"coordinates":[10.174613,49.82629],"type":"Point"}
}