{
  "type": "Feature",
  "properties": {
    "iso:country":"DE",
    "sg:address":"Kaiserstr. 7",
    "sg:city":"Rosenheim",
    "sg:phone":"+49 8031/15592",
    "sg:postcode":"83022",
    "sg:province":"Bayern",
    "wof:name":"Max Urban",
    "wof:placetype":"venue"
},
  "geometry": {"coordinates":[12.128121,47.857361],"type":"Point"}
}