{
  "type": "Feature",
  "properties": {
    "iso:country":"DE",
    "sg:address":"Meessen 1",
    "sg:city":"Oststeinbek",
    "sg:phone":"+49 40/7148880",
    "sg:postcode":"22113",
    "sg:province":"Schleswig-Holstein",
    "wof:name":"J. Hass Tooltechnik Gmbh",
    "wof:placetype":"venue"
},
  "geometry": {"coordinates":[10.1547832489,53.5486946106],"type":"Point"}
}