{
  "type": "Feature",
  "properties": {
    "iso:country":"DE",
    "sg:address":"Langenberger Str. 55",
    "sg:city":"Gera",
    "sg:phone":"+49 365/438265",
    "sg:postcode":"07552",
    "sg:province":"Th\u00fcringen",
    "wof:name":"D Com Infotec Gesellschaft F\u00fcr Kommunikationssysteme Mbh",
    "wof:placetype":"venue"
},
  "geometry": {"coordinates":[12.060197,50.914886],"type":"Point"}
}