{
  "type": "Feature",
  "properties": {
    "iso:country":"DE",
    "sg:address":"Schnellerstr. 2",
    "sg:city":"Schwaigern",
    "sg:phone":"+49 7138/7756",
    "sg:postcode":"74193",
    "sg:province":"Baden-W\u00fcrttemberg",
    "wof:name":"Wolfgang Ley Massagepraxis",
    "wof:placetype":"venue"
},
  "geometry": {"coordinates":[9.055976,49.140705],"type":"Point"}
}