{
  "type": "Feature",
  "properties": {
    "iso:country":"DE",
    "sg:address":"In der Au 30",
    "sg:city":"Gaildorf",
    "sg:phone":"+49 160 1523885",
    "sg:postcode":"74405",
    "sg:province":"Baden-W\u00fcrttemberg",
    "wof:name":"Roessner Helmut - Gaildorf",
    "wof:placetype":"venue"
},
  "geometry": {"coordinates":[9.764715,49.004929],"type":"Point"}
}