{
  "type": "Feature",
  "properties": {
    "iso:country":"DE",
    "sg:address":"Heerstr. 3",
    "sg:city":"Cuxhaven",
    "sg:phone":"+49 4722/2522",
    "sg:postcode":"27478",
    "sg:province":"Niedersachsen",
    "wof:name":"Hermann Bahr",
    "wof:placetype":"venue"
},
  "geometry": {"coordinates":[8.760645,53.819893],"type":"Point"}
}