{
  "type": "Feature",
  "properties": {
    "iso:country":"DE",
    "sg:address":"Zweidorfer Ring 1",
    "sg:city":"Wendeburg",
    "sg:phone":"+49 5303/2856",
    "sg:postcode":"38176",
    "sg:province":"Niedersachsen",
    "wof:name":"L. Stelzer",
    "wof:placetype":"venue"
},
  "geometry": {"coordinates":[10.377795,52.328449],"type":"Point"}
}