{
  "type": "Feature",
  "properties": {
    "iso:country":"DE",
    "sg:address":"Wilhelmsbader Allee 2",
    "sg:city":"Hanau",
    "sg:phone":"+49 6181/840525",
    "sg:postcode":"63454",
    "sg:province":"Hessen",
    "wof:name":"Glockenturm Immobilien Gmbh",
    "wof:placetype":"venue"
},
  "geometry": {"coordinates":[8.891778,50.144405],"type":"Point"}
}