{
  "type": "Feature",
  "properties": {
    "iso:country":"DE",
    "sg:address":"Hornstr. 1",
    "sg:city":"Trier",
    "sg:phone":"+49 651/87671",
    "sg:postcode":"54294",
    "sg:province":"Rheinland-Pfalz",
    "wof:name":"Gertrud Heidebrecht",
    "wof:placetype":"venue"
},
  "geometry": {"coordinates":[6.621482,49.751842],"type":"Point"}
}