{
  "type": "Feature",
  "properties": {
    "iso:country":"DE",
    "sg:address":"Weidenauer Str. 191",
    "sg:city":"Siegen",
    "sg:phone":"+49 271/45097",
    "sg:postcode":"57076",
    "sg:province":"Nordrhein-Westfalen",
    "wof:name":"Punkt-apotheke",
    "wof:placetype":"venue"
},
  "geometry": {"coordinates":[8.028164,50.895844],"type":"Point"}
}