{
  "type": "Feature",
  "properties": {
    "iso:country":"DE",
    "sg:address":"Sieben Bauern 119",
    "sg:city":"Minden",
    "sg:postcode":"32425",
    "sg:province":"Nordrhein-Westfalen",
    "wof:name":"Joachim Klein",
    "wof:placetype":"venue"
},
  "geometry": {"coordinates":[8.8751602173,52.3078308105],"type":"Point"}
}