{
  "type": "Feature",
  "properties": {
    "iso:country":"DE",
    "sg:address":"Daimlerstr. 19",
    "sg:city":"Rodgau",
    "sg:phone":"+49 6106/876806",
    "sg:postcode":"63110",
    "sg:province":"Hessen",
    "wof:name":"Hgb Baumaschinen Gmbh",
    "wof:placetype":"venue"
},
  "geometry": {"coordinates":[8.898225,50.059574],"type":"Point"}
}