{
  "type": "Feature",
  "properties": {
    "iso:country":"DE",
    "sg:address":"Schmiedegasse 7",
    "sg:city":"K\u00f6ln",
    "sg:phone":"+49 221/7407931",
    "sg:postcode":"50735",
    "sg:province":"Nordrhein-Westfalen",
    "wof:name":"Marianne Senf",
    "wof:placetype":"venue"
},
  "geometry": {"coordinates":[6.946953,50.980789],"type":"Point"}
}