{
  "type": "Feature",
  "properties": {
    "iso:country":"DE",
    "sg:address":"Ostrittrumer Str. 13",
    "sg:city":"Hatten",
    "sg:phone":"+49 4482/927000",
    "sg:postcode":"26209",
    "sg:province":"Niedersachsen",
    "wof:name":"J\u00fcrgen Martin",
    "wof:placetype":"venue"
},
  "geometry": {"coordinates":[8.3238220215,52.9995117188],"type":"Point"}
}