{
  "type": "Feature",
  "properties": {
    "iso:country":"DE",
    "sg:address":"Pariser Str. 350",
    "sg:city":"Kaiserslautern",
    "sg:phone":"+49 631/72037",
    "sg:postcode":"67663",
    "sg:province":"Rheinland-Pfalz",
    "wof:name":"Globetrotter Reiseservice Gmbh",
    "wof:placetype":"venue"
},
  "geometry": {"coordinates":[7.7125401497,49.4385643005],"type":"Point"}
}