{
  "type": "Feature",
  "properties": {
    "iso:country":"DE",
    "sg:address":"Frankstr. 4",
    "sg:city":"Hagen",
    "sg:phone":"+49 2331/42255",
    "sg:postcode":"58135",
    "sg:province":"Nordrhein-Westfalen",
    "wof:name":"Boldt & B\u00f6rsch Ohg",
    "wof:placetype":"venue"
},
  "geometry": {"coordinates":[7.4216599464,51.3478927612],"type":"Point"}
}