{
  "type": "Feature",
  "properties": {
    "iso:country":"DE",
    "sg:address":"Freisinger Str. 22",
    "sg:city":"Ismaning",
    "sg:phone":"+49 89/967549",
    "sg:postcode":"85737",
    "sg:province":"Bayern",
    "wof:name":"Nikolaus Kraus",
    "wof:placetype":"venue"
},
  "geometry": {"coordinates":[11.676437,48.230919],"type":"Point"}
}