{
  "type": "Feature",
  "properties": {
    "iso:country":"DE",
    "sg:address":"Adlgasser Str. 11 a",
    "sg:city":"Inzell",
    "sg:phone":"+49 8665/7105",
    "sg:postcode":"83334",
    "sg:province":"Bayern",
    "wof:name":"Norbert Egger",
    "wof:placetype":"venue"
},
  "geometry": {"coordinates":[12.749252,47.762688],"type":"Point"}
}