{
  "type": "Feature",
  "properties": {
    "iso:country":"DE",
    "sg:address":"Ziegeleiweg 1b",
    "sg:city":"Weimar",
    "sg:phone":"+49 3643/53722",
    "sg:postcode":"99425",
    "sg:province":"Th\u00fcringen",
    "wof:name":"W. Rybarz",
    "wof:placetype":"venue"
},
  "geometry": {"coordinates":[11.3390369415,50.9638748169],"type":"Point"}
}