{
  "type": "Feature",
  "properties": {
    "iso:country":"DE",
    "sg:address":"Heinrich-Schulz-Weg 2b",
    "sg:city":"Hamburg",
    "sg:phone":"+49 40/6776874",
    "sg:postcode":"22149",
    "sg:province":"Hamburg",
    "wof:name":"Monika Sch\u00f6tz",
    "wof:placetype":"venue"
},
  "geometry": {"coordinates":[10.177373,53.597569],"type":"Point"}
}