{
  "type": "Feature",
  "properties": {
    "iso:country":"DE",
    "sg:address":"L\u00f6hner Str. 200",
    "sg:city":"L\u00f6hne",
    "sg:postcode":"32584",
    "sg:province":"Nordrhein-Westfalen",
    "wof:name":"Sch\u00e4ffer Informations- Technik Gmbh",
    "wof:placetype":"venue"
},
  "geometry": {"coordinates":[8.750818,52.2001],"type":"Point"}
}