{
  "type": "Feature",
  "properties": {
    "iso:country":"DE",
    "sg:address":"Industriestr. 85-95",
    "sg:city":"Leipzig",
    "sg:phone":"+49 341/49840",
    "sg:postcode":"04229",
    "sg:province":"Sachsen",
    "wof:name":"Konsum Leipzig Handels- Und Dienstleistungsges. Mbh",
    "wof:placetype":"venue"
},
  "geometry": {"coordinates":[12.3306407928,51.328037262],"type":"Point"}
}