{
  "type": "Feature",
  "properties": {
    "iso:country":"DE",
    "sg:address":"Neckargasse 12",
    "sg:city":"Horb",
    "sg:phone":"+49 7482/7193",
    "sg:postcode":"72160",
    "sg:province":"Baden-W\u00fcrttemberg",
    "wof:name":"Ute O\u00dfwald",
    "wof:placetype":"venue"
},
  "geometry": {"coordinates":[8.635833,48.415874],"type":"Point"}
}