{
  "type": "Feature",
  "properties": {
    "iso:country":"DE",
    "sg:address":"D\u00fcrerstr. 46A",
    "sg:city":"Berlin",
    "sg:postcode":"12203",
    "sg:province":"Berlin",
    "wof:name":"Bjw Bauingenieurges. Mbh",
    "wof:placetype":"venue"
},
  "geometry": {"coordinates":[13.3133440018,52.4404563904],"type":"Point"}
}