{
  "type": "Feature",
  "properties": {
    "iso:country":"DE",
    "sg:address":"Aarstr. 135",
    "sg:city":"Taunusstein",
    "sg:phone":"+49 6128/3553",
    "sg:postcode":"65232",
    "sg:province":"Hessen",
    "wof:name":"W. Schnauss",
    "wof:placetype":"venue"
},
  "geometry": {"coordinates":[8.1307077408,50.136806488],"type":"Point"}
}