{
  "type": "Feature",
  "properties": {
    "iso:country":"DE",
    "sg:address":"Ro\u00dfstr. 5",
    "sg:city":"Elsterwerda",
    "sg:phone":"+49 3533/3035",
    "sg:postcode":"04910",
    "sg:province":"Brandenburg",
    "wof:name":"Modehaus Galle Inh. G. Galle",
    "wof:placetype":"venue"
},
  "geometry": {"coordinates":[13.522514,51.458549],"type":"Point"}
}