{
  "type": "Feature",
  "properties": {
    "iso:country":"DE",
    "sg:address":"Diezelweg 23",
    "sg:city":"D\u00fcsseldorf",
    "sg:phone":"+49 211/411136",
    "sg:postcode":"40468",
    "sg:province":"Nordrhein-Westfalen",
    "wof:name":"Franz Josef Strake",
    "wof:placetype":"venue"
},
  "geometry": {"coordinates":[6.7699360847,51.2634773254],"type":"Point"}
}