{
  "type": "Feature",
  "properties": {
    "iso:country":"DE",
    "sg:address":"Amalienruher Weg 4",
    "sg:city":"S\u00fclzfeld",
    "sg:phone":"+49 36945/5860",
    "sg:postcode":"98617",
    "sg:province":"Th\u00fcringen",
    "wof:name":"Aluminium Stahlbau Gmbh",
    "wof:placetype":"venue"
},
  "geometry": {"coordinates":[10.383456,50.509853],"type":"Point"}
}