{
  "type": "Feature",
  "properties": {
    "iso:country":"DE",
    "sg:address":"Niederrheinallee 81",
    "sg:city":"Neukirchen-Vluyn",
    "sg:phone":"+49 2845/32299",
    "sg:postcode":"47506",
    "sg:province":"Nordrhein-Westfalen",
    "wof:name":"Famka",
    "wof:placetype":"venue"
},
  "geometry": {"coordinates":[6.5726261139,51.4470558167],"type":"Point"}
}