{
  "type": "Feature",
  "properties": {
    "iso:country":"DE",
    "sg:address":"Schlesierstr. 14",
    "sg:city":"Nordhorn",
    "sg:phone":"+49 5921/34043",
    "sg:postcode":"48531",
    "sg:province":"Niedersachsen",
    "wof:name":"Dieter Veldboer Werbegeschenk-hdl.",
    "wof:placetype":"venue"
},
  "geometry": {"coordinates":[7.1494679451,52.4626922607],"type":"Point"}
}