{
  "type": "Feature",
  "properties": {
    "iso:country":"DE",
    "sg:address":"Zeppelinstr. 12",
    "sg:city":"Reichenbach",
    "sg:phone":"+49 7153/51300",
    "sg:postcode":"73262",
    "sg:province":"Baden-W\u00fcrttemberg",
    "wof:name":"Hans Halm Schilder Und Lichtreklame",
    "wof:placetype":"venue"
},
  "geometry": {"coordinates":[9.453777,48.710217],"type":"Point"}
}