{
  "type": "Feature",
  "properties": {
    "iso:country":"DE",
    "sg:address":"Dogerner Str. 19",
    "sg:city":"Albbruck",
    "sg:phone":"+49 7753/617",
    "sg:postcode":"79774",
    "sg:province":"Baden-W\u00fcrttemberg",
    "wof:name":"Franz Indlekofer",
    "wof:placetype":"venue"
},
  "geometry": {"coordinates":[8.14781,47.625011],"type":"Point"}
}