{
  "type": "Feature",
  "properties": {
    "iso:country":"DE",
    "sg:address":"Bahnhofstr. 2",
    "sg:city":"Kell",
    "sg:phone":"+49 6589/988286",
    "sg:postcode":"54427",
    "sg:province":"Rheinland-Pfalz",
    "wof:name":"Kell-med. E. K.",
    "wof:placetype":"venue"
},
  "geometry": {"coordinates":[6.822406,49.634048],"type":"Point"}
}