{
  "type": "Feature",
  "properties": {
    "iso:country":"DE",
    "sg:address":"Herzbergstr. 105",
    "sg:city":"Berlin",
    "sg:postcode":"10365",
    "sg:province":"Berlin",
    "wof:name":"Import-exporthandel Gbr",
    "wof:placetype":"venue"
},
  "geometry": {"coordinates":[13.4979419708,52.5265083313],"type":"Point"}
}