{
  "type": "Feature",
  "properties": {
    "iso:country":"DE",
    "sg:address":"Hauptstr. 297",
    "sg:city":"Alfter",
    "sg:phone":"+49 228/6420935",
    "sg:postcode":"53347",
    "sg:province":"Nordrhein-Westfalen",
    "wof:name":"Magdalinski Karosseriebau Ohg",
    "wof:placetype":"venue"
},
  "geometry": {"coordinates":[7.023822,50.69865],"type":"Point"}
}