{
  "type": "Feature",
  "properties": {
    "iso:country":"DE",
    "sg:address":"Hauptstr. 107",
    "sg:city":"Altmittweida",
    "sg:phone":"+49 3727/3224",
    "sg:postcode":"09648",
    "sg:province":"Sachsen",
    "wof:name":"Birgit Gelbrich",
    "wof:placetype":"venue"
},
  "geometry": {"coordinates":[12.929048,50.958912],"type":"Point"}
}