{
  "type": "Feature",
  "properties": {
    "iso:country":"DE",
    "sg:address":"Bei der Frauenkirche 8",
    "sg:city":"M\u00fchlacker",
    "sg:phone":"+49 7041/6856",
    "sg:postcode":"75417",
    "sg:province":"Baden-W\u00fcrttemberg",
    "wof:name":"Walter Sattler",
    "wof:placetype":"venue"
},
  "geometry": {"coordinates":[8.8584709167,48.9730682373],"type":"Point"}
}