{
  "type": "Feature",
  "properties": {
    "iso:country":"DE",
    "sg:address":"S\u00e4gem\u00fcllerstr. 7",
    "sg:city":"Clausthal-Zellerfeld",
    "sg:phone":"+49 5323/3582",
    "sg:postcode":"38678",
    "sg:province":"Niedersachsen",
    "wof:name":"Zum Wurstezipfel",
    "wof:placetype":"venue"
},
  "geometry": {"coordinates":[10.3339920044,51.8023986816],"type":"Point"}
}