{
  "type": "Feature",
  "properties": {
    "iso:country":"DE",
    "sg:address":"Fischerstr. 17",
    "sg:city":"Ansbach",
    "sg:phone":"+49 981/61862",
    "sg:postcode":"91522",
    "sg:province":"Bayern",
    "wof:name":"Dr. Med. M. M\u00fcnkel",
    "wof:placetype":"venue"
},
  "geometry": {"coordinates":[10.5689220428,49.2969093323],"type":"Point"}
}