{
  "type": "Feature",
  "properties": {
    "iso:country":"DE",
    "sg:address":"Bachstr. 9",
    "sg:city":"Bad Homburg",
    "sg:phone":"+49 6172/81489",
    "sg:postcode":"61350",
    "sg:province":"Hessen",
    "wof:name":"Peter Becker",
    "wof:placetype":"venue"
},
  "geometry": {"coordinates":[8.609521,50.24015],"type":"Point"}
}