{
  "type": "Feature",
  "properties": {
    "iso:country":"DE",
    "sg:address":"Leipziger Str.",
    "sg:city":"Delitzsch",
    "sg:phone":"+49 34202/51594",
    "sg:postcode":"04509",
    "sg:province":"Sachsen",
    "wof:name":"China Imbiss",
    "wof:placetype":"venue"
},
  "geometry": {"coordinates":[12.3354253769,51.5172615051],"type":"Point"}
}