{
  "type": "Feature",
  "properties": {
    "iso:country":"DE",
    "sg:address":"Cranachstr. 40",
    "sg:city":"Weimar",
    "sg:phone":"+49 3643/501786",
    "sg:postcode":"99423",
    "sg:province":"Th\u00fcringen",
    "wof:name":"Grafe Polymer Technik Gmbh",
    "wof:placetype":"venue"
},
  "geometry": {"coordinates":[11.317461,50.975052],"type":"Point"}
}