{
  "type": "Feature",
  "properties": {
    "iso:country":"DE",
    "sg:address":"Konrad-Adenauer Str. 1",
    "sg:city":"Remscheid",
    "sg:phone":"+49 2191/4330",
    "sg:postcode":"42853",
    "sg:province":"Nordrhein-Westfalen",
    "wof:name":"Commerzbank Ag",
    "wof:placetype":"venue"
},
  "geometry": {"coordinates":[7.193274,51.181065],"type":"Point"}
}