{
  "type": "Feature",
  "properties": {
    "iso:country":"DE",
    "sg:address":"Gartenkampsweg 10 a",
    "sg:city":"Mettmann",
    "sg:phone":"+49 2104/53465",
    "sg:postcode":"40822",
    "sg:province":"Nordrhein-Westfalen",
    "wof:name":"Buchholz",
    "wof:placetype":"venue"
},
  "geometry": {"coordinates":[6.95041,51.2658],"type":"Point"}
}