{
  "type": "Feature",
  "properties": {
    "iso:country":"DE",
    "sg:address":"Maximilianstr. 30",
    "sg:city":"Baden-Baden",
    "sg:phone":"+49 7221/75588",
    "sg:postcode":"76534",
    "sg:province":"Baden-W\u00fcrttemberg",
    "wof:name":"Herbert Kr\u00e4mer",
    "wof:placetype":"venue"
},
  "geometry": {"coordinates":[8.252622,48.750637],"type":"Point"}
}