{
  "type": "Feature",
  "properties": {
    "iso:country":"DE",
    "sg:address":"Ostertagstr. 43",
    "sg:city":"Leonberg",
    "sg:phone":"+49 7152/904950",
    "sg:postcode":"71229",
    "sg:province":"Baden-W\u00fcrttemberg",
    "wof:name":"Miniruf Gmbh",
    "wof:placetype":"venue"
},
  "geometry": {"coordinates":[9.0122776031,48.7936935425],"type":"Point"}
}