{
  "type": "Feature",
  "properties": {
    "iso:country":"DE",
    "sg:address":"Seminarstr. 5",
    "sg:city":"Ludwigslust",
    "sg:phone":"+49 3874/428442",
    "sg:postcode":"19288",
    "sg:province":"Mecklenburg-Vorpommern",
    "wof:name":"Storchen-apotheke Frank Fechner E. K.",
    "wof:placetype":"venue"
},
  "geometry": {"coordinates":[11.49772,53.327972],"type":"Point"}
}