{
  "type": "Feature",
  "properties": {
    "iso:country":"DE",
    "sg:address":"An der Schleuse",
    "sg:city":"Rendsburg",
    "sg:phone":"+49 4331/22002",
    "sg:postcode":"24768",
    "sg:province":"Schleswig-Holstein",
    "wof:name":"Gastst\u00e4tte Br\u00fccken-terrassen",
    "wof:placetype":"venue"
},
  "geometry": {"coordinates":[9.658621788,54.3071403503],"type":"Point"}
}