{
  "type": "Feature",
  "properties": {
    "iso:country":"DE",
    "sg:address":"Birlenbacher Str. 124",
    "sg:city":"Siegen",
    "sg:phone":"+49 271/880136",
    "sg:postcode":"57078",
    "sg:province":"Nordrhein-Westfalen",
    "wof:name":"Kravag",
    "wof:placetype":"venue"
},
  "geometry": {"coordinates":[7.9918217659,50.9055938721],"type":"Point"}
}