{
  "type": "Feature",
  "properties": {
    "iso:country":"DE",
    "sg:address":"Marktstr. 21",
    "sg:city":"Gladenbach",
    "sg:phone":"+49 6462/6540",
    "sg:postcode":"35075",
    "sg:province":"Hessen",
    "wof:name":"Petra Alberding-immel Krankengymnastin",
    "wof:placetype":"venue"
},
  "geometry": {"coordinates":[8.582448,50.76907],"type":"Point"}
}