{
  "type": "Feature",
  "properties": {
    "iso:country":"DE",
    "sg:address":"Burgstr. 48",
    "sg:city":"Stuttgart",
    "sg:phone":"+49 711/6873400",
    "sg:postcode":"70569",
    "sg:province":"Baden-W\u00fcrttemberg",
    "wof:name":"Elemente- Und Massivbau- Systeme Gmbh",
    "wof:placetype":"venue"
},
  "geometry": {"coordinates":[9.1328191757,48.7413978577],"type":"Point"}
}