{
  "type": "Feature",
  "properties": {
    "iso:country":"DE",
    "sg:address":"Holtenklinker Str. 54",
    "sg:city":"Hamburg",
    "sg:phone":"+49 40/7216510",
    "sg:postcode":"21029",
    "sg:province":"Hamburg",
    "wof:name":"Westfalia-anh\u00e4nger Inh. Riege",
    "wof:placetype":"venue"
},
  "geometry": {"coordinates":[10.220655,53.483608],"type":"Point"}
}