{
  "type": "Feature",
  "properties": {
    "iso:country":"DE",
    "sg:address":"Schlaifhausen",
    "sg:city":"Wiesenthau",
    "sg:phone":"+49 9199/419",
    "sg:postcode":"91369",
    "sg:province":"Bayern",
    "wof:name":"Nagengast",
    "wof:placetype":"venue"
},
  "geometry": {"coordinates":[11.1465053558,49.7066955566],"type":"Point"}
}