{
  "type": "Feature",
  "properties": {
    "iso:country":"DE",
    "sg:address":"Hausner Str. 98",
    "sg:city":"Kirchheim",
    "sg:postcode":"85551",
    "sg:province":"Bayern",
    "wof:name":"Regulierungsb\u00fcro Reiter",
    "wof:placetype":"venue"
},
  "geometry": {"coordinates":[11.750127,48.176792],"type":"Point"}
}