{
  "type": "Feature",
  "properties": {
    "iso:country":"DE",
    "sg:address":"Stra\u00dfe der Einheit 38",
    "sg:city":"Karsdorf",
    "sg:phone":"+49 34461/5110",
    "sg:postcode":"06638",
    "sg:province":"Sachsen-Anhalt",
    "wof:name":"Biber-beton Verwaltungs- Gmbh",
    "wof:placetype":"venue"
},
  "geometry": {"coordinates":[11.65879,51.277122],"type":"Point"}
}