{
  "type": "Feature",
  "properties": {
    "iso:country":"DE",
    "sg:address":"Elvekumer Weg 18",
    "sg:city":"Dormagen",
    "sg:phone":"+49 2133/71100",
    "sg:postcode":"41542",
    "sg:province":"Nordrhein-Westfalen",
    "wof:name":"Dieter Baum Ingenieur",
    "wof:placetype":"venue"
},
  "geometry": {"coordinates":[6.7823400497,51.1317520142],"type":"Point"}
}