{
  "type": "Feature",
  "properties": {
    "iso:country":"DE",
    "sg:address":"Poetenweg 14a",
    "sg:city":"Leipzig",
    "sg:phone":"+49 341/5662569",
    "sg:postcode":"04155",
    "sg:province":"Sachsen",
    "wof:name":"Prof. Dr. Hans H\u00f6nig",
    "wof:placetype":"venue"
},
  "geometry": {"coordinates":[12.3664550781,51.3566856384],"type":"Point"}
}