{
  "type": "Feature",
  "properties": {
    "iso:country":"DE",
    "sg:address":"Drei-Lilien-Platz 1",
    "sg:city":"Wiesbaden",
    "sg:phone":"+49 611/370730",
    "sg:postcode":"65183",
    "sg:province":"Hessen",
    "wof:name":"K. D. Sch\u00f6pfeldt",
    "wof:placetype":"venue"
},
  "geometry": {"coordinates":[8.242003,50.084366],"type":"Point"}
}