{
  "type": "Feature",
  "properties": {
    "iso:country":"DE",
    "sg:address":"Heymannstr. 3",
    "sg:city":"Hamburg",
    "sg:phone":"+49 40/451350",
    "sg:postcode":"20253",
    "sg:province":"Hamburg",
    "wof:name":"Gerd Schulz",
    "wof:placetype":"venue"
},
  "geometry": {"coordinates":[9.9717597961,53.5719871521],"type":"Point"}
}