{
  "type": "Feature",
  "properties": {
    "iso:country":"DE",
    "sg:address":"Apostel-Paulus-Str. 12",
    "sg:city":"Berlin",
    "sg:postcode":"10825",
    "sg:province":"Berlin",
    "wof:name":"Augenoptiker-innung Berlin",
    "wof:placetype":"venue"
},
  "geometry": {"coordinates":[13.3441543579,52.4879798889],"type":"Point"}
}