{
  "type": "Feature",
  "properties": {
    "iso:country":"DE",
    "sg:address":"Schildberg 105",
    "sg:city":"M\u00fclheim",
    "sg:phone":"+49 208/71513",
    "sg:postcode":"45475",
    "sg:province":"Nordrhein-Westfalen",
    "wof:name":"Herbert Henning",
    "wof:placetype":"venue"
},
  "geometry": {"coordinates":[6.89217,51.465954],"type":"Point"}
}