{
  "type": "Feature",
  "properties": {
    "iso:country":"DE",
    "sg:address":"Droste-H\u00fclshoff-Str. 1",
    "sg:city":"Everswinkel",
    "sg:phone":"+49 2582/1496",
    "sg:postcode":"48351",
    "sg:province":"Nordrhein-Westfalen",
    "wof:name":"Georg Markfort",
    "wof:placetype":"venue"
},
  "geometry": {"coordinates":[7.853268,51.926762],"type":"Point"}
}