{
  "type": "Feature",
  "properties": {
    "iso:country":"DE",
    "sg:address":"Am Erlenbach 62",
    "sg:city":"Eitorf",
    "sg:phone":"+49 2243/81913",
    "sg:postcode":"53783",
    "sg:province":"Nordrhein-Westfalen",
    "wof:name":"Bintech Gmbh",
    "wof:placetype":"venue"
},
  "geometry": {"coordinates":[7.4274759293,50.7749176025],"type":"Point"}
}