{
  "type": "Feature",
  "properties": {
    "iso:country":"DE",
    "sg:address":"Dorfstr. 37",
    "sg:city":"Hermsdorf",
    "sg:phone":"+49 35052/20156",
    "sg:postcode":"01776",
    "sg:province":"Sachsen",
    "wof:name":"Rudi Lichtenberger",
    "wof:placetype":"venue"
},
  "geometry": {"coordinates":[13.622484,50.767784],"type":"Point"}
}