{
  "type": "Feature",
  "properties": {
    "iso:country":"DE",
    "sg:address":"Olpener Str. 4",
    "sg:city":"Engelskirchen",
    "sg:phone":"+49 2263/3502",
    "sg:postcode":"51766",
    "sg:province":"Nordrhein-Westfalen",
    "wof:name":"Franz Bockheim Gmbh",
    "wof:placetype":"venue"
},
  "geometry": {"coordinates":[7.4137701988,50.9837303162],"type":"Point"}
}