{
  "type": "Feature",
  "properties": {
    "iso:country":"DE",
    "sg:address":"M\u00fchlenstr. 2",
    "sg:city":"Werther",
    "sg:phone":"+49 5203/70517",
    "sg:postcode":"33824",
    "sg:province":"Nordrhein-Westfalen",
    "wof:name":"Stadtarchiv",
    "wof:placetype":"venue"
},
  "geometry": {"coordinates":[8.417067,52.073933],"type":"Point"}
}