{
  "type": "Feature",
  "properties": {
    "iso:country":"DE",
    "sg:address":"Am Kirchberg 3",
    "sg:city":"Colmberg",
    "sg:phone":"+49 9803/222",
    "sg:postcode":"91598",
    "sg:province":"Bayern",
    "wof:name":"Ev. Luth. Pfarramt",
    "wof:placetype":"venue"
},
  "geometry": {"coordinates":[10.4115686417,49.3534202576],"type":"Point"}
}