{
  "type": "Feature",
  "properties": {
    "iso:country":"DE",
    "sg:address":"Berchenstr. 55",
    "sg:city":"Konstanz",
    "sg:phone":"+49 7531/79998",
    "sg:postcode":"78467",
    "sg:province":"Baden-W\u00fcrttemberg",
    "wof:name":"Manfred Jansen",
    "wof:placetype":"venue"
},
  "geometry": {"coordinates":[9.1562862396,47.6821136475],"type":"Point"}
}