{
  "type": "Feature",
  "properties": {
    "iso:country":"DE",
    "sg:address":"Buscher Str. 3",
    "sg:city":"H\u00fcckelhoven",
    "sg:phone":"+49 2433/5324",
    "sg:postcode":"41836",
    "sg:province":"Nordrhein-Westfalen",
    "wof:name":"Walter Hen\u00dfen",
    "wof:placetype":"venue"
},
  "geometry": {"coordinates":[6.189525,51.065224],"type":"Point"}
}