{
  "type": "Feature",
  "properties": {
    "iso:country":"DE",
    "sg:address":"Hauchenbergweg 6",
    "sg:city":"Weitnau",
    "sg:postcode":"87480",
    "sg:province":"Bayern",
    "wof:name":"Willkommen In Weitnau Und Seinen Partnergemeinden",
    "wof:placetype":"venue"
},
  "geometry": {"coordinates":[10.1239271164,47.6402359009],"type":"Point"}
}