{
  "type": "Feature",
  "properties": {
    "iso:country":"DE",
    "sg:address":"Stefanienstr. 38",
    "sg:city":"Lahr",
    "sg:phone":"+49 7821/32180",
    "sg:postcode":"77933",
    "sg:province":"Baden-W\u00fcrttemberg",
    "wof:name":"Roland Sch\u00e4fer",
    "wof:placetype":"venue"
},
  "geometry": {"coordinates":[7.881426,48.342121],"type":"Point"}
}