{
  "type": "Feature",
  "properties": {
    "iso:country":"DE",
    "sg:address":"Freiherr-vom-Stein-Str. 26",
    "sg:city":"Gro\u00df-Rohrheim",
    "sg:phone":"+49 6245/907340",
    "sg:postcode":"68649",
    "sg:province":"Hessen",
    "wof:name":"H & M Handling Und Montage Gmbh",
    "wof:placetype":"venue"
},
  "geometry": {"coordinates":[8.4790096283,49.7098083496],"type":"Point"}
}