{
  "type": "Feature",
  "properties": {
    "iso:country":"DE",
    "sg:address":"M\u00fcnzstr.",
    "sg:city":"M\u00fcnster",
    "sg:postcode":"48143",
    "sg:province":"Nordrhein-Westfalen",
    "wof:name":"Galerie Am Kalkmarkt",
    "wof:placetype":"venue"
},
  "geometry": {"coordinates":[7.619086,51.966679],"type":"Point"}
}