{
  "type": "Feature",
  "properties": {
    "iso:country":"DE",
    "sg:address":"Im Bacchuswinkel 5",
    "sg:city":"Nierstein",
    "sg:phone":"+49 6133/59544",
    "sg:postcode":"55283",
    "sg:province":"Rheinland-Pfalz",
    "wof:name":"Creativewebteam - Mit Uns Ins Internet",
    "wof:placetype":"venue"
},
  "geometry": {"coordinates":[8.329723,49.868481],"type":"Point"}
}