{
  "type": "Feature",
  "properties": {
    "iso:country":"DE",
    "sg:address":"Flittarder Hauptstr. 94",
    "sg:city":"K\u00f6ln",
    "sg:phone":"+49 221/663724",
    "sg:postcode":"51061",
    "sg:province":"Nordrhein-Westfalen",
    "wof:name":"E. Appelmann Heissmangel",
    "wof:placetype":"venue"
},
  "geometry": {"coordinates":[6.9769921303,51.0045318604],"type":"Point"}
}