{
  "type": "Feature",
  "properties": {
    "iso:country":"DE",
    "sg:address":"Raiffeisenstr. 7",
    "sg:city":"Stetten",
    "sg:postcode":"72510",
    "sg:province":"Baden-W\u00fcrttemberg",
    "wof:name":"Viehversicherungsverein Anton Dreher",
    "wof:placetype":"venue"
},
  "geometry": {"coordinates":[9.0304813385,48.1169281006],"type":"Point"}
}