{
  "type": "Feature",
  "properties": {
    "iso:country":"DE",
    "sg:address":"Gipsenweg 10",
    "sg:city":"Wolfratshausen",
    "sg:phone":"+49 8171/18583",
    "sg:postcode":"82515",
    "sg:province":"Bayern",
    "wof:name":"Tourinet Gmbh",
    "wof:placetype":"venue"
},
  "geometry": {"coordinates":[11.4255561829,47.91746521],"type":"Point"}
}