{
  "type": "Feature",
  "properties": {
    "iso:country":"DE",
    "sg:address":"Bendemannstr. 16",
    "sg:city":"D\u00fcsseldorf",
    "sg:postcode":"40210",
    "sg:province":"Nordrhein-Westfalen",
    "wof:name":"Novotech Beteiligungs Gmbh",
    "wof:placetype":"venue"
},
  "geometry": {"coordinates":[6.791227,51.223297],"type":"Point"}
}