{
  "type": "Feature",
  "properties": {
    "iso:country":"DE",
    "sg:address":"Hauptstr. 119",
    "sg:city":"Eschborn",
    "sg:postcode":"65760",
    "sg:province":"Hessen",
    "wof:name":"D2-shop",
    "wof:placetype":"venue"
},
  "geometry": {"coordinates":[8.5593338013,50.1455688477],"type":"Point"}
}