{
  "type": "Feature",
  "properties": {
    "iso:country":"DE",
    "sg:address":"Illnh\u00e4user Str. 3",
    "sg:city":"Gedern",
    "sg:phone":"+49 6045/7138",
    "sg:postcode":"63688",
    "sg:province":"Hessen",
    "wof:name":"Ludwig Winter",
    "wof:placetype":"venue"
},
  "geometry": {"coordinates":[9.24816,50.386841],"type":"Point"}
}