{
  "type": "Feature",
  "properties": {
    "iso:country":"DE",
    "sg:address":"Am S\u00e4gewerk 7",
    "sg:city":"Melsungen",
    "sg:phone":"+49 5661/2188",
    "sg:postcode":"34212",
    "sg:province":"Hessen",
    "wof:name":"Karl-heinz Schneider",
    "wof:placetype":"venue"
},
  "geometry": {"coordinates":[9.5467100143,51.1530914307],"type":"Point"}
}