{
  "type": "Feature",
  "properties": {
    "iso:country":"DE",
    "sg:address":"Riedh\u00f6fe",
    "sg:city":"K\u00f6ngen",
    "sg:phone":"+49 7024/81802",
    "sg:postcode":"73257",
    "sg:province":"Baden-W\u00fcrttemberg",
    "wof:name":"Wilhelm Zimmermann",
    "wof:placetype":"venue"
},
  "geometry": {"coordinates":[9.340405,48.691395],"type":"Point"}
}