{
  "type": "Feature",
  "properties": {
    "iso:country":"DE",
    "sg:address":"Liebrechtstr. 43",
    "sg:city":"Moers",
    "sg:phone":"+49 2841/22461",
    "sg:postcode":"47445",
    "sg:province":"Nordrhein-Westfalen",
    "wof:name":"Dr. Med. Hans.-d. Haeuber",
    "wof:placetype":"venue"
},
  "geometry": {"coordinates":[6.6249628067,51.4672088623],"type":"Point"}
}