{
  "type": "Feature",
  "properties": {
    "iso:country":"DE",
    "sg:address":"Langwiesenstr. 15",
    "sg:city":"Weissach",
    "sg:phone":"+49 7191/51853",
    "sg:postcode":"71554",
    "sg:province":"Baden-W\u00fcrttemberg",
    "wof:name":"Matthias Stelly",
    "wof:placetype":"venue"
},
  "geometry": {"coordinates":[9.51811409,48.9227600098],"type":"Point"}
}