{
  "type": "Feature",
  "properties": {
    "iso:country":"DE",
    "sg:address":"Gelderner Str. 3",
    "sg:city":"F\u00fcrstenberg",
    "sg:phone":"+49 33093/38726",
    "sg:postcode":"16798",
    "sg:province":"Brandenburg",
    "wof:name":"Harro Stellmacher",
    "wof:placetype":"venue"
},
  "geometry": {"coordinates":[13.145246,53.184719],"type":"Point"}
}