{
  "type": "Feature",
  "properties": {
    "iso:country":"DE",
    "sg:address":"Wiesenstr.7",
    "sg:city":"Viernheim",
    "sg:phone":"+49 6204/67370",
    "sg:postcode":"68519",
    "sg:province":"Hessen",
    "wof:name":"Willkommen Bei Der Photo-poster Gallery",
    "wof:placetype":"venue"
},
  "geometry": {"coordinates":[8.585317,49.539131],"type":"Point"}
}