{
  "type": "Feature",
  "properties": {
    "iso:country":"DE",
    "sg:address":"Zum K\u00f6nigsgraben",
    "sg:city":"Dabendorf",
    "sg:postcode":"15806",
    "sg:province":"Brandenburg",
    "wof:name":"Hays Logistics Gmbh Zwndl. Zossen",
    "wof:placetype":"venue"
},
  "geometry": {"coordinates":[13.4257030487,52.241558075],"type":"Point"}
}