{
  "type": "Feature",
  "properties": {
    "iso:country":"DE",
    "sg:address":"Rodensteiner Str. 4",
    "sg:city":"Fl\u00f6rsheim-Dalsheim",
    "sg:phone":"+49 6243/483",
    "sg:postcode":"67592",
    "sg:province":"Rheinland-Pfalz",
    "wof:name":"Hans Bicking K\u00fcferei",
    "wof:placetype":"venue"
},
  "geometry": {"coordinates":[8.211065,49.66441],"type":"Point"}
}