{
  "type": "Feature",
  "properties": {
    "iso:country":"DE",
    "sg:city":"Wassertr\u00fcdingen",
    "sg:phone":"+49 9832/1449",
    "sg:postcode":"91717",
    "sg:province":"Bayern",
    "wof:name":"Zum Schwarzen Adler Priv. Brauerei",
    "wof:placetype":"venue"
},
  "geometry": {"coordinates":[10.596995,49.041164],"type":"Point"}
}