{
  "type": "Feature",
  "properties": {
    "iso:country":"DE",
    "sg:address":"Pommernstr. 13",
    "sg:city":"Erlangen",
    "sg:phone":"+49 9131/34061",
    "sg:postcode":"91052",
    "sg:province":"Bayern",
    "wof:name":"Konrad Zeitner Bau Gmbh",
    "wof:placetype":"venue"
},
  "geometry": {"coordinates":[10.9933624268,49.5893936157],"type":"Point"}
}