{
  "type": "Feature",
  "properties": {
    "iso:country":"DE",
    "sg:address":"Rottenburger Str. 15",
    "sg:city":"Pfeffenhausen",
    "sg:phone":"+49 8782/8130",
    "sg:postcode":"84076",
    "sg:province":"Bayern",
    "wof:name":"J. Bachmaier",
    "wof:placetype":"venue"
},
  "geometry": {"coordinates":[11.9663648605,48.6667327881],"type":"Point"}
}