{
  "type": "Feature",
  "properties": {
    "iso:country":"DE",
    "sg:address":"Telgenstr. 1",
    "sg:city":"Warendorf",
    "sg:phone":"+49 2584/1019",
    "sg:postcode":"48231",
    "sg:province":"Nordrhein-Westfalen",
    "wof:name":"Fr. Schabh\u00fcser",
    "wof:placetype":"venue"
},
  "geometry": {"coordinates":[7.94793,51.999912],"type":"Point"}
}