{
  "type": "Feature",
  "properties": {
    "iso:country":"DE",
    "sg:address":"Britzer Damm 88",
    "sg:city":"Berlin",
    "sg:phone":"+49 30/6064465",
    "sg:postcode":"12347",
    "sg:province":"Berlin",
    "wof:name":"Joseph P. Harmon Arzt F\u00fcr Allgemeinmedizin",
    "wof:placetype":"venue"
},
  "geometry": {"coordinates":[13.4374961853,52.4548072815],"type":"Point"}
}