{
  "type": "Feature",
  "properties": {
    "iso:country":"DE",
    "sg:address":"Rheinhessenstr. 3",
    "sg:city":"Mainz",
    "sg:phone":"+49 6131/59718",
    "sg:postcode":"55129",
    "sg:province":"Rheinland-Pfalz",
    "wof:name":"Fritz Giese Gmbh & Co. Kg",
    "wof:placetype":"venue"
},
  "geometry": {"coordinates":[8.270119,49.970589],"type":"Point"}
}