{
  "type": "Feature",
  "properties": {
    "iso:country":"DE",
    "sg:address":"Alte Bundesstr. 19",
    "sg:city":"Krempel",
    "sg:postcode":"25774",
    "sg:province":"Schleswig-Holstein",
    "wof:name":"Lbc Landschaftsbau Clau\u00dfen Gmbh",
    "wof:placetype":"venue"
},
  "geometry": {"coordinates":[9.0274467468,54.3208885193],"type":"Point"}
}