{
  "type": "Feature",
  "properties": {
    "iso:country":"DE",
    "sg:address":"Max-Eyth-Str. 7",
    "sg:city":"Winnenden",
    "sg:phone":"+49 7195/91420",
    "sg:postcode":"71364",
    "sg:province":"Baden-W\u00fcrttemberg",
    "wof:name":"Khalil Resch Gmbh",
    "wof:placetype":"venue"
},
  "geometry": {"coordinates":[9.3893413544,48.8746147156],"type":"Point"}
}