{
  "type": "Feature",
  "properties": {
    "iso:country":"DE",
    "sg:address":"Kirchheimer Str. 73",
    "sg:city":"Stuttgart",
    "sg:phone":"+49 711/473580",
    "sg:postcode":"70619",
    "sg:province":"Baden-W\u00fcrttemberg",
    "wof:name":"A. Lang",
    "wof:placetype":"venue"
},
  "geometry": {"coordinates":[9.2145442963,48.7437553406],"type":"Point"}
}