{
  "type": "Feature",
  "properties": {
    "iso:country":"DE",
    "sg:address":"Sundernstr. 19",
    "sg:city":"Tecklenburg",
    "sg:phone":"+49 5482/97036",
    "sg:postcode":"49545",
    "sg:province":"Nordrhein-Westfalen",
    "wof:name":"Grundst\u00fccksgesellschaft Aschebrock Gmbh & Co. Kg",
    "wof:placetype":"venue"
},
  "geometry": {"coordinates":[7.8152341843,52.2381477356],"type":"Point"}
}