{
  "type": "Feature",
  "properties": {
    "iso:country":"DE",
    "sg:address":"Bachstr. 12",
    "sg:city":"Oberderdingen",
    "sg:postcode":"75038",
    "sg:province":"Baden-W\u00fcrttemberg",
    "wof:name":"Kunststoffwabe- Verwertungs Gmbh",
    "wof:placetype":"venue"
},
  "geometry": {"coordinates":[8.8048963547,49.0693092346],"type":"Point"}
}