{
  "type": "Feature",
  "properties": {
    "iso:country":"DE",
    "sg:address":"Bernhardstr. 37",
    "sg:city":"Essen",
    "sg:phone":"+49 201/402223",
    "sg:postcode":"45239",
    "sg:province":"Nordrhein-Westfalen",
    "wof:name":"Wolfgang Zeunert Beteiligungs Gmbh",
    "wof:placetype":"venue"
},
  "geometry": {"coordinates":[7.0236058235,51.3938064575],"type":"Point"}
}