{
  "type": "Feature",
  "properties": {
    "iso:country":"DE",
    "sg:address":"Gellenberg 18",
    "sg:city":"Rheden",
    "sg:phone":"+49 5182/2256",
    "sg:postcode":"31039",
    "sg:province":"Niedersachsen",
    "wof:name":"Klaus Sprengel",
    "wof:placetype":"venue"
},
  "geometry": {"coordinates":[9.791885,52.059284],"type":"Point"}
}