{
  "type": "Feature",
  "properties": {
    "iso:country":"DE",
    "sg:address":"Franz-Mehring-Str. 5",
    "sg:city":"Schwerin",
    "sg:phone":"+49 385/564040",
    "sg:postcode":"19053",
    "sg:province":"Mecklenburg-Vorpommern",
    "wof:name":"Roland Streit Rechtsanwalt",
    "wof:placetype":"venue"
},
  "geometry": {"coordinates":[11.4095211029,53.6309738159],"type":"Point"}
}