{
  "type": "Feature",
  "properties": {
    "iso:country":"DE",
    "sg:address":"Am Weinberg 1 a",
    "sg:city":"Bergen",
    "sg:phone":"+49 5051/3543",
    "sg:postcode":"29303",
    "sg:province":"Niedersachsen",
    "wof:name":"Pizzeria Bella Napoli",
    "wof:placetype":"venue"
},
  "geometry": {"coordinates":[9.9616727829,52.8113632202],"type":"Point"}
}