{
  "type": "Feature",
  "properties": {
    "iso:country":"DE",
    "sg:address":"Hofstetten 22",
    "sg:city":"Roth",
    "sg:phone":"+49 9171/3390",
    "sg:postcode":"91154",
    "sg:province":"Bayern",
    "wof:name":"Maria Keller",
    "wof:placetype":"venue"
},
  "geometry": {"coordinates":[11.1300210953,49.2282447815],"type":"Point"}
}