{
  "type": "Feature",
  "properties": {
    "iso:country":"DE",
    "sg:address":"Am Deich 26",
    "sg:city":"Kleve",
    "sg:postcode":"47533",
    "sg:province":"Nordrhein-Westfalen",
    "wof:name":"Www.siemenstelefone.de",
    "wof:placetype":"venue"
},
  "geometry": {"coordinates":[6.177254,51.79073],"type":"Point"}
}