{
  "type": "Feature",
  "properties": {
    "iso:country":"DE",
    "sg:address":"Windm\u00fchlenstr. 8",
    "sg:city":"Dresden",
    "sg:postcode":"01257",
    "sg:province":"Sachsen",
    "wof:name":"H & R Anlagenbau Und Co. Kg",
    "wof:placetype":"venue"
},
  "geometry": {"coordinates":[13.816374,50.998363],"type":"Point"}
}