{
  "type": "Feature",
  "properties": {
    "iso:country":"DE",
    "sg:address":"Am Pfarrgarten 1",
    "sg:city":"Barsinghausen",
    "sg:postcode":"30890",
    "sg:province":"Niedersachsen",
    "wof:name":"Gabriela Kopf Architektin",
    "wof:placetype":"venue"
},
  "geometry": {"coordinates":[9.429952,52.318291],"type":"Point"}
}