{
  "type": "Feature",
  "properties": {
    "iso:country":"DE",
    "sg:address":"Drei-K\u00f6nig-Weg 12",
    "sg:city":"Crailsheim",
    "sg:postcode":"74564",
    "sg:province":"Baden-W\u00fcrttemberg",
    "wof:name":"Digital Art & Animation Gmbh",
    "wof:placetype":"venue"
},
  "geometry": {"coordinates":[10.056312,49.146084],"type":"Point"}
}