{
  "type": "Feature",
  "properties": {
    "iso:country":"DE",
    "sg:address":"Obermarkt 40",
    "sg:city":"Murnau",
    "sg:phone":"+49 8841/90220",
    "sg:postcode":"82418",
    "sg:province":"Bayern",
    "wof:name":"Trend Brillen Gmbh",
    "wof:placetype":"venue"
},
  "geometry": {"coordinates":[11.2015686035,47.6805152893],"type":"Point"}
}