{
  "type": "Feature",
  "properties": {
    "iso:country":"DE",
    "sg:address":"Fasanenstr. 47",
    "sg:city":"Meppen",
    "sg:phone":"+49 5931/2831",
    "sg:postcode":"49716",
    "sg:province":"Niedersachsen",
    "wof:name":"Heinrich Grosch Architekt",
    "wof:placetype":"venue"
},
  "geometry": {"coordinates":[7.305501,52.687725],"type":"Point"}
}