{
  "type": "Feature",
  "properties": {
    "iso:country":"DE",
    "sg:address":"Ihlenfelder Str. 151",
    "sg:city":"Neubrandenburg",
    "sg:postcode":"17034",
    "sg:province":"Mecklenburg-Vorpommern",
    "wof:name":"Otto Versand Kundenbetreuung",
    "wof:placetype":"venue"
},
  "geometry": {"coordinates":[13.2999706268,53.5771369934],"type":"Point"}
}