{
  "type": "Feature",
  "properties": {
    "iso:country":"DE",
    "sg:address":"Kaiserstr. 32",
    "sg:city":"Friedberg",
    "sg:phone":"+49 6031/61679",
    "sg:postcode":"61169",
    "sg:province":"Hessen",
    "wof:name":"Bettenhaus Decher Inh. Norbert Decher",
    "wof:placetype":"venue"
},
  "geometry": {"coordinates":[8.7544431686,50.3387031555],"type":"Point"}
}