{
  "type": "Feature",
  "properties": {
    "iso:country":"DE",
    "sg:address":"Am Zirkel 19",
    "sg:city":"Werlte",
    "sg:postcode":"49757",
    "sg:province":"Niedersachsen",
    "wof:name":"Bbs-technik Gmbh",
    "wof:placetype":"venue"
},
  "geometry": {"coordinates":[7.6562728882,52.857585907],"type":"Point"}
}