{
  "type": "Feature",
  "properties": {
    "iso:country":"DE",
    "sg:address":"Zehlendorfer Str. 69",
    "sg:city":"Pattensen",
    "sg:phone":"+49 5101/14413",
    "sg:postcode":"30982",
    "sg:province":"Niedersachsen",
    "wof:name":"Pfeiffer Plastik Gmbh",
    "wof:placetype":"venue"
},
  "geometry": {"coordinates":[9.76565,52.2682],"type":"Point"}
}