{
  "type": "Feature",
  "properties": {
    "iso:country":"DE",
    "sg:address":"Barnstorfer Weg 36",
    "sg:city":"Rostock",
    "sg:phone":"+49 381/2004353",
    "sg:postcode":"18057",
    "sg:province":"Mecklenburg-Vorpommern",
    "wof:name":"I. Glasow",
    "wof:placetype":"venue"
},
  "geometry": {"coordinates":[12.1187467575,54.0880317688],"type":"Point"}
}