{
  "type": "Feature",
  "properties": {
    "iso:country":"DE",
    "sg:address":"Chemnitzerstr. 16",
    "sg:city":"Stuttgart",
    "sg:phone":"+49 4971/1900810",
    "sg:postcode":"70597",
    "sg:province":"Baden-W\u00fcrttemberg",
    "wof:name":"Dirk Lenhard",
    "wof:placetype":"venue"
},
  "geometry": {"coordinates":[9.1673135757,48.7382011414],"type":"Point"}
}