{
  "type": "Feature",
  "properties": {
    "iso:country":"DE",
    "sg:address":"Lagerstr. 13",
    "sg:city":"Sprockh\u00f6vel",
    "sg:phone":"+49 2339/2632",
    "sg:postcode":"45549",
    "sg:province":"Nordrhein-Westfalen",
    "wof:name":"Werner L\u00fcddecke",
    "wof:placetype":"venue"
},
  "geometry": {"coordinates":[7.299171,51.347218],"type":"Point"}
}