{
  "type": "Feature",
  "properties": {
    "iso:country":"DE",
    "sg:address":"Zerzabelshofer Hauptstr. 22",
    "sg:city":"N\u00fcrnberg",
    "sg:phone":"+49 911/400016",
    "sg:postcode":"90480",
    "sg:province":"Bayern",
    "wof:name":"Ernst Schwartz Architekt",
    "wof:placetype":"venue"
},
  "geometry": {"coordinates":[11.124721,49.443073],"type":"Point"}
}