{
  "type": "Feature",
  "properties": {
    "iso:country":"DE",
    "sg:address":"Hauptstr. 18",
    "sg:city":"Rehlingen",
    "sg:phone":"+49 4132/335",
    "sg:postcode":"21385",
    "sg:province":"Niedersachsen",
    "wof:name":"Dietrich Thiede",
    "wof:placetype":"venue"
},
  "geometry": {"coordinates":[10.220025,53.10651],"type":"Point"}
}