{
  "type": "Feature",
  "properties": {
    "iso:country":"DE",
    "sg:address":"Zur Kirche 2",
    "sg:city":"Bad Oeynhausen",
    "sg:phone":"+49 5734/611031",
    "sg:postcode":"32549",
    "sg:province":"Nordrhein-Westfalen",
    "wof:name":"Evangelisches Berufskolleg Wittekindshof",
    "wof:placetype":"venue"
},
  "geometry": {"coordinates":[8.7866697311,52.2571334839],"type":"Point"}
}