{
  "type": "Feature",
  "properties": {
    "iso:country":"DE",
    "sg:address":"H\u00e4mmerlingstr.34",
    "sg:city":"Berlin",
    "sg:phone":"+49 30/65322446",
    "sg:postcode":"12555",
    "sg:province":"Berlin",
    "wof:name":"Vermadia",
    "wof:placetype":"venue"
},
  "geometry": {"coordinates":[13.571269989,52.4634895325],"type":"Point"}
}