{
  "type": "Feature",
  "properties": {
    "iso:country":"DE",
    "sg:address":"Bergkirchener Str. 476",
    "sg:city":"Bad Oeynhausen",
    "sg:postcode":"32549",
    "sg:province":"Nordrhein-Westfalen",
    "wof:name":"Hotelrestaurant Wittekinds- Quelle Verwaltungs-gmbh",
    "wof:placetype":"venue"
},
  "geometry": {"coordinates":[8.7754278183,52.2701644897],"type":"Point"}
}