{
  "type": "Feature",
  "properties": {
    "iso:country":"DE",
    "sg:address":"Julius-Lucas-Weg 26",
    "sg:city":"Wuppertal",
    "sg:phone":"+49 202/715667",
    "sg:postcode":"42113",
    "sg:province":"Nordrhein-Westfalen",
    "wof:name":"Karl Heinz Nolte",
    "wof:placetype":"venue"
},
  "geometry": {"coordinates":[7.11772,51.263088],"type":"Point"}
}