{
  "type": "Feature",
  "properties": {
    "iso:country":"DE",
    "sg:address":"Berntalstr. 72",
    "sg:city":"Sachsenheim",
    "sg:phone":"+49 7147/6265",
    "sg:postcode":"74343",
    "sg:province":"Baden-W\u00fcrttemberg",
    "wof:name":"Burkhard Bayer Architekt",
    "wof:placetype":"venue"
},
  "geometry": {"coordinates":[9.048274,48.965942],"type":"Point"}
}