{
  "type": "Feature",
  "properties": {
    "iso:country":"DE",
    "sg:address":"Friedrich-Borgwardt-Str. 11",
    "sg:city":"K\u00fchlungsborn",
    "sg:postcode":"18225",
    "sg:province":"Mecklenburg-Vorpommern",
    "wof:name":"K. Gust",
    "wof:placetype":"venue"
},
  "geometry": {"coordinates":[11.7290267944,54.1484260559],"type":"Point"}
}