{
  "type": "Feature",
  "properties": {
    "iso:country":"DE",
    "sg:address":"Thyssenstr. 19-21",
    "sg:city":"Berlin",
    "sg:phone":"+49 4930/4090490",
    "sg:postcode":"13407",
    "sg:province":"Berlin",
    "wof:name":"Begra Granulate Gmbh & Co.",
    "wof:placetype":"venue"
},
  "geometry": {"coordinates":[13.3427696228,52.5798034668],"type":"Point"}
}