{
  "type": "Feature",
  "properties": {
    "iso:country":"DE",
    "sg:address":"Am Lindenhofe 8",
    "sg:city":"Hannover",
    "sg:postcode":"30519",
    "sg:province":"Niedersachsen",
    "wof:name":"Die Aufbau Gmbh",
    "wof:placetype":"venue"
},
  "geometry": {"coordinates":[9.760848,52.335892],"type":"Point"}
}