{
  "type": "Feature",
  "properties": {
    "iso:country":"DE",
    "sg:address":"Dorfstr. 8 D",
    "sg:city":"Schwalmtal",
    "sg:phone":"+49 2163/1681",
    "sg:postcode":"41366",
    "sg:province":"Nordrhein-Westfalen",
    "wof:name":"Dr. Henryk Bocianski Tierarzt",
    "wof:placetype":"venue"
},
  "geometry": {"coordinates":[6.2481331825,51.234336853],"type":"Point"}
}