{
  "type": "Feature",
  "properties": {
    "iso:country":"DE",
    "sg:address":"Weidenkamp 52",
    "sg:city":"Uetersen",
    "sg:phone":"+49 4122/45576",
    "sg:postcode":"25436",
    "sg:province":"Schleswig-Holstein",
    "wof:name":"Berthold Krome Edv-beratung",
    "wof:placetype":"venue"
},
  "geometry": {"coordinates":[9.6993732452,53.68491745],"type":"Point"}
}