{
  "type": "Feature",
  "properties": {
    "iso:country":"DE",
    "sg:address":"Hermann-L\u00f6ns-Str. 20",
    "sg:city":"Hanau",
    "sg:phone":"+49 6181/69392",
    "sg:postcode":"63456",
    "sg:province":"Hessen",
    "wof:name":"Rosi Bindemann",
    "wof:placetype":"venue"
},
  "geometry": {"coordinates":[8.932746,50.099541],"type":"Point"}
}