{
  "type": "Feature",
  "properties": {
    "iso:country":"DE",
    "sg:address":"Satzenbergstr. 5",
    "sg:city":"Wertheim",
    "sg:phone":"+49 9342/39782",
    "sg:postcode":"97877",
    "sg:province":"Baden-W\u00fcrttemberg",
    "wof:name":"Horst Dinziol Malerwerkstatt Gmbh",
    "wof:placetype":"venue"
},
  "geometry": {"coordinates":[9.53633,49.725193],"type":"Point"}
}