{
  "type": "Feature",
  "properties": {
    "iso:country":"DE",
    "sg:address":"Unstrutstr. 13",
    "sg:city":"Halle",
    "sg:phone":"+49 345/8045461",
    "sg:postcode":"06122",
    "sg:province":"Sachsen-Anhalt",
    "wof:name":"Dr. Med. Tamara R\u00f6hr-tatar",
    "wof:placetype":"venue"
},
  "geometry": {"coordinates":[11.944426,51.482937],"type":"Point"}
}