{
  "type": "Feature",
  "properties": {
    "iso:country":"DE",
    "sg:address":"Frintroper Str. 68",
    "sg:city":"Essen",
    "sg:phone":"+49 201/672659",
    "sg:postcode":"45359",
    "sg:province":"Nordrhein-Westfalen",
    "wof:name":"Aral Ag",
    "wof:placetype":"venue"
},
  "geometry": {"coordinates":[6.9410610199,51.4625434875],"type":"Point"}
}