{
  "type": "Feature",
  "properties": {
    "iso:country":"DE",
    "sg:address":"Sonnenhang 34",
    "sg:city":"K\u00f6rle",
    "sg:phone":"+49 5665/3602",
    "sg:postcode":"34327",
    "sg:province":"Hessen",
    "wof:name":"Georg Kilian",
    "wof:placetype":"venue"
},
  "geometry": {"coordinates":[9.506948,51.179131],"type":"Point"}
}