{
  "type": "Feature",
  "properties": {
    "iso:country":"DE",
    "sg:address":"Konrad-Zuse-Bogen 17",
    "sg:city":"Krailling",
    "sg:phone":"+49 89/802535",
    "sg:postcode":"82152",
    "sg:province":"Bayern",
    "wof:name":"Bkf Apparatebau Gmbh",
    "wof:placetype":"venue"
},
  "geometry": {"coordinates":[11.3613271713,48.0938682556],"type":"Point"}
}