{
  "type": "Feature",
  "properties": {
    "iso:country":"DE",
    "sg:address":"Heinrich-Emerich-Str. 20",
    "sg:city":"\u00dcberlingen",
    "sg:phone":"+49 7551/4174",
    "sg:postcode":"88662",
    "sg:province":"Baden-W\u00fcrttemberg",
    "wof:name":"Ballweg Verfahrenstechnik Und Anlagenbau Gmbh",
    "wof:placetype":"venue"
},
  "geometry": {"coordinates":[9.175705,47.76582],"type":"Point"}
}