{
  "type": "Feature",
  "properties": {
    "iso:country":"DE",
    "sg:address":"Esch 10",
    "sg:city":"Beelen",
    "sg:phone":"+49 2586/562",
    "sg:postcode":"48361",
    "sg:province":"Nordrhein-Westfalen",
    "wof:name":"Loeber Malerbetriebe",
    "wof:placetype":"venue"
},
  "geometry": {"coordinates":[8.122207,51.924194],"type":"Point"}
}