{
  "type": "Feature",
  "properties": {
    "iso:country":"DE",
    "sg:address":"Rosheimer Str. 19",
    "sg:city":"Landau",
    "sg:phone":"+49 6341/34110",
    "sg:postcode":"76829",
    "sg:province":"Rheinland-Pfalz",
    "wof:name":"Dr. Med. Joachim Gemmel",
    "wof:placetype":"venue"
},
  "geometry": {"coordinates":[8.0874032974,49.1908035278],"type":"Point"}
}