{
  "type": "Feature",
  "properties": {
    "iso:country":"DE",
    "sg:address":"Bilenbarg 12",
    "sg:city":"Hamburg",
    "sg:phone":"+49 40/6084333",
    "sg:postcode":"22397",
    "sg:province":"Hamburg",
    "wof:name":"Sylvia Klein Rechtsanw\u00e4ltin",
    "wof:placetype":"venue"
},
  "geometry": {"coordinates":[10.0876913071,53.6886024475],"type":"Point"}
}