{
  "type": "Feature",
  "properties": {
    "iso:country":"DE",
    "sg:address":"bergstr. 31",
    "sg:city":"dresden",
    "sg:phone":"+49 4943/1321654",
    "sg:postcode":"76766",
    "sg:province":"Sachsen",
    "wof:name":"Veronas Lust!!! Kostenlose Bildergalerie",
    "wof:placetype":"venue"
},
  "geometry": {"coordinates":[13.889774,51.006409],"type":"Point"}
}