{
  "type": "Feature",
  "properties": {
    "iso:country":"DE",
    "sg:address":"Rheinstr. 14",
    "sg:city":"Steinmauern",
    "sg:phone":"+49 7222/22565",
    "sg:postcode":"76479",
    "sg:province":"Baden-W\u00fcrttemberg",
    "wof:name":"Reinhard K\u00fchn",
    "wof:placetype":"venue"
},
  "geometry": {"coordinates":[8.195642,48.900551],"type":"Point"}
}