{
  "type": "Feature",
  "properties": {
    "iso:country":"DE",
    "sg:address":"Heiligenstr. 21",
    "sg:city":"Saarlouis",
    "sg:phone":"+49 6831/81600",
    "sg:postcode":"66740",
    "sg:province":"Saarland",
    "wof:name":"M. Reiter Heissmangel",
    "wof:placetype":"venue"
},
  "geometry": {"coordinates":[6.7468490601,49.3338851929],"type":"Point"}
}