{
  "type": "Feature",
  "properties": {
    "iso:country":"DE",
    "sg:address":"Nachtigallstr. 5",
    "sg:city":"N\u00fcrnberg",
    "sg:phone":"+49 911/988830",
    "sg:postcode":"90455",
    "sg:province":"Bayern",
    "wof:name":"Stalimex Stahl-import-export Gmbh",
    "wof:placetype":"venue"
},
  "geometry": {"coordinates":[11.0655460358,49.3739585876],"type":"Point"}
}