{
  "type": "Feature",
  "properties": {
    "iso:country":"DE",
    "sg:address":"Schlierseestr. 77",
    "sg:city":"M\u00fcnchen",
    "sg:phone":"+49 89/6917707",
    "sg:postcode":"81539",
    "sg:province":"Bayern",
    "wof:name":"Giesinger Bahnhof-apotheke",
    "wof:placetype":"venue"
},
  "geometry": {"coordinates":[11.59373,48.112022],"type":"Point"}
}