{
  "type": "Feature",
  "properties": {
    "iso:country":"DE",
    "sg:address":"Steinwegstr. 29",
    "sg:city":"H\u00f6chstadt",
    "sg:phone":"+49 9193/3437",
    "sg:postcode":"91315",
    "sg:province":"Bayern",
    "wof:name":"Fliesen Benkert Gmbh",
    "wof:placetype":"venue"
},
  "geometry": {"coordinates":[10.8068408966,49.7049674988],"type":"Point"}
}