{
  "type": "Feature",
  "properties": {
    "iso:country":"DE",
    "sg:address":"Bahnhofstr. 32",
    "sg:city":"Altenkirchen",
    "sg:phone":"+49 2681/4117",
    "sg:postcode":"57610",
    "sg:province":"Rheinland-Pfalz",
    "wof:name":"Gastst\u00e4tte Petz-stuben",
    "wof:placetype":"venue"
},
  "geometry": {"coordinates":[7.6384539604,50.6851844788],"type":"Point"}
}