{
  "type": "Feature",
  "properties": {
    "iso:country":"DE",
    "sg:address":"Ludwig-Erhard-Allee 9",
    "sg:city":"D\u00fcsseldorf",
    "sg:phone":"+49 211/99460",
    "sg:postcode":"40227",
    "sg:province":"Nordrhein-Westfalen",
    "wof:name":"Ilv Leasinggesellschaft F\u00fcr Grundst\u00fccke Mbh",
    "wof:placetype":"venue"
},
  "geometry": {"coordinates":[6.7973151207,51.2200927734],"type":"Point"}
}