{
  "type": "Feature",
  "properties": {
    "iso:country":"DE",
    "sg:address":"Schlo\u00dfstr. 7",
    "sg:city":"Donzdorf",
    "sg:phone":"+49 7162/20050",
    "sg:postcode":"73072",
    "sg:province":"Baden-W\u00fcrttemberg",
    "wof:name":"Hotel-restaurant Becher",
    "wof:placetype":"venue"
},
  "geometry": {"coordinates":[9.8112506866,48.6866188049],"type":"Point"}
}