{
  "type": "Feature",
  "properties": {
    "iso:country":"DE",
    "sg:address":"Lindenstr. 19",
    "sg:city":"Osternienburg",
    "sg:phone":"+49 34973/21307",
    "sg:postcode":"06386",
    "sg:province":"Sachsen-Anhalt",
    "wof:name":"Rosen-apotheke",
    "wof:placetype":"venue"
},
  "geometry": {"coordinates":[12.01525,51.799068],"type":"Point"}
}