{
  "type": "Feature",
  "properties": {
    "iso:country":"DE",
    "sg:address":"L\u00fcbecker Str. 51",
    "sg:city":"Berlin",
    "sg:phone":"+49 30/3945922",
    "sg:postcode":"10559",
    "sg:province":"Berlin",
    "wof:name":"M\u00f6llring",
    "wof:placetype":"venue"
},
  "geometry": {"coordinates":[13.345225,52.526882],"type":"Point"}
}