{
  "type": "Feature",
  "properties": {
    "iso:country":"DE",
    "sg:address":"M\u00fchlenstr. 31",
    "sg:city":"L\u00fcdinghausen",
    "sg:postcode":"59348",
    "sg:province":"Nordrhein-Westfalen",
    "wof:name":"Arbeitsgemeinschaft L\u00fcdinghauser Kaufleute",
    "wof:placetype":"venue"
},
  "geometry": {"coordinates":[7.4472517967,51.7705497742],"type":"Point"}
}