{
  "type": "Feature",
  "properties": {
    "iso:country":"DE",
    "sg:address":"Senckenberganlage 13-17",
    "sg:city":"Frankfurt",
    "sg:phone":"+49 69/7982007",
    "sg:postcode":"60325",
    "sg:province":"Hessen",
    "wof:name":"Fachbereich Gesellschafts- Wissenschaften",
    "wof:placetype":"venue"
},
  "geometry": {"coordinates":[8.6514806747,50.1153144836],"type":"Point"}
}