{
  "type": "Feature",
  "properties": {
    "iso:country":"DE",
    "sg:address":"Parsberger H\u00f6he 4a",
    "sg:city":"Miesbach",
    "sg:phone":"+49 8025/5540",
    "sg:postcode":"83714",
    "sg:province":"Bayern",
    "wof:name":"Hm Veranstaltungsservice Gmbh",
    "wof:placetype":"venue"
},
  "geometry": {"coordinates":[11.884358,47.771626],"type":"Point"}
}