{
  "type": "Feature",
  "properties": {
    "iso:country":"DE",
    "sg:address":"Baldinger Str. 3",
    "sg:city":"N\u00f6rdlingen",
    "sg:postcode":"86720",
    "sg:province":"Bayern",
    "wof:name":"Reformhaus Wittmann & Grunert Ohg",
    "wof:placetype":"venue"
},
  "geometry": {"coordinates":[10.4878149033,48.8520774841],"type":"Point"}
}