{
  "type": "Feature",
  "properties": {
    "iso:country":"DE",
    "sg:address":"Schulze-Delitzsch-Str. 16",
    "sg:city":"Meppen",
    "sg:phone":"+49 5931/17170",
    "sg:postcode":"49716",
    "sg:province":"Niedersachsen",
    "wof:name":"Manfred L\u00fchring",
    "wof:placetype":"venue"
},
  "geometry": {"coordinates":[7.2962431908,52.6649131775],"type":"Point"}
}