{
  "type": "Feature",
  "properties": {
    "iso:country":"DE",
    "sg:address":"Merveldtstr. 309",
    "sg:city":"Recklinghausen",
    "sg:phone":"+49 2361/81064",
    "sg:postcode":"45665",
    "sg:province":"Nordrhein-Westfalen",
    "wof:name":"Heinrich G\u00f6ttken Gmbh",
    "wof:placetype":"venue"
},
  "geometry": {"coordinates":[7.2589120865,51.59167099],"type":"Point"}
}