{
  "type": "Feature",
  "properties": {
    "iso:country":"DE",
    "sg:address":"Silostr. 5",
    "sg:city":"J\u00fcchen",
    "sg:phone":"+49 2165/888",
    "sg:postcode":"41363",
    "sg:province":"Nordrhein-Westfalen",
    "wof:name":"J\u00fcchener Molkerei- Genossenschaft Eg",
    "wof:placetype":"venue"
},
  "geometry": {"coordinates":[6.4997210503,51.0975723267],"type":"Point"}
}