{
  "type": "Feature",
  "properties": {
    "iso:country":"DE",
    "sg:address":"Eberst\u00e4dter Str. 131",
    "sg:city":"Pfungstadt",
    "sg:phone":"+49 6157/81364",
    "sg:postcode":"64319",
    "sg:province":"Hessen",
    "wof:name":"Deutsche Shell Ag",
    "wof:placetype":"venue"
},
  "geometry": {"coordinates":[8.611287117,49.8070106506],"type":"Point"}
}