{
  "type": "Feature",
  "properties": {
    "iso:country":"DE",
    "sg:address":"Freitagsgasse 1",
    "sg:city":"Meiningen",
    "sg:phone":"+49 3693/471343",
    "sg:postcode":"98617",
    "sg:province":"Th\u00fcringen",
    "wof:name":"Stz S\u00fcdth\u00fcringer Zeitung",
    "wof:placetype":"venue"
},
  "geometry": {"coordinates":[10.4168195724,50.5669364929],"type":"Point"}
}