{
  "type": "Feature",
  "properties": {
    "iso:country":"DE",
    "sg:address":"Bettenser Weg 1",
    "sg:city":"Ronnenberg",
    "sg:phone":"+49 5109/7691",
    "sg:postcode":"30952",
    "sg:province":"Niedersachsen",
    "wof:name":"Friedrich Keese",
    "wof:placetype":"venue"
},
  "geometry": {"coordinates":[9.66118,52.313793],"type":"Point"}
}