{
  "type": "Feature",
  "properties": {
    "iso:country":"DE",
    "sg:address":"Moselstr. 11",
    "sg:city":"Kesten",
    "sg:phone":"+49 6535/463",
    "sg:postcode":"54518",
    "sg:province":"Rheinland-Pfalz",
    "wof:name":"H. Falkenberg-j\u00fcngling",
    "wof:placetype":"venue"
},
  "geometry": {"coordinates":[6.9576821327,49.9019088745],"type":"Point"}
}