{
  "type": "Feature",
  "properties": {
    "iso:country":"DE",
    "sg:address":"Junckerstr.",
    "sg:city":"Neuruppin",
    "sg:phone":"+49 3391/505511",
    "sg:postcode":"16816",
    "sg:province":"Brandenburg",
    "wof:name":"Bierkneipe City-dance-club 019",
    "wof:placetype":"venue"
},
  "geometry": {"coordinates":[12.7961597443,52.9195289612],"type":"Point"}
}