{
  "type": "Feature",
  "properties": {
    "iso:country":"DE",
    "sg:address":"Sedanstr. 3",
    "sg:city":"Herne",
    "sg:phone":"+49 2323/21090",
    "sg:postcode":"44629",
    "sg:province":"Nordrhein-Westfalen",
    "wof:name":"Felix Ohlsen Textilien",
    "wof:placetype":"venue"
},
  "geometry": {"coordinates":[7.2070941925,51.5443916321],"type":"Point"}
}