{
  "type": "Feature",
  "properties": {
    "iso:country":"DE",
    "sg:address":"Pottensteiner Str. 11",
    "sg:city":"Hummeltal",
    "sg:phone":"+49 9201/1036",
    "sg:postcode":"95503",
    "sg:province":"Bayern",
    "wof:name":"Pension Seemannruh",
    "wof:placetype":"venue"
},
  "geometry": {"coordinates":[11.5088129044,49.8887214661],"type":"Point"}
}