{
  "type": "Feature",
  "properties": {
    "iso:country":"DE",
    "sg:address":"Oberdiller Str. 48",
    "sg:city":"Baierbrunn",
    "sg:phone":"+49 89/7931780",
    "sg:postcode":"82065",
    "sg:province":"Bayern",
    "wof:name":"Hans Jauss",
    "wof:placetype":"venue"
},
  "geometry": {"coordinates":[11.470971,48.021309],"type":"Point"}
}