{
  "type": "Feature",
  "properties": {
    "iso:country":"DE",
    "sg:address":"Aktienstr. 1-7",
    "sg:city":"M\u00fclheim",
    "sg:phone":"+49 208/479240",
    "sg:postcode":"45473",
    "sg:province":"Nordrhein-Westfalen",
    "wof:name":"Vvk Shop Gmbh",
    "wof:placetype":"venue"
},
  "geometry": {"coordinates":[6.8770718575,51.4337310791],"type":"Point"}
}