{
  "type": "Feature",
  "properties": {
    "iso:country":"DE",
    "sg:address":"Kurgartenstr. 17",
    "sg:city":"Bad D\u00fcrkheim",
    "sg:phone":"+49 6322/6020",
    "sg:postcode":"67098",
    "sg:province":"Rheinland-Pfalz",
    "wof:name":"Parkhotel Leininger Hof Gmbh",
    "wof:placetype":"venue"
},
  "geometry": {"coordinates":[8.1692905426,49.4623031616],"type":"Point"}
}