{
  "type": "Feature",
  "properties": {
    "iso:country":"DE",
    "sg:address":"67595",
    "sg:city":"Bechtheim",
    "sg:phone":"+49 6242/1504",
    "sg:postcode":"67595",
    "sg:province":"Rheinland-Pfalz",
    "wof:name":"Ev. Pfarramt",
    "wof:placetype":"venue"
},
  "geometry": {"coordinates":[8.2923269272,49.72681427],"type":"Point"}
}