{
  "type": "Feature",
  "properties": {
    "iso:country":"DE",
    "sg:address":"Leimbergerstr. 4",
    "sg:city":"Weiden",
    "sg:phone":"+49 961/23405",
    "sg:postcode":"92637",
    "sg:province":"Bayern",
    "wof:name":"Sonnen-apotheke",
    "wof:placetype":"venue"
},
  "geometry": {"coordinates":[12.15061,49.672394],"type":"Point"}
}