{
  "type": "Feature",
  "properties": {
    "iso:country":"DE",
    "sg:address":"Th\u00fcnenstr. 2",
    "sg:city":"L\u00fcdenscheid",
    "sg:phone":"+49 2351/38278",
    "sg:postcode":"58511",
    "sg:province":"Nordrhein-Westfalen",
    "wof:name":"Knoop-troullier Moden Gmbh & Co. Kg",
    "wof:placetype":"venue"
},
  "geometry": {"coordinates":[7.63121,51.217224],"type":"Point"}
}