{
  "type": "Feature",
  "properties": {
    "iso:country":"DE",
    "sg:address":"Schuchardstr. 11",
    "sg:city":"Schwalmstadt",
    "sg:phone":"+49 6691/24389",
    "sg:postcode":"34613",
    "sg:province":"Hessen",
    "wof:name":"U. Ochse",
    "wof:placetype":"venue"
},
  "geometry": {"coordinates":[9.176896,50.910358],"type":"Point"}
}