{
  "type": "Feature",
  "properties": {
    "iso:country":"DE",
    "sg:address":"Albert-Schweitzer-Str. 6",
    "sg:city":"Linkenheim-Hochstetten",
    "sg:phone":"+49 7247/4028",
    "sg:postcode":"76351",
    "sg:province":"Baden-W\u00fcrttemberg",
    "wof:name":"Jakob Container Service Gmbh",
    "wof:placetype":"venue"
},
  "geometry": {"coordinates":[8.4084482193,49.1241874695],"type":"Point"}
}