{
  "type": "Feature",
  "properties": {
    "iso:country":"DE",
    "sg:address":"Bahnhofstr. 15",
    "sg:city":"Armsheim",
    "sg:phone":"+49 6732/8010",
    "sg:postcode":"55288",
    "sg:province":"Rheinland-Pfalz",
    "wof:name":"Raiffeisen Warengenossenschaft Eg",
    "wof:placetype":"venue"
},
  "geometry": {"coordinates":[8.059044,49.80714],"type":"Point"}
}