{
  "type": "Feature",
  "properties": {
    "iso:country":"DE",
    "sg:address":"Jahnstr. 28",
    "sg:city":"D\u00fcsseldorf",
    "sg:phone":"+49 211/377704",
    "sg:postcode":"40215",
    "sg:province":"Nordrhein-Westfalen",
    "wof:name":"Marlies Und Friedr. Kluth Ohg",
    "wof:placetype":"venue"
},
  "geometry": {"coordinates":[6.7809591293,51.2158088684],"type":"Point"}
}