{
  "type": "Feature",
  "properties": {
    "iso:country":"DE",
    "sg:address":"Siegburger Str. 5",
    "sg:city":"Bendorf",
    "sg:phone":"+49 2622/94170",
    "sg:postcode":"56170",
    "sg:province":"Rheinland-Pfalz",
    "wof:name":"Mabanaft Deutschland Gmbh",
    "wof:placetype":"venue"
},
  "geometry": {"coordinates":[7.5757808685,50.4238471985],"type":"Point"}
}