{
  "type": "Feature",
  "properties": {
    "iso:country":"DE",
    "sg:address":"Ober-Rodener-Str. 121",
    "sg:city":"Rodgau",
    "sg:phone":"+49 6106/876373",
    "sg:postcode":"63110",
    "sg:province":"Hessen",
    "wof:name":"R. Und U. Hetzel",
    "wof:placetype":"venue"
},
  "geometry": {"coordinates":[8.865058,49.993877],"type":"Point"}
}