{
  "type": "Feature",
  "properties": {
    "iso:country":"DE",
    "sg:address":"Kleine Hammerstr. 49",
    "sg:city":"Essen",
    "sg:postcode":"45326",
    "sg:province":"Nordrhein-Westfalen",
    "wof:name":"As Bauunternehmung Gmbh",
    "wof:placetype":"venue"
},
  "geometry": {"coordinates":[6.996969,51.476692],"type":"Point"}
}