{
  "type": "Feature",
  "properties": {
    "iso:country":"DE",
    "sg:address":"Graurheindorfer Str. 153 b",
    "sg:city":"Bonn",
    "sg:postcode":"53117",
    "sg:province":"Nordrhein-Westfalen",
    "wof:name":"Callahan Nordrhein- Westfalen Gmbh",
    "wof:placetype":"venue"
},
  "geometry": {"coordinates":[7.089885,50.751694],"type":"Point"}
}