{
  "type": "Feature",
  "properties": {
    "iso:country":"DE",
    "sg:address":"Wittener Str. 227",
    "sg:city":"Bochum",
    "sg:phone":"+49 234/350974",
    "sg:postcode":"44803",
    "sg:province":"Nordrhein-Westfalen",
    "wof:name":"Schraubenkiste Gerda Rutkowski",
    "wof:placetype":"venue"
},
  "geometry": {"coordinates":[7.2463798523,51.4719772339],"type":"Point"}
}