{
  "type": "Feature",
  "properties": {
    "iso:country":"DE",
    "sg:address":"Am M\u00fchlbach 2",
    "sg:city":"Lichtenfels",
    "sg:phone":"+49 9571/74250",
    "sg:postcode":"96215",
    "sg:province":"Bayern",
    "wof:name":"Joachim Schachler",
    "wof:placetype":"venue"
},
  "geometry": {"coordinates":[11.0614051819,50.1499023438],"type":"Point"}
}