{
  "type": "Feature",
  "properties": {
    "iso:country":"DE",
    "sg:address":"Kaiserstr. 12",
    "sg:city":"Gummersbach",
    "sg:phone":"+49 2261/28348",
    "sg:postcode":"51643",
    "sg:province":"Nordrhein-Westfalen",
    "wof:name":"Primus Consult E. K.",
    "wof:placetype":"venue"
},
  "geometry": {"coordinates":[7.566238,51.026978],"type":"Point"}
}