{
  "type": "Feature",
  "properties": {
    "iso:country":"DE",
    "sg:address":"Gartenstr. 6",
    "sg:city":"Aschheim",
    "sg:phone":"+49 89/9031917",
    "sg:postcode":"85609",
    "sg:province":"Bayern",
    "wof:name":"Fritz Berkermann",
    "wof:placetype":"venue"
},
  "geometry": {"coordinates":[11.7088279724,48.1793327332],"type":"Point"}
}