{
  "type": "Feature",
  "properties": {
    "iso:country":"DE",
    "sg:address":"Haldenbergerstr. 28",
    "sg:city":"M\u00fcnchen",
    "sg:phone":"+49 89/1404252",
    "sg:postcode":"80997",
    "sg:province":"Bayern",
    "wof:name":"Lang Winterg\u00e4rten Vertriebs Gmbh",
    "wof:placetype":"venue"
},
  "geometry": {"coordinates":[11.4897222519,48.1766624451],"type":"Point"}
}