{
  "type": "Feature",
  "properties": {
    "iso:country":"DE",
    "sg:address":"Theodor-Heuss-Str. 6",
    "sg:city":"M\u00fcnchberg",
    "sg:phone":"+49 9251/80060",
    "sg:postcode":"95213",
    "sg:province":"Bayern",
    "wof:name":"T. Pabstmann",
    "wof:placetype":"venue"
},
  "geometry": {"coordinates":[11.7774076462,50.1892166138],"type":"Point"}
}