{
  "type": "Feature",
  "properties": {
    "iso:country":"DE",
    "sg:address":"Ellwanger Str. 97",
    "sg:city":"Bopfingen",
    "sg:postcode":"73441",
    "sg:province":"Baden-W\u00fcrttemberg",
    "wof:name":"Re-bo Reber Gmbh",
    "wof:placetype":"venue"
},
  "geometry": {"coordinates":[10.345633,48.871841],"type":"Point"}
}