{
  "type": "Feature",
  "properties": {
    "iso:country":"DE",
    "sg:address":"Laberstr. 5",
    "sg:city":"Mallersdorf-Pfaffenberg",
    "sg:phone":"+49 8772/252",
    "sg:postcode":"84066",
    "sg:province":"Bayern",
    "wof:name":"Fritz Steger",
    "wof:placetype":"venue"
},
  "geometry": {"coordinates":[12.2307395935,48.7662086487],"type":"Point"}
}