{
  "type": "Feature",
  "properties": {
    "iso:country":"DE",
    "sg:address":"Zur M\u00e4rk 6",
    "sg:city":"Warburg",
    "sg:phone":"+49 5642/1216",
    "sg:postcode":"34414",
    "sg:province":"Nordrhein-Westfalen",
    "wof:name":"Werner Wagemann",
    "wof:placetype":"venue"
},
  "geometry": {"coordinates":[9.062279,51.531673],"type":"Point"}
}