{
  "type": "Feature",
  "properties": {
    "iso:country":"DE",
    "sg:address":"Lange Str. 38",
    "sg:city":"Luckau",
    "sg:phone":"+49 3544/2490",
    "sg:postcode":"15926",
    "sg:province":"Brandenburg",
    "wof:name":"Thomas Zrocke",
    "wof:placetype":"venue"
},
  "geometry": {"coordinates":[13.7173871994,51.8516159058],"type":"Point"}
}