{
  "type": "Feature",
  "properties": {
    "iso:country":"DE",
    "sg:address":"Buchholzer Str. 8",
    "sg:city":"Hannover",
    "sg:phone":"+49 511/580179",
    "sg:postcode":"30629",
    "sg:province":"Niedersachsen",
    "wof:name":"Hans-joachim Kielmann",
    "wof:placetype":"venue"
},
  "geometry": {"coordinates":[9.8518362045,52.391204834],"type":"Point"}
}