{
  "type": "Feature",
  "properties": {
    "iso:country":"DE",
    "sg:address":"Hoher Weg 1",
    "sg:city":"Waldenbuch",
    "sg:phone":"+49 7157/72644",
    "sg:postcode":"71111",
    "sg:province":"Baden-W\u00fcrttemberg",
    "wof:name":"A. Fischer Heilpraktiker",
    "wof:placetype":"venue"
},
  "geometry": {"coordinates":[9.1567401886,48.6301269531],"type":"Point"}
}