{
  "type": "Feature",
  "properties": {
    "iso:country":"DE",
    "sg:address":"Waldweg 53",
    "sg:city":"Waldfeucht",
    "sg:postcode":"52525",
    "sg:province":"Nordrhein-Westfalen",
    "wof:name":"Spectro Verwertungs- Und Entsorgungssysteme Gmbh",
    "wof:placetype":"venue"
},
  "geometry": {"coordinates":[6.0196948051,51.0910606384],"type":"Point"}
}