{
  "type": "Feature",
  "properties": {
    "iso:country":"DE",
    "sg:address":"Mauerstr. 22",
    "sg:city":"D\u00fcsseldorf",
    "sg:phone":"+49 211/4911527",
    "sg:postcode":"40476",
    "sg:province":"Nordrhein-Westfalen",
    "wof:name":"Im Laternchen",
    "wof:placetype":"venue"
},
  "geometry": {"coordinates":[6.7789411545,51.2420196533],"type":"Point"}
}