{
  "type": "Feature",
  "properties": {
    "iso:country":"DE",
    "sg:address":"Hauptstr. 38",
    "sg:city":"K\u00fchnhaide",
    "sg:phone":"+49 37364/88802",
    "sg:postcode":"09496",
    "sg:province":"Sachsen",
    "wof:name":"Ehvo Sonderanlagenbau Gmbh",
    "wof:placetype":"venue"
},
  "geometry": {"coordinates":[13.191801,50.619682],"type":"Point"}
}