{
  "type": "Feature",
  "properties": {
    "iso:country":"DE",
    "sg:address":"Linder Str. 7",
    "sg:city":"Zirndorf",
    "sg:postcode":"90513",
    "sg:province":"Bayern",
    "wof:name":"Madeleine Mode Gmbh",
    "wof:placetype":"venue"
},
  "geometry": {"coordinates":[10.9522161484,49.4372901917],"type":"Point"}
}