{
  "type": "Feature",
  "properties": {
    "iso:country":"DE",
    "sg:address":"Simmerner Str. 7",
    "sg:city":"Argenthal",
    "sg:phone":"+49 4967/613935",
    "sg:postcode":"55496",
    "sg:province":"Rheinland-Pfalz",
    "wof:name":"Walter Kunz",
    "wof:placetype":"venue"
},
  "geometry": {"coordinates":[7.594686985,49.975933075],"type":"Point"}
}