{
  "type": "Feature",
  "properties": {
    "iso:country":"DE",
    "sg:address":"Grabbenweg 1",
    "sg:city":"Aerzen",
    "sg:phone":"+49 5154/8700",
    "sg:postcode":"31855",
    "sg:province":"Niedersachsen",
    "wof:name":"Karl Pape",
    "wof:placetype":"venue"
},
  "geometry": {"coordinates":[9.224333,52.072006],"type":"Point"}
}