{
  "type": "Feature",
  "properties": {
    "iso:country":"DE",
    "sg:address":"Unterf\u00fcrberger Str. 21",
    "sg:city":"F\u00fcrth",
    "sg:phone":"+49 911/722462",
    "sg:postcode":"90768",
    "sg:province":"Bayern",
    "wof:name":"Elke Steinbrecher",
    "wof:placetype":"venue"
},
  "geometry": {"coordinates":[10.9606361389,49.4730682373],"type":"Point"}
}