{
  "type": "Feature",
  "properties": {
    "iso:country":"DE",
    "sg:address":"Langgasse 26",
    "sg:city":"Hungen",
    "sg:phone":"+49 6402/504737",
    "sg:postcode":"35410",
    "sg:province":"Hessen",
    "wof:name":"Elektro- & Industrietechnik Reif Gmbh",
    "wof:placetype":"venue"
},
  "geometry": {"coordinates":[8.93849,50.504616],"type":"Point"}
}