{
  "type": "Feature",
  "properties": {
    "iso:country":"DE",
    "sg:address":"Lehmkuhlenweg 17",
    "sg:city":"M\u00f6nchengladbach",
    "sg:phone":"+49 2161/96860",
    "sg:postcode":"41065",
    "sg:province":"Nordrhein-Westfalen",
    "wof:name":"Windeln- Verwaltungsgesellschaft Mbh",
    "wof:placetype":"venue"
},
  "geometry": {"coordinates":[6.473266,51.211269],"type":"Point"}
}