{
  "type": "Feature",
  "properties": {
    "iso:country":"DE",
    "sg:address":"Freisinger Str. 71",
    "sg:city":"Ismaning",
    "sg:phone":"+49 89/964373",
    "sg:postcode":"85737",
    "sg:province":"Bayern",
    "wof:name":"Franz Seidl Bodenbel\u00e4ge Inh. Robert Seidl E. K.",
    "wof:placetype":"venue"
},
  "geometry": {"coordinates":[11.6883096695,48.2469100952],"type":"Point"}
}