{
  "type": "Feature",
  "properties": {
    "iso:country":"DE",
    "sg:address":"R\u00f6hlingsplatz 1",
    "sg:city":"Rendsburg",
    "sg:postcode":"24768",
    "sg:province":"Schleswig-Holstein",
    "wof:name":"Beteiligungs- Und Verwaltungsgesellschaft",
    "wof:placetype":"venue"
},
  "geometry": {"coordinates":[9.6679153442,54.3034591675],"type":"Point"}
}