{
  "type": "Feature",
  "properties": {
    "iso:country":"DE",
    "sg:address":"Stolzingstr. 35",
    "sg:city":"M\u00fcnchen",
    "sg:phone":"+49 89/912371",
    "sg:postcode":"81927",
    "sg:province":"Bayern",
    "wof:name":"W. Querfurt",
    "wof:placetype":"venue"
},
  "geometry": {"coordinates":[11.6326723099,48.1578826904],"type":"Point"}
}