{
  "type": "Feature",
  "properties": {
    "iso:country":"DE",
    "sg:address":"Konrad-Adenauer-Allee 10",
    "sg:city":"Bad Vilbel",
    "sg:postcode":"61118",
    "sg:province":"Hessen",
    "wof:name":"Centrum Bad Vilbel Gmbh",
    "wof:placetype":"venue"
},
  "geometry": {"coordinates":[8.7434625626,50.2030563354],"type":"Point"}
}