{
  "type": "Feature",
  "properties": {
    "iso:country":"DE",
    "sg:address":"Bergstr. 89",
    "sg:city":"Lahr",
    "sg:phone":"+49 7821/955250",
    "sg:postcode":"77933",
    "sg:province":"Baden-W\u00fcrttemberg",
    "wof:name":"Ivb Immobilien Ohg",
    "wof:placetype":"venue"
},
  "geometry": {"coordinates":[7.8487639427,48.3428153992],"type":"Point"}
}