{
  "type": "Feature",
  "properties": {
    "iso:country":"DE",
    "sg:address":"Alsfelder Str. 17",
    "sg:city":"Dietzenbach",
    "sg:phone":"+49 6074/27122",
    "sg:postcode":"63128",
    "sg:province":"Hessen",
    "wof:name":"Wolfgang Gan\u00df Ingenieur",
    "wof:placetype":"venue"
},
  "geometry": {"coordinates":[8.7715520859,49.9958305359],"type":"Point"}
}