{
  "type": "Feature",
  "properties": {
    "iso:country":"DE",
    "sg:address":"Londorfer Stra\u00dfe 65",
    "sg:city":"Gr\u00fcnberg",
    "sg:phone":"+49 6401",
    "sg:postcode":"35305",
    "sg:province":"Hessen",
    "wof:name":"Bender Gmbh & Co. Kg - Elektrische Sicherheit",
    "wof:placetype":"venue"
},
  "geometry": {"coordinates":[8.947932,50.592278],"type":"Point"}
}