{
  "type": "Feature",
  "properties": {
    "iso:country":"DE",
    "sg:address":"Henri-Spaak-Str. 57",
    "sg:city":"Alfter",
    "sg:phone":"+49 228/645758",
    "sg:postcode":"53347",
    "sg:province":"Nordrhein-Westfalen",
    "wof:name":"Edgar Fischer Regalsysteme",
    "wof:placetype":"venue"
},
  "geometry": {"coordinates":[7.026341,50.71117],"type":"Point"}
}