{
  "type": "Feature",
  "properties": {
    "iso:country":"DE",
    "sg:address":"H\u00e4berlstr. 12",
    "sg:city":"M\u00fcnchen",
    "sg:phone":"+49 89/532265",
    "sg:postcode":"80337",
    "sg:province":"Bayern",
    "wof:name":"Ronald Fischer",
    "wof:placetype":"venue"
},
  "geometry": {"coordinates":[11.5582752228,48.1281852722],"type":"Point"}
}