{
  "type": "Feature",
  "properties": {
    "iso:country":"DE",
    "sg:address":"Kirchweiler Stra\u00dfe 11",
    "sg:city":"Pelm",
    "sg:phone":"+49 171 8274440",
    "sg:postcode":"54570",
    "sg:province":"Rheinland-Pfalz",
    "wof:name":"Andre Gilles E.t.m.",
    "wof:placetype":"venue"
},
  "geometry": {"coordinates":[6.691987,50.233883],"type":"Point"}
}