{
  "type": "Feature",
  "properties": {
    "iso:country":"DE",
    "sg:address":"Honigloch 17",
    "sg:city":"Velbert",
    "sg:phone":"+49 2051/65983",
    "sg:postcode":"42549",
    "sg:province":"Nordrhein-Westfalen",
    "wof:name":"Hans Hornscheidt Heilpraktiker",
    "wof:placetype":"venue"
},
  "geometry": {"coordinates":[7.0351948738,51.325843811],"type":"Point"}
}