{
  "type": "Feature",
  "properties": {
    "iso:country":"DE",
    "sg:address":"Spessartstr. 14",
    "sg:city":"Eppertshausen",
    "sg:phone":"+49 6071/32569",
    "sg:postcode":"64859",
    "sg:province":"Hessen",
    "wof:name":"Karl Prosch",
    "wof:placetype":"venue"
},
  "geometry": {"coordinates":[8.85962677,49.9490318298],"type":"Point"}
}