{
  "type": "Feature",
  "properties": {
    "iso:country":"DE",
    "sg:address":"Hauptstr.",
    "sg:city":"H\u00f6nningen",
    "sg:phone":"+49 2695/92010",
    "sg:postcode":"53506",
    "sg:province":"Rheinland-Pfalz",
    "wof:name":"Josef Emmerich Pumpenfabrik Gmbh",
    "wof:placetype":"venue"
},
  "geometry": {"coordinates":[6.9504370689,50.4702453613],"type":"Point"}
}