{
  "type": "Feature",
  "properties": {
    "iso:country":"DE",
    "sg:city":"Schweskau Simander",
    "sg:phone":"+49 4958/83262",
    "sg:postcode":"29485",
    "sg:province":"Niedersachsen",
    "wof:name":"Volksbank Wendland Eg",
    "wof:placetype":"venue"
},
  "geometry": {"coordinates":[11.322247,52.919483],"type":"Point"}
}