{
  "type": "Feature",
  "properties": {
    "iso:country":"DE",
    "sg:address":"Dieselstr. 1",
    "sg:city":"Eggenstein-Leopoldshafen",
    "sg:phone":"+49 4972/1978340",
    "sg:postcode":"76344",
    "sg:province":"Baden-W\u00fcrttemberg",
    "wof:name":"Petrie Elektrotechnik Gmbh",
    "wof:placetype":"venue"
},
  "geometry": {"coordinates":[8.378021,49.075813],"type":"Point"}
}