{
  "type": "Feature",
  "properties": {
    "iso:country":"DE",
    "sg:address":"An der Engesohde 4",
    "sg:city":"Hannover",
    "sg:phone":"+49 511/883306",
    "sg:postcode":"30173",
    "sg:province":"Niedersachsen",
    "wof:name":"Heinrich Mensing",
    "wof:placetype":"venue"
},
  "geometry": {"coordinates":[9.7540225983,52.3522415161],"type":"Point"}
}