{
  "type": "Feature",
  "properties": {
    "iso:country":"DE",
    "sg:address":"Heinestr 6",
    "sg:city":"Selb",
    "sg:phone":"+49 9287/2163",
    "sg:postcode":"95100",
    "sg:province":"Bayern",
    "wof:name":"Druck- Und Werbezentrum Selb",
    "wof:placetype":"venue"
},
  "geometry": {"coordinates":[12.1264438629,50.1707839966],"type":"Point"}
}