{
  "type": "Feature",
  "properties": {
    "iso:country":"DE",
    "sg:address":"Siedlungsstr. 6",
    "sg:city":"Gr\u00fcndau",
    "sg:phone":"+49 6051/12950",
    "sg:postcode":"63584",
    "sg:province":"Hessen",
    "wof:name":"Reinhold-wagner Formen-werkzeug- Und",
    "wof:placetype":"venue"
},
  "geometry": {"coordinates":[9.137881,50.207466],"type":"Point"}
}