{
  "type": "Feature",
  "properties": {
    "iso:country":"DE",
    "sg:address":"Kirchweg 10",
    "sg:city":"Regensburg",
    "sg:phone":"+49 941/76464",
    "sg:postcode":"93055",
    "sg:province":"Bayern",
    "wof:name":"Karl Gietl",
    "wof:placetype":"venue"
},
  "geometry": {"coordinates":[12.139529,48.992481],"type":"Point"}
}