{
  "type": "Feature",
  "properties": {
    "iso:country":"DE",
    "sg:address":"L\u00f6hrstr. 1",
    "sg:city":"Amorbach",
    "sg:phone":"+49 9373/3171",
    "sg:postcode":"63916",
    "sg:province":"Bayern",
    "wof:name":"H. Kraft",
    "wof:placetype":"venue"
},
  "geometry": {"coordinates":[9.218858,49.644257],"type":"Point"}
}