{
  "type": "Feature",
  "properties": {
    "iso:country":"DE",
    "sg:address":"Alte Str. 2",
    "sg:city":"Altenbrak",
    "sg:phone":"+49 39456/309",
    "sg:postcode":"38889",
    "sg:province":"Sachsen-Anhalt",
    "wof:name":"Rolf Br\u00f6mer",
    "wof:placetype":"venue"
},
  "geometry": {"coordinates":[10.9287347794,51.729511261],"type":"Point"}
}