{
  "type": "Feature",
  "properties": {
    "iso:country":"DE",
    "sg:address":"6 grande rue",
    "sg:city":"fontenay aux roses",
    "sg:phone":"+49 6162/52584",
    "sg:postcode":"92260",
    "sg:province":"Bayern",
    "wof:name":"Win Money",
    "wof:placetype":"venue"
},
  "geometry": {"coordinates":[2.286185,48.792885],"type":"Point"}
}