{
  "type": "Feature",
  "properties": {
    "iso:country":"DE",
    "sg:address":"Norderstr. 2",
    "sg:city":"Marne",
    "sg:phone":"+49 4851/1432",
    "sg:postcode":"25709",
    "sg:province":"Schleswig-Holstein",
    "wof:name":"Bimmels Kneipothek",
    "wof:placetype":"venue"
},
  "geometry": {"coordinates":[9.0091285706,53.9535675049],"type":"Point"}
}