{
  "type": "Feature",
  "properties": {
    "iso:country":"DE",
    "sg:address":"Wittelsbacherstr. 1",
    "sg:city":"Geiselh\u00f6ring",
    "sg:phone":"+49 9423/582",
    "sg:postcode":"94333",
    "sg:province":"Bayern",
    "wof:name":"\u00d6ffentliche B\u00fccherei",
    "wof:placetype":"venue"
},
  "geometry": {"coordinates":[12.396359,48.825607],"type":"Point"}
}