{
  "type": "Feature",
  "properties": {
    "iso:country":"DE",
    "sg:address":"Am Mittelweg 2a",
    "sg:city":"Friedrichroda",
    "sg:phone":"+49 3623/200161",
    "sg:postcode":"99894",
    "sg:province":"Th\u00fcringen",
    "wof:name":"Ausbau Schleiwies Gmbh",
    "wof:placetype":"venue"
},
  "geometry": {"coordinates":[10.583829,50.858353],"type":"Point"}
}