{
  "type": "Feature",
  "properties": {
    "iso:country":"DE",
    "sg:address":"Kocherstr. 11",
    "sg:city":"Schw\u00e4bisch Hall",
    "sg:phone":"+49 791/43375",
    "sg:postcode":"74523",
    "sg:province":"Baden-W\u00fcrttemberg",
    "wof:name":"Munz",
    "wof:placetype":"venue"
},
  "geometry": {"coordinates":[9.741918,49.129845],"type":"Point"}
}