{
  "type": "Feature",
  "properties": {
    "iso:country":"DE",
    "sg:address":"Rohrstr. 3",
    "sg:city":"Hagen",
    "sg:phone":"+49 2331/57378",
    "sg:postcode":"58093",
    "sg:province":"Nordrhein-Westfalen",
    "wof:name":"Klaus Jung",
    "wof:placetype":"venue"
},
  "geometry": {"coordinates":[7.5140271187,51.3800163269],"type":"Point"}
}