{
  "type": "Feature",
  "properties": {
    "iso:country":"DE",
    "sg:address":"Buchenhag 221",
    "sg:city":"Waldalgesheim",
    "sg:phone":"+49 6721/32231",
    "sg:postcode":"55425",
    "sg:province":"Rheinland-Pfalz",
    "wof:name":"Waldsch\u00e4nke",
    "wof:placetype":"venue"
},
  "geometry": {"coordinates":[7.815926075,49.9703178406],"type":"Point"}
}