{
  "type": "Feature",
  "properties": {
    "iso:country":"DE",
    "sg:address":"Markt 9",
    "sg:city":"Kemberg",
    "sg:phone":"+49 34921/20225",
    "sg:postcode":"06901",
    "sg:province":"Sachsen-Anhalt",
    "wof:name":"E. H\u00f6ger",
    "wof:placetype":"venue"
},
  "geometry": {"coordinates":[12.6358308792,51.7735290527],"type":"Point"}
}