{
  "type": "Feature",
  "properties": {
    "iso:country":"DE",
    "sg:address":"Himmelreichallee 40",
    "sg:city":"M\u00fcnster",
    "sg:phone":"+49 251/511896",
    "sg:postcode":"48149",
    "sg:province":"Nordrhein-Westfalen",
    "wof:name":"Lbs Wohnungsbau Gmbh",
    "wof:placetype":"venue"
},
  "geometry": {"coordinates":[7.613831,51.958488],"type":"Point"}
}