{
  "type": "Feature",
  "properties": {
    "iso:country":"DE",
    "sg:address":"Platzl 4a",
    "sg:city":"M\u00fcnchen",
    "sg:phone":"+49 89/222900",
    "sg:postcode":"80331",
    "sg:province":"Bayern",
    "wof:name":"Dr. Elsbeth Schwarz Zahn\u00e4rztin",
    "wof:placetype":"venue"
},
  "geometry": {"coordinates":[11.580407,48.138313],"type":"Point"}
}