{
  "type": "Feature",
  "properties": {
    "iso:country":"DE",
    "sg:address":"Westenfeld 56",
    "sg:city":"Altenberge",
    "sg:phone":"+49 2505/8558",
    "sg:postcode":"48341",
    "sg:province":"Nordrhein-Westfalen",
    "wof:name":"Peter Sondermann",
    "wof:placetype":"venue"
},
  "geometry": {"coordinates":[7.4434938431,52.0471076965],"type":"Point"}
}