{
  "type": "Feature",
  "properties": {
    "iso:country":"DE",
    "sg:address":"Zum Tal 4",
    "sg:city":"Wolfsheim",
    "sg:phone":"+49 6701/8213",
    "sg:postcode":"55578",
    "sg:province":"Rheinland-Pfalz",
    "wof:name":"Nashville Amerikanische Und Mexikanische Lebensmittel",
    "wof:placetype":"venue"
},
  "geometry": {"coordinates":[8.0442838669,49.8726806641],"type":"Point"}
}