{
  "type": "Feature",
  "properties": {
    "iso:country":"DE",
    "sg:address":"Hauptstr. 31",
    "sg:city":"Wedemark",
    "sg:phone":"+49 5130/40870",
    "sg:postcode":"30900",
    "sg:province":"Niedersachsen",
    "wof:name":"L. Steinbarth",
    "wof:placetype":"venue"
},
  "geometry": {"coordinates":[9.6818180084,52.5545425415],"type":"Point"}
}