{
  "type": "Feature",
  "properties": {
    "iso:country":"DE",
    "sg:address":"Hagenstr. 10",
    "sg:city":"Pritzwalk",
    "sg:phone":"+49 3395/302097",
    "sg:postcode":"16928",
    "sg:province":"Brandenburg",
    "wof:name":"W. Kovarnik Rechtsanwalt",
    "wof:placetype":"venue"
},
  "geometry": {"coordinates":[12.1770591736,53.1473655701],"type":"Point"}
}