{
  "type": "Feature",
  "properties": {
    "iso:country":"DE",
    "sg:address":"Laubstr. 7 b",
    "sg:city":"Baden-Baden",
    "sg:phone":"+49 7221/301773",
    "sg:postcode":"76530",
    "sg:province":"Baden-W\u00fcrttemberg",
    "wof:name":"Gerhard W. Schmidt Architekt",
    "wof:placetype":"venue"
},
  "geometry": {"coordinates":[8.22251,48.770302],"type":"Point"}
}