{
  "type": "Feature",
  "properties": {
    "iso:country":"DE",
    "sg:address":"Br\u00fchlgasse 14",
    "sg:city":"Waldshut-Tiengen",
    "sg:phone":"+49 7741/2089",
    "sg:postcode":"79761",
    "sg:province":"Baden-W\u00fcrttemberg",
    "wof:name":"Textilreinigung Suso Baumgartner",
    "wof:placetype":"venue"
},
  "geometry": {"coordinates":[8.2767601013,47.6342697144],"type":"Point"}
}