{
  "type": "Feature",
  "properties": {
    "iso:country":"DE",
    "sg:address":"Kn\u00fcll 6",
    "sg:city":"Sch\u00f6nberg",
    "sg:phone":"+49 4344/3080",
    "sg:postcode":"24217",
    "sg:province":"Schleswig-Holstein",
    "wof:name":"Kreissparkasse Pl\u00f6n",
    "wof:placetype":"venue"
},
  "geometry": {"coordinates":[10.372335,54.393486],"type":"Point"}
}