{
  "type": "Feature",
  "properties": {
    "iso:country":"DE",
    "sg:address":"Birkland 44",
    "sg:city":"Peiting",
    "sg:phone":"+49 8869/465",
    "sg:postcode":"86971",
    "sg:province":"Bayern",
    "wof:name":"Neuwirt",
    "wof:placetype":"venue"
},
  "geometry": {"coordinates":[10.9494934082,47.8584785461],"type":"Point"}
}