{
  "type": "Feature",
  "properties": {
    "iso:country":"DE",
    "sg:address":"Bahnhofstr. 83",
    "sg:city":"Ratingen",
    "sg:phone":"+49 2102/66403",
    "sg:postcode":"40883",
    "sg:province":"Nordrhein-Westfalen",
    "wof:name":"Ernst Werntges",
    "wof:placetype":"venue"
},
  "geometry": {"coordinates":[6.901771,51.33559],"type":"Point"}
}