{
  "type": "Feature",
  "properties": {
    "iso:country":"DE",
    "sg:address":"Konrad-Adenauer-Str. 154",
    "sg:city":"Geilenkirchen",
    "sg:phone":"+49 2451/68808",
    "sg:postcode":"52511",
    "sg:province":"Nordrhein-Westfalen",
    "wof:name":"Rainer Dohlen",
    "wof:placetype":"venue"
},
  "geometry": {"coordinates":[6.12054,50.963905],"type":"Point"}
}