{
  "type": "Feature",
  "properties": {
    "iso:country":"DE",
    "sg:address":"Organistenweg 5",
    "sg:city":"Buxtehude",
    "sg:phone":"+49 4161/3518",
    "sg:postcode":"21614",
    "sg:province":"Niedersachsen",
    "wof:name":"Tvilum-scanbirk Gmbh",
    "wof:placetype":"venue"
},
  "geometry": {"coordinates":[9.6990604401,53.4799537659],"type":"Point"}
}