{
  "type": "Feature",
  "properties": {
    "iso:country":"DE",
    "sg:address":"Schellenbergweg 3",
    "sg:city":"Bergen",
    "sg:phone":"+49 8662/8347",
    "sg:postcode":"83346",
    "sg:province":"Bayern",
    "wof:name":"G\u00e4stehaus Franz Eberl",
    "wof:placetype":"venue"
},
  "geometry": {"coordinates":[12.5845899582,47.8072242737],"type":"Point"}
}