{
  "type": "Feature",
  "properties": {
    "iso:country":"DE",
    "sg:address":"Carl-Scheele-Str. 12",
    "sg:city":"Berlin",
    "sg:postcode":"12489",
    "sg:province":"Berlin",
    "wof:name":"Iq Vision Gmbh",
    "wof:placetype":"venue"
},
  "geometry": {"coordinates":[13.5258264542,52.4302024841],"type":"Point"}
}