{
  "type": "Feature",
  "properties": {
    "iso:country":"DE",
    "sg:address":"Hauptstr. 36",
    "sg:city":"Stipshausen",
    "sg:phone":"+49 6544/8589",
    "sg:postcode":"55758",
    "sg:province":"Rheinland-Pfalz",
    "wof:name":"Kuhstall",
    "wof:placetype":"venue"
},
  "geometry": {"coordinates":[7.2916941643,49.8483772278],"type":"Point"}
}