{
  "type": "Feature",
  "properties": {
    "iso:country":"DE",
    "sg:address":"Am Forsthaus 7",
    "sg:city":"Gablingen",
    "sg:postcode":"86456",
    "sg:province":"Bayern",
    "wof:name":"Erber Immobilien E. K.",
    "wof:placetype":"venue"
},
  "geometry": {"coordinates":[10.7898578644,48.4646453857],"type":"Point"}
}