{
  "type": "Feature",
  "properties": {
    "iso:country":"DE",
    "sg:address":"An der Chaussee 45",
    "sg:city":"Gl\u00fcckstadt",
    "sg:phone":"+49 4124/4941",
    "sg:postcode":"25348",
    "sg:province":"Schleswig-Holstein",
    "wof:name":"Susanne & Martin Mahn Gmbh",
    "wof:placetype":"venue"
},
  "geometry": {"coordinates":[9.4361028671,53.7971572876],"type":"Point"}
}