{
  "type": "Feature",
  "properties": {
    "iso:country":"DE",
    "sg:address":"Franz-von-Taxis-Ring 55a",
    "sg:city":"Regensburg",
    "sg:phone":"+49 941/31529",
    "sg:postcode":"93049",
    "sg:province":"Bayern",
    "wof:name":"Intercon E. Kfr.",
    "wof:placetype":"venue"
},
  "geometry": {"coordinates":[12.0516891479,49.0138282776],"type":"Point"}
}