{
  "type": "Feature",
  "properties": {
    "iso:country":"DE",
    "sg:address":"J\u00e4gerhofstr. 19/20",
    "sg:city":"D\u00fcsseldorf",
    "sg:phone":"+49 211/4915990",
    "sg:postcode":"40479",
    "sg:province":"Nordrhein-Westfalen",
    "wof:name":"Concert Team Konzerte Und Veranstaltungen Gmbh",
    "wof:placetype":"venue"
},
  "geometry": {"coordinates":[6.78549,51.230652],"type":"Point"}
}