{
  "type": "Feature",
  "properties": {
    "iso:country":"DE",
    "sg:address":"Werdandiweg 2",
    "sg:city":"Spalt",
    "sg:phone":"+49 9175/328",
    "sg:postcode":"91174",
    "sg:province":"Bayern",
    "wof:name":"H. Und G. Kastner",
    "wof:placetype":"venue"
},
  "geometry": {"coordinates":[10.9183197021,49.1827735901],"type":"Point"}
}