{
  "type": "Feature",
  "properties": {
    "iso:country":"DE",
    "sg:address":"N\u00f6rdliche Gr\u00fcnauer Str. 61",
    "sg:city":"Neuburg",
    "sg:phone":"+49 8431/49499",
    "sg:postcode":"86633",
    "sg:province":"Bayern",
    "wof:name":"Bva-bergm\u00fcller",
    "wof:placetype":"venue"
},
  "geometry": {"coordinates":[11.224146843,48.7389526367],"type":"Point"}
}