{
  "type": "Feature",
  "properties": {
    "iso:country":"DE",
    "sg:address":"Mendener Str. 26",
    "sg:city":"Wickede",
    "sg:phone":"+49 2377/9260",
    "sg:postcode":"58739",
    "sg:province":"Nordrhein-Westfalen",
    "wof:name":"Kath. \u00d6ffentliche Bibliothek Heilig-geist-kloster",
    "wof:placetype":"venue"
},
  "geometry": {"coordinates":[7.856652,51.480114],"type":"Point"}
}