{
  "type": "Feature",
  "properties": {
    "iso:country":"DE",
    "sg:address":"Im Honigsack 6",
    "sg:city":"Kehl",
    "sg:phone":"+49 7854/7214",
    "sg:postcode":"77694",
    "sg:province":"Baden-W\u00fcrttemberg",
    "wof:name":"Christina Seidler Architektin",
    "wof:placetype":"venue"
},
  "geometry": {"coordinates":[7.826366,48.517479],"type":"Point"}
}