{
  "type": "Feature",
  "properties": {
    "iso:country":"DE",
    "sg:address":"Klosterholzweg 3",
    "sg:city":"Starnberg",
    "sg:phone":"+49 8157/7267",
    "sg:postcode":"82319",
    "sg:province":"Bayern",
    "wof:name":"Bilanz Finanzberatung Gmbh",
    "wof:placetype":"venue"
},
  "geometry": {"coordinates":[11.2466592789,47.9855117798],"type":"Point"}
}