{
  "type": "Feature",
  "properties": {
    "iso:country":"DE",
    "sg:address":"Langgasse 6",
    "sg:city":"Weilburg",
    "sg:phone":"+49 6471/39556",
    "sg:postcode":"35781",
    "sg:province":"Hessen",
    "wof:name":"H. Sieber",
    "wof:placetype":"venue"
},
  "geometry": {"coordinates":[8.259924,50.486675],"type":"Point"}
}