{
  "type": "Feature",
  "properties": {
    "iso:country":"DE",
    "sg:address":"Jacobstr. 11",
    "sg:city":"Sangerhausen",
    "sg:phone":"+49 3464/570034",
    "sg:postcode":"06526",
    "sg:province":"Sachsen-Anhalt",
    "wof:name":"Dr. Hans-w. Langrock Zahnarzt",
    "wof:placetype":"venue"
},
  "geometry": {"coordinates":[11.296474,51.474171],"type":"Point"}
}