{
  "type": "Feature",
  "properties": {
    "iso:country":"DE",
    "sg:address":"Wiesg\u00e4\u00dfchen 37",
    "sg:city":"Langen",
    "sg:phone":"+49 6103/22669",
    "sg:postcode":"63225",
    "sg:province":"Hessen",
    "wof:name":"H. Frank",
    "wof:placetype":"venue"
},
  "geometry": {"coordinates":[8.672185,49.988209],"type":"Point"}
}