{
  "type": "Feature",
  "properties": {
    "iso:country":"DE",
    "sg:address":"Warnenweg 1",
    "sg:city":"Hamburg",
    "sg:phone":"+49 40/5523208",
    "sg:postcode":"22455",
    "sg:province":"Hamburg",
    "wof:name":"Elke Heinrich Patentauswertung",
    "wof:placetype":"venue"
},
  "geometry": {"coordinates":[9.9539327621,53.6466598511],"type":"Point"}
}