{
  "type": "Feature",
  "properties": {
    "iso:country":"DE",
    "sg:address":"Rosa-Luxemburg-Str. 40",
    "sg:city":"Wilkau-Ha\u00dflau",
    "sg:phone":"+49 375/671442",
    "sg:postcode":"08112",
    "sg:province":"Sachsen",
    "wof:name":"Kaden Fertighausvertrieb Inh. Gabriele Kaden",
    "wof:placetype":"venue"
},
  "geometry": {"coordinates":[12.502007,50.672367],"type":"Point"}
}