{
  "type": "Feature",
  "properties": {
    "iso:country":"DE",
    "sg:address":"K\u00fcsthardtstr. 3",
    "sg:city":"Hildesheim",
    "sg:phone":"+49 5121/31616",
    "sg:postcode":"31134",
    "sg:province":"Niedersachsen",
    "wof:name":"Pusteblume",
    "wof:placetype":"venue"
},
  "geometry": {"coordinates":[9.953803,52.149166],"type":"Point"}
}