{
  "type": "Feature",
  "properties": {
    "iso:country":"DE",
    "sg:address":"Pfarrer-Wenke-Weg 15",
    "sg:city":"Berlin",
    "sg:phone":"+49 30",
    "sg:postcode":"12349",
    "sg:province":"Berlin",
    "wof:name":"Haba-\u00e4nderungsschneiderei In Berlin-buckow",
    "wof:placetype":"venue"
},
  "geometry": {"coordinates":[13.421427,52.413876],"type":"Point"}
}