{
  "type": "Feature",
  "properties": {
    "iso:country":"DE",
    "sg:address":"B\u00fcrgerstr. 56",
    "sg:city":"Dortmund",
    "sg:postcode":"44149",
    "sg:province":"Nordrhein-Westfalen",
    "wof:name":"Derwald Globalbau Gmbh & Co. Dortmund Kg",
    "wof:placetype":"venue"
},
  "geometry": {"coordinates":[7.41987,51.513649],"type":"Point"}
}