{
  "type": "Feature",
  "properties": {
    "iso:country":"DE",
    "sg:address":"Schulze-Delitzsch-Str 49",
    "sg:city":"Pforzheim",
    "sg:phone":"+49 7231/23992",
    "sg:postcode":"75173",
    "sg:province":"Baden-W\u00fcrttemberg",
    "wof:name":"Schmuckbehausungen Petra Ohnmacht",
    "wof:placetype":"venue"
},
  "geometry": {"coordinates":[8.6916513443,48.8854866028],"type":"Point"}
}