{
  "type": "Feature",
  "properties": {
    "iso:country":"DE",
    "sg:address":"Am Markt 22",
    "sg:city":"Burg",
    "sg:phone":"+49 4371/3036",
    "sg:postcode":"23769",
    "sg:province":"Schleswig-Holstein",
    "wof:name":"Peter F. Thomsen Inh. Peter Friedr. Butensch\u00f6n",
    "wof:placetype":"venue"
},
  "geometry": {"coordinates":[11.1978330612,54.4386062622],"type":"Point"}
}