{
  "type": "Feature",
  "properties": {
    "iso:country":"DE",
    "sg:address":"Metzgerstr. 1",
    "sg:city":"Ravensburg",
    "sg:phone":"+49 751/25736",
    "sg:postcode":"88212",
    "sg:province":"Baden-W\u00fcrttemberg",
    "wof:name":"Vereinsgastst\u00e4tte Eisenbahner- Sportheim",
    "wof:placetype":"venue"
},
  "geometry": {"coordinates":[9.6077203751,47.7862167358],"type":"Point"}
}