{
  "type": "Feature",
  "properties": {
    "iso:country":"DE",
    "sg:address":"Realschulstr. 17",
    "sg:city":"Gro\u00df-Umstadt",
    "sg:phone":"+49 6078/74400",
    "sg:postcode":"64823",
    "sg:province":"Hessen",
    "wof:name":"Frank D\u00f6rr",
    "wof:placetype":"venue"
},
  "geometry": {"coordinates":[8.9259586334,49.8690795898],"type":"Point"}
}