{
  "type": "Feature",
  "properties": {
    "iso:country":"DE",
    "sg:address":"Storck-Barracks",
    "sg:city":"Illesheim",
    "sg:phone":"+49 9841/68600",
    "sg:postcode":"91471",
    "sg:province":"Bayern",
    "wof:name":"Carlson Wagonlit Travel",
    "wof:placetype":"venue"
},
  "geometry": {"coordinates":[10.3868703842,49.4819984436],"type":"Point"}
}