{
  "type": "Feature",
  "properties": {
    "iso:country":"DE",
    "sg:address":"Hammergasse 9b",
    "sg:city":"Steinbach-Hallenberg",
    "sg:phone":"+49 36847/40591",
    "sg:postcode":"98587",
    "sg:province":"Th\u00fcringen",
    "wof:name":"Margitta Eidam Rechtsanw\u00e4ltin",
    "wof:placetype":"venue"
},
  "geometry": {"coordinates":[10.5695238113,50.6990242004],"type":"Point"}
}