{
  "type": "Feature",
  "properties": {
    "iso:country":"DE",
    "sg:address":"Luitpoldstr. 8",
    "sg:city":"Dinkelsb\u00fchl",
    "sg:phone":"+49 9851/7443",
    "sg:postcode":"91550",
    "sg:province":"Bayern",
    "wof:name":"Roland Hofrichter Steuerberater",
    "wof:placetype":"venue"
},
  "geometry": {"coordinates":[10.3256397247,49.0694313049],"type":"Point"}
}