{
  "type": "Feature",
  "properties": {
    "iso:country":"DE",
    "sg:address":"K\u00fcmperfeld 7",
    "sg:city":"Bergisch Gladbach",
    "sg:phone":"+49 2202/982761",
    "sg:postcode":"51467",
    "sg:province":"Nordrhein-Westfalen",
    "wof:name":"Ralf B\u00fchler Steuerberater",
    "wof:placetype":"venue"
},
  "geometry": {"coordinates":[7.0763077736,51.012752533],"type":"Point"}
}