{
  "type": "Feature",
  "properties": {
    "iso:country":"DE",
    "sg:address":"Porschestr. 10",
    "sg:city":"Bad Salzuflen",
    "sg:postcode":"32107",
    "sg:province":"Nordrhein-Westfalen",
    "wof:name":"Rbk Vertriebs- Und Montage Gmbh",
    "wof:placetype":"venue"
},
  "geometry": {"coordinates":[8.756058,52.046555],"type":"Point"}
}