{
  "type": "Feature",
  "properties": {
    "iso:country":"DE",
    "sg:address":"Matrumer Str. 6",
    "sg:city":"Molbergen",
    "sg:phone":"+49 4475/947100",
    "sg:postcode":"49696",
    "sg:province":"Niedersachsen",
    "wof:name":"Olding & Rolfes",
    "wof:placetype":"venue"
},
  "geometry": {"coordinates":[7.9176659584,52.8507843018],"type":"Point"}
}