{
  "type": "Feature",
  "properties": {
    "iso:country":"DE",
    "sg:address":"Sprungschanzenweg 31",
    "sg:city":"Berlin",
    "sg:phone":"+49 30/8141169",
    "sg:postcode":"14169",
    "sg:province":"Berlin",
    "wof:name":"G\u00fcnter K\u00f6hn Architekt",
    "wof:placetype":"venue"
},
  "geometry": {"coordinates":[13.255322,52.454124],"type":"Point"}
}