{
  "type": "Feature",
  "properties": {
    "iso:country":"DE",
    "sg:address":"Ledebrink 45",
    "sg:city":"L\u00f6hne",
    "sg:phone":"+49 5732/7876",
    "sg:postcode":"32584",
    "sg:province":"Nordrhein-Westfalen",
    "wof:name":"Heinrich Ledebrink",
    "wof:placetype":"venue"
},
  "geometry": {"coordinates":[8.721226,52.229397],"type":"Point"}
}