{
  "type": "Feature",
  "properties": {
    "iso:country":"DE",
    "sg:address":"Hammersbacher Str. 71",
    "sg:city":"Bruchk\u00f6bel",
    "sg:phone":"+49 6181/77778",
    "sg:postcode":"63486",
    "sg:province":"Hessen",
    "wof:name":"Helmut Sch\u00e4fer",
    "wof:placetype":"venue"
},
  "geometry": {"coordinates":[8.92473,50.186069],"type":"Point"}
}