{
  "type": "Feature",
  "properties": {
    "iso:country":"DE",
    "sg:address":"Celler Str. 20",
    "sg:city":"Ebstorf",
    "sg:phone":"+49 5822/5751",
    "sg:postcode":"29574",
    "sg:province":"Niedersachsen",
    "wof:name":"M\u00fcllers-eck",
    "wof:placetype":"venue"
},
  "geometry": {"coordinates":[10.4165048599,53.0287246704],"type":"Point"}
}