{
  "type": "Feature",
  "properties": {
    "iso:country":"DE",
    "sg:address":"Auf der Bleeke 7",
    "sg:city":"Werther",
    "sg:phone":"+49 5203/97130",
    "sg:postcode":"33824",
    "sg:province":"Nordrhein-Westfalen",
    "wof:name":"H\u00e4ger-versicherungsmakler Gmbh",
    "wof:placetype":"venue"
},
  "geometry": {"coordinates":[8.4513950348,52.0966873169],"type":"Point"}
}