{
  "type": "Feature",
  "properties": {
    "iso:country":"DE",
    "sg:address":"Brabandstr. 67",
    "sg:city":"Hamburg",
    "sg:phone":"+49 40/5116803",
    "sg:postcode":"22297",
    "sg:province":"Hamburg",
    "wof:name":"Tetenal Photowerk Gmbh",
    "wof:placetype":"venue"
},
  "geometry": {"coordinates":[10.0135660172,53.6145477295],"type":"Point"}
}