{
  "type": "Feature",
  "properties": {
    "iso:country":"DE",
    "sg:address":"Adolf-Kolping-Str. 36",
    "sg:city":"Solingen",
    "sg:phone":"+49 212/310089",
    "sg:postcode":"42719",
    "sg:province":"Nordrhein-Westfalen",
    "wof:name":"H. H. Schmidt & Co. Gmbh",
    "wof:placetype":"venue"
},
  "geometry": {"coordinates":[7.0322780609,51.1805686951],"type":"Point"}
}