{
  "type": "Feature",
  "properties": {
    "iso:country":"DE",
    "sg:address":"Im Sundernkamp 7",
    "sg:city":"Enger",
    "sg:phone":"+49 5224/98880",
    "sg:postcode":"32130",
    "sg:province":"Nordrhein-Westfalen",
    "wof:name":"Kr\u00e4utica Pharma Gmbh & Co Kg",
    "wof:placetype":"venue"
},
  "geometry": {"coordinates":[8.5548791885,52.1111755371],"type":"Point"}
}