{
  "type": "Feature",
  "properties": {
    "iso:country":"DE",
    "sg:address":"Karlstr. 91",
    "sg:city":"Aachen",
    "sg:phone":"+49 241/553516",
    "sg:postcode":"52080",
    "sg:province":"Nordrhein-Westfalen",
    "wof:name":"Hans Reinartz",
    "wof:placetype":"venue"
},
  "geometry": {"coordinates":[6.1529211998,50.7821655273],"type":"Point"}
}