{
  "type": "Feature",
  "properties": {
    "iso:country":"DE",
    "sg:address":"Dorfstr. 17",
    "sg:city":"Suckow",
    "sg:phone":"+49 38729/20327",
    "sg:postcode":"19376",
    "sg:province":"Mecklenburg-Vorpommern",
    "wof:name":"Reinhold Penning",
    "wof:placetype":"venue"
},
  "geometry": {"coordinates":[11.96655,53.308449],"type":"Point"}
}