{
  "type": "Feature",
  "properties": {
    "iso:country":"DE",
    "sg:address":"Jesuitenweg 5",
    "sg:city":"Alt\u00f6tting",
    "sg:phone":"+49 8671/5667",
    "sg:postcode":"84503",
    "sg:province":"Bayern",
    "wof:name":"Simon Ober",
    "wof:placetype":"venue"
},
  "geometry": {"coordinates":[12.6866064072,48.2280845642],"type":"Point"}
}