{
  "type": "Feature",
  "properties": {
    "iso:country":"DE",
    "sg:address":"Im Wiesental 4",
    "sg:city":"Kirchheim",
    "sg:phone":"+49 6625/1010",
    "sg:postcode":"36275",
    "sg:province":"Hessen",
    "wof:name":"Naumann Gmbh & Co. Kg",
    "wof:placetype":"venue"
},
  "geometry": {"coordinates":[9.5731134415,50.8368148804],"type":"Point"}
}