{
  "type": "Feature",
  "properties": {
    "iso:country":"DE",
    "sg:address":"K\u00fcsterkoppel 15",
    "sg:city":"Brande-H\u00f6rnerkirchen",
    "sg:phone":"+49 4127/97990",
    "sg:postcode":"25364",
    "sg:province":"Schleswig-Holstein",
    "wof:name":"Brigitte Fubel Steuerberaterin",
    "wof:placetype":"venue"
},
  "geometry": {"coordinates":[9.7005329132,53.8565483093],"type":"Point"}
}