{
  "type": "Feature",
  "properties": {
    "iso:country":"DE",
    "sg:address":"An der Lesumer Kirche 14",
    "sg:city":"Bremen",
    "sg:phone":"+49 421/6365962",
    "sg:postcode":"28717",
    "sg:province":"Bremen",
    "wof:name":"Silvia Neumann Drogerie",
    "wof:placetype":"venue"
},
  "geometry": {"coordinates":[8.691363,53.167408],"type":"Point"}
}