{
  "type": "Feature",
  "properties": {
    "iso:country":"DE",
    "sg:address":"Stadtseeallee 35",
    "sg:city":"Stendal",
    "sg:postcode":"39576",
    "sg:province":"Sachsen-Anhalt",
    "wof:name":"B\u00e4dje Korte R\u00f6sch Partnerschaft",
    "wof:placetype":"venue"
},
  "geometry": {"coordinates":[11.846007,52.60215],"type":"Point"}
}