{
  "type": "Feature",
  "properties": {
    "iso:country":"DE",
    "sg:address":"Am Fl\u00fcthedamm 2",
    "sg:city":"Rosdorf",
    "sg:phone":"+49 551/500870",
    "sg:postcode":"37124",
    "sg:province":"Niedersachsen",
    "wof:name":"Ruch",
    "wof:placetype":"venue"
},
  "geometry": {"coordinates":[9.914435,51.509312],"type":"Point"}
}