{
  "type": "Feature",
  "properties": {
    "iso:country":"DE",
    "sg:address":"Kurt-Schumacher-Allee 2",
    "sg:city":"Hamburg",
    "sg:postcode":"20097",
    "sg:province":"Hamburg",
    "wof:name":"Beteiligungsgesellschaft Auto Eins Mbh",
    "wof:placetype":"venue"
},
  "geometry": {"coordinates":[10.018966,53.552486],"type":"Point"}
}