{
  "type": "Feature",
  "properties": {
    "iso:country":"DE",
    "sg:address":"Frauengasse 8",
    "sg:city":"Neu\u00f6tting",
    "sg:postcode":"84524",
    "sg:province":"Bayern",
    "wof:name":"Lei\u00df Gmbh",
    "wof:placetype":"venue"
},
  "geometry": {"coordinates":[12.6879806519,48.2397918701],"type":"Point"}
}