{
  "type": "Feature",
  "properties": {
    "iso:country":"DE",
    "sg:address":"Schopenhauerstr. 29",
    "sg:city":"Potsdam",
    "sg:postcode":"14467",
    "sg:province":"Brandenburg",
    "wof:name":"G. Klemm",
    "wof:placetype":"venue"
},
  "geometry": {"coordinates":[13.048505,52.399391],"type":"Point"}
}