{
  "type": "Feature",
  "properties": {
    "iso:country":"DE",
    "sg:address":"Amtsstr. 13",
    "sg:city":"Moorrege",
    "sg:phone":"+49 4122/81761",
    "sg:postcode":"25436",
    "sg:province":"Schleswig-Holstein",
    "wof:name":"Hans-j\u00fcrgen Rechter Immobilienmakler",
    "wof:placetype":"venue"
},
  "geometry": {"coordinates":[9.6737918854,53.6749763489],"type":"Point"}
}