{
  "type": "Feature",
  "properties": {
    "iso:country":"DE",
    "sg:address":"Karlsbader Str. 39",
    "sg:city":"Gelnhausen",
    "sg:postcode":"63571",
    "sg:province":"Hessen",
    "wof:name":"Dr. Martin Bankmann",
    "wof:placetype":"venue"
},
  "geometry": {"coordinates":[9.167744,50.182503],"type":"Point"}
}