{
  "type": "Feature",
  "properties": {
    "iso:country":"DE",
    "sg:address":"Am Lindenstein 6",
    "sg:city":"Baunatal",
    "sg:postcode":"34225",
    "sg:province":"Hessen",
    "wof:name":"Pev Baufinanz- Vermittlungs Gmbh",
    "wof:placetype":"venue"
},
  "geometry": {"coordinates":[9.4242420197,51.2459068298],"type":"Point"}
}