{
  "type": "Feature",
  "properties": {
    "iso:country":"DE",
    "sg:address":"Salinenstr. 45",
    "sg:city":"Bad Kreuznach",
    "sg:phone":"+49 671/41007",
    "sg:postcode":"55543",
    "sg:province":"Rheinland-Pfalz",
    "wof:name":"Martin Und Petra Uth Rechtsanw\u00e4lte",
    "wof:placetype":"venue"
},
  "geometry": {"coordinates":[7.8587598801,49.8396911621],"type":"Point"}
}