{
  "type": "Feature",
  "properties": {
    "iso:country":"DE",
    "sg:address":"Muldenweg 63",
    "sg:city":"Kitzingen",
    "sg:phone":"+49 9321/13260",
    "sg:postcode":"97318",
    "sg:province":"Bayern",
    "wof:name":"Muschiol Gmbh",
    "wof:placetype":"venue"
},
  "geometry": {"coordinates":[10.1438102722,49.7411651611],"type":"Point"}
}