{
  "type": "Feature",
  "properties": {
    "iso:country":"DE",
    "sg:address":"Postfach 2240",
    "sg:city":"Obertshausen",
    "sg:phone":"+49 6104/702546",
    "sg:postcode":"63171",
    "sg:province":"Hessen",
    "wof:name":"Ymos-metallwerke Wolf & Becker Gmbh & Co.",
    "wof:placetype":"venue"
},
  "geometry": {"coordinates":[8.84683,50.069656],"type":"Point"}
}