{
  "type": "Feature",
  "properties": {
    "iso:country":"DE",
    "sg:address":"Bismarckstr. 8",
    "sg:city":"Koblenz",
    "sg:phone":"+49 261/36033",
    "sg:postcode":"56068",
    "sg:province":"Rheinland-Pfalz",
    "wof:name":"Dr. Manfred Und Dr. Alois Wirtz",
    "wof:placetype":"venue"
},
  "geometry": {"coordinates":[7.598968029,50.3517913818],"type":"Point"}
}