{
  "type": "Feature",
  "properties": {
    "iso:country":"DE",
    "sg:address":"Rentzelstr. 14",
    "sg:city":"Hamburg",
    "sg:phone":"+49 40/4102348",
    "sg:postcode":"20146",
    "sg:province":"Hamburg",
    "wof:name":"Marcel Fugere",
    "wof:placetype":"venue"
},
  "geometry": {"coordinates":[9.9797382355,53.5664901733],"type":"Point"}
}