{
  "type": "Feature",
  "properties": {
    "iso:country":"DE",
    "sg:address":"Ritterstr. 19",
    "sg:city":"Georgensgm\u00fcnd",
    "sg:phone":"+49 9172/1396",
    "sg:postcode":"91166",
    "sg:province":"Bayern",
    "wof:name":"K. Volkert",
    "wof:placetype":"venue"
},
  "geometry": {"coordinates":[11.025223732,49.2211608887],"type":"Point"}
}