{
  "type": "Feature",
  "properties": {
    "iso:country":"DE",
    "sg:address":"Hauptstr. 33",
    "sg:city":"Illingen",
    "sg:phone":"+49 6825/2282",
    "sg:postcode":"66557",
    "sg:province":"Saarland",
    "wof:name":"Johann Resch",
    "wof:placetype":"venue"
},
  "geometry": {"coordinates":[7.0518260002,49.3765983582],"type":"Point"}
}