{
  "type": "Feature",
  "properties": {
    "iso:country":"DE",
    "sg:address":"Schmiedeweg 1",
    "sg:city":"Platten",
    "sg:phone":"+49 6535/890",
    "sg:postcode":"54518",
    "sg:province":"Rheinland-Pfalz",
    "wof:name":"Klaus Basten-m\u00fcller",
    "wof:placetype":"venue"
},
  "geometry": {"coordinates":[6.95431,49.949844],"type":"Point"}
}