{
  "type": "Feature",
  "properties": {
    "iso:country":"DE",
    "sg:address":"R\u00f6merstr. 50",
    "sg:city":"Heidelberg",
    "sg:phone":"+49 6221/25717",
    "sg:postcode":"69115",
    "sg:province":"Baden-W\u00fcrttemberg",
    "wof:name":"Hanna Korthals Krankengymnastin",
    "wof:placetype":"venue"
},
  "geometry": {"coordinates":[8.684656,49.402473],"type":"Point"}
}