{
  "type": "Feature",
  "properties": {
    "iso:country":"DE",
    "sg:address":"Otto-Beck-Str. 32",
    "sg:city":"Bensheim",
    "sg:phone":"+49 6251/71810",
    "sg:postcode":"64625",
    "sg:province":"Hessen",
    "wof:name":"Gastst\u00e4tte Am Bahnhof",
    "wof:placetype":"venue"
},
  "geometry": {"coordinates":[8.613951683,49.7023468018],"type":"Point"}
}