{
  "type": "Feature",
  "properties": {
    "iso:country":"DE",
    "sg:address":"Komotauer Str. 30",
    "sg:city":"F\u00fcrth",
    "sg:phone":"+49 911/759950",
    "sg:postcode":"90766",
    "sg:province":"Bayern",
    "wof:name":"Gemeinn\u00fctzige Wohnungs- Baugesellschaft Mbh",
    "wof:placetype":"venue"
},
  "geometry": {"coordinates":[10.9567928314,49.4805679321],"type":"Point"}
}