{
  "type": "Feature",
  "properties": {
    "iso:country":"DE",
    "sg:address":"Flachsrode 7",
    "sg:city":"H\u00f6velhof",
    "sg:phone":"+49 5257/99916",
    "sg:postcode":"33161",
    "sg:province":"Nordrhein-Westfalen",
    "wof:name":"Dispa Handelsges. Mbh",
    "wof:placetype":"venue"
},
  "geometry": {"coordinates":[8.6645460129,51.81772995],"type":"Point"}
}