{
  "type": "Feature",
  "properties": {
    "iso:country":"DE",
    "sg:address":"Hofstr. 14",
    "sg:city":"Weilheim",
    "sg:phone":"+49 7023/6828",
    "sg:postcode":"73235",
    "sg:province":"Baden-W\u00fcrttemberg",
    "wof:name":"S. Kaiser",
    "wof:placetype":"venue"
},
  "geometry": {"coordinates":[8.24333,47.656708],"type":"Point"}
}