{
  "type": "Feature",
  "properties": {
    "iso:country":"DE",
    "sg:address":"An der Feuerwache 3",
    "sg:city":"Neukirch",
    "sg:phone":"+49 35951/32152",
    "sg:postcode":"01904",
    "sg:province":"Sachsen",
    "wof:name":"Harald F\u00f6rster",
    "wof:placetype":"venue"
},
  "geometry": {"coordinates":[14.312991,51.093594],"type":"Point"}
}