{
  "type": "Feature",
  "properties": {
    "iso:country":"DE",
    "sg:address":"Bierpohlweg 29",
    "sg:city":"Minden",
    "sg:phone":"+49 571/43293",
    "sg:postcode":"32425",
    "sg:province":"Nordrhein-Westfalen",
    "wof:name":"Carl Hummel Schiffseigner",
    "wof:placetype":"venue"
},
  "geometry": {"coordinates":[8.90721,52.304924],"type":"Point"}
}