{
  "type": "Feature",
  "properties": {
    "iso:country":"DE",
    "sg:address":"Pfaffenhofener Str. 1",
    "sg:city":"Hohenwart",
    "sg:phone":"+49 8443/92650",
    "sg:postcode":"86558",
    "sg:province":"Bayern",
    "wof:name":"Michael Fahn",
    "wof:placetype":"venue"
},
  "geometry": {"coordinates":[11.382665,48.593121],"type":"Point"}
}