{
  "type": "Feature",
  "properties": {
    "iso:country":"DE",
    "sg:address":"Adolf-M\u00fcnch-Weg 5",
    "sg:city":"Hachenburg",
    "sg:phone":"+49 2662/3029",
    "sg:postcode":"57627",
    "sg:province":"Rheinland-Pfalz",
    "wof:name":"Extra Bau- Und Hobby Markt Betriebs Gmbh",
    "wof:placetype":"venue"
},
  "geometry": {"coordinates":[7.8135318756,50.6636123657],"type":"Point"}
}