{
  "type": "Feature",
  "properties": {
    "iso:country":"DE",
    "sg:address":"Vinetaplatz 4",
    "sg:city":"Kiel",
    "sg:phone":"+49 431/737489",
    "sg:postcode":"24143",
    "sg:province":"Schleswig-Holstein",
    "wof:name":"Sch\u00f6nefelder Holzspielzeug",
    "wof:placetype":"venue"
},
  "geometry": {"coordinates":[10.1470823288,54.311214447],"type":"Point"}
}