{
  "type": "Feature",
  "properties": {
    "iso:country":"DE",
    "sg:address":"B\u00e4ckerstr. 29",
    "sg:city":"Minden",
    "sg:phone":"+49 571/25261",
    "sg:postcode":"32423",
    "sg:province":"Nordrhein-Westfalen",
    "wof:name":"Esprit Retail Gmbh",
    "wof:placetype":"venue"
},
  "geometry": {"coordinates":[8.91843,52.290195],"type":"Point"}
}