{
  "type": "Feature",
  "properties": {
    "iso:country":"DE",
    "sg:address":"Seestr. 37",
    "sg:city":"Berlin",
    "sg:phone":"+49 30/4537794",
    "sg:postcode":"13353",
    "sg:province":"Berlin",
    "wof:name":"See-tank",
    "wof:placetype":"venue"
},
  "geometry": {"coordinates":[13.3499965668,52.549030304],"type":"Point"}
}