{
  "type": "Feature",
  "properties": {
    "iso:country":"DE",
    "sg:address":"Im Auchtert 27",
    "sg:city":"Kirchheim",
    "sg:phone":"+49 7021/950600",
    "sg:postcode":"73230",
    "sg:province":"Baden-W\u00fcrttemberg",
    "wof:name":"Ebersp\u00e4cher Gmbh",
    "wof:placetype":"venue"
},
  "geometry": {"coordinates":[9.478883,48.615578],"type":"Point"}
}