{
  "type": "Feature",
  "properties": {
    "iso:country":"DE",
    "sg:address":"Goethestr. 3",
    "sg:city":"R\u00f6srath",
    "sg:phone":"+49 2205/1294",
    "sg:postcode":"51503",
    "sg:province":"Nordrhein-Westfalen",
    "wof:name":"L. Breuer",
    "wof:placetype":"venue"
},
  "geometry": {"coordinates":[7.1785879135,50.9015007019],"type":"Point"}
}