{
  "type": "Feature",
  "properties": {
    "iso:country":"DE",
    "sg:address":"R\u00fcben\u00e4cker 1",
    "sg:city":"Trossingen",
    "sg:phone":"+49 7425/6708",
    "sg:postcode":"78647",
    "sg:province":"Baden-W\u00fcrttemberg",
    "wof:name":"Joaquim Gomes Da Silva",
    "wof:placetype":"venue"
},
  "geometry": {"coordinates":[8.6375026703,48.0548362732],"type":"Point"}
}