{
  "type": "Feature",
  "properties": {
    "iso:country":"DE",
    "sg:address":"Sonsbecker Str. 36",
    "sg:city":"Xanten",
    "sg:phone":"+49 2801/884",
    "sg:postcode":"46509",
    "sg:province":"Nordrhein-Westfalen",
    "wof:name":"Metallverarbeitung Kanders & Peters Gmbh",
    "wof:placetype":"venue"
},
  "geometry": {"coordinates":[6.436601162,51.6537742615],"type":"Point"}
}