{
  "type": "Feature",
  "properties": {
    "iso:country":"DE",
    "sg:address":"Henkelstr. 295",
    "sg:city":"D\u00fcsseldorf",
    "sg:postcode":"40599",
    "sg:province":"Nordrhein-Westfalen",
    "wof:name":"Pflegedienst D\u00fcsseldorf S\u00fcd Meyer Von Ameln Gbr",
    "wof:placetype":"venue"
},
  "geometry": {"coordinates":[6.858637,51.179092],"type":"Point"}
}