{
  "type": "Feature",
  "properties": {
    "iso:country":"DE",
    "sg:address":"Kurt-Schumacher-Damm 52-54",
    "sg:city":"Osnabr\u00fcck",
    "sg:phone":"+49 541/48011",
    "sg:postcode":"49078",
    "sg:province":"Niedersachsen",
    "wof:name":"Novo-einkaufszentrum",
    "wof:placetype":"venue"
},
  "geometry": {"coordinates":[8.0168304443,52.2694816589],"type":"Point"}
}