{
  "type": "Feature",
  "properties": {
    "iso:country":"DE",
    "sg:address":"Herrenh\u00fcttener Str. 81",
    "sg:city":"S\u00fcdbrookmerland",
    "sg:phone":"+49 4942/912063",
    "sg:postcode":"26624",
    "sg:province":"Niedersachsen",
    "wof:name":"Janssen Gmbh",
    "wof:placetype":"venue"
},
  "geometry": {"coordinates":[7.386267,53.459953],"type":"Point"}
}