{
  "type": "Feature",
  "properties": {
    "iso:country":"DE",
    "sg:address":"Gildenstr. 2 a",
    "sg:city":"M\u00fcnster",
    "sg:postcode":"48157",
    "sg:province":"Nordrhein-Westfalen",
    "wof:name":"Vpu Verbund Partner Unternehmensberatungs Gmbh",
    "wof:placetype":"venue"
},
  "geometry": {"coordinates":[7.7078948021,51.9797096252],"type":"Point"}
}