{
  "type": "Feature",
  "properties": {
    "iso:country":"DE",
    "sg:address":"Nadlerstr. 20",
    "sg:city":"Stuttgart",
    "sg:phone":"+49 711/241918",
    "sg:postcode":"70173",
    "sg:province":"Baden-W\u00fcrttemberg",
    "wof:name":"Cleopatra",
    "wof:placetype":"venue"
},
  "geometry": {"coordinates":[9.177926,48.773884],"type":"Point"}
}