{
  "type": "Feature",
  "properties": {
    "iso:country":"DE",
    "sg:address":"Heckenweg 11",
    "sg:city":"Wei\u00dfensberg",
    "sg:phone":"+49 8389/1736",
    "sg:postcode":"88138",
    "sg:province":"Bayern",
    "wof:name":"Solveig Sch\u00f6nebeck Heilpraktikerin",
    "wof:placetype":"venue"
},
  "geometry": {"coordinates":[9.715010643,47.5830039978],"type":"Point"}
}