{
  "type": "Feature",
  "properties": {
    "iso:country":"DE",
    "sg:address":"Sandstr. 2",
    "sg:city":"Krefeld",
    "sg:phone":"+49 2841/61511",
    "sg:postcode":"47802",
    "sg:province":"Nordrhein-Westfalen",
    "wof:name":"Rolf Reifenschneider",
    "wof:placetype":"venue"
},
  "geometry": {"coordinates":[6.6260809898,51.3902435303],"type":"Point"}
}