{
  "type": "Feature",
  "properties": {
    "iso:country":"DE",
    "sg:address":"Wiesenweg 3",
    "sg:city":"Margetsh\u00f6chheim",
    "sg:phone":"+49 931/464334",
    "sg:postcode":"97276",
    "sg:province":"Bayern",
    "wof:name":"Ladyfit-studio",
    "wof:placetype":"venue"
},
  "geometry": {"coordinates":[9.8660926819,49.8277816772],"type":"Point"}
}