{
  "type": "Feature",
  "properties": {
    "iso:country":"DE",
    "sg:address":"Raiffeisenstr. 7",
    "sg:city":"Pleidelsheim",
    "sg:phone":"+49 7144/29474",
    "sg:postcode":"74385",
    "sg:province":"Baden-W\u00fcrttemberg",
    "wof:name":"Pewa Flachdachbau Gmbh",
    "wof:placetype":"venue"
},
  "geometry": {"coordinates":[9.197859,48.949982],"type":"Point"}
}