{
  "type": "Feature",
  "properties": {
    "iso:country":"DE",
    "sg:address":"Boschstr. 14",
    "sg:city":"Wiernsheim",
    "sg:phone":"+49 7044/96160",
    "sg:postcode":"75446",
    "sg:province":"Baden-W\u00fcrttemberg",
    "wof:name":"Gerlinde Jahn",
    "wof:placetype":"venue"
},
  "geometry": {"coordinates":[8.844679,48.891228],"type":"Point"}
}