{
  "type": "Feature",
  "properties": {
    "iso:country":"DE",
    "sg:address":"Mozartstr. 15",
    "sg:city":"Obrigheim",
    "sg:phone":"+49 6359/840400",
    "sg:postcode":"67283",
    "sg:province":"Rheinland-Pfalz",
    "wof:name":"Ambulanter Pflegedienst Christel Werle",
    "wof:placetype":"venue"
},
  "geometry": {"coordinates":[8.201809,49.591221],"type":"Point"}
}