{
  "type": "Feature",
  "properties": {
    "iso:country":"DE",
    "sg:address":"Marktstr. 1",
    "sg:city":"Titting",
    "sg:phone":"+49 8423/629",
    "sg:postcode":"85135",
    "sg:province":"Bayern",
    "wof:name":"Dittenhofer Gmbh",
    "wof:placetype":"venue"
},
  "geometry": {"coordinates":[11.210596,48.996143],"type":"Point"}
}