{
  "type": "Feature",
  "properties": {
    "iso:country":"DE",
    "sg:address":"Wiesestr. 68",
    "sg:city":"Gera",
    "sg:phone":"+49 365/31227",
    "sg:postcode":"07548",
    "sg:province":"Th\u00fcringen",
    "wof:name":"Aida Friseur Kosmetik Und Sch\u00f6nheitspflege Gmbh",
    "wof:placetype":"venue"
},
  "geometry": {"coordinates":[12.0726270676,50.8655357361],"type":"Point"}
}