{
  "type": "Feature",
  "properties": {
    "iso:country":"DE",
    "sg:address":"Br\u00fcckenplatz 1",
    "sg:city":"Ro\u00dfwein",
    "sg:phone":"+49 34322/42507",
    "sg:postcode":"04741",
    "sg:province":"Sachsen",
    "wof:name":"Fleisch- Und Wurstwaren Gmbh",
    "wof:placetype":"venue"
},
  "geometry": {"coordinates":[13.1820201874,51.0629463196],"type":"Point"}
}