{
  "type": "Feature",
  "properties": {
    "iso:country":"DE",
    "sg:address":"Albrechtstr. 34",
    "sg:city":"Berlin",
    "sg:phone":"+49 30/7908810",
    "sg:postcode":"12167",
    "sg:province":"Berlin",
    "wof:name":"Wisotzki & Gaida Bauingenieurgesellschaft Mbh",
    "wof:placetype":"venue"
},
  "geometry": {"coordinates":[13.332532,52.452332],"type":"Point"}
}