{
  "type": "Feature",
  "properties": {
    "iso:country":"DE",
    "sg:address":"Georgstr. 14",
    "sg:city":"Hannover",
    "sg:phone":"+49 511/306508",
    "sg:postcode":"30159",
    "sg:province":"Niedersachsen",
    "wof:name":"Foot Locker Germany Gmbh",
    "wof:placetype":"venue"
},
  "geometry": {"coordinates":[9.736089,52.374905],"type":"Point"}
}