{
  "type": "Feature",
  "properties": {
    "iso:country":"DE",
    "sg:address":"Hauptstr. 36",
    "sg:city":"Warburg",
    "sg:phone":"+49 5641/4785",
    "sg:postcode":"34414",
    "sg:province":"Nordrhein-Westfalen",
    "wof:name":"Reiseb\u00fcro Simon Gmbh",
    "wof:placetype":"venue"
},
  "geometry": {"coordinates":[9.1504983902,51.4885025024],"type":"Point"}
}