{
  "type": "Feature",
  "properties": {
    "iso:country":"DE",
    "sg:address":"Seestr. 45",
    "sg:city":"K\u00f6nigseggwald",
    "sg:phone":"+49 7587/680",
    "sg:postcode":"88376",
    "sg:province":"Baden-W\u00fcrttemberg",
    "wof:name":"Paul Uhl",
    "wof:placetype":"venue"
},
  "geometry": {"coordinates":[9.42592,47.929031],"type":"Point"}
}