{
  "type": "Feature",
  "properties": {
    "iso:country":"DE",
    "sg:address":"Bogenstr. 42",
    "sg:city":"Aachen",
    "sg:phone":"+49 241/161734",
    "sg:postcode":"52080",
    "sg:province":"Nordrhein-Westfalen",
    "wof:name":"Ismini Stefanidis",
    "wof:placetype":"venue"
},
  "geometry": {"coordinates":[6.129252,50.799458],"type":"Point"}
}