{
  "type": "Feature",
  "properties": {
    "iso:country":"DE",
    "sg:address":"Hohenstaufenring 28",
    "sg:city":"Koeln",
    "sg:phone":"+49 221/92424340",
    "sg:postcode":"50674",
    "sg:province":"Nordrhein-Westfalen",
    "wof:name":"Praxis Dr. Andersson",
    "wof:placetype":"venue"
},
  "geometry": {"coordinates":[6.941207,50.931202],"type":"Point"}
}