{
  "type": "Feature",
  "properties": {
    "iso:country":"DE",
    "sg:address":"Alter Schulweg 4",
    "sg:city":"Papendorf",
    "sg:phone":"+49 381/405390",
    "sg:postcode":"18059",
    "sg:province":"Mecklenburg-Vorpommern",
    "wof:name":"J\u00fcrgen Tesche Gmbh",
    "wof:placetype":"venue"
},
  "geometry": {"coordinates":[12.133377,54.034813],"type":"Point"}
}