{
  "type": "Feature",
  "properties": {
    "iso:country":"DE",
    "sg:address":"Borntalstr. 54",
    "sg:city":"Stadtlengsfeld",
    "sg:phone":"+49 36965/61506",
    "sg:postcode":"36457",
    "sg:province":"Th\u00fcringen",
    "wof:name":"G. Gerstberger",
    "wof:placetype":"venue"
},
  "geometry": {"coordinates":[10.1239595413,50.7779693604],"type":"Point"}
}