{
  "type": "Feature",
  "properties": {
    "iso:country":"DE",
    "sg:address":"Schnellengasse 17",
    "sg:city":"Eschweiler",
    "sg:phone":"+49 2403/37415",
    "sg:postcode":"52249",
    "sg:province":"Nordrhein-Westfalen",
    "wof:name":"Jever-deel",
    "wof:placetype":"venue"
},
  "geometry": {"coordinates":[6.2695550919,50.8200111389],"type":"Point"}
}