{
  "type": "Feature",
  "properties": {
    "iso:country":"DE",
    "sg:address":"Schlernweg 12",
    "sg:city":"Friedberg",
    "sg:phone":"+49 821",
    "sg:postcode":"86316",
    "sg:province":"Bayern",
    "wof:name":"Fabrics * Fashion * Fantasy ** Iris Fiala **",
    "wof:placetype":"venue"
},
  "geometry": {"coordinates":[10.9950504303,48.3645973206],"type":"Point"}
}