{
  "type": "Feature",
  "properties": {
    "iso:country":"DE",
    "sg:address":"M\u00f6hnestr. 79",
    "sg:city":"Warstein",
    "sg:phone":"+49 2925/2939",
    "sg:postcode":"59581",
    "sg:province":"Nordrhein-Westfalen",
    "wof:name":"Herbold & J\u00e4ger",
    "wof:placetype":"venue"
},
  "geometry": {"coordinates":[8.2615766525,51.4859008789],"type":"Point"}
}