{
  "type": "Feature",
  "properties": {
    "iso:country":"DE",
    "sg:address":"Hauptstr. 106",
    "sg:city":"Quierschied",
    "sg:phone":"+49 6825/5811",
    "sg:postcode":"66287",
    "sg:province":"Saarland",
    "wof:name":"Alt Poschd",
    "wof:placetype":"venue"
},
  "geometry": {"coordinates":[7.0348558426,49.345905304],"type":"Point"}
}