{
  "type": "Feature",
  "properties": {
    "iso:country":"DE",
    "sg:address":"L\u00e4ngenholz 3",
    "sg:city":"Herrenberg",
    "sg:phone":"+49 7032/22319",
    "sg:postcode":"71083",
    "sg:province":"Baden-W\u00fcrttemberg",
    "wof:name":"Hallenbad Herrenberg",
    "wof:placetype":"venue"
},
  "geometry": {"coordinates":[8.8758401871,48.5900382996],"type":"Point"}
}