{
  "type": "Feature",
  "properties": {
    "iso:country":"DE",
    "sg:address":"Wormbacher Str. 1",
    "sg:city":"Schmallenberg",
    "sg:phone":"+49 2972/48054",
    "sg:postcode":"57392",
    "sg:province":"Nordrhein-Westfalen",
    "wof:name":"Staatl. Aufbaugymnasium Mit Internat",
    "wof:placetype":"venue"
},
  "geometry": {"coordinates":[8.2372694016,51.1663513184],"type":"Point"}
}