{
  "type": "Feature",
  "properties": {
    "iso:country":"DE",
    "sg:address":"K\u00f6lnische Str. 49",
    "sg:city":"Kassel",
    "sg:phone":"+49 561/103343",
    "sg:postcode":"34117",
    "sg:province":"Hessen",
    "wof:name":"Dr. Wilhelm Windeknecht Rechtsanwalt Und Notar",
    "wof:placetype":"venue"
},
  "geometry": {"coordinates":[9.4873714447,51.3166236877],"type":"Point"}
}