{
  "type": "Feature",
  "properties": {
    "iso:country":"DE",
    "sg:address":"Schmedenstedter Str. 36",
    "sg:city":"Peine",
    "sg:phone":"+49 5171/82617",
    "sg:postcode":"31226",
    "sg:province":"Niedersachsen",
    "wof:name":"Restaurant Zum Alten Krug",
    "wof:placetype":"venue"
},
  "geometry": {"coordinates":[10.2629299164,52.2983093262],"type":"Point"}
}