{
  "type": "Feature",
  "properties": {
    "iso:country":"DE",
    "sg:address":"Apfelstr. 13",
    "sg:city":"Steinhagen",
    "sg:phone":"+49 5204/5712",
    "sg:postcode":"33803",
    "sg:province":"Nordrhein-Westfalen",
    "wof:name":"Maxpax-automaten G\u00fcnter Ottensmann",
    "wof:placetype":"venue"
},
  "geometry": {"coordinates":[8.432166,52.017124],"type":"Point"}
}