{
  "type": "Feature",
  "properties": {
    "iso:country":"DE",
    "sg:address":"Rotthof 94",
    "sg:city":"Neuhaus",
    "sg:phone":"+49 8503/1594",
    "sg:postcode":"94152",
    "sg:province":"Bayern",
    "wof:name":"Eichinger & Drexler Ohg Bauschreinerei",
    "wof:placetype":"venue"
},
  "geometry": {"coordinates":[13.408786,48.484169],"type":"Point"}
}