{
  "type": "Feature",
  "properties": {
    "iso:country":"DE",
    "sg:address":"Auleiten 21",
    "sg:city":"Finsing",
    "sg:phone":"+49 8121/3772",
    "sg:postcode":"85464",
    "sg:province":"Bayern",
    "wof:name":"Georg Henner",
    "wof:placetype":"venue"
},
  "geometry": {"coordinates":[11.824625,48.216011],"type":"Point"}
}