{
  "type": "Feature",
  "properties": {
    "iso:country":"DE",
    "sg:address":"Overweg 22",
    "sg:city":"Soest",
    "sg:phone":"+49 2921/96540",
    "sg:postcode":"59494",
    "sg:province":"Nordrhein-Westfalen",
    "wof:name":"Otto Th. Menke Gmbh",
    "wof:placetype":"venue"
},
  "geometry": {"coordinates":[8.1491613388,51.5550270081],"type":"Point"}
}