{
  "type": "Feature",
  "properties": {
    "iso:country":"DE",
    "sg:address":"Hauptstr. 38",
    "sg:city":"Saterland",
    "sg:phone":"+49 4492/1209",
    "sg:postcode":"26683",
    "sg:province":"Niedersachsen",
    "wof:name":"U. Otten",
    "wof:placetype":"venue"
},
  "geometry": {"coordinates":[7.73383,53.049881],"type":"Point"}
}