{
  "type": "Feature",
  "properties": {
    "iso:country":"DE",
    "sg:address":"Kilianstr. 9",
    "sg:city":"Bad Kreuznach",
    "sg:phone":"+49 671/990",
    "sg:postcode":"55543",
    "sg:province":"Rheinland-Pfalz",
    "wof:name":"Hallenbad Badgesellschaft Mbh",
    "wof:placetype":"venue"
},
  "geometry": {"coordinates":[7.8619651794,49.8460578918],"type":"Point"}
}