{
  "type": "Feature",
  "properties": {
    "iso:country":"DE",
    "sg:address":"Nerotalstr. 4",
    "sg:city":"Mainz",
    "sg:phone":"+49 6131/941411",
    "sg:postcode":"55124",
    "sg:province":"Rheinland-Pfalz",
    "wof:name":"Dr. J\u00fcrgen Braun",
    "wof:placetype":"venue"
},
  "geometry": {"coordinates":[8.2099933624,50.0032310486],"type":"Point"}
}