{
  "type": "Feature",
  "properties": {
    "iso:country":"DE",
    "sg:address":"Schr\u00f6tting 1",
    "sg:city":"Michelsneukirchen",
    "sg:phone":"+49 9467/253",
    "sg:postcode":"93185",
    "sg:province":"Bayern",
    "wof:name":"Schr\u00f6ttinger Br\u00e4u Wolfgang Krottenthaler E. K.",
    "wof:placetype":"venue"
},
  "geometry": {"coordinates":[12.535615,49.132236],"type":"Point"}
}