{
  "type": "Feature",
  "properties": {
    "iso:country":"DE",
    "sg:address":"Hirschstr. 1",
    "sg:city":"Baden-Baden",
    "sg:phone":"+49 7221/31511",
    "sg:postcode":"76530",
    "sg:province":"Baden-W\u00fcrttemberg",
    "wof:name":"Klaus Hasenfratz Masseur",
    "wof:placetype":"venue"
},
  "geometry": {"coordinates":[8.238444,48.763199],"type":"Point"}
}