{
  "type": "Feature",
  "properties": {
    "iso:country":"DE",
    "sg:address":"Preetzer Str. 32 b",
    "sg:city":"Kiel",
    "sg:phone":"+49 431/76355",
    "sg:postcode":"24143",
    "sg:province":"Schleswig-Holstein",
    "wof:name":"Cantica A. Schenk",
    "wof:placetype":"venue"
},
  "geometry": {"coordinates":[10.1457548141,54.3067436218],"type":"Point"}
}