{
  "type": "Feature",
  "properties": {
    "iso:country":"DE",
    "sg:address":"Goethestr. 5",
    "sg:city":"Neu-Ulm",
    "sg:phone":"+49 731/79280",
    "sg:postcode":"89231",
    "sg:province":"Bayern",
    "wof:name":"Kath. Pfarramt St. Albert",
    "wof:placetype":"venue"
},
  "geometry": {"coordinates":[10.0205841064,48.4009742737],"type":"Point"}
}