{
  "type": "Feature",
  "properties": {
    "iso:country":"DE",
    "sg:address":"Hauptstr. 21",
    "sg:city":"Ruppertsweiler",
    "sg:phone":"+49 6395/8700",
    "sg:postcode":"66957",
    "sg:province":"Rheinland-Pfalz",
    "wof:name":"Iduna Versicherung, Handwerk, Handel Und Gewerbe",
    "wof:placetype":"venue"
},
  "geometry": {"coordinates":[7.6894497871,49.1970710754],"type":"Point"}
}