{
  "type": "Feature",
  "properties": {
    "iso:country":"DE",
    "sg:address":"Johannesstr. 26",
    "sg:city":"Schwerin",
    "sg:phone":"+49 385/733215",
    "sg:postcode":"19053",
    "sg:province":"Mecklenburg-Vorpommern",
    "wof:name":"Gerd Guckel Fernmeldearbeiten Scherin -",
    "wof:placetype":"venue"
},
  "geometry": {"coordinates":[11.4051866531,53.6304206848],"type":"Point"}
}