{
  "type": "Feature",
  "properties": {
    "iso:country":"DE",
    "sg:address":"Wesselswerth 26",
    "sg:city":"Essen",
    "sg:phone":"+49 201/491477",
    "sg:postcode":"45239",
    "sg:province":"Nordrhein-Westfalen",
    "wof:name":"Herbert Veltmann Rechtsanwalt Und Notar",
    "wof:placetype":"venue"
},
  "geometry": {"coordinates":[7.0018172264,51.3850593567],"type":"Point"}
}