{
  "type": "Feature",
  "properties": {
    "iso:country":"DE",
    "sg:address":"Schillerstra\u00dfe",
    "sg:city":"Halle",
    "sg:postcode":"06114",
    "sg:province":"Sachsen-Anhalt",
    "wof:name":"Reifenservice Joachim Fuhrmann",
    "wof:placetype":"venue"
},
  "geometry": {"coordinates":[11.979855,51.49398],"type":"Point"}
}