{
  "type": "Feature",
  "properties": {
    "iso:country":"DE",
    "sg:address":"Dielenstr. 18",
    "sg:city":"Stolzenau",
    "sg:phone":"+49 5761/2841",
    "sg:postcode":"31592",
    "sg:province":"Niedersachsen",
    "wof:name":"R. Rorijs",
    "wof:placetype":"venue"
},
  "geometry": {"coordinates":[9.068513,52.514126],"type":"Point"}
}