{
  "type": "Feature",
  "properties": {
    "iso:country":"DE",
    "sg:address":"Schelmkapper Str. 6",
    "sg:city":"L\u00f6ningen",
    "sg:phone":"+49 5434/2759",
    "sg:postcode":"49624",
    "sg:province":"Niedersachsen",
    "wof:name":"Karl-heinz Wichmann",
    "wof:placetype":"venue"
},
  "geometry": {"coordinates":[7.8575592041,52.7284507751],"type":"Point"}
}