{
  "type": "Feature",
  "properties": {
    "iso:country":"DE",
    "sg:address":"Scharnhorststr. 121",
    "sg:city":"M\u00fcnster",
    "sg:postcode":"48151",
    "sg:province":"Nordrhein-Westfalen",
    "wof:name":"Institut F\u00fcr P\u00e4dagogik",
    "wof:placetype":"venue"
},
  "geometry": {"coordinates":[7.606883049,51.9495925903],"type":"Point"}
}