{
  "type": "Feature",
  "properties": {
    "iso:country":"DE",
    "sg:address":"Markt 2",
    "sg:city":"Barth",
    "sg:phone":"+49 38231/2573",
    "sg:postcode":"18356",
    "sg:province":"Mecklenburg-Vorpommern",
    "wof:name":"Donnerwetter Pub",
    "wof:placetype":"venue"
},
  "geometry": {"coordinates":[12.72585392,54.368686676],"type":"Point"}
}