{
  "type": "Feature",
  "properties": {
    "iso:country":"DE",
    "sg:address":"Hofstr. 14",
    "sg:city":"Steinheim",
    "sg:phone":"+49 7144/36427",
    "sg:postcode":"71711",
    "sg:province":"Baden-W\u00fcrttemberg",
    "wof:name":"Friedrich Wagner",
    "wof:placetype":"venue"
},
  "geometry": {"coordinates":[9.259047,48.961868],"type":"Point"}
}