{
  "type": "Feature",
  "properties": {
    "iso:country":"DE",
    "sg:address":"Trubachweg 26",
    "sg:city":"N\u00fcrnberg",
    "sg:phone":"+49 179 5884444",
    "sg:postcode":"90449",
    "sg:province":"Bayern",
    "wof:name":"Omega Systems Store",
    "wof:placetype":"venue"
},
  "geometry": {"coordinates":[11.010629,49.429913],"type":"Point"}
}