{
  "type": "Feature",
  "properties": {
    "iso:country":"DE",
    "sg:address":"Weinmarkt 3",
    "sg:city":"N\u00fcrnberg",
    "sg:phone":"+49 911/225131",
    "sg:postcode":"90403",
    "sg:province":"Bayern",
    "wof:name":"Restaurant Essigbr\u00e4tlein",
    "wof:placetype":"venue"
},
  "geometry": {"coordinates":[11.0747213364,49.4551849365],"type":"Point"}
}