{
  "type": "Feature",
  "properties": {
    "iso:country":"DE",
    "sg:address":"Hohlgasse 2",
    "sg:city":"Abtsgm\u00fcnd",
    "sg:phone":"+49 7975/95750",
    "sg:postcode":"73453",
    "sg:province":"Baden-W\u00fcrttemberg",
    "wof:name":"W\u00fcrttembergische Versicherung Klaus H\u00e4gele",
    "wof:placetype":"venue"
},
  "geometry": {"coordinates":[9.8917627335,48.9180831909],"type":"Point"}
}