{
  "type": "Feature",
  "properties": {
    "iso:country":"DE",
    "sg:address":"Dorfstr. 33",
    "sg:city":"Werther",
    "sg:phone":"+49 3631/603438",
    "sg:postcode":"99735",
    "sg:province":"Th\u00fcringen",
    "wof:name":"Udo K\u00fcrbis",
    "wof:placetype":"venue"
},
  "geometry": {"coordinates":[10.7500400543,51.4671287537],"type":"Point"}
}