{
  "type": "Feature",
  "properties": {
    "iso:country":"DE",
    "sg:address":"Amselweg 1",
    "sg:city":"W\u00f6rth",
    "sg:phone":"+49 8702/1781",
    "sg:postcode":"84109",
    "sg:province":"Bayern",
    "wof:name":"Schmidt Druck",
    "wof:placetype":"venue"
},
  "geometry": {"coordinates":[12.332359314,48.6224327087],"type":"Point"}
}