{
  "type": "Feature",
  "properties": {
    "iso:country":"DE",
    "sg:address":"Dahlemstr. 11",
    "sg:city":"Aschaffenburg",
    "sg:phone":"+49 6021/47714",
    "sg:postcode":"63741",
    "sg:province":"Bayern",
    "wof:name":"Shm Schweiss-handel- Maschinen Gmbh",
    "wof:placetype":"venue"
},
  "geometry": {"coordinates":[9.141982,49.989105],"type":"Point"}
}