{
  "type": "Feature",
  "properties": {
    "iso:country":"DE",
    "sg:address":"Wilhelmstr. 48",
    "sg:city":"Dortmund",
    "sg:phone":"+49 231/149107",
    "sg:postcode":"44137",
    "sg:province":"Nordrhein-Westfalen",
    "wof:name":"Pizzeria Piccola Roma",
    "wof:placetype":"venue"
},
  "geometry": {"coordinates":[7.4544620514,51.5108528137],"type":"Point"}
}