{
  "type": "Feature",
  "properties": {
    "iso:country":"DE",
    "sg:address":"Urspringer Str. 4",
    "sg:city":"Steinfeld",
    "sg:phone":"+49 9359/232",
    "sg:postcode":"97854",
    "sg:province":"Bayern",
    "wof:name":"A. Loschert",
    "wof:placetype":"venue"
},
  "geometry": {"coordinates":[9.6691179276,49.9509544373],"type":"Point"}
}