{
  "type": "Feature",
  "properties": {
    "iso:country":"DE",
    "sg:address":"Mauerstr. 58",
    "sg:city":"D\u00fcsseldorf",
    "sg:postcode":"40476",
    "sg:province":"Nordrhein-Westfalen",
    "wof:name":"Fleischhandel Lugara Gmbh",
    "wof:placetype":"venue"
},
  "geometry": {"coordinates":[6.7764081955,51.245010376],"type":"Point"}
}