{
  "type": "Feature",
  "properties": {
    "iso:country":"DE",
    "sg:address":"Windsberger Str. 24",
    "sg:city":"Pirmasens",
    "sg:phone":"+49 4963/3165100",
    "sg:postcode":"66954",
    "sg:province":"Rheinland-Pfalz",
    "wof:name":"Roos & Co. Sohlenfabrikation Gmbh",
    "wof:placetype":"venue"
},
  "geometry": {"coordinates":[7.563242,49.199463],"type":"Point"}
}