{
  "type": "Feature",
  "properties": {
    "iso:country":"DE",
    "sg:address":"Walter-Kolb-Str. 17",
    "sg:city":"Langenfeld",
    "sg:phone":"+49 2173/978946",
    "sg:postcode":"40764",
    "sg:province":"Nordrhein-Westfalen",
    "wof:name":"Olaf Werner Ingenieur",
    "wof:placetype":"venue"
},
  "geometry": {"coordinates":[6.9440951347,51.1205558777],"type":"Point"}
}