{
  "type": "Feature",
  "properties": {
    "iso:country":"DE",
    "sg:address":"Matthias-Gr\u00fcnewald-Ring 22",
    "sg:city":"Schweinfurt",
    "sg:postcode":"97422",
    "sg:province":"Bayern",
    "wof:name":"Siegfried Wei\u00df Gmbh",
    "wof:placetype":"venue"
},
  "geometry": {"coordinates":[10.2296514511,50.0675811768],"type":"Point"}
}