{
  "type": "Feature",
  "properties": {
    "iso:country":"DE",
    "sg:address":"Essener Str. 16",
    "sg:city":"Hattingen",
    "sg:phone":"+49 2324/41267",
    "sg:postcode":"45529",
    "sg:province":"Nordrhein-Westfalen",
    "wof:name":"Hubert Battling E. K.",
    "wof:placetype":"venue"
},
  "geometry": {"coordinates":[7.1376409531,51.4049186707],"type":"Point"}
}