{
  "type": "Feature",
  "properties": {
    "iso:country":"DE",
    "sg:address":"Wilhelmstr. 54",
    "sg:city":"Menden",
    "sg:phone":"+49 2373/2729",
    "sg:postcode":"58706",
    "sg:province":"Nordrhein-Westfalen",
    "wof:name":"Bruno Kipper",
    "wof:placetype":"venue"
},
  "geometry": {"coordinates":[7.79886,51.43644],"type":"Point"}
}