{
  "type": "Feature",
  "properties": {
    "iso:country":"DE",
    "sg:address":"Hagenstr. 35",
    "sg:city":"Bayreuth",
    "sg:phone":"+49 921/13693",
    "sg:postcode":"95448",
    "sg:province":"Bayern",
    "wof:name":"C. St\u00fcbinger",
    "wof:placetype":"venue"
},
  "geometry": {"coordinates":[11.583702,49.954826],"type":"Point"}
}