{
  "type": "Feature",
  "properties": {
    "iso:country":"DE",
    "sg:address":"Hauptstr. 58",
    "sg:city":"Wadgassen",
    "sg:phone":"+49 6834/69161",
    "sg:postcode":"66787",
    "sg:province":"Saarland",
    "wof:name":"Bayard & Zimmer Gmbh",
    "wof:placetype":"venue"
},
  "geometry": {"coordinates":[6.774548,49.243076],"type":"Point"}
}