{
  "type": "Feature",
  "properties": {
    "iso:country":"DE",
    "sg:address":"Rottkamp 5",
    "sg:city":"Herzebrock-Clarholz",
    "sg:phone":"+49 5245/5066",
    "sg:postcode":"33442",
    "sg:province":"Nordrhein-Westfalen",
    "wof:name":"Thomas Nienaber",
    "wof:placetype":"venue"
},
  "geometry": {"coordinates":[8.174011,51.928829],"type":"Point"}
}