{
  "type": "Feature",
  "properties": {
    "iso:country":"DE",
    "sg:address":"Elsterwerdaer Str. 36",
    "sg:city":"Dresden",
    "sg:postcode":"01239",
    "sg:province":"Sachsen",
    "wof:name":"M. Trakel",
    "wof:placetype":"venue"
},
  "geometry": {"coordinates":[13.801723,51.003254],"type":"Point"}
}