{
  "type": "Feature",
  "properties": {
    "iso:country":"DE",
    "sg:address":"Worthstr. 10",
    "sg:city":"B\u00fctzer",
    "sg:phone":"+49 3386/210332",
    "sg:postcode":"14715",
    "sg:province":"Brandenburg",
    "wof:name":"Wolfgang Klee",
    "wof:placetype":"venue"
},
  "geometry": {"coordinates":[12.301618576,52.5364952087],"type":"Point"}
}