{
  "type": "Feature",
  "properties": {
    "iso:country":"DE",
    "sg:address":"Loxstedter Str. 21",
    "sg:city":"Schwaan",
    "sg:phone":"+49 3844/813994",
    "sg:postcode":"18258",
    "sg:province":"Mecklenburg-Vorpommern",
    "wof:name":"C. Peters",
    "wof:placetype":"venue"
},
  "geometry": {"coordinates":[12.1123123169,53.9395065308],"type":"Point"}
}