{
  "type": "Feature",
  "properties": {
    "iso:country":"DE",
    "sg:address":"Leverner Str. 27",
    "sg:city":"Preu\u00dfisch Oldendorf",
    "sg:phone":"+49 5742/921228",
    "sg:postcode":"32361",
    "sg:province":"Nordrhein-Westfalen",
    "wof:name":"A. Schiegnitz",
    "wof:placetype":"venue"
},
  "geometry": {"coordinates":[8.4564218521,52.3513221741],"type":"Point"}
}