{
  "type": "Feature",
  "properties": {
    "iso:country":"DE",
    "sg:address":"H\u00f6lleweg 10",
    "sg:city":"G\u00f6ttingen",
    "sg:postcode":"37077",
    "sg:province":"Niedersachsen",
    "wof:name":"Areal Konzept Immobilien- Bautr\u00e4ger Gmbh",
    "wof:placetype":"venue"
},
  "geometry": {"coordinates":[9.983585,51.56086],"type":"Point"}
}