{
  "type": "Feature",
  "properties": {
    "iso:country":"DE",
    "sg:address":"Auricher Str. 41",
    "sg:city":"Esens",
    "sg:phone":"+49 4971/1579",
    "sg:postcode":"26427",
    "sg:province":"Niedersachsen",
    "wof:name":"Georg Schoolmann",
    "wof:placetype":"venue"
},
  "geometry": {"coordinates":[7.6137537956,53.6318588257],"type":"Point"}
}