{
  "type": "Feature",
  "properties": {
    "iso:country":"DE",
    "sg:address":"G\u00e4rtnerstr. 11",
    "sg:city":"Papenburg",
    "sg:phone":"+49 4961/75196",
    "sg:postcode":"26871",
    "sg:province":"Niedersachsen",
    "wof:name":"Ewald Brelage",
    "wof:placetype":"venue"
},
  "geometry": {"coordinates":[7.39553,53.048191],"type":"Point"}
}