{
  "type": "Feature",
  "properties": {
    "iso:country":"DE",
    "sg:address":"Grenzenm\u00fchlenweg 1",
    "sg:city":"Wittighausen",
    "sg:phone":"+49 9347/261",
    "sg:postcode":"97957",
    "sg:province":"Baden-W\u00fcrttemberg",
    "wof:name":"Helmut Pfitzner",
    "wof:placetype":"venue"
},
  "geometry": {"coordinates":[9.8528642654,49.6213302612],"type":"Point"}
}