{
  "type": "Feature",
  "properties": {
    "iso:country":"DE",
    "sg:address":"Brechtstr. 12",
    "sg:city":"Erkrath",
    "sg:phone":"+49 2104/45455",
    "sg:postcode":"40699",
    "sg:province":"Nordrhein-Westfalen",
    "wof:name":"Kupferkanne",
    "wof:placetype":"venue"
},
  "geometry": {"coordinates":[6.9599747658,51.2011566162],"type":"Point"}
}