{
  "type": "Feature",
  "properties": {
    "iso:country":"DE",
    "sg:address":"Landvogtstr. 34",
    "sg:city":"Berlin",
    "sg:phone":"+49 30/5667840",
    "sg:postcode":"12623",
    "sg:province":"Berlin",
    "wof:name":"Zimmervermittlung Bed And Breakfast Gmbh",
    "wof:placetype":"venue"
},
  "geometry": {"coordinates":[13.6274318695,52.5082473755],"type":"Point"}
}