{
  "type": "Feature",
  "properties": {
    "iso:country":"DE",
    "sg:address":"Rudolf-Herzog-Str. 14",
    "sg:city":"Wuppertal",
    "sg:phone":"+49 202/558989",
    "sg:postcode":"42275",
    "sg:province":"Nordrhein-Westfalen",
    "wof:name":"Ulrich Schieck",
    "wof:placetype":"venue"
},
  "geometry": {"coordinates":[7.2048459053,51.2716789246],"type":"Point"}
}