{
  "type": "Feature",
  "properties": {
    "iso:country":"DE",
    "sg:address":"Goethestr. 33",
    "sg:city":"Sprockh\u00f6vel",
    "sg:phone":"+49 2324/971481",
    "sg:postcode":"45549",
    "sg:province":"Nordrhein-Westfalen",
    "wof:name":"Eberhard Koch Steuerberater",
    "wof:placetype":"venue"
},
  "geometry": {"coordinates":[7.2416892052,51.3614997864],"type":"Point"}
}