{
  "type": "Feature",
  "properties": {
    "iso:country":"DE",
    "sg:address":"Schnieglinger Str. 272",
    "sg:city":"N\u00fcrnberg",
    "sg:phone":"+49 911/302546",
    "sg:postcode":"90427",
    "sg:province":"Bayern",
    "wof:name":"Blumengalerie",
    "wof:placetype":"venue"
},
  "geometry": {"coordinates":[11.024213,49.468807],"type":"Point"}
}