{
  "type": "Feature",
  "properties": {
    "iso:country":"DE",
    "sg:address":"Hauptstr. 1",
    "sg:city":"Uehlfeld",
    "sg:phone":"+49 9163/968821",
    "sg:postcode":"91486",
    "sg:province":"Bayern",
    "wof:name":"B. Zwingel",
    "wof:placetype":"venue"
},
  "geometry": {"coordinates":[10.721619606,49.6698684692],"type":"Point"}
}