{
  "type": "Feature",
  "properties": {
    "iso:country":"DE",
    "sg:address":"Kirschenweg 5",
    "sg:city":"Cadolzburg",
    "sg:phone":"+49 9103/2485",
    "sg:postcode":"90556",
    "sg:province":"Bayern",
    "wof:name":"G. Kaselow",
    "wof:placetype":"venue"
},
  "geometry": {"coordinates":[10.8559370041,49.4541015625],"type":"Point"}
}