{
  "type": "Feature",
  "properties": {
    "iso:country":"DE",
    "sg:address":"Darlaten 4",
    "sg:city":"Uchte",
    "sg:phone":"+49 5763/3584",
    "sg:postcode":"31600",
    "sg:province":"Niedersachsen",
    "wof:name":"Ortsverein Darlaten E. V.",
    "wof:placetype":"venue"
},
  "geometry": {"coordinates":[8.8260784149,52.5223884583],"type":"Point"}
}