{
  "type": "Feature",
  "properties": {
    "iso:country":"DE",
    "sg:address":"Ulrich-G\u00fcnther-Str. 20",
    "sg:city":"L\u00fctjenburg",
    "sg:phone":"+49 4381/7100",
    "sg:postcode":"24321",
    "sg:province":"Schleswig-Holstein",
    "wof:name":"D. Schmudlach Bau Gmbh",
    "wof:placetype":"venue"
},
  "geometry": {"coordinates":[10.5872373581,54.2877426147],"type":"Point"}
}