{
  "type": "Feature",
  "properties": {
    "iso:country":"DE",
    "sg:address":"Centrumstr. 11",
    "sg:city":"Essen",
    "sg:phone":"+49 201/556100",
    "sg:postcode":"45307",
    "sg:province":"Nordrhein-Westfalen",
    "wof:name":"Dorandt",
    "wof:placetype":"venue"
},
  "geometry": {"coordinates":[7.107327,51.465935],"type":"Point"}
}