{
  "type": "Feature",
  "properties": {
    "iso:country":"DE",
    "sg:address":"Industriestr. 15",
    "sg:city":"Meckesheim",
    "sg:phone":"+49 6226/1022",
    "sg:postcode":"74909",
    "sg:province":"Baden-W\u00fcrttemberg",
    "wof:name":"Ditec Dr. Siegfried Kahlich Und Dirk Langer Gmbh",
    "wof:placetype":"venue"
},
  "geometry": {"coordinates":[8.8117609024,49.3209457397],"type":"Point"}
}