{
  "type": "Feature",
  "properties": {
    "iso:country":"DE",
    "sg:address":"Waldstr. 40a",
    "sg:city":"Karlsruhe",
    "sg:phone":"+49 721/23353",
    "sg:postcode":"76133",
    "sg:province":"Baden-W\u00fcrttemberg",
    "wof:name":"Dr. Palm Gmbh",
    "wof:placetype":"venue"
},
  "geometry": {"coordinates":[8.3955621719,49.0089645386],"type":"Point"}
}