{
  "type": "Feature",
  "properties": {
    "iso:country":"DE",
    "sg:address":"Dorfstr. 3",
    "sg:city":"Delingsdorf",
    "sg:phone":"+49 4532/24966",
    "sg:postcode":"22941",
    "sg:province":"Schleswig-Holstein",
    "wof:name":"J\u00fcrgen Scharf",
    "wof:placetype":"venue"
},
  "geometry": {"coordinates":[10.2525033951,53.7086296082],"type":"Point"}
}