{
  "type": "Feature",
  "properties": {
    "iso:country":"DE",
    "sg:address":"Meierweg 6",
    "sg:city":"Augsburg",
    "sg:phone":"+49 821/415033",
    "sg:postcode":"86154",
    "sg:province":"Bayern",
    "wof:name":"Helmut Zerrle Schweisstechnik-grosshandel",
    "wof:placetype":"venue"
},
  "geometry": {"coordinates":[10.87574,48.39716],"type":"Point"}
}