{
  "type": "Feature",
  "properties": {
    "iso:country":"DE",
    "sg:address":"Kellergasse 2",
    "sg:city":"Dietfurt",
    "sg:phone":"+49 8464/9401",
    "sg:postcode":"92345",
    "sg:province":"Bayern",
    "wof:name":"Josef Schweiger",
    "wof:placetype":"venue"
},
  "geometry": {"coordinates":[11.5859861374,49.0359191895],"type":"Point"}
}