{
  "type": "Feature",
  "properties": {
    "iso:country":"DE",
    "sg:address":"Lindenstr. 76",
    "sg:city":"Berlin",
    "sg:postcode":"10969",
    "sg:province":"Berlin",
    "wof:name":"Redaktion Jahrbuch Preussi- Scher Kulturbesitz",
    "wof:placetype":"venue"
},
  "geometry": {"coordinates":[13.396188736,52.5054855347],"type":"Point"}
}