{
  "type": "Feature",
  "properties": {
    "iso:country":"DE",
    "sg:address":"Oberstr. 18",
    "sg:city":"Gro\u00dffischlingen",
    "sg:phone":"+49 6323/3208",
    "sg:postcode":"67483",
    "sg:province":"Rheinland-Pfalz",
    "wof:name":"Norbert Rohr",
    "wof:placetype":"venue"
},
  "geometry": {"coordinates":[8.171664238,49.269443512],"type":"Point"}
}