{
  "type": "Feature",
  "properties": {
    "iso:country":"DE",
    "sg:address":"Propsteistr. 46",
    "sg:city":"M\u00fcnster",
    "sg:phone":"+49 251/391826",
    "sg:postcode":"48145",
    "sg:province":"Nordrhein-Westfalen",
    "wof:name":"Heinz Steven Dipl. Ingenieur",
    "wof:placetype":"venue"
},
  "geometry": {"coordinates":[7.6566858292,51.9654197693],"type":"Point"}
}