{
  "type": "Feature",
  "properties": {
    "iso:country":"DE",
    "sg:address":"Am Walde 10",
    "sg:city":"Isernhagen",
    "sg:phone":"+49 511/612963",
    "sg:postcode":"30916",
    "sg:province":"Niedersachsen",
    "wof:name":"Caravan Vertriebs Gmbh",
    "wof:placetype":"venue"
},
  "geometry": {"coordinates":[9.8750953674,52.4356880188],"type":"Point"}
}