{
  "type": "Feature",
  "properties": {
    "iso:country":"DE",
    "sg:address":"Hirblinger Str. 160-162a",
    "sg:city":"Augsburg",
    "sg:phone":"+49 821/466072",
    "sg:postcode":"86156",
    "sg:province":"Bayern",
    "wof:name":"Hwd-haushalts-produkte Gmbh",
    "wof:placetype":"venue"
},
  "geometry": {"coordinates":[10.865109,48.395779],"type":"Point"}
}