{
  "type": "Feature",
  "properties": {
    "iso:country":"DE",
    "sg:address":"Gei\u00dfstr. 16",
    "sg:city":"Stuttgart",
    "sg:phone":"+49 711/244121",
    "sg:postcode":"70173",
    "sg:province":"Baden-W\u00fcrttemberg",
    "wof:name":"Kulmbacher Bierstuben",
    "wof:placetype":"venue"
},
  "geometry": {"coordinates":[9.1767292023,48.7735824585],"type":"Point"}
}