{
  "type": "Feature",
  "properties": {
    "iso:country":"DE",
    "sg:address":"Starkensiek 15",
    "sg:city":"Bad Oeynhausen",
    "sg:phone":"+49 5734/3991",
    "sg:postcode":"32549",
    "sg:province":"Nordrhein-Westfalen",
    "wof:name":"Hermann Ovesiek",
    "wof:placetype":"venue"
},
  "geometry": {"coordinates":[8.789477,52.253708],"type":"Point"}
}