{
  "type": "Feature",
  "properties": {
    "iso:country":"DE",
    "sg:address":"Steveder Weg 39",
    "sg:city":"Coesfeld",
    "sg:phone":"+49 2541/82335",
    "sg:postcode":"48653",
    "sg:province":"Nordrhein-Westfalen",
    "wof:name":"Hubert Gro\u00df-langenhoff Steuerberater",
    "wof:placetype":"venue"
},
  "geometry": {"coordinates":[7.1487908363,51.9364433289],"type":"Point"}
}