{
  "type": "Feature",
  "properties": {
    "iso:country":"DE",
    "sg:address":"Fuhrenweg 8",
    "sg:city":"Bardowick",
    "sg:phone":"+49 4131/121736",
    "sg:postcode":"21357",
    "sg:province":"Niedersachsen",
    "wof:name":"Uwe Apel",
    "wof:placetype":"venue"
},
  "geometry": {"coordinates":[10.3601799011,53.2908592224],"type":"Point"}
}