{
  "type": "Feature",
  "properties": {
    "iso:country":"DE",
    "sg:address":"Brahmsstr. 2b",
    "sg:city":"Birkenau",
    "sg:phone":"+49 6201/32067",
    "sg:postcode":"69488",
    "sg:province":"Hessen",
    "wof:name":"Werner Wielandt Anlageberater",
    "wof:placetype":"venue"
},
  "geometry": {"coordinates":[8.7175836563,49.5689239502],"type":"Point"}
}