{
  "type": "Feature",
  "properties": {
    "iso:country":"DE",
    "sg:address":"Siefenfeldchen 115",
    "sg:city":"Bornheim",
    "sg:postcode":"53332",
    "sg:province":"Nordrhein-Westfalen",
    "wof:name":"Haco Handel Und Commissionierung Gmbh",
    "wof:placetype":"venue"
},
  "geometry": {"coordinates":[7.0012750626,50.7567596436],"type":"Point"}
}