{
  "type": "Feature",
  "properties": {
    "iso:country":"DE",
    "sg:address":"Im Ring 12",
    "sg:city":"Drochtersen",
    "sg:phone":"+49 4148/1688",
    "sg:postcode":"21706",
    "sg:province":"Niedersachsen",
    "wof:name":"Reederei Frank Dahl Ms Orade Kg",
    "wof:placetype":"venue"
},
  "geometry": {"coordinates":[9.424077,53.690941],"type":"Point"}
}