{
  "type": "Feature",
  "properties": {
    "iso:country":"DE",
    "sg:address":"Wilhelm-Hauff-Str. 18",
    "sg:city":"Halle",
    "sg:phone":"+49 345/6877701",
    "sg:postcode":"06126",
    "sg:province":"Sachsen-Anhalt",
    "wof:name":"Creativo Haarkosmetik Und K\u00f6rperpflege Gmbh",
    "wof:placetype":"venue"
},
  "geometry": {"coordinates":[11.9064569473,51.473941803],"type":"Point"}
}