{
  "type": "Feature",
  "properties": {
    "iso:country":"DE",
    "sg:address":"M\u00fcllinger Str. 41",
    "sg:city":"Sehnde",
    "sg:phone":"+49 5138/1380",
    "sg:postcode":"31319",
    "sg:province":"Niedersachsen",
    "wof:name":"Restaurant M\u00fcllinger Tivoli",
    "wof:placetype":"venue"
},
  "geometry": {"coordinates":[9.89523983,52.3092575073],"type":"Point"}
}