{
  "type": "Feature",
  "properties": {
    "iso:country":"DE",
    "sg:address":"Industriestr. 7",
    "sg:city":"Winterbach",
    "sg:phone":"+49 7181/74343",
    "sg:postcode":"73650",
    "sg:province":"Baden-W\u00fcrttemberg",
    "wof:name":"Horst Kruppok",
    "wof:placetype":"venue"
},
  "geometry": {"coordinates":[9.4772701263,48.8039703369],"type":"Point"}
}