{
  "type": "Feature",
  "properties": {
    "iso:country":"DE",
    "sg:address":"Hetzleser Str.",
    "sg:city":"Neunkirchen",
    "sg:phone":"+49 9134/1851",
    "sg:postcode":"91077",
    "sg:province":"Bayern",
    "wof:name":"R. Heinlein",
    "wof:placetype":"venue"
},
  "geometry": {"coordinates":[11.129997,49.616314],"type":"Point"}
}