{
  "type": "Feature",
  "properties": {
    "iso:country":"DE",
    "sg:address":"Max-Reger-Str. 21",
    "sg:city":"Bremen",
    "sg:phone":"+49 421/344636",
    "sg:postcode":"28209",
    "sg:province":"Bremen",
    "wof:name":"Beteiligungsgesellschaft Kr\u00f6ncke Mbh",
    "wof:placetype":"venue"
},
  "geometry": {"coordinates":[8.836151,53.085831],"type":"Point"}
}