{
  "type": "Feature",
  "properties": {
    "iso:country":"DE",
    "sg:address":"Karlsbader Str. 11 a",
    "sg:city":"Schneeberg",
    "sg:phone":"+49 3772/22597",
    "sg:postcode":"08289",
    "sg:province":"Sachsen",
    "wof:name":"Erzgeb. Raiffeisen-handels- Genossenschaft L\u00f6\u00dfnitz Eg",
    "wof:placetype":"venue"
},
  "geometry": {"coordinates":[12.63892,50.587952],"type":"Point"}
}