{
  "type": "Feature",
  "properties": {
    "iso:country":"DE",
    "sg:address":"Jerichostr. 41",
    "sg:city":"Bocholt",
    "sg:phone":"+49 2871/42775",
    "sg:postcode":"46399",
    "sg:province":"Nordrhein-Westfalen",
    "wof:name":"Frank Steverding",
    "wof:placetype":"venue"
},
  "geometry": {"coordinates":[6.6033349037,51.8423042297],"type":"Point"}
}