{
  "type": "Feature",
  "properties": {
    "iso:country":"DE",
    "sg:address":"Kirchstr. 1",
    "sg:city":"Dinslaken",
    "sg:phone":"+49 2064/91955",
    "sg:postcode":"46539",
    "sg:province":"Nordrhein-Westfalen",
    "wof:name":"Br. Watermann Und Karin Bockm\u00fchl",
    "wof:placetype":"venue"
},
  "geometry": {"coordinates":[6.7648792267,51.5624351501],"type":"Point"}
}