{
  "type": "Feature",
  "properties": {
    "iso:country":"DE",
    "sg:address":"Roggenhof 4",
    "sg:city":"D\u00e4geling",
    "sg:phone":"+49 4821/85005",
    "sg:postcode":"25578",
    "sg:province":"Schleswig-Holstein",
    "wof:name":"Gunda Pattberg Steuerberaterin",
    "wof:placetype":"venue"
},
  "geometry": {"coordinates":[9.5339307785,53.8782463074],"type":"Point"}
}