{
  "type": "Feature",
  "properties": {
    "iso:country":"DE",
    "sg:address":"Tillystr. 17",
    "sg:city":"Hannover",
    "sg:phone":"+49 4951/141070",
    "sg:postcode":"30459",
    "sg:province":"Niedersachsen",
    "wof:name":"Martin Braun Backmittel & Essenzen Kg",
    "wof:placetype":"venue"
},
  "geometry": {"coordinates":[9.719201,52.339314],"type":"Point"}
}