{
  "type": "Feature",
  "properties": {
    "iso:country":"DE",
    "sg:address":"Schmiedberg 13",
    "sg:city":"Burgau",
    "sg:phone":"+49 8222/96780",
    "sg:postcode":"89331",
    "sg:province":"Bayern",
    "wof:name":"Beate Mendle Rechtsanw\u00e4ltin",
    "wof:placetype":"venue"
},
  "geometry": {"coordinates":[10.4067840576,48.4328651428],"type":"Point"}
}