{
  "type": "Feature",
  "properties": {
    "iso:country":"DE",
    "sg:address":"K\u00fcckstr.",
    "sg:city":"Baesweiler",
    "sg:phone":"+49 2401/4623",
    "sg:postcode":"52499",
    "sg:province":"Nordrhein-Westfalen",
    "wof:name":"Maria-th. Joswig",
    "wof:placetype":"venue"
},
  "geometry": {"coordinates":[6.178964138,50.9101028442],"type":"Point"}
}