{
  "type": "Feature",
  "properties": {
    "iso:country":"DE",
    "sg:address":"Hauptstr. 61",
    "sg:city":"W\u00f6lfersheim",
    "sg:phone":"+49 6036/6051",
    "sg:postcode":"61200",
    "sg:province":"Hessen",
    "wof:name":"Heinrich Leschhorn Inh. Heinrich Erich Leschhorn",
    "wof:placetype":"venue"
},
  "geometry": {"coordinates":[8.8117961884,50.3979301453],"type":"Point"}
}