{
  "type": "Feature",
  "properties": {
    "iso:country":"DE",
    "sg:address":"Hollerdeich 29",
    "sg:city":"Wischhafen",
    "sg:phone":"+49 4770/831212",
    "sg:postcode":"21737",
    "sg:province":"Niedersachsen",
    "wof:name":"Jo Hammar",
    "wof:placetype":"venue"
},
  "geometry": {"coordinates":[9.3188495636,53.7804603577],"type":"Point"}
}