{
  "type": "Feature",
  "properties": {
    "iso:country":"DE",
    "sg:address":"Breidenplatz 4",
    "sg:city":"D\u00fcsseldorf",
    "sg:phone":"+49 211/9253330",
    "sg:postcode":"40627",
    "sg:province":"Nordrhein-Westfalen",
    "wof:name":"Kuhlen Optik Handels Gmbh",
    "wof:placetype":"venue"
},
  "geometry": {"coordinates":[6.89482,51.204163],"type":"Point"}
}