{
  "type": "Feature",
  "properties": {
    "iso:country":"DE",
    "sg:address":"Rilkepfad 2",
    "sg:city":"Berlin",
    "sg:phone":"+49 30/8477130",
    "sg:postcode":"14167",
    "sg:province":"Berlin",
    "wof:name":"Ulrich Weber Architekt",
    "wof:placetype":"venue"
},
  "geometry": {"coordinates":[13.272643,52.420567],"type":"Point"}
}