{
  "type": "Feature",
  "properties": {
    "iso:country":"DE",
    "sg:address":"Neuwiese 1",
    "sg:city":"Dohr",
    "sg:phone":"+49 2671/7492",
    "sg:postcode":"56812",
    "sg:province":"Rheinland-Pfalz",
    "wof:name":"Winfried Sch\u00e4fer",
    "wof:placetype":"venue"
},
  "geometry": {"coordinates":[7.167131,50.145538],"type":"Point"}
}