{
  "type": "Feature",
  "properties": {
    "iso:country":"DE",
    "sg:address":"Wirsbergstr. 14",
    "sg:city":"W\u00fcrzburg",
    "sg:phone":"+49 931/59165",
    "sg:postcode":"97070",
    "sg:province":"Bayern",
    "wof:name":"Fabricius Und Moser Rechtsanw\u00e4lte",
    "wof:placetype":"venue"
},
  "geometry": {"coordinates":[9.9286050797,49.7901000977],"type":"Point"}
}