{
  "type": "Feature",
  "properties": {
    "iso:country":"DE",
    "sg:address":"Paul-Kemp-Str. 24",
    "sg:city":"Bonn",
    "sg:phone":"+49 228/356376",
    "sg:postcode":"53173",
    "sg:province":"Nordrhein-Westfalen",
    "wof:name":"U. Degenhardt-wiehlp\u00fctz Rechtsanwalt",
    "wof:placetype":"venue"
},
  "geometry": {"coordinates":[7.1548361778,50.6876068115],"type":"Point"}
}