{
  "type": "Feature",
  "properties": {
    "iso:country":"DE",
    "sg:address":"Karlstr. 34",
    "sg:city":"Karlsruhe",
    "sg:phone":"+49 721/26770",
    "sg:postcode":"76133",
    "sg:province":"Baden-W\u00fcrttemberg",
    "wof:name":"Ruf & Co. Willi Schaarmann",
    "wof:placetype":"venue"
},
  "geometry": {"coordinates":[8.3944797516,49.0067558289],"type":"Point"}
}