{
  "type": "Feature",
  "properties": {
    "iso:country":"DE",
    "sg:address":"Stenglingser Weg 46",
    "sg:city":"Iserlohn",
    "sg:postcode":"58642",
    "sg:province":"Nordrhein-Westfalen",
    "wof:name":"Krupp Stahl Gmbh",
    "wof:placetype":"venue"
},
  "geometry": {"coordinates":[7.6365170479,51.3596878052],"type":"Point"}
}