{
  "type": "Feature",
  "properties": {
    "iso:country":"DE",
    "sg:address":"Rahmer Str. 3",
    "sg:city":"Dortmund",
    "sg:phone":"+49 231/314163",
    "sg:postcode":"44369",
    "sg:province":"Nordrhein-Westfalen",
    "wof:name":"Elke Weist",
    "wof:placetype":"venue"
},
  "geometry": {"coordinates":[7.414616,51.531742],"type":"Point"}
}