{
  "type": "Feature",
  "properties": {
    "iso:country":"DE",
    "sg:address":"Am Steinb\u00fchl 11",
    "sg:city":"Naila",
    "sg:phone":"+49 9282/690",
    "sg:postcode":"95119",
    "sg:province":"Bayern",
    "wof:name":"Heilp\u00e4d. Kinderheim Martinsberg",
    "wof:placetype":"venue"
},
  "geometry": {"coordinates":[11.7006502151,50.3188095093],"type":"Point"}
}