{
  "type": "Feature",
  "properties": {
    "iso:country":"DE",
    "sg:address":"Gehlenbecker Str. 13",
    "sg:city":"Espelkamp",
    "sg:phone":"+49 171 7491449",
    "sg:postcode":"32339",
    "sg:province":"Nordrhein-Westfalen",
    "wof:name":"J\u00f6rg-friedrich M\u00f6hlmeyer",
    "wof:placetype":"venue"
},
  "geometry": {"coordinates":[8.651135,52.341633],"type":"Point"}
}