{
  "type": "Feature",
  "properties": {
    "iso:country":"DE",
    "sg:address":"Riedinger Strasse 22a",
    "sg:city":"Augsburg",
    "sg:phone":"+49 172 6693549",
    "sg:postcode":"86153",
    "sg:province":"Bayern",
    "wof:name":"Christian Heilmann Internet Service",
    "wof:placetype":"venue"
},
  "geometry": {"coordinates":[10.890542984,48.3835258484],"type":"Point"}
}