{
  "type": "Feature",
  "properties": {
    "iso:country":"DE",
    "sg:address":"Am Gr\u00fcnen Weg 2",
    "sg:city":"Kelsterbach",
    "sg:phone":"+49 6107/7523",
    "sg:postcode":"65451",
    "sg:province":"Hessen",
    "wof:name":"Alpha Gesellschaft F\u00fcr Reiseb\u00fcros Mbh",
    "wof:placetype":"venue"
},
  "geometry": {"coordinates":[8.5435304642,50.0487327576],"type":"Point"}
}