{
  "type": "Feature",
  "properties": {
    "iso:country":"DE",
    "sg:address":"Hofj\u00e4gerallee 21",
    "sg:city":"Berlin",
    "sg:postcode":"13465",
    "sg:province":"Berlin",
    "wof:name":"Acon Energie Management Gmbh",
    "wof:placetype":"venue"
},
  "geometry": {"coordinates":[13.298349,52.637333],"type":"Point"}
}