{
  "type": "Feature",
  "properties": {
    "iso:country":"DE",
    "sg:address":"Altenburger Str. 27",
    "sg:city":"Lucka",
    "sg:phone":"+49 34492/22228",
    "sg:postcode":"04613",
    "sg:province":"Th\u00fcringen",
    "wof:name":"Fleischerei Bruno Heydasch Gmbh",
    "wof:placetype":"venue"
},
  "geometry": {"coordinates":[12.3332118988,51.0978507996],"type":"Point"}
}