{
  "type": "Feature",
  "properties": {
    "iso:country":"DE",
    "sg:address":"Rotacker 11",
    "sg:city":"Hasselfelde",
    "sg:phone":"+49 39459/71320",
    "sg:postcode":"38899",
    "sg:province":"Sachsen-Anhalt",
    "wof:name":"Pension Rebentisch Inh. Bernd Matthes",
    "wof:placetype":"venue"
},
  "geometry": {"coordinates":[10.8341989517,51.6749000549],"type":"Point"}
}