{
  "type": "Feature",
  "properties": {
    "iso:country":"DE",
    "sg:address":"Steilshooper Allee",
    "sg:city":"Hamburg",
    "sg:phone":"+49 40/6323999",
    "sg:postcode":"22309",
    "sg:province":"Hamburg",
    "wof:name":"Blumen Rojan",
    "wof:placetype":"venue"
},
  "geometry": {"coordinates":[10.06695,53.608589],"type":"Point"}
}