{
  "type": "Feature",
  "properties": {
    "iso:country":"DE",
    "sg:address":"Neusiedlung 1a",
    "sg:city":"Eixen",
    "sg:postcode":"18334",
    "sg:province":"Mecklenburg-Vorpommern",
    "wof:name":"Landwirtschaftsges. Mbh Kavelsdorf & Co. Kg",
    "wof:placetype":"venue"
},
  "geometry": {"coordinates":[12.673225,54.06662],"type":"Point"}
}