{
  "type": "Feature",
  "properties": {
    "iso:country":"DE",
    "sg:address":"Bornstr.14",
    "sg:city":"Dortmund",
    "sg:phone":"+49 231/573619",
    "sg:postcode":"44135",
    "sg:province":"Nordrhein-Westfalen",
    "wof:name":"Adonis-center",
    "wof:placetype":"venue"
},
  "geometry": {"coordinates":[7.4691758156,51.5181732178],"type":"Point"}
}