{
  "type": "Feature",
  "properties": {
    "iso:country":"DE",
    "sg:address":"Breite Str. 8",
    "sg:city":"Hillersleben",
    "sg:postcode":"39343",
    "sg:province":"Sachsen-Anhalt",
    "wof:name":"Angela Lakenmacher",
    "wof:placetype":"venue"
},
  "geometry": {"coordinates":[11.4906425476,52.2737922668],"type":"Point"}
}