{
  "type": "Feature",
  "properties": {
    "iso:country":"DE",
    "sg:address":"Grafenstr. 36",
    "sg:city":"Essen",
    "sg:phone":"+49 201/491112",
    "sg:postcode":"45239",
    "sg:province":"Nordrhein-Westfalen",
    "wof:name":"B. Schulte-schnitker",
    "wof:placetype":"venue"
},
  "geometry": {"coordinates":[7.0007538795,51.38879776],"type":"Point"}
}