{
  "type": "Feature",
  "properties": {
    "iso:country":"DE",
    "sg:address":"Am Wall 148",
    "sg:city":"Bremen",
    "sg:phone":"+49 421/327502",
    "sg:postcode":"28195",
    "sg:province":"Bremen",
    "wof:name":"Plan 9",
    "wof:placetype":"venue"
},
  "geometry": {"coordinates":[8.8094911575,53.0784683228],"type":"Point"}
}