{
  "type": "Feature",
  "properties": {
    "iso:country":"DE",
    "sg:address":"Am Gro\u00dfen Weserbogen 31",
    "sg:city":"Bad Oeynhausen",
    "sg:phone":"+49 5731/51411",
    "sg:postcode":"32549",
    "sg:province":"Nordrhein-Westfalen",
    "wof:name":"Dieter Meister Verlags- Vertretungverwaltungsges. Mbh",
    "wof:placetype":"venue"
},
  "geometry": {"coordinates":[8.8283262253,52.2253761292],"type":"Point"}
}