{
  "type": "Feature",
  "properties": {
    "iso:country":"DE",
    "sg:address":"Breitenfeld 2a",
    "sg:city":"L\u00fcdenscheid",
    "sg:phone":"+49 2351/52309",
    "sg:postcode":"58507",
    "sg:province":"Nordrhein-Westfalen",
    "wof:name":"G\u00fcnter He\u00dfmert",
    "wof:placetype":"venue"
},
  "geometry": {"coordinates":[7.618901,51.229294],"type":"Point"}
}