{
  "type": "Feature",
  "properties": {
    "iso:country":"DE",
    "sg:address":"L\u00fcbbecker Str. 129",
    "sg:city":"Kirchlengern",
    "sg:phone":"+49 5223/75397",
    "sg:postcode":"32278",
    "sg:province":"Nordrhein-Westfalen",
    "wof:name":"Helga's Imbi\u00df",
    "wof:placetype":"venue"
},
  "geometry": {"coordinates":[8.6394119263,52.2054023743],"type":"Point"}
}