{
  "type": "Feature",
  "properties": {
    "iso:country":"DE",
    "sg:address":"Schwarze-B\u00e4ren-Str. 4",
    "sg:city":"Regensburg",
    "sg:phone":"+49 941/560463",
    "sg:postcode":"93047",
    "sg:province":"Bayern",
    "wof:name":"C. M. Schmitt Gmbh & Co.",
    "wof:placetype":"venue"
},
  "geometry": {"coordinates":[12.0983810425,49.0177345276],"type":"Point"}
}