{
  "type": "Feature",
  "properties": {
    "iso:country":"DE",
    "sg:address":"Fischbachstr. 51 - 53",
    "sg:city":"Bergheim",
    "sg:postcode":"50127",
    "sg:province":"Nordrhein-Westfalen",
    "wof:name":"Rkh Rheinkies Hitdorf Verwaltungs Gmbh",
    "wof:placetype":"venue"
},
  "geometry": {"coordinates":[6.705752,50.925323],"type":"Point"}
}