{
  "type": "Feature",
  "properties": {
    "iso:country":"DE",
    "sg:address":"Peter-Kintgen-Str. 10",
    "sg:city":"K\u00f6ln",
    "sg:phone":"+49 221/434394",
    "sg:postcode":"50935",
    "sg:province":"Nordrhein-Westfalen",
    "wof:name":"Sz Verm\u00f6gensverwaltungs Gmbh",
    "wof:placetype":"venue"
},
  "geometry": {"coordinates":[6.8952789307,50.9198493958],"type":"Point"}
}