{
  "type": "Feature",
  "properties": {
    "iso:country":"DE",
    "sg:address":"Koppenhof 5",
    "sg:city":"N\u00f6rdlingen",
    "sg:phone":"+49 9081/28362",
    "sg:postcode":"86720",
    "sg:province":"Bayern",
    "wof:name":"Stark",
    "wof:placetype":"venue"
},
  "geometry": {"coordinates":[10.4908914566,48.849937439],"type":"Point"}
}