{
  "type": "Feature",
  "properties": {
    "iso:country":"DE",
    "sg:address":"Klosterstr. 36",
    "sg:city":"Schoden",
    "sg:phone":"+49 6581/6555",
    "sg:postcode":"54441",
    "sg:province":"Rheinland-Pfalz",
    "wof:name":"G\u00fcnther Sch\u00f6rgenhummer",
    "wof:placetype":"venue"
},
  "geometry": {"coordinates":[6.5767478943,49.6391372681],"type":"Point"}
}