{
  "type": "Feature",
  "properties": {
    "iso:country":"DE",
    "sg:address":"Mannhagener Str. 11",
    "sg:city":"Panten",
    "sg:phone":"+49 4542/7022",
    "sg:postcode":"23896",
    "sg:province":"Schleswig-Holstein",
    "wof:name":"Adolf Von Wahden Handels- U. Vertriebs-gmbh",
    "wof:placetype":"venue"
},
  "geometry": {"coordinates":[10.6024799347,53.6472206116],"type":"Point"}
}