{
  "type": "Feature",
  "properties": {
    "iso:country":"DE",
    "sg:address":"Hohlstr. 76",
    "sg:city":"Velbert",
    "sg:phone":"+49 2052/4777",
    "sg:postcode":"42555",
    "sg:province":"Nordrhein-Westfalen",
    "wof:name":"G\u00fcnter B\u00fcchter",
    "wof:placetype":"venue"
},
  "geometry": {"coordinates":[7.1203899384,51.3383407593],"type":"Point"}
}