{
  "type": "Feature",
  "properties": {
    "iso:country":"DE",
    "sg:address":"Bahnhof",
    "sg:city":"Geltendorf",
    "sg:phone":"+49 8193/206",
    "sg:postcode":"82269",
    "sg:province":"Bayern",
    "wof:name":"Deutsche Bahn Ag",
    "wof:placetype":"venue"
},
  "geometry": {"coordinates":[11.0321149826,48.1162033081],"type":"Point"}
}