{
  "type": "Feature",
  "properties": {
    "iso:country":"DE",
    "sg:address":"Westerwaldweg 3",
    "sg:city":"Sollwitt",
    "sg:phone":"+49 4843/325",
    "sg:postcode":"25884",
    "sg:province":"Schleswig-Holstein",
    "wof:name":"H.-h. Und E. Clausen",
    "wof:placetype":"venue"
},
  "geometry": {"coordinates":[9.232933,54.608227],"type":"Point"}
}