{
  "type": "Feature",
  "properties": {
    "iso:country":"DE",
    "sg:address":"Weiherhausstr. 6",
    "sg:city":"Heppenheim",
    "sg:phone":"+49 6252/72173",
    "sg:postcode":"64646",
    "sg:province":"Hessen",
    "wof:name":"Psychosoziale Beratungsstelle F. Suchtkranke",
    "wof:placetype":"venue"
},
  "geometry": {"coordinates":[8.629515,49.643559],"type":"Point"}
}