{
  "type": "Feature",
  "properties": {
    "iso:country":"DE",
    "sg:address":"Hauptstr. 195",
    "sg:city":"Gro\u00dfhartmannsdorf",
    "sg:phone":"+49 37329/379",
    "sg:postcode":"09618",
    "sg:province":"Sachsen",
    "wof:name":"Heinz Wicke",
    "wof:placetype":"venue"
},
  "geometry": {"coordinates":[13.3213262558,50.8026123047],"type":"Point"}
}