{
  "type": "Feature",
  "properties": {
    "iso:country":"DE",
    "sg:address":"Alte Siedlung 13",
    "sg:city":"Kalletal",
    "sg:phone":"+49 5264/5452",
    "sg:postcode":"32689",
    "sg:province":"Nordrhein-Westfalen",
    "wof:name":"Fritz Drewes Landwirt. Lohnbetrieb",
    "wof:placetype":"venue"
},
  "geometry": {"coordinates":[8.977125,52.151054],"type":"Point"}
}