{
  "type": "Feature",
  "properties": {
    "iso:country":"DE",
    "sg:address":"An der Hengelbirke 3",
    "sg:city":"Glandorf",
    "sg:phone":"+49 5426/4558",
    "sg:postcode":"49219",
    "sg:province":"Niedersachsen",
    "wof:name":"Josef Beckemeyer",
    "wof:placetype":"venue"
},
  "geometry": {"coordinates":[7.914509,52.074284],"type":"Point"}
}