{
  "type": "Feature",
  "properties": {
    "iso:country":"DE",
    "sg:address":"Wilhelmstr. 18",
    "sg:city":"Bad Neuenahr-Ahrweiler",
    "sg:phone":"+49 2641/34464",
    "sg:postcode":"53474",
    "sg:province":"Rheinland-Pfalz",
    "wof:name":"Peter J. Sch\u00fctz Weinanbau",
    "wof:placetype":"venue"
},
  "geometry": {"coordinates":[7.1017870903,50.5452880859],"type":"Point"}
}