{
  "type": "Feature",
  "properties": {
    "iso:country":"DE",
    "sg:address":"5 cour du centre",
    "sg:city":"boulogne sur mer",
    "sg:postcode":"62200",
    "wof:name":"Deepexplorer..voyage Vers Les Grandes Profondeurs",
    "wof:placetype":"venue"
},
  "geometry": {"coordinates":[1.615514,50.727444],"type":"Point"}
}