{
  "type": "Feature",
  "properties": {
    "iso:country":"DE",
    "sg:address":"Martinshofstr. 15",
    "sg:city":"Pullach",
    "sg:phone":"+49 89/7930752",
    "sg:postcode":"82049",
    "sg:province":"Bayern",
    "wof:name":"Eec & S Gmbh Electronic Equipment",
    "wof:placetype":"venue"
},
  "geometry": {"coordinates":[11.5185937881,48.066368103],"type":"Point"}
}