{
  "type": "Feature",
  "properties": {
    "iso:country":"DE",
    "sg:address":"Am Lagerhaus 4",
    "sg:city":"Niederwerrn",
    "sg:phone":"+49 9726/709",
    "sg:postcode":"97464",
    "sg:province":"Bayern",
    "wof:name":"Heribert Waltinger Gmbh",
    "wof:placetype":"venue"
},
  "geometry": {"coordinates":[10.152676,50.068386],"type":"Point"}
}