{
  "type": "Feature",
  "properties": {
    "iso:country":"DE",
    "sg:address":"Buchholzmarkt 10",
    "sg:city":"Bockenem",
    "sg:phone":"+49 5067/2228",
    "sg:postcode":"31167",
    "sg:province":"Niedersachsen",
    "wof:name":"Schrecke",
    "wof:placetype":"venue"
},
  "geometry": {"coordinates":[10.129745,52.009026],"type":"Point"}
}