{
  "type": "Feature",
  "properties": {
    "iso:country":"DE",
    "sg:address":"Schwalbacher Str. 76",
    "sg:city":"Saarwellingen",
    "sg:phone":"+49 6838/3328",
    "sg:postcode":"66793",
    "sg:province":"Saarland",
    "wof:name":"W. Jungmann & H. Martin Architekten",
    "wof:placetype":"venue"
},
  "geometry": {"coordinates":[6.854159,49.322498],"type":"Point"}
}