{
  "type": "Feature",
  "properties": {
    "iso:country":"DE",
    "sg:address":"Friedenstr. 31",
    "sg:city":"Steinheim",
    "sg:phone":"+49 7329/1419",
    "sg:postcode":"89555",
    "sg:province":"Baden-W\u00fcrttemberg",
    "wof:name":"Gerda Sekanina Masseur",
    "wof:placetype":"venue"
},
  "geometry": {"coordinates":[10.054297,48.688915],"type":"Point"}
}