{
  "type": "Feature",
  "properties": {
    "iso:country":"DE",
    "sg:address":"Carl-Zeiss-Str. 1",
    "sg:city":"Offenburg",
    "sg:phone":"+49 781/60702",
    "sg:postcode":"77656",
    "sg:province":"Baden-W\u00fcrttemberg",
    "wof:name":"Hobby Und Freizeit Verlag Und Vertrieb Verwaltungsges. Mbh",
    "wof:placetype":"venue"
},
  "geometry": {"coordinates":[7.932059,48.437992],"type":"Point"}
}