{
  "type": "Feature",
  "properties": {
    "iso:country":"DE",
    "sg:address":"Zwickauer Str. 41",
    "sg:city":"Hartenstein",
    "sg:phone":"+49 37605/5328",
    "sg:postcode":"08118",
    "sg:province":"Sachsen",
    "wof:name":"J\u00f6rg Leupold",
    "wof:placetype":"venue"
},
  "geometry": {"coordinates":[12.6613464355,50.6655654907],"type":"Point"}
}