{
  "type": "Feature",
  "properties": {
    "iso:country":"DE",
    "sg:address":"Edith-Stein-Str. 5",
    "sg:city":"Schifferstadt",
    "sg:phone":"+49 6235/5724",
    "sg:postcode":"67105",
    "sg:province":"Rheinland-Pfalz",
    "wof:name":"Reinhold Glaser Steuerberater",
    "wof:placetype":"venue"
},
  "geometry": {"coordinates":[8.3780078888,49.376411438],"type":"Point"}
}