{
  "type": "Feature",
  "properties": {
    "iso:country":"DE",
    "sg:address":"K\u00f6nigsbacher Str. 1",
    "sg:city":"Ludwigshafen",
    "sg:phone":"+49 621/673725",
    "sg:postcode":"67067",
    "sg:province":"Rheinland-Pfalz",
    "wof:name":"U. Brucher Anlageberater",
    "wof:placetype":"venue"
},
  "geometry": {"coordinates":[8.4096336365,49.4626235962],"type":"Point"}
}