{
  "type": "Feature",
  "properties": {
    "iso:country":"DE",
    "sg:address":"Bernh\u00e4user Hauptstr. 7",
    "sg:city":"Filderstadt",
    "sg:phone":"+49 711/702608",
    "sg:postcode":"70794",
    "sg:province":"Baden-W\u00fcrttemberg",
    "wof:name":"Neue Apotheke Apotheker Karl J. Koch",
    "wof:placetype":"venue"
},
  "geometry": {"coordinates":[9.216868,48.678394],"type":"Point"}
}