{
  "type": "Feature",
  "properties": {
    "iso:country":"DE",
    "sg:address":"Dillenburger Str. 42",
    "sg:city":"Dillenburg",
    "sg:phone":"+49 2771/30090",
    "sg:postcode":"35685",
    "sg:province":"Hessen",
    "wof:name":"Confisseur L\u00e4derach Gmbh & Co. Kg",
    "wof:placetype":"venue"
},
  "geometry": {"coordinates":[8.2693786621,50.7635421753],"type":"Point"}
}