{
  "type": "Feature",
  "properties": {
    "iso:country":"DE",
    "sg:address":"Gartenstr. 1",
    "sg:city":"Schuttertal",
    "sg:phone":"+49 7826/96706",
    "sg:postcode":"77978",
    "sg:province":"Baden-W\u00fcrttemberg",
    "wof:name":"Bauwerk Bautr\u00e4ger Gmbh",
    "wof:placetype":"venue"
},
  "geometry": {"coordinates":[7.96753,48.219322],"type":"Point"}
}