{
  "type": "Feature",
  "properties": {
    "iso:country":"DE",
    "sg:address":"Pappelallee 6",
    "sg:city":"Hamm",
    "sg:phone":"+49 2381/53221",
    "sg:postcode":"59063",
    "sg:province":"Nordrhein-Westfalen",
    "wof:name":"Horst Liebetanz",
    "wof:placetype":"venue"
},
  "geometry": {"coordinates":[7.849321,51.668533],"type":"Point"}
}