{
  "type": "Feature",
  "properties": {
    "iso:country":"DE",
    "sg:address":"Schulstr. 18",
    "sg:city":"D\u00f6rfles-Esbach",
    "sg:phone":"+49 9561/62751",
    "sg:postcode":"96487",
    "sg:province":"Bayern",
    "wof:name":"Gastst\u00e4tte Tsv Sportheim",
    "wof:placetype":"venue"
},
  "geometry": {"coordinates":[10.987077713,50.280456543],"type":"Point"}
}