{
  "type": "Feature",
  "properties": {
    "iso:country":"DE",
    "sg:address":"Willinghepper Str. 13",
    "sg:city":"Soest",
    "sg:phone":"+49 2921/80903",
    "sg:postcode":"59494",
    "sg:province":"Nordrhein-Westfalen",
    "wof:name":"Baumietservice Rainer Schenkel Gmbh",
    "wof:placetype":"venue"
},
  "geometry": {"coordinates":[8.1125383377,51.6171073914],"type":"Point"}
}