{
  "type": "Feature",
  "properties": {
    "iso:country":"DE",
    "sg:address":"Hilblestr. 54",
    "sg:city":"M\u00fcnchen",
    "sg:phone":"+49 89/7693626",
    "sg:postcode":"80636",
    "sg:province":"Bayern",
    "wof:name":"Repro & Druck Gmbh",
    "wof:placetype":"venue"
},
  "geometry": {"coordinates":[11.543886,48.155582],"type":"Point"}
}