{
  "type": "Feature",
  "properties": {
    "iso:country":"DE",
    "sg:address":"Ernest-Solvay-Str. 1",
    "sg:city":"Bernburg",
    "sg:phone":"+49 3471/34766",
    "sg:postcode":"06406",
    "sg:province":"Sachsen-Anhalt",
    "wof:name":"Pr\u00fcfgesellschaft F\u00fcr Stra\u00dfen- Und Tiefbau Mbh",
    "wof:placetype":"venue"
},
  "geometry": {"coordinates":[11.75459,51.774414],"type":"Point"}
}