{
  "type": "Feature",
  "properties": {
    "iso:country":"DE",
    "sg:address":"Flugh HH-Fuhlsb\u00fcttel 172",
    "sg:city":"Hamburg",
    "sg:postcode":"22335",
    "sg:province":"Hamburg",
    "wof:name":"Saems Special Airport Equipment And Maintenance",
    "wof:placetype":"venue"
},
  "geometry": {"coordinates":[10.01651,53.634521],"type":"Point"}
}