{
  "type": "Feature",
  "properties": {
    "iso:country":"DE",
    "sg:address":"Untertalstr. 39",
    "sg:city":"Simonswald",
    "sg:phone":"+49 7683/1414",
    "sg:postcode":"79263",
    "sg:province":"Baden-W\u00fcrttemberg",
    "wof:name":"L. Fuchs",
    "wof:placetype":"venue"
},
  "geometry": {"coordinates":[8.0519943237,48.1011581421],"type":"Point"}
}