{
  "type": "Feature",
  "properties": {
    "iso:country":"DE",
    "sg:address":"Urftstr. 4",
    "sg:city":"Dahlem",
    "sg:phone":"+49 2447/346",
    "sg:postcode":"53949",
    "sg:province":"Nordrhein-Westfalen",
    "wof:name":"Urftklause",
    "wof:placetype":"venue"
},
  "geometry": {"coordinates":[6.5521540642,50.4180145264],"type":"Point"}
}