{
  "type": "Feature",
  "properties": {
    "iso:country":"DE",
    "sg:address":"Westring 227",
    "sg:city":"Castrop-Rauxel",
    "sg:phone":"+49 2305/18086",
    "sg:postcode":"44579",
    "sg:province":"Nordrhein-Westfalen",
    "wof:name":"Fairpack Industrieverpackungen Vertriebsgesellschaft Mbh",
    "wof:placetype":"venue"
},
  "geometry": {"coordinates":[7.2938699722,51.5543785095],"type":"Point"}
}