{
  "type": "Feature",
  "properties": {
    "iso:country":"DE",
    "sg:address":"Niedervellmarer Str. 6",
    "sg:city":"Kassel",
    "sg:phone":"+49 561/989080",
    "sg:postcode":"34127",
    "sg:province":"Hessen",
    "wof:name":"Gebr. H\u00fcbenthal Gmbh",
    "wof:placetype":"venue"
},
  "geometry": {"coordinates":[9.4884967804,51.3387451172],"type":"Point"}
}