{
  "type": "Feature",
  "properties": {
    "iso:country":"DE",
    "sg:address":"Westernkamp 1",
    "sg:city":"Steinhagen",
    "sg:phone":"+49 5204/3226",
    "sg:postcode":"33803",
    "sg:province":"Nordrhein-Westfalen",
    "wof:name":"Rechenzentrum Gmbh",
    "wof:placetype":"venue"
},
  "geometry": {"coordinates":[8.4044532776,52.0030937195],"type":"Point"}
}