{
  "type": "Feature",
  "properties": {
    "iso:country":"DE",
    "sg:address":"Ulrichstr. 49",
    "sg:city":"Tangerm\u00fcnde",
    "sg:phone":"+49 39322/42149",
    "sg:postcode":"39590",
    "sg:province":"Sachsen-Anhalt",
    "wof:name":"Lothar Drobek",
    "wof:placetype":"venue"
},
  "geometry": {"coordinates":[11.9737234116,52.5497169495],"type":"Point"}
}