{
  "type": "Feature",
  "properties": {
    "iso:country":"DE",
    "sg:address":"Gro\u00dfe Str. 19",
    "sg:city":"Steinfeld",
    "sg:phone":"+49 5492/2296",
    "sg:postcode":"49439",
    "sg:province":"Niedersachsen",
    "wof:name":"Gastst\u00e4tte Dieter Westermann",
    "wof:placetype":"venue"
},
  "geometry": {"coordinates":[9.2053556442,53.2218437195],"type":"Point"}
}