{
  "type": "Feature",
  "properties": {
    "iso:country":"DE",
    "sg:address":"Poststr. 4",
    "sg:city":"Hohn",
    "sg:phone":"+49 4335/608",
    "sg:postcode":"24806",
    "sg:province":"Schleswig-Holstein",
    "wof:name":"Bernd M\u00fcller E. K.",
    "wof:placetype":"venue"
},
  "geometry": {"coordinates":[9.498921,54.29665],"type":"Point"}
}