{
  "type": "Feature",
  "properties": {
    "iso:country":"DE",
    "sg:address":"Behnsdorfer Str.",
    "sg:city":"Flechtingen",
    "sg:phone":"+49 39054/27434",
    "sg:postcode":"39345",
    "sg:province":"Sachsen-Anhalt",
    "wof:name":"Zur Bowlingbahn",
    "wof:placetype":"venue"
},
  "geometry": {"coordinates":[11.2361249924,52.330871582],"type":"Point"}
}