{
  "type": "Feature",
  "properties": {
    "iso:country":"DE",
    "sg:address":"Willy-Brandt-Pl 2",
    "sg:city":"Frankfurt",
    "sg:phone":"+49 4969/2585549",
    "sg:postcode":"65929",
    "sg:province":"Hessen",
    "wof:name":"Bfg Bank Ag",
    "wof:placetype":"venue"
},
  "geometry": {"coordinates":[8.543885,50.099094],"type":"Point"}
}