{
  "type": "Feature",
  "properties": {
    "iso:country":"DE",
    "sg:address":"R\u00f6merstr. 22",
    "sg:city":"Heidelberg",
    "sg:phone":"+49 6221/28676",
    "sg:postcode":"69115",
    "sg:province":"Baden-W\u00fcrttemberg",
    "wof:name":"Ernst Winnewisser",
    "wof:placetype":"venue"
},
  "geometry": {"coordinates":[8.684565,49.404453],"type":"Point"}
}