{
  "type": "Feature",
  "properties": {
    "iso:country":"DE",
    "sg:address":"Pfinztalstr. 19",
    "sg:city":"Karlsruhe",
    "sg:phone":"+49 721/44088",
    "sg:postcode":"76227",
    "sg:province":"Baden-W\u00fcrttemberg",
    "wof:name":"Karch",
    "wof:placetype":"venue"
},
  "geometry": {"coordinates":[8.4723701477,48.9990959167],"type":"Point"}
}