{
  "type": "Feature",
  "properties": {
    "iso:country":"DE",
    "sg:address":"Mehringdamm 72",
    "sg:city":"Berlin",
    "sg:phone":"+49 30/7859742",
    "sg:postcode":"10961",
    "sg:province":"Berlin",
    "wof:name":"Pizzeria Primavera",
    "wof:placetype":"venue"
},
  "geometry": {"coordinates":[13.3861923218,52.4903030396],"type":"Point"}
}