{
  "type": "Feature",
  "properties": {
    "iso:country":"DE",
    "sg:address":"Bindingstr. 13",
    "sg:city":"Frankfurt",
    "sg:phone":"+49 69/622369",
    "sg:postcode":"60598",
    "sg:province":"Hessen",
    "wof:name":"Glaserei Dikel Gmbh",
    "wof:placetype":"venue"
},
  "geometry": {"coordinates":[8.6894731522,50.0980453491],"type":"Point"}
}