{
  "type": "Feature",
  "properties": {
    "iso:country":"DE",
    "sg:address":"Goethestr. 8",
    "sg:city":"Ronneburg",
    "sg:phone":"+49 36602/22771",
    "sg:postcode":"07580",
    "sg:province":"Th\u00fcringen",
    "wof:name":"Knut Lechner",
    "wof:placetype":"venue"
},
  "geometry": {"coordinates":[12.1854810715,50.8644828796],"type":"Point"}
}