{
  "type": "Feature",
  "properties": {
    "iso:country":"DE",
    "sg:address":"Friedensstr. 29",
    "sg:city":"Schwerin",
    "sg:phone":"+49 385/731400",
    "sg:postcode":"19053",
    "sg:province":"Mecklenburg-Vorpommern",
    "wof:name":"Dr. J. Rost Steuerberater",
    "wof:placetype":"venue"
},
  "geometry": {"coordinates":[11.4043951035,53.631187439],"type":"Point"}
}