{
  "type": "Feature",
  "properties": {
    "iso:country":"DE",
    "sg:address":"August-Bebel-Str. 2",
    "sg:city":"Geyer",
    "sg:phone":"+49 37346/1768",
    "sg:postcode":"09468",
    "sg:province":"Sachsen",
    "wof:name":"Reinhold Hofmann",
    "wof:placetype":"venue"
},
  "geometry": {"coordinates":[12.9225606918,50.6244468689],"type":"Point"}
}