{
  "type": "Feature",
  "properties": {
    "iso:country":"DE",
    "sg:address":"Max-Planck-Str. 19A",
    "sg:city":"Erkrath",
    "sg:phone":"+49 211/2092015",
    "sg:postcode":"40699",
    "sg:province":"Nordrhein-Westfalen",
    "wof:name":"Rottec Drucklufttechnik E. K.",
    "wof:placetype":"venue"
},
  "geometry": {"coordinates":[6.9345002174,51.1994590759],"type":"Point"}
}