{
  "type": "Feature",
  "properties": {
    "iso:country":"DE",
    "sg:address":"Homburger Str. 28",
    "sg:city":"Karben",
    "sg:phone":"+49 6039/3434",
    "sg:postcode":"61184",
    "sg:province":"Hessen",
    "wof:name":"M. Kraft Tabakwaren",
    "wof:placetype":"venue"
},
  "geometry": {"coordinates":[8.7727489471,50.22914505],"type":"Point"}
}