{
  "type": "Feature",
  "properties": {
    "iso:country":"DE",
    "sg:address":"Dieselstr. 22",
    "sg:city":"Karben",
    "sg:postcode":"61184",
    "sg:province":"Hessen",
    "wof:name":"Zinnecker Werbung Werbegestaltung Gmbh",
    "wof:placetype":"venue"
},
  "geometry": {"coordinates":[8.762813,50.223698],"type":"Point"}
}