{
  "type": "Feature",
  "properties": {
    "iso:country":"DE",
    "sg:address":"Berliner Str. 21 a",
    "sg:city":"Hammelburg",
    "sg:phone":"+49 9732/1090",
    "sg:postcode":"97762",
    "sg:province":"Bayern",
    "wof:name":"Optik-heenes Kg",
    "wof:placetype":"venue"
},
  "geometry": {"coordinates":[9.8996810913,50.1172790527],"type":"Point"}
}