{
  "type": "Feature",
  "properties": {
    "iso:country":"DE",
    "sg:address":"Bautzener Str. 56",
    "sg:city":"Gro\u00dfpostwitz",
    "sg:phone":"+49 3591/304371",
    "sg:postcode":"02692",
    "sg:province":"Sachsen",
    "wof:name":"Ralf R\u00f6ber",
    "wof:placetype":"venue"
},
  "geometry": {"coordinates":[14.441783905,51.136341095],"type":"Point"}
}