{
  "type": "Feature",
  "properties": {
    "iso:country":"DE",
    "sg:address":"Blissestr. 63",
    "sg:city":"Berlin",
    "sg:phone":"+49 30/85726006",
    "sg:postcode":"10713",
    "sg:province":"Berlin",
    "wof:name":"Peter Pietsch Rechtsanwalt Und Notar",
    "wof:placetype":"venue"
},
  "geometry": {"coordinates":[13.320558548,52.4795074463],"type":"Point"}
}