{
  "type": "Feature",
  "properties": {
    "iso:country":"DE",
    "sg:address":"Ahornweg 3",
    "sg:city":"Genshagen",
    "sg:phone":"+49 3378/8900",
    "sg:postcode":"14974",
    "sg:province":"Brandenburg",
    "wof:name":"Electronic Partner Handel Gmbh Nl Bln. Brdbg.-park",
    "wof:placetype":"venue"
},
  "geometry": {"coordinates":[13.2615060806,52.3008117676],"type":"Point"}
}