{
  "type": "Feature",
  "properties": {
    "iso:country":"DE",
    "sg:address":"Immenst\u00e4dter Str. 20",
    "sg:city":"Kempten",
    "sg:postcode":"87435",
    "sg:province":"Bayern",
    "wof:name":"Alpenl\u00e4ndische-naturholz Gmbh",
    "wof:placetype":"venue"
},
  "geometry": {"coordinates":[10.311226,47.720528],"type":"Point"}
}