{
  "type": "Feature",
  "properties": {
    "iso:country":"DE",
    "sg:address":"Kirchenbollenbacher Str. 14",
    "sg:city":"Idar-Oberstein",
    "sg:phone":"+49 6784/2476",
    "sg:postcode":"55743",
    "sg:province":"Rheinland-Pfalz",
    "wof:name":"Herbert Grammes",
    "wof:placetype":"venue"
},
  "geometry": {"coordinates":[7.410565,49.693249],"type":"Point"}
}