{
  "type": "Feature",
  "properties": {
    "iso:country":"DE",
    "sg:address":"Hessenstr. 17",
    "sg:city":"Hungen",
    "sg:phone":"+49 6402/50267",
    "sg:postcode":"35410",
    "sg:province":"Hessen",
    "wof:name":"Kammer",
    "wof:placetype":"venue"
},
  "geometry": {"coordinates":[8.923638,50.443127],"type":"Point"}
}