{
  "type": "Feature",
  "properties": {
    "iso:country":"DE",
    "sg:address":"Bocholter Str. 26",
    "sg:city":"Oberhausen",
    "sg:phone":"+49 208/608161",
    "sg:postcode":"46119",
    "sg:province":"Nordrhein-Westfalen",
    "wof:name":"C. Gosewinkel",
    "wof:placetype":"venue"
},
  "geometry": {"coordinates":[6.8839349747,51.5336303711],"type":"Point"}
}