{
  "type": "Feature",
  "properties": {
    "iso:country":"DE",
    "sg:address":"Lochhamer Str. 13",
    "sg:city":"Planegg",
    "sg:phone":"+49 89/85652200",
    "sg:postcode":"82152",
    "sg:province":"Bayern",
    "wof:name":"M-quadrat Beteiligungsverwaltung Gmbh",
    "wof:placetype":"venue"
},
  "geometry": {"coordinates":[11.451725,48.110714],"type":"Point"}
}