{
  "type": "Feature",
  "properties": {
    "iso:country":"DE",
    "sg:address":"Luisenstr. 8",
    "sg:city":"L\u00f6rrach",
    "sg:phone":"+49 7621/84374",
    "sg:postcode":"79539",
    "sg:province":"Baden-W\u00fcrttemberg",
    "wof:name":"W. Klein",
    "wof:placetype":"venue"
},
  "geometry": {"coordinates":[7.6627907753,47.6157531738],"type":"Point"}
}