{
  "type": "Feature",
  "properties": {
    "iso:country":"DE",
    "sg:address":"Suchsdorfer Weg 122",
    "sg:city":"Kronshagen",
    "sg:phone":"+49 431/3198666",
    "sg:postcode":"24119",
    "sg:province":"Schleswig-Holstein",
    "wof:name":"Heizungs- Und L\u00fcftungstechnik Rolf Schultze",
    "wof:placetype":"venue"
},
  "geometry": {"coordinates":[10.0811471939,54.340839386],"type":"Point"}
}