{
  "type": "Feature",
  "properties": {
    "iso:country":"DE",
    "sg:address":"Am Kap 3",
    "sg:city":"Norderney",
    "sg:phone":"+49 4932/2102",
    "sg:postcode":"26548",
    "sg:province":"Niedersachsen",
    "wof:name":"R. Bermuth",
    "wof:placetype":"venue"
},
  "geometry": {"coordinates":[7.1558389664,53.7107887268],"type":"Point"}
}