{
  "type": "Feature",
  "properties": {
    "iso:country":"DE",
    "sg:address":"Riegelsteiner Str. 2",
    "sg:city":"Plech",
    "sg:phone":"+49 9244/281",
    "sg:postcode":"91287",
    "sg:province":"Bayern",
    "wof:name":"Hutzler & Fleischer Ohg",
    "wof:placetype":"venue"
},
  "geometry": {"coordinates":[11.4672660828,49.6503791809],"type":"Point"}
}