{
  "type": "Feature",
  "properties": {
    "iso:country":"DE",
    "sg:address":"Lorscher Str. 15",
    "sg:city":"Leingarten",
    "sg:phone":"+49 7131/900430",
    "sg:postcode":"74211",
    "sg:province":"Baden-W\u00fcrttemberg",
    "wof:name":"Ges. F\u00f6rderg. Und Reha- Bilitation Brackenheim",
    "wof:placetype":"venue"
},
  "geometry": {"coordinates":[9.1094064713,49.1455345154],"type":"Point"}
}