{
  "type": "Feature",
  "properties": {
    "iso:country":"DE",
    "sg:address":"Wernerstr. 61",
    "sg:city":"Ludwigsburg",
    "sg:phone":"+49 7141/462039",
    "sg:postcode":"71636",
    "sg:province":"Baden-W\u00fcrttemberg",
    "wof:name":"Theo H\u00e4rlen",
    "wof:placetype":"venue"
},
  "geometry": {"coordinates":[9.1736593246,48.89503479],"type":"Point"}
}