{
  "type": "Feature",
  "properties": {
    "iso:country":"DE",
    "sg:address":"Heidelberger Str. 49",
    "sg:city":"Edingen-Neckarhausen",
    "sg:phone":"+49 6203/85726",
    "sg:postcode":"68535",
    "sg:province":"Baden-W\u00fcrttemberg",
    "wof:name":"U. Heil",
    "wof:placetype":"venue"
},
  "geometry": {"coordinates":[8.611963,49.448475],"type":"Point"}
}