{
  "type": "Feature",
  "properties": {
    "iso:country":"DE",
    "sg:address":"Mozartstrasse 16",
    "sg:city":"Oftersheim",
    "sg:phone":"+49 6202",
    "sg:postcode":"68723",
    "sg:province":"Baden-W\u00fcrttemberg",
    "wof:name":"B\u00fcro F\u00fcr Gestaltung Raum M\u00f6bel Klaus Mergenthaler",
    "wof:placetype":"venue"
},
  "geometry": {"coordinates":[8.5852842331,49.3710861206],"type":"Point"}
}