{
  "type": "Feature",
  "properties": {
    "iso:country":"DE",
    "sg:address":"Bunter Weg 8-9",
    "sg:city":"Magdeburg",
    "sg:postcode":"39118",
    "sg:province":"Sachsen-Anhalt",
    "wof:name":"Sigrid Franke",
    "wof:placetype":"venue"
},
  "geometry": {"coordinates":[11.613624,52.097057],"type":"Point"}
}