{
  "type": "Feature",
  "properties": {
    "iso:country":"DE",
    "sg:address":"Dorfstr. 37",
    "sg:city":"L\u00f6bau",
    "sg:phone":"+49 3585/402321",
    "sg:postcode":"02708",
    "sg:province":"Sachsen",
    "wof:name":"U. Lehmann",
    "wof:placetype":"venue"
},
  "geometry": {"coordinates":[14.685891,51.074493],"type":"Point"}
}