{
  "type": "Feature",
  "properties": {
    "iso:country":"DE",
    "sg:address":"Elmenhorster Chaussee 27 b",
    "sg:city":"S\u00fclfeld",
    "sg:phone":"+49 4537/530",
    "sg:postcode":"23867",
    "sg:province":"Schleswig-Holstein",
    "wof:name":"Gerhard Gielow",
    "wof:placetype":"venue"
},
  "geometry": {"coordinates":[10.23263,53.79644],"type":"Point"}
}