{
  "type": "Feature",
  "properties": {
    "iso:country":"DE",
    "sg:address":"Rosenstr. 17",
    "sg:city":"Spraitbach",
    "sg:phone":"+49 7176/891",
    "sg:postcode":"73565",
    "sg:province":"Baden-W\u00fcrttemberg",
    "wof:name":"Hubertus Wolf Unternehmensberatung",
    "wof:placetype":"venue"
},
  "geometry": {"coordinates":[9.7698802948,48.8848114014],"type":"Point"}
}