{
  "type": "Feature",
  "properties": {
    "iso:country":"DE",
    "sg:address":"Breitscheidplatz 1",
    "sg:city":"Ballenstedt",
    "sg:phone":"+49 39483/9480",
    "sg:postcode":"06493",
    "sg:province":"Sachsen-Anhalt",
    "wof:name":"Ballenstedter Elektroservice Gmbh",
    "wof:placetype":"venue"
},
  "geometry": {"coordinates":[11.23812,51.721279],"type":"Point"}
}