{
  "type": "Feature",
  "properties": {
    "iso:country":"DE",
    "sg:address":"Alte Str. 69",
    "sg:city":"Ochsenhausen",
    "sg:phone":"+49 7352/8729",
    "sg:postcode":"88416",
    "sg:province":"Baden-W\u00fcrttemberg",
    "wof:name":"Gerd M\u00fcller",
    "wof:placetype":"venue"
},
  "geometry": {"coordinates":[9.9527101517,48.0697555542],"type":"Point"}
}