{
  "type": "Feature",
  "properties": {
    "iso:country":"DE",
    "sg:address":"Weierle 2",
    "sg:city":"Bernau",
    "sg:phone":"+49 7675/671",
    "sg:postcode":"79872",
    "sg:province":"Baden-W\u00fcrttemberg",
    "wof:name":"G\u00e4stehaus Feriendorf Rechbergblick",
    "wof:placetype":"venue"
},
  "geometry": {"coordinates":[8.0362987518,47.8017158508],"type":"Point"}
}