{
  "type": "Feature",
  "properties": {
    "iso:country":"DE",
    "sg:address":"Industriestr. 5",
    "sg:city":"Werl",
    "sg:phone":"+49 2922/84645",
    "sg:postcode":"59457",
    "sg:province":"Nordrhein-Westfalen",
    "wof:name":"Schaffitzel Gmbh & Co.",
    "wof:placetype":"venue"
},
  "geometry": {"coordinates":[7.923413,51.559467],"type":"Point"}
}