{
  "type": "Feature",
  "properties": {
    "iso:country":"DE",
    "sg:address":"Faunastr. 1 a",
    "sg:city":"D\u00fcsseldorf",
    "sg:phone":"+49 211/461513",
    "sg:postcode":"40239",
    "sg:province":"Nordrhein-Westfalen",
    "wof:name":"Ursula Muscheler-zehres Architektin",
    "wof:placetype":"venue"
},
  "geometry": {"coordinates":[6.804774,51.239525],"type":"Point"}
}