{
  "type": "Feature",
  "properties": {
    "iso:country":"DE",
    "sg:address":"Langenbiebererstra\u00dfe 10",
    "sg:city":"Hofbieber",
    "sg:phone":"+49 6657/1791",
    "sg:postcode":"36145",
    "sg:province":"Hessen",
    "wof:name":"Weber Inh. Lothar Stock",
    "wof:placetype":"venue"
},
  "geometry": {"coordinates":[9.83762,50.5858],"type":"Point"}
}