{
  "type": "Feature",
  "properties": {
    "iso:country":"DE",
    "sg:address":"S\u00fcdenfeldmark 7",
    "sg:city":"Bad Driburg",
    "sg:phone":"+49 5253/2557",
    "sg:postcode":"33014",
    "sg:province":"Nordrhein-Westfalen",
    "wof:name":"Pension B. Ewers",
    "wof:placetype":"venue"
},
  "geometry": {"coordinates":[9.0082273483,51.7194862366],"type":"Point"}
}