{
  "type": "Feature",
  "properties": {
    "iso:country":"DE",
    "sg:address":"Dohmanns Kamp 10",
    "sg:city":"Essen",
    "sg:phone":"+49 201/774917",
    "sg:postcode":"45130",
    "sg:province":"Nordrhein-Westfalen",
    "wof:name":"Colligs Gmbh",
    "wof:placetype":"venue"
},
  "geometry": {"coordinates":[7.0080018044,51.4389038086],"type":"Point"}
}