{
  "type": "Feature",
  "properties": {
    "iso:country":"DE",
    "sg:address":"Bengeser Str. 72",
    "sg:city":"P\u00fcttlingen",
    "sg:phone":"+49 6898/66175",
    "sg:postcode":"66346",
    "sg:province":"Saarland",
    "wof:name":"Albert Schmidt",
    "wof:placetype":"venue"
},
  "geometry": {"coordinates":[6.891425,49.283268],"type":"Point"}
}