{
  "type": "Feature",
  "properties": {
    "iso:country":"DE",
    "sg:address":"Ostseestr. 15-21",
    "sg:city":"Berlin",
    "sg:phone":"+49 4930/421920",
    "sg:postcode":"10409",
    "sg:province":"Berlin",
    "wof:name":"Bfh Berliner Fachhandel Gmbh",
    "wof:placetype":"venue"
},
  "geometry": {"coordinates":[13.4333143234,52.5502662659],"type":"Point"}
}