{
  "type": "Feature",
  "properties": {
    "iso:country":"DE",
    "sg:address":"Markt 18",
    "sg:city":"Lutherstadt Eisleben",
    "sg:phone":"+49 3475/602274",
    "sg:postcode":"06295",
    "sg:province":"Sachsen-Anhalt",
    "wof:name":"L\u00f6wen-apotheke",
    "wof:placetype":"venue"
},
  "geometry": {"coordinates":[11.54779,51.52874],"type":"Point"}
}