{
  "type": "Feature",
  "properties": {
    "iso:country":"DE",
    "sg:address":"Buterlandstr. 51",
    "sg:city":"Gronau",
    "sg:phone":"+49 2562/3646",
    "sg:postcode":"48599",
    "sg:province":"Nordrhein-Westfalen",
    "wof:name":"Gastst\u00e4tte Franz Nieuwmeyer",
    "wof:placetype":"venue"
},
  "geometry": {"coordinates":[7.0055828094,52.2104225159],"type":"Point"}
}