{
  "type": "Feature",
  "properties": {
    "iso:country":"DE",
    "sg:address":"Meinekestr. 22",
    "sg:city":"Berlin",
    "sg:postcode":"10719",
    "sg:province":"Berlin",
    "wof:name":"Ddc Theta Neue L\u00e4nder Projekt- Grundst\u00fccks- Und Verw. Gmbh &",
    "wof:placetype":"venue"
},
  "geometry": {"coordinates":[13.329249382,52.50182724],"type":"Point"}
}