{
  "type": "Feature",
  "properties": {
    "iso:country":"DE",
    "sg:address":"Provinzialstr. 168",
    "sg:city":"Wadgassen",
    "sg:phone":"+49 6834/41021",
    "sg:postcode":"66787",
    "sg:province":"Saarland",
    "wof:name":"Wib Gmbh",
    "wof:placetype":"venue"
},
  "geometry": {"coordinates":[6.8195061684,49.2509498596],"type":"Point"}
}