{
  "type": "Feature",
  "properties": {
    "iso:country":"DE",
    "sg:address":"\u00c4u\u00dfere Crimmitschauer Str. 97",
    "sg:city":"Meerane",
    "sg:phone":"+49 3764/4288",
    "sg:postcode":"08393",
    "sg:province":"Sachsen",
    "wof:name":"Flossi",
    "wof:placetype":"venue"
},
  "geometry": {"coordinates":[12.448720932,50.8433227539],"type":"Point"}
}