{
  "type": "Feature",
  "properties": {
    "iso:country":"DE",
    "sg:address":"Potsdamer Str. 120 a",
    "sg:city":"Ludwigsfelde",
    "sg:phone":"+49 3378/870044",
    "sg:postcode":"14974",
    "sg:province":"Brandenburg",
    "wof:name":"Brunnen-apotheke Dr. Dieter Wendorff",
    "wof:placetype":"venue"
},
  "geometry": {"coordinates":[13.24609,52.30925],"type":"Point"}
}