{
  "type": "Feature",
  "properties": {
    "iso:country":"DE",
    "sg:address":"Theresenstr. 18",
    "sg:city":"Betzdorf",
    "sg:phone":"+49 2741/24782",
    "sg:postcode":"57518",
    "sg:province":"Rheinland-Pfalz",
    "wof:name":"Helga Prinz U. Heinrich Bruche",
    "wof:placetype":"venue"
},
  "geometry": {"coordinates":[7.854924202,50.7948493958],"type":"Point"}
}