{
  "type": "Feature",
  "properties": {
    "iso:country":"DE",
    "sg:address":"M\u00fchlstr. 15",
    "sg:city":"Lichtenstein",
    "sg:phone":"+49 7129/2397",
    "sg:postcode":"72805",
    "sg:province":"Baden-W\u00fcrttemberg",
    "wof:name":"Eugen Beck",
    "wof:placetype":"venue"
},
  "geometry": {"coordinates":[9.258234,48.434052],"type":"Point"}
}