{
  "type": "Feature",
  "properties": {
    "iso:country":"DE",
    "sg:address":"Hermann-Hesse-Str. 15",
    "sg:city":"Linkenheim-Hochstetten",
    "sg:phone":"+49 7247/946565",
    "sg:postcode":"76351",
    "sg:province":"Baden-W\u00fcrttemberg",
    "wof:name":"A. Kirst\u00e4tter",
    "wof:placetype":"venue"
},
  "geometry": {"coordinates":[8.409153,49.13496],"type":"Point"}
}