{
  "type": "Feature",
  "properties": {
    "iso:country":"DE",
    "sg:address":"Schie\u00dfhausstr. 185",
    "sg:city":"Neuburg",
    "sg:phone":"+49 8431/2746",
    "sg:postcode":"86633",
    "sg:province":"Bayern",
    "wof:name":"Manfred H\u00e4usler",
    "wof:placetype":"venue"
},
  "geometry": {"coordinates":[11.184209,48.734909],"type":"Point"}
}