{
  "type": "Feature",
  "properties": {
    "iso:country":"DE",
    "sg:address":"Lange Str. 65",
    "sg:city":"F\u00fcrth",
    "sg:phone":"+49 911/970750",
    "sg:postcode":"90762",
    "sg:province":"Bayern",
    "wof:name":"Da Kapo Kreative Werbung Gmbh",
    "wof:placetype":"venue"
},
  "geometry": {"coordinates":[11.0057458878,49.4689407349],"type":"Point"}
}