{
  "type": "Feature",
  "properties": {
    "iso:country":"DE",
    "sg:address":"Stumsdorfer Str. 3",
    "sg:city":"Z\u00f6rbig",
    "sg:postcode":"06780",
    "sg:province":"Sachsen-Anhalt",
    "wof:name":"Wer Shk-gro\u00dfhandel",
    "wof:placetype":"venue"
},
  "geometry": {"coordinates":[12.1115398407,51.6275634766],"type":"Point"}
}