{
  "type": "Feature",
  "properties": {
    "iso:country":"DE",
    "sg:address":"Katharinenstr. 55",
    "sg:city":"Friedrichshafen",
    "sg:phone":"+49 7541/31408",
    "sg:postcode":"88045",
    "sg:province":"Baden-W\u00fcrttemberg",
    "wof:name":"Bodensee-bibliothek",
    "wof:placetype":"venue"
},
  "geometry": {"coordinates":[9.476727,47.657295],"type":"Point"}
}