{
  "type": "Feature",
  "properties": {
    "iso:country":"DE",
    "sg:address":"Schillerstr 44",
    "sg:city":"Winnenden",
    "sg:phone":"+49 7195/174051",
    "sg:postcode":"71364",
    "sg:province":"Baden-W\u00fcrttemberg",
    "wof:name":"Gewitec Me\u00dftechnik Und Beratung Gmbh",
    "wof:placetype":"venue"
},
  "geometry": {"coordinates":[9.4072704315,48.8693885803],"type":"Point"}
}