{
  "type": "Feature",
  "properties": {
    "iso:country":"DE",
    "sg:address":"Maxstr. 17",
    "sg:city":"Bochum",
    "sg:phone":"+49 234/686834",
    "sg:postcode":"44793",
    "sg:province":"Nordrhein-Westfalen",
    "wof:name":"Uenlue Tandura",
    "wof:placetype":"venue"
},
  "geometry": {"coordinates":[7.2050609589,51.4770317078],"type":"Point"}
}