{
  "type": "Feature",
  "properties": {
    "iso:country":"DE",
    "sg:address":"G\u00f6rlitzer Str. 5",
    "sg:city":"Wagh\u00e4usel",
    "sg:phone":"+49 7254/950053",
    "sg:postcode":"68753",
    "sg:province":"Baden-W\u00fcrttemberg",
    "wof:name":"Lux Immobilienverwaltung Gmbh",
    "wof:placetype":"venue"
},
  "geometry": {"coordinates":[8.5086517334,49.2265892029],"type":"Point"}
}