{
  "type": "Feature",
  "properties": {
    "iso:country":"DE",
    "sg:address":"Karlsplatz 9",
    "sg:city":"Altentreptow",
    "sg:postcode":"17087",
    "sg:province":"Mecklenburg-Vorpommern",
    "wof:name":"H & A Bau Gmbh",
    "wof:placetype":"venue"
},
  "geometry": {"coordinates":[13.249686,53.697018],"type":"Point"}
}