{
  "type": "Feature",
  "properties": {
    "iso:country":"DE",
    "sg:address":"Wilhelmstr. 10",
    "sg:city":"Wesel",
    "sg:phone":"+49 281/21793",
    "sg:postcode":"46483",
    "sg:province":"Nordrhein-Westfalen",
    "wof:name":"Scala-theater",
    "wof:placetype":"venue"
},
  "geometry": {"coordinates":[6.6238532066,51.6565246582],"type":"Point"}
}