{
  "type": "Feature",
  "properties": {
    "iso:country":"DE",
    "sg:address":"Hauptstr. 190",
    "sg:city":"Heimbuchenthal",
    "sg:phone":"+49 6092/1509",
    "sg:postcode":"63872",
    "sg:province":"Bayern",
    "wof:name":"Pension O. Und H. B\u00fcttner",
    "wof:placetype":"venue"
},
  "geometry": {"coordinates":[9.2937526703,49.882598877],"type":"Point"}
}