{
  "type": "Feature",
  "properties": {
    "iso:country":"DE",
    "sg:address":"Rauer Werth 4",
    "sg:city":"Wuppertal",
    "sg:phone":"+49 202/559933",
    "sg:postcode":"42275",
    "sg:province":"Nordrhein-Westfalen",
    "wof:name":"Meike Hilgenberg Steuerberaterin",
    "wof:placetype":"venue"
},
  "geometry": {"coordinates":[7.2082247734,51.274105072],"type":"Point"}
}