{
  "type": "Feature",
  "properties": {
    "iso:country":"DE",
    "sg:address":"K\u00f6nigshagener Ring 1",
    "sg:city":"Bad Lauterberg",
    "sg:phone":"+49 5524/4384",
    "sg:postcode":"37431",
    "sg:province":"Niedersachsen",
    "wof:name":"Alfred Wienrich",
    "wof:placetype":"venue"
},
  "geometry": {"coordinates":[10.382124,51.602928],"type":"Point"}
}