{
  "type": "Feature",
  "properties": {
    "iso:country":"DE",
    "sg:address":"Elisabethstr. 1",
    "sg:city":"Westerland",
    "sg:postcode":"25980",
    "sg:province":"Schleswig-Holstein",
    "wof:name":"Boardriders Club Sylt Inh. Roy Komorr E. K.",
    "wof:placetype":"venue"
},
  "geometry": {"coordinates":[8.301435,54.908939],"type":"Point"}
}