{
  "type": "Feature",
  "properties": {
    "iso:country":"DE",
    "sg:address":"Kaiserstr. 15",
    "sg:city":"K\u00f6ln",
    "sg:phone":"+49 2203/292178",
    "sg:postcode":"51145",
    "sg:province":"Nordrhein-Westfalen",
    "wof:name":"A. Enkler",
    "wof:placetype":"venue"
},
  "geometry": {"coordinates":[7.079068,50.880978],"type":"Point"}
}