{
  "type": "Feature",
  "properties": {
    "iso:country":"DE",
    "sg:address":"Ulrichstr. 14",
    "sg:city":"Aichach",
    "sg:phone":"+49 8251/827900",
    "sg:postcode":"86551",
    "sg:province":"Bayern",
    "wof:name":"Augusta-verlag E. K.",
    "wof:placetype":"venue"
},
  "geometry": {"coordinates":[11.1524496078,48.4697532654],"type":"Point"}
}