{
  "type": "Feature",
  "properties": {
    "iso:country":"DE",
    "sg:address":"Auf Der Trift 3",
    "sg:city":"Saarbr\u00fccken",
    "sg:phone":"+49 4968/9831013",
    "sg:postcode":"66127",
    "sg:province":"Saarland",
    "wof:name":"Gta Gesellschaft F. Transport-u. Aufbereitungstechnik Gmbh",
    "wof:placetype":"venue"
},
  "geometry": {"coordinates":[6.902105,49.227467],"type":"Point"}
}