{
  "type": "Feature",
  "properties": {
    "iso:country":"DE",
    "sg:address":"Uhlstr. 96",
    "sg:city":"Br\u00fchl",
    "sg:phone":"+49 2232/945100",
    "sg:postcode":"50321",
    "sg:province":"Nordrhein-Westfalen",
    "wof:name":"Giesler Brauerei Verwaltungs- Gmbh",
    "wof:placetype":"venue"
},
  "geometry": {"coordinates":[6.900842,50.825733],"type":"Point"}
}