{
  "type": "Feature",
  "properties": {
    "iso:country":"DE",
    "sg:address":"Weender Landstr. 13",
    "sg:city":"G\u00f6ttingen",
    "sg:phone":"+49 551/486507",
    "sg:postcode":"37073",
    "sg:province":"Niedersachsen",
    "wof:name":"Spielothek-automaten-freizeit- Center Gauselmann Gmbh & Co.",
    "wof:placetype":"venue"
},
  "geometry": {"coordinates":[9.9330120087,51.5404281616],"type":"Point"}
}