{
  "type": "Feature",
  "properties": {
    "iso:country":"DE",
    "sg:address":"Schwarzbachstr. 39",
    "sg:city":"Mettmann",
    "sg:postcode":"40822",
    "sg:province":"Nordrhein-Westfalen",
    "wof:name":"Kolp Beteiligungs Gmbh",
    "wof:placetype":"venue"
},
  "geometry": {"coordinates":[6.978149,51.253277],"type":"Point"}
}