{
  "type": "Feature",
  "properties": {
    "iso:country":"DE",
    "sg:address":"Tiefer Weg 22",
    "sg:city":"Sinsheim",
    "sg:phone":"+49 7261/63709",
    "sg:postcode":"74889",
    "sg:province":"Baden-W\u00fcrttemberg",
    "wof:name":"Adolf Baier",
    "wof:placetype":"venue"
},
  "geometry": {"coordinates":[8.8385820389,49.2440185547],"type":"Point"}
}