{
  "type": "Feature",
  "properties": {
    "iso:country":"DE",
    "sg:address":"Wieslensdorfer Str. 33",
    "sg:city":"Obersulm",
    "sg:phone":"+49 7130/450046",
    "sg:postcode":"74182",
    "sg:province":"Baden-W\u00fcrttemberg",
    "wof:name":"Ekasa Gmbh",
    "wof:placetype":"venue"
},
  "geometry": {"coordinates":[9.4074792862,49.1408462524],"type":"Point"}
}