{
  "type": "Feature",
  "properties": {
    "iso:country":"DE",
    "sg:address":"Deutelbacher Str. 19",
    "sg:city":"Jossgrund",
    "sg:phone":"+49 6059/229",
    "sg:postcode":"63637",
    "sg:province":"Hessen",
    "wof:name":"Hermann R\u00fcbsam",
    "wof:placetype":"venue"
},
  "geometry": {"coordinates":[9.475849,50.188709],"type":"Point"}
}