{
  "type": "Feature",
  "properties": {
    "iso:country":"DE",
    "sg:address":"Runtestr. 11",
    "sg:city":"Werl",
    "sg:postcode":"59457",
    "sg:province":"Nordrhein-Westfalen",
    "wof:name":"Brehm Gmbh",
    "wof:placetype":"venue"
},
  "geometry": {"coordinates":[7.89104,51.56361],"type":"Point"}
}