{
  "type": "Feature",
  "properties": {
    "iso:country":"DE",
    "sg:address":"Stauffenbergstr. 01",
    "sg:city":"Delitzsch",
    "sg:postcode":"04509",
    "sg:province":"Sachsen",
    "wof:name":"Simone Fraustein E. K.",
    "wof:placetype":"venue"
},
  "geometry": {"coordinates":[12.3296003342,51.535900116],"type":"Point"}
}