{
  "type": "Feature",
  "properties": {
    "iso:country":"DE",
    "sg:address":"Gartenstr. 46",
    "sg:city":"Radebeul",
    "sg:phone":"+49 351/8303006",
    "sg:postcode":"01445",
    "sg:province":"Sachsen",
    "wof:name":"Elektro-kontakt Radebeul Gmbh",
    "wof:placetype":"venue"
},
  "geometry": {"coordinates":[13.683613,51.09586],"type":"Point"}
}