{
  "type": "Feature",
  "properties": {
    "iso:country":"DE",
    "sg:address":"Dorfstr.",
    "sg:city":"L\u00fcdershagen",
    "sg:phone":"+49 38227/50320",
    "sg:postcode":"18314",
    "sg:province":"Mecklenburg-Vorpommern",
    "wof:name":"Hofgutprodukte L\u00fcdershagen Gmbh",
    "wof:placetype":"venue"
},
  "geometry": {"coordinates":[12.610024,54.305828],"type":"Point"}
}