{
  "type": "Feature",
  "properties": {
    "iso:country":"DE",
    "sg:address":"An der Windecke 20",
    "sg:city":"Wetter",
    "sg:phone":"+49 2335/6835",
    "sg:postcode":"58300",
    "sg:province":"Nordrhein-Westfalen",
    "wof:name":"Kath. Pfarramt St. Augustinus-monika",
    "wof:placetype":"venue"
},
  "geometry": {"coordinates":[7.3768539429,51.3764228821],"type":"Point"}
}