{
  "type": "Feature",
  "properties": {
    "iso:country":"DE",
    "sg:address":"Schmalbachstr. 2",
    "sg:city":"Ahlen",
    "sg:phone":"+49 4923/828560",
    "sg:postcode":"59227",
    "sg:province":"Nordrhein-Westfalen",
    "wof:name":"Wpm Gmbh & Co Kg",
    "wof:placetype":"venue"
},
  "geometry": {"coordinates":[7.9017591476,51.7668647766],"type":"Point"}
}