{
  "type": "Feature",
  "properties": {
    "iso:country":"DE",
    "sg:address":"Tauschaer Str. 6",
    "sg:city":"Dobra",
    "sg:phone":"+49 35240/72281",
    "sg:postcode":"01561",
    "sg:province":"Sachsen",
    "wof:name":"Agrargenossenschaft Eg",
    "wof:placetype":"venue"
},
  "geometry": {"coordinates":[13.631883,51.289631],"type":"Point"}
}