{
  "type": "Feature",
  "properties": {
    "iso:country":"DE",
    "sg:address":"Torstr. 16",
    "sg:city":"Hannover",
    "sg:postcode":"30169",
    "sg:province":"Niedersachsen",
    "wof:name":"Abr - Service Gmbh",
    "wof:placetype":"venue"
},
  "geometry": {"coordinates":[9.7443828583,52.3589515686],"type":"Point"}
}