{
  "type": "Feature",
  "properties": {
    "iso:country":"DE",
    "sg:address":"Klosterstr. 61",
    "sg:city":"Mainz",
    "sg:phone":"+49 6131/42979",
    "sg:postcode":"55124",
    "sg:province":"Rheinland-Pfalz",
    "wof:name":"D. J. Kropp",
    "wof:placetype":"venue"
},
  "geometry": {"coordinates":[8.2057142258,49.9980316162],"type":"Point"}
}