{
  "type": "Feature",
  "properties": {
    "iso:country":"DE",
    "sg:address":"Bahnhofstr. 14",
    "sg:city":"Vilsbiburg",
    "sg:phone":"+49 8741/4900",
    "sg:postcode":"84137",
    "sg:province":"Bayern",
    "wof:name":"Norbert Weber Architekt",
    "wof:placetype":"venue"
},
  "geometry": {"coordinates":[12.34794,48.447399],"type":"Point"}
}