{
  "type": "Feature",
  "properties": {
    "iso:country":"DE",
    "sg:address":"Nr. 13",
    "sg:city":"Retschow",
    "sg:postcode":"18211",
    "sg:province":"Mecklenburg-Vorpommern",
    "wof:name":"Ev.-luth. Kirche",
    "wof:placetype":"venue"
},
  "geometry": {"coordinates":[11.9776296616,54.1110305786],"type":"Point"}
}