{
  "type": "Feature",
  "properties": {
    "iso:country":"DE",
    "sg:address":"Am Lautengrund 1",
    "sg:city":"Marienberg",
    "sg:postcode":"09496",
    "sg:province":"Sachsen",
    "wof:name":"G\u00f6tze Tankstellen Gmbh",
    "wof:placetype":"venue"
},
  "geometry": {"coordinates":[13.1539039612,50.6582870483],"type":"Point"}
}