{
  "type": "Feature",
  "properties": {
    "iso:country":"DE",
    "sg:address":"Landshuter Str. 1",
    "sg:city":"Adlkofen",
    "sg:phone":"+49 8707/291",
    "sg:postcode":"84166",
    "sg:province":"Bayern",
    "wof:name":"Alter Wirt",
    "wof:placetype":"venue"
},
  "geometry": {"coordinates":[12.2646789551,48.5494689941],"type":"Point"}
}