{
  "type": "Feature",
  "properties": {
    "iso:country":"DE",
    "sg:address":"Cronenberger Str. 144",
    "sg:city":"Wuppertal",
    "sg:phone":"+49 202/421475",
    "sg:postcode":"42119",
    "sg:province":"Nordrhein-Westfalen",
    "wof:name":"R. Busch",
    "wof:placetype":"venue"
},
  "geometry": {"coordinates":[7.1463980675,51.2390632629],"type":"Point"}
}