{
  "type": "Feature",
  "properties": {
    "iso:country":"DE",
    "sg:address":"Gerburgisstr.1",
    "sg:city":"Greven",
    "sg:postcode":"48268",
    "sg:province":"Nordrhein-Westfalen",
    "wof:name":"Kommunikation & Internet Komplett",
    "wof:placetype":"venue"
},
  "geometry": {"coordinates":[7.613071,52.101871],"type":"Point"}
}