{
  "type": "Feature",
  "properties": {
    "iso:country":"DE",
    "sg:address":"Aurikelstieg 114",
    "sg:city":"Norderstedt",
    "sg:postcode":"22850",
    "sg:province":"Schleswig-Holstein",
    "wof:name":"Antonius Romberg Steuerberater",
    "wof:placetype":"venue"
},
  "geometry": {"coordinates":[9.9888267517,53.6907997131],"type":"Point"}
}