{
  "type": "Feature",
  "properties": {
    "iso:country":"DE",
    "sg:address":"Obere Breite Str. 7",
    "sg:city":"Ravensburg",
    "sg:phone":"+49 751/33348",
    "sg:postcode":"88212",
    "sg:province":"Baden-W\u00fcrttemberg",
    "wof:name":"Charivari",
    "wof:placetype":"venue"
},
  "geometry": {"coordinates":[9.611196,47.782539],"type":"Point"}
}