{
  "type": "Feature",
  "properties": {
    "iso:country":"DE",
    "sg:address":"Norderheverkoogstr.",
    "sg:city":"Osterhever",
    "sg:phone":"+49 4865/222",
    "sg:postcode":"25836",
    "sg:province":"Schleswig-Holstein",
    "wof:name":"F. Brandt",
    "wof:placetype":"venue"
},
  "geometry": {"coordinates":[8.76843,54.398556],"type":"Point"}
}