{
  "type": "Feature",
  "properties": {
    "iso:country":"DE",
    "sg:address":"Ricklinger Str. 128",
    "sg:city":"Hannover",
    "sg:phone":"+49 511/4583404",
    "sg:postcode":"30449",
    "sg:province":"Niedersachsen",
    "wof:name":"Karakaya B\u00e4ckerei Gmbh",
    "wof:placetype":"venue"
},
  "geometry": {"coordinates":[9.719854,52.357952],"type":"Point"}
}