{
  "type": "Feature",
  "properties": {
    "iso:country":"DE",
    "sg:address":"Kirchbergstr. 20",
    "sg:city":"Wildsteig",
    "sg:phone":"+49 8867/378",
    "sg:postcode":"82409",
    "sg:province":"Bayern",
    "wof:name":"Mathias Lang",
    "wof:placetype":"venue"
},
  "geometry": {"coordinates":[10.934361,47.702641],"type":"Point"}
}