{
  "type": "Feature",
  "properties": {
    "iso:country":"DE",
    "sg:address":"Gartenstr. 29",
    "sg:city":"Oberursel",
    "sg:phone":"+49 6171/79006",
    "sg:postcode":"61440",
    "sg:province":"Hessen",
    "wof:name":"Paul Steinbach",
    "wof:placetype":"venue"
},
  "geometry": {"coordinates":[8.580796,50.182152],"type":"Point"}
}