{
  "type": "Feature",
  "properties": {
    "iso:country":"DE",
    "sg:address":"Vor dem Tore 76",
    "sg:city":"Duisburg",
    "sg:phone":"+49 203/727320",
    "sg:postcode":"47279",
    "sg:province":"Nordrhein-Westfalen",
    "wof:name":"Vereinsgastst\u00e4tte Clubheim Etus",
    "wof:placetype":"venue"
},
  "geometry": {"coordinates":[6.8127717972,51.3861274719],"type":"Point"}
}