{
  "type": "Feature",
  "properties": {
    "iso:country":"DE",
    "sg:address":"Eichenstr 1",
    "sg:city":"V\u00f6hringen",
    "sg:phone":"+49 7454/3913",
    "sg:postcode":"72189",
    "sg:province":"Baden-W\u00fcrttemberg",
    "wof:name":"Willy Wirtz",
    "wof:placetype":"venue"
},
  "geometry": {"coordinates":[10.085657,48.283409],"type":"Point"}
}