{
  "type": "Feature",
  "properties": {
    "iso:country":"DE",
    "sg:address":"Nieder-Ramst\u00e4dter-Str. 32",
    "sg:city":"Ober-Ramstadt",
    "sg:phone":"+49 6154/1550",
    "sg:postcode":"64372",
    "sg:province":"Hessen",
    "wof:name":"Foto-atelier Breitwieser",
    "wof:placetype":"venue"
},
  "geometry": {"coordinates":[8.7413635254,49.8311080933],"type":"Point"}
}