{
  "type": "Feature",
  "properties": {
    "iso:country":"DE",
    "sg:address":"Br\u00fchl 23",
    "sg:city":"Werdau",
    "sg:phone":"+49 3761/700650",
    "sg:postcode":"08412",
    "sg:province":"Sachsen",
    "wof:name":"Physiotherapie",
    "wof:placetype":"venue"
},
  "geometry": {"coordinates":[12.375047,50.734943],"type":"Point"}
}