{
  "type": "Feature",
  "properties": {
    "iso:country":"DE",
    "sg:address":"Marktstr. 8",
    "sg:city":"Soest",
    "sg:postcode":"59494",
    "sg:province":"Nordrhein-Westfalen",
    "wof:name":"St. Petri-pauli- Kirchengemeinde",
    "wof:placetype":"venue"
},
  "geometry": {"coordinates":[8.105463028,51.5713844299],"type":"Point"}
}