{
  "type": "Feature",
  "properties": {
    "iso:country":"DE",
    "sg:address":"Im Braunger\u00f6ll 19",
    "sg:city":"Frankfurt",
    "sg:phone":"+49 69/521582",
    "sg:postcode":"60431",
    "sg:province":"Hessen",
    "wof:name":"Walter Sch\u00e4fer",
    "wof:placetype":"venue"
},
  "geometry": {"coordinates":[8.649564743,50.1429405212],"type":"Point"}
}