{
  "type": "Feature",
  "properties": {
    "iso:country":"DE",
    "sg:address":"Im Bruch 29",
    "sg:city":"Seevetal",
    "sg:phone":"+49 4105/82348",
    "sg:postcode":"21220",
    "sg:province":"Niedersachsen",
    "wof:name":"Karin Geschke Steuerberaterin",
    "wof:placetype":"venue"
},
  "geometry": {"coordinates":[10.0477676392,53.4044570923],"type":"Point"}
}