{
  "type": "Feature",
  "properties": {
    "iso:country":"DE",
    "sg:address":"Eduard-Schmid-Str. 24",
    "sg:city":"M\u00fcnchen",
    "sg:phone":"+49 89/62500843",
    "sg:postcode":"81541",
    "sg:province":"Bayern",
    "wof:name":"Rmt Trading Gmbh",
    "wof:placetype":"venue"
},
  "geometry": {"coordinates":[11.5759963989,48.1244163513],"type":"Point"}
}