{
  "type": "Feature",
  "properties": {
    "iso:country":"DE",
    "sg:address":"Treverer Str. 2",
    "sg:city":"Detzem",
    "sg:phone":"+49 6507/4182",
    "sg:postcode":"54340",
    "sg:province":"Rheinland-Pfalz",
    "wof:name":"H. Bamberg",
    "wof:placetype":"venue"
},
  "geometry": {"coordinates":[6.8429288864,49.8257675171],"type":"Point"}
}