{
  "type": "Feature",
  "properties": {
    "iso:country":"DE",
    "sg:address":"Poppenb\u00fctteler Bogen 28",
    "sg:city":"Hamburg",
    "sg:phone":"+49 40/6061870",
    "sg:postcode":"22399",
    "sg:province":"Hamburg",
    "wof:name":"Scherwatzki Zerspanungstechnik",
    "wof:placetype":"venue"
},
  "geometry": {"coordinates":[10.069279,53.670498],"type":"Point"}
}