{
  "type": "Feature",
  "properties": {
    "iso:country":"DE",
    "sg:address":"Christophstr. 3",
    "sg:city":"T\u00fcbingen",
    "sg:phone":"+49 7071/93990",
    "sg:postcode":"72072",
    "sg:province":"Baden-W\u00fcrttemberg",
    "wof:name":"T. M. Kurcz Immobilienmakler",
    "wof:placetype":"venue"
},
  "geometry": {"coordinates":[9.0596647263,48.514957428],"type":"Point"}
}