{
  "type": "Feature",
  "properties": {
    "iso:country":"DE",
    "sg:address":"Lipper Weg 6",
    "sg:city":"Marl",
    "sg:phone":"+49 2365/4191",
    "sg:postcode":"45770",
    "sg:province":"Nordrhein-Westfalen",
    "wof:name":"Seniorenzentrum Der Awo",
    "wof:placetype":"venue"
},
  "geometry": {"coordinates":[7.125767,51.662571],"type":"Point"}
}