{
  "type": "Feature",
  "properties": {
    "iso:country":"DE",
    "sg:address":"Hache 1",
    "sg:city":"Engeln",
    "sg:phone":"+49 4247/376",
    "sg:postcode":"27305",
    "sg:province":"Niedersachsen",
    "wof:name":"Otto Butt",
    "wof:placetype":"venue"
},
  "geometry": {"coordinates":[8.905672,52.784988],"type":"Point"}
}