{
  "type": "Feature",
  "properties": {
    "iso:country":"DE",
    "sg:address":"Am Sand 1c",
    "sg:city":"Diera-Zehren",
    "sg:phone":"+49 3525/71860",
    "sg:postcode":"01665",
    "sg:province":"Sachsen",
    "wof:name":"Satztechnik Mei\u00dfen Gmbh",
    "wof:placetype":"venue"
},
  "geometry": {"coordinates":[13.4145383835,51.2199630737],"type":"Point"}
}