{
  "type": "Feature",
  "properties": {
    "iso:country":"DE",
    "sg:address":"Boldixumer Str. 11",
    "sg:city":"Wyk",
    "sg:phone":"+49 4681/1737",
    "sg:postcode":"25938",
    "sg:province":"Schleswig-Holstein",
    "wof:name":"Oluf Braren & B\u00f6rge Tramm Gbr",
    "wof:placetype":"venue"
},
  "geometry": {"coordinates":[8.5664377213,54.6913566589],"type":"Point"}
}