{
  "type": "Feature",
  "properties": {
    "iso:country":"DE",
    "sg:address":"Hessenknapp 47",
    "sg:city":"Ennigerloh",
    "sg:phone":"+49 2524/7660",
    "sg:postcode":"59320",
    "sg:province":"Nordrhein-Westfalen",
    "wof:name":"Heinrich Zumsande",
    "wof:placetype":"venue"
},
  "geometry": {"coordinates":[8.0774183273,51.8596687317],"type":"Point"}
}