{
  "type": "Feature",
  "properties": {
    "iso:country":"DE",
    "sg:address":"Hauptstr. 30",
    "sg:city":"M\u00f6ckm\u00fchl",
    "sg:phone":"+49 6298/1371",
    "sg:postcode":"74219",
    "sg:province":"Baden-W\u00fcrttemberg",
    "wof:name":"G. Wagner",
    "wof:placetype":"venue"
},
  "geometry": {"coordinates":[9.360616,49.323349],"type":"Point"}
}