{
  "type": "Feature",
  "properties": {
    "iso:country":"DE",
    "sg:address":"Oben Borgfelde 40",
    "sg:city":"Hamburg",
    "sg:postcode":"20535",
    "sg:province":"Hamburg",
    "wof:name":"Begebau Immobilien-beratungs- Verwaltungs- Gmbh",
    "wof:placetype":"venue"
},
  "geometry": {"coordinates":[10.05485,53.560089],"type":"Point"}
}