{
  "type": "Feature",
  "properties": {
    "iso:country":"DE",
    "sg:address":"Lingscheiderweg 3",
    "sg:city":"Meschede",
    "sg:phone":"+49 291/50550",
    "sg:postcode":"59872",
    "sg:province":"Nordrhein-Westfalen",
    "wof:name":"E. Pilz Gmbh",
    "wof:placetype":"venue"
},
  "geometry": {"coordinates":[8.330827713,51.3664894104],"type":"Point"}
}