{
  "type": "Feature",
  "properties": {
    "iso:country":"DE",
    "sg:address":"Augsburger Str. 655",
    "sg:city":"Stuttgart",
    "sg:phone":"+49 711/321766",
    "sg:postcode":"70329",
    "sg:province":"Baden-W\u00fcrttemberg",
    "wof:name":"Doris Rehm",
    "wof:placetype":"venue"
},
  "geometry": {"coordinates":[9.268222,48.764015],"type":"Point"}
}