{
  "type": "Feature",
  "properties": {
    "iso:country":"DE",
    "sg:address":"Ziegelstr. 12",
    "sg:city":"Leipzig",
    "sg:phone":"+49 34297/40923",
    "sg:postcode":"04288",
    "sg:province":"Sachsen",
    "wof:name":"G. Bothe",
    "wof:placetype":"venue"
},
  "geometry": {"coordinates":[12.469129,51.314163],"type":"Point"}
}