{
  "type": "Feature",
  "properties": {
    "iso:country":"DE",
    "sg:address":"Kufsteiner Str. 12",
    "sg:city":"Rosenheim",
    "sg:phone":"+49 8031/1880",
    "sg:postcode":"83022",
    "sg:province":"Bayern",
    "wof:name":"Raiffeisenbank, Rosenheim Eg",
    "wof:placetype":"venue"
},
  "geometry": {"coordinates":[12.12615,47.85313],"type":"Point"}
}