{
  "type": "Feature",
  "properties": {
    "iso:country":"DE",
    "sg:address":"Spieser Str. 87",
    "sg:city":"Spiesen-Elversberg",
    "sg:phone":"+49 6821/730962",
    "sg:postcode":"66583",
    "sg:province":"Saarland",
    "wof:name":"Digro Food-nonfood Discount Und Gro\u00dfhandels Gmbh",
    "wof:placetype":"venue"
},
  "geometry": {"coordinates":[7.1345210075,49.312084198],"type":"Point"}
}