{
  "type": "Feature",
  "properties": {
    "iso:country":"DE",
    "sg:address":"Ritterstr. 3",
    "sg:city":"Mutterstadt",
    "sg:phone":"+49 6234/7758",
    "sg:postcode":"67112",
    "sg:province":"Rheinland-Pfalz",
    "wof:name":"I. Blumhardt-sch\u00e4fer",
    "wof:placetype":"venue"
},
  "geometry": {"coordinates":[8.352848053,49.4461746216],"type":"Point"}
}