{
  "type": "Feature",
  "properties": {
    "iso:country":"DE",
    "sg:address":"Mahlsteinweg 6",
    "sg:city":"Westerhorn",
    "sg:phone":"+49 4127/285",
    "sg:postcode":"25364",
    "sg:province":"Schleswig-Holstein",
    "wof:name":"Ulrich Horn",
    "wof:placetype":"venue"
},
  "geometry": {"coordinates":[9.677778,53.860115],"type":"Point"}
}