{
  "type": "Feature",
  "properties": {
    "iso:country":"DE",
    "sg:address":"Am Bahndamm 4",
    "sg:city":"Stadtoldendorf",
    "sg:phone":"+49 5532/3371",
    "sg:postcode":"37627",
    "sg:province":"Niedersachsen",
    "wof:name":"Wolfgang Becker",
    "wof:placetype":"venue"
},
  "geometry": {"coordinates":[9.624512,51.87952],"type":"Point"}
}