{
  "type": "Feature",
  "properties": {
    "iso:country":"DE",
    "sg:address":"Industriestr 21",
    "sg:city":"Gr\u00f6benzell",
    "sg:phone":"+49 7171/18670",
    "sg:postcode":"82194",
    "sg:province":"Bayern",
    "wof:name":"Prodigital Softwaresysteme Gmbh",
    "wof:placetype":"venue"
},
  "geometry": {"coordinates":[9.753074646,48.7882766724],"type":"Point"}
}