{
  "type": "Feature",
  "properties": {
    "iso:country":"DE",
    "sg:address":"Landsberger Str. 44",
    "sg:city":"Mindelheim",
    "sg:phone":"+49 8261/76500",
    "sg:postcode":"87719",
    "sg:province":"Bayern",
    "wof:name":"Wassermann & Co. Gmbh",
    "wof:placetype":"venue"
},
  "geometry": {"coordinates":[10.5034189224,48.0479888916],"type":"Point"}
}