{
  "type": "Feature",
  "properties": {
    "iso:country":"DE",
    "sg:address":"Schuhstr. 46",
    "sg:city":"Hildesheim",
    "sg:phone":"+49 5121/134146",
    "sg:postcode":"31134",
    "sg:province":"Niedersachsen",
    "wof:name":"Betten-gerloff",
    "wof:placetype":"venue"
},
  "geometry": {"coordinates":[9.9528102875,52.150478363],"type":"Point"}
}