{
  "type": "Feature",
  "properties": {
    "iso:country":"DE",
    "sg:address":"Steinlestr. 23",
    "sg:city":"Frankfurt",
    "sg:phone":"+49 69/635578",
    "sg:postcode":"60596",
    "sg:province":"Hessen",
    "wof:name":"Mara Eggert",
    "wof:placetype":"venue"
},
  "geometry": {"coordinates":[8.6717672348,50.1012268066],"type":"Point"}
}