{
  "type": "Feature",
  "properties": {
    "iso:country":"DE",
    "sg:address":"Rotenberg 2",
    "sg:city":"Saterland",
    "sg:phone":"+49 4944/9292820",
    "sg:postcode":"26683",
    "sg:province":"Niedersachsen",
    "wof:name":"Nikko Presswerk Gmbh",
    "wof:placetype":"venue"
},
  "geometry": {"coordinates":[7.723065,53.061859],"type":"Point"}
}