{
  "type": "Feature",
  "properties": {
    "iso:country":"DE",
    "sg:address":"Breite Str. 12-13",
    "sg:city":"Neu K\u00f6nigsaue",
    "sg:phone":"+49 3473/2057",
    "sg:postcode":"06449",
    "sg:province":"Sachsen-Anhalt",
    "wof:name":"Kaufcenter",
    "wof:placetype":"venue"
},
  "geometry": {"coordinates":[11.402341,51.834007],"type":"Point"}
}