{
  "type": "Feature",
  "properties": {
    "iso:country":"DE",
    "sg:address":"Franz-Wisbacher-Str. 4",
    "sg:city":"Ainring",
    "sg:phone":"+49 8654/485134",
    "sg:postcode":"83404",
    "sg:province":"Bayern",
    "wof:name":"A. Und H. Rehrl",
    "wof:placetype":"venue"
},
  "geometry": {"coordinates":[12.9582967758,47.8051452637],"type":"Point"}
}