{
  "type": "Feature",
  "properties": {
    "iso:country":"DE",
    "sg:address":"Baierecker Str. 53",
    "sg:city":"Schorndorf",
    "sg:phone":"+49 7181/920330",
    "sg:postcode":"73614",
    "sg:province":"Baden-W\u00fcrttemberg",
    "wof:name":"Beste Wasseraufbereitung Gmbh",
    "wof:placetype":"venue"
},
  "geometry": {"coordinates":[9.505501,48.768471],"type":"Point"}
}