{
  "type": "Feature",
  "properties": {
    "iso:country":"DE",
    "sg:address":"Schlagbaumweg 25",
    "sg:city":"Oldenburg",
    "sg:postcode":"26131",
    "sg:province":"Niedersachsen",
    "wof:name":"Haferkamp Cpc Packaging Gmbh & Co. Kg",
    "wof:placetype":"venue"
},
  "geometry": {"coordinates":[8.187235,53.114536],"type":"Point"}
}