{
  "type": "Feature",
  "properties": {
    "iso:country":"DE",
    "sg:address":"Haldenstr. 28",
    "sg:city":"Weinstadt",
    "sg:phone":"+49 7151/66423",
    "sg:postcode":"71384",
    "sg:province":"Baden-W\u00fcrttemberg",
    "wof:name":"Walter G\u00f6keler",
    "wof:placetype":"venue"
},
  "geometry": {"coordinates":[9.404768,48.792629],"type":"Point"}
}