{
  "type": "Feature",
  "properties": {
    "iso:country":"DE",
    "sg:address":"Westring 47",
    "sg:city":"Bochum",
    "sg:phone":"+49 234/687880",
    "sg:postcode":"44787",
    "sg:province":"Nordrhein-Westfalen",
    "wof:name":"Akademie F\u00fcr Betriebswirtschaft Und Unternehmensf\u00fchrung Gmbh",
    "wof:placetype":"venue"
},
  "geometry": {"coordinates":[7.211071,51.483173],"type":"Point"}
}