{
  "type": "Feature",
  "properties": {
    "iso:country":"DE",
    "sg:address":"Schnurrstr. 45",
    "sg:city":"Adelberg",
    "sg:postcode":"73099",
    "sg:province":"Baden-W\u00fcrttemberg",
    "wof:name":"Deppe Verwaltungs- Gmbh",
    "wof:placetype":"venue"
},
  "geometry": {"coordinates":[9.604083,48.759472],"type":"Point"}
}