{
  "type": "Feature",
  "properties": {
    "iso:country":"DE",
    "sg:address":"Allmenweg 12",
    "sg:city":"Immendingen",
    "sg:phone":"+49 7462/1422",
    "sg:postcode":"78194",
    "sg:province":"Baden-W\u00fcrttemberg",
    "wof:name":"Reinhard Keller",
    "wof:placetype":"venue"
},
  "geometry": {"coordinates":[8.6966123581,47.9259338379],"type":"Point"}
}