{
  "type": "Feature",
  "properties": {
    "iso:country":"DE",
    "sg:address":"Petritorwall 22",
    "sg:city":"Braunschweig",
    "sg:phone":"+49 531/45021",
    "sg:postcode":"38118",
    "sg:province":"Niedersachsen",
    "wof:name":"Uwe Wolter",
    "wof:placetype":"venue"
},
  "geometry": {"coordinates":[10.5106773376,52.2653541565],"type":"Point"}
}