{
  "type": "Feature",
  "properties": {
    "iso:country":"DE",
    "sg:address":"Oberberger Str. 115",
    "sg:city":"Meschede",
    "sg:phone":"+49 2903/97790",
    "sg:postcode":"59872",
    "sg:province":"Nordrhein-Westfalen",
    "wof:name":"Severin Bergerhammer Gmbh",
    "wof:placetype":"venue"
},
  "geometry": {"coordinates":[8.162423,51.318985],"type":"Point"}
}