{
  "type": "Feature",
  "properties": {
    "iso:country":"DE",
    "sg:address":"Nockhergasse 1",
    "sg:city":"Bad T\u00f6lz",
    "sg:phone":"+49 8041/9695",
    "sg:postcode":"83646",
    "sg:province":"Bayern",
    "wof:name":"Adolf Detter",
    "wof:placetype":"venue"
},
  "geometry": {"coordinates":[11.560197,47.761868],"type":"Point"}
}