{
  "type": "Feature",
  "properties": {
    "iso:country":"DE",
    "sg:address":"Neuburger Str. 26",
    "sg:city":"Augsburg",
    "sg:phone":"+49 821/791347",
    "sg:postcode":"86167",
    "sg:province":"Bayern",
    "wof:name":"Norma Gmbh & Co. Kg Lebensmittelfilialbetrieb",
    "wof:placetype":"venue"
},
  "geometry": {"coordinates":[10.9151201248,48.3794136047],"type":"Point"}
}