{
  "type": "Feature",
  "properties": {
    "iso:country":"DE",
    "sg:address":"Quellen",
    "sg:city":"Wistedt",
    "sg:phone":"+49 4182/1277",
    "sg:postcode":"21255",
    "sg:province":"Niedersachsen",
    "wof:name":"Heinz-dietrich Rothschild",
    "wof:placetype":"venue"
},
  "geometry": {"coordinates":[9.6993,53.261669],"type":"Point"}
}