{
  "type": "Feature",
  "properties": {
    "iso:country":"DE",
    "sg:address":"Bademutterstr. 10",
    "sg:city":"Wismar",
    "sg:phone":"+49 3841/613548",
    "sg:postcode":"23966",
    "sg:province":"Mecklenburg-Vorpommern",
    "wof:name":"M. Jorowitz",
    "wof:placetype":"venue"
},
  "geometry": {"coordinates":[11.4659996033,53.8935623169],"type":"Point"}
}