{
  "type": "Feature",
  "properties": {
    "iso:country":"DE",
    "sg:address":"Ziegelei Str. 1",
    "sg:city":"Lankau",
    "sg:phone":"+49 4543/7318",
    "sg:postcode":"23881",
    "sg:province":"Schleswig-Holstein",
    "wof:name":"Claudia Fiedler Rechtsanw\u00e4ltin",
    "wof:placetype":"venue"
},
  "geometry": {"coordinates":[10.6359586716,53.688457489],"type":"Point"}
}