{
  "type": "Feature",
  "properties": {
    "iso:country":"DE",
    "sg:address":"Demmeljochstr. 52",
    "sg:city":"Bad T\u00f6lz",
    "sg:postcode":"83646",
    "sg:province":"Bayern",
    "wof:name":"Motorrad Niederberger Gesch\u00e4ftsf\u00fchrungs Gmbh",
    "wof:placetype":"venue"
},
  "geometry": {"coordinates":[11.56538,47.748829],"type":"Point"}
}