{
  "type": "Feature",
  "properties": {
    "iso:country":"DE",
    "sg:address":"Bleichstr. 5",
    "sg:city":"Bruchk\u00f6bel",
    "sg:phone":"+49 6181/77302",
    "sg:postcode":"63486",
    "sg:province":"Hessen",
    "wof:name":"Otto Rein\u00e4cker",
    "wof:placetype":"venue"
},
  "geometry": {"coordinates":[8.9136,50.200851],"type":"Point"}
}