{
  "type": "Feature",
  "properties": {
    "iso:country":"DE",
    "sg:address":"Am Bahnhof 8",
    "sg:city":"Westoverledingen",
    "sg:phone":"+49 4955/92260",
    "sg:postcode":"26810",
    "sg:province":"Niedersachsen",
    "wof:name":"Raiffeisen Markt",
    "wof:placetype":"venue"
},
  "geometry": {"coordinates":[7.447619,53.164852],"type":"Point"}
}