{
  "type": "Feature",
  "properties": {
    "iso:country":"DE",
    "sg:address":"Am Hollemann 43",
    "sg:city":"Brilon",
    "sg:phone":"+49 2961/4035",
    "sg:postcode":"59929",
    "sg:province":"Nordrhein-Westfalen",
    "wof:name":"H.-j. Raspe Steuerberater",
    "wof:placetype":"venue"
},
  "geometry": {"coordinates":[8.565580368,51.3870391846],"type":"Point"}
}