{
  "type": "Feature",
  "properties": {
    "iso:country":"DE",
    "sg:city":"Rositz",
    "sg:postcode":"04617",
    "sg:province":"Th\u00fcringen",
    "wof:name":"Bibliothek",
    "wof:placetype":"venue"
},
  "geometry": {"coordinates":[12.36918,51.016701],"type":"Point"}
}