{
  "type": "Feature",
  "properties": {
    "iso:country":"DE",
    "sg:address":"Hipperweg 1",
    "sg:city":"Ravensburg",
    "sg:phone":"+49 751/22764",
    "sg:postcode":"88214",
    "sg:province":"Baden-W\u00fcrttemberg",
    "wof:name":"Hans Fe\u00dfler Heilpraktiker",
    "wof:placetype":"venue"
},
  "geometry": {"coordinates":[9.6071224213,47.7674980164],"type":"Point"}
}