{
  "type": "Feature",
  "properties": {
    "iso:country":"DE",
    "sg:address":"Gro\u00dfe Burgstr. 24",
    "sg:city":"L\u00fcbeck",
    "sg:phone":"+49 451/74891",
    "sg:postcode":"23552",
    "sg:province":"Schleswig-Holstein",
    "wof:name":"Ostasienhaus Inh. Ursula Langfeldt",
    "wof:placetype":"venue"
},
  "geometry": {"coordinates":[10.69033,53.872513],"type":"Point"}
}