{
  "type": "Feature",
  "properties": {
    "iso:country":"DE",
    "sg:address":"Eschweg 8",
    "sg:city":"Kirchlengern",
    "sg:phone":"+49 5223/71294",
    "sg:postcode":"32278",
    "sg:province":"Nordrhein-Westfalen",
    "wof:name":"Deppermann",
    "wof:placetype":"venue"
},
  "geometry": {"coordinates":[8.639307,52.201691],"type":"Point"}
}