{
  "type": "Feature",
  "properties": {
    "iso:country":"DE",
    "sg:address":"Am Alten Weg 8",
    "sg:city":"Wolfstein",
    "sg:phone":"+49 6304/1722",
    "sg:postcode":"67752",
    "sg:province":"Rheinland-Pfalz",
    "wof:name":"Markant-markt",
    "wof:placetype":"venue"
},
  "geometry": {"coordinates":[7.6096158028,49.5830078125],"type":"Point"}
}