{
  "type": "Feature",
  "properties": {
    "iso:country":"DE",
    "sg:address":"Freie-Vogel-Str. 5",
    "sg:city":"Dortmund",
    "sg:phone":"+49 231/415453",
    "sg:postcode":"44263",
    "sg:province":"Nordrhein-Westfalen",
    "wof:name":"Willi Sch\u00f6nborn Inh. Grete Sch\u00f6nborn",
    "wof:placetype":"venue"
},
  "geometry": {"coordinates":[7.519168,51.494617],"type":"Point"}
}