{
  "type": "Feature",
  "properties": {
    "iso:country":"DE",
    "sg:address":"Frankenstr. 258",
    "sg:city":"Essen",
    "sg:phone":"+49 201/442171",
    "sg:postcode":"45134",
    "sg:province":"Nordrhein-Westfalen",
    "wof:name":"Emil G\u00f6bel Jun.",
    "wof:placetype":"venue"
},
  "geometry": {"coordinates":[7.026724,51.421638],"type":"Point"}
}