{
  "type": "Feature",
  "properties": {
    "iso:country":"DE",
    "sg:address":"Hohenzollerndamm 81",
    "sg:city":"Berlin",
    "sg:phone":"+49 30/8938490",
    "sg:postcode":"14199",
    "sg:province":"Berlin",
    "wof:name":"Pe & Ef Bautr\u00e4ger Gmbh",
    "wof:placetype":"venue"
},
  "geometry": {"coordinates":[13.286728,52.480652],"type":"Point"}
}