{
  "type": "Feature",
  "properties": {
    "iso:country":"DE",
    "sg:address":"Haus-Nr. 1 1/2",
    "sg:city":"Ebersberg",
    "sg:phone":"+49 8092/22697",
    "sg:postcode":"85560",
    "sg:province":"Bayern",
    "wof:name":"Katholisches Pfarramt St. Georg",
    "wof:placetype":"venue"
},
  "geometry": {"coordinates":[11.9685602188,48.0784301758],"type":"Point"}
}