{
  "type": "Feature",
  "properties": {
    "iso:country":"DE",
    "sg:address":"Hauptstr. 17",
    "sg:city":"P\u00f6lich",
    "sg:phone":"+49 6507/93800",
    "sg:postcode":"54340",
    "sg:province":"Rheinland-Pfalz",
    "wof:name":"Cal Chemisch-analytisches Laboratorium",
    "wof:placetype":"venue"
},
  "geometry": {"coordinates":[6.848566,49.797287],"type":"Point"}
}