{
  "type": "Feature",
  "properties": {
    "iso:country":"DE",
    "sg:address":"Grafenstr. 22",
    "sg:city":"Darmstadt",
    "sg:phone":"+49 6151/1773660",
    "sg:postcode":"64283",
    "sg:province":"Hessen",
    "wof:name":"Hdi Versicherungen",
    "wof:placetype":"venue"
},
  "geometry": {"coordinates":[8.6496582031,49.8713302612],"type":"Point"}
}