{
  "type": "Feature",
  "properties": {
    "iso:country":"DE",
    "sg:address":"Knesebeckstr. 74",
    "sg:city":"Berlin",
    "sg:phone":"+49 30/8825884",
    "sg:postcode":"10623",
    "sg:province":"Berlin",
    "wof:name":"Petra Haffter Filmproduktion Gmbh",
    "wof:placetype":"venue"
},
  "geometry": {"coordinates":[13.322319,52.503765],"type":"Point"}
}