{
  "type": "Feature",
  "properties": {
    "iso:country":"DE",
    "sg:address":"Bahnhofstr. 6",
    "sg:city":"Genthin",
    "sg:phone":"+49 3933/803138",
    "sg:postcode":"39307",
    "sg:province":"Sachsen-Anhalt",
    "wof:name":"Kister Und Kister Rechtsanw\u00e4lte",
    "wof:placetype":"venue"
},
  "geometry": {"coordinates":[12.1581392288,52.4053382874],"type":"Point"}
}