{
  "type": "Feature",
  "properties": {
    "iso:country":"DE",
    "sg:address":"Sigmundstr 110",
    "sg:city":"N\u00fcrnberg",
    "sg:phone":"+49 911/32283010",
    "sg:postcode":"90431",
    "sg:province":"Bayern",
    "wof:name":"Schmidt Oberfl\u00e4chentechnik Gmbh",
    "wof:placetype":"venue"
},
  "geometry": {"coordinates":[11.0142040253,49.4518089294],"type":"Point"}
}