{
  "type": "Feature",
  "properties": {
    "iso:country":"DE",
    "sg:address":"Bonifatiusstr. 46",
    "sg:city":"Rheine",
    "sg:phone":"+49 5971/71817",
    "sg:postcode":"48429",
    "sg:province":"Nordrhein-Westfalen",
    "wof:name":"Wilhelm Hinterding",
    "wof:placetype":"venue"
},
  "geometry": {"coordinates":[7.4456510544,52.2932090759],"type":"Point"}
}