{
  "type": "Feature",
  "properties": {
    "iso:country":"DE",
    "sg:address":"Hauptstr. 29",
    "sg:city":"Unlingen",
    "sg:phone":"+49 7371/2410",
    "sg:postcode":"88527",
    "sg:province":"Baden-W\u00fcrttemberg",
    "wof:name":"Reinhard Schmid",
    "wof:placetype":"venue"
},
  "geometry": {"coordinates":[9.522092,48.16769],"type":"Point"}
}