{
  "type": "Feature",
  "properties": {
    "iso:country":"DE",
    "sg:address":"Schwarze Str. 3",
    "sg:city":"Langballig",
    "sg:phone":"+49 4636/1489",
    "sg:postcode":"24977",
    "sg:province":"Schleswig-Holstein",
    "wof:name":"Peter Preusser",
    "wof:placetype":"venue"
},
  "geometry": {"coordinates":[9.630524,54.799042],"type":"Point"}
}