{
  "type": "Feature",
  "properties": {
    "iso:country":"DE",
    "sg:address":"Vollmoellerstr. 33",
    "sg:city":"Stuttgart",
    "sg:phone":"+49 711/733925",
    "sg:postcode":"70563",
    "sg:province":"Baden-W\u00fcrttemberg",
    "wof:name":"T. Neidlein",
    "wof:placetype":"venue"
},
  "geometry": {"coordinates":[9.1073627472,48.7274780273],"type":"Point"}
}