{
  "type": "Feature",
  "properties": {
    "iso:country":"DE",
    "sg:address":"Br\u00fcckstr. 23",
    "sg:city":"Emden",
    "sg:phone":"+49 4921/21625",
    "sg:postcode":"26725",
    "sg:province":"Niedersachsen",
    "wof:name":"Elras Und Bart Ab Gmbh",
    "wof:placetype":"venue"
},
  "geometry": {"coordinates":[7.208193779,53.3670387268],"type":"Point"}
}