{
  "type": "Feature",
  "properties": {
    "iso:country":"DE",
    "sg:address":"Hoffeldstr. 88",
    "sg:city":"D\u00fcsseldorf",
    "sg:phone":"+49 211/667890",
    "sg:postcode":"40235",
    "sg:province":"Nordrhein-Westfalen",
    "wof:name":"Dieter Schankweiler Ingenieur",
    "wof:placetype":"venue"
},
  "geometry": {"coordinates":[6.8149490356,51.2275314331],"type":"Point"}
}