{
  "type": "Feature",
  "properties": {
    "iso:country":"DE",
    "sg:address":"Aringer Kirchweg 2",
    "sg:city":"Bissendorf",
    "sg:phone":"+49 5402/5973",
    "sg:postcode":"49143",
    "sg:province":"Niedersachsen",
    "wof:name":"Hartex Gmbh",
    "wof:placetype":"venue"
},
  "geometry": {"coordinates":[8.216594696,52.2238502502],"type":"Point"}
}