{
  "type": "Feature",
  "properties": {
    "iso:country":"DE",
    "sg:address":"Am M\u00fchlenberg 1",
    "sg:city":"Ottersberg",
    "sg:phone":"+49 4293/391",
    "sg:postcode":"28870",
    "sg:province":"Niedersachsen",
    "wof:name":"Harm Dirk Gieschen",
    "wof:placetype":"venue"
},
  "geometry": {"coordinates":[9.080971,53.13472],"type":"Point"}
}