{
  "type": "Feature",
  "properties": {
    "iso:country":"DE",
    "sg:address":"Weinheimer Str. 71",
    "sg:city":"Viernheim",
    "sg:phone":"+49 6204/2424",
    "sg:postcode":"68519",
    "sg:province":"Hessen",
    "wof:name":"Werner Helbig Steuerbevollm\u00e4chtigter",
    "wof:placetype":"venue"
},
  "geometry": {"coordinates":[8.5849790573,49.5374984741],"type":"Point"}
}