{
  "type": "Feature",
  "properties": {
    "iso:country":"DE",
    "sg:address":"Herdecker Bach 33 a",
    "sg:city":"Herdecke",
    "sg:phone":"+49 2330/3168",
    "sg:postcode":"58313",
    "sg:province":"Nordrhein-Westfalen",
    "wof:name":"Gerhard Kister Ingenieur",
    "wof:placetype":"venue"
},
  "geometry": {"coordinates":[7.4313960075,51.4137763977],"type":"Point"}
}