{
  "type": "Feature",
  "properties": {
    "iso:country":"DE",
    "sg:address":"Sch\u00fctzenstr. 28",
    "sg:city":"Netzschkau",
    "sg:phone":"+49 3765/34646",
    "sg:postcode":"08491",
    "sg:province":"Sachsen",
    "wof:name":"M. Rudert",
    "wof:placetype":"venue"
},
  "geometry": {"coordinates":[12.24244,50.607895],"type":"Point"}
}