{
  "type": "Feature",
  "properties": {
    "iso:country":"DE",
    "sg:address":"Am Turm 2",
    "sg:city":"Gutach",
    "sg:phone":"+49 7831/6525",
    "sg:postcode":"77793",
    "sg:province":"Baden-W\u00fcrttemberg",
    "wof:name":"Manfred Breithaupt Anlageberater",
    "wof:placetype":"venue"
},
  "geometry": {"coordinates":[8.2102193832,48.2505111694],"type":"Point"}
}