{
  "type": "Feature",
  "properties": {
    "iso:country":"DE",
    "sg:address":"Postfach 1039",
    "sg:city":"Schmelz",
    "sg:phone":"+49 6887/2071",
    "sg:postcode":"66832",
    "sg:province":"Saarland",
    "wof:name":"Dolerit-basalt Grundwert- Und Beteiligungs- Ag",
    "wof:placetype":"venue"
},
  "geometry": {"coordinates":[6.8574252129,49.4407501221],"type":"Point"}
}