{
  "type": "Feature",
  "properties": {
    "iso:country":"DE",
    "sg:address":"Lippenwiesen 5",
    "sg:city":"Radolfzell",
    "sg:phone":"+49 7732/56485",
    "sg:postcode":"78315",
    "sg:province":"Baden-W\u00fcrttemberg",
    "wof:name":"Wacker-werke Gmbh & Co. Kg",
    "wof:placetype":"venue"
},
  "geometry": {"coordinates":[8.953867,47.744011],"type":"Point"}
}