{
  "type": "Feature",
  "properties": {
    "iso:country":"DE",
    "sg:address":"Wei\u00dfensteiner Str. 1a",
    "sg:city":"Schw\u00e4bisch Gm\u00fcnd",
    "sg:phone":"+49 7171/69944",
    "sg:postcode":"73525",
    "sg:province":"Baden-W\u00fcrttemberg",
    "wof:name":"Mathias H\u00fctter",
    "wof:placetype":"venue"
},
  "geometry": {"coordinates":[9.799413,48.795399],"type":"Point"}
}