{
  "type": "Feature",
  "properties": {
    "iso:country":"DE",
    "sg:address":"Pestalozzistrasse 13",
    "sg:city":"Potsdam",
    "sg:phone":"+49 331/707808",
    "sg:postcode":"14482",
    "sg:province":"Brandenburg",
    "wof:name":"Internet Partnersuche",
    "wof:placetype":"venue"
},
  "geometry": {"coordinates":[13.104541,52.389023],"type":"Point"}
}