{
  "type": "Feature",
  "properties": {
    "iso:country":"DE",
    "sg:address":"Am Sportplatz 6",
    "sg:city":"Breisach",
    "sg:phone":"+49 7664/2687",
    "sg:postcode":"79206",
    "sg:province":"Baden-W\u00fcrttemberg",
    "wof:name":"Ott Steuer- Und Regeltechnik Gmbh",
    "wof:placetype":"venue"
},
  "geometry": {"coordinates":[7.6637539864,47.9747962952],"type":"Point"}
}