{
  "type": "Feature",
  "properties": {
    "iso:country":"DE",
    "sg:address":"Wieckstra\u00dfe 22",
    "sg:city":"Hamburg",
    "sg:phone":"+49 40/43181130",
    "sg:postcode":"22527",
    "sg:province":"Hamburg",
    "wof:name":"Aumeso Multimediale Audioproduktionen Aller Art!",
    "wof:placetype":"venue"
},
  "geometry": {"coordinates":[9.942482,53.583473],"type":"Point"}
}