{
  "type": "Feature",
  "properties": {
    "iso:country":"DE",
    "sg:address":"Grafenstr. 25",
    "sg:city":"Darmstadt",
    "sg:phone":"+49 6151/22013",
    "sg:postcode":"64283",
    "sg:province":"Hessen",
    "wof:name":"S. Ehrig Cateringservice Mr. Break E. Kfr.",
    "wof:placetype":"venue"
},
  "geometry": {"coordinates":[8.649009,49.872005],"type":"Point"}
}