{
  "type": "Feature",
  "properties": {
    "iso:country":"DE",
    "sg:address":"R\u00fcckersdorfer Str. 53",
    "sg:city":"R\u00f6thenbach",
    "sg:phone":"+49 911/5709957",
    "sg:postcode":"90552",
    "sg:province":"Bayern",
    "wof:name":"Schuster",
    "wof:placetype":"venue"
},
  "geometry": {"coordinates":[11.2451715469,49.4855270386],"type":"Point"}
}