{
  "type": "Feature",
  "properties": {
    "iso:country":"DE",
    "sg:address":"Am Bahndamm 2",
    "sg:city":"Walpertskirchen",
    "sg:phone":"+49 8122/48404",
    "sg:postcode":"85469",
    "sg:province":"Bayern",
    "wof:name":"Heinrich Brandl Handels- Vertretung Cdh E. K.",
    "wof:placetype":"venue"
},
  "geometry": {"coordinates":[11.9741420746,48.2627296448],"type":"Point"}
}