{
  "type": "Feature",
  "properties": {
    "iso:country":"DE",
    "sg:address":"Dianastr. 17-27",
    "sg:city":"N\u00fcrnberg",
    "sg:postcode":"90441",
    "sg:province":"Bayern",
    "wof:name":"Veba Heizoel Vertriebs Gmbh",
    "wof:placetype":"venue"
},
  "geometry": {"coordinates":[11.0652732849,49.4276390076],"type":"Point"}
}