{
  "type": "Feature",
  "properties": {
    "iso:country":"DE",
    "sg:address":"Habichtweg 9",
    "sg:city":"Sarstedt",
    "sg:phone":"+49 5066/5906",
    "sg:postcode":"31157",
    "sg:province":"Niedersachsen",
    "wof:name":"1. Kleintierkolonie Sarstedt Von 1978 E. V.",
    "wof:placetype":"venue"
},
  "geometry": {"coordinates":[9.8652324677,52.2340507507],"type":"Point"}
}