{
  "type": "Feature",
  "properties": {
    "iso:country":"DE",
    "sg:address":"Sch\u00f6necker Str. 29",
    "sg:city":"Gondershausen",
    "sg:phone":"+49 6745/366",
    "sg:postcode":"56283",
    "sg:province":"Rheinland-Pfalz",
    "wof:name":"Friedrich Lenz Edelstahlbau Und Schlosserei Gmbh",
    "wof:placetype":"venue"
},
  "geometry": {"coordinates":[7.496099,50.16296],"type":"Point"}
}