{
  "type": "Feature",
  "properties": {
    "iso:country":"DE",
    "sg:address":"An der Weide 2",
    "sg:city":"Syke",
    "sg:phone":"+49 4242/95990",
    "sg:postcode":"28857",
    "sg:province":"Niedersachsen",
    "wof:name":"Steenken Gmbh",
    "wof:placetype":"venue"
},
  "geometry": {"coordinates":[8.816127,52.913902],"type":"Point"}
}