{
  "type": "Feature",
  "properties": {
    "iso:country":"DE",
    "sg:address":"Hauptstr. 26",
    "sg:city":"Bad Zwischenahn",
    "sg:phone":"+49 4403/5530",
    "sg:postcode":"26160",
    "sg:province":"Niedersachsen",
    "wof:name":"G\u00fcnther Meinen",
    "wof:placetype":"venue"
},
  "geometry": {"coordinates":[7.9410200119,53.1476593018],"type":"Point"}
}