{
  "type": "Feature",
  "properties": {
    "iso:country":"DE",
    "sg:address":"Auf dem Langen Kampe 25a",
    "sg:city":"Bielefeld",
    "sg:phone":"+49 521/320260",
    "sg:postcode":"33607",
    "sg:province":"Nordrhein-Westfalen",
    "wof:name":"Gerrit Hoorn Architekt",
    "wof:placetype":"venue"
},
  "geometry": {"coordinates":[8.563269,52.025734],"type":"Point"}
}