{
  "type": "Feature",
  "properties": {
    "iso:country":"DE",
    "sg:address":"Rheinstr. 8",
    "sg:city":"Worms",
    "sg:phone":"+49 6241/28983",
    "sg:postcode":"67547",
    "sg:province":"Rheinland-Pfalz",
    "wof:name":"Kurt Markert",
    "wof:placetype":"venue"
},
  "geometry": {"coordinates":[8.3664169312,49.6322250366],"type":"Point"}
}