{
  "type": "Feature",
  "properties": {
    "iso:country":"DE",
    "sg:address":"Gaisgasse 34",
    "sg:city":"Kirchheim",
    "sg:phone":"+49 7021/2230",
    "sg:postcode":"73230",
    "sg:province":"Baden-W\u00fcrttemberg",
    "wof:name":"Karl Eger",
    "wof:placetype":"venue"
},
  "geometry": {"coordinates":[9.450222,48.644142],"type":"Point"}
}