{
  "type": "Feature",
  "properties": {
    "iso:country":"DE",
    "sg:address":"Am Richtfunkturm",
    "sg:city":"Rostock",
    "sg:phone":"+49 381/4001457",
    "sg:postcode":"18059",
    "sg:province":"Mecklenburg-Vorpommern",
    "wof:name":"Pfelgeheim Awo-stadtheide",
    "wof:placetype":"venue"
},
  "geometry": {"coordinates":[12.072877,54.074406],"type":"Point"}
}