{
  "type": "Feature",
  "properties": {
    "iso:country":"DE",
    "sg:address":"Heckenweg 39",
    "sg:city":"Leonberg",
    "sg:phone":"+49 7152/75355",
    "sg:postcode":"71229",
    "sg:province":"Baden-W\u00fcrttemberg",
    "wof:name":"Hans Dieter St\u00e4hle Gmbh",
    "wof:placetype":"venue"
},
  "geometry": {"coordinates":[9.029404,48.792202],"type":"Point"}
}