{
  "type": "Feature",
  "properties": {
    "iso:country":"DE",
    "sg:address":"Helenastr. 2",
    "sg:city":"Bocholt",
    "sg:phone":"+49 2871/38101",
    "sg:postcode":"46397",
    "sg:province":"Nordrhein-Westfalen",
    "wof:name":"Gastst\u00e4tte G\u00fcnther Schmitz",
    "wof:placetype":"venue"
},
  "geometry": {"coordinates":[6.6669178009,51.8846817017],"type":"Point"}
}