{
  "type": "Feature",
  "properties": {
    "iso:country":"DE",
    "sg:address":"Ernst-Th\u00e4lmann-Str. 9",
    "sg:city":"Holleben",
    "sg:phone":"+49 345/6130905",
    "sg:postcode":"06179",
    "sg:province":"Sachsen-Anhalt",
    "wof:name":"Immobilien Und Bauleistungs- Vertrieb Gmbh",
    "wof:placetype":"venue"
},
  "geometry": {"coordinates":[11.9000482559,51.4481163025],"type":"Point"}
}