{
  "type": "Feature",
  "properties": {
    "iso:country":"DE",
    "sg:address":"Stra\u00dfe der Befreiung 40",
    "sg:city":"Reinsdorf",
    "sg:phone":"+49 375/293383",
    "sg:postcode":"08141",
    "sg:province":"Sachsen",
    "wof:name":"Ronald Neubert",
    "wof:placetype":"venue"
},
  "geometry": {"coordinates":[12.532672,50.704182],"type":"Point"}
}