{
  "type": "Feature",
  "properties": {
    "iso:country":"DE",
    "sg:address":"Ortfeld 4",
    "sg:city":"Langwedel",
    "sg:phone":"+49 4235/1777",
    "sg:postcode":"27299",
    "sg:province":"Niedersachsen",
    "wof:name":"Dietmar Junge Handels Gmbh",
    "wof:placetype":"venue"
},
  "geometry": {"coordinates":[9.1155223846,52.9985809326],"type":"Point"}
}