{
  "type": "Feature",
  "properties": {
    "iso:country":"DE",
    "sg:address":"Klenzestr. 7",
    "sg:city":"M\u00fcnchen",
    "sg:phone":"+49 89/2904565",
    "sg:postcode":"80469",
    "sg:province":"Bayern",
    "wof:name":"City Reiseb\u00fcro Inh. Matthias Fuhs",
    "wof:placetype":"venue"
},
  "geometry": {"coordinates":[11.5791149139,48.1334152222],"type":"Point"}
}