{
  "type": "Feature",
  "properties": {
    "iso:country":"DE",
    "sg:address":"Bruchsaler Str. 3",
    "sg:city":"Bruchsal",
    "sg:phone":"+49 7257/3000",
    "sg:postcode":"76646",
    "sg:province":"Baden-W\u00fcrttemberg",
    "wof:name":"Wolfgang Zimmermann Rechtsanwalt",
    "wof:placetype":"venue"
},
  "geometry": {"coordinates":[8.5562953949,49.1403160095],"type":"Point"}
}