{
  "type": "Feature",
  "properties": {
    "iso:country":"DE",
    "sg:address":"August-Hirsch-Str. 3",
    "sg:city":"Duisburg",
    "sg:postcode":"47119",
    "sg:province":"Nordrhein-Westfalen",
    "wof:name":"Rheintank- Gmbh",
    "wof:placetype":"venue"
},
  "geometry": {"coordinates":[6.7415099144,51.4485168457],"type":"Point"}
}