{
  "type": "Feature",
  "properties": {
    "iso:country":"DE",
    "sg:address":"An der Tumpe 20",
    "sg:city":"Werdohl",
    "sg:phone":"+49 2392/91850",
    "sg:postcode":"58791",
    "sg:province":"Nordrhein-Westfalen",
    "wof:name":"Hans Hesmer",
    "wof:placetype":"venue"
},
  "geometry": {"coordinates":[7.721559,51.268757],"type":"Point"}
}