{
  "type": "Feature",
  "properties": {
    "iso:country":"DE",
    "sg:address":"Finkenstr. 63",
    "sg:city":"Marl",
    "sg:phone":"+49 2365/26022",
    "sg:postcode":"45772",
    "sg:province":"Nordrhein-Westfalen",
    "wof:name":"H.-j. Scherer Masseur",
    "wof:placetype":"venue"
},
  "geometry": {"coordinates":[7.124806,51.686604],"type":"Point"}
}