{
  "type": "Feature",
  "properties": {
    "iso:country":"DE",
    "sg:address":"Wolfersh\u00e4user Str. 13",
    "sg:city":"Ederm\u00fcnde",
    "sg:phone":"+49 5665/5749",
    "sg:postcode":"34295",
    "sg:province":"Hessen",
    "wof:name":"Walter Hanke",
    "wof:placetype":"venue"
},
  "geometry": {"coordinates":[9.431488,51.1996],"type":"Point"}
}