{
  "type": "Feature",
  "properties": {
    "iso:country":"DE",
    "sg:address":"Klingenhagen 22",
    "sg:city":"Halle",
    "sg:phone":"+49 5201/2423",
    "sg:postcode":"33790",
    "sg:province":"Nordrhein-Westfalen",
    "wof:name":"Wellmeier Spedition",
    "wof:placetype":"venue"
},
  "geometry": {"coordinates":[8.3542995453,52.0579948425],"type":"Point"}
}