{
  "type": "Feature",
  "properties": {
    "iso:country":"DE",
    "sg:address":"Gewerbering 2",
    "sg:city":"Garrel",
    "sg:phone":"+49 4474/7274",
    "sg:postcode":"49681",
    "sg:province":"Niedersachsen",
    "wof:name":"Helmut Rolfes Stra\u00dfen- Und Tiefbau Gmbh",
    "wof:placetype":"venue"
},
  "geometry": {"coordinates":[8.026847,52.944897],"type":"Point"}
}