{
  "type": "Feature",
  "properties": {
    "iso:country":"DE",
    "sg:address":"Stresemannstr. 79",
    "sg:city":"Stuttgart",
    "sg:phone":"+49 711/89500",
    "sg:postcode":"70191",
    "sg:province":"Baden-W\u00fcrttemberg",
    "wof:name":"Dete Immobilien Deutsche Telekom Immobilien",
    "wof:placetype":"venue"
},
  "geometry": {"coordinates":[9.1794347763,48.808380127],"type":"Point"}
}