{
  "type": "Feature",
  "properties": {
    "iso:country":"DE",
    "sg:address":"Diepenauer Str. 54",
    "sg:city":"Espelkamp",
    "sg:phone":"+49 5743/8525",
    "sg:postcode":"32339",
    "sg:province":"Nordrhein-Westfalen",
    "wof:name":"Fritz Blase Elektroinstallation",
    "wof:placetype":"venue"
},
  "geometry": {"coordinates":[8.670558,52.352345],"type":"Point"}
}