{
  "type": "Feature",
  "properties": {
    "iso:country":"DE",
    "sg:address":"Am Wiesengrund 5",
    "sg:city":"Langenberg",
    "sg:phone":"+49 5248/274",
    "sg:postcode":"33449",
    "sg:province":"Nordrhein-Westfalen",
    "wof:name":"Heinz Langewender",
    "wof:placetype":"venue"
},
  "geometry": {"coordinates":[8.311708,51.774551],"type":"Point"}
}