{
  "type": "Feature",
  "properties": {
    "iso:country":"DE",
    "sg:address":"Schillerstr. 10",
    "sg:city":"Heusenstamm",
    "sg:phone":"+49 4961/0496380",
    "sg:postcode":"63150",
    "sg:province":"Hessen",
    "wof:name":"Artis Dental Gmbh",
    "wof:placetype":"venue"
},
  "geometry": {"coordinates":[8.8020219803,50.0558547974],"type":"Point"}
}