{
  "type": "Feature",
  "properties": {
    "iso:country":"DE",
    "sg:address":"M\u00fchlenstr. 44",
    "sg:city":"Altena",
    "sg:phone":"+49 4923/5271383",
    "sg:postcode":"58762",
    "sg:province":"Nordrhein-Westfalen",
    "wof:name":"Bdf Gmbh",
    "wof:placetype":"venue"
},
  "geometry": {"coordinates":[7.746604,51.296806],"type":"Point"}
}