{
  "type": "Feature",
  "properties": {
    "iso:country":"DE",
    "sg:address":"M\u00e4rkischer Platz 1",
    "sg:city":"Dallgow",
    "sg:phone":"+49 3322/201861",
    "sg:postcode":"14624",
    "sg:province":"Brandenburg",
    "wof:name":"M\u00e4rkische Bierstube Inh. Michael Werner",
    "wof:placetype":"venue"
},
  "geometry": {"coordinates":[13.057844162,52.5444450378],"type":"Point"}
}