{
  "type": "Feature",
  "properties": {
    "iso:country":"DE",
    "sg:address":"Schie\u00dfgrabenstr. 6",
    "sg:city":"Augsburg",
    "sg:phone":"+49 821/345920",
    "sg:postcode":"86150",
    "sg:province":"Bayern",
    "wof:name":"Planungsb\u00fcro Diehl Gmbh",
    "wof:placetype":"venue"
},
  "geometry": {"coordinates":[10.894969,48.363922],"type":"Point"}
}