{
  "type": "Feature",
  "properties": {
    "iso:country":"DE",
    "sg:address":"Herrnwaldstr. 16",
    "sg:city":"Bensheim",
    "sg:postcode":"64625",
    "sg:province":"Hessen",
    "wof:name":"Wackerbarth K\u00f6hle Und Heiligenthal",
    "wof:placetype":"venue"
},
  "geometry": {"coordinates":[8.646364212,49.7101783752],"type":"Point"}
}