{
  "type": "Feature",
  "properties": {
    "iso:country":"DE",
    "sg:address":"Vennstr. 159",
    "sg:city":"Stolberg",
    "sg:phone":"+49 2408/5403",
    "sg:postcode":"52224",
    "sg:province":"Nordrhein-Westfalen",
    "wof:name":"Anneliese Casteel Bildhauerin",
    "wof:placetype":"venue"
},
  "geometry": {"coordinates":[6.218232,50.7089],"type":"Point"}
}