{
  "type": "Feature",
  "properties": {
    "iso:country":"DE",
    "sg:address":"Voithstr. 5",
    "sg:city":"Renningen",
    "sg:phone":"+49 7159/6082",
    "sg:postcode":"71272",
    "sg:province":"Baden-W\u00fcrttemberg",
    "wof:name":"Aerob Entstaubungsanlagen Gmbh",
    "wof:placetype":"venue"
},
  "geometry": {"coordinates":[8.899989,48.781776],"type":"Point"}
}