{
  "type": "Feature",
  "properties": {
    "iso:country":"DE",
    "sg:address":"Regensburger Str. 80",
    "sg:city":"Kelheim",
    "sg:postcode":"93309",
    "sg:province":"Bayern",
    "wof:name":"B\u00e4ckerei Pfaffelhuber Kg",
    "wof:placetype":"venue"
},
  "geometry": {"coordinates":[11.886429,48.90757],"type":"Point"}
}