{
  "type": "Feature",
  "properties": {
    "iso:country":"DE",
    "sg:address":"Wedemarkstr. 30",
    "sg:city":"Wedemark",
    "sg:phone":"+49 5130/3012",
    "sg:postcode":"30900",
    "sg:province":"Niedersachsen",
    "wof:name":"Borgas",
    "wof:placetype":"venue"
},
  "geometry": {"coordinates":[9.732259,52.545643],"type":"Point"}
}