{
  "type": "Feature",
  "properties": {
    "iso:country":"DE",
    "sg:address":"Alte Elbgaustr. 10",
    "sg:city":"Hamburg",
    "sg:phone":"+49 40/5703940",
    "sg:postcode":"22523",
    "sg:province":"Hamburg",
    "wof:name":"Irma Reim Masseurin",
    "wof:placetype":"venue"
},
  "geometry": {"coordinates":[9.903621,53.607639],"type":"Point"}
}