{
  "type": "Feature",
  "properties": {
    "iso:country":"DE",
    "sg:address":"Dorfstr. 47a",
    "sg:city":"Emseloh",
    "sg:phone":"+49 34659/60309",
    "sg:postcode":"06528",
    "sg:province":"Sachsen-Anhalt",
    "wof:name":"Dietrich Plock Ingenieur",
    "wof:placetype":"venue"
},
  "geometry": {"coordinates":[11.3931818008,51.5041885376],"type":"Point"}
}