{
  "type": "Feature",
  "properties": {
    "iso:country":"DE",
    "sg:address":"R\u00fcbezahlweg 2b",
    "sg:city":"Landshut",
    "sg:phone":"+49 871/55442",
    "sg:postcode":"84028",
    "sg:province":"Bayern",
    "wof:name":"Creativ Wohnbau Gmbh",
    "wof:placetype":"venue"
},
  "geometry": {"coordinates":[12.175936,48.552059],"type":"Point"}
}