{
  "type": "Feature",
  "properties": {
    "iso:country":"DE",
    "sg:address":"Haus Bandemer 1",
    "sg:city":"Niersbach",
    "sg:phone":"+49 6575/95200",
    "sg:postcode":"54518",
    "sg:province":"Rheinland-Pfalz",
    "wof:name":"Eifel-quarz-mix Estrich Und M\u00f6rtel Gmbh",
    "wof:placetype":"venue"
},
  "geometry": {"coordinates":[6.9573907852,49.9205932617],"type":"Point"}
}