{
  "type": "Feature",
  "properties": {
    "iso:country":"DE",
    "sg:address":"Paderborner Str. 20",
    "sg:city":"Herne",
    "sg:phone":"+49 2323/451874",
    "sg:postcode":"44625",
    "sg:province":"Nordrhein-Westfalen",
    "wof:name":"Polster Design-gestaltung Lothar Zwiener Gmbh",
    "wof:placetype":"venue"
},
  "geometry": {"coordinates":[7.1890602112,51.5374031067],"type":"Point"}
}