{
  "type": "Feature",
  "properties": {
    "iso:country":"DE",
    "sg:address":"Dorfstr. 1",
    "sg:city":"Kelheim",
    "sg:phone":"+49 9441/80142",
    "sg:postcode":"93309",
    "sg:province":"Bayern",
    "wof:name":"Georg Metzger",
    "wof:placetype":"venue"
},
  "geometry": {"coordinates":[11.896261,48.879494],"type":"Point"}
}