{
  "type": "Feature",
  "properties": {
    "iso:country":"DE",
    "sg:address":"Neust\u00e4dter Str. 13",
    "sg:city":"K\u00f6then",
    "sg:phone":"+49 3496/214704",
    "sg:postcode":"06366",
    "sg:province":"Sachsen-Anhalt",
    "wof:name":"Dressler & Hentschel",
    "wof:placetype":"venue"
},
  "geometry": {"coordinates":[11.9793663025,51.7524986267],"type":"Point"}
}