{
  "type": "Feature",
  "properties": {
    "iso:country":"DE",
    "sg:address":"Breslauer Str. 25",
    "sg:city":"Ketsch",
    "sg:phone":"+49 6202/65992",
    "sg:postcode":"68775",
    "sg:province":"Baden-W\u00fcrttemberg",
    "wof:name":"F. Wilhelm Sengewald Gmbh",
    "wof:placetype":"venue"
},
  "geometry": {"coordinates":[8.530975,49.373981],"type":"Point"}
}