{
  "type": "Feature",
  "properties": {
    "iso:country":"DE",
    "sg:address":"Im Dorfe 30",
    "sg:city":"Legefeld",
    "sg:phone":"+49 3643/849426",
    "sg:postcode":"99438",
    "sg:province":"Th\u00fcringen",
    "wof:name":"Lothar Ra\u00dfloff",
    "wof:placetype":"venue"
},
  "geometry": {"coordinates":[11.282585144,50.8988685608],"type":"Point"}
}