{
  "type": "Feature",
  "properties": {
    "iso:country":"DE",
    "sg:address":"Bleichstr. 38a",
    "sg:city":"Frankfurt",
    "sg:phone":"+49 69/287505",
    "sg:postcode":"60313",
    "sg:province":"Hessen",
    "wof:name":"Feinschnitt",
    "wof:placetype":"venue"
},
  "geometry": {"coordinates":[8.6840133667,50.1180877686],"type":"Point"}
}