{
  "type": "Feature",
  "properties": {
    "iso:country":"DE",
    "sg:address":"Ringstr. 5",
    "sg:city":"Illerrieden",
    "sg:phone":"+49 7306/96320",
    "sg:postcode":"89186",
    "sg:province":"Baden-W\u00fcrttemberg",
    "wof:name":"Richard B\u00e4hr Gmbh",
    "wof:placetype":"venue"
},
  "geometry": {"coordinates":[10.0209407806,48.2803459167],"type":"Point"}
}