{
  "type": "Feature",
  "properties": {
    "iso:country":"DE",
    "sg:address":"Mittlere Str. 53",
    "sg:city":"Mengen",
    "sg:phone":"+49 7572/8293",
    "sg:postcode":"88512",
    "sg:province":"Baden-W\u00fcrttemberg",
    "wof:name":"Restaurant Pizzeria Drei K\u00f6nig",
    "wof:placetype":"venue"
},
  "geometry": {"coordinates":[9.3297739029,48.0478897095],"type":"Point"}
}