{
  "type": "Feature",
  "properties": {
    "iso:country":"DE",
    "sg:address":"Ringstr. 14",
    "sg:city":"Altenstadt",
    "sg:phone":"+49 8337/281",
    "sg:postcode":"89281",
    "sg:province":"Bayern",
    "wof:name":"Gebr. Wiest",
    "wof:placetype":"venue"
},
  "geometry": {"coordinates":[10.116113,48.160503],"type":"Point"}
}