{
  "type": "Feature",
  "properties": {
    "iso:country":"DE",
    "sg:address":"Mersch 28",
    "sg:city":"Bad Bentheim",
    "sg:phone":"+49 5924/990872",
    "sg:postcode":"48455",
    "sg:province":"Niedersachsen",
    "wof:name":"Jan Goossen Gmbh & Co. Kg",
    "wof:placetype":"venue"
},
  "geometry": {"coordinates":[7.098019,52.298798],"type":"Point"}
}