{
  "type": "Feature",
  "properties": {
    "iso:country":"DE",
    "sg:address":"Kindleber Str. 42",
    "sg:city":"Gotha",
    "sg:phone":"+49 3621/300782",
    "sg:postcode":"99867",
    "sg:province":"Th\u00fcringen",
    "wof:name":"W. Conrad",
    "wof:placetype":"venue"
},
  "geometry": {"coordinates":[10.7119979858,50.9559059143],"type":"Point"}
}