{
  "type": "Feature",
  "properties": {
    "iso:country":"DE",
    "sg:address":"Am Dornbusch 36",
    "sg:city":"M\u00fcnster",
    "sg:postcode":"48163",
    "sg:province":"Nordrhein-Westfalen",
    "wof:name":"H. Lange",
    "wof:placetype":"venue"
},
  "geometry": {"coordinates":[7.6161160469,51.8812217712],"type":"Point"}
}