{
  "type": "Feature",
  "properties": {
    "iso:country":"DE",
    "sg:address":"Mittelb\u00fcgweg 8",
    "sg:city":"Schwaig",
    "sg:phone":"+49 911/500410",
    "sg:postcode":"90571",
    "sg:province":"Bayern",
    "wof:name":"Ursula Eberlein Tennislehrer",
    "wof:placetype":"venue"
},
  "geometry": {"coordinates":[11.200091362,49.474067688],"type":"Point"}
}