{
  "type": "Feature",
  "properties": {
    "iso:country":"DE",
    "sg:address":"Bahnhofstr. 16",
    "sg:city":"Mallersdorf-Pfaffenberg",
    "sg:phone":"+49 8772/69183",
    "sg:postcode":"84066",
    "sg:province":"Bayern",
    "wof:name":"Elektrizit\u00e4tswerk",
    "wof:placetype":"venue"
},
  "geometry": {"coordinates":[12.253235,48.774303],"type":"Point"}
}