{
  "type": "Feature",
  "properties": {
    "iso:country":"DE",
    "sg:address":"K\u00f6kerstr. 7-9",
    "sg:city":"G\u00fctersloh",
    "sg:phone":"+49 5241/26685",
    "sg:postcode":"33330",
    "sg:province":"Nordrhein-Westfalen",
    "wof:name":"Stadtmuseum",
    "wof:placetype":"venue"
},
  "geometry": {"coordinates":[8.379934,51.906433],"type":"Point"}
}