{
  "type": "Feature",
  "properties": {
    "iso:country":"DE",
    "sg:address":"Am Sch\u00f6lkegraben 18",
    "sg:city":"Salzgitter",
    "sg:phone":"+49 5341/13335",
    "sg:postcode":"38226",
    "sg:province":"Niedersachsen",
    "wof:name":"C. Kosigk",
    "wof:placetype":"venue"
},
  "geometry": {"coordinates":[10.3341846466,52.1454963684],"type":"Point"}
}