{
  "type": "Feature",
  "properties": {
    "iso:country":"DE",
    "sg:address":"Im Moldengraben 42",
    "sg:city":"Kornwestheim",
    "sg:phone":"+49 7154/82250",
    "sg:postcode":"70806",
    "sg:province":"Baden-W\u00fcrttemberg",
    "wof:name":"Robos Bodamer Gmbh & Co. Kg",
    "wof:placetype":"venue"
},
  "geometry": {"coordinates":[9.2001867294,48.8705596924],"type":"Point"}
}