{
  "type": "Feature",
  "properties": {
    "iso:country":"DE",
    "sg:address":"Kurf\u00fcrstenallee 15",
    "sg:city":"Bremen",
    "sg:postcode":"28211",
    "sg:province":"Bremen",
    "wof:name":"Bremer Logenhaus E. V.",
    "wof:placetype":"venue"
},
  "geometry": {"coordinates":[8.8413095474,53.0810699463],"type":"Point"}
}