{
  "type": "Feature",
  "properties": {
    "iso:country":"DE",
    "sg:address":"Krowelstr. 5",
    "sg:city":"Berlin",
    "sg:phone":"+49 30/3321671",
    "sg:postcode":"13581",
    "sg:province":"Berlin",
    "wof:name":"Bodo Ginko",
    "wof:placetype":"venue"
},
  "geometry": {"coordinates":[13.201848,52.523968],"type":"Point"}
}