{
  "type": "Feature",
  "properties": {
    "iso:country":"DE",
    "sg:address":"Pfortenstr. 14",
    "sg:city":"M\u00fchlhausen",
    "sg:phone":"+49 36018/12527",
    "sg:postcode":"99974",
    "sg:province":"Th\u00fcringen",
    "wof:name":"Dieter Thon",
    "wof:placetype":"venue"
},
  "geometry": {"coordinates":[10.4551258087,51.2110977173],"type":"Point"}
}