{
  "type": "Feature",
  "properties": {
    "iso:country":"DE",
    "sg:address":"Heinrich-Heine-Str. 8",
    "sg:city":"Ennepetal",
    "sg:phone":"+49 2333/73878",
    "sg:postcode":"58256",
    "sg:province":"Nordrhein-Westfalen",
    "wof:name":"Rudolf Peikert Architekt",
    "wof:placetype":"venue"
},
  "geometry": {"coordinates":[7.355221,51.290707],"type":"Point"}
}