{
  "type": "Feature",
  "properties": {
    "iso:country":"DE",
    "sg:address":"Schulstr. 9",
    "sg:city":"Kumhausen",
    "sg:phone":"+49 871/41012",
    "sg:postcode":"84036",
    "sg:province":"Bayern",
    "wof:name":"Ziegel- Und Betonwerke Georg Bauer Gmbh & Co.",
    "wof:placetype":"venue"
},
  "geometry": {"coordinates":[12.1597652435,48.5070381165],"type":"Point"}
}