{
  "type": "Feature",
  "properties": {
    "iso:country":"DE",
    "sg:address":"B\u00e4renschanzstr. 89",
    "sg:city":"N\u00fcrnberg",
    "sg:phone":"+49 911/264837",
    "sg:postcode":"90429",
    "sg:province":"Bayern",
    "wof:name":"Zur Schmiede",
    "wof:placetype":"venue"
},
  "geometry": {"coordinates":[11.053147316,49.452545166],"type":"Point"}
}