{
  "type": "Feature",
  "properties": {
    "iso:country":"DE",
    "sg:address":"Ringstr. 1",
    "sg:city":"Waibstadt",
    "sg:phone":"+49 7263/3930",
    "sg:postcode":"74915",
    "sg:province":"Baden-W\u00fcrttemberg",
    "wof:name":"R. Freischlag",
    "wof:placetype":"venue"
},
  "geometry": {"coordinates":[8.9203968048,49.2989044189],"type":"Point"}
}