{
  "type": "Feature",
  "properties": {
    "iso:country":"DE",
    "sg:address":"Kapellenstr. 12",
    "sg:city":"Seligenstadt",
    "sg:phone":"+49 6182/3560",
    "sg:postcode":"63500",
    "sg:province":"Hessen",
    "wof:name":"F. Mayer",
    "wof:placetype":"venue"
},
  "geometry": {"coordinates":[8.969576,50.044552],"type":"Point"}
}