{
  "type": "Feature",
  "properties": {
    "iso:country":"DE",
    "sg:address":"Patroklusweg 37",
    "sg:city":"Dortmund",
    "sg:phone":"+49 231/7270030",
    "sg:postcode":"44229",
    "sg:province":"Nordrhein-Westfalen",
    "wof:name":"Kurpf\u00e4lzische Immobilien- Und Wohnungs Gmbh",
    "wof:placetype":"venue"
},
  "geometry": {"coordinates":[7.4625878334,51.4544334412],"type":"Point"}
}