{
  "type": "Feature",
  "properties": {
    "iso:country":"DE",
    "sg:address":"Entengasse 26",
    "sg:city":"Besigheim",
    "sg:phone":"+49 7143/31011",
    "sg:postcode":"74354",
    "sg:province":"Baden-W\u00fcrttemberg",
    "wof:name":"La Mode G. Waiblinger",
    "wof:placetype":"venue"
},
  "geometry": {"coordinates":[9.140995,49.00032],"type":"Point"}
}