{
  "type": "Feature",
  "properties": {
    "iso:country":"DE",
    "sg:address":"Uerdinger Str. 104",
    "sg:city":"Moers",
    "sg:postcode":"47441",
    "sg:province":"Nordrhein-Westfalen",
    "wof:name":"Bl Systems Gmbh",
    "wof:placetype":"venue"
},
  "geometry": {"coordinates":[6.6386737823,51.4435653687],"type":"Point"}
}