{
  "type": "Feature",
  "properties": {
    "iso:country":"DE",
    "sg:address":"Michelerstr. 1",
    "sg:city":"G\u00fcnzburg",
    "sg:phone":"+49 8221/31937",
    "sg:postcode":"89312",
    "sg:province":"Bayern",
    "wof:name":"Erwin Bodensteiner Rechtsanwalt",
    "wof:placetype":"venue"
},
  "geometry": {"coordinates":[10.2813663483,48.4450263977],"type":"Point"}
}