{
  "type": "Feature",
  "properties": {
    "iso:country":"DE",
    "sg:address":"Neuhof 4",
    "sg:city":"Blankenheim",
    "sg:phone":"+49 2697/7405",
    "sg:postcode":"53945",
    "sg:province":"Nordrhein-Westfalen",
    "wof:name":"P. Rick",
    "wof:placetype":"venue"
},
  "geometry": {"coordinates":[6.62662,50.438259],"type":"Point"}
}