{
  "type": "Feature",
  "properties": {
    "iso:country":"DE",
    "sg:address":"Groz-Beckert-Str. 4",
    "sg:city":"Wehingen",
    "sg:phone":"+49 7426/52900",
    "sg:postcode":"78564",
    "sg:province":"Baden-W\u00fcrttemberg",
    "wof:name":"Gewatec Gebr\u00fcder Walz Gmbh & Co. Kg",
    "wof:placetype":"venue"
},
  "geometry": {"coordinates":[8.7913761139,48.1487960815],"type":"Point"}
}