{
  "type": "Feature",
  "properties": {
    "iso:country":"DE",
    "sg:address":"Carl-von-Ossietzky-Str. 2",
    "sg:city":"Leverkusen",
    "sg:phone":"+49 214/92880",
    "sg:postcode":"51377",
    "sg:province":"Nordrhein-Westfalen",
    "wof:name":"R. Ludwig",
    "wof:placetype":"venue"
},
  "geometry": {"coordinates":[7.0621509552,51.0490875244],"type":"Point"}
}