{
  "type": "Feature",
  "properties": {
    "iso:country":"DE",
    "sg:address":"Danziger Weg 2",
    "sg:city":"Giebelstadt",
    "sg:phone":"+49 9334/1212",
    "sg:postcode":"97232",
    "sg:province":"Bayern",
    "wof:name":"Emil Kinzinger",
    "wof:placetype":"venue"
},
  "geometry": {"coordinates":[9.941675,49.653271],"type":"Point"}
}