{
  "type": "Feature",
  "properties": {
    "iso:country":"DE",
    "sg:address":"Spreuergasse 25",
    "sg:city":"Stuttgart",
    "sg:phone":"+49 711/9561396",
    "sg:postcode":"70372",
    "sg:province":"Baden-W\u00fcrttemberg",
    "wof:name":"Sch\u00e4fers Musikladen",
    "wof:placetype":"venue"
},
  "geometry": {"coordinates":[9.2160625458,48.8054466248],"type":"Point"}
}