{
  "type": "Feature",
  "properties": {
    "iso:country":"DE",
    "sg:address":"Widdergasse 2a",
    "sg:city":"Garbsen",
    "sg:phone":"+49 5137/79807",
    "sg:postcode":"30823",
    "sg:province":"Niedersachsen",
    "wof:name":"Klaus L\u00fcssen Architekt",
    "wof:placetype":"venue"
},
  "geometry": {"coordinates":[9.606507,52.417259],"type":"Point"}
}