{
  "type": "Feature",
  "properties": {
    "iso:country":"DE",
    "sg:address":"Ueckerstrasse 95",
    "sg:city":"Ueckerm\u00fcnde",
    "sg:phone":"+49 39771",
    "sg:postcode":"17373",
    "sg:province":"Mecklenburg-Vorpommern",
    "wof:name":"Der Maritime Geschenke Online Versandshop",
    "wof:placetype":"venue"
},
  "geometry": {"coordinates":[14.0463943481,53.7362213135],"type":"Point"}
}