{
  "type": "Feature",
  "properties": {
    "iso:country":"DE",
    "sg:address":"Gartenstr. 12",
    "sg:city":"Eisenberg",
    "sg:phone":"+49 36691/43822",
    "sg:postcode":"07607",
    "sg:province":"Th\u00fcringen",
    "wof:name":"Peter Hermann",
    "wof:placetype":"venue"
},
  "geometry": {"coordinates":[11.907107,50.969318],"type":"Point"}
}