{
  "type": "Feature",
  "properties": {
    "iso:country":"DE",
    "sg:address":"Hauptstr. 6",
    "sg:city":"Soltendieck",
    "sg:phone":"+49 5874/269",
    "sg:postcode":"29594",
    "sg:province":"Niedersachsen",
    "wof:name":"Alfred Schweitzer",
    "wof:placetype":"venue"
},
  "geometry": {"coordinates":[10.7612667084,52.8725776672],"type":"Point"}
}