{
  "type": "Feature",
  "properties": {
    "iso:country":"DE",
    "sg:address":"Laischaftsstr. 21",
    "sg:city":"Osnabr\u00fcck",
    "sg:phone":"+49 541/84084",
    "sg:postcode":"49080",
    "sg:province":"Niedersachsen",
    "wof:name":"B\u00f6ttcher Gmbh",
    "wof:placetype":"venue"
},
  "geometry": {"coordinates":[8.043357,52.266132],"type":"Point"}
}