{
  "type": "Feature",
  "properties": {
    "iso:country":"DE",
    "sg:address":"B\u00fctzgenweg 4",
    "sg:city":"Essen",
    "sg:phone":"+49 4920/1840080",
    "sg:postcode":"45239",
    "sg:province":"Nordrhein-Westfalen",
    "wof:name":"Tfa Fernmeldebau Kron Gmbh & Co. Kg",
    "wof:placetype":"venue"
},
  "geometry": {"coordinates":[7.0170049667,51.365146637],"type":"Point"}
}