{
  "type": "Feature",
  "properties": {
    "iso:country":"DE",
    "sg:address":"Innere Wiener Str. 30",
    "sg:city":"M\u00fcnchen",
    "sg:phone":"+49 89/482904",
    "sg:postcode":"81667",
    "sg:province":"Bayern",
    "wof:name":"Blumen Rudat",
    "wof:placetype":"venue"
},
  "geometry": {"coordinates":[11.594289,48.133553],"type":"Point"}
}