{
  "type": "Feature",
  "properties": {
    "iso:country":"DE",
    "sg:address":"Argelanderstr. 92",
    "sg:city":"Bonn",
    "sg:postcode":"53115",
    "sg:province":"Nordrhein-Westfalen",
    "wof:name":"Emsk Gmbh",
    "wof:placetype":"venue"
},
  "geometry": {"coordinates":[7.0986962318,50.7233047485],"type":"Point"}
}