{
  "type": "Feature",
  "properties": {
    "iso:country":"DE",
    "sg:address":"Am Kettelerplatz 10",
    "sg:city":"Bonn",
    "sg:phone":"+49 228/661344",
    "sg:postcode":"53121",
    "sg:province":"Nordrhein-Westfalen",
    "wof:name":"Antonius-apotheke",
    "wof:placetype":"venue"
},
  "geometry": {"coordinates":[7.049627,50.738949],"type":"Point"}
}