{
  "type": "Feature",
  "properties": {
    "iso:country":"DE",
    "sg:city":"Leverkusen",
    "sg:phone":"+49 214",
    "sg:postcode":"51371",
    "sg:province":"Nordrhein-Westfalen",
    "wof:name":"Camping Club Bonn",
    "wof:placetype":"venue"
},
  "geometry": {"coordinates":[6.950927,51.050503],"type":"Point"}
}