{
  "type": "Feature",
  "properties": {
    "iso:country":"DE",
    "sg:address":"Lindenweg 1",
    "sg:city":"Angelbachtal",
    "sg:postcode":"74918",
    "sg:province":"Baden-W\u00fcrttemberg",
    "wof:name":"Climacell Gmbh",
    "wof:placetype":"venue"
},
  "geometry": {"coordinates":[8.78241539,49.2254257202],"type":"Point"}
}