{
  "type": "Feature",
  "properties": {
    "iso:country":"DE",
    "sg:address":"Hanauer Str. 31",
    "sg:city":"Ronneburg",
    "sg:phone":"+49 6048/96060",
    "sg:postcode":"63549",
    "sg:province":"Hessen",
    "wof:name":"Staweli-wehrheim Kg",
    "wof:placetype":"venue"
},
  "geometry": {"coordinates":[9.057915,50.232609],"type":"Point"}
}