{
  "type": "Feature",
  "properties": {
    "iso:country":"DE",
    "sg:address":"Berliner Str. 22",
    "sg:city":"Gunzenhausen",
    "sg:phone":"+49 9831/89800",
    "sg:postcode":"91710",
    "sg:province":"Bayern",
    "wof:name":"Thilo Schmoll Innenarchitekt",
    "wof:placetype":"venue"
},
  "geometry": {"coordinates":[10.774332,49.122894],"type":"Point"}
}