{
  "type": "Feature",
  "properties": {
    "iso:country":"DE",
    "sg:address":"Gr\u00fcnaustr. 5",
    "sg:city":"Hannover",
    "sg:phone":"+49 511/496666",
    "sg:postcode":"30455",
    "sg:province":"Niedersachsen",
    "wof:name":"Peter Goetz Gmbh",
    "wof:placetype":"venue"
},
  "geometry": {"coordinates":[9.672638,52.356415],"type":"Point"}
}