{
  "type": "Feature",
  "properties": {
    "iso:country":"DE",
    "sg:address":"Freibadweg",
    "sg:city":"Burbach",
    "sg:phone":"+49 2736/6122",
    "sg:postcode":"57299",
    "sg:province":"Nordrhein-Westfalen",
    "wof:name":"Freibad Burbach",
    "wof:placetype":"venue"
},
  "geometry": {"coordinates":[8.0825004578,50.7430305481],"type":"Point"}
}