{
  "type": "Feature",
  "properties": {
    "iso:country":"DE",
    "sg:address":"Herrengraben 31",
    "sg:city":"Hamburg",
    "sg:phone":"+49 40/36975710",
    "sg:postcode":"20459",
    "sg:province":"Hamburg",
    "wof:name":"Ahrenkiel Seeschiffahrts- Beteiligungen Gmbh & Co. Kg",
    "wof:placetype":"venue"
},
  "geometry": {"coordinates":[9.981726,53.546104],"type":"Point"}
}