{
  "type": "Feature",
  "properties": {
    "iso:country":"DE",
    "sg:address":"Huppertzhof",
    "sg:city":"M\u00f6nchengladbach",
    "sg:postcode":"41066",
    "sg:province":"Nordrhein-Westfalen",
    "wof:name":"Atelier Heinz Mack K\u00fcnstler Aus M\u00f6nchengladbach",
    "wof:placetype":"venue"
},
  "geometry": {"coordinates":[6.468764782,51.2238693237],"type":"Point"}
}