{
  "type": "Feature",
  "properties": {
    "iso:country":"DE",
    "sg:address":"Johannes-Kepler-Str. 1",
    "sg:city":"Stuhr",
    "sg:phone":"+49 4942/156895",
    "sg:postcode":"28816",
    "sg:province":"Niedersachsen",
    "wof:name":"Bernhard W. Engbert Gmbh & Co.",
    "wof:placetype":"venue"
},
  "geometry": {"coordinates":[8.7692203522,53.0205688477],"type":"Point"}
}