{
  "type": "Feature",
  "properties": {
    "iso:country":"DE",
    "sg:address":"Dieselstr 18",
    "sg:city":"Limburg",
    "sg:phone":"+49 6431/22457",
    "sg:postcode":"65549",
    "sg:province":"Hessen",
    "wof:name":"Baugutachter Dipl.- Ing. Joachim Egenolf",
    "wof:placetype":"venue"
},
  "geometry": {"coordinates":[8.051859,50.400295],"type":"Point"}
}