{
  "type": "Feature",
  "properties": {
    "iso:country":"DE",
    "sg:address":"Neue Str. 11",
    "sg:city":"Backnang",
    "sg:phone":"+49 7191/68597",
    "sg:postcode":"71522",
    "sg:province":"Baden-W\u00fcrttemberg",
    "wof:name":"Krone Inh. E. Marquardt",
    "wof:placetype":"venue"
},
  "geometry": {"coordinates":[9.4325151443,48.9483757019],"type":"Point"}
}