{
  "type": "Feature",
  "properties": {
    "iso:country":"DE",
    "sg:address":"Ettinger Str. 24",
    "sg:city":"Ingolstadt",
    "sg:postcode":"85057",
    "sg:province":"Bayern",
    "wof:name":"Presse Und Lotto Cigar & Malt Peter Schiemann E. K.",
    "wof:placetype":"venue"
},
  "geometry": {"coordinates":[11.417269,48.775585],"type":"Point"}
}