{
  "type": "Feature",
  "properties": {
    "iso:country":"DE",
    "sg:address":"Ringstr. 157",
    "sg:city":"Essen",
    "sg:phone":"+49 2054/5264",
    "sg:postcode":"45219",
    "sg:province":"Nordrhein-Westfalen",
    "wof:name":"Breilmann Haircompany Friseurbetriebs Gmbh",
    "wof:placetype":"venue"
},
  "geometry": {"coordinates":[6.9338870049,51.359249115],"type":"Point"}
}