{
  "type": "Feature",
  "properties": {
    "iso:country":"DE",
    "sg:address":"F\u00fcrstenfeldbrucker Str. 12",
    "sg:city":"Olching",
    "sg:phone":"+49 8142/18455",
    "sg:postcode":"82140",
    "sg:province":"Bayern",
    "wof:name":"A. Eldersch",
    "wof:placetype":"venue"
},
  "geometry": {"coordinates":[11.322288,48.202141],"type":"Point"}
}