{
  "type": "Feature",
  "properties": {
    "iso:country":"DE",
    "sg:address":"Bechlingen 6",
    "sg:city":"Tettnang",
    "sg:postcode":"88069",
    "sg:province":"Baden-W\u00fcrttemberg",
    "wof:name":"Safe Divers Intern. Standard Fischer & Commerell Ohg",
    "wof:placetype":"venue"
},
  "geometry": {"coordinates":[9.5874385834,47.6790924072],"type":"Point"}
}