{
  "type": "Feature",
  "properties": {
    "iso:country":"DE",
    "sg:address":"Im Winkel 3",
    "sg:city":"B\u00f6r\u00dfum",
    "sg:phone":"+49 5334/6402",
    "sg:postcode":"38312",
    "sg:province":"Niedersachsen",
    "wof:name":"Friedrich L\u00f6hr",
    "wof:placetype":"venue"
},
  "geometry": {"coordinates":[10.587188,52.068489],"type":"Point"}
}