{
  "type": "Feature",
  "properties": {
    "iso:country":"DE",
    "sg:address":"Silder Moor 3",
    "sg:city":"Kavelstorf",
    "sg:phone":"+49 38208/809810",
    "sg:postcode":"18196",
    "sg:province":"Mecklenburg-Vorpommern",
    "wof:name":"Suchen Und Finden In Rostock",
    "wof:placetype":"venue"
},
  "geometry": {"coordinates":[12.226105,54.016113],"type":"Point"}
}