{
  "type": "Feature",
  "properties": {
    "iso:country":"DE",
    "sg:address":"Alte Blankenburger Heerstr.",
    "sg:city":"Halberstadt",
    "sg:phone":"+49 3941/26159",
    "sg:postcode":"38820",
    "sg:province":"Sachsen-Anhalt",
    "wof:name":"Agip Deutschland Ag",
    "wof:placetype":"venue"
},
  "geometry": {"coordinates":[11.0310583115,51.8851509094],"type":"Point"}
}