{
  "type": "Feature",
  "properties": {
    "iso:country":"DE",
    "sg:address":"Hauptstr. 49",
    "sg:city":"Ostercappeln",
    "sg:phone":"+49 5476/1797",
    "sg:postcode":"49179",
    "sg:province":"Niedersachsen",
    "wof:name":"Erich Grafeneder Heilpraktiker",
    "wof:placetype":"venue"
},
  "geometry": {"coordinates":[8.2187767029,52.3611946106],"type":"Point"}
}