{
  "type": "Feature",
  "properties": {
    "iso:country":"DE",
    "sg:address":"Bebelstr. 151",
    "sg:city":"Oberhausen",
    "sg:phone":"+49 208/846077",
    "sg:postcode":"46049",
    "sg:province":"Nordrhein-Westfalen",
    "wof:name":"W. Br\u00fchl",
    "wof:placetype":"venue"
},
  "geometry": {"coordinates":[6.8356032372,51.4637145996],"type":"Point"}
}