{
  "type": "Feature",
  "properties": {
    "iso:country":"DE",
    "sg:address":"Am Wingert 147",
    "sg:city":"D\u00fcren",
    "sg:phone":"+49 2421/61396",
    "sg:postcode":"52355",
    "sg:province":"Nordrhein-Westfalen",
    "wof:name":"Ewald Lennartz",
    "wof:placetype":"venue"
},
  "geometry": {"coordinates":[6.443711,50.790779],"type":"Point"}
}