{
  "type": "Feature",
  "properties": {
    "iso:country":"DE",
    "sg:address":"Industriestr. 8 - 13",
    "sg:city":"Hemmoor",
    "sg:phone":"+49 4947/716030",
    "sg:postcode":"21745",
    "sg:province":"Niedersachsen",
    "wof:name":"Bargstedt Handlingsysteme Gmbh",
    "wof:placetype":"venue"
},
  "geometry": {"coordinates":[9.156568,53.683277],"type":"Point"}
}