{
  "type": "Feature",
  "properties": {
    "iso:country":"DE",
    "sg:address":"Gutenbergweg 11",
    "sg:city":"Beckum",
    "sg:phone":"+49 2521/7525",
    "sg:postcode":"59269",
    "sg:province":"Nordrhein-Westfalen",
    "wof:name":"Winfried Blaschke Architekt",
    "wof:placetype":"venue"
},
  "geometry": {"coordinates":[8.032443,51.750607],"type":"Point"}
}