{
  "type": "Feature",
  "properties": {
    "iso:country":"DE",
    "sg:address":"Robert-Koch-Str. 42",
    "sg:city":"Eningen",
    "sg:phone":"+49 7121/88505",
    "sg:postcode":"72800",
    "sg:province":"Baden-W\u00fcrttemberg",
    "wof:name":"M. Auchter Industrievertretungen",
    "wof:placetype":"venue"
},
  "geometry": {"coordinates":[9.2789697647,48.4830513],"type":"Point"}
}