{
  "type": "Feature",
  "properties": {
    "iso:country":"DE",
    "sg:address":"Straubinger Str. 16",
    "sg:city":"M\u00fcnchen",
    "sg:phone":"+49 89/572240",
    "sg:postcode":"80687",
    "sg:province":"Bayern",
    "wof:name":"M. Brunner",
    "wof:placetype":"venue"
},
  "geometry": {"coordinates":[11.5197143555,48.1379737854],"type":"Point"}
}