{
  "type": "Feature",
  "properties": {
    "iso:country":"DE",
    "sg:address":"Marktstr. 40",
    "sg:city":"Freyenstein",
    "sg:phone":"+49 33967/60214",
    "sg:postcode":"16918",
    "sg:province":"Brandenburg",
    "wof:name":"Wolfgang Briesemeister",
    "wof:placetype":"venue"
},
  "geometry": {"coordinates":[12.353975296,53.2870559692],"type":"Point"}
}