{
  "type": "Feature",
  "properties": {
    "iso:country":"DE",
    "sg:address":"Ebenreuth 6",
    "sg:city":"Thurmansbang",
    "sg:phone":"+49 9907/331",
    "sg:postcode":"94169",
    "sg:province":"Bayern",
    "wof:name":"M. Geier",
    "wof:placetype":"venue"
},
  "geometry": {"coordinates":[13.2842817307,48.8009567261],"type":"Point"}
}