{
  "type": "Feature",
  "properties": {
    "iso:country":"DE",
    "sg:address":"K\u00f6nigstr. 8",
    "sg:city":"Tuttlingen",
    "sg:phone":"+49 7461/12494",
    "sg:postcode":"78532",
    "sg:province":"Baden-W\u00fcrttemberg",
    "wof:name":"Step In Jeans Und Junge Mode Gmbh",
    "wof:placetype":"venue"
},
  "geometry": {"coordinates":[8.81997,47.984577],"type":"Point"}
}