{
  "type": "Feature",
  "properties": {
    "iso:country":"DE",
    "sg:address":"Nassauische Str. 57",
    "sg:city":"Berlin",
    "sg:phone":"+49 30/8610875",
    "sg:postcode":"10717",
    "sg:province":"Berlin",
    "wof:name":"Berg-apotheke",
    "wof:placetype":"venue"
},
  "geometry": {"coordinates":[13.326737,52.490696],"type":"Point"}
}