{
  "type": "Feature",
  "properties": {
    "iso:country":"DE",
    "sg:address":"Gro\u00dfe Eschenheimer Str. 41a",
    "sg:city":"Frankfurt",
    "sg:phone":"+49 69/280001",
    "sg:postcode":"60313",
    "sg:province":"Hessen",
    "wof:name":"Steinweg Gmbh",
    "wof:placetype":"venue"
},
  "geometry": {"coordinates":[8.679476738,50.1162109375],"type":"Point"}
}