{
  "type": "Feature",
  "properties": {
    "iso:country":"DE",
    "sg:address":"Schwarzwaldstr 11",
    "sg:city":"Singen",
    "sg:phone":"+49 7731/66655",
    "sg:postcode":"78224",
    "sg:province":"Baden-W\u00fcrttemberg",
    "wof:name":"Schlie\u00df- Und Sicherheitstechnik Steinmann Gmbh",
    "wof:placetype":"venue"
},
  "geometry": {"coordinates":[8.83947,47.761448],"type":"Point"}
}