{
  "type": "Feature",
  "properties": {
    "iso:country":"DE",
    "sg:address":"Marburger Str. 44",
    "sg:city":"Lollar",
    "sg:phone":"+49 6406/73134",
    "sg:postcode":"35457",
    "sg:province":"Hessen",
    "wof:name":"Kurt Horst",
    "wof:placetype":"venue"
},
  "geometry": {"coordinates":[8.706807,50.651478],"type":"Point"}
}