{
  "type": "Feature",
  "properties": {
    "iso:country":"DE",
    "sg:address":"Welfengarten 1A",
    "sg:city":"Hannover",
    "sg:phone":"+49 511/7010670",
    "sg:postcode":"30167",
    "sg:province":"Niedersachsen",
    "wof:name":"Institut F\u00fcr Maschinenelemente",
    "wof:placetype":"venue"
},
  "geometry": {"coordinates":[9.7178087234,52.3822517395],"type":"Point"}
}