{
  "type": "Feature",
  "properties": {
    "iso:country":"DE",
    "sg:address":"Im Feldle 9",
    "sg:city":"Calw",
    "sg:phone":"+49 7051/79240",
    "sg:postcode":"75365",
    "sg:province":"Baden-W\u00fcrttemberg",
    "wof:name":"K\u00f6gler Gmbh & Co Calw Kg",
    "wof:placetype":"venue"
},
  "geometry": {"coordinates":[8.766634,48.707611],"type":"Point"}
}