{
  "type": "Feature",
  "properties": {
    "iso:country":"DE",
    "sg:address":"Spaglstr. 2",
    "sg:city":"Hutthurm",
    "sg:phone":"+49 8505/9400",
    "sg:postcode":"94116",
    "sg:province":"Bayern",
    "wof:name":"Spagl Gmbh",
    "wof:placetype":"venue"
},
  "geometry": {"coordinates":[13.4522447586,48.6888847351],"type":"Point"}
}