{
  "type": "Feature",
  "properties": {
    "iso:country":"DE",
    "sg:address":"In den Rosen\u00e4ckern 10",
    "sg:city":"Braunschweig",
    "sg:phone":"+49 531/2567013",
    "sg:postcode":"38116",
    "sg:province":"Niedersachsen",
    "wof:name":"Seniorenzentrum Stadt Braunschweig",
    "wof:placetype":"venue"
},
  "geometry": {"coordinates":[10.480678,52.273518],"type":"Point"}
}