{
  "type": "Feature",
  "properties": {
    "iso:country":"DE",
    "sg:address":"Lothringer Str. 11",
    "sg:city":"Friedberg",
    "sg:phone":"+49 821/665554",
    "sg:postcode":"86316",
    "sg:province":"Bayern",
    "wof:name":"Judith Geisdorf Heilpraktikerin",
    "wof:placetype":"venue"
},
  "geometry": {"coordinates":[10.957151413,48.3503417969],"type":"Point"}
}