{
  "type": "Feature",
  "properties": {
    "iso:country":"DE",
    "sg:address":"Breitenbronner Str. 46",
    "sg:city":"Aglasterhausen",
    "sg:phone":"+49 6262/6233",
    "sg:postcode":"74858",
    "sg:province":"Baden-W\u00fcrttemberg",
    "wof:name":"Karlheinz Bender Gartenbaubetrieb",
    "wof:placetype":"venue"
},
  "geometry": {"coordinates":[8.99152,49.357368],"type":"Point"}
}