{
  "type": "Feature",
  "properties": {
    "iso:country":"DE",
    "sg:address":"Erlenweg 6",
    "sg:city":"B\u00f6rger",
    "sg:phone":"+49 5953/1562",
    "sg:postcode":"26904",
    "sg:province":"Niedersachsen",
    "wof:name":"Thomas Belke",
    "wof:placetype":"venue"
},
  "geometry": {"coordinates":[7.546754837,52.9164657593],"type":"Point"}
}