{
  "type": "Feature",
  "properties": {
    "iso:country":"DE",
    "sg:address":"Im Hahnacker 38",
    "sg:city":"Saarlouis",
    "sg:phone":"+49 6831/893429",
    "sg:postcode":"66740",
    "sg:province":"Saarland",
    "wof:name":"Aweiwi Kurierdienst Gmbh",
    "wof:placetype":"venue"
},
  "geometry": {"coordinates":[6.75065,49.339085],"type":"Point"}
}