{
  "type": "Feature",
  "properties": {
    "iso:country":"DE",
    "sg:address":"Rathausstr. 17",
    "sg:city":"Oerlinghausen",
    "sg:phone":"+49 5202/9939390",
    "sg:postcode":"33813",
    "sg:province":"Nordrhein-Westfalen",
    "wof:name":"F. Lange",
    "wof:placetype":"venue"
},
  "geometry": {"coordinates":[8.6658315659,51.9608688354],"type":"Point"}
}