{
  "type": "Feature",
  "properties": {
    "iso:country":"DE",
    "sg:address":"Werastr. 93",
    "sg:city":"Stuttgart",
    "sg:phone":"+49 711/2624155",
    "sg:postcode":"70190",
    "sg:province":"Baden-W\u00fcrttemberg",
    "wof:name":"Widmann Und Jonk Rechtsanw\u00e4lte",
    "wof:placetype":"venue"
},
  "geometry": {"coordinates":[9.1938648224,48.7860565186],"type":"Point"}
}