{
  "type": "Feature",
  "properties": {
    "iso:country":"DE",
    "sg:address":"Geheimrat-Rosenthal-Str. 115",
    "sg:city":"Selb",
    "sg:phone":"+49 9287/2742",
    "sg:postcode":"95100",
    "sg:province":"Bayern",
    "wof:name":"Erna Zeidler",
    "wof:placetype":"venue"
},
  "geometry": {"coordinates":[12.1417245865,50.1879768372],"type":"Point"}
}