{
  "type": "Feature",
  "properties": {
    "iso:country":"DE",
    "sg:address":"S\u00fcddorfer Str. 6",
    "sg:city":"Edewecht",
    "sg:postcode":"26188",
    "sg:province":"Niedersachsen",
    "wof:name":"Werner Tholen",
    "wof:placetype":"venue"
},
  "geometry": {"coordinates":[7.9436941147,53.1047935486],"type":"Point"}
}