{
  "type": "Feature",
  "properties": {
    "iso:country":"DE",
    "sg:address":"Klausenerstr. 35",
    "sg:city":"Magdeburg",
    "sg:phone":"+49 391/568300",
    "sg:postcode":"39112",
    "sg:province":"Sachsen-Anhalt",
    "wof:name":"Domus-immobilien- Verwaltungsges. Mbh",
    "wof:placetype":"venue"
},
  "geometry": {"coordinates":[11.604857,52.116058],"type":"Point"}
}