{
  "type": "Feature",
  "properties": {
    "iso:country":"DE",
    "sg:address":"Dorfstr. 34",
    "sg:city":"Oststeinbek",
    "sg:phone":"+49 40/7399565",
    "sg:postcode":"22113",
    "sg:province":"Schleswig-Holstein",
    "wof:name":"Hans-heinrich Wulff",
    "wof:placetype":"venue"
},
  "geometry": {"coordinates":[10.1691083908,53.5260314941],"type":"Point"}
}