{
  "type": "Feature",
  "properties": {
    "iso:country":"DE",
    "sg:address":"Am Starzenbach 5",
    "sg:city":"Wolnzach",
    "sg:phone":"+49 8442/92550",
    "sg:postcode":"85283",
    "sg:province":"Bayern",
    "wof:name":"Waltron Elektronik-vertriebs-gmbh",
    "wof:placetype":"venue"
},
  "geometry": {"coordinates":[11.6268310547,48.6021728516],"type":"Point"}
}