{
  "type": "Feature",
  "properties": {
    "iso:country":"DE",
    "sg:address":"M\u00fcnchinger Str. 22",
    "sg:city":"Markgr\u00f6ningen",
    "sg:phone":"+49 7145/5309",
    "sg:postcode":"71706",
    "sg:province":"Baden-W\u00fcrttemberg",
    "wof:name":"Stuber",
    "wof:placetype":"venue"
},
  "geometry": {"coordinates":[9.084162,48.901569],"type":"Point"}
}