{
  "type": "Feature",
  "properties": {
    "iso:country":"DE",
    "sg:address":"Magdeburger Str. 97",
    "sg:city":"Sch\u00f6nebeck",
    "sg:phone":"+49 3928/81107",
    "sg:postcode":"39218",
    "sg:province":"Sachsen-Anhalt",
    "wof:name":"Franz Plake",
    "wof:placetype":"venue"
},
  "geometry": {"coordinates":[11.716516,52.005726],"type":"Point"}
}