{
  "type": "Feature",
  "properties": {
    "iso:country":"DE",
    "sg:address":"Mengenicher Str. 12",
    "sg:city":"K\u00f6ln",
    "sg:phone":"+49 221/5902739",
    "sg:postcode":"50767",
    "sg:province":"Nordrhein-Westfalen",
    "wof:name":"Hotel-restaurant Sch\u00fctzenhof",
    "wof:placetype":"venue"
},
  "geometry": {"coordinates":[6.8757181168,50.9975852966],"type":"Point"}
}