{
  "type": "Feature",
  "properties": {
    "iso:country":"DE",
    "sg:address":"K\u00f6rnerstr. 1",
    "sg:city":"Westerburg",
    "sg:phone":"+49 2663/4784",
    "sg:postcode":"56457",
    "sg:province":"Rheinland-Pfalz",
    "wof:name":"Studio Sonnenschein Gmbh",
    "wof:placetype":"venue"
},
  "geometry": {"coordinates":[7.970108,50.559544],"type":"Point"}
}