{
  "type": "Feature",
  "properties": {
    "iso:country":"DE",
    "sg:address":"Vulkanstr. 13",
    "sg:city":"D\u00fcsseldorf",
    "sg:phone":"+49 211/780628",
    "sg:postcode":"40227",
    "sg:province":"Nordrhein-Westfalen",
    "wof:name":"Sport Akademie Kim",
    "wof:placetype":"venue"
},
  "geometry": {"coordinates":[6.7920007706,51.2163963318],"type":"Point"}
}