{
  "type": "Feature",
  "properties": {
    "iso:country":"DE",
    "sg:address":"P\u00f6deldorfer Str. 4",
    "sg:city":"Litzendorf",
    "sg:phone":"+49 9505/1658",
    "sg:postcode":"96123",
    "sg:province":"Bayern",
    "wof:name":"Bruno Und Elisabeth Knoblach",
    "wof:placetype":"venue"
},
  "geometry": {"coordinates":[11.0048208237,49.9257774353],"type":"Point"}
}