{
  "type": "Feature",
  "properties": {
    "iso:country":"DE",
    "sg:address":"Hauptstr. 18",
    "sg:city":"Adelshofen",
    "sg:phone":"+49 9865/941810",
    "sg:postcode":"91587",
    "sg:province":"Bayern",
    "wof:name":"Pevak-putz Und Stuck Gmbh",
    "wof:placetype":"venue"
},
  "geometry": {"coordinates":[10.17511,49.437653],"type":"Point"}
}