{
  "type": "Feature",
  "properties": {
    "iso:country":"DE",
    "sg:address":"Zeppelinstr. 2",
    "sg:city":"Plettenberg",
    "sg:phone":"+49 2391/10103",
    "sg:postcode":"58840",
    "sg:province":"Nordrhein-Westfalen",
    "wof:name":"Colortap Gmbh",
    "wof:placetype":"venue"
},
  "geometry": {"coordinates":[7.8666939735,51.205821991],"type":"Point"}
}