{
  "type": "Feature",
  "properties": {
    "iso:country":"DE",
    "sg:address":"Eichenstr. 57",
    "sg:city":"Oldenburg",
    "sg:phone":"+49 441/53567",
    "sg:postcode":"26131",
    "sg:province":"Niedersachsen",
    "wof:name":"Kath. Pfarramt St. Willehad",
    "wof:placetype":"venue"
},
  "geometry": {"coordinates":[8.1809473038,53.1381759644],"type":"Point"}
}