{
  "type": "Feature",
  "properties": {
    "iso:country":"DE",
    "sg:address":"Altenglaner Str. 7",
    "sg:city":"Bosenbach",
    "sg:phone":"+49 6385/1385",
    "sg:postcode":"66887",
    "sg:province":"Rheinland-Pfalz",
    "wof:name":"Hotel Westrich",
    "wof:placetype":"venue"
},
  "geometry": {"coordinates":[7.4966812134,49.5427703857],"type":"Point"}
}