{
  "type": "Feature",
  "properties": {
    "iso:country":"DE",
    "sg:address":"Osterstr. 7",
    "sg:city":"Aurich",
    "sg:phone":"+49 4941/2810",
    "sg:postcode":"26603",
    "sg:province":"Niedersachsen",
    "wof:name":"Johann Christmann Inh. Wilhelm F\u00fcrst",
    "wof:placetype":"venue"
},
  "geometry": {"coordinates":[7.483154,53.469437],"type":"Point"}
}