{
  "type": "Feature",
  "properties": {
    "iso:country":"DE",
    "sg:address":"Hauptstr. 14",
    "sg:city":"Gaildorf",
    "sg:phone":"+49 7971/6662",
    "sg:postcode":"74405",
    "sg:province":"Baden-W\u00fcrttemberg",
    "wof:name":"Heinrich Maier",
    "wof:placetype":"venue"
},
  "geometry": {"coordinates":[9.776772,48.980328],"type":"Point"}
}