{
  "type": "Feature",
  "properties": {
    "iso:country":"DE",
    "sg:address":"Molkereistr. 12",
    "sg:city":"Regen",
    "sg:phone":"+49 9921/2177",
    "sg:postcode":"94209",
    "sg:province":"Bayern",
    "wof:name":"Autovermietung Riedl",
    "wof:placetype":"venue"
},
  "geometry": {"coordinates":[13.13446,48.966572],"type":"Point"}
}