{
  "type": "Feature",
  "properties": {
    "iso:country":"DE",
    "sg:address":"Mittelstr. 38",
    "sg:city":"Extertal",
    "sg:phone":"+49 5262/3197",
    "sg:postcode":"32699",
    "sg:province":"Nordrhein-Westfalen",
    "wof:name":"Hotel Unter Den Linden",
    "wof:placetype":"venue"
},
  "geometry": {"coordinates":[9.1275959015,52.0680885315],"type":"Point"}
}