{
  "type": "Feature",
  "properties": {
    "iso:country":"DE",
    "sg:address":"Hauptstr. 9",
    "sg:city":"Rheinbach",
    "sg:phone":"+49 2226/13326",
    "sg:postcode":"53359",
    "sg:province":"Nordrhein-Westfalen",
    "wof:name":"Gastst\u00e4tte Ch. Und G. Kremmi",
    "wof:placetype":"venue"
},
  "geometry": {"coordinates":[6.9503397942,50.625667572],"type":"Point"}
}