{
  "type": "Feature",
  "properties": {
    "iso:country":"DE",
    "sg:address":"Eschstr. 37",
    "sg:city":"Stadtlohn",
    "sg:phone":"+49 2563/97133",
    "sg:postcode":"48703",
    "sg:province":"Nordrhein-Westfalen",
    "wof:name":"China",
    "wof:placetype":"venue"
},
  "geometry": {"coordinates":[6.9144377708,51.9895935059],"type":"Point"}
}