{
  "type": "Feature",
  "properties": {
    "iso:country":"DE",
    "sg:address":"Ringstr. 2",
    "sg:city":"Schwedt",
    "sg:phone":"+49 3332/418094",
    "sg:postcode":"16303",
    "sg:province":"Brandenburg",
    "wof:name":"Wert-haushaltger\u00e4te",
    "wof:placetype":"venue"
},
  "geometry": {"coordinates":[14.2687578201,53.0659980774],"type":"Point"}
}