{
  "type": "Feature",
  "properties": {
    "iso:country":"DE",
    "sg:address":"Diezstr. 7",
    "sg:city":"Gie\u00dfen",
    "sg:phone":"+49 641/932680",
    "sg:postcode":"35390",
    "sg:province":"Hessen",
    "wof:name":"E.-l. Sommerlad Und J. Giers Architekten",
    "wof:placetype":"venue"
},
  "geometry": {"coordinates":[8.677245,50.585426],"type":"Point"}
}