{
  "type": "Feature",
  "properties": {
    "iso:country":"DE",
    "sg:address":"Kamekestr. 31",
    "sg:city":"K\u00f6ln",
    "sg:phone":"+49 221/517366",
    "sg:postcode":"50672",
    "sg:province":"Nordrhein-Westfalen",
    "wof:name":"J.u.h. Rondholz Nachf. Horst Meier E. K.",
    "wof:placetype":"venue"
},
  "geometry": {"coordinates":[6.9374828339,50.9430961609],"type":"Point"}
}