{
  "type": "Feature",
  "properties": {
    "iso:country":"DE",
    "sg:city":"Bad Homburg v.d.H.",
    "sg:postcode":"61352",
    "sg:province":"Hessen",
    "wof:name":"Media-print Taunusdruck",
    "wof:placetype":"venue"
},
  "geometry": {"coordinates":[8.68215,50.226044],"type":"Point"}
}