{
  "type": "Feature",
  "properties": {
    "iso:country":"DE",
    "sg:address":"Altgandersheim",
    "sg:city":"Bad Gandersheim",
    "sg:phone":"+49 4953/825095",
    "sg:postcode":"37581",
    "sg:province":"Niedersachsen",
    "wof:name":"Gandersheimer Volksbank Eg",
    "wof:placetype":"venue"
},
  "geometry": {"coordinates":[10.056145,51.908562],"type":"Point"}
}