{
  "type": "Feature",
  "properties": {
    "iso:country":"DE",
    "sg:address":"Schulstr 5-7",
    "sg:city":"Fl\u00f6rsheim",
    "sg:phone":"+49 6145/938017",
    "sg:postcode":"65439",
    "sg:province":"Hessen",
    "wof:name":"Mp Marketing Promotion Gmbh",
    "wof:placetype":"venue"
},
  "geometry": {"coordinates":[8.424145,50.009693],"type":"Point"}
}