{
  "type": "Feature",
  "properties": {
    "iso:country":"DE",
    "sg:address":"Steinenstr. 83",
    "sg:city":"Bad S\u00e4ckingen",
    "sg:phone":"+49 7761/919955",
    "sg:postcode":"79713",
    "sg:province":"Baden-W\u00fcrttemberg",
    "wof:name":"Bauunternehmen Schmid Gmbh",
    "wof:placetype":"venue"
},
  "geometry": {"coordinates":[7.914211,47.574718],"type":"Point"}
}