{
  "type": "Feature",
  "properties": {
    "iso:country":"DE",
    "sg:address":"Naheweinstr. 213",
    "sg:city":"Langenlonsheim",
    "sg:phone":"+49 6704/1362",
    "sg:postcode":"55450",
    "sg:province":"Rheinland-Pfalz",
    "wof:name":"F. H. B\u00e4hr",
    "wof:placetype":"venue"
},
  "geometry": {"coordinates":[7.8992381096,49.9017181396],"type":"Point"}
}