{
  "type": "Feature",
  "properties": {
    "iso:country":"DE",
    "sg:address":"R\u00f6ntgenstr. 42",
    "sg:city":"Hof",
    "sg:postcode":"95032",
    "sg:province":"Bayern",
    "wof:name":"Spog Immobilien Gmbh & Co. Kg",
    "wof:placetype":"venue"
},
  "geometry": {"coordinates":[11.904865,50.299397],"type":"Point"}
}