{
  "type": "Feature",
  "properties": {
    "iso:country":"DE",
    "sg:address":"Viktoriastr. 2",
    "sg:city":"Aachen",
    "sg:phone":"+49 241/500573",
    "sg:postcode":"52066",
    "sg:province":"Nordrhein-Westfalen",
    "wof:name":"Anna Opree",
    "wof:placetype":"venue"
},
  "geometry": {"coordinates":[6.1064209938,50.774055481],"type":"Point"}
}