{
  "type": "Feature",
  "properties": {
    "iso:country":"DE",
    "sg:address":"Rahlstedter Str. 98",
    "sg:city":"Hamburg",
    "sg:phone":"+49 40/6777010",
    "sg:postcode":"22149",
    "sg:province":"Hamburg",
    "wof:name":"Sch\u00f6nfelder Technische Bauelemente E. K.",
    "wof:placetype":"venue"
},
  "geometry": {"coordinates":[10.154255867,53.5983657837],"type":"Point"}
}