{
  "type": "Feature",
  "properties": {
    "iso:country":"DE",
    "sg:address":"Karlstr. 8",
    "sg:city":"Fulda",
    "sg:phone":"+49 661/78828",
    "sg:postcode":"36037",
    "sg:province":"Hessen",
    "wof:name":"M. Dietz",
    "wof:placetype":"venue"
},
  "geometry": {"coordinates":[9.6760883331,50.5498352051],"type":"Point"}
}