{
  "type": "Feature",
  "properties": {
    "iso:country":"DE",
    "sg:address":"Dumicker Str. 3",
    "sg:city":"Drolshagen",
    "sg:phone":"+49 2761/64572",
    "sg:postcode":"57489",
    "sg:province":"Nordrhein-Westfalen",
    "wof:name":"Ulrich Schimanski Ingenieur",
    "wof:placetype":"venue"
},
  "geometry": {"coordinates":[7.8201370239,51.0592803955],"type":"Point"}
}