{
  "type": "Feature",
  "properties": {
    "iso:country":"DE",
    "sg:address":"Siedlerstr. 18",
    "sg:city":"Schwerte",
    "sg:phone":"+49 2304/63112",
    "sg:postcode":"58239",
    "sg:province":"Nordrhein-Westfalen",
    "wof:name":"I. Wilk",
    "wof:placetype":"venue"
},
  "geometry": {"coordinates":[7.5290751457,51.4265937805],"type":"Point"}
}