{
  "type": "Feature",
  "properties": {
    "iso:country":"DE",
    "sg:address":"Listrupweg 35",
    "sg:city":"Rheine",
    "sg:phone":"+49 5971/83340",
    "sg:postcode":"48429",
    "sg:province":"Nordrhein-Westfalen",
    "wof:name":"Mirring & Partner Gmbh Werbeagentur",
    "wof:placetype":"venue"
},
  "geometry": {"coordinates":[7.4376740456,52.288269043],"type":"Point"}
}