{
  "type": "Feature",
  "properties": {
    "iso:country":"DE",
    "sg:address":"August-Rost-Str. 9",
    "sg:city":"Arnstadt",
    "sg:phone":"+49 3628/629020",
    "sg:postcode":"99310",
    "sg:province":"Th\u00fcringen",
    "wof:name":"Hermos Gesellschaft F\u00fcr Steuer-mess- Und",
    "wof:placetype":"venue"
},
  "geometry": {"coordinates":[10.951198,50.855125],"type":"Point"}
}