{
  "type": "Feature",
  "properties": {
    "iso:country":"DE",
    "sg:address":"Hans-Rollwagen-Str. 8",
    "sg:city":"Augsburg",
    "sg:phone":"+49 821/544303",
    "sg:postcode":"86157",
    "sg:province":"Bayern",
    "wof:name":"Superco Handels Gmbh",
    "wof:placetype":"venue"
},
  "geometry": {"coordinates":[10.8620119095,48.3551254272],"type":"Point"}
}