{
  "type": "Feature",
  "properties": {
    "iso:country":"DE",
    "sg:address":"W\u00f6rthstr. 30",
    "sg:city":"M\u00fcnchen",
    "sg:phone":"+49 89/4486627",
    "sg:postcode":"81667",
    "sg:province":"Bayern",
    "wof:name":"Farben & Lacke Macke",
    "wof:placetype":"venue"
},
  "geometry": {"coordinates":[11.60079,48.129673],"type":"Point"}
}