{
  "type": "Feature",
  "properties": {
    "iso:country":"DE",
    "sg:address":"Hans-Fallada-Str. 8",
    "sg:city":"Greifswald",
    "sg:phone":"+49 3834/502472",
    "sg:postcode":"17489",
    "sg:province":"Mecklenburg-Vorpommern",
    "wof:name":"Urbano Gesellschaft F\u00fcr Parf\u00fcm-handel Mbh",
    "wof:placetype":"venue"
},
  "geometry": {"coordinates":[13.3670682907,54.0968132019],"type":"Point"}
}