{
  "type": "Feature",
  "properties": {
    "iso:country":"DE",
    "sg:address":"Tempelhofer Str. 33",
    "sg:city":"Wiesbaden",
    "sg:phone":"+49 611/702424",
    "sg:postcode":"65205",
    "sg:province":"Hessen",
    "wof:name":"Gerhard Reinemer",
    "wof:placetype":"venue"
},
  "geometry": {"coordinates":[8.29615,50.061802],"type":"Point"}
}