{
  "type": "Feature",
  "properties": {
    "iso:country":"DE",
    "sg:address":"Wadgasser Str. 163",
    "sg:city":"Wadgassen",
    "sg:phone":"+49 6834/943076",
    "sg:postcode":"66787",
    "sg:province":"Saarland",
    "wof:name":"Walter B\u00f6hm Steuerberater",
    "wof:placetype":"venue"
},
  "geometry": {"coordinates":[6.8070402145,49.2665138245],"type":"Point"}
}