{
  "type": "Feature",
  "properties": {
    "iso:country":"DE",
    "sg:address":"Kleiststr. 4",
    "sg:city":"B\u00f6blingen",
    "sg:phone":"+49 7031/223159",
    "sg:postcode":"71032",
    "sg:province":"Baden-W\u00fcrttemberg",
    "wof:name":"Anneliese Schabdach",
    "wof:placetype":"venue"
},
  "geometry": {"coordinates":[9.0171337128,48.6941223145],"type":"Point"}
}