{
  "type": "Feature",
  "properties": {
    "iso:country":"DE",
    "sg:address":"Hauptstr. 33",
    "sg:city":"Bastheim",
    "sg:phone":"+49 9773/363",
    "sg:postcode":"97654",
    "sg:province":"Bayern",
    "wof:name":"G\u00fcnter Irmschler Bildhauer",
    "wof:placetype":"venue"
},
  "geometry": {"coordinates":[10.200632,50.40324],"type":"Point"}
}