{
  "type": "Feature",
  "properties": {
    "iso:country":"DE",
    "sg:address":"St.-Stephans-Platz 3",
    "sg:city":"Griesheim",
    "sg:phone":"+49 6155/62203",
    "sg:postcode":"64347",
    "sg:province":"Hessen",
    "wof:name":"Raiffeisen-warengenossenschaft St. Stephan Eg",
    "wof:placetype":"venue"
},
  "geometry": {"coordinates":[8.581054,49.855522],"type":"Point"}
}