{
  "type": "Feature",
  "properties": {
    "iso:country":"DE",
    "sg:address":"An der Schlenke 5",
    "sg:city":"Soest",
    "sg:phone":"+49 2921/51786",
    "sg:postcode":"59494",
    "sg:province":"Nordrhein-Westfalen",
    "wof:name":"Tri-colore Spiel- & Geschenkideen Gmbh",
    "wof:placetype":"venue"
},
  "geometry": {"coordinates":[8.0832576752,51.5404968262],"type":"Point"}
}