{
  "type": "Feature",
  "properties": {
    "iso:country":"DE",
    "sg:address":"Rebenring 64",
    "sg:city":"Braunschweig",
    "sg:phone":"+49 531/335481",
    "sg:postcode":"38106",
    "sg:province":"Niedersachsen",
    "wof:name":"Akafunk E. V. Jens Werner",
    "wof:placetype":"venue"
},
  "geometry": {"coordinates":[10.5226659775,52.2749977112],"type":"Point"}
}