{
  "type": "Feature",
  "properties": {
    "iso:country":"DE",
    "sg:address":"Asternweg 1",
    "sg:city":"Hanau",
    "sg:phone":"+49 6181/69496",
    "sg:postcode":"63456",
    "sg:province":"Hessen",
    "wof:name":"Dr. Emil Komo Rechtsanwalt",
    "wof:placetype":"venue"
},
  "geometry": {"coordinates":[8.9220018387,50.096496582],"type":"Point"}
}