{
  "type": "Feature",
  "properties": {
    "iso:country":"DE",
    "sg:address":"Ostermarscher Str. 13 a",
    "sg:city":"Norden",
    "sg:phone":"+49 4931/2395",
    "sg:postcode":"26506",
    "sg:province":"Niedersachsen",
    "wof:name":"Reno Schmidt",
    "wof:placetype":"venue"
},
  "geometry": {"coordinates":[7.181035,53.610725],"type":"Point"}
}