{
  "type": "Feature",
  "properties": {
    "iso:country":"DE",
    "sg:address":"Zweifelbergstr. 3",
    "sg:city":"Brackenheim",
    "sg:phone":"+49 7135/16099",
    "sg:postcode":"74336",
    "sg:province":"Baden-W\u00fcrttemberg",
    "wof:name":"M. Radies",
    "wof:placetype":"venue"
},
  "geometry": {"coordinates":[9.064891,49.081707],"type":"Point"}
}