{
  "type": "Feature",
  "properties": {
    "iso:country":"DE",
    "sg:address":"Herrenfeldchen 4",
    "sg:city":"Eschweiler",
    "sg:postcode":"52249",
    "sg:province":"Nordrhein-Westfalen",
    "wof:name":"Tm Immobilien- Und Verm\u00f6gensverwaltungsges. Mbh",
    "wof:placetype":"venue"
},
  "geometry": {"coordinates":[6.2825198174,50.804271698],"type":"Point"}
}