{
  "type": "Feature",
  "properties": {
    "iso:country":"DE",
    "sg:address":"Hauptstr. 150",
    "sg:city":"Miltenberg",
    "sg:postcode":"63897",
    "sg:province":"Bayern",
    "wof:name":"Arnold Mode E. K.",
    "wof:placetype":"venue"
},
  "geometry": {"coordinates":[9.2529382706,49.6993484497],"type":"Point"}
}