{
  "type": "Feature",
  "properties": {
    "iso:country":"DE",
    "sg:address":"Dorfstr. 21a",
    "sg:city":"Woggersin",
    "sg:postcode":"17039",
    "sg:province":"Mecklenburg-Vorpommern",
    "wof:name":"S 2001 Marktservice Gmbh",
    "wof:placetype":"venue"
},
  "geometry": {"coordinates":[13.234184,53.608242],"type":"Point"}
}