{
  "type": "Feature",
  "properties": {
    "iso:country":"DE",
    "sg:address":"Hamburger Str 146",
    "sg:city":"Ahrensburg",
    "sg:phone":"+49 700 6624 5466",
    "sg:postcode":"22926",
    "sg:province":"Schleswig-Holstein",
    "wof:name":"Jr - Reisemobilservice & Vermietung",
    "wof:placetype":"venue"
},
  "geometry": {"coordinates":[10.222348,53.664833],"type":"Point"}
}