{
  "type": "Feature",
  "properties": {
    "iso:country":"DE",
    "sg:address":"Hauptstr. 20",
    "sg:city":"Rauhenebrach",
    "sg:phone":"+49 9554/219",
    "sg:postcode":"96181",
    "sg:province":"Bayern",
    "wof:name":"Kuhn Gmbh",
    "wof:placetype":"venue"
},
  "geometry": {"coordinates":[10.552795,49.888557],"type":"Point"}
}