{
  "type": "Feature",
  "properties": {
    "iso:country":"DE",
    "sg:address":"Hamicher Str. 3",
    "sg:city":"Langerwehe",
    "sg:phone":"+49 2423/2050",
    "sg:postcode":"52379",
    "sg:province":"Nordrhein-Westfalen",
    "wof:name":"Restaurant Haus Horst",
    "wof:placetype":"venue"
},
  "geometry": {"coordinates":[6.3358039856,50.7966156006],"type":"Point"}
}