{
  "type": "Feature",
  "properties": {
    "iso:country":"DE",
    "sg:address":"Wasserstr. 10",
    "sg:city":"Freiburg",
    "sg:phone":"+49 761/502255",
    "sg:postcode":"79098",
    "sg:province":"Baden-W\u00fcrttemberg",
    "wof:name":"\u00d6ko U. Natur Umweltprodukte- Vertriebs- Gmbh",
    "wof:placetype":"venue"
},
  "geometry": {"coordinates":[7.85003,47.997849],"type":"Point"}
}