{
  "type": "Feature",
  "properties": {
    "iso:country":"DE",
    "sg:address":"Sandkamp 10",
    "sg:city":"Kiebitzreihe",
    "sg:phone":"+49 4121/50001",
    "sg:postcode":"25368",
    "sg:province":"Schleswig-Holstein",
    "wof:name":"Muk Maschinenbau Und Konstruktion Gmbh",
    "wof:placetype":"venue"
},
  "geometry": {"coordinates":[9.621511,53.784779],"type":"Point"}
}