{
  "type": "Feature",
  "properties": {
    "iso:country":"DE",
    "sg:address":"Hinter den G\u00e4rten 15",
    "sg:city":"Owingen",
    "sg:phone":"+49 7551/3021",
    "sg:postcode":"88696",
    "sg:province":"Baden-W\u00fcrttemberg",
    "wof:name":"Gerhard Sauerstein Ingenieur",
    "wof:placetype":"venue"
},
  "geometry": {"coordinates":[9.1704521179,47.8103790283],"type":"Point"}
}