{
  "type": "Feature",
  "properties": {
    "iso:country":"DE",
    "sg:address":"Steinwies 20",
    "sg:city":"Prem",
    "sg:postcode":"86984",
    "sg:province":"Bayern",
    "wof:name":"Allg\u00e4uer Alpenk\u00e4serei Gmbh",
    "wof:placetype":"venue"
},
  "geometry": {"coordinates":[10.8038244247,47.6887016296],"type":"Point"}
}