{
  "type": "Feature",
  "properties": {
    "iso:country":"DE",
    "sg:address":"Lind",
    "sg:city":"Oberviechtach",
    "sg:phone":"+49 9671/3980",
    "sg:postcode":"92526",
    "sg:province":"Bayern",
    "wof:name":"P. Zimmermann",
    "wof:placetype":"venue"
},
  "geometry": {"coordinates":[12.466845,49.463158],"type":"Point"}
}