{
  "type": "Feature",
  "properties": {
    "iso:country":"DE",
    "sg:address":"Zehdenicker Str. 1a",
    "sg:city":"F\u00fcrstenberg",
    "sg:phone":"+49 33093/38538",
    "sg:postcode":"16798",
    "sg:province":"Brandenburg",
    "wof:name":"G. Stapel",
    "wof:placetype":"venue"
},
  "geometry": {"coordinates":[13.144684,53.18082],"type":"Point"}
}