{
  "type": "Feature",
  "properties": {
    "iso:country":"DE",
    "sg:address":"B\u00fcrgermeister-Zahn-Str. 32",
    "sg:city":"Hockenheim",
    "sg:phone":"+49 6205/188377",
    "sg:postcode":"68766",
    "sg:province":"Baden-W\u00fcrttemberg",
    "wof:name":"Italker Fliesen Und Keramik E. K.",
    "wof:placetype":"venue"
},
  "geometry": {"coordinates":[8.5496463776,49.3246307373],"type":"Point"}
}