{
  "type": "Feature",
  "properties": {
    "iso:country":"DE",
    "sg:address":"\u00d6jendorfer Damm 38",
    "sg:city":"Hamburg",
    "sg:postcode":"22043",
    "sg:province":"Hamburg",
    "wof:name":"Aldi Gmbh & Co. Kg",
    "wof:placetype":"venue"
},
  "geometry": {"coordinates":[10.1354846954,53.5699386597],"type":"Point"}
}