{
  "type": "Feature",
  "properties": {
    "iso:country":"DE",
    "sg:address":"Leipziger Str. 56",
    "sg:city":"Dommitzsch",
    "sg:phone":"+49 34223/40070",
    "sg:postcode":"04880",
    "sg:province":"Sachsen",
    "wof:name":"Crazy-night Inh. G\u00fcnter Rosner",
    "wof:placetype":"venue"
},
  "geometry": {"coordinates":[12.87422,51.636345],"type":"Point"}
}