{
  "type": "Feature",
  "properties": {
    "iso:country":"DE",
    "sg:address":"Radegaster Str. 19",
    "sg:city":"Salzfurtkapelle",
    "sg:phone":"+49 3494/31728",
    "sg:postcode":"06779",
    "sg:province":"Sachsen-Anhalt",
    "wof:name":"H. U. L. Trocha",
    "wof:placetype":"venue"
},
  "geometry": {"coordinates":[12.25474,51.721977],"type":"Point"}
}