{
  "type": "Feature",
  "properties": {
    "iso:country":"DE",
    "sg:address":"Lise-Meitner-Str. 12",
    "sg:city":"Langenfeld",
    "sg:phone":"+49 2173/70394",
    "sg:postcode":"40764",
    "sg:province":"Nordrhein-Westfalen",
    "wof:name":"Rolf Holzschuh",
    "wof:placetype":"venue"
},
  "geometry": {"coordinates":[6.959174,51.137661],"type":"Point"}
}