{
  "type": "Feature",
  "properties": {
    "iso:country":"DE",
    "sg:address":"Hauptstr. 70",
    "sg:city":"Bensheim",
    "sg:phone":"+49 6251/610996",
    "sg:postcode":"64625",
    "sg:province":"Hessen",
    "wof:name":"Mabs By Cicero",
    "wof:placetype":"venue"
},
  "geometry": {"coordinates":[8.6219530106,49.6795730591],"type":"Point"}
}