{
  "type": "Feature",
  "properties": {
    "iso:country":"DE",
    "sg:address":"Dortmunder Str. 74a",
    "sg:city":"Hamm",
    "sg:phone":"+49 2381/940910",
    "sg:postcode":"59067",
    "sg:province":"Nordrhein-Westfalen",
    "wof:name":"Icu-connect Gmbh & Co Kg - Systemhaus",
    "wof:placetype":"venue"
},
  "geometry": {"coordinates":[7.767763,51.665592],"type":"Point"}
}