{
  "type": "Feature",
  "properties": {
    "iso:country":"DE",
    "sg:address":"Am Schertzer 18",
    "sg:city":"Steinbach-Hallenberg",
    "sg:postcode":"98587",
    "sg:province":"Th\u00fcringen",
    "wof:name":"Atlanta Elektrosysteme Verwaltungs-gmbh",
    "wof:placetype":"venue"
},
  "geometry": {"coordinates":[10.561471,50.673679],"type":"Point"}
}