{
  "type": "Feature",
  "properties": {
    "iso:country":"DE",
    "sg:address":"Clara-Zetkin-Platz 12",
    "sg:city":"Bernburg",
    "sg:phone":"+49 3471/34900",
    "sg:postcode":"06406",
    "sg:province":"Sachsen-Anhalt",
    "wof:name":"B\u00e4r-apotheke",
    "wof:placetype":"venue"
},
  "geometry": {"coordinates":[11.748229,51.790173],"type":"Point"}
}