{
  "type": "Feature",
  "properties": {
    "iso:country":"DE",
    "sg:address":"Am Bahndamm 29",
    "sg:city":"Emsb\u00fcren",
    "sg:phone":"+49 5903/598",
    "sg:postcode":"48488",
    "sg:province":"Niedersachsen",
    "wof:name":"Gastst\u00e4tte Ursula Sch\u00fcring",
    "wof:placetype":"venue"
},
  "geometry": {"coordinates":[7.3095221519,52.3945083618],"type":"Point"}
}