{
  "type": "Feature",
  "properties": {
    "iso:country":"DE",
    "sg:address":"B\u00fcrgerhaus",
    "sg:city":"W\u00f6lfersheim",
    "sg:postcode":"61200",
    "sg:province":"Hessen",
    "wof:name":"Gemeindeb\u00fccherei",
    "wof:placetype":"venue"
},
  "geometry": {"coordinates":[8.816821,50.399441],"type":"Point"}
}