{
  "type": "Feature",
  "properties": {
    "iso:country":"DE",
    "sg:address":"Feldstr. 24",
    "sg:city":"Owschlag",
    "sg:phone":"+49 4336/655",
    "sg:postcode":"24811",
    "sg:province":"Schleswig-Holstein",
    "wof:name":"Restaurant Blokkhus",
    "wof:placetype":"venue"
},
  "geometry": {"coordinates":[9.580414772,54.3935127258],"type":"Point"}
}