{
  "type": "Feature",
  "properties": {
    "iso:country":"DE",
    "sg:address":"Ludwig-Rudolf-Str. 4",
    "sg:city":"Blankenburg",
    "sg:postcode":"38889",
    "sg:province":"Sachsen-Anhalt",
    "wof:name":"Apotheke An Der Poliklinik Blankenburg",
    "wof:placetype":"venue"
},
  "geometry": {"coordinates":[10.945674,51.79356],"type":"Point"}
}