{
  "type": "Feature",
  "properties": {
    "iso:country":"DE",
    "sg:address":"Bastionstr. 2 b",
    "sg:city":"D\u00fcsseldorf",
    "sg:phone":"+49 211/326880",
    "sg:postcode":"40213",
    "sg:province":"Nordrhein-Westfalen",
    "wof:name":"Ulrich Schiller",
    "wof:placetype":"venue"
},
  "geometry": {"coordinates":[6.7719140053,51.2217292786],"type":"Point"}
}