{
  "type": "Feature",
  "properties": {
    "iso:country":"DE",
    "sg:address":"Karl-Heine-Str. 27",
    "sg:city":"Leipzig",
    "sg:postcode":"04229",
    "sg:province":"Sachsen",
    "wof:name":"Neue H\u00fctte Verlag F\u00fcr Grundstoffindustrie",
    "wof:placetype":"venue"
},
  "geometry": {"coordinates":[12.3429527283,51.3321418762],"type":"Point"}
}