{
  "type": "Feature",
  "properties": {
    "iso:country":"DE",
    "sg:address":"Wintersbacher Str. 73a",
    "sg:city":"Dammbach",
    "sg:phone":"+49 4960/927844",
    "sg:postcode":"63874",
    "sg:province":"Bayern",
    "wof:name":"Sparkasse Aschaffenburg-alzenau",
    "wof:placetype":"venue"
},
  "geometry": {"coordinates":[9.31182,49.862648],"type":"Point"}
}