{
  "type": "Feature",
  "properties": {
    "iso:country":"DE",
    "sg:address":"Brunsb\u00fcller Str. 9",
    "sg:city":"Sterup",
    "sg:postcode":"24996",
    "sg:province":"Schleswig-Holstein",
    "wof:name":"Wolfgang Hansen",
    "wof:placetype":"venue"
},
  "geometry": {"coordinates":[9.7584190369,54.7055511475],"type":"Point"}
}