{
  "type": "Feature",
  "properties": {
    "iso:country":"DE",
    "sg:address":"Bahnhofstr. 47a",
    "sg:city":"Berlin",
    "sg:phone":"+49 30/7448796",
    "sg:postcode":"12305",
    "sg:province":"Berlin",
    "wof:name":"J\u00fcrgen Pflanz",
    "wof:placetype":"venue"
},
  "geometry": {"coordinates":[13.401794,52.386536],"type":"Point"}
}