{
  "type": "Feature",
  "properties": {
    "iso:country":"DE",
    "sg:address":"Schrottinsel 2",
    "sg:city":"Duisburg",
    "sg:phone":"+49 203/446058",
    "sg:postcode":"47138",
    "sg:province":"Nordrhein-Westfalen",
    "wof:name":"Navigare Stauerei- Und Speditions Gmbh",
    "wof:placetype":"venue"
},
  "geometry": {"coordinates":[6.771089,51.457073],"type":"Point"}
}