{
  "type": "Feature",
  "properties": {
    "iso:country":"DE",
    "sg:address":"Hopfenstr. 67",
    "sg:city":"Kiel",
    "sg:postcode":"24103",
    "sg:province":"Schleswig-Holstein",
    "wof:name":"Hotel Haddeby Stark Kg",
    "wof:placetype":"venue"
},
  "geometry": {"coordinates":[10.1305398941,54.3184394836],"type":"Point"}
}