{
  "type": "Feature",
  "properties": {
    "iso:country":"DE",
    "sg:address":"Knochenhauerstr. 38",
    "sg:city":"Bremen",
    "sg:postcode":"28195",
    "sg:province":"Bremen",
    "wof:name":"N\u00e4hmaschinen-philipp Gmbh",
    "wof:placetype":"venue"
},
  "geometry": {"coordinates":[8.806674,53.078617],"type":"Point"}
}