{
  "type": "Feature",
  "properties": {
    "iso:country":"DE",
    "sg:address":"K\u00f6lner Str. 110",
    "sg:city":"Bergheim",
    "sg:postcode":"50127",
    "sg:province":"Nordrhein-Westfalen",
    "wof:name":"Breitenau Holding Gmbh",
    "wof:placetype":"venue"
},
  "geometry": {"coordinates":[6.667869,50.945869],"type":"Point"}
}