{
  "type": "Feature",
  "properties": {
    "iso:country":"DE",
    "sg:address":"Lauschaer Str. 38",
    "sg:city":"Steinach",
    "sg:phone":"+49 36762/32371",
    "sg:postcode":"96523",
    "sg:province":"Th\u00fcringen",
    "wof:name":"Hausd\u00f6rfer Spielwaren Gmbh",
    "wof:placetype":"venue"
},
  "geometry": {"coordinates":[11.1546154022,50.4402198792],"type":"Point"}
}