{
  "type": "Feature",
  "properties": {
    "iso:country":"DE",
    "sg:address":"Im Gewerbegebiet 3",
    "sg:city":"Lichtenau",
    "sg:phone":"+49 7227/95940",
    "sg:postcode":"77839",
    "sg:province":"Baden-W\u00fcrttemberg",
    "wof:name":"Sarnatech Wild Gmbh",
    "wof:placetype":"venue"
},
  "geometry": {"coordinates":[7.996534,48.721863],"type":"Point"}
}