{
  "type": "Feature",
  "properties": {
    "iso:country":"DE",
    "sg:address":"Dahmer Str. 5",
    "sg:city":"Luckenwalde",
    "sg:postcode":"14943",
    "sg:province":"Brandenburg",
    "wof:name":"Kurt Mummert",
    "wof:placetype":"venue"
},
  "geometry": {"coordinates":[13.174477,52.086754],"type":"Point"}
}