{
  "type": "Feature",
  "properties": {
    "iso:country":"DE",
    "sg:address":"Blender Hauptstr. 36",
    "sg:city":"Blender",
    "sg:phone":"+49 4233/93000",
    "sg:postcode":"27337",
    "sg:province":"Niedersachsen",
    "wof:name":"Gerhard M\u00fcller Ingenieur",
    "wof:placetype":"venue"
},
  "geometry": {"coordinates":[9.1334314346,52.9259262085],"type":"Point"}
}