{
  "type": "Feature",
  "properties": {
    "iso:country":"DE",
    "sg:address":"Modering 5",
    "sg:city":"Hamburg",
    "sg:phone":"+49 40/5594136",
    "sg:postcode":"22457",
    "sg:province":"Hamburg",
    "wof:name":"Accessoires Und Mode",
    "wof:placetype":"venue"
},
  "geometry": {"coordinates":[9.9222564697,53.6375579834],"type":"Point"}
}