{
  "type": "Feature",
  "properties": {
    "iso:country":"DE",
    "sg:address":"Am Heerweg 8",
    "sg:city":"Wallenhorst",
    "sg:phone":"+49 5407/39477",
    "sg:postcode":"49134",
    "sg:province":"Niedersachsen",
    "wof:name":"Klaus D\u00f6bber Steuerberater",
    "wof:placetype":"venue"
},
  "geometry": {"coordinates":[8.0174446106,52.3515701294],"type":"Point"}
}