{
  "type": "Feature",
  "properties": {
    "iso:country":"DE",
    "sg:address":"Ansbacher Str. 35",
    "sg:city":"Rothenburg",
    "sg:phone":"+49 9861/3050",
    "sg:postcode":"91541",
    "sg:province":"Bayern",
    "wof:name":"Pizzeria Scaps",
    "wof:placetype":"venue"
},
  "geometry": {"coordinates":[10.1910829544,49.3754882812],"type":"Point"}
}