{
  "type": "Feature",
  "properties": {
    "iso:country":"DE",
    "sg:address":"Dahmestr. 9",
    "sg:city":"Eichwalde",
    "sg:phone":"+49 30/6758101",
    "sg:postcode":"15732",
    "sg:province":"Brandenburg",
    "wof:name":"Hans-joachim Meusel",
    "wof:placetype":"venue"
},
  "geometry": {"coordinates":[13.6339941025,52.3702354431],"type":"Point"}
}