{
  "type": "Feature",
  "properties": {
    "iso:country":"DE",
    "sg:address":"Talstr. 20",
    "sg:city":"K\u00f6ln",
    "sg:phone":"+49 221/687109",
    "sg:postcode":"51069",
    "sg:province":"Nordrhein-Westfalen",
    "wof:name":"Helmut Kauss Ingenieur",
    "wof:placetype":"venue"
},
  "geometry": {"coordinates":[7.0674500465,50.9732170105],"type":"Point"}
}