{
  "type": "Feature",
  "properties": {
    "iso:country":"DE",
    "sg:address":"Westf\u00e4lische Str 32",
    "sg:city":"Berlin",
    "sg:phone":"+49 30/8925993",
    "sg:postcode":"10709",
    "sg:province":"Berlin",
    "wof:name":"\u00c4sthetik Dentallabor Heydenreich Gmbh",
    "wof:placetype":"venue"
},
  "geometry": {"coordinates":[13.297083,52.495819],"type":"Point"}
}