{
  "type": "Feature",
  "properties": {
    "iso:country":"DE",
    "sg:address":"Sch\u00f6nstr. 44",
    "sg:city":"M\u00fcnchen",
    "sg:phone":"+49 89/656884",
    "sg:postcode":"81543",
    "sg:province":"Bayern",
    "wof:name":"Alfred Sommer",
    "wof:placetype":"venue"
},
  "geometry": {"coordinates":[11.565046,48.108177],"type":"Point"}
}