{
  "type": "Feature",
  "properties": {
    "iso:country":"DE",
    "sg:address":"Neefestr. 80 a",
    "sg:city":"Chemnitz",
    "sg:postcode":"09119",
    "sg:province":"Sachsen",
    "wof:name":"Lernstatt-gro\u00dfteile- Fertigung Gmbh",
    "wof:placetype":"venue"
},
  "geometry": {"coordinates":[12.8904304504,50.8194084167],"type":"Point"}
}