{
  "type": "Feature",
  "properties": {
    "iso:country":"DE",
    "sg:address":"Hindenburgstr. 60",
    "sg:city":"\u00d6hringen",
    "sg:phone":"+49 7941/33009",
    "sg:postcode":"74613",
    "sg:province":"Baden-W\u00fcrttemberg",
    "wof:name":"Landw. Beratungsdienst Hohenlohe-franken E. V.",
    "wof:placetype":"venue"
},
  "geometry": {"coordinates":[9.4970626831,49.2042694092],"type":"Point"}
}