{
  "type": "Feature",
  "properties": {
    "iso:country":"DE",
    "sg:address":"Hamburger Allee 12",
    "sg:city":"Frankfurt",
    "sg:phone":"+49 69/774026",
    "sg:postcode":"60486",
    "sg:province":"Hessen",
    "wof:name":"Laves Chemie Gesellschaft F\u00fcr Chemie-marktforschung",
    "wof:placetype":"venue"
},
  "geometry": {"coordinates":[8.649815,50.114506],"type":"Point"}
}