{
  "type": "Feature",
  "properties": {
    "iso:country":"DE",
    "sg:address":"Braker Str. 110",
    "sg:city":"Bielefeld",
    "sg:phone":"+49 521/772314",
    "sg:postcode":"33729",
    "sg:province":"Nordrhein-Westfalen",
    "wof:name":"Lindemann Gmbh",
    "wof:placetype":"venue"
},
  "geometry": {"coordinates":[8.596036911,52.0712013245],"type":"Point"}
}