{
  "type": "Feature",
  "properties": {
    "iso:country":"DE",
    "sg:address":"Prinzenstr. 46-50",
    "sg:city":"Schwelm",
    "sg:phone":"+49 2336/919100",
    "sg:postcode":"58332",
    "sg:province":"Nordrhein-Westfalen",
    "wof:name":"Traxit International August Neuhoff",
    "wof:placetype":"venue"
},
  "geometry": {"coordinates":[7.299119,51.29562],"type":"Point"}
}