{
  "type": "Feature",
  "properties": {
    "iso:country":"DE",
    "sg:address":"R\u00fcckertstr. 47",
    "sg:city":"Frankfurt",
    "sg:phone":"+49 69/9434530",
    "sg:postcode":"60314",
    "sg:province":"Hessen",
    "wof:name":"Temming Gallrein Und Beringer-geske",
    "wof:placetype":"venue"
},
  "geometry": {"coordinates":[8.6993150711,50.1120376587],"type":"Point"}
}