{
  "type": "Feature",
  "properties": {
    "iso:country":"DE",
    "sg:address":"Brinkhof 4",
    "sg:city":"Rinteln",
    "sg:phone":"+49 5751/75777",
    "sg:postcode":"31737",
    "sg:province":"Niedersachsen",
    "wof:name":"Babalu",
    "wof:placetype":"venue"
},
  "geometry": {"coordinates":[9.102809,52.204056],"type":"Point"}
}