{
  "type": "Feature",
  "properties": {
    "iso:country":"DE",
    "sg:address":"Mettfelder Str. 2",
    "sg:city":"K\u00f6ln",
    "sg:phone":"+49 221/391509",
    "sg:postcode":"50996",
    "sg:province":"Nordrhein-Westfalen",
    "wof:name":"B. Walgenbach",
    "wof:placetype":"venue"
},
  "geometry": {"coordinates":[6.9987101555,50.890247345],"type":"Point"}
}