{
  "type": "Feature",
  "properties": {
    "iso:country":"DE",
    "sg:address":"Schlo\u00dfstr. 48",
    "sg:city":"Saarbr\u00fccken",
    "sg:phone":"+49 681/583807",
    "sg:postcode":"66117",
    "sg:province":"Saarland",
    "wof:name":"Hans Maas",
    "wof:placetype":"venue"
},
  "geometry": {"coordinates":[6.9885830879,49.2316894531],"type":"Point"}
}