{
  "type": "Feature",
  "properties": {
    "iso:country":"DE",
    "sg:address":"Laurentiusstr. 98",
    "sg:city":"Bergisch Gladbach",
    "sg:phone":"+49 2202/31512",
    "sg:postcode":"51465",
    "sg:province":"Nordrhein-Westfalen",
    "wof:name":"Restaurant Bei Stanko",
    "wof:placetype":"venue"
},
  "geometry": {"coordinates":[7.1348371506,50.9956054688],"type":"Point"}
}