{
  "type": "Feature",
  "properties": {
    "iso:country":"DE",
    "sg:address":"Hagedornweg 4",
    "sg:city":"Solingen",
    "sg:phone":"+49 212/651669",
    "sg:postcode":"42699",
    "sg:province":"Nordrhein-Westfalen",
    "wof:name":"Gisela Luchtenberg",
    "wof:placetype":"venue"
},
  "geometry": {"coordinates":[7.00845,51.15136],"type":"Point"}
}