{
  "type": "Feature",
  "properties": {
    "iso:country":"DE",
    "sg:address":"An der Alten Synagoge 5",
    "sg:city":"Paderborn",
    "sg:phone":"+49 5251/282865",
    "sg:postcode":"33098",
    "sg:province":"Nordrhein-Westfalen",
    "wof:name":"Dom-apotheke",
    "wof:placetype":"venue"
},
  "geometry": {"coordinates":[8.758726,51.718853],"type":"Point"}
}