{
  "type": "Feature",
  "properties": {
    "iso:country":"DE",
    "sg:address":"Otto-Sendtner-Str. 4",
    "sg:city":"M\u00fcnchen",
    "sg:phone":"+49 89/3231230",
    "sg:postcode":"80939",
    "sg:province":"Bayern",
    "wof:name":"Stefan Schewe",
    "wof:placetype":"venue"
},
  "geometry": {"coordinates":[11.630736,48.190502],"type":"Point"}
}