{
  "type": "Feature",
  "properties": {
    "iso:country":"DE",
    "sg:address":"Karl-Legien-Str. 24",
    "sg:city":"Essen",
    "sg:phone":"+49 201/3680870",
    "sg:postcode":"45356",
    "sg:province":"Nordrhein-Westfalen",
    "wof:name":"Naderi Beteiligungs Gmbh",
    "wof:placetype":"venue"
},
  "geometry": {"coordinates":[6.9850358963,51.4977798462],"type":"Point"}
}