{
  "type": "Feature",
  "properties": {
    "iso:country":"DE",
    "sg:address":"Am Ihlberg 18",
    "sg:city":"Melsdorf",
    "sg:phone":"+49 431/6913335",
    "sg:postcode":"24109",
    "sg:province":"Schleswig-Holstein",
    "wof:name":"Eisenhenkel Logistik Gmbh",
    "wof:placetype":"venue"
},
  "geometry": {"coordinates":[10.046377,54.297832],"type":"Point"}
}