{
  "type": "Feature",
  "properties": {
    "iso:country":"DE",
    "sg:address":"Sch\u00e4fflestr. 1",
    "sg:city":"Frankfurt",
    "sg:phone":"+49 69/412206",
    "sg:postcode":"60386",
    "sg:province":"Hessen",
    "wof:name":"G. Schmehl",
    "wof:placetype":"venue"
},
  "geometry": {"coordinates":[8.7332344055,50.1309547424],"type":"Point"}
}