{
  "type": "Feature",
  "properties": {
    "iso:country":"DE",
    "sg:address":"Am Hang 22",
    "sg:city":"Bad Vilbel",
    "sg:postcode":"61118",
    "sg:province":"Hessen",
    "wof:name":"D\u00fcren Verm\u00f6gensverwaltung Gmbh",
    "wof:placetype":"venue"
},
  "geometry": {"coordinates":[8.7275285721,50.1706428528],"type":"Point"}
}