{
  "type": "Feature",
  "properties": {
    "iso:country":"DE",
    "sg:address":"Neukirchener Str.",
    "sg:city":"Triftern",
    "sg:phone":"+49 8562/596",
    "sg:postcode":"84371",
    "sg:province":"Bayern",
    "wof:name":"Max Karlhuber",
    "wof:placetype":"venue"
},
  "geometry": {"coordinates":[12.995935,48.394386],"type":"Point"}
}