{
  "type": "Feature",
  "properties": {
    "iso:country":"DE",
    "sg:address":"Nienburger Damm 11",
    "sg:city":"Nienburg",
    "sg:phone":"+49 4950/2160150",
    "sg:postcode":"31582",
    "sg:province":"Niedersachsen",
    "wof:name":"Autohaus Anders Gmbh",
    "wof:placetype":"venue"
},
  "geometry": {"coordinates":[9.2404146194,52.6230888367],"type":"Point"}
}