{
  "type": "Feature",
  "properties": {
    "iso:country":"DE",
    "sg:address":"Barbarossastr. 28",
    "sg:city":"Gelnhausen",
    "sg:phone":"+49 6051/480711",
    "sg:postcode":"63571",
    "sg:province":"Hessen",
    "wof:name":"Wirtschaftsf\u00f6rderung Und Tourismus Gmbh",
    "wof:placetype":"venue"
},
  "geometry": {"coordinates":[9.1974201202,50.2012290955],"type":"Point"}
}