{
  "type": "Feature",
  "properties": {
    "iso:country":"DE",
    "sg:address":"Franz-Kruckenberg-Str. 6",
    "sg:city":"Uetersen",
    "sg:phone":"+49 4122/2104",
    "sg:postcode":"25436",
    "sg:province":"Schleswig-Holstein",
    "wof:name":"Tischlerei Girnus Gmbh",
    "wof:placetype":"venue"
},
  "geometry": {"coordinates":[9.696586,53.67981],"type":"Point"}
}