{
  "type": "Feature",
  "properties": {
    "iso:country":"DE",
    "sg:address":"Friedeburger Hauptstr. 44",
    "sg:city":"Friedeburg",
    "sg:phone":"+49 4465/8115",
    "sg:postcode":"26446",
    "sg:province":"Niedersachsen",
    "wof:name":"Gretchen H\u00f6ger",
    "wof:placetype":"venue"
},
  "geometry": {"coordinates":[7.8421430588,53.4500961304],"type":"Point"}
}