{
  "type": "Feature",
  "properties": {
    "iso:country":"DE",
    "sg:address":"Zum Lith 71",
    "sg:city":"Duisburg",
    "sg:phone":"+49 203/770377",
    "sg:postcode":"47055",
    "sg:province":"Nordrhein-Westfalen",
    "wof:name":"Sportecke",
    "wof:placetype":"venue"
},
  "geometry": {"coordinates":[6.7681298256,51.4050788879],"type":"Point"}
}