{
  "type": "Feature",
  "properties": {
    "iso:country":"DE",
    "sg:address":"Freiheitstr. 76",
    "sg:city":"Remscheid",
    "sg:phone":"+49 2191/291956",
    "sg:postcode":"42853",
    "sg:province":"Nordrhein-Westfalen",
    "wof:name":"Fliesen Ital. Keramik",
    "wof:placetype":"venue"
},
  "geometry": {"coordinates":[7.1899809837,51.1776542664],"type":"Point"}
}