{
  "type": "Feature",
  "properties": {
    "iso:country":"DE",
    "sg:address":"Holm 22",
    "sg:city":"Flensburg",
    "sg:postcode":"24937",
    "sg:province":"Schleswig-Holstein",
    "wof:name":"M & P Tax Steuerberatungs- Gesellschaft Mbh",
    "wof:placetype":"venue"
},
  "geometry": {"coordinates":[9.4344892502,54.7853622437],"type":"Point"}
}