{
  "type": "Feature",
  "properties": {
    "iso:country":"DE",
    "sg:address":"Sudetenstr. 28",
    "sg:city":"Cremlingen",
    "sg:phone":"+49 5306/4474",
    "sg:postcode":"38162",
    "sg:province":"Niedersachsen",
    "wof:name":"Wolfgang Wegener Gmbh",
    "wof:placetype":"venue"
},
  "geometry": {"coordinates":[10.6347026825,52.2748336792],"type":"Point"}
}