{
  "type": "Feature",
  "properties": {
    "iso:country":"DE",
    "sg:address":"Voithstr. 13",
    "sg:city":"Ulm",
    "sg:phone":"+49 731/44156",
    "sg:postcode":"89079",
    "sg:province":"Baden-W\u00fcrttemberg",
    "wof:name":"Donau-asphalt-mischwerke Gmbh",
    "wof:placetype":"venue"
},
  "geometry": {"coordinates":[9.9553079605,48.362953186],"type":"Point"}
}