{
  "type": "Feature",
  "properties": {
    "iso:country":"DE",
    "sg:address":"Eisenzahnstr. 64::",
    "sg:city":"Berlin",
    "sg:phone":"+49 4930/8968950",
    "sg:postcode":"10709",
    "sg:province":"Berlin",
    "wof:name":"Consulata Steuerberatungsgesellscgaft Mbh",
    "wof:placetype":"venue"
},
  "geometry": {"coordinates":[13.305559,52.498196],"type":"Point"}
}