{
  "type": "Feature",
  "properties": {
    "iso:country":"DE",
    "sg:address":"Carl-Diem-Str. 12",
    "sg:city":"Neufahrn",
    "sg:phone":"+49 8165/691639",
    "sg:postcode":"85375",
    "sg:province":"Bayern",
    "wof:name":"Wolfgang Lauber",
    "wof:placetype":"venue"
},
  "geometry": {"coordinates":[11.6571426392,48.3142929077],"type":"Point"}
}