{
  "type": "Feature",
  "properties": {
    "iso:country":"DE",
    "sg:address":"Auf dem Pfennig 10",
    "sg:city":"Mettmann",
    "sg:phone":"+49 2104/52717",
    "sg:postcode":"40822",
    "sg:province":"Nordrhein-Westfalen",
    "wof:name":"Horst Winzer Ingenieur",
    "wof:placetype":"venue"
},
  "geometry": {"coordinates":[6.962542057,51.2629013062],"type":"Point"}
}