{
  "type": "Feature",
  "properties": {
    "iso:country":"DE",
    "sg:address":"Friedhofstr. 9",
    "sg:city":"Lienen",
    "sg:phone":"+49 5483/8171",
    "sg:postcode":"49536",
    "sg:province":"Nordrhein-Westfalen",
    "wof:name":"Hans Schrecke Pension",
    "wof:placetype":"venue"
},
  "geometry": {"coordinates":[7.974919796,52.1445388794],"type":"Point"}
}