{
  "type": "Feature",
  "properties": {
    "iso:country":"DE",
    "sg:address":"Dorothea-Erxlebenstrasse 4",
    "sg:city":"Kiel",
    "sg:phone":"+49 4943/1718899",
    "sg:postcode":"24145",
    "sg:province":"Schleswig-Holstein",
    "wof:name":"H Chr Storjohann Gmbh",
    "wof:placetype":"venue"
},
  "geometry": {"coordinates":[10.156261,54.281101],"type":"Point"}
}