{
  "type": "Feature",
  "properties": {
    "iso:country":"DE",
    "sg:address":"Auguststr. 63",
    "sg:city":"Berlin",
    "sg:postcode":"10117",
    "sg:province":"Berlin",
    "wof:name":"Bwf Service-point Gmbh",
    "wof:placetype":"venue"
},
  "geometry": {"coordinates":[13.3971986771,52.5271949768],"type":"Point"}
}