{
  "type": "Feature",
  "properties": {
    "iso:country":"DE",
    "sg:address":"Unterstr. 1",
    "sg:city":"L\u00f6hnberg",
    "sg:phone":"+49 6471/8309",
    "sg:postcode":"35792",
    "sg:province":"Hessen",
    "wof:name":"H. Gerhardt Versicherung",
    "wof:placetype":"venue"
},
  "geometry": {"coordinates":[8.2750797272,50.5113601685],"type":"Point"}
}