{
  "type": "Feature",
  "properties": {
    "iso:country":"DE",
    "sg:address":"K\u00f6lner Str. 9",
    "sg:city":"Lindlar",
    "sg:phone":"+49 2266/7549",
    "sg:postcode":"51789",
    "sg:province":"Nordrhein-Westfalen",
    "wof:name":"Helmut S\u00fcnger",
    "wof:placetype":"venue"
},
  "geometry": {"coordinates":[7.3738188744,51.0185203552],"type":"Point"}
}