{
  "type": "Feature",
  "properties": {
    "iso:country":"DE",
    "sg:address":"G\u00e4rtnerstr. 2",
    "sg:city":"Lahr",
    "sg:phone":"+49 7821/32105",
    "sg:postcode":"77933",
    "sg:province":"Baden-W\u00fcrttemberg",
    "wof:name":"Orient-grill",
    "wof:placetype":"venue"
},
  "geometry": {"coordinates":[7.8768582344,48.3416061401],"type":"Point"}
}