{
  "type": "Feature",
  "properties": {
    "iso:country":"DE",
    "sg:address":"Die\u00dfener Str. 10",
    "sg:city":"Schongau",
    "sg:phone":"+49 8861/4107",
    "sg:postcode":"86956",
    "sg:province":"Bayern",
    "wof:name":"Robert Sch\u00f6nstein Gmbh",
    "wof:placetype":"venue"
},
  "geometry": {"coordinates":[10.9182977676,47.8130264282],"type":"Point"}
}