{
  "type": "Feature",
  "properties": {
    "iso:country":"DE",
    "sg:address":"Burgstr. 39",
    "sg:city":"B\u00fcren",
    "sg:phone":"+49 2951/5966",
    "sg:postcode":"33142",
    "sg:province":"Nordrhein-Westfalen",
    "wof:name":"Brigittes Sport Shop",
    "wof:placetype":"venue"
},
  "geometry": {"coordinates":[8.558747,51.551453],"type":"Point"}
}