{
  "type": "Feature",
  "properties": {
    "iso:country":"DE",
    "sg:address":"Merkenicher Hauptstr. 176",
    "sg:city":"K\u00f6ln",
    "sg:phone":"+49 221/705700",
    "sg:postcode":"50769",
    "sg:province":"Nordrhein-Westfalen",
    "wof:name":"Karl Weck Gmbh",
    "wof:placetype":"venue"
},
  "geometry": {"coordinates":[6.9579281807,51.0266456604],"type":"Point"}
}