{
  "type": "Feature",
  "properties": {
    "iso:country":"DE",
    "sg:address":"Schlo\u00dfberg 1",
    "sg:city":"Kleve",
    "sg:phone":"+49 2821/25250",
    "sg:postcode":"47533",
    "sg:province":"Nordrhein-Westfalen",
    "wof:name":"R\u00fcdiger Hendricks",
    "wof:placetype":"venue"
},
  "geometry": {"coordinates":[6.138646,51.786003],"type":"Point"}
}