{
  "type": "Feature",
  "properties": {
    "iso:country":"DE",
    "sg:address":"Michelstadter Str. 14",
    "sg:city":"Mannheim",
    "sg:postcode":"68305",
    "sg:province":"Baden-W\u00fcrttemberg",
    "wof:name":"P. A. P. Computer Gmbh",
    "wof:placetype":"venue"
},
  "geometry": {"coordinates":[8.4941139221,49.5263214111],"type":"Point"}
}