{
  "type": "Feature",
  "properties": {
    "iso:country":"DE",
    "sg:address":"Scheffelstr. 10-2",
    "sg:city":"Radolfzell",
    "sg:phone":"+49 7732/12694",
    "sg:postcode":"78315",
    "sg:province":"Baden-W\u00fcrttemberg",
    "wof:name":"Welschinger Gmbh",
    "wof:placetype":"venue"
},
  "geometry": {"coordinates":[8.975461,47.73613],"type":"Point"}
}