{
  "type": "Feature",
  "properties": {
    "iso:country":"DE",
    "sg:address":"Kempter Str. 46",
    "sg:city":"Memmingen",
    "sg:phone":"+49 8331/4065",
    "sg:postcode":"87700",
    "sg:province":"Bayern",
    "wof:name":"Karl-heinz Zimmermann Steuerberater",
    "wof:placetype":"venue"
},
  "geometry": {"coordinates":[10.1821870804,47.9800415039],"type":"Point"}
}