{
  "type": "Feature",
  "properties": {
    "iso:country":"DE",
    "sg:address":"Pestalozzistr. 27",
    "sg:city":"Zwickau",
    "sg:phone":"+49 375/784163",
    "sg:postcode":"08062",
    "sg:province":"Sachsen",
    "wof:name":"Andrea Blechschmidt",
    "wof:placetype":"venue"
},
  "geometry": {"coordinates":[12.4650564194,50.6919136047],"type":"Point"}
}