{
  "type": "Feature",
  "properties": {
    "iso:country":"DE",
    "sg:address":"Buchackerstr. 4",
    "sg:city":"Zirndorf",
    "sg:phone":"+49 911/609062",
    "sg:postcode":"90513",
    "sg:province":"Bayern",
    "wof:name":"Pfeiffer Beteiligungs Gmbh",
    "wof:placetype":"venue"
},
  "geometry": {"coordinates":[10.95315,49.438141],"type":"Point"}
}