{
  "type": "Feature",
  "properties": {
    "iso:country":"DE",
    "sg:address":"Murnauer Str. 5",
    "sg:city":"Weilheim",
    "sg:phone":"+49 881/2693",
    "sg:postcode":"82362",
    "sg:province":"Bayern",
    "wof:name":"Dachsbr\u00e4ust\u00fcberl",
    "wof:placetype":"venue"
},
  "geometry": {"coordinates":[11.1499900818,47.8426704407],"type":"Point"}
}