{
  "type": "Feature",
  "properties": {
    "iso:country":"DE",
    "sg:address":"Leiderer Str 12",
    "sg:city":"Stockstadt",
    "sg:phone":"+49 6027/20846",
    "sg:postcode":"63811",
    "sg:province":"Bayern",
    "wof:name":"Bls Gmbh",
    "wof:placetype":"venue"
},
  "geometry": {"coordinates":[9.0813531876,49.9694442749],"type":"Point"}
}