{
  "type": "Feature",
  "properties": {
    "iso:country":"DE",
    "sg:address":"Hauptstr. 40",
    "sg:city":"Schwegenheim",
    "sg:phone":"+49 6344/4233",
    "sg:postcode":"67365",
    "sg:province":"Rheinland-Pfalz",
    "wof:name":"Gustav Hammelmann",
    "wof:placetype":"venue"
},
  "geometry": {"coordinates":[8.332349,49.270954],"type":"Point"}
}