{
  "type": "Feature",
  "properties": {
    "iso:country":"DE",
    "sg:address":"H\u00fclen",
    "sg:city":"Lauchheim",
    "sg:phone":"+49 7363/5358",
    "sg:postcode":"73466",
    "sg:province":"Baden-W\u00fcrttemberg",
    "wof:name":"Ernst Schneider Gmbh & Co.",
    "wof:placetype":"venue"
},
  "geometry": {"coordinates":[10.2460699081,48.871761322],"type":"Point"}
}