{
  "type": "Feature",
  "properties": {
    "iso:country":"DE",
    "sg:address":"Hacklthaler Str. 6",
    "sg:city":"Kirchdorf",
    "sg:phone":"+49 8072/1320",
    "sg:postcode":"83527",
    "sg:province":"Bayern",
    "wof:name":"Kath. Pfarramt Mari\u00e4 Himmelfahrt",
    "wof:placetype":"venue"
},
  "geometry": {"coordinates":[12.1966114044,48.1759414673],"type":"Point"}
}