{
  "type": "Feature",
  "properties": {
    "iso:country":"DE",
    "sg:address":"Alte Dorfstr. 5",
    "sg:city":"Seukendorf",
    "sg:phone":"+49 911/7540662",
    "sg:postcode":"90556",
    "sg:province":"Bayern",
    "wof:name":"Heinz Grauberger",
    "wof:placetype":"venue"
},
  "geometry": {"coordinates":[10.892737,49.482525],"type":"Point"}
}