{
  "type": "Feature",
  "properties": {
    "iso:country":"DE",
    "sg:address":"Hafenlohrweg 8",
    "sg:city":"Aschaffenburg",
    "sg:phone":"+49 6021/450047",
    "sg:postcode":"63741",
    "sg:province":"Bayern",
    "wof:name":"Zieroff S W\u00e4schetruhe",
    "wof:placetype":"venue"
},
  "geometry": {"coordinates":[9.1458005905,49.9911117554],"type":"Point"}
}