{
  "type": "Feature",
  "properties": {
    "iso:country":"DE",
    "sg:address":"Rudolf-Diesel-Stra\u00dfe 10",
    "sg:city":"Ganderkesee",
    "sg:phone":"+49 4222/94300",
    "sg:postcode":"27777",
    "sg:province":"Niedersachsen",
    "wof:name":"Sitec-alarmanlagen Gmbh & Co. Kg",
    "wof:placetype":"venue"
},
  "geometry": {"coordinates":[8.549694,53.048237],"type":"Point"}
}