{
  "type": "Feature",
  "properties": {
    "iso:country":"DE",
    "sg:address":"Von-Vincke-Str. 12",
    "sg:city":"M\u00fcnster",
    "sg:phone":"+49 251/58939",
    "sg:postcode":"48143",
    "sg:province":"Nordrhein-Westfalen",
    "wof:name":"Bernd Kreimer Architekt",
    "wof:placetype":"venue"
},
  "geometry": {"coordinates":[7.632187,51.958202],"type":"Point"}
}