{
  "type": "Feature",
  "properties": {
    "iso:country":"DE",
    "sg:address":"Hauptstr. 22",
    "sg:city":"Melle",
    "sg:phone":"+49 5428/442",
    "sg:postcode":"49326",
    "sg:province":"Niedersachsen",
    "wof:name":"Helmut Vodegel",
    "wof:placetype":"venue"
},
  "geometry": {"coordinates":[8.3848876953,52.136516571],"type":"Point"}
}