{
  "type": "Feature",
  "properties": {
    "iso:country":"DE",
    "sg:address":"St. Annenstr. 61",
    "sg:city":"St. Wendel",
    "sg:phone":"+49 6851/2111",
    "sg:postcode":"66606",
    "sg:province":"Saarland",
    "wof:name":"Handwerker-verein St. Wendel Leonhard Baureis",
    "wof:placetype":"venue"
},
  "geometry": {"coordinates":[7.1625099182,49.4732437134],"type":"Point"}
}