{
  "type": "Feature",
  "properties": {
    "iso:country":"DE",
    "sg:address":"Herdweg 64",
    "sg:city":"Stuttgart",
    "sg:phone":"+49 711/223380",
    "sg:postcode":"70174",
    "sg:province":"Baden-W\u00fcrttemberg",
    "wof:name":"Asp-plan Gmbh",
    "wof:placetype":"venue"
},
  "geometry": {"coordinates":[9.1626243591,48.7867546082],"type":"Point"}
}