{
  "type": "Feature",
  "properties": {
    "iso:country":"DE",
    "sg:address":"Saint-Priest-Str. 5",
    "sg:city":"M\u00fchlheim",
    "sg:phone":"+49 6108/990294",
    "sg:postcode":"63165",
    "sg:province":"Hessen",
    "wof:name":"Richard Rocker Architekt",
    "wof:placetype":"venue"
},
  "geometry": {"coordinates":[8.835747,50.127342],"type":"Point"}
}