{
  "type": "Feature",
  "properties": {
    "iso:country":"DE",
    "sg:address":"Albrecht-D\u00fcrer-Str. 29",
    "sg:city":"Gochsheim",
    "sg:phone":"+49 9721/645210",
    "sg:postcode":"97469",
    "sg:province":"Bayern",
    "wof:name":"Y-werbekommunikation",
    "wof:placetype":"venue"
},
  "geometry": {"coordinates":[10.282029,50.026836],"type":"Point"}
}