{
  "type": "Feature",
  "properties": {
    "iso:country":"DE",
    "sg:address":"Fichtenstr. 12",
    "sg:city":"Mosbach",
    "sg:phone":"+49 6261/2566",
    "sg:postcode":"74821",
    "sg:province":"Baden-W\u00fcrttemberg",
    "wof:name":"Kastein M\u00f6bel Und Leuchten Gmbh",
    "wof:placetype":"venue"
},
  "geometry": {"coordinates":[9.1346826553,49.366569519],"type":"Point"}
}