{
  "type": "Feature",
  "properties": {
    "iso:country":"DE",
    "sg:address":"Otto-Hahn-Str. 2",
    "sg:city":"Erkrath",
    "sg:phone":"+49 211/251831",
    "sg:postcode":"40699",
    "sg:province":"Nordrhein-Westfalen",
    "wof:name":"Autotechnik Klocke",
    "wof:placetype":"venue"
},
  "geometry": {"coordinates":[6.917025,51.197388],"type":"Point"}
}