{
  "type": "Feature",
  "properties": {
    "iso:country":"DE",
    "sg:address":"Zeppelinstr. 27",
    "sg:city":"Nordhorn",
    "sg:phone":"+49 5921/34143",
    "sg:postcode":"48529",
    "sg:province":"Niedersachsen",
    "wof:name":"Johann Brinkers",
    "wof:placetype":"venue"
},
  "geometry": {"coordinates":[7.0700478554,52.4240760803],"type":"Point"}
}