{
  "type": "Feature",
  "properties": {
    "iso:country":"DE",
    "sg:address":"Stra\u00dfmannstr. 13",
    "sg:city":"Berlin",
    "sg:phone":"+49 30/4223158",
    "sg:postcode":"10249",
    "sg:province":"Berlin",
    "wof:name":"Klaus Haufschild",
    "wof:placetype":"venue"
},
  "geometry": {"coordinates":[13.4486160278,52.5220146179],"type":"Point"}
}