{
  "type": "Feature",
  "properties": {
    "iso:country":"DE",
    "sg:address":"Br\u00fcckenstr. 11",
    "sg:city":"Leichlingen",
    "sg:phone":"+49 2175/970921",
    "sg:postcode":"42799",
    "sg:province":"Nordrhein-Westfalen",
    "wof:name":"Nerger Und Schilling Gmbh",
    "wof:placetype":"venue"
},
  "geometry": {"coordinates":[7.012942791,51.1051025391],"type":"Point"}
}