{
  "type": "Feature",
  "properties": {
    "iso:country":"DE",
    "sg:address":"Hauptstr. 4",
    "sg:city":"Tauscha",
    "sg:postcode":"01561",
    "sg:province":"Sachsen",
    "wof:name":"J. Scheibe",
    "wof:placetype":"venue"
},
  "geometry": {"coordinates":[13.794462,51.267605],"type":"Point"}
}