{
  "type": "Feature",
  "properties": {
    "iso:country":"DE",
    "sg:address":"Frankfurter Str. 208",
    "sg:city":"Gie\u00dfen",
    "sg:phone":"+49 641/22872",
    "sg:postcode":"35398",
    "sg:province":"Hessen",
    "wof:name":"Albert Deibel",
    "wof:placetype":"venue"
},
  "geometry": {"coordinates":[8.6521654129,50.5660896301],"type":"Point"}
}