{
  "type": "Feature",
  "properties": {
    "iso:country":"DE",
    "sg:address":"Am Steinberg 25",
    "sg:city":"D\u00fcren",
    "sg:phone":"+49 2421/87071",
    "sg:postcode":"52353",
    "sg:province":"Nordrhein-Westfalen",
    "wof:name":"Nork Und Berger",
    "wof:placetype":"venue"
},
  "geometry": {"coordinates":[6.4359459877,50.8316116333],"type":"Point"}
}