{
  "type": "Feature",
  "properties": {
    "iso:country":"DE",
    "sg:address":"Silberkaute 51",
    "sg:city":"Freudenberg",
    "sg:phone":"+49 2737/9690",
    "sg:postcode":"57258",
    "sg:province":"Nordrhein-Westfalen",
    "wof:name":"Ajo Tec Gmbh",
    "wof:placetype":"venue"
},
  "geometry": {"coordinates":[7.91176,50.868179],"type":"Point"}
}