{
  "type": "Feature",
  "properties": {
    "iso:country":"DE",
    "sg:address":"Am Krohm 4",
    "sg:city":"Bockenem",
    "sg:phone":"+49 5067/1819",
    "sg:postcode":"31167",
    "sg:province":"Niedersachsen",
    "wof:name":"C. Sickfeld-hillebrecht",
    "wof:placetype":"venue"
},
  "geometry": {"coordinates":[10.152636,52.020149],"type":"Point"}
}