{
  "type": "Feature",
  "properties": {
    "iso:country":"DE",
    "sg:address":"Am Eichenhof 4",
    "sg:city":"Bremerv\u00f6rde",
    "sg:phone":"+49 4767/275",
    "sg:postcode":"27432",
    "sg:province":"Niedersachsen",
    "wof:name":"E. Krischer",
    "wof:placetype":"venue"
},
  "geometry": {"coordinates":[9.177782,53.441357],"type":"Point"}
}