{
  "type": "Feature",
  "properties": {
    "iso:country":"DE",
    "sg:address":"Bahnhofstr. 13",
    "sg:city":"Warstein",
    "sg:phone":"+49 2902/71097",
    "sg:postcode":"59581",
    "sg:province":"Nordrhein-Westfalen",
    "wof:name":"Karl-heinz Linn",
    "wof:placetype":"venue"
},
  "geometry": {"coordinates":[8.336771965,51.4862747192],"type":"Point"}
}