{
  "type": "Feature",
  "properties": {
    "iso:country":"DE",
    "sg:address":"Schulstr. 43",
    "sg:city":"Eibau",
    "sg:phone":"+49 3586/387094",
    "sg:postcode":"02739",
    "sg:province":"Sachsen",
    "wof:name":"Heinz Fiedler",
    "wof:placetype":"venue"
},
  "geometry": {"coordinates":[14.6583127975,50.9792060852],"type":"Point"}
}