{
  "type": "Feature",
  "properties": {
    "iso:country":"DE",
    "sg:address":"L\u00f6ninger Str. 22",
    "sg:city":"L\u00e4hden",
    "sg:phone":"+49 5432/94120",
    "sg:postcode":"49774",
    "sg:province":"Niedersachsen",
    "wof:name":"Willi Herbes",
    "wof:placetype":"venue"
},
  "geometry": {"coordinates":[7.691247,52.775631],"type":"Point"}
}