{
  "type": "Feature",
  "properties": {
    "iso:country":"DE",
    "sg:address":"Auf der L\u00f6bke 5",
    "sg:city":"Halver",
    "sg:postcode":"58553",
    "sg:province":"Nordrhein-Westfalen",
    "wof:name":"E B V-elektronik-bauelemente Vertriebs Gmbh",
    "wof:placetype":"venue"
},
  "geometry": {"coordinates":[7.489813,51.194859],"type":"Point"}
}