{
  "type": "Feature",
  "properties": {
    "iso:country":"DE",
    "sg:address":"Steinstr. 10",
    "sg:city":"Westeregeln",
    "sg:postcode":"39448",
    "sg:province":"Sachsen-Anhalt",
    "wof:name":"Nyhuis Gmbh",
    "wof:placetype":"venue"
},
  "geometry": {"coordinates":[11.391818,51.963482],"type":"Point"}
}