{
  "type": "Feature",
  "properties": {
    "iso:country":"DE",
    "sg:address":"Gneisenaustr. 13",
    "sg:city":"Wiesbaden",
    "sg:phone":"+49 611/405553",
    "sg:postcode":"65195",
    "sg:province":"Hessen",
    "wof:name":"Penny-markt Gmbh",
    "wof:placetype":"venue"
},
  "geometry": {"coordinates":[8.2250699997,50.0811958313],"type":"Point"}
}