{
  "type": "Feature",
  "properties": {
    "iso:country":"DE",
    "sg:address":"Rappenhof",
    "sg:city":"Leonberg",
    "sg:phone":"+49 7152/48418",
    "sg:postcode":"71229",
    "sg:province":"Baden-W\u00fcrttemberg",
    "wof:name":"Herbert Ott Ingenieur",
    "wof:placetype":"venue"
},
  "geometry": {"coordinates":[9.0437746048,48.7761497498],"type":"Point"}
}