{
  "type": "Feature",
  "properties": {
    "iso:country":"DE",
    "sg:address":"Marktstr. 3",
    "sg:city":"Schelklingen",
    "sg:phone":"+49 7394/743",
    "sg:postcode":"89601",
    "sg:province":"Baden-W\u00fcrttemberg",
    "wof:name":"Kurt Boos Gmbh",
    "wof:placetype":"venue"
},
  "geometry": {"coordinates":[9.7322969437,48.3760032654],"type":"Point"}
}