{
  "type": "Feature",
  "properties": {
    "iso:country":"DE",
    "sg:address":"Ruhpoldinger Str. 5",
    "sg:city":"Siegsdorf",
    "sg:phone":"+49 8662/2849",
    "sg:postcode":"83313",
    "sg:province":"Bayern",
    "wof:name":"Priska Geisreiter Steuerberaterin",
    "wof:placetype":"venue"
},
  "geometry": {"coordinates":[12.6451702118,47.8211746216],"type":"Point"}
}