{
  "type": "Feature",
  "properties": {
    "iso:country":"DE",
    "sg:address":"Ringstr. 28",
    "sg:city":"Hackenheim",
    "sg:phone":"+49 671/66641",
    "sg:postcode":"55546",
    "sg:province":"Rheinland-Pfalz",
    "wof:name":"Jupp Korz",
    "wof:placetype":"venue"
},
  "geometry": {"coordinates":[7.8978967667,49.8238067627],"type":"Point"}
}