{
  "type": "Feature",
  "properties": {
    "iso:country":"DE",
    "sg:address":"Magdeburger Str. 53",
    "sg:city":"Krefeld",
    "sg:phone":"+49 2151/496450",
    "sg:postcode":"47800",
    "sg:province":"Nordrhein-Westfalen",
    "wof:name":"Isan Metall Gmbh",
    "wof:placetype":"venue"
},
  "geometry": {"coordinates":[6.617333,51.360229],"type":"Point"}
}