{
  "type": "Feature",
  "properties": {
    "iso:country":"DE",
    "sg:address":"Siemensstr. 2",
    "sg:city":"Ha\u00dfloch",
    "sg:phone":"+49 6324/989040",
    "sg:postcode":"67454",
    "sg:province":"Rheinland-Pfalz",
    "wof:name":"Technischer \u00dcberwachungs- Verein Pfalz E. V.",
    "wof:placetype":"venue"
},
  "geometry": {"coordinates":[8.2376594543,49.3463401794],"type":"Point"}
}