{
  "type": "Feature",
  "properties": {
    "iso:country":"DE",
    "sg:address":"B\u00fcltstiege 14",
    "sg:city":"Rheine",
    "sg:phone":"+49 5971/64181",
    "sg:postcode":"48429",
    "sg:province":"Nordrhein-Westfalen",
    "wof:name":"Holthaus Fu\u00dfbodentechnik Gmbh",
    "wof:placetype":"venue"
},
  "geometry": {"coordinates":[7.4420719147,52.2805328369],"type":"Point"}
}