{
  "type": "Feature",
  "properties": {
    "iso:country":"DE",
    "sg:address":"Hauptstr. 60",
    "sg:city":"Ubstadt-Weiher",
    "sg:phone":"+49 7251/61960",
    "sg:postcode":"76698",
    "sg:province":"Baden-W\u00fcrttemberg",
    "wof:name":"Nikolaus-apotheke",
    "wof:placetype":"venue"
},
  "geometry": {"coordinates":[8.620841,49.177891],"type":"Point"}
}