{
  "type": "Feature",
  "properties": {
    "iso:country":"DE",
    "sg:address":"Burger Str. 19",
    "sg:city":"Kirchzarten",
    "sg:phone":"+49 7661/980555",
    "sg:postcode":"79199",
    "sg:province":"Baden-W\u00fcrttemberg",
    "wof:name":"Mediquip Medizintechnik Inh. Helmut Kaltenbach",
    "wof:placetype":"venue"
},
  "geometry": {"coordinates":[7.958113,47.96674],"type":"Point"}
}