{
  "type": "Feature",
  "properties": {
    "iso:country":"DE",
    "sg:address":"Marienplatz 8",
    "sg:city":"M\u00fcnchen",
    "sg:phone":"+49 89/294132",
    "sg:postcode":"80331",
    "sg:province":"Bayern",
    "wof:name":"Antiquit\u00e4ten Im Rathaus Peter Vogt",
    "wof:placetype":"venue"
},
  "geometry": {"coordinates":[11.576031,48.137444],"type":"Point"}
}