{
  "type": "Feature",
  "properties": {
    "iso:country":"DE",
    "sg:address":"Pfandh\u00f6ferstr. 32",
    "sg:city":"Oberhausen",
    "sg:phone":"+49 208",
    "sg:postcode":"46145",
    "sg:province":"Nordrhein-Westfalen",
    "wof:name":"Fa Automobile",
    "wof:placetype":"venue"
},
  "geometry": {"coordinates":[6.8644680977,51.5208396912],"type":"Point"}
}