{
  "type": "Feature",
  "properties": {
    "iso:country":"DE",
    "sg:address":"Mainzer Str. 4",
    "sg:city":"Eggenstein-Leopoldshafen",
    "sg:phone":"+49 7247/21089",
    "sg:postcode":"76344",
    "sg:province":"Baden-W\u00fcrttemberg",
    "wof:name":"Mode-truhe Gmbh",
    "wof:placetype":"venue"
},
  "geometry": {"coordinates":[8.4041404724,49.0991325378],"type":"Point"}
}