{
  "type": "Feature",
  "properties": {
    "iso:country":"DE",
    "sg:address":"Mehringdamm 97",
    "sg:city":"Berlin",
    "sg:phone":"+49 30/78704707",
    "sg:postcode":"10965",
    "sg:province":"Berlin",
    "wof:name":"Mse Consulting Und Software Gmbh",
    "wof:placetype":"venue"
},
  "geometry": {"coordinates":[13.3863210678,52.4879646301],"type":"Point"}
}