{
  "type": "Feature",
  "properties": {
    "iso:country":"DE",
    "sg:address":"Ollenhauerstr. 23",
    "sg:city":"Berlin",
    "sg:phone":"+49 30/4969310",
    "sg:postcode":"13403",
    "sg:province":"Berlin",
    "wof:name":"La Mondina",
    "wof:placetype":"venue"
},
  "geometry": {"coordinates":[13.3298711777,52.5681495667],"type":"Point"}
}