{
  "type": "Feature",
  "properties": {
    "iso:country":"DE",
    "sg:address":"Lindenstr. 45",
    "sg:city":"Kreien",
    "sg:postcode":"19386",
    "sg:province":"Mecklenburg-Vorpommern",
    "wof:name":"Hmm Hamburg-mannheimer Zweite Immobilien-verwaltungs-",
    "wof:placetype":"venue"
},
  "geometry": {"coordinates":[12.0540895462,53.4077110291],"type":"Point"}
}