{
  "type": "Feature",
  "properties": {
    "iso:country":"DE",
    "sg:address":"Butschstr 2",
    "sg:city":"Trossingen",
    "sg:phone":"+49 7425/27313",
    "sg:postcode":"78647",
    "sg:province":"Baden-W\u00fcrttemberg",
    "wof:name":"Printoplast Gmbh",
    "wof:placetype":"venue"
},
  "geometry": {"coordinates":[8.6379785538,48.0772781372],"type":"Point"}
}