{
  "type": "Feature",
  "properties": {
    "iso:country":"DE",
    "sg:address":"Schmiedestr. 11",
    "sg:city":"Wahrenholz",
    "sg:phone":"+49 5835/519",
    "sg:postcode":"29399",
    "sg:province":"Niedersachsen",
    "wof:name":"Walter Mispelhorn",
    "wof:placetype":"venue"
},
  "geometry": {"coordinates":[10.592384,52.624729],"type":"Point"}
}