{
  "type": "Feature",
  "properties": {
    "iso:country":"DE",
    "sg:address":"Greding",
    "sg:city":"Greding",
    "sg:phone":"+49 8463/237",
    "sg:postcode":"91171",
    "sg:province":"Bayern",
    "wof:name":"Raiffeisenbank Thalm\u00e4ssing Eg",
    "wof:placetype":"venue"
},
  "geometry": {"coordinates":[11.33753,49.066471],"type":"Point"}
}