{
  "type": "Feature",
  "properties": {
    "iso:country":"DE",
    "sg:address":"Fontanestr. 18",
    "sg:city":"Augsburg",
    "sg:phone":"+49 821/553377",
    "sg:postcode":"86161",
    "sg:province":"Bayern",
    "wof:name":"I. Jakob",
    "wof:placetype":"venue"
},
  "geometry": {"coordinates":[10.922611,48.352242],"type":"Point"}
}