{
  "type": "Feature",
  "properties": {
    "iso:country":"DE",
    "sg:address":"Wilhelm-Pieck-Str. 42",
    "sg:city":"Petershagen",
    "sg:phone":"+49 33439/9110",
    "sg:postcode":"15370",
    "sg:province":"Brandenburg",
    "wof:name":"Hotel Blaufuchs",
    "wof:placetype":"venue"
},
  "geometry": {"coordinates":[13.7852010727,52.5194320679],"type":"Point"}
}