{
  "type": "Feature",
  "properties": {
    "iso:country":"DE",
    "sg:address":"Lenzhahner Weg 23a",
    "sg:city":"Niedernhausen",
    "sg:postcode":"65527",
    "sg:province":"Hessen",
    "wof:name":"Dem Quality Consulting Gmbh",
    "wof:placetype":"venue"
},
  "geometry": {"coordinates":[8.3161277771,50.1689872742],"type":"Point"}
}