{
  "type": "Feature",
  "properties": {
    "iso:country":"DE",
    "sg:address":"Markt 3",
    "sg:city":"Falkenberg",
    "sg:postcode":"04895",
    "sg:province":"Brandenburg",
    "wof:name":"Amtsarchiv",
    "wof:placetype":"venue"
},
  "geometry": {"coordinates":[13.237507,51.586834],"type":"Point"}
}