{
  "type": "Feature",
  "properties": {
    "iso:country":"DE",
    "sg:address":"Kuhlengasse 18",
    "sg:city":"Monschau",
    "sg:phone":"+49 2472/1315",
    "sg:postcode":"52156",
    "sg:province":"Nordrhein-Westfalen",
    "wof:name":"M. K. Plast Kunststoff Konfektionsierung Gmbh",
    "wof:placetype":"venue"
},
  "geometry": {"coordinates":[6.230599,50.515678],"type":"Point"}
}