{
  "type": "Feature",
  "properties": {
    "iso:country":"DE",
    "sg:address":"Ledergasse 7",
    "sg:city":"Hohenstein",
    "sg:phone":"+49 7387/465",
    "sg:postcode":"72531",
    "sg:province":"Baden-W\u00fcrttemberg",
    "wof:name":"Hans H\u00f6lz",
    "wof:placetype":"venue"
},
  "geometry": {"coordinates":[9.331158,48.330399],"type":"Point"}
}