{
  "type": "Feature",
  "properties": {
    "iso:country":"DE",
    "sg:address":"Hauptstr. 43",
    "sg:city":"Kirchdorf",
    "sg:phone":"+49 9444/595",
    "sg:postcode":"93348",
    "sg:province":"Bayern",
    "wof:name":"Sparkasse Abensberg",
    "wof:placetype":"venue"
},
  "geometry": {"coordinates":[11.904701,48.770992],"type":"Point"}
}