{
  "type": "Feature",
  "properties": {
    "iso:country":"DE",
    "sg:address":"Altgendorfer Str. 70",
    "sg:city":"Burgkirchen",
    "sg:phone":"+49 8679/5454",
    "sg:postcode":"84508",
    "sg:province":"Bayern",
    "wof:name":"Hans Dirschl",
    "wof:placetype":"venue"
},
  "geometry": {"coordinates":[12.7092199326,48.1688117981],"type":"Point"}
}