{
  "type": "Feature",
  "properties": {
    "iso:country":"DE",
    "sg:address":"Am Gunbelsee",
    "sg:city":"Maxdorf",
    "sg:phone":"+49 6237/6660",
    "sg:postcode":"67133",
    "sg:province":"Rheinland-Pfalz",
    "wof:name":"Vereinsgastst\u00e4tte Sch\u00e4ferhundeverein",
    "wof:placetype":"venue"
},
  "geometry": {"coordinates":[8.2958498001,49.4825134277],"type":"Point"}
}