{
  "type": "Feature",
  "properties": {
    "iso:country":"DE",
    "sg:address":"Werdohler Str. 13",
    "sg:city":"L\u00fcdenscheid",
    "sg:phone":"+49 2351/380132",
    "sg:postcode":"58511",
    "sg:province":"Nordrhein-Westfalen",
    "wof:name":"Cosmetic Dantas",
    "wof:placetype":"venue"
},
  "geometry": {"coordinates":[7.636349,51.216637],"type":"Point"}
}