{
  "type": "Feature",
  "properties": {
    "iso:country":"DE",
    "sg:address":"Haydnweg 12",
    "sg:city":"Traunreut",
    "sg:phone":"+49 8669/37284",
    "sg:postcode":"83301",
    "sg:province":"Bayern",
    "wof:name":"Heiner Und Barbara Klug",
    "wof:placetype":"venue"
},
  "geometry": {"coordinates":[12.583384,47.968216],"type":"Point"}
}