{
  "type": "Feature",
  "properties": {
    "iso:country":"DE",
    "sg:address":"Marktplatz 14",
    "sg:city":"Cham",
    "sg:phone":"+49 9971/20622",
    "sg:postcode":"93413",
    "sg:province":"Bayern",
    "wof:name":"P 2-mode",
    "wof:placetype":"venue"
},
  "geometry": {"coordinates":[12.666171,49.217289],"type":"Point"}
}