{
  "type": "Feature",
  "properties": {
    "iso:country":"DE",
    "sg:address":"Hindenburgstr. 31",
    "sg:city":"Bad K\u00f6nigshofen",
    "sg:phone":"+49 9761/3403",
    "sg:postcode":"97631",
    "sg:province":"Bayern",
    "wof:name":"H. Werner",
    "wof:placetype":"venue"
},
  "geometry": {"coordinates":[10.464876,50.29837],"type":"Point"}
}