{
  "type": "Feature",
  "properties": {
    "iso:country":"DE",
    "sg:address":"Danziger Str. 21",
    "sg:city":"G\u00f6ttingen",
    "sg:phone":"+49 551/704644",
    "sg:postcode":"37083",
    "sg:province":"Niedersachsen",
    "wof:name":"Bel Fit",
    "wof:placetype":"venue"
},
  "geometry": {"coordinates":[9.9463996887,51.5211143494],"type":"Point"}
}