{
  "type": "Feature",
  "properties": {
    "iso:country":"DE",
    "sg:address":"Wilhelm-Hennemann-Str. 8",
    "sg:city":"Schwerin",
    "sg:postcode":"19061",
    "sg:province":"Mecklenburg-Vorpommern",
    "wof:name":"Verwaltungsgesellschaft Mayer Van Ess Mbh",
    "wof:placetype":"venue"
},
  "geometry": {"coordinates":[11.4192457199,53.600189209],"type":"Point"}
}