{
  "type": "Feature",
  "properties": {
    "iso:country":"DE",
    "sg:address":"Am Thomasberg",
    "sg:city":"Eisfeld",
    "sg:postcode":"98673",
    "sg:province":"Th\u00fcringen",
    "wof:name":"Dr. Med. Hans-henning Axthelm",
    "wof:placetype":"venue"
},
  "geometry": {"coordinates":[10.898745,50.426426],"type":"Point"}
}