{
  "type": "Feature",
  "properties": {
    "iso:country":"DE",
    "sg:address":"Bahnhofstr. 9",
    "sg:city":"Schk\u00f6len",
    "sg:phone":"+49 36694/22305",
    "sg:postcode":"07619",
    "sg:province":"Th\u00fcringen",
    "wof:name":"Hilmar Kubik",
    "wof:placetype":"venue"
},
  "geometry": {"coordinates":[11.8243341446,51.0458908081],"type":"Point"}
}