{
  "type": "Feature",
  "properties": {
    "iso:country":"DE",
    "sg:address":"Am Rathaus 1",
    "sg:city":"Geeste",
    "sg:phone":"+49 5937/98686",
    "sg:postcode":"49744",
    "sg:province":"Niedersachsen",
    "wof:name":"Caritas-sozialstation Geest-twist",
    "wof:placetype":"venue"
},
  "geometry": {"coordinates":[7.22951,52.589638],"type":"Point"}
}