{
  "type": "Feature",
  "properties": {
    "iso:country":"DE",
    "sg:address":"R\u00fcdigerstr. 46",
    "sg:city":"Berlin",
    "sg:phone":"+49 30/5596939",
    "sg:postcode":"10365",
    "sg:province":"Berlin",
    "wof:name":"Katrin Ziehrock",
    "wof:placetype":"venue"
},
  "geometry": {"coordinates":[13.499728,52.515453],"type":"Point"}
}