{
  "type": "Feature",
  "properties": {
    "iso:country":"DE",
    "sg:address":"Untere Haardt 30",
    "sg:city":"Zeulenroda",
    "sg:phone":"+49 36628/82589",
    "sg:postcode":"07937",
    "sg:province":"Th\u00fcringen",
    "wof:name":"Gerhard Wei\u00dfleder",
    "wof:placetype":"venue"
},
  "geometry": {"coordinates":[12.010847,50.658318],"type":"Point"}
}