{
  "type": "Feature",
  "properties": {
    "iso:country":"DE",
    "sg:address":"Dorfstr. 19",
    "sg:city":"Rosdorf",
    "sg:phone":"+49 5502/4598",
    "sg:postcode":"37124",
    "sg:province":"Niedersachsen",
    "wof:name":"Dieter M\u00fcller",
    "wof:placetype":"venue"
},
  "geometry": {"coordinates":[9.81673,51.50663],"type":"Point"}
}