{
  "type": "Feature",
  "properties": {
    "iso:country":"DE",
    "sg:address":"Georg-Richter-Str. 16",
    "sg:city":"Frankfurt",
    "sg:phone":"+49 335/414550",
    "sg:postcode":"15234",
    "sg:province":"Brandenburg",
    "wof:name":"Stinnes Stahlhandel Gmbh",
    "wof:placetype":"venue"
},
  "geometry": {"coordinates":[14.503695,52.353226],"type":"Point"}
}