{
  "type": "Feature",
  "properties": {
    "iso:country":"DE",
    "sg:address":"Im Lauser 4",
    "sg:city":"Ummendorf",
    "sg:phone":"+49 7351/44410",
    "sg:postcode":"88444",
    "sg:province":"Baden-W\u00fcrttemberg",
    "wof:name":"Cato Trennwand Gmbh",
    "wof:placetype":"venue"
},
  "geometry": {"coordinates":[9.8138694763,48.0696907043],"type":"Point"}
}