{
  "type": "Feature",
  "properties": {
    "iso:country":"DE",
    "sg:address":"Viktoriastr. 32",
    "sg:city":"M\u00fcnchen",
    "sg:phone":"+49 89/30777666",
    "sg:postcode":"80803",
    "sg:province":"Bayern",
    "wof:name":"M Blade Editing E. K.",
    "wof:placetype":"venue"
},
  "geometry": {"coordinates":[11.5793418884,48.1660575867],"type":"Point"}
}