{
  "type": "Feature",
  "properties": {
    "iso:country":"DE",
    "sg:address":"Galileistr. 19",
    "sg:city":"Bad Oeynhausen",
    "sg:phone":"+49 5731/21040",
    "sg:postcode":"32547",
    "sg:province":"Nordrhein-Westfalen",
    "wof:name":"Regina Hoberg Steuerberaterin",
    "wof:placetype":"venue"
},
  "geometry": {"coordinates":[8.8219079971,52.211566925],"type":"Point"}
}