{
  "type": "Feature",
  "properties": {
    "iso:country":"DE",
    "sg:address":"Vorbrucher Str. 42",
    "sg:city":"Schwanewede",
    "sg:phone":"+49 421/689874",
    "sg:postcode":"28790",
    "sg:province":"Niedersachsen",
    "wof:name":"Uslar & Morisse Tischlerei Und Fensterbau Gmbh & Co. Kg",
    "wof:placetype":"venue"
},
  "geometry": {"coordinates":[8.527236,53.23925],"type":"Point"}
}