{
  "type": "Feature",
  "properties": {
    "iso:country":"DE",
    "sg:address":"R\u00f6hrstr. 6",
    "sg:city":"Weimar",
    "sg:phone":"+49 3643/202702",
    "sg:postcode":"99423",
    "sg:province":"Th\u00fcringen",
    "wof:name":"Bernhard Hesse",
    "wof:placetype":"venue"
},
  "geometry": {"coordinates":[11.3226852417,50.9880065918],"type":"Point"}
}