{
  "type": "Feature",
  "properties": {
    "iso:country":"DE",
    "sg:address":"Kaiserstr. 25",
    "sg:city":"Pfullingen",
    "sg:phone":"+49 7121/754567",
    "sg:postcode":"72793",
    "sg:province":"Baden-W\u00fcrttemberg",
    "wof:name":"B. W\u00fcst",
    "wof:placetype":"venue"
},
  "geometry": {"coordinates":[9.227258,48.468521],"type":"Point"}
}