{
  "type": "Feature",
  "properties": {
    "iso:country":"DE",
    "sg:address":"Rudolf-Diesel-Str. 3",
    "sg:city":"Genthin",
    "sg:phone":"+49 3933/802943",
    "sg:postcode":"39307",
    "sg:province":"Sachsen-Anhalt",
    "wof:name":"Dhs Druckluft Und Hydraulik Steuerungen Gesellschaft Mbh",
    "wof:placetype":"venue"
},
  "geometry": {"coordinates":[12.141499,52.390018],"type":"Point"}
}