{
  "type": "Feature",
  "properties": {
    "iso:country":"DE",
    "sg:address":"Waldstr. 4",
    "sg:city":"Hilgert",
    "sg:phone":"+49 2624/3291",
    "sg:postcode":"56206",
    "sg:province":"Rheinland-Pfalz",
    "wof:name":"I. Achtzehn",
    "wof:placetype":"venue"
},
  "geometry": {"coordinates":[7.694195,50.453449],"type":"Point"}
}