{
  "type": "Feature",
  "properties": {
    "iso:country":"DE",
    "sg:address":"Benkendorferstr. 19",
    "sg:city":"Schwabach",
    "sg:phone":"+49 9122/12630",
    "sg:postcode":"91126",
    "sg:province":"Bayern",
    "wof:name":"Knollinger",
    "wof:placetype":"venue"
},
  "geometry": {"coordinates":[11.0178985596,49.3307685852],"type":"Point"}
}