{
  "type": "Feature",
  "properties": {
    "iso:country":"DE",
    "sg:address":"Vorbecker Landweg 36",
    "sg:city":"Schwaan",
    "sg:phone":"+49 3844/811062",
    "sg:postcode":"18258",
    "sg:province":"Mecklenburg-Vorpommern",
    "wof:name":"I. Becker",
    "wof:placetype":"venue"
},
  "geometry": {"coordinates":[12.0996208191,53.9300270081],"type":"Point"}
}