{
  "type": "Feature",
  "properties": {
    "iso:country":"DE",
    "sg:address":"Oberes Brunnental 9",
    "sg:city":"Lauingen",
    "sg:postcode":"89415",
    "sg:province":"Bayern",
    "wof:name":"Heinrich B. Weyers",
    "wof:placetype":"venue"
},
  "geometry": {"coordinates":[10.4303855896,48.5674705505],"type":"Point"}
}