{
  "type": "Feature",
  "properties": {
    "iso:country":"DE",
    "sg:address":"Tiefer Weg 3",
    "sg:city":"Georgsmarienh\u00fctte",
    "sg:phone":"+49 5409/510",
    "sg:postcode":"49124",
    "sg:province":"Niedersachsen",
    "wof:name":"Stefan Sielschott",
    "wof:placetype":"venue"
},
  "geometry": {"coordinates":[8.12792,52.20195],"type":"Point"}
}