{
  "type": "Feature",
  "properties": {
    "iso:country":"DE",
    "sg:address":"Fritz-Rahmen-Str. 44",
    "sg:city":"M\u00f6nchengladbach",
    "sg:phone":"+49 2161/583983",
    "sg:postcode":"41239",
    "sg:province":"Nordrhein-Westfalen",
    "wof:name":"Hans-hermann Nothofer Steuerberater",
    "wof:placetype":"venue"
},
  "geometry": {"coordinates":[6.4255490303,51.1557350159],"type":"Point"}
}