{
  "type": "Feature",
  "properties": {
    "iso:country":"DE",
    "sg:address":"Sonnenallee 217",
    "sg:city":"Berlin",
    "sg:phone":"+49 30/6898980",
    "sg:postcode":"12059",
    "sg:province":"Berlin",
    "wof:name":"Erich Roder Sanit\u00e4r Heizung Bauklempnerei Berlin",
    "wof:placetype":"venue"
},
  "geometry": {"coordinates":[13.455602,52.474205],"type":"Point"}
}