{
  "type": "Feature",
  "properties": {
    "iso:country":"DE",
    "sg:address":"Bahnhofstr. 5",
    "sg:city":"Frankenberg",
    "sg:phone":"+49 6451/716105",
    "sg:postcode":"35066",
    "sg:province":"Hessen",
    "wof:name":"Ristorante Azzuro",
    "wof:placetype":"venue"
},
  "geometry": {"coordinates":[8.7920331955,51.056098938],"type":"Point"}
}