{
  "type": "Feature",
  "properties": {
    "iso:country":"DE",
    "sg:address":"Klosterstr. 5",
    "sg:city":"Forchheim",
    "sg:phone":"+49 9191/70880",
    "sg:postcode":"91301",
    "sg:province":"Bayern",
    "wof:name":"Redaktion Fr\u00e4nkischer Tag",
    "wof:placetype":"venue"
},
  "geometry": {"coordinates":[11.0629863739,49.7183151245],"type":"Point"}
}