{
  "type": "Feature",
  "properties": {
    "iso:country":"DE",
    "sg:address":"Friesenstr. 49",
    "sg:city":"K\u00f6ln",
    "sg:phone":"+49 221/2583536",
    "sg:postcode":"50670",
    "sg:province":"Nordrhein-Westfalen",
    "wof:name":"James",
    "wof:placetype":"venue"
},
  "geometry": {"coordinates":[6.9433660507,50.9406051636],"type":"Point"}
}