{
  "type": "Feature",
  "properties": {
    "iso:country":"DE",
    "sg:address":"K\u00f6nigsallee 178b",
    "sg:city":"Bochum",
    "sg:phone":"+49 234/777666",
    "sg:postcode":"44799",
    "sg:province":"Nordrhein-Westfalen",
    "wof:name":"Starlight-express",
    "wof:placetype":"venue"
},
  "geometry": {"coordinates":[7.223470211,51.4583358765],"type":"Point"}
}