{
  "type": "Feature",
  "properties": {
    "iso:country":"DE",
    "sg:address":"Wischmattenweg 3B",
    "sg:city":"Berlin",
    "sg:phone":"+49 30/5348018",
    "sg:postcode":"12357",
    "sg:province":"Berlin",
    "wof:name":"Johann Wei\u00df",
    "wof:placetype":"venue"
},
  "geometry": {"coordinates":[13.5117902756,52.4244537354],"type":"Point"}
}