{
  "type": "Feature",
  "properties": {
    "iso:country":"DE",
    "sg:address":"Eichendorffstr. 3",
    "sg:city":"Dreieich",
    "sg:postcode":"63303",
    "sg:province":"Hessen",
    "wof:name":"P & P Wohnungsbau- Gesellschaft Mbh",
    "wof:placetype":"venue"
},
  "geometry": {"coordinates":[8.726255,49.996784],"type":"Point"}
}