{
  "type": "Feature",
  "properties": {
    "iso:country":"DE",
    "sg:address":"Krumme Str. 10",
    "sg:city":"Berlin",
    "sg:phone":"+49 30/3423032",
    "sg:postcode":"10585",
    "sg:province":"Berlin",
    "wof:name":"Birgit M\u00f6ller Masseurin",
    "wof:placetype":"venue"
},
  "geometry": {"coordinates":[13.309475,52.514507],"type":"Point"}
}