{
  "type": "Feature",
  "properties": {
    "iso:country":"DE",
    "sg:address":"Gei\u00dfg\u00e4\u00dfchen 1",
    "sg:city":"Bodenmais",
    "sg:phone":"+49 9924/859",
    "sg:postcode":"94249",
    "sg:province":"Bayern",
    "wof:name":"Pizzeria Italia",
    "wof:placetype":"venue"
},
  "geometry": {"coordinates":[13.0979356766,49.0674133301],"type":"Point"}
}