{
  "type": "Feature",
  "properties": {
    "iso:country":"DE",
    "sg:address":"Hermann-Funk-Str. 4",
    "sg:city":"Bremen",
    "sg:postcode":"28309",
    "sg:province":"Bremen",
    "wof:name":"Zech Gewerbebau Gmbh",
    "wof:placetype":"venue"
},
  "geometry": {"coordinates":[8.881041,53.055855],"type":"Point"}
}