{
  "type": "Feature",
  "properties": {
    "iso:country":"DE",
    "sg:address":"Richard-Vosgerau-Str. 65",
    "sg:city":"Eckernf\u00f6rde",
    "sg:phone":"+49 4351/85616",
    "sg:postcode":"24340",
    "sg:province":"Schleswig-Holstein",
    "wof:name":"Eva Schneider Hebamme",
    "wof:placetype":"venue"
},
  "geometry": {"coordinates":[9.83781,54.465633],"type":"Point"}
}