{
  "type": "Feature",
  "properties": {
    "iso:country":"DE",
    "sg:address":"Anton-Jaumann-Industriepark 9",
    "sg:city":"N\u00f6rdlingen",
    "sg:phone":"+49 9081/80120",
    "sg:postcode":"86720",
    "sg:province":"Bayern",
    "wof:name":"Symrise Gmbh & Co Kg",
    "wof:placetype":"venue"
},
  "geometry": {"coordinates":[10.508335,48.839996],"type":"Point"}
}