{
  "type": "Feature",
  "properties": {
    "iso:country":"DE",
    "sg:address":"Elisabethstr. 35",
    "sg:city":"Eutin",
    "sg:phone":"+49 4521/2553",
    "sg:postcode":"23701",
    "sg:province":"Schleswig-Holstein",
    "wof:name":"Klaus Schr\u00f6der Bestattungen Gmbh",
    "wof:placetype":"venue"
},
  "geometry": {"coordinates":[10.612359,54.132908],"type":"Point"}
}