{
  "type": "Feature",
  "properties": {
    "iso:country":"DE",
    "sg:address":"Sanddornweg 1 b",
    "sg:city":"Bad Hersfeld",
    "sg:postcode":"36251",
    "sg:province":"Hessen",
    "wof:name":"Bartek Hausbau Gmbh",
    "wof:placetype":"venue"
},
  "geometry": {"coordinates":[9.702332,50.84618],"type":"Point"}
}