{
  "type": "Feature",
  "properties": {
    "iso:country":"DE",
    "sg:address":"Entenweg 1",
    "sg:city":"Saarlouis",
    "sg:phone":"+49 6831/48001",
    "sg:postcode":"66740",
    "sg:province":"Saarland",
    "wof:name":"Jochen Birk Architekt",
    "wof:placetype":"venue"
},
  "geometry": {"coordinates":[6.74132,49.309357],"type":"Point"}
}