{
  "type": "Feature",
  "properties": {
    "iso:country":"DE",
    "sg:address":"Gewerbestr. 10",
    "sg:city":"Sprockh\u00f6vel",
    "sg:phone":"+49 2339/3156",
    "sg:postcode":"45549",
    "sg:province":"Nordrhein-Westfalen",
    "wof:name":"Bernd Wehmeier",
    "wof:placetype":"venue"
},
  "geometry": {"coordinates":[7.261705,51.331486],"type":"Point"}
}