{
  "type": "Feature",
  "properties": {
    "iso:country":"DE",
    "sg:address":"Goethestr. 91",
    "sg:city":"Schwerin",
    "sg:phone":"+49 385/5574610",
    "sg:postcode":"19053",
    "sg:province":"Mecklenburg-Vorpommern",
    "wof:name":"Schweriner Azur Reiseb\u00fcro Gmbh",
    "wof:placetype":"venue"
},
  "geometry": {"coordinates":[11.4106760025,53.6272506714],"type":"Point"}
}