{
  "type": "Feature",
  "properties": {
    "iso:country":"DE",
    "sg:address":"Methfesselstr. 60",
    "sg:city":"Hamburg",
    "sg:phone":"+49 40/405596",
    "sg:postcode":"20257",
    "sg:province":"Hamburg",
    "wof:name":"Ursula Nickel",
    "wof:placetype":"venue"
},
  "geometry": {"coordinates":[9.946104,53.57959],"type":"Point"}
}