{
  "type": "Feature",
  "properties": {
    "iso:country":"DE",
    "sg:address":"Mariental 69",
    "sg:city":"Herzberg",
    "sg:phone":"+49 5521/5475",
    "sg:postcode":"37412",
    "sg:province":"Niedersachsen",
    "wof:name":"Pension Ingrid Specht",
    "wof:placetype":"venue"
},
  "geometry": {"coordinates":[10.3571567535,51.6948394775],"type":"Point"}
}