{
  "type": "Feature",
  "properties": {
    "iso:country":"DE",
    "sg:address":"Schwalbenstr. 12",
    "sg:city":"Pasewalk",
    "sg:phone":"+49 3973/213910",
    "sg:postcode":"17309",
    "sg:province":"Mecklenburg-Vorpommern",
    "wof:name":"R. Rollin",
    "wof:placetype":"venue"
},
  "geometry": {"coordinates":[13.993705,53.494122],"type":"Point"}
}