{
  "type": "Feature",
  "properties": {
    "iso:country":"DE",
    "sg:address":"Martinistr. 48",
    "sg:city":"Bremen",
    "sg:phone":"+49 421/30750",
    "sg:postcode":"28195",
    "sg:province":"Bremen",
    "wof:name":"Nf-verm\u00f6gensverwaltung Gmbh",
    "wof:placetype":"venue"
},
  "geometry": {"coordinates":[8.8026733398,53.0772247314],"type":"Point"}
}