{
  "type": "Feature",
  "properties": {
    "iso:country":"DE",
    "sg:address":"Zeppelinstr. 3",
    "sg:city":"Bamberg",
    "sg:phone":"+49 951/406070",
    "sg:postcode":"96052",
    "sg:province":"Bayern",
    "wof:name":"J. C. Neupert",
    "wof:placetype":"venue"
},
  "geometry": {"coordinates":[10.9072389603,49.9157752991],"type":"Point"}
}