{
  "type": "Feature",
  "properties": {
    "iso:country":"DE",
    "sg:address":"N\u00fcrnberger Str. 17a",
    "sg:city":"Veitsbronn",
    "sg:phone":"+49 911/751772",
    "sg:postcode":"90587",
    "sg:province":"Bayern",
    "wof:name":"Friedrich Trautnitz",
    "wof:placetype":"venue"
},
  "geometry": {"coordinates":[10.886445,49.509914],"type":"Point"}
}