{
  "type": "Feature",
  "properties": {
    "iso:country":"DE",
    "sg:city":"Puderbach",
    "sg:phone":"+49 2684/1570",
    "sg:postcode":"56305",
    "sg:province":"Rheinland-Pfalz",
    "wof:name":"Wilfried Kaul Gmbh",
    "wof:placetype":"venue"
},
  "geometry": {"coordinates":[7.611309,50.600327],"type":"Point"}
}