{
  "type": "Feature",
  "properties": {
    "iso:country":"DE",
    "sg:address":"Kalinnastr. 4",
    "sg:city":"Lauingen",
    "sg:phone":"+49 9072/3066",
    "sg:postcode":"89415",
    "sg:province":"Bayern",
    "wof:name":"Stadtzeitung Vertriebs Gmbh",
    "wof:placetype":"venue"
},
  "geometry": {"coordinates":[10.432687,48.578777],"type":"Point"}
}