{
  "type": "Feature",
  "properties": {
    "iso:country":"DE",
    "sg:address":"Osterfeldstr. 14",
    "sg:city":"Gelsenkirchen",
    "sg:phone":"+49 209/170010",
    "sg:postcode":"45886",
    "sg:province":"Nordrhein-Westfalen",
    "wof:name":"Vereinigte Bauhand- Werker Gmbh",
    "wof:placetype":"venue"
},
  "geometry": {"coordinates":[7.1236729622,51.4935646057],"type":"Point"}
}