{
  "type": "Feature",
  "properties": {
    "iso:country":"DE",
    "sg:address":"Gartenweg 10",
    "sg:city":"Oberelsbach",
    "sg:phone":"+49 9774/331",
    "sg:postcode":"97656",
    "sg:province":"Bayern",
    "wof:name":"G\u00fcnter Riedenberger",
    "wof:placetype":"venue"
},
  "geometry": {"coordinates":[10.1237850189,50.4413414001],"type":"Point"}
}