{"geometry":{"type":"Point","coordinates":[9.094076,51.942356]},"type":"Feature","id":102560667,"bbox":[9.094076,51.942356,9.094076,51.942356],"properties":{"sg:province":"Nordrhein-Westfalen","geom:longitude":9.094076,"wof:breaches":[],"sg:href":"http://api.simplegeo.com/1.0/features/SG_3kMbVGPLhMqRVSzlp0CPkL_51.942356_9.094076@1306268793.json","sg:owner":"simplegeo","sg:postcode":"32825","geom:latitude":51.942356,"sg:classifiers":[],"sg:address":"Rosenstr. 5::","sg:phone":"+49 4952/3595080","wof:hierarchy":[{"locality_id":101809135,"venue_id":102560667,"country_id":85633111,"region_id":85682513,"county_id":102063883}],"geom:area":0.000000,"sg:city":"Blomberg","wof:lastmodified":1438093324,"iso:country":"DE","wof:geomhash":"dfedb708063d5f39586a3aca47d38239","wof:name":"Stadtsparkasse Blomberg/lippe","wof:belongsto":[101809135,85633111,85682513,102063883],"src:geom":"simplegeo","wof:placetype":"venue","wof:supersedes":[],"wof:id":102560667,"wof:superseded_by":[],"wof:concordances":{"sg:id":"SG_3kMbVGPLhMqRVSzlp0CPkL_51.942356_9.094076@1306268793"},"wof:parent_id":101809135}}