{
  "type": "Feature",
  "properties": {
    "iso:country":"DE",
    "sg:address":"Rosenstr. 5::",
    "sg:city":"Blomberg",
    "sg:href":"http://api.simplegeo.com/1.0/features/SG_3kMbVGPLhMqRVSzlp0CPkL_51.942356_9.094076@1306268793.json",
    "sg:phone":"+49 4952/3595080",
    "sg:postcode":"32825",
    "sg:province":"Nordrhein-Westfalen",
    "wof:name":"Stadtsparkasse Blomberg/lippe",
    "wof:placetype":"venue"
},
  "geometry": {"coordinates":[9.094076,51.942356],"type":"Point"}
}