{
  "type": "Feature",
  "properties": {
    "iso:country":"DE",
    "sg:address":"Naumburger Str. 6",
    "sg:city":"Osterfeld",
    "sg:phone":"+49 34422/21228",
    "sg:postcode":"06721",
    "sg:province":"Sachsen-Anhalt",
    "wof:name":"Bauernstube",
    "wof:placetype":"venue"
},
  "geometry": {"coordinates":[11.926448822,51.0817222595],"type":"Point"}
}