{
  "type": "Feature",
  "properties": {
    "iso:country":"DE",
    "sg:address":"Langer Kummer 53",
    "sg:city":"Iserlohn",
    "sg:postcode":"58642",
    "sg:province":"Nordrhein-Westfalen",
    "wof:name":"Bauland Gmbh",
    "wof:placetype":"venue"
},
  "geometry": {"coordinates":[7.6148638725,51.3648300171],"type":"Point"}
}