{
  "type": "Feature",
  "properties": {
    "iso:country":"DE",
    "sg:address":"Riedstr. 10",
    "sg:city":"Ochsenhausen",
    "sg:phone":"+49 7352/7531",
    "sg:postcode":"88416",
    "sg:province":"Baden-W\u00fcrttemberg",
    "wof:name":"A. Kutter",
    "wof:placetype":"venue"
},
  "geometry": {"coordinates":[9.954000473,48.068031311],"type":"Point"}
}