{
  "type": "Feature",
  "properties": {
    "iso:country":"DE",
    "sg:address":"Schubertstr. 7",
    "sg:city":"Mettmann",
    "sg:phone":"+49 2104/12889",
    "sg:postcode":"40822",
    "sg:province":"Nordrhein-Westfalen",
    "wof:name":"K. Sch\u00fcrmann",
    "wof:placetype":"venue"
},
  "geometry": {"coordinates":[6.9822602272,51.2387275696],"type":"Point"}
}