{
  "type": "Feature",
  "properties": {
    "iso:country":"DE",
    "sg:address":"Herzogenriedstr 16",
    "sg:city":"Mannheim",
    "sg:phone":"+49 621/305283",
    "sg:postcode":"68169",
    "sg:province":"Baden-W\u00fcrttemberg",
    "wof:name":"Elektro Kuhn Ek",
    "wof:placetype":"venue"
},
  "geometry": {"coordinates":[8.472807,49.508183],"type":"Point"}
}