{
  "type": "Feature",
  "properties": {
    "iso:country":"DE",
    "sg:address":"Thing 17",
    "sg:city":"Salzkotten",
    "sg:phone":"+49 2955/7332",
    "sg:postcode":"33154",
    "sg:province":"Nordrhein-Westfalen",
    "wof:name":"Josef B\u00f6gemann",
    "wof:placetype":"venue"
},
  "geometry": {"coordinates":[8.67853,51.634708],"type":"Point"}
}