{
  "type": "Feature",
  "properties": {
    "iso:country":"DE",
    "sg:address":"Hohenpfad 15",
    "sg:city":"Bremen",
    "sg:phone":"+49 421/700020",
    "sg:postcode":"28203",
    "sg:province":"Bremen",
    "wof:name":"Computer-agentur Hering",
    "wof:placetype":"venue"
},
  "geometry": {"coordinates":[8.8196115494,53.0726661682],"type":"Point"}
}