{
  "type": "Feature",
  "properties": {
    "iso:country":"DE",
    "sg:address":"Feldstra\u00dfe 11",
    "sg:city":"Seehausen",
    "sg:phone":"+49 39386/54353",
    "sg:postcode":"39615",
    "sg:province":"Sachsen-Anhalt",
    "wof:name":"Interactive Design",
    "wof:placetype":"venue"
},
  "geometry": {"coordinates":[11.741226,52.889843],"type":"Point"}
}