{
  "type": "Feature",
  "properties": {
    "iso:country":"DE",
    "sg:address":"Kahnsgasse 6",
    "sg:city":"Bernburg",
    "sg:phone":"+49 3471/352003",
    "sg:postcode":"06406",
    "sg:province":"Sachsen-Anhalt",
    "wof:name":"Eberhardt Gawlich",
    "wof:placetype":"venue"
},
  "geometry": {"coordinates":[11.734391,51.799278],"type":"Point"}
}