{
  "type": "Feature",
  "properties": {
    "iso:country":"DE",
    "sg:address":"Annen 3",
    "sg:city":"Gro\u00df Ippener",
    "sg:postcode":"27243",
    "sg:province":"Niedersachsen",
    "wof:name":"Werner Reumann Dachbegr\u00fcnung Gmbh",
    "wof:placetype":"venue"
},
  "geometry": {"coordinates":[8.616267,52.990479],"type":"Point"}
}