{
  "type": "Feature",
  "properties": {
    "iso:country":"DE",
    "sg:address":"K\u00fchnhofener Str. 9",
    "sg:city":"Hersbruck",
    "sg:phone":"+49 9151/95112",
    "sg:postcode":"91217",
    "sg:province":"Bayern",
    "wof:name":"Anna Biegel",
    "wof:placetype":"venue"
},
  "geometry": {"coordinates":[11.4131813049,49.51039505],"type":"Point"}
}