{
  "type": "Feature",
  "properties": {
    "iso:country":"DE",
    "sg:address":"Alte Landstr 11",
    "sg:city":"Bedburg-Hau",
    "sg:phone":"+49 2821/47887",
    "sg:postcode":"47551",
    "sg:province":"Nordrhein-Westfalen",
    "wof:name":"Volksbank Eg",
    "wof:placetype":"venue"
},
  "geometry": {"coordinates":[6.17199,51.760471],"type":"Point"}
}