{
  "type": "Feature",
  "properties": {
    "iso:country":"DE",
    "sg:address":"Cloppenburger Str. 280",
    "sg:city":"Oldenburg",
    "sg:phone":"+49 441/42266",
    "sg:postcode":"26133",
    "sg:province":"Niedersachsen",
    "wof:name":"Iris Kalkbrenner",
    "wof:placetype":"venue"
},
  "geometry": {"coordinates":[8.211807,53.113785],"type":"Point"}
}