{
  "type": "Feature",
  "properties": {
    "iso:country":"DE",
    "sg:address":"Mutzkstr. 3",
    "sg:city":"Senftenberg",
    "sg:phone":"+49 3573/3363",
    "sg:postcode":"01968",
    "sg:province":"Brandenburg",
    "wof:name":"Reinhard Gurk",
    "wof:placetype":"venue"
},
  "geometry": {"coordinates":[13.997515,51.522144],"type":"Point"}
}