{
  "type": "Feature",
  "properties": {
    "iso:country":"DE",
    "sg:address":"Baldusstr. 3",
    "sg:city":"Duisburg",
    "sg:phone":"+49 4920/3437870",
    "sg:postcode":"47138",
    "sg:province":"Nordrhein-Westfalen",
    "wof:name":"Adm Media E.k.",
    "wof:placetype":"venue"
},
  "geometry": {"coordinates":[6.7874331474,51.457195282],"type":"Point"}
}