{
  "type": "Feature",
  "properties": {
    "iso:country":"DE",
    "sg:address":"Semmelweisstr. 74",
    "sg:city":"N\u00fcrnberg",
    "sg:phone":"+49 911/543608",
    "sg:postcode":"90482",
    "sg:province":"Bayern",
    "wof:name":"Hans Heumann",
    "wof:placetype":"venue"
},
  "geometry": {"coordinates":[11.1383905411,49.4648246765],"type":"Point"}
}