{
  "type": "Feature",
  "properties": {
    "iso:country":"DE",
    "sg:address":"Beethovenstr. 11",
    "sg:city":"Bergisch Gladbach",
    "sg:phone":"+49 2204/22016",
    "sg:postcode":"51427",
    "sg:province":"Nordrhein-Westfalen",
    "wof:name":"Jakob Baltes",
    "wof:placetype":"venue"
},
  "geometry": {"coordinates":[7.139257,50.953766],"type":"Point"}
}