{
  "type": "Feature",
  "properties": {
    "iso:country":"DE",
    "sg:address":"Echternstr. 17",
    "sg:city":"Peine",
    "sg:phone":"+49 5171/15720",
    "sg:postcode":"31224",
    "sg:province":"Niedersachsen",
    "wof:name":"H. Hildebrandt",
    "wof:placetype":"venue"
},
  "geometry": {"coordinates":[10.2283973694,52.3223457336],"type":"Point"}
}