{
  "type": "Feature",
  "properties": {
    "iso:country":"DE",
    "sg:address":"Agathe-Zeiss-Str. 5 POSTFACH 10131",
    "sg:city":"Radeberg",
    "sg:phone":"+49 4935/2840820",
    "sg:postcode":"01446",
    "sg:province":"Sachsen",
    "wof:name":"Bira-produktions-und Handels Gmbh",
    "wof:placetype":"venue"
},
  "geometry": {"coordinates":[13.9280185699,51.1042861938],"type":"Point"}
}