{
  "type": "Feature",
  "properties": {
    "iso:country":"DE",
    "sg:address":"Birkend\u00f6rfle 20",
    "sg:city":"Stuttgart",
    "sg:phone":"+49 711/2567310",
    "sg:postcode":"70191",
    "sg:province":"Baden-W\u00fcrttemberg",
    "wof:name":"Wn Pressen Systeme Gmbh",
    "wof:placetype":"venue"
},
  "geometry": {"coordinates":[9.173049,48.791992],"type":"Point"}
}