{
  "type": "Feature",
  "properties": {
    "iso:country":"DE",
    "sg:address":"Schwalbacher Str 76",
    "sg:city":"Wiesbaden",
    "sg:phone":"+49 611/180990",
    "sg:postcode":"65183",
    "sg:province":"Hessen",
    "wof:name":"Scholz & Volkmer Intermediales Design Gmbh",
    "wof:placetype":"venue"
},
  "geometry": {"coordinates":[8.2355079651,50.0863037109],"type":"Point"}
}