{
  "type": "Feature",
  "properties": {
    "iso:country":"DE",
    "sg:address":"Dockenhudener Chaussee 79",
    "sg:city":"Halstenbek",
    "sg:postcode":"25469",
    "sg:province":"Schleswig-Holstein",
    "wof:name":"Japanisches Institut In Hamburg E. V.",
    "wof:placetype":"venue"
},
  "geometry": {"coordinates":[9.8305997849,53.6256484985],"type":"Point"}
}