{
  "type": "Feature",
  "properties": {
    "iso:country":"DE",
    "sg:address":"Tegernseer Str. 15",
    "sg:city":"Hausham",
    "sg:phone":"+49 8026/8370",
    "sg:postcode":"83734",
    "sg:province":"Bayern",
    "wof:name":"Hannelore Sing Reform-drogerie Honner",
    "wof:placetype":"venue"
},
  "geometry": {"coordinates":[11.834574,47.750706],"type":"Point"}
}