{
  "type": "Feature",
  "properties": {
    "iso:country":"DE",
    "sg:address":"Altenberger Str. 6",
    "sg:city":"Havixbeck",
    "sg:phone":"+49 2507/4675",
    "sg:postcode":"48329",
    "sg:province":"Nordrhein-Westfalen",
    "wof:name":"Extra-schnitt Das Andere Frisurenerlebnis",
    "wof:placetype":"venue"
},
  "geometry": {"coordinates":[7.411465168,51.9763565063],"type":"Point"}
}