{
  "type": "Feature",
  "properties": {
    "iso:country":"DE",
    "sg:address":"K\u00f6nigsbergallee 11",
    "sg:city":"Bad Arolsen",
    "sg:phone":"+49 5691/5774",
    "sg:postcode":"34454",
    "sg:province":"Hessen",
    "wof:name":"H. Flemmer Fu\u00dfpflege",
    "wof:placetype":"venue"
},
  "geometry": {"coordinates":[9.0185880661,51.373008728],"type":"Point"}
}