{
  "type": "Feature",
  "properties": {
    "iso:country":"DE",
    "sg:address":"Nieder-Ramst\u00e4dter-Str. 48",
    "sg:city":"Ober-Ramstadt",
    "sg:phone":"+49 6154/2209",
    "sg:postcode":"64372",
    "sg:province":"Hessen",
    "wof:name":"Deutsche Shell Ag",
    "wof:placetype":"venue"
},
  "geometry": {"coordinates":[8.7399406433,49.8313941956],"type":"Point"}
}