{
  "type": "Feature",
  "properties": {
    "iso:country":"DE",
    "sg:address":"Wambeler Hellweg 175",
    "sg:city":"Dortmund",
    "sg:phone":"+49 231/593300",
    "sg:postcode":"44143",
    "sg:province":"Nordrhein-Westfalen",
    "wof:name":"K. J. Knocke",
    "wof:placetype":"venue"
},
  "geometry": {"coordinates":[7.528654,51.521847],"type":"Point"}
}