{
  "type": "Feature",
  "properties": {
    "iso:country":"DE",
    "sg:address":"Frielendorfer Str. 17",
    "sg:city":"Borken",
    "sg:phone":"+49 6693/407",
    "sg:postcode":"34582",
    "sg:province":"Hessen",
    "wof:name":"Georg Heide",
    "wof:placetype":"venue"
},
  "geometry": {"coordinates":[9.289919,50.996517],"type":"Point"}
}