{
  "type": "Feature",
  "properties": {
    "iso:country":"DE",
    "sg:address":"Im Wiesbrunnen 32",
    "sg:city":"Weil der Stadt",
    "sg:phone":"+49 7033/36434",
    "sg:postcode":"71263",
    "sg:province":"Baden-W\u00fcrttemberg",
    "wof:name":"M. Und M. Blanz",
    "wof:placetype":"venue"
},
  "geometry": {"coordinates":[8.818936348,48.7714653015],"type":"Point"}
}