{
  "type": "Feature",
  "properties": {
    "iso:country":"DE",
    "sg:address":"Brockmannsweg 8",
    "sg:city":"Hemmoor",
    "sg:postcode":"21745",
    "sg:province":"Niedersachsen",
    "wof:name":"Ms Gisela W. Waller Kg",
    "wof:placetype":"venue"
},
  "geometry": {"coordinates":[9.173452,53.680988],"type":"Point"}
}