{
  "type": "Feature",
  "properties": {
    "iso:country":"DE",
    "sg:address":"Kohlfurther Str. 37",
    "sg:city":"Solingen",
    "sg:phone":"+49 212/57250",
    "sg:postcode":"42651",
    "sg:province":"Nordrhein-Westfalen",
    "wof:name":"Wecomatic Ger\u00e4tebau Und Handel Gmbh",
    "wof:placetype":"venue"
},
  "geometry": {"coordinates":[7.108945,51.189919],"type":"Point"}
}