{
  "type": "Feature",
  "properties": {
    "iso:country":"DE",
    "sg:address":"Ansbacher Str. 9",
    "sg:city":"Neustadt",
    "sg:phone":"+49 9161/88840",
    "sg:postcode":"91413",
    "sg:province":"Bayern",
    "wof:name":"Bayer. Versicherungskammer",
    "wof:placetype":"venue"
},
  "geometry": {"coordinates":[10.6064195633,49.576839447],"type":"Point"}
}