{
  "type": "Feature",
  "properties": {
    "iso:country":"DE",
    "sg:address":"Moritzh\u00f6fen 8 b",
    "sg:city":"Bayreuth",
    "sg:postcode":"95447",
    "sg:province":"Bayern",
    "wof:name":"A. B. P. Division Schmuck- Gro\u00dfhandel Gmbh & Co. Kg",
    "wof:placetype":"venue"
},
  "geometry": {"coordinates":[11.5739459991,49.9379997253],"type":"Point"}
}