{
  "type": "Feature",
  "properties": {
    "iso:country":"DE",
    "sg:address":"Demexallee 1",
    "sg:city":"Elstal",
    "sg:postcode":"14627",
    "wof:name":"Demex Systembau Gmbh",
    "wof:placetype":"venue"
},
  "geometry": {"coordinates":[12.981481,52.527168],"type":"Point"}
}