{
  "type": "Feature",
  "properties": {
    "iso:country":"DE",
    "sg:address":"Grabenstr. 210",
    "sg:city":"Duisburg",
    "sg:phone":"+49 203/352088",
    "sg:postcode":"47057",
    "sg:province":"Nordrhein-Westfalen",
    "wof:name":"Br\u00fchmann Gmbh",
    "wof:placetype":"venue"
},
  "geometry": {"coordinates":[6.779731,51.420464],"type":"Point"}
}