{
  "type": "Feature",
  "properties": {
    "iso:country":"DE",
    "sg:address":"Rurstr. 14",
    "sg:city":"Kaarst",
    "sg:phone":"+49 4921/3168023",
    "sg:postcode":"41564",
    "sg:province":"Nordrhein-Westfalen",
    "wof:name":"Objecta Gmbh",
    "wof:placetype":"venue"
},
  "geometry": {"coordinates":[6.62647295,51.2192115784],"type":"Point"}
}