{
  "type": "Feature",
  "properties": {
    "iso:country":"DE",
    "sg:address":"Altenaer Str.",
    "sg:city":"L\u00fcdenscheid",
    "sg:postcode":"58507",
    "sg:province":"Nordrhein-Westfalen",
    "wof:name":"Vermietungsgesellschaft Berg Und W. Von Niessen",
    "wof:placetype":"venue"
},
  "geometry": {"coordinates":[7.6298699379,51.2370491028],"type":"Point"}
}