{
  "type": "Feature",
  "properties": {
    "iso:country":"DE",
    "sg:address":"Unter M\u00fchlenstra\u00dfe 10",
    "sg:city":"Leipzig",
    "sg:phone":"+49 341/4418162",
    "sg:postcode":"04178",
    "sg:province":"Sachsen",
    "wof:name":"Maus Kommunal - & Industrieservice Gmbh",
    "wof:placetype":"venue"
},
  "geometry": {"coordinates":[12.289936,51.359669],"type":"Point"}
}