{
  "type": "Feature",
  "properties": {
    "iso:country":"DE",
    "sg:address":"Br\u00fcckstr. 79",
    "sg:city":"Essen",
    "sg:postcode":"45239",
    "sg:province":"Nordrhein-Westfalen",
    "wof:name":"Kath. \u00f6ffentliche Bibliothek St. Ludgerus",
    "wof:placetype":"venue"
},
  "geometry": {"coordinates":[7.004179,51.388542],"type":"Point"}
}