{
  "type": "Feature",
  "properties": {
    "iso:country":"DE",
    "sg:address":"Ehrenbergstr. 39",
    "sg:city":"Tuttlingen",
    "sg:postcode":"78532",
    "sg:province":"Baden-W\u00fcrttemberg",
    "wof:name":"A. Handtke Medizintechnik Inh. Hermann Alfred Handtke",
    "wof:placetype":"venue"
},
  "geometry": {"coordinates":[8.810623,47.979759],"type":"Point"}
}