{
  "type": "Feature",
  "properties": {
    "iso:country":"DE",
    "sg:address":"Bahnhofstr. 28",
    "sg:city":"Neustadt",
    "sg:phone":"+49 9161/2243",
    "sg:postcode":"91413",
    "sg:province":"Bayern",
    "wof:name":"Gerhard Stocker",
    "wof:placetype":"venue"
},
  "geometry": {"coordinates":[9.039065,49.813923],"type":"Point"}
}