{
  "type": "Feature",
  "properties": {
    "iso:country":"DE",
    "sg:address":"Tannenweg 33",
    "sg:city":"Kappelrodeck",
    "sg:phone":"+49 7842/3308",
    "sg:postcode":"77876",
    "sg:province":"Baden-W\u00fcrttemberg",
    "wof:name":"T. Geiser",
    "wof:placetype":"venue"
},
  "geometry": {"coordinates":[8.1102218628,48.5841217041],"type":"Point"}
}