{
  "type": "Feature",
  "properties": {
    "iso:country":"DE",
    "sg:address":"Els\u00e4sser Str. 33",
    "sg:city":"Bonn",
    "sg:phone":"+49 228/951160",
    "sg:postcode":"53175",
    "sg:province":"Nordrhein-Westfalen",
    "wof:name":"Medienagentur Liebe Glaube Hoffnung Ges. F\u00fcr Visuelle",
    "wof:placetype":"venue"
},
  "geometry": {"coordinates":[7.1455612183,50.6899147034],"type":"Point"}
}