{
  "type": "Feature",
  "properties": {
    "iso:country":"DE",
    "sg:address":"Dorfstr. 16 a",
    "sg:city":"Bahro",
    "sg:postcode":"15898",
    "sg:province":"Brandenburg",
    "wof:name":"Blumen Und Floristik Gmbh & Co. Kg",
    "wof:placetype":"venue"
},
  "geometry": {"coordinates":[14.560281,52.054874],"type":"Point"}
}