{
  "type": "Feature",
  "properties": {
    "iso:country":"DE",
    "sg:address":"Dreifertstr. 1",
    "sg:city":"Cottbus",
    "sg:phone":"+49 355/700581",
    "sg:postcode":"03044",
    "sg:province":"Brandenburg",
    "wof:name":"Modul-ar Planer Und Ingenieurges. Mbh",
    "wof:placetype":"venue"
},
  "geometry": {"coordinates":[14.33351,51.763165],"type":"Point"}
}