{
  "type": "Feature",
  "properties": {
    "iso:country":"DE",
    "sg:address":"Wilhelm-Niessen-Str. 9",
    "sg:city":"M\u00f6nchengladbach",
    "sg:phone":"+49 2166/602059",
    "sg:postcode":"41199",
    "sg:province":"Nordrhein-Westfalen",
    "wof:name":"Herbert Coonen Versicherungsvermittlung Gmbh",
    "wof:placetype":"venue"
},
  "geometry": {"coordinates":[6.452943,51.1329],"type":"Point"}
}