{
  "type": "Feature",
  "properties": {
    "iso:country":"DE",
    "sg:address":"Bergedorfer Str. 51",
    "sg:city":"Geesthacht",
    "sg:phone":"+49 4152/75126",
    "sg:postcode":"21502",
    "sg:province":"Schleswig-Holstein",
    "wof:name":"Wolfgang Piel Versicherungsmakler E. K.",
    "wof:placetype":"venue"
},
  "geometry": {"coordinates":[10.3706769943,53.4353141785],"type":"Point"}
}