{
  "type": "Feature",
  "properties": {
    "iso:country":"DE",
    "sg:address":"Marienfelder Allee 146",
    "sg:city":"Berlin",
    "sg:phone":"+49 30/7224484",
    "sg:postcode":"12279",
    "sg:province":"Berlin",
    "wof:name":"M & C Sportswear Gmbh",
    "wof:placetype":"venue"
},
  "geometry": {"coordinates":[13.3627338409,52.4130821228],"type":"Point"}
}