{
  "type": "Feature",
  "properties": {
    "iso:country":"DE",
    "sg:address":"Bachstr. 7",
    "sg:city":"Salach",
    "sg:phone":"+49 7162/41152",
    "sg:postcode":"73084",
    "sg:province":"Baden-W\u00fcrttemberg",
    "wof:name":"Dieter Gaugele",
    "wof:placetype":"venue"
},
  "geometry": {"coordinates":[9.736079216,48.6967201233],"type":"Point"}
}