{
  "type": "Feature",
  "properties": {
    "iso:country":"DE",
    "sg:address":"Gerstenstr. 22",
    "sg:city":"Stein",
    "sg:phone":"+49 911/678009",
    "sg:postcode":"90547",
    "sg:province":"Bayern",
    "wof:name":"Horst B\u00fcrgermeister",
    "wof:placetype":"venue"
},
  "geometry": {"coordinates":[11.007188797,49.3992881775],"type":"Point"}
}