{
  "type": "Feature",
  "properties": {
    "iso:country":"DE",
    "sg:address":"Kurf\u00fcrstenstr. 12",
    "sg:city":"Hagen",
    "sg:phone":"+49 2331/77539",
    "sg:postcode":"58091",
    "sg:province":"Nordrhein-Westfalen",
    "wof:name":"Jonas Gmbh",
    "wof:placetype":"venue"
},
  "geometry": {"coordinates":[7.4925508499,51.3469161987],"type":"Point"}
}