{
  "type": "Feature",
  "properties": {
    "iso:country":"DE",
    "sg:address":"Heerstr. 4",
    "sg:city":"Vettwei\u00df",
    "sg:phone":"+49 2424/7100",
    "sg:postcode":"52391",
    "sg:province":"Nordrhein-Westfalen",
    "wof:name":"Elektroinstallationen Ernst M\u00fcllejans",
    "wof:placetype":"venue"
},
  "geometry": {"coordinates":[6.633511,50.771347],"type":"Point"}
}