{
  "type": "Feature",
  "properties": {
    "iso:country":"DE",
    "sg:address":"Am Flutgraben 30",
    "sg:city":"Schwanewede",
    "sg:phone":"+49 4296/227",
    "sg:postcode":"28790",
    "sg:province":"Niedersachsen",
    "wof:name":"Johann Brummerloh",
    "wof:placetype":"venue"
},
  "geometry": {"coordinates":[8.541957,53.284973],"type":"Point"}
}