{
  "type": "Feature",
  "properties": {
    "iso:country":"DE",
    "sg:address":"Eduard-M\u00f6rike-Str. 9",
    "sg:city":"Bissingen",
    "sg:phone":"+49 7023/2301",
    "sg:postcode":"73266",
    "sg:province":"Baden-W\u00fcrttemberg",
    "wof:name":"Christian Schmid",
    "wof:placetype":"venue"
},
  "geometry": {"coordinates":[9.5107412338,48.5780639648],"type":"Point"}
}