{
  "type": "Feature",
  "properties": {
    "iso:country":"DE",
    "sg:address":"Birkenallee 2-4",
    "sg:city":"Lensahn",
    "sg:postcode":"23738",
    "sg:province":"Schleswig-Holstein",
    "wof:name":"Autovermietung Baltic Rent",
    "wof:placetype":"venue"
},
  "geometry": {"coordinates":[10.880843,54.208271],"type":"Point"}
}