{
  "type": "Feature",
  "properties": {
    "iso:country":"DE",
    "sg:address":"Crimmitschauer Str. 104",
    "sg:city":"Zwickau",
    "sg:phone":"+49 375/527508",
    "sg:postcode":"08058",
    "sg:province":"Sachsen",
    "wof:name":"Ralf Schwartz",
    "wof:placetype":"venue"
},
  "geometry": {"coordinates":[12.4559602737,50.7396202087],"type":"Point"}
}