{
  "type": "Feature",
  "properties": {
    "iso:country":"DE",
    "sg:address":"Hangweg 5",
    "sg:city":"St. Andreasberg",
    "sg:phone":"+49 5582/797",
    "sg:postcode":"37444",
    "sg:province":"Niedersachsen",
    "wof:name":"Haus Clementine",
    "wof:placetype":"venue"
},
  "geometry": {"coordinates":[10.5110177994,51.7136764526],"type":"Point"}
}