{
  "type": "Feature",
  "properties": {
    "iso:country":"DE",
    "sg:address":"Humboldtstr. 46",
    "sg:city":"M\u00fclheim",
    "sg:phone":"+49 208/490521",
    "sg:postcode":"45472",
    "sg:province":"Nordrhein-Westfalen",
    "wof:name":"M. Eulgem & U. Jungen",
    "wof:placetype":"venue"
},
  "geometry": {"coordinates":[6.9573078156,51.4356307983],"type":"Point"}
}