{
  "type": "Feature",
  "properties": {
    "iso:country":"DE",
    "sg:address":"Bahnhofstr. 116",
    "sg:city":"M\u00fccke",
    "sg:phone":"+49 6400/8191",
    "sg:postcode":"35325",
    "sg:province":"Hessen",
    "wof:name":"Landhotel G\u00e4rtner",
    "wof:placetype":"venue"
},
  "geometry": {"coordinates":[9.0267457962,50.6149978638],"type":"Point"}
}