{
  "type": "Feature",
  "properties": {
    "iso:country":"DE",
    "sg:address":"Barbarossastr. 34",
    "sg:city":"Rodenbach",
    "sg:phone":"+49 6184/51010",
    "sg:postcode":"63517",
    "sg:province":"Hessen",
    "wof:name":"Wolfram Steuernagel Anlageberater",
    "wof:placetype":"venue"
},
  "geometry": {"coordinates":[9.0600204468,50.1348495483],"type":"Point"}
}