{
  "type": "Feature",
  "properties": {
    "iso:country":"DE",
    "sg:address":"Kennerweg 13",
    "sg:city":"Konstanz",
    "sg:phone":"+49 7531/97164",
    "sg:postcode":"78467",
    "sg:province":"Baden-W\u00fcrttemberg",
    "wof:name":"Sch\u00e4fer Immobilien- Und Bautr\u00e4ger Gmbh",
    "wof:placetype":"venue"
},
  "geometry": {"coordinates":[9.146974,47.692741],"type":"Point"}
}