{
  "type": "Feature",
  "properties": {
    "iso:country":"DE",
    "sg:address":"Am Werkhaus 18",
    "sg:city":"Weitnau",
    "sg:phone":"+49 8375/8333",
    "sg:postcode":"87480",
    "sg:province":"Bayern",
    "wof:name":"Simo-ger\u00c4tebau Haslinger Kg",
    "wof:placetype":"venue"
},
  "geometry": {"coordinates":[10.0902719498,47.6595611572],"type":"Point"}
}