{
  "type": "Feature",
  "properties": {
    "iso:country":"DE",
    "sg:address":"Lobuschstr. 24",
    "sg:city":"Hamburg",
    "sg:phone":"+49 40/396457",
    "sg:postcode":"22765",
    "sg:province":"Hamburg",
    "wof:name":"Gastst\u00e4tte A. Mohammadi",
    "wof:placetype":"venue"
},
  "geometry": {"coordinates":[9.9330587387,53.5500640869],"type":"Point"}
}