{
  "type": "Feature",
  "properties": {
    "iso:country":"DE",
    "sg:address":"K\u00f6nigstr. 21",
    "sg:city":"Lehrte",
    "sg:phone":"+49 5132/2254",
    "sg:postcode":"31275",
    "sg:province":"Niedersachsen",
    "wof:name":"Hatesuer Reifenfachhandel Gmbh",
    "wof:placetype":"venue"
},
  "geometry": {"coordinates":[9.9764318466,52.3706626892],"type":"Point"}
}