{
  "type": "Feature",
  "properties": {
    "iso:country":"DE",
    "sg:address":"Hufelandstr.",
    "sg:city":"Wolgast",
    "sg:phone":"+49 3836/204519",
    "sg:postcode":"17438",
    "sg:province":"Mecklenburg-Vorpommern",
    "wof:name":"A. Sch\u00e4tzchen",
    "wof:placetype":"venue"
},
  "geometry": {"coordinates":[13.761058,54.05262],"type":"Point"}
}