{
  "type": "Feature",
  "properties": {
    "iso:country":"DE",
    "sg:address":"Charlottenstrasse 5",
    "sg:city":"Naumburg(Saale)",
    "sg:phone":"+49 3445",
    "sg:postcode":"06618",
    "sg:province":"Sachsen-Anhalt",
    "wof:name":"Ulrike Cink Rechtsanw\u00e4ltin",
    "wof:placetype":"venue"
},
  "geometry": {"coordinates":[11.81213,51.145493],"type":"Point"}
}