{
  "type": "Feature",
  "properties": {
    "iso:country":"DE",
    "sg:address":"Amselweg 16",
    "sg:city":"Bernkastel-Kues",
    "sg:phone":"+49 6531/2894",
    "sg:postcode":"54470",
    "sg:province":"Rheinland-Pfalz",
    "wof:name":"Helga Wolff Steuerberater",
    "wof:placetype":"venue"
},
  "geometry": {"coordinates":[7.0498828888,49.9224853516],"type":"Point"}
}