{
  "type": "Feature",
  "properties": {
    "iso:country":"DE",
    "sg:address":"Auf der Hude 72",
    "sg:city":"L\u00fcneburg",
    "sg:phone":"+49 4131/35879",
    "sg:postcode":"21339",
    "sg:province":"Niedersachsen",
    "wof:name":"Gastst\u00e4tte Garage",
    "wof:placetype":"venue"
},
  "geometry": {"coordinates":[10.4140262604,53.2595176697],"type":"Point"}
}