{
  "type": "Feature",
  "properties": {
    "iso:country":"DE",
    "sg:address":"Heilbronner Stra\u00dfe 51",
    "sg:city":"Esslingen",
    "sg:phone":"+49 711/9392250",
    "sg:postcode":"73728",
    "sg:province":"Baden-W\u00fcrttemberg",
    "wof:name":"Bart Und Timm Gmbh & Co.",
    "wof:placetype":"venue"
},
  "geometry": {"coordinates":[9.3199272156,48.7347602844],"type":"Point"}
}