{
  "type": "Feature",
  "properties": {
    "iso:country":"DE",
    "sg:address":"An der Windm\u00fchle 6",
    "sg:city":"Essen",
    "sg:phone":"+49 201/255076",
    "sg:postcode":"45289",
    "sg:province":"Nordrhein-Westfalen",
    "wof:name":"Plamont Ingenieur- Gemeinschaft Gmbh",
    "wof:placetype":"venue"
},
  "geometry": {"coordinates":[7.0978050232,51.4183883667],"type":"Point"}
}