{
  "type": "Feature",
  "properties": {
    "iso:country":"DE",
    "sg:address":"Bahnhofstr. 8",
    "sg:city":"Rheine",
    "sg:phone":"+49 5971/4040",
    "sg:postcode":"48431",
    "sg:province":"Nordrhein-Westfalen",
    "wof:name":"Rheiner Anzeiger",
    "wof:placetype":"venue"
},
  "geometry": {"coordinates":[7.4363598824,52.2776794434],"type":"Point"}
}