{
  "type": "Feature",
  "properties": {
    "iso:country":"DE",
    "sg:address":"Forsthausstr. 74",
    "sg:city":"F\u00fcrth",
    "sg:phone":"+49 911/7234346",
    "sg:postcode":"90768",
    "sg:province":"Bayern",
    "wof:name":"Dtti Diving Traveling & Trading",
    "wof:placetype":"venue"
},
  "geometry": {"coordinates":[10.965487,49.464241],"type":"Point"}
}