{
  "type": "Feature",
  "properties": {
    "iso:country":"DE",
    "sg:address":"Weinbergweg 100",
    "sg:city":"Bad Muskau",
    "sg:phone":"+49 35771/60233",
    "sg:postcode":"02953",
    "sg:province":"Sachsen",
    "wof:name":"Joachim Riedel",
    "wof:placetype":"venue"
},
  "geometry": {"coordinates":[14.704857,51.537071],"type":"Point"}
}