{
  "type": "Feature",
  "properties": {
    "iso:country":"DE",
    "sg:address":"Karl-Marx-Str. 81",
    "sg:city":"Neuruppin",
    "sg:phone":"+49 3391/45030",
    "sg:postcode":"16816",
    "sg:province":"Brandenburg",
    "wof:name":"Asb-gesellschaft F\u00fcr Soziale Einrichtungen Mbh",
    "wof:placetype":"venue"
},
  "geometry": {"coordinates":[12.806306,52.9254],"type":"Point"}
}