{
  "type": "Feature",
  "properties": {
    "iso:country":"DE",
    "sg:address":"Oststr 3",
    "sg:city":"Norderstedt",
    "sg:phone":"+49 40/53530707",
    "sg:postcode":"22844",
    "sg:province":"Schleswig-Holstein",
    "wof:name":"Spedition Hans Davids Gmbh",
    "wof:placetype":"venue"
},
  "geometry": {"coordinates":[10.0238924026,53.7221794128],"type":"Point"}
}