{
  "type": "Feature",
  "properties": {
    "iso:country":"DE",
    "sg:address":"Westersoder Schulstr. 8",
    "sg:city":"Hemmoor",
    "sg:phone":"+49 4771/7440",
    "sg:postcode":"21745",
    "sg:province":"Niedersachsen",
    "wof:name":"Helmut Eggers",
    "wof:placetype":"venue"
},
  "geometry": {"coordinates":[9.112087,53.697758],"type":"Point"}
}