{
  "type": "Feature",
  "properties": {
    "iso:country":"DE",
    "sg:address":"Badstr. 1",
    "sg:city":"Boll",
    "sg:phone":"+49 7164/5095",
    "sg:postcode":"73087",
    "sg:province":"Baden-W\u00fcrttemberg",
    "wof:name":"Bistro Monopol",
    "wof:placetype":"venue"
},
  "geometry": {"coordinates":[9.6160879135,48.6389465332],"type":"Point"}
}