{
  "type": "Feature",
  "properties": {
    "iso:country":"DE",
    "sg:address":"Im Seitenbach 4",
    "sg:city":"Waldenbuch",
    "sg:phone":"+49 7157",
    "sg:postcode":"71111",
    "sg:province":"Baden-W\u00fcrttemberg",
    "wof:name":"Cozimil",
    "wof:placetype":"venue"
},
  "geometry": {"coordinates":[9.1278858185,48.6357078552],"type":"Point"}
}