{
  "type": "Feature",
  "properties": {
    "iso:country":"DE",
    "sg:address":"Ludwigstr. 37",
    "sg:city":"M\u00fcnchberg",
    "sg:phone":"+49 9251/7271",
    "sg:postcode":"95213",
    "sg:province":"Bayern",
    "wof:name":"Gerhard M\u00f6ckel",
    "wof:placetype":"venue"
},
  "geometry": {"coordinates":[11.7889900208,50.1938171387],"type":"Point"}
}