{
  "type": "Feature",
  "properties": {
    "iso:country":"DE",
    "sg:address":"Buchentorstr. 17",
    "sg:city":"Lienen",
    "sg:phone":"+49 4954/84562",
    "sg:postcode":"49536",
    "sg:province":"Nordrhein-Westfalen",
    "wof:name":"Volksbank Kattenvenne Eg",
    "wof:placetype":"venue"
},
  "geometry": {"coordinates":[7.865128,52.112305],"type":"Point"}
}