{
  "type": "Feature",
  "properties": {
    "iso:country":"DE",
    "sg:address":"Katharinenstr. 18",
    "sg:city":"Gotha",
    "sg:phone":"+49 3621/704357",
    "sg:postcode":"99867",
    "sg:province":"Th\u00fcringen",
    "wof:name":"K. Gundermann",
    "wof:placetype":"venue"
},
  "geometry": {"coordinates":[10.697172,50.937977],"type":"Point"}
}