{
  "type": "Feature",
  "properties": {
    "iso:country":"DE",
    "sg:address":"Am Wolfrum 2",
    "sg:city":"Gladenbach",
    "sg:phone":"+49 6462/2977",
    "sg:postcode":"35075",
    "sg:province":"Hessen",
    "wof:name":"Walter Wagner & S\u00f6hne",
    "wof:placetype":"venue"
},
  "geometry": {"coordinates":[8.5719356537,50.7563438416],"type":"Point"}
}