{
  "type": "Feature",
  "properties": {
    "iso:country":"DE",
    "sg:address":"Franz-Mehring-Str. 10",
    "sg:city":"S\u00f6mmerda",
    "sg:phone":"+49 3634/614450",
    "sg:postcode":"99610",
    "sg:province":"Th\u00fcringen",
    "wof:name":"Ulrich Weidner Patentanwalt",
    "wof:placetype":"venue"
},
  "geometry": {"coordinates":[11.1179380417,51.1679801941],"type":"Point"}
}