{
  "type": "Feature",
  "properties": {
    "iso:country":"DE",
    "sg:address":"F\u00fcrstenweg 9",
    "sg:city":"Freilassing",
    "sg:phone":"+49 8654/66944",
    "sg:postcode":"83395",
    "sg:province":"Bayern",
    "wof:name":"Electronic Handel Peter Negele",
    "wof:placetype":"venue"
},
  "geometry": {"coordinates":[12.9802284241,47.8387641907],"type":"Point"}
}