{
  "type": "Feature",
  "properties": {
    "iso:country":"DE",
    "sg:address":"In der Helle 7",
    "sg:city":"Kierspe",
    "sg:phone":"+49 2359/6630",
    "sg:postcode":"58566",
    "sg:province":"Nordrhein-Westfalen",
    "wof:name":"Arnold Knipping Gmbh",
    "wof:placetype":"venue"
},
  "geometry": {"coordinates":[7.589165,51.121571],"type":"Point"}
}