{
  "type": "Feature",
  "properties": {
    "iso:country":"DE",
    "sg:address":"Wurmbergstr. 6",
    "sg:city":"Braunlage",
    "sg:phone":"+49 5520/8273",
    "sg:postcode":"38700",
    "sg:province":"Niedersachsen",
    "wof:name":"Ruth Kuhfu\u00df",
    "wof:placetype":"venue"
},
  "geometry": {"coordinates":[10.6137180328,51.7291526794],"type":"Point"}
}