{
  "type": "Feature",
  "properties": {
    "iso:country":"DE",
    "sg:address":"Helenenstr. 7",
    "sg:city":"V\u00f6lklingen",
    "sg:phone":"+49 6898/370777",
    "sg:postcode":"66333",
    "sg:province":"Saarland",
    "wof:name":"Versicherungsb\u00fcro Jost",
    "wof:placetype":"venue"
},
  "geometry": {"coordinates":[6.8736867905,49.2362098694],"type":"Point"}
}