{
  "type": "Feature",
  "properties": {
    "iso:country":"DE",
    "sg:address":"Lagerhausweg 7",
    "sg:city":"Pocking",
    "sg:phone":"+49 8531/7300",
    "sg:postcode":"94060",
    "sg:province":"Bayern",
    "wof:name":"Stockbauer St\u00fcberl",
    "wof:placetype":"venue"
},
  "geometry": {"coordinates":[13.3097362518,48.4050064087],"type":"Point"}
}