{
  "type": "Feature",
  "properties": {
    "iso:country":"DE",
    "sg:address":"Schlo\u00dfstr. 112",
    "sg:city":"Rheinberg",
    "sg:phone":"+49 2843/860112",
    "sg:postcode":"47495",
    "sg:province":"Nordrhein-Westfalen",
    "wof:name":"Kie\u00dfling Gmbh",
    "wof:placetype":"venue"
},
  "geometry": {"coordinates":[6.5796661377,51.5729560852],"type":"Point"}
}