{
  "type": "Feature",
  "properties": {
    "iso:country":"DE",
    "sg:address":"Pahlkestr. 74",
    "sg:city":"Wuppertal",
    "sg:phone":"+49 202/713869",
    "sg:postcode":"42115",
    "sg:province":"Nordrhein-Westfalen",
    "wof:name":"Carsten Seibold",
    "wof:placetype":"venue"
},
  "geometry": {"coordinates":[7.094947,51.261208],"type":"Point"}
}