{
  "type": "Feature",
  "properties": {
    "iso:country":"DE",
    "sg:address":"Friedrich-K\u00f6nig-Str. 7",
    "sg:city":"Suhl",
    "sg:postcode":"98527",
    "sg:province":"Th\u00fcringen",
    "wof:name":"R. T. S.-reisen",
    "wof:placetype":"venue"
},
  "geometry": {"coordinates":[10.6889028549,50.6100006104],"type":"Point"}
}