{
  "type": "Feature",
  "properties": {
    "iso:country":"DE",
    "sg:address":"64354",
    "sg:city":"Reinheim",
    "sg:phone":"+49 6162/3357",
    "sg:postcode":"64354",
    "sg:province":"Hessen",
    "wof:name":"Deutsche Bahn Ag",
    "wof:placetype":"venue"
},
  "geometry": {"coordinates":[8.8250198364,49.8260688782],"type":"Point"}
}