{
  "type": "Feature",
  "properties": {
    "iso:country":"DE",
    "sg:address":"Bergstr. 13",
    "sg:city":"Mertesdorf",
    "sg:phone":"+49 651/57686",
    "sg:postcode":"54318",
    "sg:province":"Rheinland-Pfalz",
    "wof:name":"Hubert Kirschner",
    "wof:placetype":"venue"
},
  "geometry": {"coordinates":[6.7354941368,49.7695121765],"type":"Point"}
}