{
  "type": "Feature",
  "properties": {
    "iso:country":"DE",
    "sg:address":"St.-Andreas-Str. 5",
    "sg:city":"P\u00f6lich",
    "sg:postcode":"54340",
    "sg:province":"Rheinland-Pfalz",
    "wof:name":"Katholisches Pfarramt St. Andreas",
    "wof:placetype":"venue"
},
  "geometry": {"coordinates":[6.8487949371,49.7975692749],"type":"Point"}
}