{
  "type": "Feature",
  "properties": {
    "iso:country":"DE",
    "sg:address":"Borsigstr. 17b",
    "sg:city":"Velbert",
    "sg:phone":"+49 2051/28790",
    "sg:postcode":"42551",
    "sg:province":"Nordrhein-Westfalen",
    "wof:name":"Reschke & Seipp Sondermaschinen Gmbh & Co.",
    "wof:placetype":"venue"
},
  "geometry": {"coordinates":[7.065849,51.346634],"type":"Point"}
}