{
  "type": "Feature",
  "properties": {
    "iso:country":"DE",
    "sg:address":"Friedrich-Ebert-Str. 40",
    "sg:city":"Helmbrechts",
    "sg:phone":"+49 9252/6574",
    "sg:postcode":"95233",
    "sg:province":"Bayern",
    "wof:name":"Horst Eckstein Holzbildhauer",
    "wof:placetype":"venue"
},
  "geometry": {"coordinates":[11.719095,50.237354],"type":"Point"}
}