{
  "type": "Feature",
  "properties": {
    "iso:country":"DE",
    "sg:address":"Kirchgasse 60",
    "sg:city":"Ramsla",
    "sg:postcode":"99439",
    "sg:province":"Th\u00fcringen",
    "wof:name":"Rudi K\u00fchn",
    "wof:placetype":"venue"
},
  "geometry": {"coordinates":[11.286577,51.051563],"type":"Point"}
}