{
  "type": "Feature",
  "properties": {
    "iso:country":"DE",
    "sg:address":"Karlsruher Str. 25",
    "sg:city":"Leipzig",
    "sg:phone":"+49 341/4115602",
    "sg:postcode":"04209",
    "sg:province":"Sachsen",
    "wof:name":"Heike Kresse",
    "wof:placetype":"venue"
},
  "geometry": {"coordinates":[12.2824373245,51.3149528503],"type":"Point"}
}