{
  "type": "Feature",
  "properties": {
    "iso:country":"DE",
    "sg:address":"Adam-M\u00fcller-Str. 11",
    "sg:city":"Pirmasens",
    "sg:phone":"+49 6331/92865",
    "sg:postcode":"66954",
    "sg:province":"Rheinland-Pfalz",
    "wof:name":"J\u00fcrgen Zinnecker",
    "wof:placetype":"venue"
},
  "geometry": {"coordinates":[7.599383,49.199127],"type":"Point"}
}