{
  "type": "Feature",
  "properties": {
    "iso:country":"DE",
    "sg:address":"Remscheider Str. 17 B",
    "sg:city":"Solingen",
    "sg:phone":"+49 4921/242091",
    "sg:postcode":"42659",
    "sg:province":"Nordrhein-Westfalen",
    "wof:name":"Herm. H\u00d6lterhoff Gmbh & Co",
    "wof:placetype":"venue"
},
  "geometry": {"coordinates":[7.112647,51.163338],"type":"Point"}
}