{
  "type": "Feature",
  "properties": {
    "iso:country":"DE",
    "sg:address":"Wassermannstr. 29",
    "sg:city":"Osnabr\u00fcck",
    "sg:phone":"+49 541/350690",
    "sg:postcode":"49074",
    "sg:province":"Niedersachsen",
    "wof:name":"Helmut Fleddermann Ingenieur",
    "wof:placetype":"venue"
},
  "geometry": {"coordinates":[8.0530700684,52.2692489624],"type":"Point"}
}