{
  "type": "Feature",
  "properties": {
    "iso:country":"DE",
    "sg:address":"Hauptstr. 5",
    "sg:city":"Steinheim",
    "sg:phone":"+49 7329/255",
    "sg:postcode":"89555",
    "sg:province":"Baden-W\u00fcrttemberg",
    "wof:name":"Karl Wittlinger",
    "wof:placetype":"venue"
},
  "geometry": {"coordinates":[10.0660848618,48.6923904419],"type":"Point"}
}