{
  "type": "Feature",
  "properties": {
    "iso:country":"DE",
    "sg:address":"Trinkbornstr. 31",
    "sg:city":"Darmstadt",
    "sg:phone":"+49 6151/82227",
    "sg:postcode":"64291",
    "sg:province":"Hessen",
    "wof:name":"Gerd Schmidt",
    "wof:placetype":"venue"
},
  "geometry": {"coordinates":[8.6442155838,49.9293937683],"type":"Point"}
}