{
  "type": "Feature",
  "properties": {
    "iso:country":"DE",
    "sg:address":"Domaxen 35",
    "sg:city":"Georgsmarienh\u00fctte",
    "sg:phone":"+49 5401/45801",
    "sg:postcode":"49124",
    "sg:province":"Niedersachsen",
    "wof:name":"E-team Elektro- Installation Gmbh",
    "wof:placetype":"venue"
},
  "geometry": {"coordinates":[8.058986,52.198257],"type":"Point"}
}