{
  "type": "Feature",
  "properties": {
    "iso:country":"DE",
    "sg:address":"St. Martin Strasse 21",
    "sg:city":"D\u00fcngenheim",
    "sg:phone":"+49 2653/910378",
    "sg:postcode":"56761",
    "sg:province":"Rheinland-Pfalz",
    "wof:name":"Informationen \u00fcber Regenerative Energiesysteme, Fahttp://w",
    "wof:placetype":"venue"
},
  "geometry": {"coordinates":[7.160627,50.263645],"type":"Point"}
}