{
  "type": "Feature",
  "properties": {
    "iso:country":"DE",
    "sg:address":"Berliner Str. 21",
    "sg:city":"Finsterwalde",
    "sg:postcode":"03238",
    "sg:province":"Brandenburg",
    "wof:name":"Hard And Soft Systems",
    "wof:placetype":"venue"
},
  "geometry": {"coordinates":[13.7083473206,51.6344985962],"type":"Point"}
}