{
  "type": "Feature",
  "properties": {
    "iso:country":"DE",
    "sg:address":"Waldstr. 3",
    "sg:city":"Vellmar",
    "sg:phone":"+49 561/821046",
    "sg:postcode":"34246",
    "sg:province":"Hessen",
    "wof:name":"Thielke Gmbh",
    "wof:placetype":"venue"
},
  "geometry": {"coordinates":[9.46895504,51.3625984192],"type":"Point"}
}