{
  "type": "Feature",
  "properties": {
    "iso:country":"DE",
    "sg:address":"Bl\u00fcmnerstr.1",
    "sg:city":"Leipzig",
    "sg:phone":"+49 1212510321848",
    "sg:postcode":"04229",
    "sg:province":"Sachsen",
    "wof:name":"Yourheadstuff",
    "wof:placetype":"venue"
},
  "geometry": {"coordinates":[12.342201,51.322872],"type":"Point"}
}