{
  "type": "Feature",
  "properties": {
    "iso:country":"DE",
    "sg:address":"H\u00fcttenstr. 49",
    "sg:city":"Gelsenkirchen",
    "sg:phone":"+49 209/208554",
    "sg:postcode":"45888",
    "sg:province":"Nordrhein-Westfalen",
    "wof:name":"Holz In Form Annette Schut & Bettina Mische",
    "wof:placetype":"venue"
},
  "geometry": {"coordinates":[7.108389,51.511925],"type":"Point"}
}