{
  "type": "Feature",
  "properties": {
    "iso:country":"DE",
    "sg:address":"Mainzer Str. 41",
    "sg:city":"Gernsheim",
    "sg:phone":"+49 4962/58120",
    "sg:postcode":"64579",
    "sg:province":"Hessen",
    "wof:name":"Merck Kgaa",
    "wof:placetype":"venue"
},
  "geometry": {"coordinates":[8.482559,49.76305],"type":"Point"}
}