{
  "type": "Feature",
  "properties": {
    "iso:country":"DE",
    "sg:address":"Schottenstr. 11",
    "sg:city":"Erfurt",
    "sg:postcode":"99084",
    "sg:province":"Th\u00fcringen",
    "wof:name":"Katholisches Pfarramt St. Nikolaus Und Jakobus",
    "wof:placetype":"venue"
},
  "geometry": {"coordinates":[11.0326356888,50.9795341492],"type":"Point"}
}