{
  "type": "Feature",
  "properties": {
    "iso:country":"DE",
    "sg:address":"Oeltzschnerstr. 10",
    "sg:city":"Merseburg",
    "sg:phone":"+49 3461/502328",
    "sg:postcode":"06217",
    "sg:province":"Sachsen-Anhalt",
    "wof:name":"Dietrich Immobilienmakler",
    "wof:placetype":"venue"
},
  "geometry": {"coordinates":[11.9741287231,51.3522186279],"type":"Point"}
}