{
  "type": "Feature",
  "properties": {
    "iso:country":"DE",
    "sg:address":"Lerchenweg 2",
    "sg:city":"Breddenberg",
    "sg:phone":"+49 5954/773",
    "sg:postcode":"26897",
    "sg:province":"Niedersachsen",
    "wof:name":"Fliesen Sch\u00fcr Gmbh",
    "wof:placetype":"venue"
},
  "geometry": {"coordinates":[7.6037549973,52.9601593018],"type":"Point"}
}