{
  "type": "Feature",
  "properties": {
    "iso:country":"DE",
    "sg:address":"Hasetorwall 17",
    "sg:city":"Osnabr\u00fcck",
    "sg:phone":"+49 541/962040",
    "sg:postcode":"49076",
    "sg:province":"Niedersachsen",
    "wof:name":"Victoria Versicherung Ag",
    "wof:placetype":"venue"
},
  "geometry": {"coordinates":[8.0414991379,52.2811470032],"type":"Point"}
}