{
  "type": "Feature",
  "properties": {
    "iso:country":"DE",
    "sg:address":"Hauptstr. 6",
    "sg:city":"Deinstedt",
    "sg:phone":"+49 4762/643",
    "sg:postcode":"27446",
    "sg:province":"Niedersachsen",
    "wof:name":"Friedrich Viebrock",
    "wof:placetype":"venue"
},
  "geometry": {"coordinates":[9.269088,53.42815],"type":"Point"}
}