{
  "type": "Feature",
  "properties": {
    "iso:country":"DE",
    "sg:address":"Hauptstr. 63",
    "sg:city":"Adelmannsfelden",
    "sg:phone":"+49 7963/511",
    "sg:postcode":"73486",
    "sg:province":"Baden-W\u00fcrttemberg",
    "wof:name":"Christoph Malisi Architekt",
    "wof:placetype":"venue"
},
  "geometry": {"coordinates":[10.005117,48.95483],"type":"Point"}
}