{
  "type": "Feature",
  "properties": {
    "iso:country":"DE",
    "sg:address":"Emsstr. 15",
    "sg:city":"Rheine",
    "sg:phone":"+49 5971/13213",
    "sg:postcode":"48431",
    "sg:province":"Nordrhein-Westfalen",
    "wof:name":"Albrecht Und Wasielewski Rechtsanw\u00e4lte",
    "wof:placetype":"venue"
},
  "geometry": {"coordinates":[7.4392762184,52.2783508301],"type":"Point"}
}