{
  "type": "Feature",
  "properties": {
    "iso:country":"DE",
    "sg:address":"Husener Str. 60",
    "sg:city":"Paderborn",
    "sg:phone":"+49 5251/71943",
    "sg:postcode":"33098",
    "sg:province":"Nordrhein-Westfalen",
    "wof:name":"Udo Sander",
    "wof:placetype":"venue"
},
  "geometry": {"coordinates":[8.76794,51.700638],"type":"Point"}
}