{
  "type": "Feature",
  "properties": {
    "iso:country":"DE",
    "sg:address":"Anzengruberstr. 8",
    "sg:city":"Neumarkt",
    "sg:phone":"+49 9181/43931",
    "sg:postcode":"92318",
    "sg:province":"Bayern",
    "wof:name":"Rupert G\u00e4rtner",
    "wof:placetype":"venue"
},
  "geometry": {"coordinates":[11.476358,49.292004],"type":"Point"}
}