{
  "type": "Feature",
  "properties": {
    "iso:country":"DE",
    "sg:address":"Moosstr. 3",
    "sg:city":"Forstinning",
    "sg:phone":"+49 8121/40218",
    "sg:postcode":"85661",
    "sg:province":"Bayern",
    "wof:name":"Peter Stimmer",
    "wof:placetype":"venue"
},
  "geometry": {"coordinates":[11.907625,48.166897],"type":"Point"}
}