{
  "type": "Feature",
  "properties": {
    "iso:country":"DE",
    "sg:address":"Postfach 16",
    "sg:city":"Hallbergmoos",
    "sg:phone":"+49 811/13330",
    "sg:postcode":"85396",
    "sg:province":"Bayern",
    "wof:name":"Vogab Elektronik Gmbh",
    "wof:placetype":"venue"
},
  "geometry": {"coordinates":[11.7451448441,48.3178749084],"type":"Point"}
}