{
  "type": "Feature",
  "properties": {
    "iso:country":"DE",
    "sg:address":"Ruhesteinstr. 41",
    "sg:city":"Ottenh\u00f6fen",
    "sg:phone":"+49 4978/429470",
    "sg:postcode":"77883",
    "sg:province":"Baden-W\u00fcrttemberg",
    "wof:name":"Wilhelm Bohnert Gmbh & Co Kg",
    "wof:placetype":"venue"
},
  "geometry": {"coordinates":[8.1482391357,48.5676345825],"type":"Point"}
}