{
  "type": "Feature",
  "properties": {
    "iso:country":"DE",
    "sg:address":"Lindeistr. 26",
    "sg:city":"Gernrode",
    "sg:phone":"+49 36076/44123",
    "sg:postcode":"37339",
    "sg:province":"Th\u00fcringen",
    "wof:name":"L. Hentrich",
    "wof:placetype":"venue"
},
  "geometry": {"coordinates":[10.411081,51.395477],"type":"Point"}
}