{
  "type": "Feature",
  "properties": {
    "iso:country":"DE",
    "sg:address":"Wilhelmstr. 75",
    "sg:city":"Eislingen",
    "sg:postcode":"73054",
    "sg:province":"Baden-W\u00fcrttemberg",
    "wof:name":"Sport Textildruck Gmbh",
    "wof:placetype":"venue"
},
  "geometry": {"coordinates":[9.7165184021,48.6925163269],"type":"Point"}
}