{
  "type": "Feature",
  "properties": {
    "iso:country":"DE",
    "sg:address":"Nadorster Str. 84",
    "sg:city":"Oldenburg",
    "sg:phone":"+49 441/82881",
    "sg:postcode":"26123",
    "sg:province":"Niedersachsen",
    "wof:name":"Joh. Voss Gmbh",
    "wof:placetype":"venue"
},
  "geometry": {"coordinates":[8.2182273865,53.1523971558],"type":"Point"}
}