{
  "type": "Feature",
  "properties": {
    "iso:country":"DE",
    "sg:address":"Moosbeerweg 10",
    "sg:city":"Bad Zwischenahn",
    "sg:phone":"+49 4403/59301",
    "sg:postcode":"26160",
    "sg:province":"Niedersachsen",
    "wof:name":"Ferienwohnung",
    "wof:placetype":"venue"
},
  "geometry": {"coordinates":[8.0200920105,53.1763725281],"type":"Point"}
}