{
  "type": "Feature",
  "properties": {
    "iso:country":"DE",
    "sg:address":"Am Holzweg 26",
    "sg:city":"Kriftel",
    "sg:phone":"+49 6192/974100",
    "sg:postcode":"65830",
    "sg:province":"Hessen",
    "wof:name":"Lsg Lufthansa Service Holding Ag",
    "wof:placetype":"venue"
},
  "geometry": {"coordinates":[8.4785852432,50.0792541504],"type":"Point"}
}