{
  "type": "Feature",
  "properties": {
    "iso:country":"DE",
    "sg:address":"Heslacher Wand 10",
    "sg:city":"Stuttgart",
    "sg:phone":"+49 711/608720",
    "sg:postcode":"70199",
    "sg:province":"Baden-W\u00fcrttemberg",
    "wof:name":"Reinhard Schulz Verlagsvertreter",
    "wof:placetype":"venue"
},
  "geometry": {"coordinates":[9.143605,48.757072],"type":"Point"}
}