{
  "type": "Feature",
  "properties": {
    "iso:country":"DE",
    "sg:address":"48268",
    "sg:city":"Greven",
    "sg:phone":"+49 2571/91157",
    "sg:postcode":"48268",
    "sg:province":"Nordrhein-Westfalen",
    "wof:name":"Flughafenrestaurant",
    "wof:placetype":"venue"
},
  "geometry": {"coordinates":[7.6393399239,52.0921592712],"type":"Point"}
}