{
  "type": "Feature",
  "properties": {
    "iso:country":"DE",
    "sg:address":"Schwarzburger Str. 135",
    "sg:city":"Neuhaus",
    "sg:phone":"+49 3679/722859",
    "sg:postcode":"98724",
    "sg:province":"Th\u00fcringen",
    "wof:name":"Dietrich B\u00fcttner",
    "wof:placetype":"venue"
},
  "geometry": {"coordinates":[11.143597,50.51923],"type":"Point"}
}