{
  "type": "Feature",
  "properties": {
    "iso:country":"DE",
    "sg:address":"Schlo\u00dfwiesenstr. 4 a",
    "sg:city":"Westerburg",
    "sg:phone":"+49 2663/8609",
    "sg:postcode":"56457",
    "sg:province":"Rheinland-Pfalz",
    "wof:name":"Armin Schmidt",
    "wof:placetype":"venue"
},
  "geometry": {"coordinates":[7.9686660767,50.5572662354],"type":"Point"}
}