{
  "type": "Feature",
  "properties": {
    "iso:country":"DE",
    "sg:address":"Bergstr. 41",
    "sg:city":"Recklinghausen",
    "sg:phone":"+49 2361/98001",
    "sg:postcode":"45665",
    "sg:province":"Nordrhein-Westfalen",
    "wof:name":"Bartoszak-estrich- Fu\u00dfbodenbau Gmbh",
    "wof:placetype":"venue"
},
  "geometry": {"coordinates":[7.2436947823,51.6086959839],"type":"Point"}
}