{
  "type": "Feature",
  "properties": {
    "iso:country":"DE",
    "sg:address":"Pfarrgasse 6",
    "sg:city":"Weil der Stadt",
    "sg:phone":"+49 7033/2058",
    "sg:postcode":"71263",
    "sg:province":"Baden-W\u00fcrttemberg",
    "wof:name":"M\u00fccke Und Neu-wolf Rechtsanw\u00e4lte",
    "wof:placetype":"venue"
},
  "geometry": {"coordinates":[8.8711652756,48.7505111694],"type":"Point"}
}