{
  "type": "Feature",
  "properties": {
    "iso:country":"DE",
    "sg:address":"Wei\u00dferitzstr. 3",
    "sg:city":"Dresden",
    "sg:phone":"+49 351/4904059",
    "sg:postcode":"01067",
    "sg:province":"Sachsen",
    "wof:name":"Mrm Steuerberatungsges. Mbh",
    "wof:placetype":"venue"
},
  "geometry": {"coordinates":[13.7266292572,51.0590019226],"type":"Point"}
}