{
  "type": "Feature",
  "properties": {
    "iso:country":"DE",
    "sg:address":"Gartenstr. 12",
    "sg:city":"Schwarzenbach a Wald",
    "sg:phone":"+49 9561/18136",
    "sg:postcode":"95131",
    "sg:province":"Bayern",
    "wof:name":"Friedrich G\u00f6tzky Masseur",
    "wof:placetype":"venue"
},
  "geometry": {"coordinates":[11.6250429153,50.2838630676],"type":"Point"}
}