{
  "type": "Feature",
  "properties": {
    "iso:country":"DE",
    "sg:address":"Hauptstr. 5",
    "sg:city":"Marktgraitz",
    "sg:phone":"+49 9574/9409",
    "sg:postcode":"96257",
    "sg:province":"Bayern",
    "wof:name":"Metzgerei Markus Partheym\u00fcller E. K.",
    "wof:placetype":"venue"
},
  "geometry": {"coordinates":[11.1977243423,50.182510376],"type":"Point"}
}