{
  "type": "Feature",
  "properties": {
    "iso:country":"DE",
    "sg:address":"Burgstr. 5",
    "sg:city":"Nienburg",
    "sg:phone":"+49 34721/22451",
    "sg:postcode":"06429",
    "sg:province":"Sachsen-Anhalt",
    "wof:name":"G\u00fcnter K\u00f6nig",
    "wof:placetype":"venue"
},
  "geometry": {"coordinates":[11.7700719833,51.8353309631],"type":"Point"}
}