{
  "type": "Feature",
  "properties": {
    "iso:country":"DE",
    "sg:address":"Schlo\u00dfgartenweg",
    "sg:city":"Ismaning",
    "sg:phone":"+49 89/96049810",
    "sg:postcode":"85737",
    "sg:province":"Bayern",
    "wof:name":"Gtg Immobilien- Hausverwaltung Gmbh",
    "wof:placetype":"venue"
},
  "geometry": {"coordinates":[11.6725702286,48.2249565125],"type":"Point"}
}