{
  "type": "Feature",
  "properties": {
    "iso:country":"DE",
    "sg:address":"Alfelder Str. 127",
    "sg:city":"Berlin",
    "sg:postcode":"12683",
    "sg:province":"Berlin",
    "wof:name":"Filmdokumentation",
    "wof:placetype":"venue"
},
  "geometry": {"coordinates":[13.563237,52.49247],"type":"Point"}
}