{
  "type": "Feature",
  "properties": {
    "iso:country":"DE",
    "sg:address":"Zeischaer Weg 12",
    "sg:city":"Bad Liebenwerda",
    "sg:phone":"+49 35341/10359",
    "sg:postcode":"04924",
    "sg:province":"Brandenburg",
    "wof:name":"Margit Tenner Notarin",
    "wof:placetype":"venue"
},
  "geometry": {"coordinates":[13.4448833466,51.5126991272],"type":"Point"}
}