{
  "type": "Feature",
  "properties": {
    "iso:country":"DE",
    "sg:address":"Puscherstra\u00dfe 9",
    "sg:city":"N\u00fcrnberg",
    "sg:phone":"+49 911/9557415",
    "sg:postcode":"90411",
    "sg:province":"Bayern",
    "wof:name":"Srs Sport-rasen-systeme",
    "wof:placetype":"venue"
},
  "geometry": {"coordinates":[11.1255779266,49.4828529358],"type":"Point"}
}