{
  "type": "Feature",
  "properties": {
    "iso:country":"DE",
    "sg:address":"Weintorstr. 1",
    "sg:city":"Mainz",
    "sg:postcode":"55116",
    "sg:province":"Rheinland-Pfalz",
    "wof:name":"Diw Deutsch-israelischer Wirtschaftsverein",
    "wof:placetype":"venue"
},
  "geometry": {"coordinates":[8.2760438919,49.9963798523],"type":"Point"}
}