{
  "type": "Feature",
  "properties": {
    "iso:country":"DE",
    "sg:address":"Wei\u00dfenburger Str. 4",
    "sg:city":"M\u00fcnchen",
    "sg:phone":"+49 89/4487017",
    "sg:postcode":"81667",
    "sg:province":"Bayern",
    "wof:name":"Eva-maria Dauscher Heilpraktikerin",
    "wof:placetype":"venue"
},
  "geometry": {"coordinates":[11.5948390961,48.1285018921],"type":"Point"}
}