{
  "type": "Feature",
  "properties": {
    "iso:country":"DE",
    "sg:address":"F\u00e4hrstr. 1",
    "sg:city":"Wischhafen",
    "sg:phone":"+49 4770/211",
    "sg:postcode":"21737",
    "sg:province":"Niedersachsen",
    "wof:name":"Werner Grothmann",
    "wof:placetype":"venue"
},
  "geometry": {"coordinates":[9.321661,53.776962],"type":"Point"}
}