{
  "type": "Feature",
  "properties": {
    "iso:country":"DE",
    "sg:address":"Am Westende 28",
    "sg:city":"Burgdorf",
    "sg:phone":"+49 5136/970555",
    "sg:postcode":"31303",
    "sg:province":"Niedersachsen",
    "wof:name":"Burkhard Seifert Rechtsanwalt",
    "wof:placetype":"venue"
},
  "geometry": {"coordinates":[9.9910726547,52.4526329041],"type":"Point"}
}