{
  "type": "Feature",
  "properties": {
    "iso:country":"DE",
    "sg:address":"Bockhorst 108",
    "sg:city":"Hamburg",
    "sg:phone":"+49 40/6901091",
    "sg:postcode":"22589",
    "sg:province":"Hamburg",
    "wof:name":"Presto Druck & Verlag Gmbh & Co.",
    "wof:placetype":"venue"
},
  "geometry": {"coordinates":[9.8372488022,53.5701904297],"type":"Point"}
}