{
  "type": "Feature",
  "properties": {
    "iso:country":"DE",
    "sg:address":"Dorfstr. 4",
    "sg:city":"Lindau-Bodolz",
    "sg:postcode":"88131",
    "sg:province":"Bayern",
    "wof:name":"Fliesen Schmid",
    "wof:placetype":"venue"
},
  "geometry": {"coordinates":[9.6654872894,47.5652389526],"type":"Point"}
}