{
  "type": "Feature",
  "properties": {
    "iso:country":"DE",
    "sg:address":"Herrenschreiberstr. 17",
    "sg:city":"Rheine",
    "sg:postcode":"48431",
    "sg:province":"Nordrhein-Westfalen",
    "wof:name":"Verband Der Kath. Kirchen- Gemeinde Des Dekanats Rheine",
    "wof:placetype":"venue"
},
  "geometry": {"coordinates":[7.4389882088,52.2774200439],"type":"Point"}
}