{
  "type": "Feature",
  "properties": {
    "iso:country":"DE",
    "sg:address":"Karl-Helfferich-Str. 16",
    "sg:city":"Neustadt",
    "sg:phone":"+49 6321/84780",
    "sg:postcode":"67433",
    "sg:province":"Rheinland-Pfalz",
    "wof:name":"Postm\u00fchl-apotheke",
    "wof:placetype":"venue"
},
  "geometry": {"coordinates":[8.140824,49.353752],"type":"Point"}
}