{
  "type": "Feature",
  "properties": {
    "iso:country":"DE",
    "sg:address":"Neuenhauser Str. 19",
    "sg:city":"Lohmar",
    "sg:phone":"+49 2246/5838",
    "sg:postcode":"53797",
    "sg:province":"Nordrhein-Westfalen",
    "wof:name":"H. U. Sachad\u00e4",
    "wof:placetype":"venue"
},
  "geometry": {"coordinates":[7.28263,50.830921],"type":"Point"}
}