{
  "type": "Feature",
  "properties": {
    "iso:country":"DE",
    "sg:address":"Schlo\u00dfstr. 4",
    "sg:city":"Falkenstein",
    "sg:phone":"+49 3745/6850",
    "sg:postcode":"08223",
    "sg:province":"Sachsen",
    "wof:name":"Sporthaus Volker Hopfmann",
    "wof:placetype":"venue"
},
  "geometry": {"coordinates":[12.368516,50.476097],"type":"Point"}
}