{
  "type": "Feature",
  "properties": {
    "iso:country":"DE",
    "sg:address":"M\u00fchlstr. 79",
    "sg:city":"Ringleben",
    "sg:phone":"+49 36201/60261",
    "sg:postcode":"99189",
    "sg:province":"Th\u00fcringen",
    "wof:name":"Uwe Gretsch",
    "wof:placetype":"venue"
},
  "geometry": {"coordinates":[10.9525260925,51.1042289734],"type":"Point"}
}