{
  "type": "Feature",
  "properties": {
    "iso:country":"DE",
    "sg:address":"Hauptstr. 12",
    "sg:city":"Neu-Ulm",
    "sg:phone":"+49 731/9717816",
    "sg:postcode":"89233",
    "sg:province":"Bayern",
    "wof:name":"S. Fahrenschon",
    "wof:placetype":"venue"
},
  "geometry": {"coordinates":[10.0331354141,48.4066925049],"type":"Point"}
}