{
  "type": "Feature",
  "properties": {
    "iso:country":"DE",
    "sg:address":"Schulstr. 7",
    "sg:city":"Ransbach-Baumbach",
    "sg:phone":"+49 2623/2763",
    "sg:postcode":"56235",
    "sg:province":"Rheinland-Pfalz",
    "wof:name":"P. Wingender",
    "wof:placetype":"venue"
},
  "geometry": {"coordinates":[7.726971,50.468266],"type":"Point"}
}