{
  "type": "Feature",
  "properties": {
    "iso:country":"DE",
    "sg:address":"Theatinerstr. 42",
    "sg:city":"M\u00fcnchen",
    "sg:phone":"+49 89/294885",
    "sg:postcode":"80333",
    "sg:province":"Bayern",
    "wof:name":"J. R. Frisch",
    "wof:placetype":"venue"
},
  "geometry": {"coordinates":[11.5763111115,48.139919281],"type":"Point"}
}