{
  "type": "Feature",
  "properties": {
    "iso:country":"DE",
    "sg:address":"Zollstock 1 b",
    "sg:city":"G\u00f6ttingen",
    "sg:phone":"+49 551/93100",
    "sg:postcode":"37081",
    "sg:province":"Niedersachsen",
    "wof:name":"R. Dawe",
    "wof:placetype":"venue"
},
  "geometry": {"coordinates":[9.89755,51.530807],"type":"Point"}
}