{
  "type": "Feature",
  "properties": {
    "iso:country":"DE",
    "sg:address":"Saarstr. 8",
    "sg:city":"Erlangen",
    "sg:phone":"+49 9131/32297",
    "sg:postcode":"91052",
    "sg:province":"Bayern",
    "wof:name":"O. Maeumbaed",
    "wof:placetype":"venue"
},
  "geometry": {"coordinates":[11.0159606934,49.5848770142],"type":"Point"}
}