{
  "type": "Feature",
  "properties": {
    "iso:country":"DE",
    "sg:address":"Unterkessacher Str. 6",
    "sg:city":"Widdern",
    "sg:phone":"+49 6298/1321",
    "sg:postcode":"74259",
    "sg:province":"Baden-W\u00fcrttemberg",
    "wof:name":"August Breiten\u00f6der",
    "wof:placetype":"venue"
},
  "geometry": {"coordinates":[9.4216928482,49.3182182312],"type":"Point"}
}