{
  "type": "Feature",
  "properties": {
    "iso:country":"DE",
    "sg:address":"Uhleb\u00fcller Dorfstr. 103",
    "sg:city":"Nieb\u00fcll",
    "sg:phone":"+49 4661/4133",
    "sg:postcode":"25899",
    "sg:province":"Schleswig-Holstein",
    "wof:name":"M. C. Petersen & Sohn",
    "wof:placetype":"venue"
},
  "geometry": {"coordinates":[8.834298,54.800259],"type":"Point"}
}