{
  "type": "Feature",
  "properties": {
    "iso:country":"DE",
    "sg:address":"Garteng\u00e4\u00dfchen 5",
    "sg:city":"Gro\u00dfenhain",
    "sg:phone":"+49 3522/501494",
    "sg:postcode":"01558",
    "sg:province":"Sachsen",
    "wof:name":"Wolfgang Rothe",
    "wof:placetype":"venue"
},
  "geometry": {"coordinates":[13.527914,51.293758],"type":"Point"}
}