{
  "type": "Feature",
  "properties": {
    "iso:country":"DE",
    "sg:address":"Stuttgarter Str. 1",
    "sg:city":"Kornwestheim",
    "sg:phone":"+49 7154/8090",
    "sg:postcode":"70806",
    "sg:province":"Baden-W\u00fcrttemberg",
    "wof:name":"Hotel Domizil",
    "wof:placetype":"venue"
},
  "geometry": {"coordinates":[9.1858234406,48.8648414612],"type":"Point"}
}