{
  "type": "Feature",
  "properties": {
    "iso:country":"DE",
    "sg:address":"Kurf\u00fcrstenstr. 35",
    "sg:city":"Br\u00fchl",
    "sg:phone":"+49 2232/42055",
    "sg:postcode":"50321",
    "sg:province":"Nordrhein-Westfalen",
    "wof:name":"H. E. Klump",
    "wof:placetype":"venue"
},
  "geometry": {"coordinates":[6.902633,50.838783],"type":"Point"}
}