{
  "type": "Feature",
  "properties": {
    "iso:country":"DE",
    "sg:address":"Br\u00fcckenstr. 4",
    "sg:city":"Ha\u00dffurt",
    "sg:phone":"+49 9521/5692",
    "sg:postcode":"97437",
    "sg:province":"Bayern",
    "wof:name":"Doris Schierling",
    "wof:placetype":"venue"
},
  "geometry": {"coordinates":[10.5065879822,50.0311508179],"type":"Point"}
}