{
  "type": "Feature",
  "properties": {
    "iso:country":"DE",
    "sg:address":"J\u00e4gerstr. 74",
    "sg:city":"Duisburg",
    "sg:postcode":"47166",
    "sg:province":"Nordrhein-Westfalen",
    "wof:name":"Deutsche Telekom T-punkt",
    "wof:placetype":"venue"
},
  "geometry": {"coordinates":[6.7717680931,51.4902954102],"type":"Point"}
}