{
  "type": "Feature",
  "properties": {
    "iso:country":"DE",
    "sg:address":"Gildenstr 7",
    "sg:city":"Oberhausen",
    "sg:phone":"+49 208/8999758",
    "sg:postcode":"46045",
    "sg:province":"Nordrhein-Westfalen",
    "wof:name":"National-bank Ag",
    "wof:placetype":"venue"
},
  "geometry": {"coordinates":[6.88529,51.501286],"type":"Point"}
}