{
  "type": "Feature",
  "properties": {
    "iso:country":"DE",
    "sg:address":"Dorfring 19",
    "sg:city":"D\u00f6tlingen",
    "sg:phone":"+49 4433/253",
    "sg:postcode":"27801",
    "sg:province":"Niedersachsen",
    "wof:name":"Heinz Friede",
    "wof:placetype":"venue"
},
  "geometry": {"coordinates":[8.3806781769,52.9352531433],"type":"Point"}
}