{
  "type": "Feature",
  "properties": {
    "iso:country":"DE",
    "sg:address":"Kapellenweg 14",
    "sg:city":"Dingdorf",
    "sg:phone":"+49 6553/920014",
    "sg:postcode":"54614",
    "sg:province":"Rheinland-Pfalz",
    "wof:name":"Matthias Ernzer",
    "wof:placetype":"venue"
},
  "geometry": {"coordinates":[6.437836,50.147667],"type":"Point"}
}