{
  "type": "Feature",
  "properties": {
    "iso:country":"DE",
    "sg:address":"Hauptstr. 61 a",
    "sg:city":"Reckendorf",
    "sg:phone":"+49 9544/982800",
    "sg:postcode":"96182",
    "sg:province":"Bayern",
    "wof:name":"Gra-ba Granit Und Basalt Handelges. Mbh",
    "wof:placetype":"venue"
},
  "geometry": {"coordinates":[10.826845,50.020702],"type":"Point"}
}