{
  "type": "Feature",
  "properties": {
    "iso:country":"DE",
    "sg:address":"Hans-B\u00f6ckler-Str. 3",
    "sg:city":"Kirchheim",
    "sg:phone":"+49 7021/94510",
    "sg:postcode":"73230",
    "sg:province":"Baden-W\u00fcrttemberg",
    "wof:name":"Cmb Automation Gmbh",
    "wof:placetype":"venue"
},
  "geometry": {"coordinates":[9.474217,48.638653],"type":"Point"}
}