{
  "type": "Feature",
  "properties": {
    "iso:country":"DE",
    "sg:address":"Wandsbeker K\u00f6nigstr. 5",
    "sg:city":"Hamburg",
    "sg:phone":"+49 40/686472",
    "sg:postcode":"22041",
    "sg:province":"Hamburg",
    "wof:name":"Dieter Wittgrefe",
    "wof:placetype":"venue"
},
  "geometry": {"coordinates":[10.0642404556,53.5717735291],"type":"Point"}
}