{
  "type": "Feature",
  "properties": {
    "iso:country":"DE",
    "sg:address":"Wiehengebirgsstr 53",
    "sg:city":"Melle",
    "sg:phone":"+49 5427/9229503",
    "sg:postcode":"49328",
    "sg:province":"Niedersachsen",
    "wof:name":"Atm-eu",
    "wof:placetype":"venue"
},
  "geometry": {"coordinates":[8.393021,52.252617],"type":"Point"}
}