{
  "type": "Feature",
  "properties": {
    "iso:country":"DE",
    "sg:address":"Habsburgerstr. 79",
    "sg:city":"Freiburg",
    "sg:phone":"+49 761/381104",
    "sg:postcode":"79104",
    "sg:province":"Baden-W\u00fcrttemberg",
    "wof:name":"Fuchs Automaten-service Gmbh",
    "wof:placetype":"venue"
},
  "geometry": {"coordinates":[7.8556728363,48.0059394836],"type":"Point"}
}