{
  "type": "Feature",
  "properties": {
    "iso:country":"DE",
    "sg:address":"Otto-Schott-Str. 13",
    "sg:city":"Jena",
    "sg:phone":"+49 3641/681694",
    "sg:postcode":"07745",
    "sg:province":"Th\u00fcringen",
    "wof:name":"Archiv Der Jenaer Glaswerk Gmbh",
    "wof:placetype":"venue"
},
  "geometry": {"coordinates":[11.576165,50.922955],"type":"Point"}
}