{
  "type": "Feature",
  "properties": {
    "iso:country":"DE",
    "sg:address":"Untere Haldenstr. 10",
    "sg:city":"Neuweiler",
    "sg:phone":"+49 7055/930372",
    "sg:postcode":"75389",
    "sg:province":"Baden-W\u00fcrttemberg",
    "wof:name":"Holzbau Frank & Co. Gmbh",
    "wof:placetype":"venue"
},
  "geometry": {"coordinates":[8.595491,48.653912],"type":"Point"}
}