{
  "type": "Feature",
  "properties": {
    "iso:country":"DE",
    "sg:address":"Elmenhorst 27",
    "sg:city":"Petershagen",
    "sg:phone":"+49 5705/370",
    "sg:postcode":"32469",
    "sg:province":"Nordrhein-Westfalen",
    "wof:name":"Kurt Proft Masseur",
    "wof:placetype":"venue"
},
  "geometry": {"coordinates":[9.052272,52.434685],"type":"Point"}
}