{
  "type": "Feature",
  "properties": {
    "iso:country":"DE",
    "sg:address":"Lenzholzer Str. 103a",
    "sg:city":"K\u00fcrten",
    "sg:postcode":"51515",
    "sg:province":"Nordrhein-Westfalen",
    "wof:name":"Rewa Beton Fertigteile Und Zubeh\u00f6r Vertrieb Gmbh",
    "wof:placetype":"venue"
},
  "geometry": {"coordinates":[7.234582901,51.0173721313],"type":"Point"}
}