{
  "type": "Feature",
  "properties": {
    "iso:country":"DE",
    "sg:address":"Hauptstr. 94",
    "sg:city":"Offenburg",
    "sg:phone":"+49 781/71039",
    "sg:postcode":"77652",
    "sg:province":"Baden-W\u00fcrttemberg",
    "wof:name":"Hotel Sonne",
    "wof:placetype":"venue"
},
  "geometry": {"coordinates":[7.9426422119,48.4690513611],"type":"Point"}
}