{
  "type": "Feature",
  "properties": {
    "iso:country":"DE",
    "sg:address":"Gro\u00dfmoorring 9",
    "sg:city":"Hamburg",
    "sg:phone":"+49 40/7660010",
    "sg:postcode":"21079",
    "sg:province":"Hamburg",
    "wof:name":"Ssd Industriesysteme Gmbh",
    "wof:placetype":"venue"
},
  "geometry": {"coordinates":[10.00605,53.456917],"type":"Point"}
}