{
  "type": "Feature",
  "properties": {
    "iso:country":"DE",
    "sg:address":"Langerweher Str. 7",
    "sg:city":"D\u00fcren",
    "sg:phone":"+49 2421/61740",
    "sg:postcode":"52355",
    "sg:province":"Nordrhein-Westfalen",
    "wof:name":"China-restaurant Happy Vallery",
    "wof:placetype":"venue"
},
  "geometry": {"coordinates":[6.4343719482,50.8022384644],"type":"Point"}
}