{
  "type": "Feature",
  "properties": {
    "iso:country":"DE",
    "sg:address":"Am G\u00f6hlenbach 101",
    "sg:city":"Kempten",
    "sg:phone":"+49 831/83259",
    "sg:postcode":"87439",
    "sg:province":"Bayern",
    "wof:name":"Roland Sieghart",
    "wof:placetype":"venue"
},
  "geometry": {"coordinates":[10.2964191437,47.7253608704],"type":"Point"}
}