{
  "type": "Feature",
  "properties": {
    "iso:country":"DE",
    "sg:address":"Charlottenstr. 6",
    "sg:city":"Leipzig",
    "sg:phone":"+49 341/6899930",
    "sg:postcode":"04317",
    "sg:province":"Sachsen",
    "wof:name":"Frank Goldmann",
    "wof:placetype":"venue"
},
  "geometry": {"coordinates":[12.4058551788,51.3345947266],"type":"Point"}
}