{
  "type": "Feature",
  "properties": {
    "iso:country":"DE",
    "sg:address":"Hamburger Str. 59",
    "sg:city":"Hamburg",
    "sg:postcode":"22083",
    "sg:province":"Hamburg",
    "wof:name":"Agentur P.e.p",
    "wof:placetype":"venue"
},
  "geometry": {"coordinates":[10.0325593948,53.5741882324],"type":"Point"}
}