{
  "type": "Feature",
  "properties": {
    "iso:country":"DE",
    "sg:address":"Im Farchet 13 1/2",
    "sg:city":"Bad T\u00f6lz",
    "sg:phone":"+49 8041/78770",
    "sg:postcode":"83646",
    "sg:province":"Bayern",
    "wof:name":"Big Entsorgungs- Technologien Gmbh",
    "wof:placetype":"venue"
},
  "geometry": {"coordinates":[11.5574674606,47.7604751587],"type":"Point"}
}