{
  "type": "Feature",
  "properties": {
    "iso:country":"DE",
    "sg:address":"Gutenbergstr. 11",
    "sg:city":"Oberhausen",
    "sg:phone":"+49 208/23766",
    "sg:postcode":"46045",
    "sg:province":"Nordrhein-Westfalen",
    "wof:name":"H. Bozkurt",
    "wof:placetype":"venue"
},
  "geometry": {"coordinates":[6.8491678238,51.4682312012],"type":"Point"}
}