{
  "type": "Feature",
  "properties": {
    "iso:country":"DE",
    "sg:address":"Noorweg 22",
    "sg:city":"Fahrdorf",
    "sg:phone":"+49 4621/33125",
    "sg:postcode":"24857",
    "sg:province":"Schleswig-Holstein",
    "wof:name":"Conrad Engel Heilpraktiker",
    "wof:placetype":"venue"
},
  "geometry": {"coordinates":[9.5831069946,54.493976593],"type":"Point"}
}