{
  "type": "Feature",
  "properties": {
    "iso:country":"DE",
    "sg:address":"G\u00e4rtnerstr. 50",
    "sg:city":"Hamburg",
    "sg:phone":"+49 40/400304",
    "sg:postcode":"20253",
    "sg:province":"Hamburg",
    "wof:name":"Verwaltung Medusa Handels Gmbh",
    "wof:placetype":"venue"
},
  "geometry": {"coordinates":[9.966413,53.58231],"type":"Point"}
}