{
  "type": "Feature",
  "properties": {
    "iso:country":"DE",
    "sg:address":"Uhlandstr. 74",
    "sg:city":"Gr\u00fcnstadt",
    "sg:postcode":"67269",
    "sg:province":"Rheinland-Pfalz",
    "wof:name":"Unicus Stahl- Und Formenbau Gmbh",
    "wof:placetype":"venue"
},
  "geometry": {"coordinates":[8.1645870209,49.5743637085],"type":"Point"}
}