{
  "type": "Feature",
  "properties": {
    "iso:country":"DE",
    "sg:address":"Kapellenstr. 20",
    "sg:city":"Reimlingen",
    "sg:phone":"+49 9081/3339",
    "sg:postcode":"86756",
    "sg:province":"Bayern",
    "wof:name":"W. Lutz",
    "wof:placetype":"venue"
},
  "geometry": {"coordinates":[10.511841,48.821152],"type":"Point"}
}