{
  "type": "Feature",
  "properties": {
    "iso:country":"DE",
    "sg:address":"Kaiserstr. 1",
    "sg:city":"Hennef",
    "sg:phone":"+49 2242/80617",
    "sg:postcode":"53773",
    "sg:province":"Nordrhein-Westfalen",
    "wof:name":"A. M. B. Folien Gmbh",
    "wof:placetype":"venue"
},
  "geometry": {"coordinates":[7.281827,50.776325],"type":"Point"}
}