{
  "type": "Feature",
  "properties": {
    "iso:country":"DE",
    "sg:address":"Im Petersborn 5",
    "sg:city":"\u00d6tzingen",
    "sg:phone":"+49 2602/69001",
    "sg:postcode":"56244",
    "sg:province":"Rheinland-Pfalz",
    "wof:name":"Schwickert Bau Gmbh & Co. Kg",
    "wof:placetype":"venue"
},
  "geometry": {"coordinates":[7.8273949623,50.4954223633],"type":"Point"}
}