{
  "type": "Feature",
  "properties": {
    "iso:country":"DE",
    "sg:address":"Waldstr. 56",
    "sg:city":"Gelnhausen",
    "sg:phone":"+49 6051/68666",
    "sg:postcode":"63571",
    "sg:province":"Hessen",
    "wof:name":"J. I. Matyes Ingenieur",
    "wof:placetype":"venue"
},
  "geometry": {"coordinates":[9.1467580795,50.1782493591],"type":"Point"}
}