{
  "type": "Feature",
  "properties": {
    "iso:country":"DE",
    "sg:address":"Arnold-Sch\u00f6nberg-Str. 2",
    "sg:city":"R\u00f6srath",
    "sg:postcode":"51503",
    "sg:province":"Nordrhein-Westfalen",
    "wof:name":"Restaurant Martini",
    "wof:placetype":"venue"
},
  "geometry": {"coordinates":[7.1868748665,50.8916702271],"type":"Point"}
}