{
  "type": "Feature",
  "properties": {
    "iso:country":"DE",
    "sg:address":"Am Kochenhof 16",
    "sg:city":"Stuttgart",
    "sg:phone":"+49 711/25890",
    "sg:postcode":"70192",
    "sg:province":"Baden-W\u00fcrttemberg",
    "wof:name":"Stuttgarter Messe- Und Kongressgesellschaft Mbh",
    "wof:placetype":"venue"
},
  "geometry": {"coordinates":[9.1688957214,48.7994537354],"type":"Point"}
}