{
  "type": "Feature",
  "properties": {
    "iso:country":"DE",
    "sg:address":"J\u00fcmberger Str. 87",
    "sg:city":"Neub\u00f6rger",
    "sg:phone":"+49 4966/286",
    "sg:postcode":"26909",
    "sg:province":"Niedersachsen",
    "wof:name":"Hermann Langen",
    "wof:placetype":"venue"
},
  "geometry": {"coordinates":[7.458511,52.96703],"type":"Point"}
}