{
  "type": "Feature",
  "properties": {
    "iso:country":"DE",
    "sg:address":"Hauptstr. 29",
    "sg:city":"Ruderatshofen",
    "sg:phone":"+49 8343/611",
    "sg:postcode":"87674",
    "sg:province":"Bayern",
    "wof:name":"Josef Engstler",
    "wof:placetype":"venue"
},
  "geometry": {"coordinates":[10.587092,47.817913],"type":"Point"}
}