{
  "type": "Feature",
  "properties": {
    "iso:country":"DE",
    "sg:address":"Kalkumer Str. 1",
    "sg:city":"D\u00fcsseldorf",
    "sg:phone":"+49 211/410837",
    "sg:postcode":"40468",
    "sg:province":"Nordrhein-Westfalen",
    "wof:name":"H. Tophofen",
    "wof:placetype":"venue"
},
  "geometry": {"coordinates":[6.77557,51.262867],"type":"Point"}
}