{
  "type": "Feature",
  "properties": {
    "iso:country":"DE",
    "sg:address":"Hauptstr. 35",
    "sg:city":"Durmersheim",
    "sg:phone":"+49 7245/89111",
    "sg:postcode":"76448",
    "sg:province":"Baden-W\u00fcrttemberg",
    "wof:name":"Travelpoint",
    "wof:placetype":"venue"
},
  "geometry": {"coordinates":[8.2663831711,48.9283905029],"type":"Point"}
}