{
  "type": "Feature",
  "properties": {
    "iso:country":"DE",
    "sg:address":"Labahnstr. 24",
    "sg:city":"Seebad Heringsdorf",
    "sg:phone":"+49 38378/22050",
    "sg:postcode":"17424",
    "sg:province":"Mecklenburg-Vorpommern",
    "wof:name":"Lutz Lehmann Spedition Gmbh",
    "wof:placetype":"venue"
},
  "geometry": {"coordinates":[14.156496048,53.9582176208],"type":"Point"}
}