{
  "type": "Feature",
  "properties": {
    "iso:country":"DE",
    "sg:address":"Nockhergasse 13",
    "sg:city":"Bad T\u00f6lz",
    "sg:phone":"+49 8041/9771",
    "sg:postcode":"83646",
    "sg:province":"Bayern",
    "wof:name":"Eva Junius",
    "wof:placetype":"venue"
},
  "geometry": {"coordinates":[11.5601968765,47.7618675232],"type":"Point"}
}