{
  "type": "Feature",
  "properties": {
    "iso:country":"DE",
    "sg:address":"Timmendorf Strand",
    "sg:city":"Insel Poel",
    "sg:phone":"+49 38425/355",
    "sg:postcode":"23999",
    "sg:province":"Mecklenburg-Vorpommern",
    "wof:name":"E. Hartig",
    "wof:placetype":"venue"
},
  "geometry": {"coordinates":[11.378455162,53.9910316467],"type":"Point"}
}