{
  "type": "Feature",
  "properties": {
    "iso:country":"DE",
    "sg:address":"August-L\u00e4mmle-Str. 49",
    "sg:city":"Reutlingen",
    "sg:postcode":"72766",
    "sg:province":"Baden-W\u00fcrttemberg",
    "wof:name":"Ursula Wohlfarth Gmbh",
    "wof:placetype":"venue"
},
  "geometry": {"coordinates":[9.2312068939,48.4862518311],"type":"Point"}
}