{
  "type": "Feature",
  "properties": {
    "iso:country":"DE",
    "sg:address":"Hans-Duncker-Str. 14",
    "sg:city":"Hamburg",
    "sg:phone":"+49 40/7341601",
    "sg:postcode":"21035",
    "sg:province":"Hamburg",
    "wof:name":"Munters Gmbh",
    "wof:placetype":"venue"
},
  "geometry": {"coordinates":[10.115349,53.490631],"type":"Point"}
}