{
  "type": "Feature",
  "properties": {
    "iso:country":"DE",
    "sg:address":"Brentanostr. 15",
    "sg:city":"Hannover",
    "sg:phone":"+49 511/5389873",
    "sg:postcode":"30625",
    "sg:province":"Niedersachsen",
    "wof:name":"Vereinte Herbert Glander",
    "wof:placetype":"venue"
},
  "geometry": {"coordinates":[9.7865943909,52.3750305176],"type":"Point"}
}