{
  "type": "Feature",
  "properties": {
    "iso:country":"DE",
    "sg:address":"Maybachstr. 4",
    "sg:city":"R\u00f6dermark",
    "sg:phone":"+49 6074/881430",
    "sg:postcode":"63322",
    "sg:province":"Hessen",
    "wof:name":"Komtec Kommunikationstechnik Vertriebs Gmbh",
    "wof:placetype":"venue"
},
  "geometry": {"coordinates":[8.8233222961,49.9710388184],"type":"Point"}
}