{
  "type": "Feature",
  "properties": {
    "iso:country":"DE",
    "sg:address":"Ortsstr. 50",
    "sg:city":"Pfakofen",
    "sg:phone":"+49 9451/3274",
    "sg:postcode":"93101",
    "sg:province":"Bayern",
    "wof:name":"Michael Santl",
    "wof:placetype":"venue"
},
  "geometry": {"coordinates":[12.227268219,48.8580169678],"type":"Point"}
}