{
  "type": "Feature",
  "properties": {
    "iso:country":"DE",
    "sg:address":"Donaustetter Str. 17",
    "sg:city":"Erbach",
    "sg:postcode":"89155",
    "sg:province":"Baden-W\u00fcrttemberg",
    "wof:name":"Raum Und Fassade Sieger Gmbh",
    "wof:placetype":"venue"
},
  "geometry": {"coordinates":[9.8947687149,48.3286170959],"type":"Point"}
}