{
  "type": "Feature",
  "properties": {
    "iso:country":"DE",
    "sg:address":"Borsigstr. 10",
    "sg:city":"Stuttgart",
    "sg:phone":"+49 711/896610",
    "sg:postcode":"70469",
    "sg:province":"Baden-W\u00fcrttemberg",
    "wof:name":"Etas Entwicklungs- Und Applikationswerkzeuge F\u00fcr",
    "wof:placetype":"venue"
},
  "geometry": {"coordinates":[9.1702394485,48.8152313232],"type":"Point"}
}