{
  "type": "Feature",
  "properties": {
    "iso:country":"DE",
    "sg:address":"Hauptstr. 16",
    "sg:city":"Dersum",
    "sg:phone":"+49 4963/8963",
    "sg:postcode":"26906",
    "sg:province":"Niedersachsen",
    "wof:name":"Heinz Janssen",
    "wof:placetype":"venue"
},
  "geometry": {"coordinates":[7.276896,52.961449],"type":"Point"}
}