{
  "type": "Feature",
  "properties": {
    "iso:country":"DE",
    "sg:address":"Uferstr 30",
    "sg:city":"Guben",
    "sg:phone":"+49 3561/66758",
    "sg:postcode":"03172",
    "sg:province":"Brandenburg",
    "wof:name":"Kreissparkasse",
    "wof:placetype":"venue"
},
  "geometry": {"coordinates":[14.711064,51.958324],"type":"Point"}
}