{
  "type": "Feature",
  "properties": {
    "iso:country":"DE",
    "sg:address":"Baubergerstr. 19",
    "sg:city":"M\u00fcnchen",
    "sg:phone":"+49 89/144923",
    "sg:postcode":"80992",
    "sg:province":"Bayern",
    "wof:name":"Bauberger Hof",
    "wof:placetype":"venue"
},
  "geometry": {"coordinates":[11.5092153549,48.1791915894],"type":"Point"}
}