{
  "type": "Feature",
  "properties": {
    "iso:country":"DE",
    "sg:address":"Hauptstr. 36",
    "sg:city":"Windach",
    "sg:postcode":"86949",
    "sg:province":"Bayern",
    "wof:name":"H & N Werbung Mike H. Neumann",
    "wof:placetype":"venue"
},
  "geometry": {"coordinates":[10.989739418,48.0647926331],"type":"Point"}
}