{
  "type": "Feature",
  "properties": {
    "iso:country":"DE",
    "sg:address":"Brunnenstr. 32",
    "sg:city":"Osann-Monzel",
    "sg:phone":"+49 6535/418",
    "sg:postcode":"54518",
    "sg:province":"Rheinland-Pfalz",
    "wof:name":"Ernst Landsmann-gorges",
    "wof:placetype":"venue"
},
  "geometry": {"coordinates":[6.9481501579,49.9146385193],"type":"Point"}
}