{
  "type": "Feature",
  "properties": {
    "iso:country":"DE",
    "sg:address":"Morgenstr. 20",
    "sg:city":"Karlsruhe",
    "sg:postcode":"76137",
    "sg:province":"Baden-W\u00fcrttemberg",
    "wof:name":"Plan B. Gmbh",
    "wof:placetype":"venue"
},
  "geometry": {"coordinates":[8.412931,49.001183],"type":"Point"}
}