{
  "type": "Feature",
  "properties": {
    "iso:country":"DE",
    "sg:address":"Felix-Wankel-Str. 12",
    "sg:city":"Dachau",
    "sg:phone":"+49 8131/1851",
    "sg:postcode":"85221",
    "sg:province":"Bayern",
    "wof:name":"J\u00dcrgen Lechner Gmbh",
    "wof:placetype":"venue"
},
  "geometry": {"coordinates":[11.473175,48.273724],"type":"Point"}
}