{
  "type": "Feature",
  "properties": {
    "iso:country":"DE",
    "sg:address":"Gartenweg 9",
    "sg:city":"Kirchdorf",
    "sg:phone":"+49 9444/8301",
    "sg:postcode":"93348",
    "sg:province":"Bayern",
    "wof:name":"A. Traublinger",
    "wof:placetype":"venue"
},
  "geometry": {"coordinates":[11.9062576294,48.7709960938],"type":"Point"}
}