{
  "type": "Feature",
  "properties": {
    "iso:country":"DE",
    "sg:address":"Memminger Str. 51",
    "sg:city":"Ochsenhausen",
    "sg:phone":"+49 7352/1767",
    "sg:postcode":"88416",
    "sg:province":"Baden-W\u00fcrttemberg",
    "wof:name":"Karl Gundelbacher",
    "wof:placetype":"venue"
},
  "geometry": {"coordinates":[9.9558515549,48.0673141479],"type":"Point"}
}