{
  "type": "Feature",
  "properties": {
    "iso:country":"DE",
    "sg:address":"Sonnenlehne 3",
    "sg:city":"Dresden",
    "sg:phone":"+49 351/4216146",
    "sg:postcode":"01157",
    "sg:province":"Sachsen",
    "wof:name":"Felix Buck",
    "wof:placetype":"venue"
},
  "geometry": {"coordinates":[13.664578,51.065437],"type":"Point"}
}