{
  "type": "Feature",
  "properties": {
    "iso:country":"DE",
    "sg:address":"Hauptstr. 31",
    "sg:city":"Bad Gandersheim",
    "sg:phone":"+49 5382/3869",
    "sg:postcode":"37581",
    "sg:province":"Niedersachsen",
    "wof:name":"Hotel Kannenberg",
    "wof:placetype":"venue"
},
  "geometry": {"coordinates":[10.0938978195,51.847114563],"type":"Point"}
}