{
  "type": "Feature",
  "properties": {
    "iso:country":"DE",
    "sg:address":"Ernststr. 14",
    "sg:city":"N\u00fcrnberg",
    "sg:phone":"+49 911/493121",
    "sg:postcode":"90478",
    "sg:province":"Bayern",
    "wof:name":"Rudolf Schneider",
    "wof:placetype":"venue"
},
  "geometry": {"coordinates":[11.1064453125,49.4464530945],"type":"Point"}
}