{
  "type": "Feature",
  "properties": {
    "iso:country":"DE",
    "sg:address":"Schuhmacherort 7",
    "sg:city":"Heide",
    "sg:phone":"+49 481/2330",
    "sg:postcode":"25746",
    "sg:province":"Schleswig-Holstein",
    "wof:name":"Ulrich Wiedemann",
    "wof:placetype":"venue"
},
  "geometry": {"coordinates":[9.094689,54.196423],"type":"Point"}
}