{
  "type": "Feature",
  "properties": {
    "iso:country":"DE",
    "sg:address":"Neue Zeile 10",
    "sg:city":"Kaufbeuren",
    "sg:phone":"+49 8341/62520",
    "sg:postcode":"87600",
    "sg:province":"Bayern",
    "wof:name":"Ewald Lucke & Co.",
    "wof:placetype":"venue"
},
  "geometry": {"coordinates":[10.620141983,47.8809204102],"type":"Point"}
}