{
  "type": "Feature",
  "properties": {
    "iso:country":"DE",
    "sg:address":"Kirchenstr. 13",
    "sg:city":"Schifferstadt",
    "sg:phone":"+49 6235/5169",
    "sg:postcode":"67105",
    "sg:province":"Rheinland-Pfalz",
    "wof:name":"Restaurant Am Museum",
    "wof:placetype":"venue"
},
  "geometry": {"coordinates":[8.3721208572,49.3868598938],"type":"Point"}
}