{
  "type": "Feature",
  "properties": {
    "iso:country":"DE",
    "sg:address":"Horbach 21",
    "sg:city":"Wachenroth",
    "sg:phone":"+49 9548/1055",
    "sg:postcode":"96193",
    "sg:province":"Bayern",
    "wof:name":"Johann G\u00f6tzel",
    "wof:placetype":"venue"
},
  "geometry": {"coordinates":[10.748121,49.745144],"type":"Point"}
}