{
  "type": "Feature",
  "properties": {
    "iso:country":"DE",
    "sg:address":"L\u00f6wenthalstr. 10",
    "sg:city":"Bad Nauheim",
    "sg:phone":"+49 6032/81514",
    "sg:postcode":"61231",
    "sg:province":"Hessen",
    "wof:name":"Helmut Gerber",
    "wof:placetype":"venue"
},
  "geometry": {"coordinates":[8.762286,50.376984],"type":"Point"}
}