{
  "type": "Feature",
  "properties": {
    "iso:country":"DE",
    "sg:address":"Am Waldhof 1",
    "sg:city":"Barsinghausen",
    "sg:phone":"+49 5105/52540",
    "sg:postcode":"30890",
    "sg:province":"Niedersachsen",
    "wof:name":"Kinderheim D.landkr.hannover",
    "wof:placetype":"venue"
},
  "geometry": {"coordinates":[9.4606800079,52.299243927],"type":"Point"}
}