{
  "type": "Feature",
  "properties": {
    "iso:country":"DE",
    "sg:address":"Werler Weg 4",
    "sg:city":"Recklinghausen",
    "sg:phone":"+49 2361/57416",
    "sg:postcode":"45659",
    "sg:province":"Nordrhein-Westfalen",
    "wof:name":"Valjanov Gmbh",
    "wof:placetype":"venue"
},
  "geometry": {"coordinates":[7.175343,51.592289],"type":"Point"}
}