{
  "type": "Feature",
  "properties": {
    "iso:country":"DE",
    "sg:address":"Karl-Broll-Str. 6",
    "sg:city":"Braunfels",
    "sg:phone":"+49 6442/4896",
    "sg:postcode":"35619",
    "sg:province":"Hessen",
    "wof:name":"Alfons Riedl Ingenieurb\u00fcro F. Heizung",
    "wof:placetype":"venue"
},
  "geometry": {"coordinates":[8.3867073059,50.5209388733],"type":"Point"}
}