{
  "type": "Feature",
  "properties": {
    "iso:country":"DE",
    "sg:address":"Stolbergstr. 10",
    "sg:city":"Eutin",
    "sg:phone":"+49 4521/2178",
    "sg:postcode":"23701",
    "sg:province":"Schleswig-Holstein",
    "wof:name":"J. Misgajski Steuerberater",
    "wof:placetype":"venue"
},
  "geometry": {"coordinates":[10.6178102493,54.13621521],"type":"Point"}
}