{
  "type": "Feature",
  "properties": {
    "iso:country":"DE",
    "sg:address":"Magnusweg 7",
    "sg:city":"Ammerbuch",
    "sg:phone":"+49 7032/71819",
    "sg:postcode":"72119",
    "sg:province":"Baden-W\u00fcrttemberg",
    "wof:name":"Rudolf Haas",
    "wof:placetype":"venue"
},
  "geometry": {"coordinates":[8.9032468796,48.5575675964],"type":"Point"}
}