{
  "type": "Feature",
  "properties": {
    "iso:country":"DE",
    "sg:address":"Am Nu\u00dfbaum 2a",
    "sg:city":"Simmerath",
    "sg:phone":"+49 2473/4444",
    "sg:postcode":"52152",
    "sg:province":"Nordrhein-Westfalen",
    "wof:name":"Uwe Liedtke",
    "wof:placetype":"venue"
},
  "geometry": {"coordinates":[6.388087,50.616962],"type":"Point"}
}