{
  "type": "Feature",
  "properties": {
    "iso:country":"DE",
    "sg:address":"Zum Quirinsborn 1",
    "sg:city":"Quierschied",
    "sg:phone":"+49 6897/61306",
    "sg:postcode":"66287",
    "sg:province":"Saarland",
    "wof:name":"Maria Meiser",
    "wof:placetype":"venue"
},
  "geometry": {"coordinates":[7.046883,49.323437],"type":"Point"}
}