{
  "type": "Feature",
  "properties": {
    "iso:country":"DE",
    "sg:address":"Ramskamp 64",
    "sg:city":"Elmshorn",
    "sg:phone":"+49 4121/74412",
    "sg:postcode":"25337",
    "sg:province":"Schleswig-Holstein",
    "wof:name":"Hans Seidler",
    "wof:placetype":"venue"
},
  "geometry": {"coordinates":[9.697917,53.741001],"type":"Point"}
}