{
  "type": "Feature",
  "properties": {
    "iso:country":"DE",
    "sg:address":"Am Hochanger 3-5",
    "sg:city":"W\u00f6rthsee",
    "sg:postcode":"82237",
    "sg:province":"Bayern",
    "wof:name":"Partners In Europe Ag",
    "wof:placetype":"venue"
},
  "geometry": {"coordinates":[11.2007703781,48.0836296082],"type":"Point"}
}