{
  "type": "Feature",
  "properties": {
    "iso:country":"DE",
    "sg:address":"H\u00f6fkerstr. 30",
    "sg:city":"Dortmund",
    "sg:phone":"+49 231/1767182",
    "sg:postcode":"44149",
    "sg:province":"Nordrhein-Westfalen",
    "wof:name":"Fr. Wilh. Ruhfus Gmbh & Co.",
    "wof:placetype":"venue"
},
  "geometry": {"coordinates":[7.40985,51.51955],"type":"Point"}
}