{
  "type": "Feature",
  "properties": {
    "iso:country":"DE",
    "sg:address":"Heidelberger Str. 42",
    "sg:city":"H\u00f6pfingen",
    "sg:phone":"+49 6283/395",
    "sg:postcode":"74746",
    "sg:province":"Baden-W\u00fcrttemberg",
    "wof:name":"Berberich Bauelemente Gmbh",
    "wof:placetype":"venue"
},
  "geometry": {"coordinates":[9.432236,49.603378],"type":"Point"}
}