{
  "type": "Feature",
  "properties": {
    "iso:country":"DE",
    "sg:address":"Am Mathildenschacht",
    "sg:city":"P\u00fcttlingen",
    "sg:phone":"+49 6898/690660",
    "sg:postcode":"66346",
    "sg:province":"Saarland",
    "wof:name":"Vlm Innovations Gmbh",
    "wof:placetype":"venue"
},
  "geometry": {"coordinates":[6.862595,49.277843],"type":"Point"}
}