{
  "type": "Feature",
  "properties": {
    "iso:country":"DE",
    "sg:address":"Meinholdstr. 8",
    "sg:city":"Koserow",
    "sg:phone":"+49 38375/20842",
    "sg:postcode":"17459",
    "sg:province":"Mecklenburg-Vorpommern",
    "wof:name":"A. Knuth",
    "wof:placetype":"venue"
},
  "geometry": {"coordinates":[14.002745,54.048798],"type":"Point"}
}