{
  "type": "Feature",
  "properties": {
    "iso:country":"DE",
    "sg:address":"R\u00f6merstr. 7",
    "sg:city":"Neckarsulm",
    "sg:phone":"+49 7132/41203",
    "sg:postcode":"74172",
    "sg:province":"Baden-W\u00fcrttemberg",
    "wof:name":"Werner Karpinski Steuerberater",
    "wof:placetype":"venue"
},
  "geometry": {"coordinates":[9.184636116,49.1994476318],"type":"Point"}
}