{
  "type": "Feature",
  "properties": {
    "iso:country":"DE",
    "sg:address":"Carl-Severing-Str. 75",
    "sg:city":"Bielefeld",
    "sg:phone":"+49 521/946330",
    "sg:postcode":"33649",
    "sg:province":"Nordrhein-Westfalen",
    "wof:name":"Provinzial Vesicherung Dirk Vollmer",
    "wof:placetype":"venue"
},
  "geometry": {"coordinates":[8.4891433716,51.9980278015],"type":"Point"}
}