{
  "type": "Feature",
  "properties": {
    "iso:country":"DE",
    "sg:address":"Von-Eichendorff-Str. 25",
    "sg:city":"Die\u00dfen",
    "sg:phone":"+49 8807/315",
    "sg:postcode":"86911",
    "sg:province":"Bayern",
    "wof:name":"Mayerwieser",
    "wof:placetype":"venue"
},
  "geometry": {"coordinates":[11.099667,47.952805],"type":"Point"}
}