{
  "type": "Feature",
  "properties": {
    "iso:country":"DE",
    "sg:address":"Niederrheinische Str. 13",
    "sg:city":"Kirchhain",
    "sg:phone":"+49 6422/1324",
    "sg:postcode":"35274",
    "sg:province":"Hessen",
    "wof:name":"Johannes Sprenger",
    "wof:placetype":"venue"
},
  "geometry": {"coordinates":[8.9244470596,50.8221321106],"type":"Point"}
}