{
  "type": "Feature",
  "properties": {
    "iso:country":"DE",
    "sg:address":"Hauptstr. 90",
    "sg:city":"Kandel",
    "sg:phone":"+49 7275/5011",
    "sg:postcode":"76870",
    "sg:province":"Rheinland-Pfalz",
    "wof:name":"Mode- Und Sporthaus Meier Inh. Dirk Kunstmann",
    "wof:placetype":"venue"
},
  "geometry": {"coordinates":[8.1958818436,49.0820159912],"type":"Point"}
}