{
  "type": "Feature",
  "properties": {
    "iso:country":"DE",
    "sg:address":"Pfalzstr. 33",
    "sg:city":"Untermaxfeld",
    "sg:phone":"+49 8454/1435",
    "sg:postcode":"86669",
    "sg:province":"Bayern",
    "wof:name":"Stadtsparkasse Neuburg A.d. Do",
    "wof:placetype":"venue"
},
  "geometry": {"coordinates":[11.220465,48.67165],"type":"Point"}
}