{
  "type": "Feature",
  "properties": {
    "iso:country":"DE",
    "sg:address":"Im Kreuz 5",
    "sg:city":"N\u00f6rten-Hardenberg",
    "sg:phone":"+49 5503/2690",
    "sg:postcode":"37176",
    "sg:province":"Niedersachsen",
    "wof:name":"Walter Vogt",
    "wof:placetype":"venue"
},
  "geometry": {"coordinates":[9.933545,51.619656],"type":"Point"}
}