{
  "type": "Feature",
  "properties": {
    "iso:country":"DE",
    "sg:address":"Bauerngasse 20",
    "sg:city":"Landau",
    "sg:phone":"+49 6341/64217",
    "sg:postcode":"76829",
    "sg:province":"Rheinland-Pfalz",
    "wof:name":"Zum Hemshof Restaurant",
    "wof:placetype":"venue"
},
  "geometry": {"coordinates":[8.1127948761,49.2248268127],"type":"Point"}
}