{
  "type": "Feature",
  "properties": {
    "iso:country":"DE",
    "sg:address":"Werkstr. 22",
    "sg:city":"B\u00f6hlen",
    "sg:phone":"+49 34206/78828",
    "sg:postcode":"04564",
    "sg:province":"Sachsen",
    "wof:name":"Cba-gesellschaft F. Chemische U. Biologische Analytik Mbh",
    "wof:placetype":"venue"
},
  "geometry": {"coordinates":[12.3801698685,51.1964988708],"type":"Point"}
}