{
  "type": "Feature",
  "properties": {
    "iso:country":"DE",
    "sg:address":"Gunzesried 1",
    "sg:city":"Blaichach",
    "sg:phone":"+49 8321/3118",
    "sg:postcode":"87544",
    "sg:province":"Bayern",
    "wof:name":"Franz Gehring",
    "wof:placetype":"venue"
},
  "geometry": {"coordinates":[10.258195,47.543102],"type":"Point"}
}