{
  "type": "Feature",
  "properties": {
    "iso:country":"DE",
    "sg:address":"Ludwig-Erhard-Str 8",
    "sg:city":"Kassel",
    "sg:phone":"+49 561/9324703",
    "sg:postcode":"34131",
    "sg:province":"Hessen",
    "wof:name":"Arnim Koch & Co Gmbh",
    "wof:placetype":"venue"
},
  "geometry": {"coordinates":[9.444005,51.305851],"type":"Point"}
}