{
  "type": "Feature",
  "properties": {
    "iso:country":"DE",
    "sg:address":"Thomasiusstr. 29",
    "sg:city":"Frankfurt",
    "sg:phone":"+49 335/545157",
    "sg:postcode":"15232",
    "sg:province":"Brandenburg",
    "wof:name":"Handels- Und Industrie- Vertretungen",
    "wof:placetype":"venue"
},
  "geometry": {"coordinates":[14.5357952118,52.3276557922],"type":"Point"}
}