{
  "type": "Feature",
  "properties": {
    "iso:country":"DE",
    "sg:address":"Bahnhofstr. 1",
    "sg:city":"Briesen",
    "sg:phone":"+49 33607/421",
    "sg:postcode":"15518",
    "sg:province":"Brandenburg",
    "wof:name":"Kreissparkasse",
    "wof:placetype":"venue"
},
  "geometry": {"coordinates":[14.279691,52.34668],"type":"Point"}
}