{
  "type": "Feature",
  "properties": {
    "iso:country":"DE",
    "sg:address":"Eichhornring 11",
    "sg:city":"Damme",
    "sg:phone":"+49 5491/4184",
    "sg:postcode":"49401",
    "sg:province":"Niedersachsen",
    "wof:name":"Hambeck Gmbh",
    "wof:placetype":"venue"
},
  "geometry": {"coordinates":[8.194796,52.530891],"type":"Point"}
}