{
  "type": "Feature",
  "properties": {
    "iso:country":"DE",
    "sg:address":"Reutebachgasse 2",
    "sg:city":"Freiburg",
    "sg:phone":"+49 761/53827",
    "sg:postcode":"79108",
    "sg:province":"Baden-W\u00fcrttemberg",
    "wof:name":"Bernlapp-apotheke",
    "wof:placetype":"venue"
},
  "geometry": {"coordinates":[7.858902,48.022629],"type":"Point"}
}