{
  "type": "Feature",
  "properties": {
    "iso:country":"DE",
    "sg:address":"Steigerweg 5",
    "sg:city":"Quierschied",
    "sg:phone":"+49 6897/61466",
    "sg:postcode":"66287",
    "sg:province":"Saarland",
    "wof:name":"Franz Andres",
    "wof:placetype":"venue"
},
  "geometry": {"coordinates":[7.0519189835,49.33070755],"type":"Point"}
}