{
  "type": "Feature",
  "properties": {
    "iso:country":"DE",
    "sg:address":"Dernburgstr. 59",
    "sg:city":"Berlin",
    "sg:phone":"+49 30/3256469",
    "sg:postcode":"14057",
    "sg:province":"Berlin",
    "wof:name":"I Ha Ge Hausverwaltung Gmbh",
    "wof:placetype":"venue"
},
  "geometry": {"coordinates":[13.2835788727,52.5058021545],"type":"Point"}
}