{
  "type": "Feature",
  "properties": {
    "iso:country":"DE",
    "sg:address":"Steine 15",
    "sg:city":"Luckau",
    "sg:phone":"+49 5844/651",
    "sg:postcode":"29487",
    "sg:province":"Niedersachsen",
    "wof:name":"K. Vogler",
    "wof:placetype":"venue"
},
  "geometry": {"coordinates":[11.0351467133,52.9356613159],"type":"Point"}
}