{
  "type": "Feature",
  "properties": {
    "iso:country":"DE",
    "sg:address":"Sudkamp 14",
    "sg:city":"Dortmund",
    "sg:phone":"+49 231/31851",
    "sg:postcode":"44369",
    "sg:province":"Nordrhein-Westfalen",
    "wof:name":"Mobiler Baustellen-beton Mbb Gmbh & Co. Kg",
    "wof:placetype":"venue"
},
  "geometry": {"coordinates":[7.4294638634,51.5361175537],"type":"Point"}
}