{
  "type": "Feature",
  "properties": {
    "iso:country":"DE",
    "sg:address":"F\u00e4rberstr. 49",
    "sg:city":"Villingen-Schwenningen",
    "sg:phone":"+49 7721/32959",
    "sg:postcode":"78050",
    "sg:province":"Baden-W\u00fcrttemberg",
    "wof:name":"Pilsbar-rosenstube",
    "wof:placetype":"venue"
},
  "geometry": {"coordinates":[8.459821701,48.0573005676],"type":"Point"}
}