{
  "type": "Feature",
  "properties": {
    "iso:country":"DE",
    "sg:address":"Schildergasse 78-82",
    "sg:city":"K\u00f6ln",
    "sg:phone":"+49 221/9258600",
    "sg:postcode":"50667",
    "sg:province":"Nordrhein-Westfalen",
    "wof:name":"Optik Simon Gmbh",
    "wof:placetype":"venue"
},
  "geometry": {"coordinates":[6.952137,50.936489],"type":"Point"}
}