{
  "type": "Feature",
  "properties": {
    "iso:country":"DE",
    "sg:address":"Im T\u00fcckwinkel 3",
    "sg:city":"Iserlohn",
    "sg:postcode":"58636",
    "sg:province":"Nordrhein-Westfalen",
    "wof:name":"Vogt Kg",
    "wof:placetype":"venue"
},
  "geometry": {"coordinates":[7.6985111237,51.3811569214],"type":"Point"}
}