{
  "type": "Feature",
  "properties": {
    "iso:country":"DE",
    "sg:address":"Brunnenplatz 4",
    "sg:city":"M\u00fcnster",
    "sg:phone":"+49 251/785133",
    "sg:postcode":"48153",
    "sg:province":"Nordrhein-Westfalen",
    "wof:name":"Martin B\u00f6ttcher Bildhauer",
    "wof:placetype":"venue"
},
  "geometry": {"coordinates":[7.612081,51.928436],"type":"Point"}
}