{
  "type": "Feature",
  "properties": {
    "iso:country":"DE",
    "sg:address":"Hechinger Str. 146 A",
    "sg:city":"T\u00fcbingen",
    "sg:phone":"+49 7071/791707",
    "sg:postcode":"72072",
    "sg:province":"Baden-W\u00fcrttemberg",
    "wof:name":"Vollmer",
    "wof:placetype":"venue"
},
  "geometry": {"coordinates":[9.059052,48.50362],"type":"Point"}
}