{
  "type": "Feature",
  "properties": {
    "iso:country":"DE",
    "sg:address":"Leicherstr. 16",
    "sg:city":"Kriftel",
    "sg:phone":"+49 6192/43530",
    "sg:postcode":"65830",
    "sg:province":"Hessen",
    "wof:name":"Edv-systeme Eid Gmbh",
    "wof:placetype":"venue"
},
  "geometry": {"coordinates":[8.4774999619,50.0854148865],"type":"Point"}
}