{
  "type": "Feature",
  "properties": {
    "iso:country":"DE",
    "sg:address":"Porschestr. 38",
    "sg:city":"Stuttgart",
    "sg:phone":"+49 711/13678902",
    "sg:postcode":"70435",
    "sg:province":"Baden-W\u00fcrttemberg",
    "wof:name":"Johanniter-unfall-hilfe E. V.",
    "wof:placetype":"venue"
},
  "geometry": {"coordinates":[9.1554002762,48.837184906],"type":"Point"}
}