{
  "type": "Feature",
  "properties": {
    "iso:country":"DE",
    "sg:address":"Industriestr. 40",
    "sg:city":"Feucht",
    "sg:phone":"+49 9128/13781",
    "sg:postcode":"90537",
    "sg:province":"Bayern",
    "wof:name":"D. Winter",
    "wof:placetype":"venue"
},
  "geometry": {"coordinates":[11.2222528458,49.3815307617],"type":"Point"}
}