{
  "type": "Feature",
  "properties": {
    "iso:country":"DE",
    "sg:address":"Winzergasse 10",
    "sg:city":"Hildburghausen",
    "sg:phone":"+49 3685/702724",
    "sg:postcode":"98646",
    "sg:province":"Th\u00fcringen",
    "wof:name":"G & G Dacheindeckungen Und Fassadenbau Gmbh",
    "wof:placetype":"venue"
},
  "geometry": {"coordinates":[10.736796,50.424973],"type":"Point"}
}