{
  "type": "Feature",
  "properties": {
    "iso:country":"DE",
    "sg:address":"Obermarkt 35",
    "sg:city":"Mittenwald",
    "sg:phone":"+49 8823/926436",
    "sg:postcode":"82481",
    "sg:province":"Bayern",
    "wof:name":"Elfriede Brandtner-albrecht",
    "wof:placetype":"venue"
},
  "geometry": {"coordinates":[11.2604999542,47.4403572083],"type":"Point"}
}