{
  "type": "Feature",
  "properties": {
    "iso:country":"DE",
    "sg:address":"Neuwied",
    "sg:city":"Neuwied",
    "sg:postcode":"56564",
    "sg:province":"Rheinland-Pfalz",
    "wof:name":"Marc Daumas Tanzschule",
    "wof:placetype":"venue"
},
  "geometry": {"coordinates":[7.4661197662,50.433681488],"type":"Point"}
}