{
  "type": "Feature",
  "properties": {
    "iso:country":"DE",
    "sg:address":"Richard-Wagner-Str. 74",
    "sg:city":"Kaiserslautern",
    "sg:phone":"+49 631/17209",
    "sg:postcode":"67655",
    "sg:province":"Rheinland-Pfalz",
    "wof:name":"Benderhof",
    "wof:placetype":"venue"
},
  "geometry": {"coordinates":[7.7672691345,49.4386901855],"type":"Point"}
}