{
  "type": "Feature",
  "properties": {
    "iso:country":"DE",
    "sg:address":"Steegerstr. 56",
    "sg:city":"Nettetal",
    "sg:phone":"+49 2153/914330",
    "sg:postcode":"41334",
    "sg:province":"Nordrhein-Westfalen",
    "wof:name":"Greven Boyxen Berge Genent Und Greven",
    "wof:placetype":"venue"
},
  "geometry": {"coordinates":[6.2800121307,51.3082275391],"type":"Point"}
}