{
  "type": "Feature",
  "properties": {
    "iso:country":"DE",
    "sg:address":"Leopold-von-Ranke-Str. 57",
    "sg:city":"Wiehe",
    "sg:phone":"+49 34672/65639",
    "sg:postcode":"06571",
    "sg:province":"Th\u00fcringen",
    "wof:name":"G. F\u00f6rster",
    "wof:placetype":"venue"
},
  "geometry": {"coordinates":[11.4111127853,51.2658805847],"type":"Point"}
}