{
  "type": "Feature",
  "properties": {
    "iso:country":"DE",
    "sg:address":"Gartenstr. 5",
    "sg:city":"Duisburg",
    "sg:phone":"+49 203/549460",
    "sg:postcode":"47167",
    "sg:province":"Nordrhein-Westfalen",
    "wof:name":"M.pajonczek & E.eichel",
    "wof:placetype":"venue"
},
  "geometry": {"coordinates":[6.782183,51.491135],"type":"Point"}
}