{
  "type": "Feature",
  "properties": {
    "iso:country":"DE",
    "sg:address":"Am Bahnhof 10",
    "sg:city":"Metelen",
    "sg:postcode":"48629",
    "sg:province":"Nordrhein-Westfalen",
    "wof:name":"Kippelt-d\u00f6bber Gmbh",
    "wof:placetype":"venue"
},
  "geometry": {"coordinates":[7.2151150703,52.1421661377],"type":"Point"}
}