{
  "type": "Feature",
  "properties": {
    "iso:country":"DE",
    "sg:address":"Adalbertsteinweg 9",
    "sg:city":"Aachen",
    "sg:phone":"+49 241/509560",
    "sg:postcode":"52070",
    "sg:province":"Nordrhein-Westfalen",
    "wof:name":"Imbiss Vesta Grill",
    "wof:placetype":"venue"
},
  "geometry": {"coordinates":[6.0975599289,50.774723053],"type":"Point"}
}