{
  "type": "Feature",
  "properties": {
    "iso:country":"DE",
    "sg:address":"Wellenkampstr 19",
    "sg:city":"Lage",
    "sg:phone":"+49 5232/9798710",
    "sg:postcode":"32791",
    "sg:province":"Nordrhein-Westfalen",
    "wof:name":"Proline",
    "wof:placetype":"venue"
},
  "geometry": {"coordinates":[8.797705,51.996696],"type":"Point"}
}