{
  "type": "Feature",
  "properties": {
    "iso:country":"DE",
    "sg:address":"Gocher Str. 192",
    "sg:city":"Weeze",
    "sg:phone":"+49 2823/877400",
    "sg:postcode":"47652",
    "sg:province":"Nordrhein-Westfalen",
    "wof:name":"I & P Immobilien U. Planung Gmbh",
    "wof:placetype":"venue"
},
  "geometry": {"coordinates":[6.1789097786,51.6570892334],"type":"Point"}
}