{
  "type": "Feature",
  "properties": {
    "iso:country":"DE",
    "sg:address":"Limbacher Str. 105",
    "sg:city":"Niederfrohna",
    "sg:phone":"+49 3722/95364",
    "sg:postcode":"09243",
    "sg:province":"Sachsen",
    "wof:name":"U. Kurth",
    "wof:placetype":"venue"
},
  "geometry": {"coordinates":[12.7511806488,50.8671951294],"type":"Point"}
}