{
  "type": "Feature",
  "properties": {
    "iso:country":"DE",
    "sg:address":"Steinweg 22 a",
    "sg:city":"Donaueschingen",
    "sg:postcode":"78166",
    "sg:province":"Baden-W\u00fcrttemberg",
    "wof:name":"Novembrini Gmbh",
    "wof:placetype":"venue"
},
  "geometry": {"coordinates":[8.481472,47.951412],"type":"Point"}
}