{
  "type": "Feature",
  "properties": {
    "iso:country":"DE",
    "sg:address":"Lersnerstr. 23",
    "sg:city":"Frankfurt",
    "sg:postcode":"60322",
    "sg:province":"Hessen",
    "wof:name":"Dialog Holding Gmbh",
    "wof:placetype":"venue"
},
  "geometry": {"coordinates":[8.679829,50.123726],"type":"Point"}
}