{
  "type": "Feature",
  "properties": {
    "iso:country":"DE",
    "sg:address":"Planckstr. 79",
    "sg:city":"Stuttgart",
    "sg:phone":"+49 711/481184",
    "sg:postcode":"70184",
    "sg:province":"Baden-W\u00fcrttemberg",
    "wof:name":"Grundst\u00fccksverwaltungs- Gesellschaft Neckar Mbh",
    "wof:placetype":"venue"
},
  "geometry": {"coordinates":[9.1983556747,48.7729072571],"type":"Point"}
}