{
  "type": "Feature",
  "properties": {
    "iso:country":"DE",
    "sg:address":"Otto-Hausmann-Ring 107",
    "sg:city":"Wuppertal",
    "sg:phone":"+49 202/271510",
    "sg:postcode":"42115",
    "sg:province":"Nordrhein-Westfalen",
    "wof:name":"Tm Lagerservice Und Logistik Gmbh",
    "wof:placetype":"venue"
},
  "geometry": {"coordinates":[7.109887,51.258224],"type":"Point"}
}