{
  "type": "Feature",
  "properties": {
    "iso:country":"DE",
    "sg:address":"Im Strickmann 210::",
    "sg:city":"Gottmadingen",
    "sg:postcode":"78244",
    "sg:province":"Baden-W\u00fcrttemberg",
    "wof:name":"Industriepark Gottmadingen Ag",
    "wof:placetype":"venue"
},
  "geometry": {"coordinates":[8.777165,47.734985],"type":"Point"}
}