{
  "type": "Feature",
  "properties": {
    "iso:country":"DE",
    "sg:address":"Asternweg 8",
    "sg:city":"Bechtsrieth",
    "sg:phone":"+49 961/390160",
    "sg:postcode":"92699",
    "sg:province":"Bayern",
    "wof:name":"Signum",
    "wof:placetype":"venue"
},
  "geometry": {"coordinates":[12.2187900543,49.6454086304],"type":"Point"}
}