{
  "type": "Feature",
  "properties": {
    "iso:country":"DE",
    "sg:address":"Brookkehre 27",
    "sg:city":"Hamburg",
    "sg:phone":"+49 40/72699626",
    "sg:postcode":"21029",
    "sg:province":"Hamburg",
    "wof:name":"L & K Bergedorfer Bauschuttsortierung Gmbh",
    "wof:placetype":"venue"
},
  "geometry": {"coordinates":[10.222154,53.480732],"type":"Point"}
}