{
  "type": "Feature",
  "properties": {
    "iso:country":"DE",
    "sg:address":"D\u00f6rmannsweg 3",
    "sg:city":"Gelsenkirchen",
    "sg:phone":"+49 209/876974",
    "sg:postcode":"45888",
    "sg:province":"Nordrhein-Westfalen",
    "wof:name":"Hans Grabowski",
    "wof:placetype":"venue"
},
  "geometry": {"coordinates":[7.118556,51.521221],"type":"Point"}
}