{
  "type": "Feature",
  "properties": {
    "iso:country":"DE",
    "sg:address":"H\u00f6ffgeshofweg 26",
    "sg:city":"Krefeld",
    "sg:phone":"+49 4921/5182865",
    "sg:postcode":"47807",
    "sg:province":"Nordrhein-Westfalen",
    "wof:name":"Schnitzler Gmbh",
    "wof:placetype":"venue"
},
  "geometry": {"coordinates":[6.568422,51.298817],"type":"Point"}
}