{
  "type": "Feature",
  "properties": {
    "iso:country":"DE",
    "sg:address":"Kilianistr. 49",
    "sg:city":"M\u00fchlhausen",
    "sg:phone":"+49 36018/16729",
    "sg:postcode":"99974",
    "sg:province":"Th\u00fcringen",
    "wof:name":"Bernhard Braun",
    "wof:placetype":"venue"
},
  "geometry": {"coordinates":[10.4646959305,51.2090988159],"type":"Point"}
}