{
  "type": "Feature",
  "properties": {
    "iso:country":"DE",
    "sg:address":"Mittelstr. 12",
    "sg:city":"Markkleeberg",
    "sg:phone":"+49 341/9911318",
    "sg:postcode":"04416",
    "sg:province":"Sachsen",
    "wof:name":"Designer-im-netz- Wir Bringen Sie Ins Www",
    "wof:placetype":"venue"
},
  "geometry": {"coordinates":[12.37488,51.281807],"type":"Point"}
}