{
  "type": "Feature",
  "properties": {
    "iso:country":"DE",
    "sg:address":"Hauptstr. 222",
    "sg:city":"Neukirchen",
    "sg:phone":"+49 371/221804",
    "sg:postcode":"09221",
    "sg:province":"Sachsen",
    "wof:name":"K\u00f6nig Transporte Gmbh",
    "wof:placetype":"venue"
},
  "geometry": {"coordinates":[12.8435821533,50.789188385],"type":"Point"}
}