{
  "type": "Feature",
  "properties": {
    "iso:country":"DE",
    "sg:address":"Friedrich-Ebert-Str. 6",
    "sg:city":"Plaidt",
    "sg:phone":"+49 2632/6304",
    "sg:postcode":"56637",
    "sg:province":"Rheinland-Pfalz",
    "wof:name":"Malergesch\u00e4ft Mannebach Inhaber Josef",
    "wof:placetype":"venue"
},
  "geometry": {"coordinates":[7.391808,50.393745],"type":"Point"}
}