{
  "type": "Feature",
  "properties": {
    "iso:country":"DE",
    "sg:address":"\u00dcber den H\u00f6fen 15",
    "sg:city":"Ahnatal",
    "sg:phone":"+49 5609/2743",
    "sg:postcode":"34292",
    "sg:province":"Hessen",
    "wof:name":"Erhard Heuser",
    "wof:placetype":"venue"
},
  "geometry": {"coordinates":[9.389913559,51.3683891296],"type":"Point"}
}