{
  "type": "Feature",
  "properties": {
    "iso:country":"DE",
    "sg:address":"Pfarrer-Graebener-Str. 35",
    "sg:city":"Karlsruhe",
    "sg:phone":"+49 721/707161",
    "sg:postcode":"76149",
    "sg:province":"Baden-W\u00fcrttemberg",
    "wof:name":"Restaurant Spundenfresser",
    "wof:placetype":"venue"
},
  "geometry": {"coordinates":[8.384976387,49.0519332886],"type":"Point"}
}