{
  "type": "Feature",
  "properties": {
    "iso:country":"DE",
    "sg:address":"Triebstr. 8",
    "sg:city":"Gutenacker",
    "sg:phone":"+49 6439/316",
    "sg:postcode":"56370",
    "sg:province":"Rheinland-Pfalz",
    "wof:name":"T. Wennheller",
    "wof:placetype":"venue"
},
  "geometry": {"coordinates":[7.9214429855,50.3196754456],"type":"Point"}
}