{
  "type": "Feature",
  "properties": {
    "iso:country":"DE",
    "sg:address":"Werler Str. 6",
    "sg:city":"Hamm",
    "sg:phone":"+49 2381/161673",
    "sg:postcode":"59065",
    "sg:province":"Nordrhein-Westfalen",
    "wof:name":"R. Hoffmann",
    "wof:placetype":"venue"
},
  "geometry": {"coordinates":[7.8214740753,51.6761474609],"type":"Point"}
}