{
  "type": "Feature",
  "properties": {
    "iso:country":"DE",
    "sg:address":"Dorfring 1",
    "sg:city":"Tangstedt",
    "sg:phone":"+49 4109/9556",
    "sg:postcode":"22889",
    "sg:province":"Schleswig-Holstein",
    "wof:name":"Wilstedter M\u00fchle Hotel-restaurant",
    "wof:placetype":"venue"
},
  "geometry": {"coordinates":[10.0856542587,53.7334403992],"type":"Point"}
}