{
  "type": "Feature",
  "properties": {
    "iso:country":"DE",
    "sg:address":"Darmst\u00e4dter Landstr. 101",
    "sg:city":"Ginsheim-Gustavsburg",
    "sg:phone":"+49 6134/51470",
    "sg:postcode":"65462",
    "sg:province":"Hessen",
    "wof:name":"Gutbrod Bedachungs Gmbh",
    "wof:placetype":"venue"
},
  "geometry": {"coordinates":[8.325683,49.995708],"type":"Point"}
}