{
  "type": "Feature",
  "properties": {
    "iso:country":"DE",
    "sg:address":"Hauptstr. 83",
    "sg:city":"Sundern",
    "sg:phone":"+49 2933/2489",
    "sg:postcode":"59846",
    "sg:province":"Nordrhein-Westfalen",
    "wof:name":"Carl B\u00fcrmann",
    "wof:placetype":"venue"
},
  "geometry": {"coordinates":[8.004314,51.327785],"type":"Point"}
}