{
  "type": "Feature",
  "properties": {
    "iso:country":"DE",
    "sg:address":"Bahnhofstr. 6",
    "sg:city":"Salzwedel",
    "sg:postcode":"29410",
    "sg:province":"Sachsen-Anhalt",
    "wof:name":"Dr. Roth Steuer- Beratungsgesellschaft- Mbh",
    "wof:placetype":"venue"
},
  "geometry": {"coordinates":[11.1578788757,52.8580741882],"type":"Point"}
}