{
  "type": "Feature",
  "properties": {
    "iso:country":"DE",
    "sg:address":"Rutschbahn 11",
    "sg:city":"Hamburg",
    "sg:phone":"+49 40/4103810",
    "sg:postcode":"20146",
    "sg:province":"Hamburg",
    "wof:name":"Restaurant Atnali",
    "wof:placetype":"venue"
},
  "geometry": {"coordinates":[9.980140686,53.5712547302],"type":"Point"}
}