{
  "type": "Feature",
  "properties": {
    "iso:country":"DE",
    "sg:address":"Lohwiese 2",
    "sg:city":"Haiger",
    "sg:phone":"+49 2773/8330",
    "sg:postcode":"35708",
    "sg:province":"Hessen",
    "wof:name":"H. H. Freischlad Ingenieur",
    "wof:placetype":"venue"
},
  "geometry": {"coordinates":[8.2079648972,50.7440834045],"type":"Point"}
}