{
  "type": "Feature",
  "properties": {
    "iso:country":"DE",
    "sg:address":"Industriestr.24",
    "sg:city":"Bochum",
    "sg:phone":"+49 234/9272037",
    "sg:postcode":"44892",
    "sg:province":"Nordrhein-Westfalen",
    "wof:name":"Fradem",
    "wof:placetype":"venue"
},
  "geometry": {"coordinates":[7.297990799,51.4738922119],"type":"Point"}
}