{
  "type": "Feature",
  "properties": {
    "iso:country":"DE",
    "sg:address":"Klein Feldhus 18",
    "sg:city":"Rastede",
    "sg:phone":"+49 4402",
    "sg:postcode":"26180",
    "sg:province":"Niedersachsen",
    "wof:name":"S C H E R Z W E L T . D E - Die Website Zum Lachen",
    "wof:placetype":"venue"
},
  "geometry": {"coordinates":[8.2208,53.214046],"type":"Point"}
}