{
  "type": "Feature",
  "properties": {
    "iso:country":"DE",
    "sg:address":"Josef-Gladbach-Platz 8",
    "sg:city":"Pulheim",
    "sg:postcode":"50259",
    "sg:province":"Nordrhein-Westfalen",
    "wof:name":"Padma Aktiengesellschaft F\u00fcr Tibetische Heilmittel",
    "wof:placetype":"venue"
},
  "geometry": {"coordinates":[6.76094,51.019741],"type":"Point"}
}