{
  "type": "Feature",
  "properties": {
    "iso:country":"DE",
    "sg:address":"Worringer Stra\u00dfe 73",
    "sg:city":"D\u00fcsseldorf",
    "sg:postcode":"40211",
    "sg:province":"Nordrhein-Westfalen",
    "wof:name":"Leder Schreyeck, D\u00fcsseldorf",
    "wof:placetype":"venue"
},
  "geometry": {"coordinates":[6.7960419655,51.2251815796],"type":"Point"}
}