{
  "type": "Feature",
  "properties": {
    "iso:country":"DE",
    "sg:address":"Ludwig-Anzengruber-Str. 2",
    "sg:city":"Gr\u00fcnwald",
    "sg:postcode":"82031",
    "sg:province":"Bayern",
    "wof:name":"Kofner Gmbh & Co. Kg",
    "wof:placetype":"venue"
},
  "geometry": {"coordinates":[11.5319566727,48.0481300354],"type":"Point"}
}