{
  "type": "Feature",
  "properties": {
    "iso:country":"DE",
    "sg:address":"D\u00f6rpstraat 27",
    "sg:city":"Duvensee",
    "sg:phone":"+49 4543/220",
    "sg:postcode":"23898",
    "sg:province":"Schleswig-Holstein",
    "wof:name":"Hans-peter Grell",
    "wof:placetype":"venue"
},
  "geometry": {"coordinates":[10.567586,53.695641],"type":"Point"}
}