{
  "type": "Feature",
  "properties": {
    "iso:country":"DE",
    "sg:address":"Sebastianstrasse 8",
    "sg:city":"Weiden",
    "sg:phone":"+49 961/6340893",
    "sg:postcode":"92637",
    "sg:province":"Bayern",
    "wof:name":"Intervision",
    "wof:placetype":"venue"
},
  "geometry": {"coordinates":[12.1669692993,49.6776618958],"type":"Point"}
}