{
  "type": "Feature",
  "properties": {
    "iso:country":"DE",
    "sg:address":"Crailsheimer Str. 13",
    "sg:city":"Schnelldorf",
    "sg:phone":"+49 7950/459",
    "sg:postcode":"91625",
    "sg:province":"Bayern",
    "wof:name":"Helmuth Schneider",
    "wof:placetype":"venue"
},
  "geometry": {"coordinates":[10.176965,49.196102],"type":"Point"}
}