{
  "type": "Feature",
  "properties": {
    "iso:country":"DE",
    "sg:address":"Wedemarkstr. 33",
    "sg:city":"Wedemark",
    "sg:phone":"+49 5130/3454",
    "sg:postcode":"30900",
    "sg:province":"Niedersachsen",
    "wof:name":"Heinrich Bertram",
    "wof:placetype":"venue"
},
  "geometry": {"coordinates":[9.73324,52.545544],"type":"Point"}
}