{
  "type": "Feature",
  "properties": {
    "iso:country":"DE",
    "sg:address":"Leostr 20",
    "sg:city":"M\u00fcnster",
    "sg:phone":"+49 251/1448824",
    "sg:postcode":"48153",
    "sg:province":"Nordrhein-Westfalen",
    "wof:name":"Agentur 4e",
    "wof:placetype":"venue"
},
  "geometry": {"coordinates":[7.6320018768,51.9529457092],"type":"Point"}
}