{
  "type": "Feature",
  "properties": {
    "iso:country":"DE",
    "sg:address":"Gr\u00fcnwalder Weg 12",
    "sg:city":"Unterhaching",
    "sg:phone":"+49 89/6141650",
    "sg:postcode":"82008",
    "sg:province":"Bayern",
    "wof:name":"Lico Stahl-und Kunststoff- Technik Gmbh",
    "wof:placetype":"venue"
},
  "geometry": {"coordinates":[11.609337,48.056423],"type":"Point"}
}