{
  "type": "Feature",
  "properties": {
    "iso:country":"DE",
    "sg:address":"Lange Reihe 24",
    "sg:city":"Burgwedel",
    "sg:phone":"+49 5139/99410",
    "sg:postcode":"30938",
    "sg:province":"Niedersachsen",
    "wof:name":"K\u00fcchen Rosenowski Gmbh",
    "wof:placetype":"venue"
},
  "geometry": {"coordinates":[9.9040203094,52.4933662415],"type":"Point"}
}