{
  "type": "Feature",
  "properties": {
    "iso:country":"DE",
    "sg:address":"M\u00fcnchener Str. 30",
    "sg:city":"Karlskron",
    "sg:phone":"+49 8450/9992",
    "sg:postcode":"85123",
    "sg:province":"Bayern",
    "wof:name":"Schmid",
    "wof:placetype":"venue"
},
  "geometry": {"coordinates":[11.454744339,48.6921806335],"type":"Point"}
}