{
  "type": "Feature",
  "properties": {
    "iso:country":"DE",
    "sg:address":"Ulmenweg 16-18",
    "sg:city":"Friedberg",
    "sg:phone":"+49 6031/73070",
    "sg:postcode":"61169",
    "sg:province":"Hessen",
    "wof:name":"Herbert Pfeifhofer Ingenieur",
    "wof:placetype":"venue"
},
  "geometry": {"coordinates":[8.706412,50.329613],"type":"Point"}
}