{
  "type": "Feature",
  "properties": {
    "iso:country":"DE",
    "sg:address":"Ulmer Str. 60",
    "sg:city":"Aalen",
    "sg:phone":"+49 7361/56030",
    "sg:postcode":"73431",
    "sg:province":"Baden-W\u00fcrttemberg",
    "wof:name":"Heinrich Aisslinger Gmbh & Co.",
    "wof:placetype":"venue"
},
  "geometry": {"coordinates":[10.0999126434,48.8341140747],"type":"Point"}
}