{
  "type": "Feature",
  "properties": {
    "iso:country":"DE",
    "sg:address":"Am Stadttor 8",
    "sg:city":"Weilrod",
    "sg:phone":"+49 6083/2081",
    "sg:postcode":"61276",
    "sg:province":"Hessen",
    "wof:name":"M. Menz",
    "wof:placetype":"venue"
},
  "geometry": {"coordinates":[8.418793,50.315639],"type":"Point"}
}