{
  "type": "Feature",
  "properties": {
    "iso:country":"DE",
    "sg:address":"Altenkunstadter Str. 48",
    "sg:city":"Altenkunstadt",
    "sg:phone":"+49 9572/790212",
    "sg:postcode":"96264",
    "sg:province":"Bayern",
    "wof:name":"M\u00fcller Gmbh",
    "wof:placetype":"venue"
},
  "geometry": {"coordinates":[11.2543115616,50.110080719],"type":"Point"}
}