{
  "type": "Feature",
  "properties": {
    "iso:country":"DE",
    "sg:address":"Schulstr. 12",
    "sg:city":"Dorsten",
    "sg:phone":"+49 2369/7160",
    "sg:postcode":"46286",
    "sg:province":"Nordrhein-Westfalen",
    "wof:name":"Sondermann & Meismann",
    "wof:placetype":"venue"
},
  "geometry": {"coordinates":[7.001075,51.759781],"type":"Point"}
}