{
  "type": "Feature",
  "properties": {
    "iso:country":"DE",
    "sg:address":"Schwandorfer Str. 14",
    "sg:city":"Ensdorf",
    "sg:phone":"+49 9624/573",
    "sg:postcode":"92266",
    "sg:province":"Bayern",
    "wof:name":"Hotel Vilsthaler Hof",
    "wof:placetype":"venue"
},
  "geometry": {"coordinates":[11.9392051697,49.343082428],"type":"Point"}
}