{
  "type": "Feature",
  "properties": {
    "iso:country":"DE",
    "sg:address":"Oberbachstr. 24",
    "sg:city":"Holzminden",
    "sg:phone":"+49 5531/61960",
    "sg:postcode":"37603",
    "sg:province":"Niedersachsen",
    "wof:name":"First Class Gmbh",
    "wof:placetype":"venue"
},
  "geometry": {"coordinates":[9.4491262436,51.8282775879],"type":"Point"}
}