{
  "type": "Feature",
  "properties": {
    "iso:country":"DE",
    "sg:address":"Walter-Geerdes-Str. 16",
    "sg:city":"Bremen",
    "sg:phone":"+49 421/483041",
    "sg:postcode":"28307",
    "sg:province":"Bremen",
    "wof:name":"Blome & Hampe",
    "wof:placetype":"venue"
},
  "geometry": {"coordinates":[8.9614515305,53.0473556519],"type":"Point"}
}