{
  "type": "Feature",
  "properties": {
    "iso:country":"DE",
    "sg:address":"Blankes T\u00e4lchen 6",
    "sg:city":"H\u00f6rnum",
    "sg:phone":"+49 4651/881007",
    "sg:postcode":"25997",
    "sg:province":"Schleswig-Holstein",
    "wof:name":"Relax",
    "wof:placetype":"venue"
},
  "geometry": {"coordinates":[8.2908716202,54.7564926147],"type":"Point"}
}