{
  "type": "Feature",
  "properties": {
    "iso:country":"DE",
    "sg:address":"Magirusstra\u00dfe 13",
    "sg:city":"Stuttgart",
    "sg:phone":"+49 711/98180",
    "sg:postcode":"70469",
    "sg:province":"Baden-W\u00fcrttemberg",
    "wof:name":"Viastore Systems Gmbh",
    "wof:placetype":"venue"
},
  "geometry": {"coordinates":[9.174171,48.817036],"type":"Point"}
}