{
  "type": "Feature",
  "properties": {
    "iso:country":"DE",
    "sg:address":"Buchenweg 49",
    "sg:city":"Emsdetten",
    "sg:phone":"+49 2572/86804",
    "sg:postcode":"48282",
    "sg:province":"Nordrhein-Westfalen",
    "wof:name":"Possemeyer Bedachungs Gmbh",
    "wof:placetype":"venue"
},
  "geometry": {"coordinates":[7.559103,52.160294],"type":"Point"}
}