{
  "type": "Feature",
  "properties": {
    "iso:country":"DE",
    "sg:address":"Karlstrasse 37-39",
    "sg:city":"Recklinghausen",
    "sg:phone":"+49 2323/656554",
    "sg:postcode":"45615",
    "sg:province":"Nordrhein-Westfalen",
    "wof:name":"Sl-arbeitsb\u00fchnenvermietung Gmbh, Recklinghausen",
    "wof:placetype":"venue"
},
  "geometry": {"coordinates":[7.183134,51.562408],"type":"Point"}
}