{
  "type": "Feature",
  "properties": {
    "iso:country":"DE",
    "sg:address":"Rahlstedter Str. 49",
    "sg:city":"Hamburg",
    "sg:phone":"+49 40/6736090",
    "sg:postcode":"22149",
    "sg:province":"Hamburg",
    "wof:name":"Hamburg-rahlstedter Baugenossenschaft Eg",
    "wof:placetype":"venue"
},
  "geometry": {"coordinates":[10.1463479996,53.5948753357],"type":"Point"}
}