{
  "type": "Feature",
  "properties": {
    "iso:country":"DE",
    "sg:address":"Maximilianstr. 40-42",
    "sg:city":"Bayreuth",
    "sg:phone":"+49 921/65079",
    "sg:postcode":"95444",
    "sg:province":"Bayern",
    "wof:name":"Franken Wkv Bank Gmbh",
    "wof:placetype":"venue"
},
  "geometry": {"coordinates":[11.573851,49.944832],"type":"Point"}
}