{
  "type": "Feature",
  "properties": {
    "iso:country":"DE",
    "sg:address":"Gro\u00dfer Plan 21",
    "sg:city":"Celle",
    "sg:phone":"+49 5141/924070",
    "sg:postcode":"29221",
    "sg:province":"Niedersachsen",
    "wof:name":"Sanit\u00e4tshaus Pahmeyer Gmbh",
    "wof:placetype":"venue"
},
  "geometry": {"coordinates":[10.080705,52.62289],"type":"Point"}
}