{
  "type": "Feature",
  "properties": {
    "iso:country":"DE",
    "sg:address":"Jordanstr. 5",
    "sg:city":"D\u00fcsseldorf",
    "sg:phone":"+49 211/443848",
    "sg:postcode":"40477",
    "sg:province":"Nordrhein-Westfalen",
    "wof:name":"Rehcontra E. K.",
    "wof:placetype":"venue"
},
  "geometry": {"coordinates":[6.789019,51.241543],"type":"Point"}
}