{
  "type": "Feature",
  "properties": {
    "iso:country":"DE",
    "sg:address":"Feldstr. 5",
    "sg:city":"Burweg",
    "sg:phone":"+49 4144/5340",
    "sg:postcode":"21709",
    "sg:province":"Niedersachsen",
    "wof:name":"Hans Breuer",
    "wof:placetype":"venue"
},
  "geometry": {"coordinates":[9.241094,53.612759],"type":"Point"}
}