{
  "type": "Feature",
  "properties": {
    "iso:country":"DE",
    "sg:address":"Am Waller Bach 4",
    "sg:city":"Meschede",
    "sg:phone":"+49 291/2617",
    "sg:postcode":"59872",
    "sg:province":"Nordrhein-Westfalen",
    "wof:name":"F. Sellmann",
    "wof:placetype":"venue"
},
  "geometry": {"coordinates":[8.208276,51.335442],"type":"Point"}
}