{
  "type": "Feature",
  "properties": {
    "iso:country":"DE",
    "sg:address":"Flurweg 12",
    "sg:city":"Seeshaupt",
    "sg:phone":"+49 8801/90900",
    "sg:postcode":"82402",
    "sg:province":"Bayern",
    "wof:name":"Hans Zellmer Gmbh",
    "wof:placetype":"venue"
},
  "geometry": {"coordinates":[11.2861948013,47.8232917786],"type":"Point"}
}