{
  "type": "Feature",
  "properties": {
    "iso:country":"DE",
    "sg:address":"Untere Str. 133",
    "sg:city":"M\u00f6nchengladbach",
    "sg:phone":"+49 2161/838088",
    "sg:postcode":"41068",
    "sg:province":"Nordrhein-Westfalen",
    "wof:name":"Bistro Hensen",
    "wof:placetype":"venue"
},
  "geometry": {"coordinates":[6.4099001884,51.1974029541],"type":"Point"}
}