{
  "type": "Feature",
  "properties": {
    "iso:country":"DE",
    "sg:address":"Twelte 3",
    "sg:city":"Kalletal",
    "sg:phone":"+49 5755/418",
    "sg:postcode":"32689",
    "sg:province":"Nordrhein-Westfalen",
    "wof:name":"Albrecht K\u00f6nemann",
    "wof:placetype":"venue"
},
  "geometry": {"coordinates":[9.008565,52.170914],"type":"Point"}
}