{
  "type": "Feature",
  "properties": {
    "iso:country":"DE",
    "sg:address":"Rosenstr. 4 a",
    "sg:city":"Bochum",
    "sg:phone":"+49 2327/98520",
    "sg:postcode":"44866",
    "sg:province":"Nordrhein-Westfalen",
    "wof:name":"Fv Radiologie Wattenscheid Gmbh",
    "wof:placetype":"venue"
},
  "geometry": {"coordinates":[7.1337938309,51.4815483093],"type":"Point"}
}