{
  "type": "Feature",
  "properties": {
    "iso:country":"DE",
    "sg:address":"Brunnenstr. 14",
    "sg:city":"Aschersleben",
    "sg:phone":"+49 3473/3990",
    "sg:postcode":"06449",
    "sg:province":"Sachsen-Anhalt",
    "wof:name":"Hans Haaser",
    "wof:placetype":"venue"
},
  "geometry": {"coordinates":[11.463039,51.761417],"type":"Point"}
}