{
  "type": "Feature",
  "properties": {
    "iso:country":"DE",
    "sg:address":"Neumarkt 21",
    "sg:city":"Schleiz",
    "sg:phone":"+49 3663/402313",
    "sg:postcode":"07907",
    "sg:province":"Th\u00fcringen",
    "wof:name":"Wachter & Posner Gdbr",
    "wof:placetype":"venue"
},
  "geometry": {"coordinates":[11.809345,50.5769],"type":"Point"}
}