{
  "type": "Feature",
  "properties": {
    "iso:country":"DE",
    "sg:address":"Fu\u00dfg\u00f6nheimer Str. 44",
    "sg:city":"Ludwigshafen",
    "sg:phone":"+49 621/551297",
    "sg:postcode":"67071",
    "sg:province":"Rheinland-Pfalz",
    "wof:name":"Fritz Und Ch. Stahlhofen Gmbh",
    "wof:placetype":"venue"
},
  "geometry": {"coordinates":[8.3238096237,49.4724464417],"type":"Point"}
}