{
  "type": "Feature",
  "properties": {
    "iso:country":"DE",
    "sg:address":"An der G\u00fcmpgesbr\u00fccke 17",
    "sg:city":"Kaarst",
    "sg:postcode":"41564",
    "sg:province":"Nordrhein-Westfalen",
    "wof:name":"Reedereikontor Eberhard Biedermann Gmbh",
    "wof:placetype":"venue"
},
  "geometry": {"coordinates":[6.636229,51.215023],"type":"Point"}
}