{
  "type": "Feature",
  "properties": {
    "iso:country":"DE",
    "sg:address":"Maximinplatz 5",
    "sg:city":"Zell",
    "sg:phone":"+49 6542/960057",
    "sg:postcode":"56856",
    "sg:province":"Rheinland-Pfalz",
    "wof:name":"Alfons Nickels Weinanbau",
    "wof:placetype":"venue"
},
  "geometry": {"coordinates":[7.1784410477,50.0258560181],"type":"Point"}
}