{
  "type": "Feature",
  "properties": {
    "iso:country":"DE",
    "sg:address":"L\u00fcchtenburger Weg 20",
    "sg:city":"Aurich",
    "sg:phone":"+49 4941/61029",
    "sg:postcode":"26603",
    "sg:province":"Niedersachsen",
    "wof:name":"Karl-heinz Vogelsang Steuerberater",
    "wof:placetype":"venue"
},
  "geometry": {"coordinates":[7.4830260277,53.4662246704],"type":"Point"}
}