{
  "type": "Feature",
  "properties": {
    "iso:country":"DE",
    "sg:address":"Meves-Berns-Str. 20",
    "sg:city":"Solingen",
    "sg:phone":"+49 212/13725",
    "sg:postcode":"42655",
    "sg:province":"Nordrhein-Westfalen",
    "wof:name":"D. Grah Immobilienmakler",
    "wof:placetype":"venue"
},
  "geometry": {"coordinates":[7.076420784,51.1771430969],"type":"Point"}
}