{
  "type": "Feature",
  "properties": {
    "iso:country":"DE",
    "sg:address":"Dehnhaide 50",
    "sg:city":"Hamburg",
    "sg:phone":"+49 40/2997655",
    "sg:postcode":"22081",
    "sg:province":"Hamburg",
    "wof:name":"Croque Mint",
    "wof:placetype":"venue"
},
  "geometry": {"coordinates":[10.0453357697,53.5789108276],"type":"Point"}
}