{
  "type": "Feature",
  "properties": {
    "iso:country":"DE",
    "sg:address":"Bahnhofstr. 10",
    "sg:city":"Briesen",
    "sg:phone":"+49 33607/333",
    "sg:postcode":"15518",
    "sg:province":"Brandenburg",
    "wof:name":"B. Obenhaupt",
    "wof:placetype":"venue"
},
  "geometry": {"coordinates":[14.2771959305,52.3446998596],"type":"Point"}
}