{
  "type": "Feature",
  "properties": {
    "iso:country":"DE",
    "sg:address":"M\u00fchlenstr. 139",
    "sg:city":"Glinde",
    "sg:phone":"+49 40/7119303",
    "sg:postcode":"21509",
    "sg:province":"Schleswig-Holstein",
    "wof:name":"Evelyn Th\u00fcner",
    "wof:placetype":"venue"
},
  "geometry": {"coordinates":[10.211520195,53.546131134],"type":"Point"}
}