{
  "type": "Feature",
  "properties": {
    "iso:country":"DE",
    "sg:address":"Billhorner M\u00fchlenweg 28",
    "sg:city":"Hamburg",
    "sg:phone":"+49 40/7809070",
    "sg:postcode":"20539",
    "sg:province":"Hamburg",
    "wof:name":"Elbbr\u00fccken-hotel",
    "wof:placetype":"venue"
},
  "geometry": {"coordinates":[10.0326347351,53.5361671448],"type":"Point"}
}