{
  "type": "Feature",
  "properties": {
    "iso:country":"DE",
    "sg:address":"Am Markt 3",
    "sg:city":"Konz",
    "sg:phone":"+49 6501/601292",
    "sg:postcode":"54329",
    "sg:province":"Rheinland-Pfalz",
    "wof:name":"Viktoria Service Center",
    "wof:placetype":"venue"
},
  "geometry": {"coordinates":[6.573141098,49.6972694397],"type":"Point"}
}