{
  "type": "Feature",
  "properties": {
    "iso:country":"DE",
    "sg:address":"Rosenkopfer Str. 3",
    "sg:city":"Bechhofen",
    "sg:phone":"+49 6372/1433",
    "sg:postcode":"66894",
    "sg:province":"Rheinland-Pfalz",
    "wof:name":"Katholisches Pfarramt St. Michael",
    "wof:placetype":"venue"
},
  "geometry": {"coordinates":[7.4100699425,49.3476638794],"type":"Point"}
}