{
  "type": "Feature",
  "properties": {
    "iso:country":"DE",
    "sg:address":"Bahnhofstr. 181",
    "sg:city":"Neu-Isenburg",
    "sg:phone":"+49 6102/27943",
    "sg:postcode":"63263",
    "sg:province":"Hessen",
    "wof:name":"Otto Schmitt",
    "wof:placetype":"venue"
},
  "geometry": {"coordinates":[8.67872,50.053276],"type":"Point"}
}