{
  "type": "Feature",
  "properties": {
    "iso:country":"DE",
    "sg:address":"Kelterstr. 35/1",
    "sg:city":"Esslingen",
    "sg:postcode":"73733",
    "sg:province":"Baden-W\u00fcrttemberg",
    "wof:name":"Advertum Ag",
    "wof:placetype":"venue"
},
  "geometry": {"coordinates":[9.2950906754,48.7565498352],"type":"Point"}
}