{
  "type": "Feature",
  "properties": {
    "iso:country":"DE",
    "sg:address":"Berntalstr. 93",
    "sg:city":"Sachsenheim",
    "sg:postcode":"74343",
    "sg:province":"Baden-W\u00fcrttemberg",
    "wof:name":"Ovw Verwalt.-gmbh",
    "wof:placetype":"venue"
},
  "geometry": {"coordinates":[9.0460586548,48.966506958],"type":"Point"}
}