{
  "type": "Feature",
  "properties": {
    "iso:country":"DE",
    "sg:address":"S\u00fcdstrand 21",
    "sg:city":"Wilhelmshaven",
    "sg:phone":"+49 4421/41142",
    "sg:postcode":"26382",
    "sg:province":"Niedersachsen",
    "wof:name":"Seewasser-aquarium",
    "wof:placetype":"venue"
},
  "geometry": {"coordinates":[8.122023,53.509941],"type":"Point"}
}