{
  "type": "Feature",
  "properties": {
    "iso:country":"DE",
    "sg:address":"Bernhard-R\u00f6ttgen-Waldweg 6",
    "sg:city":"Br\u00fcggen",
    "sg:postcode":"41379",
    "sg:province":"Nordrhein-Westfalen",
    "wof:name":"C. Jackels",
    "wof:placetype":"venue"
},
  "geometry": {"coordinates":[6.1855177879,51.2486076355],"type":"Point"}
}