{
  "type": "Feature",
  "properties": {
    "iso:country":"DE",
    "sg:address":"Universit\u00e4tsstr. 29",
    "sg:city":"M\u00fcnster",
    "sg:postcode":"48143",
    "sg:province":"Nordrhein-Westfalen",
    "wof:name":"J. Vrahimis Gmbh",
    "wof:placetype":"venue"
},
  "geometry": {"coordinates":[7.6181368828,51.9617118835],"type":"Point"}
}