{
  "type": "Feature",
  "properties": {
    "iso:country":"DE",
    "sg:address":"Schafhofstr. 41",
    "sg:city":"W\u00fcrzburg",
    "sg:phone":"+49 931/94602",
    "sg:postcode":"97080",
    "sg:province":"Bayern",
    "wof:name":"Waldsch\u00e4nke",
    "wof:placetype":"venue"
},
  "geometry": {"coordinates":[9.9175720215,49.8282432556],"type":"Point"}
}