{
  "type": "Feature",
  "properties": {
    "iso:country":"DE",
    "sg:address":"Hammfelddamm 6",
    "sg:city":"Neuss",
    "sg:phone":"+49 2131/15980",
    "sg:postcode":"41460",
    "sg:province":"Nordrhein-Westfalen",
    "wof:name":"Pro Event Reise Gmbh",
    "wof:placetype":"venue"
},
  "geometry": {"coordinates":[6.7105560303,51.1938514709],"type":"Point"}
}