{
  "type": "Feature",
  "properties": {
    "iso:country":"DE",
    "sg:address":"Jahnstr. 1",
    "sg:city":"Sonthofen",
    "sg:phone":"+49 8321/86272",
    "sg:postcode":"87527",
    "sg:province":"Bayern",
    "wof:name":"Norma Lebensmittel- Filialbetrieb Gmbh & Co. Kg",
    "wof:placetype":"venue"
},
  "geometry": {"coordinates":[10.2806873322,47.5181236267],"type":"Point"}
}