{
  "type": "Feature",
  "properties": {
    "iso:country":"DE",
    "sg:address":"Wiesengrundstr. 7",
    "sg:city":"Gebhardshain",
    "sg:phone":"+49 2747/3197",
    "sg:postcode":"57580",
    "sg:province":"Rheinland-Pfalz",
    "wof:name":"Pension Dagmar Und J\u00fcrgen J\u00e4dtke",
    "wof:placetype":"venue"
},
  "geometry": {"coordinates":[7.8220739365,50.7452087402],"type":"Point"}
}