{
  "type": "Feature",
  "properties": {
    "iso:country":"DE",
    "sg:address":"Am Pfarrhof",
    "sg:city":"Vettwei\u00df",
    "sg:phone":"+49 2424/7478",
    "sg:postcode":"52391",
    "sg:province":"Nordrhein-Westfalen",
    "wof:name":"Kath. Pfarramt St. Martin",
    "wof:placetype":"venue"
},
  "geometry": {"coordinates":[6.5716648102,50.7125701904],"type":"Point"}
}