{
  "type": "Feature",
  "properties": {
    "iso:country":"DE",
    "sg:address":"Schlichterstr. 8",
    "sg:city":"Wiesbaden",
    "sg:phone":"+49 611/374949",
    "sg:postcode":"65185",
    "sg:province":"Hessen",
    "wof:name":"V. Jung",
    "wof:placetype":"venue"
},
  "geometry": {"coordinates":[8.2422637939,50.0737342834],"type":"Point"}
}