{
  "type": "Feature",
  "properties": {
    "iso:country":"DE",
    "sg:address":"Walkenm\u00fchleweg",
    "sg:city":"Hechingen",
    "sg:phone":"+49 7471/5684",
    "sg:postcode":"72379",
    "sg:province":"Baden-W\u00fcrttemberg",
    "wof:name":"Martin Baur Transportbeton",
    "wof:placetype":"venue"
},
  "geometry": {"coordinates":[8.9832601547,48.3505897522],"type":"Point"}
}