{
  "type": "Feature",
  "properties": {
    "iso:country":"DE",
    "sg:address":"Am Buddenberg 1",
    "sg:city":"Selm",
    "sg:phone":"+49 2592/240160",
    "sg:postcode":"59379",
    "sg:province":"Nordrhein-Westfalen",
    "wof:name":"Restaurant Hirschklause",
    "wof:placetype":"venue"
},
  "geometry": {"coordinates":[7.4762988091,51.6878890991],"type":"Point"}
}