{
  "type": "Feature",
  "properties": {
    "iso:country":"DE",
    "sg:address":"Dorfstr. 36",
    "sg:city":"Kaltenwestheim",
    "sg:phone":"+49 36946/771",
    "sg:postcode":"98634",
    "sg:province":"Th\u00fcringen",
    "wof:name":"Gastst\u00e4tte Zur Linde",
    "wof:placetype":"venue"
},
  "geometry": {"coordinates":[10.1160402298,50.6104393005],"type":"Point"}
}