{
  "type": "Feature",
  "properties": {
    "iso:country":"DE",
    "sg:address":"Wei\u00dfendorfer Str. 6",
    "sg:city":"Zeulenroda",
    "sg:phone":"+49 36628/63967",
    "sg:postcode":"07937",
    "sg:province":"Th\u00fcringen",
    "wof:name":"Knoll Elektrowerkzeuge-elektromotoren",
    "wof:placetype":"venue"
},
  "geometry": {"coordinates":[11.995371,50.661873],"type":"Point"}
}