{
  "type": "Feature",
  "properties": {
    "iso:country":"DE",
    "sg:address":"Jahnstr. 3",
    "sg:city":"Mainhausen",
    "sg:phone":"+49 6182/93820",
    "sg:postcode":"63533",
    "sg:province":"Hessen",
    "wof:name":"H\u00f6fling Baumarkt Gmbh",
    "wof:placetype":"venue"
},
  "geometry": {"coordinates":[8.9952821732,50.016998291],"type":"Point"}
}