{
  "type": "Feature",
  "properties": {
    "iso:country":"DE",
    "sg:address":"Keltenstrasse 2",
    "sg:city":"Saarlouis",
    "sg:phone":"+49 6831/988459",
    "sg:postcode":"66740",
    "sg:province":"Saarland",
    "wof:name":"Csh Computersysteme Gdbr",
    "wof:placetype":"venue"
},
  "geometry": {"coordinates":[6.75755,49.336052],"type":"Point"}
}