{
  "type": "Feature",
  "properties": {
    "iso:country":"DE",
    "sg:address":"Peuter Elbdeich 21",
    "sg:city":"Hamburg",
    "sg:phone":"+49 40/782035",
    "sg:postcode":"20539",
    "sg:province":"Hamburg",
    "wof:name":"G. Und W. Essen",
    "wof:placetype":"venue"
},
  "geometry": {"coordinates":[10.038869,53.525673],"type":"Point"}
}