{
  "type": "Feature",
  "properties": {
    "iso:country":"DE",
    "sg:address":"Im Grund 2",
    "sg:city":"Billigheim",
    "sg:phone":"+49 6265/95322",
    "sg:postcode":"74842",
    "sg:province":"Baden-W\u00fcrttemberg",
    "wof:name":"Alfons Gro\u00dfkinsky",
    "wof:placetype":"venue"
},
  "geometry": {"coordinates":[9.248852,49.374672],"type":"Point"}
}