{
  "type": "Feature",
  "properties": {
    "iso:country":"DE",
    "sg:address":"Althengstett",
    "sg:city":"Althengstett",
    "sg:phone":"+49 4970/511844",
    "sg:postcode":"75382",
    "sg:province":"Baden-W\u00fcrttemberg",
    "wof:name":"Raiffeisenbank Althengstett Eg",
    "wof:placetype":"venue"
},
  "geometry": {"coordinates":[8.78197,48.733891],"type":"Point"}
}