{
  "type": "Feature",
  "properties": {
    "iso:country":"DE",
    "sg:address":"Im Erftgrund 8",
    "sg:city":"Grevenbroich",
    "sg:phone":"+49 2182/825172",
    "sg:postcode":"41516",
    "sg:province":"Nordrhein-Westfalen",
    "wof:name":"Bfah B\u00fcro F\u00fcr Analytische Hausratsbewertung Gmbh",
    "wof:placetype":"venue"
},
  "geometry": {"coordinates":[6.6436638832,51.1305351257],"type":"Point"}
}