{
  "type": "Feature",
  "properties": {
    "iso:country":"DE",
    "sg:address":"Fischerstr. 65",
    "sg:city":"Duisburg",
    "sg:phone":"+49 203/779058",
    "sg:postcode":"47055",
    "sg:province":"Nordrhein-Westfalen",
    "wof:name":"H\u00e4hnchen King",
    "wof:placetype":"venue"
},
  "geometry": {"coordinates":[6.7572069168,51.402469635],"type":"Point"}
}