{
  "type": "Feature",
  "properties": {
    "iso:country":"DE",
    "sg:address":"Schirnstr. 2",
    "sg:city":"K\u00f6tzting",
    "sg:phone":"+49 9941/7200",
    "sg:postcode":"93444",
    "sg:province":"Bayern",
    "wof:name":"P. J. Klein Architekt",
    "wof:placetype":"venue"
},
  "geometry": {"coordinates":[12.85544,49.175884],"type":"Point"}
}