{
  "type": "Feature",
  "properties": {
    "iso:country":"DE",
    "sg:address":"Ubierring 2",
    "sg:city":"K\u00f6ln",
    "sg:phone":"+49 221/315767",
    "sg:postcode":"50678",
    "sg:province":"Nordrhein-Westfalen",
    "wof:name":"Ubier-apotheke Inh. Gunther Franke E. K.",
    "wof:placetype":"venue"
},
  "geometry": {"coordinates":[6.960141,50.921001],"type":"Point"}
}