{
  "type": "Feature",
  "properties": {
    "iso:country":"DE",
    "sg:address":"Schleusenstr. 36",
    "sg:city":"Voerde",
    "sg:phone":"+49 281/944100",
    "sg:postcode":"46562",
    "sg:province":"Nordrhein-Westfalen",
    "wof:name":"Terminal Emmelsum Ag & Co. Kg",
    "wof:placetype":"venue"
},
  "geometry": {"coordinates":[6.6159038544,51.6273841858],"type":"Point"}
}