{
  "type": "Feature",
  "properties": {
    "iso:country":"DE",
    "sg:address":"Bertelsdorfer Str. 57",
    "sg:city":"Stein",
    "sg:phone":"+49 911/675064",
    "sg:postcode":"90547",
    "sg:province":"Bayern",
    "wof:name":"Werner Roth Beteiligungs Gmbh",
    "wof:placetype":"venue"
},
  "geometry": {"coordinates":[10.990563,49.391014],"type":"Point"}
}