{
  "type": "Feature",
  "properties": {
    "iso:country":"DE",
    "sg:address":"Vorderster Berg 22",
    "sg:city":"V\u00f6lklingen",
    "sg:phone":"+49 4968/9850300",
    "sg:postcode":"66333",
    "sg:province":"Saarland",
    "wof:name":"Scherer B\u00dcroelektronik Gmbh",
    "wof:placetype":"venue"
},
  "geometry": {"coordinates":[6.8312082291,49.2487220764],"type":"Point"}
}