{
  "type": "Feature",
  "properties": {
    "iso:country":"DE",
    "sg:address":"Moritzstr. 16",
    "sg:city":"Bad Gandersheim",
    "sg:phone":"+49 5382/1231",
    "sg:postcode":"37581",
    "sg:province":"Niedersachsen",
    "wof:name":"Blumen H. Fischer",
    "wof:placetype":"venue"
},
  "geometry": {"coordinates":[10.024231,51.869808],"type":"Point"}
}