{
  "type": "Feature",
  "properties": {
    "iso:country":"DE",
    "sg:address":"Uferstr. 30",
    "sg:city":"Eschweiler",
    "sg:phone":"+49 2403/24949",
    "sg:postcode":"52249",
    "sg:province":"Nordrhein-Westfalen",
    "wof:name":"El Paso",
    "wof:placetype":"venue"
},
  "geometry": {"coordinates":[6.270318985,50.817363739],"type":"Point"}
}