{
  "type": "Feature",
  "properties": {
    "iso:country":"DE",
    "sg:address":"Am Waldgraben 6",
    "sg:city":"Hanau",
    "sg:phone":"+49 6181/571227",
    "sg:postcode":"63457",
    "sg:province":"Hessen",
    "wof:name":"Werner Funk",
    "wof:placetype":"venue"
},
  "geometry": {"coordinates":[8.9473485947,50.1086387634],"type":"Point"}
}