{
  "type": "Feature",
  "properties": {
    "iso:country":"DE",
    "sg:address":"P\u00f6ttmeser Str. 152",
    "sg:city":"K\u00f6nigsmoos",
    "sg:phone":"+49 8433/628",
    "sg:postcode":"86669",
    "sg:province":"Bayern",
    "wof:name":"Fritz Mutzbauer",
    "wof:placetype":"venue"
},
  "geometry": {"coordinates":[11.141152,48.605728],"type":"Point"}
}