{
  "type": "Feature",
  "properties": {
    "iso:country":"DE",
    "sg:address":"Gewerbegebiet 5",
    "sg:city":"Vastorf",
    "sg:phone":"+49 4137/814290",
    "sg:postcode":"21397",
    "sg:province":"Niedersachsen",
    "wof:name":"Klinker & Naturstein-kontor Verwaltungs Gmbh",
    "wof:placetype":"venue"
},
  "geometry": {"coordinates":[10.532731,53.20784],"type":"Point"}
}