{
  "type": "Feature",
  "properties": {
    "iso:country":"DE",
    "sg:address":"Hafenstr. 140",
    "sg:city":"Bremerhaven",
    "sg:phone":"+49 4947/15970",
    "sg:postcode":"27576",
    "sg:province":"Bremen",
    "wof:name":"Nordsee-zeitung Gmbh",
    "wof:placetype":"venue"
},
  "geometry": {"coordinates":[8.5859498978,53.5591850281],"type":"Point"}
}