{
  "type": "Feature",
  "properties": {
    "iso:country":"DE",
    "sg:address":"Postfach 2065",
    "sg:city":"Worms",
    "sg:phone":"+49 6241/853349",
    "sg:postcode":"67510",
    "sg:province":"Rheinland-Pfalz",
    "wof:name":"Zeitschriften-lesesaal",
    "wof:placetype":"venue"
},
  "geometry": {"coordinates":[8.35791,49.630638],"type":"Point"}
}