{
  "type": "Feature",
  "properties": {
    "iso:country":"DE",
    "sg:address":"Im Gleisdreieck 36",
    "sg:city":"L\u00fcbeck",
    "sg:phone":"+49 451/66079",
    "sg:postcode":"23566",
    "sg:province":"Schleswig-Holstein",
    "wof:name":"Gebr. Schoer Maschinenbau Gmbh",
    "wof:placetype":"venue"
},
  "geometry": {"coordinates":[10.743758,53.865154],"type":"Point"}
}