{
  "type": "Feature",
  "properties": {
    "iso:country":"DE",
    "sg:address":"Haseng\u00e4rtlestr.",
    "sg:city":"Aulendorf",
    "sg:postcode":"88326",
    "sg:province":"Baden-W\u00fcrttemberg",
    "wof:name":"Aktiv-markt Bernd",
    "wof:placetype":"venue"
},
  "geometry": {"coordinates":[9.6382045746,47.9438438416],"type":"Point"}
}