{
  "type": "Feature",
  "properties": {
    "iso:country":"DE",
    "sg:address":"Hauptstr. 45",
    "sg:city":"Billigheim-Ingenheim",
    "sg:phone":"+49 6349/7045",
    "sg:postcode":"76831",
    "sg:province":"Rheinland-Pfalz",
    "wof:name":"Hotel-restaurant Pf\u00e4lzer Hof",
    "wof:placetype":"venue"
},
  "geometry": {"coordinates":[8.0321235657,49.2040672302],"type":"Point"}
}