{
  "type": "Feature",
  "properties": {
    "iso:country":"DE",
    "sg:address":"Georgstr. 14",
    "sg:city":"Eisfeld",
    "sg:phone":"+49 3686/3710",
    "sg:postcode":"98673",
    "sg:province":"Th\u00fcringen",
    "wof:name":"Docter-optic-eisfeld Gmbh",
    "wof:placetype":"venue"
},
  "geometry": {"coordinates":[10.9076375961,50.4228553772],"type":"Point"}
}