{
  "type": "Feature",
  "properties": {
    "iso:country":"DE",
    "sg:address":"Am Poseckschen Garten 1",
    "sg:city":"Weimar",
    "sg:phone":"+49 3643/202789",
    "sg:postcode":"99423",
    "sg:province":"Th\u00fcringen",
    "wof:name":"Gz Gartenzentrum Weimar Gmbh",
    "wof:placetype":"venue"
},
  "geometry": {"coordinates":[11.324448,50.974895],"type":"Point"}
}