{
  "type": "Feature",
  "properties": {
    "iso:country":"DE",
    "sg:address":"Dorfstr. 56",
    "sg:city":"G\u00f6mnigk",
    "sg:phone":"+49 33844/311",
    "sg:postcode":"14822",
    "sg:province":"Brandenburg",
    "wof:name":"Kurt Ebert Fliesenleger Gmbh",
    "wof:placetype":"venue"
},
  "geometry": {"coordinates":[12.7360029221,52.1692047119],"type":"Point"}
}