{
  "type": "Feature",
  "properties": {
    "iso:country":"DE",
    "sg:address":"Lippetor 3",
    "sg:city":"Dorsten",
    "sg:phone":"+49 2362/22800",
    "sg:postcode":"46282",
    "sg:province":"Nordrhein-Westfalen",
    "wof:name":"Gebr\u00fcder Schwanz Gmbh",
    "wof:placetype":"venue"
},
  "geometry": {"coordinates":[6.9634737968,51.6607284546],"type":"Point"}
}