{
  "type": "Feature",
  "properties": {
    "iso:country":"DE",
    "sg:address":"Falkenstr. 4",
    "sg:city":"Oppenweiler",
    "sg:phone":"+49 7191",
    "sg:postcode":"71570",
    "sg:province":"Baden-W\u00fcrttemberg",
    "wof:name":"Slt-siteko Lichttechnik Vertriebs Gmbh",
    "wof:placetype":"venue"
},
  "geometry": {"coordinates":[9.4631958008,48.9884986877],"type":"Point"}
}