{
  "type": "Feature",
  "properties": {
    "iso:country":"DE",
    "sg:address":"Alter Bannweg 18",
    "sg:city":"Konstanz",
    "sg:phone":"+49 7531/55495",
    "sg:postcode":"78467",
    "sg:province":"Baden-W\u00fcrttemberg",
    "wof:name":"Anna G\u00fcnther Architektin",
    "wof:placetype":"venue"
},
  "geometry": {"coordinates":[9.172362,47.679787],"type":"Point"}
}