{
  "type": "Feature",
  "properties": {
    "iso:country":"DE",
    "sg:address":"Wilhelm-Geiler-Str. 11 c",
    "sg:city":"Westerstede",
    "sg:phone":"+49 4488/1898",
    "sg:postcode":"26655",
    "sg:province":"Niedersachsen",
    "wof:name":"Micompan Inh. Heino R\u00fctemann",
    "wof:placetype":"venue"
},
  "geometry": {"coordinates":[7.9296941757,53.2528038025],"type":"Point"}
}