{
  "type": "Feature",
  "properties": {
    "iso:country":"DE",
    "sg:address":"Karl-Marx-Str. 78",
    "sg:city":"Neuruppin",
    "sg:phone":"+49 3391/650531",
    "sg:postcode":"16816",
    "sg:province":"Brandenburg",
    "wof:name":"Dr. Fuchs Beteiligungs- Gesellschaft Mbh",
    "wof:placetype":"venue"
},
  "geometry": {"coordinates":[12.804347,52.923916],"type":"Point"}
}