{
  "type": "Feature",
  "properties": {
    "iso:country":"DE",
    "sg:address":"Eisenbahnstr. 9 a",
    "sg:city":"Schliengen",
    "sg:phone":"+49 7635/477",
    "sg:postcode":"79418",
    "sg:province":"Baden-W\u00fcrttemberg",
    "wof:name":"Restaurant Krone",
    "wof:placetype":"venue"
},
  "geometry": {"coordinates":[7.5759072304,47.7557983398],"type":"Point"}
}