{
  "type": "Feature",
  "properties": {
    "iso:country":"DE",
    "sg:address":"Gutenbergstr. 79",
    "sg:city":"Kiel",
    "sg:phone":"+49 431/16920",
    "sg:postcode":"24116",
    "sg:province":"Schleswig-Holstein",
    "wof:name":"Amt F\u00fcr Abfallwirtschaft Und Stra\u00dfenreinigung",
    "wof:placetype":"venue"
},
  "geometry": {"coordinates":[10.1130943298,54.3327255249],"type":"Point"}
}