{
  "type": "Feature",
  "properties": {
    "iso:country":"DE",
    "sg:address":"Geisaer Str. 25",
    "sg:city":"Dermbach",
    "sg:postcode":"36466",
    "sg:province":"Th\u00fcringen",
    "wof:name":"Katholisches Pfarramt Dermbach",
    "wof:placetype":"venue"
},
  "geometry": {"coordinates":[10.1198196411,50.7164802551],"type":"Point"}
}