{
  "type": "Feature",
  "properties": {
    "iso:country":"DE",
    "sg:address":"Holbeinstr. 67",
    "sg:city":"Reutlingen",
    "sg:phone":"+49 7121/311984",
    "sg:postcode":"72760",
    "sg:province":"Baden-W\u00fcrttemberg",
    "wof:name":"Him-ke Betrieb Von Fahrzeugwaschanlagen Gmbh",
    "wof:placetype":"venue"
},
  "geometry": {"coordinates":[9.20013,48.510544],"type":"Point"}
}