{
  "type": "Feature",
  "properties": {
    "iso:country":"DE",
    "sg:address":"Hauptstr. 77",
    "sg:city":"H\u00f6nningen",
    "sg:phone":"+49 2643/6440",
    "sg:postcode":"53506",
    "sg:province":"Rheinland-Pfalz",
    "wof:name":"H. Kreucher",
    "wof:placetype":"venue"
},
  "geometry": {"coordinates":[6.959197998,50.473487854],"type":"Point"}
}