{
  "type": "Feature",
  "properties": {
    "iso:country":"DE",
    "sg:address":"Lippestr. 4",
    "sg:city":"Dorsten",
    "sg:phone":"+49 2362/22360",
    "sg:postcode":"46282",
    "sg:province":"Nordrhein-Westfalen",
    "wof:name":"Kloster-apotheke",
    "wof:placetype":"venue"
},
  "geometry": {"coordinates":[6.963888,51.660709],"type":"Point"}
}