{
  "type": "Feature",
  "properties": {
    "iso:country":"DE",
    "sg:address":"Poststr. 90",
    "sg:city":"Donzdorf",
    "sg:phone":"+49 7162/928730",
    "sg:postcode":"73072",
    "sg:province":"Baden-W\u00fcrttemberg",
    "wof:name":"Schneider L\u00e4rmschutztechnik Gmbh",
    "wof:placetype":"venue"
},
  "geometry": {"coordinates":[9.80281353,48.6847686768],"type":"Point"}
}