{
  "type": "Feature",
  "properties": {
    "iso:country":"DE",
    "sg:address":"Sandkuhlenweg 11",
    "sg:city":"D\u00fclmen",
    "sg:phone":"+49 2594/2761",
    "sg:postcode":"48249",
    "sg:province":"Nordrhein-Westfalen",
    "wof:name":"Johannes Wietheger Innenarchitekt",
    "wof:placetype":"venue"
},
  "geometry": {"coordinates":[7.287234,51.83099],"type":"Point"}
}