{
  "type": "Feature",
  "properties": {
    "iso:country":"DE",
    "sg:address":"St.-Lorenz-Str. 6",
    "sg:city":"Donaueschingen",
    "sg:phone":"+49 771/2513",
    "sg:postcode":"78166",
    "sg:province":"Baden-W\u00fcrttemberg",
    "wof:name":"Martin Neufeldt",
    "wof:placetype":"venue"
},
  "geometry": {"coordinates":[8.494481,47.954361],"type":"Point"}
}