{
  "type": "Feature",
  "properties": {
    "iso:country":"DE",
    "sg:address":"Rainr\u00f6der Weg 55",
    "sg:city":"Grebenau",
    "sg:phone":"+49 6646/518",
    "sg:postcode":"36323",
    "sg:province":"Hessen",
    "wof:name":"Georg Becker",
    "wof:placetype":"venue"
},
  "geometry": {"coordinates":[9.4127464294,50.7187309265],"type":"Point"}
}