{
  "type": "Feature",
  "properties": {
    "iso:country":"DE",
    "sg:address":"Marx-Wadle-Stra\u00dfe 12",
    "sg:city":"M\u00fcnchweiler/Rodalb",
    "sg:phone":"+49 6395/8352",
    "sg:postcode":"66981",
    "sg:province":"Rheinland-Pfalz",
    "wof:name":"Gewo - Gro\u00dfhandel Werkstattbedarf",
    "wof:placetype":"venue"
},
  "geometry": {"coordinates":[7.7061710358,49.2181053162],"type":"Point"}
}