{
  "type": "Feature",
  "properties": {
    "iso:country":"DE",
    "sg:address":"Kolpingstr. 12",
    "sg:city":"Hagen",
    "sg:phone":"+49 5405/7377",
    "sg:postcode":"49170",
    "sg:province":"Niedersachsen",
    "wof:name":"Rich. Schulte To B\u00fchne",
    "wof:placetype":"venue"
},
  "geometry": {"coordinates":[7.9803700447,52.1976203918],"type":"Point"}
}