{
  "type": "Feature",
  "properties": {
    "iso:country":"DE",
    "sg:address":"Brahmsallee 18",
    "sg:city":"Hamburg",
    "sg:postcode":"20144",
    "sg:province":"Hamburg",
    "wof:name":"Nerissa Ag",
    "wof:placetype":"venue"
},
  "geometry": {"coordinates":[9.982085228,53.5741119385],"type":"Point"}
}