{
  "type": "Feature",
  "properties": {
    "iso:country":"DE",
    "sg:address":"Flutstr. 60",
    "sg:city":"Kleve",
    "sg:phone":"+49 2821/75510",
    "sg:postcode":"47533",
    "sg:province":"Nordrhein-Westfalen",
    "wof:name":"Pari-autoteile Verwaltungs- Gmbh",
    "wof:placetype":"venue"
},
  "geometry": {"coordinates":[6.1399841309,51.7955780029],"type":"Point"}
}