{
  "type": "Feature",
  "properties": {
    "iso:country":"DE",
    "sg:address":"Georgsdorfer Str. 4",
    "sg:city":"Twist",
    "sg:phone":"+49 5946/506",
    "sg:postcode":"49767",
    "sg:province":"Niedersachsen",
    "wof:name":"Hans Rothl\u00fcbbers",
    "wof:placetype":"venue"
},
  "geometry": {"coordinates":[7.089476,52.609501],"type":"Point"}
}