{
  "type": "Feature",
  "properties": {
    "iso:country":"DE",
    "sg:address":"Pfandhausstr. 11",
    "sg:city":"Fulda",
    "sg:phone":"+49 661/73334",
    "sg:postcode":"36037",
    "sg:province":"Hessen",
    "wof:name":"B. Zwergel-gl\u00e4ser Steuerberater",
    "wof:placetype":"venue"
},
  "geometry": {"coordinates":[9.674949646,50.5522499084],"type":"Point"}
}