{
  "type": "Feature",
  "properties": {
    "iso:country":"DE",
    "sg:address":"Kocheler Str. 14",
    "sg:city":"Benediktbeuern",
    "sg:phone":"+49 8857/8170",
    "sg:postcode":"83671",
    "sg:province":"Bayern",
    "wof:name":"Ingenieurb\u00fcro Christian Hempel Gmbh",
    "wof:placetype":"venue"
},
  "geometry": {"coordinates":[11.4111385345,47.7064590454],"type":"Point"}
}