{
  "type": "Feature",
  "properties": {
    "iso:country":"DE",
    "sg:address":"Hauptstr. 38",
    "sg:city":"Wienhausen",
    "sg:phone":"+49 5149/394",
    "sg:postcode":"29342",
    "sg:province":"Niedersachsen",
    "wof:name":"Albert Hohnemann",
    "wof:placetype":"venue"
},
  "geometry": {"coordinates":[10.194019,52.577763],"type":"Point"}
}