{
  "type": "Feature",
  "properties": {
    "iso:country":"DE",
    "sg:address":"Werler Str. 24",
    "sg:city":"Unna",
    "sg:phone":"+49 2303/40348",
    "sg:postcode":"59423",
    "sg:province":"Nordrhein-Westfalen",
    "wof:name":"Mav Filter- Und Umwelttechnik Gmbh",
    "wof:placetype":"venue"
},
  "geometry": {"coordinates":[7.719812,51.536037],"type":"Point"}
}