{
  "type": "Feature",
  "properties": {
    "iso:country":"DE",
    "sg:address":"Dr.-Lauter-Str. 2",
    "sg:city":"Memmingen",
    "sg:phone":"+49 8331/9750",
    "sg:postcode":"87700",
    "sg:province":"Bayern",
    "wof:name":"Hans Kolb Wellpappe Gmbh & Co.",
    "wof:placetype":"venue"
},
  "geometry": {"coordinates":[10.1593341827,47.9949455261],"type":"Point"}
}