{
  "type": "Feature",
  "properties": {
    "iso:country":"DE",
    "sg:address":"Heberndorf 89",
    "sg:city":"Wurzbach",
    "sg:phone":"+49 36652/22306",
    "sg:postcode":"07343",
    "sg:province":"Th\u00fcringen",
    "wof:name":"Horst Schilling Bau Gmbh",
    "wof:placetype":"venue"
},
  "geometry": {"coordinates":[11.5105209351,50.4858436584],"type":"Point"}
}