{
  "type": "Feature",
  "properties": {
    "iso:country":"DE",
    "sg:address":"K\u00e4mpenstr. 4",
    "sg:city":"Paderborn",
    "sg:phone":"+49 5254/953131",
    "sg:postcode":"33106",
    "sg:province":"Nordrhein-Westfalen",
    "wof:name":"H & O Hausbau Gmbh",
    "wof:placetype":"venue"
},
  "geometry": {"coordinates":[8.683552,51.728867],"type":"Point"}
}