{
  "type": "Feature",
  "properties": {
    "iso:country":"DE",
    "sg:address":"Helenenstr. 68",
    "sg:city":"Essen",
    "sg:phone":"+49 201/6461979",
    "sg:postcode":"45143",
    "sg:province":"Nordrhein-Westfalen",
    "wof:name":"Edaphone, Mobilfunk Und Mehr, Handy Zubeh\u00f6r Welt",
    "wof:placetype":"venue"
},
  "geometry": {"coordinates":[6.982368,51.464226],"type":"Point"}
}