{
  "type": "Feature",
  "properties": {
    "iso:country":"DE",
    "sg:address":"Vogelsbergstr. 48",
    "sg:city":"Ulrichstein",
    "sg:phone":"+49 6645/468",
    "sg:postcode":"35327",
    "sg:province":"Hessen",
    "wof:name":"Kurt Schleuning",
    "wof:placetype":"venue"
},
  "geometry": {"coordinates":[9.2221546173,50.6092300415],"type":"Point"}
}