{
  "type": "Feature",
  "properties": {
    "iso:country":"DE",
    "sg:address":"Obstweg 1",
    "sg:city":"Lauf",
    "sg:phone":"+49 9123/85758",
    "sg:postcode":"91207",
    "sg:province":"Bayern",
    "wof:name":"Petra Ringler",
    "wof:placetype":"venue"
},
  "geometry": {"coordinates":[11.2608718872,49.4978065491],"type":"Point"}
}