{
  "type": "Feature",
  "properties": {
    "iso:country":"DE",
    "sg:address":"Bahnhofstr. 3",
    "sg:city":"Dermbach",
    "sg:phone":"+49 36964/7581",
    "sg:postcode":"36466",
    "sg:province":"Th\u00fcringen",
    "wof:name":"Nkd Textilhandel",
    "wof:placetype":"venue"
},
  "geometry": {"coordinates":[10.1219081879,50.7136077881],"type":"Point"}
}