{
  "type": "Feature",
  "properties": {
    "iso:country":"DE",
    "sg:address":"Rockenbrunn 5",
    "sg:city":"R\u00f6thenbach",
    "sg:phone":"+49 9120/181733",
    "sg:postcode":"90552",
    "sg:province":"Bayern",
    "wof:name":"Konrad Kuchlbauer",
    "wof:placetype":"venue"
},
  "geometry": {"coordinates":[11.293567,49.4678],"type":"Point"}
}