{
  "type": "Feature",
  "properties": {
    "iso:country":"DE",
    "sg:address":"Heinrich-Osterath-Str. 256",
    "sg:city":"Hamburg",
    "sg:phone":"+49 40/7372270",
    "sg:postcode":"21037",
    "sg:province":"Hamburg",
    "wof:name":"Paddel Meier",
    "wof:placetype":"venue"
},
  "geometry": {"coordinates":[10.1399269104,53.456993103],"type":"Point"}
}