{
  "type": "Feature",
  "properties": {
    "iso:country":"DE",
    "sg:address":"Schwanseestr. 143",
    "sg:city":"Weimar",
    "sg:phone":"+49 4936/4356604",
    "sg:postcode":"99427",
    "sg:province":"Th\u00fcringen",
    "wof:name":"Coca Cola Erfrischungsgetr\u00c4nke Ag",
    "wof:placetype":"venue"
},
  "geometry": {"coordinates":[11.2965250015,50.9850158691],"type":"Point"}
}