{
  "type": "Feature",
  "properties": {
    "iso:country":"DE",
    "sg:address":"Keltenstr. 5",
    "sg:city":"Bad Homburg",
    "sg:phone":"+49 6172/456298",
    "sg:postcode":"61348",
    "sg:province":"Hessen",
    "wof:name":"Hildegard Neufeld",
    "wof:placetype":"venue"
},
  "geometry": {"coordinates":[8.627240181,50.2229881287],"type":"Point"}
}