{
  "type": "Feature",
  "properties": {
    "iso:country":"DE",
    "sg:address":"Neippergstr. 20",
    "sg:city":"Stuttgart",
    "sg:phone":"+49 711/818638",
    "sg:postcode":"70469",
    "sg:province":"Baden-W\u00fcrttemberg",
    "wof:name":"Irene Skalitz",
    "wof:placetype":"venue"
},
  "geometry": {"coordinates":[9.153029,48.808125],"type":"Point"}
}