{
  "type": "Feature",
  "properties": {
    "iso:country":"DE",
    "sg:address":"Westkampweg 81",
    "sg:city":"Bielefeld",
    "sg:phone":"+49 521/402044",
    "sg:postcode":"33659",
    "sg:province":"Nordrhein-Westfalen",
    "wof:name":"Schule F\u00fcr K\u00f6rperbehinderte",
    "wof:placetype":"venue"
},
  "geometry": {"coordinates":[8.5483732224,51.9556045532],"type":"Point"}
}