{
  "type": "Feature",
  "properties": {
    "iso:country":"DE",
    "sg:address":"Oskar-Mayer-Str. 7",
    "sg:city":"N\u00f6rdlingen",
    "sg:phone":"+49 9081/24746",
    "sg:postcode":"86720",
    "sg:province":"Bayern",
    "wof:name":"Latino & Forcillo Gmbh",
    "wof:placetype":"venue"
},
  "geometry": {"coordinates":[10.4931259155,48.8471603394],"type":"Point"}
}