{
  "type": "Feature",
  "properties": {
    "iso:country":"DE",
    "sg:address":"Querstr. 11",
    "sg:city":"Friedberg",
    "sg:phone":"+49 6031/12211",
    "sg:postcode":"61169",
    "sg:province":"Hessen",
    "wof:name":"Planung Und Baubetreuungs Gmbh",
    "wof:placetype":"venue"
},
  "geometry": {"coordinates":[8.766044,50.333076],"type":"Point"}
}