{
  "type": "Feature",
  "properties": {
    "iso:country":"DE",
    "sg:address":"Petersbergstr. 7 1/2",
    "sg:city":"Bruckm\u00fchl",
    "sg:phone":"+49 8062/6709",
    "sg:postcode":"83052",
    "sg:province":"Bayern",
    "wof:name":"Josef Wei\u00dfenbacher",
    "wof:placetype":"venue"
},
  "geometry": {"coordinates":[11.9151687622,47.8826522827],"type":"Point"}
}