{
  "type": "Feature",
  "properties": {
    "iso:country":"DE",
    "sg:address":"Kurf\u00fcrstenstr. 5 a",
    "sg:city":"Mainz",
    "sg:phone":"+49 6131/671061",
    "sg:postcode":"55118",
    "sg:province":"Rheinland-Pfalz",
    "wof:name":"Alfred Hebel & Sohn Gmbh",
    "wof:placetype":"venue"
},
  "geometry": {"coordinates":[8.258751,50.005432],"type":"Point"}
}