{
  "type": "Feature",
  "properties": {
    "iso:country":"DE",
    "sg:address":"Am Kesselrasen 2a",
    "sg:city":"Haina",
    "sg:phone":"+49 36948/21297",
    "sg:postcode":"98631",
    "sg:province":"Th\u00fcringen",
    "wof:name":"Lik\u00f6rfabrik Arno Bechmann Inh. Klaus Erkenbrecher Ek",
    "wof:placetype":"venue"
},
  "geometry": {"coordinates":[10.4379119873,50.4555702209],"type":"Point"}
}