{
  "type": "Feature",
  "properties": {
    "iso:country":"DE",
    "sg:address":"Hohler Weg 6",
    "sg:city":"Warstein",
    "sg:phone":"+49 2902/71050",
    "sg:postcode":"59581",
    "sg:province":"Nordrhein-Westfalen",
    "wof:name":"Hirsch-apotheke Inh. Dirk Sch\u00fcrmann",
    "wof:placetype":"venue"
},
  "geometry": {"coordinates":[8.330906,51.48167],"type":"Point"}
}