{
  "type": "Feature",
  "properties": {
    "iso:country":"DE",
    "sg:address":"Frizstr. 1",
    "sg:city":"Fellbach",
    "sg:phone":"+49 711/580455",
    "sg:postcode":"70734",
    "sg:province":"Baden-W\u00fcrttemberg",
    "wof:name":"Erwin Winkle",
    "wof:placetype":"venue"
},
  "geometry": {"coordinates":[9.2778501511,48.8118782043],"type":"Point"}
}