{
  "type": "Feature",
  "properties": {
    "iso:country":"DE",
    "sg:address":"Weierstr. 34",
    "sg:city":"Langerwehe",
    "sg:phone":"+49 2423/4425",
    "sg:postcode":"52379",
    "sg:province":"Nordrhein-Westfalen",
    "wof:name":"Herm. Sp\u00f6lgen",
    "wof:placetype":"venue"
},
  "geometry": {"coordinates":[6.4052348137,50.8026771545],"type":"Point"}
}