{
  "type": "Feature",
  "properties": {
    "iso:country":"DE",
    "sg:address":"Gro\u00dfe Kampstr. 8",
    "sg:city":"Sehnde",
    "sg:phone":"+49 5138/3877",
    "sg:postcode":"31319",
    "sg:province":"Niedersachsen",
    "wof:name":"Wilhelm Gellermann",
    "wof:placetype":"venue"
},
  "geometry": {"coordinates":[9.929439,52.31781],"type":"Point"}
}