{
  "type": "Feature",
  "properties": {
    "iso:country":"DE",
    "sg:address":"Am Ostbahnhof 1",
    "sg:city":"Aurich",
    "sg:phone":"+49 4941/2632",
    "sg:postcode":"26603",
    "sg:province":"Niedersachsen",
    "wof:name":"Druckerei Meyer Gmbh",
    "wof:placetype":"venue"
},
  "geometry": {"coordinates":[7.4928011894,53.4673118591],"type":"Point"}
}