{
  "type": "Feature",
  "properties": {
    "iso:country":"DE",
    "sg:address":"Ochsenfurter Str. 2",
    "sg:city":"Eibelstadt",
    "sg:phone":"+49 9303/90820",
    "sg:postcode":"97246",
    "sg:province":"Bayern",
    "wof:name":"Pieralisi Deutschland Gmbh",
    "wof:placetype":"venue"
},
  "geometry": {"coordinates":[10.003229,49.722492],"type":"Point"}
}