{
  "type": "Feature",
  "properties": {
    "iso:country":"DE",
    "sg:address":"Friedrichsh\u00f6ferstr. 22",
    "sg:city":"Meldorf",
    "sg:phone":"+49 4832/5022",
    "sg:postcode":"25704",
    "sg:province":"Schleswig-Holstein",
    "wof:name":"Bistro 22",
    "wof:placetype":"venue"
},
  "geometry": {"coordinates":[9.0703611374,54.0833702087],"type":"Point"}
}