{
  "type": "Feature",
  "properties": {
    "iso:country":"DE",
    "sg:address":"Carl-Zeiss-Str. 7",
    "sg:city":"G\u00fctersloh",
    "sg:phone":"+49 5241/600520",
    "sg:postcode":"33334",
    "sg:province":"Nordrhein-Westfalen",
    "wof:name":"Htg Transporte Gmbh",
    "wof:placetype":"venue"
},
  "geometry": {"coordinates":[8.413312912,51.9291381836],"type":"Point"}
}