{
  "type": "Feature",
  "properties": {
    "iso:country":"DE",
    "sg:address":"Spaldingstr. 110a",
    "sg:city":"Hamburg",
    "sg:phone":"+49 40/233800",
    "sg:postcode":"20097",
    "sg:province":"Hamburg",
    "wof:name":"Sixt Ag",
    "wof:placetype":"venue"
},
  "geometry": {"coordinates":[10.018081,53.549549],"type":"Point"}
}