{
  "type": "Feature",
  "properties": {
    "iso:country":"DE",
    "sg:address":"Wei\u00dfhausstr. 2",
    "sg:city":"Aachen",
    "sg:phone":"+49 4924/1600301",
    "sg:postcode":"52066",
    "sg:province":"Nordrhein-Westfalen",
    "wof:name":"Philips Gmbh",
    "wof:placetype":"venue"
},
  "geometry": {"coordinates":[6.083531,50.757526],"type":"Point"}
}