{
  "type": "Feature",
  "properties": {
    "iso:country":"DE",
    "sg:address":"Castroper Str. 254",
    "sg:city":"Datteln",
    "sg:phone":"+49 2363/61614",
    "sg:postcode":"45711",
    "sg:province":"Nordrhein-Westfalen",
    "wof:name":"Transporte Walter Steinweg Inh. Helene Steinweg E. Kfr.",
    "wof:placetype":"venue"
},
  "geometry": {"coordinates":[7.3312110901,51.6341667175],"type":"Point"}
}