{
  "type": "Feature",
  "properties": {
    "iso:country":"DE",
    "sg:address":"Densberger Str. 27",
    "sg:city":"Jesberg",
    "sg:phone":"+49 6695/1397",
    "sg:postcode":"34632",
    "sg:province":"Hessen",
    "wof:name":"Horst Dickhaut",
    "wof:placetype":"venue"
},
  "geometry": {"coordinates":[9.1407308578,50.9974021912],"type":"Point"}
}