{
  "type": "Feature",
  "properties": {
    "iso:country":"DE",
    "sg:address":"Industriestr 10",
    "sg:city":"L\u00fcbz",
    "sg:phone":"+49 38731/5050",
    "sg:postcode":"19386",
    "sg:province":"Mecklenburg-Vorpommern",
    "wof:name":"Hans-otto Schl\u00fcter Stahl- Und Rohrleitungsbau Gmbh",
    "wof:placetype":"venue"
},
  "geometry": {"coordinates":[12.026472,53.474663],"type":"Point"}
}