{
  "type": "Feature",
  "properties": {
    "iso:country":"DE",
    "sg:address":"Jahnstr. 11",
    "sg:city":"Hochheim",
    "sg:phone":"+49 6146/9734",
    "sg:postcode":"65239",
    "sg:province":"Hessen",
    "wof:name":"Hans Weilb\u00e4cher Gmbh",
    "wof:placetype":"venue"
},
  "geometry": {"coordinates":[8.3546152115,50.0160484314],"type":"Point"}
}