{
  "type": "Feature",
  "properties": {
    "iso:country":"DE",
    "sg:address":"St.-Longinus-Str. 10",
    "sg:city":"Weingarten",
    "sg:phone":"+49 751/556126",
    "sg:postcode":"88250",
    "sg:province":"Baden-W\u00fcrttemberg",
    "wof:name":"Rolf Deussen Ingenieurb\u00fcro",
    "wof:placetype":"venue"
},
  "geometry": {"coordinates":[9.646106,47.809597],"type":"Point"}
}