{
  "type": "Feature",
  "properties": {
    "iso:country":"DE",
    "sg:address":"Ulmer Str. 12",
    "sg:city":"Pfaffenhofen",
    "sg:phone":"+49 7302/3374",
    "sg:postcode":"89284",
    "sg:province":"Bayern",
    "wof:name":"Jakob Meier",
    "wof:placetype":"venue"
},
  "geometry": {"coordinates":[10.161385,48.352798],"type":"Point"}
}