{
  "type": "Feature",
  "properties": {
    "iso:country":"DE",
    "sg:address":"Lorenz-Schott-Str. 4",
    "sg:city":"Mainz-Kastel",
    "sg:phone":"+49 6134/71930",
    "sg:postcode":"55252",
    "sg:province":"Hessen",
    "wof:name":"Autinform Ag",
    "wof:placetype":"venue"
},
  "geometry": {"coordinates":[8.277438,50.026608],"type":"Point"}
}