{
  "type": "Feature",
  "properties": {
    "iso:country":"DE",
    "sg:address":"Marschweg 7",
    "sg:city":"Vechta",
    "sg:phone":"+49 4441/4314",
    "sg:postcode":"49377",
    "sg:province":"Niedersachsen",
    "wof:name":"P. Gerdes Agrarhandel Und Transporte Gmbh",
    "wof:placetype":"venue"
},
  "geometry": {"coordinates":[8.28321,52.723412],"type":"Point"}
}