{
  "type": "Feature",
  "properties": {
    "iso:country":"DE",
    "sg:address":"Gro\u00dfe Dammstr. 13",
    "sg:city":"Otterndorf",
    "sg:phone":"+49 4751/2844",
    "sg:postcode":"21762",
    "sg:province":"Niedersachsen",
    "wof:name":"Hans-dietrich Bardenhagen",
    "wof:placetype":"venue"
},
  "geometry": {"coordinates":[8.9013595581,53.8069229126],"type":"Point"}
}