{
  "type": "Feature",
  "properties": {
    "iso:country":"DE",
    "sg:address":"Rosenaustr. 4",
    "sg:city":"Markt Erlbach",
    "sg:phone":"+49 9106/437",
    "sg:postcode":"91459",
    "sg:province":"Bayern",
    "wof:name":"Helmuth Gr\u00fcnbaum",
    "wof:placetype":"venue"
},
  "geometry": {"coordinates":[10.6612052917,49.4927444458],"type":"Point"}
}