{
  "type": "Feature",
  "properties": {
    "iso:country":"DE",
    "sg:address":"Danziger Str. 10 a",
    "sg:city":"Hemer",
    "sg:phone":"+49 2372/94790",
    "sg:postcode":"58675",
    "sg:province":"Nordrhein-Westfalen",
    "wof:name":"Grundbesitz Sundwig Verwaltungsges. Mbh",
    "wof:placetype":"venue"
},
  "geometry": {"coordinates":[7.7701148987,51.374382019],"type":"Point"}
}