{
  "type": "Feature",
  "properties": {
    "iso:country":"DE",
    "sg:address":"Am Pferdemarkt 5",
    "sg:city":"Aurich",
    "sg:phone":"+49 4941/92290",
    "sg:postcode":"26603",
    "sg:province":"Niedersachsen",
    "wof:name":"Kaufhalle Ag",
    "wof:placetype":"venue"
},
  "geometry": {"coordinates":[7.4825139046,53.4729003906],"type":"Point"}
}