{
  "type": "Feature",
  "properties": {
    "iso:country":"DE",
    "sg:address":"Meierstr. 23a",
    "sg:city":"L\u00fcbeck",
    "sg:phone":"+49 451/84292",
    "sg:postcode":"23558",
    "sg:province":"Schleswig-Holstein",
    "wof:name":"Comrex Gmbh",
    "wof:placetype":"venue"
},
  "geometry": {"coordinates":[10.669328,53.862541],"type":"Point"}
}