{
  "type": "Feature",
  "properties": {
    "iso:country":"DE",
    "sg:address":"Frammersbach",
    "sg:city":"Fl\u00f6rsbachtal",
    "sg:phone":"+49 6057/1451",
    "sg:postcode":"63639",
    "sg:province":"Hessen",
    "wof:name":"Go\u00dfmann Ofenbau Gmbh",
    "wof:placetype":"venue"
},
  "geometry": {"coordinates":[9.4161500931,50.1301765442],"type":"Point"}
}