{
  "type": "Feature",
  "properties": {
    "iso:country":"DE",
    "sg:address":"Gallbergstr. 1",
    "sg:city":"Elmlohe",
    "sg:phone":"+49 4704/94990",
    "sg:postcode":"27624",
    "sg:province":"Niedersachsen",
    "wof:name":"Kastanienhof",
    "wof:placetype":"venue"
},
  "geometry": {"coordinates":[8.741404,53.586365],"type":"Point"}
}