{
  "type": "Feature",
  "properties": {
    "iso:country":"DE",
    "sg:address":"Robert-Koch-Str. 5",
    "sg:city":"Clausthal-Zellerfeld",
    "sg:phone":"+49 5323/7150",
    "sg:postcode":"38678",
    "sg:province":"Niedersachsen",
    "wof:name":"Stadtwerke Clausthal-zellerfeld Gmbh",
    "wof:placetype":"venue"
},
  "geometry": {"coordinates":[10.339345,51.811153],"type":"Point"}
}