{
  "type": "Feature",
  "properties": {
    "iso:country":"DE",
    "sg:address":"Neue Str. 4",
    "sg:city":"T\u00fcbingen",
    "sg:phone":"+49 7071/52266",
    "sg:postcode":"72070",
    "sg:province":"Baden-W\u00fcrttemberg",
    "wof:name":"Lunette Augenoptiker Gmbh",
    "wof:placetype":"venue"
},
  "geometry": {"coordinates":[9.056669,48.520638],"type":"Point"}
}