{
  "type": "Feature",
  "properties": {
    "iso:country":"DE",
    "sg:address":"Harffstr. 33a",
    "sg:city":"D\u00fcsseldorf",
    "sg:phone":"+49 211/480483",
    "sg:postcode":"40591",
    "sg:province":"Nordrhein-Westfalen",
    "wof:name":"Klimawart Gesellschaft Zur Wartung Von",
    "wof:placetype":"venue"
},
  "geometry": {"coordinates":[6.815466,51.197559],"type":"Point"}
}