{
  "type": "Feature",
  "properties": {
    "iso:country":"DE",
    "sg:address":"Heinrich-Heine-Str. 10",
    "sg:city":"Vetschau",
    "sg:phone":"+49 35433/70014",
    "sg:postcode":"03226",
    "sg:province":"Brandenburg",
    "wof:name":"Uwe Witsch",
    "wof:placetype":"venue"
},
  "geometry": {"coordinates":[14.0804872513,51.7791404724],"type":"Point"}
}