{
  "type": "Feature",
  "properties": {
    "iso:country":"DE",
    "sg:address":"Paderborner Str. 247",
    "sg:city":"G\u00fctersloh",
    "sg:phone":"+49 5209/2142",
    "sg:postcode":"33335",
    "sg:province":"Nordrhein-Westfalen",
    "wof:name":"Restaurant Siekh\u00e4nschen Inh. Ursula Reker",
    "wof:placetype":"venue"
},
  "geometry": {"coordinates":[8.4903612137,51.9116592407],"type":"Point"}
}