{
  "type": "Feature",
  "properties": {
    "iso:country":"DE",
    "sg:address":"Zachariasstr. 1",
    "sg:city":"Bad Honnef",
    "sg:phone":"+49 2224/80754",
    "sg:postcode":"53604",
    "sg:province":"Nordrhein-Westfalen",
    "wof:name":"H. Schmitt",
    "wof:placetype":"venue"
},
  "geometry": {"coordinates":[7.299973011,50.6736488342],"type":"Point"}
}