{
  "type": "Feature",
  "properties": {
    "iso:country":"DE",
    "sg:address":"Heimhuder Str. 70",
    "sg:city":"Hamburg",
    "sg:phone":"+49 40/4147840",
    "sg:postcode":"20148",
    "sg:province":"Hamburg",
    "wof:name":"Gesellschaft F\u00fcr Europ\u00e4ische Kommunikation Mbh",
    "wof:placetype":"venue"
},
  "geometry": {"coordinates":[9.993087,53.569008],"type":"Point"}
}