{
  "type": "Feature",
  "properties": {
    "iso:country":"DE",
    "sg:address":"Hessenring 26",
    "sg:city":"B\u00fcttelborn",
    "sg:phone":"+49 6152/52858",
    "sg:postcode":"64572",
    "sg:province":"Hessen",
    "wof:name":"Claudia Herzig Gbr",
    "wof:placetype":"venue"
},
  "geometry": {"coordinates":[8.526804924,49.8988838196],"type":"Point"}
}