{
  "type": "Feature",
  "properties": {
    "iso:country":"DE",
    "sg:address":"Alte Zeilen 6",
    "sg:city":"Essen",
    "sg:phone":"+49 201/515528",
    "sg:postcode":"45276",
    "sg:province":"Nordrhein-Westfalen",
    "wof:name":"Eiscafe Dolce Vita",
    "wof:placetype":"venue"
},
  "geometry": {"coordinates":[7.076114,51.447479],"type":"Point"}
}