{
  "type": "Feature",
  "properties": {
    "iso:country":"DE",
    "sg:address":"Schalksburgstr.",
    "sg:city":"Porta Westfalica",
    "sg:phone":"+49 571/72621",
    "sg:postcode":"32457",
    "sg:province":"Nordrhein-Westfalen",
    "wof:name":"Die Brille Augenoptik Gmbh",
    "wof:placetype":"venue"
},
  "geometry": {"coordinates":[8.9216346741,52.2392234802],"type":"Point"}
}