{
  "type": "Feature",
  "properties": {
    "iso:country":"DE",
    "sg:address":"Zum Nackenberg 10",
    "sg:city":"Reisbach",
    "sg:phone":"+49 8734/932172",
    "sg:postcode":"94419",
    "sg:province":"Bayern",
    "wof:name":"Benedikt Und Hildeg. Schreiner",
    "wof:placetype":"venue"
},
  "geometry": {"coordinates":[12.6178150177,48.5621109009],"type":"Point"}
}