{
  "type": "Feature",
  "properties": {
    "iso:country":"DE",
    "sg:address":"Ostring 58",
    "sg:city":"Bottrop",
    "sg:phone":"+49 2041/34587",
    "sg:postcode":"46238",
    "sg:province":"Nordrhein-Westfalen",
    "wof:name":"Barbara-apotheke",
    "wof:placetype":"venue"
},
  "geometry": {"coordinates":[6.94211,51.527802],"type":"Point"}
}