{
  "type": "Feature",
  "properties": {
    "iso:country":"DE",
    "sg:address":"Gollierstr. 28",
    "sg:city":"M\u00fcnchen",
    "sg:postcode":"80339",
    "sg:province":"Bayern",
    "wof:name":"Komo Projektierung Und Handel Gmbh",
    "wof:placetype":"venue"
},
  "geometry": {"coordinates":[11.541799,48.135864],"type":"Point"}
}