{
  "type": "Feature",
  "properties": {
    "iso:country":"DE",
    "sg:address":"Stockenstr. 19",
    "sg:city":"Bonn",
    "sg:phone":"+49 228/657690",
    "sg:postcode":"53113",
    "sg:province":"Nordrhein-Westfalen",
    "wof:name":"Restaurant Zebulon",
    "wof:placetype":"venue"
},
  "geometry": {"coordinates":[7.1037487984,50.7345352173],"type":"Point"}
}