{
  "type": "Feature",
  "properties": {
    "iso:country":"DE",
    "sg:address":"Schmiedelstr. 1",
    "sg:city":"Kitzingen",
    "sg:phone":"+49 9321/6569",
    "sg:postcode":"97318",
    "sg:province":"Bayern",
    "wof:name":"Traudls Schubkarren",
    "wof:placetype":"venue"
},
  "geometry": {"coordinates":[10.1613140106,49.7353591919],"type":"Point"}
}