{
  "type": "Feature",
  "properties": {
    "iso:country":"DE",
    "sg:address":"Am Kreuzacker 15",
    "sg:city":"Oberau",
    "sg:phone":"+49 8824/944094",
    "sg:postcode":"82496",
    "sg:province":"Bayern",
    "wof:name":"J. Brey",
    "wof:placetype":"venue"
},
  "geometry": {"coordinates":[11.1308698654,47.5593910217],"type":"Point"}
}