{
  "type": "Feature",
  "properties": {
    "iso:country":"DE",
    "sg:address":"Hans-de-Fries-Str. 63",
    "sg:city":"M\u00f6nchengladbach",
    "sg:phone":"+49 2166/984690",
    "sg:postcode":"41238",
    "sg:province":"Nordrhein-Westfalen",
    "wof:name":"Meerkamper B\u00e4ren",
    "wof:placetype":"venue"
},
  "geometry": {"coordinates":[6.4888029099,51.1654586792],"type":"Point"}
}