{
  "type": "Feature",
  "properties": {
    "iso:country":"DE",
    "sg:address":"Auwanne 23",
    "sg:city":"Karlstein",
    "sg:phone":"+49 6188/50916",
    "sg:postcode":"63791",
    "sg:province":"Bayern",
    "wof:name":"Schuller Gmbh Werk Dettingen",
    "wof:placetype":"venue"
},
  "geometry": {"coordinates":[9.035284996,50.0448684692],"type":"Point"}
}