{
  "type": "Feature",
  "properties": {
    "iso:country":"DE",
    "sg:address":"Sch\u00f6neb\u00fcrgstr. 6",
    "sg:city":"Crailsheim",
    "sg:phone":"+49 7951/5028",
    "sg:postcode":"74564",
    "sg:province":"Baden-W\u00fcrttemberg",
    "wof:name":"G\u00fcnter Hofmann Rechtsanwalt",
    "wof:placetype":"venue"
},
  "geometry": {"coordinates":[10.0754423141,49.1377639771],"type":"Point"}
}