{
  "type": "Feature",
  "properties": {
    "iso:country":"DE",
    "sg:address":"Bortenberg 7",
    "sg:city":"Domb\u00fchl",
    "sg:phone":"+49 9868/932114",
    "sg:postcode":"91601",
    "sg:province":"Bayern",
    "wof:name":"Stefan Gruber E. K.",
    "wof:placetype":"venue"
},
  "geometry": {"coordinates":[10.3178882599,49.2485923767],"type":"Point"}
}