{
  "type": "Feature",
  "properties": {
    "iso:country":"DE",
    "sg:address":"Lammsgasse 18",
    "sg:city":"N\u00fcrnberg",
    "sg:phone":"+49 911/221642",
    "sg:postcode":"90403",
    "sg:province":"Bayern",
    "wof:name":"Neon Zimmerhackel Inh. Kurt Zimmerhackel",
    "wof:placetype":"venue"
},
  "geometry": {"coordinates":[11.073103,49.456142],"type":"Point"}
}