{
  "type": "Feature",
  "properties": {
    "iso:country":"DE",
    "sg:address":"Walme 24-30",
    "sg:city":"Warburg",
    "sg:phone":"+49 5642",
    "sg:postcode":"34414",
    "sg:province":"Nordrhein-Westfalen",
    "wof:name":"Auto Forum R\u00f6hll Gmbh",
    "wof:placetype":"venue"
},
  "geometry": {"coordinates":[9.0054073334,51.5213470459],"type":"Point"}
}