{
  "type": "Feature",
  "properties": {
    "iso:country":"DE",
    "sg:address":"Freudenst\u00e4dter Str. 12",
    "sg:city":"Baiersbronn",
    "sg:phone":"+49 7442/81350",
    "sg:postcode":"72270",
    "sg:province":"Baden-W\u00fcrttemberg",
    "wof:name":"Buch & Kunst Hanspeter Burkard",
    "wof:placetype":"venue"
},
  "geometry": {"coordinates":[8.3704442978,48.5087814331],"type":"Point"}
}