{
  "type": "Feature",
  "properties": {
    "iso:country":"DE",
    "sg:address":"Lessingstr. 4",
    "sg:city":"Homburg",
    "sg:phone":"+49 6841/64730",
    "sg:postcode":"66424",
    "sg:province":"Saarland",
    "wof:name":"Wilfried Weber",
    "wof:placetype":"venue"
},
  "geometry": {"coordinates":[7.3338809013,49.3226203918],"type":"Point"}
}