{
  "type": "Feature",
  "properties": {
    "iso:country":"DE",
    "sg:address":"Liliencronstr. 1",
    "sg:city":"Stuttgart",
    "sg:postcode":"70619",
    "sg:province":"Baden-W\u00fcrttemberg",
    "wof:name":"Elterninitiative Sillenbuch Verein F\u00fcr Gemeinsame",
    "wof:placetype":"venue"
},
  "geometry": {"coordinates":[9.2137136459,48.7438011169],"type":"Point"}
}