{
  "type": "Feature",
  "properties": {
    "iso:country":"DE",
    "sg:address":"Dorfstr. 4",
    "sg:city":"Reddern",
    "sg:phone":"+49 35434/12929",
    "sg:postcode":"03229",
    "sg:province":"Brandenburg",
    "wof:name":"Ingenieurb\u00fcro F\u00fcr Freiraum- Planung Hohmann Und Partner",
    "wof:placetype":"venue"
},
  "geometry": {"coordinates":[14.028859,51.666965],"type":"Point"}
}