{
  "type": "Feature",
  "properties": {
    "iso:country":"DE",
    "sg:address":"Frankfurter Str. 166",
    "sg:city":"Troisdorf",
    "sg:phone":"+49 2241/77177",
    "sg:postcode":"53840",
    "sg:province":"Nordrhein-Westfalen",
    "wof:name":"Hotel An Der Aggerbr\u00fccke",
    "wof:placetype":"venue"
},
  "geometry": {"coordinates":[7.183619976,50.8123664856],"type":"Point"}
}