{
  "type": "Feature",
  "properties": {
    "iso:country":"DE",
    "sg:address":"D\u00fcsterpoth 16",
    "sg:city":"Soest",
    "sg:phone":"+49 2921/2126",
    "sg:postcode":"59494",
    "sg:province":"Nordrhein-Westfalen",
    "wof:name":"Werner-m. Gill Architekt",
    "wof:placetype":"venue"
},
  "geometry": {"coordinates":[8.114259,51.573936],"type":"Point"}
}