{
  "type": "Feature",
  "properties": {
    "iso:country":"DE",
    "sg:address":"Feldstr. 43",
    "sg:city":"Kalbe",
    "sg:postcode":"39624",
    "sg:province":"Sachsen-Anhalt",
    "wof:name":"Dieter Pregtz",
    "wof:placetype":"venue"
},
  "geometry": {"coordinates":[11.380877,52.654499],"type":"Point"}
}