{
  "type": "Feature",
  "properties": {
    "iso:country":"DE",
    "sg:address":"Schamerloh 12",
    "sg:city":"Warmsen",
    "sg:phone":"+49 5767/93163",
    "sg:postcode":"31606",
    "sg:province":"Niedersachsen",
    "wof:name":"H. Rohde",
    "wof:placetype":"venue"
},
  "geometry": {"coordinates":[8.8592252731,52.4277915955],"type":"Point"}
}