{
  "type": "Feature",
  "properties": {
    "iso:country":"DE",
    "sg:address":"Dirlenbacher Str. 200",
    "sg:city":"Freudenberg",
    "sg:phone":"+49 2734/61359",
    "sg:postcode":"57258",
    "sg:province":"Nordrhein-Westfalen",
    "wof:name":"Holzindustrie Hunsr\u00fcck Gmbh",
    "wof:placetype":"venue"
},
  "geometry": {"coordinates":[7.884375,50.875431],"type":"Point"}
}