{
  "type": "Feature",
  "properties": {
    "iso:country":"DE",
    "sg:address":"Hauptstr. 176",
    "sg:city":"Alfter",
    "sg:phone":"+49 228/7483777",
    "sg:postcode":"53347",
    "sg:province":"Nordrhein-Westfalen",
    "wof:name":"Mini Pizzeria Nino",
    "wof:placetype":"venue"
},
  "geometry": {"coordinates":[7.0220332146,50.7030906677],"type":"Point"}
}