{
  "type": "Feature",
  "properties": {
    "iso:country":"DE",
    "sg:address":"Spitalhof 8",
    "sg:city":"Rothenburg",
    "sg:postcode":"91541",
    "sg:province":"Bayern",
    "wof:name":"Reichsstadthalle",
    "wof:placetype":"venue"
},
  "geometry": {"coordinates":[10.179874,49.371441],"type":"Point"}
}