{
  "type": "Feature",
  "properties": {
    "iso:country":"DE",
    "sg:address":"Essenheimer Str. 65",
    "sg:city":"Mainz",
    "sg:phone":"+49 6131/34121",
    "sg:postcode":"55128",
    "sg:province":"Rheinland-Pfalz",
    "wof:name":"Joachim Hirt",
    "wof:placetype":"venue"
},
  "geometry": {"coordinates":[8.2417850494,49.9792976379],"type":"Point"}
}