{
  "type": "Feature",
  "properties": {
    "iso:country":"DE",
    "sg:address":"Hochstr. 35",
    "sg:city":"Bobingen",
    "sg:phone":"+49 8234/2025",
    "sg:postcode":"86399",
    "sg:province":"Bayern",
    "wof:name":"Kreis- Und Stadtsparkasse",
    "wof:placetype":"venue"
},
  "geometry": {"coordinates":[10.836058,48.273079],"type":"Point"}
}