{
  "type": "Feature",
  "properties": {
    "iso:country":"DE",
    "sg:address":"Hauptstr. 56",
    "sg:city":"Seeg",
    "sg:phone":"+49 8364/485",
    "sg:postcode":"87637",
    "sg:province":"Bayern",
    "wof:name":"Anni Faller",
    "wof:placetype":"venue"
},
  "geometry": {"coordinates":[10.6058349609,47.6529960632],"type":"Point"}
}