{
  "type": "Feature",
  "properties": {
    "iso:country":"DE",
    "sg:address":"Alte K\u00f6nigstr. 7",
    "sg:city":"Hamburg",
    "sg:phone":"+49 40/382387",
    "sg:postcode":"22767",
    "sg:province":"Hamburg",
    "wof:name":"Naefeke-aktenvernichtung",
    "wof:placetype":"venue"
},
  "geometry": {"coordinates":[9.938990593,53.547454834],"type":"Point"}
}