{
  "type": "Feature",
  "properties": {
    "iso:country":"DE",
    "sg:address":"Herrenstr. 1",
    "sg:city":"Ehrenkirchen",
    "sg:phone":"+49 7633/5344",
    "sg:postcode":"79238",
    "sg:province":"Baden-W\u00fcrttemberg",
    "wof:name":"K. Federle",
    "wof:placetype":"venue"
},
  "geometry": {"coordinates":[7.7419238091,47.9233322144],"type":"Point"}
}