{
  "type": "Feature",
  "properties": {
    "iso:country":"DE",
    "sg:address":"Griebelstr. 14",
    "sg:city":"R\u00f6mhild",
    "sg:phone":"+49 36948/20533",
    "sg:postcode":"98631",
    "sg:province":"Th\u00fcringen",
    "wof:name":"K. Theilig",
    "wof:placetype":"venue"
},
  "geometry": {"coordinates":[10.53903,50.39727],"type":"Point"}
}