{
  "type": "Feature",
  "properties": {
    "iso:country":"DE",
    "sg:address":"Hinterm Dorf 6",
    "sg:city":"Bergen",
    "sg:phone":"+49 5051/8873",
    "sg:postcode":"29303",
    "sg:province":"Niedersachsen",
    "wof:name":"Willi Marquardt",
    "wof:placetype":"venue"
},
  "geometry": {"coordinates":[9.981353,52.77272],"type":"Point"}
}