{
  "type": "Feature",
  "properties": {
    "iso:country":"DE",
    "sg:address":"Rosenpark 2",
    "sg:city":"Hattersheim",
    "sg:phone":"+49 6190/3032",
    "sg:postcode":"65795",
    "sg:province":"Hessen",
    "wof:name":"Dr. Med. Monika Simon \u00c4rztin F\u00fcr Innere Medizin",
    "wof:placetype":"venue"
},
  "geometry": {"coordinates":[8.4870281219,50.0735092163],"type":"Point"}
}