{
  "type": "Feature",
  "properties": {
    "iso:country":"DE",
    "sg:address":"Buschrosenweg 22",
    "sg:city":"M\u00fcnchen",
    "sg:postcode":"81377",
    "sg:province":"Bayern",
    "wof:name":"Ingeborg Ergenzinger",
    "wof:placetype":"venue"
},
  "geometry": {"coordinates":[11.4844141006,48.106842041],"type":"Point"}
}