{
  "type": "Feature",
  "properties": {
    "iso:country":"DE",
    "sg:address":"Wolfgang-Borchert-Str. 4",
    "sg:city":"Wendelstein",
    "sg:phone":"+49 9129/4349",
    "sg:postcode":"90530",
    "sg:province":"Bayern",
    "wof:name":"Klaus Fr\u00f6hlke Gmbh",
    "wof:placetype":"venue"
},
  "geometry": {"coordinates":[11.1573295593,49.3507080078],"type":"Point"}
}