{
  "type": "Feature",
  "properties": {
    "iso:country":"DE",
    "sg:address":"In der Donk 17",
    "sg:city":"D\u00fcsseldorf",
    "sg:phone":"+49 211/742410",
    "sg:postcode":"40599",
    "sg:province":"Nordrhein-Westfalen",
    "wof:name":"K\u00e4the Stein Steuerberaterin",
    "wof:placetype":"venue"
},
  "geometry": {"coordinates":[6.8652729988,51.1846160889],"type":"Point"}
}