{
  "type": "Feature",
  "properties": {
    "iso:country":"DE",
    "sg:address":"Honigr\u00fcckweg 15",
    "sg:city":"Sinntal",
    "sg:phone":"+49 6665/919070",
    "sg:postcode":"36391",
    "sg:province":"Hessen",
    "wof:name":"Helmut Maienschein Architekt",
    "wof:placetype":"venue"
},
  "geometry": {"coordinates":[9.608315,50.248268],"type":"Point"}
}