{
  "type": "Feature",
  "properties": {
    "iso:country":"DE",
    "sg:address":"Wellendinger Str 4",
    "sg:city":"Frittlingen",
    "sg:phone":"+49 7426/7448",
    "sg:postcode":"78665",
    "sg:province":"Baden-W\u00fcrttemberg",
    "wof:name":"Gebr. Dreher Gmbh",
    "wof:placetype":"venue"
},
  "geometry": {"coordinates":[8.705024,48.132595],"type":"Point"}
}