{
  "type": "Feature",
  "properties": {
    "iso:country":"DE",
    "sg:address":"Stephanstr. 60",
    "sg:city":"Berlin",
    "sg:phone":"+49 30/3957043",
    "sg:postcode":"10559",
    "sg:province":"Berlin",
    "wof:name":"Das Ninjutsu-dojo Rudi Langer",
    "wof:placetype":"venue"
},
  "geometry": {"coordinates":[13.3518342972,52.5342979431],"type":"Point"}
}