{
  "type": "Feature",
  "properties": {
    "iso:country":"DE",
    "sg:address":"Johannes-Kepler-Platz 2",
    "sg:city":"Potsdam",
    "sg:phone":"+49 331/6263362",
    "sg:postcode":"14480",
    "sg:province":"Brandenburg",
    "wof:name":"Hans-j\u00fcrgen Kernbach Rechtsanwalt",
    "wof:placetype":"venue"
},
  "geometry": {"coordinates":[13.131357193,52.3757705688],"type":"Point"}
}