{
  "type": "Feature",
  "properties": {
    "iso:country":"DE",
    "sg:address":"S\u00fcderstr. 77",
    "sg:city":"Hamburg",
    "sg:phone":"+49 40/23898180",
    "sg:postcode":"20097",
    "sg:province":"Hamburg",
    "wof:name":"M. Schmidt Immobilienmakler",
    "wof:placetype":"venue"
},
  "geometry": {"coordinates":[10.0286855698,53.5449676514],"type":"Point"}
}