{
  "type": "Feature",
  "properties": {
    "iso:country":"DE",
    "sg:address":"Im Bremer 20",
    "sg:city":"Neuwied",
    "sg:postcode":"56567",
    "sg:province":"Rheinland-Pfalz",
    "wof:name":"Kirmesgesellschaft Irlich 1970 E. V.",
    "wof:placetype":"venue"
},
  "geometry": {"coordinates":[7.4520478249,50.444026947],"type":"Point"}
}