{
  "type": "Feature",
  "properties": {
    "iso:country":"DE",
    "sg:address":"Wandersmannstr. 2 a",
    "sg:city":"Wiesbaden",
    "sg:phone":"+49 611/712552",
    "sg:postcode":"65205",
    "sg:province":"Hessen",
    "wof:name":"K. Engert",
    "wof:placetype":"venue"
},
  "geometry": {"coordinates":[8.299516,50.055141],"type":"Point"}
}