{
  "type": "Feature",
  "properties": {
    "iso:country":"DE",
    "sg:address":"Bachstr. 7",
    "sg:city":"Geseke",
    "sg:phone":"+49 2942/5479",
    "sg:postcode":"59590",
    "sg:province":"Nordrhein-Westfalen",
    "wof:name":"Sch\u00fctte Gmbh",
    "wof:placetype":"venue"
},
  "geometry": {"coordinates":[8.510443,51.640785],"type":"Point"}
}