{
  "type": "Feature",
  "properties": {
    "iso:country":"DE",
    "sg:address":"Arnold-Janssen-Str. 24",
    "sg:city":"Sankt Augustin",
    "sg:phone":"+49 2241/237365",
    "sg:postcode":"53757",
    "sg:province":"Nordrhein-Westfalen",
    "wof:name":"Steyler Missionswissensch. Institut",
    "wof:placetype":"venue"
},
  "geometry": {"coordinates":[7.18148,50.774342],"type":"Point"}
}