{
  "type": "Feature",
  "properties": {
    "iso:country":"DE",
    "sg:address":"Gutenbergstr. 19",
    "sg:city":"Oberhausen",
    "sg:phone":"+49 208/208374",
    "sg:postcode":"46045",
    "sg:province":"Nordrhein-Westfalen",
    "wof:name":"Elipse",
    "wof:placetype":"venue"
},
  "geometry": {"coordinates":[6.8490757942,51.4676399231],"type":"Point"}
}