{
  "type": "Feature",
  "properties": {
    "iso:country":"DE",
    "sg:address":"Binninger Str. 12",
    "sg:city":"Hilzingen",
    "sg:phone":"+49 7739/1589",
    "sg:postcode":"78247",
    "sg:province":"Baden-W\u00fcrttemberg",
    "wof:name":"R. G\u00f6lz",
    "wof:placetype":"venue"
},
  "geometry": {"coordinates":[8.7652368546,47.800075531],"type":"Point"}
}