{
  "type": "Feature",
  "properties": {
    "iso:country":"DE",
    "sg:address":"Im Langental",
    "sg:city":"Neunkirchen",
    "sg:phone":"+49 6821/94100",
    "sg:postcode":"66539",
    "sg:province":"Saarland",
    "wof:name":"Spedition Enkler Gmbh",
    "wof:placetype":"venue"
},
  "geometry": {"coordinates":[7.2393422127,49.3484458923],"type":"Point"}
}