{
  "type": "Feature",
  "properties": {
    "iso:country":"DE",
    "sg:address":"M\u00fchlackerstr. 29",
    "sg:city":"Weimar",
    "sg:phone":"+49 6424/4461",
    "sg:postcode":"35096",
    "sg:province":"Hessen",
    "wof:name":"S. Gutsche Laborbedarf",
    "wof:placetype":"venue"
},
  "geometry": {"coordinates":[8.695483,50.738533],"type":"Point"}
}