{
  "type": "Feature",
  "properties": {
    "iso:country":"DE",
    "sg:address":"Koppweg 23",
    "sg:city":"Dortmund",
    "sg:phone":"+49 231/9730060",
    "sg:postcode":"44229",
    "sg:province":"Nordrhein-Westfalen",
    "wof:name":"Dr. Erb & Partner Gesellschaft F\u00fcr Grundst\u00fccks- Und",
    "wof:placetype":"venue"
},
  "geometry": {"coordinates":[7.4650378227,51.4442825317],"type":"Point"}
}