{
  "type": "Feature",
  "properties": {
    "iso:country":"DE",
    "sg:address":"Rheinstr. 181 A",
    "sg:city":"Viersen",
    "sg:phone":"+49 2162/8635",
    "sg:postcode":"41749",
    "sg:province":"Nordrhein-Westfalen",
    "wof:name":"Kurt Koszescha Architekt",
    "wof:placetype":"venue"
},
  "geometry": {"coordinates":[6.390573,51.272602],"type":"Point"}
}