{
  "type": "Feature",
  "properties": {
    "iso:country":"DE",
    "sg:address":"K\u00f6nigsbr\u00fccker Str. 2",
    "sg:city":"Dresden",
    "sg:phone":"+49 351/8020505",
    "sg:postcode":"01099",
    "sg:province":"Sachsen",
    "wof:name":"B\u00e4rbel Wolf",
    "wof:placetype":"venue"
},
  "geometry": {"coordinates":[13.7470016479,51.0638160706],"type":"Point"}
}