{
  "type": "Feature",
  "properties": {
    "iso:country":"DE",
    "sg:address":"Postfach 246",
    "sg:city":"Sigmaringen",
    "sg:postcode":"72481",
    "sg:province":"Baden-W\u00fcrttemberg",
    "wof:name":"Hermann Boos Kg Eisenwaren",
    "wof:placetype":"venue"
},
  "geometry": {"coordinates":[9.21761,48.085983],"type":"Point"}
}