{
  "type": "Feature",
  "properties": {
    "iso:country":"DE",
    "sg:address":"B\u00e4ckerssiepen 3",
    "sg:city":"Altena",
    "sg:phone":"+49 2352/972971",
    "sg:postcode":"58762",
    "sg:province":"Nordrhein-Westfalen",
    "wof:name":"Pego Warenhandels Gmbh",
    "wof:placetype":"venue"
},
  "geometry": {"coordinates":[7.75607,51.298378],"type":"Point"}
}