{
  "type": "Feature",
  "properties": {
    "iso:country":"DE",
    "sg:address":"Beilsteinweg 8",
    "sg:city":"Lohr",
    "sg:phone":"+49 9352/4466",
    "sg:postcode":"97816",
    "sg:province":"Bayern",
    "wof:name":"Hermann Diel Elektromeister",
    "wof:placetype":"venue"
},
  "geometry": {"coordinates":[9.574995,50.003128],"type":"Point"}
}