{
  "type": "Feature",
  "properties": {
    "iso:country":"DE",
    "sg:address":"Kaiserstr. 44",
    "sg:city":"Radevormwald",
    "sg:phone":"+49 2195/91510",
    "sg:postcode":"42477",
    "sg:province":"Nordrhein-Westfalen",
    "wof:name":"Biesenbach Gmbh",
    "wof:placetype":"venue"
},
  "geometry": {"coordinates":[7.3532400131,51.2032279968],"type":"Point"}
}