{
  "type": "Feature",
  "properties": {
    "iso:country":"DE",
    "sg:address":"T\u00f6lzer Str. 30",
    "sg:city":"Gr\u00fcnwald",
    "sg:postcode":"82031",
    "sg:province":"Bayern",
    "wof:name":"Mola Gmbh & Co. Kg Verwaltungsgesellschaft",
    "wof:placetype":"venue"
},
  "geometry": {"coordinates":[11.520882,48.03437],"type":"Point"}
}