{
  "type": "Feature",
  "properties": {
    "iso:country":"DE",
    "sg:address":"Murrhardter Str. 55",
    "sg:city":"Welzheim",
    "sg:phone":"+49 7182/49153",
    "sg:postcode":"73642",
    "sg:province":"Baden-W\u00fcrttemberg",
    "wof:name":"Barrabas Grafik Gmbh",
    "wof:placetype":"venue"
},
  "geometry": {"coordinates":[9.633149,48.881435],"type":"Point"}
}