{
  "type": "Feature",
  "properties": {
    "iso:country":"DE",
    "sg:address":"Petzvalstr. 35",
    "sg:city":"Braunschweig",
    "sg:phone":"+49 531/377525",
    "sg:postcode":"38104",
    "sg:province":"Niedersachsen",
    "wof:name":"Rolf Weis B\u00fcrgel",
    "wof:placetype":"venue"
},
  "geometry": {"coordinates":[10.57434,52.289295],"type":"Point"}
}