{
  "type": "Feature",
  "properties": {
    "iso:country":"DE",
    "sg:address":"Doblerstr. 10",
    "sg:city":"T\u00fcbingen",
    "sg:phone":"+49 7071/23978",
    "sg:postcode":"72074",
    "sg:province":"Baden-W\u00fcrttemberg",
    "wof:name":"Peter Zoll Rechtsanwalt",
    "wof:placetype":"venue"
},
  "geometry": {"coordinates":[9.0594215393,48.5219192505],"type":"Point"}
}