{
  "type": "Feature",
  "properties": {
    "iso:country":"DE",
    "sg:address":"Bahnhofstr. 36",
    "sg:city":"Karlsruhe",
    "sg:phone":"+49 721/386263",
    "sg:postcode":"76137",
    "sg:province":"Baden-W\u00fcrttemberg",
    "wof:name":"Fotostudio Helfer",
    "wof:placetype":"venue"
},
  "geometry": {"coordinates":[8.3991613388,48.9966888428],"type":"Point"}
}