{
  "type": "Feature",
  "properties": {
    "iso:country":"DE",
    "sg:address":"Torgauer Str 43",
    "sg:city":"Annaburg",
    "sg:phone":"+49 35385/20303",
    "sg:postcode":"06925",
    "sg:province":"Sachsen-Anhalt",
    "wof:name":"Druckerei Steinbei\u00df",
    "wof:placetype":"venue"
},
  "geometry": {"coordinates":[13.043144,51.730328],"type":"Point"}
}