{
  "type": "Feature",
  "properties": {
    "iso:country":"DE",
    "sg:address":"Falkenweg 16",
    "sg:city":"Buchholz",
    "sg:phone":"+49 4187/321122",
    "sg:postcode":"21244",
    "sg:province":"Niedersachsen",
    "wof:name":"Brinkhaus Trockungs- Systeme Gmbh",
    "wof:placetype":"venue"
},
  "geometry": {"coordinates":[9.862565,53.288631],"type":"Point"}
}