{
  "type": "Feature",
  "properties": {
    "iso:country":"DE",
    "sg:address":"Knorrstr. 9",
    "sg:city":"Wilhelmshaven",
    "sg:phone":"+49 4421/37814",
    "sg:postcode":"26384",
    "sg:province":"Niedersachsen",
    "wof:name":"L. Neumann Tanzschule",
    "wof:placetype":"venue"
},
  "geometry": {"coordinates":[8.1263990402,53.5253334045],"type":"Point"}
}