{
  "type": "Feature",
  "properties": {
    "iso:country":"DE",
    "sg:address":"Saarbr\u00fccker Str.",
    "sg:city":"Mandelbachtal",
    "sg:phone":"+49 6803/2197",
    "sg:postcode":"66399",
    "sg:province":"Saarland",
    "wof:name":"Johann Gerum",
    "wof:placetype":"venue"
},
  "geometry": {"coordinates":[7.159792,49.217083],"type":"Point"}
}