{
  "type": "Feature",
  "properties": {
    "iso:country":"DE",
    "sg:address":"Bernhardstr. 98",
    "sg:city":"Chemnitz",
    "sg:phone":"+49 371/5619114",
    "sg:postcode":"09126",
    "sg:province":"Sachsen",
    "wof:name":"J. Kr\u00fcger",
    "wof:placetype":"venue"
},
  "geometry": {"coordinates":[12.950337,50.830002],"type":"Point"}
}