{
  "type": "Feature",
  "properties": {
    "iso:country":"DE",
    "sg:address":"H\u00f6ster Damm 2",
    "sg:city":"Lienen",
    "sg:phone":"+49 5481/94433",
    "sg:postcode":"49536",
    "sg:province":"Nordrhein-Westfalen",
    "wof:name":"Draht-placke Kg",
    "wof:placetype":"venue"
},
  "geometry": {"coordinates":[7.8964347839,52.1440887451],"type":"Point"}
}