{
  "type": "Feature",
  "properties": {
    "iso:country":"DE",
    "sg:address":"Industriestr 42-44",
    "sg:city":"Mittelbiberach",
    "sg:phone":"+49 7351/58010",
    "sg:postcode":"88441",
    "sg:province":"Baden-W\u00fcrttemberg",
    "wof:name":"Artur Reich Gmbh & Co",
    "wof:placetype":"venue"
},
  "geometry": {"coordinates":[9.7596502304,48.0930175781],"type":"Point"}
}