{
  "type": "Feature",
  "properties": {
    "iso:country":"DE",
    "sg:address":"Bismarckstr. 43 b",
    "sg:city":"Bitterfeld",
    "sg:phone":"+49 3493/23492",
    "sg:postcode":"06749",
    "sg:province":"Sachsen-Anhalt",
    "wof:name":"Rudi D\u00f6ring",
    "wof:placetype":"venue"
},
  "geometry": {"coordinates":[12.3188228607,51.6189804077],"type":"Point"}
}