{
  "type": "Feature",
  "properties": {
    "iso:country":"DE",
    "sg:address":"Wilhelm-Rausch-Strasse 9",
    "sg:city":"Peine",
    "sg:phone":"+49 5171/3666",
    "sg:postcode":"31228",
    "sg:province":"Niedersachsen",
    "wof:name":"Autohaus Maskos In Peine",
    "wof:placetype":"venue"
},
  "geometry": {"coordinates":[10.2432546616,52.3401298523],"type":"Point"}
}