{
  "type": "Feature",
  "properties": {
    "iso:country":"DE",
    "sg:address":"Boskopweg 30",
    "sg:city":"Stuttgart",
    "sg:phone":"+49 711/4093905",
    "sg:postcode":"70329",
    "sg:province":"Baden-W\u00fcrttemberg",
    "wof:name":"Dr. W. Geisslreither Gmbh",
    "wof:placetype":"venue"
},
  "geometry": {"coordinates":[9.2335176468,48.760635376],"type":"Point"}
}