{
  "type": "Feature",
  "properties": {
    "iso:country":"DE",
    "sg:address":"Am K\u00e4ppele 9",
    "sg:city":"B\u00f6blingen",
    "sg:phone":"+49 7031/25157",
    "sg:postcode":"71032",
    "sg:province":"Baden-W\u00fcrttemberg",
    "wof:name":"Rosemarie Sp\u00e4th",
    "wof:placetype":"venue"
},
  "geometry": {"coordinates":[9.017622,48.686089],"type":"Point"}
}