{
  "type": "Feature",
  "properties": {
    "iso:country":"DE",
    "sg:address":"Grauenbrunnenweg 12",
    "sg:city":"Leimen",
    "sg:phone":"+49 6224/71345",
    "sg:postcode":"69181",
    "sg:province":"Baden-W\u00fcrttemberg",
    "wof:name":"G. Refior Gmbh",
    "wof:placetype":"venue"
},
  "geometry": {"coordinates":[8.6979103088,49.3437728882],"type":"Point"}
}