{
  "type": "Feature",
  "properties": {
    "iso:country":"DE",
    "sg:address":"Bahnhofstr. 10",
    "sg:city":"Reken",
    "sg:phone":"+49 2864/1644",
    "sg:postcode":"48734",
    "sg:province":"Nordrhein-Westfalen",
    "wof:name":"Felix K\u00fcdde",
    "wof:placetype":"venue"
},
  "geometry": {"coordinates":[7.043328,51.806812],"type":"Point"}
}