{
  "type": "Feature",
  "properties": {
    "iso:country":"DE",
    "sg:address":"Am Sand 12",
    "sg:city":"Regen",
    "sg:phone":"+49 9921/3660",
    "sg:postcode":"94209",
    "sg:province":"Bayern",
    "wof:name":"H.-j. Pongratz",
    "wof:placetype":"venue"
},
  "geometry": {"coordinates":[13.125169,48.969547],"type":"Point"}
}