{
  "type": "Feature",
  "properties": {
    "iso:country":"DE",
    "sg:address":"Alte Heerstr. 5",
    "sg:city":"Wertheim",
    "sg:phone":"+49 9342/30880",
    "sg:postcode":"97877",
    "sg:province":"Baden-W\u00fcrttemberg",
    "wof:name":"Wanner Technik Gmbh",
    "wof:placetype":"venue"
},
  "geometry": {"coordinates":[9.528983,49.727993],"type":"Point"}
}