{
  "type": "Feature",
  "properties": {
    "iso:country":"DE",
    "sg:address":"Am Meerkamp 20",
    "sg:city":"Meerbusch",
    "sg:postcode":"40667",
    "sg:province":"Nordrhein-Westfalen",
    "wof:name":"Ute Mutlu Rechtsanw\u00e4ltin",
    "wof:placetype":"venue"
},
  "geometry": {"coordinates":[6.6910247803,51.2518959045],"type":"Point"}
}