{
  "type": "Feature",
  "properties": {
    "iso:country":"DE",
    "sg:address":"Rhein-Mosel-Str. 96",
    "sg:city":"Emmelshausen",
    "sg:phone":"+49 6747/6122",
    "sg:postcode":"56281",
    "sg:province":"Rheinland-Pfalz",
    "wof:name":"Rudolf Seus",
    "wof:placetype":"venue"
},
  "geometry": {"coordinates":[7.55137,50.155739],"type":"Point"}
}