{
  "type": "Feature",
  "properties": {
    "iso:country":"DE",
    "sg:address":"K\u00f6terwelt 1",
    "sg:city":"Dransfeld",
    "sg:phone":"+49 5502/3579",
    "sg:postcode":"37127",
    "sg:province":"Niedersachsen",
    "wof:name":"Friedrich Rehkop Architekt",
    "wof:placetype":"venue"
},
  "geometry": {"coordinates":[9.756504,51.501045],"type":"Point"}
}