{
  "type": "Feature",
  "properties": {
    "iso:country":"DE",
    "sg:address":"M\u00fchlgasse 16",
    "sg:city":"Lauchheim",
    "sg:phone":"+49 7363/921771",
    "sg:postcode":"73466",
    "sg:province":"Baden-W\u00fcrttemberg",
    "wof:name":"Eberhard Brenner Innenarchitekt",
    "wof:placetype":"venue"
},
  "geometry": {"coordinates":[10.24602,48.870949],"type":"Point"}
}