{
  "type": "Feature",
  "properties": {
    "iso:country":"DE",
    "sg:address":"Kirchstr. 10",
    "sg:city":"Lingen",
    "sg:phone":"+49 591/912420",
    "sg:postcode":"49808",
    "sg:province":"Niedersachsen",
    "wof:name":"Oldiges Wirtschafts- Pr\u00fcfung Gmbh",
    "wof:placetype":"venue"
},
  "geometry": {"coordinates":[7.3154511452,52.5233078003],"type":"Point"}
}