{
  "type": "Feature",
  "properties": {
    "iso:country":"DE",
    "sg:address":"Obergraben 1",
    "sg:city":"Neustadt",
    "sg:phone":"+49 3596/2491",
    "sg:postcode":"01844",
    "sg:province":"Sachsen",
    "wof:name":"Ingenieurb\u00fcro Haarmann",
    "wof:placetype":"venue"
},
  "geometry": {"coordinates":[14.2122144699,51.0193252563],"type":"Point"}
}