{
  "type": "Feature",
  "properties": {
    "iso:country":"DE",
    "sg:address":"Kapellplatz 38",
    "sg:city":"Alt\u00f6tting",
    "sg:phone":"+49 8671/6933",
    "sg:postcode":"84503",
    "sg:province":"Bayern",
    "wof:name":"Dom. Barbarino & Sohn",
    "wof:placetype":"venue"
},
  "geometry": {"coordinates":[12.67548,48.226089],"type":"Point"}
}