{
  "type": "Feature",
  "properties": {
    "iso:country":"DE",
    "sg:address":"Forststr. 12",
    "sg:city":"Landstuhl",
    "sg:phone":"+49 6371/2272",
    "sg:postcode":"66849",
    "sg:province":"Rheinland-Pfalz",
    "wof:name":"Herbert Braun Ingenieur",
    "wof:placetype":"venue"
},
  "geometry": {"coordinates":[7.5768990517,49.3998413086],"type":"Point"}
}