{
  "type": "Feature",
  "properties": {
    "iso:country":"DE",
    "sg:address":"Menzelweg 7",
    "sg:city":"Lehrte",
    "sg:phone":"+49 5132/4521",
    "sg:postcode":"31275",
    "sg:province":"Niedersachsen",
    "wof:name":"Jutta Meyer",
    "wof:placetype":"venue"
},
  "geometry": {"coordinates":[9.966351,52.360874],"type":"Point"}
}