{
  "type": "Feature",
  "properties": {
    "iso:country":"DE",
    "sg:address":"Hampoel 24",
    "sg:city":"Nettetal",
    "sg:phone":"+49 2157/4285",
    "sg:postcode":"41334",
    "sg:province":"Nordrhein-Westfalen",
    "wof:name":"Heinrich Schouren",
    "wof:placetype":"venue"
},
  "geometry": {"coordinates":[6.219705,51.336079],"type":"Point"}
}