{
  "type": "Feature",
  "properties": {
    "iso:country":"DE",
    "sg:address":"Frankenstr. 41",
    "sg:city":"Niederkassel",
    "sg:phone":"+49 2208/6293",
    "sg:postcode":"53859",
    "sg:province":"Nordrhein-Westfalen",
    "wof:name":"Wilhelm Eich",
    "wof:placetype":"venue"
},
  "geometry": {"coordinates":[7.05043,50.788708],"type":"Point"}
}