{
  "type": "Feature",
  "properties": {
    "iso:country":"DE",
    "sg:address":"Schlesische Str. 29-30",
    "sg:city":"Berlin",
    "sg:phone":"+49 4930/6124811",
    "sg:postcode":"10997",
    "sg:province":"Berlin",
    "wof:name":"Erich Hoffmann Gmbh",
    "wof:placetype":"venue"
},
  "geometry": {"coordinates":[13.4468240738,52.4986724854],"type":"Point"}
}