{
  "type": "Feature",
  "properties": {
    "iso:country":"DE",
    "sg:address":"K\u00f6nigstr. 67",
    "sg:city":"Bonn",
    "sg:phone":"+49 228/217512",
    "sg:postcode":"53115",
    "sg:province":"Nordrhein-Westfalen",
    "wof:name":"Willibald Irmer",
    "wof:placetype":"venue"
},
  "geometry": {"coordinates":[7.0976362228,50.7264900208],"type":"Point"}
}