{
  "type": "Feature",
  "properties": {
    "iso:country":"DE",
    "sg:address":"Walsumer Str. 4",
    "sg:city":"Raubling",
    "sg:phone":"+49 8035/2627",
    "sg:postcode":"83064",
    "sg:province":"Bayern",
    "wof:name":"Franz Hable",
    "wof:placetype":"venue"
},
  "geometry": {"coordinates":[12.114116,47.796722],"type":"Point"}
}