{
  "type": "Feature",
  "properties": {
    "iso:country":"DE",
    "sg:address":"L\u00f6hrstr. 28-33",
    "sg:city":"Koblenz",
    "sg:phone":"+49 261/15081",
    "sg:postcode":"56068",
    "sg:province":"Rheinland-Pfalz",
    "wof:name":"Weinkauf & Sohn Sehen Und H\u00f6ren Gmbh",
    "wof:placetype":"venue"
},
  "geometry": {"coordinates":[7.5936541557,50.359790802],"type":"Point"}
}