{
  "type": "Feature",
  "properties": {
    "iso:country":"DE",
    "sg:address":"Benesisstr. 25",
    "sg:city":"K\u00f6ln",
    "sg:phone":"+49 221/256441",
    "sg:postcode":"50672",
    "sg:province":"Nordrhein-Westfalen",
    "wof:name":"J\u00fcrgen Kesseler",
    "wof:placetype":"venue"
},
  "geometry": {"coordinates":[6.9421610832,50.9367103577],"type":"Point"}
}