{
  "type": "Feature",
  "properties": {
    "iso:country":"DE",
    "sg:address":"Wittbende 29",
    "sg:city":"Mayen",
    "sg:phone":"+49 2651/3826",
    "sg:postcode":"56727",
    "sg:province":"Rheinland-Pfalz",
    "wof:name":"Brigitte Strobel",
    "wof:placetype":"venue"
},
  "geometry": {"coordinates":[7.220261097,50.3323135376],"type":"Point"}
}