{
  "type": "Feature",
  "properties": {
    "iso:country":"DE",
    "sg:address":"K\u00f6nigsseer Str. 1",
    "sg:city":"Berchtesgaden",
    "sg:phone":"+49 8652/2990",
    "sg:postcode":"83471",
    "sg:province":"Bayern",
    "wof:name":"Schwaben-lichtspiele",
    "wof:placetype":"venue"
},
  "geometry": {"coordinates":[13.0007143021,47.6257171631],"type":"Point"}
}