{
  "type": "Feature",
  "properties": {
    "iso:country":"DE",
    "sg:address":"Bleichstr. 18",
    "sg:city":"Erbach",
    "sg:phone":"+49 6062/61377",
    "sg:postcode":"64711",
    "sg:province":"Hessen",
    "wof:name":"Royal",
    "wof:placetype":"venue"
},
  "geometry": {"coordinates":[8.99162,49.659153],"type":"Point"}
}