{
  "type": "Feature",
  "properties": {
    "iso:country":"DE",
    "sg:address":"Carl-Benz-Str. 5",
    "sg:city":"Eppingen",
    "sg:phone":"+49 7262/5318",
    "sg:postcode":"75031",
    "sg:province":"Baden-W\u00fcrttemberg",
    "wof:name":"Manfred Kenngott E. Kfm.",
    "wof:placetype":"venue"
},
  "geometry": {"coordinates":[8.925705,49.135883],"type":"Point"}
}