{
  "type": "Feature",
  "properties": {
    "iso:country":"DE",
    "sg:address":"Baron-Voght-Str. 144",
    "sg:city":"Hamburg",
    "sg:postcode":"22607",
    "sg:province":"Hamburg",
    "wof:name":"Stadtlandflu\u00df E. Pomykaj E. K.",
    "wof:placetype":"venue"
},
  "geometry": {"coordinates":[9.8697776794,53.5634117126],"type":"Point"}
}