{
  "type": "Feature",
  "properties": {
    "iso:country":"DE",
    "sg:address":"Zum Strothebach 1",
    "sg:city":"Bad Lippspringe",
    "sg:phone":"+49 5252/5645",
    "sg:postcode":"33175",
    "sg:province":"Nordrhein-Westfalen",
    "wof:name":"E. Sprenger Maler-fachbetrieb Gmbh",
    "wof:placetype":"venue"
},
  "geometry": {"coordinates":[8.79026,51.776802],"type":"Point"}
}