{
  "type": "Feature",
  "properties": {
    "iso:country":"DE",
    "sg:address":"Schmiedberg 2",
    "sg:city":"Buch",
    "sg:phone":"+49 8124/910483",
    "sg:postcode":"85656",
    "sg:province":"Bayern",
    "wof:name":"Martin Hehenberger",
    "wof:placetype":"venue"
},
  "geometry": {"coordinates":[11.993885,48.213928],"type":"Point"}
}