{
  "type": "Feature",
  "properties": {
    "iso:country":"DE",
    "sg:address":"Hirschfelder Str.5",
    "sg:city":"Gr\u00f6den",
    "sg:phone":"+49 180 3 435367",
    "sg:postcode":"04932",
    "sg:province":"Brandenburg",
    "wof:name":"Accordeon, Musiknoten, Musik Zunhammer",
    "wof:placetype":"venue"
},
  "geometry": {"coordinates":[13.5760650635,51.4053840637],"type":"Point"}
}