{
  "type": "Feature",
  "properties": {
    "iso:country":"DE",
    "sg:address":"Schneckengasse 15",
    "sg:city":"Sauldorf",
    "sg:phone":"+49 7777/238",
    "sg:postcode":"88605",
    "sg:province":"Baden-W\u00fcrttemberg",
    "wof:name":"Estrich-muffler Gmbh",
    "wof:placetype":"venue"
},
  "geometry": {"coordinates":[9.0452003479,47.9597930908],"type":"Point"}
}