{
  "type": "Feature",
  "properties": {
    "iso:country":"DE",
    "sg:address":"Odenwaldring 1",
    "sg:city":"Reinheim",
    "sg:phone":"+49 6162/2425",
    "sg:postcode":"64354",
    "sg:province":"Hessen",
    "wof:name":"Georg Schneider",
    "wof:placetype":"venue"
},
  "geometry": {"coordinates":[8.831345,49.821838],"type":"Point"}
}