{
  "type": "Feature",
  "properties": {
    "iso:country":"DE",
    "sg:address":"Reustadt 16-2",
    "sg:city":"Hattenhofen",
    "sg:phone":"+49 7164/130190",
    "sg:postcode":"73110",
    "sg:province":"Baden-W\u00fcrttemberg",
    "wof:name":"Bautenschutz G\u00f6lz",
    "wof:placetype":"venue"
},
  "geometry": {"coordinates":[9.578759,48.667938],"type":"Point"}
}