{
  "type": "Feature",
  "properties": {
    "iso:country":"DE",
    "sg:address":"Im Schlahbruch 19",
    "sg:city":"Meschede",
    "sg:phone":"+49 291/9081140",
    "sg:postcode":"59872",
    "sg:province":"Nordrhein-Westfalen",
    "wof:name":"Klauke & Fisch Gmbh",
    "wof:placetype":"venue"
},
  "geometry": {"coordinates":[8.2536888123,51.3551635742],"type":"Point"}
}