{
  "type": "Feature",
  "properties": {
    "iso:country":"DE",
    "sg:address":"Panzerleite",
    "sg:city":"Bamberg",
    "sg:phone":"+49 951/52705",
    "sg:postcode":"96049",
    "sg:province":"Bayern",
    "wof:name":"Fun-sports Freizeitanlagen Und Zubeh\u00f6rteile Gmbh",
    "wof:placetype":"venue"
},
  "geometry": {"coordinates":[10.879585,49.888885],"type":"Point"}
}