{
  "type": "Feature",
  "properties": {
    "iso:country":"DE",
    "sg:address":"Illenauer Allee 1",
    "sg:city":"Achern",
    "sg:phone":"+49 7841/3363",
    "sg:postcode":"77855",
    "sg:province":"Baden-W\u00fcrttemberg",
    "wof:name":"Wilhelm Beck",
    "wof:placetype":"venue"
},
  "geometry": {"coordinates":[8.079867363,48.6283950806],"type":"Point"}
}