{
  "type": "Feature",
  "properties": {
    "iso:country":"DE",
    "sg:address":"Schwalbacher Str. 3",
    "sg:city":"Wiesbaden",
    "sg:phone":"+49 611/376024",
    "sg:postcode":"65185",
    "sg:province":"Hessen",
    "wof:name":"Hans-peter Schneider Rechtsanwalt Und Notar",
    "wof:placetype":"venue"
},
  "geometry": {"coordinates":[8.2369279861,50.0780944824],"type":"Point"}
}