{
  "type": "Feature",
  "properties": {
    "iso:country":"DE",
    "sg:address":"Hecknerstr. 1",
    "sg:city":"Aschersleben",
    "sg:phone":"+49 3473/807205",
    "sg:postcode":"06449",
    "sg:province":"Sachsen-Anhalt",
    "wof:name":"Barbara Grollm\u00fctz Notariat",
    "wof:placetype":"venue"
},
  "geometry": {"coordinates":[11.4580230713,51.7548751831],"type":"Point"}
}