{
  "type": "Feature",
  "properties": {
    "iso:country":"DE",
    "sg:address":"Mohnstr. 50",
    "sg:city":"Dresden",
    "sg:phone":"+49 351/8489897",
    "sg:postcode":"01127",
    "sg:province":"Sachsen",
    "wof:name":"Ulrike Weller",
    "wof:placetype":"venue"
},
  "geometry": {"coordinates":[13.7168149948,51.0778884888],"type":"Point"}
}