{
  "type": "Feature",
  "properties": {
    "iso:country":"DE",
    "sg:address":"Industriegel\u00e4nde 03",
    "sg:city":"Ringenhain",
    "sg:phone":"+49 35951/31459",
    "sg:postcode":"01904",
    "sg:province":"Sachsen",
    "wof:name":"Siegemund Pulver- Beschichtungs Gmbh",
    "wof:placetype":"venue"
},
  "geometry": {"coordinates":[14.3394403458,51.0754966736],"type":"Point"}
}