{
  "type": "Feature",
  "properties": {
    "iso:country":"DE",
    "sg:address":"Stra\u00dfe der Jugend 12",
    "sg:city":"Velgast",
    "sg:phone":"+49 38324/371",
    "sg:postcode":"18469",
    "sg:province":"Mecklenburg-Vorpommern",
    "wof:name":"Gastst\u00e4tte Gr\u00fcnspan",
    "wof:placetype":"venue"
},
  "geometry": {"coordinates":[12.8057126999,54.2735481262],"type":"Point"}
}