{
  "type": "Feature",
  "properties": {
    "iso:country":"DE",
    "sg:address":"Kemmater Weg 12",
    "sg:city":"R\u00f6dental",
    "sg:phone":"+49 9563/8320",
    "sg:postcode":"96472",
    "sg:province":"Bayern",
    "wof:name":"Herbert Truckenbrodt",
    "wof:placetype":"venue"
},
  "geometry": {"coordinates":[11.085858,50.287247],"type":"Point"}
}