{
  "type": "Feature",
  "properties": {
    "iso:country":"DE",
    "sg:address":"Weidacher Str 1-3",
    "sg:city":"Durach",
    "sg:phone":"+49 831/564190",
    "sg:postcode":"87471",
    "sg:province":"Bayern",
    "wof:name":"Wilhelm Fischer Spezialmaschinenfabrik Gmbh",
    "wof:placetype":"venue"
},
  "geometry": {"coordinates":[10.344655,47.695915],"type":"Point"}
}