{
  "type": "Feature",
  "properties": {
    "iso:country":"DE",
    "sg:address":"Sperberstr. 12",
    "sg:city":"M\u00f6nchengladbach",
    "sg:phone":"+49 2166/3557",
    "sg:postcode":"41239",
    "sg:province":"Nordrhein-Westfalen",
    "wof:name":"Paul Stefansky",
    "wof:placetype":"venue"
},
  "geometry": {"coordinates":[6.4206590652,51.1529045105],"type":"Point"}
}