{
  "type": "Feature",
  "properties": {
    "iso:country":"DE",
    "sg:address":"Am Eiskeller 1",
    "sg:city":"Gro\u00dfpostwitz",
    "sg:phone":"+49 35938/51175",
    "sg:postcode":"02692",
    "sg:province":"Sachsen",
    "wof:name":"Team Boro Haus Gmbh",
    "wof:placetype":"venue"
},
  "geometry": {"coordinates":[14.41587,51.128208],"type":"Point"}
}