{
  "type": "Feature",
  "properties": {
    "iso:country":"DE",
    "sg:address":"Kastanienweg 88",
    "sg:city":"Ahlen",
    "sg:phone":"+49 2382/73853",
    "sg:postcode":"59229",
    "sg:province":"Nordrhein-Westfalen",
    "wof:name":"Willi Gebhardt",
    "wof:placetype":"venue"
},
  "geometry": {"coordinates":[7.8841,51.742481],"type":"Point"}
}