{
  "type": "Feature",
  "properties": {
    "iso:country":"DE",
    "sg:address":"Westernk\u00f6tter Str. 193",
    "sg:city":"Lippstadt",
    "sg:phone":"+49 2941",
    "sg:postcode":"59557",
    "sg:province":"Nordrhein-Westfalen",
    "wof:name":"Hellweg Automobile Gmbh",
    "wof:placetype":"venue"
},
  "geometry": {"coordinates":[8.3567829132,51.6538505554],"type":"Point"}
}