{
  "type": "Feature",
  "properties": {
    "iso:country":"DE",
    "sg:address":"Moltkestr. 3",
    "sg:city":"Duisburg",
    "sg:phone":"+49 203/337272",
    "sg:postcode":"47058",
    "sg:province":"Nordrhein-Westfalen",
    "wof:name":"G\u00fcnter Koczy Rechtsanwalt",
    "wof:placetype":"venue"
},
  "geometry": {"coordinates":[6.7901768684,51.4336929321],"type":"Point"}
}