{
  "type": "Feature",
  "properties": {
    "iso:country":"DE",
    "sg:address":"Hauptstr. 34",
    "sg:city":"L\u00f6rrach",
    "sg:phone":"+49 7621/86378",
    "sg:postcode":"79540",
    "sg:province":"Baden-W\u00fcrttemberg",
    "wof:name":"R. Metzger",
    "wof:placetype":"venue"
},
  "geometry": {"coordinates":[7.6627168655,47.6015396118],"type":"Point"}
}