{
  "type": "Feature",
  "properties": {
    "iso:country":"DE",
    "sg:address":"Im Sch\u00fctzenhof 2",
    "sg:city":"Daaden",
    "sg:phone":"+49 2743/2394",
    "sg:postcode":"57567",
    "sg:province":"Rheinland-Pfalz",
    "wof:name":"G\u00fcnter Weber Drogerie",
    "wof:placetype":"venue"
},
  "geometry": {"coordinates":[7.967181,50.738033],"type":"Point"}
}