{
  "type": "Feature",
  "properties": {
    "iso:country":"DE",
    "sg:address":"Kurf\u00fcrstenstr. 14a",
    "sg:city":"Br\u00fchl",
    "sg:phone":"+49 2232/45714",
    "sg:postcode":"50321",
    "sg:province":"Nordrhein-Westfalen",
    "wof:name":"Hans J. Meyer Ingenieur",
    "wof:placetype":"venue"
},
  "geometry": {"coordinates":[6.9042711258,50.8350257874],"type":"Point"}
}