{
  "type": "Feature",
  "properties": {
    "iso:country":"DE",
    "sg:address":"Alte B\u00f6hmische Str. 4",
    "sg:city":"Altenberg",
    "sg:phone":"+49 35052/20905",
    "sg:postcode":"01773",
    "sg:province":"Sachsen",
    "wof:name":"Haus Dorotheenh\u00f6he",
    "wof:placetype":"venue"
},
  "geometry": {"coordinates":[13.6670637131,50.8206596375],"type":"Point"}
}