{
  "type": "Feature",
  "properties": {
    "iso:country":"DE",
    "sg:address":"Tiergartenstr. 68",
    "sg:city":"Kleve",
    "sg:postcode":"47533",
    "sg:province":"Nordrhein-Westfalen",
    "wof:name":"St\u00e4dt. Kinder- Und Altersheim-m\u00fcnze",
    "wof:placetype":"venue"
},
  "geometry": {"coordinates":[6.1217799187,51.799533844],"type":"Point"}
}