{
  "type": "Feature",
  "properties": {
    "iso:country":"DE",
    "sg:address":"Zietenstr. 65",
    "sg:city":"Chemnitz",
    "sg:phone":"+49 371/4012965",
    "sg:postcode":"09130",
    "sg:province":"Sachsen",
    "wof:name":"Werkst\u00e4tten F\u00fcr Buchbinderei Donath Kg",
    "wof:placetype":"venue"
},
  "geometry": {"coordinates":[12.9406957626,50.8378753662],"type":"Point"}
}