{
  "type": "Feature",
  "properties": {
    "iso:country":"DE",
    "sg:address":"Krugkamp 8",
    "sg:city":"Adenstedt",
    "sg:phone":"+49 5065/8160",
    "sg:postcode":"31079",
    "sg:province":"Niedersachsen",
    "wof:name":"Walter Stoffregen",
    "wof:placetype":"venue"
},
  "geometry": {"coordinates":[9.935368,52.014999],"type":"Point"}
}