{
  "type": "Feature",
  "properties": {
    "iso:country":"DE",
    "sg:address":"Gertraud-Rostosky-Str. 48",
    "sg:city":"W\u00fcrzburg",
    "sg:phone":"+49 931/7900660",
    "sg:postcode":"97082",
    "sg:province":"Bayern",
    "wof:name":"Ceta Entsorgungssysteme Gmbh",
    "wof:placetype":"venue"
},
  "geometry": {"coordinates":[9.9021520615,49.7867507935],"type":"Point"}
}