{
  "type": "Feature",
  "properties": {
    "iso:country":"DE",
    "sg:address":"M\u00fcnchhausenweg 16",
    "sg:city":"Hamburg",
    "sg:phone":"+49 40/5521647",
    "sg:postcode":"22453",
    "sg:province":"Hamburg",
    "wof:name":"Wolfgang Ruhrmann Rechtsanwalt",
    "wof:placetype":"venue"
},
  "geometry": {"coordinates":[9.973156929,53.6374359131],"type":"Point"}
}