{
  "type": "Feature",
  "properties": {
    "iso:country":"DE",
    "sg:address":"Gut Grauhof 2",
    "sg:city":"Goslar",
    "sg:phone":"+49 5321/81174",
    "sg:postcode":"38644",
    "sg:province":"Niedersachsen",
    "wof:name":"Kath. Pfarramt St. Georg",
    "wof:placetype":"venue"
},
  "geometry": {"coordinates":[10.4477119446,51.9364547729],"type":"Point"}
}