{
  "type": "Feature",
  "properties": {
    "iso:country":"DE",
    "sg:address":"Am Hof 5",
    "sg:city":"Wei\u00dfenburg",
    "sg:phone":"+49 9141/3449",
    "sg:postcode":"91781",
    "sg:province":"Bayern",
    "wof:name":"Cvc-videothek",
    "wof:placetype":"venue"
},
  "geometry": {"coordinates":[10.9711399078,49.0310897827],"type":"Point"}
}