{
  "type": "Feature",
  "properties": {
    "iso:country":"DE",
    "sg:address":"Postplatz 7",
    "sg:city":"Schwerte",
    "sg:phone":"+49 2304/18778",
    "sg:postcode":"58239",
    "sg:province":"Nordrhein-Westfalen",
    "wof:name":"Cafe R. Thiel",
    "wof:placetype":"venue"
},
  "geometry": {"coordinates":[7.5655918121,51.4420852661],"type":"Point"}
}