{
  "type": "Feature",
  "properties": {
    "iso:country":"DE",
    "sg:address":"An Der Walze 8",
    "sg:city":"Coswig",
    "sg:phone":"+49 4935/2372378",
    "sg:postcode":"01640",
    "sg:province":"Sachsen",
    "wof:name":"Entlackung & Service Gmbh",
    "wof:placetype":"venue"
},
  "geometry": {"coordinates":[13.588279,51.118668],"type":"Point"}
}