{
  "type": "Feature",
  "properties": {
    "iso:country":"DE",
    "sg:address":"Breite Str. 15",
    "sg:city":"Luckenwalde",
    "sg:phone":"+49 3371/631295",
    "sg:postcode":"14943",
    "sg:province":"Brandenburg",
    "wof:name":"Caf\u00e9 Zebra Musikcafe",
    "wof:placetype":"venue"
},
  "geometry": {"coordinates":[13.171641,52.087738],"type":"Point"}
}