{
  "type": "Feature",
  "properties": {
    "iso:country":"DE",
    "sg:address":"Wachbergstr. 6",
    "sg:city":"Dresden",
    "sg:postcode":"01326",
    "sg:province":"Sachsen",
    "wof:name":"Hilfswerk Altersheim Der Christengemeinschaft",
    "wof:placetype":"venue"
},
  "geometry": {"coordinates":[13.831164,51.056225],"type":"Point"}
}