{
  "type": "Feature",
  "properties": {
    "iso:country":"DE",
    "sg:address":"Kirchstr. 22",
    "sg:city":"Rittersgr\u00fcn",
    "sg:phone":"+49 37757/7201",
    "sg:postcode":"08355",
    "wof:name":"Junghans S\u00f6hne Gmbh",
    "wof:placetype":"venue"
},
  "geometry": {"coordinates":[12.7971353531,50.4780960083],"type":"Point"}
}