{
  "type": "Feature",
  "properties": {
    "iso:country":"DE",
    "sg:address":"Hauptstr. 10",
    "sg:city":"Gronau",
    "sg:postcode":"31028",
    "sg:province":"Niedersachsen",
    "wof:name":"Textilhaus Kruse Inh. Hartmut Kruse",
    "wof:placetype":"venue"
},
  "geometry": {"coordinates":[8.78104496,50.1950340271],"type":"Point"}
}