{
  "type": "Feature",
  "properties": {
    "iso:country":"DE",
    "sg:address":"Astrup 80",
    "sg:city":"Visbek",
    "sg:phone":"+49 4445/961014",
    "sg:postcode":"49429",
    "sg:province":"Niedersachsen",
    "wof:name":"Theo Gerdes",
    "wof:placetype":"venue"
},
  "geometry": {"coordinates":[8.303477,52.79776],"type":"Point"}
}