{
  "type": "Feature",
  "properties": {
    "iso:country":"DE",
    "sg:address":"Felsberger Str. 28",
    "sg:city":"\u00dcberherrn",
    "sg:phone":"+49 6836/5871",
    "sg:postcode":"66802",
    "sg:province":"Saarland",
    "wof:name":"Die Tenne",
    "wof:placetype":"venue"
},
  "geometry": {"coordinates":[6.7037401199,49.2775497437],"type":"Point"}
}