{
  "type": "Feature",
  "properties": {
    "iso:country":"DE",
    "sg:address":"Bahnhofstr. 8",
    "sg:city":"Ortrand",
    "sg:phone":"+49 35755/51885",
    "sg:postcode":"01990",
    "sg:province":"Brandenburg",
    "wof:name":"Schr\u00f6der",
    "wof:placetype":"venue"
},
  "geometry": {"coordinates":[13.7581386566,51.3754806519],"type":"Point"}
}