{
  "type": "Feature",
  "properties": {
    "iso:country":"DE",
    "sg:address":"Freiheitstr. 9",
    "sg:city":"Castrop-Rauxel",
    "sg:phone":"+49 2367/1679",
    "sg:postcode":"44581",
    "sg:province":"Nordrhein-Westfalen",
    "wof:name":"Dorfsch\u00e4nke",
    "wof:placetype":"venue"
},
  "geometry": {"coordinates":[7.3117880821,51.5988845825],"type":"Point"}
}