{
  "type": "Feature",
  "properties": {
    "iso:country":"DE",
    "sg:address":"Wilsdruffer Str. 10",
    "sg:city":"Dresden",
    "sg:phone":"+49 351/4901855",
    "sg:postcode":"01067",
    "sg:province":"Sachsen",
    "wof:name":"Metz Ambiente In Stile Einrichtungs Gmbh",
    "wof:placetype":"venue"
},
  "geometry": {"coordinates":[13.7411956787,51.0500640869],"type":"Point"}
}