{
  "type": "Feature",
  "properties": {
    "iso:country":"DE",
    "sg:address":"Westendorf 13",
    "sg:city":"Sch\u00f6ningen",
    "sg:phone":"+49 5352/2533",
    "sg:postcode":"38364",
    "sg:province":"Niedersachsen",
    "wof:name":"Fritz K\u00f6lling",
    "wof:placetype":"venue"
},
  "geometry": {"coordinates":[10.961346,52.139923],"type":"Point"}
}