{
  "type": "Feature",
  "properties": {
    "iso:country":"DE",
    "sg:address":"Jakob-Krebs-Str. 135",
    "sg:city":"Willich",
    "sg:phone":"+49 2156/3180",
    "sg:postcode":"47877",
    "sg:province":"Nordrhein-Westfalen",
    "wof:name":"Bistro-cafe",
    "wof:placetype":"venue"
},
  "geometry": {"coordinates":[6.4531002045,51.2828216553],"type":"Point"}
}