{
  "type": "Feature",
  "properties": {
    "iso:country":"DE",
    "sg:address":"Am Husarendenkmal 56",
    "sg:city":"Hamburg",
    "sg:phone":"+49 40/6527412",
    "sg:postcode":"22043",
    "sg:province":"Hamburg",
    "wof:name":"K\u00e4lteanlagen Polaris",
    "wof:placetype":"venue"
},
  "geometry": {"coordinates":[10.0791273117,53.5648536682],"type":"Point"}
}