{
  "type": "Feature",
  "properties": {
    "iso:country":"DE",
    "sg:address":"Breslauer Str. 1",
    "sg:city":"Ilvesheim",
    "sg:phone":"+49 621/4962063",
    "sg:postcode":"68549",
    "sg:province":"Baden-W\u00fcrttemberg",
    "wof:name":"Thomas Zeidler",
    "wof:placetype":"venue"
},
  "geometry": {"coordinates":[8.5614318848,49.479511261],"type":"Point"}
}