{
  "type": "Feature",
  "properties": {
    "iso:country":"DE",
    "sg:address":"Osterbekstr. 90 B",
    "sg:city":"Hamburg",
    "sg:postcode":"22083",
    "sg:province":"Hamburg",
    "wof:name":"Agc Beteiligungs Gmbh",
    "wof:placetype":"venue"
},
  "geometry": {"coordinates":[10.029127,53.583427],"type":"Point"}
}