{
  "type": "Feature",
  "properties": {
    "iso:country":"DE",
    "sg:address":"B\u00fcnder Str. 27",
    "sg:city":"Herford",
    "sg:phone":"+49 5221/529165",
    "sg:postcode":"32051",
    "sg:province":"Nordrhein-Westfalen",
    "wof:name":"D\u00fcmmer Stube",
    "wof:placetype":"venue"
},
  "geometry": {"coordinates":[8.6628160477,52.1220016479],"type":"Point"}
}