{
  "type": "Feature",
  "properties": {
    "iso:country":"DE",
    "sg:address":"Lerchenweg 11",
    "sg:city":"Dillenburg",
    "sg:phone":"+49 2771/22935",
    "sg:postcode":"35683",
    "sg:province":"Hessen",
    "wof:name":"Geschichtsverein Herrn Ossner",
    "wof:placetype":"venue"
},
  "geometry": {"coordinates":[8.2783145905,50.7309188843],"type":"Point"}
}