{
  "type": "Feature",
  "properties": {
    "iso:country":"DE",
    "sg:address":"Berner Stieg 25",
    "sg:city":"Hamburg",
    "sg:phone":"+49 40/64427213",
    "sg:postcode":"22145",
    "sg:province":"Hamburg",
    "wof:name":"Dzzi Inst. F. Zahn\u00e4rztl. Implantologie Gmbh",
    "wof:placetype":"venue"
},
  "geometry": {"coordinates":[10.14479,53.627724],"type":"Point"}
}