{
  "type": "Feature",
  "properties": {
    "iso:country":"DE",
    "sg:address":"Dr.-Alexander-Str. 35",
    "sg:city":"Boizenburg",
    "sg:phone":"+49 38847/54149",
    "sg:postcode":"19258",
    "sg:province":"Mecklenburg-Vorpommern",
    "wof:name":"Klaus-dieter Wille",
    "wof:placetype":"venue"
},
  "geometry": {"coordinates":[10.7264518738,53.3870773315],"type":"Point"}
}