{
  "type": "Feature",
  "properties": {
    "iso:country":"DE",
    "sg:address":"Brennerstr. 1",
    "sg:city":"Leonberg",
    "sg:phone":"+49 7152/43343",
    "sg:postcode":"71229",
    "sg:province":"Baden-W\u00fcrttemberg",
    "wof:name":"Hindenburg Apotheke Leonberg E. K.",
    "wof:placetype":"venue"
},
  "geometry": {"coordinates":[9.010251,48.795349],"type":"Point"}
}