{
  "type": "Feature",
  "properties": {
    "iso:country":"DE",
    "sg:address":"Demminer Str. 7-8",
    "sg:city":"T\u00fctzpatz",
    "sg:postcode":"17091",
    "sg:province":"Mecklenburg-Vorpommern",
    "wof:name":"Von Paepcke Schweinehaltungs Kg",
    "wof:placetype":"venue"
},
  "geometry": {"coordinates":[13.1404695511,53.7234039307],"type":"Point"}
}