{
  "type": "Feature",
  "properties": {
    "iso:country":"DE",
    "sg:address":"Heubergredder 38",
    "sg:city":"Hamburg",
    "sg:phone":"+49 40/516246",
    "sg:postcode":"22297",
    "sg:province":"Hamburg",
    "wof:name":"Feuerfest",
    "wof:placetype":"venue"
},
  "geometry": {"coordinates":[10.0106887817,53.6071472168],"type":"Point"}
}