{
  "type": "Feature",
  "properties": {
    "iso:country":"DE",
    "sg:address":"Kirchweg 62",
    "sg:city":"Engelsbrand",
    "sg:phone":"+49 7082/79266",
    "sg:postcode":"75331",
    "sg:province":"Baden-W\u00fcrttemberg",
    "wof:name":"Teamziereis Gmbh",
    "wof:placetype":"venue"
},
  "geometry": {"coordinates":[8.647947,48.836487],"type":"Point"}
}