{
  "type": "Feature",
  "properties": {
    "iso:country":"DE",
    "sg:address":"Steinbruchweg 5",
    "sg:city":"Halle",
    "sg:phone":"+49 345/7700940",
    "sg:postcode":"06128",
    "sg:province":"Sachsen-Anhalt",
    "wof:name":"Senioren- Und Hauswirt- Schaftliche Betreuung",
    "wof:placetype":"venue"
},
  "geometry": {"coordinates":[11.937884,51.443279],"type":"Point"}
}