{
  "type": "Feature",
  "properties": {
    "iso:country":"DE",
    "sg:address":"Schopenhauerstr 105",
    "sg:city":"M\u00fcnchen",
    "sg:phone":"+49 89/3508614",
    "sg:postcode":"80809",
    "sg:province":"Bayern",
    "wof:name":"Datenerfassung Max Sterner",
    "wof:placetype":"venue"
},
  "geometry": {"coordinates":[11.564409,48.179008],"type":"Point"}
}