{
  "type": "Feature",
  "properties": {
    "iso:country":"DE",
    "sg:address":"Gerikestr. 102",
    "sg:city":"Haldensleben",
    "sg:phone":"+49 3904/473200",
    "sg:postcode":"39340",
    "sg:province":"Sachsen-Anhalt",
    "wof:name":"Althaldensleber Erbbegr\u00e4bnis Der Familie Von Nathusius",
    "wof:placetype":"venue"
},
  "geometry": {"coordinates":[11.4237880707,52.2797927856],"type":"Point"}
}