{
  "type": "Feature",
  "properties": {
    "iso:country":"DE",
    "sg:address":"Mainstr. 17",
    "sg:city":"Viereth-Trunstadt",
    "sg:postcode":"96191",
    "sg:province":"Bayern",
    "wof:name":"Main\u00e4cker Kieswerk Gmbh & Co. Kg",
    "wof:placetype":"venue"
},
  "geometry": {"coordinates":[10.7752685547,49.9239883423],"type":"Point"}
}