{
  "type": "Feature",
  "properties": {
    "iso:country":"DE",
    "sg:address":"Wilhelmstr. 84",
    "sg:city":"Reutlingen",
    "sg:phone":"+49 7121/37460",
    "sg:postcode":"72764",
    "sg:province":"Baden-W\u00fcrttemberg",
    "wof:name":"D2-shop",
    "wof:placetype":"venue"
},
  "geometry": {"coordinates":[9.2129039764,48.4909172058],"type":"Point"}
}