{
  "type": "Feature",
  "properties": {
    "iso:country":"DE",
    "sg:address":"Karl-Friedrich-Str. 17",
    "sg:city":"Karlsruhe",
    "sg:phone":"+49 721/9260",
    "sg:postcode":"76133",
    "sg:province":"Baden-W\u00fcrttemberg",
    "wof:name":"Landesgewerbeamt Baden-w\u00fcrttemberg",
    "wof:placetype":"venue"
},
  "geometry": {"coordinates":[8.403918,49.007462],"type":"Point"}
}