{
  "type": "Feature",
  "properties": {
    "iso:country":"DE",
    "sg:address":"Rheinstr. 10",
    "sg:city":"Hohberg",
    "sg:phone":"+49 7808/1010",
    "sg:postcode":"77749",
    "sg:province":"Baden-W\u00fcrttemberg",
    "wof:name":"Christa Gauglitz",
    "wof:placetype":"venue"
},
  "geometry": {"coordinates":[7.9026851654,48.4231491089],"type":"Point"}
}