{
  "type": "Feature",
  "properties": {
    "iso:country":"DE",
    "sg:address":"Hummelsb\u00fctteler Landstr. 9",
    "sg:city":"Hamburg",
    "sg:phone":"+49 40/503641",
    "sg:postcode":"22335",
    "sg:province":"Hamburg",
    "wof:name":"Schlemmermarkt Struve",
    "wof:placetype":"venue"
},
  "geometry": {"coordinates":[10.0241060257,53.627204895],"type":"Point"}
}