{
  "type": "Feature",
  "properties": {
    "iso:country":"DE",
    "sg:address":"Erftalstr. 89",
    "sg:city":"Hardheim",
    "sg:phone":"+49 6283/1027",
    "sg:postcode":"74736",
    "sg:province":"Baden-W\u00fcrttemberg",
    "wof:name":"Hack Gmbh",
    "wof:placetype":"venue"
},
  "geometry": {"coordinates":[9.488293,49.577122],"type":"Point"}
}