{
  "type": "Feature",
  "properties": {
    "iso:country":"DE",
    "sg:address":"Beethovenstr. 31",
    "sg:city":"Solingen",
    "sg:phone":"+49 212/54343",
    "sg:postcode":"42655",
    "sg:province":"Nordrhein-Westfalen",
    "wof:name":"Fritz-peter Mayer",
    "wof:placetype":"venue"
},
  "geometry": {"coordinates":[7.070336,51.175777],"type":"Point"}
}