{
  "type": "Feature",
  "properties": {
    "iso:country":"DE",
    "sg:address":"Untere Hauptstr. 7",
    "sg:city":"Freising",
    "sg:phone":"+49 8161/42742",
    "sg:postcode":"85354",
    "sg:province":"Bayern",
    "wof:name":"Peter Hofmair Gmbh",
    "wof:placetype":"venue"
},
  "geometry": {"coordinates":[11.744972229,48.4012336731],"type":"Point"}
}