{
  "type": "Feature",
  "properties": {
    "iso:country":"DE",
    "sg:address":"Flattichstr. 23",
    "sg:city":"Ludwigsburg",
    "sg:phone":"+49 7141/52652",
    "sg:postcode":"71642",
    "sg:province":"Baden-W\u00fcrttemberg",
    "wof:name":"Wilhelm Sch\u00e4fer Architekt",
    "wof:placetype":"venue"
},
  "geometry": {"coordinates":[9.200251,48.909977],"type":"Point"}
}