{
  "type": "Feature",
  "properties": {
    "iso:country":"DE",
    "sg:address":"Hinterriedstr. 37",
    "sg:city":"Renningen",
    "sg:phone":"+49 7159/2569",
    "sg:postcode":"71272",
    "sg:province":"Baden-W\u00fcrttemberg",
    "wof:name":"Vereinsgastst\u00e4tte M\u00e4nner- Gesangverein Frohsinn",
    "wof:placetype":"venue"
},
  "geometry": {"coordinates":[8.9291629791,48.7715339661],"type":"Point"}
}