{
  "type": "Feature",
  "properties": {
    "iso:country":"DE",
    "sg:address":"Friedrich-Ebert-Str. 434",
    "sg:city":"Wuppertal",
    "sg:phone":"+49 202/715758",
    "sg:postcode":"42117",
    "sg:province":"Nordrhein-Westfalen",
    "wof:name":"Herm. G\u00f6rke",
    "wof:placetype":"venue"
},
  "geometry": {"coordinates":[7.1052908897,51.2457427979],"type":"Point"}
}