{
  "type": "Feature",
  "properties": {
    "iso:country":"DE",
    "sg:address":"Ifenstr. 12",
    "sg:city":"Friedrichshafen",
    "sg:phone":"+49 7541/26160",
    "sg:postcode":"88045",
    "sg:province":"Baden-W\u00fcrttemberg",
    "wof:name":"Josef Wund Architekt",
    "wof:placetype":"venue"
},
  "geometry": {"coordinates":[9.456841,47.656261],"type":"Point"}
}