{
  "type": "Feature",
  "properties": {
    "iso:country":"DE",
    "sg:address":"Rotdornallee 18",
    "sg:city":"Bremen",
    "sg:phone":"+49 421/6938011",
    "sg:postcode":"28717",
    "sg:province":"Bremen",
    "wof:name":"Fdp-shop",
    "wof:placetype":"venue"
},
  "geometry": {"coordinates":[8.6857700348,53.1735229492],"type":"Point"}
}