{
  "type": "Feature",
  "properties": {
    "iso:country":"DE",
    "sg:address":"Ledaweg 1",
    "sg:city":"Bremen",
    "sg:postcode":"28359",
    "sg:province":"Bremen",
    "wof:name":"Kath. \u00d6ffentliche Bibliothek St. Georg",
    "wof:placetype":"venue"
},
  "geometry": {"coordinates":[8.874315,53.101723],"type":"Point"}
}