{
  "type": "Feature",
  "properties": {
    "iso:country":"DE",
    "sg:address":"Bergheimer Str. 56",
    "sg:city":"Heidelberg",
    "sg:phone":"+49 6221/22472",
    "sg:postcode":"69115",
    "sg:province":"Baden-W\u00fcrttemberg",
    "wof:name":"Bestattungsinstitut Friede Hermann Hesser",
    "wof:placetype":"venue"
},
  "geometry": {"coordinates":[8.686226,49.408283],"type":"Point"}
}