{
  "type": "Feature",
  "properties": {
    "iso:country":"DE",
    "sg:address":"Ulzburger Str. 410b",
    "sg:city":"Norderstedt",
    "sg:phone":"+49 40/5227222",
    "sg:postcode":"22844",
    "sg:province":"Schleswig-Holstein",
    "wof:name":"Klaus Friedrich",
    "wof:placetype":"venue"
},
  "geometry": {"coordinates":[9.9978542328,53.7250175476],"type":"Point"}
}