{
  "type": "Feature",
  "properties": {
    "iso:country":"DE",
    "sg:address":"N\u00f6rdliche Ringstr. 12",
    "sg:city":"Schwabach",
    "sg:phone":"+49 9122/1860",
    "sg:postcode":"91126",
    "sg:province":"Bayern",
    "wof:name":"St\u00c4dtler & Uhl",
    "wof:placetype":"venue"
},
  "geometry": {"coordinates":[11.023722,49.331715],"type":"Point"}
}