{
  "type": "Feature",
  "properties": {
    "iso:country":"DE",
    "sg:address":"Hohenzollernring 60",
    "sg:city":"Bayreuth",
    "sg:phone":"+49 921/764610",
    "sg:postcode":"95444",
    "sg:province":"Bayern",
    "wof:name":"Rudolf W\u00f6hrl Das Haus Der Markenkleidung Gmbh & Co. Kg",
    "wof:placetype":"venue"
},
  "geometry": {"coordinates":[11.570713,49.94511],"type":"Point"}
}