{
  "type": "Feature",
  "properties": {
    "iso:country":"DE",
    "sg:address":"Unterd\u00f6rnen 89",
    "sg:city":"Wuppertal",
    "sg:phone":"+49 202/592081",
    "sg:postcode":"42283",
    "sg:province":"Nordrhein-Westfalen",
    "wof:name":"D\u00f6rner Wohnungsbau Gmbh",
    "wof:placetype":"venue"
},
  "geometry": {"coordinates":[7.1919960976,51.2688865662],"type":"Point"}
}