{
  "type": "Feature",
  "properties": {
    "iso:country":"DE",
    "sg:address":"Otto-Lilienthal-Str. 36",
    "sg:city":"Dinslaken",
    "sg:phone":"+49 2064/55749",
    "sg:postcode":"46539",
    "sg:province":"Nordrhein-Westfalen",
    "wof:name":"Frank Bungert Innenarchitekt",
    "wof:placetype":"venue"
},
  "geometry": {"coordinates":[6.754896,51.567604],"type":"Point"}
}