{
  "type": "Feature",
  "properties": {
    "iso:country":"DE",
    "sg:address":"Langenstr. 19",
    "sg:city":"Sendenhorst",
    "sg:phone":"+49 2526/1533",
    "sg:postcode":"48324",
    "sg:province":"Nordrhein-Westfalen",
    "wof:name":"Waldemar Hoening",
    "wof:placetype":"venue"
},
  "geometry": {"coordinates":[7.840222,51.839081],"type":"Point"}
}