{
  "type": "Feature",
  "properties": {
    "iso:country":"DE",
    "sg:address":"Gartenstr. 11",
    "sg:city":"W\u00fclfrath",
    "sg:phone":"+49 2058/72332",
    "sg:postcode":"42489",
    "sg:province":"Nordrhein-Westfalen",
    "wof:name":"Michael Thiel",
    "wof:placetype":"venue"
},
  "geometry": {"coordinates":[7.0301270485,51.282169342],"type":"Point"}
}