{
  "type": "Feature",
  "properties": {
    "iso:country":"DE",
    "sg:address":"Beckergrube 83/85",
    "sg:city":"L\u00fcbeck",
    "sg:phone":"+49 451/7987030",
    "sg:postcode":"23552",
    "sg:province":"Schleswig-Holstein",
    "wof:name":"Debeka Lebensversicherungs- Verein A.g.",
    "wof:placetype":"venue"
},
  "geometry": {"coordinates":[10.681315,53.86956],"type":"Point"}
}