{
  "type": "Feature",
  "properties": {
    "iso:country":"DE",
    "sg:address":"Niederfeldstr. 29",
    "sg:city":"Essen",
    "sg:phone":"+49 201/2439190",
    "sg:postcode":"45143",
    "sg:province":"Nordrhein-Westfalen",
    "wof:name":"Udo-dieter Gaedeke Gmbh",
    "wof:placetype":"venue"
},
  "geometry": {"coordinates":[6.9766120911,51.4640655518],"type":"Point"}
}