{
  "type": "Feature",
  "properties": {
    "iso:country":"DE",
    "sg:address":"Hellerstr. 16 a",
    "sg:city":"Dresden",
    "sg:phone":"+49 351/8804028",
    "sg:postcode":"01109",
    "sg:province":"Sachsen",
    "wof:name":"Lindengarten Hellerau",
    "wof:placetype":"venue"
},
  "geometry": {"coordinates":[13.7356805801,51.1161956787],"type":"Point"}
}