{
  "type": "Feature",
  "properties": {
    "iso:country":"DE",
    "sg:address":"Ludwig-Jahn-Str. 25",
    "sg:city":"Ruhland",
    "sg:phone":"+49 35752/16431",
    "sg:postcode":"01945",
    "sg:province":"Brandenburg",
    "wof:name":"Hoffmann",
    "wof:placetype":"venue"
},
  "geometry": {"coordinates":[13.8553886414,51.4329528809],"type":"Point"}
}