{
  "type": "Feature",
  "properties": {
    "iso:country":"DE",
    "sg:address":"S\u00fclzer Str. 40",
    "sg:city":"Gnoien",
    "sg:phone":"+49 39971/12795",
    "sg:postcode":"17179",
    "sg:province":"Mecklenburg-Vorpommern",
    "wof:name":"Johann Dautermann",
    "wof:placetype":"venue"
},
  "geometry": {"coordinates":[12.699594,53.976669],"type":"Point"}
}