{
  "type": "Feature",
  "properties": {
    "iso:country":"DE",
    "sg:address":"Ottenbacher Str. 22",
    "sg:city":"G\u00f6ppingen",
    "sg:phone":"+49 7165/1042",
    "sg:postcode":"73037",
    "sg:province":"Baden-W\u00fcrttemberg",
    "wof:name":"Siegfried Mix",
    "wof:placetype":"venue"
},
  "geometry": {"coordinates":[9.7231378555,48.7414550781],"type":"Point"}
}