{
  "type": "Feature",
  "properties": {
    "iso:country":"DE",
    "sg:address":"Paschacker 11",
    "sg:city":"Duisburg",
    "sg:phone":"+49 4920/6577480",
    "sg:postcode":"47228",
    "sg:province":"Nordrhein-Westfalen",
    "wof:name":"Bzn Bildungszentrum Der Wirtschaft Am Niederrhein Gmbh",
    "wof:placetype":"venue"
},
  "geometry": {"coordinates":[6.684621,51.417309],"type":"Point"}
}