{
  "type": "Feature",
  "properties": {
    "iso:country":"DE",
    "sg:address":"Liegnitzer Str. 8",
    "sg:city":"Kaiserslautern",
    "sg:phone":"+49 631/76200",
    "sg:postcode":"67659",
    "sg:province":"Rheinland-Pfalz",
    "wof:name":"H. Weber",
    "wof:placetype":"venue"
},
  "geometry": {"coordinates":[7.743611,49.451191],"type":"Point"}
}