{
  "type": "Feature",
  "properties": {
    "iso:country":"DE",
    "sg:address":"Aglishardter Str. 56",
    "sg:city":"R\u00f6merstein",
    "sg:phone":"+49 7382/93820",
    "sg:postcode":"72587",
    "sg:province":"Baden-W\u00fcrttemberg",
    "wof:name":"Thomas L\u00e4nge",
    "wof:placetype":"venue"
},
  "geometry": {"coordinates":[9.5065040588,48.4913063049],"type":"Point"}
}