{
  "type": "Feature",
  "properties": {
    "iso:country":"DE",
    "sg:address":"Falkenstr. 5",
    "sg:city":"Bremen",
    "sg:phone":"+49 421/13935",
    "sg:postcode":"28195",
    "sg:province":"Bremen",
    "wof:name":"Bernfried M\u00f6llenberg",
    "wof:placetype":"venue"
},
  "geometry": {"coordinates":[8.8073682785,53.0827255249],"type":"Point"}
}