{
  "type": "Feature",
  "properties": {
    "iso:country":"DE",
    "sg:address":"Nostitz 15",
    "sg:city":"Wei\u00dfenberg",
    "sg:postcode":"02627",
    "sg:province":"Sachsen",
    "wof:name":"Lafrentz Bau Nostitz Zn Der Lafrentz Bau- Und",
    "wof:placetype":"venue"
},
  "geometry": {"coordinates":[14.673038,51.165363],"type":"Point"}
}