{
  "type": "Feature",
  "properties": {
    "iso:country":"DE",
    "sg:address":"Hainstra\u00dfe 114",
    "sg:city":"Chemnitz",
    "sg:phone":"+49 371",
    "sg:postcode":"09130",
    "sg:province":"Sachsen",
    "wof:name":"Boardinghouse Sunflower",
    "wof:placetype":"venue"
},
  "geometry": {"coordinates":[12.938158,50.842819],"type":"Point"}
}