{
  "type": "Feature",
  "properties": {
    "iso:country":"DE",
    "sg:address":"Holstendorfer Weg 1",
    "sg:city":"Gro\u00df Sarau",
    "sg:phone":"+49 4509/8186",
    "sg:postcode":"23627",
    "sg:province":"Schleswig-Holstein",
    "wof:name":"Martin Rahser",
    "wof:placetype":"venue"
},
  "geometry": {"coordinates":[10.72659,53.765778],"type":"Point"}
}