{
  "type": "Feature",
  "properties": {
    "iso:country":"DE",
    "sg:address":"Dieselstr. 6",
    "sg:city":"Erlensee",
    "sg:postcode":"63526",
    "sg:province":"Hessen",
    "wof:name":"Behage Betonhandels Gmbh & Co. Kg",
    "wof:placetype":"venue"
},
  "geometry": {"coordinates":[8.9767837524,50.155544281],"type":"Point"}
}