{
  "type": "Feature",
  "properties": {
    "iso:country":"DE",
    "sg:city":"Bochum-Wattenscheid",
    "sg:phone":"+49 2327/322202",
    "sg:postcode":"44866",
    "sg:province":"Nordrhein-Westfalen",
    "wof:name":"Musik Service Westermann / Mobile Diskotheken",
    "wof:placetype":"venue"
},
  "geometry": {"coordinates":[7.147385,51.495548],"type":"Point"}
}