{
  "type": "Feature",
  "properties": {
    "iso:country":"DE",
    "sg:address":"Plattenweg 1a",
    "sg:city":"Manching",
    "sg:phone":"+49 8459/30349",
    "sg:postcode":"85077",
    "sg:province":"Bayern",
    "wof:name":"Gutkes Elektro Vertriebs Gmbh",
    "wof:placetype":"venue"
},
  "geometry": {"coordinates":[11.4571523666,48.7095298767],"type":"Point"}
}