{
  "type": "Feature",
  "properties": {
    "iso:country":"DE",
    "sg:address":"Ramsenweg 2",
    "sg:city":"Braunlage",
    "sg:phone":"+49 5520/2644",
    "sg:postcode":"38700",
    "sg:province":"Niedersachsen",
    "wof:name":"Cafeteria Im Hallenbad",
    "wof:placetype":"venue"
},
  "geometry": {"coordinates":[10.617558,51.726681],"type":"Point"}
}