{
  "type": "Feature",
  "properties": {
    "iso:country":"DE",
    "sg:address":"Poststr. 108",
    "sg:city":"Timmendorfer Strand",
    "sg:phone":"+49 4503/31117",
    "sg:postcode":"23669",
    "sg:province":"Schleswig-Holstein",
    "wof:name":"R. Olsen",
    "wof:placetype":"venue"
},
  "geometry": {"coordinates":[10.800863,53.989777],"type":"Point"}
}