{
  "type": "Feature",
  "properties": {
    "iso:country":"DE",
    "sg:address":"Pflugweg 62F",
    "sg:city":"Adendorf",
    "sg:phone":"+49 4131/981331",
    "sg:postcode":"21365",
    "sg:province":"Niedersachsen",
    "wof:name":"Matthias Stoll",
    "wof:placetype":"venue"
},
  "geometry": {"coordinates":[10.4528646469,53.2851142883],"type":"Point"}
}