{
  "type": "Feature",
  "properties": {
    "iso:country":"DE",
    "sg:address":"K\u00f6nigsteiner Str. 192",
    "sg:city":"Frankfurt",
    "sg:phone":"+49 69/309100",
    "sg:postcode":"65929",
    "sg:province":"Hessen",
    "wof:name":"Hans Solarski",
    "wof:placetype":"venue"
},
  "geometry": {"coordinates":[8.534515,50.114426],"type":"Point"}
}