{
  "type": "Feature",
  "properties": {
    "iso:country":"DE",
    "sg:address":"Ziegelh\u00fctte 9",
    "sg:city":"Mitterteich",
    "sg:phone":"+49 9633/508",
    "sg:postcode":"95666",
    "sg:province":"Bayern",
    "wof:name":"Spedition Schaumberger Verwaltungs Gmbh",
    "wof:placetype":"venue"
},
  "geometry": {"coordinates":[12.2525873184,49.9444122314],"type":"Point"}
}