{
  "type": "Feature",
  "properties": {
    "iso:country":"DE",
    "sg:address":"Nideggener Str. 72",
    "sg:city":"Z\u00fclpich",
    "sg:phone":"+49 2252/2499",
    "sg:postcode":"53909",
    "sg:province":"Nordrhein-Westfalen",
    "wof:name":"Maria Hoff",
    "wof:placetype":"venue"
},
  "geometry": {"coordinates":[6.64439,50.686111],"type":"Point"}
}