{
  "type": "Feature",
  "properties": {
    "iso:country":"DE",
    "sg:address":"Skandinaviendamm 328",
    "sg:city":"Kiel",
    "sg:phone":"+49 431/129308",
    "sg:postcode":"24109",
    "sg:province":"Schleswig-Holstein",
    "wof:name":"K. Kamrani",
    "wof:placetype":"venue"
},
  "geometry": {"coordinates":[10.052647,54.32357],"type":"Point"}
}