{
  "type": "Feature",
  "properties": {
    "iso:country":"DE",
    "sg:address":"Batterieweg 105",
    "sg:city":"Remagen",
    "sg:phone":"+49 2642/44136",
    "sg:postcode":"53424",
    "sg:province":"Rheinland-Pfalz",
    "wof:name":"Wms Beteiligungs Gmbh",
    "wof:placetype":"venue"
},
  "geometry": {"coordinates":[7.265377,50.566551],"type":"Point"}
}