{
  "type": "Feature",
  "properties": {
    "iso:country":"DE",
    "sg:address":"Crostaer Str. 8",
    "sg:city":"Gro\u00dfdubrau",
    "sg:phone":"+49 35934/8906",
    "sg:postcode":"02694",
    "sg:province":"Sachsen",
    "wof:name":"G\u00fcnter Mersiowsky",
    "wof:placetype":"venue"
},
  "geometry": {"coordinates":[14.460498,51.256851],"type":"Point"}
}