{
  "type": "Feature",
  "properties": {
    "iso:country":"DE",
    "sg:address":"Buschstr. 247",
    "sg:city":"Krefeld",
    "sg:phone":"+49 2151/590123",
    "sg:postcode":"47800",
    "sg:province":"Nordrhein-Westfalen",
    "wof:name":"Hotel-restaurant Haus Am Sollbr\u00fcckenpark",
    "wof:placetype":"venue"
},
  "geometry": {"coordinates":[6.609703064,51.34765625],"type":"Point"}
}