{
  "type": "Feature",
  "properties": {
    "iso:country":"DE",
    "sg:address":"Alte Dauner Str. 12",
    "sg:city":"Darscheid",
    "sg:phone":"+49 6592/8008",
    "sg:postcode":"54552",
    "sg:province":"Rheinland-Pfalz",
    "wof:name":"Schmitz Immobilienmakler",
    "wof:placetype":"venue"
},
  "geometry": {"coordinates":[6.8888912201,50.2134246826],"type":"Point"}
}