{
  "type": "Feature",
  "properties": {
    "iso:country":"DE",
    "sg:address":"Diesterwegstr. 7",
    "sg:city":"Frankfurt",
    "sg:phone":"+49 69/622523",
    "sg:postcode":"60594",
    "sg:province":"Hessen",
    "wof:name":"Das Lesecafe",
    "wof:placetype":"venue"
},
  "geometry": {"coordinates":[8.6820459366,50.1015472412],"type":"Point"}
}