{
  "type": "Feature",
  "properties": {
    "iso:country":"DE",
    "sg:address":"Schie\u00dfhausstr. 36",
    "sg:city":"Ludwigshafen",
    "sg:phone":"+49 621/563712",
    "sg:postcode":"67061",
    "sg:province":"Rheinland-Pfalz",
    "wof:name":"S. Autenrieth",
    "wof:placetype":"venue"
},
  "geometry": {"coordinates":[8.450172,49.471199],"type":"Point"}
}