{
  "type": "Feature",
  "properties": {
    "iso:country":"DE",
    "sg:address":"N\u00fcrtinger Str. 42 -2",
    "sg:city":"Neuffen",
    "sg:phone":"+49 7025/7997",
    "sg:postcode":"72639",
    "sg:province":"Baden-W\u00fcrttemberg",
    "wof:name":"Reiner Diez E. K.",
    "wof:placetype":"venue"
},
  "geometry": {"coordinates":[9.372517,48.558243],"type":"Point"}
}