{
  "type": "Feature",
  "properties": {
    "iso:country":"DE",
    "sg:address":"Am Tiergarten 28",
    "sg:city":"Frankfurt",
    "sg:phone":"+49 69/444571",
    "sg:postcode":"60316",
    "sg:province":"Hessen",
    "wof:name":"Hans-j\u00f6rg Schreiber",
    "wof:placetype":"venue"
},
  "geometry": {"coordinates":[8.702286,50.114212],"type":"Point"}
}