{
  "type": "Feature",
  "properties": {
    "iso:country":"DE",
    "sg:address":"Karolinenstr. 25",
    "sg:city":"N\u00fcrnberg",
    "sg:phone":"+49 911/203451",
    "sg:postcode":"90402",
    "sg:province":"Bayern",
    "wof:name":"Burkert Gmbh Eisenwaren",
    "wof:placetype":"venue"
},
  "geometry": {"coordinates":[11.075605,49.450886],"type":"Point"}
}