{
  "type": "Feature",
  "properties": {
    "iso:country":"DE",
    "sg:address":"Am Euzenberg 25",
    "sg:city":"Duderstadt",
    "sg:phone":"+49 5527/5488",
    "sg:postcode":"37115",
    "sg:province":"Niedersachsen",
    "wof:name":"Arnold Ehrhardt",
    "wof:placetype":"venue"
},
  "geometry": {"coordinates":[10.241128,51.508308],"type":"Point"}
}