{
  "type": "Feature",
  "properties": {
    "iso:country":"DE",
    "sg:address":"Unterm Ohmberg 2",
    "sg:city":"Marsberg",
    "sg:phone":"+49 2992/908411",
    "sg:postcode":"34431",
    "sg:province":"Nordrhein-Westfalen",
    "wof:name":"Centroplast Kunststofferzeugnisse",
    "wof:placetype":"venue"
},
  "geometry": {"coordinates":[8.870978,51.474712],"type":"Point"}
}