{
  "type": "Feature",
  "properties": {
    "iso:country":"DE",
    "sg:address":"Mecklenburger Str. 32",
    "sg:city":"Cuxhaven",
    "sg:phone":"+49 4723/3632",
    "sg:postcode":"27478",
    "sg:province":"Niedersachsen",
    "wof:name":"Ev. Pfarramt Ii Cuxhaven-altenwalde",
    "wof:placetype":"venue"
},
  "geometry": {"coordinates":[8.6602144241,53.8111343384],"type":"Point"}
}