{
  "type": "Feature",
  "properties": {
    "iso:country":"DE",
    "sg:address":"An der M\u00fchlenriede 36",
    "sg:city":"Wolfsburg",
    "sg:phone":"+49 5362/5680",
    "sg:postcode":"38442",
    "sg:province":"Niedersachsen",
    "wof:name":"K. Hildenbrand",
    "wof:placetype":"venue"
},
  "geometry": {"coordinates":[10.69194,52.39349],"type":"Point"}
}