{
  "type": "Feature",
  "properties": {
    "iso:country":"DE",
    "sg:address":"Saal\u00e4ckerstr. 8",
    "sg:city":"Kleinostheim",
    "sg:phone":"+49 6027/46160",
    "sg:postcode":"63801",
    "sg:province":"Bayern",
    "wof:name":"Lbi - Lutz",
    "wof:placetype":"venue"
},
  "geometry": {"coordinates":[9.0723371506,49.9952087402],"type":"Point"}
}