{
  "type": "Feature",
  "properties": {
    "iso:country":"DE",
    "sg:address":"St.-Josef-Str. 141",
    "sg:city":"Ibbenb\u00fcren",
    "sg:phone":"+49 5451/590859",
    "sg:postcode":"49479",
    "sg:province":"Nordrhein-Westfalen",
    "wof:name":"Concept-spedition Und Logistik Gmbh",
    "wof:placetype":"venue"
},
  "geometry": {"coordinates":[7.6705417633,52.2763290405],"type":"Point"}
}