{
  "type": "Feature",
  "properties": {
    "iso:country":"DE",
    "sg:address":"Stahlschmidtsbr\u00fccke 32",
    "sg:city":"H\u00fcckeswagen",
    "sg:postcode":"42499",
    "sg:province":"Nordrhein-Westfalen",
    "wof:name":"Kratzer & G\u00fcldenpfennig Ohg",
    "wof:placetype":"venue"
},
  "geometry": {"coordinates":[7.3353562355,51.133846283],"type":"Point"}
}