{
  "type": "Feature",
  "properties": {
    "iso:country":"DE",
    "sg:address":"Georgewitzer Str. 25",
    "sg:city":"L\u00f6bau",
    "sg:postcode":"02708",
    "sg:province":"Sachsen",
    "wof:name":"F & F Freizeit- Und Fitne\u00df- Center Gmbh",
    "wof:placetype":"venue"
},
  "geometry": {"coordinates":[14.6835689545,51.105178833],"type":"Point"}
}