{
  "type": "Feature",
  "properties": {
    "iso:country":"DE",
    "sg:address":"Wurzacher Str. 4",
    "sg:city":"Leutkirch",
    "sg:phone":"+49 7561/4802",
    "sg:postcode":"88299",
    "sg:province":"Baden-W\u00fcrttemberg",
    "wof:name":"Walter Hohl",
    "wof:placetype":"venue"
},
  "geometry": {"coordinates":[10.0178146362,47.8267364502],"type":"Point"}
}