{
  "type": "Feature",
  "properties": {
    "iso:country":"DE",
    "sg:address":"Neum\u00e4rker Str. 21",
    "sg:city":"Helmstedt",
    "sg:phone":"+49 5351/6168",
    "sg:postcode":"38350",
    "sg:province":"Niedersachsen",
    "wof:name":"H. Berlin Gmbh & Co. Kg",
    "wof:placetype":"venue"
},
  "geometry": {"coordinates":[11.0057878494,52.2276382446],"type":"Point"}
}