{
  "type": "Feature",
  "properties": {
    "iso:country":"DE",
    "sg:address":"Hauptstr. 58b",
    "sg:city":"Aarbergen",
    "sg:phone":"+49 6120/3940",
    "sg:postcode":"65326",
    "sg:province":"Hessen",
    "wof:name":"E. Haas",
    "wof:placetype":"venue"
},
  "geometry": {"coordinates":[8.05818,50.233089],"type":"Point"}
}