{
  "type": "Feature",
  "properties": {
    "iso:country":"DE",
    "sg:address":"Haffstr 36",
    "sg:city":"Dollerup",
    "sg:phone":"+49 4636/1039",
    "sg:postcode":"24989",
    "sg:province":"Schleswig-Holstein",
    "wof:name":"Tvg Tankvertriebsges. Mbh",
    "wof:placetype":"venue"
},
  "geometry": {"coordinates":[9.6712198257,54.7962303162],"type":"Point"}
}