{
  "type": "Feature",
  "properties": {
    "iso:country":"DE",
    "sg:address":"Bahnhofstr. 8",
    "sg:city":"Eschwege",
    "sg:phone":"+49 5651/3595",
    "sg:postcode":"37269",
    "sg:province":"Hessen",
    "wof:name":"G. Reis",
    "wof:placetype":"venue"
},
  "geometry": {"coordinates":[10.046620369,51.1913108826],"type":"Point"}
}