{
  "type": "Feature",
  "properties": {
    "iso:country":"DE",
    "sg:address":"Kollwitzstr. 77",
    "sg:city":"Berlin",
    "sg:phone":"+49 30/41716928",
    "sg:postcode":"10435",
    "sg:province":"Berlin",
    "wof:name":"Kinderinsel Gmbh",
    "wof:placetype":"venue"
},
  "geometry": {"coordinates":[13.4191560745,52.5375366211],"type":"Point"}
}