{
  "type": "Feature",
  "properties": {
    "iso:country":"DE",
    "sg:address":"Alleestr. 24",
    "sg:city":"Bad Soden",
    "sg:phone":"+49 6196/670276",
    "sg:postcode":"65812",
    "sg:province":"Hessen",
    "wof:name":"Indisches Restaurant Maharani",
    "wof:placetype":"venue"
},
  "geometry": {"coordinates":[8.4993038177,50.1401863098],"type":"Point"}
}