{
  "type": "Feature",
  "properties": {
    "iso:country":"DE",
    "sg:address":"Reisstr. 12",
    "sg:city":"Hadamar",
    "sg:phone":"+49 6433/2183",
    "sg:postcode":"65589",
    "sg:province":"Hessen",
    "wof:name":"Helmut Schick",
    "wof:placetype":"venue"
},
  "geometry": {"coordinates":[8.0322742462,50.4362869263],"type":"Point"}
}