{
  "type": "Feature",
  "properties": {
    "iso:country":"DE",
    "sg:address":"Gut-D\u00e4mme-Str. 11 -13",
    "sg:city":"Aachen",
    "sg:phone":"+49 241/918060",
    "sg:postcode":"52070",
    "sg:province":"Nordrhein-Westfalen",
    "wof:name":"Gimret-gesellschaft F\u00fcr Industrieanl. Der Me\u00df- Regel-",
    "wof:placetype":"venue"
},
  "geometry": {"coordinates":[6.106061,50.796314],"type":"Point"}
}