{
  "type": "Feature",
  "properties": {
    "iso:country":"DE",
    "sg:address":"Friedensstr. 1",
    "sg:city":"Kerken",
    "sg:phone":"+49 2833/3515",
    "sg:postcode":"47647",
    "sg:province":"Nordrhein-Westfalen",
    "wof:name":"Georg Dicks Rechtsanwalt",
    "wof:placetype":"venue"
},
  "geometry": {"coordinates":[6.3739600182,51.4571609497],"type":"Point"}
}