{
  "type": "Feature",
  "properties": {
    "iso:country":"DE",
    "sg:address":"Hauptstr. 82",
    "sg:city":"Carlsfeld",
    "sg:phone":"+49 37752/2112",
    "sg:postcode":"08325",
    "wof:name":"Glaswerk Olbernhau",
    "wof:placetype":"venue"
},
  "geometry": {"coordinates":[12.5805072784,50.4374656677],"type":"Point"}
}