{
  "type": "Feature",
  "properties": {
    "iso:country":"DE",
    "sg:address":"Kirchheidstr. 16",
    "sg:city":"Aachen",
    "sg:phone":"+49 4924/1562018",
    "sg:postcode":"52078",
    "sg:province":"Nordrhein-Westfalen",
    "wof:name":"Automation & Formenbau Afg Gmbh",
    "wof:placetype":"venue"
},
  "geometry": {"coordinates":[6.1612801552,50.7491226196],"type":"Point"}
}