{
  "type": "Feature",
  "properties": {
    "iso:country":"DE",
    "sg:address":"Haardtstr. 1",
    "sg:city":"Limburgerhof",
    "sg:phone":"+49 6236/6459",
    "sg:postcode":"67117",
    "sg:province":"Rheinland-Pfalz",
    "wof:name":"Spinatwachtel",
    "wof:placetype":"venue"
},
  "geometry": {"coordinates":[8.3962507248,49.4197235107],"type":"Point"}
}