{
  "type": "Feature",
  "properties": {
    "iso:country":"DE",
    "sg:address":"Hauptstr. 61",
    "sg:city":"Korschenbroich",
    "sg:phone":"+49 2182/50644",
    "sg:postcode":"41352",
    "sg:province":"Nordrhein-Westfalen",
    "wof:name":"Hans J. Rakels",
    "wof:placetype":"venue"
},
  "geometry": {"coordinates":[6.57631,51.165443],"type":"Point"}
}