{
  "type": "Feature",
  "properties": {
    "iso:country":"DE",
    "sg:address":"Limpurger Platz",
    "sg:city":"Schw\u00e4bisch Hall",
    "sg:phone":"+49 791/47979",
    "sg:postcode":"74523",
    "sg:province":"Baden-W\u00fcrttemberg",
    "wof:name":"Gabriele R\u00f6\u00dfler",
    "wof:placetype":"venue"
},
  "geometry": {"coordinates":[9.7513799667,49.1154289246],"type":"Point"}
}