{
  "type": "Feature",
  "properties": {
    "iso:country":"DE",
    "sg:address":"Joh-Friedr-Oberlin-Str 11-13",
    "sg:city":"Hagen",
    "sg:phone":"+49 2331/3680",
    "sg:postcode":"58099",
    "sg:province":"Nordrhein-Westfalen",
    "wof:name":"Helmut-turck-zentrum Seniorenheim",
    "wof:placetype":"venue"
},
  "geometry": {"coordinates":[7.481714,51.391994],"type":"Point"}
}