{
  "type": "Feature",
  "properties": {
    "iso:country":"DE",
    "sg:address":"Kapuzinerstr. 26",
    "sg:city":"Bamberg",
    "sg:phone":"+49 951/25025",
    "sg:postcode":"96047",
    "sg:province":"Bayern",
    "wof:name":"Bauunternehmung T\u00f6ppner Gmbh",
    "wof:placetype":"venue"
},
  "geometry": {"coordinates":[10.885597,49.894474],"type":"Point"}
}