{
  "type": "Feature",
  "properties": {
    "iso:country":"DE",
    "sg:address":"Buchhorst 6",
    "sg:city":"Wehrbleck",
    "sg:phone":"+49 4274/266",
    "sg:postcode":"27259",
    "sg:province":"Niedersachsen",
    "wof:name":"Wilhelm L\u00fcdeke",
    "wof:placetype":"venue"
},
  "geometry": {"coordinates":[8.711081,52.642464],"type":"Point"}
}