{
  "type": "Feature",
  "properties": {
    "iso:country":"DE",
    "sg:address":"Albersloher Weg 1",
    "sg:city":"M\u00fcnster",
    "sg:phone":"+49 251/609250",
    "sg:postcode":"48155",
    "sg:province":"Nordrhein-Westfalen",
    "wof:name":"Hotel T. Beisenk\u00f6tter",
    "wof:placetype":"venue"
},
  "geometry": {"coordinates":[7.6364798546,51.9524307251],"type":"Point"}
}