{
  "type": "Feature",
  "properties": {
    "iso:country":"DE",
    "sg:address":"Budenheimer Str. 1",
    "sg:city":"Mainz",
    "sg:phone":"+49 6131/910460",
    "sg:postcode":"55124",
    "sg:province":"Rheinland-Pfalz",
    "wof:name":"Franz Ludwig Gmbh",
    "wof:placetype":"venue"
},
  "geometry": {"coordinates":[8.207201004,49.9985618591],"type":"Point"}
}