{
  "type": "Feature",
  "properties": {
    "iso:country":"DE",
    "sg:address":"Cosimastr. 2",
    "sg:city":"M\u00fcnchen",
    "sg:phone":"+49 89/911024",
    "sg:postcode":"81927",
    "sg:province":"Bayern",
    "wof:name":"Hc Heraldic Consult Beratungs- Gmbh",
    "wof:placetype":"venue"
},
  "geometry": {"coordinates":[11.6298303604,48.1538505554],"type":"Point"}
}