{
  "type": "Feature",
  "properties": {
    "iso:country":"DE",
    "sg:address":"Plenterstr. 72",
    "sg:city":"Kr\u00f6v",
    "sg:phone":"+49 6541/3489",
    "sg:postcode":"54536",
    "sg:province":"Rheinland-Pfalz",
    "wof:name":"H. Und D. R\u00f6mer",
    "wof:placetype":"venue"
},
  "geometry": {"coordinates":[7.0826182365,49.9750061035],"type":"Point"}
}