{
  "type": "Feature",
  "properties": {
    "iso:country":"DE",
    "sg:address":"Steinlache 4",
    "sg:city":"Themar",
    "sg:phone":"+49 36873/60454",
    "sg:postcode":"98660",
    "sg:province":"Th\u00fcringen",
    "wof:name":"Tfa - Themar Fischzucht- Anlagen Gmbh",
    "wof:placetype":"venue"
},
  "geometry": {"coordinates":[10.6151046753,50.5060768127],"type":"Point"}
}