{
  "type": "Feature",
  "properties": {
    "iso:country":"DE",
    "sg:address":"Am Waldfriedhof 14",
    "sg:city":"Mainz",
    "sg:phone":"+49 6131/685013",
    "sg:postcode":"55120",
    "sg:province":"Rheinland-Pfalz",
    "wof:name":"Dachbau Reinartz Gmbh",
    "wof:placetype":"venue"
},
  "geometry": {"coordinates":[8.201473,50.022217],"type":"Point"}
}