{
  "type": "Feature",
  "properties": {
    "iso:country":"DE",
    "sg:address":"Koringstr. 17",
    "sg:city":"Bremen",
    "sg:phone":"+49 421/665789",
    "sg:postcode":"28755",
    "sg:province":"Bremen",
    "wof:name":"Arbeitslosen Und Sozialhilfe- Empf\u00e4nger Organisation Bremen",
    "wof:placetype":"venue"
},
  "geometry": {"coordinates":[8.6330127716,53.1859855652],"type":"Point"}
}