{
  "type": "Feature",
  "properties": {
    "iso:country":"DE",
    "sg:address":"Wismarer Weg 10",
    "sg:city":"Strasburg",
    "sg:phone":"+49 39753/22725",
    "sg:postcode":"17335",
    "sg:province":"Mecklenburg-Vorpommern",
    "wof:name":"Ingenieurb\u00fcro \u00d6ku-projekt",
    "wof:placetype":"venue"
},
  "geometry": {"coordinates":[13.7560358047,53.5086021423],"type":"Point"}
}