{
  "type": "Feature",
  "properties": {
    "iso:country":"DE",
    "sg:address":"Hauptstr. 22",
    "sg:city":"B\u00fcttstedt",
    "sg:phone":"+49 36075/64235",
    "sg:postcode":"37359",
    "sg:province":"Th\u00fcringen",
    "wof:name":"G. T\u00f6pfer",
    "wof:placetype":"venue"
},
  "geometry": {"coordinates":[10.3093109131,51.2598571777],"type":"Point"}
}