{
  "type": "Feature",
  "properties": {
    "iso:country":"DE",
    "sg:address":"August-Wilhelm-Pf\u00e4ffle-Str. 8",
    "sg:city":"Lorch",
    "sg:phone":"+49 7172/926120",
    "sg:postcode":"73547",
    "sg:province":"Baden-W\u00fcrttemberg",
    "wof:name":"Pf\u00e4ffle Gmbh",
    "wof:placetype":"venue"
},
  "geometry": {"coordinates":[9.690343,48.797295],"type":"Point"}
}