{
  "type": "Feature",
  "properties": {
    "iso:country":"DE",
    "sg:address":"Gartenstr. 2a",
    "sg:city":"Berg",
    "sg:phone":"+49 7273/93370",
    "sg:postcode":"76768",
    "sg:province":"Rheinland-Pfalz",
    "wof:name":"R. Gebhard Und R. Franke Architekten",
    "wof:placetype":"venue"
},
  "geometry": {"coordinates":[7.8132,50.254734],"type":"Point"}
}