{
  "type": "Feature",
  "properties": {
    "iso:country":"DE",
    "sg:address":"Uferstr. 10",
    "sg:city":"Remshalden",
    "sg:phone":"+49 7151/71586",
    "sg:postcode":"73630",
    "sg:province":"Baden-W\u00fcrttemberg",
    "wof:name":"Hans-peter Kleinmaier",
    "wof:placetype":"venue"
},
  "geometry": {"coordinates":[9.4157018661,48.8126335144],"type":"Point"}
}