{
  "type": "Feature",
  "properties": {
    "iso:country":"DE",
    "sg:address":"Im Hanfl\u00e4nder 5",
    "sg:city":"Lahr",
    "sg:phone":"+49 7821/983998",
    "sg:postcode":"77933",
    "sg:province":"Baden-W\u00fcrttemberg",
    "wof:name":"Werchan Dental Gmbh",
    "wof:placetype":"venue"
},
  "geometry": {"coordinates":[7.807255,48.313477],"type":"Point"}
}