{
  "type": "Feature",
  "properties": {
    "iso:country":"DE",
    "sg:address":"Trierer Str. 9",
    "sg:city":"Koblenz",
    "sg:phone":"+49 261/802418",
    "sg:postcode":"56072",
    "sg:province":"Rheinland-Pfalz",
    "wof:name":"K. Ollig",
    "wof:placetype":"venue"
},
  "geometry": {"coordinates":[7.57667,50.370129],"type":"Point"}
}