{
  "type": "Feature",
  "properties": {
    "iso:country":"DE",
    "sg:address":"Burgweg 2 a",
    "sg:city":"Bad Bocklet",
    "sg:phone":"+49 9708/1639",
    "sg:postcode":"97708",
    "sg:province":"Bayern",
    "wof:name":"Hermann Wirsching",
    "wof:placetype":"venue"
},
  "geometry": {"coordinates":[10.058082,50.255974],"type":"Point"}
}