{
  "type": "Feature",
  "properties": {
    "iso:country":"DE",
    "sg:address":"\u00d6lendorf",
    "sg:city":"Neukirchen",
    "sg:phone":"+49 4365/7454",
    "sg:postcode":"23779",
    "sg:province":"Schleswig-Holstein",
    "wof:name":"J. Gr\u00fcgelsiepe Ingenieur",
    "wof:placetype":"venue"
},
  "geometry": {"coordinates":[11.0528459549,54.3240623474],"type":"Point"}
}