{
  "type": "Feature",
  "properties": {
    "iso:country":"DE",
    "sg:address":"Amselweg 31",
    "sg:city":"Remseck",
    "sg:phone":"+49 7146/821236",
    "sg:postcode":"71686",
    "sg:province":"Baden-W\u00fcrttemberg",
    "wof:name":"Berolina Schriftbild S\u00fcdwest K. H. Hirner Gmbh",
    "wof:placetype":"venue"
},
  "geometry": {"coordinates":[9.276971817,48.8724403381],"type":"Point"}
}