{
  "type": "Feature",
  "properties": {
    "iso:country":"DE",
    "sg:address":"Springeltwiete 7",
    "sg:city":"Hamburg",
    "sg:phone":"+49 40/338416",
    "sg:postcode":"20095",
    "sg:province":"Hamburg",
    "wof:name":"J\u00f6rg Stolze Steuerberater",
    "wof:placetype":"venue"
},
  "geometry": {"coordinates":[10.0031986237,53.5497436523],"type":"Point"}
}