{
  "type": "Feature",
  "properties": {
    "iso:country":"DE",
    "sg:address":"Wernher-von-Braun-Str. 10",
    "sg:city":"Putzbrunn",
    "sg:phone":"+49 89/4565500",
    "sg:postcode":"85640",
    "sg:province":"Bayern",
    "wof:name":"Conti Grundverm\u00f6gen Gmbh",
    "wof:placetype":"venue"
},
  "geometry": {"coordinates":[11.7198619843,48.0775260925],"type":"Point"}
}