{
  "type": "Feature",
  "properties": {
    "iso:country":"DE",
    "sg:address":"Hindenburgstr. 3",
    "sg:city":"Bad Sachsa",
    "sg:phone":"+49 5523/2192",
    "sg:postcode":"37441",
    "sg:province":"Niedersachsen",
    "wof:name":"Hotel Haus Hasenpatt Garni",
    "wof:placetype":"venue"
},
  "geometry": {"coordinates":[10.5501928329,51.59715271],"type":"Point"}
}