{
  "type": "Feature",
  "properties": {
    "iso:country":"DE",
    "sg:address":"Sebastian-Englerth-Str. 5a",
    "sg:city":"Randersacker",
    "sg:phone":"+49 931/414473",
    "sg:postcode":"97236",
    "sg:province":"Bayern",
    "wof:name":"Peter Krischke",
    "wof:placetype":"venue"
},
  "geometry": {"coordinates":[9.991391,49.76606],"type":"Point"}
}