{
  "type": "Feature",
  "properties": {
    "iso:country":"DE",
    "sg:address":"Kirchstr. 1",
    "sg:city":"Mengerskirchen",
    "sg:phone":"+49 6476/8303",
    "sg:postcode":"35794",
    "sg:province":"Hessen",
    "wof:name":"Zum Schwarzen B\u00e4ren",
    "wof:placetype":"venue"
},
  "geometry": {"coordinates":[8.1553964615,50.5655632019],"type":"Point"}
}