{
  "type": "Feature",
  "properties": {
    "iso:country":"DE",
    "sg:address":"K\u00f6nigstr. 2",
    "sg:city":"G\u00fctersloh",
    "sg:phone":"+49 5241/15552",
    "sg:postcode":"33330",
    "sg:province":"Nordrhein-Westfalen",
    "wof:name":"Parf\u00fcmerie Douglas West Gmbh & Co. Kg",
    "wof:placetype":"venue"
},
  "geometry": {"coordinates":[8.378555,51.90641],"type":"Point"}
}