{
  "type": "Feature",
  "properties": {
    "iso:country":"DE",
    "sg:address":"Schillerstr. 72",
    "sg:city":"Erfurt",
    "sg:postcode":"99096",
    "sg:province":"Th\u00fcringen",
    "wof:name":"Deutsche Verm\u00f6gensberatung Ag",
    "wof:placetype":"venue"
},
  "geometry": {"coordinates":[11.0217294693,50.9659156799],"type":"Point"}
}