{
  "type": "Feature",
  "properties": {
    "iso:country":"DE",
    "sg:address":"Hasestr. 55",
    "sg:city":"Osnabr\u00fcck",
    "sg:phone":"+49 541/201730",
    "sg:postcode":"49074",
    "sg:province":"Niedersachsen",
    "wof:name":"Gastst\u00e4tte Pilatus",
    "wof:placetype":"venue"
},
  "geometry": {"coordinates":[8.0438556671,52.279548645],"type":"Point"}
}