{
  "type": "Feature",
  "properties": {
    "iso:country":"DE",
    "sg:address":"Friedhofstr. 2",
    "sg:city":"Bad Urach",
    "sg:phone":"+49 7125/2142",
    "sg:postcode":"72574",
    "sg:province":"Baden-W\u00fcrttemberg",
    "wof:name":"Erwin Stoo\u00df",
    "wof:placetype":"venue"
},
  "geometry": {"coordinates":[9.46384,48.483383],"type":"Point"}
}