{
  "type": "Feature",
  "properties": {
    "iso:country":"DE",
    "sg:address":"Rohfeld 4",
    "sg:city":"Herford",
    "sg:phone":"+49 5221/70819",
    "sg:postcode":"32052",
    "sg:province":"Nordrhein-Westfalen",
    "wof:name":"G\u00fcnter Berg",
    "wof:placetype":"venue"
},
  "geometry": {"coordinates":[8.666779,52.105324],"type":"Point"}
}