{
  "type": "Feature",
  "properties": {
    "iso:country":"DE",
    "sg:address":"Venloer Str. 8",
    "sg:city":"Viersen",
    "sg:phone":"+49 2162/55117",
    "sg:postcode":"41751",
    "sg:province":"Nordrhein-Westfalen",
    "wof:name":"B. Schumacher",
    "wof:placetype":"venue"
},
  "geometry": {"coordinates":[6.331223,51.251919],"type":"Point"}
}