{
  "type": "Feature",
  "properties": {
    "iso:country":"DE",
    "sg:address":"Am Jagdhaus 108",
    "sg:city":"Wuppertal",
    "sg:phone":"+49 202/2721080",
    "sg:postcode":"42113",
    "sg:province":"Nordrhein-Westfalen",
    "wof:name":"Michael Jaroch Immobilienmakler",
    "wof:placetype":"venue"
},
  "geometry": {"coordinates":[7.1058049202,51.2786636353],"type":"Point"}
}