{
  "type": "Feature",
  "properties": {
    "iso:country":"DE",
    "sg:address":"Beethovenstr. 7",
    "sg:city":"Itzehoe",
    "sg:postcode":"25524",
    "sg:province":"Schleswig-Holstein",
    "wof:name":"Exakt Ag",
    "wof:placetype":"venue"
},
  "geometry": {"coordinates":[9.5200834274,53.9317054749],"type":"Point"}
}