{
  "type": "Feature",
  "properties": {
    "iso:country":"DE",
    "sg:address":"Hoher Kamp 25",
    "sg:city":"G\u00fctersloh",
    "sg:phone":"+49 5241/4238",
    "sg:postcode":"33332",
    "sg:province":"Nordrhein-Westfalen",
    "wof:name":"Richter",
    "wof:placetype":"venue"
},
  "geometry": {"coordinates":[8.3887395859,51.8815612793],"type":"Point"}
}