{
  "type": "Feature",
  "properties": {
    "iso:country":"DE",
    "sg:address":"In den Birken 27",
    "sg:city":"Hinterweidenthal",
    "sg:phone":"+49 6396/287",
    "sg:postcode":"66999",
    "sg:province":"Rheinland-Pfalz",
    "wof:name":"A. Calucci",
    "wof:placetype":"venue"
},
  "geometry": {"coordinates":[7.751754,49.189583],"type":"Point"}
}