{
  "type": "Feature",
  "properties": {
    "iso:country":"DE",
    "sg:address":"Poststr. 4",
    "sg:city":"Zerf",
    "sg:phone":"+49 6587/252",
    "sg:postcode":"54314",
    "sg:province":"Rheinland-Pfalz",
    "wof:name":"Josef Steinbach Elektroinstallation",
    "wof:placetype":"venue"
},
  "geometry": {"coordinates":[6.687189,49.600903],"type":"Point"}
}