{
  "type": "Feature",
  "properties": {
    "iso:country":"DE",
    "sg:address":"Oldenburger Str. 32",
    "sg:city":"Zetel",
    "sg:phone":"+49 4453/4999",
    "sg:postcode":"26340",
    "sg:province":"Niedersachsen",
    "wof:name":"Haus Shiva",
    "wof:placetype":"venue"
},
  "geometry": {"coordinates":[7.973669,53.411736],"type":"Point"}
}