{
  "type": "Feature",
  "properties": {
    "iso:country":"DE",
    "sg:address":"Gro\u00dfkahler Str. 23",
    "sg:city":"Kleinkahl",
    "sg:phone":"+49 6024/80556",
    "sg:postcode":"63828",
    "sg:province":"Bayern",
    "wof:name":"Agt Abgastechnik E. K.",
    "wof:placetype":"venue"
},
  "geometry": {"coordinates":[9.276395,50.108715],"type":"Point"}
}