{
  "type": "Feature",
  "properties": {
    "iso:country":"DE",
    "sg:address":"H\u00f6fstr. 1",
    "sg:city":"Lichtenstein",
    "sg:phone":"+49 7129/6423",
    "sg:postcode":"72805",
    "sg:province":"Baden-W\u00fcrttemberg",
    "wof:name":"Silvia Metzger",
    "wof:placetype":"venue"
},
  "geometry": {"coordinates":[9.258628,48.433804],"type":"Point"}
}