{
  "type": "Feature",
  "properties": {
    "iso:country":"DE",
    "sg:address":"Hauptstr. 50",
    "sg:city":"Sch\u00f6nau-Berzdorf",
    "sg:phone":"+49 35874/27214",
    "sg:postcode":"02899",
    "sg:province":"Sachsen",
    "wof:name":"Wei\u00dfes R\u00f6ssel",
    "wof:placetype":"venue"
},
  "geometry": {"coordinates":[14.8819675446,51.0618858337],"type":"Point"}
}