{
  "type": "Feature",
  "properties": {
    "iso:country":"DE",
    "sg:address":"Am Plessenfelde 1",
    "sg:city":"Hannover",
    "sg:phone":"+49 511/6490085",
    "sg:postcode":"30659",
    "sg:province":"Niedersachsen",
    "wof:name":"Karin Bodirsky Heilpraktikerin",
    "wof:placetype":"venue"
},
  "geometry": {"coordinates":[9.7982997894,52.4062767029],"type":"Point"}
}