{
  "type": "Feature",
  "properties": {
    "iso:country":"DE",
    "sg:address":"Talerweg 12",
    "sg:city":"M\u00fcnchen",
    "sg:phone":"+49 89/438963",
    "sg:postcode":"81825",
    "sg:province":"Bayern",
    "wof:name":"E. Graml",
    "wof:placetype":"venue"
},
  "geometry": {"coordinates":[11.6533117294,48.1239585876],"type":"Point"}
}