{
  "type": "Feature",
  "properties": {
    "iso:country":"DE",
    "sg:address":"Eschenauer Str. 40",
    "sg:city":"Lauf",
    "sg:phone":"+49 9123/2883",
    "sg:postcode":"91207",
    "sg:province":"Bayern",
    "wof:name":"Ernst Steger",
    "wof:placetype":"venue"
},
  "geometry": {"coordinates":[11.268336,49.510899],"type":"Point"}
}