{
  "type": "Feature",
  "properties": {
    "iso:country":"DE",
    "sg:address":"Schartauer Str. 17",
    "sg:city":"Burg",
    "sg:phone":"+49 3921/982527",
    "sg:postcode":"39288",
    "sg:province":"Sachsen-Anhalt",
    "wof:name":"Elke Stolt Rechtsanw\u00e4ltin",
    "wof:placetype":"venue"
},
  "geometry": {"coordinates":[11.8522224426,52.2712097168],"type":"Point"}
}