{
  "type": "Feature",
  "properties": {
    "iso:country":"DE",
    "sg:address":"Stra\u00dfe der Freundschaft 13",
    "sg:city":"Gro\u00df Germersleben",
    "sg:phone":"+49 39408/480",
    "sg:postcode":"39398",
    "sg:province":"Sachsen-Anhalt",
    "wof:name":"Heinz Naeter",
    "wof:placetype":"venue"
},
  "geometry": {"coordinates":[11.301653,51.99004],"type":"Point"}
}