{
  "type": "Feature",
  "properties": {
    "iso:country":"DE",
    "sg:address":"Marktstr. 9",
    "sg:city":"Cottbus",
    "sg:phone":"+49 355/79523637",
    "sg:postcode":"03046",
    "sg:province":"Brandenburg",
    "wof:name":"Silvia Lion Cottbus",
    "wof:placetype":"venue"
},
  "geometry": {"coordinates":[14.3316612244,51.7602882385],"type":"Point"}
}