{
  "type": "Feature",
  "properties": {
    "iso:country":"DE",
    "sg:address":"M\u00f6rikestr. 14",
    "sg:city":"Weissach",
    "sg:phone":"+49 7191/53898",
    "sg:postcode":"71554",
    "sg:province":"Baden-W\u00fcrttemberg",
    "wof:name":"Kurt Bauer",
    "wof:placetype":"venue"
},
  "geometry": {"coordinates":[8.930994,48.849483],"type":"Point"}
}