{
  "type": "Feature",
  "properties": {
    "iso:country":"DE",
    "sg:address":"Gerichtsstr. 21",
    "sg:city":"Oldenburg",
    "sg:phone":"+49 441/12424",
    "sg:postcode":"26135",
    "sg:province":"Niedersachsen",
    "wof:name":"Kruse Und Partner Architekten",
    "wof:placetype":"venue"
},
  "geometry": {"coordinates":[8.216995,53.133057],"type":"Point"}
}