{
  "type": "Feature",
  "properties": {
    "iso:country":"DE",
    "sg:address":"Berthold-Schwarz-Str. 26",
    "sg:city":"Ludwigshafen",
    "sg:phone":"+49 621/695051",
    "sg:postcode":"67063",
    "sg:province":"Rheinland-Pfalz",
    "wof:name":"Prof. Gerd Heene Architekt",
    "wof:placetype":"venue"
},
  "geometry": {"coordinates":[8.417216,49.495956],"type":"Point"}
}