{
  "type": "Feature",
  "properties": {
    "iso:country":"DE",
    "sg:address":"Cranachstr. 19",
    "sg:city":"Weimar",
    "sg:phone":"+49 3643/853208",
    "sg:postcode":"99423",
    "sg:province":"Th\u00fcringen",
    "wof:name":"Dr. Siegfried Matten Ingenieur",
    "wof:placetype":"venue"
},
  "geometry": {"coordinates":[11.320687294,50.9739494324],"type":"Point"}
}