{
  "type": "Feature",
  "properties": {
    "iso:country":"DE",
    "sg:address":"Im Aatal 2",
    "sg:city":"W\u00fcnnenberg",
    "sg:phone":"+49 2953/8087",
    "sg:postcode":"33181",
    "sg:province":"Nordrhein-Westfalen",
    "wof:name":"Volksbank W\u00fcnnenberg",
    "wof:placetype":"venue"
},
  "geometry": {"coordinates":[8.699819,51.519272],"type":"Point"}
}