{
  "type": "Feature",
  "properties": {
    "iso:country":"DE",
    "sg:address":"Sch\u00fctzenstr. 42",
    "sg:city":"Winterberg",
    "sg:phone":"+49 2981/2988",
    "sg:postcode":"59955",
    "sg:province":"Nordrhein-Westfalen",
    "wof:name":"Berghotel Kubiak",
    "wof:placetype":"venue"
},
  "geometry": {"coordinates":[8.568810463,51.1565818787],"type":"Point"}
}