{
  "type": "Feature",
  "properties": {
    "iso:country":"DE",
    "sg:address":"Rosengartenstr. 7",
    "sg:city":"Rottenburg",
    "sg:phone":"+49 7457/1609",
    "sg:postcode":"72108",
    "sg:province":"Baden-W\u00fcrttemberg",
    "wof:name":"E. Wellh\u00e4usser",
    "wof:placetype":"venue"
},
  "geometry": {"coordinates":[8.8679180145,48.5280456543],"type":"Point"}
}