{
  "type": "Feature",
  "properties": {
    "iso:country":"DE",
    "sg:address":"Am Venusberg 7",
    "sg:city":"Chieming",
    "sg:phone":"+49 8664/284",
    "sg:postcode":"83339",
    "sg:province":"Bayern",
    "wof:name":"Bruno L\u00f6ssl Verkaufshilfen Aus Draht",
    "wof:placetype":"venue"
},
  "geometry": {"coordinates":[12.5366344452,47.8869819641],"type":"Point"}
}