{
  "type": "Feature",
  "properties": {
    "iso:country":"DE",
    "sg:address":"Ummendorfer Str. 6",
    "sg:city":"Magdeburg",
    "sg:postcode":"39110",
    "sg:province":"Sachsen-Anhalt",
    "wof:name":"Baugesch\u00e4ft Christian Schmidt Gmbh",
    "wof:placetype":"venue"
},
  "geometry": {"coordinates":[11.571217,52.129593],"type":"Point"}
}