{
  "type": "Feature",
  "properties": {
    "iso:country":"DE",
    "sg:address":"Provinzialstr. 115",
    "sg:city":"Saarlouis",
    "sg:phone":"+49 6831/40674",
    "sg:postcode":"66740",
    "sg:province":"Saarland",
    "wof:name":"Erhard Ecker",
    "wof:placetype":"venue"
},
  "geometry": {"coordinates":[6.7604842186,49.2990531921],"type":"Point"}
}