{
  "type": "Feature",
  "properties": {
    "iso:country":"DE",
    "sg:city":"Drochtersen",
    "sg:postcode":"21706",
    "sg:province":"Niedersachsen",
    "wof:name":"Ms Meta Beteiligungs- Gesellschaft Mbh",
    "wof:placetype":"venue"
},
  "geometry": {"coordinates":[9.381375,53.711655],"type":"Point"}
}