{
  "type": "Feature",
  "properties": {
    "iso:country":"DE",
    "sg:address":"Gartenstr. 1",
    "sg:city":"Ebersdorf",
    "sg:phone":"+49 9562/1882",
    "sg:postcode":"96237",
    "sg:province":"Bayern",
    "wof:name":"Dieter Eichhorn",
    "wof:placetype":"venue"
},
  "geometry": {"coordinates":[11.088594,50.215107],"type":"Point"}
}