{
  "type": "Feature",
  "properties": {
    "iso:country":"DE",
    "sg:address":"Leunatorstr. 4805",
    "sg:city":"Leuna",
    "sg:postcode":"06237",
    "sg:province":"Sachsen-Anhalt",
    "wof:name":"Isl Gmbh & Co. Handels Kg",
    "wof:placetype":"venue"
},
  "geometry": {"coordinates":[12.00248,51.33012],"type":"Point"}
}