{
  "type": "Feature",
  "properties": {
    "iso:country":"DE",
    "sg:address":"Karl-Liebknecht-Str. 65",
    "sg:city":"Krostitz",
    "sg:postcode":"04509",
    "sg:province":"Sachsen",
    "wof:name":"Horn & Grabsch Gmbh",
    "wof:placetype":"venue"
},
  "geometry": {"coordinates":[12.353229,51.511105],"type":"Point"}
}