{
  "type": "Feature",
  "properties": {
    "iso:country":"DE",
    "sg:address":"Bahnhofstr. 19",
    "sg:city":"Butzbach",
    "sg:phone":"+49 6033/920073",
    "sg:postcode":"35510",
    "sg:province":"Hessen",
    "wof:name":"Volker Matth\u00e4us",
    "wof:placetype":"venue"
},
  "geometry": {"coordinates":[8.6696300507,50.4315185547],"type":"Point"}
}