{
  "type": "Feature",
  "properties": {
    "iso:country":"DE",
    "sg:address":"Herzogenauracher Str. 59",
    "sg:city":"N\u00fcrnberg",
    "sg:phone":"+49 911/3262608",
    "sg:postcode":"90431",
    "sg:province":"Bayern",
    "wof:name":"Hans Reu\u00df",
    "wof:placetype":"venue"
},
  "geometry": {"coordinates":[11.033159,49.452488],"type":"Point"}
}