{
  "type": "Feature",
  "properties": {
    "iso:country":"DE",
    "sg:address":"Bohlens Allee 62",
    "sg:city":"Hamburg",
    "sg:phone":"+49 40/6539135",
    "sg:postcode":"22043",
    "sg:province":"Hamburg",
    "wof:name":"Porfitec Irene Figueiredo E.k.",
    "wof:placetype":"venue"
},
  "geometry": {"coordinates":[10.1234283447,53.5700111389],"type":"Point"}
}