{
  "type": "Feature",
  "properties": {
    "iso:country":"DE",
    "sg:address":"Franz-Haniel-Str. 8-10",
    "sg:city":"Moers",
    "sg:phone":"+49 2841/509086",
    "sg:postcode":"47443",
    "sg:province":"Nordrhein-Westfalen",
    "wof:name":"Infotel Software Gmbh",
    "wof:placetype":"venue"
},
  "geometry": {"coordinates":[6.6598911285,51.4533348083],"type":"Point"}
}