{
  "type": "Feature",
  "properties": {
    "iso:country":"DE",
    "sg:address":"Maria-Theresia-Str. 13",
    "sg:city":"M\u00fcnchen",
    "sg:phone":"+49 89/4708060",
    "sg:postcode":"81675",
    "sg:province":"Bayern",
    "wof:name":"Heb Heimwerkermarkt Beteiligungs-gmbh",
    "wof:placetype":"venue"
},
  "geometry": {"coordinates":[11.598536,48.139805],"type":"Point"}
}