{
  "type": "Feature",
  "properties": {
    "iso:country":"DE",
    "sg:address":"56253",
    "sg:city":"Treis-Karden",
    "sg:postcode":"56253",
    "sg:province":"Rheinland-Pfalz",
    "wof:name":"Raiffeisenbank Treis Eg",
    "wof:placetype":"venue"
},
  "geometry": {"coordinates":[7.29657,50.162922],"type":"Point"}
}