{
  "type": "Feature",
  "properties": {
    "iso:country":"DE",
    "sg:address":"Karlstr. 74",
    "sg:city":"Dettingen",
    "sg:phone":"+49 4971/2397950",
    "sg:postcode":"72581",
    "sg:province":"Baden-W\u00fcrttemberg",
    "wof:name":"Dettinger Bank Eg",
    "wof:placetype":"venue"
},
  "geometry": {"coordinates":[9.346087,48.528023],"type":"Point"}
}