{
  "type": "Feature",
  "properties": {
    "iso:country":"DE",
    "sg:address":"Am Schinkelberg 18",
    "sg:city":"Belm",
    "sg:phone":"+49 5406/5252",
    "sg:postcode":"49191",
    "sg:province":"Niedersachsen",
    "wof:name":"U. Kleinschmidt",
    "wof:placetype":"venue"
},
  "geometry": {"coordinates":[8.112401,52.298145],"type":"Point"}
}