{
  "type": "Feature",
  "properties": {
    "iso:country":"DE",
    "sg:address":"Obermarkt 19",
    "sg:city":"Murnau",
    "sg:phone":"+49 8841/1819",
    "sg:postcode":"82418",
    "sg:province":"Bayern",
    "wof:name":"Brillen Moog Gmbh",
    "wof:placetype":"venue"
},
  "geometry": {"coordinates":[11.200826,47.679192],"type":"Point"}
}