{
  "type": "Feature",
  "properties": {
    "iso:country":"DE",
    "sg:address":"Landkommiss\u00e4rstr. 18",
    "sg:city":"Landau",
    "sg:phone":"+49 6341/510890",
    "sg:postcode":"76829",
    "sg:province":"Rheinland-Pfalz",
    "wof:name":"Centra Leichtmetallr\u00e4der Gmbh",
    "wof:placetype":"venue"
},
  "geometry": {"coordinates":[8.163799,49.204834],"type":"Point"}
}