{
  "type": "Feature",
  "properties": {
    "iso:country":"DE",
    "sg:address":"Hauptstr. 4",
    "sg:city":"Sellerich",
    "sg:phone":"+49 6551/4056",
    "sg:postcode":"54608",
    "sg:province":"Rheinland-Pfalz",
    "wof:name":"Cafe Bollermann",
    "wof:placetype":"venue"
},
  "geometry": {"coordinates":[6.36572,50.227829],"type":"Point"}
}