{
  "type": "Feature",
  "properties": {
    "iso:country":"DE",
    "sg:address":"Buschstr. 9",
    "sg:city":"H\u00fcrth",
    "sg:phone":"+49 2233/943108",
    "sg:postcode":"50354",
    "sg:province":"Nordrhein-Westfalen",
    "wof:name":"J. Hillie",
    "wof:placetype":"venue"
},
  "geometry": {"coordinates":[6.8797597885,50.862449646],"type":"Point"}
}