{
  "type": "Feature",
  "properties": {
    "iso:country":"DE",
    "sg:address":"Gro\u00dfer Ring 53",
    "sg:city":"Dorsten",
    "sg:phone":"+49 2369/6745",
    "sg:postcode":"46286",
    "sg:province":"Nordrhein-Westfalen",
    "wof:name":"Kleinschmidt Gmbh",
    "wof:placetype":"venue"
},
  "geometry": {"coordinates":[7.0228309631,51.7147216797],"type":"Point"}
}