{
  "type": "Feature",
  "properties": {
    "iso:country":"DE",
    "sg:address":"Hauptstr. 12",
    "sg:city":"Friesenried",
    "sg:phone":"+49 8347/685",
    "sg:postcode":"87654",
    "sg:province":"Bayern",
    "wof:name":"Am Forsthaus",
    "wof:placetype":"venue"
},
  "geometry": {"coordinates":[10.5363721848,47.8758201599],"type":"Point"}
}