{
  "type": "Feature",
  "properties": {
    "iso:country":"DE",
    "sg:address":"Damaschkestr. 30",
    "sg:city":"Aue",
    "sg:phone":"+49 4937/204700",
    "sg:postcode":"08280",
    "sg:province":"Sachsen",
    "wof:name":"Oris Fahrzeugteile Gmbh",
    "wof:placetype":"venue"
},
  "geometry": {"coordinates":[12.6243858337,50.792224884],"type":"Point"}
}