{
  "type": "Feature",
  "properties": {
    "iso:country":"DE",
    "sg:address":"Narzissenweg 2",
    "sg:city":"Bad Lippspringe",
    "sg:postcode":"33175",
    "sg:province":"Nordrhein-Westfalen",
    "wof:name":"Gebr\u00fcder Schmitz Verwaltungs- Und Beteiligungs Gmbh",
    "wof:placetype":"venue"
},
  "geometry": {"coordinates":[8.8056669235,51.772819519],"type":"Point"}
}