{
  "type": "Feature",
  "properties": {
    "iso:country":"DE",
    "sg:address":"Hagenstr. 34",
    "sg:city":"Haldensleben",
    "sg:phone":"+49 3904/4710",
    "sg:postcode":"39340",
    "sg:province":"Sachsen-Anhalt",
    "wof:name":"Haldensleber Bank- Raiffeisenbank Eg",
    "wof:placetype":"venue"
},
  "geometry": {"coordinates":[11.4081344604,52.2895278931],"type":"Point"}
}