{
  "type": "Feature",
  "properties": {
    "iso:country":"DE",
    "sg:address":"Ernst-Haeckel-Str. 94 b",
    "sg:city":"M\u00fcnchen",
    "sg:phone":"+49 89/8121232",
    "sg:postcode":"80999",
    "sg:province":"Bayern",
    "wof:name":"Weidinger Wohnbau Gmbh",
    "wof:placetype":"venue"
},
  "geometry": {"coordinates":[11.4425163269,48.1831359863],"type":"Point"}
}