{
  "type": "Feature",
  "properties": {
    "iso:country":"DE",
    "sg:address":"Schleifweg 38",
    "sg:city":"Tussenhausen",
    "sg:phone":"+49 8268/783",
    "sg:postcode":"86874",
    "sg:province":"Bayern",
    "wof:name":"Konrad Zientek",
    "wof:placetype":"venue"
},
  "geometry": {"coordinates":[10.5495595932,48.0890083313],"type":"Point"}
}