{
  "type": "Feature",
  "properties": {
    "iso:country":"DE",
    "sg:address":"Gelber Damm 10 A",
    "sg:city":"Isernhagen",
    "sg:phone":"+49 511/613538",
    "sg:postcode":"30916",
    "sg:province":"Niedersachsen",
    "wof:name":"Petra Von Amsberg",
    "wof:placetype":"venue"
},
  "geometry": {"coordinates":[9.8336896896,52.4302139282],"type":"Point"}
}