{
  "type": "Feature",
  "properties": {
    "iso:country":"DE",
    "sg:address":"Windschl\u00e4ger Str. 3",
    "sg:city":"Durbach",
    "sg:phone":"+49 781/22497",
    "sg:postcode":"77770",
    "sg:province":"Baden-W\u00fcrttemberg",
    "wof:name":"Kath. Pfarramt Hl. Kreuz",
    "wof:placetype":"venue"
},
  "geometry": {"coordinates":[7.9818987846,48.5075416565],"type":"Point"}
}