{
  "type": "Feature",
  "properties": {
    "iso:country":"DE",
    "sg:address":"Vater-Jahn-Str. 9",
    "sg:city":"Lehrte",
    "sg:phone":"+49 5132/57748",
    "sg:postcode":"31275",
    "sg:province":"Niedersachsen",
    "wof:name":"Dirk Und Sabine Belka",
    "wof:placetype":"venue"
},
  "geometry": {"coordinates":[9.9861745834,52.3868942261],"type":"Point"}
}