{
  "type": "Feature",
  "properties": {
    "iso:country":"DE",
    "sg:address":"Hauptstr. 68",
    "sg:city":"Nu\u00dfloch",
    "sg:phone":"+49 6224/10677",
    "sg:postcode":"69226",
    "sg:province":"Baden-W\u00fcrttemberg",
    "wof:name":"Burkhard Hinzmann",
    "wof:placetype":"venue"
},
  "geometry": {"coordinates":[8.6951332092,49.3238143921],"type":"Point"}
}