{
  "type": "Feature",
  "properties": {
    "iso:country":"DE",
    "sg:address":"Neu Brackede 2",
    "sg:city":"Bleckede",
    "sg:postcode":"21354",
    "sg:province":"Niedersachsen",
    "wof:name":"Elbmarsch \u00d6lm\u00fchle Gmbh",
    "wof:placetype":"venue"
},
  "geometry": {"coordinates":[10.6871290207,53.3493804932],"type":"Point"}
}