{
  "type": "Feature",
  "properties": {
    "iso:country":"DE",
    "sg:address":"An der Volksb\u00fchne 4",
    "sg:city":"Ueckerm\u00fcnde",
    "sg:postcode":"17373",
    "sg:province":"Mecklenburg-Vorpommern",
    "wof:name":"Volksb\u00fchne",
    "wof:placetype":"venue"
},
  "geometry": {"coordinates":[14.0442743301,53.7383575439],"type":"Point"}
}