{
  "type": "Feature",
  "properties": {
    "iso:country":"DE",
    "sg:address":"Bahnhofstr. 10",
    "sg:city":"Dorsten",
    "sg:phone":"+49 2369/77317",
    "sg:postcode":"46286",
    "sg:province":"Nordrhein-Westfalen",
    "wof:name":"Hohenstein Geb\u00e4udereinigung",
    "wof:placetype":"venue"
},
  "geometry": {"coordinates":[7.009324,51.755177],"type":"Point"}
}