{
  "type": "Feature",
  "properties": {
    "iso:country":"DE",
    "sg:address":"Mahlastr. 23",
    "sg:city":"Frankenthal",
    "sg:phone":"+49 6233/4410",
    "sg:postcode":"67227",
    "sg:province":"Rheinland-Pfalz",
    "wof:name":"Deutsche Crown Cork Gmbh",
    "wof:placetype":"venue"
},
  "geometry": {"coordinates":[8.354686,49.528511],"type":"Point"}
}