{
  "type": "Feature",
  "properties": {
    "iso:country":"DE",
    "sg:address":"Bredstedter Str. 37",
    "sg:city":"Husum",
    "sg:phone":"+49 4841/83630",
    "sg:postcode":"25813",
    "sg:province":"Schleswig-Holstein",
    "wof:name":"Raiffeisen Haupt- Genossenschaft Nord Ag",
    "wof:placetype":"venue"
},
  "geometry": {"coordinates":[9.045661,54.488979],"type":"Point"}
}