{
  "type": "Feature",
  "properties": {
    "iso:country":"DE",
    "sg:address":"Grabenstr 73",
    "sg:city":"Eschweiler",
    "sg:phone":"+49 2403/37985",
    "sg:postcode":"52249",
    "sg:province":"Nordrhein-Westfalen",
    "wof:name":"Dresdner Bank Ag",
    "wof:placetype":"venue"
},
  "geometry": {"coordinates":[6.266246,50.817875],"type":"Point"}
}