{
  "type": "Feature",
  "properties": {
    "iso:country":"DE",
    "sg:address":"Bauernwaldstr. 144",
    "sg:city":"Stuttgart",
    "sg:postcode":"70195",
    "sg:province":"Baden-W\u00fcrttemberg",
    "wof:name":"Sikorski-quartett",
    "wof:placetype":"venue"
},
  "geometry": {"coordinates":[9.118419,48.783325],"type":"Point"}
}