{
  "type": "Feature",
  "properties": {
    "iso:country":"DE",
    "sg:address":"Dunkle Str. 18",
    "sg:city":"Harsum",
    "sg:phone":"+49 5127/931017",
    "sg:postcode":"31177",
    "sg:province":"Niedersachsen",
    "wof:name":"Andreas Steinmann-l\u00fcders",
    "wof:placetype":"venue"
},
  "geometry": {"coordinates":[9.964625,52.208134],"type":"Point"}
}