{
  "type": "Feature",
  "properties": {
    "iso:country":"DE",
    "sg:address":"Carl-Alexanderstr. 90",
    "sg:city":"\u00dcbach-Palenberg",
    "sg:phone":"+49 2404/912023",
    "sg:postcode":"52531",
    "sg:province":"Nordrhein-Westfalen",
    "wof:name":"Zeichen- Und Planungsb\u00fcro",
    "wof:placetype":"venue"
},
  "geometry": {"coordinates":[6.141028,50.908726],"type":"Point"}
}