{
  "type": "Feature",
  "properties": {
    "iso:country":"DE",
    "sg:address":"Gartenstr. 10",
    "sg:city":"Freiburg",
    "sg:phone":"+49 761/32440",
    "sg:postcode":"79098",
    "sg:province":"Baden-W\u00fcrttemberg",
    "wof:name":"M. Dreyer-kirchhofer",
    "wof:placetype":"venue"
},
  "geometry": {"coordinates":[7.847126,47.991863],"type":"Point"}
}