{
  "type": "Feature",
  "properties": {
    "iso:country":"DE",
    "sg:address":"Neue J\u00fclicher Str. 12",
    "sg:city":"D\u00fcren",
    "sg:phone":"+49 2421/41709",
    "sg:postcode":"52353",
    "sg:province":"Nordrhein-Westfalen",
    "wof:name":"M. Franzen",
    "wof:placetype":"venue"
},
  "geometry": {"coordinates":[6.4786810875,50.811088562],"type":"Point"}
}