{
  "type": "Feature",
  "properties": {
    "iso:country":"DE",
    "sg:address":"Moorhof 2 D",
    "sg:city":"Hamburg",
    "sg:phone":"+49 40/6087020",
    "sg:postcode":"22399",
    "sg:province":"Hamburg",
    "wof:name":"H. & W. Goothusen",
    "wof:placetype":"venue"
},
  "geometry": {"coordinates":[10.085517,53.661404],"type":"Point"}
}