{
  "type": "Feature",
  "properties": {
    "iso:country":"DE",
    "sg:address":"Stephanienstr. 12",
    "sg:city":"Karlsruhe",
    "sg:postcode":"76133",
    "sg:province":"Baden-W\u00fcrttemberg",
    "wof:name":"Mediasalon.de E. K.",
    "wof:placetype":"venue"
},
  "geometry": {"coordinates":[8.397211,49.012589],"type":"Point"}
}