{
  "type": "Feature",
  "properties": {
    "iso:country":"DE",
    "sg:address":"Hauptstr. 32",
    "sg:city":"Freilassing",
    "sg:phone":"+49 8654/9575",
    "sg:postcode":"83395",
    "sg:province":"Bayern",
    "wof:name":"Annemarie Brotsack",
    "wof:placetype":"venue"
},
  "geometry": {"coordinates":[12.981259346,47.8376235962],"type":"Point"}
}