{
  "type": "Feature",
  "properties": {
    "iso:country":"DE",
    "sg:address":"Neckarstr. 29",
    "sg:city":"Horb",
    "sg:phone":"+49 7451/1084",
    "sg:postcode":"72160",
    "sg:province":"Baden-W\u00fcrttemberg",
    "wof:name":"Schwarzw\u00e4lder Bote",
    "wof:placetype":"venue"
},
  "geometry": {"coordinates":[8.6912698746,48.4441413879],"type":"Point"}
}