{
  "type": "Feature",
  "properties": {
    "iso:country":"DE",
    "sg:address":"Ger\u00e4mmestr. 83",
    "sg:city":"Essingen",
    "sg:phone":"+49 6347/419",
    "sg:postcode":"76879",
    "sg:province":"Rheinland-Pfalz",
    "wof:name":"A. Stoll",
    "wof:placetype":"venue"
},
  "geometry": {"coordinates":[8.1639890671,49.2350082397],"type":"Point"}
}