{
  "type": "Feature",
  "properties": {
    "iso:country":"DE",
    "sg:address":"Kapellenweg 12",
    "sg:city":"Volkach",
    "sg:phone":"+49 9381/2356",
    "sg:postcode":"97332",
    "sg:province":"Bayern",
    "wof:name":"Gerhard Pfeiffer",
    "wof:placetype":"venue"
},
  "geometry": {"coordinates":[10.231851,49.862968],"type":"Point"}
}