{
  "type": "Feature",
  "properties": {
    "iso:country":"DE",
    "sg:address":"Kondelstr. 47",
    "sg:city":"Kinderbeuern",
    "sg:phone":"+49 6532/3186",
    "sg:postcode":"54538",
    "sg:province":"Rheinland-Pfalz",
    "wof:name":"Ewald Weberskirch",
    "wof:placetype":"venue"
},
  "geometry": {"coordinates":[7.026214,50.022175],"type":"Point"}
}