{
  "type": "Feature",
  "properties": {
    "iso:country":"DE",
    "sg:address":"Arberweg 49",
    "sg:city":"Garching",
    "sg:phone":"+49 89/3207219",
    "sg:postcode":"85748",
    "sg:province":"Bayern",
    "wof:name":"E-dienste Elektonische Dienst- Leistungssysteme Gmbh",
    "wof:placetype":"venue"
},
  "geometry": {"coordinates":[-110.729874,32.191959],"type":"Point"}
}