{
  "type": "Feature",
  "properties": {
    "iso:country":"DE",
    "sg:address":"Weiershagener Str. 26",
    "sg:city":"Wiehl",
    "sg:phone":"+49 2262/701096",
    "sg:postcode":"51674",
    "sg:province":"Nordrhein-Westfalen",
    "wof:name":"Pavo Baustoffe Gmbh",
    "wof:placetype":"venue"
},
  "geometry": {"coordinates":[7.487557,50.972122],"type":"Point"}
}