{
  "type": "Feature",
  "properties": {
    "iso:country":"DE",
    "sg:address":"Bahnhofstr. 22",
    "sg:city":"Meuselwitz",
    "sg:phone":"+49 3448/3760",
    "sg:postcode":"04610",
    "sg:province":"Th\u00fcringen",
    "wof:name":"Hermann Fandre & Petra R\u00f6\u00dfler",
    "wof:placetype":"venue"
},
  "geometry": {"coordinates":[12.296088,51.041878],"type":"Point"}
}