{
  "type": "Feature",
  "properties": {
    "iso:country":"DE",
    "sg:address":"Claude-Dornierstr. 5",
    "sg:city":"Bitburg/Eifel",
    "sg:phone":"+49 6561/940136",
    "sg:postcode":"54634",
    "sg:province":"Rheinland-Pfalz",
    "wof:name":"A-alle Baumaschinen-ersatzteile-veit Gmbh",
    "wof:placetype":"venue"
},
  "geometry": {"coordinates":[6.5889701843,49.9800567627],"type":"Point"}
}