{
  "type": "Feature",
  "properties": {
    "iso:country":"DE",
    "sg:address":"Hildastr. 31",
    "sg:city":"Freiburg",
    "sg:phone":"+49 761/791290",
    "sg:postcode":"79102",
    "sg:province":"Baden-W\u00fcrttemberg",
    "wof:name":"Reinhard Vogel Steuerberater",
    "wof:placetype":"venue"
},
  "geometry": {"coordinates":[7.8545498848,47.988822937],"type":"Point"}
}