{
  "type": "Feature",
  "properties": {
    "iso:country":"DE",
    "sg:address":"Tegelweg 203",
    "sg:city":"Hamburg",
    "sg:phone":"+49 40/6438222",
    "sg:postcode":"22159",
    "sg:province":"Hamburg",
    "wof:name":"Andreas Vogel",
    "wof:placetype":"venue"
},
  "geometry": {"coordinates":[10.1003026962,53.6091156006],"type":"Point"}
}