{
  "type": "Feature",
  "properties": {
    "iso:country":"DE",
    "sg:address":"Sandstr. 51",
    "sg:city":"Siegen",
    "sg:phone":"+49 271/22840",
    "sg:postcode":"57072",
    "sg:province":"Nordrhein-Westfalen",
    "wof:name":"R. Kuhajda",
    "wof:placetype":"venue"
},
  "geometry": {"coordinates":[8.0224580765,50.8775863647],"type":"Point"}
}