{
  "type": "Feature",
  "properties": {
    "iso:country":"DE",
    "sg:address":"Klenzestr. 2",
    "sg:city":"Hausham",
    "sg:phone":"+49 8026/5725",
    "sg:postcode":"83734",
    "sg:province":"Bayern",
    "wof:name":"Hartl",
    "wof:placetype":"venue"
},
  "geometry": {"coordinates":[11.8383808136,47.7459259033],"type":"Point"}
}