{
  "type": "Feature",
  "properties": {
    "iso:country":"DE",
    "sg:address":"Kreuzb\u00fchler Str. 13",
    "sg:city":"Schnaittach",
    "sg:phone":"+49 9153/8681",
    "sg:postcode":"91220",
    "sg:province":"Bayern",
    "wof:name":"Lorenz Meier",
    "wof:placetype":"venue"
},
  "geometry": {"coordinates":[11.366388,49.586929],"type":"Point"}
}