{
  "type": "Feature",
  "properties": {
    "iso:country":"DE",
    "sg:address":"Borgheller Str. 24",
    "sg:city":"Werdohl",
    "sg:phone":"+49 2392/2793",
    "sg:postcode":"58791",
    "sg:province":"Nordrhein-Westfalen",
    "wof:name":"Robert Groll Immobilienmakler",
    "wof:placetype":"venue"
},
  "geometry": {"coordinates":[7.7670059204,51.2635269165],"type":"Point"}
}