{
  "type": "Feature",
  "properties": {
    "iso:country":"DE",
    "sg:address":"Sporerstra\u00dfe 2",
    "sg:city":"Oschatz",
    "sg:phone":"+49 3435",
    "sg:postcode":"04758",
    "sg:province":"Sachsen",
    "wof:name":"Oschatzer Gasthaus Zum Schwan",
    "wof:placetype":"venue"
},
  "geometry": {"coordinates":[13.108997,51.297775],"type":"Point"}
}