{
  "type": "Feature",
  "properties": {
    "iso:country":"DE",
    "sg:address":"Alte Hauptstr. 87",
    "sg:city":"Essen",
    "sg:phone":"+49 201/578789",
    "sg:postcode":"45289",
    "sg:province":"Nordrhein-Westfalen",
    "wof:name":"Willi Hollbr\u00f6gge",
    "wof:placetype":"venue"
},
  "geometry": {"coordinates":[7.1109218597,51.4147987366],"type":"Point"}
}