{
  "type": "Feature",
  "properties": {
    "iso:country":"DE",
    "sg:address":"Schlo\u00dfstr. 5-7",
    "sg:city":"Wiesloch",
    "sg:phone":"+49 6222/52807",
    "sg:postcode":"69168",
    "sg:province":"Baden-W\u00fcrttemberg",
    "wof:name":"Helmut Wimmer Elektromeister",
    "wof:placetype":"venue"
},
  "geometry": {"coordinates":[8.694818,49.295567],"type":"Point"}
}