{
  "type": "Feature",
  "properties": {
    "iso:country":"DE",
    "sg:address":"Pferdestr. 13",
    "sg:city":"Osnabr\u00fcck",
    "sg:phone":"+49 4954/1380320",
    "sg:postcode":"49084",
    "sg:province":"Niedersachsen",
    "wof:name":"Hansa-flex Hydraulik Gmbh",
    "wof:placetype":"venue"
},
  "geometry": {"coordinates":[8.07206,52.260498],"type":"Point"}
}