{
  "type": "Feature",
  "properties": {
    "iso:country":"DE",
    "sg:address":"Winkelstr. 14-16",
    "sg:city":"Bremen",
    "sg:phone":"+49 421/498056",
    "sg:postcode":"28207",
    "sg:province":"Bremen",
    "wof:name":"Glatzel Verwaltungsges. Mbh",
    "wof:placetype":"venue"
},
  "geometry": {"coordinates":[8.875599,53.067333],"type":"Point"}
}