{
  "type": "Feature",
  "properties": {
    "iso:country":"DE",
    "sg:address":"Konrad-Adenauer-Str. 9",
    "sg:city":"Offenbach",
    "sg:phone":"+49 69/82375263",
    "sg:postcode":"63073",
    "sg:province":"Hessen",
    "wof:name":"Internet Services - Antonio Fonseca",
    "wof:placetype":"venue"
},
  "geometry": {"coordinates":[8.7962646484,50.0862426758],"type":"Point"}
}