{
  "type": "Feature",
  "properties": {
    "iso:country":"DE",
    "sg:address":"Beethovenstr. 2",
    "sg:city":"Leer",
    "sg:phone":"+49 491/71787",
    "sg:postcode":"26789",
    "sg:province":"Niedersachsen",
    "wof:name":"Wegesend-beteiligungs- Und Verm\u00f6gensverwaltungs-gmbh",
    "wof:placetype":"venue"
},
  "geometry": {"coordinates":[7.479742,53.23304],"type":"Point"}
}