{
  "type": "Feature",
  "properties": {
    "iso:country":"DE",
    "sg:address":"K\u00f6rnerplatz 2",
    "sg:city":"Essen",
    "sg:phone":"+49 201/622093",
    "sg:postcode":"45143",
    "sg:province":"Nordrhein-Westfalen",
    "wof:name":"Elektrotechnik August Peters Nachfolger Gmbh",
    "wof:placetype":"venue"
},
  "geometry": {"coordinates":[6.97496,51.45763],"type":"Point"}
}