{
  "type": "Feature",
  "properties": {
    "iso:country":"DE",
    "sg:address":"Hauptstr. 5",
    "sg:city":"Hammoor",
    "sg:phone":"+49 4532/5533",
    "sg:postcode":"22941",
    "sg:province":"Schleswig-Holstein",
    "wof:name":"M. Niebuhr",
    "wof:placetype":"venue"
},
  "geometry": {"coordinates":[10.3258733749,53.7137947083],"type":"Point"}
}