{
  "type": "Feature",
  "properties": {
    "iso:country":"DE",
    "sg:address":"Dorfstr. 37",
    "sg:city":"Rietschen",
    "sg:phone":"+49 35772/40626",
    "sg:postcode":"02956",
    "sg:province":"Sachsen",
    "wof:name":"Isolde Meister",
    "wof:placetype":"venue"
},
  "geometry": {"coordinates":[14.826943,51.396488],"type":"Point"}
}