{
  "type": "Feature",
  "properties": {
    "iso:country":"DE",
    "sg:address":"Beckersgraben 16",
    "sg:city":"Bad Hersfeld",
    "sg:phone":"+49 6621/78115",
    "sg:postcode":"36251",
    "sg:province":"Hessen",
    "wof:name":"Friedrich Krumme Gmbh",
    "wof:placetype":"venue"
},
  "geometry": {"coordinates":[9.7199497223,50.8793907166],"type":"Point"}
}