{
  "type": "Feature",
  "properties": {
    "iso:country":"DE",
    "sg:address":"Adelbergergasse 7",
    "sg:city":"Ellwangen",
    "sg:phone":"+49 7961/561377",
    "sg:postcode":"73479",
    "sg:province":"Baden-W\u00fcrttemberg",
    "wof:name":"G. St\u00f6lzle",
    "wof:placetype":"venue"
},
  "geometry": {"coordinates":[10.1307439804,48.9595031738],"type":"Point"}
}