{
  "type": "Feature",
  "properties": {
    "iso:country":"DE",
    "sg:address":"August-Bebel-Str. 18",
    "sg:city":"Schwerin",
    "sg:postcode":"19055",
    "sg:province":"Mecklenburg-Vorpommern",
    "wof:name":"Lot Software Gmbh",
    "wof:placetype":"venue"
},
  "geometry": {"coordinates":[11.4140481949,53.6337013245],"type":"Point"}
}