{
  "type": "Feature",
  "properties": {
    "iso:country":"DE",
    "sg:address":"Pirnaer Str. 58",
    "sg:city":"Heidenau",
    "sg:phone":"+49 3529/517444",
    "sg:postcode":"01809",
    "sg:province":"Sachsen",
    "wof:name":"Restaurant Sachsen-eck",
    "wof:placetype":"venue"
},
  "geometry": {"coordinates":[13.8791265488,50.9705352783],"type":"Point"}
}