{
  "type": "Feature",
  "properties": {
    "iso:country":"DE",
    "sg:address":"Strietm\u00fchle 2",
    "sg:city":"Donzdorf",
    "sg:phone":"+49 7162/27329",
    "sg:postcode":"73072",
    "sg:province":"Baden-W\u00fcrttemberg",
    "wof:name":"R. Dre\u00dfler",
    "wof:placetype":"venue"
},
  "geometry": {"coordinates":[9.787959,48.721828],"type":"Point"}
}