{
  "type": "Feature",
  "properties": {
    "iso:country":"DE",
    "sg:address":"Salzstr. 7-9",
    "sg:city":"Bingen",
    "sg:phone":"+49 6721/13820",
    "sg:postcode":"55411",
    "sg:province":"Rheinland-Pfalz",
    "wof:name":"Brager Gmbh",
    "wof:placetype":"venue"
},
  "geometry": {"coordinates":[7.8953251839,49.9685401917],"type":"Point"}
}