{
  "type": "Feature",
  "properties": {
    "iso:country":"DE",
    "sg:address":"Nienburger Str. 2",
    "sg:city":"Syke",
    "sg:phone":"+49 4242/930939",
    "sg:postcode":"28857",
    "sg:province":"Niedersachsen",
    "wof:name":"Bistro Feuerstein",
    "wof:placetype":"venue"
},
  "geometry": {"coordinates":[8.8273172379,52.912563324],"type":"Point"}
}