{
  "type": "Feature",
  "properties": {
    "iso:country":"DE",
    "sg:address":"Freiherr-vom-Stein-Str. 16",
    "sg:city":"M\u00f6ssingen",
    "sg:phone":"+49 4974/733720",
    "sg:postcode":"72116",
    "sg:province":"Baden-W\u00fcrttemberg",
    "wof:name":"Kreissparkasse T\u00fcbingen",
    "wof:placetype":"venue"
},
  "geometry": {"coordinates":[9.048531,48.40456],"type":"Point"}
}