{
  "type": "Feature",
  "properties": {
    "iso:country":"DE",
    "sg:address":"Bismarckstr. 15",
    "sg:city":"Isselburg",
    "sg:phone":"+49 2874/95702",
    "sg:postcode":"46419",
    "sg:province":"Nordrhein-Westfalen",
    "wof:name":"T. Kock",
    "wof:placetype":"venue"
},
  "geometry": {"coordinates":[6.4588050842,51.8333435059],"type":"Point"}
}