{
  "type": "Feature",
  "properties": {
    "iso:country":"DE",
    "sg:address":"In der Esche 7",
    "sg:city":"Herne",
    "sg:phone":"+49 2323/63563",
    "sg:postcode":"44627",
    "sg:province":"Nordrhein-Westfalen",
    "wof:name":"Wab",
    "wof:placetype":"venue"
},
  "geometry": {"coordinates":[7.2520041466,51.5344009399],"type":"Point"}
}