{
  "type": "Feature",
  "properties": {
    "iso:country":"DE",
    "sg:address":"Untersteinbach 14",
    "sg:city":"Geroldsgr\u00fcn",
    "sg:phone":"+49 9288/8898",
    "sg:postcode":"95179",
    "sg:province":"Bayern",
    "wof:name":"Thomas Sell",
    "wof:placetype":"venue"
},
  "geometry": {"coordinates":[11.5799951553,50.3421554565],"type":"Point"}
}