{
  "type": "Feature",
  "properties": {
    "iso:country":"DE",
    "sg:address":"Alte Bahnhofstr. 155",
    "sg:city":"Bochum",
    "sg:phone":"+49 234/287084",
    "sg:postcode":"44892",
    "sg:province":"Nordrhein-Westfalen",
    "wof:name":"Krukenberg Verwaltungsgesellschaft Mbh",
    "wof:placetype":"venue"
},
  "geometry": {"coordinates":[7.307986,51.473667],"type":"Point"}
}