{
  "type": "Feature",
  "properties": {
    "iso:country":"DE",
    "sg:address":"Gro\u00dfe D\u00fcwelstr. 8",
    "sg:city":"Hannover",
    "sg:phone":"+49 511/817098",
    "sg:postcode":"30171",
    "sg:province":"Niedersachsen",
    "wof:name":"Andreas Pakebusch Rechtsanwalt",
    "wof:placetype":"venue"
},
  "geometry": {"coordinates":[9.7608366013,52.3691139221],"type":"Point"}
}