{
  "type": "Feature",
  "properties": {
    "iso:country":"DE",
    "sg:address":"Metzer Str. 63",
    "sg:city":"\u00dcberherrn",
    "sg:phone":"+49 6837/614",
    "sg:postcode":"66802",
    "sg:province":"Saarland",
    "wof:name":"Frischdienst Union Felsberg Vertriebsges. F\u00fcr Fleisch-und",
    "wof:placetype":"venue"
},
  "geometry": {"coordinates":[6.6982898712,49.242565155],"type":"Point"}
}