{
  "type": "Feature",
  "properties": {
    "iso:country":"DE",
    "sg:address":"Hauptstr. 10",
    "sg:city":"Eisenberg",
    "sg:phone":"+49 6351/8667",
    "sg:postcode":"67304",
    "sg:province":"Rheinland-Pfalz",
    "wof:name":"Erich Koch",
    "wof:placetype":"venue"
},
  "geometry": {"coordinates":[8.066617,49.554146],"type":"Point"}
}