{
  "type": "Feature",
  "properties": {
    "iso:country":"DE",
    "sg:address":"Schilteckstr. 7",
    "sg:city":"Schramberg",
    "sg:phone":"+49 4974/2294980",
    "sg:postcode":"78713",
    "sg:province":"Baden-W\u00fcrttemberg",
    "wof:name":"Uwe Rettkowski Gmbh",
    "wof:placetype":"venue"
},
  "geometry": {"coordinates":[8.376286,48.236103],"type":"Point"}
}