{
  "type": "Feature",
  "properties": {
    "iso:country":"DE",
    "sg:address":"Industriestr. 3",
    "sg:city":"Asslar",
    "sg:phone":"+49 4964/4180060",
    "sg:postcode":"35614",
    "sg:province":"Hessen",
    "wof:name":"Buderus-schleiftechnik Gmbh",
    "wof:placetype":"venue"
},
  "geometry": {"coordinates":[8.47608,50.581966],"type":"Point"}
}