{
  "type": "Feature",
  "properties": {
    "iso:country":"DE",
    "sg:address":"Duttenstedter Str. 3",
    "sg:city":"Peine",
    "sg:phone":"+49 5171/15859",
    "sg:postcode":"31224",
    "sg:province":"Niedersachsen",
    "wof:name":"T\u00e4uber Verwaltungsges. Mbh",
    "wof:placetype":"venue"
},
  "geometry": {"coordinates":[10.2321662903,52.3287734985],"type":"Point"}
}