{
  "type": "Feature",
  "properties": {
    "iso:country":"DE",
    "sg:address":"Scheibenweg 19",
    "sg:city":"Illingen",
    "sg:phone":"+49 6825/41850",
    "sg:postcode":"66557",
    "sg:province":"Saarland",
    "wof:name":"Erwin Wagner",
    "wof:placetype":"venue"
},
  "geometry": {"coordinates":[7.0934348106,49.3988037109],"type":"Point"}
}