{
  "type": "Feature",
  "properties": {
    "iso:country":"DE",
    "sg:address":"L\u00e4rchenring 7 a",
    "sg:city":"Oldenburg",
    "sg:phone":"+49 441/41023",
    "sg:postcode":"26133",
    "sg:province":"Niedersachsen",
    "wof:name":"Ingenieurgemeinschaft Majcher Scheidt & Partner",
    "wof:placetype":"venue"
},
  "geometry": {"coordinates":[8.2358293533,53.1117095947],"type":"Point"}
}