{
  "type": "Feature",
  "properties": {
    "iso:country":"DE",
    "sg:address":"Dorfstr. 23",
    "sg:city":"Lutter",
    "sg:phone":"+49 5383/376",
    "sg:postcode":"38729",
    "sg:province":"Niedersachsen",
    "wof:name":"Dorfkrug",
    "wof:placetype":"venue"
},
  "geometry": {"coordinates":[10.293510437,51.984577179],"type":"Point"}
}