{
  "type": "Feature",
  "properties": {
    "iso:country":"DE",
    "sg:address":"Kemeritz",
    "sg:city":"Thurnau",
    "sg:phone":"+49 9228/1662",
    "sg:postcode":"95349",
    "sg:province":"Bayern",
    "wof:name":"P. Gr\u00e4f",
    "wof:placetype":"venue"
},
  "geometry": {"coordinates":[11.4217224121,50.0534324646],"type":"Point"}
}