{
  "type": "Feature",
  "properties": {
    "iso:country":"DE",
    "sg:address":"Z\u00e4hringerstr. 10",
    "sg:city":"Villingen-Schwenningen",
    "sg:phone":"+49 7721/25479",
    "sg:postcode":"78050",
    "sg:province":"Baden-W\u00fcrttemberg",
    "wof:name":"Albert F\u00f6hrenbach",
    "wof:placetype":"venue"
},
  "geometry": {"coordinates":[8.457255,48.055309],"type":"Point"}
}