{
  "type": "Feature",
  "properties": {
    "iso:country":"DE",
    "sg:address":"Liebigstr. 1-2",
    "sg:city":"Fl\u00f6rsheim",
    "sg:phone":"+49 6145/5080",
    "sg:postcode":"65439",
    "sg:province":"Hessen",
    "wof:name":"Hennig Arzneimittel Verwaltungs-gmbh",
    "wof:placetype":"venue"
},
  "geometry": {"coordinates":[8.4179821014,50.0062217712],"type":"Point"}
}