{
  "type": "Feature",
  "properties": {
    "iso:country":"DE",
    "sg:address":"Hauptstr. 40",
    "sg:city":"Spechbach",
    "sg:phone":"+49 4962/2641415",
    "sg:postcode":"74937",
    "sg:province":"Baden-W\u00fcrttemberg",
    "wof:name":"Volksbank Meckesheim Eg",
    "wof:placetype":"venue"
},
  "geometry": {"coordinates":[8.883787,49.345947],"type":"Point"}
}