{
  "type": "Feature",
  "properties": {
    "iso:country":"DE",
    "sg:address":"Bremer Str. 4b",
    "sg:city":"Langwedel-Etelsen",
    "sg:postcode":"27299",
    "sg:province":"Niedersachsen",
    "wof:name":"Weihnachtsb\u00e4ume Vom Hof Beckr\u00f6ge",
    "wof:placetype":"venue"
},
  "geometry": {"coordinates":[9.113027,52.995358],"type":"Point"}
}