{
  "type": "Feature",
  "properties": {
    "iso:country":"DE",
    "sg:address":"Langer Brauck 15",
    "sg:city":"Iserlohn",
    "sg:phone":"+49 4923/7197630",
    "sg:postcode":"58640",
    "sg:province":"Nordrhein-Westfalen",
    "wof:name":"Achim Schulz-lauterbach Vertrieb Med. Produkte Gmbh",
    "wof:placetype":"venue"
},
  "geometry": {"coordinates":[7.7004032135,51.4171447754],"type":"Point"}
}