{
  "type": "Feature",
  "properties": {
    "iso:country":"DE",
    "sg:address":"Fleischgasse 13",
    "sg:city":"Saalfeld",
    "sg:phone":"+49 3671/529595",
    "sg:postcode":"07318",
    "sg:province":"Th\u00fcringen",
    "wof:name":"Saaltel Kommunikationssysteme",
    "wof:placetype":"venue"
},
  "geometry": {"coordinates":[11.359703064,50.6491203308],"type":"Point"}
}