{
  "type": "Feature",
  "properties": {
    "iso:country":"DE",
    "sg:address":"Dieselstr. 1",
    "sg:city":"Friedberg",
    "sg:postcode":"61169",
    "sg:province":"Hessen",
    "wof:name":"Fitmaxx Gmbh Fitness- Und Wellnesscenter",
    "wof:placetype":"venue"
},
  "geometry": {"coordinates":[8.7563581467,50.3455543518],"type":"Point"}
}