{
  "type": "Feature",
  "properties": {
    "iso:country":"DE",
    "sg:address":"Am Guckenberg 6",
    "sg:city":"Diez",
    "sg:phone":"+49 6432/2395",
    "sg:postcode":"65582",
    "sg:province":"Rheinland-Pfalz",
    "wof:name":"Handels- Und Beratungsges. Peter Gemeiner Mbh",
    "wof:placetype":"venue"
},
  "geometry": {"coordinates":[8.0075387955,50.3683929443],"type":"Point"}
}