{
  "type": "Feature",
  "properties": {
    "iso:country":"DE",
    "sg:address":"Postfach 1753",
    "sg:city":"Neumarkt",
    "sg:postcode":"92307",
    "wof:name":"Die Radlerburg Wolfstein",
    "wof:placetype":"venue"
},
  "geometry": {"coordinates":[11.45709,49.282291],"type":"Point"}
}