{
  "type": "Feature",
  "properties": {
    "iso:country":"DE",
    "sg:address":"Obertal Str. 8",
    "sg:city":"Furtwangen",
    "sg:phone":"+49 7723/503620",
    "sg:postcode":"78120",
    "sg:province":"Baden-W\u00fcrttemberg",
    "wof:name":"Andre Wassertechnik Gmbh",
    "wof:placetype":"venue"
},
  "geometry": {"coordinates":[8.20656,48.048038],"type":"Point"}
}