{
  "type": "Feature",
  "properties": {
    "iso:country":"DE",
    "sg:address":"Stadtplatz 29",
    "sg:city":"Aichach",
    "sg:phone":"+49 8251/2529",
    "sg:postcode":"86551",
    "sg:province":"Bayern",
    "wof:name":"Stadt-apotheke Aichach P\u00e4chterin Angelika Pflaum E.k.",
    "wof:placetype":"venue"
},
  "geometry": {"coordinates":[11.131103,48.458843],"type":"Point"}
}