{
  "type": "Feature",
  "properties": {
    "iso:country":"DE",
    "sg:address":"Eintrachtstr. 85",
    "sg:city":"Wuppertal",
    "sg:phone":"+49 202/505288",
    "sg:postcode":"42277",
    "sg:province":"Nordrhein-Westfalen",
    "wof:name":"Andreas Werth E. K.",
    "wof:placetype":"venue"
},
  "geometry": {"coordinates":[7.2067670822,51.279838562],"type":"Point"}
}