{
  "type": "Feature",
  "properties": {
    "iso:country":"DE",
    "sg:address":"Sch\u00fctzenstr. 22 - 24",
    "sg:city":"Solingen",
    "sg:phone":"+49 212/41068",
    "sg:postcode":"42659",
    "sg:province":"Nordrhein-Westfalen",
    "wof:name":"Millies Gmbh",
    "wof:placetype":"venue"
},
  "geometry": {"coordinates":[7.0906891823,51.1655921936],"type":"Point"}
}