{
  "type": "Feature",
  "properties": {
    "iso:country":"DE",
    "sg:address":"Martinstr. 53",
    "sg:city":"Harsum",
    "sg:phone":"+49 5127/1536",
    "sg:postcode":"31177",
    "sg:province":"Niedersachsen",
    "wof:name":"Johannes Vollmer",
    "wof:placetype":"venue"
},
  "geometry": {"coordinates":[10.010135,52.209],"type":"Point"}
}