{
  "type": "Feature",
  "properties": {
    "iso:country":"DE",
    "sg:address":"Industriestr. 15",
    "sg:city":"Ottersweier",
    "sg:phone":"+49 7223/984325",
    "sg:postcode":"77833",
    "sg:province":"Baden-W\u00fcrttemberg",
    "wof:name":"M\u00fcller Widerstands- Schwei\u00dftechnik Gmbh",
    "wof:placetype":"venue"
},
  "geometry": {"coordinates":[8.116538,48.678051],"type":"Point"}
}