{
  "type": "Feature",
  "properties": {
    "iso:country":"DE",
    "sg:address":"An der Synagoge 7",
    "sg:city":"Korschenbroich",
    "sg:phone":"+49 2161/64629",
    "sg:postcode":"41352",
    "sg:province":"Nordrhein-Westfalen",
    "wof:name":"Helmut Ditzel",
    "wof:placetype":"venue"
},
  "geometry": {"coordinates":[6.5105671883,51.1910972595],"type":"Point"}
}