{
  "type": "Feature",
  "properties": {
    "iso:country":"DE",
    "sg:address":"Corneliusstr. 5",
    "sg:city":"Kevelaer",
    "sg:phone":"+49 2832/40344",
    "sg:postcode":"47624",
    "sg:province":"Nordrhein-Westfalen",
    "wof:name":"J\u00fcrgen Ingenkamp",
    "wof:placetype":"venue"
},
  "geometry": {"coordinates":[6.2128891945,51.5526504517],"type":"Point"}
}