{
  "type": "Feature",
  "properties": {
    "iso:country":"DE",
    "sg:address":"Frankfurter Str. 44",
    "sg:city":"Jossgrund",
    "sg:phone":"+49 6059/686",
    "sg:postcode":"63637",
    "sg:province":"Hessen",
    "wof:name":"Jossa-apotheke E. K.",
    "wof:placetype":"venue"
},
  "geometry": {"coordinates":[9.473248,50.195248],"type":"Point"}
}