{
  "type": "Feature",
  "properties": {
    "iso:country":"DE",
    "sg:address":"Hofmark 1",
    "sg:city":"Rinchnach",
    "sg:phone":"+49 9921/2703",
    "sg:postcode":"94269",
    "sg:province":"Bayern",
    "wof:name":"Josef Schaller",
    "wof:placetype":"venue"
},
  "geometry": {"coordinates":[13.1987810135,48.9501419067],"type":"Point"}
}