{
  "type": "Feature",
  "properties": {
    "iso:country":"DE",
    "sg:address":"Hagener Str. 68",
    "sg:city":"Iserlohn",
    "sg:phone":"+49 2374/2136",
    "sg:postcode":"58642",
    "sg:province":"Nordrhein-Westfalen",
    "wof:name":"Auto Kalthoff Inh. Ralf Kalthoff",
    "wof:placetype":"venue"
},
  "geometry": {"coordinates":[7.607327,51.365929],"type":"Point"}
}