{
  "type": "Feature",
  "properties": {
    "iso:country":"DE",
    "sg:address":"Hainbuchenweg 2",
    "sg:city":"Leonberg",
    "sg:postcode":"71229",
    "sg:province":"Baden-W\u00fcrttemberg",
    "wof:name":"Talented Athlete Progr.leonbg. Franco Maoro",
    "wof:placetype":"venue"
},
  "geometry": {"coordinates":[9.0176744461,48.794757843],"type":"Point"}
}