{
  "type": "Feature",
  "properties": {
    "iso:country":"DE",
    "sg:address":"Fr\u00fchlingstr. 13",
    "sg:city":"Wackersdorf",
    "sg:postcode":"92442",
    "sg:province":"Bayern",
    "wof:name":"Neunburger Brauereigasthof",
    "wof:placetype":"venue"
},
  "geometry": {"coordinates":[12.1840410233,49.3174934387],"type":"Point"}
}