{
  "type": "Feature",
  "properties": {
    "iso:country":"DE",
    "sg:address":"Billhorner Kanalstr. 56",
    "sg:city":"Hamburg",
    "sg:phone":"+49 40/7893952",
    "sg:postcode":"20539",
    "sg:province":"Hamburg",
    "wof:name":"A. Damman & Co.",
    "wof:placetype":"venue"
},
  "geometry": {"coordinates":[10.0386219025,53.5371780396],"type":"Point"}
}