{
  "type": "Feature",
  "properties": {
    "iso:country":"DE",
    "sg:address":"St\u00f6ckenbergweg 5",
    "sg:city":"Esslingen",
    "sg:phone":"+49 711/378891",
    "sg:postcode":"73732",
    "sg:province":"Baden-W\u00fcrttemberg",
    "wof:name":"Country Und Garden Antiques Gesellschaft F\u00fcr Kunst-",
    "wof:placetype":"venue"
},
  "geometry": {"coordinates":[9.3406457901,48.7464752197],"type":"Point"}
}