{
  "type": "Feature",
  "properties": {
    "iso:country":"DE",
    "sg:address":"Kalzhofer Str. 1",
    "sg:city":"Oberstaufen",
    "sg:postcode":"87534",
    "sg:province":"Bayern",
    "wof:name":"Gelis Trachtenst\u00fcberl Gmbh",
    "wof:placetype":"venue"
},
  "geometry": {"coordinates":[10.022094,47.555],"type":"Point"}
}