{
  "type": "Feature",
  "properties": {
    "iso:country":"DE",
    "sg:address":"Jakob-Kaiser-Weg 3",
    "sg:city":"Rheinfelden",
    "sg:phone":"+49 7623/1366",
    "sg:postcode":"79618",
    "sg:province":"Baden-W\u00fcrttemberg",
    "wof:name":"G. Vogtmann",
    "wof:placetype":"venue"
},
  "geometry": {"coordinates":[7.7807807922,47.5674552917],"type":"Point"}
}