{
  "type": "Feature",
  "properties": {
    "iso:country":"DE",
    "sg:address":"Nattheimer Str. 59",
    "sg:city":"Heidenheim",
    "sg:phone":"+49 7321/965739",
    "sg:postcode":"89520",
    "sg:province":"Baden-W\u00fcrttemberg",
    "wof:name":"Hans M\u00fchlberger",
    "wof:placetype":"venue"
},
  "geometry": {"coordinates":[10.1666488647,48.7046890259],"type":"Point"}
}