{
  "type": "Feature",
  "properties": {
    "iso:country":"DE",
    "sg:address":"M\u00fchlenstr. 5",
    "sg:city":"Allendorf",
    "sg:phone":"+49 6452/91028",
    "sg:postcode":"35108",
    "sg:province":"Hessen",
    "wof:name":"Klaus Schmidt Gmbh",
    "wof:placetype":"venue"
},
  "geometry": {"coordinates":[8.693278,51.025997],"type":"Point"}
}