{
  "type": "Feature",
  "properties": {
    "iso:country":"DE",
    "sg:address":"Hohemarkstr. 158",
    "sg:city":"Oberursel",
    "sg:phone":"+49 6171/26160",
    "sg:postcode":"61440",
    "sg:province":"Hessen",
    "wof:name":"Immosachs Verwaltungs Gmbh",
    "wof:placetype":"venue"
},
  "geometry": {"coordinates":[8.547586,50.215],"type":"Point"}
}