{
  "type": "Feature",
  "properties": {
    "iso:country":"DE",
    "sg:address":"Fischertwiete 2",
    "sg:city":"Hamburg",
    "sg:phone":"+49 40/339790",
    "sg:postcode":"20095",
    "sg:province":"Hamburg",
    "wof:name":"Gratenau & Hesselbacher Zellstoff-papier-karton Gmbh & Co Kg",
    "wof:placetype":"venue"
},
  "geometry": {"coordinates":[10.00159,53.548302],"type":"Point"}
}