{
  "type": "Feature",
  "properties": {
    "iso:country":"DE",
    "sg:address":"Albert-Lortzing-Str. 10",
    "sg:city":"Hof",
    "sg:phone":"+49 9281/91561",
    "sg:postcode":"95030",
    "sg:province":"Bayern",
    "wof:name":"Friedrich Huber Haus- Und K\u00fcchenger\u00e4te",
    "wof:placetype":"venue"
},
  "geometry": {"coordinates":[11.8998851776,50.310092926],"type":"Point"}
}