{
  "type": "Feature",
  "properties": {
    "iso:country":"DE",
    "sg:address":"Corneliuspforte 5",
    "sg:city":"Schweich",
    "sg:phone":"+49 6502/2869",
    "sg:postcode":"54338",
    "sg:province":"Rheinland-Pfalz",
    "wof:name":"Kordel Elektroinstallation",
    "wof:placetype":"venue"
},
  "geometry": {"coordinates":[6.755881,49.823406],"type":"Point"}
}