{
  "type": "Feature",
  "properties": {
    "iso:country":"DE",
    "sg:address":"Schulstr. 29",
    "sg:city":"Pfaffenhofen",
    "sg:phone":"+49 7302/5259",
    "sg:postcode":"89284",
    "sg:province":"Bayern",
    "wof:name":"Anton Wenger",
    "wof:placetype":"venue"
},
  "geometry": {"coordinates":[10.159504,48.346958],"type":"Point"}
}