{
  "type": "Feature",
  "properties": {
    "iso:country":"DE",
    "sg:address":"Rumfordstr 41",
    "sg:city":"M\u00fcnchen",
    "sg:phone":"+49 89/24208090",
    "sg:postcode":"80469",
    "sg:province":"Bayern",
    "wof:name":"Der Karaoke-spezialist Handels- Gmbh",
    "wof:placetype":"venue"
},
  "geometry": {"coordinates":[11.5806179047,48.1340179443],"type":"Point"}
}