{
  "type": "Feature",
  "properties": {
    "iso:country":"DE",
    "sg:address":"Sudhoferweg 93",
    "sg:city":"Beckum",
    "sg:postcode":"59269",
    "sg:province":"Nordrhein-Westfalen",
    "wof:name":"Intra Management Gmbh",
    "wof:placetype":"venue"
},
  "geometry": {"coordinates":[8.0722265244,51.7566490173],"type":"Point"}
}