{
  "type": "Feature",
  "properties": {
    "iso:country":"DE",
    "sg:address":"Maria-Theresia-Allee 85",
    "sg:city":"Aachen",
    "sg:phone":"+49 241/9790210",
    "sg:postcode":"52064",
    "sg:province":"Nordrhein-Westfalen",
    "wof:name":"Franz-josef Unteregge Steuerberater",
    "wof:placetype":"venue"
},
  "geometry": {"coordinates":[6.0791430473,50.7591362],"type":"Point"}
}