{
  "type": "Feature",
  "properties": {
    "iso:country":"DE",
    "sg:address":"Oranienstr. 155-159",
    "sg:city":"Berlin",
    "sg:phone":"+49 30/6169370",
    "sg:postcode":"10969",
    "sg:province":"Berlin",
    "wof:name":"Gustav Epple Bau- Unternehmung Gmbh",
    "wof:placetype":"venue"
},
  "geometry": {"coordinates":[13.412591,52.503021],"type":"Point"}
}