{
  "type": "Feature",
  "properties": {
    "iso:country":"DE",
    "sg:address":"Dreienbergstr. 1",
    "sg:city":"Friedewald",
    "sg:phone":"+49 6674/279",
    "sg:postcode":"36289",
    "sg:province":"Hessen",
    "wof:name":"Wilhelm Deiseroth",
    "wof:placetype":"venue"
},
  "geometry": {"coordinates":[9.8619117737,50.8817939758],"type":"Point"}
}