{
  "type": "Feature",
  "properties": {
    "iso:country":"DE",
    "sg:address":"Kaiserswerther Str. 19",
    "sg:city":"D\u00fcsseldorf",
    "sg:phone":"+49 211/4984010",
    "sg:postcode":"40477",
    "sg:province":"Nordrhein-Westfalen",
    "wof:name":"Konditorei Chocolatier Kuhlen",
    "wof:placetype":"venue"
},
  "geometry": {"coordinates":[6.7783131599,51.2383880615],"type":"Point"}
}