{
  "type": "Feature",
  "properties": {
    "iso:country":"DE",
    "sg:address":"F\u00e4rbergasse 2 a",
    "sg:city":"Weilm\u00fcnster",
    "sg:phone":"+49 6472/2422",
    "sg:postcode":"35789",
    "sg:province":"Hessen",
    "wof:name":"Gastst\u00e4tte Spielb\u00f6rse",
    "wof:placetype":"venue"
},
  "geometry": {"coordinates":[8.3735809326,50.432182312],"type":"Point"}
}