{
  "type": "Feature",
  "properties": {
    "iso:country":"DE",
    "sg:address":"Marktplatz 2",
    "sg:city":"Ludwigsburg",
    "sg:phone":"+49 7141/925009",
    "sg:postcode":"71634",
    "sg:province":"Baden-W\u00fcrttemberg",
    "wof:name":"Gasthof Shanghai",
    "wof:placetype":"venue"
},
  "geometry": {"coordinates":[9.1920518875,48.8967857361],"type":"Point"}
}