{
  "type": "Feature",
  "properties": {
    "iso:country":"DE",
    "sg:address":"Robert-Koch-Str. 9e",
    "sg:city":"Neubrandenburg",
    "sg:phone":"+49 395/7074649",
    "sg:postcode":"17036",
    "sg:province":"Mecklenburg-Vorpommern",
    "wof:name":"Manfred M\u00fcnch",
    "wof:placetype":"venue"
},
  "geometry": {"coordinates":[13.2965250015,53.548160553],"type":"Point"}
}