{
  "type": "Feature",
  "properties": {
    "iso:country":"DE",
    "sg:address":"Wiedmannstr. 12",
    "sg:city":"Tegernheim",
    "sg:phone":"+49 9403/584",
    "sg:postcode":"93105",
    "sg:province":"Bayern",
    "wof:name":"Erich Zahnweh",
    "wof:placetype":"venue"
},
  "geometry": {"coordinates":[12.175172,49.023273],"type":"Point"}
}