{
  "type": "Feature",
  "properties": {
    "iso:country":"DE",
    "sg:address":"Bahnhofstr. 41",
    "sg:city":"Herrsching",
    "sg:phone":"+49 8152/40590",
    "sg:postcode":"82211",
    "sg:province":"Bayern",
    "wof:name":"Ammersee Pilsst\u00fcberl",
    "wof:placetype":"venue"
},
  "geometry": {"coordinates":[11.171918,47.998394],"type":"Point"}
}