{
  "type": "Feature",
  "properties": {
    "iso:country":"DE",
    "sg:address":"Autenbrunnstr. 76",
    "sg:city":"Leinfelden-Echterdingen",
    "sg:phone":"+49 711/792400",
    "sg:postcode":"70771",
    "sg:province":"Baden-W\u00fcrttemberg",
    "wof:name":"Andreas Scharf Bauunternehmen Gmbh",
    "wof:placetype":"venue"
},
  "geometry": {"coordinates":[9.1594,48.681995],"type":"Point"}
}