{
  "type": "Feature",
  "properties": {
    "iso:country":"DE",
    "sg:address":"Am Brunnen 8",
    "sg:city":"Reichshof",
    "sg:phone":"+49 2296/991107",
    "sg:postcode":"51580",
    "sg:province":"Nordrhein-Westfalen",
    "wof:name":"Willi Und Markus Staudinger",
    "wof:placetype":"venue"
},
  "geometry": {"coordinates":[7.649591,50.936066],"type":"Point"}
}