{
  "type": "Feature",
  "properties": {
    "iso:country":"DE",
    "sg:address":"Hohenhausen 4",
    "sg:city":"Ahlerstedt",
    "sg:phone":"+49 4166/7725",
    "sg:postcode":"21702",
    "sg:province":"Niedersachsen",
    "wof:name":"Johann Meier Holzbau Gmbh",
    "wof:placetype":"venue"
},
  "geometry": {"coordinates":[9.4422159195,53.3544769287],"type":"Point"}
}