{
  "type": "Feature",
  "properties": {
    "iso:country":"DE",
    "sg:address":"Hauffstr. 9",
    "sg:city":"Haigerloch",
    "sg:phone":"+49 7474/2405",
    "sg:postcode":"72401",
    "sg:province":"Baden-W\u00fcrttemberg",
    "wof:name":"Leander Epple",
    "wof:placetype":"venue"
},
  "geometry": {"coordinates":[8.8195695877,48.3605155945],"type":"Point"}
}