{
  "type": "Feature",
  "properties": {
    "iso:country":"DE",
    "sg:address":"Sch\u00fctzengraben 3",
    "sg:city":"Brilon",
    "sg:phone":"+49 2961/8464",
    "sg:postcode":"59929",
    "sg:province":"Nordrhein-Westfalen",
    "wof:name":"Franz Varnhagen",
    "wof:placetype":"venue"
},
  "geometry": {"coordinates":[8.567394,51.398506],"type":"Point"}
}