{
  "type": "Feature",
  "properties": {
    "iso:country":"DE",
    "sg:address":"Hamalandstr. 31",
    "sg:city":"Bocholt",
    "sg:phone":"+49 2871/42166",
    "sg:postcode":"46399",
    "sg:province":"Nordrhein-Westfalen",
    "wof:name":"R. M\u00f6llmann",
    "wof:placetype":"venue"
},
  "geometry": {"coordinates":[6.5898079872,51.8640823364],"type":"Point"}
}