{
  "type": "Feature",
  "properties": {
    "iso:country":"DE",
    "sg:address":"Ammonitenstr. 8",
    "sg:city":"Balingen",
    "sg:phone":"+49 7433/8051",
    "sg:postcode":"72336",
    "sg:province":"Baden-W\u00fcrttemberg",
    "wof:name":"Eugen Koch",
    "wof:placetype":"venue"
},
  "geometry": {"coordinates":[8.863514,48.298149],"type":"Point"}
}