{
  "type": "Feature",
  "properties": {
    "iso:country":"DE",
    "sg:address":"August-Bebel-Str. 49",
    "sg:city":"Neuruppin",
    "sg:phone":"+49 3391/2361",
    "sg:postcode":"16816",
    "sg:province":"Brandenburg",
    "wof:name":"Redaktion Ruppiner Tageblatt",
    "wof:placetype":"venue"
},
  "geometry": {"coordinates":[12.8036680222,52.9255943298],"type":"Point"}
}