{
  "type": "Feature",
  "properties": {
    "iso:country":"DE",
    "sg:address":"Neul\u00e4nder 1a",
    "sg:city":"Burbach",
    "sg:phone":"+49 2736/3322",
    "sg:postcode":"57299",
    "sg:province":"Nordrhein-Westfalen",
    "wof:name":"Stoll Metalliesierung Gmbh",
    "wof:placetype":"venue"
},
  "geometry": {"coordinates":[8.131594,50.733379],"type":"Point"}
}