{
  "type": "Feature",
  "properties": {
    "iso:country":"DE",
    "sg:address":"K\u00f6lner Str. 10",
    "sg:city":"Eschborn",
    "sg:postcode":"65760",
    "sg:province":"Hessen",
    "wof:name":"Vareva Consulting Gmbh & Co. Kg",
    "wof:placetype":"venue"
},
  "geometry": {"coordinates":[8.5714664459,50.1319351196],"type":"Point"}
}