{
  "type": "Feature",
  "properties": {
    "iso:country":"DE",
    "sg:address":"F.-O.-Schimmel-Str. 13",
    "sg:city":"Chemnitz",
    "sg:phone":"+49 371/517250",
    "sg:postcode":"09120",
    "sg:province":"Sachsen",
    "wof:name":"Cnc - Technik Lamich Gmbh",
    "wof:placetype":"venue"
},
  "geometry": {"coordinates":[12.923997879,50.8049697876],"type":"Point"}
}