{
  "type": "Feature",
  "properties": {
    "iso:country":"DE",
    "sg:address":"Maingasse 10",
    "sg:city":"Lichtenfels",
    "sg:phone":"+49 9571/4724",
    "sg:postcode":"96215",
    "sg:province":"Bayern",
    "wof:name":"Mathias S\u00f6llner",
    "wof:placetype":"venue"
},
  "geometry": {"coordinates":[11.060058,50.151283],"type":"Point"}
}