{
  "type": "Feature",
  "properties": {
    "iso:country":"DE",
    "sg:city":"Schwabhausen",
    "sg:phone":"+49 8138/9771",
    "sg:postcode":"85247",
    "sg:province":"Bayern",
    "wof:name":"Gema Marie-luise Uthoff",
    "wof:placetype":"venue"
},
  "geometry": {"coordinates":[11.353665,48.303745],"type":"Point"}
}