{
  "type": "Feature",
  "properties": {
    "iso:country":"DE",
    "sg:address":"Gnoiener Str. 9",
    "sg:city":"Tessin",
    "sg:postcode":"18195",
    "sg:province":"Mecklenburg-Vorpommern",
    "wof:name":"Dr. Med. Wolf-dietrich Bahm",
    "wof:placetype":"venue"
},
  "geometry": {"coordinates":[12.469617,54.026672],"type":"Point"}
}