{
  "type": "Feature",
  "properties": {
    "iso:country":"DE",
    "sg:address":"Blitzkuhlenstr 121",
    "sg:city":"Recklinghausen",
    "sg:phone":"+49 2361/655334",
    "sg:postcode":"45659",
    "sg:province":"Nordrhein-Westfalen",
    "wof:name":"Emc Fashion Gmbh & Co Kg",
    "wof:placetype":"venue"
},
  "geometry": {"coordinates":[7.2246007919,51.5943717957],"type":"Point"}
}