{
  "type": "Feature",
  "properties": {
    "iso:country":"DE",
    "sg:address":"Charlottenstr. 35-36",
    "sg:city":"Berlin",
    "sg:phone":"+49 30/2061080",
    "sg:postcode":"10117",
    "sg:province":"Berlin",
    "wof:name":"Havanna Lounge Berlin Veranstaltungsforum Gmbh",
    "wof:placetype":"venue"
},
  "geometry": {"coordinates":[13.3910951614,52.5159416199],"type":"Point"}
}