{
  "type": "Feature",
  "properties": {
    "iso:country":"DE",
    "sg:address":"Gewerbestr. 17",
    "sg:city":"Dogern",
    "sg:phone":"+49 7751/83720",
    "sg:postcode":"79804",
    "sg:province":"Baden-W\u00fcrttemberg",
    "wof:name":"Carl G\u00f6tz Gmbh",
    "wof:placetype":"venue"
},
  "geometry": {"coordinates":[8.157382,47.60265],"type":"Point"}
}