{
  "type": "Feature",
  "properties": {
    "iso:country":"DE",
    "sg:address":"Rathausplatz 1",
    "sg:city":"Lotte",
    "sg:phone":"+49 5404/96500",
    "sg:postcode":"49504",
    "sg:province":"Nordrhein-Westfalen",
    "wof:name":"Hw Wohnbau Gmbh",
    "wof:placetype":"venue"
},
  "geometry": {"coordinates":[7.941268,52.313183],"type":"Point"}
}