{
  "type": "Feature",
  "properties": {
    "iso:country":"DE",
    "sg:address":"B\u00fcrgerschaft 19",
    "sg:city":"St. Peter",
    "sg:phone":"+49 7660/202",
    "sg:postcode":"79271",
    "sg:province":"Baden-W\u00fcrttemberg",
    "wof:name":"Manfred Kreutz",
    "wof:placetype":"venue"
},
  "geometry": {"coordinates":[8.029292,48.01511],"type":"Point"}
}