{
  "type": "Feature",
  "properties": {
    "iso:country":"DE",
    "sg:address":"Pallasweg 4",
    "sg:city":"Magdeburg",
    "sg:phone":"+49 391/611200",
    "sg:postcode":"39118",
    "sg:province":"Sachsen-Anhalt",
    "wof:name":"Twenty Bowling Gmbh",
    "wof:placetype":"venue"
},
  "geometry": {"coordinates":[11.6103973389,52.0815467834],"type":"Point"}
}