{
  "type": "Feature",
  "properties": {
    "iso:country":"DE",
    "sg:address":"Bahnhofstr. 11",
    "sg:city":"Winsen",
    "sg:phone":"+49 4171/603",
    "sg:postcode":"21423",
    "sg:province":"Niedersachsen",
    "wof:name":"Kreissparkasse Harburg",
    "wof:placetype":"venue"
},
  "geometry": {"coordinates":[10.20601,53.359741],"type":"Point"}
}