{
  "type": "Feature",
  "properties": {
    "iso:country":"DE",
    "sg:address":"Arnstorfer Str 16",
    "sg:city":"Simbach",
    "sg:phone":"+49 9954/932010",
    "sg:postcode":"94436",
    "sg:province":"Bayern",
    "wof:name":"Josef Kimmel",
    "wof:placetype":"venue"
},
  "geometry": {"coordinates":[12.739303,48.565392],"type":"Point"}
}