{
  "type": "Feature",
  "properties": {
    "iso:country":"DE",
    "sg:address":"Aachener Str. 85a",
    "sg:city":"Koblenz",
    "sg:phone":"+49 261/2100186",
    "sg:postcode":"56072",
    "sg:province":"Rheinland-Pfalz",
    "wof:name":"E. Vacin Immobilienmakler",
    "wof:placetype":"venue"
},
  "geometry": {"coordinates":[7.5189361572,50.3701858521],"type":"Point"}
}