{
  "type": "Feature",
  "properties": {
    "iso:country":"DE",
    "sg:address":"Luisenstr. 14",
    "sg:city":"Kehl",
    "sg:phone":"+49 7851/2512",
    "sg:postcode":"77694",
    "sg:province":"Baden-W\u00fcrttemberg",
    "wof:name":"Helmut Wernigk",
    "wof:placetype":"venue"
},
  "geometry": {"coordinates":[7.816408,48.569469],"type":"Point"}
}