{
  "type": "Feature",
  "properties": {
    "iso:country":"DE",
    "sg:address":"Am Wiesengrund 1",
    "sg:city":"Laage",
    "sg:phone":"+49 38459/6810",
    "sg:postcode":"18299",
    "sg:province":"Mecklenburg-Vorpommern",
    "wof:name":"Klaus Gmbh & Co. Kg",
    "wof:placetype":"venue"
},
  "geometry": {"coordinates":[12.313582,53.937267],"type":"Point"}
}