{
  "type": "Feature",
  "properties": {
    "iso:country":"DE",
    "sg:address":"Bruchweg 22",
    "sg:city":"Birkenheide",
    "sg:phone":"+49 6237/3317",
    "sg:postcode":"67134",
    "sg:province":"Rheinland-Pfalz",
    "wof:name":"Kurt Bitsch",
    "wof:placetype":"venue"
},
  "geometry": {"coordinates":[8.2543783188,49.481136322],"type":"Point"}
}