{
  "type": "Feature",
  "properties": {
    "iso:country":"DE",
    "sg:address":"Seeplanstr. 9",
    "sg:city":"Eisenh\u00fcttenstadt",
    "sg:phone":"+49 3364/414730",
    "sg:postcode":"15890",
    "sg:province":"Brandenburg",
    "wof:name":"H. Zimdahl",
    "wof:placetype":"venue"
},
  "geometry": {"coordinates":[14.630941,52.156647],"type":"Point"}
}