{
  "type": "Feature",
  "properties": {
    "iso:country":"DE",
    "sg:address":"Klaus-Groth-Str. 4",
    "sg:city":"Schuby",
    "sg:phone":"+49 4621/4991",
    "sg:postcode":"24850",
    "sg:province":"Schleswig-Holstein",
    "wof:name":"Olaf K\u00f6nig",
    "wof:placetype":"venue"
},
  "geometry": {"coordinates":[9.4758520126,54.516910553],"type":"Point"}
}