{
  "type": "Feature",
  "properties": {
    "iso:country":"DE",
    "sg:address":"Adenauerring 6",
    "sg:city":"Worms",
    "sg:phone":"+49 6241/6169",
    "sg:postcode":"67547",
    "sg:province":"Rheinland-Pfalz",
    "wof:name":"China Restaurant Pavillon",
    "wof:placetype":"venue"
},
  "geometry": {"coordinates":[8.3633041382,49.6336784363],"type":"Point"}
}