{
  "type": "Feature",
  "properties": {
    "iso:country":"DE",
    "sg:address":"Wilhelm-Strau\u00df-Weg 17",
    "sg:city":"Hamburg",
    "sg:postcode":"21109",
    "sg:province":"Hamburg",
    "wof:name":"Gbl Kemal G\u00fcven",
    "wof:placetype":"venue"
},
  "geometry": {"coordinates":[10.011026,53.498871],"type":"Point"}
}