{
  "type": "Feature",
  "properties": {
    "iso:country":"DE",
    "sg:address":"Harburger Str. 29",
    "sg:city":"Hanstedt",
    "sg:phone":"+49 4184/7152",
    "sg:postcode":"21271",
    "sg:province":"Niedersachsen",
    "wof:name":"G\u00fcnther Jendryssek",
    "wof:placetype":"venue"
},
  "geometry": {"coordinates":[10.010986,53.261936],"type":"Point"}
}