{
  "type": "Feature",
  "properties": {
    "iso:country":"DE",
    "sg:address":"Adam-Kraft-Str. 7",
    "sg:city":"Lauf",
    "sg:phone":"+49 9123/4311",
    "sg:postcode":"91207",
    "sg:province":"Bayern",
    "wof:name":"Oskar H\u00f6pfner Ingenieur",
    "wof:placetype":"venue"
},
  "geometry": {"coordinates":[11.2695817947,49.5207977295],"type":"Point"}
}