{
  "type": "Feature",
  "properties": {
    "iso:country":"DE",
    "sg:address":"Burgwedeler Str. 12 - 14",
    "sg:city":"Isernhagen",
    "sg:phone":"+49 511/735292",
    "sg:postcode":"30916",
    "sg:province":"Niedersachsen",
    "wof:name":"Contact-impex",
    "wof:placetype":"venue"
},
  "geometry": {"coordinates":[9.7900114059,52.4566307068],"type":"Point"}
}