{
  "type": "Feature",
  "properties": {
    "iso:country":"DE",
    "sg:address":"Berliner Str. 106",
    "sg:city":"Fichtenwalde",
    "sg:postcode":"14547",
    "sg:province":"Brandenburg",
    "wof:name":"Fiwag Bautr\u00e4gerges. Mbh",
    "wof:placetype":"venue"
},
  "geometry": {"coordinates":[12.8898353577,52.2800636292],"type":"Point"}
}