{
  "type": "Feature",
  "properties": {
    "iso:country":"DE",
    "sg:address":"Oldendorfer Str. 28",
    "sg:city":"Amelinghausen",
    "sg:phone":"+49 4132/910353",
    "sg:postcode":"21385",
    "sg:province":"Niedersachsen",
    "wof:name":"Leo Frank Gmbh Erdbau",
    "wof:placetype":"venue"
},
  "geometry": {"coordinates":[10.2143659592,53.1350975037],"type":"Point"}
}