{
  "type": "Feature",
  "properties": {
    "iso:country":"DE",
    "sg:address":"Stadtplatz 2",
    "sg:city":"Vilsbiburg",
    "sg:phone":"+49 8741/96420",
    "sg:postcode":"84137",
    "sg:province":"Bayern",
    "wof:name":"Elektro-radio Hammer",
    "wof:placetype":"venue"
},
  "geometry": {"coordinates":[12.3536949158,48.4497947693],"type":"Point"}
}