{
  "type": "Feature",
  "properties": {
    "iso:country":"DE",
    "sg:address":"In der Reis 5",
    "sg:city":"March",
    "sg:phone":"+49 7665/3597",
    "sg:postcode":"79232",
    "sg:province":"Baden-W\u00fcrttemberg",
    "wof:name":"G-cad Thomas Gerspach Gmbh",
    "wof:placetype":"venue"
},
  "geometry": {"coordinates":[7.7732200623,48.0575904846],"type":"Point"}
}