{
  "type": "Feature",
  "properties": {
    "iso:country":"DE",
    "sg:address":"mdljfkdflstrasse23",
    "sg:city":"ddfkfjdfj",
    "sg:phone":"+49 190123456",
    "sg:postcode":"56844",
    "wof:name":"The Biggest Girls",
    "wof:placetype":"venue"
},
  "geometry": {"coordinates":[-98.87190200000001,19.050989],"type":"Point"}
}