{
  "type": "Feature",
  "properties": {
    "iso:country":"DE",
    "sg:address":"Wiesenaustr. 4",
    "sg:city":"Oberursel",
    "sg:phone":"+49 6171/4610",
    "sg:postcode":"61440",
    "sg:province":"Hessen",
    "wof:name":"Dr. G\u00fcnther H. Schmidt Rechtsanwalt",
    "wof:placetype":"venue"
},
  "geometry": {"coordinates":[8.5828866959,50.1977539062],"type":"Point"}
}