{
  "type": "Feature",
  "properties": {
    "iso:country":"DE",
    "sg:address":"Ingolst\u00e4dter Str. 10",
    "sg:city":"Karlskron",
    "sg:phone":"+49 8450/1418",
    "sg:postcode":"85123",
    "sg:province":"Bayern",
    "wof:name":"G\u00d6tz Gmbh",
    "wof:placetype":"venue"
},
  "geometry": {"coordinates":[11.407268,48.681999],"type":"Point"}
}