{
  "type": "Feature",
  "properties": {
    "iso:country":"DE",
    "sg:address":"Hansastr. 1",
    "sg:city":"Lahr",
    "sg:phone":"+49 4978/2190740",
    "sg:postcode":"77933",
    "sg:province":"Baden-W\u00fcrttemberg",
    "wof:name":"Rolf Kelch Electronic Gmbh",
    "wof:placetype":"venue"
},
  "geometry": {"coordinates":[7.865642,48.339233],"type":"Point"}
}