{
  "type": "Feature",
  "properties": {
    "iso:country":"DE",
    "sg:address":"Hennener Str. 73",
    "sg:city":"Iserlohn",
    "sg:phone":"+49 2304/5240",
    "sg:postcode":"58640",
    "sg:province":"Nordrhein-Westfalen",
    "wof:name":"Tankstelle U. Kfz-reparatur- Betreib Gerhard Struck E. K.",
    "wof:placetype":"venue"
},
  "geometry": {"coordinates":[7.6538991928,51.4422149658],"type":"Point"}
}