{
  "type": "Feature",
  "properties": {
    "iso:country":"DE",
    "sg:address":"Schlo\u00dfstr. 10",
    "sg:city":"Haiterbach",
    "sg:phone":"+49 7456/93840",
    "sg:postcode":"72221",
    "sg:province":"Baden-W\u00fcrttemberg",
    "wof:name":"Gca Gesellschaft F\u00fcr Computeranlagen Mbh",
    "wof:placetype":"venue"
},
  "geometry": {"coordinates":[8.6715402603,48.5414047241],"type":"Point"}
}