{
  "type": "Feature",
  "properties": {
    "iso:country":"DE",
    "sg:address":"Austr. 3",
    "sg:city":"B\u00f6blingen",
    "sg:phone":"+49 7031/236474",
    "sg:postcode":"71034",
    "sg:province":"Baden-W\u00fcrttemberg",
    "wof:name":"Gesellschaft F\u00fcr Rationelles Bauen Mbh",
    "wof:placetype":"venue"
},
  "geometry": {"coordinates":[9.005396,48.68515],"type":"Point"}
}