{
  "type": "Feature",
  "properties": {
    "iso:country":"DE",
    "sg:address":"Michaelkirchplatz 11",
    "sg:city":"Berlin",
    "sg:phone":"+49 30/2793614",
    "sg:postcode":"10179",
    "sg:province":"Berlin",
    "wof:name":"Berliner Wappen",
    "wof:placetype":"venue"
},
  "geometry": {"coordinates":[13.4205255508,52.5078201294],"type":"Point"}
}