{
  "type": "Feature",
  "properties": {
    "iso:country":"DE",
    "sg:address":"Siedlerweg 6a",
    "sg:city":"Sassenburg",
    "sg:phone":"+49 5378/470",
    "sg:postcode":"38524",
    "sg:province":"Niedersachsen",
    "wof:name":"Sch\u00fctz Verwaltungs Gmbh",
    "wof:placetype":"venue"
},
  "geometry": {"coordinates":[10.613861084,52.5456962585],"type":"Point"}
}