{
  "type": "Feature",
  "properties": {
    "iso:country":"DE",
    "sg:address":"Oestertalstr. 108",
    "sg:city":"Plettenberg",
    "sg:phone":"+49 2391/70380",
    "sg:postcode":"58840",
    "sg:province":"Nordrhein-Westfalen",
    "wof:name":"Hannelore Seebo Kg",
    "wof:placetype":"venue"
},
  "geometry": {"coordinates":[7.8614602089,51.1907806396],"type":"Point"}
}