{
  "type": "Feature",
  "properties": {
    "iso:country":"DE",
    "sg:address":"Hofmannstr. 23",
    "sg:city":"Dresden",
    "sg:phone":"+49 351/340780",
    "sg:postcode":"01277",
    "sg:province":"Sachsen",
    "wof:name":"Schneider & Partner Gmbh",
    "wof:placetype":"venue"
},
  "geometry": {"coordinates":[13.8108301163,51.0416946411],"type":"Point"}
}