{
  "type": "Feature",
  "properties": {
    "iso:country":"DE",
    "sg:address":"Zehntwiesenstr. 68",
    "sg:city":"Ettlingen",
    "sg:phone":"+49 7243/535770",
    "sg:postcode":"76275",
    "sg:province":"Baden-W\u00fcrttemberg",
    "wof:name":"F. Zittel",
    "wof:placetype":"venue"
},
  "geometry": {"coordinates":[8.3911161423,48.9458312988],"type":"Point"}
}