{
  "type": "Feature",
  "properties": {
    "iso:country":"DE",
    "sg:address":"Werner-von-Siemens-Str. 11",
    "sg:city":"Wunstorf",
    "sg:phone":"+49 5031/9610",
    "sg:postcode":"31515",
    "sg:province":"Niedersachsen",
    "wof:name":"Sikkens Gmbh",
    "wof:placetype":"venue"
},
  "geometry": {"coordinates":[9.455924,52.415791],"type":"Point"}
}