{
  "type": "Feature",
  "properties": {
    "iso:country":"DE",
    "sg:address":"Pirnaer Str. 30",
    "sg:city":"Heidenau",
    "sg:phone":"+49 3529/512340",
    "sg:postcode":"01809",
    "sg:province":"Sachsen",
    "wof:name":"S\u00fcd-apotheke",
    "wof:placetype":"venue"
},
  "geometry": {"coordinates":[13.874025,50.972702],"type":"Point"}
}