{
  "type": "Feature",
  "properties": {
    "iso:country":"DE",
    "sg:address":"Hauptstr. 117",
    "sg:city":"K\u00f6nigswinter",
    "sg:phone":"+49 2223/27216",
    "sg:postcode":"53639",
    "sg:province":"Nordrhein-Westfalen",
    "wof:name":"Die Pumpe",
    "wof:placetype":"venue"
},
  "geometry": {"coordinates":[7.1795330048,50.693561554],"type":"Point"}
}