{
  "type": "Feature",
  "properties": {
    "iso:country":"DE",
    "sg:address":"Marktstr. 43/44 Aldi Passage",
    "sg:city":"Bad Sachsa",
    "sg:postcode":"37441",
    "sg:province":"Niedersachsen",
    "wof:name":"Aldi Gmbh & Co. Kg",
    "wof:placetype":"venue"
},
  "geometry": {"coordinates":[10.5504417419,51.5946006775],"type":"Point"}
}