{
  "type": "Feature",
  "properties": {
    "iso:country":"DE",
    "sg:address":"Am Auwald 11",
    "sg:city":"Hindelang",
    "sg:phone":"+49 8324/335",
    "sg:postcode":"87541",
    "sg:province":"Bayern",
    "wof:name":"Benninghoff Holzbau Gmbh",
    "wof:placetype":"venue"
},
  "geometry": {"coordinates":[10.3471517563,47.5015335083],"type":"Point"}
}