{
  "type": "Feature",
  "properties": {
    "iso:country":"DE",
    "sg:address":"Weideweg 4",
    "sg:city":"Breitscheid",
    "sg:phone":"+49 2777/7236",
    "sg:postcode":"35767",
    "sg:province":"Hessen",
    "wof:name":"G\u00fcnter Thomas",
    "wof:placetype":"venue"
},
  "geometry": {"coordinates":[8.147085,50.679783],"type":"Point"}
}