{
  "type": "Feature",
  "properties": {
    "iso:country":"DE",
    "sg:address":"Im Kirchenfelde 41",
    "sg:city":"Paderborn",
    "sg:postcode":"33106",
    "sg:province":"Nordrhein-Westfalen",
    "wof:name":"Paderwolle Gmbh",
    "wof:placetype":"venue"
},
  "geometry": {"coordinates":[8.6981601715,51.6805610657],"type":"Point"}
}