{
  "type": "Feature",
  "properties": {
    "iso:country":"DE",
    "sg:address":"Dammweg 6",
    "sg:city":"Wesel",
    "sg:phone":"+49 281/23058",
    "sg:postcode":"46483",
    "sg:province":"Nordrhein-Westfalen",
    "wof:name":"Theo Sondermann Steuerberater",
    "wof:placetype":"venue"
},
  "geometry": {"coordinates":[6.6265292168,51.651008606],"type":"Point"}
}