{
  "type": "Feature",
  "properties": {
    "iso:country":"DE",
    "sg:address":"T\u00f6pferstr. 96",
    "sg:city":"Geilenkirchen",
    "sg:phone":"+49 2451/5152",
    "sg:postcode":"52511",
    "sg:province":"Nordrhein-Westfalen",
    "wof:name":"Adam Cremers Gmbh",
    "wof:placetype":"venue"
},
  "geometry": {"coordinates":[6.0756502151,50.9529495239],"type":"Point"}
}