{
  "type": "Feature",
  "properties": {
    "iso:country":"DE",
    "sg:address":"Zum Kahlen Felde 12",
    "sg:city":"Northeim",
    "sg:phone":"+49 5551/5026",
    "sg:postcode":"37154",
    "sg:province":"Niedersachsen",
    "wof:name":"Spedition Eckhardt Roth",
    "wof:placetype":"venue"
},
  "geometry": {"coordinates":[9.9591693878,51.7623558044],"type":"Point"}
}