{
  "type": "Feature",
  "properties": {
    "iso:country":"DE",
    "sg:address":"Go\u00dflerstr. 18",
    "sg:city":"Berlin",
    "sg:phone":"+49 30/8515880",
    "sg:postcode":"12161",
    "sg:province":"Berlin",
    "wof:name":"Karin Hyzdal Von Miserony",
    "wof:placetype":"venue"
},
  "geometry": {"coordinates":[13.3243494034,52.4689407349],"type":"Point"}
}