{
  "type": "Feature",
  "properties": {
    "iso:country":"DE",
    "sg:address":"Rantumer Str. 16",
    "sg:city":"H\u00f6rnum",
    "sg:postcode":"25997",
    "sg:province":"Schleswig-Holstein",
    "wof:name":"Spar-markt Ingo Dehn",
    "wof:placetype":"venue"
},
  "geometry": {"coordinates":[8.2876462936,54.7560386658],"type":"Point"}
}