{
  "type": "Feature",
  "properties": {
    "iso:country":"DE",
    "sg:address":"Breslauer Str. 8",
    "sg:city":"Sindelfingen",
    "sg:phone":"+49 7031/876543",
    "sg:postcode":"71065",
    "sg:province":"Baden-W\u00fcrttemberg",
    "wof:name":"Hans-georg Lang",
    "wof:placetype":"venue"
},
  "geometry": {"coordinates":[9.021953,48.701439],"type":"Point"}
}