{
  "type": "Feature",
  "properties": {
    "iso:country":"DE",
    "sg:address":"Prinz-Albrecht-Ring 12",
    "sg:city":"Hannover",
    "sg:phone":"+49 511/6069777",
    "sg:postcode":"30657",
    "sg:province":"Niedersachsen",
    "wof:name":"M. Kr\u00f6smann Praxis F\u00fcr Ergotherapie",
    "wof:placetype":"venue"
},
  "geometry": {"coordinates":[9.78943,52.412468],"type":"Point"}
}