{
  "type": "Feature",
  "properties": {
    "iso:country":"DE",
    "sg:address":"Vilshofener Str. 23",
    "sg:city":"Eging",
    "sg:phone":"+49 8544/8198",
    "sg:postcode":"94535",
    "sg:province":"Bayern",
    "wof:name":"Duschl Mietauto Inh. Katharina Duschl",
    "wof:placetype":"venue"
},
  "geometry": {"coordinates":[13.263972,48.710766],"type":"Point"}
}