{
  "type": "Feature",
  "properties": {
    "iso:country":"DE",
    "sg:address":"Am Brande 18",
    "sg:city":"Altenbeken",
    "sg:phone":"+49 5255",
    "sg:postcode":"33184",
    "sg:province":"Nordrhein-Westfalen",
    "wof:name":"I B S - Ingenieur - B\u00fcro - Sprenger Altenbeken",
    "wof:placetype":"venue"
},
  "geometry": {"coordinates":[8.947896,51.76136],"type":"Point"}
}