{
  "type": "Feature",
  "properties": {
    "iso:country":"DE",
    "sg:address":"Feldstr. 9",
    "sg:city":"Kleinblittersdorf",
    "sg:phone":"+49 6805/4780",
    "sg:postcode":"66271",
    "sg:province":"Saarland",
    "wof:name":"Manfred Kany Ingenieur",
    "wof:placetype":"venue"
},
  "geometry": {"coordinates":[7.0701098442,49.1351127625],"type":"Point"}
}