{
  "type": "Feature",
  "properties": {
    "iso:country":"DE",
    "sg:address":"Eisackstr. 37",
    "sg:city":"Berlin",
    "sg:phone":"+49 30/8551553",
    "sg:postcode":"10827",
    "sg:province":"Berlin",
    "wof:name":"Frank Weise Architekt",
    "wof:placetype":"venue"
},
  "geometry": {"coordinates":[13.345049,52.476948],"type":"Point"}
}