{
  "type": "Feature",
  "properties": {
    "iso:country":"DE",
    "sg:address":"Pfingstweidstr. 16",
    "sg:city":"Mannheim",
    "sg:phone":"+49 621/844090",
    "sg:postcode":"68199",
    "sg:province":"Baden-W\u00fcrttemberg",
    "wof:name":"Vfg Dessous Vertriebs Gmbh",
    "wof:placetype":"venue"
},
  "geometry": {"coordinates":[8.4996442795,49.460521698],"type":"Point"}
}