{
  "type": "Feature",
  "properties": {
    "iso:country":"DE",
    "sg:address":"Karlsruher Str. 8",
    "sg:city":"Schwetzingen",
    "sg:phone":"+49 6202/24891",
    "sg:postcode":"68723",
    "sg:province":"Baden-W\u00fcrttemberg",
    "wof:name":"Selbstverteidigungsschule",
    "wof:placetype":"venue"
},
  "geometry": {"coordinates":[8.5723056793,49.3835029602],"type":"Point"}
}