{
  "type": "Feature",
  "properties": {
    "iso:country":"DE",
    "sg:address":"Bodestr. 16",
    "sg:city":"Hamburg",
    "sg:phone":"+49 40/7390534",
    "sg:postcode":"21031",
    "sg:province":"Hamburg",
    "wof:name":"Uwe F. R\u00f6ssler",
    "wof:placetype":"venue"
},
  "geometry": {"coordinates":[10.1813936234,53.5089950562],"type":"Point"}
}