{
  "type": "Feature",
  "properties": {
    "iso:country":"DE",
    "sg:address":"\u00dcberseering 18",
    "sg:city":"Hamburg",
    "sg:phone":"+49 4969/66390",
    "sg:postcode":"22297",
    "sg:province":"Hamburg",
    "wof:name":"Techem Ag",
    "wof:placetype":"venue"
},
  "geometry": {"coordinates":[8.6328144073,50.0814437866],"type":"Point"}
}