{
  "type": "Feature",
  "properties": {
    "iso:country":"DE",
    "sg:address":"billerbeckstrasse",
    "sg:city":"witten",
    "sg:postcode":"58453",
    "sg:province":"Nordrhein-Westfalen",
    "wof:name":"Rudolf Steiner Schule Witten",
    "wof:placetype":"venue"
},
  "geometry": {"coordinates":[7.31749,51.438389],"type":"Point"}
}