{
  "type": "Feature",
  "properties": {
    "iso:country":"DE",
    "sg:address":"Moltkestr. 1",
    "sg:city":"M\u00fcnchen",
    "sg:phone":"+49 89/397744",
    "sg:postcode":"80803",
    "sg:province":"Bayern",
    "wof:name":"Hermann M\u00fchlbauer Rechtsanwalt",
    "wof:placetype":"venue"
},
  "geometry": {"coordinates":[11.5807008743,48.1642417908],"type":"Point"}
}