{
  "type": "Feature",
  "properties": {
    "iso:country":"DE",
    "sg:address":"Deweerthstr. 117",
    "sg:city":"Wuppertal",
    "sg:phone":"+49 202/493940",
    "sg:postcode":"42107",
    "sg:province":"Nordrhein-Westfalen",
    "wof:name":"Beratungsstelle D. Dia- Konischen Werkes",
    "wof:placetype":"venue"
},
  "geometry": {"coordinates":[7.152873,51.259686],"type":"Point"}
}