{
  "type": "Feature",
  "properties": {
    "iso:country":"DE",
    "sg:address":"Schlesische Str. 6-8",
    "sg:city":"Geretsried",
    "sg:phone":"+49 8171/61021",
    "sg:postcode":"82538",
    "sg:province":"Bayern",
    "wof:name":"Private Krankenanstalt Geretsried Gmbh",
    "wof:placetype":"venue"
},
  "geometry": {"coordinates":[11.468651,47.878372],"type":"Point"}
}