{
  "type": "Feature",
  "properties": {
    "iso:country":"DE",
    "sg:address":"Flurlgasse 11",
    "sg:city":"Straubing",
    "sg:phone":"+49 9421/2880",
    "sg:postcode":"94315",
    "sg:province":"Bayern",
    "wof:name":"Regenbogenhaus Jutta Schmelter",
    "wof:placetype":"venue"
},
  "geometry": {"coordinates":[12.5710144043,48.8814353943],"type":"Point"}
}