{
  "type": "Feature",
  "properties": {
    "iso:country":"DE",
    "sg:address":"Johann-Bensberg-Str. 49",
    "sg:city":"K\u00f6ln",
    "sg:phone":"+49 221/695909",
    "sg:postcode":"51067",
    "sg:province":"Nordrhein-Westfalen",
    "wof:name":"Restaurant Isenburg",
    "wof:placetype":"venue"
},
  "geometry": {"coordinates":[7.0415301323,50.9659805298],"type":"Point"}
}