{
  "type": "Feature",
  "properties": {
    "iso:country":"DE",
    "sg:address":"Guido-Seeber-Weg 13",
    "sg:city":"Potsdam",
    "sg:postcode":"14480",
    "sg:province":"Brandenburg",
    "wof:name":"Verm\u00f6gensberatung Peter Diering",
    "wof:placetype":"venue"
},
  "geometry": {"coordinates":[13.1380252838,52.3691482544],"type":"Point"}
}