{
  "type": "Feature",
  "properties": {
    "iso:country":"DE",
    "sg:address":"Birkenweg 17",
    "sg:city":"Grenzach-Wyhlen",
    "sg:phone":"+49 7624/8445",
    "sg:postcode":"79639",
    "sg:province":"Baden-W\u00fcrttemberg",
    "wof:name":"Norbert Stiefvater",
    "wof:placetype":"venue"
},
  "geometry": {"coordinates":[7.7072901726,47.5459861755],"type":"Point"}
}