{
  "type": "Feature",
  "properties": {
    "iso:country":"DE",
    "sg:address":"Rubihornstr. 5",
    "sg:city":"Oberstdorf",
    "sg:phone":"+49 8326/461",
    "sg:postcode":"87561",
    "sg:province":"Bayern",
    "wof:name":"Fremdenheim Neidhart",
    "wof:placetype":"venue"
},
  "geometry": {"coordinates":[10.2949237823,47.4577178955],"type":"Point"}
}