{
  "type": "Feature",
  "properties": {
    "iso:country":"DE",
    "sg:address":"Hamburger Allee 6/2002",
    "sg:city":"Hannover",
    "sg:phone":"+49 511/311283",
    "sg:postcode":"30161",
    "sg:province":"Niedersachsen",
    "wof:name":"Br\u00fcger Gmbh & Co. Simulation Und Training Kg",
    "wof:placetype":"venue"
},
  "geometry": {"coordinates":[9.742528,52.379997],"type":"Point"}
}