{
  "type": "Feature",
  "properties": {
    "iso:country":"DE",
    "sg:address":"Marktstr. 25",
    "sg:city":"Kirchheim",
    "sg:phone":"+49 7021/92230",
    "sg:postcode":"73230",
    "sg:province":"Baden-W\u00fcrttemberg",
    "wof:name":"Friedrich Riethm\u00fcller Gmbh",
    "wof:placetype":"venue"
},
  "geometry": {"coordinates":[9.4514017105,48.6481437683],"type":"Point"}
}