{
  "type": "Feature",
  "properties": {
    "iso:country":"DE",
    "sg:address":"Hollener Landstr. 8",
    "sg:city":"Uplengen",
    "sg:phone":"+49 4956/1284",
    "sg:postcode":"26670",
    "sg:province":"Niedersachsen",
    "wof:name":"Ev. Pfarramt Hollen",
    "wof:placetype":"venue"
},
  "geometry": {"coordinates":[7.6996507645,53.2502632141],"type":"Point"}
}