{
  "type": "Feature",
  "properties": {
    "iso:country":"DE",
    "sg:address":"Daimlerstr. 6",
    "sg:city":"H\u00fcrth",
    "sg:phone":"+49 2233/974070",
    "sg:postcode":"50354",
    "sg:province":"Nordrhein-Westfalen",
    "wof:name":"Adam Mund Gmbh & Co Kg",
    "wof:placetype":"venue"
},
  "geometry": {"coordinates":[6.899535,50.884548],"type":"Point"}
}