{
  "type": "Feature",
  "properties": {
    "iso:country":"DE",
    "sg:address":"Kleiberstr. 9",
    "sg:city":"Vaterstetten",
    "sg:phone":"+49 8106/303950",
    "sg:postcode":"85591",
    "sg:province":"Bayern",
    "wof:name":"Edeltraud Walter",
    "wof:placetype":"venue"
},
  "geometry": {"coordinates":[11.766781,48.106602],"type":"Point"}
}