{
  "type": "Feature",
  "properties": {
    "iso:country":"DE",
    "sg:address":"Hauptstr. 19",
    "sg:city":"Alsbach H\u00e4hnlein",
    "sg:phone":"+49 4962/572693",
    "sg:postcode":"64665",
    "sg:province":"Hessen",
    "wof:name":"Stadt- U. Kreis-sparkasse Darmstadt",
    "wof:placetype":"venue"
},
  "geometry": {"coordinates":[8.624828,49.741474],"type":"Point"}
}