{
  "type": "Feature",
  "properties": {
    "iso:country":"DE",
    "sg:address":"Bovender Str.",
    "sg:city":"Bovenden",
    "sg:phone":"+49 5593/8040",
    "sg:postcode":"37120",
    "sg:province":"Niedersachsen",
    "wof:name":"Raulf Bau- Gmbh",
    "wof:placetype":"venue"
},
  "geometry": {"coordinates":[9.878632,51.582863],"type":"Point"}
}