{
  "type": "Feature",
  "properties": {
    "iso:country":"DE",
    "sg:address":"Gebr.-Meyer-Str. 6",
    "sg:city":"Detmold",
    "sg:phone":"+49 5232/8198",
    "sg:postcode":"32758",
    "sg:province":"Nordrhein-Westfalen",
    "wof:name":"De Wa Bo Malerbetriebs Gmbh",
    "wof:placetype":"venue"
},
  "geometry": {"coordinates":[8.813657,51.953369],"type":"Point"}
}