{
  "type": "Feature",
  "properties": {
    "iso:country":"DE",
    "sg:address":"L\u00f6hrstr. 113",
    "sg:city":"Koblenz",
    "sg:postcode":"56068",
    "sg:province":"Rheinland-Pfalz",
    "wof:name":"Gbe Gleisbau-engineering Gmbh",
    "wof:placetype":"venue"
},
  "geometry": {"coordinates":[7.590362,50.354706],"type":"Point"}
}