{
  "type": "Feature",
  "properties": {
    "iso:country":"DE",
    "sg:address":"Ringstr. 23",
    "sg:city":"Fahrenzhausen",
    "sg:phone":"+49 8133/1061",
    "sg:postcode":"85777",
    "sg:province":"Bayern",
    "wof:name":"Ilse Pf\u00e4hler Krankengymnastin",
    "wof:placetype":"venue"
},
  "geometry": {"coordinates":[11.528925,48.356632],"type":"Point"}
}