{
  "type": "Feature",
  "properties": {
    "iso:country":"DE",
    "sg:address":"Am Wall 19-25",
    "sg:city":"Bochum",
    "sg:phone":"+49 2327/85719",
    "sg:postcode":"44866",
    "sg:province":"Nordrhein-Westfalen",
    "wof:name":"K\u00e4nguruh-apotheke Joachim Schwarz",
    "wof:placetype":"venue"
},
  "geometry": {"coordinates":[7.135784,51.479465],"type":"Point"}
}