{
  "type": "Feature",
  "properties": {
    "iso:country":"DE",
    "sg:address":"Halenreie 42-44",
    "sg:city":"Hamburg",
    "sg:phone":"+49 40/603070",
    "sg:postcode":"22359",
    "sg:province":"Hamburg",
    "wof:name":"Dbv-winterthur",
    "wof:placetype":"venue"
},
  "geometry": {"coordinates":[10.160871,53.653679],"type":"Point"}
}