{
  "type": "Feature",
  "properties": {
    "iso:country":"DE",
    "sg:address":"Nordrg. 70",
    "sg:city":"Sch\u00fcttorf",
    "sg:phone":"+49 4959/234777",
    "sg:postcode":"48465",
    "sg:province":"Niedersachsen",
    "wof:name":"Eissing Tankstellen Und Transport Gmbh",
    "wof:placetype":"venue"
},
  "geometry": {"coordinates":[7.247064,52.329144],"type":"Point"}
}