{
  "type": "Feature",
  "properties": {
    "iso:country":"DE",
    "sg:address":"Sandstr. 7",
    "sg:city":"Lingen",
    "sg:postcode":"49808",
    "sg:province":"Niedersachsen",
    "wof:name":"E. Meyersieck Heissmangelbetrieb",
    "wof:placetype":"venue"
},
  "geometry": {"coordinates":[7.3158597946,52.5215492249],"type":"Point"}
}