{
  "type": "Feature",
  "properties": {
    "iso:country":"DE",
    "sg:address":"Luxemburger Str. 51",
    "sg:city":"Trier",
    "sg:phone":"+49 651/85992",
    "sg:postcode":"54294",
    "sg:province":"Rheinland-Pfalz",
    "wof:name":"Friedel Thome",
    "wof:placetype":"venue"
},
  "geometry": {"coordinates":[6.624378,49.747143],"type":"Point"}
}