{
  "type": "Feature",
  "properties": {
    "iso:country":"DE",
    "sg:address":"Sch\u00fcppenstr. 2-4",
    "sg:city":"Coesfeld",
    "sg:phone":"+49 2541/982677",
    "sg:postcode":"48653",
    "sg:province":"Nordrhein-Westfalen",
    "wof:name":"Spielothek Play 2000 Gmbh",
    "wof:placetype":"venue"
},
  "geometry": {"coordinates":[7.1674108505,51.9457168579],"type":"Point"}
}