{
  "type": "Feature",
  "properties": {
    "iso:country":"DE",
    "sg:address":"Schwerzeralle 60",
    "sg:city":"Schw\u00e4bisch Gm\u00fcnd",
    "sg:postcode":"73525",
    "sg:province":"Baden-W\u00fcrttemberg",
    "wof:name":"Knightigale & Knights",
    "wof:placetype":"venue"
},
  "geometry": {"coordinates":[9.795355,48.797001],"type":"Point"}
}