{
  "type": "Feature",
  "properties": {
    "iso:country":"DE",
    "sg:address":"Kiesgrube",
    "sg:city":"Kirchhain",
    "sg:phone":"+49 6422/922000",
    "sg:postcode":"35274",
    "sg:province":"Hessen",
    "wof:name":"Kieswerk Herrmann Verwaltungs Gmbh",
    "wof:placetype":"venue"
},
  "geometry": {"coordinates":[8.92074,50.820984],"type":"Point"}
}