{
  "type": "Feature",
  "properties": {
    "iso:country":"DE",
    "sg:address":"Gartenstr. 5",
    "sg:city":"Schwarzenberg",
    "sg:postcode":"08340",
    "sg:province":"Sachsen",
    "wof:name":"Sani Gmbh",
    "wof:placetype":"venue"
},
  "geometry": {"coordinates":[12.8103103638,50.5070075989],"type":"Point"}
}