{
  "type": "Feature",
  "properties": {
    "iso:country":"DE",
    "sg:address":"Buchbergstr. 1a",
    "sg:city":"Bermatingen",
    "sg:phone":"+49 7544/8094",
    "sg:postcode":"88697",
    "sg:province":"Baden-W\u00fcrttemberg",
    "wof:name":"Konrad Dilger",
    "wof:placetype":"venue"
},
  "geometry": {"coordinates":[9.3524303436,47.7292633057],"type":"Point"}
}