{
  "type": "Feature",
  "properties": {
    "iso:country":"DE",
    "sg:address":"Vorbusch 9",
    "sg:city":"N\u00fcmbrecht",
    "sg:phone":"+49 2293/7673",
    "sg:postcode":"51588",
    "sg:province":"Nordrhein-Westfalen",
    "wof:name":"Ruth Und Waldemar Nessler",
    "wof:placetype":"venue"
},
  "geometry": {"coordinates":[7.5867528915,50.9298973083],"type":"Point"}
}