{
  "type": "Feature",
  "properties": {
    "iso:country":"DE",
    "sg:address":"Hubertusweg 3",
    "sg:city":"Lohne",
    "sg:phone":"+49 4442/1789",
    "sg:postcode":"49393",
    "sg:province":"Niedersachsen",
    "wof:name":"Hermann Krogmann Antiquit\u00e4ten",
    "wof:placetype":"venue"
},
  "geometry": {"coordinates":[8.2596950531,52.6757392883],"type":"Point"}
}