{
  "type": "Feature",
  "properties": {
    "iso:country":"DE",
    "sg:address":"Im K\u00f6bler 1",
    "sg:city":"Knittlingen",
    "sg:phone":"+49 7043/1060",
    "sg:postcode":"75438",
    "sg:province":"Baden-W\u00fcrttemberg",
    "wof:name":"Holzschuh-verwaltungs- Gmbh",
    "wof:placetype":"venue"
},
  "geometry": {"coordinates":[8.816379,49.020912],"type":"Point"}
}