{
  "type": "Feature",
  "properties": {
    "iso:country":"DE",
    "sg:address":"Scheringer Str. 5 a",
    "sg:city":"Pasewalk",
    "sg:postcode":"17309",
    "sg:province":"Mecklenburg-Vorpommern",
    "wof:name":"Dr. Karl-h. Michels",
    "wof:placetype":"venue"
},
  "geometry": {"coordinates":[13.99182,53.496109],"type":"Point"}
}