{
  "type": "Feature",
  "properties": {
    "iso:country":"DE",
    "sg:address":"Neuses 68",
    "sg:city":"Bundorf",
    "sg:phone":"+49 9763/931167",
    "sg:postcode":"97494",
    "sg:province":"Bayern",
    "wof:name":"Theo Lutsch Telekommunikation",
    "wof:placetype":"venue"
},
  "geometry": {"coordinates":[10.5637722015,50.2002410889],"type":"Point"}
}