{
  "type": "Feature",
  "properties": {
    "iso:country":"DE",
    "sg:address":"Schneiderstr. 16 a",
    "sg:city":"Wathlingen",
    "sg:postcode":"29339",
    "sg:province":"Niedersachsen",
    "wof:name":"J. Kell Gmbh",
    "wof:placetype":"venue"
},
  "geometry": {"coordinates":[10.1511278152,52.5377349854],"type":"Point"}
}