{
  "type": "Feature",
  "properties": {
    "iso:country":"DE",
    "sg:address":"Manfredstr. 30",
    "sg:city":"M\u00fcnster",
    "sg:phone":"+49 251/132427",
    "sg:postcode":"48145",
    "sg:province":"Nordrhein-Westfalen",
    "wof:name":"Dr. Med. Nadia N\u00fc\u00dfler",
    "wof:placetype":"venue"
},
  "geometry": {"coordinates":[7.6510090828,51.9666900635],"type":"Point"}
}