{
  "type": "Feature",
  "properties": {
    "iso:country":"DE",
    "sg:address":"Steinerstr. 28",
    "sg:city":"Laupheim",
    "sg:phone":"+49 7392/912025",
    "sg:postcode":"88471",
    "sg:province":"Baden-W\u00fcrttemberg",
    "wof:name":"K. Toleikis",
    "wof:placetype":"venue"
},
  "geometry": {"coordinates":[9.881338,48.233765],"type":"Point"}
}