{
  "type": "Feature",
  "properties": {
    "iso:country":"DE",
    "sg:address":"Hauptstr. 15",
    "sg:city":"Lauf",
    "sg:phone":"+49 7841/3585",
    "sg:postcode":"77886",
    "sg:province":"Baden-W\u00fcrttemberg",
    "wof:name":"Wanderst\u00fcble",
    "wof:placetype":"venue"
},
  "geometry": {"coordinates":[8.1270608902,48.6533050537],"type":"Point"}
}