{
  "type": "Feature",
  "properties": {
    "iso:country":"DE",
    "sg:address":"Charley-Jacob-Str. 7",
    "sg:city":"Goslar",
    "sg:phone":"+49 5321/43913",
    "sg:postcode":"38640",
    "sg:province":"Niedersachsen",
    "wof:name":"Spiel Und Freizeit Breustedt",
    "wof:placetype":"venue"
},
  "geometry": {"coordinates":[10.4304876328,51.9066543579],"type":"Point"}
}