{
  "type": "Feature",
  "properties": {
    "iso:country":"DE",
    "sg:address":"Castroper Str. 52",
    "sg:city":"Dortmund",
    "sg:phone":"+49 231/337655",
    "sg:postcode":"44357",
    "sg:province":"Nordrhein-Westfalen",
    "wof:name":"Marion Wolfsdorff Rechtsanw\u00e4ltin",
    "wof:placetype":"venue"
},
  "geometry": {"coordinates":[7.3632130623,51.5623817444],"type":"Point"}
}