{
  "type": "Feature",
  "properties": {
    "iso:country":"DE",
    "sg:address":"Wilhelm-Spaeth-Str. 5",
    "sg:city":"N\u00fcrnberg",
    "sg:phone":"+49 911/949530",
    "sg:postcode":"90461",
    "sg:province":"Bayern",
    "wof:name":"K\u00f6hler Datentechnik Gmbh",
    "wof:placetype":"venue"
},
  "geometry": {"coordinates":[11.0939369202,49.4423522949],"type":"Point"}
}