{
  "type": "Feature",
  "properties": {
    "iso:country":"DE",
    "sg:address":"Pistoriusstr. 43",
    "sg:city":"Crailsheim",
    "sg:phone":"+49 7951/93900",
    "sg:postcode":"74564",
    "sg:province":"Baden-W\u00fcrttemberg",
    "wof:name":"Alwico Hesterberg Gmbh",
    "wof:placetype":"venue"
},
  "geometry": {"coordinates":[10.071475,49.130165],"type":"Point"}
}