{
  "type": "Feature",
  "properties": {
    "iso:country":"DE",
    "sg:address":"Am Goldanger 9",
    "sg:city":"Hellwege",
    "sg:phone":"+49 4264/9056",
    "sg:postcode":"27367",
    "sg:province":"Niedersachsen",
    "wof:name":"Herbert Tramm",
    "wof:placetype":"venue"
},
  "geometry": {"coordinates":[9.22977,53.072773],"type":"Point"}
}