{
  "type": "Feature",
  "properties": {
    "iso:country":"DE",
    "sg:address":"Truseweg 10",
    "sg:city":"Berlin",
    "sg:phone":"+49 30/6814726",
    "sg:postcode":"12059",
    "sg:province":"Berlin",
    "wof:name":"Annemarie Wagner",
    "wof:placetype":"venue"
},
  "geometry": {"coordinates":[13.447012,52.482368],"type":"Point"}
}