{
  "type": "Feature",
  "properties": {
    "iso:country":"DE",
    "sg:address":"Ungererstra\u00dfe 40",
    "sg:city":"Munich",
    "sg:classifiers":[
        {
            "category":"Professional",
            "subcategory":"Computer Services",
            "type":"Services"
        }
    ],
    "sg:postcode":"80802 ",
    "sg:website":"http://www.adscale.de",
    "wof:name":"AdScale",
    "wof:placetype":"venue"
},
  "geometry": {"coordinates":[11.589037,48.165282],"type":"Point"}
}