{
  "type": "Feature",
  "properties": {
    "iso:country":"DE",
    "sg:address":"Hauptstr. 13",
    "sg:city":"Domnitz",
    "sg:phone":"+49 34603/20985",
    "sg:postcode":"06420",
    "sg:province":"Sachsen-Anhalt",
    "wof:name":"F. Und L. Hammer Gbr",
    "wof:placetype":"venue"
},
  "geometry": {"coordinates":[11.840388298,51.6461410522],"type":"Point"}
}