{
  "type": "Feature",
  "properties": {
    "iso:country":"DE",
    "sg:address":"Bahnhofstr. 111",
    "sg:city":"Kleinblittersdorf",
    "sg:phone":"+49 6805/5572",
    "sg:postcode":"66271",
    "sg:province":"Saarland",
    "wof:name":"Gisela Amthor-h\u00f6rth Garten- Und",
    "wof:placetype":"venue"
},
  "geometry": {"coordinates":[7.053161,49.114738],"type":"Point"}
}