{
  "type": "Feature",
  "properties": {
    "iso:country":"DE",
    "sg:address":"Birkenweg 4",
    "sg:city":"Cottbus",
    "sg:postcode":"03050",
    "sg:province":"Brandenburg",
    "wof:name":"Dr. Med. Alfred Zimmer",
    "wof:placetype":"venue"
},
  "geometry": {"coordinates":[14.344729,51.730091],"type":"Point"}
}