{
  "type": "Feature",
  "properties": {
    "iso:country":"DE",
    "sg:address":"Zum Alten Bauernhof 14",
    "sg:city":"Schwerin",
    "sg:phone":"+49 385/201717",
    "sg:postcode":"19063",
    "sg:province":"Mecklenburg-Vorpommern",
    "wof:name":"U. Noreck",
    "wof:placetype":"venue"
},
  "geometry": {"coordinates":[11.4831762314,53.6013793945],"type":"Point"}
}