{
  "type": "Feature",
  "properties": {
    "iso:country":"DE",
    "sg:address":"Braunfelser Str. 18",
    "sg:city":"Wetzlar",
    "sg:phone":"+49 6441/24189",
    "sg:postcode":"35578",
    "sg:province":"Hessen",
    "wof:name":"Willi Fr\u00f6bel Mech.werkstatt",
    "wof:placetype":"venue"
},
  "geometry": {"coordinates":[8.482754,50.550308],"type":"Point"}
}