{
  "type": "Feature",
  "properties": {
    "iso:country":"DE",
    "sg:address":"Am Graben 5",
    "sg:city":"Auerbach",
    "sg:phone":"+49 3744/213730",
    "sg:postcode":"08209",
    "sg:province":"Sachsen",
    "wof:name":"Christa Z\u00f6bisch",
    "wof:placetype":"venue"
},
  "geometry": {"coordinates":[12.3989467621,50.5082168579],"type":"Point"}
}