{
  "type": "Feature",
  "properties": {
    "iso:country":"DE",
    "sg:address":"Rudower Chaussee 5",
    "sg:city":"Berlin",
    "sg:phone":"+49 30/639222441",
    "sg:postcode":"12489",
    "sg:province":"Berlin",
    "wof:name":"Idms-integrierte Dienste F\u00fcr Management Und Elektronische",
    "wof:placetype":"venue"
},
  "geometry": {"coordinates":[13.536908,52.433025],"type":"Point"}
}