{
  "type": "Feature",
  "properties": {
    "iso:country":"DE",
    "sg:address":"Trebbiner Str.",
    "sg:city":"Mahlow",
    "sg:postcode":"15831",
    "sg:province":"Brandenburg",
    "wof:name":"Extra",
    "wof:placetype":"venue"
},
  "geometry": {"coordinates":[13.4122552872,52.3647689819],"type":"Point"}
}