{
  "type": "Feature",
  "properties": {
    "iso:country":"DE",
    "sg:address":"Alte Kampstr. 3",
    "sg:city":"L\u00f6hne",
    "sg:phone":"+49 5731/8083",
    "sg:postcode":"32584",
    "sg:province":"Nordrhein-Westfalen",
    "wof:name":"Cti-industrieberatungen Cornelia Tychsen",
    "wof:placetype":"venue"
},
  "geometry": {"coordinates":[8.762409,52.203087],"type":"Point"}
}