{
  "type": "Feature",
  "properties": {
    "iso:country":"DE",
    "sg:address":"Weberstr. 22",
    "sg:city":"Herford",
    "sg:phone":"+49 5221/57483",
    "sg:postcode":"32051",
    "sg:province":"Nordrhein-Westfalen",
    "wof:name":"V. Schwabbauer",
    "wof:placetype":"venue"
},
  "geometry": {"coordinates":[8.6543922424,52.1117286682],"type":"Point"}
}