{
  "type": "Feature",
  "properties": {
    "iso:country":"DE",
    "sg:address":"Stra\u00dfe der Freundschaft 9",
    "sg:city":"Zeithain",
    "sg:phone":"+49 35264/97348",
    "sg:postcode":"01619",
    "sg:province":"Sachsen",
    "wof:name":"Beate Gutsche",
    "wof:placetype":"venue"
},
  "geometry": {"coordinates":[13.2551488876,51.3729820251],"type":"Point"}
}