{
  "type": "Feature",
  "properties": {
    "iso:country":"DE",
    "sg:address":"M\u00f6rser Str. 67",
    "sg:city":"Wolfsburg",
    "sg:phone":"+49 4953/62150",
    "sg:postcode":"38442",
    "sg:province":"Niedersachsen",
    "wof:name":"Hansmann Logistik Gmbh & Co.kg",
    "wof:placetype":"venue"
},
  "geometry": {"coordinates":[10.7160100937,52.4184417725],"type":"Point"}
}