{
  "type": "Feature",
  "properties": {
    "iso:country":"DE",
    "sg:address":"Dorfstr. 34",
    "sg:city":"Uetz",
    "sg:phone":"+49 33208/57255",
    "sg:postcode":"14476",
    "sg:province":"Brandenburg",
    "wof:name":"Wild- Und Rinderfarm Uetz Gmbh",
    "wof:placetype":"venue"
},
  "geometry": {"coordinates":[12.9432668686,52.4688682556],"type":"Point"}
}