{
  "type": "Feature",
  "properties": {
    "iso:country":"DE",
    "sg:address":"Blyinghausen 3",
    "sg:city":"Stadthagen",
    "sg:phone":"+49 5721/3617",
    "sg:postcode":"31655",
    "sg:province":"Niedersachsen",
    "wof:name":"Friedrich Hasse",
    "wof:placetype":"venue"
},
  "geometry": {"coordinates":[9.251874,52.317856],"type":"Point"}
}