{
  "type": "Feature",
  "properties": {
    "iso:country":"DE",
    "sg:address":"Gropiusstr. 6",
    "sg:city":"Weimar",
    "sg:phone":"+49 3643/59717",
    "sg:postcode":"99423",
    "sg:province":"Th\u00fcringen",
    "wof:name":"Raiffeisenbank Weimar E. G.",
    "wof:placetype":"venue"
},
  "geometry": {"coordinates":[11.324296,50.978333],"type":"Point"}
}