{
  "type": "Feature",
  "properties": {
    "iso:country":"DE",
    "sg:address":"Humboldtstr. 3",
    "sg:city":"Montabaur",
    "sg:phone":"+49 2602/5606",
    "sg:postcode":"56410",
    "sg:province":"Rheinland-Pfalz",
    "wof:name":"Schulpsychologische Beratungsstelle",
    "wof:placetype":"venue"
},
  "geometry": {"coordinates":[7.818623,50.439693],"type":"Point"}
}