{
  "type": "Feature",
  "properties": {
    "iso:country":"DE",
    "sg:address":"Odenwaldring 102",
    "sg:city":"Offenbach",
    "sg:phone":"+49 69/843266",
    "sg:postcode":"63069",
    "sg:province":"Hessen",
    "wof:name":"Burghardt",
    "wof:placetype":"venue"
},
  "geometry": {"coordinates":[8.7561283112,50.0894126892],"type":"Point"}
}