{
  "type": "Feature",
  "properties": {
    "iso:country":"DE",
    "sg:address":"Josefstr. 51-53",
    "sg:city":"Oberhausen",
    "sg:phone":"+49 208/598004",
    "sg:postcode":"46045",
    "sg:province":"Nordrhein-Westfalen",
    "wof:name":"Sommer",
    "wof:placetype":"venue"
},
  "geometry": {"coordinates":[6.855075,51.469452],"type":"Point"}
}