{
  "type": "Feature",
  "properties": {
    "iso:country":"DE",
    "sg:address":"Lorenz-Scherer-Str. 11",
    "sg:city":"Dachau",
    "sg:phone":"+49 8131/71928",
    "sg:postcode":"85221",
    "sg:province":"Bayern",
    "wof:name":"Werkm\u00fcller Gmbh",
    "wof:placetype":"venue"
},
  "geometry": {"coordinates":[11.444705,48.244511],"type":"Point"}
}