{
  "type": "Feature",
  "properties": {
    "iso:country":"DE",
    "sg:address":"Tenstedter Str 50",
    "sg:city":"Cappeln",
    "sg:phone":"+49 4478/880",
    "sg:postcode":"49692",
    "sg:province":"Niedersachsen",
    "wof:name":"Beckermann K\u00fcchen Gmbh",
    "wof:placetype":"venue"
},
  "geometry": {"coordinates":[8.1204004288,52.8025856018],"type":"Point"}
}