{
  "type": "Feature",
  "properties": {
    "iso:country":"DE",
    "sg:address":"Hauptstr. 13",
    "sg:city":"Egling",
    "sg:phone":"+49 8141/37192",
    "sg:postcode":"86492",
    "sg:province":"Bayern",
    "wof:name":"Roman Kovar",
    "wof:placetype":"venue"
},
  "geometry": {"coordinates":[10.9836549759,48.1885414124],"type":"Point"}
}