{
  "type": "Feature",
  "properties": {
    "iso:country":"DE",
    "sg:address":"Gundekarstr. 10",
    "sg:city":"Altdorf",
    "sg:phone":"+49 9187/5917",
    "sg:postcode":"90518",
    "sg:province":"Bayern",
    "wof:name":"Rudolf Falk",
    "wof:placetype":"venue"
},
  "geometry": {"coordinates":[11.400511,49.377827],"type":"Point"}
}