{
  "type": "Feature",
  "properties": {
    "iso:country":"DE",
    "sg:address":"Stiller Weg 28",
    "sg:city":"Oldenburg",
    "sg:phone":"+49 441/31478",
    "sg:postcode":"26121",
    "sg:province":"Niedersachsen",
    "wof:name":"Nordkap",
    "wof:placetype":"venue"
},
  "geometry": {"coordinates":[8.2232818604,53.1624908447],"type":"Point"}
}