{
  "type": "Feature",
  "properties": {
    "iso:country":"DE",
    "sg:address":"Heidestr. 84",
    "sg:city":"Westoverledingen",
    "sg:phone":"+49 4955/972800",
    "sg:postcode":"26810",
    "sg:province":"Niedersachsen",
    "wof:name":"Wiechers",
    "wof:placetype":"venue"
},
  "geometry": {"coordinates":[7.439789772,53.121509552],"type":"Point"}
}