{
  "type": "Feature",
  "properties": {
    "iso:country":"DE",
    "sg:address":"K\u00e4ferflugstr. 13",
    "sg:city":"Heilbronn",
    "sg:phone":"+49 7131/162642",
    "sg:postcode":"74076",
    "sg:province":"Baden-W\u00fcrttemberg",
    "wof:name":"K\u00e4ferimbi\u00df",
    "wof:placetype":"venue"
},
  "geometry": {"coordinates":[9.224729538,49.1542854309],"type":"Point"}
}