{
  "type": "Feature",
  "properties": {
    "iso:country":"DE",
    "sg:address":"Edisonstr. 2",
    "sg:city":"Lampertheim",
    "sg:phone":"+49 6206/58409",
    "sg:postcode":"68623",
    "sg:province":"Hessen",
    "wof:name":"U. B\u00f6h",
    "wof:placetype":"venue"
},
  "geometry": {"coordinates":[8.48192,49.602203],"type":"Point"}
}