{
  "type": "Feature",
  "properties": {
    "iso:country":"DE",
    "sg:address":"Frauenstr. 3",
    "sg:city":"M\u00fcnster",
    "sg:phone":"+49 251/89503",
    "sg:postcode":"48143",
    "sg:province":"Nordrhein-Westfalen",
    "wof:name":"Christliche Initiative Romero E. V.",
    "wof:placetype":"venue"
},
  "geometry": {"coordinates":[7.6215691566,51.9636878967],"type":"Point"}
}