{
  "type": "Feature",
  "properties": {
    "iso:country":"DE",
    "sg:address":"Bahnhofstr. 26",
    "sg:city":"Northeim",
    "sg:phone":"+49 5551/911770",
    "sg:postcode":"37154",
    "sg:province":"Niedersachsen",
    "wof:name":"Sozialberatungsstelle Kreis-caritasverband",
    "wof:placetype":"venue"
},
  "geometry": {"coordinates":[9.993239,51.705204],"type":"Point"}
}