{
  "type": "Feature",
  "properties": {
    "iso:country":"DE",
    "sg:address":"lr Klr. 2",
    "sg:city":"47190M00941 767 365eriseurgewerbe",
    "sg:postcode":"525",
    "wof:name":"1re-\u00fc3",
    "wof:placetype":"venue"
},
  "geometry": {"coordinates":[-59.9538612366,-24.6677494049],"type":"Point"}
}