{
  "type": "Feature",
  "properties": {
    "iso:country":"DE",
    "sg:address":"Neust\u00e4dter Str. 5",
    "sg:city":"Fritzlar",
    "sg:phone":"+49 5622/3300",
    "sg:postcode":"34560",
    "sg:province":"Hessen",
    "wof:name":"F. Kuyken",
    "wof:placetype":"venue"
},
  "geometry": {"coordinates":[9.2753896713,51.1314163208],"type":"Point"}
}