{
  "type": "Feature",
  "properties": {
    "iso:country":"DE",
    "sg:address":"Mathildenstr 20-22",
    "sg:city":"Kiel",
    "sg:phone":"+49 431/335146",
    "sg:postcode":"24148",
    "sg:province":"Schleswig-Holstein",
    "wof:name":"Fenster Complett Vertriebs Gmbh",
    "wof:placetype":"venue"
},
  "geometry": {"coordinates":[10.166566,54.323555],"type":"Point"}
}