{
  "type": "Feature",
  "properties": {
    "iso:country":"DE",
    "sg:address":"Schwaibach",
    "sg:city":"Bad Birnbach",
    "sg:phone":"+49 8563/96080",
    "sg:postcode":"84364",
    "sg:province":"Bayern",
    "wof:name":"Schwaibacher Hof",
    "wof:placetype":"venue"
},
  "geometry": {"coordinates":[13.0630998611,48.435459137],"type":"Point"}
}