{
  "type": "Feature",
  "properties": {
    "iso:country":"DE",
    "sg:address":"Bahnhofstr. 34",
    "sg:city":"Hagen",
    "sg:phone":"+49 2331/14873",
    "sg:postcode":"58095",
    "sg:province":"Nordrhein-Westfalen",
    "wof:name":"H. Jarzyna",
    "wof:placetype":"venue"
},
  "geometry": {"coordinates":[7.465019,51.360901],"type":"Point"}
}