{
  "type": "Feature",
  "properties": {
    "iso:country":"DE",
    "sg:address":"Langener Str. 90 B",
    "sg:city":"M\u00f6rfelden-Walldorf",
    "sg:phone":"+49 6105/278473",
    "sg:postcode":"64546",
    "sg:province":"Hessen",
    "wof:name":"Ris Gmbh Systemberatung U. Organisation",
    "wof:placetype":"venue"
},
  "geometry": {"coordinates":[8.5768070221,49.9779586792],"type":"Point"}
}