{
  "type": "Feature",
  "properties": {
    "iso:country":"DE",
    "sg:address":"Peter-Stahs-Str. 37",
    "sg:city":"J\u00fcchen",
    "sg:phone":"+49 2181/248106",
    "sg:postcode":"41363",
    "sg:province":"Nordrhein-Westfalen",
    "wof:name":"Ingo Hamecher Rechtsanwalt",
    "wof:placetype":"venue"
},
  "geometry": {"coordinates":[6.5646090508,51.1211776733],"type":"Point"}
}