{
  "type": "Feature",
  "properties": {
    "iso:country":"DE",
    "sg:address":"R\u00e4berweg 12",
    "sg:city":"Unterl\u00fc\u00df",
    "sg:phone":"+49 5827/5011",
    "sg:postcode":"29345",
    "sg:province":"Niedersachsen",
    "wof:name":"Vereinigte Kieselgurwerke Gmbh & Co. Kg",
    "wof:placetype":"venue"
},
  "geometry": {"coordinates":[10.3000812531,52.8364028931],"type":"Point"}
}