{
  "type": "Feature",
  "properties": {
    "iso:country":"DE",
    "sg:address":"Bloecherhalde 20",
    "sg:city":"Altensteig-Garrweiler",
    "sg:phone":"+49 7453/94700",
    "sg:postcode":"72213",
    "sg:province":"Baden-W\u00fcrttemberg",
    "wof:name":"Fritz Schlecht Gmbh Objekteinrichtungen",
    "wof:placetype":"venue"
},
  "geometry": {"coordinates":[8.5581970215,48.5779495239],"type":"Point"}
}