{
  "type": "Feature",
  "properties": {
    "iso:country":"DE",
    "sg:address":"Herderstr. 94",
    "sg:city":"K\u00f6ln",
    "sg:postcode":"51147",
    "sg:province":"Nordrhein-Westfalen",
    "wof:name":"T. H. B. Technische Hausbetreuung Gmbh",
    "wof:placetype":"venue"
},
  "geometry": {"coordinates":[7.099036,50.871189],"type":"Point"}
}