{
  "type": "Feature",
  "properties": {
    "iso:country":"DE",
    "sg:address":"Fritz-M\u00fcller-Str 107",
    "sg:city":"Esslingen",
    "sg:phone":"+49 711/3154780",
    "sg:postcode":"73730",
    "sg:province":"Baden-W\u00fcrttemberg",
    "wof:name":"Blp Software Gmbh",
    "wof:placetype":"venue"
},
  "geometry": {"coordinates":[9.343018,48.725468],"type":"Point"}
}