{
  "type": "Feature",
  "properties": {
    "iso:country":"DE",
    "sg:address":"Warendorfer Str. 155",
    "sg:city":"M\u00fcnster",
    "sg:postcode":"48145",
    "sg:province":"Nordrhein-Westfalen",
    "wof:name":"Wadebo Gesellschaft Zur F\u00fcr Investitionsg\u00fcter Mbh",
    "wof:placetype":"venue"
},
  "geometry": {"coordinates":[7.653177,51.966118],"type":"Point"}
}