{
  "type": "Feature",
  "properties": {
    "iso:country":"DE",
    "sg:address":"Richtweg 21",
    "sg:city":"Langwedel",
    "sg:phone":"+49 4235/779",
    "sg:postcode":"27299",
    "sg:province":"Niedersachsen",
    "wof:name":"H.-j. Otto",
    "wof:placetype":"venue"
},
  "geometry": {"coordinates":[9.1357479095,52.9922523499],"type":"Point"}
}