{
  "type": "Feature",
  "properties": {
    "iso:country":"DE",
    "sg:address":"Gabelsbergerstr. 2",
    "sg:city":"Dortmund",
    "sg:phone":"+49 231/2868600",
    "sg:postcode":"44141",
    "sg:province":"Nordrhein-Westfalen",
    "wof:name":"Landesjagdverband Nordrhein-westfalen E. V.",
    "wof:placetype":"venue"
},
  "geometry": {"coordinates":[7.5145821571,51.5045051575],"type":"Point"}
}