{
  "type": "Feature",
  "properties": {
    "iso:country":"DE",
    "sg:address":"Luhdorfer Str. 67",
    "sg:city":"Winsen",
    "sg:phone":"+49 4171/781136",
    "sg:postcode":"21423",
    "sg:province":"Niedersachsen",
    "wof:name":"Avia-tankstelle",
    "wof:placetype":"venue"
},
  "geometry": {"coordinates":[10.2070131302,53.3481369019],"type":"Point"}
}