{
  "type": "Feature",
  "properties": {
    "iso:country":"DE",
    "sg:address":"Hasenpfuhlstr. 7",
    "sg:city":"Speyer",
    "sg:phone":"+49 6232/75657",
    "sg:postcode":"67346",
    "sg:province":"Rheinland-Pfalz",
    "wof:name":"Klaus Herklotz Architekt",
    "wof:placetype":"venue"
},
  "geometry": {"coordinates":[8.439109,49.319736],"type":"Point"}
}