{
  "type": "Feature",
  "properties": {
    "iso:country":"DE",
    "sg:address":"Rosenstr. 1",
    "sg:city":"Kornwestheim",
    "sg:phone":"+49 7154/4649",
    "sg:postcode":"70806",
    "sg:province":"Baden-W\u00fcrttemberg",
    "wof:name":"Reinhold Peer",
    "wof:placetype":"venue"
},
  "geometry": {"coordinates":[9.188897,48.860477],"type":"Point"}
}