{
  "type": "Feature",
  "properties": {
    "iso:country":"DE",
    "sg:address":"Landhausstr. 6",
    "sg:city":"Stuttgart",
    "sg:phone":"+49 711/291907",
    "sg:postcode":"70182",
    "sg:province":"Baden-W\u00fcrttemberg",
    "wof:name":"Cemil Urcun Dolmetscher",
    "wof:placetype":"venue"
},
  "geometry": {"coordinates":[9.189093,48.782764],"type":"Point"}
}