{
  "type": "Feature",
  "properties": {
    "iso:country":"DE",
    "sg:address":"Rebg\u00e4rten 60 A",
    "sg:city":"Frankfurt",
    "sg:phone":"+49 69/521829",
    "sg:postcode":"60431",
    "sg:province":"Hessen",
    "wof:name":"Goldenberg Art Dekorativ Interieur & Accessoires",
    "wof:placetype":"venue"
},
  "geometry": {"coordinates":[8.6525125504,50.1387023926],"type":"Point"}
}