{
  "type": "Feature",
  "properties": {
    "iso:country":"DE",
    "sg:address":"Zum Berge 14",
    "sg:city":"Freudenberg",
    "sg:phone":"+49 2734/2948",
    "sg:postcode":"57258",
    "sg:province":"Nordrhein-Westfalen",
    "wof:name":"Erhard Hosfeld",
    "wof:placetype":"venue"
},
  "geometry": {"coordinates":[7.908894062,50.8935241699],"type":"Point"}
}