{
  "type": "Feature",
  "properties": {
    "iso:country":"DE",
    "sg:address":"Ludwigplatz 12",
    "sg:city":"Plattling",
    "sg:phone":"+49 9931/72300",
    "sg:postcode":"94447",
    "sg:province":"Bayern",
    "wof:name":"Deutsche Woolworth Gmbh & Co. Ohg",
    "wof:placetype":"venue"
},
  "geometry": {"coordinates":[12.87532,48.775551],"type":"Point"}
}