{
  "type": "Feature",
  "properties": {
    "iso:country":"DE",
    "sg:address":"Neersener Str. 32",
    "sg:city":"Kaarst",
    "sg:phone":"+49 2131/88000",
    "sg:postcode":"41564",
    "sg:province":"Nordrhein-Westfalen",
    "wof:name":"Carl Bernh. Hoffmann Gmbh",
    "wof:placetype":"venue"
},
  "geometry": {"coordinates":[6.604473114,51.2240371704],"type":"Point"}
}