{
  "type": "Feature",
  "properties": {
    "iso:country":"DE",
    "sg:address":"Gewerbestr. 1 A",
    "sg:city":"Freudenberg",
    "sg:postcode":"57258",
    "sg:province":"Nordrhein-Westfalen",
    "wof:name":"Wieds Ecochem Ag",
    "wof:placetype":"venue"
},
  "geometry": {"coordinates":[7.913824,50.911762],"type":"Point"}
}