{
  "type": "Feature",
  "properties": {
    "iso:country":"DE",
    "sg:address":"Kirchf\u00e4hrendorfer Str. 3",
    "sg:city":"Bad D\u00fcrrenberg",
    "sg:phone":"+49 3462/87470",
    "sg:postcode":"06231",
    "sg:province":"Sachsen-Anhalt",
    "wof:name":"Hans-norbert Mertens Architekt",
    "wof:placetype":"venue"
},
  "geometry": {"coordinates":[12.05731,51.293312],"type":"Point"}
}