{
  "type": "Feature",
  "properties": {
    "iso:country":"DE",
    "sg:address":"Sch\u00f6nhauser Allee 147 a",
    "sg:city":"Berlin",
    "sg:phone":"+49 30/4401270",
    "sg:postcode":"10435",
    "sg:province":"Berlin",
    "wof:name":"Berlinevent-medienservice M. Sievert Kg",
    "wof:placetype":"venue"
},
  "geometry": {"coordinates":[13.4117841721,52.5397872925],"type":"Point"}
}