{
  "type": "Feature",
  "properties": {
    "iso:country":"DE",
    "sg:address":"Ehrensteinstr. 44",
    "sg:city":"Leipzig",
    "sg:phone":"+49 341/5906102",
    "sg:postcode":"04105",
    "sg:province":"Sachsen",
    "wof:name":"Horst Schladitz",
    "wof:placetype":"venue"
},
  "geometry": {"coordinates":[12.375375,51.358337],"type":"Point"}
}