{
  "type": "Feature",
  "properties": {
    "iso:country":"DE",
    "sg:address":"Osnabr\u00fccker Str. 553",
    "sg:city":"B\u00fcnde",
    "sg:phone":"+49 5226/2141",
    "sg:postcode":"32257",
    "sg:province":"Nordrhein-Westfalen",
    "wof:name":"Monokel",
    "wof:placetype":"venue"
},
  "geometry": {"coordinates":[8.4821195602,52.1967964172],"type":"Point"}
}