{
  "type": "Feature",
  "properties": {
    "iso:country":"DE",
    "sg:address":"Osserstr. 34",
    "sg:city":"Lam",
    "sg:phone":"+49 9943/518",
    "sg:postcode":"93462",
    "sg:province":"Bayern",
    "wof:name":"Pension Josef Liebl",
    "wof:placetype":"venue"
},
  "geometry": {"coordinates":[13.0663223267,49.1997795105],"type":"Point"}
}