{
  "type": "Feature",
  "properties": {
    "iso:country":"DE",
    "sg:address":"Haeckelstr. 12a",
    "sg:city":"Heidenau",
    "sg:phone":"+49 3529/515587",
    "sg:postcode":"01809",
    "sg:province":"Sachsen",
    "wof:name":"J. Kreisel",
    "wof:placetype":"venue"
},
  "geometry": {"coordinates":[13.8701028824,50.9766807556],"type":"Point"}
}