{
  "type": "Feature",
  "properties": {
    "iso:country":"DE",
    "sg:address":"W\u00fclfingstr. 23a",
    "sg:city":"Wuppertal",
    "sg:phone":"+49 202/447606",
    "sg:postcode":"42107",
    "sg:province":"Nordrhein-Westfalen",
    "wof:name":"Friseur Schnittpunkt",
    "wof:placetype":"venue"
},
  "geometry": {"coordinates":[7.148353,51.260227],"type":"Point"}
}