{
  "type": "Feature",
  "properties": {
    "iso:country":"DE",
    "sg:address":"Ascherothstr. 58",
    "sg:city":"Hagen",
    "sg:phone":"+49 2331/54343",
    "sg:postcode":"58093",
    "sg:province":"Nordrhein-Westfalen",
    "wof:name":"L. Gro\u00dfer",
    "wof:placetype":"venue"
},
  "geometry": {"coordinates":[7.5035018921,51.3555870056],"type":"Point"}
}