{
  "type": "Feature",
  "properties": {
    "iso:country":"DE",
    "sg:address":"Wilhelm-Busch-Weg 1",
    "sg:city":"Bremen",
    "sg:phone":"+49 421/471915",
    "sg:postcode":"28329",
    "sg:province":"Bremen",
    "wof:name":"J. H. Hirschberg Architekt",
    "wof:placetype":"venue"
},
  "geometry": {"coordinates":[8.907001,53.071785],"type":"Point"}
}