{
  "type": "Feature",
  "properties": {
    "iso:country":"DE",
    "sg:address":"Holzstr. 28",
    "sg:city":"Viernheim",
    "sg:phone":"+49 6204/2392",
    "sg:postcode":"68519",
    "sg:province":"Hessen",
    "wof:name":"Horst Tubach Ingenieur",
    "wof:placetype":"venue"
},
  "geometry": {"coordinates":[8.5757923126,49.5332527161],"type":"Point"}
}