{
  "type": "Feature",
  "properties": {
    "iso:country":"DE",
    "sg:address":"Hollefeldstr. 34",
    "sg:city":"Emsdetten",
    "sg:phone":"+49 2572/93640",
    "sg:postcode":"48282",
    "sg:province":"Nordrhein-Westfalen",
    "wof:name":"Nordenia Deutschland Emsdetten Gmbh",
    "wof:placetype":"venue"
},
  "geometry": {"coordinates":[7.5618991852,52.1530914307],"type":"Point"}
}