{
  "type": "Feature",
  "properties": {
    "iso:country":"DE",
    "sg:address":"Nieskyer Str. 100",
    "sg:city":"G\u00f6rlitz",
    "sg:phone":"+49 3581/316543",
    "sg:postcode":"02828",
    "sg:province":"Sachsen",
    "wof:name":"Reiseb\u00fcro Martin",
    "wof:placetype":"venue"
},
  "geometry": {"coordinates":[14.9697237015,51.1683197021],"type":"Point"}
}