{
  "type": "Feature",
  "properties": {
    "iso:country":"DE",
    "sg:address":"Stra\u00dfe der Befreiung 2",
    "sg:city":"Bad Salzungen",
    "sg:postcode":"36433",
    "sg:province":"Th\u00fcringen",
    "wof:name":"Gem Wohnungsbau Gmbh",
    "wof:placetype":"venue"
},
  "geometry": {"coordinates":[10.231955,50.811886],"type":"Point"}
}