{
  "type": "Feature",
  "properties": {
    "iso:country":"DE",
    "sg:address":"Thorwaldsenanlage 66a",
    "sg:city":"Wiesbaden",
    "sg:phone":"+49 611/523719",
    "sg:postcode":"65195",
    "sg:province":"Hessen",
    "wof:name":"Erwin Bopp",
    "wof:placetype":"venue"
},
  "geometry": {"coordinates":[8.2195253372,50.0947341919],"type":"Point"}
}