{
  "type": "Feature",
  "properties": {
    "iso:country":"DE",
    "sg:address":"Weinberghof",
    "sg:city":"Waldsolms",
    "sg:phone":"+49 6085/3566",
    "sg:postcode":"35647",
    "sg:province":"Hessen",
    "wof:name":"Petschull Gesellschaft F\u00fcr Hunde-verhaltenstraining Mbh",
    "wof:placetype":"venue"
},
  "geometry": {"coordinates":[8.462435,50.4538],"type":"Point"}
}