{
  "type": "Feature",
  "properties": {
    "iso:country":"DE",
    "sg:address":"Osnabr\u00fccker Str. 1",
    "sg:city":"Rahden",
    "sg:phone":"+49 5771/968380",
    "sg:postcode":"32369",
    "sg:province":"Nordrhein-Westfalen",
    "wof:name":"Restaurant Leonardo",
    "wof:placetype":"venue"
},
  "geometry": {"coordinates":[8.6105709076,52.4319953918],"type":"Point"}
}