{
  "type": "Feature",
  "properties": {
    "iso:country":"DE",
    "sg:address":"Zeil 111",
    "sg:city":"Frankfurt",
    "sg:postcode":"60313",
    "sg:province":"Hessen",
    "wof:name":"Heliwert Helmut Limberg",
    "wof:placetype":"venue"
},
  "geometry": {"coordinates":[8.680992,50.113956],"type":"Point"}
}