{
  "type": "Feature",
  "properties": {
    "iso:country":"DE",
    "sg:address":"Am Bahnhof St. Magnus 2a",
    "sg:city":"Bremen",
    "sg:phone":"+49 421/621145",
    "sg:postcode":"28759",
    "sg:province":"Bremen",
    "wof:name":"Liek Ut Bremer Bo\u00dfelclub Von 1975 E. V.",
    "wof:placetype":"venue"
},
  "geometry": {"coordinates":[8.6695261002,53.1743659973],"type":"Point"}
}