{
  "type": "Feature",
  "properties": {
    "iso:country":"DE",
    "sg:address":"Hasensprung 6 b",
    "sg:city":"Menden",
    "sg:phone":"+49 2373/81035",
    "sg:postcode":"58710",
    "sg:province":"Nordrhein-Westfalen",
    "wof:name":"Hubert Bettermann Verm\u00f6gens- Verwaltungs-gmbh & Co. Kg",
    "wof:placetype":"venue"
},
  "geometry": {"coordinates":[7.8171658516,51.4043121338],"type":"Point"}
}