{
  "type": "Feature",
  "properties": {
    "iso:country":"DE",
    "sg:address":"Sch\u00fctzenbr\u00fccke 3",
    "sg:city":"Quedlinburg",
    "sg:phone":"+49 3946/3679",
    "sg:postcode":"06484",
    "sg:province":"Sachsen-Anhalt",
    "wof:name":"Heinrich Meyerding",
    "wof:placetype":"venue"
},
  "geometry": {"coordinates":[11.152776,51.795643],"type":"Point"}
}