{
  "type": "Feature",
  "properties": {
    "iso:country":"DE",
    "sg:address":"Ostdeutsche Str. 13",
    "sg:city":"Alzey",
    "sg:phone":"+49 6731/2818",
    "sg:postcode":"55232",
    "sg:province":"Rheinland-Pfalz",
    "wof:name":"Wichard Bolle Notar",
    "wof:placetype":"venue"
},
  "geometry": {"coordinates":[8.116232872,49.747631073],"type":"Point"}
}