{
  "type": "Feature",
  "properties": {
    "iso:country":"DE",
    "sg:address":"Stolbergerstra\u00dfe 33",
    "sg:city":"Wiesbaden",
    "sg:phone":"+49 6122/2689",
    "sg:postcode":"65205",
    "sg:province":"Hessen",
    "wof:name":"A. Heidmann & Saal Gmbh Sicherheitssysteme",
    "wof:placetype":"venue"
},
  "geometry": {"coordinates":[8.344063,50.063335],"type":"Point"}
}