{
  "type": "Feature",
  "properties": {
    "iso:country":"DE",
    "sg:address":"Heinrichstr. 14 c",
    "sg:city":"Osnabr\u00fcck",
    "sg:postcode":"49080",
    "sg:province":"Niedersachsen",
    "wof:name":"Objektges. Kleine Domsfreiheit Verwaltungs Gmbh",
    "wof:placetype":"venue"
},
  "geometry": {"coordinates":[8.0434713364,52.2677955627],"type":"Point"}
}