{
  "type": "Feature",
  "properties": {
    "iso:country":"DE",
    "sg:address":"Schulenburger Landstr. 58",
    "sg:city":"Hannover",
    "sg:phone":"+49 511/3521133",
    "sg:postcode":"30165",
    "sg:province":"Niedersachsen",
    "wof:name":"Hans-joachim Langhans",
    "wof:placetype":"venue"
},
  "geometry": {"coordinates":[9.71386,52.399574],"type":"Point"}
}