{
  "type": "Feature",
  "properties": {
    "iso:country":"DE",
    "sg:address":"Filsstr. 2",
    "sg:city":"Kuchen",
    "sg:phone":"+49 7331/81286",
    "sg:postcode":"73329",
    "sg:province":"Baden-W\u00fcrttemberg",
    "wof:name":"Kath. Pfarramt Zum Hl. Kreuz",
    "wof:placetype":"venue"
},
  "geometry": {"coordinates":[9.7976665497,48.6428031921],"type":"Point"}
}