{
  "type": "Feature",
  "properties": {
    "iso:country":"DE",
    "sg:address":"Eschach",
    "sg:city":"Aichstetten",
    "sg:phone":"+49 7565/1595",
    "sg:postcode":"88317",
    "sg:province":"Baden-W\u00fcrttemberg",
    "wof:name":"Alfred Schneider",
    "wof:placetype":"venue"
},
  "geometry": {"coordinates":[10.047643,47.894833],"type":"Point"}
}