{
  "type": "Feature",
  "properties": {
    "iso:country":"DE",
    "sg:address":"Leonberger Ring 22",
    "sg:city":"Berlin",
    "sg:postcode":"12349",
    "sg:province":"Berlin",
    "wof:name":"Form Be Ohg",
    "wof:placetype":"venue"
},
  "geometry": {"coordinates":[13.43229,52.425571],"type":"Point"}
}