{
  "type": "Feature",
  "properties": {
    "iso:country":"DE",
    "sg:address":"Bochumer Str. 15",
    "sg:city":"Sprockh\u00f6vel",
    "sg:phone":"+49 2324/90916",
    "sg:postcode":"45549",
    "sg:province":"Nordrhein-Westfalen",
    "wof:name":"Sparkasse Sprockh\u00f6vel",
    "wof:placetype":"venue"
},
  "geometry": {"coordinates":[7.251049,51.371487],"type":"Point"}
}