{
  "type": "Feature",
  "properties": {
    "iso:country":"DE",
    "sg:address":"Ortrander Str. 4",
    "sg:city":"Hirschfeld",
    "sg:phone":"+49 35343/60940",
    "sg:postcode":"04932",
    "sg:province":"Brandenburg",
    "wof:name":"Henry Thieme",
    "wof:placetype":"venue"
},
  "geometry": {"coordinates":[13.619688,51.38599],"type":"Point"}
}