{
  "type": "Feature",
  "properties": {
    "iso:country":"DE",
    "sg:address":"An den Buhnen 4",
    "sg:city":"Rostock",
    "sg:phone":"+49 381/7699449",
    "sg:postcode":"18119",
    "sg:province":"Mecklenburg-Vorpommern",
    "wof:name":"J\u00f6rg D\u00fccker Finanzberater",
    "wof:placetype":"venue"
},
  "geometry": {"coordinates":[12.0383472443,54.1667556763],"type":"Point"}
}