{
  "type": "Feature",
  "properties": {
    "iso:country":"DE",
    "sg:address":"W\u00fcrthstr. 14",
    "sg:city":"Duisburg",
    "sg:phone":"+49 4967/183300",
    "sg:postcode":"47053",
    "sg:province":"Nordrhein-Westfalen",
    "wof:name":"Thomas Graf Von Zedlitz Und Tr\u00dctzschler Gmbh",
    "wof:placetype":"venue"
},
  "geometry": {"coordinates":[7.860799,49.839664],"type":"Point"}
}