{
  "type": "Feature",
  "properties": {
    "iso:country":"DE",
    "sg:address":"Ludwigstr. 6",
    "sg:city":"F\u00fcrstenfeldbruck",
    "sg:phone":"+49 8141/327750",
    "sg:postcode":"82256",
    "sg:province":"Bayern",
    "wof:name":"Neuhierl Und Gierke Rechtsanw\u00e4lte",
    "wof:placetype":"venue"
},
  "geometry": {"coordinates":[11.2508220673,48.1777076721],"type":"Point"}
}