{
  "type": "Feature",
  "properties": {
    "iso:country":"DE",
    "sg:address":"R\u00f6hrigstr. 11",
    "sg:city":"Hamburg",
    "sg:phone":"+49 40/85150230",
    "sg:postcode":"22763",
    "sg:province":"Hamburg",
    "wof:name":"Neustadt Architekten",
    "wof:placetype":"venue"
},
  "geometry": {"coordinates":[9.915969,53.55603],"type":"Point"}
}