{
  "type": "Feature",
  "properties": {
    "iso:country":"DE",
    "sg:address":"Lauenbr\u00fcck",
    "sg:city":"Lauenbr\u00fcck",
    "sg:phone":"+49 4267/323",
    "sg:postcode":"27389",
    "sg:province":"Niedersachsen",
    "wof:name":"Sparkasse Schee\u00dfel",
    "wof:placetype":"venue"
},
  "geometry": {"coordinates":[9.553042,53.200619],"type":"Point"}
}