{
  "type": "Feature",
  "properties": {
    "iso:country":"DE",
    "sg:address":"Amtsstr. 47",
    "sg:city":"Wolfsburg",
    "sg:phone":"+49 5363/7915",
    "sg:postcode":"38448",
    "sg:province":"Niedersachsen",
    "wof:name":"Reisecenter Alltours",
    "wof:placetype":"venue"
},
  "geometry": {"coordinates":[10.8361282349,52.4407043457],"type":"Point"}
}