{
  "type": "Feature",
  "properties": {
    "iso:country":"DE",
    "sg:address":"Kies\u00e4cker 2",
    "sg:city":"Schw\u00e4bisch Gm\u00fcnd",
    "sg:phone":"+49 7171/62448",
    "sg:postcode":"73527",
    "sg:province":"Baden-W\u00fcrttemberg",
    "wof:name":"Vierjahreszeiten",
    "wof:placetype":"venue"
},
  "geometry": {"coordinates":[9.8130750656,48.8033370972],"type":"Point"}
}