{
  "type": "Feature",
  "properties": {
    "iso:country":"DE",
    "sg:address":"Ostring 20",
    "sg:city":"Bochum",
    "sg:phone":"+49 234/67629",
    "sg:postcode":"44787",
    "sg:province":"Nordrhein-Westfalen",
    "wof:name":"Euroteam Gym Inh. Parusel",
    "wof:placetype":"venue"
},
  "geometry": {"coordinates":[7.2245979309,51.4825248718],"type":"Point"}
}