{
  "type": "Feature",
  "properties": {
    "iso:country":"DE",
    "sg:address":"Gro\u00dfes Osterfeld 22a",
    "sg:city":"Hameln",
    "sg:phone":"+49 5151/51727",
    "sg:postcode":"31787",
    "sg:province":"Niedersachsen",
    "wof:name":"Feierabendst\u00fcbchen",
    "wof:placetype":"venue"
},
  "geometry": {"coordinates":[9.3803863525,52.1061859131],"type":"Point"}
}