{
  "type": "Feature",
  "properties": {
    "iso:country":"DE",
    "sg:address":"Otto-Hahn-Str 21",
    "sg:city":"Dachau",
    "sg:phone":"+49 8131/51730",
    "sg:postcode":"85221",
    "sg:province":"Bayern",
    "wof:name":"Ek Design Ag",
    "wof:placetype":"venue"
},
  "geometry": {"coordinates":[11.470406,48.273048],"type":"Point"}
}