{
  "type": "Feature",
  "properties": {
    "iso:country":"DE",
    "sg:address":"Luisenstr. 42",
    "sg:city":"Mannheim",
    "sg:phone":"+49 621/851233",
    "sg:postcode":"68199",
    "sg:province":"Baden-W\u00fcrttemberg",
    "wof:name":"Vogler",
    "wof:placetype":"venue"
},
  "geometry": {"coordinates":[8.4881086349,49.4552955627],"type":"Point"}
}