{
  "type": "Feature",
  "properties": {
    "iso:country":"DE",
    "sg:address":"Schifferstr. 2",
    "sg:city":"Neu Wulmstorf",
    "sg:postcode":"21629",
    "sg:province":"Niedersachsen",
    "wof:name":"Vitalex-apotheke Alexandra Gorn-papenfu\u00df E. K.",
    "wof:placetype":"venue"
},
  "geometry": {"coordinates":[9.80048,53.464638],"type":"Point"}
}