{
  "type": "Feature",
  "properties": {
    "iso:country":"DE",
    "sg:address":"Franz-Alexander-Str.",
    "sg:city":"Burghausen",
    "sg:phone":"+49 8677/2041",
    "sg:postcode":"84489",
    "sg:province":"Bayern",
    "wof:name":"Hallenbad",
    "wof:placetype":"venue"
},
  "geometry": {"coordinates":[12.8353652954,48.1769561768],"type":"Point"}
}