{
  "type": "Feature",
  "properties": {
    "iso:country":"DE",
    "sg:address":"Lisztstr. 31",
    "sg:city":"Bopfingen",
    "sg:phone":"+49 7362/7850",
    "sg:postcode":"73441",
    "sg:province":"Baden-W\u00fcrttemberg",
    "wof:name":"Eberhard L\u00f6cklin",
    "wof:placetype":"venue"
},
  "geometry": {"coordinates":[10.3661556244,48.8606452942],"type":"Point"}
}