{
  "type": "Feature",
  "properties": {
    "iso:country":"DE",
    "sg:address":"Coburger Str. 19",
    "sg:city":"Neustadt",
    "sg:phone":"+49 9568/2565",
    "sg:postcode":"96465",
    "sg:province":"Bayern",
    "wof:name":"K. Fleischmann",
    "wof:placetype":"venue"
},
  "geometry": {"coordinates":[11.1207952499,50.3286247253],"type":"Point"}
}