{
  "type": "Feature",
  "properties": {
    "iso:country":"DE",
    "sg:address":"Bahnhofstr. 41",
    "sg:city":"Wegberg",
    "sg:postcode":"41844",
    "sg:province":"Nordrhein-Westfalen",
    "wof:name":"Dienst-ma Gmbh",
    "wof:placetype":"venue"
},
  "geometry": {"coordinates":[6.278401,51.142742],"type":"Point"}
}