{
  "type": "Feature",
  "properties": {
    "iso:country":"DE",
    "sg:address":"Agnesstr. 13",
    "sg:city":"Schleiz",
    "sg:phone":"+49 3663/402631",
    "sg:postcode":"07907",
    "sg:province":"Th\u00fcringen",
    "wof:name":"Karl-heinz Luckner",
    "wof:placetype":"venue"
},
  "geometry": {"coordinates":[11.8073205948,50.5781936646],"type":"Point"}
}