{
  "type": "Feature",
  "properties": {
    "iso:country":"DE",
    "sg:address":"Br\u00fcsseler Str. 171",
    "sg:city":"K\u00f6ln",
    "sg:phone":"+49 2203/33333",
    "sg:postcode":"51149",
    "sg:province":"Nordrhein-Westfalen",
    "wof:name":"K\u00e4sekiste",
    "wof:placetype":"venue"
},
  "geometry": {"coordinates":[7.0617399216,50.8959312439],"type":"Point"}
}