{
  "type": "Feature",
  "properties": {
    "iso:country":"DE",
    "sg:address":"M\u00fchlweg 2",
    "sg:city":"Arnstadt",
    "sg:phone":"+49 3628/79763",
    "sg:postcode":"99310",
    "sg:province":"Th\u00fcringen",
    "wof:name":"Kr\u00f6ning Oberfl\u00e4chentechnik Gmbh",
    "wof:placetype":"venue"
},
  "geometry": {"coordinates":[10.958293,50.847168],"type":"Point"}
}