{
  "type": "Feature",
  "properties": {
    "iso:country":"DE",
    "sg:address":"Friedrich-Humbert-Str. 141",
    "sg:city":"Bremen",
    "sg:phone":"+49 421/623070",
    "sg:postcode":"28759",
    "sg:province":"Bremen",
    "wof:name":"W.-d. Scheeper Rechtsanwalt",
    "wof:placetype":"venue"
},
  "geometry": {"coordinates":[8.6330862045,53.1672172546],"type":"Point"}
}