{
  "type": "Feature",
  "properties": {
    "iso:country":"DE",
    "sg:address":"M\u00fchlenstr. 9",
    "sg:city":"Uelzen",
    "sg:phone":"+49 581/30920",
    "sg:postcode":"29525",
    "sg:province":"Niedersachsen",
    "wof:name":"Kaisers Tengelmann Ag",
    "wof:placetype":"venue"
},
  "geometry": {"coordinates":[10.5631923676,52.9640235901],"type":"Point"}
}