{
  "type": "Feature",
  "properties": {
    "iso:country":"DE",
    "sg:address":"Kirchbachstr. 93",
    "sg:city":"Bremen",
    "sg:postcode":"28211",
    "sg:province":"Bremen",
    "wof:name":"Dr. Sigmund Rostowski Tierarzt",
    "wof:placetype":"venue"
},
  "geometry": {"coordinates":[8.8551301956,53.0780830383],"type":"Point"}
}