{
  "type": "Feature",
  "properties": {
    "iso:country":"DE",
    "sg:address":"M\u00fchlg\u00e4\u00dfle 17",
    "sg:city":"Wain",
    "sg:postcode":"88489",
    "sg:province":"Baden-W\u00fcrttemberg",
    "wof:name":"Hurdy Gurdy Maker - Drehleierbau - Helmut Gotschy",
    "wof:placetype":"venue"
},
  "geometry": {"coordinates":[10.018423,48.193218],"type":"Point"}
}