{
  "type": "Feature",
  "properties": {
    "iso:country":"DE",
    "sg:address":"Kirchplatz 16",
    "sg:city":"Bedburg",
    "sg:phone":"+49 2272/6016",
    "sg:postcode":"50181",
    "sg:province":"Nordrhein-Westfalen",
    "wof:name":"Kath. Pfarrb\u00fccherei K\u00f6nigshoven",
    "wof:placetype":"venue"
},
  "geometry": {"coordinates":[6.55837,51.010059],"type":"Point"}
}