{
  "type": "Feature",
  "properties": {
    "iso:country":"DE",
    "sg:address":"Carl-Petersen-Str. 58",
    "sg:city":"Hamburg",
    "sg:phone":"+49 40/25495533",
    "sg:postcode":"20535",
    "sg:province":"Hamburg",
    "wof:name":"Dtp Das Team F\u00fcr Ambulante Pflege Gmbh",
    "wof:placetype":"venue"
},
  "geometry": {"coordinates":[10.045813,53.558262],"type":"Point"}
}