{
  "type": "Feature",
  "properties": {
    "iso:country":"DE",
    "sg:address":"Hanauer Str. 38",
    "sg:city":"Nidderau",
    "sg:phone":"+49 6187/901533",
    "sg:postcode":"61130",
    "sg:province":"Hessen",
    "wof:name":"H.-j. Gomeier",
    "wof:placetype":"venue"
},
  "geometry": {"coordinates":[8.90719,50.216572],"type":"Point"}
}