{
  "type": "Feature",
  "properties": {
    "iso:country":"DE",
    "sg:address":"Bgm.-R\u00e4dler-Stra\u00dfe",
    "sg:city":"Petershausen",
    "sg:phone":"+49 8137/5882",
    "sg:postcode":"85238",
    "sg:province":"Bayern",
    "wof:name":"Gemeinde Petershausen",
    "wof:placetype":"venue"
},
  "geometry": {"coordinates":[11.4724521637,48.4119720459],"type":"Point"}
}