{
  "type": "Feature",
  "properties": {
    "iso:country":"DE",
    "sg:address":"Nistertalstr. 3",
    "sg:city":"Dreisbach",
    "sg:phone":"+49 2661/20101",
    "sg:postcode":"56472",
    "sg:province":"Rheinland-Pfalz",
    "wof:name":"Sabine Cermann-hanewinkel",
    "wof:placetype":"venue"
},
  "geometry": {"coordinates":[7.9302310944,50.6172637939],"type":"Point"}
}