{
  "type": "Feature",
  "properties": {
    "iso:country":"DE",
    "sg:address":"Hergenstadt",
    "sg:city":"Adelsheim",
    "sg:phone":"+49 6291/7053",
    "sg:postcode":"74740",
    "sg:province":"Baden-W\u00fcrttemberg",
    "wof:name":"Edeltraud Karsten",
    "wof:placetype":"venue"
},
  "geometry": {"coordinates":[9.4006347656,49.3996658325],"type":"Point"}
}