{
  "type": "Feature",
  "properties": {
    "iso:country":"DE",
    "sg:address":"Alleeweg 2",
    "sg:city":"Gosda",
    "sg:phone":"+49 35694/316",
    "sg:postcode":"03149",
    "sg:province":"Brandenburg",
    "wof:name":"Kegelbahn",
    "wof:placetype":"venue"
},
  "geometry": {"coordinates":[14.5416717529,51.7460823059],"type":"Point"}
}