{
  "type": "Feature",
  "properties": {
    "iso:country":"DE",
    "sg:address":"Schaphusstr. 9",
    "sg:city":"Dortmund",
    "sg:phone":"+49 231/333191",
    "sg:postcode":"44359",
    "sg:province":"Nordrhein-Westfalen",
    "wof:name":"Aral Ag",
    "wof:placetype":"venue"
},
  "geometry": {"coordinates":[7.3868441582,51.5736885071],"type":"Point"}
}