{
  "type": "Feature",
  "properties": {
    "iso:country":"DE",
    "sg:address":"Dellwiger Weg 10",
    "sg:city":"Iserlohn",
    "sg:phone":"+49 2378/2205",
    "sg:postcode":"58640",
    "sg:province":"Nordrhein-Westfalen",
    "wof:name":"Campingplatz Kampmeier",
    "wof:placetype":"venue"
},
  "geometry": {"coordinates":[7.679018,51.465588],"type":"Point"}
}