{
  "type": "Feature",
  "properties": {
    "iso:country":"DE",
    "sg:address":"Nu\u00dfbacherstr. 34",
    "sg:city":"Triberg",
    "sg:phone":"+49 4977/2296990",
    "sg:postcode":"78098",
    "sg:province":"Baden-W\u00fcrttemberg",
    "wof:name":"Arnold Dold Gmbh & Co.kg",
    "wof:placetype":"venue"
},
  "geometry": {"coordinates":[8.244809,48.136089],"type":"Point"}
}