{
  "type": "Feature",
  "properties": {
    "iso:country":"DE",
    "sg:address":"Lohbredde 2",
    "sg:city":"Werl",
    "sg:phone":"+49 2922/5322",
    "sg:postcode":"59457",
    "sg:province":"Nordrhein-Westfalen",
    "wof:name":"Stuckmann Gmbh",
    "wof:placetype":"venue"
},
  "geometry": {"coordinates":[7.858979,51.549767],"type":"Point"}
}