{
  "type": "Feature",
  "properties": {
    "iso:country":"DE",
    "sg:address":"Melchiorstr. 20-22",
    "sg:city":"Berlin",
    "sg:postcode":"10179",
    "sg:province":"Berlin",
    "wof:name":"Rohrnetzbetriebsstelle",
    "wof:placetype":"venue"
},
  "geometry": {"coordinates":[13.4218473434,52.5074195862],"type":"Point"}
}