{
  "type": "Feature",
  "properties": {
    "iso:country":"DE",
    "sg:address":"D\u00fcrener Stra\u00dfe 589a",
    "sg:city":"Eschweiler",
    "sg:phone":"+49 2403",
    "sg:postcode":"52249",
    "sg:province":"Nordrhein-Westfalen",
    "wof:name":"Uwe M\u00fcller Gmbh",
    "wof:placetype":"venue"
},
  "geometry": {"coordinates":[6.3044881821,50.8228492737],"type":"Point"}
}