{
  "type": "Feature",
  "properties": {
    "iso:country":"DE",
    "sg:address":"Franz-Haniel-Platz 1",
    "sg:city":"Duisburg",
    "sg:phone":"+49 203/8060",
    "sg:postcode":"47119",
    "sg:province":"Nordrhein-Westfalen",
    "wof:name":"Haniel Schiffahrt Gmbh",
    "wof:placetype":"venue"
},
  "geometry": {"coordinates":[6.733285,51.451462],"type":"Point"}
}