{
  "type": "Feature",
  "properties": {
    "iso:country":"DE",
    "sg:address":"Alte Dorfstr. 28",
    "sg:city":"Tolk",
    "sg:postcode":"24894",
    "sg:province":"Schleswig-Holstein",
    "wof:name":"Haus Fallen-anker",
    "wof:placetype":"venue"
},
  "geometry": {"coordinates":[9.6355876923,54.580493927],"type":"Point"}
}