{
  "type": "Feature",
  "properties": {
    "iso:country":"DE",
    "sg:address":"An der Wei\u00dfe 50",
    "sg:city":"Arnstadt",
    "sg:phone":"+49 3628/723080",
    "sg:postcode":"99310",
    "sg:province":"Th\u00fcringen",
    "wof:name":"Marlis Hirche",
    "wof:placetype":"venue"
},
  "geometry": {"coordinates":[10.94687,50.835545],"type":"Point"}
}