{
  "type": "Feature",
  "properties": {
    "iso:country":"DE",
    "sg:address":"Kurt-Moosdorf-Str. 32",
    "sg:city":"Bad Vilbel",
    "sg:phone":"+49 6101/85030",
    "sg:postcode":"61118",
    "sg:province":"Hessen",
    "wof:name":"Ev. Pfarramt Bad Vilbel S\u00fcd",
    "wof:placetype":"venue"
},
  "geometry": {"coordinates":[8.7299976349,50.1745948792],"type":"Point"}
}