{
  "type": "Feature",
  "properties": {
    "iso:country":"DE",
    "sg:address":"Nikolaus-Mommer-Str. 3",
    "sg:city":"Trier",
    "sg:phone":"+49 651/307070",
    "sg:postcode":"54296",
    "sg:province":"Rheinland-Pfalz",
    "wof:name":"Wolfgang Cartus",
    "wof:placetype":"venue"
},
  "geometry": {"coordinates":[6.6949868202,49.7379951477],"type":"Point"}
}