{
  "type": "Feature",
  "properties": {
    "iso:country":"DE",
    "sg:address":"Wellweg 47",
    "sg:city":"Sarstedt",
    "sg:phone":"+49 5066/692664",
    "sg:postcode":"31157",
    "sg:province":"Niedersachsen",
    "wof:name":"Ring Deutscher Baubetriebe Impatex Cortin",
    "wof:placetype":"venue"
},
  "geometry": {"coordinates":[9.861448,52.241982],"type":"Point"}
}