{
  "type": "Feature",
  "properties": {
    "iso:country":"DE",
    "sg:address":"Ringstr. 3",
    "sg:city":"Memmelsdorf",
    "sg:phone":"+49 951/43036",
    "sg:postcode":"96117",
    "sg:province":"Bayern",
    "wof:name":"Ckis Klaus Knappe Informations-systeme",
    "wof:placetype":"venue"
},
  "geometry": {"coordinates":[10.9604253769,49.9287452698],"type":"Point"}
}