{
  "type": "Feature",
  "properties": {
    "iso:country":"DE",
    "sg:address":"S\u00fcdhag 1",
    "sg:city":"Dahme",
    "sg:phone":"+49 35451/343",
    "sg:postcode":"15936",
    "sg:province":"Brandenburg",
    "wof:name":"W. Kaszynski",
    "wof:placetype":"venue"
},
  "geometry": {"coordinates":[13.428651,51.868465],"type":"Point"}
}