{
  "type": "Feature",
  "properties": {
    "iso:country":"DE",
    "sg:address":"Im Kirchfeld 6",
    "sg:city":"Klais",
    "sg:phone":"+49 8823/8173",
    "sg:postcode":"82493",
    "sg:province":"Bayern",
    "wof:name":"Pension Martha Koppe",
    "wof:placetype":"venue"
},
  "geometry": {"coordinates":[11.2393484116,47.481262207],"type":"Point"}
}