{
  "type": "Feature",
  "properties": {
    "iso:country":"DE",
    "sg:address":"Weststr. 1",
    "sg:city":"Dresden",
    "sg:phone":"+49 351/4210519",
    "sg:postcode":"01157",
    "sg:province":"Sachsen",
    "wof:name":"Henning Schulz",
    "wof:placetype":"venue"
},
  "geometry": {"coordinates":[13.665432,51.060326],"type":"Point"}
}