{
  "type": "Feature",
  "properties": {
    "iso:country":"DE",
    "sg:address":"Marktplatz 11",
    "sg:city":"Pf\u00f6rring",
    "sg:phone":"+49 8403/278",
    "sg:postcode":"85104",
    "sg:province":"Bayern",
    "wof:name":"Gastst\u00e4tte Karl Seidl",
    "wof:placetype":"venue"
},
  "geometry": {"coordinates":[11.6894083023,48.8082466125],"type":"Point"}
}