{
  "type": "Feature",
  "properties": {
    "iso:country":"DE",
    "sg:address":"Merowingerstr. 170",
    "sg:city":"D\u00fcsseldorf",
    "sg:phone":"+49 211/331784",
    "sg:postcode":"40225",
    "sg:province":"Nordrhein-Westfalen",
    "wof:name":"Katholisches Pfarramt St. Ludgerus",
    "wof:placetype":"venue"
},
  "geometry": {"coordinates":[6.7782459259,51.1967201233],"type":"Point"}
}