{
  "type": "Feature",
  "properties": {
    "iso:country":"DE",
    "sg:address":"Angelburger Str. 22",
    "sg:city":"Flensburg",
    "sg:phone":"+49 461/144950",
    "sg:postcode":"24937",
    "sg:province":"Schleswig-Holstein",
    "wof:name":"Knaack Und Partner Jochen Jens Und Helga Knaack",
    "wof:placetype":"venue"
},
  "geometry": {"coordinates":[9.4385566711,54.7825508118],"type":"Point"}
}