{
  "type": "Feature",
  "properties": {
    "iso:country":"DE",
    "sg:address":"M\u00fchlenweg 41",
    "sg:city":"Ratzeburg",
    "sg:phone":"+49 4541/2421",
    "sg:postcode":"23909",
    "sg:province":"Schleswig-Holstein",
    "wof:name":"Bernd-michael Noelle Masseur",
    "wof:placetype":"venue"
},
  "geometry": {"coordinates":[10.801111,53.699257],"type":"Point"}
}