{
  "type": "Feature",
  "properties": {
    "iso:country":"DE",
    "sg:address":"Ackerstr. 36",
    "sg:city":"Herford",
    "sg:phone":"+49 5221/981710",
    "sg:postcode":"32051",
    "sg:province":"Nordrhein-Westfalen",
    "wof:name":"Ravensberger Sack-planen Fabrik Fr. Wilhelm Brockfeld",
    "wof:placetype":"venue"
},
  "geometry": {"coordinates":[8.653178215,52.1301574707],"type":"Point"}
}