{
  "type": "Feature",
  "properties": {
    "iso:country":"DE",
    "sg:address":"Kirchstr. 14",
    "sg:city":"Essen",
    "sg:phone":"+49 5434/2000",
    "sg:postcode":"49632",
    "sg:province":"Niedersachsen",
    "wof:name":"H. Fiebak",
    "wof:placetype":"venue"
},
  "geometry": {"coordinates":[7.114311,51.414104],"type":"Point"}
}