{
  "type": "Feature",
  "properties": {
    "iso:country":"DE",
    "sg:address":"Bahnhofstr. 28",
    "sg:city":"Senftenberg",
    "sg:phone":"+49 3573/37590",
    "sg:postcode":"01968",
    "sg:province":"Brandenburg",
    "wof:name":"Schafeld Und Partner Rechtsanwalt",
    "wof:placetype":"venue"
},
  "geometry": {"coordinates":[14.0042238235,51.5220680237],"type":"Point"}
}