{
  "type": "Feature",
  "properties": {
    "iso:country":"DE",
    "sg:address":"Vordergasse 35",
    "sg:city":"Rodgau",
    "sg:phone":"+49 6106/3583",
    "sg:postcode":"63110",
    "sg:province":"Hessen",
    "wof:name":"Differenz",
    "wof:placetype":"venue"
},
  "geometry": {"coordinates":[8.8829545975,50.0262527466],"type":"Point"}
}