{
  "type": "Feature",
  "properties": {
    "iso:country":"DE",
    "sg:address":"Theresia-von-W\u00fcllenweber-Str.",
    "sg:city":"Kerpen",
    "sg:phone":"+49 2273/4881",
    "sg:postcode":"50169",
    "sg:province":"Nordrhein-Westfalen",
    "wof:name":"G\u00fcnter Noris Arrangeur",
    "wof:placetype":"venue"
},
  "geometry": {"coordinates":[6.722799778,50.9131736755],"type":"Point"}
}