{
  "type": "Feature",
  "properties": {
    "iso:country":"DE",
    "sg:address":"H\u00f6lderlinstr. 5",
    "sg:city":"Kolbingen",
    "sg:phone":"+49 7463/1588",
    "sg:postcode":"78600",
    "sg:province":"Baden-W\u00fcrttemberg",
    "wof:name":"Ludwig Amann",
    "wof:placetype":"venue"
},
  "geometry": {"coordinates":[8.890136,48.051788],"type":"Point"}
}