{
  "type": "Feature",
  "properties": {
    "iso:country":"DE",
    "sg:address":"Laurentiusstr. 10",
    "sg:city":"Marsberg",
    "sg:phone":"+49 2994/750",
    "sg:postcode":"34431",
    "sg:province":"Nordrhein-Westfalen",
    "wof:name":"Katholisches Pfarramt St. Laurentius",
    "wof:placetype":"venue"
},
  "geometry": {"coordinates":[8.8642044067,51.5144195557],"type":"Point"}
}