{
  "type": "Feature",
  "properties": {
    "iso:country":"DE",
    "sg:address":"Bahnhofstr. 9",
    "sg:city":"Putbus",
    "sg:phone":"+49 38301/278",
    "sg:postcode":"18581",
    "sg:province":"Mecklenburg-Vorpommern",
    "wof:name":"Bahnhofsgastst\u00e4tte Am Rasenden Roland",
    "wof:placetype":"venue"
},
  "geometry": {"coordinates":[13.479809761,54.3543243408],"type":"Point"}
}