{
  "type": "Feature",
  "properties": {
    "iso:country":"DE",
    "sg:address":"Wilmersdorfer Str. 59",
    "sg:city":"Berlin",
    "sg:phone":"+49 30/3236032",
    "sg:postcode":"10627",
    "sg:province":"Berlin",
    "wof:name":"Ruhnke Optik",
    "wof:placetype":"venue"
},
  "geometry": {"coordinates":[13.3062076569,52.5074310303],"type":"Point"}
}