{
  "type": "Feature",
  "properties": {
    "iso:country":"DE",
    "sg:address":"Bahnhofsallee 24",
    "sg:city":"Coesfeld",
    "sg:phone":"+49 2546/250",
    "sg:postcode":"48653",
    "sg:province":"Nordrhein-Westfalen",
    "wof:name":"Alois Stegemann",
    "wof:placetype":"venue"
},
  "geometry": {"coordinates":[7.1883,51.89341],"type":"Point"}
}