{
  "type": "Feature",
  "properties": {
    "iso:country":"DE",
    "sg:address":"R\u00f6blingstr. 144-146",
    "sg:city":"Berlin",
    "sg:postcode":"12105",
    "sg:province":"Berlin",
    "wof:name":"Gebr. Becker T\u00fcren Und Tore Gmbh",
    "wof:placetype":"venue"
},
  "geometry": {"coordinates":[13.364466,52.450306],"type":"Point"}
}