{
  "type": "Feature",
  "properties": {
    "iso:country":"DE",
    "sg:address":"Ellerstadter Str.99",
    "sg:city":"Ludwigshafen",
    "sg:phone":"+49 6237/59370",
    "sg:postcode":"67071",
    "sg:province":"Rheinland-Pfalz",
    "wof:name":"Herbalife Bestell - Shop",
    "wof:placetype":"venue"
},
  "geometry": {"coordinates":[8.3314647675,49.4704704285],"type":"Point"}
}