{
  "type": "Feature",
  "properties": {
    "iso:country":"DE",
    "sg:address":"Sulzbachgasse 18",
    "sg:city":"Stuttgart",
    "sg:phone":"+49 711/551156",
    "sg:postcode":"70372",
    "sg:province":"Baden-W\u00fcrttemberg",
    "wof:name":"Rappen",
    "wof:placetype":"venue"
},
  "geometry": {"coordinates":[9.2157411575,48.8049545288],"type":"Point"}
}