{
  "type": "Feature",
  "properties": {
    "iso:country":"DE",
    "sg:address":"Brauerstr. 52",
    "sg:city":"Kellinghusen",
    "sg:phone":"+49 4822/8506",
    "sg:postcode":"25548",
    "sg:province":"Schleswig-Holstein",
    "wof:name":"Hauschild Gmbh",
    "wof:placetype":"venue"
},
  "geometry": {"coordinates":[9.728952,53.952087],"type":"Point"}
}