{
  "type": "Feature",
  "properties": {
    "iso:country":"DE",
    "sg:address":"Reinhardtstr. 29 c",
    "sg:city":"Berlin",
    "sg:postcode":"10117",
    "sg:province":"Berlin",
    "wof:name":"Cut For You Gmbh",
    "wof:placetype":"venue"
},
  "geometry": {"coordinates":[13.381769,52.522804],"type":"Point"}
}