{
  "type": "Feature",
  "properties": {
    "iso:country":"DE",
    "sg:address":"Kobachstr. 13",
    "sg:city":"Idar-Oberstein",
    "sg:phone":"+49 6781/44880",
    "sg:postcode":"55743",
    "sg:province":"Rheinland-Pfalz",
    "wof:name":"Carmen Stauch",
    "wof:placetype":"venue"
},
  "geometry": {"coordinates":[7.302731,49.720222],"type":"Point"}
}