{
  "type": "Feature",
  "properties": {
    "iso:country":"DE",
    "sg:address":"Ottensener Str. 125",
    "sg:city":"Hamburg",
    "sg:postcode":"22525",
    "sg:province":"Hamburg",
    "wof:name":"D\u00f6rner-hansa Gmbh",
    "wof:placetype":"venue"
},
  "geometry": {"coordinates":[9.907474,53.588463],"type":"Point"}
}