{
  "type": "Feature",
  "properties": {
    "iso:country":"DE",
    "sg:address":"Am Mittelkamp",
    "sg:city":"Brodersby",
    "sg:postcode":"24398",
    "sg:province":"Schleswig-Holstein",
    "wof:name":"Aparthotel Am Schlo\u00dfpark",
    "wof:placetype":"venue"
},
  "geometry": {"coordinates":[10.0227174759,54.6284828186],"type":"Point"}
}