{
  "type": "Feature",
  "properties": {
    "iso:country":"DE",
    "sg:address":"Lerchenstr. 15",
    "sg:city":"Eichendorf",
    "sg:phone":"+49 9952/905045",
    "sg:postcode":"94428",
    "sg:province":"Bayern",
    "wof:name":"S-h-f- Kanalabdichtungs Gmbh",
    "wof:placetype":"venue"
},
  "geometry": {"coordinates":[12.852848,48.629299],"type":"Point"}
}