{
  "type": "Feature",
  "properties": {
    "iso:country":"DE",
    "sg:address":"Rohrdorferstr. 133 PF 100353",
    "sg:city":"Rosenheim",
    "sg:phone":"+49 8031/7000",
    "sg:postcode":"83003",
    "sg:province":"Bayern",
    "wof:name":"Hamberger Industriewerke Gmbh",
    "wof:placetype":"venue"
},
  "geometry": {"coordinates":[12.1240196228,47.8560791016],"type":"Point"}
}