{
  "type": "Feature",
  "properties": {
    "iso:country":"DE",
    "sg:address":"Hans-Urmiller-Ring 12a",
    "sg:city":"Wolfratshausen",
    "sg:phone":"+49 8171/43540",
    "sg:postcode":"82515",
    "sg:province":"Bayern",
    "wof:name":"Schwarz Extrusionswerkzeuge Gmbh",
    "wof:placetype":"venue"
},
  "geometry": {"coordinates":[11.426076,47.906773],"type":"Point"}
}