{
  "type": "Feature",
  "properties": {
    "iso:country":"DE",
    "sg:address":"Edelstrut 3",
    "sg:city":"Adelmannsfelden",
    "sg:phone":"+49 7963/90300",
    "sg:postcode":"73486",
    "sg:province":"Baden-W\u00fcrttemberg",
    "wof:name":"Betec Gmbh Umform - Schweisstechnik",
    "wof:placetype":"venue"
},
  "geometry": {"coordinates":[9.9968,48.951912],"type":"Point"}
}