{
  "type": "Feature",
  "properties": {
    "iso:country":"DE",
    "sg:address":"Industriestr. 9",
    "sg:city":"Heusenstamm",
    "sg:phone":"+49 6104/65733",
    "sg:postcode":"63150",
    "sg:province":"Hessen",
    "wof:name":"Down Town Textil- Handels Gmbh",
    "wof:placetype":"venue"
},
  "geometry": {"coordinates":[8.798457,50.048428],"type":"Point"}
}