{
  "type": "Feature",
  "properties": {
    "iso:country":"DE",
    "sg:address":"Adlzreiterstr. 1",
    "sg:city":"M\u00fcnchen",
    "sg:phone":"+49 89/7255427",
    "sg:postcode":"80337",
    "sg:province":"Bayern",
    "wof:name":"Marijas",
    "wof:placetype":"venue"
},
  "geometry": {"coordinates":[11.556178093,48.1276855469],"type":"Point"}
}