{
  "type": "Feature",
  "properties": {
    "iso:country":"DE",
    "sg:address":"Burgstr.6",
    "sg:city":"Westerstede",
    "sg:phone":"+49 4944/8883840",
    "sg:postcode":"26655",
    "sg:province":"Niedersachsen",
    "wof:name":"Detlef Coldewey Gmbh",
    "wof:placetype":"venue"
},
  "geometry": {"coordinates":[7.92719,53.25853],"type":"Point"}
}