{
  "type": "Feature",
  "properties": {
    "iso:country":"DE",
    "sg:address":"M\u00fcnchner Str. 55",
    "sg:city":"Rodgau",
    "sg:phone":"+49 6106/886927",
    "sg:postcode":"63110",
    "sg:province":"Hessen",
    "wof:name":"Maison Praline Warenvertriebs Gmbh",
    "wof:placetype":"venue"
},
  "geometry": {"coordinates":[8.8599767685,50.0022163391],"type":"Point"}
}