{
  "type": "Feature",
  "properties": {
    "iso:country":"DE",
    "sg:address":"Hamburger Chaussee 10",
    "sg:city":"Kiel",
    "sg:phone":"+49 431/664890",
    "sg:postcode":"24114",
    "sg:province":"Schleswig-Holstein",
    "wof:name":"Regionalbahn Schleswig- Holstein Gmbh",
    "wof:placetype":"venue"
},
  "geometry": {"coordinates":[10.1234140396,54.3073120117],"type":"Point"}
}