{
  "type": "Feature",
  "properties": {
    "iso:country":"DE",
    "sg:address":"Heinrich-Fries-Str. 103",
    "sg:city":"Oedheim",
    "sg:phone":"+49 7136/22271",
    "sg:postcode":"74229",
    "sg:province":"Baden-W\u00fcrttemberg",
    "wof:name":"Ck-verwaltungs-gmbh",
    "wof:placetype":"venue"
},
  "geometry": {"coordinates":[9.2510614395,49.2342643738],"type":"Point"}
}