{
  "type": "Feature",
  "properties": {
    "iso:country":"DE",
    "sg:address":"G\u00fcterweg 122 g",
    "sg:city":"Crottendorf",
    "sg:phone":"+49 37344/7390",
    "sg:postcode":"09474",
    "sg:province":"Sachsen",
    "wof:name":"Landgasthof-pension Am Park",
    "wof:placetype":"venue"
},
  "geometry": {"coordinates":[12.9340896606,50.5083084106],"type":"Point"}
}