{
  "type": "Feature",
  "properties": {
    "iso:country":"DE",
    "sg:address":"L\u00e4rchenweg 31",
    "sg:city":"Nassenfels",
    "sg:phone":"+49 8424/715",
    "sg:postcode":"85128",
    "sg:province":"Bayern",
    "wof:name":"L. Und R. Klingenberg",
    "wof:placetype":"venue"
},
  "geometry": {"coordinates":[11.2180070877,48.8025665283],"type":"Point"}
}