{
  "type": "Feature",
  "properties": {
    "iso:country":"DE",
    "sg:address":"Gro\u00dfer Ring 32",
    "sg:city":"Heist",
    "sg:phone":"+49 4122/81589",
    "sg:postcode":"25492",
    "sg:province":"Schleswig-Holstein",
    "wof:name":"Elsbeth Hackert",
    "wof:placetype":"venue"
},
  "geometry": {"coordinates":[9.6519050598,53.6534004211],"type":"Point"}
}