{
  "type": "Feature",
  "properties": {
    "iso:country":"DE",
    "sg:address":"Schlo\u00dfstr. 7",
    "sg:city":"Blaufelden",
    "sg:phone":"+49 7958/363",
    "sg:postcode":"74572",
    "sg:province":"Baden-W\u00fcrttemberg",
    "wof:name":"M. Hemer Fensterbau Gmbh",
    "wof:placetype":"venue"
},
  "geometry": {"coordinates":[10.091756,49.313755],"type":"Point"}
}