{
  "type": "Feature",
  "properties": {
    "iso:country":"DE",
    "sg:address":"An den Ziegelh\u00fctten 23 b",
    "sg:city":"Saarbr\u00fccken",
    "sg:postcode":"66127",
    "sg:province":"Saarland",
    "wof:name":"Bauunternehmung Brechtel Gmbh",
    "wof:placetype":"venue"
},
  "geometry": {"coordinates":[6.903863,49.228416],"type":"Point"}
}