{
  "type": "Feature",
  "properties": {
    "iso:country":"DE",
    "sg:address":"Suhler Str. 23",
    "sg:city":"Schmalkalden",
    "sg:phone":"+49 3683/601016",
    "sg:postcode":"98574",
    "sg:province":"Th\u00fcringen",
    "wof:name":"M\u00f6llers",
    "wof:placetype":"venue"
},
  "geometry": {"coordinates":[10.474265,50.713501],"type":"Point"}
}