{
  "type": "Feature",
  "properties": {
    "iso:country":"DE",
    "sg:address":"Norderreihe 6a",
    "sg:city":"Borkum",
    "sg:phone":"+49 4922/1753",
    "sg:postcode":"26757",
    "sg:province":"Niedersachsen",
    "wof:name":"Ommo Akkermann",
    "wof:placetype":"venue"
},
  "geometry": {"coordinates":[6.665201,53.588829],"type":"Point"}
}