{
  "type": "Feature",
  "properties": {
    "iso:country":"DE",
    "sg:address":"Marktler Str. 1a",
    "sg:city":"Burghausen",
    "sg:phone":"+49 8677/911330",
    "sg:postcode":"84489",
    "sg:province":"Bayern",
    "wof:name":"Cr & P Technik F\u00fcr Elektro- Fahrzeuge Vertriebs Gmbh",
    "wof:placetype":"venue"
},
  "geometry": {"coordinates":[12.8321676254,48.1673164368],"type":"Point"}
}