{
  "type": "Feature",
  "properties": {
    "iso:country":"DE",
    "sg:address":"Gro\u00dfg\u00f6rschenstr. 35",
    "sg:city":"Berlin",
    "sg:phone":"+49 30/21755010",
    "sg:postcode":"10827",
    "sg:province":"Berlin",
    "wof:name":"Hornat Inh. Klaus-peter Hornat",
    "wof:placetype":"venue"
},
  "geometry": {"coordinates":[13.3639373779,52.4915733337],"type":"Point"}
}