{
  "type": "Feature",
  "properties": {
    "iso:country":"DE",
    "sg:address":"An den Teichwiesen 1",
    "sg:city":"Goslar",
    "sg:phone":"+49 5325/2610",
    "sg:postcode":"38644",
    "sg:province":"Niedersachsen",
    "wof:name":"Hermann Schwarze",
    "wof:placetype":"venue"
},
  "geometry": {"coordinates":[10.3410100937,51.860080719],"type":"Point"}
}