{
  "type": "Feature",
  "properties": {
    "iso:country":"DE",
    "sg:address":"Hauptstr. 39",
    "sg:city":"Dettenheim",
    "sg:phone":"+49 7247/6279",
    "sg:postcode":"76706",
    "sg:province":"Baden-W\u00fcrttemberg",
    "wof:name":"Ochsen",
    "wof:placetype":"venue"
},
  "geometry": {"coordinates":[8.4160518646,49.161075592],"type":"Point"}
}