{
  "type": "Feature",
  "properties": {
    "iso:country":"DE",
    "sg:address":"Dr.-Danzebrink-Str. 16b",
    "sg:city":"Fulda",
    "sg:phone":"+49 661/51507",
    "sg:postcode":"36039",
    "sg:province":"Hessen",
    "wof:name":"Gad Gmbh",
    "wof:placetype":"venue"
},
  "geometry": {"coordinates":[9.6622409821,50.5665512085],"type":"Point"}
}