{
  "type": "Feature",
  "properties": {
    "iso:country":"DE",
    "sg:address":"Kirchstr. 18",
    "sg:city":"Wintersheim",
    "sg:phone":"+49 6733/7783",
    "sg:postcode":"67587",
    "sg:province":"Rheinland-Pfalz",
    "wof:name":"Klaus Weidmann",
    "wof:placetype":"venue"
},
  "geometry": {"coordinates":[8.279694,49.776821],"type":"Point"}
}