{
  "type": "Feature",
  "properties": {
    "iso:country":"DE",
    "sg:address":"Bellingsen",
    "sg:city":"Arnsberg",
    "sg:phone":"+49 2932/97230",
    "sg:postcode":"59757",
    "sg:province":"Nordrhein-Westfalen",
    "wof:name":"Wildwald Vosswinkel",
    "wof:placetype":"venue"
},
  "geometry": {"coordinates":[7.877820015,51.4615898132],"type":"Point"}
}