{
  "type": "Feature",
  "properties": {
    "iso:country":"DE",
    "sg:address":"Daimlerstr. 15",
    "sg:city":"Weinheim",
    "sg:phone":"+49 6201/64084",
    "sg:postcode":"69469",
    "sg:province":"Baden-W\u00fcrttemberg",
    "wof:name":"Auto Pawelak Gmbh",
    "wof:placetype":"venue"
},
  "geometry": {"coordinates":[8.623175621,49.546749115],"type":"Point"}
}