{
  "type": "Feature",
  "properties": {
    "iso:country":"DE",
    "sg:address":"Im Karrensteigle 8",
    "sg:city":"H\u00fclben",
    "sg:phone":"+49 7125/5356",
    "sg:postcode":"72584",
    "sg:province":"Baden-W\u00fcrttemberg",
    "wof:name":"S. K\u00e4chele",
    "wof:placetype":"venue"
},
  "geometry": {"coordinates":[9.4107,48.522259],"type":"Point"}
}