{
  "type": "Feature",
  "properties": {
    "iso:country":"DE",
    "sg:address":"Arnold-von-Podewils-Str. 28",
    "sg:city":"Uhingen",
    "sg:phone":"+49 7161/352799",
    "sg:postcode":"73066",
    "sg:province":"Baden-W\u00fcrttemberg",
    "wof:name":"E. Kramer",
    "wof:placetype":"venue"
},
  "geometry": {"coordinates":[9.5791311264,48.6999931335],"type":"Point"}
}