{
  "type": "Feature",
  "properties": {
    "iso:country":"DE",
    "sg:address":"Bergstr. 6",
    "sg:city":"Falkenfels",
    "sg:phone":"+49 9961/6392",
    "sg:postcode":"94350",
    "sg:province":"Bayern",
    "wof:name":"Maria Moro",
    "wof:placetype":"venue"
},
  "geometry": {"coordinates":[12.5923843384,49.0050621033],"type":"Point"}
}