{
  "type": "Feature",
  "properties": {
    "iso:country":"DE",
    "sg:address":"Essigkammweg 8",
    "sg:city":"Heppenheim",
    "sg:postcode":"64646",
    "sg:province":"Hessen",
    "wof:name":"Compi Tence Gmbh",
    "wof:placetype":"venue"
},
  "geometry": {"coordinates":[8.647971,49.637676],"type":"Point"}
}