{
  "type": "Feature",
  "properties": {
    "iso:country":"DE",
    "sg:address":"Berlinallee 1 d",
    "sg:city":"Hockenheim",
    "sg:phone":"+49 6205/8303",
    "sg:postcode":"68766",
    "sg:province":"Baden-W\u00fcrttemberg",
    "wof:name":"Roland Reineck Architekt",
    "wof:placetype":"venue"
},
  "geometry": {"coordinates":[8.545032,49.325478],"type":"Point"}
}