{
  "type": "Feature",
  "properties": {
    "iso:country":"DE",
    "sg:address":"Schillerstr. 94",
    "sg:city":"Berlin",
    "sg:phone":"+49 30/3157120",
    "sg:postcode":"10625",
    "sg:province":"Berlin",
    "wof:name":"Barkow Und Leibinger Architekten",
    "wof:placetype":"venue"
},
  "geometry": {"coordinates":[13.310696,52.510223],"type":"Point"}
}