{
  "type": "Feature",
  "properties": {
    "iso:country":"DE",
    "sg:address":"Dr.-Von-Fromm-Str. 3::",
    "sg:city":"Weiden",
    "sg:phone":"+49 961/60050",
    "sg:postcode":"92637",
    "sg:province":"Bayern",
    "wof:name":"W\u00c4rmetechnik V\u00d6lkl Gmbh",
    "wof:placetype":"venue"
},
  "geometry": {"coordinates":[12.099361,49.688389],"type":"Point"}
}