{
  "type": "Feature",
  "properties": {
    "iso:country":"DE",
    "sg:address":"Im Kurzst\u00fcck 5",
    "sg:city":"Gorxheimertal",
    "sg:phone":"+49 4961/0860090",
    "sg:postcode":"69517",
    "sg:province":"Hessen",
    "wof:name":"M. J. S. Air Klima Gmbh & Co. Kg",
    "wof:placetype":"venue"
},
  "geometry": {"coordinates":[8.84891,50.119629],"type":"Point"}
}