{
  "type": "Feature",
  "properties": {
    "iso:country":"DE",
    "sg:address":"Ostener Str. 3",
    "sg:city":"Wischhafen",
    "sg:phone":"+49 4770/7108",
    "sg:postcode":"21737",
    "sg:province":"Niedersachsen",
    "wof:name":"Gastst\u00e4tte H. Sieb",
    "wof:placetype":"venue"
},
  "geometry": {"coordinates":[9.2981452942,53.7464637756],"type":"Point"}
}