{
  "type": "Feature",
  "properties": {
    "iso:country":"DE",
    "sg:address":"Am Hofgarten 15",
    "sg:city":"Bonn",
    "sg:phone":"+49 228/737487",
    "sg:postcode":"53113",
    "sg:province":"Nordrhein-Westfalen",
    "wof:name":"Seminar F\u00fcr Politsche Wissenschaft",
    "wof:placetype":"venue"
},
  "geometry": {"coordinates":[7.105318,50.73103],"type":"Point"}
}