{
  "type": "Feature",
  "properties": {
    "iso:country":"DE",
    "sg:address":"Widenmayerstrasse 5",
    "sg:city":"M\u00fcnchen",
    "sg:postcode":"80538",
    "sg:province":"Bayern",
    "wof:name":"Verwaltungs-und Treuhandgesellschaft Von 1963 Mbh",
    "wof:placetype":"venue"
},
  "geometry": {"coordinates":[-88.039818,43.913101],"type":"Point"}
}