{
  "type": "Feature",
  "properties": {
    "iso:country":"DE",
    "sg:address":"Carl-Peters-Str. 39",
    "sg:city":"Soltau",
    "sg:phone":"+49 5191/13473",
    "sg:postcode":"29614",
    "sg:province":"Niedersachsen",
    "wof:name":"Gerhard K\u00fcsel",
    "wof:placetype":"venue"
},
  "geometry": {"coordinates":[9.830568,52.995892],"type":"Point"}
}