{
  "type": "Feature",
  "properties": {
    "iso:country":"DE",
    "sg:address":"Matth\u00e4istr. 11",
    "sg:city":"Bonn",
    "sg:phone":"+49 228/798061",
    "sg:postcode":"53123",
    "sg:province":"Nordrhein-Westfalen",
    "wof:name":"G\u00fcnter Schwaier",
    "wof:placetype":"venue"
},
  "geometry": {"coordinates":[7.0594110489,50.7138900757],"type":"Point"}
}