{
  "type": "Feature",
  "properties": {
    "iso:country":"DE",
    "sg:address":"Auf der Mauer 42",
    "sg:city":"Kaub",
    "sg:phone":"+49 6774/663",
    "sg:postcode":"56349",
    "sg:province":"Rheinland-Pfalz",
    "wof:name":"H. Und C. Wittemann",
    "wof:placetype":"venue"
},
  "geometry": {"coordinates":[7.7618498802,50.0877113342],"type":"Point"}
}