{
  "type": "Feature",
  "properties": {
    "iso:country":"DE",
    "sg:address":"Mozartstr. 6",
    "sg:city":"K\u00f6nigswinter",
    "sg:phone":"+49 2244/5100",
    "sg:postcode":"53639",
    "sg:province":"Nordrhein-Westfalen",
    "wof:name":"Wenzel Chroust",
    "wof:placetype":"venue"
},
  "geometry": {"coordinates":[7.2794008255,50.7075843811],"type":"Point"}
}