{
  "type": "Feature",
  "properties": {
    "iso:country":"DE",
    "sg:address":"Zur Ruthenaar 2",
    "sg:city":"Willingen",
    "sg:phone":"+49 5632/6621",
    "sg:postcode":"34508",
    "sg:province":"Hessen",
    "wof:name":"K\u00f6hlerh\u00fctte",
    "wof:placetype":"venue"
},
  "geometry": {"coordinates":[8.593894,51.289799],"type":"Point"}
}