{
  "type": "Feature",
  "properties": {
    "iso:country":"DE",
    "sg:address":"Johann-Zinken-Str. 6",
    "sg:city":"Seesen",
    "sg:postcode":"38723",
    "sg:province":"Niedersachsen",
    "wof:name":"Video Buster Vertriebs- Verwaltungsgesellschaft Mbh",
    "wof:placetype":"venue"
},
  "geometry": {"coordinates":[10.1554031372,51.8788871765],"type":"Point"}
}