{
  "type": "Feature",
  "properties": {
    "iso:country":"DE",
    "sg:address":"An der Au 14",
    "sg:city":"Alsfeld",
    "sg:phone":"+49 6631/5041",
    "sg:postcode":"36304",
    "sg:province":"Hessen",
    "wof:name":"Alsfelder Baumarkt Verwaltungs Gmbh",
    "wof:placetype":"venue"
},
  "geometry": {"coordinates":[9.278347,50.753624],"type":"Point"}
}