{
  "type": "Feature",
  "properties": {
    "iso:country":"DE",
    "sg:address":"Krautgartenweg 1",
    "sg:city":"Westendorf",
    "sg:phone":"+49 8273/8186",
    "sg:postcode":"86707",
    "sg:province":"Bayern",
    "wof:name":"Holzbau Riess - Pr\u00e4zision In Holz !",
    "wof:placetype":"venue"
},
  "geometry": {"coordinates":[10.837026,48.570744],"type":"Point"}
}