{
  "type": "Feature",
  "properties": {
    "iso:country":"DE",
    "sg:address":"Lampertsweg",
    "sg:city":"Blankenheim",
    "sg:phone":"+49 2697/1729",
    "sg:postcode":"53945",
    "sg:province":"Nordrhein-Westfalen",
    "wof:name":"Fc Dori",
    "wof:placetype":"venue"
},
  "geometry": {"coordinates":[6.7044820786,50.3751831055],"type":"Point"}
}