{
  "type": "Feature",
  "properties": {
    "iso:country":"DE",
    "sg:address":"Eisbachstr. 31",
    "sg:city":"Sulzbach-Laufen",
    "sg:postcode":"74429",
    "sg:province":"Baden-W\u00fcrttemberg",
    "wof:name":"Ingrid Mottl",
    "wof:placetype":"venue"
},
  "geometry": {"coordinates":[9.843074,48.966843],"type":"Point"}
}