{
  "type": "Feature",
  "properties": {
    "iso:country":"DE",
    "sg:address":"Rosenstr. 11",
    "sg:city":"Blieskastel",
    "sg:phone":"+49 6842/6071",
    "sg:postcode":"66440",
    "sg:province":"Saarland",
    "wof:name":"Doris Sattler",
    "wof:placetype":"venue"
},
  "geometry": {"coordinates":[7.2062149048,49.2505187988],"type":"Point"}
}