{
  "type": "Feature",
  "properties": {
    "iso:country":"DE",
    "sg:address":"Pilziggrundstr. 54",
    "sg:city":"W\u00fcrzburg",
    "sg:postcode":"97076",
    "sg:province":"Bayern",
    "wof:name":"Aldenkortt Entwicklungs Gmbh",
    "wof:placetype":"venue"
},
  "geometry": {"coordinates":[9.9804697037,49.801399231],"type":"Point"}
}