{
  "type": "Feature",
  "properties": {
    "iso:country":"DE",
    "sg:address":"Boschstr. 10",
    "sg:city":"Goch",
    "sg:phone":"+49 2823/93240",
    "sg:postcode":"47574",
    "sg:province":"Nordrhein-Westfalen",
    "wof:name":"V\u00f6lckersche Druckerei Gmbh",
    "wof:placetype":"venue"
},
  "geometry": {"coordinates":[6.144589,51.68504],"type":"Point"}
}