{
  "type": "Feature",
  "properties": {
    "iso:country":"DE",
    "sg:address":"Marbacher Str. 15",
    "sg:city":"Villingen-Schwenningen",
    "sg:postcode":"78048",
    "sg:province":"Baden-W\u00fcrttemberg",
    "wof:name":"Preidel, Hirt & Butz Bestattungshaus Am",
    "wof:placetype":"venue"
},
  "geometry": {"coordinates":[8.470851,48.055328],"type":"Point"}
}