{
  "type": "Feature",
  "properties": {
    "iso:country":"DE",
    "sg:address":"M\u00f6rfelder Landstr. 212a",
    "sg:city":"Frankfurt",
    "sg:postcode":"60598",
    "sg:province":"Hessen",
    "wof:name":"Evang. Ostergemeinde",
    "wof:placetype":"venue"
},
  "geometry": {"coordinates":[8.6737480164,50.0913391113],"type":"Point"}
}