{
  "type": "Feature",
  "properties": {
    "iso:country":"DE",
    "sg:address":"Priel 1",
    "sg:city":"Lindau",
    "sg:phone":"+49 8382/3342",
    "sg:postcode":"88131",
    "sg:province":"Bayern",
    "wof:name":"Alfred Kunzendorf",
    "wof:placetype":"venue"
},
  "geometry": {"coordinates":[9.663177,47.572323],"type":"Point"}
}