{
  "type": "Feature",
  "properties": {
    "iso:country":"DE",
    "sg:address":"Feldhusstr. 15",
    "sg:city":"Delmenhorst",
    "sg:phone":"+49 4221/92670",
    "sg:postcode":"27755",
    "sg:province":"Niedersachsen",
    "wof:name":"Sperling Gmbh & Co. Beh\u00e4lter- Und Apparatebau Kg",
    "wof:placetype":"venue"
},
  "geometry": {"coordinates":[8.650028,53.016926],"type":"Point"}
}