{
  "type": "Feature",
  "properties": {
    "iso:country":"DE",
    "sg:address":"Kaltes Feld 13",
    "sg:city":"Heinsdorfergrund",
    "sg:phone":"+49 3765/551111",
    "sg:postcode":"08468",
    "sg:province":"Sachsen",
    "wof:name":"Vimpex Vertriebs-gmbh & Co. Kg",
    "wof:placetype":"venue"
},
  "geometry": {"coordinates":[12.32945,50.601566],"type":"Point"}
}