{
  "type": "Feature",
  "properties": {
    "iso:country":"DE",
    "sg:address":"Am Klompenkothen 14",
    "sg:city":"D\u00fcsseldorf",
    "sg:phone":"+49 211/133108",
    "sg:postcode":"40489",
    "sg:province":"Nordrhein-Westfalen",
    "wof:name":"Dental-labor Jahic Gmbh",
    "wof:placetype":"venue"
},
  "geometry": {"coordinates":[6.75741,51.307137],"type":"Point"}
}