{
  "type": "Feature",
  "properties": {
    "iso:country":"DE",
    "sg:address":"Langstr. 23",
    "sg:city":"Bacharach",
    "sg:phone":"+49 6743/1232",
    "sg:postcode":"55422",
    "sg:province":"Rheinland-Pfalz",
    "wof:name":"Karl Mai & Sohn Inh. Hans Sch\u00f6nel",
    "wof:placetype":"venue"
},
  "geometry": {"coordinates":[7.768782,50.058743],"type":"Point"}
}