{
  "type": "Feature",
  "properties": {
    "iso:country":"DE",
    "sg:address":"Fabrikstr. 18",
    "sg:city":"Waldkirch",
    "sg:postcode":"79183",
    "sg:province":"Baden-W\u00fcrttemberg",
    "wof:name":"Stema Medien-design Gmbh",
    "wof:placetype":"venue"
},
  "geometry": {"coordinates":[7.974051,48.103668],"type":"Point"}
}