{
  "type": "Feature",
  "properties": {
    "iso:country":"DE",
    "sg:address":"Aschaffenburger Str. 4",
    "sg:city":"Waldaschaff",
    "sg:phone":"+49 6095/568",
    "sg:postcode":"63857",
    "sg:province":"Bayern",
    "wof:name":"Restaurant Ii Trullo",
    "wof:placetype":"venue"
},
  "geometry": {"coordinates":[9.3004102707,49.9725456238],"type":"Point"}
}