{
  "type": "Feature",
  "properties": {
    "iso:country":"DE",
    "sg:address":"Rumbecker Holz 34 a",
    "sg:city":"Arnsberg",
    "sg:phone":"+49 2932",
    "sg:postcode":"59759",
    "sg:province":"Nordrhein-Westfalen",
    "wof:name":"Graf Gottfried Gymnasium Arnsberg",
    "wof:placetype":"venue"
},
  "geometry": {"coordinates":[7.963715,51.436825],"type":"Point"}
}