{
  "type": "Feature",
  "properties": {
    "iso:country":"DE",
    "sg:address":"Schwerinstr. 12",
    "sg:city":"Wuppertal",
    "sg:phone":"+49 202/250860",
    "sg:postcode":"42281",
    "sg:province":"Nordrhein-Westfalen",
    "wof:name":"Allgemeine Baugenossenschaft Wuppertal Eg",
    "wof:placetype":"venue"
},
  "geometry": {"coordinates":[7.194456,51.281624],"type":"Point"}
}