{
  "type": "Feature",
  "properties": {
    "iso:country":"DE",
    "sg:address":"Heidestr. 6",
    "sg:city":"Nuthe-Urstromtal",
    "sg:postcode":"14947",
    "sg:province":"Brandenburg",
    "wof:name":"Lehmann-gravuren",
    "wof:placetype":"venue"
},
  "geometry": {"coordinates":[13.209012,52.111099],"type":"Point"}
}