{
  "type": "Feature",
  "properties": {
    "iso:country":"DE",
    "sg:address":"Brackeler Hellweg 181",
    "sg:city":"Dortmund",
    "sg:phone":"+49 231/256759",
    "sg:postcode":"44309",
    "sg:province":"Nordrhein-Westfalen",
    "wof:name":"Brackeler Galerie",
    "wof:placetype":"venue"
},
  "geometry": {"coordinates":[7.5522232056,51.5239448547],"type":"Point"}
}