{
  "type": "Feature",
  "properties": {
    "iso:country":"DE",
    "sg:address":"T\u00fcrkenstr. 47",
    "sg:city":"M\u00fcnchen",
    "sg:phone":"+49 89/2800750",
    "sg:postcode":"80799",
    "sg:province":"Bayern",
    "wof:name":"August Niehaus",
    "wof:placetype":"venue"
},
  "geometry": {"coordinates":[11.575594902,48.1500587463],"type":"Point"}
}