{
  "type": "Feature",
  "properties": {
    "iso:country":"DE",
    "sg:address":"Br\u00fcxer Str. 2",
    "sg:city":"Neuhausen",
    "sg:phone":"+49 37361/45353",
    "sg:postcode":"09544",
    "sg:province":"Sachsen",
    "wof:name":"Rita Thiel",
    "wof:placetype":"venue"
},
  "geometry": {"coordinates":[13.4654607773,50.6737480164],"type":"Point"}
}