{
  "type": "Feature",
  "properties": {
    "iso:country":"DE",
    "sg:address":"Peterplatz 5",
    "sg:city":"W\u00fcrzburg",
    "sg:phone":"+49 931/571343",
    "sg:postcode":"97070",
    "sg:province":"Bayern",
    "wof:name":"Auflauf",
    "wof:placetype":"venue"
},
  "geometry": {"coordinates":[9.9328365326,49.7894973755],"type":"Point"}
}