{
  "type": "Feature",
  "properties": {
    "iso:country":"DE",
    "sg:address":"Am Eichbaum 27",
    "sg:city":"H\u00f6hn",
    "sg:phone":"+49 2661/949105",
    "sg:postcode":"56462",
    "sg:province":"Rheinland-Pfalz",
    "wof:name":"Heiko K\u00fchn Steuerberater",
    "wof:placetype":"venue"
},
  "geometry": {"coordinates":[7.9925231934,50.6136016846],"type":"Point"}
}