{
  "type": "Feature",
  "properties": {
    "iso:country":"DE",
    "sg:address":"Kyllstr. 68",
    "sg:city":"Trier",
    "sg:phone":"+49 651/69865",
    "sg:postcode":"54293",
    "sg:province":"Rheinland-Pfalz",
    "wof:name":"Rolf L\u00fcbeck",
    "wof:placetype":"venue"
},
  "geometry": {"coordinates":[6.68552,49.807697],"type":"Point"}
}