{
  "type": "Feature",
  "properties": {
    "iso:country":"DE",
    "sg:address":"Betzdorfer Str. 77a",
    "sg:city":"Daaden",
    "sg:phone":"+49 4927/438010",
    "sg:postcode":"57567",
    "sg:province":"Rheinland-Pfalz",
    "wof:name":"B\u00d6denpresswerk Daaden Gmbh",
    "wof:placetype":"venue"
},
  "geometry": {"coordinates":[7.9575500488,50.7462806702],"type":"Point"}
}