{
  "type": "Feature",
  "properties": {
    "iso:country":"DE",
    "sg:address":"Finkenweg 9",
    "sg:city":"Allershausen",
    "sg:postcode":"85391",
    "sg:province":"Bayern",
    "wof:name":"Beauty- Hair Gmbh",
    "wof:placetype":"venue"
},
  "geometry": {"coordinates":[11.597885,48.435566],"type":"Point"}
}