{
  "type": "Feature",
  "properties": {
    "iso:country":"DE",
    "sg:address":"Johann-Georg-Fischer-Str. 9",
    "sg:city":"S\u00fc\u00dfen",
    "sg:phone":"+49 7162/41660",
    "sg:postcode":"73079",
    "sg:province":"Baden-W\u00fcrttemberg",
    "wof:name":"Restaurant Hirsch",
    "wof:placetype":"venue"
},
  "geometry": {"coordinates":[9.7573060989,48.6786613464],"type":"Point"}
}