{
  "type": "Feature",
  "properties": {
    "iso:country":"DE",
    "sg:address":"Hauptstr. 26",
    "sg:city":"Nu\u00dfloch",
    "sg:phone":"+49 6224/16251",
    "sg:postcode":"69226",
    "sg:province":"Baden-W\u00fcrttemberg",
    "wof:name":"M. Disterheft Videothek",
    "wof:placetype":"venue"
},
  "geometry": {"coordinates":[8.6944265366,49.3271217346],"type":"Point"}
}