{
  "type": "Feature",
  "properties": {
    "iso:country":"DE",
    "sg:address":"Bielatalstr. 30",
    "sg:city":"K\u00f6nigstein",
    "sg:phone":"+49 35021/68517",
    "sg:postcode":"01824",
    "sg:province":"Sachsen",
    "wof:name":"Wolfgang G\u00fcrth",
    "wof:placetype":"venue"
},
  "geometry": {"coordinates":[14.070873,50.914879],"type":"Point"}
}