{
  "type": "Feature",
  "properties": {
    "iso:country":"DE",
    "sg:address":"Brunner Hauptstr. 14",
    "sg:city":"Emskirchen",
    "sg:phone":"+49 9104/554",
    "sg:postcode":"91448",
    "sg:province":"Bayern",
    "wof:name":"Intertech Gmbh",
    "wof:placetype":"venue"
},
  "geometry": {"coordinates":[10.7080307007,49.5711708069],"type":"Point"}
}