{
  "type": "Feature",
  "properties": {
    "iso:country":"DE",
    "sg:address":"Bergstr. 7",
    "sg:city":"Hamburg",
    "sg:postcode":"20095",
    "sg:province":"Hamburg",
    "wof:name":"Holger Antz Beteiligungs- Und Vern\u00f6gensverwaltung Gmbh",
    "wof:placetype":"venue"
},
  "geometry": {"coordinates":[9.995775,53.550411],"type":"Point"}
}