{
  "type": "Feature",
  "properties": {
    "iso:country":"DE",
    "sg:address":"Fichtenstr. 32",
    "sg:city":"M\u00f6nchweiler",
    "sg:phone":"+49 7721/71085",
    "sg:postcode":"78087",
    "sg:province":"Baden-W\u00fcrttemberg",
    "wof:name":"Waldemar Rieber",
    "wof:placetype":"venue"
},
  "geometry": {"coordinates":[8.421356,48.098598],"type":"Point"}
}