{
  "type": "Feature",
  "properties": {
    "iso:country":"DE",
    "sg:address":"Neues Ufer 12",
    "sg:city":"Berlin",
    "sg:phone":"+49 30/3444539",
    "sg:postcode":"10553",
    "sg:province":"Berlin",
    "wof:name":"Digitalkamera Onlineshop Berlin",
    "wof:placetype":"venue"
},
  "geometry": {"coordinates":[13.315941,52.526569],"type":"Point"}
}