{
  "type": "Feature",
  "properties": {
    "iso:country":"DE",
    "sg:address":"Stadthausbr\u00fccke 32",
    "sg:city":"Hamburg",
    "sg:postcode":"20355",
    "sg:province":"Hamburg",
    "wof:name":"Actum Consulting Products Gmbh",
    "wof:placetype":"venue"
},
  "geometry": {"coordinates":[9.9857902527,53.5519104004],"type":"Point"}
}