{
  "type": "Feature",
  "properties": {
    "iso:country":"DE",
    "sg:address":"Neuburger Str. 3",
    "sg:city":"Karlshuld",
    "sg:phone":"+49 8454/657",
    "sg:postcode":"86668",
    "sg:province":"Bayern",
    "wof:name":"Annemarie Lang",
    "wof:placetype":"venue"
},
  "geometry": {"coordinates":[11.2861909866,48.6826171875],"type":"Point"}
}