{
  "type": "Feature",
  "properties": {
    "iso:country":"DE",
    "sg:address":"Dorfstr. 1",
    "sg:city":"Wredenhagen",
    "sg:phone":"+49 39925/2346",
    "sg:postcode":"17209",
    "sg:province":"Mecklenburg-Vorpommern",
    "wof:name":"Cafe Scheune",
    "wof:placetype":"venue"
},
  "geometry": {"coordinates":[12.542696,53.296368],"type":"Point"}
}