{
  "type": "Feature",
  "properties": {
    "iso:country":"DE",
    "sg:address":"D\u00fcrener Str. 221",
    "sg:city":"K\u00f6ln",
    "sg:phone":"+49 221/9402290",
    "sg:postcode":"50931",
    "sg:province":"Nordrhein-Westfalen",
    "wof:name":"Foto Lucas Gmbh",
    "wof:placetype":"venue"
},
  "geometry": {"coordinates":[6.9123129845,50.9293441772],"type":"Point"}
}