{
  "type": "Feature",
  "properties": {
    "iso:country":"DE",
    "sg:address":"Hauptstr. 11",
    "sg:city":"Wellendingen",
    "sg:phone":"+49 7426/1285",
    "sg:postcode":"78669",
    "sg:province":"Baden-W\u00fcrttemberg",
    "wof:name":"Kath. Pfarramt St. Ulrich",
    "wof:placetype":"venue"
},
  "geometry": {"coordinates":[8.7026281357,48.1471061707],"type":"Point"}
}