{
  "type": "Feature",
  "properties": {
    "iso:country":"DE",
    "sg:address":"Saarbr\u00fccker Str. 5",
    "sg:city":"Schmelz",
    "sg:postcode":"66839",
    "sg:province":"Saarland",
    "wof:name":"Caldera Bekleidungs- Gmbh",
    "wof:placetype":"venue"
},
  "geometry": {"coordinates":[6.8554139137,49.4426803589],"type":"Point"}
}