{
  "type": "Feature",
  "properties": {
    "iso:country":"DE",
    "sg:address":"Hauptstr. 8",
    "sg:city":"Efringen-Kirchen",
    "sg:phone":"+49 7628/336",
    "sg:postcode":"79588",
    "sg:province":"Baden-W\u00fcrttemberg",
    "wof:name":"Pfalz-apotheke Efringen- Kirchen Brigitte Knaudt E. K.",
    "wof:placetype":"venue"
},
  "geometry": {"coordinates":[7.564525,47.653961],"type":"Point"}
}