{
  "type": "Feature",
  "properties": {
    "iso:country":"DE",
    "sg:address":"Rathausstr. 1",
    "sg:city":"Sch\u00f6nbrunn",
    "sg:phone":"+49 6262/1224",
    "sg:postcode":"69436",
    "sg:province":"Baden-W\u00fcrttemberg",
    "wof:name":"Georgia Jensen Und Klaus Haag Masseure",
    "wof:placetype":"venue"
},
  "geometry": {"coordinates":[8.930177,49.396118],"type":"Point"}
}