{
  "type": "Feature",
  "properties": {
    "iso:country":"DE",
    "sg:address":"Magdeburger Str. 60 a",
    "sg:city":"Eichenbarleben",
    "sg:phone":"+49 39206/50834",
    "sg:postcode":"39167",
    "sg:province":"Sachsen-Anhalt",
    "wof:name":"Eiscafe Ulrich Karpe",
    "wof:placetype":"venue"
},
  "geometry": {"coordinates":[11.406965,52.168438],"type":"Point"}
}