{
  "type": "Feature",
  "properties": {
    "iso:country":"DE",
    "sg:address":"Louisenstr. 11",
    "sg:city":"Bad Homburg",
    "sg:phone":"+49 6172/24641",
    "sg:postcode":"61348",
    "sg:province":"Hessen",
    "wof:name":"Spielothek Gmbh & Co. Kg",
    "wof:placetype":"venue"
},
  "geometry": {"coordinates":[8.6127986908,50.2284889221],"type":"Point"}
}