{
  "type": "Feature",
  "properties": {
    "iso:country":"DE",
    "sg:address":"Waldstr. 1d",
    "sg:city":"Freiburg",
    "sg:phone":"+49 7665/4910",
    "sg:postcode":"79108",
    "sg:province":"Baden-W\u00fcrttemberg",
    "wof:name":"Erhard Radziwill",
    "wof:placetype":"venue"
},
  "geometry": {"coordinates":[7.803705,48.044914],"type":"Point"}
}