{
  "type": "Feature",
  "properties": {
    "iso:country":"DE",
    "sg:address":"Soldnerstr. 19",
    "sg:city":"Augsburg",
    "sg:phone":"+49 821/792378",
    "sg:postcode":"86167",
    "sg:province":"Bayern",
    "wof:name":"H. Weber Und D. Schneider Architekten",
    "wof:placetype":"venue"
},
  "geometry": {"coordinates":[10.91306,48.383087],"type":"Point"}
}