{
  "type": "Feature",
  "properties": {
    "iso:country":"DE",
    "sg:address":"Dorfstr. 1",
    "sg:city":"Grebin",
    "sg:phone":"+49 4383/333",
    "sg:postcode":"24329",
    "sg:province":"Schleswig-Holstein",
    "wof:name":"Homilius & B\u00fcnning Gmbh",
    "wof:placetype":"venue"
},
  "geometry": {"coordinates":[10.4894762039,54.1980514526],"type":"Point"}
}