{
  "type": "Feature",
  "properties": {
    "iso:country":"DE",
    "sg:address":"Kottbusser Damm 86",
    "sg:city":"Berlin",
    "sg:phone":"+49 30/6913071",
    "sg:postcode":"10967",
    "sg:province":"Berlin",
    "wof:name":"Mauritius Apotheke Torsten Heyne E. K.",
    "wof:placetype":"venue"
},
  "geometry": {"coordinates":[13.422661,52.492554],"type":"Point"}
}