{
  "type": "Feature",
  "properties": {
    "iso:country":"DE",
    "sg:address":"Uellendahler Str. 91",
    "sg:city":"Wuppertal",
    "sg:phone":"+49 202/755745",
    "sg:postcode":"42107",
    "sg:province":"Nordrhein-Westfalen",
    "wof:name":"China-restaurant",
    "wof:placetype":"venue"
},
  "geometry": {"coordinates":[7.1483159065,51.2699356079],"type":"Point"}
}