{
  "type": "Feature",
  "properties": {
    "iso:country":"DE",
    "sg:address":"Bovingerweg 5",
    "sg:city":"Butjadingen",
    "sg:phone":"+49 4731/37748",
    "sg:postcode":"26969",
    "sg:province":"Niedersachsen",
    "wof:name":"Ferien Auf Dem Bauernhof Bei Rena Und Theo Ratjen",
    "wof:placetype":"venue"
},
  "geometry": {"coordinates":[8.437982,53.534492],"type":"Point"}
}