{
  "type": "Feature",
  "properties": {
    "iso:country":"DE",
    "sg:address":"Untertorstr. 10",
    "sg:city":"Gr\u00fcnstadt",
    "sg:phone":"+49 6359/2100",
    "sg:postcode":"67269",
    "sg:province":"Rheinland-Pfalz",
    "wof:name":"Gropp Kreiselmayer",
    "wof:placetype":"venue"
},
  "geometry": {"coordinates":[8.1597585678,49.5489082336],"type":"Point"}
}