{
  "type": "Feature",
  "properties": {
    "iso:country":"DE",
    "sg:address":"hafenstrasse 2",
    "sg:city":"weissenthurm",
    "sg:phone":"+49 2637/8691",
    "sg:postcode":"56575",
    "sg:province":"Rheinland-Pfalz",
    "wof:name":"Arbeitssicherheit Berufsgenossenschaft Dienst",
    "wof:placetype":"venue"
},
  "geometry": {"coordinates":[7.477131,50.409485],"type":"Point"}
}