{
  "type": "Feature",
  "properties": {
    "iso:country":"DE",
    "sg:address":"Osnabr\u00fccker Str. 53",
    "sg:city":"Rheine",
    "sg:postcode":"48429",
    "sg:province":"Nordrhein-Westfalen",
    "wof:name":"Inova Personal Nach Ma\u00df Verwaltungs- Und",
    "wof:placetype":"venue"
},
  "geometry": {"coordinates":[7.4482979774,52.2820968628],"type":"Point"}
}