{
  "type": "Feature",
  "properties": {
    "iso:country":"DE",
    "sg:address":"Lederergasse 16",
    "sg:city":"Dingolfing",
    "sg:phone":"+49 8731/2226",
    "sg:postcode":"84130",
    "sg:province":"Bayern",
    "wof:name":"Baugenossenschaft Dingolfing Eg",
    "wof:placetype":"venue"
},
  "geometry": {"coordinates":[12.4981384277,48.6300392151],"type":"Point"}
}