{
  "type": "Feature",
  "properties": {
    "iso:country":"DE",
    "sg:address":"Am Weinberg 14",
    "sg:city":"Gundelsheim",
    "sg:phone":"+49 951/44672",
    "sg:postcode":"96163",
    "sg:province":"Bayern",
    "wof:name":"Friedrich Gerfertz",
    "wof:placetype":"venue"
},
  "geometry": {"coordinates":[10.9328927994,49.9405021667],"type":"Point"}
}