{
  "type": "Feature",
  "properties": {
    "iso:country":"DE",
    "sg:address":"Springerwiese 2",
    "sg:city":"Drolshagen",
    "sg:phone":"+49 2763/7622",
    "sg:postcode":"57489",
    "sg:province":"Nordrhein-Westfalen",
    "wof:name":"Sondermann",
    "wof:placetype":"venue"
},
  "geometry": {"coordinates":[7.768173,51.039345],"type":"Point"}
}