{
  "type": "Feature",
  "properties": {
    "iso:country":"DE",
    "sg:address":"Sch\u00f6nebecker Str. 97",
    "sg:city":"Magdeburg",
    "sg:phone":"+49 391/42675",
    "sg:postcode":"39104",
    "sg:province":"Sachsen-Anhalt",
    "wof:name":"Volksbank",
    "wof:placetype":"venue"
},
  "geometry": {"coordinates":[11.641404,52.10556],"type":"Point"}
}