{
  "type": "Feature",
  "properties": {
    "iso:country":"DE",
    "sg:address":"Heilmannstr. 19",
    "sg:city":"Frankfurt",
    "sg:phone":"+49 69/583423",
    "sg:postcode":"60439",
    "sg:province":"Hessen",
    "wof:name":"Ursula Br\u00f6ckl",
    "wof:placetype":"venue"
},
  "geometry": {"coordinates":[8.6260204315,50.1554985046],"type":"Point"}
}