{
  "type": "Feature",
  "properties": {
    "iso:country":"DE",
    "sg:address":"Benrather Str.",
    "sg:city":"Wuppertal",
    "sg:postcode":"42115",
    "sg:province":"Nordrhein-Westfalen",
    "wof:name":"Erwerbergemeinschaft Gro\u00dfmarkt Varresbeck Gmbh",
    "wof:placetype":"venue"
},
  "geometry": {"coordinates":[7.1003661156,51.2537307739],"type":"Point"}
}