{
  "type": "Feature",
  "properties": {
    "iso:country":"DE",
    "sg:address":"Wiesenweg 4",
    "sg:city":"Bleckede",
    "sg:phone":"+49 5853/292",
    "sg:postcode":"21354",
    "sg:province":"Niedersachsen",
    "wof:name":"Cafe Michelshof",
    "wof:placetype":"venue"
},
  "geometry": {"coordinates":[10.845042,53.239822],"type":"Point"}
}