{
  "type": "Feature",
  "properties": {
    "iso:country":"DE",
    "sg:address":"Aufelderstr. 12",
    "sg:city":"Aschaffenburg",
    "sg:phone":"+49 6021",
    "sg:postcode":"63741",
    "sg:province":"Bayern",
    "wof:name":"Kfz-handel Schreck Gmbh",
    "wof:placetype":"venue"
},
  "geometry": {"coordinates":[9.1258602142,49.9753684998],"type":"Point"}
}