{
  "type": "Feature",
  "properties": {
    "iso:country":"DE",
    "sg:address":"Alsfelder Str. 46",
    "sg:city":"Grebenau",
    "sg:phone":"+49 6646/368",
    "sg:postcode":"36323",
    "sg:province":"Hessen",
    "wof:name":"Helmut Becker",
    "wof:placetype":"venue"
},
  "geometry": {"coordinates":[9.4125099182,50.7228126526],"type":"Point"}
}