{
  "type": "Feature",
  "properties": {
    "iso:country":"DE",
    "sg:address":"Neue Dorfstr. 12",
    "sg:city":"Halle",
    "sg:phone":"+49 5201/16105",
    "sg:postcode":"33790",
    "sg:province":"Nordrhein-Westfalen",
    "wof:name":"Johannes Petersen",
    "wof:placetype":"venue"
},
  "geometry": {"coordinates":[8.302478,52.04718],"type":"Point"}
}