{
  "type": "Feature",
  "properties": {
    "iso:country":"DE",
    "sg:address":"Poststr. 12",
    "sg:city":"J\u00fclich",
    "sg:phone":"+49 2461/59725",
    "sg:postcode":"52428",
    "sg:province":"Nordrhein-Westfalen",
    "wof:name":"Schneider",
    "wof:placetype":"venue"
},
  "geometry": {"coordinates":[6.360614,50.9217],"type":"Point"}
}