{
  "type": "Feature",
  "properties": {
    "iso:country":"DE",
    "sg:address":"Am Panneschopp 7",
    "sg:city":"Nettetal",
    "sg:postcode":"41334",
    "sg:province":"Nordrhein-Westfalen",
    "wof:name":"B\u00fcckers Verwaltungs- Gesellschaft Mbh",
    "wof:placetype":"venue"
},
  "geometry": {"coordinates":[6.182812,51.321918],"type":"Point"}
}