{
  "type": "Feature",
  "properties": {
    "iso:country":"DE",
    "sg:address":"Blankeneser Bahnhofstr. 4",
    "sg:city":"Hamburg",
    "sg:phone":"+49 40/864651",
    "sg:postcode":"22587",
    "sg:province":"Hamburg",
    "wof:name":"Dr. Detlef Winter Und Erdtmann Rechtsanw\u00e4lte",
    "wof:placetype":"venue"
},
  "geometry": {"coordinates":[9.8113937378,53.5589637756],"type":"Point"}
}