{
  "type": "Feature",
  "properties": {
    "iso:country":"DE",
    "sg:address":"Saalburg-R\u00f6merkastell",
    "sg:city":"Bad Homburg",
    "sg:phone":"+49 6172/3148",
    "sg:postcode":"61350",
    "sg:province":"Hessen",
    "wof:name":"Saalburgmuseum",
    "wof:placetype":"venue"
},
  "geometry": {"coordinates":[8.56321,50.250431],"type":"Point"}
}