{
  "type": "Feature",
  "properties": {
    "iso:country":"DE",
    "sg:address":"Bahnhofstr. 44",
    "sg:city":"Celle",
    "sg:phone":"+49 5141/217176",
    "sg:postcode":"29221",
    "sg:province":"Niedersachsen",
    "wof:name":"Orchideen-apotheke Inh. Ralph M\u00f6ller",
    "wof:placetype":"venue"
},
  "geometry": {"coordinates":[10.064658,52.620869],"type":"Point"}
}