{
  "type": "Feature",
  "properties": {
    "iso:country":"DE",
    "sg:address":"Luisenstr. 15",
    "sg:city":"Besigheim",
    "sg:phone":"+49 7143/830189",
    "sg:postcode":"74354",
    "sg:province":"Baden-W\u00fcrttemberg",
    "wof:name":"Eight Miles High Bietigheim Rolf Nestrasil",
    "wof:placetype":"venue"
},
  "geometry": {"coordinates":[9.1388940811,48.9948616028],"type":"Point"}
}