{
  "type": "Feature",
  "properties": {
    "iso:country":"DE",
    "sg:address":"Bahnhofstr. 19",
    "sg:city":"Weikersheim",
    "sg:phone":"+49 7934/990036",
    "sg:postcode":"97990",
    "sg:province":"Baden-W\u00fcrttemberg",
    "wof:name":"Dekanat Wiekersheim",
    "wof:placetype":"venue"
},
  "geometry": {"coordinates":[9.9027366638,49.4792175293],"type":"Point"}
}