{
  "type": "Feature",
  "properties": {
    "iso:country":"DE",
    "sg:address":"Augenerstr. 84",
    "sg:city":"Essen",
    "sg:phone":"+49 201/535333",
    "sg:postcode":"45276",
    "sg:province":"Nordrhein-Westfalen",
    "wof:name":"K. Neumann",
    "wof:placetype":"venue"
},
  "geometry": {"coordinates":[7.089603,51.448975],"type":"Point"}
}