{
  "type": "Feature",
  "properties": {
    "iso:country":"DE",
    "sg:address":"Sch\u00fctzenstr. 11",
    "sg:city":"Selb",
    "sg:phone":"+49 9287/3493",
    "sg:postcode":"95100",
    "sg:province":"Bayern",
    "wof:name":"L. Jahn",
    "wof:placetype":"venue"
},
  "geometry": {"coordinates":[12.13358,50.167],"type":"Point"}
}