{
  "type": "Feature",
  "properties": {
    "iso:country":"DE",
    "sg:address":"Kellen 15",
    "sg:city":"Blumberg",
    "sg:phone":"+49 7702/419044",
    "sg:postcode":"78176",
    "sg:province":"Baden-W\u00fcrttemberg",
    "wof:name":"Produktionsservice Gmbh",
    "wof:placetype":"venue"
},
  "geometry": {"coordinates":[8.532217,47.84428],"type":"Point"}
}