{
  "type": "Feature",
  "properties": {
    "iso:country":"DE",
    "sg:address":"Semmelweisstr. 34",
    "sg:city":"M\u00fclheim",
    "sg:phone":"+49 208/374440",
    "sg:postcode":"45470",
    "sg:province":"Nordrhein-Westfalen",
    "wof:name":"Von Rohr Haus Demmin Gmbh",
    "wof:placetype":"venue"
},
  "geometry": {"coordinates":[6.8991689682,51.4153938293],"type":"Point"}
}