{
  "type": "Feature",
  "properties": {
    "iso:country":"DE",
    "sg:address":"Kirchstr. 9",
    "sg:city":"Fuchsstadt",
    "sg:phone":"+49 9732/2190",
    "sg:postcode":"97727",
    "sg:province":"Bayern",
    "wof:name":"Katholisches Pfarramt Mari\u00e4 Himmelfahrt",
    "wof:placetype":"venue"
},
  "geometry": {"coordinates":[9.933257103,50.1077270508],"type":"Point"}
}