{
  "type": "Feature",
  "properties": {
    "iso:country":"DE",
    "sg:address":"Am Mattenstieg 16",
    "sg:city":"Dabel",
    "sg:phone":"+49 38485/20111",
    "sg:postcode":"19406",
    "sg:province":"Mecklenburg-Vorpommern",
    "wof:name":"Storchen-apotheke Inh. Grit Kamphausen E. Kfr.",
    "wof:placetype":"venue"
},
  "geometry": {"coordinates":[11.90157,53.659546],"type":"Point"}
}