{
  "type": "Feature",
  "properties": {
    "iso:country":"DE",
    "sg:address":"Am Plan 1a",
    "sg:city":"Koblenz",
    "sg:phone":"+49 261",
    "sg:postcode":"56068",
    "sg:province":"Rheinland-Pfalz",
    "wof:name":"Kieferorthop\u00e4de Dr. Bernd Prestel",
    "wof:placetype":"venue"
},
  "geometry": {"coordinates":[7.594522,50.360458],"type":"Point"}
}