{
  "type": "Feature",
  "properties": {
    "iso:country":"DE",
    "sg:address":"Uhlenberg 5",
    "sg:city":"Reken",
    "sg:phone":"+49 2864/72015",
    "sg:postcode":"48734",
    "sg:province":"Nordrhein-Westfalen",
    "wof:name":"H. Krott",
    "wof:placetype":"venue"
},
  "geometry": {"coordinates":[7.0236439705,51.8116607666],"type":"Point"}
}