{
  "type": "Feature",
  "properties": {
    "iso:country":"DE",
    "sg:address":"D\u00fcrener Stra\u00dfe 316-318",
    "sg:city":"Kerpen",
    "sg:phone":"+49 2275/912670",
    "sg:postcode":"50171",
    "sg:province":"Nordrhein-Westfalen",
    "wof:name":"Combiserv, Nagelstudio, Dob Und Post-agentur",
    "wof:placetype":"venue"
},
  "geometry": {"coordinates":[6.629907,50.854004],"type":"Point"}
}