{
  "type": "Feature",
  "properties": {
    "iso:country":"DE",
    "sg:address":"Mansfelder Str. 21",
    "sg:city":"Gro\u00df\u00f6rner",
    "sg:phone":"+49 3476/812933",
    "sg:postcode":"06348",
    "wof:name":"Sonnen-apotheke Inh. Sabine Raschke",
    "wof:placetype":"venue"
},
  "geometry": {"coordinates":[11.491141,51.617126],"type":"Point"}
}