{
  "type": "Feature",
  "properties": {
    "iso:country":"DE",
    "sg:address":"Sittarder Str. 63",
    "sg:city":"Viersen",
    "sg:phone":"+49 2162/266290",
    "sg:postcode":"41748",
    "sg:province":"Nordrhein-Westfalen",
    "wof:name":"Busch Wickenhagen Gmbh",
    "wof:placetype":"venue"
},
  "geometry": {"coordinates":[6.4009890556,51.2663841248],"type":"Point"}
}