{
  "type": "Feature",
  "properties": {
    "iso:country":"DE",
    "sg:address":"Am Kirchplatz 1",
    "sg:city":"Duisburg",
    "sg:phone":"+49 2065/61534",
    "sg:postcode":"47228",
    "sg:province":"Nordrhein-Westfalen",
    "wof:name":"U.-u. Arndt",
    "wof:placetype":"venue"
},
  "geometry": {"coordinates":[6.6853852272,51.4156036377],"type":"Point"}
}