{
  "type": "Feature",
  "properties": {
    "iso:country":"DE",
    "sg:address":"Hugenottenstr. 54",
    "sg:city":"Friedrichsdorf",
    "sg:phone":"+49 6172/74284",
    "sg:postcode":"61381",
    "sg:province":"Hessen",
    "wof:name":"Pizzeria Da Cimino",
    "wof:placetype":"venue"
},
  "geometry": {"coordinates":[8.63804245,50.2549667358],"type":"Point"}
}