{
  "type": "Feature",
  "properties": {
    "iso:country":"DE",
    "sg:address":"Frankensteiner Str. 37",
    "sg:city":"Hasbergen",
    "sg:phone":"+49 5405/1048",
    "sg:postcode":"49205",
    "sg:province":"Niedersachsen",
    "wof:name":"Sabine Schuld",
    "wof:placetype":"venue"
},
  "geometry": {"coordinates":[7.955767,52.234776],"type":"Point"}
}