{
  "type": "Feature",
  "properties": {
    "iso:country":"DE",
    "sg:address":"Kathreinerstr. 26",
    "sg:city":"Bad W\u00f6rishofen",
    "sg:phone":"+49 8247/1011",
    "sg:postcode":"86825",
    "sg:province":"Bayern",
    "wof:name":"W\u00fcstenrot Bausparkasse",
    "wof:placetype":"venue"
},
  "geometry": {"coordinates":[10.59257,48.007359],"type":"Point"}
}