{
  "type": "Feature",
  "properties": {
    "iso:country":"DE",
    "sg:address":"Aachener Str. 81",
    "sg:city":"\u00dcbach-Palenberg",
    "sg:phone":"+49 2451/41487",
    "sg:postcode":"52531",
    "sg:province":"Nordrhein-Westfalen",
    "wof:name":"Edmund Malburg",
    "wof:placetype":"venue"
},
  "geometry": {"coordinates":[6.0990138054,50.9265823364],"type":"Point"}
}