{
  "type": "Feature",
  "properties": {
    "iso:country":"DE",
    "sg:address":"Gro\u00dfe Str. 59",
    "sg:city":"Damme",
    "sg:phone":"+49 5491/2332",
    "sg:postcode":"49401",
    "sg:province":"Niedersachsen",
    "wof:name":"Heinrich Arlinghaus",
    "wof:placetype":"venue"
},
  "geometry": {"coordinates":[8.19547,52.519981],"type":"Point"}
}