{
  "type": "Feature",
  "properties": {
    "iso:country":"DE",
    "sg:address":"Klein-Sehnder-Weg 7",
    "sg:city":"Algermissen",
    "sg:phone":"+49 5126/8197",
    "sg:postcode":"31191",
    "sg:province":"Niedersachsen",
    "wof:name":"Angelika Str\u00fcber",
    "wof:placetype":"venue"
},
  "geometry": {"coordinates":[9.950657,52.277214],"type":"Point"}
}