{
  "type": "Feature",
  "properties": {
    "iso:country":"DE",
    "sg:address":"Boschstr. 11",
    "sg:city":"Pulheim",
    "sg:phone":"+49 2238/962926",
    "sg:postcode":"50259",
    "sg:province":"Nordrhein-Westfalen",
    "wof:name":"Lambertz & Co. Bau- Ingenieurb\u00fcro Gmbh",
    "wof:placetype":"venue"
},
  "geometry": {"coordinates":[6.818564,50.991901],"type":"Point"}
}