{
  "type": "Feature",
  "properties": {
    "iso:country":"DE",
    "sg:address":"L\u00f6hrstr.",
    "sg:city":"Koblenz",
    "sg:phone":"+49 261/18177",
    "sg:postcode":"56068",
    "sg:province":"Rheinland-Pfalz",
    "wof:name":"U. Popken",
    "wof:placetype":"venue"
},
  "geometry": {"coordinates":[7.593955,50.360016],"type":"Point"}
}