{
  "type": "Feature",
  "properties": {
    "iso:country":"DE",
    "sg:address":"Erftstr. 80b",
    "sg:city":"Neuss",
    "sg:phone":"+49 2131/24248",
    "sg:postcode":"41460",
    "sg:province":"Nordrhein-Westfalen",
    "wof:name":"Ulrich Walter Rechtsanwalt",
    "wof:placetype":"venue"
},
  "geometry": {"coordinates":[6.6894412041,51.1966018677],"type":"Point"}
}