{
  "type": "Feature",
  "properties": {
    "iso:country":"DE",
    "sg:address":"Ernst-Friedrich-Str. 1a",
    "sg:city":"Karlsruhe",
    "sg:phone":"+49 721/9419120",
    "sg:postcode":"76227",
    "sg:province":"Baden-W\u00fcrttemberg",
    "wof:name":"Vks Vertrieb Von Kommunikations Und",
    "wof:placetype":"venue"
},
  "geometry": {"coordinates":[8.4644432068,48.9996528625],"type":"Point"}
}