{
  "type": "Feature",
  "properties": {
    "iso:country":"DE",
    "sg:address":"Ohner Str. 48",
    "sg:city":"Sch\u00fcttorf",
    "sg:phone":"+49 5923/2236",
    "sg:postcode":"48465",
    "sg:province":"Niedersachsen",
    "wof:name":"Dieter Van Der Veen",
    "wof:placetype":"venue"
},
  "geometry": {"coordinates":[7.224374,52.312687],"type":"Point"}
}