{
  "type": "Feature",
  "properties": {
    "iso:country":"DE",
    "sg:address":"Bernardstr. 35",
    "sg:city":"Offenbach",
    "sg:postcode":"63067",
    "sg:province":"Hessen",
    "wof:name":"Malow Dekobau Gmbh",
    "wof:placetype":"venue"
},
  "geometry": {"coordinates":[8.7535476685,50.1077537537],"type":"Point"}
}