{
  "type": "Feature",
  "properties": {
    "iso:country":"DE",
    "sg:address":"Rottland 1",
    "sg:city":"Waldbr\u00f6l",
    "sg:phone":"+49 2291/7434",
    "sg:postcode":"51545",
    "sg:province":"Nordrhein-Westfalen",
    "wof:name":"Harold Fritsch",
    "wof:placetype":"venue"
},
  "geometry": {"coordinates":[7.562523,50.867149],"type":"Point"}
}