{
  "type": "Feature",
  "properties": {
    "iso:country":"DE",
    "sg:address":"Seligenst\u00e4dter Str. 127",
    "sg:city":"Offenbach",
    "sg:postcode":"63073",
    "sg:province":"Hessen",
    "wof:name":"Schmidt Verwaltungs- Und Beteiligungsgesellschaft Mbh",
    "wof:placetype":"venue"
},
  "geometry": {"coordinates":[8.8179779053,50.0839080811],"type":"Point"}
}