{
  "type": "Feature",
  "properties": {
    "iso:country":"DE",
    "sg:address":"Kasseler Str. 1",
    "sg:city":"Frielendorf",
    "sg:phone":"+49 6691/94940",
    "sg:postcode":"34621",
    "sg:province":"Hessen",
    "wof:name":"Gebr. Flach Gmbh",
    "wof:placetype":"venue"
},
  "geometry": {"coordinates":[9.279624939,50.9406852722],"type":"Point"}
}