{
  "type": "Feature",
  "properties": {
    "iso:country":"DE",
    "sg:address":"Auf der M\u00fchle 15",
    "sg:city":"Glinde",
    "sg:postcode":"21509",
    "sg:province":"Schleswig-Holstein",
    "wof:name":"Peter Wierich E. Kfm.",
    "wof:placetype":"venue"
},
  "geometry": {"coordinates":[10.2117,53.547932],"type":"Point"}
}