{
  "type": "Feature",
  "properties": {
    "iso:country":"DE",
    "sg:address":"Nordendstr. 36",
    "sg:city":"M\u00f6rfelden-Walldorf",
    "sg:postcode":"64546",
    "sg:province":"Hessen",
    "wof:name":"Gebhardt & Partner Bedachungen Gmbh",
    "wof:placetype":"venue"
},
  "geometry": {"coordinates":[8.582022,50.016369],"type":"Point"}
}