{
  "type": "Feature",
  "properties": {
    "iso:country":"DE",
    "sg:address":"Kirchstr. 9",
    "sg:city":"Wei\u00dfensberg",
    "sg:phone":"+49 8389/98230",
    "sg:postcode":"88138",
    "sg:province":"Bayern",
    "wof:name":"Sieglinde Me\u00dfmer Heilpraktikerin",
    "wof:placetype":"venue"
},
  "geometry": {"coordinates":[9.7269039154,47.5834503174],"type":"Point"}
}