{
  "type": "Feature",
  "properties": {
    "iso:country":"DE",
    "sg:address":"Klingenstr 40",
    "sg:city":"Geroldshausen",
    "sg:phone":"+49 9366/502",
    "sg:postcode":"97256",
    "sg:province":"Bayern",
    "wof:name":"Feuerland-werkst\u00e4tten Ernst Beilhack Gmbh & Co Kg",
    "wof:placetype":"venue"
},
  "geometry": {"coordinates":[9.904583931,49.6890640259],"type":"Point"}
}