{
  "type": "Feature",
  "properties": {
    "iso:country":"DE",
    "sg:address":"St.-Bruno-Str. 43",
    "sg:city":"Bad Neustadt",
    "sg:phone":"+49 9771/3738",
    "sg:postcode":"97616",
    "sg:province":"Bayern",
    "wof:name":"J. Scheuplein",
    "wof:placetype":"venue"
},
  "geometry": {"coordinates":[10.196169,50.32325],"type":"Point"}
}