{
  "type": "Feature",
  "properties": {
    "iso:country":"DE",
    "sg:address":"M\u00fchlenstr. 5",
    "sg:city":"Borken",
    "sg:phone":"+49 2861/2768",
    "sg:postcode":"46325",
    "sg:province":"Nordrhein-Westfalen",
    "wof:name":"Heinrich Benning",
    "wof:placetype":"venue"
},
  "geometry": {"coordinates":[6.8592791557,51.8444213867],"type":"Point"}
}