{
  "type": "Feature",
  "properties": {
    "iso:country":"DE",
    "sg:address":"Horading 2",
    "sg:city":"Falkenberg",
    "sg:phone":"+49 8727/659",
    "sg:postcode":"84326",
    "sg:province":"Bayern",
    "wof:name":"Josef L\u00f6ffl Ferienbauernhof",
    "wof:placetype":"venue"
},
  "geometry": {"coordinates":[12.7062721252,48.4773216248],"type":"Point"}
}