{
  "type": "Feature",
  "properties": {
    "iso:country":"DE",
    "sg:address":"M\u00fcggendorfer Str. 2",
    "sg:city":"Otterndorf",
    "sg:postcode":"21762",
    "sg:province":"Niedersachsen",
    "wof:name":"Bon Vita Klinik Und Hotel Gmbh",
    "wof:placetype":"venue"
},
  "geometry": {"coordinates":[8.8873405457,53.8134727478],"type":"Point"}
}