{
  "type": "Feature",
  "properties": {
    "iso:country":"DE",
    "sg:address":"Kirchplatz 4",
    "sg:city":"Schorndorf",
    "sg:phone":"+49 9467/280",
    "sg:postcode":"93489",
    "sg:province":"Bayern",
    "wof:name":"Kath. Pfarramt Maria Immaculata",
    "wof:placetype":"venue"
},
  "geometry": {"coordinates":[12.5923576355,49.1598091125],"type":"Point"}
}