{
  "type": "Feature",
  "properties": {
    "iso:country":"DE",
    "sg:address":"Rh\u00f6nstr. 4",
    "sg:city":"Geroda",
    "sg:phone":"+49 9747/1655",
    "sg:postcode":"97779",
    "sg:province":"Bayern",
    "wof:name":"K.-h. Kn\u00fcttel",
    "wof:placetype":"venue"
},
  "geometry": {"coordinates":[9.9108600616,50.2783737183],"type":"Point"}
}