{
  "type": "Feature",
  "properties": {
    "iso:country":"DE",
    "sg:address":"Johannisstr. 8-10",
    "sg:city":"M\u00fcnster",
    "sg:phone":"+49 251/832639",
    "sg:postcode":"48143",
    "sg:province":"Nordrhein-Westfalen",
    "wof:name":"Vereinigte Seminare Der Kath.-theoloigschen Fakult\u00e4t",
    "wof:placetype":"venue"
},
  "geometry": {"coordinates":[7.62221,51.961552],"type":"Point"}
}