{
  "type": "Feature",
  "properties": {
    "iso:country":"DE",
    "sg:address":"Adelheider Str. 77",
    "sg:city":"Delmenhorst",
    "sg:phone":"+49 4221/23577",
    "sg:postcode":"27755",
    "sg:province":"Niedersachsen",
    "wof:name":"Aral Ag",
    "wof:placetype":"venue"
},
  "geometry": {"coordinates":[8.6214828491,53.0321884155],"type":"Point"}
}