{
  "type": "Feature",
  "properties": {
    "iso:country":"DE",
    "sg:address":"T\u00f6nningstr. 140",
    "sg:city":"Voerde",
    "sg:postcode":"46562",
    "sg:province":"Nordrhein-Westfalen",
    "wof:name":"Transfer Deutschland Gmbh",
    "wof:placetype":"venue"
},
  "geometry": {"coordinates":[6.671113,51.602486],"type":"Point"}
}