{
  "type": "Feature",
  "properties": {
    "iso:country":"DE",
    "sg:address":"Hollingbusch",
    "sg:city":"Schwabstedt",
    "sg:phone":"+49 4884/791",
    "sg:postcode":"25876",
    "sg:province":"Schleswig-Holstein",
    "wof:name":"Heinz Clausen-hansen",
    "wof:placetype":"venue"
},
  "geometry": {"coordinates":[9.200661,54.393288],"type":"Point"}
}