{
  "type": "Feature",
  "properties": {
    "iso:country":"DE",
    "sg:address":"Alte Hauptstr. 16",
    "sg:city":"Essen",
    "sg:phone":"+49 201/57696",
    "sg:postcode":"45289",
    "sg:province":"Nordrhein-Westfalen",
    "wof:name":"G. Gr\u00e4ler",
    "wof:placetype":"venue"
},
  "geometry": {"coordinates":[7.120001,51.416893],"type":"Point"}
}