{
  "type": "Feature",
  "properties": {
    "iso:country":"DE",
    "sg:address":"Hansestr. 24",
    "sg:city":"Sittensen",
    "sg:phone":"+49 4282/2233",
    "sg:postcode":"27419",
    "sg:province":"Niedersachsen",
    "wof:name":"H. Bolte",
    "wof:placetype":"venue"
},
  "geometry": {"coordinates":[9.502402,53.296059],"type":"Point"}
}