{
  "type": "Feature",
  "properties": {
    "iso:country":"DE",
    "sg:address":"Turmstr. 20",
    "sg:city":"Nagold",
    "sg:phone":"+49 7452/2004",
    "sg:postcode":"72202",
    "sg:province":"Baden-W\u00fcrttemberg",
    "wof:name":"Pinguin-apotheke Dr. Wolfgang Einhoff",
    "wof:placetype":"venue"
},
  "geometry": {"coordinates":[8.724133,48.551609],"type":"Point"}
}