{
  "type": "Feature",
  "properties": {
    "iso:country":"DE",
    "sg:address":"Bergstr. 4B",
    "sg:city":"Sondershausen",
    "sg:phone":"+49 3632/602987",
    "sg:postcode":"99706",
    "sg:province":"Th\u00fcringen",
    "wof:name":"Margit Sp\u00f6hr Hebamme",
    "wof:placetype":"venue"
},
  "geometry": {"coordinates":[10.860996,51.366478],"type":"Point"}
}