{
  "type": "Feature",
  "properties": {
    "iso:country":"DE",
    "sg:address":"An den Reesenbetten 13",
    "sg:city":"B\u00fcdelsdorf",
    "sg:phone":"+49 4331/71720",
    "sg:postcode":"24782",
    "sg:province":"Schleswig-Holstein",
    "wof:name":"Essen Auf R\u00e4dern Im Kreis",
    "wof:placetype":"venue"
},
  "geometry": {"coordinates":[9.696296,54.321781],"type":"Point"}
}