{
  "type": "Feature",
  "properties": {
    "iso:country":"DE",
    "sg:address":"Florastr. 44",
    "sg:city":"Berlin",
    "sg:phone":"+49 30/48637336",
    "sg:postcode":"13187",
    "sg:province":"Berlin",
    "wof:name":"Sonnen-apotheke",
    "wof:placetype":"venue"
},
  "geometry": {"coordinates":[13.409391,52.56628],"type":"Point"}
}