{
  "type": "Feature",
  "properties": {
    "iso:country":"DE",
    "sg:address":"Hegelall. 53",
    "sg:city":"Potsdam",
    "sg:phone":"+49 4933/1291103",
    "sg:postcode":"14467",
    "sg:province":"Brandenburg",
    "wof:name":"Druckerei Edmund Stein Gmbh",
    "wof:placetype":"venue"
},
  "geometry": {"coordinates":[13.0564651489,52.4029502869],"type":"Point"}
}