{
  "type": "Feature",
  "properties": {
    "iso:country":"DE",
    "sg:address":"Alte Dorfstr. 18",
    "sg:city":"Sch\u00f6neck",
    "sg:phone":"+49 6187/95635",
    "sg:postcode":"61137",
    "sg:province":"Hessen",
    "wof:name":"Resch Cosmetics Inh. Waltraud Resch",
    "wof:placetype":"venue"
},
  "geometry": {"coordinates":[8.8238105774,50.1979637146],"type":"Point"}
}