{
  "type": "Feature",
  "properties": {
    "iso:country":"DE",
    "sg:address":"Wei\u00dfenfelser Str. 100",
    "sg:city":"Zeitz",
    "sg:phone":"+49 3441/61840",
    "sg:postcode":"06712",
    "sg:province":"Sachsen-Anhalt",
    "wof:name":"Hellweg Die Profi-baum\u00e4rkte Gmbh",
    "wof:placetype":"venue"
},
  "geometry": {"coordinates":[12.1217279434,51.0690994263],"type":"Point"}
}