{
  "type": "Feature",
  "properties": {
    "iso:country":"DE",
    "sg:city":"Hohnstein",
    "sg:postcode":"01848",
    "sg:province":"Sachsen",
    "wof:name":"Bieger Beteiligungsges. Mbh",
    "wof:placetype":"venue"
},
  "geometry": {"coordinates":[14.109665,50.980206],"type":"Point"}
}