{
  "type": "Feature",
  "properties": {
    "iso:country":"DE",
    "sg:address":"Seelower Stra\u00dfe 9",
    "sg:city":"Berlin",
    "sg:phone":"+49 30",
    "sg:postcode":"10439",
    "sg:province":"Berlin",
    "wof:name":"Zahnarztpraxis Dr. R\u00f6hnert",
    "wof:placetype":"venue"
},
  "geometry": {"coordinates":[13.410879,52.552139],"type":"Point"}
}