{
  "type": "Feature",
  "properties": {
    "iso:country":"DE",
    "sg:address":"Kressengartenstr. 2",
    "sg:city":"N\u00fcrnberg",
    "sg:postcode":"90402",
    "sg:province":"Bayern",
    "wof:name":"Good Leg Shoes Beteiligungs Gmbh",
    "wof:placetype":"venue"
},
  "geometry": {"coordinates":[11.100761,49.450333],"type":"Point"}
}