{
  "type": "Feature",
  "properties": {
    "iso:country":"DE",
    "sg:address":"Schmidtmannstr. 86",
    "sg:city":"Aschersleben",
    "sg:phone":"+49 3473/9600",
    "sg:postcode":"06449",
    "sg:province":"Sachsen-Anhalt",
    "wof:name":"Arbeitsgemeinschaft Der Polizeisportvereine D. Landes",
    "wof:placetype":"venue"
},
  "geometry": {"coordinates":[11.4840698242,51.754989624],"type":"Point"}
}