{
  "type": "Feature",
  "properties": {
    "iso:country":"DE",
    "sg:address":"Lindenberg 167",
    "sg:city":"P\u00f6cking",
    "sg:phone":"+49 8157/8944",
    "sg:postcode":"82343",
    "sg:province":"Bayern",
    "wof:name":"Karius Ingenieur",
    "wof:placetype":"venue"
},
  "geometry": {"coordinates":[11.2892198563,47.9654541016],"type":"Point"}
}