{
  "type": "Feature",
  "properties": {
    "iso:country":"DE",
    "sg:address":"Eisenberger Str. 23",
    "sg:city":"B\u00fcrgel",
    "sg:phone":"+49 36692/22250",
    "sg:postcode":"07616",
    "sg:province":"Th\u00fcringen",
    "wof:name":"Keramik Museum",
    "wof:placetype":"venue"
},
  "geometry": {"coordinates":[11.756749,50.94194],"type":"Point"}
}