{
  "type": "Feature",
  "properties": {
    "iso:country":"DE",
    "sg:address":"B\u00fcrgerm.-Lienhop-Str. 15",
    "sg:city":"Bassum",
    "sg:phone":"+49 4241/1441",
    "sg:postcode":"27211",
    "sg:province":"Niedersachsen",
    "wof:name":"Kliem Gartenbau",
    "wof:placetype":"venue"
},
  "geometry": {"coordinates":[8.737607,52.849815],"type":"Point"}
}