{
  "type": "Feature",
  "properties": {
    "iso:country":"DE",
    "sg:address":"Pichelsdorfer Str. 135",
    "sg:city":"Berlin",
    "sg:phone":"+49 30/3315000",
    "sg:postcode":"13595",
    "sg:province":"Berlin",
    "wof:name":"X-tra Tours Reiseb\u00fcro Gmbh",
    "wof:placetype":"venue"
},
  "geometry": {"coordinates":[13.1960849762,52.5265846252],"type":"Point"}
}