{
  "type": "Feature",
  "properties": {
    "iso:country":"DE",
    "sg:address":"Bodenmaiser Str. 39",
    "sg:city":"Regen",
    "sg:phone":"+49 9921/7849",
    "sg:postcode":"94209",
    "sg:province":"Bayern",
    "wof:name":"Gastst\u00e4tte Lorenz",
    "wof:placetype":"venue"
},
  "geometry": {"coordinates":[13.1303682327,48.974319458],"type":"Point"}
}