{
  "type": "Feature",
  "properties": {
    "iso:country":"DE",
    "sg:address":"G\u00f6dewitzer Weg 51 A",
    "sg:city":"Fienstedt",
    "sg:phone":"+49 34609/20256",
    "sg:postcode":"06198",
    "sg:province":"Sachsen-Anhalt",
    "wof:name":"T\u00fcrenfein F\u00e4rber",
    "wof:placetype":"venue"
},
  "geometry": {"coordinates":[11.788454,51.55196],"type":"Point"}
}