{
  "type": "Feature",
  "properties": {
    "iso:country":"DE",
    "sg:address":"Schwaigerner Str. 12",
    "sg:city":"Gemmingen",
    "sg:phone":"+49 7267/91210",
    "sg:postcode":"75050",
    "sg:province":"Baden-W\u00fcrttemberg",
    "wof:name":"Retzbach Drogeriemarkt Gmbh",
    "wof:placetype":"venue"
},
  "geometry": {"coordinates":[8.98379,49.156124],"type":"Point"}
}