{
  "type": "Feature",
  "properties": {
    "iso:country":"DE",
    "sg:address":"Thomas-M\u00fcntzer-Str. 4",
    "sg:city":"Wanzleben",
    "sg:phone":"+49 39209/3118",
    "sg:postcode":"39164",
    "sg:province":"Sachsen-Anhalt",
    "wof:name":"Raiffeisen-warengenossenschaft Wanzleben Eg",
    "wof:placetype":"venue"
},
  "geometry": {"coordinates":[11.443158,52.063324],"type":"Point"}
}