{
  "type": "Feature",
  "properties": {
    "iso:country":"DE",
    "sg:address":"Schweriner Str. 2b",
    "sg:city":"L\u00fcbesse",
    "sg:phone":"+49 4938/68222",
    "sg:postcode":"19077",
    "sg:province":"Mecklenburg-Vorpommern",
    "wof:name":"Ludwig Warncke Gmbh & Co. Kg",
    "wof:placetype":"venue"
},
  "geometry": {"coordinates":[11.463128,53.491753],"type":"Point"}
}