{
  "type": "Feature",
  "properties": {
    "iso:country":"DE",
    "sg:address":"Magnusweg 18",
    "sg:city":"Legau",
    "sg:phone":"+49 8330/1424",
    "sg:postcode":"87764",
    "sg:province":"Bayern",
    "wof:name":"Wolfgang Pallas",
    "wof:placetype":"venue"
},
  "geometry": {"coordinates":[10.12498,47.862896],"type":"Point"}
}