{
  "type": "Feature",
  "properties": {
    "iso:country":"DE",
    "sg:address":"S\u00fcdring 7",
    "sg:city":"M\u00fchlheim",
    "sg:phone":"+49 6108/73807",
    "sg:postcode":"63165",
    "sg:province":"Hessen",
    "wof:name":"Rolladen Epple",
    "wof:placetype":"venue"
},
  "geometry": {"coordinates":[8.844207,50.111385],"type":"Point"}
}