{
  "type": "Feature",
  "properties": {
    "iso:country":"DE",
    "sg:address":"Veterin\u00e4ramt",
    "sg:city":"Altenkirchen",
    "sg:postcode":"57610",
    "sg:province":"Rheinland-Pfalz",
    "wof:name":"Dr. Carl G\u00f6bels Tierarzt",
    "wof:placetype":"venue"
},
  "geometry": {"coordinates":[7.6399049759,50.6865081787],"type":"Point"}
}