{
  "type": "Feature",
  "properties": {
    "iso:country":"DE",
    "sg:address":"Marktplatz 17",
    "sg:city":"Aidenbach",
    "sg:postcode":"94501",
    "sg:province":"Bayern",
    "wof:name":"Mode- Und Bettenhaus Sturm Inh. Hermann",
    "wof:placetype":"venue"
},
  "geometry": {"coordinates":[13.0885028839,48.5674171448],"type":"Point"}
}