{
  "type": "Feature",
  "properties": {
    "iso:country":"DE",
    "sg:address":"Kurf\u00fcrstenstr. 88",
    "sg:city":"Koblenz",
    "sg:postcode":"56068",
    "sg:province":"Rheinland-Pfalz",
    "wof:name":"Vertrieb Von Service- Und Bonuskarten G. P. E. K.",
    "wof:placetype":"venue"
},
  "geometry": {"coordinates":[7.592989,50.346703],"type":"Point"}
}