{
  "type": "Feature",
  "properties": {
    "iso:country":"DE",
    "sg:address":"Marienstr. 1",
    "sg:city":"Neu-Ulm",
    "sg:phone":"+49 731/82002",
    "sg:postcode":"89231",
    "sg:province":"Bayern",
    "wof:name":"Dr. Med. Thomas Graf Arzt F\u00fcr Allgemeinmedizin",
    "wof:placetype":"venue"
},
  "geometry": {"coordinates":[9.9964704514,48.3953781128],"type":"Point"}
}