{
  "type": "Feature",
  "properties": {
    "iso:country":"DE",
    "sg:address":"Marktstr. 8",
    "sg:city":"W\u00f6rth",
    "sg:phone":"+49 7271/126069",
    "sg:postcode":"76744",
    "sg:province":"Rheinland-Pfalz",
    "wof:name":"Hubert Thill Rechtsanwalt",
    "wof:placetype":"venue"
},
  "geometry": {"coordinates":[8.0699548721,49.0640830994],"type":"Point"}
}