{
  "type": "Feature",
  "properties": {
    "iso:country":"DE",
    "sg:address":"Dr.-Hermann-Ludewig-Ring 14",
    "sg:city":"Rudolstadt",
    "sg:phone":"+49 3672/52160",
    "sg:postcode":"07407",
    "sg:province":"Th\u00fcringen",
    "wof:name":"Rabs Gmbh",
    "wof:placetype":"venue"
},
  "geometry": {"coordinates":[11.335059166,50.6902656555],"type":"Point"}
}