{
  "type": "Feature",
  "properties": {
    "iso:country":"DE",
    "sg:address":"Eschenstr 25",
    "sg:city":"N\u00fcrnberg",
    "sg:phone":"+49 911/940877",
    "sg:postcode":"90441",
    "sg:province":"Bayern",
    "wof:name":"V+e Consult Verpackungsberatung Und Engineering Gmbh",
    "wof:placetype":"venue"
},
  "geometry": {"coordinates":[11.07092,49.427666],"type":"Point"}
}