{
  "type": "Feature",
  "properties": {
    "iso:country":"DE",
    "sg:address":"Eutritzscher Str. 8",
    "sg:city":"Leipzig",
    "sg:postcode":"04105",
    "sg:province":"Sachsen",
    "wof:name":"Hans-ulrich K\u00fchne",
    "wof:placetype":"venue"
},
  "geometry": {"coordinates":[12.376681,51.348709],"type":"Point"}
}