{
  "type": "Feature",
  "properties": {
    "iso:country":"DE",
    "sg:address":"Wintergasse 60",
    "sg:city":"Weinheim",
    "sg:phone":"+49 6201/5060",
    "sg:postcode":"69469",
    "sg:province":"Baden-W\u00fcrttemberg",
    "wof:name":"Nordtek Textil- Und Kunstgewerbe",
    "wof:placetype":"venue"
},
  "geometry": {"coordinates":[8.6642665863,49.5252113342],"type":"Point"}
}