{
  "type": "Feature",
  "properties": {
    "iso:country":"DE",
    "sg:address":"Marktplatz 10",
    "sg:city":"Bad Urach",
    "sg:phone":"+49 7125/7764",
    "sg:postcode":"72574",
    "sg:province":"Baden-W\u00fcrttemberg",
    "wof:name":"Apotheke Am Markt",
    "wof:placetype":"venue"
},
  "geometry": {"coordinates":[9.39936,48.492901],"type":"Point"}
}