{
  "type": "Feature",
  "properties": {
    "iso:country":"DE",
    "sg:address":"Winsbergring 38::",
    "sg:city":"Hamburg",
    "sg:phone":"+49 4977/6194220",
    "sg:postcode":"22525",
    "sg:province":"Hamburg",
    "wof:name":"Adrians Kg",
    "wof:placetype":"venue"
},
  "geometry": {"coordinates":[7.9119329453,47.5622825623],"type":"Point"}
}