{
  "type": "Feature",
  "properties": {
    "iso:country":"DE",
    "sg:address":"Gebr\u00fcder-Heyn-Str. 17",
    "sg:city":"L\u00fcneburg",
    "sg:phone":"+49 4131/89130",
    "sg:postcode":"21337",
    "sg:province":"Niedersachsen",
    "wof:name":"Air Products Gmbh",
    "wof:placetype":"venue"
},
  "geometry": {"coordinates":[10.470495,53.241257],"type":"Point"}
}