{
  "type": "Feature",
  "properties": {
    "iso:country":"DE",
    "sg:address":"Am Gewerbegebiet 3",
    "sg:city":"Walderbach",
    "sg:phone":"+49 9464/260",
    "sg:postcode":"93194",
    "sg:province":"Bayern",
    "wof:name":"F. Schwarzfischer",
    "wof:placetype":"venue"
},
  "geometry": {"coordinates":[12.376161,49.193195],"type":"Point"}
}