{
  "type": "Feature",
  "properties": {
    "iso:country":"DE",
    "sg:address":"Herbertinger Str. 33",
    "sg:city":"Bad Saulgau",
    "sg:phone":"+49 7581/3406",
    "sg:postcode":"88348",
    "sg:province":"Baden-W\u00fcrttemberg",
    "wof:name":"Avia-tankstelle",
    "wof:placetype":"venue"
},
  "geometry": {"coordinates":[9.4917211533,48.0204467773],"type":"Point"}
}