{
  "type": "Feature",
  "properties": {
    "iso:country":"DE",
    "sg:address":"Am Hofacker 8",
    "sg:city":"Leverkusen",
    "sg:phone":"+49 2171/31030",
    "sg:postcode":"51381",
    "sg:province":"Nordrhein-Westfalen",
    "wof:name":"Brigitte Grube Steuerbevollm\u00e4chtigte",
    "wof:placetype":"venue"
},
  "geometry": {"coordinates":[7.0230731964,51.0825767517],"type":"Point"}
}