{
  "type": "Feature",
  "properties": {
    "iso:country":"DE",
    "sg:address":"M\u00fcntzer Weg 51",
    "sg:city":"Titz",
    "sg:phone":"+49 2463/1245",
    "sg:postcode":"52445",
    "sg:province":"Nordrhein-Westfalen",
    "wof:name":"Peter Von Wirth",
    "wof:placetype":"venue"
},
  "geometry": {"coordinates":[6.384065,51.006474],"type":"Point"}
}