{
  "type": "Feature",
  "properties": {
    "iso:country":"DE",
    "sg:address":"Adenauerstr. 16",
    "sg:city":"Altenbeken",
    "sg:phone":"+49 4952/5598660",
    "sg:postcode":"33184",
    "sg:province":"Nordrhein-Westfalen",
    "wof:name":"Schleupen Ag",
    "wof:placetype":"venue"
},
  "geometry": {"coordinates":[8.9318056107,51.7639808655],"type":"Point"}
}