{
  "type": "Feature",
  "properties": {
    "iso:country":"DE",
    "sg:address":"Schalker Str. 143",
    "sg:city":"Gelsenkirchen",
    "sg:phone":"+49 209/45856",
    "sg:postcode":"45881",
    "sg:province":"Nordrhein-Westfalen",
    "wof:name":"H. Van Haaren Masseur",
    "wof:placetype":"venue"
},
  "geometry": {"coordinates":[7.089401,51.519657],"type":"Point"}
}