{
  "type": "Feature",
  "properties": {
    "iso:country":"DE",
    "sg:address":"Weitseestr. 28",
    "sg:city":"Reit im Winkl",
    "sg:phone":"+49 8640/8866",
    "sg:postcode":"83242",
    "sg:province":"Bayern",
    "wof:name":"Marlies Welter",
    "wof:placetype":"venue"
},
  "geometry": {"coordinates":[12.471169,47.674191],"type":"Point"}
}