{
  "type": "Feature",
  "properties": {
    "iso:country":"DE",
    "sg:address":"Platz des Friedens 16",
    "sg:city":"Dippoldiswalde",
    "sg:phone":"+49 3504/614002",
    "sg:postcode":"01744",
    "sg:province":"Sachsen",
    "wof:name":"R. Schwind",
    "wof:placetype":"venue"
},
  "geometry": {"coordinates":[13.6549367905,50.8967170715],"type":"Point"}
}