{
  "type": "Feature",
  "properties": {
    "iso:country":"DE",
    "sg:address":"Max-von-Eyth-Str. 3",
    "sg:city":"Ismaning",
    "sg:phone":"+49 89/963046",
    "sg:postcode":"85737",
    "sg:province":"Bayern",
    "wof:name":"Pulse Engineering",
    "wof:placetype":"venue"
},
  "geometry": {"coordinates":[11.679088,48.233273],"type":"Point"}
}