{
  "type": "Feature",
  "properties": {
    "iso:country":"DE",
    "sg:address":"Coudraystr. 6",
    "sg:city":"Weimar",
    "sg:phone":"+49 3643/516331",
    "sg:postcode":"99423",
    "sg:province":"Th\u00fcringen",
    "wof:name":"Huk-coburg",
    "wof:placetype":"venue"
},
  "geometry": {"coordinates":[11.32330513,50.9807052612],"type":"Point"}
}