{
  "type": "Feature",
  "properties": {
    "iso:country":"DE",
    "sg:address":"G\u00f6hrder Str. 1",
    "sg:city":"Zernien",
    "sg:phone":"+49 5863/263",
    "sg:postcode":"29499",
    "sg:province":"Niedersachsen",
    "wof:name":"Hans-j. Eckloff & Sohn Malereibetrieb Gmbh",
    "wof:placetype":"venue"
},
  "geometry": {"coordinates":[10.885835,53.066608],"type":"Point"}
}