{
  "type": "Feature",
  "properties": {
    "iso:country":"DE",
    "sg:address":"Seebergstr. 45",
    "sg:city":"Gotha",
    "sg:phone":"+49 3621/854321",
    "sg:postcode":"99867",
    "sg:province":"Th\u00fcringen",
    "wof:name":"Claudia Stephan Masseur",
    "wof:placetype":"venue"
},
  "geometry": {"coordinates":[10.720158,50.943268],"type":"Point"}
}