{
  "type": "Feature",
  "properties": {
    "iso:country":"DE",
    "sg:address":"Raiffeisenstr. 5",
    "sg:city":"Vachendorf",
    "sg:phone":"+49 861/2201",
    "sg:postcode":"83377",
    "sg:province":"Bayern",
    "wof:name":"Dental Seifert Gmbh",
    "wof:placetype":"venue"
},
  "geometry": {"coordinates":[12.6039657593,47.8463363647],"type":"Point"}
}