{
  "type": "Feature",
  "properties": {
    "iso:country":"DE",
    "sg:address":"Barer Str. 37",
    "sg:city":"M\u00fcnchen",
    "sg:phone":"+49 89/2317100",
    "sg:postcode":"80799",
    "sg:province":"Bayern",
    "wof:name":"Neumeister Gmbh & Co. Grundst\u00fccks Kg",
    "wof:placetype":"venue"
},
  "geometry": {"coordinates":[11.5727834702,48.1506958008],"type":"Point"}
}