{
  "type": "Feature",
  "properties": {
    "iso:country":"DE",
    "sg:address":"Templiner Str. 3 a",
    "sg:city":"Joachimsthal",
    "sg:phone":"+49 33361/9811",
    "sg:postcode":"16247",
    "sg:province":"Brandenburg",
    "wof:name":"Seeadler-apotheke",
    "wof:placetype":"venue"
},
  "geometry": {"coordinates":[13.744139,52.978428],"type":"Point"}
}