{
  "type": "Feature",
  "properties": {
    "iso:country":"DE",
    "sg:address":"Am Tiefbrunnen 22",
    "sg:city":"Kulmbach",
    "sg:phone":"+49 9221/83161",
    "sg:postcode":"95326",
    "sg:province":"Bayern",
    "wof:name":"Dietmar Krause",
    "wof:placetype":"venue"
},
  "geometry": {"coordinates":[11.406559,50.104691],"type":"Point"}
}