{
  "type": "Feature",
  "properties": {
    "iso:country":"DE",
    "sg:address":"Notburgastr. 18",
    "sg:city":"Klettgau",
    "sg:phone":"+49 7742/5463",
    "sg:postcode":"79771",
    "sg:province":"Baden-W\u00fcrttemberg",
    "wof:name":"H. Ritzmann",
    "wof:placetype":"venue"
},
  "geometry": {"coordinates":[8.4645872116,47.6161117554],"type":"Point"}
}