{
  "type": "Feature",
  "properties": {
    "iso:country":"DE",
    "sg:address":"Waldstr. 36",
    "sg:city":"Herborn",
    "sg:phone":"+49 2772/42522",
    "sg:postcode":"35745",
    "sg:province":"Hessen",
    "wof:name":"Vogelpark Herborn-uckersdorf",
    "wof:placetype":"venue"
},
  "geometry": {"coordinates":[8.263031,50.700634],"type":"Point"}
}