{
  "type": "Feature",
  "properties": {
    "iso:country":"DE",
    "sg:address":"Am Milchbornsberg 20 a",
    "sg:city":"Bergisch Gladbach",
    "sg:phone":"+49 2204/55838",
    "sg:postcode":"51429",
    "sg:province":"Nordrhein-Westfalen",
    "wof:name":"Alfred Zerban",
    "wof:placetype":"venue"
},
  "geometry": {"coordinates":[7.1588258743,50.9687728882],"type":"Point"}
}