{
  "type": "Feature",
  "properties": {
    "iso:country":"DE",
    "sg:address":"Bodellerstr 2",
    "sg:city":"Dipperz",
    "sg:phone":"+49 6657/96250",
    "sg:postcode":"36160",
    "sg:province":"Hessen",
    "wof:name":"Leopold Feuerstein Holzwerke Gmbh & Co Kg",
    "wof:placetype":"venue"
},
  "geometry": {"coordinates":[9.7920074463,50.5423812866],"type":"Point"}
}