{
  "type": "Feature",
  "properties": {
    "iso:country":"DE",
    "sg:address":"Berliner Platz 1",
    "sg:city":"Bonn",
    "sg:phone":"+49 228/650166",
    "sg:postcode":"53111",
    "sg:province":"Nordrhein-Westfalen",
    "wof:name":"Pizzeria Roma",
    "wof:placetype":"venue"
},
  "geometry": {"coordinates":[7.0964479446,50.7367515564],"type":"Point"}
}