{
  "type": "Feature",
  "properties": {
    "iso:country":"DE",
    "sg:address":"Thomasstr. 7",
    "sg:city":"Bad Homburg",
    "sg:phone":"+49 6172/690272",
    "sg:postcode":"61348",
    "sg:province":"Hessen",
    "wof:name":"Christine Heinz Krankengymnastin",
    "wof:placetype":"venue"
},
  "geometry": {"coordinates":[8.617421,50.225796],"type":"Point"}
}