{
  "type": "Feature",
  "properties": {
    "iso:country":"DE",
    "sg:address":"Robert-Bosch-Str. 16",
    "sg:city":"K\u00f6nigsbronn",
    "sg:phone":"+49 7328/6435",
    "sg:postcode":"89551",
    "sg:province":"Baden-W\u00fcrttemberg",
    "wof:name":"Paula Pfeiffer Heissmangel",
    "wof:placetype":"venue"
},
  "geometry": {"coordinates":[10.1079063416,48.7443504333],"type":"Point"}
}