{
  "type": "Feature",
  "properties": {
    "iso:country":"DE",
    "sg:address":"Mellinghofer Str. 188",
    "sg:city":"M\u00fclheim",
    "sg:phone":"+49 208/70855",
    "sg:postcode":"45473",
    "sg:province":"Nordrhein-Westfalen",
    "wof:name":"Ilse Endejan Und Irmgard Mecke",
    "wof:placetype":"venue"
},
  "geometry": {"coordinates":[6.8840579987,51.4513435364],"type":"Point"}
}