{
  "type": "Feature",
  "properties": {
    "iso:country":"DE",
    "sg:address":"Lise-Meitner-Str. 20",
    "sg:city":"Langenfeld",
    "sg:phone":"+49 2173/73231",
    "sg:postcode":"40764",
    "sg:province":"Nordrhein-Westfalen",
    "wof:name":"Peter Kerkhoff",
    "wof:placetype":"venue"
},
  "geometry": {"coordinates":[6.9576711655,51.1379013062],"type":"Point"}
}