{
  "type": "Feature",
  "properties": {
    "iso:country":"DE",
    "sg:address":"Hajo-R\u00fcter-Str. 2",
    "sg:city":"Hochheim",
    "sg:phone":"+49 6146/83420",
    "sg:postcode":"65239",
    "sg:province":"Hessen",
    "wof:name":"Braun & Company Papierwaren Gmbh",
    "wof:placetype":"venue"
},
  "geometry": {"coordinates":[8.373184,50.014496],"type":"Point"}
}