{
  "type": "Feature",
  "properties": {
    "iso:country":"DE",
    "sg:address":"M\u00fcnsterstr. 9",
    "sg:city":"Bottrop",
    "sg:phone":"+49 2045/7152",
    "sg:postcode":"46244",
    "sg:province":"Nordrhein-Westfalen",
    "wof:name":"Dr. Roesner Gmbh",
    "wof:placetype":"venue"
},
  "geometry": {"coordinates":[6.9142971039,51.6107673645],"type":"Point"}
}