{
  "type": "Feature",
  "properties": {
    "iso:country":"DE",
    "sg:address":"Holzener Weg",
    "sg:city":"Nordendorf",
    "sg:phone":"+49 8273/2268",
    "sg:postcode":"86695",
    "sg:province":"Bayern",
    "wof:name":"Karl Rei\u00dfler",
    "wof:placetype":"venue"
},
  "geometry": {"coordinates":[10.8247804642,48.5872192383],"type":"Point"}
}