{
  "type": "Feature",
  "properties": {
    "iso:country":"DE",
    "sg:address":"Friedrich-Ebert-Str 28",
    "sg:city":"Treffurt",
    "sg:phone":"+49 36923/80884",
    "sg:postcode":"99830",
    "sg:province":"Th\u00fcringen",
    "wof:name":"Le-is Stahlm\u00f6bel Gmbh",
    "wof:placetype":"venue"
},
  "geometry": {"coordinates":[10.223509,51.138252],"type":"Point"}
}