{
  "type": "Feature",
  "properties": {
    "iso:country":"DE",
    "sg:address":"Waldstr. 2 1/2",
    "sg:city":"Bad W\u00f6rishofen",
    "sg:phone":"+49 8247/90115",
    "sg:postcode":"86825",
    "sg:province":"Bayern",
    "wof:name":"Hackspiel",
    "wof:placetype":"venue"
},
  "geometry": {"coordinates":[10.60299,48.004307],"type":"Point"}
}