{
  "type": "Feature",
  "properties": {
    "iso:country":"DE",
    "sg:address":"Nr. 21",
    "sg:city":"K\u00f6nigshain",
    "sg:postcode":"02829",
    "sg:province":"Sachsen",
    "wof:name":"Evangelisches Pfarramt K\u00f6nigshain",
    "wof:placetype":"venue"
},
  "geometry": {"coordinates":[14.9123773575,51.1761894226],"type":"Point"}
}