{
  "type": "Feature",
  "properties": {
    "iso:country":"DE",
    "sg:address":"Albert-Schweitzer-Str. 40",
    "sg:city":"Karlsruhe",
    "sg:phone":"+49 721/683456",
    "sg:postcode":"76139",
    "sg:province":"Baden-W\u00fcrttemberg",
    "wof:name":"Prof. Friedrich Mang Ingenieur",
    "wof:placetype":"venue"
},
  "geometry": {"coordinates":[8.4490604401,49.0484466553],"type":"Point"}
}