{
  "type": "Feature",
  "properties": {
    "iso:country":"DE",
    "sg:address":"Luitpoldstr. 10",
    "sg:city":"Hindelang",
    "sg:phone":"+49 8324/2184",
    "sg:postcode":"87541",
    "sg:province":"Bayern",
    "wof:name":"Pension Haus Rotspitze",
    "wof:placetype":"venue"
},
  "geometry": {"coordinates":[10.3874616623,47.5035743713],"type":"Point"}
}