{
  "type": "Feature",
  "properties": {
    "iso:country":"DE",
    "sg:address":"Kniphauser Str. 19",
    "sg:city":"Wilhelmshaven",
    "sg:phone":"+49 4421/81410",
    "sg:postcode":"26389",
    "sg:province":"Niedersachsen",
    "wof:name":"Karl Elsner",
    "wof:placetype":"venue"
},
  "geometry": {"coordinates":[8.0743169785,53.5376739502],"type":"Point"}
}