{
  "type": "Feature",
  "properties": {
    "iso:country":"DE",
    "sg:address":"Robert-Koch-Str. 6",
    "sg:city":"Illertissen",
    "sg:phone":"+49 7303/2084",
    "sg:postcode":"89257",
    "sg:province":"Bayern",
    "wof:name":"Dr. Reinhard K\u00f6ssinger Notar",
    "wof:placetype":"venue"
},
  "geometry": {"coordinates":[10.1057462692,48.2253379822],"type":"Point"}
}