{
  "type": "Feature",
  "properties": {
    "iso:country":"DE",
    "sg:address":"Hoffnung 26",
    "sg:city":"Schmalkalden",
    "sg:phone":"+49 3683/601905",
    "sg:postcode":"98574",
    "sg:province":"Th\u00fcringen",
    "wof:name":"G. Kraus Immobilienmakler",
    "wof:placetype":"venue"
},
  "geometry": {"coordinates":[10.4554185867,50.7215881348],"type":"Point"}
}