{
  "type": "Feature",
  "properties": {
    "iso:country":"DE",
    "sg:address":"Petristr. 13",
    "sg:city":"Heilbad Heiligenstadt",
    "sg:phone":"+49 3606/606610",
    "sg:postcode":"37308",
    "sg:province":"Th\u00fcringen",
    "wof:name":"Klaus Rheinl\u00e4nder Architekt",
    "wof:placetype":"venue"
},
  "geometry": {"coordinates":[10.134547,51.37521],"type":"Point"}
}