{
  "type": "Feature",
  "properties": {
    "iso:country":"DE",
    "sg:address":"Gartenstr. 4",
    "sg:city":"Mirow",
    "sg:postcode":"17252",
    "sg:province":"Mecklenburg-Vorpommern",
    "wof:name":"Katholisches Pfarramt Mirow",
    "wof:placetype":"venue"
},
  "geometry": {"coordinates":[12.817150116,53.2764587402],"type":"Point"}
}