{
  "type": "Feature",
  "properties": {
    "iso:country":"DE",
    "sg:address":"Blumenstr. 5",
    "sg:city":"Penzberg",
    "sg:phone":"+49 8856/3761",
    "sg:postcode":"82377",
    "sg:province":"Bayern",
    "wof:name":"Johann Auhuber",
    "wof:placetype":"venue"
},
  "geometry": {"coordinates":[11.3648462296,47.7615737915],"type":"Point"}
}