{
  "type": "Feature",
  "properties": {
    "iso:country":"DE",
    "sg:address":"Nordh\u00e4user Str. 55",
    "sg:city":"Ellrich",
    "sg:phone":"+49 36332/20566",
    "sg:postcode":"99755",
    "sg:province":"Th\u00fcringen",
    "wof:name":"Cafe Alte Backstube",
    "wof:placetype":"venue"
},
  "geometry": {"coordinates":[10.666063,51.584106],"type":"Point"}
}