{
  "type": "Feature",
  "properties": {
    "iso:country":"DE",
    "sg:address":"Keltenweg 2",
    "sg:city":"Speicher",
    "sg:phone":"+49 6562/8634",
    "sg:postcode":"54662",
    "sg:province":"Rheinland-Pfalz",
    "wof:name":"Erwin Hardt",
    "wof:placetype":"venue"
},
  "geometry": {"coordinates":[6.6487817764,49.9343643188],"type":"Point"}
}