{
  "type": "Feature",
  "properties": {
    "iso:country":"DE",
    "sg:address":"Brinkstr. 24",
    "sg:city":"Borgholzhausen",
    "sg:phone":"+49 5425/933255",
    "sg:postcode":"33829",
    "sg:province":"Nordrhein-Westfalen",
    "wof:name":"Sternengasse Gmbh",
    "wof:placetype":"venue"
},
  "geometry": {"coordinates":[8.2722234726,52.099407196],"type":"Point"}
}