{
  "type": "Feature",
  "properties": {
    "iso:country":"DE",
    "sg:address":"Dorfstr. 40",
    "sg:city":"Teichland",
    "sg:phone":"+49 35601/82152",
    "sg:postcode":"03185",
    "sg:province":"Brandenburg",
    "wof:name":"Siegmar Starosta",
    "wof:placetype":"venue"
},
  "geometry": {"coordinates":[14.4753055573,51.8099937439],"type":"Point"}
}