{
  "type": "Feature",
  "properties": {
    "iso:country":"DE",
    "sg:address":"Pfaffendorfer Str. 26",
    "sg:city":"Leipzig",
    "sg:phone":"+49 341/5641500",
    "sg:postcode":"04105",
    "sg:province":"Sachsen",
    "wof:name":"Karo Architekten Partnerschaft Heuer Rettich",
    "wof:placetype":"venue"
},
  "geometry": {"coordinates":[12.371348,51.347775],"type":"Point"}
}