{
  "type": "Feature",
  "properties": {
    "iso:country":"DE",
    "sg:address":"Kirchenstr. 45",
    "sg:city":"Bad Schwartau",
    "sg:postcode":"23611",
    "sg:province":"Schleswig-Holstein",
    "wof:name":"Asko-trade Verwaltungsges. Mbh",
    "wof:placetype":"venue"
},
  "geometry": {"coordinates":[10.6828660965,53.9172172546],"type":"Point"}
}