{
  "type": "Feature",
  "properties": {
    "iso:country":"DE",
    "sg:address":"Am Eisweiher 18",
    "sg:city":"Mosbach",
    "sg:phone":"+49 6261/92070",
    "sg:postcode":"74821",
    "sg:province":"Baden-W\u00fcrttemberg",
    "wof:name":"J. Schuler",
    "wof:placetype":"venue"
},
  "geometry": {"coordinates":[9.148009,49.363926],"type":"Point"}
}