{
  "type": "Feature",
  "properties": {
    "iso:country":"DE",
    "sg:address":"Westufer 3",
    "sg:city":"M\u00fcllrose",
    "sg:phone":"+49 33606/573",
    "sg:postcode":"15299",
    "sg:province":"Brandenburg",
    "wof:name":"Herbert Effnert",
    "wof:placetype":"venue"
},
  "geometry": {"coordinates":[14.4137935638,52.2345123291],"type":"Point"}
}