{
  "type": "Feature",
  "properties": {
    "iso:country":"DE",
    "sg:address":"Wiesenstr. 39",
    "sg:city":"Schorndorf",
    "sg:phone":"+49 7181/2050",
    "sg:postcode":"73614",
    "sg:province":"Baden-W\u00fcrttemberg",
    "wof:name":"M\u00f6ssner-verwaltungs- Gmbh",
    "wof:placetype":"venue"
},
  "geometry": {"coordinates":[9.538936,48.816975],"type":"Point"}
}