{
  "type": "Feature",
  "properties": {
    "iso:country":"DE",
    "sg:address":"Noppdorf 50a",
    "sg:city":"Viersen",
    "sg:phone":"+49 2162/31679",
    "sg:postcode":"41747",
    "sg:province":"Nordrhein-Westfalen",
    "wof:name":"H. Wiemes-kleinen Und G. Hellwig",
    "wof:placetype":"venue"
},
  "geometry": {"coordinates":[6.373347,51.258202],"type":"Point"}
}