{
  "type": "Feature",
  "properties": {
    "iso:country":"DE",
    "sg:address":"Gumpe 8",
    "sg:city":"Werther",
    "sg:postcode":"99735",
    "sg:province":"Th\u00fcringen",
    "wof:name":"H. G\u00f6x",
    "wof:placetype":"venue"
},
  "geometry": {"coordinates":[10.74979,51.464264],"type":"Point"}
}