{
  "type": "Feature",
  "properties": {
    "iso:country":"DE",
    "sg:address":"Haldenstr. 47",
    "sg:city":"Filderstadt",
    "sg:phone":"+49 711/705575",
    "sg:postcode":"70794",
    "sg:province":"Baden-W\u00fcrttemberg",
    "wof:name":"Harald Reiner Steuerberater",
    "wof:placetype":"venue"
},
  "geometry": {"coordinates":[9.2108449936,48.6756134033],"type":"Point"}
}