{
  "type": "Feature",
  "properties": {
    "iso:country":"DE",
    "sg:address":"Scharnweberstr. 136",
    "sg:city":"Berlin",
    "sg:phone":"+49 30/4178760",
    "sg:postcode":"13405",
    "sg:province":"Berlin",
    "wof:name":"Bonus Immobilien Betriebs- Und Verwaltungs Gmbh",
    "wof:placetype":"venue"
},
  "geometry": {"coordinates":[13.3263988495,52.5642280579],"type":"Point"}
}