{
  "type": "Feature",
  "properties": {
    "iso:country":"DE",
    "sg:address":"Wenkenstr. 97",
    "sg:city":"Bad Salzuflen",
    "sg:phone":"+49 5222/13478",
    "sg:postcode":"32105",
    "sg:province":"Nordrhein-Westfalen",
    "wof:name":"Pension Haus Andrea",
    "wof:placetype":"venue"
},
  "geometry": {"coordinates":[8.7588253021,52.0912513733],"type":"Point"}
}