{
  "type": "Feature",
  "properties": {
    "iso:country":"DE",
    "sg:address":"Marktstr. 20",
    "sg:city":"Rahden",
    "sg:phone":"+49 5771/97040",
    "sg:postcode":"32369",
    "sg:province":"Nordrhein-Westfalen",
    "wof:name":"Arno F. St\u00f6ver Und Partner Rechtsanw\u00e4lte Und Notar",
    "wof:placetype":"venue"
},
  "geometry": {"coordinates":[8.6174154282,52.4305915833],"type":"Point"}
}