{
  "type": "Feature",
  "properties": {
    "iso:country":"DE",
    "sg:address":"Hasberger Str. 202",
    "sg:city":"Delmenhorst",
    "sg:phone":"+49 4221/44013",
    "sg:postcode":"27751",
    "sg:province":"Niedersachsen",
    "wof:name":"Rudolf Licht Gmbh",
    "wof:placetype":"venue"
},
  "geometry": {"coordinates":[8.653425,53.067703],"type":"Point"}
}