{
  "type": "Feature",
  "properties": {
    "iso:country":"DE",
    "sg:address":"Parkstr. 40",
    "sg:city":"Willich",
    "sg:phone":"+49 2154/912691",
    "sg:postcode":"47877",
    "sg:province":"Nordrhein-Westfalen",
    "wof:name":"Bistro La Follia",
    "wof:placetype":"venue"
},
  "geometry": {"coordinates":[6.5442910194,51.2665481567],"type":"Point"}
}