{
  "type": "Feature",
  "properties": {
    "iso:country":"DE",
    "sg:address":"Rheinstr. 16",
    "sg:city":"Habichtswald",
    "sg:phone":"+49 5606/9096",
    "sg:postcode":"34317",
    "sg:province":"Hessen",
    "wof:name":"Joachim K\u00e4ufer",
    "wof:placetype":"venue"
},
  "geometry": {"coordinates":[9.313331604,51.3184967041],"type":"Point"}
}