{
  "type": "Feature",
  "properties": {
    "iso:country":"DE",
    "sg:address":"Lintorfer Str. 42",
    "sg:city":"Ratingen",
    "sg:postcode":"40878",
    "sg:province":"Nordrhein-Westfalen",
    "wof:name":"Hsr Bautr\u00e4ger- Und Projektentwicklungsges. Mbh",
    "wof:placetype":"venue"
},
  "geometry": {"coordinates":[6.8461050987,51.3005752563],"type":"Point"}
}