{
  "type": "Feature",
  "properties": {
    "iso:country":"DE",
    "sg:address":"Seem\u00fchle 5",
    "sg:city":"H\u00fcfingen",
    "sg:postcode":"78183",
    "sg:province":"Baden-W\u00fcrttemberg",
    "wof:name":"Erka Holding Gmbh",
    "wof:placetype":"venue"
},
  "geometry": {"coordinates":[8.47933,47.924011],"type":"Point"}
}