{
  "type": "Feature",
  "properties": {
    "iso:country":"DE",
    "sg:address":"Wilhelmstr. 2",
    "sg:city":"Neustadt",
    "sg:phone":"+49 9568/6668",
    "sg:postcode":"96465",
    "sg:province":"Bayern",
    "wof:name":"Beim Thomas",
    "wof:placetype":"venue"
},
  "geometry": {"coordinates":[11.1238384247,50.327545166],"type":"Point"}
}