{
  "type": "Feature",
  "properties": {
    "iso:country":"DE",
    "sg:address":"Hohenstaufenstr. 51",
    "sg:city":"Pforzheim",
    "sg:phone":"+49 7231/357145",
    "sg:postcode":"75177",
    "sg:province":"Baden-W\u00fcrttemberg",
    "wof:name":"Reumann",
    "wof:placetype":"venue"
},
  "geometry": {"coordinates":[8.709408,48.896408],"type":"Point"}
}