{
  "type": "Feature",
  "properties": {
    "iso:country":"DE",
    "sg:address":"Crottorfer Str. 45",
    "sg:city":"Reichshof",
    "sg:phone":"+49 2297/617",
    "sg:postcode":"51580",
    "sg:province":"Nordrhein-Westfalen",
    "wof:name":"Wilfried S\u00e4nger",
    "wof:placetype":"venue"
},
  "geometry": {"coordinates":[7.75754,50.929886],"type":"Point"}
}