{
  "type": "Feature",
  "properties": {
    "iso:country":"DE",
    "sg:address":"Jungstr. 8",
    "sg:city":"Wuppertal",
    "sg:phone":"+49 202/500342",
    "sg:postcode":"42277",
    "sg:province":"Nordrhein-Westfalen",
    "wof:name":"Qualit\u00e4tsmaler Pohli- Meisterbetrieb Gmbh",
    "wof:placetype":"venue"
},
  "geometry": {"coordinates":[7.210658,51.281952],"type":"Point"}
}