{
  "type": "Feature",
  "properties": {
    "iso:country":"DE",
    "sg:address":"Justus-von-Liebig-Siedlung 13",
    "sg:city":"Halberstadt",
    "sg:phone":"+49 3941/27780",
    "sg:postcode":"38820",
    "sg:province":"Sachsen-Anhalt",
    "wof:name":"Letz Gmbh",
    "wof:placetype":"venue"
},
  "geometry": {"coordinates":[11.028488,51.887337],"type":"Point"}
}