{
  "type": "Feature",
  "properties": {
    "iso:country":"DE",
    "sg:address":"Sprudelweg 11",
    "sg:city":"Bad Brambach",
    "sg:phone":"+49 37438/20216",
    "sg:postcode":"08648",
    "sg:province":"Sachsen",
    "wof:name":"Kurheim Elysium Inh. Waldemar Schr\u00f6der",
    "wof:placetype":"venue"
},
  "geometry": {"coordinates":[12.3024072647,50.221446991],"type":"Point"}
}