{
  "type": "Feature",
  "properties": {
    "iso:country":"DE",
    "sg:address":"Steinstr. 55",
    "sg:city":"Moers",
    "sg:phone":"+49 2841/22223",
    "sg:postcode":"47441",
    "sg:province":"Nordrhein-Westfalen",
    "wof:name":"Apotheke Am K\u00f6niglichen Hof Dr. Otto Paul Horst",
    "wof:placetype":"venue"
},
  "geometry": {"coordinates":[6.628612,51.450676],"type":"Point"}
}