{
  "type": "Feature",
  "properties": {
    "iso:country":"DE",
    "sg:address":"Birkenweg 12",
    "sg:city":"Frammersbach",
    "sg:phone":"+49 6020/1718",
    "sg:postcode":"97833",
    "sg:province":"Bayern",
    "wof:name":"Heribert Kunkel",
    "wof:placetype":"venue"
},
  "geometry": {"coordinates":[9.395289,50.061237],"type":"Point"}
}