{
  "type": "Feature",
  "properties": {
    "iso:country":"DE",
    "sg:address":"Antonsthaler Str. 9",
    "sg:city":"Lauter",
    "sg:phone":"+49 3771/29070",
    "sg:postcode":"08312",
    "sg:province":"Sachsen",
    "wof:name":"B\u00f6ttcher \u00d6fen Und Fliesen Gmbh",
    "wof:placetype":"venue"
},
  "geometry": {"coordinates":[12.7371444702,50.5578041077],"type":"Point"}
}