{
  "type": "Feature",
  "properties": {
    "iso:country":"DE",
    "sg:address":"Bitterfelder Str. 3a",
    "sg:city":"L\u00f6bnitz",
    "sg:phone":"+49 34208/72463",
    "sg:postcode":"04509",
    "sg:province":"Sachsen",
    "wof:name":"Monika Volk",
    "wof:placetype":"venue"
},
  "geometry": {"coordinates":[12.462099,51.592014],"type":"Point"}
}