{
  "type": "Feature",
  "properties": {
    "iso:country":"DE",
    "sg:address":"Hauptstr. 15a",
    "sg:city":"Oberbrombach",
    "sg:phone":"+49 6787/8375",
    "sg:postcode":"55767",
    "sg:province":"Rheinland-Pfalz",
    "wof:name":"Schmierstoffe Hartenberger E. K.",
    "wof:placetype":"venue"
},
  "geometry": {"coordinates":[7.261027813,49.6985015869],"type":"Point"}
}