{
  "type": "Feature",
  "properties": {
    "iso:country":"DE",
    "sg:address":"Schlo\u00dfstr. 10",
    "sg:city":"Rainau",
    "sg:phone":"+49 7961/3488",
    "sg:postcode":"73492",
    "sg:province":"Baden-W\u00fcrttemberg",
    "wof:name":"Wendelin May",
    "wof:placetype":"venue"
},
  "geometry": {"coordinates":[10.169977,48.920071],"type":"Point"}
}