{
  "type": "Feature",
  "properties": {
    "iso:country":"DE",
    "sg:address":"Christinastr. 4-6",
    "sg:city":"K\u00f6ln",
    "sg:phone":"+49 221/727664",
    "sg:postcode":"50733",
    "sg:province":"Nordrhein-Westfalen",
    "wof:name":"J. Wenzel",
    "wof:placetype":"venue"
},
  "geometry": {"coordinates":[6.952895,50.95974],"type":"Point"}
}