{
  "type": "Feature",
  "properties": {
    "iso:country":"DE",
    "sg:address":"Kranichstr. 20",
    "sg:city":"Nordhausen",
    "sg:phone":"+49 3631/972424",
    "sg:postcode":"99734",
    "sg:province":"Th\u00fcringen",
    "wof:name":"Kerstin Kinne-meister Rechtsanw\u00e4ltin",
    "wof:placetype":"venue"
},
  "geometry": {"coordinates":[10.7924089432,51.5035552979],"type":"Point"}
}