{
  "type": "Feature",
  "properties": {
    "iso:country":"DE",
    "sg:address":"Alemannenstr. 22",
    "sg:city":"Heitersheim",
    "sg:phone":"+49 7634/2089",
    "sg:postcode":"79423",
    "sg:province":"Baden-W\u00fcrttemberg",
    "wof:name":"Hans Peter Reimann Steuerberater",
    "wof:placetype":"venue"
},
  "geometry": {"coordinates":[7.6636571884,47.8745803833],"type":"Point"}
}