{
  "type": "Feature",
  "properties": {
    "iso:country":"DE",
    "sg:address":"Gartenstr. 3",
    "sg:city":"Heubach",
    "sg:phone":"+49 7173/4069",
    "sg:postcode":"73540",
    "sg:province":"Baden-W\u00fcrttemberg",
    "wof:name":"Josef Schmid Inh. Walter Schmid",
    "wof:placetype":"venue"
},
  "geometry": {"coordinates":[9.9338645935,48.7940101624],"type":"Point"}
}