{
  "type": "Feature",
  "properties": {
    "iso:country":"DE",
    "sg:address":"Heidestr. 20 b",
    "sg:city":"Berlin",
    "sg:phone":"+49 30/2614400",
    "sg:postcode":"10557",
    "sg:province":"Berlin",
    "wof:name":"Nostalgic Art",
    "wof:placetype":"venue"
},
  "geometry": {"coordinates":[13.363735199,52.5356178284],"type":"Point"}
}