{
  "type": "Feature",
  "properties": {
    "iso:country":"DE",
    "sg:address":"Unterheydener Str. 12",
    "sg:city":"M\u00f6nchengladbach",
    "sg:phone":"+49 2166/850380",
    "sg:postcode":"41236",
    "sg:province":"Nordrhein-Westfalen",
    "wof:name":"Schneider Verwaltungs-gmbh",
    "wof:placetype":"venue"
},
  "geometry": {"coordinates":[6.4494872093,51.1566619873],"type":"Point"}
}