{
  "type": "Feature",
  "properties": {
    "iso:country":"DE",
    "sg:address":"Osterbrocker Str. 2",
    "sg:city":"Geeste",
    "sg:phone":"+49 5907/7202",
    "sg:postcode":"49744",
    "sg:province":"Niedersachsen",
    "wof:name":"H. Lonnemann",
    "wof:placetype":"venue"
},
  "geometry": {"coordinates":[7.268524,52.600681],"type":"Point"}
}