{
  "type": "Feature",
  "properties": {
    "iso:country":"DE",
    "sg:address":"An der Qu\u00f6bbe 11",
    "sg:city":"Boizenburg",
    "sg:postcode":"19258",
    "sg:province":"Mecklenburg-Vorpommern",
    "wof:name":"Wasserversorgung Und Abwasser- Behandlung Schwerin",
    "wof:placetype":"venue"
},
  "geometry": {"coordinates":[10.7235803604,53.376789093],"type":"Point"}
}