{
  "type": "Feature",
  "properties": {
    "iso:country":"DE",
    "sg:address":"Daimlerstr. 16",
    "sg:city":"Stockelsdorf",
    "sg:phone":"+49 451/499910",
    "sg:postcode":"23617",
    "sg:province":"Schleswig-Holstein",
    "wof:name":"Gebr\u00fcder Heick Heimtextilien Gmbh",
    "wof:placetype":"venue"
},
  "geometry": {"coordinates":[10.6230363846,53.8930931091],"type":"Point"}
}