{
  "type": "Feature",
  "properties": {
    "iso:country":"DE",
    "sg:address":"Linnenbr\u00fcggerstr. 25",
    "sg:city":"M\u00fcnchen",
    "sg:postcode":"81829",
    "sg:province":"Bayern",
    "wof:name":"Millass Consulting Unternehmensberatung Gmbh",
    "wof:placetype":"venue"
},
  "geometry": {"coordinates":[11.6773338318,48.132019043],"type":"Point"}
}