{
  "type": "Feature",
  "properties": {
    "iso:country":"DE",
    "sg:address":"Zuger Str. 19-20",
    "sg:city":"Brand-Erbisdorf",
    "sg:phone":"+49 37322/80435",
    "sg:postcode":"09618",
    "sg:province":"Sachsen",
    "wof:name":"Storch Transportges. Mbh",
    "wof:placetype":"venue"
},
  "geometry": {"coordinates":[13.3285942078,50.872013092],"type":"Point"}
}