{
  "type": "Feature",
  "properties": {
    "iso:country":"DE",
    "sg:address":"Witte Sand 14 a",
    "sg:city":"Coesfeld",
    "sg:phone":"+49 2541/82373",
    "sg:postcode":"48653",
    "sg:province":"Nordrhein-Westfalen",
    "wof:name":"Frank Und Corina Schulz",
    "wof:placetype":"venue"
},
  "geometry": {"coordinates":[7.1258158684,51.9305000305],"type":"Point"}
}