{
  "type": "Feature",
  "properties": {
    "iso:country":"DE",
    "sg:address":"Heinrichstr. 81",
    "sg:city":"Angerm\u00fcnde",
    "sg:phone":"+49 3331/32343",
    "sg:postcode":"16278",
    "sg:province":"Brandenburg",
    "wof:name":"Gasversorgung Frankfurt An Der Oder Und Umgebung Gmbh",
    "wof:placetype":"venue"
},
  "geometry": {"coordinates":[13.9978427887,53.0184783936],"type":"Point"}
}