{
  "type": "Feature",
  "properties": {
    "iso:country":"DE",
    "sg:address":"Saseler Damm 9",
    "sg:city":"Hamburg",
    "sg:postcode":"22395",
    "sg:province":"Hamburg",
    "wof:name":"Net Check Gmbh",
    "wof:placetype":"venue"
},
  "geometry": {"coordinates":[10.1009206772,53.6543540955],"type":"Point"}
}