{
  "type": "Feature",
  "properties": {
    "iso:country":"DE",
    "sg:address":"Kaiserstr. 113",
    "sg:city":"Bruchm\u00fchlbach-Miesau",
    "sg:phone":"+49 6372/1247",
    "sg:postcode":"66892",
    "sg:province":"Rheinland-Pfalz",
    "wof:name":"Hermann Schmidt",
    "wof:placetype":"venue"
},
  "geometry": {"coordinates":[7.416187,49.376923],"type":"Point"}
}