{
  "type": "Feature",
  "properties": {
    "iso:country":"DE",
    "sg:address":"Breslauer Str. 388",
    "sg:city":"N\u00fcrnberg",
    "sg:phone":"+49 911/9897850",
    "sg:postcode":"90471",
    "sg:province":"Bayern",
    "wof:name":"Techno-licht Oem Distribution Gmbh",
    "wof:placetype":"venue"
},
  "geometry": {"coordinates":[11.126244545,49.4011459351],"type":"Point"}
}