{
  "type": "Feature",
  "properties": {
    "iso:country":"DE",
    "sg:address":"Bundesstr. 15",
    "sg:city":"Uslar",
    "sg:phone":"+49 5571/5530",
    "sg:postcode":"37170",
    "sg:province":"Niedersachsen",
    "wof:name":"G\u00fcnter Schultze",
    "wof:placetype":"venue"
},
  "geometry": {"coordinates":[9.6804027557,51.6542053223],"type":"Point"}
}