{
  "type": "Feature",
  "properties": {
    "iso:country":"DE",
    "sg:address":"S\u00fcdliche M\u00fcnchner Str 26",
    "sg:city":"Gr\u00fcnwald",
    "sg:phone":"+49 89/64919513",
    "sg:postcode":"82031",
    "sg:province":"Bayern",
    "wof:name":"Wieser Edv Systemhaus Gmbh",
    "wof:placetype":"venue"
},
  "geometry": {"coordinates":[11.5288543701,48.0453491211],"type":"Point"}
}