{
  "type": "Feature",
  "properties": {
    "iso:country":"DE",
    "sg:address":"Lehnheimer Weg 14",
    "sg:city":"Gr\u00fcnberg",
    "sg:phone":"+49 6401/90273",
    "sg:postcode":"35305",
    "sg:province":"Hessen",
    "wof:name":"Dieter Krech Elektroinstallation",
    "wof:placetype":"venue"
},
  "geometry": {"coordinates":[8.960993,50.596432],"type":"Point"}
}