{
  "type": "Feature",
  "properties": {
    "iso:country":"DE",
    "sg:address":"Auf dem Rade 12",
    "sg:city":"Ronnenberg",
    "sg:phone":"+49 511/466643",
    "sg:postcode":"30952",
    "sg:province":"Niedersachsen",
    "wof:name":"N. Kopper \u00c4nderungsschneiderei",
    "wof:placetype":"venue"
},
  "geometry": {"coordinates":[9.665692,52.344826],"type":"Point"}
}