{
  "type": "Feature",
  "properties": {
    "iso:country":"DE",
    "sg:address":"Schlo\u00dfstr. 35",
    "sg:city":"Koblenz",
    "sg:phone":"+49 261/300160",
    "sg:postcode":"56068",
    "sg:province":"Rheinland-Pfalz",
    "wof:name":"Piano Thilemann",
    "wof:placetype":"venue"
},
  "geometry": {"coordinates":[7.5949449539,50.356590271],"type":"Point"}
}