{
  "type": "Feature",
  "properties": {
    "iso:country":"DE",
    "sg:address":"Karl-Marx-Strasse 205",
    "sg:city":"Aachen",
    "sg:phone":"+49 241/61599",
    "sg:postcode":"52066",
    "sg:province":"Nordrhein-Westfalen",
    "wof:name":"Wirtschaftsberatung Hans-peter Boekmann",
    "wof:placetype":"venue"
},
  "geometry": {"coordinates":[6.101467,50.756256],"type":"Point"}
}