{
  "type": "Feature",
  "properties": {
    "iso:country":"DE",
    "sg:address":"Dahlener Str. 1",
    "sg:city":"Torgau",
    "sg:phone":"+49 3421/72900",
    "sg:postcode":"04860",
    "sg:province":"Sachsen",
    "wof:name":"Kaufland",
    "wof:placetype":"venue"
},
  "geometry": {"coordinates":[13.001244545,51.5552825928],"type":"Point"}
}