{
  "type": "Feature",
  "properties": {
    "iso:country":"DE",
    "sg:address":"Weinbergstr. 83",
    "sg:city":"Templin",
    "sg:phone":"+49 3987/6992",
    "sg:postcode":"17268",
    "sg:province":"Brandenburg",
    "wof:name":"Eiscafe Mickis Eisluke Inh. B. Kaminski",
    "wof:placetype":"venue"
},
  "geometry": {"coordinates":[13.513063,53.128536],"type":"Point"}
}