{
  "type": "Feature",
  "properties": {
    "iso:country":"DE",
    "sg:address":"Quetziner Str. 7",
    "sg:city":"Plau",
    "sg:phone":"+49 38735/44690",
    "sg:postcode":"19395",
    "sg:province":"Mecklenburg-Vorpommern",
    "wof:name":"Wolfgang Papke",
    "wof:placetype":"venue"
},
  "geometry": {"coordinates":[12.1918888092,53.3706474304],"type":"Point"}
}