{
  "type": "Feature",
  "properties": {
    "iso:country":"DE",
    "sg:address":"Klusstr. 4",
    "sg:city":"Detmold",
    "sg:phone":"+49 5231/22314",
    "sg:postcode":"32756",
    "sg:province":"Nordrhein-Westfalen",
    "wof:name":"Cieslik Gmbh & Co. Kg",
    "wof:placetype":"venue"
},
  "geometry": {"coordinates":[8.887596,51.939739],"type":"Point"}
}