{
  "type": "Feature",
  "properties": {
    "iso:country":"DE",
    "sg:address":"Liebfrauenstr. 61",
    "sg:city":"Eschweiler",
    "sg:phone":"+49 2403/35905",
    "sg:postcode":"52249",
    "sg:province":"Nordrhein-Westfalen",
    "wof:name":"R. Ziemons",
    "wof:placetype":"venue"
},
  "geometry": {"coordinates":[6.2618560791,50.8244590759],"type":"Point"}
}