{
  "type": "Feature",
  "properties": {
    "iso:country":"DE",
    "sg:address":"Kirchstr. 2",
    "sg:city":"Hemmingen",
    "sg:phone":"+49 511/415329",
    "sg:postcode":"30966",
    "sg:province":"Niedersachsen",
    "wof:name":"Ahrens Und B\u00f6bel Gmbh",
    "wof:placetype":"venue"
},
  "geometry": {"coordinates":[9.7572746277,52.3126182556],"type":"Point"}
}