{
  "type": "Feature",
  "properties": {
    "iso:country":"DE",
    "sg:address":"Schweriner Str. 12",
    "sg:city":"Hamburg",
    "sg:phone":"+49 40/6757920",
    "sg:postcode":"22143",
    "sg:province":"Hamburg",
    "wof:name":"Bps Treuhand Gmbh Steuerberatungsges.",
    "wof:placetype":"venue"
},
  "geometry": {"coordinates":[10.1584205627,53.6050491333],"type":"Point"}
}