{
  "type": "Feature",
  "properties": {
    "iso:country":"DE",
    "sg:address":"Holter Landstr. 51",
    "sg:city":"Verl",
    "sg:phone":"+49 5246/3605",
    "sg:postcode":"33415",
    "sg:province":"Nordrhein-Westfalen",
    "wof:name":"Heinrich Koch E. K.",
    "wof:placetype":"venue"
},
  "geometry": {"coordinates":[8.5628700256,51.87657547],"type":"Point"}
}