{
  "type": "Feature",
  "properties": {
    "iso:country":"DE",
    "sg:address":"Friedrich-H\u00f6lderlin-Weg 26",
    "sg:city":"Speyer",
    "sg:phone":"+49 6232/93563",
    "sg:postcode":"67346",
    "sg:province":"Rheinland-Pfalz",
    "wof:name":"Werner Hock",
    "wof:placetype":"venue"
},
  "geometry": {"coordinates":[8.413310051,49.3236694336],"type":"Point"}
}