{
  "type": "Feature",
  "properties": {
    "iso:country":"DE",
    "sg:address":"Lindlarer Str. 94",
    "sg:city":"Overath",
    "sg:phone":"+49 2204/71965",
    "sg:postcode":"51491",
    "sg:province":"Nordrhein-Westfalen",
    "wof:name":"Adele Kierspel",
    "wof:placetype":"venue"
},
  "geometry": {"coordinates":[7.2391219139,50.9605026245],"type":"Point"}
}