{
  "type": "Feature",
  "properties": {
    "iso:country":"DE",
    "sg:address":"Bachstr. 3",
    "sg:city":"Osterhofen",
    "sg:phone":"+49 9932/1693",
    "sg:postcode":"94486",
    "sg:province":"Bayern",
    "wof:name":"Johann Heindl",
    "wof:placetype":"venue"
},
  "geometry": {"coordinates":[13.0183467865,48.6937255859],"type":"Point"}
}