{
  "type": "Feature",
  "properties": {
    "iso:country":"DE",
    "sg:address":"Robert-Schuman-Str. 151",
    "sg:city":"Kr\u00f6v",
    "sg:phone":"+49 6541/6432",
    "sg:postcode":"54536",
    "sg:province":"Rheinland-Pfalz",
    "wof:name":"Hans Schneiders",
    "wof:placetype":"venue"
},
  "geometry": {"coordinates":[7.0818572044,49.9771347046],"type":"Point"}
}