{
  "type": "Feature",
  "properties": {
    "iso:country":"DE",
    "sg:address":"Breite Str. 27",
    "sg:city":"Gro\u00dfalsleben",
    "sg:postcode":"39387",
    "sg:province":"Sachsen-Anhalt",
    "wof:name":"Hans-otto Ilse",
    "wof:placetype":"venue"
},
  "geometry": {"coordinates":[11.229539,52.028641],"type":"Point"}
}