{
  "type": "Feature",
  "properties": {
    "iso:country":"DE",
    "sg:address":"Hauptstr. 46",
    "sg:city":"Werlte",
    "sg:phone":"+49 5951/3334",
    "sg:postcode":"49757",
    "sg:province":"Niedersachsen",
    "wof:name":"Buch- Und Schreibwaren Wevering E. Kfm.",
    "wof:placetype":"venue"
},
  "geometry": {"coordinates":[7.6805782318,52.8510322571],"type":"Point"}
}