{
  "type": "Feature",
  "properties": {
    "iso:country":"DE",
    "sg:address":"Friesenstr. 1",
    "sg:city":"L\u00fcdenscheid",
    "sg:phone":"+49 2351/20911",
    "sg:postcode":"58509",
    "sg:province":"Nordrhein-Westfalen",
    "wof:name":"Kornkammer",
    "wof:placetype":"venue"
},
  "geometry": {"coordinates":[7.6163668633,51.2200775146],"type":"Point"}
}