{
  "type": "Feature",
  "properties": {
    "iso:country":"DE",
    "sg:address":"Promenade 6",
    "sg:city":"Bad Lauterberg",
    "sg:phone":"+49 5524/3617",
    "sg:postcode":"37431",
    "sg:province":"Niedersachsen",
    "wof:name":"Praxis Albrecht Und Dr. Med. Markgraf",
    "wof:placetype":"venue"
},
  "geometry": {"coordinates":[10.4695796967,51.6301345825],"type":"Point"}
}