{
  "type": "Feature",
  "properties": {
    "iso:country":"DE",
    "sg:address":"Simmersh\u00e4user Str. 101A",
    "sg:city":"Kassel",
    "sg:phone":"+49 561/814222",
    "sg:postcode":"34125",
    "sg:province":"Hessen",
    "wof:name":"Reinhard Ritter",
    "wof:placetype":"venue"
},
  "geometry": {"coordinates":[9.5120077133,51.3405570984],"type":"Point"}
}