{
  "type": "Feature",
  "properties": {
    "iso:country":"DE",
    "sg:address":"Antoniusstr. 83",
    "sg:city":"Kaarst",
    "sg:phone":"+49 2131/602049",
    "sg:postcode":"41564",
    "sg:province":"Nordrhein-Westfalen",
    "wof:name":"Altes Bierst\u00fcbchen",
    "wof:placetype":"venue"
},
  "geometry": {"coordinates":[6.5902709961,51.2192077637],"type":"Point"}
}