{
  "type": "Feature",
  "properties": {
    "iso:country":"DE",
    "sg:address":"Zum Sperlingsfeld 1",
    "sg:city":"Leezen",
    "sg:phone":"+49 3866/492656",
    "sg:postcode":"19067",
    "sg:province":"Mecklenburg-Vorpommern",
    "wof:name":"Apotheke Am Schlo\u00df Leezen Apoth. Katrin Seehase E. Kfr.",
    "wof:placetype":"venue"
},
  "geometry": {"coordinates":[11.49643,53.659328],"type":"Point"}
}