{
  "type": "Feature",
  "properties": {
    "iso:country":"DE",
    "sg:address":"Bahnhofstr. 63",
    "sg:city":"Bad Pyrmont",
    "sg:phone":"+49 5281/960800",
    "sg:postcode":"31812",
    "sg:province":"Niedersachsen",
    "wof:name":"Autoverleih Dreyer",
    "wof:placetype":"venue"
},
  "geometry": {"coordinates":[9.266579,51.977818],"type":"Point"}
}