{
  "type": "Feature",
  "properties": {
    "iso:country":"DE",
    "sg:address":"Jessenstr. 3",
    "sg:city":"Hamburg",
    "sg:phone":"+49 40/3068330",
    "sg:postcode":"22767",
    "sg:province":"Hamburg",
    "wof:name":"Wisserodt Gesellschaft F\u00fcr Ingenieurleistungen Im",
    "wof:placetype":"venue"
},
  "geometry": {"coordinates":[9.9460115433,53.5509529114],"type":"Point"}
}