{
  "type": "Feature",
  "properties": {
    "iso:country":"DE",
    "sg:address":"Pestalozzistr. 72a",
    "sg:city":"D\u00fcsseldorf",
    "sg:phone":"+49 211/504624",
    "sg:postcode":"40549",
    "sg:province":"Nordrhein-Westfalen",
    "wof:name":"Erwin Schubert",
    "wof:placetype":"venue"
},
  "geometry": {"coordinates":[6.718836,51.229118],"type":"Point"}
}