{
  "type": "Feature",
  "properties": {
    "iso:country":"DE",
    "sg:address":"Winklerstr. 24",
    "sg:city":"N\u00fcrnberg",
    "sg:phone":"+49 911/447788",
    "sg:postcode":"90403",
    "sg:province":"Bayern",
    "wof:name":"Abadat Ag",
    "wof:placetype":"venue"
},
  "geometry": {"coordinates":[11.075971,49.454777],"type":"Point"}
}