{
  "type": "Feature",
  "properties": {
    "iso:country":"DE",
    "sg:address":"Holbeinstr. 6",
    "sg:city":"Magdeburg",
    "sg:phone":"+49 391/6224102",
    "sg:postcode":"39112",
    "sg:province":"Sachsen-Anhalt",
    "wof:name":"Harald Heise",
    "wof:placetype":"venue"
},
  "geometry": {"coordinates":[11.609301,52.117252],"type":"Point"}
}