{
  "type": "Feature",
  "properties": {
    "iso:country":"DE",
    "sg:address":"Schlachthofstr.",
    "sg:city":"Oldenburg",
    "sg:postcode":"26135",
    "sg:province":"Niedersachsen",
    "wof:name":"Georg Krinke",
    "wof:placetype":"venue"
},
  "geometry": {"coordinates":[8.2636995316,53.108291626],"type":"Point"}
}