{
  "type": "Feature",
  "properties": {
    "iso:country":"DE",
    "sg:address":"Iserlohner Str. 177",
    "sg:city":"Unna",
    "sg:phone":"+49 2303/81475",
    "sg:postcode":"59427",
    "sg:province":"Nordrhein-Westfalen",
    "wof:name":"Erika Stoltefu\u00df Gmbh",
    "wof:placetype":"venue"
},
  "geometry": {"coordinates":[7.702589035,51.502166748],"type":"Point"}
}