{
  "type": "Feature",
  "properties": {
    "iso:country":"DE",
    "sg:address":"Wildstr. 20",
    "sg:city":"Duisburg",
    "sg:phone":"+49 4920/3993680",
    "sg:postcode":"47057",
    "sg:province":"Nordrhein-Westfalen",
    "wof:name":"Duisburger Kettenfabrik Und Hammerwerk H Dhone Gmbh & Co Kg",
    "wof:placetype":"venue"
},
  "geometry": {"coordinates":[6.787685,51.419502],"type":"Point"}
}