{
  "type": "Feature",
  "properties": {
    "iso:country":"DE",
    "sg:address":"Bahnhofstr.11/Eingang Baustr.",
    "sg:city":"Ludwigslust",
    "sg:phone":"+49 3874",
    "sg:postcode":"19288",
    "sg:province":"Mecklenburg-Vorpommern",
    "wof:name":"Baulaser & Funktechnik Dipl.-ing. Rolf Meincke",
    "wof:placetype":"venue"
},
  "geometry": {"coordinates":[11.4954595566,53.3244361877],"type":"Point"}
}