{
  "type": "Feature",
  "properties": {
    "iso:country":"DE",
    "sg:address":"An der Grotte 13",
    "sg:city":"Meppen",
    "sg:phone":"+49 5931/89600",
    "sg:postcode":"49716",
    "sg:province":"Niedersachsen",
    "wof:name":"Iak",
    "wof:placetype":"venue"
},
  "geometry": {"coordinates":[7.2302770615,52.7165031433],"type":"Point"}
}