{
  "type": "Feature",
  "properties": {
    "iso:country":"DE",
    "sg:address":"Lehrberg 2",
    "sg:city":"Hohenwestedt",
    "sg:phone":"+49 4871/3287",
    "sg:postcode":"24594",
    "sg:province":"Schleswig-Holstein",
    "wof:name":"Carlas Und Erikas Modest\u00fcbchen",
    "wof:placetype":"venue"
},
  "geometry": {"coordinates":[9.657525,54.09161],"type":"Point"}
}