{
  "type": "Feature",
  "properties": {
    "iso:country":"DE",
    "sg:address":"Rosenstr. 22",
    "sg:city":"Homburg",
    "sg:postcode":"66424",
    "sg:province":"Saarland",
    "wof:name":"Stadtb\u00fccherei Zweigstelle",
    "wof:placetype":"venue"
},
  "geometry": {"coordinates":[7.32462,49.252869],"type":"Point"}
}