{
  "type": "Feature",
  "properties": {
    "iso:country":"DE",
    "sg:address":"Immigrather Str. 36",
    "sg:city":"Langenfeld",
    "sg:phone":"+49 2173/72246",
    "sg:postcode":"40764",
    "sg:province":"Nordrhein-Westfalen",
    "wof:name":"Siegfried Hoppe",
    "wof:placetype":"venue"
},
  "geometry": {"coordinates":[6.9521889687,51.1231994629],"type":"Point"}
}