{
  "type": "Feature",
  "properties": {
    "iso:country":"DE",
    "sg:address":"Leibnizstr. 7-9",
    "sg:city":"Calw",
    "sg:phone":"+49 4970/5120966",
    "sg:postcode":"75365",
    "sg:province":"Baden-W\u00fcrttemberg",
    "wof:name":"Cnc - Technische Anlagen Waidelich Gmbh",
    "wof:placetype":"venue"
},
  "geometry": {"coordinates":[8.762189,48.705051],"type":"Point"}
}