{
  "type": "Feature",
  "properties": {
    "iso:country":"DE",
    "sg:address":"Dobelstr. 9",
    "sg:city":"Langenbach",
    "sg:postcode":"85416",
    "sg:province":"Bayern",
    "wof:name":"Euralis Saatzucht Gmbh",
    "wof:placetype":"venue"
},
  "geometry": {"coordinates":[11.881114,48.433971],"type":"Point"}
}