{
  "type": "Feature",
  "properties": {
    "iso:country":"DE",
    "sg:address":"Sch\u00fctzenanger 4",
    "sg:city":"G\u00f6ttingen",
    "sg:phone":"+49 4955/1307190",
    "sg:postcode":"37081",
    "sg:province":"Niedersachsen",
    "wof:name":"Tritech Computer-u. Softwaredienstleistungs-gmbh",
    "wof:placetype":"venue"
},
  "geometry": {"coordinates":[9.9246044159,51.5416641235],"type":"Point"}
}