{
  "type": "Feature",
  "properties": {
    "iso:country":"DE",
    "sg:address":"Am Wilden Graben 30",
    "sg:city":"Bad Langensalza",
    "sg:postcode":"99947",
    "sg:province":"Th\u00fcringen",
    "wof:name":"Seebers Fischmarkt",
    "wof:placetype":"venue"
},
  "geometry": {"coordinates":[10.6457252502,51.1092643738],"type":"Point"}
}