{
  "type": "Feature",
  "properties": {
    "iso:country":"DE",
    "sg:address":"Auberg 17",
    "sg:city":"Tiefenbach",
    "sg:phone":"+49 8709/3724",
    "sg:postcode":"84184",
    "sg:province":"Bayern",
    "wof:name":"Dr. G\u00fcnther Frank Tierarzt",
    "wof:placetype":"venue"
},
  "geometry": {"coordinates":[12.0982151031,48.5121154785],"type":"Point"}
}