{
  "type": "Feature",
  "properties": {
    "iso:country":"DE",
    "sg:address":"Hauptstr. 21",
    "sg:city":"Geislingen",
    "sg:phone":"+49 7331/41778",
    "sg:postcode":"73312",
    "sg:province":"Baden-W\u00fcrttemberg",
    "wof:name":"Wilhelm Kessler Inh. Hans Adolf Schall",
    "wof:placetype":"venue"
},
  "geometry": {"coordinates":[9.843535,48.61409],"type":"Point"}
}