{
  "type": "Feature",
  "properties": {
    "iso:country":"DE",
    "sg:address":"Dornstetter Str. 1",
    "sg:city":"Glatten",
    "sg:phone":"+49 7443/8959",
    "sg:postcode":"72293",
    "sg:province":"Baden-W\u00fcrttemberg",
    "wof:name":"Helmut Trik",
    "wof:placetype":"venue"
},
  "geometry": {"coordinates":[8.51305,48.444046],"type":"Point"}
}