{
  "type": "Feature",
  "properties": {
    "iso:country":"DE",
    "sg:address":"Jahnstr. 27-29",
    "sg:city":"Mainhausen",
    "sg:phone":"+49 6182/93040",
    "sg:postcode":"63533",
    "sg:province":"Hessen",
    "wof:name":"Kn\u00fcrr Ag",
    "wof:placetype":"venue"
},
  "geometry": {"coordinates":[8.994875,50.021221],"type":"Point"}
}