{
  "type": "Feature",
  "properties": {
    "iso:country":"DE",
    "sg:address":"Cracauer Str. 61",
    "sg:city":"Magdeburg",
    "sg:phone":"+49 391/8114337",
    "sg:postcode":"39114",
    "sg:province":"Sachsen-Anhalt",
    "wof:name":"Hausger\u00e4te Kundendienst Gmbh",
    "wof:placetype":"venue"
},
  "geometry": {"coordinates":[11.6605472565,52.1196517944],"type":"Point"}
}