{
  "type": "Feature",
  "properties": {
    "iso:country":"DE",
    "sg:address":"Hauptstr. 16",
    "sg:city":"Kurort Oybin",
    "sg:phone":"+49 35844/70080",
    "sg:postcode":"02797",
    "sg:province":"Sachsen",
    "wof:name":"Berg- Und Klosteranlage Oybin",
    "wof:placetype":"venue"
},
  "geometry": {"coordinates":[14.742942,50.842644],"type":"Point"}
}