{
  "type": "Feature",
  "properties": {
    "iso:country":"DE",
    "sg:address":"Egon - Erwin - Kisch - Weg 39",
    "sg:city":"Leipzig",
    "sg:phone":"+49 341/8620532",
    "sg:postcode":"04299",
    "sg:province":"Sachsen",
    "wof:name":"Zimmerei Axel Thiele",
    "wof:placetype":"venue"
},
  "geometry": {"coordinates":[12.4131498337,51.3191452026],"type":"Point"}
}