{
  "type": "Feature",
  "properties": {
    "iso:country":"DE",
    "sg:address":"fischteichweg 6",
    "sg:city":"petershagen",
    "sg:phone":"+49 5707",
    "sg:postcode":"32469",
    "sg:province":"Nordrhein-Westfalen",
    "wof:name":"Kfz.-sachverst\u00e4ndigen-b\u00fcro",
    "wof:placetype":"venue"
},
  "geometry": {"coordinates":[8.9610433578,52.3785591125],"type":"Point"}
}