{
  "type": "Feature",
  "properties": {
    "iso:country":"DE",
    "sg:address":"Eugen-Jaekle-Platz 2",
    "sg:city":"Heidenheim",
    "sg:phone":"+49 7321/22445",
    "sg:postcode":"89518",
    "sg:province":"Baden-W\u00fcrttemberg",
    "wof:name":"Bernd Maschek",
    "wof:placetype":"venue"
},
  "geometry": {"coordinates":[10.15201,48.6782],"type":"Point"}
}