{
  "type": "Feature",
  "properties": {
    "iso:country":"DE",
    "sg:address":"Am Vogelsang 4",
    "sg:city":"Emmendingen",
    "sg:phone":"+49 7641/570609",
    "sg:postcode":"79312",
    "sg:province":"Baden-W\u00fcrttemberg",
    "wof:name":"V. Stelz",
    "wof:placetype":"venue"
},
  "geometry": {"coordinates":[7.8571,48.124519],"type":"Point"}
}