{
  "type": "Feature",
  "properties": {
    "iso:country":"DE",
    "sg:address":"Schulstr. 2",
    "sg:city":"Lorsch",
    "sg:phone":"+49 6251/54243",
    "sg:postcode":"64653",
    "sg:province":"Hessen",
    "wof:name":"A. J\u00e4ger",
    "wof:placetype":"venue"
},
  "geometry": {"coordinates":[8.5667552948,49.6538543701],"type":"Point"}
}