{
  "type": "Feature",
  "properties": {
    "iso:country":"DE",
    "sg:address":"Karolinenstr. 4",
    "sg:city":"M\u00fcnchen",
    "sg:phone":"+49 89/225179",
    "sg:postcode":"80538",
    "sg:province":"Bayern",
    "wof:name":"Iih Italien Import Handels Gmbh",
    "wof:placetype":"venue"
},
  "geometry": {"coordinates":[11.5953607559,48.1486625671],"type":"Point"}
}