{
  "type": "Feature",
  "properties": {
    "iso:country":"DE",
    "sg:address":"K\u00f6nigstr. 23-25",
    "sg:city":"Duisburg",
    "sg:postcode":"47051",
    "sg:province":"Nordrhein-Westfalen",
    "wof:name":"Icc Immobilien- Competence-center Gmbh",
    "wof:placetype":"venue"
},
  "geometry": {"coordinates":[6.7678427696,51.4332389832],"type":"Point"}
}