{
  "type": "Feature",
  "properties": {
    "iso:country":"DE",
    "sg:address":"Dortmunder Str. 140",
    "sg:city":"Castrop-Rauxel",
    "sg:postcode":"44577",
    "sg:province":"Nordrhein-Westfalen",
    "wof:name":"Aktiv-markt",
    "wof:placetype":"venue"
},
  "geometry": {"coordinates":[7.3306798935,51.542930603],"type":"Point"}
}