{
  "type": "Feature",
  "properties": {
    "iso:country":"DE",
    "sg:address":"Herrlinghausen 104",
    "sg:city":"Wermelskirchen",
    "sg:phone":"+49 2196/5431",
    "sg:postcode":"42929",
    "sg:province":"Nordrhein-Westfalen",
    "wof:name":"Artur G\u00f6rner",
    "wof:placetype":"venue"
},
  "geometry": {"coordinates":[7.2009701729,51.116859436],"type":"Point"}
}