{
  "type": "Feature",
  "properties": {
    "iso:country":"DE",
    "sg:address":"Schillerstr. 46-48",
    "sg:city":"Bielefeld",
    "sg:phone":"+49 521/82098",
    "sg:postcode":"33609",
    "sg:province":"Nordrhein-Westfalen",
    "wof:name":"Wiedey Kg",
    "wof:placetype":"venue"
},
  "geometry": {"coordinates":[8.5496997833,52.0417556763],"type":"Point"}
}