{
  "type": "Feature",
  "properties": {
    "iso:country":"DE",
    "sg:address":"Kelterstr. 185",
    "sg:city":"Kreuzau",
    "sg:phone":"+49 2422/5315",
    "sg:postcode":"52372",
    "sg:province":"Nordrhein-Westfalen",
    "wof:name":"August Zolke",
    "wof:placetype":"venue"
},
  "geometry": {"coordinates":[6.476771,50.729729],"type":"Point"}
}