{
  "type": "Feature",
  "properties": {
    "iso:country":"DE",
    "sg:address":"Hindenburgstr. 53",
    "sg:city":"Itzehoe",
    "sg:phone":"+49 4821/9637",
    "sg:postcode":"25524",
    "sg:province":"Schleswig-Holstein",
    "wof:name":"M\u00e4nnerturnverein Itzehoe E. V.",
    "wof:placetype":"venue"
},
  "geometry": {"coordinates":[9.5258226395,53.9250831604],"type":"Point"}
}