{
  "type": "Feature",
  "properties": {
    "iso:country":"DE",
    "sg:address":"Thuner Weg 6",
    "sg:city":"D\u00fcsseldorf",
    "sg:postcode":"40625",
    "sg:province":"Nordrhein-Westfalen",
    "wof:name":"Rezan Gastst\u00e4ttenbetriebs Gmbh",
    "wof:placetype":"venue"
},
  "geometry": {"coordinates":[6.8407959938,51.2238426208],"type":"Point"}
}