{
  "type": "Feature",
  "properties": {
    "iso:country":"DE",
    "sg:address":"Bleichstr. 56",
    "sg:city":"Paderborn",
    "sg:phone":"+49 5251/36616",
    "sg:postcode":"33102",
    "sg:province":"Nordrhein-Westfalen",
    "wof:name":"Dipl. Kfm. Dirkmorfeld Gmbh",
    "wof:placetype":"venue"
},
  "geometry": {"coordinates":[8.7410898209,51.7201118469],"type":"Point"}
}