{
  "type": "Feature",
  "properties": {
    "iso:country":"DE",
    "sg:address":"M\u00fcllerstr. 19",
    "sg:city":"Augsburg",
    "sg:phone":"+49 821/38936",
    "sg:postcode":"86153",
    "sg:province":"Bayern",
    "wof:name":"Joe Pena Cantina Y Bar",
    "wof:placetype":"venue"
},
  "geometry": {"coordinates":[10.900627,48.378269],"type":"Point"}
}