{
  "type": "Feature",
  "properties": {
    "iso:country":"DE",
    "sg:address":"K\u00f6nigslacher Str. 25",
    "sg:city":"Frankfurt",
    "sg:postcode":"60528",
    "sg:province":"Hessen",
    "wof:name":"M. Schneider Haus Der Gelegenheiten Gmbh",
    "wof:placetype":"venue"
},
  "geometry": {"coordinates":[8.649097,50.081177],"type":"Point"}
}