{
  "type": "Feature",
  "properties": {
    "iso:country":"DE",
    "sg:address":"Leuzenberg 18",
    "sg:city":"Reichenschwand",
    "sg:phone":"+49 9151/6721",
    "sg:postcode":"91244",
    "sg:province":"Bayern",
    "wof:name":"Prof. Dr. Hans U. Bilek",
    "wof:placetype":"venue"
},
  "geometry": {"coordinates":[11.3742399216,49.5214691162],"type":"Point"}
}