{
  "type": "Feature",
  "properties": {
    "iso:country":"DE",
    "sg:address":"Siebenmorgenweg 29",
    "sg:city":"Heilbronn",
    "sg:phone":"+49 7131/380534",
    "sg:postcode":"74081",
    "sg:province":"Baden-W\u00fcrttemberg",
    "wof:name":"Pb Wohnbau Gmbh",
    "wof:placetype":"venue"
},
  "geometry": {"coordinates":[9.1497573853,49.1216583252],"type":"Point"}
}