{
  "type": "Feature",
  "properties": {
    "iso:country":"DE",
    "sg:address":"Sch\u00fctzenstr. 23",
    "sg:city":"Niefern-\u00d6schelbronn",
    "sg:phone":"+49 7233/96110",
    "sg:postcode":"75223",
    "sg:province":"Baden-W\u00fcrttemberg",
    "wof:name":"Heinz-dieter Wolf Gmbh",
    "wof:placetype":"venue"
},
  "geometry": {"coordinates":[8.81475,48.907116],"type":"Point"}
}