{
  "type": "Feature",
  "properties": {
    "iso:country":"DE",
    "sg:address":"Willi-Stamer-Str. 5 a",
    "sg:city":"Gr\u00fcnwald",
    "sg:phone":"+49 89/6412172",
    "sg:postcode":"82031",
    "sg:province":"Bayern",
    "wof:name":"R. Brandtner Handels Gmbh",
    "wof:placetype":"venue"
},
  "geometry": {"coordinates":[11.5371427536,48.0392036438],"type":"Point"}
}