{
  "type": "Feature",
  "properties": {
    "iso:country":"DE",
    "sg:address":"Zehntfeldstr. 242 a",
    "sg:city":"M\u00fcnchen",
    "sg:phone":"+49 89/4391163",
    "sg:postcode":"81825",
    "sg:province":"Bayern",
    "wof:name":"Gerhard Herzog Steuerberater",
    "wof:placetype":"venue"
},
  "geometry": {"coordinates":[11.6644992828,48.1075401306],"type":"Point"}
}