{
  "type": "Feature",
  "properties": {
    "iso:country":"DE",
    "sg:address":"Albinistr. 8",
    "sg:city":"Mainz",
    "sg:phone":"+49 6131/229975",
    "sg:postcode":"55116",
    "sg:province":"Rheinland-Pfalz",
    "wof:name":"Ribbeck",
    "wof:placetype":"venue"
},
  "geometry": {"coordinates":[8.268313,50.007534],"type":"Point"}
}