{
  "type": "Feature",
  "properties": {
    "iso:country":"DE",
    "sg:address":"Im Siegfeld 76",
    "sg:city":"Hennef",
    "sg:postcode":"53773",
    "sg:province":"Nordrhein-Westfalen",
    "wof:name":"B\u00fclgenauel",
    "wof:placetype":"venue"
},
  "geometry": {"coordinates":[7.378106,50.77689],"type":"Point"}
}