{
  "type": "Feature",
  "properties": {
    "iso:country":"DE",
    "sg:address":"Vardingholter Str. 30",
    "sg:city":"Bocholt",
    "sg:phone":"+49 2871/220552",
    "sg:postcode":"46397",
    "sg:province":"Nordrhein-Westfalen",
    "wof:name":"Sabine Terhart-ebert Krankengymnastin",
    "wof:placetype":"venue"
},
  "geometry": {"coordinates":[6.652679,51.858952],"type":"Point"}
}