{
  "type": "Feature",
  "properties": {
    "iso:country":"DE",
    "sg:address":"Tal 23",
    "sg:city":"M\u00fcnchen",
    "sg:phone":"+49 89/2285289",
    "sg:postcode":"80331",
    "sg:province":"Bayern",
    "wof:name":"Michael M\u00fcller Immobilienmakler",
    "wof:placetype":"venue"
},
  "geometry": {"coordinates":[11.5800952911,48.1358718872],"type":"Point"}
}