{
  "type": "Feature",
  "properties": {
    "iso:country":"DE",
    "sg:address":"Hauptstuhler Str. 14",
    "sg:city":"H\u00fctschenhausen",
    "sg:phone":"+49 6372/2321",
    "sg:postcode":"66882",
    "sg:province":"Rheinland-Pfalz",
    "wof:name":"Michael Fiebig",
    "wof:placetype":"venue"
},
  "geometry": {"coordinates":[7.4823098183,49.4177513123],"type":"Point"}
}