{
  "type": "Feature",
  "properties": {
    "iso:country":"DE",
    "sg:address":"Ramonville Str 4",
    "sg:city":"Karben",
    "sg:phone":"+49 6039/7031",
    "sg:postcode":"61184",
    "sg:province":"Hessen",
    "wof:name":"Mavert Industrieanlagen Gmbh",
    "wof:placetype":"venue"
},
  "geometry": {"coordinates":[8.7617282867,50.2340736389],"type":"Point"}
}