{
  "type": "Feature",
  "properties": {
    "iso:country":"DE",
    "sg:address":"Markt 11",
    "sg:city":"Erkelenz",
    "sg:phone":"+49 2431/4031",
    "sg:postcode":"41812",
    "sg:province":"Nordrhein-Westfalen",
    "wof:name":"Breuer Und Geulen Rechtsanw\u00e4lte",
    "wof:placetype":"venue"
},
  "geometry": {"coordinates":[6.3163199425,51.0790214539],"type":"Point"}
}