{
  "type": "Feature",
  "properties": {
    "iso:country":"DE",
    "sg:address":"Lupsteiner Weg 66a",
    "sg:city":"Berlin",
    "sg:phone":"+49 30/8157679",
    "sg:postcode":"14165",
    "sg:province":"Berlin",
    "wof:name":"Klaus-dieter Pawils",
    "wof:placetype":"venue"
},
  "geometry": {"coordinates":[13.256623,52.414928],"type":"Point"}
}