{
  "type": "Feature",
  "properties": {
    "iso:country":"DE",
    "sg:address":"Elektrastr. 8",
    "sg:city":"M\u00fcnchen",
    "sg:phone":"+49 89/919044",
    "sg:postcode":"81925",
    "sg:province":"Bayern",
    "wof:name":"Haconex Handels Gmbh",
    "wof:placetype":"venue"
},
  "geometry": {"coordinates":[11.6219444275,48.1519165039],"type":"Point"}
}