{
  "type": "Feature",
  "properties": {
    "iso:country":"DE",
    "sg:address":"Hildegardstr. 16",
    "sg:city":"Berlin",
    "sg:phone":"+49 30/85729671",
    "sg:postcode":"10715",
    "sg:province":"Berlin",
    "wof:name":"Dr. Wolfgang Holstein",
    "wof:placetype":"venue"
},
  "geometry": {"coordinates":[13.3213062286,52.4819335938],"type":"Point"}
}