{
  "type": "Feature",
  "properties": {
    "iso:country":"DE",
    "sg:address":"Oststr. 53",
    "sg:city":"Gronau",
    "sg:phone":"+49 2565/1414",
    "sg:postcode":"48599",
    "sg:province":"Nordrhein-Westfalen",
    "wof:name":"Lvm-versicherungen",
    "wof:placetype":"venue"
},
  "geometry": {"coordinates":[7.0453510284,52.1782226562],"type":"Point"}
}