{
  "type": "Feature",
  "properties": {
    "iso:country":"DE",
    "sg:address":"Graseckstr. 4",
    "sg:city":"Kochel",
    "sg:postcode":"82431",
    "sg:province":"Bayern",
    "wof:name":"Lichtpausen Habla Gmbh",
    "wof:placetype":"venue"
},
  "geometry": {"coordinates":[11.3668298721,47.654499054],"type":"Point"}
}