{
  "type": "Feature",
  "properties": {
    "iso:country":"DE",
    "sg:address":"Gottlieb-Daimler-Str. 2",
    "sg:city":"Lich",
    "sg:postcode":"35423",
    "sg:province":"Hessen",
    "wof:name":"Bhu B\u00fcro-organisation Inh. Ewald Humer E. K.",
    "wof:placetype":"venue"
},
  "geometry": {"coordinates":[8.827194,50.511448],"type":"Point"}
}