{
  "type": "Feature",
  "properties": {
    "iso:country":"DE",
    "sg:address":"Wahlstrasse 35",
    "sg:city":"Sch\u00f6nau am K\u00f6nigssee",
    "sg:phone":"+49 8652/9450",
    "sg:postcode":"83471",
    "sg:province":"Bayern",
    "wof:name":"Alpenhotel Zechmeisterlehen",
    "wof:placetype":"venue"
},
  "geometry": {"coordinates":[12.9775705338,47.6153678894],"type":"Point"}
}