{
  "type": "Feature",
  "properties": {
    "iso:country":"DE",
    "sg:address":"Hauptstr. 50",
    "sg:city":"Walternienburg",
    "sg:postcode":"39264",
    "sg:province":"Sachsen-Anhalt",
    "wof:name":"Robert Stein",
    "wof:placetype":"venue"
},
  "geometry": {"coordinates":[11.939946,51.964367],"type":"Point"}
}