{
  "type": "Feature",
  "properties": {
    "iso:country":"DE",
    "sg:address":"Bahnhofstr. 30",
    "sg:city":"Oelde",
    "sg:phone":"+49 2522/1052",
    "sg:postcode":"59302",
    "sg:province":"Nordrhein-Westfalen",
    "wof:name":"Hermann Minning Architekt",
    "wof:placetype":"venue"
},
  "geometry": {"coordinates":[8.143043,51.828438],"type":"Point"}
}