{
  "type": "Feature",
  "properties": {
    "iso:country":"DE",
    "sg:address":"Leckerfeld",
    "sg:city":"Wesel",
    "sg:phone":"+49 2859/422",
    "sg:postcode":"46487",
    "sg:province":"Nordrhein-Westfalen",
    "wof:name":"Readymix Transportbeton Gmbh",
    "wof:placetype":"venue"
},
  "geometry": {"coordinates":[6.4971299171,51.6713943481],"type":"Point"}
}