{
  "type": "Feature",
  "properties": {
    "iso:country":"DE",
    "sg:address":"Hauptstr. 151",
    "sg:city":"B\u00fchlertal",
    "sg:phone":"+49 7223/73838",
    "sg:postcode":"77830",
    "sg:province":"Baden-W\u00fcrttemberg",
    "wof:name":"Griesbach Und Bleich Ohg",
    "wof:placetype":"venue"
},
  "geometry": {"coordinates":[8.1909837723,48.6837615967],"type":"Point"}
}