{
  "type": "Feature",
  "properties": {
    "iso:country":"DE",
    "sg:address":"Fuchsberg 20",
    "sg:city":"Bergen",
    "sg:phone":"+49 5054/8732",
    "sg:postcode":"29303",
    "sg:province":"Niedersachsen",
    "wof:name":"Peisker & Elit Bautischlerei Und Fachsanierung Gmbh",
    "wof:placetype":"venue"
},
  "geometry": {"coordinates":[10.047366,52.744629],"type":"Point"}
}