{
  "type": "Feature",
  "properties": {
    "iso:country":"DE",
    "sg:address":"Sammenheim",
    "sg:city":"Dittenheim",
    "sg:phone":"+49 9833/867",
    "sg:postcode":"91723",
    "sg:province":"Bayern",
    "wof:name":"H. Edel",
    "wof:placetype":"venue"
},
  "geometry": {"coordinates":[10.752141,49.049118],"type":"Point"}
}