{
  "type": "Feature",
  "properties": {
    "iso:country":"DE",
    "sg:address":"Wolkenstieg 5",
    "sg:city":"Sittensen",
    "sg:postcode":"27419",
    "sg:province":"Niedersachsen",
    "wof:name":"Nicol",
    "wof:placetype":"venue"
},
  "geometry": {"coordinates":[9.522293,53.280891],"type":"Point"}
}