{
  "type": "Feature",
  "properties": {
    "iso:country":"DE",
    "sg:address":"Taunusanlage 1",
    "sg:city":"Frankfurt",
    "sg:phone":"+49 69/71500",
    "sg:postcode":"60329",
    "sg:province":"Hessen",
    "wof:name":"Kistra Beteiligungs Gmbh",
    "wof:placetype":"venue"
},
  "geometry": {"coordinates":[8.670204,50.110943],"type":"Point"}
}