{
  "type": "Feature",
  "properties": {
    "iso:country":"DE",
    "sg:address":"Keltenstr. 5",
    "sg:city":"Weil der Stadt",
    "sg:phone":"+49 7033/7127",
    "sg:postcode":"71263",
    "sg:province":"Baden-W\u00fcrttemberg",
    "wof:name":"Gemeinn. Bau- Und Siedlungsg. Neues Heim Egmbh",
    "wof:placetype":"venue"
},
  "geometry": {"coordinates":[8.8815956116,48.7569541931],"type":"Point"}
}