{
  "type": "Feature",
  "properties": {
    "iso:country":"DE",
    "sg:address":"Faber-Castell-Str. 16",
    "sg:city":"Oberasbach",
    "sg:phone":"+49 911/696704",
    "sg:postcode":"90522",
    "sg:province":"Bayern",
    "wof:name":"Paneutz Trading Gmbh",
    "wof:placetype":"venue"
},
  "geometry": {"coordinates":[10.9880008698,49.4151992798],"type":"Point"}
}