{
  "type": "Feature",
  "properties": {
    "iso:country":"DE",
    "sg:address":"Leinwebergasse 4",
    "sg:city":"Frankfurt",
    "sg:phone":"+49 69/424323",
    "sg:postcode":"60386",
    "sg:province":"Hessen",
    "wof:name":"Markus Hartmann",
    "wof:placetype":"venue"
},
  "geometry": {"coordinates":[8.770388,50.123165],"type":"Point"}
}