{
  "type": "Feature",
  "properties": {
    "iso:country":"DE",
    "sg:address":"Carl-Schurz-Str. 3",
    "sg:city":"Siegburg",
    "sg:phone":"+49 2241/69518",
    "sg:postcode":"53721",
    "sg:province":"Nordrhein-Westfalen",
    "wof:name":"Paul Hochgeschurz Architekt",
    "wof:placetype":"venue"
},
  "geometry": {"coordinates":[7.200091,50.809109],"type":"Point"}
}