{
  "type": "Feature",
  "properties": {
    "iso:country":"DE",
    "sg:address":"Langelohstra\u00dfe 134",
    "sg:city":"Hamburg",
    "sg:phone":"+49 40",
    "sg:postcode":"22549",
    "sg:province":"Hamburg",
    "wof:name":"Gfm-getas/wba",
    "wof:placetype":"venue"
},
  "geometry": {"coordinates":[9.846783,53.571152],"type":"Point"}
}