{
  "type": "Feature",
  "properties": {
    "iso:country":"DE",
    "sg:address":"Rossertstr. 62",
    "sg:city":"Kriftel",
    "sg:phone":"+49 6192/44868",
    "sg:postcode":"65830",
    "sg:province":"Hessen",
    "wof:name":"Gunter Roemheld Rechtsanwalt",
    "wof:placetype":"venue"
},
  "geometry": {"coordinates":[8.467218399,50.0884284973],"type":"Point"}
}