{
  "type": "Feature",
  "properties": {
    "iso:country":"DE",
    "sg:address":"Albert-Lortzing-Str. 6",
    "sg:city":"Sinsheim",
    "sg:phone":"+49 7261/3776",
    "sg:postcode":"74889",
    "sg:province":"Baden-W\u00fcrttemberg",
    "wof:name":"I. Sch\u00fcle",
    "wof:placetype":"venue"
},
  "geometry": {"coordinates":[8.8861045837,49.2547149658],"type":"Point"}
}