{
  "type": "Feature",
  "properties": {
    "iso:country":"DE",
    "sg:address":"Burgplatz 2",
    "sg:city":"Braunschweig",
    "sg:phone":"+49 531/480130",
    "sg:postcode":"38100",
    "sg:province":"Niedersachsen",
    "wof:name":"Betriebswirte Des Handwerks E. V.",
    "wof:placetype":"venue"
},
  "geometry": {"coordinates":[10.5233688354,52.2648849487],"type":"Point"}
}