{
  "type": "Feature",
  "properties": {
    "iso:country":"DE",
    "sg:address":"Moitzfeld 88",
    "sg:city":"Bergisch Gladbach",
    "sg:phone":"+49 2204/83542",
    "sg:postcode":"51429",
    "sg:province":"Nordrhein-Westfalen",
    "wof:name":"Dea-tankstelle",
    "wof:placetype":"venue"
},
  "geometry": {"coordinates":[7.1877589226,50.9674377441],"type":"Point"}
}