{
  "type": "Feature",
  "properties": {
    "iso:country":"DE",
    "sg:address":"Karl-Wiechert-Allee 55",
    "sg:city":"Hannover",
    "sg:phone":"+49 511/57010",
    "sg:postcode":"30625",
    "sg:province":"Niedersachsen",
    "wof:name":"Concordia Rechtsschutz- Versicherungs-ag",
    "wof:placetype":"venue"
},
  "geometry": {"coordinates":[9.8023738861,52.3917198181],"type":"Point"}
}