{
  "type": "Feature",
  "properties": {
    "iso:country":"DE",
    "sg:address":"Elbchaussee 5",
    "sg:city":"Hamburg",
    "sg:postcode":"22765",
    "sg:province":"Hamburg",
    "wof:name":"Verwaltungsgesellschaft Bos Planungs Mbh",
    "wof:placetype":"venue"
},
  "geometry": {"coordinates":[9.931416,53.546509],"type":"Point"}
}