{
  "type": "Feature",
  "properties": {
    "iso:country":"DE",
    "sg:address":"Lindenstr. 6c",
    "sg:city":"Erdeborn",
    "sg:phone":"+49 34774/27181",
    "sg:postcode":"06317",
    "sg:province":"Sachsen-Anhalt",
    "wof:name":"Horst Th\u00fcrmer",
    "wof:placetype":"venue"
},
  "geometry": {"coordinates":[11.633263588,51.4778633118],"type":"Point"}
}