{
  "type": "Feature",
  "properties": {
    "iso:country":"DE",
    "sg:address":"N\u00fcrnberger Str. 18",
    "sg:city":"Zirndorf",
    "sg:phone":"+49 911/606047",
    "sg:postcode":"90513",
    "sg:province":"Bayern",
    "wof:name":"Kugel-apotheke",
    "wof:placetype":"venue"
},
  "geometry": {"coordinates":[10.9597,49.440559],"type":"Point"}
}