{
  "type": "Feature",
  "properties": {
    "iso:country":"DE",
    "sg:address":"Am S\u00fcdhang 6",
    "sg:city":"Callenberg",
    "sg:phone":"+49 37608/3353",
    "sg:postcode":"09337",
    "sg:province":"Sachsen",
    "wof:name":"R. Teichmann",
    "wof:placetype":"venue"
},
  "geometry": {"coordinates":[12.632584,50.845062],"type":"Point"}
}