{
  "type": "Feature",
  "properties": {
    "iso:country":"DE",
    "sg:address":"Wilhelm-K\u00fclz-Platz 1",
    "sg:city":"Rostock",
    "sg:phone":"+49 381/49940",
    "sg:postcode":"18055",
    "sg:province":"Mecklenburg-Vorpommern",
    "wof:name":"Tlg Treuhand Liegenschafts Gmbh",
    "wof:placetype":"venue"
},
  "geometry": {"coordinates":[12.1359519958,54.0795936584],"type":"Point"}
}