{
  "type": "Feature",
  "properties": {
    "iso:country":"DE",
    "sg:address":"Osterfeldstr. 56-60",
    "sg:city":"Hamburg",
    "sg:phone":"+49 40/5533055",
    "sg:postcode":"22529",
    "sg:province":"Hamburg",
    "wof:name":"Regenbogen Musikverlag Inh. Wolfgang Timpe",
    "wof:placetype":"venue"
},
  "geometry": {"coordinates":[9.9703826904,53.5989189148],"type":"Point"}
}