{
  "type": "Feature",
  "properties": {
    "iso:country":"DE",
    "sg:address":"Bundesstr. 32",
    "sg:city":"Breisach",
    "sg:phone":"+49 7664/2515",
    "sg:postcode":"79206",
    "sg:province":"Baden-W\u00fcrttemberg",
    "wof:name":"Hirschen",
    "wof:placetype":"venue"
},
  "geometry": {"coordinates":[7.6628298759,47.9781227112],"type":"Point"}
}