{
  "type": "Feature",
  "properties": {
    "iso:country":"DE",
    "sg:address":"Lamontstr. 32",
    "sg:city":"M\u00fcnchen",
    "sg:postcode":"81679",
    "sg:province":"Bayern",
    "wof:name":"Rappmannsberger Und Partner Architekten",
    "wof:placetype":"venue"
},
  "geometry": {"coordinates":[11.605259,48.143883],"type":"Point"}
}