{
  "type": "Feature",
  "properties": {
    "iso:country":"DE",
    "sg:address":"Im Moorkamp 7",
    "sg:city":"Brodenbach",
    "sg:phone":"+49 2605/3389",
    "sg:postcode":"56332",
    "sg:province":"Rheinland-Pfalz",
    "wof:name":"Jugendherberge Brodenbach",
    "wof:placetype":"venue"
},
  "geometry": {"coordinates":[7.4417700768,50.2240066528],"type":"Point"}
}