{
  "type": "Feature",
  "properties": {
    "iso:country":"DE",
    "sg:address":"Hansjakobweg 1",
    "sg:city":"Radolfzell",
    "sg:phone":"+49 7732/10101",
    "sg:postcode":"78315",
    "sg:province":"Baden-W\u00fcrttemberg",
    "wof:name":"C. Str\u00f6hle Immobilienmakler",
    "wof:placetype":"venue"
},
  "geometry": {"coordinates":[8.9789457321,47.7351951599],"type":"Point"}
}