{
  "type": "Feature",
  "properties": {
    "iso:country":"DE",
    "sg:address":"Hauptstr. 68",
    "sg:city":"G\u00f6llingen",
    "sg:postcode":"06567",
    "sg:province":"Th\u00fcringen",
    "wof:name":"Gemeindeschwesterstation",
    "wof:placetype":"venue"
},
  "geometry": {"coordinates":[11.010295,51.341709],"type":"Point"}
}