{
  "type": "Feature",
  "properties": {
    "iso:country":"DE",
    "sg:address":"Heilbronner Str. 26",
    "sg:city":"Schw\u00e4bisch Hall",
    "sg:phone":"+49 791/6705",
    "sg:postcode":"74523",
    "sg:province":"Baden-W\u00fcrttemberg",
    "wof:name":"Wilhelm Mulfinger",
    "wof:placetype":"venue"
},
  "geometry": {"coordinates":[9.737632,49.120956],"type":"Point"}
}