{
  "type": "Feature",
  "properties": {
    "iso:country":"DE",
    "sg:address":"Fichtenweg 7",
    "sg:city":"Moosthenning",
    "sg:phone":"+49 8731/9495",
    "sg:postcode":"84164",
    "sg:province":"Bayern",
    "wof:name":"Fischer & Sohn",
    "wof:placetype":"venue"
},
  "geometry": {"coordinates":[12.534529686,48.7060012817],"type":"Point"}
}