{
  "type": "Feature",
  "properties": {
    "iso:country":"DE",
    "sg:address":"Rudolf-Diesel-Str. 11",
    "sg:city":"Nieb\u00fcll",
    "sg:phone":"+49 4661/2930",
    "sg:postcode":"25899",
    "sg:province":"Schleswig-Holstein",
    "wof:name":"Sven Danielsen",
    "wof:placetype":"venue"
},
  "geometry": {"coordinates":[8.8340129852,54.7964172363],"type":"Point"}
}