{
  "type": "Feature",
  "properties": {
    "iso:country":"DE",
    "sg:address":"Weinsberger Str. 30",
    "sg:city":"Erlenbach",
    "sg:phone":"+49 7132/5538",
    "sg:postcode":"74235",
    "sg:province":"Baden-W\u00fcrttemberg",
    "wof:name":"Stabilo Landtechnik Gmbh",
    "wof:placetype":"venue"
},
  "geometry": {"coordinates":[9.266499,49.167549],"type":"Point"}
}