{
  "type": "Feature",
  "properties": {
    "iso:country":"DE",
    "sg:address":"Am Langenberg 12",
    "sg:city":"Lauenf\u00f6rde",
    "sg:phone":"+49 5273/8283",
    "sg:postcode":"37697",
    "sg:province":"Niedersachsen",
    "wof:name":"Schulze Tiefbau Gmbh & Co. Kg",
    "wof:placetype":"venue"
},
  "geometry": {"coordinates":[9.4008188248,51.6844406128],"type":"Point"}
}