{
  "type": "Feature",
  "properties": {
    "iso:country":"DE",
    "sg:address":"Am Hagsbrink 40",
    "sg:city":"B\u00fcnde",
    "sg:phone":"+49 5223/61586",
    "sg:postcode":"32257",
    "sg:province":"Nordrhein-Westfalen",
    "wof:name":"Otto Wulfmeier",
    "wof:placetype":"venue"
},
  "geometry": {"coordinates":[8.55155,52.233353],"type":"Point"}
}