{
  "type": "Feature",
  "properties": {
    "iso:country":"DE",
    "sg:address":"Arthur-Thiele-Weg 16",
    "sg:city":"Leipzig",
    "sg:phone":"+49 341/2513701",
    "sg:postcode":"04319",
    "sg:province":"Sachsen",
    "wof:name":"Zt Zehrfeld & Co. Gmbh",
    "wof:placetype":"venue"
},
  "geometry": {"coordinates":[12.5002603531,51.3450889587],"type":"Point"}
}