{
  "type": "Feature",
  "properties": {
    "iso:country":"DE",
    "sg:address":"Krausestr. 27",
    "sg:city":"Wittenberge",
    "sg:phone":"+49 3877/79445",
    "sg:postcode":"19322",
    "sg:province":"Brandenburg",
    "wof:name":"Hartmut Fietze",
    "wof:placetype":"venue"
},
  "geometry": {"coordinates":[11.752599,53.003212],"type":"Point"}
}