{
  "type": "Feature",
  "properties": {
    "iso:country":"DE",
    "sg:address":"Friesenring 58",
    "sg:city":"M\u00fcnster",
    "sg:phone":"+49 4925/1201876",
    "sg:postcode":"48147",
    "sg:province":"Nordrhein-Westfalen",
    "wof:name":"Bilderbogen Aus M\u00fcnster",
    "wof:placetype":"venue"
},
  "geometry": {"coordinates":[7.620332,51.974491],"type":"Point"}
}