{
  "type": "Feature",
  "properties": {
    "iso:country":"DE",
    "sg:address":"Kirchr\u00f6der Str. 16",
    "sg:city":"Hannover",
    "sg:phone":"+49 511/554021",
    "sg:postcode":"30625",
    "sg:province":"Niedersachsen",
    "wof:name":"Caro Verwaltungs Gmbh",
    "wof:placetype":"venue"
},
  "geometry": {"coordinates":[9.795129776,52.3711967468],"type":"Point"}
}