{
  "type": "Feature",
  "properties": {
    "iso:country":"DE",
    "sg:address":"Groenwold 1A",
    "sg:city":"Nottuln",
    "sg:phone":"+49 2509/262",
    "sg:postcode":"48301",
    "sg:province":"Nordrhein-Westfalen",
    "wof:name":"B. Kuhlmann Eierhandlung",
    "wof:placetype":"venue"
},
  "geometry": {"coordinates":[7.4140791893,51.933757782],"type":"Point"}
}