{
  "type": "Feature",
  "properties": {
    "iso:country":"DE",
    "sg:address":"Birnbaumstr. 21",
    "sg:city":"Landau",
    "sg:phone":"+49 6341/50921",
    "sg:postcode":"76829",
    "sg:province":"Rheinland-Pfalz",
    "wof:name":"Restaurant Sommergarten",
    "wof:placetype":"venue"
},
  "geometry": {"coordinates":[8.136425972,49.1947097778],"type":"Point"}
}