{
  "type": "Feature",
  "properties": {
    "iso:country":"DE",
    "sg:address":"Flugplatz 422",
    "sg:city":"Bitburg",
    "sg:phone":"+49 6561/95050",
    "sg:postcode":"54634",
    "sg:province":"Rheinland-Pfalz",
    "wof:name":"Mylius Flugzeugwerk Gmbh & Co. Kg",
    "wof:placetype":"venue"
},
  "geometry": {"coordinates":[6.52291,49.972256],"type":"Point"}
}