{
  "type": "Feature",
  "properties": {
    "iso:country":"DE",
    "sg:address":"Kaiserstr. 7",
    "sg:city":"Homburg",
    "sg:phone":"+49 6841/3028",
    "sg:postcode":"66424",
    "sg:province":"Saarland",
    "wof:name":"Musikhaus Kohl Inh. Karin Volkert-mischler",
    "wof:placetype":"venue"
},
  "geometry": {"coordinates":[7.3392219543,49.3242607117],"type":"Point"}
}