{
  "type": "Feature",
  "properties": {
    "iso:country":"DE",
    "sg:address":"Barkhausenweg 10",
    "sg:city":"Hamburg",
    "sg:phone":"+49 40/539950",
    "sg:postcode":"22339",
    "sg:province":"Hamburg",
    "wof:name":"Waldemar Link Gmbh & Co",
    "wof:placetype":"venue"
},
  "geometry": {"coordinates":[10.058930397,53.6474761963],"type":"Point"}
}