{
  "type": "Feature",
  "properties": {
    "iso:country":"DE",
    "sg:address":"Bornbarch 10",
    "sg:city":"Norderstedt",
    "sg:phone":"+49 40/528650",
    "sg:postcode":"22848",
    "sg:province":"Schleswig-Holstein",
    "wof:name":"Casio Computer Co. Gmbh",
    "wof:placetype":"venue"
},
  "geometry": {"coordinates":[9.9868345261,53.6632499695],"type":"Point"}
}