{
  "type": "Feature",
  "properties": {
    "iso:country":"DE",
    "sg:address":"Nansenstr. 6",
    "sg:city":"Marktredwitz",
    "sg:phone":"+49 9231/87468",
    "sg:postcode":"95615",
    "sg:province":"Bayern",
    "wof:name":"Osa Schmuck Atelier Gmbh",
    "wof:placetype":"venue"
},
  "geometry": {"coordinates":[12.06443,50.002731],"type":"Point"}
}