{
  "type": "Feature",
  "properties": {
    "iso:country":"DE",
    "sg:address":"Mozartstr. 16",
    "sg:city":"Mainz-Gustavsburg",
    "sg:postcode":"56462",
    "sg:province":"Rheinland-Pfalz",
    "wof:name":"Akupunktur Tcm Gesellschaft Atc\u00e4 Peking China",
    "wof:placetype":"venue"
},
  "geometry": {"coordinates":[7.986734,50.619423],"type":"Point"}
}