{
  "type": "Feature",
  "properties": {
    "iso:country":"DE",
    "sg:address":"K\u00f6nigsf\u00f6rder Str. 44",
    "sg:city":"Lindau",
    "sg:phone":"+49 4346/8859",
    "sg:postcode":"24214",
    "sg:province":"Schleswig-Holstein",
    "wof:name":"Heinz Hansen",
    "wof:placetype":"venue"
},
  "geometry": {"coordinates":[9.919781,54.37746],"type":"Point"}
}