{
  "type": "Feature",
  "properties": {
    "iso:country":"DE",
    "sg:address":"Kaulbachstr. 6 D",
    "sg:city":"Berlin",
    "sg:phone":"+49 30/7717374",
    "sg:postcode":"12247",
    "sg:province":"Berlin",
    "wof:name":"Deutscher Dienst F\u00fcr Wissenschaft Und Kultur-",
    "wof:placetype":"venue"
},
  "geometry": {"coordinates":[13.3303899765,52.4365348816],"type":"Point"}
}