{
  "type": "Feature",
  "properties": {
    "iso:country":"DE",
    "sg:address":"Otto-Hahn-Str. 10-24",
    "sg:city":"Hanau",
    "sg:phone":"+49 6181/6780",
    "sg:postcode":"63456",
    "sg:province":"Hessen",
    "wof:name":"M\u00f6bel Erbes Sb M\u00f6bel Markt Gmbh",
    "wof:placetype":"venue"
},
  "geometry": {"coordinates":[8.8953485489,50.1133537292],"type":"Point"}
}