{
  "type": "Feature",
  "properties": {
    "iso:country":"DE",
    "sg:address":"Baumstr. 62",
    "sg:city":"Bremen",
    "sg:phone":"+49 421/393558",
    "sg:postcode":"28217",
    "sg:province":"Bremen",
    "wof:name":"Stauerei Pierags Gmbh",
    "wof:placetype":"venue"
},
  "geometry": {"coordinates":[8.7878856659,53.0858078003],"type":"Point"}
}