{
  "type": "Feature",
  "properties": {
    "iso:country":"DE",
    "sg:address":"Enge Gasse 9",
    "sg:city":"Augustusburg",
    "sg:phone":"+49 37291/20406",
    "sg:postcode":"09573",
    "sg:province":"Sachsen",
    "wof:name":"Dietmar Tr\u00e4upmann",
    "wof:placetype":"venue"
},
  "geometry": {"coordinates":[13.1012659073,50.8141021729],"type":"Point"}
}