{
  "type": "Feature",
  "properties": {
    "iso:country":"DE",
    "sg:address":"Hochweiseler Str 10",
    "sg:city":"Butzbach",
    "sg:phone":"+49 6033/91030",
    "sg:postcode":"35510",
    "sg:province":"Hessen",
    "wof:name":"Euler Holzbau Gmbh",
    "wof:placetype":"venue"
},
  "geometry": {"coordinates":[8.66698,50.42979],"type":"Point"}
}