{
  "type": "Feature",
  "properties": {
    "iso:country":"DE",
    "sg:address":"Am Tor 5",
    "sg:city":"St. Ingbert",
    "sg:phone":"+49 6894/35719",
    "sg:postcode":"66386",
    "sg:province":"Saarland",
    "wof:name":"Bubi Sold Gmbh",
    "wof:placetype":"venue"
},
  "geometry": {"coordinates":[7.1719689369,49.2677078247],"type":"Point"}
}