{
  "type": "Feature",
  "properties": {
    "iso:country":"DE",
    "sg:address":"Industriestr. 3",
    "sg:city":"Kettenkamp",
    "sg:phone":"+49 5436/1880",
    "sg:postcode":"49577",
    "sg:province":"Niedersachsen",
    "wof:name":"H. Kl\u00f6vekorn Gmbh",
    "wof:placetype":"venue"
},
  "geometry": {"coordinates":[7.820582,52.586712],"type":"Point"}
}