{
  "type": "Feature",
  "properties": {
    "iso:country":"DE",
    "sg:address":"Dornhofstr. 69",
    "sg:city":"Neu-Isenburg",
    "sg:phone":"+49 6102/36570",
    "sg:postcode":"63263",
    "sg:province":"Hessen",
    "wof:name":"Alp Baugesellschaft Mbh",
    "wof:placetype":"venue"
},
  "geometry": {"coordinates":[8.6819295883,50.0456008911],"type":"Point"}
}