{
  "type": "Feature",
  "properties": {
    "iso:country":"DE",
    "sg:address":"Hagenweg 2",
    "sg:city":"G\u00f6ttingen",
    "sg:phone":"+49 551/504560",
    "sg:postcode":"37081",
    "sg:province":"Niedersachsen",
    "wof:name":"Hainberg-tiefbau Gmbh",
    "wof:placetype":"venue"
},
  "geometry": {"coordinates":[9.9168863297,51.54895401],"type":"Point"}
}