{
  "type": "Feature",
  "properties": {
    "iso:country":"DE",
    "sg:address":"Dorfstr. 40",
    "sg:city":"Mallin",
    "sg:phone":"+49 3962/210009",
    "sg:postcode":"17217",
    "sg:province":"Mecklenburg-Vorpommern",
    "wof:name":"Vier Linden",
    "wof:placetype":"venue"
},
  "geometry": {"coordinates":[13.1420412064,53.5326461792],"type":"Point"}
}