{
  "type": "Feature",
  "properties": {
    "iso:country":"DE",
    "sg:address":"Danziger Str. 10",
    "sg:city":"Hemsbach",
    "sg:phone":"+49 6201/74856",
    "sg:postcode":"69502",
    "sg:province":"Baden-W\u00fcrttemberg",
    "wof:name":"Ingeborg B\u00e4rwinkel-franze Architektin",
    "wof:placetype":"venue"
},
  "geometry": {"coordinates":[8.642698,49.591072],"type":"Point"}
}