{
  "type": "Feature",
  "properties": {
    "iso:country":"DE",
    "sg:address":"Wilhelm-Reuter-Str. 5",
    "sg:city":"Eppstein",
    "sg:phone":"+49 6198/502535",
    "sg:postcode":"65817",
    "sg:province":"Hessen",
    "wof:name":"Oswald G. Kaufmann Steuerberater Und",
    "wof:placetype":"venue"
},
  "geometry": {"coordinates":[8.3633155823,50.1390037537],"type":"Point"}
}