{
  "type": "Feature",
  "properties": {
    "iso:country":"DE",
    "sg:address":"P\u00fctzdelle 7",
    "sg:city":"Leverkusen",
    "sg:phone":"+49 214/22381",
    "sg:postcode":"51371",
    "sg:province":"Nordrhein-Westfalen",
    "wof:name":"Ferdinand Hackenbroich",
    "wof:placetype":"venue"
},
  "geometry": {"coordinates":[6.947958,51.051292],"type":"Point"}
}