{
  "type": "Feature",
  "properties": {
    "iso:country":"DE",
    "sg:address":"Schillerstr. 3 a",
    "sg:city":"Waldfischbach-Burgalben",
    "sg:phone":"+49 6333/5079",
    "sg:postcode":"67714",
    "sg:province":"Rheinland-Pfalz",
    "wof:name":"Brigitte Schuhmoden Inh. Wolfgang Scholz",
    "wof:placetype":"venue"
},
  "geometry": {"coordinates":[7.653711,49.282463],"type":"Point"}
}