{
  "type": "Feature",
  "properties": {
    "iso:country":"DE",
    "sg:address":"M\u00fcnchener Str. 11",
    "sg:city":"Berlin",
    "sg:phone":"+49 30/7445159",
    "sg:postcode":"12309",
    "sg:province":"Berlin",
    "wof:name":"Hannelore Raffel Steuerberaterin",
    "wof:placetype":"venue"
},
  "geometry": {"coordinates":[13.4149093628,52.384552002],"type":"Point"}
}