{
  "type": "Feature",
  "properties": {
    "iso:country":"DE",
    "sg:address":"Hebelermeer 81",
    "sg:city":"Twist",
    "sg:phone":"+49 5935/1434",
    "sg:postcode":"49767",
    "sg:province":"Niedersachsen",
    "wof:name":"Gerhard Hollen",
    "wof:placetype":"venue"
},
  "geometry": {"coordinates":[7.081532,52.736019],"type":"Point"}
}