{
  "type": "Feature",
  "properties": {
    "iso:country":"DE",
    "sg:address":"Hermann-Laur-Str 1",
    "sg:city":"Eigeltingen",
    "sg:phone":"+49 7774/93450",
    "sg:postcode":"78253",
    "sg:province":"Baden-W\u00fcrttemberg",
    "wof:name":"Dgs System Gmbh",
    "wof:placetype":"venue"
},
  "geometry": {"coordinates":[8.904131,47.854919],"type":"Point"}
}