{
  "type": "Feature",
  "properties": {
    "iso:country":"DE",
    "sg:address":"Vahrenheider Markt 4",
    "sg:city":"Hannover",
    "sg:phone":"+49 4951/1671813",
    "sg:postcode":"30179",
    "sg:province":"Niedersachsen",
    "wof:name":"Dresdner Bank",
    "wof:placetype":"venue"
},
  "geometry": {"coordinates":[9.749779,52.411163],"type":"Point"}
}