{
  "type": "Feature",
  "properties": {
    "iso:country":"DE",
    "sg:address":"Strandallee 124",
    "sg:city":"Timmendorfer Strand",
    "sg:phone":"+49 4503/2651",
    "sg:postcode":"23669",
    "sg:province":"Schleswig-Holstein",
    "wof:name":"Hotel Seestern",
    "wof:placetype":"venue"
},
  "geometry": {"coordinates":[10.7876672745,53.9954109192],"type":"Point"}
}