{
  "type": "Feature",
  "properties": {
    "iso:country":"DE",
    "sg:address":"Varrentrappstr. 15",
    "sg:city":"Braunschweig",
    "sg:phone":"+49 531/681328",
    "sg:postcode":"38114",
    "sg:province":"Niedersachsen",
    "wof:name":"Bsix Information Exchange Gmbh",
    "wof:placetype":"venue"
},
  "geometry": {"coordinates":[10.5079851151,52.2797966003],"type":"Point"}
}