{
  "type": "Feature",
  "properties": {
    "iso:country":"DE",
    "sg:address":"S\u00e4gstr. 20",
    "sg:city":"Weiherhammer",
    "sg:phone":"+49 9605/3550",
    "sg:postcode":"92729",
    "sg:province":"Bayern",
    "wof:name":"Pinguino",
    "wof:placetype":"venue"
},
  "geometry": {"coordinates":[12.0501232147,49.6345367432],"type":"Point"}
}