{
  "type": "Feature",
  "properties": {
    "iso:country":"DE",
    "sg:address":"Reigersbachstr. 17",
    "sg:city":"M\u00fcnchen",
    "sg:phone":"+49 89/1506677",
    "sg:postcode":"80995",
    "sg:province":"Bayern",
    "wof:name":"Joachim Winkler",
    "wof:placetype":"venue"
},
  "geometry": {"coordinates":[11.506075,48.200634],"type":"Point"}
}