{
  "type": "Feature",
  "properties": {
    "iso:country":"DE",
    "sg:address":"Hochstr. 30",
    "sg:city":"Andernach",
    "sg:phone":"+49 2632/44848",
    "sg:postcode":"56626",
    "sg:province":"Rheinland-Pfalz",
    "wof:name":"Weinhaus Merowingerhof",
    "wof:placetype":"venue"
},
  "geometry": {"coordinates":[7.3985238075,50.4399299622],"type":"Point"}
}