{
  "type": "Feature",
  "properties": {
    "iso:country":"DE",
    "sg:address":"Benckiserstr. 39a",
    "sg:city":"Ludwigshafen",
    "sg:phone":"+49 621/622197",
    "sg:postcode":"67059",
    "sg:province":"Rheinland-Pfalz",
    "wof:name":"Pizzahaus",
    "wof:placetype":"venue"
},
  "geometry": {"coordinates":[8.4412975311,49.4820899963],"type":"Point"}
}