{
  "type": "Feature",
  "properties": {
    "iso:country":"DE",
    "sg:address":"Moritzstr. 17",
    "sg:city":"Amberg",
    "sg:phone":"+49 9621/81215",
    "sg:postcode":"92224",
    "sg:province":"Bayern",
    "wof:name":"Georg Strobl",
    "wof:placetype":"venue"
},
  "geometry": {"coordinates":[11.876854,49.443115],"type":"Point"}
}