{
  "type": "Feature",
  "properties": {
    "iso:country":"DE",
    "sg:address":"St.-Georg-Str. 13",
    "sg:city":"Schenklengsfeld",
    "sg:phone":"+49 6629/919353",
    "sg:postcode":"36277",
    "sg:province":"Hessen",
    "wof:name":"Reiseb\u00fcro Fun & Business Tours",
    "wof:placetype":"venue"
},
  "geometry": {"coordinates":[9.8471078873,50.8173446655],"type":"Point"}
}