{
  "type": "Feature",
  "properties": {
    "iso:country":"DE",
    "sg:address":"Wassergasse 9",
    "sg:city":"Regensburg",
    "sg:phone":"+49 941/593000",
    "sg:postcode":"93059",
    "sg:province":"Bayern",
    "wof:name":"Ludwig Loverde Architekt",
    "wof:placetype":"venue"
},
  "geometry": {"coordinates":[12.097801,49.024147],"type":"Point"}
}