{
  "type": "Feature",
  "properties": {
    "iso:country":"DE",
    "sg:address":"Gutenbergstr. 15",
    "sg:city":"Dornhan",
    "sg:phone":"+49 7455/8725",
    "sg:postcode":"72175",
    "sg:province":"Baden-W\u00fcrttemberg",
    "wof:name":"Faller Druck Gmbh",
    "wof:placetype":"venue"
},
  "geometry": {"coordinates":[8.511704,48.344234],"type":"Point"}
}