{
  "type": "Feature",
  "properties": {
    "iso:country":"DE",
    "sg:address":"Streubergweg 2",
    "sg:city":"Roth",
    "sg:phone":"+49 9171/97200",
    "sg:postcode":"91154",
    "sg:province":"Bayern",
    "wof:name":"Torsten Brauns Architekt",
    "wof:placetype":"venue"
},
  "geometry": {"coordinates":[11.089883,49.205162],"type":"Point"}
}