{
  "type": "Feature",
  "properties": {
    "iso:country":"DE",
    "sg:address":"Buchelweg 1",
    "sg:city":"Marktoberdorf",
    "sg:phone":"+49 8342/5970",
    "sg:postcode":"87616",
    "sg:province":"Bayern",
    "wof:name":"K. Rieger",
    "wof:placetype":"venue"
},
  "geometry": {"coordinates":[10.621802,47.776958],"type":"Point"}
}