{
  "type": "Feature",
  "properties": {
    "iso:country":"DE",
    "sg:address":"Franz-Eugen-Huber-Str. 89",
    "sg:city":"Illertissen",
    "sg:phone":"+49 7303/2784",
    "sg:postcode":"89257",
    "sg:province":"Bayern",
    "wof:name":"Untere Iller Ag",
    "wof:placetype":"venue"
},
  "geometry": {"coordinates":[10.086217,48.226749],"type":"Point"}
}