{
  "type": "Feature",
  "properties": {
    "iso:country":"DE",
    "sg:address":"Lange Str. 34",
    "sg:city":"Willebadessen",
    "sg:phone":"+49 5644/1001",
    "sg:postcode":"34439",
    "sg:province":"Nordrhein-Westfalen",
    "wof:name":"Kr\u00fcger M\u00f6bel Gmbh",
    "wof:placetype":"venue"
},
  "geometry": {"coordinates":[9.0348911285,51.6262054443],"type":"Point"}
}