{
  "type": "Feature",
  "properties": {
    "iso:country":"DE",
    "sg:address":"Dahlienstr. 39",
    "sg:city":"Radevormwald",
    "sg:postcode":"42477",
    "sg:province":"Nordrhein-Westfalen",
    "wof:name":"Casetec Gmbh",
    "wof:placetype":"venue"
},
  "geometry": {"coordinates":[7.3854241371,51.2039680481],"type":"Point"}
}