{
  "type": "Feature",
  "properties": {
    "iso:country":"DE",
    "sg:address":"Heisterstr. 27",
    "sg:city":"Neunkirchen-Seelscheid",
    "sg:phone":"+49 2247/6088",
    "sg:postcode":"53819",
    "sg:province":"Nordrhein-Westfalen",
    "wof:name":"Alfred Piel",
    "wof:placetype":"venue"
},
  "geometry": {"coordinates":[7.30775,50.856941],"type":"Point"}
}