{
  "type": "Feature",
  "properties": {
    "iso:country":"DE",
    "sg:address":"Ostertorsteinweg 49",
    "sg:city":"Bremen",
    "sg:phone":"+49 421/325484",
    "sg:postcode":"28203",
    "sg:province":"Bremen",
    "wof:name":"Hoins-intermusik",
    "wof:placetype":"venue"
},
  "geometry": {"coordinates":[8.8172206879,53.0724334717],"type":"Point"}
}