{
  "type": "Feature",
  "properties": {
    "iso:country":"DE",
    "sg:address":"Mittelweg 98",
    "sg:city":"Oelde",
    "sg:phone":"+49 2522/93210",
    "sg:postcode":"59302",
    "sg:province":"Nordrhein-Westfalen",
    "wof:name":"Pollmann Elektrotechnik Gmbh",
    "wof:placetype":"venue"
},
  "geometry": {"coordinates":[8.1432342529,51.8496208191],"type":"Point"}
}