{
  "type": "Feature",
  "properties": {
    "iso:country":"DE",
    "sg:address":"Richard-Wagner-Str. 6",
    "sg:city":"K\u00fcps",
    "sg:phone":"+49 9264/8859",
    "sg:postcode":"96328",
    "sg:province":"Bayern",
    "wof:name":"Werner Hentsch",
    "wof:placetype":"venue"
},
  "geometry": {"coordinates":[11.2707080841,50.1945228577],"type":"Point"}
}