{
  "type": "Feature",
  "properties": {
    "iso:country":"DE",
    "sg:address":"Lichtenauer Str. 45a",
    "sg:city":"Chemnitz",
    "sg:phone":"+49 371/449810",
    "sg:postcode":"09131",
    "sg:province":"Sachsen",
    "wof:name":"Dachdecker-fachbetrieb Stengel Gmbh",
    "wof:placetype":"venue"
},
  "geometry": {"coordinates":[12.9683933258,50.8752441406],"type":"Point"}
}