{
  "type": "Feature",
  "properties": {
    "iso:country":"DE",
    "sg:address":"Siegertstr.14",
    "sg:city":"Hilpoltstein",
    "sg:phone":"+49 9174/9605",
    "sg:postcode":"91161",
    "sg:province":"Bayern",
    "wof:name":"Schwarm-schilder",
    "wof:placetype":"venue"
},
  "geometry": {"coordinates":[11.1913967133,49.1879615784],"type":"Point"}
}