{
  "type": "Feature",
  "properties": {
    "iso:country":"DE",
    "sg:address":"Kaagangerstr. 10a",
    "sg:city":"Eching",
    "sg:postcode":"82279",
    "sg:province":"Bayern",
    "wof:name":"Dr. M\u00fcller Medien Und Mehr 3 M Gmbh",
    "wof:placetype":"venue"
},
  "geometry": {"coordinates":[11.1137809753,48.0758056641],"type":"Point"}
}