{
  "type": "Feature",
  "properties": {
    "iso:country":"DE",
    "sg:address":"Chemnitzer Str. 42 A",
    "sg:city":"Chemnitz OT Gr\u00fcna",
    "sg:postcode":"09224",
    "sg:province":"Sachsen",
    "wof:name":"Dirk Lichtenberger",
    "wof:placetype":"venue"
},
  "geometry": {"coordinates":[12.78139,50.810558],"type":"Point"}
}