{
  "type": "Feature",
  "properties": {
    "iso:country":"DE",
    "sg:address":"Freiherr-vom-Stein-Str. 31",
    "sg:city":"Altena",
    "sg:phone":"+49 2352/23405",
    "sg:postcode":"58762",
    "sg:province":"Nordrhein-Westfalen",
    "wof:name":"Horst Pirags Und K. Wisgalle Architekten",
    "wof:placetype":"venue"
},
  "geometry": {"coordinates":[7.66747,51.300938],"type":"Point"}
}