{
  "type": "Feature",
  "properties": {
    "iso:country":"DE",
    "sg:address":"Lochfeldstr 29",
    "sg:city":"Rastatt",
    "sg:phone":"+49 7222/95310",
    "sg:postcode":"76437",
    "sg:province":"Baden-W\u00fcrttemberg",
    "wof:name":"Rastatter Metallgiesserei E. Eck Kg",
    "wof:placetype":"venue"
},
  "geometry": {"coordinates":[8.230078,48.854984],"type":"Point"}
}