{
  "type": "Feature",
  "properties": {
    "iso:country":"DE",
    "sg:address":"Adolphstr. 18",
    "sg:city":"Gro\u00dfr\u00f6hrsdorf",
    "sg:phone":"+49 35952/46955",
    "sg:postcode":"01900",
    "sg:province":"Sachsen",
    "wof:name":"Eberhard Reimer",
    "wof:placetype":"venue"
},
  "geometry": {"coordinates":[14.023605,51.141243],"type":"Point"}
}