{
  "type": "Feature",
  "properties": {
    "iso:country":"DE",
    "sg:address":"R\u00f6merstr. 74",
    "sg:city":"Uhingen",
    "sg:phone":"+49 7161/388106",
    "sg:postcode":"73066",
    "sg:province":"Baden-W\u00fcrttemberg",
    "wof:name":"Weinhandlung Stolzenberger",
    "wof:placetype":"venue"
},
  "geometry": {"coordinates":[9.6010599136,48.7055664062],"type":"Point"}
}