{
  "type": "Feature",
  "properties": {
    "iso:country":"DE",
    "sg:address":"Hauptstr. 25",
    "sg:city":"Borgdorf-Seedorf",
    "sg:phone":"+49 4392/4762",
    "sg:postcode":"24589",
    "sg:province":"Schleswig-Holstein",
    "wof:name":"Kieshandel Und Transport M. Thriene Kg",
    "wof:placetype":"venue"
},
  "geometry": {"coordinates":[9.873799324,54.17345047],"type":"Point"}
}