{
  "type": "Feature",
  "properties": {
    "iso:country":"DE",
    "sg:address":"Eltener Str. 1",
    "sg:city":"Emmerich",
    "sg:phone":"+49 2822/70453",
    "sg:postcode":"46446",
    "sg:province":"Nordrhein-Westfalen",
    "wof:name":"Heinz Convent",
    "wof:placetype":"venue"
},
  "geometry": {"coordinates":[6.235679,51.83403],"type":"Point"}
}