{
  "type": "Feature",
  "properties": {
    "iso:country":"DE",
    "sg:address":"Bodenbreitenstr. 78",
    "sg:city":"M\u00fcnchen",
    "sg:phone":"+49 89/152571",
    "sg:postcode":"80992",
    "sg:province":"Bayern",
    "wof:name":"Rudolf Decker Inh. Albert Kaiblinger",
    "wof:placetype":"venue"
},
  "geometry": {"coordinates":[11.5215549469,48.1744842529],"type":"Point"}
}