{
  "type": "Feature",
  "properties": {
    "iso:country":"DE",
    "sg:address":"Pappelgasse 26a",
    "sg:city":"Erlangen",
    "sg:postcode":"91056",
    "sg:province":"Bayern",
    "wof:name":"Air Bridge Cargo Handling Luftfrachtvermittlung Gmbh",
    "wof:placetype":"venue"
},
  "geometry": {"coordinates":[10.9853515625,49.5980186462],"type":"Point"}
}