{
  "type": "Feature",
  "properties": {
    "iso:country":"DE",
    "sg:address":"Wasserreihe 31",
    "sg:city":"Husum",
    "sg:phone":"+49 4841/666270",
    "sg:postcode":"25813",
    "sg:province":"Schleswig-Holstein",
    "wof:name":"Theodor-storm-archiv",
    "wof:placetype":"venue"
},
  "geometry": {"coordinates":[9.047703,54.475697],"type":"Point"}
}