{
  "type": "Feature",
  "properties": {
    "iso:country":"DE",
    "sg:address":"Flaesheimer Str. 23",
    "sg:city":"Haltern",
    "sg:phone":"+49 2364/13439",
    "sg:postcode":"45721",
    "sg:province":"Nordrhein-Westfalen",
    "wof:name":"Herbert Frei",
    "wof:placetype":"venue"
},
  "geometry": {"coordinates":[7.1899762154,51.7281608582],"type":"Point"}
}