{
  "type": "Feature",
  "properties": {
    "iso:country":"DE",
    "sg:address":"Waldstr. 63A",
    "sg:city":"Gro\u00df-Zimmern",
    "sg:phone":"+49 6071/950120",
    "sg:postcode":"64846",
    "sg:province":"Hessen",
    "wof:name":"Communicare Gmbh",
    "wof:placetype":"venue"
},
  "geometry": {"coordinates":[8.8211326599,49.8794212341],"type":"Point"}
}