{
  "type": "Feature",
  "properties": {
    "iso:country":"DE",
    "sg:address":"Redwitzstr. 59",
    "sg:city":"K\u00f6ln",
    "sg:phone":"+49 221/444876",
    "sg:postcode":"50937",
    "sg:province":"Nordrhein-Westfalen",
    "wof:name":"E. A. Wirdeier Bildhauer",
    "wof:placetype":"venue"
},
  "geometry": {"coordinates":[6.924509,50.921066],"type":"Point"}
}