{
  "type": "Feature",
  "properties": {
    "iso:country":"DE",
    "sg:address":"Neuensteiner Str. 8",
    "sg:city":"Oppenau",
    "sg:phone":"+49 4978/042001",
    "sg:postcode":"77728",
    "sg:province":"Baden-W\u00fcrttemberg",
    "wof:name":"Ziegler Kg",
    "wof:placetype":"venue"
},
  "geometry": {"coordinates":[8.1373729706,48.497882843],"type":"Point"}
}