{
  "type": "Feature",
  "properties": {
    "iso:country":"DE",
    "sg:address":"Hedwigstr. 2",
    "sg:city":"Oelde",
    "sg:phone":"+49 2522/961730",
    "sg:postcode":"59302",
    "sg:province":"Nordrhein-Westfalen",
    "wof:name":"A. Stutenb\u00e4umer",
    "wof:placetype":"venue"
},
  "geometry": {"coordinates":[8.1425600052,51.8339004517],"type":"Point"}
}