{
  "type": "Feature",
  "properties": {
    "iso:country":"DE",
    "sg:address":"Monheimer Str. 22",
    "sg:city":"Monheim",
    "sg:phone":"+49 2173/64047",
    "sg:postcode":"40789",
    "sg:province":"Nordrhein-Westfalen",
    "wof:name":"M. Schmidt",
    "wof:placetype":"venue"
},
  "geometry": {"coordinates":[6.888657,51.112949],"type":"Point"}
}