{
  "type": "Feature",
  "properties": {
    "iso:country":"DE",
    "sg:address":"Hagedorner Kirchweg 27",
    "sg:city":"Kirchlengern",
    "sg:phone":"+49 5223/78178",
    "sg:postcode":"32278",
    "sg:province":"Nordrhein-Westfalen",
    "wof:name":"Brunhild Rullk\u00f6tter",
    "wof:placetype":"venue"
},
  "geometry": {"coordinates":[8.6432714462,52.2007598877],"type":"Point"}
}