{
  "type": "Feature",
  "properties": {
    "iso:country":"DE",
    "sg:address":"Venner Str. 28",
    "sg:city":"Viersen",
    "sg:phone":"+49 2162/40921",
    "sg:postcode":"41751",
    "sg:province":"Nordrhein-Westfalen",
    "wof:name":"Hubert Heyer",
    "wof:placetype":"venue"
},
  "geometry": {"coordinates":[6.354063,51.23621],"type":"Point"}
}