{
  "type": "Feature",
  "properties": {
    "iso:country":"DE",
    "sg:address":"Friedrichstr. 40a",
    "sg:city":"Mannheim",
    "sg:phone":"+49 621/8620598",
    "sg:postcode":"68199",
    "sg:province":"Baden-W\u00fcrttemberg",
    "wof:name":"Bistro Bananas",
    "wof:placetype":"venue"
},
  "geometry": {"coordinates":[8.4891414642,49.4528465271],"type":"Point"}
}