{
  "type": "Feature",
  "properties": {
    "iso:country":"DE",
    "sg:address":"Veltener Str.",
    "sg:city":"Germendorf",
    "sg:phone":"+49 3301/58570",
    "sg:postcode":"16767",
    "sg:province":"Brandenburg",
    "wof:name":"Keller Grundbau Gmbh",
    "wof:placetype":"venue"
},
  "geometry": {"coordinates":[13.193445,52.723694],"type":"Point"}
}