{
  "type": "Feature",
  "properties": {
    "iso:country":"DE",
    "sg:address":"Werftstr. 2",
    "sg:city":"Karlsruhe",
    "sg:phone":"+49 721/5990",
    "sg:postcode":"76189",
    "sg:province":"Baden-W\u00fcrttemberg",
    "wof:name":"St\u00e4dtische Rheinh\u00e4fen Karlsruhe",
    "wof:placetype":"venue"
},
  "geometry": {"coordinates":[8.3449239731,49.0165214539],"type":"Point"}
}