{
  "type": "Feature",
  "properties": {
    "iso:country":"DE",
    "sg:address":"Joseph-Bernhart-Str. 23",
    "sg:city":"Mindelheim",
    "sg:phone":"+49 8261/738399",
    "sg:postcode":"87719",
    "sg:province":"Bayern",
    "wof:name":"Georg Altmayr Architekt",
    "wof:placetype":"venue"
},
  "geometry": {"coordinates":[10.502584,48.050159],"type":"Point"}
}