{
  "type": "Feature",
  "properties": {
    "iso:country":"DE",
    "sg:address":"Sommersdorf 46",
    "sg:city":"Burgoberbach",
    "sg:phone":"+49 9805/640",
    "sg:postcode":"91595",
    "sg:province":"Bayern",
    "wof:name":"E. Schilfahrt",
    "wof:placetype":"venue"
},
  "geometry": {"coordinates":[10.585662,49.204533],"type":"Point"}
}