{
  "type": "Feature",
  "properties": {
    "iso:country":"DE",
    "sg:address":"Neue Gr\u00fcnhainer Str. 5",
    "sg:city":"Bernsbach",
    "sg:postcode":"08315",
    "sg:province":"Sachsen",
    "wof:name":"Smb Stanzerei Metall- Bearbeitung Gmbh",
    "wof:placetype":"venue"
},
  "geometry": {"coordinates":[12.7676315308,50.583480835],"type":"Point"}
}