{
  "type": "Feature",
  "properties": {
    "iso:country":"DE",
    "sg:address":"B\u00e4renstr. 4",
    "sg:city":"Plauen",
    "sg:postcode":"08523",
    "sg:province":"Sachsen",
    "wof:name":"Parcotherm",
    "wof:placetype":"venue"
},
  "geometry": {"coordinates":[12.1339960098,50.4984207153],"type":"Point"}
}