{
  "type": "Feature",
  "properties": {
    "iso:country":"DE",
    "sg:address":"Scharling 1",
    "sg:city":"Scharling",
    "sg:phone":"+49 8681/215",
    "sg:postcode":"83329",
    "sg:province":"Bayern",
    "wof:name":"Josef Umkehrer S\u00e4gewerk Und Hobelwerk",
    "wof:placetype":"venue"
},
  "geometry": {"coordinates":[12.7082586288,47.9220085144],"type":"Point"}
}