{
  "type": "Feature",
  "properties": {
    "iso:country":"DE",
    "sg:address":"Querstr. 12",
    "sg:city":"Dortmund",
    "sg:phone":"+49 231/121213",
    "sg:postcode":"44139",
    "sg:province":"Nordrhein-Westfalen",
    "wof:name":"Thomas Thal",
    "wof:placetype":"venue"
},
  "geometry": {"coordinates":[7.4564929008,51.5015907288],"type":"Point"}
}