{
  "type": "Feature",
  "properties": {
    "iso:country":"DE",
    "sg:address":"Jacobsgasse 14",
    "sg:city":"Wurzen",
    "sg:phone":"+49 3425/925878",
    "sg:postcode":"04808",
    "sg:province":"Sachsen",
    "wof:name":"Thieme",
    "wof:placetype":"venue"
},
  "geometry": {"coordinates":[12.7371292114,51.3699913025],"type":"Point"}
}