{
  "type": "Feature",
  "properties": {
    "iso:country":"DE",
    "sg:address":"Zollstr 47",
    "sg:city":"Leutkirch",
    "sg:phone":"+49 7563/909233",
    "sg:postcode":"88299",
    "sg:province":"Baden-W\u00fcrttemberg",
    "wof:name":"Erich Scheerer Gmbh",
    "wof:placetype":"venue"
},
  "geometry": {"coordinates":[9.95728,47.79031],"type":"Point"}
}