{
  "type": "Feature",
  "properties": {
    "iso:country":"DE",
    "sg:address":"Spitalstr. 31",
    "sg:city":"Nettetal",
    "sg:phone":"+49 2157/811774",
    "sg:postcode":"41334",
    "sg:province":"Nordrhein-Westfalen",
    "wof:name":"Hans Buschmann Steuerberater",
    "wof:placetype":"venue"
},
  "geometry": {"coordinates":[6.2041630745,51.3168334961],"type":"Point"}
}