{
  "type": "Feature",
  "properties": {
    "iso:country":"DE",
    "sg:address":"Wehrkirchstr. 30",
    "sg:city":"Wertheim",
    "sg:phone":"+49 9342/7891",
    "sg:postcode":"97877",
    "sg:province":"Baden-W\u00fcrttemberg",
    "wof:name":"K.-u. Patz",
    "wof:placetype":"venue"
},
  "geometry": {"coordinates":[9.572735,49.746391],"type":"Point"}
}