{
  "type": "Feature",
  "properties": {
    "iso:country":"DE",
    "sg:address":"Dalbergstr. 4",
    "sg:city":"Aschaffenburg",
    "sg:phone":"+49 6021/200538",
    "sg:postcode":"63739",
    "sg:province":"Bayern",
    "wof:name":"Hausch Cafe Gmbh",
    "wof:placetype":"venue"
},
  "geometry": {"coordinates":[9.1463155746,49.974445343],"type":"Point"}
}