{
  "type": "Feature",
  "properties": {
    "iso:country":"DE",
    "sg:address":"Eibauer Str 18",
    "sg:city":"Dresden",
    "sg:phone":"+49 351/2620515",
    "sg:postcode":"01324",
    "sg:province":"Sachsen",
    "wof:name":"Dresdner I. Medaillenm\u00fcnze Glaser & Sohn Gmbh",
    "wof:placetype":"venue"
},
  "geometry": {"coordinates":[13.838198,51.061275],"type":"Point"}
}