{
  "type": "Feature",
  "properties": {
    "iso:country":"DE",
    "sg:address":"Freilichtgradstr. 10",
    "sg:city":"Rudolstadt",
    "sg:phone":"+49 3672/24561",
    "sg:postcode":"07407",
    "sg:province":"Th\u00fcringen",
    "wof:name":"Commerzbank Ag",
    "wof:placetype":"venue"
},
  "geometry": {"coordinates":[11.342651,50.719467],"type":"Point"}
}