{
  "type": "Feature",
  "properties": {
    "iso:country":"DE",
    "sg:address":"Birkenweg 22",
    "sg:city":"Gro\u00dfheide",
    "sg:postcode":"26532",
    "sg:province":"Niedersachsen",
    "wof:name":"A. Hasbergen",
    "wof:placetype":"venue"
},
  "geometry": {"coordinates":[7.379947,53.55513],"type":"Point"}
}