{
  "type": "Feature",
  "properties": {
    "iso:country":"DE",
    "sg:address":"Dinkelbergstr. 15",
    "sg:city":"Rheinfelden",
    "sg:phone":"+49 7623/47133",
    "sg:postcode":"79618",
    "sg:province":"Baden-W\u00fcrttemberg",
    "wof:name":"Gabriele Sch\u00e4fer-fackler",
    "wof:placetype":"venue"
},
  "geometry": {"coordinates":[7.7559909821,47.5981292725],"type":"Point"}
}