{
  "type": "Feature",
  "properties": {
    "iso:country":"DE",
    "sg:address":"Porschestr. 90",
    "sg:city":"Wolfsburg",
    "sg:phone":"+49 5361/14130",
    "sg:postcode":"38440",
    "sg:province":"Niedersachsen",
    "wof:name":"Tivoli-automatenhalle",
    "wof:placetype":"venue"
},
  "geometry": {"coordinates":[10.785382,52.420139],"type":"Point"}
}