{
  "type": "Feature",
  "properties": {
    "iso:country":"DE",
    "sg:address":"Saaruferstr. 16",
    "sg:city":"Saarbr\u00fccken",
    "sg:phone":"+49 681/51154",
    "sg:postcode":"66117",
    "sg:province":"Saarland",
    "wof:name":"G\u00fcnther Koch",
    "wof:placetype":"venue"
},
  "geometry": {"coordinates":[6.989358902,49.2358932495],"type":"Point"}
}