{
  "type": "Feature",
  "properties": {
    "iso:country":"DE",
    "sg:address":"Darmst\u00e4dter Str. 31",
    "sg:city":"B\u00fcttelborn",
    "sg:phone":"+49 6152/59172",
    "sg:postcode":"64572",
    "sg:province":"Hessen",
    "wof:name":"Georg Schamber",
    "wof:placetype":"venue"
},
  "geometry": {"coordinates":[8.516277,49.899506],"type":"Point"}
}