{
  "type": "Feature",
  "properties": {
    "iso:country":"DE",
    "sg:address":"Seestr. 9",
    "sg:city":"Ludwigsburg",
    "sg:phone":"+49 7141/96190",
    "sg:postcode":"71638",
    "sg:province":"Baden-W\u00fcrttemberg",
    "wof:name":"Siegfried Zillmann Architekt",
    "wof:placetype":"venue"
},
  "geometry": {"coordinates":[9.190472,48.895237],"type":"Point"}
}