{
  "type": "Feature",
  "properties": {
    "iso:country":"DE",
    "sg:address":"Rhanwaltinger Str 32-34",
    "sg:city":"Cham",
    "sg:phone":"+49 9971/85710",
    "sg:postcode":"93413",
    "sg:province":"Bayern",
    "wof:name":"Cd-lux Gmbh",
    "wof:placetype":"venue"
},
  "geometry": {"coordinates":[12.645972,49.24371],"type":"Point"}
}