{
  "type": "Feature",
  "properties": {
    "iso:country":"DE",
    "sg:address":"M\u00fcnsterstr. 48",
    "sg:city":"Steinfurt",
    "sg:phone":"+49 2552/2089",
    "sg:postcode":"48565",
    "sg:province":"Nordrhein-Westfalen",
    "wof:name":"Hubert Harking",
    "wof:placetype":"venue"
},
  "geometry": {"coordinates":[7.3932847977,52.1227798462],"type":"Point"}
}