{
  "type": "Feature",
  "properties": {
    "iso:country":"DE",
    "sg:address":"Zuhornstr. 15",
    "sg:city":"M\u00fcnster",
    "sg:phone":"+49 251/20735",
    "sg:postcode":"48147",
    "sg:province":"Nordrhein-Westfalen",
    "wof:name":"D. Und Martin Medenwaldt Architekten",
    "wof:placetype":"venue"
},
  "geometry": {"coordinates":[7.626948,51.970329],"type":"Point"}
}