{
  "type": "Feature",
  "properties": {
    "iso:country":"DE",
    "sg:address":"Mahlbergstr. 12",
    "sg:city":"Karlsbad",
    "sg:phone":"+49 7202/941215",
    "sg:postcode":"76307",
    "sg:province":"Baden-W\u00fcrttemberg",
    "wof:name":"G. Dahlinger",
    "wof:placetype":"venue"
},
  "geometry": {"coordinates":[8.4677877426,48.8940315247],"type":"Point"}
}