{
  "type": "Feature",
  "properties": {
    "iso:country":"DE",
    "sg:address":"Willenberg 14",
    "sg:city":"Diepholz",
    "sg:phone":"+49 5441/1050",
    "sg:postcode":"49356",
    "sg:province":"Niedersachsen",
    "wof:name":"Pizza-kurier Mattias Pleick",
    "wof:placetype":"venue"
},
  "geometry": {"coordinates":[8.366246,52.603771],"type":"Point"}
}