{
  "type": "Feature",
  "properties": {
    "iso:country":"DE",
    "sg:address":"V\u00f6lgerstr. 9",
    "sg:city":"Hannover",
    "sg:phone":"+49 511/865088",
    "sg:postcode":"30519",
    "sg:province":"Niedersachsen",
    "wof:name":"Dz Werbung Gmbh",
    "wof:placetype":"venue"
},
  "geometry": {"coordinates":[9.779154,52.333157],"type":"Point"}
}