{
  "type": "Feature",
  "properties": {
    "iso:country":"DE",
    "sg:address":"Steppach 82",
    "sg:city":"Pommersfelden",
    "sg:phone":"+49 9548/1867",
    "sg:postcode":"96178",
    "sg:province":"Bayern",
    "wof:name":"M. Schmelzer",
    "wof:placetype":"venue"
},
  "geometry": {"coordinates":[10.8043870926,49.7721366882],"type":"Point"}
}