{
  "type": "Feature",
  "properties": {
    "iso:country":"DE",
    "sg:address":"Zum Lith 130",
    "sg:city":"Duisburg",
    "sg:phone":"+49 203/770287",
    "sg:postcode":"47055",
    "sg:province":"Nordrhein-Westfalen",
    "wof:name":"Helmut Schenkewitz",
    "wof:placetype":"venue"
},
  "geometry": {"coordinates":[6.767506,51.400749],"type":"Point"}
}