{
  "type": "Feature",
  "properties": {
    "iso:country":"DE",
    "sg:address":"Marienthal",
    "sg:city":"Regenstauf",
    "sg:phone":"+49 9436/2980",
    "sg:postcode":"93128",
    "sg:province":"Bayern",
    "wof:name":"H. Kleemann Jun.",
    "wof:placetype":"venue"
},
  "geometry": {"coordinates":[12.1796150208,49.2222862244],"type":"Point"}
}