{
  "type": "Feature",
  "properties": {
    "iso:country":"DE",
    "sg:address":"K\u00e4mmererstr. 69",
    "sg:city":"Worms",
    "sg:phone":"+49 6241/82236",
    "sg:postcode":"67547",
    "sg:province":"Rheinland-Pfalz",
    "wof:name":"Kilian-reisen E. K.",
    "wof:placetype":"venue"
},
  "geometry": {"coordinates":[8.3642759323,49.6334877014],"type":"Point"}
}