{
  "type": "Feature",
  "properties": {
    "iso:country":"DE",
    "sg:address":"Von-Th\u00fcnen-Str. 12",
    "sg:city":"Bremen",
    "sg:phone":"+49 4942/148930",
    "sg:postcode":"28307",
    "sg:province":"Bremen",
    "wof:name":"Aqua Signal Ag Spezialleuchtenfabrik",
    "wof:placetype":"venue"
},
  "geometry": {"coordinates":[8.96987,53.04277],"type":"Point"}
}