{
  "type": "Feature",
  "properties": {
    "iso:country":"DE",
    "sg:address":"Matth\u00e4ikirchstr. 1",
    "sg:city":"Berlin",
    "sg:phone":"+49 30/254880",
    "sg:postcode":"10785",
    "sg:province":"Berlin",
    "wof:name":"Philharmonie",
    "wof:placetype":"venue"
},
  "geometry": {"coordinates":[13.363442,52.509857],"type":"Point"}
}