{
  "type": "Feature",
  "properties": {
    "iso:country":"DE",
    "sg:address":"Grafweg 11",
    "sg:city":"Plettenberg",
    "sg:phone":"+49 2391/818180",
    "sg:postcode":"58840",
    "sg:province":"Nordrhein-Westfalen",
    "wof:name":"Druckerei Overhoff",
    "wof:placetype":"venue"
},
  "geometry": {"coordinates":[7.8735809326,51.2094154358],"type":"Point"}
}