{
  "type": "Feature",
  "properties": {
    "iso:country":"DE",
    "sg:address":"Karl-Marx-Str. 14",
    "sg:city":"Cottbus",
    "sg:phone":"+49 355/24378",
    "sg:postcode":"03044",
    "sg:province":"Brandenburg",
    "wof:name":"Galenus-apotheke Inh. Gertrud Mandreck",
    "wof:placetype":"venue"
},
  "geometry": {"coordinates":[14.327296,51.763737],"type":"Point"}
}