{
  "type": "Feature",
  "properties": {
    "iso:country":"DE",
    "sg:address":"Krumbacher Str. 2",
    "sg:city":"Babenhausen",
    "sg:phone":"+49 8333/3720",
    "sg:postcode":"87727",
    "sg:province":"Bayern",
    "wof:name":"Reinhold Gruber",
    "wof:placetype":"venue"
},
  "geometry": {"coordinates":[10.2577648163,48.1446914673],"type":"Point"}
}