{
  "type": "Feature",
  "properties": {
    "iso:country":"DE",
    "sg:address":"Kirchsteig 1a",
    "sg:city":"Gro\u00dfkarolinenfeld",
    "sg:phone":"+49 8067/688",
    "sg:postcode":"83109",
    "sg:province":"Bayern",
    "wof:name":"Zimmerei A. Maicher Gmbh",
    "wof:placetype":"venue"
},
  "geometry": {"coordinates":[12.0828619003,47.930393219],"type":"Point"}
}