{
  "type": "Feature",
  "properties": {
    "iso:country":"DE",
    "sg:address":"Badstubenwiese 3",
    "sg:city":"\u00d6stringen",
    "sg:phone":"+49 7259/336",
    "sg:postcode":"76684",
    "sg:province":"Baden-W\u00fcrttemberg",
    "wof:name":"Klaus Fehrer Marmor -und Granitbetrieb Gmbh",
    "wof:placetype":"venue"
},
  "geometry": {"coordinates":[8.7544736862,49.1763343811],"type":"Point"}
}