{
  "type": "Feature",
  "properties": {
    "iso:country":"DE",
    "sg:address":"Gartenstra\u00dfe 5",
    "sg:city":"Niesky",
    "sg:postcode":"02906",
    "sg:province":"Sachsen",
    "wof:name":"Steuerberater Viola Hoffmann",
    "wof:placetype":"venue"
},
  "geometry": {"coordinates":[14.819524765,51.2939682007],"type":"Point"}
}