{
  "type": "Feature",
  "properties": {
    "iso:country":"DE",
    "sg:address":"Greimharting 2",
    "sg:city":"Rimsting",
    "sg:phone":"+49 8051/64656",
    "sg:postcode":"83253",
    "sg:province":"Bayern",
    "wof:name":"Georg Heindl Gmbh",
    "wof:placetype":"venue"
},
  "geometry": {"coordinates":[12.3187122345,47.8696136475],"type":"Point"}
}