{
  "type": "Feature",
  "properties": {
    "iso:country":"DE",
    "sg:address":"Bahnhofstr. 12",
    "sg:city":"Fulda",
    "sg:phone":"+49 661/928030",
    "sg:postcode":"36037",
    "sg:province":"Hessen",
    "wof:name":"Stadt-apotheke Bernd T\u00fcnsmeyer",
    "wof:placetype":"venue"
},
  "geometry": {"coordinates":[9.681614,50.553288],"type":"Point"}
}