{
  "type": "Feature",
  "properties": {
    "iso:country":"DE",
    "sg:address":"Puschkinstr. 37",
    "sg:city":"Coswig",
    "sg:phone":"+49 34903/64111",
    "sg:postcode":"06869",
    "sg:province":"Sachsen-Anhalt",
    "wof:name":"Bennewitz Klose Und Meybohm Rechtsanw\u00e4lte",
    "wof:placetype":"venue"
},
  "geometry": {"coordinates":[12.4508600235,51.8862457275],"type":"Point"}
}