{
  "type": "Feature",
  "properties": {
    "iso:country":"DE",
    "sg:address":"Uferweg 3",
    "sg:city":"S\u00fcdlohn",
    "sg:phone":"+49 2862/7110",
    "sg:postcode":"46354",
    "sg:province":"Nordrhein-Westfalen",
    "wof:name":"Heinz Schrieverhoff",
    "wof:placetype":"venue"
},
  "geometry": {"coordinates":[6.8606090546,51.9439888],"type":"Point"}
}