{
  "type": "Feature",
  "properties": {
    "iso:country":"DE",
    "sg:address":"Herrenstr. 10",
    "sg:city":"Harsefeld",
    "sg:phone":"+49 4164/4128",
    "sg:postcode":"21698",
    "sg:province":"Niedersachsen",
    "wof:name":"B\u00f6hmke Verwaltungs Gmbh",
    "wof:placetype":"venue"
},
  "geometry": {"coordinates":[9.499882,53.454197],"type":"Point"}
}