{
  "type": "Feature",
  "properties": {
    "iso:country":"DE",
    "sg:address":"Bismarckplatz 8",
    "sg:city":"Regensburg",
    "sg:phone":"+49 941/585660",
    "sg:postcode":"93047",
    "sg:province":"Bayern",
    "wof:name":"Ia Information Systems Ag",
    "wof:placetype":"venue"
},
  "geometry": {"coordinates":[12.090116,49.018803],"type":"Point"}
}