{
  "type": "Feature",
  "properties": {
    "iso:country":"DE",
    "sg:address":"Glash\u00fcttenstr. 58",
    "sg:city":"Quierschied",
    "sg:phone":"+49 6897/61482",
    "sg:postcode":"66287",
    "sg:province":"Saarland",
    "wof:name":"Moselst\u00fcbchen",
    "wof:placetype":"venue"
},
  "geometry": {"coordinates":[7.0569801331,49.3327026367],"type":"Point"}
}