{
  "type": "Feature",
  "properties": {
    "iso:country":"DE",
    "sg:address":"Bernh\u00e4user Hauptstr. 1",
    "sg:city":"Filderstadt",
    "sg:phone":"+49 711/703168",
    "sg:postcode":"70794",
    "sg:province":"Baden-W\u00fcrttemberg",
    "wof:name":"Domino Raumgestaltung",
    "wof:placetype":"venue"
},
  "geometry": {"coordinates":[9.2164020538,48.678314209],"type":"Point"}
}