{
  "type": "Feature",
  "properties": {
    "iso:country":"DE",
    "sg:address":"Am Holzweg 26",
    "sg:city":"Kriftel",
    "sg:phone":"+49 6192/971200",
    "sg:postcode":"65830",
    "sg:province":"Hessen",
    "wof:name":"Verband Deutscher Wohnwagen- Und Wohnmobil-hersteller E. V.",
    "wof:placetype":"venue"
},
  "geometry": {"coordinates":[8.478585,50.079254],"type":"Point"}
}