{
  "type": "Feature",
  "properties": {
    "iso:country":"DE",
    "sg:address":"Neumarkter Str. 29",
    "sg:city":"Berngau",
    "sg:phone":"+49 9181/8164",
    "sg:postcode":"92361",
    "sg:province":"Bayern",
    "wof:name":"Wm Reisen Walburga Meier",
    "wof:placetype":"venue"
},
  "geometry": {"coordinates":[11.4050645828,49.2520980835],"type":"Point"}
}