{
  "type": "Feature",
  "properties": {
    "iso:country":"DE",
    "sg:address":"Marktstr. 10",
    "sg:city":"Neustadt",
    "sg:phone":"+49 5032/2032",
    "sg:postcode":"31535",
    "sg:province":"Niedersachsen",
    "wof:name":"Ohlau & Hemme",
    "wof:placetype":"venue"
},
  "geometry": {"coordinates":[9.035198,49.817066],"type":"Point"}
}