{
  "type": "Feature",
  "properties": {
    "iso:country":"DE",
    "sg:address":"Bahnhofstr. 8",
    "sg:city":"Altmannstein",
    "sg:phone":"+49 9446/2289",
    "sg:postcode":"93336",
    "sg:province":"Bayern",
    "wof:name":"Theobald Brandl",
    "wof:placetype":"venue"
},
  "geometry": {"coordinates":[11.6494855881,48.8978118896],"type":"Point"}
}