{
  "type": "Feature",
  "properties": {
    "iso:country":"DE",
    "sg:address":"Bochumer Str. 178",
    "sg:city":"Recklinghausen",
    "sg:phone":"+49 2361/61701",
    "sg:postcode":"45661",
    "sg:province":"Nordrhein-Westfalen",
    "wof:name":"K.o. M\u00f6ller",
    "wof:placetype":"venue"
},
  "geometry": {"coordinates":[7.211549,51.568939],"type":"Point"}
}