{
  "type": "Feature",
  "properties": {
    "iso:country":"DE",
    "sg:address":"Escherstr. 5",
    "sg:city":"Kirchwald",
    "sg:postcode":"56729",
    "sg:province":"Rheinland-Pfalz",
    "wof:name":"Hermann Josef Neis Gmbh",
    "wof:placetype":"venue"
},
  "geometry": {"coordinates":[7.0318398476,50.3492660522],"type":"Point"}
}