{
  "type": "Feature",
  "properties": {
    "iso:country":"DE",
    "sg:address":"Fuggerstr. 62",
    "sg:city":"Wasserburg",
    "sg:phone":"+49 8382/3544",
    "sg:postcode":"88142",
    "sg:province":"Bayern",
    "wof:name":"Gastst\u00e4tte Max Greising",
    "wof:placetype":"venue"
},
  "geometry": {"coordinates":[9.6546287537,47.565776825],"type":"Point"}
}