{
  "type": "Feature",
  "properties": {
    "iso:country":"DE",
    "sg:address":"Meimsheimer Str. 14",
    "sg:city":"Brackenheim",
    "sg:phone":"+49 7135/6623",
    "sg:postcode":"74336",
    "sg:province":"Baden-W\u00fcrttemberg",
    "wof:name":"Hans Dittus Architekt",
    "wof:placetype":"venue"
},
  "geometry": {"coordinates":[9.07915,49.084225],"type":"Point"}
}