{
  "type": "Feature",
  "properties": {
    "iso:country":"DE",
    "sg:address":"Mittermayerweg 45",
    "sg:city":"Darmstadt",
    "sg:phone":"+49 6151/75526",
    "sg:postcode":"64289",
    "sg:province":"Hessen",
    "wof:name":"Dr. Dieter D\u00fcmmerling Rechtsanwalt",
    "wof:placetype":"venue"
},
  "geometry": {"coordinates":[8.6891040802,49.8949279785],"type":"Point"}
}