{
  "type": "Feature",
  "properties": {
    "iso:country":"DE",
    "sg:address":"Torgauer Str. 4",
    "sg:city":"Dresden",
    "sg:phone":"+49 351/8484653",
    "sg:postcode":"01127",
    "sg:province":"Sachsen",
    "wof:name":"Volksmissionskreis Sachsen E. V.",
    "wof:placetype":"venue"
},
  "geometry": {"coordinates":[13.722407341,51.0753898621],"type":"Point"}
}