{
  "type": "Feature",
  "properties": {
    "iso:country":"DE",
    "sg:address":"Augsburger Str. 45",
    "sg:city":"Schrobenhausen",
    "sg:postcode":"86529",
    "sg:province":"Bayern",
    "wof:name":"E-center",
    "wof:placetype":"venue"
},
  "geometry": {"coordinates":[11.2620868683,48.5513916016],"type":"Point"}
}