{
  "type": "Feature",
  "properties": {
    "iso:country":"DE",
    "sg:address":"Schulgasse 16",
    "sg:city":"Regen",
    "sg:phone":"+49 9921/3702",
    "sg:postcode":"94209",
    "sg:province":"Bayern",
    "wof:name":"Alois Rauch",
    "wof:placetype":"venue"
},
  "geometry": {"coordinates":[13.123614,48.969879],"type":"Point"}
}