{
  "type": "Feature",
  "properties": {
    "iso:country":"DE",
    "sg:address":"Adenauerstr. 100",
    "sg:city":"Marienfeld",
    "sg:phone":"+49 5247/8525",
    "sg:postcode":"33428",
    "sg:province":"Nordrhein-Westfalen",
    "wof:name":"Karl-heinz Markmann",
    "wof:placetype":"venue"
},
  "geometry": {"coordinates":[8.26438,51.949841],"type":"Point"}
}