{
  "type": "Feature",
  "properties": {
    "iso:country":"DE",
    "sg:address":"Hausbayer Str. 8",
    "sg:city":"Pfalzfeld",
    "sg:phone":"+49 6746/9300",
    "sg:postcode":"56291",
    "sg:province":"Rheinland-Pfalz",
    "wof:name":"M. M. M\u00fcller Backwaren Gmbh",
    "wof:placetype":"venue"
},
  "geometry": {"coordinates":[7.577449,50.112316],"type":"Point"}
}