{
  "type": "Feature",
  "properties": {
    "iso:country":"DE",
    "sg:address":"Wilhelmstr. 25",
    "sg:city":"Crailsheim",
    "sg:phone":"+49 7951/5623",
    "sg:postcode":"74564",
    "sg:province":"Baden-W\u00fcrttemberg",
    "wof:name":"Kaufhaus Woha Drexel Gmbh",
    "wof:placetype":"venue"
},
  "geometry": {"coordinates":[10.07023,49.13842],"type":"Point"}
}