{
  "type": "Feature",
  "properties": {
    "iso:country":"DE",
    "sg:address":"Hauptstr.",
    "sg:city":"Niedersch\u00f6nenfeld",
    "sg:postcode":"86694",
    "sg:province":"Bayern",
    "wof:name":"J. Marb",
    "wof:placetype":"venue"
},
  "geometry": {"coordinates":[10.9111289978,48.7057151794],"type":"Point"}
}