{
  "type": "Feature",
  "properties": {
    "iso:country":"DE",
    "sg:address":"Meisterstr. 15",
    "sg:city":"Langelsheim",
    "sg:phone":"+49 5326/2539",
    "sg:postcode":"38685",
    "sg:province":"Niedersachsen",
    "wof:name":"Biedermann",
    "wof:placetype":"venue"
},
  "geometry": {"coordinates":[10.3354949951,51.9370155334],"type":"Point"}
}