{
  "type": "Feature",
  "properties": {
    "iso:country":"DE",
    "sg:address":"Schellertstr. 58",
    "sg:city":"Rietberg",
    "sg:phone":"+49 5244/5196",
    "sg:postcode":"33397",
    "sg:province":"Nordrhein-Westfalen",
    "wof:name":"Antonius Hartk\u00e4mper",
    "wof:placetype":"venue"
},
  "geometry": {"coordinates":[8.45178,51.820236],"type":"Point"}
}