{
  "type": "Feature",
  "properties": {
    "iso:country":"DE",
    "sg:address":"Karl-Rolle-Str. 43",
    "sg:city":"Eggenfelden",
    "sg:phone":"+49 8721/507243",
    "sg:postcode":"84307",
    "sg:province":"Bayern",
    "wof:name":"S\u00dcwa Produktions Gmbh",
    "wof:placetype":"venue"
},
  "geometry": {"coordinates":[12.7500267029,48.4058952332],"type":"Point"}
}