{
  "type": "Feature",
  "properties": {
    "iso:country":"DE",
    "sg:address":"Rheinstr. 29",
    "sg:city":"Rheinstetten",
    "sg:phone":"+49 7242/6636",
    "sg:postcode":"76287",
    "sg:province":"Baden-W\u00fcrttemberg",
    "wof:name":"Hans Schneider",
    "wof:placetype":"venue"
},
  "geometry": {"coordinates":[8.265162468,48.9715042114],"type":"Point"}
}