{
  "type": "Feature",
  "properties": {
    "iso:country":"DE",
    "sg:address":"Wiesenweg 22",
    "sg:city":"Fa\u00dfberg",
    "sg:phone":"+49 5053/1228",
    "sg:postcode":"29328",
    "sg:province":"Niedersachsen",
    "wof:name":"Elektro Bruns Gmbh",
    "wof:placetype":"venue"
},
  "geometry": {"coordinates":[10.122224,52.869289],"type":"Point"}
}