{
  "type": "Feature",
  "properties": {
    "iso:country":"DE",
    "sg:address":"Schenkendorfstr. 8",
    "sg:city":"Regensburg",
    "sg:phone":"+49 941/26739",
    "sg:postcode":"93049",
    "sg:province":"Bayern",
    "wof:name":"Wolfgang Rohde Krankengymnast",
    "wof:placetype":"venue"
},
  "geometry": {"coordinates":[12.078072,49.021065],"type":"Point"}
}