{
  "type": "Feature",
  "properties": {
    "iso:country":"DE",
    "sg:address":"Bernecker Str. 9",
    "sg:city":"Marktschorgast",
    "sg:phone":"+49 9227/940010",
    "sg:postcode":"95509",
    "sg:province":"Bayern",
    "wof:name":"Napos Kunststoffverarbeitung Gmbh",
    "wof:placetype":"venue"
},
  "geometry": {"coordinates":[11.6541385651,50.090133667],"type":"Point"}
}