{
  "type": "Feature",
  "properties": {
    "iso:country":"DE",
    "sg:address":"Neubaustr. 32",
    "sg:city":"Prosselsheim",
    "sg:phone":"+49 9386/99920",
    "sg:postcode":"97279",
    "sg:province":"Bayern",
    "wof:name":"Bsg Bau-service-gbr",
    "wof:placetype":"venue"
},
  "geometry": {"coordinates":[10.1292495728,49.8618431091],"type":"Point"}
}