{
  "type": "Feature",
  "properties": {
    "iso:country":"DE",
    "sg:address":"Burghof 5",
    "sg:city":"Lindlar",
    "sg:phone":"+49 2206/2717",
    "sg:postcode":"51789",
    "sg:province":"Nordrhein-Westfalen",
    "wof:name":"Kath. Pfarrb\u00fccherei",
    "wof:placetype":"venue"
},
  "geometry": {"coordinates":[7.310228,50.980278],"type":"Point"}
}