{
  "type": "Feature",
  "properties": {
    "iso:country":"DE",
    "sg:address":"Birken\u00f6sch 10",
    "sg:city":"Pfullendorf",
    "sg:phone":"+49 7552/5765",
    "sg:postcode":"88630",
    "sg:province":"Baden-W\u00fcrttemberg",
    "wof:name":"R. & S. Frickinger",
    "wof:placetype":"venue"
},
  "geometry": {"coordinates":[9.197938,47.911797],"type":"Point"}
}