{
  "type": "Feature",
  "properties": {
    "iso:country":"DE",
    "sg:address":"Ro\u00dfdorfer Str. 17",
    "sg:city":"Frankfurt",
    "sg:phone":"+49 69/439690",
    "sg:postcode":"60385",
    "sg:province":"Hessen",
    "wof:name":"Reiner K\u00f6pnick",
    "wof:placetype":"venue"
},
  "geometry": {"coordinates":[8.706895,50.123821],"type":"Point"}
}