{
  "type": "Feature",
  "properties": {
    "iso:country":"DE",
    "sg:address":"B\u00e4ckergasse 8",
    "sg:city":"Euerbach",
    "sg:phone":"+49 9726/1609",
    "sg:postcode":"97502",
    "sg:province":"Bayern",
    "wof:name":"Franz Thews Heilpraktiker",
    "wof:placetype":"venue"
},
  "geometry": {"coordinates":[10.0945110321,50.0753593445],"type":"Point"}
}