{
  "type": "Feature",
  "properties": {
    "iso:country":"DE",
    "sg:address":"Wasserwiesen 32",
    "sg:city":"Balingen",
    "sg:phone":"+49 7433/21517",
    "sg:postcode":"72336",
    "sg:province":"Baden-W\u00fcrttemberg",
    "wof:name":"Angeletti Gmbh",
    "wof:placetype":"venue"
},
  "geometry": {"coordinates":[8.852175,48.258587],"type":"Point"}
}