{
  "type": "Feature",
  "properties": {
    "iso:country":"DE",
    "sg:address":"Schulstr. 22",
    "sg:city":"Trostberg",
    "sg:phone":"+49 8621/979890",
    "sg:postcode":"83308",
    "sg:province":"Bayern",
    "wof:name":"Bestattungsinstitut Denk Gmbh Trauerhilfe Kg",
    "wof:placetype":"venue"
},
  "geometry": {"coordinates":[12.556176,48.028713],"type":"Point"}
}