{
  "type": "Feature",
  "properties": {
    "iso:country":"DE",
    "sg:address":"Vautierstr. 73",
    "sg:city":"D\u00fcsseldorf",
    "sg:postcode":"40235",
    "sg:province":"Nordrhein-Westfalen",
    "wof:name":"Erkens",
    "wof:placetype":"venue"
},
  "geometry": {"coordinates":[6.8233308792,51.2419891357],"type":"Point"}
}