{
  "type": "Feature",
  "properties": {
    "iso:country":"DE",
    "sg:address":"Lange Str. 9",
    "sg:city":"Lippstadt",
    "sg:phone":"+49 2941/58096",
    "sg:postcode":"59555",
    "sg:province":"Nordrhein-Westfalen",
    "wof:name":"Gastst\u00e4tte A. Landgr\u00e4ber",
    "wof:placetype":"venue"
},
  "geometry": {"coordinates":[8.3466043472,51.6766624451],"type":"Point"}
}