{
  "type": "Feature",
  "properties": {
    "iso:country":"DE",
    "sg:address":"Waldstr. 38",
    "sg:city":"Tr\u00f6stau",
    "sg:phone":"+49 9232/2001",
    "sg:postcode":"95709",
    "sg:province":"Bayern",
    "wof:name":"Wittig Baugesch\u00e4ft Gmbh",
    "wof:placetype":"venue"
},
  "geometry": {"coordinates":[11.943189,50.010517],"type":"Point"}
}