{
  "type": "Feature",
  "properties": {
    "iso:country":"DE",
    "sg:address":"Lohstr. 29",
    "sg:city":"Osnabr\u00fcck",
    "sg:phone":"+49 541/2599891",
    "sg:postcode":"49074",
    "sg:province":"Niedersachsen",
    "wof:name":"Gastst\u00e4tte Lohgerber",
    "wof:placetype":"venue"
},
  "geometry": {"coordinates":[8.0427131653,52.2795944214],"type":"Point"}
}