{
  "type": "Feature",
  "properties": {
    "iso:country":"DE",
    "sg:address":"Papenstr. 84A",
    "sg:city":"Hamburg",
    "sg:phone":"+49 40/208850",
    "sg:postcode":"22089",
    "sg:province":"Hamburg",
    "wof:name":"Hasta-archiv Gmbh",
    "wof:placetype":"venue"
},
  "geometry": {"coordinates":[10.045923,53.565269],"type":"Point"}
}