{
  "type": "Feature",
  "properties": {
    "iso:country":"DE",
    "sg:address":"F\u00e4rberstr. 76",
    "sg:city":"D\u00fcsseldorf",
    "sg:phone":"+49 211/720372",
    "sg:postcode":"40223",
    "sg:province":"Nordrhein-Westfalen",
    "wof:name":"Ig Malerwerkst\u00e4tte Gmbh",
    "wof:placetype":"venue"
},
  "geometry": {"coordinates":[6.785846,51.209538],"type":"Point"}
}