{
  "type": "Feature",
  "properties": {
    "iso:country":"DE",
    "sg:address":"Hauptstr. 62",
    "sg:city":"Sulzfeld",
    "sg:phone":"+49 7269/515",
    "sg:postcode":"75056",
    "sg:province":"Baden-W\u00fcrttemberg",
    "wof:name":"Pizzeria Grillstube",
    "wof:placetype":"venue"
},
  "geometry": {"coordinates":[8.8569908142,49.1038246155],"type":"Point"}
}