{
  "type": "Feature",
  "properties": {
    "iso:country":"DE",
    "sg:address":"August-Bebel-Str. 8",
    "sg:city":"Grimma",
    "sg:phone":"+49 3437/763092",
    "sg:postcode":"04668",
    "sg:province":"Sachsen",
    "wof:name":"Lutz Engel",
    "wof:placetype":"venue"
},
  "geometry": {"coordinates":[12.7225036621,51.2356033325],"type":"Point"}
}