{
  "type": "Feature",
  "properties": {
    "iso:country":"DE",
    "sg:address":"Am Markt 12",
    "sg:city":"Melsungen",
    "sg:phone":"+49 5661/923890",
    "sg:postcode":"34212",
    "sg:province":"Hessen",
    "wof:name":"Bekleidungshaus Gleim Gmbh",
    "wof:placetype":"venue"
},
  "geometry": {"coordinates":[9.543536,51.131577],"type":"Point"}
}