{
  "type": "Feature",
  "properties": {
    "iso:country":"DE",
    "sg:address":"Nieringser Weg 21a",
    "sg:city":"Hemer",
    "sg:phone":"+49 2372/60783",
    "sg:postcode":"58675",
    "sg:province":"Nordrhein-Westfalen",
    "wof:name":"Friedrich Amelung Rechtsanwalt Und Notar",
    "wof:placetype":"venue"
},
  "geometry": {"coordinates":[7.8020610809,51.3742828369],"type":"Point"}
}