{
  "type": "Feature",
  "properties": {
    "iso:country":"DE",
    "sg:address":"Haselweg 1",
    "sg:city":"Ottobrunn",
    "sg:phone":"+49 89/6081110",
    "sg:postcode":"85521",
    "sg:province":"Bayern",
    "wof:name":"Pc Data Dv-systeme Verwaltungs Gmbh",
    "wof:placetype":"venue"
},
  "geometry": {"coordinates":[11.6575088501,48.0597648621],"type":"Point"}
}