{
  "type": "Feature",
  "properties": {
    "iso:country":"DE",
    "sg:address":"Borchersweg 25",
    "sg:city":"Oldenburg",
    "sg:phone":"+49 441",
    "sg:postcode":"26135",
    "sg:province":"Niedersachsen",
    "wof:name":"Autorecycling Wiechmann",
    "wof:placetype":"venue"
},
  "geometry": {"coordinates":[8.2761716843,53.1051940918],"type":"Point"}
}