{
  "type": "Feature",
  "properties": {
    "iso:country":"DE",
    "sg:address":"Schmiedestr. 29",
    "sg:city":"Hannover",
    "sg:phone":"+49 511/3631153",
    "sg:postcode":"30159",
    "sg:province":"Niedersachsen",
    "wof:name":"Hans-j\u00fcrgen Reichardt",
    "wof:placetype":"venue"
},
  "geometry": {"coordinates":[9.734317,52.373894],"type":"Point"}
}