{
  "type": "Feature",
  "properties": {
    "iso:country":"DE",
    "sg:address":"Obere Dorfstr. 2",
    "sg:city":"K\u00f6tz",
    "sg:phone":"+49 8221/4197",
    "sg:postcode":"89359",
    "sg:province":"Bayern",
    "wof:name":"W. M\u00fcller",
    "wof:placetype":"venue"
},
  "geometry": {"coordinates":[10.2729463577,48.4070625305],"type":"Point"}
}