{
  "type": "Feature",
  "properties": {
    "iso:country":"DE",
    "sg:address":"Altnaundorf 25",
    "sg:city":"Radebeul",
    "sg:phone":"+49 351/8360353",
    "sg:postcode":"01445",
    "sg:province":"Sachsen",
    "wof:name":"Apv Bautr\u00e4ger Gmbh",
    "wof:placetype":"venue"
},
  "geometry": {"coordinates":[13.606567,51.112164],"type":"Point"}
}