{
  "type": "Feature",
  "properties": {
    "iso:country":"DE",
    "sg:address":"Deichslerstr. 13",
    "sg:city":"N\u00fcrnberg",
    "sg:phone":"+49 911/5303640",
    "sg:postcode":"90489",
    "sg:province":"Bayern",
    "wof:name":"Giovanni Di Noia",
    "wof:placetype":"venue"
},
  "geometry": {"coordinates":[11.101608,49.458347],"type":"Point"}
}