{
  "type": "Feature",
  "properties": {
    "iso:country":"DE",
    "sg:address":"Holmweg 45",
    "sg:city":"Langenhorn",
    "sg:phone":"+49 4672/470",
    "sg:postcode":"25842",
    "sg:province":"Schleswig-Holstein",
    "wof:name":"Helmuth Sievertsen Inh. Johann R\u00fccker",
    "wof:placetype":"venue"
},
  "geometry": {"coordinates":[8.935415,54.674152],"type":"Point"}
}