{
  "type": "Feature",
  "properties": {
    "iso:country":"DE",
    "sg:address":"J\u00e4gerhausstr. 22",
    "sg:city":"Simmerath",
    "sg:phone":"+49 4924/736010",
    "sg:postcode":"52152",
    "sg:province":"Nordrhein-Westfalen",
    "wof:name":"Otto Junker Gmbh",
    "wof:placetype":"venue"
},
  "geometry": {"coordinates":[6.267702,50.640533],"type":"Point"}
}