{
  "type": "Feature",
  "properties": {
    "iso:country":"DE",
    "sg:address":"Weidenbacherstr.9",
    "sg:city":"Kesseling",
    "sg:phone":"+49 2647",
    "sg:postcode":"53506",
    "sg:province":"Rheinland-Pfalz",
    "wof:name":"Elektro Czuba Gmbh, Elektroinstallationen Aller Ar",
    "wof:placetype":"venue"
},
  "geometry": {"coordinates":[7.025167,50.481022],"type":"Point"}
}