{
  "type": "Feature",
  "properties": {
    "iso:country":"DE",
    "sg:address":"Weinberge 26",
    "sg:city":"Zossen",
    "sg:phone":"+49 3377/302389",
    "sg:postcode":"15806",
    "sg:province":"Brandenburg",
    "wof:name":"H & H Software Jens Heinrich",
    "wof:placetype":"venue"
},
  "geometry": {"coordinates":[13.4669151306,52.20495224],"type":"Point"}
}