{
  "type": "Feature",
  "properties": {
    "iso:country":"DE",
    "sg:address":"Birkenweg 1",
    "sg:city":"Ziemetshausen",
    "sg:phone":"+49 8284/338",
    "sg:postcode":"86473",
    "sg:province":"Bayern",
    "wof:name":"Josef Vogele",
    "wof:placetype":"venue"
},
  "geometry": {"coordinates":[10.534054,48.29063],"type":"Point"}
}