{
  "type": "Feature",
  "properties": {
    "iso:country":"DE",
    "sg:address":"An St. Swidbert 10",
    "sg:city":"D\u00fcsseldorf",
    "sg:phone":"+49 211/407265",
    "sg:postcode":"40489",
    "sg:province":"Nordrhein-Westfalen",
    "wof:name":"Gerhild Siegel",
    "wof:placetype":"venue"
},
  "geometry": {"coordinates":[6.735932827,51.3009490967],"type":"Point"}
}