{
  "type": "Feature",
  "properties": {
    "iso:country":"DE",
    "sg:address":"Kirchheimer Str. 25",
    "sg:city":"Gr\u00fcnstadt",
    "sg:phone":"+49 6359/3107",
    "sg:postcode":"67269",
    "sg:province":"Rheinland-Pfalz",
    "wof:name":"Horst Schmitt",
    "wof:placetype":"venue"
},
  "geometry": {"coordinates":[8.166303,49.56234],"type":"Point"}
}