{
  "type": "Feature",
  "properties": {
    "iso:country":"DE",
    "sg:address":"Neum\u00fchleweg 32",
    "sg:city":"Urbach",
    "sg:phone":"+49 7181/81071",
    "sg:postcode":"73660",
    "sg:province":"Baden-W\u00fcrttemberg",
    "wof:name":"Hotel Zur M\u00fchle",
    "wof:placetype":"venue"
},
  "geometry": {"coordinates":[9.5733413696,48.8081893921],"type":"Point"}
}