{
  "type": "Feature",
  "properties": {
    "iso:country":"DE",
    "sg:address":"Barfusstr. 16",
    "sg:city":"Berlin",
    "sg:phone":"+49 30/4525058",
    "sg:postcode":"13349",
    "sg:province":"Berlin",
    "wof:name":"Gastst\u00e4tte Schillerh\u00fctte",
    "wof:placetype":"venue"
},
  "geometry": {"coordinates":[13.3474693298,52.555644989],"type":"Point"}
}