{
  "type": "Feature",
  "properties": {
    "iso:country":"DE",
    "sg:address":"Cheruskerstr. 67",
    "sg:city":"D\u00fcsseldorf",
    "sg:phone":"+49 211/572141",
    "sg:postcode":"40545",
    "sg:province":"Nordrhein-Westfalen",
    "wof:name":"Kl\u00e4hn Und Samnee Rechtsanw\u00e4lte",
    "wof:placetype":"venue"
},
  "geometry": {"coordinates":[6.7514519691,51.2302742004],"type":"Point"}
}