{
  "type": "Feature",
  "properties": {
    "iso:country":"DE",
    "sg:address":"Eys\u00f6lden",
    "sg:city":"Eys\u00f6lden",
    "sg:phone":"+49 9173/1611",
    "sg:postcode":"93107",
    "sg:province":"Bayern",
    "wof:name":"Sparkasse Eys\u00f6lden",
    "wof:placetype":"venue"
},
  "geometry": {"coordinates":[-119.698853,34.419239],"type":"Point"}
}