{
  "type": "Feature",
  "properties": {
    "iso:country":"DE",
    "sg:address":"P\u00fctzlachstr. 15",
    "sg:city":"K\u00f6ln",
    "sg:phone":"+49 221/662802",
    "sg:postcode":"51061",
    "sg:province":"Nordrhein-Westfalen",
    "wof:name":"P. Gilberg",
    "wof:placetype":"venue"
},
  "geometry": {"coordinates":[6.976065,51.00148],"type":"Point"}
}