{
  "type": "Feature",
  "properties": {
    "iso:country":"DE",
    "sg:address":"In der Hohl 5",
    "sg:city":"Gehlweiler",
    "sg:phone":"+49 6765/312",
    "sg:postcode":"55490",
    "sg:province":"Rheinland-Pfalz",
    "wof:name":"Emil Michel",
    "wof:placetype":"venue"
},
  "geometry": {"coordinates":[7.466415,49.882786],"type":"Point"}
}