{
  "type": "Feature",
  "properties": {
    "iso:country":"DE",
    "sg:address":"Parkstr. 1",
    "sg:city":"Treuenbrietzen",
    "sg:phone":"+49 33748/15291",
    "sg:postcode":"14929",
    "sg:province":"Brandenburg",
    "wof:name":"Fiedler Leistner Schwerdt",
    "wof:placetype":"venue"
},
  "geometry": {"coordinates":[12.86856,52.092541],"type":"Point"}
}