{
  "type": "Feature",
  "properties": {
    "iso:country":"DE",
    "sg:address":"Eberhardstr. 45",
    "sg:city":"Fellbach",
    "sg:phone":"+49 711/5781175",
    "sg:postcode":"70736",
    "sg:province":"Baden-W\u00fcrttemberg",
    "wof:name":"Pedalo Werner Sch\u00fcle",
    "wof:placetype":"venue"
},
  "geometry": {"coordinates":[9.276052,48.815849],"type":"Point"}
}