{
  "type": "Feature",
  "properties": {
    "iso:country":"DE",
    "sg:address":"Heessener Dorfstr 46",
    "sg:city":"Hamm",
    "sg:phone":"+49 2381/38250",
    "sg:postcode":"59073",
    "sg:province":"Nordrhein-Westfalen",
    "wof:name":"Sparding",
    "wof:placetype":"venue"
},
  "geometry": {"coordinates":[7.8395757675,51.7050514221],"type":"Point"}
}