{
  "type": "Feature",
  "properties": {
    "iso:country":"DE",
    "sg:address":"Schlachthausstr. 30",
    "sg:city":"G\u00fcnzburg",
    "sg:phone":"+49 8221/251289",
    "sg:postcode":"89312",
    "sg:province":"Bayern",
    "wof:name":"Elisabeth Kr\u00fcger",
    "wof:placetype":"venue"
},
  "geometry": {"coordinates":[10.2745361328,48.4568443298],"type":"Point"}
}