{
  "type": "Feature",
  "properties": {
    "iso:country":"DE",
    "sg:address":"Heinrichstr. 8",
    "sg:city":"Fulda",
    "sg:phone":"+49 661/75455",
    "sg:postcode":"36037",
    "sg:province":"Hessen",
    "wof:name":"Theo M\u00fcller Optik Gmbh",
    "wof:placetype":"venue"
},
  "geometry": {"coordinates":[9.6816129684,50.5537567139],"type":"Point"}
}