{
  "type": "Feature",
  "properties": {
    "iso:country":"DE",
    "sg:address":"Peterstr. 1",
    "sg:city":"Westerstede",
    "sg:phone":"+49 4488/6090",
    "sg:postcode":"26655",
    "sg:province":"Niedersachsen",
    "wof:name":"A. Meisner",
    "wof:placetype":"venue"
},
  "geometry": {"coordinates":[7.9271740913,53.2569313049],"type":"Point"}
}