{
  "type": "Feature",
  "properties": {
    "iso:country":"DE",
    "sg:address":"Postfach 1028:: 68790 Oberhausen-Rheinhausen:: Germany.^^Adlerstr 1::",
    "sg:city":"Oberhausen-Rheinhausen",
    "sg:phone":"+49 7254/2060",
    "sg:postcode":"68794",
    "sg:province":"Baden-W\u00fcrttemberg",
    "wof:name":"Bruhrainer Volksbank Eg",
    "wof:placetype":"venue"
},
  "geometry": {"coordinates":[8.483247,49.260353],"type":"Point"}
}