{
  "type": "Feature",
  "properties": {
    "iso:country":"DE",
    "sg:address":"Wilhelmstr. 6",
    "sg:city":"Bad Liebenzell",
    "sg:phone":"+49 7052/924644",
    "sg:postcode":"75378",
    "sg:province":"Baden-W\u00fcrttemberg",
    "wof:name":"Icg Immobilien Christian Genthner",
    "wof:placetype":"venue"
},
  "geometry": {"coordinates":[8.7315826416,48.7718315125],"type":"Point"}
}