{
  "type": "Feature",
  "properties": {
    "iso:country":"DE",
    "sg:address":"Borntaler Hof",
    "sg:city":"Osthofen",
    "sg:phone":"+49 172 6248882",
    "sg:postcode":"67574",
    "sg:province":"Rheinland-Pfalz",
    "wof:name":"Franz Lang",
    "wof:placetype":"venue"
},
  "geometry": {"coordinates":[8.3218402863,49.703792572],"type":"Point"}
}