{
  "type": "Feature",
  "properties": {
    "iso:country":"DE",
    "sg:address":"Preu\u00dfenrg. 46",
    "sg:city":"Minden",
    "sg:phone":"+49 4957/1828860",
    "sg:postcode":"32427",
    "sg:province":"Nordrhein-Westfalen",
    "wof:name":"Sieckmann Bad- U. Heizung Gmbh",
    "wof:placetype":"venue"
},
  "geometry": {"coordinates":[8.88832,52.292759],"type":"Point"}
}