{
  "type": "Feature",
  "properties": {
    "iso:country":"DE",
    "sg:address":"Auerbacher Str. 270 a",
    "sg:city":"Klingenthal",
    "sg:phone":"+49 37467/22003",
    "sg:postcode":"08248",
    "sg:province":"Sachsen",
    "wof:name":"Lothar Lucas",
    "wof:placetype":"venue"
},
  "geometry": {"coordinates":[12.483384,50.384575],"type":"Point"}
}