{
  "type": "Feature",
  "properties": {
    "iso:country":"DE",
    "sg:address":"F\u00fcnffensterstr. 5",
    "sg:city":"Kassel",
    "sg:postcode":"34117",
    "sg:province":"Hessen",
    "wof:name":"Direct Services Ag",
    "wof:placetype":"venue"
},
  "geometry": {"coordinates":[9.490534,51.313011],"type":"Point"}
}