{
  "type": "Feature",
  "properties": {
    "iso:country":"DE",
    "sg:city":"Boren",
    "sg:postcode":"24392",
    "sg:province":"Schleswig-Holstein",
    "wof:name":"Thopa Ges. F\u00fcr Umweltfreund- Liche Energieumwandlung Mbh",
    "wof:placetype":"venue"
},
  "geometry": {"coordinates":[9.81812,54.613579],"type":"Point"}
}