{
  "type": "Feature",
  "properties": {
    "iso:country":"DE",
    "sg:address":"Rheingoldstr. 116",
    "sg:city":"Manubach",
    "sg:phone":"+49 6743/2943",
    "sg:postcode":"55413",
    "sg:province":"Rheinland-Pfalz",
    "wof:name":"Edelfaul",
    "wof:placetype":"venue"
},
  "geometry": {"coordinates":[7.7553739548,50.0305976868],"type":"Point"}
}