{
  "type": "Feature",
  "properties": {
    "iso:country":"DE",
    "sg:address":"Marktplatz 5",
    "sg:city":"Esslingen",
    "sg:phone":"+49 711/354484",
    "sg:postcode":"73728",
    "sg:province":"Baden-W\u00fcrttemberg",
    "wof:name":"Taekwondo-schule",
    "wof:placetype":"venue"
},
  "geometry": {"coordinates":[9.305981636,48.743106842],"type":"Point"}
}