{
  "type": "Feature",
  "properties": {
    "iso:country":"DE",
    "sg:address":"Obere K\u00f6nigstr. 53 a",
    "sg:city":"Bamberg",
    "sg:phone":"+49 951/22948",
    "sg:postcode":"96052",
    "sg:province":"Bayern",
    "wof:name":"Schwanen-apotheke",
    "wof:placetype":"venue"
},
  "geometry": {"coordinates":[10.895502,49.896969],"type":"Point"}
}