{
  "type": "Feature",
  "properties": {
    "iso:country":"DE",
    "sg:address":"Fischerweg 10 a",
    "sg:city":"Wunstorf",
    "sg:phone":"+49 5033/5315",
    "sg:postcode":"31515",
    "sg:province":"Niedersachsen",
    "wof:name":"Carl Riebe",
    "wof:placetype":"venue"
},
  "geometry": {"coordinates":[9.356111,52.456398],"type":"Point"}
}