{
  "type": "Feature",
  "properties": {
    "iso:country":"DE",
    "sg:address":"Hessenring 13 A",
    "sg:city":"Moerfelden-Walldorf",
    "sg:phone":"+49 4961/052050",
    "sg:postcode":"64546",
    "sg:province":"Hessen",
    "wof:name":"Nike International Ndl Deutschland Ltd",
    "wof:placetype":"venue"
},
  "geometry": {"coordinates":[8.585397,49.98645],"type":"Point"}
}