{
  "type": "Feature",
  "properties": {
    "iso:country":"DE",
    "sg:address":"Gro\u00dfer Fledderweg 91",
    "sg:city":"Osnabr\u00fcck",
    "sg:phone":"+49 541/505090",
    "sg:postcode":"49084",
    "sg:province":"Niedersachsen",
    "wof:name":"Georg Schober Beteiligungs Gmbh",
    "wof:placetype":"venue"
},
  "geometry": {"coordinates":[8.07257,52.264572],"type":"Point"}
}