{
  "type": "Feature",
  "properties": {
    "iso:country":"DE",
    "sg:address":"Lauterbacher Str. 9",
    "sg:city":"Ulrichstein",
    "sg:phone":"+49 6645/292",
    "sg:postcode":"35327",
    "sg:province":"Hessen",
    "wof:name":"Darmst\u00e4dter Hof",
    "wof:placetype":"venue"
},
  "geometry": {"coordinates":[9.1862611771,50.552116394],"type":"Point"}
}