{
  "type": "Feature",
  "properties": {
    "iso:country":"DE",
    "sg:address":"Ochtruper Str. 8",
    "sg:city":"Bad Bentheim",
    "sg:phone":"+49 5922/5214",
    "sg:postcode":"48455",
    "sg:province":"Niedersachsen",
    "wof:name":"Warsteiner Treff",
    "wof:placetype":"venue"
},
  "geometry": {"coordinates":[7.1613440514,52.3010559082],"type":"Point"}
}