{
  "type": "Feature",
  "properties": {
    "iso:country":"DE",
    "sg:address":"Aswinstr. 1",
    "sg:city":"Bogen",
    "sg:phone":"+49 9422/85520",
    "sg:postcode":"94327",
    "sg:province":"Bayern",
    "wof:name":"Weber",
    "wof:placetype":"venue"
},
  "geometry": {"coordinates":[12.684676,48.910965],"type":"Point"}
}