{
  "type": "Feature",
  "properties": {
    "iso:country":"DE",
    "sg:address":"Brookgang 43",
    "sg:city":"Gr\u00f6mitz",
    "sg:phone":"+49 4562/5663",
    "sg:postcode":"23743",
    "sg:province":"Schleswig-Holstein",
    "wof:name":"E. Petersen Verleihbetrieb",
    "wof:placetype":"venue"
},
  "geometry": {"coordinates":[10.9609241486,54.1523857117],"type":"Point"}
}