{
  "type": "Feature",
  "properties": {
    "iso:country":"DE",
    "sg:address":"Luisenstr. 3",
    "sg:city":"Offenbach",
    "sg:postcode":"63067",
    "sg:province":"Hessen",
    "wof:name":"Franz-georg Lannert E. K.",
    "wof:placetype":"venue"
},
  "geometry": {"coordinates":[8.759475708,50.0998344421],"type":"Point"}
}