{
  "type": "Feature",
  "properties": {
    "iso:country":"DE",
    "sg:address":"Friedrich-Engels-Str. 30",
    "sg:city":"Fuldatal",
    "sg:phone":"+49 5607/269",
    "sg:postcode":"34233",
    "sg:province":"Hessen",
    "wof:name":"K. Lifka Masseur",
    "wof:placetype":"venue"
},
  "geometry": {"coordinates":[9.516755,51.387733],"type":"Point"}
}