{
  "type": "Feature",
  "properties": {
    "iso:country":"DE",
    "sg:address":"Bergstr. 2a",
    "sg:city":"Schlepzig",
    "sg:phone":"+49 35472/6650",
    "sg:postcode":"15910",
    "sg:province":"Brandenburg",
    "wof:name":"Armaturen M. Schuster Gmbh",
    "wof:placetype":"venue"
},
  "geometry": {"coordinates":[13.904394,52.027084],"type":"Point"}
}