{
  "type": "Feature",
  "properties": {
    "iso:country":"DE",
    "sg:address":"Hauptstr 48",
    "sg:city":"Leipzig",
    "sg:phone":"+49 34297/13697",
    "sg:postcode":"04288",
    "sg:province":"Sachsen",
    "wof:name":"Tele-partner Elektro- Und Kommunikationstechnik Gmbh",
    "wof:placetype":"venue"
},
  "geometry": {"coordinates":[12.465792,51.311836],"type":"Point"}
}