{
  "type": "Feature",
  "properties": {
    "iso:country":"DE",
    "sg:address":"Pilsheim 1",
    "sg:city":"Burglengenfeld",
    "sg:phone":"+49 9474/910033",
    "sg:postcode":"93133",
    "sg:province":"Bayern",
    "wof:name":"Silvias Reiterladl",
    "wof:placetype":"venue"
},
  "geometry": {"coordinates":[11.961012,49.272209],"type":"Point"}
}