{
  "type": "Feature",
  "properties": {
    "iso:country":"DE",
    "sg:address":"Arthur-Piechler-Str. 14",
    "sg:city":"Augsburg",
    "sg:phone":"+49 821/564010",
    "sg:postcode":"86161",
    "sg:province":"Bayern",
    "wof:name":"Ingrid Bannwolf Steuerberaterin",
    "wof:placetype":"venue"
},
  "geometry": {"coordinates":[10.9184026718,48.3600692749],"type":"Point"}
}