{
  "type": "Feature",
  "properties": {
    "iso:country":"DE",
    "sg:address":"Ebertstra\u00dfe 1",
    "sg:city":"Gr\u00fcnwald",
    "sg:phone":"+49 89/6418910",
    "sg:postcode":"82031",
    "sg:province":"Bayern",
    "wof:name":"Gr\u00fcnwalder Freizeitpark",
    "wof:placetype":"venue"
},
  "geometry": {"coordinates":[11.5326709747,48.0506515503],"type":"Point"}
}