{
  "type": "Feature",
  "properties": {
    "iso:country":"DE",
    "sg:address":"Friedrich-Ratzel-Str. 2",
    "sg:city":"Angelbachtal",
    "sg:postcode":"74918",
    "sg:province":"Baden-W\u00fcrttemberg",
    "wof:name":"Aibig Mbh",
    "wof:placetype":"venue"
},
  "geometry": {"coordinates":[8.7713022232,49.2331848145],"type":"Point"}
}