{
  "type": "Feature",
  "properties": {
    "iso:country":"DE",
    "sg:address":"Industriestr. 6",
    "sg:city":"Hagen",
    "sg:postcode":"49170",
    "sg:province":"Niedersachsen",
    "wof:name":"Wolf Goege Automation Gmbh",
    "wof:placetype":"venue"
},
  "geometry": {"coordinates":[7.9151701927,52.2129592896],"type":"Point"}
}