{
  "type": "Feature",
  "properties": {
    "iso:country":"DE",
    "sg:address":"Hauptstr. 73",
    "sg:city":"R\u00f6srath",
    "sg:phone":"+49 2205/910306",
    "sg:postcode":"51503",
    "sg:province":"Nordrhein-Westfalen",
    "wof:name":"Fritz Wember",
    "wof:placetype":"venue"
},
  "geometry": {"coordinates":[7.1829719543,50.8993110657],"type":"Point"}
}