{
  "type": "Feature",
  "properties": {
    "iso:country":"DE",
    "sg:address":"Helene-Mayer-Str. 4 - 6",
    "sg:city":"Offenbach",
    "sg:phone":"+49 69/843280",
    "sg:postcode":"63069",
    "sg:province":"Hessen",
    "wof:name":"Vereinsgastst\u00e4tte Offenbacher Tennisclub E. V.",
    "wof:placetype":"venue"
},
  "geometry": {"coordinates":[8.7502641678,50.0983200073],"type":"Point"}
}