{
  "type": "Feature",
  "properties": {
    "iso:country":"DE",
    "sg:address":"Adenauerstr. 68",
    "sg:city":"Haren",
    "sg:phone":"+49 5932/2167",
    "sg:postcode":"49733",
    "sg:province":"Niedersachsen",
    "wof:name":"Gerhard Bramsmann",
    "wof:placetype":"venue"
},
  "geometry": {"coordinates":[7.215726,52.788509],"type":"Point"}
}