{
  "type": "Feature",
  "properties": {
    "iso:country":"DE",
    "sg:address":"Hauptstr. 71",
    "sg:city":"Bad Endbach",
    "sg:phone":"+49 2776/8050",
    "sg:postcode":"35080",
    "sg:province":"Hessen",
    "wof:name":"Hinterlang Und Burk Gmbh & Co. Kg",
    "wof:placetype":"venue"
},
  "geometry": {"coordinates":[8.457352,50.756008],"type":"Point"}
}