{
  "type": "Feature",
  "properties": {
    "iso:country":"DE",
    "sg:address":"Trennemoor 2",
    "sg:city":"Isernhagen",
    "sg:postcode":"30916",
    "sg:province":"Niedersachsen",
    "wof:name":"Callmax Gmbh",
    "wof:placetype":"venue"
},
  "geometry": {"coordinates":[9.8919897079,52.442150116],"type":"Point"}
}