{
  "type": "Feature",
  "properties": {
    "iso:country":"DE",
    "sg:address":"Am Alten Gymnasium 4",
    "sg:city":"Neuruppin",
    "sg:phone":"+49 3391/3200",
    "sg:postcode":"16816",
    "sg:province":"Brandenburg",
    "wof:name":"Peter Harzdorf Bestattungshaus",
    "wof:placetype":"venue"
},
  "geometry": {"coordinates":[12.806362,52.924606],"type":"Point"}
}