{
  "type": "Feature",
  "properties": {
    "iso:country":"DE",
    "sg:address":"Moritztal 10",
    "sg:city":"Hirschfeld",
    "sg:phone":"+49 35242/68963",
    "sg:postcode":"09634",
    "sg:province":"Sachsen",
    "wof:name":"Astrid Kupferschmied",
    "wof:placetype":"venue"
},
  "geometry": {"coordinates":[13.3631410599,51.0419311523],"type":"Point"}
}