{
  "type": "Feature",
  "properties": {
    "iso:country":"DE",
    "sg:address":"Friesenberg 1",
    "sg:city":"Heidelberg",
    "sg:phone":"+49 6221/27764",
    "sg:postcode":"69117",
    "sg:province":"Baden-W\u00fcrttemberg",
    "wof:name":"Evm Gmbh",
    "wof:placetype":"venue"
},
  "geometry": {"coordinates":[8.7162151337,49.4123954773],"type":"Point"}
}