{
  "type": "Feature",
  "properties": {
    "iso:country":"DE",
    "sg:address":"Im Kleinen Maser 3",
    "sg:city":"Lamspringe",
    "sg:postcode":"31195",
    "sg:province":"Niedersachsen",
    "wof:name":"Aldi Gmbh & Co. Kg",
    "wof:placetype":"venue"
},
  "geometry": {"coordinates":[10.002081871,51.9562492371],"type":"Point"}
}