{
  "type": "Feature",
  "properties": {
    "iso:country":"DE",
    "sg:address":"Kreuzstr. 40",
    "sg:city":"Willich",
    "sg:phone":"+49 2154/40442",
    "sg:postcode":"47877",
    "sg:province":"Nordrhein-Westfalen",
    "wof:name":"Hans R\u00fcttgens",
    "wof:placetype":"venue"
},
  "geometry": {"coordinates":[6.550682,51.261375],"type":"Point"}
}