{
  "type": "Feature",
  "properties": {
    "iso:country":"DE",
    "sg:address":"Schmiedestra\u00dfe 18",
    "sg:city":"Ilsenburg",
    "sg:phone":"+49 39452/2494",
    "sg:postcode":"38871",
    "sg:province":"Sachsen-Anhalt",
    "wof:name":"F\u00fcrst Stolberg H\u00fctte Ilsenburg Gmbh",
    "wof:placetype":"venue"
},
  "geometry": {"coordinates":[10.684173584,51.8684082031],"type":"Point"}
}