{
  "type": "Feature",
  "properties": {
    "iso:country":"DE",
    "sg:address":"Leverkusener Str. 17",
    "sg:city":"Bergisch Gladbach",
    "sg:phone":"+49 2202/83506",
    "sg:postcode":"51467",
    "sg:province":"Nordrhein-Westfalen",
    "wof:name":"Wilhelm Wittkamp",
    "wof:placetype":"venue"
},
  "geometry": {"coordinates":[7.077959,51.017456],"type":"Point"}
}