{
  "type": "Feature",
  "properties": {
    "iso:country":"DE",
    "sg:address":"Hindenburgstr. 47",
    "sg:city":"Gronau",
    "sg:phone":"+49 2562/96797",
    "sg:postcode":"48599",
    "sg:province":"Nordrhein-Westfalen",
    "wof:name":"Heiner Pasch E-msr Planungen Gmbh",
    "wof:placetype":"venue"
},
  "geometry": {"coordinates":[7.0453281403,52.2190933228],"type":"Point"}
}