{
  "type": "Feature",
  "properties": {
    "iso:country":"DE",
    "sg:address":"Nu\u00dfbaumallee 15",
    "sg:city":"Leipzig",
    "sg:phone":"+49 34297/43331",
    "sg:postcode":"04288",
    "sg:province":"Sachsen",
    "wof:name":"Efm Finanzdienstleistungen Gmbh",
    "wof:placetype":"venue"
},
  "geometry": {"coordinates":[12.4500646591,51.3136901855],"type":"Point"}
}