{
  "type": "Feature",
  "properties": {
    "iso:country":"DE",
    "sg:address":"G\u00f6schwitzer Str. 25",
    "sg:city":"Jena",
    "sg:postcode":"07745",
    "sg:province":"Th\u00fcringen",
    "wof:name":"Brooks Automation Holding Gmbh",
    "wof:placetype":"venue"
},
  "geometry": {"coordinates":[11.597674,50.886456],"type":"Point"}
}