{
  "type": "Feature",
  "properties": {
    "iso:country":"DE",
    "sg:address":"Kirchstr. 12",
    "sg:city":"Staufen",
    "sg:postcode":"79219",
    "sg:province":"Baden-W\u00fcrttemberg",
    "wof:name":"It Novation Gmbh",
    "wof:placetype":"venue"
},
  "geometry": {"coordinates":[9.6165943146,51.3717765808],"type":"Point"}
}