{
  "type": "Feature",
  "properties": {
    "iso:country":"DE",
    "sg:address":"Bahnhofstr. 7",
    "sg:city":"L\u00fcdinghausen",
    "sg:phone":"+49 2591/1659",
    "sg:postcode":"59348",
    "sg:province":"Nordrhein-Westfalen",
    "wof:name":"Hansa-stube",
    "wof:placetype":"venue"
},
  "geometry": {"coordinates":[7.4361481667,51.7628898621],"type":"Point"}
}