{
  "type": "Feature",
  "properties": {
    "iso:country":"DE",
    "sg:address":"Haarhofstr. 65",
    "sg:city":"Aachen",
    "sg:phone":"+49 241/550350",
    "sg:postcode":"52078",
    "sg:province":"Nordrhein-Westfalen",
    "wof:name":"Josef Krings",
    "wof:placetype":"venue"
},
  "geometry": {"coordinates":[6.154858,50.773682],"type":"Point"}
}