{
  "type": "Feature",
  "properties": {
    "iso:country":"DE",
    "sg:address":"Westendstr. 13",
    "sg:city":"Wiesbaden",
    "sg:postcode":"65195",
    "sg:province":"Hessen",
    "wof:name":"Hans J\u00fcrgen Garnier",
    "wof:placetype":"venue"
},
  "geometry": {"coordinates":[8.227013588,50.082660675],"type":"Point"}
}