{
  "type": "Feature",
  "properties": {
    "iso:country":"DE",
    "sg:address":"Mindener Str. 104",
    "sg:city":"H\u00fcllhorst",
    "sg:phone":"+49 5744/1336",
    "sg:postcode":"32609",
    "sg:province":"Nordrhein-Westfalen",
    "wof:name":"Holdack-haus-bau- Verwaltungs Gmbh",
    "wof:placetype":"venue"
},
  "geometry": {"coordinates":[8.733234,52.273952],"type":"Point"}
}