{
  "type": "Feature",
  "properties": {
    "iso:country":"DE",
    "sg:address":"Zaitzkofen 3",
    "sg:city":"Adlkofen",
    "sg:phone":"+49 8707/8199",
    "sg:postcode":"84166",
    "sg:province":"Bayern",
    "wof:name":"Georg Stemberger",
    "wof:placetype":"venue"
},
  "geometry": {"coordinates":[12.262403,48.573257],"type":"Point"}
}