{
  "type": "Feature",
  "properties": {
    "iso:country":"DE",
    "sg:address":"Gottlob-Molt-Str. 8",
    "sg:city":"Ludwigsburg",
    "sg:phone":"+49 7141/926141",
    "sg:postcode":"71636",
    "sg:province":"Baden-W\u00fcrttemberg",
    "wof:name":"Herta Aurenz Masseurin",
    "wof:placetype":"venue"
},
  "geometry": {"coordinates":[9.180856,48.894848],"type":"Point"}
}