{
  "type": "Feature",
  "properties": {
    "iso:country":"DE",
    "sg:address":"R\u00f6merstr. 98",
    "sg:city":"Neumagen-Dhron",
    "sg:phone":"+49 6507/5366",
    "sg:postcode":"54347",
    "sg:province":"Rheinland-Pfalz",
    "wof:name":"Erwin Krebs",
    "wof:placetype":"venue"
},
  "geometry": {"coordinates":[6.894199,49.851788],"type":"Point"}
}