{
  "type": "Feature",
  "properties": {
    "iso:country":"DE",
    "sg:address":"Weilerswister Str. 28",
    "sg:city":"Erftstadt",
    "sg:phone":"+49 2235/690174",
    "sg:postcode":"50374",
    "sg:province":"Nordrhein-Westfalen",
    "wof:name":"K\u00e4the Berf Haus- Und K\u00fcchenger\u00e4te",
    "wof:placetype":"venue"
},
  "geometry": {"coordinates":[6.7698249817,50.7553710938],"type":"Point"}
}