{
  "type": "Feature",
  "properties": {
    "iso:country":"DE",
    "sg:address":"Wiesenstr. 12",
    "sg:city":"Bensheim",
    "sg:phone":"+49 6251/4356",
    "sg:postcode":"64625",
    "sg:province":"Hessen",
    "wof:name":"Horst Prossl Gmbh",
    "wof:placetype":"venue"
},
  "geometry": {"coordinates":[8.590082,49.68288],"type":"Point"}
}