{
  "type": "Feature",
  "properties": {
    "iso:country":"DE",
    "sg:address":"H\u00f6chst\u00e4dtstr. 6",
    "sg:city":"Neuburg",
    "sg:phone":"+49 8431/8232",
    "sg:postcode":"86633",
    "sg:province":"Bayern",
    "wof:name":"Rolf Klement Ingenieur",
    "wof:placetype":"venue"
},
  "geometry": {"coordinates":[11.1887311935,48.7248344421],"type":"Point"}
}