{
  "type": "Feature",
  "properties": {
    "iso:country":"DE",
    "sg:address":"Hindenburgstr. 160",
    "sg:city":"Hamburg",
    "sg:phone":"+49 40/5005660",
    "sg:postcode":"22297",
    "sg:province":"Hamburg",
    "wof:name":"Hansa Grafia Grafische Systeme Gmbh",
    "wof:placetype":"venue"
},
  "geometry": {"coordinates":[10.004771,53.618359],"type":"Point"}
}