{
  "type": "Feature",
  "properties": {
    "iso:country":"DE",
    "sg:address":"Am Holze 8",
    "sg:city":"Hemsloh",
    "sg:phone":"+49 5446/684",
    "sg:postcode":"49453",
    "sg:province":"Niedersachsen",
    "wof:name":"Helmut Imsande",
    "wof:placetype":"venue"
},
  "geometry": {"coordinates":[8.508461,52.603508],"type":"Point"}
}