{
  "type": "Feature",
  "properties": {
    "iso:country":"DE",
    "sg:address":"Daimlerstr. 25",
    "sg:city":"Himmelstadt",
    "sg:phone":"+49 9364/4425",
    "sg:postcode":"97267",
    "sg:province":"Bayern",
    "wof:name":"Thomas Staab Architekt",
    "wof:placetype":"venue"
},
  "geometry": {"coordinates":[9.810177,49.920895],"type":"Point"}
}