{
  "type": "Feature",
  "properties": {
    "iso:country":"DE",
    "sg:address":"Herzog-Wilhelm-Str.",
    "sg:city":"Mering",
    "sg:phone":"+49 8233/4899",
    "sg:postcode":"86415",
    "sg:province":"Bayern",
    "wof:name":"Dr. Wilfried M\u00fcller Tierarzt",
    "wof:placetype":"venue"
},
  "geometry": {"coordinates":[10.9883308411,48.2680625916],"type":"Point"}
}