{
  "type": "Feature",
  "properties": {
    "iso:country":"DE",
    "sg:address":"Kulmer Str. 54",
    "sg:city":"Mannheim",
    "sg:phone":"+49 621/772663",
    "sg:postcode":"68307",
    "sg:province":"Baden-W\u00fcrttemberg",
    "wof:name":"R. Wegner",
    "wof:placetype":"venue"
},
  "geometry": {"coordinates":[8.4478988647,49.5433044434],"type":"Point"}
}