{
  "type": "Feature",
  "properties": {
    "iso:country":"DE",
    "sg:address":"Jadestr. 8",
    "sg:city":"Schortens",
    "sg:phone":"+49 4461/83352",
    "sg:postcode":"26419",
    "sg:province":"Niedersachsen",
    "wof:name":"Arne Arlinghaus",
    "wof:placetype":"venue"
},
  "geometry": {"coordinates":[7.9489169121,53.5400543213],"type":"Point"}
}