{
  "type": "Feature",
  "properties": {
    "iso:country":"DE",
    "sg:address":"Bornh\u00f6vedstr. 43",
    "sg:city":"Schwerin",
    "sg:postcode":"19055",
    "sg:province":"Mecklenburg-Vorpommern",
    "wof:name":"Haase-schmidt Steuer- Beratungsgesellschaft Mbh",
    "wof:placetype":"venue"
},
  "geometry": {"coordinates":[11.4286546707,53.63463974],"type":"Point"}
}