{
  "type": "Feature",
  "properties": {
    "iso:country":"DE",
    "sg:address":"Guxhagener Str. 20",
    "sg:city":"Ederm\u00fcnde",
    "sg:phone":"+49 5665/7672",
    "sg:postcode":"34295",
    "sg:province":"Hessen",
    "wof:name":"Eder-apotheke",
    "wof:placetype":"venue"
},
  "geometry": {"coordinates":[9.44552,51.211723],"type":"Point"}
}