{
  "type": "Feature",
  "properties": {
    "iso:country":"DE",
    "sg:address":"Darmst\u00e4dter Landstr. 93",
    "sg:city":"Frankfurt",
    "sg:phone":"+49 69/615593",
    "sg:postcode":"60598",
    "sg:province":"Hessen",
    "wof:name":"Wolfgang Thiele Immobilienmakler Rdm",
    "wof:placetype":"venue"
},
  "geometry": {"coordinates":[8.6914281845,50.0989875793],"type":"Point"}
}