{
  "type": "Feature",
  "properties": {
    "iso:country":"DE",
    "sg:address":"Wolfsittard 51",
    "sg:city":"M\u00f6nchengladbach",
    "sg:postcode":"41179",
    "sg:province":"Nordrhein-Westfalen",
    "wof:name":"Visicom E. K.",
    "wof:placetype":"venue"
},
  "geometry": {"coordinates":[6.372462,51.174694],"type":"Point"}
}