{
  "type": "Feature",
  "properties": {
    "iso:country":"DE",
    "sg:address":"Im Rohmen 34",
    "sg:city":"M\u00fchlhausen-Ehingen",
    "sg:phone":"+49 7733/1859",
    "sg:postcode":"78259",
    "sg:province":"Baden-W\u00fcrttemberg",
    "wof:name":"Dr. J. Pecht",
    "wof:placetype":"venue"
},
  "geometry": {"coordinates":[8.820605278,47.8074951172],"type":"Point"}
}