{
  "type": "Feature",
  "properties": {
    "iso:country":"DE",
    "sg:address":"Fabrikstr. 17",
    "sg:city":"S\u00fcnching",
    "sg:phone":"+49 9480/180",
    "sg:postcode":"93104",
    "sg:province":"Bayern",
    "wof:name":"S\u00fcdst\u00e4rke Gmbh",
    "wof:placetype":"venue"
},
  "geometry": {"coordinates":[12.3548803329,48.886138916],"type":"Point"}
}