{
  "type": "Feature",
  "properties": {
    "iso:country":"DE",
    "sg:address":"Friedrich-Ebert-Str. 35",
    "sg:city":"Cottbus",
    "sg:postcode":"03044",
    "sg:province":"Brandenburg",
    "wof:name":"Platinum Automatenbetrieb Gmbh",
    "wof:placetype":"venue"
},
  "geometry": {"coordinates":[14.3324184418,51.7641944885],"type":"Point"}
}