{
  "type": "Feature",
  "properties": {
    "iso:country":"DE",
    "sg:address":"Am Eichgraben 2",
    "sg:city":"Eisfeld",
    "sg:phone":"+49 3686/39200",
    "sg:postcode":"98673",
    "sg:province":"Th\u00fcringen",
    "wof:name":"Tbg Transportbeton Werra Gmbh & Co. Kg",
    "wof:placetype":"venue"
},
  "geometry": {"coordinates":[10.9048156738,50.4155044556],"type":"Point"}
}