{
  "type": "Feature",
  "properties": {
    "iso:country":"DE",
    "sg:address":"Alte Str. 40",
    "sg:city":"Remagen",
    "sg:phone":"+49 2642/21347",
    "sg:postcode":"53424",
    "sg:province":"Rheinland-Pfalz",
    "wof:name":"Kurt Und Heinz Schild",
    "wof:placetype":"venue"
},
  "geometry": {"coordinates":[7.2396011353,50.5767860413],"type":"Point"}
}