{
  "type": "Feature",
  "properties": {
    "iso:country":"DE",
    "sg:address":"D\u00fcsseldorfer Str. 56",
    "sg:city":"Leverkusen",
    "sg:phone":"+49 2171/1285",
    "sg:postcode":"51379",
    "sg:province":"Nordrhein-Westfalen",
    "wof:name":"Theo Bruere Inh. Markus Odendahl E. K.",
    "wof:placetype":"venue"
},
  "geometry": {"coordinates":[6.9990730286,51.0711517334],"type":"Point"}
}