{
  "type": "Feature",
  "properties": {
    "iso:country":"DE",
    "sg:address":"Diesel Str. 8",
    "sg:city":"Rheda-Wiedenbr\u00fcck",
    "sg:phone":"+49 4922/533130",
    "sg:postcode":"33378",
    "sg:province":"Nordrhein-Westfalen",
    "wof:name":"Peter Greven Fettchemie Gmbh & Co Kg",
    "wof:placetype":"venue"
},
  "geometry": {"coordinates":[6.767229,50.576305],"type":"Point"}
}