{
  "type": "Feature",
  "properties": {
    "iso:country":"DE",
    "sg:address":"Karl-Heine-Str. 27",
    "sg:city":"Leipzig",
    "sg:phone":"+49 341/4804141",
    "sg:postcode":"04229",
    "sg:province":"Sachsen",
    "wof:name":"B\u00f6hme Gmbh Wirtschafts.u.personalberatung",
    "wof:placetype":"venue"
},
  "geometry": {"coordinates":[12.3429527283,51.3321418762],"type":"Point"}
}