{
  "type": "Feature",
  "properties": {
    "iso:country":"DE",
    "sg:address":"Altwiesenstr. 9",
    "sg:city":"Bad Wildbad",
    "sg:phone":"+49 7081/6683",
    "sg:postcode":"75323",
    "sg:province":"Baden-W\u00fcrttemberg",
    "wof:name":"Anneliese Kiefer",
    "wof:placetype":"venue"
},
  "geometry": {"coordinates":[8.5782365799,48.7754325867],"type":"Point"}
}