{
  "type": "Feature",
  "properties": {
    "iso:country":"DE",
    "sg:address":"Insterburger Str. 7",
    "sg:city":"Frankfurt",
    "sg:phone":"+49 69/59796410",
    "sg:postcode":"60487",
    "sg:province":"Hessen",
    "wof:name":"Hortus Immobilien Managementgesellschaft",
    "wof:placetype":"venue"
},
  "geometry": {"coordinates":[8.6287078857,50.1275215149],"type":"Point"}
}