{
  "type": "Feature",
  "properties": {
    "iso:country":"DE",
    "sg:address":"Brunnenstr. 13a",
    "sg:city":"Lohfelden",
    "sg:phone":"+49 5608/2172",
    "sg:postcode":"34253",
    "sg:province":"Hessen",
    "wof:name":"Heide Tatzel Massagepraxis",
    "wof:placetype":"venue"
},
  "geometry": {"coordinates":[9.563914,51.262722],"type":"Point"}
}