{
  "type": "Feature",
  "properties": {
    "iso:country":"DE",
    "sg:address":"Hogenkamp 71",
    "sg:city":"Pinneberg",
    "sg:phone":"+49 4101/61490",
    "sg:postcode":"25421",
    "sg:province":"Schleswig-Holstein",
    "wof:name":"Thomas Janson",
    "wof:placetype":"venue"
},
  "geometry": {"coordinates":[9.793753,53.641575],"type":"Point"}
}