{
  "type": "Feature",
  "properties": {
    "iso:country":"DE",
    "sg:address":"Untere Ziel 1",
    "sg:city":"Sexau",
    "sg:phone":"+49 7641/91140",
    "sg:postcode":"79350",
    "sg:province":"Baden-W\u00fcrttemberg",
    "wof:name":"Maxon Motor Gmbh",
    "wof:placetype":"venue"
},
  "geometry": {"coordinates":[7.8953838348,48.0908851624],"type":"Point"}
}