{
  "type": "Feature",
  "properties": {
    "iso:country":"DE",
    "sg:address":"Betriebsstr. 1",
    "sg:city":"L\u00f6hne",
    "sg:phone":"+49 5731/8430",
    "sg:postcode":"32584",
    "sg:province":"Nordrhein-Westfalen",
    "wof:name":"Yamaha Motor Deutschland Gmbh",
    "wof:placetype":"venue"
},
  "geometry": {"coordinates":[8.724181,52.199097],"type":"Point"}
}