{
  "type": "Feature",
  "properties": {
    "iso:country":"DE",
    "sg:address":"Pfaffenbergergasse 6",
    "sg:city":"Gundelfingen",
    "sg:phone":"+49 9073/638",
    "sg:postcode":"89423",
    "sg:province":"Bayern",
    "wof:name":"Josef Und Michael Althammer",
    "wof:placetype":"venue"
},
  "geometry": {"coordinates":[10.371171,48.551907],"type":"Point"}
}