{
  "type": "Feature",
  "properties": {
    "iso:country":"DE",
    "sg:address":"Peter-Maier-Str. 16",
    "sg:city":"Donaueschingen",
    "sg:phone":"+49 7705/466",
    "sg:postcode":"78166",
    "sg:province":"Baden-W\u00fcrttemberg",
    "wof:name":"Schwimmbad Hubertushofen",
    "wof:placetype":"venue"
},
  "geometry": {"coordinates":[8.3918676376,47.9576759338],"type":"Point"}
}