{
  "type": "Feature",
  "properties": {
    "iso:country":"DE",
    "sg:address":"Eggeweg 35",
    "sg:city":"Lage",
    "sg:phone":"+49 5232/78766",
    "sg:postcode":"32791",
    "sg:province":"Nordrhein-Westfalen",
    "wof:name":"Bri Unternehmensberatung Gmbh",
    "wof:placetype":"venue"
},
  "geometry": {"coordinates":[8.7685098648,51.9630699158],"type":"Point"}
}