{
  "type": "Feature",
  "properties": {
    "iso:country":"DE",
    "sg:address":"Falkenberger Str. 3",
    "sg:city":"Tirschenreuth",
    "sg:phone":"+49 9631/1340",
    "sg:postcode":"95643",
    "sg:province":"Bayern",
    "wof:name":"Gv Spezialdienst F\u00fcr Gastronomie Und Gro\u00dfk\u00fcchen",
    "wof:placetype":"venue"
},
  "geometry": {"coordinates":[12.3243236542,49.8800468445],"type":"Point"}
}