{
  "type": "Feature",
  "properties": {
    "iso:country":"DE",
    "sg:address":"R\u00f6dingsmarkt 1",
    "sg:city":"Hamburg",
    "sg:phone":"+49 40/365442",
    "sg:postcode":"20459",
    "sg:province":"Hamburg",
    "wof:name":"Harald Stamp Rechtsanwalt",
    "wof:placetype":"venue"
},
  "geometry": {"coordinates":[9.9872303009,53.5484199524],"type":"Point"}
}