{
  "type": "Feature",
  "properties": {
    "iso:country":"DE",
    "sg:address":"Prinzregentenstr. 54",
    "sg:city":"M\u00fcnchen",
    "sg:phone":"+49 89/298160",
    "sg:postcode":"80538",
    "sg:province":"Bayern",
    "wof:name":"Redinomedica Ag",
    "wof:placetype":"venue"
},
  "geometry": {"coordinates":[11.593662262,48.1418838501],"type":"Point"}
}