{
  "type": "Feature",
  "properties": {
    "iso:country":"DE",
    "sg:address":"L\u00e4rchenall. 2",
    "sg:city":"Schwerin",
    "sg:phone":"+49 385/4841006",
    "sg:postcode":"19057",
    "sg:province":"Mecklenburg-Vorpommern",
    "wof:name":"Etecom",
    "wof:placetype":"venue"
},
  "geometry": {"coordinates":[11.3418931961,53.6494255066],"type":"Point"}
}