{
  "type": "Feature",
  "properties": {
    "iso:country":"DE",
    "sg:address":"Haidlinsgasse 14",
    "sg:city":"Walddorfh\u00e4slach",
    "sg:phone":"+49 7127/32522",
    "sg:postcode":"72141",
    "sg:province":"Baden-W\u00fcrttemberg",
    "wof:name":"Sch\u00f6nbuch-apotheke",
    "wof:placetype":"venue"
},
  "geometry": {"coordinates":[9.182036,48.58604],"type":"Point"}
}