{
  "type": "Feature",
  "properties": {
    "iso:country":"DE",
    "sg:address":"Konrad-K\u00fcmmel-Weg 2",
    "sg:city":"Friedrichshafen",
    "sg:phone":"+49 7541/52030",
    "sg:postcode":"88045",
    "sg:province":"Baden-W\u00fcrttemberg",
    "wof:name":"Hans Augustin Dipl.-ing.",
    "wof:placetype":"venue"
},
  "geometry": {"coordinates":[9.4699306488,47.6689605713],"type":"Point"}
}