{
  "type": "Feature",
  "properties": {
    "iso:country":"DE",
    "sg:address":"Storkower Str. 139b",
    "sg:city":"Berlin",
    "sg:phone":"+49 30/4286025",
    "sg:postcode":"10407",
    "sg:province":"Berlin",
    "wof:name":"Interquest Handels- Und Speditionsgesellschaft Mbh",
    "wof:placetype":"venue"
},
  "geometry": {"coordinates":[13.4547557831,52.533290863],"type":"Point"}
}