{
  "type": "Feature",
  "properties": {
    "iso:country":"DE",
    "sg:address":"Waldstr. 5a",
    "sg:city":"Heide",
    "sg:phone":"+49 481/786920",
    "sg:postcode":"25746",
    "sg:province":"Schleswig-Holstein",
    "wof:name":"Hagebaumarkt Heide Gmbh & Co. Kg",
    "wof:placetype":"venue"
},
  "geometry": {"coordinates":[9.1600580215,54.2000961304],"type":"Point"}
}