{
  "type": "Feature",
  "properties": {
    "iso:country":"DE",
    "sg:address":"Brachter Str. 62",
    "sg:city":"Br\u00fcggen",
    "sg:phone":"+49 2163/5476",
    "sg:postcode":"41379",
    "sg:province":"Nordrhein-Westfalen",
    "wof:name":"A. Dammer",
    "wof:placetype":"venue"
},
  "geometry": {"coordinates":[6.18398,51.256813],"type":"Point"}
}