{
  "type": "Feature",
  "properties": {
    "iso:country":"DE",
    "sg:address":"Hammersteig 1",
    "sg:city":"Kronach",
    "sg:phone":"+49 9261/93175",
    "sg:postcode":"96317",
    "sg:province":"Bayern",
    "wof:name":"Anneliese Na\u00df",
    "wof:placetype":"venue"
},
  "geometry": {"coordinates":[11.3268280029,50.2334251404],"type":"Point"}
}