{
  "type": "Feature",
  "properties": {
    "iso:country":"DE",
    "sg:address":"Friedrich-Kaiser-Str. 21",
    "sg:city":"Iserlohn",
    "sg:postcode":"58638",
    "sg:province":"Nordrhein-Westfalen",
    "wof:name":"New Media Agency Gmbh",
    "wof:placetype":"venue"
},
  "geometry": {"coordinates":[7.6836681366,51.3947525024],"type":"Point"}
}