{
  "type": "Feature",
  "properties": {
    "iso:country":"DE",
    "sg:address":"Br\u00fcckkanalstr. 3",
    "sg:city":"Feucht",
    "sg:postcode":"90537",
    "sg:province":"Bayern",
    "wof:name":"Alsys Bildverarbeitungssysteme Gmbh",
    "wof:placetype":"venue"
},
  "geometry": {"coordinates":[11.2113075256,49.3705711365],"type":"Point"}
}