{
  "type": "Feature",
  "properties": {
    "iso:country":"DE",
    "sg:address":"Potsdamer Str. 53",
    "sg:city":"Teltow",
    "sg:phone":"+49 3328/40100",
    "sg:postcode":"14513",
    "sg:province":"Brandenburg",
    "wof:name":"Brotbr\u00e4uhaus",
    "wof:placetype":"venue"
},
  "geometry": {"coordinates":[13.2590017319,52.4018554688],"type":"Point"}
}