{
  "type": "Feature",
  "properties": {
    "iso:country":"DE",
    "sg:address":"In de Berken 50",
    "sg:city":"Kevelaer",
    "sg:postcode":"47626",
    "sg:province":"Nordrhein-Westfalen",
    "wof:name":"Garasali Verm\u00f6gensverw. Gmbh",
    "wof:placetype":"venue"
},
  "geometry": {"coordinates":[6.2862000465,51.6006469727],"type":"Point"}
}