{
  "type": "Feature",
  "properties": {
    "iso:country":"DE",
    "sg:address":"Am Urnenfeld 16",
    "sg:city":"Bergisch Gladbach",
    "sg:phone":"+49 2202/78628",
    "sg:postcode":"51467",
    "sg:province":"Nordrhein-Westfalen",
    "wof:name":"Dr. Klaus Katz",
    "wof:placetype":"venue"
},
  "geometry": {"coordinates":[7.1215538979,51.0091667175],"type":"Point"}
}