{
  "type": "Feature",
  "properties": {
    "iso:country":"DE",
    "sg:address":"M\u00f6gglinger Str. 54",
    "sg:city":"Heubach",
    "sg:phone":"+49 7173/8842",
    "sg:postcode":"73540",
    "sg:province":"Baden-W\u00fcrttemberg",
    "wof:name":"Pension Eugen Kiemele",
    "wof:placetype":"venue"
},
  "geometry": {"coordinates":[9.937713623,48.7968063354],"type":"Point"}
}