{
  "type": "Feature",
  "properties": {
    "iso:country":"DE",
    "sg:address":"Hillegosser Str. 92",
    "sg:city":"Bielefeld",
    "sg:phone":"+49 521/296911",
    "sg:postcode":"33719",
    "sg:province":"Nordrhein-Westfalen",
    "wof:name":"Levenhagen Gmbh",
    "wof:placetype":"venue"
},
  "geometry": {"coordinates":[8.609649,52.024921],"type":"Point"}
}