{
  "type": "Feature",
  "properties": {
    "iso:country":"DE",
    "sg:address":"Rommelsrieder Str. 16",
    "sg:city":"Diedorf",
    "sg:phone":"+49 821/488524",
    "sg:postcode":"86420",
    "sg:province":"Bayern",
    "wof:name":"Werner Kemter",
    "wof:placetype":"venue"
},
  "geometry": {"coordinates":[10.760125,48.375629],"type":"Point"}
}