{
  "type": "Feature",
  "properties": {
    "iso:country":"DE",
    "sg:address":"Weiherstr. 6",
    "sg:city":"Windhagen",
    "sg:phone":"+49 2683/43938",
    "sg:postcode":"53578",
    "sg:province":"Rheinland-Pfalz",
    "wof:name":"Rainer G\u00f6tze",
    "wof:placetype":"venue"
},
  "geometry": {"coordinates":[7.3656358719,50.6569290161],"type":"Point"}
}