{
  "type": "Feature",
  "properties": {
    "iso:country":"DE",
    "sg:address":"Pfarrstr. 2",
    "sg:city":"K\u00fchbach",
    "sg:phone":"+49 8251/3467",
    "sg:postcode":"86556",
    "sg:province":"Bayern",
    "wof:name":"Kath. Pfarramt",
    "wof:placetype":"venue"
},
  "geometry": {"coordinates":[11.1847000122,48.4910697937],"type":"Point"}
}