{
  "type": "Feature",
  "properties": {
    "iso:country":"DE",
    "sg:address":"Habsburgerstr. 4",
    "sg:city":"Berlin",
    "sg:phone":"+49 30/21756779",
    "sg:postcode":"10781",
    "sg:province":"Berlin",
    "wof:name":"Amh Treuhand Gmbh",
    "wof:placetype":"venue"
},
  "geometry": {"coordinates":[13.3520431519,52.4956588745],"type":"Point"}
}