{
  "type": "Feature",
  "properties": {
    "iso:country":"DE",
    "sg:address":"Lange Geismarstr. 32",
    "sg:city":"G\u00f6ttingen",
    "sg:phone":"+49 551/58801",
    "sg:postcode":"37073",
    "sg:province":"Niedersachsen",
    "wof:name":"Ingrid Hausen Krankengymnastin",
    "wof:placetype":"venue"
},
  "geometry": {"coordinates":[9.937877,51.531796],"type":"Point"}
}