{
  "type": "Feature",
  "properties": {
    "iso:country":"DE",
    "sg:address":"Im Gewerbegebiet",
    "sg:city":"Friedewald",
    "sg:phone":"+49 6674/8058",
    "sg:postcode":"36289",
    "sg:province":"Hessen",
    "wof:name":"Brandau Gelenkketten Gmbh + Co Kg",
    "wof:placetype":"venue"
},
  "geometry": {"coordinates":[9.868035,50.889904],"type":"Point"}
}