{
  "type": "Feature",
  "properties": {
    "iso:country":"DE",
    "sg:address":"Mittlerer Herrenberg 9",
    "sg:city":"Eisenbach",
    "sg:phone":"+49 7657/1679",
    "sg:postcode":"79871",
    "sg:province":"Baden-W\u00fcrttemberg",
    "wof:name":"Wolfgang Krause",
    "wof:placetype":"venue"
},
  "geometry": {"coordinates":[8.268266,47.962696],"type":"Point"}
}