{
  "type": "Feature",
  "properties": {
    "iso:country":"DE",
    "sg:address":"Kirchplatz 13",
    "sg:city":"Laaber",
    "sg:phone":"+49 9498/1500",
    "sg:postcode":"93164",
    "sg:province":"Bayern",
    "wof:name":"P. Fritsch",
    "wof:placetype":"venue"
},
  "geometry": {"coordinates":[11.8842000961,49.0650787354],"type":"Point"}
}