{
  "type": "Feature",
  "properties": {
    "iso:country":"DE",
    "sg:address":"Ostendstr. 124",
    "sg:city":"N\u00fcrnberg",
    "sg:phone":"+49 911/54820",
    "sg:postcode":"90482",
    "sg:province":"Bayern",
    "wof:name":"Staub & Co.",
    "wof:placetype":"venue"
},
  "geometry": {"coordinates":[11.1189279556,49.4556694031],"type":"Point"}
}