{
  "type": "Feature",
  "properties": {
    "iso:country":"DE",
    "sg:address":"Reinefarthstr. 81-83",
    "sg:city":"Merseburg",
    "sg:phone":"+49 3461/204614",
    "sg:postcode":"06217",
    "sg:province":"Sachsen-Anhalt",
    "wof:name":"Plato & Co. Gmbh",
    "wof:placetype":"venue"
},
  "geometry": {"coordinates":[11.984205,51.363091],"type":"Point"}
}