{
  "type": "Feature",
  "properties": {
    "iso:country":"DE",
    "sg:address":"Richard-Wagner-Str. 21",
    "sg:city":"Bayreuth",
    "sg:phone":"+49 921/759400",
    "sg:postcode":"95444",
    "sg:province":"Bayern",
    "wof:name":"J. N. Oberpaur Gmbh & Co. Kg",
    "wof:placetype":"venue"
},
  "geometry": {"coordinates":[11.580587,49.942684],"type":"Point"}
}