{
  "type": "Feature",
  "properties": {
    "iso:country":"DE",
    "sg:address":"Cohnenhofstr. 49 a",
    "sg:city":"K\u00f6ln",
    "sg:phone":"+49 221/7088098",
    "sg:postcode":"50769",
    "sg:province":"Nordrhein-Westfalen",
    "wof:name":"Willi Otto",
    "wof:placetype":"venue"
},
  "geometry": {"coordinates":[6.9203147888,51.0483551025],"type":"Point"}
}