{
  "type": "Feature",
  "properties": {
    "iso:country":"DE",
    "sg:address":"Berliner Weg 3",
    "sg:city":"Extertal",
    "sg:phone":"+49 5262/4662",
    "sg:postcode":"32699",
    "sg:province":"Nordrhein-Westfalen",
    "wof:name":"Andreas Brand",
    "wof:placetype":"venue"
},
  "geometry": {"coordinates":[9.119179,52.07016],"type":"Point"}
}