{
  "type": "Feature",
  "properties": {
    "iso:country":"DE",
    "sg:address":"Bergweg 5",
    "sg:city":"Pyrbaum",
    "sg:phone":"+49 9180/417",
    "sg:postcode":"90602",
    "sg:province":"Bayern",
    "wof:name":"W. Dittrich",
    "wof:placetype":"venue"
},
  "geometry": {"coordinates":[11.236793,49.280987],"type":"Point"}
}