{
  "type": "Feature",
  "properties": {
    "iso:country":"DE",
    "sg:address":"Klarenthaler Str. 10",
    "sg:city":"Wiesbaden",
    "sg:phone":"+49 611/47265",
    "sg:postcode":"65197",
    "sg:province":"Hessen",
    "wof:name":"B\u00e4ckerei Klein Gmbh & Co. Kg",
    "wof:placetype":"venue"
},
  "geometry": {"coordinates":[8.226927,50.077618],"type":"Point"}
}