{
  "type": "Feature",
  "properties": {
    "iso:country":"DE",
    "sg:address":"Eickeler Markt 3 a",
    "sg:city":"Herne",
    "sg:phone":"+49 2325/33011",
    "sg:postcode":"44651",
    "sg:province":"Nordrhein-Westfalen",
    "wof:name":"Peter Und Mahlberg Rechtsanw\u00e4lte",
    "wof:placetype":"venue"
},
  "geometry": {"coordinates":[7.1795678139,51.5150222778],"type":"Point"}
}