{
  "type": "Feature",
  "properties": {
    "iso:country":"DE",
    "sg:address":"Rotenberger Str. 24",
    "sg:city":"Malsch",
    "sg:phone":"+49 7253/23659",
    "sg:postcode":"69254",
    "sg:province":"Baden-W\u00fcrttemberg",
    "wof:name":"Gertrud Rittel",
    "wof:placetype":"venue"
},
  "geometry": {"coordinates":[8.6866340637,49.246219635],"type":"Point"}
}