{
  "type": "Feature",
  "properties": {
    "iso:country":"DE",
    "sg:address":"Backhausgasse 3",
    "sg:city":"Siefersheim",
    "sg:phone":"+49 6703/960320",
    "sg:postcode":"55599",
    "sg:province":"Rheinland-Pfalz",
    "wof:name":"J\u00f6rg Und Arthur Zimmermann",
    "wof:placetype":"venue"
},
  "geometry": {"coordinates":[7.958427906,49.7973442078],"type":"Point"}
}