{
  "type": "Feature",
  "properties": {
    "iso:country":"DE",
    "sg:address":"Waldstr. 17",
    "sg:city":"Kruft",
    "sg:phone":"+49 2652/8080",
    "sg:postcode":"56642",
    "sg:province":"Rheinland-Pfalz",
    "wof:name":"Gebr. Zieglowski Beteiligungsgesellschaft Mbh",
    "wof:placetype":"venue"
},
  "geometry": {"coordinates":[7.3306860924,50.3854446411],"type":"Point"}
}