{
  "type": "Feature",
  "properties": {
    "iso:country":"DE",
    "sg:address":"Ilzhamer Str. 2",
    "sg:city":"Obing",
    "sg:phone":"+49 8624/2398",
    "sg:postcode":"83119",
    "sg:province":"Bayern",
    "wof:name":"Ao Consulting Gmbh",
    "wof:placetype":"venue"
},
  "geometry": {"coordinates":[12.400348,48.001774],"type":"Point"}
}