{
  "type": "Feature",
  "properties": {
    "iso:country":"DE",
    "sg:address":"Kirchstr. 13",
    "sg:city":"Langenbach",
    "sg:phone":"+49 8761/70414",
    "sg:postcode":"85416",
    "sg:province":"Bayern",
    "wof:name":"Messkom Vertriebs-gmbh",
    "wof:placetype":"venue"
},
  "geometry": {"coordinates":[11.875925,48.427887],"type":"Point"}
}