{
  "type": "Feature",
  "properties": {
    "iso:country":"DE",
    "sg:address":"Fachenfelder Weg 138",
    "sg:city":"Seevetal",
    "sg:phone":"+49 4105/82369",
    "sg:postcode":"21220",
    "sg:province":"Niedersachsen",
    "wof:name":"Ernst A. Jung Export-import",
    "wof:placetype":"venue"
},
  "geometry": {"coordinates":[10.05932,53.381008],"type":"Point"}
}