{
  "type": "Feature",
  "properties": {
    "iso:country":"DE",
    "sg:address":"Alt Gonzenheim 12",
    "sg:city":"Bad Homburg",
    "sg:phone":"+49 6172/44966",
    "sg:postcode":"61352",
    "sg:province":"Hessen",
    "wof:name":"Wolfgang Kl\u00fch Tennislehrer",
    "wof:placetype":"venue"
},
  "geometry": {"coordinates":[8.6424436569,50.2212982178],"type":"Point"}
}