{
  "type": "Feature",
  "properties": {
    "iso:country":"DE",
    "sg:address":"Waldstr. 8",
    "sg:city":"Eggersdorf",
    "sg:phone":"+49 3341/48430",
    "sg:postcode":"15345",
    "sg:province":"Brandenburg",
    "wof:name":"Werner Schulz Rechtsanwalt",
    "wof:placetype":"venue"
},
  "geometry": {"coordinates":[13.8219690323,52.5347671509],"type":"Point"}
}