{
  "type": "Feature",
  "properties": {
    "iso:country":"DE",
    "sg:address":"Mitternachm\u00fchle 6",
    "sg:city":"Sch\u00f6nberg",
    "sg:phone":"+49 8554/713",
    "sg:postcode":"94513",
    "sg:province":"Bayern",
    "wof:name":"Gastwirtschaft T. Besendorfer",
    "wof:placetype":"venue"
},
  "geometry": {"coordinates":[13.3377962112,48.84034729],"type":"Point"}
}