{
  "type": "Feature",
  "properties": {
    "iso:country":"DE",
    "sg:address":"Frachtstr. 12",
    "sg:city":"J\u00fcbar",
    "sg:phone":"+49 39003/272",
    "sg:postcode":"38489",
    "sg:province":"Sachsen-Anhalt",
    "wof:name":"Behrens Keil & Lorenz Ohg",
    "wof:placetype":"venue"
},
  "geometry": {"coordinates":[10.9118328094,52.6874694824],"type":"Point"}
}