{
  "type": "Feature",
  "properties": {
    "iso:country":"DE",
    "sg:address":"Bismarckstr. 19",
    "sg:city":"\u00d6hringen",
    "sg:phone":"+49 7941/91710",
    "sg:postcode":"74613",
    "sg:province":"Baden-W\u00fcrttemberg",
    "wof:name":"Kern-wohnbau Gmbh",
    "wof:placetype":"venue"
},
  "geometry": {"coordinates":[9.502844,49.20166],"type":"Point"}
}