{
  "type": "Feature",
  "properties": {
    "iso:country":"DE",
    "sg:address":"Ortsstr. 28",
    "sg:city":"Ebermannsdorf",
    "sg:phone":"+49 9438/1688",
    "sg:postcode":"92263",
    "sg:province":"Bayern",
    "wof:name":"Gasthof Goldener Hirsch",
    "wof:placetype":"venue"
},
  "geometry": {"coordinates":[12.0292806625,49.3695106506],"type":"Point"}
}