{
  "type": "Feature",
  "properties": {
    "iso:country":"DE",
    "sg:address":"Bahnhofstr. 2",
    "sg:city":"F\u00fcrstenstein",
    "sg:phone":"+49 8504/8101",
    "sg:postcode":"94538",
    "sg:province":"Bayern",
    "wof:name":"Heidi Gei\u00dfinger",
    "wof:placetype":"venue"
},
  "geometry": {"coordinates":[13.3303413391,48.7163047791],"type":"Point"}
}