{
  "type": "Feature",
  "properties": {
    "iso:country":"DE",
    "sg:address":"Peter-Sander-Str 28",
    "sg:city":"Mainz-Kastel",
    "sg:phone":"+49 6134/26390",
    "sg:postcode":"55252",
    "sg:province":"Hessen",
    "wof:name":"Lasertec Gmbh",
    "wof:placetype":"venue"
},
  "geometry": {"coordinates":[8.274505,50.02935],"type":"Point"}
}