{
  "type": "Feature",
  "properties": {
    "iso:country":"DE",
    "sg:address":"Petersplatz 11",
    "sg:city":"M\u00fcnchen",
    "sg:phone":"+49 89/2603245",
    "sg:postcode":"80331",
    "sg:province":"Bayern",
    "wof:name":"Achim Kr\u00e4mer",
    "wof:placetype":"venue"
},
  "geometry": {"coordinates":[11.575388,48.136311],"type":"Point"}
}