{
  "type": "Feature",
  "properties": {
    "iso:country":"DE",
    "sg:address":"Bahnhofstr. 69::",
    "sg:city":"Wiesbaden",
    "sg:phone":"+49 4961/1178",
    "sg:postcode":"65185",
    "sg:province":"Hessen",
    "wof:name":"Oeffentliche Lebensversicherungsanstalt Hessen-nassau-thueringen",
    "wof:placetype":"venue"
},
  "geometry": {"coordinates":[8.242831,50.072784],"type":"Point"}
}