{
  "type": "Feature",
  "properties": {
    "iso:country":"DE",
    "sg:address":"K\u00f6nigstr. 10",
    "sg:city":"Gronau",
    "sg:phone":"+49 2562/6697",
    "sg:postcode":"48599",
    "sg:province":"Nordrhein-Westfalen",
    "wof:name":"Bernard Beerlage",
    "wof:placetype":"venue"
},
  "geometry": {"coordinates":[7.0072321892,52.2139549255],"type":"Point"}
}