{
  "type": "Feature",
  "properties": {
    "iso:country":"DE",
    "sg:address":"Hauptstr. 19",
    "sg:city":"Bensheim",
    "sg:phone":"+49 6251/66182",
    "sg:postcode":"64625",
    "sg:province":"Hessen",
    "wof:name":"Kochl\u00f6ffel Gmbh & Co. Kg",
    "wof:placetype":"venue"
},
  "geometry": {"coordinates":[8.6221427917,49.6816711426],"type":"Point"}
}