{
  "type": "Feature",
  "properties": {
    "iso:country":"DE",
    "sg:address":"Schievenstr. 48",
    "sg:city":"Gelsenkirchen",
    "sg:phone":"+49 209/73232",
    "sg:postcode":"45891",
    "sg:province":"Nordrhein-Westfalen",
    "wof:name":"Posny Lebensmittel- Einzelhandelsges. Mbh",
    "wof:placetype":"venue"
},
  "geometry": {"coordinates":[7.0846028328,51.5734825134],"type":"Point"}
}