{
  "type": "Feature",
  "properties": {
    "iso:country":"DE",
    "sg:address":"Heinrichstr. 57",
    "sg:city":"Fulda",
    "sg:phone":"+49 661/73173",
    "sg:postcode":"36037",
    "sg:province":"Hessen",
    "wof:name":"Pizzeria Marathon",
    "wof:placetype":"venue"
},
  "geometry": {"coordinates":[9.6850004196,50.5515213013],"type":"Point"}
}