{
  "type": "Feature",
  "properties": {
    "iso:country":"DE",
    "sg:address":"Oberhofer Str. 24",
    "sg:city":"Zella-Mehlis",
    "sg:phone":"+49 3682/482732",
    "sg:postcode":"98544",
    "sg:province":"Th\u00fcringen",
    "wof:name":"Rolf-dieter Mentzel Heilpraktiker",
    "wof:placetype":"venue"
},
  "geometry": {"coordinates":[10.6735448837,50.6544914246],"type":"Point"}
}