{
  "type": "Feature",
  "properties": {
    "iso:country":"DE",
    "sg:address":"Im Dahl 15",
    "sg:city":"Bonn",
    "sg:phone":"+49 228/676389",
    "sg:postcode":"53117",
    "sg:province":"Nordrhein-Westfalen",
    "wof:name":"Kosmetik Im Maritim Inh. Ulrike Winter",
    "wof:placetype":"venue"
},
  "geometry": {"coordinates":[7.057669,50.75713],"type":"Point"}
}