{
  "type": "Feature",
  "properties": {
    "iso:country":"DE",
    "sg:address":"Bismarckstr. 2",
    "sg:city":"Varel",
    "sg:phone":"+49 4451/82326",
    "sg:postcode":"26316",
    "sg:province":"Niedersachsen",
    "wof:name":"Dirk Bohlen Architekt",
    "wof:placetype":"venue"
},
  "geometry": {"coordinates":[8.14337,53.40012],"type":"Point"}
}