{
  "type": "Feature",
  "properties": {
    "iso:country":"DE",
    "sg:address":"Hauptstr. 64",
    "sg:city":"S\u00fcderl\u00fcgum",
    "sg:postcode":"25923",
    "sg:province":"Schleswig-Holstein",
    "wof:name":"Kay Uwe Jensens Discount S\u00fcderl\u00fcgum Gmbh",
    "wof:placetype":"venue"
},
  "geometry": {"coordinates":[8.908993721,54.8763465881],"type":"Point"}
}