{
  "type": "Feature",
  "properties": {
    "iso:country":"DE",
    "sg:address":"Bokeler Str. 31",
    "sg:city":"Rheda-Wiedenbr\u00fcck",
    "sg:phone":"+49 5242/7185",
    "sg:postcode":"33378",
    "sg:province":"Nordrhein-Westfalen",
    "wof:name":"Bernhard M\u00f6nning",
    "wof:placetype":"venue"
},
  "geometry": {"coordinates":[8.331228,51.811256],"type":"Point"}
}