{
  "type": "Feature",
  "properties": {
    "iso:country":"DE",
    "sg:address":"Viktoriastr. 9",
    "sg:city":"Berlin",
    "sg:postcode":"12203",
    "sg:province":"Berlin",
    "wof:name":"Dogg E. K.",
    "wof:placetype":"venue"
},
  "geometry": {"coordinates":[13.306235,52.442898],"type":"Point"}
}