{
  "type": "Feature",
  "properties": {
    "iso:country":"DE",
    "sg:address":"Gewerbegebiet D\u00f6gelm\u00fchle",
    "sg:city":"Karben",
    "sg:phone":"+49 6039/91300",
    "sg:postcode":"61184",
    "sg:province":"Hessen",
    "wof:name":"Sirius Beschallungstechnik",
    "wof:placetype":"venue"
},
  "geometry": {"coordinates":[8.772262,50.237507],"type":"Point"}
}