{
  "type": "Feature",
  "properties": {
    "iso:country":"DE",
    "sg:address":"Neu Friederikengroden 1",
    "sg:city":"Wangerland",
    "sg:phone":"+49 4463/347",
    "sg:postcode":"26434",
    "sg:province":"Niedersachsen",
    "wof:name":"Adalbert Lowien",
    "wof:placetype":"venue"
},
  "geometry": {"coordinates":[7.907536,53.705578],"type":"Point"}
}