{
  "type": "Feature",
  "properties": {
    "iso:country":"DE",
    "sg:address":"Gr\u00fcnstr. 34",
    "sg:city":"Neuenhagen",
    "sg:phone":"+49 3342/200449",
    "sg:postcode":"15366",
    "sg:province":"Brandenburg",
    "wof:name":"Manfred Gassan Rechtsanwalt",
    "wof:placetype":"venue"
},
  "geometry": {"coordinates":[13.6645202637,52.5320510864],"type":"Point"}
}