{
  "type": "Feature",
  "properties": {
    "iso:country":"DE",
    "sg:address":"Boltraystr. 289",
    "sg:city":"Voerde",
    "sg:phone":"+49 2855/6238",
    "sg:postcode":"46562",
    "sg:province":"Nordrhein-Westfalen",
    "wof:name":"Hermann Abel",
    "wof:placetype":"venue"
},
  "geometry": {"coordinates":[6.636237,51.610989],"type":"Point"}
}