{
  "type": "Feature",
  "properties": {
    "iso:country":"DE",
    "sg:address":"Rennertshofen",
    "sg:city":"Rennertshofen",
    "sg:phone":"+49 8434/258",
    "sg:postcode":"86643",
    "sg:province":"Bayern",
    "wof:name":"Hypo-bank Ag",
    "wof:placetype":"venue"
},
  "geometry": {"coordinates":[11.04692,48.772579],"type":"Point"}
}