{
  "type": "Feature",
  "properties": {
    "iso:country":"DE",
    "sg:address":"Kreuzbergstr. 30",
    "sg:city":"Hallerndorf",
    "sg:phone":"+49 9545/7472",
    "sg:postcode":"91352",
    "sg:province":"Bayern",
    "wof:name":"Albin Willner",
    "wof:placetype":"venue"
},
  "geometry": {"coordinates":[10.9769,49.75679],"type":"Point"}
}