{
  "type": "Feature",
  "properties": {
    "iso:country":"DE",
    "sg:address":"Falkenstr. 12",
    "sg:city":"Erkrath",
    "sg:phone":"+49 211/243045",
    "sg:postcode":"40699",
    "sg:province":"Nordrhein-Westfalen",
    "wof:name":"K. Gisch Immobilienmakler",
    "wof:placetype":"venue"
},
  "geometry": {"coordinates":[6.9158082008,51.2184143066],"type":"Point"}
}