{
  "type": "Feature",
  "properties": {
    "iso:country":"DE",
    "sg:address":"Sulzbachtalstr. 70",
    "sg:city":"Sulzbach",
    "sg:phone":"+49 4968/973044",
    "sg:postcode":"66280",
    "sg:province":"Saarland",
    "wof:name":"Bayerische Vereinsbank Ag",
    "wof:placetype":"venue"
},
  "geometry": {"coordinates":[7.061303,49.299068],"type":"Point"}
}