{
  "type": "Feature",
  "properties": {
    "iso:country":"DE",
    "sg:address":"Kr\u00e4henweg 53",
    "sg:city":"F\u00fcrth",
    "sg:phone":"+49 911/752353",
    "sg:postcode":"90768",
    "sg:province":"Bayern",
    "wof:name":"M. Und R. Marr",
    "wof:placetype":"venue"
},
  "geometry": {"coordinates":[10.938303,49.489567],"type":"Point"}
}