{
  "type": "Feature",
  "properties": {
    "iso:country":"DE",
    "sg:address":"Hauptstr. 58",
    "sg:city":"Ellingshausen",
    "sg:phone":"+49 36949",
    "sg:postcode":"98617",
    "sg:province":"Th\u00fcringen",
    "wof:name":"Autoland Ellingshausen",
    "wof:placetype":"venue"
},
  "geometry": {"coordinates":[10.4735527039,50.5492515564],"type":"Point"}
}