{
  "type": "Feature",
  "properties": {
    "iso:country":"DE",
    "sg:address":"Speckenstr. 24",
    "sg:city":"Dorum",
    "sg:phone":"+49 4742/1007",
    "sg:postcode":"27632",
    "sg:province":"Niedersachsen",
    "wof:name":"Foto-quelle",
    "wof:placetype":"venue"
},
  "geometry": {"coordinates":[8.5708503723,53.6870651245],"type":"Point"}
}