{
  "type": "Feature",
  "properties": {
    "iso:country":"DE",
    "sg:address":"Knollstr. 170",
    "sg:city":"Osnabr\u00fcck",
    "sg:phone":"+49 541/185353",
    "sg:postcode":"49088",
    "sg:province":"Niedersachsen",
    "wof:name":"Westerfeld",
    "wof:placetype":"venue"
},
  "geometry": {"coordinates":[8.064831,52.2934],"type":"Point"}
}