{
  "type": "Feature",
  "properties": {
    "iso:country":"DE",
    "sg:address":"Gleueler Str. 316",
    "sg:city":"K\u00f6ln",
    "sg:phone":"+49 221/4305410",
    "sg:postcode":"50935",
    "sg:province":"Nordrhein-Westfalen",
    "wof:name":"J\u00fcrgen Maria Sch\u00f6nenkorb Hausbetreuung Gmbh",
    "wof:placetype":"venue"
},
  "geometry": {"coordinates":[6.901006,50.917374],"type":"Point"}
}