{
  "type": "Feature",
  "properties": {
    "iso:country":"DE",
    "sg:address":"Gerstunger Str. 4",
    "sg:city":"Lauchr\u00f6den",
    "sg:postcode":"99819",
    "sg:province":"Th\u00fcringen",
    "wof:name":"Quelleagentur Schneider",
    "wof:placetype":"venue"
},
  "geometry": {"coordinates":[10.1559419632,50.9931030273],"type":"Point"}
}