{
  "type": "Feature",
  "properties": {
    "iso:country":"DE",
    "sg:address":"Brunnenstr 31",
    "sg:city":"Krauchenwies",
    "sg:phone":"+49 7576/96050",
    "sg:postcode":"72505",
    "sg:province":"Baden-W\u00fcrttemberg",
    "wof:name":"Gebr. Oelkuch Gmbh & Co Kg",
    "wof:placetype":"venue"
},
  "geometry": {"coordinates":[9.22469,48.022812],"type":"Point"}
}