{
  "type": "Feature",
  "properties": {
    "iso:country":"DE",
    "sg:address":"Bahnhofstr. 4",
    "sg:city":"Neu\u00f6tting",
    "sg:phone":"+49 8671/71077",
    "sg:postcode":"84524",
    "sg:province":"Bayern",
    "wof:name":"Charlys Treff",
    "wof:placetype":"venue"
},
  "geometry": {"coordinates":[12.68126297,48.2430038452],"type":"Point"}
}