{
  "type": "Feature",
  "properties": {
    "iso:country":"DE",
    "sg:address":"Conrad-R\u00f6ntgen-Str. 1",
    "sg:city":"Wasserliesch",
    "sg:phone":"+49 6501/31201",
    "sg:postcode":"54332",
    "sg:province":"Rheinland-Pfalz",
    "wof:name":"Pott & H\u00f6nscheid Gmbh",
    "wof:placetype":"venue"
},
  "geometry": {"coordinates":[6.5597891808,49.6946144104],"type":"Point"}
}