{
  "type": "Feature",
  "properties": {
    "iso:country":"DE",
    "sg:address":"Feldhusstr. 1",
    "sg:city":"Delmenhorst",
    "sg:phone":"+49 4221/92690",
    "sg:postcode":"27755",
    "sg:province":"Niedersachsen",
    "wof:name":"Apmann Gesellschaft F\u00fcr Daten- Und Kommunikations-",
    "wof:placetype":"venue"
},
  "geometry": {"coordinates":[8.6519603729,53.0181655884],"type":"Point"}
}