{
  "type": "Feature",
  "properties": {
    "iso:country":"DE",
    "sg:address":"Hauptstra\u00dfe 241",
    "sg:city":"M\u00fcnsingen - Auingen",
    "sg:phone":"+49 7381/935040",
    "sg:postcode":"72525",
    "sg:province":"Baden-W\u00fcrttemberg",
    "wof:name":"Maler Kraft",
    "wof:placetype":"venue"
},
  "geometry": {"coordinates":[9.5300703049,48.4127311707],"type":"Point"}
}