{
  "type": "Feature",
  "properties": {
    "iso:country":"DE",
    "sg:address":"Seidlstr. 24",
    "sg:city":"M\u00fcnchen",
    "sg:phone":"+49 89/2340",
    "sg:postcode":"80335",
    "sg:province":"Bayern",
    "wof:name":"Siemens Kapitalanlagegesellschaft Mbh",
    "wof:placetype":"venue"
},
  "geometry": {"coordinates":[11.5580387115,48.1451454163],"type":"Point"}
}