{
  "type": "Feature",
  "properties": {
    "iso:country":"DE",
    "sg:address":"Karl-Liebknecht-Str. 21",
    "sg:city":"Neugersdorf",
    "sg:phone":"+49 3586/32575",
    "sg:postcode":"02727",
    "sg:province":"Sachsen",
    "wof:name":"S. Fiedler",
    "wof:placetype":"venue"
},
  "geometry": {"coordinates":[14.609794,50.975948],"type":"Point"}
}