{
  "type": "Feature",
  "properties": {
    "iso:country":"DE",
    "sg:address":"Fichtenhofer Str. 24",
    "sg:city":"Ammerthal",
    "sg:phone":"+49 9628/914204",
    "sg:postcode":"92260",
    "sg:province":"Bayern",
    "wof:name":"Holzbau Kiener Gmbh",
    "wof:placetype":"venue"
},
  "geometry": {"coordinates":[11.762462616,49.4435195923],"type":"Point"}
}