{
  "type": "Feature",
  "properties": {
    "iso:country":"DE",
    "sg:address":"Brookh\u00f6rn 18",
    "sg:city":"Eckernf\u00f6rde",
    "sg:phone":"+49 4351/41353",
    "sg:postcode":"24340",
    "sg:province":"Schleswig-Holstein",
    "wof:name":"Ev. Pfarramt Iii St. Nicolai",
    "wof:placetype":"venue"
},
  "geometry": {"coordinates":[9.8503303528,54.4510879517],"type":"Point"}
}