{
  "type": "Feature",
  "properties": {
    "iso:country":"DE",
    "sg:address":"Am Ernst-Th\u00e4lmann-Hain 1",
    "sg:city":"Gelenau",
    "sg:postcode":"09423",
    "sg:province":"Sachsen",
    "wof:name":"Textilhandel-vertretung Wieland & Nitsche",
    "wof:placetype":"venue"
},
  "geometry": {"coordinates":[12.9793434143,50.7124557495],"type":"Point"}
}