{
  "type": "Feature",
  "properties": {
    "iso:country":"DE",
    "sg:address":"Weusterstr. 1",
    "sg:city":"Bottrop",
    "sg:phone":"+49 2041/48492",
    "sg:postcode":"46240",
    "sg:province":"Nordrhein-Westfalen",
    "wof:name":"Beta-micro Test Gmbh",
    "wof:placetype":"venue"
},
  "geometry": {"coordinates":[6.979311,51.543613],"type":"Point"}
}