{
  "type": "Feature",
  "properties": {
    "iso:country":"DE",
    "sg:address":"Firmungstr. 34",
    "sg:city":"Koblenz",
    "sg:phone":"+49 261/35517",
    "sg:postcode":"56068",
    "sg:province":"Rheinland-Pfalz",
    "wof:name":"Eiscafe Brustolon",
    "wof:placetype":"venue"
},
  "geometry": {"coordinates":[7.598709,50.360775],"type":"Point"}
}