{
  "type": "Feature",
  "properties": {
    "iso:country":"DE",
    "sg:address":"Mozartstr. 38",
    "sg:city":"Emmendingen",
    "sg:phone":"+49 7641/8274",
    "sg:postcode":"79312",
    "sg:province":"Baden-W\u00fcrttemberg",
    "wof:name":"Renate Langenbrink Krankenhausbedarf",
    "wof:placetype":"venue"
},
  "geometry": {"coordinates":[7.861066,48.123238],"type":"Point"}
}