{
  "type": "Feature",
  "properties": {
    "iso:country":"DE",
    "sg:address":"Hauptstr. 42",
    "sg:city":"Bad Bertrich",
    "sg:phone":"+49 2674/546",
    "sg:postcode":"56864",
    "sg:province":"Rheinland-Pfalz",
    "wof:name":"Harald Burgard",
    "wof:placetype":"venue"
},
  "geometry": {"coordinates":[7.0184969902,50.0882759094],"type":"Point"}
}