{
  "type": "Feature",
  "properties": {
    "iso:country":"DE",
    "sg:address":"Gl\u00fcckaufstr. 14",
    "sg:city":"Waakirchen",
    "sg:phone":"+49 8021/215",
    "sg:postcode":"83666",
    "sg:province":"Bayern",
    "wof:name":"Sportzentrum Keglst\u00fcberl",
    "wof:placetype":"venue"
},
  "geometry": {"coordinates":[11.6837205887,47.7713088989],"type":"Point"}
}