{
  "type": "Feature",
  "properties": {
    "iso:country":"DE",
    "sg:address":"Mainzer Landstra\u00dfe 97",
    "sg:city":"Frankfurt",
    "sg:phone":"+49 69/2624900",
    "sg:postcode":"60329",
    "sg:province":"Hessen",
    "wof:name":"Diemer Outplacement",
    "wof:placetype":"venue"
},
  "geometry": {"coordinates":[8.66134,50.109718],"type":"Point"}
}