{
  "type": "Feature",
  "properties": {
    "iso:country":"DE",
    "sg:address":"Lochnerstr. 12",
    "sg:city":"Ratingen",
    "sg:phone":"+49 2102/870396",
    "sg:postcode":"40878",
    "sg:province":"Nordrhein-Westfalen",
    "wof:name":"P. Lerschmacher",
    "wof:placetype":"venue"
},
  "geometry": {"coordinates":[6.842556,51.289589],"type":"Point"}
}