{
  "type": "Feature",
  "properties": {
    "iso:country":"DE",
    "sg:address":"Blumenrather Str. 32",
    "sg:city":"Alsdorf",
    "sg:phone":"+49 2404/63296",
    "sg:postcode":"52477",
    "sg:province":"Nordrhein-Westfalen",
    "wof:name":"Pizzeria O Vesuvia",
    "wof:placetype":"venue"
},
  "geometry": {"coordinates":[6.1881542206,50.861164093],"type":"Point"}
}