{
  "type": "Feature",
  "properties": {
    "iso:country":"DE",
    "sg:address":"22 rue des ebiosres",
    "sg:city":"plaisir",
    "sg:phone":"+49 6843/35184",
    "sg:postcode":"78370",
    "wof:name":"Ordipassion",
    "wof:placetype":"venue"
},
  "geometry": {"coordinates":[1.952318,48.827194],"type":"Point"}
}