{
  "type": "Feature",
  "properties": {
    "iso:country":"DE",
    "sg:address":"Reginenstr. 5",
    "sg:city":"Leipzig",
    "sg:postcode":"04155",
    "sg:province":"Sachsen",
    "wof:name":"Qsl-dx-funker-club- Exklusiv-leipzig E. V.",
    "wof:placetype":"venue"
},
  "geometry": {"coordinates":[12.3672742844,51.3626060486],"type":"Point"}
}