{
  "type": "Feature",
  "properties": {
    "iso:country":"DE",
    "sg:address":"Weilergasse 5",
    "sg:city":"Dormagen",
    "sg:phone":"+49 2133/10494",
    "sg:postcode":"41540",
    "sg:province":"Nordrhein-Westfalen",
    "wof:name":"Hotel Weilerhof",
    "wof:placetype":"venue"
},
  "geometry": {"coordinates":[6.8118457794,51.0992202759],"type":"Point"}
}