{
  "type": "Feature",
  "properties": {
    "iso:country":"DE",
    "sg:address":"Hauptstr. 41",
    "sg:city":"Westendorf",
    "sg:phone":"+49 8273/1463",
    "sg:postcode":"86707",
    "sg:province":"Bayern",
    "wof:name":"Leonhard Wiedemann",
    "wof:placetype":"venue"
},
  "geometry": {"coordinates":[10.834491,48.573219],"type":"Point"}
}