{
  "type": "Feature",
  "properties": {
    "iso:country":"DE",
    "sg:address":"Olper Str. 69 a",
    "sg:city":"Overath",
    "sg:phone":"+49 2204/74593",
    "sg:postcode":"51491",
    "sg:province":"Nordrhein-Westfalen",
    "wof:name":"Der Weinladen",
    "wof:placetype":"venue"
},
  "geometry": {"coordinates":[7.2228097916,50.9442405701],"type":"Point"}
}