{
  "type": "Feature",
  "properties": {
    "iso:country":"DE",
    "sg:address":"Christofstr. 21",
    "sg:city":"Waiblingen",
    "sg:phone":"+49 7151/15654",
    "sg:postcode":"71332",
    "sg:province":"Baden-W\u00fcrttemberg",
    "wof:name":"Musik- Und Kunstschule Unteres Remstal",
    "wof:placetype":"venue"
},
  "geometry": {"coordinates":[9.3089590073,48.8322257996],"type":"Point"}
}