{
  "type": "Feature",
  "properties": {
    "iso:country":"DE",
    "sg:address":"F\u00fcrstenbergstr. 7 a",
    "sg:city":"Paderborn",
    "sg:phone":"+49 5251/27914",
    "sg:postcode":"33102",
    "sg:province":"Nordrhein-Westfalen",
    "wof:name":"Druckpunkt Gmbh",
    "wof:placetype":"venue"
},
  "geometry": {"coordinates":[8.7450380325,51.7165412903],"type":"Point"}
}