{
  "type": "Feature",
  "properties": {
    "iso:country":"DE",
    "sg:address":"Fron\u00e4ckerstr 50",
    "sg:city":"Sindelfingen",
    "sg:phone":"+49 7031/795360",
    "sg:postcode":"71063",
    "sg:province":"Baden-W\u00fcrttemberg",
    "wof:name":"Pwm Gmbh & Co. Kg Promotionwear Merchandising",
    "wof:placetype":"venue"
},
  "geometry": {"coordinates":[8.985817,48.708977],"type":"Point"}
}