{
  "type": "Feature",
  "properties": {
    "iso:country":"DE",
    "sg:address":"Max-Planck-Rg. 14",
    "sg:city":"Ilmenau",
    "sg:phone":"+49 4936/77690",
    "sg:postcode":"98693",
    "sg:province":"Th\u00fcringen",
    "wof:name":"Technische Universit\u00c4t Ilmenau",
    "wof:placetype":"venue"
},
  "geometry": {"coordinates":[10.93302,50.681099],"type":"Point"}
}