{
  "type": "Feature",
  "properties": {
    "iso:country":"DE",
    "sg:address":"Im Entenb\u00fchl 5",
    "sg:city":"Radolfzell",
    "sg:phone":"+49 7732/10353",
    "sg:postcode":"78315",
    "sg:province":"Baden-W\u00fcrttemberg",
    "wof:name":"Schlaraffia Porta Alpina Constantiae E. V.",
    "wof:placetype":"venue"
},
  "geometry": {"coordinates":[9.0060195923,47.7654762268],"type":"Point"}
}