{
  "type": "Feature",
  "properties": {
    "iso:country":"DE",
    "sg:address":"Cuno-Hoffmeister-Str. 9",
    "sg:city":"Sonneberg",
    "sg:phone":"+49 3675/89850",
    "sg:postcode":"96515",
    "sg:province":"Th\u00fcringen",
    "wof:name":"Elektro Sonneberg Fachgesch\u00e4ft Und Service Gmbh",
    "wof:placetype":"venue"
},
  "geometry": {"coordinates":[11.1733875275,50.3565483093],"type":"Point"}
}