{
  "type": "Feature",
  "properties": {
    "iso:country":"DE",
    "sg:address":"Birkelbacher Str. 4",
    "sg:city":"Satteldorf",
    "sg:phone":"+49 7950/925064",
    "sg:postcode":"74589",
    "sg:province":"Baden-W\u00fcrttemberg",
    "wof:name":"Buchhandlung Otto Spatz Gmbh & Co. Kg",
    "wof:placetype":"venue"
},
  "geometry": {"coordinates":[10.142118454,49.1756439209],"type":"Point"}
}