{
  "type": "Feature",
  "properties": {
    "iso:country":"DE",
    "sg:address":"Hansastr. 17",
    "sg:city":"M\u00fcnchen",
    "sg:phone":"+49 89/5470300",
    "sg:postcode":"80686",
    "sg:province":"Bayern",
    "wof:name":"Dks Daten-kontroll- Systeme Gmbh",
    "wof:placetype":"venue"
},
  "geometry": {"coordinates":[11.5265655518,48.1343841553],"type":"Point"}
}