{
  "type": "Feature",
  "properties": {
    "iso:country":"DE",
    "sg:address":"Hauptstr. 107",
    "sg:city":"Calw",
    "sg:phone":"+49 7051/93140",
    "sg:postcode":"75365",
    "sg:province":"Baden-W\u00fcrttemberg",
    "wof:name":"Ver-point Immobilien- Und",
    "wof:placetype":"venue"
},
  "geometry": {"coordinates":[8.762055397,48.6979103088],"type":"Point"}
}