{
  "type": "Feature",
  "properties": {
    "iso:country":"DE",
    "sg:address":"Otto-Grot-Str. 69",
    "sg:city":"Hamburg",
    "sg:phone":"+49 40/7355771",
    "sg:postcode":"21035",
    "sg:province":"Hamburg",
    "wof:name":"Peter L\u00fchr",
    "wof:placetype":"venue"
},
  "geometry": {"coordinates":[10.1533679962,53.4885406494],"type":"Point"}
}