{
  "type": "Feature",
  "properties": {
    "iso:country":"DE",
    "sg:address":"Othmarstr. 7",
    "sg:city":"Frechen",
    "sg:phone":"+49 2234/58303",
    "sg:postcode":"50226",
    "sg:province":"Nordrhein-Westfalen",
    "wof:name":"Eberhard Manthey",
    "wof:placetype":"venue"
},
  "geometry": {"coordinates":[6.8142309189,50.9084625244],"type":"Point"}
}