{
  "type": "Feature",
  "properties": {
    "iso:country":"DE",
    "sg:address":"Roteb\u00fchlstr. 163",
    "sg:city":"Stuttgart",
    "sg:phone":"+49 711/666460",
    "sg:postcode":"70197",
    "sg:province":"Baden-W\u00fcrttemberg",
    "wof:name":"Dr. Wilhelm Verwaltungs- Gmbh & Co. Kg",
    "wof:placetype":"venue"
},
  "geometry": {"coordinates":[9.153527,48.76931],"type":"Point"}
}