{
  "type": "Feature",
  "properties": {
    "iso:country":"DE",
    "sg:address":"Gerbergasse 36",
    "sg:city":"Alpirsbach",
    "sg:phone":"+49 7444/2048",
    "sg:postcode":"72275",
    "sg:province":"Baden-W\u00fcrttemberg",
    "wof:name":"Willy Eberhard",
    "wof:placetype":"venue"
},
  "geometry": {"coordinates":[8.406536,48.345451],"type":"Point"}
}