{
  "type": "Feature",
  "properties": {
    "iso:country":"DE",
    "sg:address":"Neheimer Markt 2",
    "sg:city":"Arnsberg",
    "sg:phone":"+49 2932/29680",
    "sg:postcode":"59755",
    "sg:province":"Nordrhein-Westfalen",
    "wof:name":"Stadtb\u00fccherei Arnsberg",
    "wof:placetype":"venue"
},
  "geometry": {"coordinates":[7.960053,51.453373],"type":"Point"}
}