{
  "type": "Feature",
  "properties": {
    "iso:country":"DE",
    "sg:address":"Hauptstr. 14 a",
    "sg:city":"Horburg-Ma\u00dflau",
    "sg:phone":"+49 34204/62282",
    "sg:postcode":"06254",
    "sg:province":"Sachsen-Anhalt",
    "wof:name":"Zema Freimut Hofmann Und J\u00fcrgen Seifert Ohg",
    "wof:placetype":"venue"
},
  "geometry": {"coordinates":[12.1736307144,51.3628463745],"type":"Point"}
}