{
  "type": "Feature",
  "properties": {
    "iso:country":"DE",
    "sg:address":"In den Kuhlen 28",
    "sg:city":"Simmerath",
    "sg:phone":"+49 2473/4523",
    "sg:postcode":"52152",
    "sg:province":"Nordrhein-Westfalen",
    "wof:name":"H. Hilgers",
    "wof:placetype":"venue"
},
  "geometry": {"coordinates":[6.3413739204,50.6312484741],"type":"Point"}
}