{
  "type": "Feature",
  "properties": {
    "iso:country":"DE",
    "sg:address":"Kyreinstr.",
    "sg:city":"Bad T\u00f6lz",
    "sg:phone":"+49 8041/77088",
    "sg:postcode":"83646",
    "sg:province":"Bayern",
    "wof:name":"Camilla Pl\u00f6ckl",
    "wof:placetype":"venue"
},
  "geometry": {"coordinates":[11.5480804443,47.7622337341],"type":"Point"}
}