{
  "type": "Feature",
  "properties": {
    "iso:country":"DE",
    "sg:address":"Am Tunnel 12",
    "sg:city":"Gr\u00e4venwiesbach",
    "sg:phone":"+49 6086/1800",
    "sg:postcode":"61279",
    "sg:province":"Hessen",
    "wof:name":"Dirk Egenolf",
    "wof:placetype":"venue"
},
  "geometry": {"coordinates":[8.48554,50.393955],"type":"Point"}
}