{
  "type": "Feature",
  "properties": {
    "iso:country":"DE",
    "sg:address":"Husumer Str. 120 a",
    "sg:city":"Bielefeld",
    "sg:phone":"+49 521/7700990",
    "sg:postcode":"33729",
    "sg:province":"Nordrhein-Westfalen",
    "wof:name":"Egoki Alliance Gmbh",
    "wof:placetype":"venue"
},
  "geometry": {"coordinates":[8.602723,52.078423],"type":"Point"}
}