{
  "type": "Feature",
  "properties": {
    "iso:country":"DE",
    "sg:address":"Heinrich-Ehrhardt-Str. 61",
    "sg:city":"D\u00fcsseldorf",
    "sg:postcode":"40468",
    "sg:province":"Nordrhein-Westfalen",
    "wof:name":"Dr. Peter Steinb\u00fcchel Tierarzt",
    "wof:placetype":"venue"
},
  "geometry": {"coordinates":[6.7884049416,51.2535591125],"type":"Point"}
}