{
  "type": "Feature",
  "properties": {
    "iso:country":"DE",
    "sg:address":"Mannheimer Str. 119",
    "sg:city":"Bad Kreuznach",
    "sg:phone":"+49 671/43187",
    "sg:postcode":"55543",
    "sg:province":"Rheinland-Pfalz",
    "wof:name":"Wehmeyer",
    "wof:placetype":"venue"
},
  "geometry": {"coordinates":[7.860326,49.843422],"type":"Point"}
}