{
  "type": "Feature",
  "properties": {
    "iso:country":"DE",
    "sg:address":"Karlsbrunnenstr 11",
    "sg:city":"Neu-Eichenberg",
    "sg:phone":"+49 5542/93610",
    "sg:postcode":"37249",
    "sg:province":"Hessen",
    "wof:name":"Eko-plant Gmbh",
    "wof:placetype":"venue"
},
  "geometry": {"coordinates":[9.900025,51.370167],"type":"Point"}
}