{
  "type": "Feature",
  "properties": {
    "iso:country":"DE",
    "sg:address":"Weinstr. 154",
    "sg:city":"Neuburg",
    "sg:phone":"+49 8431/8484",
    "sg:postcode":"86633",
    "sg:province":"Bayern",
    "wof:name":"Josef Heseler",
    "wof:placetype":"venue"
},
  "geometry": {"coordinates":[11.1838159561,48.7358055115],"type":"Point"}
}