{
  "type": "Feature",
  "properties": {
    "iso:country":"DE",
    "sg:address":"Brunnenstr. 3",
    "sg:city":"Oberscheidweiler",
    "sg:phone":"+49 6574/8792",
    "sg:postcode":"54533",
    "sg:province":"Rheinland-Pfalz",
    "wof:name":"Brunnenstube",
    "wof:placetype":"venue"
},
  "geometry": {"coordinates":[6.9340600967,50.0743789673],"type":"Point"}
}