{
  "type": "Feature",
  "properties": {
    "iso:country":"DE",
    "sg:address":"G\u00e4rtnerweg 15f",
    "sg:city":"Dietzenbach",
    "sg:phone":"+49 6074/309506",
    "sg:postcode":"63128",
    "sg:province":"Hessen",
    "wof:name":"K. Bittner",
    "wof:placetype":"venue"
},
  "geometry": {"coordinates":[8.7671079636,50.015750885],"type":"Point"}
}