{
  "type": "Feature",
  "properties": {
    "iso:country":"DE",
    "sg:address":"Luisenstr. 11",
    "sg:city":"K\u00f6ln",
    "sg:phone":"+49 221/9808270",
    "sg:postcode":"50679",
    "sg:province":"Nordrhein-Westfalen",
    "wof:name":"Armin Klaes Immobilienmakler",
    "wof:placetype":"venue"
},
  "geometry": {"coordinates":[6.9756789207,50.9362220764],"type":"Point"}
}