{
  "type": "Feature",
  "properties": {
    "iso:country":"DE",
    "sg:address":"Lunstruat 9",
    "sg:city":"Norddorf",
    "sg:phone":"+49 4682/995485",
    "sg:postcode":"25946",
    "sg:province":"Schleswig-Holstein",
    "wof:name":"Restaurant Pavarotti",
    "wof:placetype":"venue"
},
  "geometry": {"coordinates":[8.3324050903,54.6794090271],"type":"Point"}
}