{
  "type": "Feature",
  "properties": {
    "iso:country":"DE",
    "sg:address":"Bahnhofstr. 2",
    "sg:city":"Kyllburg",
    "sg:phone":"+49 6563/2344",
    "sg:postcode":"54655",
    "sg:province":"Rheinland-Pfalz",
    "wof:name":"Deutsche Bahn Ag",
    "wof:placetype":"venue"
},
  "geometry": {"coordinates":[6.5905351639,50.041015625],"type":"Point"}
}