{
  "type": "Feature",
  "properties": {
    "iso:country":"DE",
    "sg:address":"Kurf\u00fcrstenstr. 2",
    "sg:city":"M\u00fcnchen",
    "sg:phone":"+49 89/333953",
    "sg:postcode":"80799",
    "sg:province":"Bayern",
    "wof:name":"Rudolf Hermstein \u00dcbersetzungsb\u00fcro",
    "wof:placetype":"venue"
},
  "geometry": {"coordinates":[11.576651,48.15308],"type":"Point"}
}