{
  "type": "Feature",
  "properties": {
    "iso:country":"DE",
    "sg:address":"Baumgarten 3",
    "sg:city":"Limbach",
    "sg:phone":"+49 6287/9300",
    "sg:postcode":"74838",
    "sg:province":"Baden-W\u00fcrttemberg",
    "wof:name":"Hotel Volk",
    "wof:placetype":"venue"
},
  "geometry": {"coordinates":[9.2125244141,49.4600028992],"type":"Point"}
}