{
  "type": "Feature",
  "properties": {
    "iso:country":"DE",
    "sg:address":"Deuil-La-Barre-Str. 52",
    "sg:city":"Frankfurt",
    "sg:phone":"+49 69/5075310",
    "sg:postcode":"60437",
    "sg:province":"Hessen",
    "wof:name":"Orthop\u00e4die Schuhmode Peter Bobsin Gmbh",
    "wof:placetype":"venue"
},
  "geometry": {"coordinates":[8.6741533279,50.1995620728],"type":"Point"}
}