{
  "type": "Feature",
  "properties": {
    "iso:country":"DE",
    "sg:address":"Huntestr. 20",
    "sg:city":"Wildeshausen",
    "sg:phone":"+49 4431/74629",
    "sg:postcode":"27793",
    "sg:province":"Niedersachsen",
    "wof:name":"Blumenbinderei In Der Gildepassage",
    "wof:placetype":"venue"
},
  "geometry": {"coordinates":[8.437852,52.897427],"type":"Point"}
}