{
  "type": "Feature",
  "properties": {
    "iso:country":"DE",
    "sg:address":"B\u00f6singer Str. 19",
    "sg:city":"Haiterbach",
    "sg:phone":"+49 4974/561315",
    "sg:postcode":"72221",
    "sg:province":"Baden-W\u00fcrttemberg",
    "wof:name":"Volksbank Haiterbach Eg",
    "wof:placetype":"venue"
},
  "geometry": {"coordinates":[8.636601,48.540253],"type":"Point"}
}