{
  "type": "Feature",
  "properties": {
    "iso:country":"DE",
    "sg:address":"Gruttensteingasse 4",
    "sg:city":"Bad Reichenhall",
    "sg:phone":"+49 8651/4671",
    "sg:postcode":"83435",
    "sg:province":"Bayern",
    "wof:name":"Kleintierz\u00fcchterverein B 104 Bad Reichenhall Und Umgebung",
    "wof:placetype":"venue"
},
  "geometry": {"coordinates":[12.8762559891,47.7196464539],"type":"Point"}
}