{
  "type": "Feature",
  "properties": {
    "iso:country":"DE",
    "sg:address":"Frankfurter Str. 5",
    "sg:city":"Bad Hersfeld",
    "sg:phone":"+49 6621/70269",
    "sg:postcode":"36251",
    "sg:province":"Hessen",
    "wof:name":"B & E Videothekenbetriebs- U. Verwaltungsges. Mbh",
    "wof:placetype":"venue"
},
  "geometry": {"coordinates":[9.717247963,50.8654136658],"type":"Point"}
}