{
  "type": "Feature",
  "properties": {
    "iso:country":"DE",
    "sg:address":"Geierstr 2",
    "sg:city":"Euskirchen",
    "sg:phone":"+49 2255/6068",
    "sg:postcode":"53881",
    "sg:province":"Nordrhein-Westfalen",
    "wof:name":"Christian Sch\u00e4fer Gmbh",
    "wof:placetype":"venue"
},
  "geometry": {"coordinates":[6.848509,50.62582],"type":"Point"}
}