{
  "type": "Feature",
  "properties": {
    "iso:country":"DE",
    "sg:address":"Mevissenstr. 60",
    "sg:city":"Krefeld",
    "sg:phone":"+49 2151/758139",
    "sg:postcode":"47803",
    "sg:province":"Nordrhein-Westfalen",
    "wof:name":"Roman Melka Optik",
    "wof:placetype":"venue"
},
  "geometry": {"coordinates":[6.533208847,51.3465576172],"type":"Point"}
}