{
  "type": "Feature",
  "properties": {
    "iso:country":"DE",
    "sg:address":"Langendorfer Str. 105",
    "sg:city":"Neuwied",
    "sg:phone":"+49 2631/25105",
    "sg:postcode":"56564",
    "sg:province":"Rheinland-Pfalz",
    "wof:name":"Fries Gmbh",
    "wof:placetype":"venue"
},
  "geometry": {"coordinates":[7.458559,50.430611],"type":"Point"}
}