{
  "type": "Feature",
  "properties": {
    "iso:country":"DE",
    "sg:address":"Kolshorner Weg 5",
    "sg:city":"Burgdorf",
    "sg:phone":"+49 172 4622467",
    "sg:postcode":"31303",
    "sg:province":"Niedersachsen",
    "wof:name":"Maik Buchholz",
    "wof:placetype":"venue"
},
  "geometry": {"coordinates":[9.969945,52.438847],"type":"Point"}
}