{
  "type": "Feature",
  "properties": {
    "iso:country":"DE",
    "sg:address":"Schulstr. 5",
    "sg:city":"Herrenberg",
    "sg:phone":"+49 7032/24034",
    "sg:postcode":"71083",
    "sg:province":"Baden-W\u00fcrttemberg",
    "wof:name":"Alte Brennerei",
    "wof:placetype":"venue"
},
  "geometry": {"coordinates":[8.8698005676,48.5955543518],"type":"Point"}
}