{
  "type": "Feature",
  "properties": {
    "iso:country":"DE",
    "sg:address":"Hauptstr. 124",
    "sg:city":"Garbsen",
    "sg:phone":"+49 5131/51945",
    "sg:postcode":"30826",
    "sg:province":"Niedersachsen",
    "wof:name":"Gastst\u00e4tte H. Uelschen",
    "wof:placetype":"venue"
},
  "geometry": {"coordinates":[9.5604743958,52.459690094],"type":"Point"}
}