{
  "type": "Feature",
  "properties": {
    "iso:country":"DE",
    "sg:address":"Breddestr. 9",
    "sg:city":"Essen",
    "sg:phone":"+49 201/286846",
    "sg:postcode":"45138",
    "sg:province":"Nordrhein-Westfalen",
    "wof:name":"D. Lorei",
    "wof:placetype":"venue"
},
  "geometry": {"coordinates":[7.054283,51.44733],"type":"Point"}
}