{
  "type": "Feature",
  "properties": {
    "iso:country":"DE",
    "sg:address":"Daimlerstr. 4-6",
    "sg:city":"Neumarkt",
    "sg:phone":"+49 9181/25920",
    "sg:postcode":"92318",
    "sg:province":"Bayern",
    "wof:name":"Hammerbacher Gmbh",
    "wof:placetype":"venue"
},
  "geometry": {"coordinates":[11.4539728165,49.2714118958],"type":"Point"}
}