{
  "type": "Feature",
  "properties": {
    "iso:country":"DE",
    "sg:address":"Heppenheimer Str. 9",
    "sg:city":"Lorsch",
    "sg:phone":"+49 6251/57216",
    "sg:postcode":"64653",
    "sg:province":"Hessen",
    "wof:name":"Heinrich Diehl",
    "wof:placetype":"venue"
},
  "geometry": {"coordinates":[8.5687704086,49.6509475708],"type":"Point"}
}