{
  "type": "Feature",
  "properties": {
    "iso:country":"DE",
    "sg:address":"Ronneburgstr. 9",
    "sg:city":"Maintal",
    "sg:phone":"+49 6181/990350",
    "sg:postcode":"63477",
    "sg:province":"Hessen",
    "wof:name":"Hans-peter Stecay Versicherungs-agentur",
    "wof:placetype":"venue"
},
  "geometry": {"coordinates":[8.8515481949,50.1675567627],"type":"Point"}
}