{
  "type": "Feature",
  "properties": {
    "iso:country":"DE",
    "sg:address":"Lindenstr. 1",
    "sg:city":"Calau",
    "sg:phone":"+49 3541/2269",
    "sg:postcode":"03205",
    "sg:province":"Brandenburg",
    "wof:name":"D. We\u00dfnick",
    "wof:placetype":"venue"
},
  "geometry": {"coordinates":[13.950402,51.744423],"type":"Point"}
}