{
  "type": "Feature",
  "properties": {
    "iso:country":"DE",
    "sg:address":"Stendaler Str. 6",
    "sg:city":"Riesa",
    "sg:phone":"+49 3525/872439",
    "sg:postcode":"01587",
    "sg:province":"Sachsen",
    "wof:name":"G. Finger",
    "wof:placetype":"venue"
},
  "geometry": {"coordinates":[13.2593402863,51.3024902344],"type":"Point"}
}