{
  "type": "Feature",
  "properties": {
    "iso:country":"DE",
    "sg:address":"Friedrichstr. 38",
    "sg:city":"Westerland",
    "sg:phone":"+49 4651/1773",
    "sg:postcode":"25980",
    "sg:province":"Schleswig-Holstein",
    "wof:name":"Cafe-bistro Leysieffer",
    "wof:placetype":"venue"
},
  "geometry": {"coordinates":[8.3008651733,54.9077911377],"type":"Point"}
}