{
  "type": "Feature",
  "properties": {
    "iso:country":"DE",
    "sg:address":"Rheinstr. 9",
    "sg:city":"Kuppenheim",
    "sg:phone":"+49 7222/42358",
    "sg:postcode":"76456",
    "sg:province":"Baden-W\u00fcrttemberg",
    "wof:name":"Bistro Leopold",
    "wof:placetype":"venue"
},
  "geometry": {"coordinates":[8.2514705658,48.8277206421],"type":"Point"}
}