{
  "type": "Feature",
  "properties": {
    "iso:country":"DE",
    "sg:address":"Leichlinger Str. 7",
    "sg:city":"D\u00fcsseldorf",
    "sg:phone":"+49 211/765175",
    "sg:postcode":"40591",
    "sg:province":"Nordrhein-Westfalen",
    "wof:name":"Kr\u00e4tzer Gmbh",
    "wof:placetype":"venue"
},
  "geometry": {"coordinates":[6.81981,51.186863],"type":"Point"}
}