{
  "type": "Feature",
  "properties": {
    "iso:country":"DE",
    "sg:address":"Geisd\u00f6rfle 17",
    "sg:city":"Seebach",
    "sg:phone":"+49 7842/2222",
    "sg:postcode":"77889",
    "sg:province":"Baden-W\u00fcrttemberg",
    "wof:name":"G\u00fcnter Bohnert",
    "wof:placetype":"venue"
},
  "geometry": {"coordinates":[8.1942043304,48.5776062012],"type":"Point"}
}