{
  "type": "Feature",
  "properties": {
    "iso:country":"DE",
    "sg:address":"Kreuzberg 42",
    "sg:city":"Freyung",
    "sg:phone":"+49 8551/910321",
    "sg:postcode":"94078",
    "sg:province":"Bayern",
    "wof:name":"Kreuzberger Werkst\u00e4tte E. K.",
    "wof:placetype":"venue"
},
  "geometry": {"coordinates":[13.574103,48.840611],"type":"Point"}
}