{
  "type": "Feature",
  "properties": {
    "iso:country":"DE",
    "sg:address":"Ringstr 19",
    "sg:city":"Hillscheid",
    "sg:phone":"+49 2624/2550",
    "sg:postcode":"56204",
    "sg:province":"Rheinland-Pfalz",
    "wof:name":"Akru-keramik Gmbh",
    "wof:placetype":"venue"
},
  "geometry": {"coordinates":[7.6920089722,50.4047164917],"type":"Point"}
}