{
  "type": "Feature",
  "properties": {
    "iso:country":"DE",
    "sg:address":"Obere Hauptstr. 7",
    "sg:city":"Sulz",
    "sg:phone":"+49 7454/406928",
    "sg:postcode":"72172",
    "sg:province":"Baden-W\u00fcrttemberg",
    "wof:name":"A & Z Bau Gmbh",
    "wof:placetype":"venue"
},
  "geometry": {"coordinates":[8.6303262711,48.3616485596],"type":"Point"}
}