{
  "type": "Feature",
  "properties": {
    "iso:country":"DE",
    "sg:address":"Brunswiker Str. 46",
    "sg:city":"Kiel",
    "sg:phone":"+49 431/5795900",
    "sg:postcode":"24105",
    "sg:province":"Schleswig-Holstein",
    "wof:name":"Drogenberatungs- Und Sucht- Therapiezentrum Kiel",
    "wof:placetype":"venue"
},
  "geometry": {"coordinates":[10.1364383698,54.3289337158],"type":"Point"}
}