{
  "type": "Feature",
  "properties": {
    "iso:country":"DE",
    "sg:address":"Bodelschwinghstr. 2",
    "sg:city":"Marktredwitz",
    "sg:phone":"+49 9231/87494",
    "sg:postcode":"95615",
    "sg:province":"Bayern",
    "wof:name":"Dr.-ing. W. Stutzenberger Gmbh",
    "wof:placetype":"venue"
},
  "geometry": {"coordinates":[12.06203,50.001968],"type":"Point"}
}