{
  "type": "Feature",
  "properties": {
    "iso:country":"DE",
    "sg:address":"Wilhelmsh\u00f6her Allee 262",
    "sg:city":"Kassel",
    "sg:phone":"+49 561/32793",
    "sg:postcode":"34131",
    "sg:province":"Hessen",
    "wof:name":"K. Geis",
    "wof:placetype":"venue"
},
  "geometry": {"coordinates":[9.4451503754,51.3138084412],"type":"Point"}
}