{
  "type": "Feature",
  "properties": {
    "iso:country":"DE",
    "sg:address":"Vogteistr. 9",
    "sg:city":"Freiburg",
    "sg:postcode":"79112",
    "sg:province":"Baden-W\u00fcrttemberg",
    "wof:name":"Weis- Ohg",
    "wof:placetype":"venue"
},
  "geometry": {"coordinates":[7.7139000893,47.9836616516],"type":"Point"}
}