{
  "type": "Feature",
  "properties": {
    "iso:country":"DE",
    "sg:address":"B\u00fcrgerhorststr. 12",
    "sg:city":"Neustrelitz",
    "sg:phone":"+49 3981/205033",
    "sg:postcode":"17235",
    "sg:province":"Mecklenburg-Vorpommern",
    "wof:name":"Christian Bentzin",
    "wof:placetype":"venue"
},
  "geometry": {"coordinates":[13.0711612701,53.3555526733],"type":"Point"}
}