{
  "type": "Feature",
  "properties": {
    "iso:country":"DE",
    "sg:address":"Heinrich-Heine-Str 2",
    "sg:city":"Zeulenroda",
    "sg:phone":"+49 36628/810",
    "sg:postcode":"07937",
    "sg:province":"Th\u00fcringen",
    "wof:name":"Excellent Intimates Gmbh",
    "wof:placetype":"venue"
},
  "geometry": {"coordinates":[11.98888,50.651356],"type":"Point"}
}