{
  "type": "Feature",
  "properties": {
    "iso:country":"DE",
    "sg:address":"Reudener Str. 83b",
    "sg:city":"Wolfen",
    "sg:phone":"+49 3494/504230",
    "sg:postcode":"06766",
    "sg:province":"Sachsen-Anhalt",
    "wof:name":"Turm-apotheke Ute Volkmar",
    "wof:placetype":"venue"
},
  "geometry": {"coordinates":[12.250783,51.667843],"type":"Point"}
}