{
  "type": "Feature",
  "properties": {
    "iso:country":"DE",
    "sg:address":"Niederwettersche Str. 4",
    "sg:city":"Lahntal",
    "sg:phone":"+49 6423/3020",
    "sg:postcode":"35094",
    "sg:province":"Hessen",
    "wof:name":"Marburger Rohstoffverwertung Johannes V\u00f6lker Gmbh",
    "wof:placetype":"venue"
},
  "geometry": {"coordinates":[8.7565660477,50.8735351562],"type":"Point"}
}