{
  "type": "Feature",
  "properties": {
    "iso:country":"DE",
    "sg:address":"Enschedestr. 14",
    "sg:city":"Nordhorn",
    "sg:postcode":"48529",
    "sg:province":"Niedersachsen",
    "wof:name":"Motorcom Verwaltungs- Und Beteiligungs- Gmbh",
    "wof:placetype":"venue"
},
  "geometry": {"coordinates":[7.050431,52.410446],"type":"Point"}
}