{
  "type": "Feature",
  "properties": {
    "iso:country":"DE",
    "sg:address":"Podbielskistr. 131",
    "sg:city":"Hannover",
    "sg:postcode":"30177",
    "sg:province":"Niedersachsen",
    "wof:name":"Putz- Und Fugerarbeiten Anastasiou Inh. Wasiliki",
    "wof:placetype":"venue"
},
  "geometry": {"coordinates":[9.768907547,52.3970947266],"type":"Point"}
}