{
  "type": "Feature",
  "properties": {
    "iso:country":"DE",
    "sg:address":"Einsteinstr. 45",
    "sg:city":"Velbert",
    "sg:postcode":"42549",
    "sg:province":"Nordrhein-Westfalen",
    "wof:name":"Pc-doktor E. K.",
    "wof:placetype":"venue"
},
  "geometry": {"coordinates":[7.0230298042,51.340171814],"type":"Point"}
}