{
  "type": "Feature",
  "properties": {
    "iso:country":"DE",
    "sg:address":"Thanhofer Str. 4",
    "sg:city":"Steinpleis",
    "sg:postcode":"08432",
    "wof:name":"Hochmuth Gmbh",
    "wof:placetype":"venue"
},
  "geometry": {"coordinates":[12.395392,50.706829],"type":"Point"}
}