{
  "type": "Feature",
  "properties": {
    "iso:country":"DE",
    "sg:address":"Bahnhofstr. 51",
    "sg:city":"Freudenberg",
    "sg:phone":"+49 2734/489177",
    "sg:postcode":"57258",
    "sg:province":"Nordrhein-Westfalen",
    "wof:name":"B\u00e4ren-apotheke Inh. Detlev Krause E. K.",
    "wof:placetype":"venue"
},
  "geometry": {"coordinates":[7.879862,50.900089],"type":"Point"}
}