{
  "type": "Feature",
  "properties": {
    "iso:country":"DE",
    "sg:address":"Winkelhauser Str. 42",
    "sg:city":"Duisburg",
    "sg:phone":"+49 2065/62401",
    "sg:postcode":"47228",
    "sg:province":"Nordrhein-Westfalen",
    "wof:name":"Ev. Pfarramt Ii Christuskirche Rheinhausen",
    "wof:placetype":"venue"
},
  "geometry": {"coordinates":[6.6942820549,51.425617218],"type":"Point"}
}