{
  "type": "Feature",
  "properties": {
    "iso:country":"DE",
    "sg:address":"Holsteinische Str. 29",
    "sg:city":"Berlin",
    "sg:phone":"+49 30/8591474",
    "sg:postcode":"12161",
    "sg:province":"Berlin",
    "wof:name":"Peter Neuhold Heilpraktiker",
    "wof:placetype":"venue"
},
  "geometry": {"coordinates":[13.3342552185,52.4660301208],"type":"Point"}
}