{
  "type": "Feature",
  "properties": {
    "iso:country":"DE",
    "sg:address":"Unterwindsberg 3",
    "sg:city":"Simmelsdorf",
    "sg:phone":"+49 9155/256",
    "sg:postcode":"91245",
    "sg:province":"Bayern",
    "wof:name":"Pension Helmut Ritter",
    "wof:placetype":"venue"
},
  "geometry": {"coordinates":[11.3164396286,49.6061096191],"type":"Point"}
}