{
  "type": "Feature",
  "properties": {
    "iso:country":"DE",
    "sg:address":"Gro\u00dfweidenm\u00fchlstr. 2",
    "sg:city":"N\u00fcrnberg",
    "sg:phone":"+49 911/399108",
    "sg:postcode":"90419",
    "sg:province":"Bayern",
    "wof:name":"Gustav-schickedanz-stiftung",
    "wof:placetype":"venue"
},
  "geometry": {"coordinates":[11.0650815964,49.4566612244],"type":"Point"}
}