{
  "type": "Feature",
  "properties": {
    "iso:country":"DE",
    "sg:address":"Am Seeberg 19",
    "sg:city":"J\u00fcrgenstorf",
    "sg:phone":"+49 39955/20663",
    "sg:postcode":"17153",
    "sg:province":"Mecklenburg-Vorpommern",
    "wof:name":"M. Rohde",
    "wof:placetype":"venue"
},
  "geometry": {"coordinates":[12.904012,53.657646],"type":"Point"}
}