{
  "type": "Feature",
  "properties": {
    "iso:country":"DE",
    "sg:address":"Neuenkirchener Str. 34",
    "sg:city":"Emsdetten",
    "sg:phone":"+49 2572/5628",
    "sg:postcode":"48282",
    "sg:province":"Nordrhein-Westfalen",
    "wof:name":"Bh. Wenkers",
    "wof:placetype":"venue"
},
  "geometry": {"coordinates":[7.510991,52.173656],"type":"Point"}
}