{
  "type": "Feature",
  "properties": {
    "iso:country":"DE",
    "sg:address":"Niendorfer Str. 25 POSTFACH 540480",
    "sg:city":"Hamburg",
    "sg:phone":"+49 40/5542140",
    "sg:postcode":"22504",
    "sg:province":"Hamburg",
    "wof:name":"B\u00c4ckerei Kamps-nord Gmbh & Co. Kg",
    "wof:placetype":"venue"
},
  "geometry": {"coordinates":[9.954019,53.603821],"type":"Point"}
}