{
  "type": "Feature",
  "properties": {
    "iso:country":"DE",
    "sg:address":"Universit\u00e4tsstr. 28",
    "sg:city":"Marburg",
    "sg:phone":"+49 6421/12266",
    "sg:postcode":"35037",
    "sg:province":"Hessen",
    "wof:name":"China-restaurant Hongkong",
    "wof:placetype":"venue"
},
  "geometry": {"coordinates":[8.7645397186,50.8064308167],"type":"Point"}
}