{
  "type": "Feature",
  "properties": {
    "iso:country":"DE",
    "sg:address":"Lindenstr. 8",
    "sg:city":"Saarlouis",
    "sg:phone":"+49 6831/83710",
    "sg:postcode":"66740",
    "sg:province":"Saarland",
    "wof:name":"Martina Kiefer & St. Weishaupt",
    "wof:placetype":"venue"
},
  "geometry": {"coordinates":[6.7476,49.329868],"type":"Point"}
}