{
  "type": "Feature",
  "properties": {
    "iso:country":"DE",
    "sg:address":"Brie\u00dfelstr. 28",
    "sg:city":"Kirchhain",
    "sg:phone":"+49 6422/5757",
    "sg:postcode":"35274",
    "sg:province":"Hessen",
    "wof:name":"Sylvias Mieder & Moden",
    "wof:placetype":"venue"
},
  "geometry": {"coordinates":[8.91834,50.821281],"type":"Point"}
}