{
  "type": "Feature",
  "properties": {
    "iso:country":"DE",
    "sg:address":"Hickelweg 21",
    "sg:city":"Aachen",
    "sg:phone":"+49 241/57099",
    "sg:postcode":"52068",
    "sg:province":"Nordrhein-Westfalen",
    "wof:name":"Thouet Kg Inh. G. Und R. Knops",
    "wof:placetype":"venue"
},
  "geometry": {"coordinates":[6.129927,50.768753],"type":"Point"}
}