{
  "type": "Feature",
  "properties": {
    "iso:country":"DE",
    "sg:address":"Obere Str. 23",
    "sg:city":"Wulften",
    "sg:phone":"+49 5556/4328",
    "sg:postcode":"37199",
    "sg:province":"Niedersachsen",
    "wof:name":"Ewald Wemheuer",
    "wof:placetype":"venue"
},
  "geometry": {"coordinates":[10.176362,51.663429],"type":"Point"}
}