{
  "type": "Feature",
  "properties": {
    "iso:country":"DE",
    "sg:address":"Dorfstr. 38",
    "sg:city":"Belgershain",
    "sg:phone":"+49 34293/33491",
    "sg:postcode":"04683",
    "sg:province":"Sachsen",
    "wof:name":"Siegfried Severin",
    "wof:placetype":"venue"
},
  "geometry": {"coordinates":[12.5331707001,51.2569046021],"type":"Point"}
}