{
  "type": "Feature",
  "properties": {
    "iso:country":"DE",
    "sg:address":"Hostmannstr. 21",
    "sg:city":"Celle",
    "sg:phone":"+49 5141/24055",
    "sg:postcode":"29221",
    "sg:province":"Niedersachsen",
    "wof:name":"C. Cwielag",
    "wof:placetype":"venue"
},
  "geometry": {"coordinates":[10.089571,52.617931],"type":"Point"}
}