{
  "type": "Feature",
  "properties": {
    "iso:country":"DE",
    "sg:address":"Malzhagener Str. 22",
    "sg:city":"N\u00fcmbrecht",
    "sg:phone":"+49 2293/91090",
    "sg:postcode":"51588",
    "sg:province":"Nordrhein-Westfalen",
    "wof:name":"Draht Jung Gmbh",
    "wof:placetype":"venue"
},
  "geometry": {"coordinates":[7.5771121979,50.9017601013],"type":"Point"}
}