{
  "type": "Feature",
  "properties": {
    "iso:country":"DE",
    "sg:address":"Palmersdorfer Hof 2",
    "sg:city":"Br\u00fchl",
    "sg:phone":"+49 2232/48743",
    "sg:postcode":"50321",
    "sg:province":"Nordrhein-Westfalen",
    "wof:name":"R. Van Husen",
    "wof:placetype":"venue"
},
  "geometry": {"coordinates":[6.9228291512,50.8276443481],"type":"Point"}
}