{
  "type": "Feature",
  "properties": {
    "iso:country":"DE",
    "sg:address":"Guntersh\u00e4user Str. 4",
    "sg:city":"Baunatal",
    "sg:phone":"+49 561/949760",
    "sg:postcode":"34225",
    "sg:province":"Hessen",
    "wof:name":"Hotel Landgasthaus Bonn",
    "wof:placetype":"venue"
},
  "geometry": {"coordinates":[9.4525194168,51.2571716309],"type":"Point"}
}