{
  "type": "Feature",
  "properties": {
    "iso:country":"DE",
    "sg:address":"Regensburger Str. 51",
    "sg:city":"Nabburg",
    "sg:postcode":"92507",
    "sg:province":"Bayern",
    "wof:name":"Forstwirtschaftliche Vereinigung",
    "wof:placetype":"venue"
},
  "geometry": {"coordinates":[12.1728458405,49.44713974],"type":"Point"}
}