{
  "type": "Feature",
  "properties": {
    "iso:country":"DE",
    "sg:address":"Stadtplatz 11",
    "sg:city":"Vilsbiburg",
    "sg:phone":"+49 8741/4495",
    "sg:postcode":"84137",
    "sg:province":"Bayern",
    "wof:name":"Klaus Pfeiffer",
    "wof:placetype":"venue"
},
  "geometry": {"coordinates":[12.354590416,48.4493026733],"type":"Point"}
}