{
  "type": "Feature",
  "properties": {
    "iso:country":"DE",
    "sg:address":"Gartzenweg 29",
    "sg:city":"Monheim",
    "sg:phone":"+49 2173/51780",
    "sg:postcode":"40789",
    "sg:province":"Nordrhein-Westfalen",
    "wof:name":"Karlheinz Reiter",
    "wof:placetype":"venue"
},
  "geometry": {"coordinates":[6.8935689926,51.0921363831],"type":"Point"}
}