{
  "type": "Feature",
  "properties": {
    "iso:country":"DE",
    "sg:address":"Weberstr. 9",
    "sg:city":"Zeitz",
    "sg:postcode":"06712",
    "sg:province":"Sachsen-Anhalt",
    "wof:name":"Reiseb\u00fcro Elstertal",
    "wof:placetype":"venue"
},
  "geometry": {"coordinates":[12.1392879486,51.0497741699],"type":"Point"}
}