{
  "type": "Feature",
  "properties": {
    "iso:country":"DE",
    "sg:address":"Spreestr. 2",
    "sg:city":"Neu Zittau",
    "sg:phone":"+49 3362/8002",
    "sg:postcode":"15537",
    "sg:province":"Brandenburg",
    "wof:name":"Joachim Baldermann",
    "wof:placetype":"venue"
},
  "geometry": {"coordinates":[13.7663440704,52.3847808838],"type":"Point"}
}