{
  "type": "Feature",
  "properties": {
    "iso:country":"DE",
    "sg:address":"Stra\u00dfburger Str. 401",
    "sg:city":"Freudenstadt",
    "sg:phone":"+49 7442/2431",
    "sg:postcode":"72250",
    "sg:province":"Baden-W\u00fcrttemberg",
    "wof:name":"Hotel Alexanderschanze",
    "wof:placetype":"venue"
},
  "geometry": {"coordinates":[8.2907543182,48.4766731262],"type":"Point"}
}