{
  "type": "Feature",
  "properties": {
    "iso:country":"DE",
    "sg:address":"Ootmarsumer Weg 38",
    "sg:city":"Nordhorn",
    "sg:phone":"+49 5921/721135",
    "sg:postcode":"48527",
    "sg:province":"Niedersachsen",
    "wof:name":"Hannelore Schieferdecker Steuerberaterin",
    "wof:placetype":"venue"
},
  "geometry": {"coordinates":[7.0525269508,52.4294929504],"type":"Point"}
}