{
  "type": "Feature",
  "properties": {
    "iso:country":"DE",
    "sg:address":"Alte Bergsteige 103",
    "sg:city":"Mosbach",
    "sg:phone":"+49 6261/17043",
    "sg:postcode":"74821",
    "sg:province":"Baden-W\u00fcrttemberg",
    "wof:name":"Psm Warenvertrieb Gmbh",
    "wof:placetype":"venue"
},
  "geometry": {"coordinates":[9.1662454605,49.3495597839],"type":"Point"}
}