{
  "type": "Feature",
  "properties": {
    "iso:country":"DE",
    "sg:address":"Zur Sette 192",
    "sg:city":"Brockum",
    "sg:phone":"+49 5443/534",
    "sg:postcode":"49448",
    "sg:province":"Niedersachsen",
    "wof:name":"W. Dietzmann",
    "wof:placetype":"venue"
},
  "geometry": {"coordinates":[8.427324,52.470222],"type":"Point"}
}