{
  "type": "Feature",
  "properties": {
    "iso:country":"DE",
    "sg:address":"Bregstr. 5",
    "sg:city":"Furtwangen",
    "sg:phone":"+49 7723/7403",
    "sg:postcode":"78120",
    "sg:province":"Baden-W\u00fcrttemberg",
    "wof:name":"Siegfried B\u00fcrkle",
    "wof:placetype":"venue"
},
  "geometry": {"coordinates":[8.2021379471,48.0486793518],"type":"Point"}
}