{
  "type": "Feature",
  "properties": {
    "iso:country":"DE",
    "sg:address":"Ringstr. 8",
    "sg:city":"Seehof",
    "sg:phone":"+49 385/512460",
    "sg:postcode":"19069",
    "sg:province":"Mecklenburg-Vorpommern",
    "wof:name":"Renate Plagens",
    "wof:placetype":"venue"
},
  "geometry": {"coordinates":[11.434538,53.704357],"type":"Point"}
}