{
  "type": "Feature",
  "properties": {
    "iso:country":"DE",
    "sg:address":"Werner Str. 10",
    "sg:city":"Selm",
    "sg:phone":"+49 2592/1332",
    "sg:postcode":"59379",
    "sg:province":"Nordrhein-Westfalen",
    "wof:name":"A. Kortendieck",
    "wof:placetype":"venue"
},
  "geometry": {"coordinates":[7.474133,51.700047],"type":"Point"}
}