{
  "type": "Feature",
  "properties": {
    "iso:country":"DE",
    "sg:address":"Udalrichstr. 18",
    "sg:city":"Heppenheim",
    "sg:phone":"+49 6252/71234",
    "sg:postcode":"64646",
    "sg:province":"Hessen",
    "wof:name":"Prof. Harald Flicke",
    "wof:placetype":"venue"
},
  "geometry": {"coordinates":[8.6360578537,49.6331634521],"type":"Point"}
}