{
  "type": "Feature",
  "properties": {
    "iso:country":"DE",
    "sg:address":"Steinstr. 10",
    "sg:city":"Kaiserslautern",
    "sg:phone":"+49 631/69895",
    "sg:postcode":"67657",
    "sg:province":"Rheinland-Pfalz",
    "wof:name":"Monokel",
    "wof:placetype":"venue"
},
  "geometry": {"coordinates":[7.772163868,49.4461021423],"type":"Point"}
}