{
  "type": "Feature",
  "properties": {
    "iso:country":"DE",
    "sg:address":"M\u00fchlstr. 41",
    "sg:city":"Weilheim",
    "sg:phone":"+49 7023/6196",
    "sg:postcode":"73235",
    "sg:province":"Baden-W\u00fcrttemberg",
    "wof:name":"Gastst\u00e4tte Ernst Ulmer",
    "wof:placetype":"venue"
},
  "geometry": {"coordinates":[8.7798404694,48.0243988037],"type":"Point"}
}