{
  "type": "Feature",
  "properties": {
    "iso:country":"DE",
    "sg:address":"G\u00f6spe 2",
    "sg:city":"Schwanewede",
    "sg:phone":"+49 421/682532",
    "sg:postcode":"28790",
    "sg:province":"Niedersachsen",
    "wof:name":"Karl-hermann Laue",
    "wof:placetype":"venue"
},
  "geometry": {"coordinates":[8.548819,53.235909],"type":"Point"}
}