{
  "type": "Feature",
  "properties": {
    "iso:country":"DE",
    "sg:address":"Lagerhausstr. 3",
    "sg:city":"Lorsch",
    "sg:phone":"+49 6251/52879",
    "sg:postcode":"64653",
    "sg:province":"Hessen",
    "wof:name":"Freie Tankstelle",
    "wof:placetype":"venue"
},
  "geometry": {"coordinates":[8.5689907074,49.6601524353],"type":"Point"}
}