{
  "type": "Feature",
  "properties": {
    "iso:country":"DE",
    "sg:address":"Kamperstr. 12",
    "sg:city":"Velbert",
    "sg:phone":"+49 2052/82197",
    "sg:postcode":"42555",
    "sg:province":"Nordrhein-Westfalen",
    "wof:name":"G. Schaumburger",
    "wof:placetype":"venue"
},
  "geometry": {"coordinates":[7.120304,51.352398],"type":"Point"}
}