{
  "type": "Feature",
  "properties": {
    "iso:country":"DE",
    "sg:address":"Hauptstr. 15",
    "sg:city":"Schwalbach",
    "sg:phone":"+49 6196/84001",
    "sg:postcode":"65824",
    "sg:province":"Hessen",
    "wof:name":"Franz Burkart",
    "wof:placetype":"venue"
},
  "geometry": {"coordinates":[6.803438,49.296913],"type":"Point"}
}