{
  "type": "Feature",
  "properties": {
    "iso:country":"DE",
    "sg:address":"Schlenkenmoor 5",
    "sg:city":"Rastdorf",
    "sg:phone":"+49 5956/234",
    "sg:postcode":"26901",
    "sg:province":"Niedersachsen",
    "wof:name":"Heinrich Theilen",
    "wof:placetype":"venue"
},
  "geometry": {"coordinates":[7.726745,52.920963],"type":"Point"}
}