{
  "type": "Feature",
  "properties": {
    "iso:country":"DE",
    "sg:address":"Mengener Str. 25",
    "sg:city":"Me\u00dfkirch",
    "sg:phone":"+49 7575/2430",
    "sg:postcode":"88605",
    "sg:province":"Baden-W\u00fcrttemberg",
    "wof:name":"J. Martin",
    "wof:placetype":"venue"
},
  "geometry": {"coordinates":[9.117733,47.993679],"type":"Point"}
}