{
  "type": "Feature",
  "properties": {
    "iso:country":"DE",
    "sg:address":"Heidelberger Str. 14-18",
    "sg:city":"K\u00f6ln",
    "sg:phone":"+49 221/612211",
    "sg:postcode":"51065",
    "sg:province":"Nordrhein-Westfalen",
    "wof:name":"Athletik-fitness-center Wolfgang Braun",
    "wof:placetype":"venue"
},
  "geometry": {"coordinates":[7.003341198,50.950504303],"type":"Point"}
}