{
  "type": "Feature",
  "properties": {
    "iso:country":"DE",
    "sg:address":"Hartwig-Mildenberg-Str. 11-19",
    "sg:city":"B\u00fcnde",
    "sg:phone":"+49 5223/17620",
    "sg:postcode":"32257",
    "sg:province":"Nordrhein-Westfalen",
    "wof:name":"Fritz Vornb\u00e4umer Gmbh & Co. Kg",
    "wof:placetype":"venue"
},
  "geometry": {"coordinates":[8.587944,52.177757],"type":"Point"}
}