{
  "type": "Feature",
  "properties": {
    "iso:country":"DE",
    "sg:address":"Aichenbachstr. 98",
    "sg:city":"Schorndorf",
    "sg:phone":"+49 7181/63154",
    "sg:postcode":"73614",
    "sg:province":"Baden-W\u00fcrttemberg",
    "wof:name":"Gerhard Schiek S\u00fcd Stahlhandel",
    "wof:placetype":"venue"
},
  "geometry": {"coordinates":[9.534905,48.795788],"type":"Point"}
}