{
  "type": "Feature",
  "properties": {
    "iso:country":"DE",
    "sg:address":"Frohnklingerstr.32",
    "sg:city":"Gorxheimertal",
    "sg:postcode":"69517",
    "sg:province":"Hessen",
    "wof:name":"Willkommen Beim Ingenieurb\u00fcro Aucosoft",
    "wof:placetype":"venue"
},
  "geometry": {"coordinates":[8.748046,49.535042],"type":"Point"}
}