{
  "type": "Feature",
  "properties": {
    "iso:country":"DE",
    "sg:address":"Dreieichweg 5",
    "sg:city":"Gro\u00df-Umstadt",
    "sg:phone":"+49 6078/2412",
    "sg:postcode":"64823",
    "sg:province":"Hessen",
    "wof:name":"G. Fischer",
    "wof:placetype":"venue"
},
  "geometry": {"coordinates":[8.921437,49.888874],"type":"Point"}
}