{
  "type": "Feature",
  "properties": {
    "iso:country":"DE",
    "sg:address":"K\u00f6rnerstr. 89",
    "sg:city":"Gevelsberg",
    "sg:phone":"+49 2332/81111",
    "sg:postcode":"58285",
    "sg:province":"Nordrhein-Westfalen",
    "wof:name":"Erhard E. R\u00fccker",
    "wof:placetype":"venue"
},
  "geometry": {"coordinates":[7.337372,51.321789],"type":"Point"}
}