{
  "type": "Feature",
  "properties": {
    "iso:country":"DE",
    "sg:address":"Hauptstra\u00dfe 72a",
    "sg:city":"Emmendingen",
    "sg:phone":"+49 7641/8831",
    "sg:postcode":"79312",
    "sg:province":"Baden-W\u00fcrttemberg",
    "wof:name":"Autohaus-ortlieb",
    "wof:placetype":"venue"
},
  "geometry": {"coordinates":[7.8778729439,48.1032562256],"type":"Point"}
}