{
  "type": "Feature",
  "properties": {
    "iso:country":"DE",
    "sg:address":"Harenburger Weg 8",
    "sg:city":"Treia",
    "sg:postcode":"24896",
    "sg:province":"Schleswig-Holstein",
    "wof:name":"Stern-transporte Dienstleistung Und Logistik",
    "wof:placetype":"venue"
},
  "geometry": {"coordinates":[9.3245420456,54.5363273621],"type":"Point"}
}