{
  "type": "Feature",
  "properties": {
    "iso:country":"DE",
    "sg:address":"S\u00e4ulingweg 9",
    "sg:city":"Kissing",
    "sg:phone":"+49 8233/8260",
    "sg:postcode":"86438",
    "sg:province":"Bayern",
    "wof:name":"Bruno Remedios Architekt",
    "wof:placetype":"venue"
},
  "geometry": {"coordinates":[10.974832,48.300068],"type":"Point"}
}