{
  "type": "Feature",
  "properties": {
    "iso:country":"DE",
    "sg:address":"Mozartstr. 5",
    "sg:city":"Asbach-B\u00e4umenheim",
    "sg:phone":"+49 906/29121",
    "sg:postcode":"86663",
    "sg:province":"Bayern",
    "wof:name":"M. Akbulut",
    "wof:placetype":"venue"
},
  "geometry": {"coordinates":[10.8101577759,48.6856193542],"type":"Point"}
}