{
  "type": "Feature",
  "properties": {
    "iso:country":"DE",
    "sg:address":"Eppenhauser Str. 161",
    "sg:city":"Hagen",
    "sg:postcode":"58093",
    "sg:province":"Nordrhein-Westfalen",
    "wof:name":"B Und B Immobilienverwaltungs- Und Beratungs- Gmbh",
    "wof:placetype":"venue"
},
  "geometry": {"coordinates":[7.5100150108,51.3623352051],"type":"Point"}
}