{
  "type": "Feature",
  "properties": {
    "iso:country":"DE",
    "sg:address":"Robert-Koch-Str. 8",
    "sg:city":"Husum",
    "sg:phone":"+49 4841/96970",
    "sg:postcode":"25813",
    "sg:province":"Schleswig-Holstein",
    "wof:name":"Auto-vertrieb Kielsburg Bernd Bahr",
    "wof:placetype":"venue"
},
  "geometry": {"coordinates":[9.0804891586,54.4911193848],"type":"Point"}
}