{
  "type": "Feature",
  "properties": {
    "iso:country":"DE",
    "sg:address":"Richard-Kuhn-Str. 15",
    "sg:city":"Heidelberg",
    "sg:phone":"+49 6221/830482",
    "sg:postcode":"69123",
    "sg:province":"Baden-W\u00fcrttemberg",
    "wof:name":"Medical Vision Europe Gmbh",
    "wof:placetype":"venue"
},
  "geometry": {"coordinates":[8.6513128281,49.4159507751],"type":"Point"}
}