{
  "type": "Feature",
  "properties": {
    "iso:country":"DE",
    "sg:address":"Inselstr. 1",
    "sg:city":"Winterberg",
    "sg:phone":"+49 2983/908108",
    "sg:postcode":"59955",
    "sg:province":"Nordrhein-Westfalen",
    "wof:name":"Eiscafe Venezia",
    "wof:placetype":"venue"
},
  "geometry": {"coordinates":[8.46583,51.253052],"type":"Point"}
}