{
  "type": "Feature",
  "properties": {
    "iso:country":"DE",
    "sg:address":"Weidengasse 16",
    "sg:city":"B\u00fcrgstadt",
    "sg:phone":"+49 9371/2468",
    "sg:postcode":"63927",
    "sg:province":"Bayern",
    "wof:name":"Gemeinde-werke B\u00fcrgstadt",
    "wof:placetype":"venue"
},
  "geometry": {"coordinates":[9.266118,49.714462],"type":"Point"}
}