{
  "type": "Feature",
  "properties": {
    "iso:country":"DE",
    "sg:address":"Lindenstr. 2a",
    "sg:city":"Bad F\u00fcssing",
    "sg:phone":"+49 8531/21885",
    "sg:postcode":"94072",
    "sg:province":"Bayern",
    "wof:name":"Seiler",
    "wof:placetype":"venue"
},
  "geometry": {"coordinates":[13.3103666306,48.3518791199],"type":"Point"}
}