{
  "type": "Feature",
  "properties": {
    "iso:country":"DE",
    "sg:address":"Bahnhofstr. 13",
    "sg:city":"Bodenfelde",
    "sg:phone":"+49 5572/1490",
    "sg:postcode":"37194",
    "sg:province":"Hessen",
    "wof:name":"Werner Reiff Kfz-verwertungsuntern.",
    "wof:placetype":"venue"
},
  "geometry": {"coordinates":[9.5604200363,51.6380882263],"type":"Point"}
}