{
  "type": "Feature",
  "properties": {
    "iso:country":"DE",
    "sg:address":"Friedrich-Ebert-Str. 19",
    "sg:city":"W\u00f6rrstadt",
    "sg:phone":"+49 6732/2424",
    "sg:postcode":"55286",
    "sg:province":"Rheinland-Pfalz",
    "wof:name":"Kr\u00e4mer & Sohn Fachgesch\u00e4ft F\u00fcr Raumausstattung E. K.",
    "wof:placetype":"venue"
},
  "geometry": {"coordinates":[8.1152305603,49.838848114],"type":"Point"}
}