{
  "type": "Feature",
  "properties": {
    "iso:country":"DE",
    "sg:address":"Egmontstr. 4",
    "sg:city":"Bad Soden",
    "sg:phone":"+49 6196/24816",
    "sg:postcode":"65812",
    "sg:province":"Hessen",
    "wof:name":"Dr. Heinrich G\u00f6tz Rechtsanwalt",
    "wof:placetype":"venue"
},
  "geometry": {"coordinates":[8.4935522079,50.146194458],"type":"Point"}
}