{
  "type": "Feature",
  "properties": {
    "iso:country":"DE",
    "sg:address":"Bahnhofstr. 8",
    "sg:city":"F\u00fcrth",
    "sg:phone":"+49 6253/22518",
    "sg:postcode":"64658",
    "sg:province":"Hessen",
    "wof:name":"Ristorante Pizzeria Da Pino",
    "wof:placetype":"venue"
},
  "geometry": {"coordinates":[8.7790803909,49.6488189697],"type":"Point"}
}