{
  "type": "Feature",
  "properties": {
    "iso:country":"DE",
    "sg:address":"Hilderather Str. 39",
    "sg:city":"M\u00f6nchengladbach",
    "sg:phone":"+49 2161/584632",
    "sg:postcode":"41179",
    "sg:province":"Nordrhein-Westfalen",
    "wof:name":"Theodor Von Dahlen",
    "wof:placetype":"venue"
},
  "geometry": {"coordinates":[6.36024,51.143471],"type":"Point"}
}