{
  "type": "Feature",
  "properties": {
    "iso:country":"DE",
    "sg:address":"An der Bode 6 Morgenrot",
    "sg:city":"Quedlinburg",
    "sg:postcode":"06484",
    "sg:province":"Sachsen-Anhalt",
    "wof:name":"Vorharz Ferkel Verwaltungs Gmbh",
    "wof:placetype":"venue"
},
  "geometry": {"coordinates":[11.14324,51.794891],"type":"Point"}
}