{
  "type": "Feature",
  "properties": {
    "iso:country":"DE",
    "sg:address":"Schwinningstr. 75",
    "sg:city":"Aachen",
    "sg:phone":"+49 2408/1711",
    "sg:postcode":"52076",
    "sg:province":"Nordrhein-Westfalen",
    "wof:name":"Gemit Gmbh",
    "wof:placetype":"venue"
},
  "geometry": {"coordinates":[6.143873,50.724979],"type":"Point"}
}