{
  "type": "Feature",
  "properties": {
    "iso:country":"DE",
    "sg:address":"Max-T\u00fcrpe-Str. 36",
    "sg:city":"Chemnitz",
    "sg:postcode":"09122",
    "sg:province":"Sachsen",
    "wof:name":"W. Graichen",
    "wof:placetype":"venue"
},
  "geometry": {"coordinates":[12.880657196,50.7910995483],"type":"Point"}
}