{
  "type": "Feature",
  "properties": {
    "iso:country":"DE",
    "sg:address":"Folwiese 60",
    "sg:city":"K\u00f6ln",
    "sg:phone":"+49 221/688847",
    "sg:postcode":"51069",
    "sg:province":"Nordrhein-Westfalen",
    "wof:name":"Wolfgang Schmidtlein Architekt",
    "wof:placetype":"venue"
},
  "geometry": {"coordinates":[7.067181,50.96431],"type":"Point"}
}