{
  "type": "Feature",
  "properties": {
    "iso:country":"DE",
    "sg:address":"Langengrundstr. 25",
    "sg:city":"Schieder-Schwalenberg",
    "sg:phone":"+49 5233/7676",
    "sg:postcode":"32816",
    "sg:province":"Nordrhein-Westfalen",
    "wof:name":"H. Benning",
    "wof:placetype":"venue"
},
  "geometry": {"coordinates":[9.160231,51.881355],"type":"Point"}
}