{
  "type": "Feature",
  "properties": {
    "iso:country":"DE",
    "sg:address":"Saarpfalzstr. 2",
    "sg:city":"Waldmohr",
    "sg:phone":"+49 6373/9396",
    "sg:postcode":"66914",
    "sg:province":"Rheinland-Pfalz",
    "wof:name":"Hotel Waldmohrer Hof",
    "wof:placetype":"venue"
},
  "geometry": {"coordinates":[7.3301291466,49.3813781738],"type":"Point"}
}