{
  "type": "Feature",
  "properties": {
    "iso:country":"DE",
    "sg:address":"Willy Brandt Allee 3",
    "sg:city":"Hannover",
    "sg:phone":"+49 4951/180080",
    "sg:postcode":"30169",
    "sg:province":"Niedersachsen",
    "wof:name":"Mercure Hotel Hannover",
    "wof:placetype":"venue"
},
  "geometry": {"coordinates":[9.740163,52.366821],"type":"Point"}
}