{
  "type": "Feature",
  "properties": {
    "iso:country":"DE",
    "sg:address":"Ardeystr. 325 a",
    "sg:city":"Witten",
    "sg:phone":"+49 2302/80792",
    "sg:postcode":"58453",
    "sg:province":"Nordrhein-Westfalen",
    "wof:name":"G\u00fcnter Maritschnigg",
    "wof:placetype":"venue"
},
  "geometry": {"coordinates":[7.4095249176,51.4329566956],"type":"Point"}
}