{
  "type": "Feature",
  "properties": {
    "iso:country":"DE",
    "sg:address":"Roteb\u00fchlstra\u00dfe 87",
    "sg:city":"Stuttgart",
    "sg:postcode":"70178",
    "sg:province":"Baden-W\u00fcrttemberg",
    "wof:name":"Stuttgart - Fai Sushi Online Bestellen",
    "wof:placetype":"venue"
},
  "geometry": {"coordinates":[9.164061,48.771996],"type":"Point"}
}