{
  "type": "Feature",
  "properties": {
    "iso:country":"DE",
    "sg:address":"An der Ziegelei 2",
    "sg:city":"Wipperf\u00fcrth",
    "sg:phone":"+49 2267/5009",
    "sg:postcode":"51688",
    "sg:province":"Nordrhein-Westfalen",
    "wof:name":"Hubert Blechmann Gmbh & Co. Kg",
    "wof:placetype":"venue"
},
  "geometry": {"coordinates":[7.3898611069,51.1202468872],"type":"Point"}
}