{
  "type": "Feature",
  "properties": {
    "iso:country":"DE",
    "sg:address":"Klein-Brodersby",
    "sg:city":"Brodersby",
    "sg:phone":"+49 4622/1704",
    "sg:postcode":"24864",
    "sg:province":"Schleswig-Holstein",
    "wof:name":"Bock Und Janik Gmbh",
    "wof:placetype":"venue"
},
  "geometry": {"coordinates":[9.70613,54.536121],"type":"Point"}
}