{
  "type": "Feature",
  "properties": {
    "iso:country":"DE",
    "sg:address":"Kirchstr. 6",
    "sg:city":"Dettingen",
    "sg:phone":"+49 7021/52992",
    "sg:postcode":"73265",
    "sg:province":"Baden-W\u00fcrttemberg",
    "wof:name":"Fleckviehzuchtverein Kirchheim Unter Teck",
    "wof:placetype":"venue"
},
  "geometry": {"coordinates":[9.4520835876,48.617149353],"type":"Point"}
}