{
  "type": "Feature",
  "properties": {
    "iso:country":"DE",
    "sg:address":"Balinger Str. 19",
    "sg:city":"Rosenfeld",
    "sg:phone":"+49 7428/434",
    "sg:postcode":"72348",
    "sg:province":"Baden-W\u00fcrttemberg",
    "wof:name":"Berta Keller Glas- Und Porzellanwaren",
    "wof:placetype":"venue"
},
  "geometry": {"coordinates":[8.7254037857,48.2866477966],"type":"Point"}
}