{
  "type": "Feature",
  "properties": {
    "iso:country":"DE",
    "sg:address":"Silberbergstr. 30",
    "sg:city":"Hof",
    "sg:phone":"+49 9281/66161",
    "sg:postcode":"95030",
    "sg:province":"Bayern",
    "wof:name":"Edith Scheuerlein",
    "wof:placetype":"venue"
},
  "geometry": {"coordinates":[11.8913431168,50.3299331665],"type":"Point"}
}