{
  "type": "Feature",
  "properties": {
    "iso:country":"DE",
    "sg:address":"Neusperger Hof",
    "sg:city":"Rohrbach",
    "sg:phone":"+49 6349/1645",
    "sg:postcode":"76865",
    "sg:province":"Rheinland-Pfalz",
    "wof:name":"Hans Gradolph",
    "wof:placetype":"venue"
},
  "geometry": {"coordinates":[8.1273784637,49.1406860352],"type":"Point"}
}