{
  "type": "Feature",
  "properties": {
    "iso:country":"DE",
    "sg:address":"Uikern 19",
    "sg:city":"Nieheim",
    "sg:phone":"+49 5274/600",
    "sg:postcode":"33039",
    "sg:province":"Nordrhein-Westfalen",
    "wof:name":"Josef Vogedes",
    "wof:placetype":"venue"
},
  "geometry": {"coordinates":[9.0534381866,51.8146629333],"type":"Point"}
}