{
  "type": "Feature",
  "properties": {
    "iso:country":"DE",
    "sg:address":"Logenstr. 20",
    "sg:city":"L\u00fcbben",
    "sg:phone":"+49 3546/27360",
    "sg:postcode":"15907",
    "sg:province":"Brandenburg",
    "wof:name":"Hartmut Eggers Steuerberater",
    "wof:placetype":"venue"
},
  "geometry": {"coordinates":[13.8879528046,51.9375915527],"type":"Point"}
}