{
  "type": "Feature",
  "properties": {
    "iso:country":"DE",
    "sg:address":"Im Camisch 49",
    "sg:city":"Kahla",
    "sg:phone":"+49 36424/8110",
    "sg:postcode":"07768",
    "sg:province":"Th\u00fcringen",
    "wof:name":"M & K Dental Gmbh",
    "wof:placetype":"venue"
},
  "geometry": {"coordinates":[11.5746622086,50.814994812],"type":"Point"}
}