{
  "type": "Feature",
  "properties": {
    "iso:country":"DE",
    "sg:address":"Blumenstr. 19",
    "sg:city":"Rheinhausen",
    "sg:phone":"+49 7643/1655",
    "sg:postcode":"79365",
    "sg:province":"Baden-W\u00fcrttemberg",
    "wof:name":"Theo Maurer Versicherungen",
    "wof:placetype":"venue"
},
  "geometry": {"coordinates":[7.7148928642,48.2375602722],"type":"Point"}
}