{
  "type": "Feature",
  "properties": {
    "iso:country":"DE",
    "sg:address":"Hochh\u00e4user Str. 12",
    "sg:city":"Obrigheim",
    "sg:phone":"+49 6261/7623",
    "sg:postcode":"74847",
    "sg:province":"Baden-W\u00fcrttemberg",
    "wof:name":"A. Kress",
    "wof:placetype":"venue"
},
  "geometry": {"coordinates":[9.096064,49.350903],"type":"Point"}
}