{
  "type": "Feature",
  "properties": {
    "iso:country":"DE",
    "sg:address":"Luchauer Str. 1",
    "sg:city":"Glash\u00fctte",
    "sg:postcode":"01768",
    "sg:province":"Sachsen",
    "wof:name":"Bestattungshaus In Glash\u00fctte Gmbh",
    "wof:placetype":"venue"
},
  "geometry": {"coordinates":[13.77115,50.852249],"type":"Point"}
}