{
  "type": "Feature",
  "properties": {
    "iso:country":"DE",
    "sg:address":"Obernburger Str. 125",
    "sg:city":"Stockstadt",
    "sg:phone":"+49 6027/20080",
    "sg:postcode":"63811",
    "sg:province":"Bayern",
    "wof:name":"Gunold & Stickma Rechnology Gmbh",
    "wof:placetype":"venue"
},
  "geometry": {"coordinates":[9.0748577118,49.9660758972],"type":"Point"}
}