{
  "type": "Feature",
  "properties": {
    "iso:country":"DE",
    "sg:address":"Im Reisiek 6",
    "sg:city":"Bad Essen",
    "sg:phone":"+49 5472/2428",
    "sg:postcode":"49152",
    "sg:province":"Niedersachsen",
    "wof:name":"Heinrich Ossenbrink",
    "wof:placetype":"venue"
},
  "geometry": {"coordinates":[8.305906,52.299755],"type":"Point"}
}