{
  "type": "Feature",
  "properties": {
    "iso:country":"DE",
    "sg:address":"Saatwinkler Damm 50",
    "sg:city":"Berlin",
    "sg:phone":"+49 30/3441298",
    "sg:postcode":"13627",
    "sg:province":"Berlin",
    "wof:name":"G\u00fcnter B\u00f6ske",
    "wof:placetype":"venue"
},
  "geometry": {"coordinates":[13.315771,52.547276],"type":"Point"}
}