{
  "type": "Feature",
  "properties": {
    "iso:country":"DE",
    "sg:address":"Kastanienallee 20",
    "sg:city":"M\u00fcnster",
    "sg:phone":"+49 6071/31354",
    "sg:postcode":"64839",
    "sg:province":"Hessen",
    "wof:name":"Hans Werner Baumg\u00e4rtner",
    "wof:placetype":"venue"
},
  "geometry": {"coordinates":[8.8661289215,49.9200668335],"type":"Point"}
}