{
  "type": "Feature",
  "properties": {
    "iso:country":"DE",
    "sg:address":"Breite Str. 5",
    "sg:city":"Niederstotzingen",
    "sg:phone":"+49 7325/8721",
    "sg:postcode":"89168",
    "sg:province":"Baden-W\u00fcrttemberg",
    "wof:name":"W. Junginger",
    "wof:placetype":"venue"
},
  "geometry": {"coordinates":[10.2360811234,48.5360221863],"type":"Point"}
}