{
  "type": "Feature",
  "properties": {
    "iso:country":"DE",
    "sg:address":"Marktplatz 1",
    "sg:city":"Obersulm",
    "sg:phone":"+49 7134/98850",
    "sg:postcode":"74182",
    "sg:province":"Baden-W\u00fcrttemberg",
    "wof:name":"Renaud & Partner Gmbh",
    "wof:placetype":"venue"
},
  "geometry": {"coordinates":[9.3830032349,49.1363983154],"type":"Point"}
}