{
  "type": "Feature",
  "properties": {
    "iso:country":"DE",
    "sg:address":"Oberrheinplatz 5",
    "sg:city":"Rheinfelden",
    "sg:phone":"+49 7623/1061",
    "sg:postcode":"79618",
    "sg:province":"Baden-W\u00fcrttemberg",
    "wof:name":"Eichler Immobilienmakler",
    "wof:placetype":"venue"
},
  "geometry": {"coordinates":[7.7852602005,47.55909729],"type":"Point"}
}