{
  "type": "Feature",
  "properties": {
    "iso:country":"DE",
    "sg:address":"H\u00f6lderlinstr. 11",
    "sg:city":"Wildberg",
    "sg:phone":"+49 7054/92650",
    "sg:postcode":"72218",
    "sg:province":"Baden-W\u00fcrttemberg",
    "wof:name":"Reiseb\u00fcro Tour Mit Schanz Gmbh",
    "wof:placetype":"venue"
},
  "geometry": {"coordinates":[8.730591774,48.6249427795],"type":"Point"}
}