{
  "type": "Feature",
  "properties": {
    "iso:country":"DE",
    "sg:address":"Schwanweg 1",
    "sg:city":"Heroldsberg",
    "sg:phone":"+49 911/5670",
    "sg:postcode":"90562",
    "sg:province":"Bayern",
    "wof:name":"Schwanh\u00e4u\u00dfer Industrie Holding Verwaltungs Gmbh",
    "wof:placetype":"venue"
},
  "geometry": {"coordinates":[11.1502780914,49.5450057983],"type":"Point"}
}