{
  "type": "Feature",
  "properties": {
    "iso:country":"DE",
    "sg:address":"W\u00f6hlerstra\u00dfe 10",
    "sg:city":"Frankfurt am Main",
    "sg:phone":"+49 69/717120",
    "sg:postcode":"60323",
    "sg:province":"Hessen",
    "wof:name":"Consors Capital Bank Ag",
    "wof:placetype":"venue"
},
  "geometry": {"coordinates":[8.667108,50.118061],"type":"Point"}
}