{
  "type": "Feature",
  "properties": {
    "iso:country":"DE",
    "sg:address":"Hintere Str. 10",
    "sg:city":"Leonberg",
    "sg:phone":"+49 7152/28520",
    "sg:postcode":"71229",
    "sg:province":"Baden-W\u00fcrttemberg",
    "wof:name":"Olympos",
    "wof:placetype":"venue"
},
  "geometry": {"coordinates":[9.0159139633,48.8013687134],"type":"Point"}
}