{
  "type": "Feature",
  "properties": {
    "iso:country":"DE",
    "sg:address":"Rheintalstr. 6",
    "sg:city":"Neuenburg",
    "sg:phone":"+49 7635/82030",
    "sg:postcode":"79395",
    "sg:province":"Baden-W\u00fcrttemberg",
    "wof:name":"Schlo\u00dfbrunnen Sattler Kg",
    "wof:placetype":"venue"
},
  "geometry": {"coordinates":[7.5530362129,47.7664642334],"type":"Point"}
}