{
  "type": "Feature",
  "properties": {
    "iso:country":"DE",
    "sg:address":"Mitteltor 7",
    "sg:city":"Dirmstein",
    "sg:postcode":"67246",
    "sg:province":"Rheinland-Pfalz",
    "wof:name":"Erich Koppenh\u00f6fer Jun.",
    "wof:placetype":"venue"
},
  "geometry": {"coordinates":[8.248008,49.563488],"type":"Point"}
}