{
  "type": "Feature",
  "properties": {
    "iso:country":"DE",
    "sg:address":"Friedrich-Ebert-Str. 150",
    "sg:city":"Krefeld",
    "sg:phone":"+49 2151/593395",
    "sg:postcode":"47800",
    "sg:province":"Nordrhein-Westfalen",
    "wof:name":"Paul Bernutat Ingenieur",
    "wof:placetype":"venue"
},
  "geometry": {"coordinates":[6.5917310715,51.3444404602],"type":"Point"}
}