{
  "type": "Feature",
  "properties": {
    "iso:country":"DE",
    "sg:address":"Auf den H\u00e4fen 7",
    "sg:city":"Bremen",
    "sg:phone":"+49 421/790090",
    "sg:postcode":"28203",
    "sg:province":"Bremen",
    "wof:name":"Reiseb\u00fcro Auf Den H\u00e4fen Flugtouristik Gmbh",
    "wof:placetype":"venue"
},
  "geometry": {"coordinates":[8.8209867477,53.0756378174],"type":"Point"}
}