{
  "type": "Feature",
  "properties": {
    "iso:country":"DE",
    "sg:address":"Im Lettenacker 1/3",
    "sg:city":"Efringen-Kirchen",
    "sg:phone":"+49 7628/941009",
    "sg:postcode":"79588",
    "sg:province":"Baden-W\u00fcrttemberg",
    "wof:name":"H. Darius",
    "wof:placetype":"venue"
},
  "geometry": {"coordinates":[7.567864,47.65686],"type":"Point"}
}