{
  "type": "Feature",
  "properties": {
    "iso:country":"DE",
    "sg:address":"Neumarkt 5",
    "sg:city":"Wuppertal",
    "sg:phone":"+49 202/442555",
    "sg:postcode":"42103",
    "sg:province":"Nordrhein-Westfalen",
    "wof:name":"Cotton Live Textilvertrieb Gmbh",
    "wof:placetype":"venue"
},
  "geometry": {"coordinates":[7.146248,51.258652],"type":"Point"}
}