{
  "type": "Feature",
  "properties": {
    "iso:country":"DE",
    "sg:address":"Dechbettener Str. 9",
    "sg:city":"Regensburg",
    "sg:phone":"+49 941/270212",
    "sg:postcode":"93049",
    "sg:province":"Bayern",
    "wof:name":"\u00d6kon Gesellschaft F\u00fcr Landschafts\u00f6kologie Gew\u00e4sser-",
    "wof:placetype":"venue"
},
  "geometry": {"coordinates":[12.0831184387,49.0168380737],"type":"Point"}
}