{
  "type": "Feature",
  "properties": {
    "iso:country":"DE",
    "sg:address":"Hubertusstr. 54",
    "sg:city":"Nalbach",
    "sg:phone":"+49 6838/84102",
    "sg:postcode":"66809",
    "sg:province":"Saarland",
    "wof:name":"Jeans Und Mode",
    "wof:placetype":"venue"
},
  "geometry": {"coordinates":[6.784506,49.378803],"type":"Point"}
}