{
  "type": "Feature",
  "properties": {
    "iso:country":"DE",
    "sg:address":"Liesbornerstr. 10",
    "sg:city":"Langenberg",
    "sg:phone":"+49 2944/1216",
    "sg:postcode":"33449",
    "sg:province":"Nordrhein-Westfalen",
    "wof:name":"Volksbank Benteler Eg",
    "wof:placetype":"venue"
},
  "geometry": {"coordinates":[8.319951,51.743965],"type":"Point"}
}