{
  "type": "Feature",
  "properties": {
    "iso:country":"DE",
    "sg:address":"Auf'm Tetelberg 7",
    "sg:city":"D\u00fcsseldorf",
    "sg:phone":"+49 211/308236",
    "sg:postcode":"40221",
    "sg:province":"Nordrhein-Westfalen",
    "wof:name":"Messegesellschaft Handwerk Nrw Gmbh",
    "wof:placetype":"venue"
},
  "geometry": {"coordinates":[6.7595739365,51.2053909302],"type":"Point"}
}