{
  "type": "Feature",
  "properties": {
    "iso:country":"DE",
    "sg:address":"Bahrendorfer Str. 19-20",
    "sg:city":"Magdeburg",
    "sg:postcode":"39112",
    "sg:province":"Sachsen-Anhalt",
    "wof:name":"Medi Team Consulting Gmbh",
    "wof:placetype":"venue"
},
  "geometry": {"coordinates":[11.59443,52.110641],"type":"Point"}
}