{
  "type": "Feature",
  "properties": {
    "iso:country":"DE",
    "sg:address":"Karlstr. 7",
    "sg:city":"M\u00fcnchberg",
    "sg:postcode":"95213",
    "sg:province":"Bayern",
    "wof:name":"Hs-beteiligungs Gmbh",
    "wof:placetype":"venue"
},
  "geometry": {"coordinates":[11.791068,50.190823],"type":"Point"}
}