{
  "type": "Feature",
  "properties": {
    "iso:country":"DE",
    "sg:address":"Berger Str. 157",
    "sg:city":"Frankfurt",
    "sg:postcode":"60385",
    "sg:province":"Hessen",
    "wof:name":"Harald Rudorf Gmbh & Co. Sandwich Kg",
    "wof:placetype":"venue"
},
  "geometry": {"coordinates":[8.7111501694,50.1304931641],"type":"Point"}
}