{
  "type": "Feature",
  "properties": {
    "iso:country":"DE",
    "sg:address":"Briloner Landstr. 27",
    "sg:city":"Korbach",
    "sg:phone":"+49 5631/95690",
    "sg:postcode":"34497",
    "sg:province":"Hessen",
    "wof:name":"Karl-adolf Suck Architekt",
    "wof:placetype":"venue"
},
  "geometry": {"coordinates":[8.866118,51.277435],"type":"Point"}
}