{
  "type": "Feature",
  "properties": {
    "iso:country":"DE",
    "sg:address":"Schlo\u00dfstr. 4",
    "sg:city":"Lohmar",
    "sg:phone":"+49 2206/83462",
    "sg:postcode":"53797",
    "sg:province":"Nordrhein-Westfalen",
    "wof:name":"Volker Bochmann Dipl.-ingenieur Agr.",
    "wof:placetype":"venue"
},
  "geometry": {"coordinates":[7.2551898956,50.8940925598],"type":"Point"}
}