{
  "type": "Feature",
  "properties": {
    "iso:country":"DE",
    "sg:address":"Heideweg 5",
    "sg:city":"Amberg",
    "sg:phone":"+49 9621/72454",
    "sg:postcode":"92224",
    "sg:province":"Bayern",
    "wof:name":"P. Heindl Propangas Und Heiz\u00f6l",
    "wof:placetype":"venue"
},
  "geometry": {"coordinates":[11.836411,49.429279],"type":"Point"}
}