{
  "type": "Feature",
  "properties": {
    "iso:country":"DE",
    "sg:address":"Froschaustr. 6",
    "sg:city":"Spechbach",
    "sg:phone":"+49 6226/40109",
    "sg:postcode":"74937",
    "sg:province":"Baden-W\u00fcrttemberg",
    "wof:name":"Josef Repper",
    "wof:placetype":"venue"
},
  "geometry": {"coordinates":[8.882723,49.343281],"type":"Point"}
}