{
  "type": "Feature",
  "properties": {
    "iso:country":"DE",
    "sg:address":"Grelckstr. 19a",
    "sg:city":"Hamburg",
    "sg:phone":"+49 40/6403626",
    "sg:postcode":"22529",
    "sg:province":"Hamburg",
    "wof:name":"P. Resch & Sohn Gmbh",
    "wof:placetype":"venue"
},
  "geometry": {"coordinates":[9.95556,53.601006],"type":"Point"}
}