{
  "type": "Feature",
  "properties": {
    "iso:country":"DE",
    "sg:address":"Mayenbergstr. 18",
    "sg:city":"Ludwigshafen",
    "sg:phone":"+49 621/661534",
    "sg:postcode":"67069",
    "sg:province":"Rheinland-Pfalz",
    "wof:name":"O. A. Fischer",
    "wof:placetype":"venue"
},
  "geometry": {"coordinates":[8.391978,49.527786],"type":"Point"}
}