{
  "type": "Feature",
  "properties": {
    "iso:country":"DE",
    "sg:address":"Hohe Str. 13",
    "sg:city":"Bremen",
    "sg:phone":"+49 421/342885",
    "sg:postcode":"28195",
    "sg:province":"Bremen",
    "wof:name":"Barbara Speckamp & Partner Finanzberater",
    "wof:placetype":"venue"
},
  "geometry": {"coordinates":[8.8079872131,53.0732917786],"type":"Point"}
}