{
  "type": "Feature",
  "properties": {
    "iso:country":"DE",
    "sg:address":"Hoyerswerdaer Str. 6-8",
    "sg:city":"Schleife",
    "sg:phone":"+49 35773/76533",
    "sg:postcode":"02959",
    "sg:province":"Sachsen",
    "wof:name":"Plf-projekt-gmbh",
    "wof:placetype":"venue"
},
  "geometry": {"coordinates":[14.534958,51.545078],"type":"Point"}
}