{
  "type": "Feature",
  "properties": {
    "iso:country":"DE",
    "sg:address":"Westerwaldstr. 9",
    "sg:city":"Menden",
    "sg:postcode":"58706",
    "sg:province":"Nordrhein-Westfalen",
    "wof:name":"Wasser Umwelt Verkehr Gmbh",
    "wof:placetype":"venue"
},
  "geometry": {"coordinates":[7.778949,51.433823],"type":"Point"}
}