{
  "type": "Feature",
  "properties": {
    "iso:country":"DE",
    "sg:address":"Am Sparrenberg 12",
    "sg:city":"Bielefeld",
    "sg:phone":"+49 521/69266",
    "sg:postcode":"33602",
    "sg:province":"Nordrhein-Westfalen",
    "wof:name":"Bernfried Wolff Rechtsanwalt",
    "wof:placetype":"venue"
},
  "geometry": {"coordinates":[8.5272083282,52.0160942078],"type":"Point"}
}