{
  "type": "Feature",
  "properties": {
    "iso:country":"DE",
    "sg:address":"Landsknechtweg 44",
    "sg:city":"Mannheim",
    "sg:phone":"+49 621/444252",
    "sg:postcode":"68163",
    "sg:province":"Baden-W\u00fcrttemberg",
    "wof:name":"Berthold Fischer",
    "wof:placetype":"venue"
},
  "geometry": {"coordinates":[8.502538681,49.465461731],"type":"Point"}
}