{
  "type": "Feature",
  "properties": {
    "iso:country":"DE",
    "sg:address":"Hofstr. 19",
    "sg:city":"F\u00f6hren",
    "sg:postcode":"54343",
    "sg:province":"Rheinland-Pfalz",
    "wof:name":"F\u00f6 Bau Vertriebsgesellschaft Mbh & Co. Kg",
    "wof:placetype":"venue"
},
  "geometry": {"coordinates":[6.767118,49.861267],"type":"Point"}
}