{
  "type": "Feature",
  "properties": {
    "iso:country":"DE",
    "sg:address":"St.-P\u00f6ltener-Str. 43",
    "sg:city":"Heidenheim",
    "sg:phone":"+49 7321/370",
    "sg:postcode":"89522",
    "sg:province":"Baden-W\u00fcrttemberg",
    "wof:name":"J. M. Voith Europa Auslandsbeteiligungen Gmbh",
    "wof:placetype":"venue"
},
  "geometry": {"coordinates":[10.15687,48.67411],"type":"Point"}
}