{
  "type": "Feature",
  "properties": {
    "iso:country":"DE",
    "sg:address":"Pestalozzistr. 14",
    "sg:city":"Bad Zwischenahn",
    "sg:phone":"+49 4403/2736",
    "sg:postcode":"26160",
    "sg:province":"Niedersachsen",
    "wof:name":"H. Und I. Onnen",
    "wof:placetype":"venue"
},
  "geometry": {"coordinates":[7.9994997978,53.1771621704],"type":"Point"}
}