{
  "type": "Feature",
  "properties": {
    "iso:country":"DE",
    "sg:address":"Ftdjei 99",
    "sg:city":"Huifb",
    "sg:postcode":"12345",
    "wof:name":"Homepage Des Ehc Thalwil",
    "wof:placetype":"venue"
},
  "geometry": {"coordinates":[-73.94101000000001,42.81226],"type":"Point"}
}