{
  "type": "Feature",
  "properties": {
    "iso:country":"DE",
    "sg:address":"Kreuzlingerforststr. 5",
    "sg:city":"Gauting",
    "sg:phone":"+49 89/8501498",
    "sg:postcode":"82131",
    "sg:province":"Bayern",
    "wof:name":"H. Schellinger Kunstmaler",
    "wof:placetype":"venue"
},
  "geometry": {"coordinates":[11.378789,48.077835],"type":"Point"}
}