{
  "type": "Feature",
  "properties": {
    "iso:country":"DE",
    "sg:address":"Villinger Str. 20",
    "sg:city":"Dauchingen",
    "sg:phone":"+49 7720/67128",
    "sg:postcode":"78083",
    "sg:province":"Baden-W\u00fcrttemberg",
    "wof:name":"U. Fleig",
    "wof:placetype":"venue"
},
  "geometry": {"coordinates":[8.546944,48.090195],"type":"Point"}
}