{
  "type": "Feature",
  "properties": {
    "iso:country":"DE",
    "sg:address":"Leninplatz 4",
    "sg:city":"Gotha",
    "sg:phone":"+49 3621/52502",
    "sg:postcode":"99867",
    "sg:province":"Th\u00fcringen",
    "wof:name":"Deutsche Bank Ag Filiale Gotha",
    "wof:placetype":"venue"
},
  "geometry": {"coordinates":[10.699534,50.940346],"type":"Point"}
}