{
  "type": "Feature",
  "properties": {
    "iso:country":"DE",
    "sg:address":"Dorfstr. 39",
    "sg:city":"Aldenhoven",
    "sg:phone":"+49 2464/7228",
    "sg:postcode":"52457",
    "sg:province":"Nordrhein-Westfalen",
    "wof:name":"Jakob Leipertz",
    "wof:placetype":"venue"
},
  "geometry": {"coordinates":[6.247325,50.928253],"type":"Point"}
}