{
  "type": "Feature",
  "properties": {
    "iso:country":"DE",
    "sg:address":"Freiheitstr. 37",
    "sg:city":"\u00dcbach-Palenberg",
    "sg:phone":"+49 2451/43703",
    "sg:postcode":"52531",
    "sg:province":"Nordrhein-Westfalen",
    "wof:name":"Hubert Meertens",
    "wof:placetype":"venue"
},
  "geometry": {"coordinates":[6.1253881454,50.9170417786],"type":"Point"}
}