{
  "type": "Feature",
  "properties": {
    "iso:country":"DE",
    "sg:address":"Essener Str. 4",
    "sg:city":"St. Wendel",
    "sg:postcode":"66606",
    "sg:province":"Saarland",
    "wof:name":"Foto - Brunninger Hugo A. Brunninger",
    "wof:placetype":"venue"
},
  "geometry": {"coordinates":[7.144704,49.464924],"type":"Point"}
}