{
  "type": "Feature",
  "properties": {
    "iso:country":"DE",
    "sg:address":"Alter Weg 44",
    "sg:city":"Rodgau",
    "sg:phone":"+49 6106/3306",
    "sg:postcode":"63110",
    "sg:province":"Hessen",
    "wof:name":"Willibald Bayer",
    "wof:placetype":"venue"
},
  "geometry": {"coordinates":[8.870527,50.026623],"type":"Point"}
}