{
  "type": "Feature",
  "properties": {
    "iso:country":"DE",
    "sg:address":"stiftstra\u00dfe 5",
    "sg:city":"oberhausen",
    "sg:phone":"+49 208",
    "sg:postcode":"46047",
    "sg:province":"Nordrhein-Westfalen",
    "wof:name":"Kontaktmarkt Rhurgebiet Und Oberhausen",
    "wof:placetype":"venue"
},
  "geometry": {"coordinates":[6.874362,51.470364],"type":"Point"}
}