{
  "type": "Feature",
  "properties": {
    "iso:country":"DE",
    "sg:address":"Herderstrasse 27",
    "sg:city":"Hilden",
    "sg:phone":"+49 2103/41957",
    "sg:postcode":"40721",
    "sg:province":"Nordrhein-Westfalen",
    "wof:name":"Prodev",
    "wof:placetype":"venue"
},
  "geometry": {"coordinates":[6.9216427803,51.1767311096],"type":"Point"}
}