{
  "type": "Feature",
  "properties": {
    "iso:country":"DE",
    "sg:address":"Isolde-Kurz-Weg 12",
    "sg:city":"Korntal-M\u00fcnchingen",
    "sg:phone":"+49 711/832546",
    "sg:postcode":"70825",
    "sg:province":"Baden-W\u00fcrttemberg",
    "wof:name":"Herbert Knodel",
    "wof:placetype":"venue"
},
  "geometry": {"coordinates":[9.111192,48.830147],"type":"Point"}
}