{
  "type": "Feature",
  "properties": {
    "iso:country":"DE",
    "sg:address":"Siegfriedstr. 80",
    "sg:city":"Berlin",
    "sg:phone":"+49 30/4428270",
    "sg:postcode":"10365",
    "sg:province":"Berlin",
    "wof:name":"Pansold Poolparadies E. K.",
    "wof:placetype":"venue"
},
  "geometry": {"coordinates":[13.501534462,52.5325279236],"type":"Point"}
}