{
  "type": "Feature",
  "properties": {
    "iso:country":"DE",
    "sg:address":"Gr\u00fcnauer Str. 57",
    "sg:city":"Berlin",
    "sg:postcode":"12557",
    "sg:province":"Berlin",
    "wof:name":"Gr\u00fcnauer Str. 57 Spielhallen Gmbh",
    "wof:placetype":"venue"
},
  "geometry": {"coordinates":[13.5709609985,52.4401664734],"type":"Point"}
}