{
  "type": "Feature",
  "properties": {
    "iso:country":"DE",
    "sg:address":"Apenkebreite 8",
    "sg:city":"Osterode",
    "sg:phone":"+49 5522/3436",
    "sg:postcode":"37520",
    "sg:province":"Niedersachsen",
    "wof:name":"Hans-herbert Bleicher Steuerberater",
    "wof:placetype":"venue"
},
  "geometry": {"coordinates":[10.2622661591,51.7241859436],"type":"Point"}
}