{
  "type": "Feature",
  "properties": {
    "iso:country":"DE",
    "sg:address":"Industriestr. 38",
    "sg:city":"Brakel",
    "sg:phone":"+49 5272/8708",
    "sg:postcode":"33034",
    "sg:province":"Nordrhein-Westfalen",
    "wof:name":"Pader Multitherm Glas Beteiligungs-gmbh",
    "wof:placetype":"venue"
},
  "geometry": {"coordinates":[9.171862,51.707485],"type":"Point"}
}