{
  "type": "Feature",
  "properties": {
    "iso:country":"DE",
    "sg:address":"Schwabacher Str. 382",
    "sg:city":"F\u00fcrth",
    "sg:phone":"+49 911/71688",
    "sg:postcode":"90763",
    "sg:province":"Bayern",
    "wof:name":"Wilhelm Graf",
    "wof:placetype":"venue"
},
  "geometry": {"coordinates":[10.9908123016,49.443901062],"type":"Point"}
}