{
  "type": "Feature",
  "properties": {
    "iso:country":"DE",
    "sg:address":"Sch\u00f6nblicker Str. 26",
    "sg:city":"Berlin",
    "sg:phone":"+49 30/6480765",
    "sg:postcode":"12589",
    "sg:province":"Berlin",
    "wof:name":"Dr. Gisela Wibeau Tier\u00e4rztin",
    "wof:placetype":"venue"
},
  "geometry": {"coordinates":[13.7180109024,52.4371833801],"type":"Point"}
}