{
  "type": "Feature",
  "properties": {
    "iso:country":"DE",
    "sg:address":"Fischbachstr. 16",
    "sg:city":"R\u00f6thenbach",
    "sg:postcode":"90552",
    "sg:province":"Bayern",
    "wof:name":"Mlrs-europ\u00e4ische Produktionsges. Mbh",
    "wof:placetype":"venue"
},
  "geometry": {"coordinates":[11.2363004684,49.4808616638],"type":"Point"}
}