{
  "type": "Feature",
  "properties": {
    "iso:country":"DE",
    "sg:address":"Ermanstr. 19",
    "sg:city":"Berlin",
    "sg:postcode":"12163",
    "sg:province":"Berlin",
    "wof:name":"K. L. U. P. Gesellschaft F\u00fcr Edv-projektdurchf\u00fchrung Mbh",
    "wof:placetype":"venue"
},
  "geometry": {"coordinates":[13.315064,52.460087],"type":"Point"}
}