{
  "type": "Feature",
  "properties": {
    "iso:country":"DE",
    "sg:address":"Eichenhain 9",
    "sg:city":"Sch\u00f6ffengrund",
    "sg:phone":"+49 4964/45855",
    "sg:postcode":"35641",
    "sg:province":"Hessen",
    "wof:name":"Dinges & Keinath",
    "wof:placetype":"venue"
},
  "geometry": {"coordinates":[8.470506,50.521732],"type":"Point"}
}