{
  "type": "Feature",
  "properties": {
    "iso:country":"DE",
    "sg:address":"Bleicherstr. 20",
    "sg:city":"Bremen",
    "sg:phone":"+49 421/325126",
    "sg:postcode":"28203",
    "sg:province":"Bremen",
    "wof:name":"Design Gruppe Jung",
    "wof:placetype":"venue"
},
  "geometry": {"coordinates":[8.815987,53.071018],"type":"Point"}
}