{
  "type": "Feature",
  "properties": {
    "iso:country":"DE",
    "sg:address":"M\u00fcnchener Str. 2",
    "sg:city":"Landsberg",
    "sg:postcode":"86899",
    "sg:province":"Bayern",
    "wof:name":"Delta Control Sws Verwaltungs Gmbh",
    "wof:placetype":"venue"
},
  "geometry": {"coordinates":[10.8832511902,48.0486030579],"type":"Point"}
}