{
  "type": "Feature",
  "properties": {
    "iso:country":"DE",
    "sg:address":"Einhauser Str. 2",
    "sg:city":"Regensburg",
    "sg:phone":"+49 941/785060",
    "sg:postcode":"93053",
    "sg:province":"Bayern",
    "wof:name":"Schirling T\u00fcren Gmbh",
    "wof:placetype":"venue"
},
  "geometry": {"coordinates":[12.1323833466,49.0036888123],"type":"Point"}
}