{
  "type": "Feature",
  "properties": {
    "iso:country":"DE",
    "sg:address":"Am Wolfssiepen 22",
    "sg:city":"Finnentrop",
    "sg:phone":"+49 2721/5909",
    "sg:postcode":"57413",
    "sg:province":"Nordrhein-Westfalen",
    "wof:name":"Sb Technical Products Manfred Schmidt Gmbh",
    "wof:placetype":"venue"
},
  "geometry": {"coordinates":[7.974752,51.170174],"type":"Point"}
}