{
  "type": "Feature",
  "properties": {
    "iso:country":"DE",
    "sg:address":"Am Berg 14",
    "sg:city":"M\u00fcllheim",
    "sg:phone":"+49 7631/6120",
    "sg:postcode":"79379",
    "sg:province":"Baden-W\u00fcrttemberg",
    "wof:name":"Alois M\u00fchlb\u00f6ck",
    "wof:placetype":"venue"
},
  "geometry": {"coordinates":[7.624934,47.830406],"type":"Point"}
}