{
  "type": "Feature",
  "properties": {
    "iso:country":"DE",
    "sg:address":"T\u00f6pferwall 1",
    "sg:city":"R\u00f6bel",
    "sg:phone":"+49 39931/51700",
    "sg:postcode":"17207",
    "sg:province":"Mecklenburg-Vorpommern",
    "wof:name":"E. Beer",
    "wof:placetype":"venue"
},
  "geometry": {"coordinates":[12.6659202576,53.3776741028],"type":"Point"}
}