{
  "type": "Feature",
  "properties": {
    "iso:country":"DE",
    "sg:address":"Klosterstr. 8-9",
    "sg:city":"Berlin",
    "sg:phone":"+49 30/3326223",
    "sg:postcode":"13581",
    "sg:province":"Berlin",
    "wof:name":"Mehmet \u00d6zg\u00fcn Imbisstand Betriebs- Und",
    "wof:placetype":"venue"
},
  "geometry": {"coordinates":[13.1973152161,52.5320053101],"type":"Point"}
}