{
  "type": "Feature",
  "properties": {
    "iso:country":"DE",
    "sg:address":"M\u00fchlweg 2a",
    "sg:city":"Sauerlach",
    "sg:phone":"+49 8104/648230",
    "sg:postcode":"82054",
    "sg:province":"Bayern",
    "wof:name":"In-situ Gmbh & Co. Kg Vision & Sensor Systems",
    "wof:placetype":"venue"
},
  "geometry": {"coordinates":[11.661605,47.967354],"type":"Point"}
}