{
  "type": "Feature",
  "properties": {
    "iso:country":"DE",
    "sg:address":"Ringstr. 3",
    "sg:city":"Fellbach",
    "sg:phone":"+49 711/575943",
    "sg:postcode":"70736",
    "sg:province":"Baden-W\u00fcrttemberg",
    "wof:name":"Restaurant China-palast",
    "wof:placetype":"venue"
},
  "geometry": {"coordinates":[9.272600174,48.8203659058],"type":"Point"}
}