{
  "type": "Feature",
  "properties": {
    "iso:country":"DE",
    "sg:address":"Auf der Worth 25a",
    "sg:city":"Vahlde",
    "sg:phone":"+49 4267/953102",
    "sg:postcode":"27389",
    "sg:province":"Niedersachsen",
    "wof:name":"Wieselball",
    "wof:placetype":"venue"
},
  "geometry": {"coordinates":[9.603759,53.210979],"type":"Point"}
}