{
  "type": "Feature",
  "properties": {
    "iso:country":"DE",
    "sg:address":"Wolfsangerstr. 122",
    "sg:city":"Kassel",
    "sg:phone":"+49 561/874289",
    "sg:postcode":"34125",
    "sg:province":"Hessen",
    "wof:name":"Altenwohnheim",
    "wof:placetype":"venue"
},
  "geometry": {"coordinates":[9.533587,51.327763],"type":"Point"}
}