{
  "type": "Feature",
  "properties": {
    "iso:country":"DE",
    "sg:address":"Rhumestr. 9",
    "sg:city":"Northeim",
    "sg:phone":"+49 5551/8318",
    "sg:postcode":"37154",
    "sg:province":"Niedersachsen",
    "wof:name":"B. Pflug",
    "wof:placetype":"venue"
},
  "geometry": {"coordinates":[9.999065,51.71236],"type":"Point"}
}