{
  "type": "Feature",
  "properties": {
    "iso:country":"DE",
    "sg:address":"Kirchmeierstr. 22",
    "sg:city":"Regensburg",
    "sg:phone":"+49 941/383000",
    "sg:postcode":"93051",
    "sg:province":"Bayern",
    "wof:name":"Auto Best Carwash",
    "wof:placetype":"venue"
},
  "geometry": {"coordinates":[12.069547,49.010883],"type":"Point"}
}