{
  "type": "Feature",
  "properties": {
    "iso:country":"DE",
    "sg:address":"Kidlerstr. 19",
    "sg:city":"M\u00fcnchen",
    "sg:phone":"+49 89/7257276",
    "sg:postcode":"81371",
    "sg:province":"Bayern",
    "wof:name":"Gisela Drescher Bildhauer",
    "wof:placetype":"venue"
},
  "geometry": {"coordinates":[11.542346,48.119984],"type":"Point"}
}