{
  "type": "Feature",
  "properties": {
    "iso:country":"DE",
    "sg:address":"Auenweg 5",
    "sg:city":"Dingolfing",
    "sg:phone":"+49 8731/4237",
    "sg:postcode":"84130",
    "sg:province":"Bayern",
    "wof:name":"Norma Lebensmittel- Filialbetrieb Gmbh & Co. Kg",
    "wof:placetype":"venue"
},
  "geometry": {"coordinates":[12.4995260239,48.6321144104],"type":"Point"}
}