{
  "type": "Feature",
  "properties": {
    "iso:country":"DE",
    "sg:address":"Hauptstr. 2",
    "sg:city":"Kirchdorf",
    "sg:phone":"+49 8166/7368",
    "sg:postcode":"85414",
    "sg:province":"Bayern",
    "wof:name":"Josef Eisenberger",
    "wof:placetype":"venue"
},
  "geometry": {"coordinates":[11.652595,48.458221],"type":"Point"}
}