{
  "type": "Feature",
  "properties": {
    "iso:country":"DE",
    "sg:address":"Harslemstr. 2",
    "sg:city":"Breitenberg",
    "sg:phone":"+49 8584/477",
    "sg:postcode":"94139",
    "sg:province":"Bayern",
    "wof:name":"A. Und M. Uhrmann",
    "wof:placetype":"venue"
},
  "geometry": {"coordinates":[13.792321,48.703804],"type":"Point"}
}