{
  "type": "Feature",
  "properties": {
    "iso:country":"DE",
    "sg:address":"Neustr. 46",
    "sg:city":"Euskirchen",
    "sg:phone":"+49 2251/929595",
    "sg:postcode":"53879",
    "sg:province":"Nordrhein-Westfalen",
    "wof:name":"Gleissner Mobilfunk",
    "wof:placetype":"venue"
},
  "geometry": {"coordinates":[6.7903428078,50.6598854065],"type":"Point"}
}