{
  "type": "Feature",
  "properties": {
    "iso:country":"DE",
    "sg:address":"In der Steele 2",
    "sg:city":"D\u00fcsseldorf",
    "sg:phone":"+49 211/740010",
    "sg:postcode":"40599",
    "sg:province":"Nordrhein-Westfalen",
    "wof:name":"Ingenieurb\u00fcro Rinas",
    "wof:placetype":"venue"
},
  "geometry": {"coordinates":[6.87071,51.18454],"type":"Point"}
}