{
  "type": "Feature",
  "properties": {
    "iso:country":"DE",
    "sg:address":"Untere Marktstr. 26",
    "sg:city":"Neumarkt",
    "sg:phone":"+49 9181/21333",
    "sg:postcode":"92318",
    "sg:province":"Bayern",
    "wof:name":"Hummel & Edenhofer Gmbh & Co. Kg",
    "wof:placetype":"venue"
},
  "geometry": {"coordinates":[11.4588890076,49.2798271179],"type":"Point"}
}