{
  "type": "Feature",
  "properties": {
    "iso:country":"DE",
    "sg:address":"Fritz-Ebert-Str. 2",
    "sg:city":"Greiz",
    "sg:postcode":"07973",
    "sg:province":"Th\u00fcringen",
    "wof:name":"Willi Ludwig",
    "wof:placetype":"venue"
},
  "geometry": {"coordinates":[12.228144,50.652531],"type":"Point"}
}