{
  "type": "Feature",
  "properties": {
    "iso:country":"DE",
    "sg:address":"Tannenstr. 8",
    "sg:city":"Nettetal",
    "sg:phone":"+49 2153/3103",
    "sg:postcode":"41334",
    "sg:province":"Nordrhein-Westfalen",
    "wof:name":"Alfred Strentz",
    "wof:placetype":"venue"
},
  "geometry": {"coordinates":[6.2858228683,51.3062934875],"type":"Point"}
}