{
  "type": "Feature",
  "properties": {
    "iso:country":"DE",
    "sg:address":"Ludwig-Thoma-Str. 15",
    "sg:city":"Bayreuth",
    "sg:phone":"+49 921/75610",
    "sg:postcode":"95447",
    "sg:province":"Bayern",
    "wof:name":"Bechert Gmbh",
    "wof:placetype":"venue"
},
  "geometry": {"coordinates":[11.569006,49.934319],"type":"Point"}
}