{
  "type": "Feature",
  "properties": {
    "iso:country":"DE",
    "sg:address":"Im Au 10",
    "sg:city":"Heilbronn",
    "sg:postcode":"71548",
    "sg:province":"Baden-W\u00fcrttemberg",
    "wof:name":"Helft Babs - Grosse Internet-spendenaktion",
    "wof:placetype":"venue"
},
  "geometry": {"coordinates":[-82.151886,30.01918],"type":"Point"}
}