{
  "type": "Feature",
  "properties": {
    "iso:country":"DE",
    "sg:address":"Wailandtstr. 8",
    "sg:city":"Aschaffenburg",
    "sg:phone":"+49 6021/88826",
    "sg:postcode":"63741",
    "sg:province":"Bayern",
    "wof:name":"Racket 57 Squash Und Badminton Gmbh",
    "wof:placetype":"venue"
},
  "geometry": {"coordinates":[9.0975875854,49.9473953247],"type":"Point"}
}