{
  "type": "Feature",
  "properties": {
    "iso:country":"DE",
    "sg:address":"Siemensstr. 8",
    "sg:city":"Pleidelsheim",
    "sg:phone":"+49 4971/427050",
    "sg:postcode":"74385",
    "sg:province":"Baden-W\u00fcrttemberg",
    "wof:name":"D\u00dcrr Dental Gmbh & Co. Kg",
    "wof:placetype":"venue"
},
  "geometry": {"coordinates":[9.195649147,48.9531669617],"type":"Point"}
}