{
  "type": "Feature",
  "properties": {
    "iso:country":"DE",
    "sg:address":"Hintere Gerbergasse 9",
    "sg:city":"Memmingen",
    "sg:phone":"+49 8331/3234",
    "sg:postcode":"87700",
    "sg:province":"Bayern",
    "wof:name":"Friedrich Schatz",
    "wof:placetype":"venue"
},
  "geometry": {"coordinates":[10.1843280792,47.9828834534],"type":"Point"}
}