{
  "type": "Feature",
  "properties": {
    "iso:country":"DE",
    "sg:address":"Coburger Str. 3",
    "sg:city":"Lichtenfels",
    "sg:phone":"+49 9571/2290",
    "sg:postcode":"96215",
    "sg:province":"Bayern",
    "wof:name":"E. Heinkelmann",
    "wof:placetype":"venue"
},
  "geometry": {"coordinates":[11.0631389618,50.1465034485],"type":"Point"}
}