{
  "type": "Feature",
  "properties": {
    "iso:country":"DE",
    "sg:address":"Dahlienstr 27",
    "sg:city":"Eckental",
    "sg:phone":"+49 9126/2750",
    "sg:postcode":"90542",
    "sg:province":"Bayern",
    "wof:name":"Flad & Flad Communication Group Gmbh",
    "wof:placetype":"venue"
},
  "geometry": {"coordinates":[11.183355,49.586311],"type":"Point"}
}