{
  "type": "Feature",
  "properties": {
    "iso:country":"DE",
    "sg:address":"Amselweg 36",
    "sg:city":"Welzheim",
    "sg:phone":"+49 7182/49292",
    "sg:postcode":"73642",
    "sg:province":"Baden-W\u00fcrttemberg",
    "wof:name":"G. Bauer",
    "wof:placetype":"venue"
},
  "geometry": {"coordinates":[9.6257743835,48.8774414062],"type":"Point"}
}