{
  "type": "Feature",
  "properties": {
    "iso:country":"DE",
    "sg:address":"Krantorstr. 3 b",
    "sg:city":"Minden",
    "sg:postcode":"32425",
    "sg:province":"Nordrhein-Westfalen",
    "wof:name":"Bmb-bautr\u00e4ger Marketing Baubetreuungs Gmbh",
    "wof:placetype":"venue"
},
  "geometry": {"coordinates":[8.932802,52.345375],"type":"Point"}
}