{
  "type": "Feature",
  "properties": {
    "iso:country":"DE",
    "sg:address":"Br\u00fcdergasse 2",
    "sg:city":"Bonn",
    "sg:phone":"+49 228/656588",
    "sg:postcode":"53111",
    "sg:province":"Nordrhein-Westfalen",
    "wof:name":"Remigius-apotheke Inh. Irmgard Wenken",
    "wof:placetype":"venue"
},
  "geometry": {"coordinates":[7.102661,50.735802],"type":"Point"}
}