{
  "type": "Feature",
  "properties": {
    "iso:country":"DE",
    "sg:address":"Marktstr. 8",
    "sg:city":"Beratzhausen",
    "sg:phone":"+49 9493/1811",
    "sg:postcode":"93176",
    "sg:province":"Bayern",
    "wof:name":"P. Pirol",
    "wof:placetype":"venue"
},
  "geometry": {"coordinates":[11.809126,49.095474],"type":"Point"}
}