{
  "type": "Feature",
  "properties": {
    "iso:country":"DE",
    "sg:address":"Triebweg 9",
    "sg:city":"Elsenfeld",
    "sg:phone":"+49 6022/8279",
    "sg:postcode":"63820",
    "sg:province":"Bayern",
    "wof:name":"Johann Schneider",
    "wof:placetype":"venue"
},
  "geometry": {"coordinates":[9.1645107269,49.8450813293],"type":"Point"}
}