{
  "type": "Feature",
  "properties": {
    "iso:country":"DE",
    "sg:address":"Steinbeisstr. 9",
    "sg:city":"Ilsfeld",
    "sg:phone":"+49 7062/63187",
    "sg:postcode":"74360",
    "sg:province":"Baden-W\u00fcrttemberg",
    "wof:name":"Dieter Fahrner",
    "wof:placetype":"venue"
},
  "geometry": {"coordinates":[9.2611455917,49.0561790466],"type":"Point"}
}