{
  "type": "Feature",
  "properties": {
    "iso:country":"DE",
    "sg:address":"Vereinsstr. 13a",
    "sg:city":"Neukirchen",
    "sg:phone":"+49 4937/622717",
    "sg:postcode":"08459",
    "sg:province":"Sachsen",
    "wof:name":"N\u00d6nnig Metallbau Gmbh",
    "wof:placetype":"venue"
},
  "geometry": {"coordinates":[12.385314,50.800282],"type":"Point"}
}