{
  "type": "Feature",
  "properties": {
    "iso:country":"DE",
    "sg:address":"Bahnhofstr. 71",
    "sg:city":"Wegberg",
    "sg:phone":"+49 2434/5671",
    "sg:postcode":"41844",
    "sg:province":"Nordrhein-Westfalen",
    "wof:name":"Dieter Stevens",
    "wof:placetype":"venue"
},
  "geometry": {"coordinates":[6.2795782089,51.1457633972],"type":"Point"}
}