{
  "type": "Feature",
  "properties": {
    "iso:country":"DE",
    "sg:address":"Bahnhofstrasse 53",
    "sg:city":"Nidda",
    "sg:postcode":"63667",
    "sg:province":"Hessen",
    "wof:name":"Rechtswanwaelte Hartmann, Humbroich Und Dr. Zwerenz",
    "wof:placetype":"venue"
},
  "geometry": {"coordinates":[9.002461,50.412258],"type":"Point"}
}