{
  "type": "Feature",
  "properties": {
    "iso:country":"DE",
    "sg:address":"Norderquerweg 180",
    "sg:city":"Hamburg",
    "sg:phone":"+49 40/79319600",
    "sg:postcode":"21037",
    "sg:province":"Hamburg",
    "wof:name":"Maurerfachbetrieb Timmann Gmbh",
    "wof:placetype":"venue"
},
  "geometry": {"coordinates":[10.202475,53.422382],"type":"Point"}
}