{
  "type": "Feature",
  "properties": {
    "iso:country":"DE",
    "sg:address":"Robert-Koch-Str.2",
    "sg:city":"Norderstedt",
    "sg:phone":"+49 40/521000",
    "sg:postcode":"22851",
    "sg:province":"Schleswig-Holstein",
    "wof:name":"Sch\u00dclke & Mayr Gmbh",
    "wof:placetype":"venue"
},
  "geometry": {"coordinates":[10.047256,53.686054],"type":"Point"}
}