{
  "type": "Feature",
  "properties": {
    "iso:country":"DE",
    "sg:address":"Rochlitzer Str. 32",
    "sg:city":"Erfurt",
    "sg:phone":"+49 361/7458072",
    "sg:postcode":"99092",
    "sg:province":"Th\u00fcringen",
    "wof:name":"Eci Enviroconsult Ingenieurb\u00fcro Dr. Lux E. K.",
    "wof:placetype":"venue"
},
  "geometry": {"coordinates":[10.988699,50.992214],"type":"Point"}
}