{
  "type": "Feature",
  "properties": {
    "iso:country":"DE",
    "sg:address":"Gro\u00dfsachsenheimer Str. 22",
    "sg:city":"Sachsenheim",
    "sg:phone":"+49 7147/6357",
    "sg:postcode":"74343",
    "sg:province":"Baden-W\u00fcrttemberg",
    "wof:name":"Hans Harrer Elektroinstallation",
    "wof:placetype":"venue"
},
  "geometry": {"coordinates":[9.069594,48.968571],"type":"Point"}
}