{
  "type": "Feature",
  "properties": {
    "iso:country":"DE",
    "sg:address":"Poggenpaulsweg 42",
    "sg:city":"Wietze",
    "sg:phone":"+49 5146/2637",
    "sg:postcode":"29323",
    "sg:province":"Niedersachsen",
    "wof:name":"F\u00f6rster Vva Gmbh",
    "wof:placetype":"venue"
},
  "geometry": {"coordinates":[9.828825,52.65147],"type":"Point"}
}