{
  "type": "Feature",
  "properties": {
    "iso:country":"DE",
    "sg:address":"Freiheit 12",
    "sg:city":"Berlin",
    "sg:phone":"+49 30/65497744",
    "sg:postcode":"12555",
    "sg:province":"Berlin",
    "wof:name":"Timmer Und Oetken Ergotherapeutische Praxis",
    "wof:placetype":"venue"
},
  "geometry": {"coordinates":[13.577679,52.447529],"type":"Point"}
}