{
  "type": "Feature",
  "properties": {
    "iso:country":"DE",
    "sg:address":"Brauhausstieg 17",
    "sg:city":"Hamburg",
    "sg:postcode":"22041",
    "sg:province":"Hamburg",
    "wof:name":"Heinrich Bolt Nachf. G\u00fcnter Stanitzke Gmbh",
    "wof:placetype":"venue"
},
  "geometry": {"coordinates":[10.0617923737,53.5720024109],"type":"Point"}
}