{
  "type": "Feature",
  "properties": {
    "iso:country":"DE",
    "sg:address":"Rosenheimer Str. 145 i",
    "sg:city":"M\u00fcnchen",
    "sg:postcode":"81671",
    "sg:province":"Bayern",
    "wof:name":"S.g.k. Steuerberatungsges. Strobel-gr\u00fcttner-knoll",
    "wof:placetype":"venue"
},
  "geometry": {"coordinates":[11.6115198135,48.1231994629],"type":"Point"}
}