{
  "type": "Feature",
  "properties": {
    "iso:country":"DE",
    "sg:address":"Im Himmel 6A",
    "sg:city":"Stuttgart",
    "sg:phone":"+49 711/6788090",
    "sg:postcode":"70569",
    "sg:province":"Baden-W\u00fcrttemberg",
    "wof:name":"J. Belz Ingenieur",
    "wof:placetype":"venue"
},
  "geometry": {"coordinates":[9.1156339645,48.7481765747],"type":"Point"}
}