{
  "type": "Feature",
  "properties": {
    "iso:country":"DE",
    "sg:address":"Wulfsdorfer Weg 93",
    "sg:city":"Ahrensburg",
    "sg:phone":"+49 4102/53557",
    "sg:postcode":"22926",
    "sg:province":"Schleswig-Holstein",
    "wof:name":"West-apotheke",
    "wof:placetype":"venue"
},
  "geometry": {"coordinates":[10.220874,53.672592],"type":"Point"}
}