{
  "type": "Feature",
  "properties": {
    "iso:country":"DE",
    "sg:address":"Heilberg 8",
    "sg:city":"B\u00fchlerzell",
    "sg:phone":"+49 7974/216",
    "sg:postcode":"74426",
    "sg:province":"Baden-W\u00fcrttemberg",
    "wof:name":"Wilhelm Wagner",
    "wof:placetype":"venue"
},
  "geometry": {"coordinates":[9.918445,49.002029],"type":"Point"}
}