{
  "type": "Feature",
  "properties": {
    "iso:country":"DE",
    "sg:address":"Heinrich-Seidel-Str. 9",
    "sg:city":"Berlin",
    "sg:phone":"+49 30/7965789",
    "sg:postcode":"12167",
    "sg:province":"Berlin",
    "wof:name":"Gertrud Frank",
    "wof:placetype":"venue"
},
  "geometry": {"coordinates":[13.344833374,52.4498176575],"type":"Point"}
}