{
  "type": "Feature",
  "properties": {
    "iso:country":"DE",
    "sg:address":"Parkstr. 29",
    "sg:city":"Neum\u00fcnster",
    "sg:postcode":"24534",
    "sg:province":"Schleswig-Holstein",
    "wof:name":"Kino-betriebsgesellschaft Kieft & Meyer 1",
    "wof:placetype":"venue"
},
  "geometry": {"coordinates":[9.987204,54.075268],"type":"Point"}
}