{
  "type": "Feature",
  "properties": {
    "iso:country":"DE",
    "sg:address":"Zazenh\u00e4user Str. 36",
    "sg:city":"Stuttgart",
    "sg:phone":"+49 711/873929",
    "sg:postcode":"70437",
    "sg:province":"Baden-W\u00fcrttemberg",
    "wof:name":"Cafe Mozart",
    "wof:placetype":"venue"
},
  "geometry": {"coordinates":[9.1808786392,48.8354034424],"type":"Point"}
}