{
  "type": "Feature",
  "properties": {
    "iso:country":"DE",
    "sg:address":"Hachtorstr. 23",
    "sg:city":"R\u00fcthen",
    "sg:phone":"+49 2952/8515",
    "sg:postcode":"59602",
    "sg:province":"Nordrhein-Westfalen",
    "wof:name":"Ratskeller",
    "wof:placetype":"venue"
},
  "geometry": {"coordinates":[8.431344986,51.49168396],"type":"Point"}
}