{
  "type": "Feature",
  "properties": {
    "iso:country":"DE",
    "sg:address":"Bergleweg 30",
    "sg:city":"Elzach",
    "sg:phone":"+49 7682/8977",
    "sg:postcode":"79215",
    "sg:province":"Baden-W\u00fcrttemberg",
    "wof:name":"Hermann Kury",
    "wof:placetype":"venue"
},
  "geometry": {"coordinates":[8.0901699066,48.1828231812],"type":"Point"}
}