{
  "type": "Feature",
  "properties": {
    "iso:country":"DE",
    "sg:address":"Rettigheimer Str. 37",
    "sg:city":"M\u00fchlhausen",
    "sg:postcode":"69242",
    "sg:province":"Baden-W\u00fcrttemberg",
    "wof:name":"Addlife E. K.",
    "wof:placetype":"venue"
},
  "geometry": {"coordinates":[8.7145843506,49.2480773926],"type":"Point"}
}