{
  "type": "Feature",
  "properties": {
    "iso:country":"DE",
    "sg:address":"Neuer Wall 20",
    "sg:city":"Moers",
    "sg:phone":"+49 2841/177156",
    "sg:postcode":"47441",
    "sg:province":"Nordrhein-Westfalen",
    "wof:name":"Ambiente",
    "wof:placetype":"venue"
},
  "geometry": {"coordinates":[6.6287641525,51.4516334534],"type":"Point"}
}