{
  "type": "Feature",
  "properties": {
    "iso:country":"DE",
    "sg:address":"Kernerstr. 20",
    "sg:city":"Dei\u00dflingen",
    "sg:phone":"+49 7420/1303",
    "sg:postcode":"78652",
    "sg:province":"Baden-W\u00fcrttemberg",
    "wof:name":"Dr. Med. Hermann Pfitzinger",
    "wof:placetype":"venue"
},
  "geometry": {"coordinates":[8.6075639725,48.1095581055],"type":"Point"}
}