{
  "type": "Feature",
  "properties": {
    "iso:country":"DE",
    "sg:address":"Fikentscherstr. 19",
    "sg:city":"Marktredwitz",
    "sg:phone":"+49 9231/2033",
    "sg:postcode":"95615",
    "sg:province":"Bayern",
    "wof:name":"Buchhandlung Budow Gmbh",
    "wof:placetype":"venue"
},
  "geometry": {"coordinates":[12.0946702957,50.0042037964],"type":"Point"}
}