{
  "type": "Feature",
  "properties": {
    "iso:country":"DE",
    "sg:address":"Friedrich-Stein-Str. 10",
    "sg:city":"Schweinfurt",
    "sg:phone":"+49 9721/2019010",
    "sg:postcode":"97421",
    "sg:province":"Bayern",
    "wof:name":"Vogt & Fritz Inh. Elke Tober-vogt",
    "wof:placetype":"venue"
},
  "geometry": {"coordinates":[10.223690033,50.0447349548],"type":"Point"}
}