{
  "type": "Feature",
  "properties": {
    "iso:country":"DE",
    "sg:address":"Rosenaustr. 7",
    "sg:city":"Offenbach",
    "sg:phone":"+49 69/832773",
    "sg:postcode":"63069",
    "sg:province":"Hessen",
    "wof:name":"E. Gries Hebamme",
    "wof:placetype":"venue"
},
  "geometry": {"coordinates":[8.753203,50.093391],"type":"Point"}
}