{
  "type": "Feature",
  "properties": {
    "iso:country":"DE",
    "sg:address":"Kleyerstr. 90",
    "sg:city":"Frankfurt",
    "sg:phone":"+49 69/9730300",
    "sg:postcode":"60326",
    "sg:province":"Hessen",
    "wof:name":"Alfred Neud\u00f6rfer Gmbh",
    "wof:placetype":"venue"
},
  "geometry": {"coordinates":[8.632679,50.098522],"type":"Point"}
}