{
  "type": "Feature",
  "properties": {
    "iso:country":"DE",
    "sg:address":"Am Gangsteig 3",
    "sg:city":"Holzkirchen",
    "sg:postcode":"83607",
    "sg:province":"Bayern",
    "wof:name":"M & H Business Solutions Gmbh",
    "wof:placetype":"venue"
},
  "geometry": {"coordinates":[11.697947,47.879749],"type":"Point"}
}