{
  "type": "Feature",
  "properties": {
    "iso:country":"DE",
    "sg:address":"Bielefelder Str. 4",
    "sg:city":"Enger",
    "sg:phone":"+49 5224/977606",
    "sg:postcode":"32130",
    "sg:province":"Nordrhein-Westfalen",
    "wof:name":"Restaurant Korfu",
    "wof:placetype":"venue"
},
  "geometry": {"coordinates":[8.5583839417,52.1371040344],"type":"Point"}
}