{
  "type": "Feature",
  "properties": {
    "iso:country":"DE",
    "sg:address":"Falkenberger Str. 145 b",
    "sg:city":"Berlin",
    "sg:phone":"+49 30/96069004",
    "sg:postcode":"13088",
    "sg:province":"Berlin",
    "wof:name":"Schuster Und Spranger Ingenieurb\u00fcro",
    "wof:placetype":"venue"
},
  "geometry": {"coordinates":[13.484105,52.557438],"type":"Point"}
}