{
  "type": "Feature",
  "properties": {
    "iso:country":"DE",
    "sg:address":"Murgtalstr. 323",
    "sg:city":"Baiersbronn",
    "sg:phone":"+49 7442/2386",
    "sg:postcode":"72270",
    "sg:province":"Baden-W\u00fcrttemberg",
    "wof:name":"Gasthof Sonne",
    "wof:placetype":"venue"
},
  "geometry": {"coordinates":[8.4019327164,48.5300598145],"type":"Point"}
}