{
  "type": "Feature",
  "properties": {
    "iso:country":"DE",
    "sg:address":"Am Pfarr\u00f6schle 50",
    "sg:city":"Pfullendorf",
    "sg:phone":"+49 7552/92150",
    "sg:postcode":"88630",
    "sg:province":"Baden-W\u00fcrttemberg",
    "wof:name":"Ibp Knaus & Zentner Gmbh",
    "wof:placetype":"venue"
},
  "geometry": {"coordinates":[9.2535896301,47.9213485718],"type":"Point"}
}