{
  "type": "Feature",
  "properties": {
    "iso:country":"DE",
    "sg:address":"Mindener Str. 179",
    "sg:city":"Herford",
    "sg:phone":"+49 5221/21570",
    "sg:postcode":"32049",
    "sg:province":"Nordrhein-Westfalen",
    "wof:name":"Fritz Pieper Kg",
    "wof:placetype":"venue"
},
  "geometry": {"coordinates":[8.6921186447,52.1349143982],"type":"Point"}
}