{
  "type": "Feature",
  "properties": {
    "iso:country":"DE",
    "sg:address":"Poststr. 10",
    "sg:city":"Plettenberg",
    "sg:phone":"+49 2391/95940",
    "sg:postcode":"58840",
    "sg:province":"Nordrhein-Westfalen",
    "wof:name":"Overbeck Reuber Und Vo\u00df Steuerberater",
    "wof:placetype":"venue"
},
  "geometry": {"coordinates":[7.8695912361,51.2328796387],"type":"Point"}
}