{
  "type": "Feature",
  "properties": {
    "iso:country":"DE",
    "sg:address":"Hauptstr. 110",
    "sg:city":"Lindenberg",
    "sg:phone":"+49 8381/82177",
    "sg:postcode":"88161",
    "sg:province":"Bayern",
    "wof:name":"Mu K Mangold & Klarmann Gesellschaft F\u00fcr Informatik",
    "wof:placetype":"venue"
},
  "geometry": {"coordinates":[8.0977888107,49.3814888],"type":"Point"}
}