{
  "type": "Feature",
  "properties": {
    "iso:country":"DE",
    "sg:address":"Kirchhofstr. 31",
    "sg:city":"Berlin",
    "sg:phone":"+49 30/4361487",
    "sg:postcode":"13585",
    "sg:province":"Berlin",
    "wof:name":"Michael H\u00fcbner",
    "wof:placetype":"venue"
},
  "geometry": {"coordinates":[13.205201149,52.5452651978],"type":"Point"}
}