{
  "type": "Feature",
  "properties": {
    "iso:country":"DE",
    "sg:address":"Friedenstr. 14",
    "sg:city":"M\u00f6mbris",
    "sg:phone":"+49 6029/6605",
    "sg:postcode":"63776",
    "sg:province":"Bayern",
    "wof:name":"Ludwig Noe Gmbh",
    "wof:placetype":"venue"
},
  "geometry": {"coordinates":[9.14144,50.044891],"type":"Point"}
}