{
  "type": "Feature",
  "properties": {
    "iso:country":"DE",
    "sg:address":"Birkmaier 1",
    "sg:city":"Reichertsheim",
    "sg:phone":"+49 8073/600",
    "sg:postcode":"84437",
    "sg:province":"Bayern",
    "wof:name":"Sch\u00f6berl Gmbh",
    "wof:placetype":"venue"
},
  "geometry": {"coordinates":[12.2612810135,48.1713142395],"type":"Point"}
}