{
  "type": "Feature",
  "properties": {
    "iso:country":"DE",
    "sg:address":"Streitw\u00e4ldle 8",
    "sg:city":"Waldachtal",
    "sg:phone":"+49 7443/8360",
    "sg:postcode":"72178",
    "sg:province":"Baden-W\u00fcrttemberg",
    "wof:name":"Gilbert St\u00f6rzer",
    "wof:placetype":"venue"
},
  "geometry": {"coordinates":[8.561083,48.492809],"type":"Point"}
}