{
  "type": "Feature",
  "properties": {
    "iso:country":"DE",
    "sg:address":"Fliederstr. 4",
    "sg:city":"Ebersbach-Musbach",
    "sg:postcode":"88371",
    "sg:province":"Baden-W\u00fcrttemberg",
    "wof:name":"Franitza-reisen E. K.",
    "wof:placetype":"venue"
},
  "geometry": {"coordinates":[9.5807104111,47.9593086243],"type":"Point"}
}