{
  "type": "Feature",
  "properties": {
    "iso:country":"DE",
    "sg:address":"J\u00e4gerstr. 89a",
    "sg:city":"Bergisch Gladbach",
    "sg:phone":"+49 2202/951912",
    "sg:postcode":"51467",
    "sg:province":"Nordrhein-Westfalen",
    "wof:name":"Innovations Eins Venture Capital Vermittlung Und",
    "wof:placetype":"venue"
},
  "geometry": {"coordinates":[7.126358,50.998959],"type":"Point"}
}