{
  "type": "Feature",
  "properties": {
    "iso:country":"DE",
    "sg:address":"M\u00fcnsterstr. 2",
    "sg:city":"Oelde",
    "sg:phone":"+49 2529/1331",
    "sg:postcode":"59302",
    "sg:province":"Nordrhein-Westfalen",
    "wof:name":"Josef Kohaus",
    "wof:placetype":"venue"
},
  "geometry": {"coordinates":[8.203669548,51.8020553589],"type":"Point"}
}