{
  "type": "Feature",
  "properties": {
    "iso:country":"DE",
    "sg:address":"Reichstr. 10",
    "sg:city":"M\u00fclheim",
    "sg:phone":"+49 208/424388",
    "sg:postcode":"45479",
    "sg:province":"Nordrhein-Westfalen",
    "wof:name":"Becker",
    "wof:placetype":"venue"
},
  "geometry": {"coordinates":[6.85973,51.426277],"type":"Point"}
}