{
  "type": "Feature",
  "properties": {
    "iso:country":"DE",
    "sg:address":"Bischof-Wittmann-Str. 26",
    "sg:city":"Regensburg",
    "sg:phone":"+49 941/90614",
    "sg:postcode":"93051",
    "sg:province":"Bayern",
    "wof:name":"H. Kessel Raumausstattung E.k.",
    "wof:placetype":"venue"
},
  "geometry": {"coordinates":[12.0831699371,49.0062561035],"type":"Point"}
}