{
  "type": "Feature",
  "properties": {
    "iso:country":"DE",
    "sg:address":"Dehrner Weg 10",
    "sg:city":"Limburg",
    "sg:phone":"+49 6431/52411",
    "sg:postcode":"65553",
    "sg:province":"Hessen",
    "wof:name":"F. Karl Gmbh",
    "wof:placetype":"venue"
},
  "geometry": {"coordinates":[8.0832395554,50.4171104431],"type":"Point"}
}