{
  "type": "Feature",
  "properties": {
    "iso:country":"DE",
    "sg:address":"Marktplatz 16",
    "sg:city":"Abtsgm\u00fcnd",
    "sg:phone":"+49 7366/2830",
    "sg:postcode":"73453",
    "sg:province":"Baden-W\u00fcrttemberg",
    "wof:name":"Mario Hohenstadt",
    "wof:placetype":"venue"
},
  "geometry": {"coordinates":[9.9356298447,48.8994483948],"type":"Point"}
}