{
  "type": "Feature",
  "properties": {
    "iso:country":"DE",
    "sg:address":"Bonholz 4",
    "sg:city":"Alfdorf",
    "sg:phone":"+49 7172/31475",
    "sg:postcode":"73553",
    "sg:province":"Baden-W\u00fcrttemberg",
    "wof:name":"Georg Kinkel",
    "wof:placetype":"venue"
},
  "geometry": {"coordinates":[9.736838,48.844063],"type":"Point"}
}