{
  "type": "Feature",
  "properties": {
    "iso:country":"DE",
    "sg:address":"Frankfurter Str. 20",
    "sg:city":"Maulbronn",
    "sg:phone":"+49 7043/6431",
    "sg:postcode":"75433",
    "sg:province":"Baden-W\u00fcrttemberg",
    "wof:name":"W. Scheytt Damen- U. Herrenfriseur",
    "wof:placetype":"venue"
},
  "geometry": {"coordinates":[8.807025,48.998817],"type":"Point"}
}