{
  "type": "Feature",
  "properties": {
    "iso:country":"DE",
    "sg:address":"Tainer Str. 12",
    "sg:city":"Fellbach",
    "sg:phone":"+49 711/582202",
    "sg:postcode":"70734",
    "sg:province":"Baden-W\u00fcrttemberg",
    "wof:name":"Christa Roesner Bildhauerin",
    "wof:placetype":"venue"
},
  "geometry": {"coordinates":[9.274832,48.809315],"type":"Point"}
}