{
  "type": "Feature",
  "properties": {
    "iso:country":"DE",
    "sg:address":"Dessauerstr. 20",
    "sg:city":"Moers",
    "sg:phone":"+49 2841/63572",
    "sg:postcode":"47445",
    "sg:province":"Nordrhein-Westfalen",
    "wof:name":"Cc Plan",
    "wof:placetype":"venue"
},
  "geometry": {"coordinates":[6.6391611099,51.4819335938],"type":"Point"}
}