{
  "type": "Feature",
  "properties": {
    "iso:country":"DE",
    "sg:address":"Feldmochinger Str. 4 a",
    "sg:city":"M\u00fcnchen",
    "sg:phone":"+49 89/1418008",
    "sg:postcode":"80992",
    "sg:province":"Bayern",
    "wof:name":"Zehetner Handelsvertretung Gmbh",
    "wof:placetype":"venue"
},
  "geometry": {"coordinates":[11.5211076736,48.177280426],"type":"Point"}
}