{
  "type": "Feature",
  "properties": {
    "iso:country":"DE",
    "sg:address":"Ostendstr. 23",
    "sg:city":"Lampertheim",
    "sg:phone":"+49 6206/2843",
    "sg:postcode":"68623",
    "sg:province":"Hessen",
    "wof:name":"Jakob Becker",
    "wof:placetype":"venue"
},
  "geometry": {"coordinates":[8.4791488647,49.591583252],"type":"Point"}
}