{
  "type": "Feature",
  "properties": {
    "iso:country":"DE",
    "sg:address":"M\u00fchlbachstr. 49",
    "sg:city":"Neus\u00e4\u00df",
    "sg:phone":"+49 821/481037",
    "sg:postcode":"86356",
    "sg:province":"Bayern",
    "wof:name":"Bartel & Sohn Gmbh",
    "wof:placetype":"venue"
},
  "geometry": {"coordinates":[10.808604,48.400852],"type":"Point"}
}