{
  "type": "Feature",
  "properties": {
    "iso:country":"DE",
    "sg:address":"Untere Kellerstr. 6",
    "sg:city":"Feucht",
    "sg:phone":"+49 9128/3357",
    "sg:postcode":"90537",
    "sg:province":"Bayern",
    "wof:name":"Kath. Pfarramt Herz-jesu",
    "wof:placetype":"venue"
},
  "geometry": {"coordinates":[11.2119607925,49.3760452271],"type":"Point"}
}