{
  "type": "Feature",
  "properties": {
    "iso:country":"DE",
    "sg:address":"Schellingstr. 16",
    "sg:city":"Pforzheim",
    "sg:phone":"+49 7231/65658",
    "sg:postcode":"75175",
    "sg:province":"Baden-W\u00fcrttemberg",
    "wof:name":"Weik",
    "wof:placetype":"venue"
},
  "geometry": {"coordinates":[8.700754,48.884407],"type":"Point"}
}