{
  "type": "Feature",
  "properties": {
    "iso:country":"DE",
    "sg:address":"Martin-Luther-Str. 6",
    "sg:city":"Warthausen",
    "sg:postcode":"88447",
    "sg:province":"Baden-W\u00fcrttemberg",
    "wof:name":"Ev. Pfarramt",
    "wof:placetype":"venue"
},
  "geometry": {"coordinates":[9.7989187241,48.1281852722],"type":"Point"}
}