{
  "type": "Feature",
  "properties": {
    "iso:country":"DE",
    "sg:address":"Hersfelder Str. 2",
    "sg:city":"Kassel",
    "sg:phone":"+49 561/85809",
    "sg:postcode":"34127",
    "sg:province":"Hessen",
    "wof:name":"Rothenberger Klause",
    "wof:placetype":"venue"
},
  "geometry": {"coordinates":[9.4855136871,51.3269882202],"type":"Point"}
}