{
  "type": "Feature",
  "properties": {
    "iso:country":"DE",
    "sg:address":"Schillerweg 1",
    "sg:city":"Bretten",
    "sg:phone":"+49 7252/6173",
    "sg:postcode":"75015",
    "sg:province":"Baden-W\u00fcrttemberg",
    "wof:name":"Walter Neff",
    "wof:placetype":"venue"
},
  "geometry": {"coordinates":[8.7110853195,49.0289993286],"type":"Point"}
}