{
  "type": "Feature",
  "properties": {
    "iso:country":"DE",
    "sg:address":"Im Dorfe 2",
    "sg:city":"Dahlenburg",
    "sg:phone":"+49 5851/7789",
    "sg:postcode":"21368",
    "sg:province":"Niedersachsen",
    "wof:name":"Pflege Daheim",
    "wof:placetype":"venue"
},
  "geometry": {"coordinates":[10.694196,53.177792],"type":"Point"}
}