{
  "type": "Feature",
  "properties": {
    "iso:country":"DE",
    "sg:address":"Meiersberger Str. 44",
    "sg:city":"Ratingen",
    "sg:phone":"+49 2102/52306",
    "sg:postcode":"40882",
    "sg:province":"Nordrhein-Westfalen",
    "wof:name":"Wolfgang Becker",
    "wof:placetype":"venue"
},
  "geometry": {"coordinates":[6.933299,51.296635],"type":"Point"}
}