{
  "type": "Feature",
  "properties": {
    "iso:country":"DE",
    "sg:address":"G\u00fctersloher Str. 19",
    "sg:city":"Rietberg",
    "sg:phone":"+49 5244/10427",
    "sg:postcode":"33397",
    "sg:province":"Nordrhein-Westfalen",
    "wof:name":"Restaurant Rossini",
    "wof:placetype":"venue"
},
  "geometry": {"coordinates":[8.4291362762,51.8402404785],"type":"Point"}
}