{
  "type": "Feature",
  "properties": {
    "iso:country":"DE",
    "sg:address":"Bahnhofstr. 42",
    "sg:city":"Gro\u00df-Bieberau",
    "sg:phone":"+49 6162/912076",
    "sg:postcode":"64401",
    "sg:province":"Hessen",
    "wof:name":"Klaus Zetsche",
    "wof:placetype":"venue"
},
  "geometry": {"coordinates":[8.8258209229,49.8035812378],"type":"Point"}
}