{
  "type": "Feature",
  "properties": {
    "iso:country":"DE",
    "sg:address":"Am Berggewann 13",
    "sg:city":"Wiesbaden",
    "sg:phone":"+49 611/422250",
    "sg:postcode":"65199",
    "sg:province":"Hessen",
    "wof:name":"Dr. Florian K\u00f6nig Tierarzt",
    "wof:placetype":"venue"
},
  "geometry": {"coordinates":[8.1897182465,50.0728225708],"type":"Point"}
}