{
  "type": "Feature",
  "properties": {
    "iso:country":"DE",
    "sg:address":"Damm 3",
    "sg:city":"Braunschweig",
    "sg:phone":"+49 531/44369",
    "sg:postcode":"38100",
    "sg:province":"Niedersachsen",
    "wof:name":"Ch. Zimmermann",
    "wof:placetype":"venue"
},
  "geometry": {"coordinates":[10.52251,52.262432],"type":"Point"}
}