{
  "type": "Feature",
  "properties": {
    "iso:country":"DE",
    "sg:address":"Schulstr. 12",
    "sg:city":"Geltendorf",
    "sg:phone":"+49 8193/6366",
    "sg:postcode":"82269",
    "sg:province":"Bayern",
    "wof:name":"Tsv Sportgastst\u00e4tte",
    "wof:placetype":"venue"
},
  "geometry": {"coordinates":[11.0348796844,48.1158103943],"type":"Point"}
}