{
  "type": "Feature",
  "properties": {
    "iso:country":"DE",
    "sg:address":"Kaspar-Zopes-Str. 5",
    "sg:city":"H\u00fcrth",
    "sg:phone":"+49 2233/44769",
    "sg:postcode":"50354",
    "sg:province":"Nordrhein-Westfalen",
    "wof:name":"Jansen & Raaf Bauges. Mbh .",
    "wof:placetype":"venue"
},
  "geometry": {"coordinates":[6.899522,50.857483],"type":"Point"}
}