{
  "type": "Feature",
  "properties": {
    "iso:country":"DE",
    "sg:address":"Hann\u00f6versche Str. 82",
    "sg:city":"Dortmund",
    "sg:phone":"+49 231/5316270",
    "sg:postcode":"44143",
    "sg:province":"Nordrhein-Westfalen",
    "wof:name":"Schymalla & Sprute Ohg",
    "wof:placetype":"venue"
},
  "geometry": {"coordinates":[7.514352,51.525276],"type":"Point"}
}