{
  "type": "Feature",
  "properties": {
    "iso:country":"DE",
    "sg:address":"Norderstedter Str. 2",
    "sg:city":"Henstedt-Ulzburg",
    "sg:phone":"+49 4193/79888",
    "sg:postcode":"24558",
    "sg:province":"Schleswig-Holstein",
    "wof:name":"Croque Und Crepes",
    "wof:placetype":"venue"
},
  "geometry": {"coordinates":[9.9965267181,53.7519302368],"type":"Point"}
}