{
  "type": "Feature",
  "properties": {
    "iso:country":"DE",
    "sg:address":"Rosenaustra\u00dfe 4",
    "sg:city":"Beilngries",
    "sg:phone":"+49 8461/64100",
    "sg:postcode":"92339",
    "sg:province":"Bayern",
    "wof:name":"Schmidt Spedition Gmbh",
    "wof:placetype":"venue"
},
  "geometry": {"coordinates":[11.4729261398,49.0324707031],"type":"Point"}
}