{
  "type": "Feature",
  "properties": {
    "iso:country":"DE",
    "sg:address":"Sch\u00f6llbronner Str. 22",
    "sg:city":"Ettlingen",
    "sg:phone":"+49 7243/12294",
    "sg:postcode":"76275",
    "sg:province":"Baden-W\u00fcrttemberg",
    "wof:name":"Hermann Maisch",
    "wof:placetype":"venue"
},
  "geometry": {"coordinates":[8.413059,48.938087],"type":"Point"}
}