{
  "type": "Feature",
  "properties": {
    "iso:country":"DE",
    "sg:address":"Springmorgen 5",
    "sg:city":"Dortmund",
    "sg:phone":"+49 231/771241",
    "sg:postcode":"44227",
    "sg:province":"Nordrhein-Westfalen",
    "wof:name":"Werner Hillmann Ingenieur",
    "wof:placetype":"venue"
},
  "geometry": {"coordinates":[7.4127979279,51.4587135315],"type":"Point"}
}