{
  "type": "Feature",
  "properties": {
    "iso:country":"DE",
    "sg:address":"Thomas-Mann-Str. 42",
    "sg:city":"Freital",
    "sg:phone":"+49 351/643740",
    "sg:postcode":"01705",
    "sg:province":"Sachsen",
    "wof:name":"Werner Hegewald",
    "wof:placetype":"venue"
},
  "geometry": {"coordinates":[13.657645,51.01416],"type":"Point"}
}