{
  "type": "Feature",
  "properties": {
    "iso:country":"DE",
    "sg:address":"Knesheckenweg 3",
    "sg:city":"Dipperz",
    "sg:phone":"+49 6657/7274",
    "sg:postcode":"36160",
    "sg:province":"Hessen",
    "wof:name":"Markus Vogel",
    "wof:placetype":"venue"
},
  "geometry": {"coordinates":[9.816791,50.517677],"type":"Point"}
}