{
  "type": "Feature",
  "properties": {
    "iso:country":"DE",
    "sg:address":"Westerweide 27",
    "sg:city":"Witten",
    "sg:phone":"+49 2302/73012",
    "sg:postcode":"58456",
    "sg:province":"Nordrhein-Westfalen",
    "wof:name":"Holzland Wischmann",
    "wof:placetype":"venue"
},
  "geometry": {"coordinates":[7.267288,51.409306],"type":"Point"}
}