{
  "type": "Feature",
  "properties": {
    "iso:country":"DE",
    "sg:address":"L\u00fcckerather Str. 9",
    "sg:city":"Kall",
    "sg:phone":"+49 2441/6233",
    "sg:postcode":"53925",
    "sg:province":"Nordrhein-Westfalen",
    "wof:name":"Hans Hemmersbach",
    "wof:placetype":"venue"
},
  "geometry": {"coordinates":[6.5784730911,50.5654411316],"type":"Point"}
}