{
  "type": "Feature",
  "properties": {
    "iso:country":"DE",
    "sg:address":"Labradorstr. 5",
    "sg:city":"Bremerhaven",
    "sg:phone":"+49 471/97210",
    "sg:postcode":"27572",
    "sg:province":"Bremen",
    "wof:name":"J. Kramer Gmbh & Co. Kg",
    "wof:placetype":"venue"
},
  "geometry": {"coordinates":[8.5875120163,53.4983520508],"type":"Point"}
}