{
  "type": "Feature",
  "properties": {
    "iso:country":"DE",
    "sg:address":"Zweibr\u00fccker Str. 185",
    "sg:city":"Pirmasens",
    "sg:phone":"+49 6331/5280",
    "sg:postcode":"66954",
    "sg:province":"Rheinland-Pfalz",
    "wof:name":"Chemoplast Gmbh",
    "wof:placetype":"venue"
},
  "geometry": {"coordinates":[7.59377,49.21965],"type":"Point"}
}