{
  "type": "Feature",
  "properties": {
    "iso:country":"DE",
    "sg:address":"K\u00f6lner Str. 69",
    "sg:city":"R\u00fcsselsheim",
    "sg:phone":"+49 6142/50393",
    "sg:postcode":"65428",
    "sg:province":"Hessen",
    "wof:name":"Renate Schlick",
    "wof:placetype":"venue"
},
  "geometry": {"coordinates":[8.4318885803,50.0043106079],"type":"Point"}
}