{
  "type": "Feature",
  "properties": {
    "iso:country":"DE",
    "sg:address":"Gilsbacher Str. 10",
    "sg:city":"Burbach",
    "sg:postcode":"57299",
    "sg:province":"Nordrhein-Westfalen",
    "wof:name":"Diehl Gmbh",
    "wof:placetype":"venue"
},
  "geometry": {"coordinates":[8.0574007034,50.7595176697],"type":"Point"}
}