{
  "type": "Feature",
  "properties": {
    "iso:country":"DE",
    "sg:address":"Julienstr. 39",
    "sg:city":"Essen",
    "sg:phone":"+49 201/8775863",
    "sg:postcode":"45130",
    "sg:province":"Nordrhein-Westfalen",
    "wof:name":"Diakoniestationen Essen Ggmbh",
    "wof:placetype":"venue"
},
  "geometry": {"coordinates":[7.00948,51.435879],"type":"Point"}
}