{
  "type": "Feature",
  "properties": {
    "iso:country":"DE",
    "sg:address":"Hindenburgdamm 125",
    "sg:city":"Berlin",
    "sg:phone":"+49 30/84306480",
    "sg:postcode":"12203",
    "sg:province":"Berlin",
    "wof:name":"Gmc German Microcontroller Gmbh",
    "wof:placetype":"venue"
},
  "geometry": {"coordinates":[13.3121709824,52.4344444275],"type":"Point"}
}