{
  "type": "Feature",
  "properties": {
    "iso:country":"DE",
    "sg:address":"Dieselstr. 19",
    "sg:city":"Rosbach",
    "sg:phone":"+49 6003/91130",
    "sg:postcode":"61191",
    "sg:province":"Hessen",
    "wof:name":"Beem Blitz-elektro-erzeug- Nisse Manufaktur Handels- Gmbh",
    "wof:placetype":"venue"
},
  "geometry": {"coordinates":[8.6901054382,50.3032836914],"type":"Point"}
}