{
  "type": "Feature",
  "properties": {
    "iso:country":"DE",
    "sg:address":"Weidenweg 17b",
    "sg:city":"Wermelskirchen",
    "sg:phone":"+49 2196/95842",
    "sg:postcode":"42929",
    "sg:province":"Nordrhein-Westfalen",
    "wof:name":"Haco-rollen-vertrieb Gmbh",
    "wof:placetype":"venue"
},
  "geometry": {"coordinates":[7.1872358322,51.1202659607],"type":"Point"}
}