{
  "type": "Feature",
  "properties": {
    "iso:country":"DE",
    "sg:address":"Wiesenhof 6",
    "sg:city":"Hasenmoor",
    "sg:phone":"+49 4195/818",
    "sg:postcode":"24640",
    "sg:province":"Schleswig-Holstein",
    "wof:name":"H. Saggau",
    "wof:placetype":"venue"
},
  "geometry": {"coordinates":[10.009295,53.912907],"type":"Point"}
}