{
  "type": "Feature",
  "properties": {
    "iso:country":"DE",
    "sg:address":"S\u00fclldorfer Landstr. 162",
    "sg:city":"Hamburg",
    "sg:phone":"+49 40/8708780",
    "sg:postcode":"22589",
    "sg:province":"Hamburg",
    "wof:name":"As Kranken- Und Seniorenhilfe Gmbh",
    "wof:placetype":"venue"
},
  "geometry": {"coordinates":[9.802115,53.579659],"type":"Point"}
}