{
  "type": "Feature",
  "properties": {
    "iso:country":"DE",
    "sg:address":"Vorderer Steinb\u00fchl 24",
    "sg:city":"Zell",
    "sg:phone":"+49 9257/227",
    "sg:postcode":"95239",
    "sg:province":"Bayern",
    "wof:name":"Bertram Unglaub",
    "wof:placetype":"venue"
},
  "geometry": {"coordinates":[11.817365,50.137486],"type":"Point"}
}