{
  "type": "Feature",
  "properties": {
    "iso:country":"DE",
    "sg:address":"Bergmannweg 2",
    "sg:city":"Emmerting",
    "sg:phone":"+49 8679/4463",
    "sg:postcode":"84547",
    "sg:province":"Bayern",
    "wof:name":"Jakob Rauscher",
    "wof:placetype":"venue"
},
  "geometry": {"coordinates":[12.769596,48.207191],"type":"Point"}
}