{
  "type": "Feature",
  "properties": {
    "iso:country":"DE",
    "sg:address":"Talm\u00fchlenstr. 32",
    "sg:city":"Kurort Hartha",
    "sg:postcode":"01737",
    "sg:province":"Sachsen",
    "wof:name":"Soniclinks -- Die Seite Mit Infos Rund Um Computer",
    "wof:placetype":"venue"
},
  "geometry": {"coordinates":[13.550003,50.981949],"type":"Point"}
}