{
  "type": "Feature",
  "properties": {
    "iso:country":"DE",
    "sg:address":"Gro\u00dfe Gartenstr. 15",
    "sg:city":"Kl\u00f6tze",
    "sg:phone":"+49 3909/2527",
    "sg:postcode":"38486",
    "sg:province":"Sachsen-Anhalt",
    "wof:name":"Marlies Weik",
    "wof:placetype":"venue"
},
  "geometry": {"coordinates":[11.169312,52.6269],"type":"Point"}
}