{
  "type": "Feature",
  "properties": {
    "iso:country":"DE",
    "sg:address":"Spiridon-Louis-Ring 7",
    "sg:city":"M\u00fcnchen",
    "sg:phone":"+49 89/3066850",
    "sg:postcode":"80809",
    "sg:province":"Bayern",
    "wof:name":"Haberl Gastronomie Gmbh & Co Kg",
    "wof:placetype":"venue"
},
  "geometry": {"coordinates":[11.555073,48.174366],"type":"Point"}
}