{
  "type": "Feature",
  "properties": {
    "iso:country":"DE",
    "sg:address":"Rudolf-Diesel-Str. 2",
    "sg:city":"Konz",
    "sg:postcode":"54329",
    "sg:province":"Rheinland-Pfalz",
    "wof:name":"Hik-erlebnisgastronomie Gmbh",
    "wof:placetype":"venue"
},
  "geometry": {"coordinates":[6.563517,49.688744],"type":"Point"}
}