{
  "type": "Feature",
  "properties": {
    "iso:country":"DE",
    "sg:address":"Bruhnskoppeler Weg 45",
    "sg:city":"Malente",
    "sg:phone":"+49 4523/6042",
    "sg:postcode":"23714",
    "sg:province":"Schleswig-Holstein",
    "wof:name":"L\u00fchrs",
    "wof:placetype":"venue"
},
  "geometry": {"coordinates":[10.60732,54.193981],"type":"Point"}
}