{
  "type": "Feature",
  "properties": {
    "iso:country":"DE",
    "sg:address":"Lenzhalde 10",
    "sg:city":"Ostfildern",
    "sg:phone":"+49 7158/2245",
    "sg:postcode":"73760",
    "sg:province":"Baden-W\u00fcrttemberg",
    "wof:name":"Walter Maier Architekt",
    "wof:placetype":"venue"
},
  "geometry": {"coordinates":[9.268817,48.708103],"type":"Point"}
}