{
  "type": "Feature",
  "properties": {
    "iso:country":"DE",
    "sg:address":"Lagerstr. 3-5",
    "sg:city":"Meschede",
    "sg:phone":"+49 4929/199010",
    "sg:postcode":"59872",
    "sg:province":"Nordrhein-Westfalen",
    "wof:name":"Theodor Leisse Gmbh & Co Kg",
    "wof:placetype":"venue"
},
  "geometry": {"coordinates":[8.2735052109,51.3509750366],"type":"Point"}
}