{
  "type": "Feature",
  "properties": {
    "iso:country":"DE",
    "sg:address":"Andreasstr. 2",
    "sg:city":"D\u00fcsseldorf",
    "sg:phone":"+49 211/131163",
    "sg:postcode":"40213",
    "sg:province":"Nordrhein-Westfalen",
    "wof:name":"Restaurant Tante Anna",
    "wof:placetype":"venue"
},
  "geometry": {"coordinates":[6.7738490105,51.2271194458],"type":"Point"}
}