{
  "type": "Feature",
  "properties": {
    "iso:country":"DE",
    "sg:address":"Kreuzstr. 17",
    "sg:city":"Erding",
    "sg:phone":"+49 8122/189933",
    "sg:postcode":"85435",
    "sg:province":"Bayern",
    "wof:name":"Anton Beil",
    "wof:placetype":"venue"
},
  "geometry": {"coordinates":[11.923616,48.349468],"type":"Point"}
}