{
  "type": "Feature",
  "properties": {
    "iso:country":"DE",
    "sg:address":"Bramscher Str. 252",
    "sg:city":"Osnabr\u00fcck",
    "sg:phone":"+49 541/62475",
    "sg:postcode":"49090",
    "sg:province":"Niedersachsen",
    "wof:name":"Angler-shop Specht",
    "wof:placetype":"venue"
},
  "geometry": {"coordinates":[8.035915,52.300011],"type":"Point"}
}