{
  "type": "Feature",
  "properties": {
    "iso:country":"DE",
    "sg:address":"Putlitzer Str. 2",
    "sg:city":"Parchim",
    "sg:phone":"+49 3871/212168",
    "sg:postcode":"19370",
    "sg:province":"Mecklenburg-Vorpommern",
    "wof:name":"K. Bernhard Und L. Josl Rechtsanw\u00e4lte",
    "wof:placetype":"venue"
},
  "geometry": {"coordinates":[11.8419065475,53.4190406799],"type":"Point"}
}