{
  "type": "Feature",
  "properties": {
    "iso:country":"DE",
    "sg:address":"Natheweg 12",
    "sg:city":"Anr\u00f6chte",
    "sg:postcode":"59609",
    "sg:province":"Nordrhein-Westfalen",
    "wof:name":"Paul Orths",
    "wof:placetype":"venue"
},
  "geometry": {"coordinates":[8.3147907257,51.563331604],"type":"Point"}
}