{
  "type": "Feature",
  "properties": {
    "iso:country":"DE",
    "sg:address":"Welitsch 61",
    "sg:city":"Pressig",
    "sg:phone":"+49 9265/9633",
    "sg:postcode":"96332",
    "sg:province":"Bayern",
    "wof:name":"Radsport Krebs",
    "wof:placetype":"venue"
},
  "geometry": {"coordinates":[11.28555,50.350273],"type":"Point"}
}