{
  "type": "Feature",
  "properties": {
    "iso:country":"DE",
    "sg:address":"Schmiedstr. 30",
    "sg:city":"Herzogenrath",
    "sg:phone":"+49 2406/4779",
    "sg:postcode":"52134",
    "sg:province":"Nordrhein-Westfalen",
    "wof:name":"Johann Frohn",
    "wof:placetype":"venue"
},
  "geometry": {"coordinates":[6.113745,50.853893],"type":"Point"}
}