{
  "type": "Feature",
  "properties": {
    "iso:country":"DE",
    "sg:address":"Hauptstr. 35",
    "sg:city":"Sontheim",
    "sg:phone":"+49 7325/5231",
    "sg:postcode":"89567",
    "sg:province":"Baden-W\u00fcrttemberg",
    "wof:name":"A. Weeber",
    "wof:placetype":"venue"
},
  "geometry": {"coordinates":[10.351763,48.009415],"type":"Point"}
}