{
  "type": "Feature",
  "properties": {
    "iso:country":"DE",
    "sg:address":"R\u00f6merstr. 4",
    "sg:city":"Hartheim",
    "sg:phone":"+49 7633/160214",
    "sg:postcode":"79258",
    "sg:province":"Baden-W\u00fcrttemberg",
    "wof:name":"M. Rickenauer",
    "wof:placetype":"venue"
},
  "geometry": {"coordinates":[7.6455359459,47.9343948364],"type":"Point"}
}