{
  "type": "Feature",
  "properties": {
    "iso:country":"DE",
    "sg:address":"Kasinostr. 2",
    "sg:city":"K\u00f6ln",
    "sg:phone":"+49 221/2408480",
    "sg:postcode":"50676",
    "sg:province":"Nordrhein-Westfalen",
    "wof:name":"Gabriele Veithen",
    "wof:placetype":"venue"
},
  "geometry": {"coordinates":[6.9573898315,50.9342346191],"type":"Point"}
}