{
  "type": "Feature",
  "properties": {
    "iso:country":"DE",
    "sg:address":"Beimoor Hof Eichkamp",
    "sg:city":"Ahrensburg",
    "sg:phone":"+49 4102/42875",
    "sg:postcode":"22926",
    "sg:province":"Schleswig-Holstein",
    "wof:name":"Peter Reck",
    "wof:placetype":"venue"
},
  "geometry": {"coordinates":[10.278101,53.683208],"type":"Point"}
}