{
  "type": "Feature",
  "properties": {
    "iso:country":"DE",
    "sg:address":"Bahnhofstr. 17",
    "sg:city":"Passau",
    "sg:phone":"+49 851/51239",
    "sg:postcode":"94032",
    "sg:province":"Bayern",
    "wof:name":"Peter Stephani",
    "wof:placetype":"venue"
},
  "geometry": {"coordinates":[13.456,48.574081],"type":"Point"}
}