{
  "type": "Feature",
  "properties": {
    "iso:country":"DE",
    "sg:address":"Cranger Str. 36",
    "sg:city":"Gelsenkirchen",
    "sg:postcode":"45894",
    "sg:province":"Nordrhein-Westfalen",
    "wof:name":"Emballage Kartonagenvertriebs Gmbh",
    "wof:placetype":"venue"
},
  "geometry": {"coordinates":[7.0622401237,51.5748672485],"type":"Point"}
}