{
  "type": "Feature",
  "properties": {
    "iso:country":"DE",
    "sg:address":"Lohgasse 6",
    "sg:city":"Marburg",
    "sg:phone":"+49 6421/25904",
    "sg:postcode":"35043",
    "sg:province":"Hessen",
    "wof:name":"Gerhard Metzker Architekt",
    "wof:placetype":"venue"
},
  "geometry": {"coordinates":[8.828583,50.818207],"type":"Point"}
}