{
  "type": "Feature",
  "properties": {
    "iso:country":"DE",
    "sg:address":"Kaulbachstr. 9",
    "sg:city":"Bad Arolsen",
    "sg:phone":"+49 5691/91888",
    "sg:postcode":"34454",
    "sg:province":"Hessen",
    "wof:name":"Gante & Thiel",
    "wof:placetype":"venue"
},
  "geometry": {"coordinates":[9.0182914734,51.3795661926],"type":"Point"}
}