{
  "type": "Feature",
  "properties": {
    "iso:country":"DE",
    "sg:address":"Am Salgenholz 4",
    "sg:city":"Braunschweig",
    "sg:phone":"+49 5307/2964",
    "sg:postcode":"38110",
    "sg:province":"Niedersachsen",
    "wof:name":"August Kumler Stra\u00dfen- Und Tiefbau",
    "wof:placetype":"venue"
},
  "geometry": {"coordinates":[10.5206327438,52.3197593689],"type":"Point"}
}