{
  "type": "Feature",
  "properties": {
    "iso:country":"DE",
    "sg:address":"Werneckstr. 25",
    "sg:city":"M\u00fcnchen",
    "sg:phone":"+49 89/347124",
    "sg:postcode":"80802",
    "sg:province":"Bayern",
    "wof:name":"Andreas Homuth Rechtsanwalt",
    "wof:placetype":"venue"
},
  "geometry": {"coordinates":[11.588842392,48.1602554321],"type":"Point"}
}