{
  "type": "Feature",
  "properties": {
    "iso:country":"DE",
    "sg:address":"Weinbergstr. 6",
    "sg:city":"Eilenburg",
    "sg:phone":"+49 3423/602521",
    "sg:postcode":"04838",
    "sg:province":"Sachsen",
    "wof:name":"Stahlbau Gmbh",
    "wof:placetype":"venue"
},
  "geometry": {"coordinates":[12.622068,51.456741],"type":"Point"}
}