{
  "type": "Feature",
  "properties": {
    "iso:country":"DE",
    "sg:address":"Dorfstr. 18",
    "sg:city":"Paunzhausen",
    "sg:postcode":"85307",
    "sg:province":"Bayern",
    "wof:name":"Kurbis Pilsstubn",
    "wof:placetype":"venue"
},
  "geometry": {"coordinates":[11.5848302841,48.4654693604],"type":"Point"}
}