{
  "type": "Feature",
  "properties": {
    "iso:country":"DE",
    "sg:address":"Breite 52",
    "sg:city":"Zerbst",
    "sg:phone":"+49 3923/785023",
    "sg:postcode":"39261",
    "sg:province":"Sachsen-Anhalt",
    "wof:name":"Sylke Schmidt",
    "wof:placetype":"venue"
},
  "geometry": {"coordinates":[12.0899066925,51.9646911621],"type":"Point"}
}