{
  "type": "Feature",
  "properties": {
    "iso:country":"DE",
    "sg:address":"Akademiestr. 5",
    "sg:city":"M\u00fcnchen",
    "sg:phone":"+49 89/399550",
    "sg:postcode":"80799",
    "sg:province":"Bayern",
    "wof:name":"Am Siegestor",
    "wof:placetype":"venue"
},
  "geometry": {"coordinates":[11.5806741714,48.1523857117],"type":"Point"}
}