{
  "type": "Feature",
  "properties": {
    "iso:country":"DE",
    "sg:address":"Wesselstr. 12",
    "sg:city":"Bonn",
    "sg:phone":"+49 228/983960",
    "sg:postcode":"53113",
    "sg:province":"Nordrhein-Westfalen",
    "wof:name":"Ilka Keller Reiseb\u00fcro Gmbh",
    "wof:placetype":"venue"
},
  "geometry": {"coordinates":[7.1000618935,50.7327079773],"type":"Point"}
}