{
  "type": "Feature",
  "properties": {
    "iso:country":"DE",
    "sg:address":"Rautstr. 8",
    "sg:city":"Eschenlohe",
    "sg:phone":"+49 8824/94000",
    "sg:postcode":"82438",
    "sg:province":"Bayern",
    "wof:name":"Geophoto",
    "wof:placetype":"venue"
},
  "geometry": {"coordinates":[11.1864089966,47.5912132263],"type":"Point"}
}