{
  "type": "Feature",
  "properties": {
    "iso:country":"DE",
    "sg:address":"Sch\u00f6ninger Str. 10",
    "sg:city":"Helmstedt",
    "sg:phone":"+49 5351/1230",
    "sg:postcode":"38350",
    "sg:province":"Niedersachsen",
    "wof:name":"Avacon Ag",
    "wof:placetype":"venue"
},
  "geometry": {"coordinates":[11.006862,52.22121],"type":"Point"}
}