{
  "type": "Feature",
  "properties": {
    "iso:country":"DE",
    "sg:address":"Liebenwerdaer Str. 33",
    "sg:city":"M\u00fchlberg",
    "sg:phone":"+49 35342/525",
    "sg:postcode":"04931",
    "sg:province":"Brandenburg",
    "wof:name":"Ebelholz Gmbh",
    "wof:placetype":"venue"
},
  "geometry": {"coordinates":[13.221135,51.437695],"type":"Point"}
}