{
  "type": "Feature",
  "properties": {
    "iso:country":"DE",
    "sg:address":"Bonifaciusring 10",
    "sg:city":"Essen",
    "sg:phone":"+49 201/552173",
    "sg:postcode":"45309",
    "sg:province":"Nordrhein-Westfalen",
    "wof:name":"Pauly Kegelbahnbau Gmbh",
    "wof:placetype":"venue"
},
  "geometry": {"coordinates":[7.0875167847,51.4758338928],"type":"Point"}
}