{
  "type": "Feature",
  "properties": {
    "iso:country":"DE",
    "sg:address":"Ostwall 90",
    "sg:city":"Krefeld",
    "sg:phone":"+49 2151/618162",
    "sg:postcode":"47798",
    "sg:province":"Nordrhein-Westfalen",
    "wof:name":"Renate Fischer Heilpraktikerin",
    "wof:placetype":"venue"
},
  "geometry": {"coordinates":[6.5669698715,51.3300704956],"type":"Point"}
}