{
  "type": "Feature",
  "properties": {
    "iso:country":"DE",
    "sg:address":"Black-u.-Decker-Str 17c",
    "sg:city":"Idstein",
    "sg:phone":"+49 6126/93210",
    "sg:postcode":"65510",
    "sg:province":"Hessen",
    "wof:name":"Future Electronics Deutschland Gmbh",
    "wof:placetype":"venue"
},
  "geometry": {"coordinates":[8.2548398972,50.210899353],"type":"Point"}
}