{
  "type": "Feature",
  "properties": {
    "iso:country":"DE",
    "sg:address":"Thorkoppel 15 b",
    "sg:city":"Barsb\u00fcttel",
    "sg:phone":"+49 40/6700353",
    "sg:postcode":"22885",
    "sg:province":"Schleswig-Holstein",
    "wof:name":"Karl-heinz Ising",
    "wof:placetype":"venue"
},
  "geometry": {"coordinates":[10.1658735275,53.570892334],"type":"Point"}
}