{
  "type": "Feature",
  "properties": {
    "iso:country":"DE",
    "sg:address":"Industriestr. 62",
    "sg:city":"Burgau",
    "sg:phone":"+49 8222/2744",
    "sg:postcode":"89331",
    "sg:province":"Bayern",
    "wof:name":"Elisabeth Kreis",
    "wof:placetype":"venue"
},
  "geometry": {"coordinates":[10.4133529663,48.4391021729],"type":"Point"}
}