{
  "type": "Feature",
  "properties": {
    "iso:country":"DE",
    "sg:address":"Isarauer Str. 77",
    "sg:city":"Aholming",
    "sg:phone":"+49 9938/91910",
    "sg:postcode":"94527",
    "sg:province":"Bayern",
    "wof:name":"Muetec Automatisierte Mikroskopie & Messtechnik Gmbh",
    "wof:placetype":"venue"
},
  "geometry": {"coordinates":[12.905677,48.745857],"type":"Point"}
}