{
  "type": "Feature",
  "properties": {
    "iso:country":"DE",
    "sg:address":"Jakob-Kaiser-Str. 38",
    "sg:city":"Neuss",
    "sg:phone":"+49 2137/77409",
    "sg:postcode":"41470",
    "sg:province":"Nordrhein-Westfalen",
    "wof:name":"Cp Consult Gmbh",
    "wof:placetype":"venue"
},
  "geometry": {"coordinates":[6.731221199,51.1314468384],"type":"Point"}
}