{
  "type": "Feature",
  "properties": {
    "iso:country":"DE",
    "sg:address":"Soltauer Str. 40",
    "sg:city":"L\u00fcneburg",
    "sg:phone":"+49 4131/44091",
    "sg:postcode":"21335",
    "sg:province":"Niedersachsen",
    "wof:name":"W. Tobinsky Architekt",
    "wof:placetype":"venue"
},
  "geometry": {"coordinates":[10.398679,53.237236],"type":"Point"}
}