{
  "type": "Feature",
  "properties": {
    "iso:country":"DE",
    "sg:address":"Niedereschbacher Str 14",
    "sg:city":"Frankfurt",
    "sg:phone":"+49 6101/4571",
    "sg:postcode":"60437",
    "sg:province":"Hessen",
    "wof:name":"Mpt Metallbehandlung + Plasmatechnik Gmbh",
    "wof:placetype":"venue"
},
  "geometry": {"coordinates":[8.7047071457,50.2046661377],"type":"Point"}
}