{
  "type": "Feature",
  "properties": {
    "iso:country":"DE",
    "sg:address":"Schlo\u00dfstr. 3",
    "sg:city":"G\u00f6ppingen",
    "sg:phone":"+49 7161/684798",
    "sg:postcode":"73033",
    "sg:province":"Baden-W\u00fcrttemberg",
    "wof:name":"Vinoteca Georg Weidmann",
    "wof:placetype":"venue"
},
  "geometry": {"coordinates":[9.6505041122,48.7034339905],"type":"Point"}
}