{
  "type": "Feature",
  "properties": {
    "iso:country":"DE",
    "sg:address":"Miquelallee 5",
    "sg:city":"Frankfurt",
    "sg:phone":"+49 69/7073319",
    "sg:postcode":"60487",
    "sg:province":"Hessen",
    "wof:name":"Klaus G\u00fcnther",
    "wof:placetype":"venue"
},
  "geometry": {"coordinates":[8.6531476974,50.1258201599],"type":"Point"}
}