{
  "type": "Feature",
  "properties": {
    "iso:country":"DE",
    "sg:address":"Vinkrather Str. 2",
    "sg:city":"Grefrath",
    "sg:phone":"+49 2158/8584",
    "sg:postcode":"47929",
    "sg:province":"Nordrhein-Westfalen",
    "wof:name":"Ralf Hansen",
    "wof:placetype":"venue"
},
  "geometry": {"coordinates":[6.33907,51.3381],"type":"Point"}
}