{
  "type": "Feature",
  "properties": {
    "iso:country":"DE",
    "sg:address":"Lindenstr. 42",
    "sg:city":"Ehingen",
    "sg:phone":"+49 7391/2474",
    "sg:postcode":"89584",
    "sg:province":"Baden-W\u00fcrttemberg",
    "wof:name":"Karl Rommel Architekt",
    "wof:placetype":"venue"
},
  "geometry": {"coordinates":[9.72853,48.282909],"type":"Point"}
}