{
  "type": "Feature",
  "properties": {
    "iso:country":"DE",
    "sg:address":"Beeskower Str. 8",
    "sg:city":"Eisenh\u00fcttenstadt",
    "sg:phone":"+49 3364/4068200",
    "sg:postcode":"15890",
    "sg:province":"Brandenburg",
    "wof:name":"Wisbert Und Weiner Rechtsanw\u00e4lte",
    "wof:placetype":"venue"
},
  "geometry": {"coordinates":[14.6532793045,52.1480636597],"type":"Point"}
}