{
  "type": "Feature",
  "properties": {
    "iso:country":"DE",
    "sg:address":"Sedanstr. 8",
    "sg:city":"Sersheim",
    "sg:phone":"+49 7042/33480",
    "sg:postcode":"74372",
    "sg:province":"Baden-W\u00fcrttemberg",
    "wof:name":"Gasthof Sonne",
    "wof:placetype":"venue"
},
  "geometry": {"coordinates":[9.0127019882,48.9607009888],"type":"Point"}
}