{
  "type": "Feature",
  "properties": {
    "iso:country":"DE",
    "sg:address":"Philosophenweg 30",
    "sg:city":"T\u00fcbingen",
    "sg:phone":"+49 7071/61738",
    "sg:postcode":"72076",
    "sg:province":"Baden-W\u00fcrttemberg",
    "wof:name":"R. Friesch Mech. Werkstatt",
    "wof:placetype":"venue"
},
  "geometry": {"coordinates":[9.050919,48.536346],"type":"Point"}
}