{
  "type": "Feature",
  "properties": {
    "iso:country":"DE",
    "sg:address":"Hauptstr. 25",
    "sg:city":"Reichshof",
    "sg:phone":"+49 2296/235",
    "sg:postcode":"51580",
    "sg:province":"Nordrhein-Westfalen",
    "wof:name":"Hotel Denklinger Hof",
    "wof:placetype":"venue"
},
  "geometry": {"coordinates":[7.6555099487,50.9147148132],"type":"Point"}
}