{
  "type": "Feature",
  "properties": {
    "iso:country":"DE",
    "sg:address":"Kapellenplatz 35",
    "sg:city":"Kevelaer",
    "sg:phone":"+49 2832/6031",
    "sg:postcode":"47623",
    "sg:province":"Nordrhein-Westfalen",
    "wof:name":"Katholisches Pfarramt St. Marien",
    "wof:placetype":"venue"
},
  "geometry": {"coordinates":[6.2438731194,51.5843353271],"type":"Point"}
}