{
  "type": "Feature",
  "properties": {
    "iso:country":"DE",
    "sg:address":"Schwerborner Str. 29a",
    "sg:city":"Erfurt",
    "sg:phone":"+49 361/71008",
    "sg:postcode":"99087",
    "sg:province":"Th\u00fcringen",
    "wof:name":"Orga Lab Th\u00fcringen Gmbh",
    "wof:placetype":"venue"
},
  "geometry": {"coordinates":[11.0280971527,51.0164794922],"type":"Point"}
}