{
  "type": "Feature",
  "properties": {
    "iso:country":"DE",
    "sg:address":"B\u00f6rlner Str. 2",
    "sg:city":"Dahlen",
    "sg:phone":"+49 34361/51369",
    "sg:postcode":"04774",
    "sg:province":"Sachsen",
    "wof:name":"Fr\u00f6hlich",
    "wof:placetype":"venue"
},
  "geometry": {"coordinates":[12.9509496689,51.4133491516],"type":"Point"}
}