{
  "type": "Feature",
  "properties": {
    "iso:country":"DE",
    "sg:address":"Hamborner Altmarkt 1-3",
    "sg:city":"Duisburg",
    "sg:postcode":"47166",
    "sg:province":"Nordrhein-Westfalen",
    "wof:name":"Horst Huber",
    "wof:placetype":"venue"
},
  "geometry": {"coordinates":[6.77298,51.48983],"type":"Point"}
}