{
  "type": "Feature",
  "properties": {
    "iso:country":"DE",
    "sg:address":"Hauptstr. 34",
    "sg:city":"Moosinning",
    "sg:phone":"+49 8123/9144",
    "sg:postcode":"85452",
    "sg:province":"Bayern",
    "wof:name":"Sumetzberger Ges. Mbh",
    "wof:placetype":"venue"
},
  "geometry": {"coordinates":[11.7983236313,48.2775268555],"type":"Point"}
}