{
  "type": "Feature",
  "properties": {
    "iso:country":"DE",
    "sg:address":"Allerheiligenstr. 8",
    "sg:city":"Ottenh\u00f6fen",
    "sg:phone":"+49 7842/30876",
    "sg:postcode":"77883",
    "sg:province":"Baden-W\u00fcrttemberg",
    "wof:name":"Adler",
    "wof:placetype":"venue"
},
  "geometry": {"coordinates":[8.1524572372,48.5666618347],"type":"Point"}
}