{
  "type": "Feature",
  "properties": {
    "iso:country":"DE",
    "sg:address":"F\u00fcrstenberger Str. 4a",
    "sg:city":"Feldberg",
    "sg:phone":"+49 39831/20019",
    "sg:postcode":"17258",
    "sg:province":"Mecklenburg-Vorpommern",
    "wof:name":"Ital. Eiscafe",
    "wof:placetype":"venue"
},
  "geometry": {"coordinates":[13.439394,53.335724],"type":"Point"}
}