{
  "type": "Feature",
  "properties": {
    "iso:country":"DE",
    "sg:address":"Senefelderstr. 95",
    "sg:city":"Stuttgart",
    "sg:phone":"+49 711/6364971",
    "sg:postcode":"70176",
    "sg:province":"Baden-W\u00fcrttemberg",
    "wof:name":"Ursula Weber-wanner Architektin",
    "wof:placetype":"venue"
},
  "geometry": {"coordinates":[9.157746,48.779419],"type":"Point"}
}