{
  "type": "Feature",
  "properties": {
    "iso:country":"DE",
    "sg:address":"Clevischer Ring 5",
    "sg:city":"K\u00f6ln",
    "sg:phone":"+49 221/626189",
    "sg:postcode":"51065",
    "sg:province":"Nordrhein-Westfalen",
    "wof:name":"Musiktreff 5",
    "wof:placetype":"venue"
},
  "geometry": {"coordinates":[7.0044670105,50.962890625],"type":"Point"}
}