{
  "type": "Feature",
  "properties": {
    "iso:country":"DE",
    "sg:address":"Bahnhofstr. 49",
    "sg:city":"Gie\u00dfen",
    "sg:phone":"+49 641/77078",
    "sg:postcode":"35390",
    "sg:province":"Hessen",
    "wof:name":"Kirschstein-freund U. Kollegen Rechtsanw\u00e4lte Und Notare",
    "wof:placetype":"venue"
},
  "geometry": {"coordinates":[8.6686649323,50.5836143494],"type":"Point"}
}