{
  "type": "Feature",
  "properties": {
    "iso:country":"DE",
    "sg:address":"Zugspitzstr. 97",
    "sg:city":"Grainau",
    "sg:phone":"+49 8821/98019",
    "sg:postcode":"82491",
    "sg:province":"Bayern",
    "wof:name":"Reinhard Bartlechner Architekt",
    "wof:placetype":"venue"
},
  "geometry": {"coordinates":[11.041621,47.471344],"type":"Point"}
}