{
  "type": "Feature",
  "properties": {
    "iso:country":"DE",
    "sg:address":"Jathostr. 9",
    "sg:city":"Isernhagen",
    "sg:phone":"+49 511/6151650",
    "sg:postcode":"30916",
    "sg:province":"Niedersachsen",
    "wof:name":"J\u00fcrgen Scharlach Architekt",
    "wof:placetype":"venue"
},
  "geometry": {"coordinates":[9.833167,52.431107],"type":"Point"}
}