{
  "type": "Feature",
  "properties": {
    "iso:country":"DE",
    "sg:address":"Alsheimer Weg 3",
    "sg:city":"Plankstadt",
    "sg:phone":"+49 6202/17487",
    "sg:postcode":"68723",
    "sg:province":"Baden-W\u00fcrttemberg",
    "wof:name":"Walter Mack",
    "wof:placetype":"venue"
},
  "geometry": {"coordinates":[8.602227,49.383892],"type":"Point"}
}