{
  "type": "Feature",
  "properties": {
    "iso:country":"DE",
    "sg:address":"Wingertstr. 13",
    "sg:city":"Nalbach",
    "sg:phone":"+49 6838/92969",
    "sg:postcode":"66809",
    "sg:province":"Saarland",
    "wof:name":"Raphael Besser",
    "wof:placetype":"venue"
},
  "geometry": {"coordinates":[6.834584,49.389503],"type":"Point"}
}