{
  "type": "Feature",
  "properties": {
    "iso:country":"DE",
    "sg:address":"Mohrenstr. 2",
    "sg:city":"Wittenberge",
    "sg:phone":"+49 3877/66258",
    "sg:postcode":"19322",
    "sg:province":"Brandenburg",
    "wof:name":"Kago Baugesellschaft Mbh",
    "wof:placetype":"venue"
},
  "geometry": {"coordinates":[11.753587,52.994591],"type":"Point"}
}