{
  "type": "Feature",
  "properties": {
    "iso:country":"DE",
    "sg:address":"Weidestr. 23",
    "sg:city":"Eutin",
    "sg:phone":"+49 4521/71515",
    "sg:postcode":"23701",
    "sg:province":"Schleswig-Holstein",
    "wof:name":"Bielke Und Struve Architekten",
    "wof:placetype":"venue"
},
  "geometry": {"coordinates":[10.617167,54.131512],"type":"Point"}
}