{
  "type": "Feature",
  "properties": {
    "iso:country":"DE",
    "sg:address":"J\u00e4gerstr. 13",
    "sg:city":"Ibbenb\u00fcren",
    "sg:phone":"+49 5451/78271",
    "sg:postcode":"49479",
    "sg:province":"Nordrhein-Westfalen",
    "wof:name":"Habichtsh\u00f6he",
    "wof:placetype":"venue"
},
  "geometry": {"coordinates":[7.7536129951,52.2790298462],"type":"Point"}
}