{
  "type": "Feature",
  "properties": {
    "iso:country":"DE",
    "sg:address":"Bahnhofplatz 5",
    "sg:city":"Pforzheim",
    "sg:phone":"+49 7231/351716",
    "sg:postcode":"75175",
    "sg:province":"Baden-W\u00fcrttemberg",
    "wof:name":"Bistro Spieloase Fascination",
    "wof:placetype":"venue"
},
  "geometry": {"coordinates":[8.7033348083,48.8931617737],"type":"Point"}
}