{
  "type": "Feature",
  "properties": {
    "iso:country":"DE",
    "sg:address":"Kaiserstr. 23",
    "sg:city":"Linkenheim-Hochstetten",
    "sg:phone":"+49 7247/7337",
    "sg:postcode":"76351",
    "sg:province":"Baden-W\u00fcrttemberg",
    "wof:name":"E. Geigle",
    "wof:placetype":"venue"
},
  "geometry": {"coordinates":[8.4127807617,49.1235733032],"type":"Point"}
}