{
  "type": "Feature",
  "properties": {
    "iso:country":"DE",
    "sg:address":"Hersbrucker Str. 62",
    "sg:city":"Lauf",
    "sg:phone":"+49 9123/99567",
    "sg:postcode":"91207",
    "sg:province":"Bayern",
    "wof:name":"Hartmann",
    "wof:placetype":"venue"
},
  "geometry": {"coordinates":[11.2896089554,49.5155982971],"type":"Point"}
}