{
  "type": "Feature",
  "properties": {
    "iso:country":"DE",
    "sg:address":"Saarstr. 107",
    "sg:city":"Trier",
    "sg:phone":"+49 651/32648",
    "sg:postcode":"54290",
    "sg:province":"Rheinland-Pfalz",
    "wof:name":"M. F\u00f6hr",
    "wof:placetype":"venue"
},
  "geometry": {"coordinates":[6.6344251633,49.7438468933],"type":"Point"}
}