{
  "type": "Feature",
  "properties": {
    "iso:country":"DE",
    "sg:address":"Teichstr. 17",
    "sg:city":"Merseburg",
    "sg:phone":"+49 3461/213508",
    "sg:postcode":"06217",
    "sg:province":"Sachsen-Anhalt",
    "wof:name":"Gudrun Sch\u00f6ppenthau",
    "wof:placetype":"venue"
},
  "geometry": {"coordinates":[11.990477562,51.353805542],"type":"Point"}
}