{
  "type": "Feature",
  "properties": {
    "iso:country":"DE",
    "sg:address":"Buchenrain 100",
    "sg:city":"G\u00f6ppingen",
    "sg:phone":"+49 7161/811203",
    "sg:postcode":"73037",
    "sg:province":"Baden-W\u00fcrttemberg",
    "wof:name":"Kath. Pfarramt Hl. Geist",
    "wof:placetype":"venue"
},
  "geometry": {"coordinates":[9.6917228699,48.6641082764],"type":"Point"}
}