{
  "type": "Feature",
  "properties": {
    "iso:country":"DE",
    "sg:address":"Schlo\u00dfstr. 40",
    "sg:city":"Hessisch Lichtenau",
    "sg:phone":"+49 5602/5822",
    "sg:postcode":"37235",
    "sg:province":"Hessen",
    "wof:name":"Heinrich Heussner",
    "wof:placetype":"venue"
},
  "geometry": {"coordinates":[9.779264,51.160389],"type":"Point"}
}