{
  "type": "Feature",
  "properties": {
    "iso:country":"DE",
    "sg:address":"Pfarrstr. 4",
    "sg:city":"Oberkotzau",
    "sg:phone":"+49 9286/249",
    "sg:postcode":"95145",
    "sg:province":"Bayern",
    "wof:name":"Ev. Luth. Pfarramt",
    "wof:placetype":"venue"
},
  "geometry": {"coordinates":[11.9336414337,50.263710022],"type":"Point"}
}