{
  "type": "Feature",
  "properties": {
    "iso:country":"DE",
    "sg:address":"Friedrichshagener Str. 9",
    "sg:city":"Berlin",
    "sg:phone":"+49 30/6934830",
    "sg:postcode":"12555",
    "sg:province":"Berlin",
    "wof:name":"Deutscher System-vertrieb Alexander Schneider",
    "wof:placetype":"venue"
},
  "geometry": {"coordinates":[13.584439,52.45158],"type":"Point"}
}