{
  "type": "Feature",
  "properties": {
    "iso:country":"DE",
    "sg:address":"Plantage 9",
    "sg:city":"Bremen",
    "sg:phone":"+49 421/377880",
    "sg:postcode":"28215",
    "sg:province":"Bremen",
    "wof:name":"Albert D. Domeyer Gmbh & Co.",
    "wof:placetype":"venue"
},
  "geometry": {"coordinates":[8.805445,53.088383],"type":"Point"}
}