{
  "type": "Feature",
  "properties": {
    "iso:country":"DE",
    "sg:address":"Max-Eyth-Str. 15",
    "sg:city":"Frickenhausen",
    "sg:phone":"+49 7022/946020",
    "sg:postcode":"72636",
    "sg:province":"Baden-W\u00fcrttemberg",
    "wof:name":"Gebra-gitterrostbau Gmbh",
    "wof:placetype":"venue"
},
  "geometry": {"coordinates":[9.3459672928,48.5881385803],"type":"Point"}
}