{
  "type": "Feature",
  "properties": {
    "iso:country":"DE",
    "sg:address":"Am Weyer 1c",
    "sg:city":"Mainz-Kastel",
    "sg:phone":"+49 6134/24344",
    "sg:postcode":"55252",
    "sg:province":"Hessen",
    "wof:name":"Udo Lahmer Gmbh",
    "wof:placetype":"venue"
},
  "geometry": {"coordinates":[8.287721,50.016899],"type":"Point"}
}