{
  "type": "Feature",
  "properties": {
    "iso:country":"DE",
    "sg:address":"Kurf\u00fcrstenstr 114",
    "sg:city":"Berlin",
    "sg:phone":"+49 30/2132097",
    "sg:postcode":"10787",
    "sg:province":"Berlin",
    "wof:name":"Action Werbeagentur Haberland & Schrader Gmbh",
    "wof:placetype":"venue"
},
  "geometry": {"coordinates":[13.347057,52.503559],"type":"Point"}
}