{
  "type": "Feature",
  "properties": {
    "iso:country":"DE",
    "sg:address":"Gartenstr. 11",
    "sg:city":"Elsterberg",
    "sg:phone":"+49 36621/20373",
    "sg:postcode":"07985",
    "sg:province":"Th\u00fcringen",
    "wof:name":"Dieter R\u00f6hr",
    "wof:placetype":"venue"
},
  "geometry": {"coordinates":[12.169525,50.607071],"type":"Point"}
}