{
  "type": "Feature",
  "properties": {
    "iso:country":"DE",
    "sg:address":"Imhofstr. 78",
    "sg:city":"Augsburg",
    "sg:phone":"+49 821/36266",
    "sg:postcode":"86159",
    "sg:province":"Bayern",
    "wof:name":"Peter Stephan Steuerberater",
    "wof:placetype":"venue"
},
  "geometry": {"coordinates":[10.8817224503,48.3546638489],"type":"Point"}
}