{
  "type": "Feature",
  "properties": {
    "iso:country":"DE",
    "sg:address":"Ebereschenallee 36",
    "sg:city":"Berlin",
    "sg:phone":"+49 30/3040900",
    "sg:postcode":"14050",
    "sg:province":"Berlin",
    "wof:name":"Brigitte Genrich Immobiliemaklerin",
    "wof:placetype":"venue"
},
  "geometry": {"coordinates":[13.2666893005,52.5158843994],"type":"Point"}
}