{
  "type": "Feature",
  "properties": {
    "iso:country":"DE",
    "sg:address":"Hanrathsweg 6",
    "sg:city":"Geldern",
    "sg:phone":"+49 2831/3777",
    "sg:postcode":"47608",
    "sg:province":"Nordrhein-Westfalen",
    "wof:name":"Rpm Reiter Projektmanagement Gmbh",
    "wof:placetype":"venue"
},
  "geometry": {"coordinates":[6.342865,51.497875],"type":"Point"}
}