{
  "type": "Feature",
  "properties": {
    "iso:country":"DE",
    "sg:address":"Wilhelm-Leuschner-Str. 243",
    "sg:city":"Griesheim",
    "sg:postcode":"64347",
    "sg:province":"Hessen",
    "wof:name":"Baubetreuung Hartmann Gmbh",
    "wof:placetype":"venue"
},
  "geometry": {"coordinates":[8.584585,49.863403],"type":"Point"}
}