{
  "type": "Feature",
  "properties": {
    "iso:country":"DE",
    "sg:address":"Leipziger Str. 14",
    "sg:city":"Frankfurt",
    "sg:phone":"+49 69/702419",
    "sg:postcode":"60487",
    "sg:province":"Hessen",
    "wof:name":"Idea Die Gr\u00fcne Drogerie Gmbh",
    "wof:placetype":"venue"
},
  "geometry": {"coordinates":[8.649095,50.121006],"type":"Point"}
}