{
  "type": "Feature",
  "properties": {
    "iso:country":"DE",
    "sg:address":"Helmholtzstr. 61",
    "sg:city":"Oberhausen",
    "sg:phone":"+49 208/807576",
    "sg:postcode":"46045",
    "sg:province":"Nordrhein-Westfalen",
    "wof:name":"Optik Birfelder E. Kfr.",
    "wof:placetype":"venue"
},
  "geometry": {"coordinates":[6.8542189598,51.469959259],"type":"Point"}
}