{
  "type": "Feature",
  "properties": {
    "iso:country":"DE",
    "sg:address":"Friedrich-Ebert-Str. 36",
    "sg:city":"Kassel",
    "sg:phone":"+49 561/772933",
    "sg:postcode":"34117",
    "sg:province":"Hessen",
    "wof:name":"China-restaurant Hong Kong",
    "wof:placetype":"venue"
},
  "geometry": {"coordinates":[9.4842128754,51.3149108887],"type":"Point"}
}