{
  "type": "Feature",
  "properties": {
    "iso:country":"DE",
    "sg:address":"Ebinger Str. 61",
    "sg:city":"Balingen",
    "sg:phone":"+49 7433/381827",
    "sg:postcode":"72336",
    "sg:province":"Baden-W\u00fcrttemberg",
    "wof:name":"R. Wolf",
    "wof:placetype":"venue"
},
  "geometry": {"coordinates":[8.8885183334,48.2394828796],"type":"Point"}
}