{
  "type": "Feature",
  "properties": {
    "iso:country":"DE",
    "sg:address":"B\u00f6tzowstr. 23",
    "sg:city":"Berlin",
    "sg:phone":"+49 30/4257627",
    "sg:postcode":"10407",
    "sg:province":"Berlin",
    "wof:name":"Thomas Neumann",
    "wof:placetype":"venue"
},
  "geometry": {"coordinates":[13.433175087,52.531124115],"type":"Point"}
}