{
  "type": "Feature",
  "properties": {
    "iso:country":"DE",
    "sg:address":"Zu den Tannen 2",
    "sg:city":"Friesoythe",
    "sg:phone":"+49 4496/466",
    "sg:postcode":"26169",
    "sg:province":"Niedersachsen",
    "wof:name":"B. Baumann",
    "wof:placetype":"venue"
},
  "geometry": {"coordinates":[7.9050087929,53.0465278625],"type":"Point"}
}