{
  "type": "Feature",
  "properties": {
    "iso:country":"DE",
    "sg:address":"Ernst-Schneller-Str. 17",
    "sg:city":"M\u00fclsen",
    "sg:phone":"+49 37601/2775",
    "sg:postcode":"08132",
    "sg:province":"Sachsen",
    "wof:name":"Jens Heine",
    "wof:placetype":"venue"
},
  "geometry": {"coordinates":[12.5778493881,50.7285423279],"type":"Point"}
}