{
  "type": "Feature",
  "properties": {
    "iso:country":"DE",
    "sg:address":"Krickelsdorf 5",
    "sg:city":"Hirschau",
    "sg:phone":"+49 9622/2130",
    "sg:postcode":"92242",
    "sg:province":"Bayern",
    "wof:name":"Sieglinde Wittmann",
    "wof:placetype":"venue"
},
  "geometry": {"coordinates":[11.887131691,49.561000824],"type":"Point"}
}