{
  "type": "Feature",
  "properties": {
    "iso:country":"DE",
    "sg:address":"Forststr. 23",
    "sg:city":"Berlin",
    "sg:phone":"+49 30/8213310",
    "sg:postcode":"12163",
    "sg:province":"Berlin",
    "wof:name":"Wolfram Pichler Ingenieur",
    "wof:placetype":"venue"
},
  "geometry": {"coordinates":[13.3113088608,52.4653282166],"type":"Point"}
}