{
  "type": "Feature",
  "properties": {
    "iso:country":"DE",
    "sg:address":"Neumarkter Str. 14 a",
    "sg:city":"Allersberg",
    "sg:phone":"+49 9176/444",
    "sg:postcode":"90584",
    "sg:province":"Bayern",
    "wof:name":"Leitner Gmbh & Co. Touristik Kg",
    "wof:placetype":"venue"
},
  "geometry": {"coordinates":[11.2407798767,49.2523994446],"type":"Point"}
}