{
  "type": "Feature",
  "properties": {
    "iso:country":"DE",
    "sg:address":"Hochstr. 86",
    "sg:city":"Saarlouis",
    "sg:phone":"+49 178 4379633",
    "sg:postcode":"66740",
    "sg:province":"Saarland",
    "wof:name":"Saarland Handy Verkauf Vertrieb Handel Nokia",
    "wof:placetype":"venue"
},
  "geometry": {"coordinates":[6.747689,49.338303],"type":"Point"}
}