{
  "type": "Feature",
  "properties": {
    "iso:country":"DE",
    "sg:address":"Avendorfer Weg 87",
    "sg:city":"Tespe",
    "sg:phone":"+49 4176/94940",
    "sg:postcode":"21395",
    "sg:province":"Niedersachsen",
    "wof:name":"Hans E. Wahle Gmbh",
    "wof:placetype":"venue"
},
  "geometry": {"coordinates":[10.4218320847,53.3861351013],"type":"Point"}
}