{
  "type": "Feature",
  "properties": {
    "iso:country":"DE",
    "sg:address":"K\u00f6nigstr. 17",
    "sg:city":"Elmshorn",
    "sg:phone":"+49 4121/423734",
    "sg:postcode":"25335",
    "sg:province":"Schleswig-Holstein",
    "wof:name":"Hinsenkamp Und Kr\u00fcger Rechtsanw\u00e4lte",
    "wof:placetype":"venue"
},
  "geometry": {"coordinates":[9.6570243835,53.7540283203],"type":"Point"}
}