{
  "type": "Feature",
  "properties": {
    "iso:country":"DE",
    "sg:address":"Augstbergstra\u00dfe 22",
    "sg:city":"Grenzach Wyhlen",
    "sg:postcode":"79639",
    "sg:province":"Baden-W\u00fcrttemberg",
    "wof:name":"Partnervermittlung Angelika Schr\u00f6ter",
    "wof:placetype":"venue"
},
  "geometry": {"coordinates":[7.7057609558,47.5478248596],"type":"Point"}
}