{
  "type": "Feature",
  "properties": {
    "iso:country":"DE",
    "sg:address":"Balger Hauptstr. 68",
    "sg:city":"Baden-Baden",
    "sg:phone":"+49 7221/50670",
    "sg:postcode":"76532",
    "sg:province":"Baden-W\u00fcrttemberg",
    "wof:name":"Blume",
    "wof:placetype":"venue"
},
  "geometry": {"coordinates":[8.2253322601,48.7881546021],"type":"Point"}
}