{
  "type": "Feature",
  "properties": {
    "iso:country":"DE",
    "sg:address":"Heinrich-Mann-Allee 103::",
    "sg:city":"Potsdam",
    "sg:phone":"+49 4933/18660",
    "sg:postcode":"14473",
    "sg:province":"Brandenburg",
    "wof:name":"Ministerium Fuer Arbeit, Soziales, Gesundheit U Frauen Des Landes Bran",
    "wof:placetype":"venue"
},
  "geometry": {"coordinates":[13.074541,52.383911],"type":"Point"}
}