{
  "type": "Feature",
  "properties": {
    "iso:country":"DE",
    "sg:address":"Ingolst\u00e4dter Str. 23",
    "sg:city":"Beilngries",
    "sg:phone":"+49 8461/9216",
    "sg:postcode":"92339",
    "sg:province":"Bayern",
    "wof:name":"Obornik",
    "wof:placetype":"venue"
},
  "geometry": {"coordinates":[11.477817,49.029766],"type":"Point"}
}