{
  "type": "Feature",
  "properties": {
    "iso:country":"DE",
    "sg:address":"Gartenstr. 4",
    "sg:city":"Bohmte",
    "sg:postcode":"49163",
    "sg:province":"Niedersachsen",
    "wof:name":"Necu Verwaltungs-gmbh",
    "wof:placetype":"venue"
},
  "geometry": {"coordinates":[8.309013,52.36018],"type":"Point"}
}