{
  "type": "Feature",
  "properties": {
    "iso:country":"DE",
    "sg:address":"Ortrander Str. 5",
    "sg:city":"Ruhland",
    "sg:phone":"+49 35752/2233",
    "sg:postcode":"01945",
    "sg:province":"Brandenburg",
    "wof:name":"Sch\u00fctzenhaus Inh. Monika Olden",
    "wof:placetype":"venue"
},
  "geometry": {"coordinates":[13.8558063507,51.4561843872],"type":"Point"}
}