{
  "type": "Feature",
  "properties": {
    "iso:country":"DE",
    "sg:address":"Heuchelheimer Str. 15",
    "sg:city":"Bad Homburg",
    "sg:phone":"+49 6172/37188",
    "sg:postcode":"61348",
    "sg:province":"Hessen",
    "wof:name":"Ibu Verwaltungs-gmbh",
    "wof:placetype":"venue"
},
  "geometry": {"coordinates":[8.6068,50.226871],"type":"Point"}
}