{
  "type": "Feature",
  "properties": {
    "iso:country":"DE",
    "sg:address":"Obere Karlsstr. 17",
    "sg:city":"Kassel",
    "sg:postcode":"34117",
    "sg:province":"Hessen",
    "wof:name":"Mennickheim Bestattungen- Zweigniederlassung Der",
    "wof:placetype":"venue"
},
  "geometry": {"coordinates":[9.494913,51.312786],"type":"Point"}
}