{
  "type": "Feature",
  "properties": {
    "iso:country":"DE",
    "sg:address":"Chiemseestr. 10",
    "sg:city":"Halfing",
    "sg:phone":"+49 8055/8951",
    "sg:postcode":"83128",
    "sg:province":"Bayern",
    "wof:name":"Helmut Langer",
    "wof:placetype":"venue"
},
  "geometry": {"coordinates":[12.2767858505,47.9506263733],"type":"Point"}
}