{
  "type": "Feature",
  "properties": {
    "iso:country":"DE",
    "sg:address":"Gemeindeberg 1",
    "sg:city":"Zschorlau",
    "sg:phone":"+49 3771/458148",
    "sg:postcode":"08321",
    "sg:province":"Sachsen",
    "wof:name":"Werner Lorenz",
    "wof:placetype":"venue"
},
  "geometry": {"coordinates":[12.6594820023,50.5780754089],"type":"Point"}
}