{
  "type": "Feature",
  "properties": {
    "iso:country":"DE",
    "sg:address":"Marienh\u00f6he 15",
    "sg:city":"Wickede",
    "sg:phone":"+49 2377/786816",
    "sg:postcode":"58739",
    "sg:province":"Nordrhein-Westfalen",
    "wof:name":"R\u00f6seler Industrieberatung Gmbh",
    "wof:placetype":"venue"
},
  "geometry": {"coordinates":[7.908456,51.495846],"type":"Point"}
}