{
  "type": "Feature",
  "properties": {
    "iso:country":"DE",
    "sg:address":"Sarkwitzer Str. 36",
    "sg:city":"Pansdorf",
    "sg:phone":"+49 4504/81240",
    "sg:postcode":"23689",
    "sg:province":"Schleswig-Holstein",
    "wof:name":"Kalksabdsteinwerke Panten Gmbh & Co.",
    "wof:placetype":"venue"
},
  "geometry": {"coordinates":[10.706580162,53.986125946],"type":"Point"}
}