{
  "type": "Feature",
  "properties": {
    "iso:country":"DE",
    "sg:address":"Markt 21",
    "sg:city":"Grimma",
    "sg:phone":"+49 3437/919732",
    "sg:postcode":"04668",
    "sg:province":"Sachsen",
    "wof:name":"Barbara Henkel",
    "wof:placetype":"venue"
},
  "geometry": {"coordinates":[12.7287817001,51.236240387],"type":"Point"}
}