{
  "type": "Feature",
  "properties": {
    "iso:country":"DE",
    "sg:address":"Buchenweg 6",
    "sg:city":"Kirchwalsede",
    "sg:phone":"+49 4269/1204",
    "sg:postcode":"27386",
    "sg:province":"Niedersachsen",
    "wof:name":"Helmut Wischmann",
    "wof:placetype":"venue"
},
  "geometry": {"coordinates":[9.392519,53.019707],"type":"Point"}
}