{
  "type": "Feature",
  "properties": {
    "iso:country":"DE",
    "sg:address":"Weidenauer Str. 96",
    "sg:city":"Siegen",
    "sg:phone":"+49 271/790671",
    "sg:postcode":"57076",
    "sg:province":"Nordrhein-Westfalen",
    "wof:name":"Landwehr & Stinner",
    "wof:placetype":"venue"
},
  "geometry": {"coordinates":[8.0229692459,50.902256012],"type":"Point"}
}