{
  "type": "Feature",
  "properties": {
    "iso:country":"DE",
    "sg:address":"Aufkirchner Str. 5",
    "sg:city":"Berg",
    "sg:phone":"+49 8151/50061",
    "sg:postcode":"82335",
    "sg:province":"Bayern",
    "wof:name":"Kreissparkasse Starnberg",
    "wof:placetype":"venue"
},
  "geometry": {"coordinates":[11.356844,47.966061],"type":"Point"}
}