{
  "type": "Feature",
  "properties": {
    "iso:country":"DE",
    "sg:address":"Max-Matern-Str. 3",
    "sg:city":"Eggesin",
    "sg:phone":"+49 39779/21194",
    "sg:postcode":"17367",
    "sg:province":"Mecklenburg-Vorpommern",
    "wof:name":"H. Strehlau",
    "wof:placetype":"venue"
},
  "geometry": {"coordinates":[14.0837459564,53.6782112122],"type":"Point"}
}