{
  "type": "Feature",
  "properties": {
    "iso:country":"DE",
    "sg:address":"Rurstr. 78",
    "sg:city":"Pulheim",
    "sg:phone":"+49 2238/55774",
    "sg:postcode":"50259",
    "sg:province":"Nordrhein-Westfalen",
    "wof:name":"Graf Ingenieur",
    "wof:placetype":"venue"
},
  "geometry": {"coordinates":[6.8227548599,51.0201034546],"type":"Point"}
}