{
  "type": "Feature",
  "properties": {
    "iso:country":"DE",
    "sg:address":"Obernstr. 16",
    "sg:city":"Bremen",
    "sg:phone":"+49 421/321039",
    "sg:postcode":"28195",
    "sg:province":"Bremen",
    "wof:name":"Dr. Peter Aselmann Rechtsanwalt Und Notar",
    "wof:placetype":"venue"
},
  "geometry": {"coordinates":[8.8059234619,53.0767211914],"type":"Point"}
}