{
  "type": "Feature",
  "properties": {
    "iso:country":"DE",
    "sg:address":"Lehrer Str. 3",
    "sg:city":"Ulm",
    "sg:phone":"+49 731/967270",
    "sg:postcode":"89081",
    "sg:province":"Baden-W\u00fcrttemberg",
    "wof:name":"Voko B\u00fcrostudio",
    "wof:placetype":"venue"
},
  "geometry": {"coordinates":[9.969379,48.42189],"type":"Point"}
}