{
  "type": "Feature",
  "properties": {
    "iso:country":"DE",
    "sg:address":"Prinz-Anselm-Allee 9",
    "sg:city":"Niederaichbach",
    "sg:postcode":"84100",
    "sg:province":"Bayern",
    "wof:name":"Urach Gmbh & Co. Verm\u00f6gensverwaltung Kg",
    "wof:placetype":"venue"
},
  "geometry": {"coordinates":[12.3160266876,48.6011276245],"type":"Point"}
}