{
  "type": "Feature",
  "properties": {
    "iso:country":"DE",
    "sg:address":"Kirchstr. 15",
    "sg:city":"Wustrow",
    "sg:phone":"+49 5843/493",
    "sg:postcode":"29462",
    "sg:province":"Niedersachsen",
    "wof:name":"Horst Boje Steuerberater",
    "wof:placetype":"venue"
},
  "geometry": {"coordinates":[11.1187534332,52.9244842529],"type":"Point"}
}