{
  "type": "Feature",
  "properties": {
    "iso:country":"DE",
    "sg:address":"Carl-von-Ossietzky-Str.",
    "sg:city":"H\u00fcrth",
    "sg:phone":"+49 2233/708384",
    "sg:postcode":"50354",
    "sg:province":"Nordrhein-Westfalen",
    "wof:name":"Fuhrmann Fitnesspark H\u00fcrth-park",
    "wof:placetype":"venue"
},
  "geometry": {"coordinates":[6.8905849457,50.8918151855],"type":"Point"}
}