{
  "type": "Feature",
  "properties": {
    "iso:country":"DE",
    "sg:address":"Binger Gasse 31",
    "sg:city":"Boppard",
    "sg:phone":"+49 6742/3572",
    "sg:postcode":"56154",
    "sg:province":"Rheinland-Pfalz",
    "wof:name":"Franz Nickenig",
    "wof:placetype":"venue"
},
  "geometry": {"coordinates":[7.595293045,50.2305450439],"type":"Point"}
}