{
  "type": "Feature",
  "properties": {
    "iso:country":"DE",
    "sg:address":"Schwandorfer Str. 16",
    "sg:city":"Altdorf",
    "sg:phone":"+49 9187/8160",
    "sg:postcode":"90518",
    "sg:province":"Bayern",
    "wof:name":"Rupprecht Bauunternehmen Gmbh",
    "wof:placetype":"venue"
},
  "geometry": {"coordinates":[11.371021,49.385014],"type":"Point"}
}