{
  "type": "Feature",
  "properties": {
    "iso:country":"DE",
    "sg:address":"An der Baderbreite 3",
    "sg:city":"Bernhardswald",
    "sg:phone":"+49 9463/276",
    "sg:postcode":"93170",
    "sg:province":"Bayern",
    "wof:name":"A. Graml-seitz Und E. Seitz",
    "wof:placetype":"venue"
},
  "geometry": {"coordinates":[12.2630777359,49.126789093],"type":"Point"}
}