{
  "type": "Feature",
  "properties": {
    "iso:country":"DE",
    "sg:address":"Waldstr. 6",
    "sg:city":"Oranienburg",
    "sg:phone":"+49 3301/595959",
    "sg:postcode":"16515",
    "sg:province":"Brandenburg",
    "wof:name":"Jewa Taxi- Und Reisedienst Gmbh",
    "wof:placetype":"venue"
},
  "geometry": {"coordinates":[13.1715202332,52.7502784729],"type":"Point"}
}