{
  "type": "Feature",
  "properties": {
    "iso:country":"DE",
    "sg:address":"K\u00f6nigsheide 16",
    "sg:city":"L\u00fcnen",
    "sg:postcode":"44536",
    "sg:province":"Nordrhein-Westfalen",
    "wof:name":"Provinzial Gesch\u00e4ftsstelle Peter Inh. J\u00f6rg Peter E. K.",
    "wof:placetype":"venue"
},
  "geometry": {"coordinates":[7.4418768883,51.5955123901],"type":"Point"}
}