{
  "type": "Feature",
  "properties": {
    "iso:country":"DE",
    "sg:address":"Karlsberg 10",
    "sg:city":"Weinheim",
    "sg:phone":"+49 6201/182868",
    "sg:postcode":"69469",
    "sg:province":"Baden-W\u00fcrttemberg",
    "wof:name":"Sentimento Di Sonja Baron",
    "wof:placetype":"venue"
},
  "geometry": {"coordinates":[8.671579,49.54945],"type":"Point"}
}