{
  "type": "Feature",
  "properties": {
    "iso:country":"DE",
    "sg:address":"Gestringer Str. 51",
    "sg:city":"Espelkamp",
    "sg:phone":"+49 5743/1894",
    "sg:postcode":"32339",
    "sg:province":"Nordrhein-Westfalen",
    "wof:name":"G\u00fcnter Hauptfleisch",
    "wof:placetype":"venue"
},
  "geometry": {"coordinates":[8.597477,52.351929],"type":"Point"}
}