{
  "type": "Feature",
  "properties": {
    "iso:country":"DE",
    "sg:address":"R\u00f6teweg 2",
    "sg:city":"Oberboihingen",
    "sg:phone":"+49 7022/66560",
    "sg:postcode":"72644",
    "sg:province":"Baden-W\u00fcrttemberg",
    "wof:name":"E. Letsche",
    "wof:placetype":"venue"
},
  "geometry": {"coordinates":[9.3667488098,48.6539497375],"type":"Point"}
}