{
  "type": "Feature",
  "properties": {
    "iso:country":"DE",
    "sg:address":"Rosenheimer Str. 181",
    "sg:city":"M\u00fcnchen",
    "sg:phone":"+49 89/401206",
    "sg:postcode":"81671",
    "sg:province":"Bayern",
    "wof:name":"Maria Gr\u00fcnwald",
    "wof:placetype":"venue"
},
  "geometry": {"coordinates":[11.610471,48.118122],"type":"Point"}
}