{
  "type": "Feature",
  "properties": {
    "iso:country":"DE",
    "sg:address":"Ludwig-Erhard-Allee 9",
    "sg:city":"D\u00fcsseldorf",
    "sg:postcode":"40227",
    "sg:province":"Nordrhein-Westfalen",
    "wof:name":"Dr. Gubelt Immobilien Vermietungs-gesellschaft",
    "wof:placetype":"venue"
},
  "geometry": {"coordinates":[6.797315,51.220093],"type":"Point"}
}