{
  "type": "Feature",
  "properties": {
    "iso:country":"DE",
    "sg:address":"Tarpenbekstr. 51",
    "sg:city":"Hamburg",
    "sg:phone":"+49 40/486431",
    "sg:postcode":"20251",
    "sg:province":"Hamburg",
    "wof:name":"Lothar Glebinski",
    "wof:placetype":"venue"
},
  "geometry": {"coordinates":[9.9837207794,53.5942306519],"type":"Point"}
}