{
  "type": "Feature",
  "properties": {
    "iso:country":"DE",
    "sg:address":"Schwaber Str. 12",
    "sg:city":"Jevenstedt",
    "sg:phone":"+49 4337/329",
    "sg:postcode":"24808",
    "sg:province":"Schleswig-Holstein",
    "wof:name":"Claus Pahl",
    "wof:placetype":"venue"
},
  "geometry": {"coordinates":[9.671181,54.234577],"type":"Point"}
}