{
  "type": "Feature",
  "properties": {
    "iso:country":"DE",
    "sg:address":"Dennenbergstr. 22",
    "sg:city":"Titisee-Neustadt",
    "sg:postcode":"79822",
    "sg:province":"Baden-W\u00fcrttemberg",
    "wof:name":"Theater-produktion Thalia Gmbh",
    "wof:placetype":"venue"
},
  "geometry": {"coordinates":[8.2185678482,47.9151687622],"type":"Point"}
}