{
  "type": "Feature",
  "properties": {
    "iso:country":"DE",
    "sg:address":"Barbarossastr. 49",
    "sg:city":"Chemnitz",
    "sg:phone":"+49 371/302043",
    "sg:postcode":"09112",
    "sg:province":"Sachsen",
    "wof:name":"Robert Messing Steuerberater",
    "wof:placetype":"venue"
},
  "geometry": {"coordinates":[12.9012336731,50.8330802917],"type":"Point"}
}