{
  "type": "Feature",
  "properties": {
    "iso:country":"DE",
    "sg:address":"B\u00f6cklerstr. 11",
    "sg:city":"Hameln",
    "sg:phone":"+49 5151/98560",
    "sg:postcode":"31789",
    "sg:province":"Niedersachsen",
    "wof:name":"R\u00fcdiger Pommerening Armaturenwerk Gmbh & Co. Kg",
    "wof:placetype":"venue"
},
  "geometry": {"coordinates":[9.34059,52.081467],"type":"Point"}
}