{
  "type": "Feature",
  "properties": {
    "iso:country":"DE",
    "sg:address":"Philipp-Glenz-Str. 4",
    "sg:city":"Ortenberg",
    "sg:phone":"+49 6046/1542",
    "sg:postcode":"63683",
    "sg:province":"Hessen",
    "wof:name":"Stadt-apotheke",
    "wof:placetype":"venue"
},
  "geometry": {"coordinates":[9.054277,50.35656],"type":"Point"}
}