{
  "type": "Feature",
  "properties": {
    "iso:country":"DE",
    "sg:address":"Braunetsriether Weg 11",
    "sg:city":"Vohenstrau\u00df",
    "sg:phone":"+49 9651/1578",
    "sg:postcode":"92648",
    "sg:province":"Bayern",
    "wof:name":"Heinrich Jungkunst",
    "wof:placetype":"venue"
},
  "geometry": {"coordinates":[12.3459749222,49.6221694946],"type":"Point"}
}