{
  "type": "Feature",
  "properties": {
    "iso:country":"DE",
    "sg:address":"Markt 9-11",
    "sg:city":"Br\u00fchl",
    "sg:phone":"+49 2232/945860",
    "sg:postcode":"50321",
    "sg:province":"Nordrhein-Westfalen",
    "wof:name":"Kaufhalle Ag",
    "wof:placetype":"venue"
},
  "geometry": {"coordinates":[6.904475,50.82851],"type":"Point"}
}