{
  "type": "Feature",
  "properties": {
    "iso:country":"DE",
    "sg:address":"Kanalstr. Nord 146",
    "sg:city":"Gro\u00dfefehn",
    "sg:phone":"+49 4943/4499",
    "sg:postcode":"26629",
    "sg:province":"Niedersachsen",
    "wof:name":"Hs Oberfl\u00e4chentechnik Gmbh",
    "wof:placetype":"venue"
},
  "geometry": {"coordinates":[7.636005,53.405392],"type":"Point"}
}