{
  "type": "Feature",
  "properties": {
    "iso:country":"DE",
    "sg:address":"Parkstr. 11",
    "sg:city":"Ahaus",
    "sg:phone":"+49 2561/82131",
    "sg:postcode":"48683",
    "sg:province":"Nordrhein-Westfalen",
    "wof:name":"E. L\u00fcnterbusch",
    "wof:placetype":"venue"
},
  "geometry": {"coordinates":[6.9166178703,52.0730209351],"type":"Point"}
}