{
  "type": "Feature",
  "properties": {
    "iso:country":"DE",
    "sg:address":"Hansestr. 31",
    "sg:city":"Braunschweig",
    "sg:phone":"+49 531/311001",
    "sg:postcode":"38112",
    "sg:province":"Niedersachsen",
    "wof:name":"Pelz Kommunal- Garten- Und Reinigungstechnik",
    "wof:placetype":"venue"
},
  "geometry": {"coordinates":[10.499756,52.312634],"type":"Point"}
}