{
  "type": "Feature",
  "properties": {
    "iso:country":"DE",
    "sg:address":"Marktplatz 33",
    "sg:city":"Kraiburg",
    "sg:phone":"+49 8638/7525",
    "sg:postcode":"84559",
    "sg:province":"Bayern",
    "wof:name":"Kath. Pfarramt",
    "wof:placetype":"venue"
},
  "geometry": {"coordinates":[12.4288034439,48.1819801331],"type":"Point"}
}