{
  "type": "Feature",
  "properties": {
    "iso:country":"DE",
    "sg:address":"Dr.-Otto-Nuschke-Str. 11",
    "sg:city":"Oelsnitz",
    "sg:phone":"+49 37298/2182",
    "sg:postcode":"09376",
    "sg:province":"Sachsen",
    "wof:name":"Werner Hilbig",
    "wof:placetype":"venue"
},
  "geometry": {"coordinates":[12.7093582153,50.7245025635],"type":"Point"}
}