{
  "type": "Feature",
  "properties": {
    "iso:country":"DE",
    "sg:address":"Schwarzwaldstr. 20",
    "sg:city":"Kirchzarten",
    "sg:phone":"+49 7661/62100",
    "sg:postcode":"79199",
    "sg:province":"Baden-W\u00fcrttemberg",
    "wof:name":"Dr. Med. Degenhardt-oehlert \u00c4rztin F\u00fcr Dermatologie",
    "wof:placetype":"venue"
},
  "geometry": {"coordinates":[7.953534,47.96357],"type":"Point"}
}