{
  "type": "Feature",
  "properties": {
    "iso:country":"DE",
    "sg:address":"Memeler Str. 63",
    "sg:city":"M\u00fcnchen",
    "sg:phone":"+49 89/937663",
    "sg:postcode":"81927",
    "sg:province":"Bayern",
    "wof:name":"Bertold Schalper Rechtsanwalt",
    "wof:placetype":"venue"
},
  "geometry": {"coordinates":[11.6394739151,48.153301239],"type":"Point"}
}