{
  "type": "Feature",
  "properties": {
    "iso:country":"DE",
    "sg:address":"Sandtorfer Weg 81 A",
    "sg:city":"Lampertheim",
    "sg:phone":"+49 6206/57279",
    "sg:postcode":"68623",
    "sg:province":"Hessen",
    "wof:name":"Wolfgang Adam Architekt",
    "wof:placetype":"venue"
},
  "geometry": {"coordinates":[8.487984,49.583969],"type":"Point"}
}