{
  "type": "Feature",
  "properties": {
    "iso:country":"DE",
    "sg:address":"Ritter-Tuschl-Str. 20",
    "sg:city":"Saldenburg",
    "sg:phone":"+49 8504/1655",
    "sg:postcode":"94163",
    "sg:province":"Bayern",
    "wof:name":"Jugendherberge",
    "wof:placetype":"venue"
},
  "geometry": {"coordinates":[13.3552656174,48.7748794556],"type":"Point"}
}