{
  "type": "Feature",
  "properties": {
    "iso:country":"DE",
    "sg:address":"Bruchstr. 25",
    "sg:city":"Bad D\u00fcrkheim",
    "sg:phone":"+49 6322/1219",
    "sg:postcode":"67098",
    "sg:province":"Rheinland-Pfalz",
    "wof:name":"Bobby Joseph Vilsmeier Beteiligungs-gmbh",
    "wof:placetype":"venue"
},
  "geometry": {"coordinates":[8.203217,49.471031],"type":"Point"}
}