{
  "type": "Feature",
  "properties": {
    "iso:country":"DE",
    "sg:address":"Hans-Pirner-Str. 18",
    "sg:city":"Ottensoos",
    "sg:phone":"+49 9123/4230",
    "sg:postcode":"91242",
    "sg:province":"Bayern",
    "wof:name":"H. H. Schmidt Immobilienmakler",
    "wof:placetype":"venue"
},
  "geometry": {"coordinates":[11.3399391174,49.5108528137],"type":"Point"}
}