{
  "type": "Feature",
  "properties": {
    "iso:country":"DE",
    "sg:address":"Danewerkstr. 11a",
    "sg:city":"Kiel",
    "sg:postcode":"24113",
    "sg:province":"Schleswig-Holstein",
    "wof:name":"Nord - Mamis",
    "wof:placetype":"venue"
},
  "geometry": {"coordinates":[10.11253,54.304623],"type":"Point"}
}