{
  "type": "Feature",
  "properties": {
    "iso:country":"DE",
    "sg:address":"Am Ziegelofen 2",
    "sg:city":"K\u00f6ln",
    "sg:phone":"+49 2236/96500",
    "sg:postcode":"50999",
    "sg:province":"Nordrhein-Westfalen",
    "wof:name":"Atlas Copco Energas Gmbh",
    "wof:placetype":"venue"
},
  "geometry": {"coordinates":[7.0066299438,50.8626937866],"type":"Point"}
}