{
  "type": "Feature",
  "properties": {
    "iso:country":"DE",
    "sg:address":"K\u00f6lner Str. 12",
    "sg:city":"Bergheim",
    "sg:postcode":"50126",
    "sg:province":"Nordrhein-Westfalen",
    "wof:name":"Versicherungs- Und Hypotheken- B\u00fcro Michael Bosbach &",
    "wof:placetype":"venue"
},
  "geometry": {"coordinates":[6.6459150314,50.9528656006],"type":"Point"}
}