{
  "type": "Feature",
  "properties": {
    "iso:country":"DE",
    "sg:address":"Alte Kirchstr. 6 m",
    "sg:city":"Braunschweig",
    "sg:phone":"+49 531/65646",
    "sg:postcode":"38126",
    "sg:province":"Niedersachsen",
    "wof:name":"Rolf Schn\u00e4delbach",
    "wof:placetype":"venue"
},
  "geometry": {"coordinates":[10.5693416595,52.2239952087],"type":"Point"}
}