{
  "type": "Feature",
  "properties": {
    "iso:country":"DE",
    "sg:address":"Bahnhofstr. 46",
    "sg:city":"Frohburg",
    "sg:phone":"+49 34348/8200",
    "sg:postcode":"04654",
    "sg:province":"Sachsen",
    "wof:name":"Deutsches Rotes Kreuz Kreisverband Geithain E. V.",
    "wof:placetype":"venue"
},
  "geometry": {"coordinates":[12.55621,51.062656],"type":"Point"}
}