{
  "type": "Feature",
  "properties": {
    "iso:country":"DE",
    "sg:address":"Beckersbergstr. 43",
    "sg:city":"Henstedt-Ulzburg",
    "sg:phone":"+49 4193/2211",
    "sg:postcode":"24558",
    "sg:province":"Schleswig-Holstein",
    "wof:name":"Joachim Sch\u00fcmann Gmbh",
    "wof:placetype":"venue"
},
  "geometry": {"coordinates":[9.986120224,53.7935905457],"type":"Point"}
}