{
  "type": "Feature",
  "properties": {
    "iso:country":"DE",
    "sg:address":"Rielasinger Str. 77",
    "sg:city":"Singen",
    "sg:phone":"+49 7731/21271",
    "sg:postcode":"78224",
    "sg:province":"Baden-W\u00fcrttemberg",
    "wof:name":"Alexander Leitz",
    "wof:placetype":"venue"
},
  "geometry": {"coordinates":[8.8430423737,47.7495918274],"type":"Point"}
}