{
  "type": "Feature",
  "properties": {
    "iso:country":"DE",
    "sg:address":"M\u00fcnchener Str. 33",
    "sg:city":"Ebersberg",
    "sg:phone":"+49 8092/88393",
    "sg:postcode":"85560",
    "sg:province":"Bayern",
    "wof:name":"Platzer Und Katterloher Rechtsanw\u00e4lte",
    "wof:placetype":"venue"
},
  "geometry": {"coordinates":[11.9541368484,48.0753440857],"type":"Point"}
}