{
  "type": "Feature",
  "properties": {
    "iso:country":"DE",
    "sg:address":"Emilienstr. 29",
    "sg:city":"Stuttgart",
    "sg:phone":"+49 711/748104",
    "sg:postcode":"70563",
    "sg:province":"Baden-W\u00fcrttemberg",
    "wof:name":"B\u00fcrk Zeitsysteme- Zeitdienst Gmbh",
    "wof:placetype":"venue"
},
  "geometry": {"coordinates":[9.1128892899,48.7288627625],"type":"Point"}
}