{
  "type": "Feature",
  "properties": {
    "iso:country":"DE",
    "sg:address":"Am Heerweg 4",
    "sg:city":"Apolda",
    "sg:postcode":"99510",
    "sg:province":"Th\u00fcringen",
    "wof:name":"A & G-albrecht & Gothmann- Arbeitsb\u00fchnen Gmbh",
    "wof:placetype":"venue"
},
  "geometry": {"coordinates":[11.49496,51.022579],"type":"Point"}
}