{
  "type": "Feature",
  "properties": {
    "iso:country":"DE",
    "sg:address":"Am Wassergarten 21",
    "sg:city":"Kreuzau",
    "sg:phone":"+49 2422/7218",
    "sg:postcode":"52372",
    "sg:province":"Nordrhein-Westfalen",
    "wof:name":"Gottschalk Und Poick",
    "wof:placetype":"venue"
},
  "geometry": {"coordinates":[6.4859919548,50.7459373474],"type":"Point"}
}