{
  "type": "Feature",
  "properties": {
    "iso:country":"DE",
    "sg:address":"Schanzgrubenweg 18",
    "sg:city":"Ulm",
    "sg:phone":"+49 731/384844",
    "sg:postcode":"89081",
    "sg:province":"Baden-W\u00fcrttemberg",
    "wof:name":"Erich Mayer",
    "wof:placetype":"venue"
},
  "geometry": {"coordinates":[9.937789917,48.4006996155],"type":"Point"}
}