{
  "type": "Feature",
  "properties": {
    "iso:country":"DE",
    "sg:address":"Augartenstr. 25",
    "sg:city":"Bensheim",
    "sg:phone":"+49 6251/63128",
    "sg:postcode":"64625",
    "sg:province":"Hessen",
    "wof:name":"Radlager A. Kratz",
    "wof:placetype":"venue"
},
  "geometry": {"coordinates":[8.624288,49.680706],"type":"Point"}
}