{
  "type": "Feature",
  "properties": {
    "iso:country":"DE",
    "sg:address":"B\u00fcscher Str. 40",
    "sg:city":"Eitorf",
    "sg:phone":"+49 2243/3176",
    "sg:postcode":"53783",
    "sg:province":"Nordrhein-Westfalen",
    "wof:name":"Hans Sonntag",
    "wof:placetype":"venue"
},
  "geometry": {"coordinates":[7.4493150711,50.7321510315],"type":"Point"}
}