{
  "type": "Feature",
  "properties": {
    "iso:country":"DE",
    "sg:address":"Maisd\u00f6rpe 1",
    "sg:city":"H\u00fcckeswagen",
    "sg:phone":"+49 2192/2566",
    "sg:postcode":"42499",
    "sg:province":"Nordrhein-Westfalen",
    "wof:name":"Alfred Liesendahl",
    "wof:placetype":"venue"
},
  "geometry": {"coordinates":[7.282049,51.138958],"type":"Point"}
}