{
  "type": "Feature",
  "properties": {
    "iso:country":"DE",
    "sg:address":"Maienwaldstr. 21",
    "sg:city":"Ebersbach",
    "sg:phone":"+49 7163/2195",
    "sg:postcode":"73061",
    "sg:province":"Baden-W\u00fcrttemberg",
    "wof:name":"Josef Fr\u00f6hlich",
    "wof:placetype":"venue"
},
  "geometry": {"coordinates":[9.4993991852,48.6865119934],"type":"Point"}
}