{
  "type": "Feature",
  "properties": {
    "iso:country":"DE",
    "sg:address":"Neue Str. 108",
    "sg:city":"Kirchlengern",
    "sg:phone":"+49 5223/73288",
    "sg:postcode":"32278",
    "sg:province":"Nordrhein-Westfalen",
    "wof:name":"Karl Steinmeier",
    "wof:placetype":"venue"
},
  "geometry": {"coordinates":[8.627888,52.233532],"type":"Point"}
}