{
  "type": "Feature",
  "properties": {
    "iso:country":"DE",
    "sg:address":"Bahnhofstr. 11",
    "sg:city":"Traunstein",
    "sg:phone":"+49 861/988820",
    "sg:postcode":"83278",
    "sg:province":"Bayern",
    "wof:name":"Parkhotel Traunsteiner Hof Gmbh",
    "wof:placetype":"venue"
},
  "geometry": {"coordinates":[12.6427907944,47.8690948486],"type":"Point"}
}