{
  "type": "Feature",
  "properties": {
    "iso:country":"DE",
    "sg:address":"Auf der T\u00f6dtheide 11",
    "sg:city":"Bielefeld",
    "sg:phone":"+49 521/5214122",
    "sg:postcode":"33729",
    "sg:province":"Nordrhein-Westfalen",
    "wof:name":"Argos-detectei",
    "wof:placetype":"venue"
},
  "geometry": {"coordinates":[8.584766,52.077374],"type":"Point"}
}