{
  "type": "Feature",
  "properties": {
    "iso:country":"DE",
    "sg:address":"Seestr. 32",
    "sg:city":"Gstadt",
    "sg:phone":"+49 8054/9233",
    "sg:postcode":"83257",
    "sg:province":"Bayern",
    "wof:name":"Michael Z\u00fcrn Rechtsanwalt",
    "wof:placetype":"venue"
},
  "geometry": {"coordinates":[12.4167299271,47.8846893311],"type":"Point"}
}