{
  "type": "Feature",
  "properties": {
    "iso:country":"DE",
    "sg:address":"Kuhlertweg 7",
    "sg:city":"Pennigsehl",
    "sg:phone":"+49 5028/269",
    "sg:postcode":"31621",
    "sg:province":"Niedersachsen",
    "wof:name":"Wilhelm Menze",
    "wof:placetype":"venue"
},
  "geometry": {"coordinates":[9.039358,52.624409],"type":"Point"}
}