{
  "type": "Feature",
  "properties": {
    "iso:country":"DE",
    "sg:address":"Hirtenstr. 71",
    "sg:city":"Dresden",
    "sg:phone":"+49 351/4113534",
    "sg:postcode":"01169",
    "sg:province":"Sachsen",
    "wof:name":"Andreas Gr\u00e4f Tischlerei",
    "wof:placetype":"venue"
},
  "geometry": {"coordinates":[13.657709,51.045994],"type":"Point"}
}