{
  "type": "Feature",
  "properties": {
    "iso:country":"DE",
    "sg:address":"Am Eichertswald 4",
    "sg:city":"Rehlingen-Siersburg",
    "sg:phone":"+49 6835/68760",
    "sg:postcode":"66780",
    "sg:province":"Saarland",
    "wof:name":"Weides Gmbh",
    "wof:placetype":"venue"
},
  "geometry": {"coordinates":[6.6563429832,49.3614425659],"type":"Point"}
}