{
  "type": "Feature",
  "properties": {
    "iso:country":"DE",
    "sg:address":"Bahnhofstrasse 3::",
    "sg:city":"Gittelde",
    "sg:phone":"+49 3596/602024",
    "sg:postcode":"37534",
    "sg:province":"Niedersachsen",
    "wof:name":"Voigt Lampenschirme Gmbh",
    "wof:placetype":"venue"
},
  "geometry": {"coordinates":[14.216083,51.023174],"type":"Point"}
}