{
  "type": "Feature",
  "properties": {
    "iso:country":"DE",
    "sg:address":"Dietrich-Bonhoeffer-Str. 4",
    "sg:city":"Cloppenburg",
    "sg:phone":"+49 4471/2505",
    "sg:postcode":"49661",
    "sg:province":"Niedersachsen",
    "wof:name":"Nova",
    "wof:placetype":"venue"
},
  "geometry": {"coordinates":[8.0428342819,52.8430519104],"type":"Point"}
}