{
  "type": "Feature",
  "properties": {
    "iso:country":"DE",
    "sg:address":"Am Steinhof 27",
    "sg:city":"Salzhemmendorf",
    "sg:phone":"+49 5153/5306",
    "sg:postcode":"31020",
    "sg:province":"Niedersachsen",
    "wof:name":"Friedrich Brockmann",
    "wof:placetype":"venue"
},
  "geometry": {"coordinates":[9.601509,52.08176],"type":"Point"}
}