{
  "type": "Feature",
  "properties": {
    "iso:country":"DE",
    "sg:address":"L\u00fcneburger Str. 7",
    "sg:city":"Stelle",
    "sg:phone":"+49 4174/4446",
    "sg:postcode":"21435",
    "sg:province":"Niedersachsen",
    "wof:name":"Sascha Schorn",
    "wof:placetype":"venue"
},
  "geometry": {"coordinates":[10.1131782532,53.3829345703],"type":"Point"}
}