{
  "type": "Feature",
  "properties": {
    "iso:country":"DE",
    "sg:address":"Kavalierstr. 65",
    "sg:city":"Dessau",
    "sg:phone":"+49 340/212426",
    "sg:postcode":"06844",
    "sg:province":"Sachsen-Anhalt",
    "wof:name":"Horst Peters",
    "wof:placetype":"venue"
},
  "geometry": {"coordinates":[12.24289608,51.8324966431],"type":"Point"}
}