{
  "type": "Feature",
  "properties": {
    "iso:country":"DE",
    "sg:address":"Schwammenauel",
    "sg:city":"Heimbach",
    "sg:phone":"+49 2446/247",
    "sg:postcode":"52396",
    "sg:province":"Nordrhein-Westfalen",
    "wof:name":"Hotel Berghof",
    "wof:placetype":"venue"
},
  "geometry": {"coordinates":[6.4482569695,50.6299514771],"type":"Point"}
}