{
  "type": "Feature",
  "properties": {
    "iso:country":"DE",
    "sg:address":"Goethestr. 6",
    "sg:city":"Dieburg",
    "sg:postcode":"64807",
    "sg:province":"Hessen",
    "wof:name":"Hans Schroth Kg",
    "wof:placetype":"venue"
},
  "geometry": {"coordinates":[8.841411,49.894531],"type":"Point"}
}