{
  "type": "Feature",
  "properties": {
    "iso:country":"DE",
    "sg:address":"Grafenwerthstr. 92",
    "sg:city":"K\u00f6ln",
    "sg:postcode":"50937",
    "sg:province":"Nordrhein-Westfalen",
    "wof:name":"Classic Haus Grundbesitzverwaltungs- Und",
    "wof:placetype":"venue"
},
  "geometry": {"coordinates":[6.9178738594,50.9095993042],"type":"Point"}
}