{
  "type": "Feature",
  "properties": {
    "iso:country":"DE",
    "sg:address":"M\u00fc\u00dfmattstr. 22",
    "sg:city":"Rheinfelden",
    "sg:phone":"+49 7623/8811",
    "sg:postcode":"79618",
    "sg:province":"Baden-W\u00fcrttemberg",
    "wof:name":"H.d. V. Schmieden M\u00fcssmatt-drogerie",
    "wof:placetype":"venue"
},
  "geometry": {"coordinates":[7.786411,47.565582],"type":"Point"}
}