{
  "type": "Feature",
  "properties": {
    "iso:country":"DE",
    "sg:address":"M\u00fchlweg 53",
    "sg:city":"Weiden",
    "sg:phone":"+49 961/24956",
    "sg:postcode":"92637",
    "sg:province":"Bayern",
    "wof:name":"Heiner Macht Architekt Bda",
    "wof:placetype":"venue"
},
  "geometry": {"coordinates":[12.140383,49.670834],"type":"Point"}
}