{
  "type": "Feature",
  "properties": {
    "iso:country":"DE",
    "sg:address":"Frankfurter Str. 24",
    "sg:city":"Wiesbaden",
    "sg:phone":"+49 611/36190",
    "sg:postcode":"65189",
    "sg:province":"Hessen",
    "wof:name":"Manfred Von Vangerow Joachim Von Vangerow",
    "wof:placetype":"venue"
},
  "geometry": {"coordinates":[8.2498922348,50.0777702332],"type":"Point"}
}