{
  "type": "Feature",
  "properties": {
    "iso:country":"DE",
    "sg:address":"Saspower Hauptstr. 54",
    "sg:city":"Cottbus",
    "sg:phone":"+49 355/821004",
    "sg:postcode":"03044",
    "sg:province":"Brandenburg",
    "wof:name":"Tagescafe-saspow Inh. Ursula Schultke",
    "wof:placetype":"venue"
},
  "geometry": {"coordinates":[14.353942,51.782925],"type":"Point"}
}