{
  "type": "Feature",
  "properties": {
    "iso:country":"DE",
    "sg:address":"G\u00e4rtnerstr. 21",
    "sg:city":"Sch\u00f6llnach",
    "sg:phone":"+49 9903/8424",
    "sg:postcode":"94508",
    "sg:province":"Bayern",
    "wof:name":"Anton Hopf",
    "wof:placetype":"venue"
},
  "geometry": {"coordinates":[13.184527,48.753109],"type":"Point"}
}