{
  "type": "Feature",
  "properties": {
    "iso:country":"DE",
    "sg:address":"K\u00f6nig-Wilhelm-Str. 6",
    "sg:city":"Freudenstadt",
    "sg:phone":"+49 7441/81875",
    "sg:postcode":"72250",
    "sg:province":"Baden-W\u00fcrttemberg",
    "wof:name":"Deutsche Rheuma-liga Arbeitsgem. Freudenstadt",
    "wof:placetype":"venue"
},
  "geometry": {"coordinates":[8.4234113693,48.4590148926],"type":"Point"}
}