{
  "type": "Feature",
  "properties": {
    "iso:country":"DE",
    "sg:address":"Blaulochstr. 90-92",
    "sg:city":"Wallerfangen",
    "sg:phone":"+49 6831/61182",
    "sg:postcode":"66798",
    "sg:province":"Saarland",
    "wof:name":"Manfred Demmerle",
    "wof:placetype":"venue"
},
  "geometry": {"coordinates":[6.698182,49.327106],"type":"Point"}
}