{
  "type": "Feature",
  "properties": {
    "iso:country":"DE",
    "sg:address":"Landfriedstr. 1",
    "sg:city":"Heidelberg",
    "sg:postcode":"69117",
    "sg:province":"Baden-W\u00fcrttemberg",
    "wof:name":"Heidelberger Sprachinstitut F\u00fcr Studium Und Berufliche",
    "wof:placetype":"venue"
},
  "geometry": {"coordinates":[8.700340271,49.4101066589],"type":"Point"}
}