{
  "type": "Feature",
  "properties": {
    "iso:country":"DE",
    "sg:address":"Richard-Wagner-Str. 33",
    "sg:city":"Kaiserslautern",
    "sg:phone":"+49 631/3606700",
    "sg:postcode":"67655",
    "sg:province":"Rheinland-Pfalz",
    "wof:name":"Hamburg-mannheimer Versicherungsgesellschaften",
    "wof:placetype":"venue"
},
  "geometry": {"coordinates":[7.7663021088,49.441368103],"type":"Point"}
}