{
  "type": "Feature",
  "properties": {
    "iso:country":"DE",
    "sg:address":"Karlstr. 5",
    "sg:city":"Hallbergmoos",
    "sg:postcode":"85399",
    "sg:province":"Bayern",
    "wof:name":"Ingenieurb\u00fcro Kollmannsberger- Siegmund Planungsges. F\u00fcr",
    "wof:placetype":"venue"
},
  "geometry": {"coordinates":[11.74663,48.32729],"type":"Point"}
}