{
  "type": "Feature",
  "properties": {
    "iso:country":"DE",
    "sg:address":"Im Wiesengrund 19",
    "sg:city":"Steinburg",
    "sg:phone":"+49 4534/1505",
    "sg:postcode":"22964",
    "sg:province":"Schleswig-Holstein",
    "wof:name":"K.f. Berodt",
    "wof:placetype":"venue"
},
  "geometry": {"coordinates":[10.3884019852,53.7041091919],"type":"Point"}
}