{
  "type": "Feature",
  "properties": {
    "iso:country":"DE",
    "sg:address":"Greifswalder Str. 74",
    "sg:city":"Schwerin",
    "sg:phone":"+49 385/484580",
    "sg:postcode":"19057",
    "sg:province":"Mecklenburg-Vorpommern",
    "wof:name":"Quelle K\u00fcchenberater Frank Maschler",
    "wof:placetype":"venue"
},
  "geometry": {"coordinates":[11.3605804443,53.6409187317],"type":"Point"}
}