{
  "type": "Feature",
  "properties": {
    "iso:country":"DE",
    "sg:address":"Enzianweg 88",
    "sg:city":"Stahnsdorf",
    "sg:phone":"+49 3329/63279",
    "sg:postcode":"14532",
    "sg:province":"Brandenburg",
    "wof:name":"Bernd H\u00fcneburg Anlageberater",
    "wof:placetype":"venue"
},
  "geometry": {"coordinates":[13.2381677628,52.3842926025],"type":"Point"}
}