{
  "type": "Feature",
  "properties": {
    "iso:country":"DE",
    "sg:address":"Piccoloministr. 304",
    "sg:city":"K\u00f6ln",
    "sg:phone":"+49 221/631863",
    "sg:postcode":"51067",
    "sg:province":"Nordrhein-Westfalen",
    "wof:name":"Vollkornb\u00e4ckerei \u00c4hrensache Gmbh",
    "wof:placetype":"venue"
},
  "geometry": {"coordinates":[7.038613,50.971504],"type":"Point"}
}