{
  "type": "Feature",
  "properties": {
    "iso:country":"DE",
    "sg:address":"Jens-Otto-Krag-Str. 11",
    "sg:city":"W\u00fcrselen (Aachen)",
    "sg:classifiers":[
        {
            "category":"Professional",
            "subcategory":"Computer Services",
            "type":"Services"
        }
    ],
    "sg:postcode":"52146",
    "sg:tags":[
        "neoreader",
        "2d-barcodes",
        "mobile-codes",
        "mobile-marketing",
        "mobile-ticketing"
    ],
    "sg:website":"http://www.neom.com",
    "wof:name":"NeoMedia Technologies",
    "wof:placetype":"venue"
},
  "geometry": {"coordinates":[6.163074,50.812765],"type":"Point"}
}