{
  "type": "Feature",
  "properties": {
    "iso:country":"DE",
    "sg:address":"Tannenweg 14",
    "sg:city":"Hundsangen",
    "sg:phone":"+49 6433/6711",
    "sg:postcode":"56414",
    "sg:province":"Rheinland-Pfalz",
    "wof:name":"C. Teich-pa\u00dfk\u00f6nig Heilpraktiker",
    "wof:placetype":"venue"
},
  "geometry": {"coordinates":[7.9874272346,50.4574699402],"type":"Point"}
}