{
  "type": "Feature",
  "properties": {
    "iso:country":"DE",
    "sg:address":"Waller Str. 47",
    "sg:city":"Winsen",
    "sg:phone":"+49 5143/8784",
    "sg:postcode":"29308",
    "sg:province":"Niedersachsen",
    "wof:name":"Ursula Lange",
    "wof:placetype":"venue"
},
  "geometry": {"coordinates":[9.9110746384,52.6885757446],"type":"Point"}
}