{
  "type": "Feature",
  "properties": {
    "iso:country":"DE",
    "sg:address":"Herzogstr 10",
    "sg:city":"Kinsau",
    "sg:phone":"+49 8869/912900",
    "sg:postcode":"86981",
    "sg:province":"Bayern",
    "wof:name":"Funky Kingdom Gmbh",
    "wof:placetype":"venue"
},
  "geometry": {"coordinates":[10.9117078781,47.8764839172],"type":"Point"}
}