{
  "type": "Feature",
  "properties": {
    "iso:country":"DE",
    "sg:address":"Wankbahnstr. 1",
    "sg:city":"Garmisch-Partenkirchen",
    "sg:phone":"+49 8821/2187",
    "sg:postcode":"82467",
    "sg:province":"Bayern",
    "wof:name":"Sch\u00fctzenhaus",
    "wof:placetype":"venue"
},
  "geometry": {"coordinates":[11.104511261,47.5039901733],"type":"Point"}
}