{
  "type": "Feature",
  "properties": {
    "iso:country":"DE",
    "sg:address":"Schlesische Str 29",
    "sg:city":"Berlin",
    "sg:phone":"+49 30/61792216",
    "sg:postcode":"10997",
    "sg:province":"Berlin",
    "wof:name":"Schoppe-keil Aufz\u00fcge Gesch\u00e4ftsbetrieb Der C. Haushahn Aufz\u00fcge Gmbh Und Co Kg",
    "wof:placetype":"venue"
},
  "geometry": {"coordinates":[13.4468240738,52.4986724854],"type":"Point"}
}