{
  "type": "Feature",
  "properties": {
    "iso:country":"DE",
    "sg:address":"Wrampestr. 5",
    "sg:city":"Dedeleben",
    "sg:phone":"+49 39422/462",
    "sg:postcode":"38836",
    "sg:province":"Sachsen-Anhalt",
    "wof:name":"W. Becker",
    "wof:placetype":"venue"
},
  "geometry": {"coordinates":[10.8927164078,52.0306663513],"type":"Point"}
}