{
  "type": "Feature",
  "properties": {
    "iso:country":"DE",
    "sg:city":"Teunz",
    "sg:phone":"+49 9671/577",
    "sg:postcode":"92552",
    "sg:province":"Bayern",
    "wof:name":"Albert Eisenschmidt Gmbh",
    "wof:placetype":"venue"
},
  "geometry": {"coordinates":[12.384223,49.479771],"type":"Point"}
}