{
  "type": "Feature",
  "properties": {
    "iso:country":"DE",
    "sg:address":"Bahnhofstr. 69",
    "sg:city":"Bodenmais",
    "sg:phone":"+49 9924/200",
    "sg:postcode":"94249",
    "sg:province":"Bayern",
    "wof:name":"Hans Treml Jun.",
    "wof:placetype":"venue"
},
  "geometry": {"coordinates":[13.098252,49.069431],"type":"Point"}
}