{
  "type": "Feature",
  "properties": {
    "iso:country":"DE",
    "sg:address":"Wambeler Hellweg 118",
    "sg:city":"Dortmund",
    "sg:postcode":"44143",
    "sg:province":"Nordrhein-Westfalen",
    "wof:name":"Aldi Gmbh & Co. Kg",
    "wof:placetype":"venue"
},
  "geometry": {"coordinates":[7.5232481956,51.521156311],"type":"Point"}
}