{
  "type": "Feature",
  "properties": {
    "iso:country":"DE",
    "sg:address":"Altvaterstr. 6",
    "sg:city":"Memmingen",
    "sg:phone":"+49 8331/6673",
    "sg:postcode":"87700",
    "sg:province":"Bayern",
    "wof:name":"Ammann Verwaltungs Gmbh",
    "wof:placetype":"venue"
},
  "geometry": {"coordinates":[10.158156,47.978588],"type":"Point"}
}