{
  "type": "Feature",
  "properties": {
    "iso:country":"DE",
    "sg:address":"Metzinger Str. 2",
    "sg:city":"Dettingen",
    "sg:phone":"+49 4971/2371061",
    "sg:postcode":"72581",
    "sg:province":"Baden-W\u00fcrttemberg",
    "wof:name":"Volksbank Metzingen Eg",
    "wof:placetype":"venue"
},
  "geometry": {"coordinates":[9.346713,48.529579],"type":"Point"}
}