{
  "type": "Feature",
  "properties": {
    "iso:country":"DE",
    "sg:address":"Hoferland 2",
    "sg:city":"Schwalmtal",
    "sg:postcode":"41366",
    "sg:province":"Nordrhein-Westfalen",
    "wof:name":"Ars Restauro Ges. F\u00fcr Restaurierungstechnik Mbh",
    "wof:placetype":"venue"
},
  "geometry": {"coordinates":[6.237473,51.232536],"type":"Point"}
}