{
  "type": "Feature",
  "properties": {
    "iso:country":"DE",
    "sg:address":"Dr\u00f6gen-Hasen-Weg 193",
    "sg:city":"Oldenburg",
    "sg:phone":"+49 441/74537",
    "sg:postcode":"26129",
    "sg:province":"Niedersachsen",
    "wof:name":"Hans Pophanken",
    "wof:placetype":"venue"
},
  "geometry": {"coordinates":[8.16368,53.15086],"type":"Point"}
}