{
  "type": "Feature",
  "properties": {
    "iso:country":"DE",
    "sg:address":"Am Ilksberg 34",
    "sg:city":"Jesteburg",
    "sg:phone":"+49 4183/5744",
    "sg:postcode":"21266",
    "sg:province":"Niedersachsen",
    "wof:name":"Mustafa R. Sanri \u00dcbersetzer",
    "wof:placetype":"venue"
},
  "geometry": {"coordinates":[9.967342,53.311481],"type":"Point"}
}