{
  "type": "Feature",
  "properties": {
    "iso:country":"DE",
    "sg:address":"Allersheimer Str. 49",
    "sg:city":"Holzminden",
    "sg:phone":"+49 5531/3263",
    "sg:postcode":"37603",
    "sg:province":"Niedersachsen",
    "wof:name":"Arthur Markworth",
    "wof:placetype":"venue"
},
  "geometry": {"coordinates":[9.460265,51.834927],"type":"Point"}
}