{
  "type": "Feature",
  "properties": {
    "iso:country":"DE",
    "sg:address":"Am Patentbusch 20",
    "sg:city":"Oldenburg",
    "sg:phone":"+49 441/939950",
    "sg:postcode":"26125",
    "sg:province":"Niedersachsen",
    "wof:name":"Oldenburger Buchbinderei Alfred Kramm Gmbh & Co. Kg",
    "wof:placetype":"venue"
},
  "geometry": {"coordinates":[8.227919,53.196301],"type":"Point"}
}