{
  "type": "Feature",
  "properties": {
    "iso:country":"DE",
    "sg:address":"Hohenwarter Str. 36",
    "sg:city":"Pforzheim",
    "sg:postcode":"75181",
    "sg:province":"Baden-W\u00fcrttemberg",
    "wof:name":"Troschke & Bischoff Partnerschaft",
    "wof:placetype":"venue"
},
  "geometry": {"coordinates":[8.7348537445,48.8542060852],"type":"Point"}
}