{
  "type": "Feature",
  "properties": {
    "iso:country":"DE",
    "sg:address":"Riepenstr. 17",
    "sg:city":"Barsinghausen",
    "sg:phone":"+49 5105/8842",
    "sg:postcode":"30890",
    "sg:province":"Niedersachsen",
    "wof:name":"Ev. Luth. Pfarramt Gem. Egestorf",
    "wof:placetype":"venue"
},
  "geometry": {"coordinates":[9.5189666748,52.2874336243],"type":"Point"}
}