{
  "type": "Feature",
  "properties": {
    "iso:country":"DE",
    "sg:address":"Buntentorsteinweg 297",
    "sg:city":"Bremen",
    "sg:phone":"+49 421/552359",
    "sg:postcode":"28201",
    "sg:province":"Bremen",
    "wof:name":"Druckerei Nagel Gmbh",
    "wof:placetype":"venue"
},
  "geometry": {"coordinates":[8.8117828369,53.0599098206],"type":"Point"}
}