{
  "type": "Feature",
  "properties": {
    "iso:country":"DE",
    "sg:address":"Mittelstr. 1a",
    "sg:city":"Gro\u00dfengottern",
    "sg:postcode":"99991",
    "sg:province":"Th\u00fcringen",
    "wof:name":"S. K.-bau Gmbh",
    "wof:placetype":"venue"
},
  "geometry": {"coordinates":[10.562448,51.148312],"type":"Point"}
}