{
  "type": "Feature",
  "properties": {
    "iso:country":"DE",
    "sg:address":"Bergstr. 2",
    "sg:city":"S\u00f6gel",
    "sg:phone":"+49 5952/1246",
    "sg:postcode":"49751",
    "sg:province":"Niedersachsen",
    "wof:name":"Deimann",
    "wof:placetype":"venue"
},
  "geometry": {"coordinates":[7.518029213,52.8408889771],"type":"Point"}
}