{
  "type": "Feature",
  "properties": {
    "iso:country":"DE",
    "sg:address":"Zeidlerstr. 23",
    "sg:city":"Hamburg",
    "sg:phone":"+49 40/7534829",
    "sg:postcode":"21107",
    "sg:province":"Hamburg",
    "wof:name":"Restaurant China",
    "wof:placetype":"venue"
},
  "geometry": {"coordinates":[9.9943380356,53.5135307312],"type":"Point"}
}