{
  "type": "Feature",
  "properties": {
    "iso:country":"DE",
    "sg:address":"Karl-von-Hahn-Str. 120",
    "sg:city":"Freudenstadt",
    "sg:phone":"+49 7441/2205",
    "sg:postcode":"72250",
    "sg:province":"Baden-W\u00fcrttemberg",
    "wof:name":"Krankenhausvollapotheke Im Kreiskrankenhaus",
    "wof:placetype":"venue"
},
  "geometry": {"coordinates":[8.403532,48.476986],"type":"Point"}
}