{
  "type": "Feature",
  "properties": {
    "iso:country":"DE",
    "sg:address":"Friedrich-Ebert-Str. 75a",
    "sg:city":"Erzhausen",
    "sg:phone":"+49 6150/980720",
    "sg:postcode":"64390",
    "sg:province":"Hessen",
    "wof:name":"Stratford-services Ohg",
    "wof:placetype":"venue"
},
  "geometry": {"coordinates":[8.644033432,49.9533081055],"type":"Point"}
}