{
  "type": "Feature",
  "properties": {
    "iso:country":"DE",
    "sg:address":"Ostlandstr. 3",
    "sg:city":"Schwanewede",
    "sg:phone":"+49 4209/837",
    "sg:postcode":"28790",
    "sg:province":"Niedersachsen",
    "wof:name":"Collings System Gmbh",
    "wof:placetype":"venue"
},
  "geometry": {"coordinates":[8.590284,53.224648],"type":"Point"}
}