{
  "type": "Feature",
  "properties": {
    "iso:country":"DE",
    "sg:address":"Friedrichstr 68",
    "sg:city":"Iserlohn",
    "sg:phone":"+49 2371/13096",
    "sg:postcode":"58636",
    "sg:province":"Nordrhein-Westfalen",
    "wof:name":"Richard Wrede Gmbh & Co Kg",
    "wof:placetype":"venue"
},
  "geometry": {"coordinates":[7.707785,51.372459],"type":"Point"}
}