{
  "type": "Feature",
  "properties": {
    "iso:country":"DE",
    "sg:address":"\u00c4chterkrommert 1",
    "sg:city":"Rhede",
    "sg:phone":"+49 2872/980555",
    "sg:postcode":"46414",
    "sg:province":"Nordrhein-Westfalen",
    "wof:name":"Gastst\u00e4tte Hubert Enck",
    "wof:placetype":"venue"
},
  "geometry": {"coordinates":[6.7139492035,51.8000030518],"type":"Point"}
}