{
  "type": "Feature",
  "properties": {
    "iso:country":"DE",
    "sg:address":"Runebergweg 14",
    "sg:city":"Berlin",
    "sg:phone":"+49 30/36803025",
    "sg:postcode":"14089",
    "sg:province":"Berlin",
    "wof:name":"Shm Strassen U Tiefbau Gmbh",
    "wof:placetype":"venue"
},
  "geometry": {"coordinates":[13.146861,52.455181],"type":"Point"}
}