{
  "type": "Feature",
  "properties": {
    "iso:country":"DE",
    "sg:address":"Westerwaldstr. 78",
    "sg:city":"Bendorf",
    "sg:phone":"+49 2601/2440",
    "sg:postcode":"56170",
    "sg:province":"Rheinland-Pfalz",
    "wof:name":"Dieter Weyand",
    "wof:placetype":"venue"
},
  "geometry": {"coordinates":[7.6022381783,50.4592056274],"type":"Point"}
}