{
  "type": "Feature",
  "properties": {
    "iso:country":"DE",
    "sg:address":"Rote Str. 15",
    "sg:city":"G\u00f6ttingen",
    "sg:phone":"+49 551/58226",
    "sg:postcode":"37073",
    "sg:province":"Niedersachsen",
    "wof:name":"Horst Schlichting Antiquit\u00e4ten",
    "wof:placetype":"venue"
},
  "geometry": {"coordinates":[9.936293,51.532906],"type":"Point"}
}