{
  "type": "Feature",
  "properties": {
    "iso:country":"DE",
    "sg:address":"Wilhelmsh\u00f6her Str. 17",
    "sg:city":"Velbert",
    "sg:phone":"+49 2052/1540",
    "sg:postcode":"42555",
    "sg:province":"Nordrhein-Westfalen",
    "wof:name":"Dohm & Huly Malerbetrieb Inh. Thomas Langkamp E. Kfm.",
    "wof:placetype":"venue"
},
  "geometry": {"coordinates":[7.119753,51.360195],"type":"Point"}
}