{
  "type": "Feature",
  "properties": {
    "iso:country":"DE",
    "sg:address":"Beethovenstr. 30",
    "sg:city":"Gro\u00df-Zimmern",
    "sg:phone":"+49 6071/41786",
    "sg:postcode":"64846",
    "sg:province":"Hessen",
    "wof:name":"Lingemann",
    "wof:placetype":"venue"
},
  "geometry": {"coordinates":[8.825317,49.869316],"type":"Point"}
}