{
  "type": "Feature",
  "properties": {
    "iso:country":"DE",
    "sg:address":"Meinert-L\u00f6ffler-Str. 75",
    "sg:city":"Bremen",
    "sg:phone":"+49 421/6520960",
    "sg:postcode":"28755",
    "sg:province":"Bremen",
    "wof:name":"Claus Gehlken",
    "wof:placetype":"venue"
},
  "geometry": {"coordinates":[8.6174697876,53.1922988892],"type":"Point"}
}