{
  "type": "Feature",
  "properties": {
    "iso:country":"DE",
    "sg:address":"Franz-Best-Weg 29",
    "sg:city":"Darmstadt",
    "sg:phone":"+49 6151/593188",
    "sg:postcode":"64297",
    "sg:province":"Hessen",
    "wof:name":"Rolf R\u00fcdiger Metzner Architekt",
    "wof:placetype":"venue"
},
  "geometry": {"coordinates":[8.653682,49.808647],"type":"Point"}
}