{
  "type": "Feature",
  "properties": {
    "iso:country":"DE",
    "sg:address":"Palmbergstr.",
    "sg:city":"Gerolsheim",
    "sg:phone":"+49 6238/2886",
    "sg:postcode":"67229",
    "sg:province":"Rheinland-Pfalz",
    "wof:name":"Sch\u00fctzenhaus",
    "wof:placetype":"venue"
},
  "geometry": {"coordinates":[8.2581996918,49.5455818176],"type":"Point"}
}