{
  "type": "Feature",
  "properties": {
    "iso:country":"DE",
    "sg:address":"Solmsstr. 24",
    "sg:city":"Berlin",
    "sg:postcode":"10961",
    "sg:province":"Berlin",
    "wof:name":"Alexa Roh- Und Fassadenbau Gmbh",
    "wof:placetype":"venue"
},
  "geometry": {"coordinates":[13.391998291,52.490196228],"type":"Point"}
}