{
  "type": "Feature",
  "properties": {
    "iso:country":"DE",
    "sg:address":"Elversweg 6",
    "sg:city":"Hamburg",
    "sg:phone":"+49 40/73717070",
    "sg:postcode":"21037",
    "sg:province":"Hamburg",
    "wof:name":"Bading-schilder",
    "wof:placetype":"venue"
},
  "geometry": {"coordinates":[10.078552,53.473488],"type":"Point"}
}