{
  "type": "Feature",
  "properties": {
    "iso:country":"DE",
    "sg:address":"Oggenhauser Hauptstr. 33",
    "sg:city":"Heidenheim",
    "sg:phone":"+49 4973/2171447",
    "sg:postcode":"89522",
    "sg:province":"Baden-W\u00fcrttemberg",
    "wof:name":"Kreissparkasse Heidenheim",
    "wof:placetype":"venue"
},
  "geometry": {"coordinates":[10.23812,48.672161],"type":"Point"}
}