{
  "type": "Feature",
  "properties": {
    "iso:country":"DE",
    "sg:address":"Sch\u00fctzenrain 5",
    "sg:city":"Rosbach",
    "sg:phone":"+49 6003/1755",
    "sg:postcode":"61191",
    "sg:province":"Hessen",
    "wof:name":"K.-h. Hofmann",
    "wof:placetype":"venue"
},
  "geometry": {"coordinates":[8.6923503876,50.3052864075],"type":"Point"}
}