{
  "type": "Feature",
  "properties": {
    "iso:country":"DE",
    "sg:address":"Markt 3",
    "sg:city":"Bad Gandersheim",
    "sg:phone":"+49 5382/4870",
    "sg:postcode":"37581",
    "sg:province":"Niedersachsen",
    "wof:name":"Pizzeria Napoli",
    "wof:placetype":"venue"
},
  "geometry": {"coordinates":[10.0243291855,51.8704872131],"type":"Point"}
}