{
  "type": "Feature",
  "properties": {
    "iso:country":"DE",
    "sg:address":"Kirchh\u00f6f 2",
    "sg:city":"Biederbach",
    "sg:phone":"+49 7682/1364",
    "sg:postcode":"79215",
    "sg:province":"Baden-W\u00fcrttemberg",
    "wof:name":"Kath. Pfarramt Oberbiederbach",
    "wof:placetype":"venue"
},
  "geometry": {"coordinates":[8.02754879,48.2198181152],"type":"Point"}
}