{
  "type": "Feature",
  "properties": {
    "iso:country":"DE",
    "sg:address":"Oldenburger Str. 66",
    "sg:city":"K\u00f6ln",
    "sg:phone":"+49 221/741826",
    "sg:postcode":"50737",
    "sg:province":"Nordrhein-Westfalen",
    "wof:name":"Wilden Gmbh",
    "wof:placetype":"venue"
},
  "geometry": {"coordinates":[6.9276800156,50.9979057312],"type":"Point"}
}