{
  "type": "Feature",
  "properties": {
    "iso:country":"DE",
    "sg:address":"Mahl\u00e4ckerstr. 173",
    "sg:city":"Schw\u00e4bisch Hall",
    "sg:phone":"+49 7907/9800",
    "sg:postcode":"74523",
    "sg:province":"Baden-W\u00fcrttemberg",
    "wof:name":"Schaffitzel M\u00f6belwerk Gmbh & Co.",
    "wof:placetype":"venue"
},
  "geometry": {"coordinates":[9.83583,49.09602],"type":"Point"}
}