{
  "type": "Feature",
  "properties": {
    "iso:country":"DE",
    "sg:address":"Frankfurter Str. 15",
    "sg:city":"Marburg",
    "sg:phone":"+49 6421/25453",
    "sg:postcode":"35037",
    "sg:province":"Hessen",
    "wof:name":"E. Althaus & R. Stephan",
    "wof:placetype":"venue"
},
  "geometry": {"coordinates":[8.7668352127,50.8026618958],"type":"Point"}
}