{
  "type": "Feature",
  "properties": {
    "iso:country":"DE",
    "sg:address":"Bergstr. 1",
    "sg:city":"Badersleben",
    "sg:phone":"+49 39422/232",
    "sg:postcode":"38836",
    "sg:province":"Sachsen-Anhalt",
    "wof:name":"Bhg Handels- Gmbh",
    "wof:placetype":"venue"
},
  "geometry": {"coordinates":[10.8925056458,51.9887390137],"type":"Point"}
}