{
  "type": "Feature",
  "properties": {
    "iso:country":"DE",
    "sg:address":"Fahrenheitstr. 1",
    "sg:city":"Bremen",
    "sg:phone":"+49 421/6169686",
    "sg:postcode":"28359",
    "sg:province":"Bremen",
    "wof:name":"Zooga Beetzendorf Gartenbau Gmbh",
    "wof:placetype":"venue"
},
  "geometry": {"coordinates":[8.847763,53.107861],"type":"Point"}
}