{
  "type": "Feature",
  "properties": {
    "iso:country":"DE",
    "sg:address":"Hohenaspen 14",
    "sg:city":"Rauenberg",
    "sg:phone":"+49 4962/2263448",
    "sg:postcode":"69231",
    "sg:province":"Baden-W\u00fcrttemberg",
    "wof:name":"Burck & Manuel Gmbh",
    "wof:placetype":"venue"
},
  "geometry": {"coordinates":[8.697581,49.275452],"type":"Point"}
}