{
  "type": "Feature",
  "properties": {
    "iso:country":"DE",
    "sg:address":"Blankeneser Chaussee 29",
    "sg:city":"Schenefeld",
    "sg:phone":"+49 40/8308640",
    "sg:postcode":"22869",
    "sg:province":"Schleswig-Holstein",
    "wof:name":"Gerd Ellerbrock",
    "wof:placetype":"venue"
},
  "geometry": {"coordinates":[9.822357,53.597263],"type":"Point"}
}