{
  "type": "Feature",
  "properties": {
    "iso:country":"DE",
    "sg:address":"Backhausgasse 6",
    "sg:city":"Siefersheim",
    "sg:phone":"+49 6703/1587",
    "sg:postcode":"55599",
    "sg:province":"Rheinland-Pfalz",
    "wof:name":"Heinrich W. Bachmann",
    "wof:placetype":"venue"
},
  "geometry": {"coordinates":[7.958022,49.797287],"type":"Point"}
}