{
  "type": "Feature",
  "properties": {
    "iso:country":"DE",
    "sg:address":"Lilienweg 5",
    "sg:city":"Weinstadt",
    "sg:phone":"+49 7151/64334",
    "sg:postcode":"71384",
    "sg:province":"Baden-W\u00fcrttemberg",
    "wof:name":"Partnerschaftsverein Weinstadt Parthenay",
    "wof:placetype":"venue"
},
  "geometry": {"coordinates":[9.3554553986,48.8101730347],"type":"Point"}
}