{
  "type": "Feature",
  "properties": {
    "iso:country":"DE",
    "sg:address":"Sch\u00f6nberger Str. 29",
    "sg:city":"Gaildorf",
    "sg:phone":"+49 7971/95850",
    "sg:postcode":"74405",
    "sg:province":"Baden-W\u00fcrttemberg",
    "wof:name":"Rettenmeier Gaildorf-unterrot Gmbh",
    "wof:placetype":"venue"
},
  "geometry": {"coordinates":[9.78094,48.978928],"type":"Point"}
}