{
  "type": "Feature",
  "properties": {
    "iso:country":"DE",
    "sg:address":"Friedl\u00e4nder Weg 54",
    "sg:city":"G\u00f6ttingen",
    "sg:phone":"+49 551/548770",
    "sg:postcode":"37085",
    "sg:province":"Niedersachsen",
    "wof:name":"Peter Roeder Von Diersburg Und Groschupf",
    "wof:placetype":"venue"
},
  "geometry": {"coordinates":[9.9460010529,51.5279426575],"type":"Point"}
}