{
  "type": "Feature",
  "properties": {
    "iso:country":"DE",
    "sg:address":"Burgenlandweg 2B",
    "sg:city":"K\u00f6ln",
    "sg:phone":"+49 221/481781",
    "sg:postcode":"50858",
    "sg:province":"Nordrhein-Westfalen",
    "wof:name":"V. Schr\u00f6der Rechtsanwalt",
    "wof:placetype":"venue"
},
  "geometry": {"coordinates":[6.8662810326,50.9301986694],"type":"Point"}
}