{
  "type": "Feature",
  "properties": {
    "iso:country":"DE",
    "sg:address":"Cronenberger Str. 200",
    "sg:city":"Solingen",
    "sg:phone":"+49 212/54177",
    "sg:postcode":"42651",
    "sg:province":"Nordrhein-Westfalen",
    "wof:name":"Sigurd Bickenbach Architekt",
    "wof:placetype":"venue"
},
  "geometry": {"coordinates":[7.098263,51.184292],"type":"Point"}
}