{
  "type": "Feature",
  "properties": {
    "iso:country":"DE",
    "sg:address":"Reckensteinstr. 1",
    "sg:city":"Mudersbach",
    "sg:phone":"+49 2745/930093",
    "sg:postcode":"57555",
    "sg:province":"Rheinland-Pfalz",
    "wof:name":"Bautec Bautr\u00e4ger Und Projekt- Entwicklungs Gmbh",
    "wof:placetype":"venue"
},
  "geometry": {"coordinates":[7.939777,50.826557],"type":"Point"}
}