{
  "type": "Feature",
  "properties": {
    "iso:country":"DE",
    "sg:address":"Sch\u00e4ferkampsweg 6",
    "sg:city":"Henstedt-Ulzburg",
    "sg:phone":"+49 4193/7100",
    "sg:postcode":"24558",
    "sg:province":"Schleswig-Holstein",
    "wof:name":"Britta M\u00f6hlenbrock Rechtsanw\u00e4ltin",
    "wof:placetype":"venue"
},
  "geometry": {"coordinates":[9.9957923889,53.7616233826],"type":"Point"}
}