{
  "type": "Feature",
  "properties": {
    "iso:country":"DE",
    "sg:address":"Wiesenstr. 1",
    "sg:city":"Herzogenrath",
    "sg:phone":"+49 2406/3868",
    "sg:postcode":"52134",
    "sg:province":"Nordrhein-Westfalen",
    "wof:name":"P. Horn",
    "wof:placetype":"venue"
},
  "geometry": {"coordinates":[6.093211174,50.8653907776],"type":"Point"}
}