{
  "type": "Feature",
  "properties": {
    "iso:country":"DE",
    "sg:address":"Rather Str. 220",
    "sg:city":"Krefeld",
    "sg:phone":"+49 2151/943040",
    "sg:postcode":"47829",
    "sg:province":"Nordrhein-Westfalen",
    "wof:name":"Rocholl Gmbh",
    "wof:placetype":"venue"
},
  "geometry": {"coordinates":[6.622422,51.375717],"type":"Point"}
}