{
  "type": "Feature",
  "properties": {
    "iso:country":"DE",
    "sg:address":"Haimhauserstr. 3a",
    "sg:city":"M\u00fcnchen",
    "sg:phone":"+49 89/3267940",
    "sg:postcode":"80802",
    "sg:province":"Bayern",
    "wof:name":"Tece Development And Engineering Gmbh",
    "wof:placetype":"venue"
},
  "geometry": {"coordinates":[11.587702,48.162415],"type":"Point"}
}