{
  "type": "Feature",
  "properties": {
    "iso:country":"DE",
    "sg:address":"Am Bahndamm 16 a",
    "sg:city":"Probstzella",
    "sg:phone":"+49 36735/70531",
    "sg:postcode":"07330",
    "sg:province":"Th\u00fcringen",
    "wof:name":"J. T\u00f6pel",
    "wof:placetype":"venue"
},
  "geometry": {"coordinates":[11.384349,50.527153],"type":"Point"}
}