{
  "type": "Feature",
  "properties": {
    "iso:country":"DE",
    "sg:address":"Meeraner Str. 9",
    "sg:city":"Berlin",
    "sg:phone":"+49 30/54801979",
    "sg:postcode":"12681",
    "sg:province":"Berlin",
    "wof:name":"Berhan Import-export Handelsges. Mbh",
    "wof:placetype":"venue"
},
  "geometry": {"coordinates":[13.5237722397,52.5287322998],"type":"Point"}
}