{
  "type": "Feature",
  "properties": {
    "iso:country":"DE",
    "sg:address":"Apfelstr. 180 a",
    "sg:city":"Bielefeld",
    "sg:phone":"+49 521/83266",
    "sg:postcode":"33611",
    "sg:province":"Nordrhein-Westfalen",
    "wof:name":"Heinz Obermann Gmbh",
    "wof:placetype":"venue"
},
  "geometry": {"coordinates":[8.5412187576,52.0509605408],"type":"Point"}
}