{
  "type": "Feature",
  "properties": {
    "iso:country":"DE",
    "sg:address":"Auf dem Bohnenberg",
    "sg:city":"Steinwenden",
    "sg:phone":"+49 6371/50487",
    "sg:postcode":"66879",
    "sg:province":"Rheinland-Pfalz",
    "wof:name":"C\u00e4cilie Klein",
    "wof:placetype":"venue"
},
  "geometry": {"coordinates":[7.5097222328,49.4503288269],"type":"Point"}
}