{
  "type": "Feature",
  "properties": {
    "iso:country":"DE",
    "sg:address":"Auf dem Teich 5",
    "sg:city":"Nickenich",
    "sg:postcode":"56645",
    "sg:province":"Rheinland-Pfalz",
    "wof:name":"Hamann Verm\u00f6gens- Gesellschaft Mbh & Co. Kg",
    "wof:placetype":"venue"
},
  "geometry": {"coordinates":[7.3320398331,50.4057884216],"type":"Point"}
}