{
  "type": "Feature",
  "properties": {
    "iso:country":"DE",
    "sg:address":"Fleischerwinkel 6",
    "sg:city":"Kiebitz",
    "sg:phone":"+49 34362/33908",
    "sg:postcode":"04720",
    "sg:province":"Sachsen",
    "wof:name":"C. Zergiebel",
    "wof:placetype":"venue"
},
  "geometry": {"coordinates":[13.0784053802,51.1869430542],"type":"Point"}
}