{
  "type": "Feature",
  "properties": {
    "iso:country":"DE",
    "sg:address":"L\u00fctzowplatz 9",
    "sg:city":"Berlin",
    "sg:phone":"+49 30/2613805",
    "sg:postcode":"10785",
    "sg:province":"Berlin",
    "wof:name":"Haus Am L\u00fctzowplatz",
    "wof:placetype":"venue"
},
  "geometry": {"coordinates":[13.353332,52.504387],"type":"Point"}
}