{
  "type": "Feature",
  "properties": {
    "iso:country":"DE",
    "sg:address":"Gottfried-J\u00e4nichen-Weg 22",
    "sg:city":"Leipzig",
    "sg:phone":"+49 341/6516425",
    "sg:postcode":"04316",
    "sg:province":"Sachsen",
    "wof:name":"Faber & Faber",
    "wof:placetype":"venue"
},
  "geometry": {"coordinates":[12.4557199478,51.3222198486],"type":"Point"}
}