{
  "type": "Feature",
  "properties": {
    "iso:country":"DE",
    "sg:address":"Maria-G\u00f6ppert-Weg 15",
    "sg:city":"G\u00f6ttingen",
    "sg:phone":"+49 551/373269",
    "sg:postcode":"37077",
    "sg:province":"Niedersachsen",
    "wof:name":"Dau Vertriebsb\u00fcro Nord",
    "wof:placetype":"venue"
},
  "geometry": {"coordinates":[9.93235,51.57196],"type":"Point"}
}