{
  "type": "Feature",
  "properties": {
    "iso:country":"DE",
    "sg:address":"Berliner Str. 109",
    "sg:city":"Wuppertal",
    "sg:phone":"+49 202/642321",
    "sg:postcode":"42275",
    "sg:province":"Nordrhein-Westfalen",
    "wof:name":"Uzeri Omonia",
    "wof:placetype":"venue"
},
  "geometry": {"coordinates":[7.2158842087,51.2750205994],"type":"Point"}
}