{
  "type": "Feature",
  "properties": {
    "iso:country":"DE",
    "sg:address":"Freiheitsstr. 55",
    "sg:city":"Dorsten",
    "sg:phone":"+49 2362/68195",
    "sg:postcode":"46284",
    "sg:province":"Nordrhein-Westfalen",
    "wof:name":"Saloniki Grill",
    "wof:placetype":"venue"
},
  "geometry": {"coordinates":[6.950138092,51.6808319092],"type":"Point"}
}