{
  "type": "Feature",
  "properties": {
    "iso:country":"DE",
    "sg:address":"Steinb\u00e4chlein 6",
    "sg:city":"Steinach",
    "sg:phone":"+49 36762/31251",
    "sg:postcode":"96523",
    "sg:province":"Th\u00fcringen",
    "wof:name":"Heinz Greiner-wohlleben",
    "wof:placetype":"venue"
},
  "geometry": {"coordinates":[11.154915,50.432404],"type":"Point"}
}