{
  "type": "Feature",
  "properties": {
    "iso:country":"DE",
    "sg:address":"Hofer Str. 13",
    "sg:city":"Oelsnitz",
    "sg:phone":"+49 37421/22992",
    "sg:postcode":"08606",
    "sg:province":"Sachsen",
    "wof:name":"Siegfried Bittrich",
    "wof:placetype":"venue"
},
  "geometry": {"coordinates":[12.159077,50.408306],"type":"Point"}
}