{
  "type": "Feature",
  "properties": {
    "iso:country":"DE",
    "sg:address":"Korbacher Str. 16",
    "sg:city":"Twistetal",
    "sg:phone":"+49 5631/61182",
    "sg:postcode":"34477",
    "sg:province":"Hessen",
    "wof:name":"Heinrich M\u00fcller",
    "wof:placetype":"venue"
},
  "geometry": {"coordinates":[8.905786,51.30714],"type":"Point"}
}