{
  "type": "Feature",
  "properties": {
    "iso:country":"DE",
    "sg:address":"Untere Kellerstr. 7 a",
    "sg:city":"Feucht",
    "sg:postcode":"90537",
    "sg:province":"Bayern",
    "wof:name":"Henck-immobilien Gmbh",
    "wof:placetype":"venue"
},
  "geometry": {"coordinates":[11.211739,49.375851],"type":"Point"}
}