{
  "type": "Feature",
  "properties": {
    "iso:country":"DE",
    "sg:address":"Alte Wache 20",
    "sg:city":"Lauenburg",
    "sg:phone":"+49 4153/58480",
    "sg:postcode":"21481",
    "sg:province":"Schleswig-Holstein",
    "wof:name":"Wilhelm Steffens",
    "wof:placetype":"venue"
},
  "geometry": {"coordinates":[10.555336,53.373756],"type":"Point"}
}