{
  "type": "Feature",
  "properties": {
    "iso:country":"DE",
    "sg:address":"Wolgograder Allee",
    "sg:city":"Chemnitz",
    "sg:postcode":"09123",
    "sg:province":"Sachsen",
    "wof:name":"Krone-markt",
    "wof:placetype":"venue"
},
  "geometry": {"coordinates":[12.9021959305,50.7880516052],"type":"Point"}
}