{
  "type": "Feature",
  "properties": {
    "iso:country":"DE",
    "sg:address":"Parkstr. 1",
    "sg:city":"Bad Kissingen",
    "sg:phone":"+49 971/6994717",
    "sg:postcode":"97688",
    "sg:province":"Bayern",
    "wof:name":"Erich Prokisch Praxis F\u00fcr Ergotherapie",
    "wof:placetype":"venue"
},
  "geometry": {"coordinates":[10.063288,50.194923],"type":"Point"}
}