{
  "type": "Feature",
  "properties": {
    "iso:country":"DE",
    "sg:address":"Bahnhofstr.21",
    "sg:city":"Teuchtlingen/Wettelsheim",
    "sg:phone":"+49 9142/96750",
    "sg:postcode":"91757",
    "sg:province":"Bayern",
    "wof:name":"K\u00d6hnlein Bau Gmbh",
    "wof:placetype":"venue"
},
  "geometry": {"coordinates":[10.886711,48.985989],"type":"Point"}
}