{
  "type": "Feature",
  "properties": {
    "iso:country":"DE",
    "sg:address":"Markt 21",
    "sg:city":"Schm\u00f6lln",
    "sg:phone":"+49 34491/22497",
    "sg:postcode":"04626",
    "sg:province":"Th\u00fcringen",
    "wof:name":"Rolf G\u00f6the",
    "wof:placetype":"venue"
},
  "geometry": {"coordinates":[12.351452,50.894711],"type":"Point"}
}