{
  "type": "Feature",
  "properties": {
    "iso:country":"DE",
    "sg:address":"Ortsstr. 10",
    "sg:city":"Heideland",
    "sg:phone":"+49 36691/52915",
    "sg:postcode":"07613",
    "sg:province":"Th\u00fcringen",
    "wof:name":"Braune",
    "wof:placetype":"venue"
},
  "geometry": {"coordinates":[11.961511,51.006172],"type":"Point"}
}