{
  "type": "Feature",
  "properties": {
    "iso:country":"DE",
    "sg:address":"Altenhoferstr. 3",
    "sg:city":"Solingen",
    "sg:phone":"+49 212",
    "sg:postcode":"42719",
    "sg:province":"Nordrhein-Westfalen",
    "wof:name":"Sommer - Ingenieurb\u00fcro F\u00fcr Tragwerksplanung",
    "wof:placetype":"venue"
},
  "geometry": {"coordinates":[7.0399570465,51.1830215454],"type":"Point"}
}