{
  "type": "Feature",
  "properties": {
    "iso:country":"DE",
    "sg:address":"Waldburgstr. 231",
    "sg:city":"Stuttgart",
    "sg:phone":"+49 711/744960",
    "sg:postcode":"70565",
    "sg:province":"Baden-W\u00fcrttemberg",
    "wof:name":"Prof. Bosse Architekt",
    "wof:placetype":"venue"
},
  "geometry": {"coordinates":[9.088884,48.718662],"type":"Point"}
}