{
  "type": "Feature",
  "properties": {
    "iso:country":"DE",
    "sg:address":"Maybachstr. 12",
    "sg:city":"Korb",
    "sg:phone":"+49 7151/37032",
    "sg:postcode":"71404",
    "sg:province":"Baden-W\u00fcrttemberg",
    "wof:name":"Active Garden Sven Freiberg",
    "wof:placetype":"venue"
},
  "geometry": {"coordinates":[9.3643455505,48.8355484009],"type":"Point"}
}