{
  "type": "Feature",
  "properties": {
    "iso:country":"DE",
    "sg:address":"Am Gr\u00fcn 26",
    "sg:city":"Rastatt",
    "sg:phone":"+49 7222/33772",
    "sg:postcode":"76437",
    "sg:province":"Baden-W\u00fcrttemberg",
    "wof:name":"Semper Gmbh",
    "wof:placetype":"venue"
},
  "geometry": {"coordinates":[8.201429,48.857307],"type":"Point"}
}