{
  "type": "Feature",
  "properties": {
    "iso:country":"DE",
    "sg:address":"Hauptstra\u00dfe 168",
    "sg:city":"Bielefeld",
    "sg:phone":"+49 521",
    "sg:postcode":"33647",
    "sg:province":"Nordrhein-Westfalen",
    "wof:name":"Lehrmann Bueroausstattung",
    "wof:placetype":"venue"
},
  "geometry": {"coordinates":[8.5050935745,51.995464325],"type":"Point"}
}