{
  "type": "Feature",
  "properties": {
    "iso:country":"DE",
    "sg:address":"Karlsruher Str. 20",
    "sg:city":"Hockenheim",
    "sg:phone":"+49 6205/102088",
    "sg:postcode":"68766",
    "sg:province":"Baden-W\u00fcrttemberg",
    "wof:name":"D2-fachcenter Hockenheim",
    "wof:placetype":"venue"
},
  "geometry": {"coordinates":[8.5434141159,49.3181495667],"type":"Point"}
}