{
  "type": "Feature",
  "properties": {
    "iso:country":"DE",
    "sg:address":"Gartenstr. 3",
    "sg:city":"Wasb\u00fcttel",
    "sg:phone":"+49 5374/6594",
    "sg:postcode":"38553",
    "sg:province":"Niedersachsen",
    "wof:name":"Axel M\u00f6hle",
    "wof:placetype":"venue"
},
  "geometry": {"coordinates":[10.5947170258,52.4107627869],"type":"Point"}
}