{
  "type": "Feature",
  "properties": {
    "iso:country":"DE",
    "sg:address":"Am Steinberg 47",
    "sg:city":"Gummersbach",
    "sg:phone":"+49 2261/23931",
    "sg:postcode":"51643",
    "sg:province":"Nordrhein-Westfalen",
    "wof:name":"Bernd Cieplik Ingenieur",
    "wof:placetype":"venue"
},
  "geometry": {"coordinates":[7.5528950691,51.0353660583],"type":"Point"}
}