{
  "type": "Feature",
  "properties": {
    "iso:country":"DE",
    "sg:address":"Landhausstr. 4",
    "sg:city":"Bad Herrenalb",
    "sg:phone":"+49 7083/51573",
    "sg:postcode":"76332",
    "sg:province":"Baden-W\u00fcrttemberg",
    "wof:name":"Sps Transport-gmbh",
    "wof:placetype":"venue"
},
  "geometry": {"coordinates":[8.4641895294,48.8167953491],"type":"Point"}
}