{
  "type": "Feature",
  "properties": {
    "iso:country":"DE",
    "sg:address":"Klarastr 3",
    "sg:city":"Dresden",
    "sg:phone":"+49 351",
    "sg:postcode":"01099",
    "sg:province":"Sachsen",
    "wof:name":"Pension Am Waldschloesschen Dresden",
    "wof:placetype":"venue"
},
  "geometry": {"coordinates":[13.781541,51.067284],"type":"Point"}
}