{
  "type": "Feature",
  "properties": {
    "iso:country":"DE",
    "sg:address":"Domplatz 48",
    "sg:city":"Halberstadt",
    "sg:postcode":"38820",
    "sg:province":"Sachsen-Anhalt",
    "wof:name":"H\u00fcldell Und Hallegger Architekten",
    "wof:placetype":"venue"
},
  "geometry": {"coordinates":[11.045505,51.896023],"type":"Point"}
}