{
  "type": "Feature",
  "properties": {
    "iso:country":"DE",
    "sg:address":"Hasen\u00e4cker 16",
    "sg:city":"Wasserburg",
    "sg:phone":"+49 8382/98570",
    "sg:postcode":"88142",
    "sg:province":"Bayern",
    "wof:name":"Nusser Dental Labor Gmbh",
    "wof:placetype":"venue"
},
  "geometry": {"coordinates":[9.634049,47.577],"type":"Point"}
}