{
  "type": "Feature",
  "properties": {
    "iso:country":"DE",
    "sg:address":"Schlettacher Str.",
    "sg:city":"Weitramsdorf",
    "sg:phone":"+49 9561/30096",
    "sg:postcode":"96479",
    "sg:province":"Bayern",
    "wof:name":"Gemeindeb\u00fccherei",
    "wof:placetype":"venue"
},
  "geometry": {"coordinates":[10.87707,50.26091],"type":"Point"}
}