{
  "type": "Feature",
  "properties": {
    "iso:country":"DE",
    "sg:address":"Mozartstr 14-16",
    "sg:city":"Hannover",
    "sg:phone":"+49 511/989640",
    "sg:postcode":"30173",
    "sg:province":"Niedersachsen",
    "wof:name":"Ibz Me\u00dftechnik Gmbh",
    "wof:placetype":"venue"
},
  "geometry": {"coordinates":[9.7533,52.356525],"type":"Point"}
}