{
  "type": "Feature",
  "properties": {
    "iso:country":"DE",
    "sg:address":"Bahnhofstr. 6",
    "sg:city":"Zittau",
    "sg:postcode":"02763",
    "sg:province":"Sachsen",
    "wof:name":"Sek Managementberatung Und Handelsgesellschaft Mbh",
    "wof:placetype":"venue"
},
  "geometry": {"coordinates":[14.8057022095,50.8997993469],"type":"Point"}
}