{
  "type": "Feature",
  "properties": {
    "iso:country":"DE",
    "sg:address":"Moltkestr. 50",
    "sg:city":"Hamburg",
    "sg:postcode":"20253",
    "sg:province":"Hamburg",
    "wof:name":"Grundst\u00fccksges. Harbke Mbh & Co.",
    "wof:placetype":"venue"
},
  "geometry": {"coordinates":[9.9713602066,53.5805473328],"type":"Point"}
}