{
  "type": "Feature",
  "properties": {
    "iso:country":"DE",
    "sg:address":"Eisenacher Str. 1",
    "sg:city":"Dortmund",
    "sg:postcode":"44143",
    "sg:province":"Nordrhein-Westfalen",
    "wof:name":"Van Vuuren M\u00f6belservice Gmbh",
    "wof:placetype":"venue"
},
  "geometry": {"coordinates":[7.4866299629,51.5182495117],"type":"Point"}
}