{
  "type": "Feature",
  "properties": {
    "iso:country":"DE",
    "sg:address":"Hopfenstr. 10",
    "sg:city":"Augsburg",
    "sg:phone":"+49 821/881161",
    "sg:postcode":"86179",
    "sg:province":"Bayern",
    "wof:name":"Blumen Werner",
    "wof:placetype":"venue"
},
  "geometry": {"coordinates":[10.897302,48.307053],"type":"Point"}
}