{
  "type": "Feature",
  "properties": {
    "iso:country":"DE",
    "sg:address":"Lehnp\u00fctz 8",
    "sg:city":"Bonn",
    "sg:phone":"+49 228/321964",
    "sg:postcode":"53177",
    "sg:province":"Nordrhein-Westfalen",
    "wof:name":"Josef Malcher",
    "wof:placetype":"venue"
},
  "geometry": {"coordinates":[7.156299,50.667824],"type":"Point"}
}