{
  "type": "Feature",
  "properties": {
    "iso:country":"DE",
    "sg:address":"B\u00fchlweg 26",
    "sg:city":"Argenb\u00fchl",
    "sg:phone":"+49 7566/2665",
    "sg:postcode":"88260",
    "sg:province":"Baden-W\u00fcrttemberg",
    "wof:name":"G\u00fcnther Klopp",
    "wof:placetype":"venue"
},
  "geometry": {"coordinates":[9.953836441,47.6880226135],"type":"Point"}
}