{
  "type": "Feature",
  "properties": {
    "iso:country":"DE",
    "sg:address":"Alte Landstr. 57 a",
    "sg:city":"Gro\u00dfhansdorf",
    "sg:phone":"+49 4102/66982",
    "sg:postcode":"22927",
    "sg:province":"Schleswig-Holstein",
    "wof:name":"Zellner Ingenieur",
    "wof:placetype":"venue"
},
  "geometry": {"coordinates":[10.2623853683,53.656539917],"type":"Point"}
}