{
  "type": "Feature",
  "properties": {
    "iso:country":"DE",
    "sg:address":"M\u00fchlstr. 4",
    "sg:city":"Gro\u00dfenhain",
    "sg:phone":"+49 3522/7454",
    "sg:postcode":"01558",
    "sg:province":"Sachsen",
    "wof:name":"Reit- Und Fahrverein E. V.",
    "wof:placetype":"venue"
},
  "geometry": {"coordinates":[13.5296525955,51.2802696228],"type":"Point"}
}