{
  "type": "Feature",
  "properties": {
    "iso:country":"DE",
    "sg:address":"Glambecker Str. 6",
    "sg:city":"Neustrelitz",
    "sg:phone":"+49 3981/205661",
    "sg:postcode":"17235",
    "sg:province":"Mecklenburg-Vorpommern",
    "wof:name":"J & D Bau Und Sanierungs Gmbh",
    "wof:placetype":"venue"
},
  "geometry": {"coordinates":[13.064403,53.364685],"type":"Point"}
}