{
  "type": "Feature",
  "properties": {
    "iso:country":"DE",
    "sg:address":"Oberlandscheid 3 a",
    "sg:city":"Burscheid",
    "sg:phone":"+49 2174/8102",
    "sg:postcode":"51399",
    "sg:province":"Nordrhein-Westfalen",
    "wof:name":"Gisela Trampert Heilpraktikerin",
    "wof:placetype":"venue"
},
  "geometry": {"coordinates":[7.1218891144,51.0740280151],"type":"Point"}
}