{
  "type": "Feature",
  "properties": {
    "iso:country":"DE",
    "sg:address":"Komphausbadstr. 28",
    "sg:city":"Aachen",
    "sg:phone":"+49 241/32647",
    "sg:postcode":"52062",
    "sg:province":"Nordrhein-Westfalen",
    "wof:name":"Baguetterie De Provence",
    "wof:placetype":"venue"
},
  "geometry": {"coordinates":[6.0886240005,50.7764587402],"type":"Point"}
}