{
  "type": "Feature",
  "properties": {
    "iso:country":"DE",
    "sg:address":"Breitenfelder Str. 10",
    "sg:city":"Leipzig",
    "sg:postcode":"04155",
    "sg:province":"Sachsen",
    "wof:name":"\u00dcberall Web Solutions Gmbh",
    "wof:placetype":"venue"
},
  "geometry": {"coordinates":[12.361243248,51.3613243103],"type":"Point"}
}