{
  "type": "Feature",
  "properties": {
    "iso:country":"DE",
    "sg:address":"Br\u00e4uhausstr. 18",
    "sg:city":"Planegg",
    "sg:phone":"+49 89/89930030",
    "sg:postcode":"82152",
    "sg:province":"Bayern",
    "wof:name":"Bistro Pe Es",
    "wof:placetype":"venue"
},
  "geometry": {"coordinates":[11.4227838516,48.1053657532],"type":"Point"}
}