{
  "type": "Feature",
  "properties": {
    "iso:country":"DE",
    "sg:address":"Ausleger 30",
    "sg:city":"Erftstadt",
    "sg:phone":"+49 2235/72585",
    "sg:postcode":"50374",
    "sg:province":"Nordrhein-Westfalen",
    "wof:name":"K. Kranz",
    "wof:placetype":"venue"
},
  "geometry": {"coordinates":[6.745743,50.832176],"type":"Point"}
}