{
  "type": "Feature",
  "properties": {
    "iso:country":"DE",
    "sg:address":"Kehdinger M\u00fchren 11",
    "sg:city":"Stade",
    "sg:phone":"+49 4141/46368",
    "sg:postcode":"21682",
    "sg:province":"Niedersachsen",
    "wof:name":"Jugendherberge Stade",
    "wof:placetype":"venue"
},
  "geometry": {"coordinates":[9.473072052,53.6039009094],"type":"Point"}
}