{
  "type": "Feature",
  "properties": {
    "iso:country":"DE",
    "sg:address":"Zum Saarpfalz-Park 310",
    "sg:city":"Bexbach",
    "sg:phone":"+49 6826/530920",
    "sg:postcode":"66450",
    "sg:province":"Saarland",
    "wof:name":"Effektiv!",
    "wof:placetype":"venue"
},
  "geometry": {"coordinates":[7.270866,49.35997],"type":"Point"}
}