{
  "type": "Feature",
  "properties": {
    "iso:country":"DE",
    "sg:city":"Buch",
    "sg:phone":"+49 6772/5542",
    "sg:postcode":"56357",
    "sg:province":"Rheinland-Pfalz",
    "wof:name":"Andrea Weyersbach",
    "wof:placetype":"venue"
},
  "geometry": {"coordinates":[7.875825,50.204887],"type":"Point"}
}