{
  "type": "Feature",
  "properties": {
    "iso:country":"DE",
    "sg:address":"Bahnhofstr. 15",
    "sg:city":"Neckargem\u00fcnd",
    "sg:phone":"+49 4962/236434",
    "sg:postcode":"69151",
    "sg:province":"Baden-W\u00fcrttemberg",
    "wof:name":"Bezirkssparkasse",
    "wof:placetype":"venue"
},
  "geometry": {"coordinates":[8.792995,49.394344],"type":"Point"}
}