{
  "type": "Feature",
  "properties": {
    "iso:country":"DE",
    "sg:address":"Salzstr. 47",
    "sg:city":"Freiburg",
    "sg:phone":"+49 761/24844",
    "sg:postcode":"79098",
    "sg:province":"Baden-W\u00fcrttemberg",
    "wof:name":"Der Blumenladen C. Fretter",
    "wof:placetype":"venue"
},
  "geometry": {"coordinates":[7.853795,47.993813],"type":"Point"}
}