{
  "type": "Feature",
  "properties": {
    "iso:country":"DE",
    "sg:address":"Grasweg 6 a",
    "sg:city":"Hamburg",
    "sg:phone":"+49 40/486282",
    "sg:postcode":"22299",
    "sg:province":"Hamburg",
    "wof:name":"Nehring & Thuroczy Gmbh",
    "wof:placetype":"venue"
},
  "geometry": {"coordinates":[10.0003,53.593719],"type":"Point"}
}