{
  "type": "Feature",
  "properties": {
    "iso:country":"DE",
    "sg:address":"Dycker Feld 24",
    "sg:city":"Solingen",
    "sg:phone":"+49 212/593097",
    "sg:postcode":"42653",
    "sg:province":"Nordrhein-Westfalen",
    "wof:name":"Siekmann Gmbh",
    "wof:placetype":"venue"
},
  "geometry": {"coordinates":[7.081828,51.198257],"type":"Point"}
}