{
  "type": "Feature",
  "properties": {
    "iso:country":"DE",
    "sg:address":"Erich-M\u00fchsam-Str. 8",
    "sg:city":"Zwickau",
    "sg:phone":"+49 375/472312",
    "sg:postcode":"08062",
    "sg:province":"Sachsen",
    "wof:name":"Heiko Pfeffer",
    "wof:placetype":"venue"
},
  "geometry": {"coordinates":[12.4734315872,50.6942481995],"type":"Point"}
}