{
  "type": "Feature",
  "properties": {
    "iso:country":"DE",
    "sg:address":"Fabriciusstr. 137",
    "sg:city":"Hamburg",
    "sg:phone":"+49 40/6421890",
    "sg:postcode":"22177",
    "sg:province":"Hamburg",
    "wof:name":"Dental Studio Hamburg Dsh Gmbh",
    "wof:placetype":"venue"
},
  "geometry": {"coordinates":[10.0659914017,53.6051483154],"type":"Point"}
}