{
  "type": "Feature",
  "properties": {
    "iso:country":"DE",
    "sg:address":"Im Gewerbegebiet 5",
    "sg:city":"Hahnbach",
    "sg:phone":"+49 9664/662",
    "sg:postcode":"92256",
    "sg:province":"Bayern",
    "wof:name":"H. Siegert",
    "wof:placetype":"venue"
},
  "geometry": {"coordinates":[11.790373,49.531708],"type":"Point"}
}