{
  "type": "Feature",
  "properties": {
    "iso:country":"DE",
    "sg:address":"Kurt-Schumacher-Str. 16",
    "sg:city":"Bergisch Gladbach",
    "sg:phone":"+49 2204/21702",
    "sg:postcode":"51427",
    "sg:province":"Nordrhein-Westfalen",
    "wof:name":"Messe Consulting-vilela Gmbh",
    "wof:placetype":"venue"
},
  "geometry": {"coordinates":[7.14197,50.952446],"type":"Point"}
}