{
  "type": "Feature",
  "properties": {
    "iso:country":"DE",
    "sg:address":"Am Birnbaum 2",
    "sg:city":"Trier",
    "sg:phone":"+49 651/28840",
    "sg:postcode":"54296",
    "sg:province":"Rheinland-Pfalz",
    "wof:name":"Prof. Dr. W. Ameling Gmbh",
    "wof:placetype":"venue"
},
  "geometry": {"coordinates":[6.6840062141,49.7535743713],"type":"Point"}
}