{
  "type": "Feature",
  "properties": {
    "iso:country":"DE",
    "sg:address":"Vaihinger Str. 54",
    "sg:city":"Leinfelden-Echterdingen",
    "sg:phone":"+49 711/7545610",
    "sg:postcode":"70771",
    "sg:province":"Baden-W\u00fcrttemberg",
    "wof:name":"W. Rist Ingenieur",
    "wof:placetype":"venue"
},
  "geometry": {"coordinates":[9.1121549606,48.7062568665],"type":"Point"}
}