{
  "type": "Feature",
  "properties": {
    "iso:country":"DE",
    "sg:address":"Grader Weg 58",
    "sg:city":"Papenburg",
    "sg:postcode":"26871",
    "sg:province":"Niedersachsen",
    "wof:name":"Hermann Mersmann E. K.",
    "wof:placetype":"venue"
},
  "geometry": {"coordinates":[7.419503212,53.0732269287],"type":"Point"}
}