{
  "type": "Feature",
  "properties": {
    "iso:country":"DE",
    "sg:address":"Valentin-Thierer-Str. 21",
    "sg:city":"Gerstetten",
    "sg:phone":"+49 7323/6302",
    "sg:postcode":"89547",
    "sg:province":"Baden-W\u00fcrttemberg",
    "wof:name":"Ev. Pfarramt",
    "wof:placetype":"venue"
},
  "geometry": {"coordinates":[9.959394455,48.6429138184],"type":"Point"}
}