{
  "type": "Feature",
  "properties": {
    "iso:country":"DE",
    "sg:address":"Schindlauchwiesenweg 10",
    "sg:city":"Rotenburg",
    "sg:postcode":"36199",
    "sg:province":"Hessen",
    "wof:name":"Urbana Baugesellschaft Mbh",
    "wof:placetype":"venue"
},
  "geometry": {"coordinates":[9.7240219116,50.9935569763],"type":"Point"}
}