{
  "type": "Feature",
  "properties": {
    "iso:country":"DE",
    "sg:address":"Marienstr. 49",
    "sg:city":"Cuxhaven",
    "sg:phone":"+49 4721/35756",
    "sg:postcode":"27472",
    "sg:province":"Niedersachsen",
    "wof:name":"Eiscafe R. Marinello",
    "wof:placetype":"venue"
},
  "geometry": {"coordinates":[8.697406,53.872036],"type":"Point"}
}