{
  "type": "Feature",
  "properties": {
    "iso:country":"DE",
    "sg:address":"Seestr. 3",
    "sg:city":"G\u00fcster",
    "sg:phone":"+49 4158/8203",
    "sg:postcode":"21514",
    "sg:province":"Schleswig-Holstein",
    "wof:name":"Karl Gloth Inh. Hans-j\u00fcrgen Swirski",
    "wof:placetype":"venue"
},
  "geometry": {"coordinates":[10.672049,53.535305],"type":"Point"}
}