{
  "type": "Feature",
  "properties": {
    "iso:country":"DE",
    "sg:address":"An der Silberh\u00fctte 14",
    "sg:city":"Erfurt",
    "sg:phone":"+49 361/5626540",
    "sg:postcode":"99094",
    "sg:province":"Th\u00fcringen",
    "wof:name":"Vema - Vereinigte Malergenossenschaft Eg",
    "wof:placetype":"venue"
},
  "geometry": {"coordinates":[11.0108194351,50.9589271545],"type":"Point"}
}