{
  "type": "Feature",
  "properties": {
    "iso:country":"DE",
    "sg:address":"Dehnhaide 18",
    "sg:city":"Hamburg",
    "sg:phone":"+49 40/53283165",
    "sg:postcode":"22081",
    "sg:province":"Hamburg",
    "wof:name":"Finn Holiday Reiseb\u00fcro",
    "wof:placetype":"venue"
},
  "geometry": {"coordinates":[10.0433530807,53.5789985657],"type":"Point"}
}