{
  "type": "Feature",
  "properties": {
    "iso:country":"DE",
    "sg:address":"Wallstr. 1",
    "sg:city":"Iserlohn",
    "sg:phone":"+49 2371/24439",
    "sg:postcode":"58638",
    "sg:province":"Nordrhein-Westfalen",
    "wof:name":"Iserlohner Verein F\u00fcr Vorbeugende Gesundheits-",
    "wof:placetype":"venue"
},
  "geometry": {"coordinates":[7.6940369606,51.3764762878],"type":"Point"}
}