{
  "type": "Feature",
  "properties": {
    "iso:country":"DE",
    "sg:address":"Wei\u00dfdornweg 27",
    "sg:city":"Schwerin",
    "sg:postcode":"19057",
    "sg:province":"Mecklenburg-Vorpommern",
    "wof:name":"Almut Rossburg",
    "wof:placetype":"venue"
},
  "geometry": {"coordinates":[11.333924,53.651218],"type":"Point"}
}