{
  "type": "Feature",
  "properties": {
    "iso:country":"DE",
    "sg:address":"Neulerstr. 6",
    "sg:city":"H\u00fcttlingen",
    "sg:phone":"+49 7361/73911",
    "sg:postcode":"73460",
    "sg:province":"Baden-W\u00fcrttemberg",
    "wof:name":"Walther-melber",
    "wof:placetype":"venue"
},
  "geometry": {"coordinates":[10.0906410217,48.9071731567],"type":"Point"}
}