{
  "type": "Feature",
  "properties": {
    "iso:country":"DE",
    "sg:address":"Erlenstr. 34-36",
    "sg:city":"Burgbrohl",
    "sg:postcode":"56659",
    "sg:province":"Rheinland-Pfalz",
    "wof:name":"Gustav Rhodius Gesell- Schaft Mit Beschr\u00e4nkter",
    "wof:placetype":"venue"
},
  "geometry": {"coordinates":[7.2735629082,50.4525108337],"type":"Point"}
}