{
  "type": "Feature",
  "properties": {
    "iso:country":"DE",
    "sg:address":"Duesseldorfer Str. 84",
    "sg:city":"Duesseldorf",
    "sg:phone":"+49 211/576148",
    "sg:postcode":"40545",
    "sg:province":"Nordrhein-Westfalen",
    "wof:name":"Ducaplast - Division Of David S Smith Plastics & Logistics",
    "wof:placetype":"venue"
},
  "geometry": {"coordinates":[6.7506051064,51.2284240723],"type":"Point"}
}