{
  "type": "Feature",
  "properties": {
    "iso:country":"DE",
    "sg:address":"Hansaring 5",
    "sg:city":"M\u00fcnster",
    "sg:phone":"+49 251/64856",
    "sg:postcode":"48155",
    "sg:province":"Nordrhein-Westfalen",
    "wof:name":"M. Huckenbeck",
    "wof:placetype":"venue"
},
  "geometry": {"coordinates":[7.637358,51.953064],"type":"Point"}
}