{
  "type": "Feature",
  "properties": {
    "iso:country":"DE",
    "sg:address":"Theodor-Heuss-Platz 10",
    "sg:city":"Bremerhaven",
    "sg:phone":"+49 471/413058",
    "sg:postcode":"27568",
    "sg:province":"Bremen",
    "wof:name":"Neckermann Reiseb\u00fcro",
    "wof:placetype":"venue"
},
  "geometry": {"coordinates":[8.5820817947,53.5442886353],"type":"Point"}
}