{
  "type": "Feature",
  "properties": {
    "iso:country":"DE",
    "sg:address":"L\u00f6hner Str. 194",
    "sg:city":"H\u00fcllhorst",
    "sg:phone":"+49 5744/4191",
    "sg:postcode":"32609",
    "sg:province":"Nordrhein-Westfalen",
    "wof:name":"Schlemmerst\u00fcbchen",
    "wof:placetype":"venue"
},
  "geometry": {"coordinates":[8.6984844208,52.2535095215],"type":"Point"}
}