{
  "type": "Feature",
  "properties": {
    "iso:country":"DE",
    "sg:address":"Goethestr. 28a",
    "sg:city":"R\u00f6dermark",
    "sg:phone":"+49 6074/96302",
    "sg:postcode":"63322",
    "sg:province":"Hessen",
    "wof:name":"G. Kappe Immobilienmakler",
    "wof:placetype":"venue"
},
  "geometry": {"coordinates":[8.8188610077,50.000202179],"type":"Point"}
}