{
  "type": "Feature",
  "properties": {
    "iso:country":"DE",
    "sg:address":"Mittelriedstr. 25",
    "sg:city":"B\u00fcrstadt",
    "sg:phone":"+49 6206/70680",
    "sg:postcode":"68642",
    "sg:province":"Hessen",
    "wof:name":"Erich R. Moos Kg",
    "wof:placetype":"venue"
},
  "geometry": {"coordinates":[8.4491920471,49.6466026306],"type":"Point"}
}