{
  "type": "Feature",
  "properties": {
    "iso:country":"DE",
    "sg:address":"Hauptstr. 38",
    "sg:city":"Karlsbad",
    "sg:phone":"+49 7202/2115",
    "sg:postcode":"76307",
    "sg:province":"Baden-W\u00fcrttemberg",
    "wof:name":"Anker",
    "wof:placetype":"venue"
},
  "geometry": {"coordinates":[8.5064458847,48.9148979187],"type":"Point"}
}