{
  "type": "Feature",
  "properties": {
    "iso:country":"DE",
    "sg:address":"Holunderweg 38",
    "sg:city":"M\u00f6nchengladbach",
    "sg:postcode":"41169",
    "sg:province":"Nordrhein-Westfalen",
    "wof:name":"Cosmarc Gmbh",
    "wof:placetype":"venue"
},
  "geometry": {"coordinates":[6.33572,51.193432],"type":"Point"}
}