{
  "type": "Feature",
  "properties": {
    "iso:country":"DE",
    "sg:address":"Wiesbadener Str. 63",
    "sg:city":"Mainz-Kastel",
    "sg:postcode":"55252",
    "sg:province":"Hessen",
    "wof:name":"Nicolas Innenausbau Gmbh",
    "wof:placetype":"venue"
},
  "geometry": {"coordinates":[8.273462,50.018326],"type":"Point"}
}