{
  "type": "Feature",
  "properties": {
    "iso:country":"DE",
    "sg:address":"Bromer Str. 3",
    "sg:city":"J\u00fcbar",
    "sg:phone":"+49 39003/243",
    "sg:postcode":"38489",
    "sg:province":"Sachsen-Anhalt",
    "wof:name":"Hoch- Und Tiefbau Gmbh",
    "wof:placetype":"venue"
},
  "geometry": {"coordinates":[10.912364006,52.6880340576],"type":"Point"}
}