{
  "type": "Feature",
  "properties": {
    "iso:country":"DE",
    "sg:address":"Paulsburgstr. 9",
    "sg:city":"Quierschied",
    "sg:phone":"+49 6897/61681",
    "sg:postcode":"66287",
    "sg:province":"Saarland",
    "wof:name":"Werner Andres",
    "wof:placetype":"venue"
},
  "geometry": {"coordinates":[7.052012,49.319981],"type":"Point"}
}