{
  "type": "Feature",
  "properties": {
    "iso:country":"DE",
    "sg:address":"Meringer Str. 45",
    "sg:city":"Friedberg",
    "sg:phone":"+49 821/65146",
    "sg:postcode":"86316",
    "sg:province":"Bayern",
    "wof:name":"Restaurant Bayerischer Wirt",
    "wof:placetype":"venue"
},
  "geometry": {"coordinates":[10.9537200928,48.3486785889],"type":"Point"}
}