{
  "type": "Feature",
  "properties": {
    "iso:country":"DE",
    "sg:address":"Marbachweg 356",
    "sg:city":"Frankfurt",
    "sg:phone":"+49 69/5601624",
    "sg:postcode":"60320",
    "sg:province":"Hessen",
    "wof:name":"Klaus D\u00f6rrbecker Und Afk",
    "wof:placetype":"venue"
},
  "geometry": {"coordinates":[8.671913147,50.1392211914],"type":"Point"}
}