{
  "type": "Feature",
  "properties": {
    "iso:country":"DE",
    "sg:address":"Mohrunger Allee 6",
    "sg:city":"Berlin",
    "sg:phone":"+49 30/3055718",
    "sg:postcode":"14055",
    "sg:province":"Berlin",
    "wof:name":"Eva Wallenhauer",
    "wof:placetype":"venue"
},
  "geometry": {"coordinates":[13.2493829727,52.5085411072],"type":"Point"}
}