{
  "type": "Feature",
  "properties": {
    "iso:country":"DE",
    "sg:address":"Hauptstr. 119",
    "sg:city":"Freudenberg",
    "sg:phone":"+49 9375/296",
    "sg:postcode":"97896",
    "sg:province":"Baden-W\u00fcrttemberg",
    "wof:name":"Marien-apotheke",
    "wof:placetype":"venue"
},
  "geometry": {"coordinates":[9.322049,49.740894],"type":"Point"}
}