{
  "type": "Feature",
  "properties": {
    "iso:country":"DE",
    "sg:address":"Lange Str. 44",
    "sg:city":"Delmenhorst",
    "sg:phone":"+49 4221/18285",
    "sg:postcode":"27749",
    "sg:province":"Niedersachsen",
    "wof:name":"Rosemarie Hirschfeld Foto-quelle",
    "wof:placetype":"venue"
},
  "geometry": {"coordinates":[8.6323642731,53.0487251282],"type":"Point"}
}