{
  "type": "Feature",
  "properties": {
    "iso:country":"DE",
    "sg:address":"Gr\u00fcnstr. 125",
    "sg:city":"Meerbusch",
    "sg:phone":"+49 2132/73198",
    "sg:postcode":"40667",
    "sg:province":"Nordrhein-Westfalen",
    "wof:name":"Stahlhandel Bongartz Gmbh",
    "wof:placetype":"venue"
},
  "geometry": {"coordinates":[6.70218,51.243618],"type":"Point"}
}