{
  "type": "Feature",
  "properties": {
    "iso:country":"DE",
    "sg:address":"Eickeler Bruch 84 a",
    "sg:city":"Herne",
    "sg:phone":"+49 2325/31448",
    "sg:postcode":"44651",
    "sg:province":"Nordrhein-Westfalen",
    "wof:name":"Karl Valentin",
    "wof:placetype":"venue"
},
  "geometry": {"coordinates":[7.1646699905,51.5175704956],"type":"Point"}
}