{
  "type": "Feature",
  "properties": {
    "iso:country":"DE",
    "sg:address":"Kraueler Hauptdeich 37",
    "sg:city":"Hamburg",
    "sg:postcode":"21037",
    "sg:province":"Hamburg",
    "wof:name":"Versus Einundsiebzigste Verwaltungsgesellschaft Mbh",
    "wof:placetype":"venue"
},
  "geometry": {"coordinates":[10.2102556229,53.4003944397],"type":"Point"}
}