{
  "type": "Feature",
  "properties": {
    "iso:country":"DE",
    "sg:address":"Hintere Marktstr. 64",
    "sg:city":"N\u00fcrnberg",
    "sg:phone":"+49 911/66093",
    "sg:postcode":"90441",
    "sg:province":"Bayern",
    "wof:name":"Steuerberatungsgesellschaft J. Wilpert Mbh",
    "wof:placetype":"venue"
},
  "geometry": {"coordinates":[11.0490159988,49.432674408],"type":"Point"}
}