{
  "type": "Feature",
  "properties": {
    "iso:country":"DE",
    "sg:address":"Rechbergstr. 34",
    "sg:city":"Schw\u00e4bisch Gm\u00fcnd",
    "sg:phone":"+49 7171/64221",
    "sg:postcode":"73525",
    "sg:province":"Baden-W\u00fcrttemberg",
    "wof:name":"Hohenrechberg",
    "wof:placetype":"venue"
},
  "geometry": {"coordinates":[9.795759201,48.7935218811],"type":"Point"}
}