{
  "type": "Feature",
  "properties": {
    "iso:country":"DE",
    "sg:address":"R\u00fcbenacher Str. 115",
    "sg:city":"Koblenz",
    "sg:phone":"+49 4926/121672",
    "sg:postcode":"56072",
    "sg:province":"Rheinland-Pfalz",
    "wof:name":"Nick Stanztechnik Gmbh",
    "wof:placetype":"venue"
},
  "geometry": {"coordinates":[7.551084,50.369793],"type":"Point"}
}