{
  "type": "Feature",
  "properties": {
    "iso:country":"DE",
    "sg:address":"Blankenburger Str. 32",
    "sg:city":"Thale",
    "sg:phone":"+49 3947/3341",
    "sg:postcode":"06502",
    "sg:province":"Sachsen-Anhalt",
    "wof:name":"Wohnungswirtschaft Mbh",
    "wof:placetype":"venue"
},
  "geometry": {"coordinates":[11.0457029343,51.7551269531],"type":"Point"}
}