{
  "type": "Feature",
  "properties": {
    "iso:country":"DE",
    "sg:address":"Gast\u00e4ckerstr. 18",
    "sg:city":"Filderstadt",
    "sg:phone":"+49 711/7776561",
    "sg:postcode":"70794",
    "sg:province":"Baden-W\u00fcrttemberg",
    "wof:name":"Init Individuelle Softwareentwickl.",
    "wof:placetype":"venue"
},
  "geometry": {"coordinates":[9.2246742249,48.6487922668],"type":"Point"}
}