{
  "type": "Feature",
  "properties": {
    "iso:country":"DE",
    "sg:address":"Mainzer Str. 23",
    "sg:city":"Berlin",
    "sg:phone":"+49 30/8537731",
    "sg:postcode":"10715",
    "sg:province":"Berlin",
    "wof:name":"Angela Breckwoldt-schmidt Rechtsanw\u00e4ltin",
    "wof:placetype":"venue"
},
  "geometry": {"coordinates":[13.3235082626,52.4800186157],"type":"Point"}
}