{
  "type": "Feature",
  "properties": {
    "iso:country":"DE",
    "sg:address":"Schattenaustr. 8",
    "sg:city":"K\u00f6tzting",
    "sg:phone":"+49 9941/2104",
    "sg:postcode":"93444",
    "sg:province":"Bayern",
    "wof:name":"Josef Starflinger Architekt",
    "wof:placetype":"venue"
},
  "geometry": {"coordinates":[12.857134,49.17886],"type":"Point"}
}