{
  "type": "Feature",
  "properties": {
    "iso:country":"DE",
    "sg:address":"Nuhnetalstr 122",
    "sg:city":"Winterberg",
    "sg:phone":"+49 2981/92300",
    "sg:postcode":"59955",
    "sg:province":"Nordrhein-Westfalen",
    "wof:name":"Josef Ante Gmbh",
    "wof:placetype":"venue"
},
  "geometry": {"coordinates":[8.5825195312,51.1495018005],"type":"Point"}
}