{
  "type": "Feature",
  "properties": {
    "iso:country":"DE",
    "sg:address":"Donaustr. 56",
    "sg:city":"Erkrath",
    "sg:phone":"+49 2104/46222",
    "sg:postcode":"40699",
    "sg:province":"Nordrhein-Westfalen",
    "wof:name":"H. V\u00f6ssing Gmbh",
    "wof:placetype":"venue"
},
  "geometry": {"coordinates":[6.9762821198,51.2112426758],"type":"Point"}
}