{
  "type": "Feature",
  "properties": {
    "iso:country":"DE",
    "sg:address":"Po\u00dfkamp 25",
    "sg:city":"Wadersloh",
    "sg:phone":"+49 2523/1327",
    "sg:postcode":"59329",
    "sg:province":"Nordrhein-Westfalen",
    "wof:name":"Maria Krabus",
    "wof:placetype":"venue"
},
  "geometry": {"coordinates":[8.2485809326,51.7388343811],"type":"Point"}
}