{
  "type": "Feature",
  "properties": {
    "iso:country":"DE",
    "sg:address":"Flugplatz",
    "sg:city":"Hof",
    "sg:phone":"+49 9281/64539",
    "sg:postcode":"95032",
    "sg:province":"Bayern",
    "wof:name":"Hofer Fluggesellschaft Mbh",
    "wof:placetype":"venue"
},
  "geometry": {"coordinates":[11.868827,50.286999],"type":"Point"}
}