{
  "type": "Feature",
  "properties": {
    "iso:country":"DE",
    "sg:address":"Am Gr\u00fcnen W\u00e4ldchen 2",
    "sg:city":"Bergisch Gladbach",
    "sg:phone":"+49 2204/25099",
    "sg:postcode":"51427",
    "sg:province":"Nordrhein-Westfalen",
    "wof:name":"Bautenschutz H. Schubert Gmbh",
    "wof:placetype":"venue"
},
  "geometry": {"coordinates":[7.1207809448,50.9660224915],"type":"Point"}
}