{
  "type": "Feature",
  "properties": {
    "iso:country":"DE",
    "sg:address":"Theodor-Storm-Str 1",
    "sg:city":"Marne",
    "sg:phone":"+49 4851/3253",
    "sg:postcode":"25709",
    "sg:province":"Schleswig-Holstein",
    "wof:name":"Spedition St\u00fchrk",
    "wof:placetype":"venue"
},
  "geometry": {"coordinates":[9.011821,53.949795],"type":"Point"}
}