{
  "type": "Feature",
  "properties": {
    "iso:country":"DE",
    "sg:address":"Martin-Luther-Weg 3",
    "sg:city":"Isernhagen",
    "sg:phone":"+49 5139/88080",
    "sg:postcode":"30916",
    "sg:province":"Niedersachsen",
    "wof:name":"Ev. Pfarramt Isernhagen",
    "wof:placetype":"venue"
},
  "geometry": {"coordinates":[9.819475174,52.4602088928],"type":"Point"}
}