{
  "type": "Feature",
  "properties": {
    "iso:country":"DE",
    "sg:address":"Varenseller Str. 77",
    "sg:city":"Rietberg",
    "sg:phone":"+49 5244/2167",
    "sg:postcode":"33397",
    "sg:province":"Nordrhein-Westfalen",
    "wof:name":"Augustin Ruiz-cardera Gmbh",
    "wof:placetype":"venue"
},
  "geometry": {"coordinates":[8.446602,51.854095],"type":"Point"}
}