{
  "type": "Feature",
  "properties": {
    "iso:country":"DE",
    "sg:address":"Althaushamer Str. 12",
    "sg:city":"Hausham",
    "sg:phone":"+49 8026/5764",
    "sg:postcode":"83734",
    "sg:province":"Bayern",
    "wof:name":"Peter Gasteiger",
    "wof:placetype":"venue"
},
  "geometry": {"coordinates":[11.84582,47.748852],"type":"Point"}
}