{
  "type": "Feature",
  "properties": {
    "iso:country":"DE",
    "sg:address":"Wassersleben 10",
    "sg:city":"Harrislee",
    "sg:phone":"+49 461/78345",
    "sg:postcode":"24955",
    "sg:province":"Schleswig-Holstein",
    "wof:name":"Strandkorb",
    "wof:placetype":"venue"
},
  "geometry": {"coordinates":[9.4193696976,54.8262901306],"type":"Point"}
}