{
  "type": "Feature",
  "properties": {
    "iso:country":"DE",
    "sg:address":"Lister Damm 15",
    "sg:city":"Hannover",
    "sg:phone":"+49 511/628073",
    "sg:postcode":"30163",
    "sg:province":"Niedersachsen",
    "wof:name":"Es Elektro- Und Schaltanlagen Gmbh",
    "wof:placetype":"venue"
},
  "geometry": {"coordinates":[9.75387,52.398586],"type":"Point"}
}