{
  "type": "Feature",
  "properties": {
    "iso:country":"DE",
    "sg:address":"Kapuzinergasse 1",
    "sg:city":"Schw\u00e4bisch Gm\u00fcnd",
    "sg:phone":"+49 7171/65777",
    "sg:postcode":"73525",
    "sg:province":"Baden-W\u00fcrttemberg",
    "wof:name":"Wolfgang Eisenmann Anlageberater",
    "wof:placetype":"venue"
},
  "geometry": {"coordinates":[9.7988586426,48.7976417542],"type":"Point"}
}