{
  "type": "Feature",
  "properties": {
    "iso:country":"DE",
    "sg:address":"Hauptstr. 28",
    "sg:city":"D\u00fclmen",
    "sg:phone":"+49 2548/229",
    "sg:postcode":"48249",
    "sg:province":"Nordrhein-Westfalen",
    "wof:name":"Norbert Merfeld",
    "wof:placetype":"venue"
},
  "geometry": {"coordinates":[7.279348,51.828785],"type":"Point"}
}