{
  "type": "Feature",
  "properties": {
    "iso:country":"DE",
    "sg:address":"Berckstr. 27",
    "sg:city":"Bremen",
    "sg:phone":"+49 421/236380",
    "sg:postcode":"28359",
    "sg:province":"Bremen",
    "wof:name":"Ev. Pfarramt Horn I",
    "wof:placetype":"venue"
},
  "geometry": {"coordinates":[8.873796463,53.0969200134],"type":"Point"}
}