{
  "type": "Feature",
  "properties": {
    "iso:country":"DE",
    "sg:address":"Carl-Spaeter-Str. 2d",
    "sg:city":"Koblenz",
    "sg:phone":"+49 4926/1984030",
    "sg:postcode":"56070",
    "sg:province":"Rheinland-Pfalz",
    "wof:name":"Kmw Konstruktion Maschinen- U. Werkzeugbau Gmbh & Co Kg",
    "wof:placetype":"venue"
},
  "geometry": {"coordinates":[7.579621,50.385414],"type":"Point"}
}