{
  "type": "Feature",
  "properties": {
    "iso:country":"DE",
    "sg:address":"Hauptstr. 81",
    "sg:city":"M\u00fcllheim",
    "sg:phone":"+49 7631/2170",
    "sg:postcode":"79379",
    "sg:province":"Baden-W\u00fcrttemberg",
    "wof:name":"Koenen",
    "wof:placetype":"venue"
},
  "geometry": {"coordinates":[7.6223368645,47.8081245422],"type":"Point"}
}