{
  "type": "Feature",
  "properties": {
    "iso:country":"DE",
    "sg:address":"Gammelbyer Weg 15",
    "sg:city":"Rieseby",
    "sg:phone":"+49 4355/1215",
    "sg:postcode":"24354",
    "sg:province":"Schleswig-Holstein",
    "wof:name":"Zimmerei Steffen & Creutz",
    "wof:placetype":"venue"
},
  "geometry": {"coordinates":[9.8019952774,54.5179901123],"type":"Point"}
}