{
  "type": "Feature",
  "properties": {
    "iso:country":"DE",
    "sg:address":"Gewerbestr. 18",
    "sg:city":"Staufen",
    "sg:phone":"+49 7633/50606",
    "sg:postcode":"79219",
    "sg:province":"Baden-W\u00fcrttemberg",
    "wof:name":"Gerhard Rau",
    "wof:placetype":"venue"
},
  "geometry": {"coordinates":[7.7202301025,47.8870773315],"type":"Point"}
}