{
  "type": "Feature",
  "properties": {
    "iso:country":"DE",
    "sg:address":"St\u00f6ckumer Str. 24",
    "sg:city":"Nordstemmen",
    "sg:phone":"+49 5069/2093",
    "sg:postcode":"31171",
    "sg:province":"Niedersachsen",
    "wof:name":"Bernhardt Grossk\u00fcche",
    "wof:placetype":"venue"
},
  "geometry": {"coordinates":[9.845048,52.15506],"type":"Point"}
}