{
  "type": "Feature",
  "properties": {
    "iso:country":"DE",
    "sg:address":"Habsburgerstr. 29",
    "sg:city":"Freiburg",
    "sg:postcode":"79104",
    "sg:province":"Baden-W\u00fcrttemberg",
    "wof:name":"Omen Computers Buchberger Ohg",
    "wof:placetype":"venue"
},
  "geometry": {"coordinates":[7.8549208641,48.0094451904],"type":"Point"}
}