{
  "type": "Feature",
  "properties": {
    "iso:country":"DE",
    "sg:address":"Osianderstr. 13",
    "sg:city":"Stuttgart",
    "sg:phone":"+49 711/659676",
    "sg:postcode":"70197",
    "sg:province":"Baden-W\u00fcrttemberg",
    "wof:name":"A. Vetter Immobilienmakler",
    "wof:placetype":"venue"
},
  "geometry": {"coordinates":[9.1503076553,48.7668380737],"type":"Point"}
}