{
  "type": "Feature",
  "properties": {
    "iso:country":"DE",
    "sg:address":"Langenberger Str 44-48",
    "sg:city":"Velbert",
    "sg:phone":"+49 2051/254291",
    "sg:postcode":"42551",
    "sg:province":"Nordrhein-Westfalen",
    "wof:name":"Christoph Mundorf Gmbh & Co",
    "wof:placetype":"venue"
},
  "geometry": {"coordinates":[7.056306,51.336102],"type":"Point"}
}