{
  "type": "Feature",
  "properties": {
    "iso:country":"DE",
    "sg:address":"Industriepark 14",
    "sg:city":"Wiebelsheim",
    "sg:phone":"+49 6766/8383",
    "sg:postcode":"56291",
    "sg:province":"Rheinland-Pfalz",
    "wof:name":"Ride Exchange Gesellschaft Zur Vermarktung Von Neuen Und",
    "wof:placetype":"venue"
},
  "geometry": {"coordinates":[7.6235160828,50.0795402527],"type":"Point"}
}