{
  "type": "Feature",
  "properties": {
    "iso:country":"DE",
    "sg:address":"Langgasse 14",
    "sg:city":"Klingenberg",
    "sg:phone":"+49 9372/2558",
    "sg:postcode":"63911",
    "sg:province":"Bayern",
    "wof:name":"Kath. Pfarramt St. Pankratius",
    "wof:placetype":"venue"
},
  "geometry": {"coordinates":[9.1854429245,49.7645568848],"type":"Point"}
}