{
  "type": "Feature",
  "properties": {
    "iso:country":"DE",
    "sg:address":"Schlieperstr. 12",
    "sg:city":"Nordhorn",
    "sg:phone":"+49 5921/73098",
    "sg:postcode":"48527",
    "sg:province":"Niedersachsen",
    "wof:name":"Gastst\u00e4tte Tr\u00e4nke",
    "wof:placetype":"venue"
},
  "geometry": {"coordinates":[7.0540828705,52.4237136841],"type":"Point"}
}