{
  "type": "Feature",
  "properties": {
    "iso:country":"DE",
    "sg:address":"Friedensstr. 2",
    "sg:city":"Heidenau",
    "sg:phone":"+49 3529/56510",
    "sg:postcode":"01809",
    "sg:province":"Sachsen",
    "wof:name":"Zum N\u00e4hst\u00fcbchen",
    "wof:placetype":"venue"
},
  "geometry": {"coordinates":[13.8656787872,50.9834785461],"type":"Point"}
}