{
  "type": "Feature",
  "properties": {
    "iso:country":"DE",
    "sg:address":"Medardusstr. 28",
    "sg:city":"Mehring",
    "sg:phone":"+49 6502/2963",
    "sg:postcode":"54346",
    "sg:province":"Rheinland-Pfalz",
    "wof:name":"Hans-peter Philippi",
    "wof:placetype":"venue"
},
  "geometry": {"coordinates":[6.8248410225,49.7949790955],"type":"Point"}
}