{
  "type": "Feature",
  "properties": {
    "iso:country":"DE",
    "sg:address":"Mattenburger Str. 6",
    "sg:city":"Bad Bederkesa",
    "sg:postcode":"27624",
    "sg:province":"Niedersachsen",
    "wof:name":"\u00d6zel Bau Gmbh",
    "wof:placetype":"venue"
},
  "geometry": {"coordinates":[8.840262,53.625885],"type":"Point"}
}