{
  "type": "Feature",
  "properties": {
    "iso:country":"DE",
    "sg:address":"Zschorlauer Str. 72",
    "sg:city":"Aue",
    "sg:phone":"+49 3771/23447",
    "sg:postcode":"08280",
    "sg:province":"Sachsen",
    "wof:name":"Freibad Auerhammer",
    "wof:placetype":"venue"
},
  "geometry": {"coordinates":[12.6735572815,50.5853843689],"type":"Point"}
}