{
  "type": "Feature",
  "properties": {
    "iso:country":"DE",
    "sg:address":"Martin-Luther-Str. 12",
    "sg:city":"Aschaffenburg",
    "sg:phone":"+49 6021/88957",
    "sg:postcode":"63741",
    "sg:province":"Bayern",
    "wof:name":"D. Und E. Scholtysik",
    "wof:placetype":"venue"
},
  "geometry": {"coordinates":[9.1232500076,49.9648017883],"type":"Point"}
}