{
  "type": "Feature",
  "properties": {
    "iso:country":"DE",
    "sg:address":"Dorfstr. 56",
    "sg:city":"Breege",
    "sg:phone":"+49 38391/341",
    "sg:postcode":"18556",
    "sg:province":"Mecklenburg-Vorpommern",
    "wof:name":"Eckhard Bertig",
    "wof:placetype":"venue"
},
  "geometry": {"coordinates":[13.3602247238,54.614440918],"type":"Point"}
}