{
  "type": "Feature",
  "properties": {
    "iso:country":"DE",
    "sg:address":"Bromberger Str. 22",
    "sg:city":"Nienburg",
    "sg:phone":"+49 5021/15805",
    "sg:postcode":"31582",
    "sg:province":"Niedersachsen",
    "wof:name":"Lachnitt Bau Und Keramik Inh. M. Lachnitt",
    "wof:placetype":"venue"
},
  "geometry": {"coordinates":[9.2672996521,52.6146736145],"type":"Point"}
}