{
  "type": "Feature",
  "properties": {
    "iso:country":"DE",
    "sg:address":"Fritz-Reuter-Str. 19",
    "sg:city":"Osnabr\u00fcck",
    "sg:phone":"+49 541/41089",
    "sg:postcode":"49080",
    "sg:province":"Niedersachsen",
    "wof:name":"Franz Laubinger",
    "wof:placetype":"venue"
},
  "geometry": {"coordinates":[8.012775,52.264694],"type":"Point"}
}