{
  "type": "Feature",
  "properties": {
    "iso:country":"DE",
    "sg:address":"Maidamm 61",
    "sg:city":"Bruchhausen-Vilsen",
    "sg:phone":"+49 4252/3600",
    "sg:postcode":"27305",
    "sg:province":"Niedersachsen",
    "wof:name":"Heinz Schr\u00f6der",
    "wof:placetype":"venue"
},
  "geometry": {"coordinates":[9.0207386017,52.8263511658],"type":"Point"}
}