{
  "type": "Feature",
  "properties": {
    "iso:country":"DE",
    "sg:address":"Van-Gils-Str. 13",
    "sg:city":"J\u00fclich",
    "sg:phone":"+49 2461/8955",
    "sg:postcode":"52428",
    "sg:province":"Nordrhein-Westfalen",
    "wof:name":"Peter Abels",
    "wof:placetype":"venue"
},
  "geometry": {"coordinates":[6.390944,50.890415],"type":"Point"}
}