{
  "type": "Feature",
  "properties": {
    "iso:country":"DE",
    "sg:address":"Hauptstr. 10",
    "sg:city":"Isernhagen",
    "sg:postcode":"30916",
    "sg:province":"Niedersachsen",
    "wof:name":"Islandpferdegest\u00fct Farsterhof Isernhagen",
    "wof:placetype":"venue"
},
  "geometry": {"coordinates":[9.835121,52.468681],"type":"Point"}
}