{
  "type": "Feature",
  "properties": {
    "iso:country":"DE",
    "sg:address":"Gr\u00f6pelinger Heerstr. 334",
    "sg:city":"Bremen",
    "sg:phone":"+49 421/611949",
    "sg:postcode":"28239",
    "sg:province":"Bremen",
    "wof:name":"Dieter W\u00f6ckener",
    "wof:placetype":"venue"
},
  "geometry": {"coordinates":[8.750831,53.122875],"type":"Point"}
}