{
  "type": "Feature",
  "properties": {
    "iso:country":"DE",
    "sg:address":"L\u00f6fflerstr. 5a",
    "sg:city":"M\u00fcnchen",
    "sg:phone":"+49 89",
    "sg:postcode":"80999",
    "sg:province":"Bayern",
    "wof:name":"Assekuranz-partner-ag",
    "wof:placetype":"venue"
},
  "geometry": {"coordinates":[11.4658145905,48.1904907227],"type":"Point"}
}