{
  "type": "Feature",
  "properties": {
    "iso:country":"DE",
    "sg:address":"Deckerstr. 17",
    "sg:city":"Korntal-M\u00fcnchingen",
    "sg:phone":"+49 711/8380491",
    "sg:postcode":"70825",
    "sg:province":"Baden-W\u00fcrttemberg",
    "wof:name":"Hermann Kreutz Architekt",
    "wof:placetype":"venue"
},
  "geometry": {"coordinates":[9.119004,48.828564],"type":"Point"}
}