{
  "type": "Feature",
  "properties": {
    "iso:country":"DE",
    "sg:address":"Gartenstr. 18",
    "sg:city":"Naumburg",
    "sg:phone":"+49 3445/703069",
    "sg:postcode":"06618",
    "sg:province":"Sachsen-Anhalt",
    "wof:name":"Einkaufs- Und Lieferge- Nossenschaft Des Holzver-",
    "wof:placetype":"venue"
},
  "geometry": {"coordinates":[11.8107852936,51.1570281982],"type":"Point"}
}