{
  "type": "Feature",
  "properties": {
    "iso:country":"DE",
    "sg:address":"Urbanstr. 1",
    "sg:city":"K\u00f6ln",
    "sg:phone":"+49 221/981410",
    "sg:postcode":"50679",
    "sg:province":"Nordrhein-Westfalen",
    "wof:name":"Altenheim St. Heribert",
    "wof:placetype":"venue"
},
  "geometry": {"coordinates":[6.969428,50.938393],"type":"Point"}
}