{
  "type": "Feature",
  "properties": {
    "iso:country":"DE",
    "sg:address":"Westicker Str. 62",
    "sg:city":"Fr\u00f6ndenberg",
    "sg:postcode":"58730",
    "sg:province":"Nordrhein-Westfalen",
    "wof:name":"Adolf Ulmke Planen E. K.",
    "wof:placetype":"venue"
},
  "geometry": {"coordinates":[7.7895832062,51.4756546021],"type":"Point"}
}