{
  "type": "Feature",
  "properties": {
    "iso:country":"DE",
    "sg:address":"Hitzlerieder Str. 2",
    "sg:city":"Seeg",
    "sg:phone":"+49 8364/271",
    "sg:postcode":"87637",
    "sg:province":"Bayern",
    "wof:name":"Herbert Janke",
    "wof:placetype":"venue"
},
  "geometry": {"coordinates":[10.6114063263,47.6551246643],"type":"Point"}
}