{
  "type": "Feature",
  "properties": {
    "iso:country":"DE",
    "sg:address":"Zweibr\u00fccker Str.",
    "sg:city":"Annweiler",
    "sg:phone":"+49 6346/7175",
    "sg:postcode":"76855",
    "sg:province":"Rheinland-Pfalz",
    "wof:name":"Jet Station",
    "wof:placetype":"venue"
},
  "geometry": {"coordinates":[7.9595608711,49.2047424316],"type":"Point"}
}