{
  "type": "Feature",
  "properties": {
    "iso:country":"DE",
    "sg:address":"Schwarzenberger Str. 5",
    "sg:city":"Aue",
    "sg:phone":"+49 3771/51341",
    "sg:postcode":"08280",
    "sg:province":"Sachsen",
    "wof:name":"W. B\u00f6hme",
    "wof:placetype":"venue"
},
  "geometry": {"coordinates":[12.703909874,50.5858421326],"type":"Point"}
}