{
  "type": "Feature",
  "properties": {
    "iso:country":"DE",
    "sg:address":"Segeberger Landstr. 59",
    "sg:city":"Bornh\u00f6ved",
    "sg:phone":"+49 4323/90730",
    "sg:postcode":"24619",
    "sg:province":"Schleswig-Holstein",
    "wof:name":"J\u00fcrgen Koch Gmbh",
    "wof:placetype":"venue"
},
  "geometry": {"coordinates":[10.230670929,54.0555458069],"type":"Point"}
}