{
  "type": "Feature",
  "properties": {
    "iso:country":"DE",
    "sg:address":"Schillerstr. 12",
    "sg:city":"Ballenstedt",
    "sg:phone":"+49 39483/8568",
    "sg:postcode":"06493",
    "sg:province":"Sachsen-Anhalt",
    "wof:name":"Vitalis",
    "wof:placetype":"venue"
},
  "geometry": {"coordinates":[11.2328224182,51.7168197632],"type":"Point"}
}