{
  "type": "Feature",
  "properties": {
    "iso:country":"DE",
    "sg:address":"Driburger Str. 7",
    "sg:city":"Brakel",
    "sg:phone":"+49 5272/7081",
    "sg:postcode":"33034",
    "sg:province":"Nordrhein-Westfalen",
    "wof:name":"Willi Glunz Gmbh Mineral\u00f6lgro\u00dfhandlung",
    "wof:placetype":"venue"
},
  "geometry": {"coordinates":[9.1770200729,51.7120437622],"type":"Point"}
}