{
  "type": "Feature",
  "properties": {
    "iso:country":"DE",
    "sg:address":"Marktstr. 19",
    "sg:city":"Lippstadt",
    "sg:phone":"+49 2941/77700",
    "sg:postcode":"59555",
    "sg:province":"Nordrhein-Westfalen",
    "wof:name":"J. R. Dohr Heilpraktiker",
    "wof:placetype":"venue"
},
  "geometry": {"coordinates":[8.3437814713,51.6762657166],"type":"Point"}
}