{
  "type": "Feature",
  "properties": {
    "iso:country":"DE",
    "sg:address":"Hohner Str 29",
    "sg:city":"Lienen",
    "sg:phone":"+49 5484/93990",
    "sg:postcode":"49536",
    "sg:province":"Nordrhein-Westfalen",
    "wof:name":"W. Himmelreich Gmbh",
    "wof:placetype":"venue"
},
  "geometry": {"coordinates":[7.8908548355,52.1450881958],"type":"Point"}
}