{
  "type": "Feature",
  "properties": {
    "iso:country":"DE",
    "sg:address":"Walsroder Stra\u00dfe 59 a",
    "sg:city":"Langenhagen",
    "sg:phone":"+49 511/7241774",
    "sg:postcode":"30851",
    "sg:province":"Niedersachsen",
    "wof:name":"Biete.de",
    "wof:placetype":"venue"
},
  "geometry": {"coordinates":[9.7322072983,52.4346427917],"type":"Point"}
}