{
  "type": "Feature",
  "properties": {
    "iso:country":"DE",
    "sg:address":"Kiehnlestr. 8",
    "sg:city":"Pforzheim",
    "sg:phone":"+49 7231/33463",
    "sg:postcode":"75172",
    "sg:province":"Baden-W\u00fcrttemberg",
    "wof:name":"Reinhard Noack",
    "wof:placetype":"venue"
},
  "geometry": {"coordinates":[8.695118,48.892879],"type":"Point"}
}