{
  "type": "Feature",
  "properties": {
    "iso:country":"DE",
    "sg:address":"An der Steige 11a",
    "sg:city":"Billigheim",
    "sg:phone":"+49 6265/7875",
    "sg:postcode":"74842",
    "sg:province":"Baden-W\u00fcrttemberg",
    "wof:name":"B. \u00d6strich",
    "wof:placetype":"venue"
},
  "geometry": {"coordinates":[9.2204561234,49.3494033813],"type":"Point"}
}