{
  "type": "Feature",
  "properties": {
    "iso:country":"DE",
    "sg:address":"Hochstr. 4",
    "sg:city":"Gerolsbach",
    "sg:phone":"+49 8250/401",
    "sg:postcode":"85302",
    "sg:province":"Bayern",
    "wof:name":"P. Schieder Gmbh",
    "wof:placetype":"venue"
},
  "geometry": {"coordinates":[11.340309,48.456837],"type":"Point"}
}