{
  "type": "Feature",
  "properties": {
    "iso:country":"DE",
    "sg:address":"Bahnhofstr. 10",
    "sg:city":"Freisen",
    "sg:phone":"+49 6855/9031",
    "sg:postcode":"66629",
    "sg:province":"Saarland",
    "wof:name":"M. Schumacher",
    "wof:placetype":"venue"
},
  "geometry": {"coordinates":[7.248003,49.552246],"type":"Point"}
}