{
  "type": "Feature",
  "properties": {
    "iso:country":"DE",
    "sg:address":"K\u00e4mertorstr. 48",
    "sg:city":"Kamen",
    "sg:phone":"+49 2307/280480",
    "sg:postcode":"59174",
    "sg:province":"Nordrhein-Westfalen",
    "wof:name":"Kaercher Center - Westfalen",
    "wof:placetype":"venue"
},
  "geometry": {"coordinates":[7.66001,51.594669],"type":"Point"}
}