{
  "type": "Feature",
  "properties": {
    "iso:country":"DE",
    "sg:address":"M\u00fcnchener Str. 153",
    "sg:city":"Ingolstadt",
    "sg:phone":"+49 841/71278",
    "sg:postcode":"85051",
    "sg:province":"Bayern",
    "wof:name":"Egidius Hocks Farben Und Tapeten Nachf.",
    "wof:placetype":"venue"
},
  "geometry": {"coordinates":[11.4374198914,48.737537384],"type":"Point"}
}