{
  "type": "Feature",
  "properties": {
    "iso:country":"DE",
    "sg:address":"Holteistr. 2",
    "sg:city":"Hannover",
    "sg:phone":"+49 511/853699",
    "sg:postcode":"30175",
    "sg:province":"Niedersachsen",
    "wof:name":"Neubau Gesellschaft F\u00fcr Neues Bauen Mbh",
    "wof:placetype":"venue"
},
  "geometry": {"coordinates":[9.758095,52.37513],"type":"Point"}
}