{
  "type": "Feature",
  "properties": {
    "iso:country":"DE",
    "sg:address":"Neuenhaus",
    "sg:city":"Overath",
    "sg:phone":"+49 2206/2142",
    "sg:postcode":"51491",
    "sg:province":"Nordrhein-Westfalen",
    "wof:name":"Franz-josef Hundt",
    "wof:placetype":"venue"
},
  "geometry": {"coordinates":[7.321025,50.947987],"type":"Point"}
}