{
  "type": "Feature",
  "properties": {
    "iso:country":"DE",
    "sg:address":"Schwerdstr. 43a",
    "sg:city":"Speyer",
    "sg:phone":"+49 6232/75254",
    "sg:postcode":"67346",
    "sg:province":"Rheinland-Pfalz",
    "wof:name":"Ortwin Lischer",
    "wof:placetype":"venue"
},
  "geometry": {"coordinates":[8.4283742905,49.3122673035],"type":"Point"}
}