{
  "type": "Feature",
  "properties": {
    "iso:country":"DE",
    "sg:address":"Weingartenstr. 25",
    "sg:city":"Buggingen",
    "sg:phone":"+49 7634/3270",
    "sg:postcode":"79426",
    "sg:province":"Baden-W\u00fcrttemberg",
    "wof:name":"Pferdeversicherungsverein Reinhard Gries",
    "wof:placetype":"venue"
},
  "geometry": {"coordinates":[7.6449961662,47.8577346802],"type":"Point"}
}