{
  "type": "Feature",
  "properties": {
    "iso:country":"DE",
    "sg:address":"Staatsstr. 30",
    "sg:city":"Neidenfels",
    "sg:phone":"+49 4963/257131",
    "sg:postcode":"67468",
    "sg:province":"Rheinland-Pfalz",
    "wof:name":"Neustadter Volksbank Eg",
    "wof:placetype":"venue"
},
  "geometry": {"coordinates":[8.045676,49.388256],"type":"Point"}
}