{
  "type": "Feature",
  "properties": {
    "iso:country":"DE",
    "sg:address":"Hauptstr. 7",
    "sg:city":"Eppelheim",
    "sg:phone":"+49 6221/764515",
    "sg:postcode":"69214",
    "sg:province":"Baden-W\u00fcrttemberg",
    "wof:name":"Schwarzer Kater",
    "wof:placetype":"venue"
},
  "geometry": {"coordinates":[8.6355876923,49.4006004333],"type":"Point"}
}