{
  "type": "Feature",
  "properties": {
    "iso:country":"DE",
    "sg:address":"Bamberger Str. 2",
    "sg:city":"Zapfendorf",
    "sg:phone":"+49 9547/6163",
    "sg:postcode":"96199",
    "sg:province":"Bayern",
    "wof:name":"Imbi\u00df-h\u00e4usla",
    "wof:placetype":"venue"
},
  "geometry": {"coordinates":[10.9304037094,50.0169372559],"type":"Point"}
}