{
  "type": "Feature",
  "properties": {
    "iso:country":"DE",
    "sg:address":"Weinerstr. 13",
    "sg:city":"Ochtrup",
    "sg:phone":"+49 2553/1238",
    "sg:postcode":"48607",
    "sg:province":"Nordrhein-Westfalen",
    "wof:name":"Anton Rosing",
    "wof:placetype":"venue"
},
  "geometry": {"coordinates":[7.1887187958,52.2089385986],"type":"Point"}
}