{
  "type": "Feature",
  "properties": {
    "iso:country":"DE",
    "sg:address":"Hauptstr. 15",
    "sg:city":"Schiffweiler",
    "sg:phone":"+49 6821/65153",
    "sg:postcode":"66578",
    "sg:province":"Saarland",
    "wof:name":"Helmut Blaschke",
    "wof:placetype":"venue"
},
  "geometry": {"coordinates":[7.130798,49.370399],"type":"Point"}
}