{
  "type": "Feature",
  "properties": {
    "iso:country":"DE",
    "sg:address":"Bahnhofstr. 17-19",
    "sg:city":"Murnau",
    "sg:phone":"+49 8841/47704",
    "sg:postcode":"82418",
    "sg:province":"Bayern",
    "wof:name":"Mue\u00dfig-elektronik Gmbh",
    "wof:placetype":"venue"
},
  "geometry": {"coordinates":[11.19797,47.679787],"type":"Point"}
}