{
  "type": "Feature",
  "properties": {
    "iso:country":"DE",
    "sg:address":"Hauptstr. 34",
    "sg:city":"Brandenburg",
    "sg:phone":"+49 3381/223610",
    "sg:postcode":"14776",
    "sg:province":"Brandenburg",
    "wof:name":"Ratsapotheke",
    "wof:placetype":"venue"
},
  "geometry": {"coordinates":[12.560166,52.409904],"type":"Point"}
}