{
  "type": "Feature",
  "properties": {
    "iso:country":"DE",
    "sg:address":"Am Bahndamm 4",
    "sg:city":"Hammelburg",
    "sg:phone":"+49 9732/91360",
    "sg:postcode":"97762",
    "sg:province":"Bayern",
    "wof:name":"Franz Kraus Verwaltungs-gmbh",
    "wof:placetype":"venue"
},
  "geometry": {"coordinates":[9.896373,50.115658],"type":"Point"}
}