{
  "type": "Feature",
  "properties": {
    "iso:country":"DE",
    "sg:address":"Hindelanger Str 35",
    "sg:city":"Sonthofen",
    "sg:phone":"+49 8321/674401",
    "sg:postcode":"87527",
    "sg:province":"Bayern",
    "wof:name":"Kontec Ohg",
    "wof:placetype":"venue"
},
  "geometry": {"coordinates":[10.291474,47.512035],"type":"Point"}
}