{
  "type": "Feature",
  "properties": {
    "iso:country":"DE",
    "sg:address":"G\u00f6rlitzer Str. 9-11",
    "sg:city":"Freilassing",
    "sg:phone":"+49 8654/46740",
    "sg:postcode":"83395",
    "sg:province":"Bayern",
    "wof:name":"Almarit Lacke Gmbh",
    "wof:placetype":"venue"
},
  "geometry": {"coordinates":[12.963944,47.854233],"type":"Point"}
}