{
  "type": "Feature",
  "properties": {
    "iso:country":"DE",
    "sg:address":"Bahnhofstr. 14",
    "sg:city":"Seesen",
    "sg:phone":"+49 5381/93610",
    "sg:postcode":"38723",
    "sg:province":"Niedersachsen",
    "wof:name":"Hagebaumarkt Kr\u00fcger",
    "wof:placetype":"venue"
},
  "geometry": {"coordinates":[10.1750984192,51.8885765076],"type":"Point"}
}