{
  "type": "Feature",
  "properties": {
    "iso:country":"DE",
    "sg:address":"Unterer Steinweg 6",
    "sg:city":"Plauen",
    "sg:phone":"+49 3741/222331",
    "sg:postcode":"08523",
    "sg:province":"Sachsen",
    "wof:name":"Orthop\u00e4die-schuhtechnik Schwarzenberg Gmbh",
    "wof:placetype":"venue"
},
  "geometry": {"coordinates":[12.1382713318,50.494178772],"type":"Point"}
}