{
  "type": "Feature",
  "properties": {
    "iso:country":"DE",
    "sg:address":"Ostseestrasse 11",
    "sg:city":"Kappeln",
    "sg:phone":"+49 4642/987357",
    "sg:postcode":"24376",
    "sg:province":"Schleswig-Holstein",
    "wof:name":"Taucherhelm",
    "wof:placetype":"venue"
},
  "geometry": {"coordinates":[9.951381,54.662434],"type":"Point"}
}