{
  "type": "Feature",
  "properties": {
    "iso:country":"DE",
    "sg:address":"Polenz 10",
    "sg:city":"Scharfenberg",
    "sg:phone":"+49 3521/457596",
    "sg:postcode":"01665",
    "sg:province":"Sachsen",
    "wof:name":"Lothar Rohde",
    "wof:placetype":"venue"
},
  "geometry": {"coordinates":[13.456019,51.127983],"type":"Point"}
}