{
  "type": "Feature",
  "properties": {
    "iso:country":"DE",
    "sg:address":"Langengrobsdorfer Str. 104",
    "sg:city":"Gera",
    "sg:phone":"+49 365/810404",
    "sg:postcode":"07548",
    "sg:province":"Th\u00fcringen",
    "wof:name":"Weber Gmbh",
    "wof:placetype":"venue"
},
  "geometry": {"coordinates":[12.02078,50.847778],"type":"Point"}
}