{
  "type": "Feature",
  "properties": {
    "iso:country":"DE",
    "sg:address":"Altenend 55",
    "sg:city":"Friesoythe",
    "sg:phone":"+49 4493/1475",
    "sg:postcode":"26169",
    "sg:province":"Niedersachsen",
    "wof:name":"Hans-werner Bahlmann Bau Gmbh",
    "wof:placetype":"venue"
},
  "geometry": {"coordinates":[7.80574,52.97324],"type":"Point"}
}