{
  "type": "Feature",
  "properties": {
    "iso:country":"DE",
    "sg:address":"S\u00fcdrg. 40",
    "sg:city":"B\u00fcnde",
    "sg:phone":"+49 4952/233162",
    "sg:postcode":"32257",
    "sg:province":"Nordrhein-Westfalen",
    "wof:name":"Helmut Schr\u00d6der Gmbh",
    "wof:placetype":"venue"
},
  "geometry": {"coordinates":[8.5828323364,52.190246582],"type":"Point"}
}