{
  "type": "Feature",
  "properties": {
    "iso:country":"DE",
    "sg:address":"Hegauer Weg 27",
    "sg:city":"Berlin",
    "sg:phone":"+49 30/8014090",
    "sg:postcode":"14163",
    "sg:province":"Berlin",
    "wof:name":"Janke",
    "wof:placetype":"venue"
},
  "geometry": {"coordinates":[13.245567,52.427708],"type":"Point"}
}