{
  "type": "Feature",
  "properties": {
    "iso:country":"DE",
    "sg:address":"Industriestr 20",
    "sg:city":"Fl\u00f6rsheim-Weilbach",
    "sg:phone":"+49 6145/936150",
    "sg:postcode":"65439",
    "sg:province":"Hessen",
    "wof:name":"Ge Capital Modular Space Gmbh Nl Frankfurt/main",
    "wof:placetype":"venue"
},
  "geometry": {"coordinates":[8.43498,50.044338],"type":"Point"}
}