{
  "type": "Feature",
  "properties": {
    "iso:country":"DE",
    "sg:address":"Schumanstr. 4",
    "sg:city":"W\u00fcrselen",
    "sg:phone":"+49 2405/94973",
    "sg:postcode":"52146",
    "sg:province":"Nordrhein-Westfalen",
    "wof:name":"J. Gr\u00fcnebaum Und W. Linden",
    "wof:placetype":"venue"
},
  "geometry": {"coordinates":[6.152536,50.80912],"type":"Point"}
}