{
  "type": "Feature",
  "properties": {
    "iso:country":"DE",
    "sg:address":"Hoher Weg 3",
    "sg:city":"Goslar",
    "sg:phone":"+49 5321/41437",
    "sg:postcode":"38640",
    "sg:province":"Niedersachsen",
    "wof:name":"Martini",
    "wof:placetype":"venue"
},
  "geometry": {"coordinates":[10.4275808334,51.9049186707],"type":"Point"}
}