{
  "type": "Feature",
  "properties": {
    "iso:country":"DE",
    "sg:address":"Pippelweg 44",
    "sg:city":"Braunschweig",
    "sg:phone":"+49 531/80100",
    "sg:postcode":"38120",
    "sg:province":"Niedersachsen",
    "wof:name":"Ccs-computer Service Streiff Gmbh & Co.",
    "wof:placetype":"venue"
},
  "geometry": {"coordinates":[10.4904203415,52.2540245056],"type":"Point"}
}