{
  "type": "Feature",
  "properties": {
    "iso:country":"DE",
    "sg:address":"Finkenweg 2",
    "sg:city":"C\u00f6lbe",
    "sg:phone":"+49 6421/84886",
    "sg:postcode":"35091",
    "sg:province":"Hessen",
    "wof:name":"Schneider",
    "wof:placetype":"venue"
},
  "geometry": {"coordinates":[8.7817,50.851753],"type":"Point"}
}