{
  "type": "Feature",
  "properties": {
    "iso:country":"DE",
    "sg:address":"Auf dem Kamm 9",
    "sg:city":"Bergisch Gladbach",
    "sg:phone":"+49 2204/921750",
    "sg:postcode":"51427",
    "sg:province":"Nordrhein-Westfalen",
    "wof:name":"Detlef Kerpen",
    "wof:placetype":"venue"
},
  "geometry": {"coordinates":[7.100709,50.956905],"type":"Point"}
}