{
  "type": "Feature",
  "properties": {
    "iso:country":"DE",
    "sg:address":"Oppaustr. 16",
    "sg:city":"Schkopau",
    "sg:phone":"+49 3461/794750",
    "sg:postcode":"06258",
    "sg:province":"Sachsen-Anhalt",
    "wof:name":"Tennisclubhaus",
    "wof:placetype":"venue"
},
  "geometry": {"coordinates":[11.9904146194,51.3874206543],"type":"Point"}
}