{
  "type": "Feature",
  "properties": {
    "iso:country":"DE",
    "sg:address":"K\u00f6nigstr. 11",
    "sg:city":"Kaarst",
    "sg:phone":"+49 4921/3165196",
    "sg:postcode":"41564",
    "sg:province":"Nordrhein-Westfalen",
    "wof:name":"Peter Schmitz & Sohn Gmbh",
    "wof:placetype":"venue"
},
  "geometry": {"coordinates":[6.613349,51.217091],"type":"Point"}
}