{
  "type": "Feature",
  "properties": {
    "iso:country":"DE",
    "sg:address":"Saarlouiser Str. 18",
    "sg:city":"Dillingen",
    "sg:phone":"+49 6831/704947",
    "sg:postcode":"66763",
    "sg:province":"Saarland",
    "wof:name":"Club Papillon",
    "wof:placetype":"venue"
},
  "geometry": {"coordinates":[6.731161,49.350864],"type":"Point"}
}