{
  "type": "Feature",
  "properties": {
    "iso:country":"DE",
    "sg:address":"Brandmatt 27",
    "sg:city":"Sasbachwalden",
    "sg:phone":"+49 7841/5580",
    "sg:postcode":"77887",
    "sg:province":"Baden-W\u00fcrttemberg",
    "wof:name":"Lotte Jacobi",
    "wof:placetype":"venue"
},
  "geometry": {"coordinates":[8.1662559509,48.6098518372],"type":"Point"}
}