{
  "type": "Feature",
  "properties": {
    "iso:country":"DE",
    "sg:address":"Elper Str. 1 a",
    "sg:city":"Herten",
    "sg:phone":"+49 2361/21201",
    "sg:postcode":"45701",
    "sg:province":"Nordrhein-Westfalen",
    "wof:name":"Peter Breuing",
    "wof:placetype":"venue"
},
  "geometry": {"coordinates":[7.135145,51.624363],"type":"Point"}
}