{
  "type": "Feature",
  "properties": {
    "iso:country":"DE",
    "sg:address":"Palmstr. 6",
    "sg:city":"L\u00f6rrach",
    "sg:phone":"+49 7621/84458",
    "sg:postcode":"79539",
    "sg:province":"Baden-W\u00fcrttemberg",
    "wof:name":"Gerber-moden Gmbh",
    "wof:placetype":"venue"
},
  "geometry": {"coordinates":[7.661477,47.614227],"type":"Point"}
}