{
  "type": "Feature",
  "properties": {
    "iso:country":"DE",
    "sg:address":"Am Graben 1",
    "sg:city":"Fambach",
    "sg:phone":"+49 36848/22461",
    "sg:postcode":"98597",
    "sg:province":"Th\u00fcringen",
    "wof:name":"J\u00f6rg Heller",
    "wof:placetype":"venue"
},
  "geometry": {"coordinates":[10.367222,50.739483],"type":"Point"}
}