{
  "type": "Feature",
  "properties": {
    "iso:country":"DE",
    "sg:address":"Arnst\u00e4dter Chaussee 37",
    "sg:city":"Erfurt",
    "sg:phone":"+49 361/3405433",
    "sg:postcode":"99096",
    "sg:province":"Th\u00fcringen",
    "wof:name":"Lsb Th\u00fcringen Sportmanagement Gmbh",
    "wof:placetype":"venue"
},
  "geometry": {"coordinates":[11.0328140259,50.9658889771],"type":"Point"}
}