{
  "type": "Feature",
  "properties": {
    "iso:country":"DE",
    "sg:address":"Langendamm",
    "sg:city":"Varel",
    "sg:phone":"+49 4451/5852",
    "sg:postcode":"26316",
    "sg:province":"Niedersachsen",
    "wof:name":"G\u00e4stehaus A. H\u00fcbner",
    "wof:placetype":"venue"
},
  "geometry": {"coordinates":[8.0871505737,53.3457870483],"type":"Point"}
}