{
  "type": "Feature",
  "properties": {
    "iso:country":"DE",
    "sg:address":"Pallottiweg 14",
    "sg:city":"Friedberg",
    "sg:phone":"+49 821/301042",
    "sg:postcode":"86316",
    "sg:province":"Bayern",
    "wof:name":"Pallottiheim Bibliothek",
    "wof:placetype":"venue"
},
  "geometry": {"coordinates":[10.99559,48.343868],"type":"Point"}
}