{
  "type": "Feature",
  "properties": {
    "iso:country":"DE",
    "sg:address":"Kleeweg 12",
    "sg:city":"Seukendorf",
    "sg:phone":"+49 911/7567567",
    "sg:postcode":"90556",
    "sg:province":"Bayern",
    "wof:name":"Metzgerei Weckerlein Gmbh",
    "wof:placetype":"venue"
},
  "geometry": {"coordinates":[10.8825616837,49.4904632568],"type":"Point"}
}