{
  "type": "Feature",
  "properties": {
    "iso:country":"DE",
    "sg:address":"G\u00fcnther-Wagner-Allee 13",
    "sg:city":"Hannover",
    "sg:phone":"+49 511/280070",
    "sg:postcode":"30177",
    "sg:province":"Niedersachsen",
    "wof:name":"Commerz Unternehmensbeteiligungs-ag",
    "wof:placetype":"venue"
},
  "geometry": {"coordinates":[9.7691049576,52.3981781006],"type":"Point"}
}