{
  "type": "Feature",
  "properties": {
    "iso:country":"DE",
    "sg:address":"Saalestr. 3",
    "sg:city":"Bad Neustadt",
    "sg:phone":"+49 9771/8987",
    "sg:postcode":"97616",
    "sg:province":"Bayern",
    "wof:name":"Vdh-video-star Verleih Gmbh",
    "wof:placetype":"venue"
},
  "geometry": {"coordinates":[10.2002820969,50.3182144165],"type":"Point"}
}