{
  "type": "Feature",
  "properties": {
    "iso:country":"DE",
    "sg:address":"Georg-Queri-Str. 5 a",
    "sg:city":"Hebertshausen",
    "sg:phone":"+49 8131/20979",
    "sg:postcode":"85241",
    "sg:province":"Bayern",
    "wof:name":"Werner Schaffer Schreinerei Gmbh",
    "wof:placetype":"venue"
},
  "geometry": {"coordinates":[11.468556,48.288025],"type":"Point"}
}