{
  "type": "Feature",
  "properties": {
    "iso:country":"DE",
    "sg:address":"Gr\u00fcne Str 38",
    "sg:city":"Wernigerode",
    "sg:phone":"+49 6124/508540",
    "sg:postcode":"38855",
    "sg:province":"Sachsen-Anhalt",
    "wof:name":"N. C. Wollitz",
    "wof:placetype":"venue"
},
  "geometry": {"coordinates":[8.07026,50.141918],"type":"Point"}
}