{
  "type": "Feature",
  "properties": {
    "iso:country":"DE",
    "sg:address":"Obere Kanalstr. 1",
    "sg:city":"N\u00fcrnberg",
    "sg:phone":"+49 911/266753",
    "sg:postcode":"90429",
    "sg:province":"Bayern",
    "wof:name":"E. Thrun",
    "wof:placetype":"venue"
},
  "geometry": {"coordinates":[11.059183,49.449413],"type":"Point"}
}