{
  "type": "Feature",
  "properties": {
    "iso:country":"DE",
    "sg:address":"Bundesstr. 6",
    "sg:city":"Mayscho\u00df",
    "sg:phone":"+49 2643/7106",
    "sg:postcode":"53508",
    "sg:province":"Rheinland-Pfalz",
    "wof:name":"F. B\u00f6lling Weinanbau",
    "wof:placetype":"venue"
},
  "geometry": {"coordinates":[7.0131158829,50.5168151855],"type":"Point"}
}