{
  "type": "Feature",
  "properties": {
    "iso:country":"DE",
    "sg:address":"In der Welsmicke 5",
    "sg:city":"Kirchhundem",
    "sg:phone":"+49 2764/9320",
    "sg:postcode":"57399",
    "sg:province":"Nordrhein-Westfalen",
    "wof:name":"Alac Elektrik-mechanik- Vertrieb Gmbh",
    "wof:placetype":"venue"
},
  "geometry": {"coordinates":[7.9898548126,51.0370635986],"type":"Point"}
}