{
  "type": "Feature",
  "properties": {
    "iso:country":"DE",
    "sg:address":"Geleitsstr. 45",
    "sg:city":"Offenbach",
    "sg:phone":"+49 69/816931",
    "sg:postcode":"63065",
    "sg:province":"Hessen",
    "wof:name":"E. Loiotile",
    "wof:placetype":"venue"
},
  "geometry": {"coordinates":[8.760487,50.103001],"type":"Point"}
}