{
  "type": "Feature",
  "properties": {
    "iso:country":"DE",
    "sg:address":"Hemplastr. 17",
    "sg:city":"Bad Steben",
    "sg:phone":"+49 9288/97290",
    "sg:postcode":"95138",
    "sg:province":"Bayern",
    "wof:name":"Kursanatorium Horn Ohg",
    "wof:placetype":"venue"
},
  "geometry": {"coordinates":[11.6383237839,50.360408783],"type":"Point"}
}