{
  "type": "Feature",
  "properties": {
    "iso:country":"DE",
    "sg:address":"Fliederstr. 15",
    "sg:city":"Wiesmoor",
    "sg:phone":"+49 4944/2523",
    "sg:postcode":"26639",
    "sg:province":"Niedersachsen",
    "wof:name":"Kreissparkasse Aurich Ostfries",
    "wof:placetype":"venue"
},
  "geometry": {"coordinates":[7.73018,53.382515],"type":"Point"}
}