{
  "type": "Feature",
  "properties": {
    "iso:country":"DE",
    "sg:address":"Kaninenbergh\u00f6he 8",
    "sg:city":"Essen",
    "sg:phone":"+49 201/894790",
    "sg:postcode":"45136",
    "sg:province":"Nordrhein-Westfalen",
    "wof:name":"Intertemp Outsourcing Gmbh",
    "wof:placetype":"venue"
},
  "geometry": {"coordinates":[7.034779,51.432228],"type":"Point"}
}