{
  "type": "Feature",
  "properties": {
    "iso:country":"DE",
    "sg:address":"Fleiner Str. 28",
    "sg:city":"Heilbronn",
    "sg:phone":"+49 7131/676080",
    "sg:postcode":"74072",
    "sg:province":"Baden-W\u00fcrttemberg",
    "wof:name":"Fielmann Ag & Co. Ohg",
    "wof:placetype":"venue"
},
  "geometry": {"coordinates":[9.219368,49.140842],"type":"Point"}
}