{
  "type": "Feature",
  "properties": {
    "iso:country":"DE",
    "sg:address":"Wilhelmshavener Str. 18",
    "sg:city":"M\u00fcnchen",
    "sg:phone":"+49 89/1496270",
    "sg:postcode":"80997",
    "sg:province":"Bayern",
    "wof:name":"Adolf Kasper",
    "wof:placetype":"venue"
},
  "geometry": {"coordinates":[11.500254631,48.1856689453],"type":"Point"}
}