{
  "type": "Feature",
  "properties": {
    "iso:country":"DE",
    "sg:address":"Besterfeld 5",
    "sg:city":"Telgte",
    "sg:phone":"+49 2504/4422",
    "sg:postcode":"48291",
    "sg:province":"Nordrhein-Westfalen",
    "wof:name":"Bernhard Aertker",
    "wof:placetype":"venue"
},
  "geometry": {"coordinates":[7.834375,51.954849],"type":"Point"}
}