{
  "type": "Feature",
  "properties": {
    "iso:country":"DE",
    "sg:address":"Junkersstr. 1",
    "sg:city":"K\u00f6nigsbrunn",
    "sg:phone":"+49 8231/1229",
    "sg:postcode":"86343",
    "sg:province":"Bayern",
    "wof:name":"Wertbau Ost-west Bau- Tr\u00e4ger Und Immobilien Gmbh",
    "wof:placetype":"venue"
},
  "geometry": {"coordinates":[10.876291,48.253166],"type":"Point"}
}