{
  "type": "Feature",
  "properties": {
    "iso:country":"DE",
    "sg:address":"Arndtstr.",
    "sg:city":"Lengerich",
    "sg:phone":"+49 5481/937421",
    "sg:postcode":"49525",
    "sg:province":"Nordrhein-Westfalen",
    "wof:name":"Grundmann-mucke- Recycling Gmbh",
    "wof:placetype":"venue"
},
  "geometry": {"coordinates":[7.881572,52.180412],"type":"Point"}
}