{
  "type": "Feature",
  "properties": {
    "iso:country":"DE",
    "sg:address":"Konstantinplatz 14",
    "sg:city":"M\u00f6nchengladbach",
    "sg:phone":"+49 2166/87361",
    "sg:postcode":"41238",
    "sg:province":"Nordrhein-Westfalen",
    "wof:name":"Schuhhaus Hasler & Prinz Inh. Helmut Hasler",
    "wof:placetype":"venue"
},
  "geometry": {"coordinates":[6.4909901619,51.1553611755],"type":"Point"}
}