{
  "type": "Feature",
  "properties": {
    "iso:country":"DE",
    "sg:address":"M\u00fcnchner Str. 18",
    "sg:city":"Gmund",
    "sg:phone":"+49 8022/76319",
    "sg:postcode":"83703",
    "sg:province":"Bayern",
    "wof:name":"Fundus-hal Steuerbera- Tungsgesellschaft Und",
    "wof:placetype":"venue"
},
  "geometry": {"coordinates":[11.7387228012,47.7522926331],"type":"Point"}
}