{
  "type": "Feature",
  "properties": {
    "iso:country":"DE",
    "sg:address":"Bavenhauser Str. 61",
    "sg:city":"Kalletal",
    "sg:phone":"+49 5264/392",
    "sg:postcode":"32689",
    "sg:province":"Nordrhein-Westfalen",
    "wof:name":"Gustav Stock",
    "wof:placetype":"venue"
},
  "geometry": {"coordinates":[8.952397,52.079792],"type":"Point"}
}