{
  "type": "Feature",
  "properties": {
    "iso:country":"DE",
    "sg:address":"Industriestr. 14",
    "sg:city":"Mainhausen",
    "sg:phone":"+49 6182/21867",
    "sg:postcode":"63533",
    "sg:province":"Hessen",
    "wof:name":"Gefinal Blech- Und Stahlbau Gmbh",
    "wof:placetype":"venue"
},
  "geometry": {"coordinates":[8.99275,50.018761],"type":"Point"}
}