{
  "type": "Feature",
  "properties": {
    "iso:country":"DE",
    "sg:address":"Luitfriedstr. 2",
    "sg:city":"Geisingen-Leipferdingen",
    "sg:postcode":"78187",
    "sg:province":"Baden-W\u00fcrttemberg",
    "wof:name":"Landgasthof Kreuz, Leipferdingen, Stadt Geisingen",
    "wof:placetype":"venue"
},
  "geometry": {"coordinates":[8.6685838699,47.8648033142],"type":"Point"}
}