{"geometry":{"type":"Point","coordinates":[13.074541,52.383911]},"type":"Feature","id":102560455,"bbox":[13.074541,52.383911,13.074541,52.383911],"properties":{"sg:province":"Brandenburg","geom:longitude":13.074541,"wof:breaches":[],"sg:href":"http://api.simplegeo.com/1.0/features/SG_62W4gxwrbOucr3Xha1wbrR_52.383911_13.074541@1306268793.json","sg:owner":"simplegeo","sg:postcode":"14473","geom:latitude":52.383911,"sg:classifiers":[],"sg:address":"Heinrich-Mann-Allee 103::","sg:phone":"+49 4933/18660","wof:hierarchy":[{"venue_id":102560455,"region_id":85682553,"country_id":85633111,"locality_id":101748815,"county_id":102063931,"neighbourhood_id":85900127}],"geom:area":0.000000,"sg:city":"Potsdam","wof:lastmodified":1438093256,"iso:country":"DE","wof:geomhash":"be9d38d07ed8a7906c650cb624cc5e1d","wof:name":"Ministerium Fuer Arbeit, Soziales, Gesundheit U Frauen Des Landes Bran","wof:belongsto":[85682553,85633111,101748815,102063931,85900127],"src:geom":"simplegeo","wof:placetype":"venue","wof:supersedes":[],"wof:id":102560455,"wof:superseded_by":[],"wof:concordances":{"sg:id":"SG_62W4gxwrbOucr3Xha1wbrR_52.383911_13.074541@1306268793"},"wof:parent_id":85900127}}