{
  "type": "Feature",
  "properties": {
    "iso:country":"DE",
    "sg:address":"Albrechtstr. 3",
    "sg:city":"Erfurt",
    "sg:phone":"+49 361/2111976",
    "sg:postcode":"99089",
    "sg:province":"Th\u00fcringen",
    "wof:name":"Mann & Nolte Partnerschaft Freie Architekten Und",
    "wof:placetype":"venue"
},
  "geometry": {"coordinates":[11.019483,50.986012],"type":"Point"}
}