{
  "type": "Feature",
  "properties": {
    "iso:country":"DE",
    "sg:address":"Dorfstr. 32a",
    "sg:city":"Arpsdorf",
    "sg:phone":"+49 4324/883908",
    "sg:postcode":"24634",
    "sg:province":"Schleswig-Holstein",
    "wof:name":"T. Weede",
    "wof:placetype":"venue"
},
  "geometry": {"coordinates":[9.8594036102,54.0375823975],"type":"Point"}
}