{
  "type": "Feature",
  "properties": {
    "iso:country":"DE",
    "sg:address":"Ringallee 5",
    "sg:city":"Osterhofen",
    "sg:phone":"+49 9932/3126",
    "sg:postcode":"94486",
    "sg:province":"Bayern",
    "wof:name":"The Rolling Dancers",
    "wof:placetype":"venue"
},
  "geometry": {"coordinates":[13.0190649033,48.6975517273],"type":"Point"}
}