{
  "type": "Feature",
  "properties": {
    "iso:country":"DE",
    "sg:address":"L\u00fcbsche Str. 34",
    "sg:city":"Wismar",
    "sg:phone":"+49 3841/211982",
    "sg:postcode":"23966",
    "sg:province":"Mecklenburg-Vorpommern",
    "wof:name":"A. Karge",
    "wof:placetype":"venue"
},
  "geometry": {"coordinates":[11.4620780945,53.8919219971],"type":"Point"}
}