{
  "type": "Feature",
  "properties": {
    "iso:country":"DE",
    "sg:address":"Lindenstr. 24",
    "sg:city":"Olpe",
    "sg:phone":"+49 2761/66418",
    "sg:postcode":"57462",
    "sg:province":"Nordrhein-Westfalen",
    "wof:name":"G\u00fcnther Besting",
    "wof:placetype":"venue"
},
  "geometry": {"coordinates":[7.8580160141,51.0290260315],"type":"Point"}
}