{
  "type": "Feature",
  "properties": {
    "iso:country":"DE",
    "sg:address":"Am Sandh\u00f6fer Weg 1",
    "sg:city":"Viernheim",
    "sg:phone":"+49 6204/3726",
    "sg:postcode":"68519",
    "sg:province":"Hessen",
    "wof:name":"Fritz Kempf Containerdienst Und",
    "wof:placetype":"venue"
},
  "geometry": {"coordinates":[8.5562982559,49.5375404358],"type":"Point"}
}