{
  "type": "Feature",
  "properties": {
    "iso:country":"DE",
    "sg:address":"Geibelstr. 14",
    "sg:city":"Hannover",
    "sg:phone":"+49 511/888272",
    "sg:postcode":"30173",
    "sg:province":"Niedersachsen",
    "wof:name":"J\u00fcrgen H. Bertram",
    "wof:placetype":"venue"
},
  "geometry": {"coordinates":[9.7584400177,52.3614768982],"type":"Point"}
}