{
  "type": "Feature",
  "properties": {
    "iso:country":"DE",
    "sg:address":"Tempelstr. 6",
    "sg:city":"Berge",
    "sg:phone":"+49 5435/656",
    "sg:postcode":"49626",
    "sg:province":"Niedersachsen",
    "wof:name":"Wilhelm Husmann",
    "wof:placetype":"venue"
},
  "geometry": {"coordinates":[7.743682,52.61956],"type":"Point"}
}