{
  "type": "Feature",
  "properties": {
    "iso:country":"DE",
    "sg:address":"Sandtrift 47",
    "sg:city":"Minden",
    "sg:phone":"+49 571/44333",
    "sg:postcode":"32425",
    "sg:province":"Nordrhein-Westfalen",
    "wof:name":"Eiscafe F. Olivotti",
    "wof:placetype":"venue"
},
  "geometry": {"coordinates":[8.893913,52.302364],"type":"Point"}
}