{
  "type": "Feature",
  "properties": {
    "iso:country":"DE",
    "sg:address":"W\u00e4chtersbacher Weg 7",
    "sg:city":"Bad Orb",
    "sg:phone":"+49 6052/3329",
    "sg:postcode":"63619",
    "sg:province":"Hessen",
    "wof:name":"Helmut Gillich Architekt",
    "wof:placetype":"venue"
},
  "geometry": {"coordinates":[9.336339,50.236771],"type":"Point"}
}