{
  "type": "Feature",
  "properties": {
    "iso:country":"DE",
    "sg:address":"B\u00fcrgler Str. 9",
    "sg:city":"Schliengen",
    "sg:phone":"+49 7635/1021",
    "sg:postcode":"79418",
    "sg:province":"Baden-W\u00fcrttemberg",
    "wof:name":"Hermann Bieg & Sohn Gmbh",
    "wof:placetype":"venue"
},
  "geometry": {"coordinates":[7.6462020874,47.756778717],"type":"Point"}
}