{
  "type": "Feature",
  "properties": {
    "iso:country":"DE",
    "sg:address":"Zeitzerstrasse 17",
    "sg:city":"Ronneburg",
    "sg:phone":"+49 36602/23177",
    "sg:postcode":"07580",
    "sg:province":"Th\u00fcringen",
    "wof:name":"Sporthotel Ronneburg",
    "wof:placetype":"venue"
},
  "geometry": {"coordinates":[12.184688,50.867138],"type":"Point"}
}