{
  "type": "Feature",
  "properties": {
    "iso:country":"DE",
    "sg:address":"Niederwall 53",
    "sg:city":"Bielefeld",
    "sg:phone":"+49 521/5951",
    "sg:postcode":"33602",
    "sg:province":"Nordrhein-Westfalen",
    "wof:name":"E. Gundlach Gmbh & Co. Kg",
    "wof:placetype":"venue"
},
  "geometry": {"coordinates":[8.533692,52.017502],"type":"Point"}
}