{
  "type": "Feature",
  "properties": {
    "iso:country":"DE",
    "sg:address":"Formerstr. 61",
    "sg:city":"Wetzlar",
    "sg:phone":"+49 6441/32424",
    "sg:postcode":"35576",
    "sg:province":"Hessen",
    "wof:name":"Linden-apotheke Klaus Kr\u00fcger",
    "wof:placetype":"venue"
},
  "geometry": {"coordinates":[8.503176,50.572407],"type":"Point"}
}