{
  "type": "Feature",
  "properties": {
    "iso:country":"DE",
    "sg:address":"Landsberger Allee 193",
    "sg:city":"Berlin",
    "sg:phone":"+49 30/9720429",
    "sg:postcode":"10369",
    "sg:province":"Berlin",
    "wof:name":"Dr. Med. G\u00fcnter Hentschel",
    "wof:placetype":"venue"
},
  "geometry": {"coordinates":[13.474427,52.533199],"type":"Point"}
}