{
  "type": "Feature",
  "properties": {
    "iso:country":"DE",
    "sg:address":"Gr\u00e4pelweg 10",
    "sg:city":"Hamburg",
    "sg:phone":"+49 40/7245343",
    "sg:postcode":"21029",
    "sg:province":"Hamburg",
    "wof:name":"Ulrich Z\u00fcndel",
    "wof:placetype":"venue"
},
  "geometry": {"coordinates":[10.2184886932,53.4891777039],"type":"Point"}
}