{
  "type": "Feature",
  "properties": {
    "iso:country":"DE",
    "sg:address":"Marktplatz 8",
    "sg:city":"Waldbronn",
    "sg:phone":"+49 7243/652220",
    "sg:postcode":"76337",
    "sg:province":"Baden-W\u00fcrttemberg",
    "wof:name":"Kult Cafe-restaurant",
    "wof:placetype":"venue"
},
  "geometry": {"coordinates":[8.472051,48.929321],"type":"Point"}
}