{
  "type": "Feature",
  "properties": {
    "iso:country":"DE",
    "sg:address":"Altenburgstr. 11",
    "sg:city":"Bonn",
    "sg:phone":"+49 228/5432750",
    "sg:postcode":"53125",
    "sg:province":"Nordrhein-Westfalen",
    "wof:name":"Johann-bernhard-mann-stiftung",
    "wof:placetype":"venue"
},
  "geometry": {"coordinates":[7.0633068085,50.6993103027],"type":"Point"}
}