{
  "type": "Feature",
  "properties": {
    "iso:country":"DE",
    "sg:address":"Griesingerstr. 35",
    "sg:city":"Reutlingen",
    "sg:phone":"+49 7121/52679",
    "sg:postcode":"72770",
    "sg:province":"Baden-W\u00fcrttemberg",
    "wof:name":"Mohrenk\u00f6pfle",
    "wof:placetype":"venue"
},
  "geometry": {"coordinates":[9.180385,48.497868],"type":"Point"}
}