{
  "type": "Feature",
  "properties": {
    "iso:country":"DE",
    "sg:address":"Schultenbusch 5",
    "sg:city":"Haltern",
    "sg:phone":"+49 2364/3197",
    "sg:postcode":"45721",
    "sg:province":"Nordrhein-Westfalen",
    "wof:name":"Adolf Stock",
    "wof:placetype":"venue"
},
  "geometry": {"coordinates":[7.198,51.751732],"type":"Point"}
}