{
  "type": "Feature",
  "properties": {
    "iso:country":"DE",
    "sg:address":"Laimer Str. 36",
    "sg:city":"M\u00fcnchen",
    "sg:phone":"+49 89/174335",
    "sg:postcode":"80639",
    "sg:province":"Bayern",
    "wof:name":"Papier Karl Gmbh & Co. Vertriebs Kg",
    "wof:placetype":"venue"
},
  "geometry": {"coordinates":[11.5044298172,48.1528968811],"type":"Point"}
}