{
  "type": "Feature",
  "properties": {
    "iso:country":"DE",
    "sg:address":"Steilhofweg 9",
    "sg:city":"Bayerisch Gmain",
    "sg:phone":"+49 8651/98820",
    "sg:postcode":"83457",
    "sg:province":"Bayern",
    "wof:name":"G\u00e4stehaus Christiane",
    "wof:placetype":"venue"
},
  "geometry": {"coordinates":[12.8896980286,47.7266845703],"type":"Point"}
}