{
  "type": "Feature",
  "properties": {
    "iso:country":"DE",
    "sg:address":"Sedlmaierstr. 8",
    "sg:city":"Reischach",
    "sg:phone":"+49 8670/267",
    "sg:postcode":"84571",
    "sg:province":"Bayern",
    "wof:name":"R. Maier",
    "wof:placetype":"venue"
},
  "geometry": {"coordinates":[12.72594,48.29361],"type":"Point"}
}