{
  "type": "Feature",
  "properties": {
    "iso:country":"DE",
    "sg:address":"Hohnerstr. 23",
    "sg:city":"Trossingen",
    "sg:phone":"+49 7425/7507",
    "sg:postcode":"78647",
    "sg:province":"Baden-W\u00fcrttemberg",
    "wof:name":"H. Link Elektro-install.",
    "wof:placetype":"venue"
},
  "geometry": {"coordinates":[8.635264,48.074654],"type":"Point"}
}