{
  "type": "Feature",
  "properties": {
    "iso:country":"DE",
    "sg:address":"Osnabr\u00fccker Str. 5",
    "sg:city":"Bad Iburg",
    "sg:postcode":"49186",
    "sg:province":"Niedersachsen",
    "wof:name":"Krabusch Bauabwicklungsges. Mbh",
    "wof:placetype":"venue"
},
  "geometry": {"coordinates":[8.04733,52.159302],"type":"Point"}
}