{
  "type": "Feature",
  "properties": {
    "iso:country":"DE",
    "sg:address":"Unterer Kuhberg 16",
    "sg:city":"Ulm",
    "sg:phone":"+49 731/32901",
    "sg:postcode":"89077",
    "sg:province":"Baden-W\u00fcrttemberg",
    "wof:name":"Fanfarenkorps Ulm E. V.",
    "wof:placetype":"venue"
},
  "geometry": {"coordinates":[9.9711999893,48.383430481],"type":"Point"}
}