{
  "type": "Feature",
  "properties": {
    "iso:country":"DE",
    "sg:address":"Industriestr. 25",
    "sg:city":"Holzkirchen",
    "sg:phone":"+49 8024/9080",
    "sg:postcode":"83607",
    "sg:province":"Bayern",
    "wof:name":"Biocur Arzneimittel Gmbh",
    "wof:placetype":"venue"
},
  "geometry": {"coordinates":[11.7132730484,47.8797683716],"type":"Point"}
}