{
  "type": "Feature",
  "properties": {
    "iso:country":"DE",
    "sg:address":"Pasteurstr. 11",
    "sg:city":"Potsdam",
    "sg:phone":"+49 331/719947",
    "sg:postcode":"14482",
    "sg:province":"Brandenburg",
    "wof:name":"P.s.o. Pr\u00fcf- Und Beratungsges. F. Oberbau-u.schwei\u00dftechn. Mbh",
    "wof:placetype":"venue"
},
  "geometry": {"coordinates":[13.0979709625,52.3971366882],"type":"Point"}
}