{
  "type": "Feature",
  "properties": {
    "iso:country":"DE",
    "sg:address":"Gie\u00dfener Str. 81",
    "sg:city":"Fritzlar",
    "sg:postcode":"34560",
    "sg:province":"Hessen",
    "wof:name":"Range Logistik Gmbh",
    "wof:placetype":"venue"
},
  "geometry": {"coordinates":[9.2788877487,51.121837616],"type":"Point"}
}