{
  "type": "Feature",
  "properties": {
    "iso:country":"DE",
    "sg:address":"Freiburger Weg 16",
    "sg:city":"Troisdorf",
    "sg:phone":"+49 2241/409684",
    "sg:postcode":"53844",
    "sg:province":"Nordrhein-Westfalen",
    "wof:name":"Agens E. K.",
    "wof:placetype":"venue"
},
  "geometry": {"coordinates":[7.116092,50.807426],"type":"Point"}
}