{
  "type": "Feature",
  "properties": {
    "iso:country":"DE",
    "sg:address":"Liricher Str. 128",
    "sg:city":"Oberhausen",
    "sg:phone":"+49 208/27003",
    "sg:postcode":"46049",
    "sg:province":"Nordrhein-Westfalen",
    "wof:name":"Helmut Kolaska",
    "wof:placetype":"venue"
},
  "geometry": {"coordinates":[6.831463,51.482807],"type":"Point"}
}