{
  "type": "Feature",
  "properties": {
    "iso:country":"DE",
    "sg:address":"Antlesbrunnweg 4",
    "sg:city":"Furth im Wald",
    "sg:phone":"+49 9973/1740",
    "sg:postcode":"93437",
    "sg:province":"Bayern",
    "wof:name":"Franz Siebenh\u00f6rl",
    "wof:placetype":"venue"
},
  "geometry": {"coordinates":[12.8426370621,49.3152313232],"type":"Point"}
}