{
  "type": "Feature",
  "properties": {
    "iso:country":"DE",
    "sg:address":"Marschweg 5",
    "sg:city":"Beetzendorf",
    "sg:phone":"+49 39000/370",
    "sg:postcode":"38489",
    "sg:province":"Sachsen-Anhalt",
    "wof:name":"Energie-versorgung Gmbh",
    "wof:placetype":"venue"
},
  "geometry": {"coordinates":[11.0901403427,52.7031326294],"type":"Point"}
}