{
  "type": "Feature",
  "properties": {
    "iso:country":"DE",
    "sg:address":"Oberdorfstr. 139",
    "sg:city":"Mittelherwigsdorf",
    "sg:phone":"+49 3583/703430",
    "sg:postcode":"02763",
    "sg:province":"Sachsen",
    "wof:name":"Klaus Sch\u00fctze",
    "wof:placetype":"venue"
},
  "geometry": {"coordinates":[14.7720184326,50.9254493713],"type":"Point"}
}