{
  "type": "Feature",
  "properties": {
    "iso:country":"DE",
    "sg:address":"G\u00e4rtnerstr. 11",
    "sg:city":"Lahr",
    "sg:phone":"+49 7821/23968",
    "sg:postcode":"77933",
    "sg:province":"Baden-W\u00fcrttemberg",
    "wof:name":"Alfa-intex Industrie- Technik Gmbh",
    "wof:placetype":"venue"
},
  "geometry": {"coordinates":[7.876487,48.340721],"type":"Point"}
}