{
  "type": "Feature",
  "properties": {
    "iso:country":"DE",
    "sg:address":"Norderhofenden 6-9",
    "sg:city":"Flensburg",
    "sg:phone":"+49 4969/79260",
    "sg:postcode":"24937",
    "sg:province":"Schleswig-Holstein",
    "wof:name":"Mercure Hotel",
    "wof:placetype":"venue"
},
  "geometry": {"coordinates":[8.639515,50.116787],"type":"Point"}
}