{
  "type": "Feature",
  "properties": {
    "iso:country":"DE",
    "sg:address":"Schmelzgerweg 8",
    "sg:city":"Dortmund",
    "sg:phone":"+49 231/800030",
    "sg:postcode":"44339",
    "sg:province":"Nordrhein-Westfalen",
    "wof:name":"Bema Maschinen-bau Gmbh",
    "wof:placetype":"venue"
},
  "geometry": {"coordinates":[7.464483,51.585186],"type":"Point"}
}