{
  "type": "Feature",
  "properties": {
    "iso:country":"DE",
    "sg:address":"Frankfurter Ring 247",
    "sg:city":"M\u00fcnchen",
    "sg:phone":"+49 89/3228019",
    "sg:postcode":"80807",
    "sg:province":"Bayern",
    "wof:name":"Schlosserei Ludwig Bauer Gmbh",
    "wof:placetype":"venue"
},
  "geometry": {"coordinates":[11.607011795,48.1865692139],"type":"Point"}
}