{
  "type": "Feature",
  "properties": {
    "iso:country":"DE",
    "sg:address":"Lierestr. 37",
    "sg:city":"Vienenburg",
    "sg:phone":"+49 4953/2477880",
    "sg:postcode":"38690",
    "sg:province":"Niedersachsen",
    "wof:name":"Dipl. Ing. Paul Drastik Gmbh",
    "wof:placetype":"venue"
},
  "geometry": {"coordinates":[10.559205,51.949341],"type":"Point"}
}