{
  "type": "Feature",
  "properties": {
    "iso:country":"DE",
    "sg:address":"Jenaische Str. 187",
    "sg:city":"Uhlst\u00e4dt",
    "sg:postcode":"07407",
    "sg:province":"Th\u00fcringen",
    "wof:name":"Kinderheim Georg Schwarz",
    "wof:placetype":"venue"
},
  "geometry": {"coordinates":[11.4712896347,50.7428016663],"type":"Point"}
}