{
  "type": "Feature",
  "properties": {
    "iso:country":"DE",
    "sg:address":"Waldenburger Str. 108",
    "sg:city":"Limbach-Oberfrohna",
    "sg:phone":"+49 3722/93669",
    "sg:postcode":"09212",
    "sg:province":"Sachsen",
    "wof:name":"Restaurant Stadt Altenburg",
    "wof:placetype":"venue"
},
  "geometry": {"coordinates":[12.728017807,50.8498573303],"type":"Point"}
}