{
  "type": "Feature",
  "properties": {
    "iso:country":"DE",
    "sg:address":"Jugenheimer Str. 4",
    "sg:city":"Zwingenberg",
    "sg:phone":"+49 6251/788890",
    "sg:postcode":"64673",
    "sg:province":"Hessen",
    "wof:name":"Michael Und Heidrun K\u00fcppers",
    "wof:placetype":"venue"
},
  "geometry": {"coordinates":[8.6162099838,49.7302703857],"type":"Point"}
}