{
  "type": "Feature",
  "properties": {
    "iso:country":"DE",
    "sg:address":"Viktoriastr. 10",
    "sg:city":"Saarbr\u00fccken",
    "sg:phone":"+49 681/31211",
    "sg:postcode":"66111",
    "sg:province":"Saarland",
    "wof:name":"Franz Strauch",
    "wof:placetype":"venue"
},
  "geometry": {"coordinates":[6.9906439781,49.2376480103],"type":"Point"}
}