{
  "type": "Feature",
  "properties": {
    "iso:country":"DE",
    "sg:address":"Georgenberg 8 a",
    "sg:city":"Naumburg",
    "sg:phone":"+49 3445/205128",
    "sg:postcode":"06618",
    "sg:province":"Sachsen-Anhalt",
    "wof:name":"Gabi Rademann",
    "wof:placetype":"venue"
},
  "geometry": {"coordinates":[11.801384,51.158279],"type":"Point"}
}