{
  "type": "Feature",
  "properties": {
    "iso:country":"DE",
    "sg:address":"Fritz-Reuter-Str. 10",
    "sg:city":"Schwerin",
    "sg:phone":"+49 385/734108",
    "sg:postcode":"19053",
    "sg:province":"Mecklenburg-Vorpommern",
    "wof:name":"Christian Vollbracht Architekt",
    "wof:placetype":"venue"
},
  "geometry": {"coordinates":[11.405229,53.628246],"type":"Point"}
}