{
  "type": "Feature",
  "properties": {
    "iso:country":"DE",
    "sg:address":"Kleindorferstr.9",
    "sg:city":"Allmendingen",
    "sg:postcode":"89604",
    "sg:province":"Baden-W\u00fcrttemberg",
    "wof:name":"The World Of Steeleater",
    "wof:placetype":"venue"
},
  "geometry": {"coordinates":[9.720264,48.329815],"type":"Point"}
}