{
  "type": "Feature",
  "properties": {
    "iso:country":"DE",
    "sg:address":"Troppauer Str. 10",
    "sg:city":"M\u00fcnchen",
    "sg:phone":"+49 89/3185580",
    "sg:postcode":"80937",
    "sg:province":"Bayern",
    "wof:name":"Dreistern Nahrungsmittel Gmbh",
    "wof:placetype":"venue"
},
  "geometry": {"coordinates":[11.5727348328,48.195098877],"type":"Point"}
}