{
  "type": "Feature",
  "properties": {
    "iso:country":"DE",
    "sg:address":"Am Gewerbepark 20",
    "sg:city":"Gransee",
    "sg:phone":"+49 4933/0679960",
    "sg:postcode":"16775",
    "sg:province":"Brandenburg",
    "wof:name":"Christensen Gmbh & Co. Kg",
    "wof:placetype":"venue"
},
  "geometry": {"coordinates":[13.1756792068,53.0065345764],"type":"Point"}
}