{
  "type": "Feature",
  "properties": {
    "iso:country":"DE",
    "sg:address":"H\u00f6hrer Str. 12",
    "sg:city":"Vallendar",
    "sg:phone":"+49 261/61898",
    "sg:postcode":"56179",
    "sg:province":"Rheinland-Pfalz",
    "wof:name":"Holz-ideen Hambach",
    "wof:placetype":"venue"
},
  "geometry": {"coordinates":[7.617386,50.401817],"type":"Point"}
}