{
  "type": "Feature",
  "properties": {
    "iso:country":"DE",
    "sg:address":"Neumarkt 6",
    "sg:city":"Gelsenkirchen",
    "sg:phone":"+49 209/207372",
    "sg:postcode":"45879",
    "sg:province":"Nordrhein-Westfalen",
    "wof:name":"Gotthardt Kg",
    "wof:placetype":"venue"
},
  "geometry": {"coordinates":[7.096739,51.509552],"type":"Point"}
}