{
  "type": "Feature",
  "properties": {
    "iso:country":"DE",
    "sg:address":"Gehrener Str. 5-7",
    "sg:city":"K\u00f6nigsee",
    "sg:postcode":"07426",
    "sg:province":"Th\u00fcringen",
    "wof:name":"Lattermann-baustoffrecycling Und Abbruch Ohg",
    "wof:placetype":"venue"
},
  "geometry": {"coordinates":[11.09357,50.660431],"type":"Point"}
}