{
  "type": "Feature",
  "properties": {
    "iso:country":"DE",
    "sg:address":"Mozartstr. 1",
    "sg:city":"B\u00fcrstadt",
    "sg:phone":"+49 6206/6369",
    "sg:postcode":"68642",
    "sg:province":"Hessen",
    "wof:name":"Nikolaus Glanzner Architekt",
    "wof:placetype":"venue"
},
  "geometry": {"coordinates":[8.456295,49.646355],"type":"Point"}
}