{
  "type": "Feature",
  "properties": {
    "iso:country":"DE",
    "sg:address":"Plan",
    "sg:city":"Wallbach",
    "sg:postcode":"98639",
    "sg:province":"Th\u00fcringen",
    "wof:name":"Ingenieurb\u00fcro Ra\u00dfmann",
    "wof:placetype":"venue"
},
  "geometry": {"coordinates":[10.3953046799,50.6284255981],"type":"Point"}
}