{
  "type": "Feature",
  "properties": {
    "iso:country":"DE",
    "sg:address":"Treuerstr. 6 a",
    "sg:city":"Clausthal-Zellerfeld",
    "sg:phone":"+49 5323/82033",
    "sg:postcode":"38678",
    "sg:province":"Niedersachsen",
    "wof:name":"Horst Stahr",
    "wof:placetype":"venue"
},
  "geometry": {"coordinates":[10.334564,51.818474],"type":"Point"}
}