{
  "type": "Feature",
  "properties": {
    "iso:country":"DE",
    "sg:address":"Im Ohle 13",
    "sg:city":"Schmallenberg",
    "sg:phone":"+49 2974/900096",
    "sg:postcode":"57392",
    "sg:province":"Nordrhein-Westfalen",
    "wof:name":"Restaurant Oskar's",
    "wof:placetype":"venue"
},
  "geometry": {"coordinates":[8.3110227585,51.1894569397],"type":"Point"}
}