{
  "type": "Feature",
  "properties": {
    "iso:country":"DE",
    "sg:address":"K\u00f6nigstr. 2",
    "sg:city":"N\u00fcrnberg",
    "sg:phone":"+49 911/227218",
    "sg:postcode":"90402",
    "sg:province":"Bayern",
    "wof:name":"Campo-eis Inh. Fabrizio Campo-bagatin",
    "wof:placetype":"venue"
},
  "geometry": {"coordinates":[11.077645,49.45248],"type":"Point"}
}