{
  "type": "Feature",
  "properties": {
    "iso:country":"DE",
    "sg:address":"Sch\u00f6nberger Str. 30",
    "sg:city":"Bad Brambach",
    "sg:phone":"+49 37438/22752",
    "sg:postcode":"08648",
    "sg:province":"Sachsen",
    "wof:name":"Pension Haus Gabriel",
    "wof:placetype":"venue"
},
  "geometry": {"coordinates":[12.3068189621,50.2150535583],"type":"Point"}
}