{
  "type": "Feature",
  "properties": {
    "iso:country":"DE",
    "sg:address":"Eschenhahner Weg 11",
    "sg:city":"Niedernhausen",
    "sg:phone":"+49 6128/73573",
    "sg:postcode":"65527",
    "sg:province":"Hessen",
    "wof:name":"Hans Fein Rechtsanwalt",
    "wof:placetype":"venue"
},
  "geometry": {"coordinates":[8.2467947006,50.1752243042],"type":"Point"}
}