{
  "type": "Feature",
  "properties": {
    "iso:country":"DE",
    "sg:address":"K\u00e4the-Kollwitz-Str. 16",
    "sg:city":"Bautzen",
    "sg:phone":"+49 3591/44582",
    "sg:postcode":"02625",
    "sg:province":"Sachsen",
    "wof:name":"Mv Bautzen Zustellservice Gmbh",
    "wof:placetype":"venue"
},
  "geometry": {"coordinates":[14.437648,51.170773],"type":"Point"}
}