{
  "type": "Feature",
  "properties": {
    "iso:country":"DE",
    "sg:address":"Schildkr\u00f6tstr 29",
    "sg:city":"Mannheim",
    "sg:phone":"+49 621/842540",
    "sg:postcode":"68199",
    "sg:province":"Baden-W\u00fcrttemberg",
    "wof:name":"Soflex Gmbh",
    "wof:placetype":"venue"
},
  "geometry": {"coordinates":[8.498989,49.455471],"type":"Point"}
}