{
  "type": "Feature",
  "properties": {
    "iso:country":"DE",
    "sg:address":"M\u00fcnsterstr. 7",
    "sg:city":"Everswinkel",
    "sg:postcode":"48351",
    "sg:province":"Nordrhein-Westfalen",
    "wof:name":"Protext Datenservice Gmbh",
    "wof:placetype":"venue"
},
  "geometry": {"coordinates":[7.8403987885,51.9263572693],"type":"Point"}
}