{
  "type": "Feature",
  "properties": {
    "iso:country":"DE",
    "sg:address":"Flurstr. 7 a",
    "sg:city":"St. Ingbert",
    "sg:phone":"+49 6894/8246",
    "sg:postcode":"66386",
    "sg:province":"Saarland",
    "wof:name":"Norbert Fries",
    "wof:placetype":"venue"
},
  "geometry": {"coordinates":[7.146868,49.242287],"type":"Point"}
}