{
  "type": "Feature",
  "properties": {
    "iso:country":"DE",
    "sg:address":"Schlehenstieg 17",
    "sg:city":"Ahrensburg",
    "sg:phone":"+49 4102/55582",
    "sg:postcode":"22926",
    "sg:province":"Schleswig-Holstein",
    "wof:name":"B. Georgiev",
    "wof:placetype":"venue"
},
  "geometry": {"coordinates":[10.209939003,53.6755714417],"type":"Point"}
}