{
  "type": "Feature",
  "properties": {
    "iso:country":"DE",
    "sg:address":"Raifeisenstr 15 A",
    "sg:city":"Roth",
    "sg:phone":"+49 9171/989120",
    "sg:postcode":"91154",
    "sg:province":"Bayern",
    "wof:name":"Peter Hufnagel Gmbh",
    "wof:placetype":"venue"
},
  "geometry": {"coordinates":[11.149797,49.217396],"type":"Point"}
}