{
  "type": "Feature",
  "properties": {
    "iso:country":"DE",
    "sg:address":"im schwarzbroich 28",
    "sg:city":"odenthal",
    "sg:phone":"+49 2202/709616",
    "sg:postcode":"51519",
    "sg:province":"Nordrhein-Westfalen",
    "wof:name":"Webservice-hambach",
    "wof:placetype":"venue"
},
  "geometry": {"coordinates":[7.109597,51.014446],"type":"Point"}
}