{
  "type": "Feature",
  "properties": {
    "iso:country":"DE",
    "sg:address":"Friedhofstr. 12",
    "sg:city":"M\u00fclheim",
    "sg:phone":"+49 4920/850235",
    "sg:postcode":"45478",
    "sg:province":"Nordrhein-Westfalen",
    "wof:name":"Fritz Riehl Druckerei Gmbh",
    "wof:placetype":"venue"
},
  "geometry": {"coordinates":[6.8427610397,51.4277496338],"type":"Point"}
}