{
  "type": "Feature",
  "properties": {
    "iso:country":"DE",
    "sg:address":"Karlstr. 1",
    "sg:city":"Zirndorf",
    "sg:phone":"+49 911/604021",
    "sg:postcode":"90513",
    "sg:province":"Bayern",
    "wof:name":"Sabine Gropengiesser Krankengymnastin",
    "wof:placetype":"venue"
},
  "geometry": {"coordinates":[10.959514,49.44046],"type":"Point"}
}