{
  "type": "Feature",
  "properties": {
    "iso:country":"DE",
    "sg:address":"Poststr. 1-11",
    "sg:city":"Coesfeld",
    "sg:phone":"+49 2541/84060",
    "sg:postcode":"48653",
    "sg:province":"Nordrhein-Westfalen",
    "wof:name":"Deutsche Post Ag",
    "wof:placetype":"venue"
},
  "geometry": {"coordinates":[7.1649279594,51.9441566467],"type":"Point"}
}