{
  "type": "Feature",
  "properties": {
    "iso:country":"DE",
    "sg:address":"Dechant-Kann-Str. 2",
    "sg:city":"Grevenbroich",
    "sg:postcode":"41516",
    "sg:province":"Nordrhein-Westfalen",
    "wof:name":"C & P Verlagsgesellschaft Mbh",
    "wof:placetype":"venue"
},
  "geometry": {"coordinates":[6.6195421219,51.1022949219],"type":"Point"}
}