{
  "type": "Feature",
  "properties": {
    "iso:country":"DE",
    "sg:address":"Linckeweg 11",
    "sg:city":"Waldkraiburg",
    "sg:phone":"+49 8638/3417",
    "sg:postcode":"84478",
    "sg:province":"Bayern",
    "wof:name":"M\u00fcller & Ullmann & Co. Gmbh",
    "wof:placetype":"venue"
},
  "geometry": {"coordinates":[12.416917,48.206482],"type":"Point"}
}