{
  "type": "Feature",
  "properties": {
    "iso:country":"DE",
    "sg:address":"Schlo\u00dfstr. 1",
    "sg:city":"Gaildorf",
    "sg:postcode":"74405",
    "sg:province":"Baden-W\u00fcrttemberg",
    "wof:name":"Marco Lindauer E. K.",
    "wof:placetype":"venue"
},
  "geometry": {"coordinates":[9.7698373795,49.0010566711],"type":"Point"}
}