{
  "type": "Feature",
  "properties": {
    "iso:country":"DE",
    "sg:address":"Industriestr. 15",
    "sg:city":"Idar-Oberstein",
    "sg:phone":"+49 6784/1088",
    "sg:postcode":"55743",
    "sg:province":"Rheinland-Pfalz",
    "wof:name":"Helmut Fuchs",
    "wof:placetype":"venue"
},
  "geometry": {"coordinates":[7.381547,49.724926],"type":"Point"}
}