{
  "type": "Feature",
  "properties": {
    "iso:country":"DE",
    "sg:address":"Hahnenstr. 18",
    "sg:city":"Riegelsberg",
    "sg:phone":"+49 6806/490368",
    "sg:postcode":"66292",
    "sg:province":"Saarland",
    "wof:name":"Michael Peter Rechtsanwalt",
    "wof:placetype":"venue"
},
  "geometry": {"coordinates":[6.9511499405,49.3129806519],"type":"Point"}
}