{
  "type": "Feature",
  "properties": {
    "iso:country":"DE",
    "sg:address":"Bahnhofstr. 18",
    "sg:city":"Ludwigshafen",
    "sg:phone":"+49 621/5291403",
    "sg:postcode":"67059",
    "sg:province":"Rheinland-Pfalz",
    "wof:name":"W\u00fcrttembergische Versicherung",
    "wof:placetype":"venue"
},
  "geometry": {"coordinates":[8.4446973801,49.4827384949],"type":"Point"}
}