{
  "type": "Feature",
  "properties": {
    "iso:country":"DE",
    "sg:address":"Gutenbergstr. 30",
    "sg:city":"Stuttgart",
    "sg:phone":"+49 711/6620",
    "sg:postcode":"70176",
    "sg:province":"Baden-W\u00fcrttemberg",
    "wof:name":"W\u00fcrttembergische Lebensversicherung Ag",
    "wof:placetype":"venue"
},
  "geometry": {"coordinates":[9.162831,48.773335],"type":"Point"}
}