{
  "type": "Feature",
  "properties": {
    "iso:country":"DE",
    "sg:address":"Burchardiestra\u00dfe 08",
    "sg:city":"Halberstadt",
    "sg:phone":"+49 3941/448376",
    "sg:postcode":"38820",
    "sg:province":"Sachsen-Anhalt",
    "wof:name":"Kg Bauservice Gmbh",
    "wof:placetype":"venue"
},
  "geometry": {"coordinates":[11.0409231186,51.9023017883],"type":"Point"}
}