{
  "type": "Feature",
  "properties": {
    "iso:country":"DE",
    "sg:address":"Dominikanergasse 3",
    "sg:city":"Augsburg",
    "sg:phone":"+49 821/38158",
    "sg:postcode":"86150",
    "sg:province":"Bayern",
    "wof:name":"Rudolf Wiesmann",
    "wof:placetype":"venue"
},
  "geometry": {"coordinates":[10.9001054764,48.3658561707],"type":"Point"}
}