{
  "type": "Feature",
  "properties": {
    "iso:country":"DE",
    "sg:address":"Burgstemmer Str. 10",
    "sg:city":"Betheln",
    "sg:phone":"+49 5182/1717",
    "sg:postcode":"31032",
    "sg:province":"Niedersachsen",
    "wof:name":"Helmut Meyer",
    "wof:placetype":"venue"
},
  "geometry": {"coordinates":[9.786567,52.112358],"type":"Point"}
}