{
  "type": "Feature",
  "properties": {
    "iso:country":"DE",
    "sg:address":"Peterstr. 27",
    "sg:city":"Willich",
    "sg:phone":"+49 2154/3398",
    "sg:postcode":"47877",
    "sg:province":"Nordrhein-Westfalen",
    "wof:name":"Foto-studio Dill",
    "wof:placetype":"venue"
},
  "geometry": {"coordinates":[6.5511078835,51.2645263672],"type":"Point"}
}