{
  "type": "Feature",
  "properties": {
    "iso:country":"DE",
    "sg:address":"Ahsener Str. 197",
    "sg:city":"Datteln",
    "sg:phone":"+49 2363/34443",
    "sg:postcode":"45711",
    "sg:province":"Nordrhein-Westfalen",
    "wof:name":"Ahsener-krug",
    "wof:placetype":"venue"
},
  "geometry": {"coordinates":[7.3087739944,51.6981735229],"type":"Point"}
}