{
  "type": "Feature",
  "properties": {
    "iso:country":"DE",
    "sg:address":"Schmerfeldstr. 4",
    "sg:city":"Kassel",
    "sg:phone":"+49 561/601668",
    "sg:postcode":"34130",
    "sg:province":"Hessen",
    "wof:name":"Com2",
    "wof:placetype":"venue"
},
  "geometry": {"coordinates":[9.452887,51.322659],"type":"Point"}
}