{
  "type": "Feature",
  "properties": {
    "iso:country":"DE",
    "sg:address":"Semlower Str. 14",
    "sg:city":"Stralsund",
    "sg:phone":"+49 3831/280425",
    "sg:postcode":"18439",
    "sg:province":"Mecklenburg-Vorpommern",
    "wof:name":"Speiserestaurant Garbrecht",
    "wof:placetype":"venue"
},
  "geometry": {"coordinates":[13.0932283401,54.3154907227],"type":"Point"}
}