{
  "type": "Feature",
  "properties": {
    "iso:country":"DE",
    "sg:address":"Pasteurallee 66",
    "sg:city":"Hannover",
    "sg:phone":"+49 511/5477668",
    "sg:postcode":"30655",
    "sg:province":"Niedersachsen",
    "wof:name":"Georg Zimmer",
    "wof:placetype":"venue"
},
  "geometry": {"coordinates":[9.810297,52.402847],"type":"Point"}
}