{
  "type": "Feature",
  "properties": {
    "iso:country":"DE",
    "sg:address":"Pr\u00e4lat-G\u00f6tz-Str. 17",
    "sg:city":"Kempten",
    "sg:phone":"+49 831/5120642",
    "sg:postcode":"87439",
    "sg:province":"Bayern",
    "wof:name":"Engel-neustadt",
    "wof:placetype":"venue"
},
  "geometry": {"coordinates":[10.3105573654,47.7312774658],"type":"Point"}
}