{
  "type": "Feature",
  "properties": {
    "iso:country":"DE",
    "sg:address":"Rheinall. 41",
    "sg:city":"Mainz",
    "sg:phone":"+49 4961/31128",
    "sg:postcode":"55118",
    "sg:province":"Rheinland-Pfalz",
    "wof:name":"Stadtwerke Mainz Ag",
    "wof:placetype":"venue"
},
  "geometry": {"coordinates":[8.264009,50.010658],"type":"Point"}
}