{
  "type": "Feature",
  "properties": {
    "iso:country":"DE",
    "sg:address":"Uferstr. 8",
    "sg:city":"Nittel",
    "sg:phone":"+49 6584/395",
    "sg:postcode":"54453",
    "sg:province":"Rheinland-Pfalz",
    "wof:name":"H. L\u00f6wenbr\u00fcck",
    "wof:placetype":"venue"
},
  "geometry": {"coordinates":[6.440965,49.652599],"type":"Point"}
}