{
  "type": "Feature",
  "properties": {
    "iso:country":"DE",
    "sg:address":"Werrestr. 6",
    "sg:city":"Lage",
    "sg:phone":"+49 5232/18888",
    "sg:postcode":"32791",
    "sg:province":"Nordrhein-Westfalen",
    "wof:name":"Frank Obermann",
    "wof:placetype":"venue"
},
  "geometry": {"coordinates":[8.7947635651,51.9866065979],"type":"Point"}
}