{
  "type": "Feature",
  "properties": {
    "iso:country":"DE",
    "sg:address":"Bergwerkstr. 53",
    "sg:city":"Hausen",
    "sg:phone":"+49 7622/669280",
    "sg:postcode":"79688",
    "sg:province":"Baden-W\u00fcrttemberg",
    "wof:name":"I. K\u00f6nninger-kohler Verm\u00f6gensverwaltung",
    "wof:placetype":"venue"
},
  "geometry": {"coordinates":[7.8425841331,47.6860923767],"type":"Point"}
}