{
  "type": "Feature",
  "properties": {
    "iso:country":"DE",
    "sg:address":"Schoppershofstr. 56",
    "sg:city":"N\u00fcrnberg",
    "sg:phone":"+49 911/511140",
    "sg:postcode":"90489",
    "sg:province":"Bayern",
    "wof:name":"Birgit Hain",
    "wof:placetype":"venue"
},
  "geometry": {"coordinates":[11.1011648178,49.4641075134],"type":"Point"}
}