{
  "type": "Feature",
  "properties": {
    "iso:country":"DE",
    "sg:address":"Nibelungenstr. 56",
    "sg:city":"Wendelstein",
    "sg:postcode":"90530",
    "sg:province":"Bayern",
    "wof:name":"Duho-tierzentrum Wendelstein Gmbh",
    "wof:placetype":"venue"
},
  "geometry": {"coordinates":[11.1781301498,49.3659744263],"type":"Point"}
}