{
  "type": "Feature",
  "properties": {
    "iso:country":"DE",
    "sg:address":"Gabriele-M\u00fcnter-Str. 5",
    "sg:city":"Germering",
    "sg:phone":"+49 89/846089",
    "sg:postcode":"82110",
    "sg:province":"Bayern",
    "wof:name":"Restaurant Pflaumengarten",
    "wof:placetype":"venue"
},
  "geometry": {"coordinates":[11.3674707413,48.1299858093],"type":"Point"}
}