{
  "type": "Feature",
  "properties": {
    "iso:country":"DE",
    "sg:address":"Theodorstr 41p",
    "sg:city":"Hamburg",
    "sg:phone":"+49 40/8906606",
    "sg:postcode":"22761",
    "sg:province":"Hamburg",
    "wof:name":"Just Ebert",
    "wof:placetype":"venue"
},
  "geometry": {"coordinates":[9.8973884583,53.5705795288],"type":"Point"}
}