{
  "type": "Feature",
  "properties": {
    "iso:country":"DE",
    "sg:address":"L\u00f6rsfelder Busch 19",
    "sg:city":"Kerpen",
    "sg:postcode":"50171",
    "sg:province":"Nordrhein-Westfalen",
    "wof:name":"V. E. Asensi Bildhauer",
    "wof:placetype":"venue"
},
  "geometry": {"coordinates":[6.684261,50.88076],"type":"Point"}
}