{
  "type": "Feature",
  "properties": {
    "iso:country":"DE",
    "sg:address":"Dresdner Str. 50",
    "sg:city":"Chemnitz",
    "sg:postcode":"09130",
    "sg:province":"Sachsen",
    "wof:name":"Notarsoziet\u00e4t Krause Jarzombski Und Kuckoreit",
    "wof:placetype":"venue"
},
  "geometry": {"coordinates":[12.938659668,50.8453292847],"type":"Point"}
}