{
  "type": "Feature",
  "properties": {
    "iso:country":"DE",
    "sg:address":"Lorenz-Lassen-Str. 28",
    "sg:city":"Husum",
    "sg:phone":"+49 4841/61214",
    "sg:postcode":"25813",
    "sg:province":"Schleswig-Holstein",
    "wof:name":"Hans Hoffmann",
    "wof:placetype":"venue"
},
  "geometry": {"coordinates":[9.0542383194,54.4699821472],"type":"Point"}
}