{
  "type": "Feature",
  "properties": {
    "iso:country":"DE",
    "sg:address":"Humannstr.8-12",
    "sg:city":"Essen",
    "sg:phone":"+49 201/515618",
    "sg:postcode":"45276",
    "sg:province":"Nordrhein-Westfalen",
    "wof:name":"Dresdner Bank",
    "wof:placetype":"venue"
},
  "geometry": {"coordinates":[7.077108,51.448341],"type":"Point"}
}