{
  "type": "Feature",
  "properties": {
    "iso:country":"DE",
    "sg:address":"Landsknechtstr. 5",
    "sg:city":"Freiburg",
    "sg:phone":"+49 761/71325",
    "sg:postcode":"79102",
    "sg:province":"Baden-W\u00fcrttemberg",
    "wof:name":"Dieter Gersemann Rechtsanwalt",
    "wof:placetype":"venue"
},
  "geometry": {"coordinates":[7.8563079834,47.988067627],"type":"Point"}
}