{
  "type": "Feature",
  "properties": {
    "iso:country":"DE",
    "sg:address":"Lembergstr. 44",
    "sg:city":"T\u00fcbingen",
    "sg:phone":"+49 7071/73074",
    "sg:postcode":"72072",
    "sg:province":"Baden-W\u00fcrttemberg",
    "wof:name":"I. Koch",
    "wof:placetype":"venue"
},
  "geometry": {"coordinates":[9.0541086197,48.5058135986],"type":"Point"}
}