{
  "type": "Feature",
  "properties": {
    "iso:country":"DE",
    "sg:address":"Albert-Rupp-Str. 8 a",
    "sg:city":"Erlangen",
    "sg:phone":"+49 9131/30590",
    "sg:postcode":"91052",
    "sg:province":"Bayern",
    "wof:name":"Basel Dienstleistungen Gmbh",
    "wof:placetype":"venue"
},
  "geometry": {"coordinates":[11.0076293945,49.5825538635],"type":"Point"}
}