{
  "type": "Feature",
  "properties": {
    "iso:country":"DE",
    "sg:address":"Osnabr\u00fccker Str. 72",
    "sg:city":"Borgholzhausen",
    "sg:phone":"+49 5425/6676",
    "sg:postcode":"33829",
    "sg:province":"Nordrhein-Westfalen",
    "wof:name":"Werner Kassenbrock",
    "wof:placetype":"venue"
},
  "geometry": {"coordinates":[8.2374229431,52.0982284546],"type":"Point"}
}