{
  "type": "Feature",
  "properties": {
    "iso:country":"DE",
    "sg:address":"Weiherer Str. 11",
    "sg:city":"Forst",
    "sg:phone":"+49 7251/85433",
    "sg:postcode":"76694",
    "sg:province":"Baden-W\u00fcrttemberg",
    "wof:name":"Klavierbau Weschenfelder",
    "wof:placetype":"venue"
},
  "geometry": {"coordinates":[8.5833387375,49.1485481262],"type":"Point"}
}