{
  "type": "Feature",
  "properties": {
    "iso:country":"DE",
    "sg:address":"Bahnhofsiedlung 1a",
    "sg:city":"Untergriesbach",
    "sg:phone":"+49 8593/276",
    "sg:postcode":"94107",
    "sg:province":"Bayern",
    "wof:name":"Siegfried Seipelt Bauunternehmen Kg",
    "wof:placetype":"venue"
},
  "geometry": {"coordinates":[13.678087,48.57333],"type":"Point"}
}