{
  "type": "Feature",
  "properties": {
    "iso:country":"DE",
    "sg:address":"Breikamp 8",
    "sg:city":"Rosendahl",
    "sg:phone":"+49 2543/4641",
    "sg:postcode":"48720",
    "sg:province":"Nordrhein-Westfalen",
    "wof:name":"Lohnunternehmen Potthoff Gmbh",
    "wof:placetype":"venue"
},
  "geometry": {"coordinates":[7.282633,52.027283],"type":"Point"}
}