{
  "type": "Feature",
  "properties": {
    "iso:country":"DE",
    "sg:address":"Stromstr. 11-17",
    "sg:city":"Berlin",
    "sg:phone":"+49 30/3944042",
    "sg:postcode":"10551",
    "sg:province":"Berlin",
    "wof:name":"Getr\u00e4nke Werner",
    "wof:placetype":"venue"
},
  "geometry": {"coordinates":[13.343546,52.526859],"type":"Point"}
}