{
  "type": "Feature",
  "properties": {
    "iso:country":"DE",
    "sg:address":"Oberstr. 14",
    "sg:city":"Quierschied",
    "sg:phone":"+49 6897/62658",
    "sg:postcode":"66287",
    "sg:province":"Saarland",
    "wof:name":"Stefan M\u00fcller",
    "wof:placetype":"venue"
},
  "geometry": {"coordinates":[7.022999,49.306431],"type":"Point"}
}