{
  "type": "Feature",
  "properties": {
    "iso:country":"DE",
    "sg:address":"Ellerbergstr. 60",
    "sg:city":"Litzendorf",
    "sg:phone":"+49 9505/8505",
    "sg:postcode":"96123",
    "sg:province":"Bayern",
    "wof:name":"Ellerbergst\u00fcbla",
    "wof:placetype":"venue"
},
  "geometry": {"coordinates":[11.0746603012,49.9183807373],"type":"Point"}
}