{
  "type": "Feature",
  "properties": {
    "iso:country":"DE",
    "sg:address":"Olivaer Platz 17",
    "sg:city":"Berlin",
    "sg:phone":"+49 30/8814410",
    "sg:postcode":"10707",
    "sg:province":"Berlin",
    "wof:name":"Apotheke Am Olivaer Platz Sabine Olivar",
    "wof:placetype":"venue"
},
  "geometry": {"coordinates":[13.313449,52.500069],"type":"Point"}
}