{
  "type": "Feature",
  "properties": {
    "iso:country":"DE",
    "sg:address":"Hauptstr. 5",
    "sg:city":"Wilhelmsthal",
    "sg:phone":"+49 9260/289",
    "sg:postcode":"96352",
    "sg:province":"Bayern",
    "wof:name":"Hans Engelhardt",
    "wof:placetype":"venue"
},
  "geometry": {"coordinates":[11.383020401,50.3209762573],"type":"Point"}
}