{
  "type": "Feature",
  "properties": {
    "iso:country":"DE",
    "sg:address":"Kiefernweg 12",
    "sg:city":"Burbach",
    "sg:phone":"+49 2736/2480",
    "sg:postcode":"57299",
    "sg:province":"Nordrhein-Westfalen",
    "wof:name":"Interbaustoff Gmbh & Co. Kg",
    "wof:placetype":"venue"
},
  "geometry": {"coordinates":[8.1426563263,50.7206230164],"type":"Point"}
}