{
  "type": "Feature",
  "properties": {
    "iso:country":"DE",
    "sg:address":"Residenzstr 94",
    "sg:city":"Berlin",
    "sg:phone":"+49 30/49997156",
    "sg:postcode":"13409",
    "sg:province":"Berlin",
    "wof:name":"Rc-druck",
    "wof:placetype":"venue"
},
  "geometry": {"coordinates":[13.368938446,52.5607452393],"type":"Point"}
}