{
  "type": "Feature",
  "properties": {
    "iso:country":"DE",
    "sg:address":"ka",
    "sg:city":"R\u00f6dermark",
    "sg:postcode":"63322",
    "sg:province":"Hessen",
    "wof:name":"Pfeffer",
    "wof:placetype":"venue"
},
  "geometry": {"coordinates":[8.819645,49.981438],"type":"Point"}
}