{
  "type": "Feature",
  "properties": {
    "iso:country":"DE",
    "sg:address":"K\u00e4nerbergstr. 7 a",
    "sg:city":"Siegen",
    "sg:phone":"+49 271/43279",
    "sg:postcode":"57076",
    "sg:province":"Nordrhein-Westfalen",
    "wof:name":"Gastst\u00e4tte Zum Krombacher",
    "wof:placetype":"venue"
},
  "geometry": {"coordinates":[8.0343236923,50.8950500488],"type":"Point"}
}