{
  "type": "Feature",
  "properties": {
    "iso:country":"DE",
    "sg:address":"Steinweg 20",
    "sg:city":"Halle",
    "sg:postcode":"06110",
    "sg:province":"Sachsen-Anhalt",
    "wof:name":"Bieneck Leasing Ohg",
    "wof:placetype":"venue"
},
  "geometry": {"coordinates":[11.970495224,51.4753036499],"type":"Point"}
}