{
  "type": "Feature",
  "properties": {
    "iso:country":"DE",
    "sg:address":"Gerhart-Hauptmann-Str. 45 a",
    "sg:city":"Sch\u00f6now",
    "sg:phone":"+49 3338/759274",
    "sg:postcode":"16321",
    "sg:province":"Brandenburg",
    "wof:name":"Ceracom Keramik- Komponenten Gmbh",
    "wof:placetype":"venue"
},
  "geometry": {"coordinates":[13.543518,52.671394],"type":"Point"}
}