{
  "type": "Feature",
  "properties": {
    "iso:country":"DE",
    "sg:address":"Ostbahnstr. 20",
    "sg:city":"Sellin",
    "sg:phone":"+49 38303/920",
    "sg:postcode":"18586",
    "sg:province":"Mecklenburg-Vorpommern",
    "wof:name":"Ferienwohnanlage Und Hotel Garni",
    "wof:placetype":"venue"
},
  "geometry": {"coordinates":[13.6994447708,54.3733062744],"type":"Point"}
}