{
  "type": "Feature",
  "properties": {
    "iso:country":"DE",
    "sg:address":"Hauptstr. 10",
    "sg:city":"Eichholz-Dr\u00f6\u00dfig",
    "sg:phone":"+49 3531/63030",
    "sg:postcode":"03238",
    "sg:province":"Brandenburg",
    "wof:name":"Wolfgang Magister",
    "wof:placetype":"venue"
},
  "geometry": {"coordinates":[13.70392,51.604351],"type":"Point"}
}