{
  "type": "Feature",
  "properties": {
    "iso:country":"DE",
    "sg:address":"Im Mediapark 5b",
    "sg:city":"K\u00f6ln",
    "sg:phone":"+49 221/4543120",
    "sg:postcode":"50670",
    "sg:province":"Nordrhein-Westfalen",
    "wof:name":"Prefix Gmbh",
    "wof:placetype":"venue"
},
  "geometry": {"coordinates":[6.945016,50.948708],"type":"Point"}
}