{
  "type": "Feature",
  "properties": {
    "iso:country":"DE",
    "sg:address":"Am Ningesberg 10",
    "sg:city":"Goldbach",
    "sg:phone":"+49 6021/53044",
    "sg:postcode":"63773",
    "sg:province":"Bayern",
    "wof:name":"Atc Textil Gmbh",
    "wof:placetype":"venue"
},
  "geometry": {"coordinates":[9.1710796356,49.9973297119],"type":"Point"}
}