{
  "type": "Feature",
  "properties": {
    "iso:country":"DE",
    "sg:address":"Eichenau 3",
    "sg:city":"G\u00f6ssenheim",
    "sg:phone":"+49 9358/200",
    "sg:postcode":"97780",
    "sg:province":"Bayern",
    "wof:name":"Alfred Matterstock",
    "wof:placetype":"venue"
},
  "geometry": {"coordinates":[9.787092,50.015694],"type":"Point"}
}