{
  "type": "Feature",
  "properties": {
    "iso:country":"DE",
    "sg:address":"Zollnerstr. 197 a",
    "sg:city":"Bamberg",
    "sg:phone":"+49 951/9370300",
    "sg:postcode":"96052",
    "sg:province":"Bayern",
    "wof:name":"R & B Liquors E. K.",
    "wof:placetype":"venue"
},
  "geometry": {"coordinates":[10.9211826324,49.9079284668],"type":"Point"}
}