{
  "type": "Feature",
  "properties": {
    "iso:country":"DE",
    "sg:address":"Schweinfurter Str. 2",
    "sg:city":"Regensburg",
    "sg:phone":"+49 941/84394",
    "sg:postcode":"93059",
    "sg:province":"Bayern",
    "wof:name":"E. G\u00f6tz",
    "wof:placetype":"venue"
},
  "geometry": {"coordinates":[12.0854997635,49.0291023254],"type":"Point"}
}