{
  "type": "Feature",
  "properties": {
    "iso:country":"DE",
    "sg:address":"Norderstr. 29",
    "sg:city":"Albersdorf",
    "sg:phone":"+49 4835/7268",
    "sg:postcode":"25767",
    "sg:province":"Schleswig-Holstein",
    "wof:name":"Airlines",
    "wof:placetype":"venue"
},
  "geometry": {"coordinates":[9.2862243652,54.149646759],"type":"Point"}
}