{
  "type": "Feature",
  "properties": {
    "iso:country":"DE",
    "sg:address":"Hasenbergsteige 5",
    "sg:city":"Stuttgart",
    "sg:phone":"+49 711/610541",
    "sg:postcode":"70178",
    "sg:province":"Baden-W\u00fcrttemberg",
    "wof:name":"Wilkhahn Wilkening & Hahne Gmbh & Co.",
    "wof:placetype":"venue"
},
  "geometry": {"coordinates":[9.162564,48.768597],"type":"Point"}
}