{
  "type": "Feature",
  "properties": {
    "iso:country":"DE",
    "sg:address":"Artilleriestr. 6",
    "sg:city":"Verden",
    "sg:postcode":"27283",
    "sg:province":"Niedersachsen",
    "wof:name":"Liekedeeler - Gmbh",
    "wof:placetype":"venue"
},
  "geometry": {"coordinates":[9.2465543747,52.9266738892],"type":"Point"}
}