{
  "type": "Feature",
  "properties": {
    "iso:country":"DE",
    "sg:address":"Schwitter Weg 17",
    "sg:city":"Menden",
    "sg:phone":"+49 2373/93770",
    "sg:postcode":"58706",
    "sg:province":"Nordrhein-Westfalen",
    "wof:name":"Adolf Schl\u00fcnder",
    "wof:placetype":"venue"
},
  "geometry": {"coordinates":[7.7956151962,51.4406967163],"type":"Point"}
}