{
  "type": "Feature",
  "properties": {
    "iso:country":"DE",
    "sg:address":"Damaschkestr. 10",
    "sg:city":"Aue",
    "sg:phone":"+49 3771/23727",
    "sg:postcode":"08280",
    "sg:province":"Sachsen",
    "wof:name":"Harry Tr\u00f6ger",
    "wof:placetype":"venue"
},
  "geometry": {"coordinates":[12.711027,50.582161],"type":"Point"}
}