{
  "type": "Feature",
  "properties": {
    "iso:country":"DE",
    "sg:address":"Auf dem Unteren Kreuzst\u00fcck 10",
    "sg:city":"Oppurg",
    "sg:phone":"+49 3647/46030",
    "sg:postcode":"07381",
    "sg:province":"Th\u00fcringen",
    "wof:name":"Osk-kiefer Gmbh Oberfl\u00e4chen- & Strahltechnik",
    "wof:placetype":"venue"
},
  "geometry": {"coordinates":[11.605529,50.699562],"type":"Point"}
}