{
  "type": "Feature",
  "properties": {
    "iso:country":"DE",
    "sg:address":"Luttersche Str. 8",
    "sg:city":"Beedenbostel",
    "sg:phone":"+49 5145/333",
    "sg:postcode":"29355",
    "sg:province":"Niedersachsen",
    "wof:name":"Karl Kremling",
    "wof:placetype":"venue"
},
  "geometry": {"coordinates":[10.260529,52.645233],"type":"Point"}
}