{
  "type": "Feature",
  "properties": {
    "iso:country":"DE",
    "sg:address":"Bahnhofstr.34a",
    "sg:city":"Lindhorst",
    "sg:phone":"+49 5725/5844",
    "sg:postcode":"31698",
    "sg:province":"Niedersachsen",
    "wof:name":"Immobilien,gewerbeimmobilien,kapitalanlage",
    "wof:placetype":"venue"
},
  "geometry": {"coordinates":[9.284518,52.357712],"type":"Point"}
}