{
  "type": "Feature",
  "properties": {
    "iso:country":"DE",
    "sg:address":"Kirchdorfer Str. 1",
    "sg:city":"Hamburg",
    "sg:phone":"+49 40/76910170",
    "sg:postcode":"21109",
    "sg:province":"Hamburg",
    "wof:name":"Kaya Estrich-verarbeitung Gmbh",
    "wof:placetype":"venue"
},
  "geometry": {"coordinates":[10.0093994141,53.4849090576],"type":"Point"}
}