{
  "type": "Feature",
  "properties": {
    "iso:country":"DE",
    "sg:address":"Ziegelstr. 12-16",
    "sg:city":"Lastrup",
    "sg:phone":"+49 4472/458",
    "sg:postcode":"49688",
    "sg:province":"Niedersachsen",
    "wof:name":"Erwin Albers Verwaltungs-gmbh",
    "wof:placetype":"venue"
},
  "geometry": {"coordinates":[7.9042539597,52.8037414551],"type":"Point"}
}