{
  "type": "Feature",
  "properties": {
    "iso:country":"DE",
    "sg:address":"Breitscheidstr. 108",
    "sg:city":"Plauen",
    "sg:phone":"+49 3741/522121",
    "sg:postcode":"08525",
    "sg:province":"Sachsen",
    "wof:name":"K.-g. Kater",
    "wof:placetype":"venue"
},
  "geometry": {"coordinates":[12.14179,50.509129],"type":"Point"}
}