{
  "type": "Feature",
  "properties": {
    "iso:country":"DE",
    "sg:address":"M\u00fchlenfeld 17",
    "sg:city":"Bornheim",
    "sg:phone":"+49 2227/3744",
    "sg:postcode":"53332",
    "sg:province":"Nordrhein-Westfalen",
    "wof:name":"A. Schuhmann",
    "wof:placetype":"venue"
},
  "geometry": {"coordinates":[6.9841351509,50.7619400024],"type":"Point"}
}