{
  "type": "Feature",
  "properties": {
    "iso:country":"DE",
    "sg:address":"Georg-Kohl-Str. 6",
    "sg:city":"Brackenheim",
    "sg:phone":"+49 7135/98050",
    "sg:postcode":"74336",
    "sg:province":"Baden-W\u00fcrttemberg",
    "wof:name":"Pbs Wohnbau Gmbh",
    "wof:placetype":"venue"
},
  "geometry": {"coordinates":[9.066776,49.074654],"type":"Point"}
}