{
  "type": "Feature",
  "properties": {
    "iso:country":"DE",
    "sg:address":"Justus-Liebig-Str. 2",
    "sg:city":"K\u00fcnzell",
    "sg:phone":"+49 661/93920",
    "sg:postcode":"36093",
    "sg:province":"Hessen",
    "wof:name":"Css Computer Software Studio Gmbh",
    "wof:placetype":"venue"
},
  "geometry": {"coordinates":[9.7147827148,50.5440673828],"type":"Point"}
}