{
  "type": "Feature",
  "properties": {
    "iso:country":"DE",
    "sg:address":"Hedderichstr. 102",
    "sg:city":"Frankfurt",
    "sg:phone":"+49 69/626239",
    "sg:postcode":"60596",
    "sg:province":"Hessen",
    "wof:name":"H. Stumpe",
    "wof:placetype":"venue"
},
  "geometry": {"coordinates":[8.682061,50.098549],"type":"Point"}
}