{
  "type": "Feature",
  "properties": {
    "iso:country":"DE",
    "sg:address":"Friedrich-Ebert-Str.",
    "sg:city":"Solingen",
    "sg:postcode":"42719",
    "sg:province":"Nordrhein-Westfalen",
    "wof:name":"Kaisers Markt",
    "wof:placetype":"venue"
},
  "geometry": {"coordinates":[7.053355217,51.186706543],"type":"Point"}
}