{
  "type": "Feature",
  "properties": {
    "iso:country":"DE",
    "sg:address":"Neumarkt 41",
    "sg:city":"K\u00f6ln",
    "sg:phone":"+49 221/230008",
    "sg:postcode":"50667",
    "sg:province":"Nordrhein-Westfalen",
    "wof:name":"Honorarkonsulat Von Costa Rica",
    "wof:placetype":"venue"
},
  "geometry": {"coordinates":[6.9465689659,50.9355659485],"type":"Point"}
}