{
  "type": "Feature",
  "properties": {
    "iso:country":"DE",
    "sg:address":"Wilhelm-Baum-Weg",
    "sg:city":"G\u00f6ttingen",
    "sg:postcode":"37077",
    "sg:province":"Niedersachsen",
    "wof:name":"Schlaf Innovationen Systeme Gmbh",
    "wof:placetype":"venue"
},
  "geometry": {"coordinates":[9.9319801331,51.5746688843],"type":"Point"}
}