{
  "type": "Feature",
  "properties": {
    "iso:country":"DE",
    "sg:address":"Berliner Str. 55",
    "sg:city":"Weilerswist",
    "sg:phone":"+49 2254/7277",
    "sg:postcode":"53919",
    "sg:province":"Nordrhein-Westfalen",
    "wof:name":"Heinz Becker",
    "wof:placetype":"venue"
},
  "geometry": {"coordinates":[6.840328,50.752934],"type":"Point"}
}