{
  "type": "Feature",
  "properties": {
    "iso:country":"DE",
    "sg:address":"Austr. 4",
    "sg:city":"Waldenbuch",
    "sg:phone":"+49 7157/880364",
    "sg:postcode":"71111",
    "sg:province":"Baden-W\u00fcrttemberg",
    "wof:name":"Gasthof Liebenau",
    "wof:placetype":"venue"
},
  "geometry": {"coordinates":[9.1482925415,48.63646698],"type":"Point"}
}