{
  "type": "Feature",
  "properties": {
    "iso:country":"DE",
    "sg:address":"Jacques-Offenbach-Str. 14 b",
    "sg:city":"Offenbach",
    "sg:phone":"+49 69/839910",
    "sg:postcode":"63069",
    "sg:province":"Hessen",
    "wof:name":"Karlheinz Born Steuerberater",
    "wof:placetype":"venue"
},
  "geometry": {"coordinates":[8.7619514465,50.0864830017],"type":"Point"}
}