{
  "type": "Feature",
  "properties": {
    "iso:country":"DE",
    "sg:address":"Stettiner Chaussee 19",
    "sg:city":"Penkun",
    "sg:phone":"+49 39751/60509",
    "sg:postcode":"17328",
    "sg:province":"Mecklenburg-Vorpommern",
    "wof:name":"Kutz-schierbaum Ohg",
    "wof:placetype":"venue"
},
  "geometry": {"coordinates":[14.245169,53.303783],"type":"Point"}
}