{
  "type": "Feature",
  "properties": {
    "iso:country":"DE",
    "sg:address":"Ettenhueberstr. 1",
    "sg:city":"M\u00fcnchen",
    "sg:phone":"+49 89/582169",
    "sg:postcode":"80687",
    "sg:province":"Bayern",
    "wof:name":"Turan Boztepe",
    "wof:placetype":"venue"
},
  "geometry": {"coordinates":[11.4908361435,48.1416397095],"type":"Point"}
}