{
  "type": "Feature",
  "properties": {
    "iso:country":"DE",
    "sg:address":"Kulmbacher Str. 1",
    "sg:city":"M\u00fcnchberg",
    "sg:phone":"+49 9251/1363",
    "sg:postcode":"95213",
    "sg:province":"Bayern",
    "wof:name":"Adolf Schadt",
    "wof:placetype":"venue"
},
  "geometry": {"coordinates":[11.7886104584,50.1913909912],"type":"Point"}
}