{
  "type": "Feature",
  "properties": {
    "iso:country":"DE",
    "sg:address":"Hafenstr. 27",
    "sg:city":"Langeoog",
    "sg:phone":"+49 4972/6156",
    "sg:postcode":"26465",
    "sg:province":"Niedersachsen",
    "wof:name":"I. Und H. Wilken",
    "wof:placetype":"venue"
},
  "geometry": {"coordinates":[7.494973,53.732098],"type":"Point"}
}