{
  "type": "Feature",
  "properties": {
    "iso:country":"DE",
    "sg:address":"Isarstr. 14",
    "sg:city":"Niederaichbach",
    "sg:phone":"+49 8702/2349",
    "sg:postcode":"84100",
    "sg:province":"Bayern",
    "wof:name":"Kath. Pfarramt St. Josef",
    "wof:placetype":"venue"
},
  "geometry": {"coordinates":[12.3167600632,48.6074295044],"type":"Point"}
}