{
  "type": "Feature",
  "properties": {
    "iso:country":"DE",
    "sg:address":"Graf-Zeppelin-Str.1",
    "sg:city":"K\u00f6ln",
    "sg:postcode":"51147",
    "sg:province":"Nordrhein-Westfalen",
    "wof:name":"Cw-consulting",
    "wof:placetype":"venue"
},
  "geometry": {"coordinates":[7.096692,50.881573],"type":"Point"}
}