{
  "type": "Feature",
  "properties": {
    "iso:country":"DE",
    "sg:address":"Veilchenweg 8",
    "sg:city":"Remshalden",
    "sg:phone":"+49 7151/73631",
    "sg:postcode":"73630",
    "sg:province":"Baden-W\u00fcrttemberg",
    "wof:name":"Sigrun Fischer Heilpraktiker",
    "wof:placetype":"venue"
},
  "geometry": {"coordinates":[9.4205694199,48.8191452026],"type":"Point"}
}