{
  "type": "Feature",
  "properties": {
    "iso:country":"DE",
    "sg:address":"Liebigstr. 1",
    "sg:city":"Kaiserslautern",
    "sg:phone":"+49 631/56096",
    "sg:postcode":"67661",
    "sg:province":"Rheinland-Pfalz",
    "wof:name":"Abc-autoglas Kaiserslautern Handels- Und Serviceges. Mbh",
    "wof:placetype":"venue"
},
  "geometry": {"coordinates":[7.6687140465,49.4336662292],"type":"Point"}
}