{
  "type": "Feature",
  "properties": {
    "iso:country":"DE",
    "sg:address":"Georg-Rinser-Weg 3",
    "sg:city":"Kirchansch\u00f6ring",
    "sg:phone":"+49 8685/222",
    "sg:postcode":"83417",
    "sg:province":"Bayern",
    "wof:name":"Kath. Pfarramt St. Michael",
    "wof:placetype":"venue"
},
  "geometry": {"coordinates":[12.8345775604,47.9519844055],"type":"Point"}
}