{
  "type": "Feature",
  "properties": {
    "iso:country":"DE",
    "sg:address":"Stromeyersdorfstr. 12",
    "sg:city":"Konstanz",
    "sg:phone":"+49 7531/81780",
    "sg:postcode":"78467",
    "sg:province":"Baden-W\u00fcrttemberg",
    "wof:name":"Motan Holding Gmbh",
    "wof:placetype":"venue"
},
  "geometry": {"coordinates":[9.157455,47.670937],"type":"Point"}
}