{
  "type": "Feature",
  "properties": {
    "iso:country":"DE",
    "sg:address":"Am Martinsgrund",
    "sg:city":"Gera",
    "sg:phone":"+49 365/810242",
    "sg:postcode":"07548",
    "sg:province":"Th\u00fcringen",
    "wof:name":"Waldsch\u00e4nke",
    "wof:placetype":"venue"
},
  "geometry": {"coordinates":[12.0658102036,50.8654251099],"type":"Point"}
}