{
  "type": "Feature",
  "properties": {
    "iso:country":"DE",
    "sg:address":"Wilhelmstr. 4",
    "sg:city":"Usingen",
    "sg:phone":"+49 6081/14000",
    "sg:postcode":"61250",
    "sg:province":"Hessen",
    "wof:name":"Gisela Steinmetz",
    "wof:placetype":"venue"
},
  "geometry": {"coordinates":[8.5356636047,50.3344764709],"type":"Point"}
}