{
  "type": "Feature",
  "properties": {
    "iso:country":"DE",
    "sg:address":"Gr\u00fcneburgweg 35",
    "sg:city":"Frankfurt",
    "sg:phone":"+49 69/174036",
    "sg:postcode":"60322",
    "sg:province":"Hessen",
    "wof:name":"Van Den Broek",
    "wof:placetype":"venue"
},
  "geometry": {"coordinates":[8.671317,50.121147],"type":"Point"}
}