{
  "type": "Feature",
  "properties": {
    "iso:country":"DE",
    "sg:address":"Regentenstr.9",
    "sg:city":"Koeln",
    "sg:phone":"+49 177 3348628",
    "sg:postcode":"51063",
    "sg:province":"Nordrhein-Westfalen",
    "wof:name":"Der Pc Doktor",
    "wof:placetype":"venue"
},
  "geometry": {"coordinates":[7.002082,50.963757],"type":"Point"}
}