{
  "type": "Feature",
  "properties": {
    "iso:country":"DE",
    "sg:address":"Quickbaumweg 3",
    "sg:city":"L\u00fcneburg",
    "sg:phone":"+49 4131/65779",
    "sg:postcode":"21339",
    "sg:province":"Niedersachsen",
    "wof:name":"R. Harder",
    "wof:placetype":"venue"
},
  "geometry": {"coordinates":[10.387778,53.271736],"type":"Point"}
}