{
  "type": "Feature",
  "properties": {
    "iso:country":"DE",
    "sg:address":"Brokeloher Str. 4",
    "sg:city":"Landesbergen",
    "sg:phone":"+49 5025/98000",
    "sg:postcode":"31628",
    "sg:province":"Niedersachsen",
    "wof:name":"Domo Besmer Gmbh",
    "wof:placetype":"venue"
},
  "geometry": {"coordinates":[9.1368980408,52.5590057373],"type":"Point"}
}