{
  "type": "Feature",
  "properties": {
    "iso:country":"DE",
    "sg:address":"Hinter den Kirschkaten 61",
    "sg:city":"L\u00fcbeck",
    "sg:phone":"+49 451/583700",
    "sg:postcode":"23560",
    "sg:province":"Schleswig-Holstein",
    "wof:name":"Johann Karstens Bauunternehmung Gmbh",
    "wof:placetype":"venue"
},
  "geometry": {"coordinates":[10.66594,53.842052],"type":"Point"}
}