{
  "type": "Feature",
  "properties": {
    "iso:country":"DE",
    "sg:address":"Horst 5",
    "sg:city":"Schneverdingen",
    "sg:phone":"+49 4265/460",
    "sg:postcode":"29640",
    "sg:province":"Niedersachsen",
    "wof:name":"Ernst Eggergl\u00fcss",
    "wof:placetype":"venue"
},
  "geometry": {"coordinates":[9.706711,53.200603],"type":"Point"}
}