{
  "type": "Feature",
  "properties": {
    "iso:country":"DE",
    "sg:address":"Bahnweg 13",
    "sg:city":"Homburg",
    "sg:phone":"+49 6841/150735",
    "sg:postcode":"66424",
    "sg:province":"Saarland",
    "wof:name":"Reinhard Forster",
    "wof:placetype":"venue"
},
  "geometry": {"coordinates":[7.365175,49.34922],"type":"Point"}
}