{
  "type": "Feature",
  "properties": {
    "iso:country":"DE",
    "sg:address":"Rudolf-Diesel-Str. 13-15",
    "sg:city":"Linkenheim-Hochstetten",
    "sg:phone":"+49 7247/7788",
    "sg:postcode":"76351",
    "sg:province":"Baden-W\u00fcrttemberg",
    "wof:name":"Dent Einrichtungen Und Neuheiten F. Zahnarztpraxen",
    "wof:placetype":"venue"
},
  "geometry": {"coordinates":[8.413079,49.128525],"type":"Point"}
}