{
  "type": "Feature",
  "properties": {
    "iso:country":"DE",
    "sg:address":"An der Schalwiese 16",
    "sg:city":"Bochum",
    "sg:phone":"+49 234/309429",
    "sg:postcode":"44789",
    "sg:province":"Nordrhein-Westfalen",
    "wof:name":"Ulrich Winter Architekt",
    "wof:placetype":"venue"
},
  "geometry": {"coordinates":[7.229506,51.471611],"type":"Point"}
}