{
  "type": "Feature",
  "properties": {
    "iso:country":"DE",
    "sg:address":"Am Gebrannten 35a",
    "sg:city":"Bochum",
    "sg:phone":"+49 234/791664",
    "sg:postcode":"44797",
    "sg:province":"Nordrhein-Westfalen",
    "wof:name":"Elektro G\u00fcnter Racherb\u00e4umer",
    "wof:placetype":"venue"
},
  "geometry": {"coordinates":[7.249464035,51.4331016541],"type":"Point"}
}