{
  "type": "Feature",
  "properties": {
    "iso:country":"DE",
    "sg:address":"Regentstr. 2",
    "sg:city":"Ellerbek",
    "sg:phone":"+49 4101/38200",
    "sg:postcode":"25474",
    "sg:province":"Schleswig-Holstein",
    "wof:name":"Wolf Containerverleih Gmbh",
    "wof:placetype":"venue"
},
  "geometry": {"coordinates":[9.8893632889,53.6423797607],"type":"Point"}
}