{
  "type": "Feature",
  "properties": {
    "iso:country":"DE",
    "sg:address":"Schmidener Str. 114",
    "sg:city":"Stuttgart",
    "sg:phone":"+49 711/557778",
    "sg:postcode":"70374",
    "sg:province":"Baden-W\u00fcrttemberg",
    "wof:name":"De Ananga Heilpraktiker",
    "wof:placetype":"venue"
},
  "geometry": {"coordinates":[9.2288160324,48.8122673035],"type":"Point"}
}