{
  "type": "Feature",
  "properties": {
    "iso:country":"DE",
    "sg:address":"Carl-Benz-Str. 4",
    "sg:city":"Renchen",
    "sg:phone":"+49 7843/992100",
    "sg:postcode":"77871",
    "sg:province":"Baden-W\u00fcrttemberg",
    "wof:name":"Mailbase Direct-marketing Gmbh",
    "wof:placetype":"venue"
},
  "geometry": {"coordinates":[8.0052604675,48.5811004639],"type":"Point"}
}