{
  "type": "Feature",
  "properties": {
    "iso:country":"DE",
    "sg:address":"Berliner Allee 25",
    "sg:city":"Norderstedt",
    "sg:phone":"+49 40/5232255",
    "sg:postcode":"22850",
    "sg:province":"Schleswig-Holstein",
    "wof:name":"Alfred Birk",
    "wof:placetype":"venue"
},
  "geometry": {"coordinates":[9.984308,53.684395],"type":"Point"}
}