{
  "type": "Feature",
  "properties": {
    "iso:country":"DE",
    "sg:address":"Altes Dorf 6",
    "sg:city":"Schkeuditz",
    "sg:phone":"+49 34204/64467",
    "sg:postcode":"04435",
    "sg:province":"Sachsen",
    "wof:name":"Flisen Ziegenhagen",
    "wof:placetype":"venue"
},
  "geometry": {"coordinates":[12.2456493378,51.3881225586],"type":"Point"}
}