{
  "type": "Feature",
  "properties": {
    "iso:country":"DE",
    "sg:address":"Lilienthalstr. 5",
    "sg:city":"Kassel",
    "sg:phone":"+49 561/9882575",
    "sg:postcode":"34123",
    "sg:province":"Hessen",
    "wof:name":"Andreas Stein",
    "wof:placetype":"venue"
},
  "geometry": {"coordinates":[9.5189199448,51.3023986816],"type":"Point"}
}