{
  "type": "Feature",
  "properties": {
    "iso:country":"DE",
    "sg:address":"Kleinleipischer Str. 9",
    "sg:city":"Lauchhammer",
    "sg:phone":"+49 3574/2188",
    "sg:postcode":"01979",
    "sg:province":"Brandenburg",
    "wof:name":"Roland Leisker",
    "wof:placetype":"venue"
},
  "geometry": {"coordinates":[13.758693,51.496086],"type":"Point"}
}