{
  "type": "Feature",
  "properties": {
    "iso:country":"DE",
    "sg:address":"Siemensstr. 9-11",
    "sg:city":"Ratingen",
    "sg:phone":"+49 2102/66033",
    "sg:postcode":"40885",
    "sg:province":"Nordrhein-Westfalen",
    "wof:name":"Divestore-mailorder & Service Gmbh",
    "wof:placetype":"venue"
},
  "geometry": {"coordinates":[6.8253798485,51.3485603333],"type":"Point"}
}