{
  "type": "Feature",
  "properties": {
    "iso:country":"DE",
    "sg:address":"Remigiusstr. 12",
    "sg:city":"Borken",
    "sg:phone":"+49 2861/2109",
    "sg:postcode":"46325",
    "sg:province":"Nordrhein-Westfalen",
    "wof:name":"Restaurant Artemis",
    "wof:placetype":"venue"
},
  "geometry": {"coordinates":[6.859817028,51.8437728882],"type":"Point"}
}