{
  "type": "Feature",
  "properties": {
    "iso:country":"DE",
    "sg:address":"Gro\u00dfvoggenhof 42",
    "sg:city":"Burgthann",
    "sg:phone":"+49 9187/5137",
    "sg:postcode":"90559",
    "sg:province":"Bayern",
    "wof:name":"F. Stadler",
    "wof:placetype":"venue"
},
  "geometry": {"coordinates":[11.315323,49.351398],"type":"Point"}
}