{
  "type": "Feature",
  "properties": {
    "iso:country":"DE",
    "sg:address":"Ostlandstr. 24",
    "sg:city":"Aglasterhausen",
    "sg:phone":"+49 6262/915124",
    "sg:postcode":"74858",
    "sg:province":"Baden-W\u00fcrttemberg",
    "wof:name":"Usp Marketing & More Gmbh",
    "wof:placetype":"venue"
},
  "geometry": {"coordinates":[8.992524147,49.3553543091],"type":"Point"}
}