{
  "type": "Feature",
  "properties": {
    "iso:country":"DE",
    "sg:address":"Hubertush\u00f6he 19",
    "sg:city":"\u00dcrzig",
    "sg:postcode":"54539",
    "sg:province":"Rheinland-Pfalz",
    "wof:name":"H. Und U. M\u00fcllers",
    "wof:placetype":"venue"
},
  "geometry": {"coordinates":[7.00586,49.985264],"type":"Point"}
}