{
  "type": "Feature",
  "properties": {
    "iso:country":"DE",
    "sg:address":"Isargestade 739",
    "sg:city":"Landshut",
    "sg:phone":"+49 871/28588",
    "sg:postcode":"84028",
    "sg:province":"Bayern",
    "wof:name":"Gasthaus Zur Schleuse",
    "wof:placetype":"venue"
},
  "geometry": {"coordinates":[12.1529350281,48.5401763916],"type":"Point"}
}