{
  "type": "Feature",
  "properties": {
    "iso:country":"DE",
    "sg:address":"H\u00f6henweg 151",
    "sg:city":"Saarbr\u00fccken",
    "sg:phone":"+49 681/894207",
    "sg:postcode":"66133",
    "sg:province":"Saarland",
    "wof:name":"Werner Philipp",
    "wof:placetype":"venue"
},
  "geometry": {"coordinates":[7.059996,49.232075],"type":"Point"}
}