{
  "type": "Feature",
  "properties": {
    "iso:country":"DE",
    "sg:address":"Dorfstr. 11",
    "sg:city":"Roden",
    "sg:phone":"+49 9396/1210",
    "sg:postcode":"97849",
    "sg:province":"Bayern",
    "wof:name":"Walter Lang",
    "wof:placetype":"venue"
},
  "geometry": {"coordinates":[9.620146,49.918118],"type":"Point"}
}