{
  "type": "Feature",
  "properties": {
    "iso:country":"DE",
    "sg:address":"Klosterwall 4-6",
    "sg:city":"Hamburg",
    "sg:phone":"+49 40/335399",
    "sg:postcode":"20095",
    "sg:province":"Hamburg",
    "wof:name":"Klaus Steger",
    "wof:placetype":"venue"
},
  "geometry": {"coordinates":[10.0056324005,53.5488586426],"type":"Point"}
}