{
  "type": "Feature",
  "properties": {
    "iso:country":"DE",
    "sg:address":"Industriehafen-S\u00fcd",
    "sg:city":"Papenburg",
    "sg:postcode":"26871",
    "sg:province":"Niedersachsen",
    "wof:name":"Hbg Hotelbesitz- Beteiligungs Gmbh",
    "wof:placetype":"venue"
},
  "geometry": {"coordinates":[7.373077,53.091846],"type":"Point"}
}