{
  "type": "Feature",
  "properties": {
    "iso:country":"DE",
    "sg:address":"Ehrenbergstr. 10",
    "sg:city":"Ilmenau",
    "sg:phone":"+49 3677/844639",
    "sg:postcode":"98693",
    "sg:province":"Th\u00fcringen",
    "wof:name":"Dr. Med. Burga Macholdt \u00c4rztin F\u00fcr Allgemeinmedizin",
    "wof:placetype":"venue"
},
  "geometry": {"coordinates":[10.9258766174,50.6832962036],"type":"Point"}
}