{
  "type": "Feature",
  "properties": {
    "iso:country":"DE",
    "sg:address":"Amsterdamer Stra\u00dfe 21",
    "sg:city":"Berlin",
    "sg:phone":"+49 30",
    "sg:postcode":"13347",
    "sg:province":"Berlin",
    "wof:name":"Abw Beratende Ingenieure",
    "wof:placetype":"venue"
},
  "geometry": {"coordinates":[13.3553333282,52.5504264832],"type":"Point"}
}