{
  "type": "Feature",
  "properties": {
    "iso:country":"DE",
    "sg:address":"Eythstr. 31",
    "sg:city":"Halle",
    "sg:phone":"+49 345/5232908",
    "sg:postcode":"06118",
    "sg:province":"Sachsen-Anhalt",
    "wof:name":"Dr. Med. Wolfgang Schubert",
    "wof:placetype":"venue"
},
  "geometry": {"coordinates":[11.980567,51.502609],"type":"Point"}
}