{
  "type": "Feature",
  "properties": {
    "iso:country":"DE",
    "sg:address":"Ludwig-Jahn-Str. 12",
    "sg:city":"Esslingen",
    "sg:phone":"+49 711/371309",
    "sg:postcode":"73732",
    "sg:province":"Baden-W\u00fcrttemberg",
    "wof:name":"Siegfried M\u00fchleisen Architekt",
    "wof:placetype":"venue"
},
  "geometry": {"coordinates":[9.336491,48.740749],"type":"Point"}
}