{
  "type": "Feature",
  "properties": {
    "iso:country":"DE",
    "sg:address":"Elly-Ney-Str. 4",
    "sg:city":"Tutzing",
    "sg:postcode":"82327",
    "sg:province":"Bayern",
    "wof:name":"Kf Informatik Gmbh",
    "wof:placetype":"venue"
},
  "geometry": {"coordinates":[11.2822561264,47.9175300598],"type":"Point"}
}