{
  "type": "Feature",
  "properties": {
    "iso:country":"DE",
    "sg:address":"Marienstr. 3-5",
    "sg:city":"Neu-Ulm",
    "sg:phone":"+49 731/723141",
    "sg:postcode":"89231",
    "sg:province":"Bayern",
    "wof:name":"Id Industrie-service Gmbh",
    "wof:placetype":"venue"
},
  "geometry": {"coordinates":[9.99647,48.395378],"type":"Point"}
}