{
  "type": "Feature",
  "properties": {
    "iso:country":"DE",
    "sg:address":"Maurerweg 12",
    "sg:city":"Markt Schwaben",
    "sg:phone":"+49 89/72430543",
    "sg:postcode":"85570",
    "sg:province":"Bayern",
    "wof:name":"Objektwerk Edv-beratung E. K.",
    "wof:placetype":"venue"
},
  "geometry": {"coordinates":[11.8661317825,48.1881561279],"type":"Point"}
}