{
  "type": "Feature",
  "properties": {
    "iso:country":"DE",
    "sg:address":"Am Leitzelbach 24",
    "sg:city":"Sinsheim",
    "sg:phone":"+49 7261/92470",
    "sg:postcode":"74889",
    "sg:province":"Baden-W\u00fcrttemberg",
    "wof:name":"Pakufol Kunststoff- Produkte Gmbh",
    "wof:placetype":"venue"
},
  "geometry": {"coordinates":[8.845663,49.250504],"type":"Point"}
}