{
  "type": "Feature",
  "properties": {
    "iso:country":"DE",
    "sg:address":"Ramsried 24",
    "sg:city":"K\u00f6tzting",
    "sg:phone":"+49 9941/2916",
    "sg:postcode":"93444",
    "sg:province":"Bayern",
    "wof:name":"Lothar Neppl",
    "wof:placetype":"venue"
},
  "geometry": {"coordinates":[12.8423,49.213772],"type":"Point"}
}