{
  "type": "Feature",
  "properties": {
    "iso:country":"DE",
    "sg:address":"Toft 6",
    "sg:city":"Maasb\u00fcll",
    "sg:postcode":"24975",
    "sg:province":"Schleswig-Holstein",
    "wof:name":"Hbm Bau Gmbh",
    "wof:placetype":"venue"
},
  "geometry": {"coordinates":[9.522832,54.776817],"type":"Point"}
}