{
  "type": "Feature",
  "properties": {
    "iso:country":"DE",
    "sg:address":"Beverner Str. 24",
    "sg:city":"Essen",
    "sg:phone":"+49 5434/684",
    "sg:postcode":"49632",
    "sg:province":"Niedersachsen",
    "wof:name":"Josef Ostendorf",
    "wof:placetype":"venue"
},
  "geometry": {"coordinates":[7.995456,52.725018],"type":"Point"}
}