{
  "type": "Feature",
  "properties": {
    "iso:country":"DE",
    "sg:address":"Altenstadter Str. 2",
    "sg:city":"Schongau",
    "sg:phone":"+49 8861/93793",
    "sg:postcode":"86956",
    "sg:province":"Bayern",
    "wof:name":"Spielcafe",
    "wof:placetype":"venue"
},
  "geometry": {"coordinates":[10.894217,47.815269],"type":"Point"}
}