{
  "type": "Feature",
  "properties": {
    "iso:country":"DE",
    "sg:address":"Mintropstr. 10",
    "sg:city":"D\u00fcsseldorf",
    "sg:phone":"+49 211/379294",
    "sg:postcode":"40215",
    "sg:province":"Nordrhein-Westfalen",
    "wof:name":"Wafabank",
    "wof:placetype":"venue"
},
  "geometry": {"coordinates":[6.788812,51.218739],"type":"Point"}
}