{
  "type": "Feature",
  "properties": {
    "iso:country":"DE",
    "sg:address":"Rudelallee",
    "sg:city":"Bickenbach",
    "sg:phone":"+49 6257",
    "sg:postcode":"64404",
    "sg:province":"Hessen",
    "wof:name":"Texxxt.com - Kostenlose Erotikgeschichen",
    "wof:placetype":"venue"
},
  "geometry": {"coordinates":[8.612407,49.754211],"type":"Point"}
}