{
  "type": "Feature",
  "properties": {
    "iso:country":"DE",
    "sg:address":"Industriestr. 7",
    "sg:city":"Grevenbroich",
    "sg:phone":"+49 2182/57770",
    "sg:postcode":"41516",
    "sg:province":"Nordrhein-Westfalen",
    "wof:name":"Daners & Seitz Gmbh & Co. Kg",
    "wof:placetype":"venue"
},
  "geometry": {"coordinates":[6.6218371391,51.1311187744],"type":"Point"}
}