{
  "type": "Feature",
  "properties": {
    "iso:country":"DE",
    "sg:address":"Lollfu\u00df 3",
    "sg:city":"Schleswig",
    "sg:phone":"+49 4621/28648",
    "sg:postcode":"24837",
    "sg:province":"Schleswig-Holstein",
    "wof:name":"Itzehoer Versicherungen Brandgilde Von 1691",
    "wof:placetype":"venue"
},
  "geometry": {"coordinates":[9.5561800003,54.515045166],"type":"Point"}
}