{
  "type": "Feature",
  "properties": {
    "iso:country":"DE",
    "sg:address":"In der Au 12",
    "sg:city":"Andechs",
    "sg:phone":"+49 8157/7900",
    "sg:postcode":"82346",
    "sg:province":"Bayern",
    "wof:name":"Ludwig Bals",
    "wof:placetype":"venue"
},
  "geometry": {"coordinates":[11.22279,47.943295],"type":"Point"}
}