{
  "type": "Feature",
  "properties": {
    "iso:country":"DE",
    "sg:address":"Bahnhofstr. 55",
    "sg:city":"Osterholz-Scharmbeck",
    "sg:phone":"+49 4791/2512",
    "sg:postcode":"27711",
    "sg:province":"Niedersachsen",
    "wof:name":"Erika Dudjahn",
    "wof:placetype":"venue"
},
  "geometry": {"coordinates":[8.7951440811,53.225402832],"type":"Point"}
}