{
  "type": "Feature",
  "properties": {
    "iso:country":"DE",
    "sg:address":"Hausacher Str. 5",
    "sg:city":"Mannheim",
    "sg:phone":"+49 621/471600",
    "sg:postcode":"68239",
    "sg:province":"Baden-W\u00fcrttemberg",
    "wof:name":"Paul H\u00e4u\u00dfler",
    "wof:placetype":"venue"
},
  "geometry": {"coordinates":[8.5595216751,49.4615058899],"type":"Point"}
}