{
  "type": "Feature",
  "properties": {
    "iso:country":"DE",
    "sg:address":"H\u00e4herweg 22",
    "sg:city":"Hamburg",
    "sg:phone":"+49 40/6065248",
    "sg:postcode":"22399",
    "sg:province":"Hamburg",
    "wof:name":"Iralman Export-import Gmbh",
    "wof:placetype":"venue"
},
  "geometry": {"coordinates":[10.0650529861,53.6513137817],"type":"Point"}
}