{
  "type": "Feature",
  "properties": {
    "iso:country":"DE",
    "sg:address":"Zum Berge 40",
    "sg:city":"Seevetal",
    "sg:phone":"+49 40/7683142",
    "sg:postcode":"21217",
    "sg:province":"Niedersachsen",
    "wof:name":"Klaus Behr",
    "wof:placetype":"venue"
},
  "geometry": {"coordinates":[10.00722,53.417301],"type":"Point"}
}