{
  "type": "Feature",
  "properties": {
    "iso:country":"DE",
    "sg:address":"Heinrich-Heine-Str. 1",
    "sg:city":"Jena",
    "sg:postcode":"07749",
    "sg:province":"Th\u00fcringen",
    "wof:name":"Gothaer Sportversicherung",
    "wof:placetype":"venue"
},
  "geometry": {"coordinates":[11.5986032486,50.9343414307],"type":"Point"}
}