{
  "type": "Feature",
  "properties": {
    "iso:country":"DE",
    "sg:address":"Heigarenweg 18",
    "sg:city":"Hagen",
    "sg:phone":"+49 2331/61680",
    "sg:postcode":"58093",
    "sg:province":"Nordrhein-Westfalen",
    "wof:name":"Gerd Liebetruth Elektroinstallation",
    "wof:placetype":"venue"
},
  "geometry": {"coordinates":[7.500307,51.389313],"type":"Point"}
}