{
  "type": "Feature",
  "properties": {
    "iso:country":"DE",
    "sg:address":"Luftschiff",
    "sg:city":"Storkau",
    "sg:phone":"+49 3443/81500",
    "sg:postcode":"06667",
    "sg:province":"Sachsen-Anhalt",
    "wof:name":"G. Sch\u00f6lzel",
    "wof:placetype":"venue"
},
  "geometry": {"coordinates":[11.8849048615,51.2336654663],"type":"Point"}
}