{
  "type": "Feature",
  "properties": {
    "iso:country":"DE",
    "sg:address":"Kinzigheimerweg 112",
    "sg:city":"Hanau",
    "sg:phone":"+49 6181/934636",
    "sg:postcode":"63450",
    "sg:province":"Hessen",
    "wof:name":"Brandschutz In Hanau Und Umgebung",
    "wof:placetype":"venue"
},
  "geometry": {"coordinates":[8.924785,50.119312],"type":"Point"}
}