{
  "type": "Feature",
  "properties": {
    "iso:country":"DE",
    "sg:address":"Bahnhofstr. 15b",
    "sg:city":"L\u00fcbstorf",
    "sg:phone":"+49 3867/4205",
    "sg:postcode":"19069",
    "sg:province":"Mecklenburg-Vorpommern",
    "wof:name":"D. Timm",
    "wof:placetype":"venue"
},
  "geometry": {"coordinates":[11.40585,53.729656],"type":"Point"}
}