{
  "type": "Feature",
  "properties": {
    "iso:country":"DE",
    "sg:address":"Friedrich-Ebert-Str. 111",
    "sg:city":"Haan",
    "sg:phone":"+49 212/9957570",
    "sg:postcode":"42781",
    "sg:province":"Nordrhein-Westfalen",
    "wof:name":"Computer Factory Gmbh",
    "wof:placetype":"venue"
},
  "geometry": {"coordinates":[7.0239400864,51.1965942383],"type":"Point"}
}