{
  "type": "Feature",
  "properties": {
    "iso:country":"DE",
    "sg:address":"Alfred-Kowalke-Str. 30",
    "sg:city":"Berlin",
    "sg:phone":"+49 30/5122113",
    "sg:postcode":"10315",
    "sg:province":"Berlin",
    "wof:name":"Bierstube",
    "wof:placetype":"venue"
},
  "geometry": {"coordinates":[13.5202083588,52.5061340332],"type":"Point"}
}