{
  "type": "Feature",
  "properties": {
    "iso:country":"DE",
    "sg:address":"Beethovenstr. 7",
    "sg:city":"Saulheim",
    "sg:phone":"+49 6732/4685",
    "sg:postcode":"55291",
    "sg:province":"Rheinland-Pfalz",
    "wof:name":"G\u00fcnter R\u00fchl",
    "wof:placetype":"venue"
},
  "geometry": {"coordinates":[8.1483612061,49.8690071106],"type":"Point"}
}