{
  "type": "Feature",
  "properties": {
    "iso:country":"DE",
    "sg:address":"Ringstr. 3b",
    "sg:city":"Brunnthal",
    "sg:postcode":"85649",
    "sg:province":"Bayern",
    "wof:name":"Walter Mayrhofer",
    "wof:placetype":"venue"
},
  "geometry": {"coordinates":[11.6595,47.996635],"type":"Point"}
}