{
  "type": "Feature",
  "properties": {
    "iso:country":"DE",
    "sg:address":"Br\u00fcckenstr. 14",
    "sg:city":"Leichlingen",
    "sg:phone":"+49 2175/3075",
    "sg:postcode":"42799",
    "sg:province":"Nordrhein-Westfalen",
    "wof:name":"Peter Monshausen Architekt",
    "wof:placetype":"venue"
},
  "geometry": {"coordinates":[7.0128,51.10511],"type":"Point"}
}