{
  "type": "Feature",
  "properties": {
    "iso:country":"DE",
    "sg:address":"Paul-Erdni\u00df-Str. 1",
    "sg:city":"Rinteln",
    "sg:phone":"+49 5751/2377",
    "sg:postcode":"31737",
    "sg:province":"Niedersachsen",
    "wof:name":"Hallenbad Im Schul- Und Sportzentrum Rinteln",
    "wof:placetype":"venue"
},
  "geometry": {"coordinates":[9.0733861923,52.1782493591],"type":"Point"}
}