{
  "type": "Feature",
  "properties": {
    "iso:country":"DE",
    "sg:address":"Dresdner Str. 9",
    "sg:city":"Ostrau",
    "sg:phone":"+49 34324/21925",
    "sg:postcode":"04749",
    "sg:province":"Sachsen",
    "wof:name":"Irmgard Krumbiegel",
    "wof:placetype":"venue"
},
  "geometry": {"coordinates":[13.1634759903,51.1983947754],"type":"Point"}
}