{
  "type": "Feature",
  "properties": {
    "iso:country":"DE",
    "sg:address":"Hauptstr. 34",
    "sg:city":"Eltville",
    "sg:phone":"+49 6723/99680",
    "sg:postcode":"65347",
    "sg:province":"Hessen",
    "wof:name":"Hotel Und Weinhaus Zum Krug Gmbh",
    "wof:placetype":"venue"
},
  "geometry": {"coordinates":[8.0609807968,50.0138587952],"type":"Point"}
}