{
  "type": "Feature",
  "properties": {
    "iso:country":"DE",
    "sg:address":"Flensburger Str. 8 B",
    "sg:city":"Schleswig",
    "sg:phone":"+49 4621/22624",
    "sg:postcode":"24837",
    "sg:province":"Schleswig-Holstein",
    "wof:name":"Gayen & Berns Homann",
    "wof:placetype":"venue"
},
  "geometry": {"coordinates":[9.5468845367,54.5144233704],"type":"Point"}
}