{
  "type": "Feature",
  "properties": {
    "iso:country":"DE",
    "sg:address":"Tulpenweg 10",
    "sg:city":"Dietenheim",
    "sg:phone":"+49 7347/4155",
    "sg:postcode":"89165",
    "sg:province":"Baden-W\u00fcrttemberg",
    "wof:name":"Wekra Gmbh",
    "wof:placetype":"venue"
},
  "geometry": {"coordinates":[10.0733032227,48.2174682617],"type":"Point"}
}