{
  "type": "Feature",
  "properties": {
    "iso:country":"DE",
    "sg:address":"Schinkelstr. 78",
    "sg:city":"Ahlen",
    "sg:phone":"+49 4923/8280740",
    "sg:postcode":"59227",
    "sg:province":"Nordrhein-Westfalen",
    "wof:name":"Fussboden - Franz Laurenz",
    "wof:placetype":"venue"
},
  "geometry": {"coordinates":[7.915126,51.772511],"type":"Point"}
}