{
  "type": "Feature",
  "properties": {
    "iso:country":"DE",
    "sg:address":"Kleinheppacher Str. 5",
    "sg:city":"Weinstadt",
    "sg:phone":"+49 7151/61287",
    "sg:postcode":"71384",
    "sg:province":"Baden-W\u00fcrttemberg",
    "wof:name":"H. Klopfer",
    "wof:placetype":"venue"
},
  "geometry": {"coordinates":[9.3653850555,48.8122634888],"type":"Point"}
}