{
  "type": "Feature",
  "properties": {
    "iso:country":"DE",
    "sg:address":"Echterdinger Str. 26",
    "sg:city":"Leinfelden-Echterdingen",
    "sg:phone":"+49 711/753926",
    "sg:postcode":"70771",
    "sg:province":"Baden-W\u00fcrttemberg",
    "wof:name":"Harald Heimerdinger Rechtsanwalt",
    "wof:placetype":"venue"
},
  "geometry": {"coordinates":[9.1451091766,48.6923332214],"type":"Point"}
}