{
  "type": "Feature",
  "properties": {
    "iso:country":"DE",
    "sg:address":"Kiebitzstr. 39",
    "sg:city":"Hoya",
    "sg:phone":"+49 4251/6626",
    "sg:postcode":"27318",
    "sg:province":"Niedersachsen",
    "wof:name":"Lars Hepcke",
    "wof:placetype":"venue"
},
  "geometry": {"coordinates":[9.1299705505,52.8113555908],"type":"Point"}
}