{
  "type": "Feature",
  "properties": {
    "iso:country":"DE",
    "sg:address":"Hochstr. 1",
    "sg:city":"Ratingen",
    "sg:phone":"+49 2102/846636",
    "sg:postcode":"40878",
    "sg:province":"Nordrhein-Westfalen",
    "wof:name":"Bergischer Hof",
    "wof:placetype":"venue"
},
  "geometry": {"coordinates":[6.8542881012,51.2989845276],"type":"Point"}
}