{
  "type": "Feature",
  "properties": {
    "iso:country":"DE",
    "sg:address":"Gewerbehof 11",
    "sg:city":"Harrislee",
    "sg:phone":"+49 461/95111",
    "sg:postcode":"24955",
    "sg:province":"Schleswig-Holstein",
    "wof:name":"Lambert & Christiansen Gmbh",
    "wof:placetype":"venue"
},
  "geometry": {"coordinates":[9.381772995,54.7911834717],"type":"Point"}
}