{
  "type": "Feature",
  "properties": {
    "iso:country":"DE",
    "sg:address":"Lennestr. 114",
    "sg:city":"Plettenberg",
    "sg:phone":"+49 2391/53383",
    "sg:postcode":"58840",
    "sg:province":"Nordrhein-Westfalen",
    "wof:name":"Fred Wilms Bootshandlung",
    "wof:placetype":"venue"
},
  "geometry": {"coordinates":[7.850084,51.233948],"type":"Point"}
}