{
  "type": "Feature",
  "properties": {
    "iso:country":"DE",
    "sg:address":"Niedere Str. 35",
    "sg:city":"R\u00fcthen",
    "sg:phone":"+49 2952/1681",
    "sg:postcode":"59602",
    "sg:province":"Nordrhein-Westfalen",
    "wof:name":"Fritz Luigs",
    "wof:placetype":"venue"
},
  "geometry": {"coordinates":[8.426345,51.49165],"type":"Point"}
}