{
  "type": "Feature",
  "properties": {
    "iso:country":"DE",
    "sg:address":"Gartenau 9",
    "sg:city":"Berchtesgaden",
    "sg:phone":"+49 8652/1442",
    "sg:postcode":"83471",
    "sg:province":"Bayern",
    "wof:name":"E. Walch",
    "wof:placetype":"venue"
},
  "geometry": {"coordinates":[13.0390090942,47.6561546326],"type":"Point"}
}