{
  "type": "Feature",
  "properties": {
    "iso:country":"DE",
    "sg:address":"Bachstr. 25",
    "sg:city":"Bonn",
    "sg:phone":"+49 228/632781",
    "sg:postcode":"53115",
    "sg:province":"Nordrhein-Westfalen",
    "wof:name":"Paul Gongolsky",
    "wof:placetype":"venue"
},
  "geometry": {"coordinates":[7.091065,50.732258],"type":"Point"}
}