{
  "type": "Feature",
  "properties": {
    "iso:country":"DE",
    "sg:address":"Am Rumpelteich 5",
    "sg:city":"Idar-Oberstein",
    "sg:phone":"+49 6781/28300",
    "sg:postcode":"55743",
    "sg:province":"Rheinland-Pfalz",
    "wof:name":"Kurt Ruth",
    "wof:placetype":"venue"
},
  "geometry": {"coordinates":[7.3390021324,49.6985855103],"type":"Point"}
}