{
  "type": "Feature",
  "properties": {
    "iso:country":"DE",
    "sg:address":"An der Kirchenpforte 47",
    "sg:city":"Mainz",
    "sg:phone":"+49 6131/280487",
    "sg:postcode":"55128",
    "sg:province":"Rheinland-Pfalz",
    "wof:name":"Graf!kb\u00fcro",
    "wof:placetype":"venue"
},
  "geometry": {"coordinates":[8.242415,49.985634],"type":"Point"}
}