{
  "type": "Feature",
  "properties": {
    "iso:country":"DE",
    "sg:address":"Im Canet 5",
    "sg:city":"Konz",
    "sg:phone":"+49 6501/15160",
    "sg:postcode":"54329",
    "sg:province":"Rheinland-Pfalz",
    "wof:name":"Albert Rohles Ingenieur",
    "wof:placetype":"venue"
},
  "geometry": {"coordinates":[6.5823640823,49.6921958923],"type":"Point"}
}