{
  "type": "Feature",
  "properties": {
    "iso:country":"DE",
    "sg:address":"Lambertusstr. 8",
    "sg:city":"Heinsberg",
    "sg:phone":"+49 2452/67355",
    "sg:postcode":"52525",
    "sg:province":"Nordrhein-Westfalen",
    "wof:name":"Dart Cafe Royal",
    "wof:placetype":"venue"
},
  "geometry": {"coordinates":[6.14584589,51.0391693115],"type":"Point"}
}