{
  "type": "Feature",
  "properties": {
    "iso:country":"DE",
    "sg:address":"Boxdorfer Str. 13",
    "sg:city":"F\u00fcrth",
    "sg:phone":"+49 911/304032",
    "sg:postcode":"90765",
    "sg:province":"Bayern",
    "wof:name":"F\u00fcrther Textildruck Gmbh",
    "wof:placetype":"venue"
},
  "geometry": {"coordinates":[11.0213127136,49.5031890869],"type":"Point"}
}