{
  "type": "Feature",
  "properties": {
    "iso:country":"DE",
    "sg:address":"Donauschwabenstr. 22",
    "sg:city":"Bielefeld",
    "sg:phone":"+49 521/72823",
    "sg:postcode":"33609",
    "sg:province":"Nordrhein-Westfalen",
    "wof:name":"Ev. Luth. Pfarramt Iv Gem. Heepen",
    "wof:placetype":"venue"
},
  "geometry": {"coordinates":[8.5999603271,52.0500831604],"type":"Point"}
}