{
  "type": "Feature",
  "properties": {
    "iso:country":"DE",
    "sg:address":"Ziegelstr. 20",
    "sg:city":"Ergoldsbach",
    "sg:phone":"+49 8771/96010",
    "sg:postcode":"84061",
    "sg:province":"Bayern",
    "wof:name":"Johannes Petz",
    "wof:placetype":"venue"
},
  "geometry": {"coordinates":[12.2008047104,48.6936073303],"type":"Point"}
}