{
  "type": "Feature",
  "properties": {
    "iso:country":"DE",
    "sg:address":"Berkenb\u00fcscher Str 5-8",
    "sg:city":"Stemwede",
    "sg:phone":"+49 5773/80090",
    "sg:postcode":"32351",
    "sg:province":"Nordrhein-Westfalen",
    "wof:name":"Fr. Piper Gmbh & Co Kg",
    "wof:placetype":"venue"
},
  "geometry": {"coordinates":[8.484571,52.444206],"type":"Point"}
}