{
  "type": "Feature",
  "properties": {
    "iso:country":"DE",
    "sg:address":"Am Pl\u00e4rrer 8",
    "sg:city":"N\u00fcrnberg",
    "sg:phone":"+49 911/929720",
    "sg:postcode":"90429",
    "sg:province":"Bayern",
    "wof:name":"Turkish Airlines Inc.",
    "wof:placetype":"venue"
},
  "geometry": {"coordinates":[11.064771,49.449055],"type":"Point"}
}