{
  "type": "Feature",
  "properties": {
    "iso:country":"DE",
    "sg:address":"Brunsdorfer Weg 6",
    "sg:city":"Hamburg",
    "sg:phone":"+49 40/6040856",
    "sg:postcode":"22359",
    "sg:province":"Hamburg",
    "wof:name":"Werner La-ramee",
    "wof:placetype":"venue"
},
  "geometry": {"coordinates":[10.14702,53.674198],"type":"Point"}
}