{
  "type": "Feature",
  "properties": {
    "iso:country":"DE",
    "sg:address":"Seestr. 23",
    "sg:city":"Genshagen",
    "sg:phone":"+49 3378/879979",
    "sg:postcode":"14974",
    "sg:province":"Brandenburg",
    "wof:name":"Bremer Transformatoren Gmbh",
    "wof:placetype":"venue"
},
  "geometry": {"coordinates":[13.3084039688,52.3119277954],"type":"Point"}
}