{
  "type": "Feature",
  "properties": {
    "iso:country":"DE",
    "sg:address":"Nesserlander Str. 72",
    "sg:city":"Emden",
    "sg:phone":"+49 4921/93970",
    "sg:postcode":"26723",
    "sg:province":"Niedersachsen",
    "wof:name":"Emder Schiffs- U. Industrieelektrik Gmbh",
    "wof:placetype":"venue"
},
  "geometry": {"coordinates":[7.195688,53.356571],"type":"Point"}
}