{
  "type": "Feature",
  "properties": {
    "iso:country":"DE",
    "sg:address":"Baroper Bahnhofstr. 65",
    "sg:city":"Dortmund",
    "sg:phone":"+49 231/752995",
    "sg:postcode":"44225",
    "sg:province":"Nordrhein-Westfalen",
    "wof:name":"Droste",
    "wof:placetype":"venue"
},
  "geometry": {"coordinates":[7.4308300018,51.4770317078],"type":"Point"}
}