{
  "type": "Feature",
  "properties": {
    "iso:country":"DE",
    "sg:address":"Max-Kurz-Str. 16",
    "sg:city":"Chieming",
    "sg:phone":"+49 8664/1246",
    "sg:postcode":"83339",
    "sg:province":"Bayern",
    "wof:name":"Wallner Wohnbau Gmbh",
    "wof:placetype":"venue"
},
  "geometry": {"coordinates":[12.5422096252,47.8893051147],"type":"Point"}
}