{
  "type": "Feature",
  "properties": {
    "iso:country":"DE",
    "sg:address":"Br\u00fcsseler Ring 71",
    "sg:city":"Aachen",
    "sg:postcode":"52074",
    "sg:province":"Nordrhein-Westfalen",
    "wof:name":"Vz-spielhallenbetriebs Gmbh",
    "wof:placetype":"venue"
},
  "geometry": {"coordinates":[6.0665187836,50.7542228699],"type":"Point"}
}