{
  "type": "Feature",
  "properties": {
    "iso:country":"DE",
    "sg:address":"Mahdentalstr. 114",
    "sg:city":"Sindelfingen",
    "sg:phone":"+49 7031/83505",
    "sg:postcode":"71065",
    "sg:province":"Baden-W\u00fcrttemberg",
    "wof:name":"Young Line Petra Fischer",
    "wof:placetype":"venue"
},
  "geometry": {"coordinates":[9.0408821106,48.7049026489],"type":"Point"}
}