{
  "type": "Feature",
  "properties": {
    "iso:country":"DE",
    "sg:address":"Winnender Str. 7",
    "sg:city":"Schwaikheim",
    "sg:phone":"+49 7195/966355",
    "sg:postcode":"71409",
    "sg:province":"Baden-W\u00fcrttemberg",
    "wof:name":"Pizzaservice Nirmal Sing",
    "wof:placetype":"venue"
},
  "geometry": {"coordinates":[9.35431,48.879044],"type":"Point"}
}