{
  "type": "Feature",
  "properties": {
    "iso:country":"DE",
    "sg:address":"Kleine Str. 19 a",
    "sg:city":"Delbr\u00fcck",
    "sg:phone":"+49 5250/7222",
    "sg:postcode":"33129",
    "sg:province":"Nordrhein-Westfalen",
    "wof:name":"Steffens-druck Gmbh",
    "wof:placetype":"venue"
},
  "geometry": {"coordinates":[8.558886,51.762505],"type":"Point"}
}