{
  "type": "Feature",
  "properties": {
    "iso:country":"DE",
    "sg:address":"Ochtruper Str. 196",
    "sg:city":"Gronau",
    "sg:phone":"+49 2562/2780",
    "sg:postcode":"48599",
    "sg:province":"Nordrhein-Westfalen",
    "wof:name":"Heinrich Reinermann",
    "wof:placetype":"venue"
},
  "geometry": {"coordinates":[7.048275,52.205467],"type":"Point"}
}