{
  "type": "Feature",
  "properties": {
    "iso:country":"DE",
    "sg:address":"D\u00fcsternstr. 1",
    "sg:city":"Hamburg",
    "sg:phone":"+49 40/376476",
    "sg:postcode":"20355",
    "sg:province":"Hamburg",
    "wof:name":"Hanseatica Erste Europa- Immobilien Fonds",
    "wof:placetype":"venue"
},
  "geometry": {"coordinates":[9.984665,53.550407],"type":"Point"}
}