{
  "type": "Feature",
  "properties": {
    "iso:country":"DE",
    "sg:address":"Hauptstr. 8",
    "sg:city":"Wurzen",
    "sg:phone":"+49 3425/923692",
    "sg:postcode":"04808",
    "sg:province":"Sachsen",
    "wof:name":"Keller",
    "wof:placetype":"venue"
},
  "geometry": {"coordinates":[12.839199,51.344845],"type":"Point"}
}