{
  "type": "Feature",
  "properties": {
    "iso:country":"DE",
    "sg:address":"Buschfelder Weg",
    "sg:city":"Erftstadt",
    "sg:phone":"+49 2235/17165",
    "sg:postcode":"50374",
    "sg:province":"Nordrhein-Westfalen",
    "wof:name":"P. Weber Architekt",
    "wof:placetype":"venue"
},
  "geometry": {"coordinates":[6.806274,50.805374],"type":"Point"}
}