{
  "type": "Feature",
  "properties": {
    "iso:country":"DE",
    "sg:address":"Zschochersche Str. 1 c",
    "sg:city":"Leipzig",
    "sg:phone":"+49 341/4802503",
    "sg:postcode":"04177",
    "sg:province":"Sachsen",
    "wof:name":"U. Eichler",
    "wof:placetype":"venue"
},
  "geometry": {"coordinates":[12.340068,51.33699],"type":"Point"}
}