{
  "type": "Feature",
  "properties": {
    "iso:country":"DE",
    "sg:address":"K\u00f6nigsberger Str. 40",
    "sg:city":"M\u00f6lln",
    "sg:phone":"+49 4542/841611",
    "sg:postcode":"23879",
    "sg:province":"Schleswig-Holstein",
    "wof:name":"Handelsb\u00fcro M\u00f6lln E. K.",
    "wof:placetype":"venue"
},
  "geometry": {"coordinates":[10.6965818405,53.5947380066],"type":"Point"}
}