{
  "type": "Feature",
  "properties": {
    "iso:country":"DE",
    "sg:address":"Kaiserwiesenweg 4",
    "sg:city":"Landau",
    "sg:phone":"+49 6341/60177",
    "sg:postcode":"76829",
    "sg:province":"Rheinland-Pfalz",
    "wof:name":"Twb Baugesellschaft Mbh",
    "wof:placetype":"venue"
},
  "geometry": {"coordinates":[8.069508,49.211128],"type":"Point"}
}