{
  "type": "Feature",
  "properties": {
    "iso:country":"DE",
    "sg:address":"Vorderer Flo\u00dfanger 8",
    "sg:city":"Coburg",
    "sg:phone":"+49 9561/54930",
    "sg:postcode":"96450",
    "sg:province":"Bayern",
    "wof:name":"Sport Hess",
    "wof:placetype":"venue"
},
  "geometry": {"coordinates":[10.969795,50.269905],"type":"Point"}
}