{
  "type": "Feature",
  "properties": {
    "iso:country":"DE",
    "sg:address":"Bergstr. 18",
    "sg:city":"Pulheim",
    "sg:phone":"+49 2238/2495",
    "sg:postcode":"50259",
    "sg:province":"Nordrhein-Westfalen",
    "wof:name":"Herbert Rogocki",
    "wof:placetype":"venue"
},
  "geometry": {"coordinates":[6.760095,51.024681],"type":"Point"}
}