{
  "type": "Feature",
  "properties": {
    "iso:country":"DE",
    "sg:address":"Auf dem Bohnenkamp 24",
    "sg:city":"Bremen",
    "sg:phone":"+49 421/540657",
    "sg:postcode":"28197",
    "sg:province":"Bremen",
    "wof:name":"Conrad Scherf Ingenieur",
    "wof:placetype":"venue"
},
  "geometry": {"coordinates":[8.766910553,53.0810890198],"type":"Point"}
}