{
  "type": "Feature",
  "properties": {
    "iso:country":"DE",
    "sg:address":"Schmiederstr 75",
    "sg:city":"Meerane",
    "sg:phone":"+49 3764/2257",
    "sg:postcode":"08393",
    "sg:province":"Sachsen",
    "wof:name":"Lumi-solar",
    "wof:placetype":"venue"
},
  "geometry": {"coordinates":[12.45195,50.850159],"type":"Point"}
}