{
  "type": "Feature",
  "properties": {
    "iso:country":"DE",
    "sg:address":"Sudetenstr. 1",
    "sg:city":"Laufen",
    "sg:phone":"+49 8682/333",
    "sg:postcode":"83410",
    "sg:province":"Bayern",
    "wof:name":"Irmgard Nowak Hebamme",
    "wof:placetype":"venue"
},
  "geometry": {"coordinates":[12.929872,47.937206],"type":"Point"}
}