{
  "type": "Feature",
  "properties": {
    "iso:country":"DE",
    "sg:address":"Schlettweiner Weg 5",
    "sg:city":"P\u00f6\u00dfneck",
    "sg:phone":"+49 3647/2665",
    "sg:postcode":"07381",
    "sg:province":"Th\u00fcringen",
    "wof:name":"Wfb- Behindertenwerkst\u00e4tten Ggmbh",
    "wof:placetype":"venue"
},
  "geometry": {"coordinates":[11.586147,50.695244],"type":"Point"}
}