{
  "type": "Feature",
  "properties": {
    "iso:country":"DE",
    "sg:address":"Zechenstr. 12/14",
    "sg:city":"Marl",
    "sg:phone":"+49 2365/96780",
    "sg:postcode":"45772",
    "sg:province":"Nordrhein-Westfalen",
    "wof:name":"Gebr. Bunzel Holzhandlung Und Baumatrialien Gmbh",
    "wof:placetype":"venue"
},
  "geometry": {"coordinates":[7.087429,51.663937],"type":"Point"}
}