{
  "type": "Feature",
  "properties": {
    "iso:country":"DE",
    "sg:address":"B\u00f6hnertwg. 9",
    "sg:city":"Essen",
    "sg:phone":"+49 4920/1867601",
    "sg:postcode":"45359",
    "sg:province":"Nordrhein-Westfalen",
    "wof:name":"Roland Schuhe Gmbh & Co Handels Kg",
    "wof:placetype":"venue"
},
  "geometry": {"coordinates":[6.93054,51.455269],"type":"Point"}
}