{
  "type": "Feature",
  "properties": {
    "iso:country":"DE",
    "sg:address":"Z\u00e4hringerstr. 33",
    "sg:city":"Berlin",
    "sg:phone":"+49 30/8832607",
    "sg:postcode":"10707",
    "sg:province":"Berlin",
    "wof:name":"Helion Galerie",
    "wof:placetype":"venue"
},
  "geometry": {"coordinates":[13.3136644363,52.4956436157],"type":"Point"}
}