{
  "type": "Feature",
  "properties": {
    "iso:country":"DE",
    "sg:address":"Weiherhofstr. 66",
    "sg:city":"Br\u00fchl",
    "sg:phone":"+49 2232/31366",
    "sg:postcode":"50321",
    "sg:province":"Nordrhein-Westfalen",
    "wof:name":"H. Und H. Balke",
    "wof:placetype":"venue"
},
  "geometry": {"coordinates":[6.9253401756,50.805141449],"type":"Point"}
}