{
  "type": "Feature",
  "properties": {
    "iso:country":"DE",
    "sg:address":"Am Speckamp 9",
    "sg:city":"Ratingen",
    "sg:phone":"+49 2102/36056",
    "sg:postcode":"40885",
    "sg:province":"Nordrhein-Westfalen",
    "wof:name":"H. Blumenkamp",
    "wof:placetype":"venue"
},
  "geometry": {"coordinates":[6.8360137939,51.336730957],"type":"Point"}
}