{
  "type": "Feature",
  "properties": {
    "iso:country":"DE",
    "sg:address":"Dorfstr. 29",
    "sg:city":"Euscheid",
    "sg:phone":"+49 6556/7234",
    "sg:postcode":"54597",
    "sg:province":"Rheinland-Pfalz",
    "wof:name":"Bernhard Lafleur",
    "wof:placetype":"venue"
},
  "geometry": {"coordinates":[6.299362,50.132427],"type":"Point"}
}