{
  "type": "Feature",
  "properties": {
    "iso:country":"DE",
    "sg:address":"Kehrstr. 2",
    "sg:city":"Boos",
    "sg:phone":"+49 2656/533",
    "sg:postcode":"56729",
    "sg:province":"Rheinland-Pfalz",
    "wof:name":"G\u00f6rgen Gmbh",
    "wof:placetype":"venue"
},
  "geometry": {"coordinates":[7.015674,50.311562],"type":"Point"}
}