{
  "type": "Feature",
  "properties": {
    "iso:country":"DE",
    "sg:address":"Schwanensteig 1",
    "sg:city":"Wildenbruch",
    "sg:phone":"+49 33205/64034",
    "sg:postcode":"14552",
    "sg:province":"Brandenburg",
    "wof:name":"Dieter Schrickel Landschaftsarchitekt",
    "wof:placetype":"venue"
},
  "geometry": {"coordinates":[13.0301704407,52.3122367859],"type":"Point"}
}