{
  "type": "Feature",
  "properties": {
    "iso:country":"DE",
    "sg:address":"Dieselstr. 4",
    "sg:city":"Lensahn",
    "sg:postcode":"23738",
    "sg:province":"Schleswig-Holstein",
    "wof:name":"Chrome E. K.",
    "wof:placetype":"venue"
},
  "geometry": {"coordinates":[10.897315979,54.2178649902],"type":"Point"}
}