{
  "type": "Feature",
  "properties": {
    "iso:country":"DE",
    "sg:address":"Niederkasseler Str. 91",
    "sg:city":"D\u00fcsseldorf",
    "sg:phone":"+49 211/551859",
    "sg:postcode":"40547",
    "sg:province":"Nordrhein-Westfalen",
    "wof:name":"Werner Hansen",
    "wof:placetype":"venue"
},
  "geometry": {"coordinates":[6.751802,51.239491],"type":"Point"}
}