{
  "type": "Feature",
  "properties": {
    "iso:country":"DE",
    "sg:address":"J\u00e4gerhausstr. 2",
    "sg:city":"Stolberg",
    "sg:phone":"+49 2402/71056",
    "sg:postcode":"52224",
    "sg:province":"Nordrhein-Westfalen",
    "wof:name":"W\u00dcs Weirauch \u00dcberdachungssysteme Gmbh",
    "wof:placetype":"venue"
},
  "geometry": {"coordinates":[6.253947,50.719337],"type":"Point"}
}