{
  "type": "Feature",
  "properties": {
    "iso:country":"DE",
    "sg:address":"Karl-Marx-Str. 3",
    "sg:city":"Thale",
    "sg:phone":"+49 3947/62037",
    "sg:postcode":"06502",
    "sg:province":"Sachsen-Anhalt",
    "wof:name":"Thomas Schmidt Steuerberater",
    "wof:placetype":"venue"
},
  "geometry": {"coordinates":[11.0333003998,51.7482681274],"type":"Point"}
}