{
  "type": "Feature",
  "properties": {
    "iso:country":"DE",
    "sg:address":"Postweg 4",
    "sg:city":"Schlier",
    "sg:phone":"+49 7529/7134",
    "sg:postcode":"88281",
    "sg:province":"Baden-W\u00fcrttemberg",
    "wof:name":"Julius Jassniger",
    "wof:placetype":"venue"
},
  "geometry": {"coordinates":[9.702546,47.796516],"type":"Point"}
}