{
  "type": "Feature",
  "properties": {
    "iso:country":"DE",
    "sg:address":"Berliner Str. 8",
    "sg:city":"Schwalbach",
    "sg:postcode":"65824",
    "sg:province":"Hessen",
    "wof:name":"Thomas Wolf",
    "wof:placetype":"venue"
},
  "geometry": {"coordinates":[8.5313062668,50.1540107727],"type":"Point"}
}