{
  "type": "Feature",
  "properties": {
    "iso:country":"DE",
    "sg:address":"Harjesstr. 3",
    "sg:city":"Gotha",
    "sg:phone":"+49 3621/72550",
    "sg:postcode":"99867",
    "sg:province":"Th\u00fcringen",
    "wof:name":"Rosebrock Gmbh & Co. K\u00fcchenzentrum Gotha Kg",
    "wof:placetype":"venue"
},
  "geometry": {"coordinates":[10.7153158188,50.9269943237],"type":"Point"}
}