{
  "type": "Feature",
  "properties": {
    "iso:country":"DE",
    "sg:address":"Heidekampweg 55",
    "sg:city":"Berlin",
    "sg:phone":"+49 30/5328418",
    "sg:postcode":"12437",
    "sg:province":"Berlin",
    "wof:name":"Waretex-textilreinlichkeit Aus Einer Hand Gmbh",
    "wof:placetype":"venue"
},
  "geometry": {"coordinates":[13.4802532196,52.4655036926],"type":"Point"}
}