{
  "type": "Feature",
  "properties": {
    "iso:country":"DE",
    "sg:address":"Eschenweg 12",
    "sg:city":"Meusegast",
    "sg:phone":"+49 35027/5828",
    "sg:postcode":"01809",
    "sg:province":"Sachsen",
    "wof:name":"Wolf Sportsysteme Cornelia Wolf",
    "wof:placetype":"venue"
},
  "geometry": {"coordinates":[13.875688,50.930126],"type":"Point"}
}