{
  "type": "Feature",
  "properties": {
    "iso:country":"DE",
    "sg:address":"Flurweg 2",
    "sg:city":"Temmels",
    "sg:phone":"+49 6584/340",
    "sg:postcode":"54441",
    "sg:province":"Rheinland-Pfalz",
    "wof:name":"Alfred Und Rudolf Gressnich",
    "wof:placetype":"venue"
},
  "geometry": {"coordinates":[6.466228,49.689705],"type":"Point"}
}