{
  "type": "Feature",
  "properties": {
    "iso:country":"DE",
    "sg:address":"W\u00fcstenbruck 19",
    "sg:city":"Ansbach",
    "sg:phone":"+49 981/461650",
    "sg:postcode":"91522",
    "sg:province":"Bayern",
    "wof:name":"Christa Wellh\u00f6fer Gmbh",
    "wof:placetype":"venue"
},
  "geometry": {"coordinates":[10.5063524246,49.2809257507],"type":"Point"}
}