{
  "type": "Feature",
  "properties": {
    "iso:country":"DE",
    "sg:address":"Indlinger Str. 11",
    "sg:city":"Pocking",
    "sg:phone":"+49 8531/130794",
    "sg:postcode":"94060",
    "sg:province":"Bayern",
    "wof:name":"Heim Und Freizeit Inh. Ludwig Gruber",
    "wof:placetype":"venue"
},
  "geometry": {"coordinates":[13.3139982224,48.401763916],"type":"Point"}
}