{
  "type": "Feature",
  "properties": {
    "iso:country":"DE",
    "sg:address":"Parkstr. 37",
    "sg:city":"Lippstadt",
    "sg:phone":"+49 2941/82002",
    "sg:postcode":"59556",
    "sg:province":"Nordrhein-Westfalen",
    "wof:name":"Peter F\u00fcrstenberg",
    "wof:placetype":"venue"
},
  "geometry": {"coordinates":[8.3322649002,51.7171401978],"type":"Point"}
}