{
  "type": "Feature",
  "properties": {
    "iso:country":"DE",
    "sg:address":"Gliesmaroder Str. 107",
    "sg:city":"Braunschweig",
    "sg:postcode":"38106",
    "sg:province":"Niedersachsen",
    "wof:name":"Bio-brotladen Sch\u00fctze Gmbh",
    "wof:placetype":"venue"
},
  "geometry": {"coordinates":[10.539262,52.273705],"type":"Point"}
}