{
  "type": "Feature",
  "properties": {
    "iso:country":"DE",
    "sg:address":"herzbergstr.10",
    "sg:city":"frankfurt",
    "sg:postcode":"60439",
    "sg:province":"Hessen",
    "wof:name":"Ferienhaus_ferienwohnung_holland",
    "wof:placetype":"venue"
},
  "geometry": {"coordinates":[8.629909,50.165306],"type":"Point"}
}