{
  "type": "Feature",
  "properties": {
    "iso:country":"DE",
    "sg:address":"Mainzer Str. 34",
    "sg:city":"Idar-Oberstein",
    "sg:phone":"+49 6781/41016",
    "sg:postcode":"55743",
    "sg:province":"Rheinland-Pfalz",
    "wof:name":"Progem Idar-oberstein Marke- Tinggesellschaft F\u00fcr Die Edel-",
    "wof:placetype":"venue"
},
  "geometry": {"coordinates":[7.3021140099,49.719203949],"type":"Point"}
}