{
  "type": "Feature",
  "properties": {
    "iso:country":"DE",
    "sg:address":"Neue Str. 15",
    "sg:city":"Druxberge",
    "sg:postcode":"39365",
    "sg:province":"Sachsen-Anhalt",
    "wof:name":"Petra Kemper",
    "wof:placetype":"venue"
},
  "geometry": {"coordinates":[11.3123340607,52.1549034119],"type":"Point"}
}