{
  "type": "Feature",
  "properties": {
    "iso:country":"DE",
    "sg:address":"Frontenhausener Str. 1",
    "sg:city":"Vilsbiburg",
    "sg:phone":"+49 8741/8588",
    "sg:postcode":"84137",
    "sg:province":"Bayern",
    "wof:name":"Antonie Bittl",
    "wof:placetype":"venue"
},
  "geometry": {"coordinates":[12.35391,48.450245],"type":"Point"}
}