{
  "type": "Feature",
  "properties": {
    "iso:country":"DE",
    "sg:address":"Frohmestr. 97",
    "sg:city":"Hamburg",
    "sg:postcode":"22459",
    "sg:province":"Hamburg",
    "wof:name":"Kn\u00f6ry Gmbh",
    "wof:placetype":"venue"
},
  "geometry": {"coordinates":[9.9285001755,53.629699707],"type":"Point"}
}