{
  "type": "Feature",
  "properties": {
    "iso:country":"DE",
    "sg:address":"B\u00e4renplatz 13",
    "sg:city":"St. Georgen",
    "sg:phone":"+49 7724/6359",
    "sg:postcode":"78112",
    "sg:province":"Baden-W\u00fcrttemberg",
    "wof:name":"Diana Oestreich",
    "wof:placetype":"venue"
},
  "geometry": {"coordinates":[8.33256,48.126556],"type":"Point"}
}