{
  "type": "Feature",
  "properties": {
    "iso:country":"DE",
    "sg:address":"Seestr. 3",
    "sg:city":"Genshagen",
    "sg:phone":"+49 3378/86430",
    "sg:postcode":"14974",
    "sg:province":"Brandenburg",
    "wof:name":"Bertram Arbeitsb\u00fchnen Gmbh",
    "wof:placetype":"venue"
},
  "geometry": {"coordinates":[13.312951,52.309532],"type":"Point"}
}