{
  "type": "Feature",
  "properties": {
    "iso:country":"DE",
    "sg:address":"Darmst\u00e4dter Str. 129 a",
    "sg:city":"Biblis",
    "sg:phone":"+49 6245/8055",
    "sg:postcode":"68647",
    "sg:province":"Hessen",
    "wof:name":"Werr Transporte Und Baustoffhandel Gmbh",
    "wof:placetype":"venue"
},
  "geometry": {"coordinates":[8.4634056091,49.6931190491],"type":"Point"}
}