{
  "type": "Feature",
  "properties": {
    "iso:country":"DE",
    "sg:address":"Kleinnaundorfer Str. 2",
    "sg:city":"Freital",
    "sg:phone":"+49 351/643979",
    "sg:postcode":"01705",
    "sg:province":"Sachsen",
    "wof:name":"Hopfenbl\u00fcte",
    "wof:placetype":"venue"
},
  "geometry": {"coordinates":[13.6853847504,51.0023765564],"type":"Point"}
}