{
  "type": "Feature",
  "properties": {
    "iso:country":"DE",
    "sg:address":"Br\u00e4ndlinweg 6",
    "sg:city":"Biberach",
    "sg:phone":"+49 7351/15750",
    "sg:postcode":"88400",
    "sg:province":"Baden-W\u00fcrttemberg",
    "wof:name":"Frankenhauser Bau- Und Grundbesitzgesellschaft Mbh",
    "wof:placetype":"venue"
},
  "geometry": {"coordinates":[9.761885,48.098469],"type":"Point"}
}