{
  "type": "Feature",
  "properties": {
    "iso:country":"DE",
    "sg:address":"Mauerstrasse 20",
    "sg:city":"Reutlingen",
    "sg:phone":"+49 7121",
    "sg:postcode":"72764",
    "sg:province":"Baden-W\u00fcrttemberg",
    "wof:name":"Gasthof Achalm",
    "wof:placetype":"venue"
},
  "geometry": {"coordinates":[9.2121639252,48.4934196472],"type":"Point"}
}