{
  "type": "Feature",
  "properties": {
    "iso:country":"DE",
    "sg:address":"Eschenrieder Str. 44",
    "sg:city":"Gr\u00f6benzell",
    "sg:phone":"+49 8142/469891",
    "sg:postcode":"82194",
    "sg:province":"Bayern",
    "wof:name":"Hwb Objekt- Und Verm\u00f6gens- Verwaltungs Gmbh",
    "wof:placetype":"venue"
},
  "geometry": {"coordinates":[11.3817691803,48.2011184692],"type":"Point"}
}