{
  "type": "Feature",
  "properties": {
    "iso:country":"DE",
    "sg:address":"Annabergstr. 40",
    "sg:city":"Sch\u00f6ningen",
    "sg:phone":"+49 5352/1745",
    "sg:postcode":"38364",
    "sg:province":"Niedersachsen",
    "wof:name":"G\u00fcnter Maack Bauunternehmen",
    "wof:placetype":"venue"
},
  "geometry": {"coordinates":[10.960252,52.131916],"type":"Point"}
}