{
  "type": "Feature",
  "properties": {
    "iso:country":"DE",
    "sg:address":"Obere Hauptstr. 2",
    "sg:city":"Eching",
    "sg:phone":"+49 89/3790796",
    "sg:postcode":"85386",
    "sg:province":"Bayern",
    "wof:name":"Omron Electronics Gmbh",
    "wof:placetype":"venue"
},
  "geometry": {"coordinates":[11.6206321716,48.2964897156],"type":"Point"}
}