{
  "type": "Feature",
  "properties": {
    "iso:country":"DE",
    "sg:address":"Irlham",
    "sg:city":"Babensham",
    "sg:phone":"+49 8071/50818",
    "sg:postcode":"83547",
    "sg:province":"Bayern",
    "wof:name":"Troadkastn",
    "wof:placetype":"venue"
},
  "geometry": {"coordinates":[12.3037147522,48.1042785645],"type":"Point"}
}