{
  "type": "Feature",
  "properties": {
    "iso:country":"DE",
    "sg:address":"H\u00f6henried 1",
    "sg:city":"Bernried",
    "sg:postcode":"82347",
    "sg:province":"Bayern",
    "wof:name":"Klinik H\u00f6henried Ggmbh Der Lva Oberbayern",
    "wof:placetype":"venue"
},
  "geometry": {"coordinates":[11.2924699783,47.8672332764],"type":"Point"}
}