{
  "type": "Feature",
  "properties": {
    "iso:country":"DE",
    "sg:address":"Kleiner Bruchweg 11",
    "sg:city":"B\u00fcnde",
    "sg:phone":"+49 5223/15049",
    "sg:postcode":"32257",
    "sg:province":"Nordrhein-Westfalen",
    "wof:name":"B\u00fcnder Dental Labor Gmbh",
    "wof:placetype":"venue"
},
  "geometry": {"coordinates":[8.5780754089,52.1996154785],"type":"Point"}
}