{
  "type": "Feature",
  "properties": {
    "iso:country":"DE",
    "sg:address":"Winterstr. 5",
    "sg:city":"M\u00fcnchen",
    "sg:phone":"+49 89/656022",
    "sg:postcode":"81543",
    "sg:province":"Bayern",
    "wof:name":"Ps Soft Computer Vertriebs Gmbh",
    "wof:placetype":"venue"
},
  "geometry": {"coordinates":[11.5717563629,48.1153678894],"type":"Point"}
}