{
  "type": "Feature",
  "properties": {
    "iso:country":"DE",
    "sg:address":"Schlo\u00dfstr. 35",
    "sg:city":"Velbert",
    "sg:phone":"+49 2051/4285",
    "sg:postcode":"42551",
    "sg:province":"Nordrhein-Westfalen",
    "wof:name":"Altenhof Und Br\u00fcninghaus Rechtsanw\u00e4lte",
    "wof:placetype":"venue"
},
  "geometry": {"coordinates":[7.0416750908,51.3444213867],"type":"Point"}
}