{
  "type": "Feature",
  "properties": {
    "iso:country":"DE",
    "sg:address":"Calbesche Str. 1",
    "sg:city":"Sta\u00dffurt",
    "sg:postcode":"39418",
    "sg:province":"Sachsen-Anhalt",
    "wof:name":"S. Wei\u00dfmann Immobilienmakler",
    "wof:placetype":"venue"
},
  "geometry": {"coordinates":[11.5899820328,51.8573646545],"type":"Point"}
}