{
  "type": "Feature",
  "properties": {
    "iso:country":"DE",
    "sg:address":"Bergfrede 44",
    "sg:city":"Hamminkeln",
    "sg:phone":"+49 2852/2306",
    "sg:postcode":"46499",
    "sg:province":"Nordrhein-Westfalen",
    "wof:name":"J. Kleinfeld Antiquit\u00e4ten",
    "wof:placetype":"venue"
},
  "geometry": {"coordinates":[6.594038,51.727573],"type":"Point"}
}