{
  "type": "Feature",
  "properties": {
    "iso:country":"DE",
    "sg:address":"Deelwisch 27 b",
    "sg:city":"Hamburg",
    "sg:phone":"+49 40/587410",
    "sg:postcode":"22529",
    "sg:province":"Hamburg",
    "wof:name":"K.-h. Rohde",
    "wof:placetype":"venue"
},
  "geometry": {"coordinates":[9.9393882751,53.6034049988],"type":"Point"}
}