{
  "type": "Feature",
  "properties": {
    "iso:country":"DE",
    "sg:address":"S\u00f6lling 8",
    "sg:city":"B\u00fcchlberg",
    "sg:phone":"+49 8582/8384",
    "sg:postcode":"94124",
    "sg:province":"Bayern",
    "wof:name":"K. Und Th. Bruckner Bau Gmbh",
    "wof:placetype":"venue"
},
  "geometry": {"coordinates":[13.547763,48.703159],"type":"Point"}
}