{
  "type": "Feature",
  "properties": {
    "iso:country":"DE",
    "sg:address":"Welschinger Str. 4",
    "sg:city":"Hilzingen",
    "sg:phone":"+49 7739/203",
    "sg:postcode":"78247",
    "sg:province":"Baden-W\u00fcrttemberg",
    "wof:name":"Herbert Gohl",
    "wof:placetype":"venue"
},
  "geometry": {"coordinates":[8.768095,47.801498],"type":"Point"}
}