{
  "type": "Feature",
  "properties": {
    "iso:country":"DE",
    "sg:address":"Im Buchenhain 25",
    "sg:city":"Langen",
    "sg:phone":"+49 6103/71802",
    "sg:postcode":"63225",
    "sg:province":"Hessen",
    "wof:name":"Heinz Frigger Patentanwalt",
    "wof:placetype":"venue"
},
  "geometry": {"coordinates":[8.6398439407,49.9890899658],"type":"Point"}
}