{
  "type": "Feature",
  "properties": {
    "iso:country":"DE",
    "sg:address":"Hauptstr. 99",
    "sg:city":"Elzach",
    "sg:phone":"+49 7682/385",
    "sg:postcode":"79215",
    "sg:province":"Baden-W\u00fcrttemberg",
    "wof:name":"Stadtwerke Elzach",
    "wof:placetype":"venue"
},
  "geometry": {"coordinates":[8.073066,48.176666],"type":"Point"}
}