{
  "type": "Feature",
  "properties": {
    "iso:country":"DE",
    "sg:address":"Bremerhavener Str. 243",
    "sg:city":"Bremen",
    "sg:postcode":"28237",
    "sg:province":"Bremen",
    "wof:name":"Alendo Internet Solutions",
    "wof:placetype":"venue"
},
  "geometry": {"coordinates":[8.7650566101,53.1078987122],"type":"Point"}
}