{
  "type": "Feature",
  "properties": {
    "iso:country":"DE",
    "sg:address":"Friedrich-Ebert-Str. 8",
    "sg:city":"Waldkirch",
    "sg:phone":"+49 7681/6193",
    "sg:postcode":"79183",
    "sg:province":"Baden-W\u00fcrttemberg",
    "wof:name":"K. Baumer",
    "wof:placetype":"venue"
},
  "geometry": {"coordinates":[7.971834,48.106968],"type":"Point"}
}