{
  "type": "Feature",
  "properties": {
    "iso:country":"DE",
    "sg:address":"Friedrich-Ebert-Str. 30",
    "sg:city":"Schwandorf",
    "sg:phone":"+49 9431/3244",
    "sg:postcode":"92421",
    "sg:province":"Bayern",
    "wof:name":"Kindermoden Max & Moritz Gmbh",
    "wof:placetype":"venue"
},
  "geometry": {"coordinates":[12.1085863113,49.3273468018],"type":"Point"}
}