{
  "type": "Feature",
  "properties": {
    "iso:country":"DE",
    "sg:address":"Geschwister-Scholl-Str. 13",
    "sg:city":"Dingelst\u00e4dt",
    "sg:phone":"+49 36075/62261",
    "sg:postcode":"37351",
    "sg:province":"Th\u00fcringen",
    "wof:name":"W. Kirchner",
    "wof:placetype":"venue"
},
  "geometry": {"coordinates":[10.317565,51.314922],"type":"Point"}
}