{
  "type": "Feature",
  "properties": {
    "iso:country":"DE",
    "sg:address":"Im Rabennest 5",
    "sg:city":"Steinfurt",
    "sg:phone":"+49 2552/1313",
    "sg:postcode":"48565",
    "sg:province":"Nordrhein-Westfalen",
    "wof:name":"Dr. Heinz Raming Rechtsanwalt",
    "wof:placetype":"venue"
},
  "geometry": {"coordinates":[7.3802390099,52.1257629395],"type":"Point"}
}