{
  "type": "Feature",
  "properties": {
    "iso:country":"DE",
    "sg:address":"Nordstr. 17",
    "sg:city":"Herford",
    "sg:phone":"+49 5221/51919",
    "sg:postcode":"32051",
    "sg:province":"Nordrhein-Westfalen",
    "wof:name":"Adolf & J\u00fcrgen Ortmann Baugesellschaft Mbh",
    "wof:placetype":"venue"
},
  "geometry": {"coordinates":[8.6726102829,52.1266593933],"type":"Point"}
}