{
  "type": "Feature",
  "properties": {
    "iso:country":"DE",
    "sg:address":"Siendorfer Weg 12",
    "sg:city":"R\u00f6dinghausen",
    "sg:phone":"+49 5746/1516",
    "sg:postcode":"32289",
    "sg:province":"Nordrhein-Westfalen",
    "wof:name":"Andreas Schuster",
    "wof:placetype":"venue"
},
  "geometry": {"coordinates":[8.5134372711,52.2414131165],"type":"Point"}
}