{
  "type": "Feature",
  "properties": {
    "iso:country":"DE",
    "sg:address":"Hohenstadt",
    "sg:city":"Abtsgm\u00fcnd",
    "sg:phone":"+49 7366/919108",
    "sg:postcode":"73453",
    "sg:province":"Baden-W\u00fcrttemberg",
    "wof:name":"W. Brenner",
    "wof:placetype":"venue"
},
  "geometry": {"coordinates":[9.961094,48.886452],"type":"Point"}
}