{
  "type": "Feature",
  "properties": {
    "iso:country":"DE",
    "sg:address":"Am Weidenbach 3",
    "sg:city":"Weilheim",
    "sg:phone":"+49 881/6850",
    "sg:postcode":"82362",
    "sg:province":"Bayern",
    "wof:name":"Sanbloc Gmbh",
    "wof:placetype":"venue"
},
  "geometry": {"coordinates":[11.1614637375,47.8320922852],"type":"Point"}
}