{
  "type": "Feature",
  "properties": {
    "iso:country":"DE",
    "sg:address":"Hauptstr. 4",
    "sg:city":"Sche\u00dflitz",
    "sg:phone":"+49 9542/8812",
    "sg:postcode":"96110",
    "sg:province":"Bayern",
    "wof:name":"Christel Elzenbeck",
    "wof:placetype":"venue"
},
  "geometry": {"coordinates":[11.0307474136,49.9757118225],"type":"Point"}
}