{
  "type": "Feature",
  "properties": {
    "iso:country":"DE",
    "sg:address":"Eduard-Weitsch-Weg 27",
    "sg:city":"Marl",
    "sg:phone":"+49 2365/63380",
    "sg:postcode":"45768",
    "sg:province":"Nordrhein-Westfalen",
    "wof:name":"Hallenbad",
    "wof:placetype":"venue"
},
  "geometry": {"coordinates":[7.0965929031,51.6584854126],"type":"Point"}
}