{
  "type": "Feature",
  "properties": {
    "iso:country":"DE",
    "sg:address":"Eppendorfer Str. 8",
    "sg:city":"Bochum",
    "sg:phone":"+49 2327/74763",
    "sg:postcode":"44869",
    "sg:province":"Nordrhein-Westfalen",
    "wof:name":"G. Fischer Masseur",
    "wof:placetype":"venue"
},
  "geometry": {"coordinates":[7.172814,51.455956],"type":"Point"}
}