{
  "type": "Feature",
  "properties": {
    "iso:country":"DE",
    "sg:address":"Margaretenstr 3",
    "sg:city":"Pirmasens",
    "sg:phone":"+49 6331/79983",
    "sg:postcode":"66955",
    "sg:province":"Rheinland-Pfalz",
    "wof:name":"Wikule Kunst- Und Lederverarbeitung",
    "wof:placetype":"venue"
},
  "geometry": {"coordinates":[7.600337,49.196014],"type":"Point"}
}