{
  "type": "Feature",
  "properties": {
    "iso:country":"DE",
    "sg:address":"Handelsstr. 13",
    "sg:city":"Eppelheim",
    "sg:phone":"+49 4962/217960",
    "sg:postcode":"69214",
    "sg:province":"Baden-W\u00fcrttemberg",
    "wof:name":"Apm Alpha Print Medien Ag",
    "wof:placetype":"venue"
},
  "geometry": {"coordinates":[8.6270637512,49.4081993103],"type":"Point"}
}