{
  "type": "Feature",
  "properties": {
    "iso:country":"DE",
    "sg:address":"Irma-Stern-Str. 1",
    "sg:city":"Schwarza",
    "sg:phone":"+49 36843/70405",
    "sg:postcode":"98547",
    "sg:province":"Th\u00fcringen",
    "wof:name":"Ulrich Walther",
    "wof:placetype":"venue"
},
  "geometry": {"coordinates":[10.5314855576,50.6184768677],"type":"Point"}
}