{
  "type": "Feature",
  "properties": {
    "iso:country":"DE",
    "sg:address":"Am Vogelherd 14",
    "sg:city":"Germering",
    "sg:phone":"+49 89/8418833",
    "sg:postcode":"82110",
    "sg:province":"Bayern",
    "wof:name":"Galerie Pompadour",
    "wof:placetype":"venue"
},
  "geometry": {"coordinates":[11.366276741,48.1180152893],"type":"Point"}
}