{
  "type": "Feature",
  "properties": {
    "iso:country":"DE",
    "sg:address":"Luisenstr. 8",
    "sg:city":"Kassel",
    "sg:phone":"+49 561/14848",
    "sg:postcode":"34119",
    "sg:province":"Hessen",
    "wof:name":"E. G\u00fclmez",
    "wof:placetype":"venue"
},
  "geometry": {"coordinates":[9.4751739502,51.3133621216],"type":"Point"}
}