{
  "type": "Feature",
  "properties": {
    "iso:country":"DE",
    "sg:address":"Hochfellnstr. 7",
    "sg:city":"Prien",
    "sg:phone":"+49 8051/309995",
    "sg:postcode":"83209",
    "sg:province":"Bayern",
    "wof:name":"Werner Hartwig",
    "wof:placetype":"venue"
},
  "geometry": {"coordinates":[12.3464136124,47.8520088196],"type":"Point"}
}