{
  "type": "Feature",
  "properties": {
    "iso:country":"DE",
    "sg:address":"Wasserbilliger Str. 73",
    "sg:city":"Trier",
    "sg:phone":"+49 651/85194",
    "sg:postcode":"54294",
    "sg:province":"Rheinland-Pfalz",
    "wof:name":"Walter Mertesdorf",
    "wof:placetype":"venue"
},
  "geometry": {"coordinates":[6.5725121498,49.7136230469],"type":"Point"}
}