{
  "type": "Feature",
  "properties": {
    "iso:country":"DE",
    "sg:address":"Robert-Bosch-Breite 3 POSTFACH 1533",
    "sg:city":"G\u00f6ttingen",
    "sg:phone":"+49 4955/16030",
    "sg:postcode":"37005",
    "sg:province":"Niedersachsen",
    "wof:name":"Robert Bosch Gmbh",
    "wof:placetype":"venue"
},
  "geometry": {"coordinates":[9.8962154388,51.5482444763],"type":"Point"}
}