{
  "type": "Feature",
  "properties": {
    "iso:country":"DE",
    "sg:address":"Hau\u00dfmannstr. 122 A",
    "sg:city":"Stuttgart",
    "sg:phone":"+49 711/260227",
    "sg:postcode":"70188",
    "sg:province":"Baden-W\u00fcrttemberg",
    "wof:name":"Nat\u00fcrlich Wohnen Biologische Farben",
    "wof:placetype":"venue"
},
  "geometry": {"coordinates":[9.200313,48.785233],"type":"Point"}
}