{
  "type": "Feature",
  "properties": {
    "iso:country":"DE",
    "sg:address":"Parkallee 19",
    "sg:city":"Hamburg",
    "sg:phone":"+49 40/4500434",
    "sg:postcode":"20144",
    "sg:province":"Hamburg",
    "wof:name":"Irion Und Miras Rechtsanwalt",
    "wof:placetype":"venue"
},
  "geometry": {"coordinates":[9.9837284088,53.5748405457],"type":"Point"}
}