{
  "type": "Feature",
  "properties": {
    "iso:country":"DE",
    "sg:address":"ABC-Str. 14",
    "sg:city":"Wismar",
    "sg:postcode":"23966",
    "sg:province":"Mecklenburg-Vorpommern",
    "wof:name":"Helmut Grabarzyk",
    "wof:placetype":"venue"
},
  "geometry": {"coordinates":[11.4661464691,53.8910751343],"type":"Point"}
}