{
  "type": "Feature",
  "properties": {
    "iso:country":"DE",
    "sg:address":"Jahnstr. 4",
    "sg:city":"Kulmain",
    "sg:phone":"+49 9642/1325",
    "sg:postcode":"95508",
    "sg:province":"Bayern",
    "wof:name":"A. V\u00f6lkl Tabakwarenhdl.",
    "wof:placetype":"venue"
},
  "geometry": {"coordinates":[11.8926868439,49.8979721069],"type":"Point"}
}