{
  "type": "Feature",
  "properties": {
    "iso:country":"DE",
    "sg:address":"H\u00f6rsten 3a",
    "sg:city":"Neuenkirchen-V\u00f6rden",
    "sg:postcode":"49434",
    "sg:province":"Niedersachsen",
    "wof:name":"Pohlmann Nellinghof Gmbh & Co. Kg",
    "wof:placetype":"venue"
},
  "geometry": {"coordinates":[8.088249,52.486782],"type":"Point"}
}