{
  "type": "Feature",
  "properties": {
    "iso:country":"DE",
    "sg:address":"Postweg 3",
    "sg:city":"Verden",
    "sg:phone":"+49 4231/3459",
    "sg:postcode":"27283",
    "sg:province":"Niedersachsen",
    "wof:name":"Vertrauens\u00e4rztlicher-dienst D. Lva Hannover",
    "wof:placetype":"venue"
},
  "geometry": {"coordinates":[9.2364606857,52.9209442139],"type":"Point"}
}