{
  "type": "Feature",
  "properties": {
    "iso:country":"DE",
    "sg:address":"Erfurter Weg 2",
    "sg:city":"Osterode",
    "sg:phone":"+49 5522/3543",
    "sg:postcode":"37520",
    "sg:province":"Niedersachsen",
    "wof:name":"Ev. Pfarramt Kreuzkirche",
    "wof:placetype":"venue"
},
  "geometry": {"coordinates":[10.3089799881,51.6765785217],"type":"Point"}
}