{
  "type": "Feature",
  "properties": {
    "iso:country":"DE",
    "sg:address":"Sperberstr. 16",
    "sg:city":"Oberkochen",
    "sg:phone":"+49 7364/8433",
    "sg:postcode":"73447",
    "sg:province":"Baden-W\u00fcrttemberg",
    "wof:name":"Franz Bischof",
    "wof:placetype":"venue"
},
  "geometry": {"coordinates":[10.0975522995,48.7844085693],"type":"Point"}
}