{
  "type": "Feature",
  "properties": {
    "iso:country":"DE",
    "sg:address":"H\u00f6henweg 17",
    "sg:city":"Bad Nauheim",
    "sg:phone":"+49 6032/4353",
    "sg:postcode":"61231",
    "sg:province":"Hessen",
    "wof:name":"Herbert Metzendorf Steuerberater",
    "wof:placetype":"venue"
},
  "geometry": {"coordinates":[8.7319831848,50.3657493591],"type":"Point"}
}