{
  "type": "Feature",
  "properties": {
    "iso:country":"DE",
    "sg:address":"Am Stadtwald 21",
    "sg:city":"Plauen",
    "sg:phone":"+49 3741/558220",
    "sg:postcode":"08525",
    "sg:province":"Sachsen",
    "wof:name":"K & R Stahlbau Gmbh",
    "wof:placetype":"venue"
},
  "geometry": {"coordinates":[12.1239175797,50.5180206299],"type":"Point"}
}