{
  "type": "Feature",
  "properties": {
    "iso:country":"DE",
    "sg:address":"Dargetzow 2. Wendung 27",
    "sg:city":"Wismar",
    "sg:phone":"+49 3841/250220",
    "sg:postcode":"23970",
    "sg:province":"Mecklenburg-Vorpommern",
    "wof:name":"Ulrich Und Gabriela Kuss",
    "wof:placetype":"venue"
},
  "geometry": {"coordinates":[11.5064888,53.8950233459],"type":"Point"}
}