{
  "type": "Feature",
  "properties": {
    "iso:country":"DE",
    "sg:address":"Eschersheimer Landstr. 388",
    "sg:city":"Frankfurt",
    "sg:phone":"+49 69/512301",
    "sg:postcode":"60433",
    "sg:province":"Hessen",
    "wof:name":"Restaurant Scheune",
    "wof:placetype":"venue"
},
  "geometry": {"coordinates":[8.6662578583,50.1483688354],"type":"Point"}
}