{
  "type": "Feature",
  "properties": {
    "iso:country":"DE",
    "sg:address":"Franz-Ludwig-Str. 5 a",
    "sg:city":"Bamberg",
    "sg:phone":"+49 951/22847",
    "sg:postcode":"96047",
    "sg:province":"Bayern",
    "wof:name":"Sandyk-gastst\u00e4ttenbetriebe Josef Sandyk",
    "wof:placetype":"venue"
},
  "geometry": {"coordinates":[10.8908662796,49.8935508728],"type":"Point"}
}