{
  "type": "Feature",
  "properties": {
    "iso:country":"DE",
    "sg:address":"Deisterstr. 28",
    "sg:city":"Hannover",
    "sg:phone":"+49 511/443141",
    "sg:postcode":"30449",
    "sg:province":"Niedersachsen",
    "wof:name":"Restaurant Fernost",
    "wof:placetype":"venue"
},
  "geometry": {"coordinates":[9.7190542221,52.3659591675],"type":"Point"}
}