{
  "type": "Feature",
  "properties": {
    "iso:country":"DE",
    "sg:address":"Br\u00fcckenstr. 3",
    "sg:city":"Schliengen",
    "sg:phone":"+49 7635/1769",
    "sg:postcode":"79418",
    "sg:province":"Baden-W\u00fcrttemberg",
    "wof:name":"H. Scheider",
    "wof:placetype":"venue"
},
  "geometry": {"coordinates":[7.6309380531,47.754535675],"type":"Point"}
}