{
  "type": "Feature",
  "properties": {
    "iso:country":"DE",
    "sg:address":"Hertigswalde 4",
    "sg:city":"Sebnitz",
    "sg:phone":"+49 35971/53688",
    "sg:postcode":"01855",
    "sg:province":"Sachsen",
    "wof:name":"G\u00fcnter Dittrich Inh. G. Winter",
    "wof:placetype":"venue"
},
  "geometry": {"coordinates":[14.271711,50.97039],"type":"Point"}
}