{
  "type": "Feature",
  "properties": {
    "iso:country":"DE",
    "sg:address":"H\u00f6ltenweg 123",
    "sg:city":"M\u00fcnster",
    "sg:phone":"+49 251/624864",
    "sg:postcode":"48155",
    "sg:province":"Nordrhein-Westfalen",
    "wof:name":"Heinrich Diekmann Inh. Ludger Diekmann",
    "wof:placetype":"venue"
},
  "geometry": {"coordinates":[7.657097,51.922268],"type":"Point"}
}