{
  "type": "Feature",
  "properties": {
    "iso:country":"DE",
    "sg:address":"Mittelstr. 5",
    "sg:city":"Emmerthal",
    "sg:phone":"+49 5157/286",
    "sg:postcode":"31860",
    "sg:province":"Niedersachsen",
    "wof:name":"Richard Niebisch",
    "wof:placetype":"venue"
},
  "geometry": {"coordinates":[9.514443,52.025578],"type":"Point"}
}