{
  "type": "Feature",
  "properties": {
    "iso:country":"DE",
    "sg:address":"Schulstr. 5",
    "sg:city":"Oelde",
    "sg:phone":"+49 2529/948080",
    "sg:postcode":"59302",
    "sg:province":"Nordrhein-Westfalen",
    "wof:name":"Schlesiger Gmbh",
    "wof:placetype":"venue"
},
  "geometry": {"coordinates":[8.2070789337,51.8016014099],"type":"Point"}
}