{
  "type": "Feature",
  "properties": {
    "iso:country":"DE",
    "sg:address":"Obergasse 42",
    "sg:city":"Greifenstein",
    "sg:phone":"+49 6449/6142",
    "sg:postcode":"35753",
    "sg:province":"Hessen",
    "wof:name":"Harry Strittmatter",
    "wof:placetype":"venue"
},
  "geometry": {"coordinates":[8.285415,50.621925],"type":"Point"}
}