{
  "type": "Feature",
  "properties": {
    "iso:country":"DE",
    "sg:address":"D\u00fcppelstr. 6",
    "sg:city":"K\u00f6ln",
    "sg:phone":"+49 221/811646",
    "sg:postcode":"50679",
    "sg:province":"Nordrhein-Westfalen",
    "wof:name":"Dr. C. Misere Rechtsanwalt",
    "wof:placetype":"venue"
},
  "geometry": {"coordinates":[6.9746317863,50.9371261597],"type":"Point"}
}