{
  "type": "Feature",
  "properties": {
    "iso:country":"DE",
    "sg:address":"Lortzingstr. 12",
    "sg:city":"Saarbr\u00fccken",
    "sg:phone":"+49 681/31993",
    "sg:postcode":"66111",
    "sg:province":"Saarland",
    "wof:name":"Rvi Kapitalanlage- Vertriebsgesellschaft Mbh",
    "wof:placetype":"venue"
},
  "geometry": {"coordinates":[6.9955711365,49.2371711731],"type":"Point"}
}