{
  "type": "Feature",
  "properties": {
    "iso:country":"DE",
    "sg:address":"Moorhof 12",
    "sg:city":"Berkenthin",
    "sg:postcode":"23919",
    "sg:province":"Schleswig-Holstein",
    "wof:name":"B + L Gmbh & Co. Kg",
    "wof:placetype":"venue"
},
  "geometry": {"coordinates":[10.6374988556,53.730091095],"type":"Point"}
}