{
  "type": "Feature",
  "properties": {
    "iso:country":"DE",
    "sg:address":"Traberhofstr. 49",
    "sg:city":"Rosenheim",
    "sg:phone":"+49 8031/66112",
    "sg:postcode":"83026",
    "sg:province":"Bayern",
    "wof:name":"Max R\u00f6ckl",
    "wof:placetype":"venue"
},
  "geometry": {"coordinates":[12.1293172836,47.8419914246],"type":"Point"}
}