{
  "type": "Feature",
  "properties": {
    "iso:country":"DE",
    "sg:address":"Tergaster Str. 12 a",
    "sg:city":"Moormerland",
    "sg:phone":"+49 4924/393",
    "sg:postcode":"26802",
    "sg:province":"Niedersachsen",
    "wof:name":"Pommer Ohg",
    "wof:placetype":"venue"
},
  "geometry": {"coordinates":[7.3442687988,53.3274459839],"type":"Point"}
}