{
  "type": "Feature",
  "properties": {
    "iso:country":"DE",
    "sg:address":"Reeser Str. 89",
    "sg:city":"Emmerich",
    "sg:phone":"+49 2822/2272",
    "sg:postcode":"46446",
    "sg:province":"Nordrhein-Westfalen",
    "wof:name":"Teppich-j\u00e4ger Gmbh",
    "wof:placetype":"venue"
},
  "geometry": {"coordinates":[6.2688751221,51.8318328857],"type":"Point"}
}