{
  "type": "Feature",
  "properties": {
    "iso:country":"DE",
    "sg:address":"D\u00fcbener Landstr.",
    "sg:city":"M\u00f6rtitz",
    "sg:phone":"+49 3423/759290",
    "sg:postcode":"04838",
    "sg:province":"Sachsen",
    "wof:name":"Ws Kies- Und Sandwerke Gmbh",
    "wof:placetype":"venue"
},
  "geometry": {"coordinates":[12.6260662079,51.49376297],"type":"Point"}
}