{
  "type": "Feature",
  "properties": {
    "iso:country":"DE",
    "sg:address":"K\u00e4ppele 15",
    "sg:city":"Kusterdingen",
    "sg:phone":"+49 7071/38313",
    "sg:postcode":"72127",
    "sg:province":"Baden-W\u00fcrttemberg",
    "wof:name":"Bht Gesellschaft F\u00fcr Verfahrenstechnik Mbh",
    "wof:placetype":"venue"
},
  "geometry": {"coordinates":[9.098259,48.496559],"type":"Point"}
}