{
  "type": "Feature",
  "properties": {
    "iso:country":"DE",
    "sg:address":"Postreitweg 103",
    "sg:city":"Essen",
    "sg:phone":"+49 201/225185",
    "sg:postcode":"45145",
    "sg:province":"Nordrhein-Westfalen",
    "wof:name":"Theater Und Konzertb\u00fcro",
    "wof:placetype":"venue"
},
  "geometry": {"coordinates":[6.960323,51.44569],"type":"Point"}
}