{
  "type": "Feature",
  "properties": {
    "iso:country":"DE",
    "sg:address":"Rudolf-Diesel-Str. 49",
    "sg:city":"Walldorf",
    "sg:phone":"+49 6227/82300",
    "sg:postcode":"69190",
    "sg:province":"Baden-W\u00fcrttemberg",
    "wof:name":"Bsb Seidler Gmbh",
    "wof:placetype":"venue"
},
  "geometry": {"coordinates":[8.649046,49.288872],"type":"Point"}
}