{
  "type": "Feature",
  "properties": {
    "iso:country":"DE",
    "sg:address":"Spiegelberg 2",
    "sg:city":"Wittenburg",
    "sg:phone":"+49 38852/52772",
    "sg:postcode":"19243",
    "sg:province":"Mecklenburg-Vorpommern",
    "wof:name":"L\u00f6wen-apotheke",
    "wof:placetype":"venue"
},
  "geometry": {"coordinates":[11.07168,53.511971],"type":"Point"}
}