{
  "type": "Feature",
  "properties": {
    "iso:country":"DE",
    "sg:address":"Karl-Marx-Allee 86",
    "sg:city":"Berlin",
    "sg:phone":"+49 30/29491123",
    "sg:postcode":"10243",
    "sg:province":"Berlin",
    "wof:name":"Norbert Bogedein",
    "wof:placetype":"venue"
},
  "geometry": {"coordinates":[13.4392824173,52.5170402527],"type":"Point"}
}