{
  "type": "Feature",
  "properties": {
    "iso:country":"DE",
    "sg:address":"Vulhopsweg 48",
    "sg:city":"Lohne",
    "sg:phone":"+49 4442/3387",
    "sg:postcode":"49393",
    "sg:province":"Niedersachsen",
    "wof:name":"Friedrich S\u00fcdkamp",
    "wof:placetype":"venue"
},
  "geometry": {"coordinates":[8.23482,52.675625],"type":"Point"}
}