{
  "type": "Feature",
  "properties": {
    "iso:country":"DE",
    "sg:address":"Esenser Str. 58",
    "sg:city":"Aurich",
    "sg:phone":"+49 4941/3635",
    "sg:postcode":"26603",
    "sg:province":"Niedersachsen",
    "wof:name":"Antje Und Rudolf Meinen",
    "wof:placetype":"venue"
},
  "geometry": {"coordinates":[7.487339,53.478104],"type":"Point"}
}