{
  "type": "Feature",
  "properties": {
    "iso:country":"DE",
    "sg:address":"Beuthstr. 51",
    "sg:city":"Berlin",
    "sg:phone":"+49 30/47487800",
    "sg:postcode":"13156",
    "sg:province":"Berlin",
    "wof:name":"Andreas Bohmann Ergotherapiepraxis",
    "wof:placetype":"venue"
},
  "geometry": {"coordinates":[13.403288,52.585709],"type":"Point"}
}