{
  "type": "Feature",
  "properties": {
    "iso:country":"DE",
    "sg:address":"N\u00fcrnberger Str. 63",
    "sg:city":"W\u00fcrzburg",
    "sg:postcode":"97076",
    "sg:province":"Bayern",
    "wof:name":"Bernhard Service F\u00fcr Schlemmer Gastronomiebetriebe",
    "wof:placetype":"venue"
},
  "geometry": {"coordinates":[9.982732,49.796558],"type":"Point"}
}