{
  "type": "Feature",
  "properties": {
    "iso:country":"DE",
    "sg:address":"Industriestr. 53",
    "sg:city":"Bielefeld",
    "sg:phone":"+49 5205/91490",
    "sg:postcode":"33689",
    "sg:province":"Nordrhein-Westfalen",
    "wof:name":"Reckhaus Gmbh",
    "wof:placetype":"venue"
},
  "geometry": {"coordinates":[8.5834236145,51.9598426819],"type":"Point"}
}