{
  "type": "Feature",
  "properties": {
    "iso:country":"DE",
    "sg:address":"Lerchenweg 14",
    "sg:city":"Owschlag",
    "sg:postcode":"24811",
    "sg:province":"Schleswig-Holstein",
    "wof:name":"Institut Deutsche Adelsforschung",
    "wof:placetype":"venue"
},
  "geometry": {"coordinates":[9.592071,54.397205],"type":"Point"}
}