{
  "type": "Feature",
  "properties": {
    "iso:country":"DE",
    "sg:address":"Feld Strasse 47",
    "sg:city":"Uetersen",
    "sg:phone":"+49 4122/47191",
    "sg:postcode":"25436",
    "sg:province":"Schleswig-Holstein",
    "wof:name":"T\u00fcrkei-immobilien",
    "wof:placetype":"venue"
},
  "geometry": {"coordinates":[9.6594781876,53.6870117188],"type":"Point"}
}