{
  "type": "Feature",
  "properties": {
    "iso:country":"DE",
    "sg:address":"Hopmannstr.2",
    "sg:city":"Bonn",
    "sg:postcode":"53177",
    "sg:province":"Nordrhein-Westfalen",
    "wof:name":"Hotelworld International Weltweites Hotelverzeichnis",
    "wof:placetype":"venue"
},
  "geometry": {"coordinates":[7.1556210518,50.6745834351],"type":"Point"}
}