{
  "type": "Feature",
  "properties": {
    "iso:country":"DE",
    "sg:address":"In der Pfarrsiedlung 1",
    "sg:city":"L\u00f6hne",
    "sg:postcode":"32584",
    "sg:province":"Nordrhein-Westfalen",
    "wof:name":"Budde Immobilien Gmbh & Co. Kg",
    "wof:placetype":"venue"
},
  "geometry": {"coordinates":[8.7263317108,52.2145957947],"type":"Point"}
}