{
  "type": "Feature",
  "properties": {
    "iso:country":"DE",
    "sg:address":"Raiffeisenstr 5",
    "sg:city":"Bottrop",
    "sg:phone":"+49 2045/89030",
    "sg:postcode":"46244",
    "sg:province":"Nordrhein-Westfalen",
    "wof:name":"Ibk Wiesehahn Gmbh",
    "wof:placetype":"venue"
},
  "geometry": {"coordinates":[6.93305,51.61068],"type":"Point"}
}