{
  "type": "Feature",
  "properties": {
    "iso:country":"DE",
    "sg:address":"T\u00fcnzhausen 15",
    "sg:city":"Allershausen",
    "sg:phone":"+49 8166/9437",
    "sg:postcode":"85391",
    "sg:province":"Bayern",
    "wof:name":"Josef Nieder",
    "wof:placetype":"venue"
},
  "geometry": {"coordinates":[11.598925,48.431145],"type":"Point"}
}