{
  "type": "Feature",
  "properties": {
    "iso:country":"DE",
    "sg:address":"Kaiserstr. 3",
    "sg:city":"M\u00fcnchen",
    "sg:phone":"+49 89/338631",
    "sg:postcode":"80801",
    "sg:province":"Bayern",
    "wof:name":"Arboga Produktionstechnik Vertriebs-gmbh",
    "wof:placetype":"venue"
},
  "geometry": {"coordinates":[11.585185051,48.1603355408],"type":"Point"}
}