{
  "type": "Feature",
  "properties": {
    "iso:country":"DE",
    "sg:address":"Lange Str. 1",
    "sg:city":"H\u00fcpstedt",
    "sg:phone":"+49 36026/90605",
    "sg:postcode":"99976",
    "sg:province":"Th\u00fcringen",
    "wof:name":"Heinz-georg Morgenthal",
    "wof:placetype":"venue"
},
  "geometry": {"coordinates":[10.442194,51.325005],"type":"Point"}
}