{
  "type": "Feature",
  "properties": {
    "iso:country":"DE",
    "sg:address":"Carl-Sch\u00fcller-Str. 29",
    "sg:city":"Bayreuth",
    "sg:phone":"+49 921/20908",
    "sg:postcode":"95444",
    "sg:province":"Bayern",
    "wof:name":"Irmhild Berg",
    "wof:placetype":"venue"
},
  "geometry": {"coordinates":[11.573791,49.949699],"type":"Point"}
}