{
  "type": "Feature",
  "properties": {
    "iso:country":"DE",
    "sg:address":"Industriestr. 5",
    "sg:city":"Rugendorf",
    "sg:phone":"+49 9223/9750",
    "sg:postcode":"95365",
    "sg:province":"Bayern",
    "wof:name":"Manfred Schmidt-hofmann Transporte",
    "wof:placetype":"venue"
},
  "geometry": {"coordinates":[11.4630098343,50.2032279968],"type":"Point"}
}