{
  "type": "Feature",
  "properties": {
    "iso:country":"DE",
    "sg:address":"Nuhnestr. 12",
    "sg:city":"Winterberg",
    "sg:phone":"+49 2981/92290",
    "sg:postcode":"59955",
    "sg:province":"Nordrhein-Westfalen",
    "wof:name":"Pension Haus Nuhnetal",
    "wof:placetype":"venue"
},
  "geometry": {"coordinates":[8.5306186676,51.1928901672],"type":"Point"}
}