{
  "type": "Feature",
  "properties": {
    "iso:country":"DE",
    "sg:address":"Schmalenbach 3",
    "sg:city":"Halver",
    "sg:phone":"+49 2353/91560",
    "sg:postcode":"58553",
    "sg:province":"Nordrhein-Westfalen",
    "wof:name":"Gebr\u00fcder Mickenhagen",
    "wof:placetype":"venue"
},
  "geometry": {"coordinates":[7.4796462059,51.190700531],"type":"Point"}
}