{
  "type": "Feature",
  "properties": {
    "iso:country":"DE",
    "sg:address":"Knobelsdorffstr. 5",
    "sg:city":"Zepernick",
    "sg:phone":"+49 30/9447556",
    "sg:postcode":"16341",
    "sg:province":"Brandenburg",
    "wof:name":"J\u00f6rg Rainer M\u00fcller E. Kfm.",
    "wof:placetype":"venue"
},
  "geometry": {"coordinates":[13.5234088898,52.6662597656],"type":"Point"}
}