{
  "type": "Feature",
  "properties": {
    "iso:country":"DE",
    "sg:address":"K\u00f6lner Str. 45",
    "sg:city":"Haan",
    "sg:phone":"+49 212/950476",
    "sg:postcode":"42781",
    "sg:province":"Nordrhein-Westfalen",
    "wof:name":"Colonia 45",
    "wof:placetype":"venue"
},
  "geometry": {"coordinates":[7.0023589134,51.1875114441],"type":"Point"}
}