{
  "type": "Feature",
  "properties": {
    "iso:country":"DE",
    "sg:address":"D\u00f6ffinger Str. 101",
    "sg:city":"Sindelfingen",
    "sg:phone":"+49 7031/673733",
    "sg:postcode":"71069",
    "sg:province":"Baden-W\u00fcrttemberg",
    "wof:name":"Gasthof Sonne",
    "wof:placetype":"venue"
},
  "geometry": {"coordinates":[8.9687519073,48.7009658813],"type":"Point"}
}