{
  "type": "Feature",
  "properties": {
    "iso:country":"DE",
    "sg:address":"Nordwalder Str. 17",
    "sg:city":"Greven",
    "sg:phone":"+49 2571/3540",
    "sg:postcode":"48268",
    "sg:province":"Nordrhein-Westfalen",
    "wof:name":"Josefsklause",
    "wof:placetype":"venue"
},
  "geometry": {"coordinates":[7.5940628052,52.0927200317],"type":"Point"}
}