{
  "type": "Feature",
  "properties": {
    "iso:country":"DE",
    "sg:address":"Eichenallee 82",
    "sg:city":"Ahaus",
    "sg:phone":"+49 2561/3057",
    "sg:postcode":"48683",
    "sg:province":"Nordrhein-Westfalen",
    "wof:name":"Indopa Market Gmbh",
    "wof:placetype":"venue"
},
  "geometry": {"coordinates":[6.98444,52.101242],"type":"Point"}
}