{
  "type": "Feature",
  "properties": {
    "iso:country":"DE",
    "sg:address":"Amselweg 20",
    "sg:city":"Filderstadt",
    "sg:phone":"+49 711/771625",
    "sg:postcode":"70794",
    "sg:province":"Baden-W\u00fcrttemberg",
    "wof:name":"Edgar Frank",
    "wof:placetype":"venue"
},
  "geometry": {"coordinates":[9.192844,48.655159],"type":"Point"}
}