{
  "type": "Feature",
  "properties": {
    "iso:country":"DE",
    "sg:address":"Goethestr. 2",
    "sg:city":"Dettingen",
    "sg:phone":"+49 7021/58883",
    "sg:postcode":"73265",
    "sg:province":"Baden-W\u00fcrttemberg",
    "wof:name":"Richard Kuhn",
    "wof:placetype":"venue"
},
  "geometry": {"coordinates":[9.451876,48.61124],"type":"Point"}
}