{
  "type": "Feature",
  "properties": {
    "iso:country":"DE",
    "sg:address":"Sch\u00fctzenstr. 6",
    "sg:city":"Darmstadt",
    "sg:phone":"+49 6151/292827",
    "sg:postcode":"64283",
    "sg:province":"Hessen",
    "wof:name":"Ristorante Napoli",
    "wof:placetype":"venue"
},
  "geometry": {"coordinates":[8.6546449661,49.8703651428],"type":"Point"}
}