{
  "type": "Feature",
  "properties": {
    "iso:country":"DE",
    "sg:address":"Rudolf-Breitscheid-Str. 28",
    "sg:city":"Altentreptow",
    "sg:phone":"+49 3961/214527",
    "sg:postcode":"17087",
    "sg:province":"Mecklenburg-Vorpommern",
    "wof:name":"Bauunternehmung Altentreptow Gmbh",
    "wof:placetype":"venue"
},
  "geometry": {"coordinates":[13.2507734299,53.6903419495],"type":"Point"}
}