{
  "type": "Feature",
  "properties": {
    "iso:country":"DE",
    "sg:address":"Bahnhofstr. 98",
    "sg:city":"Ahaus",
    "sg:phone":"+49 2561/444411",
    "sg:postcode":"48683",
    "sg:province":"Nordrhein-Westfalen",
    "wof:name":"Sindbad Pizzeria",
    "wof:placetype":"venue"
},
  "geometry": {"coordinates":[7.0135860443,52.0811805725],"type":"Point"}
}