{
  "type": "Feature",
  "properties": {
    "iso:country":"DE",
    "sg:address":"Georg-Diederichs-Ring 21",
    "sg:city":"Northeim",
    "sg:phone":"+49 5551/910320",
    "sg:postcode":"37154",
    "sg:province":"Niedersachsen",
    "wof:name":"Harald Baumgarten Trenn- Und Schleifmaschinen",
    "wof:placetype":"venue"
},
  "geometry": {"coordinates":[10.001925,51.691498],"type":"Point"}
}