{
  "type": "Feature",
  "properties": {
    "iso:country":"DE",
    "sg:address":"Karl-Marx-Str. 82",
    "sg:city":"Neuruppin",
    "sg:phone":"+49 3391/650700",
    "sg:postcode":"16816",
    "sg:province":"Brandenburg",
    "wof:name":"Bernd Boller",
    "wof:placetype":"venue"
},
  "geometry": {"coordinates":[12.8064470291,52.9255027771],"type":"Point"}
}