{
  "type": "Feature",
  "properties": {
    "iso:country":"DE",
    "sg:address":"Vogtsreichenbach 5",
    "sg:city":"Cadolzburg",
    "sg:phone":"+49 9103/400",
    "sg:postcode":"90556",
    "sg:province":"Bayern",
    "wof:name":"Hans M\u00fcller",
    "wof:placetype":"venue"
},
  "geometry": {"coordinates":[10.823257,49.430023],"type":"Point"}
}