{
  "type": "Feature",
  "properties": {
    "iso:country":"DE",
    "sg:address":"Bahnhofstr. 61",
    "sg:city":"Voerde",
    "sg:phone":"+49 2855/7007",
    "sg:postcode":"46562",
    "sg:province":"Nordrhein-Westfalen",
    "wof:name":"Bernhard Feldhoff",
    "wof:placetype":"venue"
},
  "geometry": {"coordinates":[6.68166399,51.5966758728],"type":"Point"}
}