{
  "type": "Feature",
  "properties": {
    "iso:country":"DE",
    "sg:address":"Auf der Werth 19",
    "sg:city":"Saarbr\u00fccken",
    "sg:phone":"+49 681",
    "sg:postcode":"66115",
    "sg:province":"Saarland",
    "wof:name":"Weine H.freis",
    "wof:placetype":"venue"
},
  "geometry": {"coordinates":[6.979289,49.240559],"type":"Point"}
}