{
  "type": "Feature",
  "properties": {
    "iso:country":"DE",
    "sg:address":"Robert-Koch-Str. 4",
    "sg:city":"Pegnitz",
    "sg:phone":"+49 9241/8410",
    "sg:postcode":"91257",
    "sg:province":"Bayern",
    "wof:name":"Redel-bau Gmbh",
    "wof:placetype":"venue"
},
  "geometry": {"coordinates":[11.543395,49.750999],"type":"Point"}
}