{
  "type": "Feature",
  "properties": {
    "iso:country":"DE",
    "sg:address":"Loher Str. 27",
    "sg:city":"Bar\u00dfel",
    "sg:phone":"+49 4499/7648",
    "sg:postcode":"26676",
    "sg:province":"Niedersachsen",
    "wof:name":"Josef Beintken",
    "wof:placetype":"venue"
},
  "geometry": {"coordinates":[7.770948,53.166992],"type":"Point"}
}