{
  "type": "Feature",
  "properties": {
    "iso:country":"DE",
    "sg:address":"Heideblick 16",
    "sg:city":"Dortmund",
    "sg:postcode":"44229",
    "sg:province":"Nordrhein-Westfalen",
    "wof:name":"E.c.voit Architekten",
    "wof:placetype":"venue"
},
  "geometry": {"coordinates":[7.4806699753,51.4677886963],"type":"Point"}
}