{
  "type": "Feature",
  "properties": {
    "iso:country":"DE",
    "sg:address":"Weinstr. 48",
    "sg:city":"Deidesheim",
    "sg:phone":"+49 6326/6819",
    "sg:postcode":"67146",
    "sg:province":"Rheinland-Pfalz",
    "wof:name":"Olympia Restaurant",
    "wof:placetype":"venue"
},
  "geometry": {"coordinates":[8.1866760254,49.4069976807],"type":"Point"}
}