{
  "type": "Feature",
  "properties": {
    "iso:country":"DE",
    "sg:address":"Klosterstr. 35",
    "sg:city":"Worms",
    "sg:phone":"+49 4962/4190760",
    "sg:postcode":"67547",
    "sg:province":"Rheinland-Pfalz",
    "wof:name":"Rheinstahl Worms Gmbh",
    "wof:placetype":"venue"
},
  "geometry": {"coordinates":[8.360582,49.622513],"type":"Point"}
}