{
  "type": "Feature",
  "properties": {
    "iso:country":"DE",
    "sg:address":"Hansestr. 42",
    "sg:city":"M\u00f6lln",
    "sg:phone":"+49 4542/2944",
    "sg:postcode":"23879",
    "sg:province":"Schleswig-Holstein",
    "wof:name":"W. Wurr Versicherung",
    "wof:placetype":"venue"
},
  "geometry": {"coordinates":[10.6795377731,53.6092338562],"type":"Point"}
}