{
  "type": "Feature",
  "properties": {
    "iso:country":"DE",
    "sg:address":"Hauptstr. 19",
    "sg:city":"Sauerlach",
    "sg:postcode":"82054",
    "sg:province":"Bayern",
    "wof:name":"Katholisches Pfarramt St. Valentin",
    "wof:placetype":"venue"
},
  "geometry": {"coordinates":[11.6026477814,47.9614143372],"type":"Point"}
}