{
  "type": "Feature",
  "properties": {
    "iso:country":"DE",
    "sg:address":"Mittelweg 151",
    "sg:city":"Hamburg",
    "sg:phone":"+49 40/20977929",
    "sg:postcode":"20148",
    "sg:province":"Hamburg",
    "wof:name":"Gabriela Sch\u00fcnke Architektin",
    "wof:placetype":"venue"
},
  "geometry": {"coordinates":[9.995601,53.568859],"type":"Point"}
}