{
  "type": "Feature",
  "properties": {
    "iso:country":"DE",
    "sg:address":"Fallbachstr. 31",
    "sg:city":"Erlensee",
    "sg:phone":"+49 6183/2844",
    "sg:postcode":"63526",
    "sg:province":"Hessen",
    "wof:name":"Robert Kalix",
    "wof:placetype":"venue"
},
  "geometry": {"coordinates":[8.9791984558,50.166934967],"type":"Point"}
}