{
  "type": "Feature",
  "properties": {
    "iso:country":"DE",
    "sg:address":"Kaiser-Friedrich-Ring 58",
    "sg:city":"Wiesbaden",
    "sg:postcode":"65185",
    "sg:province":"Hessen",
    "wof:name":"Gewerkschaft Der Polizei Landesbez. Hessen.",
    "wof:placetype":"venue"
},
  "geometry": {"coordinates":[8.2350606918,50.0726051331],"type":"Point"}
}