{
  "type": "Feature",
  "properties": {
    "iso:country":"DE",
    "sg:address":"Trombacher Hof",
    "sg:city":"Niederstadtfeld",
    "sg:phone":"+49 6596",
    "sg:postcode":"54570",
    "sg:province":"Rheinland-Pfalz",
    "wof:name":"Reiten-secondhandshop,gebrauchte Reitsportartikel",
    "wof:placetype":"venue"
},
  "geometry": {"coordinates":[6.784175,50.163105],"type":"Point"}
}