{
  "type": "Feature",
  "properties": {
    "iso:country":"DE",
    "sg:address":"Friedrichstr. 68",
    "sg:city":"Kuppenheim",
    "sg:phone":"+49 7222/47086",
    "sg:postcode":"76456",
    "sg:province":"Baden-W\u00fcrttemberg",
    "wof:name":"W. Z\u00e4pfel",
    "wof:placetype":"venue"
},
  "geometry": {"coordinates":[8.254703,48.82869],"type":"Point"}
}