{
  "type": "Feature",
  "properties": {
    "iso:country":"DE",
    "sg:address":"Obere K\u00f6nigsstr. 8",
    "sg:city":"Kassel",
    "sg:phone":"+49 561/15928",
    "sg:postcode":"34117",
    "sg:province":"Hessen",
    "wof:name":"Ratskeller",
    "wof:placetype":"venue"
},
  "geometry": {"coordinates":[9.4927768707,51.3124923706],"type":"Point"}
}