{
  "type": "Feature",
  "properties": {
    "iso:country":"DE",
    "sg:address":"Altenstadter Str 1",
    "sg:city":"Cham",
    "sg:phone":"+49 9971/85510",
    "sg:postcode":"93413",
    "sg:province":"Bayern",
    "wof:name":"Muggenthaler Zeitungs- Und Zeitschriften Gro\u00dfvertrieb Gmbh",
    "wof:placetype":"venue"
},
  "geometry": {"coordinates":[12.6709852219,49.2227478027],"type":"Point"}
}