{
  "type": "Feature",
  "properties": {
    "iso:country":"DE",
    "sg:address":"Dorfstr. 45",
    "sg:city":"Emtmannsberg",
    "sg:phone":"+49 9209/746",
    "sg:postcode":"95517",
    "sg:province":"Bayern",
    "wof:name":"Karl Gebhardt",
    "wof:placetype":"venue"
},
  "geometry": {"coordinates":[11.642976,49.892551],"type":"Point"}
}