{
  "type": "Feature",
  "properties": {
    "iso:country":"DE",
    "sg:address":"Ludwig-Zorn-Str. 9",
    "sg:city":"Eppingen",
    "sg:phone":"+49 7262/219",
    "sg:postcode":"75031",
    "sg:province":"Baden-W\u00fcrttemberg",
    "wof:name":"Kath. Pfarramt Unserer Lieben Frau",
    "wof:placetype":"venue"
},
  "geometry": {"coordinates":[8.9072208405,49.1371154785],"type":"Point"}
}