{
  "type": "Feature",
  "properties": {
    "iso:country":"DE",
    "sg:address":"Rabenfelsstr. 1",
    "sg:city":"Rheinfelden",
    "sg:phone":"+49 7623/4365",
    "sg:postcode":"79618",
    "sg:province":"Baden-W\u00fcrttemberg",
    "wof:name":"Restaurant Linde",
    "wof:placetype":"venue"
},
  "geometry": {"coordinates":[7.7335238457,47.5573501587],"type":"Point"}
}