{
  "type": "Feature",
  "properties": {
    "iso:country":"DE",
    "sg:address":"Tersteegenstr. 88",
    "sg:city":"D\u00fcsseldorf",
    "sg:phone":"+49 211/4541331",
    "sg:postcode":"40474",
    "sg:province":"Nordrhein-Westfalen",
    "wof:name":"Ev. Pfarramt I Und Ii Tersteegenkirche",
    "wof:placetype":"venue"
},
  "geometry": {"coordinates":[6.7591471672,51.2560272217],"type":"Point"}
}