{
  "type": "Feature",
  "properties": {
    "iso:country":"DE",
    "sg:address":"Postfach 1143:: 21651 Stade:: Germany.^^Archivstr 3/5::",
    "sg:city":"Stade",
    "sg:postcode":"21682",
    "sg:province":"Niedersachsen",
    "wof:name":"Rn Beteiligungs Gmbh",
    "wof:placetype":"venue"
},
  "geometry": {"coordinates":[-91.552673,34.498363],"type":"Point"}
}