{
  "type": "Feature",
  "properties": {
    "iso:country":"DE",
    "sg:address":"Frankfurter Str. 307",
    "sg:city":"Kassel",
    "sg:postcode":"34134",
    "sg:province":"Hessen",
    "wof:name":"Kempf & Veith Gmbh",
    "wof:placetype":"venue"
},
  "geometry": {"coordinates":[9.467015,51.282486],"type":"Point"}
}