{
  "type": "Feature",
  "properties": {
    "iso:country":"DE",
    "sg:address":"Bullendorf",
    "sg:city":"Altenmoor",
    "sg:phone":"+49 4121/452003",
    "sg:postcode":"25335",
    "sg:province":"Schleswig-Holstein",
    "wof:name":"K. M\u00fcnster",
    "wof:placetype":"venue"
},
  "geometry": {"coordinates":[9.623982,53.772118],"type":"Point"}
}