{
  "type": "Feature",
  "properties": {
    "iso:country":"DE",
    "sg:address":"Estorffstr. 22",
    "sg:city":"Hamm",
    "sg:phone":"+49 2381/780217",
    "sg:postcode":"59075",
    "sg:province":"Nordrhein-Westfalen",
    "wof:name":"Peter Zapf",
    "wof:placetype":"venue"
},
  "geometry": {"coordinates":[7.75248909,51.6883430481],"type":"Point"}
}