{
  "type": "Feature",
  "properties": {
    "iso:country":"DE",
    "sg:address":"Kielmannseggstr. 70",
    "sg:city":"Hamburg",
    "sg:phone":"+49 40/6573940",
    "sg:postcode":"22043",
    "sg:province":"Hamburg",
    "wof:name":"Marienthaler-apotheke",
    "wof:placetype":"venue"
},
  "geometry": {"coordinates":[10.092581,53.568165],"type":"Point"}
}