{
  "type": "Feature",
  "properties": {
    "iso:country":"DE",
    "sg:address":"Moosinninger Str. 14",
    "sg:city":"Erding",
    "sg:phone":"+49 8122/902484",
    "sg:postcode":"85435",
    "sg:province":"Bayern",
    "wof:name":"Hermann Kollmannsberger",
    "wof:placetype":"venue"
},
  "geometry": {"coordinates":[11.898068428,48.2979621887],"type":"Point"}
}