{
  "type": "Feature",
  "properties": {
    "iso:country":"DE",
    "sg:address":"Schleicherweg 21",
    "sg:city":"Brackenheim",
    "sg:phone":"+49 4971/352564",
    "sg:postcode":"74336",
    "sg:province":"Baden-W\u00fcrttemberg",
    "wof:name":"Richard Wagner Gmbh",
    "wof:placetype":"venue"
},
  "geometry": {"coordinates":[9.069642,49.067589],"type":"Point"}
}