{
  "type": "Feature",
  "properties": {
    "iso:country":"DE",
    "sg:address":"Im Dorfe 36",
    "sg:city":"H\u00fcllhorst",
    "sg:phone":"+49 5744/785",
    "sg:postcode":"32609",
    "sg:province":"Nordrhein-Westfalen",
    "wof:name":"Klaus Becker",
    "wof:placetype":"venue"
},
  "geometry": {"coordinates":[8.651985,52.264496],"type":"Point"}
}