{
  "type": "Feature",
  "properties": {
    "iso:country":"DE",
    "sg:address":"Postfach 1264:: 27234 Twistringen:: Germany.^^Kirchstr 7::",
    "sg:city":"Twistringen",
    "sg:phone":"+49 4243/4120",
    "sg:postcode":"27239",
    "sg:province":"Niedersachsen",
    "wof:name":"Volksbank Twistringen Eg",
    "wof:placetype":"venue"
},
  "geometry": {"coordinates":[8.639106,52.800392],"type":"Point"}
}