{
  "type": "Feature",
  "properties": {
    "iso:country":"DE",
    "sg:address":"Zeppelinstr. 14",
    "sg:city":"Bensheim",
    "sg:phone":"+49 6251/68597",
    "sg:postcode":"64625",
    "sg:province":"Hessen",
    "wof:name":"Wissner Schulartikel- Produktion Gmbh",
    "wof:placetype":"venue"
},
  "geometry": {"coordinates":[8.592371,49.686852],"type":"Point"}
}