{
  "type": "Feature",
  "properties": {
    "iso:country":"DE",
    "sg:address":"Kranzmaarstr. 32",
    "sg:city":"H\u00fcrth",
    "sg:phone":"+49 2233/15386",
    "sg:postcode":"50354",
    "sg:province":"Nordrhein-Westfalen",
    "wof:name":"B. Nickl",
    "wof:placetype":"venue"
},
  "geometry": {"coordinates":[6.8676400185,50.8715324402],"type":"Point"}
}