{
  "type": "Feature",
  "properties": {
    "iso:country":"DE",
    "sg:address":"Dunkerstra\u00dfe 6",
    "sg:city":"Bad Nauheim",
    "sg:postcode":"61231",
    "sg:province":"Hessen",
    "wof:name":"Forum F\u00fcr Yachtsport Und Segeln",
    "wof:placetype":"venue"
},
  "geometry": {"coordinates":[8.7379722595,50.3608169556],"type":"Point"}
}