{
  "type": "Feature",
  "properties": {
    "iso:country":"DE",
    "sg:address":"Langgasse 8",
    "sg:city":"Wetzlar",
    "sg:phone":"+49 6441/45259",
    "sg:postcode":"35576",
    "sg:province":"Hessen",
    "wof:name":"I. Minoudis",
    "wof:placetype":"venue"
},
  "geometry": {"coordinates":[8.4975204468,50.5565910339],"type":"Point"}
}