{
  "type": "Feature",
  "properties": {
    "iso:country":"DE",
    "sg:address":"K\u00fclftalstr. 26",
    "sg:city":"Hoyershausen",
    "sg:phone":"+49 5185/233",
    "sg:postcode":"31093",
    "sg:province":"Niedersachsen",
    "wof:name":"Wolfgang Brandes",
    "wof:placetype":"venue"
},
  "geometry": {"coordinates":[9.727961,52.033627],"type":"Point"}
}