{
  "type": "Feature",
  "properties": {
    "iso:country":"DE",
    "sg:address":"Regina-Protmann-Str. 16",
    "sg:city":"M\u00fcnster",
    "sg:phone":"+49 251/21030",
    "sg:postcode":"48159",
    "sg:province":"Nordrhein-Westfalen",
    "wof:name":"A.s.i. Assekuranzmakler Gmbh",
    "wof:placetype":"venue"
},
  "geometry": {"coordinates":[7.6170310974,51.991191864],"type":"Point"}
}