{
  "type": "Feature",
  "properties": {
    "iso:country":"DE",
    "sg:address":"Holstenstr. 1",
    "sg:city":"Hamburg",
    "sg:phone":"+49 40/31791882",
    "sg:postcode":"22767",
    "sg:province":"Hamburg",
    "wof:name":"I. Pr\u00f6hl",
    "wof:placetype":"venue"
},
  "geometry": {"coordinates":[9.955843,53.549908],"type":"Point"}
}