{
  "type": "Feature",
  "properties": {
    "iso:country":"DE",
    "sg:address":"H\u00f6rlebacher Str. 5",
    "sg:city":"Ilshofen",
    "sg:phone":"+49 7904/221",
    "sg:postcode":"74532",
    "sg:province":"Baden-W\u00fcrttemberg",
    "wof:name":"Von Berg & J\u00e4ger Gmbh",
    "wof:placetype":"venue"
},
  "geometry": {"coordinates":[9.9162797928,49.1711807251],"type":"Point"}
}