{
  "type": "Feature",
  "properties": {
    "iso:country":"DE",
    "sg:address":"H\u00e4berlstr. 21",
    "sg:city":"M\u00fcnchen",
    "sg:postcode":"80337",
    "sg:province":"Bayern",
    "wof:name":"Bilnet Computer- Und Kommunikation E. K.",
    "wof:placetype":"venue"
},
  "geometry": {"coordinates":[11.5586242676,48.1270751953],"type":"Point"}
}