{
  "type": "Feature",
  "properties": {
    "iso:country":"DE",
    "sg:address":"In der Teichmatt 1",
    "sg:city":"Maulburg",
    "sg:phone":"+49 7622/666850",
    "sg:postcode":"79689",
    "sg:province":"Baden-W\u00fcrttemberg",
    "wof:name":"Greiner Gmbh",
    "wof:placetype":"venue"
},
  "geometry": {"coordinates":[7.7699489594,47.6450614929],"type":"Point"}
}