{
  "type": "Feature",
  "properties": {
    "iso:country":"DE",
    "sg:address":"Friedrich-Ludwig-Jahn-Str. 50",
    "sg:city":"Lenzen",
    "sg:phone":"+49 38792/7420",
    "sg:postcode":"19309",
    "sg:province":"Brandenburg",
    "wof:name":"Klaus Engelhardt Fahrradservice Und Verleih",
    "wof:placetype":"venue"
},
  "geometry": {"coordinates":[11.474708,53.090591],"type":"Point"}
}