{
  "type": "Feature",
  "properties": {
    "iso:country":"DE",
    "sg:address":"Obertrennbach",
    "sg:city":"Obertrennbach",
    "sg:phone":"+49 8722/741",
    "sg:postcode":"84140",
    "sg:province":"Bayern",
    "wof:name":"Raiffeisenbank Obertrennbach",
    "wof:placetype":"venue"
},
  "geometry": {"coordinates":[12.56305,48.484482],"type":"Point"}
}