{
  "type": "Feature",
  "properties": {
    "iso:country":"DE",
    "sg:address":"Burgstr. 20",
    "sg:city":"St\u00f6dtlen",
    "sg:phone":"+49 7964/660",
    "sg:postcode":"73495",
    "sg:province":"Baden-W\u00fcrttemberg",
    "wof:name":"Josef Klein",
    "wof:placetype":"venue"
},
  "geometry": {"coordinates":[10.303472,49.001698],"type":"Point"}
}