{
  "type": "Feature",
  "properties": {
    "iso:country":"DE",
    "sg:address":"Baben de M\u00f6hl 12",
    "sg:city":"Hamburg",
    "sg:phone":"+49 40/6040141",
    "sg:postcode":"22395",
    "sg:province":"Hamburg",
    "wof:name":"Hans-joachim Erdmann",
    "wof:placetype":"venue"
},
  "geometry": {"coordinates":[10.109132,53.673145],"type":"Point"}
}