{
  "type": "Feature",
  "properties": {
    "iso:country":"DE",
    "sg:address":"Livry-Gargan-Str. 10",
    "sg:city":"F\u00fcrstenfeldbruck",
    "sg:phone":"+49 8141/350",
    "sg:postcode":"82256",
    "sg:province":"Bayern",
    "wof:name":"National Semiconductor Gmbh",
    "wof:placetype":"venue"
},
  "geometry": {"coordinates":[11.221748,48.163643],"type":"Point"}
}