{
  "type": "Feature",
  "properties": {
    "iso:country":"DE",
    "sg:address":"Rheingaustr. 100",
    "sg:city":"Wiesbaden",
    "sg:phone":"+49 4961/1967640",
    "sg:postcode":"65203",
    "sg:province":"Hessen",
    "wof:name":"Mahr Gmbh Anlagentechnik F\u00dcr Sch\u00dcttg\u00dcter",
    "wof:placetype":"venue"
},
  "geometry": {"coordinates":[8.22415,50.039799],"type":"Point"}
}