{
  "type": "Feature",
  "properties": {
    "iso:country":"DE",
    "sg:address":"J\u00e4gerhalde 121",
    "sg:city":"Stuttgart",
    "sg:phone":"+49 711/422528",
    "sg:postcode":"70327",
    "sg:province":"Baden-W\u00fcrttemberg",
    "wof:name":"Margot Tournier",
    "wof:placetype":"venue"
},
  "geometry": {"coordinates":[9.227786,48.778374],"type":"Point"}
}