{
  "type": "Feature",
  "properties": {
    "iso:country":"DE",
    "sg:address":"Friedrich-Ebert-Str. 61",
    "sg:city":"Leipzig",
    "sg:phone":"+49 341/9612001",
    "sg:postcode":"04109",
    "sg:province":"Sachsen",
    "wof:name":"Ratiomat K\u00fcchenm\u00f6bel Programme Gmbh",
    "wof:placetype":"venue"
},
  "geometry": {"coordinates":[12.3618211746,51.3392181396],"type":"Point"}
}