{
  "type": "Feature",
  "properties": {
    "iso:country":"DE",
    "sg:address":"An der Stadtmauer 5",
    "sg:city":"Blieskastel",
    "sg:phone":"+49 6842/3327",
    "sg:postcode":"66440",
    "sg:province":"Saarland",
    "wof:name":"Pizzeria Zum Schlangenbrunnen",
    "wof:placetype":"venue"
},
  "geometry": {"coordinates":[7.2589559555,49.2385864258],"type":"Point"}
}