{
  "type": "Feature",
  "properties": {
    "iso:country":"DE",
    "sg:address":"Mindener Str. 70",
    "sg:city":"Herford",
    "sg:phone":"+49 5221/24312",
    "sg:postcode":"32049",
    "sg:province":"Nordrhein-Westfalen",
    "wof:name":"Treffpunkt",
    "wof:placetype":"venue"
},
  "geometry": {"coordinates":[8.6830940247,52.1241188049],"type":"Point"}
}