{
  "type": "Feature",
  "properties": {
    "iso:country":"DE",
    "sg:address":"Solmser Gewerbepark 14b",
    "sg:city":"Solms",
    "sg:phone":"+49 6442/22361",
    "sg:postcode":"35606",
    "sg:province":"Hessen",
    "wof:name":"Solmser Pulverbeschichtungen Und Industrievertretungen Weil Gmbh",
    "wof:placetype":"venue"
},
  "geometry": {"coordinates":[8.4148206711,50.5422439575],"type":"Point"}
}