{
  "type": "Feature",
  "properties": {
    "iso:country":"DE",
    "sg:address":"Alexanderstr. 14 a",
    "sg:city":"Eisenach",
    "sg:phone":"+49 3691/2732488",
    "sg:postcode":"99817",
    "sg:province":"Th\u00fcringen",
    "wof:name":"Constanze Bachmann",
    "wof:placetype":"venue"
},
  "geometry": {"coordinates":[10.321843,50.97596],"type":"Point"}
}