{
  "type": "Feature",
  "properties": {
    "iso:country":"DE",
    "sg:address":"Schm\u00f6lzer Str. 4",
    "sg:city":"Redwitz",
    "sg:phone":"+49 9264/6500",
    "sg:postcode":"96257",
    "sg:province":"Bayern",
    "wof:name":"H.-j. Schmidt",
    "wof:placetype":"venue"
},
  "geometry": {"coordinates":[11.220487,50.198246],"type":"Point"}
}