{
  "type": "Feature",
  "properties": {
    "iso:country":"DE",
    "sg:address":"Lorenzstr. 10",
    "sg:city":"Stutensee",
    "sg:phone":"+49 7244/7320",
    "sg:postcode":"76297",
    "sg:province":"Baden-W\u00fcrttemberg",
    "wof:name":"Pii Pipetronix Gmbh",
    "wof:placetype":"venue"
},
  "geometry": {"coordinates":[8.4553031921,49.0733528137],"type":"Point"}
}