{
  "type": "Feature",
  "properties": {
    "iso:country":"DE",
    "sg:address":"Essener Str. 4",
    "sg:city":"Leipzig",
    "sg:postcode":"04129",
    "sg:province":"Sachsen",
    "wof:name":"Michael L\u00fcdtke",
    "wof:placetype":"venue"
},
  "geometry": {"coordinates":[12.386097908,51.3760223389],"type":"Point"}
}