{
  "type": "Feature",
  "properties": {
    "iso:country":"DE",
    "sg:address":"Alter Zollweg 132",
    "sg:city":"Hamburg",
    "sg:postcode":"22147",
    "sg:province":"Hamburg",
    "wof:name":"Michael Wei\u00df Tankstellen- Gesellschaft Mbh",
    "wof:placetype":"venue"
},
  "geometry": {"coordinates":[10.137376,53.608101],"type":"Point"}
}