{
  "type": "Feature",
  "properties": {
    "iso:country":"DE",
    "sg:address":"St.-Ottilien-Str.",
    "sg:city":"Eresing",
    "sg:phone":"+49 8193/71261",
    "sg:postcode":"86922",
    "sg:province":"Bayern",
    "wof:name":"Red. M\u00fcnchener Theologische Zeitschrift",
    "wof:placetype":"venue"
},
  "geometry": {"coordinates":[11.0272979736,48.0905761719],"type":"Point"}
}