{
  "type": "Feature",
  "properties": {
    "iso:country":"DE",
    "sg:address":"Alpenstr. 69",
    "sg:city":"Baisweil",
    "sg:phone":"+49 8340/1081",
    "sg:postcode":"87650",
    "sg:province":"Bayern",
    "wof:name":"M. H\u00f6lzle",
    "wof:placetype":"venue"
},
  "geometry": {"coordinates":[10.534108,47.971107],"type":"Point"}
}