{
  "type": "Feature",
  "properties": {
    "iso:country":"DE",
    "sg:address":"Nordstr. 25",
    "sg:city":"Treuen",
    "sg:phone":"+49 37468/2630",
    "sg:postcode":"08233",
    "sg:province":"Sachsen",
    "wof:name":"Frank Herzog",
    "wof:placetype":"venue"
},
  "geometry": {"coordinates":[12.307096,50.542622],"type":"Point"}
}