{
  "type": "Feature",
  "properties": {
    "iso:country":"DE",
    "sg:address":"Industriestr. 15",
    "sg:city":"Reichshof",
    "sg:phone":"+49 2261/55558",
    "sg:postcode":"51580",
    "sg:province":"Nordrhein-Westfalen",
    "wof:name":"Kurt Bergerhof",
    "wof:placetype":"venue"
},
  "geometry": {"coordinates":[7.602249,50.980099],"type":"Point"}
}