{
  "type": "Feature",
  "properties": {
    "iso:country":"DE",
    "sg:address":"Hauptstr. 50",
    "sg:city":"Dietrichingen",
    "sg:phone":"+49 6338/7183",
    "sg:postcode":"66484",
    "sg:province":"Rheinland-Pfalz",
    "wof:name":"Wilfried Heller Ingenieur",
    "wof:placetype":"venue"
},
  "geometry": {"coordinates":[7.4145197868,49.1930198669],"type":"Point"}
}