{
  "type": "Feature",
  "properties": {
    "iso:country":"DE",
    "sg:address":"Balthasar-Neumann-Str. 9",
    "sg:city":"Bayreuth",
    "sg:phone":"+49 921/69199",
    "sg:postcode":"95444",
    "sg:province":"Bayern",
    "wof:name":"Lothar Beiergr\u00f6\u00dflein Rechtsanwalt",
    "wof:placetype":"venue"
},
  "geometry": {"coordinates":[11.5775413513,49.9377784729],"type":"Point"}
}