{
  "type": "Feature",
  "properties": {
    "iso:country":"DE",
    "sg:address":"Hauptstr. 15",
    "sg:city":"Lonsee",
    "sg:phone":"+49 7336/5665",
    "sg:postcode":"89173",
    "sg:province":"Baden-W\u00fcrttemberg",
    "wof:name":"Alexander Kohnle Masseur",
    "wof:placetype":"venue"
},
  "geometry": {"coordinates":[9.916935,48.544491],"type":"Point"}
}