{
  "type": "Feature",
  "properties": {
    "iso:country":"DE",
    "sg:address":"Borchersweg 54",
    "sg:city":"Oldenburg",
    "sg:phone":"+49 441/202700",
    "sg:postcode":"26135",
    "sg:province":"Niedersachsen",
    "wof:name":"Heino Warns",
    "wof:placetype":"venue"
},
  "geometry": {"coordinates":[8.276189,53.100861],"type":"Point"}
}