{
  "type": "Feature",
  "properties": {
    "iso:country":"DE",
    "sg:address":"Max-und-Moritz-Str 8",
    "sg:city":"Delmenhorst",
    "sg:phone":"+49 4221/52666",
    "sg:postcode":"27753",
    "sg:province":"Niedersachsen",
    "wof:name":"Rm Speditions Gmbh",
    "wof:placetype":"venue"
},
  "geometry": {"coordinates":[8.6129865646,53.05884552],"type":"Point"}
}