{
  "type": "Feature",
  "properties": {
    "iso:country":"DE",
    "sg:address":"Bachtalstr. 387",
    "sg:city":"Schwalbach",
    "sg:phone":"+49 6834/953090",
    "sg:postcode":"66773",
    "sg:province":"Saarland",
    "wof:name":"Stein Tec Gmbh",
    "wof:placetype":"venue"
},
  "geometry": {"coordinates":[6.855825901,49.3079452515],"type":"Point"}
}