{
  "type": "Feature",
  "properties": {
    "iso:country":"DE",
    "sg:address":"Alfred-Martin-Str. 10",
    "sg:city":"Bad Nauheim",
    "sg:phone":"+49 6032/5659",
    "sg:postcode":"61231",
    "sg:province":"Hessen",
    "wof:name":"Herbert Loos Masseur",
    "wof:placetype":"venue"
},
  "geometry": {"coordinates":[8.742166,50.355373],"type":"Point"}
}