{
  "type": "Feature",
  "properties": {
    "iso:country":"DE",
    "sg:address":"Burgstr. 24",
    "sg:city":"Langg\u00f6ns",
    "sg:postcode":"35428",
    "sg:province":"Hessen",
    "wof:name":"Hf Communication & Technology Gmbh",
    "wof:placetype":"venue"
},
  "geometry": {"coordinates":[8.6142835617,50.4769172668],"type":"Point"}
}