{
  "type": "Feature",
  "properties": {
    "iso:country":"DE",
    "sg:address":"Eschenbeeker Str. 11",
    "sg:city":"Wuppertal",
    "sg:phone":"+49 202/751752",
    "sg:postcode":"42109",
    "sg:province":"Nordrhein-Westfalen",
    "wof:name":"Adolf Enge E. K.",
    "wof:placetype":"venue"
},
  "geometry": {"coordinates":[7.1463561058,51.2707862854],"type":"Point"}
}