{
  "type": "Feature",
  "properties": {
    "iso:country":"DE",
    "sg:address":"Wellingstr. 8",
    "sg:city":"Kirchheim",
    "sg:phone":"+49 7021/46865",
    "sg:postcode":"73230",
    "sg:province":"Baden-W\u00fcrttemberg",
    "wof:name":"Sergio Da Pescheria",
    "wof:placetype":"venue"
},
  "geometry": {"coordinates":[9.4519424438,48.6474990845],"type":"Point"}
}