{
  "type": "Feature",
  "properties": {
    "iso:country":"DE",
    "sg:address":"Mittelstr. 6",
    "sg:city":"Gro\u00dfweil",
    "sg:phone":"+49 8851/7174",
    "sg:postcode":"82439",
    "sg:province":"Bayern",
    "wof:name":"Martin Huber",
    "wof:placetype":"venue"
},
  "geometry": {"coordinates":[11.3018169403,47.6761436462],"type":"Point"}
}