{
  "type": "Feature",
  "properties": {
    "iso:country":"DE",
    "sg:address":"Ebersbacher Weg 30",
    "sg:city":"Schorndorf",
    "sg:phone":"+49 7181/60040",
    "sg:postcode":"73614",
    "sg:province":"Baden-W\u00fcrttemberg",
    "wof:name":"Alten- Und Pflegeheim Spittler-stift",
    "wof:placetype":"venue"
},
  "geometry": {"coordinates":[9.526779,48.787933],"type":"Point"}
}