{
  "type": "Feature",
  "properties": {
    "iso:country":"DE",
    "sg:address":"Gneisenaustr. 1",
    "sg:city":"Arnsberg",
    "sg:phone":"+49 2932/32466",
    "sg:postcode":"59755",
    "sg:province":"Nordrhein-Westfalen",
    "wof:name":"Karin Dicty-streckenbach",
    "wof:placetype":"venue"
},
  "geometry": {"coordinates":[7.9700608253,51.4458084106],"type":"Point"}
}