{
  "type": "Feature",
  "properties": {
    "iso:country":"DE",
    "sg:address":"Industriestra\u00dfe 6",
    "sg:city":"Rottenburg-Hailfingen",
    "sg:postcode":"72108",
    "sg:province":"Baden-W\u00fcrttemberg",
    "wof:name":"Stoz Oberfl\u00e4chentechnik",
    "wof:placetype":"venue"
},
  "geometry": {"coordinates":[8.87705,48.528847],"type":"Point"}
}