{
  "type": "Feature",
  "properties": {
    "iso:country":"DE",
    "sg:address":"Poststr. 37",
    "sg:city":"Voerde",
    "sg:phone":"+49 281/43764",
    "sg:postcode":"46562",
    "sg:province":"Nordrhein-Westfalen",
    "wof:name":"Erhan Zumrut",
    "wof:placetype":"venue"
},
  "geometry": {"coordinates":[6.6460819244,51.6292457581],"type":"Point"}
}