{
  "type": "Feature",
  "properties": {
    "iso:country":"DE",
    "sg:address":"Hauptstr. 65",
    "sg:city":"Breidenbach",
    "sg:phone":"+49 6465/1368",
    "sg:postcode":"35236",
    "sg:province":"Hessen",
    "wof:name":"Restaurant Perfstube",
    "wof:placetype":"venue"
},
  "geometry": {"coordinates":[8.4537782669,50.8879508972],"type":"Point"}
}