{
  "type": "Feature",
  "properties": {
    "iso:country":"DE",
    "sg:address":"Oskarstr. 6",
    "sg:city":"Essen",
    "sg:phone":"+49 201/421432",
    "sg:postcode":"45133",
    "sg:province":"Nordrhein-Westfalen",
    "wof:name":"Wilhelmine Kamitz",
    "wof:placetype":"venue"
},
  "geometry": {"coordinates":[7.0005760193,51.4224205017],"type":"Point"}
}