{
  "type": "Feature",
  "properties": {
    "iso:country":"DE",
    "sg:address":"Lantzallee 4",
    "sg:city":"D\u00fcsseldorf",
    "sg:phone":"+49 211/4360650",
    "sg:postcode":"40474",
    "sg:province":"Nordrhein-Westfalen",
    "wof:name":"Matthias Schwab Rechtsanwalt",
    "wof:placetype":"venue"
},
  "geometry": {"coordinates":[6.7408890724,51.2777328491],"type":"Point"}
}