{
  "type": "Feature",
  "properties": {
    "iso:country":"DE",
    "sg:address":"Grauh\u00f6fer Str. 8 a",
    "sg:city":"Goslar",
    "sg:phone":"+49 5321/22697",
    "sg:postcode":"38640",
    "sg:province":"Niedersachsen",
    "wof:name":"Ludwig Bamberg Architekt",
    "wof:placetype":"venue"
},
  "geometry": {"coordinates":[10.42629,51.913086],"type":"Point"}
}