{
  "type": "Feature",
  "properties": {
    "iso:country":"DE",
    "sg:address":"Memelstr. 3a",
    "sg:city":"Nienburg",
    "sg:phone":"+49 5021/911606",
    "sg:postcode":"31582",
    "sg:province":"Niedersachsen",
    "wof:name":"W. Thomas",
    "wof:placetype":"venue"
},
  "geometry": {"coordinates":[9.270459,52.613266],"type":"Point"}
}