{
  "type": "Feature",
  "properties": {
    "iso:country":"DE",
    "sg:address":"D\u00fcrener Str. 308",
    "sg:city":"Eschweiler",
    "sg:phone":"+49 2403/21572",
    "sg:postcode":"52249",
    "sg:province":"Nordrhein-Westfalen",
    "wof:name":"Startol-tankstelle",
    "wof:placetype":"venue"
},
  "geometry": {"coordinates":[6.2917881012,50.8197097778],"type":"Point"}
}