{
  "type": "Feature",
  "properties": {
    "iso:country":"DE",
    "sg:address":"H\u00fcntestr 68",
    "sg:city":"Aschendorf",
    "sg:phone":"+49 4962/5050",
    "sg:postcode":"26871",
    "sg:province":"Niedersachsen",
    "wof:name":"Ado Gardinenwerke Gmbh & Co",
    "wof:placetype":"venue"
},
  "geometry": {"coordinates":[7.42354,53.072861],"type":"Point"}
}