{
  "type": "Feature",
  "properties": {
    "iso:country":"DE",
    "sg:address":"Reitbahnstr. 1",
    "sg:city":"Tangerm\u00fcnde",
    "sg:phone":"+49 39322/3201",
    "sg:postcode":"39590",
    "sg:province":"Sachsen-Anhalt",
    "wof:name":"Schulz",
    "wof:placetype":"venue"
},
  "geometry": {"coordinates":[11.970361,52.539719],"type":"Point"}
}