{
  "type": "Feature",
  "properties": {
    "iso:country":"DE",
    "sg:address":"Bahnhofsweg 17",
    "sg:city":"Diez",
    "sg:phone":"+49 6432/2133",
    "sg:postcode":"65582",
    "sg:province":"Rheinland-Pfalz",
    "wof:name":"Marianne M\u00fcller",
    "wof:placetype":"venue"
},
  "geometry": {"coordinates":[8.0273427963,50.3722267151],"type":"Point"}
}