{
  "type": "Feature",
  "properties": {
    "iso:country":"DE",
    "sg:address":"Lise-Meitner-Allee 45",
    "sg:city":"Tornesch",
    "sg:phone":"+49 4120/708010",
    "sg:postcode":"25436",
    "sg:province":"Schleswig-Holstein",
    "wof:name":"Protected Gmbh",
    "wof:placetype":"venue"
},
  "geometry": {"coordinates":[9.7595701218,53.7175712585],"type":"Point"}
}