{
  "type": "Feature",
  "properties": {
    "iso:country":"DE",
    "sg:address":"Bahnhofstr. 4",
    "sg:city":"Schweppenhausen",
    "sg:phone":"+49 4967/24214",
    "sg:postcode":"55444",
    "sg:province":"Rheinland-Pfalz",
    "wof:name":"Hille Boote Gmbh",
    "wof:placetype":"venue"
},
  "geometry": {"coordinates":[7.797359,49.926212],"type":"Point"}
}