{
  "type": "Feature",
  "properties": {
    "iso:country":"DE",
    "sg:address":"Hammstr. 19",
    "sg:city":"Frankenthal",
    "sg:phone":"+49 6233/349286",
    "sg:postcode":"67227",
    "sg:province":"Rheinland-Pfalz",
    "wof:name":"Steiner",
    "wof:placetype":"venue"
},
  "geometry": {"coordinates":[8.34992,49.520569],"type":"Point"}
}