{
  "type": "Feature",
  "properties": {
    "iso:country":"DE",
    "sg:address":"F\u00e4rbergasse 8",
    "sg:city":"Wasserburg",
    "sg:phone":"+49 8071/2843",
    "sg:postcode":"83512",
    "sg:province":"Bayern",
    "wof:name":"F. Kohlmann",
    "wof:placetype":"venue"
},
  "geometry": {"coordinates":[12.231931,48.061405],"type":"Point"}
}