{
  "type": "Feature",
  "properties": {
    "iso:country":"DE",
    "sg:address":"Leipziger Str. 7",
    "sg:city":"Penig",
    "sg:phone":"+49 37381/5592",
    "sg:postcode":"09322",
    "sg:province":"Sachsen",
    "wof:name":"Martin H\u00e4hnel",
    "wof:placetype":"venue"
},
  "geometry": {"coordinates":[12.7024250031,50.9344100952],"type":"Point"}
}