{
  "type": "Feature",
  "properties": {
    "iso:country":"DE",
    "sg:address":"Langgasse 5",
    "sg:city":"Kulmbach",
    "sg:phone":"+49 9221/84618",
    "sg:postcode":"95326",
    "sg:province":"Bayern",
    "wof:name":"Hussel S\u00fc\u00dfwarenfachgesch\u00e4ft",
    "wof:placetype":"venue"
},
  "geometry": {"coordinates":[11.4573602676,50.1069755554],"type":"Point"}
}