{
  "type": "Feature",
  "properties": {
    "iso:country":"DE",
    "sg:address":"Kreuzstr. 83",
    "sg:city":"L\u00f6rrach",
    "sg:phone":"+49 7621/92770",
    "sg:postcode":"79540",
    "sg:province":"Baden-W\u00fcrttemberg",
    "wof:name":"Michael Kaiser",
    "wof:placetype":"venue"
},
  "geometry": {"coordinates":[7.6617679596,47.6055221558],"type":"Point"}
}