{
  "type": "Feature",
  "properties": {
    "iso:country":"DE",
    "sg:address":"Paul-Gerhardt-Str. 8",
    "sg:city":"Schwaigern",
    "sg:phone":"+49 7138/920570",
    "sg:postcode":"74193",
    "sg:province":"Baden-W\u00fcrttemberg",
    "wof:name":"Lvs-leichtbauplatten-vertriebs Gmbh",
    "wof:placetype":"venue"
},
  "geometry": {"coordinates":[9.0589513779,49.1465034485],"type":"Point"}
}