{
  "type": "Feature",
  "properties": {
    "iso:country":"DE",
    "sg:address":"Bahnhofstr. 47",
    "sg:city":"Roth",
    "sg:phone":"+49 9171/60079",
    "sg:postcode":"91154",
    "sg:province":"Bayern",
    "wof:name":"Hans Raithel Granit- Und Syenitwerke",
    "wof:placetype":"venue"
},
  "geometry": {"coordinates":[11.0834178925,49.2411842346],"type":"Point"}
}