{
  "type": "Feature",
  "properties": {
    "iso:country":"DE",
    "sg:address":"An der Bahn 4",
    "sg:city":"Gastrose-Kerkwitz",
    "sg:phone":"+49 35692/206",
    "sg:postcode":"03172",
    "sg:province":"Brandenburg",
    "wof:name":"Hotel Und Gastst\u00e4tte \u00b4j\u00e4gerhof\u00b4",
    "wof:placetype":"venue"
},
  "geometry": {"coordinates":[14.6419296265,51.9538383484],"type":"Point"}
}