{
  "type": "Feature",
  "properties": {
    "iso:country":"DE",
    "sg:address":"Im Tal 14",
    "sg:city":"Augsburg",
    "sg:phone":"+49 821/808410",
    "sg:postcode":"86179",
    "sg:province":"Bayern",
    "wof:name":"Gebacom Gesellschaft F\u00dcr Edv Und Btx Anwendung Mbh",
    "wof:placetype":"venue"
},
  "geometry": {"coordinates":[10.891831398,48.3154296875],"type":"Point"}
}