{
  "type": "Feature",
  "properties": {
    "iso:country":"DE",
    "sg:address":"Bremer Str. 120",
    "sg:city":"Bohmte",
    "sg:phone":"+49 5471/901330",
    "sg:postcode":"49163",
    "sg:province":"Niedersachsen",
    "wof:name":"K\u00f6cklar & Thomas Bauunternehmung Gmbh",
    "wof:placetype":"venue"
},
  "geometry": {"coordinates":[8.31519,52.388874],"type":"Point"}
}