{
  "type": "Feature",
  "properties": {
    "iso:country":"DE",
    "sg:address":"Markgrafenstr. 125a",
    "sg:city":"Dortmund",
    "sg:phone":"+49 231/123706",
    "sg:postcode":"44139",
    "sg:province":"Nordrhein-Westfalen",
    "wof:name":"Aral Ag",
    "wof:placetype":"venue"
},
  "geometry": {"coordinates":[7.4654450417,51.5013771057],"type":"Point"}
}