{
  "type": "Feature",
  "properties": {
    "iso:country":"DE",
    "sg:address":"\u00d6sterreicher Str. 44",
    "sg:city":"Dresden",
    "sg:phone":"+49 351/2511626",
    "sg:postcode":"01279",
    "sg:province":"Sachsen",
    "wof:name":"Schuservice Und Orthop\u00e4die- Schutechnik Empor Dresden Eg",
    "wof:placetype":"venue"
},
  "geometry": {"coordinates":[13.8371553421,51.025062561],"type":"Point"}
}