{
  "type": "Feature",
  "properties": {
    "iso:country":"DE",
    "sg:address":"Truderinger Str. 191",
    "sg:city":"M\u00fcnchen",
    "sg:postcode":"81673",
    "sg:province":"Bayern",
    "wof:name":"Sch\u00e4fer Einspritztechnik Gmbh",
    "wof:placetype":"venue"
},
  "geometry": {"coordinates":[11.644418,48.131294],"type":"Point"}
}