{
  "type": "Feature",
  "properties": {
    "iso:country":"DE",
    "sg:address":"Im Hahlfeld 23",
    "sg:city":"K\u00fcnzell",
    "sg:phone":"+49 661/33483",
    "sg:postcode":"36093",
    "sg:province":"Hessen",
    "wof:name":"A. R\u00f6hrig",
    "wof:placetype":"venue"
},
  "geometry": {"coordinates":[9.7108516693,50.5385169983],"type":"Point"}
}