{
  "type": "Feature",
  "properties": {
    "iso:country":"DE",
    "sg:address":"Pferdemarktstr. 30",
    "sg:city":"Leer",
    "sg:phone":"+49 491/9279103",
    "sg:postcode":"26789",
    "sg:province":"Niedersachsen",
    "wof:name":"Gerhard Eden Architekt",
    "wof:placetype":"venue"
},
  "geometry": {"coordinates":[7.446075,53.22588],"type":"Point"}
}