{
  "type": "Feature",
  "properties": {
    "iso:country":"DE",
    "sg:address":"Dorotheenstr. 27",
    "sg:city":"Bad Homburg",
    "sg:phone":"+49 6172/690232",
    "sg:postcode":"61348",
    "sg:province":"Hessen",
    "wof:name":"K. Gallmann",
    "wof:placetype":"venue"
},
  "geometry": {"coordinates":[8.614883,50.226013],"type":"Point"}
}