{
  "type": "Feature",
  "properties": {
    "iso:country":"DE",
    "sg:address":"Pfaffenbergstr. 27",
    "sg:city":"Kaiserslautern",
    "sg:phone":"+49 631/3115236",
    "sg:postcode":"67663",
    "sg:province":"Rheinland-Pfalz",
    "wof:name":"Ernst Bulla",
    "wof:placetype":"venue"
},
  "geometry": {"coordinates":[7.7605361938,49.4317970276],"type":"Point"}
}