{
  "type": "Feature",
  "properties": {
    "iso:country":"DE",
    "sg:address":"Am Buchenring 29",
    "sg:city":"Buchholz",
    "sg:phone":"+49 5751/5515",
    "sg:postcode":"31710",
    "sg:province":"Niedersachsen",
    "wof:name":"Ralf Seiler",
    "wof:placetype":"venue"
},
  "geometry": {"coordinates":[9.136341,52.227345],"type":"Point"}
}