{
  "type": "Feature",
  "properties": {
    "iso:country":"DE",
    "sg:address":"Sch\u00e4ferstr. 2",
    "sg:city":"Ludwigsburg",
    "sg:phone":"+49 7141/51816",
    "sg:postcode":"71642",
    "sg:province":"Baden-W\u00fcrttemberg",
    "wof:name":"H.-p. Raggi",
    "wof:placetype":"venue"
},
  "geometry": {"coordinates":[9.205112,48.910313],"type":"Point"}
}