{
  "type": "Feature",
  "properties": {
    "iso:country":"DE",
    "sg:address":"Ringbergstr. 20",
    "sg:city":"Bad Wiessee",
    "sg:phone":"+49 8022/83562",
    "sg:postcode":"83707",
    "sg:province":"Bayern",
    "wof:name":"G\u00e4stehaus Krinnerhof",
    "wof:placetype":"venue"
},
  "geometry": {"coordinates":[11.7319936752,47.7023773193],"type":"Point"}
}