{
  "type": "Feature",
  "properties": {
    "iso:country":"DE",
    "sg:address":"Friedenbachstr. 23",
    "sg:city":"Weilburg",
    "sg:phone":"+49 6471/922749",
    "sg:postcode":"35781",
    "sg:province":"Hessen",
    "wof:name":"Heimann Heizung & Sanit\u00e4r Vertrieb & Service Gmbh",
    "wof:placetype":"venue"
},
  "geometry": {"coordinates":[8.2929639816,50.4767494202],"type":"Point"}
}