{
  "type": "Feature",
  "properties": {
    "iso:country":"DE",
    "sg:address":"Parkstr. 3 c",
    "sg:city":"Osnabr\u00fcck",
    "sg:phone":"+49 541/804348",
    "sg:postcode":"49080",
    "sg:province":"Niedersachsen",
    "wof:name":"Mehnert",
    "wof:placetype":"venue"
},
  "geometry": {"coordinates":[8.043683,52.264229],"type":"Point"}
}