{
  "type": "Feature",
  "properties": {
    "iso:country":"DE",
    "sg:address":"St.-J\u00fcrgen-Str. 106",
    "sg:city":"Bremen",
    "sg:phone":"+49 421/73833",
    "sg:postcode":"28203",
    "sg:province":"Bremen",
    "wof:name":"Friedrich Mester",
    "wof:placetype":"venue"
},
  "geometry": {"coordinates":[8.836056,53.074657],"type":"Point"}
}