{
  "type": "Feature",
  "properties": {
    "iso:country":"DE",
    "sg:address":"Am Redder 11",
    "sg:city":"Bargteheide",
    "sg:postcode":"22941",
    "sg:province":"Schleswig-Holstein",
    "wof:name":"Tem Equipment Management Gmbh",
    "wof:placetype":"venue"
},
  "geometry": {"coordinates":[10.2826080322,53.7255134583],"type":"Point"}
}