{
  "type": "Feature",
  "properties": {
    "iso:country":"DE",
    "sg:address":"An der Rheinschanze 1",
    "sg:city":"Ludwigshafen",
    "sg:phone":"+49 4962/159970",
    "sg:postcode":"67059",
    "sg:province":"Rheinland-Pfalz",
    "wof:name":"Pf\u00e4lzische Hypothekenbank Zw.nrdl., Der Deutschen Hypo-bank Frankfurt",
    "wof:placetype":"venue"
},
  "geometry": {"coordinates":[8.451569,49.480698],"type":"Point"}
}