{
  "type": "Feature",
  "properties": {
    "iso:country":"DE",
    "sg:address":"Mittelstr. 1",
    "sg:city":"Kiel",
    "sg:postcode":"24103",
    "sg:province":"Schleswig-Holstein",
    "wof:name":"Lady Fitness Kiel Gmbh",
    "wof:placetype":"venue"
},
  "geometry": {"coordinates":[10.1314935684,54.3294296265],"type":"Point"}
}