{
  "type": "Feature",
  "properties": {
    "iso:country":"DE",
    "sg:address":"Elsterwerdaer Str. 34",
    "sg:city":"Gr\u00f6den",
    "sg:phone":"+49 35343/60780",
    "sg:postcode":"04932",
    "sg:province":"Brandenburg",
    "wof:name":"M. T\u00f6pfer & W. T\u00f6pfer Gbr",
    "wof:placetype":"venue"
},
  "geometry": {"coordinates":[13.546397,51.418278],"type":"Point"}
}