{
  "type": "Feature",
  "properties": {
    "iso:country":"DE",
    "sg:address":"Industriestr. 11",
    "sg:city":"Dielheim",
    "sg:phone":"+49 6222/75438",
    "sg:postcode":"69234",
    "sg:province":"Baden-W\u00fcrttemberg",
    "wof:name":"Tornado Gmbh Antennen-systeme Und Bauteile",
    "wof:placetype":"venue"
},
  "geometry": {"coordinates":[8.7456951141,49.2776222229],"type":"Point"}
}