{
  "type": "Feature",
  "properties": {
    "iso:country":"DE",
    "sg:address":"K\u00fcferstr. 26",
    "sg:city":"K\u00f6ngen",
    "sg:phone":"+49 7024/983880",
    "sg:postcode":"73257",
    "sg:province":"Baden-W\u00fcrttemberg",
    "wof:name":"Weag Wertstoff-aufbereitungs- Verwaltungs Gmbh",
    "wof:placetype":"venue"
},
  "geometry": {"coordinates":[9.3745927811,48.6835823059],"type":"Point"}
}