{
  "type": "Feature",
  "properties": {
    "iso:country":"DE",
    "sg:address":"Osterbrooksweg 21",
    "sg:city":"Schenefeld",
    "sg:phone":"+49 40/8397564",
    "sg:postcode":"22869",
    "sg:province":"Schleswig-Holstein",
    "wof:name":"Atik Ohg",
    "wof:placetype":"venue"
},
  "geometry": {"coordinates":[9.837473,53.59753],"type":"Point"}
}