{
  "type": "Feature",
  "properties": {
    "iso:country":"DE",
    "sg:address":"Holzstr. 19",
    "sg:city":"Mainz",
    "sg:phone":"+49 6131/227272",
    "sg:postcode":"55116",
    "sg:province":"Rheinland-Pfalz",
    "wof:name":"Restaurant Zum R\u00f6merschiff",
    "wof:placetype":"venue"
},
  "geometry": {"coordinates":[8.2773447037,49.9968719482],"type":"Point"}
}