{
  "type": "Feature",
  "properties": {
    "iso:country":"DE",
    "sg:address":"Hospitalbad 7",
    "sg:city":"Rottenburg",
    "sg:phone":"+49 7472/26283",
    "sg:postcode":"72108",
    "sg:province":"Baden-W\u00fcrttemberg",
    "wof:name":"D. G\u00fcrtuna Immobilienmakler",
    "wof:placetype":"venue"
},
  "geometry": {"coordinates":[8.9327096939,48.4753684998],"type":"Point"}
}