{
  "type": "Feature",
  "properties": {
    "iso:country":"DE",
    "sg:address":"Baderstr 8",
    "sg:city":"Rathenow",
    "sg:phone":"+49 3385/516972",
    "sg:postcode":"14712",
    "sg:province":"Brandenburg",
    "wof:name":"Werbung & Gestaltung Schruth",
    "wof:placetype":"venue"
},
  "geometry": {"coordinates":[12.330406,52.609959],"type":"Point"}
}