{
  "type": "Feature",
  "properties": {
    "iso:country":"DE",
    "sg:address":"M\u00f6rikeweg 30",
    "sg:city":"Owen",
    "sg:phone":"+49 7021/52472",
    "sg:postcode":"73277",
    "sg:province":"Baden-W\u00fcrttemberg",
    "wof:name":"E. Klein Steuerbevollm\u00e4chtigter",
    "wof:placetype":"venue"
},
  "geometry": {"coordinates":[9.4484529495,48.5926551819],"type":"Point"}
}