{
  "type": "Feature",
  "properties": {
    "iso:country":"DE",
    "sg:address":"Marderweg 32a",
    "sg:city":"Augsburg",
    "sg:phone":"+49 821/706380",
    "sg:postcode":"86169",
    "sg:province":"Bayern",
    "wof:name":"Inge Berchtold Kunststopferei",
    "wof:placetype":"venue"
},
  "geometry": {"coordinates":[10.8987989426,48.4067726135],"type":"Point"}
}