{
  "type": "Feature",
  "properties": {
    "iso:country":"DE",
    "sg:address":"Rothweg 39",
    "sg:city":"Kirchheim",
    "sg:postcode":"97268",
    "sg:province":"Bayern",
    "wof:name":"Kalamishi & Korbmann Gmbh Natursteinfachbetrieb",
    "wof:placetype":"venue"
},
  "geometry": {"coordinates":[9.8633203506,49.6587791443],"type":"Point"}
}