{
  "type": "Feature",
  "properties": {
    "iso:country":"DE",
    "sg:address":"Andernacher Str. 226",
    "sg:city":"Koblenz",
    "sg:phone":"+49 261/82290",
    "sg:postcode":"56070",
    "sg:province":"Rheinland-Pfalz",
    "wof:name":"Hoehn Kfz-verwertungsuntern.",
    "wof:placetype":"venue"
},
  "geometry": {"coordinates":[7.5814828873,50.3795471191],"type":"Point"}
}