{
  "type": "Feature",
  "properties": {
    "iso:country":"DE",
    "sg:address":"Landshuter Str. 1",
    "sg:city":"Unterschlei\u00dfheim",
    "sg:postcode":"85716",
    "sg:province":"Bayern",
    "wof:name":"Aiv Amann Industrievertretung Gmbh",
    "wof:placetype":"venue"
},
  "geometry": {"coordinates":[11.576621,48.294266],"type":"Point"}
}