{
  "type": "Feature",
  "properties": {
    "iso:country":"DE",
    "sg:address":"B\u00e4hringhausen 5",
    "sg:city":"Wermelskirchen",
    "sg:phone":"+49 2196/3830",
    "sg:postcode":"42929",
    "sg:province":"Nordrhein-Westfalen",
    "wof:name":"Helmut M\u00fcller",
    "wof:placetype":"venue"
},
  "geometry": {"coordinates":[7.1931581497,51.1245307922],"type":"Point"}
}