{
  "type": "Feature",
  "properties": {
    "iso:country":"DE",
    "sg:address":"D\u00fcrerstr. 16",
    "sg:city":"Stockelsdorf",
    "sg:phone":"+49 451/4981410",
    "sg:postcode":"23617",
    "sg:province":"Schleswig-Holstein",
    "wof:name":"P. Tretau Anlageberater",
    "wof:placetype":"venue"
},
  "geometry": {"coordinates":[10.6358766556,53.8818283081],"type":"Point"}
}