{
  "type": "Feature",
  "properties": {
    "iso:country":"DE",
    "sg:address":"Mittelwei\u00dfenbach 39 a",
    "sg:city":"Selb",
    "sg:phone":"+49 9287/99590",
    "sg:postcode":"95100",
    "sg:province":"Bayern",
    "wof:name":"Hans Fr\u00f6ber Hoch- Und Tiefbau Kg",
    "wof:placetype":"venue"
},
  "geometry": {"coordinates":[12.1003131866,50.1640281677],"type":"Point"}
}