{
  "type": "Feature",
  "properties": {
    "iso:country":"DE",
    "sg:address":"Am Wetterbach 41",
    "sg:city":"Karlsruhe",
    "sg:phone":"+49 721/451224",
    "sg:postcode":"76228",
    "sg:province":"Baden-W\u00fcrttemberg",
    "wof:name":"Tr\u00f6dler",
    "wof:placetype":"venue"
},
  "geometry": {"coordinates":[8.467004776,48.9577178955],"type":"Point"}
}