{
  "type": "Feature",
  "properties": {
    "iso:country":"DE",
    "sg:address":"Nikolaiplatz 5",
    "sg:city":"Reutlingen",
    "sg:phone":"+49 7121/321847",
    "sg:postcode":"72764",
    "sg:province":"Baden-W\u00fcrttemberg",
    "wof:name":"Kunterbunt Spielwaren",
    "wof:placetype":"venue"
},
  "geometry": {"coordinates":[9.2099885941,48.4939575195],"type":"Point"}
}