{
  "type": "Feature",
  "properties": {
    "iso:country":"DE",
    "sg:address":"Ottenser Hauptstr. 10",
    "sg:city":"Hamburg",
    "sg:postcode":"22765",
    "sg:province":"Hamburg",
    "wof:name":"Bandelt & Junius Ohg",
    "wof:placetype":"venue"
},
  "geometry": {"coordinates":[9.932639,53.552334],"type":"Point"}
}