{
  "type": "Feature",
  "properties": {
    "iso:country":"DE",
    "sg:address":"Hauptstr. 23",
    "sg:city":"Pottum",
    "sg:phone":"+49 2664/7600",
    "sg:postcode":"56459",
    "sg:province":"Rheinland-Pfalz",
    "wof:name":"Bernhard Schmidt",
    "wof:placetype":"venue"
},
  "geometry": {"coordinates":[7.997361,50.597061],"type":"Point"}
}