{
  "type": "Feature",
  "properties": {
    "iso:country":"DE",
    "sg:address":"Heerserheider Str. 31",
    "sg:city":"Bad Salzuflen",
    "sg:phone":"+49 5222/21345",
    "sg:postcode":"32107",
    "sg:province":"Nordrhein-Westfalen",
    "wof:name":"Wilhelm B\u00e4umer",
    "wof:placetype":"venue"
},
  "geometry": {"coordinates":[8.751659,52.03812],"type":"Point"}
}