{
  "type": "Feature",
  "properties": {
    "iso:country":"DE",
    "sg:address":"Von-Stauffenberg-Str. 39",
    "sg:city":"M\u00fcnster",
    "sg:phone":"+49 251/233221",
    "sg:postcode":"48151",
    "sg:province":"Nordrhein-Westfalen",
    "wof:name":"R. Albers",
    "wof:placetype":"venue"
},
  "geometry": {"coordinates":[7.6121721268,51.9453582764],"type":"Point"}
}