{
  "type": "Feature",
  "properties": {
    "iso:country":"DE",
    "sg:address":"Buchhornplatz 8",
    "sg:city":"Friedrichshafen",
    "sg:phone":"+49 7541/373873",
    "sg:postcode":"88045",
    "sg:province":"Baden-W\u00fcrttemberg",
    "wof:name":"K & G",
    "wof:placetype":"venue"
},
  "geometry": {"coordinates":[9.4817152023,47.6513366699],"type":"Point"}
}