{
  "type": "Feature",
  "properties": {
    "iso:country":"DE",
    "sg:address":"Achalmstr. 18",
    "sg:city":"Leinfelden-Echterdingen",
    "sg:phone":"+49 711/975570",
    "sg:postcode":"70771",
    "sg:province":"Baden-W\u00fcrttemberg",
    "wof:name":"Reinicke Verwaltungs- Gmbh",
    "wof:placetype":"venue"
},
  "geometry": {"coordinates":[9.118691,48.703217],"type":"Point"}
}