{
  "type": "Feature",
  "properties": {
    "iso:country":"DE",
    "sg:address":"Obere Karlstr. 2",
    "sg:city":"Blankenhain",
    "sg:phone":"+49 36459/62623",
    "sg:postcode":"99444",
    "sg:province":"Th\u00fcringen",
    "wof:name":"Irene Klein Anlageberater",
    "wof:placetype":"venue"
},
  "geometry": {"coordinates":[11.3396139145,50.858127594],"type":"Point"}
}