{
  "type": "Feature",
  "properties": {
    "iso:country":"DE",
    "sg:address":"Bellingrathweg 10",
    "sg:city":"Haan",
    "sg:phone":"+49 4921/0461514",
    "sg:postcode":"42781",
    "sg:province":"Nordrhein-Westfalen",
    "wof:name":"Jurk Schleifsysteme Gmbh",
    "wof:placetype":"venue"
},
  "geometry": {"coordinates":[6.995255,51.179169],"type":"Point"}
}