{
  "type": "Feature",
  "properties": {
    "iso:country":"DE",
    "sg:address":"Ohmstr. 10",
    "sg:city":"Bamberg",
    "sg:phone":"+49 951/14721",
    "sg:postcode":"96050",
    "sg:province":"Bayern",
    "wof:name":"Neller Gmbh & Co. Kg",
    "wof:placetype":"venue"
},
  "geometry": {"coordinates":[10.9169874191,49.895614624],"type":"Point"}
}