{
  "type": "Feature",
  "properties": {
    "iso:country":"DE",
    "sg:address":"Jakob-Germes-Str. 8",
    "sg:city":"Willich",
    "sg:phone":"+49 2154/7540",
    "sg:postcode":"47877",
    "sg:province":"Nordrhein-Westfalen",
    "wof:name":"Rudolf Hendricks",
    "wof:placetype":"venue"
},
  "geometry": {"coordinates":[6.53868,51.247093],"type":"Point"}
}