{
  "type": "Feature",
  "properties": {
    "iso:country":"DE",
    "sg:address":"Friedhofsweg 5",
    "sg:city":"Pl\u00f6tzky",
    "sg:phone":"+49 39200/51177",
    "sg:postcode":"39245",
    "sg:province":"Sachsen-Anhalt",
    "wof:name":"Kurt Zach",
    "wof:placetype":"venue"
},
  "geometry": {"coordinates":[11.8063468933,52.0541801453],"type":"Point"}
}