{
  "type": "Feature",
  "properties": {
    "iso:country":"DE",
    "sg:address":"Passauerstr. 2 a",
    "sg:city":"M\u00fcnchen",
    "sg:phone":"+49 89/74370590",
    "sg:postcode":"81369",
    "sg:province":"Bayern",
    "wof:name":"Helenen-apotheke",
    "wof:placetype":"venue"
},
  "geometry": {"coordinates":[11.53341,48.116592],"type":"Point"}
}