{
  "type": "Feature",
  "properties": {
    "iso:country":"DE",
    "sg:address":"M\u00fcckenstrauch 13",
    "sg:city":"Biebertal",
    "sg:phone":"+49 6446/921700",
    "sg:postcode":"35444",
    "sg:province":"Hessen",
    "wof:name":"J. Dietrich",
    "wof:placetype":"venue"
},
  "geometry": {"coordinates":[8.54357,50.640301],"type":"Point"}
}