{
  "type": "Feature",
  "properties": {
    "iso:country":"DE",
    "sg:address":"Kardinal-Faulhaber-Platz",
    "sg:city":"W\u00fcrzburg",
    "sg:phone":"+49 931/15323",
    "sg:postcode":"97070",
    "sg:province":"Bayern",
    "wof:name":"Buhl",
    "wof:placetype":"venue"
},
  "geometry": {"coordinates":[9.9351902008,49.7946586609],"type":"Point"}
}