{
  "type": "Feature",
  "properties": {
    "iso:country":"DE",
    "sg:address":"Rebenring 33",
    "sg:city":"Braunschweig",
    "sg:phone":"+49 531/38040",
    "sg:postcode":"38106",
    "sg:province":"Niedersachsen",
    "wof:name":"Technologiepark Braunschweig Gmbh",
    "wof:placetype":"venue"
},
  "geometry": {"coordinates":[10.531318,52.275661],"type":"Point"}
}