{
  "type": "Feature",
  "properties": {
    "iso:country":"DE",
    "sg:address":"Mittelgasse 26",
    "sg:city":"Gau-Weinheim",
    "sg:phone":"+49 6732/2348",
    "sg:postcode":"55578",
    "sg:province":"Rheinland-Pfalz",
    "wof:name":"Kath. Pfarramt St. Katharina",
    "wof:placetype":"venue"
},
  "geometry": {"coordinates":[8.0475387573,49.8472061157],"type":"Point"}
}