{
  "type": "Feature",
  "properties": {
    "iso:country":"DE",
    "sg:address":"Albert-Funk-Siedlung 7",
    "sg:city":"M\u00fclsen",
    "sg:postcode":"08132",
    "sg:province":"Sachsen",
    "wof:name":"Thomas Maron Ingenieur",
    "wof:placetype":"venue"
},
  "geometry": {"coordinates":[12.6490077972,50.7101020813],"type":"Point"}
}