{
  "type": "Feature",
  "properties": {
    "iso:country":"DE",
    "sg:address":"Lange Str. 21",
    "sg:city":"Krakow",
    "sg:phone":"+49 38457/23000",
    "sg:postcode":"18292",
    "sg:province":"Mecklenburg-Vorpommern",
    "wof:name":"Doris Fentzahn",
    "wof:placetype":"venue"
},
  "geometry": {"coordinates":[12.3657302856,53.6824493408],"type":"Point"}
}