{
  "type": "Feature",
  "properties": {
    "iso:country":"DE",
    "sg:address":"M\u00f6rikestr. 4",
    "sg:city":"Mayen",
    "sg:phone":"+49 2651/5819",
    "sg:postcode":"56727",
    "sg:province":"Rheinland-Pfalz",
    "wof:name":"Matthias Rossbach Weinanbau",
    "wof:placetype":"venue"
},
  "geometry": {"coordinates":[7.2231321335,50.3217353821],"type":"Point"}
}