{
  "type": "Feature",
  "properties": {
    "iso:country":"DE",
    "sg:address":"B\u00f6vingen 134",
    "sg:city":"Much",
    "sg:phone":"+49 2245/610080",
    "sg:postcode":"53804",
    "sg:province":"Nordrhein-Westfalen",
    "wof:name":"Anton Miebach Werkzeug- Und Maschinenbau Gmbh",
    "wof:placetype":"venue"
},
  "geometry": {"coordinates":[7.38798,50.916359],"type":"Point"}
}