{
  "type": "Feature",
  "properties": {
    "iso:country":"DE",
    "sg:address":"Baumschulenstr. 87",
    "sg:city":"Berlin",
    "sg:phone":"+49 30/5323706",
    "sg:postcode":"12437",
    "sg:province":"Berlin",
    "wof:name":"Peter Lemke",
    "wof:placetype":"venue"
},
  "geometry": {"coordinates":[13.486262,52.465153],"type":"Point"}
}