{
  "type": "Feature",
  "properties": {
    "iso:country":"DE",
    "sg:address":"Salbker Chaussee 1",
    "sg:city":"Magdeburg",
    "sg:phone":"+49 391/6213308",
    "sg:postcode":"39116",
    "sg:province":"Sachsen-Anhalt",
    "wof:name":"Ihr Augenoptiker Gmbh",
    "wof:placetype":"venue"
},
  "geometry": {"coordinates":[11.5841503143,52.0833015442],"type":"Point"}
}