{
  "type": "Feature",
  "properties": {
    "iso:country":"DE",
    "sg:address":"Uhlandstr. 26",
    "sg:city":"Sch\u00f6naich",
    "sg:phone":"+49 7031/652112",
    "sg:postcode":"71101",
    "sg:province":"Baden-W\u00fcrttemberg",
    "wof:name":"J\u00f6rg C. Koch Architekt Und Ingenieur",
    "wof:placetype":"venue"
},
  "geometry": {"coordinates":[9.066232,48.653919],"type":"Point"}
}