{
  "type": "Feature",
  "properties": {
    "iso:country":"DE",
    "sg:address":"Borngasse 3",
    "sg:city":"Feldatal",
    "sg:phone":"+49 6637/919140",
    "sg:postcode":"36325",
    "sg:province":"Hessen",
    "wof:name":"Karl-j\u00fcrgen Tigges Rechtsanwalt",
    "wof:placetype":"venue"
},
  "geometry": {"coordinates":[9.1800260544,50.6484298706],"type":"Point"}
}