{
  "type": "Feature",
  "properties": {
    "iso:country":"DE",
    "sg:address":"Pfeilshofer Weg 17",
    "sg:city":"Hamburg",
    "sg:phone":"+49 40/336076",
    "sg:postcode":"22391",
    "sg:province":"Hamburg",
    "wof:name":"Gerotex Gmbh",
    "wof:placetype":"venue"
},
  "geometry": {"coordinates":[10.0917882919,53.6429748535],"type":"Point"}
}