{
  "type": "Feature",
  "properties": {
    "iso:country":"DE",
    "sg:address":"In der Neckarhelle 115",
    "sg:city":"Heidelberg",
    "sg:phone":"+49 6221/802675",
    "sg:postcode":"69118",
    "sg:province":"Baden-W\u00fcrttemberg",
    "wof:name":"Esso Deutschland Gmbh",
    "wof:placetype":"venue"
},
  "geometry": {"coordinates":[8.7448883057,49.4174537659],"type":"Point"}
}