{
  "type": "Feature",
  "properties": {
    "iso:country":"DE",
    "sg:address":"L\u00fcbecker Str. 99a",
    "sg:city":"Magdeburg",
    "sg:phone":"+49 391/2527492",
    "sg:postcode":"39124",
    "sg:province":"Sachsen-Anhalt",
    "wof:name":"E. Banaszikiewicz",
    "wof:placetype":"venue"
},
  "geometry": {"coordinates":[11.6354179382,52.1601448059],"type":"Point"}
}