{
  "type": "Feature",
  "properties": {
    "iso:country":"DE",
    "sg:address":"T\u00fcbinger Str. 27",
    "sg:city":"Hechingen",
    "sg:phone":"+49 7471/13162",
    "sg:postcode":"72379",
    "sg:province":"Baden-W\u00fcrttemberg",
    "wof:name":"Walter Beck",
    "wof:placetype":"venue"
},
  "geometry": {"coordinates":[8.9694871902,48.3605957031],"type":"Point"}
}