{
  "type": "Feature",
  "properties": {
    "iso:country":"DE",
    "sg:address":"Eutiner Str. 54",
    "sg:city":"Pansdorf",
    "sg:phone":"+49 4504/3258",
    "sg:postcode":"23689",
    "sg:province":"Schleswig-Holstein",
    "wof:name":"Express-textilpflege Horst Stieglitz Gmbh",
    "wof:placetype":"venue"
},
  "geometry": {"coordinates":[10.7123756409,53.9846000671],"type":"Point"}
}