{
  "type": "Feature",
  "properties": {
    "iso:country":"DE",
    "sg:address":"Kehler Str. 67",
    "sg:city":"Willst\u00e4tt",
    "sg:phone":"+49 7854/7954",
    "sg:postcode":"77731",
    "sg:province":"Baden-W\u00fcrttemberg",
    "wof:name":"Blume",
    "wof:placetype":"venue"
},
  "geometry": {"coordinates":[7.8543839455,48.527141571],"type":"Point"}
}