{
  "type": "Feature",
  "properties": {
    "iso:country":"DE",
    "sg:address":"Stuifenstr. 8",
    "sg:city":"Stuttgart",
    "sg:phone":"+49 711/260498",
    "sg:postcode":"70188",
    "sg:province":"Baden-W\u00fcrttemberg",
    "wof:name":"Helmut Fehling",
    "wof:placetype":"venue"
},
  "geometry": {"coordinates":[9.2053966522,48.7852325439],"type":"Point"}
}