{
  "type": "Feature",
  "properties": {
    "iso:country":"DE",
    "sg:address":"Spandauer Burgwall 22",
    "sg:city":"Berlin",
    "sg:postcode":"13581",
    "sg:province":"Berlin",
    "wof:name":"Comtrade Consulting Sokolov Barshevskij Zscheyge Ohg",
    "wof:placetype":"venue"
},
  "geometry": {"coordinates":[13.1980333328,52.5274124146],"type":"Point"}
}