{
  "type": "Feature",
  "properties": {
    "iso:country":"DE",
    "sg:address":"Im H\u00f6stert 17",
    "sg:city":"Euskirchen",
    "sg:phone":"+49 2251/780480",
    "sg:postcode":"53881",
    "sg:province":"Nordrhein-Westfalen",
    "wof:name":"Fas Facilities And Services Montage- Und Anlagenbau Gmbh",
    "wof:placetype":"venue"
},
  "geometry": {"coordinates":[6.82529,50.653301],"type":"Point"}
}