{
  "type": "Feature",
  "properties": {
    "iso:country":"DE",
    "sg:address":"Auf dem Nippes 8",
    "sg:city":"Nettersheim",
    "sg:phone":"+49 2486/226",
    "sg:postcode":"53947",
    "sg:province":"Nordrhein-Westfalen",
    "wof:name":"Karl H\u00f6ger Gmbh",
    "wof:placetype":"venue"
},
  "geometry": {"coordinates":[6.5779671669,50.4744873047],"type":"Point"}
}