{
  "type": "Feature",
  "properties": {
    "iso:country":"DE",
    "sg:address":"Zum Wirrgarten 2",
    "sg:city":"Lich",
    "sg:phone":"+49 6004/2563",
    "sg:postcode":"35423",
    "sg:province":"Hessen",
    "wof:name":"Wilfried Euler",
    "wof:placetype":"venue"
},
  "geometry": {"coordinates":[8.762882,50.481239],"type":"Point"}
}