{
  "type": "Feature",
  "properties": {
    "iso:country":"DE",
    "sg:address":"Haselbergweg 1",
    "sg:city":"Geiersthal",
    "sg:phone":"+49 9923/9804",
    "sg:postcode":"94244",
    "sg:province":"Bayern",
    "wof:name":"Franz Xaver Moser",
    "wof:placetype":"venue"
},
  "geometry": {"coordinates":[12.9624586105,49.0366249084],"type":"Point"}
}