{
  "type": "Feature",
  "properties": {
    "iso:country":"DE",
    "sg:address":"Lu\u00dfhardtstr. 20",
    "sg:city":"Karlsdorf-Neuthard",
    "sg:phone":"+49 7251/94300",
    "sg:postcode":"76689",
    "sg:province":"Baden-W\u00fcrttemberg",
    "wof:name":"Lu\u00dfhardt Transportbeton Gmbh & Co. Kg",
    "wof:placetype":"venue"
},
  "geometry": {"coordinates":[8.5475740433,49.149394989],"type":"Point"}
}