{
  "type": "Feature",
  "properties": {
    "iso:country":"DE",
    "sg:address":"Eckstr. 4",
    "sg:city":"Homburg",
    "sg:phone":"+49 6841/2296",
    "sg:postcode":"66424",
    "sg:province":"Saarland",
    "wof:name":"Pulver",
    "wof:placetype":"venue"
},
  "geometry": {"coordinates":[7.3697209358,49.3013038635],"type":"Point"}
}