{
  "type": "Feature",
  "properties": {
    "iso:country":"DE",
    "sg:address":"Raiffeisenstr. 2",
    "sg:city":"Wei\u00dfenborn",
    "sg:phone":"+49 5659/305",
    "sg:postcode":"37299",
    "sg:province":"Hessen",
    "wof:name":"Rudi Franke",
    "wof:placetype":"venue"
},
  "geometry": {"coordinates":[10.147644,51.106464],"type":"Point"}
}