{
  "type": "Feature",
  "properties": {
    "iso:country":"DE",
    "sg:address":"Obertor 17",
    "sg:city":"Ilfeld",
    "sg:phone":"+49 36331/46290",
    "sg:postcode":"99768",
    "sg:province":"Th\u00fcringen",
    "wof:name":"Ralf Ernert",
    "wof:placetype":"venue"
},
  "geometry": {"coordinates":[10.782996,51.580753],"type":"Point"}
}