{
  "type": "Feature",
  "properties": {
    "iso:country":"DE",
    "sg:address":"Helstr. 12",
    "sg:city":"Winterlingen",
    "sg:phone":"+49 7434/8560",
    "sg:postcode":"72474",
    "sg:province":"Baden-W\u00fcrttemberg",
    "wof:name":"E. Und G. Neher",
    "wof:placetype":"venue"
},
  "geometry": {"coordinates":[9.1198310852,48.1781349182],"type":"Point"}
}