{
  "type": "Feature",
  "properties": {
    "iso:country":"DE",
    "sg:address":"Unterer Hof 10",
    "sg:city":"Heusweiler",
    "sg:phone":"+49 6806/77496",
    "sg:postcode":"66265",
    "sg:province":"Saarland",
    "wof:name":"Marianne Paul",
    "wof:placetype":"venue"
},
  "geometry": {"coordinates":[6.9387798309,49.3502655029],"type":"Point"}
}