{
  "type": "Feature",
  "properties": {
    "iso:country":"DE",
    "sg:address":"Kirchweg 3",
    "sg:city":"B\u00fcckeburg",
    "sg:phone":"+49 5722/91311",
    "sg:postcode":"31675",
    "sg:province":"Niedersachsen",
    "wof:name":"Eckehard Brands Rechtsanwalt",
    "wof:placetype":"venue"
},
  "geometry": {"coordinates":[9.0503892899,52.2598152161],"type":"Point"}
}