{
  "type": "Feature",
  "properties": {
    "iso:country":"DE",
    "sg:address":"Steinstr. 28",
    "sg:city":"Duderstadt",
    "sg:phone":"+49 5527/941510",
    "sg:postcode":"37115",
    "sg:province":"Niedersachsen",
    "wof:name":"Coolstuff-uhren",
    "wof:placetype":"venue"
},
  "geometry": {"coordinates":[10.2613592148,51.5114860535],"type":"Point"}
}