{
  "type": "Feature",
  "properties": {
    "iso:country":"DE",
    "sg:address":"Kunigunde 6",
    "sg:city":"Liebenburg",
    "sg:phone":"+49 5346/4416",
    "sg:postcode":"38704",
    "sg:province":"Niedersachsen",
    "wof:name":"Tief- & Stra\u00dfenbau Dipl.-ing. Dirk Pr\u00fcser",
    "wof:placetype":"venue"
},
  "geometry": {"coordinates":[10.375734,51.989151],"type":"Point"}
}