{
  "type": "Feature",
  "properties": {
    "iso:country":"DE",
    "sg:address":"Bergsteig 3",
    "sg:city":"Kulmbach",
    "sg:phone":"+49 9221/4938",
    "sg:postcode":"95326",
    "sg:province":"Bayern",
    "wof:name":"E. Und W. Wittek",
    "wof:placetype":"venue"
},
  "geometry": {"coordinates":[11.456276,50.102592],"type":"Point"}
}