{
  "type": "Feature",
  "properties": {
    "iso:country":"DE",
    "sg:address":"Stadtwaldstr. 30",
    "sg:city":"M\u00f6nchengladbach",
    "sg:phone":"+49 2161/584202",
    "sg:postcode":"41179",
    "sg:province":"Nordrhein-Westfalen",
    "wof:name":"P. Und H. Sch\u00fcrger",
    "wof:placetype":"venue"
},
  "geometry": {"coordinates":[6.373194,51.147942],"type":"Point"}
}