{
  "type": "Feature",
  "properties": {
    "iso:country":"DE",
    "sg:address":"Schlo\u00dfstr. 80",
    "sg:city":"Berlin",
    "sg:phone":"+49 30/7904",
    "sg:postcode":"12165",
    "sg:province":"Berlin",
    "wof:name":"Beratungsstelle F\u00fcr Behinderte",
    "wof:placetype":"venue"
},
  "geometry": {"coordinates":[13.319961,52.455696],"type":"Point"}
}