{
  "type": "Feature",
  "properties": {
    "iso:country":"DE",
    "sg:address":"Isselhorster Str. 380",
    "sg:city":"G\u00fctersloh",
    "sg:phone":"+49 4952/416163",
    "sg:postcode":"33334",
    "sg:province":"Nordrhein-Westfalen",
    "wof:name":"Willy Osthus",
    "wof:placetype":"venue"
},
  "geometry": {"coordinates":[8.4205560684,51.9449539185],"type":"Point"}
}