{
  "type": "Feature",
  "properties": {
    "iso:country":"DE",
    "sg:address":"Hintergasse 8",
    "sg:city":"Friedewald",
    "sg:postcode":"36289",
    "sg:province":"Hessen",
    "wof:name":"A. Ehrhoff",
    "wof:placetype":"venue"
},
  "geometry": {"coordinates":[9.858353,50.884426],"type":"Point"}
}