{
  "type": "Feature",
  "properties": {
    "iso:country":"DE",
    "sg:address":"Buer-Gladbecker-Strasse 71",
    "sg:city":"Gelsenkirchen",
    "sg:postcode":"45894",
    "sg:province":"Nordrhein-Westfalen",
    "wof:name":"Ericsson-siemens-klingelt\u00f6ne & Logos",
    "wof:placetype":"venue"
},
  "geometry": {"coordinates":[7.036891,51.579369],"type":"Point"}
}