{
  "type": "Feature",
  "properties": {
    "iso:country":"DE",
    "sg:address":"Kirchbachstr. 37",
    "sg:city":"M\u00fclheim",
    "sg:phone":"+49 208/405468",
    "sg:postcode":"45476",
    "sg:province":"Nordrhein-Westfalen",
    "wof:name":"Werner Kolkmann",
    "wof:placetype":"venue"
},
  "geometry": {"coordinates":[6.8569788933,51.4577178955],"type":"Point"}
}