{
  "type": "Feature",
  "properties": {
    "iso:country":"DE",
    "sg:address":"Zum Seeberg 4",
    "sg:city":"Tolk",
    "sg:phone":"+49 4622/2268",
    "sg:postcode":"24894",
    "sg:province":"Schleswig-Holstein",
    "wof:name":"Egon Rosin",
    "wof:placetype":"venue"
},
  "geometry": {"coordinates":[9.634119,54.580376],"type":"Point"}
}