{
  "type": "Feature",
  "properties": {
    "iso:country":"DE",
    "sg:address":"Humboldtstr. 11",
    "sg:city":"Gro\u00dfkrotzenburg",
    "sg:phone":"+49 6186/201670",
    "sg:postcode":"63538",
    "sg:province":"Hessen",
    "wof:name":"Ullrich Oberfl\u00e4chentechnik- Vertriebsgesellschaft Mbh",
    "wof:placetype":"venue"
},
  "geometry": {"coordinates":[8.98907,50.08194],"type":"Point"}
}