{
  "type": "Feature",
  "properties": {
    "iso:country":"DE",
    "sg:address":"Petersbergstr. 5",
    "sg:city":"Sankt Augustin",
    "sg:postcode":"53757",
    "sg:province":"Nordrhein-Westfalen",
    "wof:name":"Ars Audiendi Ohg",
    "wof:placetype":"venue"
},
  "geometry": {"coordinates":[7.187183857,50.7560081482],"type":"Point"}
}