{
  "type": "Feature",
  "properties": {
    "iso:country":"DE",
    "sg:address":"Dornenweg 23",
    "sg:city":"Langen",
    "sg:phone":"+49 4707/233",
    "sg:postcode":"27607",
    "sg:province":"Niedersachsen",
    "wof:name":"Raiffeisen Weser-elbe Eg",
    "wof:placetype":"venue"
},
  "geometry": {"coordinates":[8.59342,53.596249],"type":"Point"}
}