{
  "type": "Feature",
  "properties": {
    "iso:country":"DE",
    "sg:address":"Merianstr. 20",
    "sg:city":"Trier",
    "sg:phone":"+49 651/78090",
    "sg:postcode":"54292",
    "sg:province":"Rheinland-Pfalz",
    "wof:name":"Sade Design",
    "wof:placetype":"venue"
},
  "geometry": {"coordinates":[6.635145,49.762093],"type":"Point"}
}