{
  "type": "Feature",
  "properties": {
    "iso:country":"DE",
    "sg:address":"Wahlerter Str. 28",
    "sg:city":"Bad Soden-Salm\u00fcnster",
    "sg:phone":"+49 6056/2743",
    "sg:postcode":"63628",
    "sg:province":"Hessen",
    "wof:name":"Jeanette",
    "wof:placetype":"venue"
},
  "geometry": {"coordinates":[9.369062,50.315544],"type":"Point"}
}