{
  "type": "Feature",
  "properties": {
    "iso:country":"DE",
    "sg:address":"Gummersbacher Str. 142",
    "sg:city":"Marienheide",
    "sg:phone":"+49 2261/22333",
    "sg:postcode":"51709",
    "sg:province":"Nordrhein-Westfalen",
    "wof:name":"Franke",
    "wof:placetype":"venue"
},
  "geometry": {"coordinates":[7.5571689606,51.0716781616],"type":"Point"}
}