{
  "type": "Feature",
  "properties": {
    "iso:country":"DE",
    "sg:address":"An der Linde 6",
    "sg:city":"Sch\u00f6ffengrund",
    "sg:phone":"+49 6445/7101",
    "sg:postcode":"35641",
    "sg:province":"Hessen",
    "wof:name":"G\u00fcnter Hecker Gmbh",
    "wof:placetype":"venue"
},
  "geometry": {"coordinates":[8.4608602524,50.5164031982],"type":"Point"}
}