{
  "type": "Feature",
  "properties": {
    "iso:country":"DE",
    "sg:address":"Hauptstr. 69",
    "sg:city":"Hackenheim",
    "sg:phone":"+49 671/65312",
    "sg:postcode":"55546",
    "sg:province":"Rheinland-Pfalz",
    "wof:name":"Metzlers Gasthof",
    "wof:placetype":"venue"
},
  "geometry": {"coordinates":[7.8965468407,49.8228569031],"type":"Point"}
}