{
  "type": "Feature",
  "properties": {
    "iso:country":"DE",
    "sg:address":"Marwitzer Str. 29",
    "sg:city":"Berlin",
    "sg:phone":"+49 30/3751032",
    "sg:postcode":"13589",
    "sg:province":"Berlin",
    "wof:name":"Adolf Fekl",
    "wof:placetype":"venue"
},
  "geometry": {"coordinates":[13.190153,52.558857],"type":"Point"}
}