{
  "type": "Feature",
  "properties": {
    "iso:country":"DE",
    "sg:address":"Beethovenstr. 34",
    "sg:city":"Lampertheim",
    "sg:postcode":"68623",
    "sg:province":"Hessen",
    "wof:name":"Rosen.-apotheke Inh. Ulla Hildebrand E. Kfm.",
    "wof:placetype":"venue"
},
  "geometry": {"coordinates":[8.46915,49.604698],"type":"Point"}
}