{
  "type": "Feature",
  "properties": {
    "iso:country":"DE",
    "sg:address":"Wannwickerstra\u00dfe 17",
    "sg:city":"Rees",
    "sg:phone":"+49 2851/2226",
    "sg:postcode":"46459",
    "sg:province":"Nordrhein-Westfalen",
    "wof:name":"Bauen Mit Der Rkb In Rees Und Umgebung",
    "wof:placetype":"venue"
},
  "geometry": {"coordinates":[6.413556,51.766491],"type":"Point"}
}