{
  "type": "Feature",
  "properties": {
    "iso:country":"DE",
    "sg:address":"Further Weg 31",
    "sg:city":"Leichlingen",
    "sg:phone":"+49 2175/88220609",
    "sg:postcode":"42799",
    "sg:province":"Nordrhein-Westfalen",
    "wof:name":"First Base Music",
    "wof:placetype":"venue"
},
  "geometry": {"coordinates":[6.9900598526,51.1021194458],"type":"Point"}
}