{
  "type": "Feature",
  "properties": {
    "iso:country":"DE",
    "sg:address":"Gerwigstr. 14",
    "sg:city":"Karlsruhe",
    "sg:phone":"+49 721/696224",
    "sg:postcode":"76131",
    "sg:province":"Baden-W\u00fcrttemberg",
    "wof:name":"U. Kindor",
    "wof:placetype":"venue"
},
  "geometry": {"coordinates":[8.4250040054,49.009147644],"type":"Point"}
}