{
  "type": "Feature",
  "properties": {
    "iso:country":"DE",
    "sg:address":"Cranger Str. 357",
    "sg:city":"Gelsenkirchen",
    "sg:phone":"+49 209/73353",
    "sg:postcode":"45891",
    "sg:province":"Nordrhein-Westfalen",
    "wof:name":"Kosmetikstudio Ks Gmbh",
    "wof:placetype":"venue"
},
  "geometry": {"coordinates":[7.097266,51.555672],"type":"Point"}
}