{
  "type": "Feature",
  "properties": {
    "iso:country":"DE",
    "sg:address":"Im Tobel 29",
    "sg:city":"Kirchheim",
    "sg:phone":"+49 7021/979444",
    "sg:postcode":"73230",
    "sg:province":"Baden-W\u00fcrttemberg",
    "wof:name":"Qdt W\u00e4rmerohrtauscher Beratungs- Und Vertriebs Gmbh",
    "wof:placetype":"venue"
},
  "geometry": {"coordinates":[9.4247913361,48.6620979309],"type":"Point"}
}