{
  "type": "Feature",
  "properties": {
    "iso:country":"DE",
    "sg:address":"Jakob-Krebs-Str. 106",
    "sg:city":"Willich",
    "sg:phone":"+49 2156/2577",
    "sg:postcode":"47877",
    "sg:province":"Nordrhein-Westfalen",
    "wof:name":"Vereinigte Seidenweberei Ag",
    "wof:placetype":"venue"
},
  "geometry": {"coordinates":[6.4536547661,51.2829017639],"type":"Point"}
}