{
  "type": "Feature",
  "properties": {
    "iso:country":"DE",
    "sg:address":"Grabower Str. 51",
    "sg:city":"Burg",
    "sg:postcode":"39288",
    "sg:province":"Sachsen-Anhalt",
    "wof:name":"Deutsche Telekom T-punkt",
    "wof:placetype":"venue"
},
  "geometry": {"coordinates":[11.8607349396,52.2672538757],"type":"Point"}
}