{
  "type": "Feature",
  "properties": {
    "iso:country":"DE",
    "sg:address":"Geschwister-Scholl-Str. 28",
    "sg:city":"Forchtenberg",
    "sg:phone":"+49 7947/7919",
    "sg:postcode":"74670",
    "sg:province":"Baden-W\u00fcrttemberg",
    "wof:name":"Epd-bezirksredaktion Nordw\u00fcrt.",
    "wof:placetype":"venue"
},
  "geometry": {"coordinates":[9.562245369,49.2933883667],"type":"Point"}
}