{
  "type": "Feature",
  "properties": {
    "iso:country":"DE",
    "sg:address":"Winterleiten 3 b",
    "sg:city":"Kist",
    "sg:postcode":"97270",
    "sg:province":"Bayern",
    "wof:name":"Dr.k\u00fcchler Medizintechnik Gmbh",
    "wof:placetype":"venue"
},
  "geometry": {"coordinates":[9.8397674561,49.7462120056],"type":"Point"}
}