{
  "type": "Feature",
  "properties": {
    "iso:country":"DE",
    "sg:address":"Groenesteynstr. 8",
    "sg:city":"Bruchsal",
    "sg:phone":"+49 7251",
    "sg:postcode":"76646",
    "sg:province":"Baden-W\u00fcrttemberg",
    "wof:name":"Eric Falbe",
    "wof:placetype":"venue"
},
  "geometry": {"coordinates":[8.5986204147,49.1301193237],"type":"Point"}
}