{
  "type": "Feature",
  "properties": {
    "iso:country":"DE",
    "sg:address":"Am Stiftswingert 4",
    "sg:city":"Mainz",
    "sg:phone":"+49 6131/982640",
    "sg:postcode":"55131",
    "sg:province":"Rheinland-Pfalz",
    "wof:name":"Hotel Am Stiftswingert",
    "wof:placetype":"venue"
},
  "geometry": {"coordinates":[8.280090332,49.9880447388],"type":"Point"}
}