{
  "type": "Feature",
  "properties": {
    "iso:country":"DE",
    "sg:address":"Westfalendamm 54",
    "sg:city":"Ahlen",
    "sg:phone":"+49 2382/86086",
    "sg:postcode":"59227",
    "sg:province":"Nordrhein-Westfalen",
    "wof:name":"Tbi Technische Beratung Industrie-brunhilde Harsch",
    "wof:placetype":"venue"
},
  "geometry": {"coordinates":[7.8844738007,51.7580223083],"type":"Point"}
}