{
  "type": "Feature",
  "properties": {
    "iso:country":"DE",
    "sg:address":"Markt 10",
    "sg:city":"Kr\u00f6pelin",
    "sg:phone":"+49 38292/82353",
    "sg:postcode":"18236",
    "sg:province":"Mecklenburg-Vorpommern",
    "wof:name":"Tischlerei Stern",
    "wof:placetype":"venue"
},
  "geometry": {"coordinates":[11.79524,54.070992],"type":"Point"}
}