{
  "type": "Feature",
  "properties": {
    "iso:country":"DE",
    "sg:address":"Ringstr. 21",
    "sg:city":"Willingen",
    "sg:phone":"+49 5632/1008",
    "sg:postcode":"34508",
    "sg:province":"Hessen",
    "wof:name":"E. Biederbick Elektro Mstr.",
    "wof:placetype":"venue"
},
  "geometry": {"coordinates":[8.66597,51.284309],"type":"Point"}
}