{
  "type": "Feature",
  "properties": {
    "iso:country":"DE",
    "sg:address":"Bellevue 29",
    "sg:city":"Hamburg",
    "sg:phone":"+49 40/2795656",
    "sg:postcode":"22301",
    "sg:province":"Hamburg",
    "wof:name":"Elbe-drei Werbeagentur Gmbh",
    "wof:placetype":"venue"
},
  "geometry": {"coordinates":[10.0041255951,53.5780944824],"type":"Point"}
}