{
  "type": "Feature",
  "properties": {
    "iso:country":"DE",
    "sg:address":"Osterstr. 59",
    "sg:city":"Laatzen",
    "sg:phone":"+49 5102/3889",
    "sg:postcode":"30880",
    "sg:province":"Niedersachsen",
    "wof:name":"Hans Oelke",
    "wof:placetype":"venue"
},
  "geometry": {"coordinates":[9.84245,52.27142],"type":"Point"}
}