{
  "type": "Feature",
  "properties": {
    "iso:country":"DE",
    "sg:address":"Rosenstr. 1",
    "sg:city":"Tecklenburg",
    "sg:phone":"+49 5481/7878",
    "sg:postcode":"49545",
    "sg:province":"Nordrhein-Westfalen",
    "wof:name":"Stift-apotheke",
    "wof:placetype":"venue"
},
  "geometry": {"coordinates":[7.886355,52.213638],"type":"Point"}
}