{
  "type": "Feature",
  "properties": {
    "iso:country":"DE",
    "sg:address":"Hechinger Str. 92",
    "sg:city":"Albstadt",
    "sg:phone":"+49 7432/8679",
    "sg:postcode":"72461",
    "sg:province":"Baden-W\u00fcrttemberg",
    "wof:name":"Mesuts",
    "wof:placetype":"venue"
},
  "geometry": {"coordinates":[9.0149211884,48.2594985962],"type":"Point"}
}