{
  "type": "Feature",
  "properties": {
    "iso:country":"DE",
    "sg:address":"Lehmder Str. 380",
    "sg:city":"Rastede",
    "sg:phone":"+49 4402/7482",
    "sg:postcode":"26180",
    "sg:province":"Niedersachsen",
    "wof:name":"Walter Kaschig",
    "wof:placetype":"venue"
},
  "geometry": {"coordinates":[8.211558,53.297985],"type":"Point"}
}