{
  "type": "Feature",
  "properties": {
    "iso:country":"DE",
    "sg:address":"Eiserntalstr. 185",
    "sg:city":"Siegen",
    "sg:postcode":"57080",
    "sg:province":"Nordrhein-Westfalen",
    "wof:name":"Wkm-multimedia Gmbh",
    "wof:placetype":"venue"
},
  "geometry": {"coordinates":[8.019819,50.831043],"type":"Point"}
}