{
  "type": "Feature",
  "properties": {
    "iso:country":"DE",
    "sg:address":"K\u00f6nigsberger Str. 24",
    "sg:city":"Stade",
    "sg:phone":"+49 4141/5772",
    "sg:postcode":"21683",
    "sg:province":"Niedersachsen",
    "wof:name":"G. Thiel",
    "wof:placetype":"venue"
},
  "geometry": {"coordinates":[9.4766407013,53.6526641846],"type":"Point"}
}