{
  "type": "Feature",
  "properties": {
    "iso:country":"DE",
    "sg:address":"Frauenlobstr. 57",
    "sg:city":"Mainz",
    "sg:phone":"+49 6131/674324",
    "sg:postcode":"55118",
    "sg:province":"Rheinland-Pfalz",
    "wof:name":"P. Krag & M. Ostermann",
    "wof:placetype":"venue"
},
  "geometry": {"coordinates":[8.262184,50.007328],"type":"Point"}
}