{
  "type": "Feature",
  "properties": {
    "iso:country":"DE",
    "sg:address":"Uhlenbusch 111",
    "sg:city":"Siek",
    "sg:postcode":"22962",
    "sg:province":"Schleswig-Holstein",
    "wof:name":"Whl Leasing Ges. Mbh",
    "wof:placetype":"venue"
},
  "geometry": {"coordinates":[10.2631998062,53.6271781921],"type":"Point"}
}