{
  "type": "Feature",
  "properties": {
    "iso:country":"DE",
    "sg:address":"Bahnstr. 7",
    "sg:city":"Plankstadt",
    "sg:phone":"+49 6202/17788",
    "sg:postcode":"68723",
    "sg:province":"Baden-W\u00fcrttemberg",
    "wof:name":"Dieter Betzwieser Immobilienmakler",
    "wof:placetype":"venue"
},
  "geometry": {"coordinates":[8.5984315872,49.387966156],"type":"Point"}
}