{
  "type": "Feature",
  "properties": {
    "iso:country":"DE",
    "sg:address":"Balderhaar 11",
    "sg:city":"Wielen",
    "sg:phone":"+49 5948/556",
    "sg:postcode":"49847",
    "sg:province":"Niedersachsen",
    "wof:name":"Berend-jan Oelen",
    "wof:placetype":"venue"
},
  "geometry": {"coordinates":[6.707796,52.527702],"type":"Point"}
}