{
  "type": "Feature",
  "properties": {
    "iso:country":"DE",
    "sg:address":"Gro\u00dfer Winkel 19",
    "sg:city":"Sasbach",
    "sg:phone":"+49 7841/3223",
    "sg:postcode":"77880",
    "sg:province":"Baden-W\u00fcrttemberg",
    "wof:name":"Albert Ernst Kg",
    "wof:placetype":"venue"
},
  "geometry": {"coordinates":[8.094581604,48.6414680481],"type":"Point"}
}