{
  "type": "Feature",
  "properties": {
    "iso:country":"DE",
    "sg:address":"Heiligenthaler Str. 4",
    "sg:city":"L\u00fcneburg",
    "sg:phone":"+49 4131/404100",
    "sg:postcode":"21335",
    "sg:province":"Niedersachsen",
    "wof:name":"Teclapharm Gmbh Arzneimittel- Und Kosmetika-",
    "wof:placetype":"venue"
},
  "geometry": {"coordinates":[10.357,53.210789],"type":"Point"}
}