{
  "type": "Feature",
  "properties": {
    "iso:country":"DE",
    "sg:address":"Untere Aue 7",
    "sg:city":"Uder",
    "sg:phone":"+49 36083/4850",
    "sg:postcode":"37318",
    "sg:province":"Th\u00fcringen",
    "wof:name":"Grs Grafik-roller-service Gmbh",
    "wof:placetype":"venue"
},
  "geometry": {"coordinates":[10.040707,51.371315],"type":"Point"}
}