{
  "type": "Feature",
  "properties": {
    "iso:country":"DE",
    "sg:address":"Dorfstr. 9a",
    "sg:city":"Uebigau",
    "sg:phone":"+49 35365/2843",
    "sg:postcode":"04938",
    "sg:province":"Brandenburg",
    "wof:name":"F. Tschischka",
    "wof:placetype":"venue"
},
  "geometry": {"coordinates":[13.3027973175,51.5960960388],"type":"Point"}
}