{
  "type": "Feature",
  "properties": {
    "iso:country":"DE",
    "sg:address":"F\u00e4rberstr. 17",
    "sg:city":"Albstadt",
    "sg:phone":"+49 7432/5146",
    "sg:postcode":"72461",
    "sg:province":"Baden-W\u00fcrttemberg",
    "wof:name":"Ch. E. H. Bitzer Verpachtung Gmbh & Co. Kg",
    "wof:placetype":"venue"
},
  "geometry": {"coordinates":[9.002566,48.258286],"type":"Point"}
}