{
  "type": "Feature",
  "properties": {
    "iso:country":"DE",
    "sg:city":"Ulm",
    "sg:postcode":"89075",
    "sg:province":"Baden-W\u00fcrttemberg",
    "wof:name":"Spielautomaten Online - Datenbank Forum Gebrauchte Ger\u00e4te",
    "wof:placetype":"venue"
},
  "geometry": {"coordinates":[10.01808,48.430061],"type":"Point"}
}