{
  "type": "Feature",
  "properties": {
    "iso:country":"DE",
    "sg:address":"Eisensteinstr. 18",
    "sg:city":"Osterode",
    "sg:phone":"+49 5522/3808",
    "sg:postcode":"37520",
    "sg:province":"Niedersachsen",
    "wof:name":"Margitta St\u00fctzer",
    "wof:placetype":"venue"
},
  "geometry": {"coordinates":[10.2491855621,51.7292747498],"type":"Point"}
}