{
  "type": "Feature",
  "properties": {
    "iso:country":"DE",
    "sg:address":"Erlenstr. 25",
    "sg:city":"Dierdorf",
    "sg:phone":"+49 2689/7715",
    "sg:postcode":"56269",
    "sg:province":"Rheinland-Pfalz",
    "wof:name":"Gerd Nies",
    "wof:placetype":"venue"
},
  "geometry": {"coordinates":[7.6655421257,50.5782470703],"type":"Point"}
}