{
  "type": "Feature",
  "properties": {
    "iso:country":"DE",
    "sg:address":"Bergerstr. 25",
    "sg:city":"Solingen",
    "sg:phone":"+49 4921/2811022",
    "sg:postcode":"42657",
    "sg:province":"Nordrhein-Westfalen",
    "wof:name":"Hermann & Schmachtenberg Kunststofftechnik Gmbh",
    "wof:placetype":"venue"
},
  "geometry": {"coordinates":[7.0611171722,51.1507225037],"type":"Point"}
}