{
  "type": "Feature",
  "properties": {
    "iso:country":"DE",
    "sg:address":"Kurhausstr. 13",
    "sg:city":"Bad Kreuznach",
    "sg:phone":"+49 671/33392",
    "sg:postcode":"55543",
    "sg:province":"Rheinland-Pfalz",
    "wof:name":"H. R. Telscher",
    "wof:placetype":"venue"
},
  "geometry": {"coordinates":[7.855663,49.842342],"type":"Point"}
}