{
  "type": "Feature",
  "properties": {
    "iso:country":"DE",
    "sg:address":"Burgstr. 22",
    "sg:city":"Mei\u00dfen",
    "sg:phone":"+49 3521/453642",
    "sg:postcode":"01662",
    "sg:province":"Sachsen",
    "wof:name":"Antje Hainz Architektin",
    "wof:placetype":"venue"
},
  "geometry": {"coordinates":[13.470491,51.164425],"type":"Point"}
}