{
  "type": "Feature",
  "properties": {
    "iso:country":"DE",
    "sg:address":"Ludwigstr. 39",
    "sg:city":"Scheyern",
    "sg:phone":"+49 8441/3103",
    "sg:postcode":"85298",
    "sg:province":"Bayern",
    "wof:name":"Dr. Hermann Enz Tierarzt",
    "wof:placetype":"venue"
},
  "geometry": {"coordinates":[11.4612970352,48.5001907349],"type":"Point"}
}