{
  "type": "Feature",
  "properties": {
    "iso:country":"DE",
    "sg:address":"Thomas-Mann-Str. 21",
    "sg:city":"Dortmund",
    "sg:phone":"+49 231/514436",
    "sg:postcode":"44141",
    "sg:province":"Nordrhein-Westfalen",
    "wof:name":"Wiscon",
    "wof:placetype":"venue"
},
  "geometry": {"coordinates":[7.49568,51.506508],"type":"Point"}
}