{
  "type": "Feature",
  "properties": {
    "iso:country":"DE",
    "sg:address":"Silcherstra\u00dfe 16",
    "sg:city":"Obernheim / W\u00fcrttemberg",
    "sg:phone":"+49 7436/910860",
    "sg:postcode":"72364",
    "sg:province":"Baden-W\u00fcrttemberg",
    "wof:name":"Gottfried Moser Dreherei",
    "wof:placetype":"venue"
},
  "geometry": {"coordinates":[8.8560800552,48.1649703979],"type":"Point"}
}