{
  "type": "Feature",
  "properties": {
    "iso:country":"DE",
    "sg:address":"Sinabronner Str. 8",
    "sg:city":"Lonsee",
    "sg:postcode":"89173",
    "sg:province":"Baden-W\u00fcrttemberg",
    "wof:name":"Fwg Forstbetriebs- Und Waldbau Gmbh",
    "wof:placetype":"venue"
},
  "geometry": {"coordinates":[9.922012,48.541103],"type":"Point"}
}