{
  "type": "Feature",
  "properties": {
    "iso:country":"DE",
    "sg:address":"Karl-Leopold-Str. 26",
    "sg:city":"Karlsruhe",
    "sg:phone":"+49 721/481342",
    "sg:postcode":"76229",
    "sg:province":"Baden-W\u00fcrttemberg",
    "wof:name":"E. E. Scheidt Elektromeister",
    "wof:placetype":"venue"
},
  "geometry": {"coordinates":[8.492503,49.010906],"type":"Point"}
}