{
  "type": "Feature",
  "properties": {
    "iso:country":"DE",
    "sg:address":"Potsdamer Str. 2",
    "sg:city":"Luckenwalde",
    "sg:phone":"+49 3371/620352",
    "sg:postcode":"14943",
    "sg:province":"Brandenburg",
    "wof:name":"E. Michaelis",
    "wof:placetype":"venue"
},
  "geometry": {"coordinates":[13.1760320663,52.095287323],"type":"Point"}
}