{
  "type": "Feature",
  "properties": {
    "iso:country":"DE",
    "sg:address":"Hindenburgstr. 24",
    "sg:city":"Hannover",
    "sg:phone":"+49 511/817031",
    "sg:postcode":"30175",
    "sg:province":"Niedersachsen",
    "wof:name":"Robert Blanke Kg",
    "wof:placetype":"venue"
},
  "geometry": {"coordinates":[9.7595329285,52.3787574768],"type":"Point"}
}