{
  "type": "Feature",
  "properties": {
    "iso:country":"DE",
    "sg:address":"Schulweg 11",
    "sg:city":"G\u00f6tz",
    "sg:phone":"+49 33207/70134",
    "sg:postcode":"14778",
    "sg:province":"Brandenburg",
    "wof:name":"M. Kuczera",
    "wof:placetype":"venue"
},
  "geometry": {"coordinates":[12.71925,52.421242],"type":"Point"}
}