{
  "type": "Feature",
  "properties": {
    "iso:country":"DE",
    "sg:address":"Eberhardstr. 27",
    "sg:city":"Friedrichshafen",
    "sg:phone":"+49 7541/72685",
    "sg:postcode":"88046",
    "sg:province":"Baden-W\u00fcrttemberg",
    "wof:name":"Siegfried Jost",
    "wof:placetype":"venue"
},
  "geometry": {"coordinates":[9.4929409027,47.6534538269],"type":"Point"}
}