{
  "type": "Feature",
  "properties": {
    "iso:country":"DE",
    "sg:address":"Hamburger Ring 3",
    "sg:city":"Klipphausen",
    "sg:phone":"+49 35204/4610",
    "sg:postcode":"01665",
    "sg:province":"Sachsen",
    "wof:name":"Jungheinrich Ag",
    "wof:placetype":"venue"
},
  "geometry": {"coordinates":[13.5151453018,51.0646095276],"type":"Point"}
}