{
  "type": "Feature",
  "properties": {
    "iso:country":"DE",
    "sg:address":"Essener Str. 10",
    "sg:city":"Gelsenkirchen",
    "sg:phone":"+49 209/55227",
    "sg:postcode":"45899",
    "sg:province":"Nordrhein-Westfalen",
    "wof:name":"Hans Baring Ingenieur",
    "wof:placetype":"venue"
},
  "geometry": {"coordinates":[7.0234389305,51.5386009216],"type":"Point"}
}