{
  "type": "Feature",
  "properties": {
    "iso:country":"DE",
    "sg:address":"Rathenaustr. 4",
    "sg:city":"Offenbach",
    "sg:phone":"+49 69/812371",
    "sg:postcode":"63067",
    "sg:province":"Hessen",
    "wof:name":"D. Marohn & Co.",
    "wof:placetype":"venue"
},
  "geometry": {"coordinates":[8.756973,50.099491],"type":"Point"}
}