{
  "type": "Feature",
  "properties": {
    "iso:country":"DE",
    "sg:address":"Heilbronner Str. 64",
    "sg:city":"Leingarten",
    "sg:phone":"+49 7131/900446",
    "sg:postcode":"74211",
    "sg:province":"Baden-W\u00fcrttemberg",
    "wof:name":"Kebab Stube \u00d6ner",
    "wof:placetype":"venue"
},
  "geometry": {"coordinates":[9.126326561,49.143699646],"type":"Point"}
}