{
  "type": "Feature",
  "properties": {
    "iso:country":"DE",
    "sg:address":"Raiffeisenstr. 3",
    "sg:city":"Steinfeld",
    "sg:phone":"+49 9359/259",
    "sg:postcode":"97854",
    "sg:province":"Bayern",
    "wof:name":"Winfried Herrmann",
    "wof:placetype":"venue"
},
  "geometry": {"coordinates":[9.661702,49.958038],"type":"Point"}
}