{
  "type": "Feature",
  "properties": {
    "iso:country":"DE",
    "sg:address":"Rotenb\u00fchlerweg 3",
    "sg:city":"Saarbr\u00fccken",
    "sg:postcode":"66123",
    "sg:province":"Saarland",
    "wof:name":"Aci Agentur F\u00fcr Corporate Identity Public Relations-",
    "wof:placetype":"venue"
},
  "geometry": {"coordinates":[7.016378,49.243118],"type":"Point"}
}