{
  "type": "Feature",
  "properties": {
    "iso:country":"DE",
    "sg:address":"Kaiserstr. 31",
    "sg:city":"Velbert",
    "sg:phone":"+49 2051/53074",
    "sg:postcode":"42549",
    "sg:province":"Nordrhein-Westfalen",
    "wof:name":"O. Escher Werksvertretung Gmbh",
    "wof:placetype":"venue"
},
  "geometry": {"coordinates":[7.0368509293,51.3389930725],"type":"Point"}
}