{
  "type": "Feature",
  "properties": {
    "iso:country":"DE",
    "sg:address":"Dorfstr. 25",
    "sg:city":"Feldheim",
    "sg:phone":"+49 33747/401",
    "sg:postcode":"14913",
    "sg:province":"Brandenburg",
    "wof:name":"Agrargen. Fl\u00e4ming Eg",
    "wof:placetype":"venue"
},
  "geometry": {"coordinates":[13.170997,51.973206],"type":"Point"}
}