{
  "type": "Feature",
  "properties": {
    "iso:country":"DE",
    "sg:address":"Heesfeld 11",
    "sg:city":"Braunschweig",
    "sg:phone":"+49 531",
    "sg:postcode":"38112",
    "sg:province":"Niedersachsen",
    "wof:name":"Vahldiek Gmbh",
    "wof:placetype":"venue"
},
  "geometry": {"coordinates":[10.4801177979,52.3071174622],"type":"Point"}
}