{
  "type": "Feature",
  "properties": {
    "iso:country":"DE",
    "sg:address":"Eldenaer Str. 29",
    "sg:city":"Berlin",
    "sg:phone":"+49 30/4226590",
    "sg:postcode":"10247",
    "sg:province":"Berlin",
    "wof:name":"Friedrichshainer Dachbau Gmbh",
    "wof:placetype":"venue"
},
  "geometry": {"coordinates":[13.4700632095,52.5203170776],"type":"Point"}
}