{
  "type": "Feature",
  "properties": {
    "iso:country":"DE",
    "sg:address":"Schulgasse 7",
    "sg:city":"Dennheritz",
    "sg:postcode":"08393",
    "sg:province":"Sachsen",
    "wof:name":"S\u00e4chsischer Notarbund",
    "wof:placetype":"venue"
},
  "geometry": {"coordinates":[12.4605073929,50.8140830994],"type":"Point"}
}