{
  "type": "Feature",
  "properties": {
    "iso:country":"DE",
    "sg:address":"Lingen 5",
    "sg:city":"Halver",
    "sg:phone":"+49 2353/10084",
    "sg:postcode":"58553",
    "sg:province":"Nordrhein-Westfalen",
    "wof:name":"Malerbetrieb J\u00f6rg L\u00fcling Gmbh",
    "wof:placetype":"venue"
},
  "geometry": {"coordinates":[7.527804,51.198124],"type":"Point"}
}