{
  "type": "Feature",
  "properties": {
    "iso:country":"DE",
    "sg:address":"Dorfstr. 14",
    "sg:city":"Bethau",
    "sg:phone":"+49 35386/23196",
    "sg:postcode":"06925",
    "sg:province":"Sachsen-Anhalt",
    "wof:name":"Friedenseiche",
    "wof:placetype":"venue"
},
  "geometry": {"coordinates":[12.9979124069,51.6735534668],"type":"Point"}
}