{
  "type": "Feature",
  "properties": {
    "iso:country":"DE",
    "sg:address":"Gustav-Eisenlohr-Weg 16",
    "sg:city":"Emmendingen",
    "sg:phone":"+49 7641/47702",
    "sg:postcode":"79312",
    "sg:province":"Baden-W\u00fcrttemberg",
    "wof:name":"Roland Schw\u00f6rer",
    "wof:placetype":"venue"
},
  "geometry": {"coordinates":[7.8428521156,48.128238678],"type":"Point"}
}