{
  "type": "Feature",
  "properties": {
    "iso:country":"DE",
    "sg:address":"Felchower Str. 35",
    "sg:city":"Crussow",
    "sg:postcode":"16278",
    "sg:province":"Brandenburg",
    "wof:name":"Plato Wachdienste Produkt- Pr\u00e4sentation Lehrveranstaltung",
    "wof:placetype":"venue"
},
  "geometry": {"coordinates":[14.0800600052,52.9998016357],"type":"Point"}
}