{
  "type": "Feature",
  "properties": {
    "iso:country":"DE",
    "sg:address":"Oldenburger Allee 24",
    "sg:city":"Hannover",
    "sg:phone":"+49 511/61851",
    "sg:postcode":"30659",
    "sg:province":"Niedersachsen",
    "wof:name":"Wichmann Gmbh",
    "wof:placetype":"venue"
},
  "geometry": {"coordinates":[9.8256282806,52.4195213318],"type":"Point"}
}