{
  "type": "Feature",
  "properties": {
    "iso:country":"DE",
    "sg:address":"K\u00f6lnische Str. 114c",
    "sg:city":"Kassel",
    "sg:phone":"+49 561/7393386",
    "sg:postcode":"34119",
    "sg:province":"Hessen",
    "wof:name":"G4 Promotion Sport",
    "wof:placetype":"venue"
},
  "geometry": {"coordinates":[9.4765148163,51.3176574707],"type":"Point"}
}