{
  "type": "Feature",
  "properties": {
    "iso:country":"DE",
    "sg:address":"Nordstr. 53",
    "sg:city":"Herzogenrath",
    "sg:phone":"+49 2407/2442",
    "sg:postcode":"52134",
    "sg:province":"Nordrhein-Westfalen",
    "wof:name":"Hubert Kuckelkorn",
    "wof:placetype":"venue"
},
  "geometry": {"coordinates":[6.086315,50.836658],"type":"Point"}
}