{
  "type": "Feature",
  "properties": {
    "iso:country":"DE",
    "sg:address":"Hinter der Bahn 1",
    "sg:city":"Drebber",
    "sg:phone":"+49 5445/1547",
    "sg:postcode":"49457",
    "sg:province":"Niedersachsen",
    "wof:name":"Tinnemeyer Ferkelaufzucht Kg",
    "wof:placetype":"venue"
},
  "geometry": {"coordinates":[8.471309,52.670513],"type":"Point"}
}