{
  "type": "Feature",
  "properties": {
    "iso:country":"DE",
    "sg:address":"Reriker Str. 9",
    "sg:city":"Berlin",
    "sg:phone":"+49 30/9298323",
    "sg:postcode":"13051",
    "sg:province":"Berlin",
    "wof:name":"Klausdieter Lenz",
    "wof:placetype":"venue"
},
  "geometry": {"coordinates":[13.491527,52.571625],"type":"Point"}
}