{
  "type": "Feature",
  "properties": {
    "iso:country":"DE",
    "sg:address":"Am Alten Berg 2",
    "sg:city":"Dreieich",
    "sg:phone":"+49 6172/964467",
    "sg:postcode":"63303",
    "sg:province":"Hessen",
    "wof:name":"Mc Personalmanagement Gmbh",
    "wof:placetype":"venue"
},
  "geometry": {"coordinates":[8.5632095337,50.2504310608],"type":"Point"}
}