{
  "type": "Feature",
  "properties": {
    "iso:country":"DE",
    "sg:address":"Adalbertstr. 13",
    "sg:city":"Frankfurt",
    "sg:phone":"+49 69/704543",
    "sg:postcode":"60486",
    "sg:province":"Hessen",
    "wof:name":"Pizzeria Peppino",
    "wof:placetype":"venue"
},
  "geometry": {"coordinates":[8.6477355957,50.1197471619],"type":"Point"}
}