{
  "type": "Feature",
  "properties": {
    "iso:country":"DE",
    "sg:address":"Am Brink 5",
    "sg:city":"Wendeburg",
    "sg:phone":"+49 5303/2320",
    "sg:postcode":"38176",
    "sg:province":"Niedersachsen",
    "wof:name":"Heinrich Wittenberg",
    "wof:placetype":"venue"
},
  "geometry": {"coordinates":[10.375874,52.326508],"type":"Point"}
}