{
  "type": "Feature",
  "properties": {
    "iso:country":"DE",
    "sg:address":"Allmuser Str. 16",
    "sg:city":"N\u00fcsttal",
    "sg:phone":"+49 6652/5910",
    "sg:postcode":"36167",
    "sg:province":"Hessen",
    "wof:name":"Winfried He\u00df",
    "wof:placetype":"venue"
},
  "geometry": {"coordinates":[9.822479,50.63002],"type":"Point"}
}