{
  "type": "Feature",
  "properties": {
    "iso:country":"DE",
    "sg:address":"Im Th\u00f6niskamp 6",
    "sg:city":"Goch",
    "sg:postcode":"47574",
    "sg:province":"Nordrhein-Westfalen",
    "wof:name":"Dr. Johannes Stephan Rechtsanwalt",
    "wof:placetype":"venue"
},
  "geometry": {"coordinates":[6.1483697891,51.6708717346],"type":"Point"}
}