{
  "type": "Feature",
  "properties": {
    "iso:country":"DE",
    "sg:address":"Geschwister-Scholl-Str. 2",
    "sg:city":"Freudenstadt",
    "sg:phone":"+49 7441/951849",
    "sg:postcode":"72250",
    "sg:province":"Baden-W\u00fcrttemberg",
    "wof:name":"Manfred Mandler",
    "wof:placetype":"venue"
},
  "geometry": {"coordinates":[8.4127998352,48.4642601013],"type":"Point"}
}