{
  "type": "Feature",
  "properties": {
    "iso:country":"DE",
    "sg:address":"In den Bergen 106",
    "sg:city":"Samern",
    "sg:phone":"+49 5923/2125",
    "sg:postcode":"48465",
    "sg:province":"Niedersachsen",
    "wof:name":"K\u00e4\u00dfler Gmbh & Co. Kg",
    "wof:placetype":"venue"
},
  "geometry": {"coordinates":[7.2454600334,52.3230514526],"type":"Point"}
}