{
  "type": "Feature",
  "properties": {
    "iso:country":"DE",
    "sg:address":"Ebersbach",
    "sg:city":"Ebersbach-Musbach",
    "sg:phone":"+49 7584/2790",
    "sg:postcode":"88371",
    "sg:province":"Baden-W\u00fcrttemberg",
    "wof:name":"Seebachhalle",
    "wof:placetype":"venue"
},
  "geometry": {"coordinates":[9.5795097351,47.9549484253],"type":"Point"}
}