{
  "type": "Feature",
  "properties": {
    "iso:country":"DE",
    "sg:address":"Allmendweg 45",
    "sg:city":"Meersburg",
    "sg:phone":"+49 7532",
    "sg:postcode":"88709",
    "sg:province":"Baden-W\u00fcrttemberg",
    "wof:name":"Braeuhauser",
    "wof:placetype":"venue"
},
  "geometry": {"coordinates":[9.2714233398,47.7013435364],"type":"Point"}
}