{
  "type": "Feature",
  "properties": {
    "iso:country":"DE",
    "sg:address":"Kaiser-Wilhelm-Ring 48",
    "sg:city":"K\u00f6ln",
    "sg:phone":"+49 4922/1120195",
    "sg:postcode":"50672",
    "sg:province":"Nordrhein-Westfalen",
    "wof:name":"Antik Hotel Bristol",
    "wof:placetype":"venue"
},
  "geometry": {"coordinates":[6.94104,50.94289],"type":"Point"}
}