{
  "type": "Feature",
  "properties": {
    "iso:country":"DE",
    "sg:address":"Neum\u00fchlen 9",
    "sg:city":"Hamburg",
    "sg:phone":"+49 40/3747990",
    "sg:postcode":"22763",
    "sg:province":"Hamburg",
    "wof:name":"Delphi Personalberatung Gmbh",
    "wof:placetype":"venue"
},
  "geometry": {"coordinates":[9.9259729385,53.544670105],"type":"Point"}
}