{
  "type": "Feature",
  "properties": {
    "iso:country":"DE",
    "sg:address":"Eickhoffstr. 5",
    "sg:city":"G\u00fctersloh",
    "sg:phone":"+49 5241/15898",
    "sg:postcode":"33330",
    "sg:province":"Nordrhein-Westfalen",
    "wof:name":"City- Und Heimatkurier",
    "wof:placetype":"venue"
},
  "geometry": {"coordinates":[8.382097,51.906761],"type":"Point"}
}