{
  "type": "Feature",
  "properties": {
    "iso:country":"DE",
    "sg:address":"R\u00f6merstrasse 38",
    "sg:city":"Riedhausen / Murnau",
    "sg:phone":"+49 8841/6277870",
    "sg:postcode":"82418",
    "sg:province":"Bayern",
    "wof:name":"Bayrische-kinderspiel-krippenfiguren",
    "wof:placetype":"venue"
},
  "geometry": {"coordinates":[11.200964,47.676182],"type":"Point"}
}