{
  "type": "Feature",
  "properties": {
    "iso:country":"DE",
    "sg:address":"Ahnfeldstr. 2-10",
    "sg:city":"D\u00fcsseldorf",
    "sg:phone":"+49 211/625311",
    "sg:postcode":"40239",
    "sg:province":"Nordrhein-Westfalen",
    "wof:name":"Aldi Gmbh & Co. Kg",
    "wof:placetype":"venue"
},
  "geometry": {"coordinates":[6.7979631424,51.2375984192],"type":"Point"}
}