{
  "type": "Feature",
  "properties": {
    "iso:country":"DE",
    "sg:address":"Lakronstr. 53",
    "sg:city":"D\u00fcsseldorf",
    "sg:phone":"+49 211/292470",
    "sg:postcode":"40625",
    "sg:province":"Nordrhein-Westfalen",
    "wof:name":"Apotheke Oelschl\u00e4ger",
    "wof:placetype":"venue"
},
  "geometry": {"coordinates":[6.849765,51.234524],"type":"Point"}
}