{
  "type": "Feature",
  "properties": {
    "iso:country":"DE",
    "sg:address":"Tollensestr. 46",
    "sg:city":"Berlin",
    "sg:phone":"+49 30/8177333",
    "sg:postcode":"14167",
    "sg:province":"Berlin",
    "wof:name":"Lothar Sommerfeld Architekt",
    "wof:placetype":"venue"
},
  "geometry": {"coordinates":[13.275706,52.413986],"type":"Point"}
}