{
  "type": "Feature",
  "properties": {
    "iso:country":"DE",
    "sg:address":"Langekamp 10",
    "sg:city":"M\u00fclheim",
    "sg:phone":"+49 208/995830",
    "sg:postcode":"45475",
    "sg:province":"Nordrhein-Westfalen",
    "wof:name":"Kurt Buchloh Gmbh",
    "wof:placetype":"venue"
},
  "geometry": {"coordinates":[6.881788,51.452469],"type":"Point"}
}