{
  "type": "Feature",
  "properties": {
    "iso:country":"DE",
    "sg:address":"Obergasse 4a",
    "sg:city":"Schlangenbad",
    "sg:phone":"+49 6129/1354",
    "sg:postcode":"65388",
    "sg:province":"Hessen",
    "wof:name":"Reinhold Luft",
    "wof:placetype":"venue"
},
  "geometry": {"coordinates":[8.09839,50.108803],"type":"Point"}
}