{
  "type": "Feature",
  "properties": {
    "iso:country":"DE",
    "sg:address":"Buchenweg 19",
    "sg:city":"Kassel",
    "sg:phone":"+49 561/62220",
    "sg:postcode":"34128",
    "sg:province":"Hessen",
    "wof:name":"Richard Krebs Kunstkabinett",
    "wof:placetype":"venue"
},
  "geometry": {"coordinates":[9.412948,51.338753],"type":"Point"}
}