{
  "type": "Feature",
  "properties": {
    "iso:country":"DE",
    "sg:address":"Speckhorner Str 233",
    "sg:city":"Recklinghausen",
    "sg:phone":"+49 2361/21029",
    "sg:postcode":"45659",
    "sg:province":"Nordrhein-Westfalen",
    "wof:name":"Egon Weidner",
    "wof:placetype":"venue"
},
  "geometry": {"coordinates":[7.1830887794,51.6445579529],"type":"Point"}
}