{
  "type": "Feature",
  "properties": {
    "iso:country":"DE",
    "sg:address":"Geiselgasteigstr 120",
    "sg:city":"M\u00fcnchen",
    "sg:phone":"+49 89/338433",
    "sg:postcode":"81545",
    "sg:province":"Bayern",
    "wof:name":"Heudorf Gmbh",
    "wof:placetype":"venue"
},
  "geometry": {"coordinates":[11.550417,48.078022],"type":"Point"}
}