{
  "type": "Feature",
  "properties": {
    "iso:country":"DE",
    "sg:address":"Karl-Morian-Str. 20",
    "sg:city":"Duisburg",
    "sg:phone":"+49 203/5180848",
    "sg:postcode":"47167",
    "sg:province":"Nordrhein-Westfalen",
    "wof:name":"Westk\u00e4lte Gmbh",
    "wof:placetype":"venue"
},
  "geometry": {"coordinates":[6.793533,51.487476],"type":"Point"}
}