{
  "type": "Feature",
  "properties": {
    "iso:country":"DE",
    "sg:address":"Linkgasse 8-10",
    "sg:city":"Solingen",
    "sg:phone":"+49 212/17066",
    "sg:postcode":"42651",
    "sg:province":"Nordrhein-Westfalen",
    "wof:name":"Hans Kleine-benne Wirtschaftspr\u00fcfer Rechtsanwalt",
    "wof:placetype":"venue"
},
  "geometry": {"coordinates":[7.0847802162,51.1709671021],"type":"Point"}
}