{
  "type": "Feature",
  "properties": {
    "iso:country":"DE",
    "sg:address":"Am Oxer 10",
    "sg:city":"Harrislee",
    "sg:phone":"+49 461/700470",
    "sg:postcode":"24955",
    "sg:province":"Schleswig-Holstein",
    "wof:name":"Dan Art Kurt Baek Nielsen & Co. Gmbh",
    "wof:placetype":"venue"
},
  "geometry": {"coordinates":[9.367791,54.801182],"type":"Point"}
}