{
  "type": "Feature",
  "properties": {
    "iso:country":"DE",
    "sg:address":"Karl-Liebknecht-Str. 112",
    "sg:city":"Leipzig",
    "sg:phone":"+49 341/3029022",
    "sg:postcode":"04275",
    "sg:province":"Sachsen",
    "wof:name":"Restaurant Maha Radscha",
    "wof:placetype":"venue"
},
  "geometry": {"coordinates":[12.3730869293,51.3164787292],"type":"Point"}
}