{
  "type": "Feature",
  "properties": {
    "iso:country":"DE",
    "sg:address":"Am Kanal 24",
    "sg:city":"Twist",
    "sg:phone":"+49 5936/507",
    "sg:postcode":"49767",
    "sg:province":"Niedersachsen",
    "wof:name":"Ahlers",
    "wof:placetype":"venue"
},
  "geometry": {"coordinates":[7.09848,52.64592],"type":"Point"}
}