{
  "type": "Feature",
  "properties": {
    "iso:country":"DE",
    "sg:city":"Rinteln",
    "sg:phone":"+49 4957/515004",
    "sg:postcode":"31737",
    "sg:province":"Niedersachsen",
    "wof:name":"Volksbank B\u00fcckeburg Eg",
    "wof:placetype":"venue"
},
  "geometry": {"coordinates":[9.08141,52.190655],"type":"Point"}
}