{
  "type": "Feature",
  "properties": {
    "iso:country":"DE",
    "sg:address":"\u00dcber der Beeke 2",
    "sg:city":"H\u00fclsede",
    "sg:phone":"+49 4950/432262",
    "sg:postcode":"31867",
    "sg:province":"Niedersachsen",
    "wof:name":"Volksbank Bad M\u00fcnder",
    "wof:placetype":"venue"
},
  "geometry": {"coordinates":[9.360509,52.248177],"type":"Point"}
}