{
  "type": "Feature",
  "properties": {
    "iso:country":"DE",
    "sg:address":"Langenberger Str. 43a",
    "sg:city":"Hude",
    "sg:phone":"+49 4408/7771",
    "sg:postcode":"27798",
    "sg:province":"Niedersachsen",
    "wof:name":"D. Tucholke",
    "wof:placetype":"venue"
},
  "geometry": {"coordinates":[8.4773616791,53.1021842957],"type":"Point"}
}