{
  "type": "Feature",
  "properties": {
    "iso:country":"DE",
    "sg:address":"Rhanwaltinger Str. 13",
    "sg:city":"Waffenbrunn",
    "sg:phone":"+49 9971/40203",
    "sg:postcode":"93494",
    "sg:province":"Bayern",
    "wof:name":"Holma Holz Und Metall- Produkte Gmbh",
    "wof:placetype":"venue"
},
  "geometry": {"coordinates":[12.6593332291,49.2563705444],"type":"Point"}
}