{
  "type": "Feature",
  "properties": {
    "iso:country":"DE",
    "sg:address":"General-Clay-Str. 22",
    "sg:city":"S\u00f6gel",
    "sg:phone":"+49 5952/903519",
    "sg:postcode":"49751",
    "sg:province":"Niedersachsen",
    "wof:name":"Robbers Industrie- Bedarf Gmbh",
    "wof:placetype":"venue"
},
  "geometry": {"coordinates":[7.52387,52.851181],"type":"Point"}
}