{
  "type": "Feature",
  "properties": {
    "iso:country":"DE",
    "sg:address":"Hohlengrabengasse 22",
    "sg:city":"Rottweil",
    "sg:phone":"+49 741/6872",
    "sg:postcode":"78628",
    "sg:province":"Baden-W\u00fcrttemberg",
    "wof:name":"Firat",
    "wof:placetype":"venue"
},
  "geometry": {"coordinates":[8.6270856857,48.1667098999],"type":"Point"}
}