{
  "type": "Feature",
  "properties": {
    "iso:country":"DE",
    "sg:address":"Strubbergstr. 4",
    "sg:city":"L\u00fcbbecke",
    "sg:phone":"+49 5741/20900",
    "sg:postcode":"32312",
    "sg:province":"Nordrhein-Westfalen",
    "wof:name":"F. Verl",
    "wof:placetype":"venue"
},
  "geometry": {"coordinates":[8.602773,52.302956],"type":"Point"}
}