{
  "type": "Feature",
  "properties": {
    "iso:country":"DE",
    "sg:address":"Austr. 26",
    "sg:city":"Aachen",
    "sg:postcode":"52066",
    "sg:province":"Nordrhein-Westfalen",
    "wof:name":"Bfu Aachen B\u00fcro F\u00fcr Umweltplanung Gmbh",
    "wof:placetype":"venue"
},
  "geometry": {"coordinates":[6.115519,50.760696],"type":"Point"}
}