{
  "type": "Feature",
  "properties": {
    "iso:country":"DE",
    "sg:address":"Hauptstr. 18",
    "sg:city":"Gartow",
    "sg:phone":"+49 5846/1224",
    "sg:postcode":"29471",
    "sg:province":"Niedersachsen",
    "wof:name":"Rosen-apotheke",
    "wof:placetype":"venue"
},
  "geometry": {"coordinates":[11.465134,53.02504],"type":"Point"}
}