{
  "type": "Feature",
  "properties": {
    "iso:country":"DE",
    "sg:address":"Weilerbacher Str. 77",
    "sg:city":"Kaiserslautern",
    "sg:phone":"+49 631/351260",
    "sg:postcode":"67661",
    "sg:province":"Rheinland-Pfalz",
    "wof:name":"Blumengro\u00dfmarkt Kaiserslautern",
    "wof:placetype":"venue"
},
  "geometry": {"coordinates":[7.6554179192,49.4370765686],"type":"Point"}
}