{
  "type": "Feature",
  "properties": {
    "iso:country":"DE",
    "sg:address":"Scheunenstr. 3",
    "sg:city":"Pausa",
    "sg:phone":"+49 37432/20436",
    "sg:postcode":"07952",
    "sg:province":"Sachsen",
    "wof:name":"Manfred Z\u00e4pernick",
    "wof:placetype":"venue"
},
  "geometry": {"coordinates":[11.997337,50.579132],"type":"Point"}
}