{
  "type": "Feature",
  "properties": {
    "iso:country":"DE",
    "sg:address":"Muehlenweg 4",
    "sg:city":"Falkenberg - Diepoltskirchen",
    "sg:phone":"+49 8727/346",
    "sg:postcode":"84326",
    "sg:province":"Bayern",
    "wof:name":"Spedition Oberberger",
    "wof:placetype":"venue"
},
  "geometry": {"coordinates":[12.730065,48.462437],"type":"Point"}
}