{
  "type": "Feature",
  "properties": {
    "iso:country":"DE",
    "sg:address":"\u00d6vern Barg 33",
    "sg:city":"Hamburg",
    "sg:phone":"+49 40/50053838",
    "sg:postcode":"22337",
    "sg:province":"Hamburg",
    "wof:name":"Sven Lorenzen Architekt",
    "wof:placetype":"venue"
},
  "geometry": {"coordinates":[10.055813,53.634914],"type":"Point"}
}