{
  "type": "Feature",
  "properties": {
    "iso:country":"DE",
    "sg:address":"Robert-Bosch-Str. 16",
    "sg:city":"Frankenthal",
    "sg:phone":"+49 6233/72131",
    "sg:postcode":"67227",
    "sg:province":"Rheinland-Pfalz",
    "wof:name":"M\u00fcller-sieber Gmbh",
    "wof:placetype":"venue"
},
  "geometry": {"coordinates":[8.3459453583,49.5503692627],"type":"Point"}
}