{
  "type": "Feature",
  "properties": {
    "iso:country":"DE",
    "sg:address":"Viktoriastr. 5",
    "sg:city":"Wermelskirchen",
    "sg:phone":"+49 2196/72280",
    "sg:postcode":"42929",
    "sg:province":"Nordrhein-Westfalen",
    "wof:name":"Saint-gobain Crystals And Detectors Gmbh",
    "wof:placetype":"venue"
},
  "geometry": {"coordinates":[7.202378,51.134464],"type":"Point"}
}