{
  "type": "Feature",
  "properties": {
    "iso:country":"DE",
    "sg:address":"R\u00e4tikonstr. 32",
    "sg:city":"Friedrichshafen",
    "sg:phone":"+49 7541/32454",
    "sg:postcode":"88045",
    "sg:province":"Baden-W\u00fcrttemberg",
    "wof:name":"Schuller Gmbh Brandschutz-technik",
    "wof:placetype":"venue"
},
  "geometry": {"coordinates":[9.458067,47.657188],"type":"Point"}
}