{
  "type": "Feature",
  "properties": {
    "iso:country":"DE",
    "sg:address":"Walter-Stoecker-Str. 29-30",
    "sg:city":"Rostock",
    "sg:phone":"+49 381/82197",
    "sg:postcode":"18069",
    "sg:province":"Mecklenburg-Vorpommern",
    "wof:name":"Modehaus Nikolaus Gmbh",
    "wof:placetype":"venue"
},
  "geometry": {"coordinates":[12.0696496964,54.0989723206],"type":"Point"}
}