{
  "type": "Feature",
  "properties": {
    "iso:country":"DE",
    "sg:address":"Badegasse 8243",
    "sg:city":"Baumholder",
    "sg:phone":"+49 6783/1544",
    "sg:postcode":"55774",
    "sg:province":"Rheinland-Pfalz",
    "wof:name":"W. Lamberti",
    "wof:placetype":"venue"
},
  "geometry": {"coordinates":[7.339473,49.615971],"type":"Point"}
}