{
  "type": "Feature",
  "properties": {
    "iso:country":"DE",
    "sg:address":"Karl-Mangold-Str 12",
    "sg:city":"M\u00fcnchen",
    "sg:phone":"+49 89/82908630",
    "sg:postcode":"81245",
    "sg:province":"Bayern",
    "wof:name":"Kurpjuhn + Partner",
    "wof:placetype":"venue"
},
  "geometry": {"coordinates":[11.468233,48.15279],"type":"Point"}
}