{
  "type": "Feature",
  "properties": {
    "iso:country":"DE",
    "sg:address":"Jacobsgasse 10",
    "sg:city":"Wurzen",
    "sg:phone":"+49 3425/920057",
    "sg:postcode":"04808",
    "sg:province":"Sachsen",
    "wof:name":"Chic Gmbh",
    "wof:placetype":"venue"
},
  "geometry": {"coordinates":[12.7367534637,51.3699913025],"type":"Point"}
}