{
  "type": "Feature",
  "properties": {
    "iso:country":"DE",
    "sg:address":"K\u00f6nigsstr. 37",
    "sg:city":"M\u00fcnster",
    "sg:phone":"+49 251/55278",
    "sg:postcode":"48143",
    "sg:province":"Nordrhein-Westfalen",
    "wof:name":"Ruth Schmidt",
    "wof:placetype":"venue"
},
  "geometry": {"coordinates":[7.626352,51.957649],"type":"Point"}
}