{
  "type": "Feature",
  "properties": {
    "iso:country":"DE",
    "sg:address":"Gustav-Freytag-Str. 39",
    "sg:city":"Wiesbaden",
    "sg:phone":"+49 611/305671",
    "sg:postcode":"65189",
    "sg:province":"Hessen",
    "wof:name":"Hans Franke Kg",
    "wof:placetype":"venue"
},
  "geometry": {"coordinates":[8.2571716309,50.0784721375],"type":"Point"}
}