{
  "type": "Feature",
  "properties": {
    "iso:country":"DE",
    "sg:address":"Itzenb\u00fctteler Sod 13 a",
    "sg:city":"Jesteburg",
    "sg:phone":"+49 4181/5693",
    "sg:postcode":"21266",
    "sg:province":"Niedersachsen",
    "wof:name":"Kurt Benrowitz Segelmacherei Ohg",
    "wof:placetype":"venue"
},
  "geometry": {"coordinates":[9.9659175873,53.3173065186],"type":"Point"}
}