{
  "type": "Feature",
  "properties": {
    "iso:country":"DE",
    "sg:address":"Xantener Str. 10",
    "sg:city":"Berlin",
    "sg:phone":"+49 30/8818181",
    "sg:postcode":"10707",
    "sg:province":"Berlin",
    "wof:name":"Detlef Ninnemann Patentanwalt",
    "wof:placetype":"venue"
},
  "geometry": {"coordinates":[13.3112277985,52.499042511],"type":"Point"}
}