{
  "type": "Feature",
  "properties": {
    "iso:country":"DE",
    "sg:address":"Wilhelmstra\u00dfe 4",
    "sg:city":"Berglen",
    "sg:postcode":"73663",
    "sg:province":"Baden-W\u00fcrttemberg",
    "wof:name":"Montagebau Brandhuber",
    "wof:placetype":"venue"
},
  "geometry": {"coordinates":[9.466085434,48.8526878357],"type":"Point"}
}