{
  "type": "Feature",
  "properties": {
    "iso:country":"DE",
    "sg:address":"Siedlerweg 1",
    "sg:city":"Utarp",
    "sg:phone":"+49 4975/7304",
    "sg:postcode":"26556",
    "sg:province":"Niedersachsen",
    "wof:name":"Abken Bau Gmbh & Co. Kg",
    "wof:placetype":"venue"
},
  "geometry": {"coordinates":[7.482558,53.606125],"type":"Point"}
}