{
  "type": "Feature",
  "properties": {
    "iso:country":"DE",
    "sg:address":"Oberhausener Str. 354",
    "sg:city":"Bottrop",
    "sg:phone":"+49 2041/94177",
    "sg:postcode":"46240",
    "sg:province":"Nordrhein-Westfalen",
    "wof:name":"E. Balger",
    "wof:placetype":"venue"
},
  "geometry": {"coordinates":[6.910319,51.558994],"type":"Point"}
}