{
  "type": "Feature",
  "properties": {
    "iso:country":"DE",
    "sg:address":"St\u00fcbelallee 9",
    "sg:city":"Dresden",
    "sg:phone":"+49 351/2501275",
    "sg:postcode":"01307",
    "sg:province":"Sachsen",
    "wof:name":"Sammelstiftung Des Bezirkes Dresden",
    "wof:placetype":"venue"
},
  "geometry": {"coordinates":[13.7621030807,51.0437545776],"type":"Point"}
}