{
  "type": "Feature",
  "properties": {
    "iso:country":"DE",
    "sg:address":"Hochstr. 39",
    "sg:city":"Viersen",
    "sg:phone":"+49 2162/7337",
    "sg:postcode":"41749",
    "sg:province":"Nordrhein-Westfalen",
    "wof:name":"Harald Graw",
    "wof:placetype":"venue"
},
  "geometry": {"coordinates":[6.36953,51.286411],"type":"Point"}
}