{
  "type": "Feature",
  "properties": {
    "iso:country":"DE",
    "sg:address":"Hohenzollernring 58",
    "sg:city":"Bayreuth",
    "sg:phone":"+49 921/57990",
    "sg:postcode":"95444",
    "sg:province":"Bayern",
    "wof:name":"Volbert",
    "wof:placetype":"venue"
},
  "geometry": {"coordinates":[11.5708446503,49.9452590942],"type":"Point"}
}