{
  "type": "Feature",
  "properties": {
    "iso:country":"DE",
    "sg:address":"Mimeweg 5",
    "sg:city":"Hamburg",
    "sg:phone":"+49 40/812646",
    "sg:postcode":"22559",
    "sg:province":"Hamburg",
    "wof:name":"Karl-heinz W\u00fcller Ingenieur",
    "wof:placetype":"venue"
},
  "geometry": {"coordinates":[9.7545585632,53.5870552063],"type":"Point"}
}