{
  "type": "Feature",
  "properties": {
    "iso:country":"DE",
    "sg:address":"Hegestr. 8",
    "sg:city":"Hamburg",
    "sg:phone":"+49 40/46093961",
    "sg:postcode":"20251",
    "sg:province":"Hamburg",
    "wof:name":"Fontelina First Class Secondhand Handel",
    "wof:placetype":"venue"
},
  "geometry": {"coordinates":[9.9806518555,53.5822982788],"type":"Point"}
}