{
  "type": "Feature",
  "properties": {
    "iso:country":"DE",
    "sg:address":"Uhlandstr. 49",
    "sg:city":"Berlin",
    "sg:phone":"+49 30/882041",
    "sg:postcode":"10719",
    "sg:province":"Berlin",
    "wof:name":"Hotel Domus Garni Gmbh",
    "wof:placetype":"venue"
},
  "geometry": {"coordinates":[13.3239631653,52.4967765808],"type":"Point"}
}