{
  "type": "Feature",
  "properties": {
    "iso:country":"DE",
    "sg:address":"Gartenstr. 14",
    "sg:city":"Zuzenhausen",
    "sg:phone":"+49 6226/3007",
    "sg:postcode":"74939",
    "sg:province":"Baden-W\u00fcrttemberg",
    "wof:name":"Wiesengrund",
    "wof:placetype":"venue"
},
  "geometry": {"coordinates":[8.8235082626,49.2992630005],"type":"Point"}
}