{
  "type": "Feature",
  "properties": {
    "iso:country":"DE",
    "sg:address":"Hauptstr. 32",
    "sg:city":"Lienen",
    "sg:phone":"+49 5483/258",
    "sg:postcode":"49536",
    "sg:province":"Nordrhein-Westfalen",
    "wof:name":"Eiscafe Capri",
    "wof:placetype":"venue"
},
  "geometry": {"coordinates":[7.975922,52.146706],"type":"Point"}
}