{
  "type": "Feature",
  "properties": {
    "iso:country":"DE",
    "sg:address":"K\u00e4the-Kollwitz-Str. 10",
    "sg:city":"Grimma",
    "sg:phone":"+49 3437/911416",
    "sg:postcode":"04668",
    "sg:province":"Sachsen",
    "wof:name":"Dr. Med. Stefan Berger",
    "wof:placetype":"venue"
},
  "geometry": {"coordinates":[12.72149,51.238098],"type":"Point"}
}