{
  "type": "Feature",
  "properties": {
    "iso:country":"DE",
    "sg:address":"Am Bahnhof 16",
    "sg:city":"Mosbach",
    "sg:phone":"+49 6261/7790",
    "sg:postcode":"74821",
    "sg:province":"Baden-W\u00fcrttemberg",
    "wof:name":"M. Maurer Ingenieur",
    "wof:placetype":"venue"
},
  "geometry": {"coordinates":[9.1138715744,49.3465766907],"type":"Point"}
}