{
  "type": "Feature",
  "properties": {
    "iso:country":"DE",
    "sg:address":"Raststra\u00dfe 8",
    "sg:city":"Coburg",
    "sg:phone":"+49 9561/509356",
    "sg:postcode":"96450",
    "sg:province":"Bayern",
    "wof:name":"Rpm-scootering Gbr",
    "wof:placetype":"venue"
},
  "geometry": {"coordinates":[10.9603271484,50.2640342712],"type":"Point"}
}