{
  "type": "Feature",
  "properties": {
    "iso:country":"DE",
    "sg:address":"Koblenzer Str. 2",
    "sg:city":"Bad Breisig",
    "sg:phone":"+49 2633/9422",
    "sg:postcode":"53498",
    "sg:province":"Rheinland-Pfalz",
    "wof:name":"Kath. \u00d6ffentliche Bibliothek St. Marien",
    "wof:placetype":"venue"
},
  "geometry": {"coordinates":[7.29871,50.509422],"type":"Point"}
}