{
  "type": "Feature",
  "properties": {
    "iso:country":"DE",
    "sg:address":"An der Hasenkuhle 7",
    "sg:city":"Rosengarten",
    "sg:phone":"+49 4108/7184",
    "sg:postcode":"21224",
    "sg:province":"Niedersachsen",
    "wof:name":"Wolfhard B\u00f6ttcher",
    "wof:placetype":"venue"
},
  "geometry": {"coordinates":[9.8877134323,53.4262580872],"type":"Point"}
}