{
  "type": "Feature",
  "properties": {
    "iso:country":"DE",
    "sg:address":"Siemensstr 9",
    "sg:city":"Waibstadt",
    "sg:phone":"+49 7263/711",
    "sg:postcode":"74915",
    "sg:province":"Baden-W\u00fcrttemberg",
    "wof:name":"Dewe Kfz-teile Vertriebs-gmbh",
    "wof:placetype":"venue"
},
  "geometry": {"coordinates":[8.902474,49.304272],"type":"Point"}
}