{
  "type": "Feature",
  "properties": {
    "iso:country":"DE",
    "sg:address":"Jahnstr. 6",
    "sg:city":"Weismain",
    "sg:phone":"+49 9575/981063",
    "sg:postcode":"96260",
    "sg:province":"Bayern",
    "wof:name":"Willi Wagner",
    "wof:placetype":"venue"
},
  "geometry": {"coordinates":[11.2431077957,50.0857582092],"type":"Point"}
}