{
  "type": "Feature",
  "properties": {
    "iso:country":"DE",
    "sg:address":"Herrenkellergasse 20",
    "sg:city":"Ulm",
    "sg:phone":"+49 731/64479",
    "sg:postcode":"89073",
    "sg:province":"Baden-W\u00fcrttemberg",
    "wof:name":"Roswitha Roederer Gmbh",
    "wof:placetype":"venue"
},
  "geometry": {"coordinates":[9.9932441711,48.4002609253],"type":"Point"}
}