{
  "type": "Feature",
  "properties": {
    "iso:country":"DE",
    "sg:address":"Langwiese",
    "sg:city":"Blieskastel",
    "sg:phone":"+49 6803/469",
    "sg:postcode":"66440",
    "sg:province":"Saarland",
    "wof:name":"Gebr. Neu Gmbh",
    "wof:placetype":"venue"
},
  "geometry": {"coordinates":[7.182489,49.211948],"type":"Point"}
}