{
  "type": "Feature",
  "properties": {
    "iso:country":"DE",
    "sg:address":"Franziskanerplatz 7",
    "sg:city":"Eggenfelden",
    "sg:phone":"+49 8721/8119",
    "sg:postcode":"84307",
    "sg:province":"Bayern",
    "wof:name":"Josef Dirnberger",
    "wof:placetype":"venue"
},
  "geometry": {"coordinates":[12.7617416382,48.4065093994],"type":"Point"}
}