{
  "type": "Feature",
  "properties": {
    "iso:country":"DE",
    "sg:address":"Robert-Blum-Str. 25",
    "sg:city":"Leverkusen",
    "sg:phone":"+49 214/4044832",
    "sg:postcode":"51373",
    "sg:province":"Nordrhein-Westfalen",
    "wof:name":"Sport Prinz Gmbh",
    "wof:placetype":"venue"
},
  "geometry": {"coordinates":[7.004009,51.04924],"type":"Point"}
}