{
  "type": "Feature",
  "properties": {
    "iso:country":"DE",
    "sg:address":"Bahnhofstr. 17",
    "sg:city":"Nordhausen",
    "sg:phone":"+49 3631/973601",
    "sg:postcode":"99734",
    "sg:province":"Th\u00fcringen",
    "wof:name":"Helmut D\u00e4hling",
    "wof:placetype":"venue"
},
  "geometry": {"coordinates":[10.7906942368,51.4949035645],"type":"Point"}
}