{
  "type": "Feature",
  "properties": {
    "iso:country":"DE",
    "sg:address":"Gertigstr. 24",
    "sg:city":"Hamburg",
    "sg:phone":"+49 40/2791270",
    "sg:postcode":"22303",
    "sg:province":"Hamburg",
    "wof:name":"Peter Michael Niethammer Architekt",
    "wof:placetype":"venue"
},
  "geometry": {"coordinates":[10.014598,53.58176],"type":"Point"}
}