{
  "type": "Feature",
  "properties": {
    "iso:country":"DE",
    "sg:address":"Gretlade 2",
    "sg:city":"Sehnde",
    "sg:phone":"+49 5132/945603",
    "sg:postcode":"31319",
    "sg:province":"Niedersachsen",
    "wof:name":"Woods Gmbh",
    "wof:placetype":"venue"
},
  "geometry": {"coordinates":[9.884459,52.352676],"type":"Point"}
}