{
  "type": "Feature",
  "properties": {
    "iso:country":"DE",
    "sg:address":"Forstweg 37",
    "sg:city":"Herrnburg",
    "sg:phone":"+49 38821/66410",
    "sg:postcode":"23923",
    "sg:province":"Mecklenburg-Vorpommern",
    "wof:name":"Atelier Kohlmann Architektengesellschaft Mbh",
    "wof:placetype":"venue"
},
  "geometry": {"coordinates":[10.762304,53.842964],"type":"Point"}
}