{
  "type": "Feature",
  "properties": {
    "iso:country":"DE",
    "sg:address":"G\u00f6llstr. 29 a",
    "sg:city":"Freilassing",
    "sg:phone":"+49 8654/46330",
    "sg:postcode":"83395",
    "sg:province":"Bayern",
    "wof:name":"Pnr Deutschland Industrie- Spritzd\u00fcsen Handels Gmbh",
    "wof:placetype":"venue"
},
  "geometry": {"coordinates":[12.973194,47.8232],"type":"Point"}
}