{
  "type": "Feature",
  "properties": {
    "iso:country":"DE",
    "sg:address":"Erkrather Str. 230",
    "sg:city":"D\u00fcsseldorf",
    "sg:postcode":"40233",
    "sg:province":"Nordrhein-Westfalen",
    "wof:name":"Inter Beteiligungs- Verwaltungs- Gmbh",
    "wof:placetype":"venue"
},
  "geometry": {"coordinates":[6.81484,51.218632],"type":"Point"}
}