{
  "type": "Feature",
  "properties": {
    "iso:country":"DE",
    "sg:address":"Am Lunedeich 147",
    "sg:city":"Bremerhaven",
    "sg:phone":"+49 4947/179690",
    "sg:postcode":"27572",
    "sg:province":"Bremen",
    "wof:name":"Nadler Feinkost Gmbh",
    "wof:placetype":"venue"
},
  "geometry": {"coordinates":[8.5906620026,53.5030937195],"type":"Point"}
}