{
  "type": "Feature",
  "properties": {
    "iso:country":"DE",
    "sg:address":"Faustackerweg 11",
    "sg:city":"M\u00fchlacker",
    "sg:phone":"+49 7041/46563",
    "sg:postcode":"75417",
    "sg:province":"Baden-W\u00fcrttemberg",
    "wof:name":"Martin Fischer Brennstoffhandel",
    "wof:placetype":"venue"
},
  "geometry": {"coordinates":[8.842002,48.95459],"type":"Point"}
}