{
  "type": "Feature",
  "properties": {
    "iso:country":"DE",
    "sg:address":"Neuburger Str. 102f",
    "sg:city":"Passau",
    "sg:phone":"+49 851/7561726",
    "sg:postcode":"94036",
    "sg:province":"Bayern",
    "wof:name":"S. Karras",
    "wof:placetype":"venue"
},
  "geometry": {"coordinates":[13.432641983,48.5645027161],"type":"Point"}
}