{
  "type": "Feature",
  "properties": {
    "iso:country":"DE",
    "sg:address":"Stufenweg 26",
    "sg:city":"Moers",
    "sg:phone":"+49 2841/22872",
    "sg:postcode":"47447",
    "sg:province":"Nordrhein-Westfalen",
    "wof:name":"Haus Der Stoffe",
    "wof:placetype":"venue"
},
  "geometry": {"coordinates":[6.6464509964,51.4272460938],"type":"Point"}
}