{
  "type": "Feature",
  "properties": {
    "iso:country":"DE",
    "sg:address":"Lindaum\u00fchlenholz 34",
    "sg:city":"Boren",
    "sg:phone":"+49 4641/3446",
    "sg:postcode":"24392",
    "sg:province":"Schleswig-Holstein",
    "wof:name":"G\u00e4stehaus B. S\u00f6rnsen",
    "wof:placetype":"venue"
},
  "geometry": {"coordinates":[9.8181200027,54.6135787964],"type":"Point"}
}