{
  "type": "Feature",
  "properties": {
    "iso:country":"DE",
    "sg:address":"Erftstr. 78",
    "sg:city":"Neuss",
    "sg:phone":"+49 2131/92050",
    "sg:postcode":"41460",
    "sg:province":"Nordrhein-Westfalen",
    "wof:name":"Makiol Schwerdtfeger Und Part. Rechtsanw\u00e4lte",
    "wof:placetype":"venue"
},
  "geometry": {"coordinates":[6.6892700195,51.1966896057],"type":"Point"}
}