{
  "type": "Feature",
  "properties": {
    "iso:country":"DE",
    "sg:address":"Raiffeisenstr 13",
    "sg:city":"Augsburg",
    "sg:phone":"+49 821/793075",
    "sg:postcode":"86167",
    "sg:province":"Bayern",
    "wof:name":"Elges Media Gmbh",
    "wof:placetype":"venue"
},
  "geometry": {"coordinates":[10.931656,48.390282],"type":"Point"}
}