{
  "type": "Feature",
  "properties": {
    "iso:country":"DE",
    "sg:address":"Alt Bonames 14",
    "sg:city":"Frankfurt",
    "sg:phone":"+49 69/502380",
    "sg:postcode":"60437",
    "sg:province":"Hessen",
    "wof:name":"Wilh. Denker",
    "wof:placetype":"venue"
},
  "geometry": {"coordinates":[8.664758,50.181759],"type":"Point"}
}