{
  "type": "Feature",
  "properties": {
    "iso:country":"DE",
    "sg:address":"Unterstadt 14",
    "sg:city":"Haigerloch",
    "sg:phone":"+49 7474/6248",
    "sg:postcode":"72401",
    "sg:province":"Baden-W\u00fcrttemberg",
    "wof:name":"J\u00f6rg Weber",
    "wof:placetype":"venue"
},
  "geometry": {"coordinates":[8.803238,48.367046],"type":"Point"}
}