{
  "type": "Feature",
  "properties": {
    "iso:country":"DE",
    "sg:address":"Leuchtenburger Str. 54",
    "sg:city":"Rastede",
    "sg:phone":"+49 4402/939556",
    "sg:postcode":"26180",
    "sg:province":"Niedersachsen",
    "wof:name":"Hans-dieter R\u00f6ben Architekt",
    "wof:placetype":"venue"
},
  "geometry": {"coordinates":[8.171943,53.235107],"type":"Point"}
}