{
  "type": "Feature",
  "properties": {
    "iso:country":"DE",
    "sg:address":"Liebetraustr. 9",
    "sg:city":"Gotha",
    "sg:phone":"+49 3621/744072",
    "sg:postcode":"99867",
    "sg:province":"Th\u00fcringen",
    "wof:name":"Wilhelm Mook",
    "wof:placetype":"venue"
},
  "geometry": {"coordinates":[10.69482,50.946362],"type":"Point"}
}