{
  "type": "Feature",
  "properties": {
    "iso:country":"DE",
    "sg:address":"Am Hohen Feld 120",
    "sg:city":"Berlin",
    "sg:postcode":"13125",
    "sg:province":"Berlin",
    "wof:name":"Stephan Arndt",
    "wof:placetype":"venue"
},
  "geometry": {"coordinates":[13.495234,52.612961],"type":"Point"}
}