{
  "type": "Feature",
  "properties": {
    "iso:country":"DE",
    "sg:address":"Schlo\u00dfstr. 23",
    "sg:city":"Essenbach",
    "sg:phone":"+49 8703/93350",
    "sg:postcode":"84051",
    "sg:province":"Bayern",
    "wof:name":"Richard Wei\u00dfacher Gmbh",
    "wof:placetype":"venue"
},
  "geometry": {"coordinates":[12.1970453262,48.6124954224],"type":"Point"}
}