{
  "type": "Feature",
  "properties": {
    "iso:country":"DE",
    "sg:address":"Auf dem G\u00e4nsemarkt 11",
    "sg:city":"Selm",
    "sg:phone":"+49 2306/56744",
    "sg:postcode":"59379",
    "sg:province":"Nordrhein-Westfalen",
    "wof:name":"Winfried L\u00f6er",
    "wof:placetype":"venue"
},
  "geometry": {"coordinates":[7.527203,51.659603],"type":"Point"}
}