{
  "type": "Feature",
  "properties": {
    "iso:country":"DE",
    "sg:address":"Alte Dorfstr. 32",
    "sg:city":"Poggensee",
    "sg:phone":"+49 4543/217",
    "sg:postcode":"23896",
    "sg:province":"Schleswig-Holstein",
    "wof:name":"Wilhelm Kr\u00fctzmann",
    "wof:placetype":"venue"
},
  "geometry": {"coordinates":[10.579391,53.639935],"type":"Point"}
}