{
  "type": "Feature",
  "properties": {
    "iso:country":"DE",
    "sg:address":"Propst-Hellmich-Promenade 9",
    "sg:city":"Bochum",
    "sg:phone":"+49 2327/87386",
    "sg:postcode":"44866",
    "sg:province":"Nordrhein-Westfalen",
    "wof:name":"Fritz Stein & Sohn",
    "wof:placetype":"venue"
},
  "geometry": {"coordinates":[7.1357851028,51.4791984558],"type":"Point"}
}