{
  "type": "Feature",
  "properties": {
    "iso:country":"DE",
    "sg:address":"Stielerstr. 8",
    "sg:city":"Ingolstadt",
    "sg:phone":"+49 841/56159",
    "sg:postcode":"85055",
    "sg:province":"Bayern",
    "wof:name":"Karin Janke",
    "wof:placetype":"venue"
},
  "geometry": {"coordinates":[11.432389,48.775887],"type":"Point"}
}