{
  "type": "Feature",
  "properties": {
    "iso:country":"DE",
    "sg:address":"Longericher Str. 445",
    "sg:city":"K\u00f6ln",
    "sg:phone":"+49 221/5991777",
    "sg:postcode":"50739",
    "sg:province":"Nordrhein-Westfalen",
    "wof:name":"M. Von Stephanie Augenoptiker",
    "wof:placetype":"venue"
},
  "geometry": {"coordinates":[6.9136347771,50.9966583252],"type":"Point"}
}