{
  "type": "Feature",
  "properties": {
    "iso:country":"DE",
    "sg:address":"K\u00f6nigstr. 28",
    "sg:city":"Stuttgart",
    "sg:phone":"+49 711/2265264",
    "sg:postcode":"70173",
    "sg:province":"Baden-W\u00fcrttemberg",
    "wof:name":"Euwax Broker Ag",
    "wof:placetype":"venue"
},
  "geometry": {"coordinates":[9.178319,48.778835],"type":"Point"}
}