{
  "type": "Feature",
  "properties": {
    "iso:country":"DE",
    "sg:address":"Pastoratsweg 2",
    "sg:city":"Sankt Augustin",
    "sg:phone":"+49 2241/333752",
    "sg:postcode":"53757",
    "sg:province":"Nordrhein-Westfalen",
    "wof:name":"M. Pachel Heissmangel",
    "wof:placetype":"venue"
},
  "geometry": {"coordinates":[7.217523098,50.7764282227],"type":"Point"}
}