{
  "type": "Feature",
  "properties": {
    "iso:country":"DE",
    "sg:address":"Salbker Chaussee",
    "sg:city":"Magdeburg",
    "sg:phone":"+49 391/628510",
    "sg:postcode":"39116",
    "sg:province":"Sachsen-Anhalt",
    "wof:name":"Top-tec Handels Gmbh",
    "wof:placetype":"venue"
},
  "geometry": {"coordinates":[11.586186409,52.0830116272],"type":"Point"}
}