{
  "type": "Feature",
  "properties": {
    "iso:country":"DE",
    "sg:address":"Heinzestr. 35",
    "sg:city":"Alfeld",
    "sg:phone":"+49 5181/5283",
    "sg:postcode":"31061",
    "sg:province":"Niedersachsen",
    "wof:name":"Hans-gerd Und Helga Steffen Steuerberater",
    "wof:placetype":"venue"
},
  "geometry": {"coordinates":[9.8347167969,51.9858932495],"type":"Point"}
}