{
  "type": "Feature",
  "properties": {
    "iso:country":"DE",
    "sg:address":"M\u00fcnchener Str. 22",
    "sg:city":"Neuburg",
    "sg:phone":"+49 8431/7318",
    "sg:postcode":"86633",
    "sg:province":"Bayern",
    "wof:name":"Dieter Baumeister Immobilienmakler",
    "wof:placetype":"venue"
},
  "geometry": {"coordinates":[11.2046298981,48.7456016541],"type":"Point"}
}