{
  "type": "Feature",
  "properties": {
    "iso:country":"DE",
    "sg:address":"Am Walzwerk 41",
    "sg:city":"Hattingen",
    "sg:postcode":"45527",
    "sg:province":"Nordrhein-Westfalen",
    "wof:name":"Ispro Grundst\u00fcck Gmbh & Co. Kg",
    "wof:placetype":"venue"
},
  "geometry": {"coordinates":[7.1904230118,51.4156074524],"type":"Point"}
}