{
  "type": "Feature",
  "properties": {
    "iso:country":"DE",
    "sg:address":"56753",
    "sg:city":"Welling",
    "sg:phone":"+49 2654/6311",
    "sg:postcode":"56753",
    "sg:province":"Rheinland-Pfalz",
    "wof:name":"Hotel Zur Post",
    "wof:placetype":"venue"
},
  "geometry": {"coordinates":[7.3139719963,50.3290023804],"type":"Point"}
}