{
  "type": "Feature",
  "properties": {
    "iso:country":"DE",
    "sg:address":"Bergstr. 4",
    "sg:city":"Kirchenlamitz",
    "sg:phone":"+49 9285/1604",
    "sg:postcode":"95158",
    "sg:province":"Bayern",
    "wof:name":"Wolfgang Nittke",
    "wof:placetype":"venue"
},
  "geometry": {"coordinates":[11.950459,50.150112],"type":"Point"}
}