{
  "type": "Feature",
  "properties": {
    "iso:country":"DE",
    "sg:address":"Langenhorner Chaussee 339",
    "sg:city":"Hamburg",
    "sg:phone":"+49 40/5314259",
    "sg:postcode":"22419",
    "sg:province":"Hamburg",
    "wof:name":"Klaus Beyer",
    "wof:placetype":"venue"
},
  "geometry": {"coordinates":[10.004491806,53.656955719],"type":"Point"}
}