{
  "type": "Feature",
  "properties": {
    "iso:country":"DE",
    "sg:address":"Herknerstr. 1",
    "sg:city":"Weingarten",
    "sg:phone":"+49 751/50916",
    "sg:postcode":"88250",
    "sg:province":"Baden-W\u00fcrttemberg",
    "wof:name":"Ibm-ingenieurb\u00fcro Mayer-breuer Gmbh",
    "wof:placetype":"venue"
},
  "geometry": {"coordinates":[9.6376152039,47.8179550171],"type":"Point"}
}