{
  "type": "Feature",
  "properties": {
    "iso:country":"DE",
    "sg:address":"M\u00e4rkische Strasse 196-200",
    "sg:city":"Dortmund",
    "sg:postcode":"44141",
    "sg:province":"Nordrhein-Westfalen",
    "wof:name":"Westfalen Revision Gmbh",
    "wof:placetype":"venue"
},
  "geometry": {"coordinates":[7.489244,51.497482],"type":"Point"}
}