{
  "type": "Feature",
  "properties": {
    "iso:country":"DE",
    "sg:address":"Hermelinplatz 25",
    "sg:city":"Leipzig",
    "sg:postcode":"04329",
    "sg:province":"Sachsen",
    "wof:name":"I. Beier",
    "wof:placetype":"venue"
},
  "geometry": {"coordinates":[12.472304,51.359055],"type":"Point"}
}