{
  "type": "Feature",
  "properties": {
    "iso:country":"DE",
    "sg:address":"Dr.-Zeiler-Platz 3",
    "sg:city":"Offingen",
    "sg:phone":"+49 8224/2002",
    "sg:postcode":"89362",
    "sg:province":"Bayern",
    "wof:name":"Keck-wear Textilvertrieb Gmbh",
    "wof:placetype":"venue"
},
  "geometry": {"coordinates":[10.3633546829,48.4792709351],"type":"Point"}
}