{
  "type": "Feature",
  "properties": {
    "iso:country":"DE",
    "sg:address":"Bergengruenstr. 22",
    "sg:city":"Hamm",
    "sg:phone":"+49 2381/51308",
    "sg:postcode":"59063",
    "sg:province":"Nordrhein-Westfalen",
    "wof:name":"Annette Moden Textilhandelsges. Mbh",
    "wof:placetype":"venue"
},
  "geometry": {"coordinates":[7.8228611946,51.6692695618],"type":"Point"}
}