{
  "type": "Feature",
  "properties": {
    "iso:country":"DE",
    "sg:address":"Rohrbachstr. 2",
    "sg:city":"Geiselbach",
    "sg:phone":"+49 6024/9303",
    "sg:postcode":"63826",
    "sg:province":"Bayern",
    "wof:name":"Reising",
    "wof:placetype":"venue"
},
  "geometry": {"coordinates":[9.1967697144,50.1222496033],"type":"Point"}
}