{
  "type": "Feature",
  "properties": {
    "iso:country":"DE",
    "sg:address":"Salzgasse 5",
    "sg:city":"Calw",
    "sg:phone":"+49 7051/12876",
    "sg:postcode":"75365",
    "sg:province":"Baden-W\u00fcrttemberg",
    "wof:name":"W. Franz",
    "wof:placetype":"venue"
},
  "geometry": {"coordinates":[8.7388277054,48.7137107849],"type":"Point"}
}