{
  "type": "Feature",
  "properties": {
    "iso:country":"DE",
    "sg:address":"Dr.-Tolberg-Str. 5",
    "sg:city":"Sch\u00f6nebeck",
    "sg:phone":"+49 3928/70050",
    "sg:postcode":"39218",
    "sg:province":"Sachsen-Anhalt",
    "wof:name":"Heidelore Schwarz Steuerberaterin",
    "wof:placetype":"venue"
},
  "geometry": {"coordinates":[11.7233915329,52.0020065308],"type":"Point"}
}