{
  "type": "Feature",
  "properties": {
    "iso:country":"DE",
    "sg:address":"Westerfelde 1a",
    "sg:city":"Hamburg",
    "sg:phone":"+49 40/6052110",
    "sg:postcode":"22397",
    "sg:province":"Hamburg",
    "wof:name":"Fritz Luhdes Erben",
    "wof:placetype":"venue"
},
  "geometry": {"coordinates":[10.1356563568,53.6948051453],"type":"Point"}
}