{
  "type": "Feature",
  "properties": {
    "iso:country":"DE",
    "sg:address":"Friedrich-Naumann-Weg 2",
    "sg:city":"Pforzheim",
    "sg:phone":"+49 7231/71765",
    "sg:postcode":"75180",
    "sg:province":"Baden-W\u00fcrttemberg",
    "wof:name":"Detlev Von Der Heyde Ingenieur",
    "wof:placetype":"venue"
},
  "geometry": {"coordinates":[8.6663169861,48.8733139038],"type":"Point"}
}