{
  "type": "Feature",
  "properties": {
    "iso:country":"DE",
    "sg:address":"Urbanusstr. 14",
    "sg:city":"Leiwen",
    "sg:phone":"+49 6507/3839",
    "sg:postcode":"54340",
    "sg:province":"Rheinland-Pfalz",
    "wof:name":"Johann Stoffel",
    "wof:placetype":"venue"
},
  "geometry": {"coordinates":[6.8740057945,49.8226623535],"type":"Point"}
}