{
  "type": "Feature",
  "properties": {
    "iso:country":"DE",
    "sg:address":"Keetstr. 14",
    "sg:city":"Lohne",
    "sg:phone":"+49 4442/1808",
    "sg:postcode":"49393",
    "sg:province":"Niedersachsen",
    "wof:name":"M. Schulze",
    "wof:placetype":"venue"
},
  "geometry": {"coordinates":[8.2328567505,52.6668624878],"type":"Point"}
}