{
  "type": "Feature",
  "properties": {
    "iso:country":"DE",
    "sg:address":"Achstr. 26",
    "sg:city":"Friedberg",
    "sg:postcode":"86316",
    "sg:province":"Bayern",
    "wof:name":"E. Biasi Gmbh",
    "wof:placetype":"venue"
},
  "geometry": {"coordinates":[10.97635,48.355621],"type":"Point"}
}