{
  "type": "Feature",
  "properties": {
    "iso:country":"DE",
    "sg:address":"Limmerstr. 2 D",
    "sg:city":"Hannover",
    "sg:phone":"+49 511/454834",
    "sg:postcode":"30451",
    "sg:province":"Niedersachsen",
    "wof:name":"Franz Troczinski Heilpraktiker",
    "wof:placetype":"venue"
},
  "geometry": {"coordinates":[9.7131052017,52.3716659546],"type":"Point"}
}