{
  "type": "Feature",
  "properties": {
    "iso:country":"DE",
    "sg:address":"Siegener Str. 25",
    "sg:city":"Kreuztal",
    "sg:phone":"+49 2732/51303",
    "sg:postcode":"57223",
    "sg:province":"Nordrhein-Westfalen",
    "wof:name":"Stadtwerke Kreuztal",
    "wof:placetype":"venue"
},
  "geometry": {"coordinates":[7.994109,50.956966],"type":"Point"}
}