{
  "type": "Feature",
  "properties": {
    "iso:country":"DE",
    "sg:address":"M\u00f6llerstr. 20",
    "sg:city":"Hagen",
    "sg:phone":"+49 2334/54111",
    "sg:postcode":"58119",
    "sg:province":"Nordrhein-Westfalen",
    "wof:name":"Dorfplatz-apotheke",
    "wof:placetype":"venue"
},
  "geometry": {"coordinates":[7.565224,51.360443],"type":"Point"}
}