{
  "type": "Feature",
  "properties": {
    "iso:country":"DE",
    "sg:address":"Hirschbergerstra\u00dfe 8",
    "sg:city":"Weyhe",
    "sg:postcode":"28844",
    "sg:province":"Niedersachsen",
    "wof:name":"Paddyscoolstuff - Die Verr\u00fcckte Seite Im Netz",
    "wof:placetype":"venue"
},
  "geometry": {"coordinates":[8.836419,52.97361],"type":"Point"}
}