{
  "type": "Feature",
  "properties": {
    "iso:country":"DE",
    "sg:address":"Feckweilerhaide 15",
    "sg:city":"Birkenfeld",
    "sg:phone":"+49 6782/99310",
    "sg:postcode":"55765",
    "sg:province":"Rheinland-Pfalz",
    "wof:name":"T\u00dcv Rheinland",
    "wof:placetype":"venue"
},
  "geometry": {"coordinates":[7.1610889435,49.6544189453],"type":"Point"}
}