{
  "type": "Feature",
  "properties": {
    "iso:country":"DE",
    "sg:address":"Stesse 6",
    "sg:city":"Meschede",
    "sg:phone":"+49 2903/509",
    "sg:postcode":"59872",
    "sg:province":"Nordrhein-Westfalen",
    "wof:name":"H. Seifert Gut Bockum",
    "wof:placetype":"venue"
},
  "geometry": {"coordinates":[8.207943,51.340164],"type":"Point"}
}