{
  "type": "Feature",
  "properties": {
    "iso:country":"DE",
    "sg:address":"Georg-Abr\u00f6ll-Str. 4",
    "sg:city":"Aldersbach",
    "sg:phone":"+49 8543/1204",
    "sg:postcode":"94501",
    "sg:province":"Bayern",
    "wof:name":"Hermann Bischl",
    "wof:placetype":"venue"
},
  "geometry": {"coordinates":[13.085098,48.590271],"type":"Point"}
}