{
  "type": "Feature",
  "properties": {
    "iso:country":"DE",
    "sg:address":"Annostr. 75",
    "sg:city":"Hennef",
    "sg:phone":"+49 2242/84088",
    "sg:postcode":"53773",
    "sg:province":"Nordrhein-Westfalen",
    "wof:name":"H. Heisinger",
    "wof:placetype":"venue"
},
  "geometry": {"coordinates":[7.305618763,50.7991523743],"type":"Point"}
}