{
  "type": "Feature",
  "properties": {
    "iso:country":"DE",
    "sg:address":"Lindenallee 2 a",
    "sg:city":"Leezen",
    "sg:phone":"+49 3866/4040",
    "sg:postcode":"19067",
    "sg:province":"Mecklenburg-Vorpommern",
    "wof:name":"Landgesellschaft Mecklenburg- Vorpommern Mbh",
    "wof:placetype":"venue"
},
  "geometry": {"coordinates":[11.495617,53.663528],"type":"Point"}
}