{
  "type": "Feature",
  "properties": {
    "iso:country":"DE",
    "sg:address":"Gr\u00fcner Brunnenweg 25",
    "sg:city":"K\u00f6ln",
    "sg:phone":"+49 221/5306112",
    "sg:postcode":"50827",
    "sg:province":"Nordrhein-Westfalen",
    "wof:name":"Erich Kratz Masseur",
    "wof:placetype":"venue"
},
  "geometry": {"coordinates":[6.900524,50.961266],"type":"Point"}
}