{
  "type": "Feature",
  "properties": {
    "iso:country":"DE",
    "sg:address":"Maxhofstr. 32",
    "sg:city":"M\u00fcnchen",
    "sg:phone":"+49 89/751645",
    "sg:postcode":"81475",
    "sg:province":"Bayern",
    "wof:name":"Maxhof-apotheke",
    "wof:placetype":"venue"
},
  "geometry": {"coordinates":[11.478273,48.087582],"type":"Point"}
}