{
  "type": "Feature",
  "properties": {
    "iso:country":"DE",
    "sg:address":"Butterberg 16",
    "sg:city":"Bergen",
    "sg:phone":"+49 4950/541052",
    "sg:postcode":"29303",
    "sg:province":"Niedersachsen",
    "wof:name":"Sparkasse Celle",
    "wof:placetype":"venue"
},
  "geometry": {"coordinates":[10.034482,52.768234],"type":"Point"}
}