{
  "type": "Feature",
  "properties": {
    "iso:country":"DE",
    "sg:address":"Hauptstr. 11",
    "sg:city":"Buxtehude",
    "sg:phone":"+49 4161/84056",
    "sg:postcode":"21614",
    "sg:province":"Niedersachsen",
    "wof:name":"Arno Ebling Rechtsanwalt Und Notar",
    "wof:placetype":"venue"
},
  "geometry": {"coordinates":[9.6894025803,53.4687957764],"type":"Point"}
}