{
  "type": "Feature",
  "properties": {
    "iso:country":"DE",
    "sg:address":"P\u00e4psen 16",
    "sg:city":"Siedenburg",
    "sg:phone":"+49 4272/7200",
    "sg:postcode":"27254",
    "sg:province":"Niedersachsen",
    "wof:name":"Frank Siemers",
    "wof:placetype":"venue"
},
  "geometry": {"coordinates":[8.9586782455,52.7046203613],"type":"Point"}
}