{
  "type": "Feature",
  "properties": {
    "iso:country":"DE",
    "sg:address":"Cherbourger Str. 15-17",
    "sg:city":"Bremerhaven",
    "sg:phone":"+49 471/9812050",
    "sg:postcode":"27580",
    "sg:province":"Bremen",
    "wof:name":"Johanniter-unfall-hilfe E. V.",
    "wof:placetype":"venue"
},
  "geometry": {"coordinates":[8.5948228836,53.58335495],"type":"Point"}
}