{
  "type": "Feature",
  "properties": {
    "iso:country":"DE",
    "sg:address":"Puschkinstr. 22",
    "sg:city":"Wei\u00dfwasser",
    "sg:postcode":"02943",
    "sg:province":"Sachsen",
    "wof:name":"Wohnungsbaugenossen- Schaft Wei\u00dfwasser Eg",
    "wof:placetype":"venue"
},
  "geometry": {"coordinates":[14.6425924301,51.5019264221],"type":"Point"}
}