{
  "type": "Feature",
  "properties": {
    "iso:country":"DE",
    "sg:address":"Hochkreuzallee 1",
    "sg:city":"Bonn",
    "sg:phone":"+49 228/30790",
    "sg:postcode":"53175",
    "sg:province":"Nordrhein-Westfalen",
    "wof:name":"Stater Deutschland Gmbh & Co. Kg",
    "wof:placetype":"venue"
},
  "geometry": {"coordinates":[7.1407251358,50.6968612671],"type":"Point"}
}