{
  "type": "Feature",
  "properties": {
    "iso:country":"DE",
    "sg:address":"Sommerhofenstr. 174",
    "sg:city":"Sindelfingen",
    "sg:phone":"+49 7031/809602",
    "sg:postcode":"71067",
    "sg:province":"Baden-W\u00fcrttemberg",
    "wof:name":"Elmar Berger Werkzeuge",
    "wof:placetype":"venue"
},
  "geometry": {"coordinates":[9.0133152008,48.7216262817],"type":"Point"}
}