{
  "type": "Feature",
  "properties": {
    "iso:country":"DE",
    "sg:address":"De-Rode-Weg 10",
    "sg:city":"Soest",
    "sg:phone":"+49 2921/33295",
    "sg:postcode":"59494",
    "sg:province":"Nordrhein-Westfalen",
    "wof:name":"Jeuneurope Studienfahrten Gem. Gmbh",
    "wof:placetype":"venue"
},
  "geometry": {"coordinates":[8.0982875824,51.5664024353],"type":"Point"}
}