{
  "type": "Feature",
  "properties": {
    "iso:country":"DE",
    "sg:address":"Borchsh\u00f6her Str. 40",
    "sg:city":"Bremen",
    "sg:phone":"+49 421/631460",
    "sg:postcode":"28757",
    "sg:province":"Bremen",
    "wof:name":"Hermann Dohr",
    "wof:placetype":"venue"
},
  "geometry": {"coordinates":[8.631899,53.180885],"type":"Point"}
}