{
  "type": "Feature",
  "properties": {
    "iso:country":"DE",
    "sg:address":"Furtenbachstr. 9",
    "sg:city":"Leutkirch",
    "sg:phone":"+49 7561/3245",
    "sg:postcode":"88299",
    "sg:province":"Baden-W\u00fcrttemberg",
    "wof:name":"Udv- Unternehmensberatungs- Und Datenverarbeitungs-gmbh",
    "wof:placetype":"venue"
},
  "geometry": {"coordinates":[10.017375946,47.8226089478],"type":"Point"}
}