{
  "type": "Feature",
  "properties": {
    "iso:country":"DE",
    "sg:address":"Kuhlenweg 28",
    "sg:city":"G\u00fcstrow",
    "sg:phone":"+49 3843/684229",
    "sg:postcode":"18273",
    "sg:province":"Mecklenburg-Vorpommern",
    "wof:name":"Reinders-seidel Hochbau Gmbh",
    "wof:placetype":"venue"
},
  "geometry": {"coordinates":[12.154912,53.79747],"type":"Point"}
}