{
  "type": "Feature",
  "properties": {
    "iso:country":"DE",
    "sg:address":"Gr\u00fcnw\u00e4lderstr. 17",
    "sg:city":"Freiburg",
    "sg:phone":"+49 761/22401",
    "sg:postcode":"79098",
    "sg:province":"Baden-W\u00fcrttemberg",
    "wof:name":"Charivari",
    "wof:placetype":"venue"
},
  "geometry": {"coordinates":[7.8513441086,47.9940834045],"type":"Point"}
}