{
  "type": "Feature",
  "properties": {
    "iso:country":"DE",
    "sg:address":"Am Markt 13",
    "sg:city":"B\u00fcrgel",
    "sg:phone":"+49 36692/22288",
    "sg:postcode":"07616",
    "sg:province":"Th\u00fcringen",
    "wof:name":"Brunnen-apotheke Gisela Kirsch",
    "wof:placetype":"venue"
},
  "geometry": {"coordinates":[11.754446,50.941406],"type":"Point"}
}