{
  "type": "Feature",
  "properties": {
    "iso:country":"DE",
    "sg:address":"Riedstr. 31",
    "sg:city":"Ochsenhausen",
    "sg:phone":"+49 7352/7534",
    "sg:postcode":"88416",
    "sg:province":"Baden-W\u00fcrttemberg",
    "wof:name":"Vinzenz Wiedmann Architekt",
    "wof:placetype":"venue"
},
  "geometry": {"coordinates":[9.954947,48.066578],"type":"Point"}
}