{
  "type": "Feature",
  "properties": {
    "iso:country":"DE",
    "sg:address":"R\u00f6nneburger Freiheit 60",
    "sg:city":"Hamburg",
    "sg:phone":"+49 40/75661515",
    "sg:postcode":"21079",
    "sg:province":"Hamburg",
    "wof:name":"Seyda Hoch- Und Ausbau Gmbh",
    "wof:placetype":"venue"
},
  "geometry": {"coordinates":[9.9993047714,53.430809021],"type":"Point"}
}