{
  "type": "Feature",
  "properties": {
    "iso:country":"DE",
    "sg:address":"Brunnenstr. 26",
    "sg:city":"Heidenheim",
    "sg:phone":"+49 7321/64112",
    "sg:postcode":"89520",
    "sg:province":"Baden-W\u00fcrttemberg",
    "wof:name":"Hermann H\u00e4ge",
    "wof:placetype":"venue"
},
  "geometry": {"coordinates":[10.153193,48.719128],"type":"Point"}
}