{
  "type": "Feature",
  "properties": {
    "iso:country":"DE",
    "sg:address":"W\u00fcnsdorfer Str. 115 b",
    "sg:city":"Berlin",
    "sg:phone":"+49 30/7445197",
    "sg:postcode":"12307",
    "sg:province":"Berlin",
    "wof:name":"Walter Knoth",
    "wof:placetype":"venue"
},
  "geometry": {"coordinates":[13.3950691223,52.3877220154],"type":"Point"}
}