{
  "type": "Feature",
  "properties": {
    "iso:country":"DE",
    "sg:address":"Frankfurter Allee 196",
    "sg:city":"Berlin",
    "sg:phone":"+49 30/5534872",
    "sg:postcode":"10365",
    "sg:province":"Berlin",
    "wof:name":"Siba Top Time Work Gmbh",
    "wof:placetype":"venue"
},
  "geometry": {"coordinates":[13.490225,52.511902],"type":"Point"}
}