{
  "type": "Feature",
  "properties": {
    "iso:country":"DE",
    "sg:address":"Eisenschachtweg 100",
    "sg:city":"St. Egidien",
    "sg:phone":"+49 3723/42367",
    "sg:postcode":"09356",
    "sg:province":"Sachsen",
    "wof:name":"Waldkaffee-birkenhain",
    "wof:placetype":"venue"
},
  "geometry": {"coordinates":[12.6482286453,50.8069000244],"type":"Point"}
}