{
  "type": "Feature",
  "properties": {
    "iso:country":"DE",
    "sg:address":"Schier 17",
    "sg:city":"Schwalmtal",
    "sg:phone":"+49 2163/450641",
    "sg:postcode":"41366",
    "sg:province":"Nordrhein-Westfalen",
    "wof:name":"Wetzels Verwaltungs Gmbh",
    "wof:placetype":"venue"
},
  "geometry": {"coordinates":[6.25436,51.216881],"type":"Point"}
}