{
  "type": "Feature",
  "properties": {
    "iso:country":"DE",
    "sg:address":"Ledergasse 2 /1",
    "sg:city":"Schw\u00e4bisch Gm\u00fcnd",
    "sg:phone":"+49 7171/39666",
    "sg:postcode":"73525",
    "sg:province":"Baden-W\u00fcrttemberg",
    "wof:name":"Vinoteca",
    "wof:placetype":"venue"
},
  "geometry": {"coordinates":[9.7957963943,48.8016357422],"type":"Point"}
}