{
  "type": "Feature",
  "properties": {
    "iso:country":"DE",
    "sg:address":"Gr\u00fcner Weg 6",
    "sg:city":"Frankfurt",
    "sg:phone":"+49 335/564780",
    "sg:postcode":"15230",
    "sg:province":"Brandenburg",
    "wof:name":"Olaf Schn\u00fcrpel Rechtsanwalt",
    "wof:placetype":"venue"
},
  "geometry": {"coordinates":[14.5403356552,52.3480491638],"type":"Point"}
}