{
  "type": "Feature",
  "properties": {
    "iso:country":"DE",
    "sg:address":"Schillerstr. 1",
    "sg:city":"Stolberg",
    "sg:phone":"+49 2409/577",
    "sg:postcode":"52224",
    "sg:province":"Nordrhein-Westfalen",
    "wof:name":"Hubert Tesch Gmbh",
    "wof:placetype":"venue"
},
  "geometry": {"coordinates":[6.2930550575,50.7832641602],"type":"Point"}
}