{
  "type": "Feature",
  "properties": {
    "iso:country":"DE",
    "sg:address":"Bahnhofstr. 22",
    "sg:city":"Gerabronn",
    "sg:phone":"+49 7952/315",
    "sg:postcode":"74582",
    "sg:province":"Baden-W\u00fcrttemberg",
    "wof:name":"Holzbau Nimrichter Gmbh",
    "wof:placetype":"venue"
},
  "geometry": {"coordinates":[9.9210109711,49.2555465698],"type":"Point"}
}