{
  "type": "Feature",
  "properties": {
    "iso:country":"DE",
    "sg:address":"Drususgasse 7 - 11",
    "sg:city":"K\u00f6ln",
    "sg:phone":"+49 221/208170",
    "sg:postcode":"50667",
    "sg:province":"Nordrhein-Westfalen",
    "wof:name":"Betz-gro\u00dfhandels- Gmbh & Co.kg",
    "wof:placetype":"venue"
},
  "geometry": {"coordinates":[6.953745,50.940029],"type":"Point"}
}