{
  "type": "Feature",
  "properties": {
    "iso:country":"DE",
    "sg:address":"Am Talberg 20",
    "sg:city":"Weinheim",
    "sg:phone":"+49 6201/55861",
    "sg:postcode":"69469",
    "sg:province":"Baden-W\u00fcrttemberg",
    "wof:name":"Volker Judith Ingenieur",
    "wof:placetype":"venue"
},
  "geometry": {"coordinates":[8.6774129868,49.5264587402],"type":"Point"}
}