{
  "type": "Feature",
  "properties": {
    "iso:country":"DE",
    "sg:address":"Obere Ortsstr. 4",
    "sg:city":"Beerfelden",
    "sg:phone":"+49 6068/1318",
    "sg:postcode":"64743",
    "sg:province":"Hessen",
    "wof:name":"Pension Das Horus Haus",
    "wof:placetype":"venue"
},
  "geometry": {"coordinates":[8.9382581711,49.568145752],"type":"Point"}
}