{
  "type": "Feature",
  "properties": {
    "iso:country":"DE",
    "sg:address":"Am Pulverturm 24",
    "sg:city":"Hameln",
    "sg:phone":"+49 5151/26231",
    "sg:postcode":"31785",
    "sg:province":"Niedersachsen",
    "wof:name":"Hans Diedrich",
    "wof:placetype":"venue"
},
  "geometry": {"coordinates":[9.3570375443,52.1007194519],"type":"Point"}
}