{
  "type": "Feature",
  "properties": {
    "iso:country":"DE",
    "sg:address":"Amselweg 20",
    "sg:city":"Plochingen",
    "sg:phone":"+49 7153",
    "sg:postcode":"73207",
    "sg:province":"Baden-W\u00fcrttemberg",
    "wof:name":"Ibc International Business Consulting",
    "wof:placetype":"venue"
},
  "geometry": {"coordinates":[9.4264450073,48.7076416016],"type":"Point"}
}