{
  "type": "Feature",
  "properties": {
    "iso:country":"DE",
    "sg:address":"Am Bl\u00fctenanger 29",
    "sg:city":"M\u00fcnchen",
    "sg:phone":"+49 89/1505643",
    "sg:postcode":"80995",
    "sg:province":"Bayern",
    "wof:name":"Otto Maier",
    "wof:placetype":"venue"
},
  "geometry": {"coordinates":[11.517842,48.199226],"type":"Point"}
}