{
  "type": "Feature",
  "properties": {
    "iso:country":"DE",
    "sg:address":"Am Mondscheinweg 40",
    "sg:city":"Worms",
    "sg:phone":"+49 6241/975205",
    "sg:postcode":"67547",
    "sg:province":"Rheinland-Pfalz",
    "wof:name":"Baumpflege Frank Bre\u00dfler",
    "wof:placetype":"venue"
},
  "geometry": {"coordinates":[8.336499,49.628113],"type":"Point"}
}