{
  "type": "Feature",
  "properties": {
    "iso:country":"DE",
    "sg:address":"Muskauer Str. 67",
    "sg:city":"Krauschwitz",
    "sg:phone":"+49 35771/5920",
    "sg:postcode":"02957",
    "sg:province":"Sachsen",
    "wof:name":"Dachdecker Klempner Und Sanit\u00e4r Gmbh",
    "wof:placetype":"venue"
},
  "geometry": {"coordinates":[14.752094,51.499065],"type":"Point"}
}