{
  "type": "Feature",
  "properties": {
    "iso:country":"DE",
    "sg:address":"Liebigstr. 24",
    "sg:city":"Darmstadt",
    "sg:phone":"+49 6151/24797",
    "sg:postcode":"64293",
    "sg:province":"Hessen",
    "wof:name":"Redaktion Magazin F\u00fcr Die Polizei",
    "wof:placetype":"venue"
},
  "geometry": {"coordinates":[8.6474990845,49.880657196],"type":"Point"}
}