{
  "type": "Feature",
  "properties": {
    "iso:country":"DE",
    "sg:address":"Am Bachmann 9",
    "sg:city":"Breuna",
    "sg:phone":"+49 5693/7400",
    "sg:postcode":"34479",
    "sg:province":"Hessen",
    "wof:name":"T-k-v-textil Konfektion Vogt Gmbh Volkmarsen",
    "wof:placetype":"venue"
},
  "geometry": {"coordinates":[9.184920311,51.4155311584],"type":"Point"}
}