{
  "type": "Feature",
  "properties": {
    "iso:country":"DE",
    "sg:address":"Harnackstr. 3",
    "sg:city":"Wolfenb\u00fcttel",
    "sg:phone":"+49 5331/61607",
    "sg:postcode":"38300",
    "sg:province":"Niedersachsen",
    "wof:name":"Leonhard Zack Steuerberater",
    "wof:placetype":"venue"
},
  "geometry": {"coordinates":[10.5610437393,52.1589927673],"type":"Point"}
}