{
  "type": "Feature",
  "properties": {
    "iso:country":"DE",
    "sg:address":"Osterstr. 65",
    "sg:city":"Bredstedt",
    "sg:phone":"+49 4671/5799",
    "sg:postcode":"25821",
    "sg:province":"Schleswig-Holstein",
    "wof:name":"B\u00fccher Bahnsen Britta Bahnsen",
    "wof:placetype":"venue"
},
  "geometry": {"coordinates":[8.9668226242,54.6180763245],"type":"Point"}
}