{
  "type": "Feature",
  "properties": {
    "iso:country":"DE",
    "sg:address":"Ackerstr. 191",
    "sg:city":"D\u00fcsseldorf",
    "sg:phone":"+49 211/6790994",
    "sg:postcode":"40233",
    "sg:province":"Nordrhein-Westfalen",
    "wof:name":"Edith Glischke",
    "wof:placetype":"venue"
},
  "geometry": {"coordinates":[6.8086400032,51.2301902771],"type":"Point"}
}