{
  "type": "Feature",
  "properties": {
    "iso:country":"DE",
    "sg:address":"Heggestr. 19",
    "sg:city":"Hagen",
    "sg:phone":"+49 5401/32877",
    "sg:postcode":"49170",
    "sg:province":"Niedersachsen",
    "wof:name":"Heinz-gerd W\u00f6hrmeyer",
    "wof:placetype":"venue"
},
  "geometry": {"coordinates":[8.011424,52.197048],"type":"Point"}
}