{
  "type": "Feature",
  "properties": {
    "iso:country":"DE",
    "sg:address":"Neue Str. 22",
    "sg:city":"G\u00fcsten",
    "sg:phone":"+49 39262/63024",
    "sg:postcode":"39439",
    "sg:province":"Sachsen-Anhalt",
    "wof:name":"E. Lissek",
    "wof:placetype":"venue"
},
  "geometry": {"coordinates":[11.607462883,51.7962303162],"type":"Point"}
}