{
  "type": "Feature",
  "properties": {
    "iso:country":"DE",
    "sg:address":"S\u00fcdlenger Str. 15",
    "sg:city":"B\u00fcnde",
    "sg:phone":"+49 5223/5851",
    "sg:postcode":"32257",
    "sg:province":"Nordrhein-Westfalen",
    "wof:name":"Helmut Schiffler",
    "wof:placetype":"venue"
},
  "geometry": {"coordinates":[8.5947761536,52.2002716064],"type":"Point"}
}