{
  "type": "Feature",
  "properties": {
    "iso:country":"DE",
    "sg:address":"Ravensteynstra\u00dfe 68",
    "sg:city":"Koblenz",
    "sg:phone":"+49 261/9731925",
    "sg:postcode":"56076",
    "sg:province":"Rheinland-Pfalz",
    "wof:name":"Pers\u00f6nlichkeitsentwicklung Im Vertriebs - Aussendi",
    "wof:placetype":"venue"
},
  "geometry": {"coordinates":[7.60237,50.34306],"type":"Point"}
}