{
  "type": "Feature",
  "properties": {
    "iso:country":"DE",
    "sg:address":"Kirchstr. 42",
    "sg:city":"Gelsenkirchen",
    "sg:phone":"+49 209/22075",
    "sg:postcode":"45888",
    "sg:province":"Nordrhein-Westfalen",
    "wof:name":"Hausger\u00e4te-kundendienst Nasse & Partner Gmbh",
    "wof:placetype":"venue"
},
  "geometry": {"coordinates":[7.1031551361,51.5099830627],"type":"Point"}
}