{
  "type": "Feature",
  "properties": {
    "iso:country":"DE",
    "sg:address":"Forsthaus Luisenlust",
    "sg:city":"Hirzenhain",
    "sg:phone":"+49 6045/1675",
    "sg:postcode":"63697",
    "sg:province":"Hessen",
    "wof:name":"R. Weber Bildhauer",
    "wof:placetype":"venue"
},
  "geometry": {"coordinates":[9.132395,50.380257],"type":"Point"}
}