{
  "type": "Feature",
  "properties": {
    "iso:country":"DE",
    "sg:address":"Hauptstr. 6",
    "sg:city":"Reken",
    "sg:phone":"+49 2864/1242",
    "sg:postcode":"48734",
    "sg:province":"Nordrhein-Westfalen",
    "wof:name":"Hermann Illerhues",
    "wof:placetype":"venue"
},
  "geometry": {"coordinates":[7.046257019,51.8319969177],"type":"Point"}
}