{
  "type": "Feature",
  "properties": {
    "iso:country":"DE",
    "sg:address":"Auf den L\u00f6sern 2",
    "sg:city":"Erfurt",
    "sg:phone":"+49 361/2227531",
    "sg:postcode":"99094",
    "sg:province":"Th\u00fcringen",
    "wof:name":"Bernd Hentschke",
    "wof:placetype":"venue"
},
  "geometry": {"coordinates":[10.998631,50.958622],"type":"Point"}
}