{
  "type": "Feature",
  "properties": {
    "iso:country":"DE",
    "sg:address":"Kornstr. 87",
    "sg:city":"Bremen",
    "sg:phone":"+49 421/532999",
    "sg:postcode":"28201",
    "sg:province":"Bremen",
    "wof:name":"Ina Gr\u00e4ser",
    "wof:placetype":"venue"
},
  "geometry": {"coordinates":[8.801105,53.064289],"type":"Point"}
}