{
  "type": "Feature",
  "properties": {
    "iso:country":"DE",
    "sg:address":"Sonnenhang 24",
    "sg:city":"Melsungen",
    "sg:phone":"+49 5661/2468",
    "sg:postcode":"34212",
    "sg:province":"Hessen",
    "wof:name":"Heinz Horn",
    "wof:placetype":"venue"
},
  "geometry": {"coordinates":[9.5390586853,51.1385307312],"type":"Point"}
}