{
  "type": "Feature",
  "properties": {
    "iso:country":"DE",
    "sg:address":"Mainzer Str. 82",
    "sg:city":"Homburg",
    "sg:phone":"+49 6841/170388",
    "sg:postcode":"66424",
    "sg:province":"Saarland",
    "wof:name":"Homburger Industriebetreuungs- Und -verwertungsgesellsch. Mbh",
    "wof:placetype":"venue"
},
  "geometry": {"coordinates":[7.3349318504,49.3196525574],"type":"Point"}
}