{
  "type": "Feature",
  "properties": {
    "iso:country":"DE",
    "sg:address":"Stra\u00dfe 72 14",
    "sg:city":"Berlin",
    "sg:phone":"+49 30/4867133",
    "sg:postcode":"12524",
    "sg:province":"Berlin",
    "wof:name":"Bakendorf Gmbh",
    "wof:placetype":"venue"
},
  "geometry": {"coordinates":[13.539691,52.420055],"type":"Point"}
}