{
  "type": "Feature",
  "properties": {
    "iso:country":"DE",
    "sg:address":"Im Steinrausch 52",
    "sg:city":"Mechernich",
    "sg:phone":"+49 2443/901078",
    "sg:postcode":"53894",
    "sg:province":"Nordrhein-Westfalen",
    "wof:name":"A. Und M. Zimmermann Anlageberater",
    "wof:placetype":"venue"
},
  "geometry": {"coordinates":[6.665350914,50.5933265686],"type":"Point"}
}