{
  "type": "Feature",
  "properties": {
    "iso:country":"DE",
    "sg:address":"Rosensteinstr. 84",
    "sg:city":"Heubach",
    "sg:phone":"+49 7173/3477",
    "sg:postcode":"73540",
    "sg:province":"Baden-W\u00fcrttemberg",
    "wof:name":"R. Ulrich",
    "wof:placetype":"venue"
},
  "geometry": {"coordinates":[9.9742326736,48.7952003479],"type":"Point"}
}