{
  "type": "Feature",
  "properties": {
    "iso:country":"DE",
    "sg:address":"Karlstr. 7",
    "sg:city":"Sigmaringen",
    "sg:phone":"+49 7571/1614",
    "sg:postcode":"72488",
    "sg:province":"Baden-W\u00fcrttemberg",
    "wof:name":"G\u00fcnter Und Kurt Fuchs Peter Vogeser",
    "wof:placetype":"venue"
},
  "geometry": {"coordinates":[9.2197504044,48.0860404968],"type":"Point"}
}