{
  "type": "Feature",
  "properties": {
    "iso:country":"DE",
    "sg:address":"Horber Str 36",
    "sg:city":"Haiterbach",
    "sg:phone":"+49 5731/4756",
    "sg:postcode":"72221",
    "sg:province":"Baden-W\u00fcrttemberg",
    "wof:name":"M\u00f6belfabrik Wolfgang Barnbeck Gmbh & Co Kg",
    "wof:placetype":"venue"
},
  "geometry": {"coordinates":[8.772797,52.215736],"type":"Point"}
}