{
  "type": "Feature",
  "properties": {
    "iso:country":"DE",
    "sg:address":"Bergstr. 228",
    "sg:city":"Odenthal",
    "sg:phone":"+49 2174/4707",
    "sg:postcode":"51519",
    "sg:province":"Nordrhein-Westfalen",
    "wof:name":"Haeger & M\u00fcller",
    "wof:placetype":"venue"
},
  "geometry": {"coordinates":[7.1152,51.05439],"type":"Point"}
}