{
  "type": "Feature",
  "properties": {
    "iso:country":"DE",
    "sg:address":"Siekerwall 15",
    "sg:city":"Bielefeld",
    "sg:phone":"+49 521/63412",
    "sg:postcode":"33602",
    "sg:province":"Nordrhein-Westfalen",
    "wof:name":"H. D. Pott Gmbh Telememo",
    "wof:placetype":"venue"
},
  "geometry": {"coordinates":[8.5319728851,52.0169296265],"type":"Point"}
}