{
  "type": "Feature",
  "properties": {
    "iso:country":"DE",
    "sg:address":"Hessengasse 7",
    "sg:city":"Sch\u00f6nbrunn",
    "sg:phone":"+49 36874/70920",
    "sg:postcode":"98667",
    "sg:province":"Th\u00fcringen",
    "wof:name":"Alfred He\u00df",
    "wof:placetype":"venue"
},
  "geometry": {"coordinates":[10.8916959763,50.5257225037],"type":"Point"}
}