{
  "type": "Feature",
  "properties": {
    "iso:country":"DE",
    "sg:address":"Land\u00e4ckerstr. 7",
    "sg:city":"Ludwigsburg",
    "sg:phone":"+49 7141/55174",
    "sg:postcode":"71642",
    "sg:province":"Baden-W\u00fcrttemberg",
    "wof:name":"Bernd Giesecke",
    "wof:placetype":"venue"
},
  "geometry": {"coordinates":[9.2202148438,48.916305542],"type":"Point"}
}