{
  "type": "Feature",
  "properties": {
    "iso:country":"DE",
    "sg:address":"Dorfstr. 57",
    "sg:city":"Molkenberg",
    "sg:postcode":"14715",
    "sg:province":"Brandenburg",
    "wof:name":"Hartmut Blumenthal",
    "wof:placetype":"venue"
},
  "geometry": {"coordinates":[-78.151871,42.072361],"type":"Point"}
}