{
  "type": "Feature",
  "properties": {
    "iso:country":"DE",
    "sg:address":"Osnabr\u00fccker Str. 6",
    "sg:city":"Bad Rothenfelde",
    "sg:phone":"+49 5424/1251",
    "sg:postcode":"49214",
    "sg:province":"Niedersachsen",
    "wof:name":"Horstmann & Kuhn Gmbh",
    "wof:placetype":"venue"
},
  "geometry": {"coordinates":[8.161995,52.111557],"type":"Point"}
}