{
  "type": "Feature",
  "properties": {
    "iso:country":"DE",
    "sg:address":"Ritter-von-Gei\u00dfler-Str. 9",
    "sg:city":"Weisenheim am Sand",
    "sg:phone":"+49 6353/8059",
    "sg:postcode":"67256",
    "sg:province":"Rheinland-Pfalz",
    "wof:name":"K. Neckerauer",
    "wof:placetype":"venue"
},
  "geometry": {"coordinates":[8.2458486557,49.5192070007],"type":"Point"}
}