{
  "type": "Feature",
  "properties": {
    "iso:country":"DE",
    "sg:address":"Burgplatz 4",
    "sg:city":"Weimar",
    "sg:phone":"+49 3643/545110",
    "sg:postcode":"99423",
    "sg:province":"Th\u00fcringen",
    "wof:name":"Stiftung Weimarer Klassik",
    "wof:placetype":"venue"
},
  "geometry": {"coordinates":[11.3316688538,50.9805107117],"type":"Point"}
}