{
  "type": "Feature",
  "properties": {
    "iso:country":"DE",
    "sg:address":"Stromberger Str. 22",
    "sg:city":"Bad Kreuznach",
    "sg:phone":"+49 671/46900",
    "sg:postcode":"55545",
    "sg:province":"Rheinland-Pfalz",
    "wof:name":"Claus Kadel Architekten",
    "wof:placetype":"venue"
},
  "geometry": {"coordinates":[7.859735,49.851387],"type":"Point"}
}