{
  "type": "Feature",
  "properties": {
    "iso:country":"DE",
    "sg:address":"H\u00f6rder Str. 28",
    "sg:city":"Dortmund",
    "sg:phone":"+49 231/258092",
    "sg:postcode":"44309",
    "sg:province":"Nordrhein-Westfalen",
    "wof:name":"Dirk Und Rainer Epking",
    "wof:placetype":"venue"
},
  "geometry": {"coordinates":[7.5444951057,51.5212135315],"type":"Point"}
}