{
  "type": "Feature",
  "properties": {
    "iso:country":"DE",
    "sg:address":"Kurt-Schumacher-Str. 36",
    "sg:city":"Neuwied",
    "sg:phone":"+49 2631/55658",
    "sg:postcode":"56567",
    "sg:province":"Rheinland-Pfalz",
    "wof:name":"Wei\u00dfer Berg",
    "wof:placetype":"venue"
},
  "geometry": {"coordinates":[7.47660923,50.4584617615],"type":"Point"}
}