{
  "type": "Feature",
  "properties": {
    "iso:country":"DE",
    "sg:address":"Kurf\u00fcrstenstr. 8",
    "sg:city":"M\u00fcnchen",
    "sg:phone":"+49 89/336897",
    "sg:postcode":"80799",
    "sg:province":"Bayern",
    "wof:name":"H. Maass",
    "wof:placetype":"venue"
},
  "geometry": {"coordinates":[11.5764932632,48.1542320251],"type":"Point"}
}