{
  "type": "Feature",
  "properties": {
    "iso:country":"DE",
    "sg:address":"Kr\u00fcgerstr. 71",
    "sg:city":"Dresden",
    "sg:phone":"+49 351/4605757",
    "sg:postcode":"01326",
    "sg:province":"Sachsen",
    "wof:name":"Erich K\u00fchne",
    "wof:placetype":"venue"
},
  "geometry": {"coordinates":[13.84048,51.050442],"type":"Point"}
}