{
  "type": "Feature",
  "properties": {
    "iso:country":"DE",
    "sg:address":"Poppitzer Landstr. 39",
    "sg:city":"Riesa",
    "sg:phone":"+49 3525/738323",
    "sg:postcode":"01589",
    "sg:province":"Sachsen",
    "wof:name":"Peter M\u00fcller",
    "wof:placetype":"venue"
},
  "geometry": {"coordinates":[13.3204317093,51.2945594788],"type":"Point"}
}