{
  "type": "Feature",
  "properties": {
    "iso:country":"DE",
    "sg:address":"Schleifbr\u00fcckenstr. 11/1",
    "sg:city":"Aalen",
    "sg:phone":"+49 7361/64017",
    "sg:postcode":"73430",
    "sg:province":"Baden-W\u00fcrttemberg",
    "wof:name":"Hubert Schaar",
    "wof:placetype":"venue"
},
  "geometry": {"coordinates":[10.0929031372,48.8427352905],"type":"Point"}
}