{
  "type": "Feature",
  "properties": {
    "iso:country":"DE",
    "sg:address":"Schillingstr. 7",
    "sg:city":"Grevenbroich",
    "sg:phone":"+49 2181/42721",
    "sg:postcode":"41517",
    "sg:province":"Nordrhein-Westfalen",
    "wof:name":"Paul Bremer",
    "wof:placetype":"venue"
},
  "geometry": {"coordinates":[6.56156,51.067081],"type":"Point"}
}