{
  "type": "Feature",
  "properties": {
    "iso:country":"DE",
    "sg:address":"Mayener Str. 21",
    "sg:city":"Kelberg",
    "sg:phone":"+49 2692/206",
    "sg:postcode":"53539",
    "sg:province":"Rheinland-Pfalz",
    "wof:name":"Schmitt",
    "wof:placetype":"venue"
},
  "geometry": {"coordinates":[6.92015,50.28479],"type":"Point"}
}