{
  "type": "Feature",
  "properties": {
    "iso:country":"DE",
    "sg:address":"Sudm\u00fchlenstr. 188",
    "sg:city":"M\u00fcnster",
    "sg:postcode":"48157",
    "sg:province":"Nordrhein-Westfalen",
    "wof:name":"Sport Tec Marketing Und Handel Gmbh",
    "wof:placetype":"venue"
},
  "geometry": {"coordinates":[7.6951861382,51.9891815186],"type":"Point"}
}