{
  "type": "Feature",
  "properties": {
    "iso:country":"DE",
    "sg:address":"Breisenbachstr. 97",
    "sg:city":"Dortmund",
    "sg:phone":"+49 231/9350100",
    "sg:postcode":"44357",
    "sg:province":"Nordrhein-Westfalen",
    "wof:name":"Kmb Klebetechnik Gmbh",
    "wof:placetype":"venue"
},
  "geometry": {"coordinates":[7.368628,51.561592],"type":"Point"}
}