{
  "type": "Feature",
  "properties": {
    "iso:country":"DE",
    "sg:address":"Stadtweg 6",
    "sg:city":"Hildesheim",
    "sg:phone":"+49 5121/62473",
    "sg:postcode":"31139",
    "sg:province":"Niedersachsen",
    "wof:name":"Hans-joachim Salland",
    "wof:placetype":"venue"
},
  "geometry": {"coordinates":[9.880934,52.150017],"type":"Point"}
}