{
  "type": "Feature",
  "properties": {
    "iso:country":"DE",
    "sg:address":"Hoher Kamp 9",
    "sg:city":"Barsinghausen",
    "sg:phone":"+49 5105/81593",
    "sg:postcode":"30890",
    "sg:province":"Niedersachsen",
    "wof:name":"M. Stransky-reichmann",
    "wof:placetype":"venue"
},
  "geometry": {"coordinates":[9.496533,52.291004],"type":"Point"}
}