{
  "type": "Feature",
  "properties": {
    "iso:country":"DE",
    "sg:address":"Karl-Kromer-Str. 1",
    "sg:city":"Mahlberg",
    "sg:phone":"+49 7825/9350",
    "sg:postcode":"77972",
    "sg:province":"Baden-W\u00fcrttemberg",
    "wof:name":"Sonne",
    "wof:placetype":"venue"
},
  "geometry": {"coordinates":[7.8123931885,48.2871627808],"type":"Point"}
}