{
  "type": "Feature",
  "properties": {
    "iso:country":"DE",
    "sg:address":"Salomonstr. 39",
    "sg:city":"G\u00f6rlitz",
    "sg:phone":"+49 3581/401428",
    "sg:postcode":"02826",
    "sg:province":"Sachsen",
    "wof:name":"Gerhard Sch\u00f6bel",
    "wof:placetype":"venue"
},
  "geometry": {"coordinates":[14.9816188812,51.1498222351],"type":"Point"}
}