{
  "type": "Feature",
  "properties": {
    "iso:country":"DE",
    "sg:address":"Hohenstaufenstr. 52",
    "sg:city":"Pforzheim",
    "sg:phone":"+49 4972/3131040",
    "sg:postcode":"75177",
    "sg:province":"Baden-W\u00fcrttemberg",
    "wof:name":"Friedrich Wacker Gmbh",
    "wof:placetype":"venue"
},
  "geometry": {"coordinates":[8.7086772919,48.8959503174],"type":"Point"}
}