{
  "type": "Feature",
  "properties": {
    "iso:country":"DE",
    "sg:address":"K\u00f6nigswiese",
    "sg:city":"Pocking",
    "sg:phone":"+49 8531/3377",
    "sg:postcode":"94060",
    "sg:province":"Bayern",
    "wof:name":"Peter Gei\u00dfler",
    "wof:placetype":"venue"
},
  "geometry": {"coordinates":[13.35049,48.430405],"type":"Point"}
}