{
  "type": "Feature",
  "properties": {
    "iso:country":"DE",
    "sg:address":"Obere Marktstr. 43",
    "sg:city":"Hildburghausen",
    "sg:phone":"+49 3685/704510",
    "sg:postcode":"98646",
    "sg:province":"Th\u00fcringen",
    "wof:name":"Geyling Immobilienmakler",
    "wof:placetype":"venue"
},
  "geometry": {"coordinates":[10.731811,50.425495],"type":"Point"}
}