{
  "type": "Feature",
  "properties": {
    "iso:country":"DE",
    "sg:address":"Wilhelmstrasse 17",
    "sg:city":"Stuttgart",
    "sg:phone":"+49 711/9547960",
    "sg:postcode":"70372",
    "sg:province":"Baden-W\u00fcrttemberg",
    "wof:name":"Werbeagentur Stuttgart: Werbeagentur Schwanitzdesi",
    "wof:placetype":"venue"
},
  "geometry": {"coordinates":[9.216733,48.804913],"type":"Point"}
}