{
  "type": "Feature",
  "properties": {
    "iso:country":"DE",
    "sg:address":"Gr\u00fcner Weg 26",
    "sg:city":"Crimmitschau",
    "sg:phone":"+49 3762/40959",
    "sg:postcode":"08451",
    "sg:province":"Sachsen",
    "wof:name":"R. Werner Bau Ingenieur",
    "wof:placetype":"venue"
},
  "geometry": {"coordinates":[12.37708,50.812],"type":"Point"}
}