{
  "type": "Feature",
  "properties": {
    "iso:country":"DE",
    "sg:address":"Weisbacher Str. 9",
    "sg:city":"Waldbrunn",
    "sg:phone":"+49 6274/92060",
    "sg:postcode":"69429",
    "sg:province":"Baden-W\u00fcrttemberg",
    "wof:name":"Gernot Diemer Deutsche Verm\u00f6gensberatung Ag",
    "wof:placetype":"venue"
},
  "geometry": {"coordinates":[9.0580654144,49.445110321],"type":"Point"}
}