{
  "type": "Feature",
  "properties": {
    "iso:country":"DE",
    "sg:address":"Ludwig-Leichhardt-Str. 32",
    "sg:city":"Trebatsch",
    "sg:phone":"+49 33674/212",
    "sg:postcode":"15848",
    "sg:province":"Brandenburg",
    "wof:name":"Ernst Richter",
    "wof:placetype":"venue"
},
  "geometry": {"coordinates":[14.1746101379,52.2288208008],"type":"Point"}
}