{
  "type": "Feature",
  "properties": {
    "iso:country":"DE",
    "sg:address":"Kaiserstr. 84",
    "sg:city":"Herten",
    "sg:phone":"+49 2366/31011",
    "sg:postcode":"45699",
    "sg:province":"Nordrhein-Westfalen",
    "wof:name":"Versicherungsb\u00fcro Martin Gruber E. K.",
    "wof:placetype":"venue"
},
  "geometry": {"coordinates":[7.1427140236,51.5956764221],"type":"Point"}
}