{
  "type": "Feature",
  "properties": {
    "iso:country":"DE",
    "sg:address":"Westerheide 7",
    "sg:city":"Handewitt",
    "sg:postcode":"24983",
    "sg:province":"Schleswig-Holstein",
    "wof:name":"Seidls Hausmeisterservice Garten & Winterdienst",
    "wof:placetype":"venue"
},
  "geometry": {"coordinates":[9.3232536316,54.7634735107],"type":"Point"}
}