{
  "type": "Feature",
  "properties": {
    "iso:country":"DE",
    "sg:address":"Papenhuder Str. 9",
    "sg:city":"Hamburg",
    "sg:phone":"+49 40/2209379",
    "sg:postcode":"22087",
    "sg:province":"Hamburg",
    "wof:name":"M. Wimmer",
    "wof:placetype":"venue"
},
  "geometry": {"coordinates":[10.0202760696,53.5644035339],"type":"Point"}
}