{
  "type": "Feature",
  "properties": {
    "iso:country":"DE",
    "sg:address":"H\u00f6henweg 16a",
    "sg:city":"Bochum",
    "sg:phone":"+49 234/493286",
    "sg:postcode":"44879",
    "sg:province":"Nordrhein-Westfalen",
    "wof:name":"Klaus Und Ursula Reifer Immobilien",
    "wof:placetype":"venue"
},
  "geometry": {"coordinates":[7.1633009911,51.4374656677],"type":"Point"}
}