{
  "type": "Feature",
  "properties": {
    "iso:country":"DE",
    "sg:address":"Ahornstr. 18",
    "sg:city":"Rechlin",
    "sg:phone":"+49 4946/8180129",
    "sg:postcode":"17248",
    "sg:province":"Mecklenburg-Vorpommern",
    "wof:name":"Wyker Dampfschiffs Reederei Amrum Gmbh",
    "wof:placetype":"venue"
},
  "geometry": {"coordinates":[8.572602272,54.6925773621],"type":"Point"}
}