{
  "type": "Feature",
  "properties": {
    "iso:country":"DE",
    "sg:address":"Corneliusstr. 17",
    "sg:city":"Solingen",
    "sg:phone":"+49 212/317676",
    "sg:postcode":"42719",
    "sg:province":"Nordrhein-Westfalen",
    "wof:name":"Rudolf Schmidt",
    "wof:placetype":"venue"
},
  "geometry": {"coordinates":[7.047195,51.191051],"type":"Point"}
}