{
  "type": "Feature",
  "properties": {
    "iso:country":"DE",
    "sg:address":"Weinstr. 1",
    "sg:city":"Kanzem",
    "sg:phone":"+49 6501/16709",
    "sg:postcode":"54441",
    "sg:province":"Rheinland-Pfalz",
    "wof:name":"Maximilian Othegraven Weinanbau",
    "wof:placetype":"venue"
},
  "geometry": {"coordinates":[6.5755228996,49.6700935364],"type":"Point"}
}