{
  "type": "Feature",
  "properties": {
    "iso:country":"DE",
    "sg:address":"Schillerstr. 26",
    "sg:city":"Gelsenkirchen",
    "sg:postcode":"45894",
    "sg:province":"Nordrhein-Westfalen",
    "wof:name":"Engler Grundbesitz Gmbh",
    "wof:placetype":"venue"
},
  "geometry": {"coordinates":[7.0654110909,51.5767059326],"type":"Point"}
}