{
  "type": "Feature",
  "properties": {
    "iso:country":"DE",
    "sg:address":"Gro\u00dfer Garten 4-4a",
    "sg:city":"Burgwedel",
    "sg:phone":"+49 5139/278071",
    "sg:postcode":"30938",
    "sg:province":"Niedersachsen",
    "wof:name":"Rebohle & Gieseler",
    "wof:placetype":"venue"
},
  "geometry": {"coordinates":[9.945224,52.501411],"type":"Point"}
}