{
  "type": "Feature",
  "properties": {
    "iso:country":"DE",
    "sg:address":"Weiersteinstr. 10",
    "sg:city":"Limburg",
    "sg:phone":"+49 6431/23000",
    "sg:postcode":"65549",
    "sg:province":"Hessen",
    "wof:name":"Wolfgang B\u00f6hmer",
    "wof:placetype":"venue"
},
  "geometry": {"coordinates":[8.0595378876,50.3856010437],"type":"Point"}
}