{
  "type": "Feature",
  "properties": {
    "iso:country":"DE",
    "sg:address":"Schwienhof 15",
    "sg:city":"Kirchbarkau",
    "sg:phone":"+49 4302/1269",
    "sg:postcode":"24245",
    "sg:province":"Schleswig-Holstein",
    "wof:name":"R. Kretschmar",
    "wof:placetype":"venue"
},
  "geometry": {"coordinates":[10.146914,54.2085],"type":"Point"}
}