{
  "type": "Feature",
  "properties": {
    "iso:country":"DE",
    "sg:address":"Kiewer Str. 1 -3",
    "sg:city":"Leipzig",
    "sg:phone":"+49 341/4227344",
    "sg:postcode":"04209",
    "sg:province":"Sachsen",
    "wof:name":"St\u00e4dtisches Bestattungswesen Leipzig",
    "wof:placetype":"venue"
},
  "geometry": {"coordinates":[12.281057,51.311817],"type":"Point"}
}