{
  "type": "Feature",
  "properties": {
    "iso:country":"DE",
    "sg:address":"Bernauer Str. 34",
    "sg:city":"R\u00fcdnitz",
    "sg:postcode":"16321",
    "sg:province":"Brandenburg",
    "wof:name":"Michael Sch\u00fclke",
    "wof:placetype":"venue"
},
  "geometry": {"coordinates":[13.6262083054,52.7219543457],"type":"Point"}
}