{
  "type": "Feature",
  "properties": {
    "iso:country":"DE",
    "sg:address":"Spittlertorgraben 19",
    "sg:city":"N\u00fcrnberg",
    "sg:phone":"+49 911/2879526",
    "sg:postcode":"90429",
    "sg:province":"Bayern",
    "wof:name":"Pronoris Geb\u00e4udereinigungs- U. Servicegesellschaft Mbh",
    "wof:placetype":"venue"
},
  "geometry": {"coordinates":[11.065834,49.450485],"type":"Point"}
}