{
  "type": "Feature",
  "properties": {
    "iso:country":"DE",
    "sg:address":"Hohenleitenstr. 1",
    "sg:city":"M\u00fcnchen",
    "sg:phone":"+49 89/7559492",
    "sg:postcode":"81476",
    "sg:province":"Bayern",
    "wof:name":"Milan Pilar Komponist",
    "wof:placetype":"venue"
},
  "geometry": {"coordinates":[11.501906395,48.0961074829],"type":"Point"}
}