{
  "type": "Feature",
  "properties": {
    "iso:country":"DE",
    "sg:address":"An der Weede 1",
    "sg:city":"Zornheim",
    "sg:phone":"+49 6136/44938",
    "sg:postcode":"55270",
    "sg:province":"Rheinland-Pfalz",
    "wof:name":"Heinrich Hepp",
    "wof:placetype":"venue"
},
  "geometry": {"coordinates":[8.2280874252,49.8881607056],"type":"Point"}
}