{
  "type": "Feature",
  "properties": {
    "iso:country":"DE",
    "sg:address":"Alte Bahnhofstr. 28",
    "sg:city":"Uetze",
    "sg:phone":"+49 5147/1453",
    "sg:postcode":"31311",
    "sg:province":"Niedersachsen",
    "wof:name":"Hermann Surburg",
    "wof:placetype":"venue"
},
  "geometry": {"coordinates":[10.0949306488,52.4867286682],"type":"Point"}
}