{
  "type": "Feature",
  "properties": {
    "iso:country":"DE",
    "sg:address":"Burgstr. 10",
    "sg:city":"Grafschaft",
    "sg:phone":"+49 2225/7923",
    "sg:postcode":"53501",
    "sg:province":"Rheinland-Pfalz",
    "wof:name":"Adolf Schweinheim",
    "wof:placetype":"venue"
},
  "geometry": {"coordinates":[7.0358119011,50.5867843628],"type":"Point"}
}