{
  "type": "Feature",
  "properties": {
    "iso:country":"DE",
    "sg:address":"Westerholtkamp 2 a",
    "sg:city":"Gro\u00dfenkneten",
    "sg:phone":"+49 4435/1720",
    "sg:postcode":"26197",
    "sg:province":"Niedersachsen",
    "wof:name":"Graf Zeppelin",
    "wof:placetype":"venue"
},
  "geometry": {"coordinates":[8.2139701843,52.9049491882],"type":"Point"}
}