{
  "type": "Feature",
  "properties": {
    "iso:country":"DE",
    "sg:address":"Theodor-Veiel-Str. 35",
    "sg:city":"Stuttgart",
    "sg:phone":"+49 711/525634",
    "sg:postcode":"70374",
    "sg:province":"Baden-W\u00fcrttemberg",
    "wof:name":"Paul W\u00f6lfle",
    "wof:placetype":"venue"
},
  "geometry": {"coordinates":[9.2406730652,48.8090286255],"type":"Point"}
}