{
  "type": "Feature",
  "properties": {
    "iso:country":"DE",
    "sg:address":"Niederrheinische Str. 78",
    "sg:city":"Kirchhain",
    "sg:phone":"+49 4964/222068",
    "sg:postcode":"35274",
    "sg:province":"Hessen",
    "wof:name":"Gebr. Weikardt",
    "wof:placetype":"venue"
},
  "geometry": {"coordinates":[8.9376602173,50.8249855042],"type":"Point"}
}