{
  "type": "Feature",
  "properties": {
    "iso:country":"DE",
    "sg:address":"Oberaulaer Weg 12",
    "sg:city":"Oberaula",
    "sg:postcode":"36280",
    "sg:province":"Hessen",
    "wof:name":"Pure Sun E. K.",
    "wof:placetype":"venue"
},
  "geometry": {"coordinates":[9.429245,50.856739],"type":"Point"}
}