{
  "type": "Feature",
  "properties": {
    "iso:country":"DE",
    "sg:address":"F\u00fcrstenrieder Str. 214",
    "sg:city":"M\u00fcnchen",
    "sg:phone":"+49 89/71039800",
    "sg:postcode":"81377",
    "sg:province":"Bayern",
    "wof:name":"Beffert & Wastian Versicherungs-",
    "wof:placetype":"venue"
},
  "geometry": {"coordinates":[11.5022563934,48.1205635071],"type":"Point"}
}