{
  "type": "Feature",
  "properties": {
    "iso:country":"DE",
    "sg:address":"Peter-Henlein-Str. 28",
    "sg:city":"K\u00fcnzell",
    "sg:phone":"+49 661/8191",
    "sg:postcode":"36093",
    "sg:province":"Hessen",
    "wof:name":"Fulmin Mineral\u00f6l-vertriebs- Gesellschaft Mbh",
    "wof:placetype":"venue"
},
  "geometry": {"coordinates":[9.72694,50.534378],"type":"Point"}
}