{
  "type": "Feature",
  "properties": {
    "iso:country":"DE",
    "sg:address":"Kleine Wollweberstr. 23",
    "sg:city":"Neubrandenburg",
    "sg:phone":"+49 395/5666123",
    "sg:postcode":"17033",
    "sg:province":"Mecklenburg-Vorpommern",
    "wof:name":"G\u00e4stehaus Manfred Bartels",
    "wof:placetype":"venue"
},
  "geometry": {"coordinates":[13.255446434,53.5559806824],"type":"Point"}
}