{
  "type": "Feature",
  "properties": {
    "iso:country":"DE",
    "sg:address":"Odenkirchener Str. 200",
    "sg:city":"M\u00f6nchengladbach",
    "sg:phone":"+49 2166/48514",
    "sg:postcode":"41236",
    "sg:province":"Nordrhein-Westfalen",
    "wof:name":"G\u00fcnter Uhlig",
    "wof:placetype":"venue"
},
  "geometry": {"coordinates":[6.447,51.157734],"type":"Point"}
}