{
  "type": "Feature",
  "properties": {
    "iso:country":"DE",
    "sg:address":"Schl\u00f6\u00dflgartenweg 25a",
    "sg:city":"Nittenau",
    "sg:phone":"+49 9436/1339",
    "sg:postcode":"93149",
    "sg:province":"Bayern",
    "wof:name":"G\u00f6tzer-bau Gmbh",
    "wof:placetype":"venue"
},
  "geometry": {"coordinates":[12.2711343765,49.1923980713],"type":"Point"}
}