{
  "type": "Feature",
  "properties": {
    "iso:country":"DE",
    "sg:address":"M\u00fchlbergstr. 12-14",
    "sg:city":"Eisenberg",
    "sg:phone":"+49 36691/42628",
    "sg:postcode":"07607",
    "sg:province":"Th\u00fcringen",
    "wof:name":"Germanus Gmbh",
    "wof:placetype":"venue"
},
  "geometry": {"coordinates":[11.8967475891,50.9729042053],"type":"Point"}
}