{
  "type": "Feature",
  "properties": {
    "iso:country":"DE",
    "sg:address":"Rathausstr. 22",
    "sg:city":"Arzberg",
    "sg:phone":"+49 9233/1318",
    "sg:postcode":"95659",
    "sg:province":"Bayern",
    "wof:name":"Friedrich Schmidt Gmbh",
    "wof:placetype":"venue"
},
  "geometry": {"coordinates":[12.186273,50.05687],"type":"Point"}
}