{
  "type": "Feature",
  "properties": {
    "iso:country":"DE",
    "sg:address":"Pfannenstiel 37",
    "sg:city":"Ravensburg",
    "sg:phone":"+49 751/94116",
    "sg:postcode":"88214",
    "sg:province":"Baden-W\u00fcrttemberg",
    "wof:name":"Jeunesse Andrea Treier",
    "wof:placetype":"venue"
},
  "geometry": {"coordinates":[9.602465,47.78199],"type":"Point"}
}