{
  "type": "Feature",
  "properties": {
    "iso:country":"DE",
    "sg:address":"Uigenauer Weg 35",
    "sg:city":"Schwabach",
    "sg:phone":"+49 9122/13473",
    "sg:postcode":"91126",
    "sg:province":"Bayern",
    "wof:name":"Kunzmann Gmbh",
    "wof:placetype":"venue"
},
  "geometry": {"coordinates":[11.014845,49.312466],"type":"Point"}
}