{
  "type": "Feature",
  "properties": {
    "iso:country":"DE",
    "sg:address":"H\u00e4usellohweg 11",
    "sg:city":"Selb",
    "sg:phone":"+49 9287/60162",
    "sg:postcode":"95100",
    "sg:province":"Bayern",
    "wof:name":"Werner Christgau Rechtsanwalt",
    "wof:placetype":"venue"
},
  "geometry": {"coordinates":[12.1457920074,50.1605262756],"type":"Point"}
}