{
  "type": "Feature",
  "properties": {
    "iso:country":"DE",
    "sg:address":"Am Sandwerder 17-19",
    "sg:city":"Berlin",
    "sg:phone":"+49 30/804830",
    "sg:postcode":"14109",
    "sg:province":"Berlin",
    "wof:name":"American Academy In Berlin Gmbh",
    "wof:placetype":"venue"
},
  "geometry": {"coordinates":[13.1809177399,52.4241905212],"type":"Point"}
}