{
  "type": "Feature",
  "properties": {
    "iso:country":"DE",
    "sg:address":"Traubinger Str. 11",
    "sg:city":"Andechs",
    "sg:phone":"+49 8157/2624",
    "sg:postcode":"82346",
    "sg:province":"Bayern",
    "wof:name":"Max Beyer",
    "wof:placetype":"venue"
},
  "geometry": {"coordinates":[11.231685,47.945236],"type":"Point"}
}