{
  "type": "Feature",
  "properties": {
    "iso:country":"DE",
    "sg:address":"Hendrik-Witte-Str. 8",
    "sg:city":"Essen",
    "sg:phone":"+49 201/224858",
    "sg:postcode":"45128",
    "sg:province":"Nordrhein-Westfalen",
    "wof:name":"Willy H. Schmoley Gesellschaft F\u00fcr Lager- Und F\u00f6rdertechnik",
    "wof:placetype":"venue"
},
  "geometry": {"coordinates":[7.0192642212,51.4452056885],"type":"Point"}
}