{
  "type": "Feature",
  "properties": {
    "iso:country":"DE",
    "sg:address":"Lahnstr. 2",
    "sg:city":"Reutlingen",
    "sg:phone":"+49 7121/67330",
    "sg:postcode":"72768",
    "sg:province":"Baden-W\u00fcrttemberg",
    "wof:name":"B.rosenbaum",
    "wof:placetype":"venue"
},
  "geometry": {"coordinates":[9.191863,48.540646],"type":"Point"}
}