{
  "type": "Feature",
  "properties": {
    "iso:country":"DE",
    "sg:address":"Sch\u00fctzenstr. 11",
    "sg:city":"Lauf",
    "sg:phone":"+49 9123/3230",
    "sg:postcode":"91207",
    "sg:province":"Bayern",
    "wof:name":"Fritz Ziegler",
    "wof:placetype":"venue"
},
  "geometry": {"coordinates":[11.2663879395,49.5080451965],"type":"Point"}
}