{
  "type": "Feature",
  "properties": {
    "iso:country":"DE",
    "sg:address":"In Der Rosenau 4",
    "sg:city":"M\u00fcnchen",
    "sg:phone":"+49 4975/2497750",
    "sg:postcode":"81829",
    "sg:province":"Bayern",
    "wof:name":"Waldsee Electronic Gmbh",
    "wof:placetype":"venue"
},
  "geometry": {"coordinates":[9.739232,47.924763],"type":"Point"}
}