{
  "type": "Feature",
  "properties": {
    "iso:country":"DE",
    "sg:address":"Neust\u00e4dter Str. 44",
    "sg:city":"Hamburg",
    "sg:phone":"+49 40/344895",
    "sg:postcode":"20355",
    "sg:province":"Hamburg",
    "wof:name":"Holsten-quelle",
    "wof:placetype":"venue"
},
  "geometry": {"coordinates":[9.9828109741,53.5534362793],"type":"Point"}
}