{
  "type": "Feature",
  "properties": {
    "iso:country":"DE",
    "sg:address":"Hoferm\u00fchle 1",
    "sg:city":"Heiligenhaus",
    "sg:phone":"+49 2102/51008",
    "sg:postcode":"42579",
    "sg:province":"Nordrhein-Westfalen",
    "wof:name":"Vo\u00df & Vo\u00df Gmbh",
    "wof:placetype":"venue"
},
  "geometry": {"coordinates":[6.942699,51.307743],"type":"Point"}
}