{
  "type": "Feature",
  "properties": {
    "iso:country":"DE",
    "sg:address":"Beuthener Str. 9",
    "sg:city":"M\u00fcnchen",
    "sg:phone":"+49 89/937281",
    "sg:postcode":"81929",
    "sg:province":"Bayern",
    "wof:name":"Uwe Eggerdinger Steuerberater",
    "wof:placetype":"venue"
},
  "geometry": {"coordinates":[11.652302742,48.1475944519],"type":"Point"}
}