{
  "type": "Feature",
  "properties": {
    "iso:country":"DE",
    "sg:address":"Mindener Str. 230",
    "sg:city":"Bad Essen",
    "sg:phone":"+49 5742/93090",
    "sg:postcode":"49152",
    "sg:province":"Niedersachsen",
    "wof:name":"Dahlinghauser Bekleidungs- Werkstatt Gmbh",
    "wof:placetype":"venue"
},
  "geometry": {"coordinates":[8.4651241302,52.3091316223],"type":"Point"}
}