{
  "type": "Feature",
  "properties": {
    "iso:country":"DE",
    "sg:address":"Kirchhuchtinger Landstr. 80",
    "sg:city":"Bremen",
    "sg:phone":"+49 421/838571",
    "sg:postcode":"28259",
    "sg:province":"Bremen",
    "wof:name":"Rudolf M\u00fcller Ohg",
    "wof:placetype":"venue"
},
  "geometry": {"coordinates":[8.739186,53.047989],"type":"Point"}
}