{
  "type": "Feature",
  "properties": {
    "iso:country":"DE",
    "sg:address":"Langenscheidtstr. 6a",
    "sg:city":"Berlin",
    "sg:phone":"+49 30/7827952",
    "sg:postcode":"10827",
    "sg:province":"Berlin",
    "wof:name":"Pizzeria Si O No 1",
    "wof:placetype":"venue"
},
  "geometry": {"coordinates":[13.3621406555,52.4891471863],"type":"Point"}
}