{
  "type": "Feature",
  "properties": {
    "iso:country":"DE",
    "sg:address":"Bahnhofstr. 23",
    "sg:city":"R\u00fcsselsheim",
    "sg:phone":"+49 6142/965303",
    "sg:postcode":"65428",
    "sg:province":"Hessen",
    "wof:name":"Denninghoff Und Kr\u00fcger Rechtsanw\u00e4lte Und Notare",
    "wof:placetype":"venue"
},
  "geometry": {"coordinates":[8.4141740799,49.993850708],"type":"Point"}
}