{
  "type": "Feature",
  "properties": {
    "iso:country":"DE",
    "sg:address":"Kurhausstr. 9",
    "sg:city":"Todtnau",
    "sg:phone":"+49 7671/1312",
    "sg:postcode":"79674",
    "sg:province":"Baden-W\u00fcrttemberg",
    "wof:name":"Herbert Rotzinger",
    "wof:placetype":"venue"
},
  "geometry": {"coordinates":[7.9400501251,47.8512001038],"type":"Point"}
}