{
  "type": "Feature",
  "properties": {
    "iso:country":"DE",
    "sg:address":"Bahnhofstr. 108",
    "sg:city":"Osterwald",
    "sg:phone":"+49 5946/693",
    "sg:postcode":"49828",
    "sg:province":"Niedersachsen",
    "wof:name":"Harm Boll",
    "wof:placetype":"venue"
},
  "geometry": {"coordinates":[7.011505,52.554611],"type":"Point"}
}