{
  "type": "Feature",
  "properties": {
    "iso:country":"DE",
    "sg:address":"Tegernseestr. 22",
    "sg:city":"Rosenheim",
    "sg:postcode":"83022",
    "sg:province":"Bayern",
    "wof:name":"Esmo Ag",
    "wof:placetype":"venue"
},
  "geometry": {"coordinates":[12.131876,47.847397],"type":"Point"}
}