{
  "type": "Feature",
  "properties": {
    "iso:country":"DE",
    "sg:address":"Oesterdieken",
    "sg:city":"Wangerland",
    "sg:phone":"+49 4425/202",
    "sg:postcode":"26434",
    "sg:province":"Niedersachsen",
    "wof:name":"Dr. Immo M\u00fcller Tierarzt",
    "wof:placetype":"venue"
},
  "geometry": {"coordinates":[7.9979200363,53.6447257996],"type":"Point"}
}