{
  "type": "Feature",
  "properties": {
    "iso:country":"DE",
    "sg:address":"Graflinger Str 37",
    "sg:city":"Deggendorf",
    "sg:phone":"+49 991",
    "sg:postcode":"94469",
    "sg:province":"Bayern",
    "wof:name":"Alle Aktuellen Musical Veranstaltungen",
    "wof:placetype":"venue"
},
  "geometry": {"coordinates":[12.95972,48.839832],"type":"Point"}
}