{
  "type": "Feature",
  "properties": {
    "iso:country":"DE",
    "sg:address":"Wartewg. 40",
    "sg:city":"Stadtoldendorf",
    "sg:phone":"+49 4955/3290010",
    "sg:postcode":"37627",
    "sg:province":"Niedersachsen",
    "wof:name":"August L\u00d6nneker Gmbh & Co. Kg",
    "wof:placetype":"venue"
},
  "geometry": {"coordinates":[9.6164274216,51.8801383972],"type":"Point"}
}