{
  "type": "Feature",
  "properties": {
    "iso:country":"DE",
    "sg:address":"Rosenheimer Str. 18",
    "sg:city":"Schechen",
    "sg:phone":"+49 8039/1527",
    "sg:postcode":"83135",
    "sg:province":"Bayern",
    "wof:name":"Wechselberger Gmbh",
    "wof:placetype":"venue"
},
  "geometry": {"coordinates":[12.1242809296,47.9288482666],"type":"Point"}
}