{
  "type": "Feature",
  "properties": {
    "iso:country":"DE",
    "sg:address":"Im Kolossa-Markt",
    "sg:city":"Br\u00fchl",
    "sg:phone":"+49 6202/72573",
    "sg:postcode":"68782",
    "sg:province":"Baden-W\u00fcrttemberg",
    "wof:name":"E. Teut",
    "wof:placetype":"venue"
},
  "geometry": {"coordinates":[8.534858,49.395103],"type":"Point"}
}