{
  "type": "Feature",
  "properties": {
    "iso:country":"DE",
    "sg:address":"Kleberstr. 6-8",
    "sg:city":"Aschaffenburg",
    "sg:phone":"+49 6021/12097",
    "sg:postcode":"63739",
    "sg:province":"Bayern",
    "wof:name":"Sigrid Aulbach Steuerberaterin",
    "wof:placetype":"venue"
},
  "geometry": {"coordinates":[9.1438493729,49.9792900085],"type":"Point"}
}