{
  "type": "Feature",
  "properties": {
    "iso:country":"DE",
    "sg:address":"Obere Waldstr. 16",
    "sg:city":"Villingen-Schwenningen",
    "sg:postcode":"78048",
    "sg:province":"Baden-W\u00fcrttemberg",
    "wof:name":"Cordes Gmbh & Co. Kg",
    "wof:placetype":"venue"
},
  "geometry": {"coordinates":[8.435269,48.070541],"type":"Point"}
}