{
  "type": "Feature",
  "properties": {
    "iso:country":"DE",
    "sg:address":"August-Bebel-Str. 2",
    "sg:city":"Finsterwalde",
    "sg:phone":"+49 3531/8514",
    "sg:postcode":"03238",
    "sg:province":"Brandenburg",
    "wof:name":"Engel-apotheke",
    "wof:placetype":"venue"
},
  "geometry": {"coordinates":[13.710913,51.633423],"type":"Point"}
}