{
  "type": "Feature",
  "properties": {
    "iso:country":"DE",
    "sg:address":"Esslinger Str. 5",
    "sg:city":"Plochingen",
    "sg:phone":"+49 7153/22530",
    "sg:postcode":"73207",
    "sg:province":"Baden-W\u00fcrttemberg",
    "wof:name":"Union-theater",
    "wof:placetype":"venue"
},
  "geometry": {"coordinates":[9.4145431519,48.7111740112],"type":"Point"}
}