{
  "type": "Feature",
  "properties": {
    "iso:country":"DE",
    "sg:address":"Ulrichstr. 21",
    "sg:city":"G\u00f6ppingen",
    "sg:postcode":"73033",
    "sg:province":"Baden-W\u00fcrttemberg",
    "wof:name":"P.m.sports",
    "wof:placetype":"venue"
},
  "geometry": {"coordinates":[9.6547908783,48.7084388733],"type":"Point"}
}