{
  "type": "Feature",
  "properties": {
    "iso:country":"DE",
    "sg:address":"St.-Gallus-Str. 17",
    "sg:city":"Gessertshausen",
    "sg:phone":"+49 8238/3869",
    "sg:postcode":"86459",
    "sg:province":"Bayern",
    "wof:name":"Georg Kraus",
    "wof:placetype":"venue"
},
  "geometry": {"coordinates":[10.73306,48.342716],"type":"Point"}
}