{
  "type": "Feature",
  "properties": {
    "iso:country":"DE",
    "sg:address":"Am J\u00e4gerberg 4",
    "sg:city":"Velten",
    "sg:phone":"+49 4933/0439650",
    "sg:postcode":"16727",
    "sg:province":"Brandenburg",
    "wof:name":"Carl Stahl Gmbh Velten",
    "wof:placetype":"venue"
},
  "geometry": {"coordinates":[13.209894,52.66613],"type":"Point"}
}