{
  "type": "Feature",
  "properties": {
    "iso:country":"DE",
    "sg:address":"Sereetzer Str.",
    "sg:city":"Bad Schwartau",
    "sg:phone":"+49 451/396271",
    "sg:postcode":"23611",
    "sg:province":"Schleswig-Holstein",
    "wof:name":"Sereetzer Kl\u00f6nstube",
    "wof:placetype":"venue"
},
  "geometry": {"coordinates":[10.7128829956,53.9286613464],"type":"Point"}
}