{
  "type": "Feature",
  "properties": {
    "iso:country":"DE",
    "sg:address":"Mittelweg 4",
    "sg:city":"Edemissen",
    "sg:phone":"+49 5176/8327",
    "sg:postcode":"31234",
    "sg:province":"Niedersachsen",
    "wof:name":"Ernst Heine",
    "wof:placetype":"venue"
},
  "geometry": {"coordinates":[10.320063,52.399773],"type":"Point"}
}