{
  "type": "Feature",
  "properties": {
    "iso:country":"DE",
    "sg:address":"Walder Str. 406",
    "sg:city":"Hilden",
    "sg:phone":"+49 2103/61926",
    "sg:postcode":"40724",
    "sg:province":"Nordrhein-Westfalen",
    "wof:name":"Franz Henkel Gmbh & Co. Kg",
    "wof:placetype":"venue"
},
  "geometry": {"coordinates":[6.981572,51.167614],"type":"Point"}
}