{
  "type": "Feature",
  "properties": {
    "iso:country":"DE",
    "sg:address":"Nicolaus-Otto-Str. 25",
    "sg:city":"Ulm",
    "sg:phone":"+49 731/387744",
    "sg:postcode":"89079",
    "sg:province":"Baden-W\u00fcrttemberg",
    "wof:name":"Helmut Rieger Ingenieur",
    "wof:placetype":"venue"
},
  "geometry": {"coordinates":[9.9318637848,48.3587646484],"type":"Point"}
}