{
  "type": "Feature",
  "properties": {
    "iso:country":"DE",
    "sg:address":"Mittelstr. 2",
    "sg:city":"Elsdorf",
    "sg:phone":"+49 2274/81800",
    "sg:postcode":"50189",
    "sg:province":"Nordrhein-Westfalen",
    "wof:name":"Pizzeria Pasquale De Vico",
    "wof:placetype":"venue"
},
  "geometry": {"coordinates":[6.5690188408,50.9345016479],"type":"Point"}
}