{
  "type": "Feature",
  "properties": {
    "iso:country":"DE",
    "sg:address":"Am Strauchbusch 4",
    "sg:city":"Neuss",
    "sg:phone":"+49 2131/591933",
    "sg:postcode":"41462",
    "sg:province":"Nordrhein-Westfalen",
    "wof:name":"Hans Funke",
    "wof:placetype":"venue"
},
  "geometry": {"coordinates":[6.680232,51.227081],"type":"Point"}
}