{
  "type": "Feature",
  "properties": {
    "iso:country":"DE",
    "sg:address":"Zwiefalter Str. 20",
    "sg:city":"Riedlingen",
    "sg:phone":"+49 7371/93020",
    "sg:postcode":"88499",
    "sg:province":"Baden-W\u00fcrttemberg",
    "wof:name":"Form Test",
    "wof:placetype":"venue"
},
  "geometry": {"coordinates":[9.4780330658,48.1564826965],"type":"Point"}
}