{
  "type": "Feature",
  "properties": {
    "iso:country":"DE",
    "sg:address":"Breslauer Str. 2",
    "sg:city":"Dettelbach",
    "sg:phone":"+49 9324/1547",
    "sg:postcode":"97337",
    "sg:province":"Bayern",
    "wof:name":"Kotzmann Inh. Thomas Kotzmann",
    "wof:placetype":"venue"
},
  "geometry": {"coordinates":[10.1557731628,49.8011436462],"type":"Point"}
}