{
  "type": "Feature",
  "properties": {
    "iso:country":"DE",
    "sg:address":"Gustav-M\u00fcller-Platz 7",
    "sg:city":"Berlin",
    "sg:phone":"+49 30/44048849",
    "sg:postcode":"10829",
    "sg:province":"Berlin",
    "wof:name":"Distant Dreams Filmproduktion Gmbh",
    "wof:placetype":"venue"
},
  "geometry": {"coordinates":[13.3621578217,52.4838180542],"type":"Point"}
}