{
  "type": "Feature",
  "properties": {
    "iso:country":"DE",
    "sg:address":"Oststr. 12",
    "sg:city":"Triebes",
    "sg:phone":"+49 36622/78510",
    "sg:postcode":"07950",
    "sg:province":"Th\u00fcringen",
    "wof:name":"Bernd Dittmar",
    "wof:placetype":"venue"
},
  "geometry": {"coordinates":[12.025207,50.686836],"type":"Point"}
}