{
  "type": "Feature",
  "properties": {
    "iso:country":"DE",
    "sg:address":"Richard-Wagner-Str. 12",
    "sg:city":"Erlangen",
    "sg:phone":"+49 9131/28912",
    "sg:postcode":"91054",
    "sg:province":"Bayern",
    "wof:name":"Kaisers Drugstore",
    "wof:placetype":"venue"
},
  "geometry": {"coordinates":[11.0027399063,49.5964546204],"type":"Point"}
}