{
  "type": "Feature",
  "properties": {
    "iso:country":"DE",
    "sg:address":"Eisenacher Str. 19",
    "sg:city":"Dortmund",
    "sg:phone":"+49 231/5570080",
    "sg:postcode":"44143",
    "sg:province":"Nordrhein-Westfalen",
    "wof:name":"Nowak Folienverarbeitung Gmbh",
    "wof:placetype":"venue"
},
  "geometry": {"coordinates":[7.4828710556,51.5167922974],"type":"Point"}
}