{
  "type": "Feature",
  "properties": {
    "iso:country":"DE",
    "sg:address":"Mittelstr. 75",
    "sg:city":"Hilden",
    "sg:phone":"+49 2103/51440",
    "sg:postcode":"40721",
    "sg:province":"Nordrhein-Westfalen",
    "wof:name":"Wulf Kg",
    "wof:placetype":"venue"
},
  "geometry": {"coordinates":[6.933776,51.168564],"type":"Point"}
}