{
  "type": "Feature",
  "properties": {
    "iso:country":"DE",
    "sg:address":"Z\u00f6beritzer Weg 2e",
    "sg:city":"Braschwitz",
    "sg:phone":"+49 34604/21972",
    "sg:postcode":"06188",
    "sg:province":"Sachsen-Anhalt",
    "wof:name":"J. T\u00e4nzer Immobilienmakler",
    "wof:placetype":"venue"
},
  "geometry": {"coordinates":[12.0560436249,51.521320343],"type":"Point"}
}