{
  "type": "Feature",
  "properties": {
    "iso:country":"DE",
    "sg:address":"Hauptstr. 27",
    "sg:city":"Salzhemmendorf",
    "sg:phone":"+49 5153/7350",
    "sg:postcode":"31020",
    "sg:province":"Niedersachsen",
    "wof:name":"A. Chetioui",
    "wof:placetype":"venue"
},
  "geometry": {"coordinates":[9.5882825851,52.0666275024],"type":"Point"}
}