{
  "type": "Feature",
  "properties": {
    "iso:country":"DE",
    "sg:address":"Kloster 7",
    "sg:city":"Rohr",
    "sg:postcode":"98530",
    "sg:province":"Th\u00fcringen",
    "wof:name":"Rastst\u00e4tte Zum Kloster Verwaltungs Gmbh",
    "wof:placetype":"venue"
},
  "geometry": {"coordinates":[10.5138731003,50.5721130371],"type":"Point"}
}