{
  "type": "Feature",
  "properties": {
    "iso:country":"DE",
    "sg:address":"Max-Planck-Str. 23",
    "sg:city":"Bad Salzuflen",
    "sg:phone":"+49 5222/22066",
    "sg:postcode":"32107",
    "sg:province":"Nordrhein-Westfalen",
    "wof:name":"Obermark Schweisstechnik Vertriebs-gmbh",
    "wof:placetype":"venue"
},
  "geometry": {"coordinates":[8.76151371,52.0390319824],"type":"Point"}
}