{
  "type": "Feature",
  "properties": {
    "iso:country":"DE",
    "sg:address":"Gro\u00dfe Gr\u00fcne Str. 28",
    "sg:city":"Waren",
    "sg:phone":"+49 3991/665538",
    "sg:postcode":"17192",
    "sg:province":"Mecklenburg-Vorpommern",
    "wof:name":"P. Borchardt",
    "wof:placetype":"venue"
},
  "geometry": {"coordinates":[12.78299,53.510941],"type":"Point"}
}