{
  "type": "Feature",
  "properties": {
    "iso:country":"DE",
    "sg:address":"B\u00f6blinger Str. 19",
    "sg:city":"Leonberg",
    "sg:phone":"+49 7152/338520",
    "sg:postcode":"71229",
    "sg:province":"Baden-W\u00fcrttemberg",
    "wof:name":"Hillmer Messebau Gmbh",
    "wof:placetype":"venue"
},
  "geometry": {"coordinates":[9.031558,48.789062],"type":"Point"}
}