{
  "type": "Feature",
  "properties": {
    "iso:country":"DE",
    "sg:address":"Syker Str. 66",
    "sg:city":"Delmenhorst",
    "sg:phone":"+49 4221/72022",
    "sg:postcode":"27751",
    "sg:province":"Niedersachsen",
    "wof:name":"Besser Sitzen",
    "wof:placetype":"venue"
},
  "geometry": {"coordinates":[8.653212,53.050724],"type":"Point"}
}