{
  "type": "Feature",
  "properties": {
    "iso:country":"DE",
    "sg:address":"Bornwiesenweg 29",
    "sg:city":"Birstein",
    "sg:postcode":"63633",
    "sg:province":"Hessen",
    "wof:name":"Svg Immobilien Projektmanagement Gmbh",
    "wof:placetype":"venue"
},
  "geometry": {"coordinates":[9.3002071381,50.3544654846],"type":"Point"}
}