{
  "type": "Feature",
  "properties": {
    "iso:country":"DE",
    "sg:address":"Eglsee 11",
    "sg:city":"Ruhstorf",
    "sg:phone":"+49 8503/521",
    "sg:postcode":"94099",
    "sg:province":"Bayern",
    "wof:name":"Johann Wagner",
    "wof:placetype":"venue"
},
  "geometry": {"coordinates":[13.391751,48.485519],"type":"Point"}
}