{
  "type": "Feature",
  "properties": {
    "iso:country":"DE",
    "sg:address":"Bahnhofstr. 4",
    "sg:city":"Suhl",
    "sg:postcode":"98527",
    "sg:province":"Th\u00fcringen",
    "wof:name":"Wissenschaftliche Allgemeinbibliothek Des",
    "wof:placetype":"venue"
},
  "geometry": {"coordinates":[10.689423,50.608429],"type":"Point"}
}