{
  "type": "Feature",
  "properties": {
    "iso:country":"DE",
    "sg:address":"Alstadenerstr.7",
    "sg:city":"Oberhausen",
    "sg:postcode":"46049",
    "sg:province":"Nordrhein-Westfalen",
    "wof:name":"Pire\u00b4 Bauelemente Design",
    "wof:placetype":"venue"
},
  "geometry": {"coordinates":[6.835518,51.46344],"type":"Point"}
}