{
  "type": "Feature",
  "properties": {
    "iso:country":"DE",
    "sg:address":"Steinweg 52",
    "sg:city":"M\u00fchlhausen",
    "sg:phone":"+49 4936/0148430",
    "sg:postcode":"99974",
    "sg:province":"Th\u00fcringen",
    "wof:name":"Herpe Werbestudio Gmbh",
    "wof:placetype":"venue"
},
  "geometry": {"coordinates":[10.4624900818,51.2100944519],"type":"Point"}
}