{
  "type": "Feature",
  "properties": {
    "iso:country":"DE",
    "sg:address":"Postfach 101033:: 40001 D\u00fcsseldorf:: Germany.^^Kasernenstr 69::",
    "sg:city":"D\u00fcsseldorf",
    "sg:phone":"+49 211/8730",
    "sg:postcode":"40213",
    "sg:province":"Nordrhein-Westfalen",
    "wof:name":"Kreissparkasse D\u00fcsseldorf",
    "wof:placetype":"venue"
},
  "geometry": {"coordinates":[6.775735,51.227871],"type":"Point"}
}