{
  "type": "Feature",
  "properties": {
    "iso:country":"DE",
    "sg:address":"W\u00fclfeler Str. 2",
    "sg:city":"Hemmingen",
    "sg:phone":"+49 511/2343221",
    "sg:postcode":"30966",
    "sg:province":"Niedersachsen",
    "wof:name":"Dog Elektronik Gmbh",
    "wof:placetype":"venue"
},
  "geometry": {"coordinates":[9.755631,52.312263],"type":"Point"}
}