{
  "type": "Feature",
  "properties": {
    "iso:country":"DE",
    "sg:address":"Martin-Luther-Str. 15",
    "sg:city":"Hattingen",
    "sg:phone":"+49 8193/71261",
    "sg:postcode":"45525",
    "sg:province":"Nordrhein-Westfalen",
    "wof:name":"Eos Verlag Erzabtei St Ottilien",
    "wof:placetype":"venue"
},
  "geometry": {"coordinates":[11.0444002151,48.0947151184],"type":"Point"}
}