{
  "type": "Feature",
  "properties": {
    "iso:country":"DE",
    "sg:address":"Ballinstr. 16",
    "sg:city":"Berlin",
    "sg:phone":"+49 4930/6898060",
    "sg:postcode":"12359",
    "sg:province":"Berlin",
    "wof:name":"Itp Ton & Bildtr\u00c4ger Gmbh",
    "wof:placetype":"venue"
},
  "geometry": {"coordinates":[13.4488515854,52.4620666504],"type":"Point"}
}