{
  "type": "Feature",
  "properties": {
    "iso:country":"DE",
    "sg:address":"Mittelstr. 12",
    "sg:city":"Rehlingen-Siersburg",
    "sg:phone":"+49 6835/2377",
    "sg:postcode":"66780",
    "sg:province":"Saarland",
    "wof:name":"Peter Augustin",
    "wof:placetype":"venue"
},
  "geometry": {"coordinates":[6.684642,49.381187],"type":"Point"}
}