{
  "type": "Feature",
  "properties": {
    "iso:country":"DE",
    "sg:address":"Wilhelm-Leuschner-Str. 28",
    "sg:city":"Worms",
    "sg:phone":"+49 6241/28674",
    "sg:postcode":"67547",
    "sg:province":"Rheinland-Pfalz",
    "wof:name":"I. Beckerle",
    "wof:placetype":"venue"
},
  "geometry": {"coordinates":[8.357571,49.634251],"type":"Point"}
}