{
  "type": "Feature",
  "properties": {
    "iso:country":"DE",
    "sg:address":"Eichenweg 2",
    "sg:city":"H\u00fcnstetten",
    "sg:phone":"+49 6128/71147",
    "sg:postcode":"65510",
    "sg:province":"Hessen",
    "wof:name":"Hans-j\u00fcrgen Werner Architekt",
    "wof:placetype":"venue"
},
  "geometry": {"coordinates":[8.259858,50.211395],"type":"Point"}
}