{
  "type": "Feature",
  "properties": {
    "iso:country":"DE",
    "sg:address":"Wilhelm-Berg-Str. 2",
    "sg:city":"G\u00f6ttingen",
    "sg:phone":"+49 551/504720",
    "sg:postcode":"37079",
    "sg:province":"Niedersachsen",
    "wof:name":"Wolfgang Euler Rechtsanwalt",
    "wof:placetype":"venue"
},
  "geometry": {"coordinates":[9.8951511383,51.5538101196],"type":"Point"}
}