{
  "type": "Feature",
  "properties": {
    "iso:country":"DE",
    "sg:address":"Rathausstr. 8",
    "sg:city":"Ratzeburg",
    "sg:postcode":"23909",
    "sg:province":"Schleswig-Holstein",
    "wof:name":"Orthop\u00e4die-technik Ratzeburg Reinald",
    "wof:placetype":"venue"
},
  "geometry": {"coordinates":[10.7741355896,53.7001571655],"type":"Point"}
}