{
  "type": "Feature",
  "properties": {
    "iso:country":"DE",
    "sg:address":"Brandenburger Str. 48",
    "sg:city":"Genthin",
    "sg:phone":"+49 3933/3250",
    "sg:postcode":"39307",
    "sg:province":"Sachsen-Anhalt",
    "wof:name":"Pension Zum Kleeblatt",
    "wof:placetype":"venue"
},
  "geometry": {"coordinates":[12.1579093933,52.4058456421],"type":"Point"}
}