{
  "type": "Feature",
  "properties": {
    "iso:country":"DE",
    "sg:address":"Camillo-Sitte-Platz 5",
    "sg:city":"Essen",
    "sg:phone":"+49 201/253871",
    "sg:postcode":"45136",
    "sg:province":"Nordrhein-Westfalen",
    "wof:name":"Real Projekt Immobilien Betreuungsges. Mbh",
    "wof:placetype":"venue"
},
  "geometry": {"coordinates":[7.0321722031,51.4430046082],"type":"Point"}
}