{
  "type": "Feature",
  "properties": {
    "iso:country":"DE",
    "sg:address":"Immbarg 34",
    "sg:city":"Henstedt-Ulzburg",
    "sg:phone":"+49 4193/892520",
    "sg:postcode":"24558",
    "sg:province":"Schleswig-Holstein",
    "wof:name":"Teratek Kabelboden Gmbh",
    "wof:placetype":"venue"
},
  "geometry": {"coordinates":[10.015057,53.758877],"type":"Point"}
}