{
  "type": "Feature",
  "properties": {
    "iso:country":"DE",
    "sg:address":"Dingholz 20",
    "sg:city":"Sterup",
    "sg:phone":"+49 4637/215",
    "sg:postcode":"24996",
    "sg:province":"Schleswig-Holstein",
    "wof:name":"J. Peter Vogt",
    "wof:placetype":"venue"
},
  "geometry": {"coordinates":[9.7121200562,54.7323303223],"type":"Point"}
}