{
  "type": "Feature",
  "properties": {
    "iso:country":"DE",
    "sg:address":"Zellerhornstr. 16",
    "sg:city":"Rosenheim",
    "sg:phone":"+49 8031/26070",
    "sg:postcode":"83026",
    "sg:province":"Bayern",
    "wof:name":"Hotel Theresia",
    "wof:placetype":"venue"
},
  "geometry": {"coordinates":[12.1192550659,47.838142395],"type":"Point"}
}