{
  "type": "Feature",
  "properties": {
    "iso:country":"DE",
    "sg:address":"Breslauer Str. 34",
    "sg:city":"B\u00fcchenbach",
    "sg:phone":"+49 9171/2096",
    "sg:postcode":"91186",
    "sg:province":"Bayern",
    "wof:name":"Psr - Versand",
    "wof:placetype":"venue"
},
  "geometry": {"coordinates":[11.071408,49.272209],"type":"Point"}
}