{
  "type": "Feature",
  "properties": {
    "iso:country":"DE",
    "sg:address":"Auhofstr. 11a",
    "sg:city":"Aschaffenburg",
    "sg:phone":"+49 4960/2134730",
    "sg:postcode":"63741",
    "sg:province":"Bayern",
    "wof:name":"Balthasar G\u00d6bel & Sohn Gmbh",
    "wof:placetype":"venue"
},
  "geometry": {"coordinates":[9.1512126923,49.9825897217],"type":"Point"}
}