{
  "type": "Feature",
  "properties": {
    "iso:country":"DE",
    "sg:address":"Weiseler Str. 41",
    "sg:city":"Butzbach",
    "sg:phone":"+49 6033/68965",
    "sg:postcode":"35510",
    "sg:province":"Hessen",
    "wof:name":"Bistro Bonjour",
    "wof:placetype":"venue"
},
  "geometry": {"coordinates":[8.66414,50.428982],"type":"Point"}
}