{
  "type": "Feature",
  "properties": {
    "iso:country":"DE",
    "sg:address":"Moislinger Allee 54",
    "sg:city":"L\u00fcbeck",
    "sg:postcode":"23558",
    "sg:province":"Schleswig-Holstein",
    "wof:name":"Motors Gmbh",
    "wof:placetype":"venue"
},
  "geometry": {"coordinates":[10.671052,53.858654],"type":"Point"}
}