{
  "type": "Feature",
  "properties": {
    "iso:country":"DE",
    "sg:address":"Bl\u00fccherstr. 70",
    "sg:city":"D\u00fcsseldorf",
    "sg:phone":"+49 211/483898",
    "sg:postcode":"40477",
    "sg:province":"Nordrhein-Westfalen",
    "wof:name":"G\u00f6rz",
    "wof:placetype":"venue"
},
  "geometry": {"coordinates":[6.7847399712,51.2371025085],"type":"Point"}
}