{
  "type": "Feature",
  "properties": {
    "iso:country":"DE",
    "sg:address":"R\u00f6merstr. 23-25",
    "sg:city":"B\u00fcrstadt",
    "sg:phone":"+49 4962/0698180",
    "sg:postcode":"68642",
    "sg:province":"Hessen",
    "wof:name":"Analytics Gmbh",
    "wof:placetype":"venue"
},
  "geometry": {"coordinates":[8.4480428696,49.6438865662],"type":"Point"}
}