{
  "type": "Feature",
  "properties": {
    "iso:country":"DE",
    "sg:address":"Heinzlm\u00fchl 1",
    "sg:city":"Nittenau",
    "sg:phone":"+49 9464/342",
    "sg:postcode":"93149",
    "sg:province":"Bayern",
    "wof:name":"Franz Weber",
    "wof:placetype":"venue"
},
  "geometry": {"coordinates":[12.328296,49.178089],"type":"Point"}
}