{
  "type": "Feature",
  "properties": {
    "iso:country":"DE",
    "sg:address":"Scharnhorststr. 2",
    "sg:city":"Augsburg",
    "sg:phone":"+49 821/791903",
    "sg:postcode":"86165",
    "sg:province":"Bayern",
    "wof:name":"M. Und D. Limmer",
    "wof:placetype":"venue"
},
  "geometry": {"coordinates":[10.924903,48.377579],"type":"Point"}
}