{
  "type": "Feature",
  "properties": {
    "iso:country":"DE",
    "sg:address":"Am Neutor 26",
    "sg:city":"Dinslaken",
    "sg:phone":"+49 2064/15858",
    "sg:postcode":"46535",
    "sg:province":"Nordrhein-Westfalen",
    "wof:name":"Roland Meissner Masseur",
    "wof:placetype":"venue"
},
  "geometry": {"coordinates":[6.741101,51.562847],"type":"Point"}
}