{
  "type": "Feature",
  "properties": {
    "iso:country":"DE",
    "sg:address":"Ernst-Schneller-Str. 4",
    "sg:city":"Jena",
    "sg:postcode":"07747",
    "sg:province":"Th\u00fcringen",
    "wof:name":"J. Jonas",
    "wof:placetype":"venue"
},
  "geometry": {"coordinates":[11.619927,50.883072],"type":"Point"}
}