{
  "type": "Feature",
  "properties": {
    "iso:country":"DE",
    "sg:address":"Hauptstr. 10b",
    "sg:city":"Pirna",
    "sg:phone":"+49 35020/70923",
    "sg:postcode":"01796",
    "sg:province":"Sachsen",
    "wof:name":"Pvb Abwasseranlagen- Beteiligungs Gmbh",
    "wof:placetype":"venue"
},
  "geometry": {"coordinates":[13.899882,50.957855],"type":"Point"}
}