{
  "type": "Feature",
  "properties": {
    "iso:country":"DE",
    "sg:address":"Am Binnenhafen 52",
    "sg:city":"Husum",
    "sg:postcode":"25813",
    "sg:province":"Schleswig-Holstein",
    "wof:name":"Claus Jacobsen E. K.",
    "wof:placetype":"venue"
},
  "geometry": {"coordinates":[9.0463495255,54.4740486145],"type":"Point"}
}