{
  "type": "Feature",
  "properties": {
    "iso:country":"DE",
    "sg:city":"Pommersfelden",
    "sg:phone":"+49 9548/8085",
    "sg:postcode":"96178",
    "sg:province":"Bayern",
    "wof:name":"H. K\u00fchlhorn",
    "wof:placetype":"venue"
},
  "geometry": {"coordinates":[10.823309,49.766048],"type":"Point"}
}