{
  "type": "Feature",
  "properties": {
    "iso:country":"DE",
    "sg:address":"Mainzer Str. 80",
    "sg:city":"Homburg",
    "sg:phone":"+49 6841/693900",
    "sg:postcode":"66424",
    "sg:province":"Saarland",
    "wof:name":"Mcs Cylinder Systems Gmbh",
    "wof:placetype":"venue"
},
  "geometry": {"coordinates":[7.334932,49.319653],"type":"Point"}
}