{
  "type": "Feature",
  "properties": {
    "iso:country":"DE",
    "sg:address":"Forstenburgstr. 38",
    "sg:city":"Bad W\u00fcnnenberg",
    "sg:phone":"+49 2953/7144",
    "sg:postcode":"33181",
    "sg:province":"Nordrhein-Westfalen",
    "wof:name":"Chese Leong",
    "wof:placetype":"venue"
},
  "geometry": {"coordinates":[8.7452497482,51.5098571777],"type":"Point"}
}