{
  "type": "Feature",
  "properties": {
    "iso:country":"DE",
    "sg:address":"Am Bahnhof 16",
    "sg:city":"Spenge",
    "sg:phone":"+49 5225/79897",
    "sg:postcode":"32139",
    "sg:province":"Nordrhein-Westfalen",
    "wof:name":"Gerhard Schade",
    "wof:placetype":"venue"
},
  "geometry": {"coordinates":[8.4861402512,52.1379508972],"type":"Point"}
}