{
  "type": "Feature",
  "properties": {
    "iso:country":"DE",
    "sg:address":"Markt-Schwabener-Str. 19",
    "sg:city":"Pliening",
    "sg:phone":"+49 8121/81500",
    "sg:postcode":"85652",
    "sg:province":"Bayern",
    "wof:name":"Lina Bogner Pension",
    "wof:placetype":"venue"
},
  "geometry": {"coordinates":[11.810802,48.197914],"type":"Point"}
}