{
  "type": "Feature",
  "properties": {
    "iso:country":"DE",
    "sg:address":"Bahnhofstr. 30-32 PF 1930",
    "sg:city":"Trier",
    "sg:phone":"+49 4965/11992",
    "sg:postcode":"54292",
    "sg:province":"Rheinland-Pfalz",
    "wof:name":"Euro Info Centre Rheinland-pfalz",
    "wof:placetype":"venue"
},
  "geometry": {"coordinates":[6.636521,49.757256],"type":"Point"}
}