{
  "type": "Feature",
  "properties": {
    "iso:country":"DE",
    "sg:address":"Sch\u00e4fergraben 5-9",
    "sg:city":"Delitzsch",
    "sg:phone":"+49 34202/25075",
    "sg:postcode":"04509",
    "sg:province":"Sachsen",
    "wof:name":"C. Bautz Und M. Nicklisch",
    "wof:placetype":"venue"
},
  "geometry": {"coordinates":[12.338494,51.525631],"type":"Point"}
}