{
  "type": "Feature",
  "properties": {
    "iso:country":"DE",
    "sg:address":"Palmaille 33",
    "sg:city":"Hamburg",
    "sg:phone":"+49 40/381080",
    "sg:postcode":"22767",
    "sg:province":"Hamburg",
    "wof:name":"Verwaltung Bsb Bulk Schiffsbeteiligungen Gmbh",
    "wof:placetype":"venue"
},
  "geometry": {"coordinates":[9.941772,53.546051],"type":"Point"}
}