{
  "type": "Feature",
  "properties": {
    "iso:country":"DE",
    "sg:address":"Koppelstr. 3",
    "sg:city":"Oldenburg",
    "sg:phone":"+49 441/25407",
    "sg:postcode":"26135",
    "sg:province":"Niedersachsen",
    "wof:name":"Wolfgang Jabbusch Patentanwalt",
    "wof:placetype":"venue"
},
  "geometry": {"coordinates":[8.2174921036,53.1352348328],"type":"Point"}
}