{
  "type": "Feature",
  "properties": {
    "iso:country":"DE",
    "sg:address":"Kotthook 8",
    "sg:city":"Nordhorn",
    "sg:phone":"+49 5921/88120",
    "sg:postcode":"48529",
    "sg:province":"Niedersachsen",
    "wof:name":"En-pro-tec Umwelt Und Technik Beratungs- Und Planungs Gmbh",
    "wof:placetype":"venue"
},
  "geometry": {"coordinates":[7.0697159767,52.4347305298],"type":"Point"}
}