{
  "type": "Feature",
  "properties": {
    "iso:country":"DE",
    "sg:address":"Hochwaldstr. 38",
    "sg:city":"Baldham",
    "sg:phone":"+49 8106/8483",
    "sg:postcode":"85598",
    "sg:province":"Bayern",
    "wof:name":"Ernst Seidenath",
    "wof:placetype":"venue"
},
  "geometry": {"coordinates":[11.7951364517,48.0944137573],"type":"Point"}
}