{
  "type": "Feature",
  "properties": {
    "iso:country":"DE",
    "sg:address":"Seestr. 8",
    "sg:city":"Sand",
    "sg:phone":"+49 9524/7888",
    "sg:postcode":"97522",
    "sg:province":"Bayern",
    "wof:name":"S. Zei\u00df",
    "wof:placetype":"venue"
},
  "geometry": {"coordinates":[10.5877180099,49.9926567078],"type":"Point"}
}