{
  "type": "Feature",
  "properties": {
    "iso:country":"DE",
    "sg:address":"Ortsstr.",
    "sg:city":"Altenbeuthen",
    "sg:phone":"+49 36737/31982",
    "sg:postcode":"07338",
    "sg:province":"Th\u00fcringen",
    "wof:name":"Kh Drognitzer H\u00f6he Agrar Gmbh & Co. Kg",
    "wof:placetype":"venue"
},
  "geometry": {"coordinates":[11.60507,50.594036],"type":"Point"}
}