{
  "type": "Feature",
  "properties": {
    "iso:country":"DE",
    "sg:address":"L\u00e4utenring 16",
    "sg:city":"Pfaffenhofen",
    "sg:phone":"+49 8134/6193",
    "sg:postcode":"85235",
    "sg:province":"Bayern",
    "wof:name":"Johann Tratz",
    "wof:placetype":"venue"
},
  "geometry": {"coordinates":[11.16543,48.294113],"type":"Point"}
}