{
  "type": "Feature",
  "properties": {
    "iso:country":"DE",
    "sg:address":"Rh\u00f6ndorfer Str. 8",
    "sg:city":"K\u00f6ln",
    "sg:phone":"+49 221/5465820",
    "sg:postcode":"50939",
    "sg:province":"Nordrhein-Westfalen",
    "wof:name":"Etc Gmbh. Qualit\u00e4ts-angebote F\u00fcr Dubai & Die Vae",
    "wof:placetype":"venue"
},
  "geometry": {"coordinates":[6.93533,50.916481],"type":"Point"}
}