{
  "type": "Feature",
  "properties": {
    "iso:country":"DE",
    "sg:address":"Seminarstr. 15",
    "sg:city":"Schneeberg",
    "sg:phone":"+49 3772/28990",
    "sg:postcode":"08289",
    "sg:province":"Sachsen",
    "wof:name":"Rutsatz Meiercord Und Partner",
    "wof:placetype":"venue"
},
  "geometry": {"coordinates":[12.6394672394,50.5967597961],"type":"Point"}
}