{
  "type": "Feature",
  "properties": {
    "iso:country":"DE",
    "sg:address":"Stahlgruberring 17",
    "sg:city":"M\u00fcnchen",
    "sg:phone":"+49 89/425211",
    "sg:postcode":"81829",
    "sg:province":"Bayern",
    "wof:name":"Garbrecht & Bischl Gmbh",
    "wof:placetype":"venue"
},
  "geometry": {"coordinates":[11.667239,48.132298],"type":"Point"}
}