{
  "type": "Feature",
  "properties": {
    "iso:country":"DE",
    "sg:address":"Grindelhof 37",
    "sg:city":"Hamburg",
    "sg:phone":"+49 40/440012",
    "sg:postcode":"20146",
    "sg:province":"Hamburg",
    "wof:name":"Wiens & Partner Gmbh Modellbau",
    "wof:placetype":"venue"
},
  "geometry": {"coordinates":[9.9830341339,53.5687217712],"type":"Point"}
}