{
  "type": "Feature",
  "properties": {
    "iso:country":"DE",
    "sg:address":"Am Sauerborn 7",
    "sg:city":"Echzell",
    "sg:phone":"+49 6008/918440",
    "sg:postcode":"61209",
    "sg:province":"Hessen",
    "wof:name":"Flamingo Restaurant",
    "wof:placetype":"venue"
},
  "geometry": {"coordinates":[8.892039299,50.390460968],"type":"Point"}
}