{
  "type": "Feature",
  "properties": {
    "iso:country":"DE",
    "sg:address":"Dorfstr. 40",
    "sg:city":"Ottendorf",
    "sg:phone":"+49 431/581613",
    "sg:postcode":"24107",
    "sg:province":"Schleswig-Holstein",
    "wof:name":"Mielimonka & Friedrichsen Inh. Claus Friedrichsen",
    "wof:placetype":"venue"
},
  "geometry": {"coordinates":[10.0470714569,54.3409805298],"type":"Point"}
}