{
  "type": "Feature",
  "properties": {
    "iso:country":"DE",
    "sg:address":"Gerichtsweg 17",
    "sg:city":"K\u00f6nigslutter",
    "sg:phone":"+49 5353/4057",
    "sg:postcode":"38154",
    "sg:province":"Niedersachsen",
    "wof:name":"Lottoteam Agentur K\u00f6niglutter",
    "wof:placetype":"venue"
},
  "geometry": {"coordinates":[10.8110265732,52.253780365],"type":"Point"}
}