{
  "type": "Feature",
  "properties": {
    "iso:country":"DE",
    "sg:address":"M\u00fchlschied 5",
    "sg:city":"Idar-Oberstein",
    "sg:phone":"+49 6784/42604",
    "sg:postcode":"55743",
    "sg:province":"Rheinland-Pfalz",
    "wof:name":"Evangelische B\u00fccherei Tiefenstein",
    "wof:placetype":"venue"
},
  "geometry": {"coordinates":[7.277107,49.742912],"type":"Point"}
}