{
  "type": "Feature",
  "properties": {
    "iso:country":"DE",
    "sg:address":"Eichenstr. 108",
    "sg:city":"M\u00f6nchengladbach",
    "sg:phone":"+49 2166/924428",
    "sg:postcode":"41238",
    "sg:province":"Nordrhein-Westfalen",
    "wof:name":"Winfried Lieven",
    "wof:placetype":"venue"
},
  "geometry": {"coordinates":[6.4658818245,51.1824684143],"type":"Point"}
}