{
  "type": "Feature",
  "properties": {
    "iso:country":"DE",
    "sg:address":"Peter-Kolb-Str. 4",
    "sg:city":"Marktredwitz",
    "sg:phone":"+49 9231/3013",
    "sg:postcode":"95615",
    "sg:province":"Bayern",
    "wof:name":"H. Heinrich Gmbh Werkzeuge",
    "wof:placetype":"venue"
},
  "geometry": {"coordinates":[12.090496,49.997238],"type":"Point"}
}