{
  "type": "Feature",
  "properties": {
    "iso:country":"DE",
    "sg:address":"Ro\u00dfmarktstr. 20",
    "sg:city":"Leipzig",
    "sg:phone":"+49 341/4801449",
    "sg:postcode":"04177",
    "sg:province":"Sachsen",
    "wof:name":"Bernd Modemann",
    "wof:placetype":"venue"
},
  "geometry": {"coordinates":[12.333027,51.338951],"type":"Point"}
}