{
  "type": "Feature",
  "properties": {
    "iso:country":"DE",
    "sg:address":"Lindenstr. 2",
    "sg:city":"Parchim",
    "sg:phone":"+49 3871/212363",
    "sg:postcode":"19370",
    "sg:province":"Mecklenburg-Vorpommern",
    "wof:name":"Bbm-b\u00fcromaschinen M\u00f6ller Gmbh",
    "wof:placetype":"venue"
},
  "geometry": {"coordinates":[11.8473300934,53.4279098511],"type":"Point"}
}