{
  "type": "Feature",
  "properties": {
    "iso:country":"DE",
    "sg:address":"B\u00f6ltestr. 2",
    "sg:city":"Erwitte",
    "sg:phone":"+49 4929/452221",
    "sg:postcode":"59597",
    "sg:province":"Nordrhein-Westfalen",
    "wof:name":"S\u00c4gewerk Wagener Gmbh",
    "wof:placetype":"venue"
},
  "geometry": {"coordinates":[8.3384599686,51.6119995117],"type":"Point"}
}