{
  "type": "Feature",
  "properties": {
    "iso:country":"DE",
    "sg:address":"Speckweg 63-65",
    "sg:city":"Mannheim",
    "sg:phone":"+49 621/741731",
    "sg:postcode":"68305",
    "sg:province":"Baden-W\u00fcrttemberg",
    "wof:name":"Botenservice Heiler Gmbh",
    "wof:placetype":"venue"
},
  "geometry": {"coordinates":[8.4901914597,49.5224914551],"type":"Point"}
}