{
  "type": "Feature",
  "properties": {
    "iso:country":"DE",
    "sg:address":"Seumestr. 2",
    "sg:city":"Magdeburg",
    "sg:phone":"+49 391/5937310",
    "sg:postcode":"39104",
    "sg:province":"Sachsen-Anhalt",
    "wof:name":"Minol Zentraltank Gmbh",
    "wof:placetype":"venue"
},
  "geometry": {"coordinates":[11.6283464432,52.1163673401],"type":"Point"}
}