{
  "type": "Feature",
  "properties": {
    "iso:country":"DE",
    "sg:address":"Am Bremkamp 44",
    "sg:city":"Bochum",
    "sg:postcode":"44795",
    "sg:province":"Nordrhein-Westfalen",
    "wof:name":"Treelogix Gmbh",
    "wof:placetype":"venue"
},
  "geometry": {"coordinates":[7.1771521568,51.4489402771],"type":"Point"}
}