{
  "type": "Feature",
  "properties": {
    "iso:country":"DE",
    "sg:address":"Universit\u00e4tsstr. 29",
    "sg:city":"Marburg",
    "sg:phone":"+49 6421/22031",
    "sg:postcode":"35037",
    "sg:province":"Hessen",
    "wof:name":"Ernst G. Heinz Rechtsanwalt Und Notar",
    "wof:placetype":"venue"
},
  "geometry": {"coordinates":[8.766295433,50.8068389893],"type":"Point"}
}