{
  "type": "Feature",
  "properties": {
    "iso:country":"DE",
    "sg:address":"Am Kirchberg 2",
    "sg:city":"Morgenr\u00f6the-Rautenkranz",
    "sg:postcode":"08262",
    "sg:province":"Sachsen",
    "wof:name":"Ev.-luth. Kirche Morgenr\u00f6the-rautenkran",
    "wof:placetype":"venue"
},
  "geometry": {"coordinates":[12.4922542572,50.4593772888],"type":"Point"}
}