{
  "type": "Feature",
  "properties": {
    "iso:country":"DE",
    "sg:address":"Muglitz 12b",
    "sg:city":"Parchtitz",
    "sg:phone":"+49 3838/313373",
    "sg:postcode":"18528",
    "sg:province":"Mecklenburg-Vorpommern",
    "wof:name":"Metall-u Zaunbau Muglitz Gmbh",
    "wof:placetype":"venue"
},
  "geometry": {"coordinates":[13.35287,54.431759],"type":"Point"}
}