{
  "type": "Feature",
  "properties": {
    "iso:country":"DE",
    "sg:address":"Nordring 14",
    "sg:city":"Waltrop",
    "sg:postcode":"45731",
    "sg:province":"Nordrhein-Westfalen",
    "wof:name":"Kultur-service Nina Rusch E. Kfr.",
    "wof:placetype":"venue"
},
  "geometry": {"coordinates":[7.386639,51.624123],"type":"Point"}
}