{
  "type": "Feature",
  "properties": {
    "iso:country":"DE",
    "sg:address":"Hochdahler Str. 83",
    "sg:city":"Hilden",
    "sg:phone":"+49 2103/44790",
    "sg:postcode":"40724",
    "sg:province":"Nordrhein-Westfalen",
    "wof:name":"F. Rauth",
    "wof:placetype":"venue"
},
  "geometry": {"coordinates":[6.93983,51.174149],"type":"Point"}
}