{
  "type": "Feature",
  "properties": {
    "iso:country":"DE",
    "sg:address":"Gladbacher Str. 49",
    "sg:city":"Elsdorf",
    "sg:phone":"+49 2274/7641",
    "sg:postcode":"50189",
    "sg:province":"Nordrhein-Westfalen",
    "wof:name":"Da Campione",
    "wof:placetype":"venue"
},
  "geometry": {"coordinates":[6.5672359467,50.9362335205],"type":"Point"}
}