{
  "type": "Feature",
  "properties": {
    "iso:country":"DE",
    "sg:address":"Auf der Wohrt 9",
    "sg:city":"Seelze",
    "sg:phone":"+49 5137/5284",
    "sg:postcode":"30916",
    "sg:province":"Niedersachsen",
    "wof:name":"Wald-kosmetik",
    "wof:placetype":"venue"
},
  "geometry": {"coordinates":[-81.9753570557,33.4790916443],"type":"Point"}
}