{
  "type": "Feature",
  "properties": {
    "iso:country":"DE",
    "sg:address":"Grottenau 11",
    "sg:city":"Bubesheim",
    "sg:phone":"+49 8221/4105",
    "sg:postcode":"89347",
    "sg:province":"Bayern",
    "wof:name":"Gerhard Seitz",
    "wof:placetype":"venue"
},
  "geometry": {"coordinates":[10.250959,48.431938],"type":"Point"}
}