{
  "type": "Feature",
  "properties": {
    "iso:country":"DE",
    "sg:address":"Am Schwesternhaus 7",
    "sg:city":"Bad Homburg",
    "sg:phone":"+49 6172/83465",
    "sg:postcode":"61350",
    "sg:province":"Hessen",
    "wof:name":"H. Hans Bornschier Architekt",
    "wof:placetype":"venue"
},
  "geometry": {"coordinates":[8.608141,50.23991],"type":"Point"}
}