{
  "type": "Feature",
  "properties": {
    "iso:country":"DE",
    "sg:address":"Rosenstr. 2",
    "sg:city":"Wannweil",
    "sg:phone":"+49 7121/57336",
    "sg:postcode":"72827",
    "sg:province":"Baden-W\u00fcrttemberg",
    "wof:name":"Roland Kern",
    "wof:placetype":"venue"
},
  "geometry": {"coordinates":[9.154549,48.510242],"type":"Point"}
}