{
  "type": "Feature",
  "properties": {
    "iso:country":"DE",
    "sg:address":"Werrastr. 18",
    "sg:city":"Bad Sooden-Allendorf",
    "sg:phone":"+49 5652/958850",
    "sg:postcode":"37242",
    "sg:province":"Hessen",
    "wof:name":"Arend Saunabad Gmbh",
    "wof:placetype":"venue"
},
  "geometry": {"coordinates":[9.978315,51.262405],"type":"Point"}
}