{
  "type": "Feature",
  "properties": {
    "iso:country":"DE",
    "sg:address":"Landgraf-Karl-Str. 21",
    "sg:city":"Kassel",
    "sg:phone":"+49 561/312762",
    "sg:postcode":"34131",
    "sg:province":"Hessen",
    "wof:name":"Mohammad Hamraz Krankengymnast",
    "wof:placetype":"venue"
},
  "geometry": {"coordinates":[9.441963,51.311604],"type":"Point"}
}