{
  "type": "Feature",
  "properties": {
    "iso:country":"DE",
    "sg:address":"Burgst\u00e4dter Str. 31",
    "sg:city":"Clau\u00dfnitz",
    "sg:phone":"+49 37202/2235",
    "sg:postcode":"09236",
    "sg:province":"Sachsen",
    "wof:name":"Joachim Neugebauer",
    "wof:placetype":"venue"
},
  "geometry": {"coordinates":[12.880884,50.935509],"type":"Point"}
}