{
  "type": "Feature",
  "properties": {
    "iso:country":"DE",
    "sg:address":"Otto-von-Guericke-Str. 80",
    "sg:city":"Magdeburg",
    "sg:phone":"+49 391/5431326",
    "sg:postcode":"39104",
    "sg:province":"Sachsen-Anhalt",
    "wof:name":"Dr. Med. Michael Uchtl\u00e4nder",
    "wof:placetype":"venue"
},
  "geometry": {"coordinates":[11.629939,52.12706],"type":"Point"}
}