{
  "type": "Feature",
  "properties": {
    "iso:country":"DE",
    "sg:address":"bahnhofstr. 40",
    "sg:city":"Bad K\u00f6stritz",
    "sg:phone":"+49 36605/625",
    "sg:postcode":"07586",
    "sg:province":"Th\u00fcringen",
    "wof:name":"Raiffeisenbank Und Handelsgenossen-, Schaft Gera E.g.",
    "wof:placetype":"venue"
},
  "geometry": {"coordinates":[12.026681,50.932285],"type":"Point"}
}