{
  "type": "Feature",
  "properties": {
    "iso:country":"DE",
    "sg:address":"Beim Knevelshof 57",
    "sg:city":"Duisburg",
    "sg:phone":"+49 203/702988",
    "sg:postcode":"47249",
    "sg:province":"Nordrhein-Westfalen",
    "wof:name":"Ev. Pfarramt Ii Wanheim",
    "wof:placetype":"venue"
},
  "geometry": {"coordinates":[6.7498760223,51.3817214966],"type":"Point"}
}