{
  "type": "Feature",
  "properties": {
    "iso:country":"DE",
    "sg:address":"Tramplerstr. 11",
    "sg:city":"Lahr",
    "sg:phone":"+49 7821/24860",
    "sg:postcode":"77933",
    "sg:province":"Baden-W\u00fcrttemberg",
    "wof:name":"H. Joos",
    "wof:placetype":"venue"
},
  "geometry": {"coordinates":[7.8648920059,48.3350448608],"type":"Point"}
}