{
  "type": "Feature",
  "properties": {
    "iso:country":"DE",
    "sg:address":"Gewerbestr. 2",
    "sg:city":"Heldenstein",
    "sg:phone":"+49 8636/857",
    "sg:postcode":"84431",
    "sg:province":"Bayern",
    "wof:name":"Richard Streller Kg",
    "wof:placetype":"venue"
},
  "geometry": {"coordinates":[12.363469,48.240826],"type":"Point"}
}