{
  "type": "Feature",
  "properties": {
    "iso:country":"DE",
    "sg:address":"Luisenstr. 1a",
    "sg:city":"Offenburg",
    "sg:phone":"+49 781/31048",
    "sg:postcode":"77654",
    "sg:province":"Baden-W\u00fcrttemberg",
    "wof:name":"Spohrer Und Drevillon Rechtsanw\u00e4lte",
    "wof:placetype":"venue"
},
  "geometry": {"coordinates":[7.9471888542,48.4726982117],"type":"Point"}
}