{
  "type": "Feature",
  "properties": {
    "iso:country":"DE",
    "sg:address":"Wilhelmstr. 19",
    "sg:city":"Metzingen",
    "sg:phone":"+49 7123/963901",
    "sg:postcode":"72555",
    "sg:province":"Baden-W\u00fcrttemberg",
    "wof:name":"Eb. Sautter B\u00e4ckerei",
    "wof:placetype":"venue"
},
  "geometry": {"coordinates":[9.28193,48.538303],"type":"Point"}
}