{
  "type": "Feature",
  "properties": {
    "iso:country":"DE",
    "sg:address":"Lerchenweg 16",
    "sg:city":"Gomaringen",
    "sg:phone":"+49 7072/7468",
    "sg:postcode":"72810",
    "sg:province":"Baden-W\u00fcrttemberg",
    "wof:name":"Walter Pflumm",
    "wof:placetype":"venue"
},
  "geometry": {"coordinates":[9.1071357727,48.4579582214],"type":"Point"}
}