{
  "type": "Feature",
  "properties": {
    "iso:country":"DE",
    "sg:address":"Otto-Keiner-Str. 57",
    "sg:city":"Benshausen",
    "sg:phone":"+49 36843/7460",
    "sg:postcode":"98554",
    "sg:province":"Th\u00fcringen",
    "wof:name":"Herzig & Marschall & Co. Gmbh",
    "wof:placetype":"venue"
},
  "geometry": {"coordinates":[10.600726,50.652039],"type":"Point"}
}