{
  "type": "Feature",
  "properties": {
    "iso:country":"DE",
    "sg:address":"Rothenfelsstr. 20",
    "sg:city":"Immenstadt",
    "sg:phone":"+49 8323/6258",
    "sg:postcode":"87509",
    "sg:province":"Bayern",
    "wof:name":"Union-filmtheater Kino 1-2",
    "wof:placetype":"venue"
},
  "geometry": {"coordinates":[10.214509964,47.5608673096],"type":"Point"}
}