{
  "type": "Feature",
  "properties": {
    "iso:country":"DE",
    "sg:address":"Gutenbergstr. 13",
    "sg:city":"Marburg",
    "sg:phone":"+49 6421/23523",
    "sg:postcode":"35037",
    "sg:province":"Hessen",
    "wof:name":"Scharf Optik H\u00f6rger\u00e4te Contactlinsen",
    "wof:placetype":"venue"
},
  "geometry": {"coordinates":[8.768860817,50.805847168],"type":"Point"}
}