{
  "type": "Feature",
  "properties": {
    "iso:country":"DE",
    "sg:address":"Virchowstr. 7",
    "sg:city":"Potsdam",
    "sg:postcode":"14482",
    "sg:province":"Brandenburg",
    "wof:name":"Johannes Wilmes Ag",
    "wof:placetype":"venue"
},
  "geometry": {"coordinates":[13.120276,52.397961],"type":"Point"}
}