{
  "type": "Feature",
  "properties": {
    "iso:country":"DE",
    "sg:address":"Charlottenstr. 25",
    "sg:city":"Potsdam",
    "sg:phone":"+49 331/2804326",
    "sg:postcode":"14467",
    "sg:province":"Brandenburg",
    "wof:name":"Foto-video Schulzendorff",
    "wof:placetype":"venue"
},
  "geometry": {"coordinates":[13.054526329,52.3991889954],"type":"Point"}
}