{
  "type": "Feature",
  "properties": {
    "iso:country":"DE",
    "sg:address":"Wendalinusstr. 62",
    "sg:city":"Lebach",
    "sg:phone":"+49 6887/2114",
    "sg:postcode":"66822",
    "sg:province":"Saarland",
    "wof:name":"A. Hassel",
    "wof:placetype":"venue"
},
  "geometry": {"coordinates":[6.9023752213,49.4530067444],"type":"Point"}
}