{
  "type": "Feature",
  "properties": {
    "iso:country":"DE",
    "sg:address":"Marienstr. 53",
    "sg:city":"Hof",
    "sg:phone":"+49 9281/2523",
    "sg:postcode":"95028",
    "sg:province":"Bayern",
    "wof:name":"Richard Hess Inh. Hans-dieter Triebner",
    "wof:placetype":"venue"
},
  "geometry": {"coordinates":[11.913254,50.315643],"type":"Point"}
}