{
  "type": "Feature",
  "properties": {
    "iso:country":"DE",
    "sg:address":"Burgstr. 60",
    "sg:city":"Mitterfels",
    "sg:phone":"+49 9961/318",
    "sg:postcode":"94360",
    "sg:province":"Bayern",
    "wof:name":"J. Pichl",
    "wof:placetype":"venue"
},
  "geometry": {"coordinates":[12.6802396774,48.9744873047],"type":"Point"}
}