{
  "type": "Feature",
  "properties": {
    "iso:country":"DE",
    "sg:address":"Richard-Strauss-Weg 2",
    "sg:city":"Dachau",
    "sg:postcode":"85221",
    "sg:province":"Bayern",
    "wof:name":"P. Asam",
    "wof:placetype":"venue"
},
  "geometry": {"coordinates":[11.42578,48.260956],"type":"Point"}
}