{
  "type": "Feature",
  "properties": {
    "iso:country":"DE",
    "sg:address":"Talaue 1 A",
    "sg:city":"Dorsten",
    "sg:phone":"+49 2369/200655",
    "sg:postcode":"46286",
    "sg:province":"Nordrhein-Westfalen",
    "wof:name":"Restaurant Pizzeria",
    "wof:placetype":"venue"
},
  "geometry": {"coordinates":[7.039208889,51.7326202393],"type":"Point"}
}