{
  "type": "Feature",
  "properties": {
    "iso:country":"DE",
    "sg:address":"Richelstr. 24",
    "sg:city":"M\u00fcnchen",
    "sg:postcode":"80634",
    "sg:province":"Bayern",
    "wof:name":"Leopold Sch\u00f6n Kg - Gmbh & Co.",
    "wof:placetype":"venue"
},
  "geometry": {"coordinates":[11.5307855606,48.1456871033],"type":"Point"}
}