{
  "type": "Feature",
  "properties": {
    "iso:country":"DE",
    "sg:address":"St.-Martin-Str. 13",
    "sg:city":"Ichenhausen",
    "sg:phone":"+49 8223/719",
    "sg:postcode":"89335",
    "sg:province":"Bayern",
    "wof:name":"Bernhard Siegner",
    "wof:placetype":"venue"
},
  "geometry": {"coordinates":[10.324752,48.392136],"type":"Point"}
}