{
  "type": "Feature",
  "properties": {
    "iso:country":"DE",
    "sg:address":"Schillerstr. 56a",
    "sg:city":"Zeuthen",
    "sg:phone":"+49 33762/71088",
    "sg:postcode":"15738",
    "sg:province":"Brandenburg",
    "wof:name":"Issel & Rother",
    "wof:placetype":"venue"
},
  "geometry": {"coordinates":[13.622764,52.361622],"type":"Point"}
}