{
  "type": "Feature",
  "properties": {
    "iso:country":"DE",
    "sg:address":"Leipziger Platz 12",
    "sg:city":"Erfurt",
    "sg:phone":"+49 361/29697",
    "sg:postcode":"99085",
    "sg:province":"Th\u00fcringen",
    "wof:name":"Zum Goldenen Anker",
    "wof:placetype":"venue"
},
  "geometry": {"coordinates":[11.0417327881,50.9808311462],"type":"Point"}
}