{
  "type": "Feature",
  "properties": {
    "iso:country":"DE",
    "sg:address":"Ergenzinger Str.",
    "sg:city":"Rottenburg",
    "sg:postcode":"72108",
    "sg:province":"Baden-W\u00fcrttemberg",
    "wof:name":"Mehrzweckhalle",
    "wof:placetype":"venue"
},
  "geometry": {"coordinates":[8.780202,48.503918],"type":"Point"}
}