{
  "type": "Feature",
  "properties": {
    "iso:country":"DE",
    "sg:address":"Merscheider Str. 160",
    "sg:city":"Solingen",
    "sg:phone":"+49 212/331101",
    "sg:postcode":"42699",
    "sg:province":"Nordrhein-Westfalen",
    "wof:name":"Hartmut Dettbarn",
    "wof:placetype":"venue"
},
  "geometry": {"coordinates":[7.026312,51.1656],"type":"Point"}
}