{
  "type": "Feature",
  "properties": {
    "iso:country":"DE",
    "sg:address":"waldstrasse 17",
    "sg:city":"leipzig",
    "sg:phone":"+49 341/1616161",
    "sg:postcode":"04103",
    "sg:province":"Sachsen",
    "wof:name":"Bike-department",
    "wof:placetype":"venue"
},
  "geometry": {"coordinates":[12.357948,51.343887],"type":"Point"}
}