{
  "type": "Feature",
  "properties": {
    "iso:country":"DE",
    "sg:address":"Waldheimer Str. 75",
    "sg:city":"D\u00f6beln",
    "sg:postcode":"04720",
    "sg:province":"Sachsen",
    "wof:name":"Osts\u00e4chsische Br\u00fccken- Und Ingenieur-tiefbau Gmbh",
    "wof:placetype":"venue"
},
  "geometry": {"coordinates":[13.0984621048,51.1166229248],"type":"Point"}
}