{
  "type": "Feature",
  "properties": {
    "iso:country":"DE",
    "sg:address":"Pfarrer-Henninger-Weg 11",
    "sg:city":"Eisingen",
    "sg:phone":"+49 9306/230",
    "sg:postcode":"97249",
    "sg:province":"Bayern",
    "wof:name":"Katholisches Pfarramt St. Nikolaus",
    "wof:placetype":"venue"
},
  "geometry": {"coordinates":[9.828119278,49.7588768005],"type":"Point"}
}