{
  "type": "Feature",
  "properties": {
    "iso:country":"DE",
    "sg:address":"Max-Keith-Str. 34",
    "sg:city":"Essen",
    "sg:phone":"+49 201/25728",
    "sg:postcode":"45136",
    "sg:province":"Nordrhein-Westfalen",
    "wof:name":"Quante Ag",
    "wof:placetype":"venue"
},
  "geometry": {"coordinates":[7.0272951126,51.4347801208],"type":"Point"}
}