{
  "type": "Feature",
  "properties": {
    "iso:country":"DE",
    "sg:address":"Hoher Rain 26",
    "sg:city":"Berg",
    "sg:phone":"+49 751/43195",
    "sg:postcode":"88276",
    "sg:province":"Baden-W\u00fcrttemberg",
    "wof:name":"Baum Ger\u00fcstbau Gmbh",
    "wof:placetype":"venue"
},
  "geometry": {"coordinates":[9.5954341888,47.8145332336],"type":"Point"}
}