{
  "type": "Feature",
  "properties": {
    "iso:country":"DE",
    "sg:address":"Altwettener Weg 4",
    "sg:city":"Kevelaer",
    "sg:phone":"+49 2832/2769",
    "sg:postcode":"47625",
    "sg:province":"Nordrhein-Westfalen",
    "wof:name":"St.josef-haus",
    "wof:placetype":"venue"
},
  "geometry": {"coordinates":[6.295902,51.570824],"type":"Point"}
}