{
  "type": "Feature",
  "properties": {
    "iso:country":"DE",
    "sg:address":"Burloer Diek 67",
    "sg:city":"Rhede",
    "sg:phone":"+49 2872/2425",
    "sg:postcode":"46414",
    "sg:province":"Nordrhein-Westfalen",
    "wof:name":"K\u00f6bes Am Diek",
    "wof:placetype":"venue"
},
  "geometry": {"coordinates":[6.7432599068,51.8893890381],"type":"Point"}
}