{
  "type": "Feature",
  "properties": {
    "iso:country":"DE",
    "sg:address":"M\u00fchlenstr. 44",
    "sg:city":"Malsfeld",
    "sg:postcode":"34323",
    "sg:province":"Hessen",
    "wof:name":"H. A. T. - Back Drive In Gmbh",
    "wof:placetype":"venue"
},
  "geometry": {"coordinates":[9.54032,51.080746],"type":"Point"}
}