{
  "type": "Feature",
  "properties": {
    "iso:country":"DE",
    "sg:address":"Rothenburgstr. 17",
    "sg:city":"Nordhausen",
    "sg:postcode":"99734",
    "sg:province":"Th\u00fcringen",
    "wof:name":"Navus Gmbh",
    "wof:placetype":"venue"
},
  "geometry": {"coordinates":[10.805972,51.492237],"type":"Point"}
}