{
  "type": "Feature",
  "properties": {
    "iso:country":"DE",
    "sg:address":"Industriestr. 4",
    "sg:city":"Dessau",
    "sg:phone":"+49 340/517756",
    "sg:postcode":"06847",
    "sg:province":"Sachsen-Anhalt",
    "wof:name":"Zum Alten Plattenwerk",
    "wof:placetype":"venue"
},
  "geometry": {"coordinates":[12.2287721634,51.818145752],"type":"Point"}
}