{
  "type": "Feature",
  "properties": {
    "iso:country":"DE",
    "sg:address":"Auf der Heide 27a",
    "sg:city":"Muelheim",
    "sg:phone":"+49 177",
    "sg:postcode":"45473",
    "sg:province":"Nordrhein-Westfalen",
    "wof:name":"I-q Schacht & Partner Qualitaetskonstruktion",
    "wof:placetype":"venue"
},
  "geometry": {"coordinates":[6.8943390846,51.4509086609],"type":"Point"}
}