{
  "type": "Feature",
  "properties": {
    "iso:country":"DE",
    "sg:address":"Hann\u00f6versche Str. 22",
    "sg:city":"Dortmund",
    "sg:phone":"+49 231/5622090",
    "sg:postcode":"44143",
    "sg:province":"Nordrhein-Westfalen",
    "wof:name":"Plansystem Gmbh",
    "wof:placetype":"venue"
},
  "geometry": {"coordinates":[7.4985637665,51.5195999146],"type":"Point"}
}