{
  "type": "Feature",
  "properties": {
    "iso:country":"DE",
    "sg:address":"Bodenstedter Weg 16",
    "sg:city":"Lengede",
    "sg:phone":"+49 5344/7660",
    "sg:postcode":"38268",
    "sg:province":"Niedersachsen",
    "wof:name":"Karl-friedrich Scheinh\u00fctte",
    "wof:placetype":"venue"
},
  "geometry": {"coordinates":[10.308578,52.205776],"type":"Point"}
}