{
  "type": "Feature",
  "properties": {
    "iso:country":"DE",
    "sg:address":"H\u00e4fnersberg 6",
    "sg:city":"H\u00f6chstadt",
    "sg:phone":"+49 9193/3520",
    "sg:postcode":"91315",
    "sg:province":"Bayern",
    "wof:name":"Konrad Gehr",
    "wof:placetype":"venue"
},
  "geometry": {"coordinates":[10.805124,49.706333],"type":"Point"}
}