{
  "type": "Feature",
  "properties": {
    "iso:country":"DE",
    "sg:address":"R\u00f6hrkastener Str. 11",
    "sg:city":"Obernkirchen",
    "sg:phone":"+49 5724/7761",
    "sg:postcode":"31683",
    "sg:province":"Niedersachsen",
    "wof:name":"Heinrich Struckmeier",
    "wof:placetype":"venue"
},
  "geometry": {"coordinates":[9.11979,52.256592],"type":"Point"}
}