{
  "type": "Feature",
  "properties": {
    "iso:country":"DE",
    "sg:address":"Stuttgarter Str. 17",
    "sg:city":"Herrenberg",
    "sg:phone":"+49 7032/28464",
    "sg:postcode":"71083",
    "sg:province":"Baden-W\u00fcrttemberg",
    "wof:name":"Imbi\u00df Altstadt",
    "wof:placetype":"venue"
},
  "geometry": {"coordinates":[8.8704414368,48.5974731445],"type":"Point"}
}