{
  "type": "Feature",
  "properties": {
    "iso:country":"DE",
    "sg:address":"Friedrich-Ebert-Str. 16",
    "sg:city":"Ottobrunn",
    "sg:phone":"+49 89/608700",
    "sg:postcode":"85521",
    "sg:province":"Bayern",
    "wof:name":"Edtz Hard- Und Software Gmbh Hard- Und Software Gmbh",
    "wof:placetype":"venue"
},
  "geometry": {"coordinates":[11.654899,48.074623],"type":"Point"}
}