{
  "type": "Feature",
  "properties": {
    "iso:country":"DE",
    "sg:address":"Kilianstr. 10",
    "sg:city":"M\u00fchltal",
    "sg:phone":"+49 6151/14229",
    "sg:postcode":"64367",
    "sg:province":"Hessen",
    "wof:name":"Georg Schick",
    "wof:placetype":"venue"
},
  "geometry": {"coordinates":[8.70317,49.828342],"type":"Point"}
}