{
  "type": "Feature",
  "properties": {
    "iso:country":"DE",
    "sg:address":"Frankenstr. 38",
    "sg:city":"Grevenbroich",
    "sg:phone":"+49 2181/82376",
    "sg:postcode":"41517",
    "sg:province":"Nordrhein-Westfalen",
    "wof:name":"Esser-giefer",
    "wof:placetype":"venue"
},
  "geometry": {"coordinates":[6.577759,51.044811],"type":"Point"}
}