{
  "type": "Feature",
  "properties": {
    "iso:country":"DE",
    "sg:address":"Weidinger Str. 7",
    "sg:city":"Sch\u00f6nsee",
    "sg:phone":"+49 9674/235",
    "sg:postcode":"92539",
    "sg:province":"Bayern",
    "wof:name":"Dr. Hans Pangerl Tierarzt",
    "wof:placetype":"venue"
},
  "geometry": {"coordinates":[12.5498533249,49.5078735352],"type":"Point"}
}