{
  "type": "Feature",
  "properties": {
    "iso:country":"DE",
    "sg:address":"Hardgraben 60",
    "sg:city":"Langenzenn",
    "sg:phone":"+49 9101/6505",
    "sg:postcode":"90579",
    "sg:province":"Bayern",
    "wof:name":"Klaus Gr\u00f6gel",
    "wof:placetype":"venue"
},
  "geometry": {"coordinates":[10.78312,49.503601],"type":"Point"}
}