{
  "type": "Feature",
  "properties": {
    "iso:country":"DE",
    "sg:address":"Ernst-Keil-Str. 2",
    "sg:city":"Leipzig",
    "sg:phone":"+49 4934/144860",
    "sg:postcode":"04179",
    "sg:province":"Sachsen",
    "wof:name":"Balcke Gmbh",
    "wof:placetype":"venue"
},
  "geometry": {"coordinates":[12.302432,51.33963],"type":"Point"}
}