{
  "type": "Feature",
  "properties": {
    "iso:country":"DE",
    "sg:address":"Fr\u00fchlingsstr. 1",
    "sg:city":"Glatten",
    "sg:phone":"+49 7443/5257",
    "sg:postcode":"72293",
    "sg:province":"Baden-W\u00fcrttemberg",
    "wof:name":"Buckelschenke",
    "wof:placetype":"venue"
},
  "geometry": {"coordinates":[8.5071430206,48.4418983459],"type":"Point"}
}