{
  "type": "Feature",
  "properties": {
    "iso:country":"DE",
    "sg:address":"Pamirring 2",
    "sg:city":"Damp",
    "sg:phone":"+49 4352/5470",
    "sg:postcode":"24351",
    "sg:province":"Schleswig-Holstein",
    "wof:name":"Albrecht & Lemke Yachthandel Und Service Gmbh",
    "wof:placetype":"venue"
},
  "geometry": {"coordinates":[10.01569,54.584259],"type":"Point"}
}