{
  "type": "Feature",
  "properties": {
    "iso:country":"DE",
    "sg:address":"Hemmingstedter Weg 28",
    "sg:city":"Berlin",
    "sg:postcode":"13503",
    "sg:province":"Berlin",
    "wof:name":"Harald Feddersen Tiefk\u00fchlspezialit\u00e4ten Gmbh",
    "wof:placetype":"venue"
},
  "geometry": {"coordinates":[13.225268364,52.6059379578],"type":"Point"}
}