{
  "type": "Feature",
  "properties": {
    "iso:country":"DE",
    "sg:address":"Gewerbestr 16",
    "sg:city":"S\u00fcdbrookmerland",
    "sg:phone":"+49 4942/99250",
    "sg:postcode":"26624",
    "sg:province":"Niedersachsen",
    "wof:name":"Groen & Janssen Gmbh -kunststoffvertrieb-",
    "wof:placetype":"venue"
},
  "geometry": {"coordinates":[7.307752,53.46925],"type":"Point"}
}