{
  "type": "Feature",
  "properties": {
    "iso:country":"DE",
    "sg:address":"Stuibenweg 7",
    "sg:city":"Kempten",
    "sg:postcode":"87435",
    "sg:province":"Bayern",
    "wof:name":"Domainfactory Gmbh",
    "wof:placetype":"venue"
},
  "geometry": {"coordinates":[10.309962,47.721394],"type":"Point"}
}