{
  "type": "Feature",
  "properties": {
    "iso:country":"DE",
    "sg:address":"Hauptstr. 40-44",
    "sg:city":"Silberstedt",
    "sg:phone":"+49 4626/434",
    "sg:postcode":"24887",
    "sg:province":"Schleswig-Holstein",
    "wof:name":"Rathje-bau Gmbh",
    "wof:placetype":"venue"
},
  "geometry": {"coordinates":[9.375693,54.518677],"type":"Point"}
}