{
  "type": "Feature",
  "properties": {
    "iso:country":"DE",
    "sg:address":"breitestr.82",
    "sg:city":"frechen",
    "sg:postcode":"50226",
    "sg:province":"Nordrhein-Westfalen",
    "wof:name":"Die Geilsten Livecams Im Netz Boys Gays Girls",
    "wof:placetype":"venue"
},
  "geometry": {"coordinates":[6.812751,50.906609],"type":"Point"}
}