{
  "type": "Feature",
  "properties": {
    "iso:country":"DE",
    "sg:address":"Ammerl\u00e4nder Heerstr. 67",
    "sg:city":"Oldenburg",
    "sg:postcode":"26129",
    "sg:province":"Niedersachsen",
    "wof:name":"Institut F\u00fcr Verwaltungsforschung Und",
    "wof:placetype":"venue"
},
  "geometry": {"coordinates":[8.1850786209,53.146987915],"type":"Point"}
}