{
  "type": "Feature",
  "properties": {
    "iso:country":"DE",
    "sg:address":"Herzog-Johann-Albrecht-Str. 39",
    "sg:city":"Braunlage",
    "sg:phone":"+49 5520/1061",
    "sg:postcode":"38700",
    "sg:province":"Niedersachsen",
    "wof:name":"Pension Sohnrey",
    "wof:placetype":"venue"
},
  "geometry": {"coordinates":[10.6081552505,51.7320671082],"type":"Point"}
}