{
  "type": "Feature",
  "properties": {
    "iso:country":"DE",
    "sg:address":"Gerichtsstr. 15",
    "sg:city":"Altena",
    "sg:phone":"+49 2352/25333",
    "sg:postcode":"58762",
    "sg:province":"Nordrhein-Westfalen",
    "wof:name":"Hotel Garni Gudrun Dewor",
    "wof:placetype":"venue"
},
  "geometry": {"coordinates":[7.6704349518,51.3000984192],"type":"Point"}
}