{
  "type": "Feature",
  "properties": {
    "iso:country":"DE",
    "sg:address":"Albert-Mayer-Str. 7",
    "sg:city":"Bruckm\u00fchl",
    "sg:phone":"+49 8062/5021",
    "sg:postcode":"83052",
    "sg:province":"Bayern",
    "wof:name":"Peter Schulte Gmbh",
    "wof:placetype":"venue"
},
  "geometry": {"coordinates":[11.930702,47.882263],"type":"Point"}
}