{
  "type": "Feature",
  "properties": {
    "iso:country":"DE",
    "sg:address":"Friedrich-Ebert-Str. 31-33",
    "sg:city":"D\u00fcsseldorf",
    "sg:phone":"+49 211/175105",
    "sg:postcode":"40210",
    "sg:province":"Nordrhein-Westfalen",
    "wof:name":"West House Projekt- Entwicklungs- Und",
    "wof:placetype":"venue"
},
  "geometry": {"coordinates":[6.7889947891,51.2216720581],"type":"Point"}
}