{
  "type": "Feature",
  "properties": {
    "iso:country":"DE",
    "sg:address":"Heisterbacher Str. 134",
    "sg:city":"K\u00f6nigswinter",
    "sg:phone":"+49 2223/22188",
    "sg:postcode":"53639",
    "sg:province":"Nordrhein-Westfalen",
    "wof:name":"Uwe P\u00fctz",
    "wof:placetype":"venue"
},
  "geometry": {"coordinates":[7.1892747879,50.6983947754],"type":"Point"}
}