{
  "type": "Feature",
  "properties": {
    "iso:country":"DE",
    "sg:address":"Am Markt 7",
    "sg:city":"Hameln",
    "sg:phone":"+49 5151/23012",
    "sg:postcode":"31785",
    "sg:province":"Niedersachsen",
    "wof:name":"Koch Seifert Und Reuter-ahrend Rechtsanw\u00e4lte",
    "wof:placetype":"venue"
},
  "geometry": {"coordinates":[9.3563432693,52.104927063],"type":"Point"}
}