{
  "type": "Feature",
  "properties": {
    "iso:country":"DE",
    "sg:address":"Dorotheenstr. 21",
    "sg:city":"Bad Homburg",
    "sg:phone":"+49 6172/690150",
    "sg:postcode":"61348",
    "sg:province":"Hessen",
    "wof:name":"Antik-m\u00f6bel-restaurierung Gmbh",
    "wof:placetype":"venue"
},
  "geometry": {"coordinates":[8.6146116257,50.2261047363],"type":"Point"}
}