{
  "type": "Feature",
  "properties": {
    "iso:country":"DE",
    "sg:address":"K\u00f6nigstr. 2",
    "sg:city":"Neuss",
    "sg:postcode":"41460",
    "sg:province":"Nordrhein-Westfalen",
    "wof:name":"Orthop\u00e4die-technik Scharf-frey E. K.",
    "wof:placetype":"venue"
},
  "geometry": {"coordinates":[6.6860327721,51.2020835876],"type":"Point"}
}