{
  "type": "Feature",
  "properties": {
    "iso:country":"DE",
    "sg:address":"Oberaustr. 24a",
    "sg:city":"Wang",
    "sg:phone":"+49 8761/5706",
    "sg:postcode":"85368",
    "sg:province":"Bayern",
    "wof:name":"Josef Obermaier",
    "wof:placetype":"venue"
},
  "geometry": {"coordinates":[11.9599437714,48.4881134033],"type":"Point"}
}