{
  "type": "Feature",
  "properties": {
    "iso:country":"DE",
    "sg:address":"Beim M\u00fchltor 1",
    "sg:city":"Kraichtal",
    "sg:postcode":"76703",
    "sg:province":"Baden-W\u00fcrttemberg",
    "wof:name":"Kraichtaler Handelsgesellsch. F\u00fcr Cerealien Und Rohstoffe",
    "wof:placetype":"venue"
},
  "geometry": {"coordinates":[8.717332,49.129269],"type":"Point"}
}