{
  "type": "Feature",
  "properties": {
    "iso:country":"DE",
    "sg:address":"Appenborner Weg 5",
    "sg:city":"Rabenau",
    "sg:phone":"+49 6407/6495",
    "sg:postcode":"35466",
    "sg:province":"Hessen",
    "wof:name":"Landw. Bezugs- Und Absatzgenossenschaft",
    "wof:placetype":"venue"
},
  "geometry": {"coordinates":[8.892586,50.661312],"type":"Point"}
}