{
  "type": "Feature",
  "properties": {
    "iso:country":"DE",
    "sg:address":"Am Markt",
    "sg:city":"Westhofen",
    "sg:phone":"+49 6244/318",
    "sg:postcode":"67593",
    "sg:province":"Rheinland-Pfalz",
    "wof:name":"Weinstube-fremdenzimmer Zur Krone",
    "wof:placetype":"venue"
},
  "geometry": {"coordinates":[8.2466249466,49.7040214539],"type":"Point"}
}