{
  "type": "Feature",
  "properties": {
    "iso:country":"DE",
    "sg:address":"Poststr. 35",
    "sg:city":"Pollhagen",
    "sg:phone":"+49 5721/2731",
    "sg:postcode":"31718",
    "sg:province":"Niedersachsen",
    "wof:name":"Depo Spedition U. Handel Dirk Dettmer",
    "wof:placetype":"venue"
},
  "geometry": {"coordinates":[9.184636,52.387012],"type":"Point"}
}