{
  "type": "Feature",
  "properties": {
    "iso:country":"DE",
    "sg:address":"Spiegelgasse 6",
    "sg:city":"Thurnau",
    "sg:phone":"+49 9228/1618",
    "sg:postcode":"95349",
    "sg:province":"Bayern",
    "wof:name":"Georg Richter Heilpraktiker",
    "wof:placetype":"venue"
},
  "geometry": {"coordinates":[11.3944473267,50.0257377625],"type":"Point"}
}