{
  "type": "Feature",
  "properties": {
    "iso:country":"DE",
    "sg:address":"Petristr. 11",
    "sg:city":"Heilbad Heiligenstadt",
    "sg:phone":"+49 3606/614241",
    "sg:postcode":"37308",
    "sg:province":"Th\u00fcringen",
    "wof:name":"Funke Und Simon Rechtsanw\u00e4lte",
    "wof:placetype":"venue"
},
  "geometry": {"coordinates":[10.1342563629,51.3752326965],"type":"Point"}
}