{
  "type": "Feature",
  "properties": {
    "iso:country":"DE",
    "sg:address":"M\u00fchlenstr. 49",
    "sg:city":"Schee\u00dfel",
    "sg:phone":"+49 4263/3333",
    "sg:postcode":"27383",
    "sg:province":"Niedersachsen",
    "wof:name":"Heiner Precht",
    "wof:placetype":"venue"
},
  "geometry": {"coordinates":[9.4685945511,53.1634407043],"type":"Point"}
}