{
  "type": "Feature",
  "properties": {
    "iso:country":"DE",
    "sg:address":"Dorfstr. 17",
    "sg:city":"Wesendahl",
    "sg:phone":"+49 3341/25140",
    "sg:postcode":"15345",
    "sg:province":"Brandenburg",
    "wof:name":"Verena Pazdzior",
    "wof:placetype":"venue"
},
  "geometry": {"coordinates":[13.820155,52.603561],"type":"Point"}
}