{
  "type": "Feature",
  "properties": {
    "iso:country":"DE",
    "sg:address":"Im Klosterbr\u00fchl 14",
    "sg:city":"Seligenstadt",
    "sg:phone":"+49 6182/27695",
    "sg:postcode":"63500",
    "sg:province":"Hessen",
    "wof:name":"Ernst Detlef Bengs Rechtsanwalt",
    "wof:placetype":"venue"
},
  "geometry": {"coordinates":[8.9795246124,50.0401420593],"type":"Point"}
}