{
  "type": "Feature",
  "properties": {
    "iso:country":"DE",
    "sg:address":"Bo\u00dflerstr. 81",
    "sg:city":"Wendlingen",
    "sg:phone":"+49 7024/3252",
    "sg:postcode":"73240",
    "sg:province":"Baden-W\u00fcrttemberg",
    "wof:name":"Gartengestalt. Dettinger Gmbh",
    "wof:placetype":"venue"
},
  "geometry": {"coordinates":[9.3992433548,48.6657676697],"type":"Point"}
}