{
  "type": "Feature",
  "properties": {
    "iso:country":"DE",
    "sg:address":"Feldbergstra\u00dfe 5",
    "sg:city":"Neuenb\u00fcrg",
    "sg:phone":"+49 7082/5667",
    "sg:postcode":"75305",
    "sg:province":"Baden-W\u00fcrttemberg",
    "wof:name":"Drollinger Informationsdienst",
    "wof:placetype":"venue"
},
  "geometry": {"coordinates":[8.580478,48.848564],"type":"Point"}
}