{
  "type": "Feature",
  "properties": {
    "iso:country":"DE",
    "sg:address":"Am Friedrichsbrunnen 20",
    "sg:city":"Bamberg",
    "sg:phone":"+49 951/54380",
    "sg:postcode":"96049",
    "sg:province":"Bayern",
    "wof:name":"Klaus Schilffarth Ingenieur",
    "wof:placetype":"venue"
},
  "geometry": {"coordinates":[10.8917207718,49.8808097839],"type":"Point"}
}