{
  "type": "Feature",
  "properties": {
    "iso:country":"DE",
    "sg:address":"N\u00fcrnberger Str. 57",
    "sg:city":"Gunzenhausen",
    "sg:phone":"+49 9831/4059",
    "sg:postcode":"91710",
    "sg:province":"Bayern",
    "wof:name":"Leberzammer Mineral\u00f6le Gmbh",
    "wof:placetype":"venue"
},
  "geometry": {"coordinates":[10.7619533539,49.1212654114],"type":"Point"}
}