{
  "type": "Feature",
  "properties": {
    "iso:country":"DE",
    "sg:address":"Carolinenstr. 7",
    "sg:city":"Greiz",
    "sg:phone":"+49 3661/670034",
    "sg:postcode":"07973",
    "sg:province":"Th\u00fcringen",
    "wof:name":"S. Randig",
    "wof:placetype":"venue"
},
  "geometry": {"coordinates":[12.197696,50.654346],"type":"Point"}
}