{
  "type": "Feature",
  "properties": {
    "iso:country":"DE",
    "sg:address":"Alte Industriestr. 5",
    "sg:city":"Cuxhaven",
    "sg:phone":"+49 4721/25077",
    "sg:postcode":"27472",
    "sg:province":"Niedersachsen",
    "wof:name":"Ernst Vorrath",
    "wof:placetype":"venue"
},
  "geometry": {"coordinates":[8.7112541199,53.8501815796],"type":"Point"}
}