{
  "type": "Feature",
  "properties": {
    "iso:country":"DE",
    "sg:address":"Hauptstr. 87",
    "sg:city":"Kleinkarlbach",
    "sg:phone":"+49 6359/2561",
    "sg:postcode":"67271",
    "sg:province":"Rheinland-Pfalz",
    "wof:name":"Rudolf G\u00f6rlitz",
    "wof:placetype":"venue"
},
  "geometry": {"coordinates":[8.1577367783,49.5399894714],"type":"Point"}
}