{
  "type": "Feature",
  "properties": {
    "iso:country":"DE",
    "sg:address":"Kirsch\u00e4ckerstr. 11",
    "sg:city":"Bamberg",
    "sg:phone":"+49 951/9320040",
    "sg:postcode":"96052",
    "sg:province":"Bayern",
    "wof:name":"Extra",
    "wof:placetype":"venue"
},
  "geometry": {"coordinates":[10.9077653885,49.9120483398],"type":"Point"}
}