{
  "type": "Feature",
  "properties": {
    "iso:country":"DE",
    "sg:address":"Waldschulstr. 10",
    "sg:city":"Weilm\u00fcnster",
    "sg:phone":"+49 6472/2081",
    "sg:postcode":"35789",
    "sg:province":"Hessen",
    "wof:name":"Texography Gmbh Textilmaschinen",
    "wof:placetype":"venue"
},
  "geometry": {"coordinates":[8.3568019867,50.4660415649],"type":"Point"}
}