{
  "type": "Feature",
  "properties": {
    "iso:country":"DE",
    "sg:address":"Ostlandstr. 6",
    "sg:city":"F\u00fcssen",
    "sg:phone":"+49 8362/7079",
    "sg:postcode":"87629",
    "sg:province":"Bayern",
    "wof:name":"St. Martin Alten- Und Pflegeheim",
    "wof:placetype":"venue"
},
  "geometry": {"coordinates":[10.680223,47.572124],"type":"Point"}
}