{
  "type": "Feature",
  "properties": {
    "iso:country":"DE",
    "sg:address":"Schulstr. 34",
    "sg:city":"D\u00fcren",
    "sg:phone":"+49 2421/44453",
    "sg:postcode":"52353",
    "sg:province":"Nordrhein-Westfalen",
    "wof:name":"H. Heidel",
    "wof:placetype":"venue"
},
  "geometry": {"coordinates":[6.4808540344,50.8120422363],"type":"Point"}
}