{
  "type": "Feature",
  "properties": {
    "iso:country":"DE",
    "sg:address":"Am Me\u00dfplatz 2",
    "sg:city":"Mannheim",
    "sg:phone":"+49 621/34727",
    "sg:postcode":"68169",
    "sg:province":"Baden-W\u00fcrttemberg",
    "wof:name":"Stadt Thessaloniki",
    "wof:placetype":"venue"
},
  "geometry": {"coordinates":[8.47153759,49.4963150024],"type":"Point"}
}