{
  "type": "Feature",
  "properties": {
    "iso:country":"DE",
    "sg:address":"Husmeer 4",
    "sg:city":"Rhede",
    "sg:phone":"+49 4964/914200",
    "sg:postcode":"26899",
    "sg:province":"Niedersachsen",
    "wof:name":"Webo Gmbh & Co. Kg",
    "wof:placetype":"venue"
},
  "geometry": {"coordinates":[7.2556109428,53.084651947],"type":"Point"}
}