{
  "type": "Feature",
  "properties": {
    "iso:country":"DE",
    "sg:address":"Schmeerstr. 6",
    "sg:city":"Halle",
    "sg:phone":"+49 345/2902458",
    "sg:postcode":"06108",
    "sg:province":"Sachsen-Anhalt",
    "wof:name":"Lothar Dietrich",
    "wof:placetype":"venue"
},
  "geometry": {"coordinates":[11.9703836441,51.4812278748],"type":"Point"}
}