{
  "type": "Feature",
  "properties": {
    "iso:country":"DE",
    "sg:address":"Am Hauptbahnhof",
    "sg:city":"Dresden",
    "sg:postcode":"01069",
    "sg:province":"Sachsen",
    "wof:name":"Lotto- Und Toto-annahme",
    "wof:placetype":"venue"
},
  "geometry": {"coordinates":[13.733344,51.039169],"type":"Point"}
}