{
  "type": "Feature",
  "properties": {
    "iso:country":"DE",
    "sg:address":"Obergasse 12",
    "sg:city":"Oberursel",
    "sg:phone":"+49 6171/54539",
    "sg:postcode":"61440",
    "sg:province":"Hessen",
    "wof:name":"Klaus Rompf",
    "wof:placetype":"venue"
},
  "geometry": {"coordinates":[8.573644,50.203468],"type":"Point"}
}