{
  "type": "Feature",
  "properties": {
    "iso:country":"DE",
    "sg:address":"Hauptstr. 2",
    "sg:city":"Langenhennersdorf",
    "sg:phone":"+49 35032/70809",
    "sg:postcode":"01819",
    "sg:province":"Sachsen",
    "wof:name":"Agrargen. Bielatal Eg",
    "wof:placetype":"venue"
},
  "geometry": {"coordinates":[14.025515,50.880844],"type":"Point"}
}