{
  "type": "Feature",
  "properties": {
    "iso:country":"DE",
    "sg:address":"Bergstr. 3",
    "sg:city":"Stolpen",
    "sg:phone":"+49 35973/26417",
    "sg:postcode":"01833",
    "sg:province":"Sachsen",
    "wof:name":"Erbgericht",
    "wof:placetype":"venue"
},
  "geometry": {"coordinates":[14.1181535721,51.0421714783],"type":"Point"}
}