{
  "type": "Feature",
  "properties": {
    "iso:country":"DE",
    "sg:address":"Koblenzer Str.",
    "sg:city":"Blankenheim",
    "sg:phone":"+49 2449/314",
    "sg:postcode":"53945",
    "sg:province":"Nordrhein-Westfalen",
    "wof:name":"Hotel-restaurant Forellenhof",
    "wof:placetype":"venue"
},
  "geometry": {"coordinates":[6.6544280052,50.4346885681],"type":"Point"}
}