{
  "type": "Feature",
  "properties": {
    "iso:country":"DE",
    "sg:address":"Dorfstr. 4",
    "sg:city":"Lemgow",
    "sg:phone":"+49 5883/1354",
    "sg:postcode":"29485",
    "sg:province":"Niedersachsen",
    "wof:name":"K. Longmuss",
    "wof:placetype":"venue"
},
  "geometry": {"coordinates":[11.35756,52.919624],"type":"Point"}
}