{
  "type": "Feature",
  "properties": {
    "iso:country":"DE",
    "sg:address":"Kolberger Weg 8",
    "sg:city":"Vienenburg",
    "sg:phone":"+49 5324/717777",
    "sg:postcode":"38690",
    "sg:province":"Niedersachsen",
    "wof:name":"Nulle",
    "wof:placetype":"venue"
},
  "geometry": {"coordinates":[10.546134,51.956638],"type":"Point"}
}