{
  "type": "Feature",
  "properties": {
    "iso:country":"DE",
    "sg:address":"Holzbrunnenstr. 11",
    "sg:city":"Beverungen",
    "sg:phone":"+49 5273/32050",
    "sg:postcode":"37688",
    "sg:province":"Nordrhein-Westfalen",
    "wof:name":"Becker",
    "wof:placetype":"venue"
},
  "geometry": {"coordinates":[9.334346,51.62048],"type":"Point"}
}