{
  "type": "Feature",
  "properties": {
    "iso:country":"DE",
    "sg:address":"Badgasse 18",
    "sg:city":"Herrenberg",
    "sg:phone":"+49 7032/6040",
    "sg:postcode":"71083",
    "sg:province":"Baden-W\u00fcrttemberg",
    "wof:name":"Hildebrand",
    "wof:placetype":"venue"
},
  "geometry": {"coordinates":[8.8690986633,48.5967597961],"type":"Point"}
}