{
  "type": "Feature",
  "properties": {
    "iso:country":"DE",
    "sg:address":"Mei\u00dfner Str. 8",
    "sg:city":"Radeburg",
    "sg:phone":"+49 35208/2305",
    "sg:postcode":"01471",
    "sg:province":"Sachsen",
    "wof:name":"Bernd Klotsche",
    "wof:placetype":"venue"
},
  "geometry": {"coordinates":[13.7224788666,51.2146987915],"type":"Point"}
}