{
  "type": "Feature",
  "properties": {
    "iso:country":"DE",
    "sg:address":"Rathenaustr. 6",
    "sg:city":"Quedlinburg",
    "sg:phone":"+49 3946/77100",
    "sg:postcode":"06484",
    "sg:province":"Sachsen-Anhalt",
    "wof:name":"T\u00f6pperwein Music Gmbh",
    "wof:placetype":"venue"
},
  "geometry": {"coordinates":[11.1537322998,51.7863616943],"type":"Point"}
}