{
  "type": "Feature",
  "properties": {
    "iso:country":"DE",
    "sg:address":"Lessingstr. 12",
    "sg:city":"D\u00fcsseldorf",
    "sg:phone":"+49 211/722161",
    "sg:postcode":"40227",
    "sg:province":"Nordrhein-Westfalen",
    "wof:name":"Frank Fendler",
    "wof:placetype":"venue"
},
  "geometry": {"coordinates":[6.7932257652,51.2160453796],"type":"Point"}
}