{
  "type": "Feature",
  "properties": {
    "iso:country":"DE",
    "sg:address":"Krumbeckstr. 34",
    "sg:city":"Velbert",
    "sg:phone":"+49 2053/923501",
    "sg:postcode":"42553",
    "sg:province":"Nordrhein-Westfalen",
    "wof:name":"Fib-forschungs-, Industrie- Und Umweltberatungs Gmbh",
    "wof:placetype":"venue"
},
  "geometry": {"coordinates":[7.0843992233,51.3000793457],"type":"Point"}
}