{
  "type": "Feature",
  "properties": {
    "iso:country":"DE",
    "sg:address":"Obere Dorfstr. 1",
    "sg:city":"Saulgrub",
    "sg:phone":"+49 8845/75106",
    "sg:postcode":"82442",
    "sg:province":"Bayern",
    "wof:name":"Autohaus Gut Inh. Josef Gut",
    "wof:placetype":"venue"
},
  "geometry": {"coordinates":[11.018603,47.649208],"type":"Point"}
}