{
  "type": "Feature",
  "properties": {
    "iso:country":"DE",
    "sg:address":"Siegmundstr. 137 PF 82025",
    "sg:city":"N\u00fcrnberg",
    "sg:phone":"+49 911/312422",
    "sg:postcode":"90431",
    "sg:province":"Bayern",
    "wof:name":"Jos. Hesse Druck - U. Papierverarbeitung Eksm",
    "wof:placetype":"venue"
},
  "geometry": {"coordinates":[11.0199804306,49.4426994324],"type":"Point"}
}