{
  "type": "Feature",
  "properties": {
    "iso:country":"DE",
    "sg:address":"Weiherstr. 29",
    "sg:city":"Villingen-Schwenningen",
    "sg:phone":"+49 7721/23737",
    "sg:postcode":"78050",
    "sg:province":"Baden-W\u00fcrttemberg",
    "wof:name":"Siegfried Schneckenburger",
    "wof:placetype":"venue"
},
  "geometry": {"coordinates":[8.4519853592,48.0523605347],"type":"Point"}
}