{
  "type": "Feature",
  "properties": {
    "iso:country":"DE",
    "sg:address":"Moltkestr. 4a",
    "sg:city":"Uetersen",
    "sg:phone":"+49 4122/45446",
    "sg:postcode":"25436",
    "sg:province":"Schleswig-Holstein",
    "wof:name":"Sharom Achawan- Farshchi Briolett",
    "wof:placetype":"venue"
},
  "geometry": {"coordinates":[9.6547451019,53.6818695068],"type":"Point"}
}