{
  "type": "Feature",
  "properties": {
    "iso:country":"DE",
    "sg:address":"Friedrichstr. 51",
    "sg:city":"Freiburg",
    "sg:postcode":"79098",
    "sg:province":"Baden-W\u00fcrttemberg",
    "wof:name":"Richard-fehrenbach- Planetarium",
    "wof:placetype":"venue"
},
  "geometry": {"coordinates":[7.8451862335,47.9993934631],"type":"Point"}
}