{
  "type": "Feature",
  "properties": {
    "iso:country":"DE",
    "sg:address":"Goethestr. 19",
    "sg:city":"M\u00fcnchen",
    "sg:phone":"+49 89/592990",
    "sg:postcode":"80336",
    "sg:province":"Bayern",
    "wof:name":"Pamukkale Reisen Gmbh",
    "wof:placetype":"venue"
},
  "geometry": {"coordinates":[11.5588169098,48.136592865],"type":"Point"}
}