{
  "type": "Feature",
  "properties": {
    "iso:country":"DE",
    "sg:address":"Bahnhofstr. 41",
    "sg:city":"K\u00f6lleda",
    "sg:phone":"+49 3635/46080",
    "sg:postcode":"99625",
    "sg:province":"Th\u00fcringen",
    "wof:name":"Isolde Schieke Steuerberater",
    "wof:placetype":"venue"
},
  "geometry": {"coordinates":[11.2468852997,51.1863098145],"type":"Point"}
}