{
  "type": "Feature",
  "properties": {
    "iso:country":"DE",
    "sg:address":"Ahrstr. 2",
    "sg:city":"Bad Neuenahr-Ahrweiler",
    "sg:phone":"+49 2641/79837",
    "sg:postcode":"53474",
    "sg:province":"Rheinland-Pfalz",
    "wof:name":"Kinderkiste",
    "wof:placetype":"venue"
},
  "geometry": {"coordinates":[7.1378221512,50.5459823608],"type":"Point"}
}