{
  "type": "Feature",
  "properties": {
    "iso:country":"DE",
    "sg:address":"Ibbenb\u00fcrener Str. 73",
    "sg:city":"Mettingen",
    "sg:phone":"+49 5452/5777",
    "sg:postcode":"49497",
    "sg:province":"Nordrhein-Westfalen",
    "wof:name":"Hotel-restaurant Schr\u00f6er Barbara Sch\u00e4nke",
    "wof:placetype":"venue"
},
  "geometry": {"coordinates":[7.7774100304,52.3030891418],"type":"Point"}
}