{
  "type": "Feature",
  "properties": {
    "iso:country":"DE",
    "sg:address":"Eichenrain 15",
    "sg:city":"Schmalkalden",
    "sg:phone":"+49 3683/69390",
    "sg:postcode":"98574",
    "sg:province":"Th\u00fcringen",
    "wof:name":"Heck Und Partner",
    "wof:placetype":"venue"
},
  "geometry": {"coordinates":[10.4367008209,50.721321106],"type":"Point"}
}