{
  "type": "Feature",
  "properties": {
    "iso:country":"DE",
    "sg:address":"Hansestr. 9",
    "sg:city":"K\u00f6ln",
    "sg:phone":"+49 2203/31122",
    "sg:postcode":"51149",
    "sg:province":"Nordrhein-Westfalen",
    "wof:name":"Heinrichs & Schmolke",
    "wof:placetype":"venue"
},
  "geometry": {"coordinates":[7.076345,50.905521],"type":"Point"}
}