{
  "type": "Feature",
  "properties": {
    "iso:country":"DE",
    "sg:address":"Burgknobelweg 2a",
    "sg:city":"Sigmarszell",
    "sg:phone":"+49 8389/98100",
    "sg:postcode":"88138",
    "sg:province":"Bayern",
    "wof:name":"Rainer Schmidt",
    "wof:placetype":"venue"
},
  "geometry": {"coordinates":[9.74212,47.588779],"type":"Point"}
}