{
  "type": "Feature",
  "properties": {
    "iso:country":"DE",
    "sg:address":"Kanzelwandstr. 5",
    "sg:city":"Mindelheim",
    "sg:postcode":"87719",
    "sg:province":"Bayern",
    "wof:name":"Mn-auto-rent Gmbh",
    "wof:placetype":"venue"
},
  "geometry": {"coordinates":[10.49836,48.0369],"type":"Point"}
}