{
  "type": "Feature",
  "properties": {
    "iso:country":"DE",
    "sg:address":"Backnanger Str. 8",
    "sg:city":"Aspach",
    "sg:phone":"+49 7191/915125",
    "sg:postcode":"71546",
    "sg:province":"Baden-W\u00fcrttemberg",
    "wof:name":"Elektrotechnik Konstantin",
    "wof:placetype":"venue"
},
  "geometry": {"coordinates":[9.399388,48.966267],"type":"Point"}
}