{
  "type": "Feature",
  "properties": {
    "iso:country":"DE",
    "sg:address":"Lange-Hop-Str. 115",
    "sg:city":"Hannover",
    "sg:phone":"+49 511/5106651",
    "sg:postcode":"30559",
    "sg:province":"Niedersachsen",
    "wof:name":"F. Filipczak Reifenmarkt Gmbh",
    "wof:placetype":"venue"
},
  "geometry": {"coordinates":[9.820812,52.351521],"type":"Point"}
}