{
  "type": "Feature",
  "properties": {
    "iso:country":"DE",
    "sg:address":"Elverdisser Str. 7",
    "sg:city":"Herford",
    "sg:phone":"+49 5221/529343",
    "sg:postcode":"32052",
    "sg:province":"Nordrhein-Westfalen",
    "wof:name":"Bernies",
    "wof:placetype":"venue"
},
  "geometry": {"coordinates":[8.6730728149,52.109790802],"type":"Point"}
}