{
  "type": "Feature",
  "properties": {
    "iso:country":"DE",
    "sg:address":"Daimlerstr. 1",
    "sg:city":"Ottobrunn",
    "sg:phone":"+49 89/629990",
    "sg:postcode":"85521",
    "sg:province":"Bayern",
    "wof:name":"Bavaria Petrol Tankstellenbetriebs- Gmbh",
    "wof:placetype":"venue"
},
  "geometry": {"coordinates":[11.652953,48.063786],"type":"Point"}
}