{
  "type": "Feature",
  "properties": {
    "iso:country":"DE",
    "sg:address":"Hainstr. 35",
    "sg:city":"H\u00fcnfelden",
    "sg:phone":"+49 6438/6000",
    "sg:postcode":"65597",
    "sg:province":"Hessen",
    "wof:name":"Sigrid Fischer Rechtsanw\u00e4ltin",
    "wof:placetype":"venue"
},
  "geometry": {"coordinates":[8.1830501556,50.3068199158],"type":"Point"}
}