{
  "type": "Feature",
  "properties": {
    "iso:country":"DE",
    "sg:address":"Apelstedt 3B",
    "sg:city":"Bassum",
    "sg:postcode":"27211",
    "sg:province":"Niedersachsen",
    "wof:name":"Stune Auf Teneriffa",
    "wof:placetype":"venue"
},
  "geometry": {"coordinates":[8.740205,52.811672],"type":"Point"}
}