{
  "type": "Feature",
  "properties": {
    "iso:country":"DE",
    "sg:address":"Bahnhofstr. 33",
    "sg:city":"Wallertheim",
    "sg:phone":"+49 4967/3291670",
    "sg:postcode":"55578",
    "sg:province":"Rheinland-Pfalz",
    "wof:name":"Tib Heyne & Co. Gmbh",
    "wof:placetype":"venue"
},
  "geometry": {"coordinates":[8.0525274277,49.8310089111],"type":"Point"}
}