{
  "type": "Feature",
  "properties": {
    "iso:country":"DE",
    "sg:address":"Herbisried 1 a",
    "sg:city":"Bad Gr\u00f6nenbach",
    "sg:phone":"+49 8334/7692",
    "sg:postcode":"87730",
    "sg:province":"Bayern",
    "wof:name":"H. Kircher Steuerberater",
    "wof:placetype":"venue"
},
  "geometry": {"coordinates":[10.2272024155,47.8595161438],"type":"Point"}
}