{
  "type": "Feature",
  "properties": {
    "iso:country":"DE",
    "sg:address":"Am Ulsterblick 19",
    "sg:city":"Motzlar",
    "sg:phone":"+49 36967/70670",
    "sg:postcode":"36419",
    "sg:province":"Th\u00fcringen",
    "wof:name":"Werner Erb",
    "wof:placetype":"venue"
},
  "geometry": {"coordinates":[9.9691848755,50.6817398071],"type":"Point"}
}