{
  "type": "Feature",
  "properties": {
    "iso:country":"DE",
    "sg:address":"Z\u00e4hringerallee 137",
    "sg:city":"Minden",
    "sg:phone":"+49 571/646220",
    "sg:postcode":"32425",
    "sg:province":"Nordrhein-Westfalen",
    "wof:name":"Iabos Organisationsentwicklung Gmbh",
    "wof:placetype":"venue"
},
  "geometry": {"coordinates":[8.883444,52.311913],"type":"Point"}
}