{
  "type": "Feature",
  "properties": {
    "iso:country":"DE",
    "sg:address":"Hauptstr. 230 a",
    "sg:city":"M\u00fcnsingen",
    "sg:phone":"+49 7381/2862",
    "sg:postcode":"72525",
    "sg:province":"Baden-W\u00fcrttemberg",
    "wof:name":"Klaus Br\u00e4ndle",
    "wof:placetype":"venue"
},
  "geometry": {"coordinates":[9.5224,48.412521],"type":"Point"}
}