{
  "type": "Feature",
  "properties": {
    "iso:country":"DE",
    "sg:address":"Thananger Str. 28",
    "sg:city":"Hunderdorf",
    "sg:postcode":"94336",
    "sg:province":"Bayern",
    "wof:name":"H\u00e4rtenberger Bauelemente Gmbh",
    "wof:placetype":"venue"
},
  "geometry": {"coordinates":[12.720056,48.947571],"type":"Point"}
}