{
  "type": "Feature",
  "properties": {
    "iso:country":"DE",
    "sg:address":"Rauschfeld 1",
    "sg:city":"Delbr\u00fcck",
    "sg:postcode":"33129",
    "sg:province":"Nordrhein-Westfalen",
    "wof:name":"Haustechnik-klein E. K.",
    "wof:placetype":"venue"
},
  "geometry": {"coordinates":[8.5595159531,51.7112388611],"type":"Point"}
}