{
  "type": "Feature",
  "properties": {
    "iso:country":"DE",
    "sg:address":"Reinsburgstr. 97",
    "sg:city":"Stuttgart",
    "sg:phone":"+49 711/4204990",
    "sg:postcode":"70197",
    "sg:province":"Baden-W\u00fcrttemberg",
    "wof:name":"Cross-fade Gmbh",
    "wof:placetype":"venue"
},
  "geometry": {"coordinates":[9.1566638947,48.7679405212],"type":"Point"}
}