{
  "type": "Feature",
  "properties": {
    "iso:country":"DE",
    "sg:address":"Gemeindehof 7",
    "sg:city":"Goslar",
    "sg:phone":"+49 5321/34920",
    "sg:postcode":"38640",
    "sg:province":"Niedersachsen",
    "wof:name":"Handwerkerhof Goslar Hans Schmidt Gmbh",
    "wof:placetype":"venue"
},
  "geometry": {"coordinates":[10.4288301468,51.9050216675],"type":"Point"}
}