{
  "type": "Feature",
  "properties": {
    "iso:country":"DE",
    "sg:address":"Altheim 69",
    "sg:city":"Dietersheim",
    "sg:phone":"+49 9846/750",
    "sg:postcode":"91463",
    "sg:province":"Bayern",
    "wof:name":"F. Hussen\u00f6der",
    "wof:placetype":"venue"
},
  "geometry": {"coordinates":[10.5078811646,49.5496063232],"type":"Point"}
}