{
  "type": "Feature",
  "properties": {
    "iso:country":"DE",
    "sg:address":"Engelbergerstr. 5",
    "sg:city":"Augsburg",
    "sg:phone":"+49 821/553484",
    "sg:postcode":"86161",
    "sg:province":"Bayern",
    "wof:name":"Monika Daenner Krankengymnastin",
    "wof:placetype":"venue"
},
  "geometry": {"coordinates":[10.909506,48.359219],"type":"Point"}
}