{
  "type": "Feature",
  "properties": {
    "iso:country":"DE",
    "sg:address":"Lobbe",
    "sg:city":"Middelhagen",
    "sg:phone":"+49 38308/2228",
    "sg:postcode":"18586",
    "sg:province":"Mecklenburg-Vorpommern",
    "wof:name":"Dornacks Pension",
    "wof:placetype":"venue"
},
  "geometry": {"coordinates":[13.7183351517,54.319606781],"type":"Point"}
}