{
  "type": "Feature",
  "properties": {
    "iso:country":"DE",
    "sg:address":"Langensalzaer Str. 100",
    "sg:city":"Eisenach",
    "sg:postcode":"99817",
    "sg:province":"Th\u00fcringen",
    "wof:name":"Eisenacher Garten- Und Freizeit-center",
    "wof:placetype":"venue"
},
  "geometry": {"coordinates":[10.3254394531,50.9743804932],"type":"Point"}
}