{
  "type": "Feature",
  "properties": {
    "iso:country":"DE",
    "sg:address":"Brauerstr. 1-3",
    "sg:city":"Kaltenkirchen",
    "sg:phone":"+49 4191/2733",
    "sg:postcode":"24568",
    "sg:province":"Schleswig-Holstein",
    "wof:name":"Praxis Dr. Med. D\u00fcrholt Und Dr. Med. Wahn",
    "wof:placetype":"venue"
},
  "geometry": {"coordinates":[9.9631624222,53.8363685608],"type":"Point"}
}