{
  "type": "Feature",
  "properties": {
    "iso:country":"DE",
    "sg:address":"Ringstr. 20",
    "sg:city":"Pfalzgrafenweiler",
    "sg:phone":"+49 7445/81306",
    "sg:postcode":"72285",
    "sg:province":"Baden-W\u00fcrttemberg",
    "wof:name":"Karl Koch",
    "wof:placetype":"venue"
},
  "geometry": {"coordinates":[8.595552,48.538158],"type":"Point"}
}