{
  "type": "Feature",
  "properties": {
    "iso:country":"DE",
    "sg:address":"Rastdorfer Str. 2",
    "sg:city":"Lorup",
    "sg:phone":"+49 5954/752",
    "sg:postcode":"26901",
    "sg:province":"Niedersachsen",
    "wof:name":"Wilhelm Funke",
    "wof:placetype":"venue"
},
  "geometry": {"coordinates":[7.6461701393,52.9240875244],"type":"Point"}
}