{
  "type": "Feature",
  "properties": {
    "iso:country":"DE",
    "sg:address":"Altendorfer Str. 42",
    "sg:city":"Essen",
    "sg:phone":"+49 201/247390",
    "sg:postcode":"45127",
    "sg:province":"Nordrhein-Westfalen",
    "wof:name":"A. H\u00f6lscher Gmbh",
    "wof:placetype":"venue"
},
  "geometry": {"coordinates":[6.9987177849,51.458820343],"type":"Point"}
}