{
  "type": "Feature",
  "properties": {
    "iso:country":"DE",
    "sg:address":"G\u00fctersloher Str. 105",
    "sg:city":"Verl",
    "sg:phone":"+49 5246/931350",
    "sg:postcode":"33415",
    "sg:province":"Nordrhein-Westfalen",
    "wof:name":"M. Aufderstroth",
    "wof:placetype":"venue"
},
  "geometry": {"coordinates":[8.492024,51.879768],"type":"Point"}
}