{
  "type": "Feature",
  "properties": {
    "iso:country":"DE",
    "sg:address":"An der B\u00e4derstr. 58",
    "sg:city":"S\u00fcsel",
    "sg:phone":"+49 4524/74548",
    "sg:postcode":"23701",
    "sg:province":"Schleswig-Holstein",
    "wof:name":"Peter Wolgast",
    "wof:placetype":"venue"
},
  "geometry": {"coordinates":[10.7156858444,54.0779685974],"type":"Point"}
}