{
  "type": "Feature",
  "properties": {
    "iso:country":"DE",
    "sg:address":"Sonnengasse 17",
    "sg:city":"Brackenheim",
    "sg:phone":"+49 7135/2903",
    "sg:postcode":"74336",
    "sg:province":"Baden-W\u00fcrttemberg",
    "wof:name":"Uwe Auderer Heizungsbau Gmbh",
    "wof:placetype":"venue"
},
  "geometry": {"coordinates":[9.0769290924,49.0885238647],"type":"Point"}
}