{
  "type": "Feature",
  "properties": {
    "iso:country":"DE",
    "sg:address":"Paulsm\u00fchlenstr. 4",
    "sg:city":"D\u00fcsseldorf",
    "sg:phone":"+49 211/717122",
    "sg:postcode":"40597",
    "sg:province":"Nordrhein-Westfalen",
    "wof:name":"Felix Ophoff",
    "wof:placetype":"venue"
},
  "geometry": {"coordinates":[6.878991,51.163864],"type":"Point"}
}