{
  "type": "Feature",
  "properties": {
    "iso:country":"DE",
    "sg:address":"Kilianstr. 11",
    "sg:city":"Heilbronn",
    "sg:phone":"+49 7131/85562",
    "sg:postcode":"74072",
    "sg:province":"Baden-W\u00fcrttemberg",
    "wof:name":"G. Bopp Tanzschule",
    "wof:placetype":"venue"
},
  "geometry": {"coordinates":[9.2209644318,49.140914917],"type":"Point"}
}