{
  "type": "Feature",
  "properties": {
    "iso:country":"DE",
    "sg:address":"Rathausgasse 25",
    "sg:city":"Freiburg",
    "sg:phone":"+49 761/32176",
    "sg:postcode":"79098",
    "sg:province":"Baden-W\u00fcrttemberg",
    "wof:name":"E. Heitzmann",
    "wof:placetype":"venue"
},
  "geometry": {"coordinates":[7.847744,47.996426],"type":"Point"}
}