{
  "type": "Feature",
  "properties": {
    "iso:country":"DE",
    "sg:address":"Scharnhorstring 35",
    "sg:city":"Magdeburg",
    "sg:phone":"+49 391/7225583",
    "sg:postcode":"39130",
    "sg:province":"Sachsen-Anhalt",
    "wof:name":"Michael Pfalzgraf",
    "wof:placetype":"venue"
},
  "geometry": {"coordinates":[11.5859212875,52.1494293213],"type":"Point"}
}