{
  "type": "Feature",
  "properties": {
    "iso:country":"DE",
    "sg:address":"Luitpoldplatz 5",
    "sg:city":"Sch\u00f6nberg",
    "sg:phone":"+49 8554/2971",
    "sg:postcode":"94513",
    "sg:province":"Bayern",
    "wof:name":"Lemberger Fr\u00fcchtehandlung",
    "wof:placetype":"venue"
},
  "geometry": {"coordinates":[13.3396100998,48.8401985168],"type":"Point"}
}