{
  "type": "Feature",
  "properties": {
    "iso:country":"DE",
    "sg:address":"Am Weserdeich 21d",
    "sg:city":"Brake",
    "sg:phone":"+49 4401/7548",
    "sg:postcode":"26919",
    "sg:province":"Niedersachsen",
    "wof:name":"J.h. Barr Gmbh & Co. Ms Anita B. Kg",
    "wof:placetype":"venue"
},
  "geometry": {"coordinates":[8.4862117767,53.3091239929],"type":"Point"}
}