{
  "type": "Feature",
  "properties": {
    "iso:country":"DE",
    "sg:address":"Kirchstr. 1",
    "sg:city":"Hindelang",
    "sg:phone":"+49 8324/8539",
    "sg:postcode":"87541",
    "sg:province":"Bayern",
    "wof:name":"Hirschbergstube",
    "wof:placetype":"venue"
},
  "geometry": {"coordinates":[10.3683280945,47.5065841675],"type":"Point"}
}