{
  "type": "Feature",
  "properties": {
    "iso:country":"DE",
    "sg:address":"Gartenstr. 3a",
    "sg:city":"Brockau",
    "sg:phone":"+49 3765/31576",
    "sg:postcode":"08491",
    "sg:province":"Sachsen",
    "wof:name":"Fickelscher Bau Gmbh",
    "wof:placetype":"venue"
},
  "geometry": {"coordinates":[12.2126569748,50.6080131531],"type":"Point"}
}