{
  "type": "Feature",
  "properties": {
    "iso:country":"DE",
    "sg:address":"Margaretenstr. 17-19",
    "sg:city":"Duisburg",
    "sg:phone":"+49 203/723256",
    "sg:postcode":"47055",
    "sg:province":"Nordrhein-Westfalen",
    "wof:name":"Eissporthallen Betriebs Gmbh",
    "wof:placetype":"venue"
},
  "geometry": {"coordinates":[6.7795548439,51.4066314697],"type":"Point"}
}