{
  "type": "Feature",
  "properties": {
    "iso:country":"DE",
    "sg:address":"Frankfurter Str. 294",
    "sg:city":"Gie\u00dfen",
    "sg:phone":"+49 641/23414",
    "sg:postcode":"35398",
    "sg:province":"Hessen",
    "wof:name":"Gerhard Klenner",
    "wof:placetype":"venue"
},
  "geometry": {"coordinates":[8.6484050751,50.5589675903],"type":"Point"}
}