{
  "type": "Feature",
  "properties": {
    "iso:country":"DE",
    "sg:address":"Neum\u00fchler Weg",
    "sg:city":"Saarbr\u00fccken",
    "sg:phone":"+49 681/988240",
    "sg:postcode":"66130",
    "sg:province":"Saarland",
    "wof:name":"F. A. Leysser Nachf.",
    "wof:placetype":"venue"
},
  "geometry": {"coordinates":[7.0237240791,49.2040214539],"type":"Point"}
}