{
  "type": "Feature",
  "properties": {
    "iso:country":"DE",
    "sg:address":"Landolinsgasse 1",
    "sg:city":"Esslingen",
    "sg:phone":"+49 711/311124",
    "sg:postcode":"73728",
    "sg:province":"Baden-W\u00fcrttemberg",
    "wof:name":"Lima - Literarisches Marionettentheater",
    "wof:placetype":"venue"
},
  "geometry": {"coordinates":[9.3102827072,48.7417526245],"type":"Point"}
}