{
  "type": "Feature",
  "properties": {
    "iso:country":"DE",
    "sg:address":"Lorettostr. 51",
    "sg:city":"D\u00fcsseldorf",
    "sg:phone":"+49 211/394373",
    "sg:postcode":"40219",
    "sg:province":"Nordrhein-Westfalen",
    "wof:name":"J. Zdieblwski",
    "wof:placetype":"venue"
},
  "geometry": {"coordinates":[6.7641611099,51.2126808167],"type":"Point"}
}