{
  "type": "Feature",
  "properties": {
    "iso:country":"DE",
    "sg:address":"Blenderstr. 6",
    "sg:city":"Durach",
    "sg:phone":"+49 831/60869",
    "sg:postcode":"87471",
    "sg:province":"Bayern",
    "wof:name":"Helmut Sch\u00f6llhorn Steuerberater",
    "wof:placetype":"venue"
},
  "geometry": {"coordinates":[10.3519630432,47.700428009],"type":"Point"}
}