{
  "type": "Feature",
  "properties": {
    "iso:country":"DE",
    "sg:address":"Linner Str. 33",
    "sg:city":"Krefeld",
    "sg:phone":"+49 2151/481453",
    "sg:postcode":"47829",
    "sg:province":"Nordrhein-Westfalen",
    "wof:name":"H. Maegle",
    "wof:placetype":"venue"
},
  "geometry": {"coordinates":[6.649719,51.348846],"type":"Point"}
}