{
  "type": "Feature",
  "properties": {
    "iso:country":"DE",
    "sg:address":"Korbacher Str. 7",
    "sg:city":"Schauenburg",
    "sg:phone":"+49 5601/1419",
    "sg:postcode":"34270",
    "sg:province":"Hessen",
    "wof:name":"Lothar Scherb",
    "wof:placetype":"venue"
},
  "geometry": {"coordinates":[9.3833560944,51.2725868225],"type":"Point"}
}