{
  "type": "Feature",
  "properties": {
    "iso:country":"DE",
    "sg:address":"Blankenfelder Str. 94",
    "sg:city":"Berlin",
    "sg:phone":"+49 30/9121231",
    "sg:postcode":"13158",
    "sg:province":"Berlin",
    "wof:name":"Reimund Dewerny",
    "wof:placetype":"venue"
},
  "geometry": {"coordinates":[13.402493,52.600487],"type":"Point"}
}