{
  "type": "Feature",
  "properties": {
    "iso:country":"DE",
    "sg:address":"Lange Str. 53",
    "sg:city":"Cloppenburg",
    "sg:phone":"+49 4471/947260",
    "sg:postcode":"49661",
    "sg:province":"Niedersachsen",
    "wof:name":"Bonita Gmbh",
    "wof:placetype":"venue"
},
  "geometry": {"coordinates":[8.038825,52.844486],"type":"Point"}
}