{
  "type": "Feature",
  "properties": {
    "iso:country":"DE",
    "sg:address":"Br\u00fcningstr 50Geb. E635",
    "sg:city":"Frankfurt",
    "sg:phone":"+49 69/30517641",
    "sg:postcode":"65929",
    "sg:province":"Hessen",
    "wof:name":"Bc Biochemie Gmbh",
    "wof:placetype":"venue"
},
  "geometry": {"coordinates":[8.543885231,50.0990943909],"type":"Point"}
}