{
  "type": "Feature",
  "properties": {
    "iso:country":"DE",
    "sg:address":"Kirrlohstr. 28",
    "sg:city":"Bad Waldsee",
    "sg:phone":"+49 7524/48335",
    "sg:postcode":"88339",
    "sg:province":"Baden-W\u00fcrttemberg",
    "wof:name":"Wolfgang G\u00f6tz Inh. Raimund Minsch",
    "wof:placetype":"venue"
},
  "geometry": {"coordinates":[9.7266321182,47.8944358826],"type":"Point"}
}