{
  "type": "Feature",
  "properties": {
    "iso:country":"DE",
    "sg:address":"Wiesenstr 6",
    "sg:city":"Hofbieber",
    "sg:phone":"+49 6657/96010",
    "sg:postcode":"36145",
    "sg:province":"Hessen",
    "wof:name":"Leo Herrmann Gmbh",
    "wof:placetype":"venue"
},
  "geometry": {"coordinates":[9.8004236221,50.5795783997],"type":"Point"}
}