{
  "type": "Feature",
  "properties": {
    "iso:country":"DE",
    "sg:address":"Freiberger Ring 6",
    "sg:city":"Mannheim",
    "sg:phone":"+49 621/2938283",
    "sg:postcode":"68309",
    "sg:province":"Baden-W\u00fcrttemberg",
    "wof:name":"Hallenbad Vogelstang",
    "wof:placetype":"venue"
},
  "geometry": {"coordinates":[8.5402669907,49.5101547241],"type":"Point"}
}