{
  "type": "Feature",
  "properties": {
    "iso:country":"DE",
    "sg:address":"Seigen 6",
    "sg:city":"Roding",
    "sg:phone":"+49 9465/382",
    "sg:postcode":"93426",
    "sg:province":"Bayern",
    "wof:name":"Elekto Griesbeck Gmbh",
    "wof:placetype":"venue"
},
  "geometry": {"coordinates":[12.521478,49.196564],"type":"Point"}
}