{
  "type": "Feature",
  "properties": {
    "iso:country":"DE",
    "sg:address":"Claudiusstr. 76",
    "sg:city":"Hamburg",
    "sg:phone":"+49 40/6527513",
    "sg:postcode":"22043",
    "sg:province":"Hamburg",
    "wof:name":"Implanto-lock Implantatentw. Fortbildung Prophylaxe Und",
    "wof:placetype":"venue"
},
  "geometry": {"coordinates":[10.0692491531,53.5658531189],"type":"Point"}
}