{
  "type": "Feature",
  "properties": {
    "iso:country":"DE",
    "sg:address":"Gladbacher Str. 63",
    "sg:city":"Heinsberg",
    "sg:phone":"+49 2452/63566",
    "sg:postcode":"52525",
    "sg:province":"Nordrhein-Westfalen",
    "wof:name":"Friedbert Adams Gmbh",
    "wof:placetype":"venue"
},
  "geometry": {"coordinates":[6.1603660583,51.0457649231],"type":"Point"}
}