{
  "type": "Feature",
  "properties": {
    "iso:country":"DE",
    "sg:address":"Platzgasse 20",
    "sg:city":"Bernstadt",
    "sg:phone":"+49 4973/486642",
    "sg:postcode":"89182",
    "sg:province":"Baden-W\u00fcrttemberg",
    "wof:name":"Sparkasse Ulm",
    "wof:placetype":"venue"
},
  "geometry": {"coordinates":[10.025044,48.501369],"type":"Point"}
}