{
  "type": "Feature",
  "properties": {
    "iso:country":"DE",
    "sg:address":"Kappelholz",
    "sg:city":"Kappeln",
    "sg:phone":"+49 4642/4919",
    "sg:postcode":"24376",
    "sg:province":"Schleswig-Holstein",
    "wof:name":"K.-u. J\u00fcrgensen",
    "wof:placetype":"venue"
},
  "geometry": {"coordinates":[9.920702,54.659977],"type":"Point"}
}