{
  "type": "Feature",
  "properties": {
    "iso:country":"DE",
    "sg:address":"Simoniusstr. 39",
    "sg:city":"Wangen",
    "sg:phone":"+49 7522/97170",
    "sg:postcode":"88239",
    "sg:province":"Baden-W\u00fcrttemberg",
    "wof:name":"Textildesign & Werkkunst Gmbh",
    "wof:placetype":"venue"
},
  "geometry": {"coordinates":[9.81269,47.688381],"type":"Point"}
}