{
  "type": "Feature",
  "properties": {
    "iso:country":"DE",
    "sg:address":"Waldburgstr. 15",
    "sg:city":"Remagen",
    "sg:phone":"+49 2642/23109",
    "sg:postcode":"53424",
    "sg:province":"Rheinland-Pfalz",
    "wof:name":"Borsch-genn",
    "wof:placetype":"venue"
},
  "geometry": {"coordinates":[7.222205162,50.5777778625],"type":"Point"}
}