{
  "type": "Feature",
  "properties": {
    "iso:country":"DE",
    "sg:address":"Ringlebstr. 10",
    "sg:city":"Arnsberg",
    "sg:phone":"+49 2931/12914",
    "sg:postcode":"59821",
    "sg:province":"Nordrhein-Westfalen",
    "wof:name":"Caritas-verband Arnsberg-sundern E. V.",
    "wof:placetype":"venue"
},
  "geometry": {"coordinates":[8.06976,51.395481],"type":"Point"}
}