{
  "type": "Feature",
  "properties": {
    "iso:country":"DE",
    "sg:address":"Ludwigstr. 32",
    "sg:city":"Rodgau",
    "sg:phone":"+49 6106/645362",
    "sg:postcode":"63110",
    "sg:province":"Hessen",
    "wof:name":"Paul Franz Weil Rechtsanwalt",
    "wof:placetype":"venue"
},
  "geometry": {"coordinates":[8.8847808838,50.0269584656],"type":"Point"}
}