{
  "type": "Feature",
  "properties": {
    "iso:country":"DE",
    "sg:address":"Hauptstr. 22",
    "sg:city":"Dillenburg",
    "sg:phone":"+49 2771/82117",
    "sg:postcode":"35683",
    "sg:province":"Hessen",
    "wof:name":"H. Hilscher",
    "wof:placetype":"venue"
},
  "geometry": {"coordinates":[8.2837486267,50.7396888733],"type":"Point"}
}