{
  "type": "Feature",
  "properties": {
    "iso:country":"DE",
    "sg:address":"Drususstr. 13A",
    "sg:city":"D\u00fcsseldorf",
    "sg:phone":"+49 211/576059",
    "sg:postcode":"40549",
    "sg:province":"Nordrhein-Westfalen",
    "wof:name":"Ingo H\u00fclser Architekt",
    "wof:placetype":"venue"
},
  "geometry": {"coordinates":[6.718873,51.233208],"type":"Point"}
}