{
  "type": "Feature",
  "properties": {
    "iso:country":"DE",
    "sg:address":"Hauptstr. 104a",
    "sg:city":"Warstein",
    "sg:phone":"+49 2902/58203",
    "sg:postcode":"59581",
    "sg:province":"Nordrhein-Westfalen",
    "wof:name":"Peter Sniehotta",
    "wof:placetype":"venue"
},
  "geometry": {"coordinates":[8.3535499573,51.4414482117],"type":"Point"}
}