{
  "type": "Feature",
  "properties": {
    "iso:country":"DE",
    "sg:address":"Altfriedstr. 18",
    "sg:city":"Dortmund",
    "sg:postcode":"44369",
    "sg:province":"Nordrhein-Westfalen",
    "wof:name":"Aldi Gmbh & Co. Kg",
    "wof:placetype":"venue"
},
  "geometry": {"coordinates":[7.4147949219,51.5316085815],"type":"Point"}
}