{
  "type": "Feature",
  "properties": {
    "iso:country":"DE",
    "sg:address":"Am Goldberg 118",
    "sg:city":"Neuss",
    "sg:phone":"+49 2137/12310",
    "sg:postcode":"41469",
    "sg:province":"Nordrhein-Westfalen",
    "wof:name":"Manfred Bickel",
    "wof:placetype":"venue"
},
  "geometry": {"coordinates":[6.7427301407,51.1611595154],"type":"Point"}
}