{
  "type": "Feature",
  "properties": {
    "iso:country":"DE",
    "sg:address":"Carl-Zeiss-Str. 25",
    "sg:city":"Garbsen",
    "sg:phone":"+49 5131/96366",
    "sg:postcode":"30827",
    "sg:province":"Niedersachsen",
    "wof:name":"D\u00fcrkopp Adler Ag",
    "wof:placetype":"venue"
},
  "geometry": {"coordinates":[9.6114635468,52.4483146667],"type":"Point"}
}