{
  "type": "Feature",
  "properties": {
    "iso:country":"DE",
    "sg:address":"Brunnengasse 10",
    "sg:city":"Wei\u00dfbach",
    "sg:phone":"+49 4979/472858",
    "sg:postcode":"74679",
    "sg:province":"Baden-W\u00fcrttemberg",
    "wof:name":"Raiffeisenbank Crispenhofen Eg",
    "wof:placetype":"venue"
},
  "geometry": {"coordinates":[9.599169,49.31604],"type":"Point"}
}