{
  "type": "Feature",
  "properties": {
    "iso:country":"DE",
    "sg:address":"F\u00e4hrstieg 6",
    "sg:city":"Hamburg",
    "sg:postcode":"21107",
    "sg:province":"Hamburg",
    "wof:name":"Flora Glass Import Und Export Gmbh",
    "wof:placetype":"venue"
},
  "geometry": {"coordinates":[9.9765577316,53.5193099976],"type":"Point"}
}