{
  "type": "Feature",
  "properties": {
    "iso:country":"DE",
    "sg:address":"Borchertring 70",
    "sg:city":"Hamburg",
    "sg:phone":"+49 40",
    "sg:postcode":"22309",
    "sg:province":"Hamburg",
    "wof:name":"Hgl",
    "wof:placetype":"venue"
},
  "geometry": {"coordinates":[10.064546,53.615929],"type":"Point"}
}