{
  "type": "Feature",
  "properties": {
    "iso:country":"DE",
    "sg:address":"Jahnstr. 43",
    "sg:city":"Bocholt",
    "sg:phone":"+49 2871/15199",
    "sg:postcode":"46397",
    "sg:province":"Nordrhein-Westfalen",
    "wof:name":"R. Gie\u00dfing",
    "wof:placetype":"venue"
},
  "geometry": {"coordinates":[6.643128,51.832294],"type":"Point"}
}