{
  "type": "Feature",
  "properties": {
    "iso:country":"DE",
    "sg:address":"Goethestr. 8",
    "sg:city":"Sta\u00dffurt",
    "sg:phone":"+49 3925/283752",
    "sg:postcode":"39418",
    "sg:province":"Sachsen-Anhalt",
    "wof:name":"M. Horstmann",
    "wof:placetype":"venue"
},
  "geometry": {"coordinates":[11.583028,51.857937],"type":"Point"}
}