{
  "type": "Feature",
  "properties": {
    "iso:country":"DE",
    "sg:address":"Ringstr. 7",
    "sg:city":"H\u00f6henkirchen-Siegertbrn",
    "sg:phone":"+49 8102/748369",
    "sg:postcode":"85635",
    "sg:province":"Bayern",
    "wof:name":"Tc Asset Management Gmbh",
    "wof:placetype":"venue"
},
  "geometry": {"coordinates":[11.7055749893,48.0212669373],"type":"Point"}
}