{
  "type": "Feature",
  "properties": {
    "iso:country":"DE",
    "sg:address":"Dorfstr. 22",
    "sg:city":"Erlangen",
    "sg:phone":"+49 9131/90200",
    "sg:postcode":"91056",
    "sg:province":"Bayern",
    "wof:name":"Peter Bretting Werkzeugbau Kg",
    "wof:placetype":"venue"
},
  "geometry": {"coordinates":[10.9654159546,49.5901222229],"type":"Point"}
}