{
  "type": "Feature",
  "properties": {
    "iso:country":"DE",
    "sg:address":"Libellenstr. 53",
    "sg:city":"H\u00f6now",
    "sg:phone":"+49 3342/305500",
    "sg:postcode":"15366",
    "sg:province":"Brandenburg",
    "wof:name":"Bau-kanzlei Bauplanungs- Gmbh",
    "wof:placetype":"venue"
},
  "geometry": {"coordinates":[13.653577,52.53051],"type":"Point"}
}