{
  "type": "Feature",
  "properties": {
    "iso:country":"DE",
    "sg:address":"Hauptstr. 23",
    "sg:city":"L\u00fcchow",
    "sg:phone":"+49 4536/8101",
    "sg:postcode":"23898",
    "sg:province":"Schleswig-Holstein",
    "wof:name":"Schornsteintechnik G\u00fcnter Redd\u00f6hl Gmbh",
    "wof:placetype":"venue"
},
  "geometry": {"coordinates":[10.526705,53.688488],"type":"Point"}
}