{
  "type": "Feature",
  "properties": {
    "iso:country":"DE",
    "sg:address":"Bergstr. 37",
    "sg:city":"Bausendorf",
    "sg:phone":"+49 6532/4674",
    "sg:postcode":"54538",
    "sg:province":"Rheinland-Pfalz",
    "wof:name":"Haus Bergfried Wohngruppen Gmbh",
    "wof:placetype":"venue"
},
  "geometry": {"coordinates":[6.9946599007,50.0154495239],"type":"Point"}
}