{
  "type": "Feature",
  "properties": {
    "iso:country":"DE",
    "sg:address":"D\u00fcrerstr. 30",
    "sg:city":"Plauen",
    "sg:postcode":"08527",
    "sg:province":"Sachsen",
    "wof:name":"Wolfram Ketzel",
    "wof:placetype":"venue"
},
  "geometry": {"coordinates":[12.130031,50.488834],"type":"Point"}
}