{
  "type": "Feature",
  "properties": {
    "iso:country":"DE",
    "sg:address":"Adalbert-Stifter-Str. 3",
    "sg:city":"Greding",
    "sg:phone":"+49 8463/1302",
    "sg:postcode":"91171",
    "sg:province":"Bayern",
    "wof:name":"Manfred Lange",
    "wof:placetype":"venue"
},
  "geometry": {"coordinates":[11.3652639389,49.0427017212],"type":"Point"}
}