{
  "type": "Feature",
  "properties": {
    "iso:country":"DE",
    "sg:address":"Murgtalstr. 22",
    "sg:city":"Murg",
    "sg:phone":"+49 7763/6455",
    "sg:postcode":"79730",
    "sg:province":"Baden-W\u00fcrttemberg",
    "wof:name":"Helmut Vetter",
    "wof:placetype":"venue"
},
  "geometry": {"coordinates":[8.022241,47.556553],"type":"Point"}
}