{
  "type": "Feature",
  "properties": {
    "iso:country":"DE",
    "sg:address":"Obertrennbach 33",
    "sg:city":"Gangkofen",
    "sg:phone":"+49 8722/529",
    "sg:postcode":"84140",
    "sg:province":"Bayern",
    "wof:name":"Bernhard Leitl",
    "wof:placetype":"venue"
},
  "geometry": {"coordinates":[12.561196,48.485115],"type":"Point"}
}