{
  "type": "Feature",
  "properties": {
    "iso:country":"DE",
    "sg:address":"Stargarder Str. 2",
    "sg:city":"Siegen",
    "sg:phone":"+49 271/310772",
    "sg:postcode":"57072",
    "sg:province":"Nordrhein-Westfalen",
    "wof:name":"Generalagentur Der W\u00fcrttem- Bergischen Versicherung Ag",
    "wof:placetype":"venue"
},
  "geometry": {"coordinates":[7.9941859245,50.8763198853],"type":"Point"}
}