{
  "type": "Feature",
  "properties": {
    "iso:country":"DE",
    "sg:address":"Bergbossendorf 24",
    "sg:city":"Haltern",
    "sg:phone":"+49 2364/3187",
    "sg:postcode":"45721",
    "sg:province":"Nordrhein-Westfalen",
    "wof:name":"Josef Ruppert",
    "wof:placetype":"venue"
},
  "geometry": {"coordinates":[7.146729,51.721939],"type":"Point"}
}