{
  "type": "Feature",
  "properties": {
    "iso:country":"DE",
    "sg:address":"Marktkirchhof 2",
    "sg:city":"Goslar",
    "sg:phone":"+49 5321/21051",
    "sg:postcode":"38640",
    "sg:province":"Niedersachsen",
    "wof:name":"Clemont Und B\u00f6ttcher Anwaltssoziet\u00e4t",
    "wof:placetype":"venue"
},
  "geometry": {"coordinates":[10.4280796051,51.9052734375],"type":"Point"}
}