{
  "type": "Feature",
  "properties": {
    "iso:country":"DE",
    "sg:address":"Landhausstr. 153",
    "sg:city":"Stuttgart",
    "sg:phone":"+49 711/264089",
    "sg:postcode":"70188",
    "sg:province":"Baden-W\u00fcrttemberg",
    "wof:name":"Susanne Prohl Krankengymnastin",
    "wof:placetype":"venue"
},
  "geometry": {"coordinates":[9.205007,48.786839],"type":"Point"}
}