{
  "type": "Feature",
  "properties": {
    "iso:country":"DE",
    "sg:address":"Vilbeler Landstr. 7",
    "sg:city":"Frankfurt",
    "sg:phone":"+49 69/425706",
    "sg:postcode":"60386",
    "sg:province":"Hessen",
    "wof:name":"La Vineria Dr. Peter Hilgard",
    "wof:placetype":"venue"
},
  "geometry": {"coordinates":[8.7661466599,50.1335868835],"type":"Point"}
}