{
  "type": "Feature",
  "properties": {
    "iso:country":"DE",
    "sg:address":"Danziger Weg 30",
    "sg:city":"Schramberg",
    "sg:phone":"+49 7422/6885",
    "sg:postcode":"78713",
    "sg:province":"Baden-W\u00fcrttemberg",
    "wof:name":"Tennis Squash Und Badminton Hans Kuret",
    "wof:placetype":"venue"
},
  "geometry": {"coordinates":[8.4246511459,48.2217636108],"type":"Point"}
}