{
  "type": "Feature",
  "properties": {
    "iso:country":"DE",
    "sg:address":"Friesdorfer Str. 3",
    "sg:city":"Bonn",
    "sg:phone":"+49 228/317750",
    "sg:postcode":"53173",
    "sg:province":"Nordrhein-Westfalen",
    "wof:name":"Restaurant Baja Sardinia",
    "wof:placetype":"venue"
},
  "geometry": {"coordinates":[7.152780056,50.6859512329],"type":"Point"}
}