{
  "type": "Feature",
  "properties": {
    "iso:country":"DE",
    "sg:address":"Schwedenstr. 23",
    "sg:city":"M\u00fcnchen",
    "sg:phone":"+49 89/3614388",
    "sg:postcode":"80805",
    "sg:province":"Bayern",
    "wof:name":"Dr. Martin Turck Rechtsanwalt",
    "wof:placetype":"venue"
},
  "geometry": {"coordinates":[11.6010828018,48.1663169861],"type":"Point"}
}