{
  "type": "Feature",
  "properties": {
    "iso:country":"DE",
    "sg:address":"Theodor-Heuss-Ring 1",
    "sg:city":"Dietzenbach",
    "sg:phone":"+49 6074/301803",
    "sg:postcode":"63128",
    "sg:province":"Hessen",
    "wof:name":"Quitschau & Sohn",
    "wof:placetype":"venue"
},
  "geometry": {"coordinates":[8.7835416794,50.0225715637],"type":"Point"}
}