{
  "type": "Feature",
  "properties": {
    "iso:country":"DE",
    "sg:address":"Nikolaiplatz 1 b",
    "sg:city":"M\u00fcnchen",
    "sg:phone":"+49 89/398682",
    "sg:postcode":"80802",
    "sg:province":"Bayern",
    "wof:name":"Frauen Wohnen Eg",
    "wof:placetype":"venue"
},
  "geometry": {"coordinates":[11.586206,48.158611],"type":"Point"}
}