{
  "type": "Feature",
  "properties": {
    "iso:country":"DE",
    "sg:address":"Motzstr.18",
    "sg:city":"Berlin",
    "sg:phone":"+49 30/2161220",
    "sg:postcode":"10777",
    "sg:province":"Berlin",
    "wof:name":"B\u00e4ckerei Paedelt",
    "wof:placetype":"venue"
},
  "geometry": {"coordinates":[13.3498706818,52.4985084534],"type":"Point"}
}