{
  "type": "Feature",
  "properties": {
    "iso:country":"DE",
    "sg:address":"Hauptstr. 7",
    "sg:city":"Asbach",
    "sg:phone":"+49 6786/7134",
    "sg:postcode":"55758",
    "sg:province":"Rheinland-Pfalz",
    "wof:name":"Schmucksteine Friedrich",
    "wof:placetype":"venue"
},
  "geometry": {"coordinates":[7.279056,49.812859],"type":"Point"}
}