{
  "type": "Feature",
  "properties": {
    "iso:country":"DE",
    "sg:address":"Akazienweg 43",
    "sg:city":"Bietigheim-Bissingen",
    "sg:phone":"+49 7142/3969",
    "sg:postcode":"74321",
    "sg:province":"Baden-W\u00fcrttemberg",
    "wof:name":"Manfred Pfisterer Architekt",
    "wof:placetype":"venue"
},
  "geometry": {"coordinates":[9.100641,48.941601],"type":"Point"}
}