{
  "type": "Feature",
  "properties": {
    "iso:country":"DE",
    "sg:address":"Haarschw\u00e4rze 11",
    "sg:city":"Borken",
    "sg:phone":"+49 5682/6641",
    "sg:postcode":"34582",
    "sg:province":"Hessen",
    "wof:name":"I. St. Johannis",
    "wof:placetype":"venue"
},
  "geometry": {"coordinates":[9.2523412704,51.0426902771],"type":"Point"}
}