{
  "type": "Feature",
  "properties": {
    "iso:country":"DE",
    "sg:address":"Halinger Dorfstr. 19",
    "sg:city":"Menden",
    "sg:phone":"+49 2378/5566",
    "sg:postcode":"58708",
    "sg:province":"Nordrhein-Westfalen",
    "wof:name":"C. Steiner-lorenz",
    "wof:placetype":"venue"
},
  "geometry": {"coordinates":[7.728,51.460423],"type":"Point"}
}