{
  "type": "Feature",
  "properties": {
    "iso:country":"DE",
    "sg:address":"Nobelstr. 5",
    "sg:city":"Ettlingen",
    "sg:phone":"+49 4972/4354060",
    "sg:postcode":"76275",
    "sg:province":"Baden-W\u00fcrttemberg",
    "wof:name":"Ing Julius Fien Gmbh",
    "wof:placetype":"venue"
},
  "geometry": {"coordinates":[8.376975,48.937168],"type":"Point"}
}