{
  "type": "Feature",
  "properties": {
    "iso:country":"DE",
    "sg:address":"Bahnhostr. 32",
    "sg:city":"Kevelaer",
    "sg:phone":"+49 4928/322481",
    "sg:postcode":"47625",
    "sg:province":"Nordrhein-Westfalen",
    "wof:name":"Rogmann Gmbh",
    "wof:placetype":"venue"
},
  "geometry": {"coordinates":[6.283134,51.551296],"type":"Point"}
}