{
  "type": "Feature",
  "properties": {
    "iso:country":"DE",
    "sg:address":"Marktplatz 4",
    "sg:city":"Suhlendorf",
    "sg:phone":"+49 5820/324",
    "sg:postcode":"29562",
    "sg:province":"Niedersachsen",
    "wof:name":"Bodo Hirse",
    "wof:placetype":"venue"
},
  "geometry": {"coordinates":[10.768727,52.92535],"type":"Point"}
}