{
  "type": "Feature",
  "properties": {
    "iso:country":"DE",
    "sg:address":"Poststr. 2",
    "sg:city":"Walsrode",
    "sg:phone":"+49 5161/8615",
    "sg:postcode":"29664",
    "sg:province":"Niedersachsen",
    "wof:name":"Pizzeria Juventus",
    "wof:placetype":"venue"
},
  "geometry": {"coordinates":[9.5934123993,52.8622169495],"type":"Point"}
}