{
  "type": "Feature",
  "properties": {
    "iso:country":"DE",
    "sg:address":"Schadowstr. 46",
    "sg:city":"D\u00fcsseldorf",
    "sg:phone":"+49 211/1793940",
    "sg:postcode":"40212",
    "sg:province":"Nordrhein-Westfalen",
    "wof:name":"Ihr Teststudio Betriebsgesellschaft Mbh",
    "wof:placetype":"venue"
},
  "geometry": {"coordinates":[6.78233,51.226238],"type":"Point"}
}