{
  "type": "Feature",
  "properties": {
    "iso:country":"DE",
    "sg:address":"Haingasse 6",
    "sg:city":"Bad Homburg",
    "sg:phone":"+49 6172/23324",
    "sg:postcode":"61348",
    "sg:province":"Hessen",
    "wof:name":"Piet\u00e4t Mest",
    "wof:placetype":"venue"
},
  "geometry": {"coordinates":[8.61243,50.228924],"type":"Point"}
}