{
  "type": "Feature",
  "properties": {
    "iso:country":"DE",
    "sg:address":"Fasanenweg 24",
    "sg:city":"Cloppenburg",
    "sg:phone":"+49 4471/3047",
    "sg:postcode":"49661",
    "sg:province":"Niedersachsen",
    "wof:name":"Alwin Bremer",
    "wof:placetype":"venue"
},
  "geometry": {"coordinates":[8.005812,52.842968],"type":"Point"}
}