{
  "type": "Feature",
  "properties": {
    "iso:country":"DE",
    "sg:address":"Schl\u00fcchterner Str. 37",
    "sg:city":"Sinntal",
    "sg:phone":"+49 6664/368",
    "sg:postcode":"36391",
    "sg:province":"Hessen",
    "wof:name":"Pension Marlies Alt",
    "wof:placetype":"venue"
},
  "geometry": {"coordinates":[9.6178274155,50.3149528503],"type":"Point"}
}