{
  "type": "Feature",
  "properties": {
    "iso:country":"DE",
    "sg:address":"Bleicherufer 5",
    "sg:city":"Schwerin",
    "sg:phone":"+49 385/569333",
    "sg:postcode":"19053",
    "sg:province":"Mecklenburg-Vorpommern",
    "wof:name":"Unternehmerverband Norddeutschland",
    "wof:placetype":"venue"
},
  "geometry": {"coordinates":[11.4017076492,53.6218147278],"type":"Point"}
}