{
  "type": "Feature",
  "properties": {
    "iso:country":"DE",
    "sg:address":"Frankenstr. 33",
    "sg:city":"Talheim",
    "sg:phone":"+49 7133/6803",
    "sg:postcode":"74388",
    "sg:province":"Baden-W\u00fcrttemberg",
    "wof:name":"Helmut Weber",
    "wof:placetype":"venue"
},
  "geometry": {"coordinates":[9.1886291504,49.0863456726],"type":"Point"}
}