{
  "type": "Feature",
  "properties": {
    "iso:country":"DE",
    "sg:address":"Lambertstr. 17",
    "sg:city":"Mainz",
    "sg:phone":"+49 6131/40231",
    "sg:postcode":"55126",
    "sg:province":"Rheinland-Pfalz",
    "wof:name":"Dieter Pfeifer",
    "wof:placetype":"venue"
},
  "geometry": {"coordinates":[8.1737003326,49.9852104187],"type":"Point"}
}