{
  "type": "Feature",
  "properties": {
    "iso:country":"DE",
    "sg:address":"Peterstr 3",
    "sg:city":"G\u00f6rlitz",
    "sg:phone":"+49 3581/406310",
    "sg:postcode":"02826",
    "sg:province":"Sachsen",
    "wof:name":"Isw Gmbh",
    "wof:placetype":"venue"
},
  "geometry": {"coordinates":[14.991234,51.157532],"type":"Point"}
}