{
  "type": "Feature",
  "properties": {
    "iso:country":"DE",
    "sg:address":"Allersberger Str. 28",
    "sg:city":"Roth",
    "sg:phone":"+49 9171/2273",
    "sg:postcode":"91154",
    "sg:province":"Bayern",
    "wof:name":"O. Bengel Steuerberater",
    "wof:placetype":"venue"
},
  "geometry": {"coordinates":[11.0954885483,49.2495422363],"type":"Point"}
}