{
  "type": "Feature",
  "properties": {
    "iso:country":"DE",
    "sg:address":"Kampstr. 30",
    "sg:city":"Lauenbr\u00fcck",
    "sg:phone":"+49 4267/1079",
    "sg:postcode":"27389",
    "sg:province":"Niedersachsen",
    "wof:name":"Manfred Krenz Gmbh",
    "wof:placetype":"venue"
},
  "geometry": {"coordinates":[9.5673112869,53.2003173828],"type":"Point"}
}