{
  "type": "Feature",
  "properties": {
    "iso:country":"DE",
    "sg:address":"Wallerfanger Str. 39",
    "sg:city":"Saarlouis",
    "sg:postcode":"66740",
    "sg:province":"Saarland",
    "wof:name":"Ochem Lb E. K.",
    "wof:placetype":"venue"
},
  "geometry": {"coordinates":[6.7312150002,49.3188972473],"type":"Point"}
}