{
  "type": "Feature",
  "properties": {
    "iso:country":"DE",
    "sg:address":"Trompetenberg 2",
    "sg:city":"Arzberg",
    "sg:phone":"+49 9233/8281",
    "sg:postcode":"95659",
    "sg:province":"Bayern",
    "wof:name":"Willi Bienfang",
    "wof:placetype":"venue"
},
  "geometry": {"coordinates":[12.185705,50.051212],"type":"Point"}
}