{
  "type": "Feature",
  "properties": {
    "iso:country":"DE",
    "sg:address":"Am Alten Hafen 113-115",
    "sg:city":"Bremerhaven",
    "sg:postcode":"27568",
    "sg:province":"Bremen",
    "wof:name":"Presseklub Bremerhaven",
    "wof:placetype":"venue"
},
  "geometry": {"coordinates":[8.5780096054,53.5431785583],"type":"Point"}
}