{
  "type": "Feature",
  "properties": {
    "iso:country":"DE",
    "sg:address":"Grabenstr. 18",
    "sg:city":"Brandenburg",
    "sg:phone":"+49 3381/229906",
    "sg:postcode":"14776",
    "sg:province":"Brandenburg",
    "wof:name":"Projektentwicklung Mario Mischker E. K.",
    "wof:placetype":"venue"
},
  "geometry": {"coordinates":[12.5565366745,52.4090614319],"type":"Point"}
}