{
  "type": "Feature",
  "properties": {
    "iso:country":"DE",
    "sg:address":"Birkenweg 22",
    "sg:city":"Dielheim",
    "sg:phone":"+49 6222/70846",
    "sg:postcode":"69234",
    "sg:province":"Baden-W\u00fcrttemberg",
    "wof:name":"Joh. Payer",
    "wof:placetype":"venue"
},
  "geometry": {"coordinates":[8.784647,49.283707],"type":"Point"}
}