{
  "type": "Feature",
  "properties": {
    "iso:country":"DE",
    "sg:address":"Gro\u00dfe Allee 43",
    "sg:city":"Dillingen",
    "sg:phone":"+49 9071/4747",
    "sg:postcode":"89407",
    "sg:province":"Bayern",
    "wof:name":"Ludwig D\u00fcthorn",
    "wof:placetype":"venue"
},
  "geometry": {"coordinates":[10.493351,48.581036],"type":"Point"}
}