{
  "type": "Feature",
  "properties": {
    "iso:country":"DE",
    "sg:address":"Altvaterstr. 110",
    "sg:city":"Kelheim",
    "sg:phone":"+49 9441/7500",
    "sg:postcode":"93309",
    "sg:province":"Bayern",
    "wof:name":"Skih\u00fctte",
    "wof:placetype":"venue"
},
  "geometry": {"coordinates":[11.8851804733,48.9050292969],"type":"Point"}
}