{
  "type": "Feature",
  "properties": {
    "iso:country":"DE",
    "sg:address":"Hauptstr. 9",
    "sg:city":"Perd\u00f6hl",
    "sg:postcode":"19243",
    "sg:province":"Mecklenburg-Vorpommern",
    "wof:name":"Katholisches Pfarramt Z\u00fchr",
    "wof:placetype":"venue"
},
  "geometry": {"coordinates":[11.0509033203,53.4663200378],"type":"Point"}
}