{
  "type": "Feature",
  "properties": {
    "iso:country":"DE",
    "sg:address":"Herderstr. 24",
    "sg:city":"Pfungstadt",
    "sg:phone":"+49 6157/990908",
    "sg:postcode":"64319",
    "sg:province":"Hessen",
    "wof:name":"Theodor Keppel Ingenieur",
    "wof:placetype":"venue"
},
  "geometry": {"coordinates":[8.6114692688,49.8064231873],"type":"Point"}
}