{
  "type": "Feature",
  "properties": {
    "iso:country":"DE",
    "sg:address":"Schlo\u00dfgarten 1",
    "sg:city":"T\u00f6nning",
    "sg:phone":"+49 4861/6160",
    "sg:postcode":"25832",
    "sg:province":"Schleswig-Holstein",
    "wof:name":"Nationalparkservice Ggmbh",
    "wof:placetype":"venue"
},
  "geometry": {"coordinates":[8.9421348572,54.3155975342],"type":"Point"}
}