{
  "type": "Feature",
  "properties": {
    "iso:country":"DE",
    "sg:address":"Herner Str. 47",
    "sg:city":"Herten",
    "sg:phone":"+49 2366/35264",
    "sg:postcode":"45699",
    "sg:province":"Nordrhein-Westfalen",
    "wof:name":"Heide-apotheke Dorothea Winter Apothekerin",
    "wof:placetype":"venue"
},
  "geometry": {"coordinates":[7.153162,51.581966],"type":"Point"}
}