{
  "type": "Feature",
  "properties": {
    "iso:country":"DE",
    "sg:address":"Richardstr.15",
    "sg:city":"Aachen",
    "sg:phone":"+49 241",
    "sg:postcode":"52062",
    "sg:province":"Nordrhein-Westfalen",
    "wof:name":"Zahnarztdr.wolfganghahn",
    "wof:placetype":"venue"
},
  "geometry": {"coordinates":[6.093201,50.771652],"type":"Point"}
}