{
  "type": "Feature",
  "properties": {
    "iso:country":"DE",
    "sg:address":"Moltkestr. 41",
    "sg:city":"Schleswig",
    "sg:phone":"+49 4621/9060",
    "sg:postcode":"24837",
    "sg:province":"Schleswig-Holstein",
    "wof:name":"Hotel Hohenzollern Inh. Uwe Lueth",
    "wof:placetype":"venue"
},
  "geometry": {"coordinates":[9.5566558838,54.5212402344],"type":"Point"}
}