{
  "type": "Feature",
  "properties": {
    "iso:country":"DE",
    "sg:address":"Eberstal",
    "sg:city":"Heidenheim",
    "sg:phone":"+49 7367/7488",
    "sg:postcode":"89520",
    "sg:province":"Baden-W\u00fcrttemberg",
    "wof:name":"Vereinsgastst\u00e4tte Sportverein Gro\u00dfkuchen E. V.",
    "wof:placetype":"venue"
},
  "geometry": {"coordinates":[10.1936302185,48.7323684692],"type":"Point"}
}