{
  "type": "Feature",
  "properties": {
    "iso:country":"DE",
    "sg:address":"Altwingertweg 10",
    "sg:city":"Hockenheim",
    "sg:phone":"+49 6205/15647",
    "sg:postcode":"68766",
    "sg:province":"Baden-W\u00fcrttemberg",
    "wof:name":"Eks-verlag Erika K\u00fcbeck-seidel E. K.",
    "wof:placetype":"venue"
},
  "geometry": {"coordinates":[8.5335741043,49.3225212097],"type":"Point"}
}