{
  "type": "Feature",
  "properties": {
    "iso:country":"DE",
    "sg:address":"Dekan-Imminger-Str. 4",
    "sg:city":"Holzkirchen",
    "sg:phone":"+49 8024/7050",
    "sg:postcode":"83607",
    "sg:province":"Bayern",
    "wof:name":"Rudolf Smolka Architekt",
    "wof:placetype":"venue"
},
  "geometry": {"coordinates":[11.694225,47.881783],"type":"Point"}
}