{
  "type": "Feature",
  "properties": {
    "iso:country":"DE",
    "sg:address":"Ostenhellweg 39",
    "sg:city":"Dortmund",
    "sg:phone":"+49 231/527381",
    "sg:postcode":"44135",
    "sg:province":"Nordrhein-Westfalen",
    "wof:name":"M & S Mode Gmbh",
    "wof:placetype":"venue"
},
  "geometry": {"coordinates":[7.470665,51.514114],"type":"Point"}
}