{
  "type": "Feature",
  "properties": {
    "iso:country":"DE",
    "sg:address":"Hindelanger Str. 29",
    "sg:city":"Hindelang",
    "sg:phone":"+49 8324/2081",
    "sg:postcode":"87541",
    "sg:province":"Bayern",
    "wof:name":"Leder-eberhard Gmbh",
    "wof:placetype":"venue"
},
  "geometry": {"coordinates":[10.378208,47.504478],"type":"Point"}
}