{
  "type": "Feature",
  "properties": {
    "iso:country":"DE",
    "sg:address":"Gerstmayrstr 6::",
    "sg:city":"Neu-Ulm",
    "sg:postcode":"89233",
    "sg:province":"Bayern",
    "wof:name":"Raiffeisenbank Burlafingen Eg",
    "wof:placetype":"venue"
},
  "geometry": {"coordinates":[10.067805,48.413834],"type":"Point"}
}