{
  "type": "Feature",
  "properties": {
    "iso:country":"DE",
    "sg:address":"Bahnhofstr. 96",
    "sg:city":"Gangelt",
    "sg:phone":"+49 2454/8895",
    "sg:postcode":"52538",
    "sg:province":"Nordrhein-Westfalen",
    "wof:name":"Pizzeria Roma",
    "wof:placetype":"venue"
},
  "geometry": {"coordinates":[6.0556340218,51.0091247559],"type":"Point"}
}