{
  "type": "Feature",
  "properties": {
    "iso:country":"DE",
    "sg:address":"Mittelstr. 18",
    "sg:city":"Bad W\u00fcnnenberg",
    "sg:phone":"+49 2953/372",
    "sg:postcode":"33181",
    "sg:province":"Nordrhein-Westfalen",
    "wof:name":"Georg Bernard",
    "wof:placetype":"venue"
},
  "geometry": {"coordinates":[8.7005910873,51.5213012695],"type":"Point"}
}