{
  "type": "Feature",
  "properties": {
    "iso:country":"DE",
    "sg:address":"Schulstr. 7",
    "sg:city":"Marbach",
    "sg:phone":"+49 7144/15557",
    "sg:postcode":"71672",
    "sg:province":"Baden-W\u00fcrttemberg",
    "wof:name":"Zimmerei Schmid",
    "wof:placetype":"venue"
},
  "geometry": {"coordinates":[9.4737157822,48.0628852844],"type":"Point"}
}