{
  "type": "Feature",
  "properties": {
    "iso:country":"DE",
    "sg:address":"Am Wandrahm 23",
    "sg:city":"Bremen",
    "sg:phone":"+49 421/3089017",
    "sg:postcode":"28195",
    "sg:province":"Bremen",
    "wof:name":"Universit\u00e4t Bremen Bibliothek An Der",
    "wof:placetype":"venue"
},
  "geometry": {"coordinates":[8.801715,53.083012],"type":"Point"}
}