{
  "type": "Feature",
  "properties": {
    "iso:country":"DE",
    "sg:address":"Feldchenstr. 56",
    "sg:city":"Aschaffenburg",
    "sg:phone":"+49 6021/94174",
    "sg:postcode":"63743",
    "sg:province":"Bayern",
    "wof:name":"Margarete Und Gerd Braun",
    "wof:placetype":"venue"
},
  "geometry": {"coordinates":[9.166546,49.952244],"type":"Point"}
}