{
  "type": "Feature",
  "properties": {
    "iso:country":"DE",
    "sg:address":"Oststr. 2",
    "sg:city":"Seifhennersdorf",
    "sg:postcode":"02782",
    "sg:province":"Sachsen",
    "wof:name":"Badeinrichtung Ute Schiffner Gbr",
    "wof:placetype":"venue"
},
  "geometry": {"coordinates":[14.6221780777,50.9355659485],"type":"Point"}
}