{
  "type": "Feature",
  "properties": {
    "iso:country":"DE",
    "sg:address":"R\u00f6merwall 53",
    "sg:city":"Mainz",
    "sg:phone":"+49 6131/232135",
    "sg:postcode":"55131",
    "sg:province":"Rheinland-Pfalz",
    "wof:name":"Hotel Am R\u00f6merwall",
    "wof:placetype":"venue"
},
  "geometry": {"coordinates":[8.2584848404,49.9967956543],"type":"Point"}
}