{
  "type": "Feature",
  "properties": {
    "iso:country":"DE",
    "sg:address":"Eichendorffallee 7",
    "sg:city":"Schifferstadt",
    "sg:phone":"+49 6235/5666",
    "sg:postcode":"67105",
    "sg:province":"Rheinland-Pfalz",
    "wof:name":"August Rosenkranz Architekt",
    "wof:placetype":"venue"
},
  "geometry": {"coordinates":[8.377809,49.368538],"type":"Point"}
}