{
  "type": "Feature",
  "properties": {
    "iso:country":"DE",
    "sg:address":"Treckgasse 26",
    "sg:city":"Euskirchen",
    "sg:phone":"+49 2251/58299",
    "sg:postcode":"53881",
    "sg:province":"Nordrhein-Westfalen",
    "wof:name":"K\u00fcpper & Hoffmann Ohg",
    "wof:placetype":"venue"
},
  "geometry": {"coordinates":[6.7383489609,50.6486206055],"type":"Point"}
}