{
  "type": "Feature",
  "properties": {
    "iso:country":"DE",
    "sg:address":"Wittland 14-18",
    "sg:city":"Kiel",
    "sg:phone":"+49 431/58630",
    "sg:postcode":"24109",
    "sg:province":"Schleswig-Holstein",
    "wof:name":"Paulsen & Br\u00e4uninger Gmbh",
    "wof:placetype":"venue"
},
  "geometry": {"coordinates":[10.0804128647,54.3266296387],"type":"Point"}
}