{
  "type": "Feature",
  "properties": {
    "iso:country":"DE",
    "sg:address":"R\u00fcdesheimer Ring 73",
    "sg:city":"Euskirchen",
    "sg:phone":"+49 2251/71310",
    "sg:postcode":"53879",
    "sg:province":"Nordrhein-Westfalen",
    "wof:name":"Lets Play Automatenbetriebe R\u00f6hring Ohg",
    "wof:placetype":"venue"
},
  "geometry": {"coordinates":[6.7840299606,50.6602210999],"type":"Point"}
}