{
  "type": "Feature",
  "properties": {
    "iso:country":"DE",
    "sg:address":"Eiterbachstr. 23",
    "sg:city":"Wald-Michelbach",
    "sg:phone":"+49 6207/6912",
    "sg:postcode":"69483",
    "sg:province":"Hessen",
    "wof:name":"Joze Petkovsek Elektoinstallation",
    "wof:placetype":"venue"
},
  "geometry": {"coordinates":[8.810552,49.546886],"type":"Point"}
}