{
  "type": "Feature",
  "properties": {
    "iso:country":"DE",
    "sg:address":"Luftbad 2",
    "sg:city":"Todtmoos",
    "sg:phone":"+49 7674/542",
    "sg:postcode":"79682",
    "sg:province":"Baden-W\u00fcrttemberg",
    "wof:name":"Friedrich Maier",
    "wof:placetype":"venue"
},
  "geometry": {"coordinates":[8.004188,47.732601],"type":"Point"}
}