{
  "type": "Feature",
  "properties": {
    "iso:country":"DE",
    "sg:address":"Lange Str. 79",
    "sg:city":"Schlieben",
    "sg:phone":"+49 35361/80130",
    "sg:postcode":"04936",
    "sg:province":"Brandenburg",
    "wof:name":"S. Lunter",
    "wof:placetype":"venue"
},
  "geometry": {"coordinates":[13.382186,51.724491],"type":"Point"}
}