{
  "type": "Feature",
  "properties": {
    "iso:country":"DE",
    "sg:address":"Steilstr. 15",
    "sg:city":"Bochum",
    "sg:phone":"+49 234/799838",
    "sg:postcode":"44797",
    "sg:province":"Nordrhein-Westfalen",
    "wof:name":"G\u00fcnter Scheuer",
    "wof:placetype":"venue"
},
  "geometry": {"coordinates":[7.2450270653,51.4277610779],"type":"Point"}
}