{
  "type": "Feature",
  "properties": {
    "iso:country":"DE",
    "sg:address":"Zwickauer Str. 10",
    "sg:city":"Chemnitz",
    "sg:postcode":"09112",
    "sg:province":"Sachsen",
    "wof:name":"Haiky International Gmbh",
    "wof:placetype":"venue"
},
  "geometry": {"coordinates":[12.9148731232,50.8290634155],"type":"Point"}
}