{
  "type": "Feature",
  "properties": {
    "iso:country":"DE",
    "sg:address":"Obere Hauptstr. 118",
    "sg:city":"Worms",
    "sg:phone":"+49 4962/413111",
    "sg:postcode":"67551",
    "sg:province":"Rheinland-Pfalz",
    "wof:name":"Familienweinkellereiras Tadeus Gmbh",
    "wof:placetype":"venue"
},
  "geometry": {"coordinates":[8.3054,49.611725],"type":"Point"}
}