{
  "type": "Feature",
  "properties": {
    "iso:country":"DE",
    "sg:address":"Kirchgasse 18",
    "sg:city":"Estenfeld",
    "sg:phone":"+49 9305/349",
    "sg:postcode":"97230",
    "sg:province":"Bayern",
    "wof:name":"W. Bayer",
    "wof:placetype":"venue"
},
  "geometry": {"coordinates":[10.0089683533,49.8301048279],"type":"Point"}
}