{
  "type": "Feature",
  "properties": {
    "iso:country":"DE",
    "sg:address":"Eschersheimer Landstr. 46",
    "sg:city":"Frankfurt",
    "sg:phone":"+49 69/594662",
    "sg:postcode":"60322",
    "sg:province":"Hessen",
    "wof:name":"Pizzeria San Marco",
    "wof:placetype":"venue"
},
  "geometry": {"coordinates":[8.6757001877,50.1208610535],"type":"Point"}
}