{
  "type": "Feature",
  "properties": {
    "iso:country":"DE",
    "sg:address":"Max-Eyth-Str. 29",
    "sg:city":"Kirchheim",
    "sg:phone":"+49 7021/6553",
    "sg:postcode":"73230",
    "sg:province":"Baden-W\u00fcrttemberg",
    "wof:name":"E. Kreyscher",
    "wof:placetype":"venue"
},
  "geometry": {"coordinates":[9.4517612457,48.6485977173],"type":"Point"}
}