{
  "type": "Feature",
  "properties": {
    "iso:country":"DE",
    "sg:address":"Hauptstr. 37",
    "sg:city":"Menden",
    "sg:phone":"+49 2373/15449",
    "sg:postcode":"58706",
    "sg:province":"Nordrhein-Westfalen",
    "wof:name":"Klems Gmbh",
    "wof:placetype":"venue"
},
  "geometry": {"coordinates":[7.79541,51.437569],"type":"Point"}
}