{
  "type": "Feature",
  "properties": {
    "iso:country":"DE",
    "sg:address":"Rosenst\u00fcckerweg 16",
    "sg:city":"Rockenhausen",
    "sg:phone":"+49 6361/1769",
    "sg:postcode":"67806",
    "sg:province":"Rheinland-Pfalz",
    "wof:name":"Anno U. Klaus Frenger Tischlerei",
    "wof:placetype":"venue"
},
  "geometry": {"coordinates":[7.78986,49.612652],"type":"Point"}
}