{
  "type": "Feature",
  "properties": {
    "iso:country":"DE",
    "sg:address":"Oberm\u00fcnchen",
    "sg:city":"Obers\u00fc\u00dfbach",
    "sg:phone":"+49 8708/354",
    "sg:postcode":"84101",
    "sg:province":"Bayern",
    "wof:name":"A. Radlmeier",
    "wof:placetype":"venue"
},
  "geometry": {"coordinates":[11.9417600632,48.5835113525],"type":"Point"}
}