{
  "type": "Feature",
  "properties": {
    "iso:country":"DE",
    "sg:address":"Hauptstr. 68",
    "sg:city":"Lilienthal",
    "sg:phone":"+49 4298/1663",
    "sg:postcode":"28865",
    "sg:province":"Niedersachsen",
    "wof:name":"Gastst\u00e4tte Fegefeuer",
    "wof:placetype":"venue"
},
  "geometry": {"coordinates":[8.9079589844,53.1411476135],"type":"Point"}
}