{
  "type": "Feature",
  "properties": {
    "iso:country":"DE",
    "sg:address":"Walter-Freitag-Str. 3",
    "sg:city":"Remscheid",
    "sg:postcode":"42899",
    "sg:province":"Nordrhein-Westfalen",
    "wof:name":"Girolstein & Bayer Gmbh",
    "wof:placetype":"venue"
},
  "geometry": {"coordinates":[7.238043,51.221855],"type":"Point"}
}