{
  "type": "Feature",
  "properties": {
    "iso:country":"DE",
    "sg:address":"Dieselstr. 2",
    "sg:city":"K\u00fchbach",
    "sg:phone":"+49 8251/87310",
    "sg:postcode":"86556",
    "sg:province":"Bayern",
    "wof:name":"F\u00f6rster Formen Gmbh",
    "wof:placetype":"venue"
},
  "geometry": {"coordinates":[11.180984,48.495644],"type":"Point"}
}