{
  "type": "Feature",
  "properties": {
    "iso:country":"DE",
    "sg:address":"M\u00fchlenstr. 9",
    "sg:city":"Beverungen",
    "sg:phone":"+49 5273/21441",
    "sg:postcode":"37688",
    "sg:province":"Nordrhein-Westfalen",
    "wof:name":"Martina Radtke",
    "wof:placetype":"venue"
},
  "geometry": {"coordinates":[9.374906,51.665375],"type":"Point"}
}