{
  "type": "Feature",
  "properties": {
    "iso:country":"DE",
    "sg:address":"18528",
    "sg:city":"Zirkow",
    "sg:postcode":"18528",
    "sg:province":"Mecklenburg-Vorpommern",
    "wof:name":"Ev.-luth. Kirche",
    "wof:placetype":"venue"
},
  "geometry": {"coordinates":[13.5391149521,54.3902397156],"type":"Point"}
}