{
  "type": "Feature",
  "properties": {
    "iso:country":"DE",
    "sg:address":"Manderscheidtstr. 16-18",
    "sg:city":"Essen",
    "sg:phone":"+49 201/89170",
    "sg:postcode":"45141",
    "sg:province":"Nordrhein-Westfalen",
    "wof:name":"Hans-joachim Schrader Industriefahrzeuge",
    "wof:placetype":"venue"
},
  "geometry": {"coordinates":[7.049197197,51.4689865112],"type":"Point"}
}