{
  "type": "Feature",
  "properties": {
    "iso:country":"DE",
    "sg:address":"Hauptstr. 62 a",
    "sg:city":"Herzfelde",
    "sg:phone":"+49 33434/8884",
    "sg:postcode":"15378",
    "sg:province":"Brandenburg",
    "wof:name":"Bfb B\u00fcroservice Und Finanzbuchhaltung Gmbh",
    "wof:placetype":"venue"
},
  "geometry": {"coordinates":[13.8501157761,52.4820594788],"type":"Point"}
}