{
  "type": "Feature",
  "properties": {
    "iso:country":"DE",
    "sg:address":"Bahnhofstr. 8",
    "sg:city":"Brockel",
    "sg:phone":"+49 4266/1273",
    "sg:postcode":"27386",
    "sg:province":"Niedersachsen",
    "wof:name":"J. Possegger",
    "wof:placetype":"venue"
},
  "geometry": {"coordinates":[9.51537,53.087158],"type":"Point"}
}