{
  "type": "Feature",
  "properties": {
    "iso:country":"DE",
    "sg:address":"Carl-August-Allee 17",
    "sg:city":"Weimar",
    "sg:phone":"+49 3643",
    "sg:postcode":"99423",
    "sg:province":"Th\u00fcringen",
    "wof:name":"Intercity-hotel Weimar",
    "wof:placetype":"venue"
},
  "geometry": {"coordinates":[11.3261737823,50.9902191162],"type":"Point"}
}