{
  "type": "Feature",
  "properties": {
    "iso:country":"DE",
    "sg:address":"Birkenweg 8",
    "sg:city":"Bietigheim",
    "sg:postcode":"76467",
    "sg:province":"Baden-W\u00fcrttemberg",
    "wof:name":"Handelsvertretung Jonczik",
    "wof:placetype":"venue"
},
  "geometry": {"coordinates":[8.2473020554,48.9038467407],"type":"Point"}
}