{
  "type": "Feature",
  "properties": {
    "iso:country":"DE",
    "sg:address":"Untermarkt 7",
    "sg:city":"Murnau",
    "sg:postcode":"82418",
    "sg:province":"Bayern",
    "wof:name":"B\u00e4uerliche Hackschnitzel Liefergesellschaft Mbh",
    "wof:placetype":"venue"
},
  "geometry": {"coordinates":[11.2010498047,47.6778755188],"type":"Point"}
}