{
  "type": "Feature",
  "properties": {
    "iso:country":"DE",
    "sg:address":"D\u00fcrener Str. 15",
    "sg:city":"Titz",
    "sg:phone":"+49 2463/8829",
    "sg:postcode":"52445",
    "sg:province":"Nordrhein-Westfalen",
    "wof:name":"Hubert Laut Gmbh",
    "wof:placetype":"venue"
},
  "geometry": {"coordinates":[6.4368019104,50.9846687317],"type":"Point"}
}