{
  "type": "Feature",
  "properties": {
    "iso:country":"DE",
    "sg:address":"Wilhelmstr. 11",
    "sg:city":"M\u00fchlacker",
    "sg:phone":"+49 7041/3066",
    "sg:postcode":"75417",
    "sg:province":"Baden-W\u00fcrttemberg",
    "wof:name":"Elektro Sch\u00e4fter Gmbh",
    "wof:placetype":"venue"
},
  "geometry": {"coordinates":[8.864292,48.933456],"type":"Point"}
}