{
  "type": "Feature",
  "properties": {
    "iso:country":"DE",
    "sg:address":"Riesebergstr. 51",
    "sg:city":"Mieste",
    "sg:phone":"+49 39082/493",
    "sg:postcode":"39649",
    "sg:province":"Sachsen-Anhalt",
    "wof:name":"E. Schwarz",
    "wof:placetype":"venue"
},
  "geometry": {"coordinates":[11.204881,52.478867],"type":"Point"}
}