{
  "type": "Feature",
  "properties": {
    "iso:country":"DE",
    "sg:address":"In der Flur 7",
    "sg:city":"Damme",
    "sg:phone":"+49 5491/4242",
    "sg:postcode":"49401",
    "sg:province":"Niedersachsen",
    "wof:name":"Stefan Bell",
    "wof:placetype":"venue"
},
  "geometry": {"coordinates":[8.194619,52.52512],"type":"Point"}
}