{
  "type": "Feature",
  "properties": {
    "iso:country":"DE",
    "sg:address":"Stefansbecke 42",
    "sg:city":"Sprockh\u00f6vel",
    "sg:phone":"+49 2339/12090",
    "sg:postcode":"45549",
    "sg:province":"Nordrhein-Westfalen",
    "wof:name":"Axel Semrau Gmbh & Co.",
    "wof:placetype":"venue"
},
  "geometry": {"coordinates":[7.277854,51.319904],"type":"Point"}
}