{
  "type": "Feature",
  "properties": {
    "iso:country":"DE",
    "sg:address":"Brunnengasse 24",
    "sg:city":"F\u00fcssen",
    "sg:phone":"+49 8362/6139",
    "sg:postcode":"87629",
    "sg:province":"Bayern",
    "wof:name":"Albert Schinagl",
    "wof:placetype":"venue"
},
  "geometry": {"coordinates":[10.701205,47.568413],"type":"Point"}
}