{
  "type": "Feature",
  "properties": {
    "iso:country":"DE",
    "sg:address":"Marienstr. 7",
    "sg:city":"Wachtberg",
    "sg:phone":"+49 228/344719",
    "sg:postcode":"53343",
    "sg:province":"Nordrhein-Westfalen",
    "wof:name":"U. Tegethoff",
    "wof:placetype":"venue"
},
  "geometry": {"coordinates":[7.160050869,50.6482887268],"type":"Point"}
}