{
  "type": "Feature",
  "properties": {
    "iso:country":"DE",
    "sg:address":"Westerlund 4",
    "sg:city":"Handewitt",
    "sg:phone":"+49 4608/96242",
    "sg:postcode":"24983",
    "sg:province":"Schleswig-Holstein",
    "wof:name":"Hans J\u00fcrgensen",
    "wof:placetype":"venue"
},
  "geometry": {"coordinates":[9.2836952209,54.7571792603],"type":"Point"}
}