{
  "type": "Feature",
  "properties": {
    "iso:country":"DE",
    "sg:address":"Ringstr. 7",
    "sg:city":"Lich",
    "sg:phone":"+49 6404/5167",
    "sg:postcode":"35423",
    "sg:province":"Hessen",
    "wof:name":"Kr\u00f6ber Gmbh",
    "wof:placetype":"venue"
},
  "geometry": {"coordinates":[8.8226575851,50.5161437988],"type":"Point"}
}