{
  "type": "Feature",
  "properties": {
    "iso:country":"DE",
    "sg:address":"Rauensteinstr. 70",
    "sg:city":"\u00dcberlingen",
    "sg:postcode":"88662",
    "sg:province":"Baden-W\u00fcrttemberg",
    "wof:name":"Grundst\u00fccksgesellschaft Appelt Ohg",
    "wof:placetype":"venue"
},
  "geometry": {"coordinates":[9.1774044037,47.76404953],"type":"Point"}
}