{
  "type": "Feature",
  "properties": {
    "iso:country":"DE",
    "sg:address":"Kalandstr. 16",
    "sg:city":"Celle",
    "sg:phone":"+49 5141/85708",
    "sg:postcode":"29227",
    "sg:province":"Niedersachsen",
    "wof:name":"Hj. Knoop",
    "wof:placetype":"venue"
},
  "geometry": {"coordinates":[10.119703,52.602222],"type":"Point"}
}