{
  "type": "Feature",
  "properties": {
    "iso:country":"DE",
    "sg:address":"Heinrich-Hertz-Str. 17",
    "sg:city":"Langen",
    "sg:phone":"+49 6103/7570",
    "sg:postcode":"63225",
    "sg:province":"Hessen",
    "wof:name":"Optovision Gesellschaft F\u00fcr Moderne Brillenglastechnik Mbh",
    "wof:placetype":"venue"
},
  "geometry": {"coordinates":[8.655349,50.005306],"type":"Point"}
}