{
  "type": "Feature",
  "properties": {
    "iso:country":"DE",
    "sg:address":"Brinkstr. 20",
    "sg:city":"Greifswald",
    "sg:postcode":"17489",
    "sg:province":"Mecklenburg-Vorpommern",
    "wof:name":"Schmidt Verwaltungs Gmbh Objektbau",
    "wof:placetype":"venue"
},
  "geometry": {"coordinates":[13.3857746124,54.0911064148],"type":"Point"}
}