{
  "type": "Feature",
  "properties": {
    "iso:country":"DE",
    "sg:address":"Drohe",
    "sg:city":"Wieren",
    "sg:phone":"+49 5825/1589",
    "sg:postcode":"29568",
    "sg:province":"Niedersachsen",
    "wof:name":"Dieter Schulz",
    "wof:placetype":"venue"
},
  "geometry": {"coordinates":[10.693677,52.89048],"type":"Point"}
}