{
  "type": "Feature",
  "properties": {
    "iso:country":"DE",
    "sg:address":"Zum Alten Hofgarten 4",
    "sg:city":"Landau",
    "sg:phone":"+49 9951/7016",
    "sg:postcode":"94405",
    "sg:province":"Bayern",
    "wof:name":"Bernkopf N\u00e4hmaschinen Gmbh",
    "wof:placetype":"venue"
},
  "geometry": {"coordinates":[12.6923122406,48.6669769287],"type":"Point"}
}