{
  "type": "Feature",
  "properties": {
    "iso:country":"DE",
    "sg:address":"Ludwig-Reinhard-Str. 1",
    "sg:city":"Boizenburg",
    "sg:phone":"+49 38847/59714",
    "sg:postcode":"19258",
    "sg:province":"Mecklenburg-Vorpommern",
    "wof:name":"Bruno Hoffmann",
    "wof:placetype":"venue"
},
  "geometry": {"coordinates":[10.727109,53.385727],"type":"Point"}
}