{
  "type": "Feature",
  "properties": {
    "iso:country":"DE",
    "sg:address":"Franz-Schubert-Stra\u00dfe 9",
    "sg:city":"Zw\u00f6nitz",
    "sg:phone":"+49 37754",
    "sg:postcode":"08297",
    "sg:province":"Sachsen",
    "wof:name":"Viehweger Leuchten Gmbh",
    "wof:placetype":"venue"
},
  "geometry": {"coordinates":[12.806096,50.633461],"type":"Point"}
}