{
  "type": "Feature",
  "properties": {
    "iso:country":"DE",
    "sg:address":"Rheinhessenstr. 61",
    "sg:city":"Bad Kreuznach",
    "sg:phone":"+49 671/61413",
    "sg:postcode":"55545",
    "sg:province":"Rheinland-Pfalz",
    "wof:name":"Friedrich Heintz",
    "wof:placetype":"venue"
},
  "geometry": {"coordinates":[7.914657,49.845139],"type":"Point"}
}