{
  "type": "Feature",
  "properties": {
    "iso:country":"DE",
    "sg:address":"Billwerder Billdeich 626",
    "sg:city":"Hamburg",
    "sg:phone":"+49 40/7218784",
    "sg:postcode":"21033",
    "sg:province":"Hamburg",
    "wof:name":"Richard Bruns",
    "wof:placetype":"venue"
},
  "geometry": {"coordinates":[10.17052,53.503151],"type":"Point"}
}