{
  "type": "Feature",
  "properties": {
    "iso:country":"DE",
    "sg:address":"Austr. 3",
    "sg:city":"Schwendi",
    "sg:phone":"+49 7347/7330",
    "sg:postcode":"88477",
    "sg:province":"Baden-W\u00fcrttemberg",
    "wof:name":"Franz Wohnhas",
    "wof:placetype":"venue"
},
  "geometry": {"coordinates":[10.0142946243,48.2133865356],"type":"Point"}
}