{
  "type": "Feature",
  "properties": {
    "iso:country":"DE",
    "sg:address":"Holzmarkt 23",
    "sg:city":"Bautzen",
    "sg:phone":"+49 3591/490432",
    "sg:postcode":"02625",
    "sg:province":"Sachsen",
    "wof:name":"Nachtclub Blue Angel",
    "wof:placetype":"venue"
},
  "geometry": {"coordinates":[14.434184,51.181778],"type":"Point"}
}