{
  "type": "Feature",
  "properties": {
    "iso:country":"DE",
    "sg:address":"An den Bodewiesen 8",
    "sg:city":"Hecklingen",
    "sg:phone":"+49 3925/282270",
    "sg:postcode":"39444",
    "sg:province":"Sachsen-Anhalt",
    "wof:name":"Weiss Sonnenschutzanlagen Gmbh",
    "wof:placetype":"venue"
},
  "geometry": {"coordinates":[11.536151,51.858063],"type":"Point"}
}