{
  "type": "Feature",
  "properties": {
    "iso:country":"DE",
    "sg:address":"Schulstr. 86",
    "sg:city":"Bad Oeynhausen",
    "sg:phone":"+49 5731/92589",
    "sg:postcode":"32547",
    "sg:province":"Nordrhein-Westfalen",
    "wof:name":"Friedrich Brandt",
    "wof:placetype":"venue"
},
  "geometry": {"coordinates":[8.813544,52.195625],"type":"Point"}
}