{
  "type": "Feature",
  "properties": {
    "iso:country":"DE",
    "sg:address":"Bertsdorfer Str. 12",
    "sg:city":"Olbersdorf",
    "sg:phone":"+49 3583/690439",
    "sg:postcode":"02785",
    "sg:province":"Sachsen",
    "wof:name":"Christine Hummel",
    "wof:placetype":"venue"
},
  "geometry": {"coordinates":[14.75806427,50.8653793335],"type":"Point"}
}