{
  "type": "Feature",
  "properties": {
    "iso:country":"DE",
    "sg:address":"Zur Bayerh\u00f6he 4",
    "sg:city":"Triebischtal",
    "sg:postcode":"01665",
    "sg:province":"Sachsen",
    "wof:name":"Herbert Lindner",
    "wof:placetype":"venue"
},
  "geometry": {"coordinates":[13.432995,51.072834],"type":"Point"}
}