{
  "type": "Feature",
  "properties": {
    "iso:country":"DE",
    "sg:address":"Karlstr. 1",
    "sg:city":"Sta\u00dffurt",
    "sg:postcode":"39418",
    "sg:province":"Sachsen-Anhalt",
    "wof:name":"H. Schurigt",
    "wof:placetype":"venue"
},
  "geometry": {"coordinates":[11.5892744064,51.8504905701],"type":"Point"}
}