{
  "type": "Feature",
  "properties": {
    "iso:country":"DE",
    "sg:address":"Churer Weg 1a",
    "sg:city":"Bad Homburg",
    "sg:postcode":"61352",
    "sg:province":"Hessen",
    "wof:name":"Mcr Gmbh",
    "wof:placetype":"venue"
},
  "geometry": {"coordinates":[8.649354,50.221169],"type":"Point"}
}