{
  "type": "Feature",
  "properties": {
    "iso:country":"DE",
    "sg:address":"Aichner-Schmied-Str. 1",
    "sg:city":"Bad Birnbach",
    "sg:phone":"+49 8563/2661",
    "sg:postcode":"84364",
    "sg:province":"Bayern",
    "wof:name":"Super 2000",
    "wof:placetype":"venue"
},
  "geometry": {"coordinates":[13.092918396,48.4422340393],"type":"Point"}
}