{
  "type": "Feature",
  "properties": {
    "iso:country":"DE",
    "sg:address":"Rohrbachstr. 43a",
    "sg:city":"Geiselbach",
    "sg:phone":"+49 6024/9378",
    "sg:postcode":"63826",
    "sg:province":"Bayern",
    "wof:name":"Otto Kaiser Komponist",
    "wof:placetype":"venue"
},
  "geometry": {"coordinates":[9.1936330795,50.1215667725],"type":"Point"}
}