{
  "type": "Feature",
  "properties": {
    "iso:country":"DE",
    "sg:address":"Fahrenheitstr. 6",
    "sg:city":"Bochum",
    "sg:phone":"+49 234/490406",
    "sg:postcode":"44879",
    "sg:province":"Nordrhein-Westfalen",
    "wof:name":"Manfred Rodemann",
    "wof:placetype":"venue"
},
  "geometry": {"coordinates":[7.1528038979,51.4330787659],"type":"Point"}
}