{
  "type": "Feature",
  "properties": {
    "iso:country":"DE",
    "sg:address":"Fennstr. 26",
    "sg:city":"Berlin",
    "sg:phone":"+49 30/6399720",
    "sg:postcode":"12439",
    "sg:province":"Berlin",
    "wof:name":"Schaller Liegenschafts- Verwaltungs-gmbh",
    "wof:placetype":"venue"
},
  "geometry": {"coordinates":[13.5164327621,52.4540100098],"type":"Point"}
}