{
  "type": "Feature",
  "properties": {
    "iso:country":"DE",
    "sg:address":"Dammgasse 1",
    "sg:city":"Stolberg",
    "sg:phone":"+49 2402/83600",
    "sg:postcode":"52222",
    "sg:province":"Nordrhein-Westfalen",
    "wof:name":"Nail Beklen",
    "wof:placetype":"venue"
},
  "geometry": {"coordinates":[6.2228808403,50.7764778137],"type":"Point"}
}