{
  "type": "Feature",
  "properties": {
    "iso:country":"DE",
    "sg:address":"Schaumainkai 17",
    "sg:city":"Frankfurt",
    "sg:phone":"+49 69/60325667",
    "sg:postcode":"60594",
    "sg:province":"Hessen",
    "wof:name":"Strandperle",
    "wof:placetype":"venue"
},
  "geometry": {"coordinates":[8.6809530258,50.106590271],"type":"Point"}
}