{
  "type": "Feature",
  "properties": {
    "iso:country":"DE",
    "sg:address":"Morsumer Weg 20",
    "sg:city":"Hamburg",
    "sg:phone":"+49 40/7125132",
    "sg:postcode":"22117",
    "sg:province":"Hamburg",
    "wof:name":"Friedrich Lippmann",
    "wof:placetype":"venue"
},
  "geometry": {"coordinates":[10.1401891708,53.5405426025],"type":"Point"}
}