{
  "type": "Feature",
  "properties": {
    "iso:country":"DE",
    "sg:address":"Horchheimer Str. 1",
    "sg:city":"Weilerswist",
    "sg:phone":"+49 2254/6715",
    "sg:postcode":"53919",
    "sg:province":"Nordrhein-Westfalen",
    "wof:name":"Josef Klein",
    "wof:placetype":"venue"
},
  "geometry": {"coordinates":[6.816388,50.732113],"type":"Point"}
}