{
  "type": "Feature",
  "properties": {
    "iso:country":"DE",
    "sg:address":"Alte Bahnhofstr. 11",
    "sg:city":"Uetze",
    "sg:phone":"+49 5147/1846",
    "sg:postcode":"31311",
    "sg:province":"Niedersachsen",
    "wof:name":"Joachim Laube",
    "wof:placetype":"venue"
},
  "geometry": {"coordinates":[10.094775,52.484795],"type":"Point"}
}