{
  "type": "Feature",
  "properties": {
    "iso:country":"DE",
    "sg:address":"Schneiderberg 15",
    "sg:city":"Langg\u00f6ns",
    "sg:phone":"+49 6447/385",
    "sg:postcode":"35428",
    "sg:province":"Hessen",
    "wof:name":"Wilhelm Bode",
    "wof:placetype":"venue"
},
  "geometry": {"coordinates":[8.617598,50.476849],"type":"Point"}
}