{
  "type": "Feature",
  "properties": {
    "iso:country":"DE",
    "sg:address":"Kapuzinerstr. 36",
    "sg:city":"Passau",
    "sg:phone":"+49 851/383870",
    "sg:postcode":"94032",
    "sg:province":"Bayern",
    "wof:name":"Concepta Projektentwicklung Und Immobilienverwaltung",
    "wof:placetype":"venue"
},
  "geometry": {"coordinates":[13.4783296585,48.5710258484],"type":"Point"}
}