{
  "type": "Feature",
  "properties": {
    "iso:country":"DE",
    "sg:address":"Richener Str. 18",
    "sg:city":"Gemmingen",
    "sg:phone":"+49 7267/1555",
    "sg:postcode":"75050",
    "sg:province":"Baden-W\u00fcrttemberg",
    "wof:name":"Parkst\u00fcble",
    "wof:placetype":"venue"
},
  "geometry": {"coordinates":[8.9819126129,49.156917572],"type":"Point"}
}