{
  "type": "Feature",
  "properties": {
    "iso:country":"DE",
    "sg:address":"Kolpingstr. 5",
    "sg:city":"Regen",
    "sg:phone":"+49 9921/2214",
    "sg:postcode":"94209",
    "sg:province":"Bayern",
    "wof:name":"W. Schicker Sen. Schilder- Und Lichtreklame",
    "wof:placetype":"venue"
},
  "geometry": {"coordinates":[13.132435,48.975563],"type":"Point"}
}