{
  "type": "Feature",
  "properties": {
    "iso:country":"DE",
    "sg:address":"Ostpassage 7",
    "sg:city":"Langenhagen",
    "sg:phone":"+49 511/7242956",
    "sg:postcode":"30853",
    "sg:province":"Niedersachsen",
    "wof:name":"Apotheke Langenhagen",
    "wof:placetype":"venue"
},
  "geometry": {"coordinates":[9.741558,52.439377],"type":"Point"}
}