{
  "type": "Feature",
  "properties": {
    "iso:country":"DE",
    "sg:address":"Westl Krl-Friedr-Str 332",
    "sg:city":"Pforzheim",
    "sg:phone":"+49 7231/465066",
    "sg:postcode":"75172",
    "sg:province":"Baden-W\u00fcrttemberg",
    "wof:name":"Hei\u00df Fachvertrieb F\u00fcr",
    "wof:placetype":"venue"
},
  "geometry": {"coordinates":[8.700255,48.890137],"type":"Point"}
}