{
  "type": "Feature",
  "properties": {
    "iso:country":"DE",
    "sg:address":"Vorderer Anger 233",
    "sg:city":"Landsberg",
    "sg:phone":"+49 8191/22351",
    "sg:postcode":"86899",
    "sg:province":"Bayern",
    "wof:name":"Boys & Girls Kindermoden",
    "wof:placetype":"venue"
},
  "geometry": {"coordinates":[10.8771781921,48.0530357361],"type":"Point"}
}