{
  "type": "Feature",
  "properties": {
    "iso:country":"DE",
    "sg:address":"Kaiserstr 130",
    "sg:city":"Karlsruhe",
    "sg:phone":"+49 721/91720",
    "sg:postcode":"76133",
    "sg:province":"Baden-W\u00fcrttemberg",
    "wof:name":"Fritz Fischer Gmbh & Co Kg",
    "wof:placetype":"venue"
},
  "geometry": {"coordinates":[8.3959980011,49.0101127625],"type":"Point"}
}