{
  "type": "Feature",
  "properties": {
    "iso:country":"DE",
    "sg:address":"Falkenweg 7",
    "sg:city":"Sangerhausen",
    "sg:postcode":"06526",
    "sg:province":"Sachsen-Anhalt",
    "wof:name":"Guttenberger Gmbh",
    "wof:placetype":"venue"
},
  "geometry": {"coordinates":[11.314859,51.470276],"type":"Point"}
}