{
  "type": "Feature",
  "properties": {
    "iso:country":"DE",
    "sg:address":"Zur Eisengrube 23",
    "sg:city":"Bitz",
    "sg:phone":"+49 7431/8578",
    "sg:postcode":"72475",
    "sg:province":"Baden-W\u00fcrttemberg",
    "wof:name":"H. Heinzelmann Mech. Werkstatt",
    "wof:placetype":"venue"
},
  "geometry": {"coordinates":[9.085651,48.240585],"type":"Point"}
}