{
  "type": "Feature",
  "properties": {
    "iso:country":"DE",
    "sg:address":"Gr\u00fcner Weg 18",
    "sg:city":"Suhl",
    "sg:phone":"+49 3681/728308",
    "sg:postcode":"98527",
    "sg:province":"Th\u00fcringen",
    "wof:name":"Udo Fr\u00fchauf",
    "wof:placetype":"venue"
},
  "geometry": {"coordinates":[10.6900196075,50.6016120911],"type":"Point"}
}