{
  "type": "Feature",
  "properties": {
    "iso:country":"DE",
    "sg:address":"Kirchplatz 2",
    "sg:city":"Burgwindheim",
    "sg:phone":"+49 9551/1030",
    "sg:postcode":"96154",
    "sg:province":"Bayern",
    "wof:name":"Sport- Und Kegelgastst\u00e4tte",
    "wof:placetype":"venue"
},
  "geometry": {"coordinates":[10.5952997208,49.8276786804],"type":"Point"}
}