{
  "type": "Feature",
  "properties": {
    "iso:country":"DE",
    "sg:address":"Gneversdorfer Weg 12",
    "sg:city":"L\u00fcbeck",
    "sg:phone":"+49 4502/5175",
    "sg:postcode":"23570",
    "sg:province":"Schleswig-Holstein",
    "wof:name":"Aral-tamkstelle",
    "wof:placetype":"venue"
},
  "geometry": {"coordinates":[10.8617105484,53.9593467712],"type":"Point"}
}