{
  "type": "Feature",
  "properties": {
    "iso:country":"DE",
    "sg:address":"Hauptstr. 93",
    "sg:city":"Bielefeld",
    "sg:phone":"+49 521/411716",
    "sg:postcode":"33647",
    "sg:province":"Nordrhein-Westfalen",
    "wof:name":"Blumen Aus Amsterdam",
    "wof:placetype":"venue"
},
  "geometry": {"coordinates":[8.510395,51.990898],"type":"Point"}
}