{
  "type": "Feature",
  "properties": {
    "iso:country":"DE",
    "sg:address":"An der Windm\u00fchle 9",
    "sg:city":"Erkelenz",
    "sg:phone":"+49 2431/2140",
    "sg:postcode":"41812",
    "sg:province":"Nordrhein-Westfalen",
    "wof:name":"Johannes Schmitz",
    "wof:placetype":"venue"
},
  "geometry": {"coordinates":[6.3099021912,51.0865097046],"type":"Point"}
}