{
  "type": "Feature",
  "properties": {
    "iso:country":"DE",
    "sg:address":"Jan-Ullrich-Str. 2",
    "sg:city":"Merdingen",
    "sg:phone":"+49 7668/351",
    "sg:postcode":"79291",
    "sg:province":"Baden-W\u00fcrttemberg",
    "wof:name":"Gemeindeb\u00fccherei Schule",
    "wof:placetype":"venue"
},
  "geometry": {"coordinates":[7.688642,48.017303],"type":"Point"}
}