{
  "type": "Feature",
  "properties": {
    "iso:country":"DE",
    "sg:address":"Postgasse 15",
    "sg:city":"Ziegelheim",
    "sg:phone":"+49 34494/80320",
    "sg:postcode":"04618",
    "sg:province":"Th\u00fcringen",
    "wof:name":"Dietrich Hartmann",
    "wof:placetype":"venue"
},
  "geometry": {"coordinates":[12.5524549484,50.9241371155],"type":"Point"}
}