{
  "type": "Feature",
  "properties": {
    "iso:country":"DE",
    "sg:address":"Charlottenburger Str. 29",
    "sg:city":"Leverkusen",
    "sg:phone":"+49 214/91952",
    "sg:postcode":"51377",
    "sg:province":"Nordrhein-Westfalen",
    "wof:name":"Johann Heinen",
    "wof:placetype":"venue"
},
  "geometry": {"coordinates":[7.077044,51.044483],"type":"Point"}
}