{
  "type": "Feature",
  "properties": {
    "iso:country":"DE",
    "sg:address":"Nebelhornstr. 10",
    "sg:city":"Oberstdorf",
    "sg:phone":"+49 8322/8280",
    "sg:postcode":"87561",
    "sg:province":"Bayern",
    "wof:name":"Gerhard Spitzer",
    "wof:placetype":"venue"
},
  "geometry": {"coordinates":[10.279652,47.408871],"type":"Point"}
}