{
  "type": "Feature",
  "properties": {
    "iso:country":"DE",
    "sg:address":"Mariental 12",
    "sg:city":"Eisenach",
    "sg:phone":"+49 3691/29630",
    "sg:postcode":"99817",
    "sg:province":"Th\u00fcringen",
    "wof:name":"Werbeagentur Frank Bode Gmbh",
    "wof:placetype":"venue"
},
  "geometry": {"coordinates":[10.315986,50.964108],"type":"Point"}
}