{
  "type": "Feature",
  "properties": {
    "iso:country":"DE",
    "sg:address":"Feldstr. 1 b",
    "sg:city":"Unterschlei\u00dfheim",
    "sg:phone":"+49 89/3101056",
    "sg:postcode":"85716",
    "sg:province":"Bayern",
    "wof:name":"Heinrich Schr\u00f6der Kg",
    "wof:placetype":"venue"
},
  "geometry": {"coordinates":[11.5888843536,48.2761993408],"type":"Point"}
}