{
  "type": "Feature",
  "properties": {
    "iso:country":"DE",
    "sg:address":"Berggarten 10",
    "sg:city":"Puderbach",
    "sg:phone":"+49 2684/979120",
    "sg:postcode":"56305",
    "sg:province":"Rheinland-Pfalz",
    "wof:name":"Hans Hobbach Inh. Jutta Noll",
    "wof:placetype":"venue"
},
  "geometry": {"coordinates":[7.6118378639,50.6011924744],"type":"Point"}
}