{
  "type": "Feature",
  "properties": {
    "iso:country":"DE",
    "sg:address":"Callenberger Str. 12",
    "sg:city":"Kirschau",
    "sg:phone":"+49 3592/34300",
    "sg:postcode":"02681",
    "sg:province":"Sachsen",
    "wof:name":"Dieter P\u00f6tschke",
    "wof:placetype":"venue"
},
  "geometry": {"coordinates":[14.432044,51.090908],"type":"Point"}
}