{
  "type": "Feature",
  "properties": {
    "iso:country":"DE",
    "sg:address":"Zwingenbergstr. 98",
    "sg:city":"Krefeld",
    "sg:phone":"+49 2151/950863",
    "sg:postcode":"47802",
    "sg:province":"Nordrhein-Westfalen",
    "wof:name":"Ks Objektdesign Gmbh & Co. Kg",
    "wof:placetype":"venue"
},
  "geometry": {"coordinates":[6.5951328278,51.363079071],"type":"Point"}
}