{
  "type": "Feature",
  "properties": {
    "iso:country":"DE",
    "sg:address":"Mercedesstr. 12",
    "sg:city":"Sindelfingen",
    "sg:phone":"+49 7031/874890",
    "sg:postcode":"71063",
    "sg:province":"Baden-W\u00fcrttemberg",
    "wof:name":"M\u00e4nnersache",
    "wof:placetype":"venue"
},
  "geometry": {"coordinates":[8.9997386932,48.705280304],"type":"Point"}
}