{
  "type": "Feature",
  "properties": {
    "iso:country":"DE",
    "sg:address":"Birkach 26",
    "sg:city":"Bechhofen",
    "sg:phone":"+49 9822/7102",
    "sg:postcode":"91572",
    "sg:province":"Bayern",
    "wof:name":"Welo Wiesenbacher Dentalhandel Gmbh",
    "wof:placetype":"venue"
},
  "geometry": {"coordinates":[10.562751,49.138321],"type":"Point"}
}