{
  "type": "Feature",
  "properties": {
    "iso:country":"DE",
    "sg:address":"Sansibarstr. 2",
    "sg:city":"Berlin",
    "sg:phone":"+49 30/4527039",
    "sg:postcode":"13351",
    "sg:province":"Berlin",
    "wof:name":"Nino Rossi",
    "wof:placetype":"venue"
},
  "geometry": {"coordinates":[13.338596344,52.5516052246],"type":"Point"}
}