{
  "type": "Feature",
  "properties": {
    "iso:country":"DE",
    "sg:address":"Bahnhofstr. 9",
    "sg:city":"Sittensen",
    "sg:phone":"+49 4282/1437",
    "sg:postcode":"27419",
    "sg:province":"Niedersachsen",
    "wof:name":"B\u00f6rde Sanit\u00e4tshaus Inh. Werner Koch",
    "wof:placetype":"venue"
},
  "geometry": {"coordinates":[9.505127,53.280273],"type":"Point"}
}