{
  "type": "Feature",
  "properties": {
    "iso:country":"DE",
    "sg:address":"Wasserzucht 9",
    "sg:city":"Wunstorf",
    "sg:phone":"+49 5031/6459",
    "sg:postcode":"31515",
    "sg:province":"Niedersachsen",
    "wof:name":"Merlin",
    "wof:placetype":"venue"
},
  "geometry": {"coordinates":[9.4281358719,52.4267997742],"type":"Point"}
}