{
  "type": "Feature",
  "properties": {
    "iso:country":"DE",
    "sg:address":"Am Marienberg 7",
    "sg:city":"Brandenburg",
    "sg:phone":"+49 3381/300946",
    "sg:postcode":"14770",
    "sg:province":"Brandenburg",
    "wof:name":"Dr. Med. Wilhelm Niegel",
    "wof:placetype":"venue"
},
  "geometry": {"coordinates":[12.548464,52.412254],"type":"Point"}
}