{
  "type": "Feature",
  "properties": {
    "iso:country":"DE",
    "sg:address":"Progre\u00dfweg 17",
    "sg:city":"Zwickau",
    "sg:phone":"+49 375/453243",
    "sg:postcode":"08066",
    "sg:province":"Sachsen",
    "wof:name":"Dieter Heinrich",
    "wof:placetype":"venue"
},
  "geometry": {"coordinates":[12.5228462219,50.7348976135],"type":"Point"}
}