{
  "type": "Feature",
  "properties": {
    "iso:country":"DE",
    "sg:address":"Karstr. 70",
    "sg:city":"M\u00f6nchengladbach",
    "sg:phone":"+49 2161/352990",
    "sg:postcode":"41068",
    "sg:province":"Nordrhein-Westfalen",
    "wof:name":"Vdh Projektmanagement Gmbh",
    "wof:placetype":"venue"
},
  "geometry": {"coordinates":[6.414357,51.189404],"type":"Point"}
}