{
  "type": "Feature",
  "properties": {
    "iso:country":"DE",
    "sg:address":"Grenzstr. 2",
    "sg:city":"Sta\u00dffurt",
    "sg:phone":"+49 3925/322184",
    "sg:postcode":"39418",
    "sg:province":"Sachsen-Anhalt",
    "wof:name":"Siegfried Weichelt",
    "wof:placetype":"venue"
},
  "geometry": {"coordinates":[11.588749,51.849548],"type":"Point"}
}