{
  "type": "Feature",
  "properties": {
    "iso:country":"DE",
    "sg:address":"Evangelische Kirchgasse 10",
    "sg:city":"Leutkirch",
    "sg:phone":"+49 7561/912494",
    "sg:postcode":"88299",
    "sg:province":"Baden-W\u00fcrttemberg",
    "wof:name":"Paul St\u00f6r Metzgerei Inh. Thaddaeus Rimmel E. K.",
    "wof:placetype":"venue"
},
  "geometry": {"coordinates":[10.0227088928,47.8261413574],"type":"Point"}
}