{
  "type": "Feature",
  "properties": {
    "iso:country":"DE",
    "sg:address":"Nu\u00dfbaumstr. 2",
    "sg:city":"Karlsfeld",
    "sg:phone":"+49 8131/90040",
    "sg:postcode":"85757",
    "sg:province":"Bayern",
    "wof:name":"Avx Gmbh",
    "wof:placetype":"venue"
},
  "geometry": {"coordinates":[11.476567,48.222958],"type":"Point"}
}