{
  "type": "Feature",
  "properties": {
    "iso:country":"DE",
    "sg:address":"Lange Str. 31a",
    "sg:city":"Sulingen",
    "sg:phone":"+49 4271/1088",
    "sg:postcode":"27232",
    "sg:province":"Niedersachsen",
    "wof:name":"Heitmann Sicherheits- Systeme Gmbh",
    "wof:placetype":"venue"
},
  "geometry": {"coordinates":[8.8072118759,52.6824073792],"type":"Point"}
}