{
  "type": "Feature",
  "properties": {
    "iso:country":"DE",
    "sg:address":"Palmstrasse 6",
    "sg:city":"L\u00f6rrach",
    "sg:phone":"+49 7621/2046",
    "sg:postcode":"79539",
    "sg:province":"Baden-W\u00fcrttemberg",
    "wof:name":"Innung Des Kfz-gewerbes L\u00f6rrach",
    "wof:placetype":"venue"
},
  "geometry": {"coordinates":[7.6614770889,47.6142272949],"type":"Point"}
}