{
  "type": "Feature",
  "properties": {
    "iso:country":"DE",
    "sg:address":"Sauerbruchstr. 8-10",
    "sg:city":"M\u00fcnchen",
    "sg:phone":"+49 89/7001514",
    "sg:postcode":"81377",
    "sg:province":"Bayern",
    "wof:name":"R. Heisig Inh. D. Strott",
    "wof:placetype":"venue"
},
  "geometry": {"coordinates":[11.476626,48.114002],"type":"Point"}
}