{
  "type": "Feature",
  "properties": {
    "iso:country":"DE",
    "sg:address":"Hauptplatz 17",
    "sg:city":"Pfaffenhofen",
    "sg:phone":"+49 8441/9652",
    "sg:postcode":"85276",
    "sg:province":"Bayern",
    "wof:name":"I. M. Trendshop Textilhandels Gmbh",
    "wof:placetype":"venue"
},
  "geometry": {"coordinates":[11.5076971054,48.5294952393],"type":"Point"}
}