{
  "type": "Feature",
  "properties": {
    "iso:country":"DE",
    "sg:address":"Am Dreieck 13",
    "sg:city":"Lohmar",
    "sg:phone":"+49 2246/2446",
    "sg:postcode":"53797",
    "sg:province":"Nordrhein-Westfalen",
    "wof:name":"Detlef Krumbe",
    "wof:placetype":"venue"
},
  "geometry": {"coordinates":[7.2690811157,50.8346977234],"type":"Point"}
}