{
  "type": "Feature",
  "properties": {
    "iso:country":"DE",
    "sg:address":"Albstr. 57",
    "sg:city":"Uhingen",
    "sg:phone":"+49 7161/32343",
    "sg:postcode":"73066",
    "sg:province":"Baden-W\u00fcrttemberg",
    "wof:name":"Ernst Haupt",
    "wof:placetype":"venue"
},
  "geometry": {"coordinates":[9.5830602646,48.6835708618],"type":"Point"}
}