{
  "type": "Feature",
  "properties": {
    "iso:country":"DE",
    "sg:address":"Ruhlsdorfer Str. 95 (Geb\u00e4ude 81)",
    "sg:city":"Stahnsdorf",
    "sg:phone":"+49 3329/614503",
    "sg:postcode":"14532",
    "sg:province":"Brandenburg",
    "wof:name":"Kay-eric Wichmann Exportverpackung, Transport & Spedition",
    "wof:placetype":"venue"
},
  "geometry": {"coordinates":[13.243765831,52.3829803467],"type":"Point"}
}