{
  "type": "Feature",
  "properties": {
    "iso:country":"DE",
    "sg:address":"Papenkamp 18",
    "sg:city":"Bielefeld",
    "sg:phone":"+49 521/443577",
    "sg:postcode":"33647",
    "sg:province":"Nordrhein-Westfalen",
    "wof:name":"Friedrich Speckmann Steuerberater",
    "wof:placetype":"venue"
},
  "geometry": {"coordinates":[8.5045204163,51.984336853],"type":"Point"}
}