{
  "type": "Feature",
  "properties": {
    "iso:country":"DE",
    "sg:address":"Carl-Bertelsmann-Str. 5",
    "sg:city":"G\u00fctersloh",
    "sg:phone":"+49 5241/12916",
    "sg:postcode":"33332",
    "sg:province":"Nordrhein-Westfalen",
    "wof:name":"B\u00e4ckerei Frieda Baumann Inh. Gerhard Teeke",
    "wof:placetype":"venue"
},
  "geometry": {"coordinates":[8.385401,51.905308],"type":"Point"}
}