{
  "type": "Feature",
  "properties": {
    "iso:country":"DE",
    "sg:address":"Curt-M\u00f6bius-Str. 34",
    "sg:city":"Cottbus",
    "sg:phone":"+49 355/714890",
    "sg:postcode":"03042",
    "sg:province":"Brandenburg",
    "wof:name":"Hans Schmidt",
    "wof:placetype":"venue"
},
  "geometry": {"coordinates":[14.356323,51.759975],"type":"Point"}
}