{
  "type": "Feature",
  "properties": {
    "iso:country":"DE",
    "sg:address":"Mechtildstr. 18",
    "sg:city":"Frankfurt",
    "sg:phone":"+49 69/5602828",
    "sg:postcode":"60320",
    "sg:province":"Hessen",
    "wof:name":"Helmut Kinast Rechtsanwalt Und Notar",
    "wof:placetype":"venue"
},
  "geometry": {"coordinates":[8.6727619171,50.1369781494],"type":"Point"}
}