{
  "type": "Feature",
  "properties": {
    "iso:country":"DE",
    "sg:address":"An der Holzbr\u00fccke 18",
    "sg:city":"Forchheim",
    "sg:phone":"+49 9191/60828",
    "sg:postcode":"91301",
    "sg:province":"Bayern",
    "wof:name":"Wolfram Ahlers",
    "wof:placetype":"venue"
},
  "geometry": {"coordinates":[11.103763,49.716763],"type":"Point"}
}