{
  "type": "Feature",
  "properties": {
    "iso:country":"DE",
    "sg:address":"Franz-Kissing-Str. 7",
    "sg:city":"Menden",
    "sg:phone":"+49 2373/9260",
    "sg:postcode":"58706",
    "sg:province":"Nordrhein-Westfalen",
    "wof:name":"Wsg Menden Wirtschafts- F\u00f6rderungs U. Stadtentwick-",
    "wof:placetype":"venue"
},
  "geometry": {"coordinates":[7.7851128578,51.4511947632],"type":"Point"}
}