{
  "type": "Feature",
  "properties": {
    "iso:country":"DE",
    "sg:address":"Willy-Brandt-Platz 2",
    "sg:city":"Reutlingen",
    "sg:postcode":"72764",
    "sg:province":"Baden-W\u00fcrttemberg",
    "wof:name":"Deutsche Telekom T-punkt",
    "wof:placetype":"venue"
},
  "geometry": {"coordinates":[9.2148704529,48.4915885925],"type":"Point"}
}