{
  "type": "Feature",
  "properties": {
    "iso:country":"DE",
    "sg:address":"Pfarrgasse 5",
    "sg:city":"R\u00f6dermark",
    "sg:phone":"+49 6074/97239",
    "sg:postcode":"63322",
    "sg:province":"Hessen",
    "wof:name":"Karl-heinz Schrod",
    "wof:placetype":"venue"
},
  "geometry": {"coordinates":[8.8280696869,49.9776115417],"type":"Point"}
}