{
  "type": "Feature",
  "properties": {
    "iso:country":"DE",
    "sg:address":"Oststr. 3",
    "sg:city":"\u00d6hringen",
    "sg:phone":"+49 7941/36276",
    "sg:postcode":"74613",
    "sg:province":"Baden-W\u00fcrttemberg",
    "wof:name":"Fritz Eisenmann",
    "wof:placetype":"venue"
},
  "geometry": {"coordinates":[9.53148,49.197258],"type":"Point"}
}