{
  "type": "Feature",
  "properties": {
    "iso:country":"DE",
    "sg:address":"Lornsenstr. 2",
    "sg:city":"S\u00fcderbrarup",
    "sg:phone":"+49 4641/2970",
    "sg:postcode":"24392",
    "sg:province":"Schleswig-Holstein",
    "wof:name":"Ssf Gerda Eichhorn",
    "wof:placetype":"venue"
},
  "geometry": {"coordinates":[9.7710599899,54.6354408264],"type":"Point"}
}