{
  "type": "Feature",
  "properties": {
    "iso:country":"DE",
    "sg:address":"Westerhamer Str. 2",
    "sg:city":"Feldkirchen-Westerham",
    "sg:phone":"+49 8063/8555",
    "sg:postcode":"83620",
    "sg:province":"Bayern",
    "wof:name":"P. Kaltner",
    "wof:placetype":"venue"
},
  "geometry": {"coordinates":[11.84493,47.909042],"type":"Point"}
}