{
  "type": "Feature",
  "properties": {
    "iso:country":"DE",
    "sg:address":"Eichenhofener Str. 75",
    "sg:city":"Seubersdorf",
    "sg:phone":"+49 9497/457",
    "sg:postcode":"92358",
    "sg:province":"Bayern",
    "wof:name":"R. Karl",
    "wof:placetype":"venue"
},
  "geometry": {"coordinates":[11.63072,49.16925],"type":"Point"}
}