{
  "type": "Feature",
  "properties": {
    "iso:country":"DE",
    "sg:address":"Fabrikstr. 31",
    "sg:city":"Eisenberg",
    "sg:phone":"+49 36691/50821",
    "sg:postcode":"07607",
    "sg:province":"Th\u00fcringen",
    "wof:name":"B. Hopfe",
    "wof:placetype":"venue"
},
  "geometry": {"coordinates":[11.900579,50.970287],"type":"Point"}
}