{
  "type": "Feature",
  "properties": {
    "iso:country":"DE",
    "sg:address":"Am Wedelgraben 25",
    "sg:city":"Heidenheim",
    "sg:phone":"+49 7321/929288",
    "sg:postcode":"89522",
    "sg:province":"Baden-W\u00fcrttemberg",
    "wof:name":"Talkline-center-partner",
    "wof:placetype":"venue"
},
  "geometry": {"coordinates":[10.1524572372,48.6755485535],"type":"Point"}
}