{
  "type": "Feature",
  "properties": {
    "iso:country":"DE",
    "sg:address":"Bahnhofstr. 35",
    "sg:city":"Hagenow",
    "sg:postcode":"19230",
    "sg:province":"Mecklenburg-Vorpommern",
    "wof:name":"Katholisches Pfarramt Hagenow",
    "wof:placetype":"venue"
},
  "geometry": {"coordinates":[11.1967134476,53.4281654358],"type":"Point"}
}