{
  "type": "Feature",
  "properties": {
    "iso:country":"DE",
    "sg:address":"Glatzer Str. 6",
    "sg:city":"Sch\u00fcttorf",
    "sg:phone":"+49 5923/663",
    "sg:postcode":"48465",
    "sg:province":"Niedersachsen",
    "wof:name":"Ev. Pfarramt",
    "wof:placetype":"venue"
},
  "geometry": {"coordinates":[7.2106161118,52.3279304504],"type":"Point"}
}