{
  "type": "Feature",
  "properties": {
    "iso:country":"DE",
    "sg:address":"Barsingh\u00e4user Str. 21a",
    "sg:city":"Gehrden",
    "sg:phone":"+49 5108/927622",
    "sg:postcode":"30989",
    "sg:province":"Niedersachsen",
    "wof:name":"Hkg H\u00e4usliche Kranken- Und Seniorenpflege Gehrden",
    "wof:placetype":"venue"
},
  "geometry": {"coordinates":[9.602783,52.316547],"type":"Point"}
}