{
  "type": "Feature",
  "properties": {
    "iso:country":"DE",
    "sg:address":"Freiheitsstr. 5",
    "sg:city":"Zwickau",
    "sg:postcode":"08064",
    "sg:province":"Sachsen",
    "wof:name":"Uwe Krau\u00df Bauunternehmen Gmbh",
    "wof:placetype":"venue"
},
  "geometry": {"coordinates":[12.4760875702,50.6768722534],"type":"Point"}
}