{
  "type": "Feature",
  "properties": {
    "iso:country":"DE",
    "sg:address":"Alte Bahnhofstr. 198",
    "sg:city":"Bochum",
    "sg:phone":"+49 234/296644",
    "sg:postcode":"44892",
    "sg:province":"Nordrhein-Westfalen",
    "wof:name":"Tengelmann Gmbh",
    "wof:placetype":"venue"
},
  "geometry": {"coordinates":[7.3027482033,51.4768447876],"type":"Point"}
}