{
  "type": "Feature",
  "properties": {
    "iso:country":"DE",
    "sg:address":"Bischof-Ketteler-Str. 19",
    "sg:city":"M\u00fchlheim",
    "sg:phone":"+49 6108/66004",
    "sg:postcode":"63165",
    "sg:province":"Hessen",
    "wof:name":"J. Becker Inh. Hannelore Moll",
    "wof:placetype":"venue"
},
  "geometry": {"coordinates":[8.855461,50.09708],"type":"Point"}
}