{
  "type": "Feature",
  "properties": {
    "iso:country":"DE",
    "sg:address":"Bonner Str. 18A",
    "sg:city":"D\u00fcsseldorf",
    "sg:phone":"+49 211/792219",
    "sg:postcode":"40589",
    "sg:province":"Nordrhein-Westfalen",
    "wof:name":"Sun Service Reiseb\u00fcro Gmbh",
    "wof:placetype":"venue"
},
  "geometry": {"coordinates":[6.8335180283,51.1744422913],"type":"Point"}
}