{
  "type": "Feature",
  "properties": {
    "iso:country":"DE",
    "sg:address":"Gr\u00fcnstiege 89 a",
    "sg:city":"Gronau",
    "sg:postcode":"48599",
    "sg:province":"Nordrhein-Westfalen",
    "wof:name":"Veprotec Gmbh",
    "wof:placetype":"venue"
},
  "geometry": {"coordinates":[7.0426888466,52.2116737366],"type":"Point"}
}