{
  "type": "Feature",
  "properties": {
    "iso:country":"DE",
    "sg:address":"Riegelsberger Str. 123",
    "sg:city":"P\u00fcttlingen",
    "sg:phone":"+49 6806/48389",
    "sg:postcode":"66346",
    "sg:province":"Saarland",
    "wof:name":"Pego Sportartikel - Handel Gmbh",
    "wof:placetype":"venue"
},
  "geometry": {"coordinates":[6.9092669487,49.2986030579],"type":"Point"}
}