{
  "type": "Feature",
  "properties": {
    "iso:country":"DE",
    "sg:address":"Esslinger Str. 3",
    "sg:city":"Plochingen",
    "sg:phone":"+49 7153/74703",
    "sg:postcode":"73207",
    "sg:province":"Baden-W\u00fcrttemberg",
    "wof:name":"Hermes",
    "wof:placetype":"venue"
},
  "geometry": {"coordinates":[9.4143800735,48.7110786438],"type":"Point"}
}