{
  "type": "Feature",
  "properties": {
    "iso:country":"DE",
    "sg:address":"Burger Landstr. 11-13",
    "sg:city":"Herborn",
    "sg:phone":"+49 2772/92630",
    "sg:postcode":"35745",
    "sg:province":"Hessen",
    "wof:name":"Thomas Und Krause",
    "wof:placetype":"venue"
},
  "geometry": {"coordinates":[8.301320076,50.6859207153],"type":"Point"}
}