{
  "type": "Feature",
  "properties": {
    "iso:country":"DE",
    "sg:address":"Schlei\u00dfheimer Str. 65",
    "sg:city":"M\u00fcnchen",
    "sg:phone":"+49 89/184478",
    "sg:postcode":"80797",
    "sg:province":"Bayern",
    "wof:name":"Margareta B\u00fctschek",
    "wof:placetype":"venue"
},
  "geometry": {"coordinates":[11.5615177155,48.1557540894],"type":"Point"}
}