{
  "type": "Feature",
  "properties": {
    "iso:country":"DE",
    "sg:address":"An den Eichen 37",
    "sg:city":"Solingen",
    "sg:phone":"+49 212/652860",
    "sg:postcode":"42699",
    "sg:province":"Nordrhein-Westfalen",
    "wof:name":"Betex Gewebeveredlungs-gmbh",
    "wof:placetype":"venue"
},
  "geometry": {"coordinates":[7.0268058777,51.1544075012],"type":"Point"}
}