{
  "type": "Feature",
  "properties": {
    "iso:country":"DE",
    "sg:address":"Ziegelhof 5",
    "sg:city":"Blaubeuren",
    "sg:phone":"+49 7344/7401",
    "sg:postcode":"89143",
    "sg:province":"Baden-W\u00fcrttemberg",
    "wof:name":"H. Hug",
    "wof:placetype":"venue"
},
  "geometry": {"coordinates":[9.80778,48.371929],"type":"Point"}
}