{
  "type": "Feature",
  "properties": {
    "iso:country":"DE",
    "sg:address":"Neum\u00fchlenallee 3",
    "sg:city":"Borken",
    "sg:phone":"+49 2861/2325",
    "sg:postcode":"46325",
    "sg:province":"Nordrhein-Westfalen",
    "wof:name":"Otto Vietor",
    "wof:placetype":"venue"
},
  "geometry": {"coordinates":[6.8629741669,51.8602752686],"type":"Point"}
}