{
  "type": "Feature",
  "properties": {
    "iso:country":"DE",
    "sg:address":"G\u00f6ttinger Str. 6",
    "sg:city":"Hannover",
    "sg:phone":"+49 511/422011",
    "sg:postcode":"30449",
    "sg:province":"Niedersachsen",
    "wof:name":"P. Bergmann",
    "wof:placetype":"venue"
},
  "geometry": {"coordinates":[9.7146711349,52.3607444763],"type":"Point"}
}