{
  "type": "Feature",
  "properties": {
    "iso:country":"DE",
    "sg:address":"Franz-von-Heeren-Str. 3",
    "sg:city":"Rottenbuch",
    "sg:phone":"+49 8867/257",
    "sg:postcode":"82401",
    "sg:province":"Bayern",
    "wof:name":"S\u00fcdband Schmidbauer Vertriebs Kg",
    "wof:placetype":"venue"
},
  "geometry": {"coordinates":[10.9675607681,47.7345085144],"type":"Point"}
}