{
  "type": "Feature",
  "properties": {
    "iso:country":"DE",
    "sg:city":"Westhofen",
    "sg:postcode":"67593",
    "sg:province":"Rheinland-Pfalz",
    "wof:name":"Senlog - Sensitive Logistik Gefahrgutschulungen",
    "wof:placetype":"venue"
},
  "geometry": {"coordinates":[8.247955,49.703011],"type":"Point"}
}