{
  "type": "Feature",
  "properties": {
    "iso:country":"DE",
    "sg:address":"Poststr. 4",
    "sg:city":"L\u00f6bau",
    "sg:phone":"+49 3585/403945",
    "sg:postcode":"02708",
    "sg:province":"Sachsen",
    "wof:name":"Orient Kebab Haus",
    "wof:placetype":"venue"
},
  "geometry": {"coordinates":[14.6660604477,51.0973548889],"type":"Point"}
}