{
  "type": "Feature",
  "properties": {
    "iso:country":"DE",
    "sg:address":"Taltitzer Str. 42",
    "sg:city":"Weischlitz",
    "sg:phone":"+49 37436/2354",
    "sg:postcode":"08538",
    "sg:province":"Sachsen",
    "wof:name":"Eberhard Schwab",
    "wof:placetype":"venue"
},
  "geometry": {"coordinates":[12.068238,50.443817],"type":"Point"}
}