{
  "type": "Feature",
  "properties": {
    "iso:country":"DE",
    "sg:address":"Ettenberg",
    "sg:city":"Marktschellenberg",
    "sg:phone":"+49 8650/245",
    "sg:postcode":"83487",
    "sg:province":"Bayern",
    "wof:name":"Gastst\u00e4tte Mesnerwirt",
    "wof:placetype":"venue"
},
  "geometry": {"coordinates":[13.0441808701,47.6956253052],"type":"Point"}
}