{
  "type": "Feature",
  "properties": {
    "iso:country":"DE",
    "sg:address":"Andreas-Passage",
    "sg:city":"Hildesheim",
    "sg:phone":"+49 5121/39190",
    "sg:postcode":"31134",
    "sg:province":"Niedersachsen",
    "wof:name":"Boutique La Donna Inh. Jutta Wegener",
    "wof:placetype":"venue"
},
  "geometry": {"coordinates":[9.948592,52.150879],"type":"Point"}
}