{
  "type": "Feature",
  "properties": {
    "iso:country":"DE",
    "sg:address":"Ritter-von-Wagner-Str. 11",
    "sg:city":"Waldershof",
    "sg:phone":"+49 9231/71182",
    "sg:postcode":"95679",
    "sg:province":"Bayern",
    "wof:name":"Manfred Detterbeck",
    "wof:placetype":"venue"
},
  "geometry": {"coordinates":[12.066536,49.981258],"type":"Point"}
}