{
  "type": "Feature",
  "properties": {
    "iso:country":"DE",
    "sg:city":"Gottmadingen",
    "sg:phone":"+49 7731/71540",
    "sg:postcode":"78244",
    "sg:province":"Baden-W\u00fcrttemberg",
    "wof:name":"Gemeindeb\u00fccherei Eichendorff-schule",
    "wof:placetype":"venue"
},
  "geometry": {"coordinates":[8.777165,47.734985],"type":"Point"}
}