{
  "type": "Feature",
  "properties": {
    "iso:country":"DE",
    "sg:address":"Gewerbestr. 3",
    "sg:city":"Steinberg",
    "sg:phone":"+49 37462/6880",
    "sg:postcode":"08237",
    "sg:province":"Sachsen",
    "wof:name":"Smb Maschinenbau Gmbh",
    "wof:placetype":"venue"
},
  "geometry": {"coordinates":[12.496554,50.54134],"type":"Point"}
}