{
  "type": "Feature",
  "properties": {
    "iso:country":"DE",
    "sg:address":"H\u00fcttenstr. 46",
    "sg:city":"Bad Lauterberg",
    "sg:phone":"+49 5524/3975",
    "sg:postcode":"37431",
    "sg:province":"Niedersachsen",
    "wof:name":"H. M. Wedekind",
    "wof:placetype":"venue"
},
  "geometry": {"coordinates":[10.4648017883,51.6240005493],"type":"Point"}
}