{
  "type": "Feature",
  "properties": {
    "iso:country":"DE",
    "sg:address":"Bucher Str. 68",
    "sg:city":"N\u00fcrnberg",
    "sg:phone":"+49 911/331739",
    "sg:postcode":"90408",
    "sg:province":"Bayern",
    "wof:name":"Peter Ki\u00dfkalt",
    "wof:placetype":"venue"
},
  "geometry": {"coordinates":[11.070544,49.464378],"type":"Point"}
}