{
  "type": "Feature",
  "properties": {
    "iso:country":"DE",
    "sg:address":"Wiesenhof",
    "sg:city":"Tangstedt",
    "sg:phone":"+49 4109/9911",
    "sg:postcode":"22889",
    "sg:province":"Schleswig-Holstein",
    "wof:name":"Maw Personal-marketing Beratungsgesellschaft Mbh",
    "wof:placetype":"venue"
},
  "geometry": {"coordinates":[10.0790748596,53.7243461609],"type":"Point"}
}