{
  "type": "Feature",
  "properties": {
    "iso:country":"DE",
    "sg:address":"Gartenstr. 37",
    "sg:city":"M\u00f6rfelden-Walldorf",
    "sg:postcode":"64546",
    "sg:province":"Hessen",
    "wof:name":"Kath. \u00d6ffentl. Bibliothek",
    "wof:placetype":"venue"
},
  "geometry": {"coordinates":[8.576192,50.003788],"type":"Point"}
}