{
  "type": "Feature",
  "properties": {
    "iso:country":"DE",
    "sg:address":"Saalestr. 10",
    "sg:city":"M\u00fclheim",
    "sg:phone":"+49 4920/8580020",
    "sg:postcode":"45478",
    "sg:province":"Nordrhein-Westfalen",
    "wof:name":"Gebr\u00dcder Spicker Kraftfahrzeuge Gmbh",
    "wof:placetype":"venue"
},
  "geometry": {"coordinates":[6.8613319397,51.4316940308],"type":"Point"}
}