{
  "type": "Feature",
  "properties": {
    "iso:country":"DE",
    "sg:address":"Buchholzstr. 5",
    "sg:city":"Bonn",
    "sg:phone":"+49 228/283756",
    "sg:postcode":"53127",
    "sg:province":"Nordrhein-Westfalen",
    "wof:name":"Cornelia Caffaro",
    "wof:placetype":"venue"
},
  "geometry": {"coordinates":[7.080906868,50.697555542],"type":"Point"}
}