{
  "type": "Feature",
  "properties": {
    "iso:country":"DE",
    "sg:address":"Am Heurech 8",
    "sg:city":"Heusweiler",
    "sg:phone":"+49 6806/82342",
    "sg:postcode":"66265",
    "sg:province":"Saarland",
    "wof:name":"Josef Engel",
    "wof:placetype":"venue"
},
  "geometry": {"coordinates":[6.962945,49.338943],"type":"Point"}
}