{
  "type": "Feature",
  "properties": {
    "iso:country":"DE",
    "sg:address":"Lindenstr. 16",
    "sg:city":"Grebs",
    "sg:phone":"+49 38750/20306",
    "sg:postcode":"19294",
    "sg:province":"Mecklenburg-Vorpommern",
    "wof:name":"J\u00fcrgen Grevsm\u00fchl",
    "wof:placetype":"venue"
},
  "geometry": {"coordinates":[11.327754,53.240116],"type":"Point"}
}