{
  "type": "Feature",
  "properties": {
    "iso:country":"DE",
    "sg:address":"In Der Rosenau 4",
    "sg:city":"M\u00fcnchen",
    "sg:phone":"+49 700 3746 5522",
    "sg:postcode":"81829",
    "sg:province":"Bayern",
    "wof:name":"Wagner & Munz Gmbh Laborfachhandel Labortechnik",
    "wof:placetype":"venue"
},
  "geometry": {"coordinates":[11.66024,48.131508],"type":"Point"}
}