{
  "type": "Feature",
  "properties": {
    "iso:country":"DE",
    "sg:address":"Schnoor 37",
    "sg:city":"Bremen",
    "sg:phone":"+49 421/323304",
    "sg:postcode":"28195",
    "sg:province":"Bremen",
    "wof:name":"Der Friseur Im Schnoor",
    "wof:placetype":"venue"
},
  "geometry": {"coordinates":[8.810005188,53.0726547241],"type":"Point"}
}