{
  "type": "Feature",
  "properties": {
    "iso:country":"DE",
    "sg:address":"Waldstr. 47",
    "sg:city":"Ohrdruf",
    "sg:phone":"+49 3624/311094",
    "sg:postcode":"99885",
    "sg:province":"Th\u00fcringen",
    "wof:name":"G. Issleiber",
    "wof:placetype":"venue"
},
  "geometry": {"coordinates":[10.7344350815,50.823348999],"type":"Point"}
}