{
  "type": "Feature",
  "properties": {
    "iso:country":"DE",
    "sg:address":"Obere Stadt 37",
    "sg:city":"Weilheim",
    "sg:phone":"+49 881/49272",
    "sg:postcode":"82362",
    "sg:province":"Bayern",
    "wof:name":"Edeltraud Hlobik",
    "wof:placetype":"venue"
},
  "geometry": {"coordinates":[11.1471529007,47.8385238647],"type":"Point"}
}