{
  "type": "Feature",
  "properties": {
    "iso:country":"DE",
    "sg:address":"Berger Str.47",
    "sg:city":"Frankfurt",
    "sg:phone":"+49 4969/491082",
    "sg:postcode":"60316",
    "sg:province":"Hessen",
    "wof:name":"Dresdner Bank",
    "wof:placetype":"venue"
},
  "geometry": {"coordinates":[8.697979,50.116199],"type":"Point"}
}