{
  "type": "Feature",
  "properties": {
    "iso:country":"DE",
    "sg:address":"Friedrich-Ebert-Platz 11",
    "sg:city":"Leverkusen",
    "sg:phone":"+49 214/44144",
    "sg:postcode":"51373",
    "sg:province":"Nordrhein-Westfalen",
    "wof:name":"H. Lomberg Gmbh & Co. Kg",
    "wof:placetype":"venue"
},
  "geometry": {"coordinates":[6.9888777733,51.0315628052],"type":"Point"}
}