{
  "type": "Feature",
  "properties": {
    "iso:country":"DE",
    "sg:address":"Poll-Vingster Str. 109",
    "sg:city":"K\u00f6ln",
    "sg:phone":"+49 221/832061",
    "sg:postcode":"51105",
    "sg:province":"Nordrhein-Westfalen",
    "wof:name":"Messebau Deeg Beteiligungs Gmbh",
    "wof:placetype":"venue"
},
  "geometry": {"coordinates":[7.006204,50.923328],"type":"Point"}
}