{
  "type": "Feature",
  "properties": {
    "iso:country":"DE",
    "sg:address":"Traunsteiner Str. 31",
    "sg:city":"Seebruck",
    "sg:phone":"+49 8667/218",
    "sg:postcode":"83358",
    "sg:province":"Bayern",
    "wof:name":"W\u00e4chters Cafestuben Inh. H. W\u00e4chter",
    "wof:placetype":"venue"
},
  "geometry": {"coordinates":[12.483926,47.933327],"type":"Point"}
}