{
  "type": "Feature",
  "properties": {
    "iso:country":"DE",
    "sg:address":"Dorfstr. 1",
    "sg:city":"G\u00fclzow",
    "sg:postcode":"18276",
    "sg:province":"Mecklenburg-Vorpommern",
    "wof:name":"Kallert Edelstahl Gmbh",
    "wof:placetype":"venue"
},
  "geometry": {"coordinates":[12.141873,53.837532],"type":"Point"}
}