{
  "type": "Feature",
  "properties": {
    "iso:country":"DE",
    "sg:address":"Bernadottestr. 263",
    "sg:city":"Hamburg",
    "sg:phone":"+49 40/8810001",
    "sg:postcode":"22605",
    "sg:province":"Hamburg",
    "wof:name":"Fast Export Gmbh",
    "wof:placetype":"venue"
},
  "geometry": {"coordinates":[9.8829202652,53.5479812622],"type":"Point"}
}