{
  "type": "Feature",
  "properties": {
    "iso:country":"DE",
    "sg:address":"Schulstr. 2",
    "sg:city":"Lauenbr\u00fcck",
    "sg:phone":"+49 4267/1533",
    "sg:postcode":"27389",
    "sg:province":"Niedersachsen",
    "wof:name":"Vergi\u00dfmeinnicht Inh. Heike J\u00f6rres",
    "wof:placetype":"venue"
},
  "geometry": {"coordinates":[9.554338,53.199657],"type":"Point"}
}