{
  "type": "Feature",
  "properties": {
    "iso:country":"DE",
    "sg:address":"Klosterstr. 1",
    "sg:city":"Herzberg",
    "sg:phone":"+49 3535/3410",
    "sg:postcode":"04916",
    "sg:province":"Brandenburg",
    "wof:name":"Rolf W\u00fcnsch",
    "wof:placetype":"venue"
},
  "geometry": {"coordinates":[13.2348613739,51.6934814453],"type":"Point"}
}