{
  "type": "Feature",
  "properties": {
    "iso:country":"DE",
    "sg:address":"Am Markt 4-5",
    "sg:city":"Schwerin",
    "sg:phone":"+49 385/565815",
    "sg:postcode":"19055",
    "sg:province":"Mecklenburg-Vorpommern",
    "wof:name":"Eduard Kettner",
    "wof:placetype":"venue"
},
  "geometry": {"coordinates":[11.414304,53.628899],"type":"Point"}
}