{
  "type": "Feature",
  "properties": {
    "iso:country":"DE",
    "sg:address":"Wackenbergstr. 65",
    "sg:city":"Berlin",
    "sg:phone":"+49 30/47411930",
    "sg:postcode":"13156",
    "sg:province":"Berlin",
    "wof:name":"Age Glas Vertrieb Gmbh & Co. Autoglas Berlin Kg",
    "wof:placetype":"venue"
},
  "geometry": {"coordinates":[13.415864,52.586754],"type":"Point"}
}