{
  "type": "Feature",
  "properties": {
    "iso:country":"DE",
    "sg:address":"Kirschallee",
    "sg:city":"Flecken Zechlin",
    "sg:postcode":"16837",
    "sg:province":"Brandenburg",
    "wof:name":"Dgb Verein Zur Jugend- F\u00f6rderung E. V.",
    "wof:placetype":"venue"
},
  "geometry": {"coordinates":[13.2928524017,51.0497283936],"type":"Point"}
}