{
  "type": "Feature",
  "properties": {
    "iso:country":"DE",
    "sg:address":"Venusstr. 27",
    "sg:city":"Oberasbach",
    "sg:phone":"+49 911/695216",
    "sg:postcode":"90522",
    "sg:province":"Bayern",
    "wof:name":"Harald H\u00e4hnlein Gmbh & Co. Kg",
    "wof:placetype":"venue"
},
  "geometry": {"coordinates":[10.976713,49.432125],"type":"Point"}
}