{
  "type": "Feature",
  "properties": {
    "iso:country":"DE",
    "sg:address":"Oststr. 10",
    "sg:city":"D\u00fcsseldorf",
    "sg:phone":"+49 211/1785960",
    "sg:postcode":"40211",
    "sg:province":"Nordrhein-Westfalen",
    "wof:name":"Mungan Gmbh",
    "wof:placetype":"venue"
},
  "geometry": {"coordinates":[6.7896571159,51.2274169922],"type":"Point"}
}