{
  "type": "Feature",
  "properties": {
    "iso:country":"DE",
    "sg:address":"Kurt-Schumacher-Str. 26",
    "sg:city":"Hildesheim",
    "sg:phone":"+49 5121/263051",
    "sg:postcode":"31139",
    "sg:province":"Niedersachsen",
    "wof:name":"Heros Gmbh",
    "wof:placetype":"venue"
},
  "geometry": {"coordinates":[9.9436826706,52.1308097839],"type":"Point"}
}