{
  "type": "Feature",
  "properties": {
    "iso:country":"DE",
    "sg:address":"H\u00fcttenstr. 100",
    "sg:city":"Aachen",
    "sg:phone":"+49 241/557176",
    "sg:postcode":"52068",
    "sg:province":"Nordrhein-Westfalen",
    "wof:name":"M. Roos",
    "wof:placetype":"venue"
},
  "geometry": {"coordinates":[6.135942,50.776791],"type":"Point"}
}