{
  "type": "Feature",
  "properties": {
    "iso:country":"DE",
    "sg:address":"Muskauer Str. 29",
    "sg:city":"Bautzen",
    "sg:phone":"+49 3591/43577",
    "sg:postcode":"02625",
    "sg:province":"Sachsen",
    "wof:name":"Harry B\u00e4ns",
    "wof:placetype":"venue"
},
  "geometry": {"coordinates":[14.436399,51.184772],"type":"Point"}
}