{
  "type": "Feature",
  "properties": {
    "iso:country":"DE",
    "sg:address":"St\u00f6ckendrebber Str. 33",
    "sg:city":"Neustadt",
    "sg:phone":"+49 5073/1859",
    "sg:postcode":"31535",
    "sg:province":"Niedersachsen",
    "wof:name":"Manfred Hambrock",
    "wof:placetype":"venue"
},
  "geometry": {"coordinates":[9.572401,52.667599],"type":"Point"}
}