{
  "type": "Feature",
  "properties": {
    "iso:country":"DE",
    "sg:address":"Pfalzburger Str. 22",
    "sg:city":"Mannheim",
    "sg:phone":"+49 621/4814060",
    "sg:postcode":"68229",
    "sg:province":"Baden-W\u00fcrttemberg",
    "wof:name":"Friedrich Wild",
    "wof:placetype":"venue"
},
  "geometry": {"coordinates":[8.572716,49.44212],"type":"Point"}
}