{
  "type": "Feature",
  "properties": {
    "iso:country":"DE",
    "sg:address":"Els\u00e4sser Str. 57",
    "sg:city":"Freiburg",
    "sg:phone":"+49 761/893765",
    "sg:postcode":"79110",
    "sg:province":"Baden-W\u00fcrttemberg",
    "wof:name":"H. Schiele",
    "wof:placetype":"venue"
},
  "geometry": {"coordinates":[7.825157,48.01442],"type":"Point"}
}