{
  "type": "Feature",
  "properties": {
    "iso:country":"DE",
    "sg:address":"Heinrich-Heine-Str. 10b",
    "sg:city":"Elbingerode",
    "sg:phone":"+49 39454/42919",
    "sg:postcode":"38875",
    "sg:province":"Sachsen-Anhalt",
    "wof:name":"Christinenteichbaude",
    "wof:placetype":"venue"
},
  "geometry": {"coordinates":[10.7975292206,51.774230957],"type":"Point"}
}