{
  "type": "Feature",
  "properties": {
    "iso:country":"DE",
    "sg:address":"Wexstr. 30",
    "sg:city":"Berlin",
    "sg:phone":"+49 30/8535330",
    "sg:postcode":"10715",
    "sg:province":"Berlin",
    "wof:name":"Hille Sagel Kameramann",
    "wof:placetype":"venue"
},
  "geometry": {"coordinates":[13.3296203613,52.4788856506],"type":"Point"}
}