{
  "type": "Feature",
  "properties": {
    "iso:country":"DE",
    "sg:address":"D\u00fcsterhauptstr. 31-38",
    "sg:city":"Berlin",
    "sg:phone":"+49 30/403710",
    "sg:postcode":"13469",
    "sg:province":"Berlin",
    "wof:name":"Mvs Miete Vertrieb Service Ag",
    "wof:placetype":"venue"
},
  "geometry": {"coordinates":[13.3189315796,52.609172821],"type":"Point"}
}