{
  "type": "Feature",
  "properties": {
    "iso:country":"DE",
    "sg:address":"Bismarckstr. 3",
    "sg:city":"Alfeld",
    "sg:phone":"+49 5181/5394",
    "sg:postcode":"31061",
    "sg:province":"Niedersachsen",
    "wof:name":"Alfred Klapproth",
    "wof:placetype":"venue"
},
  "geometry": {"coordinates":[9.8297739029,51.9863166809],"type":"Point"}
}