{
  "type": "Feature",
  "properties": {
    "iso:country":"DE",
    "sg:address":"Kokenhammer 7",
    "sg:city":"Holzminden",
    "sg:phone":"+49 5531/4739",
    "sg:postcode":"37603",
    "sg:province":"Niedersachsen",
    "wof:name":"Herbert Effe",
    "wof:placetype":"venue"
},
  "geometry": {"coordinates":[9.466285,51.826359],"type":"Point"}
}