{
  "type": "Feature",
  "properties": {
    "iso:country":"DE",
    "sg:address":"Industriestr. 5",
    "sg:city":"Kissing",
    "sg:phone":"+49 8233/5370",
    "sg:postcode":"86438",
    "sg:province":"Bayern",
    "wof:name":"M\u00f6bel Schneider",
    "wof:placetype":"venue"
},
  "geometry": {"coordinates":[10.96296978,48.300163269],"type":"Point"}
}