{
  "type": "Feature",
  "properties": {
    "iso:country":"DE",
    "sg:address":"Hausener Str.",
    "sg:city":"Aindling",
    "sg:phone":"+49 8237/448",
    "sg:postcode":"86447",
    "sg:province":"Bayern",
    "wof:name":"Leopold Reiser Kunstmaler",
    "wof:placetype":"venue"
},
  "geometry": {"coordinates":[10.984585,48.495483],"type":"Point"}
}