{
  "type": "Feature",
  "properties": {
    "iso:country":"DE",
    "sg:address":"Leharstr. 17",
    "sg:city":"Hamburg",
    "sg:phone":"+49 40/6794676",
    "sg:postcode":"22145",
    "sg:province":"Hamburg",
    "wof:name":"Happy Meeting Veranstaltungs- Und Medienproduktion Gmbh",
    "wof:placetype":"venue"
},
  "geometry": {"coordinates":[10.1605501175,53.6322059631],"type":"Point"}
}