{
  "type": "Feature",
  "properties": {
    "iso:country":"DE",
    "sg:address":"Kuhberg 1",
    "sg:city":"Neum\u00fcnster",
    "sg:phone":"+49 4321/47415",
    "sg:postcode":"24534",
    "sg:province":"Schleswig-Holstein",
    "wof:name":"China-restaurant",
    "wof:placetype":"venue"
},
  "geometry": {"coordinates":[9.9810276031,54.0766906738],"type":"Point"}
}