{
  "type": "Feature",
  "properties": {
    "iso:country":"DE",
    "sg:address":"Am Kretelmoor 10",
    "sg:city":"Kaltenkirchen",
    "sg:phone":"+49 4191/770439",
    "sg:postcode":"24568",
    "sg:province":"Schleswig-Holstein",
    "wof:name":"Internet-marketing & Dienstleistung",
    "wof:placetype":"venue"
},
  "geometry": {"coordinates":[9.951213,53.830585],"type":"Point"}
}