{
  "type": "Feature",
  "properties": {
    "iso:country":"DE",
    "sg:address":"Neue Str. 18",
    "sg:city":"Willroth",
    "sg:phone":"+49 2687/929414",
    "sg:postcode":"56594",
    "sg:province":"Rheinland-Pfalz",
    "wof:name":"Wagner Immobilien Versicherungs- Und",
    "wof:placetype":"venue"
},
  "geometry": {"coordinates":[7.5288910866,50.5684356689],"type":"Point"}
}