{
  "type": "Feature",
  "properties": {
    "iso:country":"DE",
    "sg:address":"Mauersbergerstr. 4",
    "sg:city":"Chemnitz",
    "sg:phone":"+49 4937/135160",
    "sg:postcode":"09117",
    "sg:province":"Sachsen",
    "wof:name":"S\u00c4chsische Gro\u00dfb\u00c4ckerei Union Gmbh Reimann",
    "wof:placetype":"venue"
},
  "geometry": {"coordinates":[12.854146,50.808506],"type":"Point"}
}