{
  "type": "Feature",
  "properties": {
    "iso:country":"DE",
    "sg:address":"Trib\u00fcnenweg 18",
    "sg:city":"Hamburg",
    "sg:phone":"+49 40/6518908",
    "sg:postcode":"22111",
    "sg:province":"Hamburg",
    "wof:name":"Max Heiden Gmbh",
    "wof:placetype":"venue"
},
  "geometry": {"coordinates":[10.078147,53.559864],"type":"Point"}
}