{
  "type": "Feature",
  "properties": {
    "iso:country":"DE",
    "sg:address":"Ortsstr. 33",
    "sg:city":"Ruppersdorf",
    "sg:phone":"+49 36643/22372",
    "sg:postcode":"07356",
    "sg:province":"Th\u00fcringen",
    "wof:name":"Reinhard Wolfram",
    "wof:placetype":"venue"
},
  "geometry": {"coordinates":[11.6273288727,50.4547615051],"type":"Point"}
}