{
  "type": "Feature",
  "properties": {
    "iso:country":"DE",
    "sg:address":"Neukirchener Str. 11",
    "sg:city":"Neuss",
    "sg:phone":"+49 2137/60474",
    "sg:postcode":"41470",
    "sg:province":"Nordrhein-Westfalen",
    "wof:name":"Wolfgang Becker",
    "wof:placetype":"venue"
},
  "geometry": {"coordinates":[6.730543,51.125797],"type":"Point"}
}