{
  "type": "Feature",
  "properties": {
    "iso:country":"DE",
    "sg:address":"Holzm\u00fchlenstra\u00dfe 57",
    "sg:city":"Hamburg",
    "sg:phone":"+49 40",
    "sg:postcode":"22041",
    "sg:province":"Hamburg",
    "wof:name":"Datenkabel F\u00fcr Nokia, Siemens, Sagem, Alcatel, Uvm",
    "wof:placetype":"venue"
},
  "geometry": {"coordinates":[10.080393,53.581951],"type":"Point"}
}