{
  "type": "Feature",
  "properties": {
    "iso:country":"DE",
    "sg:address":"M\u00fchlenstr. 16",
    "sg:city":"W\u00fclfrath",
    "sg:phone":"+49 2058/3470",
    "sg:postcode":"42489",
    "sg:province":"Nordrhein-Westfalen",
    "wof:name":"Rosa Hessler",
    "wof:placetype":"venue"
},
  "geometry": {"coordinates":[7.0296311378,51.2818870544],"type":"Point"}
}