{
  "type": "Feature",
  "properties": {
    "iso:country":"DE",
    "sg:address":"Lindenstr. 15",
    "sg:city":"L\u00fcerdissen",
    "sg:phone":"+49 5534/999810",
    "sg:postcode":"37635",
    "sg:province":"Niedersachsen",
    "wof:name":"Sprachschule Und \u00dcbersetzungen B. Rolff Gmbh",
    "wof:placetype":"venue"
},
  "geometry": {"coordinates":[9.6145601273,51.9430503845],"type":"Point"}
}