{
  "type": "Feature",
  "properties": {
    "iso:country":"DE",
    "sg:address":"Hoffnung",
    "sg:city":"Handewitt",
    "sg:phone":"+49 4630/305",
    "sg:postcode":"24983",
    "sg:province":"Schleswig-Holstein",
    "wof:name":"H. Asmussen",
    "wof:placetype":"venue"
},
  "geometry": {"coordinates":[9.3535404205,54.7171936035],"type":"Point"}
}