{
  "type": "Feature",
  "properties": {
    "iso:country":"DE",
    "sg:address":"Lindenstr. 10",
    "sg:city":"Baesweiler",
    "sg:phone":"+49 2401/51042",
    "sg:postcode":"52499",
    "sg:province":"Nordrhein-Westfalen",
    "wof:name":"Matthias Plum",
    "wof:placetype":"venue"
},
  "geometry": {"coordinates":[6.1664261818,50.9237327576],"type":"Point"}
}