{
  "type": "Feature",
  "properties": {
    "iso:country":"DE",
    "sg:address":"Mecklenburger Str. 19",
    "sg:city":"L\u00fcbow",
    "sg:phone":"+49 3841/780483",
    "sg:postcode":"23972",
    "sg:province":"Mecklenburg-Vorpommern",
    "wof:name":"H. Oldenburg",
    "wof:placetype":"venue"
},
  "geometry": {"coordinates":[11.517838,53.852966],"type":"Point"}
}