{
  "type": "Feature",
  "properties": {
    "iso:country":"DE",
    "sg:address":"Weserstr. 3",
    "sg:city":"Waldkappel",
    "sg:phone":"+49 5656/311",
    "sg:postcode":"37284",
    "sg:province":"Hessen",
    "wof:name":"Fesch-bau Gmbh",
    "wof:placetype":"venue"
},
  "geometry": {"coordinates":[9.816124,51.110062],"type":"Point"}
}