{
  "type": "Feature",
  "properties": {
    "iso:country":"DE",
    "sg:address":"Reideburger Str. 27",
    "sg:city":"Halle",
    "sg:phone":"+49 345/56750",
    "sg:postcode":"06112",
    "sg:province":"Sachsen-Anhalt",
    "wof:name":"Pacos Gmbh",
    "wof:placetype":"venue"
},
  "geometry": {"coordinates":[11.99711,51.483776],"type":"Point"}
}