{
  "type": "Feature",
  "properties": {
    "iso:country":"DE",
    "sg:address":"Staplack 2",
    "sg:city":"Hagen",
    "sg:phone":"+49 2331/77246",
    "sg:postcode":"58091",
    "sg:province":"Nordrhein-Westfalen",
    "wof:name":"Haus Staplack",
    "wof:placetype":"venue"
},
  "geometry": {"coordinates":[7.5241508484,51.3471946716],"type":"Point"}
}