{
  "type": "Feature",
  "properties": {
    "iso:country":"DE",
    "sg:address":"Birkenweg 8",
    "sg:city":"Neu-Anspach",
    "sg:phone":"+49 6081/7947",
    "sg:postcode":"61267",
    "sg:province":"Hessen",
    "wof:name":"Orbis-dialog-software Heidrun Duhm",
    "wof:placetype":"venue"
},
  "geometry": {"coordinates":[8.5063991547,50.2950935364],"type":"Point"}
}