{
  "type": "Feature",
  "properties": {
    "iso:country":"DE",
    "sg:address":"Altk\u00f6nigstr. 4",
    "sg:city":"Offenbach",
    "sg:phone":"+49 69/86080",
    "sg:postcode":"63075",
    "sg:province":"Hessen",
    "wof:name":"Mainbogen Hotel Gmbh",
    "wof:placetype":"venue"
},
  "geometry": {"coordinates":[8.78328228,50.1135635376],"type":"Point"}
}