{
  "type": "Feature",
  "properties": {
    "iso:country":"DE",
    "sg:address":"T\u00f6pferstr. 29",
    "sg:city":"Mirow",
    "sg:phone":"+49 39833/20470",
    "sg:postcode":"17252",
    "sg:province":"Mecklenburg-Vorpommern",
    "wof:name":"Wilfried Janke",
    "wof:placetype":"venue"
},
  "geometry": {"coordinates":[12.815049,53.274174],"type":"Point"}
}