{
  "type": "Feature",
  "properties": {
    "iso:country":"DE",
    "sg:city":"Frankenroda",
    "sg:phone":"+49 36924/2079",
    "sg:postcode":"99826",
    "sg:province":"Th\u00fcringen",
    "wof:name":"Cafe Gisela Und B\u00e4ckerei",
    "wof:placetype":"venue"
},
  "geometry": {"coordinates":[10.274943,51.095284],"type":"Point"}
}