{
  "type": "Feature",
  "properties": {
    "iso:country":"DE",
    "sg:address":"Zur Ruppertsklamm 12",
    "sg:city":"Lahnstein",
    "sg:phone":"+49 2621/8922",
    "sg:postcode":"56112",
    "sg:province":"Rheinland-Pfalz",
    "wof:name":"Paul M\u00fcller Ingenieur",
    "wof:placetype":"venue"
},
  "geometry": {"coordinates":[7.6099629402,50.3098640442],"type":"Point"}
}