{
  "type": "Feature",
  "properties": {
    "iso:country":"DE",
    "sg:address":"Klusstr. 3",
    "sg:city":"Osnabr\u00fcck",
    "sg:phone":"+49 541/357980",
    "sg:postcode":"49074",
    "sg:province":"Niedersachsen",
    "wof:name":"Stephanswerk Wohnungsbaugesellschaft Mbh",
    "wof:placetype":"venue"
},
  "geometry": {"coordinates":[8.0520963669,52.2747955322],"type":"Point"}
}