{
  "type": "Feature",
  "properties": {
    "iso:country":"DE",
    "sg:address":"Vogtswiesen 65",
    "sg:city":"Schorndorf",
    "sg:phone":"+49 4971/8175313",
    "sg:postcode":"73614",
    "sg:province":"Baden-W\u00fcrttemberg",
    "wof:name":"Ks Sensortechnik Gmbh",
    "wof:placetype":"venue"
},
  "geometry": {"coordinates":[9.516394,48.826763],"type":"Point"}
}