{
  "type": "Feature",
  "properties": {
    "iso:country":"DE",
    "sg:address":"Brockhagener Str. 40",
    "sg:city":"Steinhagen",
    "sg:phone":"+49 5204/4313",
    "sg:postcode":"33803",
    "sg:province":"Nordrhein-Westfalen",
    "wof:name":"H. W. Schlichte Steinh\u00e4ger- Und Kornbrennerei Gmbh & Co.",
    "wof:placetype":"venue"
},
  "geometry": {"coordinates":[8.4090251923,52.0019721985],"type":"Point"}
}