{
  "type": "Feature",
  "properties": {
    "iso:country":"DE",
    "sg:address":"Im Reite 11",
    "sg:city":"Springe",
    "sg:phone":"+49 5041/2301",
    "sg:postcode":"31832",
    "sg:province":"Niedersachsen",
    "wof:name":"Leo Radny",
    "wof:placetype":"venue"
},
  "geometry": {"coordinates":[9.573364,52.20657],"type":"Point"}
}