{
  "type": "Feature",
  "properties": {
    "iso:country":"DE",
    "sg:address":"Ziegeleiweg 20",
    "sg:city":"Cham",
    "sg:phone":"+49 9971/40040",
    "sg:postcode":"93413",
    "sg:province":"Bayern",
    "wof:name":"Kunststoffwerk Katzbach Gmbh",
    "wof:placetype":"venue"
},
  "geometry": {"coordinates":[12.6432666779,49.2348442078],"type":"Point"}
}