{
  "type": "Feature",
  "properties": {
    "iso:country":"DE",
    "sg:address":"Brunnenallee 8",
    "sg:city":"Bad Wildungen",
    "sg:phone":"+49 5621/2260",
    "sg:postcode":"34537",
    "sg:province":"Hessen",
    "wof:name":"L\u00f6wen-apotheke",
    "wof:placetype":"venue"
},
  "geometry": {"coordinates":[9.117776,51.117317],"type":"Point"}
}