{
  "type": "Feature",
  "properties": {
    "iso:country":"DE",
    "sg:address":"Zeppelinstr. 8",
    "sg:city":"Kolkwitz",
    "sg:phone":"+49 35604/6180",
    "sg:postcode":"03099",
    "sg:province":"Brandenburg",
    "wof:name":"Th\u00f6nes Reisen Touristik Gmbh",
    "wof:placetype":"venue"
},
  "geometry": {"coordinates":[14.1584415436,51.7615470886],"type":"Point"}
}