{
  "type": "Feature",
  "properties": {
    "iso:country":"DE",
    "sg:address":"Kurf\u00fcrstenstr. 1",
    "sg:city":"Solingen",
    "sg:phone":"+49 212/203486",
    "sg:postcode":"42655",
    "sg:province":"Nordrhein-Westfalen",
    "wof:name":"Fotostudio Ute Klein",
    "wof:placetype":"venue"
},
  "geometry": {"coordinates":[7.0835351944,51.1766967773],"type":"Point"}
}