{
  "type": "Feature",
  "properties": {
    "iso:country":"DE",
    "sg:address":"Am Hebelpark 3",
    "sg:city":"L\u00f6rrach",
    "sg:phone":"+49 7621/3123",
    "sg:postcode":"79539",
    "sg:province":"Baden-W\u00fcrttemberg",
    "wof:name":"R. Und W. Hofmann Gmbh",
    "wof:placetype":"venue"
},
  "geometry": {"coordinates":[7.663839817,47.6132202148],"type":"Point"}
}