{
  "type": "Feature",
  "properties": {
    "iso:country":"DE",
    "sg:address":"Auf dem Brink 86",
    "sg:city":"Oyten",
    "sg:phone":"+49 4207/4604",
    "sg:postcode":"28876",
    "sg:province":"Niedersachsen",
    "wof:name":"Dieter Meinken",
    "wof:placetype":"venue"
},
  "geometry": {"coordinates":[9.054961,53.072327],"type":"Point"}
}