{
  "type": "Feature",
  "properties": {
    "iso:country":"DE",
    "sg:address":"Ochsenbusch Campingplatz",
    "sg:city":"Eisenberg",
    "sg:phone":"+49 6351/8500",
    "sg:postcode":"67304",
    "sg:province":"Rheinland-Pfalz",
    "wof:name":"Karl-heinz Hafner",
    "wof:placetype":"venue"
},
  "geometry": {"coordinates":[8.0710220337,49.5596046448],"type":"Point"}
}