{
  "type": "Feature",
  "properties": {
    "iso:country":"DE",
    "sg:address":"Mittagsweg 38a",
    "sg:city":"Oldenburg",
    "sg:phone":"+49 441/42545",
    "sg:postcode":"26133",
    "sg:province":"Niedersachsen",
    "wof:name":"Andreas Thiele",
    "wof:placetype":"venue"
},
  "geometry": {"coordinates":[8.2171268463,53.1065406799],"type":"Point"}
}