{
  "type": "Feature",
  "properties": {
    "iso:country":"DE",
    "sg:address":"Parkstr. 5-7",
    "sg:city":"Burglengenfeld",
    "sg:phone":"+49 9471/70240",
    "sg:postcode":"93133",
    "sg:province":"Bayern",
    "wof:name":"Karl & Rausch",
    "wof:placetype":"venue"
},
  "geometry": {"coordinates":[12.047164,49.20052],"type":"Point"}
}