{
  "type": "Feature",
  "properties": {
    "iso:country":"DE",
    "sg:address":"Bonifatiusstr. 42",
    "sg:city":"\u00dcberherrn",
    "sg:phone":"+49 6836/2307",
    "sg:postcode":"66802",
    "sg:province":"Saarland",
    "wof:name":"Gisela Schneider",
    "wof:placetype":"venue"
},
  "geometry": {"coordinates":[6.6946787834,49.244934082],"type":"Point"}
}