{
  "type": "Feature",
  "properties": {
    "iso:country":"DE",
    "sg:address":"Werner-von-Siemens-Str. 2",
    "sg:city":"Schweinfurt",
    "sg:phone":"+49 9721/77130",
    "sg:postcode":"97424",
    "sg:province":"Bayern",
    "wof:name":"Edeka C & C Gro\u00dfmarkt Gmbh",
    "wof:placetype":"venue"
},
  "geometry": {"coordinates":[10.2297744751,50.0312843323],"type":"Point"}
}