{
  "type": "Feature",
  "properties": {
    "iso:country":"DE",
    "sg:address":"Gartenstr. 69",
    "sg:city":"Nauen",
    "sg:phone":"+49 3321/455396",
    "sg:postcode":"14641",
    "sg:province":"Brandenburg",
    "wof:name":"Werner Masuhr",
    "wof:placetype":"venue"
},
  "geometry": {"coordinates":[12.880973,52.607986],"type":"Point"}
}