{
  "type": "Feature",
  "properties": {
    "iso:country":"DE",
    "sg:address":"Bahnhofstr. 37",
    "sg:city":"Hameln",
    "sg:phone":"+49 5151/88948",
    "sg:postcode":"31785",
    "sg:province":"Niedersachsen",
    "wof:name":"Zolotenko",
    "wof:placetype":"venue"
},
  "geometry": {"coordinates":[9.372476,52.10157],"type":"Point"}
}