{
  "type": "Feature",
  "properties": {
    "iso:country":"DE",
    "sg:address":"Betzinger Str. 61",
    "sg:city":"Reutlingen",
    "sg:phone":"+49 7121/55868",
    "sg:postcode":"72770",
    "sg:province":"Baden-W\u00fcrttemberg",
    "wof:name":"Habitat Immobilien Gmbh",
    "wof:placetype":"venue"
},
  "geometry": {"coordinates":[9.1463317871,48.4834594727],"type":"Point"}
}