{
  "type": "Feature",
  "properties": {
    "iso:country":"DE",
    "sg:address":"Alter Weg 27",
    "sg:city":"Monschau",
    "sg:phone":"+49 2472/4784",
    "sg:postcode":"52156",
    "sg:province":"Nordrhein-Westfalen",
    "wof:name":"M. Weirauch",
    "wof:placetype":"venue"
},
  "geometry": {"coordinates":[6.249932,50.541977],"type":"Point"}
}