{
  "type": "Feature",
  "properties": {
    "iso:country":"DE",
    "sg:address":"Boltersener Str. 25",
    "sg:city":"Rullstorf",
    "sg:phone":"+49 4136/436",
    "sg:postcode":"21379",
    "sg:province":"Niedersachsen",
    "wof:name":"Harri Fabel",
    "wof:placetype":"venue"
},
  "geometry": {"coordinates":[10.53675,53.283447],"type":"Point"}
}