{
  "type": "Feature",
  "properties": {
    "iso:country":"DE",
    "sg:address":"Hauptstr. 61",
    "sg:city":"Wiesau",
    "sg:phone":"+49 9634/1232",
    "sg:postcode":"95676",
    "sg:province":"Bayern",
    "wof:name":"Hotel Deutsches Haus",
    "wof:placetype":"venue"
},
  "geometry": {"coordinates":[12.1888055801,49.9078140259],"type":"Point"}
}