{
  "type": "Feature",
  "properties": {
    "iso:country":"DE",
    "sg:address":"Halsbach",
    "sg:city":"Lohr",
    "sg:phone":"+49 9359/581",
    "sg:postcode":"97816",
    "sg:province":"Bayern",
    "wof:name":"Gastst\u00e4tte Anton Amend",
    "wof:placetype":"venue"
},
  "geometry": {"coordinates":[9.6567697525,50.0115203857],"type":"Point"}
}