{
  "type": "Feature",
  "properties": {
    "iso:country":"DE",
    "sg:address":"Kirchweg 11",
    "sg:city":"Untrasried",
    "sg:phone":"+49 8372/2745",
    "sg:postcode":"87496",
    "sg:province":"Bayern",
    "wof:name":"Kath. Pfarramt St. Sebastian",
    "wof:placetype":"venue"
},
  "geometry": {"coordinates":[10.3795881271,47.8268928528],"type":"Point"}
}