{
  "type": "Feature",
  "properties": {
    "iso:country":"DE",
    "sg:address":"Bur 8",
    "sg:city":"Neuenkirchen",
    "sg:phone":"+49 5465/1270",
    "sg:postcode":"49586",
    "sg:province":"Niedersachsen",
    "wof:name":"August Br\u00fcwer",
    "wof:placetype":"venue"
},
  "geometry": {"coordinates":[7.847564,52.440186],"type":"Point"}
}