{
  "type": "Feature",
  "properties": {
    "iso:country":"DE",
    "sg:address":"Benzstr. 13",
    "sg:city":"Gelsenkirchen",
    "sg:phone":"+49 209/73347",
    "sg:postcode":"45891",
    "sg:province":"Nordrhein-Westfalen",
    "wof:name":"F. Suttmeier",
    "wof:placetype":"venue"
},
  "geometry": {"coordinates":[7.074162,51.54604],"type":"Point"}
}