{
  "type": "Feature",
  "properties": {
    "iso:country":"DE",
    "sg:address":"Klosterstr. 20",
    "sg:city":"Uder",
    "sg:postcode":"37318",
    "sg:province":"Th\u00fcringen",
    "wof:name":"Lbj Ausbau Gmbh",
    "wof:placetype":"venue"
},
  "geometry": {"coordinates":[10.079449,51.36504],"type":"Point"}
}