{
  "type": "Feature",
  "properties": {
    "iso:country":"DE",
    "sg:address":"Coburger Str. 173",
    "sg:city":"Eisfeld",
    "sg:phone":"+49 3686/302178",
    "sg:postcode":"98673",
    "sg:province":"Th\u00fcringen",
    "wof:name":"Grill-oase",
    "wof:placetype":"venue"
},
  "geometry": {"coordinates":[10.9206876755,50.4105186462],"type":"Point"}
}