{
  "type": "Feature",
  "properties": {
    "iso:country":"DE",
    "sg:address":"Von-Wemighe-Str. 19",
    "sg:city":"Sehnde",
    "sg:phone":"+49 5138/1040",
    "sg:postcode":"31319",
    "sg:province":"Niedersachsen",
    "wof:name":"Hermann Ruhkopf",
    "wof:placetype":"venue"
},
  "geometry": {"coordinates":[9.9340810776,52.2991981506],"type":"Point"}
}