{
  "type": "Feature",
  "properties": {
    "iso:country":"DE",
    "sg:address":"Kirchenstr. 1",
    "sg:city":"Uetersen",
    "sg:postcode":"25436",
    "sg:province":"Schleswig-Holstein",
    "wof:name":"Alarm-tec Gesellschaft F\u00fcr Sicherheitstechnik Mbh",
    "wof:placetype":"venue"
},
  "geometry": {"coordinates":[9.655469,53.68251],"type":"Point"}
}