{
  "type": "Feature",
  "properties": {
    "iso:country":"DE",
    "sg:address":"Neustadter Str. 197",
    "sg:city":"Sonneberg",
    "sg:phone":"+49 3675/742915",
    "sg:postcode":"96515",
    "sg:province":"Th\u00fcringen",
    "wof:name":"Sonneberger M\u00f6bel-markt Robert Simon Gmbh",
    "wof:placetype":"venue"
},
  "geometry": {"coordinates":[11.146728,50.344555],"type":"Point"}
}