{
  "type": "Feature",
  "properties": {
    "iso:country":"DE",
    "sg:address":"Flehinger Str. 20",
    "sg:city":"Oberderdingen",
    "sg:phone":"+49 7045/40188",
    "sg:postcode":"75038",
    "sg:province":"Baden-W\u00fcrttemberg",
    "wof:name":"Imbiss Korfu",
    "wof:placetype":"venue"
},
  "geometry": {"coordinates":[8.8011388779,49.0635108948],"type":"Point"}
}