{
  "type": "Feature",
  "properties": {
    "iso:country":"DE",
    "sg:address":"Rotk\u00e4ppchenstr. 35",
    "sg:city":"Berlin",
    "sg:postcode":"12555",
    "sg:province":"Berlin",
    "wof:name":"Studio K Text Bild Kommunikation",
    "wof:placetype":"venue"
},
  "geometry": {"coordinates":[13.58735466,52.4663276672],"type":"Point"}
}