{
  "type": "Feature",
  "properties": {
    "iso:country":"DE",
    "sg:address":"Wolfsegger Str. 16",
    "sg:city":"Wolfsegg",
    "sg:phone":"+49 9409/861250",
    "sg:postcode":"93195",
    "sg:province":"Bayern",
    "wof:name":"Georg Schafberger",
    "wof:placetype":"venue"
},
  "geometry": {"coordinates":[11.9773330688,49.1074066162],"type":"Point"}
}