{
  "type": "Feature",
  "properties": {
    "iso:country":"DE",
    "sg:address":"Neuh\u00e4user Str. 31",
    "sg:city":"Paderborn",
    "sg:phone":"+49 5251/22354",
    "sg:postcode":"33102",
    "sg:province":"Nordrhein-Westfalen",
    "wof:name":"Johannes Kohrs",
    "wof:placetype":"venue"
},
  "geometry": {"coordinates":[8.744594,51.72184],"type":"Point"}
}