{
  "type": "Feature",
  "properties": {
    "iso:country":"DE",
    "sg:address":"Kienitzer Str. 56",
    "sg:city":"Berlin",
    "sg:phone":"+49 30/8813170",
    "sg:postcode":"12053",
    "sg:province":"Berlin",
    "wof:name":"Imbi\u00df Yildz Song\u00fcl",
    "wof:placetype":"venue"
},
  "geometry": {"coordinates":[13.4334812164,52.47706604],"type":"Point"}
}