{
  "type": "Feature",
  "properties": {
    "iso:country":"DE",
    "sg:address":"Minden-Weseler Weg 60",
    "sg:city":"Enger",
    "sg:phone":"+49 5224/2832",
    "sg:postcode":"32130",
    "sg:province":"Nordrhein-Westfalen",
    "wof:name":"H. Tiemann",
    "wof:placetype":"venue"
},
  "geometry": {"coordinates":[8.570859,52.154285],"type":"Point"}
}