{
  "type": "Feature",
  "properties": {
    "iso:country":"DE",
    "sg:address":"St.-Martin-Str. 2",
    "sg:city":"Brigachtal",
    "sg:phone":"+49 7721/22244",
    "sg:postcode":"78086",
    "sg:province":"Baden-W\u00fcrttemberg",
    "wof:name":"Kath. Pfarramt St. Martin",
    "wof:placetype":"venue"
},
  "geometry": {"coordinates":[8.4700069427,48.015247345],"type":"Point"}
}