{
  "type": "Feature",
  "properties": {
    "iso:country":"DE",
    "sg:address":"Rugenbarg 61",
    "sg:city":"Norderstedt",
    "sg:phone":"+49 40/5282262",
    "sg:postcode":"22848",
    "sg:province":"Schleswig-Holstein",
    "wof:name":"Horst Drews Gmbh",
    "wof:placetype":"venue"
},
  "geometry": {"coordinates":[9.9883422852,53.6685523987],"type":"Point"}
}