{
  "type": "Feature",
  "properties": {
    "iso:country":"DE",
    "sg:address":"Leintal 12",
    "sg:city":"Alfdorf",
    "sg:phone":"+49 7172/937890",
    "sg:postcode":"73553",
    "sg:province":"Baden-W\u00fcrttemberg",
    "wof:name":"Spindler Gmbh",
    "wof:placetype":"venue"
},
  "geometry": {"coordinates":[9.688997,48.840935],"type":"Point"}
}