{
  "type": "Feature",
  "properties": {
    "iso:country":"DE",
    "sg:address":"Schaumburger Str. 28",
    "sg:city":"B\u00fcckeburg",
    "sg:phone":"+49 5722/4382",
    "sg:postcode":"31675",
    "sg:province":"Niedersachsen",
    "wof:name":"Friedrich Molthahn",
    "wof:placetype":"venue"
},
  "geometry": {"coordinates":[8.995282,52.280972],"type":"Point"}
}