{
  "type": "Feature",
  "properties": {
    "iso:country":"DE",
    "sg:address":"Beimoorweg 54",
    "sg:city":"Gro\u00dfhansdorf",
    "sg:phone":"+49 4102/61244",
    "sg:postcode":"22927",
    "sg:province":"Schleswig-Holstein",
    "wof:name":"G\u00fcnter Huget Steuerberater",
    "wof:placetype":"venue"
},
  "geometry": {"coordinates":[10.2909889221,53.6723136902],"type":"Point"}
}