{
  "type": "Feature",
  "properties": {
    "iso:country":"DE",
    "sg:address":"Westernfeld 25",
    "sg:city":"G\u00fctersloh",
    "sg:phone":"+49 5241/13666",
    "sg:postcode":"33334",
    "sg:province":"Nordrhein-Westfalen",
    "wof:name":"H. Seew\u00f6ster",
    "wof:placetype":"venue"
},
  "geometry": {"coordinates":[8.354796,51.903393],"type":"Point"}
}