{
  "type": "Feature",
  "properties": {
    "iso:country":"DE",
    "sg:address":"Heristiestr. 49",
    "sg:city":"Bad Driburg",
    "sg:phone":"+49 5253/940974",
    "sg:postcode":"33014",
    "sg:province":"Nordrhein-Westfalen",
    "wof:name":"T\u00f6lle Und Peine-t\u00f6lle",
    "wof:placetype":"venue"
},
  "geometry": {"coordinates":[9.096076,51.710503],"type":"Point"}
}