{
  "type": "Feature",
  "properties": {
    "iso:country":"DE",
    "sg:address":"Ramsauer Str. 102",
    "sg:city":"Berchtesgaden",
    "sg:phone":"+49 8652/3691",
    "sg:postcode":"83471",
    "sg:province":"Bayern",
    "wof:name":"Fremdenheim Rudolf Koller",
    "wof:placetype":"venue"
},
  "geometry": {"coordinates":[12.9916296005,47.6243286133],"type":"Point"}
}