{
  "type": "Feature",
  "properties": {
    "iso:country":"DE",
    "sg:address":"M\u00fchlenstr. 10",
    "sg:city":"K\u00f6then",
    "sg:phone":"+49 3496/554404",
    "sg:postcode":"06366",
    "sg:province":"Sachsen-Anhalt",
    "wof:name":"Jens Berger",
    "wof:placetype":"venue"
},
  "geometry": {"coordinates":[11.979782,51.749786],"type":"Point"}
}