{
  "type": "Feature",
  "properties": {
    "iso:country":"DE",
    "sg:address":"Hansestra\u00dfe 30b",
    "sg:city":"Borken",
    "sg:phone":"+49 2861/93390",
    "sg:postcode":"46325",
    "sg:province":"Nordrhein-Westfalen",
    "wof:name":"Borkener Kistenfabrik",
    "wof:placetype":"venue"
},
  "geometry": {"coordinates":[6.8851480484,51.8490982056],"type":"Point"}
}