{
  "type": "Feature",
  "properties": {
    "iso:country":"DE",
    "sg:address":"Lechstr. 5",
    "sg:city":"Landsberg",
    "sg:phone":"+49 8191/91950",
    "sg:postcode":"86899",
    "sg:province":"Bayern",
    "wof:name":"B\u00fcrgerstift Landsberg Seniorenheim",
    "wof:placetype":"venue"
},
  "geometry": {"coordinates":[10.874772,48.052925],"type":"Point"}
}