{
  "type": "Feature",
  "properties": {
    "iso:country":"DE",
    "sg:address":"Herbert-Weichmann-Str. 26",
    "sg:city":"Hamburg",
    "sg:postcode":"22085",
    "sg:province":"Hamburg",
    "wof:name":"Objektgesellschaft Leipzig Holbeinstra\u00dfe Mbh",
    "wof:placetype":"venue"
},
  "geometry": {"coordinates":[10.015124,53.570358],"type":"Point"}
}