{
  "type": "Feature",
  "properties": {
    "iso:country":"DE",
    "sg:address":"Orsberger Str. 1",
    "sg:city":"Erpel",
    "sg:phone":"+49 2644/2418",
    "sg:postcode":"53579",
    "sg:province":"Rheinland-Pfalz",
    "wof:name":"Werner Lindlohr Architekt",
    "wof:placetype":"venue"
},
  "geometry": {"coordinates":[7.238884,50.585655],"type":"Point"}
}