{
  "type": "Feature",
  "properties": {
    "iso:country":"DE",
    "sg:address":"Gustav-Stresemann-Str. 3",
    "sg:city":"Ensdorf",
    "sg:phone":"+49 6831/95620",
    "sg:postcode":"66806",
    "sg:province":"Saarland",
    "wof:name":"Rupp Edelst\u00e4hle Handelsgesellschaft Mbh",
    "wof:placetype":"venue"
},
  "geometry": {"coordinates":[6.7781748772,49.3073348999],"type":"Point"}
}