{
  "type": "Feature",
  "properties": {
    "iso:country":"DE",
    "sg:address":"Schmiechastr. 179",
    "sg:city":"Albstadt",
    "sg:phone":"+49 7431/90510",
    "sg:postcode":"72458",
    "sg:province":"Baden-W\u00fcrttemberg",
    "wof:name":"Carlo Le Figaro",
    "wof:placetype":"venue"
},
  "geometry": {"coordinates":[9.0282001495,48.2221488953],"type":"Point"}
}