{
  "type": "Feature",
  "properties": {
    "iso:country":"DE",
    "sg:address":"Friedhofstr. 1",
    "sg:city":"Rieschweiler",
    "sg:phone":"+49 4963/366076",
    "sg:postcode":"66509",
    "sg:province":"Rheinland-Pfalz",
    "wof:name":"Kreissparkasse Zweibr\u00fccken",
    "wof:placetype":"venue"
},
  "geometry": {"coordinates":[7.50185,49.24617],"type":"Point"}
}