{
  "type": "Feature",
  "properties": {
    "iso:country":"DE",
    "sg:address":"Saalstr. 22",
    "sg:city":"Saalfeld",
    "sg:phone":"+49 3671/54540",
    "sg:postcode":"07318",
    "sg:province":"Th\u00fcringen",
    "wof:name":"Friseurgenossenschaft Chic Eg",
    "wof:placetype":"venue"
},
  "geometry": {"coordinates":[11.363031,50.648758],"type":"Point"}
}