{
  "type": "Feature",
  "properties": {
    "iso:country":"DE",
    "sg:address":"Selkamp 12",
    "sg:city":"Dortmund",
    "sg:phone":"+49 231/44960",
    "sg:postcode":"44287",
    "sg:province":"Nordrhein-Westfalen",
    "wof:name":"Ingenieurb\u00fcro D\u00fcffel Ingenieurgesellschaft",
    "wof:placetype":"venue"
},
  "geometry": {"coordinates":[7.569562912,51.499622345],"type":"Point"}
}