{
  "type": "Feature",
  "properties": {
    "iso:country":"DE",
    "sg:address":"Hauptstr. 26",
    "sg:city":"Helmstedt",
    "sg:phone":"+49 5351/32005",
    "sg:postcode":"38350",
    "sg:province":"Niedersachsen",
    "wof:name":"Heinrich Schwarze",
    "wof:placetype":"venue"
},
  "geometry": {"coordinates":[10.97396,52.24358],"type":"Point"}
}