{
  "type": "Feature",
  "properties": {
    "iso:country":"DE",
    "sg:address":"Schlo\u00df",
    "sg:city":"B\u00fcckeburg",
    "sg:phone":"+49 5722/21014",
    "sg:postcode":"31675",
    "sg:province":"Niedersachsen",
    "wof:name":"Stadtarchiv",
    "wof:placetype":"venue"
},
  "geometry": {"coordinates":[9.045615,52.260075],"type":"Point"}
}