{
  "type": "Feature",
  "properties": {
    "iso:country":"DE",
    "sg:address":"Schulstr. 8",
    "sg:city":"Waldm\u00fcnchen",
    "sg:phone":"+49 9972/8353",
    "sg:postcode":"93449",
    "sg:province":"Bayern",
    "wof:name":"Max Kreuzer",
    "wof:placetype":"venue"
},
  "geometry": {"coordinates":[12.7072153091,49.3790550232],"type":"Point"}
}