{
  "type": "Feature",
  "properties": {
    "iso:country":"DE",
    "sg:address":"Winzerstr. 10",
    "sg:city":"Bonn",
    "sg:phone":"+49 228/230112",
    "sg:postcode":"53129",
    "sg:province":"Nordrhein-Westfalen",
    "wof:name":"Peter Karsten Maria Elsner-karsten",
    "wof:placetype":"venue"
},
  "geometry": {"coordinates":[7.1150507927,50.7031860352],"type":"Point"}
}