{
  "type": "Feature",
  "properties": {
    "iso:country":"DE",
    "sg:address":"Sophienstr. 1",
    "sg:city":"Schildow",
    "sg:phone":"+49 33056/2520",
    "sg:postcode":"16552",
    "sg:province":"Brandenburg",
    "wof:name":"Datennetze In Berlin E. Kfm.",
    "wof:placetype":"venue"
},
  "geometry": {"coordinates":[13.3748703003,52.6524238586],"type":"Point"}
}