{
  "type": "Feature",
  "properties": {
    "iso:country":"DE",
    "sg:address":"Maiplatz 5",
    "sg:city":"Plettenberg",
    "sg:phone":"+49 2391/3966",
    "sg:postcode":"58840",
    "sg:province":"Nordrhein-Westfalen",
    "wof:name":"Schlemmeria-restaurant",
    "wof:placetype":"venue"
},
  "geometry": {"coordinates":[7.8736200333,51.2129249573],"type":"Point"}
}