{
  "type": "Feature",
  "properties": {
    "iso:country":"DE",
    "sg:address":"\u00dcber dem Dieterstedter Bache",
    "sg:city":"Apolda",
    "sg:phone":"+49 3644/555925",
    "sg:postcode":"99510",
    "sg:province":"Th\u00fcringen",
    "wof:name":"Handwerk-und Schneider Gmbh I.g.",
    "wof:placetype":"venue"
},
  "geometry": {"coordinates":[11.4651203156,51.0087585449],"type":"Point"}
}