{
  "type": "Feature",
  "properties": {
    "iso:country":"DE",
    "sg:address":"Erich-Hausmann-Str 1",
    "sg:city":"Trebsen",
    "sg:phone":"+49 34383/91180",
    "sg:postcode":"04687",
    "sg:province":"Sachsen",
    "wof:name":"Bavaria Lager- Und Spedition Gmbh",
    "wof:placetype":"venue"
},
  "geometry": {"coordinates":[12.7343530655,51.2849235535],"type":"Point"}
}