{
  "type": "Feature",
  "properties": {
    "iso:country":"DE",
    "sg:address":"Mexikoring 19",
    "sg:city":"Hamburg",
    "sg:phone":"+49 40/6390630",
    "sg:postcode":"22297",
    "sg:province":"Hamburg",
    "wof:name":"Alvern Gmbh",
    "wof:placetype":"venue"
},
  "geometry": {"coordinates":[10.023308,53.603039],"type":"Point"}
}