{
  "type": "Feature",
  "properties": {
    "iso:country":"DE",
    "sg:address":"Oberfeldstr. 91",
    "sg:city":"Berlin",
    "sg:phone":"+49 30",
    "sg:postcode":"12683",
    "sg:province":"Berlin",
    "wof:name":"Auto Centrum Biesdorf",
    "wof:placetype":"venue"
},
  "geometry": {"coordinates":[13.5592594147,52.5338745117],"type":"Point"}
}