{
  "type": "Feature",
  "properties": {
    "iso:country":"DE",
    "sg:address":"Hinterbirkenhof 13",
    "sg:city":"Hinterbirkenhof",
    "sg:phone":"+49 7144/36144",
    "sg:postcode":"71711",
    "sg:province":"Baden-W\u00fcrttemberg",
    "wof:name":"Felix S\u00e4lzer",
    "wof:placetype":"venue"
},
  "geometry": {"coordinates":[9.278525,48.965771],"type":"Point"}
}