{
  "type": "Feature",
  "properties": {
    "iso:country":"DE",
    "sg:address":"Obergasse 27",
    "sg:city":"Schlangenbad",
    "sg:phone":"+49 6129/512960",
    "sg:postcode":"65388",
    "sg:province":"Hessen",
    "wof:name":"Dr. Lothar Pfeifer Patentanwalt",
    "wof:placetype":"venue"
},
  "geometry": {"coordinates":[8.1012802124,50.110004425],"type":"Point"}
}