{
  "type": "Feature",
  "properties": {
    "iso:country":"DE",
    "sg:address":"Zschernweg 17",
    "sg:city":"L\u00f6bnitz",
    "sg:phone":"+49 34208/72207",
    "sg:postcode":"04509",
    "sg:province":"Sachsen",
    "wof:name":"Lutz S\u00fcpple",
    "wof:placetype":"venue"
},
  "geometry": {"coordinates":[12.457726,51.590347],"type":"Point"}
}