{
  "type": "Feature",
  "properties": {
    "iso:country":"DE",
    "sg:address":"Ladestr. 15",
    "sg:city":"Hoisdorf",
    "sg:phone":"+49 4107/4027",
    "sg:postcode":"22955",
    "sg:province":"Schleswig-Holstein",
    "wof:name":"J\u00f6rg Steffen Architekt",
    "wof:placetype":"venue"
},
  "geometry": {"coordinates":[10.33431,53.64603],"type":"Point"}
}