{
  "type": "Feature",
  "properties": {
    "iso:country":"DE",
    "sg:address":"Am Hinterwald 8",
    "sg:city":"Dietzenbach",
    "sg:phone":"+49 6074/23314",
    "sg:postcode":"63128",
    "sg:province":"Hessen",
    "wof:name":"H\u00e4uslicher Pflegedienst K. & M. Z\u00f6ller Gmbh",
    "wof:placetype":"venue"
},
  "geometry": {"coordinates":[8.771885,50.01693],"type":"Point"}
}