{
  "type": "Feature",
  "properties": {
    "iso:country":"DE",
    "sg:address":"Bredeneyer Str. 134",
    "sg:city":"Essen",
    "sg:phone":"+49 201/412257",
    "sg:postcode":"45133",
    "sg:province":"Nordrhein-Westfalen",
    "wof:name":"Pizzeria Caravella",
    "wof:placetype":"venue"
},
  "geometry": {"coordinates":[6.9936227798,51.4122772217],"type":"Point"}
}