{
  "type": "Feature",
  "properties": {
    "iso:country":"DE",
    "sg:address":"Marienstr. 2a",
    "sg:city":"Quierschied",
    "sg:phone":"+49 6897/966054",
    "sg:postcode":"66287",
    "sg:province":"Saarland",
    "wof:name":"Horst St\u00f6hr Drogerie",
    "wof:placetype":"venue"
},
  "geometry": {"coordinates":[7.053293,49.324844],"type":"Point"}
}