{
  "type": "Feature",
  "properties": {
    "iso:country":"DE",
    "sg:address":"Lange Str. 22",
    "sg:city":"Havelberg",
    "sg:phone":"+49 39387/88870",
    "sg:postcode":"39539",
    "sg:province":"Sachsen-Anhalt",
    "wof:name":"Lichthaus-pension",
    "wof:placetype":"venue"
},
  "geometry": {"coordinates":[12.073261261,52.8242492676],"type":"Point"}
}