{
  "type": "Feature",
  "properties": {
    "iso:country":"DE",
    "sg:address":"Siedlung 2",
    "sg:city":"Edertal",
    "sg:phone":"+49 5623/4243",
    "sg:postcode":"34549",
    "sg:province":"Hessen",
    "wof:name":"Helmut Relke",
    "wof:placetype":"venue"
},
  "geometry": {"coordinates":[9.12731,51.194813],"type":"Point"}
}