{
  "type": "Feature",
  "properties": {
    "iso:country":"DE",
    "sg:address":"Friedrichstr. 84",
    "sg:city":"Dortmund",
    "sg:phone":"+49 231/998930",
    "sg:postcode":"44137",
    "sg:province":"Nordrhein-Westfalen",
    "wof:name":"Nick Verwaltungs Kg",
    "wof:placetype":"venue"
},
  "geometry": {"coordinates":[7.453732,51.508247],"type":"Point"}
}