{
  "type": "Feature",
  "properties": {
    "iso:country":"DE",
    "sg:address":"Friedrich-Wolf-Str. 9",
    "sg:city":"Suhl",
    "sg:phone":"+49 3681/306660",
    "sg:postcode":"98527",
    "sg:province":"Th\u00fcringen",
    "wof:name":"J\u00fcrgen Zimmermann",
    "wof:placetype":"venue"
},
  "geometry": {"coordinates":[10.7048206329,50.6112747192],"type":"Point"}
}