{
  "type": "Feature",
  "properties": {
    "iso:country":"DE",
    "sg:address":"Polsumer Str. 121",
    "sg:city":"Gelsenkirchen",
    "sg:phone":"+49 209/64909",
    "sg:postcode":"45896",
    "sg:province":"Nordrhein-Westfalen",
    "wof:name":"Karl-heinz Temminghoff",
    "wof:placetype":"venue"
},
  "geometry": {"coordinates":[7.0514788628,51.595500946],"type":"Point"}
}