{
  "type": "Feature",
  "properties": {
    "iso:country":"DE",
    "sg:address":"Hellersdorfer Str. 57",
    "sg:city":"Berlin",
    "sg:phone":"+49 30/56301933",
    "sg:postcode":"12619",
    "sg:province":"Berlin",
    "wof:name":"Wolfgang P\u00f6schick",
    "wof:placetype":"venue"
},
  "geometry": {"coordinates":[13.5879859924,52.5199813843],"type":"Point"}
}