{
  "type": "Feature",
  "properties": {
    "iso:country":"DE",
    "sg:address":"M\u00fcnchhof 1",
    "sg:city":"Dannstadt-Schauernheim",
    "sg:phone":"+49 6231/91980",
    "sg:postcode":"67125",
    "sg:province":"Rheinland-Pfalz",
    "wof:name":"Gerd Sahler",
    "wof:placetype":"venue"
},
  "geometry": {"coordinates":[8.3255367279,49.4176101685],"type":"Point"}
}