{
  "type": "Feature",
  "properties": {
    "iso:country":"DE",
    "sg:address":"Am Pappelhain 10",
    "sg:city":"Groitzsch",
    "sg:phone":"+49 4934/2967330",
    "sg:postcode":"04539",
    "sg:province":"Sachsen",
    "wof:name":"S\u00c4chsische Schlossfabrik Gmbh",
    "wof:placetype":"venue"
},
  "geometry": {"coordinates":[12.2831468582,51.1460571289],"type":"Point"}
}