{
  "type": "Feature",
  "properties": {
    "iso:country":"DE",
    "sg:address":"Karl-Marx-Str. 11",
    "sg:city":"Ducherow",
    "sg:phone":"+49 39726/28009",
    "sg:postcode":"17398",
    "sg:province":"Mecklenburg-Vorpommern",
    "wof:name":"Holzbau Ducherow Gebr. Holl Ohg",
    "wof:placetype":"venue"
},
  "geometry": {"coordinates":[13.778166,53.76342],"type":"Point"}
}