{
  "type": "Feature",
  "properties": {
    "iso:country":"DE",
    "sg:address":"Kolonnenstr. 12",
    "sg:city":"Berlin",
    "sg:phone":"+49 30/7875973",
    "sg:postcode":"10829",
    "sg:province":"Berlin",
    "wof:name":"Avci & Ilaslan",
    "wof:placetype":"venue"
},
  "geometry": {"coordinates":[13.3620195389,52.485584259],"type":"Point"}
}