{
  "type": "Feature",
  "properties": {
    "iso:country":"DE",
    "sg:address":"Schwimmbadweg 2",
    "sg:city":"Kandern",
    "sg:phone":"+49 7626/7874",
    "sg:postcode":"79400",
    "sg:province":"Baden-W\u00fcrttemberg",
    "wof:name":"Campingplatz",
    "wof:placetype":"venue"
},
  "geometry": {"coordinates":[7.660136,47.720356],"type":"Point"}
}