{
  "type": "Feature",
  "properties": {
    "iso:country":"DE",
    "sg:address":"Parcusstr. 21",
    "sg:city":"Darmstadt",
    "sg:phone":"+49 6151/294383",
    "sg:postcode":"64293",
    "sg:province":"Hessen",
    "wof:name":"Irish Pub",
    "wof:placetype":"venue"
},
  "geometry": {"coordinates":[8.6471824646,49.8814888],"type":"Point"}
}