{
  "type": "Feature",
  "properties": {
    "iso:country":"DE",
    "sg:address":"Goethestr. 11",
    "sg:city":"Bensheim",
    "sg:phone":"+49 6251/70970",
    "sg:postcode":"64625",
    "sg:province":"Hessen",
    "wof:name":"Br\u00e4uer Aufbereitungsmaschinen Gmbh & Co. F\u00f6rderanlagen Kg",
    "wof:placetype":"venue"
},
  "geometry": {"coordinates":[8.616946,49.705215],"type":"Point"}
}