{
  "type": "Feature",
  "properties": {
    "iso:country":"DE",
    "sg:address":"Schlo\u00dfstr. 4",
    "sg:city":"Dessau",
    "sg:phone":"+49 340/2213827",
    "sg:postcode":"06844",
    "sg:province":"Sachsen-Anhalt",
    "wof:name":"D.-p. Peschel & M. Lutze Gbr",
    "wof:placetype":"venue"
},
  "geometry": {"coordinates":[12.247565,51.834595],"type":"Point"}
}