{
  "type": "Feature",
  "properties": {
    "iso:country":"DE",
    "sg:address":"M\u00fcnchener Str. 63",
    "sg:city":"Essen",
    "sg:postcode":"45145",
    "sg:province":"Nordrhein-Westfalen",
    "wof:name":"Horst Peter Grundst\u00fccksverwaltungs Gmbh",
    "wof:placetype":"venue"
},
  "geometry": {"coordinates":[6.994576931,51.4480133057],"type":"Point"}
}