{
  "type": "Feature",
  "properties": {
    "iso:country":"DE",
    "sg:address":"Hauptstr. 33",
    "sg:city":"Wolfenb\u00fcttel",
    "sg:phone":"+49 5331/1315",
    "sg:postcode":"38304",
    "sg:province":"Niedersachsen",
    "wof:name":"Wenzel & Co. Gmbh",
    "wof:placetype":"venue"
},
  "geometry": {"coordinates":[10.515607,52.17421],"type":"Point"}
}