{
  "type": "Feature",
  "properties": {
    "iso:country":"DE",
    "sg:address":"Rosenstr. 52",
    "sg:city":"D\u00fcsseldorf",
    "sg:phone":"+49 211/4983199",
    "sg:postcode":"40479",
    "sg:province":"Nordrhein-Westfalen",
    "wof:name":"Paul Spiegel",
    "wof:placetype":"venue"
},
  "geometry": {"coordinates":[6.7839531898,51.2334938049],"type":"Point"}
}