{
  "type": "Feature",
  "properties": {
    "iso:country":"DE",
    "sg:address":"Heinrich-Helbing-Str. 16",
    "sg:city":"Hamburg",
    "sg:phone":"+49 40/616210",
    "sg:postcode":"22177",
    "sg:province":"Hamburg",
    "wof:name":"H. Heuchert",
    "wof:placetype":"venue"
},
  "geometry": {"coordinates":[10.0577707291,53.59608078],"type":"Point"}
}