{
  "type": "Feature",
  "properties": {
    "iso:country":"DE",
    "sg:address":"Tramplerstr. 44",
    "sg:city":"Lahr",
    "sg:phone":"+49 7821/23239",
    "sg:postcode":"77933",
    "sg:province":"Baden-W\u00fcrttemberg",
    "wof:name":"G. Lehmann Gmbh",
    "wof:placetype":"venue"
},
  "geometry": {"coordinates":[7.857281208,48.3341026306],"type":"Point"}
}