{
  "type": "Feature",
  "properties": {
    "iso:country":"DE",
    "sg:address":"Virchowstr. 1",
    "sg:city":"Wetzlar",
    "sg:phone":"+49 6441/71038",
    "sg:postcode":"35578",
    "sg:province":"Hessen",
    "wof:name":"Friedrich Balasch Gmbh",
    "wof:placetype":"venue"
},
  "geometry": {"coordinates":[8.534715,50.540939],"type":"Point"}
}