{
  "type": "Feature",
  "properties": {
    "iso:country":"DE",
    "sg:address":"Am Eichenhain 10",
    "sg:city":"Reinstorf",
    "sg:phone":"+49 4137/345",
    "sg:postcode":"21400",
    "sg:province":"Niedersachsen",
    "wof:name":"Wilhelm Ferlemann",
    "wof:placetype":"venue"
},
  "geometry": {"coordinates":[10.581358,53.239861],"type":"Point"}
}