{
  "type": "Feature",
  "properties": {
    "iso:country":"DE",
    "sg:address":"Herzogstr. 10",
    "sg:city":"K\u00f6ln",
    "sg:phone":"+49 221/253191",
    "sg:postcode":"50667",
    "sg:province":"Nordrhein-Westfalen",
    "wof:name":"Pietas Allgemeine Bestattungsgesellschaft Mbh",
    "wof:placetype":"venue"
},
  "geometry": {"coordinates":[6.9539442062,50.9369850159],"type":"Point"}
}