{
  "type": "Feature",
  "properties": {
    "iso:country":"DE",
    "sg:address":"Wiesenstr. 2",
    "sg:city":"Bedburg-Hau",
    "sg:phone":"+49 2821/40311",
    "sg:postcode":"47551",
    "sg:province":"Nordrhein-Westfalen",
    "wof:name":"Karl-heinz Ebbing",
    "wof:placetype":"venue"
},
  "geometry": {"coordinates":[6.142676,51.767128],"type":"Point"}
}