{
  "type": "Feature",
  "properties": {
    "iso:country":"DE",
    "sg:address":"Veldorfer Str. 18",
    "sg:city":"Velburg",
    "sg:phone":"+49 9182/1307",
    "sg:postcode":"92355",
    "sg:province":"Bayern",
    "wof:name":"Walter Hummel",
    "wof:placetype":"venue"
},
  "geometry": {"coordinates":[11.668505,49.226345],"type":"Point"}
}