{
  "type": "Feature",
  "properties": {
    "iso:country":"DE",
    "sg:address":"Scheffelstr. 27",
    "sg:city":"Friedrichshafen",
    "sg:phone":"+49 7541/24667",
    "sg:postcode":"88045",
    "sg:province":"Baden-W\u00fcrttemberg",
    "wof:name":"A. Mueller",
    "wof:placetype":"venue"
},
  "geometry": {"coordinates":[9.4798030853,47.6572952271],"type":"Point"}
}