{
  "type": "Feature",
  "properties": {
    "iso:country":"DE",
    "sg:address":"Ingolst\u00e4dter Str. 19",
    "sg:city":"Eichst\u00e4tt",
    "sg:phone":"+49 8421/3142",
    "sg:postcode":"85072",
    "sg:province":"Bayern",
    "wof:name":"Jakob Fath Bootsvermietungen",
    "wof:placetype":"venue"
},
  "geometry": {"coordinates":[11.1823091507,48.8890838623],"type":"Point"}
}