{
  "type": "Feature",
  "properties": {
    "iso:country":"DE",
    "sg:address":"Silgestr. 1",
    "sg:city":"Ludwigshafen",
    "sg:phone":"+49 621/558450",
    "sg:postcode":"67067",
    "sg:province":"Rheinland-Pfalz",
    "wof:name":"Courage Swiss Vertriebsb\u00fcro",
    "wof:placetype":"venue"
},
  "geometry": {"coordinates":[8.373348,49.455154],"type":"Point"}
}