{
  "type": "Feature",
  "properties": {
    "iso:country":"DE",
    "sg:address":"Stiegelenweg 16",
    "sg:city":"Staufen",
    "sg:phone":"+49 7633/50999",
    "sg:postcode":"79219",
    "sg:province":"Baden-W\u00fcrttemberg",
    "wof:name":"Armin Scherer Architekt",
    "wof:placetype":"venue"
},
  "geometry": {"coordinates":[7.72037,47.879856],"type":"Point"}
}