{
  "type": "Feature",
  "properties": {
    "iso:country":"DE",
    "sg:address":"Auf dem Spitt 23",
    "sg:city":"Fr\u00f6ndenberg",
    "sg:postcode":"58730",
    "sg:province":"Nordrhein-Westfalen",
    "wof:name":"Mh Bandstahl Gmbh",
    "wof:placetype":"venue"
},
  "geometry": {"coordinates":[7.7435641289,51.4965896606],"type":"Point"}
}