{
  "type": "Feature",
  "properties": {
    "iso:country":"DE",
    "sg:address":"Hoch\u00e4ckerstr. 110",
    "sg:city":"M\u00fcnchen",
    "sg:phone":"+49 89/6707872",
    "sg:postcode":"81737",
    "sg:province":"Bayern",
    "wof:name":"K. Platten Mech. Werkstatt",
    "wof:placetype":"venue"
},
  "geometry": {"coordinates":[11.626985,48.101208],"type":"Point"}
}