{
  "type": "Feature",
  "properties": {
    "iso:country":"DE",
    "sg:address":"Hohe Str. 138",
    "sg:city":"K\u00f6ln",
    "sg:phone":"+49 221/2582667",
    "sg:postcode":"50667",
    "sg:province":"Nordrhein-Westfalen",
    "wof:name":"China-restaurant Shanghai",
    "wof:placetype":"venue"
},
  "geometry": {"coordinates":[6.9564919472,50.9392967224],"type":"Point"}
}