{
  "type": "Feature",
  "properties": {
    "iso:country":"DE",
    "sg:address":"Burgallee 16",
    "sg:city":"Hanau",
    "sg:phone":"+49 6181/23496",
    "sg:postcode":"63454",
    "sg:province":"Hessen",
    "wof:name":"Reusswig & Weniger Ohg",
    "wof:placetype":"venue"
},
  "geometry": {"coordinates":[8.88494,50.142319],"type":"Point"}
}