{
  "type": "Feature",
  "properties": {
    "iso:country":"DE",
    "sg:address":"Leckingser Str. 229",
    "sg:city":"Iserlohn",
    "sg:phone":"+49 4923/7140262",
    "sg:postcode":"58640",
    "sg:province":"Nordrhein-Westfalen",
    "wof:name":"Thomas Gmbh",
    "wof:placetype":"venue"
},
  "geometry": {"coordinates":[7.6754078865,51.4249382019],"type":"Point"}
}