{
  "type": "Feature",
  "properties": {
    "iso:country":"DE",
    "sg:address":"Pommernstr. 14",
    "sg:city":"Freilassing",
    "sg:phone":"+49 8654/63010",
    "sg:postcode":"83395",
    "sg:province":"Bayern",
    "wof:name":"Sch\u00f6ssmetall Gmbh & Co. Kg",
    "wof:placetype":"venue"
},
  "geometry": {"coordinates":[12.963129,47.852463],"type":"Point"}
}