{
  "type": "Feature",
  "properties": {
    "iso:country":"DE",
    "sg:address":"Vetschauer Str. 9",
    "sg:city":"Calau",
    "sg:phone":"+49 3541/801491",
    "sg:postcode":"03205",
    "sg:province":"Brandenburg",
    "wof:name":"Total Tankstelle",
    "wof:placetype":"venue"
},
  "geometry": {"coordinates":[13.9550628662,51.7483215332],"type":"Point"}
}