{
  "type": "Feature",
  "properties": {
    "iso:country":"DE",
    "sg:address":"Schlo\u00dfstr. 59 c",
    "sg:city":"Stuttgart",
    "sg:phone":"+49 711/616431",
    "sg:postcode":"70176",
    "sg:province":"Baden-W\u00fcrttemberg",
    "wof:name":"L\u00f6wen-apotheke",
    "wof:placetype":"venue"
},
  "geometry": {"coordinates":[9.164876,48.776962],"type":"Point"}
}