{
  "type": "Feature",
  "properties": {
    "iso:country":"DE",
    "sg:address":"Elmendorfer Str. 5",
    "sg:city":"Bad Zwischenahn",
    "sg:phone":"+49 4403/71606",
    "sg:postcode":"26160",
    "sg:province":"Niedersachsen",
    "wof:name":"Schnick- Schnack",
    "wof:placetype":"venue"
},
  "geometry": {"coordinates":[7.979091,53.197464],"type":"Point"}
}