{
  "type": "Feature",
  "properties": {
    "iso:country":"DE",
    "sg:address":"Am Handelspark 2",
    "sg:city":"Bad Doberan",
    "sg:phone":"+49 38203/63488",
    "sg:postcode":"18209",
    "sg:province":"Mecklenburg-Vorpommern",
    "wof:name":"K\u00fcche Attraktiv Gmbh",
    "wof:placetype":"venue"
},
  "geometry": {"coordinates":[11.920999,54.108624],"type":"Point"}
}