{
  "type": "Feature",
  "properties": {
    "iso:country":"DE",
    "sg:address":"Hiltroper Landwehr 144",
    "sg:city":"Bochum",
    "sg:phone":"+49 234/850605",
    "sg:postcode":"44805",
    "sg:province":"Nordrhein-Westfalen",
    "wof:name":"Plange",
    "wof:placetype":"venue"
},
  "geometry": {"coordinates":[7.261642,51.525253],"type":"Point"}
}