{
  "type": "Feature",
  "properties": {
    "iso:country":"DE",
    "sg:address":"Basler Str. 81",
    "sg:city":"L\u00f6rrach",
    "sg:phone":"+49 7621/48574",
    "sg:postcode":"79540",
    "sg:province":"Baden-W\u00fcrttemberg",
    "wof:name":"Christine Ahlschwede",
    "wof:placetype":"venue"
},
  "geometry": {"coordinates":[7.6590600014,47.6044921875],"type":"Point"}
}