{
  "type": "Feature",
  "properties": {
    "iso:country":"DE",
    "sg:address":"Venloer Str. 313",
    "sg:city":"K\u00f6ln",
    "sg:phone":"+49 221/9520306",
    "sg:postcode":"50823",
    "sg:province":"Nordrhein-Westfalen",
    "wof:name":"Kochl\u00f6ffel Gmbh & Co. Kg",
    "wof:placetype":"venue"
},
  "geometry": {"coordinates":[6.9195151329,50.9484901428],"type":"Point"}
}