{
  "type": "Feature",
  "properties": {
    "iso:country":"DE",
    "sg:address":"Steinkuhlenstr. 19",
    "sg:city":"Bad Salzuflen",
    "sg:phone":"+49 5222/6622",
    "sg:postcode":"32108",
    "sg:province":"Nordrhein-Westfalen",
    "wof:name":"Herbert Wolff Architekt",
    "wof:placetype":"venue"
},
  "geometry": {"coordinates":[8.78133,52.099434],"type":"Point"}
}