{
  "type": "Feature",
  "properties": {
    "iso:country":"DE",
    "sg:address":"Kuseler Str. 31",
    "sg:city":"St. Wendel",
    "sg:phone":"+49 6856/780",
    "sg:postcode":"66606",
    "sg:province":"Saarland",
    "wof:name":"Margarethen-apotheke",
    "wof:placetype":"venue"
},
  "geometry": {"coordinates":[7.252865,49.469418],"type":"Point"}
}