{
  "type": "Feature",
  "properties": {
    "iso:country":"DE",
    "sg:address":"Am Schafstrieb 26",
    "sg:city":"Bad Orb",
    "sg:phone":"+49 6052/6730",
    "sg:postcode":"63619",
    "sg:province":"Hessen",
    "wof:name":"B. Walter",
    "wof:placetype":"venue"
},
  "geometry": {"coordinates":[9.347650528,50.2332649231],"type":"Point"}
}