{
  "type": "Feature",
  "properties": {
    "iso:country":"DE",
    "sg:address":"Athenstr. 14",
    "sg:city":"Zweibr\u00fccken",
    "sg:phone":"+49 6332/40535",
    "sg:postcode":"66482",
    "sg:province":"Rheinland-Pfalz",
    "wof:name":"G. Platz",
    "wof:placetype":"venue"
},
  "geometry": {"coordinates":[7.3881278038,49.2581520081],"type":"Point"}
}