{
  "type": "Feature",
  "properties": {
    "iso:country":"DE",
    "sg:address":"Zeilweg 11",
    "sg:city":"Magstadt",
    "sg:phone":"+49 7159/43993",
    "sg:postcode":"71106",
    "sg:province":"Baden-W\u00fcrttemberg",
    "wof:name":"J\u00f6rg-achim Mahrt Architekt",
    "wof:placetype":"venue"
},
  "geometry": {"coordinates":[8.952072,48.745945],"type":"Point"}
}