{
  "type": "Feature",
  "properties": {
    "iso:country":"DE",
    "sg:address":"Lingener Str. 11",
    "sg:city":"L\u00fcnne",
    "sg:phone":"+49 5906/9070",
    "sg:postcode":"48480",
    "sg:province":"Niedersachsen",
    "wof:name":"Degener Gmbh",
    "wof:placetype":"venue"
},
  "geometry": {"coordinates":[7.4290289879,52.42370224],"type":"Point"}
}