{
  "type": "Feature",
  "properties": {
    "iso:country":"DE",
    "sg:address":"Bachstr. 52",
    "sg:city":"Altena",
    "sg:phone":"+49 2352/22958",
    "sg:postcode":"58762",
    "sg:province":"Nordrhein-Westfalen",
    "wof:name":"E. Harte",
    "wof:placetype":"venue"
},
  "geometry": {"coordinates":[7.676266,51.30151],"type":"Point"}
}