{
  "type": "Feature",
  "properties": {
    "iso:country":"DE",
    "sg:address":"Finkenweg 12",
    "sg:city":"Zw\u00f6nitz",
    "sg:postcode":"08297",
    "sg:province":"Sachsen",
    "wof:name":"Dr. Med. Peter J\u00e4hn",
    "wof:placetype":"venue"
},
  "geometry": {"coordinates":[12.82165,50.648449],"type":"Point"}
}