{
  "type": "Feature",
  "properties": {
    "iso:country":"DE",
    "sg:address":"Robert-Bosch-Str. 9",
    "sg:city":"Garching",
    "sg:phone":"+49 89/32928006",
    "sg:postcode":"85748",
    "sg:province":"Bayern",
    "wof:name":"Ssg Spedition Gmbh",
    "wof:placetype":"venue"
},
  "geometry": {"coordinates":[-110.7298736572,32.1919593811],"type":"Point"}
}