{
  "type": "Feature",
  "properties": {
    "iso:country":"DE",
    "sg:address":"Nunsdorfer Ring 18",
    "sg:city":"Berlin",
    "sg:phone":"+49 30/7239720",
    "sg:postcode":"12277",
    "sg:province":"Berlin",
    "wof:name":"Komplet Kg B\u00e4ckereigrundstoff",
    "wof:placetype":"venue"
},
  "geometry": {"coordinates":[13.38281,52.406929],"type":"Point"}
}