{
  "type": "Feature",
  "properties": {
    "iso:country":"DE",
    "sg:address":"Lortzingstr. 17",
    "sg:city":"Mannheim",
    "sg:phone":"+49 621/332817",
    "sg:postcode":"68169",
    "sg:province":"Baden-W\u00fcrttemberg",
    "wof:name":"Flora",
    "wof:placetype":"venue"
},
  "geometry": {"coordinates":[8.4691457748,49.4987258911],"type":"Point"}
}