{
  "type": "Feature",
  "properties": {
    "iso:country":"DE",
    "sg:address":"Lessingstr. 35",
    "sg:city":"Neu Wulmstorf",
    "sg:phone":"+49 40/7001990",
    "sg:postcode":"21629",
    "sg:province":"Niedersachsen",
    "wof:name":"Ernst Peters Gmbh",
    "wof:placetype":"venue"
},
  "geometry": {"coordinates":[9.777607,53.46228],"type":"Point"}
}