{
  "type": "Feature",
  "properties": {
    "iso:country":"DE",
    "sg:address":"Bahnhofstr. 68",
    "sg:city":"Weibern",
    "sg:phone":"+49 2655/960283",
    "sg:postcode":"56745",
    "sg:province":"Rheinland-Pfalz",
    "wof:name":"Albert Fronert Inh. Hans Fronert",
    "wof:placetype":"venue"
},
  "geometry": {"coordinates":[7.1512718201,50.4084777832],"type":"Point"}
}