{
  "type": "Feature",
  "properties": {
    "iso:country":"DE",
    "sg:address":"Schillerstr. 3",
    "sg:city":"Tannhausen",
    "sg:phone":"+49 4979/64441",
    "sg:postcode":"73497",
    "sg:province":"Baden-W\u00fcrttemberg",
    "wof:name":"Raiffeisenbank Tannhausen Eg",
    "wof:placetype":"venue"
},
  "geometry": {"coordinates":[10.363558,48.97953],"type":"Point"}
}