{
  "type": "Feature",
  "properties": {
    "iso:country":"DE",
    "sg:address":"Schenkendorfstr. 5",
    "sg:city":"Regensburg",
    "sg:postcode":"93049",
    "sg:province":"Bayern",
    "wof:name":"Rudolf Schels Beteiligungs Gmbh",
    "wof:placetype":"venue"
},
  "geometry": {"coordinates":[12.078524,49.021488],"type":"Point"}
}