{
  "type": "Feature",
  "properties": {
    "iso:country":"DE",
    "sg:address":"Marktstr. 2",
    "sg:city":"Uetze",
    "sg:phone":"+49 5173/2548",
    "sg:postcode":"31311",
    "sg:province":"Niedersachsen",
    "wof:name":"Jugendcafe",
    "wof:placetype":"venue"
},
  "geometry": {"coordinates":[10.202781,52.470131],"type":"Point"}
}