{
  "type": "Feature",
  "properties": {
    "iso:country":"DE",
    "sg:address":"Hansering 17",
    "sg:city":"Halle",
    "sg:phone":"+49 345/28517",
    "sg:postcode":"06108",
    "sg:province":"Sachsen-Anhalt",
    "wof:name":"Landtechnik Sachsen-anhalt E. V.",
    "wof:placetype":"venue"
},
  "geometry": {"coordinates":[11.97353,51.484573],"type":"Point"}
}