{
  "type": "Feature",
  "properties": {
    "iso:country":"DE",
    "sg:address":"74575",
    "sg:city":"Schrozberg-Leuzendorf",
    "sg:postcode":"74575",
    "sg:province":"Baden-W\u00fcrttemberg",
    "wof:name":"Raiffeisenbank Leuzendorf Eg",
    "wof:placetype":"venue"
},
  "geometry": {"coordinates":[10.09156,49.347408],"type":"Point"}
}