{
  "type": "Feature",
  "properties": {
    "iso:country":"DE",
    "sg:address":"Georg-Reism\u00fcller-Str. 18",
    "sg:city":"M\u00fcnchen",
    "sg:postcode":"80999",
    "sg:province":"Bayern",
    "wof:name":"Event Solutions E. K.",
    "wof:placetype":"venue"
},
  "geometry": {"coordinates":[11.465637,48.193005],"type":"Point"}
}