{
  "type": "Feature",
  "properties": {
    "iso:country":"DE",
    "sg:address":"Schlei\u00dfbergstr. 43",
    "sg:city":"Ohorn",
    "sg:phone":"+49 35955/73680",
    "sg:postcode":"01896",
    "sg:province":"Sachsen",
    "wof:name":"Bernd Hennersdorf",
    "wof:placetype":"venue"
},
  "geometry": {"coordinates":[14.0559091568,51.1803245544],"type":"Point"}
}