{
  "type": "Feature",
  "properties": {
    "iso:country":"DE",
    "sg:address":"Waldstr. 126",
    "sg:city":"Castrop-Rauxel",
    "sg:phone":"+49 2367/180777",
    "sg:postcode":"44577",
    "sg:province":"Nordrhein-Westfalen",
    "wof:name":"Ralf Ohlinger Rechtsanwalt",
    "wof:placetype":"venue"
},
  "geometry": {"coordinates":[7.3114061356,51.6090660095],"type":"Point"}
}