{
  "type": "Feature",
  "properties": {
    "iso:country":"DE",
    "sg:address":"Kahrstr. 71",
    "sg:city":"Niederkr\u00fcchten",
    "sg:phone":"+49 2163/82502",
    "sg:postcode":"41372",
    "sg:province":"Nordrhein-Westfalen",
    "wof:name":"W. Frettl\u00f6h",
    "wof:placetype":"venue"
},
  "geometry": {"coordinates":[6.2265501022,51.2142410278],"type":"Point"}
}