{
  "type": "Feature",
  "properties": {
    "iso:country":"DE",
    "sg:address":"Steinweg 8",
    "sg:city":"Ahnatal",
    "sg:phone":"+49 5609/373",
    "sg:postcode":"34292",
    "sg:province":"Hessen",
    "wof:name":"R. Koch",
    "wof:placetype":"venue"
},
  "geometry": {"coordinates":[9.393183,51.366745],"type":"Point"}
}