{
  "type": "Feature",
  "properties": {
    "iso:country":"DE",
    "sg:address":"Garten Str.42",
    "sg:city":"Kerpen",
    "sg:phone":"+49 2273/954350",
    "sg:postcode":"50170",
    "sg:province":"Nordrhein-Westfalen",
    "wof:name":"Rt-online",
    "wof:placetype":"venue"
},
  "geometry": {"coordinates":[6.6804032326,50.9096031189],"type":"Point"}
}