{
  "type": "Feature",
  "properties": {
    "iso:country":"DE",
    "sg:address":"Dorfstr. 39",
    "sg:city":"Uebigau",
    "sg:phone":"+49 3522/51330",
    "sg:postcode":"01561",
    "sg:province":"Sachsen",
    "wof:name":"Elektro-service Kie\u00dfling",
    "wof:placetype":"venue"
},
  "geometry": {"coordinates":[13.5634098053,51.3395233154],"type":"Point"}
}