{
  "type": "Feature",
  "properties": {
    "iso:country":"DE",
    "sg:address":"Im Hegen 4",
    "sg:city":"Oststeinbek",
    "sg:phone":"+49 40/7120064",
    "sg:postcode":"22113",
    "sg:province":"Schleswig-Holstein",
    "wof:name":"Max Engel Ingenieurb\u00fcro",
    "wof:placetype":"venue"
},
  "geometry": {"coordinates":[10.1539211273,53.5492744446],"type":"Point"}
}