{
  "type": "Feature",
  "properties": {
    "iso:country":"DE",
    "sg:address":"Arendseer Str. 11",
    "sg:city":"Seehausen",
    "sg:phone":"+49 39386/52484",
    "sg:postcode":"39615",
    "sg:province":"Sachsen-Anhalt",
    "wof:name":"Ralf Siggel",
    "wof:placetype":"venue"
},
  "geometry": {"coordinates":[11.741484,52.889149],"type":"Point"}
}