{
  "type": "Feature",
  "properties": {
    "iso:country":"DE",
    "sg:address":"Hauptstr. 46",
    "sg:city":"Girod",
    "sg:phone":"+49 6485/8055",
    "sg:postcode":"56412",
    "sg:province":"Rheinland-Pfalz",
    "wof:name":"Pizzeria Belmonte",
    "wof:placetype":"venue"
},
  "geometry": {"coordinates":[7.9110379219,50.4505767822],"type":"Point"}
}