{
  "type": "Feature",
  "properties": {
    "iso:country":"DE",
    "sg:address":"Ripshorster Str. 367a",
    "sg:city":"Essen",
    "sg:phone":"+49 201/605978",
    "sg:postcode":"45357",
    "sg:province":"Nordrhein-Westfalen",
    "wof:name":"Werner Podlewski Und Dirk Freese Gmbh",
    "wof:placetype":"venue"
},
  "geometry": {"coordinates":[6.9098100662,51.4890861511],"type":"Point"}
}