{
  "type": "Feature",
  "properties": {
    "iso:country":"DE",
    "sg:address":"Salzburger Str. 6b",
    "sg:city":"Dresden",
    "sg:postcode":"01279",
    "sg:province":"Sachsen",
    "wof:name":"Eurospar",
    "wof:placetype":"venue"
},
  "geometry": {"coordinates":[13.83223629,51.0277938843],"type":"Point"}
}