{
  "type": "Feature",
  "properties": {
    "iso:country":"DE",
    "sg:address":"Friedenstr. 34 a",
    "sg:city":"M\u00fcnchen",
    "sg:phone":"+49 89/496009",
    "sg:postcode":"81671",
    "sg:province":"Bayern",
    "wof:name":"Otto Herz Steuerberater",
    "wof:placetype":"venue"
},
  "geometry": {"coordinates":[11.6105928421,48.1298065186],"type":"Point"}
}