{
  "type": "Feature",
  "properties": {
    "iso:country":"DE",
    "sg:address":"Am Holzgraben 1",
    "sg:city":"Hannover",
    "sg:phone":"+49 511/31090",
    "sg:postcode":"30161",
    "sg:province":"Niedersachsen",
    "wof:name":"Gundlach Beteiligungs- Gmbh",
    "wof:placetype":"venue"
},
  "geometry": {"coordinates":[9.7531785965,52.3858566284],"type":"Point"}
}