{
  "type": "Feature",
  "properties": {
    "iso:country":"DE",
    "sg:address":"Sandgasse 1",
    "sg:city":"Aschaffenburg",
    "sg:phone":"+49 6021/21505",
    "sg:postcode":"63739",
    "sg:province":"Bayern",
    "wof:name":"Optik Hock Gmbh",
    "wof:placetype":"venue"
},
  "geometry": {"coordinates":[9.1467809677,49.9746131897],"type":"Point"}
}