{
  "type": "Feature",
  "properties": {
    "iso:country":"DE",
    "sg:address":"Berliner Str. 136",
    "sg:city":"M\u00f6nchengladbach",
    "sg:phone":"+49 2166/46138",
    "sg:postcode":"41236",
    "sg:province":"Nordrhein-Westfalen",
    "wof:name":"Zarah",
    "wof:placetype":"venue"
},
  "geometry": {"coordinates":[6.440334,51.158401],"type":"Point"}
}