{
  "type": "Feature",
  "properties": {
    "iso:country":"DE",
    "sg:address":"Kirchhofallee 66",
    "sg:city":"Kiel",
    "sg:phone":"+49 431/519640",
    "sg:postcode":"24114",
    "sg:province":"Schleswig-Holstein",
    "wof:name":"Duag Deutsche Umwelt Ag",
    "wof:placetype":"venue"
},
  "geometry": {"coordinates":[10.119902,54.315979],"type":"Point"}
}