{
  "type": "Feature",
  "properties": {
    "iso:country":"DE",
    "sg:address":"Robert-Bosch-Str. 16",
    "sg:city":"M\u00f6glingen",
    "sg:phone":"+49 7141/481442",
    "sg:postcode":"71696",
    "sg:province":"Baden-W\u00fcrttemberg",
    "wof:name":"G\u00fcnter Bertz",
    "wof:placetype":"venue"
},
  "geometry": {"coordinates":[9.141758,48.887409],"type":"Point"}
}