{
  "type": "Feature",
  "properties": {
    "iso:country":"DE",
    "sg:address":"Sch\u00fcrenkampstr. 62",
    "sg:city":"Gladbeck",
    "sg:phone":"+49 2043/24731",
    "sg:postcode":"45964",
    "sg:province":"Nordrhein-Westfalen",
    "wof:name":"J. Kirstein Gmbh",
    "wof:placetype":"venue"
},
  "geometry": {"coordinates":[7.003827,51.571526],"type":"Point"}
}