{
  "type": "Feature",
  "properties": {
    "iso:country":"DE",
    "sg:address":"Binnerstr. 50",
    "sg:city":"Weiden",
    "sg:phone":"+49 961/45506",
    "sg:postcode":"92637",
    "sg:province":"Bayern",
    "wof:name":"Wild Gmbh",
    "wof:placetype":"venue"
},
  "geometry": {"coordinates":[12.136937,49.635216],"type":"Point"}
}