{
  "type": "Feature",
  "properties": {
    "iso:country":"DE",
    "sg:address":"Obere K\u00f6nigstr. 9",
    "sg:city":"Bamberg",
    "sg:phone":"+49 951/23358",
    "sg:postcode":"96052",
    "sg:province":"Bayern",
    "wof:name":"Marmaris",
    "wof:placetype":"venue"
},
  "geometry": {"coordinates":[10.8922042847,49.8971481323],"type":"Point"}
}