{
  "type": "Feature",
  "properties": {
    "iso:country":"DE",
    "sg:address":"Carlo-Schmid-Str. 2",
    "sg:city":"D\u00fcsseldorf",
    "sg:postcode":"40595",
    "sg:province":"Nordrhein-Westfalen",
    "wof:name":"Aldi Gmbh & Co. Kg",
    "wof:placetype":"venue"
},
  "geometry": {"coordinates":[6.9078960419,51.1318130493],"type":"Point"}
}