{
  "type": "Feature",
  "properties": {
    "iso:country":"DE",
    "sg:address":"Tilsiter Str. 7",
    "sg:city":"Bad Arolsen",
    "sg:phone":"+49 5691/1590",
    "sg:postcode":"34454",
    "sg:province":"Hessen",
    "wof:name":"O. Eyckmans",
    "wof:placetype":"venue"
},
  "geometry": {"coordinates":[9.021608,51.373615],"type":"Point"}
}