{
  "type": "Feature",
  "properties": {
    "iso:country":"DE",
    "sg:address":"Rosenstr. 6",
    "sg:city":"Klein Offenseth-Sparries",
    "sg:phone":"+49 4121/482266",
    "sg:postcode":"25365",
    "sg:province":"Schleswig-Holstein",
    "wof:name":"H.-h. K\u00e4ckenhoff",
    "wof:placetype":"venue"
},
  "geometry": {"coordinates":[9.6856,53.779137],"type":"Point"}
}