{
  "type": "Feature",
  "properties": {
    "iso:country":"DE",
    "sg:address":"Sperberweg 44",
    "sg:city":"Peine",
    "sg:phone":"+49 5171/3848",
    "sg:postcode":"31224",
    "sg:province":"Niedersachsen",
    "wof:name":"K\u00f6hler",
    "wof:placetype":"venue"
},
  "geometry": {"coordinates":[10.253327,52.328953],"type":"Point"}
}