{
  "type": "Feature",
  "properties": {
    "iso:country":"DE",
    "sg:address":"Saarbr\u00fccker Str. 5",
    "sg:city":"Friedrichsthal",
    "sg:phone":"+49 6897/86280",
    "sg:postcode":"66299",
    "sg:province":"Saarland",
    "wof:name":"Guiseppe Paolo Masseur",
    "wof:placetype":"venue"
},
  "geometry": {"coordinates":[7.090691,49.31955],"type":"Point"}
}