{
  "type": "Feature",
  "properties": {
    "iso:country":"DE",
    "sg:address":"Nickelstr. 7",
    "sg:city":"Verl",
    "sg:phone":"+49 5246/92980",
    "sg:postcode":"33415",
    "sg:province":"Nordrhein-Westfalen",
    "wof:name":"Bjm Fensterkomponenten Gmbh",
    "wof:placetype":"venue"
},
  "geometry": {"coordinates":[8.457311,51.875656],"type":"Point"}
}