{
  "type": "Feature",
  "properties": {
    "iso:country":"DE",
    "sg:address":"Elisabethenstr. 10",
    "sg:city":"Frankfurt",
    "sg:phone":"+49 69/6109150",
    "sg:postcode":"60594",
    "sg:province":"Hessen",
    "wof:name":"Hl-markt",
    "wof:placetype":"venue"
},
  "geometry": {"coordinates":[8.6886463165,50.1058883667],"type":"Point"}
}