{
  "type": "Feature",
  "properties": {
    "iso:country":"DE",
    "sg:address":"Schlo\u00dfhofstr. 87 a",
    "sg:city":"Bielefeld",
    "sg:phone":"+49 521/888207",
    "sg:postcode":"33615",
    "sg:province":"Nordrhein-Westfalen",
    "wof:name":"Dorothea Kuhn",
    "wof:placetype":"venue"
},
  "geometry": {"coordinates":[8.5153398514,52.0374565125],"type":"Point"}
}