{
  "type": "Feature",
  "properties": {
    "iso:country":"DE",
    "sg:address":"Bahnhofstr. 13",
    "sg:city":"Oberthal",
    "sg:phone":"+49 6854/8849",
    "sg:postcode":"66649",
    "sg:province":"Saarland",
    "wof:name":"A. Backes",
    "wof:placetype":"venue"
},
  "geometry": {"coordinates":[7.0883178711,49.5119247437],"type":"Point"}
}