{
  "type": "Feature",
  "properties": {
    "iso:country":"DE",
    "sg:address":"Landwehrstr 14",
    "sg:city":"Moers",
    "sg:phone":"+49 2841/27771",
    "sg:postcode":"47441",
    "sg:province":"Nordrhein-Westfalen",
    "wof:name":"Ck Automations- Und Steuerungstechnik Gmbh",
    "wof:placetype":"venue"
},
  "geometry": {"coordinates":[6.633067,51.451828],"type":"Point"}
}