{
  "type": "Feature",
  "properties": {
    "iso:country":"DE",
    "sg:address":"Feldstr. 11a",
    "sg:city":"Winterberg",
    "sg:phone":"+49 2981",
    "sg:postcode":"59955",
    "sg:province":"Nordrhein-Westfalen",
    "wof:name":"Rosenkaimer Gmbh",
    "wof:placetype":"venue"
},
  "geometry": {"coordinates":[8.5268335342,51.1942367554],"type":"Point"}
}