{
  "type": "Feature",
  "properties": {
    "iso:country":"DE",
    "sg:address":"Wanner Str. 99",
    "sg:city":"Recklinghausen",
    "sg:phone":"+49 2361/35501",
    "sg:postcode":"45661",
    "sg:province":"Nordrhein-Westfalen",
    "wof:name":"Egbert Daubitz",
    "wof:placetype":"venue"
},
  "geometry": {"coordinates":[7.182788,51.560471],"type":"Point"}
}