{
  "type": "Feature",
  "properties": {
    "iso:country":"DE",
    "sg:address":"Am Faulbusch 45",
    "sg:city":"Rheda-Wiedenbr\u00fcck",
    "sg:phone":"+49 5242/43045",
    "sg:postcode":"33378",
    "sg:province":"Nordrhein-Westfalen",
    "wof:name":"A. Und W. Liemke",
    "wof:placetype":"venue"
},
  "geometry": {"coordinates":[8.2653579712,51.8642616272],"type":"Point"}
}