{
  "type": "Feature",
  "properties": {
    "iso:country":"DE",
    "sg:address":"Friedrichstr. 22",
    "sg:city":"Rheinfelden",
    "sg:phone":"+49 7623/2320",
    "sg:postcode":"79618",
    "sg:province":"Baden-W\u00fcrttemberg",
    "wof:name":"Klaus M\u00fclhaupt",
    "wof:placetype":"venue"
},
  "geometry": {"coordinates":[7.78994,47.56039],"type":"Point"}
}