{
  "type": "Feature",
  "properties": {
    "iso:country":"DE",
    "sg:address":"Bismarckstr. 161",
    "sg:city":"N\u00fcrnberg",
    "sg:phone":"+49 911/591781",
    "sg:postcode":"90491",
    "sg:province":"Bayern",
    "wof:name":"Friedrich Kaiser Architekt",
    "wof:placetype":"venue"
},
  "geometry": {"coordinates":[11.116473,49.465439],"type":"Point"}
}