{
  "type": "Feature",
  "properties": {
    "iso:country":"DE",
    "sg:address":"Dresdner Str. 95",
    "sg:city":"Weinb\u00f6hla",
    "sg:phone":"+49 35243/32389",
    "sg:postcode":"01689",
    "sg:province":"Sachsen",
    "wof:name":"Heinz-j\u00fcrgen M\u00fcller E. K.",
    "wof:placetype":"venue"
},
  "geometry": {"coordinates":[13.569033,51.148071],"type":"Point"}
}