{
  "type": "Feature",
  "properties": {
    "iso:country":"DE",
    "sg:address":"M\u00fcnzstr. 5",
    "sg:city":"Schwerin",
    "sg:postcode":"19055",
    "sg:province":"Mecklenburg-Vorpommern",
    "wof:name":"Mecklenburger Waagenservice Und Getreidetechnik Gmbh",
    "wof:placetype":"venue"
},
  "geometry": {"coordinates":[11.418873,53.631645],"type":"Point"}
}