{
  "type": "Feature",
  "properties": {
    "iso:country":"DE",
    "sg:address":"Ratsstr. 34",
    "sg:city":"D\u00fcren",
    "sg:phone":"+49 2421/66118",
    "sg:postcode":"52355",
    "sg:province":"Nordrhein-Westfalen",
    "wof:name":"Care Pflegedienst Gmbh",
    "wof:placetype":"venue"
},
  "geometry": {"coordinates":[6.449989,50.793064],"type":"Point"}
}