{
  "type": "Feature",
  "properties": {
    "iso:country":"DE",
    "sg:address":"G\u00f6rlitzer Str. 3",
    "sg:city":"Cottbus",
    "sg:phone":"+49 355/474715",
    "sg:postcode":"03046",
    "sg:province":"Brandenburg",
    "wof:name":"Meiser K\u00fcchenstudio Gmbh",
    "wof:placetype":"venue"
},
  "geometry": {"coordinates":[14.3316507339,51.7495613098],"type":"Point"}
}