{
  "type": "Feature",
  "properties": {
    "iso:country":"DE",
    "sg:address":"Friedensstr. 16",
    "sg:city":"Reichelsheim",
    "sg:phone":"+49 6035/3586",
    "sg:postcode":"61203",
    "sg:province":"Hessen",
    "wof:name":"Birgit Gro\u00df",
    "wof:placetype":"venue"
},
  "geometry": {"coordinates":[8.8687610626,50.3572807312],"type":"Point"}
}