{
  "type": "Feature",
  "properties": {
    "iso:country":"DE",
    "sg:address":"Starenweg 62",
    "sg:city":"Braunschweig",
    "sg:phone":"+49 531/875769",
    "sg:postcode":"38122",
    "sg:province":"Niedersachsen",
    "wof:name":"Hans Schomerus",
    "wof:placetype":"venue"
},
  "geometry": {"coordinates":[10.4780359268,52.2317276001],"type":"Point"}
}