{
  "type": "Feature",
  "properties": {
    "iso:country":"DE",
    "sg:address":"Altfridstr. 2",
    "sg:city":"Bochum",
    "sg:phone":"+49 234/866047",
    "sg:postcode":"44805",
    "sg:province":"Nordrhein-Westfalen",
    "wof:name":"Richter",
    "wof:placetype":"venue"
},
  "geometry": {"coordinates":[7.271999,51.50201],"type":"Point"}
}