{
  "type": "Feature",
  "properties": {
    "iso:country":"DE",
    "sg:address":"Am Wickersberg 24",
    "sg:city":"Saarbr\u00fccken",
    "sg:phone":"+49 6893/3722",
    "sg:postcode":"66131",
    "sg:province":"Saarland",
    "wof:name":"Kinader Und Wack",
    "wof:placetype":"venue"
},
  "geometry": {"coordinates":[7.105149,49.207325],"type":"Point"}
}