{
  "type": "Feature",
  "properties": {
    "iso:country":"DE",
    "sg:address":"Schwimmbadstr.",
    "sg:city":"V\u00f6hrenbach",
    "sg:postcode":"78147",
    "sg:province":"Baden-W\u00fcrttemberg",
    "wof:name":"St\u00e4dtisches Freibad",
    "wof:placetype":"venue"
},
  "geometry": {"coordinates":[8.2998065948,48.0450325012],"type":"Point"}
}