{
  "type": "Feature",
  "properties": {
    "iso:country":"DE",
    "sg:address":"Bergstr. 39",
    "sg:city":"Katlenburg-Lindau",
    "sg:phone":"+49 5552/91147",
    "sg:postcode":"37191",
    "sg:province":"Niedersachsen",
    "wof:name":"Klaus Langethal",
    "wof:placetype":"venue"
},
  "geometry": {"coordinates":[10.062082,51.67173],"type":"Point"}
}