{
  "type": "Feature",
  "properties": {
    "iso:country":"DE",
    "sg:address":"Billsteinstr. 1",
    "sg:city":"Krefeld",
    "sg:phone":"+49 2151/363516",
    "sg:postcode":"47805",
    "sg:province":"Nordrhein-Westfalen",
    "wof:name":"U. Schulzki",
    "wof:placetype":"venue"
},
  "geometry": {"coordinates":[6.572849,51.324265],"type":"Point"}
}