{
  "type": "Feature",
  "properties": {
    "iso:country":"DE",
    "sg:address":"Kleiner Schlo\u00dfpl 11",
    "sg:city":"Stuttgart",
    "sg:phone":"+49 711/2094631",
    "sg:postcode":"70173",
    "sg:province":"Baden-W\u00fcrttemberg",
    "wof:name":"Baden-w\u00fcrttembergische Bank Ag",
    "wof:placetype":"venue"
},
  "geometry": {"coordinates":[9.176094,48.778645],"type":"Point"}
}