{
  "type": "Feature",
  "properties": {
    "iso:country":"DE",
    "sg:address":"Kunreuth",
    "sg:city":"Kunreuth",
    "sg:phone":"+49 9199/337",
    "sg:postcode":"91358",
    "sg:province":"Bayern",
    "wof:name":"Sparkasse Leutenbach",
    "wof:placetype":"venue"
},
  "geometry": {"coordinates":[11.143468,49.682346],"type":"Point"}
}