{
  "type": "Feature",
  "properties": {
    "iso:country":"DE",
    "sg:address":"K\u00f6nigstr. 72",
    "sg:city":"N\u00fcrnberg",
    "sg:phone":"+49 911/203201",
    "sg:postcode":"90402",
    "sg:province":"Bayern",
    "wof:name":"Knauss Und Hille Notare",
    "wof:placetype":"venue"
},
  "geometry": {"coordinates":[11.0805177689,49.4482307434],"type":"Point"}
}