{
  "type": "Feature",
  "properties": {
    "iso:country":"DE",
    "sg:address":"Fabrikstr.",
    "sg:city":"Plauen",
    "sg:phone":"+49 3741/15380",
    "sg:postcode":"08527",
    "sg:province":"Sachsen",
    "wof:name":"Karosserie- Und Lackiererei-service Gmbh",
    "wof:placetype":"venue"
},
  "geometry": {"coordinates":[12.1364049911,50.4887962341],"type":"Point"}
}