{
  "type": "Feature",
  "properties": {
    "iso:country":"DE",
    "sg:address":"Ondrup 38",
    "sg:city":"L\u00fcdinghausen",
    "sg:phone":"+49 2591/8507",
    "sg:postcode":"59348",
    "sg:province":"Nordrhein-Westfalen",
    "wof:name":"Heinrich Uphoff",
    "wof:placetype":"venue"
},
  "geometry": {"coordinates":[7.380203,51.782406],"type":"Point"}
}