{
  "type": "Feature",
  "properties": {
    "iso:country":"DE",
    "sg:address":"Kumeliusstr. 2-4",
    "sg:city":"Oberursel",
    "sg:phone":"+49 6171/63630",
    "sg:postcode":"61440",
    "sg:province":"Hessen",
    "wof:name":"Sporthaus Taunus Inh. Horst Michel E. K.",
    "wof:placetype":"venue"
},
  "geometry": {"coordinates":[8.581201,50.201817],"type":"Point"}
}