{
  "type": "Feature",
  "properties": {
    "iso:country":"DE",
    "sg:address":"Kirchstr. 18",
    "sg:city":"Montabaur",
    "sg:phone":"+49 2602/1540",
    "sg:postcode":"56410",
    "sg:province":"Rheinland-Pfalz",
    "wof:name":"Brasserie Victors",
    "wof:placetype":"venue"
},
  "geometry": {"coordinates":[7.8313832283,50.4357757568],"type":"Point"}
}