{
  "type": "Feature",
  "properties": {
    "iso:country":"DE",
    "sg:address":"Berliner Str. 11",
    "sg:city":"Regensburg",
    "sg:phone":"+49 941/61335",
    "sg:postcode":"93057",
    "sg:province":"Bayern",
    "wof:name":"Josef Schreiner Dipl.-ingenieur",
    "wof:placetype":"venue"
},
  "geometry": {"coordinates":[12.1175279617,49.0454597473],"type":"Point"}
}