{
  "type": "Feature",
  "properties": {
    "iso:country":"DE",
    "sg:address":"Sophienstr. 15",
    "sg:city":"Reinbek",
    "sg:phone":"+49 40/7221368",
    "sg:postcode":"21465",
    "sg:province":"Schleswig-Holstein",
    "wof:name":"Fritz K\u00f6rber Architekt",
    "wof:placetype":"venue"
},
  "geometry": {"coordinates":[10.256105,53.509407],"type":"Point"}
}