{
  "type": "Feature",
  "properties": {
    "iso:country":"DE",
    "sg:address":"Von-H\u00fcnefeld-Str 81",
    "sg:city":"K\u00f6ln",
    "sg:phone":"+49 221/956810",
    "sg:postcode":"50829",
    "sg:province":"Nordrhein-Westfalen",
    "wof:name":"Wiba Theater & Studio-equipment Gmbh",
    "wof:placetype":"venue"
},
  "geometry": {"coordinates":[6.888899,50.986752],"type":"Point"}
}