{
  "type": "Feature",
  "properties": {
    "iso:country":"DE",
    "sg:address":"Kirchstr. 13",
    "sg:city":"Selters",
    "sg:phone":"+49 700 7325 4633",
    "sg:postcode":"56242",
    "sg:province":"Rheinland-Pfalz",
    "wof:name":"Seminar Ladungssicherung Auf Stra\u00dfenfahrzeugen",
    "wof:placetype":"venue"
},
  "geometry": {"coordinates":[7.713651,50.55127],"type":"Point"}
}