{
  "type": "Feature",
  "properties": {
    "iso:country":"DE",
    "sg:address":"Hagenhausen",
    "sg:city":"Altdorf",
    "sg:phone":"+49 9187/3952",
    "sg:postcode":"90518",
    "sg:province":"Bayern",
    "wof:name":"Kalbus",
    "wof:placetype":"venue"
},
  "geometry": {"coordinates":[11.40013,49.381828],"type":"Point"}
}