{
  "type": "Feature",
  "properties": {
    "iso:country":"DE",
    "sg:address":"Tonndorfer Hauptstr. 174",
    "sg:city":"Hamburg",
    "sg:phone":"+49 40/664969",
    "sg:postcode":"22045",
    "sg:province":"Hamburg",
    "wof:name":"Michael Carstens E. K.",
    "wof:placetype":"venue"
},
  "geometry": {"coordinates":[10.13697,53.592339],"type":"Point"}
}