{
  "type": "Feature",
  "properties": {
    "iso:country":"DE",
    "sg:address":"Kleiner Eiderkamp 4",
    "sg:city":"Molfsee",
    "sg:phone":"+49 431/651489",
    "sg:postcode":"24113",
    "sg:province":"Schleswig-Holstein",
    "wof:name":"Imex Textilgro\u00dfhandel Gmbh",
    "wof:placetype":"venue"
},
  "geometry": {"coordinates":[10.0886249542,54.2886543274],"type":"Point"}
}