{
  "type": "Feature",
  "properties": {
    "iso:country":"DE",
    "sg:address":"Inselstr. 9",
    "sg:city":"Mainz",
    "sg:phone":"+49 6131/287990",
    "sg:postcode":"55116",
    "sg:province":"Rheinland-Pfalz",
    "wof:name":"Vhv Vereinigte Haftpflicht - Versicherung",
    "wof:placetype":"venue"
},
  "geometry": {"coordinates":[8.2687635422,49.9986839294],"type":"Point"}
}