{
  "type": "Feature",
  "properties": {
    "iso:country":"DE",
    "sg:address":"Kampstr. 16",
    "sg:city":"Trassenheide",
    "sg:phone":"+49 38371/28100",
    "sg:postcode":"17449",
    "sg:province":"Mecklenburg-Vorpommern",
    "wof:name":"Upeg-usedom Bautr\u00e4ger- Gesellschaft Mbh",
    "wof:placetype":"venue"
},
  "geometry": {"coordinates":[13.8643722534,54.0875434875],"type":"Point"}
}