{
  "type": "Feature",
  "properties": {
    "iso:country":"DE",
    "sg:address":"Dorfaue 12",
    "sg:city":"Zeesen",
    "sg:phone":"+49 3375/900041",
    "sg:postcode":"15711",
    "sg:province":"Brandenburg",
    "wof:name":"Waidmannsruh",
    "wof:placetype":"venue"
},
  "geometry": {"coordinates":[13.6416406631,52.2737503052],"type":"Point"}
}