{
  "type": "Feature",
  "properties": {
    "iso:country":"DE",
    "sg:address":"Dorstener Str. 301",
    "sg:city":"Oberhausen",
    "sg:phone":"+49 208/602243",
    "sg:postcode":"46145",
    "sg:province":"Nordrhein-Westfalen",
    "wof:name":"Ralf Piechel Finanzberater",
    "wof:placetype":"venue"
},
  "geometry": {"coordinates":[6.8642020226,51.5237884521],"type":"Point"}
}