{
  "type": "Feature",
  "properties": {
    "iso:country":"DE",
    "sg:address":"Josef-Schregel-Str. 40",
    "sg:city":"D\u00fcren",
    "sg:phone":"+49 2421/17569",
    "sg:postcode":"52349",
    "sg:province":"Nordrhein-Westfalen",
    "wof:name":"Ruschmeyer",
    "wof:placetype":"venue"
},
  "geometry": {"coordinates":[6.481391,50.807129],"type":"Point"}
}