{
  "type": "Feature",
  "properties": {
    "iso:country":"DE",
    "sg:address":"H\u00fcgelstr. 19",
    "sg:city":"Ober-Ramstadt",
    "sg:phone":"+49 6154/2252",
    "sg:postcode":"64372",
    "sg:province":"Hessen",
    "wof:name":"Karl Nieder Architekt",
    "wof:placetype":"venue"
},
  "geometry": {"coordinates":[8.745829,49.831223],"type":"Point"}
}