{
  "type": "Feature",
  "properties": {
    "iso:country":"DE",
    "sg:address":"Kirchstr. 11",
    "sg:city":"Oberrieden",
    "sg:phone":"+49 8265/321",
    "sg:postcode":"87769",
    "sg:province":"Bayern",
    "wof:name":"Erhard Klement Elektro",
    "wof:placetype":"venue"
},
  "geometry": {"coordinates":[10.426159,48.090298],"type":"Point"}
}