{
  "type": "Feature",
  "properties": {
    "iso:country":"DE",
    "sg:address":"Weidenbaumsweg 54",
    "sg:city":"Hamburg",
    "sg:phone":"+49 40/7248788",
    "sg:postcode":"21035",
    "sg:province":"Hamburg",
    "wof:name":"Appel Und Wagner",
    "wof:placetype":"venue"
},
  "geometry": {"coordinates":[10.2021026611,53.4859733582],"type":"Point"}
}