{
  "type": "Feature",
  "properties": {
    "iso:country":"DE",
    "sg:address":"Oststr. 3",
    "sg:city":"Kurort Oberwiesenthal",
    "sg:phone":"+49 37348/7793",
    "sg:postcode":"09484",
    "sg:province":"Sachsen",
    "wof:name":"K. Ullmann",
    "wof:placetype":"venue"
},
  "geometry": {"coordinates":[12.9796247482,50.4209213257],"type":"Point"}
}