{
  "type": "Feature",
  "properties": {
    "iso:country":"DE",
    "sg:address":"Bernkasteler Str. 49",
    "sg:city":"Longkamp",
    "sg:phone":"+49 6531/6366",
    "sg:postcode":"54472",
    "sg:province":"Rheinland-Pfalz",
    "wof:name":"Otto Weber",
    "wof:placetype":"venue"
},
  "geometry": {"coordinates":[7.113475,49.891182],"type":"Point"}
}