{
  "type": "Feature",
  "properties": {
    "iso:country":"DE",
    "sg:address":"N\u00fcrnberger Str. 10",
    "sg:city":"Donauw\u00f6rth",
    "sg:phone":"+49 906/706680",
    "sg:postcode":"86609",
    "sg:province":"Bayern",
    "wof:name":"Jotha Fahrzeugbau Ag",
    "wof:placetype":"venue"
},
  "geometry": {"coordinates":[10.7783498764,48.7301673889],"type":"Point"}
}