{
  "type": "Feature",
  "properties": {
    "iso:country":"DE",
    "sg:address":"Kurpromenade 36",
    "sg:city":"Helgoland",
    "sg:postcode":"27498",
    "sg:province":"Schleswig-Holstein",
    "wof:name":"Hochsee Yachtschule Helgoland Kg",
    "wof:placetype":"venue"
},
  "geometry": {"coordinates":[7.889947,54.182278],"type":"Point"}
}