{
  "type": "Feature",
  "properties": {
    "iso:country":"DE",
    "sg:address":"Im Brauke 8a",
    "sg:city":"Schmallenberg",
    "sg:phone":"+49 2972/2304",
    "sg:postcode":"57392",
    "sg:province":"Nordrhein-Westfalen",
    "wof:name":"Stelzer Fliesen Und Kachelofenbau Gmbh",
    "wof:placetype":"venue"
},
  "geometry": {"coordinates":[8.2992839813,51.1581840515],"type":"Point"}
}