{
  "type": "Feature",
  "properties": {
    "iso:country":"DE",
    "sg:address":"Wittenmoor 47",
    "sg:city":"Hamburg",
    "sg:postcode":"22525",
    "sg:province":"Hamburg",
    "wof:name":"B. J. N. Warenhandels Ohg",
    "wof:placetype":"venue"
},
  "geometry": {"coordinates":[9.9147443771,53.5933074951],"type":"Point"}
}