{
  "type": "Feature",
  "properties": {
    "iso:country":"DE",
    "sg:address":"Ellernstra\u00dfe 22",
    "sg:city":"Garbsen",
    "sg:phone":"+49 5131/447388",
    "sg:postcode":"30826",
    "sg:province":"Niedersachsen",
    "wof:name":"Erotik-welt - Erotisches F\u00fcr Sie Und Ihn",
    "wof:placetype":"venue"
},
  "geometry": {"coordinates":[9.5444107056,52.4389266968],"type":"Point"}
}