{
  "type": "Feature",
  "properties": {
    "iso:country":"DE",
    "sg:address":"Lange Str. 63",
    "sg:city":"Walsrode",
    "sg:phone":"+49 5161/3680",
    "sg:postcode":"29664",
    "sg:province":"Niedersachsen",
    "wof:name":"Friedrich Hoffmeyer",
    "wof:placetype":"venue"
},
  "geometry": {"coordinates":[9.588295,52.860954],"type":"Point"}
}