{
  "type": "Feature",
  "properties": {
    "iso:country":"DE",
    "sg:address":"Gerlestr. 7",
    "sg:city":"N\u00fcrnberg",
    "sg:phone":"+49 911/458335",
    "sg:postcode":"90459",
    "sg:province":"Bayern",
    "wof:name":"G\u00fcnter Schuh",
    "wof:placetype":"venue"
},
  "geometry": {"coordinates":[11.0858163834,49.4424362183],"type":"Point"}
}