{
  "type": "Feature",
  "properties": {
    "iso:country":"DE",
    "sg:address":"Vorwerker Str. 63",
    "sg:city":"L\u00fcbeck",
    "sg:phone":"+49 451/405485",
    "sg:postcode":"23554",
    "sg:province":"Schleswig-Holstein",
    "wof:name":"K.-g. Friedrichs",
    "wof:placetype":"venue"
},
  "geometry": {"coordinates":[10.6843318939,53.8963279724],"type":"Point"}
}