{
  "type": "Feature",
  "properties": {
    "iso:country":"DE",
    "sg:address":"Mittelstr. 51",
    "sg:city":"Elchesheim-Illingen",
    "sg:phone":"+49 7245/83977",
    "sg:postcode":"76477",
    "sg:province":"Baden-W\u00fcrttemberg",
    "wof:name":"K. Leptig Werkzeuge",
    "wof:placetype":"venue"
},
  "geometry": {"coordinates":[8.207741,48.936485],"type":"Point"}
}