{
  "type": "Feature",
  "properties": {
    "iso:country":"DE",
    "sg:address":"Theodor-Meissner-Str 4",
    "sg:city":"Biedenkopf",
    "sg:phone":"+49 6461/8020",
    "sg:postcode":"35216",
    "sg:province":"Hessen",
    "wof:name":"Meissner Ag",
    "wof:placetype":"venue"
},
  "geometry": {"coordinates":[8.466791153,50.9226531982],"type":"Point"}
}