{
  "type": "Feature",
  "properties": {
    "iso:country":"DE",
    "sg:address":"Br\u00fchlstr. 7",
    "sg:city":"Bruchsal",
    "sg:phone":"+49 7257/1574",
    "sg:postcode":"76646",
    "sg:province":"Baden-W\u00fcrttemberg",
    "wof:name":"Walter Pflaum Rechtsanwalt",
    "wof:placetype":"venue"
},
  "geometry": {"coordinates":[8.5500230789,49.0829734802],"type":"Point"}
}