{
  "type": "Feature",
  "properties": {
    "iso:country":"DE",
    "sg:address":"Poststr. 10",
    "sg:city":"Buchholz",
    "sg:postcode":"21244",
    "sg:province":"Niedersachsen",
    "wof:name":"Heide Optik Ohg",
    "wof:placetype":"venue"
},
  "geometry": {"coordinates":[9.8791446686,53.3267784119],"type":"Point"}
}