{
  "type": "Feature",
  "properties": {
    "iso:country":"DE",
    "sg:address":"Oberf\u00f6rster-Ganter-Str. 3",
    "sg:city":"Villingen-Schwenningen",
    "sg:postcode":"78048",
    "sg:province":"Baden-W\u00fcrttemberg",
    "wof:name":"Mil-holding Gmbh",
    "wof:placetype":"venue"
},
  "geometry": {"coordinates":[8.434326,48.070824],"type":"Point"}
}