{
  "type": "Feature",
  "properties": {
    "iso:country":"DE",
    "sg:address":"Steglitzer Str. 24",
    "sg:city":"Rendsburg",
    "sg:postcode":"24768",
    "sg:province":"Schleswig-Holstein",
    "wof:name":"Jugendaufbauwerk Schlesw.-holstein",
    "wof:placetype":"venue"
},
  "geometry": {"coordinates":[9.7005395889,54.3049087524],"type":"Point"}
}