{
  "type": "Feature",
  "properties": {
    "iso:country":"DE",
    "sg:address":"Deichstr. 10",
    "sg:city":"Derben",
    "sg:phone":"+49 39349/90090",
    "sg:postcode":"39317",
    "sg:province":"Sachsen-Anhalt",
    "wof:name":"Baustoff Netzband Gmbh",
    "wof:placetype":"venue"
},
  "geometry": {"coordinates":[11.9904003143,52.4153709412],"type":"Point"}
}