{
  "type": "Feature",
  "properties": {
    "iso:country":"DE",
    "sg:address":"Wiesenstr. 6",
    "sg:city":"Schopp",
    "sg:phone":"+49 6307/92120",
    "sg:postcode":"67707",
    "sg:province":"Rheinland-Pfalz",
    "wof:name":"Gross Funk Gmbh",
    "wof:placetype":"venue"
},
  "geometry": {"coordinates":[7.6902871132,49.3569259644],"type":"Point"}
}