{
  "type": "Feature",
  "properties": {
    "iso:country":"DE",
    "sg:address":"Silcherstr. 5",
    "sg:city":"T\u00fcbingen",
    "sg:phone":"+49 7071/294820",
    "sg:postcode":"72076",
    "sg:province":"Baden-W\u00fcrttemberg",
    "wof:name":"Universit\u00e4t T\u00fcbingen Universit\u00e4ts-hals-nasen-",
    "wof:placetype":"venue"
},
  "geometry": {"coordinates":[9.057517,48.524715],"type":"Point"}
}