{
  "type": "Feature",
  "properties": {
    "iso:country":"DE",
    "sg:address":"Greifswalder Str. 87",
    "sg:city":"Berlin",
    "sg:phone":"+49 30/42161051",
    "sg:postcode":"10409",
    "sg:province":"Berlin",
    "wof:name":"Astoria-reisen",
    "wof:placetype":"venue"
},
  "geometry": {"coordinates":[13.4405946732,52.5422515869],"type":"Point"}
}