{
  "type": "Feature",
  "properties": {
    "iso:country":"DE",
    "sg:address":"Marktplatz 9",
    "sg:city":"Calw",
    "sg:phone":"+49 7051/1951",
    "sg:postcode":"75365",
    "sg:province":"Baden-W\u00fcrttemberg",
    "wof:name":"Gro\u00dfe Kreisstadt Calw",
    "wof:placetype":"venue"
},
  "geometry": {"coordinates":[8.7389116287,48.7141189575],"type":"Point"}
}