{
  "type": "Feature",
  "properties": {
    "iso:country":"DE",
    "sg:address":"Randstr. 8",
    "sg:city":"Burgwald",
    "sg:phone":"+49 6451/8958",
    "sg:postcode":"35099",
    "sg:province":"Hessen",
    "wof:name":"Rhein-ruhr Maschinenb. Gmbh Dura Sandstrahltechnik",
    "wof:placetype":"venue"
},
  "geometry": {"coordinates":[8.7537174225,51.02186203],"type":"Point"}
}