{
  "type": "Feature",
  "properties": {
    "iso:country":"DE",
    "sg:address":"Dachauer Str. 265",
    "sg:city":"M\u00fcnchen",
    "sg:phone":"+49 89/15982271",
    "sg:postcode":"80637",
    "sg:province":"Bayern",
    "wof:name":"Medea Sys Gmbh",
    "wof:placetype":"venue"
},
  "geometry": {"coordinates":[11.5366697311,48.1666679382],"type":"Point"}
}