{
  "type": "Feature",
  "properties": {
    "iso:country":"DE",
    "sg:address":"M\u00fchlenstr. 2",
    "sg:city":"Oberstaufen",
    "sg:phone":"+49 8386/1214",
    "sg:postcode":"87534",
    "sg:province":"Bayern",
    "wof:name":"Herbert H\u00e4u\u00dfler",
    "wof:placetype":"venue"
},
  "geometry": {"coordinates":[10.0215511322,47.5484313965],"type":"Point"}
}