{
  "type": "Feature",
  "properties": {
    "iso:country":"DE",
    "sg:address":"Rosenstr. 19",
    "sg:city":"Haiterbach",
    "sg:phone":"+49 7456/263",
    "sg:postcode":"72221",
    "sg:province":"Baden-W\u00fcrttemberg",
    "wof:name":"Ernst Kaupp Ohg",
    "wof:placetype":"venue"
},
  "geometry": {"coordinates":[8.65295,48.526218],"type":"Point"}
}