{
  "type": "Feature",
  "properties": {
    "iso:country":"DE",
    "sg:address":"W\u00fcrzburger Str. 22",
    "sg:city":"N\u00f6rdlingen",
    "sg:phone":"+49 9081/4357",
    "sg:postcode":"86720",
    "sg:province":"Bayern",
    "wof:name":"Hans Thum Inh. G\u00fcnter Thum",
    "wof:placetype":"venue"
},
  "geometry": {"coordinates":[10.480791,48.855782],"type":"Point"}
}