{
  "type": "Feature",
  "properties": {
    "iso:country":"DE",
    "sg:address":"Stettiner Str. 16",
    "sg:city":"Schifferstadt",
    "sg:phone":"+49 6235/7321",
    "sg:postcode":"67105",
    "sg:province":"Rheinland-Pfalz",
    "wof:name":"Ralf Reinert",
    "wof:placetype":"venue"
},
  "geometry": {"coordinates":[8.3818693161,49.3915596008],"type":"Point"}
}