{
  "type": "Feature",
  "properties": {
    "iso:country":"DE",
    "sg:address":"Priesterweg 6",
    "sg:city":"Berlin",
    "sg:phone":"+49 30",
    "sg:postcode":"10829",
    "sg:province":"Berlin",
    "wof:name":"F\u00fchrungs-akademie Berlin Des Deutschen Sportbundes E.v.",
    "wof:placetype":"venue"
},
  "geometry": {"coordinates":[13.355896,52.475002],"type":"Point"}
}