{
  "type": "Feature",
  "properties": {
    "iso:country":"DE",
    "sg:address":"Borgfeldtstr. 11",
    "sg:city":"Eisenberg",
    "sg:phone":"+49 4936/6915640",
    "sg:postcode":"07607",
    "sg:province":"Th\u00fcringen",
    "wof:name":"Spautz Holzhandel Innenausbau Gmbh",
    "wof:placetype":"venue"
},
  "geometry": {"coordinates":[11.8953332901,50.9808692932],"type":"Point"}
}