{
  "type": "Feature",
  "properties": {
    "iso:country":"DE",
    "sg:address":"Wittekindstr. 15",
    "sg:city":"L\u00fcnen",
    "sg:phone":"+49 231/871304",
    "sg:postcode":"44536",
    "sg:province":"Nordrhein-Westfalen",
    "wof:name":"G\u00fcnter Leimann Werbegeschenke",
    "wof:placetype":"venue"
},
  "geometry": {"coordinates":[7.4403271675,51.5980682373],"type":"Point"}
}