{
  "type": "Feature",
  "properties": {
    "iso:country":"DE",
    "sg:address":"Teutstr. 127",
    "sg:city":"Oberhausen",
    "sg:phone":"+49 208/893110",
    "sg:postcode":"46117",
    "sg:province":"Nordrhein-Westfalen",
    "wof:name":"Theo Marre Architekt",
    "wof:placetype":"venue"
},
  "geometry": {"coordinates":[6.881462,51.497414],"type":"Point"}
}