{
  "type": "Feature",
  "properties": {
    "iso:country":"DE",
    "sg:address":"Kolpingstr. 4",
    "sg:city":"Viechtach",
    "sg:phone":"+49 9942/5322",
    "sg:postcode":"94234",
    "sg:province":"Bayern",
    "wof:name":"Gerhard Lackerbeck",
    "wof:placetype":"venue"
},
  "geometry": {"coordinates":[12.887597084,49.0786132812],"type":"Point"}
}