{
  "type": "Feature",
  "properties": {
    "iso:country":"DE",
    "sg:address":"Herzog-Wilhelm-Str. 22",
    "sg:city":"M\u00fcnchen",
    "sg:phone":"+49 89/592355",
    "sg:postcode":"80331",
    "sg:province":"Bayern",
    "wof:name":"Konrad Grasser Rechtsanwalt",
    "wof:placetype":"venue"
},
  "geometry": {"coordinates":[11.5665197372,48.1352958679],"type":"Point"}
}