{
  "type": "Feature",
  "properties": {
    "iso:country":"DE",
    "sg:address":"J\u00fclicher Str. 11",
    "sg:city":"K\u00f6ln",
    "sg:phone":"+49 221/2404367",
    "sg:postcode":"50674",
    "sg:province":"Nordrhein-Westfalen",
    "wof:name":"Pizzeria Pizza Pazza",
    "wof:placetype":"venue"
},
  "geometry": {"coordinates":[6.9341831207,50.9339141846],"type":"Point"}
}