{
  "type": "Feature",
  "properties": {
    "iso:country":"DE",
    "sg:address":"Bahnhofstr. 9",
    "sg:city":"Delligsen",
    "sg:phone":"+49 5187/1860",
    "sg:postcode":"31073",
    "sg:province":"Niedersachsen",
    "wof:name":"R. Heise",
    "wof:placetype":"venue"
},
  "geometry": {"coordinates":[9.804356,51.94278],"type":"Point"}
}