{
  "type": "Feature",
  "properties": {
    "iso:country":"DE",
    "sg:address":"Bismarckstr. 181",
    "sg:city":"Gelsenkirchen",
    "sg:phone":"+49 209/85683",
    "sg:postcode":"45889",
    "sg:province":"Nordrhein-Westfalen",
    "wof:name":"Glocken Apotheke Inh. Ulrich Br\u00fcggemann",
    "wof:placetype":"venue"
},
  "geometry": {"coordinates":[7.105852,51.526356],"type":"Point"}
}