{
  "type": "Feature",
  "properties": {
    "iso:country":"DE",
    "sg:address":"Sudetenstr. 3",
    "sg:city":"Ehringshausen",
    "sg:phone":"+49 6443/9675",
    "sg:postcode":"35630",
    "sg:province":"Hessen",
    "wof:name":"A. Lehmann Heissmangel",
    "wof:placetype":"venue"
},
  "geometry": {"coordinates":[8.3658618927,50.5931053162],"type":"Point"}
}