{
  "type": "Feature",
  "properties": {
    "iso:country":"DE",
    "sg:address":"Steinheider Str. 7",
    "sg:city":"Mengersgereuth-H\u00e4mmern",
    "sg:phone":"+49 3675/805650",
    "sg:postcode":"96529",
    "sg:province":"Th\u00fcringen",
    "wof:name":"Gastst\u00e4tte B\u00fcchner",
    "wof:placetype":"venue"
},
  "geometry": {"coordinates":[11.1171655655,50.4079399109],"type":"Point"}
}