{
  "type": "Feature",
  "properties": {
    "iso:country":"DE",
    "sg:address":"Bahnhofstr. 12",
    "sg:city":"Taucha",
    "sg:postcode":"06679",
    "sg:province":"Sachsen-Anhalt",
    "wof:name":"Dendatec Gesellschaft F\u00fcr Dental- Und Datentechnik Mbh",
    "wof:placetype":"venue"
},
  "geometry": {"coordinates":[12.076127,51.191532],"type":"Point"}
}