{
  "type": "Feature",
  "properties": {
    "iso:country":"DE",
    "sg:address":"Alt Erlenbach 65",
    "sg:city":"Frankfurt",
    "sg:phone":"+49 6101/41003",
    "sg:postcode":"60437",
    "sg:province":"Hessen",
    "wof:name":"Marie Wuschanski Bekleidung Und Ausstattung",
    "wof:placetype":"venue"
},
  "geometry": {"coordinates":[8.7077770233,50.20470047],"type":"Point"}
}