{
  "type": "Feature",
  "properties": {
    "iso:country":"DE",
    "sg:address":"Louisenstr. 60",
    "sg:city":"Bad Homburg",
    "sg:phone":"+49 6172/29617",
    "sg:postcode":"61348",
    "sg:province":"Hessen",
    "wof:name":"Bertram Von Aufschnaiter",
    "wof:placetype":"venue"
},
  "geometry": {"coordinates":[8.6155557632,50.227432251],"type":"Point"}
}