{
  "type": "Feature",
  "properties": {
    "iso:country":"DE",
    "sg:address":"Espenstr. 3",
    "sg:city":"Mammendorf",
    "sg:postcode":"82291",
    "sg:province":"Bayern",
    "wof:name":"Rega Hydraulik Und Metallbau Gmbh",
    "wof:placetype":"venue"
},
  "geometry": {"coordinates":[11.1564531326,48.2062988281],"type":"Point"}
}