{
  "type": "Feature",
  "properties": {
    "iso:country":"DE",
    "sg:address":"K\u00f6nigsberger Str. 41",
    "sg:city":"Sulzbach",
    "sg:phone":"+49 6028/996683",
    "sg:postcode":"63834",
    "sg:province":"Bayern",
    "wof:name":"Fath",
    "wof:placetype":"venue"
},
  "geometry": {"coordinates":[9.167509079,49.9154205322],"type":"Point"}
}