{
  "type": "Feature",
  "properties": {
    "iso:country":"DE",
    "sg:address":"F\u00f6hrenweg 1",
    "sg:city":"G\u00f6ttingen",
    "sg:postcode":"37077",
    "sg:province":"Niedersachsen",
    "wof:name":"Scilands Gmbh",
    "wof:placetype":"venue"
},
  "geometry": {"coordinates":[9.9418001175,51.5590896606],"type":"Point"}
}