{
  "type": "Feature",
  "properties": {
    "iso:country":"DE",
    "sg:address":"30982",
    "sg:city":"Pattensen",
    "sg:phone":"+49 5101/10060",
    "sg:postcode":"30982",
    "sg:province":"Niedersachsen",
    "wof:name":"Volksbank Eg Pattensen B Hannover",
    "wof:placetype":"venue"
},
  "geometry": {"coordinates":[9.75859,52.234051],"type":"Point"}
}