{
  "type": "Feature",
  "properties": {
    "iso:country":"DE",
    "sg:address":"Am Hachelturm 44",
    "sg:city":"Pforzheim",
    "sg:phone":"+49 7231/102163",
    "sg:postcode":"75177",
    "sg:province":"Baden-W\u00fcrttemberg",
    "wof:name":"H. Frey Ingenieur",
    "wof:placetype":"venue"
},
  "geometry": {"coordinates":[8.6831035614,48.9019203186],"type":"Point"}
}