{
  "type": "Feature",
  "properties": {
    "iso:country":"DE",
    "sg:address":"Lipper Hellweg 153",
    "sg:city":"Bielefeld",
    "sg:phone":"+49 521/25212",
    "sg:postcode":"33605",
    "sg:province":"Nordrhein-Westfalen",
    "wof:name":"H. W. G\u00fcse",
    "wof:placetype":"venue"
},
  "geometry": {"coordinates":[8.5720481873,51.996723175],"type":"Point"}
}