{
  "type": "Feature",
  "properties": {
    "iso:country":"DE",
    "sg:address":"Bornheimer Str. 24",
    "sg:city":"Bonn",
    "sg:phone":"+49 228/725470",
    "sg:postcode":"53111",
    "sg:province":"Nordrhein-Westfalen",
    "wof:name":"Stahl Lippok Und Hovemeyer Rechtsanw\u00e4lte",
    "wof:placetype":"venue"
},
  "geometry": {"coordinates":[7.092982769,50.7362937927],"type":"Point"}
}