{
  "type": "Feature",
  "properties": {
    "iso:country":"DE",
    "sg:address":"Birkenweg 2",
    "sg:city":"Wiesentheid",
    "sg:phone":"+49 9383/2255",
    "sg:postcode":"97353",
    "sg:province":"Bayern",
    "wof:name":"Udo Ziegler",
    "wof:placetype":"venue"
},
  "geometry": {"coordinates":[10.3494911194,49.7913742065],"type":"Point"}
}