{
  "type": "Feature",
  "properties": {
    "iso:country":"DE",
    "sg:address":"Friederikenstr 12",
    "sg:city":"Harzgerode",
    "sg:phone":"+49 39484/960",
    "sg:postcode":"06493",
    "sg:province":"Sachsen-Anhalt",
    "wof:name":"Mofo Modell- Und Formenbau Gmbh",
    "wof:placetype":"venue"
},
  "geometry": {"coordinates":[11.1481304169,51.6419029236],"type":"Point"}
}