{
  "type": "Feature",
  "properties": {
    "iso:country":"DE",
    "sg:address":"Spitztannenweg 19",
    "sg:city":"W\u00fcrzburg",
    "sg:phone":"+49 931/60320",
    "sg:postcode":"97084",
    "sg:province":"Bayern",
    "wof:name":"Heinrich B\u00f6ll E. Kfm.",
    "wof:placetype":"venue"
},
  "geometry": {"coordinates":[9.9346408844,49.7448616028],"type":"Point"}
}