{
  "type": "Feature",
  "properties": {
    "iso:country":"DE",
    "sg:address":"Frankfurter Str. 82",
    "sg:city":"Gie\u00dfen",
    "sg:postcode":"35392",
    "sg:province":"Hessen",
    "wof:name":"Kev K\u00fcchen- Und Elektro- Vertriebsges. In Gie\u00dfen Mbh",
    "wof:placetype":"venue"
},
  "geometry": {"coordinates":[8.6613492966,50.5750617981],"type":"Point"}
}