{
  "type": "Feature",
  "properties": {
    "iso:country":"DE",
    "sg:address":"Christenfeld 10",
    "sg:city":"Br\u00fcggen",
    "sg:phone":"+49 2157/871977",
    "sg:postcode":"41379",
    "sg:province":"Nordrhein-Westfalen",
    "wof:name":"Wfk - Testgewebe Gmbh",
    "wof:placetype":"venue"
},
  "geometry": {"coordinates":[6.1783070564,51.2822570801],"type":"Point"}
}