{
  "type": "Feature",
  "properties": {
    "iso:country":"DE",
    "sg:address":"Wilhelmstr. 52",
    "sg:city":"Tuttlingen",
    "sg:phone":"+49 7461/3569",
    "sg:postcode":"78532",
    "sg:province":"Baden-W\u00fcrttemberg",
    "wof:name":"Willi Rothenburger",
    "wof:placetype":"venue"
},
  "geometry": {"coordinates":[8.816434,47.980885],"type":"Point"}
}