{
  "type": "Feature",
  "properties": {
    "iso:country":"DE",
    "sg:address":"Georg-Herwegh-Str. 9",
    "sg:city":"Eberswalde",
    "sg:phone":"+49 3334/235830",
    "sg:postcode":"16225",
    "sg:province":"Brandenburg",
    "wof:name":"Katharina Storch",
    "wof:placetype":"venue"
},
  "geometry": {"coordinates":[13.822837,52.828167],"type":"Point"}
}