{
  "type": "Feature",
  "properties": {
    "iso:country":"DE",
    "sg:address":"Schloitweg 17",
    "sg:city":"Soest",
    "sg:phone":"+49 2921/96040",
    "sg:postcode":"59494",
    "sg:province":"Nordrhein-Westfalen",
    "wof:name":"Volkmann Gmbh",
    "wof:placetype":"venue"
},
  "geometry": {"coordinates":[8.0813493729,51.5581893921],"type":"Point"}
}