{
  "type": "Feature",
  "properties": {
    "iso:country":"DE",
    "sg:address":"Untere Bockenheimer Str. 21",
    "sg:city":"Hohen-S\u00fclzen",
    "sg:phone":"+49 6243/908363",
    "sg:postcode":"67591",
    "sg:province":"Rheinland-Pfalz",
    "wof:name":"Gabriele Parow-bode Heilpraktikerin",
    "wof:placetype":"venue"
},
  "geometry": {"coordinates":[8.2219543457,49.6166610718],"type":"Point"}
}