{
  "type": "Feature",
  "properties": {
    "iso:country":"DE",
    "sg:address":"Marienfelder Allee 41",
    "sg:city":"Berlin",
    "sg:phone":"+49 30/7213941",
    "sg:postcode":"12277",
    "sg:province":"Berlin",
    "wof:name":"K. Vogelmann",
    "wof:placetype":"venue"
},
  "geometry": {"coordinates":[13.370375,52.421764],"type":"Point"}
}