{
  "type": "Feature",
  "properties": {
    "iso:country":"DE",
    "sg:address":"Liebigstr. 3",
    "sg:city":"Freiburg",
    "sg:phone":"+49 761/500873",
    "sg:postcode":"79108",
    "sg:province":"Baden-W\u00fcrttemberg",
    "wof:name":"Heinz Preu\u00df Gmbh",
    "wof:placetype":"venue"
},
  "geometry": {"coordinates":[7.8492307663,48.0198860168],"type":"Point"}
}