{
  "type": "Feature",
  "properties": {
    "iso:country":"DE",
    "sg:address":"Magdeburger Str. 13",
    "sg:city":"Haldensleben",
    "sg:phone":"+49 3904/462950",
    "sg:postcode":"39340",
    "sg:province":"Sachsen-Anhalt",
    "wof:name":"Bhw Bausparkasse Ag",
    "wof:placetype":"venue"
},
  "geometry": {"coordinates":[11.411745,52.291534],"type":"Point"}
}