{
  "type": "Feature",
  "properties": {
    "iso:country":"DE",
    "sg:address":"Lattenkamp 4",
    "sg:city":"Hamburg",
    "sg:phone":"+49 40/516420",
    "sg:postcode":"22299",
    "sg:province":"Hamburg",
    "wof:name":"Hans J. Und S. Wild",
    "wof:placetype":"venue"
},
  "geometry": {"coordinates":[9.99655056,53.5977058411],"type":"Point"}
}