{
  "type": "Feature",
  "properties": {
    "iso:country":"DE",
    "sg:address":"Johann-Strau\u00df-Weg 6",
    "sg:city":"Verl",
    "sg:phone":"+49 5246",
    "sg:postcode":"33415",
    "sg:province":"Nordrhein-Westfalen",
    "wof:name":"Ereion - Erfolgreich Online",
    "wof:placetype":"venue"
},
  "geometry": {"coordinates":[8.504394,51.875038],"type":"Point"}
}