{
  "type": "Feature",
  "properties": {
    "iso:country":"DE",
    "sg:address":"Ludwigsluster Str. 30",
    "sg:city":"Malli\u00df",
    "sg:phone":"+49 38750/20226",
    "sg:postcode":"19294",
    "sg:province":"Mecklenburg-Vorpommern",
    "wof:name":"E. St\u00fcrzenbecher",
    "wof:placetype":"venue"
},
  "geometry": {"coordinates":[11.3254051208,53.2131309509],"type":"Point"}
}