{
  "type": "Feature",
  "properties": {
    "iso:country":"DE",
    "sg:address":"Fuhrberger Str. 160",
    "sg:city":"Celle",
    "sg:phone":"+49 5141/44742",
    "sg:postcode":"29225",
    "sg:province":"Niedersachsen",
    "wof:name":"Klaus Wisch",
    "wof:placetype":"venue"
},
  "geometry": {"coordinates":[10.0388431549,52.6116371155],"type":"Point"}
}