{
  "type": "Feature",
  "properties": {
    "iso:country":"DE",
    "sg:address":"Berliner Str. 23",
    "sg:city":"A\u00dflar",
    "sg:phone":"+49 6441/81232",
    "sg:postcode":"35614",
    "sg:province":"Hessen",
    "wof:name":"Windisch Gmbh & Co. Transport Kg",
    "wof:placetype":"venue"
},
  "geometry": {"coordinates":[8.4672393799,50.5847434998],"type":"Point"}
}