{
  "type": "Feature",
  "properties": {
    "iso:country":"DE",
    "sg:address":"Von-Hutten-Str. 6",
    "sg:city":"Bad Bocklet",
    "sg:phone":"+49 9708/234",
    "sg:postcode":"97708",
    "sg:province":"Bayern",
    "wof:name":"Paul Beck",
    "wof:placetype":"venue"
},
  "geometry": {"coordinates":[10.0798110962,50.2658538818],"type":"Point"}
}