{
  "type": "Feature",
  "properties": {
    "iso:country":"DE",
    "sg:address":"Burgstr. 12",
    "sg:city":"Freigericht",
    "sg:phone":"+49 6055/5689",
    "sg:postcode":"63579",
    "sg:province":"Hessen",
    "wof:name":"Bernhard Hufnagel",
    "wof:placetype":"venue"
},
  "geometry": {"coordinates":[9.14483,50.140888],"type":"Point"}
}