{
  "type": "Feature",
  "properties": {
    "iso:country":"DE",
    "sg:address":"Am Neuen Bau 2",
    "sg:city":"Schwabach",
    "sg:phone":"+49 9122/15246",
    "sg:postcode":"91126",
    "sg:province":"Bayern",
    "wof:name":"Astrid Meyer",
    "wof:placetype":"venue"
},
  "geometry": {"coordinates":[11.016138,49.329445],"type":"Point"}
}