{
  "type": "Feature",
  "properties": {
    "iso:country":"DE",
    "sg:address":"Am Kahlenturm 2a",
    "sg:city":"Euskirchen",
    "sg:phone":"+49 2251/79260",
    "sg:postcode":"53879",
    "sg:province":"Nordrhein-Westfalen",
    "wof:name":"Lemm Kommunikations Gmbh",
    "wof:placetype":"venue"
},
  "geometry": {"coordinates":[6.790992,50.661438],"type":"Point"}
}