{
  "type": "Feature",
  "properties": {
    "iso:country":"DE",
    "sg:address":"Mercatorstr. 27",
    "sg:city":"Frankfurt",
    "sg:phone":"+49 69/444001",
    "sg:postcode":"60316",
    "sg:province":"Hessen",
    "wof:name":"Alison Gould",
    "wof:placetype":"venue"
},
  "geometry": {"coordinates":[8.6893777847,50.1206512451],"type":"Point"}
}