{
  "type": "Feature",
  "properties": {
    "iso:country":"DE",
    "sg:address":"Brenneckestr 94",
    "sg:city":"Magdeburg",
    "sg:phone":"+49 391/6229141",
    "sg:postcode":"39116",
    "sg:province":"Sachsen-Anhalt",
    "wof:name":"Pactex Gmbh",
    "wof:placetype":"venue"
},
  "geometry": {"coordinates":[11.589284,52.104828],"type":"Point"}
}