{
  "type": "Feature",
  "properties": {
    "iso:country":"DE",
    "sg:address":"Niederkasseler Str. 18",
    "sg:city":"K\u00f6ln",
    "sg:phone":"+49 2203/63759",
    "sg:postcode":"51147",
    "sg:province":"Nordrhein-Westfalen",
    "wof:name":"Auto-service Busse Gmbh",
    "wof:placetype":"venue"
},
  "geometry": {"coordinates":[7.104976,50.841373],"type":"Point"}
}