{
  "type": "Feature",
  "properties": {
    "iso:country":"DE",
    "sg:address":"N\u00fcrnberger Str. 19 -21",
    "sg:city":"Lauf",
    "sg:phone":"+49 9123/175512",
    "sg:postcode":"91207",
    "sg:province":"Bayern",
    "wof:name":"Verlag Hans Fahner",
    "wof:placetype":"venue"
},
  "geometry": {"coordinates":[11.2788162231,49.5117034912],"type":"Point"}
}