{
  "type": "Feature",
  "properties": {
    "iso:country":"DE",
    "sg:address":"Hofstr. 267",
    "sg:city":"Koblenz",
    "sg:phone":"+49 261/703364",
    "sg:postcode":"56077",
    "sg:province":"Rheinland-Pfalz",
    "wof:name":"China-restaurant Peking",
    "wof:placetype":"venue"
},
  "geometry": {"coordinates":[7.6103658676,50.360294342],"type":"Point"}
}