{
  "type": "Feature",
  "properties": {
    "iso:country":"DE",
    "sg:address":"Bauernweg 12",
    "sg:city":"Nordenham",
    "sg:phone":"+49 4731/2535",
    "sg:postcode":"26954",
    "sg:province":"Niedersachsen",
    "wof:name":"Gemeindeb\u00fccherei",
    "wof:placetype":"venue"
},
  "geometry": {"coordinates":[8.471398,53.497402],"type":"Point"}
}