{
  "type": "Feature",
  "properties": {
    "iso:country":"DE",
    "sg:address":"Hirtenstr. 2",
    "sg:city":"Mei\u00dfenheim",
    "sg:phone":"+49 7824/2189",
    "sg:postcode":"77974",
    "sg:province":"Baden-W\u00fcrttemberg",
    "wof:name":"R\u00fcdiger Wingert Rechtsanwalt",
    "wof:placetype":"venue"
},
  "geometry": {"coordinates":[7.7744669914,48.4090919495],"type":"Point"}
}