{
  "type": "Feature",
  "properties": {
    "iso:country":"DE",
    "sg:address":"Weststr. 30",
    "sg:city":"Hilden",
    "sg:phone":"+49 2103/55329",
    "sg:postcode":"40721",
    "sg:province":"Nordrhein-Westfalen",
    "wof:name":"G. Prause",
    "wof:placetype":"venue"
},
  "geometry": {"coordinates":[6.920737,51.162624],"type":"Point"}
}