{
  "type": "Feature",
  "properties": {
    "iso:country":"DE",
    "sg:address":"Komotauer Str. 32",
    "sg:city":"F\u00fcrth",
    "sg:phone":"+49 911/736533",
    "sg:postcode":"90766",
    "sg:province":"Bayern",
    "wof:name":"Manfred Eckart Steuerberater",
    "wof:placetype":"venue"
},
  "geometry": {"coordinates":[10.9565486908,49.4805641174],"type":"Point"}
}