{
  "type": "Feature",
  "properties": {
    "iso:country":"DE",
    "sg:address":"Bleckenstedter Str. 5",
    "sg:city":"Hildesheim",
    "sg:phone":"+49 5121/513036",
    "sg:postcode":"31137",
    "sg:province":"Niedersachsen",
    "wof:name":"Gero Koellmann",
    "wof:placetype":"venue"
},
  "geometry": {"coordinates":[9.9371767044,52.152015686],"type":"Point"}
}