{
  "type": "Feature",
  "properties": {
    "iso:country":"DE",
    "sg:address":"Bahnhofsplatz 21",
    "sg:city":"Hameln",
    "sg:phone":"+49 5151/13688",
    "sg:postcode":"31785",
    "sg:province":"Niedersachsen",
    "wof:name":"Bahnhofsgastst\u00e4tte",
    "wof:placetype":"venue"
},
  "geometry": {"coordinates":[9.3741235733,52.1009788513],"type":"Point"}
}