{
  "type": "Feature",
  "properties": {
    "iso:country":"DE",
    "sg:address":"Alte Schulstr. 13a",
    "sg:city":"Bad Nauheim",
    "sg:phone":"+49 6032/81217",
    "sg:postcode":"61231",
    "sg:province":"Hessen",
    "wof:name":"Bernhard Laux",
    "wof:placetype":"venue"
},
  "geometry": {"coordinates":[8.7451019287,50.4008674622],"type":"Point"}
}