{
  "type": "Feature",
  "properties": {
    "iso:country":"DE",
    "sg:address":"Augsburger Str. 38",
    "sg:city":"Aichach",
    "sg:postcode":"86551",
    "sg:province":"Bayern",
    "wof:name":"Solutec Lackiertechnik Gmbh",
    "wof:placetype":"venue"
},
  "geometry": {"coordinates":[11.12657,48.453094],"type":"Point"}
}