{
  "type": "Feature",
  "properties": {
    "iso:country":"DE",
    "sg:address":"Freunder Landstr. 6",
    "sg:city":"Aachen",
    "sg:phone":"+49 241/525200",
    "sg:postcode":"52078",
    "sg:province":"Nordrhein-Westfalen",
    "wof:name":"G\u00f6rlich & Vopel",
    "wof:placetype":"venue"
},
  "geometry": {"coordinates":[6.1910800934,50.751991272],"type":"Point"}
}