{
  "type": "Feature",
  "properties": {
    "iso:country":"DE",
    "sg:address":"Offerstr. 3",
    "sg:city":"Velbert",
    "sg:phone":"+49 2051/52342",
    "sg:postcode":"42551",
    "sg:province":"Nordrhein-Westfalen",
    "wof:name":"J\u00fcrgen Luckas Steuerberater",
    "wof:placetype":"venue"
},
  "geometry": {"coordinates":[7.045124054,51.3389472961],"type":"Point"}
}