{
  "type": "Feature",
  "properties": {
    "iso:country":"DE",
    "sg:address":"Gewerbegebiet Goellnitz",
    "sg:city":"Goellnitz",
    "sg:phone":"+49 34495/75690",
    "sg:postcode":"04626",
    "sg:province":"Th\u00fcringen",
    "wof:name":"Agrartech Lorenz Kfz - Landmaschinen - Stahlbau Service- U. Vertriebs Gm",
    "wof:placetype":"venue"
},
  "geometry": {"coordinates":[12.306,50.900211],"type":"Point"}
}