{
  "type": "Feature",
  "properties": {
    "iso:country":"DE",
    "sg:address":"Goethestr. 17",
    "sg:city":"Untersteinach",
    "sg:phone":"+49 9225/789",
    "sg:postcode":"95369",
    "sg:province":"Bayern",
    "wof:name":"Ulrich Kewel",
    "wof:placetype":"venue"
},
  "geometry": {"coordinates":[11.519657135,50.1313781738],"type":"Point"}
}