{
  "type": "Feature",
  "properties": {
    "iso:country":"DE",
    "sg:address":"Bergiusstr. 1",
    "sg:city":"Augsburg",
    "sg:phone":"+49 821/91359",
    "sg:postcode":"86199",
    "sg:province":"Bayern",
    "wof:name":"Centa Heidrich",
    "wof:placetype":"venue"
},
  "geometry": {"coordinates":[10.8851003647,48.3425788879],"type":"Point"}
}