{
  "type": "Feature",
  "properties": {
    "iso:country":"DE",
    "sg:address":"Aegidienstr. 73",
    "sg:city":"L\u00fcbeck",
    "sg:phone":"+49 451/75914",
    "sg:postcode":"23552",
    "sg:province":"Schleswig-Holstein",
    "wof:name":"Bodo Rindfleisch",
    "wof:placetype":"venue"
},
  "geometry": {"coordinates":[10.690032959,53.8642196655],"type":"Point"}
}