{
  "type": "Feature",
  "properties": {
    "iso:country":"DE",
    "sg:address":"Am Plan 3",
    "sg:city":"Berngau",
    "sg:phone":"+49 9181/905126",
    "sg:postcode":"92361",
    "sg:province":"Bayern",
    "wof:name":"Erich Sendner",
    "wof:placetype":"venue"
},
  "geometry": {"coordinates":[11.396705,49.251671],"type":"Point"}
}