{
  "type": "Feature",
  "properties": {
    "iso:country":"DE",
    "sg:address":"Espertstr. 7",
    "sg:city":"Mainburg",
    "sg:phone":"+49 8751/1342",
    "sg:postcode":"84048",
    "sg:province":"Bayern",
    "wof:name":"Espert-klause",
    "wof:placetype":"venue"
},
  "geometry": {"coordinates":[11.7880487442,48.6426506042],"type":"Point"}
}