{
  "type": "Feature",
  "properties": {
    "iso:country":"DE",
    "sg:address":"Am Arenberg 34",
    "sg:city":"Gablingen",
    "sg:phone":"+49 8230/2129",
    "sg:postcode":"86456",
    "sg:province":"Bayern",
    "wof:name":"Markus Bender",
    "wof:placetype":"venue"
},
  "geometry": {"coordinates":[10.8259267807,48.4608612061],"type":"Point"}
}