{
  "type": "Feature",
  "properties": {
    "iso:country":"DE",
    "sg:address":"Werner Von Siemens Str. 2",
    "sg:city":"Pfungstadt",
    "sg:phone":"+49 4961/57120",
    "sg:postcode":"64319",
    "sg:province":"Hessen",
    "wof:name":"Snap On Dtschl. Holding Gmbh",
    "wof:placetype":"venue"
},
  "geometry": {"coordinates":[8.619467,49.816998],"type":"Point"}
}