{
  "type": "Feature",
  "properties": {
    "iso:country":"DE",
    "sg:address":"Konrad-Adenauer-Str. 16",
    "sg:city":"Reinheim",
    "sg:phone":"+49 6162/941844",
    "sg:postcode":"64354",
    "sg:province":"Hessen",
    "wof:name":"Thorsten Str\u00f6her",
    "wof:placetype":"venue"
},
  "geometry": {"coordinates":[8.8318729401,49.8326721191],"type":"Point"}
}