{
  "type": "Feature",
  "properties": {
    "iso:country":"DE",
    "sg:address":"In der Schell 12",
    "sg:city":"Katzweiler",
    "sg:phone":"+49 6301/71460",
    "sg:postcode":"67734",
    "sg:province":"Rheinland-Pfalz",
    "wof:name":"Karl Barz",
    "wof:placetype":"venue"
},
  "geometry": {"coordinates":[7.6997351646,49.5053367615],"type":"Point"}
}