{
  "type": "Feature",
  "properties": {
    "iso:country":"DE",
    "sg:address":"Wasserstr. 6",
    "sg:city":"Moringen",
    "sg:phone":"+49 5554/8185",
    "sg:postcode":"37186",
    "sg:province":"Niedersachsen",
    "wof:name":"Sport Albrecht Gmbh",
    "wof:placetype":"venue"
},
  "geometry": {"coordinates":[9.871567,51.699425],"type":"Point"}
}