{
  "type": "Feature",
  "properties": {
    "iso:country":"DE",
    "sg:address":"Buchenstr. 5",
    "sg:city":"Baldham",
    "sg:postcode":"85598",
    "sg:province":"Bayern",
    "wof:name":"Seibold Verm\u00f6gens- Verwaltung Gmbh",
    "wof:placetype":"venue"
},
  "geometry": {"coordinates":[11.7799978256,48.0981712341],"type":"Point"}
}