{
  "type": "Feature",
  "properties": {
    "iso:country":"DE",
    "sg:address":"Nymphenburger Str. 190",
    "sg:city":"M\u00fcnchen",
    "sg:phone":"+49 89/167660",
    "sg:postcode":"80634",
    "sg:province":"Bayern",
    "wof:name":"Constanze-moden Vertrieb Max Koller",
    "wof:placetype":"venue"
},
  "geometry": {"coordinates":[11.53215,48.155811],"type":"Point"}
}