{
  "type": "Feature",
  "properties": {
    "iso:country":"DE",
    "sg:address":"Bergstr. 16",
    "sg:city":"Bernterode",
    "sg:phone":"+49 36076/44216",
    "sg:postcode":"37355",
    "sg:province":"Th\u00fcringen",
    "wof:name":"Wigbert Schwarz",
    "wof:placetype":"venue"
},
  "geometry": {"coordinates":[10.4750442505,51.397064209],"type":"Point"}
}