{
  "type": "Feature",
  "properties": {
    "iso:country":"DE",
    "sg:address":"Allmersallee 28",
    "sg:city":"Stade",
    "sg:phone":"+49 4141/62169",
    "sg:postcode":"21680",
    "sg:province":"Niedersachsen",
    "wof:name":"Gerhard Pr\u00f6hl",
    "wof:placetype":"venue"
},
  "geometry": {"coordinates":[9.481269,53.59269],"type":"Point"}
}