{
  "type": "Feature",
  "properties": {
    "iso:country":"DE",
    "sg:address":"Friedhofstr. 6",
    "sg:city":"Burglauer",
    "sg:phone":"+49 9733/3787",
    "sg:postcode":"97724",
    "sg:province":"Bayern",
    "wof:name":"Richard Pflaum Verlag Gmbh & Co. Kg",
    "wof:placetype":"venue"
},
  "geometry": {"coordinates":[10.1787834167,50.2748908997],"type":"Point"}
}