{
  "type": "Feature",
  "properties": {
    "iso:country":"DE",
    "sg:address":"Freiherrenstr. 1",
    "sg:city":"Grevenbroich",
    "sg:phone":"+49 2181/240700",
    "sg:postcode":"41515",
    "sg:province":"Nordrhein-Westfalen",
    "wof:name":"Heinz-j\u00fcrgen Ulrich Steuerberatungs Gmbh",
    "wof:placetype":"venue"
},
  "geometry": {"coordinates":[6.5728979111,51.091468811],"type":"Point"}
}