{
  "type": "Feature",
  "properties": {
    "iso:country":"DE",
    "sg:address":"Paul-Schneider-Str. 53",
    "sg:city":"Weimar",
    "sg:phone":"+49 3643/501369",
    "sg:postcode":"99425",
    "sg:province":"Th\u00fcringen",
    "wof:name":"S. Und Thomas R\u00e4mmler Architekten",
    "wof:placetype":"venue"
},
  "geometry": {"coordinates":[11.309491,50.978935],"type":"Point"}
}