{
  "type": "Feature",
  "properties": {
    "iso:country":"DE",
    "sg:address":"Am Emsdeich 33",
    "sg:city":"Leer",
    "sg:phone":"+49 491/9253540",
    "sg:postcode":"26789",
    "sg:province":"Niedersachsen",
    "wof:name":"Lammers Schiffselektronik Gmbh Rhauderfehn",
    "wof:placetype":"venue"
},
  "geometry": {"coordinates":[7.4349751472,53.2218360901],"type":"Point"}
}