{
  "type": "Feature",
  "properties": {
    "iso:country":"DE",
    "sg:address":"Kirchstr. 34",
    "sg:city":"Steyerberg",
    "sg:phone":"+49 5764/1023",
    "sg:postcode":"31595",
    "sg:province":"Niedersachsen",
    "wof:name":"H. Droste",
    "wof:placetype":"venue"
},
  "geometry": {"coordinates":[9.030875,52.568481],"type":"Point"}
}