{
  "type": "Feature",
  "properties": {
    "iso:country":"DE",
    "sg:address":"Sarningh\u00e4user Str. 47",
    "sg:city":"Steyerberg",
    "sg:phone":"+49 5764/877",
    "sg:postcode":"31595",
    "sg:province":"Niedersachsen",
    "wof:name":"Rotex Textilhandels- Und Produktionsges. Mbh",
    "wof:placetype":"venue"
},
  "geometry": {"coordinates":[9.0172491074,52.563835144],"type":"Point"}
}