{
  "type": "Feature",
  "properties": {
    "iso:country":"DE",
    "sg:address":"Neustr. 68",
    "sg:city":"H\u00fcckelhoven",
    "sg:phone":"+49 2462/4799",
    "sg:postcode":"41836",
    "sg:province":"Nordrhein-Westfalen",
    "wof:name":"Hermann-josef Mertzbach",
    "wof:placetype":"venue"
},
  "geometry": {"coordinates":[6.237513,51.005428],"type":"Point"}
}