{
  "type": "Feature",
  "properties": {
    "iso:country":"DE",
    "sg:address":"Nordenhamer Str. 156",
    "sg:city":"Delmenhorst",
    "sg:phone":"+49 4221/42225",
    "sg:postcode":"27751",
    "sg:province":"Niedersachsen",
    "wof:name":"Restaurant Am Schlachthof Cornelia Baldus-bollweg",
    "wof:placetype":"venue"
},
  "geometry": {"coordinates":[8.64727211,53.0638198853],"type":"Point"}
}