{
  "type": "Feature",
  "properties": {
    "iso:country":"DE",
    "sg:city":"Erfurt",
    "sg:postcode":"99087",
    "sg:province":"Th\u00fcringen",
    "wof:name":"Livestrip.cc",
    "wof:placetype":"venue"
},
  "geometry": {"coordinates":[11.023075,50.977684],"type":"Point"}
}