{
  "type": "Feature",
  "properties": {
    "iso:country":"DE",
    "sg:address":"Bayreuther Str. 3",
    "sg:city":"Himmelkron",
    "sg:phone":"+49 9273/96116",
    "sg:postcode":"95502",
    "sg:province":"Bayern",
    "wof:name":"Hotel Sleep & Go",
    "wof:placetype":"venue"
},
  "geometry": {"coordinates":[11.610704422,50.0565223694],"type":"Point"}
}