{
  "type": "Feature",
  "properties": {
    "iso:country":"DE",
    "sg:address":"Obernstr. 11",
    "sg:city":"Bielefeld",
    "sg:phone":"+49 521/68932",
    "sg:postcode":"33602",
    "sg:province":"Nordrhein-Westfalen",
    "wof:name":"Krane Optik- Und Akustik Gmbh & Co. Betriebs Kg",
    "wof:placetype":"venue"
},
  "geometry": {"coordinates":[8.5308570862,52.0201797485],"type":"Point"}
}