{
  "type": "Feature",
  "properties": {
    "iso:country":"DE",
    "sg:address":"Laubenweg 12",
    "sg:city":"K\u00f6nigswinter",
    "sg:phone":"+49 2244/3280",
    "sg:postcode":"53639",
    "sg:province":"Nordrhein-Westfalen",
    "wof:name":"Dr. Med. Marianne Ostwald \u00c4rztin F\u00fcr Allgemeinmedizin",
    "wof:placetype":"venue"
},
  "geometry": {"coordinates":[7.3400998116,50.6857681274],"type":"Point"}
}