{
  "type": "Feature",
  "properties": {
    "iso:country":"DE",
    "sg:address":"Breite Str. 53",
    "sg:city":"Wismar",
    "sg:postcode":"23966",
    "sg:province":"Mecklenburg-Vorpommern",
    "wof:name":"D. Borchert",
    "wof:placetype":"venue"
},
  "geometry": {"coordinates":[11.4607439041,53.8944244385],"type":"Point"}
}