{
  "type": "Feature",
  "properties": {
    "iso:country":"DE",
    "sg:address":"Nizzaallee 75",
    "sg:city":"Aachen",
    "sg:phone":"+49 241/155912",
    "sg:postcode":"52072",
    "sg:province":"Nordrhein-Westfalen",
    "wof:name":"Este Karla Tsantiotis",
    "wof:placetype":"venue"
},
  "geometry": {"coordinates":[6.074244976,50.7868652344],"type":"Point"}
}