{
  "type": "Feature",
  "properties": {
    "iso:country":"DE",
    "sg:address":"Alpenstr. 64",
    "sg:city":"Marktschellenberg",
    "sg:phone":"+49 8650/292",
    "sg:postcode":"83487",
    "sg:province":"Bayern",
    "wof:name":"Almbachklamm",
    "wof:placetype":"venue"
},
  "geometry": {"coordinates":[13.0347118378,47.6648521423],"type":"Point"}
}