{
  "type": "Feature",
  "properties": {
    "iso:country":"DE",
    "sg:address":"Benzer Str. 8",
    "sg:city":"Malente-N\u00fcchel",
    "sg:phone":"+49 3603/848656",
    "sg:postcode":"23714",
    "sg:province":"Schleswig-Holstein",
    "wof:name":"Salzadruck Gmbh",
    "wof:placetype":"venue"
},
  "geometry": {"coordinates":[10.6343164444,51.1056289673],"type":"Point"}
}