{
  "type": "Feature",
  "properties": {
    "iso:country":"DE",
    "sg:address":"Dorfstr. 55",
    "sg:city":"Meerbusch",
    "sg:phone":"+49 2132/93823",
    "sg:postcode":"40667",
    "sg:province":"Nordrhein-Westfalen",
    "wof:name":"Anglo Stahl Gmbh",
    "wof:placetype":"venue"
},
  "geometry": {"coordinates":[6.698694,51.253872],"type":"Point"}
}