{
  "type": "Feature",
  "properties": {
    "iso:country":"DE",
    "sg:address":"Heidestr 3",
    "sg:city":"Lemberg",
    "sg:phone":"+49 6331/40416",
    "sg:postcode":"66969",
    "sg:province":"Rheinland-Pfalz",
    "wof:name":"Vgv Georg Votteler",
    "wof:placetype":"venue"
},
  "geometry": {"coordinates":[7.6503081322,49.1667671204],"type":"Point"}
}