{
  "type": "Feature",
  "properties": {
    "iso:country":"DE",
    "sg:address":"Rheinaustr. 8",
    "sg:city":"Mannheim",
    "sg:phone":"+49 621/824846",
    "sg:postcode":"68163",
    "sg:province":"Baden-W\u00fcrttemberg",
    "wof:name":"Ursula Grombach",
    "wof:placetype":"venue"
},
  "geometry": {"coordinates":[8.467443,49.475433],"type":"Point"}
}