{
  "type": "Feature",
  "properties": {
    "iso:country":"DE",
    "sg:address":"Lessingstr. 9",
    "sg:city":"Herne",
    "sg:phone":"+49 2325/31407",
    "sg:postcode":"44652",
    "sg:province":"Nordrhein-Westfalen",
    "wof:name":"F. Illburger",
    "wof:placetype":"venue"
},
  "geometry": {"coordinates":[7.1722249985,51.5152740479],"type":"Point"}
}