{
  "type": "Feature",
  "properties": {
    "iso:country":"DE",
    "sg:address":"Goldsternstra\u00dfe 7-9",
    "sg:city":"Leipzig",
    "sg:phone":"+49 341/2511876",
    "sg:postcode":"04329",
    "sg:province":"Sachsen",
    "wof:name":"Fernsehmeister Und K\u00fcchenstudio Enghardt",
    "wof:placetype":"venue"
},
  "geometry": {"coordinates":[12.456438,51.354427],"type":"Point"}
}