{
  "type": "Feature",
  "properties": {
    "iso:country":"DE",
    "sg:address":"Langes Tal 11a",
    "sg:city":"Suhl",
    "sg:phone":"+49 3681/308139",
    "sg:postcode":"98529",
    "sg:province":"Th\u00fcringen",
    "wof:name":"H.-j. Junge",
    "wof:placetype":"venue"
},
  "geometry": {"coordinates":[10.627553,50.603062],"type":"Point"}
}