{
  "type": "Feature",
  "properties": {
    "iso:country":"DE",
    "sg:address":"Leifringhauser Str. 43c",
    "sg:city":"L\u00fcdenscheid",
    "sg:phone":"+49 2351/41474",
    "sg:postcode":"58511",
    "sg:province":"Nordrhein-Westfalen",
    "wof:name":"Friedhelm Schulte",
    "wof:placetype":"venue"
},
  "geometry": {"coordinates":[7.664440155,51.2179222107],"type":"Point"}
}