{
  "type": "Feature",
  "properties": {
    "iso:country":"DE",
    "sg:address":"Hauptstr.",
    "sg:city":"Durmersheim",
    "sg:phone":"+49 7245/3844",
    "sg:postcode":"76448",
    "sg:province":"Baden-W\u00fcrttemberg",
    "wof:name":"Esso Station",
    "wof:placetype":"venue"
},
  "geometry": {"coordinates":[8.266122818,48.9274253845],"type":"Point"}
}