{
  "type": "Feature",
  "properties": {
    "iso:country":"DE",
    "sg:address":"Schwanenstr. 5",
    "sg:city":"B\u00fchl",
    "sg:phone":"+49 7223/24355",
    "sg:postcode":"77815",
    "sg:province":"Baden-W\u00fcrttemberg",
    "wof:name":"Parkplatzbetriebsgesell. H\u00fcflischer Hof Mbh",
    "wof:placetype":"venue"
},
  "geometry": {"coordinates":[8.136758,48.695293],"type":"Point"}
}