{
  "type": "Feature",
  "properties": {
    "iso:country":"DE",
    "sg:address":"Bitscher Str. 8",
    "sg:city":"Fischbach",
    "sg:phone":"+49 6393/270",
    "sg:postcode":"66996",
    "sg:province":"Rheinland-Pfalz",
    "wof:name":"K. Heim",
    "wof:placetype":"venue"
},
  "geometry": {"coordinates":[7.661792,49.075432],"type":"Point"}
}