{
  "type": "Feature",
  "properties": {
    "iso:country":"DE",
    "sg:address":"Buchenstr. 24",
    "sg:city":"Kettershausen",
    "sg:phone":"+49 8333/2898",
    "sg:postcode":"86498",
    "sg:province":"Bayern",
    "wof:name":"Hans M\u00f6st",
    "wof:placetype":"venue"
},
  "geometry": {"coordinates":[10.27189,48.195984],"type":"Point"}
}