{
  "type": "Feature",
  "properties": {
    "iso:country":"DE",
    "sg:address":"Hinterbreitenthann 4",
    "sg:city":"Feuchtwangen",
    "sg:phone":"+49 9852/2437",
    "sg:postcode":"91555",
    "sg:province":"Bayern",
    "wof:name":"Wilhelm K\u00f6rber E. K.",
    "wof:placetype":"venue"
},
  "geometry": {"coordinates":[10.348173,49.215672],"type":"Point"}
}