{
  "type": "Feature",
  "properties": {
    "iso:country":"DE",
    "sg:address":"Gr\u00fcnstr. 11",
    "sg:city":"Velbert",
    "sg:phone":"+49 2051/53042",
    "sg:postcode":"42551",
    "sg:province":"Nordrhein-Westfalen",
    "wof:name":"Augenoptik M\u00f6ller Gmbh",
    "wof:placetype":"venue"
},
  "geometry": {"coordinates":[7.0482201576,51.3382492065],"type":"Point"}
}