{
  "type": "Feature",
  "properties": {
    "iso:country":"DE",
    "sg:address":"Alsterufer 10",
    "sg:city":"Hamburg",
    "sg:phone":"+49 40/414070",
    "sg:postcode":"20354",
    "sg:province":"Hamburg",
    "wof:name":"Russ Beteiligungs- Gmbh & Co. Kg",
    "wof:placetype":"venue"
},
  "geometry": {"coordinates":[9.996028,53.560375],"type":"Point"}
}