{
  "type": "Feature",
  "properties": {
    "iso:country":"DE",
    "sg:address":"Gostritzer Str. 61-63",
    "sg:city":"Dresden",
    "sg:phone":"+49 351/47348631",
    "sg:postcode":"01217",
    "sg:province":"Sachsen",
    "wof:name":"A & S Ingenieurges. Mbh",
    "wof:placetype":"venue"
},
  "geometry": {"coordinates":[13.7480201721,51.0129203796],"type":"Point"}
}