{
  "type": "Feature",
  "properties": {
    "iso:country":"DE",
    "sg:address":"Emil-Nolde-Weg 3",
    "sg:city":"Sindelfingen",
    "sg:phone":"+49 7031/879959",
    "sg:postcode":"71065",
    "sg:province":"Baden-W\u00fcrttemberg",
    "wof:name":"Gisela Porschke Masseurin",
    "wof:placetype":"venue"
},
  "geometry": {"coordinates":[9.036567,48.708977],"type":"Point"}
}