{
  "type": "Feature",
  "properties": {
    "iso:country":"DE",
    "sg:address":"Zuppinger Str. 31",
    "sg:city":"Freyung",
    "sg:phone":"+49 8551/96030",
    "sg:postcode":"94078",
    "sg:province":"Bayern",
    "wof:name":"Wolfsteiner Werkst\u00e4tten",
    "wof:placetype":"venue"
},
  "geometry": {"coordinates":[13.538809,48.808369],"type":"Point"}
}