{
  "type": "Feature",
  "properties": {
    "iso:country":"DE",
    "sg:address":"Brander Str. 43a",
    "sg:city":"Freiberg",
    "sg:phone":"+49 3731/71093",
    "sg:postcode":"09599",
    "sg:province":"Sachsen",
    "wof:name":"Fleischerei Richter Gmbh",
    "wof:placetype":"venue"
},
  "geometry": {"coordinates":[13.3380260468,50.9039573669],"type":"Point"}
}