{
  "type": "Feature",
  "properties": {
    "iso:country":"DE",
    "sg:address":"Bergblick 13",
    "sg:city":"Hameln",
    "sg:postcode":"31787",
    "sg:province":"Niedersachsen",
    "wof:name":"Weserberglandverlag Vertrieb",
    "wof:placetype":"venue"
},
  "geometry": {"coordinates":[9.28008461,52.1277236938],"type":"Point"}
}