{
  "type": "Feature",
  "properties": {
    "iso:country":"DE",
    "sg:address":"H\u00e4denkampstr. 17",
    "sg:city":"Essen",
    "sg:phone":"+49 4920/1620001",
    "sg:postcode":"45143",
    "sg:province":"Nordrhein-Westfalen",
    "wof:name":"Transcran Essen Transport Gmbh",
    "wof:placetype":"venue"
},
  "geometry": {"coordinates":[6.9853639603,51.4567718506],"type":"Point"}
}