{
  "type": "Feature",
  "properties": {
    "iso:country":"DE",
    "sg:address":"G\u00f6rresstr. 4",
    "sg:city":"D\u00fcsseldorf",
    "sg:phone":"+49 211/719292",
    "sg:postcode":"40597",
    "sg:province":"Nordrhein-Westfalen",
    "wof:name":"Lederwaren Und Polsterm\u00f6bel Brass",
    "wof:placetype":"venue"
},
  "geometry": {"coordinates":[6.8729982376,51.1641464233],"type":"Point"}
}