{
  "type": "Feature",
  "properties": {
    "iso:country":"DE",
    "sg:address":"Zwickauer Str. 10",
    "sg:city":"Lichtentanne",
    "sg:phone":"+49 375/528001",
    "sg:postcode":"08115",
    "sg:province":"Sachsen",
    "wof:name":"Gunter Vollgold Rechtsanwalt",
    "wof:placetype":"venue"
},
  "geometry": {"coordinates":[12.4017648697,50.6750679016],"type":"Point"}
}