{
  "type": "Feature",
  "properties": {
    "iso:country":"DE",
    "sg:address":"Wilhelmstr. 123-124",
    "sg:city":"Berlin",
    "sg:phone":"+49 30/260070",
    "sg:postcode":"10963",
    "sg:province":"Berlin",
    "wof:name":"Wohnpark Wilmersdorf Rudolf Schmidt Kg",
    "wof:placetype":"venue"
},
  "geometry": {"coordinates":[13.3873806,52.5034599304],"type":"Point"}
}