{
  "type": "Feature",
  "properties": {
    "iso:country":"DE",
    "sg:address":"Struhbach 2",
    "sg:city":"Hohen\u00f6llen",
    "sg:phone":"+49 6382/8405",
    "sg:postcode":"67744",
    "sg:province":"Rheinland-Pfalz",
    "wof:name":"Karl Kunz",
    "wof:placetype":"venue"
},
  "geometry": {"coordinates":[7.6285991669,49.621257782],"type":"Point"}
}