{
  "type": "Feature",
  "properties": {
    "iso:country":"DE",
    "sg:address":"Karl-Liebknecht-Str. 2",
    "sg:city":"Gardelegen",
    "sg:phone":"+49 3907/713986",
    "sg:postcode":"39638",
    "sg:province":"Sachsen-Anhalt",
    "wof:name":"F. Kuba",
    "wof:placetype":"venue"
},
  "geometry": {"coordinates":[11.405392,52.535625],"type":"Point"}
}