{
  "type": "Feature",
  "properties": {
    "iso:country":"DE",
    "sg:address":"\u00d6tztaler Str. 27",
    "sg:city":"Stuttgart",
    "sg:phone":"+49 711/331980",
    "sg:postcode":"70327",
    "sg:province":"Baden-W\u00fcrttemberg",
    "wof:name":"Rudolf Hammer",
    "wof:placetype":"venue"
},
  "geometry": {"coordinates":[9.251283,48.783173],"type":"Point"}
}