{
  "type": "Feature",
  "properties": {
    "iso:country":"DE",
    "sg:address":"Christoph-Sturm-Str. 25",
    "sg:city":"Hilpoltstein",
    "sg:phone":"+49 9174/3616",
    "sg:postcode":"91161",
    "sg:province":"Bayern",
    "wof:name":"Dies & Das Gdbr Geschenke",
    "wof:placetype":"venue"
},
  "geometry": {"coordinates":[11.1921,49.188011],"type":"Point"}
}