{
  "type": "Feature",
  "properties": {
    "iso:country":"DE",
    "sg:address":"Industriestr. 1",
    "sg:city":"Neunkirchen-Seelscheid",
    "sg:phone":"+49 4922/477020",
    "sg:postcode":"53819",
    "sg:province":"Nordrhein-Westfalen",
    "wof:name":"Easytec Hoffmannmaschinenbau Gmbh",
    "wof:placetype":"venue"
},
  "geometry": {"coordinates":[7.34157,50.884979],"type":"Point"}
}