{
  "type": "Feature",
  "properties": {
    "iso:country":"DE",
    "sg:address":"Martin-Luther-Str. 34",
    "sg:city":"Solingen",
    "sg:phone":"+49 212/272247",
    "sg:postcode":"42651",
    "sg:province":"Nordrhein-Westfalen",
    "wof:name":"Cimino",
    "wof:placetype":"venue"
},
  "geometry": {"coordinates":[7.0774569511,51.1659393311],"type":"Point"}
}