{
  "type": "Feature",
  "properties": {
    "iso:country":"DE",
    "sg:address":"Grenzstr. 8",
    "sg:city":"Steinigtwolmsdorf",
    "sg:phone":"+49 35951/32371",
    "sg:postcode":"01904",
    "sg:province":"Sachsen",
    "wof:name":"Reinhold Keul",
    "wof:placetype":"venue"
},
  "geometry": {"coordinates":[14.345342,51.06197],"type":"Point"}
}