{
  "type": "Feature",
  "properties": {
    "iso:country":"DE",
    "sg:address":"M\u00fchlenstr. 27",
    "sg:city":"Ettlingen",
    "sg:phone":"+49 7243/12133",
    "sg:postcode":"76275",
    "sg:province":"Baden-W\u00fcrttemberg",
    "wof:name":"Erbprinz-apotheke",
    "wof:placetype":"venue"
},
  "geometry": {"coordinates":[8.40578,48.94202],"type":"Point"}
}