{
  "type": "Feature",
  "properties": {
    "iso:country":"DE",
    "sg:address":"B\u00fcgels\u00e4ge 9",
    "sg:city":"Heikendorf",
    "sg:phone":"+49 431/24666",
    "sg:postcode":"24226",
    "sg:province":"Schleswig-Holstein",
    "wof:name":"Minicar Heikendorf Inh. Till Wenzkus",
    "wof:placetype":"venue"
},
  "geometry": {"coordinates":[10.2157554626,54.3791160583],"type":"Point"}
}