{
  "type": "Feature",
  "properties": {
    "iso:country":"DE",
    "sg:address":"Am Steinb\u00fchl 8",
    "sg:city":"Liebsch\u00fctz",
    "sg:phone":"+49 36640/22392",
    "sg:postcode":"07368",
    "sg:province":"Th\u00fcringen",
    "wof:name":"Wilfried Linke",
    "wof:placetype":"venue"
},
  "geometry": {"coordinates":[11.650145,50.568996],"type":"Point"}
}