{
  "type": "Feature",
  "properties": {
    "iso:country":"DE",
    "sg:address":"Hermann-L\u00f6ns-Str. 7",
    "sg:city":"Bad Salzuflen",
    "sg:postcode":"32105",
    "sg:province":"Nordrhein-Westfalen",
    "wof:name":"Kurhotel Und Pension Ostwestfalen Hof Gmbh",
    "wof:placetype":"venue"
},
  "geometry": {"coordinates":[8.753200531,52.0843467712],"type":"Point"}
}