{
  "type": "Feature",
  "properties": {
    "iso:country":"DE",
    "sg:address":"Teterower Str. 60",
    "sg:city":"J\u00f6rdenstorf",
    "sg:phone":"+49 39977/3550",
    "sg:postcode":"17168",
    "sg:province":"Mecklenburg-Vorpommern",
    "wof:name":"W\u00fcstenberg Landtechnik Gmbh & Co. Kg",
    "wof:placetype":"venue"
},
  "geometry": {"coordinates":[12.61775,53.881199],"type":"Point"}
}