{
  "type": "Feature",
  "properties": {
    "iso:country":"DE",
    "sg:address":"Elbestr. 35",
    "sg:city":"Mainz",
    "sg:phone":"+49 6131/41519",
    "sg:postcode":"55122",
    "sg:province":"Rheinland-Pfalz",
    "wof:name":"Georg Krupp",
    "wof:placetype":"venue"
},
  "geometry": {"coordinates":[8.217968,50.005016],"type":"Point"}
}