{
  "type": "Feature",
  "properties": {
    "iso:country":"DE",
    "sg:address":"Haarlemer Str. 31",
    "sg:city":"Berlin",
    "sg:phone":"+49 30/6097750",
    "sg:postcode":"12359",
    "sg:province":"Berlin",
    "wof:name":"Internea Gmbh",
    "wof:placetype":"venue"
},
  "geometry": {"coordinates":[13.4522562027,52.4573478699],"type":"Point"}
}