{
  "type": "Feature",
  "properties": {
    "iso:country":"DE",
    "sg:address":"Schwimmbadstr. 22",
    "sg:city":"M\u00f6nchberg",
    "sg:phone":"+49 9374/578",
    "sg:postcode":"63933",
    "sg:province":"Bayern",
    "wof:name":"A. Miltenberger",
    "wof:placetype":"venue"
},
  "geometry": {"coordinates":[9.2697372437,49.7917442322],"type":"Point"}
}