{
  "type": "Feature",
  "properties": {
    "iso:country":"DE",
    "sg:address":"Oberdorfer Str. 11",
    "sg:city":"Langenargen",
    "sg:phone":"+49 7543/3090",
    "sg:postcode":"88085",
    "sg:province":"Baden-W\u00fcrttemberg",
    "wof:name":"Hotel-restaurant Adler",
    "wof:placetype":"venue"
},
  "geometry": {"coordinates":[9.5403318405,47.5980072021],"type":"Point"}
}