{
  "type": "Feature",
  "properties": {
    "iso:country":"DE",
    "sg:address":"Am Bauhof 11",
    "sg:city":"Seevetal",
    "sg:phone":"+49 4105/57200",
    "sg:postcode":"21218",
    "sg:province":"Niedersachsen",
    "wof:name":"Kraftverkehr-ges. Mbh Kvg",
    "wof:placetype":"venue"
},
  "geometry": {"coordinates":[10.0062465668,53.3863258362],"type":"Point"}
}