{
  "type": "Feature",
  "properties": {
    "iso:country":"DE",
    "sg:address":"S\u00e4gendobel 9",
    "sg:city":"St. Peter",
    "sg:phone":"+49 7660/829",
    "sg:postcode":"79271",
    "sg:province":"Baden-W\u00fcrttemberg",
    "wof:name":"Fridolin Scherer",
    "wof:placetype":"venue"
},
  "geometry": {"coordinates":[8.0312414169,48.0363388062],"type":"Point"}
}