{
  "type": "Feature",
  "properties": {
    "iso:country":"DE",
    "sg:address":"Hauptstr. 97",
    "sg:city":"Nieb\u00fcll",
    "sg:phone":"+49 4661/9700",
    "sg:postcode":"25899",
    "sg:province":"Schleswig-Holstein",
    "wof:name":"Graphic Works Uwe Mussack E. K.",
    "wof:placetype":"venue"
},
  "geometry": {"coordinates":[8.823335,54.782391],"type":"Point"}
}