{
  "type": "Feature",
  "properties": {
    "iso:country":"DE",
    "sg:address":"Marktstr. 4",
    "sg:city":"Soltau",
    "sg:postcode":"29614",
    "sg:province":"Niedersachsen",
    "wof:name":"Textilhaus Bahrenburg Gmbh & Co. Kg",
    "wof:placetype":"venue"
},
  "geometry": {"coordinates":[9.8394041061,52.9861564636],"type":"Point"}
}