{
  "type": "Feature",
  "properties": {
    "iso:country":"DE",
    "sg:address":"Etterstr. 9",
    "sg:city":"Obersulm",
    "sg:phone":"+49 7134/17783",
    "sg:postcode":"74182",
    "sg:province":"Baden-W\u00fcrttemberg",
    "wof:name":"Ewald Volpp",
    "wof:placetype":"venue"
},
  "geometry": {"coordinates":[9.342114,49.147331],"type":"Point"}
}