{
  "type": "Feature",
  "properties": {
    "iso:country":"DE",
    "sg:address":"Drosselstr. 11",
    "sg:city":"Gevelsberg",
    "sg:phone":"+49 2332/4466",
    "sg:postcode":"58285",
    "sg:province":"Nordrhein-Westfalen",
    "wof:name":"W. Bremer",
    "wof:placetype":"venue"
},
  "geometry": {"coordinates":[7.331332,51.327351],"type":"Point"}
}