{
  "type": "Feature",
  "properties": {
    "iso:country":"DE",
    "sg:address":"Berliner Ring 4",
    "sg:city":"Lahstedt",
    "sg:phone":"+49 5172/37374",
    "sg:postcode":"31246",
    "sg:province":"Niedersachsen",
    "wof:name":"Manuela Wiese",
    "wof:placetype":"venue"
},
  "geometry": {"coordinates":[10.247395,52.260788],"type":"Point"}
}