{
  "type": "Feature",
  "properties": {
    "iso:country":"DE",
    "sg:address":"Marktplatz 19",
    "sg:city":"Gersfeld",
    "sg:postcode":"36129",
    "sg:province":"Hessen",
    "wof:name":"Stadtwerke Gersfeld",
    "wof:placetype":"venue"
},
  "geometry": {"coordinates":[9.917912,50.450249],"type":"Point"}
}