{
  "type": "Feature",
  "properties": {
    "iso:country":"DE",
    "sg:address":"Felsen",
    "sg:city":"Herzlake",
    "sg:phone":"+49 5962/517",
    "sg:postcode":"49770",
    "sg:province":"Niedersachsen",
    "wof:name":"Gastst\u00e4tte D. Br\u00fcggen",
    "wof:placetype":"venue"
},
  "geometry": {"coordinates":[7.596159935,52.6685409546],"type":"Point"}
}