{
  "type": "Feature",
  "properties": {
    "iso:country":"DE",
    "sg:address":"Wittighausensteige 2-1",
    "sg:city":"Unterm\u00fcnkheim",
    "sg:phone":"+49 791/75990",
    "sg:postcode":"74547",
    "sg:province":"Baden-W\u00fcrttemberg",
    "wof:name":"Robert Philipp Gmbh & Co. Kg",
    "wof:placetype":"venue"
},
  "geometry": {"coordinates":[9.710097,49.156391],"type":"Point"}
}