{
  "type": "Feature",
  "properties": {
    "iso:country":"DE",
    "sg:address":"Temdestr. 8a",
    "sg:city":"Detmold",
    "sg:phone":"+49 5231/68594",
    "sg:postcode":"32756",
    "sg:province":"Nordrhein-Westfalen",
    "wof:name":"Hubert Hermstein",
    "wof:placetype":"venue"
},
  "geometry": {"coordinates":[8.867483,51.941334],"type":"Point"}
}