{
  "type": "Feature",
  "properties": {
    "iso:country":"DE",
    "sg:address":"Am Markt 23",
    "sg:city":"Bad Hersfeld",
    "sg:phone":"+49 6621/14796",
    "sg:postcode":"36251",
    "sg:province":"Hessen",
    "wof:name":"Werner B\u00e4tz",
    "wof:placetype":"venue"
},
  "geometry": {"coordinates":[9.743666,50.897663],"type":"Point"}
}