{
  "type": "Feature",
  "properties": {
    "iso:country":"DE",
    "sg:address":"In der Ecke 23",
    "sg:city":"Litzendorf",
    "sg:phone":"+49 9505/7258",
    "sg:postcode":"96123",
    "sg:province":"Bayern",
    "wof:name":"H. Braun",
    "wof:placetype":"venue"
},
  "geometry": {"coordinates":[11.0729217529,49.9183311462],"type":"Point"}
}