{
  "type": "Feature",
  "properties": {
    "iso:country":"DE",
    "sg:address":"Parkstr. 4",
    "sg:city":"Altdorf",
    "sg:phone":"+49 9187/8858",
    "sg:postcode":"90518",
    "sg:province":"Bayern",
    "wof:name":"R. Wei\u00df",
    "wof:placetype":"venue"
},
  "geometry": {"coordinates":[11.339175,49.401218],"type":"Point"}
}