{
  "type": "Feature",
  "properties": {
    "iso:country":"DE",
    "sg:address":"Wallensteinstr. 4",
    "sg:city":"N\u00fcrnberg",
    "sg:postcode":"90439",
    "sg:province":"Bayern",
    "wof:name":"Pe Petz Electro Gmbh & Co. Kg",
    "wof:placetype":"venue"
},
  "geometry": {"coordinates":[11.0390357971,49.4402160645],"type":"Point"}
}