{
  "type": "Feature",
  "properties": {
    "iso:country":"DE",
    "sg:address":"Otto-Heilmann-Str. 24 b",
    "sg:city":"Gr\u00fcnwald",
    "sg:phone":"+49 89/64914053",
    "sg:postcode":"82031",
    "sg:province":"Bayern",
    "wof:name":"Toger Media Und Veranstaltungs Gmbh",
    "wof:placetype":"venue"
},
  "geometry": {"coordinates":[11.5354309082,48.0356788635],"type":"Point"}
}