{
  "type": "Feature",
  "properties": {
    "iso:country":"DE",
    "sg:address":"Hauptstr. 230",
    "sg:city":"Spiesen-Elversberg",
    "sg:phone":"+49 6821/730204",
    "sg:postcode":"66583",
    "sg:province":"Saarland",
    "wof:name":"J. G\u00fcnther",
    "wof:placetype":"venue"
},
  "geometry": {"coordinates":[7.1455159187,49.3110771179],"type":"Point"}
}