{
  "type": "Feature",
  "properties": {
    "iso:country":"DE",
    "sg:address":"Palanterstr. 5b",
    "sg:city":"K\u00f6ln",
    "sg:phone":"+49 221/424012",
    "sg:postcode":"50937",
    "sg:province":"Nordrhein-Westfalen",
    "wof:name":"Zwei Plus Zwei Andreas Gehlen Ohg",
    "wof:placetype":"venue"
},
  "geometry": {"coordinates":[6.926355,50.923111],"type":"Point"}
}