{
  "type": "Feature",
  "properties": {
    "iso:country":"DE",
    "sg:address":"Auf der Schlo\u00dfweide 65",
    "sg:city":"Stadecken-Elsheim",
    "sg:phone":"+49 6130/1277",
    "sg:postcode":"55271",
    "sg:province":"Rheinland-Pfalz",
    "wof:name":"Gerolf Clauss Darmhandel Ohg",
    "wof:placetype":"venue"
},
  "geometry": {"coordinates":[8.1280326843,49.9140701294],"type":"Point"}
}