{
  "type": "Feature",
  "properties": {
    "iso:country":"DE",
    "sg:address":"Willinghusener Weg 1",
    "sg:city":"Oststeinbek",
    "sg:phone":"+49 40/7132527",
    "sg:postcode":"22113",
    "sg:province":"Schleswig-Holstein",
    "wof:name":"Holger Schneider",
    "wof:placetype":"venue"
},
  "geometry": {"coordinates":[10.153958,53.54575],"type":"Point"}
}