{
  "type": "Feature",
  "properties": {
    "iso:country":"DE",
    "sg:address":"Dreskenkamp 5",
    "sg:city":"Ostercappeln",
    "sg:phone":"+49 5476/1531",
    "sg:postcode":"49179",
    "sg:province":"Niedersachsen",
    "wof:name":"Willi Sander",
    "wof:placetype":"venue"
},
  "geometry": {"coordinates":[8.19056,52.391315],"type":"Point"}
}