{
  "type": "Feature",
  "properties": {
    "iso:country":"DE",
    "sg:address":"J\u00e4gerstieg 17",
    "sg:city":"Hamburg",
    "sg:phone":"+49 40/6409530",
    "sg:postcode":"22391",
    "sg:province":"Hamburg",
    "wof:name":"Hamburger Hostessen Service Kurt Schnehagen",
    "wof:placetype":"venue"
},
  "geometry": {"coordinates":[10.095817,53.635479],"type":"Point"}
}