{
  "type": "Feature",
  "properties": {
    "iso:country":"DE",
    "sg:address":"Hornsteiner Strasse 2",
    "sg:city":"Bingen",
    "sg:postcode":"72511",
    "sg:province":"Baden-W\u00fcrttemberg",
    "wof:name":"Logdos Gmbh",
    "wof:placetype":"venue"
},
  "geometry": {"coordinates":[9.271566391,48.1108436584],"type":"Point"}
}