{
  "type": "Feature",
  "properties": {
    "iso:country":"DE",
    "sg:address":"Kastanienweg 17",
    "sg:city":"Zeven",
    "sg:phone":"+49 4281/3022",
    "sg:postcode":"27404",
    "sg:province":"Niedersachsen",
    "wof:name":"Hotel Garni Landhaus",
    "wof:placetype":"venue"
},
  "geometry": {"coordinates":[9.2745456696,53.3081626892],"type":"Point"}
}