{
  "type": "Feature",
  "properties": {
    "iso:country":"DE",
    "sg:address":"L\u00e4ngwitzer Str. 8",
    "sg:city":"Arnstadt",
    "sg:phone":"+49 3628/602571",
    "sg:postcode":"99310",
    "sg:province":"Th\u00fcringen",
    "wof:name":"Konrad L\u00f6ber",
    "wof:placetype":"venue"
},
  "geometry": {"coordinates":[10.952473,50.83263],"type":"Point"}
}