{
  "type": "Feature",
  "properties": {
    "iso:country":"DE",
    "sg:address":"Benrather Marktplatz 4",
    "sg:city":"D\u00fcsseldorf",
    "sg:phone":"+49 211/7118820",
    "sg:postcode":"40597",
    "sg:province":"Nordrhein-Westfalen",
    "wof:name":"Birk",
    "wof:placetype":"venue"
},
  "geometry": {"coordinates":[6.8731307983,51.1634483337],"type":"Point"}
}