{
  "type": "Feature",
  "properties": {
    "iso:country":"DE",
    "sg:address":"Hauptstr. 2",
    "sg:city":"Freystadt",
    "sg:phone":"+49 9179/5114",
    "sg:postcode":"92342",
    "sg:province":"Bayern",
    "wof:name":"Stadt-apotheke Freystadt Ingrid Popp",
    "wof:placetype":"venue"
},
  "geometry": {"coordinates":[11.356201,49.170685],"type":"Point"}
}