{
  "type": "Feature",
  "properties": {
    "iso:country":"DE",
    "sg:address":"Sonnenstr. 51",
    "sg:city":"Schongau",
    "sg:postcode":"86956",
    "sg:province":"Bayern",
    "wof:name":"Rudolf Eder",
    "wof:placetype":"venue"
},
  "geometry": {"coordinates":[10.8998003006,47.8193893433],"type":"Point"}
}