{
  "type": "Feature",
  "properties": {
    "iso:country":"DE",
    "sg:address":"M\u00fchlsteig 5",
    "sg:city":"Gersdorf",
    "sg:phone":"+49 37203/68318",
    "sg:postcode":"09355",
    "sg:province":"Sachsen",
    "wof:name":"Frieder Kleindienst",
    "wof:placetype":"venue"
},
  "geometry": {"coordinates":[14.05953,51.224941],"type":"Point"}
}