{
  "type": "Feature",
  "properties": {
    "iso:country":"DE",
    "sg:address":"Hohenloher Str.2",
    "sg:city":"Unterm\u00fcnkheim",
    "sg:phone":"+49 791",
    "sg:postcode":"74547",
    "sg:province":"Baden-W\u00fcrttemberg",
    "wof:name":"Gerhardt-zahntechnik",
    "wof:placetype":"venue"
},
  "geometry": {"coordinates":[9.734417,49.151569],"type":"Point"}
}