{
  "type": "Feature",
  "properties": {
    "iso:country":"DE",
    "sg:address":"Hauptstr. 7",
    "sg:city":"Vinningen",
    "sg:phone":"+49 6335/376",
    "sg:postcode":"66957",
    "sg:province":"Rheinland-Pfalz",
    "wof:name":"Schuster & Lelle",
    "wof:placetype":"venue"
},
  "geometry": {"coordinates":[7.553761,49.154224],"type":"Point"}
}