{
  "type": "Feature",
  "properties": {
    "iso:country":"DE",
    "sg:address":"M\u00fcnchener Str. 60",
    "sg:city":"Forstinning",
    "sg:phone":"+49 8121/3540",
    "sg:postcode":"85661",
    "sg:province":"Bayern",
    "wof:name":"Hans Hundhammer",
    "wof:placetype":"venue"
},
  "geometry": {"coordinates":[11.904054,48.162216],"type":"Point"}
}