{
  "type": "Feature",
  "properties": {
    "iso:country":"DE",
    "sg:address":"Rheinstr. 16",
    "sg:city":"Krefeld",
    "sg:phone":"+49 2151/560008",
    "sg:postcode":"47799",
    "sg:province":"Nordrhein-Westfalen",
    "wof:name":"Fischerheim-gesellschaft Kaufels Kg",
    "wof:placetype":"venue"
},
  "geometry": {"coordinates":[6.5704340935,51.3345756531],"type":"Point"}
}