{
  "type": "Feature",
  "properties": {
    "iso:country":"DE",
    "sg:address":"Berliner Str. 117",
    "sg:city":"Berlin",
    "sg:postcode":"10713",
    "sg:province":"Berlin",
    "wof:name":"Vvg Wohn- Und Gesch\u00e4ftsbauten Kg Verm\u00f6gens-verwaltungs-",
    "wof:placetype":"venue"
},
  "geometry": {"coordinates":[13.317208,52.486374],"type":"Point"}
}