{
  "type": "Feature",
  "properties": {
    "iso:country":"DE",
    "sg:address":"Gro\u00dfenroder Str. 3",
    "sg:city":"Moringen",
    "sg:phone":"+49 5503/698",
    "sg:postcode":"37186",
    "sg:province":"Niedersachsen",
    "wof:name":"Albert Rosenthal",
    "wof:placetype":"venue"
},
  "geometry": {"coordinates":[9.9055109024,51.6673202515],"type":"Point"}
}