{
  "type": "Feature",
  "properties": {
    "iso:country":"DE",
    "sg:address":"Lepsiusstr. 114",
    "sg:city":"Berlin",
    "sg:phone":"+49 30/79000701",
    "sg:postcode":"12165",
    "sg:province":"Berlin",
    "wof:name":"Bau-herr Verwaltungs Gmbh & Co. Goldammerstra\u00dfe Kg",
    "wof:placetype":"venue"
},
  "geometry": {"coordinates":[13.3123178482,52.4560089111],"type":"Point"}
}