{
  "type": "Feature",
  "properties": {
    "iso:country":"DE",
    "sg:address":"Am Sportplatz 12",
    "sg:city":"Dippmannsdorf",
    "sg:phone":"+49 33846/40002",
    "sg:postcode":"14806",
    "sg:province":"Brandenburg",
    "wof:name":"Gastst\u00e4tte Paradies",
    "wof:placetype":"venue"
},
  "geometry": {"coordinates":[12.5922651291,52.2226104736],"type":"Point"}
}