{
  "type": "Feature",
  "properties": {
    "iso:country":"DE",
    "sg:address":"Winkel 23",
    "sg:city":"Bernterode",
    "sg:phone":"+49 36082/40303",
    "sg:postcode":"37308",
    "sg:province":"Th\u00fcringen",
    "wof:name":"L. Reumann Immobilienmakler",
    "wof:placetype":"venue"
},
  "geometry": {"coordinates":[10.1365747452,51.3768615723],"type":"Point"}
}