{
  "type": "Feature",
  "properties": {
    "iso:country":"DE",
    "sg:address":"Asamstr. 5",
    "sg:city":"Pfeffenhausen",
    "sg:phone":"+49 8782/96020",
    "sg:postcode":"84076",
    "sg:province":"Bayern",
    "wof:name":"J. Maier",
    "wof:placetype":"venue"
},
  "geometry": {"coordinates":[11.9594955444,48.6659317017],"type":"Point"}
}