{
  "type": "Feature",
  "properties": {
    "iso:country":"DE",
    "sg:address":"Bayrische Str. 97",
    "sg:city":"Dortmund",
    "sg:phone":"+49 231/851082",
    "sg:postcode":"44339",
    "sg:province":"Nordrhein-Westfalen",
    "wof:name":"F. Neuhaus",
    "wof:placetype":"venue"
},
  "geometry": {"coordinates":[7.477261,51.554638],"type":"Point"}
}