{
  "type": "Feature",
  "properties": {
    "iso:country":"DE",
    "sg:address":"Irisstr. 31",
    "sg:city":"Kressbronn a.B.",
    "sg:phone":"+49 7543",
    "sg:postcode":"88079",
    "sg:province":"Baden-W\u00fcrttemberg",
    "wof:name":"Halbhuber",
    "wof:placetype":"venue"
},
  "geometry": {"coordinates":[9.5931749344,47.590133667],"type":"Point"}
}