{
  "type": "Feature",
  "properties": {
    "iso:country":"DE",
    "sg:address":"Schweriner Str. 23 a",
    "sg:city":"R\u00fcting",
    "sg:phone":"+49 38822/3441",
    "sg:postcode":"23936",
    "sg:province":"Mecklenburg-Vorpommern",
    "wof:name":"Elkes Landhaus",
    "wof:placetype":"venue"
},
  "geometry": {"coordinates":[11.2224559784,53.7934494019],"type":"Point"}
}