{
  "type": "Feature",
  "properties": {
    "iso:country":"DE",
    "sg:address":"Heinrich-Heine-Str 5",
    "sg:city":"Aschersleben",
    "sg:phone":"+49 3473/806250",
    "sg:postcode":"06449",
    "sg:province":"Sachsen-Anhalt",
    "wof:name":"F\u00f6lbrig",
    "wof:placetype":"venue"
},
  "geometry": {"coordinates":[11.462056,51.762047],"type":"Point"}
}