{
  "type": "Feature",
  "properties": {
    "iso:country":"DE",
    "sg:address":"Am Gummibahnhof 2",
    "sg:city":"Salzgitter",
    "sg:phone":"+49 5341/25256",
    "sg:postcode":"38239",
    "sg:province":"Niedersachsen",
    "wof:name":"Werner Dohrendorf Gmbh",
    "wof:placetype":"venue"
},
  "geometry": {"coordinates":[10.482886,52.187721],"type":"Point"}
}