{
  "type": "Feature",
  "properties": {
    "iso:country":"DE",
    "sg:address":"Hauptstr. 140",
    "sg:city":"Heidelberg",
    "sg:phone":"+49 6221/24001",
    "sg:postcode":"69117",
    "sg:province":"Baden-W\u00fcrttemberg",
    "wof:name":"Ilse Frosch",
    "wof:placetype":"venue"
},
  "geometry": {"coordinates":[8.706945,49.411591],"type":"Point"}
}