{
  "type": "Feature",
  "properties": {
    "iso:country":"DE",
    "sg:address":"Reuterstr. 11",
    "sg:city":"Kassel",
    "sg:postcode":"34117",
    "sg:province":"Hessen",
    "wof:name":"Abc Automobilhandelsfirmen Beteiligung-cooperation Gmbh",
    "wof:placetype":"venue"
},
  "geometry": {"coordinates":[9.490194,51.322392],"type":"Point"}
}