{
  "type": "Feature",
  "properties": {
    "iso:country":"DE",
    "sg:address":"Laurentiusplatz 1",
    "sg:city":"Senden",
    "sg:postcode":"48308",
    "sg:province":"Nordrhein-Westfalen",
    "wof:name":"Schwangerschaftskonflikt- Beratung",
    "wof:placetype":"venue"
},
  "geometry": {"coordinates":[7.487945,51.854946],"type":"Point"}
}