{
  "type": "Feature",
  "properties": {
    "iso:country":"DE",
    "sg:address":"Hombergallee 2",
    "sg:city":"Bad Wildungen",
    "sg:phone":"+49 5621/4127",
    "sg:postcode":"34537",
    "sg:province":"Hessen",
    "wof:name":"Reinhard Koch",
    "wof:placetype":"venue"
},
  "geometry": {"coordinates":[9.0800867081,51.1133842468],"type":"Point"}
}