{
  "type": "Feature",
  "properties": {
    "iso:country":"DE",
    "sg:address":"Gregor-Boecker-Str.3",
    "sg:city":"Witten",
    "sg:phone":"+49 2302/888107",
    "sg:postcode":"58455",
    "sg:province":"Nordrhein-Westfalen",
    "wof:name":"Krane Electronic",
    "wof:placetype":"venue"
},
  "geometry": {"coordinates":[7.346448,51.448605],"type":"Point"}
}