{
  "type": "Feature",
  "properties": {
    "iso:country":"DE",
    "sg:address":"Rudolf-Herzog-Str. 15",
    "sg:city":"Wuppertal",
    "sg:postcode":"42275",
    "sg:province":"Nordrhein-Westfalen",
    "wof:name":"Tennis Sport Umbrath E. K.",
    "wof:placetype":"venue"
},
  "geometry": {"coordinates":[7.19655,51.271564],"type":"Point"}
}