{
  "type": "Feature",
  "properties": {
    "iso:country":"DE",
    "sg:address":"Kirchdamm 9",
    "sg:city":"Grasberg",
    "sg:postcode":"28879",
    "sg:province":"Niedersachsen",
    "wof:name":"Planungsb\u00fcro M. Jesske Und A. Von Salzen",
    "wof:placetype":"venue"
},
  "geometry": {"coordinates":[8.9803762436,53.1890449524],"type":"Point"}
}