{
  "type": "Feature",
  "properties": {
    "iso:country":"DE",
    "sg:address":"Im Sp\u00f6\u00df 4",
    "sg:city":"Rehlingen-Siersburg",
    "sg:phone":"+49 6861/2596",
    "sg:postcode":"66780",
    "sg:province":"Saarland",
    "wof:name":"C. Rehlinger Immobilienmakler",
    "wof:placetype":"venue"
},
  "geometry": {"coordinates":[6.6483969688,49.4005813599],"type":"Point"}
}