{
  "type": "Feature",
  "properties": {
    "iso:country":"DE",
    "sg:address":"H\u00f6henstr. 2",
    "sg:city":"Leimen",
    "sg:phone":"+49 6226/8778",
    "sg:postcode":"69181",
    "sg:province":"Baden-W\u00fcrttemberg",
    "wof:name":"Medtro Gmbh",
    "wof:placetype":"venue"
},
  "geometry": {"coordinates":[8.75473,49.344864],"type":"Point"}
}