{
  "type": "Feature",
  "properties": {
    "iso:country":"DE",
    "sg:address":"Neuenhofstr. 66",
    "sg:city":"Duisburg",
    "sg:phone":"+49 203/734490",
    "sg:postcode":"47055",
    "sg:province":"Nordrhein-Westfalen",
    "wof:name":"Sebastiano Orlando",
    "wof:placetype":"venue"
},
  "geometry": {"coordinates":[6.753021,51.393829],"type":"Point"}
}