{
  "type": "Feature",
  "properties": {
    "iso:country":"DE",
    "sg:address":"Kemptener Str. 6-8",
    "sg:city":"Oberg\u00fcnzburg",
    "sg:phone":"+49 8372/7030",
    "sg:postcode":"87634",
    "sg:province":"Bayern",
    "wof:name":"J. M. Gabler Saliter Gmbh & Co. Kg",
    "wof:placetype":"venue"
},
  "geometry": {"coordinates":[10.4181480408,47.8454399109],"type":"Point"}
}