{
  "type": "Feature",
  "properties": {
    "iso:country":"DE",
    "sg:address":"Mecklenburger Str. 50",
    "sg:city":"L\u00fcbeck",
    "sg:phone":"+49 4945/169533",
    "sg:postcode":"23568",
    "sg:province":"Schleswig-Holstein",
    "wof:name":"Harry Maass Galvano- U. H\u00c4rtetechnik Gmbh",
    "wof:placetype":"venue"
},
  "geometry": {"coordinates":[10.799583,53.888016],"type":"Point"}
}