{
  "type": "Feature",
  "properties": {
    "iso:country":"DE",
    "sg:address":"Zum Gerlen 2",
    "sg:city":"Saarbr\u00fccken",
    "sg:phone":"+49 6893/3008",
    "sg:postcode":"66131",
    "sg:province":"Saarland",
    "wof:name":"K. Reuther S\u00f6hne",
    "wof:placetype":"venue"
},
  "geometry": {"coordinates":[7.1126961708,49.2108459473],"type":"Point"}
}