{
  "type": "Feature",
  "properties": {
    "iso:country":"DE",
    "sg:address":"Am Bahndamm 2",
    "sg:city":"Ense",
    "sg:phone":"+49 2938/49397",
    "sg:postcode":"59469",
    "sg:province":"Nordrhein-Westfalen",
    "wof:name":"Combi Selex Lebensmittel Gmbh & Co. Kg",
    "wof:placetype":"venue"
},
  "geometry": {"coordinates":[7.9981369972,51.4906005859],"type":"Point"}
}