{
  "type": "Feature",
  "properties": {
    "iso:country":"DE",
    "sg:address":"Am Flugfeld 33",
    "sg:city":"D\u00fcsseldorf",
    "sg:phone":"+49 211/404529",
    "sg:postcode":"40489",
    "sg:province":"Nordrhein-Westfalen",
    "wof:name":"Werner Metzner Rechtsanwalt",
    "wof:placetype":"venue"
},
  "geometry": {"coordinates":[6.7556538582,51.2962799072],"type":"Point"}
}