{
  "type": "Feature",
  "properties": {
    "iso:country":"DE",
    "sg:address":"Deichstr. 9",
    "sg:city":"Hamburg",
    "sg:phone":"+49 40/3743521",
    "sg:postcode":"20459",
    "sg:province":"Hamburg",
    "wof:name":"Verwaltung Take Off Aviation Advertising Gmbh",
    "wof:placetype":"venue"
},
  "geometry": {"coordinates":[9.9883556366,53.5467262268],"type":"Point"}
}