{
  "type": "Feature",
  "properties": {
    "iso:country":"DE",
    "sg:address":"Baruther Str. 4",
    "sg:city":"Zossen",
    "sg:postcode":"15806",
    "sg:province":"Brandenburg",
    "wof:name":"Planbau Gmbh",
    "wof:placetype":"venue"
},
  "geometry": {"coordinates":[13.45095,52.215069],"type":"Point"}
}