{
  "type": "Feature",
  "properties": {
    "iso:country":"DE",
    "sg:address":"Osterholzer Dorfstr. 19",
    "sg:city":"Bremen",
    "sg:phone":"+49 421/454084",
    "sg:postcode":"28307",
    "sg:province":"Bremen",
    "wof:name":"Lti Leistungsteam Ingenieurwesen",
    "wof:placetype":"venue"
},
  "geometry": {"coordinates":[8.9252300262,53.0580787659],"type":"Point"}
}