{
  "type": "Feature",
  "properties": {
    "iso:country":"DE",
    "sg:address":"Kannh\u00f6he 15",
    "sg:city":"Bad Sooden-Allendorf",
    "sg:phone":"+49 5652/2969",
    "sg:postcode":"37242",
    "sg:province":"Hessen",
    "wof:name":"D. Sonnabend",
    "wof:placetype":"venue"
},
  "geometry": {"coordinates":[9.9686508179,51.2762641907],"type":"Point"}
}