{
  "type": "Feature",
  "properties": {
    "iso:country":"DE",
    "sg:address":"Drosselweg 39",
    "sg:city":"Trier",
    "sg:phone":"+49 651/968170",
    "sg:postcode":"54293",
    "sg:province":"Rheinland-Pfalz",
    "wof:name":"Kugel-deges Ingenieur",
    "wof:placetype":"venue"
},
  "geometry": {"coordinates":[6.6818208694,49.7986907959],"type":"Point"}
}