{
  "type": "Feature",
  "properties": {
    "iso:country":"DE",
    "sg:address":"Pulsnitzer Str. 24",
    "sg:city":"Radeberg",
    "sg:phone":"+49 3528/443511",
    "sg:postcode":"01454",
    "sg:province":"Sachsen",
    "wof:name":"Radeberger Bierstube",
    "wof:placetype":"venue"
},
  "geometry": {"coordinates":[13.9214096069,51.1191291809],"type":"Point"}
}