{
  "type": "Feature",
  "properties": {
    "iso:country":"DE",
    "sg:address":"Rotenh\u00f6fer Weg 52",
    "sg:city":"Borgstedt",
    "sg:phone":"+49 4331/38444",
    "sg:postcode":"24794",
    "sg:province":"Schleswig-Holstein",
    "wof:name":"M\u00f6belvertretung Hardmut Sieg",
    "wof:placetype":"venue"
},
  "geometry": {"coordinates":[9.7109823227,54.3347358704],"type":"Point"}
}