{
  "type": "Feature",
  "properties": {
    "iso:country":"DE",
    "sg:address":"Schuttergasse 3",
    "sg:city":"Offenburg",
    "sg:phone":"+49 781/92280",
    "sg:postcode":"77652",
    "sg:province":"Baden-W\u00fcrttemberg",
    "wof:name":"Rainer Kr\u00e4mer Und Hanns Wolz Architekten",
    "wof:placetype":"venue"
},
  "geometry": {"coordinates":[7.945485,48.470444],"type":"Point"}
}