{
  "type": "Feature",
  "properties": {
    "iso:country":"DE",
    "sg:address":"Hellweg 5",
    "sg:city":"Bochum",
    "sg:phone":"+49 234/686421",
    "sg:postcode":"44787",
    "sg:province":"Nordrhein-Westfalen",
    "wof:name":"Kookai",
    "wof:placetype":"venue"
},
  "geometry": {"coordinates":[7.22048,51.479965],"type":"Point"}
}