{
  "type": "Feature",
  "properties": {
    "iso:country":"DE",
    "sg:address":"Triftstr. 90",
    "sg:city":"Essen",
    "sg:phone":"+49 201/692549",
    "sg:postcode":"45357",
    "sg:province":"Nordrhein-Westfalen",
    "wof:name":"D. Funck",
    "wof:placetype":"venue"
},
  "geometry": {"coordinates":[6.930704,51.479969],"type":"Point"}
}