{
  "type": "Feature",
  "properties": {
    "iso:country":"DE",
    "sg:address":"Talweg 2 d",
    "sg:city":"Kirchseeon",
    "sg:phone":"+49 8091/9965",
    "sg:postcode":"85614",
    "sg:province":"Bayern",
    "wof:name":"Alfred Kurz Architekt",
    "wof:placetype":"venue"
},
  "geometry": {"coordinates":[11.899355,48.070194],"type":"Point"}
}