{
  "type": "Feature",
  "properties": {
    "iso:country":"DE",
    "sg:address":"Am Wolfsbaum 1",
    "sg:city":"Neulingen",
    "sg:phone":"+49 7237/4300",
    "sg:postcode":"75245",
    "sg:province":"Baden-W\u00fcrttemberg",
    "wof:name":"Rob-electronic Gmbh",
    "wof:placetype":"venue"
},
  "geometry": {"coordinates":[8.708383,48.953339],"type":"Point"}
}