{
  "type": "Feature",
  "properties": {
    "iso:country":"DE",
    "sg:address":"An der Ruhrbr\u00fccke",
    "sg:city":"Schwerte",
    "sg:phone":"+49 2304/7601",
    "sg:postcode":"58239",
    "sg:province":"Nordrhein-Westfalen",
    "wof:name":"Aral Ag",
    "wof:placetype":"venue"
},
  "geometry": {"coordinates":[7.5672860146,51.4356803894],"type":"Point"}
}