{
  "type": "Feature",
  "properties": {
    "iso:country":"DE",
    "sg:address":"Lindenstr. 15",
    "sg:city":"K\u00f6ln",
    "sg:phone":"+49 221/238917",
    "sg:postcode":"50674",
    "sg:province":"Nordrhein-Westfalen",
    "wof:name":"Inge Balkhausen Antiquit\u00e4ten",
    "wof:placetype":"venue"
},
  "geometry": {"coordinates":[6.93784,50.934139],"type":"Point"}
}