{
  "type": "Feature",
  "properties": {
    "iso:country":"DE",
    "sg:address":"Radolfzeller Str. 33",
    "sg:city":"Stockach",
    "sg:phone":"+49 7771/2659",
    "sg:postcode":"78333",
    "sg:province":"Baden-W\u00fcrttemberg",
    "wof:name":"M. Klatt",
    "wof:placetype":"venue"
},
  "geometry": {"coordinates":[9.0002088547,47.8453712463],"type":"Point"}
}