{
  "type": "Feature",
  "properties": {
    "iso:country":"DE",
    "sg:address":"Bergweg 5",
    "sg:city":"Goldbach",
    "sg:phone":"+49 6021/57752",
    "sg:postcode":"63773",
    "sg:province":"Bayern",
    "wof:name":"H. Bergmann",
    "wof:placetype":"venue"
},
  "geometry": {"coordinates":[9.1789808273,50.0000762939],"type":"Point"}
}