{
  "type": "Feature",
  "properties": {
    "iso:country":"DE",
    "sg:address":"Schwarzbachstr. 42",
    "sg:city":"Stuttgart",
    "sg:phone":"+49 711/741598",
    "sg:postcode":"70565",
    "sg:province":"Baden-W\u00fcrttemberg",
    "wof:name":"Kurt Bressel",
    "wof:placetype":"venue"
},
  "geometry": {"coordinates":[9.1091480255,48.7175598145],"type":"Point"}
}