{
  "type": "Feature",
  "properties": {
    "iso:country":"DE",
    "sg:address":"Wetzlerstra\u00dfe 12",
    "sg:city":"G\u00fcnzburg (Germany)",
    "sg:phone":"+49 8221/250910",
    "sg:postcode":"89312",
    "sg:province":"Bayern",
    "wof:name":"Das Gute Wort",
    "wof:placetype":"venue"
},
  "geometry": {"coordinates":[10.260178,48.454086],"type":"Point"}
}