{
  "type": "Feature",
  "properties": {
    "iso:country":"DE",
    "sg:address":"Fundstr. 29",
    "sg:city":"Hannover",
    "sg:phone":"+49 511/314861",
    "sg:postcode":"30161",
    "sg:province":"Niedersachsen",
    "wof:name":"Schweckendiek Und Metzler Rechtsanw\u00e4lte",
    "wof:placetype":"venue"
},
  "geometry": {"coordinates":[9.7537174225,52.3833580017],"type":"Point"}
}