{
  "type": "Feature",
  "properties": {
    "iso:country":"DE",
    "sg:address":"Mitterstra\u00dfweg 15",
    "sg:city":"Stra\u00dflach-Dingharting",
    "sg:phone":"+49 4926/4691480",
    "sg:postcode":"82064",
    "sg:province":"Bayern",
    "wof:name":"Lipowski & Thelen Gmbh",
    "wof:placetype":"venue"
},
  "geometry": {"coordinates":[7.0974931717,50.4873657227],"type":"Point"}
}