{
  "type": "Feature",
  "properties": {
    "iso:country":"DE",
    "sg:address":"Am Kreuzgarten 4",
    "sg:city":"Gersfeld",
    "sg:phone":"+49 6654/557",
    "sg:postcode":"36129",
    "sg:province":"Hessen",
    "wof:name":"G\u00e4stehaus Julius Weinig",
    "wof:placetype":"venue"
},
  "geometry": {"coordinates":[9.9139461517,50.4523239136],"type":"Point"}
}