{
  "type": "Feature",
  "properties": {
    "iso:country":"DE",
    "sg:address":"Hauptstr. 2",
    "sg:city":"Langensendelbach",
    "sg:phone":"+49 9133/4192",
    "sg:postcode":"91094",
    "sg:province":"Bayern",
    "wof:name":"Manfred K\u00f6gel",
    "wof:placetype":"venue"
},
  "geometry": {"coordinates":[11.0704393387,49.6414604187],"type":"Point"}
}