{
  "type": "Feature",
  "properties": {
    "iso:country":"DE",
    "sg:address":"Klingenhagen 6",
    "sg:city":"Vechta",
    "sg:postcode":"49377",
    "sg:province":"Niedersachsen",
    "wof:name":"Stiftung St. Antoniushaus",
    "wof:placetype":"venue"
},
  "geometry": {"coordinates":[8.2888307571,52.7292518616],"type":"Point"}
}