{
  "type": "Feature",
  "properties": {
    "iso:country":"DE",
    "sg:address":"Ulmenweg 5",
    "sg:city":"Rosenheim",
    "sg:phone":"+49 8031/68200",
    "sg:postcode":"83022",
    "sg:province":"Bayern",
    "wof:name":"Wilhelm Zehetmaier",
    "wof:placetype":"venue"
},
  "geometry": {"coordinates":[12.1470975876,47.8452758789],"type":"Point"}
}