{
  "type": "Feature",
  "properties": {
    "iso:country":"DE",
    "sg:address":"Am Moritzpark 13",
    "sg:city":"Wallerstein",
    "sg:phone":"+49 9085/1765",
    "sg:postcode":"86757",
    "sg:province":"Bayern",
    "wof:name":"Rolf Aichinger Transport Gmbh",
    "wof:placetype":"venue"
},
  "geometry": {"coordinates":[10.4636487961,48.8869628906],"type":"Point"}
}