{
  "type": "Feature",
  "properties": {
    "iso:country":"DE",
    "sg:address":"Ledererzeile 23",
    "sg:city":"Wasserburg",
    "sg:phone":"+49 8071/924815",
    "sg:postcode":"83512",
    "sg:province":"Bayern",
    "wof:name":"H & T Messe Wasserburg Gmbh",
    "wof:placetype":"venue"
},
  "geometry": {"coordinates":[12.230988,48.061909],"type":"Point"}
}