{
  "type": "Feature",
  "properties": {
    "iso:country":"DE",
    "sg:address":"Industriestr 15a-d",
    "sg:city":"Henstedt-Ulzburg",
    "sg:phone":"+49 4193/89770",
    "sg:postcode":"24558",
    "sg:province":"Schleswig-Holstein",
    "wof:name":"G\u00d6rg\u00dc Hydraulik - Maschinenbau Gmbh",
    "wof:placetype":"venue"
},
  "geometry": {"coordinates":[9.981962,53.762573],"type":"Point"}
}