{
  "type": "Feature",
  "properties": {
    "iso:country":"DE",
    "sg:address":"Mittelpfad 23-25",
    "sg:city":"Linkenheim-Hochstetten",
    "sg:phone":"+49 7247/1500",
    "sg:postcode":"76351",
    "sg:province":"Baden-W\u00fcrttemberg",
    "wof:name":"Rolf Sch\u00f6necker Masseur",
    "wof:placetype":"venue"
},
  "geometry": {"coordinates":[8.408448,49.124187],"type":"Point"}
}