{
  "type": "Feature",
  "properties": {
    "iso:country":"DE",
    "sg:address":"Dinslakener Landstr. 25",
    "sg:city":"Wesel",
    "sg:phone":"+49 4928/1338920",
    "sg:postcode":"46483",
    "sg:province":"Nordrhein-Westfalen",
    "wof:name":"Man Nutzfahrzeuge Ag",
    "wof:placetype":"venue"
},
  "geometry": {"coordinates":[6.626318,51.652496],"type":"Point"}
}