{
  "type": "Feature",
  "properties": {
    "iso:country":"DE",
    "sg:address":"Untergath 175",
    "sg:city":"Krefeld",
    "sg:postcode":"47805",
    "sg:province":"Nordrhein-Westfalen",
    "wof:name":"Car-charter Autovermietung Gmbh",
    "wof:placetype":"venue"
},
  "geometry": {"coordinates":[6.589737,51.320934],"type":"Point"}
}