{
  "type": "Feature",
  "properties": {
    "iso:country":"DE",
    "sg:address":"K\u00f6penicker Allee 110-118",
    "sg:city":"Waldesruh b. Berlin",
    "sg:phone":"+49 30/56699205",
    "sg:postcode":"12625",
    "sg:province":"Berlin",
    "wof:name":"Nva-soldat",
    "wof:placetype":"venue"
},
  "geometry": {"coordinates":[13.6278,52.47974],"type":"Point"}
}