{
  "type": "Feature",
  "properties": {
    "iso:country":"DE",
    "sg:address":"Am Busbahnhof",
    "sg:city":"Wei\u00dfwasser",
    "sg:phone":"+49 3576/205114",
    "sg:postcode":"02943",
    "sg:province":"Sachsen",
    "wof:name":"Uschis Imbi\u00df",
    "wof:placetype":"venue"
},
  "geometry": {"coordinates":[14.6144952774,51.4643287659],"type":"Point"}
}