{
  "type": "Feature",
  "properties": {
    "iso:country":"DE",
    "sg:address":"Raubaer Str. 1",
    "sg:city":"Lommatzsch",
    "sg:phone":"+49 35241/560",
    "sg:postcode":"01623",
    "sg:province":"Sachsen",
    "wof:name":"Kn\u00fcrr Electronics Gmbh",
    "wof:placetype":"venue"
},
  "geometry": {"coordinates":[13.3046102524,51.1926612854],"type":"Point"}
}