{
  "type": "Feature",
  "properties": {
    "iso:country":"DE",
    "sg:address":"Schalaunische Str. 2",
    "sg:city":"K\u00f6then",
    "sg:phone":"+49 3496/212920",
    "sg:postcode":"06366",
    "sg:province":"Sachsen-Anhalt",
    "wof:name":"Fr\u00fcchtehaus Gitschel",
    "wof:placetype":"venue"
},
  "geometry": {"coordinates":[11.9741477966,51.7495613098],"type":"Point"}
}