{
  "type": "Feature",
  "properties": {
    "iso:country":"DE",
    "sg:address":"Chausseestr. 31",
    "sg:city":"Rehagen",
    "sg:phone":"+49 33703/7565",
    "sg:postcode":"15806",
    "sg:province":"Brandenburg",
    "wof:name":"Werner Tomzak",
    "wof:placetype":"venue"
},
  "geometry": {"coordinates":[13.3700389862,52.1665039062],"type":"Point"}
}