{
  "type": "Feature",
  "properties": {
    "iso:country":"DE",
    "sg:address":"Almh\u00f6he 7",
    "sg:city":"Soltau",
    "sg:phone":"+49 5191/5077",
    "sg:postcode":"29614",
    "sg:province":"Niedersachsen",
    "wof:name":"Rathsmann Gmbh & Co.",
    "wof:placetype":"venue"
},
  "geometry": {"coordinates":[9.8214673996,52.9752426147],"type":"Point"}
}