{
  "type": "Feature",
  "properties": {
    "iso:country":"DE",
    "sg:address":"Frankenpl. 1",
    "sg:city":"Kirchberg",
    "sg:phone":"+49 4979/54505",
    "sg:postcode":"74592",
    "sg:province":"Baden-W\u00fcrttemberg",
    "wof:name":"Volksbank Gerabronn Eg.",
    "wof:placetype":"venue"
},
  "geometry": {"coordinates":[9.980623,49.202637],"type":"Point"}
}