{
  "type": "Feature",
  "properties": {
    "iso:country":"DE",
    "sg:address":"Regensburger Str. 5A",
    "sg:city":"Berlin",
    "sg:phone":"+49 30/2114455",
    "sg:postcode":"10777",
    "sg:province":"Berlin",
    "wof:name":"Sibylle Kirchner",
    "wof:placetype":"venue"
},
  "geometry": {"coordinates":[13.338631,52.496002],"type":"Point"}
}