{
  "type": "Feature",
  "properties": {
    "iso:country":"DE",
    "sg:address":"Stormarnring 18",
    "sg:city":"Stapelfeld",
    "sg:phone":"+49 40/6775370",
    "sg:postcode":"22145",
    "sg:province":"Hamburg",
    "wof:name":"Dieter Scheel Buch- Und Offsetdruckerei",
    "wof:placetype":"venue"
},
  "geometry": {"coordinates":[10.205811,53.603951],"type":"Point"}
}