{
  "type": "Feature",
  "properties": {
    "iso:country":"DE",
    "sg:address":"Ellener Str. 21",
    "sg:city":"D\u00fcren",
    "sg:phone":"+49 2421/33146",
    "sg:postcode":"52353",
    "sg:province":"Nordrhein-Westfalen",
    "wof:name":"H.j. Hinzen",
    "wof:placetype":"venue"
},
  "geometry": {"coordinates":[6.4919810295,50.8397521973],"type":"Point"}
}