{
  "type": "Feature",
  "properties": {
    "iso:country":"DE",
    "sg:address":"Rudolf-Eucken-Str. 3",
    "sg:city":"Moormerland",
    "sg:phone":"+49 4954/6575",
    "sg:postcode":"26802",
    "sg:province":"Niedersachsen",
    "wof:name":"M. Niemeyer",
    "wof:placetype":"venue"
},
  "geometry": {"coordinates":[7.4867610931,53.3084487915],"type":"Point"}
}