{
  "type": "Feature",
  "properties": {
    "iso:country":"DE",
    "sg:address":"Am Anger 4",
    "sg:city":"Welden",
    "sg:phone":"+49 8293/7141",
    "sg:postcode":"86465",
    "sg:province":"Bayern",
    "wof:name":"I. Kunzmann",
    "wof:placetype":"venue"
},
  "geometry": {"coordinates":[10.657592,48.461212],"type":"Point"}
}