{
  "type": "Feature",
  "properties": {
    "iso:country":"DE",
    "sg:address":"Bahnhofstr. 35",
    "sg:city":"Garching",
    "sg:phone":"+49 8634/66745",
    "sg:postcode":"84518",
    "sg:province":"Bayern",
    "wof:name":"Rubatex Gmbh",
    "wof:placetype":"venue"
},
  "geometry": {"coordinates":[12.5734767914,48.1366882324],"type":"Point"}
}