{
  "type": "Feature",
  "properties": {
    "iso:country":"DE",
    "sg:address":"Weiherstr. 7",
    "sg:city":"Heilsbronn",
    "sg:phone":"+49 9872/2501",
    "sg:postcode":"91560",
    "sg:province":"Bayern",
    "wof:name":"Hermann Ebert",
    "wof:placetype":"venue"
},
  "geometry": {"coordinates":[10.788473,49.340096],"type":"Point"}
}