{
  "type": "Feature",
  "properties": {
    "iso:country":"DE",
    "sg:address":"Mattentwiete 2",
    "sg:city":"Hamburg",
    "sg:postcode":"20457",
    "sg:province":"Hamburg",
    "wof:name":"B\u00f6hler & Busch Dienstleistungs- Gmbh",
    "wof:placetype":"venue"
},
  "geometry": {"coordinates":[9.989103,53.545788],"type":"Point"}
}