{
  "type": "Feature",
  "properties": {
    "iso:country":"DE",
    "sg:address":"Kurt-Schumacher-Str. 12",
    "sg:city":"Rosbach",
    "sg:phone":"+49 6003/1898",
    "sg:postcode":"61191",
    "sg:province":"Hessen",
    "wof:name":"Jon P. Pahlow",
    "wof:placetype":"venue"
},
  "geometry": {"coordinates":[8.6886491776,50.3072891235],"type":"Point"}
}