{
  "type": "Feature",
  "properties": {
    "iso:country":"DE",
    "sg:address":"Marktplatz 10",
    "sg:city":"Weilm\u00fcnster",
    "sg:phone":"+49 6472/7611",
    "sg:postcode":"35789",
    "sg:province":"Hessen",
    "wof:name":"Gundis",
    "wof:placetype":"venue"
},
  "geometry": {"coordinates":[8.375135,50.431629],"type":"Point"}
}