{
  "type": "Feature",
  "properties": {
    "iso:country":"DE",
    "sg:address":"Dahmsdorfer Str. 6",
    "sg:city":"Reichenwalde",
    "sg:phone":"+49 33631/8570",
    "sg:postcode":"15526",
    "sg:province":"Brandenburg",
    "wof:name":"Hoffnungstaler Anstalten",
    "wof:placetype":"venue"
},
  "geometry": {"coordinates":[13.995966,52.263409],"type":"Point"}
}