{
  "type": "Feature",
  "properties": {
    "iso:country":"DE",
    "sg:address":"Gr\u00e4fenberger Str. 30a",
    "sg:city":"Neunkirchen",
    "sg:phone":"+49 9134/995629",
    "sg:postcode":"91077",
    "sg:province":"Bayern",
    "wof:name":"A. Und A. Fuchs",
    "wof:placetype":"venue"
},
  "geometry": {"coordinates":[11.134256,49.610985],"type":"Point"}
}