{
  "type": "Feature",
  "properties": {
    "iso:country":"DE",
    "sg:address":"Sprucker Str. 89",
    "sg:city":"Guben",
    "sg:phone":"+49 3561/67400",
    "sg:postcode":"03172",
    "sg:province":"Brandenburg",
    "wof:name":"Udo Bley",
    "wof:placetype":"venue"
},
  "geometry": {"coordinates":[14.6975870132,51.9484291077],"type":"Point"}
}