{
  "type": "Feature",
  "properties": {
    "iso:country":"DE",
    "sg:address":"Illerweg 2",
    "sg:city":"Olching",
    "sg:phone":"+49 8142/489310",
    "sg:postcode":"82140",
    "sg:province":"Bayern",
    "wof:name":"Bernd Nickel Architekt",
    "wof:placetype":"venue"
},
  "geometry": {"coordinates":[11.334241,48.211983],"type":"Point"}
}