{
  "type": "Feature",
  "properties": {
    "iso:country":"DE",
    "sg:address":"Diefenbach",
    "sg:city":"Sternenfels",
    "sg:phone":"+49 7043/2448",
    "sg:postcode":"75447",
    "sg:province":"Baden-W\u00fcrttemberg",
    "wof:name":"Adler",
    "wof:placetype":"venue"
},
  "geometry": {"coordinates":[8.8528699875,49.0284385681],"type":"Point"}
}