{
  "type": "Feature",
  "properties": {
    "iso:country":"DE",
    "sg:address":"Primelweg 10",
    "sg:city":"Gr\u00fcnwald",
    "sg:phone":"+49 89/64939184",
    "sg:postcode":"82031",
    "sg:province":"Bayern",
    "wof:name":"Michael Brucks Rechtsanwalt",
    "wof:placetype":"venue"
},
  "geometry": {"coordinates":[11.5371236801,48.0428504944],"type":"Point"}
}