{
  "type": "Feature",
  "properties": {
    "iso:country":"DE",
    "sg:address":"Briloner Str. 14",
    "sg:city":"Bad Arolsen",
    "sg:phone":"+49 5691/2559",
    "sg:postcode":"34454",
    "sg:province":"Hessen",
    "wof:name":"Christian B\u00f6hle Metallbau",
    "wof:placetype":"venue"
},
  "geometry": {"coordinates":[8.953979,51.391403],"type":"Point"}
}