{
  "type": "Feature",
  "properties": {
    "iso:country":"DE",
    "sg:address":"L\u00f6tscher Weg 69",
    "sg:city":"Nettetal",
    "sg:phone":"+49 37362/8408",
    "sg:postcode":"41334",
    "sg:province":"Nordrhein-Westfalen",
    "wof:name":"Herbert Helbig",
    "wof:placetype":"venue"
},
  "geometry": {"coordinates":[13.441129,50.647762],"type":"Point"}
}