{
  "type": "Feature",
  "properties": {
    "iso:country":"DE",
    "sg:address":"Sonnenstr. 4",
    "sg:city":"Bad Gr\u00f6nenbach",
    "sg:postcode":"87730",
    "sg:province":"Bayern",
    "wof:name":"Raiffeisen-waren Gmbh",
    "wof:placetype":"venue"
},
  "geometry": {"coordinates":[10.222604,47.874943],"type":"Point"}
}