{
  "type": "Feature",
  "properties": {
    "iso:country":"DE",
    "sg:address":"R\u00f6nnebecker Str. 11",
    "sg:city":"Flessau",
    "sg:phone":"+49 39392/339",
    "sg:postcode":"39606",
    "sg:province":"Sachsen-Anhalt",
    "wof:name":"Horst-g\u00fcnter Penningstorf",
    "wof:placetype":"venue"
},
  "geometry": {"coordinates":[11.670814,52.763897],"type":"Point"}
}