{
  "type": "Feature",
  "properties": {
    "iso:country":"DE",
    "sg:address":"Am Lindenhofe 19",
    "sg:city":"Hannover",
    "sg:phone":"+49 511/842740",
    "sg:postcode":"30519",
    "sg:province":"Niedersachsen",
    "wof:name":"Ev. Pfarramt St. Petrikirche D\u00f6hren",
    "wof:placetype":"venue"
},
  "geometry": {"coordinates":[9.7620363235,52.3350143433],"type":"Point"}
}