{
  "type": "Feature",
  "properties": {
    "iso:country":"DE",
    "sg:address":"Widumestr. 9",
    "sg:city":"Bochum",
    "sg:phone":"+49 234/12813",
    "sg:postcode":"44787",
    "sg:province":"Nordrhein-Westfalen",
    "wof:name":"August Hahnel Kg",
    "wof:placetype":"venue"
},
  "geometry": {"coordinates":[7.215131,51.486961],"type":"Point"}
}