{
  "type": "Feature",
  "properties": {
    "iso:country":"DE",
    "sg:address":"Friedhofweg 2",
    "sg:city":"Uffenheim",
    "sg:phone":"+49 9842/97877",
    "sg:postcode":"97215",
    "sg:province":"Bayern",
    "wof:name":"Erich Kamleiter Ingenieur",
    "wof:placetype":"venue"
},
  "geometry": {"coordinates":[10.2344903946,49.5437698364],"type":"Point"}
}