{
  "type": "Feature",
  "properties": {
    "iso:country":"DE",
    "sg:address":"Waldheimstr. 16",
    "sg:city":"Wildenbruch",
    "sg:phone":"+49 33205/63008",
    "sg:postcode":"14552",
    "sg:province":"Brandenburg",
    "wof:name":"Dr. B. Toepel Rechtsanwalt",
    "wof:placetype":"venue"
},
  "geometry": {"coordinates":[13.0466499329,52.2977485657],"type":"Point"}
}