{
  "type": "Feature",
  "properties": {
    "iso:country":"DE",
    "sg:address":"Nidaforum 5",
    "sg:city":"Frankfurt",
    "sg:phone":"+49 69/570786",
    "sg:postcode":"60439",
    "sg:province":"Hessen",
    "wof:name":"E. M\u00fchlensiepen Gmbh & Co. Kg",
    "wof:placetype":"venue"
},
  "geometry": {"coordinates":[8.6321191788,50.1576957703],"type":"Point"}
}