{
  "type": "Feature",
  "properties": {
    "iso:country":"DE",
    "sg:address":"Stresemannallee 19",
    "sg:city":"Frankfurt",
    "sg:postcode":"60596",
    "sg:province":"Hessen",
    "wof:name":"Gesellschaft Zur F\u00f6rderung Der Elektrischen Hausger\u00e4te-",
    "wof:placetype":"venue"
},
  "geometry": {"coordinates":[8.670294,50.098412],"type":"Point"}
}