{
  "type": "Feature",
  "properties": {
    "iso:country":"DE",
    "sg:address":"Am Stadion",
    "sg:city":"Schwaf\u00f6rden",
    "sg:phone":"+49 4277/609",
    "sg:postcode":"27252",
    "sg:province":"Niedersachsen",
    "wof:name":"Sportlerheim",
    "wof:placetype":"venue"
},
  "geometry": {"coordinates":[8.8185186386,52.7366638184],"type":"Point"}
}