{
  "type": "Feature",
  "properties": {
    "iso:country":"DE",
    "sg:address":"Sudetenstr. 74",
    "sg:city":"Kaufbeuren",
    "sg:phone":"+49 8341/98338",
    "sg:postcode":"87600",
    "sg:province":"Bayern",
    "wof:name":"St. Barbara-apotheke An Den Kirchen",
    "wof:placetype":"venue"
},
  "geometry": {"coordinates":[10.646222,47.897789],"type":"Point"}
}