{
  "type": "Feature",
  "properties": {
    "iso:country":"DE",
    "sg:address":"G\u00fcterstra\u00dfe 5",
    "sg:city":"Krefeld",
    "sg:phone":"+49 2151/389292",
    "sg:postcode":"47805",
    "sg:province":"Nordrhein-Westfalen",
    "wof:name":"F1 Indoor Kart Gmbh Krefeld",
    "wof:placetype":"venue"
},
  "geometry": {"coordinates":[6.5829968452,51.3284225464],"type":"Point"}
}