{
  "type": "Feature",
  "properties": {
    "iso:country":"DE",
    "sg:address":"Postfach 2706",
    "sg:city":"Mainz",
    "sg:phone":"+49 6135/9100",
    "sg:postcode":"55017",
    "wof:name":"Kuemmerling Gmbh",
    "wof:placetype":"venue"
},
  "geometry": {"coordinates":[8.2678499222,49.9978790283],"type":"Point"}
}