{
  "type": "Feature",
  "properties": {
    "iso:country":"DE",
    "sg:address":"Wilhelm-Ruppert-Str. 38",
    "sg:city":"K\u00f6ln",
    "sg:phone":"+49 2203/63095",
    "sg:postcode":"51147",
    "sg:province":"Nordrhein-Westfalen",
    "wof:name":"Der Fliesen Mann Handels-gmbh",
    "wof:placetype":"venue"
},
  "geometry": {"coordinates":[7.0902791023,50.8571662903],"type":"Point"}
}