{
  "type": "Feature",
  "properties": {
    "iso:country":"DE",
    "sg:address":"Br\u00fcckenstr. 14",
    "sg:city":"Chemnitz",
    "sg:phone":"+49 371/6761376",
    "sg:postcode":"09111",
    "sg:province":"Sachsen",
    "wof:name":"Buchhaus Gmbh Inh. Monika Lang Und",
    "wof:placetype":"venue"
},
  "geometry": {"coordinates":[12.9212121964,50.8366661072],"type":"Point"}
}