{
  "type": "Feature",
  "properties": {
    "iso:country":"DE",
    "sg:address":"Am Alten Weiher 5",
    "sg:city":"Winterbach",
    "sg:phone":"+49 9075/415",
    "sg:postcode":"89368",
    "sg:province":"Bayern",
    "wof:name":"H. Braun",
    "wof:placetype":"venue"
},
  "geometry": {"coordinates":[10.5136709213,48.4630622864],"type":"Point"}
}