{
  "type": "Feature",
  "properties": {
    "iso:country":"DE",
    "sg:address":"Fischmarkt 16",
    "sg:city":"Hamburg",
    "sg:phone":"+49 40/31792390",
    "sg:postcode":"22767",
    "sg:province":"Hamburg",
    "wof:name":"Esn Engineering Services Network Gmbh",
    "wof:placetype":"venue"
},
  "geometry": {"coordinates":[9.9523935318,53.5460014343],"type":"Point"}
}