{
  "type": "Feature",
  "properties": {
    "iso:country":"DE",
    "sg:address":"Franz-Schweizer-Str. 13",
    "sg:city":"St Martin",
    "sg:phone":"+49 6323/980423",
    "sg:postcode":"67487",
    "sg:province":"Rheinland-Pfalz",
    "wof:name":"S. St\u00f6ckl",
    "wof:placetype":"venue"
},
  "geometry": {"coordinates":[8.1070365906,49.3024177551],"type":"Point"}
}