{
  "type": "Feature",
  "properties": {
    "iso:country":"DE",
    "sg:address":"Langert 15",
    "sg:city":"Fichtenberg",
    "sg:postcode":"74427",
    "sg:province":"Baden-W\u00fcrttemberg",
    "wof:name":"Hampele Profiltechnik Gmbh",
    "wof:placetype":"venue"
},
  "geometry": {"coordinates":[9.68895,48.979416],"type":"Point"}
}