{
  "type": "Feature",
  "properties": {
    "iso:country":"DE",
    "sg:address":"J\u00fcdenstr. 8",
    "sg:city":"Zerbst",
    "sg:phone":"+49 3923/781933",
    "sg:postcode":"39261",
    "sg:province":"Sachsen-Anhalt",
    "wof:name":"Joachim Beyer",
    "wof:placetype":"venue"
},
  "geometry": {"coordinates":[12.082359314,51.9678688049],"type":"Point"}
}