{
  "type": "Feature",
  "properties": {
    "iso:country":"DE",
    "sg:address":"Belforter Str. 15",
    "sg:city":"Gelsenkirchen",
    "sg:phone":"+49 209/136825",
    "sg:postcode":"45884",
    "sg:province":"Nordrhein-Westfalen",
    "wof:name":"Klaus Sielisch",
    "wof:placetype":"venue"
},
  "geometry": {"coordinates":[7.081497,51.489464],"type":"Point"}
}