{
  "type": "Feature",
  "properties": {
    "iso:country":"DE",
    "sg:address":"Elbeallee 83",
    "sg:city":"Falkensee",
    "sg:phone":"+49 3322/3419",
    "sg:postcode":"14612",
    "sg:province":"Brandenburg",
    "wof:name":"Fritz Timmermann Gmbh",
    "wof:placetype":"venue"
},
  "geometry": {"coordinates":[13.0643520355,52.5744438171],"type":"Point"}
}