{
  "type": "Feature",
  "properties": {
    "iso:country":"DE",
    "sg:address":"Bahnhofstr. 33",
    "sg:city":"Kruft",
    "sg:phone":"+49 2652/6183",
    "sg:postcode":"56642",
    "sg:province":"Rheinland-Pfalz",
    "wof:name":"M\u00f6bel Sch\u00fctz Rhegro Einrichtungs- Gmbh",
    "wof:placetype":"venue"
},
  "geometry": {"coordinates":[7.33621,50.388699],"type":"Point"}
}