{
  "type": "Feature",
  "properties": {
    "iso:country":"DE",
    "sg:address":"Am Steinicht 11",
    "sg:city":"Coburg",
    "sg:phone":"+49 9561/66663",
    "sg:postcode":"96450",
    "sg:province":"Bayern",
    "wof:name":"Gerhard Bengl Rechtsanwalt",
    "wof:placetype":"venue"
},
  "geometry": {"coordinates":[10.9475679398,50.2781219482],"type":"Point"}
}