{
  "type": "Feature",
  "properties": {
    "iso:country":"DE",
    "sg:address":"Winzerring 36",
    "sg:city":"Frankfurt",
    "sg:phone":"+49 335/541711",
    "sg:postcode":"15236",
    "sg:province":"Brandenburg",
    "wof:name":"Walter Macholl",
    "wof:placetype":"venue"
},
  "geometry": {"coordinates":[14.5304718018,52.3347625732],"type":"Point"}
}