{
  "type": "Feature",
  "properties": {
    "iso:country":"DE",
    "sg:address":"Neuer Markt 1",
    "sg:city":"Lohne",
    "sg:phone":"+49 4442/71630",
    "sg:postcode":"49393",
    "sg:province":"Niedersachsen",
    "wof:name":"Franziskaner",
    "wof:placetype":"venue"
},
  "geometry": {"coordinates":[8.2337608337,52.6658706665],"type":"Point"}
}