{
  "type": "Feature",
  "properties": {
    "iso:country":"DE",
    "sg:address":"Schr\u00f6ttinghauser Str. 6",
    "sg:city":"Bielefeld",
    "sg:phone":"+49 521/885857",
    "sg:postcode":"33739",
    "sg:province":"Nordrhein-Westfalen",
    "wof:name":"Wilhelm B\u00fcltmann",
    "wof:placetype":"venue"
},
  "geometry": {"coordinates":[8.496068,52.060459],"type":"Point"}
}