{
  "type": "Feature",
  "properties": {
    "iso:country":"DE",
    "sg:address":"Bernardstr. 94",
    "sg:city":"Offenbach",
    "sg:phone":"+49 69/880533",
    "sg:postcode":"63067",
    "sg:province":"Hessen",
    "wof:name":"H. Euler",
    "wof:placetype":"venue"
},
  "geometry": {"coordinates":[8.7481107712,50.1070213318],"type":"Point"}
}