{
  "type": "Feature",
  "properties": {
    "iso:country":"DE",
    "sg:address":"Kahmannshof 2a",
    "sg:city":"Bielefeld",
    "sg:phone":"+49 5206/707323",
    "sg:postcode":"33739",
    "sg:province":"Nordrhein-Westfalen",
    "wof:name":"Paul Smart",
    "wof:placetype":"venue"
},
  "geometry": {"coordinates":[8.5042915344,52.0985069275],"type":"Point"}
}