{
  "type": "Feature",
  "properties": {
    "iso:country":"DE",
    "sg:address":"Kn\u00f6pflerstr. 1",
    "sg:city":"M\u00fcnchen",
    "sg:phone":"+49 89/75080401",
    "sg:postcode":"81476",
    "sg:province":"Bayern",
    "wof:name":"Layer",
    "wof:placetype":"venue"
},
  "geometry": {"coordinates":[11.4977502823,48.0946311951],"type":"Point"}
}