{
  "type": "Feature",
  "properties": {
    "iso:country":"DE",
    "sg:address":"Ulhaus 21",
    "sg:city":"Langerwehe",
    "sg:postcode":"52379",
    "sg:province":"Nordrhein-Westfalen",
    "wof:name":"Tpd Dienstleistungen Gmbh",
    "wof:placetype":"venue"
},
  "geometry": {"coordinates":[6.3547911644,50.8184204102],"type":"Point"}
}