{
  "type": "Feature",
  "properties": {
    "iso:country":"DE",
    "sg:address":"Moltkestr. 89",
    "sg:city":"K\u00f6ln",
    "sg:phone":"+49 221/511473",
    "sg:postcode":"50674",
    "sg:province":"Nordrhein-Westfalen",
    "wof:name":"Ralf Leinburger",
    "wof:placetype":"venue"
},
  "geometry": {"coordinates":[6.932415,50.937809],"type":"Point"}
}