{
  "type": "Feature",
  "properties": {
    "iso:country":"DE",
    "sg:address":"Mundsburger Damm 67",
    "sg:city":"Hamburg",
    "sg:phone":"+49 40/2205343",
    "sg:postcode":"22087",
    "sg:province":"Hamburg",
    "wof:name":"Mc Donalds Deutschland Inc.",
    "wof:placetype":"venue"
},
  "geometry": {"coordinates":[10.026684761,53.5701751709],"type":"Point"}
}