{
  "type": "Feature",
  "properties": {
    "iso:country":"DE",
    "sg:address":"Markttwiete 8",
    "sg:city":"Bad Schwartau",
    "sg:phone":"+49 451/26667",
    "sg:postcode":"23611",
    "sg:province":"Schleswig-Holstein",
    "wof:name":"N. Mende",
    "wof:placetype":"venue"
},
  "geometry": {"coordinates":[10.6972665787,53.9184417725],"type":"Point"}
}