{
  "type": "Feature",
  "properties": {
    "iso:country":"DE",
    "sg:address":"Ziegeleiweg 1",
    "sg:city":"Erndtebr\u00fcck",
    "sg:phone":"+49 2753/66132",
    "sg:postcode":"57339",
    "sg:province":"Nordrhein-Westfalen",
    "wof:name":"Gewa - Gebr. Wahl Gmbh & Co. Kg",
    "wof:placetype":"venue"
},
  "geometry": {"coordinates":[8.2925014496,50.9975738525],"type":"Point"}
}