{
  "type": "Feature",
  "properties": {
    "iso:country":"DE",
    "sg:address":"Bergstr. 6",
    "sg:city":"Erdweg",
    "sg:postcode":"85253",
    "sg:province":"Bayern",
    "wof:name":"Canjos Sportartikel Gmbh",
    "wof:placetype":"venue"
},
  "geometry": {"coordinates":[11.2909431458,48.3247108459],"type":"Point"}
}