{
  "type": "Feature",
  "properties": {
    "iso:country":"DE",
    "sg:address":"Ottersteig 13",
    "sg:city":"Dorsten",
    "sg:phone":"+49 2362/27496",
    "sg:postcode":"46282",
    "sg:province":"Nordrhein-Westfalen",
    "wof:name":"Heribert Hantrop Architekt",
    "wof:placetype":"venue"
},
  "geometry": {"coordinates":[6.95189,51.654915],"type":"Point"}
}