{
  "type": "Feature",
  "properties": {
    "iso:country":"DE",
    "sg:address":"G\u00fcntherstr. 11",
    "sg:city":"Haldensleben",
    "sg:phone":"+49 3904/71820",
    "sg:postcode":"39340",
    "sg:province":"Sachsen-Anhalt",
    "wof:name":"A Und I Planungsb\u00fcro",
    "wof:placetype":"venue"
},
  "geometry": {"coordinates":[11.3982210159,52.2878341675],"type":"Point"}
}