{
  "type": "Feature",
  "properties": {
    "iso:country":"DE",
    "sg:address":"Schlo\u00dfstr. 1",
    "sg:city":"Nagold",
    "sg:postcode":"72202",
    "sg:province":"Baden-W\u00fcrttemberg",
    "wof:name":"O & B Ortmeier & Bayer Gmbh",
    "wof:placetype":"venue"
},
  "geometry": {"coordinates":[8.749098,48.51091],"type":"Point"}
}