{
  "type": "Feature",
  "properties": {
    "iso:country":"DE",
    "sg:address":"Rienecker Str. 5",
    "sg:city":"M\u00fcnchen",
    "sg:phone":"+49 89/876712",
    "sg:postcode":"81249",
    "sg:province":"Bayern",
    "wof:name":"Thomas Feckl",
    "wof:placetype":"venue"
},
  "geometry": {"coordinates":[11.417787,48.153721],"type":"Point"}
}