{
  "type": "Feature",
  "properties": {
    "iso:country":"DE",
    "sg:address":"Gelmer Str. 20",
    "sg:city":"Greven",
    "sg:phone":"+49 2571/98450",
    "sg:postcode":"48268",
    "sg:province":"Nordrhein-Westfalen",
    "wof:name":"R. Schlott",
    "wof:placetype":"venue"
},
  "geometry": {"coordinates":[7.642853,52.056149],"type":"Point"}
}