{
  "type": "Feature",
  "properties": {
    "iso:country":"DE",
    "sg:address":"Distelweg 7",
    "sg:city":"K\u00f6ln",
    "sg:phone":"+49 2203/64874",
    "sg:postcode":"51147",
    "sg:province":"Nordrhein-Westfalen",
    "wof:name":"Elisabeth Euler Steuerberaterin",
    "wof:placetype":"venue"
},
  "geometry": {"coordinates":[7.088657856,50.8595046997],"type":"Point"}
}