{
  "type": "Feature",
  "properties": {
    "iso:country":"DE",
    "sg:address":"Am Hambiegel 13",
    "sg:city":"Dettenheim",
    "sg:phone":"+49 7247/93630",
    "sg:postcode":"76706",
    "sg:province":"Baden-W\u00fcrttemberg",
    "wof:name":"Wilfried Schwab Gmbh",
    "wof:placetype":"venue"
},
  "geometry": {"coordinates":[8.410192,49.15921],"type":"Point"}
}