{
  "type": "Feature",
  "properties": {
    "iso:country":"DE",
    "sg:address":"Marktstr. 16",
    "sg:city":"Sehnde",
    "sg:phone":"+49 5138/1579",
    "sg:postcode":"31319",
    "sg:province":"Niedersachsen",
    "wof:name":"Heinrich Busch",
    "wof:placetype":"venue"
},
  "geometry": {"coordinates":[9.945782,52.296616],"type":"Point"}
}