{
  "type": "Feature",
  "properties": {
    "iso:country":"DE",
    "sg:address":"Frankfurter Str. 22",
    "sg:city":"Halver",
    "sg:phone":"+49 2353/10844",
    "sg:postcode":"58553",
    "sg:province":"Nordrhein-Westfalen",
    "wof:name":"Eiscafe Riviera",
    "wof:placetype":"venue"
},
  "geometry": {"coordinates":[7.500456,51.186432],"type":"Point"}
}