{
  "type": "Feature",
  "properties": {
    "iso:country":"DE",
    "sg:address":"Rosenstr. 6",
    "sg:city":"Kirchheim",
    "sg:phone":"+49 9336/633",
    "sg:postcode":"97268",
    "sg:province":"Bayern",
    "wof:name":"Ludwig Lesch",
    "wof:placetype":"venue"
},
  "geometry": {"coordinates":[9.877472,49.639599],"type":"Point"}
}