{
  "type": "Feature",
  "properties": {
    "iso:country":"DE",
    "sg:address":"Am Korsorsberg 76",
    "sg:city":"Wardenburg",
    "sg:postcode":"26203",
    "sg:province":"Niedersachsen",
    "wof:name":"Awotex Reisen Werbung Und Vertriebs Gmbh",
    "wof:placetype":"venue"
},
  "geometry": {"coordinates":[8.1328296661,53.0849990845],"type":"Point"}
}