{
  "type": "Feature",
  "properties": {
    "iso:country":"DE",
    "sg:address":"Trutenbachstr. 3",
    "sg:city":"Kre\u00dfberg",
    "sg:phone":"+49 7957/583",
    "sg:postcode":"74594",
    "sg:province":"Baden-W\u00fcrttemberg",
    "wof:name":"O. Stegmeier",
    "wof:placetype":"venue"
},
  "geometry": {"coordinates":[10.1702852249,49.15076828],"type":"Point"}
}