{
  "type": "Feature",
  "properties": {
    "iso:country":"DE",
    "sg:address":"Grindelalle 148",
    "sg:city":"Hamburg",
    "sg:phone":"+49 40",
    "sg:postcode":"20146",
    "sg:province":"Hamburg",
    "wof:name":"Cafe Backwahn",
    "wof:placetype":"venue"
},
  "geometry": {"coordinates":[9.979516983,53.5695953369],"type":"Point"}
}