{
  "type": "Feature",
  "properties": {
    "iso:country":"DE",
    "sg:address":"Am Waltenberg 4",
    "sg:city":"Winterberg",
    "sg:phone":"+49 2981/81086",
    "sg:postcode":"59955",
    "sg:province":"Nordrhein-Westfalen",
    "wof:name":"H. Bonita Gmbh & Co. Kg",
    "wof:placetype":"venue"
},
  "geometry": {"coordinates":[8.532369,51.194012],"type":"Point"}
}