{
  "type": "Feature",
  "properties": {
    "iso:country":"DE",
    "sg:address":"August-Bebel-Str. 11",
    "sg:city":"Geyer",
    "sg:phone":"+49 37346/1515",
    "sg:postcode":"09468",
    "sg:province":"Sachsen",
    "wof:name":"O. Porges",
    "wof:placetype":"venue"
},
  "geometry": {"coordinates":[12.9219303131,50.6248626709],"type":"Point"}
}