{
  "type": "Feature",
  "properties": {
    "iso:country":"DE",
    "sg:address":"Alter Uentroper Weg 187",
    "sg:city":"Hamm",
    "sg:phone":"+49 2381/983780",
    "sg:postcode":"59071",
    "sg:province":"Nordrhein-Westfalen",
    "wof:name":"Ksh Haustechnik Gmbh",
    "wof:placetype":"venue"
},
  "geometry": {"coordinates":[7.891579,51.690765],"type":"Point"}
}