{
  "type": "Feature",
  "properties": {
    "iso:country":"DE",
    "sg:address":"Lerchenfeldstr. 8",
    "sg:city":"M\u00fcnchen",
    "sg:postcode":"80538",
    "sg:province":"Bayern",
    "wof:name":"Munich Sport Gmbh",
    "wof:placetype":"venue"
},
  "geometry": {"coordinates":[11.5927801132,48.1456108093],"type":"Point"}
}