{
  "type": "Feature",
  "properties": {
    "iso:country":"DE",
    "sg:address":"Leisniger Str. 14 OT Abla\u00df",
    "sg:city":"Sornzig-Abla\u00df",
    "sg:phone":"+49 34362/4020",
    "sg:postcode":"04769",
    "sg:province":"Sachsen",
    "wof:name":"Frank Siegel Gmbh",
    "wof:placetype":"venue"
},
  "geometry": {"coordinates":[13.04945,51.235909],"type":"Point"}
}