{
  "type": "Feature",
  "properties": {
    "iso:country":"DE",
    "sg:address":"M\u00fclheimer Str. 76b",
    "sg:city":"Leverkusen",
    "sg:phone":"+49 214/503232",
    "sg:postcode":"51375",
    "sg:province":"Nordrhein-Westfalen",
    "wof:name":"I. Parusel",
    "wof:placetype":"venue"
},
  "geometry": {"coordinates":[7.0447459221,51.0247306824],"type":"Point"}
}