{
  "type": "Feature",
  "properties": {
    "iso:country":"DE",
    "sg:address":"Pascalstr. 15",
    "sg:city":"Aachen",
    "sg:phone":"+49 2408/95450",
    "sg:postcode":"52076",
    "sg:province":"Nordrhein-Westfalen",
    "wof:name":"Aixtra Soft Gmbh",
    "wof:placetype":"venue"
},
  "geometry": {"coordinates":[6.145043,50.714314],"type":"Point"}
}