{
  "type": "Feature",
  "properties": {
    "iso:country":"DE",
    "sg:address":"Ottenhof 23",
    "sg:city":"Plech",
    "sg:phone":"+49 9244/1682",
    "sg:postcode":"91287",
    "sg:province":"Bayern",
    "wof:name":"Triska",
    "wof:placetype":"venue"
},
  "geometry": {"coordinates":[11.4616527557,49.6683197021],"type":"Point"}
}