{
  "type": "Feature",
  "properties": {
    "iso:country":"DE",
    "sg:address":"H\u00f6lderlinstr. 8",
    "sg:city":"Gladbeck",
    "sg:phone":"+49 2043/22199",
    "sg:postcode":"45964",
    "sg:province":"Nordrhein-Westfalen",
    "wof:name":"G. Oberbossel",
    "wof:placetype":"venue"
},
  "geometry": {"coordinates":[6.9890918732,51.5782318115],"type":"Point"}
}