{
  "type": "Feature",
  "properties": {
    "iso:country":"DE",
    "sg:address":"Hohe Str. 15",
    "sg:city":"Wildenhain",
    "sg:phone":"+49 3522/38494",
    "sg:postcode":"01561",
    "sg:province":"Sachsen",
    "wof:name":"Isolux Schurig",
    "wof:placetype":"venue"
},
  "geometry": {"coordinates":[13.4787569046,51.3065643311],"type":"Point"}
}