{
  "type": "Feature",
  "properties": {
    "iso:country":"DE",
    "sg:address":"In der Haarschnur 33",
    "sg:city":"Gr\u00fcnstadt",
    "sg:phone":"+49 6359/3033",
    "sg:postcode":"67269",
    "sg:province":"Rheinland-Pfalz",
    "wof:name":"Heinz Kr\u00fcchten",
    "wof:placetype":"venue"
},
  "geometry": {"coordinates":[8.170393,49.563492],"type":"Point"}
}