{
  "type": "Feature",
  "properties": {
    "iso:country":"DE",
    "sg:address":"Wallersstr. 77",
    "sg:city":"Bad Breisig",
    "sg:phone":"+49 2633/97184",
    "sg:postcode":"53498",
    "sg:province":"Rheinland-Pfalz",
    "wof:name":"Hermann Winkelmann",
    "wof:placetype":"venue"
},
  "geometry": {"coordinates":[7.271882,50.496861],"type":"Point"}
}