{
  "type": "Feature",
  "properties": {
    "iso:country":"DE",
    "sg:address":"Dom-Pedro-Str 22",
    "sg:city":"M\u00fcnchen",
    "sg:phone":"+49 89/30636510",
    "sg:postcode":"80637",
    "sg:province":"Bayern",
    "wof:name":"Profleet Gmbh",
    "wof:placetype":"venue"
},
  "geometry": {"coordinates":[11.542672,48.15976],"type":"Point"}
}