{
  "type": "Feature",
  "properties": {
    "iso:country":"DE",
    "sg:address":"Harmate 16",
    "sg:city":"Ahaus",
    "sg:phone":"+49 2561/86161",
    "sg:postcode":"48683",
    "sg:province":"Nordrhein-Westfalen",
    "wof:name":"Hermann St\u00f6teler Gmbh",
    "wof:placetype":"venue"
},
  "geometry": {"coordinates":[6.96229,52.06889],"type":"Point"}
}