{
  "type": "Feature",
  "properties": {
    "iso:country":"DE",
    "sg:address":"Annenstr. 180",
    "sg:city":"Witten",
    "sg:phone":"+49 2302/690505",
    "sg:postcode":"58453",
    "sg:province":"Nordrhein-Westfalen",
    "wof:name":"Pils-b\u00f6rse",
    "wof:placetype":"venue"
},
  "geometry": {"coordinates":[7.3769278526,51.4475440979],"type":"Point"}
}