{
  "type": "Feature",
  "properties": {
    "iso:country":"DE",
    "sg:address":"Ickerottweg 7-11",
    "sg:city":"Recklinghausen",
    "sg:phone":"+49 2361/80010",
    "sg:postcode":"45665",
    "sg:province":"Nordrhein-Westfalen",
    "wof:name":"Maschinenbau Kolk Gmbh",
    "wof:placetype":"venue"
},
  "geometry": {"coordinates":[7.272436142,51.6103897095],"type":"Point"}
}