{
  "type": "Feature",
  "properties": {
    "iso:country":"DE",
    "sg:address":"Sankt-Gallus-Str. 4",
    "sg:city":"Brigachtal",
    "sg:phone":"+49 4977/2121113",
    "sg:postcode":"78086",
    "sg:province":"Baden-W\u00fcrttemberg",
    "wof:name":"Sparkasse Villingen-schwenningen",
    "wof:placetype":"venue"
},
  "geometry": {"coordinates":[8.469364,48.013309],"type":"Point"}
}