{
  "type": "Feature",
  "properties": {
    "iso:country":"DE",
    "sg:address":"Viehbachweg 11",
    "sg:city":"Dannstadt-Schauernheim",
    "sg:phone":"+49 6231/915056",
    "sg:postcode":"67125",
    "sg:province":"Rheinland-Pfalz",
    "wof:name":"W. Manz",
    "wof:placetype":"venue"
},
  "geometry": {"coordinates":[8.32046,49.427273],"type":"Point"}
}