{
  "type": "Feature",
  "properties": {
    "iso:country":"DE",
    "sg:address":"Hebelstr. 19",
    "sg:city":"L\u00f6rrach",
    "sg:phone":"+49 7621/51463",
    "sg:postcode":"79541",
    "sg:province":"Baden-W\u00fcrttemberg",
    "wof:name":"Rolf Urban Architekt",
    "wof:placetype":"venue"
},
  "geometry": {"coordinates":[7.700154,47.645496],"type":"Point"}
}