{
  "type": "Feature",
  "properties": {
    "iso:country":"DE",
    "sg:address":"Seidenweberweg 1",
    "sg:city":"Metelen",
    "sg:phone":"+49 2556/985303",
    "sg:postcode":"48629",
    "sg:province":"Nordrhein-Westfalen",
    "wof:name":"Bigbagger Im Kreis Steinfurt",
    "wof:placetype":"venue"
},
  "geometry": {"coordinates":[7.209676,52.145031],"type":"Point"}
}