{
  "type": "Feature",
  "properties": {
    "iso:country":"DE",
    "sg:address":"Hedelfinger Str. 18/1",
    "sg:city":"Ostfildern",
    "sg:phone":"+49 711/412100",
    "sg:postcode":"73760",
    "sg:province":"Baden-W\u00fcrttemberg",
    "wof:name":"Rosen-apotheke",
    "wof:placetype":"venue"
},
  "geometry": {"coordinates":[9.25382,48.736629],"type":"Point"}
}