{
  "type": "Feature",
  "properties": {
    "iso:country":"DE",
    "sg:city":"Amerdingen",
    "sg:phone":"+49 9089/346",
    "sg:postcode":"86735",
    "sg:province":"Bayern",
    "wof:name":"Cafe Gut",
    "wof:placetype":"venue"
},
  "geometry": {"coordinates":[10.485638,48.725521],"type":"Point"}
}