{
  "type": "Feature",
  "properties": {
    "iso:country":"DE",
    "sg:address":"Celler Str. 15",
    "sg:city":"Bergen",
    "sg:phone":"+49 5051/3890",
    "sg:postcode":"29303",
    "sg:province":"Niedersachsen",
    "wof:name":"Zimmermann",
    "wof:placetype":"venue"
},
  "geometry": {"coordinates":[9.9656906128,52.8075447083],"type":"Point"}
}