{
  "type": "Feature",
  "properties": {
    "iso:country":"DE",
    "sg:address":"Zum Panrepel 7-9",
    "sg:city":"Bremen",
    "sg:phone":"+49 421/486860",
    "sg:postcode":"28307",
    "sg:province":"Bremen",
    "wof:name":"Joachim Wiegmann & Co.",
    "wof:placetype":"venue"
},
  "geometry": {"coordinates":[8.9624156952,53.0431365967],"type":"Point"}
}