{
  "type": "Feature",
  "properties": {
    "iso:country":"DE",
    "sg:address":"Siloahweg 1",
    "sg:city":"Hamburg",
    "sg:phone":"+49 40/5583814",
    "sg:postcode":"22457",
    "sg:province":"Hamburg",
    "wof:name":"Koch Apv Vertriebs Gmbh",
    "wof:placetype":"venue"
},
  "geometry": {"coordinates":[9.901124,53.635071],"type":"Point"}
}