{
  "type": "Feature",
  "properties": {
    "iso:country":"DE",
    "sg:address":"Erntestr. 6",
    "sg:city":"Zwickau",
    "sg:phone":"+49 375/522296",
    "sg:postcode":"08060",
    "sg:province":"Sachsen",
    "wof:name":"Heinz Wolf",
    "wof:placetype":"venue"
},
  "geometry": {"coordinates":[12.45566,50.717739],"type":"Point"}
}