{
  "type": "Feature",
  "properties": {
    "iso:country":"DE",
    "sg:address":"Kelkheimer Str. 56a",
    "sg:city":"Kelkheim",
    "sg:phone":"+49 6195/62643",
    "sg:postcode":"65779",
    "sg:province":"Hessen",
    "wof:name":"Pension Ursula Zimmermann",
    "wof:placetype":"venue"
},
  "geometry": {"coordinates":[8.428902626,50.1460494995],"type":"Point"}
}