{
  "type": "Feature",
  "properties": {
    "iso:country":"DE",
    "sg:address":"Gerichtsweg 12",
    "sg:city":"D\u00fcren",
    "sg:phone":"+49 2421/55611",
    "sg:postcode":"52355",
    "sg:province":"Nordrhein-Westfalen",
    "wof:name":"F. J. Porschen",
    "wof:placetype":"venue"
},
  "geometry": {"coordinates":[6.4723930359,50.7667579651],"type":"Point"}
}