{
  "type": "Feature",
  "properties": {
    "iso:country":"DE",
    "sg:address":"Geschwister-Scholl-Str 26",
    "sg:city":"Hildburghausen",
    "sg:phone":"+49 3685/79060",
    "sg:postcode":"98646",
    "sg:province":"Th\u00fcringen",
    "wof:name":"Offizin Hildburghausen Gmbh",
    "wof:placetype":"venue"
},
  "geometry": {"coordinates":[10.7275943756,50.4275474548],"type":"Point"}
}