{
  "type": "Feature",
  "properties": {
    "iso:country":"DE",
    "sg:address":"Schlo\u00dfparkstr. 95",
    "sg:city":"Aachen",
    "sg:phone":"+49 241/14450",
    "sg:postcode":"52072",
    "sg:province":"Nordrhein-Westfalen",
    "wof:name":"Dr. Hans-peter Uffmann Ingenieur",
    "wof:placetype":"venue"
},
  "geometry": {"coordinates":[6.0724349022,50.8007202148],"type":"Point"}
}