{
  "type": "Feature",
  "properties": {
    "iso:country":"DE",
    "sg:address":"Marktplatz 8",
    "sg:city":"Geisenhausen",
    "sg:phone":"+49 8743/96090",
    "sg:postcode":"84144",
    "sg:province":"Bayern",
    "wof:name":"Peter H\u00e4useler Und H. Bleicher Steuerberatungs Gmbh",
    "wof:placetype":"venue"
},
  "geometry": {"coordinates":[12.2573575974,48.4733123779],"type":"Point"}
}