{
  "type": "Feature",
  "properties": {
    "iso:country":"DE",
    "sg:address":"Marktstr. 17",
    "sg:city":"Hamminkeln",
    "sg:phone":"+49 2852/4722",
    "sg:postcode":"46499",
    "sg:province":"Nordrhein-Westfalen",
    "wof:name":"B\u00fcrgerhaus",
    "wof:placetype":"venue"
},
  "geometry": {"coordinates":[6.5900321007,51.7308158875],"type":"Point"}
}