{
  "type": "Feature",
  "properties": {
    "iso:country":"DE",
    "sg:address":"Schafbr\u00fcckenweg",
    "sg:city":"Hochdorf-Assenheim",
    "sg:phone":"+49 6231/5153",
    "sg:postcode":"67126",
    "sg:province":"Rheinland-Pfalz",
    "wof:name":"Herrmanshof F. Lenz",
    "wof:placetype":"venue"
},
  "geometry": {"coordinates":[8.2672939301,49.4147949219],"type":"Point"}
}