{
  "type": "Feature",
  "properties": {
    "iso:country":"DE",
    "sg:address":"Moltkestr. 77",
    "sg:city":"Kiel",
    "sg:postcode":"24105",
    "sg:province":"Schleswig-Holstein",
    "wof:name":"Conaris Research Institute Gmbh",
    "wof:placetype":"venue"
},
  "geometry": {"coordinates":[10.145945549,54.3424797058],"type":"Point"}
}