{
  "type": "Feature",
  "properties": {
    "iso:country":"DE",
    "sg:address":"Memminger Str. 82",
    "sg:city":"Leutkirch",
    "sg:phone":"+49 7561/71210",
    "sg:postcode":"88299",
    "sg:province":"Baden-W\u00fcrttemberg",
    "wof:name":"Pizzeria Roma",
    "wof:placetype":"venue"
},
  "geometry": {"coordinates":[10.0170192719,47.8369750977],"type":"Point"}
}