{
  "type": "Feature",
  "properties": {
    "iso:country":"DE",
    "sg:address":"Heidelberger Str. 120",
    "sg:city":"Mosbach",
    "sg:phone":"+49 6261/63248",
    "sg:postcode":"74821",
    "sg:province":"Baden-W\u00fcrttemberg",
    "wof:name":"Kurt Gro\u00dfkopf",
    "wof:placetype":"venue"
},
  "geometry": {"coordinates":[9.1050786972,49.3502960205],"type":"Point"}
}