{
  "type": "Feature",
  "properties": {
    "iso:country":"DE",
    "sg:address":"Bahnhofstr. 36",
    "sg:city":"Owschlag",
    "sg:phone":"+49 4336/1505",
    "sg:postcode":"24811",
    "sg:province":"Schleswig-Holstein",
    "wof:name":"Krings",
    "wof:placetype":"venue"
},
  "geometry": {"coordinates":[9.596581,54.392563],"type":"Point"}
}