{
  "type": "Feature",
  "properties": {
    "iso:country":"DE",
    "sg:address":"Mittelstr. 112",
    "sg:city":"Sankt Augustin",
    "sg:phone":"+49 2241/314564",
    "sg:postcode":"53757",
    "sg:province":"Nordrhein-Westfalen",
    "wof:name":"Restaurant Kaisergrill",
    "wof:placetype":"venue"
},
  "geometry": {"coordinates":[7.1607561111,50.7836952209],"type":"Point"}
}