{
  "type": "Feature",
  "properties": {
    "iso:country":"DE",
    "sg:address":"Sternstr. 38",
    "sg:city":"Neuss",
    "sg:phone":"+49 2131/276097",
    "sg:postcode":"41460",
    "sg:province":"Nordrhein-Westfalen",
    "wof:name":"Kr\u00fcll-hotel",
    "wof:placetype":"venue"
},
  "geometry": {"coordinates":[6.6817989349,51.1973838806],"type":"Point"}
}