{
  "type": "Feature",
  "properties": {
    "iso:country":"DE",
    "sg:address":"Br\u00fcckstr. 24",
    "sg:city":"Dortmund",
    "sg:phone":"+49 231/523442",
    "sg:postcode":"44135",
    "sg:province":"Nordrhein-Westfalen",
    "wof:name":"Runners Point",
    "wof:placetype":"venue"
},
  "geometry": {"coordinates":[7.466302,51.515736],"type":"Point"}
}