{
  "type": "Feature",
  "properties": {
    "iso:country":"DE",
    "sg:address":"Merziener Str. 38",
    "sg:city":"K\u00f6then",
    "sg:phone":"+49 3496/310018",
    "sg:postcode":"06366",
    "sg:province":"Sachsen-Anhalt",
    "wof:name":"L & B Bau-gmbh",
    "wof:placetype":"venue"
},
  "geometry": {"coordinates":[12.004801,51.753933],"type":"Point"}
}