{
  "type": "Feature",
  "properties": {
    "iso:country":"DE",
    "sg:address":"Issumer Str. 51",
    "sg:city":"Geldern",
    "sg:phone":"+49 2832/1426",
    "sg:postcode":"47608",
    "sg:province":"Nordrhein-Westfalen",
    "wof:name":"Dix Reiseb\u00fcro",
    "wof:placetype":"venue"
},
  "geometry": {"coordinates":[6.3250141144,51.5187530518],"type":"Point"}
}