{
  "type": "Feature",
  "properties": {
    "iso:country":"DE",
    "sg:address":"R\u00f6ttgerhof",
    "sg:city":"Mechernich",
    "sg:phone":"+49 2256/7183",
    "sg:postcode":"53894",
    "sg:province":"Nordrhein-Westfalen",
    "wof:name":"A. Hodenberg Rechtsanwalt",
    "wof:placetype":"venue"
},
  "geometry": {"coordinates":[6.7132821083,50.5812683105],"type":"Point"}
}