{
  "type": "Feature",
  "properties": {
    "iso:country":"DE",
    "sg:address":"Sedanstr. 21",
    "sg:city":"Peine",
    "sg:phone":"+49 5171/10814",
    "sg:postcode":"31224",
    "sg:province":"Niedersachsen",
    "wof:name":"Nina Schubert Heilpraktikerin",
    "wof:placetype":"venue"
},
  "geometry": {"coordinates":[10.2309865952,52.3258628845],"type":"Point"}
}