{
  "type": "Feature",
  "properties": {
    "iso:country":"DE",
    "sg:address":"Rochusstr. 21",
    "sg:city":"Aachen",
    "sg:phone":"+49 241/22727",
    "sg:postcode":"52062",
    "sg:province":"Nordrhein-Westfalen",
    "wof:name":"Hans-joachim Jungheim",
    "wof:placetype":"venue"
},
  "geometry": {"coordinates":[6.0866241455,50.7800140381],"type":"Point"}
}