{
  "type": "Feature",
  "properties": {
    "iso:country":"DE",
    "sg:address":"Reinhardsbrunner Str. 33",
    "sg:city":"Gotha",
    "sg:phone":"+49 3621/705130",
    "sg:postcode":"99867",
    "sg:province":"Th\u00fcringen",
    "wof:name":"H. Walter Immobilienmakler",
    "wof:placetype":"venue"
},
  "geometry": {"coordinates":[10.6935195923,50.9403915405],"type":"Point"}
}