{
  "type": "Feature",
  "properties": {
    "iso:country":"DE",
    "sg:address":"Mehringer Str. 49 B",
    "sg:city":"Burghausen",
    "sg:phone":"+49 8677/1890",
    "sg:postcode":"84489",
    "sg:province":"Bayern",
    "wof:name":"Westermeier & Oberpeilsteiner Gmbh",
    "wof:placetype":"venue"
},
  "geometry": {"coordinates":[12.8253364563,48.1712875366],"type":"Point"}
}