{
  "type": "Feature",
  "properties": {
    "iso:country":"DE",
    "sg:address":"Mosbacher Str. 65",
    "sg:city":"Mannheim",
    "sg:phone":"+49 621/7140901",
    "sg:postcode":"68259",
    "sg:province":"Baden-W\u00fcrttemberg",
    "wof:name":"Bernhard Rohr",
    "wof:placetype":"venue"
},
  "geometry": {"coordinates":[8.545063,49.497341],"type":"Point"}
}