{
  "type": "Feature",
  "properties": {
    "iso:country":"DE",
    "sg:address":"Sonnenscheinstr. 15",
    "sg:city":"Schorndorf",
    "sg:phone":"+49 7181/410913",
    "sg:postcode":"73614",
    "sg:province":"Baden-W\u00fcrttemberg",
    "wof:name":"Marsh Gmbh",
    "wof:placetype":"venue"
},
  "geometry": {"coordinates":[9.5344562531,48.80286026],"type":"Point"}
}