{
  "type": "Feature",
  "properties": {
    "iso:country":"DE",
    "sg:address":"Claasbruch 36",
    "sg:city":"Leverkusen",
    "sg:phone":"+49 2171/80622",
    "sg:postcode":"51381",
    "sg:province":"Nordrhein-Westfalen",
    "wof:name":"Helmut Kolk Innenarchitekt",
    "wof:placetype":"venue"
},
  "geometry": {"coordinates":[7.035774,51.069584],"type":"Point"}
}