{
  "type": "Feature",
  "properties": {
    "iso:country":"DE",
    "sg:address":"Svendborger Str. 24",
    "sg:city":"Kiel",
    "sg:phone":"+49 431/521735",
    "sg:postcode":"24109",
    "sg:province":"Schleswig-Holstein",
    "wof:name":"Georg Felger Bauingenieur",
    "wof:placetype":"venue"
},
  "geometry": {"coordinates":[10.0531387329,54.3128929138],"type":"Point"}
}