{
  "type": "Feature",
  "properties": {
    "iso:country":"DE",
    "sg:address":"Aegidientorplatz",
    "sg:city":"Hannover",
    "sg:phone":"+49 511/325520",
    "sg:postcode":"30159",
    "sg:province":"Niedersachsen",
    "wof:name":"Polster-richter Gmbh",
    "wof:placetype":"venue"
},
  "geometry": {"coordinates":[9.7438001633,52.3693580627],"type":"Point"}
}