{
  "type": "Feature",
  "properties": {
    "iso:country":"DE",
    "sg:address":"Kirchweg 1",
    "sg:city":"Schauenstein",
    "sg:phone":"+49 9252/393",
    "sg:postcode":"95197",
    "sg:province":"Bayern",
    "wof:name":"Ev. Luth. Pfarramt",
    "wof:placetype":"venue"
},
  "geometry": {"coordinates":[11.7416400909,50.2787818909],"type":"Point"}
}