{
  "type": "Feature",
  "properties": {
    "iso:country":"DE",
    "sg:address":"Kreuzholzstr. 8",
    "sg:city":"Ludwigshafen",
    "sg:postcode":"67069",
    "sg:province":"Rheinland-Pfalz",
    "wof:name":"Schwarz Gesch\u00e4ftsf\u00fchrungs- Gesellschaft Mbh",
    "wof:placetype":"venue"
},
  "geometry": {"coordinates":[8.40664,49.541065],"type":"Point"}
}