{
  "type": "Feature",
  "properties": {
    "iso:country":"DE",
    "sg:address":"M\u00fchlenstr. 35",
    "sg:city":"Alf",
    "sg:phone":"+49 6542/1435",
    "sg:postcode":"56859",
    "sg:province":"Rheinland-Pfalz",
    "wof:name":"Kurt Jackel Weinanbau",
    "wof:placetype":"venue"
},
  "geometry": {"coordinates":[7.1213531494,50.0545768738],"type":"Point"}
}