{
  "type": "Feature",
  "properties": {
    "iso:country":"DE",
    "sg:address":"Schlachthofstr. 21",
    "sg:city":"M\u00fcnchberg",
    "sg:phone":"+49 9251/1343",
    "sg:postcode":"95213",
    "sg:province":"Bayern",
    "wof:name":"Georg Popp",
    "wof:placetype":"venue"
},
  "geometry": {"coordinates":[11.797679,50.190113],"type":"Point"}
}