{
  "type": "Feature",
  "properties": {
    "iso:country":"DE",
    "sg:address":"Felderhof 7",
    "sg:city":"Ratingen",
    "sg:postcode":"40880",
    "sg:province":"Nordrhein-Westfalen",
    "wof:name":"Mkl Immobilien Gmbh",
    "wof:placetype":"venue"
},
  "geometry": {"coordinates":[6.829436779,51.2826728821],"type":"Point"}
}