{
  "type": "Feature",
  "properties": {
    "iso:country":"DE",
    "sg:address":"Siemersplatz 3",
    "sg:city":"Hamburg",
    "sg:phone":"+49 40/56069083",
    "sg:postcode":"22529",
    "sg:province":"Hamburg",
    "wof:name":"X-pack-t Handelsges. Mbh & Co. Kg",
    "wof:placetype":"venue"
},
  "geometry": {"coordinates":[9.963939,53.599449],"type":"Point"}
}