{
  "type": "Feature",
  "properties": {
    "iso:country":"DE",
    "sg:address":"Breisgauer Str. 31",
    "sg:city":"Freiburg",
    "sg:phone":"+49 761/891516",
    "sg:postcode":"79110",
    "sg:province":"Baden-W\u00fcrttemberg",
    "wof:name":"Ilona K\u00e4ufer Masseur",
    "wof:placetype":"venue"
},
  "geometry": {"coordinates":[7.802833,48.014893],"type":"Point"}
}