{
  "type": "Feature",
  "properties": {
    "iso:country":"DE",
    "sg:address":"Annaberger Str. 227b",
    "sg:city":"Crottendorf",
    "sg:phone":"+49 37344/8689",
    "sg:postcode":"09474",
    "sg:province":"Sachsen",
    "wof:name":"Wolfgang Schulz",
    "wof:placetype":"venue"
},
  "geometry": {"coordinates":[12.9424781799,50.5136413574],"type":"Point"}
}