{
  "type": "Feature",
  "properties": {
    "iso:country":"DE",
    "sg:address":"Friedrichstr. 1",
    "sg:city":"Schwetzingen",
    "sg:phone":"+49 6202/270413",
    "sg:postcode":"68723",
    "sg:province":"Baden-W\u00fcrttemberg",
    "wof:name":"Lokmann G\u00fcl Arslans Kebap",
    "wof:placetype":"venue"
},
  "geometry": {"coordinates":[8.5747871399,49.3842391968],"type":"Point"}
}