{
  "type": "Feature",
  "properties": {
    "iso:country":"DE",
    "sg:address":"Goethestr. 10",
    "sg:city":"Hargesheim",
    "sg:phone":"+49 671/36139",
    "sg:postcode":"55595",
    "sg:province":"Rheinland-Pfalz",
    "wof:name":"P. L\u00e4ngin",
    "wof:placetype":"venue"
},
  "geometry": {"coordinates":[7.8243370056,49.8663711548],"type":"Point"}
}