{
  "type": "Feature",
  "properties": {
    "iso:country":"DE",
    "sg:address":"Alsbachstra\u00dfe 45",
    "sg:city":"Marpingen",
    "sg:phone":"+49 6853/922140",
    "sg:postcode":"66646",
    "sg:province":"Saarland",
    "wof:name":"Ebs Edv-benutzer-service",
    "wof:placetype":"venue"
},
  "geometry": {"coordinates":[7.057493,49.456059],"type":"Point"}
}