{
  "type": "Feature",
  "properties": {
    "iso:country":"DE",
    "sg:address":"Mittelstr. 20",
    "sg:city":"Doberlug-Kirchhain",
    "sg:postcode":"03253",
    "sg:province":"Brandenburg",
    "wof:name":"Dodge City Country Club Doberlug E. V.",
    "wof:placetype":"venue"
},
  "geometry": {"coordinates":[13.551027298,51.6127967834],"type":"Point"}
}