{
  "type": "Feature",
  "properties": {
    "iso:country":"DE",
    "sg:address":"Ortsstr. 13",
    "sg:city":"Oberasbach",
    "sg:phone":"+49 911/697583",
    "sg:postcode":"90522",
    "sg:province":"Bayern",
    "wof:name":"Adolf Ranzinger",
    "wof:placetype":"venue"
},
  "geometry": {"coordinates":[10.977521,49.425644],"type":"Point"}
}