{
  "type": "Feature",
  "properties": {
    "iso:country":"DE",
    "sg:address":"Peterstr. 10a",
    "sg:city":"Westerstede",
    "sg:phone":"+49 4488/2686",
    "sg:postcode":"26655",
    "sg:province":"Niedersachsen",
    "wof:name":"Apotheke Westerstede",
    "wof:placetype":"venue"
},
  "geometry": {"coordinates":[7.927764,53.25629],"type":"Point"}
}