{
  "type": "Feature",
  "properties": {
    "iso:country":"DE",
    "sg:address":"Rethelstr. 32",
    "sg:city":"D\u00fcsseldorf",
    "sg:phone":"+49 211/661344",
    "sg:postcode":"40237",
    "sg:province":"Nordrhein-Westfalen",
    "wof:name":"Barbara Lipke",
    "wof:placetype":"venue"
},
  "geometry": {"coordinates":[6.7983517647,51.2318191528],"type":"Point"}
}