{
  "type": "Feature",
  "properties": {
    "iso:country":"DE",
    "sg:address":"Hauptstr. 37",
    "sg:city":"Donzdorf",
    "sg:phone":"+49 7162/929740",
    "sg:postcode":"73072",
    "sg:province":"Baden-W\u00fcrttemberg",
    "wof:name":"Liepelt Und Partner",
    "wof:placetype":"venue"
},
  "geometry": {"coordinates":[9.8064622879,48.6865234375],"type":"Point"}
}