{
  "type": "Feature",
  "properties": {
    "iso:country":"DE",
    "sg:address":"Huldsessen",
    "sg:city":"Unterdietfurt",
    "sg:phone":"+49 8721/2283",
    "sg:postcode":"84339",
    "sg:province":"Bayern",
    "wof:name":"E. Bauer",
    "wof:placetype":"venue"
},
  "geometry": {"coordinates":[12.69535,48.395889],"type":"Point"}
}