{
  "type": "Feature",
  "properties": {
    "iso:country":"DE",
    "sg:address":"Alemannenstr. 21",
    "sg:city":"Denkendorf",
    "sg:phone":"+49 8466/94100",
    "sg:postcode":"85095",
    "sg:province":"Bayern",
    "wof:name":"Ias Maschinenbau Gmbh",
    "wof:placetype":"venue"
},
  "geometry": {"coordinates":[11.464159,48.936077],"type":"Point"}
}