{
  "type": "Feature",
  "properties": {
    "iso:country":"DE",
    "sg:address":"L\u00f6hstr. 29",
    "sg:city":"Viersen",
    "sg:phone":"+49 4921/6223864",
    "sg:postcode":"41747",
    "sg:province":"Nordrhein-Westfalen",
    "wof:name":"Master-reithosen",
    "wof:placetype":"venue"
},
  "geometry": {"coordinates":[6.3719201088,51.2524147034],"type":"Point"}
}