{
  "type": "Feature",
  "properties": {
    "iso:country":"DE",
    "sg:address":"Silcherstr. 7",
    "sg:city":"Dietenheim",
    "sg:postcode":"89165",
    "sg:province":"Baden-W\u00fcrttemberg",
    "wof:name":"Merchel Warentransport- Systeme Gmbh",
    "wof:placetype":"venue"
},
  "geometry": {"coordinates":[10.055905,48.240444],"type":"Point"}
}