{
  "type": "Feature",
  "properties": {
    "iso:country":"DE",
    "sg:address":"Dieselstr. 19-21",
    "sg:city":"Gerlingen",
    "sg:phone":"+49 7156/22083",
    "sg:postcode":"70839",
    "sg:province":"Baden-W\u00fcrttemberg",
    "wof:name":"Weidle Gmbh",
    "wof:placetype":"venue"
},
  "geometry": {"coordinates":[9.0733308792,48.8052062988],"type":"Point"}
}