{
  "type": "Feature",
  "properties": {
    "iso:country":"DE",
    "sg:address":"Bahnhofstr. 31",
    "sg:city":"Michelstadt",
    "sg:phone":"+49 6061/701280",
    "sg:postcode":"64720",
    "sg:province":"Hessen",
    "wof:name":"Vobis Immobilien Gmbh",
    "wof:placetype":"venue"
},
  "geometry": {"coordinates":[9.0026082993,49.6817855835],"type":"Point"}
}