{
  "type": "Feature",
  "properties": {
    "iso:country":"DE",
    "sg:address":"Hauptstr. 5",
    "sg:city":"Neubiberg",
    "sg:phone":"+49 89/6010160",
    "sg:postcode":"85579",
    "sg:province":"Bayern",
    "wof:name":"W. Baumann",
    "wof:placetype":"venue"
},
  "geometry": {"coordinates":[11.660902,48.076641],"type":"Point"}
}