{
  "type": "Feature",
  "properties": {
    "iso:country":"DE",
    "sg:address":"Konradstr. 7",
    "sg:city":"N\u00fcrnberg",
    "sg:phone":"+49 911/3266290",
    "sg:postcode":"90429",
    "sg:province":"Bayern",
    "wof:name":"Christof Scheuring",
    "wof:placetype":"venue"
},
  "geometry": {"coordinates":[11.020022,49.461182],"type":"Point"}
}