{
  "type": "Feature",
  "properties": {
    "iso:country":"DE",
    "sg:address":"Schanzwiese 7",
    "sg:city":"Landsberg",
    "sg:phone":"+49 8191/21387",
    "sg:postcode":"86899",
    "sg:province":"Bayern",
    "wof:name":"Manfred Leimk\u00fchler Rechtsanwalt",
    "wof:placetype":"venue"
},
  "geometry": {"coordinates":[10.8793010712,48.0455703735],"type":"Point"}
}