{
  "type": "Feature",
  "properties": {
    "iso:country":"DE",
    "sg:address":"Kurler Str. 149",
    "sg:city":"Dortmund",
    "sg:phone":"+49 231/281669",
    "sg:postcode":"44319",
    "sg:province":"Nordrhein-Westfalen",
    "wof:name":"Haus Buchbinder",
    "wof:placetype":"venue"
},
  "geometry": {"coordinates":[7.5797262192,51.5606231689],"type":"Point"}
}