{
  "type": "Feature",
  "properties": {
    "iso:country":"DE",
    "sg:address":"Dorfstr. 54",
    "sg:city":"Rathendorf",
    "sg:phone":"+49 34346/61432",
    "sg:postcode":"04657",
    "sg:province":"Sachsen",
    "wof:name":"Stuck-schmidt Gmbh",
    "wof:placetype":"venue"
},
  "geometry": {"coordinates":[12.686847,51.014797],"type":"Point"}
}