{
  "type": "Feature",
  "properties": {
    "iso:country":"DE",
    "sg:address":"Birkigtweg 5",
    "sg:city":"Naila",
    "sg:phone":"+49 9282/5770",
    "sg:postcode":"95119",
    "sg:province":"Bayern",
    "wof:name":"Ulis Kosmetikstudio",
    "wof:placetype":"venue"
},
  "geometry": {"coordinates":[11.706155,50.328735],"type":"Point"}
}