{
  "type": "Feature",
  "properties": {
    "iso:country":"DE",
    "sg:address":"Uhlandstr. 24",
    "sg:city":"Geislingen",
    "sg:phone":"+49 7331/43590",
    "sg:postcode":"73312",
    "sg:province":"Baden-W\u00fcrttemberg",
    "wof:name":"Ruth Grupp",
    "wof:placetype":"venue"
},
  "geometry": {"coordinates":[9.8392925262,48.6162376404],"type":"Point"}
}