{
  "type": "Feature",
  "properties": {
    "iso:country":"DE",
    "sg:address":"K\u00f6nigstr. 2",
    "sg:city":"Halstenbek",
    "sg:phone":"+49 4101/402601",
    "sg:postcode":"25469",
    "sg:province":"Schleswig-Holstein",
    "wof:name":"Blume-im Dorf Sigrid Machacek",
    "wof:placetype":"venue"
},
  "geometry": {"coordinates":[9.842989,53.636169],"type":"Point"}
}