{
  "type": "Feature",
  "properties": {
    "iso:country":"DE",
    "sg:address":"B\u00fcrgerm.-Schmid-Str. 9",
    "sg:city":"Friedberg",
    "sg:postcode":"86316",
    "sg:province":"Bayern",
    "wof:name":"C. Martin Hebamme",
    "wof:placetype":"venue"
},
  "geometry": {"coordinates":[10.978345,48.355072],"type":"Point"}
}