{
  "type": "Feature",
  "properties": {
    "iso:country":"DE",
    "sg:address":"Raiffeisenstr. 1",
    "sg:city":"Hohenroth",
    "sg:phone":"+49 9771/7066",
    "sg:postcode":"97618",
    "sg:province":"Bayern",
    "wof:name":"Raiffeisenbank Hohenroth-niederl.eg",
    "wof:placetype":"venue"
},
  "geometry": {"coordinates":[10.175158,50.31525],"type":"Point"}
}