{
  "type": "Feature",
  "properties": {
    "iso:country":"DE",
    "sg:address":"An der Brunnsteige 21",
    "sg:city":"Volkach",
    "sg:postcode":"97332",
    "sg:province":"Bayern",
    "wof:name":"W. S. G. Warenautomaten- Handelsgesellschaft Mbh",
    "wof:placetype":"venue"
},
  "geometry": {"coordinates":[10.224623,49.870914],"type":"Point"}
}