{
  "type": "Feature",
  "properties": {
    "iso:country":"DE",
    "sg:address":"Krummstiege 4 a",
    "sg:city":"Haltern",
    "sg:phone":"+49 2364/13670",
    "sg:postcode":"45721",
    "sg:province":"Nordrhein-Westfalen",
    "wof:name":"Signal Iduna Versicherung Thomas Forell",
    "wof:placetype":"venue"
},
  "geometry": {"coordinates":[7.2870597839,51.7380256653],"type":"Point"}
}