{
  "type": "Feature",
  "properties": {
    "iso:country":"DE",
    "sg:address":"Jahnstr. 33",
    "sg:city":"Schwalbach",
    "sg:phone":"+49 6834/52591",
    "sg:postcode":"66773",
    "sg:province":"Saarland",
    "wof:name":"Turnerheim",
    "wof:placetype":"venue"
},
  "geometry": {"coordinates":[6.8091230392,49.2982177734],"type":"Point"}
}