{
  "type": "Feature",
  "properties": {
    "iso:country":"DE",
    "sg:address":"Baumredder 43",
    "sg:city":"Uetersen",
    "sg:phone":"+49 4122/52854",
    "sg:postcode":"25436",
    "sg:province":"Schleswig-Holstein",
    "wof:name":"Uwe Weidemann",
    "wof:placetype":"venue"
},
  "geometry": {"coordinates":[9.7057237625,53.6964530945],"type":"Point"}
}