{
  "type": "Feature",
  "properties": {
    "iso:country":"DE",
    "sg:address":"Riemannstr. 17",
    "sg:city":"Eutin",
    "sg:phone":"+49 4521/2125",
    "sg:postcode":"23701",
    "sg:province":"Schleswig-Holstein",
    "wof:name":"W. M\u00fcller",
    "wof:placetype":"venue"
},
  "geometry": {"coordinates":[10.6145353317,54.1407356262],"type":"Point"}
}