{
  "type": "Feature",
  "properties": {
    "iso:country":"DE",
    "sg:address":"Dorfstr. 9",
    "sg:city":"Ottendorf-Okrilla",
    "sg:phone":"+49 35205/73126",
    "sg:postcode":"01458",
    "sg:province":"Sachsen",
    "wof:name":"Angela Haake Steuerberaterin",
    "wof:placetype":"venue"
},
  "geometry": {"coordinates":[13.7909584045,51.1838989258],"type":"Point"}
}