{
  "type": "Feature",
  "properties": {
    "iso:country":"DE",
    "sg:address":"Georgenstr. 6",
    "sg:city":"Spremberg",
    "sg:phone":"+49 3563/600827",
    "sg:postcode":"03130",
    "sg:province":"Brandenburg",
    "wof:name":"Tip-discount Handels Gmbh & Co. Kg",
    "wof:placetype":"venue"
},
  "geometry": {"coordinates":[14.3780794144,51.5738983154],"type":"Point"}
}