{
  "type": "Feature",
  "properties": {
    "iso:country":"DE",
    "sg:address":"Fasanengarten 9",
    "sg:city":"Lehrte",
    "sg:phone":"+49 5175/2021",
    "sg:postcode":"31275",
    "sg:province":"Niedersachsen",
    "wof:name":"Bruno Thumann",
    "wof:placetype":"venue"
},
  "geometry": {"coordinates":[10.063633,52.390247],"type":"Point"}
}