{
  "type": "Feature",
  "properties": {
    "iso:country":"DE",
    "sg:address":"Friedhofstr. 11",
    "sg:city":"Allendorf",
    "sg:postcode":"35469",
    "sg:province":"Hessen",
    "wof:name":"Fiedler Schreinerei- Innenausbau E. K.",
    "wof:placetype":"venue"
},
  "geometry": {"coordinates":[8.826688,50.678726],"type":"Point"}
}