{
  "type": "Feature",
  "properties": {
    "iso:country":"DE",
    "sg:address":"Waldstr. 21",
    "sg:city":"Lathen",
    "sg:phone":"+49 5933/1751",
    "sg:postcode":"49762",
    "sg:province":"Niedersachsen",
    "wof:name":"Theodor H\u00f6mmen",
    "wof:placetype":"venue"
},
  "geometry": {"coordinates":[7.3415980339,52.8581733704],"type":"Point"}
}