{
  "type": "Feature",
  "properties": {
    "iso:country":"DE",
    "sg:address":"Halberst\u00e4dter Str. 122",
    "sg:city":"Magdeburg",
    "sg:phone":"+49 391/601960",
    "sg:postcode":"39112",
    "sg:province":"Sachsen-Anhalt",
    "wof:name":"Dr. Med. Sabine Ahrendt",
    "wof:placetype":"venue"
},
  "geometry": {"coordinates":[11.600897789,52.1104202271],"type":"Point"}
}