{
  "type": "Feature",
  "properties": {
    "iso:country":"DE",
    "sg:address":"Eiskellerberg 12",
    "sg:city":"Tangstedt",
    "sg:phone":"+49 4109/9420",
    "sg:postcode":"22889",
    "sg:province":"Schleswig-Holstein",
    "wof:name":"Nord Plan Gmbh",
    "wof:placetype":"venue"
},
  "geometry": {"coordinates":[10.088684082,53.7367668152],"type":"Point"}
}