{
  "type": "Feature",
  "properties": {
    "iso:country":"DE",
    "sg:address":"Winkelgasse 10",
    "sg:city":"Buchen",
    "sg:phone":"+49 6281/3673",
    "sg:postcode":"74722",
    "sg:province":"Baden-W\u00fcrttemberg",
    "wof:name":"G\u00fcnter Pflaum",
    "wof:placetype":"venue"
},
  "geometry": {"coordinates":[9.394654274,49.495803833],"type":"Point"}
}