{
  "type": "Feature",
  "properties": {
    "iso:country":"DE",
    "sg:address":"Tiefenstockheim",
    "sg:city":"Seinsheim",
    "sg:postcode":"97342",
    "sg:province":"Bayern",
    "wof:name":"Katholisches Pfarramt St. Peter Und Paul",
    "wof:placetype":"venue"
},
  "geometry": {"coordinates":[10.2043895721,49.6633415222],"type":"Point"}
}