{
  "type": "Feature",
  "properties": {
    "iso:country":"DE",
    "sg:address":"Heisenbergstr. 7",
    "sg:city":"Dachau",
    "sg:phone":"+49 8131/21216",
    "sg:postcode":"85221",
    "sg:province":"Bayern",
    "wof:name":"Gafert & Schmidt Inh. Ernst Schmidt",
    "wof:placetype":"venue"
},
  "geometry": {"coordinates":[11.4767179489,48.2679977417],"type":"Point"}
}