{
  "type": "Feature",
  "properties": {
    "iso:country":"DE",
    "sg:address":"Stegen 3 b",
    "sg:city":"Rendsburg",
    "sg:phone":"+49 4331/56234",
    "sg:postcode":"24768",
    "sg:province":"Schleswig-Holstein",
    "wof:name":"Lehnecke",
    "wof:placetype":"venue"
},
  "geometry": {"coordinates":[9.665823,54.304512],"type":"Point"}
}