{
  "type": "Feature",
  "properties": {
    "iso:country":"DE",
    "sg:address":"Zeil 65-69",
    "sg:city":"Frankfurt",
    "sg:phone":"+49 6349/929838",
    "sg:postcode":"60313",
    "sg:province":"Hessen",
    "wof:name":"Bfw Bundesverband Fernw\u00e4rmeleitungen E.v.",
    "wof:placetype":"venue"
},
  "geometry": {"coordinates":[8.685917,50.114517],"type":"Point"}
}