{
  "type": "Feature",
  "properties": {
    "iso:country":"DE",
    "sg:address":"Oeseder Str. 67",
    "sg:city":"Georgsmarienh\u00fctte",
    "sg:phone":"+49 5401/5265",
    "sg:postcode":"49124",
    "sg:province":"Niedersachsen",
    "wof:name":"Gildehaus",
    "wof:placetype":"venue"
},
  "geometry": {"coordinates":[8.0653190613,52.2072906494],"type":"Point"}
}