{
  "type": "Feature",
  "properties": {
    "iso:country":"DE",
    "sg:address":"Homburger Landstr. 179",
    "sg:city":"Frankfurt",
    "sg:phone":"+49 69/542096",
    "sg:postcode":"60435",
    "sg:province":"Hessen",
    "wof:name":"Frank Und Alfred Schuckhardt Projekt Sprendlingen Kg",
    "wof:placetype":"venue"
},
  "geometry": {"coordinates":[8.691009,50.153023],"type":"Point"}
}