{
  "type": "Feature",
  "properties": {
    "iso:country":"DE",
    "sg:address":"Alfred-Mozer-Str. 6",
    "sg:city":"Nordhorn",
    "sg:phone":"+49 5921/88090",
    "sg:postcode":"48527",
    "sg:province":"Niedersachsen",
    "wof:name":"Orga-ratio Organisations- Und Rationalisierungs Gmbh",
    "wof:placetype":"venue"
},
  "geometry": {"coordinates":[7.0344481468,52.4249458313],"type":"Point"}
}