{
  "type": "Feature",
  "properties": {
    "iso:country":"DE",
    "sg:address":"Lichtensteiner Str. 13",
    "sg:city":"Callenberg",
    "sg:phone":"+49 37608/21828",
    "sg:postcode":"09337",
    "sg:province":"Sachsen",
    "wof:name":"Scheffler-umz\u00fcge E. K.",
    "wof:placetype":"venue"
},
  "geometry": {"coordinates":[12.6388864517,50.8420791626],"type":"Point"}
}