{
  "type": "Feature",
  "properties": {
    "iso:country":"DE",
    "sg:address":"Gro\u00dfenhainer Stra\u00dfe 117",
    "sg:city":"Dresden",
    "sg:phone":"+49 351/8489602",
    "sg:postcode":"01127",
    "sg:province":"Sachsen",
    "wof:name":"Floristik & Raumbegr\u00fcnung",
    "wof:placetype":"venue"
},
  "geometry": {"coordinates":[13.728712,51.083511],"type":"Point"}
}