{
  "type": "Feature",
  "properties": {
    "iso:country":"DE",
    "sg:address":"Campingplatz",
    "sg:city":"Guldental",
    "sg:phone":"+49 6707/633",
    "sg:postcode":"55452",
    "sg:province":"Rheinland-Pfalz",
    "wof:name":"Campingplatz Lindengrund Gmbh",
    "wof:placetype":"venue"
},
  "geometry": {"coordinates":[7.843628,49.892307],"type":"Point"}
}