{
  "type": "Feature",
  "properties": {
    "iso:country":"DE",
    "sg:address":"Bahnhofstr. 1",
    "sg:city":"Scharbeutz",
    "sg:phone":"+49 4503/5225",
    "sg:postcode":"23683",
    "sg:province":"Schleswig-Holstein",
    "wof:name":"Pension Brigitte",
    "wof:placetype":"venue"
},
  "geometry": {"coordinates":[10.749256134,54.0209655762],"type":"Point"}
}