{
  "type": "Feature",
  "properties": {
    "iso:country":"DE",
    "sg:address":"Bodelschwinghstr. 25",
    "sg:city":"Kerpen",
    "sg:phone":"+49 2273/955845",
    "sg:postcode":"50170",
    "sg:province":"Nordrhein-Westfalen",
    "wof:name":"Allwego Gmbh Industriebedarf",
    "wof:placetype":"venue"
},
  "geometry": {"coordinates":[6.682484,50.901096],"type":"Point"}
}