{
  "type": "Feature",
  "properties": {
    "iso:country":"DE",
    "sg:address":"Hauptstrasse 14",
    "sg:city":"Engelsbrand",
    "sg:postcode":"75331",
    "sg:province":"Baden-W\u00fcrttemberg",
    "wof:name":"Kachelofenbauverzeichnis",
    "wof:placetype":"venue"
},
  "geometry": {"coordinates":[8.64525,48.830231],"type":"Point"}
}