{
  "type": "Feature",
  "properties": {
    "iso:country":"DE",
    "sg:address":"Hasenbergstr. 6a",
    "sg:city":"Dahn",
    "sg:phone":"+49 6391/1309",
    "sg:postcode":"66994",
    "sg:province":"Rheinland-Pfalz",
    "wof:name":"Helmut Seebach",
    "wof:placetype":"venue"
},
  "geometry": {"coordinates":[7.7787938118,49.1498603821],"type":"Point"}
}