{
  "type": "Feature",
  "properties": {
    "iso:country":"DE",
    "sg:address":"Hirschenweg 10",
    "sg:city":"Stegen",
    "sg:phone":"+49 7661/61359",
    "sg:postcode":"79252",
    "sg:province":"Baden-W\u00fcrttemberg",
    "wof:name":"Anneliese Fehr",
    "wof:placetype":"venue"
},
  "geometry": {"coordinates":[7.9657711983,47.9837722778],"type":"Point"}
}