{
  "type": "Feature",
  "properties": {
    "iso:country":"DE",
    "sg:address":"Gartenstr. 29",
    "sg:city":"Bornheim",
    "sg:phone":"+49 2222/81428",
    "sg:postcode":"53332",
    "sg:province":"Nordrhein-Westfalen",
    "wof:name":"Uwe Halft",
    "wof:placetype":"venue"
},
  "geometry": {"coordinates":[7.0448050499,50.7700881958],"type":"Point"}
}