{
  "type": "Feature",
  "properties": {
    "iso:country":"DE",
    "sg:address":"Hauptstr. 5",
    "sg:city":"Waltershausen",
    "sg:phone":"+49 3622/902369",
    "sg:postcode":"99880",
    "sg:province":"Th\u00fcringen",
    "wof:name":"Fleisch- Und Wurstwaren L\u00f6blein Thop Gmbh",
    "wof:placetype":"venue"
},
  "geometry": {"coordinates":[10.5568552017,50.8984718323],"type":"Point"}
}