{
  "type": "Feature",
  "properties": {
    "iso:country":"DE",
    "sg:address":"Uferallee 23",
    "sg:city":"Zeltingen-Rachtig",
    "sg:phone":"+49 6532/2596",
    "sg:postcode":"54492",
    "sg:province":"Rheinland-Pfalz",
    "wof:name":"Romedio Reichsgraf Von Thun Hohen-",
    "wof:placetype":"venue"
},
  "geometry": {"coordinates":[7.0141630173,49.9533004761],"type":"Point"}
}