{
  "type": "Feature",
  "properties": {
    "iso:country":"DE",
    "sg:address":"Nordhausener Str. 4",
    "sg:city":"Brackenheim",
    "sg:phone":"+49 7135/5041",
    "sg:postcode":"74336",
    "sg:province":"Baden-W\u00fcrttemberg",
    "wof:name":"Stadtarchiv Verwaltungsstelle Hausen",
    "wof:placetype":"venue"
},
  "geometry": {"coordinates":[9.106504,49.07811],"type":"Point"}
}