{
  "type": "Feature",
  "properties": {
    "iso:country":"DE",
    "sg:address":"Isestr. 39",
    "sg:city":"Hamburg",
    "sg:phone":"+49 40/4808670",
    "sg:postcode":"20144",
    "sg:province":"Hamburg",
    "wof:name":"Oliver C. Leisau Immobilien Gmbh",
    "wof:placetype":"venue"
},
  "geometry": {"coordinates":[9.9807767868,53.5809898376],"type":"Point"}
}