{
  "type": "Feature",
  "properties": {
    "iso:country":"DE",
    "sg:address":"Meisengrund 12",
    "sg:city":"Nordwalde",
    "sg:phone":"+49 2573/957324",
    "sg:postcode":"48356",
    "sg:province":"Nordrhein-Westfalen",
    "wof:name":"Andreas Bosch",
    "wof:placetype":"venue"
},
  "geometry": {"coordinates":[7.471159,52.082256],"type":"Point"}
}