{
  "type": "Feature",
  "properties": {
    "iso:country":"DE",
    "sg:address":"Bruchstr. 13",
    "sg:city":"Ratingen",
    "sg:phone":"+49 2102/873330",
    "sg:postcode":"40882",
    "sg:province":"Nordrhein-Westfalen",
    "wof:name":"Helmut Koch",
    "wof:placetype":"venue"
},
  "geometry": {"coordinates":[6.8718428612,51.3024520874],"type":"Point"}
}