{
  "type": "Feature",
  "properties": {
    "iso:country":"DE",
    "sg:address":"Urbanstr. 30",
    "sg:city":"Stuttgart",
    "sg:phone":"+49 711/244528",
    "sg:postcode":"70182",
    "sg:province":"Baden-W\u00fcrttemberg",
    "wof:name":"Dieter Baur",
    "wof:placetype":"venue"
},
  "geometry": {"coordinates":[9.186614,48.777996],"type":"Point"}
}