{
  "type": "Feature",
  "properties": {
    "iso:country":"DE",
    "sg:address":"Junkernfelder Weg 5",
    "sg:city":"Clausthal-Zellerfeld",
    "sg:phone":"+49 5323/1301",
    "sg:postcode":"38678",
    "sg:province":"Niedersachsen",
    "wof:name":"W. Hille",
    "wof:placetype":"venue"
},
  "geometry": {"coordinates":[10.3315315247,51.7769737244],"type":"Point"}
}