{
  "type": "Feature",
  "properties": {
    "iso:country":"DE",
    "sg:address":"Otto-Hahn-Str. 3",
    "sg:city":"Glinde",
    "sg:phone":"+49 40/4220243",
    "sg:postcode":"21509",
    "sg:province":"Schleswig-Holstein",
    "wof:name":"Omega Telefonanlagen Service Gmbh",
    "wof:placetype":"venue"
},
  "geometry": {"coordinates":[10.234146,53.529709],"type":"Point"}
}