{
  "type": "Feature",
  "properties": {
    "iso:country":"DE",
    "sg:address":"Gl\u00fcckaufstr. 20 a",
    "sg:city":"Recklinghausen",
    "sg:phone":"+49 2361/33450",
    "sg:postcode":"45663",
    "sg:province":"Nordrhein-Westfalen",
    "wof:name":"Detlef Berger",
    "wof:placetype":"venue"
},
  "geometry": {"coordinates":[7.227568,51.587143],"type":"Point"}
}