{
  "type": "Feature",
  "properties": {
    "iso:country":"DE",
    "sg:address":"Im S\u00e4mann 33",
    "sg:city":"Waiblingen",
    "sg:phone":"+49 7151/23604",
    "sg:postcode":"71334",
    "sg:province":"Baden-W\u00fcrttemberg",
    "wof:name":"Horst Frey Ingenieur",
    "wof:placetype":"venue"
},
  "geometry": {"coordinates":[9.3279352188,48.8348350525],"type":"Point"}
}