{
  "type": "Feature",
  "properties": {
    "iso:country":"DE",
    "sg:address":"Carl-Sonnenschein-Str. 70",
    "sg:city":"Krefeld",
    "sg:phone":"+49 2151/570027",
    "sg:postcode":"47809",
    "sg:province":"Nordrhein-Westfalen",
    "wof:name":"Tedima Technische Dichtungen Maschinen Und Anlagen Gmbh",
    "wof:placetype":"venue"
},
  "geometry": {"coordinates":[6.640518,51.344421],"type":"Point"}
}