{
  "type": "Feature",
  "properties": {
    "iso:country":"DE",
    "sg:address":"Moltkestr. 19",
    "sg:city":"Gummersbach",
    "sg:phone":"+49 2261/64015",
    "sg:postcode":"51643",
    "sg:province":"Nordrhein-Westfalen",
    "wof:name":"Karin Riese",
    "wof:placetype":"venue"
},
  "geometry": {"coordinates":[7.567673,51.027531],"type":"Point"}
}