{
  "type": "Feature",
  "properties": {
    "iso:country":"DE",
    "sg:address":"Schaftrift 4",
    "sg:city":"Geschwenda",
    "sg:phone":"+49 36205/95630",
    "sg:postcode":"98716",
    "sg:province":"Th\u00fcringen",
    "wof:name":"Motorrad-touren-guide",
    "wof:placetype":"venue"
},
  "geometry": {"coordinates":[10.823348999,50.7317962646],"type":"Point"}
}