{
  "type": "Feature",
  "properties": {
    "iso:country":"DE",
    "sg:address":"Josephsburgstr. 62",
    "sg:city":"M\u00fcnchen",
    "sg:phone":"+49 89/43670628",
    "sg:postcode":"81673",
    "sg:province":"Bayern",
    "wof:name":"Dr. Gerhard Schaefer Patentanwalt",
    "wof:placetype":"venue"
},
  "geometry": {"coordinates":[11.6356267929,48.125453949],"type":"Point"}
}