{
  "type": "Feature",
  "properties": {
    "iso:country":"DE",
    "sg:address":"Gerbergasse 1",
    "sg:city":"M\u00fcnchberg",
    "sg:phone":"+49 9251/5032",
    "sg:postcode":"95213",
    "sg:province":"Bayern",
    "wof:name":"Erwin Seeberger",
    "wof:placetype":"venue"
},
  "geometry": {"coordinates":[11.7873735428,50.1907081604],"type":"Point"}
}