{
  "type": "Feature",
  "properties": {
    "iso:country":"DE",
    "sg:address":"Finkenstr. 23",
    "sg:city":"Bad Rappenau",
    "sg:phone":"+49 7264/206565",
    "sg:postcode":"74906",
    "sg:province":"Baden-W\u00fcrttemberg",
    "wof:name":"Kaps Immobilien Gmbh",
    "wof:placetype":"venue"
},
  "geometry": {"coordinates":[9.0948591232,49.2424850464],"type":"Point"}
}