{
  "type": "Feature",
  "properties": {
    "iso:country":"DE",
    "sg:address":"Laiberbergstr. 36",
    "sg:city":"Heidenheim",
    "sg:postcode":"89520",
    "sg:province":"Baden-W\u00fcrttemberg",
    "wof:name":"Reitsport Straub Kg",
    "wof:placetype":"venue"
},
  "geometry": {"coordinates":[10.15816,48.701012],"type":"Point"}
}