{
  "type": "Feature",
  "properties": {
    "iso:country":"DE",
    "sg:address":"In dem Breil 16",
    "sg:city":"Herne",
    "sg:phone":"+49 2323/450000",
    "sg:postcode":"44623",
    "sg:province":"Nordrhein-Westfalen",
    "wof:name":"Ruhr-lippe Wohnungsges. Mbh",
    "wof:placetype":"venue"
},
  "geometry": {"coordinates":[7.2324371338,51.5319252014],"type":"Point"}
}