{
  "type": "Feature",
  "properties": {
    "iso:country":"DE",
    "sg:address":"Beeskower Str. 1a",
    "sg:city":"Eisenh\u00fcttenstadt",
    "sg:phone":"+49 3364/455600",
    "sg:postcode":"15890",
    "sg:province":"Brandenburg",
    "wof:name":"Gut Gleis- Und Tiefbau Gmbh",
    "wof:placetype":"venue"
},
  "geometry": {"coordinates":[14.6563272476,52.1472892761],"type":"Point"}
}