{
  "type": "Feature",
  "properties": {
    "iso:country":"DE",
    "sg:address":"Schaumbergstr. 174",
    "sg:city":"Lebach",
    "sg:phone":"+49 6888/225",
    "sg:postcode":"66822",
    "sg:province":"Saarland",
    "wof:name":"Kurt Weber",
    "wof:placetype":"venue"
},
  "geometry": {"coordinates":[6.9679088593,49.4489860535],"type":"Point"}
}