{
  "type": "Feature",
  "properties": {
    "iso:country":"DE",
    "sg:address":"Escher-Wyss-Str. 25",
    "sg:city":"Ravensburg",
    "sg:phone":"+49 751/8301",
    "sg:postcode":"88212",
    "sg:province":"Baden-W\u00fcrttemberg",
    "wof:name":"Voith Paper Verwaltungs Gmbh",
    "wof:placetype":"venue"
},
  "geometry": {"coordinates":[9.6056785583,47.7855453491],"type":"Point"}
}