{
  "type": "Feature",
  "properties": {
    "iso:country":"DE",
    "sg:address":"Frankenwaldstr. 16",
    "sg:city":"Geroldsgr\u00fcn",
    "sg:phone":"+49 9288/210",
    "sg:postcode":"95179",
    "sg:province":"Bayern",
    "wof:name":"Max G\u00f6lkel",
    "wof:placetype":"venue"
},
  "geometry": {"coordinates":[11.595962,50.334766],"type":"Point"}
}