{
  "type": "Feature",
  "properties": {
    "iso:country":"DE",
    "sg:address":"Quellenweg 4",
    "sg:city":"Bad Homburg",
    "sg:phone":"+49 6172/450582",
    "sg:postcode":"61348",
    "sg:province":"Hessen",
    "wof:name":"Karl Brixner",
    "wof:placetype":"venue"
},
  "geometry": {"coordinates":[8.632819,50.228256],"type":"Point"}
}