{
  "type": "Feature",
  "properties": {
    "iso:country":"DE",
    "sg:address":"Neulandstr. 10",
    "sg:city":"Naila",
    "sg:phone":"+49 9282/5555",
    "sg:postcode":"95119",
    "sg:province":"Bayern",
    "wof:name":"Beratungsstelle Der Inneren Mission Hof",
    "wof:placetype":"venue"
},
  "geometry": {"coordinates":[11.709828,50.324886],"type":"Point"}
}