{
  "type": "Feature",
  "properties": {
    "iso:country":"DE",
    "sg:address":"Am Meierhof 7",
    "sg:city":"Landwehr",
    "sg:phone":"+49 5184/241",
    "sg:postcode":"31087",
    "sg:province":"Niedersachsen",
    "wof:name":"J\u00fcrgen Bohnsack",
    "wof:placetype":"venue"
},
  "geometry": {"coordinates":[9.969752,51.910713],"type":"Point"}
}