{
  "type": "Feature",
  "properties": {
    "iso:country":"DE",
    "sg:address":"Eichstr. 22",
    "sg:city":"Bad D\u00fcrkheim",
    "sg:phone":"+49 6322/67001",
    "sg:postcode":"67098",
    "sg:province":"Rheinland-Pfalz",
    "wof:name":"Eberhard Bopst Rechtsanwalt",
    "wof:placetype":"venue"
},
  "geometry": {"coordinates":[8.1653871536,49.4606590271],"type":"Point"}
}