{
  "type": "Feature",
  "properties": {
    "iso:country":"DE",
    "sg:address":"Zum F\u00fcrstenholz 1",
    "sg:city":"Wietmarschen",
    "sg:phone":"+49 5925/302",
    "sg:postcode":"49835",
    "sg:province":"Niedersachsen",
    "wof:name":"Franz L\u00fctkeniehoff",
    "wof:placetype":"venue"
},
  "geometry": {"coordinates":[7.137464,52.501022],"type":"Point"}
}