{
  "type": "Feature",
  "properties": {
    "iso:country":"DE",
    "sg:address":"Schillerstr. 45",
    "sg:city":"Schipkau",
    "sg:phone":"+49 35754/60880",
    "sg:postcode":"01993",
    "sg:province":"Brandenburg",
    "wof:name":"Neue P\u00f6\u00dfnitz Apotheke Sabine Kempa",
    "wof:placetype":"venue"
},
  "geometry": {"coordinates":[13.899545,51.51585],"type":"Point"}
}