{
  "type": "Feature",
  "properties": {
    "iso:country":"DE",
    "sg:address":"H\u00f6fel 14",
    "sg:city":"Marienheide",
    "sg:phone":"+49 2264/7627",
    "sg:postcode":"51709",
    "sg:province":"Nordrhein-Westfalen",
    "wof:name":"Ernst Schneider",
    "wof:placetype":"venue"
},
  "geometry": {"coordinates":[7.531342,51.083202],"type":"Point"}
}