{
  "type": "Feature",
  "properties": {
    "iso:country":"DE",
    "sg:address":"Bachgasse 2",
    "sg:city":"Gleiszellen-Gleishorbach",
    "sg:phone":"+49 6343/7880",
    "sg:postcode":"76889",
    "sg:province":"Rheinland-Pfalz",
    "wof:name":"Jacoby & Huber Herrenmode Gmbh",
    "wof:placetype":"venue"
},
  "geometry": {"coordinates":[8.0067195892,49.1249198914],"type":"Point"}
}