{
  "type": "Feature",
  "properties": {
    "iso:country":"DE",
    "sg:address":"Glockenstr. 5",
    "sg:city":"Trier",
    "sg:phone":"+49 651/75097",
    "sg:postcode":"54290",
    "sg:province":"Rheinland-Pfalz",
    "wof:name":"Bermes Ohg",
    "wof:placetype":"venue"
},
  "geometry": {"coordinates":[6.6430487633,49.7578392029],"type":"Point"}
}