{
  "type": "Feature",
  "properties": {
    "iso:country":"DE",
    "sg:address":"Kunzenweg 25",
    "sg:city":"Freiburg",
    "sg:phone":"+49 761/611230",
    "sg:postcode":"79117",
    "sg:province":"Baden-W\u00fcrttemberg",
    "wof:name":"H. Henseleit Ingenieur",
    "wof:placetype":"venue"
},
  "geometry": {"coordinates":[7.8932819366,47.9808807373],"type":"Point"}
}