{
  "type": "Feature",
  "properties": {
    "iso:country":"DE",
    "sg:address":"Verler Str. 1",
    "sg:city":"G\u00fctersloh",
    "sg:phone":"+49 5241/15230",
    "sg:postcode":"33332",
    "sg:province":"Nordrhein-Westfalen",
    "wof:name":"Ferdinand Allmandinger",
    "wof:placetype":"venue"
},
  "geometry": {"coordinates":[8.3935642242,51.9043312073],"type":"Point"}
}