{
  "type": "Feature",
  "properties": {
    "iso:country":"DE",
    "sg:address":"Allee-Center",
    "sg:city":"Remscheid",
    "sg:phone":"+49 2191/26640",
    "sg:postcode":"42853",
    "sg:province":"Nordrhein-Westfalen",
    "wof:name":"Hans J. Harnischmacher",
    "wof:placetype":"venue"
},
  "geometry": {"coordinates":[7.1930251122,51.1792907715],"type":"Point"}
}