{
  "type": "Feature",
  "properties": {
    "iso:country":"DE",
    "sg:address":"Norderweg 3",
    "sg:city":"Bondelum",
    "sg:phone":"+49 4843/1202",
    "sg:postcode":"25850",
    "sg:province":"Schleswig-Holstein",
    "wof:name":"E. Thomsen",
    "wof:placetype":"venue"
},
  "geometry": {"coordinates":[9.272534,54.561691],"type":"Point"}
}