{
  "type": "Feature",
  "properties": {
    "iso:country":"DE",
    "sg:address":"Friedrichstr. 18",
    "sg:city":"K\u00f6then",
    "sg:postcode":"06366",
    "sg:province":"Sachsen-Anhalt",
    "wof:name":"Avk Service E. K. Inhaber Dagmar Richter",
    "wof:placetype":"venue"
},
  "geometry": {"coordinates":[11.982857,51.754086],"type":"Point"}
}