{
  "type": "Feature",
  "properties": {
    "iso:country":"DE",
    "sg:address":"Riedener Str. 12a",
    "sg:city":"M\u00fcnchen",
    "sg:phone":"+49 89/7594270",
    "sg:postcode":"81475",
    "sg:province":"Bayern",
    "wof:name":"I. W\u00e4chter-hoppe",
    "wof:placetype":"venue"
},
  "geometry": {"coordinates":[11.480051,48.087208],"type":"Point"}
}