{
  "type": "Feature",
  "properties": {
    "iso:country":"DE",
    "sg:address":"Badstr. 54",
    "sg:city":"Calw",
    "sg:phone":"+49 7051/3667",
    "sg:postcode":"75365",
    "sg:province":"Baden-W\u00fcrttemberg",
    "wof:name":"B. Ramge",
    "wof:placetype":"venue"
},
  "geometry": {"coordinates":[8.7395706177,48.7093162537],"type":"Point"}
}