{
  "type": "Feature",
  "properties": {
    "iso:country":"DE",
    "sg:address":"Am Eichengarten 26",
    "sg:city":"Dessau",
    "sg:phone":"+49 340/218220",
    "sg:postcode":"06842",
    "sg:province":"Sachsen-Anhalt",
    "wof:name":"Auto-haas Gmbh",
    "wof:placetype":"venue"
},
  "geometry": {"coordinates":[12.297961,51.81768],"type":"Point"}
}