{
  "type": "Feature",
  "properties": {
    "iso:country":"DE",
    "sg:address":"Flughafenstr. 9",
    "sg:city":"D\u00fcsseldorf",
    "sg:phone":"+49 211/4544417",
    "sg:postcode":"40474",
    "sg:province":"Nordrhein-Westfalen",
    "wof:name":"B.stefic & G.krekekler",
    "wof:placetype":"venue"
},
  "geometry": {"coordinates":[6.759009,51.273121],"type":"Point"}
}