{
  "type": "Feature",
  "properties": {
    "iso:country":"DE",
    "sg:address":"Hohensteinstr.",
    "sg:city":"Gingen",
    "sg:phone":"+49 7162/9301220",
    "sg:postcode":"73333",
    "sg:province":"Baden-W\u00fcrttemberg",
    "wof:name":"Cad Design-service",
    "wof:placetype":"venue"
},
  "geometry": {"coordinates":[9.790616,48.657162],"type":"Point"}
}