{
  "type": "Feature",
  "properties": {
    "iso:country":"DE",
    "sg:address":"Stuttgarter Str. 70",
    "sg:city":"Leutenbach",
    "sg:phone":"+49 7195/178022",
    "sg:postcode":"71397",
    "sg:province":"Baden-W\u00fcrttemberg",
    "wof:name":"P. Rold",
    "wof:placetype":"venue"
},
  "geometry": {"coordinates":[9.3759346008,48.8974304199],"type":"Point"}
}