{
  "type": "Feature",
  "properties": {
    "iso:country":"DE",
    "sg:address":"Obere Au 28",
    "sg:city":"Niederviehbach",
    "sg:phone":"+49 8702/2210",
    "sg:postcode":"84183",
    "sg:province":"Bayern",
    "wof:name":"W. Antesberger",
    "wof:placetype":"venue"
},
  "geometry": {"coordinates":[12.37397,48.622684],"type":"Point"}
}