{
  "type": "Feature",
  "properties": {
    "iso:country":"DE",
    "sg:address":"Am Schulberg 13",
    "sg:city":"Winnenden",
    "sg:phone":"+49 7195/174200",
    "sg:postcode":"71364",
    "sg:province":"Baden-W\u00fcrttemberg",
    "wof:name":"Erika Abelein Steuerberaterin",
    "wof:placetype":"venue"
},
  "geometry": {"coordinates":[9.424700737,48.8879356384],"type":"Point"}
}