{
  "type": "Feature",
  "properties": {
    "iso:country":"DE",
    "sg:address":"Burgsteinfurter Damm 89",
    "sg:city":"Neuenkirchen",
    "sg:phone":"+49 5973/6301",
    "sg:postcode":"48485",
    "sg:province":"Nordrhein-Westfalen",
    "wof:name":"Windhoff Wassertechnik Gmbh",
    "wof:placetype":"venue"
},
  "geometry": {"coordinates":[7.3728652,52.2301750183],"type":"Point"}
}