{
  "type": "Feature",
  "properties": {
    "iso:country":"DE",
    "sg:address":"Uerdinger Str. 62",
    "sg:city":"Krefeld",
    "sg:postcode":"47799",
    "sg:province":"Nordrhein-Westfalen",
    "wof:name":"Jam Multimedia Gmbh",
    "wof:placetype":"venue"
},
  "geometry": {"coordinates":[6.5747900009,51.3358879089],"type":"Point"}
}