{
  "type": "Feature",
  "properties": {
    "iso:country":"DE",
    "sg:address":"Werderstr. 48",
    "sg:city":"Eggenstein-Leopoldshafen",
    "sg:phone":"+49 721/786840",
    "sg:postcode":"76344",
    "sg:province":"Baden-W\u00fcrttemberg",
    "wof:name":"Erich P. K\u00f6hler",
    "wof:placetype":"venue"
},
  "geometry": {"coordinates":[8.392102,49.079536],"type":"Point"}
}