{
  "type": "Feature",
  "properties": {
    "iso:country":"DE",
    "sg:address":"Go\u00dflerstr. 5",
    "sg:city":"Berlin",
    "sg:phone":"+49 30/8312190",
    "sg:postcode":"14195",
    "sg:province":"Berlin",
    "wof:name":"Joachim K\u00f6gel",
    "wof:placetype":"venue"
},
  "geometry": {"coordinates":[13.291577,52.44582],"type":"Point"}
}