{
  "type": "Feature",
  "properties": {
    "iso:country":"DE",
    "sg:address":"Am Riedenbach 17",
    "sg:city":"Osnabr\u00fcck",
    "sg:phone":"+49 541/51568",
    "sg:postcode":"49082",
    "sg:province":"Niedersachsen",
    "wof:name":"Oberkrainer Deele",
    "wof:placetype":"venue"
},
  "geometry": {"coordinates":[8.0612211227,52.2609443665],"type":"Point"}
}