{
  "type": "Feature",
  "properties": {
    "iso:country":"DE",
    "sg:address":"Wilstorfer Str. 92",
    "sg:city":"Hamburg",
    "sg:phone":"+49 40/7653680",
    "sg:postcode":"21073",
    "sg:province":"Hamburg",
    "wof:name":"Horst-g. Hahn",
    "wof:placetype":"venue"
},
  "geometry": {"coordinates":[9.987478,53.453957],"type":"Point"}
}