{
  "type": "Feature",
  "properties": {
    "iso:country":"DE",
    "sg:address":"Wesselberg 28",
    "sg:city":"L\u00fcdenscheid",
    "sg:phone":"+49 2351/23355",
    "sg:postcode":"58515",
    "sg:province":"Nordrhein-Westfalen",
    "wof:name":"Udo Weigand",
    "wof:placetype":"venue"
},
  "geometry": {"coordinates":[7.592649,51.199604],"type":"Point"}
}