{
  "type": "Feature",
  "properties": {
    "iso:country":"DE",
    "sg:address":"Halverder Str. 18",
    "sg:city":"Hopsten",
    "sg:phone":"+49 5458/530",
    "sg:postcode":"48496",
    "sg:province":"Nordrhein-Westfalen",
    "wof:name":"Franz Bresch",
    "wof:placetype":"venue"
},
  "geometry": {"coordinates":[7.62127,52.388561],"type":"Point"}
}