{
  "type": "Feature",
  "properties": {
    "iso:country":"DE",
    "sg:address":"Rohrweg 31",
    "sg:city":"H\u00f6xter",
    "sg:phone":"+49 5271/97560",
    "sg:postcode":"37671",
    "sg:province":"Nordrhein-Westfalen",
    "wof:name":"Gronemeyer Maschinenfabrik Verwaltungsges. Mbh",
    "wof:placetype":"venue"
},
  "geometry": {"coordinates":[9.386857,51.780178],"type":"Point"}
}