{
  "type": "Feature",
  "properties": {
    "iso:country":"DE",
    "sg:address":"Weserstr. 33",
    "sg:city":"Rinteln",
    "sg:phone":"+49 5751/2772",
    "sg:postcode":"31737",
    "sg:province":"Niedersachsen",
    "wof:name":"Cigarren-touristik Schaefer Gmbh",
    "wof:placetype":"venue"
},
  "geometry": {"coordinates":[9.0810785294,52.1890602112],"type":"Point"}
}