{
  "type": "Feature",
  "properties": {
    "iso:country":"DE",
    "sg:address":"Ihlower Str. 50",
    "sg:city":"Ihlow",
    "sg:phone":"+49 4929/332",
    "sg:postcode":"26632",
    "sg:province":"Niedersachsen",
    "wof:name":"Johann M\u00fcller",
    "wof:placetype":"venue"
},
  "geometry": {"coordinates":[7.403705,53.37429],"type":"Point"}
}