{
  "type": "Feature",
  "properties": {
    "iso:country":"DE",
    "sg:address":"M\u00fchlstr. 8",
    "sg:city":"Altlu\u00dfheim",
    "sg:phone":"+49 6205/32733",
    "sg:postcode":"68804",
    "sg:province":"Baden-W\u00fcrttemberg",
    "wof:name":"Roland Und B\u00e4rbel K\u00f6hler",
    "wof:placetype":"venue"
},
  "geometry": {"coordinates":[8.5007486343,49.2993087769],"type":"Point"}
}