{
  "type": "Feature",
  "properties": {
    "iso:country":"DE",
    "sg:address":"Schwarzengrund 9",
    "sg:city":"Hohenroda",
    "sg:phone":"+49 4966/76181",
    "sg:postcode":"36284",
    "sg:province":"Hessen",
    "wof:name":"Hessen Hotelpark Hohenroda Gmbh",
    "wof:placetype":"venue"
},
  "geometry": {"coordinates":[9.899948,50.809517],"type":"Point"}
}