{
  "type": "Feature",
  "properties": {
    "iso:country":"DE",
    "sg:address":"Ludwigsplatz 17",
    "sg:city":"Straubing",
    "sg:phone":"+49 9421/99040",
    "sg:postcode":"94315",
    "sg:province":"Bayern",
    "wof:name":"Auer Holding Gmbh",
    "wof:placetype":"venue"
},
  "geometry": {"coordinates":[12.5724983215,48.8821525574],"type":"Point"}
}