{
  "type": "Feature",
  "properties": {
    "iso:country":"DE",
    "sg:address":"Harkortshof 5",
    "sg:city":"Dortmund",
    "sg:phone":"+49 231/75788",
    "sg:postcode":"44227",
    "sg:province":"Nordrhein-Westfalen",
    "wof:name":"Herbert M\u00f6ckel",
    "wof:placetype":"venue"
},
  "geometry": {"coordinates":[7.4294247627,51.4706993103],"type":"Point"}
}