{
  "type": "Feature",
  "properties": {
    "iso:country":"DE",
    "sg:address":"Stra\u00dfe der Freundschaft 61a",
    "sg:city":"Espenhain",
    "sg:postcode":"04579",
    "sg:province":"Sachsen",
    "wof:name":"Bv Bauelemente Vertriebs Gmbh & Co.",
    "wof:placetype":"venue"
},
  "geometry": {"coordinates":[12.5266056061,51.2189559937],"type":"Point"}
}