{
  "type": "Feature",
  "properties": {
    "iso:country":"DE",
    "sg:address":"Stra\u00dfe des Friedens 26",
    "sg:city":"Holzwei\u00dfig",
    "sg:phone":"+49 3493/69147",
    "sg:postcode":"06808",
    "sg:province":"Sachsen-Anhalt",
    "wof:name":"Fleischerei Ackermann Gmbh",
    "wof:placetype":"venue"
},
  "geometry": {"coordinates":[12.3075008392,51.5974731445],"type":"Point"}
}