{
  "type": "Feature",
  "properties": {
    "iso:country":"DE",
    "sg:address":"Elly-Heuss-Knapp-Ring 86",
    "sg:city":"Hamburg",
    "sg:phone":"+49 40/7358590",
    "sg:postcode":"21035",
    "sg:province":"Hamburg",
    "wof:name":"Walter Lempik",
    "wof:placetype":"venue"
},
  "geometry": {"coordinates":[10.164921,53.479134],"type":"Point"}
}