{
  "type": "Feature",
  "properties": {
    "iso:country":"DE",
    "sg:address":"Gr\u00fcne Str 05",
    "sg:city":"Rieder",
    "sg:phone":"+49 39485/62764",
    "sg:postcode":"06507",
    "sg:province":"Sachsen-Anhalt",
    "wof:name":"Sportverein Gr\u00fcn Weiss Rieder 47 E.v.",
    "wof:placetype":"venue"
},
  "geometry": {"coordinates":[11.083061,51.695652],"type":"Point"}
}