{
  "type": "Feature",
  "properties": {
    "iso:country":"DE",
    "sg:address":"Raiffeisenstr. 11",
    "sg:city":"Altom\u00fcnster",
    "sg:phone":"+49 8254/723",
    "sg:postcode":"85250",
    "sg:province":"Bayern",
    "wof:name":"Maria Wackerl",
    "wof:placetype":"venue"
},
  "geometry": {"coordinates":[11.201472,48.404205],"type":"Point"}
}