{
  "type": "Feature",
  "properties": {
    "iso:country":"DE",
    "sg:address":"Neue Mauerstr. 13",
    "sg:city":"Bad Homburg",
    "sg:phone":"+49 6172/690867",
    "sg:postcode":"61348",
    "sg:province":"Hessen",
    "wof:name":"Heinz Schneider",
    "wof:placetype":"venue"
},
  "geometry": {"coordinates":[8.609735,50.231937],"type":"Point"}
}