{
  "type": "Feature",
  "properties": {
    "iso:country":"DE",
    "sg:address":"Badstr. 30",
    "sg:city":"Calw",
    "sg:phone":"+49 7051/2134",
    "sg:postcode":"75365",
    "sg:province":"Baden-W\u00fcrttemberg",
    "wof:name":"Davids Grill",
    "wof:placetype":"venue"
},
  "geometry": {"coordinates":[8.7405452728,48.7114906311],"type":"Point"}
}