{
  "type": "Feature",
  "properties": {
    "iso:country":"DE",
    "sg:address":"Bahnhofstr. 13",
    "sg:city":"Wiesentheid",
    "sg:phone":"+49 9383/817",
    "sg:postcode":"97353",
    "sg:province":"Bayern",
    "wof:name":"Castell-bank",
    "wof:placetype":"venue"
},
  "geometry": {"coordinates":[10.341249,49.791531],"type":"Point"}
}