{
  "type": "Feature",
  "properties": {
    "iso:country":"DE",
    "sg:address":"Lilienthalstr 3",
    "sg:city":"Hodenhagen",
    "sg:phone":"+49 5164/986690",
    "sg:postcode":"29693",
    "sg:province":"Niedersachsen",
    "wof:name":"Ars Altmann Ag",
    "wof:placetype":"venue"
},
  "geometry": {"coordinates":[9.603243,52.766869],"type":"Point"}
}