{
  "type": "Feature",
  "properties": {
    "iso:country":"DE",
    "sg:address":"Meissnerstr. 45",
    "sg:city":"Kassel",
    "sg:postcode":"34134",
    "sg:province":"Hessen",
    "wof:name":"Claudia Bach",
    "wof:placetype":"venue"
},
  "geometry": {"coordinates":[9.447596,51.295719],"type":"Point"}
}