{
  "type": "Feature",
  "properties": {
    "iso:country":"DE",
    "sg:address":"Werkstr. 9",
    "sg:city":"Bad K\u00f6nig",
    "sg:phone":"+49 6063/1559",
    "sg:postcode":"64732",
    "sg:province":"Hessen",
    "wof:name":"Alfred Weidner",
    "wof:placetype":"venue"
},
  "geometry": {"coordinates":[9.002028,49.740688],"type":"Point"}
}