{
  "type": "Feature",
  "properties": {
    "iso:country":"DE",
    "sg:address":"Lortzingstr. 31",
    "sg:city":"Bremen",
    "sg:postcode":"28209",
    "sg:province":"Bremen",
    "wof:name":"Roco Kaffee- Handelsgesellschaft",
    "wof:placetype":"venue"
},
  "geometry": {"coordinates":[8.842748642,53.08568573],"type":"Point"}
}