{
  "type": "Feature",
  "properties": {
    "iso:country":"DE",
    "sg:address":"Alter Zollweg 188",
    "sg:city":"Hamburg",
    "sg:phone":"+49 40/6471052",
    "sg:postcode":"22147",
    "sg:province":"Hamburg",
    "wof:name":"D\u00fchring Masseur",
    "wof:placetype":"venue"
},
  "geometry": {"coordinates":[10.129761,53.603119],"type":"Point"}
}