{
  "type": "Feature",
  "properties": {
    "iso:country":"DE",
    "sg:address":"Zeppelinstr. 1",
    "sg:city":"S\u00fc\u00dfen",
    "sg:phone":"+49 7162/45823",
    "sg:postcode":"73079",
    "sg:province":"Baden-W\u00fcrttemberg",
    "wof:name":"R. Basler",
    "wof:placetype":"venue"
},
  "geometry": {"coordinates":[9.7614250183,48.6845550537],"type":"Point"}
}