{
  "type": "Feature",
  "properties": {
    "iso:country":"DE",
    "sg:address":"Am Bahnhof 5a",
    "sg:city":"Ziesar",
    "sg:phone":"+49 33830/60310",
    "sg:postcode":"14793",
    "sg:province":"Brandenburg",
    "wof:name":"Heinz Lucht",
    "wof:placetype":"venue"
},
  "geometry": {"coordinates":[12.296079,52.265438],"type":"Point"}
}