{
  "type": "Feature",
  "properties": {
    "iso:country":"DE",
    "sg:address":"Homert 30",
    "sg:city":"L\u00fcdenscheid",
    "sg:phone":"+49 2351/40939",
    "sg:postcode":"58515",
    "sg:province":"Nordrhein-Westfalen",
    "wof:name":"Wilhelm Clever",
    "wof:placetype":"venue"
},
  "geometry": {"coordinates":[7.567339,51.209743],"type":"Point"}
}