{
  "type": "Feature",
  "properties": {
    "iso:country":"DE",
    "sg:address":"Kernstr. 12",
    "sg:city":"Traunstein",
    "sg:phone":"+49 861/8031",
    "sg:postcode":"83278",
    "sg:province":"Bayern",
    "wof:name":"Dr. Med. Helmut Gr\u00fcndobler Arzt F\u00fcr Allgemeinmedizin",
    "wof:placetype":"venue"
},
  "geometry": {"coordinates":[12.6385669708,47.8723716736],"type":"Point"}
}