{
  "type": "Feature",
  "properties": {
    "iso:country":"DE",
    "sg:address":"W\u00fcrzburger Str. 33",
    "sg:city":"K\u00f6ln",
    "sg:phone":"+49 221/874561",
    "sg:postcode":"51103",
    "sg:province":"Nordrhein-Westfalen",
    "wof:name":"G\u00fcnter Kohl",
    "wof:placetype":"venue"
},
  "geometry": {"coordinates":[7.018982,50.936028],"type":"Point"}
}