{
  "type": "Feature",
  "properties": {
    "iso:country":"DE",
    "sg:address":"Boderitzer Str. 13",
    "sg:city":"Dresden",
    "sg:phone":"+49 351/4712440",
    "sg:postcode":"01217",
    "sg:province":"Sachsen",
    "wof:name":"Dr. Dieter Reinhold",
    "wof:placetype":"venue"
},
  "geometry": {"coordinates":[13.7509126663,51.0147666931],"type":"Point"}
}