{
  "type": "Feature",
  "properties": {
    "iso:country":"DE",
    "sg:address":"Neusser Str. 49",
    "sg:city":"Grevenbroich",
    "sg:phone":"+49 2182/2784",
    "sg:postcode":"41516",
    "sg:province":"Nordrhein-Westfalen",
    "wof:name":"Drei K\u00f6nige",
    "wof:placetype":"venue"
},
  "geometry": {"coordinates":[6.6276741028,51.1297607422],"type":"Point"}
}