{
  "type": "Feature",
  "properties": {
    "iso:country":"DE",
    "sg:address":"Friedensplatz 8",
    "sg:city":"Oberhausen",
    "sg:phone":"+49 208/200020",
    "sg:postcode":"46045",
    "sg:province":"Nordrhein-Westfalen",
    "wof:name":"Stehcafe Am Friedensplatz",
    "wof:placetype":"venue"
},
  "geometry": {"coordinates":[6.84755,51.469765],"type":"Point"}
}