{
  "type": "Feature",
  "properties": {
    "iso:country":"DE",
    "sg:address":"Rudolf-Breitscheid-Str. 34",
    "sg:city":"Bernsdorf",
    "sg:phone":"+49 35723/21373",
    "sg:postcode":"02994",
    "sg:province":"Sachsen",
    "wof:name":"Eberhard Sch\u00f6ne Maschinenbau E. K.",
    "wof:placetype":"venue"
},
  "geometry": {"coordinates":[14.062568,51.382095],"type":"Point"}
}