{
  "type": "Feature",
  "properties": {
    "iso:country":"DE",
    "sg:address":"Waldwinkel 30",
    "sg:city":"Hamburg",
    "sg:phone":"+49 40/6735020",
    "sg:postcode":"22149",
    "sg:province":"Hamburg",
    "wof:name":"Prof. Dr. A. Schwennicke Ingenieur",
    "wof:placetype":"venue"
},
  "geometry": {"coordinates":[10.1744098663,53.5923614502],"type":"Point"}
}