{
  "type": "Feature",
  "properties": {
    "iso:country":"DE",
    "sg:address":"Sportplatzstr. 19",
    "sg:city":"Bad Birnbach",
    "sg:phone":"+49 8561/1829",
    "sg:postcode":"84364",
    "sg:province":"Bayern",
    "wof:name":"Willibald Stranzinger",
    "wof:placetype":"venue"
},
  "geometry": {"coordinates":[13.014205,48.441647],"type":"Point"}
}