{
  "type": "Feature",
  "properties": {
    "iso:country":"DE",
    "sg:address":"Industriestr. 1",
    "sg:city":"Bramsche",
    "sg:phone":"+49 5461/6941",
    "sg:postcode":"49565",
    "sg:province":"Niedersachsen",
    "wof:name":"T. Philipps Gmbh",
    "wof:placetype":"venue"
},
  "geometry": {"coordinates":[7.9645209312,52.4473724365],"type":"Point"}
}