{
  "type": "Feature",
  "properties": {
    "iso:country":"DE",
    "sg:address":"B\u00fcssemfeld 25",
    "sg:city":"Viersen",
    "sg:phone":"+49 2162/14010",
    "sg:postcode":"41748",
    "sg:province":"Nordrhein-Westfalen",
    "wof:name":"Claus Biste",
    "wof:placetype":"venue"
},
  "geometry": {"coordinates":[6.3873071671,51.2704429626],"type":"Point"}
}