{
  "type": "Feature",
  "properties": {
    "iso:country":"DE",
    "sg:address":"Lessingstr. 15",
    "sg:city":"Eschwege",
    "sg:phone":"+49 5651/50695",
    "sg:postcode":"37269",
    "sg:province":"Hessen",
    "wof:name":"Reinhold Zeuch Kunstmaler",
    "wof:placetype":"venue"
},
  "geometry": {"coordinates":[10.046901,51.188766],"type":"Point"}
}