{
  "type": "Feature",
  "properties": {
    "iso:country":"DE",
    "sg:address":"Koogstraat 6",
    "sg:city":"Norderfriedrichskoog",
    "sg:postcode":"25870",
    "sg:province":"Schleswig-Holstein",
    "wof:name":"Rtl-immobilien Verwaltungs Gmbh",
    "wof:placetype":"venue"
},
  "geometry": {"coordinates":[8.9002151489,54.4011268616],"type":"Point"}
}