{
  "type": "Feature",
  "properties": {
    "iso:country":"DE",
    "sg:address":"Die Hute 1",
    "sg:city":"V\u00f6hl",
    "sg:phone":"+49 5635/384",
    "sg:postcode":"34516",
    "sg:province":"Hessen",
    "wof:name":"W. Mitze",
    "wof:placetype":"venue"
},
  "geometry": {"coordinates":[8.975119,51.203362],"type":"Point"}
}