{
  "type": "Feature",
  "properties": {
    "iso:country":"DE",
    "sg:address":"Kinderwiesenstr. 4",
    "sg:city":"Uslar",
    "sg:phone":"+49 5571/2626",
    "sg:postcode":"37170",
    "sg:province":"Niedersachsen",
    "wof:name":"Werner Poppe",
    "wof:placetype":"venue"
},
  "geometry": {"coordinates":[9.5587244034,51.6915359497],"type":"Point"}
}