{
  "type": "Feature",
  "properties": {
    "iso:country":"DE",
    "sg:address":"Brunnenstr. 1",
    "sg:city":"Metzingen",
    "sg:phone":"+49 7123/2284",
    "sg:postcode":"72555",
    "sg:province":"Baden-W\u00fcrttemberg",
    "wof:name":"G\u00e4stehaus Reusch",
    "wof:placetype":"venue"
},
  "geometry": {"coordinates":[9.3075017929,48.5280532837],"type":"Point"}
}