{
  "type": "Feature",
  "properties": {
    "iso:country":"DE",
    "sg:address":"Halbmondstrasse 20",
    "sg:city":"Holzminden",
    "sg:phone":"+49 5531/3597",
    "sg:postcode":"37603",
    "sg:province":"Niedersachsen",
    "wof:name":"Wiesenack Lederwaren - Holzminden Und H\u00f6xter",
    "wof:placetype":"venue"
},
  "geometry": {"coordinates":[9.4472999573,51.8287849426],"type":"Point"}
}