{
  "type": "Feature",
  "properties": {
    "iso:country":"DE",
    "sg:address":"Hauptstr. 17",
    "sg:city":"Mintraching",
    "sg:phone":"+49 9406/874",
    "sg:postcode":"93098",
    "sg:province":"Bayern",
    "wof:name":"Michael Geser",
    "wof:placetype":"venue"
},
  "geometry": {"coordinates":[12.2408533096,48.9537582397],"type":"Point"}
}