{
  "type": "Feature",
  "properties": {
    "iso:country":"DE",
    "sg:address":"Vohenstrau\u00dfer Str. 4",
    "sg:city":"Flo\u00df",
    "sg:phone":"+49 9603/1557",
    "sg:postcode":"92685",
    "sg:province":"Bayern",
    "wof:name":"Edmund Emmerling",
    "wof:placetype":"venue"
},
  "geometry": {"coordinates":[12.27675,49.722904],"type":"Point"}
}