{
  "type": "Feature",
  "properties": {
    "iso:country":"DE",
    "sg:address":"Leo-Wohleb-Str. 3",
    "sg:city":"Blumberg",
    "sg:phone":"+49 7702/43920",
    "sg:postcode":"78176",
    "sg:province":"Baden-W\u00fcrttemberg",
    "wof:name":"Energieversorgung S\u00fcdbaar Gmbh",
    "wof:placetype":"venue"
},
  "geometry": {"coordinates":[8.540154,47.838428],"type":"Point"}
}