{
  "type": "Feature",
  "properties": {
    "iso:country":"DE",
    "sg:address":"Ladestr. 2",
    "sg:city":"Remscheid",
    "sg:phone":"+49 2191/24848",
    "sg:postcode":"42859",
    "sg:province":"Nordrhein-Westfalen",
    "wof:name":"Taxi-vereinigung",
    "wof:placetype":"venue"
},
  "geometry": {"coordinates":[7.1953887939,51.1762695312],"type":"Point"}
}