{
  "type": "Feature",
  "properties": {
    "iso:country":"DE",
    "sg:address":"An der Sonnhalde 8",
    "sg:city":"Herbolzheim",
    "sg:phone":"+49 7643/913020",
    "sg:postcode":"79336",
    "sg:province":"Baden-W\u00fcrttemberg",
    "wof:name":"Agw Hausger\u00e4teservice Gmbh",
    "wof:placetype":"venue"
},
  "geometry": {"coordinates":[7.7774300575,48.222492218],"type":"Point"}
}