{
  "type": "Feature",
  "properties": {
    "iso:country":"DE",
    "sg:address":"Graf-Zeppelin-Str. 15",
    "sg:city":"Forst",
    "sg:phone":"+49 7251/2016",
    "sg:postcode":"76694",
    "sg:province":"Baden-W\u00fcrttemberg",
    "wof:name":"Richard B\u00f6ser Kg",
    "wof:placetype":"venue"
},
  "geometry": {"coordinates":[8.571575,49.160442],"type":"Point"}
}