{
  "type": "Feature",
  "properties": {
    "iso:country":"DE",
    "sg:address":"Karlshulder Str. 6",
    "sg:city":"Brunnen",
    "sg:phone":"+49 8454/3199",
    "sg:postcode":"86564",
    "sg:province":"Bayern",
    "wof:name":"Ch. Kopold",
    "wof:placetype":"venue"
},
  "geometry": {"coordinates":[11.311123,48.631554],"type":"Point"}
}