{
  "type": "Feature",
  "properties": {
    "iso:country":"DE",
    "sg:address":"Vor der Bahn 1",
    "sg:city":"Hann. M\u00fcnden",
    "sg:phone":"+49 5541/72061",
    "sg:postcode":"34346",
    "sg:province":"Niedersachsen",
    "wof:name":"Baustoffhandelsges. Mbh & Co. Betriebs Kg-zn D. Bhg Baumarkt",
    "wof:placetype":"venue"
},
  "geometry": {"coordinates":[9.663465,51.415691],"type":"Point"}
}