{
  "type": "Feature",
  "properties": {
    "iso:country":"DE",
    "sg:address":"Friedrich-Rech-Str. 168",
    "sg:city":"Neuwied",
    "sg:phone":"+49 2631/47518",
    "sg:postcode":"56566",
    "sg:province":"Rheinland-Pfalz",
    "wof:name":"Wiedischer Hof",
    "wof:placetype":"venue"
},
  "geometry": {"coordinates":[7.5021481514,50.4738960266],"type":"Point"}
}