{
  "type": "Feature",
  "properties": {
    "iso:country":"DE",
    "sg:address":"Dr.-Hans-Wilhelmi-Weg 1",
    "sg:city":"Lahnau",
    "sg:phone":"+49 6441/6010",
    "sg:postcode":"35633",
    "sg:province":"Hessen",
    "wof:name":"Wilhelmi Gmbh",
    "wof:placetype":"venue"
},
  "geometry": {"coordinates":[8.572149,50.578228],"type":"Point"}
}