{
  "type": "Feature",
  "properties": {
    "iso:country":"DE",
    "sg:address":"Eisentalstra\u00dfe 34 - Lautlingen",
    "sg:city":"Albstadt",
    "sg:phone":"+49 7431/72671",
    "sg:postcode":"72459",
    "sg:province":"Baden-W\u00fcrttemberg",
    "wof:name":"Peter Hecht",
    "wof:placetype":"venue"
},
  "geometry": {"coordinates":[8.96232,48.214802],"type":"Point"}
}