{
  "type": "Feature",
  "properties": {
    "iso:country":"DE",
    "sg:address":"Opphofer Str. 15-17",
    "sg:city":"Wuppertal",
    "sg:postcode":"42107",
    "sg:province":"Nordrhein-Westfalen",
    "wof:name":"Potemkin Kg",
    "wof:placetype":"venue"
},
  "geometry": {"coordinates":[7.152257,51.266392],"type":"Point"}
}