{
  "type": "Feature",
  "properties": {
    "iso:country":"DE",
    "sg:address":"Bahnhofstr. 1",
    "sg:city":"Bad Hersfeld",
    "sg:phone":"+49 6621/77229",
    "sg:postcode":"36251",
    "sg:province":"Hessen",
    "wof:name":"V. Mitkoy",
    "wof:placetype":"venue"
},
  "geometry": {"coordinates":[9.7129602432,50.8699264526],"type":"Point"}
}