{
  "type": "Feature",
  "properties": {
    "iso:country":"DE",
    "sg:address":"Boschring 9",
    "sg:city":"Egelsbach",
    "sg:phone":"+49 6103/45170",
    "sg:postcode":"63329",
    "sg:province":"Hessen",
    "wof:name":"Hermann Jochum",
    "wof:placetype":"venue"
},
  "geometry": {"coordinates":[8.668703,49.961723],"type":"Point"}
}