{
  "type": "Feature",
  "properties": {
    "iso:country":"DE",
    "sg:address":"Brunnenstr. 46",
    "sg:city":"Sindelfingen",
    "sg:phone":"+49 7031/382413",
    "sg:postcode":"71069",
    "sg:province":"Baden-W\u00fcrttemberg",
    "wof:name":"Hotel-pension Krone",
    "wof:placetype":"venue"
},
  "geometry": {"coordinates":[8.9621353149,48.7255401611],"type":"Point"}
}