{
  "type": "Feature",
  "properties": {
    "iso:country":"DE",
    "sg:address":"Breite Str. 32",
    "sg:city":"Gro\u00dfostheim",
    "sg:phone":"+49 6026/8447",
    "sg:postcode":"63762",
    "sg:province":"Bayern",
    "wof:name":"Seniorentagespflegest\u00e4tte Des Caritasverbandes",
    "wof:placetype":"venue"
},
  "geometry": {"coordinates":[9.075013,49.91861],"type":"Point"}
}