{
  "type": "Feature",
  "properties": {
    "iso:country":"DE",
    "sg:address":"Illertstr. 16",
    "sg:city":"Viernheim",
    "sg:phone":"+49 6204/74426",
    "sg:postcode":"68519",
    "sg:province":"Hessen",
    "wof:name":"Ilse Mandel",
    "wof:placetype":"venue"
},
  "geometry": {"coordinates":[8.5730600357,49.5426139832],"type":"Point"}
}