{
  "type": "Feature",
  "properties": {
    "iso:country":"DE",
    "sg:address":"Vormwalder Str. 16",
    "sg:city":"Hilchenbach",
    "sg:phone":"+49 2733/4044",
    "sg:postcode":"57271",
    "sg:province":"Nordrhein-Westfalen",
    "wof:name":"Pension G. Heide",
    "wof:placetype":"venue"
},
  "geometry": {"coordinates":[8.1250648499,50.9911956787],"type":"Point"}
}