{
  "type": "Feature",
  "properties": {
    "iso:country":"DE",
    "sg:address":"Getzelauer Str.",
    "sg:city":"Leipzig",
    "sg:phone":"+49 341/3383735",
    "sg:postcode":"04279",
    "sg:province":"Sachsen",
    "wof:name":"Zur W\u00fcrze",
    "wof:placetype":"venue"
},
  "geometry": {"coordinates":[12.4025201797,51.2858200073],"type":"Point"}
}