{
  "type": "Feature",
  "properties": {
    "iso:country":"DE",
    "sg:address":"Neustadt 59",
    "sg:city":"Gr\u00fcnberg",
    "sg:phone":"+49 6401/903100",
    "sg:postcode":"35305",
    "sg:province":"Hessen",
    "wof:name":"Erwin Keller",
    "wof:placetype":"venue"
},
  "geometry": {"coordinates":[8.961312294,50.5881614685],"type":"Point"}
}