{
  "type": "Feature",
  "properties": {
    "iso:country":"DE",
    "sg:address":"Albtalstr. 58",
    "sg:city":"Malsch",
    "sg:phone":"+49 7204/225",
    "sg:postcode":"76316",
    "sg:province":"Baden-W\u00fcrttemberg",
    "wof:name":"B\u00fccherei V\u00f6lkersbach",
    "wof:placetype":"venue"
},
  "geometry": {"coordinates":[8.390798,48.871681],"type":"Point"}
}