{
  "type": "Feature",
  "properties": {
    "iso:country":"DE",
    "sg:address":"Moosstr. 8",
    "sg:city":"Starnberg",
    "sg:phone":"+49 4952/345051",
    "sg:postcode":"82319",
    "sg:province":"Bayern",
    "wof:name":"Internationale Spedition F W Harre Gmbh & Co Kg",
    "wof:placetype":"venue"
},
  "geometry": {"coordinates":[8.9734611511,51.8377685547],"type":"Point"}
}