{
  "type": "Feature",
  "properties": {
    "iso:country":"DE",
    "sg:address":"Daimlerstr. 10",
    "sg:city":"Riedlingen",
    "sg:phone":"+49 7371/93370",
    "sg:postcode":"88499",
    "sg:province":"Baden-W\u00fcrttemberg",
    "wof:name":"List-bierer Gmbh",
    "wof:placetype":"venue"
},
  "geometry": {"coordinates":[9.4999370575,48.1536216736],"type":"Point"}
}