{
  "type": "Feature",
  "properties": {
    "iso:country":"DE",
    "sg:address":"Bergstr. 6",
    "sg:city":"Waffenbrunn",
    "sg:phone":"+49 9971/20474",
    "sg:postcode":"93494",
    "sg:province":"Bayern",
    "wof:name":"Franz Dankerl Ingenieur",
    "wof:placetype":"venue"
},
  "geometry": {"coordinates":[12.661863327,49.2606620789],"type":"Point"}
}