{
  "type": "Feature",
  "properties": {
    "iso:country":"DE",
    "sg:address":"Breitscheidstr. 45",
    "sg:city":"Dresden",
    "sg:phone":"+49 351/2527462",
    "sg:postcode":"01237",
    "sg:province":"Sachsen",
    "wof:name":"M. Fleischer",
    "wof:placetype":"venue"
},
  "geometry": {"coordinates":[13.810812,51.01432],"type":"Point"}
}