{
  "type": "Feature",
  "properties": {
    "iso:country":"DE",
    "sg:address":"Klusriede 16A",
    "sg:city":"Langenhagen",
    "sg:postcode":"30851",
    "sg:province":"Niedersachsen",
    "wof:name":"Carsten Skoruppa",
    "wof:placetype":"venue"
},
  "geometry": {"coordinates":[9.7375202179,52.4277687073],"type":"Point"}
}