{
  "type": "Feature",
  "properties": {
    "iso:country":"DE",
    "sg:address":"K\u00f6penicker Str. 36",
    "sg:city":"Berlin",
    "sg:postcode":"10179",
    "sg:province":"Berlin",
    "wof:name":"Gfw Gesellschaft F\u00fcr Waggon- Leasing Mbh & Co.",
    "wof:placetype":"venue"
},
  "geometry": {"coordinates":[13.4264917374,52.5082855225],"type":"Point"}
}