{
  "type": "Feature",
  "properties": {
    "iso:country":"DE",
    "sg:address":"Buchholzstr. 3",
    "sg:city":"Bonn",
    "sg:phone":"+49 228/283327",
    "sg:postcode":"53127",
    "sg:province":"Nordrhein-Westfalen",
    "wof:name":"Kaisers Tengelmann Ag",
    "wof:placetype":"venue"
},
  "geometry": {"coordinates":[7.0807452202,50.6975288391],"type":"Point"}
}