{
  "type": "Feature",
  "properties": {
    "iso:country":"DE",
    "sg:address":"Schwalbacher Str. 88",
    "sg:city":"Eltville",
    "sg:phone":"+49 6123/2222",
    "sg:postcode":"65343",
    "sg:province":"Hessen",
    "wof:name":"Rosen-m\u00fcller",
    "wof:placetype":"venue"
},
  "geometry": {"coordinates":[8.1167736053,50.0357933044],"type":"Point"}
}