{
  "type": "Feature",
  "properties": {
    "iso:country":"DE",
    "sg:address":"Zeppelinstr. 4",
    "sg:city":"Zell",
    "sg:phone":"+49 7164/902227",
    "sg:postcode":"73119",
    "sg:province":"Baden-W\u00fcrttemberg",
    "wof:name":"G. U. K. Frank Gmbh",
    "wof:placetype":"venue"
},
  "geometry": {"coordinates":[9.5705909729,48.6532249451],"type":"Point"}
}