{
  "type": "Feature",
  "properties": {
    "iso:country":"DE",
    "sg:address":"Habsburgerallee 43",
    "sg:city":"Frankfurt",
    "sg:phone":"+49 69/447375",
    "sg:postcode":"60385",
    "sg:province":"Hessen",
    "wof:name":"Madrid",
    "wof:placetype":"venue"
},
  "geometry": {"coordinates":[8.7055387497,50.1200828552],"type":"Point"}
}