{
  "type": "Feature",
  "properties": {
    "iso:country":"DE",
    "sg:address":"Sonnau 10",
    "sg:city":"Starnberg",
    "sg:phone":"+49 8151/746245",
    "sg:postcode":"82319",
    "sg:province":"Bayern",
    "wof:name":"Elfriede Erdle",
    "wof:placetype":"venue"
},
  "geometry": {"coordinates":[11.2774267197,47.9890403748],"type":"Point"}
}