{
  "type": "Feature",
  "properties": {
    "iso:country":"DE",
    "sg:address":"Weberstr. 11",
    "sg:city":"Detmold",
    "sg:phone":"+49 5232/87013",
    "sg:postcode":"32758",
    "sg:province":"Nordrhein-Westfalen",
    "wof:name":"Karl-heinz Hausmann",
    "wof:placetype":"venue"
},
  "geometry": {"coordinates":[8.78668,51.954189],"type":"Point"}
}