{
  "type": "Feature",
  "properties": {
    "iso:country":"DE",
    "sg:address":"Halterner Str. 91",
    "sg:city":"Marl",
    "sg:phone":"+49 2365/84004",
    "sg:postcode":"45770",
    "sg:province":"Nordrhein-Westfalen",
    "wof:name":"Rolf Langer",
    "wof:placetype":"venue"
},
  "geometry": {"coordinates":[7.182052,51.659988],"type":"Point"}
}