{
  "type": "Feature",
  "properties": {
    "iso:country":"DE",
    "sg:address":"Wassertr\u00fcdinger Str. 4",
    "sg:city":"Dinkelsb\u00fchl",
    "sg:phone":"+49 9851/877",
    "sg:postcode":"91550",
    "sg:province":"Bayern",
    "wof:name":"Rainer Z\u00fcrn Rechtsanwalt",
    "wof:placetype":"venue"
},
  "geometry": {"coordinates":[10.3332738876,49.0662384033],"type":"Point"}
}