{
  "type": "Feature",
  "properties": {
    "iso:country":"DE",
    "sg:address":"Schinkelstr. 52",
    "sg:city":"D\u00fcsseldorf",
    "sg:phone":"+49 211/352960",
    "sg:postcode":"40211",
    "sg:province":"Nordrhein-Westfalen",
    "wof:name":"Carl Tolles Kg",
    "wof:placetype":"venue"
},
  "geometry": {"coordinates":[6.7934031487,51.2333259583],"type":"Point"}
}