{
  "type": "Feature",
  "properties": {
    "iso:country":"DE",
    "sg:address":"An der Vogelrute 50",
    "sg:city":"Euskirchen",
    "sg:phone":"+49 2251/62266",
    "sg:postcode":"53879",
    "sg:province":"Nordrhein-Westfalen",
    "wof:name":"Keymer Gmbh",
    "wof:placetype":"venue"
},
  "geometry": {"coordinates":[6.801232,50.653885],"type":"Point"}
}