{
  "type": "Feature",
  "properties": {
    "iso:country":"DE",
    "sg:address":"K\u00f6ln-Berliner-Str. 87",
    "sg:city":"Dortmund",
    "sg:phone":"+49 231/458959",
    "sg:postcode":"44287",
    "sg:province":"Nordrhein-Westfalen",
    "wof:name":"Weinblatt",
    "wof:placetype":"venue"
},
  "geometry": {"coordinates":[7.5639619827,51.4960708618],"type":"Point"}
}