{
  "type": "Feature",
  "properties": {
    "iso:country":"DE",
    "sg:address":"G\u00fcntzelstra\u00dfe 45",
    "sg:city":"Berlin",
    "sg:phone":"+49 30/2413861",
    "sg:postcode":"10717",
    "sg:province":"Berlin",
    "wof:name":"Meinteehaus",
    "wof:placetype":"venue"
},
  "geometry": {"coordinates":[13.3255167007,52.4911346436],"type":"Point"}
}