{
  "type": "Feature",
  "properties": {
    "iso:country":"DE",
    "sg:address":"Landgrafenstr. 6",
    "sg:city":"Frankfurt",
    "sg:phone":"+49 69/7073207",
    "sg:postcode":"60486",
    "sg:province":"Hessen",
    "wof:name":"Adolf Waltz Gmbh",
    "wof:placetype":"venue"
},
  "geometry": {"coordinates":[8.64728,50.121155],"type":"Point"}
}