{
  "type": "Feature",
  "properties": {
    "iso:country":"DE",
    "sg:address":"Hauptstr. 2",
    "sg:city":"Reichshof",
    "sg:phone":"+49 2297/1310",
    "sg:postcode":"51580",
    "sg:province":"Nordrhein-Westfalen",
    "wof:name":"Gerd Brandt-wagenf\u00fchr",
    "wof:placetype":"venue"
},
  "geometry": {"coordinates":[7.622473,50.983326],"type":"Point"}
}