{
  "type": "Feature",
  "properties": {
    "iso:country":"DE",
    "sg:address":"Molsberger Str. 7",
    "sg:city":"Happurg",
    "sg:phone":"+49 9151/71330",
    "sg:postcode":"91230",
    "sg:province":"Bayern",
    "wof:name":"B\u00e4ckerei Wacker Gmbh",
    "wof:placetype":"venue"
},
  "geometry": {"coordinates":[11.5013771057,49.4751968384],"type":"Point"}
}