{
  "type": "Feature",
  "properties": {
    "iso:country":"DE",
    "sg:address":"Dorfstr. 20",
    "sg:city":"Pl\u00f6\u00dfberg",
    "sg:phone":"+49 9636/347",
    "sg:postcode":"95703",
    "sg:province":"Bayern",
    "wof:name":"Maria Busl",
    "wof:placetype":"venue"
},
  "geometry": {"coordinates":[12.2913093567,49.7937850952],"type":"Point"}
}