{
  "type": "Feature",
  "properties": {
    "iso:country":"DE",
    "sg:address":"Gayernstr. 8",
    "sg:city":"Veringenstadt",
    "sg:phone":"+49 7577/3755",
    "sg:postcode":"72519",
    "sg:province":"Baden-W\u00fcrttemberg",
    "wof:name":"Gustl Greiner",
    "wof:placetype":"venue"
},
  "geometry": {"coordinates":[9.2117958069,48.18491745],"type":"Point"}
}