{
  "type": "Feature",
  "properties": {
    "iso:country":"DE",
    "sg:address":"Voigtwiese 8",
    "sg:city":"Langenhagen",
    "sg:phone":"+49 511/735059",
    "sg:postcode":"30851",
    "sg:province":"Niedersachsen",
    "wof:name":"Renate Barth",
    "wof:placetype":"venue"
},
  "geometry": {"coordinates":[9.7356376648,52.4314002991],"type":"Point"}
}