{
  "type": "Feature",
  "properties": {
    "iso:country":"DE",
    "sg:address":"Schulstr. 55",
    "sg:city":"Sankt Augustin",
    "sg:phone":"+49 2241/334430",
    "sg:postcode":"53757",
    "sg:province":"Nordrhein-Westfalen",
    "wof:name":"Ev. Pfarrb\u00fccherei Niederpleis",
    "wof:placetype":"venue"
},
  "geometry": {"coordinates":[7.209407,50.776325],"type":"Point"}
}