{
  "type": "Feature",
  "properties": {
    "iso:country":"DE",
    "sg:address":"Gontardstr. 1",
    "sg:city":"Potsdam",
    "sg:phone":"+49 331/972762",
    "sg:postcode":"14471",
    "sg:province":"Brandenburg",
    "wof:name":"Rolf Dietz",
    "wof:placetype":"venue"
},
  "geometry": {"coordinates":[13.0147256851,52.3857574463],"type":"Point"}
}