{
  "type": "Feature",
  "properties": {
    "iso:country":"DE",
    "sg:address":"Rabenstein 24",
    "sg:city":"Bayreuth",
    "sg:phone":"+49 921/48693",
    "sg:postcode":"95445",
    "sg:province":"Bayern",
    "wof:name":"M. Und G. Hirz",
    "wof:placetype":"venue"
},
  "geometry": {"coordinates":[11.5557613373,49.944694519],"type":"Point"}
}