{
  "type": "Feature",
  "properties": {
    "iso:country":"DE",
    "sg:address":"Eckernf\u00f6rder Str. 13",
    "sg:city":"B\u00fctzow",
    "sg:postcode":"18246",
    "sg:province":"Mecklenburg-Vorpommern",
    "wof:name":"G\u00fcnter Dyck",
    "wof:placetype":"venue"
},
  "geometry": {"coordinates":[11.954701,53.844624],"type":"Point"}
}