{
  "type": "Feature",
  "properties": {
    "iso:country":"DE",
    "sg:address":"Am H\u00fc\u00dfberg 31",
    "sg:city":"Fl\u00f6rsbachtal",
    "sg:phone":"+49 6057/90000",
    "sg:postcode":"63639",
    "sg:province":"Hessen",
    "wof:name":"Bmi Immobilienberatungs- Gmbh",
    "wof:placetype":"venue"
},
  "geometry": {"coordinates":[9.4883575439,50.1270675659],"type":"Point"}
}