{
  "type": "Feature",
  "properties": {
    "iso:country":"DE",
    "sg:address":"Untere Torstr. 3",
    "sg:city":"Bad Rappenau",
    "sg:phone":"+49 7066/8125",
    "sg:postcode":"74906",
    "sg:province":"Baden-W\u00fcrttemberg",
    "wof:name":"Ev. Pfarramt Gem. F\u00fcrfeld",
    "wof:placetype":"venue"
},
  "geometry": {"coordinates":[9.0574645996,49.2094345093],"type":"Point"}
}