{
  "type": "Feature",
  "properties": {
    "iso:country":"DE",
    "sg:address":"Fridolin-Amann-Str. 2",
    "sg:city":"Salem",
    "sg:phone":"+49 7553/279",
    "sg:postcode":"88682",
    "sg:province":"Baden-W\u00fcrttemberg",
    "wof:name":"Kath. Pfarramt St. Peter Und Paul",
    "wof:placetype":"venue"
},
  "geometry": {"coordinates":[9.3094911575,47.7613258362],"type":"Point"}
}