{
  "type": "Feature",
  "properties": {
    "iso:country":"DE",
    "sg:address":"Mauerstr. 10",
    "sg:city":"Gevelsberg",
    "sg:phone":"+49 2332/4539",
    "sg:postcode":"58285",
    "sg:province":"Nordrhein-Westfalen",
    "wof:name":"Manfred Hellk\u00f6tter Steuerberater",
    "wof:placetype":"venue"
},
  "geometry": {"coordinates":[7.3393650055,51.3183822632],"type":"Point"}
}