{
  "type": "Feature",
  "properties": {
    "iso:country":"DE",
    "sg:address":"Kaiserallee 17",
    "sg:city":"Berlin",
    "sg:postcode":"12277",
    "sg:province":"Berlin",
    "wof:name":"Allround Capital Management Gmbh",
    "wof:placetype":"venue"
},
  "geometry": {"coordinates":[13.370839119,52.4179039001],"type":"Point"}
}