{
  "type": "Feature",
  "properties": {
    "iso:country":"DE",
    "sg:address":"Lange Str. 22",
    "sg:city":"Zeven",
    "sg:phone":"+49 4281/2407",
    "sg:postcode":"27404",
    "sg:province":"Niedersachsen",
    "wof:name":"Hammer Fachm\u00e4rkte F\u00fcr Heimausstattung Gmbh & Co. Kg",
    "wof:placetype":"venue"
},
  "geometry": {"coordinates":[9.2779684067,53.293346405],"type":"Point"}
}