{
  "type": "Feature",
  "properties": {
    "iso:country":"DE",
    "sg:address":"Friedhofstr. 82",
    "sg:city":"Kehl",
    "sg:phone":"+49 7851/76672",
    "sg:postcode":"77694",
    "sg:province":"Baden-W\u00fcrttemberg",
    "wof:name":"Hans Birk",
    "wof:placetype":"venue"
},
  "geometry": {"coordinates":[7.828456,48.565884],"type":"Point"}
}