{
  "type": "Feature",
  "properties": {
    "iso:country":"DE",
    "sg:address":"Danziger Str. 78",
    "sg:city":"Wiesbaden",
    "sg:phone":"+49 611/543960",
    "sg:postcode":"65191",
    "sg:province":"Hessen",
    "wof:name":"O. Kyriakidis-brandt Immobilienmakler",
    "wof:placetype":"venue"
},
  "geometry": {"coordinates":[8.2602891922,50.0968666077],"type":"Point"}
}