{
  "type": "Feature",
  "properties": {
    "iso:country":"DE",
    "sg:address":"Welterstr. 57",
    "sg:city":"Siegen",
    "sg:postcode":"57072",
    "sg:province":"Nordrhein-Westfalen",
    "wof:name":"Virtual Solution Gmbh & Co. Kg",
    "wof:placetype":"venue"
},
  "geometry": {"coordinates":[8.0319375992,50.8868675232],"type":"Point"}
}