{
  "type": "Feature",
  "properties": {
    "iso:country":"DE",
    "sg:address":"Gather Landstr. 51",
    "sg:city":"Nieb\u00fcll",
    "sg:phone":"+49 4661/1370",
    "sg:postcode":"25899",
    "sg:province":"Schleswig-Holstein",
    "wof:name":"Karlheinz Voss Masseur",
    "wof:placetype":"venue"
},
  "geometry": {"coordinates":[8.837523,54.791557],"type":"Point"}
}