{
  "type": "Feature",
  "properties": {
    "iso:country":"DE",
    "sg:address":"Hochholzweg 24",
    "sg:city":"Stuttgart",
    "sg:phone":"+49 711/442271",
    "sg:postcode":"70619",
    "sg:province":"Baden-W\u00fcrttemberg",
    "wof:name":"Walter Schnitzer",
    "wof:placetype":"venue"
},
  "geometry": {"coordinates":[9.227350235,48.7425880432],"type":"Point"}
}