{
  "type": "Feature",
  "properties": {
    "iso:country":"DE",
    "sg:address":"Johannes-Brahms-Platz 9",
    "sg:city":"Hamburg",
    "sg:phone":"+49 40/35713593",
    "sg:postcode":"20355",
    "sg:province":"Hamburg",
    "wof:name":"Michael Wulff Rechtsanwalt",
    "wof:placetype":"venue"
},
  "geometry": {"coordinates":[9.980260849,53.5549736023],"type":"Point"}
}