{
  "type": "Feature",
  "properties": {
    "iso:country":"DE",
    "sg:address":"Waldweg 3 b",
    "sg:city":"R\u00f6vershagen",
    "sg:phone":"+49 381/659430",
    "sg:postcode":"18182",
    "sg:province":"Mecklenburg-Vorpommern",
    "wof:name":"Elta Engineering Gmbh",
    "wof:placetype":"venue"
},
  "geometry": {"coordinates":[12.261759758,54.1820602417],"type":"Point"}
}