{
  "type": "Feature",
  "properties": {
    "iso:country":"DE",
    "sg:address":"Krumme Str. 70",
    "sg:city":"Berlin",
    "sg:postcode":"10627",
    "sg:province":"Berlin",
    "wof:name":"Udo Sch\u00fcbbe Bettenhandel Gmbh",
    "wof:placetype":"venue"
},
  "geometry": {"coordinates":[13.3096828461,52.5110473633],"type":"Point"}
}