{
  "type": "Feature",
  "properties": {
    "iso:country":"DE",
    "sg:address":"Albertinenstr. 18",
    "sg:city":"Berlin",
    "sg:phone":"+49 30/25700396",
    "sg:postcode":"13086",
    "sg:province":"Berlin",
    "wof:name":"G-plan Gmbh",
    "wof:placetype":"venue"
},
  "geometry": {"coordinates":[13.459661,52.552773],"type":"Point"}
}