{
  "type": "Feature",
  "properties": {
    "iso:country":"DE",
    "sg:address":"Elisabethenstr. 49",
    "sg:city":"Rodalben",
    "sg:phone":"+49 6331/16733",
    "sg:postcode":"66976",
    "sg:province":"Rheinland-Pfalz",
    "wof:name":"F. Blanz",
    "wof:placetype":"venue"
},
  "geometry": {"coordinates":[7.637993,49.243065],"type":"Point"}
}