{
  "type": "Feature",
  "properties": {
    "iso:country":"DE",
    "sg:address":"Marienstr. 9-11",
    "sg:city":"Hannover",
    "sg:phone":"+49 511/3631834",
    "sg:postcode":"30171",
    "sg:province":"Niedersachsen",
    "wof:name":"Foto-sewing Gmbh",
    "wof:placetype":"venue"
},
  "geometry": {"coordinates":[9.7451868057,52.3691825867],"type":"Point"}
}