{
  "type": "Feature",
  "properties": {
    "iso:country":"DE",
    "sg:address":"Birnbaumstr. 3",
    "sg:city":"Dettingen",
    "sg:phone":"+49 7123/7688",
    "sg:postcode":"72581",
    "sg:province":"Baden-W\u00fcrttemberg",
    "wof:name":"Fritz Planung Gmbh",
    "wof:placetype":"venue"
},
  "geometry": {"coordinates":[9.3538351059,48.528629303],"type":"Point"}
}