{
  "type": "Feature",
  "properties": {
    "iso:country":"DE",
    "sg:address":"Cecilienallee 68",
    "sg:city":"D\u00fcsseldorf",
    "sg:phone":"+49 211/439290",
    "sg:postcode":"40474",
    "sg:province":"Nordrhein-Westfalen",
    "wof:name":"Tse Europe Gmbh",
    "wof:placetype":"venue"
},
  "geometry": {"coordinates":[6.7640190125,51.2478141785],"type":"Point"}
}