{
  "type": "Feature",
  "properties": {
    "iso:country":"DE",
    "sg:address":"Julius-Bauser-Str. 34",
    "sg:city":"Empfingen",
    "sg:phone":"+49 7485/99970",
    "sg:postcode":"72186",
    "sg:province":"Baden-W\u00fcrttemberg",
    "wof:name":"Ahorn Sportswear Textilien Gmbh",
    "wof:placetype":"venue"
},
  "geometry": {"coordinates":[8.715703,48.3979],"type":"Point"}
}