{
  "type": "Feature",
  "properties": {
    "iso:country":"DE",
    "sg:address":"Laerer Landweg 187",
    "sg:city":"M\u00fcnster",
    "sg:phone":"+49 251/311514",
    "sg:postcode":"48155",
    "sg:province":"Nordrhein-Westfalen",
    "wof:name":"Johannes Kunz",
    "wof:placetype":"venue"
},
  "geometry": {"coordinates":[7.67069,51.95163],"type":"Point"}
}