{
  "type": "Feature",
  "properties": {
    "iso:country":"DE",
    "sg:address":"Ostackerweg 45",
    "sg:city":"Duisburg",
    "sg:phone":"+49 203/463237",
    "sg:postcode":"47139",
    "sg:province":"Nordrhein-Westfalen",
    "wof:name":"Spickermann",
    "wof:placetype":"venue"
},
  "geometry": {"coordinates":[6.7460398674,51.4823455811],"type":"Point"}
}