{
  "type": "Feature",
  "properties": {
    "iso:country":"DE",
    "sg:address":"Queichstr. 10",
    "sg:city":"Albersweiler",
    "sg:phone":"+49 6345/1619",
    "sg:postcode":"76857",
    "sg:province":"Rheinland-Pfalz",
    "wof:name":"Irene Schuller",
    "wof:placetype":"venue"
},
  "geometry": {"coordinates":[8.0315380096,49.2180252075],"type":"Point"}
}