{
  "type": "Feature",
  "properties": {
    "iso:country":"DE",
    "sg:address":"Eichelgasse 1",
    "sg:city":"L\u00f6bau",
    "sg:phone":"+49 3585/402062",
    "sg:postcode":"02708",
    "sg:province":"Sachsen",
    "wof:name":"Franz Pehta",
    "wof:placetype":"venue"
},
  "geometry": {"coordinates":[14.6667118073,51.0949821472],"type":"Point"}
}