{
  "type": "Feature",
  "properties": {
    "iso:country":"DE",
    "sg:address":"Herrenstr. 17",
    "sg:city":"Burgst\u00e4dt",
    "sg:phone":"+49 3724/3436",
    "sg:postcode":"09217",
    "sg:province":"Sachsen",
    "wof:name":"Helmut Haase",
    "wof:placetype":"venue"
},
  "geometry": {"coordinates":[12.8041706085,50.9197044373],"type":"Point"}
}