{
  "type": "Feature",
  "properties": {
    "iso:country":"DE",
    "sg:address":"Schulstr. 31",
    "sg:city":"Lahnstein",
    "sg:phone":"+49 2621/50159",
    "sg:postcode":"56112",
    "sg:province":"Rheinland-Pfalz",
    "wof:name":"G\u00fcnther Gerhardt",
    "wof:placetype":"venue"
},
  "geometry": {"coordinates":[7.6086540222,50.3000450134],"type":"Point"}
}