{
  "type": "Feature",
  "properties": {
    "iso:country":"DE",
    "sg:address":"Twietbergstr. 53",
    "sg:city":"Itzehoe",
    "sg:phone":"+49 4821/42060",
    "sg:postcode":"25524",
    "sg:province":"Schleswig-Holstein",
    "wof:name":"Ev. Pfarramt St. Jakobi",
    "wof:placetype":"venue"
},
  "geometry": {"coordinates":[9.5178098679,53.9432601929],"type":"Point"}
}