{
  "type": "Feature",
  "properties": {
    "iso:country":"DE",
    "sg:address":"Kurf\u00fcrstendamm 21",
    "sg:city":"Berlin",
    "sg:phone":"+49 30/88753810",
    "sg:postcode":"10719",
    "sg:province":"Berlin",
    "wof:name":"Via Bona Reisen Gmbh",
    "wof:placetype":"venue"
},
  "geometry": {"coordinates":[13.3304080963,52.5037727356],"type":"Point"}
}