{
  "type": "Feature",
  "properties": {
    "iso:country":"DE",
    "sg:address":"Josef-Frankl-Str. 52",
    "sg:city":"M\u00fcnchen",
    "sg:phone":"+49 89/3133343",
    "sg:postcode":"80995",
    "sg:province":"Bayern",
    "wof:name":"Evi Dziki",
    "wof:placetype":"venue"
},
  "geometry": {"coordinates":[11.53127,48.215271],"type":"Point"}
}