{
  "type": "Feature",
  "properties": {
    "iso:country":"DE",
    "sg:address":"Hebridenstr. 44",
    "sg:city":"Bielefeld",
    "sg:phone":"+49 521/771484",
    "sg:postcode":"33729",
    "sg:province":"Nordrhein-Westfalen",
    "wof:name":"Metallbau Bernd Grote Gmbh & Co. Kg",
    "wof:placetype":"venue"
},
  "geometry": {"coordinates":[8.6209182739,52.0618515015],"type":"Point"}
}