{
  "type": "Feature",
  "properties": {
    "iso:country":"DE",
    "sg:address":"Hauptstr. 66",
    "sg:city":"Bokel",
    "sg:phone":"+49 4748/1469",
    "sg:postcode":"27616",
    "sg:province":"Niedersachsen",
    "wof:name":"Fredi Breden",
    "wof:placetype":"venue"
},
  "geometry": {"coordinates":[8.769149,53.392414],"type":"Point"}
}