{
  "type": "Feature",
  "properties": {
    "iso:country":"DE",
    "sg:address":"Zirbenweg 46",
    "sg:city":"Waltenhofen",
    "sg:postcode":"87448",
    "sg:province":"Bayern",
    "wof:name":"Ambulanter Pflegedienst Hein Gmbh",
    "wof:placetype":"venue"
},
  "geometry": {"coordinates":[10.3136548996,47.6863021851],"type":"Point"}
}