{
  "type": "Feature",
  "properties": {
    "iso:country":"DE",
    "sg:address":"Jakobstrasse 10",
    "sg:city":"Kornwestheim",
    "sg:phone":"+49 7154/21874",
    "sg:postcode":"70806",
    "sg:province":"Baden-W\u00fcrttemberg",
    "wof:name":"Fahrschule Seiler",
    "wof:placetype":"venue"
},
  "geometry": {"coordinates":[9.1848592758,48.8652458191],"type":"Point"}
}