{
  "type": "Feature",
  "properties": {
    "iso:country":"DE",
    "sg:address":"Olper Str. 1",
    "sg:city":"Siegen",
    "sg:phone":"+49 271/82580",
    "sg:postcode":"57078",
    "sg:province":"Nordrhein-Westfalen",
    "wof:name":"Alfred Richter",
    "wof:placetype":"venue"
},
  "geometry": {"coordinates":[8.010565,50.912987],"type":"Point"}
}