{
  "type": "Feature",
  "properties": {
    "iso:country":"DE",
    "sg:address":"Fuchsbichl 68",
    "sg:city":"Icking",
    "sg:phone":"+49 8178/5698",
    "sg:postcode":"82057",
    "sg:province":"Bayern",
    "wof:name":"Irmhild Walch Krankengymnastin",
    "wof:placetype":"venue"
},
  "geometry": {"coordinates":[11.423904,47.949398],"type":"Point"}
}