{
  "type": "Feature",
  "properties": {
    "iso:country":"DE",
    "sg:address":"Ernst-Hohner-Str. 54-56",
    "sg:city":"Trossingen",
    "sg:phone":"+49 7425/94050",
    "sg:postcode":"78647",
    "sg:province":"Baden-W\u00fcrttemberg",
    "wof:name":"Messner Verwaltungs- Gmbh",
    "wof:placetype":"venue"
},
  "geometry": {"coordinates":[8.627445,48.075584],"type":"Point"}
}