{
  "type": "Feature",
  "properties": {
    "iso:country":"DE",
    "sg:address":"Friedrichstr. 2",
    "sg:city":"Bruchsal",
    "sg:phone":"+49 7251/14229",
    "sg:postcode":"76646",
    "sg:province":"Baden-W\u00fcrttemberg",
    "wof:name":"Restaurant Erbprinz",
    "wof:placetype":"venue"
},
  "geometry": {"coordinates":[8.5982818604,49.1268424988],"type":"Point"}
}