{
  "type": "Feature",
  "properties": {
    "iso:country":"DE",
    "sg:address":"Doppelm\u00fchle 1",
    "sg:city":"Bischofsmais",
    "sg:phone":"+49 9920/669",
    "sg:postcode":"94253",
    "sg:province":"Bayern",
    "wof:name":"Johannes Groschupf",
    "wof:placetype":"venue"
},
  "geometry": {"coordinates":[13.0811328888,48.9181861877],"type":"Point"}
}