{
  "type": "Feature",
  "properties": {
    "iso:country":"DE",
    "sg:address":"Unterensinger Str. 32",
    "sg:city":"N\u00fcrtingen",
    "sg:phone":"+49 7022/62972",
    "sg:postcode":"72622",
    "sg:province":"Baden-W\u00fcrttemberg",
    "wof:name":"Franz B\u00fcrger",
    "wof:placetype":"venue"
},
  "geometry": {"coordinates":[9.352434,48.647873],"type":"Point"}
}