{
  "type": "Feature",
  "properties": {
    "iso:country":"DE",
    "sg:address":"F\u00fcrther Str. 20",
    "sg:city":"N\u00fcrnberg",
    "sg:phone":"+49 911/262407",
    "sg:postcode":"90429",
    "sg:province":"Bayern",
    "wof:name":"Old Bier Bar Eugenie",
    "wof:placetype":"venue"
},
  "geometry": {"coordinates":[11.0603647232,49.4498291016],"type":"Point"}
}