{
  "type": "Feature",
  "properties": {
    "iso:country":"DE",
    "sg:address":"Oberer Kapellberg 41",
    "sg:city":"Hallstadt",
    "sg:postcode":"96103",
    "sg:province":"Bayern",
    "wof:name":"No Wet Abdichtungs Gmbh",
    "wof:placetype":"venue"
},
  "geometry": {"coordinates":[10.860511,49.934429],"type":"Point"}
}