{
  "type": "Feature",
  "properties": {
    "iso:country":"DE",
    "sg:address":"Wasserkunststr. 27 a",
    "sg:city":"Magdeburg",
    "sg:postcode":"39124",
    "sg:province":"Sachsen-Anhalt",
    "wof:name":"Pht Magdeburger Bau Gmbh",
    "wof:placetype":"venue"
},
  "geometry": {"coordinates":[11.650211,52.155117],"type":"Point"}
}