{
  "type": "Feature",
  "properties": {
    "iso:country":"DE",
    "sg:address":"In der Au 7",
    "sg:city":"Sternenfels",
    "sg:phone":"+49 7043/920500",
    "sg:postcode":"75447",
    "sg:province":"Baden-W\u00fcrttemberg",
    "wof:name":"Dietmar Appich E. K.",
    "wof:placetype":"venue"
},
  "geometry": {"coordinates":[8.8503856659,49.0317153931],"type":"Point"}
}