{
  "type": "Feature",
  "properties": {
    "iso:country":"DE",
    "sg:address":"Lingener Str. 2",
    "sg:city":"Meppen",
    "sg:phone":"+49 5931/12814",
    "sg:postcode":"49716",
    "sg:province":"Niedersachsen",
    "wof:name":"Hotel Dom",
    "wof:placetype":"venue"
},
  "geometry": {"coordinates":[7.290954113,52.688167572],"type":"Point"}
}