{
  "type": "Feature",
  "properties": {
    "iso:country":"DE",
    "sg:address":"Goldbachstr. 30",
    "sg:city":"Bernkastel-Kues",
    "sg:phone":"+49 6531/3541",
    "sg:postcode":"54470",
    "sg:province":"Rheinland-Pfalz",
    "wof:name":"Helmut Kr\u00f6hner",
    "wof:placetype":"venue"
},
  "geometry": {"coordinates":[7.0424118042,49.9093856812],"type":"Point"}
}