{
  "type": "Feature",
  "properties": {
    "iso:country":"DE",
    "sg:address":"Ludwig-Winter-Str. 2",
    "sg:city":"Braunschweig",
    "sg:phone":"+49 531/28520",
    "sg:postcode":"38120",
    "sg:province":"Niedersachsen",
    "wof:name":"Bibliothek Der Fachhochschule Braunschweig",
    "wof:placetype":"venue"
},
  "geometry": {"coordinates":[10.49004,52.249573],"type":"Point"}
}