{
  "type": "Feature",
  "properties": {
    "iso:country":"DE",
    "sg:address":"Gai\u00dfacher Str. 69",
    "sg:city":"Bad T\u00f6lz",
    "sg:phone":"+49 8041/78290",
    "sg:postcode":"83646",
    "sg:province":"Bayern",
    "wof:name":"Anton Lindmayr Steuerberater",
    "wof:placetype":"venue"
},
  "geometry": {"coordinates":[11.5732164383,47.7557220459],"type":"Point"}
}