{
  "type": "Feature",
  "properties": {
    "iso:country":"DE",
    "sg:address":"Max-Jehn-Str. 22",
    "sg:city":"G\u00f6\u00dfnitz",
    "sg:phone":"+49 34493/22243",
    "sg:postcode":"04639",
    "sg:province":"Th\u00fcringen",
    "wof:name":"Sbh-schm\u00f6llner Bau-holz Gmbh",
    "wof:placetype":"venue"
},
  "geometry": {"coordinates":[12.431591,50.895454],"type":"Point"}
}