{
  "type": "Feature",
  "properties": {
    "iso:country":"DE",
    "sg:address":"Am Galgenberg 1",
    "sg:city":"Bad Wildungen",
    "sg:phone":"+49 5621/4583",
    "sg:postcode":"34537",
    "sg:province":"Hessen",
    "wof:name":"Ernst Mogk",
    "wof:placetype":"venue"
},
  "geometry": {"coordinates":[9.145,51.114445],"type":"Point"}
}