{
  "type": "Feature",
  "properties": {
    "iso:country":"DE",
    "sg:address":"Am Falkenberg 105",
    "sg:city":"Berlin",
    "sg:postcode":"12524",
    "sg:province":"Berlin",
    "wof:name":"Arcos Verwaltung Und Management Gmbh",
    "wof:placetype":"venue"
},
  "geometry": {"coordinates":[13.563344,52.413559],"type":"Point"}
}