{
  "type": "Feature",
  "properties": {
    "iso:country":"DE",
    "sg:address":"Bl\u00fcttenstr. 2",
    "sg:city":"L\u00fcbbecke",
    "sg:phone":"+49 5741/20880",
    "sg:postcode":"32312",
    "sg:province":"Nordrhein-Westfalen",
    "wof:name":"Wittekind-apotheke",
    "wof:placetype":"venue"
},
  "geometry": {"coordinates":[8.61553,52.303768],"type":"Point"}
}