{
  "type": "Feature",
  "properties": {
    "iso:country":"DE",
    "sg:address":"Ulzburger Str 572",
    "sg:city":"Norderstedt",
    "sg:phone":"+49 40/53309647",
    "sg:postcode":"22844",
    "sg:province":"Schleswig-Holstein",
    "wof:name":"Dah \u00ae - Deutsch/asiatisches Handelshaus Fischer & Guo Im- Export Gbr",
    "wof:placetype":"venue"
},
  "geometry": {"coordinates":[9.9956274033,53.7422142029],"type":"Point"}
}