{
  "type": "Feature",
  "properties": {
    "iso:country":"DE",
    "sg:address":"Corneliusstr. 7",
    "sg:city":"Frankfurt",
    "sg:postcode":"60325",
    "sg:province":"Hessen",
    "wof:name":"Emopol Flux- Und Oberfl\u00e4chentechnik Gmbh",
    "wof:placetype":"venue"
},
  "geometry": {"coordinates":[8.657893,50.116882],"type":"Point"}
}