{
  "type": "Feature",
  "properties": {
    "iso:country":"DE",
    "sg:address":"Bergstr 2a",
    "sg:city":"Hersbruck",
    "sg:phone":"+49 9151/862454",
    "sg:postcode":"91217",
    "sg:province":"Bayern",
    "wof:name":"Ci Pencils",
    "wof:placetype":"venue"
},
  "geometry": {"coordinates":[11.408103,49.511036],"type":"Point"}
}