{
  "type": "Feature",
  "properties": {
    "iso:country":"DE",
    "sg:address":"Ottostr. 4",
    "sg:city":"Erkrath",
    "sg:phone":"+49 211/243323",
    "sg:postcode":"40699",
    "sg:province":"Nordrhein-Westfalen",
    "wof:name":"Axel Pragal Rechtsanwalt",
    "wof:placetype":"venue"
},
  "geometry": {"coordinates":[6.9078121185,51.2258110046],"type":"Point"}
}