{
  "type": "Feature",
  "properties": {
    "iso:country":"DE",
    "sg:address":"Auf den Scheffeln 5",
    "sg:city":"Bochum",
    "sg:phone":"+49 234/288441",
    "sg:postcode":"44894",
    "sg:province":"Nordrhein-Westfalen",
    "wof:name":"Carsten Dick",
    "wof:placetype":"venue"
},
  "geometry": {"coordinates":[7.301443,51.483227],"type":"Point"}
}