{
  "type": "Feature",
  "properties": {
    "iso:country":"DE",
    "sg:address":"Zeiler Str. 35",
    "sg:city":"Ha\u00dffurt",
    "sg:phone":"+49 9521/2137",
    "sg:postcode":"97437",
    "sg:province":"Bayern",
    "wof:name":"S. Und M. Wolfschmidt Ohg Eisenwaren",
    "wof:placetype":"venue"
},
  "geometry": {"coordinates":[10.5202550888,50.0309448242],"type":"Point"}
}