{
  "type": "Feature",
  "properties": {
    "iso:country":"DE",
    "sg:address":"Himmelstadter Str. 8",
    "sg:city":"Zellingen",
    "sg:phone":"+49 9364/3442",
    "sg:postcode":"97225",
    "sg:province":"Bayern",
    "wof:name":"Christiane R\u00f6der",
    "wof:placetype":"venue"
},
  "geometry": {"coordinates":[9.8133983612,49.9010238647],"type":"Point"}
}