{
  "type": "Feature",
  "properties": {
    "iso:country":"DE",
    "sg:address":"Werth 100",
    "sg:city":"Wuppertal",
    "sg:phone":"+49 202/558463",
    "sg:postcode":"42275",
    "sg:province":"Nordrhein-Westfalen",
    "wof:name":"Reiseb\u00fcro Dr. Tigges Gmbh",
    "wof:placetype":"venue"
},
  "geometry": {"coordinates":[7.2058877945,51.2724723816],"type":"Point"}
}