{
  "type": "Feature",
  "properties": {
    "iso:country":"DE",
    "sg:address":"Glattbacher Str. 1",
    "sg:city":"Aschaffenburg",
    "sg:phone":"+49 6021/460967",
    "sg:postcode":"63741",
    "sg:province":"Bayern",
    "wof:name":"Restaurant Zur Gem\u00fctlichkeit",
    "wof:placetype":"venue"
},
  "geometry": {"coordinates":[9.1476449966,49.9821395874],"type":"Point"}
}