{
  "type": "Feature",
  "properties": {
    "iso:country":"DE",
    "sg:address":"Schulstr. 13",
    "sg:city":"Titz",
    "sg:phone":"+49 2463/8191",
    "sg:postcode":"52445",
    "sg:province":"Nordrhein-Westfalen",
    "wof:name":"Print-service Vertriebsgesellschaft",
    "wof:placetype":"venue"
},
  "geometry": {"coordinates":[6.428946,51.003311],"type":"Point"}
}