{
  "type": "Feature",
  "properties": {
    "iso:country":"DE",
    "sg:address":"Knooper Weg 175",
    "sg:city":"Kiel",
    "sg:phone":"+49 431/8886721",
    "sg:postcode":"24118",
    "sg:province":"Schleswig-Holstein",
    "wof:name":"Siegfried J. Exner Rechtsanwalt",
    "wof:placetype":"venue"
},
  "geometry": {"coordinates":[10.1320514679,54.3373603821],"type":"Point"}
}