{
  "type": "Feature",
  "properties": {
    "iso:country":"DE",
    "sg:address":"Hauptstr. 33",
    "sg:city":"Gehofen",
    "sg:phone":"+49 3466/320707",
    "sg:postcode":"06571",
    "sg:province":"Th\u00fcringen",
    "wof:name":"Dachdeckerbetrieb Thiele Gmbh",
    "wof:placetype":"venue"
},
  "geometry": {"coordinates":[11.325095,51.322872],"type":"Point"}
}