{
  "type": "Feature",
  "properties": {
    "iso:country":"DE",
    "sg:address":"L\u00fcbecker Str. 135",
    "sg:city":"Hamburg",
    "sg:phone":"+49 40/2504414",
    "sg:postcode":"22087",
    "sg:province":"Hamburg",
    "wof:name":"E. M\u00fcller Anlageberater",
    "wof:placetype":"venue"
},
  "geometry": {"coordinates":[10.0335931778,53.5636405945],"type":"Point"}
}