{
  "type": "Feature",
  "properties": {
    "iso:country":"DE",
    "sg:address":"Mainzer Str. 48",
    "sg:city":"Nierstein",
    "sg:phone":"+49 6133/5314",
    "sg:postcode":"55283",
    "sg:province":"Rheinland-Pfalz",
    "wof:name":"Franz-karl Schmitt",
    "wof:placetype":"venue"
},
  "geometry": {"coordinates":[8.3413419724,49.876499176],"type":"Point"}
}