{
  "type": "Feature",
  "properties": {
    "iso:country":"DE",
    "sg:address":"Am Buchweg 4",
    "sg:city":"Niederwerrn",
    "sg:phone":"+49 9726/2001",
    "sg:postcode":"97464",
    "sg:province":"Bayern",
    "wof:name":"Dieter Mansius",
    "wof:placetype":"venue"
},
  "geometry": {"coordinates":[10.1516675949,50.0694847107],"type":"Point"}
}