{
  "type": "Feature",
  "properties": {
    "iso:country":"DE",
    "sg:address":"Hangweg 5",
    "sg:city":"Neunkirchen",
    "sg:phone":"+49 9134/5811",
    "sg:postcode":"91077",
    "sg:province":"Bayern",
    "wof:name":"Julius Martin",
    "wof:placetype":"venue"
},
  "geometry": {"coordinates":[11.1393184662,49.61195755],"type":"Point"}
}