{
  "type": "Feature",
  "properties": {
    "iso:country":"DE",
    "sg:address":"Voltastr. 6",
    "sg:city":"Dreieich",
    "sg:phone":"+49 6103/939636",
    "sg:postcode":"63303",
    "sg:province":"Hessen",
    "wof:name":"Hartmann Partyservice",
    "wof:placetype":"venue"
},
  "geometry": {"coordinates":[8.701015,50.028969],"type":"Point"}
}