{
  "type": "Feature",
  "properties": {
    "iso:country":"DE",
    "sg:address":"Uhlandstr. 26",
    "sg:city":"Asperg",
    "sg:postcode":"71679",
    "sg:province":"Baden-W\u00fcrttemberg",
    "wof:name":"Gvkf Gesellschaft Zur Vermittl. Kapitalorientierter",
    "wof:placetype":"venue"
},
  "geometry": {"coordinates":[9.1317300797,48.9080696106],"type":"Point"}
}