{
  "type": "Feature",
  "properties": {
    "iso:country":"DE",
    "sg:address":"Igelweg 24",
    "sg:city":"K\u00f6ln",
    "sg:phone":"+49 2203/24522",
    "sg:postcode":"51145",
    "sg:province":"Nordrhein-Westfalen",
    "wof:name":"Wolfgang Dyhr Arrangeur",
    "wof:placetype":"venue"
},
  "geometry": {"coordinates":[7.0815391541,50.8770980835],"type":"Point"}
}