{
  "type": "Feature",
  "properties": {
    "iso:country":"DE",
    "sg:address":"Im M\u00fchlenfelde 41",
    "sg:city":"Pattensen",
    "sg:phone":"+49 5101/6704",
    "sg:postcode":"30982",
    "sg:province":"Niedersachsen",
    "wof:name":"Willi Brandt",
    "wof:placetype":"venue"
},
  "geometry": {"coordinates":[9.757516,52.267666],"type":"Point"}
}