{
  "type": "Feature",
  "properties": {
    "iso:country":"DE",
    "sg:address":"Heuweg 2",
    "sg:city":"Weigendorf",
    "sg:phone":"+49 9154/4840",
    "sg:postcode":"91249",
    "sg:province":"Bayern",
    "wof:name":"L. Wittmann Kunststopferei",
    "wof:placetype":"venue"
},
  "geometry": {"coordinates":[11.5703430176,49.5060157776],"type":"Point"}
}