{
  "type": "Feature",
  "properties": {
    "iso:country":"DE",
    "sg:address":"Leonhardtstr. 17",
    "sg:city":"Berlin",
    "sg:phone":"+49 30/3236091",
    "sg:postcode":"14057",
    "sg:province":"Berlin",
    "wof:name":"Schwarting Immobilien Gmbh",
    "wof:placetype":"venue"
},
  "geometry": {"coordinates":[13.2962741852,52.5053710938],"type":"Point"}
}