{
  "type": "Feature",
  "properties": {
    "iso:country":"DE",
    "sg:address":"Obere Str. 11",
    "sg:city":"Gleichen",
    "sg:phone":"+49 5508/693",
    "sg:postcode":"37130",
    "sg:province":"Niedersachsen",
    "wof:name":"Ernst Vollmer",
    "wof:placetype":"venue"
},
  "geometry": {"coordinates":[10.084948,51.44733],"type":"Point"}
}