{
  "type": "Feature",
  "properties": {
    "iso:country":"DE",
    "sg:address":"Parkstr. 6",
    "sg:city":"Hemer",
    "sg:phone":"+49 4923/7294720",
    "sg:postcode":"58675",
    "sg:province":"Nordrhein-Westfalen",
    "wof:name":"August Schr\u00d6der Gmbh & Co. Kg",
    "wof:placetype":"venue"
},
  "geometry": {"coordinates":[7.763058,51.388412],"type":"Point"}
}