{
  "type": "Feature",
  "properties": {
    "iso:country":"DE",
    "sg:address":"Lehrer K\u00f6hne Stra\u00dfe 9",
    "sg:city":"Papenburg",
    "sg:phone":"+49 4961",
    "sg:postcode":"26871",
    "sg:province":"Niedersachsen",
    "wof:name":"Fahrzeughaus Hans Nee Gmbh",
    "wof:placetype":"venue"
},
  "geometry": {"coordinates":[7.4105839729,53.0641212463],"type":"Point"}
}