{
  "type": "Feature",
  "properties": {
    "iso:country":"DE",
    "sg:address":"Paulinenstr. 4",
    "sg:city":"Friedrichshafen",
    "sg:phone":"+49 7541/24535",
    "sg:postcode":"88046",
    "sg:province":"Baden-W\u00fcrttemberg",
    "wof:name":"Atescier",
    "wof:placetype":"venue"
},
  "geometry": {"coordinates":[9.4812450409,47.6529541016],"type":"Point"}
}