{
  "type": "Feature",
  "properties": {
    "iso:country":"DE",
    "sg:address":"Magdeburger Str. 6",
    "sg:city":"K\u00f6nnern",
    "sg:postcode":"06420",
    "sg:province":"Sachsen-Anhalt",
    "wof:name":"Akzente Gmbh",
    "wof:placetype":"venue"
},
  "geometry": {"coordinates":[11.773589,51.672569],"type":"Point"}
}