{
  "type": "Feature",
  "properties": {
    "iso:country":"DE",
    "sg:address":"Schl\u00fcterstr. 22",
    "sg:city":"Hamburg",
    "sg:postcode":"20146",
    "sg:province":"Hamburg",
    "wof:name":"Gsg Sport- Und Golfhotels Verwaltungs Gmbh",
    "wof:placetype":"venue"
},
  "geometry": {"coordinates":[9.986851,53.566044],"type":"Point"}
}