{
  "type": "Feature",
  "properties": {
    "iso:country":"DE",
    "sg:address":"Maximilianstrasse 11",
    "sg:city":"Trautmannshofen",
    "sg:phone":"+49 9186",
    "sg:postcode":"92283",
    "sg:province":"Bayern",
    "wof:name":"A.b.t. Auto Burger Tuning For Renault",
    "wof:placetype":"venue"
},
  "geometry": {"coordinates":[11.5627670288,49.345916748],"type":"Point"}
}