{
  "type": "Feature",
  "properties": {
    "iso:country":"DE",
    "sg:address":"Bachstr. 4a",
    "sg:city":"Obertshausen",
    "sg:phone":"+49 6104/973082",
    "sg:postcode":"63179",
    "sg:province":"Hessen",
    "wof:name":"Verlag Kommunistischer Und Antifaschistischer Schriften",
    "wof:placetype":"venue"
},
  "geometry": {"coordinates":[8.8680372238,50.0815582275],"type":"Point"}
}