{
  "type": "Feature",
  "properties": {
    "iso:country":"DE",
    "sg:address":"Brunnenstr. 29",
    "sg:city":"Krauchenwies",
    "sg:phone":"+49 7576/1041",
    "sg:postcode":"72505",
    "sg:province":"Baden-W\u00fcrttemberg",
    "wof:name":"Gebr. Stolz Gmbh",
    "wof:placetype":"venue"
},
  "geometry": {"coordinates":[9.22469,48.022812],"type":"Point"}
}