{
  "type": "Feature",
  "properties": {
    "iso:country":"DE",
    "sg:address":"Besendahlweg 1",
    "sg:city":"Friedland",
    "sg:phone":"+49 39601/26342",
    "sg:postcode":"17098",
    "sg:province":"Mecklenburg-Vorpommern",
    "wof:name":"Kunkel",
    "wof:placetype":"venue"
},
  "geometry": {"coordinates":[13.539327,53.658478],"type":"Point"}
}