{
  "type": "Feature",
  "properties": {
    "iso:country":"DE",
    "sg:address":"Saarstra\u00dfe 27",
    "sg:city":"Filderstadt",
    "sg:phone":"+49 711/7799780",
    "sg:postcode":"70794",
    "sg:province":"Baden-W\u00fcrttemberg",
    "wof:name":"Office-system Alexander K\u00d6nig B\u00dcrom\u00d6bel Direkt",
    "wof:placetype":"venue"
},
  "geometry": {"coordinates":[9.2004699707,48.6502304077],"type":"Point"}
}