{
  "type": "Feature",
  "properties": {
    "iso:country":"DE",
    "sg:address":"Karl-Kunger-Str. 66",
    "sg:city":"Berlin",
    "sg:phone":"+49 30/5335764",
    "sg:postcode":"12435",
    "sg:province":"Berlin",
    "wof:name":"Peter Palakowski",
    "wof:placetype":"venue"
},
  "geometry": {"coordinates":[13.4458055496,52.4923324585],"type":"Point"}
}