{
  "type": "Feature",
  "properties": {
    "iso:country":"DE",
    "sg:address":"Weserm\u00fcnder Str. 6",
    "sg:city":"Bremerv\u00f6rde",
    "sg:postcode":"27432",
    "sg:province":"Niedersachsen",
    "wof:name":"M. Zapf Verwaltungs Gmbh",
    "wof:placetype":"venue"
},
  "geometry": {"coordinates":[9.137547,53.489811],"type":"Point"}
}