{
  "type": "Feature",
  "properties": {
    "iso:country":"DE",
    "sg:address":"Bienenstr. 4",
    "sg:city":"Obermoschel",
    "sg:phone":"+49 6362/3467",
    "sg:postcode":"67823",
    "sg:province":"Rheinland-Pfalz",
    "wof:name":"W. Dindorf",
    "wof:placetype":"venue"
},
  "geometry": {"coordinates":[7.771496,49.72794],"type":"Point"}
}