{
  "type": "Feature",
  "properties": {
    "iso:country":"DE",
    "sg:address":"Markt",
    "sg:city":"K\u00f6lleda",
    "sg:phone":"+49 3635/400787",
    "sg:postcode":"99625",
    "sg:province":"Th\u00fcringen",
    "wof:name":"Imbi\u00dfbetrieb Z. Tahonyi",
    "wof:placetype":"venue"
},
  "geometry": {"coordinates":[11.2469949722,51.189994812],"type":"Point"}
}