{
  "type": "Feature",
  "properties": {
    "iso:country":"DE",
    "sg:address":"Bahnhofstr. 6",
    "sg:city":"Schee\u00dfel",
    "sg:phone":"+49 4263/1367",
    "sg:postcode":"27383",
    "sg:province":"Niedersachsen",
    "wof:name":"Modehaus Kruse Gmbh & Co. Kg",
    "wof:placetype":"venue"
},
  "geometry": {"coordinates":[9.4824647903,53.1678352356],"type":"Point"}
}