{
  "type": "Feature",
  "properties": {
    "iso:country":"DE",
    "sg:address":"Hamburger Allee 39",
    "sg:city":"Hannover",
    "sg:postcode":"30161",
    "sg:province":"Niedersachsen",
    "wof:name":"Borgemien & Walka Gmbh",
    "wof:placetype":"venue"
},
  "geometry": {"coordinates":[9.7372617722,52.3822937012],"type":"Point"}
}