{
  "type": "Feature",
  "properties": {
    "iso:country":"DE",
    "sg:address":"Hinseler Hof 5",
    "sg:city":"Essen",
    "sg:phone":"+49 201/583181",
    "sg:postcode":"45277",
    "sg:province":"Nordrhein-Westfalen",
    "wof:name":"Sattmacher Grill",
    "wof:placetype":"venue"
},
  "geometry": {"coordinates":[7.0769929886,51.4286193848],"type":"Point"}
}