{
  "type": "Feature",
  "properties": {
    "iso:country":"DE",
    "sg:address":"Industriestr. 19-21",
    "sg:city":"Dieburg",
    "sg:phone":"+49 4960/7120040",
    "sg:postcode":"64807",
    "sg:province":"Hessen",
    "wof:name":"James Robinson Gmbh",
    "wof:placetype":"venue"
},
  "geometry": {"coordinates":[8.851889,49.907738],"type":"Point"}
}