{
  "type": "Feature",
  "properties": {
    "iso:country":"DE",
    "sg:address":"Mittelh\u00f6fer Str. 17",
    "sg:city":"Felsberg",
    "sg:postcode":"34587",
    "sg:province":"Hessen",
    "wof:name":"Btg Betonfertigteil- Systeme Gmbh",
    "wof:placetype":"venue"
},
  "geometry": {"coordinates":[9.4216690063,51.1346092224],"type":"Point"}
}