{
  "type": "Feature",
  "properties": {
    "iso:country":"DE",
    "sg:address":"Am Wei\u00dfiger Bach 151",
    "sg:city":"Dresden",
    "sg:phone":"+49 351/266190",
    "sg:postcode":"01328",
    "sg:province":"Sachsen",
    "wof:name":"Remmel & Peters Verwaltungs-gmbh",
    "wof:placetype":"venue"
},
  "geometry": {"coordinates":[13.885071,51.069405],"type":"Point"}
}