{
  "type": "Feature",
  "properties": {
    "iso:country":"DE",
    "sg:address":"Marktplatz 10",
    "sg:city":"Zell",
    "sg:phone":"+49 9257/249",
    "sg:postcode":"95239",
    "sg:province":"Bayern",
    "wof:name":"Rotes Ro\u00df",
    "wof:placetype":"venue"
},
  "geometry": {"coordinates":[11.8205299377,50.1334877014],"type":"Point"}
}