{
  "type": "Feature",
  "properties": {
    "iso:country":"DE",
    "sg:address":"Bellevue 58",
    "sg:city":"Hamburg",
    "sg:phone":"+49 40/2708824",
    "sg:postcode":"22301",
    "sg:province":"Hamburg",
    "wof:name":"M. W. Joost Inh. Dr. J\u00fcrgen Blankenburg",
    "wof:placetype":"venue"
},
  "geometry": {"coordinates":[10.003071785,53.5826034546],"type":"Point"}
}