{
  "type": "Feature",
  "properties": {
    "iso:country":"DE",
    "sg:address":"Burgkirchen am Wald 2",
    "sg:city":"T\u00fc\u00dfling",
    "sg:phone":"+49 8633/221",
    "sg:postcode":"84577",
    "sg:province":"Bayern",
    "wof:name":"Katholisches Pfarramt St. Georg",
    "wof:placetype":"venue"
},
  "geometry": {"coordinates":[12.6068782806,48.2087059021],"type":"Point"}
}