{
  "type": "Feature",
  "properties": {
    "iso:country":"DE",
    "sg:address":"Glescher Weg 3",
    "sg:city":"Bedburg",
    "sg:phone":"+49 2272/81985",
    "sg:postcode":"50181",
    "sg:province":"Nordrhein-Westfalen",
    "wof:name":"Astone E Mondello Gmbh",
    "wof:placetype":"venue"
},
  "geometry": {"coordinates":[6.5760240555,50.9812355042],"type":"Point"}
}