{
  "type": "Feature",
  "properties": {
    "iso:country":"DE",
    "sg:address":"Im D\u00f6ppelter 11",
    "sg:city":"Neustadt",
    "sg:phone":"+49 6321/39560",
    "sg:postcode":"67434",
    "sg:province":"Rheinland-Pfalz",
    "wof:name":"Lutz W. Zeter",
    "wof:placetype":"venue"
},
  "geometry": {"coordinates":[8.1320352554,49.3220291138],"type":"Point"}
}