{
  "type": "Feature",
  "properties": {
    "iso:country":"DE",
    "sg:address":"Burgstr. 11",
    "sg:city":"Lahnstein",
    "sg:phone":"+49 2621/2487",
    "sg:postcode":"56112",
    "sg:province":"Rheinland-Pfalz",
    "wof:name":"H. H\u00f6fer Haus- Und K\u00fcchenger\u00e4te",
    "wof:placetype":"venue"
},
  "geometry": {"coordinates":[7.6059799194,50.3002738953],"type":"Point"}
}