{
  "type": "Feature",
  "properties": {
    "iso:country":"DE",
    "sg:address":"Alte Heerstr. 22",
    "sg:city":"Weeze",
    "sg:phone":"+49 2837/8657",
    "sg:postcode":"47652",
    "sg:province":"Nordrhein-Westfalen",
    "wof:name":"Rolladen Engemann Und Goris Gmbh & Co. Kg",
    "wof:placetype":"venue"
},
  "geometry": {"coordinates":[6.201376,51.623524],"type":"Point"}
}