{
  "type": "Feature",
  "properties": {
    "iso:country":"DE",
    "sg:address":"Klausstr. 32",
    "sg:city":"Bad Hersfeld",
    "sg:phone":"+49 6621/2465",
    "sg:postcode":"36251",
    "sg:province":"Hessen",
    "wof:name":"Santana Beteiligungs- Verwaltungs Gmbh",
    "wof:placetype":"venue"
},
  "geometry": {"coordinates":[9.7099809647,50.8692550659],"type":"Point"}
}