{
  "type": "Feature",
  "properties": {
    "iso:country":"DE",
    "sg:address":"Im Heidewinkel 66",
    "sg:city":"Asendorf",
    "sg:phone":"+49 4183/5108",
    "sg:postcode":"21271",
    "sg:province":"Niedersachsen",
    "wof:name":"Gerhard Schulze Ingenieur",
    "wof:placetype":"venue"
},
  "geometry": {"coordinates":[9.9778366089,53.3069458008],"type":"Point"}
}