{
  "type": "Feature",
  "properties": {
    "iso:country":"DE",
    "sg:address":"Kap-Horn-Str. 14",
    "sg:city":"Bremen",
    "sg:phone":"+49 421/612888",
    "sg:postcode":"28237",
    "sg:province":"Bremen",
    "wof:name":"Fa\u00dffabrik Alfred Krogemann Gmbh",
    "wof:placetype":"venue"
},
  "geometry": {"coordinates":[8.7226104736,53.1293716431],"type":"Point"}
}