{
  "type": "Feature",
  "properties": {
    "iso:country":"DE",
    "sg:address":"Leipziger Str. 35-37",
    "sg:city":"Kassel",
    "sg:phone":"+49 561/81090",
    "sg:postcode":"34125",
    "sg:province":"Hessen",
    "wof:name":"Techconsult Gmbh",
    "wof:placetype":"venue"
},
  "geometry": {"coordinates":[9.511547,51.311581],"type":"Point"}
}