{
  "type": "Feature",
  "properties": {
    "iso:country":"DE",
    "sg:address":"Rathausstr. 1a",
    "sg:city":"Saarbr\u00fccken",
    "sg:phone":"+49 6897/75758",
    "sg:postcode":"66125",
    "sg:province":"Saarland",
    "wof:name":"Wolfgang Maringer",
    "wof:placetype":"venue"
},
  "geometry": {"coordinates":[7.0360131264,49.2779846191],"type":"Point"}
}