{
  "type": "Feature",
  "properties": {
    "iso:country":"DE",
    "sg:address":"Lechfeldstr. 92",
    "sg:city":"Landsberg",
    "sg:phone":"+49 8191/42392",
    "sg:postcode":"86899",
    "sg:province":"Bayern",
    "wof:name":"Rauch Ingenieurb\u00fcro",
    "wof:placetype":"venue"
},
  "geometry": {"coordinates":[10.865957,48.061859],"type":"Point"}
}