{
  "type": "Feature",
  "properties": {
    "iso:country":"DE",
    "sg:address":"Storchenstr. 21",
    "sg:city":"Tettnang",
    "sg:phone":"+49 7542/54411",
    "sg:postcode":"88069",
    "sg:province":"Baden-W\u00fcrttemberg",
    "wof:name":"Pizzeria Pronto",
    "wof:placetype":"venue"
},
  "geometry": {"coordinates":[9.5913391113,47.672077179],"type":"Point"}
}