{
  "type": "Feature",
  "properties": {
    "iso:country":"DE",
    "sg:address":"Schrammstr. 61",
    "sg:city":"Zittau",
    "sg:phone":"+49 3583/684631",
    "sg:postcode":"02763",
    "sg:province":"Sachsen",
    "wof:name":"Horschig",
    "wof:placetype":"venue"
},
  "geometry": {"coordinates":[14.80406,50.888515],"type":"Point"}
}