{
  "type": "Feature",
  "properties": {
    "iso:country":"DE",
    "sg:address":"Im Eichengrund 50",
    "sg:city":"Coesfeld",
    "sg:phone":"+49 2541/3337",
    "sg:postcode":"48653",
    "sg:province":"Nordrhein-Westfalen",
    "wof:name":"Kort\u00fcm Textil Fachvertretung Gmbh",
    "wof:placetype":"venue"
},
  "geometry": {"coordinates":[7.1847848892,51.9347877502],"type":"Point"}
}