{
  "type": "Feature",
  "properties": {
    "iso:country":"DE",
    "sg:address":"Bergstr. 30",
    "sg:city":"Klein Rogahn",
    "sg:postcode":"19073",
    "sg:province":"Mecklenburg-Vorpommern",
    "wof:name":"Hermann H. Heik",
    "wof:placetype":"venue"
},
  "geometry": {"coordinates":[11.3232440948,53.5964393616],"type":"Point"}
}