{
  "type": "Feature",
  "properties": {
    "iso:country":"DE",
    "sg:address":"Dorfstr. 29",
    "sg:city":"Rieseby",
    "sg:postcode":"24354",
    "sg:province":"Schleswig-Holstein",
    "wof:name":"Schulhausapotheke Inh. Sigrun Kramer E. Kfr.",
    "wof:placetype":"venue"
},
  "geometry": {"coordinates":[9.815276,54.54211],"type":"Point"}
}