{
  "type": "Feature",
  "properties": {
    "iso:country":"DE",
    "sg:city":"Konstanz",
    "sg:postcode":"78434",
    "sg:province":"Baden-W\u00fcrttemberg",
    "wof:name":"Club Leglover",
    "wof:placetype":"venue"
},
  "geometry": {"coordinates":[9.17206,47.661282],"type":"Point"}
}