{
  "type": "Feature",
  "properties": {
    "iso:country":"DE",
    "sg:address":"Konrad-Adenauer-Str. 15",
    "sg:city":"B\u00fchl",
    "sg:phone":"+49 7223/83858",
    "sg:postcode":"77815",
    "sg:province":"Baden-W\u00fcrttemberg",
    "wof:name":"Michael Manz Praxis F\u00fcr Ergotherapie",
    "wof:placetype":"venue"
},
  "geometry": {"coordinates":[8.1365,48.68856],"type":"Point"}
}