{
  "type": "Feature",
  "properties": {
    "iso:country":"DE",
    "sg:address":"An den Ruschewiesen 5",
    "sg:city":"Dresden",
    "sg:phone":"+49 351/8889357",
    "sg:postcode":"01109",
    "sg:province":"Sachsen",
    "wof:name":"Dr. Hartmut Bourcevet Patentanwalt",
    "wof:placetype":"venue"
},
  "geometry": {"coordinates":[13.7706546783,51.1113357544],"type":"Point"}
}