{
  "type": "Feature",
  "properties": {
    "iso:country":"DE",
    "sg:address":"Heinrich-Heine-Allee 33",
    "sg:city":"D\u00fcsseldorf",
    "sg:phone":"+49 211/132081",
    "sg:postcode":"40213",
    "sg:province":"Nordrhein-Westfalen",
    "wof:name":"Volksbank D\u00fcsseldorf Neuss Eg",
    "wof:placetype":"venue"
},
  "geometry": {"coordinates":[6.7766890526,51.2263221741],"type":"Point"}
}