{
  "type": "Feature",
  "properties": {
    "iso:country":"DE",
    "sg:address":"Heinrichsallee 24",
    "sg:city":"Eschweiler",
    "sg:phone":"+49 2403/22859",
    "sg:postcode":"52249",
    "sg:province":"Nordrhein-Westfalen",
    "wof:name":"Efi Gmbh",
    "wof:placetype":"venue"
},
  "geometry": {"coordinates":[6.2517209053,50.8074531555],"type":"Point"}
}