{
  "type": "Feature",
  "properties": {
    "iso:country":"DE",
    "sg:address":"An der Wallburg 76",
    "sg:city":"Bergisch Gladbach",
    "sg:postcode":"51427",
    "sg:province":"Nordrhein-Westfalen",
    "wof:name":"Lebens-art Einrichtungs-design Gmbh",
    "wof:placetype":"venue"
},
  "geometry": {"coordinates":[7.1191940308,50.9612197876],"type":"Point"}
}