{
  "type": "Feature",
  "properties": {
    "iso:country":"DE",
    "sg:address":"Sanddornweg 2",
    "sg:city":"Karlsruhe",
    "sg:phone":"+49 721/756681",
    "sg:postcode":"76149",
    "sg:province":"Baden-W\u00fcrttemberg",
    "wof:name":"Weisbrod Umz\u00fcge",
    "wof:placetype":"venue"
},
  "geometry": {"coordinates":[8.3923921585,49.0353622437],"type":"Point"}
}