{
  "type": "Feature",
  "properties": {
    "iso:country":"DE",
    "sg:address":"Julius-H\u00f6lder-Str. 32",
    "sg:city":"Stuttgart",
    "sg:phone":"+49 711/7261041",
    "sg:postcode":"70597",
    "sg:province":"Baden-W\u00fcrttemberg",
    "wof:name":"Rudolf Lichtwerbung Gmbh",
    "wof:placetype":"venue"
},
  "geometry": {"coordinates":[9.1676769257,48.7387504578],"type":"Point"}
}