{
  "type": "Feature",
  "properties": {
    "iso:country":"DE",
    "sg:address":"Ploucquetstr. 11",
    "sg:city":"Heidenheim",
    "sg:phone":"+49 7321/3250",
    "sg:postcode":"89522",
    "sg:province":"Baden-W\u00fcrttemberg",
    "wof:name":"Ploucquet Holding Gmbh",
    "wof:placetype":"venue"
},
  "geometry": {"coordinates":[10.1561670303,48.676197052],"type":"Point"}
}