{
  "type": "Feature",
  "properties": {
    "iso:country":"DE",
    "sg:address":"Kleine M\u00fcnsterstr. 10",
    "sg:city":"L\u00fcdinghausen",
    "sg:phone":"+49 2591/96090",
    "sg:postcode":"59348",
    "sg:province":"Nordrhein-Westfalen",
    "wof:name":"Benetton",
    "wof:placetype":"venue"
},
  "geometry": {"coordinates":[7.444925,51.771214],"type":"Point"}
}