{
  "type": "Feature",
  "properties": {
    "iso:country":"DE",
    "sg:address":"Hauptstr 105",
    "sg:city":"Jettingen-Scheppach",
    "sg:phone":"+49 8225/96990",
    "sg:postcode":"89343",
    "sg:province":"Bayern",
    "wof:name":"Ludo Fact Gmbh",
    "wof:placetype":"venue"
},
  "geometry": {"coordinates":[10.439048,48.39513],"type":"Point"}
}