{
  "type": "Feature",
  "properties": {
    "iso:country":"DE",
    "sg:address":"Br\u00fcckenhof 3",
    "sg:city":"Schw\u00e4bisch Hall",
    "sg:phone":"+49 791/6656",
    "sg:postcode":"74523",
    "sg:province":"Baden-W\u00fcrttemberg",
    "wof:name":"Emil Schmidt",
    "wof:placetype":"venue"
},
  "geometry": {"coordinates":[9.73359,49.112755],"type":"Point"}
}