{
  "type": "Feature",
  "properties": {
    "iso:country":"DE",
    "sg:address":"Bahnhofstr 43",
    "sg:city":"Langenfeld",
    "sg:phone":"+49 2173/919310",
    "sg:postcode":"40764",
    "sg:province":"Nordrhein-Westfalen",
    "wof:name":"Rinas Ingenieurgesellschaft Mbh",
    "wof:placetype":"venue"
},
  "geometry": {"coordinates":[6.941261,51.099239],"type":"Point"}
}