{
  "type": "Feature",
  "properties": {
    "iso:country":"DE",
    "sg:address":"Brandauer Str. 10 a",
    "sg:city":"Modautal",
    "sg:phone":"+49 6254/1378",
    "sg:postcode":"64397",
    "sg:province":"Hessen",
    "wof:name":"Walter Nicklas",
    "wof:placetype":"venue"
},
  "geometry": {"coordinates":[8.7670478821,49.7423629761],"type":"Point"}
}