{
  "type": "Feature",
  "properties": {
    "iso:country":"DE",
    "sg:address":"Maternusstr. 8-10",
    "sg:city":"K\u00f6ln",
    "sg:postcode":"50996",
    "sg:province":"Nordrhein-Westfalen",
    "wof:name":"Lutter Immobilien- Vermietung Kg",
    "wof:placetype":"venue"
},
  "geometry": {"coordinates":[6.9941630363,50.8931465149],"type":"Point"}
}