{
  "type": "Feature",
  "properties": {
    "iso:country":"DE",
    "sg:address":"Hofgartenstr. 7",
    "sg:city":"Heilbronn",
    "sg:phone":"+49 7131/251106",
    "sg:postcode":"74081",
    "sg:province":"Baden-W\u00fcrttemberg",
    "wof:name":"G. H. Stein Kohlenhandlung",
    "wof:placetype":"venue"
},
  "geometry": {"coordinates":[9.191285,49.118107],"type":"Point"}
}