{
  "type": "Feature",
  "properties": {
    "iso:country":"DE",
    "sg:address":"Tannendorfstr. 1",
    "sg:city":"Greiz",
    "sg:phone":"+49 3661/63502",
    "sg:postcode":"07973",
    "sg:province":"Th\u00fcringen",
    "wof:name":"Auto-mehlhorn Gmbh",
    "wof:placetype":"venue"
},
  "geometry": {"coordinates":[12.194175,50.646908],"type":"Point"}
}