{
  "type": "Feature",
  "properties": {
    "iso:country":"DE",
    "sg:address":"Berliner Str. 94",
    "sg:city":"Homburg",
    "sg:phone":"+49 6841/74437",
    "sg:postcode":"66424",
    "sg:province":"Saarland",
    "wof:name":"Bistro Jolly",
    "wof:placetype":"venue"
},
  "geometry": {"coordinates":[7.3326511383,49.340473175],"type":"Point"}
}