{
  "type": "Feature",
  "properties": {
    "iso:country":"DE",
    "sg:address":"Eichredder 14",
    "sg:city":"Oststeinbek",
    "sg:phone":"+49 40/7321285",
    "sg:postcode":"22113",
    "sg:province":"Schleswig-Holstein",
    "wof:name":"Gso Gmbh W. Kahl - Ges. F. Softwareent-",
    "wof:placetype":"venue"
},
  "geometry": {"coordinates":[10.1596441269,53.54088974],"type":"Point"}
}