{
  "type": "Feature",
  "properties": {
    "iso:country":"DE",
    "sg:address":"Kopfenstr. 1 a",
    "sg:city":"Cuxhaven",
    "sg:phone":"+49 4724/1878",
    "sg:postcode":"27478",
    "sg:province":"Niedersachsen",
    "wof:name":"G\u00fcnter Behrens",
    "wof:placetype":"venue"
},
  "geometry": {"coordinates":[8.713529,53.776676],"type":"Point"}
}