{
  "type": "Feature",
  "properties": {
    "iso:country":"DE",
    "sg:address":"Rheinstr. 28",
    "sg:city":"Bornheim",
    "sg:phone":"+49 2222/81661",
    "sg:postcode":"53332",
    "sg:province":"Nordrhein-Westfalen",
    "wof:name":"Dr. Med. Rolf Schmitt Arzt F\u00fcr Allgemeinmedizin",
    "wof:placetype":"venue"
},
  "geometry": {"coordinates":[7.0523810387,50.7663612366],"type":"Point"}
}