{
  "type": "Feature",
  "properties": {
    "iso:country":"DE",
    "sg:address":"Flurstr. 1",
    "sg:city":"Wilhelmsdorf",
    "sg:phone":"+49 9104/3211",
    "sg:postcode":"91489",
    "sg:province":"Bayern",
    "wof:name":"Riwotec Gmbh",
    "wof:placetype":"venue"
},
  "geometry": {"coordinates":[10.743145,49.561871],"type":"Point"}
}