{
  "type": "Feature",
  "properties": {
    "iso:country":"DE",
    "sg:address":"Josef-Schneider-Str. 2",
    "sg:city":"W\u00fcrzburg",
    "sg:postcode":"97080",
    "sg:province":"Bayern",
    "wof:name":"Vereinigung Deutscher Strahlenschutz\u00e4rzte",
    "wof:placetype":"venue"
},
  "geometry": {"coordinates":[9.953566,49.800941],"type":"Point"}
}