{
  "type": "Feature",
  "properties": {
    "iso:country":"DE",
    "sg:address":"Ludenberger Str. 26",
    "sg:city":"Erkrath",
    "sg:phone":"+49 211/241061",
    "sg:postcode":"40699",
    "sg:province":"Nordrhein-Westfalen",
    "wof:name":"Werner Keil Bedachung Gmbh",
    "wof:placetype":"venue"
},
  "geometry": {"coordinates":[6.897607,51.221401],"type":"Point"}
}