{
  "type": "Feature",
  "properties": {
    "iso:country":"DE",
    "sg:address":"Ostlandring 3",
    "sg:city":"Hohenaspe",
    "sg:phone":"+49 4893/787",
    "sg:postcode":"25582",
    "sg:province":"Schleswig-Holstein",
    "wof:name":"A. Meier",
    "wof:placetype":"venue"
},
  "geometry": {"coordinates":[9.517548,53.987373],"type":"Point"}
}