{
  "type": "Feature",
  "properties": {
    "iso:country":"DE",
    "sg:address":"Rosa-Luxemburg-Str. 9",
    "sg:city":"Altenburg",
    "sg:phone":"+49 3447/311460",
    "sg:postcode":"04600",
    "sg:province":"Th\u00fcringen",
    "wof:name":"Foto M\u00fcller",
    "wof:placetype":"venue"
},
  "geometry": {"coordinates":[12.4384174347,50.9895172119],"type":"Point"}
}