{
  "type": "Feature",
  "properties": {
    "iso:country":"DE",
    "sg:address":"Bahnhofstr. 12",
    "sg:city":"Fredenbeck",
    "sg:phone":"+49 4149/920770",
    "sg:postcode":"21717",
    "sg:province":"Niedersachsen",
    "wof:name":"Brillenschmiede Fredenbeck Gmbh",
    "wof:placetype":"venue"
},
  "geometry": {"coordinates":[9.39855,53.521694],"type":"Point"}
}