{
  "type": "Feature",
  "properties": {
    "iso:country":"DE",
    "sg:address":"Weinstr. 101",
    "sg:city":"Edenkoben",
    "sg:postcode":"67480",
    "sg:province":"Rheinland-Pfalz",
    "wof:name":"Blumenhaus Am Goldenen Eck E. Kfr.",
    "wof:placetype":"venue"
},
  "geometry": {"coordinates":[8.127156,49.282883],"type":"Point"}
}