{
  "type": "Feature",
  "properties": {
    "iso:country":"DE",
    "sg:address":"Bregstr. 3",
    "sg:city":"Furtwangen",
    "sg:phone":"+49 7723/7316",
    "sg:postcode":"78120",
    "sg:province":"Baden-W\u00fcrttemberg",
    "wof:name":"H. Kornhaas",
    "wof:placetype":"venue"
},
  "geometry": {"coordinates":[8.2023773193,48.0487785339],"type":"Point"}
}