{
  "type": "Feature",
  "properties": {
    "iso:country":"DE",
    "sg:address":"Im P\u00fchlchen 3",
    "sg:city":"Koblenz",
    "sg:phone":"+49 261/46110",
    "sg:postcode":"56072",
    "sg:province":"Rheinland-Pfalz",
    "wof:name":"Joachim Becker",
    "wof:placetype":"venue"
},
  "geometry": {"coordinates":[7.5488119125,50.3477745056],"type":"Point"}
}