{
  "type": "Feature",
  "properties": {
    "iso:country":"DE",
    "sg:address":"Lohfeldener Weg 66",
    "sg:city":"Kassel",
    "sg:phone":"+49 561/5102540",
    "sg:postcode":"23123",
    "sg:province":"Hessen",
    "wof:name":"Das Autohaus Online",
    "wof:placetype":"venue"
},
  "geometry": {"coordinates":[9.540174,51.288773],"type":"Point"}
}