{
  "type": "Feature",
  "properties": {
    "iso:country":"DE",
    "sg:address":"Hertzstr. 5",
    "sg:city":"Aschersleben",
    "sg:phone":"+49 4934/7392490",
    "sg:postcode":"06449",
    "sg:province":"Sachsen-Anhalt",
    "wof:name":"Wvg Getr\u00c4nke Gmbh",
    "wof:placetype":"venue"
},
  "geometry": {"coordinates":[11.483866,51.770382],"type":"Point"}
}