{
  "type": "Feature",
  "properties": {
    "iso:country":"DE",
    "sg:address":"W\u00e4scherhof 4",
    "sg:city":"W\u00e4schenbeuren",
    "sg:phone":"+49 7172/8845",
    "sg:postcode":"73116",
    "sg:province":"Baden-W\u00fcrttemberg",
    "wof:name":"Roland Kuhn",
    "wof:placetype":"venue"
},
  "geometry": {"coordinates":[9.689588,48.760967],"type":"Point"}
}