{
  "type": "Feature",
  "properties": {
    "iso:country":"DE",
    "sg:address":"Hauptstr. 68",
    "sg:city":"Obersch\u00f6nau",
    "sg:postcode":"98587",
    "sg:province":"Th\u00fcringen",
    "wof:name":"Sanitherm Haustechnik Service E. K.",
    "wof:placetype":"venue"
},
  "geometry": {"coordinates":[10.610538,50.715832],"type":"Point"}
}