{
  "type": "Feature",
  "properties": {
    "iso:country":"DE",
    "sg:address":"Hauptstr. 6",
    "sg:city":"Bensheim",
    "sg:phone":"+49 6251/3011",
    "sg:postcode":"64625",
    "sg:province":"Hessen",
    "wof:name":"St. Georg-apotheke",
    "wof:placetype":"venue"
},
  "geometry": {"coordinates":[8.622188,49.682571],"type":"Point"}
}