{
  "type": "Feature",
  "properties": {
    "iso:country":"DE",
    "sg:address":"Obergraben 23",
    "sg:city":"Siegen",
    "sg:phone":"+49 271/55125",
    "sg:postcode":"57072",
    "sg:province":"Nordrhein-Westfalen",
    "wof:name":"Aktimed Gmbh",
    "wof:placetype":"venue"
},
  "geometry": {"coordinates":[8.0221557617,50.8727226257],"type":"Point"}
}