{
  "type": "Feature",
  "properties": {
    "iso:country":"DE",
    "sg:address":"Hasel\u00fcnner Str. 9",
    "sg:city":"Herzlake",
    "sg:phone":"+49 5962/733",
    "sg:postcode":"49770",
    "sg:province":"Niedersachsen",
    "wof:name":"Gastst\u00e4tte Bernhard Witte",
    "wof:placetype":"venue"
},
  "geometry": {"coordinates":[7.6021881104,52.6841773987],"type":"Point"}
}