{
  "type": "Feature",
  "properties": {
    "iso:country":"DE",
    "sg:address":"Nienburger Str.",
    "sg:city":"Latdorf",
    "sg:phone":"+49 3471/621263",
    "sg:postcode":"06408",
    "sg:province":"Sachsen-Anhalt",
    "wof:name":"I. Bernhardt",
    "wof:placetype":"venue"
},
  "geometry": {"coordinates":[11.802079,51.811398],"type":"Point"}
}