{
  "type": "Feature",
  "properties": {
    "iso:country":"DE",
    "sg:address":"Sch\u00f6nbrunnerstrasse 14",
    "sg:city":"Landshut",
    "sg:phone":"+49 871/22444",
    "sg:postcode":"84036",
    "sg:province":"Bayern",
    "wof:name":"Obstkelterei G\u00e4rttner Fruchts\u00e4fte",
    "wof:placetype":"venue"
},
  "geometry": {"coordinates":[12.164774,48.537731],"type":"Point"}
}