{
  "type": "Feature",
  "properties": {
    "iso:country":"DE",
    "sg:address":"Steinweg 1",
    "sg:city":"Dieburg",
    "sg:phone":"+49 6071/21133",
    "sg:postcode":"64807",
    "sg:province":"Hessen",
    "wof:name":"Bistro Prisma",
    "wof:placetype":"venue"
},
  "geometry": {"coordinates":[8.8365306854,49.8971481323],"type":"Point"}
}