{
  "type": "Feature",
  "properties": {
    "iso:country":"DE",
    "sg:address":"Deichstr. 64b",
    "sg:city":"Borkum",
    "sg:postcode":"26757",
    "sg:province":"Niedersachsen",
    "wof:name":"Genius Insel-reinigungs Gmbh",
    "wof:placetype":"venue"
},
  "geometry": {"coordinates":[6.679125,53.581741],"type":"Point"}
}