{
  "type": "Feature",
  "properties": {
    "iso:country":"DE",
    "sg:address":"Schie\u00dfbahn 10",
    "sg:city":"Z\u00fclpich",
    "sg:phone":"+49 2252/2683",
    "sg:postcode":"53909",
    "sg:province":"Nordrhein-Westfalen",
    "wof:name":"Kaspar P\u00fctz",
    "wof:placetype":"venue"
},
  "geometry": {"coordinates":[6.645629,50.691513],"type":"Point"}
}