{
  "type": "Feature",
  "properties": {
    "iso:country":"DE",
    "sg:address":"Gummeringer Str. 12",
    "sg:city":"Niederviehbach",
    "sg:phone":"+49 8702/2272",
    "sg:postcode":"84183",
    "sg:province":"Bayern",
    "wof:name":"Franz Haider",
    "wof:placetype":"venue"
},
  "geometry": {"coordinates":[12.385088,48.618984],"type":"Point"}
}