{
  "type": "Feature",
  "properties": {
    "iso:country":"DE",
    "sg:address":"Pestalozzistr. 27",
    "sg:city":"Bamberg",
    "sg:phone":"+49 951/31257",
    "sg:postcode":"96052",
    "sg:province":"Bayern",
    "wof:name":"Ev.-luth. Pfarramt Auferstehungskirche",
    "wof:placetype":"venue"
},
  "geometry": {"coordinates":[10.9161643982,49.9098777771],"type":"Point"}
}