{
  "type": "Feature",
  "properties": {
    "iso:country":"DE",
    "sg:address":"Bahnhofstr. 14",
    "sg:city":"Halle",
    "sg:phone":"+49 5201/2409",
    "sg:postcode":"33790",
    "sg:province":"Nordrhein-Westfalen",
    "wof:name":"Karl Hess Eisenwaren",
    "wof:placetype":"venue"
},
  "geometry": {"coordinates":[8.3608446121,52.0600776672],"type":"Point"}
}