{
  "type": "Feature",
  "properties": {
    "iso:country":"DE",
    "sg:address":"Seeshaupter Stra\u00dfe 46",
    "sg:city":"Penzberg",
    "sg:phone":"+49 8856/803461",
    "sg:postcode":"82377",
    "sg:province":"Bayern",
    "wof:name":"Car-sound-systeme",
    "wof:placetype":"venue"
},
  "geometry": {"coordinates":[11.362737,47.764107],"type":"Point"}
}