{
  "type": "Feature",
  "properties": {
    "iso:country":"DE",
    "sg:address":"Prof.-Wilhelm-Kempff-Weg 1",
    "sg:city":"Thurnau",
    "sg:phone":"+49 9228/5331",
    "sg:postcode":"95349",
    "sg:province":"Bayern",
    "wof:name":"Dr. Med. Barbara Grelich",
    "wof:placetype":"venue"
},
  "geometry": {"coordinates":[11.4001550674,50.0268058777],"type":"Point"}
}