{
  "type": "Feature",
  "properties": {
    "iso:country":"DE",
    "sg:address":"Reinhardshausen 3",
    "sg:city":"Stadtlauringen",
    "sg:phone":"+49 9724/2158",
    "sg:postcode":"97488",
    "sg:province":"Bayern",
    "wof:name":"Franz St\u00fcrmer",
    "wof:placetype":"venue"
},
  "geometry": {"coordinates":[10.369154,50.176571],"type":"Point"}
}