{
  "type": "Feature",
  "properties": {
    "iso:country":"DE",
    "sg:address":"Gie\u00dfenbachstr. 1",
    "sg:city":"Rosenheim",
    "sg:phone":"+49 8031/16480",
    "sg:postcode":"83022",
    "sg:province":"Bayern",
    "wof:name":"Heinz Putschies",
    "wof:placetype":"venue"
},
  "geometry": {"coordinates":[12.136674881,47.8493003845],"type":"Point"}
}