{
  "type": "Feature",
  "properties": {
    "iso:country":"DE",
    "sg:address":"Sterngasse 7",
    "sg:city":"L\u00fcdenscheid",
    "sg:phone":"+49 2351/20961",
    "sg:postcode":"58511",
    "sg:province":"Nordrhein-Westfalen",
    "wof:name":"S. Altun",
    "wof:placetype":"venue"
},
  "geometry": {"coordinates":[7.630420208,51.2161026001],"type":"Point"}
}