{
  "type": "Feature",
  "properties": {
    "iso:country":"DE",
    "sg:address":"Potsdamer Str. 215",
    "sg:city":"Bielefeld",
    "sg:phone":"+49 5208/7948",
    "sg:postcode":"33719",
    "sg:province":"Nordrhein-Westfalen",
    "wof:name":"M\u00fcller B\u00fcrom\u00f6bel Sofort Bielefeld Gmbh",
    "wof:placetype":"venue"
},
  "geometry": {"coordinates":[8.6116952896,52.0057525635],"type":"Point"}
}