{
  "type": "Feature",
  "properties": {
    "iso:country":"DE",
    "sg:address":"Elbstr. 15",
    "sg:city":"Bleckede",
    "sg:phone":"+49 5852/3168",
    "sg:postcode":"21354",
    "sg:province":"Niedersachsen",
    "wof:name":"Gastst\u00e4tte F\u00e4hrhaus",
    "wof:placetype":"venue"
},
  "geometry": {"coordinates":[10.7342214584,53.297870636],"type":"Point"}
}