{
  "type": "Feature",
  "properties": {
    "iso:country":"DE",
    "sg:address":"Au\u00dfer-Ort-Str. 6",
    "sg:city":"Engen",
    "sg:phone":"+49 7733/50000",
    "sg:postcode":"78234",
    "sg:province":"Baden-W\u00fcrttemberg",
    "wof:name":"M\u00f6belhaus Willauer Gmbh",
    "wof:placetype":"venue"
},
  "geometry": {"coordinates":[8.7686319351,47.8471450806],"type":"Point"}
}