{
  "type": "Feature",
  "properties": {
    "iso:country":"DE",
    "sg:address":"Ausbau 1",
    "sg:city":"Divitz",
    "sg:phone":"+49 38231/3378",
    "sg:postcode":"18314",
    "sg:province":"Mecklenburg-Vorpommern",
    "wof:name":"Wolfgang Ewert",
    "wof:placetype":"venue"
},
  "geometry": {"coordinates":[12.6945638657,54.3323516846],"type":"Point"}
}