{
  "type": "Feature",
  "properties": {
    "iso:country":"DE",
    "sg:address":"Bahnhofstr. 9",
    "sg:city":"Sindelfingen",
    "sg:phone":"+49 7031/61090",
    "sg:postcode":"71063",
    "sg:province":"Baden-W\u00fcrttemberg",
    "wof:name":"Wohnst\u00e4tten Sindelfingen Gmbh",
    "wof:placetype":"venue"
},
  "geometry": {"coordinates":[9.0022277832,48.7068519592],"type":"Point"}
}