{
  "type": "Feature",
  "properties": {
    "iso:country":"DE",
    "sg:address":"Feuchtwanger Str. 22",
    "sg:city":"Schnelldorf",
    "sg:phone":"+49 7950/2187",
    "sg:postcode":"91625",
    "sg:province":"Bayern",
    "wof:name":"Felix Marx",
    "wof:placetype":"venue"
},
  "geometry": {"coordinates":[10.180101,49.197689],"type":"Point"}
}