{
  "type": "Feature",
  "properties": {
    "iso:country":"DE",
    "sg:address":"Fleischmengergasse 29",
    "sg:city":"K\u00f6ln",
    "sg:phone":"+49 221/237379",
    "sg:postcode":"50676",
    "sg:province":"Nordrhein-Westfalen",
    "wof:name":"Libresso",
    "wof:placetype":"venue"
},
  "geometry": {"coordinates":[6.948498,50.934029],"type":"Point"}
}