{
  "type": "Feature",
  "properties": {
    "iso:country":"DE",
    "sg:address":"Alte Talstr. 36",
    "sg:city":"Kirschweiler",
    "sg:phone":"+49 6781/933378",
    "sg:postcode":"55743",
    "sg:province":"Rheinland-Pfalz",
    "wof:name":"R\u00f6del",
    "wof:placetype":"venue"
},
  "geometry": {"coordinates":[7.250122,49.757858],"type":"Point"}
}