{
  "type": "Feature",
  "properties": {
    "iso:country":"DE",
    "sg:address":"K\u00f6nigsteiner Str. 7",
    "sg:city":"Bad Soden",
    "sg:phone":"+49 6196/60910",
    "sg:postcode":"65812",
    "sg:province":"Hessen",
    "wof:name":"Volpert Verwaltungs Gmbh",
    "wof:placetype":"venue"
},
  "geometry": {"coordinates":[8.507554,50.138069],"type":"Point"}
}