{
  "type": "Feature",
  "properties": {
    "iso:country":"DE",
    "sg:address":"P\u00fctzgasse 4",
    "sg:city":"Kinheim",
    "sg:phone":"+49 6532/2742",
    "sg:postcode":"54538",
    "sg:province":"Rheinland-Pfalz",
    "wof:name":"Dorfkrug",
    "wof:placetype":"venue"
},
  "geometry": {"coordinates":[7.0536308289,49.9736557007],"type":"Point"}
}