{
  "type": "Feature",
  "properties": {
    "iso:country":"DE",
    "sg:address":"Mooskamp 20",
    "sg:city":"Dortmund",
    "sg:phone":"+49 231/352492",
    "sg:postcode":"44359",
    "sg:province":"Nordrhein-Westfalen",
    "wof:name":"Seniorenheime Pflegeheim Mooskamp",
    "wof:placetype":"venue"
},
  "geometry": {"coordinates":[7.403285,51.549946],"type":"Point"}
}