{
  "type": "Feature",
  "properties": {
    "iso:country":"DE",
    "sg:address":"Kastanienallee 21",
    "sg:city":"Berlin",
    "sg:phone":"+49 30/82710240",
    "sg:postcode":"10435",
    "sg:province":"Berlin",
    "wof:name":"Wolfgang Sachse",
    "wof:placetype":"venue"
},
  "geometry": {"coordinates":[13.408685,52.537849],"type":"Point"}
}