{
  "type": "Feature",
  "properties": {
    "iso:country":"DE",
    "sg:address":"Hauptstr. 57",
    "sg:city":"Lauf",
    "sg:phone":"+49 7841/21362",
    "sg:postcode":"77886",
    "sg:province":"Baden-W\u00fcrttemberg",
    "wof:name":"Wolfgang Strau\u00df Gmbh",
    "wof:placetype":"venue"
},
  "geometry": {"coordinates":[8.1308059692,48.6488342285],"type":"Point"}
}