{
  "type": "Feature",
  "properties": {
    "iso:country":"DE",
    "sg:address":"Schlehdornweg 3",
    "sg:city":"Greifswald",
    "sg:phone":"+49 3834/843753",
    "sg:postcode":"17493",
    "sg:province":"Mecklenburg-Vorpommern",
    "wof:name":"Werner Franke",
    "wof:placetype":"venue"
},
  "geometry": {"coordinates":[13.4422855377,54.0891418457],"type":"Point"}
}