{
  "type": "Feature",
  "properties": {
    "iso:country":"DE",
    "sg:address":"H\u00fcbnerstr. 11",
    "sg:city":"Dresden",
    "sg:phone":"+49 351/4710667",
    "sg:postcode":"01069",
    "sg:province":"Sachsen",
    "wof:name":"Jugendherberge Rudi Arndt",
    "wof:placetype":"venue"
},
  "geometry": {"coordinates":[13.7259540558,51.0341796875],"type":"Point"}
}