{
  "type": "Feature",
  "properties": {
    "iso:country":"DE",
    "sg:address":"Goethestr. 6",
    "sg:city":"Pinneberg",
    "sg:phone":"+49 4101/693010",
    "sg:postcode":"25421",
    "sg:province":"Schleswig-Holstein",
    "wof:name":"B. Fink",
    "wof:placetype":"venue"
},
  "geometry": {"coordinates":[9.7912683487,53.6482772827],"type":"Point"}
}