{
  "type": "Feature",
  "properties": {
    "iso:country":"DE",
    "sg:address":"Riedener Weg 23",
    "sg:city":"Starnberg",
    "sg:phone":"+49 8151/8219",
    "sg:postcode":"82319",
    "sg:province":"Bayern",
    "wof:name":"Glenwood Gmbh Pharmazeutische Erzeugnisse",
    "wof:placetype":"venue"
},
  "geometry": {"coordinates":[11.3449354172,48.0061035156],"type":"Point"}
}