{
  "type": "Feature",
  "properties": {
    "iso:country":"DE",
    "sg:address":"Tannenloheweg 12",
    "sg:city":"Wiesau",
    "sg:phone":"+49 9634/425",
    "sg:postcode":"95676",
    "sg:province":"Bayern",
    "wof:name":"H. Burger",
    "wof:placetype":"venue"
},
  "geometry": {"coordinates":[12.1952199936,49.8896942139],"type":"Point"}
}