{
  "type": "Feature",
  "properties": {
    "iso:country":"DE",
    "sg:address":"Schulgasse 50",
    "sg:city":"Ro\u00dfdorf",
    "sg:phone":"+49 6154/63369",
    "sg:postcode":"64380",
    "sg:province":"Hessen",
    "wof:name":"Einspacher Hof",
    "wof:placetype":"venue"
},
  "geometry": {"coordinates":[8.7589597702,49.8551902771],"type":"Point"}
}