{
  "type": "Feature",
  "properties": {
    "iso:country":"DE",
    "sg:address":"Johanniskirchstr. 1 a",
    "sg:city":"Essen",
    "sg:postcode":"45329",
    "sg:province":"Nordrhein-Westfalen",
    "wof:name":"Kath. \u00f6ffentl. Bibliothek St. Johann",
    "wof:placetype":"venue"
},
  "geometry": {"coordinates":[7.007363,51.500507],"type":"Point"}
}