{
  "type": "Feature",
  "properties": {
    "iso:country":"DE",
    "sg:address":"Im Fuchsloch 7",
    "sg:city":"Frankfurt",
    "sg:phone":"+49 69/7380031",
    "sg:postcode":"60437",
    "sg:province":"Hessen",
    "wof:name":"Klf-zvl Gmbh",
    "wof:placetype":"venue"
},
  "geometry": {"coordinates":[8.703089,50.207207],"type":"Point"}
}