{
  "type": "Feature",
  "properties": {
    "iso:country":"DE",
    "sg:address":"Henleinstr. 18",
    "sg:city":"K\u00f6ln",
    "sg:postcode":"51107",
    "sg:province":"Nordrhein-Westfalen",
    "wof:name":"Nordland-reisen Gmbh",
    "wof:placetype":"venue"
},
  "geometry": {"coordinates":[7.0445108414,50.9308280945],"type":"Point"}
}