{
  "type": "Feature",
  "properties": {
    "iso:country":"DE",
    "sg:address":"Bismarckstr. 24",
    "sg:city":"Geislingen",
    "sg:phone":"+49 7331/40271",
    "sg:postcode":"73312",
    "sg:province":"Baden-W\u00fcrttemberg",
    "wof:name":"K. Schlumberger",
    "wof:placetype":"venue"
},
  "geometry": {"coordinates":[9.8408756256,48.6129837036],"type":"Point"}
}