{
  "type": "Feature",
  "properties": {
    "iso:country":"DE",
    "sg:address":"Nordsteimker Str.",
    "sg:city":"Wolfsburg",
    "sg:phone":"+49 5363/4100",
    "sg:postcode":"38446",
    "sg:province":"Niedersachsen",
    "wof:name":"M\u00f6bel Unger",
    "wof:placetype":"venue"
},
  "geometry": {"coordinates":[10.8012857437,52.4188919067],"type":"Point"}
}