{
  "type": "Feature",
  "properties": {
    "iso:country":"DE",
    "sg:address":"Beethovenstr. 2",
    "sg:city":"Neuss",
    "sg:phone":"+49 2131/295810",
    "sg:postcode":"41462",
    "sg:province":"Nordrhein-Westfalen",
    "wof:name":"Iteco Oilfield Supply Gmbh",
    "wof:placetype":"venue"
},
  "geometry": {"coordinates":[6.678771,51.228439],"type":"Point"}
}