{
  "type": "Feature",
  "properties": {
    "iso:country":"DE",
    "sg:address":"Einsteinstr. 11",
    "sg:city":"Herford",
    "sg:phone":"+49 5221/97001",
    "sg:postcode":"32052",
    "sg:province":"Nordrhein-Westfalen",
    "wof:name":"Prewi Schneidwerkzeuge Gmbh",
    "wof:placetype":"venue"
},
  "geometry": {"coordinates":[8.6747913361,52.094417572],"type":"Point"}
}