{
  "type": "Feature",
  "properties": {
    "iso:country":"DE",
    "sg:address":"Hainhorster Weg 43",
    "sg:city":"Visselh\u00f6vede",
    "sg:phone":"+49 4260/228",
    "sg:postcode":"27374",
    "sg:province":"Niedersachsen",
    "wof:name":"Alfred Lohmann Architekt",
    "wof:placetype":"venue"
},
  "geometry": {"coordinates":[9.510289,53.0033],"type":"Point"}
}