{
  "type": "Feature",
  "properties": {
    "iso:country":"DE",
    "sg:address":"Steinweg",
    "sg:city":"Staig",
    "sg:phone":"+49 7346/3604",
    "sg:postcode":"89195",
    "sg:province":"Baden-W\u00fcrttemberg",
    "wof:name":"Anton Mayer",
    "wof:placetype":"venue"
},
  "geometry": {"coordinates":[9.978935,48.304375],"type":"Point"}
}