{
  "type": "Feature",
  "properties": {
    "iso:country":"DE",
    "sg:address":"Muttergottesstiege 13",
    "sg:city":"Haltern",
    "sg:phone":"+49 2364/93950",
    "sg:postcode":"45721",
    "sg:province":"Nordrhein-Westfalen",
    "wof:name":"Bruno Wittkemper Steuerberater",
    "wof:placetype":"venue"
},
  "geometry": {"coordinates":[7.1824598312,51.7441596985],"type":"Point"}
}