{
  "type": "Feature",
  "properties": {
    "iso:country":"DE",
    "sg:address":"B\u00f6kenf\u00f6rder Str. 9-11",
    "sg:city":"Lippstadt",
    "sg:phone":"+49 2941/14066",
    "sg:postcode":"59557",
    "sg:province":"Nordrhein-Westfalen",
    "wof:name":"Albers & S\u00f6hne Gmbh",
    "wof:placetype":"venue"
},
  "geometry": {"coordinates":[8.346837,51.66848],"type":"Point"}
}