{
  "type": "Feature",
  "properties": {
    "iso:country":"DE",
    "sg:address":"Schwandorfstr. 19",
    "sg:city":"Bretten",
    "sg:phone":"+49 7252/4775",
    "sg:postcode":"75015",
    "sg:province":"Baden-W\u00fcrttemberg",
    "wof:name":"Manufekt Lohnpack G\u00fcnter Flammann",
    "wof:placetype":"venue"
},
  "geometry": {"coordinates":[8.675752,49.040779],"type":"Point"}
}