{
  "type": "Feature",
  "properties": {
    "iso:country":"DE",
    "sg:address":"Babenhauser Str. 79",
    "sg:city":"Bielefeld",
    "sg:phone":"+49 521/881486",
    "sg:postcode":"33619",
    "sg:province":"Nordrhein-Westfalen",
    "wof:name":"Friedrich-wilhelm Schwarze Ingenieur",
    "wof:placetype":"venue"
},
  "geometry": {"coordinates":[8.4823904037,52.0576515198],"type":"Point"}
}