{
  "type": "Feature",
  "properties": {
    "iso:country":"DE",
    "sg:address":"Liebigstr. 6",
    "sg:city":"Wiesbaden",
    "sg:phone":"+49 611/524262",
    "sg:postcode":"65193",
    "sg:province":"Hessen",
    "wof:name":"Aug. Cranz Gmbh",
    "wof:placetype":"venue"
},
  "geometry": {"coordinates":[8.2448968887,50.0934410095],"type":"Point"}
}