{
  "type": "Feature",
  "properties": {
    "iso:country":"DE",
    "sg:address":"Borsigstr. 7",
    "sg:city":"Rutesheim",
    "sg:phone":"+49 7152/53347",
    "sg:postcode":"71277",
    "sg:province":"Baden-W\u00fcrttemberg",
    "wof:name":"Bernd W\u00f6rner",
    "wof:placetype":"venue"
},
  "geometry": {"coordinates":[8.960721,48.811996],"type":"Point"}
}