{
  "type": "Feature",
  "properties": {
    "iso:country":"DE",
    "sg:address":"Matth\u00e4ikirchstr. 37",
    "sg:city":"Hannover",
    "sg:phone":"+49 511",
    "sg:postcode":"30519",
    "sg:province":"Niedersachsen",
    "wof:name":"Kampfkunstschule Shindo",
    "wof:placetype":"venue"
},
  "geometry": {"coordinates":[9.7806987762,52.3313827515],"type":"Point"}
}