{
  "type": "Feature",
  "properties": {
    "iso:country":"DE",
    "sg:address":"Leintalstr. 28",
    "sg:city":"Abtsgm\u00fcnd",
    "sg:phone":"+49 7366/7420",
    "sg:postcode":"73453",
    "sg:province":"Baden-W\u00fcrttemberg",
    "wof:name":"Gasthaus Hans K\u00f6ngeter",
    "wof:placetype":"venue"
},
  "geometry": {"coordinates":[9.9670228958,48.8664321899],"type":"Point"}
}