{
  "type": "Feature",
  "properties": {
    "iso:country":"DE",
    "sg:address":"Uellendahler Str. 412",
    "sg:city":"Wuppertal",
    "sg:phone":"+49 202/700208",
    "sg:postcode":"42109",
    "sg:province":"Nordrhein-Westfalen",
    "wof:name":"Uellendahler St\u00fcbchen",
    "wof:placetype":"venue"
},
  "geometry": {"coordinates":[7.1653552055,51.2792358398],"type":"Point"}
}