{
  "type": "Feature",
  "properties": {
    "iso:country":"DE",
    "sg:address":"Himmelgeister Str. 100",
    "sg:city":"D\u00fcsseldorf",
    "sg:postcode":"40225",
    "sg:province":"Nordrhein-Westfalen",
    "wof:name":"Bio Klion Gmbh",
    "wof:placetype":"venue"
},
  "geometry": {"coordinates":[6.782306,51.199291],"type":"Point"}
}