{
  "type": "Feature",
  "properties": {
    "iso:country":"DE",
    "sg:address":"Forsterbruchstr. 5",
    "sg:city":"Oberhausen",
    "sg:phone":"+49 208/661688",
    "sg:postcode":"46149",
    "sg:province":"Nordrhein-Westfalen",
    "wof:name":"Hans Hut Magnetsysteme Gmbh",
    "wof:placetype":"venue"
},
  "geometry": {"coordinates":[6.8445630074,51.5040473938],"type":"Point"}
}