{
  "type": "Feature",
  "properties": {
    "iso:country":"DE",
    "sg:address":"Von-Lingg-Str. 15",
    "sg:city":"Nesselwang",
    "sg:phone":"+49 8361/1823",
    "sg:postcode":"87484",
    "sg:province":"Bayern",
    "wof:name":"Ullas Seidenboutique",
    "wof:placetype":"venue"
},
  "geometry": {"coordinates":[10.500098,47.623383],"type":"Point"}
}