{
  "type": "Feature",
  "properties": {
    "iso:country":"DE",
    "sg:address":"Fuldaer Str. 22-24",
    "sg:city":"Schl\u00fcchtern",
    "sg:phone":"+49 6661/71234",
    "sg:postcode":"36381",
    "sg:province":"Hessen",
    "wof:name":"Daub & Koch Gmbh & Co. Und Van Enst Destillerie",
    "wof:placetype":"venue"
},
  "geometry": {"coordinates":[9.5244693756,50.3534507751],"type":"Point"}
}