{
  "type": "Feature",
  "properties": {
    "iso:country":"DE",
    "sg:address":"Lankwitzer Str. 1-2",
    "sg:city":"Berlin",
    "sg:phone":"+49 30/7406760",
    "sg:postcode":"12107",
    "sg:province":"Berlin",
    "wof:name":"Autoservice G\u00f6tz Gmbh",
    "wof:placetype":"venue"
},
  "geometry": {"coordinates":[13.368398,52.435802],"type":"Point"}
}