{
  "type": "Feature",
  "properties": {
    "iso:country":"DE",
    "sg:address":"Mainzer Str. 92 a - 94 a",
    "sg:city":"Wiesbaden",
    "sg:phone":"+49 611/719307",
    "sg:postcode":"65189",
    "sg:province":"Hessen",
    "wof:name":"Auto-leasing-ideal Gmbh",
    "wof:placetype":"venue"
},
  "geometry": {"coordinates":[8.249363,50.068676],"type":"Point"}
}