{
  "type": "Feature",
  "properties": {
    "iso:country":"DE",
    "sg:address":"Forstenrieder Allee 17",
    "sg:city":"M\u00fcnchen",
    "sg:phone":"+49 89/7556648",
    "sg:postcode":"81476",
    "sg:province":"Bayern",
    "wof:name":"Ail Laser Solutions Gmbh",
    "wof:placetype":"venue"
},
  "geometry": {"coordinates":[11.4996643066,48.099773407],"type":"Point"}
}