{
  "type": "Feature",
  "properties": {
    "iso:country":"DE",
    "sg:address":"Gr\u00e4fin-Justitia-Str 2",
    "sg:city":"Egling",
    "sg:phone":"+49 8176/7454",
    "sg:postcode":"82544",
    "sg:province":"Bayern",
    "wof:name":"Raiffeisenbank Thanning & Umgebung",
    "wof:placetype":"venue"
},
  "geometry": {"coordinates":[11.536031,47.920868],"type":"Point"}
}