{
  "type": "Feature",
  "properties": {
    "iso:country":"DE",
    "sg:address":"Spielberger Str. 4",
    "sg:city":"Gnotzheim",
    "sg:phone":"+49 9833/770",
    "sg:postcode":"91728",
    "sg:province":"Bayern",
    "wof:name":"Vereinigte Sparkassen Gunzenhausen",
    "wof:placetype":"venue"
},
  "geometry": {"coordinates":[10.71403,49.058945],"type":"Point"}
}