{
  "type": "Feature",
  "properties": {
    "iso:country":"DE",
    "sg:address":"Schlo\u00dfbergstr. 21",
    "sg:city":"Aiglsbach",
    "sg:postcode":"84089",
    "sg:province":"Bayern",
    "wof:name":"Sebastian Und Kreszens Berger Transporte Gmbh & Co. Kg",
    "wof:placetype":"venue"
},
  "geometry": {"coordinates":[11.7046251297,48.6671714783],"type":"Point"}
}