{
  "type": "Feature",
  "properties": {
    "iso:country":"DE",
    "sg:address":"Hambr\u00fccker Landstr. 6",
    "sg:city":"Wagh\u00e4usel",
    "sg:phone":"+49 7254/2020",
    "sg:postcode":"68753",
    "sg:province":"Baden-W\u00fcrttemberg",
    "wof:name":"Uvg Vermietungs Gmbh",
    "wof:placetype":"venue"
},
  "geometry": {"coordinates":[8.5277271271,49.2138442993],"type":"Point"}
}