{
  "type": "Feature",
  "properties": {
    "iso:country":"DE",
    "sg:address":"Mottmannstr 4a",
    "sg:city":"Troisdorf",
    "sg:phone":"+49 8121/8020",
    "sg:postcode":"53842",
    "sg:province":"Nordrhein-Westfalen",
    "wof:name":"Sv Research Gesellschaft F\u00fcr Bildverarbeitung Mbh",
    "wof:placetype":"venue"
},
  "geometry": {"coordinates":[11.853901,48.194874],"type":"Point"}
}