{
  "type": "Feature",
  "properties": {
    "iso:country":"DE",
    "sg:address":"Westendstr. 95",
    "sg:city":"M\u00fcnchen",
    "sg:phone":"+49 89/5021347",
    "sg:postcode":"80339",
    "sg:province":"Bayern",
    "wof:name":"I. Scheffler",
    "wof:placetype":"venue"
},
  "geometry": {"coordinates":[11.5392351151,48.1379623413],"type":"Point"}
}