{
  "type": "Feature",
  "properties": {
    "iso:country":"DE",
    "sg:address":"Ahrweg 5",
    "sg:city":"Hanau",
    "sg:phone":"+49 6181/659356",
    "sg:postcode":"63456",
    "sg:province":"Hessen",
    "wof:name":"Fachcenter Schmiedt Gmbh",
    "wof:placetype":"venue"
},
  "geometry": {"coordinates":[8.904258728,50.1140823364],"type":"Point"}
}