{
  "type": "Feature",
  "properties": {
    "iso:country":"DE",
    "sg:address":"Bahnstr. 67",
    "sg:city":"Wuppertal",
    "sg:phone":"+49 202/781168",
    "sg:postcode":"42327",
    "sg:province":"Nordrhein-Westfalen",
    "wof:name":"Hainbach Verwaltungsgesell- Schaft F\u00fcr W\u00e4rmeservice Mbh",
    "wof:placetype":"venue"
},
  "geometry": {"coordinates":[7.0707302094,51.2433013916],"type":"Point"}
}