{
  "type": "Feature",
  "properties": {
    "iso:country":"DE",
    "sg:address":"Frankfurter Str. 28",
    "sg:city":"Bad Vilbel",
    "sg:phone":"+49 6101/83852",
    "sg:postcode":"61118",
    "sg:province":"Hessen",
    "wof:name":"Nidda-apotheke",
    "wof:placetype":"venue"
},
  "geometry": {"coordinates":[8.742381,50.181946],"type":"Point"}
}