{
  "type": "Feature",
  "properties": {
    "iso:country":"DE",
    "sg:address":"Rosenw\u00e4ldchen 3",
    "sg:city":"Herborn",
    "sg:phone":"+49 2772/40303",
    "sg:postcode":"35745",
    "sg:province":"Hessen",
    "wof:name":"Hans Kessler Architekt",
    "wof:placetype":"venue"
},
  "geometry": {"coordinates":[8.307852,50.681366],"type":"Point"}
}