{
  "type": "Feature",
  "properties": {
    "iso:country":"DE",
    "sg:address":"Hauptstr. 51",
    "sg:city":"Ebensfeld",
    "sg:phone":"+49 9573/6449",
    "sg:postcode":"96250",
    "sg:province":"Bayern",
    "wof:name":"Gasthof E. Neuner",
    "wof:placetype":"venue"
},
  "geometry": {"coordinates":[10.9577512741,50.065372467],"type":"Point"}
}