{
  "type": "Feature",
  "properties": {
    "iso:country":"DE",
    "sg:address":"Dieselstr. 6",
    "sg:city":"Leonberg",
    "sg:phone":"+49 4971/5241627",
    "sg:postcode":"71229",
    "sg:province":"Baden-W\u00fcrttemberg",
    "wof:name":"Werner Jilg Lederwarenfabrikation Gmbh",
    "wof:placetype":"venue"
},
  "geometry": {"coordinates":[9.002972,48.79427],"type":"Point"}
}