{
  "type": "Feature",
  "properties": {
    "iso:country":"DE",
    "sg:address":"Rheingoldstr. 215 -217",
    "sg:city":"Mannheim",
    "sg:phone":"+49 621/20047",
    "sg:postcode":"68199",
    "sg:province":"Baden-W\u00fcrttemberg",
    "wof:name":"Vela Verwaltungsges. Mbh",
    "wof:placetype":"venue"
},
  "geometry": {"coordinates":[8.46891,49.450081],"type":"Point"}
}