{
  "type": "Feature",
  "properties": {
    "iso:country":"DE",
    "sg:address":"Lerchenstr. 20",
    "sg:city":"Kiel",
    "sg:phone":"+49 431/546320",
    "sg:postcode":"24103",
    "sg:province":"Schleswig-Holstein",
    "wof:name":"Lerchenhof-immobilien Gmbh",
    "wof:placetype":"venue"
},
  "geometry": {"coordinates":[10.129032135,54.3169975281],"type":"Point"}
}