{
  "type": "Feature",
  "properties": {
    "iso:country":"DE",
    "sg:address":"Am Gro\u00dfen Grunde 18",
    "sg:city":"Marl",
    "sg:phone":"+49 2365/81131",
    "sg:postcode":"45770",
    "sg:province":"Nordrhein-Westfalen",
    "wof:name":"Ralf Brinkmann Rechtsanwalt",
    "wof:placetype":"venue"
},
  "geometry": {"coordinates":[7.164044857,51.6635665894],"type":"Point"}
}