{
  "type": "Feature",
  "properties": {
    "iso:country":"DE",
    "sg:address":"Kirchstr. 22",
    "sg:city":"Wachtberg",
    "sg:phone":"+49 2225/10036",
    "sg:postcode":"53343",
    "sg:province":"Nordrhein-Westfalen",
    "wof:name":"Margarete Sch\u00f6neck",
    "wof:placetype":"venue"
},
  "geometry": {"coordinates":[7.061729908,50.6129608154],"type":"Point"}
}