{
  "type": "Feature",
  "properties": {
    "iso:country":"DE",
    "sg:address":"Avrillestr. 3",
    "sg:city":"Schwalbach",
    "sg:phone":"+49 6196/83722",
    "sg:postcode":"65824",
    "sg:province":"Hessen",
    "wof:name":"Pinguin-apotheke Inh. Lothar Schreck",
    "wof:placetype":"venue"
},
  "geometry": {"coordinates":[8.530205,50.153915],"type":"Point"}
}