{
  "type": "Feature",
  "properties": {
    "iso:country":"DE",
    "sg:address":"Wangener Str. 79",
    "sg:city":"Starnberg",
    "sg:phone":"+49 8151/8166",
    "sg:postcode":"82319",
    "sg:province":"Bayern",
    "wof:name":"Dr. Helmut E. Messerer Architekt",
    "wof:placetype":"venue"
},
  "geometry": {"coordinates":[11.376063,48.023727],"type":"Point"}
}