{
  "type": "Feature",
  "properties": {
    "iso:country":"DE",
    "sg:address":"Tonhallenstr. 14",
    "sg:city":"D\u00fcsseldorf",
    "sg:phone":"+49 211/367204",
    "sg:postcode":"40211",
    "sg:province":"Nordrhein-Westfalen",
    "wof:name":"Konsulat Von Finnland",
    "wof:placetype":"venue"
},
  "geometry": {"coordinates":[6.7882380486,51.2260169983],"type":"Point"}
}