{
  "type": "Feature",
  "properties": {
    "iso:country":"DE",
    "sg:address":"Froschgasse 20",
    "sg:city":"N\u00fcrnberg",
    "sg:phone":"+49 911/936970",
    "sg:postcode":"90427",
    "sg:province":"Bayern",
    "wof:name":"Digilog Automation Gmbh",
    "wof:placetype":"venue"
},
  "geometry": {"coordinates":[11.027841568,49.5170783997],"type":"Point"}
}