{
  "type": "Feature",
  "properties": {
    "iso:country":"DE",
    "sg:address":"Teichstr. 2",
    "sg:city":"Koblenz",
    "sg:phone":"+49 261/403695",
    "sg:postcode":"56072",
    "sg:province":"Rheinland-Pfalz",
    "wof:name":"Pizzeria La Palma",
    "wof:placetype":"venue"
},
  "geometry": {"coordinates":[7.548263073,50.3436279297],"type":"Point"}
}