{
  "type": "Feature",
  "properties": {
    "iso:country":"DE",
    "sg:address":"Bahnhofstr. 5 a",
    "sg:city":"Altenbeken",
    "sg:phone":"+49 5255/6229",
    "sg:postcode":"33184",
    "sg:province":"Nordrhein-Westfalen",
    "wof:name":"Wasserwerk Altenbeken",
    "wof:placetype":"venue"
},
  "geometry": {"coordinates":[8.94189,51.764782],"type":"Point"}
}