{
  "type": "Feature",
  "properties": {
    "iso:country":"DE",
    "sg:address":"An der Allee 6",
    "sg:city":"Wutha-Farnroda",
    "sg:postcode":"99848",
    "sg:province":"Th\u00fcringen",
    "wof:name":"Cardag Deutschland Gmbh",
    "wof:placetype":"venue"
},
  "geometry": {"coordinates":[10.390714,50.949589],"type":"Point"}
}