{
  "type": "Feature",
  "properties": {
    "iso:country":"DE",
    "sg:address":"Unter Mastein 2",
    "sg:city":"Schweich",
    "sg:phone":"+49 6502/99200",
    "sg:postcode":"54338",
    "sg:province":"Rheinland-Pfalz",
    "wof:name":"Helfende H\u00e4nde",
    "wof:placetype":"venue"
},
  "geometry": {"coordinates":[6.748738,49.820221],"type":"Point"}
}