{
  "type": "Feature",
  "properties": {
    "iso:country":"DE",
    "sg:address":"Ziegelweg 11",
    "sg:city":"Gro\u00dfkarolinenfeld",
    "sg:phone":"+49 8031/50111",
    "sg:postcode":"83109",
    "sg:province":"Bayern",
    "wof:name":"J. Fasolt Hebamme",
    "wof:placetype":"venue"
},
  "geometry": {"coordinates":[12.083226,47.885925],"type":"Point"}
}