{
  "type": "Feature",
  "properties": {
    "iso:country":"DE",
    "sg:address":"Franz-Marc-Str. 8 a",
    "sg:city":"Elmshorn",
    "sg:phone":"+49 4121/92085",
    "sg:postcode":"25336",
    "sg:province":"Schleswig-Holstein",
    "wof:name":"Spezialsatz Lothar Wolf",
    "wof:placetype":"venue"
},
  "geometry": {"coordinates":[9.6450634003,53.7375183105],"type":"Point"}
}