{
  "type": "Feature",
  "properties": {
    "iso:country":"DE",
    "sg:address":"Charlottenstr. 1",
    "sg:city":"Friedrichshafen",
    "sg:phone":"+49 7541/92330",
    "sg:postcode":"88045",
    "sg:province":"Baden-W\u00fcrttemberg",
    "wof:name":"Hotel Goldener Hirsch",
    "wof:placetype":"venue"
},
  "geometry": {"coordinates":[9.4758329391,47.6540870667],"type":"Point"}
}