{
  "type": "Feature",
  "properties": {
    "iso:country":"DE",
    "sg:address":"Alter Schlo\u00dfberg 3",
    "sg:city":"Pforzheim",
    "sg:phone":"+49 7231/314085",
    "sg:postcode":"75175",
    "sg:province":"Baden-W\u00fcrttemberg",
    "wof:name":"Joseph Schrey Gmbh & Co. Kg",
    "wof:placetype":"venue"
},
  "geometry": {"coordinates":[8.702025,48.89172],"type":"Point"}
}