{
  "type": "Feature",
  "properties": {
    "iso:country":"DE",
    "sg:address":"Am Schieferberg 4",
    "sg:city":"Kelkheim",
    "sg:phone":"+49 6195/5454",
    "sg:postcode":"65779",
    "sg:province":"Hessen",
    "wof:name":"Franz Althen Pr\u00e4zisionswerkzeuge Gmbh",
    "wof:placetype":"venue"
},
  "geometry": {"coordinates":[8.459222,50.133663],"type":"Point"}
}