{
  "type": "Feature",
  "properties": {
    "iso:country":"DE",
    "sg:address":"Ilseder Str. 2",
    "sg:city":"Peine",
    "sg:phone":"+49 5171/17727",
    "sg:postcode":"31226",
    "sg:province":"Niedersachsen",
    "wof:name":"Michael D. K\u00f6hler",
    "wof:placetype":"venue"
},
  "geometry": {"coordinates":[10.231921,52.316147],"type":"Point"}
}