{
  "type": "Feature",
  "properties": {
    "iso:country":"DE",
    "sg:address":"Versmolder Str. 33",
    "sg:city":"Bad Laer",
    "sg:phone":"+49 5424/70915",
    "sg:postcode":"49196",
    "sg:province":"Niedersachsen",
    "wof:name":"M. Koch",
    "wof:placetype":"venue"
},
  "geometry": {"coordinates":[8.1218614578,52.07629776],"type":"Point"}
}