{
  "type": "Feature",
  "properties": {
    "iso:country":"DE",
    "sg:address":"Stadtlohner Str. 17",
    "sg:city":"Ahaus",
    "sg:phone":"+49 2561/82008",
    "sg:postcode":"48683",
    "sg:province":"Nordrhein-Westfalen",
    "wof:name":"Josef D\u00f6rken",
    "wof:placetype":"venue"
},
  "geometry": {"coordinates":[6.9816842079,52.0675201416],"type":"Point"}
}