{
  "type": "Feature",
  "properties": {
    "iso:country":"DE",
    "sg:address":"Dollendorfer Str. 42",
    "sg:city":"K\u00f6nigswinter",
    "sg:phone":"+49 2223/7878",
    "sg:postcode":"53639",
    "sg:province":"Nordrhein-Westfalen",
    "wof:name":"U. Bruch Heilpraktiker",
    "wof:placetype":"venue"
},
  "geometry": {"coordinates":[7.232899189,50.6970787048],"type":"Point"}
}