{
  "type": "Feature",
  "properties": {
    "iso:country":"DE",
    "sg:address":"ElsenheimerStra\u00dfe",
    "sg:city":"M\u00fcnchen",
    "sg:postcode":"80687",
    "sg:province":"Bayern",
    "wof:name":"Ksw Satz Repro Gmbh",
    "wof:placetype":"venue"
},
  "geometry": {"coordinates":[11.519681,48.139191],"type":"Point"}
}