{
  "type": "Feature",
  "properties": {
    "iso:country":"DE",
    "sg:address":"Franzstr",
    "sg:city":"Bocholt",
    "sg:phone":"+49 2871/952204",
    "sg:postcode":"46395",
    "sg:province":"Nordrhein-Westfalen",
    "wof:name":"Volksbank Bocholt Eg",
    "wof:placetype":"venue"
},
  "geometry": {"coordinates":[6.622355,51.834122],"type":"Point"}
}