{
  "type": "Feature",
  "properties": {
    "iso:country":"DE",
    "sg:address":"Am Metternicher Bahnhof 11",
    "sg:city":"Koblenz",
    "sg:postcode":"56072",
    "sg:province":"Rheinland-Pfalz",
    "wof:name":"Kcf Promotional Products Deutschland Gmbh",
    "wof:placetype":"venue"
},
  "geometry": {"coordinates":[7.5539717674,50.3698387146],"type":"Point"}
}