{
  "type": "Feature",
  "properties": {
    "iso:country":"DE",
    "sg:address":"An der Martinischule 4",
    "sg:city":"Greven",
    "sg:phone":"+49 2571/53357",
    "sg:postcode":"48268",
    "sg:province":"Nordrhein-Westfalen",
    "wof:name":"Christel Burgstett",
    "wof:placetype":"venue"
},
  "geometry": {"coordinates":[7.613315,52.093193],"type":"Point"}
}