{
  "type": "Feature",
  "properties": {
    "iso:country":"DE",
    "sg:address":"Schulstr. 34",
    "sg:city":"Waldeck",
    "sg:phone":"+49 5623/5547",
    "sg:postcode":"34513",
    "sg:province":"Hessen",
    "wof:name":"Gasthaus Hermann Schaumburg",
    "wof:placetype":"venue"
},
  "geometry": {"coordinates":[9.0651931763,51.2048873901],"type":"Point"}
}