{
  "type": "Feature",
  "properties": {
    "iso:country":"DE",
    "sg:address":"Hauptstr. 18",
    "sg:city":"M\u00fchlhausen",
    "sg:phone":"+49 9548/1519",
    "sg:postcode":"96172",
    "sg:province":"Bayern",
    "wof:name":"Georg Hertlein",
    "wof:placetype":"venue"
},
  "geometry": {"coordinates":[10.7732925415,49.7533454895],"type":"Point"}
}