{
  "type": "Feature",
  "properties": {
    "iso:country":"DE",
    "sg:address":"Marktplatz 10",
    "sg:city":"Ellwangen",
    "sg:phone":"+49 7961/2271",
    "sg:postcode":"73479",
    "sg:province":"Baden-W\u00fcrttemberg",
    "wof:name":"Gasthaus Josef Rief",
    "wof:placetype":"venue"
},
  "geometry": {"coordinates":[10.1306877136,48.9616546631],"type":"Point"}
}