{
  "type": "Feature",
  "properties": {
    "iso:country":"DE",
    "sg:address":"H\u00f6ntjebarg 63",
    "sg:city":"Varel",
    "sg:phone":"+49 4451/2063",
    "sg:postcode":"26316",
    "sg:province":"Niedersachsen",
    "wof:name":"Hans-georg Buschmann",
    "wof:placetype":"venue"
},
  "geometry": {"coordinates":[8.092039,53.404472],"type":"Point"}
}