{
  "type": "Feature",
  "properties": {
    "iso:country":"DE",
    "sg:address":"Zeppelinstr. 28",
    "sg:city":"L\u00fcneburg",
    "sg:phone":"+49 4131/87070",
    "sg:postcode":"21337",
    "sg:province":"Niedersachsen",
    "wof:name":"Dr. Scholze Confiserie Kg",
    "wof:placetype":"venue"
},
  "geometry": {"coordinates":[10.463697,53.248024],"type":"Point"}
}