{
  "type": "Feature",
  "properties": {
    "iso:country":"DE",
    "sg:address":"Lahnstr. 10",
    "sg:city":"Netphen",
    "sg:phone":"+49 2738/1294",
    "sg:postcode":"57250",
    "sg:province":"Nordrhein-Westfalen",
    "wof:name":"Horst G\u00f6bel",
    "wof:placetype":"venue"
},
  "geometry": {"coordinates":[8.099708,50.913853],"type":"Point"}
}