{
  "type": "Feature",
  "properties": {
    "iso:country":"DE",
    "sg:address":"Fordeweg 2",
    "sg:city":"Saterland",
    "sg:phone":"+49 4498/1608",
    "sg:postcode":"26683",
    "sg:province":"Niedersachsen",
    "wof:name":"Bernhard Kruse",
    "wof:placetype":"venue"
},
  "geometry": {"coordinates":[7.668428,53.10379],"type":"Point"}
}