{
  "type": "Feature",
  "properties": {
    "iso:country":"DE",
    "sg:address":"Stickgraser Damm 124",
    "sg:city":"Delmenhorst",
    "sg:phone":"+49 4221/72544",
    "sg:postcode":"27749",
    "sg:province":"Niedersachsen",
    "wof:name":"Restaurant Adriatik",
    "wof:placetype":"venue"
},
  "geometry": {"coordinates":[8.6514282227,53.0471839905],"type":"Point"}
}