{
  "type": "Feature",
  "properties": {
    "iso:country":"DE",
    "sg:address":"Am Kirchengut 16",
    "sg:city":"Demmin",
    "sg:phone":"+49 3998/222264",
    "sg:postcode":"17109",
    "sg:province":"Mecklenburg-Vorpommern",
    "wof:name":"S. Zalewski Finanzberater",
    "wof:placetype":"venue"
},
  "geometry": {"coordinates":[13.0661354065,53.901058197],"type":"Point"}
}