{
  "type": "Feature",
  "properties": {
    "iso:country":"DE",
    "sg:address":"Schillerstr. 13",
    "sg:city":"K\u00f6nigsbach-Stein",
    "sg:phone":"+49 7232/9148",
    "sg:postcode":"75203",
    "sg:province":"Baden-W\u00fcrttemberg",
    "wof:name":"Gerhard Mannsd\u00f6rfer",
    "wof:placetype":"venue"
},
  "geometry": {"coordinates":[8.614521,48.959953],"type":"Point"}
}