{
  "type": "Feature",
  "properties": {
    "iso:country":"DE",
    "sg:address":"Walter-Flex-Str. 4",
    "sg:city":"Hof",
    "sg:postcode":"95032",
    "sg:province":"Bayern",
    "wof:name":"Afs Bau Und Immobilien Gmbh",
    "wof:placetype":"venue"
},
  "geometry": {"coordinates":[11.906595,50.297527],"type":"Point"}
}