{
  "type": "Feature",
  "properties": {
    "iso:country":"DE",
    "sg:address":"Lagerstr. 6",
    "sg:city":"Meschede",
    "sg:phone":"+49 291/3689",
    "sg:postcode":"59872",
    "sg:province":"Nordrhein-Westfalen",
    "wof:name":"Dr. Med. Thomas R\u00f6hrig",
    "wof:placetype":"venue"
},
  "geometry": {"coordinates":[8.2800960541,51.3501014709],"type":"Point"}
}