{
  "type": "Feature",
  "properties": {
    "iso:country":"DE",
    "sg:address":"Schlachthofstr. 1a",
    "sg:city":"Sta\u00dffurt",
    "sg:phone":"+49 3925/625182",
    "sg:postcode":"39418",
    "sg:province":"Sachsen-Anhalt",
    "wof:name":"Dieter Tr\u00fcmper",
    "wof:placetype":"venue"
},
  "geometry": {"coordinates":[11.589181,51.855724],"type":"Point"}
}