{
  "type": "Feature",
  "properties": {
    "iso:country":"DE",
    "sg:address":"Lindauer Str. 3",
    "sg:city":"Kempten",
    "sg:phone":"+49 831/24024",
    "sg:postcode":"87435",
    "sg:province":"Bayern",
    "wof:name":"Heinz Bufler",
    "wof:placetype":"venue"
},
  "geometry": {"coordinates":[10.3104019165,47.7236404419],"type":"Point"}
}