{
  "type": "Feature",
  "properties": {
    "iso:country":"DE",
    "sg:address":"In der Weede 137",
    "sg:city":"M\u00fcnster",
    "sg:phone":"+49 2536/8477",
    "sg:postcode":"48163",
    "sg:province":"Nordrhein-Westfalen",
    "wof:name":"A. T. I. Gmbh",
    "wof:placetype":"venue"
},
  "geometry": {"coordinates":[7.5238900185,51.9218406677],"type":"Point"}
}