{
  "type": "Feature",
  "properties": {
    "iso:country":"DE",
    "sg:address":"Borsteler Bogen 27",
    "sg:city":"Hamburg",
    "sg:phone":"+49 40/5533948",
    "sg:postcode":"22453",
    "sg:province":"Hamburg",
    "wof:name":"Franz Hering",
    "wof:placetype":"venue"
},
  "geometry": {"coordinates":[9.972345,53.612289],"type":"Point"}
}