{
  "type": "Feature",
  "properties": {
    "iso:country":"DE",
    "sg:address":"Wilhelmstr. 2",
    "sg:city":"Dallgow",
    "sg:postcode":"14624",
    "sg:province":"Brandenburg",
    "wof:name":"Katholisches Pfarramt Dallgow",
    "wof:placetype":"venue"
},
  "geometry": {"coordinates":[13.054725647,52.5427017212],"type":"Point"}
}