{
  "type": "Feature",
  "properties": {
    "iso:country":"DE",
    "sg:address":"Aminghauser Str. 52 g",
    "sg:city":"Minden",
    "sg:phone":"+49 571/387040",
    "sg:postcode":"32423",
    "sg:province":"Nordrhein-Westfalen",
    "wof:name":"Westfalen Ag",
    "wof:placetype":"venue"
},
  "geometry": {"coordinates":[8.9145956039,52.2885742188],"type":"Point"}
}