{
  "type": "Feature",
  "properties": {
    "iso:country":"DE",
    "sg:address":"Hausstattstr. 4",
    "sg:city":"Raubling",
    "sg:phone":"+49 8035/3145",
    "sg:postcode":"83064",
    "sg:province":"Bayern",
    "wof:name":"Thomas & Veronika Rechenauer",
    "wof:placetype":"venue"
},
  "geometry": {"coordinates":[12.1124925613,47.7670898438],"type":"Point"}
}