{
  "type": "Feature",
  "properties": {
    "iso:country":"DE",
    "sg:address":"Bandstr. 35",
    "sg:city":"Essen",
    "sg:phone":"+49 201/603746",
    "sg:postcode":"45359",
    "sg:province":"Nordrhein-Westfalen",
    "wof:name":"Ev.\u00f6ffentliche Bibliothek Der Kirchengem. Bedingrade-",
    "wof:placetype":"venue"
},
  "geometry": {"coordinates":[6.928337,51.464523],"type":"Point"}
}