{
  "type": "Feature",
  "properties": {
    "iso:country":"DE",
    "sg:address":"N\u00f6rdlinger Str. 2",
    "sg:city":"Oettingen",
    "sg:phone":"+49 9082/3207",
    "sg:postcode":"86732",
    "sg:province":"Bayern",
    "wof:name":"Pizzeria Romana",
    "wof:placetype":"venue"
},
  "geometry": {"coordinates":[10.5764112473,48.9453849792],"type":"Point"}
}