{
  "type": "Feature",
  "properties": {
    "iso:country":"DE",
    "sg:address":"Weinheimer Str. 32",
    "sg:city":"F\u00fcrth",
    "sg:phone":"+49 6253/85876",
    "sg:postcode":"64658",
    "sg:province":"Hessen",
    "wof:name":"Annette Cech Heilpraktikerin",
    "wof:placetype":"venue"
},
  "geometry": {"coordinates":[8.7610301971,49.6392707825],"type":"Point"}
}