{
  "type": "Feature",
  "properties": {
    "iso:country":"DE",
    "sg:address":"Stra\u00dfburger Str. 23",
    "sg:city":"Stuttgart",
    "sg:phone":"+49 711/8790108",
    "sg:postcode":"70435",
    "sg:province":"Baden-W\u00fcrttemberg",
    "wof:name":"Drei Mohren",
    "wof:placetype":"venue"
},
  "geometry": {"coordinates":[9.1724891663,48.8297653198],"type":"Point"}
}