{
  "type": "Feature",
  "properties": {
    "iso:country":"DE",
    "sg:address":"Winterseitenweg 53",
    "sg:city":"Baiersbronn",
    "sg:phone":"+49 7442/121297",
    "sg:postcode":"72270",
    "sg:province":"Baden-W\u00fcrttemberg",
    "wof:name":"Karl Finkbeiner",
    "wof:placetype":"venue"
},
  "geometry": {"coordinates":[8.35416,48.509903],"type":"Point"}
}