{
  "type": "Feature",
  "properties": {
    "iso:country":"DE",
    "sg:address":"Ahrallee 39",
    "sg:city":"Bad Neuenahr-Ahrweiler",
    "sg:phone":"+49 2641/5890",
    "sg:postcode":"53474",
    "sg:province":"Rheinland-Pfalz",
    "wof:name":"Avenida",
    "wof:placetype":"venue"
},
  "geometry": {"coordinates":[7.107296,50.540359],"type":"Point"}
}