{
  "type": "Feature",
  "properties": {
    "iso:country":"DE",
    "sg:address":"Carl-von-Essen-Str. 10",
    "sg:city":"Stralsund",
    "sg:postcode":"18435",
    "sg:province":"Mecklenburg-Vorpommern",
    "wof:name":"Dr. Med. Anke Kraft",
    "wof:placetype":"venue"
},
  "geometry": {"coordinates":[13.076925,54.319412],"type":"Point"}
}