{
  "type": "Feature",
  "properties": {
    "iso:country":"DE",
    "sg:address":"Bahnhofstr. 15",
    "sg:city":"M\u00fchlacker",
    "sg:phone":"+49 7041/6282",
    "sg:postcode":"75417",
    "sg:province":"Baden-W\u00fcrttemberg",
    "wof:name":"Fuchs Kr\u00fcger Und Constroffer",
    "wof:placetype":"venue"
},
  "geometry": {"coordinates":[8.840045929,48.9472618103],"type":"Point"}
}