{
  "type": "Feature",
  "properties": {
    "iso:country":"DE",
    "sg:address":"Parkstr. 22",
    "sg:city":"Klosterfelde",
    "sg:phone":"+49 33396/372",
    "sg:postcode":"16348",
    "sg:province":"Brandenburg",
    "wof:name":"Klaus Pawlowski Anlageberater",
    "wof:placetype":"venue"
},
  "geometry": {"coordinates":[13.4823198318,52.80260849],"type":"Point"}
}