{
  "type": "Feature",
  "properties": {
    "iso:country":"DE",
    "sg:address":"Haldenstr. 15",
    "sg:city":"Riedlingen",
    "sg:phone":"+49 7371/12241",
    "sg:postcode":"88499",
    "sg:province":"Baden-W\u00fcrttemberg",
    "wof:name":"J\u00f6rg Ulrich Engel-drogerie",
    "wof:placetype":"venue"
},
  "geometry": {"coordinates":[9.475612,48.152855],"type":"Point"}
}