{
  "type": "Feature",
  "properties": {
    "iso:country":"DE",
    "sg:address":"Oebisfelder Str. 4",
    "sg:city":"Calv\u00f6rde",
    "sg:phone":"+49 39051/5500",
    "sg:postcode":"39359",
    "sg:province":"Sachsen-Anhalt",
    "wof:name":"Baugesch\u00e4ft Kurt Loh\u00f6fer Gmbh & Co. Kg",
    "wof:placetype":"venue"
},
  "geometry": {"coordinates":[11.29213,52.395233],"type":"Point"}
}