{
  "type": "Feature",
  "properties": {
    "iso:country":"DE",
    "sg:address":"Th\u00e4lmannstr. 91 f",
    "sg:city":"Spickendorf",
    "sg:postcode":"06188",
    "sg:province":"Sachsen-Anhalt",
    "wof:name":"Detektei Und Sicherungsdienst Dirk Hasse E. Kfm.",
    "wof:placetype":"venue"
},
  "geometry": {"coordinates":[12.105232,51.52739],"type":"Point"}
}