{
  "type": "Feature",
  "properties": {
    "iso:country":"DE",
    "sg:address":"Zur Heide 11",
    "sg:city":"Guckheim",
    "sg:phone":"+49 6435/2222",
    "sg:postcode":"56459",
    "sg:province":"Rheinland-Pfalz",
    "wof:name":"T. Jung",
    "wof:placetype":"venue"
},
  "geometry": {"coordinates":[7.943789959,50.5272712708],"type":"Point"}
}