{
  "type": "Feature",
  "properties": {
    "iso:country":"DE",
    "sg:address":"Motardstr. 82",
    "sg:city":"Berlin",
    "sg:phone":"+49 30/3839520",
    "sg:postcode":"13629",
    "sg:province":"Berlin",
    "wof:name":"Heckel & Partner Hebelift Vertriebs Gmbh",
    "wof:placetype":"venue"
},
  "geometry": {"coordinates":[13.25748,52.534721],"type":"Point"}
}