{
  "type": "Feature",
  "properties": {
    "iso:country":"DE",
    "sg:address":"Deelb\u00f6genkamp 5",
    "sg:city":"Hamburg",
    "sg:phone":"+49 40/5119450",
    "sg:postcode":"22297",
    "sg:province":"Hamburg",
    "wof:name":"Theodor Orgass",
    "wof:placetype":"venue"
},
  "geometry": {"coordinates":[9.9909772873,53.6023597717],"type":"Point"}
}