{
  "type": "Feature",
  "properties": {
    "iso:country":"DE",
    "sg:address":"Beethovenstra\u00dfe 9",
    "sg:city":"Dossenheim",
    "sg:phone":"+49 6221/861965",
    "sg:postcode":"69221",
    "sg:province":"Baden-W\u00fcrttemberg",
    "wof:name":"Funpage24",
    "wof:placetype":"venue"
},
  "geometry": {"coordinates":[8.67263,49.448082],"type":"Point"}
}