{
  "type": "Feature",
  "properties": {
    "iso:country":"DE",
    "sg:address":"Paul-M\u00fcller-Str. 45",
    "sg:city":"Freiberg",
    "sg:phone":"+49 3731/245216",
    "sg:postcode":"09599",
    "sg:province":"Sachsen",
    "wof:name":"Dr. Dieter Vogel",
    "wof:placetype":"venue"
},
  "geometry": {"coordinates":[13.3226222992,50.9191589355],"type":"Point"}
}