{
  "type": "Feature",
  "properties": {
    "iso:country":"DE",
    "sg:address":"Hillnh\u00fctter Str. 76",
    "sg:city":"Hilchenbach",
    "sg:phone":"+49 2733/51182",
    "sg:postcode":"57271",
    "sg:province":"Nordrhein-Westfalen",
    "wof:name":"Werner D\u00fcrre Heilpraktiker",
    "wof:placetype":"venue"
},
  "geometry": {"coordinates":[8.0632648468,50.9724273682],"type":"Point"}
}