{
  "type": "Feature",
  "properties": {
    "iso:country":"DE",
    "sg:address":"Fuchsberg 61",
    "sg:city":"Teunz",
    "sg:phone":"+49 9671/679",
    "sg:postcode":"92552",
    "sg:province":"Bayern",
    "wof:name":"Wilhelm Greber",
    "wof:placetype":"venue"
},
  "geometry": {"coordinates":[12.397069931,49.4961853027],"type":"Point"}
}