{
  "type": "Feature",
  "properties": {
    "iso:country":"DE",
    "sg:address":"Auf der H\u00f6he 3",
    "sg:city":"Windhausen",
    "sg:phone":"+49 5327/859446",
    "sg:postcode":"37539",
    "sg:province":"Niedersachsen",
    "wof:name":"M. Sturm",
    "wof:placetype":"venue"
},
  "geometry": {"coordinates":[10.2121925354,51.7884407043],"type":"Point"}
}