{
  "type": "Feature",
  "properties": {
    "iso:country":"DE",
    "sg:address":"Kr\u00f6llstr. 7",
    "sg:city":"Grafenau",
    "sg:phone":"+49 8552/408980",
    "sg:postcode":"94481",
    "sg:province":"Bayern",
    "wof:name":"Maria Blach",
    "wof:placetype":"venue"
},
  "geometry": {"coordinates":[13.3958511353,48.8547554016],"type":"Point"}
}