{
  "type": "Feature",
  "properties": {
    "iso:country":"DE",
    "sg:address":"Lindenweg 5",
    "sg:city":"Aindling",
    "sg:phone":"+49 8237/951968",
    "sg:postcode":"86447",
    "sg:province":"Bayern",
    "wof:name":"H. Hiller",
    "wof:placetype":"venue"
},
  "geometry": {"coordinates":[10.9653301239,48.5318183899],"type":"Point"}
}