{
  "type": "Feature",
  "properties": {
    "iso:country":"DE",
    "sg:address":"Kornstr. 1",
    "sg:city":"Meppen",
    "sg:phone":"+49 5931/17662",
    "sg:postcode":"49716",
    "sg:province":"Niedersachsen",
    "wof:name":"Maria Rothk\u00f6tter Farmbetriebe Gmbh",
    "wof:placetype":"venue"
},
  "geometry": {"coordinates":[7.220713,52.717861],"type":"Point"}
}