{
  "type": "Feature",
  "properties": {
    "iso:country":"DE",
    "sg:address":"Pfarrer-Jung-Str. 2",
    "sg:city":"Effeltrich",
    "sg:phone":"+49 9133/2670",
    "sg:postcode":"91090",
    "sg:province":"Bayern",
    "wof:name":"Engelbert Erner",
    "wof:placetype":"venue"
},
  "geometry": {"coordinates":[11.08977,49.660984],"type":"Point"}
}