{
  "type": "Feature",
  "properties": {
    "iso:country":"DE",
    "sg:address":"Steigerwaldstr. 19",
    "sg:city":"L\u00fclsfeld",
    "sg:phone":"+49 9382/8749",
    "sg:postcode":"97511",
    "sg:province":"Bayern",
    "wof:name":"Georg Grembler",
    "wof:placetype":"venue"
},
  "geometry": {"coordinates":[10.3235969543,49.8656921387],"type":"Point"}
}