{
  "type": "Feature",
  "properties": {
    "iso:country":"DE",
    "sg:address":"Fuchst\u00e4lchen",
    "sg:city":"Saarbr\u00fccken",
    "sg:postcode":"66123",
    "sg:province":"Saarland",
    "wof:name":"Universit\u00e4t Studienberatung",
    "wof:placetype":"venue"
},
  "geometry": {"coordinates":[7.0272340775,49.2472267151],"type":"Point"}
}