{
  "type": "Feature",
  "properties": {
    "iso:country":"DE",
    "sg:address":"Regerstr. 76",
    "sg:city":"Solingen",
    "sg:phone":"+49 212/810900",
    "sg:postcode":"42657",
    "sg:province":"Nordrhein-Westfalen",
    "wof:name":"H. Peters",
    "wof:placetype":"venue"
},
  "geometry": {"coordinates":[7.0672497749,51.150138855],"type":"Point"}
}