{
  "type": "Feature",
  "properties": {
    "iso:country":"DE",
    "sg:address":"Hauptstr. 7",
    "sg:city":"Simmerath",
    "sg:phone":"+49 2473/8002",
    "sg:postcode":"52152",
    "sg:province":"Nordrhein-Westfalen",
    "wof:name":"Inductotherm Deutschland Gmbh",
    "wof:placetype":"venue"
},
  "geometry": {"coordinates":[6.30424,50.617508],"type":"Point"}
}