{
  "type": "Feature",
  "properties": {
    "iso:country":"DE",
    "sg:address":"Feldstr. 203",
    "sg:city":"Goch",
    "sg:phone":"+49 4928/2392410",
    "sg:postcode":"47574",
    "sg:province":"Nordrhein-Westfalen",
    "wof:name":"Minerva Spirituosen Gmbh & Co Betriebs Kg",
    "wof:placetype":"venue"
},
  "geometry": {"coordinates":[6.154404,51.692795],"type":"Point"}
}