{
  "type": "Feature",
  "properties": {
    "iso:country":"DE",
    "sg:address":"H\u00e4ndelstr. 33",
    "sg:city":"K\u00f6ln",
    "sg:phone":"+49 221/236855",
    "sg:postcode":"50674",
    "sg:province":"Nordrhein-Westfalen",
    "wof:name":"Restaurant Tandoor Palace",
    "wof:placetype":"venue"
},
  "geometry": {"coordinates":[6.9362912178,50.9349365234],"type":"Point"}
}