{
  "type": "Feature",
  "properties": {
    "iso:country":"DE",
    "sg:address":"Triftstr. 33",
    "sg:city":"Oberau",
    "sg:phone":"+49 8824/8423",
    "sg:postcode":"82496",
    "sg:province":"Bayern",
    "wof:name":"G. Weber",
    "wof:placetype":"venue"
},
  "geometry": {"coordinates":[11.138328,47.56583],"type":"Point"}
}