{
  "type": "Feature",
  "properties": {
    "iso:country":"DE",
    "sg:address":"Poststr. 6",
    "sg:city":"Vlotho",
    "sg:phone":"+49 4957/337891",
    "sg:postcode":"32602",
    "sg:province":"Nordrhein-Westfalen",
    "wof:name":"Willi Bloos",
    "wof:placetype":"venue"
},
  "geometry": {"coordinates":[8.863196,52.166809],"type":"Point"}
}