{
  "type": "Feature",
  "properties": {
    "iso:country":"DE",
    "sg:address":"Gai\u00dfacher Str. 28",
    "sg:city":"Lenggries",
    "sg:phone":"+49 8042/8763",
    "sg:postcode":"83661",
    "sg:province":"Bayern",
    "wof:name":"Hans Epp",
    "wof:placetype":"venue"
},
  "geometry": {"coordinates":[11.575322,47.68586],"type":"Point"}
}