{
  "type": "Feature",
  "properties": {
    "iso:country":"DE",
    "sg:address":"Heidstr. 117",
    "sg:city":"Herne",
    "sg:phone":"+49 2325/580055",
    "sg:postcode":"44649",
    "sg:province":"Nordrhein-Westfalen",
    "wof:name":"Ivg Mbh",
    "wof:placetype":"venue"
},
  "geometry": {"coordinates":[7.1589741707,51.5391159058],"type":"Point"}
}