{
  "type": "Feature",
  "properties": {
    "iso:country":"DE",
    "sg:address":"Altbrandsleber Weg 11",
    "sg:city":"Schermcke",
    "sg:phone":"+49 39407/5945",
    "sg:postcode":"39387",
    "sg:province":"Sachsen-Anhalt",
    "wof:name":"Sapu Gmbh",
    "wof:placetype":"venue"
},
  "geometry": {"coordinates":[11.283891,52.056698],"type":"Point"}
}