{
  "type": "Feature",
  "properties": {
    "iso:country":"DE",
    "sg:address":"Gewerbegebiet 2",
    "sg:city":"Schalkau",
    "sg:phone":"+49 36766/2960",
    "sg:postcode":"96528",
    "sg:province":"Th\u00fcringen",
    "wof:name":"Zwergnase",
    "wof:placetype":"venue"
},
  "geometry": {"coordinates":[10.996462,50.400806],"type":"Point"}
}