{
  "type": "Feature",
  "properties": {
    "iso:country":"DE",
    "sg:address":"Lauerskreuz 9",
    "sg:city":"Neckargerach",
    "sg:phone":"+49 6263/45274",
    "sg:postcode":"69437",
    "sg:province":"Baden-W\u00fcrttemberg",
    "wof:name":"Stark & Co. Gmbh",
    "wof:placetype":"venue"
},
  "geometry": {"coordinates":[9.073857,49.415287],"type":"Point"}
}