{
  "type": "Feature",
  "properties": {
    "iso:country":"DE",
    "sg:address":"Philosophenweg 19",
    "sg:city":"Duisburg",
    "sg:phone":"+49 2066/99640",
    "sg:postcode":"47051",
    "sg:province":"Nordrhein-Westfalen",
    "wof:name":"Asku-scholten Gmbh",
    "wof:placetype":"venue"
},
  "geometry": {"coordinates":[6.768577,51.440025],"type":"Point"}
}