{
  "type": "Feature",
  "properties": {
    "iso:country":"DE",
    "sg:address":"Engesserstr 8",
    "sg:city":"Freiburg",
    "sg:phone":"+49 761/5110",
    "sg:postcode":"79108",
    "sg:province":"Baden-W\u00fcrttemberg",
    "wof:name":"Nylstar Gmbh",
    "wof:placetype":"venue"
},
  "geometry": {"coordinates":[7.8462347984,48.0206565857],"type":"Point"}
}