{
  "type": "Feature",
  "properties": {
    "iso:country":"DE",
    "sg:address":"Hindenburgstr. 26 a",
    "sg:city":"P\u00f6cking",
    "sg:postcode":"82343",
    "sg:province":"Bayern",
    "wof:name":"Fitas Verwaltung Gmbh & Co. Dritte Vermietungs-kg",
    "wof:placetype":"venue"
},
  "geometry": {"coordinates":[11.3049669266,47.9644851685],"type":"Point"}
}