{
  "type": "Feature",
  "properties": {
    "iso:country":"DE",
    "sg:address":"D\u00f6bra",
    "sg:city":"Schwarzenbach a Wald",
    "sg:phone":"+49 9289/6619",
    "sg:postcode":"95131",
    "sg:province":"Bayern",
    "wof:name":"Helga Hauei\u00dfen Architektin",
    "wof:placetype":"venue"
},
  "geometry": {"coordinates":[11.656946,50.281815],"type":"Point"}
}