{
  "type": "Feature",
  "properties": {
    "iso:country":"DE",
    "sg:address":"Nesserlander Str. 1",
    "sg:city":"Emden",
    "sg:phone":"+49 4921/93190",
    "sg:postcode":"26721",
    "sg:province":"Niedersachsen",
    "wof:name":"Embdena Treuhand Und Verwaltung Gmbh",
    "wof:placetype":"venue"
},
  "geometry": {"coordinates":[7.204046,53.362881],"type":"Point"}
}