{
  "type": "Feature",
  "properties": {
    "iso:country":"DE",
    "sg:address":"Rh\u00f6nstr. 14",
    "sg:city":"Eichenzell",
    "sg:phone":"+49 6656/1373",
    "sg:postcode":"36124",
    "sg:province":"Hessen",
    "wof:name":"V. Maehl Masseur",
    "wof:placetype":"venue"
},
  "geometry": {"coordinates":[9.754599,50.477257],"type":"Point"}
}