{
  "type": "Feature",
  "properties": {
    "iso:country":"DE",
    "sg:address":"Kapellenstr. 58",
    "sg:city":"Aachen",
    "sg:phone":"+49 241/67526",
    "sg:postcode":"52066",
    "sg:province":"Nordrhein-Westfalen",
    "wof:name":"Hilde Fr\u00fchauf Steuerbevollm\u00e4chtigte",
    "wof:placetype":"venue"
},
  "geometry": {"coordinates":[6.093875885,50.7598838806],"type":"Point"}
}