{
  "type": "Feature",
  "properties": {
    "iso:country":"DE",
    "sg:address":"Beiersdorfstra\u00dfe 7",
    "sg:city":"Emmerich",
    "sg:postcode":"46446",
    "sg:province":"Nordrhein-Westfalen",
    "wof:name":"Werkzeughandel Emmerich",
    "wof:placetype":"venue"
},
  "geometry": {"coordinates":[6.272789,51.839825],"type":"Point"}
}