{
  "type": "Feature",
  "properties": {
    "iso:country":"DE",
    "sg:address":"Herrenm\u00fchle 1",
    "sg:city":"Friesdorf",
    "sg:phone":"+49 34775/21411",
    "sg:postcode":"06543",
    "sg:province":"Sachsen-Anhalt",
    "wof:name":"Pension Herrenm\u00fchle",
    "wof:placetype":"venue"
},
  "geometry": {"coordinates":[11.3128595352,51.593624115],"type":"Point"}
}