{
  "type": "Feature",
  "properties": {
    "iso:country":"DE",
    "sg:address":"Osterstr. 27",
    "sg:city":"M\u00fcnsterdorf",
    "sg:phone":"+49 4821",
    "sg:postcode":"25587",
    "sg:province":"Schleswig-Holstein",
    "wof:name":"Nordisk Panorama",
    "wof:placetype":"venue"
},
  "geometry": {"coordinates":[9.5478725433,53.903629303],"type":"Point"}
}