{
  "type": "Feature",
  "properties": {
    "iso:country":"DE",
    "sg:address":"Flach-Fengler-Str. 62",
    "sg:city":"Wesseling",
    "sg:phone":"+49 2236/45198",
    "sg:postcode":"50389",
    "sg:province":"Nordrhein-Westfalen",
    "wof:name":"Jonen Augenoptik",
    "wof:placetype":"venue"
},
  "geometry": {"coordinates":[6.977918148,50.8223876953],"type":"Point"}
}