{
  "type": "Feature",
  "properties": {
    "iso:country":"DE",
    "sg:address":"Peterstr. 54",
    "sg:city":"Nordenham",
    "sg:phone":"+49 4731/88327",
    "sg:postcode":"26954",
    "sg:province":"Niedersachsen",
    "wof:name":"Werner L\u00fchr",
    "wof:placetype":"venue"
},
  "geometry": {"coordinates":[8.483479,53.481171],"type":"Point"}
}