{
  "type": "Feature",
  "properties": {
    "iso:country":"DE",
    "sg:address":"Schlo\u00dfstr. 22",
    "sg:city":"Me\u00dfkirch",
    "sg:phone":"+49 7575/93135",
    "sg:postcode":"88605",
    "sg:province":"Baden-W\u00fcrttemberg",
    "wof:name":"Sozialstation St. Heimerad",
    "wof:placetype":"venue"
},
  "geometry": {"coordinates":[9.110004,47.993858],"type":"Point"}
}