{
  "type": "Feature",
  "properties": {
    "iso:country":"DE",
    "sg:address":"Krippstr. 21",
    "sg:city":"D\u00fcsseldorf",
    "sg:phone":"+49 211/9216379",
    "sg:postcode":"40229",
    "sg:province":"Nordrhein-Westfalen",
    "wof:name":"Peter Iwantschitsch Rechtsanwalt",
    "wof:placetype":"venue"
},
  "geometry": {"coordinates":[6.8463368416,51.2018127441],"type":"Point"}
}