{
  "type": "Feature",
  "properties": {
    "iso:country":"DE",
    "sg:address":"Kumpstr. 1-2",
    "sg:city":"Altenkirchen",
    "sg:phone":"+49 4926/813017",
    "sg:postcode":"57610",
    "sg:province":"Rheinland-Pfalz",
    "wof:name":"Landmaschinen Str\u00d6der",
    "wof:placetype":"venue"
},
  "geometry": {"coordinates":[7.64175,50.686615],"type":"Point"}
}