{
  "type": "Feature",
  "properties": {
    "iso:country":"DE",
    "sg:address":"Wiesenweg 20",
    "sg:city":"Steinbach-Hallenberg",
    "sg:phone":"+49 36847/48258",
    "sg:postcode":"98587",
    "sg:province":"Th\u00fcringen",
    "wof:name":"Anding Haustechnik Gmbh",
    "wof:placetype":"venue"
},
  "geometry": {"coordinates":[10.5563097,50.6803398132],"type":"Point"}
}