{
  "type": "Feature",
  "properties": {
    "iso:country":"DE",
    "sg:address":"Kronprinzenstrasse 34",
    "sg:city":"Bonn",
    "sg:phone":"+49 228",
    "sg:postcode":"53173",
    "sg:province":"Nordrhein-Westfalen",
    "wof:name":"Alexander Schiele, Systemischer Organisationsberatung",
    "wof:placetype":"venue"
},
  "geometry": {"coordinates":[7.1637067795,50.6882705688],"type":"Point"}
}