{
  "type": "Feature",
  "properties": {
    "iso:country":"DE",
    "sg:address":"Passauer Str. 35",
    "sg:city":"R\u00f6hrnbach",
    "sg:phone":"+49 8582/387",
    "sg:postcode":"94133",
    "sg:province":"Bayern",
    "wof:name":"M. Denk",
    "wof:placetype":"venue"
},
  "geometry": {"coordinates":[13.5233278275,48.7355155945],"type":"Point"}
}