{
  "type": "Feature",
  "properties": {
    "iso:country":"DE",
    "sg:address":"Von-Ketteler-Str. 2",
    "sg:city":"K\u00f6ln",
    "sg:phone":"+49 221/603728",
    "sg:postcode":"51061",
    "sg:province":"Nordrhein-Westfalen",
    "wof:name":"Kath. Pfarramt St. Hedwig",
    "wof:placetype":"venue"
},
  "geometry": {"coordinates":[7.0225992203,50.9835624695],"type":"Point"}
}