{
  "type": "Feature",
  "properties": {
    "iso:country":"DE",
    "sg:city":"Norden",
    "sg:postcode":"26491",
    "sg:province":"Niedersachsen",
    "wof:name":"Bertram & Partner, Ltd.",
    "wof:placetype":"venue"
},
  "geometry": {"coordinates":[7.20248,53.59499],"type":"Point"}
}