{
  "type": "Feature",
  "properties": {
    "iso:country":"DE",
    "sg:address":"Industriestr.",
    "sg:city":"Stuhr",
    "sg:phone":"+49 421/89940",
    "sg:postcode":"28816",
    "sg:province":"Niedersachsen",
    "wof:name":"Burmeister Gmbh & Co.",
    "wof:placetype":"venue"
},
  "geometry": {"coordinates":[8.7528848648,52.9924850464],"type":"Point"}
}