{
  "type": "Feature",
  "properties": {
    "iso:country":"DE",
    "sg:address":"Iblherstr. 19",
    "sg:city":"M\u00fcnchen",
    "sg:postcode":"81739",
    "sg:province":"Bayern",
    "wof:name":"Avo Handelsgesellschaft Mbh",
    "wof:placetype":"venue"
},
  "geometry": {"coordinates":[11.6506214142,48.0944023132],"type":"Point"}
}