{
  "type": "Feature",
  "properties": {
    "iso:country":"DE",
    "sg:address":"Cloppenburger Str. 315",
    "sg:city":"Oldenburg",
    "sg:phone":"+49 441/42192",
    "sg:postcode":"26133",
    "sg:province":"Niedersachsen",
    "wof:name":"E. Didzun",
    "wof:placetype":"venue"
},
  "geometry": {"coordinates":[8.2113809586,53.1124267578],"type":"Point"}
}