{
  "type": "Feature",
  "properties": {
    "iso:country":"DE",
    "sg:address":"Luitpoldstr. 27",
    "sg:city":"Helmbrechts",
    "sg:phone":"+49 9252/990411",
    "sg:postcode":"95233",
    "sg:province":"Bayern",
    "wof:name":"Helmbrechtser Reiseb\u00fcro",
    "wof:placetype":"venue"
},
  "geometry": {"coordinates":[11.7175683975,50.2397575378],"type":"Point"}
}