{
  "type": "Feature",
  "properties": {
    "iso:country":"DE",
    "sg:address":"Talstr. 25",
    "sg:city":"Homburg",
    "sg:postcode":"66424",
    "sg:province":"Saarland",
    "wof:name":"Bayerische Wohnungsgesellschaft F\u00fcr Handel Und Industrie Mbh",
    "wof:placetype":"venue"
},
  "geometry": {"coordinates":[11.57752,48.13641],"type":"Point"}
}