{
  "type": "Feature",
  "properties": {
    "iso:country":"DE",
    "sg:address":"Schafredder 22",
    "sg:city":"Fockbek",
    "sg:phone":"+49 4331/61163",
    "sg:postcode":"24787",
    "sg:province":"Schleswig-Holstein",
    "wof:name":"Kurt M\u00f6ller & Sohn Gmbh",
    "wof:placetype":"venue"
},
  "geometry": {"coordinates":[9.598711,54.307945],"type":"Point"}
}