{
  "type": "Feature",
  "properties": {
    "iso:country":"DE",
    "sg:address":"Gerbergasse 2",
    "sg:city":"Leiwen",
    "sg:phone":"+49 6507/4126",
    "sg:postcode":"54340",
    "sg:province":"Rheinland-Pfalz",
    "wof:name":"Karl-hans Herres",
    "wof:placetype":"venue"
},
  "geometry": {"coordinates":[6.880297184,49.8240013123],"type":"Point"}
}