{
  "type": "Feature",
  "properties": {
    "iso:country":"DE",
    "sg:address":"Postfach 1169",
    "sg:city":"Sulzbach",
    "sg:phone":"+49 7193/5148",
    "sg:postcode":"71555",
    "sg:province":"Hessen",
    "wof:name":"Festhalle Mehrzweckhalle",
    "wof:placetype":"venue"
},
  "geometry": {"coordinates":[9.50495,49.008049],"type":"Point"}
}