{
  "type": "Feature",
  "properties": {
    "iso:country":"DE",
    "sg:address":"Radeberger Str. 36",
    "sg:city":"Gro\u00dfr\u00f6hrsdorf",
    "sg:phone":"+49 35952/33572",
    "sg:postcode":"01900",
    "sg:province":"Sachsen",
    "wof:name":"Karl-heinz Wolf",
    "wof:placetype":"venue"
},
  "geometry": {"coordinates":[14.0122413635,51.1414756775],"type":"Point"}
}