{
  "type": "Feature",
  "properties": {
    "iso:country":"DE",
    "sg:address":"K\u00f6lner Str. 53",
    "sg:city":"Krefeld",
    "sg:phone":"+49 2151/391132",
    "sg:postcode":"47805",
    "sg:province":"Nordrhein-Westfalen",
    "wof:name":"Pizzeria Da Salvatore",
    "wof:placetype":"venue"
},
  "geometry": {"coordinates":[6.5699357986,51.3224754333],"type":"Point"}
}