{
  "type": "Feature",
  "properties": {
    "iso:country":"DE",
    "sg:address":"23966",
    "sg:city":"Wismar",
    "sg:postcode":"23966",
    "sg:province":"Mecklenburg-Vorpommern",
    "wof:name":"Raiffeisenbank Eg Wismar",
    "wof:placetype":"venue"
},
  "geometry": {"coordinates":[11.466146,53.891075],"type":"Point"}
}