{
  "type": "Feature",
  "properties": {
    "iso:country":"DE",
    "sg:address":"Bahnhofstr. 29a",
    "sg:city":"K\u00f6nigslutter",
    "sg:phone":"+49 5353/4015",
    "sg:postcode":"38154",
    "sg:province":"Niedersachsen",
    "wof:name":"Hotel Garni Fieback Inh. Otto Fieback",
    "wof:placetype":"venue"
},
  "geometry": {"coordinates":[10.8155593872,52.2544670105],"type":"Point"}
}