{
  "type": "Feature",
  "properties": {
    "iso:country":"DE",
    "sg:address":"Am Schwarzbach 30",
    "sg:city":"Friedrichroda",
    "sg:phone":"+49 3623/36240",
    "sg:postcode":"99894",
    "sg:province":"Th\u00fcringen",
    "wof:name":"Wohnungsverwaltungs Gmbh",
    "wof:placetype":"venue"
},
  "geometry": {"coordinates":[10.574469,50.86327],"type":"Point"}
}