{
  "type": "Feature",
  "properties": {
    "iso:country":"DE",
    "sg:address":"Pestalozziweg 40",
    "sg:city":"R\u00f6srath",
    "sg:phone":"+49 2205/81649",
    "sg:postcode":"51503",
    "sg:province":"Nordrhein-Westfalen",
    "wof:name":"Axel Degewitz",
    "wof:placetype":"venue"
},
  "geometry": {"coordinates":[7.1613330841,50.8937721252],"type":"Point"}
}