{
  "type": "Feature",
  "properties": {
    "iso:country":"DE",
    "sg:address":"Bernauer Str. 2",
    "sg:city":"Kirchroth",
    "sg:phone":"+49 9428/278",
    "sg:postcode":"94356",
    "sg:province":"Bayern",
    "wof:name":"Franz Scherer",
    "wof:placetype":"venue"
},
  "geometry": {"coordinates":[12.543928,48.95047],"type":"Point"}
}