{
  "type": "Feature",
  "properties": {
    "iso:country":"DE",
    "sg:address":"Gewerbering 28",
    "sg:city":"Kevelaer",
    "sg:phone":"+49 2832/404391",
    "sg:postcode":"47623",
    "sg:province":"Nordrhein-Westfalen",
    "wof:name":"Billard-bistro",
    "wof:placetype":"venue"
},
  "geometry": {"coordinates":[6.2614488602,51.5782814026],"type":"Point"}
}