{
  "type": "Feature",
  "properties": {
    "iso:country":"DE",
    "sg:address":"W\u00f6ssinger Str.62",
    "sg:city":"Walzbachtal",
    "sg:phone":"+49 7203/922106",
    "sg:postcode":"75045",
    "sg:province":"Baden-W\u00fcrttemberg",
    "wof:name":"Fernseh Fischer",
    "wof:placetype":"venue"
},
  "geometry": {"coordinates":[8.609415,49.012238],"type":"Point"}
}