{
  "type": "Feature",
  "properties": {
    "iso:country":"DE",
    "sg:address":"Stettiner Str. 1-9",
    "sg:city":"Gelnhausen",
    "sg:phone":"+49 4960/518210",
    "sg:postcode":"63571",
    "sg:province":"Hessen",
    "wof:name":"Veritas Ag",
    "wof:placetype":"venue"
},
  "geometry": {"coordinates":[9.1806020737,50.1971168518],"type":"Point"}
}