{
  "type": "Feature",
  "properties": {
    "iso:country":"DE",
    "sg:address":"Marktplatz 41",
    "sg:city":"Gunzenhausen",
    "sg:phone":"+49 9831/3068",
    "sg:postcode":"91710",
    "sg:province":"Bayern",
    "wof:name":"Altes Rathaus",
    "wof:placetype":"venue"
},
  "geometry": {"coordinates":[10.7548294067,49.1138725281],"type":"Point"}
}