{
  "type": "Feature",
  "properties": {
    "iso:country":"DE",
    "sg:address":"Langgasse 59",
    "sg:city":"Lorch",
    "sg:phone":"+49 6726/9391",
    "sg:postcode":"65391",
    "sg:province":"Rheinland-Pfalz",
    "wof:name":"Karl Dahlen",
    "wof:placetype":"venue"
},
  "geometry": {"coordinates":[7.804922,50.046089],"type":"Point"}
}