{
  "type": "Feature",
  "properties": {
    "iso:country":"DE",
    "sg:address":"Pyramidenweg 1",
    "sg:city":"Ellerbek",
    "sg:phone":"+49 4101/30210",
    "sg:postcode":"25474",
    "sg:province":"Schleswig-Holstein",
    "wof:name":"Papierverarbeitung Nordia Gmbh & Co. Kg",
    "wof:placetype":"venue"
},
  "geometry": {"coordinates":[9.8869514465,53.6444549561],"type":"Point"}
}