{
  "type": "Feature",
  "properties": {
    "iso:country":"DE",
    "sg:address":"Uhlandstr. 1",
    "sg:city":"Lo\u00dfburg",
    "sg:phone":"+49 7446/1344",
    "sg:postcode":"72290",
    "sg:province":"Baden-W\u00fcrttemberg",
    "wof:name":"Waltraud Armbruster",
    "wof:placetype":"venue"
},
  "geometry": {"coordinates":[8.442429,48.420933],"type":"Point"}
}