{
  "type": "Feature",
  "properties": {
    "iso:country":"DE",
    "sg:address":"Mitschurinstr. 51",
    "sg:city":"Frankfurt",
    "sg:phone":"+49 335/542188",
    "sg:postcode":"15232",
    "sg:province":"Brandenburg",
    "wof:name":"Bau- Und Reparatur Service Gmbh",
    "wof:placetype":"venue"
},
  "geometry": {"coordinates":[14.539972,52.330128],"type":"Point"}
}