{
  "type": "Feature",
  "properties": {
    "iso:country":"DE",
    "sg:address":"Alte Schulstr. 2",
    "sg:city":"Braunschweig",
    "sg:phone":"+49 5309/5148",
    "sg:postcode":"38108",
    "sg:province":"Niedersachsen",
    "wof:name":"U. Saffran-grollmu\u00df",
    "wof:placetype":"venue"
},
  "geometry": {"coordinates":[10.601444,52.300991],"type":"Point"}
}