{
  "type": "Feature",
  "properties": {
    "iso:country":"DE",
    "sg:address":"Korffstr. 41",
    "sg:city":"Frankfurt",
    "sg:phone":"+49 6101/42594",
    "sg:postcode":"60437",
    "sg:province":"Hessen",
    "wof:name":"H. Schmidt",
    "wof:placetype":"venue"
},
  "geometry": {"coordinates":[8.690738678,50.1844291687],"type":"Point"}
}