{
  "type": "Feature",
  "properties": {
    "iso:country":"DE",
    "sg:address":"Margarethenstr.",
    "sg:city":"Moers",
    "sg:phone":"+49 2841/61330",
    "sg:postcode":"47447",
    "sg:province":"Nordrhein-Westfalen",
    "wof:name":"Josef Und Monika Genneper",
    "wof:placetype":"venue"
},
  "geometry": {"coordinates":[6.637816906,51.432182312],"type":"Point"}
}