{
  "type": "Feature",
  "properties": {
    "iso:country":"DE",
    "sg:address":"Neundorfer Str. 18",
    "sg:city":"Plauen",
    "sg:phone":"+49 3741/222415",
    "sg:postcode":"08523",
    "sg:province":"Sachsen",
    "wof:name":"Dietze Und Kollegen Rechtsanw\u00e4lte",
    "wof:placetype":"venue"
},
  "geometry": {"coordinates":[12.1307430267,50.4948921204],"type":"Point"}
}