{
  "type": "Feature",
  "properties": {
    "iso:country":"DE",
    "sg:address":"Fellbacher Str. 4",
    "sg:city":"Remseck",
    "sg:phone":"+49 7146/8200",
    "sg:postcode":"71686",
    "sg:province":"Baden-W\u00fcrttemberg",
    "wof:name":"Heinrich Krieger & S\u00f6hne",
    "wof:placetype":"venue"
},
  "geometry": {"coordinates":[9.2717657089,48.8715667725],"type":"Point"}
}