{
  "type": "Feature",
  "properties": {
    "iso:country":"DE",
    "sg:address":"Blumenstr. 23",
    "sg:city":"M\u00fcnchen",
    "sg:phone":"+49 89/41941677",
    "sg:postcode":"80331",
    "sg:province":"Bayern",
    "wof:name":"T & T Technik Ums Telefon Vertriebs Gmbh",
    "wof:placetype":"venue"
},
  "geometry": {"coordinates":[11.5716552734,48.1321601868],"type":"Point"}
}