{
  "type": "Feature",
  "properties": {
    "iso:country":"DE",
    "sg:address":"Ebersdorfer Str. 79",
    "sg:city":"Neustadt",
    "sg:phone":"+49 9568/87333",
    "sg:postcode":"96465",
    "sg:province":"Bayern",
    "wof:name":"Frank Machold",
    "wof:placetype":"venue"
},
  "geometry": {"coordinates":[11.1110601425,50.3102493286],"type":"Point"}
}