{
  "type": "Feature",
  "properties": {
    "iso:country":"DE",
    "sg:address":"Merodestr. 8",
    "sg:city":"Koblenz",
    "sg:phone":"+49 261/55707",
    "sg:postcode":"56075",
    "sg:province":"Rheinland-Pfalz",
    "wof:name":"G. H. Norgel Steuerberater",
    "wof:placetype":"venue"
},
  "geometry": {"coordinates":[7.5730190277,50.3456916809],"type":"Point"}
}