{
  "type": "Feature",
  "properties": {
    "iso:country":"DE",
    "sg:address":"Georg-Schumann-Str. 56",
    "sg:city":"Leipzig",
    "sg:phone":"+49 341/5905999",
    "sg:postcode":"04155",
    "sg:province":"Sachsen",
    "wof:name":"H. D. Textilpflege Gmbh",
    "wof:placetype":"venue"
},
  "geometry": {"coordinates":[12.3696460724,51.3617591858],"type":"Point"}
}