{
  "type": "Feature",
  "properties": {
    "iso:country":"DE",
    "sg:address":"Von-der-Recke-Str. 14",
    "sg:city":"Gelsenkirchen",
    "sg:phone":"+49 209/145488",
    "sg:postcode":"45879",
    "sg:province":"Nordrhein-Westfalen",
    "wof:name":"Dat Fass",
    "wof:placetype":"venue"
},
  "geometry": {"coordinates":[7.0969171524,51.5076179504],"type":"Point"}
}