{
  "type": "Feature",
  "properties": {
    "iso:country":"DE",
    "sg:address":"Corinthstr. 13",
    "sg:city":"Leipzig",
    "sg:phone":"+49 341/9114571",
    "sg:postcode":"04157",
    "sg:province":"Sachsen",
    "wof:name":"Th\u00fcringer Rostbr\u00e4tl",
    "wof:placetype":"venue"
},
  "geometry": {"coordinates":[12.3709487915,51.3682785034],"type":"Point"}
}