{
  "type": "Feature",
  "properties": {
    "iso:country":"DE",
    "sg:address":"Stephanstr. 3",
    "sg:city":"Westerland",
    "sg:phone":"+49 4651/201430",
    "sg:postcode":"25980",
    "sg:province":"Schleswig-Holstein",
    "wof:name":"Stephansklause",
    "wof:placetype":"venue"
},
  "geometry": {"coordinates":[8.3076200485,54.9077301025],"type":"Point"}
}