{
  "type": "Feature",
  "properties": {
    "iso:country":"DE",
    "sg:address":"Am M\u00fchlgraben 5",
    "sg:city":"Parthenstein",
    "sg:phone":"+49 3437/763244",
    "sg:postcode":"04668",
    "sg:province":"Sachsen",
    "wof:name":"P & B Baustoffhandel Und Transport Gmbh",
    "wof:placetype":"venue"
},
  "geometry": {"coordinates":[12.619485,51.242603],"type":"Point"}
}