{
  "type": "Feature",
  "properties": {
    "iso:country":"DE",
    "sg:address":"Auf dem Schilling 14",
    "sg:city":"Twistetal",
    "sg:phone":"+49 5695/995120",
    "sg:postcode":"34477",
    "sg:province":"Hessen",
    "wof:name":"Dr. G\u00fcnter Leyhe Tierarzt",
    "wof:placetype":"venue"
},
  "geometry": {"coordinates":[8.9702320099,51.3330421448],"type":"Point"}
}