{
  "type": "Feature",
  "properties": {
    "iso:country":"DE",
    "sg:address":"Brandstorstr 9",
    "sg:city":"Essen",
    "sg:phone":"+49 201/494345",
    "sg:postcode":"45239",
    "sg:province":"Nordrhein-Westfalen",
    "wof:name":"Loermann + Schr\u00f6dter Werbeagentur Gmbh",
    "wof:placetype":"venue"
},
  "geometry": {"coordinates":[7.003117,51.386093],"type":"Point"}
}