{
  "type": "Feature",
  "properties": {
    "iso:country":"DE",
    "sg:address":"Kappler Str.",
    "sg:city":"Lenzkirch",
    "sg:phone":"+49 7653/217",
    "sg:postcode":"79853",
    "sg:province":"Baden-W\u00fcrttemberg",
    "wof:name":"Blume",
    "wof:placetype":"venue"
},
  "geometry": {"coordinates":[8.2102403641,47.8674736023],"type":"Point"}
}