{
  "type": "Feature",
  "properties": {
    "iso:country":"DE",
    "sg:address":"Boschertweg 4",
    "sg:city":"A\u00dfling",
    "sg:postcode":"85617",
    "sg:province":"Bayern",
    "wof:name":"Josef Heiss",
    "wof:placetype":"venue"
},
  "geometry": {"coordinates":[12.005668,47.993546],"type":"Point"}
}