{
  "type": "Feature",
  "properties": {
    "iso:country":"DE",
    "sg:address":"Industriestr. 19",
    "sg:city":"Meckesheim",
    "sg:postcode":"74909",
    "sg:province":"Baden-W\u00fcrttemberg",
    "wof:name":"Schmidt-f\u00f6rster Gmbh",
    "wof:placetype":"venue"
},
  "geometry": {"coordinates":[8.8113212585,49.321346283],"type":"Point"}
}