{
  "type": "Feature",
  "properties": {
    "iso:country":"DE",
    "sg:address":"Steinfeldstr. 5",
    "sg:city":"Barleben",
    "sg:phone":"+49 39203/83140",
    "sg:postcode":"39179",
    "sg:province":"Sachsen-Anhalt",
    "wof:name":"Ias Beckel & Werner Gbr",
    "wof:placetype":"venue"
},
  "geometry": {"coordinates":[11.5989093781,52.1964797974],"type":"Point"}
}