{
  "type": "Feature",
  "properties": {
    "iso:country":"DE",
    "sg:address":"Landwehrstr. 1a",
    "sg:city":"Reichshof",
    "sg:phone":"+49 2265/285",
    "sg:postcode":"51580",
    "sg:province":"Nordrhein-Westfalen",
    "wof:name":"Ernst Albrecht",
    "wof:placetype":"venue"
},
  "geometry": {"coordinates":[7.69514,50.989319],"type":"Point"}
}