{
  "type": "Feature",
  "properties": {
    "iso:country":"DE",
    "sg:address":"Gellertstr. 16",
    "sg:city":"K\u00f6ln",
    "sg:phone":"+49 221/9725777",
    "sg:postcode":"50733",
    "sg:province":"Nordrhein-Westfalen",
    "wof:name":"Wiltshire International Gmbh",
    "wof:placetype":"venue"
},
  "geometry": {"coordinates":[6.9572138786,50.9627990723],"type":"Point"}
}