{
  "type": "Feature",
  "properties": {
    "iso:country":"DE",
    "sg:address":"Markt 18",
    "sg:city":"Rehna",
    "sg:phone":"+49 38872/53442",
    "sg:postcode":"19217",
    "sg:province":"Mecklenburg-Vorpommern",
    "wof:name":"E. Bohmann",
    "wof:placetype":"venue"
},
  "geometry": {"coordinates":[11.048754,53.780865],"type":"Point"}
}