{
  "type": "Feature",
  "properties": {
    "iso:country":"DE",
    "sg:address":"Goethering 66",
    "sg:city":"Offenbach",
    "sg:phone":"+49 69/8007740",
    "sg:postcode":"63067",
    "sg:province":"Hessen",
    "wof:name":"Albatros Air Courier Gmbh",
    "wof:placetype":"venue"
},
  "geometry": {"coordinates":[8.7411394119,50.111530304],"type":"Point"}
}