{
  "type": "Feature",
  "properties": {
    "iso:country":"DE",
    "sg:address":"Ferdinand-Porsche-Str 8",
    "sg:city":"Heinsberg",
    "sg:phone":"+49 2452/91040",
    "sg:postcode":"52525",
    "sg:province":"Nordrhein-Westfalen",
    "wof:name":"Sbh Tiefbautechnik Gmbh",
    "wof:placetype":"venue"
},
  "geometry": {"coordinates":[6.1212477684,51.0620803833],"type":"Point"}
}