{
  "type": "Feature",
  "properties": {
    "iso:country":"DE",
    "sg:address":"Parkstr. 55",
    "sg:city":"L\u00fcdenscheid",
    "sg:phone":"+49 2351/381108",
    "sg:postcode":"58509",
    "sg:province":"Nordrhein-Westfalen",
    "wof:name":"F. H\u00fcttebr\u00e4uker",
    "wof:placetype":"venue"
},
  "geometry": {"coordinates":[7.6148819923,51.2191429138],"type":"Point"}
}