{
  "type": "Feature",
  "properties": {
    "iso:country":"DE",
    "sg:address":"Pr\u00fcner Gang 16-20",
    "sg:city":"Kiel",
    "sg:postcode":"24103",
    "sg:province":"Schleswig-Holstein",
    "wof:name":"Ambulante Schnittbild- Diagnostik Schleswig-holstein",
    "wof:placetype":"venue"
},
  "geometry": {"coordinates":[10.12634,54.320335],"type":"Point"}
}