{
  "type": "Feature",
  "properties": {
    "iso:country":"DE",
    "sg:address":"Ellwanger Str. 42",
    "sg:city":"Crailsheim",
    "sg:phone":"+49 7951/8366",
    "sg:postcode":"74564",
    "sg:province":"Baden-W\u00fcrttemberg",
    "wof:name":"Jet Tankstelle",
    "wof:placetype":"venue"
},
  "geometry": {"coordinates":[10.0773448944,49.1307182312],"type":"Point"}
}