{
  "type": "Feature",
  "properties": {
    "iso:country":"DE",
    "sg:address":"Kornkamp 44",
    "sg:city":"Ahrensburg",
    "sg:phone":"+49 4941/0242536",
    "sg:postcode":"22926",
    "sg:province":"Schleswig-Holstein",
    "wof:name":"Eigbrecht Gmbh",
    "wof:placetype":"venue"
},
  "geometry": {"coordinates":[10.2560148239,53.6891822815],"type":"Point"}
}