{
  "type": "Feature",
  "properties": {
    "iso:country":"DE",
    "sg:address":"Rehenwiesen 7a",
    "sg:city":"Seevetal",
    "sg:phone":"+49 40/7684368",
    "sg:postcode":"21217",
    "sg:province":"Niedersachsen",
    "wof:name":"Karl-heinz Post",
    "wof:placetype":"venue"
},
  "geometry": {"coordinates":[10.032399,53.419567],"type":"Point"}
}