{
  "type": "Feature",
  "properties": {
    "iso:country":"DE",
    "sg:address":"Stettiner Str. 6",
    "sg:city":"Wadersloh",
    "sg:phone":"+49 2523/6218",
    "sg:postcode":"59329",
    "sg:province":"Nordrhein-Westfalen",
    "wof:name":"Marie-luise Goldau Heilpraktikerin",
    "wof:placetype":"venue"
},
  "geometry": {"coordinates":[8.2504720688,51.705783844],"type":"Point"}
}