{
  "type": "Feature",
  "properties": {
    "iso:country":"DE",
    "sg:address":"S\u00fcdfeldstr. 5",
    "sg:city":"Hannover",
    "sg:phone":"+49 4951/1921760",
    "sg:postcode":"30453",
    "sg:province":"Niedersachsen",
    "wof:name":"Hollmann Gmbh, Otto",
    "wof:placetype":"venue"
},
  "geometry": {"coordinates":[9.683432579,52.3674201965],"type":"Point"}
}