{
  "type": "Feature",
  "properties": {
    "iso:country":"DE",
    "sg:address":"Industriegebiet Hirschau",
    "sg:city":"T\u00fcbingen",
    "sg:phone":"+49 4970/7175080",
    "sg:postcode":"72070",
    "sg:province":"Baden-W\u00fcrttemberg",
    "wof:name":"T\u00dcbinger Stahlfeinguss Franz Stadtler Gmbh",
    "wof:placetype":"venue"
},
  "geometry": {"coordinates":[9.04911,48.52037],"type":"Point"}
}