{
  "type": "Feature",
  "properties": {
    "iso:country":"DE",
    "sg:address":"Butzenwinkelstr. 3",
    "sg:city":"Tettnang",
    "sg:phone":"+49 7543/8630",
    "sg:postcode":"88069",
    "sg:province":"Baden-W\u00fcrttemberg",
    "wof:name":"Holzbau Dingler Gmbh",
    "wof:placetype":"venue"
},
  "geometry": {"coordinates":[9.625152,47.635082],"type":"Point"}
}