{
  "type": "Feature",
  "properties": {
    "iso:country":"DE",
    "sg:address":"Westwall 10",
    "sg:city":"Menden",
    "sg:phone":"+49 2373/4970",
    "sg:postcode":"58706",
    "sg:province":"Nordrhein-Westfalen",
    "wof:name":"Gabriele Asch",
    "wof:placetype":"venue"
},
  "geometry": {"coordinates":[7.7931141853,51.4383392334],"type":"Point"}
}