{
  "type": "Feature",
  "properties": {
    "iso:country":"DE",
    "sg:address":"Steinburgsgang 7",
    "sg:city":"Leer",
    "sg:phone":"+49 491/4291",
    "sg:postcode":"26789",
    "sg:province":"Niedersachsen",
    "wof:name":"Dr. Med. Heidrun Hapig-heer",
    "wof:placetype":"venue"
},
  "geometry": {"coordinates":[7.4442639351,53.2274475098],"type":"Point"}
}