{
  "type": "Feature",
  "properties": {
    "iso:country":"DE",
    "sg:address":"Zschierener Str. 5",
    "sg:city":"Heidenau",
    "sg:phone":"+49 3529/513890",
    "sg:postcode":"01809",
    "sg:province":"Sachsen",
    "wof:name":"Imhof Baumaschinen Gmbh & Co. Kg",
    "wof:placetype":"venue"
},
  "geometry": {"coordinates":[13.861324,50.989014],"type":"Point"}
}