{
  "type": "Feature",
  "properties": {
    "iso:country":"DE",
    "sg:address":"Georgstr. 26",
    "sg:city":"Friedberg",
    "sg:phone":"+49 8208/447",
    "sg:postcode":"86316",
    "sg:province":"Bayern",
    "wof:name":"Anton Altmann",
    "wof:placetype":"venue"
},
  "geometry": {"coordinates":[11.0450181961,48.3081665039],"type":"Point"}
}