{
  "type": "Feature",
  "properties": {
    "iso:country":"DE",
    "sg:address":"Nestelreuther Weg 3",
    "sg:city":"Naila",
    "sg:postcode":"95119",
    "sg:province":"Bayern",
    "wof:name":"Suchmaschienen Anmelden Und Eintragen - Ihr Suchma",
    "wof:placetype":"venue"
},
  "geometry": {"coordinates":[11.691921,50.307243],"type":"Point"}
}