{
  "type": "Feature",
  "properties": {
    "iso:country":"DE",
    "sg:address":"Hauptstr. 49",
    "sg:city":"Elze",
    "sg:phone":"+49 5068/3222",
    "sg:postcode":"31008",
    "sg:province":"Niedersachsen",
    "wof:name":"Erich Kratzsch",
    "wof:placetype":"venue"
},
  "geometry": {"coordinates":[9.7375793457,52.1170806885],"type":"Point"}
}