{
  "type": "Feature",
  "properties": {
    "iso:country":"DE",
    "sg:address":"D\u00fcrener Str. 18",
    "sg:city":"Euskirchen",
    "sg:phone":"+49 2251/2100",
    "sg:postcode":"53879",
    "sg:province":"Nordrhein-Westfalen",
    "wof:name":"E. Seifert",
    "wof:placetype":"venue"
},
  "geometry": {"coordinates":[6.7770428658,50.6619186401],"type":"Point"}
}