{
  "type": "Feature",
  "properties": {
    "iso:country":"DE",
    "sg:address":"L\u00fctzowufer 26",
    "sg:city":"Berlin",
    "sg:postcode":"10787",
    "sg:province":"Berlin",
    "wof:name":"Bbah-berlin-branden- Burgische Automobil",
    "wof:placetype":"venue"
},
  "geometry": {"coordinates":[13.349497,52.506245],"type":"Point"}
}