{
  "type": "Feature",
  "properties": {
    "iso:country":"DE",
    "sg:address":"W\u00f6hrder Hauptstr. 21",
    "sg:city":"N\u00fcrnberg",
    "sg:phone":"+49 911/552255",
    "sg:postcode":"90489",
    "sg:province":"Bayern",
    "wof:name":"Schweizerische Lebensver- Sicherungs- Und Rentenanstalt",
    "wof:placetype":"venue"
},
  "geometry": {"coordinates":[11.095413208,49.4541740417],"type":"Point"}
}