{
  "type": "Feature",
  "properties": {
    "iso:country":"DE",
    "sg:address":"Landwehrstr. 26",
    "sg:city":"Speyer",
    "sg:phone":"+49 6232/43320",
    "sg:postcode":"67346",
    "sg:province":"Rheinland-Pfalz",
    "wof:name":"Reinhard Burkard",
    "wof:placetype":"venue"
},
  "geometry": {"coordinates":[8.426128,49.338329],"type":"Point"}
}