{
  "type": "Feature",
  "properties": {
    "iso:country":"DE",
    "sg:address":"Schulstr. 22",
    "sg:city":"Rottendorf",
    "sg:phone":"+49 9302/1207",
    "sg:postcode":"97228",
    "sg:province":"Bayern",
    "wof:name":"Theodor Heu\u00dfner",
    "wof:placetype":"venue"
},
  "geometry": {"coordinates":[10.024407,49.793171],"type":"Point"}
}