{
  "type": "Feature",
  "properties": {
    "iso:country":"DE",
    "sg:address":"H\u00f6rster Str. 7",
    "sg:city":"Halle",
    "sg:phone":"+49 5201/81280",
    "sg:postcode":"33790",
    "sg:province":"Nordrhein-Westfalen",
    "wof:name":"Eugen Theis Gmbh",
    "wof:placetype":"venue"
},
  "geometry": {"coordinates":[8.304889679,52.0464286804],"type":"Point"}
}