{
  "type": "Feature",
  "properties": {
    "iso:country":"DE",
    "sg:address":"Dammallee 23",
    "sg:city":"Bayreuth",
    "sg:phone":"+49 921/68858",
    "sg:postcode":"95444",
    "sg:province":"Bayern",
    "wof:name":"Harald Paul",
    "wof:placetype":"venue"
},
  "geometry": {"coordinates":[11.571554,49.943729],"type":"Point"}
}