{
  "type": "Feature",
  "properties": {
    "iso:country":"DE",
    "sg:address":"Lindenweg 3",
    "sg:city":"Schnaittach",
    "sg:phone":"+49 9153/8404",
    "sg:postcode":"91220",
    "sg:province":"Bayern",
    "wof:name":"Hans Holfelder",
    "wof:placetype":"venue"
},
  "geometry": {"coordinates":[11.3120012283,49.5690956116],"type":"Point"}
}