{
  "type": "Feature",
  "properties": {
    "iso:country":"DE",
    "sg:address":"Karither Str. 2",
    "sg:city":"Gommern",
    "sg:phone":"+49 39200/51727",
    "sg:postcode":"39245",
    "sg:province":"Sachsen-Anhalt",
    "wof:name":"Arno Ruthe",
    "wof:placetype":"venue"
},
  "geometry": {"coordinates":[11.8296642303,52.0739746094],"type":"Point"}
}