{
  "type": "Feature",
  "properties": {
    "iso:country":"DE",
    "sg:address":"Am Fohlenhof 13",
    "sg:city":"F\u00fcrstenfeldbruck",
    "sg:postcode":"82256",
    "sg:province":"Bayern",
    "wof:name":"Amper Hausanschlu\u00df Gmbh",
    "wof:placetype":"venue"
},
  "geometry": {"coordinates":[11.2481765747,48.1961212158],"type":"Point"}
}