{
  "type": "Feature",
  "properties": {
    "iso:country":"DE",
    "sg:address":"Pfirnleite 9",
    "sg:city":"Bad Wiessee",
    "sg:phone":"+49 8022/81688",
    "sg:postcode":"83707",
    "sg:province":"Bayern",
    "wof:name":"Damenoberbekleidung Kurt Sommer",
    "wof:placetype":"venue"
},
  "geometry": {"coordinates":[11.7173652649,47.7112312317],"type":"Point"}
}