{
  "type": "Feature",
  "properties": {
    "iso:country":"DE",
    "sg:address":"Martin-Luther-Str. 5",
    "sg:city":"Rheinfelden",
    "sg:phone":"+49 7623/50367",
    "sg:postcode":"79618",
    "sg:province":"Baden-W\u00fcrttemberg",
    "wof:name":"K. Und D. Biermann",
    "wof:placetype":"venue"
},
  "geometry": {"coordinates":[7.789755,47.59893],"type":"Point"}
}