{
  "type": "Feature",
  "properties": {
    "iso:country":"DE",
    "sg:address":"Obentrautstr. 16-18",
    "sg:city":"Berlin",
    "sg:phone":"+49 30/25905154",
    "sg:postcode":"10963",
    "sg:province":"Berlin",
    "wof:name":"F\u00f6rderung Des Kraftfahrzeug- Gewerbes Berlin Gmbh",
    "wof:placetype":"venue"
},
  "geometry": {"coordinates":[13.387485,52.49649],"type":"Point"}
}