{
  "type": "Feature",
  "properties": {
    "iso:country":"DE",
    "sg:address":"Lindenstr. 29",
    "sg:city":"L\u00fcneburg",
    "sg:phone":"+49 4131/41920",
    "sg:postcode":"21335",
    "sg:province":"Niedersachsen",
    "wof:name":"Dr. Heinz Brockm\u00f6ller Rechtsanwalt",
    "wof:placetype":"venue"
},
  "geometry": {"coordinates":[10.4091463089,53.2443237305],"type":"Point"}
}