{
  "type": "Feature",
  "properties": {
    "iso:country":"DE",
    "sg:address":"L\u00fctgendortmunder Hellweg 242",
    "sg:city":"Dortmund",
    "sg:phone":"+49 231/61830",
    "sg:postcode":"44388",
    "sg:province":"Nordrhein-Westfalen",
    "wof:name":"H. L. Br\u00fcgmann Und Geheimr. Dr. C. Br\u00fcgmann-",
    "wof:placetype":"venue"
},
  "geometry": {"coordinates":[7.3596601486,51.4978103638],"type":"Point"}
}