{
  "type": "Feature",
  "properties": {
    "iso:country":"DE",
    "sg:address":"Zur Sch\u00f6n 11",
    "sg:city":"Pottenstein",
    "sg:postcode":"91278",
    "sg:province":"Bayern",
    "wof:name":"Wieg\u00e4rtner Bau Gmbh",
    "wof:placetype":"venue"
},
  "geometry": {"coordinates":[11.417969,49.728054],"type":"Point"}
}