{
  "type": "Feature",
  "properties": {
    "iso:country":"DE",
    "sg:address":"Heydbrekenstr. 2",
    "sg:city":"Dortmund",
    "sg:phone":"+49 231/279487",
    "sg:postcode":"44319",
    "sg:province":"Nordrhein-Westfalen",
    "wof:name":"Bernd B\u00f6ker Rechtsanwalt",
    "wof:placetype":"venue"
},
  "geometry": {"coordinates":[7.5846190453,51.5281829834],"type":"Point"}
}