{
  "type": "Feature",
  "properties": {
    "iso:country":"DE",
    "sg:address":"Glauburgstr. 36",
    "sg:city":"Frankfurt",
    "sg:phone":"+49 69/552063",
    "sg:postcode":"60318",
    "sg:province":"Hessen",
    "wof:name":"Oskar Und H. Habersack",
    "wof:placetype":"venue"
},
  "geometry": {"coordinates":[8.6873693466,50.1269264221],"type":"Point"}
}