{
  "type": "Feature",
  "properties": {
    "iso:country":"DE",
    "sg:address":"Belziger Str. 34",
    "sg:city":"Berlin",
    "sg:phone":"+49 30/7845485",
    "sg:postcode":"10823",
    "sg:province":"Berlin",
    "wof:name":"Taverna Kreta",
    "wof:placetype":"venue"
},
  "geometry": {"coordinates":[13.3519830704,52.4866943359],"type":"Point"}
}