{
  "type": "Feature",
  "properties": {
    "iso:country":"DE",
    "sg:address":"Georg-Schulhoff-Platz 1",
    "sg:city":"D\u00fcsseldorf",
    "sg:phone":"+49 211/8795352",
    "sg:postcode":"40221",
    "sg:province":"Nordrhein-Westfalen",
    "wof:name":"Hwk-d\u00fcsseldorf",
    "wof:placetype":"venue"
},
  "geometry": {"coordinates":[6.7602,51.206642],"type":"Point"}
}