{
  "type": "Feature",
  "properties": {
    "iso:country":"DE",
    "sg:address":"Kahlstr. 50",
    "sg:city":"Kleinkahl",
    "sg:phone":"+49 6024/9282",
    "sg:postcode":"63828",
    "sg:province":"Bayern",
    "wof:name":"Herbert B\u00fcttner",
    "wof:placetype":"venue"
},
  "geometry": {"coordinates":[9.280154,50.1077],"type":"Point"}
}