{
  "type": "Feature",
  "properties": {
    "iso:country":"DE",
    "sg:address":"Marbacher Weg 5",
    "sg:city":"Stuhr",
    "sg:phone":"+49 421/511351",
    "sg:postcode":"28816",
    "sg:province":"Niedersachsen",
    "wof:name":"Christa Ricklefs Heilpraktikerin",
    "wof:placetype":"venue"
},
  "geometry": {"coordinates":[8.7662239075,53.0495948792],"type":"Point"}
}