{
  "type": "Feature",
  "properties": {
    "iso:country":"DE",
    "sg:address":"Bodenseestr. 154",
    "sg:city":"Sigmarszell",
    "sg:phone":"+49 8382/79111",
    "sg:postcode":"88138",
    "sg:province":"Bayern",
    "wof:name":"Gerhard Brutscher",
    "wof:placetype":"venue"
},
  "geometry": {"coordinates":[9.738179,47.568649],"type":"Point"}
}