{
  "type": "Feature",
  "properties": {
    "iso:country":"DE",
    "sg:address":"Wittener Str. 164",
    "sg:city":"Witten",
    "sg:phone":"+49 4923/2493470",
    "sg:postcode":"58456",
    "sg:province":"Nordrhein-Westfalen",
    "wof:name":"Wengeler & Kalthoff Hammerwerke Gmbh & Co. Kg",
    "wof:placetype":"venue"
},
  "geometry": {"coordinates":[7.259017,51.409321],"type":"Point"}
}