{
  "type": "Feature",
  "properties": {
    "iso:country":"DE",
    "sg:address":"Gl\u00fccksburger Str. 55",
    "sg:city":"Flensburg",
    "sg:phone":"+49 461/17878",
    "sg:postcode":"24943",
    "sg:province":"Schleswig-Holstein",
    "wof:name":"H. G. Hansen Beteiligungs Gmbh",
    "wof:placetype":"venue"
},
  "geometry": {"coordinates":[9.448957,54.785927],"type":"Point"}
}