{
  "type": "Feature",
  "properties": {
    "iso:country":"DE",
    "sg:address":"Sch\u00fctzenstr. 4 a",
    "sg:city":"L\u00fcdenscheid",
    "sg:phone":"+49 2351/980016",
    "sg:postcode":"58511",
    "sg:province":"Nordrhein-Westfalen",
    "wof:name":"Kaufpark",
    "wof:placetype":"venue"
},
  "geometry": {"coordinates":[7.6437849998,51.2122955322],"type":"Point"}
}