{
  "type": "Feature",
  "properties": {
    "iso:country":"DE",
    "sg:address":"Heimbacher Gasse 12",
    "sg:city":"Schw\u00e4bisch Hall",
    "sg:phone":"+49 791/71848",
    "sg:postcode":"74523",
    "sg:province":"Baden-W\u00fcrttemberg",
    "wof:name":"Sabine Bertsch",
    "wof:placetype":"venue"
},
  "geometry": {"coordinates":[9.731535,49.112667],"type":"Point"}
}