{
  "type": "Feature",
  "properties": {
    "iso:country":"DE",
    "sg:address":"Ernst-Th\u00e4lmann-Str. 22",
    "sg:city":"Klostermansfeld",
    "sg:phone":"+49 34772/25516",
    "sg:postcode":"06308",
    "sg:province":"Sachsen-Anhalt",
    "wof:name":"Hartmut Ignaszewski",
    "wof:placetype":"venue"
},
  "geometry": {"coordinates":[11.4902734756,51.5785102844],"type":"Point"}
}