{
  "type": "Feature",
  "properties": {
    "iso:country":"DE",
    "sg:address":"Unter der Pfordt 35",
    "sg:city":"Sch\u00f6necken",
    "sg:phone":"+49 6553/2806",
    "sg:postcode":"54614",
    "sg:province":"Rheinland-Pfalz",
    "wof:name":"Rolladen-graff E. K. Inh. J\u00fcrgen Schleider",
    "wof:placetype":"venue"
},
  "geometry": {"coordinates":[6.46232,50.158646],"type":"Point"}
}