{
  "type": "Feature",
  "properties": {
    "iso:country":"DE",
    "sg:address":"Schuhstr. 37",
    "sg:city":"Uelzen",
    "sg:phone":"+49 581/5051",
    "sg:postcode":"29525",
    "sg:province":"Niedersachsen",
    "wof:name":"J. K\u00f6berich",
    "wof:placetype":"venue"
},
  "geometry": {"coordinates":[10.560826,52.963577],"type":"Point"}
}