{
  "type": "Feature",
  "properties": {
    "iso:country":"DE",
    "sg:address":"Hauptstr. 34",
    "sg:city":"Taben-Rodt",
    "sg:phone":"+49 6582/99020",
    "sg:postcode":"54441",
    "sg:province":"Rheinland-Pfalz",
    "wof:name":"Kd-service",
    "wof:placetype":"venue"
},
  "geometry": {"coordinates":[6.5897622108,49.5474700928],"type":"Point"}
}