{
  "type": "Feature",
  "properties": {
    "iso:country":"DE",
    "sg:address":"Falkenstr. 6",
    "sg:city":"Ostfildern",
    "sg:phone":"+49 7158/3439",
    "sg:postcode":"73760",
    "sg:province":"Baden-W\u00fcrttemberg",
    "wof:name":"Rudolf Jehle Annahmestelle",
    "wof:placetype":"venue"
},
  "geometry": {"coordinates":[9.256141,48.705917],"type":"Point"}
}