{
  "type": "Feature",
  "properties": {
    "iso:country":"DE",
    "sg:address":"Hugo-Wolf-Weg 13",
    "sg:city":"Dorsten",
    "sg:postcode":"46282",
    "sg:province":"Nordrhein-Westfalen",
    "wof:name":"Vvw Gepe Gmbh",
    "wof:placetype":"venue"
},
  "geometry": {"coordinates":[6.9876060486,51.6544151306],"type":"Point"}
}