{
  "type": "Feature",
  "properties": {
    "iso:country":"DE",
    "sg:address":"Zwickauer Str. 2",
    "sg:city":"Wolfsburg",
    "sg:postcode":"38444",
    "sg:province":"Niedersachsen",
    "wof:name":"Sina",
    "wof:placetype":"venue"
},
  "geometry": {"coordinates":[10.736594,52.407303],"type":"Point"}
}