{
  "type": "Feature",
  "properties": {
    "iso:country":"DE",
    "sg:address":"Eschweilerstr. 12",
    "sg:city":"Stolberg",
    "sg:phone":"+49 2402/12000",
    "sg:postcode":"52222",
    "sg:province":"Nordrhein-Westfalen",
    "wof:name":"Redaktion Eilendorf Ac-s\u00fcd- Ost",
    "wof:placetype":"venue"
},
  "geometry": {"coordinates":[6.2233638763,50.7790336609],"type":"Point"}
}