{
  "type": "Feature",
  "properties": {
    "iso:country":"DE",
    "sg:address":"Veit-Sto\u00df-Str. 14",
    "sg:city":"M\u00fcnnerstadt",
    "sg:phone":"+49 9733/9606",
    "sg:postcode":"97702",
    "sg:province":"Bayern",
    "wof:name":"Norbert Reiter Rechtsanwalt",
    "wof:placetype":"venue"
},
  "geometry": {"coordinates":[10.1939439774,50.2477684021],"type":"Point"}
}