{
  "type": "Feature",
  "properties": {
    "iso:country":"DE",
    "sg:address":"Waldprechtsstr. 44",
    "sg:city":"Malsch",
    "sg:phone":"+49 7246/6541",
    "sg:postcode":"76316",
    "sg:province":"Baden-W\u00fcrttemberg",
    "wof:name":"J. Kara",
    "wof:placetype":"venue"
},
  "geometry": {"coordinates":[8.3349790573,48.8786964417],"type":"Point"}
}