{
  "type": "Feature",
  "properties": {
    "iso:country":"DE",
    "sg:address":"Albanastr. 6",
    "sg:city":"Trier",
    "sg:phone":"+49 651/300740",
    "sg:postcode":"54290",
    "sg:province":"Rheinland-Pfalz",
    "wof:name":"Reinhard M\u00fcller Heilpraktiker",
    "wof:placetype":"venue"
},
  "geometry": {"coordinates":[6.6332421303,49.7395362854],"type":"Point"}
}