{
  "type": "Feature",
  "properties": {
    "iso:country":"DE",
    "sg:address":"Siegenburger Str. 28",
    "sg:city":"Neustadt",
    "sg:phone":"+49 9444/575",
    "sg:postcode":"93333",
    "sg:province":"Bayern",
    "wof:name":"Alfons Bauer",
    "wof:placetype":"venue"
},
  "geometry": {"coordinates":[11.797052,48.774387],"type":"Point"}
}