{
  "type": "Feature",
  "properties": {
    "iso:country":"DE",
    "sg:address":"Vredener Str. 23",
    "sg:city":"Stadtlohn",
    "sg:postcode":"48703",
    "sg:province":"Nordrhein-Westfalen",
    "wof:name":"Willi Kenkel Fleischservice Gmbh",
    "wof:placetype":"venue"
},
  "geometry": {"coordinates":[6.9136838913,51.9909553528],"type":"Point"}
}