{
  "type": "Feature",
  "properties": {
    "iso:country":"DE",
    "sg:address":"Am Kanal 134",
    "sg:city":"Apen",
    "sg:phone":"+49 4489/710",
    "sg:postcode":"26689",
    "sg:province":"Niedersachsen",
    "wof:name":"Stahlwerk Augustfehen Gmbh",
    "wof:placetype":"venue"
},
  "geometry": {"coordinates":[7.7727570534,53.2403450012],"type":"Point"}
}