{
  "type": "Feature",
  "properties": {
    "iso:country":"DE",
    "sg:address":"Im Niedernbrock 46",
    "sg:city":"L\u00f6hne",
    "sg:postcode":"32584",
    "sg:province":"Nordrhein-Westfalen",
    "wof:name":"L\u00f6ny Verm\u00f6gensverwaltungs Und Beteiligungs Gmbh",
    "wof:placetype":"venue"
},
  "geometry": {"coordinates":[8.7109098434,52.206451416],"type":"Point"}
}