{
  "type": "Feature",
  "properties": {
    "iso:country":"DE",
    "sg:address":"Theodor-Storm-Str. 30",
    "sg:city":"Leck",
    "sg:phone":"+49 4662/3507",
    "sg:postcode":"25917",
    "sg:province":"Schleswig-Holstein",
    "wof:name":"Kurt Petersen",
    "wof:placetype":"venue"
},
  "geometry": {"coordinates":[8.98276,54.774357],"type":"Point"}
}