{
  "type": "Feature",
  "properties": {
    "iso:country":"DE",
    "sg:address":"Engelhardstr. 29",
    "sg:city":"M\u00fcnchen",
    "sg:phone":"+49 89/7252732",
    "sg:postcode":"81369",
    "sg:province":"Bayern",
    "wof:name":"Bernhard Nierlein Elektromeister",
    "wof:placetype":"venue"
},
  "geometry": {"coordinates":[11.53859,48.111607],"type":"Point"}
}