{
  "type": "Feature",
  "properties": {
    "iso:country":"DE",
    "sg:address":"Friedrich-Ebert-Str. 92",
    "sg:city":"Donaueschingen",
    "sg:postcode":"78166",
    "sg:province":"Baden-W\u00fcrttemberg",
    "wof:name":"Gisela Bitschnau Gmbh",
    "wof:placetype":"venue"
},
  "geometry": {"coordinates":[8.496653,47.936623],"type":"Point"}
}