{
  "type": "Feature",
  "properties": {
    "iso:country":"DE",
    "sg:address":"Freiburger Str. 3",
    "sg:city":"Weinheim",
    "sg:postcode":"69469",
    "sg:province":"Baden-W\u00fcrttemberg",
    "wof:name":"Datagrav Gmbh Kunststoff- Und",
    "wof:placetype":"venue"
},
  "geometry": {"coordinates":[8.6295013428,49.5460128784],"type":"Point"}
}