{
  "type": "Feature",
  "properties": {
    "iso:country":"DE",
    "sg:address":"Lilienthalstr 17",
    "sg:city":"Hannover",
    "sg:phone":"+49 511/4383370",
    "sg:postcode":"30179",
    "sg:province":"Niedersachsen",
    "wof:name":"Tawi Gmbh",
    "wof:placetype":"venue"
},
  "geometry": {"coordinates":[9.7382745743,52.4196395874],"type":"Point"}
}