{
  "type": "Feature",
  "properties": {
    "iso:country":"DE",
    "sg:address":"Achter de Weiden 10",
    "sg:city":"Schenefeld",
    "sg:phone":"+49 40/8406462",
    "sg:postcode":"22869",
    "sg:province":"Schleswig-Holstein",
    "wof:name":"Nordpr\u00e4zision Werkzeugfabrik Gmbh",
    "wof:placetype":"venue"
},
  "geometry": {"coordinates":[9.8271684647,53.6061477661],"type":"Point"}
}