{
  "type": "Feature",
  "properties": {
    "iso:country":"DE",
    "sg:address":"Stahler Ufer 5",
    "sg:city":"H\u00f6xter",
    "sg:phone":"+49 5531/12900",
    "sg:postcode":"37671",
    "sg:province":"Nordrhein-Westfalen",
    "wof:name":"Steiskal Auto-leasing Gmbh",
    "wof:placetype":"venue"
},
  "geometry": {"coordinates":[9.437323,51.829971],"type":"Point"}
}