{
  "type": "Feature",
  "properties": {
    "iso:country":"DE",
    "sg:address":"Rathausplatz 10",
    "sg:city":"Gardelegen",
    "sg:phone":"+49 3907/6519",
    "sg:postcode":"39638",
    "sg:province":"Sachsen-Anhalt",
    "wof:name":"Stadtmuseum",
    "wof:placetype":"venue"
},
  "geometry": {"coordinates":[11.392404,52.526775],"type":"Point"}
}