{
  "type": "Feature",
  "properties": {
    "iso:country":"DE",
    "sg:address":"Keilswingert 12",
    "sg:city":"Weilburg",
    "sg:phone":"+49 6471/922430",
    "sg:postcode":"35781",
    "sg:province":"Hessen",
    "wof:name":"Sport-profimarkt Gmbh",
    "wof:placetype":"venue"
},
  "geometry": {"coordinates":[8.28713,50.48225],"type":"Point"}
}