{
  "type": "Feature",
  "properties": {
    "iso:country":"DE",
    "sg:address":"Zum Hochgericht 9",
    "sg:city":"Munderkingen",
    "sg:phone":"+49 7393/2193",
    "sg:postcode":"89597",
    "sg:province":"Baden-W\u00fcrttemberg",
    "wof:name":"Schotterwerk Kirchen",
    "wof:placetype":"venue"
},
  "geometry": {"coordinates":[9.6560201645,48.2431411743],"type":"Point"}
}