{
  "type": "Feature",
  "properties": {
    "iso:country":"DE",
    "sg:address":"Beendorfer Str. 93",
    "sg:city":"Morsleben",
    "sg:phone":"+49 39050/2780",
    "sg:postcode":"39343",
    "sg:province":"Sachsen-Anhalt",
    "wof:name":"Am Schlo\u00dfpark Inh. Inge L\u00fcdtke",
    "wof:placetype":"venue"
},
  "geometry": {"coordinates":[11.10887146,52.220035553],"type":"Point"}
}