{
  "type": "Feature",
  "properties": {
    "iso:country":"DE",
    "sg:address":"Feldherrnweg 11",
    "sg:city":"Ostrach",
    "sg:phone":"+49 7585/91749",
    "sg:postcode":"88356",
    "sg:province":"Baden-W\u00fcrttemberg",
    "wof:name":"Johanna Renz",
    "wof:placetype":"venue"
},
  "geometry": {"coordinates":[9.3862924576,47.9554023743],"type":"Point"}
}