{
  "type": "Feature",
  "properties": {
    "iso:country":"DE",
    "sg:address":"Berckhusenstr. 83",
    "sg:city":"Hannover",
    "sg:phone":"+49 511/555543",
    "sg:postcode":"30625",
    "sg:province":"Niedersachsen",
    "wof:name":"Piepers Backparadies",
    "wof:placetype":"venue"
},
  "geometry": {"coordinates":[9.797961,52.376274],"type":"Point"}
}