{
  "type": "Feature",
  "properties": {
    "iso:country":"DE",
    "sg:address":"Bohlendamm 4",
    "sg:city":"Hannover",
    "sg:phone":"+49 511/364530",
    "sg:postcode":"30159",
    "sg:province":"Niedersachsen",
    "wof:name":"Ralf Voigt Steuerbevollm\u00e4chtigter",
    "wof:placetype":"venue"
},
  "geometry": {"coordinates":[9.7349767685,52.3708000183],"type":"Point"}
}