{
  "type": "Feature",
  "properties": {
    "iso:country":"DE",
    "sg:address":"Adelburgweg 1",
    "sg:city":"Seubersdorf",
    "sg:phone":"+49 9497/6316",
    "sg:postcode":"92358",
    "sg:province":"Bayern",
    "wof:name":"Christian Hug Gmbh",
    "wof:placetype":"venue"
},
  "geometry": {"coordinates":[11.6486177444,49.1856956482],"type":"Point"}
}