{
  "type": "Feature",
  "properties": {
    "iso:country":"DE",
    "sg:address":"Friedrich-Wilhelm-Str. 43",
    "sg:city":"Braunschweig",
    "sg:postcode":"38100",
    "sg:province":"Niedersachsen",
    "wof:name":"Cirkler & S\u00f6llig Ohg",
    "wof:placetype":"venue"
},
  "geometry": {"coordinates":[10.519583,52.260574],"type":"Point"}
}