{
  "type": "Feature",
  "properties": {
    "iso:country":"DE",
    "sg:address":"Bayernstr. 11",
    "sg:city":"Langenhagen",
    "sg:phone":"+49 511/78000",
    "sg:postcode":"30855",
    "sg:province":"Niedersachsen",
    "wof:name":"Itt Flygt Pumpen Gmbh",
    "wof:placetype":"venue"
},
  "geometry": {"coordinates":[9.7039709091,52.4429664612],"type":"Point"}
}