{
  "type": "Feature",
  "properties": {
    "iso:country":"DE",
    "sg:address":"Sorge 19",
    "sg:city":"Clausthal-Zellerfeld",
    "sg:phone":"+49 5323/3114",
    "sg:postcode":"38678",
    "sg:province":"Niedersachsen",
    "wof:name":"Karl Keller",
    "wof:placetype":"venue"
},
  "geometry": {"coordinates":[10.3318662643,51.805393219],"type":"Point"}
}