{
  "type": "Feature",
  "properties": {
    "iso:country":"DE",
    "sg:address":"Fritz-M\u00fcller-Str. 113",
    "sg:city":"Esslingen",
    "sg:phone":"+49 711/311661",
    "sg:postcode":"73730",
    "sg:province":"Baden-W\u00fcrttemberg",
    "wof:name":"Julius Fingerle & S\u00f6hne",
    "wof:placetype":"venue"
},
  "geometry": {"coordinates":[9.3441505432,48.7252426147],"type":"Point"}
}