{
  "type": "Feature",
  "properties": {
    "iso:country":"DE",
    "sg:address":"Heinrichstr 169a",
    "sg:city":"D\u00fcsseldorf",
    "sg:phone":"+49 211/230390",
    "sg:postcode":"40239",
    "sg:province":"Nordrhein-Westfalen",
    "wof:name":"Zcc Europe Gmbh",
    "wof:placetype":"venue"
},
  "geometry": {"coordinates":[6.80224,51.250332],"type":"Point"}
}