{
  "type": "Feature",
  "properties": {
    "iso:country":"DE",
    "sg:address":"Colonnaden 41",
    "sg:city":"Hamburg",
    "sg:phone":"+49 40/340788",
    "sg:postcode":"20354",
    "sg:province":"Hamburg",
    "wof:name":"Ristorante Don Franco",
    "wof:placetype":"venue"
},
  "geometry": {"coordinates":[9.9898471832,53.5572929382],"type":"Point"}
}