{
  "type": "Feature",
  "properties": {
    "iso:country":"DE",
    "sg:address":"Ehrenfeldg\u00fcrtel 78",
    "sg:city":"K\u00f6ln",
    "sg:postcode":"50823",
    "sg:province":"Nordrhein-Westfalen",
    "wof:name":"B\u00fcrgergarde Blau-gold Veranstaltungs- Und",
    "wof:placetype":"venue"
},
  "geometry": {"coordinates":[6.917347908,50.9504089355],"type":"Point"}
}