{
  "type": "Feature",
  "properties": {
    "iso:country":"DE",
    "sg:address":"Ernst-Moritz-Arndt-Str. 68",
    "sg:city":"Neustrelitz",
    "sg:phone":"+49 3981/440106",
    "sg:postcode":"17235",
    "sg:province":"Mecklenburg-Vorpommern",
    "wof:name":"Neustrelitzer Wohnungsges. Mbh",
    "wof:placetype":"venue"
},
  "geometry": {"coordinates":[13.0890436172,53.355594635],"type":"Point"}
}