{
  "type": "Feature",
  "properties": {
    "iso:country":"DE",
    "sg:address":"David-Hansemann-Str. 12",
    "sg:city":"\u00dcbach-Palenberg",
    "sg:phone":"+49 2451/941177",
    "sg:postcode":"52531",
    "sg:province":"Nordrhein-Westfalen",
    "wof:name":"Elemente Vertrieb Rima Gmbh",
    "wof:placetype":"venue"
},
  "geometry": {"coordinates":[6.14545,50.917011],"type":"Point"}
}