{
  "type": "Feature",
  "properties": {
    "iso:country":"DE",
    "sg:address":"Bahnhofstr. 14",
    "sg:city":"Bad K\u00f6nigshofen",
    "sg:phone":"+49 9761/91100",
    "sg:postcode":"97631",
    "sg:province":"Bayern",
    "wof:name":"Zehner Energie Gmbh",
    "wof:placetype":"venue"
},
  "geometry": {"coordinates":[10.459767,50.296913],"type":"Point"}
}