{
  "type": "Feature",
  "properties": {
    "iso:country":"DE",
    "sg:address":"Klingenteichstrasse",
    "sg:city":"Heidelberg",
    "sg:phone":"+49 6221/20828",
    "sg:postcode":"69117",
    "sg:province":"Baden-W\u00fcrttemberg",
    "wof:name":"Neue Betriebswirtschaft",
    "wof:placetype":"venue"
},
  "geometry": {"coordinates":[8.7156476974,49.4053421021],"type":"Point"}
}