{
  "type": "Feature",
  "properties": {
    "iso:country":"DE",
    "sg:address":"Voltastr. 1",
    "sg:city":"N\u00fcrnberg",
    "sg:phone":"+49 911/445737",
    "sg:postcode":"90459",
    "sg:province":"Bayern",
    "wof:name":"Humboldt-apotheke",
    "wof:placetype":"venue"
},
  "geometry": {"coordinates":[11.077406,49.438267],"type":"Point"}
}