{
  "type": "Feature",
  "properties": {
    "iso:country":"DE",
    "sg:address":"An der Weide 1",
    "sg:city":"Hemsbach",
    "sg:phone":"+49 6201/72136",
    "sg:postcode":"69502",
    "sg:province":"Baden-W\u00fcrttemberg",
    "wof:name":"Kreis & S\u00f6hne Gmbh",
    "wof:placetype":"venue"
},
  "geometry": {"coordinates":[8.6258049011,49.5969390869],"type":"Point"}
}