{
  "type": "Feature",
  "properties": {
    "iso:country":"DE",
    "sg:address":"Zeppelinstr. 45",
    "sg:city":"D\u00fcsseldorf",
    "sg:phone":"+49 211/219711",
    "sg:postcode":"40231",
    "sg:province":"Nordrhein-Westfalen",
    "wof:name":"Mahmut Inci",
    "wof:placetype":"venue"
},
  "geometry": {"coordinates":[6.833038,51.205563],"type":"Point"}
}