{
  "type": "Feature",
  "properties": {
    "iso:country":"DE",
    "sg:address":"Scherbaumstr. 18",
    "sg:city":"M\u00fcnchen",
    "sg:postcode":"81737",
    "sg:province":"Bayern",
    "wof:name":"Nie\u00dfl",
    "wof:placetype":"venue"
},
  "geometry": {"coordinates":[11.6274499893,48.0983467102],"type":"Point"}
}