{
  "type": "Feature",
  "properties": {
    "iso:country":"DE",
    "sg:address":"Breitscheidstr. 43",
    "sg:city":"Cossebaude",
    "sg:phone":"+49 351/454470",
    "sg:postcode":"01462",
    "wof:name":"Comrent Gmbh",
    "wof:placetype":"venue"
},
  "geometry": {"coordinates":[13.638416,51.082096],"type":"Point"}
}