{
  "type": "Feature",
  "properties": {
    "iso:country":"DE",
    "sg:address":"Westring 37",
    "sg:city":"G\u00fctersloh",
    "sg:phone":"+49 5241/15974",
    "sg:postcode":"33334",
    "sg:province":"Nordrhein-Westfalen",
    "wof:name":"R\u00f6wekamp \u00d6kologischer Baubedarf",
    "wof:placetype":"venue"
},
  "geometry": {"coordinates":[8.3616104126,51.8934288025],"type":"Point"}
}