{
  "type": "Feature",
  "properties": {
    "iso:country":"DE",
    "sg:address":"Wildunger Str. 38",
    "sg:city":"Bad Wildungen",
    "sg:phone":"+49 5621/3406",
    "sg:postcode":"34537",
    "sg:province":"Hessen",
    "wof:name":"Restaurant Heust\u00fcbl",
    "wof:placetype":"venue"
},
  "geometry": {"coordinates":[9.1133146286,51.0889625549],"type":"Point"}
}