{
  "type": "Feature",
  "properties": {
    "iso:country":"DE",
    "sg:address":"Wielinger Str. 16",
    "sg:city":"Feldafing",
    "sg:phone":"+49 8157/7991",
    "sg:postcode":"82340",
    "sg:province":"Bayern",
    "wof:name":"Kurt Klawonn",
    "wof:placetype":"venue"
},
  "geometry": {"coordinates":[11.290681839,47.9492340088],"type":"Point"}
}