{
  "type": "Feature",
  "properties": {
    "iso:country":"DE",
    "sg:address":"Friedrichstr. 19",
    "sg:city":"Meckesheim",
    "sg:phone":"+49 6226/8831",
    "sg:postcode":"74909",
    "sg:province":"Baden-W\u00fcrttemberg",
    "wof:name":"Billardcafe",
    "wof:placetype":"venue"
},
  "geometry": {"coordinates":[8.819817543,49.3218727112],"type":"Point"}
}