{
  "type": "Feature",
  "properties": {
    "iso:country":"DE",
    "sg:address":"Ysenburgstr. 9",
    "sg:city":"Germersheim",
    "sg:phone":"+49 7274/4005",
    "sg:postcode":"76726",
    "sg:province":"Rheinland-Pfalz",
    "wof:name":"H\u00e4hnchengrill Kern",
    "wof:placetype":"venue"
},
  "geometry": {"coordinates":[8.3745794296,49.2250022888],"type":"Point"}
}