{
  "type": "Feature",
  "properties": {
    "iso:country":"DE",
    "sg:address":"Neupforte 18",
    "sg:city":"Aachen",
    "sg:phone":"+49 241/601271",
    "sg:postcode":"52062",
    "sg:province":"Nordrhein-Westfalen",
    "wof:name":"Breuer Vertriebsges. Mbh",
    "wof:placetype":"venue"
},
  "geometry": {"coordinates":[6.08441782,50.7781333923],"type":"Point"}
}