{
  "type": "Feature",
  "properties": {
    "iso:country":"DE",
    "sg:address":"Kaiser-Friedrich-Ring 62",
    "sg:city":"Wiesbaden",
    "sg:phone":"+49 611/3083230",
    "sg:postcode":"65185",
    "sg:province":"Hessen",
    "wof:name":"50 N-erlebnisse Am Rhein Und Taunus E. K.",
    "wof:placetype":"venue"
},
  "geometry": {"coordinates":[8.2356967926,50.0723304749],"type":"Point"}
}