{
  "type": "Feature",
  "properties": {
    "iso:country":"DE",
    "sg:address":"Ahornweg 10",
    "sg:city":"Gommern",
    "sg:phone":"+49 39200/55941",
    "sg:postcode":"39245",
    "sg:province":"Sachsen-Anhalt",
    "wof:name":"S-kom Deutschland Rent A Handy Schmidt -kommunikationstechnik",
    "wof:placetype":"venue"
},
  "geometry": {"coordinates":[11.808385849,52.0782203674],"type":"Point"}
}