{
  "type": "Feature",
  "properties": {
    "iso:country":"DE",
    "sg:address":"Friedrich-Ebert-Str. 41",
    "sg:city":"D\u00fcsseldorf",
    "sg:phone":"+49 211/1640891",
    "sg:postcode":"40210",
    "sg:province":"Nordrhein-Westfalen",
    "wof:name":"Stefanos Reisen",
    "wof:placetype":"venue"
},
  "geometry": {"coordinates":[6.7898850441,51.22133255],"type":"Point"}
}