{
  "type": "Feature",
  "properties": {
    "iso:country":"DE",
    "sg:address":"Dinnendahlstr. 15",
    "sg:city":"Kleve",
    "sg:phone":"+49 2821/13726",
    "sg:postcode":"47533",
    "sg:province":"Nordrhein-Westfalen",
    "wof:name":"Bendig Autolackiererei Gmbh",
    "wof:placetype":"venue"
},
  "geometry": {"coordinates":[6.13762,51.804165],"type":"Point"}
}