{
  "type": "Feature",
  "properties": {
    "iso:country":"DE",
    "sg:address":"Lichtenseermoos",
    "sg:city":"Niederviehbach",
    "sg:phone":"+49 8702/2937",
    "sg:postcode":"84183",
    "sg:province":"Bayern",
    "wof:name":"Paul H\u00f6schl",
    "wof:placetype":"venue"
},
  "geometry": {"coordinates":[12.3968734741,48.6331596375],"type":"Point"}
}