{
  "type": "Feature",
  "properties": {
    "iso:country":"DE",
    "sg:address":"Wilhelm-Pieck-Str. 55",
    "sg:city":"Dabel",
    "sg:phone":"+49 38485/20278",
    "sg:postcode":"19406",
    "sg:province":"Mecklenburg-Vorpommern",
    "wof:name":"Fritz Ide",
    "wof:placetype":"venue"
},
  "geometry": {"coordinates":[11.896819,53.661339],"type":"Point"}
}