{
  "type": "Feature",
  "properties": {
    "iso:country":"DE",
    "sg:address":"Kirchstr. 169",
    "sg:city":"Herzogenrath",
    "sg:phone":"+49 2406/61166",
    "sg:postcode":"52134",
    "sg:province":"Nordrhein-Westfalen",
    "wof:name":"Eat Energie- Anlagen-technik Gmbh",
    "wof:placetype":"venue"
},
  "geometry": {"coordinates":[6.092008,50.896843],"type":"Point"}
}