{
  "type": "Feature",
  "properties": {
    "iso:country":"DE",
    "sg:address":"Hauptstr. 11",
    "sg:city":"Simbach",
    "sg:phone":"+49 9956/433",
    "sg:postcode":"94436",
    "sg:province":"Bayern",
    "wof:name":"Gasthof Lang",
    "wof:placetype":"venue"
},
  "geometry": {"coordinates":[12.7171106339,48.6071929932],"type":"Point"}
}