{
  "type": "Feature",
  "properties": {
    "iso:country":"DE",
    "sg:address":"Akazienw\u00e4ldchen 8",
    "sg:city":"Dessau",
    "sg:phone":"+49 340/2204422",
    "sg:postcode":"06844",
    "sg:province":"Sachsen-Anhalt",
    "wof:name":"Omega Baudienstleistungen Gmbh",
    "wof:placetype":"venue"
},
  "geometry": {"coordinates":[12.236446,51.833637],"type":"Point"}
}