{
  "type": "Feature",
  "properties": {
    "iso:country":"DE",
    "sg:address":"Havelstr. 78",
    "sg:city":"Birkenwerder",
    "sg:phone":"+49 3303/501364",
    "sg:postcode":"16547",
    "sg:province":"Brandenburg",
    "wof:name":"Gruschkas Heimtierbedarf",
    "wof:placetype":"venue"
},
  "geometry": {"coordinates":[13.260403,52.688408],"type":"Point"}
}