{
  "type": "Feature",
  "properties": {
    "iso:country":"DE",
    "sg:address":"Cochemer Str. 6",
    "sg:city":"Kaisersesch",
    "sg:phone":"+49 2653/3981",
    "sg:postcode":"56759",
    "sg:province":"Rheinland-Pfalz",
    "wof:name":"Eisdiele Dolce Vita",
    "wof:placetype":"venue"
},
  "geometry": {"coordinates":[7.140802,50.229801],"type":"Point"}
}