{
  "type": "Feature",
  "properties": {
    "iso:country":"DE",
    "sg:address":"Branderiede 5",
    "sg:city":"Isernhagen",
    "sg:phone":"+49 511/773300",
    "sg:postcode":"30916",
    "sg:province":"Niedersachsen",
    "wof:name":"Jordan Gmbh",
    "wof:placetype":"venue"
},
  "geometry": {"coordinates":[9.8012228012,52.4814872742],"type":"Point"}
}