{
  "type": "Feature",
  "properties": {
    "iso:country":"DE",
    "sg:address":"Hauptstr. 70",
    "sg:city":"Heuchlingen",
    "sg:phone":"+49 7174/6629",
    "sg:postcode":"73572",
    "sg:province":"Baden-W\u00fcrttemberg",
    "wof:name":"Swo Orthop\u00e4die Zubeh\u00f6r Gmbh",
    "wof:placetype":"venue"
},
  "geometry": {"coordinates":[9.9455337524,48.8557281494],"type":"Point"}
}