{
  "type": "Feature",
  "properties": {
    "iso:country":"DE",
    "sg:address":"Postfach 49",
    "sg:city":"Trebur",
    "sg:phone":"+49 6147/7217",
    "sg:postcode":"65463",
    "sg:province":"Hessen",
    "wof:name":"Schwimmbad",
    "wof:placetype":"venue"
},
  "geometry": {"coordinates":[8.4094552994,49.9242553711],"type":"Point"}
}