{
  "type": "Feature",
  "properties": {
    "iso:country":"DE",
    "sg:address":"Schlei\u00dfheimer Str. 276",
    "sg:city":"M\u00fcnchen",
    "sg:phone":"+49 89/303912",
    "sg:postcode":"80809",
    "sg:province":"Bayern",
    "wof:name":"Walter Geiger Komponist",
    "wof:placetype":"venue"
},
  "geometry": {"coordinates":[11.5665960312,48.1749000549],"type":"Point"}
}