{
  "type": "Feature",
  "properties": {
    "iso:country":"DE",
    "sg:address":"Staulinie 5a",
    "sg:city":"Oldenburg",
    "sg:phone":"+49 441/26222",
    "sg:postcode":"26122",
    "sg:province":"Niedersachsen",
    "wof:name":"Apotheke Langer Im Elisengang",
    "wof:placetype":"venue"
},
  "geometry": {"coordinates":[8.214264,53.142902],"type":"Point"}
}