{
  "type": "Feature",
  "properties": {
    "iso:country":"DE",
    "sg:address":"Engishausen 51",
    "sg:city":"Egg",
    "sg:phone":"+49 8333/1435",
    "sg:postcode":"87743",
    "sg:province":"Bayern",
    "wof:name":"Kath. Pfarramt St. Sebastian",
    "wof:placetype":"venue"
},
  "geometry": {"coordinates":[10.2714605331,48.1096878052],"type":"Point"}
}