{
  "type": "Feature",
  "properties": {
    "iso:country":"DE",
    "sg:address":"Weststr. 178a",
    "sg:city":"Bochum",
    "sg:phone":"+49 2327/320038",
    "sg:postcode":"44866",
    "sg:province":"Nordrhein-Westfalen",
    "wof:name":"Erhard Linka",
    "wof:placetype":"venue"
},
  "geometry": {"coordinates":[7.113074,51.481113],"type":"Point"}
}