{
  "type": "Feature",
  "properties": {
    "iso:country":"DE",
    "sg:address":"Fliednerstr. 40",
    "sg:city":"D\u00fcsseldorf",
    "sg:postcode":"40489",
    "sg:province":"Nordrhein-Westfalen",
    "wof:name":"Die Event Und Marketing Idee Gmbh",
    "wof:placetype":"venue"
},
  "geometry": {"coordinates":[6.7373490334,51.3016319275],"type":"Point"}
}