{
  "type": "Feature",
  "properties": {
    "iso:country":"DE",
    "sg:address":"Sch\u00fcppenstr. 10",
    "sg:city":"Coesfeld",
    "sg:phone":"+49 2541/2765",
    "sg:postcode":"48653",
    "sg:province":"Nordrhein-Westfalen",
    "wof:name":"Reinhard Lezgus Herrenausstatter E. K.",
    "wof:placetype":"venue"
},
  "geometry": {"coordinates":[7.1669712067,51.9453582764],"type":"Point"}
}