{
  "type": "Feature",
  "properties": {
    "iso:country":"DE",
    "sg:address":"Haunstetter Str. 5",
    "sg:city":"K\u00f6nigsbrunn",
    "sg:phone":"+49 8231/31368",
    "sg:postcode":"86343",
    "sg:province":"Bayern",
    "wof:name":"Karl-heinz Baumgart",
    "wof:placetype":"venue"
},
  "geometry": {"coordinates":[10.8980169296,48.292049408],"type":"Point"}
}