{
  "type": "Feature",
  "properties": {
    "iso:country":"DE",
    "sg:address":"Schillerstr. 35",
    "sg:city":"Stein",
    "sg:phone":"+49 911/678800",
    "sg:postcode":"90547",
    "sg:province":"Bayern",
    "wof:name":"Manfred Sack",
    "wof:placetype":"venue"
},
  "geometry": {"coordinates":[11.016713,49.400547],"type":"Point"}
}