{
  "type": "Feature",
  "properties": {
    "iso:country":"DE",
    "sg:address":"Frankenstr. 13",
    "sg:city":"W\u00fcstenrot",
    "sg:postcode":"71543",
    "sg:province":"Baden-W\u00fcrttemberg",
    "wof:name":"P & I Classic-trend- Collection Deutschland E. K.",
    "wof:placetype":"venue"
},
  "geometry": {"coordinates":[9.4847736359,49.1039581299],"type":"Point"}
}