{
  "type": "Feature",
  "properties": {
    "iso:country":"DE",
    "sg:address":"Auguststr. 45",
    "sg:city":"Bremen",
    "sg:phone":"+49 421/382146",
    "sg:postcode":"28219",
    "sg:province":"Bremen",
    "wof:name":"Reinhard Pohl",
    "wof:placetype":"venue"
},
  "geometry": {"coordinates":[8.791641,53.101898],"type":"Point"}
}