{
  "type": "Feature",
  "properties": {
    "iso:country":"DE",
    "sg:address":"Lessingstr. 35",
    "sg:city":"Heppenheim",
    "sg:phone":"+49 6252/982078",
    "sg:postcode":"64646",
    "sg:province":"Hessen",
    "wof:name":"G\u00fcnther M\u00fcllers Textilvertretungen Gmbh",
    "wof:placetype":"venue"
},
  "geometry": {"coordinates":[8.6289453506,49.6424789429],"type":"Point"}
}