{
  "type": "Feature",
  "properties": {
    "iso:country":"DE",
    "sg:address":"Metzgergasse 6",
    "sg:city":"Neustadt",
    "sg:phone":"+49 6321/354186",
    "sg:postcode":"67433",
    "sg:province":"Rheinland-Pfalz",
    "wof:name":"Marktst\u00fcbl",
    "wof:placetype":"venue"
},
  "geometry": {"coordinates":[8.1358203888,49.3532028198],"type":"Point"}
}