{
  "type": "Feature",
  "properties": {
    "iso:country":"DE",
    "sg:address":"Inastr. 12",
    "sg:city":"H\u00f6chstadt",
    "sg:phone":"+49 9193/3399",
    "sg:postcode":"91315",
    "sg:province":"Bayern",
    "wof:name":"U. Vatter",
    "wof:placetype":"venue"
},
  "geometry": {"coordinates":[10.806345,49.694817],"type":"Point"}
}