{
  "type": "Feature",
  "properties": {
    "iso:country":"DE",
    "sg:address":"Westermeyerstr. 10",
    "sg:city":"Feldkirchen-Westerham",
    "sg:postcode":"83620",
    "sg:province":"Bayern",
    "wof:name":"Mamut Retail Gmbh",
    "wof:placetype":"venue"
},
  "geometry": {"coordinates":[11.843572,47.907646],"type":"Point"}
}