{
  "type": "Feature",
  "properties": {
    "iso:country":"DE",
    "sg:address":"Hopen 2",
    "sg:city":"St. Michaelisdonn",
    "sg:phone":"+49 4853/915",
    "sg:postcode":"25693",
    "sg:province":"Schleswig-Holstein",
    "wof:name":"Helga Jannsen",
    "wof:placetype":"venue"
},
  "geometry": {"coordinates":[9.1336660385,53.986328125],"type":"Point"}
}