{
  "type": "Feature",
  "properties": {
    "iso:country":"DE",
    "sg:address":"Greifswalder Chaussee 54",
    "sg:city":"Stralsund",
    "sg:phone":"+49 3831/270986",
    "sg:postcode":"18439",
    "sg:province":"Mecklenburg-Vorpommern",
    "wof:name":"Quast",
    "wof:placetype":"venue"
},
  "geometry": {"coordinates":[13.095362,54.288513],"type":"Point"}
}