{
  "type": "Feature",
  "properties": {
    "iso:country":"DE",
    "sg:address":"Stadelbergerstr 2a",
    "sg:city":"F\u00fcrstenfeldbruck",
    "sg:phone":"+49 8141/621632",
    "sg:postcode":"82256",
    "sg:province":"Bayern",
    "wof:name":"Imkerei M\u00fcller",
    "wof:placetype":"venue"
},
  "geometry": {"coordinates":[11.257386,48.181877],"type":"Point"}
}