{
  "type": "Feature",
  "properties": {
    "iso:country":"DE",
    "sg:address":"Zur Kieskuhle 8",
    "sg:city":"Hitzhusen",
    "sg:postcode":"24576",
    "sg:province":"Schleswig-Holstein",
    "wof:name":"Winkelmann Gmbh",
    "wof:placetype":"venue"
},
  "geometry": {"coordinates":[9.843624115,53.9225883484],"type":"Point"}
}