{
  "type": "Feature",
  "properties": {
    "iso:country":"DE",
    "sg:address":"84 rue Boileau",
    "sg:city":"PARIS",
    "sg:postcode":"75016",
    "wof:name":"Database Administrator On Db2",
    "wof:placetype":"venue"
},
  "geometry": {"coordinates":[2.262132,48.840775],"type":"Point"}
}