{
  "type": "Feature",
  "properties": {
    "iso:country":"DE",
    "sg:address":"Zeumerstr. 1",
    "sg:city":"Leipzig",
    "sg:postcode":"04347",
    "sg:province":"Sachsen",
    "wof:name":"Pflegeheim Sch\u00f6nefeld",
    "wof:placetype":"venue"
},
  "geometry": {"coordinates":[12.408067,51.359276],"type":"Point"}
}