{
  "type": "Feature",
  "properties": {
    "iso:country":"DE",
    "sg:address":"Bern\u00f6ckersiedlung 9",
    "sg:city":"Gmund",
    "sg:phone":"+49 8022/75461",
    "sg:postcode":"83703",
    "sg:province":"Bayern",
    "wof:name":"Friedrich Czerny",
    "wof:placetype":"venue"
},
  "geometry": {"coordinates":[11.7284383774,47.7540092468],"type":"Point"}
}