{
  "type": "Feature",
  "properties": {
    "iso:country":"DE",
    "sg:address":"Dieburger Str. 52",
    "sg:city":"Darmstadt",
    "sg:phone":"+49 6151/710211",
    "sg:postcode":"64287",
    "sg:province":"Hessen",
    "wof:name":"Elif Sevim",
    "wof:placetype":"venue"
},
  "geometry": {"coordinates":[8.6649131775,49.8779067993],"type":"Point"}
}