{
  "type": "Feature",
  "properties": {
    "iso:country":"DE",
    "sg:address":"Jurastr. 1",
    "sg:city":"Pollenfeld",
    "sg:phone":"+49 8423/572",
    "sg:postcode":"85131",
    "sg:province":"Bayern",
    "wof:name":"Michael Und Xaver Hell Ohg",
    "wof:placetype":"venue"
},
  "geometry": {"coordinates":[11.2249555588,48.9600982666],"type":"Point"}
}