{
  "type": "Feature",
  "properties": {
    "iso:country":"DE",
    "sg:address":"Eichenstr. 5",
    "sg:city":"Michelau",
    "sg:phone":"+49 9571/88266",
    "sg:postcode":"96247",
    "sg:province":"Bayern",
    "wof:name":"Lorenz Gmbh",
    "wof:placetype":"venue"
},
  "geometry": {"coordinates":[11.120154,50.168934],"type":"Point"}
}