{
  "type": "Feature",
  "properties": {
    "iso:country":"DE",
    "sg:address":"Leuchau",
    "sg:city":"Kulmbach",
    "sg:phone":"+49 9221/74828",
    "sg:postcode":"95326",
    "sg:province":"Bayern",
    "wof:name":"Gastst\u00e4tte Willi F\u00f6rster",
    "wof:placetype":"venue"
},
  "geometry": {"coordinates":[11.4778404236,50.0684814453],"type":"Point"}
}