{
  "type": "Feature",
  "properties": {
    "iso:country":"DE",
    "sg:address":"Jenaer Str. 1",
    "sg:city":"Bad Salzuflen",
    "sg:phone":"+49 5222/72964",
    "sg:postcode":"32107",
    "sg:province":"Nordrhein-Westfalen",
    "wof:name":"Reuters Schlemmerservice",
    "wof:placetype":"venue"
},
  "geometry": {"coordinates":[8.740249,52.056915],"type":"Point"}
}