{
  "type": "Feature",
  "properties": {
    "iso:country":"DE",
    "sg:address":"Alpenstr 32",
    "sg:city":"Memmingen",
    "sg:phone":"+49 8331/95090",
    "sg:postcode":"87700",
    "sg:province":"Bayern",
    "wof:name":"Schwaben-vlies Gmbh",
    "wof:placetype":"venue"
},
  "geometry": {"coordinates":[10.189475,47.974518],"type":"Point"}
}