{
  "type": "Feature",
  "properties": {
    "iso:country":"DE",
    "sg:address":"Tannh\u00e4user Grund 23",
    "sg:city":"Brombachtal",
    "sg:phone":"+49 6063/58685",
    "sg:postcode":"64753",
    "sg:province":"Hessen",
    "wof:name":"Duschl Handelsgesellschaft Mbh",
    "wof:placetype":"venue"
},
  "geometry": {"coordinates":[8.9403944016,49.7216377258],"type":"Point"}
}