{
  "type": "Feature",
  "properties": {
    "iso:country":"DE",
    "sg:address":"Hagenplatz 5",
    "sg:city":"Berlin",
    "sg:postcode":"14193",
    "sg:province":"Berlin",
    "wof:name":"Z & P Vermietungs- Gesellschaft Mbh",
    "wof:placetype":"venue"
},
  "geometry": {"coordinates":[13.2669496536,52.4833679199],"type":"Point"}
}