{
  "type": "Feature",
  "properties": {
    "iso:country":"DE",
    "sg:address":"Marktplatz 39",
    "sg:city":"Reisbach",
    "sg:phone":"+49 8734/1588",
    "sg:postcode":"94419",
    "sg:province":"Bayern",
    "wof:name":"Brunnen-apotheke Angela Prechtl",
    "wof:placetype":"venue"
},
  "geometry": {"coordinates":[12.628615,48.571438],"type":"Point"}
}