{
  "type": "Feature",
  "properties": {
    "iso:country":"DE",
    "sg:address":"Wisholzstr. 12",
    "sg:city":"L\u00f6ffingen",
    "sg:phone":"+49 7654/7005",
    "sg:postcode":"79843",
    "sg:province":"Baden-W\u00fcrttemberg",
    "wof:name":"A. Bausch",
    "wof:placetype":"venue"
},
  "geometry": {"coordinates":[8.346602,47.873627],"type":"Point"}
}