{
  "type": "Feature",
  "properties": {
    "iso:country":"DE",
    "sg:address":"Sonthofener Str. 5",
    "sg:city":"Burgberg",
    "sg:phone":"+49 8321/22519",
    "sg:postcode":"87545",
    "sg:province":"Bayern",
    "wof:name":"Kreuz",
    "wof:placetype":"venue"
},
  "geometry": {"coordinates":[10.2856016159,47.5374755859],"type":"Point"}
}