{
  "type": "Feature",
  "properties": {
    "iso:country":"DE",
    "sg:address":"Reiherweg 9",
    "sg:city":"Marl",
    "sg:phone":"+49 2365/24900",
    "sg:postcode":"45772",
    "sg:province":"Nordrhein-Westfalen",
    "wof:name":"Wohl-bau Bau Gmbh",
    "wof:placetype":"venue"
},
  "geometry": {"coordinates":[7.123949,51.683224],"type":"Point"}
}