{
  "type": "Feature",
  "properties": {
    "iso:country":"DE",
    "sg:address":"Freiheitsstr. 23 b",
    "sg:city":"Nordhausen",
    "sg:phone":"+49 3631/61390",
    "sg:postcode":"99734",
    "sg:province":"Th\u00fcringen",
    "wof:name":"Thomas Dietrich",
    "wof:placetype":"venue"
},
  "geometry": {"coordinates":[10.7795534134,51.5301933289],"type":"Point"}
}