{
  "type": "Feature",
  "properties": {
    "iso:country":"DE",
    "sg:address":"Avenue Charles de Gaulle 10",
    "sg:city":"Berlin",
    "sg:postcode":"13469",
    "sg:province":"Berlin",
    "wof:name":"Aldi Gmbh & Co. Kg",
    "wof:placetype":"venue"
},
  "geometry": {"coordinates":[13.3223810196,52.6026573181],"type":"Point"}
}