{
  "type": "Feature",
  "properties": {
    "iso:country":"DE",
    "sg:address":"Lindenstr. 2",
    "sg:city":"Dettingen",
    "sg:phone":"+49 7021/59292",
    "sg:postcode":"73265",
    "sg:province":"Baden-W\u00fcrttemberg",
    "wof:name":"Alfred Stuhler",
    "wof:placetype":"venue"
},
  "geometry": {"coordinates":[9.452331,48.615051],"type":"Point"}
}