{
  "type": "Feature",
  "properties": {
    "iso:country":"DE",
    "sg:address":"Speyerer Str. 33",
    "sg:city":"Mannheim",
    "sg:phone":"+49 621/814868",
    "sg:postcode":"68199",
    "sg:province":"Baden-W\u00fcrttemberg",
    "wof:name":"Roland Ringler",
    "wof:placetype":"venue"
},
  "geometry": {"coordinates":[8.480092,49.466446],"type":"Point"}
}