{
  "type": "Feature",
  "properties": {
    "iso:country":"DE",
    "sg:address":"Possenallee 2a",
    "sg:city":"Sondershausen",
    "sg:phone":"+49 3632/783112",
    "sg:postcode":"99706",
    "sg:province":"Th\u00fcringen",
    "wof:name":"Gerhard Braun",
    "wof:placetype":"venue"
},
  "geometry": {"coordinates":[10.8716268539,51.3681755066],"type":"Point"}
}