{
  "type": "Feature",
  "properties": {
    "iso:country":"DE",
    "sg:address":"Auweg 38",
    "sg:city":"Wildeck",
    "sg:phone":"+49 6626/238",
    "sg:postcode":"36208",
    "sg:province":"Hessen",
    "wof:name":"H. Eimer",
    "wof:placetype":"venue"
},
  "geometry": {"coordinates":[10.0421228409,50.947845459],"type":"Point"}
}