{
  "type": "Feature",
  "properties": {
    "iso:country":"DE",
    "sg:address":"Industriestr. 16",
    "sg:city":"Greding",
    "sg:phone":"+49 8463/774",
    "sg:postcode":"91171",
    "sg:province":"Bayern",
    "wof:name":"Groh Transport- Vermittlungs Gmbh",
    "wof:placetype":"venue"
},
  "geometry": {"coordinates":[11.3406095505,49.0460014343],"type":"Point"}
}