{
  "type": "Feature",
  "properties": {
    "iso:country":"DE",
    "sg:address":"Feldstr. 32",
    "sg:city":"Alveslohe",
    "sg:phone":"+49 4193/1355",
    "sg:postcode":"25486",
    "sg:province":"Schleswig-Holstein",
    "wof:name":"M. Skibbe",
    "wof:placetype":"venue"
},
  "geometry": {"coordinates":[9.909198761,53.7923812866],"type":"Point"}
}