{
  "type": "Feature",
  "properties": {
    "iso:country":"DE",
    "sg:address":"Glatzer Str. 27",
    "sg:city":"Hamburg",
    "sg:phone":"+49 40/67391868",
    "sg:postcode":"22045",
    "sg:province":"Hamburg",
    "wof:name":"Bernhard Br\u00fcggemann Architekt",
    "wof:placetype":"venue"
},
  "geometry": {"coordinates":[10.145865,53.577084],"type":"Point"}
}