{
  "type": "Feature",
  "properties": {
    "iso:country":"DE",
    "sg:address":"K\u00f6lner Str. 6",
    "sg:city":"Eschborn",
    "sg:phone":"+49 4961/964740",
    "sg:postcode":"65760",
    "sg:province":"Hessen",
    "wof:name":"Deutsche Shell Chemie Gmbh",
    "wof:placetype":"venue"
},
  "geometry": {"coordinates":[8.570119,50.13279],"type":"Point"}
}