{
  "type": "Feature",
  "properties": {
    "iso:country":"DE",
    "sg:address":"J\u00fcdtstr. 60",
    "sg:city":"Ansbach",
    "sg:phone":"+49 981/84125",
    "sg:postcode":"91522",
    "sg:province":"Bayern",
    "wof:name":"G. B\u00fcttner",
    "wof:placetype":"venue"
},
  "geometry": {"coordinates":[10.5731,49.31179],"type":"Point"}
}