{
  "type": "Feature",
  "properties": {
    "iso:country":"DE",
    "sg:address":"Arnulf-Str. 203",
    "sg:city":"M\u00fcnchen",
    "sg:phone":"+49 89/52080",
    "sg:postcode":"80634",
    "sg:province":"Bayern",
    "wof:name":"Eon Bayern Ag",
    "wof:placetype":"venue"
},
  "geometry": {"coordinates":[11.521355,48.149231],"type":"Point"}
}