{
  "type": "Feature",
  "properties": {
    "iso:country":"DE",
    "sg:address":"Schwarzersdorf 3",
    "sg:city":"Mauern",
    "sg:phone":"+49 8764/466",
    "sg:postcode":"85419",
    "sg:province":"Bayern",
    "wof:name":"Josef Halbinger Gmbh",
    "wof:placetype":"venue"
},
  "geometry": {"coordinates":[11.9161701202,48.5289154053],"type":"Point"}
}