{
  "type": "Feature",
  "properties": {
    "iso:country":"DE",
    "sg:address":"Karolingerstr. 14",
    "sg:city":"Andernach",
    "sg:phone":"+49 2632/949642",
    "sg:postcode":"56626",
    "sg:province":"Rheinland-Pfalz",
    "wof:name":"T. Manstein",
    "wof:placetype":"venue"
},
  "geometry": {"coordinates":[7.40697,50.437698],"type":"Point"}
}