{
  "type": "Feature",
  "properties": {
    "iso:country":"DE",
    "sg:address":"Am Pflanzkamp 28",
    "sg:city":"D\u00fcsseldorf",
    "sg:phone":"+49 211/224901",
    "sg:postcode":"40229",
    "sg:province":"Nordrhein-Westfalen",
    "wof:name":"Werner Mehl",
    "wof:placetype":"venue"
},
  "geometry": {"coordinates":[6.862194,51.192024],"type":"Point"}
}