{
  "type": "Feature",
  "properties": {
    "iso:country":"DE",
    "sg:address":"Leopoldstr. 11",
    "sg:city":"Marktredwitz",
    "sg:phone":"+49 9231/5481",
    "sg:postcode":"95615",
    "sg:province":"Bayern",
    "wof:name":"Jahn Orthop\u00e4die Gmbh",
    "wof:placetype":"venue"
},
  "geometry": {"coordinates":[12.084394455,50.0003051758],"type":"Point"}
}