{
  "type": "Feature",
  "properties": {
    "iso:country":"DE",
    "sg:address":"Geismar Landstr. 5",
    "sg:city":"G\u00f6ttingen",
    "sg:phone":"+49 551/44660",
    "sg:postcode":"37083",
    "sg:province":"Niedersachsen",
    "wof:name":"Dr. S. Nolte Rechtsanwalt",
    "wof:placetype":"venue"
},
  "geometry": {"coordinates":[9.9402503967,51.5292205811],"type":"Point"}
}