{
  "type": "Feature",
  "properties": {
    "iso:country":"DE",
    "sg:address":"Rehmendamm 49",
    "sg:city":"Seevetal",
    "sg:phone":"+49 40/7685795",
    "sg:postcode":"21217",
    "sg:province":"Niedersachsen",
    "wof:name":"Hentschel Gmbh",
    "wof:placetype":"venue"
},
  "geometry": {"coordinates":[10.054698,53.425564],"type":"Point"}
}