{
  "type": "Feature",
  "properties": {
    "iso:country":"DE",
    "sg:address":"K\u00f6lnstr. 433",
    "sg:city":"Bonn",
    "sg:phone":"+49 228/673305",
    "sg:postcode":"53117",
    "sg:province":"Nordrhein-Westfalen",
    "wof:name":"Kloster-apotheke",
    "wof:placetype":"venue"
},
  "geometry": {"coordinates":[7.075071,50.751587],"type":"Point"}
}