{
  "type": "Feature",
  "properties": {
    "iso:country":"DE",
    "sg:address":"L\u00fcbbenauer Str. 7",
    "sg:city":"Luckau",
    "sg:postcode":"15926",
    "sg:province":"Brandenburg",
    "wof:name":"Verazi Beteiligungs Gmbh",
    "wof:placetype":"venue"
},
  "geometry": {"coordinates":[13.72826,51.852608],"type":"Point"}
}