{
  "type": "Feature",
  "properties": {
    "iso:country":"DE",
    "sg:address":"Dircksenstr. 49",
    "sg:city":"Berlin",
    "sg:postcode":"10178",
    "sg:province":"Berlin",
    "wof:name":"Neue Hackesche H\u00f6fe Immobilien Verwaltungs Gmbh",
    "wof:placetype":"venue"
},
  "geometry": {"coordinates":[13.4045305252,52.5235404968],"type":"Point"}
}