{
  "type": "Feature",
  "properties": {
    "iso:country":"DE",
    "sg:address":"Koblenzer Str. 23",
    "sg:city":"Nentershausen",
    "sg:phone":"+49 6485/4914",
    "sg:postcode":"56412",
    "sg:province":"Rheinland-Pfalz",
    "wof:name":"W. Skorupowski",
    "wof:placetype":"venue"
},
  "geometry": {"coordinates":[7.934527,50.420288],"type":"Point"}
}