{
  "type": "Feature",
  "properties": {
    "iso:country":"DE",
    "sg:address":"Quelkhorner Landstr. 17",
    "sg:city":"Ottersberg",
    "sg:phone":"+49 4205/779599",
    "sg:postcode":"28870",
    "sg:province":"Niedersachsen",
    "wof:name":"Bit Bautr\u00e4ger Inovation Und Technik Gmbh",
    "wof:placetype":"venue"
},
  "geometry": {"coordinates":[9.081843,53.133518],"type":"Point"}
}