{
  "type": "Feature",
  "properties": {
    "iso:country":"DE",
    "sg:address":"Schulstr. 84",
    "sg:city":"Duisburg",
    "sg:phone":"+49 2841/8428",
    "sg:postcode":"47199",
    "sg:province":"Nordrhein-Westfalen",
    "wof:name":"D. Rohde",
    "wof:placetype":"venue"
},
  "geometry": {"coordinates":[6.7354221344,51.5226020813],"type":"Point"}
}