{
  "type": "Feature",
  "properties": {
    "iso:country":"DE",
    "sg:address":"Friedbergstr. 20",
    "sg:city":"Berlin",
    "sg:phone":"+49 30/3238357",
    "sg:postcode":"14057",
    "sg:province":"Berlin",
    "wof:name":"Christel Gust",
    "wof:placetype":"venue"
},
  "geometry": {"coordinates":[13.2953443527,52.5043907166],"type":"Point"}
}