{
  "type": "Feature",
  "properties": {
    "iso:country":"DE",
    "sg:address":"Bahnhofstr. 39",
    "sg:city":"Buchloe",
    "sg:postcode":"86807",
    "sg:province":"Bayern",
    "wof:name":"K\u00f6nigsheideweg 240 Berlin- Treptow Grundbesitz Ge-",
    "wof:placetype":"venue"
},
  "geometry": {"coordinates":[10.719544,48.034416],"type":"Point"}
}