{
  "type": "Feature",
  "properties": {
    "iso:country":"DE",
    "sg:address":"Karpfenstr. 10",
    "sg:city":"Kaiserslautern",
    "sg:phone":"+49 631/891305",
    "sg:postcode":"67655",
    "sg:province":"Rheinland-Pfalz",
    "wof:name":"Mescic",
    "wof:placetype":"venue"
},
  "geometry": {"coordinates":[7.7741470337,49.4419555664],"type":"Point"}
}