{
  "type": "Feature",
  "properties": {
    "iso:country":"DE",
    "sg:address":"Sonnenstr. 8",
    "sg:city":"V\u00f6hringen",
    "sg:phone":"+49 7306/96050",
    "sg:postcode":"89269",
    "sg:province":"Bayern",
    "wof:name":"Ihle Grundst\u00fccksverwaltungs Gmbh & Co. Kg",
    "wof:placetype":"venue"
},
  "geometry": {"coordinates":[10.0857086182,48.282245636],"type":"Point"}
}