{
  "type": "Feature",
  "properties": {
    "iso:country":"DE",
    "sg:address":"Leonhardstr. 12",
    "sg:city":"N\u00fcrnberg",
    "sg:phone":"+49 911/264392",
    "sg:postcode":"90443",
    "sg:province":"Bayern",
    "wof:name":"Dieter Bernet",
    "wof:placetype":"venue"
},
  "geometry": {"coordinates":[11.063489,49.446075],"type":"Point"}
}