{
  "type": "Feature",
  "properties": {
    "iso:country":"DE",
    "sg:address":"Klarastr. 32",
    "sg:city":"bochum",
    "sg:postcode":"44793",
    "sg:province":"Nordrhein-Westfalen",
    "wof:name":"H\u00d6nn`s Galaxy",
    "wof:placetype":"venue"
},
  "geometry": {"coordinates":[7.203356,51.477825],"type":"Point"}
}