{
  "type": "Feature",
  "properties": {
    "iso:country":"DE",
    "sg:address":"Rathenaustr. 10",
    "sg:city":"Hamm",
    "sg:phone":"+49 2381/417703",
    "sg:postcode":"59067",
    "sg:province":"Nordrhein-Westfalen",
    "wof:name":"Steinbrecher Hvv Gmbh",
    "wof:placetype":"venue"
},
  "geometry": {"coordinates":[7.7911391258,51.6563606262],"type":"Point"}
}