{
  "type": "Feature",
  "properties": {
    "iso:country":"DE",
    "sg:address":"L\u00f6tterfelder Str. 5",
    "sg:city":"Meerbusch",
    "sg:phone":"+49 2132/72719",
    "sg:postcode":"40667",
    "sg:province":"Nordrhein-Westfalen",
    "wof:name":"Grete Und Josef Wienen",
    "wof:placetype":"venue"
},
  "geometry": {"coordinates":[6.6864929199,51.2398529053],"type":"Point"}
}