{
  "type": "Feature",
  "properties": {
    "iso:country":"DE",
    "sg:address":"M\u00fchlenstr. 2",
    "sg:city":"Paderborn",
    "sg:postcode":"33098",
    "sg:province":"Nordrhein-Westfalen",
    "wof:name":"El Sol Detmold Gmbh",
    "wof:placetype":"venue"
},
  "geometry": {"coordinates":[8.7524728775,51.7203483582],"type":"Point"}
}