{
  "type": "Feature",
  "properties": {
    "iso:country":"DE",
    "sg:address":"Schneiderm\u00fchl 1",
    "sg:city":"Tittling",
    "sg:phone":"+49 8504/1780",
    "sg:postcode":"94104",
    "sg:province":"Bayern",
    "wof:name":"Heinrich Breinbauer Schneiderm\u00fchl",
    "wof:placetype":"venue"
},
  "geometry": {"coordinates":[13.4033155441,48.7555541992],"type":"Point"}
}