{
  "type": "Feature",
  "properties": {
    "iso:country":"DE",
    "sg:address":"Industriestr. 30",
    "sg:city":"Kronach",
    "sg:postcode":"96317",
    "sg:province":"Bayern",
    "wof:name":"Rubenbauer Verwaltungs Gmbh",
    "wof:placetype":"venue"
},
  "geometry": {"coordinates":[11.3391752243,50.2318191528],"type":"Point"}
}