{
  "type": "Feature",
  "properties": {
    "iso:country":"DE",
    "sg:address":"Fabriciusstr. 87",
    "sg:city":"Hamburg",
    "sg:phone":"+49 40/6912222",
    "sg:postcode":"22177",
    "sg:province":"Hamburg",
    "wof:name":"A. Dietz",
    "wof:placetype":"venue"
},
  "geometry": {"coordinates":[10.0623903275,53.6016349792],"type":"Point"}
}