{
  "type": "Feature",
  "properties": {
    "iso:country":"DE",
    "sg:address":"Pestalozzistr. 2",
    "sg:city":"Weifa",
    "sg:phone":"+49 35951/31702",
    "sg:postcode":"01904",
    "sg:province":"Sachsen",
    "wof:name":"Reiner Schramm",
    "wof:placetype":"venue"
},
  "geometry": {"coordinates":[14.3636217117,51.0762329102],"type":"Point"}
}