{
  "type": "Feature",
  "properties": {
    "iso:country":"DE",
    "sg:address":"Elbeweg 79",
    "sg:city":"Langenhagen",
    "sg:phone":"+49 511/731682",
    "sg:postcode":"30851",
    "sg:province":"Niedersachsen",
    "wof:name":"Klaus Kr\u00fcger",
    "wof:placetype":"venue"
},
  "geometry": {"coordinates":[9.749317,52.436832],"type":"Point"}
}