{
  "type": "Feature",
  "properties": {
    "iso:country":"DE",
    "sg:address":"Langer Hagen",
    "sg:city":"Dedelstorf",
    "sg:phone":"+49 5832/6405",
    "sg:postcode":"29386",
    "sg:province":"Niedersachsen",
    "wof:name":"U. Gerstl",
    "wof:placetype":"venue"
},
  "geometry": {"coordinates":[10.517839,52.731995],"type":"Point"}
}