{
  "type": "Feature",
  "properties": {
    "iso:country":"DE",
    "sg:address":"Dorfstr. 51",
    "sg:city":"Spalt",
    "sg:phone":"+49 9175/9726",
    "sg:postcode":"91174",
    "sg:province":"Bayern",
    "wof:name":"Josef Maurer",
    "wof:placetype":"venue"
},
  "geometry": {"coordinates":[10.942251,49.167831],"type":"Point"}
}