{
  "type": "Feature",
  "properties": {
    "iso:country":"DE",
    "sg:address":"Poppauer Str. 42",
    "sg:city":"Kl\u00f6tze",
    "sg:postcode":"38486",
    "sg:province":"Sachsen-Anhalt",
    "wof:name":"Kreisarchiv Au\u00dfenstelle Kl\u00f6tze",
    "wof:placetype":"venue"
},
  "geometry": {"coordinates":[11.155284,52.629543],"type":"Point"}
}