{
  "type": "Feature",
  "properties": {
    "iso:country":"DE",
    "sg:address":"Uferstr. 20",
    "sg:city":"Oststeinbek",
    "sg:phone":"+49 40/7125448",
    "sg:postcode":"22113",
    "sg:province":"Schleswig-Holstein",
    "wof:name":"Hamburger Verband F\u00fcr Sportakrobatik",
    "wof:placetype":"venue"
},
  "geometry": {"coordinates":[10.1662921906,53.5399131775],"type":"Point"}
}