{
  "type": "Feature",
  "properties": {
    "iso:country":"DE",
    "sg:address":"Freiherr-vom-Stein-Str. 11",
    "sg:city":"Dreieich",
    "sg:phone":"+49 6103/66666",
    "sg:postcode":"63303",
    "sg:province":"Hessen",
    "wof:name":"W. Sch\u00e4fer",
    "wof:placetype":"venue"
},
  "geometry": {"coordinates":[8.6935558319,50.0296859741],"type":"Point"}
}