{
  "type": "Feature",
  "properties": {
    "iso:country":"DE",
    "sg:address":"Hauptstr. 25",
    "sg:city":"Apen",
    "sg:phone":"+49 4489/6360",
    "sg:postcode":"26689",
    "sg:province":"Niedersachsen",
    "wof:name":"Ratsgrill",
    "wof:placetype":"venue"
},
  "geometry": {"coordinates":[7.8428401947,53.2300415039],"type":"Point"}
}