{
  "type": "Feature",
  "properties": {
    "iso:country":"DE",
    "sg:address":"Gro\u00dfe Str. 69",
    "sg:city":"Strausberg",
    "sg:phone":"+49 3341/22283",
    "sg:postcode":"15344",
    "sg:province":"Brandenburg",
    "wof:name":"Benno Klein",
    "wof:placetype":"venue"
},
  "geometry": {"coordinates":[13.881816,52.578217],"type":"Point"}
}