{
  "type": "Feature",
  "properties": {
    "iso:country":"DE",
    "sg:address":"Nollesweg 10",
    "sg:city":"Niederkr\u00fcchten",
    "sg:phone":"+49 2163/83022",
    "sg:postcode":"41372",
    "sg:province":"Nordrhein-Westfalen",
    "wof:name":"Serax Gmbh",
    "wof:placetype":"venue"
},
  "geometry": {"coordinates":[6.13434,51.212387],"type":"Point"}
}