{
  "type": "Feature",
  "properties": {
    "iso:country":"DE",
    "sg:address":"Wilmersdorfer Str. 122",
    "sg:city":"Berlin",
    "sg:phone":"+49 30/6289020",
    "sg:postcode":"10627",
    "sg:province":"Berlin",
    "wof:name":"Kompakt Versicherungs- Service Gmbh & Co. Kg",
    "wof:placetype":"venue"
},
  "geometry": {"coordinates":[13.3061437607,52.5090904236],"type":"Point"}
}