{
  "type": "Feature",
  "properties": {
    "iso:country":"DE",
    "sg:address":"Hauptstr. 114 a",
    "sg:city":"Pei\u00dfenberg",
    "sg:phone":"+49 8803/9226",
    "sg:postcode":"82380",
    "sg:province":"Bayern",
    "wof:name":"Michael Sendl",
    "wof:placetype":"venue"
},
  "geometry": {"coordinates":[11.0633153915,47.7991447449],"type":"Point"}
}