{
  "type": "Feature",
  "properties": {
    "iso:country":"DE",
    "sg:address":"Kaiserstr. 14",
    "sg:city":"Brechen",
    "sg:phone":"+49 6438/2362",
    "sg:postcode":"65611",
    "sg:province":"Hessen",
    "wof:name":"Josef W. Kremer",
    "wof:placetype":"venue"
},
  "geometry": {"coordinates":[8.162714,50.361584],"type":"Point"}
}