{
  "type": "Feature",
  "properties": {
    "iso:country":"DE",
    "sg:address":"Schwalbacher Str. 70",
    "sg:city":"Eschborn",
    "sg:phone":"+49 6196/43724",
    "sg:postcode":"65760",
    "sg:province":"Hessen",
    "wof:name":"Zuper Kg",
    "wof:placetype":"venue"
},
  "geometry": {"coordinates":[8.5573835373,50.1445198059],"type":"Point"}
}