{
  "type": "Feature",
  "properties": {
    "iso:country":"DE",
    "sg:address":"Theodor-K\u00f6rner-Str 44",
    "sg:city":"Rostock",
    "sg:phone":"+49 381/712444",
    "sg:postcode":"18106",
    "sg:province":"Mecklenburg-Vorpommern",
    "wof:name":"Herrmann",
    "wof:placetype":"venue"
},
  "geometry": {"coordinates":[12.05073,54.124313],"type":"Point"}
}