{
  "type": "Feature",
  "properties": {
    "iso:country":"DE",
    "sg:address":"Mannebacher Str. 23a",
    "sg:city":"Tawern",
    "sg:phone":"+49 6501/99440",
    "sg:postcode":"54456",
    "sg:province":"Rheinland-Pfalz",
    "wof:name":"Martin Wittschler",
    "wof:placetype":"venue"
},
  "geometry": {"coordinates":[6.5209379196,49.6723937988],"type":"Point"}
}