{
  "type": "Feature",
  "properties": {
    "iso:country":"DE",
    "sg:address":"Heckenbeck",
    "sg:city":"Bad Gandersheim",
    "sg:postcode":"37581",
    "sg:province":"Niedersachsen",
    "wof:name":"B\u00fcrgergemeinschaft Heckenbeck Horst Frenzel",
    "wof:placetype":"venue"
},
  "geometry": {"coordinates":[9.9607400894,51.8848190308],"type":"Point"}
}