{
  "type": "Feature",
  "properties": {
    "iso:country":"DE",
    "sg:address":"Bahnhofstr. 37",
    "sg:city":"Plaidt",
    "sg:phone":"+49 2632/5208",
    "sg:postcode":"56637",
    "sg:province":"Rheinland-Pfalz",
    "wof:name":"E. Mosen",
    "wof:placetype":"venue"
},
  "geometry": {"coordinates":[7.3914790154,50.3912773132],"type":"Point"}
}