{
  "type": "Feature",
  "properties": {
    "iso:country":"DE",
    "sg:address":"Hopfenstr. 2",
    "sg:city":"Baden-Baden",
    "sg:phone":"+49 7221/24669",
    "sg:postcode":"76530",
    "sg:province":"Baden-W\u00fcrttemberg",
    "wof:name":"Alexander Wiedholz Kg",
    "wof:placetype":"venue"
},
  "geometry": {"coordinates":[8.247631073,48.757938385],"type":"Point"}
}