{
  "type": "Feature",
  "properties": {
    "iso:country":"DE",
    "sg:address":"Landstr. 4",
    "sg:city":"Rasdorf",
    "sg:phone":"+49 6651/371",
    "sg:postcode":"36169",
    "sg:province":"Hessen",
    "wof:name":"Alfred Ziegler Nah-und Fernverkehrs",
    "wof:placetype":"venue"
},
  "geometry": {"coordinates":[9.8964834213,50.7168769836],"type":"Point"}
}