{
  "type": "Feature",
  "properties": {
    "iso:country":"DE",
    "sg:address":"Hindenburgring 35",
    "sg:city":"Gronau",
    "sg:phone":"+49 2565/97490",
    "sg:postcode":"48599",
    "sg:province":"Nordrhein-Westfalen",
    "wof:name":"Zegna Baruffa Lane Borgosesia Gmbh",
    "wof:placetype":"venue"
},
  "geometry": {"coordinates":[7.04165,52.181484],"type":"Point"}
}