{
  "type": "Feature",
  "properties": {
    "iso:country":"DE",
    "sg:address":"S\u00fcderweg 3",
    "sg:city":"Wanderup",
    "sg:postcode":"24997",
    "sg:province":"Schleswig-Holstein",
    "wof:name":"Windpark Bentstreek Ohg",
    "wof:placetype":"venue"
},
  "geometry": {"coordinates":[9.332205,54.687035],"type":"Point"}
}