{
  "type": "Feature",
  "properties": {
    "iso:country":"DE",
    "sg:address":"Riemeisterstr. 122",
    "sg:city":"Berlin",
    "sg:phone":"+49 30/8138448",
    "sg:postcode":"14169",
    "sg:province":"Berlin",
    "wof:name":"Dieter Schulz",
    "wof:placetype":"venue"
},
  "geometry": {"coordinates":[13.255455,52.449043],"type":"Point"}
}