{
  "type": "Feature",
  "properties": {
    "iso:country":"DE",
    "sg:address":"Karl-Hertel-Str. 2",
    "sg:city":"N\u00fcrnberg",
    "sg:phone":"+49 911/835838",
    "sg:postcode":"90475",
    "sg:province":"Bayern",
    "wof:name":"R. Und J. Zimmermann Drogerie",
    "wof:placetype":"venue"
},
  "geometry": {"coordinates":[11.173496,49.412228],"type":"Point"}
}