{
  "type": "Feature",
  "properties": {
    "iso:country":"DE",
    "sg:address":"Kniereit 22",
    "sg:city":"Sch\u00f6fweg",
    "sg:phone":"+49 9908/320",
    "sg:postcode":"94572",
    "sg:province":"Bayern",
    "wof:name":"Heribert Lang Holzbildhauer",
    "wof:placetype":"venue"
},
  "geometry": {"coordinates":[13.2463283539,48.8321418762],"type":"Point"}
}