{
  "type": "Feature",
  "properties": {
    "iso:country":"DE",
    "sg:address":"K\u00f6rnerstr. 72",
    "sg:city":"Neuss",
    "sg:phone":"+49 2131/42681",
    "sg:postcode":"41464",
    "sg:province":"Nordrhein-Westfalen",
    "wof:name":"Restaurant A Guitarra",
    "wof:placetype":"venue"
},
  "geometry": {"coordinates":[6.6924939156,51.1862373352],"type":"Point"}
}