{
  "type": "Feature",
  "properties": {
    "iso:country":"DE",
    "sg:address":"Aletshauser Str.",
    "sg:city":"Waltenhausen",
    "sg:phone":"+49 8263/227",
    "sg:postcode":"86480",
    "sg:province":"Bayern",
    "wof:name":"Gert Specker",
    "wof:placetype":"venue"
},
  "geometry": {"coordinates":[10.364859581,48.1931533813],"type":"Point"}
}