{
  "type": "Feature",
  "properties": {
    "iso:country":"DE",
    "sg:address":"Am Exerzierplatz 15",
    "sg:city":"Mannheim",
    "sg:phone":"+49 621/301051",
    "sg:postcode":"68167",
    "sg:province":"Baden-W\u00fcrttemberg",
    "wof:name":"Carbo Kohlens\u00e4urevertrieb Und Feuerl\u00f6schanlagen Gmbh",
    "wof:placetype":"venue"
},
  "geometry": {"coordinates":[8.4968643188,49.504360199],"type":"Point"}
}