{
  "type": "Feature",
  "properties": {
    "iso:country":"DE",
    "sg:address":"Alexander-Gerbig-Str. 26",
    "sg:city":"Suhl",
    "sg:phone":"+49 3681/762133",
    "sg:postcode":"98527",
    "sg:province":"Th\u00fcringen",
    "wof:name":"Andreas Gie\u00dfler",
    "wof:placetype":"venue"
},
  "geometry": {"coordinates":[10.7098789215,50.6108016968],"type":"Point"}
}