{
  "type": "Feature",
  "properties": {
    "iso:country":"DE",
    "sg:address":"Dolberger Str. 136",
    "sg:city":"Ahlen",
    "sg:phone":"+49 2382/65675",
    "sg:postcode":"59229",
    "sg:province":"Nordrhein-Westfalen",
    "wof:name":"D. Knippschild",
    "wof:placetype":"venue"
},
  "geometry": {"coordinates":[7.8977351189,51.7493515015],"type":"Point"}
}