{
  "type": "Feature",
  "properties": {
    "iso:country":"DE",
    "sg:address":"An Der Eisenschmelze 7",
    "sg:city":"Sonthofen",
    "sg:phone":"+49 8321/66400",
    "sg:postcode":"87527",
    "sg:province":"Bayern",
    "wof:name":"Offsetdruck Gmbh Sonthofen",
    "wof:placetype":"venue"
},
  "geometry": {"coordinates":[10.2736,47.52113],"type":"Point"}
}