{
  "type": "Feature",
  "properties": {
    "iso:country":"DE",
    "sg:address":"Pl\u00f6ner Str. 5",
    "sg:city":"Ahrensb\u00f6k",
    "sg:phone":"+49 4525/1228",
    "sg:postcode":"23623",
    "sg:province":"Schleswig-Holstein",
    "wof:name":"K\u00f6nigl. Privilegierte Apotheke",
    "wof:placetype":"venue"
},
  "geometry": {"coordinates":[10.571976,54.016167],"type":"Point"}
}