{
  "type": "Feature",
  "properties": {
    "iso:country":"DE",
    "sg:address":"Sch\u00f6nhauser Allee 124",
    "sg:city":"Berlin",
    "sg:phone":"+49 30/4485842",
    "sg:postcode":"10437",
    "sg:province":"Berlin",
    "wof:name":"Star-burger",
    "wof:placetype":"venue"
},
  "geometry": {"coordinates":[13.4129343033,52.5474967957],"type":"Point"}
}