{
  "type": "Feature",
  "properties": {
    "iso:country":"DE",
    "sg:address":"Brunnengasse 17",
    "sg:city":"Neuhausen",
    "sg:phone":"+49 7777/7477",
    "sg:postcode":"78579",
    "sg:province":"Baden-W\u00fcrttemberg",
    "wof:name":"M. Binkele",
    "wof:placetype":"venue"
},
  "geometry": {"coordinates":[9.0070228577,47.9434356689],"type":"Point"}
}