{
  "type": "Feature",
  "properties": {
    "iso:country":"DE",
    "sg:address":"Feldstr. 2 a",
    "sg:city":"Hennstedt",
    "sg:postcode":"25779",
    "sg:province":"Schleswig-Holstein",
    "wof:name":"Dieter Albertz",
    "wof:placetype":"venue"
},
  "geometry": {"coordinates":[9.1599626541,54.2891845703],"type":"Point"}
}