{
  "type": "Feature",
  "properties": {
    "iso:country":"DE",
    "sg:address":"Kurf\u00fcrstenstr. 51",
    "sg:city":"Bocholt",
    "sg:phone":"+49 2871/42874",
    "sg:postcode":"46399",
    "sg:province":"Nordrhein-Westfalen",
    "wof:name":"Carl Schmale",
    "wof:placetype":"venue"
},
  "geometry": {"coordinates":[6.6085557938,51.8407325745],"type":"Point"}
}