{
  "type": "Feature",
  "properties": {
    "iso:country":"DE",
    "sg:address":"Waldfeldweg 3",
    "sg:city":"Althegnenberg",
    "sg:phone":"+49 8202/1270",
    "sg:postcode":"82278",
    "sg:province":"Bayern",
    "wof:name":"Karl Berger Garten- Und Landschafts-",
    "wof:placetype":"venue"
},
  "geometry": {"coordinates":[11.063596,48.233425],"type":"Point"}
}