{
  "type": "Feature",
  "properties": {
    "iso:country":"DE",
    "sg:address":"Prenzlauer Allee 204",
    "sg:city":"Berlin",
    "sg:phone":"+49 30/4416104",
    "sg:postcode":"10405",
    "sg:province":"Berlin",
    "wof:name":"Imbi\u00df Senem Yologlu",
    "wof:placetype":"venue"
},
  "geometry": {"coordinates":[13.4229478836,52.5376663208],"type":"Point"}
}