{
  "type": "Feature",
  "properties": {
    "iso:country":"DE",
    "sg:address":"Bahnhofstr. 22",
    "sg:city":"R\u00fcsselsheim",
    "sg:phone":"+49 6142/965583",
    "sg:postcode":"65428",
    "sg:province":"Hessen",
    "wof:name":"Fielmann Ag & Co.",
    "wof:placetype":"venue"
},
  "geometry": {"coordinates":[8.4145889282,49.9938011169],"type":"Point"}
}