{
  "type": "Feature",
  "properties": {
    "iso:country":"DE",
    "sg:address":"Prinzessinnenstr. 30",
    "sg:city":"Berlin",
    "sg:phone":"+49 30/841820",
    "sg:postcode":"10969",
    "sg:province":"Berlin",
    "wof:name":"F\u00fcrstenau & Partner Ingenieurgesellschaft Mbh",
    "wof:placetype":"venue"
},
  "geometry": {"coordinates":[13.4139671326,52.5015945435],"type":"Point"}
}