{
  "type": "Feature",
  "properties": {
    "iso:country":"DE",
    "sg:address":"Ihmerter Str. 92",
    "sg:city":"Hemer",
    "sg:phone":"+49 2372/8407",
    "sg:postcode":"58675",
    "sg:province":"Nordrhein-Westfalen",
    "wof:name":"Wolf & Co. Gmbh",
    "wof:placetype":"venue"
},
  "geometry": {"coordinates":[7.7470459938,51.3501052856],"type":"Point"}
}