{
  "type": "Feature",
  "properties": {
    "iso:country":"DE",
    "sg:address":"Robert-Bosch-Str. 18",
    "sg:city":"Weil im Sch\u00f6nbuch",
    "sg:phone":"+49 7157/61231",
    "sg:postcode":"71093",
    "sg:province":"Baden-W\u00fcrttemberg",
    "wof:name":"M. Zimmermann",
    "wof:placetype":"venue"
},
  "geometry": {"coordinates":[9.037427,48.621376],"type":"Point"}
}