{
  "type": "Feature",
  "properties": {
    "iso:country":"DE",
    "sg:address":"Hahler Str. 38-40",
    "sg:city":"Minden",
    "sg:phone":"+49 5121/264636",
    "sg:postcode":"32427",
    "sg:province":"Nordrhein-Westfalen",
    "wof:name":"Restaurant Zum Dorfkrug",
    "wof:placetype":"venue"
},
  "geometry": {"coordinates":[8.9067077637,52.2935256958],"type":"Point"}
}