{
  "type": "Feature",
  "properties": {
    "iso:country":"DE",
    "sg:address":"Gr\u00f6bm\u00fchlstr. 18",
    "sg:city":"Dachau",
    "sg:postcode":"85221",
    "sg:province":"Bayern",
    "wof:name":"Adeptus Kft Budapest Zweigniederl. Dachau",
    "wof:placetype":"venue"
},
  "geometry": {"coordinates":[11.441259,48.255348],"type":"Point"}
}