{
  "type": "Feature",
  "properties": {
    "iso:country":"DE",
    "sg:address":"Eisenlohrstr. 23a",
    "sg:city":"Karlsruhe",
    "sg:phone":"+49 721/821220",
    "sg:postcode":"76135",
    "sg:province":"Baden-W\u00fcrttemberg",
    "wof:name":"Elsner & Schichor - Agentur & Verlag F\u00fcr Karten Grafik",
    "wof:placetype":"venue"
},
  "geometry": {"coordinates":[8.374088,49.004318],"type":"Point"}
}