{
  "type": "Feature",
  "properties": {
    "iso:country":"DE",
    "sg:address":"Werkstr. 6",
    "sg:city":"Buggingen",
    "sg:phone":"+49 7631/4300",
    "sg:postcode":"79426",
    "sg:province":"Baden-W\u00fcrttemberg",
    "wof:name":"Impulsiv Freizeitcenter Gmbh",
    "wof:placetype":"venue"
},
  "geometry": {"coordinates":[7.6215400696,47.8566818237],"type":"Point"}
}