{
  "type": "Feature",
  "properties": {
    "iso:country":"DE",
    "sg:address":"L\u00e4mmerspieler Str. 100",
    "sg:city":"M\u00fchlheim",
    "sg:phone":"+49 6108/90070",
    "sg:postcode":"63165",
    "sg:province":"Hessen",
    "wof:name":"August Wesemann Gmbh",
    "wof:placetype":"venue"
},
  "geometry": {"coordinates":[8.8433418274,50.1100654602],"type":"Point"}
}