{
  "type": "Feature",
  "properties": {
    "iso:country":"DE",
    "sg:address":"Kaiserstra\u00dfe 96",
    "sg:city":"Saulgau",
    "sg:phone":"+49 7581",
    "sg:postcode":"88348",
    "sg:province":"Baden-W\u00fcrttemberg",
    "wof:name":"Hauskrankenpflegedienst",
    "wof:placetype":"venue"
},
  "geometry": {"coordinates":[9.504889,48.011639],"type":"Point"}
}