{
  "type": "Feature",
  "properties": {
    "iso:country":"DE",
    "sg:address":"Dorfstr. 64",
    "sg:city":"Warder",
    "sg:phone":"+49 4329/226",
    "sg:postcode":"24646",
    "sg:province":"Schleswig-Holstein",
    "wof:name":"Karin E. Green",
    "wof:placetype":"venue"
},
  "geometry": {"coordinates":[9.886762619,54.2132797241],"type":"Point"}
}