{
  "type": "Feature",
  "properties": {
    "iso:country":"DE",
    "sg:address":"M\u00fcnsterstr. 42",
    "sg:city":"Ahlen",
    "sg:phone":"+49 2528/950550",
    "sg:postcode":"59227",
    "sg:province":"Nordrhein-Westfalen",
    "wof:name":"Karl-heinz Holle Signal Iduna Versicherung",
    "wof:placetype":"venue"
},
  "geometry": {"coordinates":[7.93039608,51.8149642944],"type":"Point"}
}