{
  "type": "Feature",
  "properties": {
    "iso:country":"DE",
    "sg:address":"Deutschhausstr. 32",
    "sg:city":"Marburg",
    "sg:phone":"+49 6421/61061",
    "sg:postcode":"35037",
    "sg:province":"Hessen",
    "wof:name":"Fiedler Und Schl\u00fcter-oelkers Rechtsanw\u00e4lte Und Notar",
    "wof:placetype":"venue"
},
  "geometry": {"coordinates":[8.7752361298,50.8136444092],"type":"Point"}
}