{
  "type": "Feature",
  "properties": {
    "iso:country":"DE",
    "sg:address":"P\u00f6hlauer Str. 46",
    "sg:city":"Zwickau",
    "sg:phone":"+49 375/297299",
    "sg:postcode":"08066",
    "sg:province":"Sachsen",
    "wof:name":"Elco Kl\u00f6ckner Heiztechnik Gmbh",
    "wof:placetype":"venue"
},
  "geometry": {"coordinates":[12.5418071747,50.7169952393],"type":"Point"}
}