{
  "type": "Feature",
  "properties": {
    "iso:country":"DE",
    "sg:address":"Moningerstr. 23",
    "sg:city":"Karlsruhe",
    "sg:postcode":"76135",
    "sg:province":"Baden-W\u00fcrttemberg",
    "wof:name":"Bas Gmbh",
    "wof:placetype":"venue"
},
  "geometry": {"coordinates":[8.3833770752,49.0061149597],"type":"Point"}
}