{
  "type": "Feature",
  "properties": {
    "iso:country":"DE",
    "sg:address":"Kirchstr. 47",
    "sg:city":"Filderstadt",
    "sg:phone":"+49 711/773330",
    "sg:postcode":"70794",
    "sg:province":"Baden-W\u00fcrttemberg",
    "wof:name":"R. Ruck",
    "wof:placetype":"venue"
},
  "geometry": {"coordinates":[9.1944198608,48.6549797058],"type":"Point"}
}