{
  "type": "Feature",
  "properties": {
    "iso:country":"DE",
    "sg:address":"Hauptstr. 34 a",
    "sg:city":"Haste",
    "sg:phone":"+49 5723/81674",
    "sg:postcode":"31559",
    "sg:province":"Niedersachsen",
    "wof:name":"Flora Apotheke",
    "wof:placetype":"venue"
},
  "geometry": {"coordinates":[9.390435,52.379494],"type":"Point"}
}