{
  "type": "Feature",
  "properties": {
    "iso:country":"DE",
    "sg:address":"Hauptstr. 4",
    "sg:city":"Scheer",
    "sg:phone":"+49 7572/2581",
    "sg:postcode":"72516",
    "sg:province":"Baden-W\u00fcrttemberg",
    "wof:name":"E. Schmuker",
    "wof:placetype":"venue"
},
  "geometry": {"coordinates":[9.2945299149,48.0733146667],"type":"Point"}
}