{
  "type": "Feature",
  "properties": {
    "iso:country":"DE",
    "sg:address":"Robert-Bosch-Str 1",
    "sg:city":"Unterm\u00fcnkheim",
    "sg:phone":"+49 7944/941115",
    "sg:postcode":"74547",
    "sg:province":"Baden-W\u00fcrttemberg",
    "wof:name":"Spedition Bakimci & Korkmaz International Transport Logistik Gmbh",
    "wof:placetype":"venue"
},
  "geometry": {"coordinates":[9.7059659958,49.1772575378],"type":"Point"}
}