{
  "type": "Feature",
  "properties": {
    "iso:country":"DE",
    "sg:address":"Master Esch 1",
    "sg:city":"Vreden",
    "sg:phone":"+49 2564/2011",
    "sg:postcode":"48691",
    "sg:province":"Nordrhein-Westfalen",
    "wof:name":"Vredener Lkw-bremsendienst Gmbh",
    "wof:placetype":"venue"
},
  "geometry": {"coordinates":[6.822458,52.029148],"type":"Point"}
}