{
  "type": "Feature",
  "properties": {
    "iso:country":"DE",
    "sg:address":"Klostergang 53",
    "sg:city":"Braunschweig",
    "sg:phone":"+49 531/37020",
    "sg:postcode":"38104",
    "sg:province":"Niedersachsen",
    "wof:name":"Mmi Marketing Management Institut Gmbh",
    "wof:placetype":"venue"
},
  "geometry": {"coordinates":[10.5757598877,52.267364502],"type":"Point"}
}