{
  "type": "Feature",
  "properties": {
    "iso:country":"DE",
    "sg:address":"Waldbrunn",
    "sg:city":"Waldbrunn",
    "sg:phone":"+49 6274/430",
    "sg:postcode":"69429",
    "sg:province":"Baden-W\u00fcrttemberg",
    "wof:name":"Volksbank Eberbach Eg",
    "wof:placetype":"venue"
},
  "geometry": {"coordinates":[9.0747,49.457008],"type":"Point"}
}