{
  "type": "Feature",
  "properties": {
    "iso:country":"DE",
    "sg:address":"Leierndorfer Str. 33",
    "sg:city":"Langquaid",
    "sg:phone":"+49 9452/345",
    "sg:postcode":"84085",
    "sg:province":"Bayern",
    "wof:name":"Manfred Schmid",
    "wof:placetype":"venue"
},
  "geometry": {"coordinates":[12.0559883118,48.8244781494],"type":"Point"}
}