{
  "type": "Feature",
  "properties": {
    "iso:country":"DE",
    "sg:address":"Mathildenstr. 3",
    "sg:city":"Brandis",
    "sg:postcode":"04821",
    "sg:province":"Sachsen",
    "wof:name":"Bauservice Siegmund Gmbh",
    "wof:placetype":"venue"
},
  "geometry": {"coordinates":[12.609643,51.335751],"type":"Point"}
}