{
  "type": "Feature",
  "properties": {
    "iso:country":"DE",
    "sg:address":"Anderter Str. 55",
    "sg:city":"Hannover",
    "sg:phone":"+49 511/580246",
    "sg:postcode":"30629",
    "sg:province":"Niedersachsen",
    "wof:name":"Horst Sander",
    "wof:placetype":"venue"
},
  "geometry": {"coordinates":[9.864207,52.377468],"type":"Point"}
}