{
  "type": "Feature",
  "properties": {
    "iso:country":"DE",
    "sg:address":"Wittelstr. 40",
    "sg:city":"Bad Oeynhausen",
    "sg:phone":"+49 5731/91753",
    "sg:postcode":"32545",
    "sg:province":"Nordrhein-Westfalen",
    "wof:name":"Udo Anton",
    "wof:placetype":"venue"
},
  "geometry": {"coordinates":[8.820081,52.181969],"type":"Point"}
}