{
  "type": "Feature",
  "properties": {
    "iso:country":"DE",
    "sg:address":"Heinrich-Fourier-Str. 2",
    "sg:city":"Gie\u00dfen",
    "sg:phone":"+49 641/492300",
    "sg:postcode":"35394",
    "sg:province":"Hessen",
    "wof:name":"Penny Gmbh",
    "wof:placetype":"venue"
},
  "geometry": {"coordinates":[8.6995306015,50.5806694031],"type":"Point"}
}