{
  "type": "Feature",
  "properties": {
    "iso:country":"DE",
    "sg:address":"Robert-Koch-Str. 3",
    "sg:city":"Unterhaching",
    "sg:phone":"+49 89/6115005",
    "sg:postcode":"82008",
    "sg:province":"Bayern",
    "wof:name":"Micro-optik Gmbh",
    "wof:placetype":"venue"
},
  "geometry": {"coordinates":[11.6047725677,48.0675086975],"type":"Point"}
}