{
  "type": "Feature",
  "properties": {
    "iso:country":"DE",
    "sg:address":"Kelsterbacher Str. 32a",
    "sg:city":"Hattersheim",
    "sg:phone":"+49 6145/30657",
    "sg:postcode":"65795",
    "sg:province":"Hessen",
    "wof:name":"Michael S\u00f6ngen",
    "wof:placetype":"venue"
},
  "geometry": {"coordinates":[8.4720783234,50.0423316956],"type":"Point"}
}