{
  "type": "Feature",
  "properties": {
    "iso:country":"DE",
    "sg:address":"Weingasse 7",
    "sg:city":"Freiberg",
    "sg:phone":"+49 3731/23732",
    "sg:postcode":"09599",
    "sg:province":"Sachsen",
    "wof:name":"Siegfried Lein",
    "wof:placetype":"venue"
},
  "geometry": {"coordinates":[13.343645,50.918217],"type":"Point"}
}