{
  "type": "Feature",
  "properties": {
    "iso:country":"DE",
    "sg:address":"Im Holte 8",
    "sg:city":"Gevelsberg",
    "sg:postcode":"58285",
    "sg:province":"Nordrhein-Westfalen",
    "wof:name":"G-web Webdesign Gmbh",
    "wof:placetype":"venue"
},
  "geometry": {"coordinates":[7.3231139183,51.3131332397],"type":"Point"}
}