{
  "type": "Feature",
  "properties": {
    "iso:country":"DE",
    "sg:address":"Wilhelm-R\u00f6ntgen-Str. 2",
    "sg:city":"Bremen",
    "sg:phone":"+49 421/2576111",
    "sg:postcode":"28357",
    "sg:province":"Bremen",
    "wof:name":"Emsikey Trendwear Ohg",
    "wof:placetype":"venue"
},
  "geometry": {"coordinates":[8.885799,53.099957],"type":"Point"}
}