{
  "type": "Feature",
  "properties": {
    "iso:country":"DE",
    "sg:address":"Sauerbruchstr. 19",
    "sg:city":"Moers",
    "sg:phone":"+49 2841/66242",
    "sg:postcode":"47447",
    "sg:province":"Nordrhein-Westfalen",
    "wof:name":"Ncm Neuro Care Mobil Gmbh",
    "wof:placetype":"venue"
},
  "geometry": {"coordinates":[6.5973272324,51.423286438],"type":"Point"}
}