{
  "type": "Feature",
  "properties": {
    "iso:country":"DE",
    "sg:address":"Lindenstr. 55",
    "sg:city":"Prettin",
    "sg:phone":"+49 35386/22691",
    "sg:postcode":"06922",
    "sg:province":"Sachsen-Anhalt",
    "wof:name":"Elke Heinisch",
    "wof:placetype":"venue"
},
  "geometry": {"coordinates":[12.929271,51.662788],"type":"Point"}
}