{
  "type": "Feature",
  "properties": {
    "iso:country":"DE",
    "sg:address":"Walder Kirchplatz 20 a",
    "sg:city":"Solingen",
    "sg:phone":"+49 212/318341",
    "sg:postcode":"42719",
    "sg:province":"Nordrhein-Westfalen",
    "wof:name":"E. Jacobi",
    "wof:placetype":"venue"
},
  "geometry": {"coordinates":[7.0413041115,51.1834754944],"type":"Point"}
}