{
  "type": "Feature",
  "properties": {
    "iso:country":"DE",
    "sg:address":"Dorfstr. 20",
    "sg:city":"Stedesand",
    "sg:phone":"+49 4662/2307",
    "sg:postcode":"25920",
    "sg:province":"Schleswig-Holstein",
    "wof:name":"P. Nissen",
    "wof:placetype":"venue"
},
  "geometry": {"coordinates":[8.925546,54.738243],"type":"Point"}
}