{
  "type": "Feature",
  "properties": {
    "iso:country":"DE",
    "sg:address":"Bahnhofstr. 65",
    "sg:city":"Wiesbaden",
    "sg:phone":"+49 611/372001",
    "sg:postcode":"65185",
    "sg:province":"Hessen",
    "wof:name":"Central-hotel Inh. Anneliese J\u00fcr\u00df",
    "wof:placetype":"venue"
},
  "geometry": {"coordinates":[8.2427406311,50.0734062195],"type":"Point"}
}