{
  "type": "Feature",
  "properties": {
    "iso:country":"DE",
    "sg:address":"Ernst-Th\u00e4lmann-Str. 8",
    "sg:city":"B\u00f6rnicke",
    "sg:postcode":"16321",
    "sg:province":"Brandenburg",
    "wof:name":"Sigrid Rzeczinski",
    "wof:placetype":"venue"
},
  "geometry": {"coordinates":[13.635744,52.6618],"type":"Point"}
}