{
  "type": "Feature",
  "properties": {
    "iso:country":"DE",
    "sg:address":"Hardtstr. 32",
    "sg:city":"Karlsruhe",
    "sg:phone":"+49 721/550080",
    "sg:postcode":"76185",
    "sg:province":"Baden-W\u00fcrttemberg",
    "wof:name":"Chinarestaurant Jumbo",
    "wof:placetype":"venue"
},
  "geometry": {"coordinates":[8.3568935394,49.0112571716],"type":"Point"}
}