{
  "type": "Feature",
  "properties": {
    "iso:country":"DE",
    "sg:address":"Heidesheimer Str. 49",
    "sg:city":"Mainz",
    "sg:phone":"+49 6131/949490",
    "sg:postcode":"55124",
    "sg:province":"Rheinland-Pfalz",
    "wof:name":"Intercom Management Gmbh",
    "wof:placetype":"venue"
},
  "geometry": {"coordinates":[8.197174,50.001945],"type":"Point"}
}