{
  "type": "Feature",
  "properties": {
    "iso:country":"DE",
    "sg:address":"Frankfurter Str. 19",
    "sg:city":"Eisdorf",
    "sg:phone":"+49 5522/82726",
    "sg:postcode":"37534",
    "sg:province":"Niedersachsen",
    "wof:name":"Ernst-august Niehus",
    "wof:placetype":"venue"
},
  "geometry": {"coordinates":[10.175972,51.759029],"type":"Point"}
}