{
  "type": "Feature",
  "properties": {
    "iso:country":"DE",
    "sg:address":"Steinweg 7a",
    "sg:city":"Walkenried",
    "sg:phone":"+49 5525/761",
    "sg:postcode":"37445",
    "sg:province":"Niedersachsen",
    "wof:name":"Gemeindeb\u00fccherei H. Schlegel",
    "wof:placetype":"venue"
},
  "geometry": {"coordinates":[10.618479,51.582584],"type":"Point"}
}