{
  "type": "Feature",
  "properties": {
    "iso:country":"DE",
    "sg:address":"Hussitenstr. 5",
    "sg:city":"G\u00f6rlitz",
    "sg:phone":"+49 3581/314665",
    "sg:postcode":"02828",
    "sg:province":"Sachsen",
    "wof:name":"Walter Schultze",
    "wof:placetype":"venue"
},
  "geometry": {"coordinates":[14.9731845856,51.1676712036],"type":"Point"}
}