{
  "type": "Feature",
  "properties": {
    "iso:country":"DE",
    "sg:address":"Dorfstr. 21",
    "sg:city":"Offingen",
    "sg:phone":"+49 8224/90801",
    "sg:postcode":"89362",
    "sg:province":"Bayern",
    "wof:name":"F. Schmid",
    "wof:placetype":"venue"
},
  "geometry": {"coordinates":[10.393055,48.479511],"type":"Point"}
}