{
  "type": "Feature",
  "properties": {
    "iso:country":"DE",
    "sg:address":"Klinggraben 3",
    "sg:city":"Haldensleben",
    "sg:phone":"+49 3904/43940",
    "sg:postcode":"39340",
    "sg:province":"Sachsen-Anhalt",
    "wof:name":"B. Brunke",
    "wof:placetype":"venue"
},
  "geometry": {"coordinates":[11.4021139145,52.2848434448],"type":"Point"}
}