{
  "type": "Feature",
  "properties": {
    "iso:country":"DE",
    "sg:address":"Kinrode 2",
    "sg:city":"Borgentreich",
    "sg:phone":"+49 5645/262",
    "sg:postcode":"34434",
    "sg:province":"Nordrhein-Westfalen",
    "wof:name":"Knipping Bauelemente Gmbh",
    "wof:placetype":"venue"
},
  "geometry": {"coordinates":[9.2543992996,51.6255340576],"type":"Point"}
}