{
  "type": "Feature",
  "properties": {
    "iso:country":"DE",
    "sg:address":"Weiherstr. 1",
    "sg:city":"Mandelbachtal",
    "sg:phone":"+49 6803/1627",
    "sg:postcode":"66399",
    "sg:province":"Saarland",
    "wof:name":"Mayer & Schweig Gmbh",
    "wof:placetype":"venue"
},
  "geometry": {"coordinates":[7.1834,49.19495],"type":"Point"}
}