{
  "type": "Feature",
  "properties": {
    "iso:country":"DE",
    "sg:address":"Neubrandenburger Str. 18",
    "sg:city":"Kessin",
    "sg:phone":"+49 381/4900396",
    "sg:postcode":"18196",
    "sg:province":"Mecklenburg-Vorpommern",
    "wof:name":"Jens W\u00f6ltje",
    "wof:placetype":"venue"
},
  "geometry": {"coordinates":[12.182829,54.060535],"type":"Point"}
}