{
  "type": "Feature",
  "properties": {
    "iso:country":"DE",
    "sg:address":"Sieboldstr. 4",
    "sg:city":"M\u00fcnchen",
    "sg:phone":"+49 89/48004330",
    "sg:postcode":"81669",
    "sg:province":"Bayern",
    "wof:name":"Tsv Ost",
    "wof:placetype":"venue"
},
  "geometry": {"coordinates":[11.5925960541,48.1248779297],"type":"Point"}
}