{
  "type": "Feature",
  "properties": {
    "iso:country":"DE",
    "sg:address":"Am Kunstfeld 21 d",
    "sg:city":"K\u00f6ln",
    "sg:postcode":"51069",
    "sg:province":"Nordrhein-Westfalen",
    "wof:name":"Optipharm Gmbh",
    "wof:placetype":"venue"
},
  "geometry": {"coordinates":[7.0358071327,51.0090675354],"type":"Point"}
}