{
  "type": "Feature",
  "properties": {
    "iso:country":"DE",
    "sg:address":"Fabrikstra\u00dfe 8",
    "sg:city":"M\u00fchlau",
    "sg:phone":"+49 3722/96911",
    "sg:postcode":"09241",
    "sg:province":"Sachsen",
    "wof:name":"Malerbetrieb Kirchh\u00fcbel",
    "wof:placetype":"venue"
},
  "geometry": {"coordinates":[12.760701,50.89629],"type":"Point"}
}