{
  "type": "Feature",
  "properties": {
    "iso:country":"DE",
    "sg:address":"Im Kappelfeld 15",
    "sg:city":"Stuttgart",
    "sg:postcode":"70469",
    "sg:province":"Baden-W\u00fcrttemberg",
    "wof:name":"Holzwarth - Ingenieurb\u00fcro F\u00fcr Bauwesen Gmbh",
    "wof:placetype":"venue"
},
  "geometry": {"coordinates":[9.1521453857,48.8103637695],"type":"Point"}
}