{
  "type": "Feature",
  "properties": {
    "iso:country":"DE",
    "sg:address":"S\u00fcrther Hauptstr. 73",
    "sg:city":"K\u00f6ln",
    "sg:postcode":"50999",
    "sg:province":"Nordrhein-Westfalen",
    "wof:name":"Wincom Gmbh",
    "wof:placetype":"venue"
},
  "geometry": {"coordinates":[7.0083050728,50.8626289368],"type":"Point"}
}