{
  "type": "Feature",
  "properties": {
    "iso:country":"DE",
    "sg:address":"Oststr. 86",
    "sg:city":"Norderstedt",
    "sg:phone":"+49 40/5222865",
    "sg:postcode":"22844",
    "sg:province":"Schleswig-Holstein",
    "wof:name":"Sede",
    "wof:placetype":"venue"
},
  "geometry": {"coordinates":[10.0229578018,53.7327690125],"type":"Point"}
}