{
  "type": "Feature",
  "properties": {
    "iso:country":"DE",
    "sg:address":"Zum Ahrenberg 20",
    "sg:city":"Nack",
    "sg:phone":"+49 6736/8043",
    "sg:postcode":"55234",
    "sg:province":"Rheinland-Pfalz",
    "wof:name":"Albert Vogt",
    "wof:placetype":"venue"
},
  "geometry": {"coordinates":[7.999385,49.747555],"type":"Point"}
}