{
  "type": "Feature",
  "properties": {
    "iso:country":"DE",
    "sg:address":"Hauptstr. 66",
    "sg:city":"Pockau",
    "sg:postcode":"09509",
    "sg:province":"Sachsen",
    "wof:name":"Agrargenossenschaft Eg",
    "wof:placetype":"venue"
},
  "geometry": {"coordinates":[13.27102,50.731709],"type":"Point"}
}