{
  "type": "Feature",
  "properties": {
    "iso:country":"DE",
    "sg:address":"Steinweg 2",
    "sg:city":"Marienhagen",
    "sg:phone":"+49 5185/1267",
    "sg:postcode":"31094",
    "sg:province":"Niedersachsen",
    "wof:name":"F. Habenicht",
    "wof:placetype":"venue"
},
  "geometry": {"coordinates":[9.6895914078,52.0385475159],"type":"Point"}
}