{
  "type": "Feature",
  "properties": {
    "iso:country":"DE",
    "sg:address":"Hachener Str. 136",
    "sg:city":"Sundern",
    "sg:phone":"+49 2935/318",
    "sg:postcode":"59846",
    "sg:province":"Nordrhein-Westfalen",
    "wof:name":"Willi Feldmann",
    "wof:placetype":"venue"
},
  "geometry": {"coordinates":[7.980596,51.371185],"type":"Point"}
}