{
  "type": "Feature",
  "properties": {
    "iso:country":"DE",
    "sg:address":"Asbacher Weg 23",
    "sg:city":"K\u00f6ln",
    "sg:phone":"+49 221/799987",
    "sg:postcode":"50767",
    "sg:province":"Nordrhein-Westfalen",
    "wof:name":"Theo Hermanns Ingenieur",
    "wof:placetype":"venue"
},
  "geometry": {"coordinates":[6.9037971497,51.0058822632],"type":"Point"}
}