{
  "type": "Feature",
  "properties": {
    "iso:country":"DE",
    "sg:address":"Hahner Hofstr. 21",
    "sg:city":"M\u00f6nchengladbach",
    "sg:phone":"+49 2166/58889",
    "sg:postcode":"41189",
    "sg:province":"Nordrhein-Westfalen",
    "wof:name":"Ulrich Illgner Gmbh Industrievertretungen",
    "wof:placetype":"venue"
},
  "geometry": {"coordinates":[6.3883562088,51.121963501],"type":"Point"}
}