{
  "type": "Feature",
  "properties": {
    "iso:country":"DE",
    "sg:address":"Heckenkamp 7",
    "sg:city":"H\u00fcnxe",
    "sg:phone":"+49 2858/2636",
    "sg:postcode":"46569",
    "sg:province":"Nordrhein-Westfalen",
    "wof:name":"Hans Weis",
    "wof:placetype":"venue"
},
  "geometry": {"coordinates":[6.7430968285,51.6601257324],"type":"Point"}
}