{
  "type": "Feature",
  "properties": {
    "iso:country":"DE",
    "sg:address":"Veldener Str. 14",
    "sg:city":"M\u00fcnchen",
    "sg:phone":"+49 89/583474",
    "sg:postcode":"80687",
    "sg:province":"Bayern",
    "wof:name":"Andreas Huber Rechtsanwalt",
    "wof:placetype":"venue"
},
  "geometry": {"coordinates":[11.4865903854,48.14427948],"type":"Point"}
}