{
  "type": "Feature",
  "properties": {
    "iso:country":"DE",
    "sg:address":"Karlstr. 76",
    "sg:city":"D\u00fcsseldorf",
    "sg:phone":"+49 211/1354518",
    "sg:postcode":"40210",
    "sg:province":"Nordrhein-Westfalen",
    "wof:name":"Hung Gmbh",
    "wof:placetype":"venue"
},
  "geometry": {"coordinates":[6.791176796,51.221824646],"type":"Point"}
}