{
  "type": "Feature",
  "properties": {
    "iso:country":"DE",
    "sg:address":"Auf dem End 2",
    "sg:city":"Petershagen",
    "sg:phone":"+49 5726/618",
    "sg:postcode":"32469",
    "sg:province":"Nordrhein-Westfalen",
    "wof:name":"Landwirtschaftlicher Orts- Verein Raderhorst",
    "wof:placetype":"venue"
},
  "geometry": {"coordinates":[9.0858039856,52.3698272705],"type":"Point"}
}