{
  "type": "Feature",
  "properties": {
    "iso:country":"DE",
    "sg:address":"Stettiner Weg 18",
    "sg:city":"H\u00fcrth",
    "sg:phone":"+49 2233/76973",
    "sg:postcode":"50354",
    "sg:province":"Nordrhein-Westfalen",
    "wof:name":"August-wilhelm Hensel Rechtsanwalt",
    "wof:placetype":"venue"
},
  "geometry": {"coordinates":[6.8760690689,50.8836631775],"type":"Point"}
}