{
  "type": "Feature",
  "properties": {
    "iso:country":"DE",
    "sg:address":"Greutstr. 50",
    "sg:city":"Ulm",
    "sg:phone":"+49 7346/2507",
    "sg:postcode":"89079",
    "sg:province":"Baden-W\u00fcrttemberg",
    "wof:name":"Vereinsgastst\u00e4tte Sportclub Unterweiler E. V.",
    "wof:placetype":"venue"
},
  "geometry": {"coordinates":[9.9625253677,48.3267097473],"type":"Point"}
}