{
  "type": "Feature",
  "properties": {
    "iso:country":"DE",
    "sg:address":"Neuwaldburg 10",
    "sg:city":"Waldburg",
    "sg:phone":"+49 751/66411",
    "sg:postcode":"88289",
    "sg:province":"Baden-W\u00fcrttemberg",
    "wof:name":"Markus Barner Anlageberater",
    "wof:placetype":"venue"
},
  "geometry": {"coordinates":[9.7263069153,47.7699508667],"type":"Point"}
}