{
  "type": "Feature",
  "properties": {
    "iso:country":"DE",
    "sg:address":"K\u00f6nigslachener Weg 18",
    "sg:city":"Schrobenhausen",
    "sg:phone":"+49 8252/89990",
    "sg:postcode":"86529",
    "sg:province":"Bayern",
    "wof:name":"Circuit Chemical Products Gmbh",
    "wof:placetype":"venue"
},
  "geometry": {"coordinates":[11.270735,48.575253],"type":"Point"}
}