{
  "type": "Feature",
  "properties": {
    "iso:country":"DE",
    "sg:address":"Hafenkopfstr. 7",
    "sg:city":"Aschaffenburg",
    "sg:phone":"+49 6021/80199",
    "sg:postcode":"63741",
    "sg:province":"Bayern",
    "wof:name":"Elvira Westarp Gmbh",
    "wof:placetype":"venue"
},
  "geometry": {"coordinates":[9.10809,49.967815],"type":"Point"}
}