{
  "type": "Feature",
  "properties": {
    "iso:country":"DE",
    "sg:address":"Oerdinghauser Str. 16",
    "sg:city":"Engeln",
    "sg:phone":"+49 4247/410",
    "sg:postcode":"27305",
    "sg:province":"Niedersachsen",
    "wof:name":"Hermann Rehmstedt",
    "wof:placetype":"venue"
},
  "geometry": {"coordinates":[8.927842,52.780365],"type":"Point"}
}