{
  "type": "Feature",
  "properties": {
    "iso:country":"DE",
    "sg:address":"Kr\u00f6gerweg 33-47",
    "sg:city":"M\u00fcnster",
    "sg:phone":"+49 251/627410",
    "sg:postcode":"48155",
    "sg:province":"Nordrhein-Westfalen",
    "wof:name":"Kr\u00fcger Gmbh & Co. Kg",
    "wof:placetype":"venue"
},
  "geometry": {"coordinates":[7.6596469879,51.9227523804],"type":"Point"}
}