{
  "type": "Feature",
  "properties": {
    "iso:country":"DE",
    "sg:address":"Ohlenfeldstr. 1",
    "sg:city":"Boppard",
    "sg:postcode":"56154",
    "sg:province":"Rheinland-Pfalz",
    "wof:name":"Rt Tennisanlagen-verpachtung- Und Verwaltungs-gmbh",
    "wof:placetype":"venue"
},
  "geometry": {"coordinates":[7.539433,50.214504],"type":"Point"}
}