{
  "type": "Feature",
  "properties": {
    "iso:country":"DE",
    "sg:address":"Brandst\u00fccken 44",
    "sg:city":"Hamburg",
    "sg:phone":"+49 40/802002",
    "sg:postcode":"22549",
    "sg:province":"Hamburg",
    "wof:name":"Georg Clasen & Co. Tischlereibetrieb",
    "wof:placetype":"venue"
},
  "geometry": {"coordinates":[9.853632,53.582321],"type":"Point"}
}