{
  "type": "Feature",
  "properties": {
    "iso:country":"DE",
    "sg:address":"Beethovenring 59",
    "sg:city":"Seeheim-Jugenheim",
    "sg:phone":"+49 6257",
    "sg:postcode":"64342",
    "sg:province":"Hessen",
    "wof:name":"Rechtsanwaltskanzlei Reinheimer Und G\u00f6ttmann",
    "wof:placetype":"venue"
},
  "geometry": {"coordinates":[8.642257,49.768665],"type":"Point"}
}