{
  "type": "Feature",
  "properties": {
    "iso:country":"DE",
    "sg:address":"K\u00fcferstr. 12 b",
    "sg:city":"Hamm",
    "sg:postcode":"59067",
    "sg:province":"Nordrhein-Westfalen",
    "wof:name":"Lang Bau Gmbh",
    "wof:placetype":"venue"
},
  "geometry": {"coordinates":[7.7592759132,51.6673164368],"type":"Point"}
}