{
  "type": "Feature",
  "properties": {
    "iso:country":"DE",
    "sg:address":"Sch\u00fctzenstr. 8",
    "sg:city":"Bad Aibling",
    "sg:phone":"+49 8061/3139",
    "sg:postcode":"83043",
    "sg:province":"Bayern",
    "wof:name":"Thomas Schreiner",
    "wof:placetype":"venue"
},
  "geometry": {"coordinates":[12.00818,47.866211],"type":"Point"}
}