{
  "type": "Feature",
  "properties": {
    "iso:country":"DE",
    "sg:address":"Markgrafenstr. 6a",
    "sg:city":"Rheinstetten",
    "sg:phone":"+49 7242/93790",
    "sg:postcode":"76287",
    "sg:province":"Baden-W\u00fcrttemberg",
    "wof:name":"Wagus Gmbh",
    "wof:placetype":"venue"
},
  "geometry": {"coordinates":[8.2664289474,48.9701843262],"type":"Point"}
}