{
  "type": "Feature",
  "properties": {
    "iso:country":"DE",
    "sg:address":"Beckersbergstr. 82",
    "sg:city":"Henstedt-Ulzburg",
    "sg:phone":"+49 4193/97711",
    "sg:postcode":"24558",
    "sg:province":"Schleswig-Holstein",
    "wof:name":"T. Lubomirsky",
    "wof:placetype":"venue"
},
  "geometry": {"coordinates":[9.9965400696,53.7925491333],"type":"Point"}
}