{
  "type": "Feature",
  "properties": {
    "iso:country":"DE",
    "sg:address":"Nymphenburger Str. 49",
    "sg:city":"M\u00fcnchen",
    "sg:phone":"+49 89/186434",
    "sg:postcode":"80335",
    "sg:province":"Bayern",
    "wof:name":"Michael Otto Kameramann",
    "wof:placetype":"venue"
},
  "geometry": {"coordinates":[11.5494222641,48.1491317749],"type":"Point"}
}