{
  "type": "Feature",
  "properties": {
    "iso:country":"DE",
    "sg:address":"Detmolder Str. 67",
    "sg:city":"Berlin",
    "sg:phone":"+49 30/8533540",
    "sg:postcode":"10715",
    "sg:province":"Berlin",
    "wof:name":"Hans-joachim Zenk Steuerberater",
    "wof:placetype":"venue"
},
  "geometry": {"coordinates":[13.3269844055,52.4785499573],"type":"Point"}
}