{
  "type": "Feature",
  "properties": {
    "iso:country":"DE",
    "sg:address":"Breite Str. 36",
    "sg:city":"Sehnde",
    "sg:phone":"+49 5138/61960",
    "sg:postcode":"31319",
    "sg:province":"Niedersachsen",
    "wof:name":"Hotel Feicht",
    "wof:placetype":"venue"
},
  "geometry": {"coordinates":[9.9667682648,52.3122406006],"type":"Point"}
}