{
  "type": "Feature",
  "properties": {
    "iso:country":"DE",
    "sg:address":"Ehretstra\u00dfe 3",
    "sg:city":"Weinheim",
    "sg:phone":"+49 6201",
    "sg:postcode":"69469",
    "sg:province":"Baden-W\u00fcrttemberg",
    "wof:name":"Juventa-verlag",
    "wof:placetype":"venue"
},
  "geometry": {"coordinates":[8.670091,49.550278],"type":"Point"}
}