{
  "type": "Feature",
  "properties": {
    "iso:country":"DE",
    "sg:address":"Schwabstr. 80",
    "sg:city":"Marbach",
    "sg:phone":"+49 7144/13469",
    "sg:postcode":"71672",
    "sg:province":"Baden-W\u00fcrttemberg",
    "wof:name":"Georg Reibling",
    "wof:placetype":"venue"
},
  "geometry": {"coordinates":[9.273907,48.941441],"type":"Point"}
}