{
  "type": "Feature",
  "properties": {
    "iso:country":"DE",
    "sg:address":"Reeperbahn 121",
    "sg:city":"Hamburg",
    "sg:phone":"+49 40/314678",
    "sg:postcode":"20359",
    "sg:province":"Hamburg",
    "wof:name":"J\u00fcrgen Wilms Inh. Renate Wilms",
    "wof:placetype":"venue"
},
  "geometry": {"coordinates":[9.9602394104,53.5493164062],"type":"Point"}
}