{
  "type": "Feature",
  "properties": {
    "iso:country":"DE",
    "sg:address":"Adolf-Reichwein-Str. 73",
    "sg:city":"Neu-Anspach",
    "sg:phone":"+49 6081/944706",
    "sg:postcode":"61267",
    "sg:province":"Hessen",
    "wof:name":"Mb Deutschmann Gmbh",
    "wof:placetype":"venue"
},
  "geometry": {"coordinates":[8.5059556961,50.2999191284],"type":"Point"}
}