{
  "type": "Feature",
  "properties": {
    "iso:country":"DE",
    "sg:address":"Kurbrunnenstr. 19",
    "sg:city":"Bad D\u00fcrkheim",
    "sg:phone":"+49 6322/981198",
    "sg:postcode":"67098",
    "sg:province":"Rheinland-Pfalz",
    "wof:name":"Guma Bautr\u00e4ger Gmbh",
    "wof:placetype":"venue"
},
  "geometry": {"coordinates":[8.170207,49.464878],"type":"Point"}
}