{
  "type": "Feature",
  "properties": {
    "iso:country":"DE",
    "sg:address":"Kurze-Geismar-Str. 17",
    "sg:city":"G\u00f6ttingen",
    "sg:phone":"+49 4955/157752",
    "sg:postcode":"37073",
    "sg:province":"Niedersachsen",
    "wof:name":"G\u00dcnter Und Uwe Albrecht",
    "wof:placetype":"venue"
},
  "geometry": {"coordinates":[9.937849,51.531216],"type":"Point"}
}