{
  "type": "Feature",
  "properties": {
    "iso:country":"DE",
    "sg:address":"Zur Brumlage 4a",
    "sg:city":"Vechta",
    "sg:phone":"+49 4447/1281",
    "sg:postcode":"49377",
    "sg:province":"Niedersachsen",
    "wof:name":"B & T Bau Und Technik Glasmontagen Gmbh",
    "wof:placetype":"venue"
},
  "geometry": {"coordinates":[8.243388176,52.775138855],"type":"Point"}
}