{
  "type": "Feature",
  "properties": {
    "iso:country":"DE",
    "sg:address":"F\u00fcllenfeld 1",
    "sg:city":"Kierspe",
    "sg:phone":"+49 2359/4149",
    "sg:postcode":"58566",
    "sg:province":"Nordrhein-Westfalen",
    "wof:name":"Benopol Gmbh",
    "wof:placetype":"venue"
},
  "geometry": {"coordinates":[7.6065239906,51.1261711121],"type":"Point"}
}