{
  "type": "Feature",
  "properties": {
    "iso:country":"DE",
    "sg:address":"Am Woog 11",
    "sg:city":"Nieder-Olm",
    "sg:phone":"+49 6136/5904",
    "sg:postcode":"55268",
    "sg:province":"Rheinland-Pfalz",
    "wof:name":"Interregio Bautr\u00e4ger Gmbh",
    "wof:placetype":"venue"
},
  "geometry": {"coordinates":[8.198857,49.909737],"type":"Point"}
}