{
  "type": "Feature",
  "properties": {
    "iso:country":"DE",
    "sg:address":"Marburger Str. 6",
    "sg:city":"Berlin",
    "sg:phone":"+49 30/2113666",
    "sg:postcode":"10789",
    "sg:province":"Berlin",
    "wof:name":"Russ. Samoware H. Amann",
    "wof:placetype":"venue"
},
  "geometry": {"coordinates":[13.336169,52.502438],"type":"Point"}
}