{
  "type": "Feature",
  "properties": {
    "iso:country":"DE",
    "sg:address":"Frundsbergstr. 46",
    "sg:city":"M\u00fcnchen",
    "sg:phone":"+49 89/164333",
    "sg:postcode":"80634",
    "sg:province":"Bayern",
    "wof:name":"Frundsberg",
    "wof:placetype":"venue"
},
  "geometry": {"coordinates":[11.5345811844,48.1573600769],"type":"Point"}
}