{
  "type": "Feature",
  "properties": {
    "iso:country":"DE",
    "sg:address":"Thedinghauser Str.",
    "sg:city":"Pratau",
    "sg:postcode":"06888",
    "sg:province":"Sachsen-Anhalt",
    "wof:name":"Pretzsch Bau Gmbh",
    "wof:placetype":"venue"
},
  "geometry": {"coordinates":[-73.35852050779999,41.1414985657],"type":"Point"}
}