{
  "type": "Feature",
  "properties": {
    "iso:country":"DE",
    "sg:address":"Altenhagener Str. 9",
    "sg:city":"Bad Salzuflen",
    "sg:phone":"+49 5208/91290",
    "sg:postcode":"32107",
    "sg:province":"Nordrhein-Westfalen",
    "wof:name":"Safe Pack Sicherheits- Verpackungen Gmbh",
    "wof:placetype":"venue"
},
  "geometry": {"coordinates":[8.669533,52.053921],"type":"Point"}
}