{
  "type": "Feature",
  "properties": {
    "iso:country":"DE",
    "sg:address":"Wellensiek 118",
    "sg:city":"Bielefeld",
    "sg:phone":"+49 521/103443",
    "sg:postcode":"33619",
    "sg:province":"Nordrhein-Westfalen",
    "wof:name":"Dieter Rasmussen",
    "wof:placetype":"venue"
},
  "geometry": {"coordinates":[8.4864587784,52.0384178162],"type":"Point"}
}