{
  "type": "Feature",
  "properties": {
    "iso:country":"DE",
    "sg:address":"Seestr. 20",
    "sg:city":"Diemelsee",
    "sg:phone":"+49 5633/332",
    "sg:postcode":"34519",
    "sg:province":"Hessen",
    "wof:name":"Bernhard Rummel",
    "wof:placetype":"venue"
},
  "geometry": {"coordinates":[8.7312164307,51.3624343872],"type":"Point"}
}