{
  "type": "Feature",
  "properties": {
    "iso:country":"DE",
    "sg:address":"Lerchenstr. 11",
    "sg:city":"Morsbach",
    "sg:phone":"+49 2294/6880",
    "sg:postcode":"51597",
    "sg:province":"Nordrhein-Westfalen",
    "wof:name":"Peter Mack Dachdeckermeister Gmbh",
    "wof:placetype":"venue"
},
  "geometry": {"coordinates":[7.715732,50.869087],"type":"Point"}
}