{
  "type": "Feature",
  "properties": {
    "iso:country":"DE",
    "sg:address":"Schlo\u00dfstr. 10",
    "sg:city":"Calw",
    "sg:phone":"+49 7051/6336",
    "sg:postcode":"75365",
    "sg:province":"Baden-W\u00fcrttemberg",
    "wof:name":"Dietmar Schl\u00e4per",
    "wof:placetype":"venue"
},
  "geometry": {"coordinates":[8.7031364441,48.72448349],"type":"Point"}
}