{
  "type": "Feature",
  "properties": {
    "iso:country":"DE",
    "sg:address":"Hafenstr.",
    "sg:city":"List",
    "sg:postcode":"25992",
    "sg:province":"Schleswig-Holstein",
    "wof:name":"Zum Wikinger",
    "wof:placetype":"venue"
},
  "geometry": {"coordinates":[8.436385,55.017021],"type":"Point"}
}