{
  "type": "Feature",
  "properties": {
    "iso:country":"DE",
    "sg:address":"Jesteburger Str. 42",
    "sg:city":"Asendorf",
    "sg:phone":"+49 4183/3762",
    "sg:postcode":"21271",
    "sg:province":"Niedersachsen",
    "wof:name":"G. Brager",
    "wof:placetype":"venue"
},
  "geometry": {"coordinates":[9.974405,53.295197],"type":"Point"}
}