{
  "type": "Feature",
  "properties": {
    "iso:country":"DE",
    "sg:address":"Bruchheide 6",
    "sg:city":"Bohmte",
    "sg:phone":"+49 5471/1295",
    "sg:postcode":"49163",
    "sg:province":"Niedersachsen",
    "wof:name":"Herbert Benke",
    "wof:placetype":"venue"
},
  "geometry": {"coordinates":[8.307584,52.381687],"type":"Point"}
}