{
  "type": "Feature",
  "properties": {
    "iso:country":"DE",
    "sg:address":"Rheinallee 10",
    "sg:city":"Oestrich-Winkel",
    "sg:phone":"+49 6723/3341",
    "sg:postcode":"65375",
    "sg:province":"Hessen",
    "wof:name":"Molsberger Rheinterrassen",
    "wof:placetype":"venue"
},
  "geometry": {"coordinates":[8.0269947052,50.0024757385],"type":"Point"}
}