{
  "type": "Feature",
  "properties": {
    "iso:country":"DE",
    "sg:address":"Am Anker 4",
    "sg:city":"Meerbusch",
    "sg:phone":"+49 2150/3210",
    "sg:postcode":"40668",
    "sg:province":"Nordrhein-Westfalen",
    "wof:name":"Weinmann Masseur",
    "wof:placetype":"venue"
},
  "geometry": {"coordinates":[6.675346,51.307381],"type":"Point"}
}