{
  "type": "Feature",
  "properties": {
    "iso:country":"DE",
    "sg:address":"Annenstr. 5",
    "sg:city":"Petershagen",
    "sg:phone":"+49 33439/85111",
    "sg:postcode":"15370",
    "sg:province":"Brandenburg",
    "wof:name":"A & S Technigro Brandschutzservice Gmbh",
    "wof:placetype":"venue"
},
  "geometry": {"coordinates":[13.7656908035,52.5181274414],"type":"Point"}
}