{
  "type": "Feature",
  "properties": {
    "iso:country":"DE",
    "sg:address":"Dorfstr. 11 a",
    "sg:city":"Atterwasch",
    "sg:phone":"+49 35692/446",
    "sg:postcode":"03172",
    "sg:province":"Brandenburg",
    "wof:name":"K. Lieske",
    "wof:placetype":"venue"
},
  "geometry": {"coordinates":[14.64193,51.953838],"type":"Point"}
}