{
  "type": "Feature",
  "properties": {
    "iso:country":"DE",
    "sg:address":"Adenauer All. 29",
    "sg:city":"Hamburg",
    "sg:phone":"+49 40/554890",
    "sg:postcode":"20097",
    "sg:province":"Hamburg",
    "wof:name":"Mccs Gmbh",
    "wof:placetype":"venue"
},
  "geometry": {"coordinates":[10.01518,53.55291],"type":"Point"}
}