{
  "type": "Feature",
  "properties": {
    "iso:country":"DE",
    "sg:address":"Josef-Wimmer-Str. 23",
    "sg:city":"J\u00fclich",
    "sg:phone":"+49 2461/2642",
    "sg:postcode":"52428",
    "sg:province":"Nordrhein-Westfalen",
    "wof:name":"Franz-josef Hamacher",
    "wof:placetype":"venue"
},
  "geometry": {"coordinates":[6.352254,50.930222],"type":"Point"}
}