{
  "type": "Feature",
  "properties": {
    "iso:country":"DE",
    "sg:address":"L\u00fcpertzender Str. 104",
    "sg:city":"M\u00f6nchengladbach",
    "sg:phone":"+49 2161/17258",
    "sg:postcode":"41061",
    "sg:province":"Nordrhein-Westfalen",
    "wof:name":"Barber-shop Beer Gmbh",
    "wof:placetype":"venue"
},
  "geometry": {"coordinates":[6.4407711029,51.1923408508],"type":"Point"}
}