{
  "type": "Feature",
  "properties": {
    "iso:country":"DE",
    "sg:address":"R\u00f6merstr. 163",
    "sg:city":"Ulm",
    "sg:phone":"+49 731/35168",
    "sg:postcode":"89077",
    "sg:province":"Baden-W\u00fcrttemberg",
    "wof:name":"Thomas Fischer",
    "wof:placetype":"venue"
},
  "geometry": {"coordinates":[9.9660520554,48.3856468201],"type":"Point"}
}