{
  "type": "Feature",
  "properties": {
    "iso:country":"DE",
    "sg:address":"Chemnitzer Str 40",
    "sg:city":"Gr\u00fcnhainichen",
    "sg:phone":"+49 37294/860",
    "sg:postcode":"09579",
    "sg:province":"Sachsen",
    "wof:name":"Wendt & K\u00fchn Kg",
    "wof:placetype":"venue"
},
  "geometry": {"coordinates":[13.153998,50.768139],"type":"Point"}
}