{
  "type": "Feature",
  "properties": {
    "iso:country":"DE",
    "sg:address":"Hochstiftstr. 26",
    "sg:city":"F\u00fcssen",
    "sg:phone":"+49 8362/921270",
    "sg:postcode":"87629",
    "sg:province":"Bayern",
    "wof:name":"G. Lingenfelder Immobilienmakler",
    "wof:placetype":"venue"
},
  "geometry": {"coordinates":[10.7066707611,47.5747261047],"type":"Point"}
}