{
  "type": "Feature",
  "properties": {
    "iso:country":"DE",
    "sg:address":"Eichendorffstr. 14",
    "sg:city":"Gladenbach",
    "sg:phone":"+49 6462/7697",
    "sg:postcode":"35075",
    "sg:province":"Hessen",
    "wof:name":"Willi Schwambach",
    "wof:placetype":"venue"
},
  "geometry": {"coordinates":[8.5808420181,50.7621841431],"type":"Point"}
}