{
  "type": "Feature",
  "properties": {
    "iso:country":"DE",
    "sg:address":"Hattorfer Str. 2",
    "sg:city":"Lehre",
    "sg:phone":"+49 5308/2304",
    "sg:postcode":"38165",
    "sg:province":"Niedersachsen",
    "wof:name":"K\u00e4the G\u00f6ttler Hebamme",
    "wof:placetype":"venue"
},
  "geometry": {"coordinates":[10.710675,52.357128],"type":"Point"}
}