{
  "type": "Feature",
  "properties": {
    "iso:country":"DE",
    "sg:address":"Schillerstr. 22",
    "sg:city":"Jockgrim",
    "sg:postcode":"76751",
    "sg:province":"Rheinland-Pfalz",
    "wof:name":"Epf Gmbh",
    "wof:placetype":"venue"
},
  "geometry": {"coordinates":[8.277286,49.09267],"type":"Point"}
}