{
  "type": "Feature",
  "properties": {
    "iso:country":"DE",
    "sg:city":"Lauf",
    "sg:phone":"+49 9123",
    "sg:postcode":"91207",
    "sg:province":"Bayern",
    "wof:name":"Martin Barth - Fotoarchive",
    "wof:placetype":"venue"
},
  "geometry": {"coordinates":[11.278816,49.511703],"type":"Point"}
}