{
  "type": "Feature",
  "properties": {
    "iso:country":"DE",
    "sg:address":"Sulzer Str. 16",
    "sg:city":"Pei\u00dfenberg",
    "sg:phone":"+49 8803/5658",
    "sg:postcode":"82380",
    "sg:province":"Bayern",
    "wof:name":"Achm\u00fcller Gmbh",
    "wof:placetype":"venue"
},
  "geometry": {"coordinates":[11.058236,47.799301],"type":"Point"}
}