{
  "type": "Feature",
  "properties": {
    "iso:country":"DE",
    "sg:address":"Hoffeldstr. 126",
    "sg:city":"Hilden",
    "sg:phone":"+49 2103/43784",
    "sg:postcode":"40721",
    "sg:province":"Nordrhein-Westfalen",
    "wof:name":"Peter Geppert",
    "wof:placetype":"venue"
},
  "geometry": {"coordinates":[6.937194,51.175137],"type":"Point"}
}