{
  "type": "Feature",
  "properties": {
    "iso:country":"DE",
    "sg:address":"Wiesenweg 6",
    "sg:city":"Bilshausen",
    "sg:phone":"+49 5528/716",
    "sg:postcode":"37434",
    "sg:province":"Niedersachsen",
    "wof:name":"Andreas W\u00fcstefeld Thomas W\u00fcstefeld E. K.",
    "wof:placetype":"venue"
},
  "geometry": {"coordinates":[10.1551847458,51.6332206726],"type":"Point"}
}