{
  "type": "Feature",
  "properties": {
    "iso:country":"DE",
    "sg:address":"Wakendorfer Str. 2",
    "sg:city":"Kisdorf",
    "sg:phone":"+49 4194/7182",
    "sg:postcode":"24629",
    "sg:province":"Schleswig-Holstein",
    "wof:name":"Ole Grimm & Walter Grimm Gas- Wasser-dach-und Bau-",
    "wof:placetype":"venue"
},
  "geometry": {"coordinates":[10.080987,53.811352],"type":"Point"}
}