{
  "type": "Feature",
  "properties": {
    "iso:country":"DE",
    "sg:address":"Interpark",
    "sg:city":"Offenbach",
    "sg:postcode":"76877",
    "sg:province":"Rheinland-Pfalz",
    "wof:name":"M. A. C. Maschinen Und Anlagen Componenten Gmbh",
    "wof:placetype":"venue"
},
  "geometry": {"coordinates":[8.205899,49.198708],"type":"Point"}
}