{
  "type": "Feature",
  "properties": {
    "iso:country":"DE",
    "sg:address":"Am Ems-Vechte-Kanal 3",
    "sg:city":"Nordhorn",
    "sg:phone":"+49 5921/34965",
    "sg:postcode":"48531",
    "sg:province":"Niedersachsen",
    "wof:name":"Bernhard Rammelkamp Architekt",
    "wof:placetype":"venue"
},
  "geometry": {"coordinates":[7.07927,52.44104],"type":"Point"}
}