{
  "type": "Feature",
  "properties": {
    "iso:country":"DE",
    "sg:address":"Dorfstr. 1",
    "sg:city":"Ralbitz-Rosenthal",
    "sg:phone":"+49 35796/96211",
    "sg:postcode":"01920",
    "sg:province":"Sachsen",
    "wof:name":"Luzica Milch- Und Rindfleisch Gmbh",
    "wof:placetype":"venue"
},
  "geometry": {"coordinates":[14.2381057739,51.32056427],"type":"Point"}
}