{
  "type": "Feature",
  "properties": {
    "iso:country":"DE",
    "sg:address":"Dammstr. 42",
    "sg:city":"Hildesheim",
    "sg:phone":"+49 5121/14533",
    "sg:postcode":"31134",
    "sg:province":"Niedersachsen",
    "wof:name":"Restaurant Adriatik",
    "wof:placetype":"venue"
},
  "geometry": {"coordinates":[9.9399909973,52.1494483948],"type":"Point"}
}