{
  "type": "Feature",
  "properties": {
    "iso:country":"DE",
    "sg:address":"Emil-Hartmann-Str. 10",
    "sg:city":"Rudolstadt",
    "sg:phone":"+49 3672/353180",
    "sg:postcode":"07407",
    "sg:province":"Th\u00fcringen",
    "wof:name":"Sch\u00f6ler & Sohn",
    "wof:placetype":"venue"
},
  "geometry": {"coordinates":[11.311454,50.684147],"type":"Point"}
}