{
  "type": "Feature",
  "properties": {
    "iso:country":"DE",
    "sg:address":"Handelshof 32 Seckenhausen",
    "sg:city":"Stuhr",
    "sg:phone":"+49 4942/189920",
    "sg:postcode":"28816",
    "sg:province":"Niedersachsen",
    "wof:name":"Lerbs Gmbh & Co Kg",
    "wof:placetype":"venue"
},
  "geometry": {"coordinates":[8.75292,53.02763],"type":"Point"}
}