{
  "type": "Feature",
  "properties": {
    "iso:country":"DE",
    "sg:address":"Rochow 1 1/2",
    "sg:city":"Ueckerm\u00fcnde",
    "sg:postcode":"17373",
    "sg:province":"Mecklenburg-Vorpommern",
    "wof:name":"Siegfried Georg Schmeil",
    "wof:placetype":"venue"
},
  "geometry": {"coordinates":[14.047765,53.735592],"type":"Point"}
}