{
  "type": "Feature",
  "properties": {
    "iso:country":"DE",
    "sg:address":"Obere Str. 8",
    "sg:city":"Villingen-Schwenningen",
    "sg:phone":"+49 7721/59590",
    "sg:postcode":"78050",
    "sg:province":"Baden-W\u00fcrttemberg",
    "wof:name":"Verena Str\u00f6bele-hoer Rechtsanw\u00e4ltin",
    "wof:placetype":"venue"
},
  "geometry": {"coordinates":[8.4481897354,48.0599098206],"type":"Point"}
}