{
  "type": "Feature",
  "properties": {
    "iso:country":"DE",
    "sg:address":"Hasenberg 1",
    "sg:city":"Hannover",
    "sg:phone":"+49 511/2716445",
    "sg:postcode":"30419",
    "sg:province":"Niedersachsen",
    "wof:name":"Torbogen",
    "wof:placetype":"venue"
},
  "geometry": {"coordinates":[9.6733236313,52.3976707458],"type":"Point"}
}