{
  "type": "Feature",
  "properties": {
    "iso:country":"DE",
    "sg:address":"Karlstr. 14 A",
    "sg:city":"Laichingen",
    "sg:phone":"+49 7333/5050",
    "sg:postcode":"89150",
    "sg:province":"Baden-W\u00fcrttemberg",
    "wof:name":"Tex-sa",
    "wof:placetype":"venue"
},
  "geometry": {"coordinates":[9.68639,48.487572],"type":"Point"}
}