{
  "type": "Feature",
  "properties": {
    "iso:country":"DE",
    "sg:address":"Mudrastr. 22",
    "sg:city":"Berlin",
    "sg:phone":"+49 30/7751011",
    "sg:postcode":"12249",
    "sg:province":"Berlin",
    "wof:name":"Ev. Pfarramt Paul-schneider-gemeinde",
    "wof:placetype":"venue"
},
  "geometry": {"coordinates":[13.3557548523,52.4305610657],"type":"Point"}
}