{
  "type": "Feature",
  "properties": {
    "iso:country":"DE",
    "sg:address":"Jurastr. 16",
    "sg:city":"Buxheim",
    "sg:phone":"+49 8458/37253",
    "sg:postcode":"85114",
    "sg:province":"Bayern",
    "wof:name":"Sanit\u00e4r- Und Heizungsbau Seeberger Appel Gmbh",
    "wof:placetype":"venue"
},
  "geometry": {"coordinates":[11.2897052765,48.80884552],"type":"Point"}
}