{
  "type": "Feature",
  "properties": {
    "iso:country":"DE",
    "sg:address":"Dobl 3",
    "sg:city":"Nittenau",
    "sg:phone":"+49 9436/662",
    "sg:postcode":"93149",
    "sg:province":"Bayern",
    "wof:name":"Horst Potempa",
    "wof:placetype":"venue"
},
  "geometry": {"coordinates":[12.2695035934,49.1967201233],"type":"Point"}
}