{
  "type": "Feature",
  "properties": {
    "iso:country":"DE",
    "sg:address":"Hackstr. 73",
    "sg:city":"Stuttgart",
    "sg:phone":"+49 711/261515",
    "sg:postcode":"70190",
    "sg:province":"Baden-W\u00fcrttemberg",
    "wof:name":"Bauer Hairstyling-team",
    "wof:placetype":"venue"
},
  "geometry": {"coordinates":[9.2061414719,48.7891273499],"type":"Point"}
}