{
  "type": "Feature",
  "properties": {
    "iso:country":"DE",
    "sg:address":"Industriestr. 15",
    "sg:city":"Dieburg",
    "sg:phone":"+49 6071/21571",
    "sg:postcode":"64807",
    "sg:province":"Hessen",
    "wof:name":"Ipes - Industrial Export Service Gmbh",
    "wof:placetype":"venue"
},
  "geometry": {"coordinates":[8.850998,49.906502],"type":"Point"}
}