{
  "type": "Feature",
  "properties": {
    "iso:country":"DE",
    "sg:address":"Ritterstr. 18",
    "sg:city":"Offenburg",
    "sg:phone":"+49 781/71630",
    "sg:postcode":"77652",
    "sg:province":"Baden-W\u00fcrttemberg",
    "wof:name":"A. Akcay",
    "wof:placetype":"venue"
},
  "geometry": {"coordinates":[7.9458217621,48.4687957764],"type":"Point"}
}