{
  "type": "Feature",
  "properties": {
    "iso:country":"DE",
    "sg:address":"Br\u00fcckenstr. 22",
    "sg:city":"Mayen",
    "sg:phone":"+49 2651/900005",
    "sg:postcode":"56727",
    "sg:province":"Rheinland-Pfalz",
    "wof:name":"Marco Schmitz",
    "wof:placetype":"venue"
},
  "geometry": {"coordinates":[7.2232708931,50.3305358887],"type":"Point"}
}