{
  "type": "Feature",
  "properties": {
    "iso:country":"DE",
    "sg:address":"Wohlgasse 8",
    "sg:city":"Gudensberg",
    "sg:phone":"+49 5603/6724",
    "sg:postcode":"34281",
    "sg:province":"Hessen",
    "wof:name":"Restaurant Bei Angela",
    "wof:placetype":"venue"
},
  "geometry": {"coordinates":[9.3771629333,51.1640892029],"type":"Point"}
}