{
  "type": "Feature",
  "properties": {
    "iso:country":"DE",
    "sg:address":"Berliner Ring",
    "sg:city":"Viernheim",
    "sg:phone":"+49 6204/78860",
    "sg:postcode":"68519",
    "sg:province":"Hessen",
    "wof:name":"Pes Privatisierungs- Entwicklungs- Und",
    "wof:placetype":"venue"
},
  "geometry": {"coordinates":[8.581077,49.534729],"type":"Point"}
}