{
  "type": "Feature",
  "properties": {
    "iso:country":"DE",
    "sg:address":"Hamburger Str. 72",
    "sg:city":"Verden",
    "sg:phone":"+49 4231/7088",
    "sg:postcode":"27283",
    "sg:province":"Niedersachsen",
    "wof:name":"Taxi-ruf In Verden Gmbh",
    "wof:placetype":"venue"
},
  "geometry": {"coordinates":[9.2368879318,52.9518051147],"type":"Point"}
}