{
  "type": "Feature",
  "properties": {
    "iso:country":"DE",
    "sg:address":"Carlo- Schmid- Str. 12a",
    "sg:city":"W\u00fcrselen",
    "sg:phone":"+49 2405",
    "sg:postcode":"52146",
    "sg:province":"Nordrhein-Westfalen",
    "wof:name":"Headset Headsets Headset Headsets Headset Headsets",
    "wof:placetype":"venue"
},
  "geometry": {"coordinates":[6.1610178947,50.8066978455],"type":"Point"}
}