{
  "type": "Feature",
  "properties": {
    "iso:country":"DE",
    "sg:address":"Theaterstr. 12",
    "sg:city":"W\u00fcrzburg",
    "sg:phone":"+49 931/55592",
    "sg:postcode":"97070",
    "sg:province":"Bayern",
    "wof:name":"Optik-wiegand",
    "wof:placetype":"venue"
},
  "geometry": {"coordinates":[9.9343271255,49.796257019],"type":"Point"}
}