{
  "type": "Feature",
  "properties": {
    "iso:country":"DE",
    "sg:address":"Zeughausmarkt 33",
    "sg:city":"Hamburg",
    "sg:postcode":"20459",
    "sg:province":"Hamburg",
    "wof:name":"Give Me F\u00fcnf Online- Kommunikation Agentur",
    "wof:placetype":"venue"
},
  "geometry": {"coordinates":[9.9741601944,53.5489196777],"type":"Point"}
}