{
  "type": "Feature",
  "properties": {
    "iso:country":"DE",
    "sg:address":"Erlenweg 29",
    "sg:city":"Obernburg",
    "sg:postcode":"63785",
    "sg:province":"Bayern",
    "wof:name":"Mht Werbetechnik",
    "wof:placetype":"venue"
},
  "geometry": {"coordinates":[9.1228,49.83839],"type":"Point"}
}