{
  "type": "Feature",
  "properties": {
    "iso:country":"DE",
    "sg:address":"Stephanienstr. 16",
    "sg:city":"Karlsruhe",
    "sg:phone":"+49 721/957893",
    "sg:postcode":"76133",
    "sg:province":"Baden-W\u00fcrttemberg",
    "wof:name":"Club Pinguin",
    "wof:placetype":"venue"
},
  "geometry": {"coordinates":[8.396805,49.012501],"type":"Point"}
}