{
  "type": "Feature",
  "properties": {
    "iso:country":"DE",
    "sg:address":"Westerstr. 83",
    "sg:city":"Norden",
    "sg:phone":"+49 4931/3322",
    "sg:postcode":"26506",
    "sg:province":"Niedersachsen",
    "wof:name":"Rats-apotheke Engelbert Groeneveld",
    "wof:placetype":"venue"
},
  "geometry": {"coordinates":[7.200809,53.594032],"type":"Point"}
}