{
  "type": "Feature",
  "properties": {
    "iso:country":"DE",
    "sg:address":"Saubsdorfer Str. 14",
    "sg:city":"Buchloe",
    "sg:postcode":"86807",
    "sg:province":"Bayern",
    "wof:name":"Ab-m\u00f6belmarkt- Gmbh",
    "wof:placetype":"venue"
},
  "geometry": {"coordinates":[10.7289237976,48.0372695923],"type":"Point"}
}