{
  "type": "Feature",
  "properties": {
    "iso:country":"DE",
    "sg:address":"Braunschweiger Str. 56",
    "sg:city":"Gifhorn",
    "sg:phone":"+49 5371/17286",
    "sg:postcode":"38518",
    "sg:province":"Niedersachsen",
    "wof:name":"Tagestreff Moin Moin Wohnungslosenhilfe",
    "wof:placetype":"venue"
},
  "geometry": {"coordinates":[10.543495,52.475147],"type":"Point"}
}