{
  "type": "Feature",
  "properties": {
    "iso:country":"DE",
    "sg:address":"Wilsdruffer Str. 5",
    "sg:city":"Freital",
    "sg:phone":"+49 351/6411153",
    "sg:postcode":"01705",
    "sg:province":"Sachsen",
    "wof:name":"Die Maler Gmbh",
    "wof:placetype":"venue"
},
  "geometry": {"coordinates":[13.656702,51.009445],"type":"Point"}
}