{
  "type": "Feature",
  "properties": {
    "iso:country":"DE",
    "sg:address":"An der Bundesstra\u00dfe",
    "sg:city":"S\u00fcdbrookmerland",
    "sg:phone":"+49 4941/88956",
    "sg:postcode":"26624",
    "sg:province":"Niedersachsen",
    "wof:name":"Elf-station",
    "wof:placetype":"venue"
},
  "geometry": {"coordinates":[7.3702998161,53.4988594055],"type":"Point"}
}