{
  "type": "Feature",
  "properties": {
    "iso:country":"DE",
    "sg:address":"Dorfstr. 30",
    "sg:city":"B\u00f6ssow",
    "sg:phone":"+49 3881/4451",
    "sg:postcode":"23936",
    "sg:province":"Mecklenburg-Vorpommern",
    "wof:name":"I. Sager",
    "wof:placetype":"venue"
},
  "geometry": {"coordinates":[11.2147359848,53.9203872681],"type":"Point"}
}