{
  "type": "Feature",
  "properties": {
    "iso:country":"DE",
    "sg:address":"Am Nordbahnhof 4",
    "sg:city":"Ingolstadt",
    "sg:phone":"+49 841/73331",
    "sg:postcode":"85049",
    "sg:province":"Bayern",
    "wof:name":"Ambulanter Pflegedienst Ingolstadt Gmbh",
    "wof:placetype":"venue"
},
  "geometry": {"coordinates":[11.432721,48.772175],"type":"Point"}
}