{
  "type": "Feature",
  "properties": {
    "iso:country":"DE",
    "sg:address":"Unterstr. 28",
    "sg:city":"Wadern",
    "sg:phone":"+49 6871/2246",
    "sg:postcode":"66687",
    "sg:province":"Saarland",
    "wof:name":"K. Schmitt",
    "wof:placetype":"venue"
},
  "geometry": {"coordinates":[6.892389,49.539154],"type":"Point"}
}