{
  "type": "Feature",
  "properties": {
    "iso:country":"DE",
    "sg:address":"Herrenstr. 14",
    "sg:city":"Feuchtwangen",
    "sg:phone":"+49 9852/67350",
    "sg:postcode":"91555",
    "sg:province":"Bayern",
    "wof:name":"Stiftsherren-apotheke",
    "wof:placetype":"venue"
},
  "geometry": {"coordinates":[10.332213,49.168522],"type":"Point"}
}