{
  "type": "Feature",
  "properties": {
    "iso:country":"DE",
    "sg:address":"Dorfstr. 9",
    "sg:city":"Hopfgarten",
    "sg:phone":"+49 37369/9279",
    "sg:postcode":"09429",
    "sg:province":"Sachsen",
    "wof:name":"Sieber Strumpffabrik Gmbh",
    "wof:placetype":"venue"
},
  "geometry": {"coordinates":[13.07771,50.663166],"type":"Point"}
}