{
  "type": "Feature",
  "properties": {
    "iso:country":"DE",
    "sg:address":"Im Westerfeld 4",
    "sg:city":"Ladbergen",
    "sg:phone":"+49 5485/3971",
    "sg:postcode":"49549",
    "sg:province":"Nordrhein-Westfalen",
    "wof:name":"Gottfried Korte",
    "wof:placetype":"venue"
},
  "geometry": {"coordinates":[7.74331,52.110706],"type":"Point"}
}