{
  "type": "Feature",
  "properties": {
    "iso:country":"DE",
    "sg:address":"Gartenstr. 20",
    "sg:city":"Wagh\u00e4usel",
    "sg:phone":"+49 7254/71784",
    "sg:postcode":"68753",
    "sg:province":"Baden-W\u00fcrttemberg",
    "wof:name":"Klaris Tierparadies",
    "wof:placetype":"venue"
},
  "geometry": {"coordinates":[8.544418,49.240166],"type":"Point"}
}