{
  "type": "Feature",
  "properties": {
    "iso:country":"DE",
    "sg:address":"Rheinstr. 3",
    "sg:city":"Teltow",
    "sg:phone":"+49 3328/446112",
    "sg:postcode":"14513",
    "sg:province":"Brandenburg",
    "wof:name":"Csa Computer Und Antriebs- Technik Gmbh",
    "wof:placetype":"venue"
},
  "geometry": {"coordinates":[13.2468214035,52.4001121521],"type":"Point"}
}