{
  "type": "Feature",
  "properties": {
    "iso:country":"DE",
    "sg:address":"B\u00f6vemannstr. 1",
    "sg:city":"Greven",
    "sg:phone":"+49 2571/7700",
    "sg:postcode":"48268",
    "sg:province":"Nordrhein-Westfalen",
    "wof:name":"Heinz Massarczyk",
    "wof:placetype":"venue"
},
  "geometry": {"coordinates":[7.607466,52.107334],"type":"Point"}
}