{
  "type": "Feature",
  "properties": {
    "iso:country":"DE",
    "sg:address":"Kegelstr. 42",
    "sg:city":"Duisburg",
    "sg:phone":"+49 203/782673",
    "sg:postcode":"47259",
    "sg:province":"Nordrhein-Westfalen",
    "wof:name":"Peter Klein",
    "wof:placetype":"venue"
},
  "geometry": {"coordinates":[6.681087,51.356655],"type":"Point"}
}