{
  "type": "Feature",
  "properties": {
    "iso:country":"DE",
    "sg:address":"Eresburgstr. 22",
    "sg:city":"Berlin",
    "sg:postcode":"12103",
    "sg:province":"Berlin",
    "wof:name":"Isophan-werke Gmbh",
    "wof:placetype":"venue"
},
  "geometry": {"coordinates":[13.3675718307,52.4670333862],"type":"Point"}
}