{
  "type": "Feature",
  "properties": {
    "iso:country":"DE",
    "sg:address":"Pfarrhofgasse 4",
    "sg:city":"Wemding",
    "sg:phone":"+49 9092/350",
    "sg:postcode":"86650",
    "sg:province":"Bayern",
    "wof:name":"Kath. Pfarramt St. Richardi St. Emmeram",
    "wof:placetype":"venue"
},
  "geometry": {"coordinates":[10.7245178223,48.8737068176],"type":"Point"}
}