{
  "type": "Feature",
  "properties": {
    "iso:country":"DE",
    "sg:address":"Ringreiterweg 8",
    "sg:city":"Rondeshagen",
    "sg:phone":"+49 4544/330",
    "sg:postcode":"23919",
    "sg:province":"Schleswig-Holstein",
    "wof:name":"J. Und P. Rebien",
    "wof:placetype":"venue"
},
  "geometry": {"coordinates":[10.632604,53.753769],"type":"Point"}
}