{
  "type": "Feature",
  "properties": {
    "iso:country":"DE",
    "sg:address":"Kurf\u00fcrst-Balduin-Str. 7",
    "sg:city":"Daun",
    "sg:phone":"+49 6592/2585",
    "sg:postcode":"54550",
    "sg:province":"Rheinland-Pfalz",
    "wof:name":"Susanne Schmitz",
    "wof:placetype":"venue"
},
  "geometry": {"coordinates":[6.8271980286,50.1958274841],"type":"Point"}
}