{
  "type": "Feature",
  "properties": {
    "iso:country":"DE",
    "sg:address":"Pulvergartenstr. 8",
    "sg:city":"Ettlingen",
    "sg:phone":"+49 7243/12122",
    "sg:postcode":"76275",
    "sg:province":"Baden-W\u00fcrttemberg",
    "wof:name":"Michael Govlja",
    "wof:placetype":"venue"
},
  "geometry": {"coordinates":[8.405884,48.946068],"type":"Point"}
}