{
  "type": "Feature",
  "properties": {
    "iso:country":"DE",
    "sg:address":"Kaiserbergsteige 22",
    "sg:city":"G\u00f6ppingen",
    "sg:phone":"+49 7161/979522",
    "sg:postcode":"73037",
    "sg:province":"Baden-W\u00fcrttemberg",
    "wof:name":"Dokumentationsraum F\u00fcr Staufische Geschichte",
    "wof:placetype":"venue"
},
  "geometry": {"coordinates":[9.71877,48.74157],"type":"Point"}
}