{
  "type": "Feature",
  "properties": {
    "iso:country":"DE",
    "sg:address":"Wandsbeker Chaussee 25",
    "sg:city":"Hamburg",
    "sg:phone":"+49 40/258404",
    "sg:postcode":"22089",
    "sg:province":"Hamburg",
    "wof:name":"W. Winter Schl\u00fcsseldienst",
    "wof:placetype":"venue"
},
  "geometry": {"coordinates":[10.0372867584,53.5656356812],"type":"Point"}
}