{
  "type": "Feature",
  "properties": {
    "iso:country":"DE",
    "sg:address":"Bruchstr. 2",
    "sg:city":"Engelskirchen",
    "sg:phone":"+49 2263/1681",
    "sg:postcode":"51766",
    "sg:province":"Nordrhein-Westfalen",
    "wof:name":"U. Kegel",
    "wof:placetype":"venue"
},
  "geometry": {"coordinates":[7.3657531738,50.9733772278],"type":"Point"}
}