{
  "type": "Feature",
  "properties": {
    "iso:country":"DE",
    "sg:address":"Wilhelmstr. 34",
    "sg:city":"Viersen",
    "sg:phone":"+49 2162/16463",
    "sg:postcode":"41747",
    "sg:province":"Nordrhein-Westfalen",
    "wof:name":"Anton Steinwitz",
    "wof:placetype":"venue"
},
  "geometry": {"coordinates":[6.3875818253,51.2535171509],"type":"Point"}
}