{
  "type": "Feature",
  "properties": {
    "iso:country":"DE",
    "sg:address":"Obere Schmiedegasse 5",
    "sg:city":"Annaberg-Buchholz",
    "sg:phone":"+49 3733/44677",
    "sg:postcode":"09456",
    "sg:province":"Sachsen",
    "wof:name":"H. Zapf",
    "wof:placetype":"venue"
},
  "geometry": {"coordinates":[13.004093,50.580917],"type":"Point"}
}