{
  "type": "Feature",
  "properties": {
    "iso:country":"DE",
    "sg:address":"M\u00fchlenweg 18",
    "sg:city":"Wiefelstede",
    "sg:phone":"+49 4403/81201",
    "sg:postcode":"26215",
    "sg:province":"Niedersachsen",
    "wof:name":"H. Finke",
    "wof:placetype":"venue"
},
  "geometry": {"coordinates":[8.060981,53.224297],"type":"Point"}
}