{
  "type": "Feature",
  "properties": {
    "iso:country":"DE",
    "sg:address":"Im Thal 6",
    "sg:city":"Penzberg",
    "sg:phone":"+49 8856/82091",
    "sg:postcode":"82377",
    "sg:province":"Bayern",
    "wof:name":"T. Baumgartner",
    "wof:placetype":"venue"
},
  "geometry": {"coordinates":[11.378405,47.755733],"type":"Point"}
}