{
  "type": "Feature",
  "properties": {
    "iso:country":"DE",
    "sg:address":"Pl\u00e4terstr. 5",
    "sg:city":"Rostock",
    "sg:phone":"+49 381/8099119",
    "sg:postcode":"18055",
    "sg:province":"Mecklenburg-Vorpommern",
    "wof:name":"Graal-m\u00fcritzer Projekt- Entwicklungs- Und",
    "wof:placetype":"venue"
},
  "geometry": {"coordinates":[12.13558,54.091228],"type":"Point"}
}