{
  "type": "Feature",
  "properties": {
    "iso:country":"DE",
    "sg:address":"Feldrenne 3",
    "sg:city":"Hildesheim",
    "sg:phone":"+49 5121/53517",
    "sg:postcode":"31135",
    "sg:province":"Niedersachsen",
    "wof:name":"Ulrike Fricke",
    "wof:placetype":"venue"
},
  "geometry": {"coordinates":[9.9701833725,52.156665802],"type":"Point"}
}