{
  "type": "Feature",
  "properties": {
    "iso:country":"DE",
    "sg:address":"Neustadt 92",
    "sg:city":"Husum",
    "sg:phone":"+49 4841/2806",
    "sg:postcode":"25813",
    "sg:province":"Schleswig-Holstein",
    "wof:name":"Martin Beilfu\u00df",
    "wof:placetype":"venue"
},
  "geometry": {"coordinates":[9.0464487076,54.4805793762],"type":"Point"}
}