{
  "type": "Feature",
  "properties": {
    "iso:country":"DE",
    "sg:address":"Rosenweg 2",
    "sg:city":"B\u00f6hmfeld",
    "sg:phone":"+49 8406/91277",
    "sg:postcode":"85113",
    "sg:province":"Bayern",
    "wof:name":"Dombek",
    "wof:placetype":"venue"
},
  "geometry": {"coordinates":[11.371117,48.859341],"type":"Point"}
}