{
  "type": "Feature",
  "properties": {
    "iso:country":"DE",
    "sg:address":"Barkel",
    "sg:city":"Schortens",
    "sg:phone":"+49 4423/6812",
    "sg:postcode":"26419",
    "sg:province":"Niedersachsen",
    "wof:name":"Johann Meiners",
    "wof:placetype":"venue"
},
  "geometry": {"coordinates":[7.987718,53.545574],"type":"Point"}
}