{
  "type": "Feature",
  "properties": {
    "iso:country":"DE",
    "sg:address":"Lindenstr. 20b",
    "sg:city":"Bernburg",
    "sg:postcode":"06406",
    "sg:province":"Sachsen-Anhalt",
    "wof:name":"Neckermann Versand Ag",
    "wof:placetype":"venue"
},
  "geometry": {"coordinates":[11.7441596985,51.7923049927],"type":"Point"}
}