{
  "type": "Feature",
  "properties": {
    "iso:country":"DE",
    "sg:address":"Kierberger Str. 158",
    "sg:city":"Br\u00fchl",
    "sg:phone":"+49 2232/29702",
    "sg:postcode":"50321",
    "sg:province":"Nordrhein-Westfalen",
    "wof:name":"Matthias Erforth Gastronomie- Betriebe Kg",
    "wof:placetype":"venue"
},
  "geometry": {"coordinates":[6.8879408836,50.8376274109],"type":"Point"}
}