{
  "type": "Feature",
  "properties": {
    "iso:country":"DE",
    "sg:address":"Neue Kirchstr. 31",
    "sg:city":"Gimbsheim",
    "sg:phone":"+49 6249/4634",
    "sg:postcode":"67578",
    "sg:province":"Rheinland-Pfalz",
    "wof:name":"Doris Janas",
    "wof:placetype":"venue"
},
  "geometry": {"coordinates":[8.3724212646,49.7791824341],"type":"Point"}
}