{
  "type": "Feature",
  "properties": {
    "iso:country":"DE",
    "sg:address":"F\u00e4rberstr. 9",
    "sg:city":"M\u00fchldorf",
    "sg:phone":"+49 8631/6286",
    "sg:postcode":"84453",
    "sg:province":"Bayern",
    "wof:name":"Textilreinigung Zahn Gmbh",
    "wof:placetype":"venue"
},
  "geometry": {"coordinates":[12.504721,48.246754],"type":"Point"}
}