{
  "type": "Feature",
  "properties": {
    "iso:country":"DE",
    "sg:address":"Am Weichselgarten 24 a",
    "sg:city":"Erlangen",
    "sg:phone":"+49 9131/771250",
    "sg:postcode":"91058",
    "sg:province":"Bayern",
    "wof:name":"Etap Hotel",
    "wof:placetype":"venue"
},
  "geometry": {"coordinates":[11.0235395432,49.5421867371],"type":"Point"}
}