{
  "type": "Feature",
  "properties": {
    "iso:country":"DE",
    "sg:address":"Steinstr. 2",
    "sg:city":"Hohenlinden",
    "sg:phone":"+49 8124/9853",
    "sg:postcode":"85664",
    "sg:province":"Bayern",
    "wof:name":"Bayer & Partner Institut F\u00fcr Umwelt- Und Bau-",
    "wof:placetype":"venue"
},
  "geometry": {"coordinates":[11.990896,48.153351],"type":"Point"}
}