{
  "type": "Feature",
  "properties": {
    "iso:country":"DE",
    "sg:address":"Parkstr. 3",
    "sg:city":"Duisburg",
    "sg:phone":"+49 203/342738",
    "sg:postcode":"47058",
    "sg:province":"Nordrhein-Westfalen",
    "wof:name":"Carsten Dietrich",
    "wof:placetype":"venue"
},
  "geometry": {"coordinates":[6.7963309288,51.4385910034],"type":"Point"}
}