{
  "type": "Feature",
  "properties": {
    "iso:country":"DE",
    "sg:address":"Hermann-Geisen-Str. 53",
    "sg:city":"H\u00f6hr-Grenzhausen",
    "sg:phone":"+49 2624/3274",
    "sg:postcode":"56203",
    "sg:province":"Rheinland-Pfalz",
    "wof:name":"Fred Karge",
    "wof:placetype":"venue"
},
  "geometry": {"coordinates":[7.656816,50.441399],"type":"Point"}
}