{
  "type": "Feature",
  "properties": {
    "iso:country":"DE",
    "sg:address":"Am M\u00fchlenweg 6",
    "sg:city":"Dreikirchen",
    "sg:phone":"+49 6435/961120",
    "sg:postcode":"56414",
    "sg:province":"Rheinland-Pfalz",
    "wof:name":"Kvs Maurer- Und Zementestrichbau Gmbh",
    "wof:placetype":"venue"
},
  "geometry": {"coordinates":[7.943981,50.448952],"type":"Point"}
}