{
  "type": "Feature",
  "properties": {
    "iso:country":"DE",
    "sg:address":"Aloys-Nesseler-Platz 6",
    "sg:city":"Bexbach",
    "sg:phone":"+49 6826/51787",
    "sg:postcode":"66450",
    "sg:province":"Saarland",
    "wof:name":"S. Sp\u00e4th & W. D\u00f6rfelt",
    "wof:placetype":"venue"
},
  "geometry": {"coordinates":[7.2559189796,49.3476409912],"type":"Point"}
}