{
  "type": "Feature",
  "properties": {
    "iso:country":"DE",
    "sg:address":"V\u00fcrfels 52",
    "sg:city":"Bergisch Gladbach",
    "sg:phone":"+49 2204/60677",
    "sg:postcode":"51427",
    "sg:province":"Nordrhein-Westfalen",
    "wof:name":"Restaurant La Venta",
    "wof:placetype":"venue"
},
  "geometry": {"coordinates":[7.10912323,50.954460144],"type":"Point"}
}