{
  "type": "Feature",
  "properties": {
    "iso:country":"DE",
    "sg:address":"Siebenmorgen 39",
    "sg:city":"Bergisch Gladbach",
    "sg:phone":"+49 2204/21107",
    "sg:postcode":"51427",
    "sg:province":"Nordrhein-Westfalen",
    "wof:name":"Linden-apotheke",
    "wof:placetype":"venue"
},
  "geometry": {"coordinates":[7.115254,50.957726],"type":"Point"}
}