{
  "type": "Feature",
  "properties": {
    "iso:country":"DE",
    "sg:address":"M\u00f6rike Str. 3",
    "sg:city":"Bad Kreuznach",
    "sg:postcode":"55543",
    "sg:province":"Rheinland-Pfalz",
    "wof:name":"Gmo Industrieautomation",
    "wof:placetype":"venue"
},
  "geometry": {"coordinates":[7.87358284,49.8309135437],"type":"Point"}
}