{
  "type": "Feature",
  "properties": {
    "iso:country":"DE",
    "sg:address":"Jahnstr. 45",
    "sg:city":"Dessau",
    "sg:phone":"+49 340/614580",
    "sg:postcode":"06846",
    "sg:province":"Sachsen-Anhalt",
    "wof:name":"Helga Krodel",
    "wof:placetype":"venue"
},
  "geometry": {"coordinates":[12.229408,51.837517],"type":"Point"}
}