{
  "type": "Feature",
  "properties": {
    "iso:country":"DE",
    "sg:address":"Neuhofstr. 1",
    "sg:city":"Wegberg",
    "sg:phone":"+49 2434/4381",
    "sg:postcode":"41844",
    "sg:province":"Nordrhein-Westfalen",
    "wof:name":"Karl-heinz Wolters Bootshandlung",
    "wof:placetype":"venue"
},
  "geometry": {"coordinates":[6.294098,51.137146],"type":"Point"}
}