{
  "type": "Feature",
  "properties": {
    "iso:country":"DE",
    "sg:address":"Bielfeldtweg 26",
    "sg:city":"Stade",
    "sg:postcode":"21682",
    "sg:province":"Niedersachsen",
    "wof:name":"Sl-automobile Gmbh",
    "wof:placetype":"venue"
},
  "geometry": {"coordinates":[9.435483,53.596298],"type":"Point"}
}