{
  "type": "Feature",
  "properties": {
    "iso:country":"DE",
    "sg:address":"Mannheimer Str. 271",
    "sg:city":"Heidelberg",
    "sg:phone":"+49 6221/830527",
    "sg:postcode":"69123",
    "sg:province":"Baden-W\u00fcrttemberg",
    "wof:name":"Hartmut H. Sch\u00e4del Augenoptiker",
    "wof:placetype":"venue"
},
  "geometry": {"coordinates":[8.6472272873,49.4261627197],"type":"Point"}
}