{
  "type": "Feature",
  "properties": {
    "iso:country":"DE",
    "sg:address":"Abteistr. 3",
    "sg:city":"Essen",
    "sg:phone":"+49 201/8496959",
    "sg:postcode":"45239",
    "sg:province":"Nordrhein-Westfalen",
    "wof:name":"Bistro Kudamm",
    "wof:placetype":"venue"
},
  "geometry": {"coordinates":[7.0009598732,51.3874320984],"type":"Point"}
}