{
  "type": "Feature",
  "properties": {
    "iso:country":"DE",
    "sg:address":"Hohenzollernring 51",
    "sg:city":"K\u00f6ln",
    "sg:phone":"+49 221/208060",
    "sg:postcode":"50672",
    "sg:province":"Nordrhein-Westfalen",
    "wof:name":"Cologne Insurance Vermittlungs Ohg",
    "wof:placetype":"venue"
},
  "geometry": {"coordinates":[6.9395718575,50.9398918152],"type":"Point"}
}