{
  "type": "Feature",
  "properties": {
    "iso:country":"DE",
    "sg:address":"Seiferitzer Allee 23",
    "sg:city":"Meerane",
    "sg:phone":"+49 3764/4666",
    "sg:postcode":"08393",
    "sg:province":"Sachsen",
    "wof:name":"Fps Montage- Und Personal- Service Gmbh",
    "wof:placetype":"venue"
},
  "geometry": {"coordinates":[12.4789352417,50.8440628052],"type":"Point"}
}