{
  "type": "Feature",
  "properties": {
    "iso:country":"DE",
    "sg:address":"Gartenstr. 35",
    "sg:city":"Nortrup",
    "sg:phone":"+49 5436/1620",
    "sg:postcode":"49638",
    "sg:province":"Niedersachsen",
    "wof:name":"A. Wellbrock",
    "wof:placetype":"venue"
},
  "geometry": {"coordinates":[7.8822221756,52.6052398682],"type":"Point"}
}