{
  "type": "Feature",
  "properties": {
    "iso:country":"DE",
    "sg:address":"Bobstr. 22",
    "sg:city":"K\u00f6ln",
    "sg:phone":"+49 221/80150",
    "sg:postcode":"50676",
    "sg:province":"Nordrhein-Westfalen",
    "wof:name":"Art Und Media Gesellschaft F\u00fcr Kulturmanagement Mbh",
    "wof:placetype":"venue"
},
  "geometry": {"coordinates":[6.946347,50.933758],"type":"Point"}
}