{
  "type": "Feature",
  "properties": {
    "iso:country":"DE",
    "sg:address":"Mittweidaer Str. 82",
    "sg:city":"Hainichen",
    "sg:phone":"+49 37207/2686",
    "sg:postcode":"09661",
    "sg:province":"Sachsen",
    "wof:name":"Detlef H\u00f6rner",
    "wof:placetype":"venue"
},
  "geometry": {"coordinates":[13.1086425781,50.9786911011],"type":"Point"}
}