{
  "type": "Feature",
  "properties": {
    "iso:country":"DE",
    "sg:city":"Hohenfels",
    "sg:phone":"+49 9472/1340",
    "sg:postcode":"92366",
    "sg:province":"Bayern",
    "wof:name":"Aafes-europe",
    "wof:placetype":"venue"
},
  "geometry": {"coordinates":[11.848002,49.203953],"type":"Point"}
}