{
  "type": "Feature",
  "properties": {
    "iso:country":"DE",
    "sg:address":"Langgasse 181a",
    "sg:city":"Ha\u00dfloch",
    "sg:phone":"+49 6324/2141",
    "sg:postcode":"67454",
    "sg:province":"Rheinland-Pfalz",
    "wof:name":"Metzgerei Vogt E. K.",
    "wof:placetype":"venue"
},
  "geometry": {"coordinates":[8.2656583786,49.3644142151],"type":"Point"}
}