{
  "type": "Feature",
  "properties": {
    "iso:country":"DE",
    "sg:address":"Stobenstr. 31",
    "sg:city":"Helmstedt",
    "sg:phone":"+49 5351/17308",
    "sg:postcode":"38350",
    "sg:province":"Niedersachsen",
    "wof:name":"Stadtb\u00fccherei Helmstedt",
    "wof:placetype":"venue"
},
  "geometry": {"coordinates":[11.007349,52.229946],"type":"Point"}
}