{
  "type": "Feature",
  "properties": {
    "iso:country":"DE",
    "sg:city":"XYV",
    "sg:postcode":"55555",
    "wof:name":"Mainbrain",
    "wof:placetype":"venue"
},
  "geometry": {"coordinates":[-93.914993,44.7836],"type":"Point"}
}