{
  "type": "Feature",
  "properties": {
    "iso:country":"DE",
    "sg:address":"Hauptstr. 31",
    "sg:city":"Leopoldsh\u00f6he",
    "sg:phone":"+49 5208/242",
    "sg:postcode":"33818",
    "sg:province":"Nordrhein-Westfalen",
    "wof:name":"Annette Kerker",
    "wof:placetype":"venue"
},
  "geometry": {"coordinates":[8.698291,52.008911],"type":"Point"}
}