{
  "type": "Feature",
  "properties": {
    "iso:country":"DE",
    "sg:address":"Lachstr. 87",
    "sg:city":"Spaichingen",
    "sg:postcode":"78549",
    "sg:province":"Baden-W\u00fcrttemberg",
    "wof:name":"Finanzkontor S\u00fcdwest",
    "wof:placetype":"venue"
},
  "geometry": {"coordinates":[8.7218933105,48.0825805664],"type":"Point"}
}