{
  "type": "Feature",
  "properties": {
    "iso:country":"DE",
    "sg:address":"Bahnhofstr. 6",
    "sg:city":"Bispingen",
    "sg:phone":"+49 5194/2634",
    "sg:postcode":"29646",
    "sg:province":"Niedersachsen",
    "wof:name":"Herta Klostermann",
    "wof:placetype":"venue"
},
  "geometry": {"coordinates":[9.9946718216,53.0850257874],"type":"Point"}
}