{
  "type": "Feature",
  "properties": {
    "iso:country":"DE",
    "sg:address":"Gro\u00dfer Griechenmarkt 87",
    "sg:city":"K\u00f6ln",
    "sg:phone":"+49 221/239059",
    "sg:postcode":"50676",
    "sg:province":"Nordrhein-Westfalen",
    "wof:name":"Stama Immobilien Gmbh",
    "wof:placetype":"venue"
},
  "geometry": {"coordinates":[6.9509801865,50.931968689],"type":"Point"}
}