{
  "type": "Feature",
  "properties": {
    "iso:country":"DE",
    "sg:address":"Hegelstr. 39",
    "sg:city":"Magdeburg",
    "sg:phone":"+49 391/5356760",
    "sg:postcode":"39104",
    "sg:province":"Sachsen-Anhalt",
    "wof:name":"Eumedias Heilberufe Ag Wirtschaftsberatung Und",
    "wof:placetype":"venue"
},
  "geometry": {"coordinates":[11.6320228577,52.1212882996],"type":"Point"}
}