{
  "type": "Feature",
  "properties": {
    "iso:country":"DE",
    "sg:address":"Feldhausen 1",
    "sg:city":"Hasel\u00fcnne",
    "sg:phone":"+49 5962/695",
    "sg:postcode":"49740",
    "sg:province":"Niedersachsen",
    "wof:name":"Heinrich Schulte",
    "wof:placetype":"venue"
},
  "geometry": {"coordinates":[7.564311,52.705418],"type":"Point"}
}