{
  "type": "Feature",
  "properties": {
    "iso:country":"DE",
    "sg:address":"Marktstr. 11",
    "sg:city":"Winterberg",
    "sg:phone":"+49 2981/6751",
    "sg:postcode":"59955",
    "sg:province":"Nordrhein-Westfalen",
    "wof:name":"Ralph Schmitz-engemann Rechtsanwalt",
    "wof:placetype":"venue"
},
  "geometry": {"coordinates":[8.5354070663,51.1946792603],"type":"Point"}
}