{
  "type": "Feature",
  "properties": {
    "iso:country":"DE",
    "sg:address":"Los-Angeles-Platz 1",
    "sg:city":"Berlin",
    "sg:phone":"+49 30/2127750",
    "sg:postcode":"10789",
    "sg:province":"Berlin",
    "wof:name":"Restaurant Destille",
    "wof:placetype":"venue"
},
  "geometry": {"coordinates":[13.3351659775,52.5026321411],"type":"Point"}
}