{
  "type": "Feature",
  "properties": {
    "iso:country":"DE",
    "sg:address":"Hinter der Altd\u00f6rfer Kirche 9",
    "sg:city":"Babenhausen",
    "sg:phone":"+49 6073/3259",
    "sg:postcode":"64832",
    "sg:province":"Hessen",
    "wof:name":"Baumann Handelsvertretung Cdh E. K.",
    "wof:placetype":"venue"
},
  "geometry": {"coordinates":[8.9522094727,49.9515380859],"type":"Point"}
}