{
  "type": "Feature",
  "properties": {
    "iso:country":"DE",
    "sg:address":"Brumhagen 8",
    "sg:city":"Buchholz",
    "sg:phone":"+49 4181/8808",
    "sg:postcode":"21244",
    "sg:province":"Niedersachsen",
    "wof:name":"Heinrich Brockmann Bedachungen Gmbh",
    "wof:placetype":"venue"
},
  "geometry": {"coordinates":[9.828089,53.321644],"type":"Point"}
}