{
  "type": "Feature",
  "properties": {
    "iso:country":"DE",
    "sg:address":"Stresemannstr. 8",
    "sg:city":"Bonn",
    "sg:phone":"+49 228/644325",
    "sg:postcode":"53123",
    "sg:province":"Nordrhein-Westfalen",
    "wof:name":"Oprost-west-publik Relations Gmbh",
    "wof:placetype":"venue"
},
  "geometry": {"coordinates":[7.0359950066,50.7097053528],"type":"Point"}
}