{
  "type": "Feature",
  "properties": {
    "iso:country":"DE",
    "sg:address":"Alte Pforzheimer Str. 3",
    "sg:city":"Wurmberg",
    "sg:phone":"+49 7044/43211",
    "sg:postcode":"75449",
    "sg:province":"Baden-W\u00fcrttemberg",
    "wof:name":"Britsch Torbau Gmbh",
    "wof:placetype":"venue"
},
  "geometry": {"coordinates":[8.807919,48.873081],"type":"Point"}
}