{
  "type": "Feature",
  "properties": {
    "iso:country":"DE",
    "sg:address":"Hammerm\u00fchle 23",
    "sg:city":"Overath",
    "sg:phone":"+49 2206/4462",
    "sg:postcode":"51491",
    "sg:province":"Nordrhein-Westfalen",
    "wof:name":"H\u00f6ck-jansen Gmbh",
    "wof:placetype":"venue"
},
  "geometry": {"coordinates":[7.2967481613,50.9396209717],"type":"Point"}
}