{
  "type": "Feature",
  "properties": {
    "iso:country":"DE",
    "sg:address":"Hoopstr. 2",
    "sg:city":"Stadtoldendorf",
    "sg:phone":"+49 5532/5060",
    "sg:postcode":"37627",
    "sg:province":"Niedersachsen",
    "wof:name":"Hotel Villa Mosler",
    "wof:placetype":"venue"
},
  "geometry": {"coordinates":[9.6222829819,51.8827972412],"type":"Point"}
}