{
  "type": "Feature",
  "properties": {
    "iso:country":"DE",
    "sg:address":"Otto-Hahn-Str 14",
    "sg:city":"Unna",
    "sg:phone":"+49 2303/88050",
    "sg:postcode":"59423",
    "sg:province":"Nordrhein-Westfalen",
    "wof:name":"Brillux Industrielacke Gmbh & Co Kg",
    "wof:placetype":"venue"
},
  "geometry": {"coordinates":[7.7238440514,51.5299224854],"type":"Point"}
}