{
  "type": "Feature",
  "properties": {
    "iso:country":"DE",
    "sg:address":"Ernst-Ludwig-Str. 57",
    "sg:city":"Egelsbach",
    "sg:phone":"+49 6103/42717",
    "sg:postcode":"63329",
    "sg:province":"Hessen",
    "wof:name":"E. Wallenfels",
    "wof:placetype":"venue"
},
  "geometry": {"coordinates":[8.667213,49.969227],"type":"Point"}
}