{
  "type": "Feature",
  "properties": {
    "iso:country":"DE",
    "sg:address":"Rykestr. 25",
    "sg:city":"Berlin",
    "sg:phone":"+49 30/44358090",
    "sg:postcode":"10405",
    "sg:province":"Berlin",
    "wof:name":"I. B. I. S. B\u00fcrger- Beratungsgesellschaft F\u00fcr",
    "wof:placetype":"venue"
},
  "geometry": {"coordinates":[13.422456,52.538479],"type":"Point"}
}