{
  "type": "Feature",
  "properties": {
    "iso:country":"DE",
    "sg:address":"Dieselstr. 35",
    "sg:city":"Meppen",
    "sg:phone":"+49 5931/87333",
    "sg:postcode":"49716",
    "sg:province":"Niedersachsen",
    "wof:name":"Druckerei Schmit Gmbh",
    "wof:placetype":"venue"
},
  "geometry": {"coordinates":[7.297257,52.658234],"type":"Point"}
}