{
  "type": "Feature",
  "properties": {
    "iso:country":"DE",
    "sg:address":"Kolpingstr. 28",
    "sg:city":"Oberhausen-Rheinhausen",
    "sg:phone":"+49 7254/2193",
    "sg:postcode":"68794",
    "sg:province":"Baden-W\u00fcrttemberg",
    "wof:name":"Weser & Reiser Versicherungsb\u00fcro Oberhausen",
    "wof:placetype":"venue"
},
  "geometry": {"coordinates":[8.4818754196,49.2618942261],"type":"Point"}
}