{
  "type": "Feature",
  "properties": {
    "iso:country":"DE",
    "sg:address":"Bornstr. 17",
    "sg:city":"Willmenrod",
    "sg:phone":"+49 2663/8558",
    "sg:postcode":"56459",
    "sg:province":"Rheinland-Pfalz",
    "wof:name":"Sandra Loos",
    "wof:placetype":"venue"
},
  "geometry": {"coordinates":[7.981742,50.54044],"type":"Point"}
}