{
  "type": "Feature",
  "properties": {
    "iso:country":"DE",
    "sg:address":"Franz-Lehar-Str. 8",
    "sg:city":"Neu-Ulm",
    "sg:phone":"+49 731/721122",
    "sg:postcode":"89231",
    "sg:province":"Bayern",
    "wof:name":"Franz Reuter",
    "wof:placetype":"venue"
},
  "geometry": {"coordinates":[10.0253620148,48.4052734375],"type":"Point"}
}