{
  "type": "Feature",
  "properties": {
    "iso:country":"DE",
    "sg:address":"Friedrich-Hegel-Str. 116",
    "sg:city":"Schwerte",
    "sg:phone":"+49 2304/83100",
    "sg:postcode":"58239",
    "sg:province":"Nordrhein-Westfalen",
    "wof:name":"Rosen-apotheke",
    "wof:placetype":"venue"
},
  "geometry": {"coordinates":[7.550626,51.441334],"type":"Point"}
}