{
  "type": "Feature",
  "properties": {
    "iso:country":"DE",
    "sg:address":"Morellstr. 33",
    "sg:city":"Augsburg",
    "sg:phone":"+49 821/576072",
    "sg:postcode":"86159",
    "sg:province":"Bayern",
    "wof:name":"Fa. Bernh. M\u00fcller Kg Augsburg",
    "wof:placetype":"venue"
},
  "geometry": {"coordinates":[10.89239,48.356129],"type":"Point"}
}