{
  "type": "Feature",
  "properties": {
    "iso:country":"DE",
    "sg:address":"Fasanenstr. 42 b",
    "sg:city":"Karlsfeld b. M\u00fcnchen",
    "sg:phone":"+49 8131",
    "sg:postcode":"85757",
    "sg:province":"Bayern",
    "wof:name":"M\u00fcnchner Zentrum F\u00fcr Bewusstseinserfahrung Und Energiearbeit",
    "wof:placetype":"venue"
},
  "geometry": {"coordinates":[11.486565,48.229961],"type":"Point"}
}