{
  "type": "Feature",
  "properties": {
    "iso:country":"DE",
    "sg:address":"Adlerstr. 2",
    "sg:city":"Oberhausen-Rheinhausen",
    "sg:phone":"+49 7254/2126",
    "sg:postcode":"68794",
    "sg:province":"Baden-W\u00fcrttemberg",
    "wof:name":"Pizzeria Bei Mario",
    "wof:placetype":"venue"
},
  "geometry": {"coordinates":[8.4961853027,49.2621383667],"type":"Point"}
}