{
  "type": "Feature",
  "properties": {
    "iso:country":"DE",
    "sg:address":"Friedensstr. 6-10",
    "sg:city":"Frankfurt",
    "sg:phone":"+49 4969/21790",
    "sg:postcode":"60311",
    "sg:province":"Hessen",
    "wof:name":"Lloyds Bank Plc",
    "wof:placetype":"venue"
},
  "geometry": {"coordinates":[8.675247,50.109718],"type":"Point"}
}