{
  "type": "Feature",
  "properties": {
    "iso:country":"DE",
    "sg:address":"Steinstr. 16",
    "sg:city":"Freyburg",
    "sg:phone":"+49 34464/27334",
    "sg:postcode":"06632",
    "sg:province":"Sachsen-Anhalt",
    "wof:name":"Roland Gro\u00dfe",
    "wof:placetype":"venue"
},
  "geometry": {"coordinates":[11.7688808441,51.2126083374],"type":"Point"}
}