{
  "type": "Feature",
  "properties": {
    "iso:country":"DE",
    "sg:address":"Hubertusstr. 66",
    "sg:city":"Recklinghausen",
    "sg:phone":"+49 2361/93030",
    "sg:postcode":"45657",
    "sg:province":"Nordrhein-Westfalen",
    "wof:name":"Jorch & Pantf\u00f6rder Gmbh",
    "wof:placetype":"venue"
},
  "geometry": {"coordinates":[7.2097210884,51.6063117981],"type":"Point"}
}