{
  "type": "Feature",
  "properties": {
    "iso:country":"DE",
    "sg:address":"Im Haag 3",
    "sg:city":"Rommersheim",
    "sg:phone":"+49 6551/7657",
    "sg:postcode":"54597",
    "sg:province":"Rheinland-Pfalz",
    "wof:name":"Paul Klein",
    "wof:placetype":"venue"
},
  "geometry": {"coordinates":[6.440512,50.191708],"type":"Point"}
}