{
  "type": "Feature",
  "properties": {
    "iso:country":"DE",
    "sg:address":"Mommsenstr. 2",
    "sg:city":"Berlin",
    "sg:phone":"+49 30/86683750",
    "sg:postcode":"10629",
    "sg:province":"Berlin",
    "wof:name":"Reinhard Landskron Architekt",
    "wof:placetype":"venue"
},
  "geometry": {"coordinates":[13.321051,52.502983],"type":"Point"}
}