{
  "type": "Feature",
  "properties": {
    "iso:country":"DE",
    "sg:address":"Krahenh\u00f6her Weg 17",
    "sg:city":"Solingen",
    "sg:phone":"+49 212/2542595",
    "sg:postcode":"42659",
    "sg:province":"Nordrhein-Westfalen",
    "wof:name":"Fds J\u00fcrgen Sauer",
    "wof:placetype":"venue"
},
  "geometry": {"coordinates":[7.11718,51.162155],"type":"Point"}
}