{
  "type": "Feature",
  "properties": {
    "iso:country":"DE",
    "sg:address":"Steinbecker Str. 43 a",
    "sg:city":"Buchholz",
    "sg:phone":"+49 4181/6572",
    "sg:postcode":"21244",
    "sg:province":"Niedersachsen",
    "wof:name":"Gastst\u00e4tte Zur M\u00fchle",
    "wof:placetype":"venue"
},
  "geometry": {"coordinates":[9.8743953705,53.3325271606],"type":"Point"}
}