{
  "type": "Feature",
  "properties": {
    "iso:country":"DE",
    "sg:address":"Rehwiese 35",
    "sg:city":"Holzminden",
    "sg:phone":"+49 5531/3293",
    "sg:postcode":"37603",
    "sg:province":"Niedersachsen",
    "wof:name":"F. Giesecke Eisenwaren",
    "wof:placetype":"venue"
},
  "geometry": {"coordinates":[9.4491157532,51.8376235962],"type":"Point"}
}