{
  "type": "Feature",
  "properties": {
    "iso:country":"DE",
    "sg:address":"Dorfstr. 48",
    "sg:city":"Netzeband",
    "sg:phone":"+49 33924/70666",
    "sg:postcode":"16818",
    "sg:province":"Brandenburg",
    "wof:name":"Theaterfestspiele Netzeband Gmbh",
    "wof:placetype":"venue"
},
  "geometry": {"coordinates":[12.6422863007,52.9981307983],"type":"Point"}
}