{
  "type": "Feature",
  "properties": {
    "iso:country":"DE",
    "sg:address":"Hauptstr. 19",
    "sg:city":"Emmerthal",
    "sg:phone":"+49 5155/8418",
    "sg:postcode":"31860",
    "sg:province":"Niedersachsen",
    "wof:name":"Hermann Schlie",
    "wof:placetype":"venue"
},
  "geometry": {"coordinates":[9.393839,52.046898],"type":"Point"}
}