{
  "type": "Feature",
  "properties": {
    "iso:country":"DE",
    "sg:address":"Verler Str. 310",
    "sg:city":"G\u00fctersloh",
    "sg:phone":"+49 5241/4101",
    "sg:postcode":"33334",
    "sg:province":"Nordrhein-Westfalen",
    "wof:name":"Pfleiderer Gmbh",
    "wof:placetype":"venue"
},
  "geometry": {"coordinates":[8.410656,51.946053],"type":"Point"}
}