{
  "type": "Feature",
  "properties": {
    "iso:country":"DE",
    "sg:address":"Finkenweg 7",
    "sg:city":"Schlangen",
    "sg:phone":"+49 5252/82357",
    "sg:postcode":"33189",
    "sg:province":"Nordrhein-Westfalen",
    "wof:name":"Erna Sch\u00fcrmann",
    "wof:placetype":"venue"
},
  "geometry": {"coordinates":[8.838312149,51.8362617493],"type":"Point"}
}