{
  "type": "Feature",
  "properties": {
    "iso:country":"DE",
    "sg:address":"In den Langen St\u00fccken 11",
    "sg:city":"Halberstadt",
    "sg:phone":"+49 3941/27087",
    "sg:postcode":"38820",
    "sg:province":"Sachsen-Anhalt",
    "wof:name":"Heine & Pattermann",
    "wof:placetype":"venue"
},
  "geometry": {"coordinates":[11.081837,51.901909],"type":"Point"}
}