{
  "type": "Feature",
  "properties": {
    "iso:country":"DE",
    "sg:address":"Fritz-Tillmann-Str. 2",
    "sg:city":"Bonn",
    "sg:phone":"+49 228/224747",
    "sg:postcode":"53113",
    "sg:province":"Nordrhein-Westfalen",
    "wof:name":"Arnold Zmyj Steuerberater",
    "wof:placetype":"venue"
},
  "geometry": {"coordinates":[7.1044039726,50.7310028076],"type":"Point"}
}