{
  "type": "Feature",
  "properties": {
    "iso:country":"DE",
    "sg:address":"Frankenbergstr. 26",
    "sg:city":"Dresden",
    "sg:phone":"+49 351/4273321",
    "sg:postcode":"01159",
    "sg:province":"Sachsen",
    "wof:name":"S. D\u00f6ring",
    "wof:placetype":"venue"
},
  "geometry": {"coordinates":[13.6999378204,51.036567688],"type":"Point"}
}