{
  "type": "Feature",
  "properties": {
    "iso:country":"DE",
    "sg:address":"Fischerstr. 17",
    "sg:city":"Torgau",
    "sg:phone":"+49 3421/904337",
    "sg:postcode":"04860",
    "sg:province":"Sachsen",
    "wof:name":"E. Mei\u00dfner",
    "wof:placetype":"venue"
},
  "geometry": {"coordinates":[13.0044326782,51.5572814941],"type":"Point"}
}