{
  "type": "Feature",
  "properties": {
    "iso:country":"DE",
    "sg:address":"Steinweg 18",
    "sg:city":"Felsberg",
    "sg:phone":"+49 5662/6110",
    "sg:postcode":"34587",
    "sg:province":"Hessen",
    "wof:name":"Gastst\u00e4tte Cadillac",
    "wof:placetype":"venue"
},
  "geometry": {"coordinates":[9.4284334183,51.1334724426],"type":"Point"}
}