{
  "type": "Feature",
  "properties": {
    "iso:country":"DE",
    "sg:address":"Altona 9",
    "sg:city":"Hollnseth",
    "sg:phone":"+49 4773/417",
    "sg:postcode":"21769",
    "sg:province":"Niedersachsen",
    "wof:name":"H. Heinsohn",
    "wof:placetype":"venue"
},
  "geometry": {"coordinates":[9.10308,53.596558],"type":"Point"}
}