{
  "type": "Feature",
  "properties": {
    "iso:country":"DE",
    "sg:address":"Lindenrain 5",
    "sg:city":"Eisenach",
    "sg:postcode":"99817",
    "sg:province":"Th\u00fcringen",
    "wof:name":"Aure Verwaltungs-gmbh",
    "wof:placetype":"venue"
},
  "geometry": {"coordinates":[10.2592611313,50.9920425415],"type":"Point"}
}