{
  "type": "Feature",
  "properties": {
    "iso:country":"DE",
    "sg:address":"Steinstr. 35",
    "sg:city":"Steinfurt",
    "sg:phone":"+49 2551/82002",
    "sg:postcode":"48565",
    "sg:province":"Nordrhein-Westfalen",
    "wof:name":"F. Vorgerd Gmbh",
    "wof:placetype":"venue"
},
  "geometry": {"coordinates":[7.336674,52.148949],"type":"Point"}
}