{
  "type": "Feature",
  "properties": {
    "iso:country":"DE",
    "sg:address":"Lachnerstr. 34",
    "sg:city":"M\u00fcnchen",
    "sg:phone":"+49 89/1784423",
    "sg:postcode":"80639",
    "sg:province":"Bayern",
    "wof:name":"Bui Beteiligungs- Und Investitions Gmbh",
    "wof:placetype":"venue"
},
  "geometry": {"coordinates":[11.523213,48.153889],"type":"Point"}
}