{
  "type": "Feature",
  "properties": {
    "iso:country":"DE",
    "sg:address":"Steinenbergstr. 46",
    "sg:city":"Reutlingen",
    "sg:phone":"+49 7121/26990",
    "sg:postcode":"72764",
    "sg:province":"Baden-W\u00fcrttemberg",
    "wof:name":"Wks Waagen Kassen Software Gmbh",
    "wof:placetype":"venue"
},
  "geometry": {"coordinates":[9.2165336609,48.4830093384],"type":"Point"}
}