{
  "type": "Feature",
  "properties": {
    "iso:country":"DE",
    "sg:address":"Alpenstr. 13",
    "sg:city":"Starnberg",
    "sg:phone":"+49 8151/3193",
    "sg:postcode":"82319",
    "sg:province":"Bayern",
    "wof:name":"Cyberware Gmbh",
    "wof:placetype":"venue"
},
  "geometry": {"coordinates":[11.3157329559,47.9986495972],"type":"Point"}
}