{
  "type": "Feature",
  "properties": {
    "iso:country":"DE",
    "sg:address":"Bachstr. 16",
    "sg:city":"Geislingen",
    "sg:phone":"+49 7433/8565",
    "sg:postcode":"72351",
    "sg:province":"Baden-W\u00fcrttemberg",
    "wof:name":"Klinkerstuben",
    "wof:placetype":"venue"
},
  "geometry": {"coordinates":[8.8103103638,48.28723526],"type":"Point"}
}