{
  "type": "Feature",
  "properties": {
    "iso:country":"DE",
    "sg:address":"L\u00fcbberstr. 12 - 20",
    "sg:city":"Herford",
    "sg:phone":"+49 5221/10440",
    "sg:postcode":"32052",
    "sg:province":"Nordrhein-Westfalen",
    "wof:name":"Pottharst Kg",
    "wof:placetype":"venue"
},
  "geometry": {"coordinates":[8.676293,52.117096],"type":"Point"}
}