{
  "type": "Feature",
  "properties": {
    "iso:country":"DE",
    "sg:address":"Vahlzener Str. 7",
    "sg:city":"Neuenkirchen",
    "sg:phone":"+49 5195/1342",
    "sg:postcode":"29643",
    "sg:province":"Niedersachsen",
    "wof:name":"Horst Br\u00fcggemann Architekt",
    "wof:placetype":"venue"
},
  "geometry": {"coordinates":[9.741263,53.066059],"type":"Point"}
}