{
  "type": "Feature",
  "properties": {
    "iso:country":"DE",
    "sg:address":"Postweg 47",
    "sg:city":"Herzebrock-Clarholz",
    "sg:phone":"+49 5245/2357",
    "sg:postcode":"33442",
    "sg:province":"Nordrhein-Westfalen",
    "wof:name":"Joseph Suren",
    "wof:placetype":"venue"
},
  "geometry": {"coordinates":[8.22882,51.88829],"type":"Point"}
}