{
  "type": "Feature",
  "properties": {
    "iso:country":"DE",
    "sg:address":"Klosterstr. 17",
    "sg:city":"Marienfeld",
    "sg:phone":"+49 5247/79020",
    "sg:postcode":"33428",
    "sg:province":"Nordrhein-Westfalen",
    "wof:name":"Maison Internationale Einrichtungen Gmbh & Co.",
    "wof:placetype":"venue"
},
  "geometry": {"coordinates":[8.2843370438,51.9477272034],"type":"Point"}
}