{
  "type": "Feature",
  "properties": {
    "iso:country":"DE",
    "sg:address":"Ronheider Berg 250",
    "sg:city":"Aachen",
    "sg:phone":"+49 241/705750",
    "sg:postcode":"52076",
    "sg:province":"Nordrhein-Westfalen",
    "wof:name":"Richard Golm",
    "wof:placetype":"venue"
},
  "geometry": {"coordinates":[6.0661001205,50.7470169067],"type":"Point"}
}