{
  "type": "Feature",
  "properties": {
    "iso:country":"DE",
    "sg:address":"Schumannweg 1",
    "sg:city":"Hannover",
    "sg:phone":"+49 511/9585928",
    "sg:postcode":"30629",
    "sg:province":"Niedersachsen",
    "wof:name":"Maico Immobilien Gmbh",
    "wof:placetype":"venue"
},
  "geometry": {"coordinates":[9.8470525742,52.3948631287],"type":"Point"}
}