{
  "type": "Feature",
  "properties": {
    "iso:country":"DE",
    "sg:address":"Am Markt 8",
    "sg:city":"Richtenberg",
    "sg:phone":"+49 38322/235",
    "sg:postcode":"18461",
    "sg:province":"Mecklenburg-Vorpommern",
    "wof:name":"Markt Apotheke Richtenberg G\u00fcnter Schultz",
    "wof:placetype":"venue"
},
  "geometry": {"coordinates":[12.885922,54.20071],"type":"Point"}
}