{
  "type": "Feature",
  "properties": {
    "iso:country":"DE",
    "sg:address":"Bartholom\u00e4usweg 35",
    "sg:city":"G\u00fctersloh",
    "sg:phone":"+49 5241/48353",
    "sg:postcode":"33334",
    "sg:province":"Nordrhein-Westfalen",
    "wof:name":"Multimedia A Eins Produktions Gmbh & Co. Kg",
    "wof:placetype":"venue"
},
  "geometry": {"coordinates":[8.4460716248,51.882144928],"type":"Point"}
}