{
  "type": "Feature",
  "properties": {
    "iso:country":"DE",
    "sg:address":"Kennedyallee 107 a",
    "sg:city":"Frankfurt",
    "sg:phone":"+49 69/637094",
    "sg:postcode":"60596",
    "sg:province":"Hessen",
    "wof:name":"Redaktion Absolut V & P Verlag",
    "wof:placetype":"venue"
},
  "geometry": {"coordinates":[8.6677217484,50.0948944092],"type":"Point"}
}