{
  "type": "Feature",
  "properties": {
    "iso:country":"DE",
    "sg:address":"Beusselstr. 44 N-Q",
    "sg:city":"Berlin",
    "sg:phone":"+49 4930/3951064",
    "sg:postcode":"10553",
    "sg:province":"Berlin",
    "wof:name":"Beyer Fleisch Gert Beyer Gmbh",
    "wof:placetype":"venue"
},
  "geometry": {"coordinates":[13.3201503754,52.5288505554],"type":"Point"}
}