{
  "type": "Feature",
  "properties": {
    "iso:country":"DE",
    "sg:address":"Burgunderstr. 35",
    "sg:city":"D\u00fcsseldorf",
    "sg:phone":"+49 211/568360",
    "sg:postcode":"40549",
    "sg:province":"Nordrhein-Westfalen",
    "wof:name":"Lhs Leasing-handels- Und Service-gmbh",
    "wof:placetype":"venue"
},
  "geometry": {"coordinates":[6.6985759735,51.2269325256],"type":"Point"}
}