{
  "type": "Feature",
  "properties": {
    "iso:country":"DE",
    "sg:address":"Donaustr. 1",
    "sg:city":"Backnang",
    "sg:phone":"+49 7191/72525",
    "sg:postcode":"71522",
    "sg:province":"Baden-W\u00fcrttemberg",
    "wof:name":"Megacom Fachmarkt F\u00fcr Unterhaltungs-",
    "wof:placetype":"venue"
},
  "geometry": {"coordinates":[9.4286689758,48.9155426025],"type":"Point"}
}