{
  "type": "Feature",
  "properties": {
    "iso:country":"DE",
    "sg:address":"Bachstr. 15",
    "sg:city":"Dernau",
    "sg:phone":"+49 2643/1660",
    "sg:postcode":"53507",
    "sg:province":"Rheinland-Pfalz",
    "wof:name":"Bruno Nietgen",
    "wof:placetype":"venue"
},
  "geometry": {"coordinates":[7.0427350998,50.5344276428],"type":"Point"}
}