{
  "type": "Feature",
  "properties": {
    "iso:country":"DE",
    "sg:address":"Bremer Str. 89",
    "sg:city":"N\u00fcrnberg",
    "sg:postcode":"90451",
    "sg:province":"Bayern",
    "wof:name":"Enron Metall Recycling Gmbh & Co. Kg",
    "wof:placetype":"venue"
},
  "geometry": {"coordinates":[11.0610141754,49.3977127075],"type":"Point"}
}