{
  "type": "Feature",
  "properties": {
    "iso:country":"DE",
    "sg:address":"Oststr. 20",
    "sg:city":"Kerken",
    "sg:phone":"+49 2833/2795",
    "sg:postcode":"47647",
    "sg:province":"Nordrhein-Westfalen",
    "wof:name":"Klaus Kleinmanns",
    "wof:placetype":"venue"
},
  "geometry": {"coordinates":[6.3744668961,51.4598884583],"type":"Point"}
}