{
  "type": "Feature",
  "properties": {
    "iso:country":"DE",
    "sg:address":"Ostfeldstr. 26",
    "sg:city":"Hannover",
    "sg:phone":"+49 511/511006",
    "sg:postcode":"30559",
    "sg:province":"Niedersachsen",
    "wof:name":"Pms Project-management- Service Gmbh",
    "wof:placetype":"venue"
},
  "geometry": {"coordinates":[9.833021,52.358536],"type":"Point"}
}