{
  "type": "Feature",
  "properties": {
    "iso:country":"DE",
    "sg:address":"Westenstr. 23",
    "sg:city":"Eichst\u00e4tt",
    "sg:phone":"+49 8421/3798",
    "sg:postcode":"85072",
    "sg:province":"Bayern",
    "wof:name":"Gazelle Gertraud Fallenbacher",
    "wof:placetype":"venue"
},
  "geometry": {"coordinates":[11.182691,48.894703],"type":"Point"}
}