{
  "type": "Feature",
  "properties": {
    "iso:country":"DE",
    "sg:address":"Salmstr. 14",
    "sg:city":"Stolberg",
    "sg:phone":"+49 2402/84814",
    "sg:postcode":"52222",
    "sg:province":"Nordrhein-Westfalen",
    "wof:name":"Esraf Uzun",
    "wof:placetype":"venue"
},
  "geometry": {"coordinates":[6.2235188484,50.7767219543],"type":"Point"}
}