{
  "type": "Feature",
  "properties": {
    "iso:country":"DE",
    "sg:address":"Hauptstr. 39",
    "sg:city":"Rammenau",
    "sg:postcode":"01877",
    "sg:province":"Sachsen",
    "wof:name":"Live Treff",
    "wof:placetype":"venue"
},
  "geometry": {"coordinates":[14.1324672699,51.1520042419],"type":"Point"}
}