{
  "type": "Feature",
  "properties": {
    "iso:country":"DE",
    "sg:address":"Herzogplatz 12",
    "sg:city":"Zorneding",
    "sg:phone":"+49 8106/22140",
    "sg:postcode":"85604",
    "sg:province":"Bayern",
    "wof:name":"Gebr. Scholz",
    "wof:placetype":"venue"
},
  "geometry": {"coordinates":[11.832702,48.086506],"type":"Point"}
}