{
  "type": "Feature",
  "properties": {
    "iso:country":"DE",
    "sg:address":"Neuburger Str. 27",
    "sg:city":"Augsburg",
    "sg:phone":"+49 821/790780",
    "sg:postcode":"86167",
    "sg:province":"Bayern",
    "wof:name":"Gerhard Gaca Steuerberater",
    "wof:placetype":"venue"
},
  "geometry": {"coordinates":[10.9147529602,48.3795394897],"type":"Point"}
}