{
  "type": "Feature",
  "properties": {
    "iso:country":"DE",
    "sg:address":"M\u00fchlenfeldstr. 69",
    "sg:city":"Bremen",
    "sg:phone":"+49 421/259164",
    "sg:postcode":"28355",
    "sg:province":"Bremen",
    "wof:name":"Bernd Kaars Architekt",
    "wof:placetype":"venue"
},
  "geometry": {"coordinates":[8.940169,53.083904],"type":"Point"}
}