{
  "type": "Feature",
  "properties": {
    "iso:country":"DE",
    "sg:address":"K\u00f6nigstr. 21",
    "sg:city":"Telgte",
    "sg:phone":"+49 2504/3847",
    "sg:postcode":"48291",
    "sg:province":"Nordrhein-Westfalen",
    "wof:name":"M. Klefisch",
    "wof:placetype":"venue"
},
  "geometry": {"coordinates":[7.784375,51.984005],"type":"Point"}
}