{
  "type": "Feature",
  "properties": {
    "iso:country":"DE",
    "sg:address":"Speyerer Str. 32",
    "sg:city":"Harthausen",
    "sg:phone":"+49 4963/442051",
    "sg:postcode":"67376",
    "sg:province":"Rheinland-Pfalz",
    "wof:name":"Volksbank Raiffeisenbank Eg",
    "wof:placetype":"venue"
},
  "geometry": {"coordinates":[8.347302,49.295601],"type":"Point"}
}