{
  "type": "Feature",
  "properties": {
    "iso:country":"DE",
    "sg:address":"Hermann-M\u00fcller-Str. 6-10",
    "sg:city":"Georgsmarienh\u00fctte",
    "sg:phone":"+49 5401/43336",
    "sg:postcode":"49124",
    "sg:province":"Niedersachsen",
    "wof:name":"Feuerwerk-vorlights",
    "wof:placetype":"venue"
},
  "geometry": {"coordinates":[8.051374,52.205692],"type":"Point"}
}