{
  "type": "Feature",
  "properties": {
    "iso:country":"DE",
    "sg:address":"Friedrich-Ebert-Str.",
    "sg:city":"Bergisch Gladbach",
    "sg:postcode":"51429",
    "sg:province":"Nordrhein-Westfalen",
    "wof:name":"Vysis Gmbh",
    "wof:placetype":"venue"
},
  "geometry": {"coordinates":[7.1847300529,50.9594345093],"type":"Point"}
}