{
  "type": "Feature",
  "properties": {
    "iso:country":"DE",
    "sg:address":"Kreuzstr. 4",
    "sg:city":"Langg\u00f6ns",
    "sg:phone":"+49 6447/886737",
    "sg:postcode":"35428",
    "sg:province":"Hessen",
    "wof:name":"Kleebachstuben",
    "wof:placetype":"venue"
},
  "geometry": {"coordinates":[8.6159133911,50.4764823914],"type":"Point"}
}