{
  "type": "Feature",
  "properties": {
    "iso:country":"DE",
    "sg:address":"Klixdorf 32",
    "sg:city":"Kempen",
    "sg:phone":"+49 2152/50550",
    "sg:postcode":"47906",
    "sg:province":"Nordrhein-Westfalen",
    "wof:name":"Robert Schneider",
    "wof:placetype":"venue"
},
  "geometry": {"coordinates":[6.3822507858,51.3521652222],"type":"Point"}
}