{
  "type": "Feature",
  "properties": {
    "iso:country":"DE",
    "sg:address":"Karl-Schurz-Str. 15",
    "sg:city":"Fulda",
    "sg:phone":"+49 661/79377",
    "sg:postcode":"36041",
    "sg:province":"Hessen",
    "wof:name":"Klaus Gabriel",
    "wof:placetype":"venue"
},
  "geometry": {"coordinates":[9.6513929367,50.5555381775],"type":"Point"}
}