{
  "type": "Feature",
  "properties": {
    "iso:country":"DE",
    "sg:address":"Oberdorf 10",
    "sg:city":"Olsberg",
    "sg:phone":"+49 2962/748",
    "sg:postcode":"59939",
    "sg:province":"Nordrhein-Westfalen",
    "wof:name":"Pension Berthold Kraft",
    "wof:placetype":"venue"
},
  "geometry": {"coordinates":[8.4661970139,51.3745613098],"type":"Point"}
}