{
  "type": "Feature",
  "properties": {
    "iso:country":"DE",
    "sg:address":"Asternweg 7",
    "sg:city":"Rommerskirchen",
    "sg:phone":"+49 2183/7527",
    "sg:postcode":"41569",
    "sg:province":"Nordrhein-Westfalen",
    "wof:name":"Willi Wingerath",
    "wof:placetype":"venue"
},
  "geometry": {"coordinates":[6.689181,51.034672],"type":"Point"}
}