{
  "type": "Feature",
  "properties": {
    "iso:country":"DE",
    "sg:address":"Zur Marburg 12",
    "sg:city":"Oelde",
    "sg:phone":"+49 2529/1082",
    "sg:postcode":"59302",
    "sg:province":"Nordrhein-Westfalen",
    "wof:name":"Josef Windh\u00f6vel",
    "wof:placetype":"venue"
},
  "geometry": {"coordinates":[8.2225170135,51.8146324158],"type":"Point"}
}