{
  "type": "Feature",
  "properties": {
    "iso:country":"DE",
    "sg:address":"Puschkinallee 16",
    "sg:city":"Potsdam",
    "sg:phone":"+49 331/2701521",
    "sg:postcode":"14469",
    "sg:province":"Brandenburg",
    "wof:name":"Naherholungsbetrieb Potsdam",
    "wof:placetype":"venue"
},
  "geometry": {"coordinates":[13.0590763092,52.4154891968],"type":"Point"}
}