{
  "type": "Feature",
  "properties": {
    "iso:country":"DE",
    "sg:address":"August-Bebel-Str. 5",
    "sg:city":"Wandlitz",
    "sg:phone":"+49 33397/21239",
    "sg:postcode":"16348",
    "sg:province":"Brandenburg",
    "wof:name":"Raumhaus B\u00fcroeinrichtungen Gmbh",
    "wof:placetype":"venue"
},
  "geometry": {"coordinates":[13.4589071274,52.7654418945],"type":"Point"}
}