{
  "type": "Feature",
  "properties": {
    "iso:country":"DE",
    "sg:address":"Kurt-Fischer-Str. 47",
    "sg:city":"Ahrensburg",
    "sg:postcode":"22926",
    "sg:province":"Schleswig-Holstein",
    "wof:name":"Dach Sanit\u00e4r Handel Eg",
    "wof:placetype":"venue"
},
  "geometry": {"coordinates":[10.25971,53.692276],"type":"Point"}
}