{
  "type": "Feature",
  "properties": {
    "iso:country":"DE",
    "sg:address":"Waldstr. 10",
    "sg:city":"Belgern",
    "sg:phone":"+49 34224/40350",
    "sg:postcode":"04874",
    "sg:province":"Sachsen",
    "wof:name":"Jochen Werner",
    "wof:placetype":"venue"
},
  "geometry": {"coordinates":[13.11709,51.483398],"type":"Point"}
}