{
  "type": "Feature",
  "properties": {
    "iso:country":"DE",
    "sg:address":"Am Klingelbach",
    "sg:city":"Bad Berleburg",
    "sg:phone":"+49 2751/7358",
    "sg:postcode":"57319",
    "sg:province":"Nordrhein-Westfalen",
    "wof:name":"Pension Fritz-gustav Kr\u00e4mer",
    "wof:placetype":"venue"
},
  "geometry": {"coordinates":[8.3860473633,51.0439605713],"type":"Point"}
}