{
  "type": "Feature",
  "properties": {
    "iso:country":"DE",
    "sg:address":"Hauptstr. 26",
    "sg:city":"Niederschlettenbach",
    "sg:phone":"+49 6394/233",
    "sg:postcode":"76891",
    "sg:province":"Rheinland-Pfalz",
    "wof:name":"T. Frey",
    "wof:placetype":"venue"
},
  "geometry": {"coordinates":[7.8454399109,49.0874290466],"type":"Point"}
}