{
  "type": "Feature",
  "properties": {
    "iso:country":"DE",
    "sg:address":"Georgistr. 97",
    "sg:city":"Chemnitz",
    "sg:phone":"+49 371/774570",
    "sg:postcode":"09127",
    "sg:province":"Sachsen",
    "wof:name":"Raue Bautr\u00e4ger Und Immobilien Gmbh",
    "wof:placetype":"venue"
},
  "geometry": {"coordinates":[12.9821472168,50.8139457703],"type":"Point"}
}