{
  "type": "Feature",
  "properties": {
    "iso:country":"DE",
    "sg:address":"Ber\u00dfener Str. 39",
    "sg:city":"S\u00f6gel",
    "sg:phone":"+49 5952/428",
    "sg:postcode":"49751",
    "sg:province":"Niedersachsen",
    "wof:name":"Bernhard Steinbild",
    "wof:placetype":"venue"
},
  "geometry": {"coordinates":[7.5087161064,52.8338737488],"type":"Point"}
}