{
  "type": "Feature",
  "properties": {
    "iso:country":"DE",
    "sg:address":"M\u00f6hlstr. 23",
    "sg:city":"M\u00fcnchen",
    "sg:postcode":"81675",
    "sg:province":"Bayern",
    "wof:name":"Innomotive Beteiligung Ag",
    "wof:placetype":"venue"
},
  "geometry": {"coordinates":[11.600526,48.14484],"type":"Point"}
}