{
  "type": "Feature",
  "properties": {
    "iso:country":"DE",
    "sg:address":"Basaltstr. 56",
    "sg:city":"Frankfurt",
    "sg:phone":"+49 69/771026",
    "sg:postcode":"60487",
    "sg:province":"Hessen",
    "wof:name":"R. Miller",
    "wof:placetype":"venue"
},
  "geometry": {"coordinates":[8.6446695328,50.1259002686],"type":"Point"}
}