{
  "type": "Feature",
  "properties": {
    "iso:country":"DE",
    "sg:address":"Obere Kirchstr. 9",
    "sg:city":"Oelsnitz",
    "sg:postcode":"08606",
    "sg:province":"Sachsen",
    "wof:name":"Elstertal Reisen Gmbh",
    "wof:placetype":"venue"
},
  "geometry": {"coordinates":[12.1708202362,50.4146728516],"type":"Point"}
}