{
  "type": "Feature",
  "properties": {
    "iso:country":"DE",
    "sg:address":"Petersberg 3",
    "sg:city":"Mallersdorf-Pfaffenberg",
    "sg:phone":"+49 8772/351",
    "sg:postcode":"84066",
    "sg:province":"Bayern",
    "wof:name":"Franz Volkmann",
    "wof:placetype":"venue"
},
  "geometry": {"coordinates":[12.245145,48.775753],"type":"Point"}
}