{
  "type": "Feature",
  "properties": {
    "iso:country":"DE",
    "sg:address":"Bochumer Str. 54",
    "sg:city":"Herne",
    "sg:phone":"+49 2323/46370",
    "sg:postcode":"44623",
    "sg:province":"Nordrhein-Westfalen",
    "wof:name":"Deutscher Supermarkt Handel Gmbh",
    "wof:placetype":"venue"
},
  "geometry": {"coordinates":[7.2235212326,51.5325698853],"type":"Point"}
}