{
  "type": "Feature",
  "properties": {
    "iso:country":"DE",
    "sg:address":"Wittener Str. 125",
    "sg:city":"Gevelsberg",
    "sg:phone":"+49 2332/10753",
    "sg:postcode":"58285",
    "sg:province":"Nordrhein-Westfalen",
    "wof:name":"Olympic-grill",
    "wof:placetype":"venue"
},
  "geometry": {"coordinates":[7.3352389336,51.3288497925],"type":"Point"}
}