{
  "type": "Feature",
  "properties": {
    "iso:country":"DE",
    "sg:address":"B\u00e4ckerfenne 9",
    "sg:city":"Braderup",
    "sg:phone":"+49 4663/999",
    "sg:postcode":"25923",
    "sg:province":"Schleswig-Holstein",
    "wof:name":"Mollenhauer Grundst\u00fccksgesellschaft Mbh",
    "wof:placetype":"venue"
},
  "geometry": {"coordinates":[8.881412,54.837917],"type":"Point"}
}