{
  "type": "Feature",
  "properties": {
    "iso:country":"DE",
    "sg:address":"Eisenbahnstr. 53",
    "sg:city":"W\u00fcrzburg",
    "sg:postcode":"97084",
    "sg:province":"Bayern",
    "wof:name":"Consult Aktiv Gmbh",
    "wof:placetype":"venue"
},
  "geometry": {"coordinates":[9.9623117447,49.7588729858],"type":"Point"}
}