{
  "type": "Feature",
  "properties": {
    "iso:country":"DE",
    "sg:address":"Am G\u00fclser Bootshafen 31",
    "sg:city":"Koblenz",
    "sg:phone":"+49 261/46249",
    "sg:postcode":"56072",
    "sg:province":"Rheinland-Pfalz",
    "wof:name":"Hotel-restaurant Sporthafen",
    "wof:placetype":"venue"
},
  "geometry": {"coordinates":[7.5551109314,50.3346099854],"type":"Point"}
}