{
  "type": "Feature",
  "properties": {
    "iso:country":"DE",
    "sg:address":"Uelzener Str. 36",
    "sg:city":"L\u00fcneburg",
    "sg:phone":"+49 4131/43504",
    "sg:postcode":"21335",
    "sg:province":"Niedersachsen",
    "wof:name":"Regina Warncke",
    "wof:placetype":"venue"
},
  "geometry": {"coordinates":[10.404702,53.23777],"type":"Point"}
}