{
  "type": "Feature",
  "properties": {
    "iso:country":"DE",
    "sg:address":"Eckernf\u00f6rder Str. 246",
    "sg:city":"Kronshagen",
    "sg:phone":"+49 431/542176",
    "sg:postcode":"24119",
    "sg:province":"Schleswig-Holstein",
    "wof:name":"M. Wolters",
    "wof:placetype":"venue"
},
  "geometry": {"coordinates":[10.100319,54.342838],"type":"Point"}
}