{
  "type": "Feature",
  "properties": {
    "iso:country":"DE",
    "sg:address":"Hof 6",
    "sg:city":"Reinsdorf",
    "sg:phone":"+49 375/617457",
    "sg:postcode":"08141",
    "sg:province":"Sachsen",
    "wof:name":"Siegfried Lorenz",
    "wof:placetype":"venue"
},
  "geometry": {"coordinates":[12.53939,50.677261],"type":"Point"}
}