{
  "type": "Feature",
  "properties": {
    "iso:country":"DE",
    "sg:address":"Liebst\u00e4dter Str. 4",
    "sg:city":"Pirna",
    "sg:phone":"+49 3501/527771",
    "sg:postcode":"01796",
    "sg:province":"Sachsen",
    "wof:name":"Bernhard Koch",
    "wof:placetype":"venue"
},
  "geometry": {"coordinates":[13.926883,50.941078],"type":"Point"}
}