{
  "type": "Feature",
  "properties": {
    "iso:country":"DE",
    "sg:address":"Dudenstr. 8 a",
    "sg:city":"Bad Hersfeld",
    "sg:phone":"+49 6621/65955",
    "sg:postcode":"36251",
    "sg:province":"Hessen",
    "wof:name":"Erich Beisheim Rechtsanwalt",
    "wof:placetype":"venue"
},
  "geometry": {"coordinates":[9.7116832733,50.8686561584],"type":"Point"}
}