{
  "type": "Feature",
  "properties": {
    "iso:country":"DE",
    "sg:address":"Bessemerstr. 7",
    "sg:city":"Chemnitz",
    "sg:phone":"+49 371/850271",
    "sg:postcode":"09116",
    "sg:province":"Sachsen",
    "wof:name":"Mwk Werkzeug- Und Vorrichtungsbau Gmbh",
    "wof:placetype":"venue"
},
  "geometry": {"coordinates":[12.8624753952,50.8186950684],"type":"Point"}
}