{
  "type": "Feature",
  "properties": {
    "iso:country":"DE",
    "sg:address":"Dammtorstr. 32",
    "sg:city":"Hamburg",
    "sg:postcode":"20354",
    "sg:province":"Hamburg",
    "wof:name":"Arbeca Verm\u00f6gens- Verwaltungs Gmbh",
    "wof:placetype":"venue"
},
  "geometry": {"coordinates":[9.9880552292,53.5560798645],"type":"Point"}
}