{
  "type": "Feature",
  "properties": {
    "iso:country":"DE",
    "sg:address":"Pivitsheider Str. 51",
    "sg:city":"Augustdorf",
    "sg:phone":"+49 5237/7929",
    "sg:postcode":"32832",
    "sg:province":"Nordrhein-Westfalen",
    "wof:name":"Wilhelm Rehm",
    "wof:placetype":"venue"
},
  "geometry": {"coordinates":[8.741756,51.90947],"type":"Point"}
}