{
  "type": "Feature",
  "properties": {
    "iso:country":"DE",
    "sg:address":"Rosenweg 2",
    "sg:city":"Willingshausen",
    "sg:phone":"+49 6697/1212",
    "sg:postcode":"34628",
    "sg:province":"Hessen",
    "wof:name":"Wilhelm B\u00e4tz",
    "wof:placetype":"venue"
},
  "geometry": {"coordinates":[9.2265,50.852539],"type":"Point"}
}