{
  "type": "Feature",
  "properties": {
    "iso:country":"DE",
    "sg:address":"Bonner Str. 19",
    "sg:city":"D\u00fcsseldorf",
    "sg:phone":"+49 211/790689",
    "sg:postcode":"40589",
    "sg:province":"Nordrhein-Westfalen",
    "wof:name":"G. Ebrahimzadeh",
    "wof:placetype":"venue"
},
  "geometry": {"coordinates":[6.8351278305,51.1750183105],"type":"Point"}
}