{
  "type": "Feature",
  "properties": {
    "iso:country":"DE",
    "sg:address":"Deutschherrenstr. 63",
    "sg:city":"Zeltingen-Rachtig",
    "sg:phone":"+49 6532/690",
    "sg:postcode":"54492",
    "sg:province":"Rheinland-Pfalz",
    "wof:name":"Pazen Gmbh Fenster-u. T\u00fcren-",
    "wof:placetype":"venue"
},
  "geometry": {"coordinates":[7.002261,49.96582],"type":"Point"}
}