{
  "type": "Feature",
  "properties": {
    "iso:country":"DE",
    "sg:address":"Borngasse 24",
    "sg:city":"Rotenburg",
    "sg:phone":"+49 6623/2758",
    "sg:postcode":"36199",
    "sg:province":"Hessen",
    "wof:name":"Kurt Martens",
    "wof:placetype":"venue"
},
  "geometry": {"coordinates":[9.7196073532,50.994354248],"type":"Point"}
}