{
  "type": "Feature",
  "properties": {
    "iso:country":"DE",
    "sg:address":"Bliesgaustr. 111",
    "sg:city":"Blieskastel",
    "sg:phone":"+49 6842/5941",
    "sg:postcode":"66440",
    "sg:province":"Saarland",
    "wof:name":"Ewald Schwartz",
    "wof:placetype":"venue"
},
  "geometry": {"coordinates":[7.259815,49.243069],"type":"Point"}
}