{
  "type": "Feature",
  "properties": {
    "iso:country":"DE",
    "sg:address":"Pastor-Blume-Str. 15",
    "sg:city":"Pausa",
    "sg:phone":"+49 37432/7660",
    "sg:postcode":"07952",
    "sg:province":"Sachsen",
    "wof:name":"Dr. Klaus Rudolph Tierarzt",
    "wof:placetype":"venue"
},
  "geometry": {"coordinates":[12.011556,50.589432],"type":"Point"}
}