{
  "type": "Feature",
  "properties": {
    "iso:country":"DE",
    "sg:address":"R\u00f6merstr. 12",
    "sg:city":"Bad Vilbel",
    "sg:phone":"+49 6101/1457",
    "sg:postcode":"61118",
    "sg:province":"Hessen",
    "wof:name":"Ochs Gmbh",
    "wof:placetype":"venue"
},
  "geometry": {"coordinates":[8.734992981,50.1733207703],"type":"Point"}
}