{
  "type": "Feature",
  "properties": {
    "iso:country":"DE",
    "sg:address":"Kapellenstr. 43",
    "sg:city":"Herzebrock-Clarholz",
    "sg:phone":"+49 5245/2479",
    "sg:postcode":"33442",
    "sg:province":"Nordrhein-Westfalen",
    "wof:name":"Ludger Heiringhoff",
    "wof:placetype":"venue"
},
  "geometry": {"coordinates":[8.207849,51.861572],"type":"Point"}
}