{
  "type": "Feature",
  "properties": {
    "iso:country":"DE",
    "sg:address":"Martin-Schmei\u00dfer-Weg 18",
    "sg:city":"Dortmund",
    "sg:phone":"+49 231/71080",
    "sg:postcode":"44227",
    "sg:province":"Nordrhein-Westfalen",
    "wof:name":"Unterst\u00fctzungskasse Der Firma Schreck-mieves Gmbh",
    "wof:placetype":"venue"
},
  "geometry": {"coordinates":[7.4037208557,51.4892501831],"type":"Point"}
}