{
  "type": "Feature",
  "properties": {
    "iso:country":"DE",
    "sg:address":"Wei\u00dfm\u00fchlweg 14",
    "sg:city":"Undenheim",
    "sg:phone":"+49 6737/1355",
    "sg:postcode":"55278",
    "sg:province":"Rheinland-Pfalz",
    "wof:name":"Renate Escher",
    "wof:placetype":"venue"
},
  "geometry": {"coordinates":[8.2192058563,49.8372993469],"type":"Point"}
}