{
  "type": "Feature",
  "properties": {
    "iso:country":"DE",
    "sg:address":"Schilden 12",
    "sg:city":"Metelen",
    "sg:phone":"+49 2556/1631",
    "sg:postcode":"48629",
    "sg:province":"Nordrhein-Westfalen",
    "wof:name":"Bistro Filou",
    "wof:placetype":"venue"
},
  "geometry": {"coordinates":[7.2122130394,52.1444091797],"type":"Point"}
}