{
  "type": "Feature",
  "properties": {
    "iso:country":"DE",
    "sg:address":"Kolpingstr. 30",
    "sg:city":"L\u00e4hden",
    "sg:phone":"+49 5964/1636",
    "sg:postcode":"49774",
    "sg:province":"Niedersachsen",
    "wof:name":"B. Bookschulte",
    "wof:placetype":"venue"
},
  "geometry": {"coordinates":[7.56296,52.737595],"type":"Point"}
}