{
  "type": "Feature",
  "properties": {
    "iso:country":"DE",
    "sg:address":"Graf-Stauffenberg-Str. 14",
    "sg:city":"Alzey",
    "sg:phone":"+49 6731/3414",
    "sg:postcode":"55232",
    "sg:province":"Rheinland-Pfalz",
    "wof:name":"Marcus Ferichs",
    "wof:placetype":"venue"
},
  "geometry": {"coordinates":[8.0972356796,49.7390174866],"type":"Point"}
}