{
  "type": "Feature",
  "properties": {
    "iso:country":"DE",
    "sg:address":"Carlstr 50",
    "sg:city":"\u00dcbach-Palenberg",
    "sg:phone":"+49 2451/9710",
    "sg:postcode":"52531",
    "sg:province":"Nordrhein-Westfalen",
    "wof:name":"Carolus-magnus-centrum F\u00fcr Umwelttechnologie \u00dcbach-palenberg Gmbh",
    "wof:placetype":"venue"
},
  "geometry": {"coordinates":[6.109935,50.925056],"type":"Point"}
}