{
  "type": "Feature",
  "properties": {
    "iso:country":"DE",
    "sg:address":"Gierenstr. 37",
    "sg:city":"Wegberg",
    "sg:phone":"+49 2434/3623",
    "sg:postcode":"41844",
    "sg:province":"Nordrhein-Westfalen",
    "wof:name":"Me\u00df-regelungstechnik Scholz Gmbh",
    "wof:placetype":"venue"
},
  "geometry": {"coordinates":[6.2748208046,51.1350975037],"type":"Point"}
}