{
  "type": "Feature",
  "properties": {
    "iso:country":"DE",
    "sg:address":"M\u00fcnnerst\u00e4dter Str. 9",
    "sg:city":"N\u00fcdlingen",
    "sg:phone":"+49 971/98004",
    "sg:postcode":"97720",
    "sg:province":"Bayern",
    "wof:name":"P. D\u00f6pfert Finanzberater",
    "wof:placetype":"venue"
},
  "geometry": {"coordinates":[10.1253900528,50.2209815979],"type":"Point"}
}