{
  "type": "Feature",
  "properties": {
    "iso:country":"DE",
    "sg:address":"H\u00f6henblick 8",
    "sg:city":"Glash\u00fctten",
    "sg:phone":"+49 6174/62972",
    "sg:postcode":"61479",
    "sg:province":"Hessen",
    "wof:name":"Nord-form Handels Gmbh",
    "wof:placetype":"venue"
},
  "geometry": {"coordinates":[8.4062738419,50.2197418213],"type":"Point"}
}