{
  "type": "Feature",
  "properties": {
    "iso:country":"DE",
    "sg:address":"Slevogtstr. 6",
    "sg:city":"Heidelberg",
    "sg:postcode":"69126",
    "sg:province":"Baden-W\u00fcrttemberg",
    "wof:name":"Mhc Grundst\u00fccksverwaltung Gmbh",
    "wof:placetype":"venue"
},
  "geometry": {"coordinates":[8.6890163422,49.3941307068],"type":"Point"}
}