{
  "type": "Feature",
  "properties": {
    "iso:country":"DE",
    "sg:address":"Alfred-Hess-Str. 22",
    "sg:city":"Erfurt",
    "sg:postcode":"99094",
    "sg:province":"Th\u00fcringen",
    "wof:name":"Solimedia Productions Gmbh",
    "wof:placetype":"venue"
},
  "geometry": {"coordinates":[11.012178421,50.9698295593],"type":"Point"}
}