{
  "type": "Feature",
  "properties": {
    "iso:country":"DE",
    "sg:address":"An den Weiden 150",
    "sg:city":"R\u00fcsselsheim",
    "sg:postcode":"65428",
    "sg:province":"Hessen",
    "wof:name":"Treber Gmbh & Co. Grundst\u00fccks- Und Maschinen-",
    "wof:placetype":"venue"
},
  "geometry": {"coordinates":[8.44985,49.993549],"type":"Point"}
}