{
  "type": "Feature",
  "properties": {
    "iso:country":"DE",
    "sg:address":"Im Steinb\u00f6hl 10",
    "sg:city":"Maxdorf",
    "sg:phone":"+49 6237/6275",
    "sg:postcode":"67133",
    "sg:province":"Rheinland-Pfalz",
    "wof:name":"Bertl Drumm",
    "wof:placetype":"venue"
},
  "geometry": {"coordinates":[8.3037996292,49.4860610962],"type":"Point"}
}