{
  "type": "Feature",
  "properties": {
    "iso:country":"DE",
    "sg:address":"Rathenaustr. 8",
    "sg:city":"Delitzsch",
    "sg:phone":"+49 34202/90307",
    "sg:postcode":"04509",
    "sg:province":"Sachsen",
    "wof:name":"Pigors - Huelsenbeck",
    "wof:placetype":"venue"
},
  "geometry": {"coordinates":[12.352259,51.529148],"type":"Point"}
}