{
  "type": "Feature",
  "properties": {
    "iso:country":"DE",
    "sg:address":"Schlo\u00dfweg 11",
    "sg:city":"N\u00fcrtingen",
    "sg:phone":"+49 7022/5050",
    "sg:postcode":"72622",
    "sg:province":"Baden-W\u00fcrttemberg",
    "wof:name":"Altenwohn- Und Pflegeheim Dr.-v\u00f6hringer-heim",
    "wof:placetype":"venue"
},
  "geometry": {"coordinates":[9.327487,48.636387],"type":"Point"}
}