{
  "type": "Feature",
  "properties": {
    "iso:country":"DE",
    "sg:address":"Langeler Damm 107",
    "sg:city":"K\u00f6ln",
    "sg:phone":"+49 221/5343672",
    "sg:postcode":"50769",
    "sg:province":"Nordrhein-Westfalen",
    "wof:name":"Hubert Salamon Hydrauliktechnik",
    "wof:placetype":"venue"
},
  "geometry": {"coordinates":[6.8706698418,51.0647239685],"type":"Point"}
}