{
  "type": "Feature",
  "properties": {
    "iso:country":"DE",
    "sg:address":"Eilenburger Str. 36a",
    "sg:city":"Delitzsch",
    "sg:postcode":"04509",
    "sg:province":"Sachsen",
    "wof:name":"S. R. Adam",
    "wof:placetype":"venue"
},
  "geometry": {"coordinates":[12.3390655518,51.5236816406],"type":"Point"}
}