{
  "type": "Feature",
  "properties": {
    "iso:country":"DE",
    "sg:address":"Talstr. 30",
    "sg:city":"Braunfels",
    "sg:phone":"+49 6445/7147",
    "sg:postcode":"35619",
    "sg:province":"Hessen",
    "wof:name":"W. Dinges",
    "wof:placetype":"venue"
},
  "geometry": {"coordinates":[8.437132,50.480728],"type":"Point"}
}