{
  "type": "Feature",
  "properties": {
    "iso:country":"DE",
    "sg:address":"Roderbirken",
    "sg:city":"Leichlingen",
    "sg:phone":"+49 2175/8201",
    "sg:postcode":"42799",
    "sg:province":"Nordrhein-Westfalen",
    "wof:name":"Landesversicherungsanstalt Rheinprovinz",
    "wof:placetype":"venue"
},
  "geometry": {"coordinates":[7.0372800827,51.10546875],"type":"Point"}
}