{
  "type": "Feature",
  "properties": {
    "iso:country":"DE",
    "sg:address":"Mitterfeldstr. 3",
    "sg:city":"Hunderdorf",
    "sg:phone":"+49 9422/6349",
    "sg:postcode":"94336",
    "sg:province":"Bayern",
    "wof:name":"K. Menacher",
    "wof:placetype":"venue"
},
  "geometry": {"coordinates":[12.7255725861,48.9401855469],"type":"Point"}
}