{
  "type": "Feature",
  "properties": {
    "iso:country":"DE",
    "sg:address":"Mosacherweg 36",
    "sg:city":"Amberg",
    "sg:phone":"+49 9621/760490",
    "sg:postcode":"92224",
    "sg:province":"Bayern",
    "wof:name":"Sf Grundst\u00fccksverwaltungs Gmbh",
    "wof:placetype":"venue"
},
  "geometry": {"coordinates":[11.883975029,49.440612793],"type":"Point"}
}