{
  "type": "Feature",
  "properties": {
    "iso:country":"DE",
    "sg:address":"Gustav-Adolf-Str. 9",
    "sg:city":"L\u00fcbeck",
    "sg:phone":"+49 451/33131",
    "sg:postcode":"23568",
    "sg:province":"Schleswig-Holstein",
    "wof:name":"Peter Klempin Rechtsanwalt Und Notar",
    "wof:placetype":"venue"
},
  "geometry": {"coordinates":[10.7077541351,53.8779525757],"type":"Point"}
}