{
  "type": "Feature",
  "properties": {
    "iso:country":"DE",
    "sg:address":"Guntherstr. 134",
    "sg:city":"Braunschweig",
    "sg:phone":"+49 531/329412",
    "sg:postcode":"38112",
    "sg:province":"Niedersachsen",
    "wof:name":"H. Nadjib Ingenieur",
    "wof:placetype":"venue"
},
  "geometry": {"coordinates":[10.5271024704,52.2889480591],"type":"Point"}
}