{
  "type": "Feature",
  "properties": {
    "iso:country":"DE",
    "sg:address":"G\u00fcterstr. 49",
    "sg:city":"Wilhelmshaven",
    "sg:phone":"+49 4421/745110",
    "sg:postcode":"26389",
    "sg:province":"Niedersachsen",
    "wof:name":"Wilfried Vollstaedt",
    "wof:placetype":"venue"
},
  "geometry": {"coordinates":[8.0736560822,53.5219192505],"type":"Point"}
}