{
  "type": "Feature",
  "properties": {
    "iso:country":"DE",
    "sg:address":"K\u00f6lner Tor 6",
    "sg:city":"Siegen",
    "sg:phone":"+49 271/24229",
    "sg:postcode":"57072",
    "sg:province":"Nordrhein-Westfalen",
    "wof:name":"Hilfswerk Der Deutschen Lions E. V.",
    "wof:placetype":"venue"
},
  "geometry": {"coordinates":[8.0200195312,50.8744697571],"type":"Point"}
}