{
  "type": "Feature",
  "properties": {
    "iso:country":"DE",
    "sg:address":"M\u00fchlenhagen 35",
    "sg:city":"Hamburg",
    "sg:phone":"+49 40/781050",
    "sg:postcode":"20539",
    "sg:province":"Hamburg",
    "wof:name":"Albis Plastic Gmbh",
    "wof:placetype":"venue"
},
  "geometry": {"coordinates":[10.0556192398,53.5409317017],"type":"Point"}
}