{
  "type": "Feature",
  "properties": {
    "iso:country":"DE",
    "sg:address":"Saarower Chaussee 34",
    "sg:city":"F\u00fcrstenwalde",
    "sg:phone":"+49 3361/301267",
    "sg:postcode":"15517",
    "sg:province":"Brandenburg",
    "wof:name":"H. Heinz Immobilienmakler",
    "wof:placetype":"venue"
},
  "geometry": {"coordinates":[14.078250885,52.3289031982],"type":"Point"}
}