{
  "type": "Feature",
  "properties": {
    "iso:country":"DE",
    "sg:address":"Leimgruben 3",
    "sg:city":"Kirchdorf",
    "sg:phone":"+49 8085/450",
    "sg:postcode":"83527",
    "sg:province":"Bayern",
    "wof:name":"Johann Kr\u00e4mer",
    "wof:placetype":"venue"
},
  "geometry": {"coordinates":[12.197309,48.210091],"type":"Point"}
}