{
  "type": "Feature",
  "properties": {
    "iso:country":"DE",
    "sg:address":"Gie\u00dfener Landstr. 2",
    "sg:city":"Lohra",
    "sg:phone":"+49 6426/237",
    "sg:postcode":"35102",
    "sg:province":"Hessen",
    "wof:name":"F. & R. G\u00e4rtner",
    "wof:placetype":"venue"
},
  "geometry": {"coordinates":[8.6083650589,50.6872940063],"type":"Point"}
}