{
  "type": "Feature",
  "properties": {
    "iso:country":"DE",
    "sg:address":"Karl-Marx-Str. 28 A",
    "sg:city":"Bickenbach",
    "sg:phone":"+49 6257/903139",
    "sg:postcode":"64404",
    "sg:province":"Hessen",
    "wof:name":"G. Stark",
    "wof:placetype":"venue"
},
  "geometry": {"coordinates":[8.613477,49.74934],"type":"Point"}
}