{
  "type": "Feature",
  "properties": {
    "iso:country":"DE",
    "sg:address":"Pfeifferstr. 7",
    "sg:city":"Rheinzabern",
    "sg:postcode":"76764",
    "sg:province":"Rheinland-Pfalz",
    "wof:name":"Old San Antonio",
    "wof:placetype":"venue"
},
  "geometry": {"coordinates":[8.2701339722,49.1144790649],"type":"Point"}
}