{
  "type": "Feature",
  "properties": {
    "iso:country":"DE",
    "sg:address":"Unter dem Griesberg 3",
    "sg:city":"Mechernich",
    "sg:phone":"+49 2443/6025",
    "sg:postcode":"53894",
    "sg:province":"Nordrhein-Westfalen",
    "wof:name":"A. Ch. Werner Ingenieur",
    "wof:placetype":"venue"
},
  "geometry": {"coordinates":[6.6466870308,50.6065254211],"type":"Point"}
}