{
  "type": "Feature",
  "properties": {
    "iso:country":"DE",
    "sg:address":"Holtermannstr. 18",
    "sg:city":"Stade",
    "sg:phone":"+49 4141/65533",
    "sg:postcode":"21680",
    "sg:province":"Niedersachsen",
    "wof:name":"Ursula Syring Masseurin",
    "wof:placetype":"venue"
},
  "geometry": {"coordinates":[9.475863,53.59153],"type":"Point"}
}