{
  "type": "Feature",
  "properties": {
    "iso:country":"DE",
    "sg:address":"Gewerbepark 9",
    "sg:city":"Thyrnau",
    "sg:phone":"+49 8501/1333",
    "sg:postcode":"94136",
    "sg:province":"Bayern",
    "wof:name":"Wero-industrieanlagen- Und Rohrleitungsbau Gmbh",
    "wof:placetype":"venue"
},
  "geometry": {"coordinates":[13.5349988937,48.6043128967],"type":"Point"}
}