{
  "type": "Feature",
  "properties": {
    "iso:country":"DE",
    "sg:address":"Am Kleinwald 13",
    "sg:city":"Herxheim",
    "sg:phone":"+49 4972/7696690",
    "sg:postcode":"76863",
    "sg:province":"Rheinland-Pfalz",
    "wof:name":"Delta Dore Schlueter Gmbh",
    "wof:placetype":"venue"
},
  "geometry": {"coordinates":[8.226727,49.140282],"type":"Point"}
}