{
  "type": "Feature",
  "properties": {
    "iso:country":"DE",
    "sg:address":"Vo\u00dfheide 9",
    "sg:city":"Halle",
    "sg:phone":"+49 5201/665284",
    "sg:postcode":"33790",
    "sg:province":"Nordrhein-Westfalen",
    "wof:name":"H. Sch\u00f6nemann",
    "wof:placetype":"venue"
},
  "geometry": {"coordinates":[8.287232399,52.035610199],"type":"Point"}
}