{
  "type": "Feature",
  "properties": {
    "iso:country":"DE",
    "sg:address":"An der B 5",
    "sg:city":"Wusterhausen",
    "sg:phone":"+49 33979/515",
    "sg:postcode":"16868",
    "sg:province":"Brandenburg",
    "wof:name":"Minol Gmbh",
    "wof:placetype":"venue"
},
  "geometry": {"coordinates":[12.462187767,52.8906173706],"type":"Point"}
}