{
  "type": "Feature",
  "properties": {
    "iso:country":"DE",
    "sg:address":"Bargteheider Str. 81",
    "sg:city":"Hamburg",
    "sg:phone":"+49 40/6473450",
    "sg:postcode":"22143",
    "sg:province":"Hamburg",
    "wof:name":"R\u00f6hrig Laedke Gmbh",
    "wof:placetype":"venue"
},
  "geometry": {"coordinates":[10.145874,53.603256],"type":"Point"}
}