{
  "type": "Feature",
  "properties": {
    "iso:country":"DE",
    "sg:address":"Langenhainer Str. 99",
    "sg:city":"Wehretal",
    "sg:phone":"+49 5651/4360",
    "sg:postcode":"37287",
    "sg:province":"Hessen",
    "wof:name":"Gerd K\u00f6hler",
    "wof:placetype":"venue"
},
  "geometry": {"coordinates":[10.011882,51.146088],"type":"Point"}
}