{
  "type": "Feature",
  "properties": {
    "iso:country":"DE",
    "sg:address":"Burgunderweg 6",
    "sg:city":"Hardthausen",
    "sg:phone":"+49 7139/6595",
    "sg:postcode":"74239",
    "sg:province":"Baden-W\u00fcrttemberg",
    "wof:name":"G. Wagemann",
    "wof:placetype":"venue"
},
  "geometry": {"coordinates":[9.3989295959,49.2454528809],"type":"Point"}
}