{
  "type": "Feature",
  "properties": {
    "iso:country":"DE",
    "sg:address":"Wichertstr. 63",
    "sg:city":"Berlin",
    "sg:phone":"+49 30/4440422",
    "sg:postcode":"10439",
    "sg:province":"Berlin",
    "wof:name":"Gastst\u00e4tte Voland",
    "wof:placetype":"venue"
},
  "geometry": {"coordinates":[13.4185190201,52.549747467],"type":"Point"}
}