{
  "type": "Feature",
  "properties": {
    "iso:country":"DE",
    "sg:address":"Lambertimarkt 18",
    "sg:city":"Nettetal",
    "sg:phone":"+49 2153/71485",
    "sg:postcode":"41334",
    "sg:province":"Nordrhein-Westfalen",
    "wof:name":"M. K\u00f6nigs",
    "wof:placetype":"venue"
},
  "geometry": {"coordinates":[6.2475662231,51.2981681824],"type":"Point"}
}