{
  "type": "Feature",
  "properties": {
    "iso:country":"DE",
    "sg:address":"Bremer Str. 23",
    "sg:city":"Hamburg",
    "sg:phone":"+49 40/778022",
    "sg:postcode":"21073",
    "sg:province":"Hamburg",
    "wof:name":"Eva M. Stadler",
    "wof:placetype":"venue"
},
  "geometry": {"coordinates":[9.9790754318,53.4567298889],"type":"Point"}
}