{
  "type": "Feature",
  "properties": {
    "iso:country":"DE",
    "sg:address":"H\u00f6henweg 8",
    "sg:city":"Seevetal",
    "sg:phone":"+49 4105/80976",
    "sg:postcode":"21220",
    "sg:province":"Niedersachsen",
    "wof:name":"Volker Tegeler Ingenieur",
    "wof:placetype":"venue"
},
  "geometry": {"coordinates":[10.0240516663,53.3747901917],"type":"Point"}
}