{
  "type": "Feature",
  "properties": {
    "iso:country":"DE",
    "sg:address":"Industriestr. 20",
    "sg:city":"Heddesheim",
    "sg:phone":"+49 6203/45201",
    "sg:postcode":"68542",
    "sg:province":"Baden-W\u00fcrttemberg",
    "wof:name":"Siracusa Gmbh",
    "wof:placetype":"venue"
},
  "geometry": {"coordinates":[8.6257324219,49.5066223145],"type":"Point"}
}