{
  "type": "Feature",
  "properties": {
    "iso:country":"DE",
    "sg:address":"Oberneulander Landstr. 123",
    "sg:city":"Bremen",
    "sg:phone":"+49 421/168077",
    "sg:postcode":"28355",
    "sg:province":"Bremen",
    "wof:name":"Intracom De Edv-beratung Gerhard Rutkowski",
    "wof:placetype":"venue"
},
  "geometry": {"coordinates":[8.9232788086,53.0988388062],"type":"Point"}
}