{
  "type": "Feature",
  "properties": {
    "iso:country":"DE",
    "sg:address":"Herm\u00fclheimer Str. 41",
    "sg:city":"H\u00fcrth",
    "sg:phone":"+49 2233/33247",
    "sg:postcode":"50354",
    "sg:province":"Nordrhein-Westfalen",
    "wof:name":"Burg-apotheke",
    "wof:placetype":"venue"
},
  "geometry": {"coordinates":[6.84751,50.886681],"type":"Point"}
}