{
  "type": "Feature",
  "properties": {
    "iso:country":"DE",
    "sg:address":"Oberer Markt 2",
    "sg:city":"Nabburg",
    "sg:phone":"+49 9433/9603",
    "sg:postcode":"92507",
    "sg:province":"Bayern",
    "wof:name":"Pl\u00f6ssl Gmbh B\u00e4ckerei Und Konditorei",
    "wof:placetype":"venue"
},
  "geometry": {"coordinates":[12.180949,49.453583],"type":"Point"}
}