{
  "type": "Feature",
  "properties": {
    "iso:country":"DE",
    "sg:address":"Charlottenstr. 61",
    "sg:city":"K\u00f6ln",
    "sg:phone":"+49 2203/17050",
    "sg:postcode":"51149",
    "sg:province":"Nordrhein-Westfalen",
    "wof:name":"Eastmann Chemical Deutschland Gmbh",
    "wof:placetype":"venue"
},
  "geometry": {"coordinates":[7.0298490524,50.9047775269],"type":"Point"}
}