{
  "type": "Feature",
  "properties": {
    "iso:country":"DE",
    "sg:address":"Am B\u00f6rdegarten 3",
    "sg:city":"Magdeburg",
    "sg:phone":"+49 391/7223640",
    "sg:postcode":"39128",
    "sg:province":"Sachsen-Anhalt",
    "wof:name":"Kemmlit Bauelemente Gmbh",
    "wof:placetype":"venue"
},
  "geometry": {"coordinates":[11.605753,52.152637],"type":"Point"}
}