{
  "type": "Feature",
  "properties": {
    "iso:country":"DE",
    "sg:address":"Schirnbornweg 7",
    "sg:city":"Kronberg",
    "sg:postcode":"61476",
    "sg:province":"Hessen",
    "wof:name":"Mass Trade Gmbh",
    "wof:placetype":"venue"
},
  "geometry": {"coordinates":[8.5033273697,50.1909065247],"type":"Point"}
}