{
  "type": "Feature",
  "properties": {
    "iso:country":"DE",
    "sg:address":"S\u00e4ntisweg 16",
    "sg:city":"Kressbronn",
    "sg:phone":"+49 7543/96060",
    "sg:postcode":"88079",
    "sg:province":"Baden-W\u00fcrttemberg",
    "wof:name":"Hwg Telekommunikations- Systeme Gmbh",
    "wof:placetype":"venue"
},
  "geometry": {"coordinates":[9.5902490616,47.5990066528],"type":"Point"}
}