{
  "type": "Feature",
  "properties": {
    "iso:country":"DE",
    "sg:address":"In der Gartenstr. 12",
    "sg:city":"Waldeck",
    "sg:phone":"+49 5623/5105",
    "sg:postcode":"34513",
    "sg:province":"Hessen",
    "wof:name":"G\u00e4stehaus Angela",
    "wof:placetype":"venue"
},
  "geometry": {"coordinates":[9.0676460266,51.2056884766],"type":"Point"}
}