{
  "type": "Feature",
  "properties": {
    "iso:country":"DE",
    "sg:address":"Dr.-Zinn-Weg 5a",
    "sg:city":"Eberswalde",
    "sg:phone":"+49 3334/23096",
    "sg:postcode":"16225",
    "sg:province":"Brandenburg",
    "wof:name":"Dr. Ehrenreich Lemke Tierarzt",
    "wof:placetype":"venue"
},
  "geometry": {"coordinates":[13.8311567307,52.8534317017],"type":"Point"}
}