{
  "type": "Feature",
  "properties": {
    "iso:country":"DE",
    "sg:address":"Mei\u00dfner Str 475",
    "sg:city":"Radebeul",
    "sg:phone":"+49 351/8399999",
    "sg:postcode":"01445",
    "sg:province":"Sachsen",
    "wof:name":"Gebr. Uibrig Gmbh",
    "wof:placetype":"venue"
},
  "geometry": {"coordinates":[13.5994901657,51.11977005],"type":"Point"}
}