{
  "type": "Feature",
  "properties": {
    "iso:country":"DE",
    "sg:address":"Bahnhofstr. 50",
    "sg:city":"Neunkirchen",
    "sg:phone":"+49 6821/23947",
    "sg:postcode":"66538",
    "sg:province":"Saarland",
    "wof:name":"Wiener Hendl Grill Inh. Manfred Winter",
    "wof:placetype":"venue"
},
  "geometry": {"coordinates":[7.1740651131,49.3495826721],"type":"Point"}
}