{
  "type": "Feature",
  "properties": {
    "iso:country":"DE",
    "sg:address":"K\u00f6rnerstr. 14",
    "sg:city":"L\u00f6rrach",
    "sg:phone":"+49 7621/10387",
    "sg:postcode":"79539",
    "sg:province":"Baden-W\u00fcrttemberg",
    "wof:name":"Fahrrad Sb Markt Gmbh",
    "wof:placetype":"venue"
},
  "geometry": {"coordinates":[7.65835,47.615742],"type":"Point"}
}