{
  "type": "Feature",
  "properties": {
    "iso:country":"DE",
    "sg:address":"Hemsack 43",
    "sg:city":"Kamen",
    "sg:phone":"+49 2307/9727921",
    "sg:postcode":"59174",
    "sg:province":"Nordrhein-Westfalen",
    "wof:name":"Objekt Id Planungs- Und Beratungsges. F\u00fcr Innen-",
    "wof:placetype":"venue"
},
  "geometry": {"coordinates":[7.644416,51.583672],"type":"Point"}
}