{
  "type": "Feature",
  "properties": {
    "iso:country":"DE",
    "sg:address":"Fette Henn 38",
    "sg:city":"Krefeld",
    "sg:phone":"+49 2151/733376",
    "sg:postcode":"47839",
    "sg:province":"Nordrhein-Westfalen",
    "wof:name":"G. Salms",
    "wof:placetype":"venue"
},
  "geometry": {"coordinates":[6.51292,51.376198],"type":"Point"}
}