{
  "type": "Feature",
  "properties": {
    "iso:country":"DE",
    "sg:address":"du pont",
    "sg:city":"bordeau",
    "sg:postcode":"33000",
    "wof:name":"Soswindows",
    "wof:placetype":"venue"
},
  "geometry": {"coordinates":[-94.868423,35.115616],"type":"Point"}
}