{
  "type": "Feature",
  "properties": {
    "iso:country":"DE",
    "sg:address":"Kilianstr. 10",
    "sg:city":"Bietigheim-Bissingen",
    "sg:phone":"+49 7142/30000",
    "sg:postcode":"74321",
    "sg:province":"Baden-W\u00fcrttemberg",
    "wof:name":"Sebastiano Puzzo",
    "wof:placetype":"venue"
},
  "geometry": {"coordinates":[9.0948390961,48.947593689],"type":"Point"}
}