{
  "type": "Feature",
  "properties": {
    "iso:country":"DE",
    "sg:address":"D\u00fcrener Str. 66",
    "sg:city":"Geilenkirchen",
    "sg:phone":"+49 2451/2868",
    "sg:postcode":"52511",
    "sg:province":"Nordrhein-Westfalen",
    "wof:name":"Willy Strank",
    "wof:placetype":"venue"
},
  "geometry": {"coordinates":[6.1706318855,50.9515724182],"type":"Point"}
}