{
  "type": "Feature",
  "properties": {
    "iso:country":"DE",
    "sg:address":"Weidm\u00fchlenstr. 4",
    "sg:city":"D\u00fcren",
    "sg:phone":"+49 2421/81107",
    "sg:postcode":"52353",
    "sg:province":"Nordrhein-Westfalen",
    "wof:name":"Anton Esser",
    "wof:placetype":"venue"
},
  "geometry": {"coordinates":[6.417588,50.828186],"type":"Point"}
}