{
  "type": "Feature",
  "properties": {
    "iso:country":"DE",
    "sg:address":"Gereonstr. 62a",
    "sg:city":"Kreuzau",
    "sg:phone":"+49 2427/6172",
    "sg:postcode":"52372",
    "sg:province":"Nordrhein-Westfalen",
    "wof:name":"Katholisches Pfarramt St. Gereon",
    "wof:placetype":"venue"
},
  "geometry": {"coordinates":[6.4975848198,50.7151832581],"type":"Point"}
}