{
  "type": "Feature",
  "properties": {
    "iso:country":"DE",
    "sg:address":"Lerchenstr. 6",
    "sg:city":"Burgwedel",
    "sg:phone":"+49 5139/7242",
    "sg:postcode":"30938",
    "sg:province":"Niedersachsen",
    "wof:name":"Fritz Bruns Gmbh",
    "wof:placetype":"venue"
},
  "geometry": {"coordinates":[9.871673584,52.510433197],"type":"Point"}
}