{
  "type": "Feature",
  "properties": {
    "iso:country":"DE",
    "sg:address":"Alter Markt 2",
    "sg:city":"Euskirchen",
    "sg:phone":"+49 2251/74748",
    "sg:postcode":"53879",
    "sg:province":"Nordrhein-Westfalen",
    "wof:name":"Linda",
    "wof:placetype":"venue"
},
  "geometry": {"coordinates":[6.787608,50.661053],"type":"Point"}
}