{
  "type": "Feature",
  "properties": {
    "iso:country":"DE",
    "sg:address":"Am Hangkamp 11",
    "sg:city":"M\u00fcnster",
    "sg:phone":"+49 251/216329",
    "sg:postcode":"48157",
    "sg:province":"Nordrhein-Westfalen",
    "wof:name":"Josef G\u00f6vert Ingenieur",
    "wof:placetype":"venue"
},
  "geometry": {"coordinates":[7.6224651337,52.0435295105],"type":"Point"}
}