{
  "type": "Feature",
  "properties": {
    "iso:country":"DE",
    "sg:address":"Mozartstr. 52",
    "sg:city":"Osnabr\u00fcck",
    "sg:phone":"+49 541/434407",
    "sg:postcode":"49076",
    "sg:province":"Niedersachsen",
    "wof:name":"M. Bode",
    "wof:placetype":"venue"
},
  "geometry": {"coordinates":[8.012861,52.279408],"type":"Point"}
}