{
  "type": "Feature",
  "properties": {
    "iso:country":"DE",
    "sg:address":"Unter dem Stiderfeld 39",
    "sg:city":"Rinteln",
    "sg:phone":"+49 5751/5556",
    "sg:postcode":"31737",
    "sg:province":"Niedersachsen",
    "wof:name":"Martin Ludwig Glas Und Porzellanwaren",
    "wof:placetype":"venue"
},
  "geometry": {"coordinates":[9.0888566971,52.1996498108],"type":"Point"}
}