{
  "type": "Feature",
  "properties": {
    "iso:country":"DE",
    "sg:address":"Hauptstr. 11 B",
    "sg:city":"Bockelwitz",
    "sg:phone":"+49 34321/2470",
    "sg:postcode":"04703",
    "sg:province":"Sachsen",
    "wof:name":"Hermann Eulitz",
    "wof:placetype":"venue"
},
  "geometry": {"coordinates":[12.9868993759,51.1840553284],"type":"Point"}
}