{
  "type": "Feature",
  "properties": {
    "iso:country":"DE",
    "sg:address":"Falkenburg",
    "sg:city":"Hohenwestedt",
    "sg:phone":"+49 4871/8710",
    "sg:postcode":"24594",
    "sg:province":"Schleswig-Holstein",
    "wof:name":"Ferienhauspark Falkenburg - Schleswig-holstein",
    "wof:placetype":"venue"
},
  "geometry": {"coordinates":[9.66524,54.104591],"type":"Point"}
}