{
  "type": "Feature",
  "properties": {
    "iso:country":"DE",
    "sg:address":"Neckarstr. 5",
    "sg:city":"Lorsch",
    "sg:phone":"+49 6251/96250",
    "sg:postcode":"64653",
    "sg:province":"Hessen",
    "wof:name":"Stadthaus-apotheke",
    "wof:placetype":"venue"
},
  "geometry": {"coordinates":[8.566714,49.651859],"type":"Point"}
}