{
  "type": "Feature",
  "properties": {
    "iso:country":"DE",
    "sg:address":"Am Kirchplatz 8",
    "sg:city":"Kelkheim",
    "sg:phone":"+49 6195/3803",
    "sg:postcode":"65779",
    "sg:province":"Hessen",
    "wof:name":"H. Zelser",
    "wof:placetype":"venue"
},
  "geometry": {"coordinates":[8.4648323059,50.1262130737],"type":"Point"}
}