{
  "type": "Feature",
  "properties": {
    "iso:country":"DE",
    "sg:address":"Marktplatz 4",
    "sg:city":"Geisenhausen",
    "sg:phone":"+49 8743/96070",
    "sg:postcode":"84144",
    "sg:province":"Bayern",
    "wof:name":"Mariahilf-apotheke Geisenhaus. Inh. Roselies L\u00fcneburg Aothek.",
    "wof:placetype":"venue"
},
  "geometry": {"coordinates":[12.257638,48.473293],"type":"Point"}
}