{
  "type": "Feature",
  "properties": {
    "iso:country":"DE",
    "sg:address":"Weberstr.37 / Ecke Kaiserstr.",
    "sg:city":"Bonn",
    "sg:phone":"+49 228/241614",
    "sg:postcode":"53115",
    "sg:province":"Nordrhein-Westfalen",
    "wof:name":"Orpheus Im Alten Weinkeller",
    "wof:placetype":"venue"
},
  "geometry": {"coordinates":[7.1016950607,50.7322998047],"type":"Point"}
}