{
  "type": "Feature",
  "properties": {
    "iso:country":"DE",
    "sg:address":"Untereisselner Str. 1",
    "sg:city":"Heikendorf",
    "sg:phone":"+49 431/242392",
    "sg:postcode":"24226",
    "sg:province":"Schleswig-Holstein",
    "wof:name":"Dr. Manfred Eduard Lubs Tierarzt",
    "wof:placetype":"venue"
},
  "geometry": {"coordinates":[10.2092151642,54.3772087097],"type":"Point"}
}