{
  "type": "Feature",
  "properties": {
    "iso:country":"DE",
    "sg:address":"Linsenberg 22",
    "sg:city":"Offenbach",
    "sg:phone":"+49 69/9824980",
    "sg:postcode":"63065",
    "sg:province":"Hessen",
    "wof:name":"Landeszentralbank In Hessen",
    "wof:placetype":"venue"
},
  "geometry": {"coordinates":[8.7592411041,50.1089935303],"type":"Point"}
}