{
  "type": "Feature",
  "properties": {
    "iso:country":"DE",
    "sg:address":"Schwalbenweg 24",
    "sg:city":"Delbr\u00fcck",
    "sg:phone":"+49 5250/98430",
    "sg:postcode":"33129",
    "sg:province":"Nordrhein-Westfalen",
    "wof:name":"G. Hartmann Maschinenbau Gmbh",
    "wof:placetype":"venue"
},
  "geometry": {"coordinates":[8.550451,51.758438],"type":"Point"}
}