{
  "type": "Feature",
  "properties": {
    "iso:country":"DE",
    "sg:address":"Promenade 57",
    "sg:city":"Ha\u00dffurt",
    "sg:phone":"+49 9521/1447",
    "sg:postcode":"97437",
    "sg:province":"Bayern",
    "wof:name":"P. Hart Lagerhaus",
    "wof:placetype":"venue"
},
  "geometry": {"coordinates":[10.503064,50.032597],"type":"Point"}
}