{
  "type": "Feature",
  "properties": {
    "iso:country":"DE",
    "sg:address":"Am Stadtgarten 1",
    "sg:city":"Karlsruhe",
    "sg:phone":"+49 721/932300",
    "sg:postcode":"76137",
    "sg:province":"Baden-W\u00fcrttemberg",
    "wof:name":"S & H Versicherungsmakler- Team Gmbh",
    "wof:placetype":"venue"
},
  "geometry": {"coordinates":[8.4037599564,48.9966812134],"type":"Point"}
}