{
  "type": "Feature",
  "properties": {
    "iso:country":"DE",
    "sg:address":"Schillerstr. 3",
    "sg:city":"Leipzig",
    "sg:phone":"+49 4934/169790",
    "sg:postcode":"04109",
    "sg:province":"Sachsen",
    "wof:name":"Volksbank Leipzig Eg",
    "wof:placetype":"venue"
},
  "geometry": {"coordinates":[12.376,51.336964],"type":"Point"}
}