{
  "type": "Feature",
  "properties": {
    "iso:country":"DE",
    "sg:address":"Haunsbergstr. 42",
    "sg:city":"Freilassing",
    "sg:phone":"+49 8654/479541",
    "sg:postcode":"83395",
    "sg:province":"Bayern",
    "wof:name":"Klaus Nagel Architekt",
    "wof:placetype":"venue"
},
  "geometry": {"coordinates":[12.969795,47.830307],"type":"Point"}
}