{
  "type": "Feature",
  "properties": {
    "iso:country":"DE",
    "sg:address":"Gerhart-Hauptmann-Str. 41",
    "sg:city":"Guben",
    "sg:phone":"+49 3561/53262",
    "sg:postcode":"03172",
    "sg:province":"Brandenburg",
    "wof:name":"Dat Pr\u00fcf- Und Sch\u00e4tzungsstelle",
    "wof:placetype":"venue"
},
  "geometry": {"coordinates":[14.666493,51.946819],"type":"Point"}
}