{
  "type": "Feature",
  "properties": {
    "iso:country":"DE",
    "sg:address":"Plutostr. 108",
    "sg:city":"Gelsenkirchen",
    "sg:phone":"+49 209/877088",
    "sg:postcode":"45888",
    "sg:province":"Nordrhein-Westfalen",
    "wof:name":"Volker Neumann",
    "wof:placetype":"venue"
},
  "geometry": {"coordinates":[7.1202020645,51.5230865479],"type":"Point"}
}