{
  "type": "Feature",
  "properties": {
    "iso:country":"DE",
    "sg:address":"Violinenstr. 4",
    "sg:city":"Dassel",
    "sg:phone":"+49 5562/453",
    "sg:postcode":"37586",
    "sg:province":"Niedersachsen",
    "wof:name":"Gerhard Melching",
    "wof:placetype":"venue"
},
  "geometry": {"coordinates":[9.6924352646,51.8015556335],"type":"Point"}
}