{
  "type": "Feature",
  "properties": {
    "iso:country":"DE",
    "sg:address":"Theodor-Heu\u00df-Str 18",
    "sg:city":"Linden",
    "sg:phone":"+49 6403/97900",
    "sg:postcode":"35440",
    "sg:province":"Hessen",
    "wof:name":"Primus Avitos Ag",
    "wof:placetype":"venue"
},
  "geometry": {"coordinates":[8.671158,50.526527],"type":"Point"}
}