{
  "type": "Feature",
  "properties": {
    "iso:country":"DE",
    "sg:address":"Ahornweg 6",
    "sg:city":"Pohlheim",
    "sg:phone":"+49 6404",
    "sg:postcode":"35415",
    "sg:province":"Hessen",
    "wof:name":"1a Design, Web-design, Re-design, Beratung,web-promo",
    "wof:placetype":"venue"
},
  "geometry": {"coordinates":[8.7531785965,50.5320320129],"type":"Point"}
}