{
  "type": "Feature",
  "properties": {
    "iso:country":"DE",
    "sg:address":"Goldgrabenstr. 9 a",
    "sg:city":"Hofheim",
    "sg:phone":"+49 6192/39245",
    "sg:postcode":"65719",
    "sg:province":"Hessen",
    "wof:name":"Wolfgang Ernst Ingenieur",
    "wof:placetype":"venue"
},
  "geometry": {"coordinates":[8.4283866882,50.0729904175],"type":"Point"}
}