{
  "type": "Feature",
  "properties": {
    "iso:country":"DE",
    "sg:address":"Donaustr. 15",
    "sg:city":"Falkensee",
    "sg:postcode":"14612",
    "sg:province":"Brandenburg",
    "wof:name":"S\u00e4uglings- Und Kleinst- Kinderheim",
    "wof:placetype":"venue"
},
  "geometry": {"coordinates":[13.074131012,52.5687065125],"type":"Point"}
}