{
  "type": "Feature",
  "properties": {
    "iso:country":"DE",
    "sg:address":"Hauptstr. 50",
    "sg:city":"Treuchtlingen",
    "sg:phone":"+49 9142/1266",
    "sg:postcode":"91757",
    "sg:province":"Bayern",
    "wof:name":"Ev. Luth. Pfarramt",
    "wof:placetype":"venue"
},
  "geometry": {"coordinates":[10.9085264206,48.955329895],"type":"Point"}
}