{
  "type": "Feature",
  "properties": {
    "iso:country":"DE",
    "sg:address":"Purkersdorfer Str. 59",
    "sg:city":"Bad S\u00e4ckingen",
    "sg:phone":"+49 7761/929990",
    "sg:postcode":"79713",
    "sg:province":"Baden-W\u00fcrttemberg",
    "wof:name":"S. F. Tr\u00f6ndle Ingenieur",
    "wof:placetype":"venue"
},
  "geometry": {"coordinates":[7.9496507645,47.5625190735],"type":"Point"}
}