{
  "type": "Feature",
  "properties": {
    "iso:country":"DE",
    "sg:address":"Naupliaallee 6",
    "sg:city":"Ottobrunn",
    "sg:phone":"+49 89/6098683",
    "sg:postcode":"85521",
    "sg:province":"Bayern",
    "wof:name":"Restaurant Villa Meraviglia",
    "wof:placetype":"venue"
},
  "geometry": {"coordinates":[11.6622161865,48.0643577576],"type":"Point"}
}