{
  "type": "Feature",
  "properties": {
    "iso:country":"DE",
    "sg:address":"Am Ried 15",
    "sg:city":"Spahl",
    "sg:phone":"+49 36967/51240",
    "sg:postcode":"36419",
    "sg:province":"Th\u00fcringen",
    "wof:name":"Kurierdienst /lastentaxi",
    "wof:placetype":"venue"
},
  "geometry": {"coordinates":[9.9109649658,50.6568450928],"type":"Point"}
}