{
  "type": "Feature",
  "properties": {
    "iso:country":"DE",
    "sg:address":"Kirchstr. 6",
    "sg:city":"Niederwiesa",
    "sg:phone":"+49 3726/2472",
    "sg:postcode":"09577",
    "sg:province":"Sachsen",
    "wof:name":"G. Biro",
    "wof:placetype":"venue"
},
  "geometry": {"coordinates":[13.016119957,50.8624992371],"type":"Point"}
}