{
  "type": "Feature",
  "properties": {
    "iso:country":"DE",
    "sg:address":"Dorfstr. 32",
    "sg:city":"Ummern",
    "sg:phone":"+49 5083/9120087",
    "sg:postcode":"29369",
    "sg:province":"Niedersachsen",
    "wof:name":"H. P. Moese Elektromeister",
    "wof:placetype":"venue"
},
  "geometry": {"coordinates":[10.437825,52.590767],"type":"Point"}
}