{
  "type": "Feature",
  "properties": {
    "iso:country":"DE",
    "sg:address":"Keltenstr 16",
    "sg:city":"Bruchk\u00f6bel",
    "sg:phone":"+49 6181/86764",
    "sg:postcode":"63486",
    "sg:province":"Hessen",
    "wof:name":"Hilberg & Partner Gmbh",
    "wof:placetype":"venue"
},
  "geometry": {"coordinates":[8.9098949432,50.1769943237],"type":"Point"}
}