{
  "type": "Feature",
  "properties": {
    "iso:country":"DE",
    "sg:address":"Charlottenstr. 190",
    "sg:city":"Heilbronn",
    "sg:phone":"+49 7131/253225",
    "sg:postcode":"74074",
    "sg:province":"Baden-W\u00fcrttemberg",
    "wof:name":"Greendoor",
    "wof:placetype":"venue"
},
  "geometry": {"coordinates":[9.216006279,49.1192550659],"type":"Point"}
}