{
  "type": "Feature",
  "properties": {
    "iso:country":"DE",
    "sg:address":"Im Gro\u00dfacker 48",
    "sg:city":"Merzhausen",
    "sg:phone":"+49 761/409361",
    "sg:postcode":"79249",
    "sg:province":"Baden-W\u00fcrttemberg",
    "wof:name":"R. G\u00fcntert Immobilienmakler",
    "wof:placetype":"venue"
},
  "geometry": {"coordinates":[7.8290700912,47.9703712463],"type":"Point"}
}