{
  "type": "Feature",
  "properties": {
    "iso:country":"DE",
    "sg:address":"Kaiserm\u00fchler Str. 21",
    "sg:city":"Gro\u00df Lindow",
    "sg:phone":"+49 33609/36783",
    "sg:postcode":"15295",
    "sg:province":"Brandenburg",
    "wof:name":"Waldsch\u00e4nke",
    "wof:placetype":"venue"
},
  "geometry": {"coordinates":[14.4772825241,52.2459030151],"type":"Point"}
}