{
  "type": "Feature",
  "properties": {
    "iso:country":"DE",
    "sg:address":"Bahnhofstr. 5",
    "sg:city":"Heidenau",
    "sg:phone":"+49 4182/4164",
    "sg:postcode":"21258",
    "sg:province":"Niedersachsen",
    "wof:name":"Hans-peter Detjen Zimmerei-s\u00e4gewerk Gmbh",
    "wof:placetype":"venue"
},
  "geometry": {"coordinates":[9.6508541107,53.3126869202],"type":"Point"}
}