{
  "type": "Feature",
  "properties": {
    "iso:country":"DE",
    "sg:address":"Feldweg 3",
    "sg:city":"Buschow",
    "sg:phone":"+49 33876/40214",
    "sg:postcode":"14715",
    "sg:province":"Brandenburg",
    "wof:name":"Biebers Fensterbau Gmbh",
    "wof:placetype":"venue"
},
  "geometry": {"coordinates":[12.31067,52.519508],"type":"Point"}
}