{
  "type": "Feature",
  "properties": {
    "iso:country":"DE",
    "sg:address":"Heerstr. 35",
    "sg:city":"Nettetal",
    "sg:phone":"+49 2157/6494",
    "sg:postcode":"41334",
    "sg:province":"Nordrhein-Westfalen",
    "wof:name":"Genenger-genneper",
    "wof:placetype":"venue"
},
  "geometry": {"coordinates":[6.219774,51.337204],"type":"Point"}
}