{
  "type": "Feature",
  "properties": {
    "iso:country":"DE",
    "sg:address":"Weidenweg 1",
    "sg:city":"Reisbach",
    "sg:phone":"+49 8734/515",
    "sg:postcode":"94419",
    "sg:province":"Bayern",
    "wof:name":"Albert Hammerstingl",
    "wof:placetype":"venue"
},
  "geometry": {"coordinates":[12.629788,48.576149],"type":"Point"}
}