{
  "type": "Feature",
  "properties": {
    "iso:country":"DE",
    "sg:address":"Dorfstr. 45",
    "sg:city":"Wallmow",
    "sg:phone":"+49 39862/2097",
    "sg:postcode":"17291",
    "sg:province":"Brandenburg",
    "wof:name":"Restaurant Dorfkrug",
    "wof:placetype":"venue"
},
  "geometry": {"coordinates":[14.1267852783,53.3230705261],"type":"Point"}
}