{
  "type": "Feature",
  "properties": {
    "iso:country":"DE",
    "sg:address":"Mintenweg 22",
    "sg:city":"Hennef",
    "sg:phone":"+49 2242/1422",
    "sg:postcode":"53773",
    "sg:province":"Nordrhein-Westfalen",
    "wof:name":"Ludwig Reuther",
    "wof:placetype":"venue"
},
  "geometry": {"coordinates":[7.237745,50.752567],"type":"Point"}
}