{
  "type": "Feature",
  "properties": {
    "iso:country":"DE",
    "sg:address":"Am Arnsbacher Pfad 8",
    "sg:city":"Usingen",
    "sg:phone":"+49 6081/67557",
    "sg:postcode":"61250",
    "sg:province":"Hessen",
    "wof:name":"Rolf Wegger",
    "wof:placetype":"venue"
},
  "geometry": {"coordinates":[8.522808075,50.3307991028],"type":"Point"}
}