{
  "type": "Feature",
  "properties": {
    "iso:country":"DE",
    "sg:address":"W\u00f6ssinger Str. 35",
    "sg:city":"K\u00f6nigsbach-Stein",
    "sg:postcode":"75203",
    "sg:province":"Baden-W\u00fcrttemberg",
    "wof:name":"Sww-speditions- Und Transport Gmbh",
    "wof:placetype":"venue"
},
  "geometry": {"coordinates":[8.6092977524,48.9686355591],"type":"Point"}
}