{
  "type": "Feature",
  "properties": {
    "iso:country":"DE",
    "sg:address":"K\u00f6nigslacherweg 2a",
    "sg:city":"Schrobenhausen",
    "sg:phone":"+49 8252/9130",
    "sg:postcode":"86529",
    "sg:province":"Bayern",
    "wof:name":"S\u00dcdstarke Gmbh",
    "wof:placetype":"venue"
},
  "geometry": {"coordinates":[11.264281,48.569469],"type":"Point"}
}