{
  "type": "Feature",
  "properties": {
    "iso:country":"DE",
    "sg:address":"K\u00fclken",
    "sg:city":"Bergenhusen",
    "sg:phone":"+49 4885/340",
    "sg:postcode":"24861",
    "sg:province":"Schleswig-Holstein",
    "wof:name":"Thomas J. Ingwersen",
    "wof:placetype":"venue"
},
  "geometry": {"coordinates":[9.307845,54.351425],"type":"Point"}
}