{
  "type": "Feature",
  "properties": {
    "iso:country":"DE",
    "sg:address":"Zum B\u00f6rneken",
    "sg:city":"Lehre",
    "sg:phone":"+49 5308/6053",
    "sg:postcode":"38165",
    "sg:province":"Niedersachsen",
    "wof:name":"Sportheim",
    "wof:placetype":"venue"
},
  "geometry": {"coordinates":[10.6675243378,52.3311843872],"type":"Point"}
}