{
  "type": "Feature",
  "properties": {
    "iso:country":"DE",
    "sg:address":"Haus Nr. 18",
    "sg:city":"Elmau",
    "sg:phone":"+49 8823/5017",
    "sg:postcode":"82493",
    "sg:province":"Bayern",
    "wof:name":"Alpengut Elmau Inh. John Brooke",
    "wof:placetype":"venue"
},
  "geometry": {"coordinates":[11.2392597198,47.4819984436],"type":"Point"}
}