{
  "type": "Feature",
  "properties": {
    "iso:country":"DE",
    "sg:address":"Agricolastr. 36",
    "sg:city":"M\u00fcnchen",
    "sg:phone":"+49 89/567287",
    "sg:postcode":"80686",
    "sg:province":"Bayern",
    "wof:name":"Rudolf Gantner Rechtsanwalt",
    "wof:placetype":"venue"
},
  "geometry": {"coordinates":[11.4919700623,48.1392059326],"type":"Point"}
}