{
  "type": "Feature",
  "properties": {
    "iso:country":"DE",
    "sg:address":"Winkel 4",
    "sg:city":"Mohlsdorf",
    "sg:postcode":"07987",
    "sg:province":"Th\u00fcringen",
    "wof:name":"A & K Handelsgesellschaft Mbh",
    "wof:placetype":"venue"
},
  "geometry": {"coordinates":[12.2794275284,50.6764259338],"type":"Point"}
}