{
  "type": "Feature",
  "properties": {
    "iso:country":"DE",
    "sg:address":"Ihringer Str. 2",
    "sg:city":"Breisach",
    "sg:phone":"+49 7668/308",
    "sg:postcode":"79206",
    "sg:province":"Baden-W\u00fcrttemberg",
    "wof:name":"Bernhard Sch\u00e4chtele",
    "wof:placetype":"venue"
},
  "geometry": {"coordinates":[7.582107,48.02821],"type":"Point"}
}