{
  "type": "Feature",
  "properties": {
    "iso:country":"DE",
    "sg:address":"Dieselstr 8",
    "sg:city":"Renningen",
    "sg:phone":"+49 7159/93130",
    "sg:postcode":"71272",
    "sg:province":"Baden-W\u00fcrttemberg",
    "wof:name":"Bernhard Holzinger",
    "wof:placetype":"venue"
},
  "geometry": {"coordinates":[8.899887085,48.7798538208],"type":"Point"}
}