{
  "type": "Feature",
  "properties": {
    "iso:country":"DE",
    "sg:address":"Lorettostr. 6",
    "sg:city":"Freiburg",
    "sg:phone":"+49 761/74616",
    "sg:postcode":"79100",
    "sg:province":"Baden-W\u00fcrttemberg",
    "wof:name":"Willi Genzler Pressephotograph",
    "wof:placetype":"venue"
},
  "geometry": {"coordinates":[7.8457660675,47.9848022461],"type":"Point"}
}