{
  "type": "Feature",
  "properties": {
    "iso:country":"DE",
    "sg:address":"Papingsweg 11",
    "sg:city":"Diepholz",
    "sg:phone":"+49 5441/2188",
    "sg:postcode":"49356",
    "sg:province":"Niedersachsen",
    "wof:name":"Curt Kosiol",
    "wof:placetype":"venue"
},
  "geometry": {"coordinates":[8.3933916092,52.6196289062],"type":"Point"}
}