{
  "type": "Feature",
  "properties": {
    "iso:country":"DE",
    "sg:address":"Manfred-von-Richthofen-Str. 21",
    "sg:city":"Pinneberg",
    "sg:phone":"+49 4101/693771",
    "sg:postcode":"25421",
    "sg:province":"Schleswig-Holstein",
    "wof:name":"Repair Bausanierungen Verwaltungsgesellschaft Mbh",
    "wof:placetype":"venue"
},
  "geometry": {"coordinates":[9.7975988388,53.6456565857],"type":"Point"}
}