{
  "type": "Feature",
  "properties": {
    "iso:country":"DE",
    "sg:address":"Leimberg 20",
    "sg:city":"Stolberg",
    "sg:phone":"+49 2402/862961",
    "sg:postcode":"52222",
    "sg:province":"Nordrhein-Westfalen",
    "wof:name":"Marben Ferntransport Gmbh",
    "wof:placetype":"venue"
},
  "geometry": {"coordinates":[6.2273478508,50.7904701233],"type":"Point"}
}