{
  "type": "Feature",
  "properties": {
    "iso:country":"DE",
    "sg:address":"Hesebergweg 49-51",
    "sg:city":"Peine",
    "sg:phone":"+49 4951/717020",
    "sg:postcode":"31228",
    "sg:province":"Niedersachsen",
    "wof:name":"Panasonic Avc Networks Germany Gmbh",
    "wof:placetype":"venue"
},
  "geometry": {"coordinates":[10.249529,52.339771],"type":"Point"}
}