{
  "type": "Feature",
  "properties": {
    "iso:country":"DE",
    "sg:address":"Kellerweg 1",
    "sg:city":"Stadtsteinach",
    "sg:phone":"+49 9225/386",
    "sg:postcode":"95346",
    "sg:province":"Bayern",
    "wof:name":"Anton Wagner",
    "wof:placetype":"venue"
},
  "geometry": {"coordinates":[11.502743721,50.1646766663],"type":"Point"}
}