{
  "type": "Feature",
  "properties": {
    "iso:country":"DE",
    "sg:address":"Feldkamp 12",
    "sg:city":"Bakum",
    "sg:phone":"+49 4446/1762",
    "sg:postcode":"49456",
    "sg:province":"Niedersachsen",
    "wof:name":"Lampe Gmbh",
    "wof:placetype":"venue"
},
  "geometry": {"coordinates":[8.1315431595,52.7529182434],"type":"Point"}
}