{
  "type": "Feature",
  "properties": {
    "iso:country":"DE",
    "sg:address":"Schmidtstr. 10 a",
    "sg:city":"Frankfurt",
    "sg:phone":"+49 69/736018",
    "sg:postcode":"60326",
    "sg:province":"Hessen",
    "wof:name":"Kab Konsumenten- Und Anlagenberatung",
    "wof:placetype":"venue"
},
  "geometry": {"coordinates":[8.618771553,50.1019210815],"type":"Point"}
}