{
  "type": "Feature",
  "properties": {
    "iso:country":"DE",
    "sg:address":"An der Johanneskirche 5a",
    "sg:city":"Cuxhaven",
    "sg:phone":"+49 4721/29817",
    "sg:postcode":"27476",
    "sg:province":"Niedersachsen",
    "wof:name":"Kurt Mertins Architekt",
    "wof:placetype":"venue"
},
  "geometry": {"coordinates":[8.631682,53.86068],"type":"Point"}
}