{
  "type": "Feature",
  "properties": {
    "iso:country":"DE",
    "sg:address":"Stadtweg 35",
    "sg:city":"Paderborn",
    "sg:phone":"+49 5252/5597",
    "sg:postcode":"33100",
    "sg:province":"Nordrhein-Westfalen",
    "wof:name":"Erwin Zimmermann",
    "wof:placetype":"venue"
},
  "geometry": {"coordinates":[8.846873,51.697483],"type":"Point"}
}