{
  "type": "Feature",
  "properties": {
    "iso:country":"DE",
    "sg:address":"Felix-und-Nabor-Str. 2",
    "sg:city":"Bad Krozingen",
    "sg:phone":"+49 7633/7776",
    "sg:postcode":"79189",
    "sg:province":"Baden-W\u00fcrttemberg",
    "wof:name":"Peter Maier",
    "wof:placetype":"venue"
},
  "geometry": {"coordinates":[7.7033371925,47.9181365967],"type":"Point"}
}