{
  "type": "Feature",
  "properties": {
    "iso:country":"DE",
    "sg:address":"Ferdinand-Wallbrecht-Str. 57",
    "sg:city":"Hannover",
    "sg:phone":"+49 511/392426",
    "sg:postcode":"30163",
    "sg:province":"Niedersachsen",
    "wof:name":"T. Nikologiannis",
    "wof:placetype":"venue"
},
  "geometry": {"coordinates":[9.744391,52.394928],"type":"Point"}
}