{
  "type": "Feature",
  "properties": {
    "iso:country":"DE",
    "sg:address":"Heimchenweg 6",
    "sg:city":"Frankfurt",
    "sg:phone":"+49 69/30850096",
    "sg:postcode":"65929",
    "sg:province":"Hessen",
    "wof:name":"Parker Hannifin Nmf Gmbh",
    "wof:placetype":"venue"
},
  "geometry": {"coordinates":[8.5325546265,50.1083374023],"type":"Point"}
}