{
  "type": "Feature",
  "properties": {
    "iso:country":"DE",
    "sg:address":"R\u00fcmannstr. 59",
    "sg:city":"M\u00fcnchen",
    "sg:phone":"+49 89/362233",
    "sg:postcode":"80804",
    "sg:province":"Bayern",
    "wof:name":"Herta Staal",
    "wof:placetype":"venue"
},
  "geometry": {"coordinates":[11.5826978683,48.1764793396],"type":"Point"}
}