{
  "type": "Feature",
  "properties": {
    "iso:country":"DE",
    "sg:address":"Hauptstr. 10",
    "sg:city":"Schlierbach",
    "sg:phone":"+49 7021/44837",
    "sg:postcode":"73278",
    "sg:province":"Baden-W\u00fcrttemberg",
    "wof:name":"M. Obermeyer",
    "wof:placetype":"venue"
},
  "geometry": {"coordinates":[9.5166635513,48.6735572815],"type":"Point"}
}