{
  "type": "Feature",
  "properties": {
    "iso:country":"DE",
    "sg:address":"Hutterer Weg 8",
    "sg:city":"Inzell",
    "sg:phone":"+49 8665/347",
    "sg:postcode":"83334",
    "sg:province":"Bayern",
    "wof:name":"H. Krebs",
    "wof:placetype":"venue"
},
  "geometry": {"coordinates":[12.7426834106,47.7789421082],"type":"Point"}
}