{
  "type": "Feature",
  "properties": {
    "iso:country":"DE",
    "sg:address":"Theodor-Heuss-Str. 8",
    "sg:city":"Moormerland",
    "sg:phone":"+49 4954/5454",
    "sg:postcode":"26802",
    "sg:province":"Niedersachsen",
    "wof:name":"B. A. Stock Ingenieur",
    "wof:placetype":"venue"
},
  "geometry": {"coordinates":[7.485106945,53.3097343445],"type":"Point"}
}