{
  "type": "Feature",
  "properties": {
    "iso:country":"DE",
    "sg:address":"Am Esch 4",
    "sg:city":"Hilkenbrook",
    "sg:phone":"+49 4493/8373",
    "sg:postcode":"26897",
    "sg:province":"Niedersachsen",
    "wof:name":"L & P Lacktechnik Gmbh",
    "wof:placetype":"venue"
},
  "geometry": {"coordinates":[7.7069010735,52.9776115417],"type":"Point"}
}