{
  "type": "Feature",
  "properties": {
    "iso:country":"DE",
    "sg:address":"Am Wollelager 11",
    "sg:city":"Delmenhorst",
    "sg:phone":"+49 4221/129862",
    "sg:postcode":"27749",
    "sg:province":"Niedersachsen",
    "wof:name":"Skm Security-detektei Inh. Markus Kunze E. K.",
    "wof:placetype":"venue"
},
  "geometry": {"coordinates":[8.6379566193,53.0537490845],"type":"Point"}
}