{
  "type": "Feature",
  "properties": {
    "iso:country":"DE",
    "sg:address":"Arndtstr. 12",
    "sg:city":"Schwalbach",
    "sg:phone":"+49 6834/568593",
    "sg:postcode":"66773",
    "sg:province":"Saarland",
    "wof:name":"R\u00fcdiger Wallendorf Finanzberater",
    "wof:placetype":"venue"
},
  "geometry": {"coordinates":[6.8217301369,49.2965736389],"type":"Point"}
}