{
  "type": "Feature",
  "properties": {
    "iso:country":"DE",
    "sg:address":"Geiststr. 10",
    "sg:city":"Halle",
    "sg:phone":"+49 345/3881171",
    "sg:postcode":"06108",
    "sg:province":"Sachsen-Anhalt",
    "wof:name":"K. Berndt",
    "wof:placetype":"venue"
},
  "geometry": {"coordinates":[11.965721,51.488697],"type":"Point"}
}