{
  "type": "Feature",
  "properties": {
    "iso:country":"DE",
    "sg:address":"Kellerstr. 13",
    "sg:city":"Bad M\u00fcnder",
    "sg:phone":"+49 5042/3249",
    "sg:postcode":"31848",
    "sg:province":"Niedersachsen",
    "wof:name":"Heimatmuseum Bad M\u00fcnder",
    "wof:placetype":"venue"
},
  "geometry": {"coordinates":[9.463604,52.198959],"type":"Point"}
}