{
  "type": "Feature",
  "properties": {
    "iso:country":"DE",
    "sg:address":"R\u00f6merstr. 35a",
    "sg:city":"Gernsheim",
    "sg:phone":"+49 6258/4949",
    "sg:postcode":"64579",
    "sg:province":"Hessen",
    "wof:name":"Riedl",
    "wof:placetype":"venue"
},
  "geometry": {"coordinates":[8.4872102737,49.7478981018],"type":"Point"}
}