{
  "type": "Feature",
  "properties": {
    "iso:country":"DE",
    "sg:address":"Von-Siemens-Str. 36",
    "sg:city":"Ketsch",
    "sg:phone":"+49 6202/69810",
    "sg:postcode":"68775",
    "sg:province":"Baden-W\u00fcrttemberg",
    "wof:name":"H. Kr\u00f6tzsch Gmbh",
    "wof:placetype":"venue"
},
  "geometry": {"coordinates":[8.5372037888,49.3608436584],"type":"Point"}
}