{
  "type": "Feature",
  "properties": {
    "iso:country":"DE",
    "sg:address":"Allewindenstr. 15",
    "sg:city":"Aulendorf",
    "sg:phone":"+49 7525/913068",
    "sg:postcode":"88326",
    "sg:province":"Baden-W\u00fcrttemberg",
    "wof:name":"Modehaus Scheffold Gmbh",
    "wof:placetype":"venue"
},
  "geometry": {"coordinates":[9.638066,47.948456],"type":"Point"}
}