{
  "type": "Feature",
  "properties": {
    "iso:country":"DE",
    "sg:address":"Pfortenstr. 36",
    "sg:city":"Frankfurt",
    "sg:phone":"+49 69/416181",
    "sg:postcode":"60386",
    "sg:province":"Hessen",
    "wof:name":"Egon Moser Versicherungen",
    "wof:placetype":"venue"
},
  "geometry": {"coordinates":[8.7659606934,50.1220397949],"type":"Point"}
}