{
  "type": "Feature",
  "properties": {
    "iso:country":"DE",
    "sg:address":"Sch\u00fctzenhausstr. 4",
    "sg:city":"Durlangen",
    "sg:phone":"+49 7176/2783",
    "sg:postcode":"73568",
    "sg:province":"Baden-W\u00fcrttemberg",
    "wof:name":"K. Fischer Ingenieur",
    "wof:placetype":"venue"
},
  "geometry": {"coordinates":[9.7978887558,48.8574752808],"type":"Point"}
}