{
  "type": "Feature",
  "properties": {
    "iso:country":"DE",
    "sg:address":"Bl\u00fctenstr. 5",
    "sg:city":"L\u00fctzelbach",
    "sg:phone":"+49 9372/944501",
    "sg:postcode":"64750",
    "sg:province":"Hessen",
    "wof:name":"R. Bauer",
    "wof:placetype":"venue"
},
  "geometry": {"coordinates":[9.1248016357,49.792842865],"type":"Point"}
}