{
  "type": "Feature",
  "properties": {
    "iso:country":"DE",
    "sg:address":"Charlottenhof 1",
    "sg:city":"Steinh\u00f6fel",
    "sg:phone":"+49 33636/226",
    "sg:postcode":"15518",
    "sg:province":"Brandenburg",
    "wof:name":"Herbert Richter",
    "wof:placetype":"venue"
},
  "geometry": {"coordinates":[14.148519,52.420372],"type":"Point"}
}