{
  "type": "Feature",
  "properties": {
    "iso:country":"DE",
    "sg:address":"Glockenstr. 25",
    "sg:city":"Chemnitz",
    "sg:phone":"+49 371/45930",
    "sg:postcode":"09130",
    "sg:province":"Sachsen",
    "wof:name":"Debeka Lebensversicherungs- Verein A.g.",
    "wof:placetype":"venue"
},
  "geometry": {"coordinates":[12.934232,50.835907],"type":"Point"}
}