{
  "type": "Feature",
  "properties": {
    "iso:country":"DE",
    "sg:address":"Mittelstr. 56",
    "sg:city":"Gevelsberg",
    "sg:phone":"+49 2332/3794",
    "sg:postcode":"58285",
    "sg:province":"Nordrhein-Westfalen",
    "wof:name":"Wilhelm Steinhauer",
    "wof:placetype":"venue"
},
  "geometry": {"coordinates":[7.336321,51.318863],"type":"Point"}
}