{
  "type": "Feature",
  "properties": {
    "iso:country":"DE",
    "sg:address":"Schellingstr. 33",
    "sg:city":"M\u00fcnchen",
    "sg:phone":"+49 89/284192",
    "sg:postcode":"80799",
    "sg:province":"Bayern",
    "wof:name":"Bestattungen Piet\u00e4t",
    "wof:placetype":"venue"
},
  "geometry": {"coordinates":[11.575187,48.150345],"type":"Point"}
}