{
  "type": "Feature",
  "properties": {
    "iso:country":"DE",
    "sg:address":"Josefstr. 56",
    "sg:city":"Nettetal",
    "sg:phone":"+49 2153/72377",
    "sg:postcode":"41334",
    "sg:province":"Nordrhein-Westfalen",
    "wof:name":"Eugen Driessen Drogerie",
    "wof:placetype":"venue"
},
  "geometry": {"coordinates":[6.24556,51.295643],"type":"Point"}
}