{
  "type": "Feature",
  "properties": {
    "iso:country":"DE",
    "sg:address":"Blumenstr. 17",
    "sg:city":"Kenzingen",
    "sg:phone":"+49 7644/8130",
    "sg:postcode":"79341",
    "sg:province":"Baden-W\u00fcrttemberg",
    "wof:name":"Karlheinz Focher",
    "wof:placetype":"venue"
},
  "geometry": {"coordinates":[7.8132390976,48.1803016663],"type":"Point"}
}