{
  "type": "Feature",
  "properties": {
    "iso:country":"DE",
    "sg:address":"Gr\u00fcngrabenstr. 20",
    "sg:city":"Albstadt",
    "sg:phone":"+49 7431/1603923",
    "sg:postcode":"72458",
    "sg:province":"Baden-W\u00fcrttemberg",
    "wof:name":"Hallenbad",
    "wof:placetype":"venue"
},
  "geometry": {"coordinates":[9.0278921127,48.213722229],"type":"Point"}
}