{
  "type": "Feature",
  "properties": {
    "iso:country":"DE",
    "sg:address":"Bergstr. 6",
    "sg:city":"Cochem",
    "sg:phone":"+49 2671/8990",
    "sg:postcode":"56812",
    "sg:province":"Rheinland-Pfalz",
    "wof:name":"G\u00e4stehaus J. G\u00f6rg",
    "wof:placetype":"venue"
},
  "geometry": {"coordinates":[7.1713609695,50.150932312],"type":"Point"}
}