{
  "type": "Feature",
  "properties": {
    "iso:country":"DE",
    "sg:address":"Max-Eyth-Str. 41",
    "sg:city":"N\u00fcrtingen",
    "sg:phone":"+49 7022/47430",
    "sg:postcode":"72622",
    "sg:province":"Baden-W\u00fcrttemberg",
    "wof:name":"Peter Geiger",
    "wof:placetype":"venue"
},
  "geometry": {"coordinates":[9.345901,48.613834],"type":"Point"}
}