{
  "type": "Feature",
  "properties": {
    "iso:country":"DE",
    "sg:address":"Leiblstr. 2",
    "sg:city":"Gr\u00f6benzell",
    "sg:postcode":"82194",
    "sg:province":"Bayern",
    "wof:name":"Hkb Industrievertretungen Gmbh",
    "wof:placetype":"venue"
},
  "geometry": {"coordinates":[11.3806829453,48.2066993713],"type":"Point"}
}