{
  "type": "Feature",
  "properties": {
    "iso:country":"DE",
    "sg:address":"Friedenstr 41-43",
    "sg:city":"Dortmund",
    "sg:phone":"+49 231/9123960",
    "sg:postcode":"44139",
    "sg:province":"Nordrhein-Westfalen",
    "wof:name":"Mid Medien- Und Informationsdesign Gmbh",
    "wof:placetype":"venue"
},
  "geometry": {"coordinates":[7.476522,51.500595],"type":"Point"}
}