{
  "type": "Feature",
  "properties": {
    "iso:country":"DE",
    "sg:address":"Goldschmidtstr. 13",
    "sg:city":"Neumarkt",
    "sg:phone":"+49 9181/6352",
    "sg:postcode":"92318",
    "sg:province":"Bayern",
    "wof:name":"Jura Geb\u00e4ude-service",
    "wof:placetype":"venue"
},
  "geometry": {"coordinates":[11.452671,49.271339],"type":"Point"}
}