{
  "type": "Feature",
  "properties": {
    "iso:country":"DE",
    "sg:address":"Oberdorfstr. 11",
    "sg:city":"Billigheim-Ingenheim",
    "sg:phone":"+49 6349/1071",
    "sg:postcode":"76831",
    "sg:province":"Rheinland-Pfalz",
    "wof:name":"Willi Sager",
    "wof:placetype":"venue"
},
  "geometry": {"coordinates":[8.0932617188,49.1323432922],"type":"Point"}
}