{
  "type": "Feature",
  "properties": {
    "iso:country":"DE",
    "sg:address":"Claus-Gieschen-Str. 11",
    "sg:city":"Loxstedt",
    "sg:phone":"+49 4744/2695",
    "sg:postcode":"27612",
    "sg:province":"Niedersachsen",
    "wof:name":"G\u00fcnther Gerkens",
    "wof:placetype":"venue"
},
  "geometry": {"coordinates":[8.645345,53.471684],"type":"Point"}
}