{
  "type": "Feature",
  "properties": {
    "iso:country":"DE",
    "sg:address":"Werner-von-Siemens-Ring 13a",
    "sg:city":"Magdeburg",
    "sg:phone":"+49 391/635500",
    "sg:postcode":"39116",
    "sg:province":"Sachsen-Anhalt",
    "wof:name":"Ruppert & Partner",
    "wof:placetype":"venue"
},
  "geometry": {"coordinates":[11.5814685822,52.0799179077],"type":"Point"}
}