{
  "type": "Feature",
  "properties": {
    "iso:country":"DE",
    "sg:address":"Wiesenweg 49",
    "sg:city":"M\u00f6glingen",
    "sg:phone":"+49 7141/24660",
    "sg:postcode":"71696",
    "sg:province":"Baden-W\u00fcrttemberg",
    "wof:name":"Jenner Gmbh",
    "wof:placetype":"venue"
},
  "geometry": {"coordinates":[9.1271381378,48.8909683228],"type":"Point"}
}