{
  "type": "Feature",
  "properties": {
    "iso:country":"DE",
    "sg:address":"Gustav-Adolf-Str. 9",
    "sg:city":"Hanau",
    "sg:postcode":"63452",
    "sg:province":"Hessen",
    "wof:name":"Hanau M\u00e4rkte Gmbh",
    "wof:placetype":"venue"
},
  "geometry": {"coordinates":[8.9074516296,50.1399917603],"type":"Point"}
}