{
  "type": "Feature",
  "properties": {
    "iso:country":"DE",
    "sg:address":"Windeweg 3",
    "sg:city":"Suhl",
    "sg:phone":"+49 3681/724348",
    "sg:postcode":"98527",
    "sg:province":"Th\u00fcringen",
    "wof:name":"Gebr. Adamy Inh. Helmut Adamy",
    "wof:placetype":"venue"
},
  "geometry": {"coordinates":[10.690618,50.605709],"type":"Point"}
}