{
  "type": "Feature",
  "properties": {
    "iso:country":"DE",
    "sg:address":"Lautertalstr. 50",
    "sg:city":"Laubach",
    "sg:phone":"+49 6401/6368",
    "sg:postcode":"35321",
    "sg:province":"Hessen",
    "wof:name":"L. Neumann",
    "wof:placetype":"venue"
},
  "geometry": {"coordinates":[8.9639854431,50.5691871643],"type":"Point"}
}