{
  "type": "Feature",
  "properties": {
    "iso:country":"DE",
    "sg:address":"Kirchfeldstr. 131",
    "sg:city":"D\u00fcsseldorf",
    "sg:phone":"+49 211/3179904",
    "sg:postcode":"40215",
    "sg:province":"Nordrhein-Westfalen",
    "wof:name":"Pizzaria Popai",
    "wof:placetype":"venue"
},
  "geometry": {"coordinates":[6.7836151123,51.2121543884],"type":"Point"}
}