{
  "type": "Feature",
  "properties": {
    "iso:country":"DE",
    "sg:address":"Brehnaer Str 20",
    "sg:city":"Landsberg",
    "sg:phone":"+49 34602/48100",
    "sg:postcode":"06188",
    "sg:province":"Sachsen-Anhalt",
    "wof:name":"Schrauben-j\u00e4ger Ag",
    "wof:placetype":"venue"
},
  "geometry": {"coordinates":[12.1051597595,51.5272598267],"type":"Point"}
}