{
  "type": "Feature",
  "properties": {
    "iso:country":"DE",
    "sg:address":"Dr.-C.-Otto-Str. 113",
    "sg:city":"Bochum",
    "sg:phone":"+49 234/495000",
    "sg:postcode":"44879",
    "sg:province":"Nordrhein-Westfalen",
    "wof:name":"Lohs-bauelemente Gmbh",
    "wof:placetype":"venue"
},
  "geometry": {"coordinates":[7.1463699341,51.4262962341],"type":"Point"}
}