{
  "type": "Feature",
  "properties": {
    "iso:country":"DE",
    "sg:address":"34376",
    "sg:city":"Immenhausen",
    "sg:phone":"+49 5673/3979",
    "sg:postcode":"34376",
    "sg:province":"Hessen",
    "wof:name":"Schwimmbadgastst\u00e4tte",
    "wof:placetype":"venue"
},
  "geometry": {"coordinates":[9.5248403549,51.4339103699],"type":"Point"}
}