{
  "type": "Feature",
  "properties": {
    "iso:country":"DE",
    "sg:address":"Hauptstr. 105",
    "sg:city":"Langenwetzendorf",
    "sg:phone":"+49 36625/20256",
    "sg:postcode":"07957",
    "sg:province":"Th\u00fcringen",
    "wof:name":"Michael Landmann",
    "wof:placetype":"venue"
},
  "geometry": {"coordinates":[12.089891,50.682186],"type":"Point"}
}