{
  "type": "Feature",
  "properties": {
    "iso:country":"DE",
    "sg:address":"Knorrstr. 66",
    "sg:city":"M\u00fcnchen",
    "sg:phone":"+49 89/3507666",
    "sg:postcode":"80807",
    "sg:province":"Bayern",
    "wof:name":"Greineder Electronic Publishing Gmbh",
    "wof:placetype":"venue"
},
  "geometry": {"coordinates":[11.5730571747,48.1848754883],"type":"Point"}
}