{
  "type": "Feature",
  "properties": {
    "iso:country":"DE",
    "sg:address":"Ehrenstr. 106",
    "sg:city":"K\u00f6ln",
    "sg:phone":"+49 221/253314",
    "sg:postcode":"50672",
    "sg:province":"Nordrhein-Westfalen",
    "wof:name":"Scale",
    "wof:placetype":"venue"
},
  "geometry": {"coordinates":[6.93935,50.93829],"type":"Point"}
}