{
  "type": "Feature",
  "properties": {
    "iso:country":"DE",
    "sg:address":"\u00c4u\u00dfere N\u00fcrnberger Str. 18",
    "sg:city":"Forchheim",
    "sg:phone":"+49 9191/2550",
    "sg:postcode":"91301",
    "sg:province":"Bayern",
    "wof:name":"Karl Hofst\u00e4tter",
    "wof:placetype":"venue"
},
  "geometry": {"coordinates":[11.061372,49.71122],"type":"Point"}
}