{
  "type": "Feature",
  "properties": {
    "iso:country":"DE",
    "sg:address":"Hauptstr. 5",
    "sg:city":"Wedemark",
    "sg:phone":"+49 5130/3598",
    "sg:postcode":"30900",
    "sg:province":"Niedersachsen",
    "wof:name":"H. Grimsehl",
    "wof:placetype":"venue"
},
  "geometry": {"coordinates":[9.688239,52.553638],"type":"Point"}
}