{
  "type": "Feature",
  "properties": {
    "iso:country":"DE",
    "sg:address":"D\u00f6berkitzer Str. 3a",
    "sg:city":"G\u00f6da",
    "sg:phone":"+49 35930/52121",
    "sg:postcode":"02633",
    "sg:province":"Sachsen",
    "wof:name":"Gartengastst\u00e4tte Elke K\u00f6hler",
    "wof:placetype":"venue"
},
  "geometry": {"coordinates":[14.3224039078,51.1795883179],"type":"Point"}
}