{
  "type": "Feature",
  "properties": {
    "iso:country":"DE",
    "sg:address":"Am Wachtelberg 10",
    "sg:city":"Rudolstadt",
    "sg:phone":"+49 3672/412742",
    "sg:postcode":"07407",
    "sg:province":"Th\u00fcringen",
    "wof:name":"Karl-heinz Bartl Ingenieur",
    "wof:placetype":"venue"
},
  "geometry": {"coordinates":[11.295548439,50.7143440247],"type":"Point"}
}