{
  "type": "Feature",
  "properties": {
    "iso:country":"DE",
    "sg:address":"Haid-und-Neu-Str 7",
    "sg:city":"Karlsruhe",
    "sg:phone":"+49 721/964670",
    "sg:postcode":"76131",
    "sg:province":"Baden-W\u00fcrttemberg",
    "wof:name":"Fe-design Gesellschaft Zur Herstellung Von Analysesoftware Mbh",
    "wof:placetype":"venue"
},
  "geometry": {"coordinates":[8.425708,49.012421],"type":"Point"}
}