{
  "type": "Feature",
  "properties": {
    "iso:country":"DE",
    "sg:address":"Douglasstr. 9",
    "sg:city":"Karlsruhe",
    "sg:postcode":"76133",
    "sg:province":"Baden-W\u00fcrttemberg",
    "wof:name":"Ibk Immobilienkonzepte Und Beteiligungen Ag",
    "wof:placetype":"venue"
},
  "geometry": {"coordinates":[8.393748,49.010983],"type":"Point"}
}