{
  "type": "Feature",
  "properties": {
    "iso:country":"DE",
    "sg:address":"Amtsstr. 11",
    "sg:city":"Geseke",
    "sg:phone":"+49 2942/570800",
    "sg:postcode":"59590",
    "sg:province":"Nordrhein-Westfalen",
    "wof:name":"Steuerberatungsges. Mbh H. Bernt",
    "wof:placetype":"venue"
},
  "geometry": {"coordinates":[8.4655151367,51.6421394348],"type":"Point"}
}