{
  "type": "Feature",
  "properties": {
    "iso:country":"DE",
    "sg:address":"Springhoe 1",
    "sg:city":"Hohenlockstedt",
    "sg:phone":"+49 4826/86020",
    "sg:postcode":"25551",
    "sg:province":"Schleswig-Holstein",
    "wof:name":"Engler",
    "wof:placetype":"venue"
},
  "geometry": {"coordinates":[9.631343,53.974751],"type":"Point"}
}