{
  "type": "Feature",
  "properties": {
    "iso:country":"DE",
    "sg:address":"Rohrbach 128",
    "sg:city":"Schiltach",
    "sg:phone":"+49 7836/2126",
    "sg:postcode":"77761",
    "sg:province":"Baden-W\u00fcrttemberg",
    "wof:name":"Rohrbachst\u00fcble",
    "wof:placetype":"venue"
},
  "geometry": {"coordinates":[8.3790645599,48.2757987976],"type":"Point"}
}