{
  "type": "Feature",
  "properties": {
    "iso:country":"DE",
    "sg:address":"Pasewaldtstr. 7",
    "sg:city":"Berlin",
    "sg:phone":"+49 30/8014026",
    "sg:postcode":"14169",
    "sg:province":"Berlin",
    "wof:name":"Bernd Schaeffer",
    "wof:placetype":"venue"
},
  "geometry": {"coordinates":[13.2594585419,52.4376754761],"type":"Point"}
}