{
  "type": "Feature",
  "properties": {
    "iso:country":"DE",
    "sg:address":"An den Eichen 29",
    "sg:city":"K\u00fcrten",
    "sg:phone":"+49 2268/3399",
    "sg:postcode":"51515",
    "sg:province":"Nordrhein-Westfalen",
    "wof:name":"Ernst H\u00e4nchen",
    "wof:placetype":"venue"
},
  "geometry": {"coordinates":[7.238149,51.066219],"type":"Point"}
}