{
  "type": "Feature",
  "properties": {
    "iso:country":"DE",
    "sg:address":"Rheinh\u00f6henstr. 1",
    "sg:city":"Neuwied",
    "sg:phone":"+49 2631/72599",
    "sg:postcode":"56567",
    "sg:province":"Rheinland-Pfalz",
    "wof:name":"Hans-dieter Klaes",
    "wof:placetype":"venue"
},
  "geometry": {"coordinates":[7.444508,50.44545],"type":"Point"}
}