{
  "type": "Feature",
  "properties": {
    "iso:country":"DE",
    "sg:address":"Im Dorf 5",
    "sg:city":"Hohenstein",
    "sg:phone":"+49 7387/98900",
    "sg:postcode":"72531",
    "sg:province":"Baden-W\u00fcrttemberg",
    "wof:name":"Brauerei-gasthof Lamm Gmbh",
    "wof:placetype":"venue"
},
  "geometry": {"coordinates":[9.375535,48.348309],"type":"Point"}
}