{
  "type": "Feature",
  "properties": {
    "iso:country":"DE",
    "sg:address":"Georg-August-Zinn-Str. 90",
    "sg:city":"Gro\u00df-Umstadt",
    "sg:phone":"+49 6078/934815",
    "sg:postcode":"64823",
    "sg:province":"Hessen",
    "wof:name":"Impuls Electronics Gbr",
    "wof:placetype":"venue"
},
  "geometry": {"coordinates":[8.9176054001,49.8708610535],"type":"Point"}
}