{
  "type": "Feature",
  "properties": {
    "iso:country":"DE",
    "sg:address":"Br\u00fchl 14a",
    "sg:city":"Ha\u00dfloch",
    "sg:phone":"+49 6324/1271",
    "sg:postcode":"67454",
    "sg:province":"Rheinland-Pfalz",
    "wof:name":"Pfalzhalle",
    "wof:placetype":"venue"
},
  "geometry": {"coordinates":[8.2582874298,49.3601455688],"type":"Point"}
}