{
  "type": "Feature",
  "properties": {
    "iso:country":"DE",
    "sg:address":"Dieringhauser Str. 47",
    "sg:city":"Gummersbach",
    "sg:postcode":"51645",
    "sg:province":"Nordrhein-Westfalen",
    "wof:name":"Ihr Videopartner",
    "wof:placetype":"venue"
},
  "geometry": {"coordinates":[7.5367279053,50.983417511],"type":"Point"}
}