{
  "type": "Feature",
  "properties": {
    "iso:country":"DE",
    "sg:address":"Faerberstr. 45::",
    "sg:city":"Nuernberg",
    "sg:phone":"+49 911/2370",
    "sg:postcode":"90402",
    "sg:province":"Bayern",
    "wof:name":"Raiffeisenbank Nuernberg Eg",
    "wof:placetype":"venue"
},
  "geometry": {"coordinates":[11.072038,49.447601],"type":"Point"}
}