{
  "type": "Feature",
  "properties": {
    "iso:country":"DE",
    "sg:address":"Hildesheimer Str. 64 A",
    "sg:city":"Alfeld",
    "sg:postcode":"31061",
    "sg:province":"Niedersachsen",
    "wof:name":"Refa Verband F\u00fcr Arbeits- Studien Und Betriebs-",
    "wof:placetype":"venue"
},
  "geometry": {"coordinates":[9.832923,51.990719],"type":"Point"}
}