{
  "type": "Feature",
  "properties": {
    "iso:country":"DE",
    "sg:address":"Donauw\u00f6rther Str. 9",
    "sg:city":"Asbach-B\u00e4umenheim",
    "sg:phone":"+49 906/91187",
    "sg:postcode":"86663",
    "sg:province":"Bayern",
    "wof:name":"Akar",
    "wof:placetype":"venue"
},
  "geometry": {"coordinates":[10.8090190887,48.6822242737],"type":"Point"}
}