{
  "type": "Feature",
  "properties": {
    "iso:country":"DE",
    "sg:address":"L\u00fcbecker Str. 110",
    "sg:city":"Magdeburg",
    "sg:postcode":"39124",
    "sg:province":"Sachsen-Anhalt",
    "wof:name":"G. Bessel Inh. Herta Simon",
    "wof:placetype":"venue"
},
  "geometry": {"coordinates":[11.6364049911,52.1574630737],"type":"Point"}
}