{
  "type": "Feature",
  "properties": {
    "iso:country":"DE",
    "sg:address":"Marktstr. 21",
    "sg:city":"Bad T\u00f6lz",
    "sg:phone":"+49 8041/3796",
    "sg:postcode":"83646",
    "sg:province":"Bayern",
    "wof:name":"Christophorus-apotheke",
    "wof:placetype":"venue"
},
  "geometry": {"coordinates":[11.558366,47.760956],"type":"Point"}
}