{
  "type": "Feature",
  "properties": {
    "iso:country":"DE",
    "sg:address":"Gartenstr. 4",
    "sg:city":"Langeoog",
    "sg:phone":"+49 4972/283",
    "sg:postcode":"26465",
    "sg:province":"Niedersachsen",
    "wof:name":"Owd-heim",
    "wof:placetype":"venue"
},
  "geometry": {"coordinates":[7.4825568199,53.7485237122],"type":"Point"}
}