{
  "type": "Feature",
  "properties": {
    "iso:country":"DE",
    "sg:address":"Burgweg 111",
    "sg:city":"Veringenstadt",
    "sg:phone":"+49 7577/7688",
    "sg:postcode":"72519",
    "sg:province":"Baden-W\u00fcrttemberg",
    "wof:name":"Gecko-spielwaren",
    "wof:placetype":"venue"
},
  "geometry": {"coordinates":[9.209107399,48.1801185608],"type":"Point"}
}