{
  "type": "Feature",
  "properties": {
    "iso:country":"DE",
    "sg:address":"Alt-Godshorn 87",
    "sg:city":"Langenhagen",
    "sg:phone":"+49 511/786100",
    "sg:postcode":"30855",
    "sg:province":"Niedersachsen",
    "wof:name":"Repha Gmbh",
    "wof:placetype":"venue"
},
  "geometry": {"coordinates":[9.704284668,52.4386024475],"type":"Point"}
}