{
  "type": "Feature",
  "properties": {
    "iso:country":"DE",
    "sg:address":"Kurpfalzhof 10",
    "sg:city":"Heidelberg",
    "sg:phone":"+49 6221/79160",
    "sg:postcode":"69124",
    "sg:province":"Baden-W\u00fcrttemberg",
    "wof:name":"Pension Kurpfalzhof",
    "wof:placetype":"venue"
},
  "geometry": {"coordinates":[8.6160984039,49.3750038147],"type":"Point"}
}