{
  "type": "Feature",
  "properties": {
    "iso:country":"DE",
    "sg:address":"Am Schlo\u00df",
    "sg:city":"Steinpleis",
    "sg:phone":"+49 375/294047",
    "sg:postcode":"08432",
    "wof:name":"Audilet Architekt",
    "wof:placetype":"venue"
},
  "geometry": {"coordinates":[12.388723,50.713356],"type":"Point"}
}