{
  "type": "Feature",
  "properties": {
    "iso:country":"DE",
    "sg:address":"Sonnenhalde 5",
    "sg:city":"Staig",
    "sg:phone":"+49 7346/2148",
    "sg:postcode":"89195",
    "sg:province":"Baden-W\u00fcrttemberg",
    "wof:name":"Meinrad J\u00f6chle",
    "wof:placetype":"venue"
},
  "geometry": {"coordinates":[10.001613,48.303612],"type":"Point"}
}