{
  "type": "Feature",
  "properties": {
    "iso:country":"DE",
    "sg:address":"Mietwagenpavillion",
    "sg:city":"Dresden",
    "sg:phone":"+49 351/5895230",
    "sg:postcode":"01109",
    "sg:province":"Sachsen",
    "wof:name":"Adac Autovermietung Gmbh",
    "wof:placetype":"venue"
},
  "geometry": {"coordinates":[13.7585,51.120491],"type":"Point"}
}