{
  "type": "Feature",
  "properties": {
    "iso:country":"DE",
    "sg:address":"Hof Gelsdorf 5",
    "sg:city":"Gransdorf",
    "sg:postcode":"54533",
    "sg:province":"Rheinland-Pfalz",
    "wof:name":"Formenbau J\u00fcrgen Jung Gmbh",
    "wof:placetype":"venue"
},
  "geometry": {"coordinates":[6.665391922,50.005695343],"type":"Point"}
}