{
  "type": "Feature",
  "properties": {
    "iso:country":"DE",
    "sg:address":"Rubensstr. 1",
    "sg:city":"Wuppertal",
    "sg:phone":"+49 202/731393",
    "sg:postcode":"42329",
    "sg:province":"Nordrhein-Westfalen",
    "wof:name":"Brawo",
    "wof:placetype":"venue"
},
  "geometry": {"coordinates":[7.068161,51.229897],"type":"Point"}
}