{
  "type": "Feature",
  "properties": {
    "iso:country":"DE",
    "sg:address":"Hohenstaufenstr. 93",
    "sg:city":"G\u00f6ppingen",
    "sg:phone":"+49 7161/74194",
    "sg:postcode":"73033",
    "sg:province":"Baden-W\u00fcrttemberg",
    "wof:name":"Helmut Feige Grabmale Gmbh",
    "wof:placetype":"venue"
},
  "geometry": {"coordinates":[9.6727733612,48.7058486938],"type":"Point"}
}