{
  "type": "Feature",
  "properties": {
    "iso:country":"DE",
    "sg:address":"Hauptstr. 7",
    "sg:city":"Dedelstorf",
    "sg:phone":"+49 5832/2819",
    "sg:postcode":"29386",
    "sg:province":"Niedersachsen",
    "wof:name":"Hermann Rodewald",
    "wof:placetype":"venue"
},
  "geometry": {"coordinates":[10.540432,52.676601],"type":"Point"}
}