{
  "type": "Feature",
  "properties": {
    "iso:country":"DE",
    "sg:address":"Kaiserstr. 1",
    "sg:city":"Gummersbach",
    "sg:phone":"+49 2261/64108",
    "sg:postcode":"51643",
    "sg:province":"Nordrhein-Westfalen",
    "wof:name":"Apropos Gummersbach Kaiserstr. 1",
    "wof:placetype":"venue"
},
  "geometry": {"coordinates":[7.5667481422,51.025932312],"type":"Point"}
}