{
  "type": "Feature",
  "properties": {
    "iso:country":"DE",
    "sg:address":"Am Sportpark 11",
    "sg:city":"N\u00f6rdlingen",
    "sg:phone":"+49 9081/3559",
    "sg:postcode":"86720",
    "sg:province":"Bayern",
    "wof:name":"Cowabanga",
    "wof:placetype":"venue"
},
  "geometry": {"coordinates":[10.4885759354,48.8527069092],"type":"Point"}
}