{
  "type": "Feature",
  "properties": {
    "iso:country":"DE",
    "sg:address":"Ernst-Th\u00e4lmann-Str. 9",
    "sg:city":"Sangerhausen",
    "sg:phone":"+49 3464/573425",
    "sg:postcode":"06526",
    "sg:province":"Sachsen-Anhalt",
    "wof:name":"Andreas Wei\u00df Steuerberater",
    "wof:placetype":"venue"
},
  "geometry": {"coordinates":[11.2936916351,51.4775772095],"type":"Point"}
}