{
  "type": "Feature",
  "properties": {
    "iso:country":"DE",
    "sg:address":"Dammwiesen 3",
    "sg:city":"Stamsried",
    "sg:phone":"+49 9466/236",
    "sg:postcode":"93491",
    "sg:province":"Bayern",
    "wof:name":"Multerer & Kraus",
    "wof:placetype":"venue"
},
  "geometry": {"coordinates":[12.5309267044,49.2644615173],"type":"Point"}
}