{
  "type": "Feature",
  "properties": {
    "iso:country":"DE",
    "sg:address":"Hohler Weg 9",
    "sg:city":"Naumburg",
    "sg:phone":"+49 5625/890",
    "sg:postcode":"34311",
    "sg:province":"Hessen",
    "wof:name":"Norbert Hahn Altenheim",
    "wof:placetype":"venue"
},
  "geometry": {"coordinates":[9.214445,51.227943],"type":"Point"}
}