{
  "type": "Feature",
  "properties": {
    "iso:country":"DE",
    "sg:address":"Hofangerstr. 47",
    "sg:city":"M\u00fcnchen",
    "sg:phone":"+49 89/406780",
    "sg:postcode":"81735",
    "sg:province":"Bayern",
    "wof:name":"Josef Biberger",
    "wof:placetype":"venue"
},
  "geometry": {"coordinates":[11.6296739578,48.1143417358],"type":"Point"}
}