{
  "type": "Feature",
  "properties": {
    "iso:country":"DE",
    "sg:address":"Amtsstr. 6",
    "sg:city":"Ludwigshafen",
    "sg:phone":"+49 621/625451",
    "sg:postcode":"67059",
    "sg:province":"Rheinland-Pfalz",
    "wof:name":"Hechler & Wand Versicherungsvermittlung Gmbh",
    "wof:placetype":"venue"
},
  "geometry": {"coordinates":[8.4460659027,49.4819602966],"type":"Point"}
}