{
  "type": "Feature",
  "properties": {
    "iso:country":"DE",
    "sg:address":"Karl-Maybach-Str. 18 PF 330",
    "sg:city":"Wangen",
    "sg:phone":"+49 7520/9567880",
    "sg:postcode":"88239",
    "sg:province":"Baden-W\u00fcrttemberg",
    "wof:name":"Rotaplast Gmbh",
    "wof:placetype":"venue"
},
  "geometry": {"coordinates":[9.8126897812,47.6883811951],"type":"Point"}
}