{
  "type": "Feature",
  "properties": {
    "iso:country":"DE",
    "sg:address":"Reuterstr. 59",
    "sg:city":"Berlin",
    "sg:phone":"+49 30/6237093",
    "sg:postcode":"12047",
    "sg:province":"Berlin",
    "wof:name":"Klaus Klingbeil H\u00f6rger.-akustik",
    "wof:placetype":"venue"
},
  "geometry": {"coordinates":[13.4288110733,52.4878692627],"type":"Point"}
}