{
  "type": "Feature",
  "properties": {
    "iso:country":"DE",
    "sg:address":"Kemnader Str. 276",
    "sg:city":"Bochum",
    "sg:phone":"+49 234/791473",
    "sg:postcode":"44797",
    "sg:province":"Nordrhein-Westfalen",
    "wof:name":"Walter Koppka",
    "wof:placetype":"venue"
},
  "geometry": {"coordinates":[7.24423,51.41658],"type":"Point"}
}