{
  "type": "Feature",
  "properties": {
    "iso:country":"DE",
    "sg:address":"H\u00f6rnenweg 9",
    "sg:city":"Kerken",
    "sg:phone":"+49 2833",
    "sg:postcode":"47647",
    "sg:province":"Nordrhein-Westfalen",
    "wof:name":"Carl-verlag - Schachliteratur Von Weltmeistern",
    "wof:placetype":"venue"
},
  "geometry": {"coordinates":[6.428674,51.432201],"type":"Point"}
}