{
  "type": "Feature",
  "properties": {
    "iso:country":"DE",
    "sg:address":"Marktstr. 2",
    "sg:city":"Neustadt",
    "sg:phone":"+49 5032/1263",
    "sg:postcode":"31535",
    "sg:province":"Niedersachsen",
    "wof:name":"Markt-apotheke",
    "wof:placetype":"venue"
},
  "geometry": {"coordinates":[11.585607,53.384243],"type":"Point"}
}