{
  "type": "Feature",
  "properties": {
    "iso:country":"DE",
    "sg:address":"Am Heidering 8",
    "sg:city":"Oranienburg",
    "sg:phone":"+49 3301/808586",
    "sg:postcode":"16515",
    "sg:province":"Brandenburg",
    "wof:name":"Fliesenfachgesch\u00e4ft Arbeit & Pre\u00dfmann",
    "wof:placetype":"venue"
},
  "geometry": {"coordinates":[13.2646932602,52.7727851868],"type":"Point"}
}