{
  "type": "Feature",
  "properties": {
    "iso:country":"DE",
    "sg:address":"Regensburger Str. 334a",
    "sg:city":"N\u00fcrnberg",
    "sg:phone":"+49 911/406091",
    "sg:postcode":"90480",
    "sg:province":"Bayern",
    "wof:name":"Dhv Ingenieur-consulting Deutschland Gmbh",
    "wof:placetype":"venue"
},
  "geometry": {"coordinates":[11.1303052902,49.432434082],"type":"Point"}
}