{
  "type": "Feature",
  "properties": {
    "iso:country":"DE",
    "sg:address":"Lange Str. 213",
    "sg:city":"Mellingen",
    "sg:phone":"+49 36453/80430",
    "sg:postcode":"99441",
    "sg:province":"Th\u00fcringen",
    "wof:name":"Harald Dathan",
    "wof:placetype":"venue"
},
  "geometry": {"coordinates":[11.390189,50.938747],"type":"Point"}
}