{
  "type": "Feature",
  "properties": {
    "iso:country":"DE",
    "sg:address":"Am Velper Bahnhof 6",
    "sg:city":"Westerkappeln",
    "sg:phone":"+49 5456/1068",
    "sg:postcode":"49492",
    "sg:province":"Nordrhein-Westfalen",
    "wof:name":"Lindemann Und Raneberg",
    "wof:placetype":"venue"
},
  "geometry": {"coordinates":[7.8624558449,52.2671775818],"type":"Point"}
}