{
  "type": "Feature",
  "properties": {
    "iso:country":"DE",
    "sg:address":"Eppelsheimer Weg 1",
    "sg:city":"Gau-Heppenheim",
    "sg:phone":"+49 6731/44807",
    "sg:postcode":"55234",
    "sg:province":"Rheinland-Pfalz",
    "wof:name":"M. M\u00fcllersch\u00f6n Gmbh",
    "wof:placetype":"venue"
},
  "geometry": {"coordinates":[8.172345,49.740845],"type":"Point"}
}