{
  "type": "Feature",
  "properties": {
    "iso:country":"DE",
    "sg:address":"Sorbenstr. 3",
    "sg:city":"Hamburg",
    "sg:postcode":"20537",
    "sg:province":"Hamburg",
    "wof:name":"Euro-handels-gesellschaft F\u00fcr Maschinen- Und Industrie-",
    "wof:placetype":"venue"
},
  "geometry": {"coordinates":[10.039157,53.549541],"type":"Point"}
}