{
  "type": "Feature",
  "properties": {
    "iso:country":"DE",
    "sg:address":"Hannoversche Str. 19",
    "sg:city":"Walsrode",
    "sg:phone":"+49 5161/5391",
    "sg:postcode":"29664",
    "sg:province":"Niedersachsen",
    "wof:name":"Adolf Eggersgl\u00fcss Wettannahme",
    "wof:placetype":"venue"
},
  "geometry": {"coordinates":[9.59534,52.857063],"type":"Point"}
}