{
  "type": "Feature",
  "properties": {
    "iso:country":"DE",
    "sg:address":"Br\u00fcckenbreite 12",
    "sg:city":"Magdeburg",
    "sg:postcode":"39114",
    "sg:province":"Sachsen-Anhalt",
    "wof:name":"Werner Weiner",
    "wof:placetype":"venue"
},
  "geometry": {"coordinates":[11.6823587418,52.1109237671],"type":"Point"}
}