{
  "type": "Feature",
  "properties": {
    "iso:country":"DE",
    "sg:address":"Firmensitz Siegen: Breite Stra\u00dfe 11",
    "sg:city":"Siegen-Weidenau",
    "sg:phone":"+49 271/4889013",
    "sg:postcode":"57076",
    "sg:province":"Nordrhein-Westfalen",
    "wof:name":"Protech & Style Digital / Siegen-bonn-frankfurt A.m.-koblenz",
    "wof:placetype":"venue"
},
  "geometry": {"coordinates":[8.0279598236,50.895690918],"type":"Point"}
}