{
  "type": "Feature",
  "properties": {
    "iso:country":"DE",
    "sg:address":"Freiligrathstr. 9",
    "sg:city":"Unkel",
    "sg:phone":"+49 2224/72943",
    "sg:postcode":"53572",
    "sg:province":"Rheinland-Pfalz",
    "wof:name":"Otto Roos",
    "wof:placetype":"venue"
},
  "geometry": {"coordinates":[7.2172708511,50.5998497009],"type":"Point"}
}