{
  "type": "Feature",
  "properties": {
    "iso:country":"DE",
    "sg:address":"Realschulstr. 10",
    "sg:city":"Gro\u00df-Umstadt",
    "sg:phone":"+49 6078/2475",
    "sg:postcode":"64823",
    "sg:province":"Hessen",
    "wof:name":"Pizzeria Salerno",
    "wof:placetype":"venue"
},
  "geometry": {"coordinates":[8.9259672165,49.8688240051],"type":"Point"}
}