{
  "type": "Feature",
  "properties": {
    "iso:country":"DE",
    "sg:address":"Karkloh 14",
    "sg:city":"Albersdorf",
    "sg:postcode":"25767",
    "sg:province":"Schleswig-Holstein",
    "wof:name":"Aldi Gmbh & Co. Kg",
    "wof:placetype":"venue"
},
  "geometry": {"coordinates":[9.2848043442,54.1403503418],"type":"Point"}
}