{
  "type": "Feature",
  "properties": {
    "iso:country":"DE",
    "sg:address":"Burloer Str. 125",
    "sg:city":"Borken",
    "sg:phone":"+49 2861/66438",
    "sg:postcode":"46325",
    "sg:province":"Nordrhein-Westfalen",
    "wof:name":"Heinrich Mels",
    "wof:placetype":"venue"
},
  "geometry": {"coordinates":[6.83959,51.856056],"type":"Point"}
}