{
  "type": "Feature",
  "properties": {
    "iso:country":"DE",
    "sg:address":"B\u00e4ckerstr. 2",
    "sg:city":"Minden",
    "sg:phone":"+49 571/8291020",
    "sg:postcode":"32423",
    "sg:province":"Nordrhein-Westfalen",
    "wof:name":"D2-shop",
    "wof:placetype":"venue"
},
  "geometry": {"coordinates":[8.9167690277,52.2899208069],"type":"Point"}
}