{
  "type": "Feature",
  "properties": {
    "iso:country":"DE",
    "sg:address":"Bahnhofstr. 5",
    "sg:city":"Korbach",
    "sg:phone":"+49 5631/913383",
    "sg:postcode":"34497",
    "sg:province":"Hessen",
    "wof:name":"Tchibo Frisch-r\u00f6st-kaffee Gmbh",
    "wof:placetype":"venue"
},
  "geometry": {"coordinates":[8.8718614578,51.2766532898],"type":"Point"}
}