{
  "type": "Feature",
  "properties": {
    "iso:country":"DE",
    "sg:address":"Adolf-Cramer-Str. 14",
    "sg:city":"Georgsmarienh\u00fctte",
    "sg:phone":"+49 5401/32170",
    "sg:postcode":"49124",
    "sg:province":"Niedersachsen",
    "wof:name":"Anja Radtke",
    "wof:placetype":"venue"
},
  "geometry": {"coordinates":[8.0132112503,52.2170829773],"type":"Point"}
}