{
  "type": "Feature",
  "properties": {
    "iso:country":"DE",
    "sg:address":"Hochdahler Markt",
    "sg:city":"Erkrath",
    "sg:phone":"+49 2104/48181",
    "sg:postcode":"40699",
    "sg:province":"Nordrhein-Westfalen",
    "wof:name":"Plus Warenhandelsges. Mbh",
    "wof:placetype":"venue"
},
  "geometry": {"coordinates":[6.9555649757,51.2076416016],"type":"Point"}
}