{
  "type": "Feature",
  "properties": {
    "iso:country":"DE",
    "sg:address":"Salierstr. 53",
    "sg:city":"Schifferstadt",
    "sg:phone":"+49 4962/351812",
    "sg:postcode":"67105",
    "sg:province":"Rheinland-Pfalz",
    "wof:name":"Volksbank Schifferstadt Zweign",
    "wof:placetype":"venue"
},
  "geometry": {"coordinates":[8.38492,49.380291],"type":"Point"}
}