{
  "type": "Feature",
  "properties": {
    "iso:country":"DE",
    "sg:address":"Rudolf-Diesel-Str. 23",
    "sg:city":"G\u00fcnzburg",
    "sg:phone":"+49 8221/361601",
    "sg:postcode":"89312",
    "sg:province":"Bayern",
    "wof:name":"G\u00fcnzburger Steigtechnik Gmbh",
    "wof:placetype":"venue"
},
  "geometry": {"coordinates":[10.271389,48.477146],"type":"Point"}
}