{
  "type": "Feature",
  "properties": {
    "iso:country":"DE",
    "sg:address":"Willestr. 12",
    "sg:city":"Kiel",
    "sg:phone":"+49 431/95247",
    "sg:postcode":"24103",
    "sg:province":"Schleswig-Holstein",
    "wof:name":"Becker",
    "wof:placetype":"venue"
},
  "geometry": {"coordinates":[10.135357,54.322346],"type":"Point"}
}