{
  "type": "Feature",
  "properties": {
    "iso:country":"DE",
    "sg:address":"St.-J\u00fcrgen-Str. 29",
    "sg:city":"Laage",
    "sg:phone":"+49 38459/32377",
    "sg:postcode":"18299",
    "sg:province":"Mecklenburg-Vorpommern",
    "wof:name":"Sch\u00fclke Und Klukas",
    "wof:placetype":"venue"
},
  "geometry": {"coordinates":[12.3493719101,53.9236564636],"type":"Point"}
}