{
  "type": "Feature",
  "properties": {
    "iso:country":"DE",
    "sg:address":"Mittelstr. 38",
    "sg:city":"Monheim",
    "sg:phone":"+49 2173/52649",
    "sg:postcode":"40789",
    "sg:province":"Nordrhein-Westfalen",
    "wof:name":"H. Peter H\u00fcte",
    "wof:placetype":"venue"
},
  "geometry": {"coordinates":[6.8950371742,51.0930786133],"type":"Point"}
}