{
  "type": "Feature",
  "properties": {
    "iso:country":"DE",
    "sg:address":"Karl-Schurz-Str 26",
    "sg:city":"Paderborn",
    "sg:phone":"+49 5251/1530",
    "sg:postcode":"33100",
    "sg:province":"Nordrhein-Westfalen",
    "wof:name":"Bonifatius Gmbh",
    "wof:placetype":"venue"
},
  "geometry": {"coordinates":[8.790514946,51.7267951965],"type":"Point"}
}