{
  "type": "Feature",
  "properties": {
    "iso:country":"DE",
    "sg:address":"Schlesierweg 11",
    "sg:city":"Oberstenfeld",
    "sg:phone":"+49 7062/5249",
    "sg:postcode":"71720",
    "sg:province":"Baden-W\u00fcrttemberg",
    "wof:name":"Hans Belser Ingenieur",
    "wof:placetype":"venue"
},
  "geometry": {"coordinates":[9.3339929581,49.0271377563],"type":"Point"}
}