{
  "type": "Feature",
  "properties": {
    "iso:country":"DE",
    "sg:address":"Krugstr. 3",
    "sg:city":"Klein Ammensleben",
    "sg:phone":"+49 39202/60809",
    "sg:postcode":"39326",
    "sg:province":"Sachsen-Anhalt",
    "wof:name":"Arthur Maurer",
    "wof:placetype":"venue"
},
  "geometry": {"coordinates":[11.518609,52.218357],"type":"Point"}
}