{
  "type": "Feature",
  "properties": {
    "iso:country":"DE",
    "sg:address":"M\u00fcllerh\u00f6hstr. 19",
    "sg:city":"B\u00f6nnigheim",
    "sg:phone":"+49 7143/21175",
    "sg:postcode":"74357",
    "sg:province":"Baden-W\u00fcrttemberg",
    "wof:name":"Michael Schnell Gmbh",
    "wof:placetype":"venue"
},
  "geometry": {"coordinates":[9.095839,49.038414],"type":"Point"}
}