{
  "type": "Feature",
  "properties": {
    "iso:country":"DE",
    "sg:address":"Kaltenhausen 88",
    "sg:city":"Lehnin",
    "sg:phone":"+49 3382/700445",
    "sg:postcode":"14797",
    "sg:province":"Brandenburg",
    "wof:name":"Mosler Gmbh",
    "wof:placetype":"venue"
},
  "geometry": {"coordinates":[12.736089,52.321045],"type":"Point"}
}