{
  "type": "Feature",
  "properties": {
    "iso:country":"DE",
    "sg:address":"Friedrich-List-Str. 6",
    "sg:city":"Leinfelden-Echterdingen",
    "sg:phone":"+49 711/799610",
    "sg:postcode":"70771",
    "sg:province":"Baden-W\u00fcrttemberg",
    "wof:name":"Gikom Nis Deutschland Gmbh",
    "wof:placetype":"venue"
},
  "geometry": {"coordinates":[9.1608819962,48.691608429],"type":"Point"}
}