{
  "type": "Feature",
  "properties": {
    "iso:country":"DE",
    "sg:address":"Schulzendorfer Str. 44",
    "sg:city":"Berlin",
    "sg:postcode":"13503",
    "sg:province":"Berlin",
    "wof:name":"Fsh Anlagen Der Haustechnik Gmbh",
    "wof:placetype":"venue"
},
  "geometry": {"coordinates":[13.2366790771,52.613445282],"type":"Point"}
}