{
  "type": "Feature",
  "properties": {
    "iso:country":"DE",
    "sg:address":"Kronenstr. 1a",
    "sg:city":"Saarbr\u00fccken",
    "sg:phone":"+49 681/373949",
    "sg:postcode":"66111",
    "sg:province":"Saarland",
    "wof:name":"Mulde",
    "wof:placetype":"venue"
},
  "geometry": {"coordinates":[6.9959349632,49.2322998047],"type":"Point"}
}