{
  "type": "Feature",
  "properties": {
    "iso:country":"DE",
    "sg:address":"Uferstr. 62",
    "sg:city":"Teublitz",
    "sg:phone":"+49 9471/97261",
    "sg:postcode":"93158",
    "sg:province":"Bayern",
    "wof:name":"Maria Popp",
    "wof:placetype":"venue"
},
  "geometry": {"coordinates":[12.08345,49.241035],"type":"Point"}
}