{
  "type": "Feature",
  "properties": {
    "iso:country":"DE",
    "sg:address":"F\u00fcrstenbergstr. 2",
    "sg:city":"L\u00f6ffingen",
    "sg:phone":"+49 7654/242",
    "sg:postcode":"79843",
    "sg:province":"Baden-W\u00fcrttemberg",
    "wof:name":"Krieg Vieh- Und Fleisch- Gro\u00dfhandel Gmbh",
    "wof:placetype":"venue"
},
  "geometry": {"coordinates":[8.3441028595,47.8884963989],"type":"Point"}
}