{
  "type": "Feature",
  "properties": {
    "iso:country":"DE",
    "sg:address":"Ostbredenstr. 62",
    "sg:city":"Ahlen",
    "sg:phone":"+49 2382/61847",
    "sg:postcode":"59229",
    "sg:province":"Nordrhein-Westfalen",
    "wof:name":"Petanque-club Ahlen La Difference Im Asc",
    "wof:placetype":"venue"
},
  "geometry": {"coordinates":[7.9066801071,51.7615737915],"type":"Point"}
}