{
  "type": "Feature",
  "properties": {
    "iso:country":"DE",
    "sg:address":"Hainsberg 13",
    "sg:city":"Langenwetzendorf",
    "sg:phone":"+49 36625/20880",
    "sg:postcode":"07957",
    "sg:province":"Th\u00fcringen",
    "wof:name":"G\u00fcnter R\u00f6del Anlageberater",
    "wof:placetype":"venue"
},
  "geometry": {"coordinates":[12.0924282074,50.6915817261],"type":"Point"}
}