{
  "type": "Feature",
  "properties": {
    "iso:country":"DE",
    "sg:address":"Ascher Str. 8",
    "sg:city":"Bergh\u00fclen",
    "sg:phone":"+49 7344/7015",
    "sg:postcode":"89180",
    "sg:province":"Baden-W\u00fcrttemberg",
    "wof:name":"C. Anhorn",
    "wof:placetype":"venue"
},
  "geometry": {"coordinates":[9.781028,48.457882],"type":"Point"}
}