{
  "type": "Feature",
  "properties": {
    "iso:country":"DE",
    "sg:address":"Altk\u00f6nigstr. 1",
    "sg:city":"K\u00f6nigstein",
    "sg:phone":"+49 6174/930005",
    "sg:postcode":"61462",
    "sg:province":"Hessen",
    "wof:name":"Gok Gesellschaft F\u00fcr Organi- Sations- Und Kommunikations-",
    "wof:placetype":"venue"
},
  "geometry": {"coordinates":[8.466913,50.188427],"type":"Point"}
}