{
  "type": "Feature",
  "properties": {
    "iso:country":"DE",
    "sg:address":"Louis-Bardorf-Str. 2",
    "sg:city":"Waltershausen",
    "sg:postcode":"99880",
    "sg:province":"Th\u00fcringen",
    "wof:name":"Merkantil Beratungs- Entwicklungs- Und",
    "wof:placetype":"venue"
},
  "geometry": {"coordinates":[10.5576667786,50.8966140747],"type":"Point"}
}