{
  "type": "Feature",
  "properties": {
    "iso:country":"DE",
    "sg:address":"Viktoriastr. 50",
    "sg:city":"Saarbr\u00fccken",
    "sg:phone":"+49 681/308398",
    "sg:postcode":"66111",
    "sg:province":"Saarland",
    "wof:name":"Deutsche Bahn Ag",
    "wof:placetype":"venue"
},
  "geometry": {"coordinates":[6.9923701286,49.2393188477],"type":"Point"}
}