{
  "type": "Feature",
  "properties": {
    "iso:country":"DE",
    "sg:address":"Niebuhrstr. 66",
    "sg:city":"Berlin",
    "sg:phone":"+49 30/3232635",
    "sg:postcode":"10629",
    "sg:province":"Berlin",
    "wof:name":"J\u00fcrgen Schmidt Buch- Und Graphikrestaurator",
    "wof:placetype":"venue"
},
  "geometry": {"coordinates":[13.3121929169,52.5043144226],"type":"Point"}
}