{
  "type": "Feature",
  "properties": {
    "iso:country":"DE",
    "sg:address":"Herzog-Philipp-Str 50",
    "sg:city":"Winnenden",
    "sg:phone":"+49 7195/76023",
    "sg:postcode":"71364",
    "sg:province":"Baden-W\u00fcrttemberg",
    "wof:name":"Tv-is Hoehne Tv-inspektions-systeme",
    "wof:placetype":"venue"
},
  "geometry": {"coordinates":[9.437307,48.859493],"type":"Point"}
}