{
  "type": "Feature",
  "properties": {
    "iso:country":"DE",
    "sg:address":"Bahnhofstr. 11",
    "sg:city":"Heidenau",
    "sg:phone":"+49 3529/515547",
    "sg:postcode":"01809",
    "sg:province":"Sachsen",
    "wof:name":"Pia Keyser",
    "wof:placetype":"venue"
},
  "geometry": {"coordinates":[13.86421,50.979839],"type":"Point"}
}