{
  "type": "Feature",
  "properties": {
    "iso:country":"DE",
    "sg:address":"St.-Valentinus-Str.",
    "sg:city":"Birkenfeld",
    "sg:phone":"+49 9398/678",
    "sg:postcode":"97834",
    "sg:province":"Bayern",
    "wof:name":"Egerbachhalle Birkenfeld",
    "wof:placetype":"venue"
},
  "geometry": {"coordinates":[9.695822,49.855503],"type":"Point"}
}