{
  "type": "Feature",
  "properties": {
    "iso:country":"DE",
    "sg:address":"am g\u00e4nseberg 10",
    "sg:city":"osterode",
    "sg:phone":"+49 5552/1256",
    "sg:postcode":"37520",
    "sg:province":"Niedersachsen",
    "wof:name":"Old House Adventure",
    "wof:placetype":"venue"
},
  "geometry": {"coordinates":[10.30898,51.676579],"type":"Point"}
}