{
  "type": "Feature",
  "properties": {
    "iso:country":"DE",
    "sg:address":"Emder Str. 5",
    "sg:city":"Ihlow",
    "sg:phone":"+49 4928/1789",
    "sg:postcode":"26632",
    "sg:province":"Niedersachsen",
    "wof:name":"Heinz Schwartinsky",
    "wof:placetype":"venue"
},
  "geometry": {"coordinates":[7.288406,53.3899],"type":"Point"}
}