{
  "type": "Feature",
  "properties": {
    "iso:country":"DE",
    "sg:address":"Tornescher Hof",
    "sg:city":"Tornesch",
    "sg:phone":"+49 4122/55756",
    "sg:postcode":"25436",
    "sg:province":"Schleswig-Holstein",
    "wof:name":"Gemeindeb\u00fccherei Tornesch",
    "wof:placetype":"venue"
},
  "geometry": {"coordinates":[9.71317,53.696606],"type":"Point"}
}