{
  "type": "Feature",
  "properties": {
    "iso:country":"DE",
    "sg:address":"Kronprinzstr. 59",
    "sg:city":"Langenfeld",
    "sg:phone":"+49 2173/22891",
    "sg:postcode":"40764",
    "sg:province":"Nordrhein-Westfalen",
    "wof:name":"H. Kinzer Heissmangelbetrieb",
    "wof:placetype":"venue"
},
  "geometry": {"coordinates":[6.9688658714,51.1212768555],"type":"Point"}
}