{
  "type": "Feature",
  "properties": {
    "iso:country":"DE",
    "sg:address":"Kreuzberger Ring 13",
    "sg:city":"Wiesbaden",
    "sg:phone":"+49 611/977770",
    "sg:postcode":"65205",
    "sg:province":"Hessen",
    "wof:name":"Ugw Ag",
    "wof:placetype":"venue"
},
  "geometry": {"coordinates":[8.2922439575,50.054473877],"type":"Point"}
}