{
  "type": "Feature",
  "properties": {
    "iso:country":"DE",
    "sg:address":"Reinhardswaldstr. 6",
    "sg:city":"Bremen",
    "sg:phone":"+49 421/487152",
    "sg:postcode":"28307",
    "sg:province":"Bremen",
    "wof:name":"Elektro Hoffmann Inh. Detlef Hoffmann E. Kfm.",
    "wof:placetype":"venue"
},
  "geometry": {"coordinates":[8.9122438431,53.045463562],"type":"Point"}
}