{
  "type": "Feature",
  "properties": {
    "iso:country":"DE",
    "sg:address":"Schuhstr. 45",
    "sg:city":"Lemgo",
    "sg:phone":"+49 5261/3900",
    "sg:postcode":"32657",
    "sg:province":"Nordrhein-Westfalen",
    "wof:name":"Piechot Dental-labor Kg",
    "wof:placetype":"venue"
},
  "geometry": {"coordinates":[8.9037981033,52.0259132385],"type":"Point"}
}