{
  "type": "Feature",
  "properties": {
    "iso:country":"DE",
    "sg:address":"Freiligrathstr. 104 a",
    "sg:city":"Wuppertal",
    "sg:phone":"+49 202/699900",
    "sg:postcode":"42289",
    "sg:province":"Nordrhein-Westfalen",
    "wof:name":"Pro Objekt Projektgesellschaft Planen Und Bauen",
    "wof:placetype":"venue"
},
  "geometry": {"coordinates":[7.21707201,51.2664794922],"type":"Point"}
}