{
  "type": "Feature",
  "properties": {
    "iso:country":"DE",
    "sg:address":"Bussenstr. 9",
    "sg:city":"Markdorf",
    "sg:phone":"+49 7544/3808",
    "sg:postcode":"88677",
    "sg:province":"Baden-W\u00fcrttemberg",
    "wof:name":"Rudolf Fleck",
    "wof:placetype":"venue"
},
  "geometry": {"coordinates":[9.388968,47.722141],"type":"Point"}
}