{
  "type": "Feature",
  "properties": {
    "iso:country":"DE",
    "sg:address":"Vier Grenzen 1",
    "sg:city":"Hannover",
    "sg:phone":"+49 511/669956",
    "sg:postcode":"30177",
    "sg:province":"Niedersachsen",
    "wof:name":"Anita Helbing",
    "wof:placetype":"venue"
},
  "geometry": {"coordinates":[9.763017,52.394794],"type":"Point"}
}