{
  "type": "Feature",
  "properties": {
    "iso:country":"DE",
    "sg:address":"Augustinerstr. 1",
    "sg:city":"W\u00fcrzburg",
    "sg:phone":"+49 931/54554",
    "sg:postcode":"97070",
    "sg:province":"Bayern",
    "wof:name":"System Clean Geb\u00e4ude- Reinigung Gmbh",
    "wof:placetype":"venue"
},
  "geometry": {"coordinates":[9.928813,49.792362],"type":"Point"}
}