{
  "type": "Feature",
  "properties": {
    "iso:country":"DE",
    "sg:address":"Roteb\u00fchlplatz 20",
    "sg:city":"Stuttgart",
    "sg:phone":"+49 711/2264978",
    "sg:postcode":"70173",
    "sg:province":"Baden-W\u00fcrttemberg",
    "wof:name":"Mc Donald's",
    "wof:placetype":"venue"
},
  "geometry": {"coordinates":[9.172211647,48.7749481201],"type":"Point"}
}