{
  "type": "Feature",
  "properties": {
    "iso:country":"DE",
    "sg:address":"Schillerstr. 2",
    "sg:city":"Karlsruhe",
    "sg:phone":"+49 721/856939",
    "sg:postcode":"76135",
    "sg:province":"Baden-W\u00fcrttemberg",
    "wof:name":"Eisfeld",
    "wof:placetype":"venue"
},
  "geometry": {"coordinates":[8.3795862198,49.0104179382],"type":"Point"}
}