{
  "type": "Feature",
  "properties": {
    "iso:country":"DE",
    "sg:address":"Paderborner Str. 101",
    "sg:city":"Dortmund",
    "sg:phone":"+49 231/516606",
    "sg:postcode":"44143",
    "sg:province":"Nordrhein-Westfalen",
    "wof:name":"Elisabeth Menge Hebamme",
    "wof:placetype":"venue"
},
  "geometry": {"coordinates":[7.509139,51.515144],"type":"Point"}
}