{
  "type": "Feature",
  "properties": {
    "iso:country":"DE",
    "sg:address":"Stadtgutstr. 18",
    "sg:city":"Werdau",
    "sg:phone":"+49 3761/2972",
    "sg:postcode":"08412",
    "sg:province":"Sachsen",
    "wof:name":"Werner Dietel",
    "wof:placetype":"venue"
},
  "geometry": {"coordinates":[12.367165,50.735214],"type":"Point"}
}