{
  "type": "Feature",
  "properties": {
    "iso:country":"DE",
    "sg:address":"Sch\u00f6ngeisinger Str. 41",
    "sg:city":"F\u00fcrstenfeldbruck",
    "sg:phone":"+49 8141/346960",
    "sg:postcode":"82256",
    "sg:province":"Bayern",
    "wof:name":"Sportreisen M\u00fcller",
    "wof:placetype":"venue"
},
  "geometry": {"coordinates":[11.251663208,48.1764297485],"type":"Point"}
}