{
  "type": "Feature",
  "properties": {
    "iso:country":"DE",
    "sg:address":"Gutenberger Str. 20",
    "sg:city":"Wallhausen",
    "sg:phone":"+49 6706/285",
    "sg:postcode":"55595",
    "sg:province":"Rheinland-Pfalz",
    "wof:name":"Oswald Und Hardy Weis",
    "wof:placetype":"venue"
},
  "geometry": {"coordinates":[7.776169,49.887745],"type":"Point"}
}