{
  "type": "Feature",
  "properties": {
    "iso:country":"DE",
    "sg:address":"Europaall. 10",
    "sg:city":"Kaiserslautern",
    "sg:phone":"+49 631/3035000",
    "sg:postcode":"67657",
    "sg:province":"Rheinland-Pfalz",
    "wof:name":"Tecmath Ag",
    "wof:placetype":"venue"
},
  "geometry": {"coordinates":[7.804254,49.456192],"type":"Point"}
}