{
  "type": "Feature",
  "properties": {
    "iso:country":"DE",
    "sg:address":"Borsigstr. 8",
    "sg:city":"Wiesbaden",
    "sg:phone":"+49 6122/92360",
    "sg:postcode":"65205",
    "sg:province":"Hessen",
    "wof:name":"Rkb Beratungsgesell. F\u00fcr Betriebl. Altersversorgung Mbh",
    "wof:placetype":"venue"
},
  "geometry": {"coordinates":[8.337184906,50.05727005],"type":"Point"}
}