{
  "type": "Feature",
  "properties": {
    "iso:country":"DE",
    "sg:address":"Vangerowstr. 37",
    "sg:city":"Heidelberg",
    "sg:postcode":"69115",
    "sg:province":"Baden-W\u00fcrttemberg",
    "wof:name":"Philipp Gmbh",
    "wof:placetype":"venue"
},
  "geometry": {"coordinates":[8.6745634079,49.4086875916],"type":"Point"}
}