{
  "type": "Feature",
  "properties": {
    "iso:country":"DE",
    "sg:address":"Gro\u00dfe Heimstr. 117",
    "sg:city":"Dortmund",
    "sg:phone":"+49 231/128243",
    "sg:postcode":"44137",
    "sg:province":"Nordrhein-Westfalen",
    "wof:name":"Helmut W\u00fcstefeld Bildhauer",
    "wof:placetype":"venue"
},
  "geometry": {"coordinates":[7.449906,51.501507],"type":"Point"}
}