{
  "type": "Feature",
  "properties": {
    "iso:country":"DE",
    "sg:address":"Garbenteicher Str.",
    "sg:city":"Pohlheim",
    "sg:postcode":"35415",
    "sg:province":"Hessen",
    "wof:name":"Behindertenwerkstatt",
    "wof:placetype":"venue"
},
  "geometry": {"coordinates":[8.743395,50.541759],"type":"Point"}
}