{
  "type": "Feature",
  "properties": {
    "iso:country":"DE",
    "sg:address":"Marienstr. 9",
    "sg:city":"Hofheim",
    "sg:postcode":"65719",
    "sg:province":"Hessen",
    "wof:name":"Axona Gmbh",
    "wof:placetype":"venue"
},
  "geometry": {"coordinates":[8.445746,50.091164],"type":"Point"}
}