{
  "type": "Feature",
  "properties": {
    "iso:country":"DE",
    "sg:address":"Industriestr. 1",
    "sg:city":"Langenselbold",
    "sg:phone":"+49 6184/2107",
    "sg:postcode":"63505",
    "sg:province":"Hessen",
    "wof:name":"Heinz Wiegand Mineral\u00f6l-grosshandel",
    "wof:placetype":"venue"
},
  "geometry": {"coordinates":[9.0508060455,50.1645317078],"type":"Point"}
}