{
  "type": "Feature",
  "properties": {
    "iso:country":"DE",
    "sg:address":"Marienstr. 14",
    "sg:city":"Aldenhoven",
    "sg:phone":"+49 2464/8088",
    "sg:postcode":"52457",
    "sg:province":"Nordrhein-Westfalen",
    "wof:name":"Taverne",
    "wof:placetype":"venue"
},
  "geometry": {"coordinates":[6.2811908722,50.8968582153],"type":"Point"}
}