{
  "type": "Feature",
  "properties": {
    "iso:country":"DE",
    "sg:address":"Am Weinberg 5",
    "sg:city":"Mittenaar",
    "sg:phone":"+49 2772/62914",
    "sg:postcode":"35756",
    "sg:province":"Hessen",
    "wof:name":"Wohnheim F\u00fcr Erwachsene Behinderte Menschen",
    "wof:placetype":"venue"
},
  "geometry": {"coordinates":[8.3813352585,50.6944236755],"type":"Point"}
}