{
  "type": "Feature",
  "properties": {
    "iso:country":"DE",
    "sg:address":"Nathanaelstr. 13",
    "sg:city":"Leipzig",
    "sg:phone":"+49 341/4802847",
    "sg:postcode":"04177",
    "sg:province":"Sachsen",
    "wof:name":"Engelmann Gmbh",
    "wof:placetype":"venue"
},
  "geometry": {"coordinates":[12.33108,51.33939],"type":"Point"}
}