{
  "type": "Feature",
  "properties": {
    "iso:country":"DE",
    "sg:address":"Frohnhofer Str. 4 a",
    "sg:city":"Breitenbach",
    "sg:phone":"+49 6386/6329",
    "sg:postcode":"66916",
    "sg:province":"Rheinland-Pfalz",
    "wof:name":"Walter Koch",
    "wof:placetype":"venue"
},
  "geometry": {"coordinates":[7.272171,49.434101],"type":"Point"}
}