{
  "type": "Feature",
  "properties": {
    "iso:country":"DE",
    "sg:address":"Siemensstr. 5 a",
    "sg:city":"Friesenheim",
    "sg:postcode":"77948",
    "sg:province":"Baden-W\u00fcrttemberg",
    "wof:name":"Pro Fina Leasing- Gesellschaft Mbh",
    "wof:placetype":"venue"
},
  "geometry": {"coordinates":[7.864539,48.381104],"type":"Point"}
}