{
  "type": "Feature",
  "properties": {
    "iso:country":"DE",
    "sg:address":"Zwickauer Str.33",
    "sg:city":"Dresden",
    "sg:phone":"+49 351/4715681",
    "sg:postcode":"01097",
    "sg:province":"Sachsen",
    "wof:name":"Heyne",
    "wof:placetype":"venue"
},
  "geometry": {"coordinates":[13.73981,51.066978],"type":"Point"}
}