{
  "type": "Feature",
  "properties": {
    "iso:country":"DE",
    "sg:address":"Mechenharder Str. 201",
    "sg:city":"Erlenbach",
    "sg:phone":"+49 9372/71621",
    "sg:postcode":"63906",
    "sg:province":"Bayern",
    "wof:name":"Bergblick",
    "wof:placetype":"venue"
},
  "geometry": {"coordinates":[9.1979866028,49.7951545715],"type":"Point"}
}