{
  "type": "Feature",
  "properties": {
    "iso:country":"DE",
    "sg:address":"Niddastr. 98/102",
    "sg:city":"Frankfurt",
    "sg:postcode":"60329",
    "sg:province":"Hessen",
    "wof:name":"Contract Gmbh",
    "wof:placetype":"venue"
},
  "geometry": {"coordinates":[8.658323288,50.1075515747],"type":"Point"}
}