{
  "type": "Feature",
  "properties": {
    "iso:country":"DE",
    "sg:address":"Kirchbergstr. 45",
    "sg:city":"Weingarten",
    "sg:phone":"+49 7244/1798",
    "sg:postcode":"76356",
    "sg:province":"Baden-W\u00fcrttemberg",
    "wof:name":"Ludwig Pfister",
    "wof:placetype":"venue"
},
  "geometry": {"coordinates":[8.538693428,49.0488967896],"type":"Point"}
}