{
  "type": "Feature",
  "properties": {
    "iso:country":"DE",
    "sg:address":"Blumenauer Bruch 2",
    "sg:city":"Mannheim",
    "sg:phone":"+49 621/783468",
    "sg:postcode":"68307",
    "sg:province":"Baden-W\u00fcrttemberg",
    "wof:name":"Rudi Und Emil R\u00f6ck",
    "wof:placetype":"venue"
},
  "geometry": {"coordinates":[8.471976,49.574055],"type":"Point"}
}