{
  "type": "Feature",
  "properties": {
    "iso:country":"DE",
    "sg:address":"Westf\u00e4lische Str. 41",
    "sg:city":"Lennestadt",
    "sg:postcode":"57368",
    "sg:province":"Nordrhein-Westfalen",
    "wof:name":"Nolting & B\u00f6hler Freizeit- Und Ferienpark",
    "wof:placetype":"venue"
},
  "geometry": {"coordinates":[7.9989728928,51.0909996033],"type":"Point"}
}