{
  "type": "Feature",
  "properties": {
    "iso:country":"DE",
    "sg:address":"Mauerbergstr. 21",
    "sg:city":"Baden-Baden",
    "sg:phone":"+49 4972/2396670",
    "sg:postcode":"76534",
    "sg:province":"Baden-W\u00fcrttemberg",
    "wof:name":"Weingut Schloss Neuweier",
    "wof:placetype":"venue"
},
  "geometry": {"coordinates":[8.20265,48.715439],"type":"Point"}
}