{
  "type": "Feature",
  "properties": {
    "iso:country":"DE",
    "sg:address":"W\u00f6rthstr. 9",
    "sg:city":"Oberhausen",
    "sg:phone":"+49 208/20815",
    "sg:postcode":"46045",
    "sg:province":"Nordrhein-Westfalen",
    "wof:name":"Vertrauens\u00e4rztlicher-dienst D. Lva Rheinprovinz",
    "wof:placetype":"venue"
},
  "geometry": {"coordinates":[6.8546319008,51.4682426453],"type":"Point"}
}