{
  "type": "Feature",
  "properties": {
    "iso:country":"DE",
    "sg:address":"Graf-Zeppelin-Str. 11",
    "sg:city":"Altenkirchen",
    "sg:phone":"+49 2681/95100",
    "sg:postcode":"57610",
    "sg:province":"Rheinland-Pfalz",
    "wof:name":"Ake-gesellschaft Der Entsorgungsunternehmen",
    "wof:placetype":"venue"
},
  "geometry": {"coordinates":[7.639905,50.686508],"type":"Point"}
}