{
  "type": "Feature",
  "properties": {
    "iso:country":"DE",
    "sg:address":"F\u00f6hrenweg 9b",
    "sg:city":"Kleinsendelbach",
    "sg:phone":"+49 9126/299059",
    "sg:postcode":"91077",
    "sg:province":"Bayern",
    "wof:name":"Rkm-immobilien Gmbh",
    "wof:placetype":"venue"
},
  "geometry": {"coordinates":[11.1672697067,49.5938873291],"type":"Point"}
}