{
  "type": "Feature",
  "properties": {
    "iso:country":"DE",
    "sg:address":"Im Oberfeld 3",
    "sg:city":"Leverkusen",
    "sg:phone":"+49 2171/30807",
    "sg:postcode":"51381",
    "sg:province":"Nordrhein-Westfalen",
    "wof:name":"E. Bruch & Co. Nachf. Inh. Ulrich Zemke",
    "wof:placetype":"venue"
},
  "geometry": {"coordinates":[7.055835,51.092457],"type":"Point"}
}