{
  "type": "Feature",
  "properties": {
    "iso:country":"DE",
    "sg:address":"Alberting 35",
    "sg:city":"Grafling",
    "sg:phone":"+49 991/25326",
    "sg:postcode":"94539",
    "sg:province":"Bayern",
    "wof:name":"Kollers Ferkelexpress Transport Gmbh",
    "wof:placetype":"venue"
},
  "geometry": {"coordinates":[12.9656496048,48.8707695007],"type":"Point"}
}