{
  "type": "Feature",
  "properties": {
    "iso:country":"DE",
    "sg:address":"Brunnenstr. 1",
    "sg:city":"Wuppertal",
    "sg:phone":"+49 202/312202",
    "sg:postcode":"42105",
    "sg:province":"Nordrhein-Westfalen",
    "wof:name":"Restaurant Caribe",
    "wof:placetype":"venue"
},
  "geometry": {"coordinates":[7.1366448402,51.2616233826],"type":"Point"}
}