{
  "type": "Feature",
  "properties": {
    "iso:country":"DE",
    "sg:address":"Schwabenstr. 31",
    "sg:city":"Reutlingen",
    "sg:phone":"+49 7121/628700",
    "sg:postcode":"72768",
    "sg:province":"Baden-W\u00fcrttemberg",
    "wof:name":"Bit Beratungsges. F. Inhouse- Und",
    "wof:placetype":"venue"
},
  "geometry": {"coordinates":[9.206284,48.530914],"type":"Point"}
}