{
  "type": "Feature",
  "properties": {
    "iso:country":"DE",
    "sg:address":"Niederndodeleber Str. 11c",
    "sg:city":"Irxleben",
    "sg:phone":"+49 39204/66670",
    "sg:postcode":"39167",
    "sg:province":"Sachsen-Anhalt",
    "wof:name":"Heidenreich Glas- Geb\u00e4ude- Und Industriereinigung",
    "wof:placetype":"venue"
},
  "geometry": {"coordinates":[11.48437,52.163223],"type":"Point"}
}