{
  "type": "Feature",
  "properties": {
    "iso:country":"DE",
    "sg:address":"Am Riedweg 16",
    "sg:city":"Salem",
    "sg:phone":"+49 7553/6166",
    "sg:postcode":"88682",
    "sg:province":"Baden-W\u00fcrttemberg",
    "wof:name":"Casablanca",
    "wof:placetype":"venue"
},
  "geometry": {"coordinates":[9.30013,47.757435],"type":"Point"}
}