{
  "type": "Feature",
  "properties": {
    "iso:country":"DE",
    "sg:address":"G\u00f6rlitzer Str. 5",
    "sg:city":"Verl",
    "sg:phone":"+49 5246/5190",
    "sg:postcode":"33415",
    "sg:province":"Nordrhein-Westfalen",
    "wof:name":"Matthias H\u00f6ber",
    "wof:placetype":"venue"
},
  "geometry": {"coordinates":[8.4697189331,51.8910751343],"type":"Point"}
}