{
  "type": "Feature",
  "properties": {
    "iso:country":"DE",
    "sg:address":"80331",
    "sg:city":"Munich",
    "sg:phone":"+49 89/759060",
    "sg:postcode":"80331",
    "sg:province":"Bayern",
    "wof:name":"Raiffeisenbank M\u00fcnchen-sud Eg",
    "wof:placetype":"venue"
},
  "geometry": {"coordinates":[11.58294,48.133621],"type":"Point"}
}