{
  "type": "Feature",
  "properties": {
    "iso:country":"DE",
    "sg:address":"Wehringhauser Str. 25 b",
    "sg:city":"Hagen",
    "sg:postcode":"58089",
    "sg:province":"Nordrhein-Westfalen",
    "wof:name":"Hg - Haus & Grund Immobilien Gmbh",
    "wof:placetype":"venue"
},
  "geometry": {"coordinates":[7.4571089745,51.3571357727],"type":"Point"}
}