{
  "type": "Feature",
  "properties": {
    "iso:country":"DE",
    "sg:address":"Friemer Str. 3",
    "sg:city":"Waldkappel",
    "sg:phone":"+49 5656/4311",
    "sg:postcode":"37284",
    "sg:province":"Hessen",
    "wof:name":"Christian Degenhardt Gmbh",
    "wof:placetype":"venue"
},
  "geometry": {"coordinates":[9.873291,51.143681],"type":"Point"}
}