{
  "type": "Feature",
  "properties": {
    "iso:country":"DE",
    "sg:address":"Falkenweg 28",
    "sg:city":"Emsdetten",
    "sg:phone":"+49 2572/5354",
    "sg:postcode":"48282",
    "sg:province":"Nordrhein-Westfalen",
    "wof:name":"Paul Br\u00f6mmelhaus",
    "wof:placetype":"venue"
},
  "geometry": {"coordinates":[7.511166,52.16674],"type":"Point"}
}