{
  "type": "Feature",
  "properties": {
    "iso:country":"DE",
    "sg:address":"Schnaitheimer Weg 20",
    "sg:city":"Steinheim",
    "sg:phone":"+49 7329/366",
    "sg:postcode":"89555",
    "sg:province":"Baden-W\u00fcrttemberg",
    "wof:name":"G\u00fcnter Ontrup",
    "wof:placetype":"venue"
},
  "geometry": {"coordinates":[10.071663,48.693279],"type":"Point"}
}