{
  "type": "Feature",
  "properties": {
    "iso:country":"DE",
    "sg:address":"Am Sonderbach",
    "sg:city":"Heppenheim",
    "sg:phone":"+49 6252/3850",
    "sg:postcode":"64646",
    "sg:province":"Hessen",
    "wof:name":"Kurt Fischer Bauschlosserei",
    "wof:placetype":"venue"
},
  "geometry": {"coordinates":[8.689988,49.637943],"type":"Point"}
}