{
  "type": "Feature",
  "properties": {
    "iso:country":"DE",
    "sg:address":"Linnicher Str. 5",
    "sg:city":"Alsdorf",
    "sg:phone":"+49 2404/919653",
    "sg:postcode":"52477",
    "sg:province":"Nordrhein-Westfalen",
    "wof:name":"Ortz",
    "wof:placetype":"venue"
},
  "geometry": {"coordinates":[6.1667490005,50.87890625],"type":"Point"}
}