{
  "type": "Feature",
  "properties": {
    "iso:country":"DE",
    "sg:address":"Wiesenstr. 5",
    "sg:city":"Bad Homburg",
    "sg:phone":"+49 6172/459530",
    "sg:postcode":"61352",
    "sg:province":"Hessen",
    "wof:name":"Stephan Kubitzki",
    "wof:placetype":"venue"
},
  "geometry": {"coordinates":[8.6283159256,50.2183189392],"type":"Point"}
}