{
  "type": "Feature",
  "properties": {
    "iso:country":"DE",
    "sg:address":"Salomon-Idler-Str. 22 c",
    "sg:city":"Augsburg",
    "sg:phone":"+49 821/591439",
    "sg:postcode":"86159",
    "sg:province":"Bayern",
    "wof:name":"Pianohaus Janos",
    "wof:placetype":"venue"
},
  "geometry": {"coordinates":[10.9012727737,48.3329772949],"type":"Point"}
}