{
  "type": "Feature",
  "properties": {
    "iso:country":"DE",
    "sg:address":"Dammkarstr. 12",
    "sg:city":"Mittenwald",
    "sg:phone":"+49 8823/8089",
    "sg:postcode":"82481",
    "sg:province":"Bayern",
    "wof:name":"G\u00e4stehaus Bergfr\u00fchling",
    "wof:placetype":"venue"
},
  "geometry": {"coordinates":[11.2649002075,47.4416465759],"type":"Point"}
}