{
  "type": "Feature",
  "properties": {
    "iso:country":"DE",
    "sg:address":"Friedrichstr. 2",
    "sg:city":"Erlangen",
    "sg:phone":"+49 9131/23883",
    "sg:postcode":"91054",
    "sg:province":"Bayern",
    "wof:name":"Sommerfeld",
    "wof:placetype":"venue"
},
  "geometry": {"coordinates":[11.0065765381,49.5957298279],"type":"Point"}
}