{
  "type": "Feature",
  "properties": {
    "iso:country":"DE",
    "sg:address":"Bojestr. 36",
    "sg:city":"Brunsb\u00fcttel",
    "sg:phone":"+49 4852/2647",
    "sg:postcode":"25541",
    "sg:province":"Schleswig-Holstein",
    "wof:name":"Kath. Pfarramt Stella Maris",
    "wof:placetype":"venue"
},
  "geometry": {"coordinates":[9.138923645,53.9001808167],"type":"Point"}
}