{
  "type": "Feature",
  "properties": {
    "iso:country":"DE",
    "sg:address":"Sonneberger Str. 18",
    "sg:city":"Bremen",
    "sg:phone":"+49 421/436340",
    "sg:postcode":"28329",
    "sg:province":"Bremen",
    "wof:name":"Mwb Handels-gmbh",
    "wof:placetype":"venue"
},
  "geometry": {"coordinates":[8.87555,53.080891],"type":"Point"}
}