{
  "type": "Feature",
  "properties": {
    "iso:country":"DE",
    "sg:address":"Drechslerweg 6",
    "sg:city":"Waldkappel",
    "sg:phone":"+49 5656/92043",
    "sg:postcode":"37284",
    "sg:province":"Hessen",
    "wof:name":"Karl Marth",
    "wof:placetype":"venue"
},
  "geometry": {"coordinates":[9.810065,51.134205],"type":"Point"}
}