{
  "type": "Feature",
  "properties": {
    "iso:country":"DE",
    "sg:address":"Katharinenstr. 8",
    "sg:city":"Landsberg",
    "sg:phone":"+49 8191/5162",
    "sg:postcode":"86899",
    "sg:province":"Bayern",
    "wof:name":"Huber-moden Gmbh",
    "wof:placetype":"venue"
},
  "geometry": {"coordinates":[10.8712539673,48.0461196899],"type":"Point"}
}