{
  "type": "Feature",
  "properties": {
    "iso:country":"DE",
    "sg:address":"Minnholzweg 2 b",
    "sg:city":"Kronberg",
    "sg:postcode":"61476",
    "sg:province":"Hessen",
    "wof:name":"Thoranet Unternehmensberatung F\u00fcr Netzwerk Und System-",
    "wof:placetype":"venue"
},
  "geometry": {"coordinates":[8.5164279938,50.1786155701],"type":"Point"}
}