{
  "type": "Feature",
  "properties": {
    "iso:country":"DE",
    "sg:address":"Bayernstr. 13b",
    "sg:city":"K\u00f6nigsbrunn",
    "sg:phone":"+49 8231/88787",
    "sg:postcode":"86343",
    "sg:province":"Bayern",
    "wof:name":"H. Sedelmaier",
    "wof:placetype":"venue"
},
  "geometry": {"coordinates":[10.895403862,48.2731437683],"type":"Point"}
}