{
  "type": "Feature",
  "properties": {
    "iso:country":"DE",
    "sg:address":"Katzenlohstr. 23",
    "sg:city":"Schopfheim",
    "sg:phone":"+49 7622/62444",
    "sg:postcode":"79650",
    "sg:province":"Baden-W\u00fcrttemberg",
    "wof:name":"Ing.-b\u00fcro Adam Gmbh",
    "wof:placetype":"venue"
},
  "geometry": {"coordinates":[7.8167800903,47.6383285522],"type":"Point"}
}