{
  "type": "Feature",
  "properties": {
    "iso:country":"DE",
    "sg:address":"Letterhausstr. 54",
    "sg:city":"Hagen",
    "sg:phone":"+49 2331/61092",
    "sg:postcode":"58099",
    "sg:province":"Nordrhein-Westfalen",
    "wof:name":"Fritz Granowski Ingenieur",
    "wof:placetype":"venue"
},
  "geometry": {"coordinates":[7.4885988235,51.3966445923],"type":"Point"}
}