{
  "type": "Feature",
  "properties": {
    "iso:country":"DE",
    "sg:address":"K\u00f6nigsteiner Str. 80",
    "sg:city":"Bad Soden",
    "sg:phone":"+49 6196/643067",
    "sg:postcode":"65812",
    "sg:province":"Hessen",
    "wof:name":"Sodenia Immobilien Gmbh",
    "wof:placetype":"venue"
},
  "geometry": {"coordinates":[8.5023603439,50.1435661316],"type":"Point"}
}