{
  "type": "Feature",
  "properties": {
    "iso:country":"DE",
    "sg:address":"Im Osterholz 21",
    "sg:city":"Asperg",
    "sg:phone":"+49 7141/664459",
    "sg:postcode":"71679",
    "sg:province":"Baden-W\u00fcrttemberg",
    "wof:name":"Gastst\u00e4tte Tsv",
    "wof:placetype":"venue"
},
  "geometry": {"coordinates":[9.1440286636,48.9031295776],"type":"Point"}
}