{
  "type": "Feature",
  "properties": {
    "iso:country":"DE",
    "sg:address":"Schnaiter Str. 21",
    "sg:city":"Remshalden",
    "sg:phone":"+49 7151/72534",
    "sg:postcode":"73630",
    "sg:province":"Baden-W\u00fcrttemberg",
    "wof:name":"E. F. H\u00f6schele Kg",
    "wof:placetype":"venue"
},
  "geometry": {"coordinates":[9.4335155487,48.8020706177],"type":"Point"}
}