{
  "type": "Feature",
  "properties": {
    "iso:country":"DE",
    "sg:address":"Goethestr. 25",
    "sg:city":"Visselh\u00f6vede",
    "sg:phone":"+49 4262/1361",
    "sg:postcode":"27374",
    "sg:province":"Niedersachsen",
    "wof:name":"Willy Karlstedt",
    "wof:placetype":"venue"
},
  "geometry": {"coordinates":[9.5768346786,52.9836769104],"type":"Point"}
}