{
  "type": "Feature",
  "properties": {
    "iso:country":"DE",
    "sg:address":"Sebastianstr. 187",
    "sg:city":"K\u00f6ln",
    "sg:phone":"+49 221/6603771",
    "sg:postcode":"50735",
    "sg:province":"Nordrhein-Westfalen",
    "wof:name":"Schug Gmbh",
    "wof:placetype":"venue"
},
  "geometry": {"coordinates":[6.961451,50.990688],"type":"Point"}
}