{
  "type": "Feature",
  "properties": {
    "iso:country":"DE",
    "sg:address":"M\u00fcnchnerstr. 79",
    "sg:city":"Unterf\u00f6hring",
    "sg:phone":"+49 89/950980",
    "sg:postcode":"85774",
    "sg:province":"Bayern",
    "wof:name":"Zur Post",
    "wof:placetype":"venue"
},
  "geometry": {"coordinates":[11.6416330338,48.1940422058],"type":"Point"}
}