{
  "type": "Feature",
  "properties": {
    "iso:country":"DE",
    "sg:address":"Heidekamp 11",
    "sg:city":"Dassendorf",
    "sg:phone":"+49 4104/969683",
    "sg:postcode":"21521",
    "sg:province":"Schleswig-Holstein",
    "wof:name":"Hajo Molzahn",
    "wof:placetype":"venue"
},
  "geometry": {"coordinates":[10.357038,53.505119],"type":"Point"}
}