{
  "type": "Feature",
  "properties": {
    "iso:country":"DE",
    "sg:address":"Dietramszeller Str. 25",
    "sg:city":"Dietramszell",
    "sg:phone":"+49 8027/675",
    "sg:postcode":"83623",
    "sg:province":"Bayern",
    "wof:name":"Eva Mause Trickstudio",
    "wof:placetype":"venue"
},
  "geometry": {"coordinates":[11.5880002975,47.8920516968],"type":"Point"}
}