{
  "type": "Feature",
  "properties": {
    "iso:country":"DE",
    "sg:address":"Windisch-Brachbach",
    "sg:city":"Ilshofen",
    "sg:phone":"+49 7906/8556",
    "sg:postcode":"74532",
    "sg:province":"Baden-W\u00fcrttemberg",
    "wof:name":"A. Mahlein",
    "wof:placetype":"venue"
},
  "geometry": {"coordinates":[9.85135,49.201859],"type":"Point"}
}