{
  "type": "Feature",
  "properties": {
    "iso:country":"DE",
    "sg:address":"St.-Martins-Str. 4",
    "sg:city":"Vechelde",
    "sg:phone":"+49 5300/1005",
    "sg:postcode":"38159",
    "sg:province":"Niedersachsen",
    "wof:name":"Horst Schmidt",
    "wof:placetype":"venue"
},
  "geometry": {"coordinates":[10.364954,52.2164],"type":"Point"}
}