{
  "type": "Feature",
  "properties": {
    "iso:country":"DE",
    "sg:address":"Winterhaldenstr. 1",
    "sg:city":"Stuttgart",
    "sg:phone":"+49 711/523765",
    "sg:postcode":"70374",
    "sg:province":"Baden-W\u00fcrttemberg",
    "wof:name":"Herbert Treffinger",
    "wof:placetype":"venue"
},
  "geometry": {"coordinates":[9.236198,48.803497],"type":"Point"}
}