{
  "type": "Feature",
  "properties": {
    "iso:country":"DE",
    "sg:address":"Echternhagen 15",
    "sg:city":"Kalletal",
    "sg:phone":"+49 5264/1500",
    "sg:postcode":"32689",
    "sg:province":"Nordrhein-Westfalen",
    "wof:name":"Rolf Limberg",
    "wof:placetype":"venue"
},
  "geometry": {"coordinates":[8.9329805374,52.1181526184],"type":"Point"}
}