{
  "type": "Feature",
  "properties": {
    "iso:country":"DE",
    "sg:address":"Postfach 100651:: 83006 Rosenheim:: Germany.^^Tegernseestr 20::",
    "sg:city":"Rosenheim",
    "sg:phone":"+49 8031/1850",
    "sg:postcode":"83022",
    "sg:province":"Bayern",
    "wof:name":"Raiffeisenbank Rosenheim Eg",
    "wof:placetype":"venue"
},
  "geometry": {"coordinates":[12.128755,47.856522],"type":"Point"}
}