{
  "type": "Feature",
  "properties": {
    "iso:country":"DE",
    "sg:address":"Lautertalstr. 47",
    "sg:city":"Lauterach",
    "sg:phone":"+49 7375/453",
    "sg:postcode":"89584",
    "sg:province":"Baden-W\u00fcrttemberg",
    "wof:name":"Josef M\u00f6nch",
    "wof:placetype":"venue"
},
  "geometry": {"coordinates":[9.580892,48.255268],"type":"Point"}
}