{
  "type": "Feature",
  "properties": {
    "iso:country":"DE",
    "sg:address":"Karlstr 13",
    "sg:city":"Oer-Erkenschwick",
    "sg:phone":"+49 2368/693916",
    "sg:postcode":"45739",
    "sg:province":"Nordrhein-Westfalen",
    "wof:name":"Hema-marx Gmbh",
    "wof:placetype":"venue"
},
  "geometry": {"coordinates":[7.2822551727,51.6475524902],"type":"Point"}
}