{
  "type": "Feature",
  "properties": {
    "iso:country":"DE",
    "sg:address":"Friedrichstal 7",
    "sg:city":"Neuenrade",
    "sg:phone":"+49 2392/61234",
    "sg:postcode":"58809",
    "sg:province":"Nordrhein-Westfalen",
    "wof:name":"Freibad",
    "wof:placetype":"venue"
},
  "geometry": {"coordinates":[7.8029842377,51.2901496887],"type":"Point"}
}