{
  "type": "Feature",
  "properties": {
    "iso:country":"DE",
    "sg:address":"Hauptstr. 23",
    "sg:city":"Schwaig",
    "sg:phone":"+49 8402/530",
    "sg:postcode":"93333",
    "sg:province":"Bayern",
    "wof:name":"Sparkasse Abensberg-kelheim-ma",
    "wof:placetype":"venue"
},
  "geometry": {"coordinates":[11.706034,48.769062],"type":"Point"}
}