{
  "type": "Feature",
  "properties": {
    "iso:country":"DE",
    "sg:address":"Siegelbacher Str. 90",
    "sg:city":"Kaiserslautern",
    "sg:phone":"+49 6301/9396",
    "sg:postcode":"67659",
    "sg:province":"Rheinland-Pfalz",
    "wof:name":"H. Kiefer",
    "wof:placetype":"venue"
},
  "geometry": {"coordinates":[7.712171,49.48201],"type":"Point"}
}