{
  "type": "Feature",
  "properties": {
    "iso:country":"DE",
    "sg:address":"Lilienweg 19a",
    "sg:city":"Wiesbaden",
    "sg:phone":"+49 611/20810",
    "sg:postcode":"65201",
    "sg:province":"Hessen",
    "wof:name":"Friedrich Schulz Elektroinstallation",
    "wof:placetype":"venue"
},
  "geometry": {"coordinates":[8.193776,50.062298],"type":"Point"}
}