{
  "type": "Feature",
  "properties": {
    "iso:country":"DE",
    "sg:address":"Bergstr. 52",
    "sg:city":"Heidelberg",
    "sg:phone":"+49 6221/439139",
    "sg:postcode":"69120",
    "sg:province":"Baden-W\u00fcrttemberg",
    "wof:name":"Joest & Walther Freie Architekten Bda",
    "wof:placetype":"venue"
},
  "geometry": {"coordinates":[8.692786,49.417873],"type":"Point"}
}