{
  "type": "Feature",
  "properties": {
    "iso:country":"DE",
    "sg:address":"Gro\u00dfopitzer Weg 7",
    "sg:city":"Kleinopitz",
    "sg:phone":"+49 35203/37541",
    "sg:postcode":"01737",
    "sg:province":"Sachsen",
    "wof:name":"Friedemann D\u00f6hner Bildhauer",
    "wof:placetype":"venue"
},
  "geometry": {"coordinates":[13.547301,50.982521],"type":"Point"}
}