{
  "type": "Feature",
  "properties": {
    "iso:country":"DE",
    "sg:address":"M\u00fc\u00dfmattstr. 30",
    "sg:city":"Rheinfelden",
    "sg:phone":"+49 7623/8681",
    "sg:postcode":"79618",
    "sg:province":"Baden-W\u00fcrttemberg",
    "wof:name":"Stadtb\u00fccherei",
    "wof:placetype":"venue"
},
  "geometry": {"coordinates":[7.786101,47.566387],"type":"Point"}
}