{
  "type": "Feature",
  "properties": {
    "iso:country":"DE",
    "sg:address":"Herderstr. 25",
    "sg:city":"Wiesbaden",
    "sg:phone":"+49 611/302225",
    "sg:postcode":"65185",
    "sg:province":"Hessen",
    "wof:name":"Mergel Und Giesl Papier- Und Schreibwaren",
    "wof:placetype":"venue"
},
  "geometry": {"coordinates":[8.234041214,50.0743637085],"type":"Point"}
}