{
  "type": "Feature",
  "properties": {
    "iso:country":"DE",
    "sg:address":"Kleiner Griechenmarkt 33",
    "sg:city":"K\u00f6ln",
    "sg:phone":"+49 221/233561",
    "sg:postcode":"50676",
    "sg:province":"Nordrhein-Westfalen",
    "wof:name":"Tilger Gmbh",
    "wof:placetype":"venue"
},
  "geometry": {"coordinates":[6.9488101006,50.9321403503],"type":"Point"}
}