{
  "type": "Feature",
  "properties": {
    "iso:country":"DE",
    "sg:address":"Vereinsstr. 38",
    "sg:city":"Bochum",
    "sg:postcode":"44793",
    "sg:province":"Nordrhein-Westfalen",
    "wof:name":"Tas Verwaltungs- Gmbh",
    "wof:placetype":"venue"
},
  "geometry": {"coordinates":[7.189955,51.478542],"type":"Point"}
}