{
  "type": "Feature",
  "properties": {
    "iso:country":"DE",
    "sg:address":"Bockhorster H\u00f6he 48",
    "sg:city":"Hamburg",
    "sg:phone":"+49 40/73590563",
    "sg:postcode":"21031",
    "sg:province":"Hamburg",
    "wof:name":"E. Westphal",
    "wof:placetype":"venue"
},
  "geometry": {"coordinates":[10.173645,53.515087],"type":"Point"}
}