{
  "type": "Feature",
  "properties": {
    "iso:country":"DE",
    "sg:address":"Breslauer Str. 6",
    "sg:city":"Lahnau",
    "sg:phone":"+49 6441/62326",
    "sg:postcode":"35633",
    "sg:province":"Hessen",
    "wof:name":"Fred Keil Steuerberater",
    "wof:placetype":"venue"
},
  "geometry": {"coordinates":[8.5587177277,50.5859642029],"type":"Point"}
}