{
  "type": "Feature",
  "properties": {
    "iso:country":"DE",
    "sg:address":"Lange Str. 62",
    "sg:city":"Vlotho",
    "sg:phone":"+49 5733/7400",
    "sg:postcode":"32602",
    "sg:province":"Nordrhein-Westfalen",
    "wof:name":"Dream",
    "wof:placetype":"venue"
},
  "geometry": {"coordinates":[8.8637104034,52.1696739197],"type":"Point"}
}