{
  "type": "Feature",
  "properties": {
    "iso:country":"DE",
    "sg:address":"Bahnhofstr. 1",
    "sg:city":"Frauenberg",
    "sg:phone":"+49 6787/1639",
    "sg:postcode":"55776",
    "sg:province":"Rheinland-Pfalz",
    "wof:name":"Burgsch\u00e4nke Inh. Sigrid Wagner",
    "wof:placetype":"venue"
},
  "geometry": {"coordinates":[7.284910202,49.6666755676],"type":"Point"}
}