{
  "type": "Feature",
  "properties": {
    "iso:country":"DE",
    "sg:address":"Postfach 92 04 39",
    "sg:city":"Hamburg",
    "sg:postcode":"21134",
    "sg:province":"Hamburg",
    "wof:name":"Hamburger Windel-service E. B\u00fcrkner",
    "wof:placetype":"venue"
},
  "geometry": {"coordinates":[9.9732999802,53.5498313904],"type":"Point"}
}