{
  "type": "Feature",
  "properties": {
    "iso:country":"DE",
    "sg:address":"Barkauer Str. 48",
    "sg:city":"Kiel",
    "sg:phone":"+49 431/7196813",
    "sg:postcode":"24145",
    "sg:province":"Schleswig-Holstein",
    "wof:name":"K\u00fcchenstudio Regina Br\u00fcske",
    "wof:placetype":"venue"
},
  "geometry": {"coordinates":[10.136218071,54.2825088501],"type":"Point"}
}