{
  "type": "Feature",
  "properties": {
    "iso:country":"DE",
    "sg:address":"R\u00f6blingstr. 16",
    "sg:city":"M\u00fchlhausen",
    "sg:phone":"+49 36014/48392",
    "sg:postcode":"99974",
    "sg:province":"Th\u00fcringen",
    "wof:name":"Jens Fritzsche",
    "wof:placetype":"venue"
},
  "geometry": {"coordinates":[10.4605093002,51.2076072693],"type":"Point"}
}