{
  "type": "Feature",
  "properties": {
    "iso:country":"DE",
    "sg:address":"Hof\u00e4ckerstr. 6",
    "sg:city":"Crailsheim",
    "sg:phone":"+49 7951/4930",
    "sg:postcode":"74564",
    "sg:province":"Baden-W\u00fcrttemberg",
    "wof:name":"Fr\u00e4nkische Druckpresse Craialsheim Verwaltungs-",
    "wof:placetype":"venue"
},
  "geometry": {"coordinates":[10.083643,49.124523],"type":"Point"}
}