{
  "type": "Feature",
  "properties": {
    "iso:country":"DE",
    "sg:address":"Rosenstr. 11",
    "sg:city":"Hanau",
    "sg:phone":"+49 6181/923520",
    "sg:postcode":"63450",
    "sg:province":"Hessen",
    "wof:name":"Heinrich Brachmann Gmbh",
    "wof:placetype":"venue"
},
  "geometry": {"coordinates":[8.91908741,50.133014679],"type":"Point"}
}