{
  "type": "Feature",
  "properties": {
    "iso:country":"DE",
    "sg:address":"Tempelhofer Str. 8",
    "sg:city":"Wiesbaden",
    "sg:phone":"+49 611/761616",
    "sg:postcode":"65205",
    "sg:province":"Hessen",
    "wof:name":"Fidibus",
    "wof:placetype":"venue"
},
  "geometry": {"coordinates":[8.2961931229,50.0566520691],"type":"Point"}
}