{
  "type": "Feature",
  "properties": {
    "iso:country":"DE",
    "sg:address":"G\u00e4rtnerstr. 103",
    "sg:city":"Leipzig",
    "sg:phone":"+49 341/4125025",
    "sg:postcode":"04209",
    "sg:province":"Sachsen",
    "wof:name":"Dieter Engelmann",
    "wof:placetype":"venue"
},
  "geometry": {"coordinates":[12.30808,51.319782],"type":"Point"}
}