{
  "type": "Feature",
  "properties": {
    "iso:country":"DE",
    "sg:address":"Burgstr. 19",
    "sg:city":"Kusterdingen",
    "sg:phone":"+49 7071/32667",
    "sg:postcode":"72127",
    "sg:province":"Baden-W\u00fcrttemberg",
    "wof:name":"Walter Rapp",
    "wof:placetype":"venue"
},
  "geometry": {"coordinates":[9.111255,48.486183],"type":"Point"}
}