{
  "type": "Feature",
  "properties": {
    "iso:country":"DE",
    "sg:address":"Schillerstr. 13",
    "sg:city":"Johannesberg",
    "sg:phone":"+49 6021/470284",
    "sg:postcode":"63867",
    "sg:province":"Bayern",
    "wof:name":"Klaus Lorenz",
    "wof:placetype":"venue"
},
  "geometry": {"coordinates":[9.147487,50.032436],"type":"Point"}
}