{
  "type": "Feature",
  "properties": {
    "iso:country":"DE",
    "sg:address":"Kurbrunnenstr. 5",
    "sg:city":"Aachen",
    "sg:phone":"+49 241/60070",
    "sg:postcode":"52066",
    "sg:province":"Nordrhein-Westfalen",
    "wof:name":"Kurklinik An Der Rosenquelle",
    "wof:placetype":"venue"
},
  "geometry": {"coordinates":[6.0956082344,50.7664337158],"type":"Point"}
}