{
  "type": "Feature",
  "properties": {
    "iso:country":"DE",
    "sg:address":"Duderst\u00e4dter Str. 53",
    "sg:city":"Worbis",
    "sg:postcode":"37339",
    "sg:province":"Th\u00fcringen",
    "wof:name":"Dr. Med. Ullrich Rupprecht",
    "wof:placetype":"venue"
},
  "geometry": {"coordinates":[10.35659,51.424637],"type":"Point"}
}