{
  "type": "Feature",
  "properties": {
    "iso:country":"DE",
    "sg:address":"Kreuzbreite 11",
    "sg:city":"B\u00fcckeburg",
    "sg:phone":"+49 5722/25007",
    "sg:postcode":"31675",
    "sg:province":"Niedersachsen",
    "wof:name":"Uthe Beteiligungs Gmbh",
    "wof:placetype":"venue"
},
  "geometry": {"coordinates":[9.067147,52.265179],"type":"Point"}
}