{
  "type": "Feature",
  "properties": {
    "iso:country":"DE",
    "sg:address":"Schlo\u00dfberg 6",
    "sg:city":"Saarburg",
    "sg:phone":"+49 6581/810",
    "sg:postcode":"54439",
    "sg:province":"Rheinland-Pfalz",
    "wof:name":"Verbandsgemeindewerke",
    "wof:placetype":"venue"
},
  "geometry": {"coordinates":[6.551317,49.608803],"type":"Point"}
}