{
  "type": "Feature",
  "properties": {
    "iso:country":"DE",
    "sg:address":"Kolhagenstr. 40",
    "sg:city":"D\u00fcsseldorf",
    "sg:phone":"+49 211/713963",
    "sg:postcode":"40593",
    "sg:province":"Nordrhein-Westfalen",
    "wof:name":"Hildegard J. Sauer \u00dcbersetzungsb\u00fcro",
    "wof:placetype":"venue"
},
  "geometry": {"coordinates":[6.870155,51.151043],"type":"Point"}
}