{
  "type": "Feature",
  "properties": {
    "iso:country":"DE",
    "sg:address":"Frydagstr. 4 Lippholthausen",
    "sg:city":"L\u00fcnen",
    "sg:phone":"+49 4942/3196460",
    "sg:postcode":"44536",
    "sg:province":"Nordrhein-Westfalen",
    "wof:name":"Schmiedbauer Stahl- & Metallbau Gmbh",
    "wof:placetype":"venue"
},
  "geometry": {"coordinates":[9.2852134705,52.9272537231],"type":"Point"}
}