{
  "type": "Feature",
  "properties": {
    "iso:country":"DE",
    "sg:address":"Dippoldiswalder Str. 6 a",
    "sg:city":"Altenberg",
    "sg:phone":"+49 35056/35958",
    "sg:postcode":"01773",
    "sg:province":"Sachsen",
    "wof:name":"A. Quentin",
    "wof:placetype":"venue"
},
  "geometry": {"coordinates":[13.7565536499,50.7657279968],"type":"Point"}
}