{
  "type": "Feature",
  "properties": {
    "iso:country":"DE",
    "sg:address":"Elstertalblick 14 OT Neundorf",
    "sg:city":"Neundorf",
    "sg:phone":"+49 9281/97790",
    "sg:postcode":"08527",
    "sg:province":"Sachsen",
    "wof:name":"Hbg Hausbaugesellschaft Mbh",
    "wof:placetype":"venue"
},
  "geometry": {"coordinates":[12.160378,50.461147],"type":"Point"}
}