{
  "type": "Feature",
  "properties": {
    "iso:country":"DE",
    "sg:address":"Hauptstr. 17",
    "sg:city":"Garrel",
    "sg:phone":"+49 4474/947360",
    "sg:postcode":"49681",
    "sg:province":"Niedersachsen",
    "wof:name":"Neue Apotheke Inh. Gerhard H. Bickelhaupt",
    "wof:placetype":"venue"
},
  "geometry": {"coordinates":[8.025349,52.958042],"type":"Point"}
}