{
  "type": "Feature",
  "properties": {
    "iso:country":"DE",
    "sg:address":"Kirchstr. 27",
    "sg:city":"Wilkau-Ha\u00dflau",
    "sg:postcode":"08112",
    "sg:province":"Sachsen",
    "wof:name":"Ev.-luth. Kirche Wilkau- Ha\u00dflau",
    "wof:placetype":"venue"
},
  "geometry": {"coordinates":[12.5266628265,50.6746177673],"type":"Point"}
}