{
  "type": "Feature",
  "properties": {
    "iso:country":"DE",
    "sg:address":"G\u00f6tscher Weg 50",
    "sg:city":"Langenfeld",
    "sg:phone":"+49 2173/70155",
    "sg:postcode":"40764",
    "sg:province":"Nordrhein-Westfalen",
    "wof:name":"Erich Richrath",
    "wof:placetype":"venue"
},
  "geometry": {"coordinates":[6.953288,51.137058],"type":"Point"}
}