{
  "type": "Feature",
  "properties": {
    "iso:country":"DE",
    "sg:address":"Innerer Graben 42",
    "sg:city":"W\u00fcrzburg",
    "sg:phone":"+49 931/355430",
    "sg:postcode":"97070",
    "sg:province":"Bayern",
    "wof:name":"Kolb Textiles Interieur Gmbh",
    "wof:placetype":"venue"
},
  "geometry": {"coordinates":[9.930884,49.7967],"type":"Point"}
}