{
  "type": "Feature",
  "properties": {
    "iso:country":"DE",
    "sg:address":"Paul-Lincke-Weg 6",
    "sg:city":"Burgdorf",
    "sg:phone":"+49 5085/349",
    "sg:postcode":"31303",
    "sg:province":"Niedersachsen",
    "wof:name":"S. Pauls",
    "wof:placetype":"venue"
},
  "geometry": {"coordinates":[10.0144147873,52.51512146],"type":"Point"}
}