{
  "type": "Feature",
  "properties": {
    "iso:country":"DE",
    "sg:address":"Kleiner Weg 10",
    "sg:city":"K\u00f6nigstein",
    "sg:phone":"+49 35021/68642",
    "sg:postcode":"01824",
    "sg:province":"Sachsen",
    "wof:name":"Klaus Ritzschel",
    "wof:placetype":"venue"
},
  "geometry": {"coordinates":[14.05959,50.91428],"type":"Point"}
}