{
  "type": "Feature",
  "properties": {
    "iso:country":"DE",
    "sg:address":"Bremer Str. 2",
    "sg:city":"Ostercappeln",
    "sg:phone":"+49 5473/1997",
    "sg:postcode":"49179",
    "sg:province":"Niedersachsen",
    "wof:name":"H. Hegge",
    "wof:placetype":"venue"
},
  "geometry": {"coordinates":[8.221644,52.341148],"type":"Point"}
}