{
  "type": "Feature",
  "properties": {
    "iso:country":"DE",
    "sg:address":"Glaadter Str. 8",
    "sg:city":"J\u00fcnkerath",
    "sg:phone":"+49 6597/961070",
    "sg:postcode":"54584",
    "sg:province":"Rheinland-Pfalz",
    "wof:name":"Ebinger Pr\u00dcf- U. Ortungstechnik Gmbh",
    "wof:placetype":"venue"
},
  "geometry": {"coordinates":[6.5649,50.349625],"type":"Point"}
}