{
  "type": "Feature",
  "properties": {
    "iso:country":"DE",
    "sg:address":"Podbielskistr. 143 a",
    "sg:city":"Hannover",
    "sg:phone":"+49 511/3942300",
    "sg:postcode":"30177",
    "sg:province":"Niedersachsen",
    "wof:name":"Gr\u00fcner Pelikan",
    "wof:placetype":"venue"
},
  "geometry": {"coordinates":[9.7703237534,52.3973960876],"type":"Point"}
}