{
  "type": "Feature",
  "properties": {
    "iso:country":"DE",
    "sg:address":"Els\u00e4sser Str. 12",
    "sg:city":"Solingen",
    "sg:phone":"+49 212/72016",
    "sg:postcode":"42697",
    "sg:province":"Nordrhein-Westfalen",
    "wof:name":"Inovatronic Elektronische Systeme Gmbh",
    "wof:placetype":"venue"
},
  "geometry": {"coordinates":[6.991176,51.166714],"type":"Point"}
}