{
  "type": "Feature",
  "properties": {
    "iso:country":"DE",
    "sg:address":"Am Kurpark 26",
    "sg:city":"Garmisch-Partenkirchen",
    "sg:phone":"+49 8821/95810",
    "sg:postcode":"82467",
    "sg:province":"Bayern",
    "wof:name":"Ips Immobilien-projekt- Entwicklungs-service",
    "wof:placetype":"venue"
},
  "geometry": {"coordinates":[11.0879716873,47.4934768677],"type":"Point"}
}