{
  "type": "Feature",
  "properties": {
    "iso:country":"DE",
    "sg:address":"B\u00e4ckergasse 10",
    "sg:city":"Schemmerhofen",
    "sg:phone":"+49 7356/3446",
    "sg:postcode":"88433",
    "sg:province":"Baden-W\u00fcrttemberg",
    "wof:name":"Franz Bochtler",
    "wof:placetype":"venue"
},
  "geometry": {"coordinates":[9.80135,48.184589],"type":"Point"}
}