{
  "type": "Feature",
  "properties": {
    "iso:country":"DE",
    "sg:address":"Schulstr. 1",
    "sg:city":"Edingen-Neckarhausen",
    "sg:phone":"+49 6203/15815",
    "sg:postcode":"68535",
    "sg:province":"Baden-W\u00fcrttemberg",
    "wof:name":"Frank Treffert",
    "wof:placetype":"venue"
},
  "geometry": {"coordinates":[8.6119632721,49.448474884],"type":"Point"}
}