{
  "type": "Feature",
  "properties": {
    "iso:country":"DE",
    "sg:address":"Frielinghausweg 30",
    "sg:city":"Dortmund",
    "sg:phone":"+49 231/803156",
    "sg:postcode":"44339",
    "sg:province":"Nordrhein-Westfalen",
    "wof:name":"Harald Goerke",
    "wof:placetype":"venue"
},
  "geometry": {"coordinates":[7.4613552094,51.5775413513],"type":"Point"}
}