{
  "type": "Feature",
  "properties": {
    "iso:country":"DE",
    "sg:address":"Leipziger Str. 71",
    "sg:city":"Taucha",
    "sg:phone":"+49 34298/34394",
    "sg:postcode":"04425",
    "sg:province":"Sachsen",
    "wof:name":"K. Busch",
    "wof:placetype":"venue"
},
  "geometry": {"coordinates":[12.486308,51.376423],"type":"Point"}
}