{
  "type": "Feature",
  "properties": {
    "iso:country":"DE",
    "sg:address":"Am Beek 13",
    "sg:city":"Goslar",
    "sg:phone":"+49 5321/20479",
    "sg:postcode":"38640",
    "sg:province":"Niedersachsen",
    "wof:name":"G\u00e4stehaus Joh. Und Renate Geier",
    "wof:placetype":"venue"
},
  "geometry": {"coordinates":[10.4202203751,51.903881073],"type":"Point"}
}