{
  "type": "Feature",
  "properties": {
    "iso:country":"DE",
    "sg:address":"Heinrich-B\u00f6ll-Ring 21-23",
    "sg:city":"Bonn",
    "sg:postcode":"53119",
    "sg:province":"Nordrhein-Westfalen",
    "wof:name":"Baustoff-pr\u00fcf-gesellschaft Bonn-hersel Mbh & Co. Kg",
    "wof:placetype":"venue"
},
  "geometry": {"coordinates":[7.0782270432,50.7415885925],"type":"Point"}
}