{
  "type": "Feature",
  "properties": {
    "iso:country":"DE",
    "sg:address":"Ilsenburger Str. 3",
    "sg:city":"Bad Harzburg",
    "sg:phone":"+49 5322/2243",
    "sg:postcode":"38667",
    "sg:province":"Niedersachsen",
    "wof:name":"Karl Sievers & S\u00f6hne",
    "wof:placetype":"venue"
},
  "geometry": {"coordinates":[10.560869,51.885941],"type":"Point"}
}