{
  "type": "Feature",
  "properties": {
    "iso:country":"DE",
    "sg:address":"Am Buschh\u00e4uschen 70",
    "sg:city":"Wuppertal",
    "sg:phone":"+49 202/316042",
    "sg:postcode":"42115",
    "sg:province":"Nordrhein-Westfalen",
    "wof:name":"Joachim Doerken",
    "wof:placetype":"venue"
},
  "geometry": {"coordinates":[7.123242,51.259819],"type":"Point"}
}