{
  "type": "Feature",
  "properties": {
    "iso:country":"DE",
    "sg:address":"Rathaus",
    "sg:city":"Ebersberg",
    "sg:postcode":"85560",
    "sg:province":"Bayern",
    "wof:name":"Holzbibliothek",
    "wof:placetype":"venue"
},
  "geometry": {"coordinates":[11.96856,48.07843],"type":"Point"}
}