{
  "type": "Feature",
  "properties": {
    "iso:country":"DE",
    "sg:address":"Landstr. 9",
    "sg:city":"Hirschberg",
    "sg:phone":"+49 4962/015050",
    "sg:postcode":"69493",
    "sg:province":"Baden-W\u00fcrttemberg",
    "wof:name":"Hotel Krone Inh. Maria Gr\u00dcber",
    "wof:placetype":"venue"
},
  "geometry": {"coordinates":[8.655691,49.511219],"type":"Point"}
}