{
  "type": "Feature",
  "properties": {
    "iso:country":"DE",
    "sg:address":"Schillerstr. 36",
    "sg:city":"Neuss",
    "sg:phone":"+49 2131/43673",
    "sg:postcode":"41464",
    "sg:province":"Nordrhein-Westfalen",
    "wof:name":"Maigatte",
    "wof:placetype":"venue"
},
  "geometry": {"coordinates":[6.692486,51.188541],"type":"Point"}
}