{
  "type": "Feature",
  "properties": {
    "iso:country":"DE",
    "sg:address":"W\u00f6rthstr. 67",
    "sg:city":"Westerburg",
    "sg:phone":"+49 2663",
    "sg:postcode":"56457",
    "sg:province":"Rheinland-Pfalz",
    "wof:name":"Outdoor Team Akademie",
    "wof:placetype":"venue"
},
  "geometry": {"coordinates":[7.9805278778,50.557762146],"type":"Point"}
}