{
  "type": "Feature",
  "properties": {
    "iso:country":"DE",
    "sg:address":"Libellenstr. 45",
    "sg:city":"Leipzig",
    "sg:postcode":"04249",
    "sg:province":"Sachsen",
    "wof:name":"F & D Folien- Und Digitalmedien Gmbh",
    "wof:placetype":"venue"
},
  "geometry": {"coordinates":[12.3232698441,51.2971458435],"type":"Point"}
}