{
  "type": "Feature",
  "properties": {
    "iso:country":"DE",
    "sg:address":"Hans-Reyhing-Str. 7",
    "sg:city":"Reutlingen",
    "sg:phone":"+49 7121/270860",
    "sg:postcode":"72762",
    "sg:province":"Baden-W\u00fcrttemberg",
    "wof:name":"Ev. Pfarramt Kreuzkirche Ii",
    "wof:placetype":"venue"
},
  "geometry": {"coordinates":[9.2014818192,48.478553772],"type":"Point"}
}