{
  "type": "Feature",
  "properties": {
    "iso:country":"DE",
    "sg:address":"Johannes-Kepler-Str. 6",
    "sg:city":"Besigheim",
    "sg:phone":"+49 4971/4385400",
    "sg:postcode":"74354",
    "sg:province":"Baden-W\u00fcrttemberg",
    "wof:name":"Stanz & Umformtechnik Gmbh",
    "wof:placetype":"venue"
},
  "geometry": {"coordinates":[9.209504,49.01326],"type":"Point"}
}