{
  "type": "Feature",
  "properties": {
    "iso:country":"DE",
    "sg:address":"Am Markt 1",
    "sg:city":"Saarbr\u00fccken",
    "sg:phone":"+49 6897/90020",
    "sg:postcode":"66125",
    "sg:province":"Saarland",
    "wof:name":"Bruckhaus Consult Gesellschaft F\u00fcr Betriebswirtschaftliche",
    "wof:placetype":"venue"
},
  "geometry": {"coordinates":[7.0365028381,49.2754440308],"type":"Point"}
}