{
  "type": "Feature",
  "properties": {
    "iso:country":"DE",
    "sg:address":"Rathausstr. 4",
    "sg:city":"Filsum",
    "sg:phone":"+49 4957/287",
    "sg:postcode":"26849",
    "sg:province":"Niedersachsen",
    "wof:name":"Sparkasse Leer-weener",
    "wof:placetype":"venue"
},
  "geometry": {"coordinates":[7.626805,53.241699],"type":"Point"}
}