{
  "type": "Feature",
  "properties": {
    "iso:country":"DE",
    "sg:address":"Schafgarbenweg 16",
    "sg:city":"M\u00fcnchen",
    "sg:phone":"+49 89/3142077",
    "sg:postcode":"80995",
    "sg:province":"Bayern",
    "wof:name":"H.-u. Merolt Steuerberater",
    "wof:placetype":"venue"
},
  "geometry": {"coordinates":[11.5271873474,48.1945991516],"type":"Point"}
}