{
  "type": "Feature",
  "properties": {
    "iso:country":"DE",
    "sg:address":"Oblatterwallstr. 2",
    "sg:city":"Augsburg",
    "sg:postcode":"86153",
    "sg:province":"Bayern",
    "wof:name":"Araman Gmbh",
    "wof:placetype":"venue"
},
  "geometry": {"coordinates":[10.9093770981,48.3710098267],"type":"Point"}
}