{
  "type": "Feature",
  "properties": {
    "iso:country":"DE",
    "sg:address":"Silberstr. 11",
    "sg:city":"N\u00fcrnberg",
    "sg:phone":"+49 911/327266",
    "sg:postcode":"90427",
    "sg:province":"Bayern",
    "wof:name":"Linz Fabrik Moderner Schreibger\u00c4te Gmbh & Co Kg",
    "wof:placetype":"venue"
},
  "geometry": {"coordinates":[11.026684761,49.4668426514],"type":"Point"}
}