{
  "type": "Feature",
  "properties": {
    "iso:country":"DE",
    "sg:address":"Eschenauer Hauptstr. 42",
    "sg:city":"Eckental",
    "sg:phone":"+49 9126/1842",
    "sg:postcode":"90542",
    "sg:province":"Bayern",
    "wof:name":"Hans Brendel",
    "wof:placetype":"venue"
},
  "geometry": {"coordinates":[11.2015533447,49.5741462708],"type":"Point"}
}