{
  "type": "Feature",
  "properties": {
    "iso:country":"DE",
    "sg:address":"Talstr. 19",
    "sg:city":"Wellendingen",
    "sg:phone":"+49 7426/96230",
    "sg:postcode":"78669",
    "sg:province":"Baden-W\u00fcrttemberg",
    "wof:name":"Leibold & Ammann Gmbh & Co. Kg",
    "wof:placetype":"venue"
},
  "geometry": {"coordinates":[8.719699,48.151524],"type":"Point"}
}