{
  "type": "Feature",
  "properties": {
    "iso:country":"DE",
    "sg:address":"Walter-Rathenau-Str. 3",
    "sg:city":"Leipzig",
    "sg:phone":"+49 34297/42395",
    "sg:postcode":"04288",
    "sg:province":"Sachsen",
    "wof:name":"Dr. Med. Ulrike Wiemers",
    "wof:placetype":"venue"
},
  "geometry": {"coordinates":[12.44666,51.292374],"type":"Point"}
}