{
  "type": "Feature",
  "properties": {
    "iso:country":"DE",
    "sg:address":"Petersbergstr. 52",
    "sg:city":"Saarbr\u00fccken",
    "sg:phone":"+49 681/55280",
    "sg:postcode":"66119",
    "sg:province":"Saarland",
    "wof:name":"Wolfgang Gerstner Ingenieur",
    "wof:placetype":"venue"
},
  "geometry": {"coordinates":[6.9904289246,49.2226905823],"type":"Point"}
}