{
  "type": "Feature",
  "properties": {
    "iso:country":"DE",
    "sg:address":"Georg-Odemer-Str. 2 b",
    "sg:city":"Neus\u00e4\u00df",
    "sg:phone":"+49 821/484015",
    "sg:postcode":"86356",
    "sg:province":"Bayern",
    "wof:name":"Abr-amtliches Bayrisches Reiseb\u00fcro Gmbh & Co. Kg",
    "wof:placetype":"venue"
},
  "geometry": {"coordinates":[10.8213024139,48.3940010071],"type":"Point"}
}