{
  "type": "Feature",
  "properties": {
    "iso:country":"DE",
    "sg:address":"Langer Weg 67::",
    "sg:city":"Magdeburg",
    "sg:phone":"+49 4939/142973",
    "sg:postcode":"39112",
    "sg:province":"Sachsen-Anhalt",
    "wof:name":"Eva-marie Grebe",
    "wof:placetype":"venue"
},
  "geometry": {"coordinates":[11.59668,52.113647],"type":"Point"}
}