{
  "type": "Feature",
  "properties": {
    "iso:country":"DE",
    "sg:address":"Burgweg 2",
    "sg:city":"Rosenheim",
    "sg:phone":"+49 8031/17265",
    "sg:postcode":"83026",
    "sg:province":"Bayern",
    "wof:name":"Irger Isoliertechnik Gmbh",
    "wof:placetype":"venue"
},
  "geometry": {"coordinates":[12.103183,47.843655],"type":"Point"}
}