{
  "type": "Feature",
  "properties": {
    "iso:country":"DE",
    "sg:address":"Talsperrenstr. 5",
    "sg:city":"Planschwitz",
    "sg:phone":"+49 37421/23200",
    "sg:postcode":"08606",
    "sg:province":"Sachsen",
    "wof:name":"Ev.-luth. Kirche Planschwitz",
    "wof:placetype":"venue"
},
  "geometry": {"coordinates":[12.1477270126,50.4030914307],"type":"Point"}
}