{
  "type": "Feature",
  "properties": {
    "iso:country":"DE",
    "sg:address":"Kapellenstr. 17",
    "sg:city":"Siegen",
    "sg:phone":"+49 271/61190",
    "sg:postcode":"57074",
    "sg:province":"Nordrhein-Westfalen",
    "wof:name":"Zimmermann",
    "wof:placetype":"venue"
},
  "geometry": {"coordinates":[8.060529,50.870628],"type":"Point"}
}