{
  "type": "Feature",
  "properties": {
    "iso:country":"DE",
    "sg:address":"Meisenweg 29",
    "sg:city":"Spenge",
    "sg:phone":"+49 5225/859570",
    "sg:postcode":"32139",
    "sg:province":"Nordrhein-Westfalen",
    "wof:name":"Eico-lackchemie Gmbh",
    "wof:placetype":"venue"
},
  "geometry": {"coordinates":[8.492756,52.132542],"type":"Point"}
}