{
  "type": "Feature",
  "properties": {
    "iso:country":"DE",
    "sg:address":"Fichtenstr. 4",
    "sg:city":"Neuried",
    "sg:phone":"+49 89/752163",
    "sg:postcode":"82061",
    "sg:province":"Bayern",
    "wof:name":"Toni Obele Gmbh",
    "wof:placetype":"venue"
},
  "geometry": {"coordinates":[11.458575,48.088623],"type":"Point"}
}