{
  "type": "Feature",
  "properties": {
    "iso:country":"DE",
    "sg:address":"Lohm\u00fchlenweg 7",
    "sg:city":"Gerolzhofen",
    "sg:phone":"+49 9382/97390",
    "sg:postcode":"97447",
    "sg:province":"Bayern",
    "wof:name":"M\u00dcller Tiefbau Gmbh",
    "wof:placetype":"venue"
},
  "geometry": {"coordinates":[10.337772,49.899807],"type":"Point"}
}