{
  "type": "Feature",
  "properties": {
    "iso:country":"DE",
    "sg:address":"Ritterstr. 10",
    "sg:city":"L\u00fcneburg",
    "sg:phone":"+49 4131/759950",
    "sg:postcode":"21335",
    "sg:province":"Niedersachsen",
    "wof:name":"Ostpreu\u00dfisches Landesmuseum",
    "wof:placetype":"venue"
},
  "geometry": {"coordinates":[10.407857,53.246304],"type":"Point"}
}