{
  "type": "Feature",
  "properties": {
    "iso:country":"DE",
    "sg:address":"Theaterstr. 15",
    "sg:city":"Biberach",
    "sg:phone":"+49 7351/73664",
    "sg:postcode":"88400",
    "sg:province":"Baden-W\u00fcrttemberg",
    "wof:name":"W. Becker",
    "wof:placetype":"venue"
},
  "geometry": {"coordinates":[9.785043,48.095596],"type":"Point"}
}