{
  "type": "Feature",
  "properties": {
    "iso:country":"DE",
    "sg:address":"Kirchgasse 9",
    "sg:city":"Immendingen",
    "sg:phone":"+49 7462/1659",
    "sg:postcode":"78194",
    "sg:province":"Baden-W\u00fcrttemberg",
    "wof:name":"Wiesengrund",
    "wof:placetype":"venue"
},
  "geometry": {"coordinates":[8.7095632553,47.9337234497],"type":"Point"}
}