{
  "type": "Feature",
  "properties": {
    "iso:country":"DE",
    "sg:address":"Gartenstr. 28",
    "sg:city":"Radebeul",
    "sg:phone":"+49 351/8382680",
    "sg:postcode":"01445",
    "sg:province":"Sachsen",
    "wof:name":"Systec Handelsges. Mbh",
    "wof:placetype":"venue"
},
  "geometry": {"coordinates":[13.680149,51.097115],"type":"Point"}
}