{
  "type": "Feature",
  "properties": {
    "iso:country":"DE",
    "sg:address":"G\u00f6ppmannsb\u00fchl 1",
    "sg:city":"Speichersdorf",
    "sg:phone":"+49 9275/1433",
    "sg:postcode":"95469",
    "sg:province":"Bayern",
    "wof:name":"Uwe Jannsen Architekt",
    "wof:placetype":"venue"
},
  "geometry": {"coordinates":[11.813215,49.885963],"type":"Point"}
}