{
  "type": "Feature",
  "properties": {
    "iso:country":"DE",
    "sg:address":"Coppistr. 48",
    "sg:city":"Leipzig",
    "sg:phone":"+49 341/9016668",
    "sg:postcode":"04157",
    "sg:province":"Sachsen",
    "wof:name":"Hannes Bemme",
    "wof:placetype":"venue"
},
  "geometry": {"coordinates":[12.3743896484,51.3672142029],"type":"Point"}
}