{
  "type": "Feature",
  "properties": {
    "iso:country":"DE",
    "sg:address":"Reiskestr. 17",
    "sg:city":"Leipzig",
    "sg:phone":"+49 341/9904372",
    "sg:postcode":"04317",
    "sg:province":"Sachsen",
    "wof:name":"Charlotte Gerstenberger",
    "wof:placetype":"venue"
},
  "geometry": {"coordinates":[12.405556,51.328407],"type":"Point"}
}