{
  "type": "Feature",
  "properties": {
    "iso:country":"DE",
    "sg:address":"Burgstr. 50",
    "sg:city":"Oberursel",
    "sg:phone":"+49 6171/53476",
    "sg:postcode":"61440",
    "sg:province":"Hessen",
    "wof:name":"Richard Mag",
    "wof:placetype":"venue"
},
  "geometry": {"coordinates":[8.603115,50.201958],"type":"Point"}
}