{
  "type": "Feature",
  "properties": {
    "iso:country":"DE",
    "sg:address":"Zoznegger Str. 13",
    "sg:city":"Stockach",
    "sg:phone":"+49 7771/4444",
    "sg:postcode":"78333",
    "sg:province":"Baden-W\u00fcrttemberg",
    "wof:name":"Herbert Wanschura",
    "wof:placetype":"venue"
},
  "geometry": {"coordinates":[9.01645,47.855373],"type":"Point"}
}