{
  "type": "Feature",
  "properties": {
    "iso:country":"DE",
    "sg:address":"N\u00f6rdliche Hauptstr. 46",
    "sg:city":"Weinheim",
    "sg:phone":"+49 6201/182222",
    "sg:postcode":"69469",
    "sg:province":"Baden-W\u00fcrttemberg",
    "wof:name":"Peter Schunk",
    "wof:placetype":"venue"
},
  "geometry": {"coordinates":[8.674466,49.557079],"type":"Point"}
}