{
  "type": "Feature",
  "properties": {
    "iso:country":"DE",
    "sg:address":"Br\u00fcckenstr. 6 b",
    "sg:city":"Netzschkau",
    "sg:phone":"+49 3765/300828",
    "sg:postcode":"08491",
    "sg:province":"Sachsen",
    "wof:name":"F.-a. Ketzel",
    "wof:placetype":"venue"
},
  "geometry": {"coordinates":[12.2470588684,50.6225967407],"type":"Point"}
}