{
  "type": "Feature",
  "properties": {
    "iso:country":"DE",
    "sg:address":"Pappelweg 5",
    "sg:city":"Haren",
    "sg:phone":"+49 5934/665",
    "sg:postcode":"49733",
    "sg:province":"Niedersachsen",
    "wof:name":"Hermann Wobken",
    "wof:placetype":"venue"
},
  "geometry": {"coordinates":[7.099451,52.807331],"type":"Point"}
}