{
  "type": "Feature",
  "properties": {
    "iso:country":"DE",
    "sg:address":"Himbach",
    "sg:city":"T\u00fcbingen",
    "sg:phone":"+49 7071/45351",
    "sg:postcode":"72070",
    "sg:province":"Baden-W\u00fcrttemberg",
    "wof:name":"Walter L\u00f6sel",
    "wof:placetype":"venue"
},
  "geometry": {"coordinates":[9.0087022781,48.5287208557],"type":"Point"}
}