{
  "type": "Feature",
  "properties": {
    "iso:country":"DE",
    "sg:address":"Zum Kornacker 4",
    "sg:city":"Niederwambach",
    "sg:phone":"+49 2685/7574",
    "sg:postcode":"57614",
    "sg:province":"Rheinland-Pfalz",
    "wof:name":"Mrs Teichmann Gmbh",
    "wof:placetype":"venue"
},
  "geometry": {"coordinates":[7.5742812157,50.6413574219],"type":"Point"}
}