{
  "type": "Feature",
  "properties": {
    "iso:country":"DE",
    "sg:address":"Upl\u00e4nder Str. 46",
    "sg:city":"Korbach",
    "sg:phone":"+49 5631/3778",
    "sg:postcode":"34497",
    "sg:province":"Hessen",
    "wof:name":"Wilke Textilien",
    "wof:placetype":"venue"
},
  "geometry": {"coordinates":[8.7872428894,51.2870025635],"type":"Point"}
}