{
  "type": "Feature",
  "properties": {
    "iso:country":"DE",
    "sg:address":"Villenweg 1",
    "sg:city":"Erftstadt",
    "sg:phone":"+49 4922/3585267",
    "sg:postcode":"50374",
    "sg:province":"Nordrhein-Westfalen",
    "wof:name":"Franz-josef Br\u00dcls",
    "wof:placetype":"venue"
},
  "geometry": {"coordinates":[6.802771,50.832111],"type":"Point"}
}