{
  "type": "Feature",
  "properties": {
    "iso:country":"DE",
    "sg:address":"Bergstr. 58",
    "sg:city":"Chemnitz",
    "sg:phone":"+49 371/369030",
    "sg:postcode":"09113",
    "sg:province":"Sachsen",
    "wof:name":"W\u00fcrttembergische Versicherung Ag",
    "wof:placetype":"venue"
},
  "geometry": {"coordinates":[12.9062690735,50.8447227478],"type":"Point"}
}