{
  "type": "Feature",
  "properties": {
    "iso:country":"DE",
    "sg:address":"Bohlweg 8",
    "sg:city":"Holle",
    "sg:phone":"+49 5062/1437",
    "sg:postcode":"31188",
    "sg:province":"Niedersachsen",
    "wof:name":"Heinrich Bartels",
    "wof:placetype":"venue"
},
  "geometry": {"coordinates":[10.107626,52.105579],"type":"Point"}
}