{
  "type": "Feature",
  "properties": {
    "iso:country":"DE",
    "sg:address":"Am Dachsbau 4",
    "sg:city":"Schwabach",
    "sg:postcode":"91126",
    "sg:province":"Bayern",
    "wof:name":"Wohnkonzept Bautr\u00e4ger Gmbh",
    "wof:placetype":"venue"
},
  "geometry": {"coordinates":[11.040869,49.326885],"type":"Point"}
}