{
  "type": "Feature",
  "properties": {
    "iso:country":"DE",
    "sg:address":"Wildtaubenweg 51",
    "sg:city":"Waiblingen",
    "sg:phone":"+49 7151/22232",
    "sg:postcode":"71334",
    "sg:province":"Baden-W\u00fcrttemberg",
    "wof:name":"Herbert Hahn",
    "wof:placetype":"venue"
},
  "geometry": {"coordinates":[9.3346843719,48.8356285095],"type":"Point"}
}