{
  "type": "Feature",
  "properties": {
    "iso:country":"DE",
    "sg:address":"Rendsburger Str. 10",
    "sg:city":"Hannover",
    "sg:phone":"+49 511/6101740",
    "sg:postcode":"30659",
    "sg:province":"Niedersachsen",
    "wof:name":"Novotek Gmbh",
    "wof:placetype":"venue"
},
  "geometry": {"coordinates":[9.8325500488,52.4198875427],"type":"Point"}
}