{
  "type": "Feature",
  "properties": {
    "iso:country":"DE",
    "sg:address":"Markt 1",
    "sg:city":"Hohenm\u00f6lsen",
    "sg:phone":"+49 34441/22342",
    "sg:postcode":"06679",
    "sg:province":"Sachsen-Anhalt",
    "wof:name":"Ratskeller",
    "wof:placetype":"venue"
},
  "geometry": {"coordinates":[12.0976247787,51.1569404602],"type":"Point"}
}