{
  "type": "Feature",
  "properties": {
    "iso:country":"DE",
    "sg:address":"Moorstr. 25",
    "sg:city":"Walsrode",
    "sg:phone":"+49 5161/5482",
    "sg:postcode":"29664",
    "sg:province":"Niedersachsen",
    "wof:name":"Ralf P\u00f6pping",
    "wof:placetype":"venue"
},
  "geometry": {"coordinates":[9.5932731628,52.8617286682],"type":"Point"}
}