{
  "type": "Feature",
  "properties": {
    "iso:country":"DE",
    "sg:address":"Riegelsteinstr. 22",
    "sg:city":"Windischeschenbach",
    "sg:phone":"+49 9681/722",
    "sg:postcode":"92670",
    "sg:province":"Bayern",
    "wof:name":"Bergler",
    "wof:placetype":"venue"
},
  "geometry": {"coordinates":[12.158683,49.792892],"type":"Point"}
}