{
  "type": "Feature",
  "properties": {
    "iso:country":"DE",
    "sg:address":"G\u00f6kerstr. 125",
    "sg:city":"Wilhelmshaven",
    "sg:phone":"+49 4421/304543",
    "sg:postcode":"26384",
    "sg:province":"Niedersachsen",
    "wof:name":"Botanischer Garten Wilhelmshaven",
    "wof:placetype":"venue"
},
  "geometry": {"coordinates":[8.123937,53.538326],"type":"Point"}
}