{
  "type": "Feature",
  "properties": {
    "iso:country":"DE",
    "sg:address":"Anton-Schmidt-Str 3",
    "sg:city":"Waiblingen",
    "sg:phone":"+49 7151/18711",
    "sg:postcode":"71332",
    "sg:province":"Baden-W\u00fcrttemberg",
    "wof:name":"Ls Lenz",
    "wof:placetype":"venue"
},
  "geometry": {"coordinates":[9.322121,48.823303],"type":"Point"}
}