{
  "type": "Feature",
  "properties": {
    "iso:country":"DE",
    "sg:address":"Petersfeldstr. 34",
    "sg:city":"Bocholt",
    "sg:phone":"+49 2871/8669",
    "sg:postcode":"46395",
    "sg:province":"Nordrhein-Westfalen",
    "wof:name":"Christel Fehr Und Franz Jansen",
    "wof:placetype":"venue"
},
  "geometry": {"coordinates":[6.622394,51.824596],"type":"Point"}
}