{
  "type": "Feature",
  "properties": {
    "iso:country":"DE",
    "sg:address":"Werftstr. 5",
    "sg:city":"Elsfleth",
    "sg:phone":"+49 4404/3333",
    "sg:postcode":"26931",
    "sg:province":"Niedersachsen",
    "wof:name":"Omnibus- Autovermietung Wilfried Gebken",
    "wof:placetype":"venue"
},
  "geometry": {"coordinates":[8.4567461014,53.2313613892],"type":"Point"}
}