{
  "type": "Feature",
  "properties": {
    "iso:country":"DE",
    "sg:address":"Altst\u00e4dter Str. 6",
    "sg:city":"Bad D\u00fcben",
    "sg:phone":"+49 34243/23425",
    "sg:postcode":"04849",
    "sg:province":"Sachsen",
    "wof:name":"Kristina Pfeffer",
    "wof:placetype":"venue"
},
  "geometry": {"coordinates":[12.587100029,51.5912590027],"type":"Point"}
}