{
  "type": "Feature",
  "properties": {
    "iso:country":"DE",
    "sg:address":"Pfaffenbrunnenstr. 124",
    "sg:city":"Hanau",
    "sg:phone":"+49 6181/62031",
    "sg:postcode":"63456",
    "sg:province":"Hessen",
    "wof:name":"Toom-markt Gmbh",
    "wof:placetype":"venue"
},
  "geometry": {"coordinates":[8.8927602768,50.1201515198],"type":"Point"}
}