{
  "type": "Feature",
  "properties": {
    "iso:country":"DE",
    "sg:address":"Harmskamp 10",
    "sg:city":"Gronau",
    "sg:phone":"+49 2565/7560",
    "sg:postcode":"48599",
    "sg:province":"Nordrhein-Westfalen",
    "wof:name":"Peter Wilmes Ingenieur",
    "wof:placetype":"venue"
},
  "geometry": {"coordinates":[7.0447077751,52.1846466064],"type":"Point"}
}