{
  "type": "Feature",
  "properties": {
    "iso:country":"DE",
    "sg:address":"Holzgasse 64",
    "sg:city":"L\u00f6rrach",
    "sg:phone":"+49 7621/2958",
    "sg:postcode":"79539",
    "sg:province":"Baden-W\u00fcrttemberg",
    "wof:name":"Dr. Konrad Lemke Tierarzt",
    "wof:placetype":"venue"
},
  "geometry": {"coordinates":[7.6737098694,47.6105232239],"type":"Point"}
}