{
  "type": "Feature",
  "properties": {
    "iso:country":"DE",
    "sg:address":"Vielitzer Holzweg 9",
    "sg:city":"Selb",
    "sg:phone":"+49 9287/3363",
    "sg:postcode":"95100",
    "sg:province":"Bayern",
    "wof:name":"Willi Fischer",
    "wof:placetype":"venue"
},
  "geometry": {"coordinates":[12.1166801453,50.1684303284],"type":"Point"}
}