{
  "type": "Feature",
  "properties": {
    "iso:country":"DE",
    "sg:address":"Markt 9",
    "sg:city":"Liebertwolkwitz",
    "sg:phone":"+49 34297/45007",
    "sg:postcode":"04445",
    "wof:name":"S. Roder",
    "wof:placetype":"venue"
},
  "geometry": {"coordinates":[12.46435,51.28249],"type":"Point"}
}