{
  "type": "Feature",
  "properties": {
    "iso:country":"DE",
    "sg:address":"M\u00f6nchw\u00f6rthstr. 24",
    "sg:city":"Mannheim",
    "sg:phone":"+49 621/8322300",
    "sg:postcode":"68199",
    "sg:province":"Baden-W\u00fcrttemberg",
    "wof:name":"Dr. A. Schreiber",
    "wof:placetype":"venue"
},
  "geometry": {"coordinates":[8.4893693924,49.4606628418],"type":"Point"}
}