{
  "type": "Feature",
  "properties": {
    "iso:country":"DE",
    "sg:address":"Corinthstr. 24",
    "sg:city":"Dresden",
    "sg:phone":"+49 351/4712084",
    "sg:postcode":"01217",
    "sg:province":"Sachsen",
    "wof:name":"Hans-dieter Wilhelm",
    "wof:placetype":"venue"
},
  "geometry": {"coordinates":[13.759466,51.020832],"type":"Point"}
}