{
  "type": "Feature",
  "properties": {
    "iso:country":"DE",
    "sg:address":"Dietenheimer Str. 11",
    "sg:city":"Illertissen",
    "sg:phone":"+49 7303/920681",
    "sg:postcode":"89257",
    "sg:province":"Bayern",
    "wof:name":"Generali Lloyd",
    "wof:placetype":"venue"
},
  "geometry": {"coordinates":[10.1009168625,48.2202568054],"type":"Point"}
}