{
  "type": "Feature",
  "properties": {
    "iso:country":"DE",
    "sg:address":"Bahnhofstr. 88",
    "sg:city":"Gr\u00e4felfing",
    "sg:phone":"+49 89/852271",
    "sg:postcode":"82166",
    "sg:province":"Bayern",
    "wof:name":"Willy Sch\u00f6ller Gmbh Inh. S. G\u00f6sswein",
    "wof:placetype":"venue"
},
  "geometry": {"coordinates":[11.4308443069,48.1180076599],"type":"Point"}
}