{
  "type": "Feature",
  "properties": {
    "iso:country":"DE",
    "sg:address":"Paul-Ehrlich-Str. 14",
    "sg:city":"Kaiserslautern",
    "sg:postcode":"67663",
    "sg:province":"Rheinland-Pfalz",
    "wof:name":"Wiss. Institut Fach Verkehrswesen",
    "wof:placetype":"venue"
},
  "geometry": {"coordinates":[7.7550191879,49.4265098572],"type":"Point"}
}