{
  "type": "Feature",
  "properties": {
    "iso:country":"DE",
    "sg:address":"Geschwister-Scholl-Str. 22",
    "sg:city":"Hartmannsdorf",
    "sg:phone":"+49 3722/97382",
    "sg:postcode":"09232",
    "sg:province":"Sachsen",
    "wof:name":"Christian Naumann",
    "wof:placetype":"venue"
},
  "geometry": {"coordinates":[12.7932128906,50.8865585327],"type":"Point"}
}