{
  "type": "Feature",
  "properties": {
    "iso:country":"DE",
    "sg:address":"Kaufbeurener Str. 19",
    "sg:city":"Marktoberdorf",
    "sg:phone":"+49 8342/42773",
    "sg:postcode":"87616",
    "sg:province":"Bayern",
    "wof:name":"Georg Ritter",
    "wof:placetype":"venue"
},
  "geometry": {"coordinates":[10.6195812225,47.782081604],"type":"Point"}
}