{
  "type": "Feature",
  "properties": {
    "iso:country":"DE",
    "sg:address":"Carl-von-Linde-Str. 38",
    "sg:city":"Unterschlei\u00dfheim",
    "sg:phone":"+49 89/6807920",
    "sg:postcode":"85716",
    "sg:province":"Bayern",
    "wof:name":"One 4 Net Gmbh",
    "wof:placetype":"venue"
},
  "geometry": {"coordinates":[11.5683145523,48.2812614441],"type":"Point"}
}