{
  "type": "Feature",
  "properties": {
    "iso:country":"DE",
    "sg:address":"Franz-Kleine-Str. 31",
    "sg:city":"Salzkotten",
    "sg:phone":"+49 5258/98620",
    "sg:postcode":"33154",
    "sg:province":"Nordrhein-Westfalen",
    "wof:name":"Kottmann & Kottmann Gmbh",
    "wof:placetype":"venue"
},
  "geometry": {"coordinates":[8.588527,51.666424],"type":"Point"}
}