{
  "type": "Feature",
  "properties": {
    "iso:country":"DE",
    "sg:address":"Putzbrunner Str. 87",
    "sg:city":"M\u00fcnchen",
    "sg:phone":"+49 89/6706196",
    "sg:postcode":"81739",
    "sg:province":"Bayern",
    "wof:name":"K. Kammergruber",
    "wof:placetype":"venue"
},
  "geometry": {"coordinates":[11.6485338211,48.0959701538],"type":"Point"}
}