{
  "type": "Feature",
  "properties": {
    "iso:country":"DE",
    "sg:address":"Ludwigstr. 1",
    "sg:city":"Sersheim",
    "sg:phone":"+49 7042/33958",
    "sg:postcode":"74372",
    "sg:province":"Baden-W\u00fcrttemberg",
    "wof:name":"Horst M\u00fcller",
    "wof:placetype":"venue"
},
  "geometry": {"coordinates":[9.013006,48.960468],"type":"Point"}
}