{
  "type": "Feature",
  "properties": {
    "iso:country":"DE",
    "sg:address":"Graesbecker Weg 12",
    "sg:city":"Walsrode",
    "sg:phone":"+49 5161/73749",
    "sg:postcode":"29664",
    "sg:province":"Niedersachsen",
    "wof:name":"Volksf\u00fcrsorge Oliver Schnittger",
    "wof:placetype":"venue"
},
  "geometry": {"coordinates":[9.605175972,52.8638153076],"type":"Point"}
}