{
  "type": "Feature",
  "properties": {
    "iso:country":"DE",
    "sg:address":"Lange Str. 60",
    "sg:city":"Barth",
    "sg:phone":"+49 38231/623",
    "sg:postcode":"18356",
    "sg:province":"Mecklenburg-Vorpommern",
    "wof:name":"Hotel Restaurant Stadt Barth",
    "wof:placetype":"venue"
},
  "geometry": {"coordinates":[12.725194931,54.3661766052],"type":"Point"}
}