{
  "type": "Feature",
  "properties": {
    "iso:country":"DE",
    "sg:address":"\u00c4u\u00dferer Zeisigweg 12a",
    "sg:city":"Leipzig",
    "sg:postcode":"04158",
    "sg:province":"Sachsen",
    "wof:name":"G\u00fcnter Hoffmann",
    "wof:placetype":"venue"
},
  "geometry": {"coordinates":[12.331095,51.385212],"type":"Point"}
}