{
  "type": "Feature",
  "properties": {
    "iso:country":"DE",
    "sg:address":"Am Birkenrain 2",
    "sg:city":"Metzingen",
    "sg:phone":"+49 7123/61423",
    "sg:postcode":"72555",
    "sg:province":"Baden-W\u00fcrttemberg",
    "wof:name":"Roland Roller",
    "wof:placetype":"venue"
},
  "geometry": {"coordinates":[9.309187,48.510712],"type":"Point"}
}