{
  "type": "Feature",
  "properties": {
    "iso:country":"DE",
    "sg:address":"Jahnstr. 11",
    "sg:city":"Hof",
    "sg:phone":"+49 9281/67595",
    "sg:postcode":"95030",
    "sg:province":"Bayern",
    "wof:name":"Konditorei D\u00e4umler Gmbh",
    "wof:placetype":"venue"
},
  "geometry": {"coordinates":[11.9054203033,50.3171195984],"type":"Point"}
}