{
  "type": "Feature",
  "properties": {
    "iso:country":"DE",
    "sg:address":"Hechtstr. 33",
    "sg:city":"Dresden",
    "sg:postcode":"01097",
    "sg:province":"Sachsen",
    "wof:name":"Planbau Gmbh",
    "wof:placetype":"venue"
},
  "geometry": {"coordinates":[13.746684,51.074696],"type":"Point"}
}