{
  "type": "Feature",
  "properties": {
    "iso:country":"DE",
    "sg:address":"Die Sang 7",
    "sg:city":"Rosbach",
    "sg:postcode":"61191",
    "sg:province":"Hessen",
    "wof:name":"Far Music Production Gmbh",
    "wof:placetype":"venue"
},
  "geometry": {"coordinates":[8.6901054382,50.3032836914],"type":"Point"}
}