{
  "type": "Feature",
  "properties": {
    "iso:country":"DE",
    "sg:address":"Heilbronner Str. 21",
    "sg:city":"Schw\u00e4bisch Hall",
    "sg:phone":"+49 791/6303",
    "sg:postcode":"74523",
    "sg:province":"Baden-W\u00fcrttemberg",
    "wof:name":"Josef Nestl",
    "wof:placetype":"venue"
},
  "geometry": {"coordinates":[9.7370910645,49.1207542419],"type":"Point"}
}