{
  "type": "Feature",
  "properties": {
    "iso:country":"DE",
    "sg:address":"Schulgasse 17",
    "sg:city":"Freyung",
    "sg:phone":"+49 8551/2331",
    "sg:postcode":"94078",
    "sg:province":"Bayern",
    "wof:name":"Backs-flash",
    "wof:placetype":"venue"
},
  "geometry": {"coordinates":[13.546518,48.808422],"type":"Point"}
}