{
  "type": "Feature",
  "properties": {
    "iso:country":"DE",
    "sg:address":"Eichenweg 2",
    "sg:city":"Dingolfing",
    "sg:phone":"+49 8731/7788",
    "sg:postcode":"84130",
    "sg:province":"Bayern",
    "wof:name":"Werbegemeinschaft Dingolfing Ernst Zahnweh",
    "wof:placetype":"venue"
},
  "geometry": {"coordinates":[12.4868850708,48.6255836487],"type":"Point"}
}