{
  "type": "Feature",
  "properties": {
    "iso:country":"DE",
    "sg:address":"Kirchplatz 2",
    "sg:city":"Hennickendorf",
    "sg:phone":"+49 33434/7227",
    "sg:postcode":"15378",
    "sg:province":"Brandenburg",
    "wof:name":"Ingo Noss",
    "wof:placetype":"venue"
},
  "geometry": {"coordinates":[13.846879,52.507339],"type":"Point"}
}