{
  "type": "Feature",
  "properties": {
    "iso:country":"DE",
    "sg:address":"Oskar-von-Miller-Str. 14",
    "sg:city":"Alt\u00f6tting",
    "sg:phone":"+49 8671/6690",
    "sg:postcode":"84503",
    "sg:province":"Bayern",
    "wof:name":"Kranverleih Saller Gmbh",
    "wof:placetype":"venue"
},
  "geometry": {"coordinates":[12.6824579239,48.2201004028],"type":"Point"}
}