{
  "type": "Feature",
  "properties": {
    "iso:country":"DE",
    "sg:address":"Kapellenweg 14",
    "sg:city":"Nachrodt-Wiblingwerde",
    "sg:phone":"+49 2352/933173",
    "sg:postcode":"58769",
    "sg:province":"Nordrhein-Westfalen",
    "wof:name":"Norbert Hammerschmidt",
    "wof:placetype":"venue"
},
  "geometry": {"coordinates":[7.643208,51.324978],"type":"Point"}
}