{
  "type": "Feature",
  "properties": {
    "iso:country":"DE",
    "sg:address":"Am Walde 14",
    "sg:city":"Fredenbeck",
    "sg:phone":"+49 4149/7498",
    "sg:postcode":"21717",
    "sg:province":"Niedersachsen",
    "wof:name":"Hans-peter Rauh Heilpraktiker",
    "wof:placetype":"venue"
},
  "geometry": {"coordinates":[9.401432991,53.5208053589],"type":"Point"}
}