{
  "type": "Feature",
  "properties": {
    "iso:country":"DE",
    "sg:address":"Ahornallee 6",
    "sg:city":"Berlin",
    "sg:postcode":"14050",
    "sg:province":"Berlin",
    "wof:name":"Bau Und Grund Unternehmens- Beratung Gmbh & Co.",
    "wof:placetype":"venue"
},
  "geometry": {"coordinates":[13.276876,52.516273],"type":"Point"}
}