{
  "type": "Feature",
  "properties": {
    "iso:country":"DE",
    "sg:address":"Corunna Str. 12A",
    "sg:city":"Iserlohn",
    "sg:phone":"+49 2371/20001",
    "sg:postcode":"58636",
    "sg:province":"Nordrhein-Westfalen",
    "wof:name":"Modellbautechnik Ralf Petrausch E. K.",
    "wof:placetype":"venue"
},
  "geometry": {"coordinates":[7.737197,51.376335],"type":"Point"}
}