{
  "type": "Feature",
  "properties": {
    "iso:country":"DE",
    "sg:address":"Kirchbergstr. 83",
    "sg:city":"Waldachtal",
    "sg:phone":"+49 7443/96280",
    "sg:postcode":"72178",
    "sg:province":"Baden-W\u00fcrttemberg",
    "wof:name":"Hotel Panorama",
    "wof:placetype":"venue"
},
  "geometry": {"coordinates":[8.5608110428,48.4923477173],"type":"Point"}
}