{
  "type": "Feature",
  "properties": {
    "iso:country":"DE",
    "sg:address":"Blankenauer Str 15",
    "sg:city":"Beverungen",
    "sg:phone":"+49 571/975290",
    "sg:postcode":"37688",
    "sg:province":"Nordrhein-Westfalen",
    "wof:name":"Gerber Communications Gmbh",
    "wof:placetype":"venue"
},
  "geometry": {"coordinates":[8.9189872742,52.2383460999],"type":"Point"}
}