{
  "type": "Feature",
  "properties": {
    "iso:country":"DE",
    "sg:address":"Bahnhofsweg 6",
    "sg:city":"Hitzacker",
    "sg:phone":"+49 5862/5009",
    "sg:postcode":"29456",
    "sg:province":"Niedersachsen",
    "wof:name":"Wzt-wendland-zerspanungs- Technik Gmbh",
    "wof:placetype":"venue"
},
  "geometry": {"coordinates":[11.0386352539,53.1421203613],"type":"Point"}
}