{
  "type": "Feature",
  "properties": {
    "iso:country":"DE",
    "sg:address":"Pahlbl\u00f6ckensstieg 1",
    "sg:city":"Hamburg",
    "sg:phone":"+49 40",
    "sg:postcode":"22143",
    "sg:province":"Hamburg",
    "wof:name":"Buecherjagd.de",
    "wof:placetype":"venue"
},
  "geometry": {"coordinates":[10.1689720154,53.6068878174],"type":"Point"}
}