{
  "type": "Feature",
  "properties": {
    "iso:country":"DE",
    "sg:address":"Hauptstr. 73",
    "sg:city":"Hornberg",
    "sg:phone":"+49 7833/282",
    "sg:postcode":"78132",
    "sg:province":"Baden-W\u00fcrttemberg",
    "wof:name":"G\u00fcnter Morgenschweis",
    "wof:placetype":"venue"
},
  "geometry": {"coordinates":[8.229323,48.212612],"type":"Point"}
}