{
  "type": "Feature",
  "properties": {
    "iso:country":"DE",
    "sg:address":"Marktstr. 15",
    "sg:city":"Hopsten",
    "sg:phone":"+49 5458/7088",
    "sg:postcode":"48496",
    "sg:province":"Nordrhein-Westfalen",
    "wof:name":"Heinrich Schmidt",
    "wof:placetype":"venue"
},
  "geometry": {"coordinates":[7.6043949127,52.3845748901],"type":"Point"}
}