{
  "type": "Feature",
  "properties": {
    "iso:country":"DE",
    "sg:address":"Haydnweg 7",
    "sg:city":"Lorch",
    "sg:phone":"+49 7172/5697",
    "sg:postcode":"73547",
    "sg:province":"Baden-W\u00fcrttemberg",
    "wof:name":"Magdalena Baur",
    "wof:placetype":"venue"
},
  "geometry": {"coordinates":[9.6786832809,48.8019142151],"type":"Point"}
}