{
  "type": "Feature",
  "properties": {
    "iso:country":"DE",
    "sg:address":"Fronm\u00fcllerstr. 22",
    "sg:city":"F\u00fcrth",
    "sg:phone":"+49 911/741293",
    "sg:postcode":"90763",
    "sg:province":"Bayern",
    "wof:name":"St\u00e4dtische Volksb\u00fccherei",
    "wof:placetype":"venue"
},
  "geometry": {"coordinates":[10.992112,49.456989],"type":"Point"}
}