{
  "type": "Feature",
  "properties": {
    "iso:country":"DE",
    "sg:address":"Birkenstr. 9",
    "sg:city":"Helmbrechts",
    "sg:phone":"+49 7907/942920",
    "sg:postcode":"95233",
    "sg:province":"Bayern",
    "wof:name":"Uni Oeler L. + G. Beck Gmbh",
    "wof:placetype":"venue"
},
  "geometry": {"coordinates":[9.74606,49.113312],"type":"Point"}
}