{
  "type": "Feature",
  "properties": {
    "iso:country":"DE",
    "sg:address":"Pischekstr. 9",
    "sg:city":"Stuttgart",
    "sg:phone":"+49 711/2368280",
    "sg:postcode":"70184",
    "sg:province":"Baden-W\u00fcrttemberg",
    "wof:name":"Adolf Hilpert",
    "wof:placetype":"venue"
},
  "geometry": {"coordinates":[9.1949472427,48.7687721252],"type":"Point"}
}