{
  "type": "Feature",
  "properties": {
    "iso:country":"DE",
    "sg:address":"Lange Str. 20",
    "sg:city":"Zschopau",
    "sg:phone":"+49 3725/22109",
    "sg:postcode":"09405",
    "sg:province":"Sachsen",
    "wof:name":"Maurer",
    "wof:placetype":"venue"
},
  "geometry": {"coordinates":[13.0701990128,50.7477493286],"type":"Point"}
}