{
  "type": "Feature",
  "properties": {
    "iso:country":"DE",
    "sg:address":"Ritter-von-Eitzenberger-Str 17",
    "sg:city":"Bayreuth",
    "sg:phone":"+49 921/757440",
    "sg:postcode":"95448",
    "sg:province":"Bayern",
    "wof:name":"Spedition U. M\u00f6beltransport Rospeg Bayreuth Gmbh",
    "wof:placetype":"venue"
},
  "geometry": {"coordinates":[11.6166448593,49.9617233276],"type":"Point"}
}