{
  "type": "Feature",
  "properties": {
    "iso:country":"DE",
    "sg:address":"Muscheider Str. 13",
    "sg:city":"D\u00fcrrholz",
    "sg:phone":"+49 2684/959262",
    "sg:postcode":"56307",
    "sg:province":"Rheinland-Pfalz",
    "wof:name":"Lazar Stan Tennishalle",
    "wof:placetype":"venue"
},
  "geometry": {"coordinates":[7.5760860443,50.5856056213],"type":"Point"}
}