{
  "type": "Feature",
  "properties": {
    "iso:country":"DE",
    "sg:address":"Pienzenauerstr. 30 A",
    "sg:city":"M\u00fcnchen",
    "sg:phone":"+49 89/989275",
    "sg:postcode":"81679",
    "sg:province":"Bayern",
    "wof:name":"Herma Verwaltungs Gmbh",
    "wof:placetype":"venue"
},
  "geometry": {"coordinates":[11.6048440933,48.153263092],"type":"Point"}
}