{
  "type": "Feature",
  "properties": {
    "iso:country":"DE",
    "sg:address":"Senserstr. 10",
    "sg:city":"M\u00fcnchen",
    "sg:phone":"+49 89/7252727",
    "sg:postcode":"81371",
    "sg:province":"Bayern",
    "wof:name":"Wolfgang Bogdanski Steuerberater",
    "wof:placetype":"venue"
},
  "geometry": {"coordinates":[11.5471000671,48.1226654053],"type":"Point"}
}