{
  "type": "Feature",
  "properties": {
    "iso:country":"DE",
    "sg:address":"Alter Kesselst\u00e4dter Weg 9",
    "sg:city":"Maintal",
    "sg:phone":"+49 6181/45472",
    "sg:postcode":"63477",
    "sg:province":"Hessen",
    "wof:name":"Schnitzel-h\u00e4uschen",
    "wof:placetype":"venue"
},
  "geometry": {"coordinates":[8.8495788574,50.1313438416],"type":"Point"}
}