{
  "type": "Feature",
  "properties": {
    "iso:country":"DE",
    "sg:city":"Waiblingen",
    "sg:postcode":"71332",
    "sg:province":"Baden-W\u00fcrttemberg",
    "wof:name":"Donner Partner Gmbh",
    "wof:placetype":"venue"
},
  "geometry": {"coordinates":[9.313598,48.832989],"type":"Point"}
}