{
  "type": "Feature",
  "properties": {
    "iso:country":"DE",
    "sg:address":"Hanauer Landstr. 2",
    "sg:city":"Kahl",
    "sg:phone":"+49 4961/882063",
    "sg:postcode":"63796",
    "sg:province":"Bayern",
    "wof:name":"Sparkasse Aschaffenburg-alzenau",
    "wof:placetype":"venue"
},
  "geometry": {"coordinates":[9.005898,50.06945],"type":"Point"}
}