{
  "type": "Feature",
  "properties": {
    "iso:country":"DE",
    "sg:address":"Rheinbabenallee 13",
    "sg:city":"Boppard",
    "sg:phone":"+49 6742/6994",
    "sg:postcode":"56154",
    "sg:province":"Rheinland-Pfalz",
    "wof:name":"Hotel Kasper",
    "wof:placetype":"venue"
},
  "geometry": {"coordinates":[7.632545948,50.207950592],"type":"Point"}
}