{
  "type": "Feature",
  "properties": {
    "iso:country":"DE",
    "sg:address":"Altrheinstr. 104",
    "sg:city":"Eich",
    "sg:phone":"+49 6246/273",
    "sg:postcode":"67575",
    "sg:province":"Rheinland-Pfalz",
    "wof:name":"Heinrich Nickel",
    "wof:placetype":"venue"
},
  "geometry": {"coordinates":[8.407238,49.750034],"type":"Point"}
}