{
  "type": "Feature",
  "properties": {
    "iso:country":"DE",
    "sg:address":"Niedersachsenweg 1",
    "sg:city":"Hamburg",
    "sg:phone":"+49 40/7643572",
    "sg:postcode":"21079",
    "sg:province":"Hamburg",
    "wof:name":"Ingeborg Laun Krankengymnastin",
    "wof:placetype":"venue"
},
  "geometry": {"coordinates":[10.002776,53.438282],"type":"Point"}
}