{
  "type": "Feature",
  "properties": {
    "iso:country":"DE",
    "sg:address":"Fischergasse 16",
    "sg:city":"Weilheim",
    "sg:phone":"+49 881/3926",
    "sg:postcode":"82362",
    "sg:province":"Bayern",
    "wof:name":"Rfa Prozesstechnik Gmbh",
    "wof:placetype":"venue"
},
  "geometry": {"coordinates":[11.137887,47.839523],"type":"Point"}
}