{
  "type": "Feature",
  "properties": {
    "iso:country":"DE",
    "sg:address":"Calhorner Kirchweg 85",
    "sg:city":"Essen",
    "sg:phone":"+49 5434/2103",
    "sg:postcode":"49632",
    "sg:province":"Niedersachsen",
    "wof:name":"Alfons Brengelmann",
    "wof:placetype":"venue"
},
  "geometry": {"coordinates":[7.9602150917,52.7267684937],"type":"Point"}
}