{
  "type": "Feature",
  "properties": {
    "iso:country":"DE",
    "sg:address":"Wallstr 12",
    "sg:city":"B\u00fchl",
    "sg:phone":"+49 7223/24016",
    "sg:postcode":"77815",
    "sg:province":"Baden-W\u00fcrttemberg",
    "wof:name":"P. Schweiger",
    "wof:placetype":"venue"
},
  "geometry": {"coordinates":[8.107766,48.723812],"type":"Point"}
}