{
  "type": "Feature",
  "properties": {
    "iso:country":"DE",
    "sg:address":"Imhofstr. 7",
    "sg:city":"Augsburg",
    "sg:phone":"+49 821/5899836",
    "sg:postcode":"86159",
    "sg:province":"Bayern",
    "wof:name":"Sting Line Gmbh",
    "wof:placetype":"venue"
},
  "geometry": {"coordinates":[10.8869991302,48.3587684631],"type":"Point"}
}