{
  "type": "Feature",
  "properties": {
    "iso:country":"DE",
    "sg:address":"Hostatostr. 25",
    "sg:city":"Frankfurt",
    "sg:phone":"+49 69/30085232",
    "sg:postcode":"65929",
    "sg:province":"Hessen",
    "wof:name":"Deutsche Post Ag",
    "wof:placetype":"venue"
},
  "geometry": {"coordinates":[8.5448923111,50.100944519],"type":"Point"}
}