{
  "type": "Feature",
  "properties": {
    "iso:country":"DE",
    "sg:address":"Biernerstr. 13",
    "sg:city":"Freising",
    "sg:phone":"+49 8161/67008",
    "sg:postcode":"85354",
    "sg:province":"Bayern",
    "wof:name":"Anton Summerer Gmbh",
    "wof:placetype":"venue"
},
  "geometry": {"coordinates":[11.734869,48.405437],"type":"Point"}
}