{
  "type": "Feature",
  "properties": {
    "iso:country":"DE",
    "sg:address":"Bogenstr. 1",
    "sg:city":"Gerhardshofen",
    "sg:phone":"+49 9163/8219",
    "sg:postcode":"91466",
    "sg:province":"Bayern",
    "wof:name":"Dr. Ernst Feigl Tierarzt",
    "wof:placetype":"venue"
},
  "geometry": {"coordinates":[10.6936683655,49.6299514771],"type":"Point"}
}