{
  "type": "Feature",
  "properties": {
    "iso:country":"DE",
    "sg:address":"Finkenweg 2",
    "sg:city":"Lebach",
    "sg:phone":"+49 6887/7359",
    "sg:postcode":"66822",
    "sg:province":"Saarland",
    "wof:name":"H. Blug",
    "wof:placetype":"venue"
},
  "geometry": {"coordinates":[6.9053797722,49.4575309753],"type":"Point"}
}