{
  "type": "Feature",
  "properties": {
    "iso:country":"DE",
    "sg:address":"Wormser Landstr. 147",
    "sg:city":"Speyer",
    "sg:phone":"+49 6232/34343",
    "sg:postcode":"67346",
    "sg:province":"Rheinland-Pfalz",
    "wof:name":"W. Rehberger Bildhauer",
    "wof:placetype":"venue"
},
  "geometry": {"coordinates":[8.430107,49.333771],"type":"Point"}
}