{
  "type": "Feature",
  "properties": {
    "iso:country":"DE",
    "sg:address":"\u00c4u\u00dfere Bayreuther Str. 53 A",
    "sg:city":"N\u00fcrnberg",
    "sg:phone":"+49 911/512269",
    "sg:postcode":"90409",
    "sg:province":"Bayern",
    "wof:name":"Stoja-verlag Paul Janke",
    "wof:placetype":"venue"
},
  "geometry": {"coordinates":[11.0987033844,49.468208313],"type":"Point"}
}