{
  "type": "Feature",
  "properties": {
    "iso:country":"DE",
    "sg:address":"Kornweg 30",
    "sg:city":"Schwerte",
    "sg:phone":"+49 2304/943323",
    "sg:postcode":"58239",
    "sg:province":"Nordrhein-Westfalen",
    "wof:name":"Gerhard R\u00f6ber Architekt",
    "wof:placetype":"venue"
},
  "geometry": {"coordinates":[7.572726,51.464855],"type":"Point"}
}