{
  "type": "Feature",
  "properties": {
    "iso:country":"DE",
    "sg:address":"Bahnhofstr. 41",
    "sg:city":"Kirkel",
    "sg:phone":"+49 6841/80990",
    "sg:postcode":"66459",
    "sg:province":"Saarland",
    "wof:name":"Walter Bau Ag Saar-pfalz",
    "wof:placetype":"venue"
},
  "geometry": {"coordinates":[7.279586,49.312843],"type":"Point"}
}