{
  "type": "Feature",
  "properties": {
    "iso:country":"DE",
    "sg:address":"Ahren 24",
    "sg:city":"M\u00f6nchengladbach",
    "sg:phone":"+49 2166/87304",
    "sg:postcode":"41238",
    "sg:province":"Nordrhein-Westfalen",
    "wof:name":"Rolf Schiffer",
    "wof:placetype":"venue"
},
  "geometry": {"coordinates":[6.4808602333,51.1540679932],"type":"Point"}
}