{
  "type": "Feature",
  "properties": {
    "iso:country":"DE",
    "sg:address":"Hildebrandtstr. 4 f",
    "sg:city":"D\u00fcsseldorf",
    "sg:postcode":"40215",
    "sg:province":"Nordrhein-Westfalen",
    "wof:name":"Cross Research Gmbh",
    "wof:placetype":"venue"
},
  "geometry": {"coordinates":[6.78545,51.213886],"type":"Point"}
}