{
  "type": "Feature",
  "properties": {
    "iso:country":"DE",
    "sg:address":"S\u00fclberg 7-9",
    "sg:city":"Hemer",
    "sg:phone":"+49 2372/98900",
    "sg:postcode":"58675",
    "sg:province":"Nordrhein-Westfalen",
    "wof:name":"Nadler Gmbh",
    "wof:placetype":"venue"
},
  "geometry": {"coordinates":[7.738881,51.351292],"type":"Point"}
}