{
  "type": "Feature",
  "properties": {
    "iso:country":"DE",
    "sg:address":"Scharnweberstr 24",
    "sg:city":"Berlin",
    "sg:phone":"+49 7524/7885",
    "sg:postcode":"13405",
    "sg:province":"Berlin",
    "wof:name":"S\u00fcdrohrbau Rohrtechnik Gmbh",
    "wof:placetype":"venue"
},
  "geometry": {"coordinates":[9.756937,47.934219],"type":"Point"}
}