{
  "type": "Feature",
  "properties": {
    "iso:country":"DE",
    "sg:address":"Lichtweg 1",
    "sg:city":"Frankenberg",
    "sg:phone":"+49 6451/9369",
    "sg:postcode":"35066",
    "sg:province":"Hessen",
    "wof:name":"Pension Helmut Zulauf",
    "wof:placetype":"venue"
},
  "geometry": {"coordinates":[8.8265609741,51.1023254395],"type":"Point"}
}