{
  "type": "Feature",
  "properties": {
    "iso:country":"DE",
    "sg:address":"Wollankstr. 66",
    "sg:city":"Berlin",
    "sg:phone":"+49 30/4931953",
    "sg:postcode":"13359",
    "sg:province":"Berlin",
    "wof:name":"Wolfgang Scheiermann Grabdenkm\u00e4ler",
    "wof:placetype":"venue"
},
  "geometry": {"coordinates":[13.3879365921,52.5604858398],"type":"Point"}
}