{
  "type": "Feature",
  "properties": {
    "iso:country":"DE",
    "sg:address":"Ohrensener Weg 3",
    "sg:city":"Harsefeld",
    "sg:phone":"+49 4164/4565",
    "sg:postcode":"21698",
    "sg:province":"Niedersachsen",
    "wof:name":"Hans Winter",
    "wof:placetype":"venue"
},
  "geometry": {"coordinates":[9.467716217,53.4382476807],"type":"Point"}
}