{
  "type": "Feature",
  "properties": {
    "iso:country":"DE",
    "sg:address":"Schwegenheimer Str. 24",
    "sg:city":"R\u00f6merberg",
    "sg:phone":"+49 6232/83944",
    "sg:postcode":"67354",
    "sg:province":"Rheinland-Pfalz",
    "wof:name":"Rolf Wagner",
    "wof:placetype":"venue"
},
  "geometry": {"coordinates":[8.395734,49.265511],"type":"Point"}
}