{
  "type": "Feature",
  "properties": {
    "iso:country":"DE",
    "sg:address":"Hauptstr. 15",
    "sg:city":"Germersheim",
    "sg:phone":"+49 7274/777044",
    "sg:postcode":"76726",
    "sg:province":"Rheinland-Pfalz",
    "wof:name":"Hermann Garrecht",
    "wof:placetype":"venue"
},
  "geometry": {"coordinates":[8.3738870621,49.21925354],"type":"Point"}
}