{
  "type": "Feature",
  "properties": {
    "iso:country":"DE",
    "sg:address":"Markt 4",
    "sg:city":"Remscheid",
    "sg:phone":"+49 2191/292498",
    "sg:postcode":"42853",
    "sg:province":"Nordrhein-Westfalen",
    "wof:name":"Sofra Schnellimbi\u00df",
    "wof:placetype":"venue"
},
  "geometry": {"coordinates":[7.1939730644,51.1796340942],"type":"Point"}
}