{
  "type": "Feature",
  "properties": {
    "iso:country":"DE",
    "sg:address":"Cuno-Hoffmeister-Str. 27",
    "sg:city":"Sonneberg",
    "sg:phone":"+49 3675/742986",
    "sg:postcode":"96515",
    "sg:province":"Th\u00fcringen",
    "wof:name":"Heidi Minkewitz",
    "wof:placetype":"venue"
},
  "geometry": {"coordinates":[11.174832,50.355595],"type":"Point"}
}