{
  "type": "Feature",
  "properties": {
    "iso:country":"DE",
    "sg:address":"Am Quall 12",
    "sg:city":"Haan",
    "sg:postcode":"42781",
    "sg:province":"Nordrhein-Westfalen",
    "wof:name":"Bbw Design Und Kommunikation Gmbh & Co. Kg",
    "wof:placetype":"venue"
},
  "geometry": {"coordinates":[7.009065,51.226505],"type":"Point"}
}