{
  "type": "Feature",
  "properties": {
    "iso:country":"DE",
    "sg:address":"Intzestr. 117",
    "sg:city":"Remscheid",
    "sg:phone":"+49 2191/93690",
    "sg:postcode":"42859",
    "sg:province":"Nordrhein-Westfalen",
    "wof:name":"Elektro Schneider",
    "wof:placetype":"venue"
},
  "geometry": {"coordinates":[7.2251391411,51.1658058167],"type":"Point"}
}