{
  "type": "Feature",
  "properties": {
    "iso:country":"DE",
    "sg:address":"Hildegardstr. 19",
    "sg:city":"Berlin",
    "sg:phone":"+49 30/8532400",
    "sg:postcode":"10715",
    "sg:province":"Berlin",
    "wof:name":"Memduh Aki",
    "wof:placetype":"venue"
},
  "geometry": {"coordinates":[13.3220357895,52.4815673828],"type":"Point"}
}