{
  "type": "Feature",
  "properties": {
    "iso:country":"DE",
    "sg:address":"Frankfurter Str. 127-129",
    "sg:city":"Bad Vilbel",
    "sg:phone":"+49 6101/582880",
    "sg:postcode":"61118",
    "sg:province":"Hessen",
    "wof:name":"Taxplan Steuerberatungs Gmbh",
    "wof:placetype":"venue"
},
  "geometry": {"coordinates":[8.7363519669,50.1790122986],"type":"Point"}
}