{
  "type": "Feature",
  "properties": {
    "iso:country":"DE",
    "sg:address":"Ehrenzug 27",
    "sg:city":"Oederan",
    "sg:phone":"+49 37292/4936",
    "sg:postcode":"09569",
    "sg:province":"Sachsen",
    "wof:name":"Peter Gehre",
    "wof:placetype":"venue"
},
  "geometry": {"coordinates":[13.177189,50.861576],"type":"Point"}
}