{
  "type": "Feature",
  "properties": {
    "iso:country":"DE",
    "sg:address":"Bahnhofsallee 22",
    "sg:city":"Hilden",
    "sg:phone":"+49 2103/55165",
    "sg:postcode":"40721",
    "sg:province":"Nordrhein-Westfalen",
    "wof:name":"Mediteran",
    "wof:placetype":"venue"
},
  "geometry": {"coordinates":[6.9234528542,51.1674079895],"type":"Point"}
}