{
  "type": "Feature",
  "properties": {
    "iso:country":"DE",
    "sg:address":"Lauensteinstr. 5",
    "sg:city":"L\u00fcneburg",
    "sg:phone":"+49 4131/38225",
    "sg:postcode":"21339",
    "sg:province":"Niedersachsen",
    "wof:name":"Beate Eichhorn",
    "wof:placetype":"venue"
},
  "geometry": {"coordinates":[10.399723053,53.2523193359],"type":"Point"}
}