{
  "type": "Feature",
  "properties": {
    "iso:country":"DE",
    "sg:address":"Ulmenweg 2",
    "sg:city":"Wertheim",
    "sg:phone":"+49 9342/38585",
    "sg:postcode":"97877",
    "sg:province":"Baden-W\u00fcrttemberg",
    "wof:name":"Gastst\u00e4ttenbetriebe Kurt Schuon Gmbh",
    "wof:placetype":"venue"
},
  "geometry": {"coordinates":[9.5075330734,49.7814254761],"type":"Point"}
}