{
  "type": "Feature",
  "properties": {
    "iso:country":"DE",
    "sg:address":"Rutenpaul 3",
    "sg:city":"Werdohl",
    "sg:phone":"+49 2392/970941",
    "sg:postcode":"58791",
    "sg:province":"Nordrhein-Westfalen",
    "wof:name":"Udo Hoffrecht",
    "wof:placetype":"venue"
},
  "geometry": {"coordinates":[7.761443,51.240173],"type":"Point"}
}