{
  "type": "Feature",
  "properties": {
    "iso:country":"DE",
    "sg:address":"Zu den Brelinger Bergen 12",
    "sg:city":"Wedemark",
    "sg:phone":"+49 5130/2212",
    "sg:postcode":"30900",
    "sg:province":"Niedersachsen",
    "wof:name":"Hermann Bohm Architekt",
    "wof:placetype":"venue"
},
  "geometry": {"coordinates":[9.6836061478,52.5574607849],"type":"Point"}
}