{
  "type": "Feature",
  "properties": {
    "iso:country":"DE",
    "sg:address":"L\u00f6nsstr. 5",
    "sg:city":"Papenburg",
    "sg:phone":"+49 4962/410",
    "sg:postcode":"26871",
    "sg:province":"Niedersachsen",
    "wof:name":"Edmund Sosnowski",
    "wof:placetype":"venue"
},
  "geometry": {"coordinates":[7.396178,53.043224],"type":"Point"}
}