{
  "type": "Feature",
  "properties": {
    "iso:country":"DE",
    "sg:address":"Moselstr. 35",
    "sg:city":"Ernst",
    "sg:phone":"+49 2671/3144",
    "sg:postcode":"56814",
    "sg:province":"Rheinland-Pfalz",
    "wof:name":"Hermann Dax Weinanbau",
    "wof:placetype":"venue"
},
  "geometry": {"coordinates":[7.2224712372,50.1443099976],"type":"Point"}
}