{
  "type": "Feature",
  "properties": {
    "iso:country":"DE",
    "sg:address":"Eifelstr. 5",
    "sg:city":"Berlin",
    "sg:phone":"+49 30/4742449",
    "sg:postcode":"13129",
    "sg:province":"Berlin",
    "wof:name":"Werner Strohschein",
    "wof:placetype":"venue"
},
  "geometry": {"coordinates":[13.452165,52.596645],"type":"Point"}
}