{
  "type": "Feature",
  "properties": {
    "iso:country":"DE",
    "sg:address":"Jusiweg 21",
    "sg:city":"Kirchheim",
    "sg:phone":"+49 7021/864338",
    "sg:postcode":"73230",
    "sg:province":"Baden-W\u00fcrttemberg",
    "wof:name":"Siegfried M\u00e4ule Drogerie",
    "wof:placetype":"venue"
},
  "geometry": {"coordinates":[9.456118,48.639526],"type":"Point"}
}