{
  "type": "Feature",
  "properties": {
    "iso:country":"DE",
    "sg:address":"Erlenweg 24",
    "sg:city":"Witten",
    "sg:phone":"+49 2302/62557",
    "sg:postcode":"58453",
    "sg:province":"Nordrhein-Westfalen",
    "wof:name":"Karl-heinz Kruse",
    "wof:placetype":"venue"
},
  "geometry": {"coordinates":[7.3660387993,51.4452095032],"type":"Point"}
}