{
  "type": "Feature",
  "properties": {
    "iso:country":"DE",
    "sg:address":"Herrengartenstr. 5",
    "sg:city":"Ottweiler",
    "sg:phone":"+49 6824/1467",
    "sg:postcode":"66564",
    "sg:province":"Saarland",
    "wof:name":"Klaus Comtesse Heilpraktiker",
    "wof:placetype":"venue"
},
  "geometry": {"coordinates":[7.162776947,49.4026870728],"type":"Point"}
}