{
  "type": "Feature",
  "properties": {
    "iso:country":"DE",
    "sg:address":"Am Sebnitzbach",
    "sg:city":"Rathmannsdorf",
    "sg:postcode":"01814",
    "sg:province":"Sachsen",
    "wof:name":"Motorcycle Company Motorradclub S\u00e4chsische Schweiz",
    "wof:placetype":"venue"
},
  "geometry": {"coordinates":[14.138625,50.942444],"type":"Point"}
}