{
  "type": "Feature",
  "properties": {
    "iso:country":"DE",
    "sg:address":"Berliner Allee 24",
    "sg:city":"Berlin",
    "sg:phone":"+49 30/925224",
    "sg:postcode":"13088",
    "sg:province":"Berlin",
    "wof:name":"Phudys Co Multiart Gmbh",
    "wof:placetype":"venue"
},
  "geometry": {"coordinates":[13.450433,52.547825],"type":"Point"}
}