{
  "type": "Feature",
  "properties": {
    "iso:country":"DE",
    "sg:address":"Am Hofacker 4 Dippach",
    "sg:city":"Eltmann",
    "sg:phone":"+49 9522/6040",
    "sg:postcode":"97483",
    "sg:province":"Bayern",
    "wof:name":"Ernst Jansen",
    "wof:placetype":"venue"
},
  "geometry": {"coordinates":[10.6667690277,49.9719314575],"type":"Point"}
}