{
  "type": "Feature",
  "properties": {
    "iso:country":"DE",
    "sg:address":"Charlottenstr. 100-1",
    "sg:city":"Reutlingen",
    "sg:phone":"+49 7121/492004",
    "sg:postcode":"72764",
    "sg:province":"Baden-W\u00fcrttemberg",
    "wof:name":"Wolfgang Ackermann Anlageberater",
    "wof:placetype":"venue"
},
  "geometry": {"coordinates":[9.2261276245,48.4906578064],"type":"Point"}
}