{
  "type": "Feature",
  "properties": {
    "iso:country":"DE",
    "sg:address":"Karl-Marx-Str. 68a",
    "sg:city":"Cottbus",
    "sg:phone":"+49 355/794493",
    "sg:postcode":"03044",
    "sg:province":"Brandenburg",
    "wof:name":"Runners Point",
    "wof:placetype":"venue"
},
  "geometry": {"coordinates":[14.327861,51.76199],"type":"Point"}
}