{
  "type": "Feature",
  "properties": {
    "iso:country":"DE",
    "sg:address":"Postfach 25",
    "sg:city":"Obernbreit",
    "sg:postcode":"97342",
    "sg:province":"Bayern",
    "wof:name":"Gemeindeb\u00fccherei Obernbreit Rathaus",
    "wof:placetype":"venue"
},
  "geometry": {"coordinates":[10.168703,49.656551],"type":"Point"}
}