{
  "type": "Feature",
  "properties": {
    "iso:country":"DE",
    "sg:address":"Neuholland",
    "sg:city":"Essen",
    "sg:postcode":"45276",
    "sg:province":"Nordrhein-Westfalen",
    "wof:name":"Judo-club-essen.de",
    "wof:placetype":"venue"
},
  "geometry": {"coordinates":[7.085,51.446316],"type":"Point"}
}