{
  "type": "Feature",
  "properties": {
    "iso:country":"DE",
    "sg:address":"Bentelerstr. 4",
    "sg:city":"Paderborn",
    "sg:phone":"+49 5254/12938",
    "sg:postcode":"33104",
    "sg:province":"Nordrhein-Westfalen",
    "wof:name":"Gebr. Ostermann",
    "wof:placetype":"venue"
},
  "geometry": {"coordinates":[8.726234,51.743713],"type":"Point"}
}