{
  "type": "Feature",
  "properties": {
    "iso:country":"DE",
    "sg:address":"Donaustr. 22",
    "sg:city":"Sinzing",
    "sg:phone":"+49 941/31854",
    "sg:postcode":"93161",
    "sg:province":"Bayern",
    "wof:name":"Josef Gruber",
    "wof:placetype":"venue"
},
  "geometry": {"coordinates":[12.041754,48.993938],"type":"Point"}
}