{
  "type": "Feature",
  "properties": {
    "iso:country":"DE",
    "sg:address":"Postfach 1446",
    "sg:city":"Bonn",
    "sg:phone":"+49 4922/81040",
    "sg:postcode":"53113",
    "sg:province":"Nordrhein-Westfalen",
    "wof:name":"Deutscher Industrie-und Handelstag",
    "wof:placetype":"venue"
},
  "geometry": {"coordinates":[7.101695,50.7323],"type":"Point"}
}