{
  "type": "Feature",
  "properties": {
    "iso:country":"DE",
    "sg:address":"Maybachstr. 4",
    "sg:city":"Karlsruhe",
    "sg:phone":"+49 721/403098",
    "sg:postcode":"76227",
    "sg:province":"Baden-W\u00fcrttemberg",
    "wof:name":"Tixit-vertrieb",
    "wof:placetype":"venue"
},
  "geometry": {"coordinates":[8.439872,48.997482],"type":"Point"}
}