{
  "type": "Feature",
  "properties": {
    "iso:country":"DE",
    "sg:address":"Flughafenstr. 52a",
    "sg:city":"Hamburg",
    "sg:phone":"+49 40/6789646",
    "sg:postcode":"22335",
    "sg:province":"Hamburg",
    "wof:name":"Atc Asia Trading Und Consulting",
    "wof:placetype":"venue"
},
  "geometry": {"coordinates":[10.0150022507,53.6400413513],"type":"Point"}
}