{
  "type": "Feature",
  "properties": {
    "iso:country":"DE",
    "sg:address":"16 Mt. Bethel Road, #214",
    "sg:city":"Warren",
    "sg:classifiers":[
        {
            "category":"Professional",
            "subcategory":"Computer Services",
            "type":"Services"
        }
    ],
    "sg:postcode":"07059",
    "sg:province":"NJ",
    "sg:tags":[
        "ecommerce-marketplace",
        "ecommerce"
    ],
    "sg:website":"http://www.silkfair.com",
    "wof:name":"Silkfair",
    "wof:placetype":"venue"
},
  "geometry": {"coordinates":[-74.504458,40.627028],"type":"Point"}
}