{
  "type": "Feature",
  "properties": {
    "iso:country":"DE",
    "sg:address":"Carl-von-Linde-Str. 2",
    "sg:city":"Schwerin",
    "sg:phone":"+49 385/65800",
    "sg:postcode":"19061",
    "sg:province":"Mecklenburg-Vorpommern",
    "wof:name":"Peterm\u00e4nnchen- Stadtrundfahrten Gmbh",
    "wof:placetype":"venue"
},
  "geometry": {"coordinates":[11.3989534378,53.574180603],"type":"Point"}
}