{
  "type": "Feature",
  "properties": {
    "iso:country":"DE",
    "sg:address":"Jahnstr. 3",
    "sg:city":"Gerolsbach",
    "sg:phone":"+49 8445/282",
    "sg:postcode":"85302",
    "sg:province":"Bayern",
    "wof:name":"Josef Stelzer Ingenieur",
    "wof:placetype":"venue"
},
  "geometry": {"coordinates":[11.3627538681,48.4968986511],"type":"Point"}
}