{
  "type": "Feature",
  "properties": {
    "iso:country":"DE",
    "sg:address":"Erfurter Str 29",
    "sg:city":"Eching",
    "sg:phone":"+49 89/3196161",
    "sg:postcode":"85386",
    "sg:province":"Bayern",
    "wof:name":"Infraserv Vakuum Und Klimaservice Gmbh",
    "wof:placetype":"venue"
},
  "geometry": {"coordinates":[11.6220207214,48.3068656921],"type":"Point"}
}