{
  "type": "Feature",
  "properties": {
    "iso:country":"DE",
    "sg:address":"Bahnhofstr. 43",
    "sg:city":"Horn-Bad Meinberg",
    "sg:postcode":"32805",
    "sg:province":"Nordrhein-Westfalen",
    "wof:name":"Js Video Gmbh",
    "wof:placetype":"venue"
},
  "geometry": {"coordinates":[8.9538249969,51.8784408569],"type":"Point"}
}