{
  "type": "Feature",
  "properties": {
    "iso:country":"DE",
    "sg:address":"Am Angelbach 5",
    "sg:city":"Wiesloch",
    "sg:phone":"+49 6222/74906",
    "sg:postcode":"69168",
    "sg:province":"Baden-W\u00fcrttemberg",
    "wof:name":"Friedrich Laier",
    "wof:placetype":"venue"
},
  "geometry": {"coordinates":[8.7460632324,49.2980194092],"type":"Point"}
}