{
  "type": "Feature",
  "properties": {
    "iso:country":"DE",
    "sg:address":"Sendlinger Str. 56",
    "sg:city":"M\u00fcnchen",
    "sg:phone":"+49 89/2609980",
    "sg:postcode":"80331",
    "sg:province":"Bayern",
    "wof:name":"Redaktion Die Memoiren Des K\u00e4pt'n Rotbart",
    "wof:placetype":"venue"
},
  "geometry": {"coordinates":[11.5681829453,48.1343078613],"type":"Point"}
}