{
  "type": "Feature",
  "properties": {
    "iso:country":"DE",
    "sg:address":"Koenigshainer Strasse 38",
    "sg:city":"Goerlitz",
    "sg:phone":"+49 3581/704496",
    "sg:postcode":"02827",
    "sg:province":"Sachsen",
    "wof:name":"Kupferschmiede-goerlitz",
    "wof:placetype":"venue"
},
  "geometry": {"coordinates":[14.94077,51.13731],"type":"Point"}
}