{
  "type": "Feature",
  "properties": {
    "iso:country":"DE",
    "sg:address":"Bodelschwinghstr. 23",
    "sg:city":"Herford",
    "sg:phone":"+49 5221/61573",
    "sg:postcode":"32049",
    "sg:province":"Nordrhein-Westfalen",
    "wof:name":"Zimmerei Kleineberg Gmbh",
    "wof:placetype":"venue"
},
  "geometry": {"coordinates":[8.6741380692,52.1360435486],"type":"Point"}
}