{
  "type": "Feature",
  "properties": {
    "iso:country":"DE",
    "sg:address":"M\u00fcggenkampstr. 14",
    "sg:city":"Hamburg",
    "sg:phone":"+49 40/40196266",
    "sg:postcode":"20257",
    "sg:province":"Hamburg",
    "wof:name":"Hartwig Bauer Architekt",
    "wof:placetype":"venue"
},
  "geometry": {"coordinates":[9.94469,53.579796],"type":"Point"}
}