{
  "type": "Feature",
  "properties": {
    "iso:country":"DE",
    "sg:address":"Alte Rheinstr. 22",
    "sg:city":"Dillenburg",
    "sg:phone":"+49 2771/812100",
    "sg:postcode":"35683",
    "sg:province":"Hessen",
    "wof:name":"R\u00f6ssner Gmbh",
    "wof:placetype":"venue"
},
  "geometry": {"coordinates":[8.2758216858,50.7352905273],"type":"Point"}
}