{
  "type": "Feature",
  "properties": {
    "iso:country":"DE",
    "sg:address":"Schw\u00e4hnselstr. 34",
    "sg:city":"Saarbr\u00fccken",
    "sg:phone":"+49 6897/729719",
    "sg:postcode":"66125",
    "sg:province":"Saarland",
    "wof:name":"Dr. Ditmar Schulze Rechtsanwalt",
    "wof:placetype":"venue"
},
  "geometry": {"coordinates":[7.0436639786,49.2726402283],"type":"Point"}
}