{
  "type": "Feature",
  "properties": {
    "iso:country":"DE",
    "sg:address":"Klippenbusch 20",
    "sg:city":"Melle",
    "sg:postcode":"49326",
    "sg:province":"Niedersachsen",
    "wof:name":"Huning Verm\u00f6gensverwaltungs- Und Beteiligungsges. Mbh",
    "wof:placetype":"venue"
},
  "geometry": {"coordinates":[8.318967,52.142593],"type":"Point"}
}