{
  "type": "Feature",
  "properties": {
    "iso:country":"DE",
    "sg:address":"Hochst\u00e4tter Str. 2",
    "sg:city":"F\u00fcrfeld",
    "sg:phone":"+49 6709/433",
    "sg:postcode":"55546",
    "sg:province":"Rheinland-Pfalz",
    "wof:name":"Ernst Arnold",
    "wof:placetype":"venue"
},
  "geometry": {"coordinates":[7.891431,49.776684],"type":"Point"}
}