{
  "type": "Feature",
  "properties": {
    "iso:country":"DE",
    "sg:address":"Kronenhofer Str. 6",
    "sg:city":"Staufenberg",
    "sg:phone":"+49 5543/3994",
    "sg:postcode":"34355",
    "sg:province":"Niedersachsen",
    "wof:name":"Erich Held Ingenieur",
    "wof:placetype":"venue"
},
  "geometry": {"coordinates":[9.5872268677,51.3540496826],"type":"Point"}
}