{
  "type": "Feature",
  "properties": {
    "iso:country":"DE",
    "sg:address":"Ossecker Str. 63",
    "sg:city":"Hof",
    "sg:phone":"+49 9281/977248",
    "sg:postcode":"95030",
    "sg:province":"Bayern",
    "wof:name":"Kaisertex Gmbh",
    "wof:placetype":"venue"
},
  "geometry": {"coordinates":[11.8960943222,50.310005188],"type":"Point"}
}