{
  "type": "Feature",
  "properties": {
    "iso:country":"DE",
    "sg:address":"Ahornstr. 8",
    "sg:city":"D\u00fcsseldorf",
    "sg:phone":"+49 211/202827",
    "sg:postcode":"40627",
    "sg:province":"Nordrhein-Westfalen",
    "wof:name":"Kl.-p. Lietz Schaufenstergestaltung",
    "wof:placetype":"venue"
},
  "geometry": {"coordinates":[6.8985562325,51.2004508972],"type":"Point"}
}