{
  "type": "Feature",
  "properties": {
    "iso:country":"DE",
    "sg:address":"Br\u00fcnnensbach 1",
    "sg:city":"\u00dcberlingen",
    "sg:phone":"+49 7551/63581",
    "sg:postcode":"88662",
    "sg:province":"Baden-W\u00fcrttemberg",
    "wof:name":"Gletscherm\u00fchle",
    "wof:placetype":"venue"
},
  "geometry": {"coordinates":[9.1308822632,47.777381897],"type":"Point"}
}