{
  "type": "Feature",
  "properties": {
    "iso:country":"DE",
    "sg:address":"Finkenweg 12",
    "sg:city":"Blankenbach",
    "sg:phone":"+49 6024/4033",
    "sg:postcode":"63825",
    "sg:province":"Bayern",
    "wof:name":"Tc Clean Systeme Verbesserte Rahmenbedingungen Im Modernen",
    "wof:placetype":"venue"
},
  "geometry": {"coordinates":[9.2268733978,50.0694503784],"type":"Point"}
}