{
  "type": "Feature",
  "properties": {
    "iso:country":"DE",
    "sg:address":"Stuttgarter Str. 20",
    "sg:city":"Wiesbaden",
    "sg:phone":"+49 6122/51426",
    "sg:postcode":"65205",
    "sg:province":"Hessen",
    "wof:name":"Rochus Freiherr Von Wechmar",
    "wof:placetype":"venue"
},
  "geometry": {"coordinates":[8.3596458435,50.040851593],"type":"Point"}
}