{
  "type": "Feature",
  "properties": {
    "iso:country":"DE",
    "sg:address":"Feldstr. 14",
    "sg:city":"Bergheim",
    "sg:phone":"+49 2271/42638",
    "sg:postcode":"50126",
    "sg:province":"Nordrhein-Westfalen",
    "wof:name":"Peter P\u00fctz Architekt Bdb",
    "wof:placetype":"venue"
},
  "geometry": {"coordinates":[6.639353,50.958927],"type":"Point"}
}