{
  "type": "Feature",
  "properties": {
    "iso:country":"DE",
    "sg:address":"M\u00fchlenweg 4",
    "sg:city":"Saarbr\u00fccken",
    "sg:phone":"+49 6805/7852",
    "sg:postcode":"66129",
    "sg:province":"Saarland",
    "wof:name":"Franz Oberhausen",
    "wof:placetype":"venue"
},
  "geometry": {"coordinates":[7.032853,49.274685],"type":"Point"}
}