{
  "type": "Feature",
  "properties": {
    "iso:country":"DE",
    "sg:address":"Hauptstr. 195",
    "sg:city":"Spaichingen",
    "sg:phone":"+49 7424/501616",
    "sg:postcode":"78549",
    "sg:province":"Baden-W\u00fcrttemberg",
    "wof:name":"Gabriele Allert",
    "wof:placetype":"venue"
},
  "geometry": {"coordinates":[8.731946,48.080685],"type":"Point"}
}