{
  "type": "Feature",
  "properties": {
    "iso:country":"DE",
    "sg:address":"Margaretenstr. 29",
    "sg:city":"Hagen",
    "sg:phone":"+49 2331/43056",
    "sg:postcode":"58089",
    "sg:province":"Nordrhein-Westfalen",
    "wof:name":"Hermann Boehme E. K.",
    "wof:placetype":"venue"
},
  "geometry": {"coordinates":[7.4430069923,51.3617591858],"type":"Point"}
}