{
  "type": "Feature",
  "properties": {
    "iso:country":"DE",
    "sg:address":"Attelsdorf 8",
    "sg:city":"Schl\u00fcsselfeld",
    "sg:phone":"+49 9552/436",
    "sg:postcode":"96132",
    "sg:province":"Bayern",
    "wof:name":"Leo W\u00e4chtler",
    "wof:placetype":"venue"
},
  "geometry": {"coordinates":[10.6345081329,49.746963501],"type":"Point"}
}