{
  "type": "Feature",
  "properties": {
    "iso:country":"DE",
    "sg:address":"Ludwigstr. 14",
    "sg:city":"Schotten",
    "sg:phone":"+49 6044/8234",
    "sg:postcode":"63679",
    "sg:province":"Hessen",
    "wof:name":"Park-apotheke",
    "wof:placetype":"venue"
},
  "geometry": {"coordinates":[9.125274,50.503426],"type":"Point"}
}