{
  "type": "Feature",
  "properties": {
    "iso:country":"DE",
    "sg:address":"Hauptstr. 78",
    "sg:city":"Eppertshausen",
    "sg:phone":"+49 6071/35659",
    "sg:postcode":"64859",
    "sg:province":"Hessen",
    "wof:name":"Maria Sperl",
    "wof:placetype":"venue"
},
  "geometry": {"coordinates":[8.842625618,49.9471740723],"type":"Point"}
}