{
  "type": "Feature",
  "properties": {
    "iso:country":"DE",
    "sg:address":"B\u00e4renstr. 12",
    "sg:city":"Forchheim",
    "sg:phone":"+49 7642/7278",
    "sg:postcode":"79362",
    "sg:province":"Baden-W\u00fcrttemberg",
    "wof:name":"B\u00e4ren",
    "wof:placetype":"venue"
},
  "geometry": {"coordinates":[7.703663826,48.1649360657],"type":"Point"}
}