{
  "type": "Feature",
  "properties": {
    "iso:country":"DE",
    "sg:address":"Konrad-St\u00fcrtzel-Str. 40",
    "sg:city":"March",
    "sg:phone":"+49 7665/95197",
    "sg:postcode":"79232",
    "sg:province":"Baden-W\u00fcrttemberg",
    "wof:name":"R. Tr\u00f6scher",
    "wof:placetype":"venue"
},
  "geometry": {"coordinates":[7.7807798386,48.0616493225],"type":"Point"}
}