{
  "type": "Feature",
  "properties": {
    "iso:country":"DE",
    "sg:address":"Hohe Str. 5",
    "sg:city":"Titz",
    "sg:phone":"+49 2463/7329",
    "sg:postcode":"52445",
    "sg:province":"Nordrhein-Westfalen",
    "wof:name":"Pizzeria Pinocchio",
    "wof:placetype":"venue"
},
  "geometry": {"coordinates":[6.4629378319,50.9620094299],"type":"Point"}
}