{
  "type": "Feature",
  "properties": {
    "iso:country":"DE",
    "sg:address":"Amselweg 39 a",
    "sg:city":"Schifferstadt",
    "sg:phone":"+49 6235/920003",
    "sg:postcode":"67105",
    "sg:province":"Rheinland-Pfalz",
    "wof:name":"Willi Knutas Masseur",
    "wof:placetype":"venue"
},
  "geometry": {"coordinates":[8.383345,49.37574],"type":"Point"}
}