{
  "type": "Feature",
  "properties": {
    "iso:country":"DE",
    "sg:address":"Goeckestr. 32-34",
    "sg:city":"Berlin",
    "sg:phone":"+49 30/97981920",
    "sg:postcode":"13055",
    "sg:province":"Berlin",
    "wof:name":"Problech Gmbh",
    "wof:placetype":"venue"
},
  "geometry": {"coordinates":[13.493437,52.539406],"type":"Point"}
}