{
  "type": "Feature",
  "properties": {
    "iso:country":"DE",
    "sg:address":"Thalmassinger Str. 4",
    "sg:city":"Alteglofsheim",
    "sg:phone":"+49 9453/446",
    "sg:postcode":"93087",
    "sg:province":"Bayern",
    "wof:name":"Albert Schmidbauer",
    "wof:placetype":"venue"
},
  "geometry": {"coordinates":[12.201762,48.920277],"type":"Point"}
}