{
  "type": "Feature",
  "properties": {
    "iso:country":"DE",
    "sg:address":"Luttinger Str. 17",
    "sg:city":"Laufenburg",
    "sg:phone":"+49 7763/7837",
    "sg:postcode":"79725",
    "sg:province":"Baden-W\u00fcrttemberg",
    "wof:name":"Robert Lauber",
    "wof:placetype":"venue"
},
  "geometry": {"coordinates":[8.0995845795,47.5734214783],"type":"Point"}
}