{
  "type": "Feature",
  "properties": {
    "iso:country":"DE",
    "sg:address":"Augsburger Str 78",
    "sg:city":"Memmingen",
    "sg:phone":"+49 7053/1413",
    "sg:postcode":"87700",
    "sg:province":"Bayern",
    "wof:name":"Sidug Dreh- Und Fr\u00e4steilfertigung Gmbh & Co Kg",
    "wof:placetype":"venue"
},
  "geometry": {"coordinates":[8.6662836075,48.7118530273],"type":"Point"}
}