{
  "type": "Feature",
  "properties": {
    "iso:country":"DE",
    "sg:address":"B\u00fcscheck 4",
    "sg:city":"B\u00f6singen",
    "sg:phone":"+49 7404/9142005",
    "sg:postcode":"78662",
    "sg:province":"Baden-W\u00fcrttemberg",
    "wof:name":"Darlehen, Finanzierung Und Baufinanzierung Schnell",
    "wof:placetype":"venue"
},
  "geometry": {"coordinates":[8.583708,48.226471],"type":"Point"}
}