{
  "type": "Feature",
  "properties": {
    "iso:country":"DE",
    "sg:address":"Sandhagen 14",
    "sg:city":"Bielefeld",
    "sg:phone":"+49 4952/1152667",
    "sg:postcode":"33617",
    "sg:province":"Nordrhein-Westfalen",
    "wof:name":"Lachs-r\u00c4ucherei Schmitz Gmbh",
    "wof:placetype":"venue"
},
  "geometry": {"coordinates":[8.5154466629,52.0084381104],"type":"Point"}
}