{
  "type": "Feature",
  "properties": {
    "iso:country":"DE",
    "sg:address":"Eisborner Dorfstr. 8",
    "sg:city":"Balve",
    "sg:phone":"+49 2379/9150",
    "sg:postcode":"58802",
    "sg:province":"Nordrhein-Westfalen",
    "wof:name":"Hotel Antoniush\u00fctte Eisborn Hermann Spiekermann",
    "wof:placetype":"venue"
},
  "geometry": {"coordinates":[7.8838529587,51.3859138489],"type":"Point"}
}