{
  "type": "Feature",
  "properties": {
    "iso:country":"DE",
    "sg:address":"Westerndorfer Str. 3 a",
    "sg:city":"Perach",
    "sg:phone":"+49 8670/1745",
    "sg:postcode":"84567",
    "sg:province":"Bayern",
    "wof:name":"Ritter Gmbh",
    "wof:placetype":"venue"
},
  "geometry": {"coordinates":[12.763816,48.265327],"type":"Point"}
}