{
  "type": "Feature",
  "properties": {
    "iso:country":"DE",
    "sg:address":"Engelbert-Zimmermann-Str. 41",
    "sg:city":"Swisttal",
    "sg:phone":"+49 2255/6993",
    "sg:postcode":"53913",
    "sg:province":"Nordrhein-Westfalen",
    "wof:name":"Karl-hermann Bulling Heilpraktiker",
    "wof:placetype":"venue"
},
  "geometry": {"coordinates":[6.8767848015,50.6510047913],"type":"Point"}
}