{
  "type": "Feature",
  "properties": {
    "iso:country":"DE",
    "sg:address":"Willdenowstr. 44",
    "sg:city":"Berlin",
    "sg:phone":"+49 30/84107500",
    "sg:postcode":"12203",
    "sg:province":"Berlin",
    "wof:name":"Forum Werbeges. Mbh & Co. Kg",
    "wof:placetype":"venue"
},
  "geometry": {"coordinates":[13.2997865677,52.4541244507],"type":"Point"}
}