{
  "type": "Feature",
  "properties": {
    "iso:country":"DE",
    "sg:address":"Stuttgarter Str. 22-1",
    "sg:city":"Lauffen",
    "sg:phone":"+49 7133/7886",
    "sg:postcode":"74348",
    "sg:province":"Baden-W\u00fcrttemberg",
    "wof:name":"Ursula Hufnagel",
    "wof:placetype":"venue"
},
  "geometry": {"coordinates":[9.154958,49.074238],"type":"Point"}
}