{
  "type": "Feature",
  "properties": {
    "iso:country":"DE",
    "sg:address":"Otto-Hahn-Str. 39",
    "sg:city":"Dreieich",
    "sg:phone":"+49 6103/388228",
    "sg:postcode":"63303",
    "sg:province":"Hessen",
    "wof:name":"Replikate Aus Der R\u00f6mischen Welt !",
    "wof:placetype":"venue"
},
  "geometry": {"coordinates":[8.708632,50.027092],"type":"Point"}
}