{
  "type": "Feature",
  "properties": {
    "iso:country":"DE",
    "sg:address":"Zeppelinstr. 3",
    "sg:city":"Magstadt",
    "sg:postcode":"71106",
    "sg:province":"Baden-W\u00fcrttemberg",
    "wof:name":"Adolf Schween Baubeschl\u00e4ge Und Bauzu-",
    "wof:placetype":"venue"
},
  "geometry": {"coordinates":[8.967997,48.737026],"type":"Point"}
}