{
  "type": "Feature",
  "properties": {
    "iso:country":"DE",
    "sg:address":"K\u00f6nigsberger Str. 7",
    "sg:city":"B\u00f6blingen",
    "sg:postcode":"71034",
    "sg:province":"Baden-W\u00fcrttemberg",
    "wof:name":"Argo Reisen Gmbh",
    "wof:placetype":"venue"
},
  "geometry": {"coordinates":[9.0037746429,48.6824378967],"type":"Point"}
}