{
  "type": "Feature",
  "properties": {
    "iso:country":"DE",
    "sg:address":"Bergmannstr. 6",
    "sg:city":"Dresden",
    "sg:phone":"+49 351/3101922",
    "sg:postcode":"01309",
    "sg:province":"Sachsen",
    "wof:name":"Rosemarie Mittag",
    "wof:placetype":"venue"
},
  "geometry": {"coordinates":[13.792548,51.04808],"type":"Point"}
}