{
  "type": "Feature",
  "properties": {
    "iso:country":"DE",
    "sg:address":"Zeithainer Str. 26",
    "sg:city":"Dresden",
    "sg:phone":"+49 351/8499018",
    "sg:postcode":"01127",
    "sg:province":"Sachsen",
    "wof:name":"Alfred Zimmer",
    "wof:placetype":"venue"
},
  "geometry": {"coordinates":[13.732044,51.082081],"type":"Point"}
}