{
  "type": "Feature",
  "properties": {
    "iso:country":"DE",
    "sg:address":"Oberstr. 26",
    "sg:city":"Ludwigshafen",
    "sg:phone":"+49 621/573478",
    "sg:postcode":"67065",
    "sg:province":"Rheinland-Pfalz",
    "wof:name":"Peter Behrens",
    "wof:placetype":"venue"
},
  "geometry": {"coordinates":[8.4270143509,49.4632072449],"type":"Point"}
}