{
  "type": "Feature",
  "properties": {
    "iso:country":"DE",
    "sg:address":"Anhauser Str. 7",
    "sg:city":"Herbrechtingen",
    "sg:phone":"+49 7324/96040",
    "sg:postcode":"89542",
    "sg:province":"Baden-W\u00fcrttemberg",
    "wof:name":"Carl Stahl Gmbh",
    "wof:placetype":"venue"
},
  "geometry": {"coordinates":[10.167779,48.624741],"type":"Point"}
}