{
  "type": "Feature",
  "properties": {
    "iso:country":"DE",
    "sg:address":"Tempelhof 1",
    "sg:city":"Nierstein",
    "sg:postcode":"55283",
    "sg:province":"Rheinland-Pfalz",
    "wof:name":"Evangelisches Dekanat Oppenheim",
    "wof:placetype":"venue"
},
  "geometry": {"coordinates":[8.3362131119,49.8746261597],"type":"Point"}
}