{
  "type": "Feature",
  "properties": {
    "iso:country":"DE",
    "sg:address":"Rasenweg",
    "sg:city":"Gro\u00dfengottern",
    "sg:phone":"+49 36022/90019",
    "sg:postcode":"99991",
    "sg:province":"Th\u00fcringen",
    "wof:name":"Elsygro Elektrosysteme Gmbh",
    "wof:placetype":"venue"
},
  "geometry": {"coordinates":[10.5634098053,51.1406860352],"type":"Point"}
}