{
  "type": "Feature",
  "properties": {
    "iso:country":"DE",
    "sg:address":"Gassen\u00e4cker 16",
    "sg:city":"Staig",
    "sg:phone":"+49 7346/96650",
    "sg:postcode":"89195",
    "sg:province":"Baden-W\u00fcrttemberg",
    "wof:name":"Alraun",
    "wof:placetype":"venue"
},
  "geometry": {"coordinates":[10.0099315643,48.2995910645],"type":"Point"}
}