{
  "type": "Feature",
  "properties": {
    "iso:country":"DE",
    "sg:address":"Immermannstr. 10",
    "sg:city":"D\u00fcsseldorf",
    "sg:phone":"+49 211/359681",
    "sg:postcode":"40210",
    "sg:province":"Nordrhein-Westfalen",
    "wof:name":"Immermann - Apotheke Friedhelm Blankenberg E. Kfm.",
    "wof:placetype":"venue"
},
  "geometry": {"coordinates":[6.785864,51.225014],"type":"Point"}
}