{
  "type": "Feature",
  "properties": {
    "iso:country":"DE",
    "sg:address":"Zittauer Str 26",
    "sg:city":"Sohland",
    "sg:phone":"+49 35936/32231",
    "sg:postcode":"02689",
    "sg:province":"Sachsen",
    "wof:name":"Spedition Dieter Zosel",
    "wof:placetype":"venue"
},
  "geometry": {"coordinates":[14.4438934326,51.0546379089],"type":"Point"}
}