{
  "type": "Feature",
  "properties": {
    "iso:country":"DE",
    "sg:address":"Auf der Wurth",
    "sg:city":"Butjadingen",
    "sg:phone":"+49 4733/717",
    "sg:postcode":"26969",
    "sg:province":"Niedersachsen",
    "wof:name":"Zum Rauchfang",
    "wof:placetype":"venue"
},
  "geometry": {"coordinates":[8.3776102066,53.5626716614],"type":"Point"}
}