{
  "type": "Feature",
  "properties": {
    "iso:country":"DE",
    "sg:address":"Im Unterdorf 16",
    "sg:city":"Zusmarshausen",
    "sg:phone":"+49 8291/9206",
    "sg:postcode":"86441",
    "sg:province":"Bayern",
    "wof:name":"Anton Fritz",
    "wof:placetype":"venue"
},
  "geometry": {"coordinates":[10.5699272156,48.3835411072],"type":"Point"}
}