{
  "type": "Feature",
  "properties": {
    "iso:country":"DE",
    "sg:address":"Sudelfeldstr. 20",
    "sg:city":"Brannenburg",
    "sg:phone":"+49 8034/90670",
    "sg:postcode":"83098",
    "sg:province":"Bayern",
    "wof:name":"Hotel-gasthof-cafe Zur Post",
    "wof:placetype":"venue"
},
  "geometry": {"coordinates":[12.1055631638,47.7339134216],"type":"Point"}
}