{
  "type": "Feature",
  "properties": {
    "iso:country":"DE",
    "sg:address":"Roteb\u00fchlstr. 81",
    "sg:city":"Stuttgart",
    "sg:phone":"+49 4971/1619790",
    "sg:postcode":"70178",
    "sg:province":"Baden-W\u00fcrttemberg",
    "wof:name":"Aktivbank Ag",
    "wof:placetype":"venue"
},
  "geometry": {"coordinates":[9.165053,48.772263],"type":"Point"}
}