{
  "type": "Feature",
  "properties": {
    "iso:country":"DE",
    "sg:address":"Pfaffendorfer Str. 18",
    "sg:city":"Leipzig",
    "sg:phone":"+49 341/982530",
    "sg:postcode":"04105",
    "sg:province":"Sachsen",
    "wof:name":"Dr. Schebitz Und Partner Rechtsanw\u00e4lte",
    "wof:placetype":"venue"
},
  "geometry": {"coordinates":[12.3714532852,51.3467979431],"type":"Point"}
}