{
  "type": "Feature",
  "properties": {
    "iso:country":"DE",
    "sg:address":"Heinrich-Heine-Str. 70",
    "sg:city":"Krauschwitz",
    "sg:postcode":"02957",
    "sg:province":"Sachsen",
    "wof:name":"Renta Control Union Verm\u00f6gensverwaltung Gmbh",
    "wof:placetype":"venue"
},
  "geometry": {"coordinates":[14.7216100693,51.514629364],"type":"Point"}
}