{
  "type": "Feature",
  "properties": {
    "iso:country":"DE",
    "sg:address":"Karlsruher Str. 2",
    "sg:city":"Karlsruhe",
    "sg:phone":"+49 721/681749",
    "sg:postcode":"76139",
    "sg:province":"Baden-W\u00fcrttemberg",
    "wof:name":"Comics",
    "wof:placetype":"venue"
},
  "geometry": {"coordinates":[8.4580745697,49.0306129456],"type":"Point"}
}