{
  "type": "Feature",
  "properties": {
    "iso:country":"DE",
    "sg:address":"Leonberger Str.",
    "sg:city":"Leonberg",
    "sg:phone":"+49 7152/73533",
    "sg:postcode":"71229",
    "sg:province":"Baden-W\u00fcrttemberg",
    "wof:name":"Tr\u00f6lsch",
    "wof:placetype":"venue"
},
  "geometry": {"coordinates":[9.024991,48.774807],"type":"Point"}
}