{
  "type": "Feature",
  "properties": {
    "iso:country":"DE",
    "sg:address":"Karlstr. 22",
    "sg:city":"Gaildorf",
    "sg:phone":"+49 7971/6368",
    "sg:postcode":"74405",
    "sg:province":"Baden-W\u00fcrttemberg",
    "wof:name":"F. W. Seeger",
    "wof:placetype":"venue"
},
  "geometry": {"coordinates":[9.7704029083,48.9995040894],"type":"Point"}
}