{
  "type": "Feature",
  "properties": {
    "iso:country":"DE",
    "sg:address":"Lengenfelder Str. 25",
    "sg:city":"Zwickau",
    "sg:phone":"+49 375/785249",
    "sg:postcode":"08064",
    "sg:province":"Sachsen",
    "wof:name":"Johannes Weber",
    "wof:placetype":"venue"
},
  "geometry": {"coordinates":[12.4784507751,50.678981781],"type":"Point"}
}