{
  "type": "Feature",
  "properties": {
    "iso:country":"DE",
    "sg:address":"Kolmberger Str. 3",
    "sg:city":"Blaibach",
    "sg:phone":"+49 9941/90100",
    "sg:postcode":"93476",
    "sg:province":"Bayern",
    "wof:name":"D. Raab",
    "wof:placetype":"venue"
},
  "geometry": {"coordinates":[12.8066730499,49.1691017151],"type":"Point"}
}