{
  "type": "Feature",
  "properties": {
    "iso:country":"DE",
    "sg:address":"Mainzer Str. 2 a",
    "sg:city":"Bad Kreuznach",
    "sg:phone":"+49 671/886080",
    "sg:postcode":"55545",
    "sg:province":"Rheinland-Pfalz",
    "wof:name":"Bauhaus Gmbh & Co. Kg",
    "wof:placetype":"venue"
},
  "geometry": {"coordinates":[7.8949189186,49.8563232422],"type":"Point"}
}