{
  "type": "Feature",
  "properties": {
    "iso:country":"DE",
    "sg:address":"Beethovenstr. 2",
    "sg:city":"Limeshain",
    "sg:phone":"+49 6047/4252",
    "sg:postcode":"63694",
    "sg:province":"Hessen",
    "wof:name":"Monika H\u00fctter",
    "wof:placetype":"venue"
},
  "geometry": {"coordinates":[8.972802,50.258316],"type":"Point"}
}