{
  "type": "Feature",
  "properties": {
    "iso:country":"DE",
    "sg:address":"Unter den Buchen 31",
    "sg:city":"Wegberg",
    "sg:postcode":"41844",
    "sg:province":"Nordrhein-Westfalen",
    "wof:name":"Randerath Gmbh",
    "wof:placetype":"venue"
},
  "geometry": {"coordinates":[6.18027,51.145199],"type":"Point"}
}