{
  "type": "Feature",
  "properties": {
    "iso:country":"DE",
    "sg:address":"L\u00fctzelwiesenstr. 23",
    "sg:city":"Sindelfingen",
    "sg:phone":"+49 7031/801899",
    "sg:postcode":"71063",
    "sg:province":"Baden-W\u00fcrttemberg",
    "wof:name":"Willi Wolf",
    "wof:placetype":"venue"
},
  "geometry": {"coordinates":[8.996685,48.712227],"type":"Point"}
}