{
  "type": "Feature",
  "properties": {
    "iso:country":"DE",
    "sg:address":"Kapellenweg 19",
    "sg:city":"Rottenburg",
    "sg:phone":"+49 7472/21279",
    "sg:postcode":"72108",
    "sg:province":"Baden-W\u00fcrttemberg",
    "wof:name":"Zur Wurmlinger Kapelle",
    "wof:placetype":"venue"
},
  "geometry": {"coordinates":[8.9713516235,48.5041007996],"type":"Point"}
}