{
  "type": "Feature",
  "properties": {
    "iso:country":"DE",
    "sg:address":"Liegnitzer Weg 6",
    "sg:city":"Moers",
    "sg:phone":"+49 2841/94524",
    "sg:postcode":"47445",
    "sg:province":"Nordrhein-Westfalen",
    "wof:name":"Heinrich Balicki Ingenieur",
    "wof:placetype":"venue"
},
  "geometry": {"coordinates":[6.6277179718,51.4788169861],"type":"Point"}
}