{
  "type": "Feature",
  "properties": {
    "iso:country":"DE",
    "sg:address":"Lange Str. 57",
    "sg:city":"Hann. M\u00fcnden",
    "sg:phone":"+49 5541/4056",
    "sg:postcode":"34346",
    "sg:province":"Niedersachsen",
    "wof:name":"Quentin Und Dix Rechtsanw\u00e4lte",
    "wof:placetype":"venue"
},
  "geometry": {"coordinates":[9.6518878937,51.4166641235],"type":"Point"}
}