{
  "type": "Feature",
  "properties": {
    "iso:country":"DE",
    "sg:address":"Gleibachweg 4",
    "sg:city":"Wettenberg",
    "sg:phone":"+49 641/82816",
    "sg:postcode":"35435",
    "sg:province":"Hessen",
    "wof:name":"Ursula M\u00fcller-langner",
    "wof:placetype":"venue"
},
  "geometry": {"coordinates":[8.642769,50.617184],"type":"Point"}
}