{
  "type": "Feature",
  "properties": {
    "iso:country":"DE",
    "sg:address":"Soinweg 36 A",
    "sg:city":"Flintsbach",
    "sg:phone":"+49 8034/2231",
    "sg:postcode":"83126",
    "sg:province":"Bayern",
    "wof:name":"G\u00f6tsch Und Burk Gmbh",
    "wof:placetype":"venue"
},
  "geometry": {"coordinates":[12.1212749481,47.7232627869],"type":"Point"}
}