{
  "type": "Feature",
  "properties": {
    "iso:country":"DE",
    "sg:address":"Marktplatz 2",
    "sg:city":"H\u00f6chst\u00e4dt",
    "sg:phone":"+49 9074/3140",
    "sg:postcode":"89420",
    "sg:province":"Bayern",
    "wof:name":"Cafe Verdi",
    "wof:placetype":"venue"
},
  "geometry": {"coordinates":[10.565076,48.610847],"type":"Point"}
}