{
  "type": "Feature",
  "properties": {
    "iso:country":"DE",
    "sg:address":"Schieringstr. 15",
    "sg:city":"Apolda",
    "sg:phone":"+49 3644/564097",
    "sg:postcode":"99510",
    "sg:province":"Th\u00fcringen",
    "wof:name":"F. Helfricht",
    "wof:placetype":"venue"
},
  "geometry": {"coordinates":[11.495105,51.019272],"type":"Point"}
}