{
  "type": "Feature",
  "properties": {
    "iso:country":"DE",
    "sg:address":"L\u00fcneburger Str. 20",
    "sg:city":"Bad Bevensen",
    "sg:phone":"+49 5821/1223",
    "sg:postcode":"29549",
    "sg:province":"Niedersachsen",
    "wof:name":"Foto-studio May Inh. Susanne May",
    "wof:placetype":"venue"
},
  "geometry": {"coordinates":[10.5773611069,53.0799942017],"type":"Point"}
}