{
  "type": "Feature",
  "properties": {
    "iso:country":"DE",
    "sg:address":"Am Hofeberg 32",
    "sg:city":"Liegau-Augustusbad",
    "sg:postcode":"01465",
    "sg:province":"Sachsen",
    "wof:name":"Claus Synatschke Fliesen- Legermeister E. K.",
    "wof:placetype":"venue"
},
  "geometry": {"coordinates":[13.8915576935,51.1387901306],"type":"Point"}
}