{
  "type": "Feature",
  "properties": {
    "iso:country":"DE",
    "sg:address":"Velberter Str. 6",
    "sg:city":"D\u00fcsseldorf",
    "sg:phone":"+49 4921/1977810",
    "sg:postcode":"40227",
    "sg:province":"Nordrhein-Westfalen",
    "wof:name":"Schaab & Co Gmbh",
    "wof:placetype":"venue"
},
  "geometry": {"coordinates":[6.801112175,51.217754364],"type":"Point"}
}