{
  "type": "Feature",
  "properties": {
    "iso:country":"DE",
    "sg:address":"Breslauer Str. 8",
    "sg:city":"Neuss",
    "sg:phone":"+49 2131/71830",
    "sg:postcode":"41460",
    "sg:province":"Nordrhein-Westfalen",
    "wof:name":"Jeans-palast Schmidt & G\u00f6rgens Vertriebs- Gmbh & Co. Kg",
    "wof:placetype":"venue"
},
  "geometry": {"coordinates":[6.72049,51.200569],"type":"Point"}
}