{
  "type": "Feature",
  "properties": {
    "iso:country":"DE",
    "sg:address":"Eduard-Pfeiffer-Str. 31",
    "sg:city":"Stuttgart",
    "sg:phone":"+49 711/222255",
    "sg:postcode":"70192",
    "sg:province":"Baden-W\u00fcrttemberg",
    "wof:name":"Bucerius Sperling Grundbesitz Gmbh",
    "wof:placetype":"venue"
},
  "geometry": {"coordinates":[9.166136,48.788998],"type":"Point"}
}