{
  "type": "Feature",
  "properties": {
    "iso:country":"DE",
    "sg:address":"Thyssenstr. 1",
    "sg:city":"Gersthofen",
    "sg:postcode":"86368",
    "sg:province":"Bayern",
    "wof:name":"Rosenblatt E. K.",
    "wof:placetype":"venue"
},
  "geometry": {"coordinates":[10.875852,48.429882],"type":"Point"}
}