{
  "type": "Feature",
  "properties": {
    "iso:country":"DE",
    "sg:address":"H\u00e4ndelallee 22",
    "sg:city":"Berlin",
    "sg:phone":"+49 30/3911301",
    "sg:postcode":"10557",
    "sg:province":"Berlin",
    "wof:name":"Ev. Pfarramt Kaiser-friedrich-ged\u00e4chtnis",
    "wof:placetype":"venue"
},
  "geometry": {"coordinates":[13.342209816,52.5154914856],"type":"Point"}
}