{
  "type": "Feature",
  "properties": {
    "iso:country":"DE",
    "sg:address":"Hauptstr. 93",
    "sg:city":"Oyten",
    "sg:phone":"+49 4207/4090",
    "sg:postcode":"28876",
    "sg:province":"Niedersachsen",
    "wof:name":"B. Stelljes",
    "wof:placetype":"venue"
},
  "geometry": {"coordinates":[9.014321,53.059395],"type":"Point"}
}