{
  "type": "Feature",
  "properties": {
    "iso:country":"DE",
    "sg:address":"An der R\u00f6ten 21",
    "sg:city":"Wachenroth",
    "sg:phone":"+49 9548/6240",
    "sg:postcode":"96193",
    "sg:province":"Bayern",
    "wof:name":"S. Weber Immobilienmakler",
    "wof:placetype":"venue"
},
  "geometry": {"coordinates":[10.7151794434,49.7539367676],"type":"Point"}
}