{
  "type": "Feature",
  "properties": {
    "iso:country":"DE",
    "sg:address":"Berliner Str. 76",
    "sg:city":"Halle",
    "sg:phone":"+49 345/5230867",
    "sg:postcode":"06116",
    "sg:province":"Sachsen-Anhalt",
    "wof:name":"G. Boas",
    "wof:placetype":"venue"
},
  "geometry": {"coordinates":[12.013619,51.496822],"type":"Point"}
}