{
  "type": "Feature",
  "properties": {
    "iso:country":"DE",
    "sg:address":"Singener Str. 39",
    "sg:city":"Stei\u00dflingen",
    "sg:phone":"+49 7738/283",
    "sg:postcode":"78256",
    "sg:province":"Baden-W\u00fcrttemberg",
    "wof:name":"Gerhard Will",
    "wof:placetype":"venue"
},
  "geometry": {"coordinates":[8.921241,47.795734],"type":"Point"}
}