{
  "type": "Feature",
  "properties": {
    "iso:country":"DE",
    "sg:address":"Hauptstr. 7",
    "sg:city":"Sankt Wolfgang",
    "sg:postcode":"84427",
    "sg:province":"Bayern",
    "wof:name":"Privatbrauerei St. Wolfgang Gmbh",
    "wof:placetype":"venue"
},
  "geometry": {"coordinates":[12.135071,48.218719],"type":"Point"}
}