{
  "type": "Feature",
  "properties": {
    "iso:country":"DE",
    "sg:address":"Hindenburgstr. 57",
    "sg:city":"Essen",
    "sg:phone":"+49 201/232627",
    "sg:postcode":"45127",
    "sg:province":"Nordrhein-Westfalen",
    "wof:name":"Albatros Bergsport Wandern Trecking",
    "wof:placetype":"venue"
},
  "geometry": {"coordinates":[7.006433,51.455128],"type":"Point"}
}