{
  "type": "Feature",
  "properties": {
    "iso:country":"DE",
    "sg:address":"Dosestr",
    "sg:city":"Hamburg",
    "sg:phone":"+49 40",
    "sg:postcode":"22767",
    "sg:province":"Hamburg",
    "wof:name":"Wohnwagen-peter - Alles F\u00fcr Den Camper",
    "wof:placetype":"venue"
},
  "geometry": {"coordinates":[9.9523067474,53.5482597351],"type":"Point"}
}