{
  "type": "Feature",
  "properties": {
    "iso:country":"DE",
    "sg:address":"Goldbekplatz 2",
    "sg:city":"Hamburg",
    "sg:phone":"+49 40/2806533",
    "sg:postcode":"22303",
    "sg:province":"Hamburg",
    "wof:name":"Kah K\u00fcchen-atelier Gmbh",
    "wof:placetype":"venue"
},
  "geometry": {"coordinates":[10.0097227097,53.5839996338],"type":"Point"}
}