{
  "type": "Feature",
  "properties": {
    "iso:country":"DE",
    "sg:address":"Innere Plauensche Str. 29",
    "sg:city":"Zwickau",
    "sg:phone":"+49 375/292548",
    "sg:postcode":"08056",
    "sg:province":"Sachsen",
    "wof:name":"Matthias Croy Rechtsanwalt",
    "wof:placetype":"venue"
},
  "geometry": {"coordinates":[12.4907503128,50.7089691162],"type":"Point"}
}