{
  "type": "Feature",
  "properties": {
    "iso:country":"DE",
    "sg:address":"Anhaltiner Platz 27",
    "sg:city":"Sandersleben",
    "sg:phone":"+49 34785/20419",
    "sg:postcode":"06456",
    "sg:province":"Sachsen-Anhalt",
    "wof:name":"Karl Detto",
    "wof:placetype":"venue"
},
  "geometry": {"coordinates":[11.569782,51.674606],"type":"Point"}
}