{
  "type": "Feature",
  "properties": {
    "iso:country":"DE",
    "sg:address":"Gereonstr. 1",
    "sg:city":"J\u00fclich",
    "sg:phone":"+49 2461/55888",
    "sg:postcode":"52428",
    "sg:province":"Nordrhein-Westfalen",
    "wof:name":"L\u00f6venich",
    "wof:placetype":"venue"
},
  "geometry": {"coordinates":[6.3570342064,50.9090957642],"type":"Point"}
}