{
  "type": "Feature",
  "properties": {
    "iso:country":"DE",
    "sg:address":"Eisenacher Str. 53",
    "sg:city":"Berlin",
    "sg:phone":"+49 30/74683704",
    "sg:postcode":"10823",
    "sg:province":"Berlin",
    "wof:name":"Oriflame Natural Cosmetics Bei Ff Marketing",
    "wof:placetype":"venue"
},
  "geometry": {"coordinates":[13.350417,52.486496],"type":"Point"}
}