{
  "type": "Feature",
  "properties": {
    "iso:country":"DE",
    "sg:address":"Sigererstr. 3a",
    "sg:city":"M\u00fcnchen",
    "sg:phone":"+49 89/86308060",
    "sg:postcode":"81249",
    "sg:province":"Bayern",
    "wof:name":"C. Brait Immobilienmakler",
    "wof:placetype":"venue"
},
  "geometry": {"coordinates":[11.4099788666,48.1718025208],"type":"Point"}
}