{
  "type": "Feature",
  "properties": {
    "iso:country":"DE",
    "sg:address":"Zellerstr. 87",
    "sg:city":"Stuttgart",
    "sg:phone":"+49 711/6406341",
    "sg:postcode":"70180",
    "sg:province":"Baden-W\u00fcrttemberg",
    "wof:name":"Manfred Beck Architekt",
    "wof:placetype":"venue"
},
  "geometry": {"coordinates":[9.169876,48.762337],"type":"Point"}
}