{
  "type": "Feature",
  "properties": {
    "iso:country":"DE",
    "sg:address":"Friedenstr. 1",
    "sg:city":"Bielefeld",
    "sg:phone":"+49 4952/1177273",
    "sg:postcode":"33602",
    "sg:province":"Nordrhein-Westfalen",
    "wof:name":"Dsl Bank",
    "wof:placetype":"venue"
},
  "geometry": {"coordinates":[8.530393,52.023712],"type":"Point"}
}