{
  "type": "Feature",
  "properties": {
    "iso:country":"DE",
    "sg:address":"Kirchbergstr. 32",
    "sg:city":"Ranstadt",
    "sg:phone":"+49 6035/2440",
    "sg:postcode":"63691",
    "sg:province":"Hessen",
    "wof:name":"\u00c4stchen",
    "wof:placetype":"venue"
},
  "geometry": {"coordinates":[8.9586210251,50.36353302],"type":"Point"}
}