{
  "type": "Feature",
  "properties": {
    "iso:country":"DE",
    "sg:address":"Meisenburgstr. 29",
    "sg:city":"Essen",
    "sg:phone":"+49 201/412249",
    "sg:postcode":"45133",
    "sg:province":"Nordrhein-Westfalen",
    "wof:name":"Pla\u00dfmann Bedachungen Gmbh",
    "wof:placetype":"venue"
},
  "geometry": {"coordinates":[6.968882,51.409325],"type":"Point"}
}