{
  "type": "Feature",
  "properties": {
    "iso:country":"DE",
    "sg:address":"Westfalenstr. 15",
    "sg:city":"M\u00fcnster",
    "sg:phone":"+49 2501/7104",
    "sg:postcode":"48165",
    "sg:province":"Nordrhein-Westfalen",
    "wof:name":"Reiner Hoppe",
    "wof:placetype":"venue"
},
  "geometry": {"coordinates":[7.6325798035,51.9154586792],"type":"Point"}
}