{
  "type": "Feature",
  "properties": {
    "iso:country":"DE",
    "sg:address":"Saargem\u00fcnder Str. 85",
    "sg:city":"Saarbr\u00fccken",
    "sg:phone":"+49 681/9850253",
    "sg:postcode":"66119",
    "sg:province":"Saarland",
    "wof:name":"Plus Warenhandels- Gesellschaft Mbh & Co. Ohg",
    "wof:placetype":"venue"
},
  "geometry": {"coordinates":[7.0096969604,49.2200279236],"type":"Point"}
}