{
  "type": "Feature",
  "properties": {
    "iso:country":"DE",
    "sg:address":"Berliner Str. 116",
    "sg:city":"Wermelskirchen",
    "sg:phone":"+49 2196/1017",
    "sg:postcode":"42929",
    "sg:province":"Nordrhein-Westfalen",
    "wof:name":"Oyen Gmbh",
    "wof:placetype":"venue"
},
  "geometry": {"coordinates":[7.2290520668,51.144947052],"type":"Point"}
}