{
  "type": "Feature",
  "properties": {
    "iso:country":"DE",
    "sg:address":"Sandsteinweg 33",
    "sg:city":"Niedereschach",
    "sg:postcode":"78078",
    "sg:province":"Baden-W\u00fcrttemberg",
    "wof:name":"Deutsche Nephro Net Verwaltungs- Gmbh",
    "wof:placetype":"venue"
},
  "geometry": {"coordinates":[8.4935884476,48.1556739807],"type":"Point"}
}