{
  "type": "Feature",
  "properties": {
    "iso:country":"DE",
    "sg:address":"Am Freihof 2",
    "sg:city":"Ronnenberg",
    "sg:phone":"+49 5109/7365",
    "sg:postcode":"30952",
    "sg:province":"Niedersachsen",
    "wof:name":"Consolit- Consulting And Solutions For Information",
    "wof:placetype":"venue"
},
  "geometry": {"coordinates":[9.659485817,52.3149223328],"type":"Point"}
}