{
  "type": "Feature",
  "properties": {
    "iso:country":"DE",
    "sg:address":"Warener Str. 53 a",
    "sg:city":"Rostock",
    "sg:phone":"+49 381/7699678",
    "sg:postcode":"18109",
    "sg:province":"Mecklenburg-Vorpommern",
    "wof:name":"Gartengastst\u00e4tte Uns Goren",
    "wof:placetype":"venue"
},
  "geometry": {"coordinates":[12.0605192184,54.1592292786],"type":"Point"}
}