{
  "type": "Feature",
  "properties": {
    "iso:country":"DE",
    "sg:address":"Rupprechtstr. 1",
    "sg:city":"Altrip",
    "sg:phone":"+49 6236/3713",
    "sg:postcode":"67122",
    "sg:province":"Rheinland-Pfalz",
    "wof:name":"H. Weissenstein",
    "wof:placetype":"venue"
},
  "geometry": {"coordinates":[8.4981613159,49.4309577942],"type":"Point"}
}