{
  "type": "Feature",
  "properties": {
    "iso:country":"DE",
    "sg:address":"Rosengasse 1a",
    "sg:city":"Neumarkt",
    "sg:phone":"+49 9181/2473",
    "sg:postcode":"92318",
    "sg:province":"Bayern",
    "wof:name":"Dringer & Maag",
    "wof:placetype":"venue"
},
  "geometry": {"coordinates":[11.4599399567,49.2786140442],"type":"Point"}
}