{
  "type": "Feature",
  "properties": {
    "iso:country":"DE",
    "sg:address":"Stennweilerstr. 12-14",
    "sg:city":"Ottweiler",
    "sg:postcode":"66564",
    "sg:province":"Saarland",
    "wof:name":"Ams Topometrix Microscopy Center Gmbh",
    "wof:placetype":"venue"
},
  "geometry": {"coordinates":[7.1558327675,49.4016838074],"type":"Point"}
}