{
  "type": "Feature",
  "properties": {
    "iso:country":"DE",
    "sg:address":"In der Spitze 32",
    "sg:city":"G\u00f6ttingen",
    "sg:phone":"+49 551/93523",
    "sg:postcode":"37079",
    "sg:province":"Niedersachsen",
    "wof:name":"Junggesellenverein Gro\u00df Ellershausen Von 1833",
    "wof:placetype":"venue"
},
  "geometry": {"coordinates":[9.8642282486,51.5189628601],"type":"Point"}
}