{
  "type": "Feature",
  "properties": {
    "iso:country":"DE",
    "sg:address":"Ludwig-Jahn-Str. 1",
    "sg:city":"Hannover",
    "sg:phone":"+49 511/5865279",
    "sg:postcode":"30629",
    "sg:province":"Niedersachsen",
    "wof:name":"Misburger Bad",
    "wof:placetype":"venue"
},
  "geometry": {"coordinates":[9.8594646454,52.3928222656],"type":"Point"}
}