{
  "type": "Feature",
  "properties": {
    "iso:country":"DE",
    "sg:address":"Bemeroder Str. 63",
    "sg:city":"Hannover",
    "sg:phone":"+49 511/526200",
    "sg:postcode":"30559",
    "sg:province":"Niedersachsen",
    "wof:name":"Martinez Gastst\u00e4tten-betriebs- Gmbh",
    "wof:placetype":"venue"
},
  "geometry": {"coordinates":[9.80560112,52.3505172729],"type":"Point"}
}