{
  "type": "Feature",
  "properties": {
    "iso:country":"DE",
    "sg:address":"Neumeyerstr. 45",
    "sg:city":"N\u00fcrnberg",
    "sg:phone":"+49 911/5201099",
    "sg:postcode":"90411",
    "sg:province":"Bayern",
    "wof:name":"Kinderheim Stadtmission",
    "wof:placetype":"venue"
},
  "geometry": {"coordinates":[11.1237010956,49.4838943481],"type":"Point"}
}