{
  "type": "Feature",
  "properties": {
    "iso:country":"DE",
    "sg:address":"H\u00e4schenstr. 19",
    "sg:city":"Bremen",
    "sg:phone":"+49 421/505515",
    "sg:postcode":"28199",
    "sg:province":"Bremen",
    "wof:name":"Sport Und Freizeit Center",
    "wof:placetype":"venue"
},
  "geometry": {"coordinates":[8.7983407974,53.0752067566],"type":"Point"}
}