{
  "type": "Feature",
  "properties": {
    "iso:country":"DE",
    "sg:address":"Am Fischbahnhof 5",
    "sg:city":"Bremerhaven",
    "sg:phone":"+49 471/97380",
    "sg:postcode":"27572",
    "sg:province":"Bremen",
    "wof:name":"Benthin Ag",
    "wof:placetype":"venue"
},
  "geometry": {"coordinates":[8.5806045532,53.5217399597],"type":"Point"}
}