{
  "type": "Feature",
  "properties": {
    "iso:country":"DE",
    "sg:address":"Kettelerstr. 5",
    "sg:city":"Verl",
    "sg:phone":"+49 5246/2800",
    "sg:postcode":"33415",
    "sg:province":"Nordrhein-Westfalen",
    "wof:name":"Eva Dolenec-lammers",
    "wof:placetype":"venue"
},
  "geometry": {"coordinates":[8.5015497208,51.8822364807],"type":"Point"}
}