{
  "type": "Feature",
  "properties": {
    "iso:country":"DE",
    "sg:address":"Fabrikstr 1",
    "sg:city":"Nerchau",
    "sg:phone":"+49 3437/911231",
    "sg:postcode":"04685",
    "sg:province":"Sachsen",
    "wof:name":"Ludwig Braml-gmach Industrieanlagen Golzern Gmbh & Co Kg",
    "wof:placetype":"venue"
},
  "geometry": {"coordinates":[12.773182869,51.2474212646],"type":"Point"}
}