{
  "type": "Feature",
  "properties": {
    "iso:country":"DE",
    "sg:address":"Reichenstr. 19",
    "sg:city":"Itzehoe",
    "sg:phone":"+49 4821/5527",
    "sg:postcode":"25524",
    "sg:province":"Schleswig-Holstein",
    "wof:name":"Amadeus",
    "wof:placetype":"venue"
},
  "geometry": {"coordinates":[9.5159873962,53.9197273254],"type":"Point"}
}