{
  "type": "Feature",
  "properties": {
    "iso:country":"DE",
    "sg:address":"Schreberstr. 7",
    "sg:city":"G\u00fcnzburg",
    "sg:phone":"+49 8221/990",
    "sg:postcode":"89312",
    "sg:province":"Bayern",
    "wof:name":"Ihle- Reifen Gmbh",
    "wof:placetype":"venue"
},
  "geometry": {"coordinates":[10.2630767822,48.4516601562],"type":"Point"}
}