{
  "type": "Feature",
  "properties": {
    "iso:country":"DE",
    "sg:address":"Simpertstr. 9",
    "sg:city":"Meitingen",
    "sg:phone":"+49 8271/5571",
    "sg:postcode":"86405",
    "sg:province":"Bayern",
    "wof:name":"Heinz Schinko Architekt",
    "wof:placetype":"venue"
},
  "geometry": {"coordinates":[10.857911,48.526527],"type":"Point"}
}