{
  "type": "Feature",
  "properties": {
    "iso:country":"DE",
    "sg:address":"Herrlohweg 10",
    "sg:city":"Winterberg",
    "sg:phone":"+49 2981/820470",
    "sg:postcode":"59955",
    "sg:province":"Nordrhein-Westfalen",
    "wof:name":"Service-wohnanlagen Lindenhof Betriebs Gmbh",
    "wof:placetype":"venue"
},
  "geometry": {"coordinates":[8.520373,51.192898],"type":"Point"}
}