{
  "type": "Feature",
  "properties": {
    "iso:country":"DE",
    "sg:address":"S 6 19",
    "sg:city":"Mannheim",
    "sg:phone":"+49 621/13557",
    "sg:postcode":"68161",
    "sg:province":"Baden-W\u00fcrttemberg",
    "wof:name":"Ilona Mariconda",
    "wof:placetype":"venue"
},
  "geometry": {"coordinates":[8.466785,49.486511],"type":"Point"}
}