{
  "type": "Feature",
  "properties": {
    "iso:country":"DE",
    "sg:address":"Kleinknechtstr. 37",
    "sg:city":"Stuttgart",
    "sg:postcode":"70567",
    "sg:province":"Baden-W\u00fcrttemberg",
    "wof:name":"S & S Immobilien Grundst\u00fccks- Und Baube-",
    "wof:placetype":"venue"
},
  "geometry": {"coordinates":[9.151668,48.72707],"type":"Point"}
}