{
  "type": "Feature",
  "properties": {
    "iso:country":"DE",
    "sg:address":"Breite Str. 37",
    "sg:city":"Wildberg",
    "sg:phone":"+49 7054/7420",
    "sg:postcode":"72218",
    "sg:province":"Baden-W\u00fcrttemberg",
    "wof:name":"Rudi Moock",
    "wof:placetype":"venue"
},
  "geometry": {"coordinates":[8.7672758102,48.649597168],"type":"Point"}
}