{
  "type": "Feature",
  "properties": {
    "iso:country":"DE",
    "sg:address":"Eupener Str. 6",
    "sg:city":"Bremen",
    "sg:phone":"+49 421/235073",
    "sg:postcode":"28213",
    "sg:province":"Bremen",
    "wof:name":"Heinz Pahl",
    "wof:placetype":"venue"
},
  "geometry": {"coordinates":[8.8582639694,53.0895500183],"type":"Point"}
}