{
  "type": "Feature",
  "properties": {
    "iso:country":"DE",
    "sg:address":"Breslauerstr.2",
    "sg:city":"Mettenheim",
    "sg:phone":"+49 1903320332",
    "sg:postcode":"67582",
    "sg:province":"Rheinland-Pfalz",
    "wof:name":"Die Kleine Welt",
    "wof:placetype":"venue"
},
  "geometry": {"coordinates":[8.331528,49.741585],"type":"Point"}
}