{
  "type": "Feature",
  "properties": {
    "iso:country":"DE",
    "sg:address":"Steenekamp 39",
    "sg:city":"Borken",
    "sg:phone":"+49 2862/2621",
    "sg:postcode":"46325",
    "sg:province":"Nordrhein-Westfalen",
    "wof:name":"Johann Olbing",
    "wof:placetype":"venue"
},
  "geometry": {"coordinates":[6.770968,51.892876],"type":"Point"}
}