{
  "type": "Feature",
  "properties": {
    "iso:country":"DE",
    "sg:address":"Landaustr. 11",
    "sg:city":"Kassel",
    "sg:phone":"+49 561/21640",
    "sg:postcode":"34121",
    "sg:province":"Hessen",
    "wof:name":"Hans Dach",
    "wof:placetype":"venue"
},
  "geometry": {"coordinates":[9.487295,51.305164],"type":"Point"}
}