{
  "type": "Feature",
  "properties": {
    "iso:country":"DE",
    "sg:address":"Engelmannweg 9",
    "sg:city":"Berlin",
    "sg:phone":"+49 30/4135012",
    "sg:postcode":"13403",
    "sg:province":"Berlin",
    "wof:name":"Holz, Holz, Rundholz,fichte,laerche,kiefer,schnitt",
    "wof:placetype":"venue"
},
  "geometry": {"coordinates":[13.319017,52.568169],"type":"Point"}
}