{
  "type": "Feature",
  "properties": {
    "iso:country":"DE",
    "sg:address":"T\u00f6pferstr. 22",
    "sg:city":"Mirow",
    "sg:phone":"+49 39833/20589",
    "sg:postcode":"17252",
    "sg:province":"Mecklenburg-Vorpommern",
    "wof:name":"Ch. Wellert Masseur",
    "wof:placetype":"venue"
},
  "geometry": {"coordinates":[12.81486,53.273266],"type":"Point"}
}