{
  "type": "Feature",
  "properties": {
    "iso:country":"DE",
    "sg:address":"Bahnhofstr. 4",
    "sg:city":"Bietigheim-Bissingen",
    "sg:phone":"+49 7142/920013",
    "sg:postcode":"74321",
    "sg:province":"Baden-W\u00fcrttemberg",
    "wof:name":"Enz-apotheke",
    "wof:placetype":"venue"
},
  "geometry": {"coordinates":[9.100314,48.947056],"type":"Point"}
}