{
  "type": "Feature",
  "properties": {
    "iso:country":"DE",
    "sg:address":"Scheffelstr.12",
    "sg:city":"Eppelheim",
    "sg:phone":"+49 6221/758066",
    "sg:postcode":"69214",
    "sg:province":"Baden-W\u00fcrttemberg",
    "wof:name":"Ok4all",
    "wof:placetype":"venue"
},
  "geometry": {"coordinates":[8.630506,49.40012],"type":"Point"}
}