{
  "type": "Feature",
  "properties": {
    "iso:country":"DE",
    "sg:address":"Sternwartenstra\u00dfe 4",
    "sg:city":"Leipzig",
    "sg:phone":"+49 341/2577307",
    "sg:postcode":"04103",
    "sg:province":"Sachsen",
    "wof:name":"Reininsleben - Www.bkj.de/reininsleben",
    "wof:placetype":"venue"
},
  "geometry": {"coordinates":[12.380014,51.334965],"type":"Point"}
}