{
  "type": "Feature",
  "properties": {
    "iso:country":"DE",
    "sg:address":"Ludwigstr. 21",
    "sg:city":"Landau",
    "sg:phone":"+49 9951/1632",
    "sg:postcode":"94405",
    "sg:province":"Bayern",
    "wof:name":"Restaurant Taverna Meteora",
    "wof:placetype":"venue"
},
  "geometry": {"coordinates":[12.6915225983,48.6706848145],"type":"Point"}
}