{
  "type": "Feature",
  "properties": {
    "iso:country":"DE",
    "sg:address":"W\u00e4chterhofstr. 1 a",
    "sg:city":"H\u00f6henkirchen-Siegertbrn",
    "sg:phone":"+49 8102/71756",
    "sg:postcode":"85635",
    "sg:province":"Bayern",
    "wof:name":"Helmut Jenak Architekt",
    "wof:placetype":"venue"
},
  "geometry": {"coordinates":[11.710087,48.020042],"type":"Point"}
}