{
  "type": "Feature",
  "properties": {
    "iso:country":"DE",
    "sg:address":"Gaselbogen 6",
    "sg:city":"Rellingen",
    "sg:phone":"+49 4101/22217",
    "sg:postcode":"25462",
    "sg:province":"Schleswig-Holstein",
    "wof:name":"Ms Mijo Armin Klingenberg Schiffahrts Kg",
    "wof:placetype":"venue"
},
  "geometry": {"coordinates":[9.842824,53.658638],"type":"Point"}
}