{
  "type": "Feature",
  "properties": {
    "iso:country":"DE",
    "sg:address":"Olpener Str. 913",
    "sg:city":"K\u00f6ln",
    "sg:phone":"+49 221/841352",
    "sg:postcode":"51109",
    "sg:province":"Nordrhein-Westfalen",
    "wof:name":"Toni Meyers",
    "wof:placetype":"venue"
},
  "geometry": {"coordinates":[7.082447,50.946583],"type":"Point"}
}