{
  "type": "Feature",
  "properties": {
    "iso:country":"DE",
    "sg:address":"Danziger Weg 10",
    "sg:city":"L\u00fcdenscheid",
    "sg:phone":"+49 2351/81469",
    "sg:postcode":"58511",
    "sg:province":"Nordrhein-Westfalen",
    "wof:name":"Danziger Krug",
    "wof:placetype":"venue"
},
  "geometry": {"coordinates":[7.6471939087,51.2157325745],"type":"Point"}
}