{
  "type": "Feature",
  "properties": {
    "iso:country":"DE",
    "sg:address":"Hauptkanal Rechts 75",
    "sg:city":"Papenburg",
    "sg:phone":"+49 4961/930",
    "sg:postcode":"26871",
    "sg:province":"Niedersachsen",
    "wof:name":"Stiftung Marienhospital",
    "wof:placetype":"venue"
},
  "geometry": {"coordinates":[7.3968701363,53.0774154663],"type":"Point"}
}