{
  "type": "Feature",
  "properties": {
    "iso:country":"DE",
    "sg:address":"Marktgasse 3",
    "sg:city":"Eichst\u00e4tt",
    "sg:phone":"+49 8421/5252",
    "sg:postcode":"85072",
    "sg:province":"Bayern",
    "wof:name":"Dr. Med. Dieter Wohlgemuth Arzt F\u00fcr Allgemeinmedizin",
    "wof:placetype":"venue"
},
  "geometry": {"coordinates":[11.1845550537,48.8932571411],"type":"Point"}
}