{
  "type": "Feature",
  "properties": {
    "iso:country":"DE",
    "sg:address":"Stapenhorststr. 91",
    "sg:city":"Bielefeld",
    "sg:postcode":"33615",
    "sg:province":"Nordrhein-Westfalen",
    "wof:name":"Harras-wolff Grundst\u00fccks- Verwaltung Gmbh & Co. Kg",
    "wof:placetype":"venue"
},
  "geometry": {"coordinates":[8.5174150467,52.0279464722],"type":"Point"}
}