{
  "type": "Feature",
  "properties": {
    "iso:country":"DE",
    "sg:address":"H\u00fclsdonker Str. 53",
    "sg:city":"Moers",
    "sg:phone":"+49 2841/170352",
    "sg:postcode":"47441",
    "sg:province":"Nordrhein-Westfalen",
    "wof:name":"Andreas Schomaker",
    "wof:placetype":"venue"
},
  "geometry": {"coordinates":[6.61531,51.451084],"type":"Point"}
}