{
  "type": "Feature",
  "properties": {
    "iso:country":"DE",
    "sg:address":"Welle 10",
    "sg:city":"Bielefeld",
    "sg:phone":"+49 521/172748",
    "sg:postcode":"33602",
    "sg:province":"Nordrhein-Westfalen",
    "wof:name":"Paulaner Keller",
    "wof:placetype":"venue"
},
  "geometry": {"coordinates":[8.5319776535,52.0197219849],"type":"Point"}
}