{
  "type": "Feature",
  "properties": {
    "iso:country":"DE",
    "sg:address":"Falkenhagener Str 56",
    "sg:city":"Falkensee",
    "sg:phone":"+49 30/6211045",
    "sg:postcode":"14612",
    "sg:province":"Brandenburg",
    "wof:name":"Druckerei Lehmann",
    "wof:placetype":"venue"
},
  "geometry": {"coordinates":[13.0960187912,52.5697135925],"type":"Point"}
}