{
  "type": "Feature",
  "properties": {
    "iso:country":"DE",
    "sg:address":"Auf der Vogelsburg 51",
    "sg:city":"Gieboldehausen",
    "sg:postcode":"37434",
    "sg:province":"Niedersachsen",
    "wof:name":"Markus Schreier E. K.",
    "wof:placetype":"venue"
},
  "geometry": {"coordinates":[10.2244405746,51.6045227051],"type":"Point"}
}