{
  "type": "Feature",
  "properties": {
    "iso:country":"DE",
    "sg:address":"Goethestr. 38",
    "sg:city":"Teterow",
    "sg:phone":"+49 3996/172437",
    "sg:postcode":"17166",
    "sg:province":"Mecklenburg-Vorpommern",
    "wof:name":"Dr. Med. Heinz Richter",
    "wof:placetype":"venue"
},
  "geometry": {"coordinates":[12.568997,53.775032],"type":"Point"}
}