{
  "type": "Feature",
  "properties": {
    "iso:country":"DE",
    "sg:address":"Blumenstr. 29",
    "sg:city":"Geisenheim",
    "sg:phone":"+49 6722",
    "sg:postcode":"65366",
    "sg:province":"Hessen",
    "wof:name":"Erlebnisreisen Christian Geith",
    "wof:placetype":"venue"
},
  "geometry": {"coordinates":[7.956551075,50.0046234131],"type":"Point"}
}