{
  "type": "Feature",
  "properties": {
    "iso:country":"DE",
    "sg:address":"Nebraer Str. 10",
    "sg:city":"Querfurt",
    "sg:phone":"+49 34771/44181",
    "sg:postcode":"06268",
    "sg:province":"Sachsen-Anhalt",
    "wof:name":"Redaktion Mitteldeutsche Zeitung",
    "wof:placetype":"venue"
},
  "geometry": {"coordinates":[11.5975513458,51.3775672913],"type":"Point"}
}