{
  "type": "Feature",
  "properties": {
    "iso:country":"DE",
    "sg:address":"Apothekergasse 1",
    "sg:city":"Parey",
    "sg:phone":"+49 39349/51023",
    "sg:postcode":"39317",
    "sg:province":"Sachsen-Anhalt",
    "wof:name":"Pareys-reisewelt",
    "wof:placetype":"venue"
},
  "geometry": {"coordinates":[11.98509,52.380543],"type":"Point"}
}