{
  "type": "Feature",
  "properties": {
    "iso:country":"DE",
    "sg:address":"Siegfriedstr. 27",
    "sg:city":"Kempen",
    "sg:phone":"+49 2152/53206",
    "sg:postcode":"47906",
    "sg:province":"Nordrhein-Westfalen",
    "wof:name":"L. Krabler",
    "wof:placetype":"venue"
},
  "geometry": {"coordinates":[6.4199681282,51.3680877686],"type":"Point"}
}