{
  "type": "Feature",
  "properties": {
    "iso:country":"DE",
    "sg:address":"Br\u00fcsseler Platz 16",
    "sg:city":"K\u00f6ln",
    "sg:phone":"+49 221/514329",
    "sg:postcode":"50674",
    "sg:province":"Nordrhein-Westfalen",
    "wof:name":"Allegro",
    "wof:placetype":"venue"
},
  "geometry": {"coordinates":[6.933584,50.938889],"type":"Point"}
}