{
  "type": "Feature",
  "properties": {
    "iso:country":"DE",
    "sg:address":"Leimeneckstr. 1",
    "sg:city":"Glottertal",
    "sg:phone":"+370 5952135",
    "sg:postcode":"79286",
    "sg:province":"Baden-W\u00fcrttemberg",
    "wof:name":"Nehrung Reisen",
    "wof:placetype":"venue"
},
  "geometry": {"coordinates":[7.939525,48.048763],"type":"Point"}
}