{
  "type": "Feature",
  "properties": {
    "iso:country":"DE",
    "sg:address":"Bergstr. 2",
    "sg:city":"Pfinztal",
    "sg:phone":"+49 7240/943434",
    "sg:postcode":"76327",
    "sg:province":"Baden-W\u00fcrttemberg",
    "wof:name":"V. H\u00fcbner",
    "wof:placetype":"venue"
},
  "geometry": {"coordinates":[8.56624,49.000648],"type":"Point"}
}