{
  "type": "Feature",
  "properties": {
    "iso:country":"DE",
    "sg:address":"Katzwanger Hauptstr. 25",
    "sg:city":"N\u00fcrnberg",
    "sg:phone":"+49 9122/76173",
    "sg:postcode":"90453",
    "sg:province":"Bayern",
    "wof:name":"Sch\u00fctzenhaus Katzwang",
    "wof:placetype":"venue"
},
  "geometry": {"coordinates":[11.0516605377,49.3559989929],"type":"Point"}
}