{
  "type": "Feature",
  "properties": {
    "iso:country":"DE",
    "sg:address":"Schallenburg 8b",
    "sg:city":"Varel",
    "sg:postcode":"26316",
    "sg:province":"Niedersachsen",
    "wof:name":"Sl Bautr\u00e4gerges. Gmbh & Co. Kg",
    "wof:placetype":"venue"
},
  "geometry": {"coordinates":[8.092422,53.401028],"type":"Point"}
}