{
  "type": "Feature",
  "properties": {
    "iso:country":"DE",
    "sg:address":"Industriestr. 13",
    "sg:city":"Gr\u00f6benzell",
    "sg:phone":"+49 8142/7905",
    "sg:postcode":"82194",
    "sg:province":"Bayern",
    "wof:name":"Herbert Iser-iser Ingenieur",
    "wof:placetype":"venue"
},
  "geometry": {"coordinates":[11.3819313049,48.1900634766],"type":"Point"}
}