{
  "type": "Feature",
  "properties": {
    "iso:country":"DE",
    "sg:address":"Osterwaldstr. 53",
    "sg:city":"M\u00fcnchen",
    "sg:phone":"+49 89/3613155",
    "sg:postcode":"80805",
    "sg:province":"Bayern",
    "wof:name":"Klaus Book Wirtschaftspr\u00fcfer",
    "wof:placetype":"venue"
},
  "geometry": {"coordinates":[11.6009960175,48.1677856445],"type":"Point"}
}