{
  "type": "Feature",
  "properties": {
    "iso:country":"DE",
    "sg:address":"Fichtestr. 20",
    "sg:city":"Frankenthal",
    "sg:phone":"+49 6233/299635",
    "sg:postcode":"67227",
    "sg:province":"Rheinland-Pfalz",
    "wof:name":"Bd Gesellschaft F\u00fcr System- Beratung Und Software Mbh",
    "wof:placetype":"venue"
},
  "geometry": {"coordinates":[8.3445730209,49.5263786316],"type":"Point"}
}