{
  "type": "Feature",
  "properties": {
    "iso:country":"DE",
    "sg:address":"Volmstr. 33",
    "sg:city":"M\u00fcnchen",
    "sg:phone":"+49 89/89620933",
    "sg:postcode":"81241",
    "sg:province":"Bayern",
    "wof:name":"Coffeeteam Kaffee- Maschinen Gmbh",
    "wof:placetype":"venue"
},
  "geometry": {"coordinates":[11.4536132812,48.1501655579],"type":"Point"}
}