{
  "type": "Feature",
  "properties": {
    "iso:country":"DE",
    "sg:address":"John-Brinckman-Str. 5",
    "sg:city":"Ludwigslust",
    "sg:postcode":"19288",
    "sg:province":"Mecklenburg-Vorpommern",
    "wof:name":"E. Thielcke",
    "wof:placetype":"venue"
},
  "geometry": {"coordinates":[11.493851,53.333492],"type":"Point"}
}