{
  "type": "Feature",
  "properties": {
    "iso:country":"DE",
    "sg:address":"Magdalenenstr. 35",
    "sg:city":"Bonn",
    "sg:phone":"+49 228/612864",
    "sg:postcode":"53121",
    "sg:province":"Nordrhein-Westfalen",
    "wof:name":"Klaus Jastrow",
    "wof:placetype":"venue"
},
  "geometry": {"coordinates":[7.076565,50.725067],"type":"Point"}
}