{
  "type": "Feature",
  "properties": {
    "iso:country":"DE",
    "sg:address":"Wei\u00dfer Str. 15",
    "sg:city":"K\u00f6ln",
    "sg:phone":"+49 221/393748",
    "sg:postcode":"50996",
    "sg:province":"Nordrhein-Westfalen",
    "wof:name":"Dr. Thomas Bereuter",
    "wof:placetype":"venue"
},
  "geometry": {"coordinates":[6.9951648712,50.8929252625],"type":"Point"}
}