{
  "type": "Feature",
  "properties": {
    "iso:country":"DE",
    "sg:address":"Dinslakener Str. 4",
    "sg:city":"H\u00fcnxe",
    "sg:phone":"+49 2858/7696",
    "sg:postcode":"46569",
    "sg:province":"Nordrhein-Westfalen",
    "wof:name":"Sigrid Adam",
    "wof:placetype":"venue"
},
  "geometry": {"coordinates":[6.7654,51.642254],"type":"Point"}
}