{
  "type": "Feature",
  "properties": {
    "iso:country":"DE",
    "sg:address":"Dorfstr. 30",
    "sg:city":"Hamdorf",
    "sg:phone":"+49 4332/759",
    "sg:postcode":"24805",
    "sg:province":"Schleswig-Holstein",
    "wof:name":"Claudia Wulfes",
    "wof:placetype":"venue"
},
  "geometry": {"coordinates":[9.5185012817,54.2217330933],"type":"Point"}
}