{
  "type": "Feature",
  "properties": {
    "iso:country":"DE",
    "sg:address":"Am Berg 4",
    "sg:city":"Pfaffenhofen",
    "sg:phone":"+49 8441/84189",
    "sg:postcode":"85276",
    "sg:province":"Bayern",
    "wof:name":"Karl-h. Und Josefine Mildner Ingenieure",
    "wof:placetype":"venue"
},
  "geometry": {"coordinates":[11.528181076,48.5654716492],"type":"Point"}
}