{
  "type": "Feature",
  "properties": {
    "iso:country":"DE",
    "sg:address":"Heimbauweg 1",
    "sg:city":"Oberhausen",
    "sg:phone":"+49 208/608958",
    "sg:postcode":"46119",
    "sg:province":"Nordrhein-Westfalen",
    "wof:name":"Gabriele K\u00f6ster Steuerberater",
    "wof:placetype":"venue"
},
  "geometry": {"coordinates":[6.8825650215,51.5149765015],"type":"Point"}
}