{
  "type": "Feature",
  "properties": {
    "iso:country":"DE",
    "sg:address":"Sommerswalde 8",
    "sg:city":"Schwante b. Berlin",
    "sg:phone":"+49 33055/70810",
    "sg:postcode":"16727",
    "sg:province":"Brandenburg",
    "wof:name":"Dharmakaya Schloss Sommerswalde E.v.",
    "wof:placetype":"venue"
},
  "geometry": {"coordinates":[13.08656,52.735199],"type":"Point"}
}