{
  "type": "Feature",
  "properties": {
    "iso:country":"DE",
    "sg:address":"Freiheitstr. 1",
    "sg:city":"Bochum",
    "sg:phone":"+49 234/232670",
    "sg:postcode":"44866",
    "sg:province":"Nordrhein-Westfalen",
    "wof:name":"B. Loszinski",
    "wof:placetype":"venue"
},
  "geometry": {"coordinates":[7.1346487999,51.4811096191],"type":"Point"}
}