{
  "type": "Feature",
  "properties": {
    "iso:country":"DE",
    "sg:address":"Winterhuder Weg 38 a",
    "sg:city":"Hamburg",
    "sg:phone":"+49 40/2203949",
    "sg:postcode":"22085",
    "sg:province":"Hamburg",
    "wof:name":"Hanseat B\u00fcrobedarf Handelsgesellschaft Mbh",
    "wof:placetype":"venue"
},
  "geometry": {"coordinates":[10.024889,53.572334],"type":"Point"}
}