{
  "type": "Feature",
  "properties": {
    "iso:country":"DE",
    "sg:address":"G\u00fcntherstr. 11",
    "sg:city":"Hannover",
    "sg:phone":"+49 511/8386848",
    "sg:postcode":"30519",
    "sg:province":"Niedersachsen",
    "wof:name":"Dr. V. Viebcke Rechtsanwalt",
    "wof:placetype":"venue"
},
  "geometry": {"coordinates":[9.7599496841,52.3457756042],"type":"Point"}
}