{
  "type": "Feature",
  "properties": {
    "iso:country":"DE",
    "sg:address":"Emil-Ufer-Str. 10",
    "sg:city":"Olbersdorf",
    "sg:phone":"+49 3583/690226",
    "sg:postcode":"02785",
    "sg:province":"Sachsen",
    "wof:name":"Frank Schiller",
    "wof:placetype":"venue"
},
  "geometry": {"coordinates":[14.7573413849,50.8663291931],"type":"Point"}
}