{
  "type": "Feature",
  "properties": {
    "iso:country":"DE",
    "sg:address":"Lindengrabenstr. 27",
    "sg:city":"Gevelsberg",
    "sg:phone":"+49 2332/4164",
    "sg:postcode":"58285",
    "sg:province":"Nordrhein-Westfalen",
    "wof:name":"Gastst\u00e4tte P. G. Herguth",
    "wof:placetype":"venue"
},
  "geometry": {"coordinates":[7.3321390152,51.3140258789],"type":"Point"}
}