{
  "type": "Feature",
  "properties": {
    "iso:country":"DE",
    "sg:address":"Luruper Hauptstr. 177",
    "sg:city":"Hamburg",
    "sg:phone":"+49 40/836525",
    "sg:postcode":"22547",
    "sg:province":"Hamburg",
    "wof:name":"Bodo Schneider",
    "wof:placetype":"venue"
},
  "geometry": {"coordinates":[9.8696861267,53.5937614441],"type":"Point"}
}