{
  "type": "Feature",
  "properties": {
    "iso:country":"DE",
    "sg:address":"Eidenborner Str. 34",
    "sg:city":"Lebach",
    "sg:phone":"+49 6881/3921",
    "sg:postcode":"66822",
    "sg:province":"Saarland",
    "wof:name":"Otmar Hoffmann",
    "wof:placetype":"venue"
},
  "geometry": {"coordinates":[6.918607235,49.3925857544],"type":"Point"}
}