{
  "type": "Feature",
  "properties": {
    "iso:country":"DE",
    "sg:address":"Winterswyker Str. 42",
    "sg:city":"S\u00fcdlohn",
    "sg:phone":"+49 2862/6325",
    "sg:postcode":"46354",
    "sg:province":"Nordrhein-Westfalen",
    "wof:name":"Wansing & Radau M\u00f6belwerkst\u00e4tten Gmbh & Co. Kg",
    "wof:placetype":"venue"
},
  "geometry": {"coordinates":[6.803289,51.936275],"type":"Point"}
}