{
  "type": "Feature",
  "properties": {
    "iso:country":"DE",
    "sg:address":"Dorfring 2",
    "sg:city":"Laasdorf",
    "sg:phone":"+49 4936/4285780",
    "sg:postcode":"07646",
    "sg:province":"Th\u00fcringen",
    "wof:name":"Jenconsult Laasdorf Planungs- & Hg F. Anlagenbau",
    "wof:placetype":"venue"
},
  "geometry": {"coordinates":[11.673232,50.872028],"type":"Point"}
}