{
  "type": "Feature",
  "properties": {
    "iso:country":"DE",
    "sg:address":"Landauer Str. 149",
    "sg:city":"Annweiler",
    "sg:phone":"+49 6346/7130",
    "sg:postcode":"76855",
    "sg:province":"Rheinland-Pfalz",
    "wof:name":"Armin Schneider Gmbh",
    "wof:placetype":"venue"
},
  "geometry": {"coordinates":[7.987592,49.214294],"type":"Point"}
}