{
  "type": "Feature",
  "properties": {
    "iso:country":"DE",
    "sg:address":"Leipziger Str. 5",
    "sg:city":"Ransbach-Baumbach",
    "sg:postcode":"56235",
    "sg:province":"Rheinland-Pfalz",
    "wof:name":"G\u00fcnther Montagebau Werkb\u00fcro Schilken",
    "wof:placetype":"venue"
},
  "geometry": {"coordinates":[7.734193,50.473473],"type":"Point"}
}