{
  "type": "Feature",
  "properties": {
    "iso:country":"DE",
    "sg:address":"Otto-Gau\u00df-Str. 23",
    "sg:city":"Pfronstetten",
    "sg:phone":"+49 7388/238",
    "sg:postcode":"72539",
    "sg:province":"Baden-W\u00fcrttemberg",
    "wof:name":"Krone",
    "wof:placetype":"venue"
},
  "geometry": {"coordinates":[9.3843126297,48.2581787109],"type":"Point"}
}