{
  "type": "Feature",
  "properties": {
    "iso:country":"DE",
    "sg:address":"Sonnenstr. 10",
    "sg:city":"Bad Bertrich",
    "sg:phone":"+49 2674/427",
    "sg:postcode":"56864",
    "sg:province":"Rheinland-Pfalz",
    "wof:name":"G\u00e4stehaus H. Johann",
    "wof:placetype":"venue"
},
  "geometry": {"coordinates":[7.0359930992,50.0728530884],"type":"Point"}
}