{
  "type": "Feature",
  "properties": {
    "iso:country":"DE",
    "sg:address":"Rudolf-Diener-Str. 17",
    "sg:city":"Gera",
    "sg:phone":"+49 365/200839",
    "sg:postcode":"07545",
    "sg:province":"Th\u00fcringen",
    "wof:name":"Peter Engelbrecht Rechtsanwalt",
    "wof:placetype":"venue"
},
  "geometry": {"coordinates":[12.0838155746,50.8795318604],"type":"Point"}
}