{
  "type": "Feature",
  "properties": {
    "iso:country":"DE",
    "sg:address":"Verler Str. 154",
    "sg:city":"G\u00fctersloh",
    "sg:phone":"+49 5241/46203",
    "sg:postcode":"33332",
    "sg:province":"Nordrhein-Westfalen",
    "wof:name":"Bernds Dance Shop",
    "wof:placetype":"venue"
},
  "geometry": {"coordinates":[8.4081897736,51.8952102661],"type":"Point"}
}