{
  "type": "Feature",
  "properties": {
    "iso:country":"DE",
    "sg:address":"Hofstetter Str. 25",
    "sg:city":"Kleinwallstadt",
    "sg:phone":"+49 6022/21325",
    "sg:postcode":"63839",
    "sg:province":"Bayern",
    "wof:name":"Hans Fuchs",
    "wof:placetype":"venue"
},
  "geometry": {"coordinates":[9.174026,49.867908],"type":"Point"}
}