{
  "type": "Feature",
  "properties": {
    "iso:country":"DE",
    "sg:address":"Molkereistr. 4",
    "sg:city":"Esens",
    "sg:phone":"+49 4971/50016",
    "sg:postcode":"26427",
    "sg:province":"Niedersachsen",
    "wof:name":"Gralf Jacobs Rechtsanwalt",
    "wof:placetype":"venue"
},
  "geometry": {"coordinates":[7.6121840477,53.6442871094],"type":"Point"}
}