{
  "type": "Feature",
  "properties": {
    "iso:country":"DE",
    "sg:address":"Eibseestr. 12",
    "sg:city":"Berlin",
    "sg:phone":"+49 30/6743490",
    "sg:postcode":"12527",
    "sg:province":"Berlin",
    "wof:name":"Michael Gietzelt",
    "wof:placetype":"venue"
},
  "geometry": {"coordinates":[13.579126,52.417194],"type":"Point"}
}