{
  "type": "Feature",
  "properties": {
    "iso:country":"DE",
    "sg:address":"Ludwigsplatz 13",
    "sg:city":"Rosenheim",
    "sg:phone":"+49 8031/17793",
    "sg:postcode":"83022",
    "sg:province":"Bayern",
    "wof:name":"Rainer Luck Restaurator",
    "wof:placetype":"venue"
},
  "geometry": {"coordinates":[12.1298885345,47.8565330505],"type":"Point"}
}