{
  "type": "Feature",
  "properties": {
    "iso:country":"DE",
    "sg:address":"Sundhausstr. 230",
    "sg:city":"Gro\u00dffahner",
    "sg:postcode":"99100",
    "sg:province":"Th\u00fcringen",
    "wof:name":"Sige-industrieb\u00f6den Gmbh",
    "wof:placetype":"venue"
},
  "geometry": {"coordinates":[10.8314714432,51.0583267212],"type":"Point"}
}