{
  "type": "Feature",
  "properties": {
    "iso:country":"DE",
    "sg:address":"Am Siegenb\u00fcttel 14",
    "sg:city":"Arnsberg",
    "sg:phone":"+49 2932",
    "sg:postcode":"59759",
    "sg:province":"Nordrhein-Westfalen",
    "wof:name":"F. Danne",
    "wof:placetype":"venue"
},
  "geometry": {"coordinates":[7.9945049286,51.4290237427],"type":"Point"}
}