{
  "type": "Feature",
  "properties": {
    "iso:country":"DE",
    "sg:address":"Fraunhoferstr. 29",
    "sg:city":"M\u00fcnchen",
    "sg:phone":"+49 89/2014523",
    "sg:postcode":"80469",
    "sg:province":"Bayern",
    "wof:name":"Blatter Gmbh",
    "wof:placetype":"venue"
},
  "geometry": {"coordinates":[11.5745134354,48.1293373108],"type":"Point"}
}