{
  "type": "Feature",
  "properties": {
    "iso:country":"DE",
    "sg:address":"Neckargasse 1",
    "sg:city":"T\u00fcbingen",
    "sg:phone":"+49 7071/921320",
    "sg:postcode":"72070",
    "sg:province":"Baden-W\u00fcrttemberg",
    "wof:name":"Annabells Boutique U. Schlotterer",
    "wof:placetype":"venue"
},
  "geometry": {"coordinates":[9.05665,48.520313],"type":"Point"}
}