{
  "type": "Feature",
  "properties": {
    "iso:country":"DE",
    "sg:address":"Moselstr. 2 b",
    "sg:city":"Hanau",
    "sg:postcode":"63452",
    "sg:province":"Hessen",
    "wof:name":"O & T Bauunternehmnung Gmbh",
    "wof:placetype":"venue"
},
  "geometry": {"coordinates":[8.938763,50.151405],"type":"Point"}
}