{
  "type": "Feature",
  "properties": {
    "iso:country":"DE",
    "sg:address":"Plettenberger Str. 7",
    "sg:city":"Melle",
    "sg:phone":"+49 5422/2212",
    "sg:postcode":"49324",
    "sg:province":"Niedersachsen",
    "wof:name":"Feyer H\u00f6rger\u00e4te-akustiker",
    "wof:placetype":"venue"
},
  "geometry": {"coordinates":[8.3359136581,52.2013587952],"type":"Point"}
}