{
  "type": "Feature",
  "properties": {
    "iso:country":"DE",
    "sg:address":"Dorfstr. 24",
    "sg:city":"Ringenwalde",
    "sg:phone":"+49 39881/49196",
    "sg:postcode":"17268",
    "sg:province":"Brandenburg",
    "wof:name":"Pro Regio Planungs- Und Vermarktungsges. F\u00fcr Wohnen",
    "wof:placetype":"venue"
},
  "geometry": {"coordinates":[13.7157716751,53.0571250916],"type":"Point"}
}