{
  "type": "Feature",
  "properties": {
    "iso:country":"DE",
    "sg:address":"Ortsstr. 1",
    "sg:city":"Diespeck",
    "sg:phone":"+49 9161/5231",
    "sg:postcode":"91456",
    "sg:province":"Bayern",
    "wof:name":"Georg Bezold",
    "wof:placetype":"venue"
},
  "geometry": {"coordinates":[10.671621,49.590691],"type":"Point"}
}