{
  "type": "Feature",
  "properties": {
    "iso:country":"DE",
    "sg:address":"Lange Str. 50",
    "sg:city":"Parchim",
    "sg:phone":"+49 3871/226148",
    "sg:postcode":"19370",
    "sg:province":"Mecklenburg-Vorpommern",
    "wof:name":"Brigitte Kratky",
    "wof:placetype":"venue"
},
  "geometry": {"coordinates":[11.846572876,53.4278717041],"type":"Point"}
}