{
  "type": "Feature",
  "properties": {
    "iso:country":"DE",
    "sg:address":"Osterhardt 23",
    "sg:city":"Werdohl",
    "sg:postcode":"58791",
    "sg:province":"Nordrhein-Westfalen",
    "wof:name":"Sida-service Gmbh",
    "wof:placetype":"venue"
},
  "geometry": {"coordinates":[7.7596921921,51.2459335327],"type":"Point"}
}