{
  "type": "Feature",
  "properties": {
    "iso:country":"DE",
    "sg:address":"Von-Der-Tann-Str. 1",
    "sg:city":"Rosenheim",
    "sg:phone":"+49 8031/380500",
    "sg:postcode":"83022",
    "sg:province":"Bayern",
    "wof:name":"Top-gast Lebensmittel Gmbh & Co.kg",
    "wof:placetype":"venue"
},
  "geometry": {"coordinates":[12.11307,47.856556],"type":"Point"}
}