{
  "type": "Feature",
  "properties": {
    "iso:country":"DE",
    "sg:address":"Gildestr. 3",
    "sg:city":"Tecklenburg",
    "sg:phone":"+49 5455/1074",
    "sg:postcode":"49545",
    "sg:province":"Nordrhein-Westfalen",
    "wof:name":"Heemann Verwaltungs- Und Beteiligungs Gmbh",
    "wof:placetype":"venue"
},
  "geometry": {"coordinates":[7.748621,52.21888],"type":"Point"}
}