{
  "type": "Feature",
  "properties": {
    "iso:country":"DE",
    "sg:address":"Gallbergweg 36",
    "sg:city":"Brilon",
    "sg:phone":"+49 2961/97860",
    "sg:postcode":"59929",
    "sg:province":"Nordrhein-Westfalen",
    "wof:name":"Heckmann Bau Gmbh",
    "wof:placetype":"venue"
},
  "geometry": {"coordinates":[8.585277,51.40374],"type":"Point"}
}