{
  "type": "Feature",
  "properties": {
    "iso:country":"DE",
    "sg:city":"Wilhelmsdorf",
    "sg:phone":"+49 7503/804",
    "sg:postcode":"88271",
    "sg:province":"Baden-W\u00fcrttemberg",
    "wof:name":"Gross Und Holzner Architekten",
    "wof:placetype":"venue"
},
  "geometry": {"coordinates":[9.42469,47.866329],"type":"Point"}
}