{
  "type": "Feature",
  "properties": {
    "iso:country":"DE",
    "sg:address":"Kochstr. 2",
    "sg:city":"Erlangen",
    "sg:phone":"+49 9131/851",
    "sg:postcode":"91054",
    "sg:province":"Bayern",
    "wof:name":"Institut F\u00fcr Rechtsgeschichte",
    "wof:placetype":"venue"
},
  "geometry": {"coordinates":[11.0170059204,49.5996513367],"type":"Point"}
}