{
  "type": "Feature",
  "properties": {
    "iso:country":"DE",
    "sg:address":"Todtgl\u00fcsinger Str. 20",
    "sg:city":"Tostedt",
    "sg:phone":"+49 4182/6224",
    "sg:postcode":"21255",
    "sg:province":"Niedersachsen",
    "wof:name":"E. K\u00e4hler",
    "wof:placetype":"venue"
},
  "geometry": {"coordinates":[9.719959259,53.2833061218],"type":"Point"}
}