{
  "type": "Feature",
  "properties": {
    "iso:country":"DE",
    "sg:address":"Steinbockstr. 9",
    "sg:city":"Stade",
    "sg:phone":"+49 4141/83313",
    "sg:postcode":"21683",
    "sg:province":"Niedersachsen",
    "wof:name":"Wilfried Kohrs Steuerberater",
    "wof:placetype":"venue"
},
  "geometry": {"coordinates":[9.4103183746,53.6014862061],"type":"Point"}
}