{
  "type": "Feature",
  "properties": {
    "iso:country":"DE",
    "sg:address":"R\u00f6dereckring 2",
    "sg:city":"Rastatt",
    "sg:phone":"+49 7222/68355",
    "sg:postcode":"76437",
    "sg:province":"Baden-W\u00fcrttemberg",
    "wof:name":"Peter Morstadt",
    "wof:placetype":"venue"
},
  "geometry": {"coordinates":[8.158273,48.884331],"type":"Point"}
}