{
  "type": "Feature",
  "properties": {
    "iso:country":"DE",
    "sg:address":"Bahnhofstr. 23",
    "sg:city":"Siegburg",
    "sg:phone":"+49 2241/62283",
    "sg:postcode":"53721",
    "sg:province":"Nordrhein-Westfalen",
    "wof:name":"Betten Raymond Inh. Christian Raymond E. Kfm.",
    "wof:placetype":"venue"
},
  "geometry": {"coordinates":[7.2028107643,50.7960014343],"type":"Point"}
}