{
  "type": "Feature",
  "properties": {
    "iso:country":"DE",
    "sg:address":"Berliner Str. 42",
    "sg:city":"Ortenberg",
    "sg:phone":"+49 6046/940843",
    "sg:postcode":"63683",
    "sg:province":"Hessen",
    "wof:name":"Mec German Management Und Engineering Consulting",
    "wof:placetype":"venue"
},
  "geometry": {"coordinates":[9.0576019287,50.3538894653],"type":"Point"}
}