{
  "type": "Feature",
  "properties": {
    "iso:country":"DE",
    "sg:address":"Kranensterzstr. 26",
    "sg:city":"Stolberg",
    "sg:phone":"+49 2402/24990",
    "sg:postcode":"52223",
    "sg:province":"Nordrhein-Westfalen",
    "wof:name":"Willy Schartmann",
    "wof:placetype":"venue"
},
  "geometry": {"coordinates":[6.225821,50.76141],"type":"Point"}
}