{
  "type": "Feature",
  "properties": {
    "iso:country":"DE",
    "sg:address":"Gut Neuh\u00f6fgen",
    "sg:city":"Neuss",
    "sg:phone":"+49 2131/476201",
    "sg:postcode":"41466",
    "sg:province":"Nordrhein-Westfalen",
    "wof:name":"Reitschule Gut Neuh\u00f6fen Beteiligungs-gmbh",
    "wof:placetype":"venue"
},
  "geometry": {"coordinates":[6.68787,51.154396],"type":"Point"}
}