{
  "type": "Feature",
  "properties": {
    "iso:country":"DE",
    "sg:address":"Halbertshofen",
    "sg:city":"Buch",
    "sg:phone":"+49 7343/6942",
    "sg:postcode":"89290",
    "sg:province":"Bayern",
    "wof:name":"G. Anzinger Immobilienmakler",
    "wof:placetype":"venue"
},
  "geometry": {"coordinates":[10.2112846375,48.2285461426],"type":"Point"}
}