{
  "type": "Feature",
  "properties": {
    "iso:country":"DE",
    "sg:address":"Winterfeldtstr. 52",
    "sg:city":"Berlin",
    "sg:postcode":"10781",
    "sg:province":"Berlin",
    "wof:name":"Brains Gesellschaft F\u00fcr Event-marketing Mbh",
    "wof:placetype":"venue"
},
  "geometry": {"coordinates":[13.3524904251,52.4969940186],"type":"Point"}
}