{
  "type": "Feature",
  "properties": {
    "iso:country":"DE",
    "sg:address":"Postfach 20",
    "sg:city":"Arnstein",
    "sg:phone":"+49 9363/680",
    "sg:postcode":"97448",
    "sg:province":"Bayern",
    "wof:name":"Miwe Michael Wenz Gmbh",
    "wof:placetype":"venue"
},
  "geometry": {"coordinates":[9.9713096619,49.9766807556],"type":"Point"}
}