{
  "type": "Feature",
  "properties": {
    "iso:country":"DE",
    "sg:address":"Altlu\u00dfheimer Str. 54",
    "sg:city":"Neulu\u00dfheim",
    "sg:phone":"+49 6205/31735",
    "sg:postcode":"68809",
    "sg:province":"Baden-W\u00fcrttemberg",
    "wof:name":"Elf Gmbh Tankstelle",
    "wof:placetype":"venue"
},
  "geometry": {"coordinates":[8.5164117813,49.2944946289],"type":"Point"}
}