{
  "type": "Feature",
  "properties": {
    "iso:country":"DE",
    "sg:address":"Buchenbusch 64",
    "sg:city":"Neu-Isenburg",
    "sg:phone":"+49 6102/326390",
    "sg:postcode":"63263",
    "sg:province":"Hessen",
    "wof:name":"G\u00fcnther Breucker Rechtsanwalt",
    "wof:placetype":"venue"
},
  "geometry": {"coordinates":[8.7046461105,50.0460586548],"type":"Point"}
}