{
  "type": "Feature",
  "properties": {
    "iso:country":"DE",
    "sg:address":"Am Pfauenzehnt 1-3",
    "sg:city":"Dinslaken",
    "sg:phone":"+49 4920/6441750",
    "sg:postcode":"46539",
    "sg:province":"Nordrhein-Westfalen",
    "wof:name":"Schmidtke & Sohn Gmbh",
    "wof:placetype":"venue"
},
  "geometry": {"coordinates":[6.7488031387,51.5683670044],"type":"Point"}
}