{
  "type": "Feature",
  "properties": {
    "iso:country":"DE",
    "sg:address":"D\u00f6rfelstr.",
    "sg:city":"Marienberg",
    "sg:postcode":"09496",
    "sg:province":"Sachsen",
    "wof:name":"Entcon Containerdienst Gmbh",
    "wof:placetype":"venue"
},
  "geometry": {"coordinates":[13.17703,50.647079],"type":"Point"}
}