{
  "type": "Feature",
  "properties": {
    "iso:country":"DE",
    "sg:address":"Mitteltorstr. 6",
    "sg:city":"Marktheidenfeld",
    "sg:phone":"+49 9391/2473",
    "sg:postcode":"97828",
    "sg:province":"Bayern",
    "wof:name":"S. Bidanel",
    "wof:placetype":"venue"
},
  "geometry": {"coordinates":[9.600883,49.843819],"type":"Point"}
}