{
  "type": "Feature",
  "properties": {
    "iso:country":"DE",
    "sg:address":"Rosenheimer Str. 3",
    "sg:city":"Oberaudorf",
    "sg:phone":"+49 8033/3241",
    "sg:postcode":"83080",
    "sg:province":"Bayern",
    "wof:name":"Restaurant Alpenrose",
    "wof:placetype":"venue"
},
  "geometry": {"coordinates":[12.1719465256,47.6477470398],"type":"Point"}
}