{
  "type": "Feature",
  "properties": {
    "iso:country":"DE",
    "sg:address":"Vogelsang 4",
    "sg:city":"Thalfang",
    "sg:phone":"+49 6504/950124",
    "sg:postcode":"54424",
    "sg:province":"Rheinland-Pfalz",
    "wof:name":"Werner Kiefer Gmbh",
    "wof:placetype":"venue"
},
  "geometry": {"coordinates":[6.9939231873,49.7507286072],"type":"Point"}
}