{
  "type": "Feature",
  "properties": {
    "iso:country":"DE",
    "sg:address":"Brehmstr. 9",
    "sg:city":"D\u00fcsseldorf",
    "sg:phone":"+49 211/9083233",
    "sg:postcode":"40239",
    "sg:province":"Nordrhein-Westfalen",
    "wof:name":"H & K Graphic Production Gmbh",
    "wof:placetype":"venue"
},
  "geometry": {"coordinates":[6.802005,51.240204],"type":"Point"}
}