{
  "type": "Feature",
  "properties": {
    "iso:country":"DE",
    "sg:address":"Prisdorfer Str. 2a",
    "sg:city":"Pinneberg",
    "sg:phone":"+49 4101/207111",
    "sg:postcode":"25421",
    "sg:province":"Schleswig-Holstein",
    "wof:name":"Private Home Page Womo Luther",
    "wof:placetype":"venue"
},
  "geometry": {"coordinates":[9.792526,53.665089],"type":"Point"}
}