{
  "type": "Feature",
  "properties": {
    "iso:country":"DE",
    "sg:address":"Im Hoflehen 65",
    "sg:city":"Triberg",
    "sg:phone":"+49 7722/969600",
    "sg:postcode":"78098",
    "sg:province":"Baden-W\u00fcrttemberg",
    "wof:name":"Berghotel Tannenhof Gmbh",
    "wof:placetype":"venue"
},
  "geometry": {"coordinates":[8.2420492172,48.1237792969],"type":"Point"}
}