{
  "type": "Feature",
  "properties": {
    "iso:country":"DE",
    "sg:address":"Obere Wilhelmstr. 4-6",
    "sg:city":"Bonn",
    "sg:phone":"+49 228/461628",
    "sg:postcode":"53225",
    "sg:province":"Nordrhein-Westfalen",
    "wof:name":"B\u00e4ckerei Konditorei Uwe Baumgart",
    "wof:placetype":"venue"
},
  "geometry": {"coordinates":[7.123703,50.739655],"type":"Point"}
}