{
  "type": "Feature",
  "properties": {
    "iso:country":"DE",
    "sg:address":"Robert-Bosch-Str. 3",
    "sg:city":"V\u00f6hringen",
    "sg:phone":"+49 4973/0696650",
    "sg:postcode":"89269",
    "sg:province":"Bayern",
    "wof:name":"Smg Sportplatzmaschinenbau Gmbh",
    "wof:placetype":"venue"
},
  "geometry": {"coordinates":[10.069816,48.296516],"type":"Point"}
}