{
  "type": "Feature",
  "properties": {
    "iso:country":"DE",
    "sg:address":"Delbr\u00fcckstr. 33",
    "sg:city":"Berlin",
    "sg:phone":"+49 30/8262633",
    "sg:postcode":"14193",
    "sg:province":"Berlin",
    "wof:name":"Katholisches Pfarramt St. Karl Borrom\u00e4us",
    "wof:placetype":"venue"
},
  "geometry": {"coordinates":[13.2813053131,52.4841194153],"type":"Point"}
}