{
  "type": "Feature",
  "properties": {
    "iso:country":"DE",
    "sg:address":"Eythstr. 20",
    "sg:city":"K\u00f6ln",
    "sg:phone":"+49 221/852946",
    "sg:postcode":"51103",
    "sg:province":"Nordrhein-Westfalen",
    "wof:name":"H. R\u00f6seler",
    "wof:placetype":"venue"
},
  "geometry": {"coordinates":[7.0109119415,50.940864563],"type":"Point"}
}