{
  "type": "Feature",
  "properties": {
    "iso:country":"DE",
    "sg:address":"Zeppelinstr. 12",
    "sg:city":"Donaueschingen",
    "sg:phone":"+49 771/2445",
    "sg:postcode":"78166",
    "sg:province":"Baden-W\u00fcrttemberg",
    "wof:name":"Kurt Gleichauf",
    "wof:placetype":"venue"
},
  "geometry": {"coordinates":[8.4959220886,47.9521827698],"type":"Point"}
}