{
  "type": "Feature",
  "properties": {
    "iso:country":"DE",
    "sg:address":"Zeppelinstr. 3",
    "sg:city":"Waiblingen",
    "sg:phone":"+49 7151/51871",
    "sg:postcode":"71332",
    "sg:province":"Baden-W\u00fcrttemberg",
    "wof:name":"Redaktion F Und I-bau Bauen Mit System",
    "wof:placetype":"venue"
},
  "geometry": {"coordinates":[9.2993383408,48.8297729492],"type":"Point"}
}