{
  "type": "Feature",
  "properties": {
    "iso:country":"DE",
    "sg:address":"Mommsenstr. 39",
    "sg:city":"K\u00f6ln",
    "sg:phone":"+49 221/432349",
    "sg:postcode":"50935",
    "sg:province":"Nordrhein-Westfalen",
    "wof:name":"Uwe J. Oldenburg",
    "wof:placetype":"venue"
},
  "geometry": {"coordinates":[6.9084849358,50.9206924438],"type":"Point"}
}