{
  "type": "Feature",
  "properties": {
    "iso:country":"DE",
    "sg:address":"Willibrordusstr. 48",
    "sg:city":"Grevenbroich",
    "sg:phone":"+49 2181/63688",
    "sg:postcode":"41517",
    "sg:province":"Nordrhein-Westfalen",
    "wof:name":"W. Vollberg",
    "wof:placetype":"venue"
},
  "geometry": {"coordinates":[6.5904269218,51.0678825378],"type":"Point"}
}