{
  "type": "Feature",
  "properties": {
    "iso:country":"DE",
    "sg:address":"Caspar-David-Friedrich-Str. 37",
    "sg:city":"Dresden",
    "sg:phone":"+49 351/877710",
    "sg:postcode":"01217",
    "sg:province":"Sachsen",
    "wof:name":"Hst-wks Hydro-system- Technik Gmbh",
    "wof:placetype":"venue"
},
  "geometry": {"coordinates":[13.7507314682,51.0222129822],"type":"Point"}
}