{
  "type": "Feature",
  "properties": {
    "iso:country":"DE",
    "sg:address":"Sch\u00fctzenstr. 3",
    "sg:city":"Peine",
    "sg:phone":"+49 5171/72878",
    "sg:postcode":"31224",
    "sg:province":"Niedersachsen",
    "wof:name":"K\u00fchn Sicherheitstechnik Gmbh",
    "wof:placetype":"venue"
},
  "geometry": {"coordinates":[10.231505,52.320408],"type":"Point"}
}