{
  "type": "Feature",
  "properties": {
    "iso:country":"DE",
    "sg:address":"Im Hammertal 72",
    "sg:city":"Witten",
    "sg:phone":"+49 2324/31677",
    "sg:postcode":"58456",
    "sg:province":"Nordrhein-Westfalen",
    "wof:name":"Blumenhaus Blankenagel",
    "wof:placetype":"venue"
},
  "geometry": {"coordinates":[7.26029,51.394192],"type":"Point"}
}