{
  "type": "Feature",
  "properties": {
    "iso:country":"DE",
    "sg:address":"Seilerweg 29",
    "sg:city":"Bad Hersfeld",
    "sg:phone":"+49 6621/880",
    "sg:postcode":"36251",
    "sg:province":"Hessen",
    "wof:name":"Krankenhausvollapotheke Im Kreiskrankenhaus",
    "wof:placetype":"venue"
},
  "geometry": {"coordinates":[9.712619,50.876144],"type":"Point"}
}