{
  "type": "Feature",
  "properties": {
    "iso:country":"DE",
    "sg:address":"Zur L\u00fcre 50",
    "sg:city":"H\u00f6xter",
    "sg:phone":"+49 5271/97120",
    "sg:postcode":"37671",
    "sg:province":"Nordrhein-Westfalen",
    "wof:name":"Andree B\u00fcrozentrum Gmbh & Co. Kg",
    "wof:placetype":"venue"
},
  "geometry": {"coordinates":[9.394623,51.783409],"type":"Point"}
}