{
  "type": "Feature",
  "properties": {
    "iso:country":"DE",
    "sg:address":"Spielmannsklinge 1",
    "sg:city":"Sinsheim",
    "sg:phone":"+49 7261/92820",
    "sg:postcode":"74889",
    "sg:province":"Baden-W\u00fcrttemberg",
    "wof:name":"Josef Koch Industrievertretungen Cdh",
    "wof:placetype":"venue"
},
  "geometry": {"coordinates":[8.8849430084,49.2529792786],"type":"Point"}
}