{
  "type": "Feature",
  "properties": {
    "iso:country":"DE",
    "sg:address":"Sommerswalder Chaussee 7",
    "sg:city":"Oberkr\u00e4mer",
    "sg:phone":"+49 33055/9870",
    "sg:postcode":"16727",
    "sg:province":"Brandenburg",
    "wof:name":"Shi Systemhaus F\u00fcr Integration Gmbh",
    "wof:placetype":"venue"
},
  "geometry": {"coordinates":[13.1025848389,52.7413368225],"type":"Point"}
}