{
  "type": "Feature",
  "properties": {
    "iso:country":"DE",
    "sg:address":"Markstr. 37",
    "sg:city":"Berlin",
    "sg:phone":"+49 30/49795590",
    "sg:postcode":"13409",
    "sg:province":"Berlin",
    "wof:name":"Ses Express Druck Gmbh",
    "wof:placetype":"venue"
},
  "geometry": {"coordinates":[13.365044,52.561211],"type":"Point"}
}