{
  "type": "Feature",
  "properties": {
    "iso:country":"DE",
    "sg:address":"Ringelsbruch 1",
    "sg:city":"Paderborn",
    "sg:postcode":"33106",
    "sg:province":"Nordrhein-Westfalen",
    "wof:name":"Peg Pader-entsorgungs Gmbh & Co. Kg",
    "wof:placetype":"venue"
},
  "geometry": {"coordinates":[8.685297,51.703655],"type":"Point"}
}