{
  "type": "Feature",
  "properties": {
    "iso:country":"DE",
    "sg:address":"Riedstr 4",
    "sg:city":"Ostrach",
    "sg:phone":"+49 7585/935380",
    "sg:postcode":"88356",
    "sg:province":"Baden-W\u00fcrttemberg",
    "wof:name":"Weimar Gmbh & Co Kg",
    "wof:placetype":"venue"
},
  "geometry": {"coordinates":[9.3801078796,47.9471473694],"type":"Point"}
}