{
  "type": "Feature",
  "properties": {
    "iso:country":"DE",
    "sg:address":"Am Dorfplatz 9",
    "sg:city":"M\u00f6ttingen",
    "sg:phone":"+49 9083/438",
    "sg:postcode":"86753",
    "sg:province":"Bayern",
    "wof:name":"Andreas L\u00f6fflad",
    "wof:placetype":"venue"
},
  "geometry": {"coordinates":[10.573936,48.828011],"type":"Point"}
}