{
  "type": "Feature",
  "properties": {
    "iso:country":"DE",
    "sg:address":"Beckergrube 29-33",
    "sg:city":"L\u00fcbeck",
    "sg:phone":"+49 451/77776",
    "sg:postcode":"23552",
    "sg:province":"Schleswig-Holstein",
    "wof:name":"Apotheke Am Theater",
    "wof:placetype":"venue"
},
  "geometry": {"coordinates":[10.685255,53.869492],"type":"Point"}
}