{
  "type": "Feature",
  "properties": {
    "iso:country":"DE",
    "sg:address":"Karpatenweg 2",
    "sg:city":"Limburgerhof",
    "sg:phone":"+49 6236/48152",
    "sg:postcode":"67117",
    "sg:province":"Rheinland-Pfalz",
    "wof:name":"Filmzeiten Film Und Video Produktion Gmbh",
    "wof:placetype":"venue"
},
  "geometry": {"coordinates":[8.3752841949,49.4239196777],"type":"Point"}
}