{
  "type": "Feature",
  "properties": {
    "iso:country":"DE",
    "sg:address":"Robert-Perthel-Str. 14",
    "sg:city":"K\u00f6ln",
    "sg:phone":"+49 221/173788",
    "sg:postcode":"50739",
    "sg:province":"Nordrhein-Westfalen",
    "wof:name":"Harald Breuer",
    "wof:placetype":"venue"
},
  "geometry": {"coordinates":[6.920561,50.979198],"type":"Point"}
}