{
  "type": "Feature",
  "properties": {
    "iso:country":"DE",
    "sg:address":"Kirchenstr. 68",
    "sg:city":"M\u00fcnchen",
    "sg:phone":"+49 89/229203",
    "sg:postcode":"81675",
    "sg:province":"Bayern",
    "wof:name":"J\u00fcrn D. Antritter Patentanwalt",
    "wof:placetype":"venue"
},
  "geometry": {"coordinates":[11.6056470871,48.1329803467],"type":"Point"}
}