{
  "type": "Feature",
  "properties": {
    "iso:country":"DE",
    "sg:address":"Karlstr. 11",
    "sg:city":"Fellbach",
    "sg:phone":"+49 711/9579770",
    "sg:postcode":"70734",
    "sg:province":"Baden-W\u00fcrttemberg",
    "wof:name":"Sch\u00e4fer Handels-gmbh",
    "wof:placetype":"venue"
},
  "geometry": {"coordinates":[9.281448,48.80711],"type":"Point"}
}