{
  "type": "Feature",
  "properties": {
    "iso:country":"DE",
    "sg:address":"Uenzen 13",
    "sg:city":"S\u00fcstedt",
    "sg:phone":"+49 4252/2011",
    "sg:postcode":"27305",
    "sg:province":"Niedersachsen",
    "wof:name":"Hermann Benjes Ingenieur",
    "wof:placetype":"venue"
},
  "geometry": {"coordinates":[8.9856996536,52.8220748901],"type":"Point"}
}