{
  "type": "Feature",
  "properties": {
    "iso:country":"DE",
    "sg:address":"Chausseestr. 75",
    "sg:city":"Marwitz",
    "sg:postcode":"16727",
    "sg:province":"Brandenburg",
    "wof:name":"Nh Massiv-haus Gmbh",
    "wof:placetype":"venue"
},
  "geometry": {"coordinates":[13.163577,52.677299],"type":"Point"}
}