{
  "type": "Feature",
  "properties": {
    "iso:country":"DE",
    "sg:address":"Mainstr. 121 B",
    "sg:city":"Neuss",
    "sg:phone":"+49 2137/8869",
    "sg:postcode":"41469",
    "sg:province":"Nordrhein-Westfalen",
    "wof:name":"Fitness-oase Felker",
    "wof:placetype":"venue"
},
  "geometry": {"coordinates":[6.7448840141,51.1513938904],"type":"Point"}
}