{
  "type": "Feature",
  "properties": {
    "iso:country":"DE",
    "sg:address":"Niebuhrstr. 54",
    "sg:city":"Bonn",
    "sg:phone":"+49 228/214574",
    "sg:postcode":"53113",
    "sg:province":"Nordrhein-Westfalen",
    "wof:name":"A. Kostka",
    "wof:placetype":"venue"
},
  "geometry": {"coordinates":[7.1081600189,50.724861145],"type":"Point"}
}