{
  "type": "Feature",
  "properties": {
    "iso:country":"DE",
    "sg:address":"Kilianstr. 10",
    "sg:city":"Heilbronn",
    "sg:phone":"+49 7131/60652",
    "sg:postcode":"74072",
    "sg:province":"Baden-W\u00fcrttemberg",
    "wof:name":"Werner Dietle Finanzberater",
    "wof:placetype":"venue"
},
  "geometry": {"coordinates":[9.2201385498,49.1409111023],"type":"Point"}
}