{
  "type": "Feature",
  "properties": {
    "iso:country":"DE",
    "sg:address":"Am Ro\u00dfacker 14",
    "sg:city":"Rosenheim",
    "sg:phone":"+49 8031/393208",
    "sg:postcode":"83022",
    "sg:province":"Bayern",
    "wof:name":"Utz Und Utz Rechtsanw\u00e4lte",
    "wof:placetype":"venue"
},
  "geometry": {"coordinates":[12.1192007065,47.8544616699],"type":"Point"}
}