{
  "type": "Feature",
  "properties": {
    "iso:country":"DE",
    "sg:address":"Hindenburgstr. 28",
    "sg:city":"Feuchtwangen",
    "sg:phone":"+49 9852/717",
    "sg:postcode":"91555",
    "sg:province":"Bayern",
    "wof:name":"Heinrich B\u00fcchler",
    "wof:placetype":"venue"
},
  "geometry": {"coordinates":[10.330175,49.16972],"type":"Point"}
}