{
  "type": "Feature",
  "properties": {
    "iso:country":"DE",
    "sg:address":"Glockenstr. 23",
    "sg:city":"Sch\u00f6neck",
    "sg:phone":"+49 6187/6191",
    "sg:postcode":"61137",
    "sg:province":"Hessen",
    "wof:name":"H. Bollenkamp",
    "wof:placetype":"venue"
},
  "geometry": {"coordinates":[8.8553390503,50.2033843994],"type":"Point"}
}