{
  "type": "Feature",
  "properties": {
    "iso:country":"DE",
    "sg:address":"Hohenmoorweg 8",
    "sg:city":"Bad Zwischenahn",
    "sg:phone":"+49 4403/8417",
    "sg:postcode":"26160",
    "sg:province":"Niedersachsen",
    "wof:name":"M. Und R. Otten",
    "wof:placetype":"venue"
},
  "geometry": {"coordinates":[7.994781,53.224743],"type":"Point"}
}