{
  "type": "Feature",
  "properties": {
    "iso:country":"DE",
    "sg:address":"Rosa-Luxemburg-Str. 15",
    "sg:city":"Herbsleben",
    "sg:phone":"+49 36041/42832",
    "sg:postcode":"99955",
    "sg:province":"Th\u00fcringen",
    "wof:name":"Harald M\u00f6ller",
    "wof:placetype":"venue"
},
  "geometry": {"coordinates":[10.833226,51.115158],"type":"Point"}
}