{
  "type": "Feature",
  "properties": {
    "iso:country":"DE",
    "sg:address":"Bleichstr. 77a",
    "sg:city":"Ortenberg",
    "sg:phone":"+49 6041/8681",
    "sg:postcode":"63683",
    "sg:province":"Hessen",
    "wof:name":"Walter Bickel Masseur",
    "wof:placetype":"venue"
},
  "geometry": {"coordinates":[9.048362,50.332169],"type":"Point"}
}