{
  "type": "Feature",
  "properties": {
    "iso:country":"DE",
    "sg:address":"Dorfstr. 82",
    "sg:city":"Bellingen",
    "sg:phone":"+49 39365/41045",
    "sg:postcode":"39579",
    "sg:province":"Sachsen-Anhalt",
    "wof:name":"Horst Wiesner",
    "wof:placetype":"venue"
},
  "geometry": {"coordinates":[11.83571,52.513569],"type":"Point"}
}