{
  "type": "Feature",
  "properties": {
    "iso:country":"DE",
    "sg:address":"Kirschallee 3",
    "sg:city":"Zerbst",
    "sg:phone":"+49 3923/780277",
    "sg:postcode":"39261",
    "sg:province":"Sachsen-Anhalt",
    "wof:name":"Bkb-verwaltungs-gmbh",
    "wof:placetype":"venue"
},
  "geometry": {"coordinates":[12.102694,51.95293],"type":"Point"}
}