{
  "type": "Feature",
  "properties": {
    "iso:country":"DE",
    "sg:address":"Goldammerweg 189",
    "sg:city":"K\u00f6ln",
    "sg:phone":"+49 221/583145",
    "sg:postcode":"50829",
    "sg:province":"Nordrhein-Westfalen",
    "wof:name":"Willi Engels Steuerberater",
    "wof:placetype":"venue"
},
  "geometry": {"coordinates":[6.8706102371,50.9626159668],"type":"Point"}
}