{
  "type": "Feature",
  "properties": {
    "iso:country":"DE",
    "sg:address":"F\u00fcllerstr. 49",
    "sg:city":"Frankfurt",
    "sg:phone":"+49 69/514839",
    "sg:postcode":"60431",
    "sg:province":"Hessen",
    "wof:name":"Br\u00fcckmann Ger\u00fcstbau- Und Bedachungs Gmbh",
    "wof:placetype":"venue"
},
  "geometry": {"coordinates":[8.650731,50.141079],"type":"Point"}
}