{
  "type": "Feature",
  "properties": {
    "iso:country":"DE",
    "sg:address":"Zuschka 4",
    "sg:city":"Cottbus",
    "sg:postcode":"03044",
    "sg:province":"Brandenburg",
    "wof:name":"1a Kartenleser, Torantriebe & Kundenkarten.",
    "wof:placetype":"venue"
},
  "geometry": {"coordinates":[14.341395,51.785564],"type":"Point"}
}