{
  "type": "Feature",
  "properties": {
    "iso:country":"DE",
    "sg:address":"Gr\u00f6\u00dfinger Ring 17",
    "sg:city":"Kienberg",
    "sg:phone":"+49 8628/373",
    "sg:postcode":"83361",
    "sg:province":"Bayern",
    "wof:name":"Georg Demmelmaier",
    "wof:placetype":"venue"
},
  "geometry": {"coordinates":[12.467748642,48.0334701538],"type":"Point"}
}