{
  "type": "Feature",
  "properties": {
    "iso:country":"DE",
    "sg:address":"Luitpoldring 30",
    "sg:city":"Vaterstetten",
    "sg:phone":"+49 8106/6474",
    "sg:postcode":"85591",
    "sg:province":"Bayern",
    "wof:name":"Gerd Zimmermann",
    "wof:placetype":"venue"
},
  "geometry": {"coordinates":[11.7696752548,48.100982666],"type":"Point"}
}