{
  "type": "Feature",
  "properties": {
    "iso:country":"DE",
    "sg:address":"Am Schleglhof 15",
    "sg:city":"Aresing",
    "sg:postcode":"86561",
    "sg:province":"Bayern",
    "wof:name":"Ics Gmbh",
    "wof:placetype":"venue"
},
  "geometry": {"coordinates":[11.3007488251,48.5334243774],"type":"Point"}
}