{
  "type": "Feature",
  "properties": {
    "iso:country":"DE",
    "sg:address":"Kolpingstr 49",
    "sg:city":"Vechta",
    "sg:phone":"+49 4441/921028",
    "sg:postcode":"49377",
    "sg:province":"Niedersachsen",
    "wof:name":"Veranstaltungstechnik Acoustic Sound Gmbh",
    "wof:placetype":"venue"
},
  "geometry": {"coordinates":[8.2857494354,52.7318687439],"type":"Point"}
}