{
  "type": "Feature",
  "properties": {
    "iso:country":"DE",
    "sg:address":"Lehmgrubenstr. 4",
    "sg:city":"Kist",
    "sg:phone":"+49 9306/99306",
    "sg:postcode":"97270",
    "sg:province":"Bayern",
    "wof:name":"Wolfgang Schwarz Steuerberater",
    "wof:placetype":"venue"
},
  "geometry": {"coordinates":[9.8446922302,49.7430992126],"type":"Point"}
}