{
  "type": "Feature",
  "properties": {
    "iso:country":"DE",
    "sg:address":"Westliche Ringstr. 6",
    "sg:city":"K\u00f6sching",
    "sg:phone":"+49 8404/930180",
    "sg:postcode":"85092",
    "sg:province":"Bayern",
    "wof:name":"Gh-telekommunikation Gr\u00f6schel & Heisler Gbr",
    "wof:placetype":"venue"
},
  "geometry": {"coordinates":[11.5428552628,48.8321800232],"type":"Point"}
}