{
  "type": "Feature",
  "properties": {
    "iso:country":"DE",
    "sg:address":"Aachener Str. 201-209",
    "sg:city":"K\u00f6ln",
    "sg:phone":"+49 221/404200",
    "sg:postcode":"50931",
    "sg:province":"Nordrhein-Westfalen",
    "wof:name":"Rad & Extras Raya Keller",
    "wof:placetype":"venue"
},
  "geometry": {"coordinates":[6.922823,50.936493],"type":"Point"}
}