{
  "type": "Feature",
  "properties": {
    "iso:country":"DE",
    "sg:address":"Flachstr. 11",
    "sg:city":"Wiesbaden",
    "sg:phone":"+49 4977/3213883",
    "sg:postcode":"65197",
    "sg:province":"Hessen",
    "wof:name":"Buchbinderei Ehe Gmbh",
    "wof:placetype":"venue"
},
  "geometry": {"coordinates":[8.9770021439,47.7527313232],"type":"Point"}
}