{
  "type": "Feature",
  "properties": {
    "iso:country":"DE",
    "sg:address":"Wolfersh\u00e4user Str. 9",
    "sg:city":"Felsberg",
    "sg:phone":"+49 5662/91008",
    "sg:postcode":"34587",
    "sg:province":"Hessen",
    "wof:name":"Christa Stock",
    "wof:placetype":"venue"
},
  "geometry": {"coordinates":[9.4397497177,51.1700057983],"type":"Point"}
}