{
  "type": "Feature",
  "properties": {
    "iso:country":"DE",
    "sg:address":"Heidelberger Landstr. 300",
    "sg:city":"Darmstadt",
    "sg:phone":"+49 6151/593710",
    "sg:postcode":"64297",
    "sg:province":"Hessen",
    "wof:name":"Eveline Schneider",
    "wof:placetype":"venue"
},
  "geometry": {"coordinates":[8.6444425583,49.8120918274],"type":"Point"}
}