{
  "type": "Feature",
  "properties": {
    "iso:country":"DE",
    "sg:address":"Sandbuck 1",
    "sg:city":"Windsbach",
    "sg:phone":"+49 9871/9171",
    "sg:postcode":"91575",
    "sg:province":"Bayern",
    "wof:name":"Georg Gugel",
    "wof:placetype":"venue"
},
  "geometry": {"coordinates":[10.821177,49.250565],"type":"Point"}
}