{
  "type": "Feature",
  "properties": {
    "iso:country":"DE",
    "sg:address":"Flughafenstr 100",
    "sg:city":"N\u00fcrnberg",
    "sg:phone":"+49 711/7973090",
    "sg:postcode":"90411",
    "sg:province":"Bayern",
    "wof:name":"Itg Gmbh",
    "wof:placetype":"venue"
},
  "geometry": {"coordinates":[11.080019,49.493393],"type":"Point"}
}