{
  "type": "Feature",
  "properties": {
    "iso:country":"DE",
    "sg:address":"R\u00fcttenscheider Str. 126",
    "sg:city":"Essen",
    "sg:phone":"+49 201/780354",
    "sg:postcode":"45131",
    "sg:province":"Nordrhein-Westfalen",
    "wof:name":"Pizza Expre\u00df",
    "wof:placetype":"venue"
},
  "geometry": {"coordinates":[7.0039129257,51.4325561523],"type":"Point"}
}