{
  "type": "Feature",
  "properties": {
    "iso:country":"DE",
    "sg:address":"Solothurner Str. 19",
    "sg:city":"M\u00fcnchen",
    "sg:phone":"+49 89/753813",
    "sg:postcode":"81475",
    "sg:province":"Bayern",
    "wof:name":"Alfred Leinauer Architekt",
    "wof:placetype":"venue"
},
  "geometry": {"coordinates":[11.484701,48.089371],"type":"Point"}
}