{
  "type": "Feature",
  "properties": {
    "iso:country":"DE",
    "sg:address":"Kr\u00fcmmelweg 14",
    "sg:city":"Wathlingen",
    "sg:phone":"+49 5144/92292",
    "sg:postcode":"29339",
    "sg:province":"Niedersachsen",
    "wof:name":"C. Busch Imobilienmakler",
    "wof:placetype":"venue"
},
  "geometry": {"coordinates":[10.1494989395,52.5325279236],"type":"Point"}
}