{
  "type": "Feature",
  "properties": {
    "iso:country":"DE",
    "sg:address":"M\u00f6rnerstr 45",
    "sg:city":"Bornheim",
    "sg:phone":"+49 2222/934090",
    "sg:postcode":"53332",
    "sg:province":"Nordrhein-Westfalen",
    "wof:name":"Biosense Labor F\u00fcr Biologische Sensorik Quintern & Holtschmidt",
    "wof:placetype":"venue"
},
  "geometry": {"coordinates":[7.0077872276,50.7589569092],"type":"Point"}
}