{
  "type": "Feature",
  "properties": {
    "iso:country":"DE",
    "sg:address":"Augustenstr. 1",
    "sg:city":"Fellbach",
    "sg:phone":"+49 711/5185850",
    "sg:postcode":"70736",
    "sg:province":"Baden-W\u00fcrttemberg",
    "wof:name":"Hotel B\u00fcrkle",
    "wof:placetype":"venue"
},
  "geometry": {"coordinates":[9.2680797577,48.8268966675],"type":"Point"}
}