{
  "type": "Feature",
  "properties": {
    "iso:country":"DE",
    "sg:address":"R-Luxemburg-Str.03",
    "sg:city":"Templin",
    "sg:postcode":"17268",
    "sg:province":"Brandenburg",
    "wof:name":"1 A Visitenkarten",
    "wof:placetype":"venue"
},
  "geometry": {"coordinates":[13.528618,52.99313],"type":"Point"}
}