{
  "type": "Feature",
  "properties": {
    "iso:country":"DE",
    "sg:address":"Am Heesen 4",
    "sg:city":"Hamburg",
    "sg:phone":"+49 40/7384473",
    "sg:postcode":"21033",
    "sg:province":"Hamburg",
    "wof:name":"Monika Maas Rechtsanw\u00e4ltin",
    "wof:placetype":"venue"
},
  "geometry": {"coordinates":[10.1662693024,53.5135726929],"type":"Point"}
}