{
  "type": "Feature",
  "properties": {
    "iso:country":"DE",
    "sg:address":"Gottswaldstr. 51a",
    "sg:city":"Offenburg",
    "sg:phone":"+49 781/57086",
    "sg:postcode":"77656",
    "sg:province":"Baden-W\u00fcrttemberg",
    "wof:name":"Hartmut Vetter",
    "wof:placetype":"venue"
},
  "geometry": {"coordinates":[7.9025301933,48.4869728088],"type":"Point"}
}