{
  "type": "Feature",
  "properties": {
    "iso:country":"DE",
    "sg:address":"Dorfstr. 7",
    "sg:city":"Immenhausen",
    "sg:phone":"+49 5673/5975",
    "sg:postcode":"34376",
    "sg:province":"Hessen",
    "wof:name":"Erwin Massie",
    "wof:placetype":"venue"
},
  "geometry": {"coordinates":[9.489441,51.452751],"type":"Point"}
}