{
  "type": "Feature",
  "properties": {
    "iso:country":"DE",
    "sg:address":"Max-Planck-Str. 19",
    "sg:city":"R\u00f6dermark",
    "sg:phone":"+49 4960/7489480",
    "sg:postcode":"63322",
    "sg:province":"Hessen",
    "wof:name":"Riedel Engineering Gmbh",
    "wof:placetype":"venue"
},
  "geometry": {"coordinates":[8.8207302094,49.9703330994],"type":"Point"}
}