{
  "type": "Feature",
  "properties": {
    "iso:country":"DE",
    "sg:address":"Gustav-Freytag-Str. 30",
    "sg:city":"Dresden",
    "sg:phone":"+49 351/3102251",
    "sg:postcode":"01277",
    "sg:province":"Sachsen",
    "wof:name":"Anita Seifert",
    "wof:placetype":"venue"
},
  "geometry": {"coordinates":[13.812191,51.042179],"type":"Point"}
}