{
  "type": "Feature",
  "properties": {
    "iso:country":"DE",
    "sg:address":"Ohlhammer Weg 7",
    "sg:city":"Nordenham",
    "sg:phone":"+49 4731/39429",
    "sg:postcode":"26954",
    "sg:province":"Niedersachsen",
    "wof:name":"Siegfried Lippa Architekt",
    "wof:placetype":"venue"
},
  "geometry": {"coordinates":[8.48108,53.522991],"type":"Point"}
}