{
  "type": "Feature",
  "properties": {
    "iso:country":"DE",
    "sg:address":"Marktplatz 2",
    "sg:city":"Offenbach",
    "sg:phone":"+49 69/888493",
    "sg:postcode":"63065",
    "sg:province":"Hessen",
    "wof:name":"Marktgrill Sabih",
    "wof:placetype":"venue"
},
  "geometry": {"coordinates":[8.7643470764,50.1041412354],"type":"Point"}
}