{
  "type": "Feature",
  "properties": {
    "iso:country":"DE",
    "sg:address":"Willhoop 1::",
    "sg:city":"Hamburg",
    "sg:href":"http://api.simplegeo.com/1.0/features/SG_1B1p38SIxc4cuG0nRWTPsg_53.612656_9.966327@1306268793.json",
    "sg:phone":"+49 40/5549560",
    "sg:postcode":"22453",
    "sg:province":"Hamburg",
    "wof:name":"Grenke Leasing Ag Niederlassung Hamburg",
    "wof:placetype":"venue"
},
  "geometry": {"coordinates":[9.966327,53.612656],"type":"Point"}
}