{"geometry":{"type":"Point","coordinates":[9.966327,53.612656]},"type":"Feature","id":102560273,"bbox":[9.966327,53.612656,9.966327,53.612656],"properties":{"sg:province":"Hamburg","geom:longitude":9.966327,"wof:breaches":[],"sg:href":"http://api.simplegeo.com/1.0/features/SG_1B1p38SIxc4cuG0nRWTPsg_53.612656_9.966327@1306268793.json","sg:owner":"simplegeo","sg:postcode":"22453","geom:latitude":53.612656,"sg:classifiers":[],"sg:address":"Willhoop 1::","sg:phone":"+49 40/5549560","wof:hierarchy":[{"venue_id":102560273,"region_id":85682505,"country_id":85633111,"locality_id":101748841,"county_id":102064053,"neighbourhood_id":85898947}],"geom:area":0.000000,"sg:city":"Hamburg","wof:lastmodified":1438093223,"iso:country":"DE","wof:geomhash":"e0b0054e7d9bcc339414509873b354dc","wof:name":"Grenke Leasing Ag Niederlassung Hamburg","wof:belongsto":[85682505,85633111,101748841,102064053,85898947],"src:geom":"simplegeo","wof:placetype":"venue","wof:supersedes":[],"wof:id":102560273,"wof:superseded_by":[],"wof:concordances":{"sg:id":"SG_1B1p38SIxc4cuG0nRWTPsg_53.612656_9.966327@1306268793"},"wof:parent_id":85898947}}