{
  "type": "Feature",
  "properties": {
    "iso:country":"DE",
    "sg:address":"Aufeldstr. 3",
    "sg:city":"Landsberg",
    "sg:phone":"+49 8191/4054",
    "sg:postcode":"86899",
    "sg:province":"Bayern",
    "wof:name":"Pension Aufeld",
    "wof:placetype":"venue"
},
  "geometry": {"coordinates":[10.8817653656,48.014125824],"type":"Point"}
}