{
  "type": "Feature",
  "properties": {
    "iso:country":"DE",
    "sg:address":"Gildehauser Str. 68",
    "sg:city":"Gronau",
    "sg:phone":"+49 2562/5180",
    "sg:postcode":"48599",
    "sg:province":"Nordrhein-Westfalen",
    "wof:name":"Antike Fundgrube",
    "wof:placetype":"venue"
},
  "geometry": {"coordinates":[7.0330781937,52.2153091431],"type":"Point"}
}