{
  "type": "Feature",
  "properties": {
    "iso:country":"DE",
    "sg:address":"Kieler Str. 4",
    "sg:city":"Eckernf\u00f6rde",
    "sg:phone":"+49 4351/3252",
    "sg:postcode":"24340",
    "sg:province":"Schleswig-Holstein",
    "wof:name":"Heike Jessen",
    "wof:placetype":"venue"
},
  "geometry": {"coordinates":[9.8364744186,54.4721298218],"type":"Point"}
}