{
  "type": "Feature",
  "properties": {
    "iso:country":"DE",
    "sg:address":"Am Steingrab 10",
    "sg:city":"Meppen",
    "sg:phone":"+49 5966/458",
    "sg:postcode":"49716",
    "sg:province":"Niedersachsen",
    "wof:name":"Hermann Wessels",
    "wof:placetype":"venue"
},
  "geometry": {"coordinates":[7.398887,52.735043],"type":"Point"}
}