{
  "type": "Feature",
  "properties": {
    "iso:country":"DE",
    "sg:address":"Wilhelm-Raabe-Str. 3",
    "sg:city":"B\u00fcckeburg",
    "sg:phone":"+49 5722/5096",
    "sg:postcode":"31675",
    "sg:province":"Niedersachsen",
    "wof:name":"Centralkauf",
    "wof:placetype":"venue"
},
  "geometry": {"coordinates":[9.0327196121,52.2619056702],"type":"Point"}
}