{
  "type": "Feature",
  "properties": {
    "iso:country":"DE",
    "sg:address":"Eichenbergstr. 2",
    "sg:city":"Ringgau",
    "sg:phone":"+49 5659/412",
    "sg:postcode":"37296",
    "sg:province":"Hessen",
    "wof:name":"A. Fey",
    "wof:placetype":"venue"
},
  "geometry": {"coordinates":[10.134148,51.073917],"type":"Point"}
}