{
  "type": "Feature",
  "properties": {
    "iso:country":"DE",
    "sg:address":"Anckelmannstr. 13",
    "sg:city":"Hamburg",
    "sg:phone":"+49 40/2509558",
    "sg:postcode":"20537",
    "sg:province":"Hamburg",
    "wof:name":"Jamka Und Hemsen-loth Rechtsanw\u00e4ltinnen",
    "wof:placetype":"venue"
},
  "geometry": {"coordinates":[10.0296802521,53.5527992249],"type":"Point"}
}