{
  "type": "Feature",
  "properties": {
    "iso:country":"DE",
    "sg:address":"Fronm\u00fcllerstr. 185",
    "sg:city":"F\u00fcrth",
    "sg:phone":"+49 911/78242",
    "sg:postcode":"90763",
    "sg:province":"Bayern",
    "wof:name":"Fgv Immobilien Gmbh",
    "wof:placetype":"venue"
},
  "geometry": {"coordinates":[11.0098981857,49.4614639282],"type":"Point"}
}