{
  "type": "Feature",
  "properties": {
    "iso:country":"DE",
    "sg:address":"Weidenstr. 5",
    "sg:city":"Hohensch\u00e4ftlarn",
    "sg:phone":"+49 8178/3066",
    "sg:postcode":"82069",
    "sg:province":"Bayern",
    "wof:name":"Dipl. Ing. Herbert Supe Architekt",
    "wof:placetype":"venue"
},
  "geometry": {"coordinates":[11.442091,47.989208],"type":"Point"}
}