{
  "type": "Feature",
  "properties": {
    "iso:country":"DE",
    "sg:address":"Feldstr. 22",
    "sg:city":"Meerbusch",
    "sg:phone":"+49 2132/93890",
    "sg:postcode":"40667",
    "sg:province":"Nordrhein-Westfalen",
    "wof:name":"Mt Legierungen Gmbh",
    "wof:placetype":"venue"
},
  "geometry": {"coordinates":[6.6948409081,51.251285553],"type":"Point"}
}