{
  "type": "Feature",
  "properties": {
    "iso:country":"DE",
    "sg:address":"Schulberg 10",
    "sg:city":"Dornstetten",
    "sg:phone":"+49 7443/7128",
    "sg:postcode":"72280",
    "sg:province":"Baden-W\u00fcrttemberg",
    "wof:name":"D. Hornberger",
    "wof:placetype":"venue"
},
  "geometry": {"coordinates":[8.479707,48.467297],"type":"Point"}
}