{
  "type": "Feature",
  "properties": {
    "iso:country":"DE",
    "sg:address":"Salzstr. 18",
    "sg:city":"Coswig",
    "sg:phone":"+49 3523/8100",
    "sg:postcode":"01640",
    "sg:province":"Sachsen",
    "wof:name":"Kaufland Warenhandel Ost-sachsen Gmbh & Co. Kg",
    "wof:placetype":"venue"
},
  "geometry": {"coordinates":[13.5849647522,51.1328659058],"type":"Point"}
}