{
  "type": "Feature",
  "properties": {
    "iso:country":"DE",
    "sg:address":"L\u00fcchower Str. 9",
    "sg:city":"Clenze",
    "sg:phone":"+49 5844/220",
    "sg:postcode":"29459",
    "sg:province":"Niedersachsen",
    "wof:name":"Elfriede A\u00dfmann",
    "wof:placetype":"venue"
},
  "geometry": {"coordinates":[10.957765,52.936634],"type":"Point"}
}