{
  "type": "Feature",
  "properties": {
    "iso:country":"DE",
    "sg:address":"Himberger Str. 10",
    "sg:city":"Bad Honnef",
    "sg:phone":"+49 2224/82149",
    "sg:postcode":"53604",
    "sg:province":"Nordrhein-Westfalen",
    "wof:name":"Hornecker Und Meinerz In Partnerschaft",
    "wof:placetype":"venue"
},
  "geometry": {"coordinates":[7.310323,50.646748],"type":"Point"}
}