{
  "type": "Feature",
  "properties": {
    "iso:country":"DE",
    "sg:address":"\u00d6hringer Str 26",
    "sg:city":"Gro\u00dfenhain",
    "sg:phone":"+49 3522/63097",
    "sg:postcode":"01558",
    "sg:province":"Sachsen",
    "wof:name":"Cws-werbung & Design",
    "wof:placetype":"venue"
},
  "geometry": {"coordinates":[13.531947,51.280075],"type":"Point"}
}