{
  "type": "Feature",
  "properties": {
    "iso:country":"DE",
    "sg:address":"Schweriner Str. 17",
    "sg:city":"Hamburg",
    "sg:phone":"+49 40/67561286",
    "sg:postcode":"22143",
    "sg:province":"Hamburg",
    "wof:name":"Marquard Immobilienmakler",
    "wof:placetype":"venue"
},
  "geometry": {"coordinates":[10.158949852,53.6051712036],"type":"Point"}
}