{
  "type": "Feature",
  "properties": {
    "iso:country":"DE",
    "sg:address":"Memelweg 1",
    "sg:city":"Gro\u00dfostheim",
    "sg:phone":"+49 6026/4222",
    "sg:postcode":"63762",
    "sg:province":"Bayern",
    "wof:name":"Dhk Grundst\u00fccks - Verwaltungs Gmbh",
    "wof:placetype":"venue"
},
  "geometry": {"coordinates":[9.032661,49.931656],"type":"Point"}
}