{
  "type": "Feature",
  "properties": {
    "iso:country":"DE",
    "sg:address":"Hauptstr. 17",
    "sg:city":"Mengkofen",
    "sg:phone":"+49 8733/930373",
    "sg:postcode":"84152",
    "sg:province":"Bayern",
    "wof:name":"Apotheke Zur Post Inh. Kurt Nagelstutz E. Kfm.",
    "wof:placetype":"venue"
},
  "geometry": {"coordinates":[12.443,48.721134],"type":"Point"}
}