{
  "type": "Feature",
  "properties": {
    "iso:country":"DE",
    "sg:address":"Ilexweg 35",
    "sg:city":"Wuppertal",
    "sg:phone":"+49 202/2775249",
    "sg:postcode":"42111",
    "sg:province":"Nordrhein-Westfalen",
    "wof:name":"Display Plus Werbemittel Gmbh",
    "wof:placetype":"venue"
},
  "geometry": {"coordinates":[7.1566510201,51.2943954468],"type":"Point"}
}