{
  "type": "Feature",
  "properties": {
    "iso:country":"DE",
    "sg:address":"Agnesstra\u00dfe 4",
    "sg:city":"Leipzig",
    "sg:phone":"+49 341/9111235",
    "sg:postcode":"04159",
    "sg:province":"Sachsen",
    "wof:name":"Trennung Von Schallbr\u00fccken",
    "wof:placetype":"venue"
},
  "geometry": {"coordinates":[12.330124855,51.3711776733],"type":"Point"}
}