{
  "type": "Feature",
  "properties": {
    "iso:country":"DE",
    "sg:address":"Ortsstr. 36 Eschenau",
    "sg:city":"Vellberg",
    "sg:phone":"+49 7907/2009",
    "sg:postcode":"74541",
    "sg:province":"Baden-W\u00fcrttemberg",
    "wof:name":"Friedrich Schumann Gmbh",
    "wof:placetype":"venue"
},
  "geometry": {"coordinates":[9.8802127838,49.0869865417],"type":"Point"}
}