{
  "type": "Feature",
  "properties": {
    "iso:country":"DE",
    "sg:address":"Friesenstr.1",
    "sg:city":"Hamburg",
    "sg:phone":"+49 421/3288890",
    "sg:postcode":"20097",
    "sg:province":"Hamburg",
    "wof:name":"Mlm Partner-ship Gmbh",
    "wof:placetype":"venue"
},
  "geometry": {"coordinates":[8.8046598434,53.0751609802],"type":"Point"}
}