{
  "type": "Feature",
  "properties": {
    "iso:country":"DE",
    "sg:address":"Robert-Bosch-Str. 26-28",
    "sg:city":"Linden",
    "sg:postcode":"35440",
    "sg:province":"Hessen",
    "wof:name":"Wellness Park Linden E. K.",
    "wof:placetype":"venue"
},
  "geometry": {"coordinates":[8.6568670273,50.5378341675],"type":"Point"}
}