{
  "type": "Feature",
  "properties": {
    "iso:country":"DE",
    "sg:address":"Pfarrstr. 9",
    "sg:city":"Lichtenau",
    "sg:phone":"+49 7227/2794",
    "sg:postcode":"77839",
    "sg:province":"Baden-W\u00fcrttemberg",
    "wof:name":"Ev. Pfarramt",
    "wof:placetype":"venue"
},
  "geometry": {"coordinates":[8.0093297958,48.7256889343],"type":"Point"}
}