{
  "type": "Feature",
  "properties": {
    "iso:country":"DE",
    "sg:address":"Am Markt 48",
    "sg:city":"Wusterhausen",
    "sg:phone":"+49 33979/14365",
    "sg:postcode":"16868",
    "sg:province":"Brandenburg",
    "wof:name":"Rudolf Lehmann",
    "wof:placetype":"venue"
},
  "geometry": {"coordinates":[12.461907,52.888756],"type":"Point"}
}