{
  "type": "Feature",
  "properties": {
    "iso:country":"DE",
    "sg:address":"Forststr. 28",
    "sg:city":"Berlin",
    "sg:phone":"+49 30/8225792",
    "sg:postcode":"12163",
    "sg:province":"Berlin",
    "wof:name":"Karin Z\u00f6ller",
    "wof:placetype":"venue"
},
  "geometry": {"coordinates":[13.309585,52.465939],"type":"Point"}
}