{
  "type": "Feature",
  "properties": {
    "iso:country":"DE",
    "sg:address":"Ortlohstr. 232",
    "sg:city":"Recklinghausen",
    "sg:phone":"+49 2361/92760",
    "sg:postcode":"45663",
    "sg:province":"Nordrhein-Westfalen",
    "wof:name":"P. Hennecke Steuerberater",
    "wof:placetype":"venue"
},
  "geometry": {"coordinates":[7.2417697906,51.5932693481],"type":"Point"}
}