{
  "type": "Feature",
  "properties": {
    "iso:country":"DE",
    "sg:address":"Zeppelinstr. 138",
    "sg:city":"Pirmasens",
    "sg:phone":"+49 6331/55650",
    "sg:postcode":"66953",
    "sg:province":"Rheinland-Pfalz",
    "wof:name":"Texstyle E. K.",
    "wof:placetype":"venue"
},
  "geometry": {"coordinates":[7.6232690811,49.2053337097],"type":"Point"}
}