{
  "type": "Feature",
  "properties": {
    "iso:country":"DE",
    "sg:address":"B\u00e4ckerreuthweg 6",
    "sg:city":"Tiefenbach",
    "sg:phone":"+49 851/398320",
    "sg:postcode":"94113",
    "sg:province":"Bayern",
    "wof:name":"Djk Eintracht Patriching Willy Baumann",
    "wof:placetype":"venue"
},
  "geometry": {"coordinates":[13.4163484573,48.6107902527],"type":"Point"}
}