{
  "type": "Feature",
  "properties": {
    "iso:country":"DE",
    "sg:address":"Baumberger Str. 16",
    "sg:city":"Langenfeld",
    "sg:phone":"+49 2173/77075",
    "sg:postcode":"40764",
    "sg:province":"Nordrhein-Westfalen",
    "wof:name":"F. Pohlmann",
    "wof:placetype":"venue"
},
  "geometry": {"coordinates":[6.9247450829,51.1140518188],"type":"Point"}
}