{
  "type": "Feature",
  "properties": {
    "iso:country":"DE",
    "sg:address":"Streitbergstr. 56",
    "sg:city":"M\u00fcnchen",
    "sg:phone":"+49 89/8713479",
    "sg:postcode":"81249",
    "sg:province":"Bayern",
    "wof:name":"Christine Wei\u00df",
    "wof:placetype":"venue"
},
  "geometry": {"coordinates":[11.4160690308,48.1485214233],"type":"Point"}
}