{
  "type": "Feature",
  "properties": {
    "iso:country":"DE",
    "sg:address":"Friesenheimer Hauptstr. 4",
    "sg:city":"Friesenheim",
    "sg:phone":"+49 7821/67964",
    "sg:postcode":"77948",
    "sg:province":"Baden-W\u00fcrttemberg",
    "wof:name":"Willi Stocker",
    "wof:placetype":"venue"
},
  "geometry": {"coordinates":[7.8756670952,48.3734397888],"type":"Point"}
}