{
  "type": "Feature",
  "properties": {
    "iso:country":"DE",
    "sg:address":"Am Marstall 9",
    "sg:city":"Hannover",
    "sg:phone":"+49 511/325651",
    "sg:postcode":"30159",
    "sg:province":"Niedersachsen",
    "wof:name":"Cd-b\u00f6rse",
    "wof:placetype":"venue"
},
  "geometry": {"coordinates":[9.732711792,52.3740692139],"type":"Point"}
}