{
  "type": "Feature",
  "properties": {
    "iso:country":"DE",
    "sg:address":"Argelsrieder Feld 22",
    "sg:city":"We\u00dfling",
    "sg:phone":"+49 8153/90810",
    "sg:postcode":"82234",
    "sg:province":"Bayern",
    "wof:name":"Aps Pharma Gmbh",
    "wof:placetype":"venue"
},
  "geometry": {"coordinates":[11.2744827271,48.0813674927],"type":"Point"}
}