{
  "type": "Feature",
  "properties": {
    "iso:country":"DE",
    "sg:address":"Hechenwanger Str. 1",
    "sg:city":"Greifenberg",
    "sg:postcode":"86926",
    "sg:province":"Bayern",
    "wof:name":"Panta Holding Gmbh",
    "wof:placetype":"venue"
},
  "geometry": {"coordinates":[11.063321,48.067871],"type":"Point"}
}