{
  "type": "Feature",
  "properties": {
    "iso:country":"DE",
    "sg:address":"Ottostr 9",
    "sg:city":"Kaiserslautern",
    "sg:phone":"+49 631/362150",
    "sg:postcode":"67657",
    "sg:province":"Rheinland-Pfalz",
    "wof:name":"Voss & Kamb Und Partner Gmbh",
    "wof:placetype":"venue"
},
  "geometry": {"coordinates":[7.771998,49.44891],"type":"Point"}
}