{
  "type": "Feature",
  "properties": {
    "iso:country":"DE",
    "sg:address":"Placidusstr. 10",
    "sg:city":"Regensburg",
    "sg:phone":"+49 941/73047",
    "sg:postcode":"93053",
    "sg:province":"Bayern",
    "wof:name":"Rosa-m. Wiesner Steuerberaterin",
    "wof:placetype":"venue"
},
  "geometry": {"coordinates":[12.1068964005,49.0097961426],"type":"Point"}
}