{
  "type": "Feature",
  "properties": {
    "iso:country":"DE",
    "sg:address":"Rheinsberger Str. 29 a",
    "sg:city":"Berlin",
    "sg:postcode":"10435",
    "sg:province":"Berlin",
    "wof:name":"Ingrid Lehmann Styling Gmbh",
    "wof:placetype":"venue"
},
  "geometry": {"coordinates":[13.402995,52.538517],"type":"Point"}
}