{
  "type": "Feature",
  "properties": {
    "iso:country":"DE",
    "sg:address":"Bergkrug 67",
    "sg:city":"Helpsen",
    "sg:phone":"+49 5724/51144",
    "sg:postcode":"31691",
    "sg:province":"Niedersachsen",
    "wof:name":"Hohmeyer Kg",
    "wof:placetype":"venue"
},
  "geometry": {"coordinates":[9.1146697998,52.3137283325],"type":"Point"}
}