{
  "type": "Feature",
  "properties": {
    "iso:country":"DE",
    "sg:address":"Schl\u00fcchterner Str. 27",
    "sg:city":"Sinntal",
    "sg:phone":"+49 6664/7849",
    "sg:postcode":"36391",
    "sg:province":"Hessen",
    "wof:name":"Penny Gmbh",
    "wof:placetype":"venue"
},
  "geometry": {"coordinates":[9.6196584702,50.3138885498],"type":"Point"}
}