{
  "type": "Feature",
  "properties": {
    "iso:country":"DE",
    "sg:address":"Dorfstr. 74",
    "sg:city":"Kirchberg",
    "sg:postcode":"08107",
    "sg:province":"Sachsen",
    "wof:name":"Annette G\u00fcnther",
    "wof:placetype":"venue"
},
  "geometry": {"coordinates":[12.487653,50.604141],"type":"Point"}
}