{
  "type": "Feature",
  "properties": {
    "iso:country":"DE",
    "sg:address":"Konrad-Adenauer-Str. 15",
    "sg:city":"Linden",
    "sg:phone":"+49 4964/039700",
    "sg:postcode":"35440",
    "sg:province":"Hessen",
    "wof:name":"Albat + Wirsam Software Vertriebs Gmbh",
    "wof:placetype":"venue"
},
  "geometry": {"coordinates":[8.6668653488,50.5258560181],"type":"Point"}
}