{"geometry":{"type":"Point","coordinates":[8.295942,49.981857]},"type":"Feature","id":102560467,"bbox":[8.295942,49.981857,8.295942,49.981857],"properties":{"sg:province":"Rheinland-Pfalz","geom:longitude":8.295942,"wof:breaches":[],"sg:href":"http://api.simplegeo.com/1.0/features/SG_3Giijf9z3DlXXdD3UNzfdb_49.981857_8.295942@1306268793.json","sg:owner":"simplegeo","sg:postcode":"55130","geom:latitude":49.981857,"sg:classifiers":[],"sg:address":"G\u00f6ttelmannstr. 2 A::","sg:phone":"+49 6131/982240","wof:hierarchy":[{"locality_id":101748569,"venue_id":102560467,"country_id":85633111,"region_id":85682491,"county_id":102063557}],"geom:area":0.000000,"sg:city":"Mainz","wof:lastmodified":1438093261,"iso:country":"DE","wof:geomhash":"27e3863e94a53a16dedced5b56402aec","wof:name":"Munck, Schmitt & Partner Steuerberatungsgmbh","wof:belongsto":[101748569,85633111,85682491,102063557],"src:geom":"simplegeo","wof:placetype":"venue","wof:supersedes":[],"wof:id":102560467,"wof:superseded_by":[],"wof:concordances":{"sg:id":"SG_3Giijf9z3DlXXdD3UNzfdb_49.981857_8.295942@1306268793"},"wof:parent_id":101748569}}