{
  "type": "Feature",
  "properties": {
    "iso:country":"DE",
    "sg:address":"G\u00f6ttelmannstr. 2 A::",
    "sg:city":"Mainz",
    "sg:href":"http://api.simplegeo.com/1.0/features/SG_3Giijf9z3DlXXdD3UNzfdb_49.981857_8.295942@1306268793.json",
    "sg:phone":"+49 6131/982240",
    "sg:postcode":"55130",
    "sg:province":"Rheinland-Pfalz",
    "wof:name":"Munck, Schmitt & Partner Steuerberatungsgmbh",
    "wof:placetype":"venue"
},
  "geometry": {"coordinates":[8.295942,49.981857],"type":"Point"}
}