{
  "type": "Feature",
  "properties": {
    "iso:country":"DE",
    "sg:address":"Bahnhofstr. 27",
    "sg:city":"Jocketa",
    "sg:phone":"+49 37439/6596",
    "sg:postcode":"08543",
    "sg:province":"Sachsen",
    "wof:name":"Linden-apotheke",
    "wof:placetype":"venue"
},
  "geometry": {"coordinates":[12.17339,50.556652],"type":"Point"}
}