{
  "type": "Feature",
  "properties": {
    "iso:country":"DE",
    "sg:address":"Teichstr. 6",
    "sg:city":"Wiek",
    "sg:phone":"+49 38391/70748",
    "sg:postcode":"18556",
    "sg:province":"Mecklenburg-Vorpommern",
    "wof:name":"J\u00fcrgen Oppermann",
    "wof:placetype":"venue"
},
  "geometry": {"coordinates":[13.2967,54.622868],"type":"Point"}
}