{
  "type": "Feature",
  "properties": {
    "iso:country":"DE",
    "sg:address":"Rote M\u00fctze 8",
    "sg:city":"Neuenrade",
    "sg:phone":"+49 2392/61821",
    "sg:postcode":"58809",
    "sg:province":"Nordrhein-Westfalen",
    "wof:name":"Rudolf Siegel",
    "wof:placetype":"venue"
},
  "geometry": {"coordinates":[7.771279,51.277248],"type":"Point"}
}