{
  "type": "Feature",
  "properties": {
    "iso:country":"DE",
    "sg:address":"M\u00fchlstr. 1",
    "sg:city":"Eichendorf",
    "sg:phone":"+49 9956/421",
    "sg:postcode":"94428",
    "sg:province":"Bayern",
    "wof:name":"R. Buchner",
    "wof:placetype":"venue"
},
  "geometry": {"coordinates":[12.7578458786,48.6160469055],"type":"Point"}
}