{
  "type": "Feature",
  "properties": {
    "iso:country":"DE",
    "sg:address":"Heinrich-Hertz-Str. 32",
    "sg:city":"Filderstadt",
    "sg:phone":"+49 711/773077",
    "sg:postcode":"70794",
    "sg:province":"Baden-W\u00fcrttemberg",
    "wof:name":"Eismann Hydraulik Gmbh",
    "wof:placetype":"venue"
},
  "geometry": {"coordinates":[9.205065,48.655922],"type":"Point"}
}