{
  "type": "Feature",
  "properties": {
    "iso:country":"DE",
    "sg:address":"Bauernweg 65",
    "sg:city":"Dresden",
    "sg:postcode":"01109",
    "sg:province":"Sachsen",
    "wof:name":"Heike H\u00f6rtsch",
    "wof:placetype":"venue"
},
  "geometry": {"coordinates":[13.7389268875,51.1192779541],"type":"Point"}
}