{
  "type": "Feature",
  "properties": {
    "iso:country":"DE",
    "sg:address":"Junkersstr. 2",
    "sg:city":"Alzenau",
    "sg:postcode":"63755",
    "sg:province":"Bayern",
    "wof:name":"Dresel Textilpflege- Center Gmbh",
    "wof:placetype":"venue"
},
  "geometry": {"coordinates":[9.048359,50.091789],"type":"Point"}
}