{
  "type": "Feature",
  "properties": {
    "iso:country":"DE",
    "sg:address":"Scholzweg 5",
    "sg:city":"Wiesbaden",
    "sg:phone":"+49 611/66716",
    "sg:postcode":"65203",
    "sg:province":"Hessen",
    "wof:name":"Josef Dzygolu Gmbh",
    "wof:placetype":"venue"
},
  "geometry": {"coordinates":[8.246052742,50.0471153259],"type":"Point"}
}