{
  "type": "Feature",
  "properties": {
    "iso:country":"DE",
    "sg:address":"Im Avelertal 4",
    "sg:city":"Trier",
    "sg:phone":"+49 651/141266",
    "sg:postcode":"54295",
    "sg:province":"Rheinland-Pfalz",
    "wof:name":"E. Anton Gmbh",
    "wof:placetype":"venue"
},
  "geometry": {"coordinates":[6.669029,49.76342],"type":"Point"}
}