{
  "type": "Feature",
  "properties": {
    "iso:country":"DE",
    "sg:address":"Bogestr. 54-56",
    "sg:city":"Eitorf",
    "sg:phone":"+49 4922/438830",
    "sg:postcode":"53783",
    "sg:province":"Nordrhein-Westfalen",
    "wof:name":"Weco Pyrotechnische Fabrik Gmbh",
    "wof:placetype":"venue"
},
  "geometry": {"coordinates":[7.468134,50.769279],"type":"Point"}
}