{
  "type": "Feature",
  "properties": {
    "iso:country":"DE",
    "sg:address":"Kulmbacher Str. 26",
    "sg:city":"Trebgast",
    "sg:phone":"+49 9227/4923",
    "sg:postcode":"95367",
    "sg:province":"Bayern",
    "wof:name":"Rainer Lauterbach",
    "wof:placetype":"venue"
},
  "geometry": {"coordinates":[11.55022,50.070202],"type":"Point"}
}