{
  "type": "Feature",
  "properties": {
    "iso:country":"DE",
    "sg:address":"Duhlwiesen 8",
    "sg:city":"Weiler",
    "sg:postcode":"55413",
    "sg:province":"Rheinland-Pfalz",
    "wof:name":"Dentaltechnik Karl Ternes Verwaltungs Gmbh",
    "wof:placetype":"venue"
},
  "geometry": {"coordinates":[7.848796,50.010666],"type":"Point"}
}