{
  "type": "Feature",
  "properties": {
    "iso:country":"DE",
    "sg:address":"Wilhelm-Leuschner-Stra\u00dfe 69-77",
    "sg:city":"Frankfurt",
    "sg:postcode":"60329",
    "sg:province":"Hessen",
    "wof:name":"Bildungswerk Rhein/main E.v.",
    "wof:placetype":"venue"
},
  "geometry": {"coordinates":[8.667284,50.104023],"type":"Point"}
}