{
  "type": "Feature",
  "properties": {
    "iso:country":"DE",
    "sg:address":"Rudolf-Diesel-Str. 37",
    "sg:city":"Gro\u00df Ippener",
    "sg:postcode":"27243",
    "sg:province":"Niedersachsen",
    "wof:name":"Schmidt & G\u00fclling Transport Gmbh",
    "wof:placetype":"venue"
},
  "geometry": {"coordinates":[8.6223716736,52.9767837524],"type":"Point"}
}