{
  "type": "Feature",
  "properties": {
    "iso:country":"DE",
    "sg:address":"Gro\u00dfe Reichenstr. 27",
    "sg:city":"Hamburg",
    "sg:phone":"+49 40/3037660",
    "sg:postcode":"20457",
    "sg:province":"Hamburg",
    "wof:name":"Pilot Media Gmbh & Co. Kg",
    "wof:placetype":"venue"
},
  "geometry": {"coordinates":[9.99558,53.548332],"type":"Point"}
}