{
  "type": "Feature",
  "properties": {
    "iso:country":"DE",
    "sg:address":"Minervastr. 15a",
    "sg:city":"Hagen",
    "sg:phone":"+49 2331/330021",
    "sg:postcode":"58089",
    "sg:province":"Nordrhein-Westfalen",
    "wof:name":"Kuro-alarm Fabrikation Elektrotechn. Apparate Gmbh",
    "wof:placetype":"venue"
},
  "geometry": {"coordinates":[7.454153,51.352261],"type":"Point"}
}