{
  "type": "Feature",
  "properties": {
    "iso:country":"DE",
    "sg:address":"Hauptstra\u00dfe 78",
    "sg:city":"Emmendingen",
    "sg:phone":"+49 7641/572291",
    "sg:postcode":"79312",
    "sg:province":"Baden-W\u00fcrttemberg",
    "wof:name":"\u00d6schger Gmbh Dreh- Und Fr\u00e4stechnik",
    "wof:placetype":"venue"
},
  "geometry": {"coordinates":[7.8748040199,48.1051826477],"type":"Point"}
}