{
  "type": "Feature",
  "properties": {
    "iso:country":"DE",
    "sg:address":"Bahnhofstr. 2",
    "sg:city":"Ingelheim",
    "sg:postcode":"55218",
    "sg:province":"Rheinland-Pfalz",
    "wof:name":"Event 24 Geselschaft F\u00fcr Sponsoring Eventmarketing",
    "wof:placetype":"venue"
},
  "geometry": {"coordinates":[8.0534687042,49.975605011],"type":"Point"}
}