{
  "type": "Feature",
  "properties": {
    "iso:country":"DE",
    "sg:address":"Wiedehopfweg 19a",
    "sg:city":"Berlin",
    "sg:phone":"+49 30/6022027",
    "sg:postcode":"12351",
    "sg:province":"Berlin",
    "wof:name":"Gerhard Scholz",
    "wof:placetype":"venue"
},
  "geometry": {"coordinates":[13.469702,52.437801],"type":"Point"}
}