{
  "type": "Feature",
  "properties": {
    "iso:country":"DE",
    "sg:address":"Krusenberg 11",
    "sg:city":"Syke",
    "sg:postcode":"28857",
    "sg:province":"Niedersachsen",
    "wof:name":"Windpark Barrien Gmbh & Co. Betriebs Kg",
    "wof:placetype":"venue"
},
  "geometry": {"coordinates":[8.8345041275,52.9380607605],"type":"Point"}
}