{
  "type": "Feature",
  "properties": {
    "iso:country":"DE",
    "sg:address":"Beisselstr. 3",
    "sg:city":"Bergheim",
    "sg:phone":"+49 2271/8060",
    "sg:postcode":"50126",
    "sg:province":"Nordrhein-Westfalen",
    "wof:name":"Hotel Garni Meyer",
    "wof:placetype":"venue"
},
  "geometry": {"coordinates":[6.6398382187,50.9539794922],"type":"Point"}
}