{
  "type": "Feature",
  "properties": {
    "iso:country":"DE",
    "sg:address":"Hauptstr. 28",
    "sg:city":"Forchheim",
    "sg:phone":"+49 9191/2982",
    "sg:postcode":"91301",
    "sg:province":"Bayern",
    "wof:name":"Eiscafe Venezia",
    "wof:placetype":"venue"
},
  "geometry": {"coordinates":[11.058243,49.719772],"type":"Point"}
}