{
  "type": "Feature",
  "properties": {
    "iso:country":"DE",
    "sg:city":"Langelsheim",
    "sg:phone":"+49 5325/4740",
    "sg:postcode":"38685",
    "sg:province":"Niedersachsen",
    "wof:name":"D. Riekeberg B\u00e4ckerei",
    "wof:placetype":"venue"
},
  "geometry": {"coordinates":[10.33493,51.93911],"type":"Point"}
}