{
  "type": "Feature",
  "properties": {
    "iso:country":"DE",
    "sg:address":"Syassenstr. 13",
    "sg:city":"Brake",
    "sg:phone":"+49 4401/936000",
    "sg:postcode":"26919",
    "sg:province":"Niedersachsen",
    "wof:name":"Dt Datentechnik T\u00f6njes Gmbh",
    "wof:placetype":"venue"
},
  "geometry": {"coordinates":[8.478937149,53.3290214539],"type":"Point"}
}