{
  "type": "Feature",
  "properties": {
    "iso:country":"DE",
    "sg:address":"Glash\u00fctter Weg 15",
    "sg:city":"Norderstedt",
    "sg:phone":"+49 40/5229330",
    "sg:postcode":"22844",
    "sg:province":"Schleswig-Holstein",
    "wof:name":"Today-express Marion Prosch E. Kfr.",
    "wof:placetype":"venue"
},
  "geometry": {"coordinates":[10.0025939941,53.7147598267],"type":"Point"}
}