{
  "type": "Feature",
  "properties": {
    "iso:country":"DE",
    "sg:address":"Meerwiesertalweg 14",
    "sg:city":"Saarbr\u00fccken",
    "sg:phone":"+49 681/399829",
    "sg:postcode":"66123",
    "sg:province":"Saarland",
    "wof:name":"Martin Petri",
    "wof:placetype":"venue"
},
  "geometry": {"coordinates":[7.0102510452,49.2428817749],"type":"Point"}
}