{
  "type": "Feature",
  "properties": {
    "iso:country":"DE",
    "sg:address":"Hadamarer Str. 22",
    "sg:city":"Elz",
    "sg:phone":"+49 6431/53061",
    "sg:postcode":"65604",
    "sg:province":"Hessen",
    "wof:name":"Rrp Gmbh",
    "wof:placetype":"venue"
},
  "geometry": {"coordinates":[8.036741,50.415554],"type":"Point"}
}