{
  "type": "Feature",
  "properties": {
    "iso:country":"DE",
    "sg:address":"R\u00e4cknitzh\u00f6he 35",
    "sg:city":"Dresden",
    "sg:phone":"+49 351/4716377",
    "sg:postcode":"01217",
    "sg:province":"Sachsen",
    "wof:name":"Schmidt & Erler Hausver- Waltung Und Immobilien",
    "wof:placetype":"venue"
},
  "geometry": {"coordinates":[13.743215,51.023605],"type":"Point"}
}