{
  "type": "Feature",
  "properties": {
    "iso:country":"DE",
    "sg:address":"Buchenweg 23",
    "sg:city":"Leidersbach",
    "sg:phone":"+49 6028/5635",
    "sg:postcode":"63849",
    "sg:province":"Bayern",
    "wof:name":"Dieter Scherf",
    "wof:placetype":"venue"
},
  "geometry": {"coordinates":[9.2362546921,49.8993644714],"type":"Point"}
}