{
  "type": "Feature",
  "properties": {
    "iso:country":"DE",
    "sg:address":"Bachstr. 18",
    "sg:city":"Weissach",
    "sg:postcode":"71554",
    "sg:province":"Baden-W\u00fcrttemberg",
    "wof:name":"R & S Spedition Gmbh",
    "wof:placetype":"venue"
},
  "geometry": {"coordinates":[9.4889097214,48.9184913635],"type":"Point"}
}