{
  "type": "Feature",
  "properties": {
    "iso:country":"DE",
    "sg:address":"H\u00e4senberg 36",
    "sg:city":"Schwalmtal",
    "sg:phone":"+49 2163/49132",
    "sg:postcode":"41366",
    "sg:province":"Nordrhein-Westfalen",
    "wof:name":"Rigobert Roidl Steuerberater",
    "wof:placetype":"venue"
},
  "geometry": {"coordinates":[6.2697038651,51.2142944336],"type":"Point"}
}