{
  "type": "Feature",
  "properties": {
    "iso:country":"DE",
    "sg:address":"Kuckucksweg 10",
    "sg:city":"Dormagen",
    "sg:phone":"+49 2133/81241",
    "sg:postcode":"41540",
    "sg:province":"Nordrhein-Westfalen",
    "wof:name":"Marianne H\u00e4sselbart",
    "wof:placetype":"venue"
},
  "geometry": {"coordinates":[6.785609,51.077446],"type":"Point"}
}