{
  "type": "Feature",
  "properties": {
    "iso:country":"DE",
    "sg:address":"B\u00f6rstel 7",
    "sg:city":"Berge",
    "sg:phone":"+49 5435/415",
    "sg:postcode":"49626",
    "sg:province":"Niedersachsen",
    "wof:name":"Franz Bohmann",
    "wof:placetype":"venue"
},
  "geometry": {"coordinates":[7.7310600281,52.6205940247],"type":"Point"}
}