{
  "type": "Feature",
  "properties": {
    "iso:country":"DE",
    "sg:address":"Hammerplatz 5",
    "sg:city":"Plauen",
    "sg:phone":"+49 3741/201080",
    "sg:postcode":"08529",
    "sg:province":"Sachsen",
    "wof:name":"V. E. P. Baumaschinen Gmbh",
    "wof:placetype":"venue"
},
  "geometry": {"coordinates":[12.155666,50.503975],"type":"Point"}
}