{
  "type": "Feature",
  "properties": {
    "iso:country":"DE",
    "sg:address":"H\u00f6lderlinstr. 30",
    "sg:city":"Oberndorf",
    "sg:phone":"+49 7423/2309",
    "sg:postcode":"78727",
    "sg:province":"Baden-W\u00fcrttemberg",
    "wof:name":"Alfons Beck",
    "wof:placetype":"venue"
},
  "geometry": {"coordinates":[8.5774707794,48.2972450256],"type":"Point"}
}