{
  "type": "Feature",
  "properties": {
    "iso:country":"DE",
    "sg:address":"Moselstr. 44",
    "sg:city":"Rivenich",
    "sg:phone":"+49 6508/7575",
    "sg:postcode":"54518",
    "sg:province":"Rheinland-Pfalz",
    "wof:name":"Bernhard Niersbach",
    "wof:placetype":"venue"
},
  "geometry": {"coordinates":[6.846354,49.875717],"type":"Point"}
}