{
  "type": "Feature",
  "properties": {
    "iso:country":"DE",
    "sg:address":"Zentnerstr. 23",
    "sg:city":"M\u00fcnchen",
    "sg:postcode":"80798",
    "sg:province":"Bayern",
    "wof:name":"Ctm Gmbh Car Transfer And Management",
    "wof:placetype":"venue"
},
  "geometry": {"coordinates":[11.563744,48.157162],"type":"Point"}
}