{
  "type": "Feature",
  "properties": {
    "iso:country":"DE",
    "sg:address":"Gustav-Siegle-Str. 8",
    "sg:city":"Ditzingen",
    "sg:phone":"+49 4971/5696310",
    "sg:postcode":"71254",
    "sg:province":"Baden-W\u00fcrttemberg",
    "wof:name":"Glems-technik Gmbh Elektro- & Kaeltetechnische Erzeugnisse",
    "wof:placetype":"venue"
},
  "geometry": {"coordinates":[9.068247,48.820816],"type":"Point"}
}