{
  "type": "Feature",
  "properties": {
    "iso:country":"DE",
    "sg:address":"Sperlingsberg 4",
    "sg:city":"Ahlsdorf",
    "sg:phone":"+49 34772/27246",
    "sg:postcode":"06313",
    "sg:province":"Sachsen-Anhalt",
    "wof:name":"Otto Scherbe",
    "wof:placetype":"venue"
},
  "geometry": {"coordinates":[11.467492,51.542629],"type":"Point"}
}