{
  "type": "Feature",
  "properties": {
    "iso:country":"DE",
    "sg:address":"Karlstr. 24",
    "sg:city":"Eisenach",
    "sg:phone":"+49 3691/203411",
    "sg:postcode":"99817",
    "sg:province":"Th\u00fcringen",
    "wof:name":"Lothar Trabert",
    "wof:placetype":"venue"
},
  "geometry": {"coordinates":[10.3223590851,50.9748878479],"type":"Point"}
}