{
  "type": "Feature",
  "properties": {
    "iso:country":"DE",
    "sg:address":"Immenhof 2",
    "sg:city":"Bremen",
    "sg:phone":"+49 421/480088",
    "sg:postcode":"28307",
    "sg:province":"Bremen",
    "wof:name":"Rolf Dohrmann Kg",
    "wof:placetype":"venue"
},
  "geometry": {"coordinates":[8.948395,53.033035],"type":"Point"}
}