{
  "type": "Feature",
  "properties": {
    "iso:country":"DE",
    "sg:address":"Hemmstr. 346",
    "sg:city":"Bremen",
    "sg:phone":"+49 421/3760071",
    "sg:postcode":"28215",
    "sg:province":"Bremen",
    "wof:name":"Lancker",
    "wof:placetype":"venue"
},
  "geometry": {"coordinates":[8.814734,53.101936],"type":"Point"}
}