{
  "type": "Feature",
  "properties": {
    "iso:country":"DE",
    "sg:address":"Karl-Barth-Str. 137",
    "sg:city":"Bonn",
    "sg:phone":"+49 228/233652",
    "sg:postcode":"53129",
    "sg:province":"Nordrhein-Westfalen",
    "wof:name":"Room-service Oldie- Und Rock-band",
    "wof:placetype":"venue"
},
  "geometry": {"coordinates":[7.1176757812,50.7077827454],"type":"Point"}
}