{
  "type": "Feature",
  "properties": {
    "iso:country":"DE",
    "sg:address":"Nordring 35",
    "sg:city":"Dieburg",
    "sg:phone":"+49 6071/1677",
    "sg:postcode":"64807",
    "sg:province":"Hessen",
    "wof:name":"Dr. K. Busch Gmbh",
    "wof:placetype":"venue"
},
  "geometry": {"coordinates":[8.860167,49.913383],"type":"Point"}
}