{
  "type": "Feature",
  "properties": {
    "iso:country":"DE",
    "sg:address":"Stralauer Allee 35::",
    "sg:city":"Berlin",
    "sg:phone":"+49 4930/2933940",
    "sg:postcode":"10245",
    "sg:province":"Berlin",
    "wof:name":"Safety Transportgesellschaft Mbh",
    "wof:placetype":"venue"
},
  "geometry": {"coordinates":[13.452753,52.501236],"type":"Point"}
}