{
  "type": "Feature",
  "properties": {
    "iso:country":"DE",
    "sg:address":"Landwehrweg 16",
    "sg:city":"Buseck",
    "sg:phone":"+49 6408/3891",
    "sg:postcode":"35418",
    "sg:province":"Hessen",
    "wof:name":"P. Lombardi",
    "wof:placetype":"venue"
},
  "geometry": {"coordinates":[8.7889356613,50.603263855],"type":"Point"}
}