{
  "type": "Feature",
  "properties": {
    "iso:country":"DE",
    "sg:address":"Ostring 18",
    "sg:city":"Hochdorf",
    "sg:phone":"+49 7153/991010",
    "sg:postcode":"73269",
    "sg:province":"Baden-W\u00fcrttemberg",
    "wof:name":"Aris Gro\u00df- Und Industrieanlagen Gmbh",
    "wof:placetype":"venue"
},
  "geometry": {"coordinates":[9.475359,48.68996],"type":"Point"}
}