{
  "type": "Feature",
  "properties": {
    "iso:country":"DE",
    "sg:address":"Kornhausgasse 9",
    "sg:city":"Ulm",
    "sg:phone":"+49 731/966370",
    "sg:postcode":"89073",
    "sg:province":"Baden-W\u00fcrttemberg",
    "wof:name":"Christ Gmbh",
    "wof:placetype":"venue"
},
  "geometry": {"coordinates":[9.9961061478,48.399723053],"type":"Point"}
}