{
  "type": "Feature",
  "properties": {
    "iso:country":"DE",
    "sg:address":"Martin-Wohmannstr. 8a",
    "sg:city":"Hofheim",
    "sg:phone":"+49 177",
    "sg:postcode":"65719",
    "sg:province":"Hessen",
    "wof:name":"Personal-training Im Rhein-main Gebiet",
    "wof:placetype":"venue"
},
  "geometry": {"coordinates":[8.451831,50.091972],"type":"Point"}
}