{
  "type": "Feature",
  "properties": {
    "iso:country":"DE",
    "sg:address":"Daimlerstr. 12",
    "sg:city":"Frittlingen",
    "sg:phone":"+49 7426/7454",
    "sg:postcode":"78665",
    "sg:province":"Baden-W\u00fcrttemberg",
    "wof:name":"E. Faulhaber Chirug. Instrumente",
    "wof:placetype":"venue"
},
  "geometry": {"coordinates":[8.702731,48.130787],"type":"Point"}
}