{
  "type": "Feature",
  "properties": {
    "iso:country":"DE",
    "sg:address":"L\u00fcbecker Str. 5",
    "sg:city":"Laatzen",
    "sg:postcode":"30880",
    "sg:province":"Niedersachsen",
    "wof:name":"Sportstudio M. Schmidt Gmbh",
    "wof:placetype":"venue"
},
  "geometry": {"coordinates":[9.8299646378,52.2943916321],"type":"Point"}
}