{
  "type": "Feature",
  "properties": {
    "iso:country":"DE",
    "sg:address":"Robert-Koch-Str. 58",
    "sg:city":"Heidenheim",
    "sg:phone":"+49 7321/24351",
    "sg:postcode":"89522",
    "sg:province":"Baden-W\u00fcrttemberg",
    "wof:name":"Eugen Kruttschnitt Architekt",
    "wof:placetype":"venue"
},
  "geometry": {"coordinates":[10.166054,48.674454],"type":"Point"}
}