{
  "type": "Feature",
  "properties": {
    "iso:country":"DE",
    "sg:address":"Neuh\u00f6fer Str. 30",
    "sg:city":"Ludwigshafen",
    "sg:phone":"+49 621/543176",
    "sg:postcode":"67065",
    "sg:province":"Rheinland-Pfalz",
    "wof:name":"Frank Schindler Ingenieur",
    "wof:placetype":"venue"
},
  "geometry": {"coordinates":[8.4205179214,49.4398422241],"type":"Point"}
}