{
  "type": "Feature",
  "properties": {
    "iso:country":"DE",
    "sg:address":"Friesenstr 13",
    "sg:city":"Hamburg",
    "sg:phone":"+49 40/78860",
    "sg:postcode":"20097",
    "sg:province":"Hamburg",
    "wof:name":"Atos Origin Gmbh",
    "wof:placetype":"venue"
},
  "geometry": {"coordinates":[10.029545784,53.5436859131],"type":"Point"}
}