{
  "type": "Feature",
  "properties": {
    "iso:country":"DE",
    "sg:address":"Bornewasserweg 11",
    "sg:city":"Wittlich",
    "sg:phone":"+49 6571/3747",
    "sg:postcode":"54516",
    "sg:province":"Rheinland-Pfalz",
    "wof:name":"Norbert Kiesgen Gmbh",
    "wof:placetype":"venue"
},
  "geometry": {"coordinates":[6.943196,49.987663],"type":"Point"}
}