{
  "type": "Feature",
  "properties": {
    "iso:country":"DE",
    "sg:address":"Am Sonnenhof 5",
    "sg:city":"\u00dcbach-Palenberg",
    "sg:phone":"+49 2451/46628",
    "sg:postcode":"52531",
    "sg:province":"Nordrhein-Westfalen",
    "wof:name":"Franz-josef Lhomme Anlageberater",
    "wof:placetype":"venue"
},
  "geometry": {"coordinates":[6.1218481064,50.9297523499],"type":"Point"}
}