{
  "type": "Feature",
  "properties": {
    "iso:country":"DE",
    "sg:address":"Oberes Kelterfeld 17",
    "sg:city":"Oettingen",
    "sg:phone":"+49 9082/90076",
    "sg:postcode":"86732",
    "sg:province":"Bayern",
    "wof:name":"Schneider Pensionsver- Pflichtungs- Gmbh",
    "wof:placetype":"venue"
},
  "geometry": {"coordinates":[10.594121933,48.9594497681],"type":"Point"}
}