{
  "type": "Feature",
  "properties": {
    "iso:country":"DE",
    "sg:address":"In den Emsenwehren 6",
    "sg:city":"Bad Sulza",
    "sg:phone":"+49 36461/20433",
    "sg:postcode":"99518",
    "sg:province":"Th\u00fcringen",
    "wof:name":"Hotel-pension Haus Marie",
    "wof:placetype":"venue"
},
  "geometry": {"coordinates":[11.6278905869,51.0964317322],"type":"Point"}
}