{
  "type": "Feature",
  "properties": {
    "iso:country":"DE",
    "sg:address":"Nr. 32",
    "sg:city":"Altenbach",
    "sg:postcode":"04828",
    "sg:province":"Sachsen",
    "wof:name":"Gemeindeschwesterstation Altenbach",
    "wof:placetype":"venue"
},
  "geometry": {"coordinates":[12.693202,51.357124],"type":"Point"}
}