{
  "type": "Feature",
  "properties": {
    "iso:country":"DE",
    "sg:address":"Fichtenstrasse",
    "sg:city":"Fuerth",
    "sg:postcode":"90763",
    "sg:province":"Bayern",
    "wof:name":"Malermeister Appis",
    "wof:placetype":"venue"
},
  "geometry": {"coordinates":[10.984065,49.467331],"type":"Point"}
}