{
  "type": "Feature",
  "properties": {
    "iso:country":"DE",
    "sg:address":"Heckschenstr. 43",
    "sg:city":"Krefeld",
    "sg:phone":"+49 2151/540568",
    "sg:postcode":"47809",
    "sg:province":"Nordrhein-Westfalen",
    "wof:name":"Karl Motes Gmbh & Co. Steinbildhauer",
    "wof:placetype":"venue"
},
  "geometry": {"coordinates":[6.6186060905,51.3253822327],"type":"Point"}
}