{
  "type": "Feature",
  "properties": {
    "iso:country":"DE",
    "sg:address":"Miltenberger Str. 7",
    "sg:city":"B\u00fcrgstadt",
    "sg:phone":"+49 9371/7009",
    "sg:postcode":"63927",
    "sg:province":"Bayern",
    "wof:name":"Martins-apotheke",
    "wof:placetype":"venue"
},
  "geometry": {"coordinates":[9.268008,49.710667],"type":"Point"}
}