{
  "type": "Feature",
  "properties": {
    "iso:country":"DE",
    "sg:address":"Waisenhausstr. 13",
    "sg:city":"Seesen",
    "sg:phone":"+49 5381/1852",
    "sg:postcode":"38723",
    "sg:province":"Niedersachsen",
    "wof:name":"Herbert Rieke Architekt",
    "wof:placetype":"venue"
},
  "geometry": {"coordinates":[10.189239,51.890461],"type":"Point"}
}