{
  "type": "Feature",
  "properties": {
    "iso:country":"DE",
    "sg:address":"Hans-B\u00f6ckler-Str. 12",
    "sg:city":"Oelde",
    "sg:phone":"+49 2522/62416",
    "sg:postcode":"59302",
    "sg:province":"Nordrhein-Westfalen",
    "wof:name":"Mersmann Tennishalle",
    "wof:placetype":"venue"
},
  "geometry": {"coordinates":[8.1562776566,51.8399581909],"type":"Point"}
}