{
  "type": "Feature",
  "properties": {
    "iso:country":"DE",
    "sg:address":"Offlum 66",
    "sg:city":"Neuenkirchen",
    "sg:phone":"+49 5973/2751",
    "sg:postcode":"48485",
    "sg:province":"Nordrhein-Westfalen",
    "wof:name":"August G\u00f6cking",
    "wof:placetype":"venue"
},
  "geometry": {"coordinates":[7.344518,52.242435],"type":"Point"}
}