{
  "type": "Feature",
  "properties": {
    "iso:country":"DE",
    "sg:address":"Burgstr. 5",
    "sg:city":"Rodgau",
    "sg:phone":"+49 6106/13385",
    "sg:postcode":"63110",
    "sg:province":"Hessen",
    "wof:name":"D. Weber",
    "wof:placetype":"venue"
},
  "geometry": {"coordinates":[8.8799219131,50.0429344177],"type":"Point"}
}