{
  "type": "Feature",
  "properties": {
    "iso:country":"DE",
    "sg:address":"Sebastiansweg 4",
    "sg:city":"Olpe",
    "sg:phone":"+49 2761/63379",
    "sg:postcode":"57462",
    "sg:province":"Nordrhein-Westfalen",
    "wof:name":"Alw Ingenieurb\u00fcro Gmbh",
    "wof:placetype":"venue"
},
  "geometry": {"coordinates":[7.844656,51.035923],"type":"Point"}
}