{
  "type": "Feature",
  "properties": {
    "iso:country":"DE",
    "sg:address":"Weberweg 6",
    "sg:city":"Hamb\u00fchren",
    "sg:phone":"+49 5084/3789",
    "sg:postcode":"29313",
    "sg:province":"Niedersachsen",
    "wof:name":"Automations Elektronik Peer Tiemer",
    "wof:placetype":"venue"
},
  "geometry": {"coordinates":[9.963976,52.631992],"type":"Point"}
}