{
  "type": "Feature",
  "properties": {
    "iso:country":"DE",
    "sg:address":"Sophienstr 35",
    "sg:city":"M\u00f6nchengladbach",
    "sg:phone":"+49 2161/45021",
    "sg:postcode":"41065",
    "sg:province":"Nordrhein-Westfalen",
    "wof:name":"Vollmer, Eggen",
    "wof:placetype":"venue"
},
  "geometry": {"coordinates":[6.447398,51.193779],"type":"Point"}
}