{
  "type": "Feature",
  "properties": {
    "iso:country":"DE",
    "sg:address":"Sch\u00f6nbergstr. 21",
    "sg:city":"Hemau",
    "sg:phone":"+49 9491/708",
    "sg:postcode":"93155",
    "sg:province":"Bayern",
    "wof:name":"Mayer Bau Gmbh",
    "wof:placetype":"venue"
},
  "geometry": {"coordinates":[11.781231,49.057873],"type":"Point"}
}