{
  "type": "Feature",
  "properties": {
    "iso:country":"DE",
    "sg:address":"Rockwellstr. 1",
    "sg:city":"Gifhorn",
    "sg:postcode":"38518",
    "sg:province":"Niedersachsen",
    "wof:name":"Rockwell Golde Gmbh",
    "wof:placetype":"venue"
},
  "geometry": {"coordinates":[10.547700882,52.4578590393],"type":"Point"}
}