{
  "type": "Feature",
  "properties": {
    "iso:country":"DE",
    "sg:address":"Alter Teichsweg 4",
    "sg:city":"Duingen",
    "sg:phone":"+49 5185/1835",
    "sg:postcode":"31089",
    "sg:province":"Niedersachsen",
    "wof:name":"Gerhard Kaspar",
    "wof:placetype":"venue"
},
  "geometry": {"coordinates":[9.7063417435,52.0047073364],"type":"Point"}
}