{
  "type": "Feature",
  "properties": {
    "iso:country":"DE",
    "sg:address":"Maienwalterstr. 23",
    "sg:city":"Esslingen",
    "sg:phone":"+49 711/372255",
    "sg:postcode":"73733",
    "sg:province":"Baden-W\u00fcrttemberg",
    "wof:name":"Sonnen-apotheke",
    "wof:placetype":"venue"
},
  "geometry": {"coordinates":[9.299853,48.758102],"type":"Point"}
}