{
  "type": "Feature",
  "properties": {
    "iso:country":"DE",
    "sg:address":"Postfach",
    "sg:city":"Melle",
    "sg:postcode":"49324",
    "sg:province":"Niedersachsen",
    "wof:name":"Celtictouch - Der Zauberhafte Internetshop",
    "wof:placetype":"venue"
},
  "geometry": {"coordinates":[8.338544,52.201374],"type":"Point"}
}