{
  "type": "Feature",
  "properties": {
    "iso:country":"DE",
    "sg:address":"Alter Graben 47",
    "sg:city":"T\u00f6nisvorst",
    "sg:phone":"+49 2151/790252",
    "sg:postcode":"47918",
    "sg:province":"Nordrhein-Westfalen",
    "wof:name":"Winfried Abels",
    "wof:placetype":"venue"
},
  "geometry": {"coordinates":[6.4947590828,51.3214225769],"type":"Point"}
}