{
  "type": "Feature",
  "properties": {
    "iso:country":"DE",
    "sg:address":"Hochstr. 18a",
    "sg:city":"Waldbr\u00f6l",
    "sg:phone":"+49 2291/3533",
    "sg:postcode":"51545",
    "sg:province":"Nordrhein-Westfalen",
    "wof:name":"W. Stahl",
    "wof:placetype":"venue"
},
  "geometry": {"coordinates":[7.6177630424,50.8756484985],"type":"Point"}
}