{
  "type": "Feature",
  "properties": {
    "iso:country":"DE",
    "sg:address":"Westermannsgang 5",
    "sg:city":"Bremerhaven",
    "sg:phone":"+49 471/32445",
    "sg:postcode":"27570",
    "sg:province":"Bremen",
    "wof:name":"G. Harms",
    "wof:placetype":"venue"
},
  "geometry": {"coordinates":[8.5918874741,53.5217552185],"type":"Point"}
}