{
  "type": "Feature",
  "properties": {
    "iso:country":"DE",
    "sg:city":"Ha\u00dfmersheim",
    "sg:phone":"+49 4962/612182",
    "sg:postcode":"74855",
    "sg:province":"Baden-W\u00fcrttemberg",
    "wof:name":"Volksbank Eg",
    "wof:placetype":"venue"
},
  "geometry": {"coordinates":[9.14257,49.300491],"type":"Point"}
}