{
  "type": "Feature",
  "properties": {
    "iso:country":"DE",
    "sg:address":"Gundringhausen 1",
    "sg:city":"Hallenberg",
    "sg:postcode":"59969",
    "sg:province":"Nordrhein-Westfalen",
    "wof:name":"Kusch Verwaltungs Gmbh",
    "wof:placetype":"venue"
},
  "geometry": {"coordinates":[8.6204948425,51.1162567139],"type":"Point"}
}