{
  "type": "Feature",
  "properties": {
    "iso:country":"DE",
    "sg:address":"Arnst\u00e4dter Str. 26 a",
    "sg:city":"Ohrdruf",
    "sg:phone":"+49 3624/314137",
    "sg:postcode":"99885",
    "sg:province":"Th\u00fcringen",
    "wof:name":"Imbi\u00df-kleingastst\u00e4tte",
    "wof:placetype":"venue"
},
  "geometry": {"coordinates":[10.7398920059,50.8284034729],"type":"Point"}
}