{
  "type": "Feature",
  "properties": {
    "iso:country":"DE",
    "sg:address":"Habichtswaldstr. 30",
    "sg:city":"Schauenburg",
    "sg:phone":"+49 5601/5876",
    "sg:postcode":"34270",
    "sg:province":"Hessen",
    "wof:name":"Karsten Resch\u00b4s Refcentral.org",
    "wof:placetype":"venue"
},
  "geometry": {"coordinates":[9.351936,51.28455],"type":"Point"}
}