{
  "type": "Feature",
  "properties": {
    "iso:country":"DE",
    "sg:city":"Lingen",
    "sg:postcode":"49808",
    "sg:province":"Niedersachsen",
    "wof:name":"Drei P Pipeline Petroleum Und Precision Services",
    "wof:placetype":"venue"
},
  "geometry": {"coordinates":[7.31586,52.521549],"type":"Point"}
}