{
  "type": "Feature",
  "properties": {
    "iso:country":"DE",
    "sg:address":"Bahnhofstr. 15",
    "sg:city":"Rauenstein",
    "sg:phone":"+49 36766/87866",
    "sg:postcode":"96528",
    "sg:province":"Th\u00fcringen",
    "wof:name":"R. Greiner",
    "wof:placetype":"venue"
},
  "geometry": {"coordinates":[11.051451683,50.4170303345],"type":"Point"}
}