{
  "type": "Feature",
  "properties": {
    "iso:country":"DE",
    "sg:address":"Walzm\u00fchle 2",
    "sg:city":"D\u00fcren",
    "sg:phone":"+49 2421/43017",
    "sg:postcode":"52349",
    "sg:province":"Nordrhein-Westfalen",
    "wof:name":"Verg\u00f6lst Partnerbetriebe Alfred Ohrem Gmbh",
    "wof:placetype":"venue"
},
  "geometry": {"coordinates":[6.470564,50.813107],"type":"Point"}
}