{
  "type": "Feature",
  "properties": {
    "iso:country":"DE",
    "sg:address":"Leipziger Str. 80",
    "sg:city":"Zwickau",
    "sg:phone":"+49 375/275880",
    "sg:postcode":"08058",
    "sg:province":"Sachsen",
    "wof:name":"Vogl",
    "wof:placetype":"venue"
},
  "geometry": {"coordinates":[12.4929542542,50.7289848328],"type":"Point"}
}