{
  "type": "Feature",
  "properties": {
    "iso:country":"DE",
    "sg:address":"Bahnhofstr. 125",
    "sg:city":"Hagenow",
    "sg:phone":"+49 3883/26125",
    "sg:postcode":"19230",
    "sg:province":"Mecklenburg-Vorpommern",
    "wof:name":"Ludwigsluster Verkehrsges. Mbh",
    "wof:placetype":"venue"
},
  "geometry": {"coordinates":[11.2127847672,53.4178581238],"type":"Point"}
}