{
  "type": "Feature",
  "properties": {
    "iso:country":"DE",
    "sg:address":"M\u00fchlenstr. 4",
    "sg:city":"Wittmund",
    "sg:phone":"+49 4464/8141",
    "sg:postcode":"26409",
    "sg:province":"Niedersachsen",
    "wof:name":"G\u00e4stehaus-restaurant Friesenheim",
    "wof:placetype":"venue"
},
  "geometry": {"coordinates":[7.7837638855,53.5781364441],"type":"Point"}
}