{
  "type": "Feature",
  "properties": {
    "iso:country":"DE",
    "sg:address":"Hamburger Str. 125",
    "sg:city":"Hamburg",
    "sg:phone":"+49 40/2997070",
    "sg:postcode":"22083",
    "sg:province":"Hamburg",
    "wof:name":"Curt Schmidt",
    "wof:placetype":"venue"
},
  "geometry": {"coordinates":[10.036324,53.575851],"type":"Point"}
}