{
  "type": "Feature",
  "properties": {
    "iso:country":"DE",
    "sg:address":"Peterstr. 37",
    "sg:city":"D\u00fcren",
    "sg:postcode":"52353",
    "sg:province":"Nordrhein-Westfalen",
    "wof:name":"Friedhelm Winkels",
    "wof:placetype":"venue"
},
  "geometry": {"coordinates":[6.422869,50.846329],"type":"Point"}
}