{
  "type": "Feature",
  "properties": {
    "iso:country":"DE",
    "sg:address":"Holl\u00e4nderstr. 42-50",
    "sg:city":"Mannheim",
    "sg:postcode":"68219",
    "sg:province":"Baden-W\u00fcrttemberg",
    "wof:name":"Wetzel Verm\u00f6gens- Verwaltung Gmbh",
    "wof:placetype":"venue"
},
  "geometry": {"coordinates":[8.509598732,49.4261741638],"type":"Point"}
}