{
  "type": "Feature",
  "properties": {
    "iso:country":"DE",
    "sg:address":"Lugstr.",
    "sg:city":"Pirna",
    "sg:phone":"+49 3501/56070",
    "sg:postcode":"01796",
    "sg:province":"Sachsen",
    "wof:name":"Dr. Adamek Dienstleistungs- Und Verwaltungsges. Mbh",
    "wof:placetype":"venue"
},
  "geometry": {"coordinates":[13.9421596527,50.9737892151],"type":"Point"}
}