{
  "type": "Feature",
  "properties": {
    "iso:country":"DE",
    "sg:address":"Obstmarschenweg 8",
    "sg:city":"Gr\u00fcnendeich",
    "sg:phone":"+49 4142/3530",
    "sg:postcode":"21720",
    "sg:province":"Niedersachsen",
    "wof:name":"H. D\u00fcrkes Und W. Lambrecht Rechtsanw\u00e4lte Und Notare",
    "wof:placetype":"venue"
},
  "geometry": {"coordinates":[9.609457016,53.5695304871],"type":"Point"}
}