{
  "type": "Feature",
  "properties": {
    "iso:country":"DE",
    "sg:address":"Kaiserstr. 59-61",
    "sg:city":"Mainz",
    "sg:phone":"+49 6131/672707",
    "sg:postcode":"55116",
    "sg:province":"Rheinland-Pfalz",
    "wof:name":"Heike Schell Rechtsanw\u00e4ltin",
    "wof:placetype":"venue"
},
  "geometry": {"coordinates":[8.2671642303,50.0084571838],"type":"Point"}
}