{
  "type": "Feature",
  "properties": {
    "iso:country":"DE",
    "sg:address":"Mowenbusch 19",
    "sg:city":"Vlotho",
    "sg:phone":"+49 5228/7149",
    "sg:postcode":"32602",
    "sg:province":"Nordrhein-Westfalen",
    "wof:name":"Eilhard Riesner",
    "wof:placetype":"venue"
},
  "geometry": {"coordinates":[8.791269,52.149075],"type":"Point"}
}