{
  "type": "Feature",
  "properties": {
    "iso:country":"DE",
    "sg:address":"Am Hochstr\u00e4\u00df 20",
    "sg:city":"Ulm",
    "sg:phone":"+49 731/382677",
    "sg:postcode":"89081",
    "sg:province":"Baden-W\u00fcrttemberg",
    "wof:name":"P. Finckh",
    "wof:placetype":"venue"
},
  "geometry": {"coordinates":[9.946598053,48.3801956177],"type":"Point"}
}