{
  "type": "Feature",
  "properties": {
    "iso:country":"DE",
    "sg:address":"Kolumbusstr. 10",
    "sg:city":"Hamburg",
    "sg:phone":"+49 40/7320081",
    "sg:postcode":"22113",
    "sg:province":"Schleswig-Holstein",
    "wof:name":"Industria Gmbh",
    "wof:placetype":"venue"
},
  "geometry": {"coordinates":[10.0886211395,53.5424118042],"type":"Point"}
}