{
  "type": "Feature",
  "properties": {
    "iso:country":"DE",
    "sg:address":"Blankenbergstr. 6",
    "sg:city":"Berlin",
    "sg:phone":"+49 30/8592171",
    "sg:postcode":"12161",
    "sg:province":"Berlin",
    "wof:name":"Horst W. Neumann Rechtsanwalt",
    "wof:placetype":"venue"
},
  "geometry": {"coordinates":[13.3241052628,52.4686546326],"type":"Point"}
}