{
  "type": "Feature",
  "properties": {
    "iso:country":"DE",
    "sg:address":"Hauptstr. 53",
    "sg:city":"Berkheim",
    "sg:phone":"+49 8395/2300",
    "sg:postcode":"88450",
    "sg:province":"Baden-W\u00fcrttemberg",
    "wof:name":"Georg Huber",
    "wof:placetype":"venue"
},
  "geometry": {"coordinates":[10.08186,48.043037],"type":"Point"}
}