{
  "type": "Feature",
  "properties": {
    "iso:country":"DE",
    "sg:address":"Plettenberger Str. 36",
    "sg:city":"Herscheid",
    "sg:phone":"+49 2357/2759",
    "sg:postcode":"58849",
    "sg:province":"Nordrhein-Westfalen",
    "wof:name":"Giselher Kober Steinmetzbetrieb",
    "wof:placetype":"venue"
},
  "geometry": {"coordinates":[7.7508912086,51.1767997742],"type":"Point"}
}