{
  "type": "Feature",
  "properties": {
    "iso:country":"DE",
    "sg:address":"Berliner Ring 11",
    "sg:city":"Wolfsburg",
    "sg:postcode":"38446",
    "sg:province":"Niedersachsen",
    "wof:name":"Christl.-wissenschaftliche Vereinigung Wolfsburg",
    "wof:placetype":"venue"
},
  "geometry": {"coordinates":[10.7949304581,52.4150657654],"type":"Point"}
}