{
  "type": "Feature",
  "properties": {
    "iso:country":"DE",
    "sg:address":"Wittensteinstr. 156",
    "sg:city":"Wuppertal",
    "sg:phone":"+49 202/280410",
    "sg:postcode":"42285",
    "sg:province":"Nordrhein-Westfalen",
    "wof:name":"Frischauf-matratzenfabrik Walter Tusch",
    "wof:placetype":"venue"
},
  "geometry": {"coordinates":[7.180018,51.262657],"type":"Point"}
}