{
  "type": "Feature",
  "properties": {
    "iso:country":"DE",
    "sg:address":"Stauffenbergring 27",
    "sg:city":"Olpe",
    "sg:phone":"+49 2761/61870",
    "sg:postcode":"57462",
    "sg:province":"Nordrhein-Westfalen",
    "wof:name":"Werner Kebbekus Gmbh & Co. Kg",
    "wof:placetype":"venue"
},
  "geometry": {"coordinates":[7.8573818207,51.0411376953],"type":"Point"}
}