{
  "type": "Feature",
  "properties": {
    "iso:country":"DE",
    "sg:address":"Im Neuen Felde 105",
    "sg:city":"Uelzen",
    "sg:postcode":"29525",
    "sg:province":"Niedersachsen",
    "wof:name":"Kooperationsges. Nieders\u00e4chsischer Versorgungs-",
    "wof:placetype":"venue"
},
  "geometry": {"coordinates":[10.554873,52.98378],"type":"Point"}
}