{
  "type": "Feature",
  "properties": {
    "iso:country":"DE",
    "sg:address":"Konstantinstr. 24",
    "sg:city":"Bonn",
    "sg:phone":"+49 228/363472",
    "sg:postcode":"53179",
    "sg:province":"Nordrhein-Westfalen",
    "wof:name":"Christa Fehr",
    "wof:placetype":"venue"
},
  "geometry": {"coordinates":[7.1699471474,50.6830863953],"type":"Point"}
}