{
  "type": "Feature",
  "properties": {
    "iso:country":"DE",
    "sg:address":"Stadtring 13 a",
    "sg:city":"Elstra",
    "sg:postcode":"01920",
    "sg:province":"Sachsen",
    "wof:name":"Pension & Gastst\u00e4tte Wolf",
    "wof:placetype":"venue"
},
  "geometry": {"coordinates":[14.1292448044,51.2222747803],"type":"Point"}
}