{
  "type": "Feature",
  "properties": {
    "iso:country":"DE",
    "sg:address":"Dickenr\u00fcck 2",
    "sg:city":"Rotenburg",
    "sg:postcode":"36199",
    "sg:province":"Hessen",
    "wof:name":"Bettenhausen Transport Gmbh",
    "wof:placetype":"venue"
},
  "geometry": {"coordinates":[9.755555,50.971416],"type":"Point"}
}