{
  "type": "Feature",
  "properties": {
    "iso:country":"DE",
    "sg:address":"Rheintalstr. 38",
    "sg:city":"Wiesbaden",
    "sg:phone":"+49 611/429295",
    "sg:postcode":"65199",
    "sg:province":"Hessen",
    "wof:name":"Dr. Med. Thorsten Gorbauch Arzt F\u00fcr Innere Medizin",
    "wof:placetype":"venue"
},
  "geometry": {"coordinates":[8.1974935532,50.0744132996],"type":"Point"}
}