{
  "type": "Feature",
  "properties": {
    "iso:country":"DE",
    "sg:address":"Bergstr. 23",
    "sg:city":"N\u00fcrnberg",
    "sg:phone":"+49 911/226228",
    "sg:postcode":"90403",
    "sg:province":"Bayern",
    "wof:name":"Robert D\u00fcll",
    "wof:placetype":"venue"
},
  "geometry": {"coordinates":[11.074664,49.457073],"type":"Point"}
}