{
  "type": "Feature",
  "properties": {
    "iso:country":"DE",
    "sg:address":"Madamenweg 25",
    "sg:city":"Braunschweig",
    "sg:phone":"+49 531/892243",
    "sg:postcode":"38118",
    "sg:province":"Niedersachsen",
    "wof:name":"Schmidt & Langermann",
    "wof:placetype":"venue"
},
  "geometry": {"coordinates":[10.500679,52.260685],"type":"Point"}
}