{
  "type": "Feature",
  "properties": {
    "iso:country":"DE",
    "sg:address":"Schertlinstr. 23",
    "sg:city":"Augsburg",
    "sg:phone":"+49 821/575858",
    "sg:postcode":"86159",
    "sg:province":"Bayern",
    "wof:name":"Value-holdings Verm\u00f6gensmanagement Gmbh",
    "wof:placetype":"venue"
},
  "geometry": {"coordinates":[10.8961601257,48.3530387878],"type":"Point"}
}