{
  "type": "Feature",
  "properties": {
    "iso:country":"DE",
    "sg:address":"Weserstr. 22",
    "sg:city":"Beverungen",
    "sg:phone":"+49 5273/1332",
    "sg:postcode":"37688",
    "sg:province":"Nordrhein-Westfalen",
    "wof:name":"Kath. Pfarramt St. Joh. Baptist",
    "wof:placetype":"venue"
},
  "geometry": {"coordinates":[9.3758602142,51.6641616821],"type":"Point"}
}