{
  "type": "Feature",
  "properties": {
    "iso:country":"DE",
    "sg:address":"Forddamm 17",
    "sg:city":"Berlin",
    "sg:phone":"+49 30/7064206",
    "sg:postcode":"12107",
    "sg:province":"Berlin",
    "wof:name":"Joachim Darge Architekt",
    "wof:placetype":"venue"
},
  "geometry": {"coordinates":[13.383117,52.437656],"type":"Point"}
}