{
  "type": "Feature",
  "properties": {
    "iso:country":"DE",
    "sg:address":"Feuerstr. 3",
    "sg:city":"Lippetal",
    "sg:phone":"+49 2923/442",
    "sg:postcode":"59510",
    "sg:province":"Nordrhein-Westfalen",
    "wof:name":"Christoph Kaup",
    "wof:placetype":"venue"
},
  "geometry": {"coordinates":[8.123054,51.689533],"type":"Point"}
}