{
  "type": "Feature",
  "properties": {
    "iso:country":"DE",
    "sg:address":"Pomona 98",
    "sg:city":"Neuss",
    "sg:phone":"+49 4921/3148710",
    "sg:postcode":"41464",
    "sg:province":"Nordrhein-Westfalen",
    "wof:name":"Klaus Madest",
    "wof:placetype":"venue"
},
  "geometry": {"coordinates":[6.691753,51.178726],"type":"Point"}
}