{
  "type": "Feature",
  "properties": {
    "iso:country":"DE",
    "sg:address":"Friedenstr. 17",
    "sg:city":"Kirchheim",
    "sg:phone":"+49 7143/93676",
    "sg:postcode":"74366",
    "sg:province":"Baden-W\u00fcrttemberg",
    "wof:name":"Erich Koch Ingenieur",
    "wof:placetype":"venue"
},
  "geometry": {"coordinates":[9.1481809616,49.0374755859],"type":"Point"}
}