{
  "type": "Feature",
  "properties": {
    "iso:country":"DE",
    "sg:address":"An der Kr\u00fcmme 5",
    "sg:city":"Ruhla",
    "sg:phone":"+49 36929/80178",
    "sg:postcode":"99842",
    "sg:province":"Th\u00fcringen",
    "wof:name":"L. M\u00fcller",
    "wof:placetype":"venue"
},
  "geometry": {"coordinates":[10.3836336136,50.8865242004],"type":"Point"}
}