{
  "type": "Feature",
  "properties": {
    "iso:country":"DE",
    "sg:address":"J\u00e4gerweg 11a",
    "sg:city":"Egmating",
    "sg:postcode":"85658",
    "sg:province":"Bayern",
    "wof:name":"Bernd Habammer Zimmerei Und Holzbau Gmbh",
    "wof:placetype":"venue"
},
  "geometry": {"coordinates":[11.7935667038,48.0074424744],"type":"Point"}
}