{
  "type": "Feature",
  "properties": {
    "iso:country":"DE",
    "sg:address":"Wiltbergstr. 50",
    "sg:city":"Berlin",
    "sg:phone":"+49 30/94010",
    "sg:postcode":"13125",
    "sg:province":"Berlin",
    "wof:name":"Apotheke Im Klinikum Buch 1",
    "wof:placetype":"venue"
},
  "geometry": {"coordinates":[13.490623,52.638691],"type":"Point"}
}