{
  "type": "Feature",
  "properties": {
    "iso:country":"DE",
    "sg:address":"Tribseer Str. 5",
    "sg:city":"Stralsund",
    "sg:postcode":"18439",
    "sg:province":"Mecklenburg-Vorpommern",
    "wof:name":"Pgh Meisterwelle",
    "wof:placetype":"venue"
},
  "geometry": {"coordinates":[13.085178,54.309711],"type":"Point"}
}