{
  "type": "Feature",
  "properties": {
    "iso:country":"DE",
    "sg:address":"Adelheider Str. 349",
    "sg:city":"Delmenhorst",
    "sg:phone":"+49 4221/23677",
    "sg:postcode":"27755",
    "sg:province":"Niedersachsen",
    "wof:name":"Herbert Springmann",
    "wof:placetype":"venue"
},
  "geometry": {"coordinates":[8.615559,53.000965],"type":"Point"}
}