{
  "type": "Feature",
  "properties": {
    "iso:country":"DE",
    "sg:address":"Wagnerstr. 3",
    "sg:city":"Weiden",
    "sg:phone":"+49 961/22664",
    "sg:postcode":"92637",
    "sg:province":"Bayern",
    "wof:name":"Brunhilde Th\u00fcmmler Masseurin",
    "wof:placetype":"venue"
},
  "geometry": {"coordinates":[12.140259,49.681984],"type":"Point"}
}