{
  "type": "Feature",
  "properties": {
    "iso:country":"DE",
    "sg:address":"Berg 7",
    "sg:city":"Rottach-Egern",
    "sg:postcode":"83700",
    "sg:province":"Bayern",
    "wof:name":"Strillinger Gmbh",
    "wof:placetype":"venue"
},
  "geometry": {"coordinates":[11.802154,47.688747],"type":"Point"}
}