{
  "type": "Feature",
  "properties": {
    "iso:country":"DE",
    "sg:address":"Gifhorner Weg 7",
    "sg:city":"Gifhorn",
    "sg:phone":"+49 5371/75610",
    "sg:postcode":"38518",
    "sg:province":"Niedersachsen",
    "wof:name":"Siegfried Heinrichs",
    "wof:placetype":"venue"
},
  "geometry": {"coordinates":[10.48431,52.507977],"type":"Point"}
}