{
  "type": "Feature",
  "properties": {
    "iso:country":"DE",
    "sg:address":"Hauptstr. 15",
    "sg:city":"Schemmerhofen",
    "sg:phone":"+49 4973/562262",
    "sg:postcode":"88433",
    "sg:province":"Baden-W\u00fcrttemberg",
    "wof:name":"Raiffeisenbank Mietingen Eg",
    "wof:placetype":"venue"
},
  "geometry": {"coordinates":[9.792413,48.174782],"type":"Point"}
}