{
  "type": "Feature",
  "properties": {
    "iso:country":"DE",
    "sg:address":"Stein\u00e4ckerstr. 1",
    "sg:city":"Friolzheim",
    "sg:phone":"+49 7044/43668",
    "sg:postcode":"71292",
    "sg:province":"Baden-W\u00fcrttemberg",
    "wof:name":"J. Scheyhing Gmbh & Co.",
    "wof:placetype":"venue"
},
  "geometry": {"coordinates":[8.8449802399,48.8365516663],"type":"Point"}
}