{
  "type": "Feature",
  "properties": {
    "iso:country":"DE",
    "sg:address":"Hedwigstr. 140",
    "sg:city":"Dinslaken",
    "sg:phone":"+49 2064/15421",
    "sg:postcode":"46537",
    "sg:province":"Nordrhein-Westfalen",
    "wof:name":"Helmut L\u00f6hr Architekt",
    "wof:placetype":"venue"
},
  "geometry": {"coordinates":[6.722875,51.579861],"type":"Point"}
}