{
  "type": "Feature",
  "properties": {
    "iso:country":"DE",
    "sg:address":"Untere Dorfstr. 5",
    "sg:city":"Braunschweig",
    "sg:phone":"+49 531/875881",
    "sg:postcode":"38122",
    "sg:province":"Niedersachsen",
    "wof:name":"Harald Sch\u00e4fer",
    "wof:placetype":"venue"
},
  "geometry": {"coordinates":[10.454771,52.226604],"type":"Point"}
}