{
  "type": "Feature",
  "properties": {
    "iso:country":"DE",
    "sg:address":"Marienh\u00f6he 3",
    "sg:city":"N\u00f6rdlingen",
    "sg:phone":"+49 9081/9673",
    "sg:postcode":"86720",
    "sg:province":"Bayern",
    "wof:name":"Cafe Sonnenkeller Niagara",
    "wof:placetype":"venue"
},
  "geometry": {"coordinates":[10.490484,48.84362],"type":"Point"}
}