{
  "type": "Feature",
  "properties": {
    "iso:country":"DE",
    "sg:address":"Scheiblerstr. 18",
    "sg:city":"Berlin",
    "sg:phone":"+49 30/5324510",
    "sg:postcode":"12437",
    "sg:province":"Berlin",
    "wof:name":"Hanni Hoock",
    "wof:placetype":"venue"
},
  "geometry": {"coordinates":[13.4934062958,52.4666557312],"type":"Point"}
}