{
  "type": "Feature",
  "properties": {
    "iso:country":"DE",
    "sg:address":"Rosenstr. 5",
    "sg:city":"Blomberg",
    "sg:phone":"+49 4952/3595080",
    "sg:postcode":"32825",
    "sg:province":"Nordrhein-Westfalen",
    "wof:name":"Stadtsparkasse Blomberg Lippe",
    "wof:placetype":"venue"
},
  "geometry": {"coordinates":[9.094076,51.942356],"type":"Point"}
}