{
  "type": "Feature",
  "properties": {
    "iso:country":"DE",
    "sg:address":"Bahnhosplatz 1",
    "sg:city":"Bietigheim-Bissingen",
    "sg:phone":"+49 7142",
    "sg:postcode":"74321",
    "sg:province":"Baden-W\u00fcrttemberg",
    "wof:name":"Ihr Office",
    "wof:placetype":"venue"
},
  "geometry": {"coordinates":[9.135476,48.948406],"type":"Point"}
}