{
  "type": "Feature",
  "properties": {
    "iso:country":"DE",
    "sg:address":"Gotteskoogdeich 2",
    "sg:city":"Nieb\u00fcll",
    "sg:phone":"+49 4661/4263",
    "sg:postcode":"25899",
    "sg:province":"Schleswig-Holstein",
    "wof:name":"Carsten Petersen",
    "wof:placetype":"venue"
},
  "geometry": {"coordinates":[8.791253,54.791496],"type":"Point"}
}