{
  "type": "Feature",
  "properties": {
    "iso:country":"DE",
    "sg:address":"Weskampstr. 17",
    "sg:city":"Oldenburg",
    "sg:phone":"+49 441/883704",
    "sg:postcode":"26121",
    "sg:province":"Niedersachsen",
    "wof:name":"Lutz Kr\u00fcger Dachdeckermeister",
    "wof:placetype":"venue"
},
  "geometry": {"coordinates":[8.211218,53.150387],"type":"Point"}
}