{
  "type": "Feature",
  "properties": {
    "iso:country":"DE",
    "sg:address":"Biebricher Allee 34",
    "sg:city":"Wiesbaden",
    "sg:phone":"+49 611/986180",
    "sg:postcode":"65187",
    "sg:province":"Hessen",
    "wof:name":"N\u00fcssler Gmbh",
    "wof:placetype":"venue"
},
  "geometry": {"coordinates":[8.241507,50.065815],"type":"Point"}
}