{
  "type": "Feature",
  "properties": {
    "iso:country":"DE",
    "sg:address":"Max-Frik-Str. 4",
    "sg:city":"Bad Wimpfen",
    "sg:phone":"+49 7063/8791",
    "sg:postcode":"74206",
    "sg:province":"Baden-W\u00fcrttemberg",
    "wof:name":"Verwaltungsges. Der Gfw Ges. F\u00fcr Wohnungsbau Mbh",
    "wof:placetype":"venue"
},
  "geometry": {"coordinates":[9.167418,49.227066],"type":"Point"}
}