{
  "type": "Feature",
  "properties": {
    "iso:country":"DE",
    "sg:address":"Holsterhauser Str. 70 a",
    "sg:city":"Herne",
    "sg:postcode":"44652",
    "sg:province":"Nordrhein-Westfalen",
    "wof:name":"Freunde Der Martin-opitz- Bibliothek E. V.",
    "wof:placetype":"venue"
},
  "geometry": {"coordinates":[7.1888279915,51.5243911743],"type":"Point"}
}