{
  "type": "Feature",
  "properties": {
    "iso:country":"DE",
    "sg:address":"Bogenstr. 16 a",
    "sg:city":"Grafschaft",
    "sg:phone":"+49 2641/29861",
    "sg:postcode":"53501",
    "sg:province":"Rheinland-Pfalz",
    "wof:name":"R. Merten",
    "wof:placetype":"venue"
},
  "geometry": {"coordinates":[7.13412714,50.5681800842],"type":"Point"}
}