{
  "type": "Feature",
  "properties": {
    "iso:country":"DE",
    "sg:address":"Saarlandstr. 52-54",
    "sg:city":"Bingen",
    "sg:phone":"+49 6721/181546",
    "sg:postcode":"55411",
    "sg:province":"Rheinland-Pfalz",
    "wof:name":"Kuhn & Siefert Gmbh & Co Kg",
    "wof:placetype":"venue"
},
  "geometry": {"coordinates":[7.897942,49.954681],"type":"Point"}
}