{
  "type": "Feature",
  "properties": {
    "iso:country":"DE",
    "sg:address":"Eichstr. 12",
    "sg:city":"Dresden",
    "sg:phone":"+49 351/3103402",
    "sg:postcode":"01309",
    "sg:province":"Sachsen",
    "wof:name":"Irmgard Weichelt",
    "wof:placetype":"venue"
},
  "geometry": {"coordinates":[13.801940918,51.0492897034],"type":"Point"}
}