{
  "type": "Feature",
  "properties": {
    "iso:country":"DE",
    "sg:address":"Hainbuchenstr. 54",
    "sg:city":"Berlin",
    "sg:phone":"+49 30/4013217",
    "sg:postcode":"13465",
    "sg:province":"Berlin",
    "wof:name":"Prof. Rudolf K\u00fcgler Kunstmaler",
    "wof:placetype":"venue"
},
  "geometry": {"coordinates":[13.266925,52.63813],"type":"Point"}
}