{
  "type": "Feature",
  "properties": {
    "iso:country":"DE",
    "sg:address":"Teichstr. 10",
    "sg:city":"Eutin",
    "sg:phone":"+49 4521/5507",
    "sg:postcode":"23701",
    "sg:province":"Schleswig-Holstein",
    "wof:name":"Rolf Wohlert",
    "wof:placetype":"venue"
},
  "geometry": {"coordinates":[10.584075,54.127621],"type":"Point"}
}