{
  "type": "Feature",
  "properties": {
    "iso:country":"DE",
    "sg:address":"Luisenstr. 7",
    "sg:city":"Ettenheim",
    "sg:phone":"+49 7822/1490",
    "sg:postcode":"77955",
    "sg:province":"Baden-W\u00fcrttemberg",
    "wof:name":"M. M\u00fcller",
    "wof:placetype":"venue"
},
  "geometry": {"coordinates":[7.8125128746,48.2584152222],"type":"Point"}
}