{
  "type": "Feature",
  "properties": {
    "iso:country":"DE",
    "sg:address":"Jahnstr. 23",
    "sg:city":"Glattbach",
    "sg:phone":"+49 6021/424466",
    "sg:postcode":"63864",
    "sg:province":"Bayern",
    "wof:name":"Schreck Heissmangel",
    "wof:placetype":"venue"
},
  "geometry": {"coordinates":[9.1426458359,50.0088119507],"type":"Point"}
}