{
  "type": "Feature",
  "properties": {
    "iso:country":"DE",
    "sg:address":"K\u00f6ppelsdorfer Str. 26",
    "sg:city":"Sonneberg",
    "sg:phone":"+49 3675/42003",
    "sg:postcode":"96515",
    "sg:province":"Th\u00fcringen",
    "wof:name":"Bhw Bausparkasse Ag",
    "wof:placetype":"venue"
},
  "geometry": {"coordinates":[11.172459,50.358524],"type":"Point"}
}