{
  "type": "Feature",
  "properties": {
    "iso:country":"DE",
    "sg:address":"C/Vivaldi 24",
    "sg:city":"Albir / Alfaz del Pi",
    "sg:phone":"+34 966 86 45 60",
    "sg:postcode":"03581",
    "wof:name":"Birowaha",
    "wof:placetype":"venue"
},
  "geometry": {"coordinates":[-0.073034,38.568893],"type":"Point"}
}