{
  "type": "Feature",
  "properties": {
    "iso:country":"DE",
    "sg:address":"Hagacker 3 A",
    "sg:city":"Ronnenberg",
    "sg:phone":"+49 5109/7277",
    "sg:postcode":"30952",
    "sg:province":"Niedersachsen",
    "wof:name":"Dr. Eberhard Winkler Tierarzt",
    "wof:placetype":"venue"
},
  "geometry": {"coordinates":[9.6540613174,52.317741394],"type":"Point"}
}