{
  "type": "Feature",
  "properties": {
    "iso:country":"DE",
    "sg:address":"Martinstr. 16",
    "sg:city":"K\u00f6ln",
    "sg:phone":"+49 221/202070",
    "sg:postcode":"50667",
    "sg:province":"Nordrhein-Westfalen",
    "wof:name":"Euro Lloyd Reiseb\u00fcro Gmbh & Co. Kg",
    "wof:placetype":"venue"
},
  "geometry": {"coordinates":[6.9590930939,50.9364242554],"type":"Point"}
}