{
  "type": "Feature",
  "properties": {
    "iso:country":"DE",
    "sg:address":"Lichteneggstr. 21",
    "sg:city":"Moos",
    "sg:phone":"+49 9938/95060",
    "sg:postcode":"94554",
    "sg:province":"Bayern",
    "wof:name":"Tri-san Geb\u00e4udesanierung Gmbh",
    "wof:placetype":"venue"
},
  "geometry": {"coordinates":[12.962695,48.749058],"type":"Point"}
}