{
  "type": "Feature",
  "properties": {
    "iso:country":"DE",
    "sg:address":"Lange Herzogstr. 30",
    "sg:city":"Wolfenb\u00fcttel",
    "sg:phone":"+49 5331/929797",
    "sg:postcode":"38300",
    "sg:province":"Niedersachsen",
    "wof:name":"P. Grutzeck",
    "wof:placetype":"venue"
},
  "geometry": {"coordinates":[10.539804,52.1642],"type":"Point"}
}