{
  "type": "Feature",
  "properties": {
    "iso:country":"DE",
    "sg:address":"Linneper Weg 1 Breitscheid",
    "sg:city":"Ratingen",
    "sg:phone":"+49 4921/021890",
    "sg:postcode":"40885",
    "sg:province":"Nordrhein-Westfalen",
    "wof:name":"Drk-blutspendedienst Nordrhein-westfalen Gemeinnuetzige Gesellschaft Mbh",
    "wof:placetype":"venue"
},
  "geometry": {"coordinates":[6.83529,51.332829],"type":"Point"}
}