{
  "type": "Feature",
  "properties": {
    "iso:country":"DE",
    "sg:address":"Nisterbergerweg 8",
    "sg:city":"Friedewald",
    "sg:phone":"+49 2743/1381",
    "sg:postcode":"57520",
    "sg:province":"Rheinland-Pfalz",
    "wof:name":"H. Zimmermann",
    "wof:placetype":"venue"
},
  "geometry": {"coordinates":[7.957967,50.707985],"type":"Point"}
}