{
  "type": "Feature",
  "properties": {
    "iso:country":"DE",
    "sg:address":"Annostr 49",
    "sg:city":"Hennef",
    "sg:phone":"+49 2242/2431",
    "sg:postcode":"53773",
    "sg:province":"Nordrhein-Westfalen",
    "wof:name":"Fischer B\u00fcrom\u00f6bel-systeme Gmbh",
    "wof:placetype":"venue"
},
  "geometry": {"coordinates":[7.3047399521,50.7987174988],"type":"Point"}
}