{
  "type": "Feature",
  "properties": {
    "iso:country":"DE",
    "sg:address":"Nordstr. 25",
    "sg:city":"Apolda",
    "sg:postcode":"99510",
    "sg:province":"Th\u00fcringen",
    "wof:name":"S & F - Sport & Freizeit Gmbh",
    "wof:placetype":"venue"
},
  "geometry": {"coordinates":[11.5172462463,51.0367965698],"type":"Point"}
}