{
  "type": "Feature",
  "properties": {
    "iso:country":"DE",
    "sg:address":"Mariaweilerstr. 65",
    "sg:city":"D\u00fcren",
    "sg:phone":"+49 2421/61556",
    "sg:postcode":"52349",
    "sg:province":"Nordrhein-Westfalen",
    "wof:name":"Nath & Sohn Beteiligungs-gmbh",
    "wof:placetype":"venue"
},
  "geometry": {"coordinates":[6.465595,50.800255],"type":"Point"}
}