{
  "type": "Feature",
  "properties": {
    "iso:country":"DE",
    "sg:address":"Haugerpfarrg. 9",
    "sg:city":"W\u00fcrzburg",
    "sg:phone":"+49 931/354150",
    "sg:postcode":"97070",
    "sg:province":"Bayern",
    "wof:name":"Franz Scheiner Graph Kunstanstalt",
    "wof:placetype":"venue"
},
  "geometry": {"coordinates":[9.9349508286,49.797794342],"type":"Point"}
}