{
  "type": "Feature",
  "properties": {
    "iso:country":"DE",
    "sg:address":"Alverdisser Str. 3",
    "sg:city":"Barntrup",
    "sg:postcode":"32683",
    "sg:province":"Nordrhein-Westfalen",
    "wof:name":"Aldi Gmbh & Co. Kg",
    "wof:placetype":"venue"
},
  "geometry": {"coordinates":[9.1188077927,51.994304657],"type":"Point"}
}