{
  "type": "Feature",
  "properties": {
    "iso:country":"DE",
    "sg:address":"An der Brache 8",
    "sg:city":"Gelsenkirchen",
    "sg:postcode":"45891",
    "sg:province":"Nordrhein-Westfalen",
    "wof:name":"T. O. P. Technologie Organisation Projekte",
    "wof:placetype":"venue"
},
  "geometry": {"coordinates":[7.084608078,51.574848175],"type":"Point"}
}