{
  "type": "Feature",
  "properties": {
    "iso:country":"DE",
    "sg:address":"Kreuzstr. 6",
    "sg:city":"Bad Krozingen",
    "sg:phone":"+49 7633/3514",
    "sg:postcode":"79189",
    "sg:province":"Baden-W\u00fcrttemberg",
    "wof:name":"Pauline",
    "wof:placetype":"venue"
},
  "geometry": {"coordinates":[7.7048721313,47.9181480408],"type":"Point"}
}