{
  "type": "Feature",
  "properties": {
    "iso:country":"DE",
    "sg:address":"Amselstr. 3",
    "sg:city":"Neuenkirchen",
    "sg:phone":"+49 5973/1407",
    "sg:postcode":"48485",
    "sg:province":"Nordrhein-Westfalen",
    "wof:name":"M. Elling",
    "wof:placetype":"venue"
},
  "geometry": {"coordinates":[7.3694047928,52.2513427734],"type":"Point"}
}