{
  "type": "Feature",
  "properties": {
    "iso:country":"DE",
    "sg:address":"Heinrich-Behr-Str. 3",
    "sg:city":"Lobenstein",
    "sg:phone":"+49 36651/2140",
    "sg:postcode":"07356",
    "sg:province":"Th\u00fcringen",
    "wof:name":"Uwe Kessel",
    "wof:placetype":"venue"
},
  "geometry": {"coordinates":[11.6399202347,50.4518127441],"type":"Point"}
}