{
  "type": "Feature",
  "properties": {
    "iso:country":"DE",
    "sg:address":"Gro\u00dfflecken 54 b",
    "sg:city":"Neum\u00fcnster",
    "sg:phone":"+49 4321/44522",
    "sg:postcode":"24534",
    "sg:province":"Schleswig-Holstein",
    "wof:name":"Fabrik Kneipenrestaurant",
    "wof:placetype":"venue"
},
  "geometry": {"coordinates":[9.9874582291,54.0702552795],"type":"Point"}
}