{
  "type": "Feature",
  "properties": {
    "iso:country":"DE",
    "sg:address":"Eisenberg",
    "sg:city":"Eisenberg",
    "sg:phone":"+49 36691/2074",
    "sg:postcode":"07607",
    "sg:province":"Th\u00fcringen",
    "wof:name":"Deutsche Bank Ag Raiffeisenbank U., Handelsgenossenschaft E. G.",
    "wof:placetype":"venue"
},
  "geometry": {"coordinates":[11.85988,50.969727],"type":"Point"}
}