{
  "type": "Feature",
  "properties": {
    "iso:country":"DE",
    "sg:address":"Merscheider Str. 235",
    "sg:city":"Solingen",
    "sg:phone":"+49 212/320426",
    "sg:postcode":"42699",
    "sg:province":"Nordrhein-Westfalen",
    "wof:name":"Chinaimbi\u00df Take Away",
    "wof:placetype":"venue"
},
  "geometry": {"coordinates":[7.0322642326,51.1683692932],"type":"Point"}
}