{
  "type": "Feature",
  "properties": {
    "iso:country":"DE",
    "sg:address":"Wiegenfeldring 2a",
    "sg:city":"Markt Schwaben",
    "sg:phone":"+49 8121/47840",
    "sg:postcode":"85570",
    "sg:province":"Bayern",
    "wof:name":"Mp & L Produktions Gmbh",
    "wof:placetype":"venue"
},
  "geometry": {"coordinates":[11.849357605,48.1895904541],"type":"Point"}
}