{
  "type": "Feature",
  "properties": {
    "iso:country":"DE",
    "sg:address":"Eiderkamp 44",
    "sg:city":"Flintbek",
    "sg:phone":"+49 4347/8188",
    "sg:postcode":"24220",
    "sg:province":"Schleswig-Holstein",
    "wof:name":"Christer Betonwerk",
    "wof:placetype":"venue"
},
  "geometry": {"coordinates":[10.0449695587,54.244178772],"type":"Point"}
}