{
  "type": "Feature",
  "properties": {
    "iso:country":"DE",
    "sg:address":"T\u00fcttendorfer Weg 1c",
    "sg:city":"Gettorf",
    "sg:phone":"+49 8136/6300",
    "sg:postcode":"24214",
    "sg:province":"Schleswig-Holstein",
    "wof:name":"Rita B\u00f6ssow",
    "wof:placetype":"venue"
},
  "geometry": {"coordinates":[9.9837255478,54.4058189392],"type":"Point"}
}