{
  "type": "Feature",
  "properties": {
    "iso:country":"DE",
    "sg:address":"Edlhofstr. 10",
    "sg:city":"Obernzell",
    "sg:phone":"+49 8591/466",
    "sg:postcode":"94130",
    "sg:province":"Bayern",
    "wof:name":"Franz Lindb\u00fcchler Gmbh",
    "wof:placetype":"venue"
},
  "geometry": {"coordinates":[13.5675039291,48.5647125244],"type":"Point"}
}