{
  "type": "Feature",
  "properties": {
    "iso:country":"DE",
    "sg:address":"Backnanger Str. 16",
    "sg:city":"Kirchberg",
    "sg:phone":"+49 7191/20443",
    "sg:postcode":"71737",
    "sg:province":"Baden-W\u00fcrttemberg",
    "wof:name":"A. Friedrich",
    "wof:placetype":"venue"
},
  "geometry": {"coordinates":[9.354484,48.964508],"type":"Point"}
}