{
  "type": "Feature",
  "properties": {
    "iso:country":"DE",
    "sg:address":"Hinter der Burg 1",
    "sg:city":"Butzbach",
    "sg:phone":"+49 6033/950180",
    "sg:postcode":"35510",
    "sg:province":"Hessen",
    "wof:name":"M & S W\u00e4schereitechnik Gmbh",
    "wof:placetype":"venue"
},
  "geometry": {"coordinates":[8.680188,50.433064],"type":"Point"}
}