{
  "type": "Feature",
  "properties": {
    "iso:country":"DE",
    "sg:address":"Beeskower Str. 218",
    "sg:city":"Eisenh\u00fcttenstadt",
    "sg:phone":"+49 3364/413389",
    "sg:postcode":"15890",
    "sg:province":"Brandenburg",
    "wof:name":"Taverne Sirtaki",
    "wof:placetype":"venue"
},
  "geometry": {"coordinates":[14.6112947464,52.1531143188],"type":"Point"}
}