{
  "type": "Feature",
  "properties": {
    "iso:country":"DE",
    "sg:address":"Birdieweg 8",
    "sg:city":"Gramkow",
    "sg:postcode":"23968",
    "sg:province":"Mecklenburg-Vorpommern",
    "wof:name":"T.o.m. Tessiner Organisation Und Management Gmbh",
    "wof:placetype":"venue"
},
  "geometry": {"coordinates":[11.3806247711,53.9026489258],"type":"Point"}
}