{
  "type": "Feature",
  "properties": {
    "iso:country":"DE",
    "sg:address":"Bahnhofstr. 5",
    "sg:city":"Calv\u00f6rde",
    "sg:postcode":"39359",
    "sg:province":"Sachsen-Anhalt",
    "wof:name":"Monika Schlueer",
    "wof:placetype":"venue"
},
  "geometry": {"coordinates":[11.2928543091,52.3978271484],"type":"Point"}
}