{
  "type": "Feature",
  "properties": {
    "iso:country":"DE",
    "sg:address":"Antoniterstr. 6",
    "sg:city":"Frechen",
    "sg:phone":"+49 2234/12984",
    "sg:postcode":"50226",
    "sg:province":"Nordrhein-Westfalen",
    "wof:name":"E. K\u00f6hler",
    "wof:placetype":"venue"
},
  "geometry": {"coordinates":[6.8090200424,50.9092979431],"type":"Point"}
}