{
  "type": "Feature",
  "properties": {
    "iso:country":"DE",
    "sg:address":"Tinzer Str. 30",
    "sg:city":"Gera",
    "sg:postcode":"07546",
    "sg:province":"Th\u00fcringen",
    "wof:name":"Leutloff Leasing Gmbh Zweigniederlassung Gera",
    "wof:placetype":"venue"
},
  "geometry": {"coordinates":[12.09385,50.88475],"type":"Point"}
}