{
  "type": "Feature",
  "properties": {
    "iso:country":"DE",
    "sg:address":"Ehrenmalstr. 28",
    "sg:city":"Nachrodt-Wiblingwerde",
    "sg:phone":"+49 2352/3794",
    "sg:postcode":"58769",
    "sg:province":"Nordrhein-Westfalen",
    "wof:name":"Elektro-brenscheidt",
    "wof:placetype":"venue"
},
  "geometry": {"coordinates":[7.64548,51.334412],"type":"Point"}
}