{
  "type": "Feature",
  "properties": {
    "iso:country":"DE",
    "sg:address":"Arno-Jacobi-Str.9",
    "sg:city":"Pfarrkirchen",
    "sg:phone":"+49 8561/96140",
    "sg:postcode":"84347",
    "sg:province":"Bayern",
    "wof:name":"Laumer Gmbh & Co",
    "wof:placetype":"venue"
},
  "geometry": {"coordinates":[12.9408359528,48.4201049805],"type":"Point"}
}