{
  "type": "Feature",
  "properties": {
    "iso:country":"DE",
    "sg:address":"T\u00e4lesbahnstr. 2",
    "sg:city":"Geislingen",
    "sg:phone":"+49 7331/64579",
    "sg:postcode":"73312",
    "sg:province":"Baden-W\u00fcrttemberg",
    "wof:name":"Dr. Welte Pharma Gmbh",
    "wof:placetype":"venue"
},
  "geometry": {"coordinates":[9.8269758224,48.6244468689],"type":"Point"}
}