{
  "type": "Feature",
  "properties": {
    "iso:country":"DE",
    "sg:address":"Plutoweg 64",
    "sg:city":"Berlin",
    "sg:phone":"+49 30/6516257",
    "sg:postcode":"12589",
    "sg:province":"Berlin",
    "wof:name":"Horst Radue Baugesellschaft Mbh",
    "wof:placetype":"venue"
},
  "geometry": {"coordinates":[13.704721,52.432709],"type":"Point"}
}