{
  "type": "Feature",
  "properties": {
    "iso:country":"DE",
    "sg:address":"Friedrichstr. 94",
    "sg:city":"Husum",
    "sg:phone":"+49 4841/2615",
    "sg:postcode":"25813",
    "sg:province":"Schleswig-Holstein",
    "wof:name":"Kammerlichtspiele",
    "wof:placetype":"venue"
},
  "geometry": {"coordinates":[9.072016,54.465263],"type":"Point"}
}