{
  "type": "Feature",
  "properties": {
    "iso:country":"DE",
    "sg:address":"Merret-Lassen-Wai 8",
    "sg:city":"Rantum",
    "sg:phone":"+49 4651/23577",
    "sg:postcode":"25980",
    "sg:province":"Schleswig-Holstein",
    "wof:name":"G\u00e4stehaus Raantem-inge",
    "wof:placetype":"venue"
},
  "geometry": {"coordinates":[8.2971801758,54.8464813232],"type":"Point"}
}