{
  "type": "Feature",
  "properties": {
    "iso:country":"DE",
    "sg:address":"Neubr\u00fccker Str. 37",
    "sg:city":"Berlin",
    "sg:postcode":"13465",
    "sg:province":"Berlin",
    "wof:name":"Freie Erfindungsk\u00fcnstler Gmbh",
    "wof:placetype":"venue"
},
  "geometry": {"coordinates":[13.276350975,52.6398506165],"type":"Point"}
}