{
  "type": "Feature",
  "properties": {
    "iso:country":"DE",
    "sg:address":"Postfach 27:: 59340 L\u00fcdinghausen:: Germany.^^Dattelner Str 1::",
    "sg:city":"L\u00fcdinghausen",
    "sg:phone":"+49 2591/98500",
    "sg:postcode":"59348",
    "sg:province":"Nordrhein-Westfalen",
    "wof:name":"Volksbank Seppenrade Eg",
    "wof:placetype":"venue"
},
  "geometry": {"coordinates":[7.447637,51.771297],"type":"Point"}
}