{
  "type": "Feature",
  "properties": {
    "iso:country":"DE",
    "sg:address":"Gr\u00fcnauer Allee 45",
    "sg:city":"Unterhaching",
    "sg:phone":"+49 89/616116",
    "sg:postcode":"82008",
    "sg:province":"Bayern",
    "wof:name":"Helga Kreutzmann",
    "wof:placetype":"venue"
},
  "geometry": {"coordinates":[11.621408,48.062454],"type":"Point"}
}