{
  "type": "Feature",
  "properties": {
    "iso:country":"DE",
    "sg:address":"Berliner Str. 4",
    "sg:city":"Geesthacht",
    "sg:phone":"+49 4152/70347",
    "sg:postcode":"21502",
    "sg:province":"Schleswig-Holstein",
    "wof:name":"Restaurant Fischst\u00fcbchen",
    "wof:placetype":"venue"
},
  "geometry": {"coordinates":[10.3689002991,53.4373817444],"type":"Point"}
}