{
  "type": "Feature",
  "properties": {
    "iso:country":"DE",
    "sg:address":"Kirchplatz 7",
    "sg:city":"Stra\u00dfkirchen",
    "sg:phone":"+49 9424/372",
    "sg:postcode":"94342",
    "sg:province":"Bayern",
    "wof:name":"H. Ring",
    "wof:placetype":"venue"
},
  "geometry": {"coordinates":[12.722443,48.830601],"type":"Point"}
}