{
  "type": "Feature",
  "properties": {
    "iso:country":"DE",
    "sg:address":"Eisenbahnstr. 21",
    "sg:city":"Hausach",
    "sg:phone":"+49 7831/82234",
    "sg:postcode":"77756",
    "sg:province":"Baden-W\u00fcrttemberg",
    "wof:name":"Antonie Benz",
    "wof:placetype":"venue"
},
  "geometry": {"coordinates":[8.177154541,48.2857284546],"type":"Point"}
}