{
  "type": "Feature",
  "properties": {
    "iso:country":"DE",
    "sg:address":"Behringstr. 5",
    "sg:city":"Mainaschaff",
    "sg:phone":"+49 6021/7700120",
    "sg:postcode":"63814",
    "sg:province":"Bayern",
    "wof:name":"Daniel Grass",
    "wof:placetype":"venue"
},
  "geometry": {"coordinates":[9.0766410828,49.9837493896],"type":"Point"}
}