{
  "type": "Feature",
  "properties": {
    "iso:country":"DE",
    "sg:address":"Postdamer Platz 2",
    "sg:city":"Soest",
    "sg:phone":"+49 2921/1861",
    "sg:postcode":"59494",
    "sg:province":"Nordrhein-Westfalen",
    "wof:name":"Dresdner Bank",
    "wof:placetype":"venue"
},
  "geometry": {"coordinates":[8.108458,51.570667],"type":"Point"}
}