{
  "type": "Feature",
  "properties": {
    "iso:country":"DE",
    "sg:address":"Alexanderstr. 170",
    "sg:city":"Stuttgart",
    "sg:phone":"+49 711/609909",
    "sg:postcode":"70180",
    "sg:province":"Baden-W\u00fcrttemberg",
    "wof:name":"H. Edelmann",
    "wof:placetype":"venue"
},
  "geometry": {"coordinates":[9.1773586273,48.7648887634],"type":"Point"}
}