{
  "type": "Feature",
  "properties": {
    "iso:country":"DE",
    "sg:address":"L\u00f6hrstr. 66 b",
    "sg:city":"Koblenz",
    "sg:phone":"+49 261/911890",
    "sg:postcode":"56068",
    "sg:province":"Rheinland-Pfalz",
    "wof:name":"G\u00f6rres-apotheke",
    "wof:placetype":"venue"
},
  "geometry": {"coordinates":[7.592304,50.358032],"type":"Point"}
}