{
  "type": "Feature",
  "properties": {
    "iso:country":"DE",
    "sg:address":"Pumpe 104",
    "sg:city":"Eschweiler",
    "sg:phone":"+49 2403/26576",
    "sg:postcode":"52249",
    "sg:province":"Nordrhein-Westfalen",
    "wof:name":"K\u00e4fer",
    "wof:placetype":"venue"
},
  "geometry": {"coordinates":[6.2408890724,50.8029098511],"type":"Point"}
}