{
  "type": "Feature",
  "properties": {
    "iso:country":"DE",
    "sg:address":"Trippstadter Str. 24",
    "sg:city":"Hochspeyer",
    "sg:phone":"+49 6305/8686",
    "sg:postcode":"67691",
    "sg:province":"Rheinland-Pfalz",
    "wof:name":"Engelbert Wuttke",
    "wof:placetype":"venue"
},
  "geometry": {"coordinates":[7.896417,49.441753],"type":"Point"}
}