{
  "type": "Feature",
  "properties": {
    "iso:country":"DE",
    "sg:address":"Wilhelm-Busch-Str. 1",
    "sg:city":"Schmelz",
    "sg:phone":"+49 6887/2198",
    "sg:postcode":"66839",
    "sg:province":"Saarland",
    "wof:name":"Kurt Herrmann",
    "wof:placetype":"venue"
},
  "geometry": {"coordinates":[6.850013,49.440968],"type":"Point"}
}