{
  "type": "Feature",
  "properties": {
    "iso:country":"DE",
    "sg:address":"Kirchhuchtinger Landstr. 24",
    "sg:city":"Bremen",
    "sg:phone":"+49 421/583077",
    "sg:postcode":"28259",
    "sg:province":"Bremen",
    "wof:name":"Ev. Pfarramt St. Georg",
    "wof:placetype":"venue"
},
  "geometry": {"coordinates":[8.740940094,53.0516662598],"type":"Point"}
}