{
  "type": "Feature",
  "properties": {
    "iso:country":"DE",
    "sg:address":"Burgherrenstr. 2",
    "sg:city":"Kaiserslautern",
    "sg:phone":"+49 631/55170",
    "sg:postcode":"67661",
    "sg:province":"Rheinland-Pfalz",
    "wof:name":"Rudolf Sauer",
    "wof:placetype":"venue"
},
  "geometry": {"coordinates":[7.698911,49.405209],"type":"Point"}
}