{
  "type": "Feature",
  "properties": {
    "iso:country":"DE",
    "sg:address":"Schlei\u00dfheimer Str. 55",
    "sg:city":"M\u00fcnchen",
    "sg:phone":"+49 89/1269950",
    "sg:postcode":"80797",
    "sg:province":"Bayern",
    "wof:name":"Mgi Management Ges. F\u00fcr Informationstechnik Mbh",
    "wof:placetype":"venue"
},
  "geometry": {"coordinates":[11.5613050461,48.1551055908],"type":"Point"}
}