{
  "type": "Feature",
  "properties": {
    "iso:country":"DE",
    "sg:address":"Schlo\u00dfg\u00e4\u00dfchen 2",
    "sg:city":"Kamenz",
    "sg:phone":"+49 35783/14681",
    "sg:postcode":"01917",
    "sg:province":"Sachsen",
    "wof:name":"Ingrid Scheumann Tabakwaren Lotto",
    "wof:placetype":"venue"
},
  "geometry": {"coordinates":[14.0978765488,51.2699928284],"type":"Point"}
}