{
  "type": "Feature",
  "properties": {
    "iso:country":"DE",
    "sg:address":"Albweg 10",
    "sg:city":"St. Blasien",
    "sg:phone":"+49 7675/466",
    "sg:postcode":"79837",
    "sg:province":"Baden-W\u00fcrttemberg",
    "wof:name":"G\u00e4stehaus Franz Wa\u00dfmer",
    "wof:placetype":"venue"
},
  "geometry": {"coordinates":[8.066904068,47.8298034668],"type":"Point"}
}