{
  "type": "Feature",
  "properties": {
    "iso:country":"DE",
    "sg:address":"Vor dem R\u00fchner Tor 2",
    "sg:city":"B\u00fctzow",
    "sg:phone":"+49 38461/3286",
    "sg:postcode":"18246",
    "sg:province":"Mecklenburg-Vorpommern",
    "wof:name":"Bar Viva",
    "wof:placetype":"venue"
},
  "geometry": {"coordinates":[11.978313,53.849403],"type":"Point"}
}