{
  "type": "Feature",
  "properties": {
    "iso:country":"DE",
    "sg:address":"August-Bebel-Str. 181",
    "sg:city":"G\u00f6rzke",
    "sg:phone":"+49 33847/40271",
    "sg:postcode":"14828",
    "sg:province":"Brandenburg",
    "wof:name":"Susanne Kiesel",
    "wof:placetype":"venue"
},
  "geometry": {"coordinates":[12.3666639328,52.1712341309],"type":"Point"}
}