{
  "type": "Feature",
  "properties": {
    "iso:country":"DE",
    "sg:address":"Hindenburgstr. 54",
    "sg:city":"Ostfildern",
    "sg:phone":"+49 711/3481978",
    "sg:postcode":"73760",
    "sg:province":"Baden-W\u00fcrttemberg",
    "wof:name":"Riegelhof-apotheke",
    "wof:placetype":"venue"
},
  "geometry": {"coordinates":[9.293868,48.713268],"type":"Point"}
}