{
  "type": "Feature",
  "properties": {
    "iso:country":"DE",
    "sg:address":"Schlager\u00f6d 1",
    "sg:city":"Grafenau",
    "sg:phone":"+49 8552",
    "sg:postcode":"94481",
    "sg:province":"Bayern",
    "wof:name":"Webdesign G\u00f6bel",
    "wof:placetype":"venue"
},
  "geometry": {"coordinates":[13.39721,48.840359],"type":"Point"}
}