{
  "type": "Feature",
  "properties": {
    "iso:country":"DE",
    "sg:address":"Heinkelstr. 3",
    "sg:city":"G\u00f6ppingen",
    "sg:phone":"+49 7161/23169",
    "sg:postcode":"73033",
    "sg:province":"Baden-W\u00fcrttemberg",
    "wof:name":"Ida Przigode",
    "wof:placetype":"venue"
},
  "geometry": {"coordinates":[9.6467924118,48.7142944336],"type":"Point"}
}