{
  "type": "Feature",
  "properties": {
    "iso:country":"DE",
    "sg:address":"Alte Steige 15",
    "sg:city":"Kaufbeuren",
    "sg:phone":"+49 8341/3985",
    "sg:postcode":"87600",
    "sg:province":"Bayern",
    "wof:name":"Markus Krenek Rechtsanwalt",
    "wof:placetype":"venue"
},
  "geometry": {"coordinates":[10.5956487656,47.8748626709],"type":"Point"}
}