{
  "type": "Feature",
  "properties": {
    "iso:country":"DE",
    "sg:address":"Falkenberger Landstr. 54 a",
    "sg:city":"Lilienthal",
    "sg:phone":"+49 4298/939437",
    "sg:postcode":"28865",
    "sg:province":"Niedersachsen",
    "wof:name":"Inplan Ingenieurgesellschaft F\u00fcr Haustechnik Mbh",
    "wof:placetype":"venue"
},
  "geometry": {"coordinates":[8.92649,53.154129],"type":"Point"}
}