{
  "type": "Feature",
  "properties": {
    "iso:country":"DE",
    "sg:address":"Westfalenstr.6",
    "sg:city":"Witten",
    "sg:postcode":"58455",
    "sg:province":"Nordrhein-Westfalen",
    "wof:name":"Christoph Genh Metallbau",
    "wof:placetype":"venue"
},
  "geometry": {"coordinates":[7.3455882072,51.4440307617],"type":"Point"}
}