{
  "type": "Feature",
  "properties": {
    "iso:country":"DE",
    "sg:address":"Hohenzollerndamm 50 A",
    "sg:city":"Berlin",
    "sg:phone":"+49 30/8231751",
    "sg:postcode":"14199",
    "sg:province":"Berlin",
    "wof:name":"Jean-claude Sens",
    "wof:placetype":"venue"
},
  "geometry": {"coordinates":[13.2993755341,52.4875488281],"type":"Point"}
}