{
  "type": "Feature",
  "properties": {
    "iso:country":"DE",
    "sg:address":"Homagstra\u00dfe 3-5",
    "sg:city":"Schopfloch",
    "sg:phone":"+49 7443/130",
    "sg:postcode":"72296",
    "sg:province":"Baden-W\u00fcrttemberg",
    "wof:name":"Homag Maschinenbau Ag",
    "wof:placetype":"venue"
},
  "geometry": {"coordinates":[8.5575151443,48.4578819275],"type":"Point"}
}