{
  "type": "Feature",
  "properties": {
    "iso:country":"DE",
    "sg:address":"Bei der Linde 23",
    "sg:city":"Ramsla",
    "sg:postcode":"99439",
    "sg:province":"Th\u00fcringen",
    "wof:name":"Agrargenossenschaft Kleinobringen Eg",
    "wof:placetype":"venue"
},
  "geometry": {"coordinates":[11.285395,51.05106],"type":"Point"}
}