{
  "type": "Feature",
  "properties": {
    "iso:country":"DE",
    "sg:address":"Weigert",
    "sg:city":"Iserlohn -Letmathe",
    "sg:phone":"+49 2374",
    "sg:postcode":"58642",
    "sg:province":"Nordrhein-Westfalen",
    "wof:name":"Weigert-letmathe",
    "wof:placetype":"venue"
},
  "geometry": {"coordinates":[7.61678,51.366791],"type":"Point"}
}