{
  "type": "Feature",
  "properties": {
    "iso:country":"DE",
    "sg:address":"Alte Hauptstr. 69",
    "sg:city":"D\u00fcrrr\u00f6hrsdorf-Dittersb",
    "sg:phone":"+49 35026/91787",
    "sg:postcode":"01833",
    "sg:province":"Sachsen",
    "wof:name":"S. Schulze",
    "wof:placetype":"venue"
},
  "geometry": {"coordinates":[-70.978218,42.724659],"type":"Point"}
}