{
  "type": "Feature",
  "properties": {
    "iso:country":"DE",
    "sg:address":"Jakobusstr. 14",
    "sg:city":"K\u00f6ln",
    "sg:phone":"+49 221/5903280",
    "sg:postcode":"50767",
    "sg:province":"Nordrhein-Westfalen",
    "wof:name":"Walter Klaus",
    "wof:placetype":"venue"
},
  "geometry": {"coordinates":[6.881449,50.997089],"type":"Point"}
}