{
  "type": "Feature",
  "properties": {
    "iso:country":"DE",
    "sg:address":"Wielandstr. 7",
    "sg:city":"Stuttgart",
    "sg:phone":"+49 711/651080",
    "sg:postcode":"70193",
    "sg:province":"Baden-W\u00fcrttemberg",
    "wof:name":"Bernd J. Przygodda",
    "wof:placetype":"venue"
},
  "geometry": {"coordinates":[9.1391000748,48.7759132385],"type":"Point"}
}