{
  "type": "Feature",
  "properties": {
    "iso:country":"DE",
    "sg:address":"Hauptstr. 24",
    "sg:city":"Gessertshausen",
    "sg:phone":"+49 8238/2218",
    "sg:postcode":"86459",
    "sg:province":"Bayern",
    "wof:name":"Herbert Dichtl",
    "wof:placetype":"venue"
},
  "geometry": {"coordinates":[10.7325105667,48.3309402466],"type":"Point"}
}