{
  "type": "Feature",
  "properties": {
    "iso:country":"DE",
    "sg:address":"Kuhweg 11",
    "sg:city":"Werl",
    "sg:phone":"+49 2922/2769",
    "sg:postcode":"59457",
    "sg:province":"Nordrhein-Westfalen",
    "wof:name":"Eberhard Kolter",
    "wof:placetype":"venue"
},
  "geometry": {"coordinates":[7.877883,51.537922],"type":"Point"}
}