{
  "type": "Feature",
  "properties": {
    "iso:country":"DE",
    "sg:address":"Am Schafstrieb 1-3",
    "sg:city":"Bad Orb",
    "sg:phone":"+49 6052/2551",
    "sg:postcode":"63619",
    "sg:province":"Hessen",
    "wof:name":"Karl Heim E. K.",
    "wof:placetype":"venue"
},
  "geometry": {"coordinates":[9.347651,50.233265],"type":"Point"}
}