{
  "type": "Feature",
  "properties": {
    "iso:country":"DE",
    "sg:address":"Schlo\u00dfplatz",
    "sg:city":"Friedberg",
    "sg:phone":"+49 821/605651",
    "sg:postcode":"86316",
    "sg:province":"Bayern",
    "wof:name":"Museum Friedberg - Das Uhren- Und Heimatmuseum",
    "wof:placetype":"venue"
},
  "geometry": {"coordinates":[10.979885,48.35767],"type":"Point"}
}