{
  "type": "Feature",
  "properties": {
    "iso:country":"DE",
    "sg:address":"Gewerbering 15",
    "sg:city":"L\u00fcbesse",
    "sg:phone":"+49 3868/43030",
    "sg:postcode":"19077",
    "sg:province":"Mecklenburg-Vorpommern",
    "wof:name":"Tetzlaff & Hoffmann Trockenbau Gmbh",
    "wof:placetype":"venue"
},
  "geometry": {"coordinates":[11.458469,53.494125],"type":"Point"}
}