{
  "type": "Feature",
  "properties": {
    "iso:country":"DE",
    "sg:address":"Im Letten 11",
    "sg:city":"Waldshut-Tiengen",
    "sg:phone":"+49 7751/70980",
    "sg:postcode":"79761",
    "sg:province":"Baden-W\u00fcrttemberg",
    "wof:name":"J\u00fcrgen Kuhr Rechtsanwalt",
    "wof:placetype":"venue"
},
  "geometry": {"coordinates":[8.2114095688,47.6254425049],"type":"Point"}
}