{
  "type": "Feature",
  "properties": {
    "iso:country":"DE",
    "sg:city":"Reichertshausen",
    "sg:phone":"+49 8441/2395",
    "sg:postcode":"85293",
    "sg:province":"Bayern",
    "wof:name":"Raiffeisenbank Pfaffenhofen/ilm Eg",
    "wof:placetype":"venue"
},
  "geometry": {"coordinates":[11.50715,48.46611],"type":"Point"}
}