{
  "type": "Feature",
  "properties": {
    "iso:country":"DE",
    "sg:address":"Heerstr. 374",
    "sg:city":"Dinslaken",
    "sg:phone":"+49 2064/50100",
    "sg:postcode":"46535",
    "sg:province":"Nordrhein-Westfalen",
    "wof:name":"Bernhard Olland",
    "wof:placetype":"venue"
},
  "geometry": {"coordinates":[6.6981091499,51.5669021606],"type":"Point"}
}