{
  "type": "Feature",
  "properties": {
    "iso:country":"DE",
    "sg:address":"Griegstr. 19",
    "sg:city":"M\u00fcnchen",
    "sg:phone":"+49 89/3597195",
    "sg:postcode":"80807",
    "sg:province":"Bayern",
    "wof:name":"Akwa Textilhandel Und Agentur Gmbh",
    "wof:placetype":"venue"
},
  "geometry": {"coordinates":[11.5789928436,48.1827163696],"type":"Point"}
}