{
  "type": "Feature",
  "properties": {
    "iso:country":"DE",
    "sg:address":"Hauptstr. 7",
    "sg:city":"Limbach-Oberfrohna",
    "sg:phone":"+49 3722/93352",
    "sg:postcode":"09212",
    "sg:province":"Sachsen",
    "wof:name":"Egon Sonntag",
    "wof:placetype":"venue"
},
  "geometry": {"coordinates":[12.7357769012,50.8686408997],"type":"Point"}
}