{
  "type": "Feature",
  "properties": {
    "iso:country":"DE",
    "sg:address":"Kleine Wiese",
    "sg:city":"Behringen",
    "sg:postcode":"99947",
    "sg:province":"Th\u00fcringen",
    "wof:name":"Wolfbehringer Parkettver- Triebs Gmbh",
    "wof:placetype":"venue"
},
  "geometry": {"coordinates":[10.647315,51.104912],"type":"Point"}
}