{
  "type": "Feature",
  "properties": {
    "iso:country":"DE",
    "sg:address":"Am Bl\u00fctenring 66",
    "sg:city":"M\u00fcnchen",
    "sg:phone":"+49 89/3227294",
    "sg:postcode":"80939",
    "sg:province":"Bayern",
    "wof:name":"Georg Mayr Architekt",
    "wof:placetype":"venue"
},
  "geometry": {"coordinates":[11.631146,48.195835],"type":"Point"}
}