{
  "type": "Feature",
  "properties": {
    "iso:country":"DE",
    "sg:address":"Rennbahnstr. 115",
    "sg:city":"Hamburg",
    "sg:phone":"+49 40/65585400",
    "sg:postcode":"22111",
    "sg:province":"Hamburg",
    "wof:name":"Archiv Des Bunds Evangelisch- Freikirchlicher Gemeinden",
    "wof:placetype":"venue"
},
  "geometry": {"coordinates":[10.079692,53.561676],"type":"Point"}
}