{
  "type": "Feature",
  "properties": {
    "iso:country":"DE",
    "sg:address":"Michaelsbergstr. 21",
    "sg:city":"Bruchsal",
    "sg:phone":"+49 7257/1417",
    "sg:postcode":"76646",
    "sg:province":"Baden-W\u00fcrttemberg",
    "wof:name":"Rolf Kussmann Steuerberater",
    "wof:placetype":"venue"
},
  "geometry": {"coordinates":[8.555770874,49.0878334045],"type":"Point"}
}