{
  "type": "Feature",
  "properties": {
    "iso:country":"DE",
    "sg:address":"Bahnhofstr. 17",
    "sg:city":"Schmallenberg",
    "sg:phone":"+49 2972/1618",
    "sg:postcode":"57392",
    "sg:province":"Nordrhein-Westfalen",
    "wof:name":"H. Pr\u00f6pper",
    "wof:placetype":"venue"
},
  "geometry": {"coordinates":[8.2886838913,51.1564331055],"type":"Point"}
}