{
  "type": "Feature",
  "properties": {
    "iso:country":"DE",
    "sg:address":"Langendellschlag 103",
    "sg:city":"Wiesbaden",
    "sg:postcode":"65199",
    "sg:province":"Hessen",
    "wof:name":"Feierabendheim Simoenhaus Gmbh",
    "wof:placetype":"venue"
},
  "geometry": {"coordinates":[8.183684,50.090763],"type":"Point"}
}