{
  "type": "Feature",
  "properties": {
    "iso:country":"DE",
    "sg:address":"L\u00f6hestr 12",
    "sg:city":"Hennef",
    "sg:phone":"+49 2242/868180",
    "sg:postcode":"53773",
    "sg:province":"Nordrhein-Westfalen",
    "wof:name":"Broich Systemtechnik F\u00f6rderanlagen Und Systeme",
    "wof:placetype":"venue"
},
  "geometry": {"coordinates":[7.259283,50.784439],"type":"Point"}
}