{
  "type": "Feature",
  "properties": {
    "iso:country":"DE",
    "sg:address":"Am Riedweg 2",
    "sg:city":"Salem",
    "sg:phone":"+49 4927/515007",
    "sg:postcode":"88682",
    "sg:province":"Baden-W\u00fcrttemberg",
    "wof:name":"Raiffeisengenossenschaft Wittgenstein-hallenberg E.g.",
    "wof:placetype":"venue"
},
  "geometry": {"coordinates":[8.3679151535,51.0343704224],"type":"Point"}
}