{
  "type": "Feature",
  "properties": {
    "iso:country":"DE",
    "sg:address":"Reiterweg 6",
    "sg:city":"Uhler",
    "sg:phone":"+49 6762/8034",
    "sg:postcode":"56290",
    "sg:province":"Rheinland-Pfalz",
    "wof:name":"Weber",
    "wof:placetype":"venue"
},
  "geometry": {"coordinates":[7.433947,50.086639],"type":"Point"}
}