{
  "type": "Feature",
  "properties": {
    "iso:country":"DE",
    "sg:address":"Lindeistr. 23",
    "sg:city":"Gernrode",
    "sg:phone":"+49 36076/52596",
    "sg:postcode":"37339",
    "sg:province":"Th\u00fcringen",
    "wof:name":"F. Holbein",
    "wof:placetype":"venue"
},
  "geometry": {"coordinates":[10.411248,51.395737],"type":"Point"}
}