{
  "type": "Feature",
  "properties": {
    "iso:country":"DE",
    "sg:address":"Luisenstr. 15",
    "sg:city":"Duisburg",
    "sg:postcode":"47119",
    "sg:province":"Nordrhein-Westfalen",
    "wof:name":"Michael Abendroth",
    "wof:placetype":"venue"
},
  "geometry": {"coordinates":[6.737176,51.453136],"type":"Point"}
}