{
  "type": "Feature",
  "properties": {
    "iso:country":"DE",
    "sg:address":"Friedrich-Ebert-Str. 16",
    "sg:city":"Landau",
    "sg:phone":"+49 6341/88521",
    "sg:postcode":"76829",
    "sg:province":"Rheinland-Pfalz",
    "wof:name":"C. Sauer",
    "wof:placetype":"venue"
},
  "geometry": {"coordinates":[8.1171836853,49.1925621033],"type":"Point"}
}