{
  "type": "Feature",
  "properties": {
    "iso:country":"DE",
    "sg:address":"Berthold-Haupt-Str. 102",
    "sg:city":"Dresden",
    "sg:postcode":"01259",
    "sg:province":"Sachsen",
    "wof:name":"Intermedia-vermittlungsagen- Tur Gmbh",
    "wof:placetype":"venue"
},
  "geometry": {"coordinates":[13.8613853455,51.0091705322],"type":"Point"}
}