{
  "type": "Feature",
  "properties": {
    "iso:country":"DE",
    "sg:address":"Judengasse 29 a",
    "sg:city":"Wei\u00dfenburg",
    "sg:postcode":"91781",
    "sg:province":"Bayern",
    "wof:name":"Vkrg Service Gmbh",
    "wof:placetype":"venue"
},
  "geometry": {"coordinates":[10.974915,49.029827],"type":"Point"}
}