{
  "type": "Feature",
  "properties": {
    "iso:country":"DE",
    "sg:address":"Immermannstr. 43",
    "sg:city":"D\u00fcsseldorf",
    "sg:phone":"+49 211/354052",
    "sg:postcode":"40210",
    "sg:province":"Nordrhein-Westfalen",
    "wof:name":"Mitsubishi Chemical Europe Gmbh",
    "wof:placetype":"venue"
},
  "geometry": {"coordinates":[6.789095,51.222893],"type":"Point"}
}