{
  "type": "Feature",
  "properties": {
    "iso:country":"DE",
    "sg:address":"Schwarzer Weg 11",
    "sg:city":"Ottersberg",
    "sg:postcode":"28870",
    "sg:province":"Niedersachsen",
    "wof:name":"Nisa-elektronik Gmbh",
    "wof:placetype":"venue"
},
  "geometry": {"coordinates":[9.1243152618,53.0956916809],"type":"Point"}
}