{
  "type": "Feature",
  "properties": {
    "iso:country":"DE",
    "sg:address":"Eschersheimer Landstr. 68",
    "sg:city":"Frankfurt",
    "sg:phone":"+49 69/550064",
    "sg:postcode":"60322",
    "sg:province":"Hessen",
    "wof:name":"L. W. Bau Lehrer & Wiedemann Bautr\u00e4gerobjekt-vertrieb Und",
    "wof:placetype":"venue"
},
  "geometry": {"coordinates":[8.675811,50.123074],"type":"Point"}
}