{
  "type": "Feature",
  "properties": {
    "iso:country":"DE",
    "sg:address":"M\u00fchlentorstr. 1",
    "sg:city":"Lingen",
    "sg:phone":"+49 591/3293",
    "sg:postcode":"49808",
    "sg:province":"Niedersachsen",
    "wof:name":"Leder Heger-berensen Gmbh",
    "wof:placetype":"venue"
},
  "geometry": {"coordinates":[7.314626,52.523781],"type":"Point"}
}