{
  "type": "Feature",
  "properties": {
    "iso:country":"DE",
    "sg:address":"Ballengasse 23",
    "sg:city":"Garmisch-Partenkirchen",
    "sg:phone":"+49 8821/52827",
    "sg:postcode":"82467",
    "sg:province":"Bayern",
    "wof:name":"Max Konstanzer",
    "wof:placetype":"venue"
},
  "geometry": {"coordinates":[11.112793,47.494511],"type":"Point"}
}