{
  "type": "Feature",
  "properties": {
    "iso:country":"DE",
    "sg:address":"Hauptstr. 137",
    "sg:city":"Niederkr\u00fcchten",
    "sg:phone":"+49 2163/81885",
    "sg:postcode":"41372",
    "sg:province":"Nordrhein-Westfalen",
    "wof:name":"Grebau Bautr\u00e4gerges. Mbh",
    "wof:placetype":"venue"
},
  "geometry": {"coordinates":[6.150994,51.209438],"type":"Point"}
}