{
  "type": "Feature",
  "properties": {
    "iso:country":"DE",
    "sg:address":"Ingolst\u00e4dter Str. 58",
    "sg:city":"M\u00fcnchen",
    "sg:postcode":"80939",
    "sg:province":"Bayern",
    "wof:name":"J. S. Keiler Gmbh",
    "wof:placetype":"venue"
},
  "geometry": {"coordinates":[11.5843410492,48.1919403076],"type":"Point"}
}