{
  "type": "Feature",
  "properties": {
    "iso:country":"DE",
    "sg:address":"Werlestr. 37",
    "sg:city":"Wuppertal",
    "sg:phone":"+49 202/626246",
    "sg:postcode":"42289",
    "sg:province":"Nordrhein-Westfalen",
    "wof:name":"Karl-heinz Faust",
    "wof:placetype":"venue"
},
  "geometry": {"coordinates":[7.222245,51.270351],"type":"Point"}
}