{
  "type": "Feature",
  "properties": {
    "iso:country":"DE",
    "sg:address":"Franziskanerstr. 16",
    "sg:city":"M\u00fcnchen",
    "sg:phone":"+49 89/485750",
    "sg:postcode":"81669",
    "sg:province":"Bayern",
    "wof:name":"Avimedia-akos Vida Agentur F\u00fcr Rundfunkwerbung",
    "wof:placetype":"venue"
},
  "geometry": {"coordinates":[11.5920581818,48.1264305115],"type":"Point"}
}