{
  "type": "Feature",
  "properties": {
    "iso:country":"DE",
    "sg:address":"Adam-Krapp-Str. 9",
    "sg:city":"Hirschaid",
    "sg:phone":"+49 9543/1280",
    "sg:postcode":"96114",
    "sg:province":"Bayern",
    "wof:name":"R. Und G. Wagner",
    "wof:placetype":"venue"
},
  "geometry": {"coordinates":[10.979842186,49.8055763245],"type":"Point"}
}