{
  "type": "Feature",
  "properties": {
    "iso:country":"DE",
    "sg:address":"Hauptstr. 21",
    "sg:city":"Immesheim",
    "sg:phone":"+49 6355/2232",
    "sg:postcode":"67308",
    "sg:province":"Rheinland-Pfalz",
    "wof:name":"Erich Vollet",
    "wof:placetype":"venue"
},
  "geometry": {"coordinates":[8.103941,49.63744],"type":"Point"}
}