{
  "type": "Feature",
  "properties": {
    "iso:country":"DE",
    "sg:address":"B\u00fcrgermeister-Fischer-Str. 6",
    "sg:city":"Augsburg",
    "sg:phone":"+49 821/31530",
    "sg:postcode":"86150",
    "sg:province":"Bayern",
    "wof:name":"Karstadt Warenhaus Ag",
    "wof:placetype":"venue"
},
  "geometry": {"coordinates":[10.89626,48.366962],"type":"Point"}
}