{
  "type": "Feature",
  "properties": {
    "iso:country":"DE",
    "sg:address":"Zinneberger Str. 11",
    "sg:city":"Glonn",
    "sg:phone":"+49 8093/3276",
    "sg:postcode":"85625",
    "sg:province":"Bayern",
    "wof:name":"U. Kargl",
    "wof:placetype":"venue"
},
  "geometry": {"coordinates":[11.874751,47.988834],"type":"Point"}
}