{
  "type": "Feature",
  "properties": {
    "iso:country":"DE",
    "sg:address":"Am Sandfeld 18",
    "sg:city":"Karlsruhe",
    "sg:phone":"+49 721/783930",
    "sg:postcode":"76149",
    "sg:province":"Baden-W\u00fcrttemberg",
    "wof:name":"Cti Labs Ag",
    "wof:placetype":"venue"
},
  "geometry": {"coordinates":[8.3917503357,49.0424156189],"type":"Point"}
}