{
  "type": "Feature",
  "properties": {
    "iso:country":"DE",
    "sg:address":"Pliensaustr. 42",
    "sg:city":"Esslingen",
    "sg:phone":"+49 711/359540",
    "sg:postcode":"73728",
    "sg:province":"Baden-W\u00fcrttemberg",
    "wof:name":"Georg Kocher",
    "wof:placetype":"venue"
},
  "geometry": {"coordinates":[9.304328,48.738701],"type":"Point"}
}