{
  "type": "Feature",
  "properties": {
    "iso:country":"DE",
    "sg:address":"Hauptstr. 132a",
    "sg:city":"Rebesgr\u00fcn",
    "sg:phone":"+49 3744/217080",
    "sg:postcode":"08209",
    "sg:province":"Sachsen",
    "wof:name":"Walther Gmbh",
    "wof:placetype":"venue"
},
  "geometry": {"coordinates":[12.3779249191,50.5198745728],"type":"Point"}
}