{
  "type": "Feature",
  "properties": {
    "iso:country":"DE",
    "sg:address":"Jakobstr. 22",
    "sg:city":"Schiffweiler",
    "sg:phone":"+49 6821/692460",
    "sg:postcode":"66578",
    "sg:province":"Saarland",
    "wof:name":"J. Henkel",
    "wof:placetype":"venue"
},
  "geometry": {"coordinates":[7.095824,49.356228],"type":"Point"}
}