{
  "type": "Feature",
  "properties": {
    "iso:country":"DE",
    "sg:address":"Leonhardsberg 1",
    "sg:city":"Gessertshausen",
    "sg:phone":"+49 8238/2252",
    "sg:postcode":"86459",
    "sg:province":"Bayern",
    "wof:name":"M. M\u00fcller",
    "wof:placetype":"venue"
},
  "geometry": {"coordinates":[10.7335090637,48.3293609619],"type":"Point"}
}