{
  "type": "Feature",
  "properties": {
    "iso:country":"DE",
    "sg:address":"S\u00fcdstr. 37",
    "sg:city":"H\u00fcckelhoven",
    "sg:phone":"+49 2462/8149",
    "sg:postcode":"41836",
    "sg:province":"Nordrhein-Westfalen",
    "wof:name":"Franz-gerd G\u00f6bbels",
    "wof:placetype":"venue"
},
  "geometry": {"coordinates":[6.245522,51.002613],"type":"Point"}
}