{
  "type": "Feature",
  "properties": {
    "iso:country":"DE",
    "sg:address":"Im Schiereick 32",
    "sg:city":"Garbsen",
    "sg:phone":"+49 5131/51258",
    "sg:postcode":"30826",
    "sg:province":"Niedersachsen",
    "wof:name":"Gerd Grigutsch",
    "wof:placetype":"venue"
},
  "geometry": {"coordinates":[9.56129,52.454575],"type":"Point"}
}