{
  "type": "Feature",
  "properties": {
    "iso:country":"DE",
    "sg:city":"Marktschellenberg",
    "sg:phone":"+49 8650/358",
    "sg:postcode":"83487",
    "sg:province":"Bayern",
    "wof:name":"Uwe Werner",
    "wof:placetype":"venue"
},
  "geometry": {"coordinates":[13.047831,47.694214],"type":"Point"}
}