{
  "type": "Feature",
  "properties": {
    "iso:country":"DE",
    "sg:address":"R\u00fcgenstr. 9",
    "sg:city":"Rietberg",
    "sg:phone":"+49 5244/8157",
    "sg:postcode":"33397",
    "sg:province":"Nordrhein-Westfalen",
    "wof:name":"Andreas Rath",
    "wof:placetype":"venue"
},
  "geometry": {"coordinates":[8.4283866882,51.8081550598],"type":"Point"}
}