{
  "type": "Feature",
  "properties": {
    "iso:country":"DE",
    "sg:address":"Trierer Str. 36",
    "sg:city":"Hermeskeil",
    "sg:phone":"+49 6503/1887",
    "sg:postcode":"54411",
    "sg:province":"Rheinland-Pfalz",
    "wof:name":"Orthop\u00e4die Bonert Gmbh",
    "wof:placetype":"venue"
},
  "geometry": {"coordinates":[6.9456620216,49.6557502747],"type":"Point"}
}