{
  "type": "Feature",
  "properties": {
    "iso:country":"DE",
    "sg:address":"Bachstr. 9",
    "sg:city":"Dillingen",
    "sg:phone":"+49 9071/3144",
    "sg:postcode":"89407",
    "sg:province":"Bayern",
    "wof:name":"Werner Kreis",
    "wof:placetype":"venue"
},
  "geometry": {"coordinates":[10.4728240967,48.5817298889],"type":"Point"}
}