{
  "type": "Feature",
  "properties": {
    "iso:country":"DE",
    "sg:address":"Kilianstr. 138",
    "sg:city":"N\u00fcrnberg",
    "sg:phone":"+49 911/364949",
    "sg:postcode":"90425",
    "sg:province":"Bayern",
    "wof:name":"Pandarent Autovermietung Gmbh",
    "wof:placetype":"venue"
},
  "geometry": {"coordinates":[11.083874,49.473598],"type":"Point"}
}