{
  "type": "Feature",
  "properties": {
    "iso:country":"DE",
    "sg:address":"Spenger Str 46",
    "sg:city":"Melle",
    "sg:phone":"+49 5226/98210",
    "sg:postcode":"49328",
    "sg:province":"Niedersachsen",
    "wof:name":"Kh System M\u00f6bel Gmbh",
    "wof:placetype":"venue"
},
  "geometry": {"coordinates":[8.4633169174,52.1940574646],"type":"Point"}
}