{
  "type": "Feature",
  "properties": {
    "iso:country":"DE",
    "sg:address":"Robert-Bosch-Str. 1",
    "sg:city":"Magstadt",
    "sg:postcode":"71106",
    "sg:province":"Baden-W\u00fcrttemberg",
    "wof:name":"E. G. Seeger Drucker- Zeugnisse Vertriebs- Gmbh",
    "wof:placetype":"venue"
},
  "geometry": {"coordinates":[8.9668054581,48.7371635437],"type":"Point"}
}