{
  "type": "Feature",
  "properties": {
    "iso:country":"DE",
    "sg:address":"Schulstr. 21",
    "sg:city":"Vienenburg",
    "sg:phone":"+49 5324/71850",
    "sg:postcode":"38690",
    "sg:province":"Niedersachsen",
    "wof:name":"J\u00f6rg Krause",
    "wof:placetype":"venue"
},
  "geometry": {"coordinates":[10.5655355453,51.9521865845],"type":"Point"}
}