{
  "type": "Feature",
  "properties": {
    "iso:country":"DE",
    "sg:address":"Th\u00fcrmerstr. 1",
    "sg:city":"M\u00fcnchen",
    "sg:phone":"+49 89/1496697",
    "sg:postcode":"80992",
    "sg:province":"Bayern",
    "wof:name":"J. Finkenzeller Mech. Werkstatt",
    "wof:placetype":"venue"
},
  "geometry": {"coordinates":[11.510804,48.174557],"type":"Point"}
}