{
  "type": "Feature",
  "properties": {
    "iso:country":"DE",
    "sg:city":"Oberkollbach",
    "sg:phone":"+49 4970/516844",
    "sg:postcode":"75394",
    "sg:province":"Baden-W\u00fcrttemberg",
    "wof:name":"Kreissparkasse Calw",
    "wof:placetype":"venue"
},
  "geometry": {"coordinates":[8.684885,48.746815],"type":"Point"}
}