{
  "type": "Feature",
  "properties": {
    "iso:country":"DE",
    "sg:address":"B\u00e4rnsdorfer Str. 185",
    "sg:city":"Dresden",
    "sg:phone":"+49 351/82130",
    "sg:postcode":"01127",
    "sg:province":"Sachsen",
    "wof:name":"Hotel Novalis",
    "wof:placetype":"venue"
},
  "geometry": {"coordinates":[13.7381219864,51.0862312317],"type":"Point"}
}