{
  "type": "Feature",
  "properties": {
    "iso:country":"DE",
    "sg:address":"Wittenburger Str. 65",
    "sg:city":"Schwerin",
    "sg:phone":"+49 385/732501",
    "sg:postcode":"19053",
    "sg:province":"Mecklenburg-Vorpommern",
    "wof:name":"Prontaprint Inh. Gerhard Sch\u00e4fer",
    "wof:placetype":"venue"
},
  "geometry": {"coordinates":[11.401938,53.62899],"type":"Point"}
}