{
  "type": "Feature",
  "properties": {
    "iso:country":"DE",
    "sg:address":"Erich-Correns-Ring 2",
    "sg:city":"Rudolstadt",
    "sg:phone":"+49 3672/3740",
    "sg:postcode":"07407",
    "sg:province":"Th\u00fcringen",
    "wof:name":"Ringhotel",
    "wof:placetype":"venue"
},
  "geometry": {"coordinates":[11.3221769333,50.6998252869],"type":"Point"}
}