{
  "type": "Feature",
  "properties": {
    "iso:country":"DE",
    "sg:address":"Bachstr. 23",
    "sg:city":"H\u00fcrth",
    "sg:phone":"+49 2233/65114",
    "sg:postcode":"50354",
    "sg:province":"Nordrhein-Westfalen",
    "wof:name":"Bernd H\u00fclzer",
    "wof:placetype":"venue"
},
  "geometry": {"coordinates":[6.8949007988,50.8946723938],"type":"Point"}
}