{
  "type": "Feature",
  "properties": {
    "iso:country":"DE",
    "sg:address":"Lauterachstr. 53",
    "sg:city":"Lauterhofen",
    "sg:phone":"+49 9186/246",
    "sg:postcode":"92283",
    "sg:province":"Bayern",
    "wof:name":"Ludwig Rubenbauer",
    "wof:placetype":"venue"
},
  "geometry": {"coordinates":[11.6041440964,49.3692779541],"type":"Point"}
}