{
  "type": "Feature",
  "properties": {
    "iso:country":"DE",
    "sg:address":"Oedinger Str. 5",
    "sg:city":"Schmallenberg",
    "sg:phone":"+49 2725/395",
    "sg:postcode":"57392",
    "sg:province":"Nordrhein-Westfalen",
    "wof:name":"Heribert Poggel",
    "wof:placetype":"venue"
},
  "geometry": {"coordinates":[8.164998,51.166328],"type":"Point"}
}