{
  "type": "Feature",
  "properties": {
    "iso:country":"DE",
    "sg:address":"Lerchenauer Str. 147",
    "sg:city":"M\u00fcnchen",
    "sg:phone":"+49 89/3515247",
    "sg:postcode":"80935",
    "sg:province":"Bayern",
    "wof:name":"Straub Grundbesitz Gmbh & Co.",
    "wof:placetype":"venue"
},
  "geometry": {"coordinates":[11.5484571457,48.191860199],"type":"Point"}
}