{
  "type": "Feature",
  "properties": {
    "iso:country":"DE",
    "sg:address":"Rheinstr. 101",
    "sg:city":"Wiesbaden",
    "sg:phone":"+49 611/372358",
    "sg:postcode":"65185",
    "sg:province":"Hessen",
    "wof:name":"Hans J. Von Goetz Inh. G\u00fcnther Lotz",
    "wof:placetype":"venue"
},
  "geometry": {"coordinates":[8.232311,50.077602],"type":"Point"}
}