{
  "type": "Feature",
  "properties": {
    "iso:country":"DE",
    "sg:address":"Kirchstr. 3",
    "sg:city":"Betzigau",
    "sg:phone":"+49 831/79119",
    "sg:postcode":"87488",
    "sg:province":"Bayern",
    "wof:name":"Wei\u00df Und Kuhn",
    "wof:placetype":"venue"
},
  "geometry": {"coordinates":[10.37938,47.735561],"type":"Point"}
}