{
  "type": "Feature",
  "properties": {
    "iso:country":"DE",
    "sg:address":"Industriestr. 1",
    "sg:city":"Lohne",
    "sg:phone":"+49 4442/80040",
    "sg:postcode":"49393",
    "sg:province":"Niedersachsen",
    "wof:name":"Bmc Menke Gmbh",
    "wof:placetype":"venue"
},
  "geometry": {"coordinates":[8.193242,52.659721],"type":"Point"}
}