{
  "type": "Feature",
  "properties": {
    "iso:country":"DE",
    "sg:address":"Im Winkel 1",
    "sg:city":"Marzahna",
    "sg:postcode":"14913",
    "sg:province":"Brandenburg",
    "wof:name":"Evangelisches Pfarramt",
    "wof:placetype":"venue"
},
  "geometry": {"coordinates":[13.0754060745,51.9901618958],"type":"Point"}
}