{
  "type": "Feature",
  "properties": {
    "iso:country":"DE",
    "sg:address":"Gro\u00dfmelten 49",
    "sg:city":"\u00d6lbronn-D\u00fcrrn",
    "sg:phone":"+49 7043/40066",
    "sg:postcode":"75248",
    "sg:province":"Baden-W\u00fcrttemberg",
    "wof:name":"Ibt Privates Institut F\u00fcr Biologische Therapien Gmbh",
    "wof:placetype":"venue"
},
  "geometry": {"coordinates":[8.7555761337,48.9821548462],"type":"Point"}
}