{
  "type": "Feature",
  "properties": {
    "iso:country":"DE",
    "sg:address":"Breite Str. 5",
    "sg:city":"Arzberg",
    "sg:phone":"+49 34222/40253",
    "sg:postcode":"04886",
    "sg:province":"Sachsen",
    "wof:name":"Lothar Thiere",
    "wof:placetype":"venue"
},
  "geometry": {"coordinates":[13.0798101425,51.566619873],"type":"Point"}
}