{
  "type": "Feature",
  "properties": {
    "iso:country":"DE",
    "sg:address":"Im Hinninghofen 54",
    "sg:city":"Essen",
    "sg:phone":"+49 2054/5945",
    "sg:postcode":"45219",
    "sg:province":"Nordrhein-Westfalen",
    "wof:name":"Franz Kellersmann Industrievertretung F\u00fcr",
    "wof:placetype":"venue"
},
  "geometry": {"coordinates":[6.9466838837,51.3694038391],"type":"Point"}
}