{
  "type": "Feature",
  "properties": {
    "iso:country":"DE",
    "sg:address":"Marienstr. 88",
    "sg:city":"Hof",
    "sg:postcode":"95028",
    "sg:province":"Bayern",
    "wof:name":"Nnh Nutzfahrzeughandel Gmbh",
    "wof:placetype":"venue"
},
  "geometry": {"coordinates":[11.91171,50.313004],"type":"Point"}
}