{
  "type": "Feature",
  "properties": {
    "iso:country":"DE",
    "sg:address":"Nelkenstr. 17",
    "sg:city":"Bruckm\u00fchl",
    "sg:phone":"+49 8062/3513",
    "sg:postcode":"83052",
    "sg:province":"Bayern",
    "wof:name":"K\u00e4the Gr\u00fcnbauer",
    "wof:placetype":"venue"
},
  "geometry": {"coordinates":[11.9434680939,47.8764724731],"type":"Point"}
}