{
  "type": "Feature",
  "properties": {
    "iso:country":"DE",
    "sg:address":"Weserstr. 104",
    "sg:city":"Wilhelmshaven",
    "sg:phone":"+49 4421/41153",
    "sg:postcode":"26382",
    "sg:province":"Niedersachsen",
    "wof:name":"Lehmann & Zille",
    "wof:placetype":"venue"
},
  "geometry": {"coordinates":[8.1134681702,53.5161590576],"type":"Point"}
}