{
  "type": "Feature",
  "properties": {
    "iso:country":"DE",
    "sg:address":"Gladbecker Str. 10",
    "sg:city":"Bottrop",
    "sg:phone":"+49 2041/20290",
    "sg:postcode":"46236",
    "sg:province":"Nordrhein-Westfalen",
    "wof:name":"Wilhelm Brinkmann",
    "wof:placetype":"venue"
},
  "geometry": {"coordinates":[6.926787,51.523369],"type":"Point"}
}