{
  "type": "Feature",
  "properties": {
    "iso:country":"DE",
    "sg:address":"Hauptstr. 5",
    "sg:city":"Neustadt",
    "sg:phone":"+49 9648/392",
    "sg:postcode":"95514",
    "sg:province":"Bayern",
    "wof:name":"Hermann Bauer",
    "wof:placetype":"venue"
},
  "geometry": {"coordinates":[10.470377,51.469551],"type":"Point"}
}