{
  "type": "Feature",
  "properties": {
    "iso:country":"DE",
    "sg:address":"Quellenweg 16",
    "sg:city":"Osterode",
    "sg:postcode":"37520",
    "sg:province":"Niedersachsen",
    "wof:name":"Hanse Wohnbau Gmbh",
    "wof:placetype":"venue"
},
  "geometry": {"coordinates":[10.271963,51.729511],"type":"Point"}
}