{
  "type": "Feature",
  "properties": {
    "iso:country":"DE",
    "sg:address":"Obersontheim",
    "sg:city":"Obersontheim",
    "sg:phone":"+49 4979/73332",
    "sg:postcode":"74423",
    "sg:province":"Baden-W\u00fcrttemberg",
    "wof:name":"Sulzdorfer Bank Eg",
    "wof:placetype":"venue"
},
  "geometry": {"coordinates":[9.899014,49.057205],"type":"Point"}
}