{
  "type": "Feature",
  "properties": {
    "iso:country":"DE",
    "sg:address":"Weinbergstr. 21",
    "sg:city":"Templin",
    "sg:phone":"+49 4939/876418",
    "sg:postcode":"17268",
    "sg:province":"Brandenburg",
    "wof:name":"Rudi H\u00dclsekopf",
    "wof:placetype":"venue"
},
  "geometry": {"coordinates":[13.501953,53.12484],"type":"Point"}
}