{
  "type": "Feature",
  "properties": {
    "iso:country":"DE",
    "sg:address":"Pinzberger Weg 31",
    "sg:city":"N\u00fcrnberg",
    "sg:phone":"+49 911/346575",
    "sg:postcode":"90425",
    "sg:province":"Bayern",
    "wof:name":"Cccs Computer Service Claus Christmeier",
    "wof:placetype":"venue"
},
  "geometry": {"coordinates":[11.059829,49.472328],"type":"Point"}
}