{
  "type": "Feature",
  "properties": {
    "iso:country":"DE",
    "sg:address":"V\u00f6lkershausen 1",
    "sg:city":"Willmars",
    "sg:postcode":"97647",
    "sg:province":"Bayern",
    "wof:name":"B\u00fccherei Der Gemeinde Willmars",
    "wof:placetype":"venue"
},
  "geometry": {"coordinates":[10.184628,50.47842],"type":"Point"}
}