{
  "type": "Feature",
  "properties": {
    "iso:country":"DE",
    "sg:address":"Alte Landstr. 64",
    "sg:city":"Weinheim",
    "sg:phone":"+49 6201/12865",
    "sg:postcode":"69469",
    "sg:province":"Baden-W\u00fcrttemberg",
    "wof:name":"H. Wetzel Kohlen-handlung",
    "wof:placetype":"venue"
},
  "geometry": {"coordinates":[8.666334,49.561035],"type":"Point"}
}