{
  "type": "Feature",
  "properties": {
    "iso:country":"DE",
    "sg:address":"Franz-Klingler-Str. 15",
    "sg:city":"Coburg",
    "sg:phone":"+49 9561/24126",
    "sg:postcode":"96450",
    "sg:province":"Bayern",
    "wof:name":"Anlageberatung Und Verm\u00f6gensverwaltung",
    "wof:placetype":"venue"
},
  "geometry": {"coordinates":[10.9785308838,50.2461929321],"type":"Point"}
}