{
  "type": "Feature",
  "properties": {
    "iso:country":"DE",
    "sg:address":"Marktplatz 13",
    "sg:city":"Ellwangen",
    "sg:phone":"+49 7961/53352",
    "sg:postcode":"73479",
    "sg:province":"Baden-W\u00fcrttemberg",
    "wof:name":"Singvogel Immobilienmakler",
    "wof:placetype":"venue"
},
  "geometry": {"coordinates":[10.131737709,48.9613304138],"type":"Point"}
}