{
  "type": "Feature",
  "properties": {
    "iso:country":"DE",
    "sg:address":"Leierndorfer Str. 8",
    "sg:city":"Langquaid",
    "sg:postcode":"84085",
    "sg:province":"Bayern",
    "wof:name":"A. Aumeier",
    "wof:placetype":"venue"
},
  "geometry": {"coordinates":[12.052482605,48.8225097656],"type":"Point"}
}