{
  "type": "Feature",
  "properties": {
    "iso:country":"DE",
    "sg:address":"Anton-Hops-Str. 5",
    "sg:city":"Villingen-Schwenningen",
    "sg:phone":"+49 7721/30461",
    "sg:postcode":"78050",
    "sg:province":"Baden-W\u00fcrttemberg",
    "wof:name":"Wilhelm Summ",
    "wof:placetype":"venue"
},
  "geometry": {"coordinates":[8.4539060593,48.0557365417],"type":"Point"}
}