{
  "type": "Feature",
  "properties": {
    "iso:country":"DE",
    "sg:address":"Hardtstr. 8",
    "sg:city":"Winterberg",
    "sg:phone":"+49 2981/3562",
    "sg:postcode":"59955",
    "sg:province":"Nordrhein-Westfalen",
    "wof:name":"Cb-luftsport",
    "wof:placetype":"venue"
},
  "geometry": {"coordinates":[8.567191124,51.1539535522],"type":"Point"}
}