{
  "type": "Feature",
  "properties": {
    "iso:country":"DE",
    "sg:address":"Oberbank 7",
    "sg:city":"Dortmund",
    "sg:phone":"+49 231/172520",
    "sg:postcode":"44149",
    "sg:province":"Nordrhein-Westfalen",
    "wof:name":"K. W. D\u00fcwell",
    "wof:placetype":"venue"
},
  "geometry": {"coordinates":[7.417888,51.501797],"type":"Point"}
}