{
  "type": "Feature",
  "properties": {
    "iso:country":"DE",
    "sg:address":"Mettlerkampsweg 6",
    "sg:city":"Hamburg",
    "sg:phone":"+49 40/2191992",
    "sg:postcode":"20535",
    "sg:province":"Hamburg",
    "wof:name":"Kurbad Lachmann-ehlers Riko Lachmann",
    "wof:placetype":"venue"
},
  "geometry": {"coordinates":[10.066151,53.556004],"type":"Point"}
}