{
  "type": "Feature",
  "properties": {
    "iso:country":"DE",
    "sg:address":"Freiligrathstr. 2",
    "sg:city":"Dreieich",
    "sg:phone":"+49 6103/34567",
    "sg:postcode":"63303",
    "sg:province":"Hessen",
    "wof:name":"Joachim Br\u00fccher",
    "wof:placetype":"venue"
},
  "geometry": {"coordinates":[8.689559,50.029869],"type":"Point"}
}