{
  "type": "Feature",
  "properties": {
    "iso:country":"DE",
    "sg:address":"H\u00fclsstr. 51a",
    "sg:city":"Marl",
    "sg:phone":"+49 2365/46377",
    "sg:postcode":"45772",
    "sg:province":"Nordrhein-Westfalen",
    "wof:name":"Gisbert M\u00fcllender",
    "wof:placetype":"venue"
},
  "geometry": {"coordinates":[7.1327981949,51.6619186401],"type":"Point"}
}