{
  "type": "Feature",
  "properties": {
    "iso:country":"DE",
    "sg:address":"Rennbahnstr. 99",
    "sg:city":"Hamburg",
    "sg:phone":"+49 40/6556409",
    "sg:postcode":"22111",
    "sg:province":"Hamburg",
    "wof:name":"Gastst\u00e4tte Pony",
    "wof:placetype":"venue"
},
  "geometry": {"coordinates":[10.0801582336,53.5607643127],"type":"Point"}
}