{
  "type": "Feature",
  "properties": {
    "iso:country":"DE",
    "sg:address":"Pfarrer-Maurer-Str. 3",
    "sg:city":"Bad D\u00fcrkheim",
    "sg:phone":"+49 6322/989600",
    "sg:postcode":"67098",
    "sg:province":"Rheinland-Pfalz",
    "wof:name":"G\u00f6tzelmann Im- Und Export Gmbh",
    "wof:placetype":"venue"
},
  "geometry": {"coordinates":[8.188116,49.475742],"type":"Point"}
}