{
  "type": "Feature",
  "properties": {
    "iso:country":"DE",
    "sg:address":"Kirchstr. 4",
    "sg:city":"Leiningen",
    "sg:phone":"+49 6746/222",
    "sg:postcode":"56291",
    "sg:province":"Rheinland-Pfalz",
    "wof:name":"Felix Vogt S\u00f6hne Gmbh",
    "wof:placetype":"venue"
},
  "geometry": {"coordinates":[7.5699701309,50.1324806213],"type":"Point"}
}