{
  "type": "Feature",
  "properties": {
    "iso:country":"DE",
    "sg:address":"Regina-Ullmann-Str. 24",
    "sg:city":"M\u00fcnchen",
    "sg:postcode":"81927",
    "sg:province":"Bayern",
    "wof:name":"Paolo Bauer Gastronomie- U. Gesch\u00e4ftseinrichtung E. K.",
    "wof:placetype":"venue"
},
  "geometry": {"coordinates":[11.637982,48.1703],"type":"Point"}
}