{
  "type": "Feature",
  "properties": {
    "iso:country":"DE",
    "sg:address":"Beethovenstr. 12",
    "sg:city":"Raschau",
    "sg:phone":"+49 3774/81543",
    "sg:postcode":"08352",
    "sg:province":"Sachsen",
    "wof:name":"Petra T\u00e4nzler Masseurin",
    "wof:placetype":"venue"
},
  "geometry": {"coordinates":[12.826825,50.525253],"type":"Point"}
}