{
  "type": "Feature",
  "properties": {
    "iso:country":"DE",
    "sg:address":"Gerberstr. 3",
    "sg:city":"Iserlohn",
    "sg:phone":"+49 2371/40453",
    "sg:postcode":"58640",
    "sg:province":"Nordrhein-Westfalen",
    "wof:name":"Fritz Muth",
    "wof:placetype":"venue"
},
  "geometry": {"coordinates":[7.711043,51.418671],"type":"Point"}
}