{
  "type": "Feature",
  "properties": {
    "iso:country":"DE",
    "sg:address":"Veitstr. 24",
    "sg:city":"Berlin",
    "sg:phone":"+49 30/4309820",
    "sg:postcode":"13507",
    "sg:province":"Berlin",
    "wof:name":"Baukunst Gmbh",
    "wof:placetype":"venue"
},
  "geometry": {"coordinates":[13.281913,52.585434],"type":"Point"}
}