{
  "type": "Feature",
  "properties": {
    "iso:country":"DE",
    "sg:address":"Pattendorf 21",
    "sg:city":"Adlkofen",
    "sg:phone":"+49 8707/720",
    "sg:postcode":"84166",
    "sg:province":"Bayern",
    "wof:name":"Maier",
    "wof:placetype":"venue"
},
  "geometry": {"coordinates":[12.3367452621,48.5265045166],"type":"Point"}
}