{
  "type": "Feature",
  "properties": {
    "iso:country":"DE",
    "sg:address":"Gabelsbergerstr. 3",
    "sg:city":"Sch\u00f6ningen",
    "sg:phone":"+49 5352/2210",
    "sg:postcode":"38364",
    "sg:province":"Niedersachsen",
    "wof:name":"D. J\u00e4ger",
    "wof:placetype":"venue"
},
  "geometry": {"coordinates":[10.977129,52.13464],"type":"Point"}
}