{
  "type": "Feature",
  "properties": {
    "iso:country":"DE",
    "sg:address":"Marktplatz 20",
    "sg:city":"Eichst\u00e4tt",
    "sg:phone":"+49 8421/6765",
    "sg:postcode":"85072",
    "sg:province":"Bayern",
    "wof:name":"Schneider Ingenieur Gmbh",
    "wof:placetype":"venue"
},
  "geometry": {"coordinates":[11.183923,48.893761],"type":"Point"}
}