{
  "type": "Feature",
  "properties": {
    "iso:country":"DE",
    "sg:address":"Vordere Str. 77",
    "sg:city":"L\u00fcgde",
    "sg:phone":"+49 5281/7360",
    "sg:postcode":"32676",
    "sg:province":"Nordrhein-Westfalen",
    "wof:name":"Udo Rohde",
    "wof:placetype":"venue"
},
  "geometry": {"coordinates":[9.2459573746,51.9551696777],"type":"Point"}
}