{
  "type": "Feature",
  "properties": {
    "iso:country":"DE",
    "sg:address":"Tecklenburger Str. 5",
    "sg:city":"Lotte",
    "sg:phone":"+49 5456/1355",
    "sg:postcode":"49504",
    "sg:province":"Nordrhein-Westfalen",
    "wof:name":"Heinrich Hackmann",
    "wof:placetype":"venue"
},
  "geometry": {"coordinates":[7.897493,52.264996],"type":"Point"}
}