{
  "type": "Feature",
  "properties": {
    "iso:country":"DE",
    "sg:address":"Obernburger Str. 8",
    "sg:city":"M\u00f6mlingen",
    "sg:phone":"+49 6022/31012",
    "sg:postcode":"63853",
    "sg:province":"Bayern",
    "wof:name":"S. Oberle",
    "wof:placetype":"venue"
},
  "geometry": {"coordinates":[9.0871353149,49.8540229797],"type":"Point"}
}