{
  "type": "Feature",
  "properties": {
    "iso:country":"DE",
    "sg:address":"Hauptstr. 41",
    "sg:city":"H\u00f6hein\u00f6d",
    "sg:phone":"+49 6333/2626",
    "sg:postcode":"66989",
    "sg:province":"Rheinland-Pfalz",
    "wof:name":"Robert Bauer",
    "wof:placetype":"venue"
},
  "geometry": {"coordinates":[7.604476,49.288097],"type":"Point"}
}