{
  "type": "Feature",
  "properties": {
    "iso:country":"DE",
    "sg:address":"Rheinallee 83",
    "sg:city":"Mainz",
    "sg:phone":"+49 6131/677048",
    "sg:postcode":"55118",
    "sg:province":"Rheinland-Pfalz",
    "wof:name":"Jos. Quirin Metz & Co.",
    "wof:placetype":"venue"
},
  "geometry": {"coordinates":[8.2623300552,50.011680603],"type":"Point"}
}