{
  "type": "Feature",
  "properties": {
    "iso:country":"DE",
    "sg:address":"Turnerheimstr. 20 a",
    "sg:city":"N\u00fcrnberg",
    "sg:phone":"+49 911/661941",
    "sg:postcode":"90441",
    "sg:province":"Bayern",
    "wof:name":"Adolf & Werner Schweizer Gmbh",
    "wof:placetype":"venue"
},
  "geometry": {"coordinates":[11.0457544327,49.4282646179],"type":"Point"}
}