{
  "type": "Feature",
  "properties": {
    "iso:country":"DE",
    "sg:address":"Zimmerstr. 19",
    "sg:city":"D\u00fcsseldorf",
    "sg:phone":"+49 211/330952",
    "sg:postcode":"40215",
    "sg:province":"Nordrhein-Westfalen",
    "wof:name":"Udo Bommer",
    "wof:placetype":"venue"
},
  "geometry": {"coordinates":[6.78148,51.209843],"type":"Point"}
}