{
  "type": "Feature",
  "properties": {
    "iso:country":"DE",
    "sg:address":"Lobker Str. 1",
    "sg:city":"Sehnde",
    "sg:phone":"+49 5138/1574",
    "sg:postcode":"31319",
    "sg:province":"Niedersachsen",
    "wof:name":"Gabriel Ebeling",
    "wof:placetype":"venue"
},
  "geometry": {"coordinates":[10.014289,52.287582],"type":"Point"}
}