{
  "type": "Feature",
  "properties": {
    "iso:country":"DE",
    "sg:address":"Industristr. 13",
    "sg:city":"Achim",
    "sg:postcode":"28832",
    "sg:province":"Niedersachsen",
    "wof:name":"Abfertigungsspedition Heinrich Hoppe Gmbh & Co. Kg",
    "wof:placetype":"venue"
},
  "geometry": {"coordinates":[9.0747308731,53.0103340149],"type":"Point"}
}