{
  "type": "Feature",
  "properties": {
    "iso:country":"DE",
    "sg:address":"Welseweg 3",
    "sg:city":"Stuhr",
    "sg:phone":"+49 421/8302626",
    "sg:postcode":"28816",
    "sg:province":"Niedersachsen",
    "wof:name":"Astrid Lorentz Finanzberaterin",
    "wof:placetype":"venue"
},
  "geometry": {"coordinates":[8.7171726227,53.0327033997],"type":"Point"}
}