{
  "type": "Feature",
  "properties": {
    "iso:country":"DE",
    "sg:address":"Dresdner Str. 28",
    "sg:city":"Hohenstein-Ernstthal",
    "sg:phone":"+49 3723/3027",
    "sg:postcode":"09337",
    "sg:province":"Sachsen",
    "wof:name":"Werner Reinhold",
    "wof:placetype":"venue"
},
  "geometry": {"coordinates":[12.7100858688,50.8021888733],"type":"Point"}
}