{
  "type": "Feature",
  "properties": {
    "iso:country":"DE",
    "sg:address":"Diestedder Str. 18",
    "sg:city":"Lippetal",
    "sg:phone":"+49 2923/555",
    "sg:postcode":"59510",
    "sg:province":"Nordrhein-Westfalen",
    "wof:name":"Markus Goldstein E. K.",
    "wof:placetype":"venue"
},
  "geometry": {"coordinates":[8.1520223618,51.6795845032],"type":"Point"}
}