{
  "type": "Feature",
  "properties": {
    "iso:country":"DE",
    "sg:address":"Vorhaller Str. 13 a",
    "sg:city":"Hagen",
    "sg:phone":"+49 2331/305515",
    "sg:postcode":"58089",
    "sg:province":"Nordrhein-Westfalen",
    "wof:name":"Wilhelm Breddermann",
    "wof:placetype":"venue"
},
  "geometry": {"coordinates":[7.4295701981,51.3835296631],"type":"Point"}
}