{
  "type": "Feature",
  "properties": {
    "iso:country":"DE",
    "sg:address":"Baislingstr. 7",
    "sg:city":"Uhingen",
    "sg:phone":"+49 7161/32614",
    "sg:postcode":"73066",
    "sg:province":"Baden-W\u00fcrttemberg",
    "wof:name":"Z. Stich",
    "wof:placetype":"venue"
},
  "geometry": {"coordinates":[9.578748703,48.703502655],"type":"Point"}
}