{
  "type": "Feature",
  "properties": {
    "iso:country":"DE",
    "sg:address":"Schneeberger Str. 2",
    "sg:city":"Zschorlau",
    "sg:postcode":"08321",
    "sg:province":"Sachsen",
    "wof:name":"Ev.-methodistische Kirche",
    "wof:placetype":"venue"
},
  "geometry": {"coordinates":[12.6404743195,50.5633888245],"type":"Point"}
}