{
  "type": "Feature",
  "properties": {
    "iso:country":"DE",
    "sg:address":"Sommerfeldstr. 25",
    "sg:city":"Rodgau",
    "sg:phone":"+49 6106/4218",
    "sg:postcode":"63110",
    "sg:province":"Hessen",
    "wof:name":"Heinz Schallmayer",
    "wof:placetype":"venue"
},
  "geometry": {"coordinates":[8.888674,50.0228],"type":"Point"}
}