{
  "type": "Feature",
  "properties": {
    "iso:country":"DE",
    "sg:address":"Lie\u00dfemer Str. 38",
    "sg:city":"Bonn",
    "sg:phone":"+49 4922/8342094",
    "sg:postcode":"53179",
    "sg:province":"Nordrhein-Westfalen",
    "wof:name":"Martin U. Gabi Balas",
    "wof:placetype":"venue"
},
  "geometry": {"coordinates":[7.170586,50.66077],"type":"Point"}
}