{
  "type": "Feature",
  "properties": {
    "iso:country":"DE",
    "sg:address":"Hauptstr. 39",
    "sg:city":"Weng",
    "sg:phone":"+49 8702/582",
    "sg:postcode":"84187",
    "sg:province":"Bayern",
    "wof:name":"Ludwig Held",
    "wof:placetype":"venue"
},
  "geometry": {"coordinates":[12.369284,48.658756],"type":"Point"}
}