{
  "type": "Feature",
  "properties": {
    "iso:country":"DE",
    "sg:address":"Marktplatz 3",
    "sg:city":"Wertingen",
    "sg:phone":"+49 8272/2456",
    "sg:postcode":"86637",
    "sg:province":"Bayern",
    "wof:name":"Willi Meyer Gmbh",
    "wof:placetype":"venue"
},
  "geometry": {"coordinates":[10.6826305389,48.5623397827],"type":"Point"}
}