{
  "type": "Feature",
  "properties": {
    "iso:country":"DE",
    "sg:address":"Dorfplatz 12",
    "sg:city":"Zesch am See",
    "sg:phone":"+49 33704/67020",
    "sg:postcode":"15838",
    "sg:province":"Brandenburg",
    "wof:name":"Internet Informationsportal Yambou.de",
    "wof:placetype":"venue"
},
  "geometry": {"coordinates":[13.40193,52.168114],"type":"Point"}
}