{
  "type": "Feature",
  "properties": {
    "iso:country":"DE",
    "sg:address":"Im Plackenbruch 20",
    "sg:city":"Bergisch Gladbach",
    "sg:phone":"+49 2202/82912",
    "sg:postcode":"51467",
    "sg:province":"Nordrhein-Westfalen",
    "wof:name":"Bauunternehmung Buhr Gmbh",
    "wof:placetype":"venue"
},
  "geometry": {"coordinates":[7.083451,51.012581],"type":"Point"}
}