{
  "type": "Feature",
  "properties": {
    "iso:country":"DE",
    "sg:address":"Mainzer Landstr. 377",
    "sg:city":"Frankfurt /Main",
    "sg:phone":"+49 69/7503308",
    "sg:postcode":"60326",
    "sg:province":"Hessen",
    "wof:name":"Arnold Aufbereitungs-technik",
    "wof:placetype":"venue"
},
  "geometry": {"coordinates":[8.6324110031,50.101776123],"type":"Point"}
}