{
  "type": "Feature",
  "properties": {
    "iso:country":"DE",
    "sg:address":"Ostendorf 23 a",
    "sg:city":"Horstmar",
    "sg:postcode":"48612",
    "sg:province":"Nordrhein-Westfalen",
    "wof:name":"Monnika L. Eberingh Architektin",
    "wof:placetype":"venue"
},
  "geometry": {"coordinates":[7.327489,52.103539],"type":"Point"}
}