{
  "type": "Feature",
  "properties": {
    "iso:country":"DE",
    "sg:address":"Am Nienhaushof 25",
    "sg:city":"Duisburg",
    "sg:postcode":"47139",
    "sg:province":"Nordrhein-Westfalen",
    "wof:name":"Ingenieurgemeinschaft F\u00fcr Fahrzeugtechnik Und Maschinen",
    "wof:placetype":"venue"
},
  "geometry": {"coordinates":[6.7187619209,51.4770469666],"type":"Point"}
}