{
  "type": "Feature",
  "properties": {
    "iso:country":"DE",
    "sg:address":"Madlower Hauptstr. 43",
    "sg:city":"Cottbus",
    "sg:postcode":"03050",
    "sg:province":"Brandenburg",
    "wof:name":"Elster-ausbau Gmbh",
    "wof:placetype":"venue"
},
  "geometry": {"coordinates":[14.344432,51.722935],"type":"Point"}
}