{
  "type": "Feature",
  "properties": {
    "iso:country":"DE",
    "sg:address":"Postplatz 17",
    "sg:city":"B\u00f6blingen",
    "sg:phone":"+49 7031/224998",
    "sg:postcode":"71032",
    "sg:province":"Baden-W\u00fcrttemberg",
    "wof:name":"\u00c4nderungsschneiderei",
    "wof:placetype":"venue"
},
  "geometry": {"coordinates":[9.0151844025,48.6856422424],"type":"Point"}
}