{
  "type": "Feature",
  "properties": {
    "iso:country":"DE",
    "sg:address":"Chemnitztalstr. 244",
    "sg:city":"Chemnitz",
    "sg:phone":"+49 371/441532",
    "sg:postcode":"09114",
    "sg:province":"Sachsen",
    "wof:name":"Lignum-bau Gmbh",
    "wof:placetype":"venue"
},
  "geometry": {"coordinates":[12.9003400803,50.8810310364],"type":"Point"}
}