{
  "type": "Feature",
  "properties": {
    "iso:country":"DE",
    "sg:address":"Klinkerstr. 4",
    "sg:city":"Friedrichskoog",
    "sg:phone":"+49 4854/207",
    "sg:postcode":"25718",
    "sg:province":"Schleswig-Holstein",
    "wof:name":"Team Nagel - Friedrichskoog",
    "wof:placetype":"venue"
},
  "geometry": {"coordinates":[8.935071,54.009892],"type":"Point"}
}