{
  "type": "Feature",
  "properties": {
    "iso:country":"DE",
    "sg:address":"Martinusstr. 45",
    "sg:city":"Vettwei\u00df",
    "sg:phone":"+49 2424/7436",
    "sg:postcode":"52391",
    "sg:province":"Nordrhein-Westfalen",
    "wof:name":"Meihseler & Bertram",
    "wof:placetype":"venue"
},
  "geometry": {"coordinates":[6.5730390549,50.7123565674],"type":"Point"}
}