{
  "type": "Feature",
  "properties": {
    "iso:country":"DE",
    "sg:address":"Grenzstr. 29-35",
    "sg:city":"Wilhelmshaven",
    "sg:phone":"+49 4421/18070",
    "sg:postcode":"26382",
    "sg:province":"Niedersachsen",
    "wof:name":"Wilhelmshavener Spar- Und Baugesellschaft Eg",
    "wof:placetype":"venue"
},
  "geometry": {"coordinates":[8.111969,53.523552],"type":"Point"}
}