{
  "type": "Feature",
  "properties": {
    "iso:country":"DE",
    "sg:address":"Professor-G\u00e4rtner-Str. 36",
    "sg:city":"Ochtrup",
    "sg:phone":"+49 2553/2272",
    "sg:postcode":"48607",
    "sg:province":"Nordrhein-Westfalen",
    "wof:name":"We\u00dfling Raumdekoration E. Kfr.",
    "wof:placetype":"venue"
},
  "geometry": {"coordinates":[7.1864700317,52.2069091797],"type":"Point"}
}