{
  "type": "Feature",
  "properties": {
    "iso:country":"DE",
    "sg:address":"Maria-Ward-Platz",
    "sg:city":"Niederalteich",
    "sg:postcode":"94557",
    "sg:province":"Bayern",
    "wof:name":"Pfarrb\u00fccherei Maria-ward-platz",
    "wof:placetype":"venue"
},
  "geometry": {"coordinates":[13.023897,48.766212],"type":"Point"}
}