{
  "type": "Feature",
  "properties": {
    "iso:country":"DE",
    "sg:address":"Kirchgasse 54",
    "sg:city":"Wiesbaden",
    "sg:phone":"+49 611/376400",
    "sg:postcode":"65183",
    "sg:province":"Hessen",
    "wof:name":"Chic In Leder Eric Spahn E. Kfm.",
    "wof:placetype":"venue"
},
  "geometry": {"coordinates":[8.2382526398,50.0815925598],"type":"Point"}
}