{
  "type": "Feature",
  "properties": {
    "iso:country":"DE",
    "sg:address":"Siebengebirgsstr. 9",
    "sg:city":"Unkel",
    "sg:phone":"+49 2224/10167",
    "sg:postcode":"53572",
    "sg:province":"Rheinland-Pfalz",
    "wof:name":"Michael Schleicher",
    "wof:placetype":"venue"
},
  "geometry": {"coordinates":[7.218741,50.604862],"type":"Point"}
}