{
  "type": "Feature",
  "properties": {
    "iso:country":"DE",
    "sg:address":"Am B\u00fcgel 62",
    "sg:city":"Hohenroda",
    "sg:postcode":"36284",
    "sg:province":"Hessen",
    "wof:name":"Exklusiv Reisen Ag",
    "wof:placetype":"venue"
},
  "geometry": {"coordinates":[9.9227046967,50.8085708618],"type":"Point"}
}