{
  "type": "Feature",
  "properties": {
    "iso:country":"DE",
    "sg:address":"Bahnhofstr 3",
    "sg:city":"Gr\u00fcnhain",
    "sg:phone":"+49 3774/15400",
    "sg:postcode":"08358",
    "wof:name":"Wkw Feuerverzinkerei Gmbh",
    "wof:placetype":"venue"
},
  "geometry": {"coordinates":[12.8043661118,50.5816497803],"type":"Point"}
}