{
  "type": "Feature",
  "properties": {
    "iso:country":"DE",
    "sg:address":"Klingener Str. 8",
    "sg:city":"Creglingen",
    "sg:phone":"+49 7933/203220",
    "sg:postcode":"97993",
    "sg:province":"Baden-W\u00fcrttemberg",
    "wof:name":"Wilhelm Vorherr Praxis F\u00fcr Ergotherapie",
    "wof:placetype":"venue"
},
  "geometry": {"coordinates":[10.028887,49.470135],"type":"Point"}
}