{
  "type": "Feature",
  "properties": {
    "iso:country":"DE",
    "sg:address":"Birkenweg 2",
    "sg:city":"Donaustauf",
    "sg:phone":"+49 9403/29042955",
    "sg:postcode":"93093",
    "sg:province":"Bayern",
    "wof:name":"Balk Werkzeugmaschinen",
    "wof:placetype":"venue"
},
  "geometry": {"coordinates":[12.2340230942,49.0296592712],"type":"Point"}
}