{
  "type": "Feature",
  "properties": {
    "iso:country":"DE",
    "sg:address":"Balduinstr. 28",
    "sg:city":"Hamburg",
    "sg:phone":"+49 40/316615",
    "sg:postcode":"20359",
    "sg:province":"Hamburg",
    "wof:name":"Nordlicht",
    "wof:placetype":"venue"
},
  "geometry": {"coordinates":[9.9597158432,53.5483856201],"type":"Point"}
}