{
  "type": "Feature",
  "properties": {
    "iso:country":"DE",
    "sg:address":"Wilstorfer Str. 68",
    "sg:city":"Hamburg",
    "sg:phone":"+49 40/774701",
    "sg:postcode":"21073",
    "sg:province":"Hamburg",
    "wof:name":"J\u00fcrgen Te\u00dfmann",
    "wof:placetype":"venue"
},
  "geometry": {"coordinates":[9.986872673,53.4554519653],"type":"Point"}
}