{
  "type": "Feature",
  "properties": {
    "iso:country":"DE",
    "sg:address":"Albert-Einstein-Str 2",
    "sg:city":"R\u00f6dermark",
    "sg:phone":"+49 6074/98590",
    "sg:postcode":"63322",
    "sg:province":"Hessen",
    "wof:name":"Karl-heinz Martin Klassische Ballettschuhe Gmbh",
    "wof:placetype":"venue"
},
  "geometry": {"coordinates":[8.823669,49.971638],"type":"Point"}
}