{
  "type": "Feature",
  "properties": {
    "iso:country":"DE",
    "sg:address":"Siedlung 11",
    "sg:city":"Markendorf",
    "sg:phone":"+49 3372/403689",
    "sg:postcode":"14913",
    "sg:province":"Brandenburg",
    "wof:name":"Manfred Botzet",
    "wof:placetype":"venue"
},
  "geometry": {"coordinates":[13.180924,51.988316],"type":"Point"}
}