{
  "type": "Feature",
  "properties": {
    "iso:country":"DE",
    "sg:address":"Zur Fl\u00fcgelau 10",
    "sg:city":"Crailsheim",
    "sg:postcode":"74564",
    "sg:province":"Baden-W\u00fcrttemberg",
    "wof:name":"Behindertenwerkstatt",
    "wof:placetype":"venue"
},
  "geometry": {"coordinates":[10.053854,49.130699],"type":"Point"}
}