{
  "type": "Feature",
  "properties": {
    "iso:country":"DE",
    "sg:address":"Weichselstr. 30",
    "sg:city":"Enkenbach-Alsenborn",
    "sg:phone":"+49 6303/983051",
    "sg:postcode":"67677",
    "sg:province":"Rheinland-Pfalz",
    "wof:name":"Eurospar",
    "wof:placetype":"venue"
},
  "geometry": {"coordinates":[7.8883647919,49.4888343811],"type":"Point"}
}