{
  "type": "Feature",
  "properties": {
    "iso:country":"DE",
    "sg:address":"Hoyaer Str. 19",
    "sg:city":"D\u00f6rverden",
    "sg:phone":"+49 4239/620",
    "sg:postcode":"27313",
    "sg:province":"Niedersachsen",
    "wof:name":"Wilhelm Meineke",
    "wof:placetype":"venue"
},
  "geometry": {"coordinates":[9.300194,52.833969],"type":"Point"}
}