{
  "type": "Feature",
  "properties": {
    "iso:country":"DE",
    "sg:address":"Am Lennedamm 1",
    "sg:city":"Finnentrop",
    "sg:phone":"+49 4927/215110",
    "sg:postcode":"57413",
    "sg:province":"Nordrhein-Westfalen",
    "wof:name":"Heinrich Eibach Gmbh",
    "wof:placetype":"venue"
},
  "geometry": {"coordinates":[7.9696660042,51.1833076477],"type":"Point"}
}