{
  "type": "Feature",
  "properties": {
    "iso:country":"DE",
    "sg:address":"Decksteiner Str. 47",
    "sg:city":"H\u00fcrth",
    "sg:phone":"+49 2233/33571",
    "sg:postcode":"50354",
    "sg:province":"Nordrhein-Westfalen",
    "wof:name":"Hans Rosenbaum",
    "wof:placetype":"venue"
},
  "geometry": {"coordinates":[6.862789,50.896164],"type":"Point"}
}