{
  "type": "Feature",
  "properties": {
    "iso:country":"DE",
    "sg:address":"Melben 5",
    "sg:city":"Villingen-Schwenningen",
    "sg:phone":"+49 7720/66909",
    "sg:postcode":"78056",
    "sg:province":"Baden-W\u00fcrttemberg",
    "wof:name":"Erhard Strohm",
    "wof:placetype":"venue"
},
  "geometry": {"coordinates":[8.557387,48.072235],"type":"Point"}
}