{
  "type": "Feature",
  "properties": {
    "iso:country":"DE",
    "sg:address":"\u00d6hringer Str. 8",
    "sg:city":"Tamm",
    "sg:phone":"+49 7141/20610",
    "sg:postcode":"71732",
    "sg:province":"Baden-W\u00fcrttemberg",
    "wof:name":"Bossert Textiagentur Gmbh",
    "wof:placetype":"venue"
},
  "geometry": {"coordinates":[9.1471672058,48.9268951416],"type":"Point"}
}