{
  "type": "Feature",
  "properties": {
    "iso:country":"DE",
    "sg:address":"Schlo\u00dfstr. 5",
    "sg:city":"Wichmannsdorf",
    "sg:phone":"+49 38292/78988",
    "sg:postcode":"18230",
    "sg:province":"Mecklenburg-Vorpommern",
    "wof:name":"Dr. G. Hoffmann Immobilienmakler",
    "wof:placetype":"venue"
},
  "geometry": {"coordinates":[11.7382793427,54.113079071],"type":"Point"}
}