{
  "type": "Feature",
  "properties": {
    "iso:country":"DE",
    "sg:address":"Ekkehardstr. 21",
    "sg:city":"Singen",
    "sg:phone":"+49 7731/65052",
    "sg:postcode":"78224",
    "sg:province":"Baden-W\u00fcrttemberg",
    "wof:name":"Reiseb\u00fcro Rominger Gmbh",
    "wof:placetype":"venue"
},
  "geometry": {"coordinates":[8.8392343521,47.7622299194],"type":"Point"}
}