{
  "type": "Feature",
  "properties": {
    "iso:country":"DE",
    "sg:address":"Friedenstr. 6",
    "sg:city":"D\u00fcren",
    "sg:phone":"+49 2421/75485",
    "sg:postcode":"52351",
    "sg:province":"Nordrhein-Westfalen",
    "wof:name":"Frank Schumacher",
    "wof:placetype":"venue"
},
  "geometry": {"coordinates":[6.4993920326,50.8043136597],"type":"Point"}
}