{
  "type": "Feature",
  "properties": {
    "iso:country":"DE",
    "sg:address":"Schulstr. 4",
    "sg:city":"Appen",
    "sg:phone":"+49 4101/27027",
    "sg:postcode":"25482",
    "sg:province":"Schleswig-Holstein",
    "wof:name":"Gemeindeb\u00fccherei",
    "wof:placetype":"venue"
},
  "geometry": {"coordinates":[9.737115,53.660542],"type":"Point"}
}