{
  "type": "Feature",
  "properties": {
    "iso:country":"DE",
    "sg:address":"Heikendorfer Weg 26",
    "sg:city":"M\u00f6nkeberg",
    "sg:phone":"+49 431/231597",
    "sg:postcode":"24248",
    "sg:province":"Schleswig-Holstein",
    "wof:name":"Ulf Richter",
    "wof:placetype":"venue"
},
  "geometry": {"coordinates":[10.1930599213,54.3504295349],"type":"Point"}
}