{
  "type": "Feature",
  "properties": {
    "iso:country":"DE",
    "sg:address":"Lise-Meitner-Str. 7",
    "sg:city":"Itzehoe",
    "sg:phone":"+49 4821/73910",
    "sg:postcode":"25524",
    "sg:province":"Schleswig-Holstein",
    "wof:name":"Baugesch\u00e4ft Schiemann Gmbh",
    "wof:placetype":"venue"
},
  "geometry": {"coordinates":[9.491341,53.951469],"type":"Point"}
}