{
  "type": "Feature",
  "properties": {
    "iso:country":"DE",
    "sg:address":"Bocholter Str. 12",
    "sg:city":"Isselburg",
    "sg:phone":"+49 2874/1599",
    "sg:postcode":"46419",
    "sg:province":"Nordrhein-Westfalen",
    "wof:name":"Restaurant Heidekrug",
    "wof:placetype":"venue"
},
  "geometry": {"coordinates":[6.4792351723,51.8133850098],"type":"Point"}
}