{
  "type": "Feature",
  "properties": {
    "iso:country":"DE",
    "sg:address":"Saarstr. 17",
    "sg:city":"Gerolzhofen",
    "sg:phone":"+49 9382/8242",
    "sg:postcode":"97447",
    "sg:province":"Bayern",
    "wof:name":"Birco Baustoffwerk Gmbh",
    "wof:placetype":"venue"
},
  "geometry": {"coordinates":[10.346616745,49.8977279663],"type":"Point"}
}