{
  "type": "Feature",
  "properties": {
    "iso:country":"DE",
    "sg:address":"Industriestr. 21",
    "sg:city":"Heusenstamm",
    "sg:phone":"+49 6104/924860",
    "sg:postcode":"63150",
    "sg:province":"Hessen",
    "wof:name":"Ews Maschinen- Und Hydraulik Gmbh",
    "wof:placetype":"venue"
},
  "geometry": {"coordinates":[8.796897,50.047802],"type":"Point"}
}