{
  "type": "Feature",
  "properties": {
    "iso:country":"DE",
    "sg:address":"Spiegelberg 17",
    "sg:city":"Reichenau",
    "sg:phone":"+49 7534/555",
    "sg:postcode":"78479",
    "sg:province":"Baden-W\u00fcrttemberg",
    "wof:name":"Weinstube K\u00fcferst\u00fcble",
    "wof:placetype":"venue"
},
  "geometry": {"coordinates":[9.062538147,47.6933898926],"type":"Point"}
}