{
  "type": "Feature",
  "properties": {
    "iso:country":"DE",
    "sg:address":"Peisinger Str. 11",
    "sg:city":"Bad Abbach",
    "sg:phone":"+49 9405/4776",
    "sg:postcode":"93077",
    "sg:province":"Bayern",
    "wof:name":"D. Stolte",
    "wof:placetype":"venue"
},
  "geometry": {"coordinates":[12.049636,48.921902],"type":"Point"}
}