{
  "type": "Feature",
  "properties": {
    "iso:country":"DE",
    "sg:address":"Burgplatz 12",
    "sg:city":"D\u00fcsseldorf",
    "sg:phone":"+49 211/327704",
    "sg:postcode":"40213",
    "sg:province":"Nordrhein-Westfalen",
    "wof:name":"Eis-cafe Claudio",
    "wof:placetype":"venue"
},
  "geometry": {"coordinates":[6.772447,51.22654],"type":"Point"}
}