{
  "type": "Feature",
  "properties": {
    "iso:country":"DE",
    "sg:address":"Haundorfer Str. 31",
    "sg:city":"Herzogenaurach",
    "sg:phone":"+49 9132/2609",
    "sg:postcode":"91074",
    "sg:province":"Bayern",
    "wof:name":"Christoph Fr\u00f6tsch",
    "wof:placetype":"venue"
},
  "geometry": {"coordinates":[10.9206542969,49.5887107849],"type":"Point"}
}