{
  "type": "Feature",
  "properties": {
    "iso:country":"DE",
    "sg:address":"Galgenberg 8",
    "sg:city":"Nentershausen",
    "sg:phone":"+49 6627/366",
    "sg:postcode":"36214",
    "sg:province":"Hessen",
    "wof:name":"J\u00f6rg Hain Architekt",
    "wof:placetype":"venue"
},
  "geometry": {"coordinates":[9.929907,51.01387],"type":"Point"}
}