{
  "type": "Feature",
  "properties": {
    "iso:country":"DE",
    "sg:address":"Teichgraben 5",
    "sg:city":"Jena",
    "sg:postcode":"07743",
    "sg:province":"Th\u00fcringen",
    "wof:name":"Gesch\u00e4ftsreise-service",
    "wof:placetype":"venue"
},
  "geometry": {"coordinates":[11.5836429596,50.9275894165],"type":"Point"}
}