{
  "type": "Feature",
  "properties": {
    "iso:country":"DE",
    "sg:address":"Vogelsbergstr. 47",
    "sg:city":"Altenstadt",
    "sg:phone":"+49 6047/96410",
    "sg:postcode":"63674",
    "sg:province":"Hessen",
    "wof:name":"Finke Gmbh",
    "wof:placetype":"venue"
},
  "geometry": {"coordinates":[8.9465856552,50.2859458923],"type":"Point"}
}