{
  "type": "Feature",
  "properties": {
    "iso:country":"DE",
    "sg:address":"Industriestr. 46",
    "sg:city":"Neunkirchen",
    "sg:phone":"+49 9153/8601",
    "sg:postcode":"91233",
    "sg:province":"Bayern",
    "wof:name":"Regiotrans Speikern",
    "wof:placetype":"venue"
},
  "geometry": {"coordinates":[11.344812,49.523731],"type":"Point"}
}