{
  "type": "Feature",
  "properties": {
    "iso:country":"DE",
    "sg:address":"Filderbahnstr. 5",
    "sg:city":"Stuttgart",
    "sg:phone":"+49 711/713241",
    "sg:postcode":"70567",
    "sg:province":"Baden-W\u00fcrttemberg",
    "wof:name":"F. Gianni",
    "wof:placetype":"venue"
},
  "geometry": {"coordinates":[9.1458930969,48.7264404297],"type":"Point"}
}