{
  "type": "Feature",
  "properties": {
    "iso:country":"DE",
    "sg:address":"Amelhauserstrasse 38",
    "sg:city":"Gro\u00dfenkneten",
    "sg:phone":"+49 4487/1531",
    "sg:postcode":"26197",
    "sg:province":"Niedersachsen",
    "wof:name":"Sportpferde-wittkopf",
    "wof:placetype":"venue"
},
  "geometry": {"coordinates":[8.304437,52.977585],"type":"Point"}
}