{
  "type": "Feature",
  "properties": {
    "iso:country":"DE",
    "sg:address":"Untersbergstra\u00dfe 2",
    "sg:city":"Teisendorf",
    "sg:phone":"+49 8666/98850",
    "sg:postcode":"83317",
    "sg:province":"Bayern",
    "wof:name":"Hoenke K\u00e4lte Klima",
    "wof:placetype":"venue"
},
  "geometry": {"coordinates":[12.818494,47.84816],"type":"Point"}
}