{
  "type": "Feature",
  "properties": {
    "iso:country":"DE",
    "sg:address":"Robert-Bosch-Str. 12",
    "sg:city":"Wimsheim",
    "sg:postcode":"71299",
    "sg:province":"Baden-W\u00fcrttemberg",
    "wof:name":"Realpack Verwaltungs- Gmbh",
    "wof:placetype":"venue"
},
  "geometry": {"coordinates":[8.828040123,48.8450584412],"type":"Point"}
}