{
  "type": "Feature",
  "properties": {
    "iso:country":"DE",
    "sg:address":"Jagdhornstr. 36",
    "sg:city":"Vechta",
    "sg:phone":"+49 4441/851753",
    "sg:postcode":"49377",
    "sg:province":"Niedersachsen",
    "wof:name":"P. Lubomirski",
    "wof:placetype":"venue"
},
  "geometry": {"coordinates":[8.306705,52.734791],"type":"Point"}
}