{
  "type": "Feature",
  "properties": {
    "iso:country":"DE",
    "sg:address":"Ostpreu\u00dfenstr. 12",
    "sg:city":"G\u00f6ppingen",
    "sg:phone":"+49 7161/21576",
    "sg:postcode":"73035",
    "sg:province":"Baden-W\u00fcrttemberg",
    "wof:name":"Martin Schweiger Anlageberater",
    "wof:placetype":"venue"
},
  "geometry": {"coordinates":[9.6117343903,48.7133865356],"type":"Point"}
}