{
  "type": "Feature",
  "properties": {
    "iso:country":"DE",
    "sg:address":"Kaiserstr. 27",
    "sg:city":"Waldshut-Tiengen",
    "sg:phone":"+49 7751/6608",
    "sg:postcode":"79761",
    "sg:province":"Baden-W\u00fcrttemberg",
    "wof:name":"Usl\u00e4nder Gmbh",
    "wof:placetype":"venue"
},
  "geometry": {"coordinates":[8.21356,47.622669],"type":"Point"}
}