{
  "type": "Feature",
  "properties": {
    "iso:country":"DE",
    "sg:address":"B\u00f6defelder Str. 23",
    "sg:city":"Winterberg",
    "sg:phone":"+49 2983/596",
    "sg:postcode":"59955",
    "sg:province":"Nordrhein-Westfalen",
    "wof:name":"Theo K\u00f6rner",
    "wof:placetype":"venue"
},
  "geometry": {"coordinates":[8.4412899017,51.2507209778],"type":"Point"}
}