{
  "type": "Feature",
  "properties": {
    "iso:country":"DE",
    "sg:address":"Willi-Eichler-Str. 26",
    "sg:city":"G\u00f6ttingen",
    "sg:phone":"+49 551/64020",
    "sg:postcode":"37079",
    "sg:province":"Niedersachsen",
    "wof:name":"Scandstick Ag",
    "wof:placetype":"venue"
},
  "geometry": {"coordinates":[9.8856697083,51.5513343811],"type":"Point"}
}