{
  "type": "Feature",
  "properties": {
    "iso:country":"DE",
    "sg:address":"Schenkendorfstr. 45-47",
    "sg:city":"Oberhausen",
    "sg:phone":"+49 208/880650",
    "sg:postcode":"46047",
    "sg:province":"Nordrhein-Westfalen",
    "wof:name":"Rohr Reinigung Regh Gmbh",
    "wof:placetype":"venue"
},
  "geometry": {"coordinates":[6.8676538467,51.4796066284],"type":"Point"}
}