{
  "type": "Feature",
  "properties": {
    "iso:country":"DE",
    "sg:address":"Bergstr. 8",
    "sg:city":"Ernst",
    "sg:phone":"+49 2671/4438",
    "sg:postcode":"56814",
    "sg:province":"Rheinland-Pfalz",
    "wof:name":"Schausten-gansen Weinanbau",
    "wof:placetype":"venue"
},
  "geometry": {"coordinates":[7.2223482132,50.1426277161],"type":"Point"}
}