{
  "type": "Feature",
  "properties": {
    "iso:country":"DE",
    "sg:address":"Schillerstr. 6",
    "sg:city":"Schmitten",
    "sg:phone":"+49 6084/2292",
    "sg:postcode":"61389",
    "sg:province":"Hessen",
    "wof:name":"Taunus-apotheke Inh. Anka Mitzel E. Kfr.",
    "wof:placetype":"venue"
},
  "geometry": {"coordinates":[8.4394,50.269909],"type":"Point"}
}