{
  "type": "Feature",
  "properties": {
    "iso:country":"DE",
    "sg:address":"Wildunger Str. 25",
    "sg:city":"Haina",
    "sg:phone":"+49 6455/460",
    "sg:postcode":"35114",
    "sg:province":"Hessen",
    "wof:name":"G\u00fcnter Wilhelmi Gmbh",
    "wof:placetype":"venue"
},
  "geometry": {"coordinates":[8.9851388931,51.0671386719],"type":"Point"}
}