{
  "type": "Feature",
  "properties": {
    "iso:country":"DE",
    "sg:address":"Annenstr. 31",
    "sg:city":"Plauen",
    "sg:phone":"+49 3741/228608",
    "sg:postcode":"08523",
    "sg:province":"Sachsen",
    "wof:name":"Forbriger",
    "wof:placetype":"venue"
},
  "geometry": {"coordinates":[12.1403,50.49971],"type":"Point"}
}