{
  "type": "Feature",
  "properties": {
    "iso:country":"DE",
    "sg:address":"Bergstr. 84",
    "sg:city":"Bad Oeynhausen",
    "sg:phone":"+49 5731/92450",
    "sg:postcode":"32547",
    "sg:province":"Nordrhein-Westfalen",
    "wof:name":"Klusmeier Reinert Hebamme",
    "wof:placetype":"venue"
},
  "geometry": {"coordinates":[8.817003,52.18998],"type":"Point"}
}