{
  "type": "Feature",
  "properties": {
    "iso:country":"DE",
    "sg:address":"Rudolf-Diesel-Str. 16",
    "sg:city":"Rangendingen",
    "sg:phone":"+49 7471/8061",
    "sg:postcode":"72414",
    "sg:province":"Baden-W\u00fcrttemberg",
    "wof:name":"Manfred Dieringer Gmbh",
    "wof:placetype":"venue"
},
  "geometry": {"coordinates":[8.8996982574,48.3822631836],"type":"Point"}
}