{
  "type": "Feature",
  "properties": {
    "iso:country":"DE",
    "sg:address":"Merkurstr. 56",
    "sg:city":"Kaiserslautern",
    "sg:phone":"+49 631/3503730",
    "sg:postcode":"67663",
    "sg:province":"Rheinland-Pfalz",
    "wof:name":"Werner M\u00fcller Gmbh",
    "wof:placetype":"venue"
},
  "geometry": {"coordinates":[7.716173172,49.4423522949],"type":"Point"}
}