{
  "type": "Feature",
  "properties": {
    "iso:country":"DE",
    "sg:address":"Arnsteiner Str. 5",
    "sg:city":"Singhofen",
    "sg:phone":"+49 2604/1350",
    "sg:postcode":"56379",
    "sg:province":"Rheinland-Pfalz",
    "wof:name":"Becker Gmbh Holzbautenschutz",
    "wof:placetype":"venue"
},
  "geometry": {"coordinates":[7.837446,50.277187],"type":"Point"}
}