{
  "type": "Feature",
  "properties": {
    "iso:country":"DE",
    "sg:address":"Friedenstr. 24",
    "sg:city":"Bestensee",
    "sg:phone":"+49 33763/61415",
    "sg:postcode":"15741",
    "sg:province":"Brandenburg",
    "wof:name":"A. Barkowsky",
    "wof:placetype":"venue"
},
  "geometry": {"coordinates":[13.659894,52.244534],"type":"Point"}
}