{
  "type": "Feature",
  "properties": {
    "iso:country":"DE",
    "sg:address":"Industriestr. 4",
    "sg:city":"Dessau",
    "sg:phone":"+49 340/513385",
    "sg:postcode":"06847",
    "sg:province":"Sachsen-Anhalt",
    "wof:name":"Lindau Autolackierung Gmbh",
    "wof:placetype":"venue"
},
  "geometry": {"coordinates":[12.228772,51.818146],"type":"Point"}
}