{
  "type": "Feature",
  "properties": {
    "iso:country":"DE",
    "sg:address":"L\u00fctgendortmunder Hellweg 187",
    "sg:city":"Dortmund",
    "sg:phone":"+49 231/632780",
    "sg:postcode":"44388",
    "sg:province":"Nordrhein-Westfalen",
    "wof:name":"Bestattungenshaus Und Tischlerei Teves",
    "wof:placetype":"venue"
},
  "geometry": {"coordinates":[7.35966,51.49781],"type":"Point"}
}