{
  "type": "Feature",
  "properties": {
    "iso:country":"DE",
    "sg:address":"Baerler Str. 62",
    "sg:city":"Moers",
    "sg:postcode":"47441",
    "sg:province":"Nordrhein-Westfalen",
    "wof:name":"Ebook Media E. K.",
    "wof:placetype":"venue"
},
  "geometry": {"coordinates":[6.634510994,51.4581184387],"type":"Point"}
}