{
  "type": "Feature",
  "properties": {
    "iso:country":"DE",
    "sg:address":"Marner Str. 18",
    "sg:city":"St. Michaelisdonn",
    "sg:phone":"+49 4853/640",
    "sg:postcode":"25693",
    "sg:province":"Schleswig-Holstein",
    "wof:name":"Gerd Grothusen",
    "wof:placetype":"venue"
},
  "geometry": {"coordinates":[9.113308,53.981567],"type":"Point"}
}