{
  "type": "Feature",
  "properties": {
    "iso:country":"DE",
    "sg:address":"Paulstr. 7",
    "sg:city":"Despetal",
    "sg:phone":"+49 5182/52462",
    "sg:postcode":"31035",
    "sg:province":"Niedersachsen",
    "wof:name":"Adolf Kreibohm Bau- Und M\u00f6beltischlerei Gmbh",
    "wof:placetype":"venue"
},
  "geometry": {"coordinates":[9.845798,52.080193],"type":"Point"}
}