{
  "type": "Feature",
  "properties": {
    "iso:country":"DE",
    "sg:address":"Schlo\u00df",
    "sg:city":"Bad Homburg",
    "sg:phone":"+49 6172/21530",
    "sg:postcode":"61348",
    "sg:province":"Hessen",
    "wof:name":"Restaurant Kofler",
    "wof:placetype":"venue"
},
  "geometry": {"coordinates":[8.610619545,50.2293167114],"type":"Point"}
}