{
  "type": "Feature",
  "properties": {
    "iso:country":"DE",
    "sg:address":"Bahnhofstr. 22 a",
    "sg:city":"Timmendorfer Strand",
    "sg:phone":"+49 4503/881180",
    "sg:postcode":"23669",
    "sg:province":"Schleswig-Holstein",
    "wof:name":"Michael H\u00e4rter Versicherungen",
    "wof:placetype":"venue"
},
  "geometry": {"coordinates":[10.766544342,53.9954566956],"type":"Point"}
}