{
  "type": "Feature",
  "properties": {
    "iso:country":"DE",
    "sg:address":"Broderskoog",
    "sg:city":"Aventoft",
    "sg:phone":"+49 4664/1087",
    "sg:postcode":"25927",
    "sg:province":"Schleswig-Holstein",
    "wof:name":"Jan Leseberg Architekt",
    "wof:placetype":"venue"
},
  "geometry": {"coordinates":[8.78103,54.889622],"type":"Point"}
}