{
  "type": "Feature",
  "properties": {
    "iso:country":"DE",
    "sg:address":"Landstr. 4",
    "sg:city":"Hanau",
    "sg:phone":"+49 6181/255665",
    "sg:postcode":"63454",
    "sg:province":"Hessen",
    "wof:name":"Etp Reisen Gmbh",
    "wof:placetype":"venue"
},
  "geometry": {"coordinates":[8.8935365677,50.1285705566],"type":"Point"}
}