{
  "type": "Feature",
  "properties": {
    "iso:country":"DE",
    "sg:address":"Altdorfer Str. 91",
    "sg:city":"Lauf",
    "sg:phone":"+49 9123/987439",
    "sg:postcode":"91207",
    "sg:province":"Bayern",
    "wof:name":"C. Lutz Blumen-kunst- Werkstatt Gmbh",
    "wof:placetype":"venue"
},
  "geometry": {"coordinates":[11.28514,49.504272],"type":"Point"}
}