{
  "type": "Feature",
  "properties": {
    "iso:country":"DE",
    "sg:address":"An der Pulverm\u00fchle 2",
    "sg:city":"K\u00f6ln",
    "sg:phone":"+49 221/884121",
    "sg:postcode":"51105",
    "sg:province":"Nordrhein-Westfalen",
    "wof:name":"Hubert Klein Kfz Verwertungsuntern.",
    "wof:placetype":"venue"
},
  "geometry": {"coordinates":[6.9942369461,50.9349555969],"type":"Point"}
}