{
  "type": "Feature",
  "properties": {
    "iso:country":"DE",
    "sg:address":"Lassallestr. 10",
    "sg:city":"Kassel",
    "sg:phone":"+49 561/770203",
    "sg:postcode":"34119",
    "sg:province":"Hessen",
    "wof:name":"D. Nieland Heissmangel",
    "wof:placetype":"venue"
},
  "geometry": {"coordinates":[9.4664907455,51.3152656555],"type":"Point"}
}