{
  "type": "Feature",
  "properties": {
    "iso:country":"DE",
    "sg:address":"Oststr. 7",
    "sg:city":"Hopsten",
    "sg:phone":"+49 5458/550",
    "sg:postcode":"48496",
    "sg:province":"Nordrhein-Westfalen",
    "wof:name":"Walter Feldhaus",
    "wof:placetype":"venue"
},
  "geometry": {"coordinates":[7.6222,52.382736],"type":"Point"}
}