{
  "type": "Feature",
  "properties": {
    "iso:country":"DE",
    "sg:address":"Besigheimer Str. 2",
    "sg:city":"L\u00f6chgau",
    "sg:phone":"+49 7143/870606",
    "sg:postcode":"74369",
    "sg:province":"Baden-W\u00fcrttemberg",
    "wof:name":"K.-h. Seemann Bildhauer",
    "wof:placetype":"venue"
},
  "geometry": {"coordinates":[9.113193,49.00148],"type":"Point"}
}