{
  "type": "Feature",
  "properties": {
    "iso:country":"DE",
    "sg:address":"Buchenwaldstr. 10",
    "sg:city":"Leinfelden-Echterdingen",
    "sg:phone":"+49 711/751676",
    "sg:postcode":"70771",
    "sg:province":"Baden-W\u00fcrttemberg",
    "wof:name":"Jolanthe Rassek Architekt",
    "wof:placetype":"venue"
},
  "geometry": {"coordinates":[9.136677,48.698322],"type":"Point"}
}