{
  "type": "Feature",
  "properties": {
    "iso:country":"DE",
    "sg:address":"Scheffelweg 2",
    "sg:city":"B\u00f6blingen",
    "sg:phone":"+49 7031/221930",
    "sg:postcode":"71032",
    "sg:province":"Baden-W\u00fcrttemberg",
    "wof:name":"Gisa Reinhold Heilpraktikerin",
    "wof:placetype":"venue"
},
  "geometry": {"coordinates":[9.0263214111,48.6856880188],"type":"Point"}
}