{
  "type": "Feature",
  "properties": {
    "iso:country":"DE",
    "sg:address":"M\u00fclheimer Str. 428",
    "sg:city":"Oberhausen",
    "sg:phone":"+49 208/889805",
    "sg:postcode":"46045",
    "sg:province":"Nordrhein-Westfalen",
    "wof:name":"Teredo-tischlerei F\u00fcr Individuelle",
    "wof:placetype":"venue"
},
  "geometry": {"coordinates":[6.862398,51.459076],"type":"Point"}
}