{
  "type": "Feature",
  "properties": {
    "iso:country":"DE",
    "sg:address":"Raiffeisenstr. 20",
    "sg:city":"Langenau",
    "sg:phone":"+49 7345/6136",
    "sg:postcode":"89129",
    "sg:province":"Baden-W\u00fcrttemberg",
    "wof:name":"H. Valencic Ingenieur",
    "wof:placetype":"venue"
},
  "geometry": {"coordinates":[10.1234712601,48.4894332886],"type":"Point"}
}