{
  "type": "Feature",
  "properties": {
    "iso:country":"DE",
    "sg:address":"Essener Str. 37",
    "sg:city":"Bochum",
    "sg:phone":"+49 234/12896",
    "sg:postcode":"44793",
    "sg:province":"Nordrhein-Westfalen",
    "wof:name":"Ev. Pfarramt Engelsburg",
    "wof:placetype":"venue"
},
  "geometry": {"coordinates":[7.1903848648,51.4760971069],"type":"Point"}
}