{
  "type": "Feature",
  "properties": {
    "iso:country":"DE",
    "sg:address":"Reimersstr.",
    "sg:city":"Leer",
    "sg:postcode":"26789",
    "sg:province":"Niedersachsen",
    "wof:name":"Grundst\u00fccksvermietung Gmbh & Co. Kg",
    "wof:placetype":"venue"
},
  "geometry": {"coordinates":[7.4658098221,53.2306900024],"type":"Point"}
}