{
  "type": "Feature",
  "properties": {
    "iso:country":"DE",
    "sg:address":"Im Geisenborn 4",
    "sg:city":"Selters",
    "sg:phone":"+49 2626/1324",
    "sg:postcode":"56242",
    "sg:province":"Rheinland-Pfalz",
    "wof:name":"Fliesen Weimbs Gmbh",
    "wof:placetype":"venue"
},
  "geometry": {"coordinates":[7.7136511803,50.5512695312],"type":"Point"}
}