{
  "type": "Feature",
  "properties": {
    "iso:country":"DE",
    "sg:address":"Lindehof",
    "sg:city":"M\u00fcnsingen",
    "sg:phone":"+49 7383/380",
    "sg:postcode":"72525",
    "sg:province":"Baden-W\u00fcrttemberg",
    "wof:name":"Reinhard B\u00f6hm",
    "wof:placetype":"venue"
},
  "geometry": {"coordinates":[9.4806699753,48.3546066284],"type":"Point"}
}