{
  "type": "Feature",
  "properties": {
    "iso:country":"DE",
    "sg:address":"Pegauer Str. 3",
    "sg:city":"Kitzen-Werben",
    "sg:phone":"+49 34296",
    "sg:postcode":"04460",
    "sg:province":"Sachsen",
    "wof:name":"Einkaufen Bei Eplanet",
    "wof:placetype":"venue"
},
  "geometry": {"coordinates":[12.2223501205,51.2199897766],"type":"Point"}
}