{
  "type": "Feature",
  "properties": {
    "iso:country":"DE",
    "sg:address":"Am Fl\u00fcgeldeich 30",
    "sg:city":"Emden",
    "sg:phone":"+49 4921/9250",
    "sg:postcode":"26723",
    "sg:province":"Niedersachsen",
    "wof:name":"Anker Schiffahrts Gmbh Seeschiffahrt-u.",
    "wof:placetype":"venue"
},
  "geometry": {"coordinates":[7.183982,53.343304],"type":"Point"}
}