{
  "type": "Feature",
  "properties": {
    "iso:country":"DE",
    "sg:address":"Schillerstr. 5",
    "sg:city":"Hausen",
    "sg:postcode":"78595",
    "sg:province":"Baden-W\u00fcrttemberg",
    "wof:name":"Value-tec Gmbh",
    "wof:placetype":"venue"
},
  "geometry": {"coordinates":[8.86151,50.082619],"type":"Point"}
}