{
  "type": "Feature",
  "properties": {
    "iso:country":"DE",
    "sg:address":"Jahnstr. 1",
    "sg:city":"Obernburg",
    "sg:phone":"+49 6022/8522",
    "sg:postcode":"63785",
    "sg:province":"Bayern",
    "wof:name":"Weinstube Oskar Rohleder",
    "wof:placetype":"venue"
},
  "geometry": {"coordinates":[9.148021698,49.8447647095],"type":"Point"}
}