{
  "type": "Feature",
  "properties": {
    "iso:country":"DE",
    "sg:address":"Harburger Stra\u00dfe 16",
    "sg:city":"Buchholz",
    "sg:phone":"+49 4181/5400",
    "sg:postcode":"21244",
    "sg:province":"Niedersachsen",
    "wof:name":"Pflegedienst Vreden Buchholz - \u00a9stadtmittelpunkt",
    "wof:placetype":"venue"
},
  "geometry": {"coordinates":[9.872256,53.364243],"type":"Point"}
}