{
  "type": "Feature",
  "properties": {
    "iso:country":"DE",
    "sg:address":"Alter Weg 11",
    "sg:city":"Gorxheimertal",
    "sg:phone":"+49 6201/21778",
    "sg:postcode":"69517",
    "sg:province":"Hessen",
    "wof:name":"M. Kohl Heissmangel",
    "wof:placetype":"venue"
},
  "geometry": {"coordinates":[8.7415103912,49.5293312073],"type":"Point"}
}