{
  "type": "Feature",
  "properties": {
    "iso:country":"DE",
    "sg:address":"Drackensteiner Str. 105",
    "sg:city":"Bad Ditzenbach",
    "sg:postcode":"73342",
    "sg:province":"Baden-W\u00fcrttemberg",
    "wof:name":"Kreativ Bautr\u00e4ger",
    "wof:placetype":"venue"
},
  "geometry": {"coordinates":[9.678539,48.573868],"type":"Point"}
}