{
  "type": "Feature",
  "properties": {
    "iso:country":"DE",
    "sg:address":"Durmersheimer Str. 13",
    "sg:city":"Karlsruhe",
    "sg:phone":"+49 721/593003",
    "sg:postcode":"76185",
    "sg:province":"Baden-W\u00fcrttemberg",
    "wof:name":"Rudi Winter",
    "wof:placetype":"venue"
},
  "geometry": {"coordinates":[8.3564929962,49.0064926147],"type":"Point"}
}