{
  "type": "Feature",
  "properties": {
    "iso:country":"DE",
    "sg:address":"Dolleruper Str. 1",
    "sg:city":"S\u00f6rup",
    "sg:phone":"+49 4635/2726",
    "sg:postcode":"24966",
    "sg:province":"Schleswig-Holstein",
    "wof:name":"Thomas Matzen",
    "wof:placetype":"venue"
},
  "geometry": {"coordinates":[9.668412,54.751377],"type":"Point"}
}