{
  "type": "Feature",
  "properties": {
    "iso:country":"DE",
    "sg:address":"Bahnhofstr 80",
    "sg:city":"Eisenh\u00fcttenstadt",
    "sg:phone":"+49 3364/750505",
    "sg:postcode":"15890",
    "sg:province":"Brandenburg",
    "wof:name":"F\u00fcrstenberger Druck & Verlag Gmbh",
    "wof:placetype":"venue"
},
  "geometry": {"coordinates":[14.6613798141,52.1475524902],"type":"Point"}
}