{
  "type": "Feature",
  "properties": {
    "iso:country":"DE",
    "sg:address":"Unteregg 55",
    "sg:city":"Altusried",
    "sg:phone":"+49 8373/8145",
    "sg:postcode":"87452",
    "sg:province":"Bayern",
    "wof:name":"G. Und H. Nelles",
    "wof:placetype":"venue"
},
  "geometry": {"coordinates":[10.1101808548,47.7989234924],"type":"Point"}
}