{
  "type": "Feature",
  "properties": {
    "iso:country":"DE",
    "sg:address":"Nonn 18",
    "sg:city":"Bad Reichenhall",
    "sg:phone":"+49 8651/3310",
    "sg:postcode":"83435",
    "sg:province":"Bayern",
    "wof:name":"G\u00e4stehaus Quellenhof",
    "wof:placetype":"venue"
},
  "geometry": {"coordinates":[12.8680143356,47.7371368408],"type":"Point"}
}