{
  "type": "Feature",
  "properties": {
    "iso:country":"DE",
    "sg:address":"Talstr. 2",
    "sg:city":"Murr",
    "sg:phone":"+49 7144",
    "sg:postcode":"71711",
    "sg:province":"Baden-W\u00fcrttemberg",
    "wof:name":"Holz & Bautenschutz/verfugungen",
    "wof:placetype":"venue"
},
  "geometry": {"coordinates":[9.260842,48.964821],"type":"Point"}
}