{
  "type": "Feature",
  "properties": {
    "iso:country":"DE",
    "sg:address":"Kleine Koppel 27",
    "sg:city":"D\u00fclmen",
    "sg:phone":"+49 2594/4768",
    "sg:postcode":"48249",
    "sg:province":"Nordrhein-Westfalen",
    "wof:name":"Johann Pricha",
    "wof:placetype":"venue"
},
  "geometry": {"coordinates":[7.2763080597,51.8209686279],"type":"Point"}
}