{
  "type": "Feature",
  "properties": {
    "iso:country":"DE",
    "sg:address":"Ansbacher Str. 1719",
    "sg:city":"Berlin",
    "sg:postcode":"10777",
    "sg:province":"Berlin",
    "wof:name":"Berliner Handels- Und Treuhandgesellschaft",
    "wof:placetype":"venue"
},
  "geometry": {"coordinates":[13.3386001587,52.4946784973],"type":"Point"}
}