{
  "type": "Feature",
  "properties": {
    "iso:country":"DE",
    "sg:address":"Kohlh\u00e4user Str. 55",
    "sg:city":"Fulda",
    "sg:phone":"+49 661/94990",
    "sg:postcode":"36043",
    "sg:province":"Hessen",
    "wof:name":"Stahlgruber Otto Gruber Gmbh & Co.",
    "wof:placetype":"venue"
},
  "geometry": {"coordinates":[9.6821336746,50.5346679688],"type":"Point"}
}