{
  "type": "Feature",
  "properties": {
    "iso:country":"DE",
    "sg:address":"Schneidem\u00fchler Str. 23",
    "sg:city":"M\u00fcnster",
    "sg:phone":"+49 251/24255",
    "sg:postcode":"48157",
    "sg:province":"Nordrhein-Westfalen",
    "wof:name":"Katholisches Pfarramt St. Norbert",
    "wof:placetype":"venue"
},
  "geometry": {"coordinates":[7.6492729187,51.9954299927],"type":"Point"}
}