{
  "type": "Feature",
  "properties": {
    "iso:country":"DE",
    "sg:address":"Seebachstr. 47",
    "sg:city":"Burkardroth",
    "sg:phone":"+49 9701/1069",
    "sg:postcode":"97705",
    "sg:province":"Bayern",
    "wof:name":"Hilmar Rustler",
    "wof:placetype":"venue"
},
  "geometry": {"coordinates":[9.982733,50.306656],"type":"Point"}
}