{
  "type": "Feature",
  "properties": {
    "iso:country":"DE",
    "sg:address":"Westendstr. 61",
    "sg:city":"M\u00fcnchen",
    "sg:phone":"+49 8032/8986",
    "sg:postcode":"80339",
    "sg:province":"Bayern",
    "wof:name":"Hans Bosseck",
    "wof:placetype":"venue"
},
  "geometry": {"coordinates":[11.5436992645,48.1382217407],"type":"Point"}
}