{
  "type": "Feature",
  "properties": {
    "iso:country":"DE",
    "sg:address":"Schneckenbergstr. 3",
    "sg:city":"Stuttgart",
    "sg:phone":"+49 711/852828",
    "sg:postcode":"70469",
    "sg:province":"Baden-W\u00fcrttemberg",
    "wof:name":"M. Arat",
    "wof:placetype":"venue"
},
  "geometry": {"coordinates":[9.153385,48.807083],"type":"Point"}
}