{
  "type": "Feature",
  "properties": {
    "iso:country":"DE",
    "sg:address":"Beethovenring 108",
    "sg:city":"Merzenich",
    "sg:phone":"+49 2421/37010",
    "sg:postcode":"52399",
    "sg:province":"Nordrhein-Westfalen",
    "wof:name":"Johann Spies Architekt",
    "wof:placetype":"venue"
},
  "geometry": {"coordinates":[6.51918,50.826511],"type":"Point"}
}