{
  "type": "Feature",
  "properties": {
    "iso:country":"DE",
    "sg:address":"H\u00f6sbacher Weg 2 b",
    "sg:city":"Goldbach",
    "sg:phone":"+49 6021/62360",
    "sg:postcode":"63773",
    "sg:province":"Bayern",
    "wof:name":"Leonhard Zimmermann",
    "wof:placetype":"venue"
},
  "geometry": {"coordinates":[9.1879796982,49.9990158081],"type":"Point"}
}