{
  "type": "Feature",
  "properties": {
    "iso:country":"DE",
    "sg:address":"Stockumer Bruch 57",
    "sg:city":"Witten",
    "sg:phone":"+49 2302/4416",
    "sg:postcode":"58454",
    "sg:province":"Nordrhein-Westfalen",
    "wof:name":"E. Armagan Ingenieur",
    "wof:placetype":"venue"
},
  "geometry": {"coordinates":[7.3820281029,51.47215271],"type":"Point"}
}