{
  "type": "Feature",
  "properties": {
    "iso:country":"DE",
    "sg:address":"Seeveplatz 1",
    "sg:city":"Hamburg",
    "sg:phone":"+49 40/773898",
    "sg:postcode":"21073",
    "sg:province":"Hamburg",
    "wof:name":"Gustav Staufenbiel Gmbh",
    "wof:placetype":"venue"
},
  "geometry": {"coordinates":[9.987669,53.457691],"type":"Point"}
}