{
  "type": "Feature",
  "properties": {
    "iso:country":"DE",
    "sg:address":"S\u00fcderstr. 153 a",
    "sg:city":"Hamburg",
    "sg:phone":"+49 40/2512121",
    "sg:postcode":"20537",
    "sg:province":"Hamburg",
    "wof:name":"\u00d6hler Und Henningsen Rechtsanwalt",
    "wof:placetype":"venue"
},
  "geometry": {"coordinates":[10.0377731323,53.5473937988],"type":"Point"}
}