{
  "type": "Feature",
  "properties": {
    "iso:country":"DE",
    "sg:address":"Hauptstr. 70",
    "sg:city":"Oestrich-Winkel",
    "sg:phone":"+49 6723/7585",
    "sg:postcode":"65375",
    "sg:province":"Hessen",
    "wof:name":"Rheingauer-riesling-keller",
    "wof:placetype":"venue"
},
  "geometry": {"coordinates":[8.0066795349,49.9981040955],"type":"Point"}
}