{
  "type": "Feature",
  "properties": {
    "iso:country":"DE",
    "sg:address":"Hofstattstr. 106 a",
    "sg:city":"V\u00f6lklingen",
    "sg:phone":"+49 6898/1510",
    "sg:postcode":"66333",
    "sg:province":"Saarland",
    "wof:name":"Debis Systemhaus Saar Gmbh",
    "wof:placetype":"venue"
},
  "geometry": {"coordinates":[6.8486800194,49.255657196],"type":"Point"}
}