{
  "type": "Feature",
  "properties": {
    "iso:country":"DE",
    "sg:address":"Frankenstr. 3",
    "sg:city":"Krombach",
    "sg:phone":"+49 6029/4884",
    "sg:postcode":"63829",
    "sg:province":"Bayern",
    "wof:name":"Levy Gmbh",
    "wof:placetype":"venue"
},
  "geometry": {"coordinates":[9.18622,50.087048],"type":"Point"}
}