{
  "type": "Feature",
  "properties": {
    "iso:country":"DE",
    "sg:address":"Eicherscheid 52",
    "sg:city":"Simmerath",
    "sg:phone":"+49 2473/7084",
    "sg:postcode":"52152",
    "sg:province":"Nordrhein-Westfalen",
    "wof:name":"Alois K\u00fcpper Kg",
    "wof:placetype":"venue"
},
  "geometry": {"coordinates":[6.3091459274,50.5754318237],"type":"Point"}
}