{
  "type": "Feature",
  "properties": {
    "iso:country":"DE",
    "sg:address":"Graben",
    "sg:city":"Steinh\u00f6ring",
    "sg:phone":"+49 8094/305",
    "sg:postcode":"85643",
    "sg:province":"Bayern",
    "wof:name":"F. Barthuber",
    "wof:placetype":"venue"
},
  "geometry": {"coordinates":[12.0451259613,48.1202201843],"type":"Point"}
}