{
  "type": "Feature",
  "properties": {
    "iso:country":"DE",
    "sg:address":"Ludwig-Landmann-Str. 162",
    "sg:city":"Frankfurt",
    "sg:phone":"+49 69/765467",
    "sg:postcode":"60488",
    "sg:province":"Hessen",
    "wof:name":"Ursula Braun Architektin",
    "wof:placetype":"venue"
},
  "geometry": {"coordinates":[8.614288,50.136566],"type":"Point"}
}