{
  "type": "Feature",
  "properties": {
    "iso:country":"DE",
    "sg:address":"J\u00fclicher Str. 37",
    "sg:city":"Neuss",
    "sg:phone":"+49 2131/45554",
    "sg:postcode":"41464",
    "sg:province":"Nordrhein-Westfalen",
    "wof:name":"Heinz Grein",
    "wof:placetype":"venue"
},
  "geometry": {"coordinates":[6.689694,51.190868],"type":"Point"}
}