{
  "type": "Feature",
  "properties": {
    "iso:country":"DE",
    "sg:address":"Steeler Stra\u00dfe 548",
    "sg:city":"Essen",
    "sg:phone":"+49 201",
    "sg:postcode":"45276",
    "sg:province":"Nordrhein-Westfalen",
    "wof:name":"Essener Keeper Camp - Torwarttraining In Essen",
    "wof:placetype":"venue"
},
  "geometry": {"coordinates":[7.0644259453,51.4472923279],"type":"Point"}
}