{
  "type": "Feature",
  "properties": {
    "iso:country":"DE",
    "sg:address":"Kraillinger Str. 37",
    "sg:city":"Pentenried",
    "sg:phone":"+49 89/8505142",
    "sg:postcode":"82349",
    "sg:province":"Bayern",
    "wof:name":"J\u00fcrgen Schenk",
    "wof:placetype":"venue"
},
  "geometry": {"coordinates":[11.3438673019,48.0781097412],"type":"Point"}
}