{
  "type": "Feature",
  "properties": {
    "iso:country":"DE",
    "sg:address":"Hitzgutstr 4",
    "sg:city":"Appenweier",
    "sg:phone":"+49 7805/9130",
    "sg:postcode":"77767",
    "sg:province":"Baden-W\u00fcrttemberg",
    "wof:name":"Kts Speditions Gmbh",
    "wof:placetype":"venue"
},
  "geometry": {"coordinates":[7.9678292274,48.5398483276],"type":"Point"}
}