{
  "type": "Feature",
  "properties": {
    "iso:country":"DE",
    "sg:address":"Frohlinder Str. 58",
    "sg:city":"Dortmund",
    "sg:phone":"+49 231/673660",
    "sg:postcode":"44379",
    "sg:province":"Nordrhein-Westfalen",
    "wof:name":"Gerd Wiggen",
    "wof:placetype":"venue"
},
  "geometry": {"coordinates":[7.365097,51.525581],"type":"Point"}
}