{
  "type": "Feature",
  "properties": {
    "iso:country":"DE",
    "sg:address":"Lindenplatz 1",
    "sg:city":"Bad D\u00fcrrheim",
    "sg:phone":"+49 7726/388",
    "sg:postcode":"78073",
    "sg:province":"Baden-W\u00fcrttemberg",
    "wof:name":"Modelia Boutiquemode Gmbh",
    "wof:placetype":"venue"
},
  "geometry": {"coordinates":[8.5308094025,48.0222473145],"type":"Point"}
}