{
  "type": "Feature",
  "properties": {
    "iso:country":"DE",
    "sg:address":"Neusser Str. 152",
    "sg:city":"J\u00fcchen",
    "sg:phone":"+49 4921/6591880",
    "sg:postcode":"41363",
    "sg:province":"Nordrhein-Westfalen",
    "wof:name":"Pick & H\u00dcbner Gmbh",
    "wof:placetype":"venue"
},
  "geometry": {"coordinates":[6.5228500366,51.1002006531],"type":"Point"}
}