{
  "type": "Feature",
  "properties": {
    "iso:country":"DE",
    "sg:address":"Ewaldstr. 39",
    "sg:city":"Herten",
    "sg:phone":"+49 2366/18190",
    "sg:postcode":"45699",
    "sg:province":"Nordrhein-Westfalen",
    "wof:name":"Project Concept Gmbh",
    "wof:placetype":"venue"
},
  "geometry": {"coordinates":[7.141675,51.591099],"type":"Point"}
}