{
  "type": "Feature",
  "properties": {
    "iso:country":"DE",
    "sg:address":"Enge Str. 27",
    "sg:city":"Rinteln",
    "sg:phone":"+49 5751/957263",
    "sg:postcode":"31737",
    "sg:province":"Niedersachsen",
    "wof:name":"Cornelia Giere Rechtsanw\u00e4ltin Und Notarin",
    "wof:placetype":"venue"
},
  "geometry": {"coordinates":[9.0817813873,52.1882896423],"type":"Point"}
}