{
  "type": "Feature",
  "properties": {
    "iso:country":"DE",
    "sg:address":"Pfauenbergsteige 78",
    "sg:city":"Esslingen",
    "sg:phone":"+49 711/373096",
    "sg:postcode":"73732",
    "sg:province":"Baden-W\u00fcrttemberg",
    "wof:name":"Dr. Sommer Techn. Entwicklungen Gmbh",
    "wof:placetype":"venue"
},
  "geometry": {"coordinates":[9.3365688324,48.747051239],"type":"Point"}
}