{
  "type": "Feature",
  "properties": {
    "iso:country":"DE",
    "sg:address":"Am Friedhof 5",
    "sg:city":"Berkenthin",
    "sg:postcode":"23919",
    "sg:province":"Schleswig-Holstein",
    "wof:name":"B. I. P. Bios International Products Gmbh",
    "wof:placetype":"venue"
},
  "geometry": {"coordinates":[10.6435232162,53.7295761108],"type":"Point"}
}