{
  "type": "Feature",
  "properties": {
    "iso:country":"DE",
    "sg:address":"L\u00fcbecker Str. 65",
    "sg:city":"Bad Schwartau",
    "sg:postcode":"23611",
    "sg:province":"Schleswig-Holstein",
    "wof:name":"Hvh Homann Verlag Und Werbung Gmbh",
    "wof:placetype":"venue"
},
  "geometry": {"coordinates":[10.694896698,53.9136657715],"type":"Point"}
}