{
  "type": "Feature",
  "properties": {
    "iso:country":"DE",
    "sg:address":"Balatonweg 6",
    "sg:city":"Leipheim",
    "sg:phone":"+49 8226",
    "sg:postcode":"89340",
    "sg:province":"Bayern",
    "wof:name":"Made By Pistor",
    "wof:placetype":"venue"
},
  "geometry": {"coordinates":[10.2279958725,48.4450492859],"type":"Point"}
}