{
  "type": "Feature",
  "properties": {
    "iso:country":"DE",
    "sg:address":"Hauptstr. 10",
    "sg:city":"Ziertheim",
    "sg:phone":"+49 9076/660",
    "sg:postcode":"89446",
    "sg:province":"Bayern",
    "wof:name":"Anna Rie\u00df",
    "wof:placetype":"venue"
},
  "geometry": {"coordinates":[10.3973388672,48.6525382996],"type":"Point"}
}