{
  "type": "Feature",
  "properties": {
    "iso:country":"DE",
    "sg:address":"Demminer Str. 67",
    "sg:city":"Neubrandenburg",
    "sg:phone":"+49 395/4222026",
    "sg:postcode":"17034",
    "sg:province":"Mecklenburg-Vorpommern",
    "wof:name":"Neubrandenburger Wohnungsbau- Genossenschaft Neuwoba Eg",
    "wof:placetype":"venue"
},
  "geometry": {"coordinates":[13.2719240189,53.5819549561],"type":"Point"}
}