{
  "type": "Feature",
  "properties": {
    "iso:country":"DE",
    "sg:address":"Stettiner Str. 5",
    "sg:city":"Prenzlau",
    "sg:phone":"+49 3984/806336",
    "sg:postcode":"17291",
    "sg:province":"Brandenburg",
    "wof:name":"Parf\u00fcmerie City-perfumes Gmbh",
    "wof:placetype":"venue"
},
  "geometry": {"coordinates":[13.862437,53.317471],"type":"Point"}
}