{
  "type": "Feature",
  "properties": {
    "iso:country":"DE",
    "sg:address":"F\u00fcrstenbergstr. 10",
    "sg:city":"Paderborn",
    "sg:phone":"+49 5251/18760",
    "sg:postcode":"33102",
    "sg:province":"Nordrhein-Westfalen",
    "wof:name":"Aachener Siedlungs- Und Wohnungsgesellschaft Mbh",
    "wof:placetype":"venue"
},
  "geometry": {"coordinates":[8.7454624176,51.7166900635],"type":"Point"}
}