{
  "type": "Feature",
  "properties": {
    "iso:country":"DE",
    "sg:address":"Wagemannstr. 22",
    "sg:city":"Wiesbaden",
    "sg:postcode":"65183",
    "sg:province":"Hessen",
    "wof:name":"Unit Gmbh",
    "wof:placetype":"venue"
},
  "geometry": {"coordinates":[8.2400550842,50.0832748413],"type":"Point"}
}