{
  "type": "Feature",
  "properties": {
    "iso:country":"DE",
    "sg:address":"Bauergraben 38",
    "sg:city":"Wolmirsleben",
    "sg:phone":"+49 39268/92209",
    "sg:postcode":"39435",
    "sg:province":"Sachsen-Anhalt",
    "wof:name":"M&m Ger\u00fcstbau",
    "wof:placetype":"venue"
},
  "geometry": {"coordinates":[11.4833402634,51.9474906921],"type":"Point"}
}