{
  "type": "Feature",
  "properties": {
    "iso:country":"DE",
    "sg:address":"Hauptstr. 58",
    "sg:city":"Freiburg",
    "sg:phone":"+49 761/3899630",
    "sg:postcode":"79104",
    "sg:province":"Baden-W\u00fcrttemberg",
    "wof:name":"Urban-apotheke",
    "wof:placetype":"venue"
},
  "geometry": {"coordinates":[7.863031,48.006714],"type":"Point"}
}