{
  "type": "Feature",
  "properties": {
    "iso:country":"DE",
    "sg:address":"Petersberg 7",
    "sg:city":"Wi\u00dfmannsdorf",
    "sg:phone":"+49 6527/1008",
    "sg:postcode":"54636",
    "sg:province":"Rheinland-Pfalz",
    "wof:name":"E. Winter",
    "wof:placetype":"venue"
},
  "geometry": {"coordinates":[6.4473547935,49.9888114929],"type":"Point"}
}