{
  "type": "Feature",
  "properties": {
    "iso:country":"DE",
    "sg:address":"Am Aggerberg 46",
    "sg:city":"Reichshof",
    "sg:phone":"+49 2265/9659",
    "sg:postcode":"51580",
    "sg:province":"Nordrhein-Westfalen",
    "wof:name":"B\u00e4rbel Fulda-huhn Und Renate Carstens",
    "wof:placetype":"venue"
},
  "geometry": {"coordinates":[7.6842708588,50.9896888733],"type":"Point"}
}