{
  "type": "Feature",
  "properties": {
    "iso:country":"DE",
    "sg:address":"Aufderh\u00f6her Str. 120",
    "sg:city":"Solingen",
    "sg:phone":"+49 212/2682028",
    "sg:postcode":"42699",
    "sg:province":"Nordrhein-Westfalen",
    "wof:name":"Nu\u00dfbaum-apotheke Inh. Andrea Willer E. K.",
    "wof:placetype":"venue"
},
  "geometry": {"coordinates":[7.014745,51.141708],"type":"Point"}
}