{
  "type": "Feature",
  "properties": {
    "iso:country":"DE",
    "sg:address":"Dornierstr. 46-48",
    "sg:city":"Straubing",
    "sg:phone":"+49 9421/60715",
    "sg:postcode":"94315",
    "sg:province":"Bayern",
    "wof:name":"U. Und L. Drexler",
    "wof:placetype":"venue"
},
  "geometry": {"coordinates":[12.6303949356,48.8876075745],"type":"Point"}
}