{
  "type": "Feature",
  "properties": {
    "iso:country":"DE",
    "sg:address":"Westerallee 51",
    "sg:city":"Flensburg",
    "sg:phone":"+49 461/55307",
    "sg:postcode":"24941",
    "sg:province":"Schleswig-Holstein",
    "wof:name":"Haus Der Kleing\u00e4rtner",
    "wof:placetype":"venue"
},
  "geometry": {"coordinates":[9.4035110474,54.7822151184],"type":"Point"}
}