{
  "type": "Feature",
  "properties": {
    "iso:country":"DE",
    "sg:address":"Neckarkatzenbacher Str. 16",
    "sg:city":"Neckargerach",
    "sg:phone":"+49 6263/1282",
    "sg:postcode":"69437",
    "sg:province":"Baden-W\u00fcrttemberg",
    "wof:name":"Armin H\u00f6flich",
    "wof:placetype":"venue"
},
  "geometry": {"coordinates":[9.0738649368,49.3900222778],"type":"Point"}
}