{
  "type": "Feature",
  "properties": {
    "iso:country":"DE",
    "sg:address":"Am Pannofen 45",
    "sg:city":"Geldern",
    "sg:phone":"+49 2831/4560",
    "sg:postcode":"47608",
    "sg:province":"Nordrhein-Westfalen",
    "wof:name":"Josef Bergers & Sohn Gmbh",
    "wof:placetype":"venue"
},
  "geometry": {"coordinates":[6.351854,51.519657],"type":"Point"}
}