{
  "type": "Feature",
  "properties": {
    "iso:country":"DE",
    "sg:address":"Ludwigstr. 14",
    "sg:city":"Raunheim",
    "sg:phone":"+49 6142/22238",
    "sg:postcode":"65479",
    "sg:province":"Hessen",
    "wof:name":"Europa-union E. V. J. Gradulewski",
    "wof:placetype":"venue"
},
  "geometry": {"coordinates":[8.4516706467,50.0123062134],"type":"Point"}
}