{
  "type": "Feature",
  "properties": {
    "iso:country":"DE",
    "sg:address":"Blumenstr. 7",
    "sg:city":"M\u00fcnchweiler",
    "sg:phone":"+49 6302/1649",
    "sg:postcode":"67728",
    "sg:province":"Rheinland-Pfalz",
    "wof:name":"Leo Blaum",
    "wof:placetype":"venue"
},
  "geometry": {"coordinates":[7.8817548752,49.5539054871],"type":"Point"}
}