{
  "type": "Feature",
  "properties": {
    "iso:country":"DE",
    "sg:address":"Spiegelstr. 24",
    "sg:city":"Pr\u00fcm",
    "sg:phone":"+49 6551/6252",
    "sg:postcode":"54595",
    "sg:province":"Rheinland-Pfalz",
    "wof:name":"Pizzeria La Perla",
    "wof:placetype":"venue"
},
  "geometry": {"coordinates":[6.4244098663,50.2081108093],"type":"Point"}
}