{
  "type": "Feature",
  "properties": {
    "iso:country":"DE",
    "sg:address":"Hafenbad 19",
    "sg:city":"Ulm",
    "sg:phone":"+49 731/69916",
    "sg:postcode":"89073",
    "sg:province":"Baden-W\u00fcrttemberg",
    "wof:name":"G. Butz",
    "wof:placetype":"venue"
},
  "geometry": {"coordinates":[9.993475914,48.4000854492],"type":"Point"}
}