{
  "type": "Feature",
  "properties": {
    "iso:country":"DE",
    "sg:address":"Am Bohnengrund 26",
    "sg:city":"Bad Salzungen",
    "sg:phone":"+49 3695/608812",
    "sg:postcode":"36433",
    "sg:province":"Th\u00fcringen",
    "wof:name":"Bernhard Lucke",
    "wof:placetype":"venue"
},
  "geometry": {"coordinates":[10.25591,50.818417],"type":"Point"}
}