{
  "type": "Feature",
  "properties": {
    "iso:country":"DE",
    "sg:address":"Oerlinghausen",
    "sg:city":"Oerlinghausen",
    "sg:phone":"+49 5202/49080",
    "sg:postcode":"33813",
    "sg:province":"Nordrhein-Westfalen",
    "wof:name":"Sparkasse Lemgo",
    "wof:placetype":"venue"
},
  "geometry": {"coordinates":[8.66891,51.949261],"type":"Point"}
}