{
  "type": "Feature",
  "properties": {
    "iso:country":"DE",
    "sg:address":"Dietrich-Bonhoeffer-Str. 7",
    "sg:city":"Taunusstein",
    "sg:phone":"+49 6128/21327",
    "sg:postcode":"65232",
    "sg:province":"Hessen",
    "wof:name":"Peter Kraus",
    "wof:placetype":"venue"
},
  "geometry": {"coordinates":[8.151084,50.151772],"type":"Point"}
}