{
  "type": "Feature",
  "properties": {
    "iso:country":"DE",
    "sg:address":"Neckarstr. 42-44",
    "sg:city":"Duisburg",
    "sg:phone":"+49 203/331032",
    "sg:postcode":"47051",
    "sg:province":"Nordrhein-Westfalen",
    "wof:name":"Schwiegelshohn Und Kollegen Rechtsanw\u00e4lte Und Notare",
    "wof:placetype":"venue"
},
  "geometry": {"coordinates":[6.7722620964,51.4361877441],"type":"Point"}
}