{
  "type": "Feature",
  "properties": {
    "iso:country":"DE",
    "sg:address":"Starenweg 7",
    "sg:city":"Meisenheim",
    "sg:phone":"+49 6753/3719",
    "sg:postcode":"55590",
    "sg:province":"Rheinland-Pfalz",
    "wof:name":"Wilhelm Heyl",
    "wof:placetype":"venue"
},
  "geometry": {"coordinates":[7.667907238,49.7001686096],"type":"Point"}
}