{
  "type": "Feature",
  "properties": {
    "iso:country":"DE",
    "sg:address":"Hauptstr. 29 Kettwig::",
    "sg:city":"Essen",
    "sg:phone":"+49 4920/5485071",
    "sg:postcode":"45219",
    "sg:province":"Nordrhein-Westfalen",
    "wof:name":"Peter Knebel",
    "wof:placetype":"venue"
},
  "geometry": {"coordinates":[6.945833,51.362202],"type":"Point"}
}