{
  "type": "Feature",
  "properties": {
    "iso:country":"DE",
    "sg:address":"Kellerberg 20",
    "sg:city":"Trittau",
    "sg:phone":"+49 4154/2838",
    "sg:postcode":"22946",
    "sg:province":"Schleswig-Holstein",
    "wof:name":"Beli Design Bernt Liebert",
    "wof:placetype":"venue"
},
  "geometry": {"coordinates":[10.405812,53.600182],"type":"Point"}
}