{
  "type": "Feature",
  "properties": {
    "iso:country":"DE",
    "sg:address":"Sevenich",
    "sg:city":"Bickenbach",
    "sg:postcode":"56291",
    "sg:province":"Rheinland-Pfalz",
    "wof:name":"Katholisches Pfarramt St. Nikolaus",
    "wof:placetype":"venue"
},
  "geometry": {"coordinates":[7.5733828545,50.130569458],"type":"Point"}
}