{
  "type": "Feature",
  "properties": {
    "iso:country":"DE",
    "sg:address":"Am Obstgarten",
    "sg:city":"B\u00fcdelsdorf",
    "sg:postcode":"24782",
    "sg:province":"Schleswig-Holstein",
    "wof:name":"Fritsche Projektentwicklungs- Gesellschaft Hollerstra\u00dfe",
    "wof:placetype":"venue"
},
  "geometry": {"coordinates":[9.6718053818,54.31690979],"type":"Point"}
}