{
  "type": "Feature",
  "properties": {
    "iso:country":"DE",
    "sg:address":"Talstr. 6",
    "sg:city":"Kenzingen",
    "sg:phone":"+49 7644/7217",
    "sg:postcode":"79341",
    "sg:province":"Baden-W\u00fcrttemberg",
    "wof:name":"Christa Und Holger Kohser",
    "wof:placetype":"venue"
},
  "geometry": {"coordinates":[7.813205,48.193943],"type":"Point"}
}