{
  "type": "Feature",
  "properties": {
    "iso:country":"DE",
    "sg:address":"Markgrafenstr. 4",
    "sg:city":"Kamp-Lintfort",
    "sg:phone":"+49 2842/3885",
    "sg:postcode":"47475",
    "sg:province":"Nordrhein-Westfalen",
    "wof:name":"Seoul",
    "wof:placetype":"venue"
},
  "geometry": {"coordinates":[6.5490307808,51.5019416809],"type":"Point"}
}