{
  "type": "Feature",
  "properties": {
    "iso:country":"DE",
    "sg:address":"M\u00fchlweg 5",
    "sg:city":"Wunsiedel",
    "sg:phone":"+49 9232/99310",
    "sg:postcode":"95632",
    "sg:province":"Bayern",
    "wof:name":"J. Keltsch Gmbh",
    "wof:placetype":"venue"
},
  "geometry": {"coordinates":[12.040018,50.048489],"type":"Point"}
}