{
  "type": "Feature",
  "properties": {
    "iso:country":"DE",
    "sg:address":"Steinweg 5",
    "sg:city":"Frankfurt",
    "sg:phone":"+49 69/9200450",
    "sg:postcode":"60313",
    "sg:province":"Hessen",
    "wof:name":"A. P. G. Air Promotion Group S. A. Zweign. Frankfurt /m. Ag",
    "wof:placetype":"venue"
},
  "geometry": {"coordinates":[8.677523,50.113358],"type":"Point"}
}