{
  "type": "Feature",
  "properties": {
    "iso:country":"DE",
    "sg:address":"R\u00fcttenscheider Str. 121",
    "sg:city":"Essen",
    "sg:phone":"+49 201/771808",
    "sg:postcode":"45130",
    "sg:province":"Nordrhein-Westfalen",
    "wof:name":"Galerie",
    "wof:placetype":"venue"
},
  "geometry": {"coordinates":[7.0053119659,51.4359779358],"type":"Point"}
}