{
  "type": "Feature",
  "properties": {
    "iso:country":"DE",
    "sg:address":"Wenzstr. 5 a",
    "sg:city":"Bad Steben",
    "sg:phone":"+49 9288/474",
    "sg:postcode":"95138",
    "sg:province":"Bayern",
    "wof:name":"Pension Haus Renate Renate Walther",
    "wof:placetype":"venue"
},
  "geometry": {"coordinates":[11.6375026703,50.3637962341],"type":"Point"}
}