{
  "type": "Feature",
  "properties": {
    "iso:country":"DE",
    "sg:address":"Kleiner Johannes 21",
    "sg:city":"Pegnitz",
    "sg:phone":"+49 9241/7220",
    "sg:postcode":"91257",
    "sg:province":"Bayern",
    "wof:name":"Gerd Hohe Gmbh & Co. Kg",
    "wof:placetype":"venue"
},
  "geometry": {"coordinates":[11.5531568527,49.7655944824],"type":"Point"}
}