{
  "type": "Feature",
  "properties": {
    "iso:country":"DE",
    "sg:address":"Aichacher Str. 8",
    "sg:city":"Schrobenhausen",
    "sg:postcode":"86529",
    "sg:province":"Bayern",
    "wof:name":"Leipa Leasing Gmbh & Co. Kg",
    "wof:placetype":"venue"
},
  "geometry": {"coordinates":[11.2646694183,48.5571556091],"type":"Point"}
}