{
  "type": "Feature",
  "properties": {
    "iso:country":"DE",
    "sg:address":"Hermersbachstr. 2",
    "sg:city":"Ramberg",
    "sg:phone":"+49 6345/959950",
    "sg:postcode":"76857",
    "sg:province":"Rheinland-Pfalz",
    "wof:name":"Pension Hermann Schmitt",
    "wof:placetype":"venue"
},
  "geometry": {"coordinates":[8.0068254471,49.2602310181],"type":"Point"}
}