{
  "type": "Feature",
  "properties": {
    "iso:country":"DE",
    "sg:address":"An der Walzenm\u00fchle 8",
    "sg:city":"Chemnitz",
    "sg:phone":"+49 371/3826318",
    "sg:postcode":"09125",
    "sg:province":"Sachsen",
    "wof:name":"Spedition Pfeifer Gmbh",
    "wof:placetype":"venue"
},
  "geometry": {"coordinates":[12.9467563629,50.7909164429],"type":"Point"}
}