{
  "type": "Feature",
  "properties": {
    "iso:country":"DE",
    "sg:address":"Industriestr. 13",
    "sg:city":"Lampertheim",
    "sg:postcode":"68623",
    "sg:province":"Hessen",
    "wof:name":"Panbrasilia Beteiligungs- Gesellschaft Mbh",
    "wof:placetype":"venue"
},
  "geometry": {"coordinates":[8.481054,49.596813],"type":"Point"}
}