{
  "type": "Feature",
  "properties": {
    "iso:country":"DE",
    "sg:address":"Rudolf-Diesel-Str. 2",
    "sg:city":"Saterland",
    "sg:phone":"+49 4498/2488",
    "sg:postcode":"26683",
    "sg:province":"Niedersachsen",
    "wof:name":"W. Seiler",
    "wof:placetype":"venue"
},
  "geometry": {"coordinates":[7.683071,53.131706],"type":"Point"}
}