{
  "type": "Feature",
  "properties": {
    "iso:country":"DE",
    "sg:address":"Gandersheimer Str. 12",
    "sg:city":"Bremen",
    "sg:postcode":"28215",
    "sg:province":"Bremen",
    "wof:name":"Freimuth Remmer Fremdenheim",
    "wof:placetype":"venue"
},
  "geometry": {"coordinates":[8.812420845,53.0970611572],"type":"Point"}
}