{
  "type": "Feature",
  "properties": {
    "iso:country":"DE",
    "sg:address":"Matthias-Claudius-Str. 15",
    "sg:city":"Neu Wulmstorf",
    "sg:phone":"+49 40/7007163",
    "sg:postcode":"21629",
    "sg:province":"Niedersachsen",
    "wof:name":"Stefan Blaskowitz Handels-gmbh",
    "wof:placetype":"venue"
},
  "geometry": {"coordinates":[9.785051,53.460487],"type":"Point"}
}