{
  "type": "Feature",
  "properties": {
    "iso:country":"DE",
    "sg:address":"Chausseestrasse 8",
    "sg:city":"Berlin",
    "sg:phone":"+49 30/820820",
    "sg:postcode":"10115",
    "sg:province":"Berlin",
    "wof:name":"Publicis Werbeagentur Gmbh, Gwa",
    "wof:placetype":"venue"
},
  "geometry": {"coordinates":[13.386478,52.528126],"type":"Point"}
}