{
  "type": "Feature",
  "properties": {
    "iso:country":"DE",
    "sg:address":"Stubenrauchstr. 8",
    "sg:city":"Zossen",
    "sg:postcode":"15806",
    "sg:province":"Brandenburg",
    "wof:name":"Sanit\u00e4tsfachhandel Orthop\u00e4die-technik Kern Gmbh",
    "wof:placetype":"venue"
},
  "geometry": {"coordinates":[13.4413633347,52.2220306396],"type":"Point"}
}