{
  "type": "Feature",
  "properties": {
    "iso:country":"DE",
    "sg:address":"Hauptstr. 28",
    "sg:city":"Sch\u00f6nwald",
    "sg:phone":"+49 7722/96000",
    "sg:postcode":"78141",
    "sg:province":"Baden-W\u00fcrttemberg",
    "wof:name":"Klaus Dold",
    "wof:placetype":"venue"
},
  "geometry": {"coordinates":[13.4396352768,52.6765594482],"type":"Point"}
}