{
  "type": "Feature",
  "properties": {
    "iso:country":"DE",
    "sg:address":"Pfarrberg 7",
    "sg:city":"Ebhausen-Rotfelden",
    "sg:phone":"+49 7054",
    "sg:postcode":"72224",
    "sg:province":"Baden-W\u00fcrttemberg",
    "wof:name":"Detektei Michael Bannasch",
    "wof:placetype":"venue"
},
  "geometry": {"coordinates":[8.676105,48.587173],"type":"Point"}
}