{
  "type": "Feature",
  "properties": {
    "iso:country":"DE",
    "sg:address":"In den L\u00f6ser 30",
    "sg:city":"Seeheim-Jugenheim",
    "sg:phone":"+49 6257/2818",
    "sg:postcode":"64342",
    "sg:province":"Hessen",
    "wof:name":"Otto Franz",
    "wof:placetype":"venue"
},
  "geometry": {"coordinates":[8.6268205643,49.7541732788],"type":"Point"}
}