{
  "type": "Feature",
  "properties": {
    "iso:country":"DE",
    "sg:address":"Slevogtstr. 85",
    "sg:city":"Chemnitz",
    "sg:phone":"+49 371/440426",
    "sg:postcode":"09114",
    "sg:province":"Sachsen",
    "wof:name":"Hebenstreit & K\u00fchne Gbr",
    "wof:placetype":"venue"
},
  "geometry": {"coordinates":[12.9493923187,50.8829994202],"type":"Point"}
}