{
  "type": "Feature",
  "properties": {
    "iso:country":"DE",
    "sg:address":"Schweizer Allee 43",
    "sg:city":"Dortmund",
    "sg:phone":"+49 231/443966",
    "sg:postcode":"44287",
    "sg:province":"Nordrhein-Westfalen",
    "wof:name":"Ebeling Gmbh",
    "wof:placetype":"venue"
},
  "geometry": {"coordinates":[7.563629,51.489044],"type":"Point"}
}