{
  "type": "Feature",
  "properties": {
    "iso:country":"DE",
    "sg:address":"Hauptstr. 26",
    "sg:city":"Weener",
    "sg:phone":"+49 4951/912443",
    "sg:postcode":"26826",
    "sg:province":"Niedersachsen",
    "wof:name":"Hinrichs Dienstleistungs- Service Gmbh",
    "wof:placetype":"venue"
},
  "geometry": {"coordinates":[7.3231,53.13652],"type":"Point"}
}