{
  "type": "Feature",
  "properties": {
    "iso:country":"DE",
    "sg:address":"Wenzel-Jaksch-Str. 9 a",
    "sg:city":"Wiesbaden",
    "sg:phone":"+49 611/460344",
    "sg:postcode":"65199",
    "sg:province":"Hessen",
    "wof:name":"Ulrich Weiland Ingenieur",
    "wof:placetype":"venue"
},
  "geometry": {"coordinates":[8.1919527054,50.0870323181],"type":"Point"}
}