{
  "type": "Feature",
  "properties": {
    "iso:country":"DE",
    "sg:address":"Herrenweg 12",
    "sg:city":"Mettlach",
    "sg:phone":"+49 6865/8145",
    "sg:postcode":"66693",
    "sg:province":"Saarland",
    "wof:name":"Rene Schwarz",
    "wof:placetype":"venue"
},
  "geometry": {"coordinates":[6.523324,49.50404],"type":"Point"}
}