{
  "type": "Feature",
  "properties": {
    "iso:country":"DE",
    "sg:address":"Roritzerstr. 27",
    "sg:city":"N\u00fcrnberg",
    "sg:phone":"+49 911/337276",
    "sg:postcode":"90419",
    "sg:province":"Bayern",
    "wof:name":"Optimal Wohnbau Gmbh",
    "wof:placetype":"venue"
},
  "geometry": {"coordinates":[11.069595,49.462082],"type":"Point"}
}