{
  "type": "Feature",
  "properties": {
    "iso:country":"DE",
    "sg:address":"Deutschherrenstr. 87",
    "sg:city":"Bonn",
    "sg:phone":"+49 228/316919",
    "sg:postcode":"53177",
    "sg:province":"Nordrhein-Westfalen",
    "wof:name":"Dr. Hans-joachim Borowka Tierarzt",
    "wof:placetype":"venue"
},
  "geometry": {"coordinates":[7.164744854,50.6708946228],"type":"Point"}
}