{
  "type": "Feature",
  "properties": {
    "iso:country":"DE",
    "sg:address":"Forster Str. 10",
    "sg:city":"D\u00f6bern",
    "sg:phone":"+49 35600/6088",
    "sg:postcode":"03159",
    "sg:province":"Brandenburg",
    "wof:name":"B. Knievel",
    "wof:placetype":"venue"
},
  "geometry": {"coordinates":[14.595221,51.616531],"type":"Point"}
}