{
  "type": "Feature",
  "properties": {
    "iso:country":"DE",
    "sg:address":"Rottendorf 28",
    "sg:city":"Niedermurach",
    "sg:phone":"+49 9671/2106",
    "sg:postcode":"92545",
    "sg:province":"Bayern",
    "wof:name":"Michael S\u00fc\u00df",
    "wof:placetype":"venue"
},
  "geometry": {"coordinates":[12.3508481979,49.461063385],"type":"Point"}
}