{
  "type": "Feature",
  "properties": {
    "iso:country":"DE",
    "sg:address":"Eichelstr. 32",
    "sg:city":"Bodnegg",
    "sg:phone":"+49 7520/9220",
    "sg:postcode":"88285",
    "sg:province":"Baden-W\u00fcrttemberg",
    "wof:name":"Zurga Damir",
    "wof:placetype":"venue"
},
  "geometry": {"coordinates":[9.697293,47.732269],"type":"Point"}
}