{
  "type": "Feature",
  "properties": {
    "iso:country":"DE",
    "sg:address":"In de Huck 4",
    "sg:city":"Bosau",
    "sg:postcode":"23715",
    "sg:province":"Schleswig-Holstein",
    "wof:name":"R. Westphal Sielmauerarbeiten Gmbh",
    "wof:placetype":"venue"
},
  "geometry": {"coordinates":[10.499624,54.078041],"type":"Point"}
}