{
  "type": "Feature",
  "properties": {
    "iso:country":"DE",
    "sg:address":"Damm 2",
    "sg:city":"Sickte",
    "sg:phone":"+49 5305/555",
    "sg:postcode":"38173",
    "sg:province":"Niedersachsen",
    "wof:name":"Walter Preu\u00df",
    "wof:placetype":"venue"
},
  "geometry": {"coordinates":[10.6359529495,52.2130279541],"type":"Point"}
}