{
  "type": "Feature",
  "properties": {
    "iso:country":"DE",
    "sg:address":"Escherstr. 14",
    "sg:city":"Hannover",
    "sg:phone":"+49 511/1610595",
    "sg:postcode":"30159",
    "sg:province":"Niedersachsen",
    "wof:name":"Concept Computer- Und Analyse- Ingenieurb\u00fcro",
    "wof:placetype":"venue"
},
  "geometry": {"coordinates":[9.7270698547,52.3766365051],"type":"Point"}
}