{
  "type": "Feature",
  "properties": {
    "iso:country":"DE",
    "sg:address":"Johannesstr. 1",
    "sg:city":"Dormagen",
    "sg:phone":"+49 2133/227041",
    "sg:postcode":"41542",
    "sg:province":"Nordrhein-Westfalen",
    "wof:name":"Alter Bahnhof",
    "wof:placetype":"venue"
},
  "geometry": {"coordinates":[6.7831997871,51.123500824],"type":"Point"}
}