{
  "type": "Feature",
  "properties": {
    "iso:country":"DE",
    "sg:address":"Wiesenweg 5",
    "sg:city":"Gieboldehausen",
    "sg:phone":"+49 5528/1306",
    "sg:postcode":"37434",
    "sg:province":"Niedersachsen",
    "wof:name":"Karl Wracker Heissmangel",
    "wof:placetype":"venue"
},
  "geometry": {"coordinates":[10.2127361298,51.6131248474],"type":"Point"}
}