{
  "type": "Feature",
  "properties": {
    "iso:country":"DE",
    "sg:address":"Friedlandstr. 9",
    "sg:city":"St. Ingbert",
    "sg:phone":"+49 6894/4808",
    "sg:postcode":"66386",
    "sg:province":"Saarland",
    "wof:name":"Bernd Britz Steuerberater",
    "wof:placetype":"venue"
},
  "geometry": {"coordinates":[7.0778059959,49.2637214661],"type":"Point"}
}