{
  "type": "Feature",
  "properties": {
    "iso:country":"DE",
    "sg:address":"Bahnhofstr. 43",
    "sg:city":"Wehrheim",
    "sg:phone":"+49 6081/59490",
    "sg:postcode":"61273",
    "sg:province":"Hessen",
    "wof:name":"Cafehaus Service U. Betriebs-gmbh",
    "wof:placetype":"venue"
},
  "geometry": {"coordinates":[8.56825,50.302078],"type":"Point"}
}