{
  "type": "Feature",
  "properties": {
    "iso:country":"DE",
    "sg:address":"Sch\u00fctzenhofweg 18",
    "sg:city":"Hofgeismar",
    "sg:phone":"+49 5671/5523",
    "sg:postcode":"34369",
    "sg:province":"Hessen",
    "wof:name":"Hans-j\u00fcrgen R\u00f6hling Architekt",
    "wof:placetype":"venue"
},
  "geometry": {"coordinates":[9.374501,51.492233],"type":"Point"}
}