{
  "type": "Feature",
  "properties": {
    "iso:country":"DE",
    "sg:address":"Robert-Bosch-Str 6",
    "sg:city":"Gosheim",
    "sg:phone":"+49 7426/6435",
    "sg:postcode":"78559",
    "sg:province":"Baden-W\u00fcrttemberg",
    "wof:name":"Karl Hermle",
    "wof:placetype":"venue"
},
  "geometry": {"coordinates":[8.758205,48.139984],"type":"Point"}
}