{
  "type": "Feature",
  "properties": {
    "iso:country":"DE",
    "sg:address":"Heinheimer Str. 82",
    "sg:city":"Darmstadt",
    "sg:phone":"+49 6151/784149",
    "sg:postcode":"64289",
    "sg:province":"Hessen",
    "wof:name":"Anhold-parkett Gmbh",
    "wof:placetype":"venue"
},
  "geometry": {"coordinates":[8.6602258682,49.8815994263],"type":"Point"}
}