{
  "type": "Feature",
  "properties": {
    "iso:country":"DE",
    "sg:address":"Alte Bahnlinie 6",
    "sg:city":"Leutkirch",
    "sg:phone":"+49 7567/1588",
    "sg:postcode":"88299",
    "sg:province":"Baden-W\u00fcrttemberg",
    "wof:name":"F. Knittel",
    "wof:placetype":"venue"
},
  "geometry": {"coordinates":[10.0577697754,47.7571487427],"type":"Point"}
}