{
  "type": "Feature",
  "properties": {
    "iso:country":"DE",
    "sg:address":"Alt Riemsloh 51",
    "sg:city":"Melle",
    "sg:phone":"+49 5226/5050",
    "sg:postcode":"49328",
    "sg:province":"Niedersachsen",
    "wof:name":"Restaurant H.-g. M\u00f6ller",
    "wof:placetype":"venue"
},
  "geometry": {"coordinates":[8.4225378036,52.1810798645],"type":"Point"}
}