{
  "type": "Feature",
  "properties": {
    "iso:country":"DE",
    "sg:address":"Ochtruper Str. 14",
    "sg:city":"Bad Bentheim",
    "sg:phone":"+49 5922/2285",
    "sg:postcode":"48455",
    "sg:province":"Niedersachsen",
    "wof:name":"G. Bergfeld",
    "wof:placetype":"venue"
},
  "geometry": {"coordinates":[7.162112236,52.3009529114],"type":"Point"}
}