{
  "type": "Feature",
  "properties": {
    "iso:country":"DE",
    "sg:address":"M\u00fcllersweg 14",
    "sg:city":"Erlenbach",
    "sg:phone":"+49 9372/8948",
    "sg:postcode":"63906",
    "sg:province":"Bayern",
    "wof:name":"Wissenschaftl. Antiquariat Pfeffer Gmbh",
    "wof:placetype":"venue"
},
  "geometry": {"coordinates":[9.1955108643,49.7919921875],"type":"Point"}
}