{
  "type": "Feature",
  "properties": {
    "iso:country":"DE",
    "sg:address":"Auguste-Viktoria-Str. 10/12",
    "sg:city":"Kiel",
    "sg:phone":"+49 431/672148",
    "sg:postcode":"24103",
    "sg:province":"Schleswig-Holstein",
    "wof:name":"Beratungsstelle Verein Zur F\u00f6rderung Der Ge-",
    "wof:placetype":"venue"
},
  "geometry": {"coordinates":[10.132993,54.316868],"type":"Point"}
}