{
  "type": "Feature",
  "properties": {
    "iso:country":"DE",
    "sg:address":"Hohlweg 7",
    "sg:city":"Neu-Anspach",
    "sg:phone":"+49 6081/7517",
    "sg:postcode":"61267",
    "sg:province":"Hessen",
    "wof:name":"Jakob Urban & S\u00f6hne Bau- Und M\u00f6belschreinerei",
    "wof:placetype":"venue"
},
  "geometry": {"coordinates":[8.504375,50.291862],"type":"Point"}
}