{
  "type": "Feature",
  "properties": {
    "iso:country":"DE",
    "sg:address":"Hofer Str. 19 a",
    "sg:city":"D\u00f6hlau",
    "sg:postcode":"95182",
    "sg:province":"Bayern",
    "wof:name":"D\u00f6llinger Rolladen Vertrieb Inh. Magdalena D\u00f6llinger",
    "wof:placetype":"venue"
},
  "geometry": {"coordinates":[11.946802,50.280788],"type":"Point"}
}