{
  "type": "Feature",
  "properties": {
    "iso:country":"DE",
    "sg:address":"Hans-B\u00f6ckler-Str. 20",
    "sg:city":"Trebur",
    "sg:phone":"+49 6147/3800",
    "sg:postcode":"65468",
    "sg:province":"Hessen",
    "wof:name":"Ristorante Pizzeria Einsiedlerhof Bei Manuel",
    "wof:placetype":"venue"
},
  "geometry": {"coordinates":[8.3864860535,49.9360542297],"type":"Point"}
}