{
  "type": "Feature",
  "properties": {
    "iso:country":"DE",
    "sg:address":"Neunkircher Str. 109",
    "sg:city":"Saarbr\u00fccken",
    "sg:phone":"+49 681/375566",
    "sg:postcode":"66113",
    "sg:province":"Saarland",
    "wof:name":"Premium Tours G\u00f6rbe Reisen Und Handelsvermittlungen Gmbh",
    "wof:placetype":"venue"
},
  "geometry": {"coordinates":[6.9949560165,49.2505950928],"type":"Point"}
}