{
  "type": "Feature",
  "properties": {
    "iso:country":"DE",
    "sg:address":"Kurt-Schumacher-Str. 34",
    "sg:city":"B\u00fcnde",
    "sg:phone":"+49 5223/160919",
    "sg:postcode":"32257",
    "sg:province":"Nordrhein-Westfalen",
    "wof:name":"Keg Klemmt Elektrotechnik Gmbh",
    "wof:placetype":"venue"
},
  "geometry": {"coordinates":[8.5777826309,52.1823959351],"type":"Point"}
}