{
  "type": "Feature",
  "properties": {
    "iso:country":"DE",
    "sg:address":"Bechtheimer Hohl 2",
    "sg:city":"Osthofen",
    "sg:phone":"+49 6242/3176",
    "sg:postcode":"67574",
    "sg:province":"Rheinland-Pfalz",
    "wof:name":"R\u00fcdiger Seibel",
    "wof:placetype":"venue"
},
  "geometry": {"coordinates":[8.320677,49.706203],"type":"Point"}
}