{
  "type": "Feature",
  "properties": {
    "iso:country":"DE",
    "sg:address":"Reuterstr. 17",
    "sg:city":"Admannshagen-Bargeshagen",
    "sg:phone":"+49 38203/5990",
    "sg:postcode":"18211",
    "sg:province":"Mecklenburg-Vorpommern",
    "wof:name":"Moeller Gmbh",
    "wof:placetype":"venue"
},
  "geometry": {"coordinates":[11.9962100983,54.1134643555],"type":"Point"}
}