{
  "type": "Feature",
  "properties": {
    "iso:country":"DE",
    "sg:address":"Tegelr Weg 103",
    "sg:city":"Berlin",
    "sg:phone":"+49 30/34502746",
    "sg:postcode":"10589",
    "sg:province":"Berlin",
    "wof:name":"Topas Consulting",
    "wof:placetype":"venue"
},
  "geometry": {"coordinates":[13.30643,52.527748],"type":"Point"}
}