{
  "type": "Feature",
  "properties": {
    "iso:country":"DE",
    "sg:address":"Noltenweg 17",
    "sg:city":"Stuttgart",
    "sg:phone":"+49 711/7651414",
    "sg:postcode":"70597",
    "sg:province":"Baden-W\u00fcrttemberg",
    "wof:name":"Gert Klopfer",
    "wof:placetype":"venue"
},
  "geometry": {"coordinates":[9.1565856934,48.744228363],"type":"Point"}
}