{
  "type": "Feature",
  "properties": {
    "iso:country":"DE",
    "sg:address":"Zerbster Str. 9",
    "sg:city":"Bornum",
    "sg:phone":"+49 39248/591",
    "sg:postcode":"39264",
    "sg:province":"Sachsen-Anhalt",
    "wof:name":"Bsv Gmbh",
    "wof:placetype":"venue"
},
  "geometry": {"coordinates":[12.198557,51.984638],"type":"Point"}
}