{
  "type": "Feature",
  "properties": {
    "iso:country":"DE",
    "sg:address":"Zum Bassin 1",
    "sg:city":"Mettlach",
    "sg:phone":"+49 6865/284",
    "sg:postcode":"66693",
    "sg:province":"Saarland",
    "wof:name":"G\u00fcnter Th\u00f6sen Kohlen-handlung",
    "wof:placetype":"venue"
},
  "geometry": {"coordinates":[6.525351,49.507339],"type":"Point"}
}