{
  "type": "Feature",
  "properties": {
    "iso:country":"DE",
    "sg:address":"Friedensstr. 1",
    "sg:city":"Graal-M\u00fcritz",
    "sg:phone":"+49 38206/337",
    "sg:postcode":"18181",
    "sg:province":"Mecklenburg-Vorpommern",
    "wof:name":"Seestern",
    "wof:placetype":"venue"
},
  "geometry": {"coordinates":[12.230340004,54.2513313293],"type":"Point"}
}