{
  "type": "Feature",
  "properties": {
    "iso:country":"DE",
    "sg:address":"N\u00fcrnberger Str. 36",
    "sg:city":"Zirndorf",
    "sg:phone":"+49 911/606976",
    "sg:postcode":"90513",
    "sg:province":"Bayern",
    "wof:name":"Regina - Dessous Elfriede K\u00f6ppen",
    "wof:placetype":"venue"
},
  "geometry": {"coordinates":[10.962564,49.439697],"type":"Point"}
}