{
  "type": "Feature",
  "properties": {
    "iso:country":"DE",
    "sg:address":"Postgartenstr. 8",
    "sg:city":"Schwandorf",
    "sg:phone":"+49 9431/1681",
    "sg:postcode":"92421",
    "sg:province":"Bayern",
    "wof:name":"Grillstuben Inh. Theresia Gillitzer",
    "wof:placetype":"venue"
},
  "geometry": {"coordinates":[12.107550621,49.326839447],"type":"Point"}
}