{
  "type": "Feature",
  "properties": {
    "iso:country":"DE",
    "sg:address":"Hog'n Dor 1",
    "sg:city":"Westerr\u00f6nfeld",
    "sg:phone":"+49 4331/80910",
    "sg:postcode":"24784",
    "sg:province":"Schleswig-Holstein",
    "wof:name":"Haus Hog N Dor Westerr\u00f6nfeld Homfeldt Ohg",
    "wof:placetype":"venue"
},
  "geometry": {"coordinates":[9.6553401947,54.2783088684],"type":"Point"}
}