{
  "type": "Feature",
  "properties": {
    "iso:country":"DE",
    "sg:address":"Friedrichstr. 38",
    "sg:city":"Darmstadt",
    "sg:phone":"+49 6151/892080",
    "sg:postcode":"64293",
    "sg:province":"Hessen",
    "wof:name":"Treuge Treuhand Gmbh",
    "wof:placetype":"venue"
},
  "geometry": {"coordinates":[8.641951561,49.8736763],"type":"Point"}
}