{
  "type": "Feature",
  "properties": {
    "iso:country":"DE",
    "sg:address":"Am Sommerkeller 3",
    "sg:city":"Reimlingen",
    "sg:phone":"+49 9081/4831",
    "sg:postcode":"86756",
    "sg:province":"Bayern",
    "wof:name":"Beyschlag Verm\u00f6gensverwaltungs Gmbh & Co. Kg",
    "wof:placetype":"venue"
},
  "geometry": {"coordinates":[10.5145330429,48.8143806458],"type":"Point"}
}