{
  "type": "Feature",
  "properties": {
    "iso:country":"DE",
    "sg:address":"Metzstr. 13",
    "sg:city":"Pullach",
    "sg:postcode":"82049",
    "sg:province":"Bayern",
    "wof:name":"Cc4u Gmbh",
    "wof:placetype":"venue"
},
  "geometry": {"coordinates":[11.5164327621,48.0628585815],"type":"Point"}
}