{
  "type": "Feature",
  "properties": {
    "iso:country":"DE",
    "sg:address":"Lange Str. 27",
    "sg:city":"Salzhemmendorf",
    "sg:phone":"+49 5186/492",
    "sg:postcode":"31020",
    "sg:province":"Niedersachsen",
    "wof:name":"G\u00fcnther Wecke Gmbh",
    "wof:placetype":"venue"
},
  "geometry": {"coordinates":[9.59008,52.065578],"type":"Point"}
}