{
  "type": "Feature",
  "properties": {
    "iso:country":"DE",
    "sg:address":"Kornstr. 108",
    "sg:city":"Bremen",
    "sg:phone":"+49 421/554566",
    "sg:postcode":"28201",
    "sg:province":"Bremen",
    "wof:name":"Jacob`s Weineck Thomas Jacob",
    "wof:placetype":"venue"
},
  "geometry": {"coordinates":[8.8039474487,53.0625953674],"type":"Point"}
}