{
  "type": "Feature",
  "properties": {
    "iso:country":"DE",
    "sg:address":"Tannichtstr.",
    "sg:city":"G\u00f6\u00dfnitz",
    "sg:postcode":"04639",
    "sg:province":"Th\u00fcringen",
    "wof:name":"St\u00e4dtisches Freibad",
    "wof:placetype":"venue"
},
  "geometry": {"coordinates":[12.4352350235,50.889755249],"type":"Point"}
}