{
  "type": "Feature",
  "properties": {
    "iso:country":"DE",
    "sg:address":"Reinhard-Booz-Str. 17",
    "sg:city":"Merzhausen",
    "sg:postcode":"79249",
    "sg:province":"Baden-W\u00fcrttemberg",
    "wof:name":"Joachim Hackenjos",
    "wof:placetype":"venue"
},
  "geometry": {"coordinates":[7.8337931633,47.9700126648],"type":"Point"}
}