{
  "type": "Feature",
  "properties": {
    "iso:country":"DE",
    "sg:address":"Hintertal 3",
    "sg:city":"Fischerbach",
    "sg:phone":"+49 7832/8437",
    "sg:postcode":"77716",
    "sg:province":"Baden-W\u00fcrttemberg",
    "wof:name":"Konrad Roser",
    "wof:placetype":"venue"
},
  "geometry": {"coordinates":[8.123511,48.305042],"type":"Point"}
}