{
  "type": "Feature",
  "properties": {
    "iso:country":"DE",
    "sg:address":"Bahnhofstr. 50",
    "sg:city":"Eppingen",
    "sg:phone":"+49 7262/5040",
    "sg:postcode":"75031",
    "sg:province":"Baden-W\u00fcrttemberg",
    "wof:name":"Deutsche Bahn Ag",
    "wof:placetype":"venue"
},
  "geometry": {"coordinates":[8.9144229889,49.1362380981],"type":"Point"}
}