{
  "type": "Feature",
  "properties": {
    "iso:country":"DE",
    "sg:address":"Bertoldsplatz 6",
    "sg:city":"St. Peter",
    "sg:phone":"+49 7660/269",
    "sg:postcode":"79271",
    "sg:province":"Baden-W\u00fcrttemberg",
    "wof:name":"B. Weber",
    "wof:placetype":"venue"
},
  "geometry": {"coordinates":[8.0314073563,48.0158615112],"type":"Point"}
}