{
  "type": "Feature",
  "properties": {
    "iso:country":"DE",
    "sg:address":"Dorfstr. 19",
    "sg:city":"Lindewitt",
    "sg:phone":"+49 4604/2123",
    "sg:postcode":"24969",
    "sg:province":"Schleswig-Holstein",
    "wof:name":"H.-c. Christiansen",
    "wof:placetype":"venue"
},
  "geometry": {"coordinates":[9.223755,54.679115],"type":"Point"}
}