{
  "type": "Feature",
  "properties": {
    "iso:country":"DE",
    "sg:address":"Merkurstr. 21",
    "sg:city":"Kaiserslautern",
    "sg:phone":"+49 631/351490",
    "sg:postcode":"67663",
    "sg:province":"Rheinland-Pfalz",
    "wof:name":"Rheinm\u00f6ve Gmbh",
    "wof:placetype":"venue"
},
  "geometry": {"coordinates":[7.726575,49.442863],"type":"Point"}
}