{
  "type": "Feature",
  "properties": {
    "iso:country":"DE",
    "sg:address":"Schillerstr. 49",
    "sg:city":"Gerlingen",
    "sg:phone":"+49 7156/43000",
    "sg:postcode":"70839",
    "sg:province":"Baden-W\u00fcrttemberg",
    "wof:name":"Frigotechnik Handels-gmbh",
    "wof:placetype":"venue"
},
  "geometry": {"coordinates":[9.0678415298,48.8025283813],"type":"Point"}
}