{
  "type": "Feature",
  "properties": {
    "iso:country":"DE",
    "sg:address":"Josef-Schmitt-Str. 1",
    "sg:city":"Lauda-K\u00f6nigshofen",
    "sg:phone":"+49 9343/4525",
    "sg:postcode":"97922",
    "sg:province":"Baden-W\u00fcrttemberg",
    "wof:name":"Aktion 365 Michael Jouaux",
    "wof:placetype":"venue"
},
  "geometry": {"coordinates":[9.7039499283,49.5692825317],"type":"Point"}
}