{
  "type": "Feature",
  "properties": {
    "iso:country":"DE",
    "sg:address":"Auricher Str. 15",
    "sg:city":"Hesel",
    "sg:phone":"+49 4950/990201",
    "sg:postcode":"26835",
    "sg:province":"Niedersachsen",
    "wof:name":"Boombastico Inh. M. U. R. Maxhuni",
    "wof:placetype":"venue"
},
  "geometry": {"coordinates":[7.5939741135,53.3078155518],"type":"Point"}
}