{
  "type": "Feature",
  "properties": {
    "iso:country":"DE",
    "sg:address":"Winkelstr. 9",
    "sg:city":"J\u00fctzenbach",
    "sg:phone":"+49 36072/81382",
    "sg:postcode":"37345",
    "sg:province":"Th\u00fcringen",
    "wof:name":"Kurt B\u00f6ning",
    "wof:placetype":"venue"
},
  "geometry": {"coordinates":[10.380588,51.524387],"type":"Point"}
}