{
  "type": "Feature",
  "properties": {
    "iso:country":"DE",
    "sg:address":"Kiefernweg",
    "sg:city":"Isernhagen",
    "sg:phone":"+49 511/733800",
    "sg:postcode":"30916",
    "sg:province":"Niedersachsen",
    "wof:name":"Bks Baustoffe Verwaltungs-gmbh",
    "wof:placetype":"venue"
},
  "geometry": {"coordinates":[9.9064750671,52.4432945251],"type":"Point"}
}