{
  "type": "Feature",
  "properties": {
    "iso:country":"DE",
    "sg:address":"Amselweg 13",
    "sg:city":"Heimsheim",
    "sg:phone":"+49 7033/32492",
    "sg:postcode":"71296",
    "sg:province":"Baden-W\u00fcrttemberg",
    "wof:name":"Biohof Walter Gommel",
    "wof:placetype":"venue"
},
  "geometry": {"coordinates":[8.859377,48.80378],"type":"Point"}
}