{
  "type": "Feature",
  "properties": {
    "iso:country":"DE",
    "sg:address":"Am Salzstadel 8",
    "sg:city":"Haldenwang",
    "sg:phone":"+49 8304/1339",
    "sg:postcode":"87490",
    "sg:province":"Bayern",
    "wof:name":"Perras & Mirsch",
    "wof:placetype":"venue"
},
  "geometry": {"coordinates":[10.3587398529,47.781375885],"type":"Point"}
}