{
  "type": "Feature",
  "properties": {
    "iso:country":"DE",
    "sg:address":"Friedrich-Ebert-Strasse 91",
    "sg:city":"Hamburg",
    "sg:phone":"+49 40/551001719",
    "sg:postcode":"22459",
    "sg:province":"Hamburg",
    "wof:name":"Morgenstern",
    "wof:placetype":"venue"
},
  "geometry": {"coordinates":[9.9359760284,53.6261634827],"type":"Point"}
}