{
  "type": "Feature",
  "properties": {
    "iso:country":"DE",
    "sg:address":"Hochheimer Str. 6 b",
    "sg:city":"Hattersheim",
    "sg:phone":"+49 6145/377920",
    "sg:postcode":"65795",
    "sg:province":"Hessen",
    "wof:name":"Rosa Gesellschaft F\u00fcr Edv-beratung Mbh",
    "wof:placetype":"venue"
},
  "geometry": {"coordinates":[8.4676275253,50.0401687622],"type":"Point"}
}