{
  "type": "Feature",
  "properties": {
    "iso:country":"DE",
    "sg:address":"Bramfelder Chaussee 253",
    "sg:city":"Hamburg",
    "sg:phone":"+49 40/6418056",
    "sg:postcode":"22177",
    "sg:province":"Hamburg",
    "wof:name":"Hans Damms",
    "wof:placetype":"venue"
},
  "geometry": {"coordinates":[10.0758953094,53.6141662598],"type":"Point"}
}