{
  "type": "Feature",
  "properties": {
    "iso:country":"DE",
    "sg:address":"Blumenstr. 11",
    "sg:city":"Schongau",
    "sg:phone":"+49 8861/23720",
    "sg:postcode":"86956",
    "sg:province":"Bayern",
    "wof:name":"C. Reiter",
    "wof:placetype":"venue"
},
  "geometry": {"coordinates":[10.8971185684,47.8166236877],"type":"Point"}
}