{
  "type": "Feature",
  "properties": {
    "iso:country":"DE",
    "sg:address":"Oberwei\u00dfbacher Str. 7-10",
    "sg:city":"Unterwei\u00dfbach",
    "sg:phone":"+49 36730/22341",
    "sg:postcode":"98744",
    "sg:province":"Th\u00fcringen",
    "wof:name":"Unterwei\u00dfbacher Werkst\u00e4tten F\u00fcr Porzellankunst Gmbh",
    "wof:placetype":"venue"
},
  "geometry": {"coordinates":[11.1653575897,50.6144943237],"type":"Point"}
}