{
  "type": "Feature",
  "properties": {
    "iso:country":"DE",
    "sg:address":"Heinrich-Sinz-Str. 30",
    "sg:city":"Krumbach",
    "sg:phone":"+49 8282/81206",
    "sg:postcode":"86381",
    "sg:province":"Bayern",
    "wof:name":"Nps New Product Service Gmbh",
    "wof:placetype":"venue"
},
  "geometry": {"coordinates":[10.370194,48.244396],"type":"Point"}
}