{
  "type": "Feature",
  "properties": {
    "iso:country":"DE",
    "sg:address":"Niemannsweg 111",
    "sg:city":"Kiel",
    "sg:phone":"+49 431/8667970",
    "sg:postcode":"24105",
    "sg:province":"Schleswig-Holstein",
    "wof:name":"Jan Wendt Architekt",
    "wof:placetype":"venue"
},
  "geometry": {"coordinates":[10.15039,54.340607],"type":"Point"}
}