{
  "type": "Feature",
  "properties": {
    "iso:country":"DE",
    "sg:address":"Ahornweg 2 A",
    "sg:city":"Waltenhofen",
    "sg:phone":"+49 831/27808",
    "sg:postcode":"87448",
    "sg:province":"Bayern",
    "wof:name":"Obst Mair Gmbh Import Export",
    "wof:placetype":"venue"
},
  "geometry": {"coordinates":[10.307832,47.682579],"type":"Point"}
}