{
  "type": "Feature",
  "properties": {
    "iso:country":"DE",
    "sg:address":"Carl-Schroeder-Str. 2",
    "sg:city":"Sondershausen",
    "sg:postcode":"99706",
    "sg:province":"Th\u00fcringen",
    "wof:name":"Foto-bl\u00e4ttermann",
    "wof:placetype":"venue"
},
  "geometry": {"coordinates":[10.8701753616,51.370765686],"type":"Point"}
}