{
  "type": "Feature",
  "properties": {
    "iso:country":"DE",
    "sg:address":"Spadenteich 1",
    "sg:city":"Hamburg",
    "sg:phone":"+49 40/2840130",
    "sg:postcode":"21109",
    "sg:province":"Hamburg",
    "wof:name":"Ipr, Idee Public Relations",
    "wof:placetype":"venue"
},
  "geometry": {"coordinates":[10.0126724243,53.4983253479],"type":"Point"}
}