{
  "type": "Feature",
  "properties": {
    "iso:country":"DE",
    "sg:address":"Ilvesheimer Str. 26",
    "sg:city":"Ladenburg",
    "sg:phone":"+49 6203/92830",
    "sg:postcode":"68526",
    "sg:province":"Baden-W\u00fcrttemberg",
    "wof:name":"C. Benz S\u00f6hne Gmbh",
    "wof:placetype":"venue"
},
  "geometry": {"coordinates":[8.596386,49.474243],"type":"Point"}
}