{
  "type": "Feature",
  "properties": {
    "iso:country":"DE",
    "sg:address":"Dresdner Str. 23",
    "sg:city":"Freiberg",
    "sg:phone":"+49 4937/3122551",
    "sg:postcode":"09599",
    "sg:province":"Sachsen",
    "wof:name":"Freiberger Metallwarenfabrikpaul Bachmann Gmbh",
    "wof:placetype":"venue"
},
  "geometry": {"coordinates":[13.358237,50.916111],"type":"Point"}
}