{
  "type": "Feature",
  "properties": {
    "iso:country":"DE",
    "sg:address":"Erlenweg 4",
    "sg:city":"Bietigheim-Bissingen",
    "sg:phone":"+49 7142/30602",
    "sg:postcode":"74321",
    "sg:province":"Baden-W\u00fcrttemberg",
    "wof:name":"Friedrich Rosemeyer",
    "wof:placetype":"venue"
},
  "geometry": {"coordinates":[9.0945320129,48.9434585571],"type":"Point"}
}