{
  "type": "Feature",
  "properties": {
    "iso:country":"DE",
    "sg:address":"Stuttgarter Allee 22",
    "sg:city":"Leipzig",
    "sg:phone":"+49 341/4225591",
    "sg:postcode":"04209",
    "sg:province":"Sachsen",
    "wof:name":"Schuberts Blumeneck",
    "wof:placetype":"venue"
},
  "geometry": {"coordinates":[12.291841,51.3167],"type":"Point"}
}