{
  "type": "Feature",
  "properties": {
    "iso:country":"DE",
    "sg:address":"Basler Str. 33 a",
    "sg:city":"L\u00f6rrach",
    "sg:phone":"+49 7621/2966",
    "sg:postcode":"79540",
    "sg:province":"Baden-W\u00fcrttemberg",
    "wof:name":"Walter Storz Holzbearbeitung",
    "wof:placetype":"venue"
},
  "geometry": {"coordinates":[7.658683,47.601677],"type":"Point"}
}