{
  "type": "Feature",
  "properties": {
    "iso:country":"DE",
    "sg:address":"Elisabethenstr. 8",
    "sg:city":"Bad K\u00f6nig",
    "sg:phone":"+49 6063/636",
    "sg:postcode":"64732",
    "sg:province":"Hessen",
    "wof:name":"Christian Schneller",
    "wof:placetype":"venue"
},
  "geometry": {"coordinates":[9.0057659149,49.742023468],"type":"Point"}
}