{
  "type": "Feature",
  "properties": {
    "iso:country":"DE",
    "sg:address":"Loschwitzer Str. 42",
    "sg:city":"Dresden",
    "sg:phone":"+49 351/3360246",
    "sg:postcode":"01309",
    "sg:province":"Sachsen",
    "wof:name":"Communal Consult Dresden/ Sachsen Gmbh_ingenieurb\u00fcro",
    "wof:placetype":"venue"
},
  "geometry": {"coordinates":[13.8004198074,51.0526123047],"type":"Point"}
}