{
  "type": "Feature",
  "properties": {
    "iso:country":"DE",
    "sg:address":"Violinenstr. 19",
    "sg:city":"Brilon",
    "sg:phone":"+49 2963/503",
    "sg:postcode":"59929",
    "sg:province":"Nordrhein-Westfalen",
    "wof:name":"Albert Erlemeier Industriebedarf",
    "wof:placetype":"venue"
},
  "geometry": {"coordinates":[8.636381,51.377144],"type":"Point"}
}