{
  "type": "Feature",
  "properties": {
    "iso:country":"DE",
    "sg:address":"Burgstr. 2",
    "sg:city":"\u00dcberherrn",
    "sg:phone":"+49 6836/2701",
    "sg:postcode":"66802",
    "sg:province":"Saarland",
    "wof:name":"Fritz Sch\u00f6nek\u00e4s",
    "wof:placetype":"venue"
},
  "geometry": {"coordinates":[6.6978340149,49.2648582458],"type":"Point"}
}