{
  "type": "Feature",
  "properties": {
    "iso:country":"DE",
    "sg:address":"06648",
    "sg:city":"Tromsdorf",
    "sg:phone":"+49 36373/412",
    "sg:postcode":"06648",
    "sg:province":"Sachsen-Anhalt",
    "wof:name":"Gastst\u00e4tte Zur Linde",
    "wof:placetype":"venue"
},
  "geometry": {"coordinates":[11.4810991287,51.1171035767],"type":"Point"}
}