{
  "type": "Feature",
  "properties": {
    "iso:country":"DE",
    "sg:address":"Hochstr. 2-28",
    "sg:city":"Duisburg",
    "sg:phone":"+49 4920/656990",
    "sg:postcode":"47228",
    "sg:province":"Nordrhein-Westfalen",
    "wof:name":"Elastoform Polsterm\u00d6bel Gmbh & Co Kg",
    "wof:placetype":"venue"
},
  "geometry": {"coordinates":[6.6944999695,51.4195594788],"type":"Point"}
}