{
  "type": "Feature",
  "properties": {
    "iso:country":"DE",
    "sg:address":"Honschaftsstr. 335",
    "sg:city":"K\u00f6ln",
    "sg:phone":"+49 221/637016",
    "sg:postcode":"51061",
    "sg:province":"Nordrhein-Westfalen",
    "wof:name":"Malven-apotheke Inh. Friedel Vierk\u00f6tter",
    "wof:placetype":"venue"
},
  "geometry": {"coordinates":[7.03236,50.980049],"type":"Point"}
}