{
  "type": "Feature",
  "properties": {
    "iso:country":"DE",
    "sg:address":"friedenstr",
    "sg:city":"solingen",
    "sg:postcode":"42699",
    "sg:province":"Nordrhein-Westfalen",
    "wof:name":"Rebi-gmbh Solingen, Ihr Partner In Solingen",
    "wof:placetype":"venue"
},
  "geometry": {"coordinates":[7.02154,51.156891],"type":"Point"}
}