{
  "type": "Feature",
  "properties": {
    "iso:country":"DE",
    "sg:address":"Katzenbachstr. 31",
    "sg:city":"Stuttgart",
    "sg:phone":"+49 711/734400",
    "sg:postcode":"70563",
    "sg:province":"Baden-W\u00fcrttemberg",
    "wof:name":"H. Voll",
    "wof:placetype":"venue"
},
  "geometry": {"coordinates":[9.108936,48.732555],"type":"Point"}
}