{
  "type": "Feature",
  "properties": {
    "iso:country":"DE",
    "sg:address":"Am Alten Sportplatz 1",
    "sg:city":"Neuss",
    "sg:phone":"+49 2131/462781",
    "sg:postcode":"41472",
    "sg:province":"Nordrhein-Westfalen",
    "wof:name":"Biewer Kl\u00e4rgrubenentleerungs-untern.",
    "wof:placetype":"venue"
},
  "geometry": {"coordinates":[6.669148922,51.1649932861],"type":"Point"}
}