{
  "type": "Feature",
  "properties": {
    "iso:country":"DE",
    "sg:address":"Sch\u00f6nst\u00e4dt 21",
    "sg:city":"R\u00f6dental",
    "sg:phone":"+49 9563/8438",
    "sg:postcode":"96472",
    "sg:province":"Bayern",
    "wof:name":"E. M\u00fcller Bildhauer",
    "wof:placetype":"venue"
},
  "geometry": {"coordinates":[11.027888,50.345169],"type":"Point"}
}