{
  "type": "Feature",
  "properties": {
    "iso:country":"DE",
    "sg:address":"Kolumbusstr. 31",
    "sg:city":"Euskirchen",
    "sg:phone":"+49 4307/910",
    "sg:postcode":"53881",
    "sg:province":"Nordrhein-Westfalen",
    "wof:name":"Hays Logistics Gmbh",
    "wof:placetype":"venue"
},
  "geometry": {"coordinates":[6.8277688026,50.6903533936],"type":"Point"}
}