{
  "type": "Feature",
  "properties": {
    "iso:country":"DE",
    "sg:address":"Karrenweg 4",
    "sg:city":"Wadern",
    "sg:phone":"+49 4968/711066",
    "sg:postcode":"66687",
    "sg:province":"Saarland",
    "wof:name":"Sidi-siebdruck Gmbh",
    "wof:placetype":"venue"
},
  "geometry": {"coordinates":[6.8881921768,49.5593757629],"type":"Point"}
}