{
  "type": "Feature",
  "properties": {
    "iso:country":"DE",
    "sg:address":"Hansestr. 69",
    "sg:city":"L\u00fcbeck",
    "sg:phone":"+49 451/84565",
    "sg:postcode":"23558",
    "sg:province":"Schleswig-Holstein",
    "wof:name":"Harry",
    "wof:placetype":"venue"
},
  "geometry": {"coordinates":[10.666176796,53.8629302979],"type":"Point"}
}