{
  "type": "Feature",
  "properties": {
    "iso:country":"DE",
    "sg:address":"Brunecker Str. 112",
    "sg:city":"N\u00fcrnberg",
    "sg:phone":"+49 911/440591",
    "sg:postcode":"90461",
    "sg:province":"Bayern",
    "wof:name":"Georg Schneider Gmbh",
    "wof:placetype":"venue"
},
  "geometry": {"coordinates":[11.0979528427,49.4229927063],"type":"Point"}
}