{
  "type": "Feature",
  "properties": {
    "iso:country":"DE",
    "sg:address":"Werderstr. 1",
    "sg:city":"K\u00f6ln",
    "sg:postcode":"50672",
    "sg:province":"Nordrhein-Westfalen",
    "wof:name":"Media Kultur K\u00f6ln Projektentwicklungs- Und",
    "wof:placetype":"venue"
},
  "geometry": {"coordinates":[6.9380869865,50.9425506592],"type":"Point"}
}