{
  "type": "Feature",
  "properties": {
    "iso:country":"DE",
    "sg:address":"Am Brookhoff 11",
    "sg:city":"Jesteburg",
    "sg:phone":"+49 4183/2241",
    "sg:postcode":"21266",
    "sg:province":"Niedersachsen",
    "wof:name":"Achim Peters",
    "wof:placetype":"venue"
},
  "geometry": {"coordinates":[9.912399,53.289188],"type":"Point"}
}