{
  "type": "Feature",
  "properties": {
    "iso:country":"DE",
    "sg:address":"Bahnstr. 4",
    "sg:city":"Baden-Baden",
    "sg:phone":"+49 7221/68760",
    "sg:postcode":"76532",
    "sg:province":"Baden-W\u00fcrttemberg",
    "wof:name":"H. D. Hertel Ingenieur",
    "wof:placetype":"venue"
},
  "geometry": {"coordinates":[8.2191333771,48.7762565613],"type":"Point"}
}