{
  "type": "Feature",
  "properties": {
    "iso:country":"DE",
    "sg:address":"Handschuhsheimer Landstr. 30",
    "sg:city":"Heidelberg",
    "sg:phone":"+49 6221/480191",
    "sg:postcode":"69120",
    "sg:province":"Baden-W\u00fcrttemberg",
    "wof:name":"Theodor Kr\u00c4mer",
    "wof:placetype":"venue"
},
  "geometry": {"coordinates":[8.689771,49.420433],"type":"Point"}
}