{
  "type": "Feature",
  "properties": {
    "iso:country":"DE",
    "sg:address":"Heegweg 3",
    "sg:city":"Grebenau",
    "sg:phone":"+49 6646/592",
    "sg:postcode":"36323",
    "sg:province":"Hessen",
    "wof:name":"Heinrich Kaiser",
    "wof:placetype":"venue"
},
  "geometry": {"coordinates":[9.4833965302,50.7509040833],"type":"Point"}
}