{
  "type": "Feature",
  "properties": {
    "iso:country":"DE",
    "sg:address":"Feldstr. 57",
    "sg:city":"Detmold",
    "sg:phone":"+49 5231/20959",
    "sg:postcode":"32756",
    "sg:province":"Nordrhein-Westfalen",
    "wof:name":"Ludwig Keeb Kfz Verwertungsuntern.",
    "wof:placetype":"venue"
},
  "geometry": {"coordinates":[8.8848314285,51.9451446533],"type":"Point"}
}