{
  "type": "Feature",
  "properties": {
    "iso:country":"DE",
    "sg:address":"Reichsstr. 33",
    "sg:city":"Chemnitz",
    "sg:phone":"+49 371/302108",
    "sg:postcode":"09112",
    "sg:province":"Sachsen",
    "wof:name":"B. Bode",
    "wof:placetype":"venue"
},
  "geometry": {"coordinates":[12.9077396393,50.8334884644],"type":"Point"}
}