{
  "type": "Feature",
  "properties": {
    "iso:country":"DE",
    "sg:city":"Tettnang",
    "sg:phone":"+49 7542/52110",
    "sg:postcode":"88069",
    "sg:province":"Baden-W\u00fcrttemberg",
    "wof:name":"H. Auerbach Hardwarehandlung",
    "wof:placetype":"venue"
},
  "geometry": {"coordinates":[9.586074,47.670479],"type":"Point"}
}