{
  "type": "Feature",
  "properties": {
    "iso:country":"DE",
    "sg:address":"H.-Koch-Str. 17",
    "sg:city":"Kahla",
    "sg:phone":"+49 36424/52998",
    "sg:postcode":"07768",
    "sg:province":"Th\u00fcringen",
    "wof:name":"Homepage Steuerb\u00fcro M\u00fcller",
    "wof:placetype":"venue"
},
  "geometry": {"coordinates":[11.5822067261,50.8047103882],"type":"Point"}
}