{
  "type": "Feature",
  "properties": {
    "iso:country":"DE",
    "sg:address":"Dorfbachweg 22",
    "sg:city":"Neundorf",
    "sg:phone":"+49 36651/3508",
    "sg:postcode":"07356",
    "sg:province":"Th\u00fcringen",
    "wof:name":"Uwe Weber",
    "wof:placetype":"venue"
},
  "geometry": {"coordinates":[11.6273288727,50.4547615051],"type":"Point"}
}