{
  "type": "Feature",
  "properties": {
    "iso:country":"DE",
    "sg:address":"K\u00f6nigstr. 27",
    "sg:city":"Elmshorn",
    "sg:phone":"+49 4121/24563",
    "sg:postcode":"25335",
    "sg:province":"Schleswig-Holstein",
    "wof:name":"Kamps Nord Gmbh & Co. Kg",
    "wof:placetype":"venue"
},
  "geometry": {"coordinates":[9.655901,53.753639],"type":"Point"}
}