{
  "type": "Feature",
  "properties": {
    "iso:country":"DE",
    "sg:address":"Im K\u00f6lbling 1",
    "sg:city":"B\u00fchl",
    "sg:phone":"+49 7223/8636",
    "sg:postcode":"77815",
    "sg:province":"Baden-W\u00fcrttemberg",
    "wof:name":"Tiger Tv & Fernseh- Produktion Gmbh",
    "wof:placetype":"venue"
},
  "geometry": {"coordinates":[8.159236908,48.7133407593],"type":"Point"}
}