{
  "type": "Feature",
  "properties": {
    "iso:country":"DE",
    "sg:address":"An den Dieken 46",
    "sg:city":"Ratingen",
    "sg:phone":"+49 2102/33606",
    "sg:postcode":"40885",
    "sg:province":"Nordrhein-Westfalen",
    "wof:name":"Dieter Malden",
    "wof:placetype":"venue"
},
  "geometry": {"coordinates":[6.827833,51.348026],"type":"Point"}
}