{
  "type": "Feature",
  "properties": {
    "iso:country":"DE",
    "sg:address":"Genfer Str. 10",
    "sg:city":"Frankfurt",
    "sg:phone":"+49 69/5000000",
    "sg:postcode":"60437",
    "sg:province":"Hessen",
    "wof:name":"Manfred-j\u00fcrgen Raak Digital-druck Gmbh",
    "wof:placetype":"venue"
},
  "geometry": {"coordinates":[8.658815,50.192177],"type":"Point"}
}