{
  "type": "Feature",
  "properties": {
    "iso:country":"DE",
    "sg:address":"Hauptstr. 2",
    "sg:city":"Iffezheim",
    "sg:phone":"+49 7229/2226",
    "sg:postcode":"76473",
    "sg:province":"Baden-W\u00fcrttemberg",
    "wof:name":"Hardt-cafe",
    "wof:placetype":"venue"
},
  "geometry": {"coordinates":[8.148902,48.82032],"type":"Point"}
}