{
  "type": "Feature",
  "properties": {
    "iso:country":"DE",
    "sg:address":"Ponter Weg 15",
    "sg:city":"Newel",
    "sg:phone":"+49 6505/99092",
    "sg:postcode":"54309",
    "sg:province":"Rheinland-Pfalz",
    "wof:name":"Hans-joachim Weber",
    "wof:placetype":"venue"
},
  "geometry": {"coordinates":[6.6197371483,49.8186531067],"type":"Point"}
}