{
  "type": "Feature",
  "properties": {
    "iso:country":"DE",
    "sg:address":"Ottenbergkamp 15",
    "sg:city":"Ahrensb\u00f6k",
    "sg:phone":"+49 4556/257",
    "sg:postcode":"23623",
    "sg:province":"Schleswig-Holstein",
    "wof:name":"M. Marquardt",
    "wof:placetype":"venue"
},
  "geometry": {"coordinates":[10.57302,54.011791],"type":"Point"}
}