{
  "type": "Feature",
  "properties": {
    "iso:country":"DE",
    "sg:address":"Trierer Str. 173 a",
    "sg:city":"Koblenz",
    "sg:phone":"+49 261/2041",
    "sg:postcode":"56072",
    "sg:province":"Rheinland-Pfalz",
    "wof:name":"Versicherungsb\u00fcro Sommer",
    "wof:placetype":"venue"
},
  "geometry": {"coordinates":[7.5613031387,50.3678665161],"type":"Point"}
}