{
  "type": "Feature",
  "properties": {
    "iso:country":"DE",
    "sg:address":"Kanonenweg 12a",
    "sg:city":"Coburg",
    "sg:phone":"+49 9561/66167",
    "sg:postcode":"96450",
    "sg:province":"Bayern",
    "wof:name":"Buchdruckerei Edmund Bl\u00fcmig",
    "wof:placetype":"venue"
},
  "geometry": {"coordinates":[10.96361,50.268394],"type":"Point"}
}