{
  "type": "Feature",
  "properties": {
    "iso:country":"DE",
    "sg:address":"Im Weidenbruch 136",
    "sg:city":"K\u00f6ln",
    "sg:phone":"+49 221/633095",
    "sg:postcode":"51061",
    "sg:province":"Nordrhein-Westfalen",
    "wof:name":"Sch\u00e4tzlein",
    "wof:placetype":"venue"
},
  "geometry": {"coordinates":[7.0352320671,50.9818191528],"type":"Point"}
}