{
  "type": "Feature",
  "properties": {
    "iso:country":"DE",
    "sg:address":"Am Hohentorshafen 1-3",
    "sg:city":"Bremen",
    "sg:phone":"+49 421/54950",
    "sg:postcode":"28197",
    "sg:province":"Bremen",
    "wof:name":"H. Golinski Gmbh",
    "wof:placetype":"venue"
},
  "geometry": {"coordinates":[8.786259,53.07729],"type":"Point"}
}