{
  "type": "Feature",
  "properties": {
    "iso:country":"DE",
    "sg:address":"Wiesenstr. 48",
    "sg:city":"Clausen",
    "sg:postcode":"66978",
    "sg:province":"Rheinland-Pfalz",
    "wof:name":"Polly-schuh Handels Gmbh",
    "wof:placetype":"venue"
},
  "geometry": {"coordinates":[7.6716871262,49.2595863342],"type":"Point"}
}