{
  "type": "Feature",
  "properties": {
    "iso:country":"DE",
    "sg:address":"max-emanuel 10",
    "sg:city":"passau",
    "sg:phone":"+49 4908/51",
    "sg:postcode":"94036",
    "sg:province":"Bayern",
    "wof:name":"Thyracont - Vacuum Instruments, Meters, Gauges,..",
    "wof:placetype":"venue"
},
  "geometry": {"coordinates":[13.407046,48.56699],"type":"Point"}
}