{
  "type": "Feature",
  "properties": {
    "iso:country":"DE",
    "sg:address":"Erfurter Str. 67",
    "sg:city":"Calw",
    "sg:phone":"+49 7051/78011",
    "sg:postcode":"75365",
    "sg:province":"Baden-W\u00fcrttemberg",
    "wof:name":"R. Zeiher",
    "wof:placetype":"venue"
},
  "geometry": {"coordinates":[8.761904,48.715637],"type":"Point"}
}