{
  "type": "Feature",
  "properties": {
    "iso:country":"DE",
    "sg:address":"Gutenbergstr. 4",
    "sg:city":"Friedberg",
    "sg:phone":"+49 6031/14847",
    "sg:postcode":"61169",
    "sg:province":"Hessen",
    "wof:name":"A.m. Zahntechnik Gmbh",
    "wof:placetype":"venue"
},
  "geometry": {"coordinates":[8.7496929169,50.3295555115],"type":"Point"}
}