{
  "type": "Feature",
  "properties": {
    "iso:country":"DE",
    "sg:address":"Wilhelmstr. 13",
    "sg:city":"Duisburg",
    "sg:phone":"+49 203/990891",
    "sg:postcode":"47169",
    "sg:province":"Nordrhein-Westfalen",
    "wof:name":"G\u00fcnter Karbach",
    "wof:placetype":"venue"
},
  "geometry": {"coordinates":[6.757206,51.503956],"type":"Point"}
}