{
  "type": "Feature",
  "properties": {
    "iso:country":"DE",
    "sg:address":"Wilhelmistr. 36",
    "sg:city":"Hamburg",
    "sg:phone":"+49 40/8226618",
    "sg:postcode":"22605",
    "sg:province":"Hamburg",
    "wof:name":"Cano Handel Gmbh",
    "wof:placetype":"venue"
},
  "geometry": {"coordinates":[9.8655700684,53.5578193665],"type":"Point"}
}