{
  "type": "Feature",
  "properties": {
    "iso:country":"DE",
    "sg:address":"Am Wehrhahn 67",
    "sg:city":"D\u00fcsseldorf",
    "sg:phone":"+49 211/363440",
    "sg:postcode":"40211",
    "sg:province":"Nordrhein-Westfalen",
    "wof:name":"Klaus Buntenbroich",
    "wof:placetype":"venue"
},
  "geometry": {"coordinates":[6.7935900688,51.2289123535],"type":"Point"}
}