{
  "type": "Feature",
  "properties": {
    "iso:country":"DE",
    "sg:address":"Hauptstr. 68",
    "sg:city":"Witten",
    "sg:phone":"+49 2302/14944",
    "sg:postcode":"58452",
    "sg:province":"Nordrhein-Westfalen",
    "wof:name":"Abs Auspuff-bremsen- Sto\u00dfd\u00e4mpfer Expre\u00df-",
    "wof:placetype":"venue"
},
  "geometry": {"coordinates":[7.3364548683,51.4437026978],"type":"Point"}
}