{
  "type": "Feature",
  "properties": {
    "iso:country":"DE",
    "sg:address":"Hildburghauser Str. 19b",
    "sg:city":"Berlin",
    "sg:phone":"+49 30/7214248",
    "sg:postcode":"12279",
    "sg:province":"Berlin",
    "wof:name":"Bbj Verlag Vetrieb Rufeida Buschendorf",
    "wof:placetype":"venue"
},
  "geometry": {"coordinates":[13.3559188843,52.4130859375],"type":"Point"}
}