{
  "type": "Feature",
  "properties": {
    "iso:country":"DE",
    "sg:address":"Bokelberger Weg 13",
    "sg:city":"M\u00fcden",
    "sg:phone":"+49 5375/2642",
    "sg:postcode":"38539",
    "sg:province":"Niedersachsen",
    "wof:name":"Garny Gmbh",
    "wof:placetype":"venue"
},
  "geometry": {"coordinates":[10.376454,52.520851],"type":"Point"}
}