{
  "type": "Feature",
  "properties": {
    "iso:country":"DE",
    "sg:address":"Kohlweg 16",
    "sg:city":"Saarbr\u00fccken",
    "sg:phone":"+49 681/390306",
    "sg:postcode":"66123",
    "sg:province":"Saarland",
    "wof:name":"Horst Faber",
    "wof:placetype":"venue"
},
  "geometry": {"coordinates":[7.021829,49.238953],"type":"Point"}
}