{
  "type": "Feature",
  "properties": {
    "iso:country":"DE",
    "sg:address":"Industriestr 10",
    "sg:city":"Hasel\u00fcnne",
    "sg:phone":"+49 5731/20322",
    "sg:postcode":"49740",
    "sg:province":"Niedersachsen",
    "wof:name":"Druckerei Udo Hartenstein",
    "wof:placetype":"venue"
},
  "geometry": {"coordinates":[8.8166599274,52.2106132507],"type":"Point"}
}