{
  "type": "Feature",
  "properties": {
    "iso:country":"DE",
    "sg:address":"Lascheider Weg 19",
    "sg:city":"Eitorf",
    "sg:phone":"+49 2243/2844",
    "sg:postcode":"53783",
    "sg:province":"Nordrhein-Westfalen",
    "wof:name":"Willi Steffens Gmbh",
    "wof:placetype":"venue"
},
  "geometry": {"coordinates":[7.4472870827,50.7599639893],"type":"Point"}
}