{
  "type": "Feature",
  "properties": {
    "iso:country":"DE",
    "sg:address":"Welzheimer Str. 22",
    "sg:city":"Rudersberg",
    "sg:phone":"+49 7183/3345",
    "sg:postcode":"73635",
    "sg:province":"Baden-W\u00fcrttemberg",
    "wof:name":"Viktor Adam Inh. Martin Zehnder",
    "wof:placetype":"venue"
},
  "geometry": {"coordinates":[9.531312,48.886147],"type":"Point"}
}