{
  "type": "Feature",
  "properties": {
    "iso:country":"DE",
    "sg:address":"Heinrichsallee 44",
    "sg:city":"Aachen",
    "sg:phone":"+49 241/4009730",
    "sg:postcode":"52062",
    "sg:province":"Nordrhein-Westfalen",
    "wof:name":"Peter Josef Keimes Rechtsanwalt",
    "wof:placetype":"venue"
},
  "geometry": {"coordinates":[6.0953030586,50.7766265869],"type":"Point"}
}