{
  "type": "Feature",
  "properties": {
    "iso:country":"DE",
    "sg:address":"Peiner Str. 13",
    "sg:city":"Edemissen",
    "sg:phone":"+49 5176/7031",
    "sg:postcode":"31234",
    "sg:province":"Niedersachsen",
    "wof:name":"Raiffeisen-warengenossenschaft",
    "wof:placetype":"venue"
},
  "geometry": {"coordinates":[10.257115,52.381893],"type":"Point"}
}