{
  "type": "Feature",
  "properties": {
    "iso:country":"DE",
    "sg:address":"Amiraplatz 3",
    "sg:city":"M\u00fcnchen",
    "sg:postcode":"80333",
    "sg:province":"Bayern",
    "wof:name":"Textilmanagement Gmbh",
    "wof:placetype":"venue"
},
  "geometry": {"coordinates":[11.575216,48.142662],"type":"Point"}
}