{
  "type": "Feature",
  "properties": {
    "iso:country":"DE",
    "sg:address":"Wilhelmstr. 9",
    "sg:city":"Wyk",
    "sg:phone":"+49 4681/2212",
    "sg:postcode":"25938",
    "sg:province":"Schleswig-Holstein",
    "wof:name":"Fischhaus Lund",
    "wof:placetype":"venue"
},
  "geometry": {"coordinates":[8.5686817169,54.6889648438],"type":"Point"}
}