{
  "type": "Feature",
  "properties": {
    "iso:country":"DE",
    "sg:address":"Beethovenstr. 60",
    "sg:city":"Hamburg",
    "sg:phone":"+49 40/29820400",
    "sg:postcode":"22083",
    "sg:province":"Hamburg",
    "wof:name":"Wirtschafts- Und Verbands Pr Gmbh",
    "wof:placetype":"venue"
},
  "geometry": {"coordinates":[10.0303659439,53.5787162781],"type":"Point"}
}