{
  "type": "Feature",
  "properties": {
    "iso:country":"DE",
    "sg:address":"Haart 181",
    "sg:city":"Neum\u00fcnster",
    "sg:phone":"+49 4321/72035",
    "sg:postcode":"24539",
    "sg:province":"Schleswig-Holstein",
    "wof:name":"Otto Kolan Inh. D. Diebowski",
    "wof:placetype":"venue"
},
  "geometry": {"coordinates":[10.005075,54.062614],"type":"Point"}
}