{
  "type": "Feature",
  "properties": {
    "iso:country":"DE",
    "sg:address":"Varrentrappstr. 2",
    "sg:city":"Braunschweig",
    "sg:phone":"+49 531/581150",
    "sg:postcode":"38114",
    "sg:province":"Niedersachsen",
    "wof:name":"D\u00e4nisches Bettenlager Gmbh & Co. Kg",
    "wof:placetype":"venue"
},
  "geometry": {"coordinates":[10.5063781738,52.2802467346],"type":"Point"}
}