{
  "type": "Feature",
  "properties": {
    "iso:country":"DE",
    "sg:address":"F\u00f6ssestr. 77A",
    "sg:city":"Hannover",
    "sg:phone":"+49 511/92399660",
    "sg:postcode":"30451",
    "sg:province":"Niedersachsen",
    "wof:name":"Holtz Steuerberatungsges. Mbh",
    "wof:placetype":"venue"
},
  "geometry": {"coordinates":[9.704574585,52.3695449829],"type":"Point"}
}