{
  "type": "Feature",
  "properties": {
    "iso:country":"DE",
    "sg:address":"Johannisstr. 5",
    "sg:city":"N\u00fcrnberg",
    "sg:phone":"+49 911/289982",
    "sg:postcode":"90419",
    "sg:province":"Bayern",
    "wof:name":"D. Blum",
    "wof:placetype":"venue"
},
  "geometry": {"coordinates":[11.0697422028,49.4568328857],"type":"Point"}
}