{
  "type": "Feature",
  "properties": {
    "iso:country":"DE",
    "sg:address":"Im Hagen 6",
    "sg:city":"Wipperf\u00fcrth",
    "sg:phone":"+49 2269/442",
    "sg:postcode":"51688",
    "sg:province":"Nordrhein-Westfalen",
    "wof:name":"Fritz Fastenrath",
    "wof:placetype":"venue"
},
  "geometry": {"coordinates":[7.480325,51.117561],"type":"Point"}
}