{
  "type": "Feature",
  "properties": {
    "iso:country":"DE",
    "sg:address":"Industriestr. 26",
    "sg:city":"Wertingen",
    "sg:phone":"+49 8272/4012",
    "sg:postcode":"86637",
    "sg:province":"Bayern",
    "wof:name":"Cbw Chemischer Betrieb Wertingen Gmbh",
    "wof:placetype":"venue"
},
  "geometry": {"coordinates":[10.690529,48.568096],"type":"Point"}
}