{
  "type": "Feature",
  "properties": {
    "iso:country":"DE",
    "sg:address":"Am Scheidweg 19",
    "sg:city":"K\u00f6ln",
    "sg:phone":"+49 221/5902351",
    "sg:postcode":"50765",
    "sg:province":"Nordrhein-Westfalen",
    "wof:name":"Helmut Groll Ingenieur",
    "wof:placetype":"venue"
},
  "geometry": {"coordinates":[6.8586039543,51.0109138489],"type":"Point"}
}