{
  "type": "Feature",
  "properties": {
    "iso:country":"DE",
    "sg:address":"Master Esch 20",
    "sg:city":"Vreden",
    "sg:phone":"+49 2564/1031",
    "sg:postcode":"48691",
    "sg:province":"Nordrhein-Westfalen",
    "wof:name":"F. Bellmann Schaufenstergestaltung",
    "wof:placetype":"venue"
},
  "geometry": {"coordinates":[6.8218989372,52.0283813477],"type":"Point"}
}