{
  "type": "Feature",
  "properties": {
    "iso:country":"DE",
    "sg:address":"Pettenkoferstr. 15a",
    "sg:city":"Bruckm\u00fchl",
    "sg:postcode":"83052",
    "sg:province":"Bayern",
    "wof:name":"Bay Wa Bau- Und Gartenmarkt",
    "wof:placetype":"venue"
},
  "geometry": {"coordinates":[11.9630041122,47.8761711121],"type":"Point"}
}