{
  "type": "Feature",
  "properties": {
    "iso:country":"DE",
    "sg:address":"Sonnenallee 68",
    "sg:city":"Berlin",
    "sg:phone":"+49 30/6231051",
    "sg:postcode":"12045",
    "sg:province":"Berlin",
    "wof:name":"Christoph Radenberg Rechtsanwalt Und Notar",
    "wof:placetype":"venue"
},
  "geometry": {"coordinates":[13.434671402,52.4840698242],"type":"Point"}
}