{
  "type": "Feature",
  "properties": {
    "iso:country":"DE",
    "sg:address":"Ippenwarfer Weg 3",
    "sg:city":"Moormerland",
    "sg:phone":"+49 4924/561",
    "sg:postcode":"26802",
    "sg:province":"Niedersachsen",
    "wof:name":"Eibe Buss",
    "wof:placetype":"venue"
},
  "geometry": {"coordinates":[7.381091,53.349098],"type":"Point"}
}