{
  "type": "Feature",
  "properties": {
    "iso:country":"DE",
    "sg:address":"Grindelberg 5",
    "sg:city":"Hamburg",
    "sg:phone":"+49 40/441190",
    "sg:postcode":"20144",
    "sg:province":"Hamburg",
    "wof:name":"Research International Gmbh",
    "wof:placetype":"venue"
},
  "geometry": {"coordinates":[9.977996,53.572838],"type":"Point"}
}