{
  "type": "Feature",
  "properties": {
    "iso:country":"DE",
    "sg:address":"Freyensteiner Str. 13",
    "sg:city":"Meyenburg",
    "sg:phone":"+49 33968/80657",
    "sg:postcode":"16945",
    "sg:province":"Brandenburg",
    "wof:name":"Gast & Stassen Gmbh",
    "wof:placetype":"venue"
},
  "geometry": {"coordinates":[12.2512054443,53.3138046265],"type":"Point"}
}