{
  "type": "Feature",
  "properties": {
    "iso:country":"DE",
    "sg:address":"H\u00fcgelstr. 70 i",
    "sg:city":"Oberhausen",
    "sg:phone":"+49 208/894861",
    "sg:postcode":"46119",
    "sg:province":"Nordrhein-Westfalen",
    "wof:name":"J. Buchwald",
    "wof:placetype":"venue"
},
  "geometry": {"coordinates":[6.875015,51.529305],"type":"Point"}
}