{
  "type": "Feature",
  "properties": {
    "iso:country":"DE",
    "sg:address":"Hauptstr. 22",
    "sg:city":"Exdorf",
    "sg:phone":"+49 36947/51295",
    "sg:postcode":"98631",
    "sg:province":"Th\u00fcringen",
    "wof:name":"J. Gramann",
    "wof:placetype":"venue"
},
  "geometry": {"coordinates":[10.5432863235,50.4586753845],"type":"Point"}
}