{
  "type": "Feature",
  "properties": {
    "iso:country":"DE",
    "sg:address":"Darmst\u00e4dter Str. 18",
    "sg:city":"Biblis",
    "sg:phone":"+49 4962/453083",
    "sg:postcode":"68647",
    "sg:province":"Hessen",
    "wof:name":"Sparkasse Worms",
    "wof:placetype":"venue"
},
  "geometry": {"coordinates":[8.452621,49.685413],"type":"Point"}
}