{
  "type": "Feature",
  "properties": {
    "iso:country":"DE",
    "sg:address":"Altheimer Str. 15",
    "sg:city":"Frickingen",
    "sg:phone":"+49 7554/8376",
    "sg:postcode":"88699",
    "sg:province":"Baden-W\u00fcrttemberg",
    "wof:name":"W. Bielewicz",
    "wof:placetype":"venue"
},
  "geometry": {"coordinates":[9.270779,47.816673],"type":"Point"}
}