{
  "type": "Feature",
  "properties": {
    "iso:country":"DE",
    "sg:address":"Poststr. 10",
    "sg:city":"Traben-Trarbach",
    "sg:phone":"+49 6541/4441",
    "sg:postcode":"56841",
    "sg:province":"Rheinland-Pfalz",
    "wof:name":"Rudolf M\u00fcller",
    "wof:placetype":"venue"
},
  "geometry": {"coordinates":[7.116934,49.950729],"type":"Point"}
}