{
  "type": "Feature",
  "properties": {
    "iso:country":"DE",
    "sg:address":"Rosenweg 1",
    "sg:city":"Eslohe",
    "sg:phone":"+49 2973/81427",
    "sg:postcode":"59889",
    "sg:province":"Nordrhein-Westfalen",
    "wof:name":"R. Plugge",
    "wof:placetype":"venue"
},
  "geometry": {"coordinates":[8.2365245819,51.2623672485],"type":"Point"}
}