{
  "type": "Feature",
  "properties": {
    "iso:country":"DE",
    "sg:address":"Eberleplatz 4",
    "sg:city":"Osnabr\u00fcck",
    "sg:phone":"+49 541/609180",
    "sg:postcode":"49090",
    "sg:province":"Niedersachsen",
    "wof:name":"Hasterberg-apotheke",
    "wof:placetype":"venue"
},
  "geometry": {"coordinates":[8.048721,52.306473],"type":"Point"}
}