{
  "type": "Feature",
  "properties": {
    "iso:country":"DE",
    "sg:address":"Wentorfer Str. 81",
    "sg:city":"Hamburg",
    "sg:phone":"+49 40/7217233",
    "sg:postcode":"21029",
    "sg:province":"Hamburg",
    "wof:name":"Erich V. D. Heide Ingenieur",
    "wof:placetype":"venue"
},
  "geometry": {"coordinates":[10.2269706726,53.4881477356],"type":"Point"}
}