{
  "type": "Feature",
  "properties": {
    "iso:country":"DE",
    "sg:address":"Westernstr. 26",
    "sg:city":"Paderborn",
    "sg:postcode":"33098",
    "sg:province":"Nordrhein-Westfalen",
    "wof:name":"Kaufhof",
    "wof:placetype":"venue"
},
  "geometry": {"coordinates":[8.749061,51.716442],"type":"Point"}
}