{
  "type": "Feature",
  "properties": {
    "iso:country":"DE",
    "sg:address":"Tupsheide 9",
    "sg:city":"Willich",
    "sg:phone":"+49 2154/6580",
    "sg:postcode":"47877",
    "sg:province":"Nordrhein-Westfalen",
    "wof:name":"Malerfachbetrieb J\u00fcrgen Meyer Gmbh",
    "wof:placetype":"venue"
},
  "geometry": {"coordinates":[6.539956,51.242851],"type":"Point"}
}