{
  "type": "Feature",
  "properties": {
    "iso:country":"DE",
    "sg:address":"M\u00f6llner Landstr. 78",
    "sg:city":"Glinde",
    "sg:phone":"+49 40/7110062",
    "sg:postcode":"21509",
    "sg:province":"Schleswig-Holstein",
    "wof:name":"Garlof Und Meyer-bellmann Rechtsanw\u00e4lte Und Notare",
    "wof:placetype":"venue"
},
  "geometry": {"coordinates":[10.2140235901,53.5425415039],"type":"Point"}
}