{
  "type": "Feature",
  "properties": {
    "iso:country":"DE",
    "sg:address":"Kantstr. 18",
    "sg:city":"Neuhofen",
    "sg:phone":"+49 6236/415000",
    "sg:postcode":"67141",
    "sg:province":"Rheinland-Pfalz",
    "wof:name":"Wilhelm M\u00fcller",
    "wof:placetype":"venue"
},
  "geometry": {"coordinates":[8.4308595657,49.4172439575],"type":"Point"}
}