{
  "type": "Feature",
  "properties": {
    "iso:country":"DE",
    "sg:address":"Hauptstr. 22",
    "sg:city":"Forchtenberg",
    "sg:phone":"+49 7947/2206",
    "sg:postcode":"74670",
    "sg:province":"Baden-W\u00fcrttemberg",
    "wof:name":"Woldemar Makowe",
    "wof:placetype":"venue"
},
  "geometry": {"coordinates":[9.562502861,49.2891426086],"type":"Point"}
}