{
  "type": "Feature",
  "properties": {
    "iso:country":"DE",
    "sg:address":"Schlebuscher Str. 8",
    "sg:city":"D\u00fcsseldorf",
    "sg:postcode":"40591",
    "sg:province":"Nordrhein-Westfalen",
    "wof:name":"Sebastian Wagner",
    "wof:placetype":"venue"
},
  "geometry": {"coordinates":[6.8249149323,51.1893806458],"type":"Point"}
}