{
  "type": "Feature",
  "properties": {
    "iso:country":"DE",
    "sg:address":"Hallesche Str. 119",
    "sg:city":"Lutherstadt Eisleben",
    "sg:phone":"+49 3475/75120",
    "sg:postcode":"06295",
    "sg:province":"Sachsen-Anhalt",
    "wof:name":"Teleshop Rainer Gerlach",
    "wof:placetype":"venue"
},
  "geometry": {"coordinates":[11.563123703,51.5178718567],"type":"Point"}
}