{
  "type": "Feature",
  "properties": {
    "iso:country":"DE",
    "sg:address":"Kapellendorfer Str. 71",
    "sg:city":"Apolda",
    "sg:phone":"+49 36465/40331",
    "sg:postcode":"99510",
    "sg:province":"Th\u00fcringen",
    "wof:name":"Gastst\u00e4tte Zur Schmiede",
    "wof:placetype":"venue"
},
  "geometry": {"coordinates":[11.4813518524,50.9974822998],"type":"Point"}
}