{
  "type": "Feature",
  "properties": {
    "iso:country":"DE",
    "sg:address":"Hof\u00e4cker 17",
    "sg:city":"Keltern",
    "sg:phone":"+49 7236/8970",
    "sg:postcode":"75210",
    "sg:province":"Baden-W\u00fcrttemberg",
    "wof:name":"Moritz Beuchle Architekt",
    "wof:placetype":"venue"
},
  "geometry": {"coordinates":[8.601315,48.898518],"type":"Point"}
}