{
  "type": "Feature",
  "properties": {
    "iso:country":"DE",
    "sg:address":"Allg\u00e4uer Str. 14",
    "sg:city":"Bad Gr\u00f6nenbach",
    "sg:phone":"+49 8334/7448",
    "sg:postcode":"87730",
    "sg:province":"Bayern",
    "wof:name":"Kath. Pfarramt St. Peter Und Paul",
    "wof:placetype":"venue"
},
  "geometry": {"coordinates":[10.206580162,47.8990211487],"type":"Point"}
}