{
  "type": "Feature",
  "properties": {
    "iso:country":"DE",
    "sg:address":"Poststr. 47",
    "sg:city":"J\u00fcchen",
    "sg:phone":"+49 2164/2215",
    "sg:postcode":"41363",
    "sg:province":"Nordrhein-Westfalen",
    "wof:name":"J. Sch\u00fcller",
    "wof:placetype":"venue"
},
  "geometry": {"coordinates":[6.462035,51.103996],"type":"Point"}
}