{
  "type": "Feature",
  "properties": {
    "iso:country":"DE",
    "sg:address":"Kortental 8",
    "sg:city":"Dortmund",
    "sg:phone":"+49 231/171007",
    "sg:postcode":"44149",
    "sg:province":"Nordrhein-Westfalen",
    "wof:name":"K.h. Hacheneuer Elektromeister",
    "wof:placetype":"venue"
},
  "geometry": {"coordinates":[7.421072,51.507938],"type":"Point"}
}