{
  "type": "Feature",
  "properties": {
    "iso:country":"DE",
    "sg:address":"Oskar-von-Miller-Str. 3",
    "sg:city":"Mammendorf",
    "sg:phone":"+49 8145/997340",
    "sg:postcode":"82291",
    "sg:province":"Bayern",
    "wof:name":"Sesam Elektronische Sicherheitssysteme Gmbh",
    "wof:placetype":"venue"
},
  "geometry": {"coordinates":[11.17571,48.211529],"type":"Point"}
}