{
  "type": "Feature",
  "properties": {
    "iso:country":"DE",
    "sg:address":"Falkstr. 26",
    "sg:city":"Berlin",
    "sg:phone":"+49 30/6238343",
    "sg:postcode":"12053",
    "sg:province":"Berlin",
    "wof:name":"Griechen Beratungsstelle To Spiti",
    "wof:placetype":"venue"
},
  "geometry": {"coordinates":[13.429392,52.477028],"type":"Point"}
}