{
  "type": "Feature",
  "properties": {
    "iso:country":"DE",
    "sg:address":"windm\u00fchlenstrasse 35",
    "sg:city":"gr\u00f6ditz",
    "sg:phone":"+49 35263/67642",
    "sg:postcode":"01609",
    "sg:province":"Sachsen",
    "wof:name":"Rechtsschutzversicherung - Vers.makler Labes",
    "wof:placetype":"venue"
},
  "geometry": {"coordinates":[13.447404,51.417988],"type":"Point"}
}