{
  "type": "Feature",
  "properties": {
    "iso:country":"DE",
    "sg:address":"Rembrandtstr. 2a",
    "sg:city":"Taunusstein",
    "sg:postcode":"65232",
    "sg:province":"Hessen",
    "wof:name":"Sexmarkt - Liebe, Lust Und Laster",
    "wof:placetype":"venue"
},
  "geometry": {"coordinates":[8.167681,50.143696],"type":"Point"}
}