{
  "type": "Feature",
  "properties": {
    "iso:country":"DE",
    "sg:address":"M\u00fchlenstr. 78",
    "sg:city":"Bad Neuenahr-Ahrweiler",
    "sg:phone":"+49 2641/201640",
    "sg:postcode":"53474",
    "sg:province":"Rheinland-Pfalz",
    "wof:name":"Imbi\u00df Heimersheim",
    "wof:placetype":"venue"
},
  "geometry": {"coordinates":[7.1861901283,50.5444717407],"type":"Point"}
}