{
  "type": "Feature",
  "properties": {
    "iso:country":"DE",
    "sg:address":"Sandfeldstr. 3 a",
    "sg:city":"Loitz",
    "sg:postcode":"17121",
    "sg:province":"Mecklenburg-Vorpommern",
    "wof:name":"Kombi-verm\u00f6gens- Verwaltungsgesellschaft Mbh",
    "wof:placetype":"venue"
},
  "geometry": {"coordinates":[13.1456232071,53.9767417908],"type":"Point"}
}