{
  "type": "Feature",
  "properties": {
    "iso:country":"DE",
    "sg:address":"Gr\u00fcner Weg 5",
    "sg:city":"Gro\u00df Glienicke",
    "sg:phone":"+49 33201/21024",
    "sg:postcode":"14476",
    "sg:province":"Brandenburg",
    "wof:name":"Hans-j\u00fcrgen Weyd Anlageberater",
    "wof:placetype":"venue"
},
  "geometry": {"coordinates":[13.1046447754,52.4734191895],"type":"Point"}
}