{
  "type": "Feature",
  "properties": {
    "iso:country":"DE",
    "sg:address":"Nordpromenade 17",
    "sg:city":"Schafst\u00e4dt",
    "sg:phone":"+49 34636/69176",
    "sg:postcode":"06255",
    "sg:province":"Sachsen-Anhalt",
    "wof:name":"Monika Zurek",
    "wof:placetype":"venue"
},
  "geometry": {"coordinates":[11.7823810577,51.3870277405],"type":"Point"}
}