{
  "type": "Feature",
  "properties": {
    "iso:country":"DE",
    "sg:address":"Cuxhavener Str. 102",
    "sg:city":"Cuxhaven",
    "sg:phone":"+49 4721/48265",
    "sg:postcode":"27476",
    "sg:province":"Niedersachsen",
    "wof:name":"Peter Christiansen Gastronomiefisch",
    "wof:placetype":"venue"
},
  "geometry": {"coordinates":[8.6422138214,53.8852462769],"type":"Point"}
}