{
  "type": "Feature",
  "properties": {
    "iso:country":"DE",
    "sg:address":"Suarezstra\u00dfe 20",
    "sg:city":"Berlin",
    "sg:phone":"+49 30/32677077",
    "sg:postcode":"14057",
    "sg:province":"Berlin",
    "wof:name":"Domainquelle",
    "wof:placetype":"venue"
},
  "geometry": {"coordinates":[13.2943630219,52.5062561035],"type":"Point"}
}