{
  "type": "Feature",
  "properties": {
    "iso:country":"DE",
    "sg:address":"Zieglershohle 15",
    "sg:city":"Gro\u00dfostheim",
    "sg:phone":"+49 6026/1473",
    "sg:postcode":"63762",
    "sg:province":"Bayern",
    "wof:name":"Thomas Loffel Zimmerei - Holzbau Gmbh",
    "wof:placetype":"venue"
},
  "geometry": {"coordinates":[9.0807304382,49.9157600403],"type":"Point"}
}