{
  "type": "Feature",
  "properties": {
    "iso:country":"DE",
    "sg:address":"Hessenweg 4",
    "sg:city":"Untermeitingen",
    "sg:phone":"+49 8232/72198",
    "sg:postcode":"86836",
    "sg:province":"Bayern",
    "wof:name":"Mende-bau Und Putz- Gmbh",
    "wof:placetype":"venue"
},
  "geometry": {"coordinates":[10.8169221878,48.1710281372],"type":"Point"}
}