{
  "type": "Feature",
  "properties": {
    "iso:country":"DE",
    "sg:address":"Am Kalkofen 6",
    "sg:city":"W\u00f6llstadt",
    "sg:phone":"+49 6034/2015",
    "sg:postcode":"61206",
    "sg:province":"Hessen",
    "wof:name":"Geiling-wideco Gmbh",
    "wof:placetype":"venue"
},
  "geometry": {"coordinates":[8.765131,50.280781],"type":"Point"}
}