{
  "type": "Feature",
  "properties": {
    "iso:country":"DE",
    "sg:address":"Torgasse 2",
    "sg:city":"Bogen",
    "sg:phone":"+49 9422/1458",
    "sg:postcode":"94327",
    "sg:province":"Bayern",
    "wof:name":"K. Stifter",
    "wof:placetype":"venue"
},
  "geometry": {"coordinates":[12.692563,48.905254],"type":"Point"}
}