{
  "type": "Feature",
  "properties": {
    "iso:country":"DE",
    "sg:address":"Kieler Strasse 21",
    "sg:city":"Rendsburg",
    "sg:phone":"+49 4331/24041",
    "sg:postcode":"24768",
    "sg:province":"Schleswig-Holstein",
    "wof:name":"Media-profiles",
    "wof:placetype":"venue"
},
  "geometry": {"coordinates":[9.672379,54.304523],"type":"Point"}
}