{
  "type": "Feature",
  "properties": {
    "iso:country":"DE",
    "sg:address":"Klosterstr. 9",
    "sg:city":"Rinteln",
    "sg:phone":"+49 5751/42131",
    "sg:postcode":"31737",
    "sg:province":"Niedersachsen",
    "wof:name":"Gerhard Henke",
    "wof:placetype":"venue"
},
  "geometry": {"coordinates":[9.0795154572,52.1864929199],"type":"Point"}
}