{
  "type": "Feature",
  "properties": {
    "iso:country":"DE",
    "sg:address":"Buchenstr. 5",
    "sg:city":"Untershausen",
    "sg:phone":"+49 2602/2545",
    "sg:postcode":"56412",
    "sg:province":"Rheinland-Pfalz",
    "wof:name":"Werner Parbel",
    "wof:placetype":"venue"
},
  "geometry": {"coordinates":[7.8426241875,50.4003982544],"type":"Point"}
}