{
  "type": "Feature",
  "properties": {
    "iso:country":"DE",
    "sg:address":"Eisenberger Str. 28",
    "sg:city":"Gera",
    "sg:phone":"+49 365/4229205",
    "sg:postcode":"07552",
    "sg:province":"Th\u00fcringen",
    "wof:name":"Siegfried Kn\u00f6fler",
    "wof:placetype":"venue"
},
  "geometry": {"coordinates":[12.049779892,50.9218406677],"type":"Point"}
}