{
  "type": "Feature",
  "properties": {
    "iso:country":"DE",
    "sg:address":"Baaderstr. 44",
    "sg:city":"Muenchen",
    "sg:postcode":"80469",
    "sg:province":"Bayern",
    "wof:name":"Inspirithat Creative Services",
    "wof:placetype":"venue"
},
  "geometry": {"coordinates":[11.578278,48.130669],"type":"Point"}
}