{
  "type": "Feature",
  "properties": {
    "iso:country":"DE",
    "sg:address":"Jahnstr. 108",
    "sg:city":"M\u00fclheim-K\u00e4rlich",
    "sg:phone":"+49 2630/1675",
    "sg:postcode":"56218",
    "sg:province":"Rheinland-Pfalz",
    "wof:name":"Karl Moskopp",
    "wof:placetype":"venue"
},
  "geometry": {"coordinates":[7.512715,50.388321],"type":"Point"}
}