{
  "type": "Feature",
  "properties": {
    "iso:country":"DE",
    "sg:address":"Gerzen",
    "sg:city":"Gerzen",
    "sg:phone":"+49 8744/414",
    "sg:postcode":"84175",
    "sg:province":"Bayern",
    "wof:name":"Raiffeisenbank Gerzen-aham Eg",
    "wof:placetype":"venue"
},
  "geometry": {"coordinates":[12.426997,48.506378],"type":"Point"}
}