{
  "type": "Feature",
  "properties": {
    "iso:country":"DE",
    "sg:address":"Stettiner Str 6-8",
    "sg:city":"Northeim",
    "sg:phone":"+49 5551/7010",
    "sg:postcode":"37154",
    "sg:province":"Niedersachsen",
    "wof:name":"Wilvorst Herrenmoden Gmbh",
    "wof:placetype":"venue"
},
  "geometry": {"coordinates":[9.990829,51.697922],"type":"Point"}
}