{
  "type": "Feature",
  "properties": {
    "iso:country":"DE",
    "sg:address":"Brucher Str. 17",
    "sg:city":"Bad Oeynhausen",
    "sg:phone":"+49 5731/790333",
    "sg:postcode":"32545",
    "sg:province":"Nordrhein-Westfalen",
    "wof:name":"Patienten-heimversorgung Dialysezentrum",
    "wof:placetype":"venue"
},
  "geometry": {"coordinates":[8.80633,52.191742],"type":"Point"}
}