{
  "type": "Feature",
  "properties": {
    "iso:country":"DE",
    "sg:address":"M\u00fchlendamm 84",
    "sg:city":"Hamburg",
    "sg:postcode":"22087",
    "sg:province":"Hamburg",
    "wof:name":"Telekom Gmbh Telekommunikations-",
    "wof:placetype":"venue"
},
  "geometry": {"coordinates":[10.0248737335,53.5635986328],"type":"Point"}
}