{
  "type": "Feature",
  "properties": {
    "iso:country":"DE",
    "sg:address":"Otto-Fleck-Schneise 10 a",
    "sg:city":"Frankfurt",
    "sg:phone":"+49 69/672812",
    "sg:postcode":"60528",
    "sg:province":"Hessen",
    "wof:name":"Deutscher Turner-bund Service Gmbh",
    "wof:placetype":"venue"
},
  "geometry": {"coordinates":[8.6426973343,50.0676422119],"type":"Point"}
}