{
  "type": "Feature",
  "properties": {
    "iso:country":"DE",
    "sg:address":"Hauptstr. 248",
    "sg:city":"Wiesmoor",
    "sg:phone":"+49 4944/3010",
    "sg:postcode":"26639",
    "sg:province":"Niedersachsen",
    "wof:name":"Bohlen & Doyen Verm\u00f6gens Gmbh",
    "wof:placetype":"venue"
},
  "geometry": {"coordinates":[7.7232789993,53.4068717957],"type":"Point"}
}