{
  "type": "Feature",
  "properties": {
    "iso:country":"DE",
    "sg:address":"R\u00fcttenscheider Str. 201",
    "sg:city":"Essen",
    "sg:phone":"+49 201/422326",
    "sg:postcode":"45131",
    "sg:province":"Nordrhein-Westfalen",
    "wof:name":"R\u00fcttenscheider",
    "wof:placetype":"venue"
},
  "geometry": {"coordinates":[7.0035028458,51.4296455383],"type":"Point"}
}