{
  "type": "Feature",
  "properties": {
    "iso:country":"DE",
    "sg:address":"Nadelkamp 8",
    "sg:city":"Vechta",
    "sg:phone":"+49 4441/81985",
    "sg:postcode":"49377",
    "sg:province":"Niedersachsen",
    "wof:name":"M. B\u00f6ske",
    "wof:placetype":"venue"
},
  "geometry": {"coordinates":[8.298206,52.705887],"type":"Point"}
}