{
  "type": "Feature",
  "properties": {
    "iso:country":"DE",
    "sg:address":"Buchholzweg 8",
    "sg:city":"Berlin",
    "sg:phone":"+49 30/4484734",
    "sg:postcode":"13627",
    "sg:province":"Berlin",
    "wof:name":"Datos Gesellschaft F\u00fcr Datenverarbeitung Organisation",
    "wof:placetype":"venue"
},
  "geometry": {"coordinates":[13.3179092407,52.5453262329],"type":"Point"}
}