{
  "type": "Feature",
  "properties": {
    "iso:country":"DE",
    "sg:address":"Dasbecker Weg 42",
    "sg:city":"Hamm",
    "sg:phone":"+49 2381/302230",
    "sg:postcode":"59073",
    "sg:province":"Nordrhein-Westfalen",
    "wof:name":"Sachsen-apotheke",
    "wof:placetype":"venue"
},
  "geometry": {"coordinates":[7.825616,51.709404],"type":"Point"}
}