{
  "type": "Feature",
  "properties": {
    "iso:country":"DE",
    "sg:address":"Stra\u00dfe der Jugend 4",
    "sg:city":"Kurort Oybin",
    "sg:phone":"+49 35844/7120",
    "sg:postcode":"02797",
    "sg:province":"Sachsen",
    "wof:name":"Hotel Zur Alten Rodelbahn",
    "wof:placetype":"venue"
},
  "geometry": {"coordinates":[14.7358531952,50.8398971558],"type":"Point"}
}