{
  "type": "Feature",
  "properties": {
    "iso:country":"DE",
    "sg:address":"Zur Heide 3",
    "sg:city":"Esche",
    "sg:phone":"+49 5941/1419",
    "sg:postcode":"49828",
    "sg:province":"Niedersachsen",
    "wof:name":"Jan Gr. Br\u00fcna",
    "wof:placetype":"venue"
},
  "geometry": {"coordinates":[6.969413,52.532082],"type":"Point"}
}