{
  "type": "Feature",
  "properties": {
    "iso:country":"DE",
    "sg:address":"Hedelfinger Str. 61",
    "sg:city":"Stuttgart",
    "sg:postcode":"70327",
    "sg:province":"Baden-W\u00fcrttemberg",
    "wof:name":"Sony Precision Technology Europe Gmbh",
    "wof:placetype":"venue"
},
  "geometry": {"coordinates":[9.2490129471,48.7673416138],"type":"Point"}
}