{
  "type": "Feature",
  "properties": {
    "iso:country":"DE",
    "sg:address":"M\u00e4rzenbecherstr. 16",
    "sg:city":"Ingolstadt",
    "sg:phone":"+49 841/967550",
    "sg:postcode":"85053",
    "sg:province":"Bayern",
    "wof:name":"Werner Ro\u00dfkamp Finanzberater",
    "wof:placetype":"venue"
},
  "geometry": {"coordinates":[11.4491100311,48.737121582],"type":"Point"}
}