{
  "type": "Feature",
  "properties": {
    "iso:country":"DE",
    "sg:address":"Bachstr. 1a",
    "sg:city":"Dreieich",
    "sg:phone":"+49 6103/63519",
    "sg:postcode":"63303",
    "sg:province":"Hessen",
    "wof:name":"Gerd Bastuck Ingenieur",
    "wof:placetype":"venue"
},
  "geometry": {"coordinates":[8.6932172775,50.0168304443],"type":"Point"}
}