{
  "type": "Feature",
  "properties": {
    "iso:country":"DE",
    "sg:address":"Schwetzinger Str. 4",
    "sg:city":"Wiesloch",
    "sg:phone":"+49 6222/2371",
    "sg:postcode":"69168",
    "sg:province":"Baden-W\u00fcrttemberg",
    "wof:name":"J\u00fcrgen Lechner",
    "wof:placetype":"venue"
},
  "geometry": {"coordinates":[8.6967954636,49.2931632996],"type":"Point"}
}