{
  "type": "Feature",
  "properties": {
    "iso:country":"DE",
    "sg:address":"B\u00fctzmattweg 39",
    "sg:city":"Inzlingen",
    "sg:phone":"+49 7621/3888",
    "sg:postcode":"79594",
    "sg:province":"Baden-W\u00fcrttemberg",
    "wof:name":"Altmann Gmbh Invest-management Mbh",
    "wof:placetype":"venue"
},
  "geometry": {"coordinates":[7.6856417656,47.5914497375],"type":"Point"}
}