{
  "type": "Feature",
  "properties": {
    "iso:country":"DE",
    "sg:address":"Betenstr. 1",
    "sg:city":"Dortmund",
    "sg:phone":"+49 231/527548",
    "sg:postcode":"44137",
    "sg:province":"Nordrhein-Westfalen",
    "wof:name":"Wenkers Brauhaus Bierspezialit\u00e4ten Gmbh",
    "wof:placetype":"venue"
},
  "geometry": {"coordinates":[7.46706,51.512909],"type":"Point"}
}