{
  "type": "Feature",
  "properties": {
    "iso:country":"DE",
    "sg:address":"Milchweg",
    "sg:city":"Leer",
    "sg:phone":"+49 491/3464",
    "sg:postcode":"26789",
    "sg:province":"Niedersachsen",
    "wof:name":"Hero Doeden",
    "wof:placetype":"venue"
},
  "geometry": {"coordinates":[7.444304,53.246632],"type":"Point"}
}