{
  "type": "Feature",
  "properties": {
    "iso:country":"DE",
    "sg:address":"Eberle-K\u00f6gl-Str. 2",
    "sg:city":"Marktoberdorf",
    "sg:phone":"+49 8342/2359",
    "sg:postcode":"87616",
    "sg:province":"Bayern",
    "wof:name":"Michael Rauh",
    "wof:placetype":"venue"
},
  "geometry": {"coordinates":[10.618309021,47.7792701721],"type":"Point"}
}