{
  "type": "Feature",
  "properties": {
    "iso:country":"DE",
    "sg:address":"Johannesstr. 6",
    "sg:city":"Ulm",
    "sg:phone":"+49 731/382083",
    "sg:postcode":"89081",
    "sg:province":"Baden-W\u00fcrttemberg",
    "wof:name":"Pauw & Co. Inh. Anna Pauw",
    "wof:placetype":"venue"
},
  "geometry": {"coordinates":[9.9477243423,48.4007873535],"type":"Point"}
}