{
  "type": "Feature",
  "properties": {
    "iso:country":"DE",
    "sg:address":"Bramfelder Chaussee 336",
    "sg:city":"Hamburg",
    "sg:postcode":"22175",
    "sg:province":"Hamburg",
    "wof:name":"Das Biol\u00e4dchen Natur Und Biofeinkost Gmbh",
    "wof:placetype":"venue"
},
  "geometry": {"coordinates":[10.0812339783,53.6195640564],"type":"Point"}
}