{
  "type": "Feature",
  "properties": {
    "iso:country":"DE",
    "sg:address":"Buchholzer Str. 65",
    "sg:city":"Annaberg-Buchholz",
    "sg:phone":"+49 3733/23049",
    "sg:postcode":"09456",
    "sg:province":"Sachsen",
    "wof:name":"Hamburg-mannheimer Versicherungs-ag",
    "wof:placetype":"venue"
},
  "geometry": {"coordinates":[13.0031013489,50.5748710632],"type":"Point"}
}