{
  "type": "Feature",
  "properties": {
    "iso:country":"DE",
    "sg:address":"Zinkenwehr 28",
    "sg:city":"Coburg",
    "sg:phone":"+49 9561/90595",
    "sg:postcode":"96450",
    "sg:province":"Bayern",
    "wof:name":"Adam Schleicher",
    "wof:placetype":"venue"
},
  "geometry": {"coordinates":[10.960609436,50.2568664551],"type":"Point"}
}