{
  "type": "Feature",
  "properties": {
    "iso:country":"DE",
    "sg:address":"Stresemannstr. 250",
    "sg:city":"Hamburg",
    "sg:phone":"+49 40/8539990",
    "sg:postcode":"22769",
    "sg:province":"Hamburg",
    "wof:name":"H. P. Friedrich Prien Verwaltungs- Und",
    "wof:placetype":"venue"
},
  "geometry": {"coordinates":[9.9395122528,53.5634918213],"type":"Point"}
}