{
  "type": "Feature",
  "properties": {
    "iso:country":"DE",
    "sg:address":"St.-Georg-Str. 6",
    "sg:city":"Aichen",
    "sg:phone":"+49 8284/274",
    "sg:postcode":"86479",
    "sg:province":"Bayern",
    "wof:name":"Kath. Pfarramt St. Ulrich",
    "wof:placetype":"venue"
},
  "geometry": {"coordinates":[10.5298175812,48.2475242615],"type":"Point"}
}