{
  "type": "Feature",
  "properties": {
    "iso:country":"DE",
    "sg:address":"Wessenbergstr. 25",
    "sg:city":"Konstanz",
    "sg:phone":"+49 7531/16112",
    "sg:postcode":"78462",
    "sg:province":"Baden-W\u00fcrttemberg",
    "wof:name":"Marc O Polo Depot",
    "wof:placetype":"venue"
},
  "geometry": {"coordinates":[9.174428,47.661846],"type":"Point"}
}