{
  "type": "Feature",
  "properties": {
    "iso:country":"DE",
    "sg:address":"Nymphenburger Str. 154",
    "sg:city":"M\u00fcnchen",
    "sg:phone":"+49 89/165004",
    "sg:postcode":"80634",
    "sg:province":"Bayern",
    "wof:name":"Spitzer Handels Gmbh & Co. Kg",
    "wof:placetype":"venue"
},
  "geometry": {"coordinates":[11.5354499817,48.1522979736],"type":"Point"}
}