{
  "type": "Feature",
  "properties": {
    "iso:country":"DE",
    "sg:address":"Flecken 23",
    "sg:city":"Deiningen",
    "sg:phone":"+49 9081/9259",
    "sg:postcode":"86738",
    "sg:province":"Bayern",
    "wof:name":"Elektro Gruber Gmbh",
    "wof:placetype":"venue"
},
  "geometry": {"coordinates":[10.5715961456,48.8593940735],"type":"Point"}
}