{
  "type": "Feature",
  "properties": {
    "iso:country":"DE",
    "sg:address":"Kirchgasse 3",
    "sg:city":"Obrigheim",
    "sg:phone":"+49 6261/2423",
    "sg:postcode":"74847",
    "sg:province":"Baden-W\u00fcrttemberg",
    "wof:name":"Kath. Pfarramt Gem. Obrigheim",
    "wof:placetype":"venue"
},
  "geometry": {"coordinates":[9.0926389694,49.3524017334],"type":"Point"}
}