{
  "type": "Feature",
  "properties": {
    "iso:country":"DE",
    "sg:address":"Herrenberger Str. 11",
    "sg:city":"Rottenburg",
    "sg:phone":"+49 7073/7434",
    "sg:postcode":"72108",
    "sg:province":"Baden-W\u00fcrttemberg",
    "wof:name":"Ludwig Hartmann",
    "wof:placetype":"venue"
},
  "geometry": {"coordinates":[8.923605,48.5243],"type":"Point"}
}