{
  "type": "Feature",
  "properties": {
    "iso:country":"DE",
    "sg:address":"Gaisberg 27",
    "sg:city":"Beilngries",
    "sg:phone":"+49 8461/1060",
    "sg:postcode":"92339",
    "sg:province":"Bayern",
    "wof:name":"Franz Hausn Bau Gmbh",
    "wof:placetype":"venue"
},
  "geometry": {"coordinates":[11.45586,49.033821],"type":"Point"}
}