{
  "type": "Feature",
  "properties": {
    "iso:country":"DE",
    "sg:address":"Langeler Weg 46",
    "sg:city":"K\u00f6ln",
    "sg:postcode":"50769",
    "sg:province":"Nordrhein-Westfalen",
    "wof:name":"Progastro Handelsges. Mbh",
    "wof:placetype":"venue"
},
  "geometry": {"coordinates":[6.874318,51.061928],"type":"Point"}
}