{
  "type": "Feature",
  "properties": {
    "iso:country":"DE",
    "sg:address":"Eichenstr. 27 c",
    "sg:city":"Berlin",
    "sg:phone":"+49 30/4772161",
    "sg:postcode":"13156",
    "sg:province":"Berlin",
    "wof:name":"Wolfgang Kolm",
    "wof:placetype":"venue"
},
  "geometry": {"coordinates":[13.392589,52.585636],"type":"Point"}
}