{
  "type": "Feature",
  "properties": {
    "iso:country":"DE",
    "sg:address":"Stuttgarter Str. 27",
    "sg:city":"Vaihingen",
    "sg:phone":"+49 7042/17016",
    "sg:postcode":"71665",
    "sg:province":"Baden-W\u00fcrttemberg",
    "wof:name":"Louis Junior",
    "wof:placetype":"venue"
},
  "geometry": {"coordinates":[8.9590520859,48.9310188293],"type":"Point"}
}