{
  "type": "Feature",
  "properties": {
    "iso:country":"DE",
    "sg:address":"Bruchk\u00f6beler Landstr. 71c",
    "sg:city":"Hanau",
    "sg:phone":"+49 6181/990300",
    "sg:postcode":"63452",
    "sg:province":"Hessen",
    "wof:name":"Mb Inkasso- Und Ermittlungs- Gmbh",
    "wof:placetype":"venue"
},
  "geometry": {"coordinates":[8.908639,50.146786],"type":"Point"}
}