{
  "type": "Feature",
  "properties": {
    "iso:country":"DE",
    "sg:address":"Robert-Blum-Str. 58",
    "sg:city":"Leverkusen",
    "sg:phone":"+49 214/68080",
    "sg:postcode":"51373",
    "sg:province":"Nordrhein-Westfalen",
    "wof:name":"Werner Decker",
    "wof:placetype":"venue"
},
  "geometry": {"coordinates":[7.0064558983,51.0518379211],"type":"Point"}
}