{
  "type": "Feature",
  "properties": {
    "iso:country":"DE",
    "sg:address":"Clara-Zetkin-Str. 20",
    "sg:city":"Ludwigsfelde",
    "sg:phone":"+49 3378/804750",
    "sg:postcode":"14974",
    "sg:province":"Brandenburg",
    "wof:name":"K. Wellenhofer",
    "wof:placetype":"venue"
},
  "geometry": {"coordinates":[13.244404,52.30727],"type":"Point"}
}