{
  "type": "Feature",
  "properties": {
    "iso:country":"DE",
    "sg:address":"Goethestr. 16",
    "sg:city":"Herrenberg",
    "sg:phone":"+49 7032/5860",
    "sg:postcode":"71083",
    "sg:province":"Baden-W\u00fcrttemberg",
    "wof:name":"Goethe-video",
    "wof:placetype":"venue"
},
  "geometry": {"coordinates":[8.8676633835,48.5909576416],"type":"Point"}
}