{
  "type": "Feature",
  "properties": {
    "iso:country":"DE",
    "sg:address":"Philipp-Kranz-Str. 12",
    "sg:city":"Gr\u00fcnstadt",
    "sg:phone":"+49 6359/2442",
    "sg:postcode":"67269",
    "sg:province":"Rheinland-Pfalz",
    "wof:name":"Werner Rock Weinanbau",
    "wof:placetype":"venue"
},
  "geometry": {"coordinates":[8.1600971222,49.5593681335],"type":"Point"}
}