{
  "type": "Feature",
  "properties": {
    "iso:country":"DE",
    "sg:address":"Endstr. 28a",
    "sg:city":"Kevelaer",
    "sg:phone":"+49 2832/78432",
    "sg:postcode":"47624",
    "sg:province":"Nordrhein-Westfalen",
    "wof:name":"J. Wustmanns & Ressing",
    "wof:placetype":"venue"
},
  "geometry": {"coordinates":[6.204215,51.561859],"type":"Point"}
}