{
  "type": "Feature",
  "properties": {
    "iso:country":"DE",
    "sg:address":"Wisserswandstr. 50",
    "sg:city":"Waldkirch",
    "sg:phone":"+49 7681/20050",
    "sg:postcode":"79183",
    "sg:province":"Baden-W\u00fcrttemberg",
    "wof:name":"Staatl. Schule F\u00fcr Sehbehinderte",
    "wof:placetype":"venue"
},
  "geometry": {"coordinates":[7.976536,48.088661],"type":"Point"}
}