{
  "type": "Feature",
  "properties": {
    "iso:country":"DE",
    "sg:address":"Westring 20",
    "sg:city":"B\u00fcren",
    "sg:phone":"+49 2951/3021",
    "sg:postcode":"33142",
    "sg:province":"Nordrhein-Westfalen",
    "wof:name":"Zentralheizungsbau Gebro Haustechnik Gmbh & Co. Kg",
    "wof:placetype":"venue"
},
  "geometry": {"coordinates":[8.5376596451,51.5594406128],"type":"Point"}
}