{
  "type": "Feature",
  "properties": {
    "iso:country":"DE",
    "sg:address":"Bismarckstr. 12",
    "sg:city":"Bremen",
    "sg:phone":"+49 421/77278",
    "sg:postcode":"28203",
    "sg:province":"Bremen",
    "wof:name":"Galerie Bismarck",
    "wof:placetype":"venue"
},
  "geometry": {"coordinates":[8.827325,53.078556],"type":"Point"}
}