{
  "type": "Feature",
  "properties": {
    "iso:country":"DE",
    "sg:address":"Am Markt 3",
    "sg:city":"St. Georgen",
    "sg:phone":"+49 7724/3045",
    "sg:postcode":"78112",
    "sg:province":"Baden-W\u00fcrttemberg",
    "wof:name":"Redaktion Schwarzw\u00e4lder Bote",
    "wof:placetype":"venue"
},
  "geometry": {"coordinates":[8.3327932358,48.1260223389],"type":"Point"}
}