{
  "type": "Feature",
  "properties": {
    "iso:country":"DE",
    "sg:address":"Schichaustr. 7-9",
    "sg:city":"Frankfurt",
    "sg:phone":"+49 69/4960856",
    "sg:postcode":"60314",
    "sg:province":"Hessen",
    "wof:name":"Fresco Lebensmittel Gmbh",
    "wof:placetype":"venue"
},
  "geometry": {"coordinates":[8.7030248642,50.1118202209],"type":"Point"}
}