{
  "type": "Feature",
  "properties": {
    "iso:country":"DE",
    "sg:address":"Hinterm Gallberg 22",
    "sg:city":"Brilon",
    "sg:phone":"+49 2961/743018",
    "sg:postcode":"59929",
    "sg:province":"Nordrhein-Westfalen",
    "wof:name":"Slt Stanz- Und Lasertechnik Gmbh",
    "wof:placetype":"venue"
},
  "geometry": {"coordinates":[8.5921201706,51.4081993103],"type":"Point"}
}