{
  "type": "Feature",
  "properties": {
    "iso:country":"DE",
    "sg:address":"Heidelberger Str. 71",
    "sg:city":"Bensheim",
    "sg:phone":"+49 4962/5139030",
    "sg:postcode":"64625",
    "sg:province":"Hessen",
    "wof:name":"Bezirkssparkasse Bensheim",
    "wof:placetype":"venue"
},
  "geometry": {"coordinates":[8.6247,49.672157],"type":"Point"}
}