{
  "type": "Feature",
  "properties": {
    "iso:country":"DE",
    "sg:address":"Bahnhofstr. 237",
    "sg:city":"Uhlst\u00e4dt",
    "sg:phone":"+49 36742/237",
    "sg:postcode":"07407",
    "sg:province":"Th\u00fcringen",
    "wof:name":"Raiffeisenbank U. Handelsgenossen-, Schaft E. G.",
    "wof:placetype":"venue"
},
  "geometry": {"coordinates":[11.461981,50.741966],"type":"Point"}
}