{
  "type": "Feature",
  "properties": {
    "iso:country":"DE",
    "sg:address":"Gartenweg 3",
    "sg:city":"Lo\u00dfburg",
    "sg:phone":"+49 7446/1514",
    "sg:postcode":"72290",
    "sg:province":"Baden-W\u00fcrttemberg",
    "wof:name":"Hotel Gasthof Traube Gmbh",
    "wof:placetype":"venue"
},
  "geometry": {"coordinates":[8.4547023773,48.4109382629],"type":"Point"}
}