{
  "type": "Feature",
  "properties": {
    "iso:country":"DE",
    "sg:address":"Langestra\u00dfe 14",
    "sg:city":"Freiamt",
    "sg:phone":"+49 7645",
    "sg:postcode":"79348",
    "sg:province":"Baden-W\u00fcrttemberg",
    "wof:name":"Exklusive Gartenausstattung G. Und C. Klumb",
    "wof:placetype":"venue"
},
  "geometry": {"coordinates":[7.9066400528,48.178604126],"type":"Point"}
}