{
  "type": "Feature",
  "properties": {
    "iso:country":"DE",
    "sg:address":"Erthalstr. 13",
    "sg:city":"W\u00fcrzburg",
    "sg:postcode":"97074",
    "sg:province":"Bayern",
    "wof:name":"Msn F\u00f6rdermittel Gmbh",
    "wof:placetype":"venue"
},
  "geometry": {"coordinates":[9.943485,49.78373],"type":"Point"}
}