{
  "type": "Feature",
  "properties": {
    "iso:country":"DE",
    "sg:address":"K\u00fcpperstr. 44",
    "sg:city":"Voerde",
    "sg:phone":"+49 2855/16792",
    "sg:postcode":"46562",
    "sg:province":"Nordrhein-Westfalen",
    "wof:name":"Hans Hahn Versicherung",
    "wof:placetype":"venue"
},
  "geometry": {"coordinates":[6.6542000771,51.5897026062],"type":"Point"}
}