{
  "type": "Feature",
  "properties": {
    "iso:country":"DE",
    "sg:address":"Reinprechtinger Str. 9",
    "sg:city":"Deggendorf",
    "sg:phone":"+49 9901/93040",
    "sg:postcode":"94469",
    "sg:province":"Bayern",
    "wof:name":"Steuerkanzlei Ruth M\u00fcller",
    "wof:placetype":"venue"
},
  "geometry": {"coordinates":[13.00127,48.798485],"type":"Point"}
}