{
  "type": "Feature",
  "properties": {
    "iso:country":"DE",
    "sg:address":"Bahnhofstr. 4",
    "sg:city":"V\u00f6hringen",
    "sg:phone":"+49 4973/066015",
    "sg:postcode":"89269",
    "sg:province":"Bayern",
    "wof:name":"Hypo-bank Ag",
    "wof:placetype":"venue"
},
  "geometry": {"coordinates":[10.079357,48.277672],"type":"Point"}
}