{
  "type": "Feature",
  "properties": {
    "iso:country":"DE",
    "sg:address":"Karl-Schurz-Str. 2-4",
    "sg:city":"Paderborn",
    "sg:phone":"+49 5251/154950",
    "sg:postcode":"33100",
    "sg:province":"Nordrhein-Westfalen",
    "wof:name":"Maxi Zoo Im Blue Park",
    "wof:placetype":"venue"
},
  "geometry": {"coordinates":[8.785858,51.729988],"type":"Point"}
}