{
  "type": "Feature",
  "properties": {
    "iso:country":"DE",
    "sg:address":"Luisenstr. 9",
    "sg:city":"Alsdorf",
    "sg:phone":"+49 2404/1403",
    "sg:postcode":"52477",
    "sg:province":"Nordrhein-Westfalen",
    "wof:name":"Heidrun Thater Buchhandlung",
    "wof:placetype":"venue"
},
  "geometry": {"coordinates":[6.1628398895,50.8737602234],"type":"Point"}
}