{
  "type": "Feature",
  "properties": {
    "iso:country":"DE",
    "sg:address":"Bayreuther Str. 106",
    "sg:city":"Forchheim",
    "sg:phone":"+49 9102/93960",
    "sg:postcode":"91301",
    "sg:province":"Bayern",
    "wof:name":"Gesellschaft F\u00fcr Haustechnik Racom Mbh",
    "wof:placetype":"venue"
},
  "geometry": {"coordinates":[11.09311,49.714912],"type":"Point"}
}