{
  "type": "Feature",
  "properties": {
    "iso:country":"DE",
    "sg:address":"Renkenstr. 56a",
    "sg:city":"Puchheim",
    "sg:phone":"+49 89/801499",
    "sg:postcode":"82178",
    "sg:province":"Bayern",
    "wof:name":"G. Stumbaum",
    "wof:placetype":"venue"
},
  "geometry": {"coordinates":[11.350433,48.148739],"type":"Point"}
}