{
  "type": "Feature",
  "properties": {
    "iso:country":"DE",
    "sg:address":"R\u00fcttenscheider Str. 56",
    "sg:city":"Essen",
    "sg:phone":"+49 201/791031",
    "sg:postcode":"45130",
    "sg:province":"Nordrhein-Westfalen",
    "wof:name":"Buddenbrock Gmbh",
    "wof:placetype":"venue"
},
  "geometry": {"coordinates":[7.0056872368,51.4388847351],"type":"Point"}
}