{
  "type": "Feature",
  "properties": {
    "iso:country":"DE",
    "sg:address":"Nordseestr. 114",
    "sg:city":"Kiel",
    "sg:phone":"+49 431/311774",
    "sg:postcode":"24107",
    "sg:province":"Schleswig-Holstein",
    "wof:name":"Carl Clasen Ingenieur",
    "wof:placetype":"venue"
},
  "geometry": {"coordinates":[10.070523262,54.3607406616],"type":"Point"}
}