{
  "type": "Feature",
  "properties": {
    "iso:country":"DE",
    "sg:address":"99819",
    "sg:city":"Oberellen",
    "sg:phone":"+49 36925/6310",
    "sg:postcode":"99819",
    "sg:province":"Th\u00fcringen",
    "wof:name":"Gastst\u00e4tte Kulturhaus",
    "wof:placetype":"venue"
},
  "geometry": {"coordinates":[10.1842002869,50.9490699768],"type":"Point"}
}