{
  "type": "Feature",
  "properties": {
    "iso:country":"DE",
    "sg:address":"Kirchstr. 14",
    "sg:city":"Kr\u00f6v",
    "sg:phone":"+49 6541/6905",
    "sg:postcode":"54536",
    "sg:province":"Rheinland-Pfalz",
    "wof:name":"Robert Bindges",
    "wof:placetype":"venue"
},
  "geometry": {"coordinates":[7.1180272102,49.98279953],"type":"Point"}
}