{
  "type": "Feature",
  "properties": {
    "iso:country":"DE",
    "sg:address":"Auf dem Garten",
    "sg:city":"Karlshausen",
    "sg:postcode":"54673",
    "sg:province":"Rheinland-Pfalz",
    "wof:name":"Gpmb Gesellschaft F\u00fcr Polsterm\u00f6belindustrie-",
    "wof:placetype":"venue"
},
  "geometry": {"coordinates":[6.225746,50.020782],"type":"Point"}
}