{
  "type": "Feature",
  "properties": {
    "iso:country":"DE",
    "sg:address":"Dorfstr. 26",
    "sg:city":"Rohr",
    "sg:phone":"+49 9122/81961",
    "sg:postcode":"91189",
    "sg:province":"Bayern",
    "wof:name":"Michael Bauer",
    "wof:placetype":"venue"
},
  "geometry": {"coordinates":[10.971929,49.334965],"type":"Point"}
}