{
  "type": "Feature",
  "properties": {
    "iso:country":"DE",
    "sg:address":"Kasselerstrasse 75",
    "sg:city":"Kassel",
    "sg:phone":"+49 172 5613646",
    "sg:postcode":"34123",
    "sg:province":"Hessen",
    "wof:name":"Schaustellerbetriebe Horst Schellberg",
    "wof:placetype":"venue"
},
  "geometry": {"coordinates":[9.52713871,51.2877464294],"type":"Point"}
}