{
  "type": "Feature",
  "properties": {
    "iso:country":"DE",
    "sg:address":"Schulstr. 19",
    "sg:city":"Dreisen",
    "sg:phone":"+49 4963/57813",
    "sg:postcode":"67816",
    "sg:province":"Rheinland-Pfalz",
    "wof:name":"Raiffeisenbank Eg",
    "wof:placetype":"venue"
},
  "geometry": {"coordinates":[8.011904,49.602894],"type":"Point"}
}