{
  "type": "Feature",
  "properties": {
    "iso:country":"DE",
    "sg:address":"Unterer Markt 3",
    "sg:city":"Nabburg",
    "sg:phone":"+49 9433/6335",
    "sg:postcode":"92507",
    "sg:province":"Bayern",
    "wof:name":"Why Not",
    "wof:placetype":"venue"
},
  "geometry": {"coordinates":[12.1805553436,49.4535484314],"type":"Point"}
}