{
  "type": "Feature",
  "properties": {
    "iso:country":"DE",
    "sg:address":"Friedrich-Wilhelms-Bleiche 2-8",
    "sg:city":"Bielefeld",
    "sg:phone":"+49 521/45567",
    "sg:postcode":"33649",
    "sg:province":"Nordrhein-Westfalen",
    "wof:name":"Volmer Baustoffe",
    "wof:placetype":"venue"
},
  "geometry": {"coordinates":[8.4921579361,51.9930114746],"type":"Point"}
}