{
  "type": "Feature",
  "properties": {
    "iso:country":"DE",
    "sg:address":"Goethestr. 1",
    "sg:city":"Bad Pyrmont",
    "sg:phone":"+49 5281/969060",
    "sg:postcode":"31812",
    "sg:province":"Niedersachsen",
    "wof:name":"A. V. Elten Architekt",
    "wof:placetype":"venue"
},
  "geometry": {"coordinates":[9.253359,51.98288],"type":"Point"}
}