{
  "type": "Feature",
  "properties": {
    "iso:country":"DE",
    "sg:address":"Moosaustr. 9",
    "sg:city":"Frauenau",
    "sg:phone":"+49 9926/706",
    "sg:postcode":"94258",
    "sg:province":"Bayern",
    "wof:name":"Erwin Eisch",
    "wof:placetype":"venue"
},
  "geometry": {"coordinates":[13.301865,48.987953],"type":"Point"}
}