{
  "type": "Feature",
  "properties": {
    "iso:country":"DE",
    "sg:address":"Geh\u00f6llweg 4",
    "sg:city":"Oberalben",
    "sg:phone":"+49 6381/1554",
    "sg:postcode":"66871",
    "sg:province":"Rheinland-Pfalz",
    "wof:name":"Otto Gilcher",
    "wof:placetype":"venue"
},
  "geometry": {"coordinates":[7.4002699852,49.5781364441],"type":"Point"}
}