{
  "type": "Feature",
  "properties": {
    "iso:country":"DE",
    "sg:address":"95679",
    "sg:city":"Waldershof",
    "sg:phone":"+49 9231/7404",
    "sg:postcode":"95679",
    "sg:province":"Bayern",
    "wof:name":"Portofino",
    "wof:placetype":"venue"
},
  "geometry": {"coordinates":[12.0559301376,49.9448699951],"type":"Point"}
}