{
  "type": "Feature",
  "properties": {
    "iso:country":"DE",
    "sg:address":"Albert-Schweitzer-Str. 26",
    "sg:city":"Bad Salzungen",
    "sg:phone":"+49 3695/608050",
    "sg:postcode":"36433",
    "sg:province":"Th\u00fcringen",
    "wof:name":"Ristorante-pizzeria Calabria",
    "wof:placetype":"venue"
},
  "geometry": {"coordinates":[10.2430057526,50.8068466187],"type":"Point"}
}