{
  "type": "Feature",
  "properties": {
    "iso:country":"DE",
    "sg:address":"Kampstr. 30",
    "sg:city":"Dortmund",
    "sg:phone":"+49 231/9130200",
    "sg:postcode":"44137",
    "sg:province":"Nordrhein-Westfalen",
    "wof:name":"Gramm Und W\u00f6stefeld Rechtsanw\u00e4lte Und Notare",
    "wof:placetype":"venue"
},
  "geometry": {"coordinates":[7.46352005,51.5148620605],"type":"Point"}
}