{
  "type": "Feature",
  "properties": {
    "iso:country":"DE",
    "sg:address":"Wilhelmstr. 4-6 u. Lohbachstr.",
    "sg:city":"Velbert",
    "sg:phone":"+49 2053/2328",
    "sg:postcode":"42553",
    "sg:province":"Nordrhein-Westfalen",
    "wof:name":"M\u00f6belhaus Eller E. K. Inh. Ralf Schmitz",
    "wof:placetype":"venue"
},
  "geometry": {"coordinates":[7.09,51.311256],"type":"Point"}
}