{
  "type": "Feature",
  "properties": {
    "iso:country":"DE",
    "sg:address":"Bruchst\u00fccker 105",
    "sg:city":"Philippsburg",
    "sg:phone":"+49 7256/4480",
    "sg:postcode":"76661",
    "sg:province":"Baden-W\u00fcrttemberg",
    "wof:name":"Hirtz Automatisierungs- Technik Gmbh",
    "wof:placetype":"venue"
},
  "geometry": {"coordinates":[8.462987,49.224537],"type":"Point"}
}