{
  "type": "Feature",
  "properties": {
    "iso:country":"DE",
    "sg:address":"Ernst-Meurin-Str. 38",
    "sg:city":"Verl",
    "sg:phone":"+49 5246/83613",
    "sg:postcode":"33415",
    "sg:province":"Nordrhein-Westfalen",
    "wof:name":"R + Ga Gmbh",
    "wof:placetype":"venue"
},
  "geometry": {"coordinates":[8.4991493225,51.8717575073],"type":"Point"}
}