{
  "type": "Feature",
  "properties": {
    "iso:country":"DE",
    "sg:address":"Obere Dorfstr. 12",
    "sg:city":"Obernheim",
    "sg:phone":"+49 7436/8696",
    "sg:postcode":"72364",
    "sg:province":"Baden-W\u00fcrttemberg",
    "wof:name":"E. Moser",
    "wof:placetype":"venue"
},
  "geometry": {"coordinates":[8.861528,48.161762],"type":"Point"}
}