{
  "type": "Feature",
  "properties": {
    "iso:country":"DE",
    "sg:address":"Theodor-Heuss-Str. 12",
    "sg:city":"Andernach",
    "sg:phone":"+49 2632/409358",
    "sg:postcode":"56626",
    "sg:province":"Rheinland-Pfalz",
    "wof:name":"Ernst Jaegers Klaus Gesell Und Peter Kriesten",
    "wof:placetype":"venue"
},
  "geometry": {"coordinates":[7.398842,50.420212],"type":"Point"}
}