{
  "type": "Feature",
  "properties": {
    "iso:country":"DE",
    "sg:address":"Korlenbergstr. 7",
    "sg:city":"Gummersbach",
    "sg:phone":"+49 2261/51037",
    "sg:postcode":"51645",
    "sg:province":"Nordrhein-Westfalen",
    "wof:name":"Karl Heinz Klotz",
    "wof:placetype":"venue"
},
  "geometry": {"coordinates":[7.5968599319,51.00522995],"type":"Point"}
}