{
  "type": "Feature",
  "properties": {
    "iso:country":"DE",
    "sg:address":"Kampweg 2",
    "sg:city":"Bad Zwischenahn",
    "sg:phone":"+49 4403/7756",
    "sg:postcode":"26160",
    "sg:province":"Niedersachsen",
    "wof:name":"Uwe Knoren Innenarchitekt",
    "wof:placetype":"venue"
},
  "geometry": {"coordinates":[7.974866,53.19112],"type":"Point"}
}