{
  "type": "Feature",
  "properties": {
    "iso:country":"DE",
    "sg:address":"Am Holzbrunnen 6",
    "sg:city":"Schw\u00e4bisch Gm\u00fcnd",
    "sg:phone":"+49 7171/72442",
    "sg:postcode":"73527",
    "sg:province":"Baden-W\u00fcrttemberg",
    "wof:name":"P. Endress",
    "wof:placetype":"venue"
},
  "geometry": {"coordinates":[9.7513713837,48.8124809265],"type":"Point"}
}