{
  "type": "Feature",
  "properties": {
    "iso:country":"DE",
    "sg:address":"Dr.-Eugen-Essig-Str. 9",
    "sg:city":"Malsch",
    "sg:postcode":"76316",
    "sg:province":"Baden-W\u00fcrttemberg",
    "wof:name":"Thb Thomas Bautr\u00e4ger Gmbh",
    "wof:placetype":"venue"
},
  "geometry": {"coordinates":[8.332759,48.877628],"type":"Point"}
}