{
  "type": "Feature",
  "properties": {
    "iso:country":"DE",
    "sg:address":"Kreienmoor 3",
    "sg:city":"Schwanewede",
    "sg:phone":"+49 4209/2662",
    "sg:postcode":"28790",
    "sg:province":"Niedersachsen",
    "wof:name":"Martin K\u00fchlken",
    "wof:placetype":"venue"
},
  "geometry": {"coordinates":[8.6110458374,53.2221412659],"type":"Point"}
}