{
  "type": "Feature",
  "properties": {
    "iso:country":"DE",
    "sg:address":"Im Felde 56",
    "sg:city":"Nienburg",
    "sg:phone":"+49 5021/912408",
    "sg:postcode":"31582",
    "sg:province":"Niedersachsen",
    "wof:name":"W. Balk",
    "wof:placetype":"venue"
},
  "geometry": {"coordinates":[9.213924408,52.62550354],"type":"Point"}
}