{
  "type": "Feature",
  "properties": {
    "iso:country":"DE",
    "sg:address":"Quenhorner Str. 37",
    "sg:city":"Herzebrock-Clarholz",
    "sg:phone":"+49 5245/1676",
    "sg:postcode":"33442",
    "sg:province":"Nordrhein-Westfalen",
    "wof:name":"Vering Kg",
    "wof:placetype":"venue"
},
  "geometry": {"coordinates":[8.2487077713,51.9234199524],"type":"Point"}
}