{
  "type": "Feature",
  "properties": {
    "iso:country":"DE",
    "sg:address":"Sedanstr. 14",
    "sg:city":"L\u00fcdenscheid",
    "sg:phone":"+49 2351/20004",
    "sg:postcode":"58507",
    "sg:province":"Nordrhein-Westfalen",
    "wof:name":"Ihs Gmbh",
    "wof:placetype":"venue"
},
  "geometry": {"coordinates":[7.6328320503,51.2201156616],"type":"Point"}
}