{
  "type": "Feature",
  "properties": {
    "iso:country":"DE",
    "sg:address":"Wolbecker Windm\u00fchle 11",
    "sg:city":"M\u00fcnster",
    "sg:phone":"+49 2506/416",
    "sg:postcode":"48167",
    "sg:province":"Nordrhein-Westfalen",
    "wof:name":"Hans Marsmann Gew\u00e4chshaus Gmbh",
    "wof:placetype":"venue"
},
  "geometry": {"coordinates":[7.719173,51.928261],"type":"Point"}
}