{
  "type": "Feature",
  "properties": {
    "iso:country":"DE",
    "sg:address":"Hamburger Str. 69",
    "sg:city":"Dortmund",
    "sg:phone":"+49 231/5865394",
    "sg:postcode":"44135",
    "sg:province":"Nordrhein-Westfalen",
    "wof:name":"Faik Genct\u00fcrk Hoch- Und Tiefbau Gmbh",
    "wof:placetype":"venue"
},
  "geometry": {"coordinates":[7.481678009,51.5138969421],"type":"Point"}
}