{
  "type": "Feature",
  "properties": {
    "iso:country":"DE",
    "sg:address":"Bonnenbroicher Str. 15",
    "sg:city":"M\u00f6nchengladbach",
    "sg:postcode":"41238",
    "sg:province":"Nordrhein-Westfalen",
    "wof:name":"Euroschnitt Gmbh",
    "wof:placetype":"venue"
},
  "geometry": {"coordinates":[6.4561481476,51.176448822],"type":"Point"}
}