{
  "type": "Feature",
  "properties": {
    "iso:country":"DE",
    "sg:address":"Leisbergstr. 17 c",
    "sg:city":"Baden-Baden",
    "sg:phone":"+49 7221/75710",
    "sg:postcode":"76534",
    "sg:province":"Baden-W\u00fcrttemberg",
    "wof:name":"Gross Verwaltungs- Und Beteiligungs Gmbh",
    "wof:placetype":"venue"
},
  "geometry": {"coordinates":[8.2527322769,48.7455062866],"type":"Point"}
}