{
  "type": "Feature",
  "properties": {
    "iso:country":"DE",
    "sg:address":"Oeverdieker Weg 15 - 17",
    "sg:city":"Timmendorfer Strand",
    "sg:phone":"+49 4503/2195",
    "sg:postcode":"23669",
    "sg:province":"Schleswig-Holstein",
    "wof:name":"Jugenderholungsheim Overdiek",
    "wof:placetype":"venue"
},
  "geometry": {"coordinates":[10.7548389435,54.0024528503],"type":"Point"}
}