{
  "type": "Feature",
  "properties": {
    "iso:country":"DE",
    "sg:address":"Grimmaische Str.",
    "sg:city":"D\u00f6beln",
    "sg:postcode":"04720",
    "sg:province":"Sachsen",
    "wof:name":"Aldi Gmbh & Co. Kg",
    "wof:placetype":"venue"
},
  "geometry": {"coordinates":[13.0992650986,51.134223938],"type":"Point"}
}