{
  "type": "Feature",
  "properties": {
    "iso:country":"DE",
    "sg:address":"Karl-Liebknecht-Str. 14",
    "sg:city":"Weimar",
    "sg:phone":"+49 3643/245310",
    "sg:postcode":"99423",
    "sg:province":"Th\u00fcringen",
    "wof:name":"Bhw-immobilien Gmbh",
    "wof:placetype":"venue"
},
  "geometry": {"coordinates":[11.3256978989,50.9825363159],"type":"Point"}
}