{
  "type": "Feature",
  "properties": {
    "iso:country":"DE",
    "sg:address":"H\u00f6ckhstr. 9",
    "sg:city":"Bad T\u00f6lz",
    "sg:postcode":"83646",
    "sg:province":"Bayern",
    "wof:name":"Hotel Pension Geiger - Herzlich Willkommen In Bad",
    "wof:placetype":"venue"
},
  "geometry": {"coordinates":[11.545545578,47.7622566223],"type":"Point"}
}