{
  "type": "Feature",
  "properties": {
    "iso:country":"DE",
    "sg:address":"Starkenburger Str. 74",
    "sg:city":"Riedstadt",
    "sg:phone":"+49 6158/1381",
    "sg:postcode":"64560",
    "sg:province":"Hessen",
    "wof:name":"Bistro Journal",
    "wof:placetype":"venue"
},
  "geometry": {"coordinates":[8.5016431808,49.8381538391],"type":"Point"}
}