{
  "type": "Feature",
  "properties": {
    "iso:country":"DE",
    "sg:address":"Carl-von-Ossietzky-Str. 1",
    "sg:city":"Cottbus",
    "sg:phone":"+49 35601/36030",
    "sg:postcode":"03046",
    "sg:province":"Brandenburg",
    "wof:name":"Brose & Partner Bauges. F\u00fcr Schl\u00fcsselfertiges Bauen Mbh",
    "wof:placetype":"venue"
},
  "geometry": {"coordinates":[14.324069,51.75568],"type":"Point"}
}