{
  "type": "Feature",
  "properties": {
    "iso:country":"DE",
    "sg:address":"Ziegelbach",
    "sg:city":"Bad Wurzach",
    "sg:phone":"+49 7564/1634",
    "sg:postcode":"88410",
    "sg:province":"Baden-W\u00fcrttemberg",
    "wof:name":"Dorfstadel",
    "wof:placetype":"venue"
},
  "geometry": {"coordinates":[9.8908281326,47.8583641052],"type":"Point"}
}