{
  "type": "Feature",
  "properties": {
    "iso:country":"DE",
    "sg:address":"Spaldingstr 77",
    "sg:city":"Hamburg",
    "sg:phone":"+49 40/2369920",
    "sg:postcode":"20097",
    "sg:province":"Hamburg",
    "wof:name":"Verleger-inkasso-stelle Wallstab & Co Gmbh & Co",
    "wof:placetype":"venue"
},
  "geometry": {"coordinates":[10.015761,53.549198],"type":"Point"}
}