{
  "type": "Feature",
  "properties": {
    "iso:country":"DE",
    "sg:address":"Unterm-Heilig-Kreuz 11",
    "sg:city":"Fulda",
    "sg:phone":"+49 661/78382",
    "sg:postcode":"36037",
    "sg:province":"Hessen",
    "wof:name":"Christoph Herbert",
    "wof:placetype":"venue"
},
  "geometry": {"coordinates":[9.676466,50.551277],"type":"Point"}
}