{
  "type": "Feature",
  "properties": {
    "iso:country":"DE",
    "sg:address":"Kirner Str. 6",
    "sg:city":"Sien",
    "sg:phone":"+49 6788/888",
    "sg:postcode":"55758",
    "sg:province":"Rheinland-Pfalz",
    "wof:name":"Otto Jung Gmbh & Co. Kg",
    "wof:placetype":"venue"
},
  "geometry": {"coordinates":[7.506453,49.696106],"type":"Point"}
}