{
  "type": "Feature",
  "properties": {
    "iso:country":"DE",
    "sg:address":"Kaiser-Wilhelm-Ring 18",
    "sg:city":"Amberg",
    "sg:phone":"+49 9621/14002",
    "sg:postcode":"92224",
    "sg:province":"Bayern",
    "wof:name":"Herbert Berka Generalvertr. D. Bvb All.",
    "wof:placetype":"venue"
},
  "geometry": {"coordinates":[11.8497438431,49.4462356567],"type":"Point"}
}