{
  "type": "Feature",
  "properties": {
    "iso:country":"DE",
    "sg:address":"D\u00fcrener Str. 41",
    "sg:city":"Eschweiler",
    "sg:phone":"+49 4924/0337393",
    "sg:postcode":"52249",
    "sg:province":"Nordrhein-Westfalen",
    "wof:name":"Kirchner Staubzauger",
    "wof:placetype":"venue"
},
  "geometry": {"coordinates":[6.271504,50.819778],"type":"Point"}
}