{
  "type": "Feature",
  "properties": {
    "iso:country":"DE",
    "sg:address":"Eschweger Str. 17",
    "sg:city":"Sontra",
    "sg:phone":"+49 5658/295",
    "sg:postcode":"36205",
    "sg:province":"Hessen",
    "wof:name":"Reinhard Reimuth",
    "wof:placetype":"venue"
},
  "geometry": {"coordinates":[9.972739,51.109715],"type":"Point"}
}