{
  "type": "Feature",
  "properties": {
    "iso:country":"DE",
    "sg:address":"Mittelstr. 20-24",
    "sg:city":"K\u00f6ln",
    "sg:phone":"+49 221/9201440",
    "sg:postcode":"50672",
    "sg:province":"Nordrhein-Westfalen",
    "wof:name":"Gg Werbeagentur Gmbh",
    "wof:placetype":"venue"
},
  "geometry": {"coordinates":[6.9433021545,50.937046051],"type":"Point"}
}