{
  "type": "Feature",
  "properties": {
    "iso:country":"DE",
    "sg:address":"Hubertusring 6",
    "sg:city":"Espelkamp",
    "sg:phone":"+49 5771/2060",
    "sg:postcode":"32339",
    "sg:province":"Nordrhein-Westfalen",
    "wof:name":"Andreas Erdelt",
    "wof:placetype":"venue"
},
  "geometry": {"coordinates":[8.6123399734,52.401058197],"type":"Point"}
}