{
  "type": "Feature",
  "properties": {
    "iso:country":"DE",
    "sg:address":"St\u00fchren 10",
    "sg:city":"Bassum",
    "sg:phone":"+49 4249/372",
    "sg:postcode":"27211",
    "sg:province":"Niedersachsen",
    "wof:name":"Horst Ziebe",
    "wof:placetype":"venue"
},
  "geometry": {"coordinates":[8.716927,52.904362],"type":"Point"}
}