{
  "type": "Feature",
  "properties": {
    "iso:country":"DE",
    "sg:address":"Villigster Str.",
    "sg:city":"Schwerte",
    "sg:phone":"+49 2304/7550",
    "sg:postcode":"58239",
    "sg:province":"Nordrhein-Westfalen",
    "wof:name":"Evangelisches Studienwerk E. V.",
    "wof:placetype":"venue"
},
  "geometry": {"coordinates":[7.5859098434,51.4358406067],"type":"Point"}
}