{
  "type": "Feature",
  "properties": {
    "iso:country":"DE",
    "sg:address":"Steinfeldstr. 21",
    "sg:city":"Laatzen",
    "sg:phone":"+49 5102/3735",
    "sg:postcode":"30880",
    "sg:province":"Niedersachsen",
    "wof:name":"Reiner Schmidt",
    "wof:placetype":"venue"
},
  "geometry": {"coordinates":[9.812016,52.292503],"type":"Point"}
}