{
  "type": "Feature",
  "properties": {
    "iso:country":"DE",
    "sg:address":"Ind.-Park Wolfen/Thalheim",
    "sg:city":"Wolfen",
    "sg:phone":"+49 3494/369500",
    "sg:postcode":"06766",
    "sg:province":"Sachsen-Anhalt",
    "wof:name":"Orwo Media Gmbh",
    "wof:placetype":"venue"
},
  "geometry": {"coordinates":[12.25423,51.669949],"type":"Point"}
}