{
  "type": "Feature",
  "properties": {
    "iso:country":"DE",
    "sg:address":"Stiegelenweg 14",
    "sg:city":"Staufen",
    "sg:phone":"+49 7633/81991",
    "sg:postcode":"79219",
    "sg:province":"Baden-W\u00fcrttemberg",
    "wof:name":"Helmut Himmelhan Innenarchitekt",
    "wof:placetype":"venue"
},
  "geometry": {"coordinates":[7.720207,47.880024],"type":"Point"}
}