{
  "type": "Feature",
  "properties": {
    "iso:country":"DE",
    "sg:address":"Bayplatz 5",
    "sg:city":"Furth im Wald",
    "sg:phone":"+49 9973/2433",
    "sg:postcode":"93437",
    "sg:province":"Bayern",
    "wof:name":"Bistro Terminus",
    "wof:placetype":"venue"
},
  "geometry": {"coordinates":[12.8459291458,49.306388855],"type":"Point"}
}