{
  "type": "Feature",
  "properties": {
    "iso:country":"DE",
    "sg:address":"Landhausstr. 2",
    "sg:city":"Berlin",
    "sg:phone":"+49 30/8611932",
    "sg:postcode":"10717",
    "sg:province":"Berlin",
    "wof:name":"Klaus-peter Stargardt",
    "wof:placetype":"venue"
},
  "geometry": {"coordinates":[13.3284254074,52.4922065735],"type":"Point"}
}