{
  "type": "Feature",
  "properties": {
    "iso:country":"DE",
    "sg:address":"Weststr. 4",
    "sg:city":"Weimar",
    "sg:phone":"+49 3643/904243",
    "sg:postcode":"99425",
    "sg:province":"Th\u00fcringen",
    "wof:name":"Herbert Haubold",
    "wof:placetype":"venue"
},
  "geometry": {"coordinates":[11.343415,50.960335],"type":"Point"}
}