{
  "type": "Feature",
  "properties": {
    "iso:country":"DE",
    "sg:address":"Marktplatz 1a",
    "sg:city":"Weingarten",
    "sg:phone":"+49 7244/5288",
    "sg:postcode":"76356",
    "sg:province":"Baden-W\u00fcrttemberg",
    "wof:name":"Cafe Am Markt",
    "wof:placetype":"venue"
},
  "geometry": {"coordinates":[8.531871,49.051914],"type":"Point"}
}