{
  "type": "Feature",
  "properties": {
    "iso:country":"DE",
    "sg:address":"Saarstr. 33",
    "sg:city":"Seeheim-Jugenheim",
    "sg:phone":"+49 6257/2456",
    "sg:postcode":"64342",
    "sg:province":"Hessen",
    "wof:name":"Eberhard Ott",
    "wof:placetype":"venue"
},
  "geometry": {"coordinates":[8.629463,49.755249],"type":"Point"}
}