{
  "type": "Feature",
  "properties": {
    "iso:country":"DE",
    "sg:address":"Hochstr. 45",
    "sg:city":"Berlin",
    "sg:phone":"+49 30/4652067",
    "sg:postcode":"13357",
    "sg:province":"Berlin",
    "wof:name":"Meurer & Co. Abdichtungsgesellschaft Mbh",
    "wof:placetype":"venue"
},
  "geometry": {"coordinates":[13.37816,52.544258],"type":"Point"}
}