{
  "type": "Feature",
  "properties": {
    "iso:country":"DE",
    "sg:address":"Breslauer Str. 3",
    "sg:city":"Bad Nauheim",
    "sg:phone":"+49 6032/6447",
    "sg:postcode":"61231",
    "sg:province":"Hessen",
    "wof:name":"Gerhard Huber Steuerberater Und",
    "wof:placetype":"venue"
},
  "geometry": {"coordinates":[8.7324237823,50.3689498901],"type":"Point"}
}