{
  "type": "Feature",
  "properties": {
    "iso:country":"DE",
    "sg:address":"Ochsengasse 12",
    "sg:city":"Auggen",
    "sg:phone":"+49 7631/16761",
    "sg:postcode":"79424",
    "sg:province":"Baden-W\u00fcrttemberg",
    "wof:name":"Synaps Informationstechnik Gmbh",
    "wof:placetype":"venue"
},
  "geometry": {"coordinates":[7.5943989754,47.7864570618],"type":"Point"}
}