{
  "type": "Feature",
  "properties": {
    "iso:country":"DE",
    "sg:address":"Hauptstr. 8",
    "sg:city":"Reiferscheid",
    "sg:phone":"+49 2685/989701",
    "sg:postcode":"57632",
    "sg:province":"Rheinland-Pfalz",
    "wof:name":"Ava-telefontechnik",
    "wof:placetype":"venue"
},
  "geometry": {"coordinates":[7.5400490761,50.6547622681],"type":"Point"}
}