{
  "type": "Feature",
  "properties": {
    "iso:country":"DE",
    "sg:address":"Am Breul 2",
    "sg:city":"Karben",
    "sg:phone":"+49 6039/2920",
    "sg:postcode":"61184",
    "sg:province":"Hessen",
    "wof:name":"Bistro Schwimmbad",
    "wof:placetype":"venue"
},
  "geometry": {"coordinates":[8.7665147781,50.2318572998],"type":"Point"}
}