{
  "type": "Feature",
  "properties": {
    "iso:country":"DE",
    "sg:address":"Winkeler Str. 54",
    "sg:city":"Geisenheim",
    "sg:phone":"+49 6722/99290",
    "sg:postcode":"65366",
    "sg:province":"Hessen",
    "wof:name":"Foto Wienen Edlefs Laden Der Foto-",
    "wof:placetype":"venue"
},
  "geometry": {"coordinates":[7.9665842056,49.9841690063],"type":"Point"}
}