{
  "type": "Feature",
  "properties": {
    "iso:country":"DE",
    "sg:address":"Schnurgasse 10",
    "sg:city":"Waldsolms",
    "sg:phone":"+49 6085/3054",
    "sg:postcode":"35647",
    "sg:province":"Hessen",
    "wof:name":"Karl H. Ott Elektroinstallation",
    "wof:placetype":"venue"
},
  "geometry": {"coordinates":[8.496415,50.43541],"type":"Point"}
}