{
  "type": "Feature",
  "properties": {
    "iso:country":"DE",
    "sg:address":"Hochstr. 40",
    "sg:city":"Rhens",
    "sg:phone":"+49 2628/2424",
    "sg:postcode":"56321",
    "sg:province":"Rheinland-Pfalz",
    "wof:name":"R. Felden",
    "wof:placetype":"venue"
},
  "geometry": {"coordinates":[7.6166958809,50.2824172974],"type":"Point"}
}