{
  "type": "Feature",
  "properties": {
    "iso:country":"DE",
    "sg:address":"R\u00f6ntgenweg 16",
    "sg:city":"Coburg",
    "sg:phone":"+49 9561/25556",
    "sg:postcode":"96450",
    "sg:province":"Bayern",
    "wof:name":"Wolfgang Sch\u00e4ftlein",
    "wof:placetype":"venue"
},
  "geometry": {"coordinates":[10.9790687561,50.2493438721],"type":"Point"}
}