{
  "type": "Feature",
  "properties": {
    "iso:country":"DE",
    "sg:address":"Walter-Kolb-Str. 9",
    "sg:city":"Frankfurt",
    "sg:phone":"+49 69/6050190",
    "sg:postcode":"60594",
    "sg:province":"Hessen",
    "wof:name":"Fizit Farnz\u00f6sisches Informationszentrum F\u00fcr",
    "wof:placetype":"venue"
},
  "geometry": {"coordinates":[8.6858034134,50.1053695679],"type":"Point"}
}