{
  "type": "Feature",
  "properties": {
    "iso:country":"DE",
    "sg:address":"Kirchenweg 38",
    "sg:city":"Rosenheim",
    "sg:phone":"+49 8031/26500",
    "sg:postcode":"83026",
    "sg:province":"Bayern",
    "wof:name":"Hotel-restaurant Ariadne Amelie Gro\u00df",
    "wof:placetype":"venue"
},
  "geometry": {"coordinates":[12.1213293076,47.8356971741],"type":"Point"}
}