{
  "type": "Feature",
  "properties": {
    "iso:country":"DE",
    "sg:address":"Schmiedestr. 8 a",
    "sg:city":"Genthin",
    "sg:phone":"+49 3933/804562",
    "sg:postcode":"39307",
    "sg:province":"Sachsen-Anhalt",
    "wof:name":"F. Kortegast",
    "wof:placetype":"venue"
},
  "geometry": {"coordinates":[12.133005,52.419338],"type":"Point"}
}