{
  "type": "Feature",
  "properties": {
    "iso:country":"DE",
    "sg:address":"Karolinenstr. 19",
    "sg:city":"Berlin",
    "sg:phone":"+49 30/4331064",
    "sg:postcode":"13507",
    "sg:province":"Berlin",
    "wof:name":"Stadtbibliothek Reinickendorf Humboldt-bibliothek",
    "wof:placetype":"venue"
},
  "geometry": {"coordinates":[13.281696,52.591476],"type":"Point"}
}