{
  "type": "Feature",
  "properties": {
    "iso:country":"DE",
    "sg:address":"Obermaierstr. 16",
    "sg:city":"N\u00fcrnberg",
    "sg:postcode":"90408",
    "sg:province":"Bayern",
    "wof:name":"Sei Interconnect Products Europe Ltd.",
    "wof:placetype":"venue"
},
  "geometry": {"coordinates":[11.073315,49.471046],"type":"Point"}
}