{
  "type": "Feature",
  "properties": {
    "iso:country":"DE",
    "sg:address":"Kapellenstr. 70",
    "sg:city":"Laupheim",
    "sg:phone":"+49 7392/6681",
    "sg:postcode":"88471",
    "sg:province":"Baden-W\u00fcrttemberg",
    "wof:name":"Billardsalon Zum Alexis",
    "wof:placetype":"venue"
},
  "geometry": {"coordinates":[9.8823766708,48.234588623],"type":"Point"}
}