{
  "type": "Feature",
  "properties": {
    "iso:country":"DE",
    "sg:address":"Mittelstr. 8",
    "sg:city":"Gieboldehausen",
    "sg:phone":"+49 5528/654",
    "sg:postcode":"37434",
    "sg:province":"Niedersachsen",
    "wof:name":"Herbert Kemmling",
    "wof:placetype":"venue"
},
  "geometry": {"coordinates":[10.215237,51.611145],"type":"Point"}
}