{
  "type": "Feature",
  "properties": {
    "iso:country":"DE",
    "sg:address":"Brahmsstr. 5",
    "sg:city":"Reilingen",
    "sg:phone":"+49 6205/6042",
    "sg:postcode":"68799",
    "sg:province":"Baden-W\u00fcrttemberg",
    "wof:name":"S. K\u00fchnle",
    "wof:placetype":"venue"
},
  "geometry": {"coordinates":[8.560167,49.294724],"type":"Point"}
}