{
  "type": "Feature",
  "properties": {
    "iso:country":"DE",
    "sg:address":"K\u00fcps",
    "sg:city":"K\u00fcps",
    "sg:phone":"+49 9264/7189",
    "sg:postcode":"96328",
    "sg:province":"Bayern",
    "wof:name":"Raiffeisenbank Burkersdorf Eg",
    "wof:placetype":"venue"
},
  "geometry": {"coordinates":[11.28645,50.19714],"type":"Point"}
}