{
  "type": "Feature",
  "properties": {
    "iso:country":"DE",
    "sg:address":"Kolmstr. 51",
    "sg:city":"Leipzig",
    "sg:phone":"+49 341/8621650",
    "sg:postcode":"04299",
    "sg:province":"Sachsen",
    "wof:name":"Wilkommen In Leipzig!",
    "wof:placetype":"venue"
},
  "geometry": {"coordinates":[12.427949,51.314457],"type":"Point"}
}