{
  "type": "Feature",
  "properties": {
    "iso:country":"DE",
    "sg:address":"Fichtenstr. 3",
    "sg:city":"Stockelsdorf",
    "sg:phone":"+49 4506/89894",
    "sg:postcode":"23617",
    "sg:province":"Schleswig-Holstein",
    "wof:name":"Beckmann & Eggers Gmbh",
    "wof:placetype":"venue"
},
  "geometry": {"coordinates":[10.5513248444,53.916267395],"type":"Point"}
}