{
  "type": "Feature",
  "properties": {
    "iso:country":"DE",
    "sg:address":"Berliner Str. 5",
    "sg:city":"Eschborn",
    "sg:phone":"+49 6196/481995",
    "sg:postcode":"65760",
    "sg:province":"Hessen",
    "wof:name":"Dr. F.-m. Winkler",
    "wof:placetype":"venue"
},
  "geometry": {"coordinates":[8.5650415421,50.1391029358],"type":"Point"}
}