{
  "type": "Feature",
  "properties": {
    "iso:country":"DE",
    "sg:address":"Helmertstr 1",
    "sg:city":"Mannheim",
    "sg:phone":"+49 621/87860",
    "sg:postcode":"68219",
    "sg:province":"Baden-W\u00fcrttemberg",
    "wof:name":"Facon Gmbh",
    "wof:placetype":"venue"
},
  "geometry": {"coordinates":[8.513404,49.453793],"type":"Point"}
}