{
  "type": "Feature",
  "properties": {
    "iso:country":"DE",
    "sg:address":"Besselstr. 13",
    "sg:city":"Berlin",
    "sg:postcode":"10969",
    "sg:province":"Berlin",
    "wof:name":"Druck + Werbung Inh. Gutschmidt",
    "wof:placetype":"venue"
},
  "geometry": {"coordinates":[13.394216,52.50465],"type":"Point"}
}