{
  "type": "Feature",
  "properties": {
    "iso:country":"DE",
    "sg:address":"Neuenkirchener Str. 54",
    "sg:city":"G\u00fctersloh",
    "sg:phone":"+49 5241/51229",
    "sg:postcode":"33332",
    "sg:province":"Nordrhein-Westfalen",
    "wof:name":"Schuette Baubetreuungs Gmbh",
    "wof:placetype":"venue"
},
  "geometry": {"coordinates":[8.378303,51.897621],"type":"Point"}
}