{
  "type": "Feature",
  "properties": {
    "iso:country":"DE",
    "sg:address":"Auf der Stadt 18 a",
    "sg:city":"Dinklage",
    "sg:phone":"+49 4443/1276",
    "sg:postcode":"49413",
    "sg:province":"Niedersachsen",
    "wof:name":"T. Pieper",
    "wof:placetype":"venue"
},
  "geometry": {"coordinates":[8.115763,52.61974],"type":"Point"}
}