{
  "type": "Feature",
  "properties": {
    "iso:country":"DE",
    "sg:address":"J\u00f6rg-Hofmann-Str. 70",
    "sg:city":"Zeil",
    "sg:phone":"+49 9524/83390",
    "sg:postcode":"97475",
    "sg:province":"Bayern",
    "wof:name":"Ehb-zeil Kommunikation Und Mehr",
    "wof:placetype":"venue"
},
  "geometry": {"coordinates":[10.5889387131,50.020149231],"type":"Point"}
}