{
  "type": "Feature",
  "properties": {
    "iso:country":"DE",
    "sg:address":"Landwehrstr. 22",
    "sg:city":"Bergkamen",
    "sg:phone":"+49 2307/68979",
    "sg:postcode":"59192",
    "sg:province":"Nordrhein-Westfalen",
    "wof:name":"Glei\u00dfner",
    "wof:placetype":"venue"
},
  "geometry": {"coordinates":[7.6354970932,51.6138153076],"type":"Point"}
}