{
  "type": "Feature",
  "properties": {
    "iso:country":"DE",
    "sg:address":"Ostring 76",
    "sg:city":"Hainburg",
    "sg:phone":"+49 6182/4176",
    "sg:postcode":"63512",
    "sg:province":"Hessen",
    "wof:name":"Zentral-kranken- Und Sterbekasse",
    "wof:placetype":"venue"
},
  "geometry": {"coordinates":[8.9742012024,50.0747680664],"type":"Point"}
}