{
  "type": "Feature",
  "properties": {
    "iso:country":"DE",
    "sg:address":"Am K\u00f6nigsfeld 3",
    "sg:city":"Brakel",
    "sg:phone":"+49 5272/39797",
    "sg:postcode":"33034",
    "sg:province":"Nordrhein-Westfalen",
    "wof:name":"J\u00f6rg Stiewe",
    "wof:placetype":"venue"
},
  "geometry": {"coordinates":[9.18068,51.709091],"type":"Point"}
}