{
  "type": "Feature",
  "properties": {
    "iso:country":"DE",
    "sg:address":"Lindenallee 8",
    "sg:city":"Lutherstadt Eisleben",
    "sg:phone":"+49 3475/696336",
    "sg:postcode":"06295",
    "sg:province":"Sachsen-Anhalt",
    "wof:name":"Dr. M. Fleischer Zahnarzt",
    "wof:placetype":"venue"
},
  "geometry": {"coordinates":[11.5517482758,51.528301239],"type":"Point"}
}