{
  "type": "Feature",
  "properties": {
    "iso:country":"DE",
    "sg:address":"Birkenkamp 2",
    "sg:city":"Diemelstadt",
    "sg:phone":"+49 2992/2053",
    "sg:postcode":"34474",
    "sg:province":"Hessen",
    "wof:name":"Fwg Freizeitwohnpark Grundbesitz Gmbh & Co.",
    "wof:placetype":"venue"
},
  "geometry": {"coordinates":[8.9072723389,51.4719009399],"type":"Point"}
}