{
  "type": "Feature",
  "properties": {
    "iso:country":"DE",
    "sg:address":"Br\u00fcckenstr. 2",
    "sg:city":"Gauersheim",
    "sg:phone":"+49 6355/523",
    "sg:postcode":"67294",
    "sg:province":"Rheinland-Pfalz",
    "wof:name":"Manfred Gerber",
    "wof:placetype":"venue"
},
  "geometry": {"coordinates":[8.0727491379,49.6598777771],"type":"Point"}
}