{
  "type": "Feature",
  "properties": {
    "iso:country":"DE",
    "sg:address":"Modering",
    "sg:city":"Hamburg",
    "sg:postcode":"22457",
    "sg:province":"Hamburg",
    "wof:name":"Mode F\u00fcr \u00dcbergr\u00f6\u00dfen Wear Big Handels Gmbh & Co. Kg",
    "wof:placetype":"venue"
},
  "geometry": {"coordinates":[9.922112,53.637371],"type":"Point"}
}