{
  "type": "Feature",
  "properties": {
    "iso:country":"DE",
    "sg:address":"An den Loddenb\u00fcschen 183",
    "sg:city":"M\u00fcnster",
    "sg:phone":"+49 251/661196",
    "sg:postcode":"48155",
    "sg:province":"Nordrhein-Westfalen",
    "wof:name":"Haus Eiting",
    "wof:placetype":"venue"
},
  "geometry": {"coordinates":[7.6496400833,51.9287376404],"type":"Point"}
}