{
  "type": "Feature",
  "properties": {
    "iso:country":"DE",
    "sg:address":"Waldheimstr. 1",
    "sg:city":"Kierspe",
    "sg:phone":"+49 2359/2435",
    "sg:postcode":"58566",
    "sg:province":"Nordrhein-Westfalen",
    "wof:name":"Wilhelm Wohlgemuth",
    "wof:placetype":"venue"
},
  "geometry": {"coordinates":[7.59252882,51.1206130981],"type":"Point"}
}