{
  "type": "Feature",
  "properties": {
    "iso:country":"DE",
    "sg:address":"Haldenstr. 1",
    "sg:city":"Dettingen",
    "sg:phone":"+49 7021/59236",
    "sg:postcode":"73265",
    "sg:province":"Baden-W\u00fcrttemberg",
    "wof:name":"Hsb",
    "wof:placetype":"venue"
},
  "geometry": {"coordinates":[9.449025,48.614666],"type":"Point"}
}