{
  "type": "Feature",
  "properties": {
    "iso:country":"DE",
    "sg:address":"Glash\u00fctter Str. 11",
    "sg:city":"Bockenem",
    "sg:phone":"+49 5067/2995",
    "sg:postcode":"31167",
    "sg:province":"Niedersachsen",
    "wof:name":"Wilhelm G\u00f6decke",
    "wof:placetype":"venue"
},
  "geometry": {"coordinates":[10.096739,51.965164],"type":"Point"}
}