{
  "type": "Feature",
  "properties": {
    "iso:country":"DE",
    "sg:address":"Martener Str. 313",
    "sg:city":"Dortmund",
    "sg:phone":"+49 231/614483",
    "sg:postcode":"44379",
    "sg:province":"Nordrhein-Westfalen",
    "wof:name":"Heinrich Ewald",
    "wof:placetype":"venue"
},
  "geometry": {"coordinates":[7.381868,51.510036],"type":"Point"}
}