{
  "type": "Feature",
  "properties": {
    "iso:country":"DE",
    "sg:address":"Auf dem Wollerscheid 11",
    "sg:city":"Simmerath",
    "sg:phone":"+49 2473/7882",
    "sg:postcode":"52152",
    "sg:province":"Nordrhein-Westfalen",
    "wof:name":"Dietmar Essers-hild Rechtsanwalt",
    "wof:placetype":"venue"
},
  "geometry": {"coordinates":[6.2676792145,50.6328086853],"type":"Point"}
}