{
  "type": "Feature",
  "properties": {
    "iso:country":"DE",
    "sg:address":"Tuchmacherstr. 42",
    "sg:city":"Potsdam",
    "sg:phone":"+49 331/710425",
    "sg:postcode":"14482",
    "sg:province":"Brandenburg",
    "wof:name":"C. Schulz",
    "wof:placetype":"venue"
},
  "geometry": {"coordinates":[13.091726,52.395733],"type":"Point"}
}