{
  "type": "Feature",
  "properties": {
    "iso:country":"DE",
    "sg:address":"Ohechaussee 7",
    "sg:city":"Norderstedt",
    "sg:phone":"+49 228/669341",
    "sg:postcode":"22848",
    "sg:province":"Schleswig-Holstein",
    "wof:name":"Commerzbank Ag",
    "wof:placetype":"venue"
},
  "geometry": {"coordinates":[7.045502,50.75],"type":"Point"}
}