{
  "type": "Feature",
  "properties": {
    "iso:country":"DE",
    "sg:address":"Sta\u00dffurter H\u00f6he 35",
    "sg:city":"Aschersleben",
    "sg:phone":"+49 3473/815809",
    "sg:postcode":"06449",
    "sg:province":"Sachsen-Anhalt",
    "wof:name":"Pension B\u00e4rbel Lehmann",
    "wof:placetype":"venue"
},
  "geometry": {"coordinates":[11.4653081894,51.7609558105],"type":"Point"}
}