{
  "type": "Feature",
  "properties": {
    "iso:country":"DE",
    "sg:address":"Leloh 24",
    "sg:city":"Schwalmtal",
    "sg:phone":"+49 2163/49511",
    "sg:postcode":"41366",
    "sg:province":"Nordrhein-Westfalen",
    "wof:name":"W. Michiels Drescherei",
    "wof:placetype":"venue"
},
  "geometry": {"coordinates":[6.308595,51.183853],"type":"Point"}
}