{
  "type": "Feature",
  "properties": {
    "iso:country":"DE",
    "sg:address":"F\u00f6lsener Str. 13",
    "sg:city":"Willebadessen",
    "sg:phone":"+49 5646/204",
    "sg:postcode":"34439",
    "sg:province":"Nordrhein-Westfalen",
    "wof:name":"Norbert Klodt",
    "wof:placetype":"venue"
},
  "geometry": {"coordinates":[9.043573,51.627506],"type":"Point"}
}