{
  "type": "Feature",
  "properties": {
    "iso:country":"DE",
    "sg:address":"Hauptstr. 27",
    "sg:city":"Herdecke",
    "sg:phone":"+49 2330/129547",
    "sg:postcode":"58313",
    "sg:province":"Nordrhein-Westfalen",
    "wof:name":"Alexandra Oberw\u00f6rder",
    "wof:placetype":"venue"
},
  "geometry": {"coordinates":[7.431073,51.399448],"type":"Point"}
}