{
  "type": "Feature",
  "properties": {
    "iso:country":"DE",
    "sg:address":"Claudiusstra\u00dfe 14",
    "sg:city":"Tangstedt",
    "sg:phone":"+49 4109/9119",
    "sg:postcode":"22889",
    "sg:province":"Schleswig-Holstein",
    "wof:name":"Schwalowsky Schanbacher Bohrerschleifmaschinen",
    "wof:placetype":"venue"
},
  "geometry": {"coordinates":[10.0873975754,53.7320556641],"type":"Point"}
}