{
  "type": "Feature",
  "properties": {
    "iso:country":"DE",
    "sg:address":"S\u00fcdstr. 48",
    "sg:city":"Betheln",
    "sg:phone":"+49 5182/948347",
    "sg:postcode":"31032",
    "sg:province":"Niedersachsen",
    "wof:name":"Ts-telecom Thomas Schmidt E. K.",
    "wof:placetype":"venue"
},
  "geometry": {"coordinates":[9.794465065,52.1098823547],"type":"Point"}
}