{
  "type": "Feature",
  "properties": {
    "iso:country":"DE",
    "sg:address":"Loh\u00e4cker Str. 19",
    "sg:city":"Langenzenn",
    "sg:phone":"+49 9102/997914",
    "sg:postcode":"90579",
    "sg:province":"Bayern",
    "wof:name":"Franziska Koblischek Kobli Tours",
    "wof:placetype":"venue"
},
  "geometry": {"coordinates":[10.7621850967,49.4906845093],"type":"Point"}
}