{
  "type": "Feature",
  "properties": {
    "iso:country":"DE",
    "sg:address":"Dahlienstr. 12",
    "sg:city":"Waldkraiburg",
    "sg:phone":"+49 8638/7857",
    "sg:postcode":"84478",
    "sg:province":"Bayern",
    "wof:name":"Hammer Immobilien Gmbh",
    "wof:placetype":"venue"
},
  "geometry": {"coordinates":[12.4234485626,48.1913909912],"type":"Point"}
}