{
  "type": "Feature",
  "properties": {
    "iso:country":"DE",
    "sg:address":"Hindenburgstr. 22",
    "sg:city":"Itzehoe",
    "sg:phone":"+49 4821/952570",
    "sg:postcode":"25524",
    "sg:province":"Schleswig-Holstein",
    "wof:name":"St. Josef Kath. Altenheim",
    "wof:placetype":"venue"
},
  "geometry": {"coordinates":[9.523728,53.923],"type":"Point"}
}