{
  "type": "Feature",
  "properties": {
    "iso:country":"DE",
    "sg:address":"Waldstr. 57",
    "sg:city":"Bad D\u00fcrkheim",
    "sg:phone":"+49 6322/7716",
    "sg:postcode":"67098",
    "sg:province":"Rheinland-Pfalz",
    "wof:name":"Tv-gastst\u00e4tte Leistadt",
    "wof:placetype":"venue"
},
  "geometry": {"coordinates":[8.1543207169,49.4907417297],"type":"Point"}
}