{
  "type": "Feature",
  "properties": {
    "iso:country":"DE",
    "sg:address":"Opelstr. 2",
    "sg:city":"Konstanz",
    "sg:phone":"+49 4975/3158140",
    "sg:postcode":"78467",
    "sg:province":"Baden-W\u00fcrttemberg",
    "wof:name":"Dr. Pharmazeutische Fabrik Gmbh",
    "wof:placetype":"venue"
},
  "geometry": {"coordinates":[9.15302,47.675316],"type":"Point"}
}