{
  "type": "Feature",
  "properties": {
    "iso:country":"DE",
    "sg:address":"Klosterstr. 30",
    "sg:city":"Willebadessen",
    "sg:phone":"+49 5646/219",
    "sg:postcode":"34439",
    "sg:province":"Nordrhein-Westfalen",
    "wof:name":"M. Und H. Kurzen",
    "wof:placetype":"venue"
},
  "geometry": {"coordinates":[9.0350627899,51.6258964539],"type":"Point"}
}