{
  "type": "Feature",
  "properties": {
    "iso:country":"DE",
    "sg:address":"Br\u00fcsseler Platz 26",
    "sg:city":"K\u00f6ln",
    "sg:phone":"+49 221/518730",
    "sg:postcode":"50674",
    "sg:province":"Nordrhein-Westfalen",
    "wof:name":"M. B\u00fcchling-k\u00f6ppe",
    "wof:placetype":"venue"
},
  "geometry": {"coordinates":[6.932904,50.938904],"type":"Point"}
}