{
  "type": "Feature",
  "properties": {
    "iso:country":"DE",
    "sg:address":"Fleischhauerstr. 49",
    "sg:city":"L\u00fcbeck",
    "sg:phone":"+49 451/74521",
    "sg:postcode":"23552",
    "sg:province":"Schleswig-Holstein",
    "wof:name":"Helga Wittek",
    "wof:placetype":"venue"
},
  "geometry": {"coordinates":[10.6894340515,53.8666915894],"type":"Point"}
}