{
  "type": "Feature",
  "properties": {
    "iso:country":"DE",
    "sg:address":"Bahnhofstr. 13",
    "sg:city":"Eichwalde",
    "sg:phone":"+49 30/6758140",
    "sg:postcode":"15732",
    "sg:province":"Brandenburg",
    "wof:name":"Foto-wollermann",
    "wof:placetype":"venue"
},
  "geometry": {"coordinates":[13.6205320358,52.3739624023],"type":"Point"}
}