{
  "type": "Feature",
  "properties": {
    "iso:country":"DE",
    "sg:address":"Werderstrasse 21",
    "sg:city":"K\u00f6ln",
    "sg:phone":"+49 221/9529120",
    "sg:postcode":"50672",
    "sg:province":"Nordrhein-Westfalen",
    "wof:name":"Ruhl Studios",
    "wof:placetype":"venue"
},
  "geometry": {"coordinates":[6.939775,50.944279],"type":"Point"}
}