{
  "type": "Feature",
  "properties": {
    "iso:country":"DE",
    "sg:address":"Untere Kirchstr. 25",
    "sg:city":"Pausa",
    "sg:phone":"+49 37432/21216",
    "sg:postcode":"07952",
    "sg:province":"Sachsen",
    "wof:name":"A. Werner",
    "wof:placetype":"venue"
},
  "geometry": {"coordinates":[11.994184,50.579918],"type":"Point"}
}