{
  "type": "Feature",
  "properties": {
    "iso:country":"DE",
    "sg:address":"Bodelschwinghstr. 9",
    "sg:city":"Lengerich",
    "sg:phone":"+49 5481/81110",
    "sg:postcode":"49525",
    "sg:province":"Nordrhein-Westfalen",
    "wof:name":"Hans Gerd Unland",
    "wof:placetype":"venue"
},
  "geometry": {"coordinates":[7.847901,52.18972],"type":"Point"}
}