{
  "type": "Feature",
  "properties": {
    "iso:country":"DE",
    "sg:address":"Hauptmarkt 2",
    "sg:city":"N\u00fcrnberg",
    "sg:phone":"+49 911/204316",
    "sg:postcode":"90403",
    "sg:province":"Bayern",
    "wof:name":"Monika H\u00fcrzeler Ballettschule",
    "wof:placetype":"venue"
},
  "geometry": {"coordinates":[11.0768280029,49.4534835815],"type":"Point"}
}