{
  "type": "Feature",
  "properties": {
    "iso:country":"DE",
    "sg:address":"Olefant 16",
    "sg:city":"Bergisch Gladbach",
    "sg:postcode":"51427",
    "sg:province":"Nordrhein-Westfalen",
    "wof:name":"W & S W\u00e4rmetechnik Gmbh",
    "wof:placetype":"venue"
},
  "geometry": {"coordinates":[7.1476,50.954449],"type":"Point"}
}