{
  "type": "Feature",
  "properties": {
    "iso:country":"DE",
    "sg:address":"Altstadt 256",
    "sg:city":"Landshut",
    "sg:postcode":"84028",
    "sg:province":"Bayern",
    "wof:name":"Open Flair Gmbh",
    "wof:placetype":"venue"
},
  "geometry": {"coordinates":[12.1508865356,48.5348548889],"type":"Point"}
}