{
  "type": "Feature",
  "properties": {
    "iso:country":"DE",
    "sg:address":"Robert-Stolz-Str. 18",
    "sg:city":"Neustadt",
    "sg:phone":"+49 6321/82091",
    "sg:postcode":"67433",
    "sg:province":"Rheinland-Pfalz",
    "wof:name":"Joachim Bassimir Rechtsanwalt",
    "wof:placetype":"venue"
},
  "geometry": {"coordinates":[8.1515951157,49.3572235107],"type":"Point"}
}