{
  "type": "Feature",
  "properties": {
    "iso:country":"DE",
    "sg:address":"Helmensbergweg 18",
    "sg:city":"Esslingen",
    "sg:phone":"+49 711/353679",
    "sg:postcode":"73728",
    "sg:province":"Baden-W\u00fcrttemberg",
    "wof:name":"Wolfgang Richter Ingenieur",
    "wof:placetype":"venue"
},
  "geometry": {"coordinates":[9.3066473007,48.7482566833],"type":"Point"}
}