{
  "type": "Feature",
  "properties": {
    "iso:country":"DE",
    "sg:address":"Schulstr. 5",
    "sg:city":"Volkmarsen",
    "sg:phone":"+49 5693/305",
    "sg:postcode":"34471",
    "sg:province":"Hessen",
    "wof:name":"W. Lauhof",
    "wof:placetype":"venue"
},
  "geometry": {"coordinates":[9.111369133,51.4112281799],"type":"Point"}
}