{
  "type": "Feature",
  "properties": {
    "iso:country":"DE",
    "sg:address":"Engenser Weg 1",
    "sg:city":"Burgwedel",
    "sg:postcode":"30938",
    "sg:province":"Niedersachsen",
    "wof:name":"Karin Daume Verwaltungs Gmbh",
    "wof:placetype":"venue"
},
  "geometry": {"coordinates":[9.9176559448,52.4784393311],"type":"Point"}
}