{
  "type": "Feature",
  "properties": {
    "iso:country":"DE",
    "sg:address":"13 rue de la Bi\u00e9vre",
    "sg:city":"Rillieux-la-Pape",
    "sg:phone":"+49 4788/82492",
    "sg:postcode":"69140",
    "wof:name":"Downloadworld",
    "wof:placetype":"venue"
},
  "geometry": {"coordinates":[4.890845,45.823807],"type":"Point"}
}