{
  "type": "Feature",
  "properties": {
    "iso:country":"DE",
    "sg:address":"Alte Reifensteige 23",
    "sg:city":"Schw\u00e4bisch Hall",
    "sg:phone":"+49 791/51775",
    "sg:postcode":"74523",
    "sg:province":"Baden-W\u00fcrttemberg",
    "wof:name":"Andrea Herrmann Hebamme",
    "wof:placetype":"venue"
},
  "geometry": {"coordinates":[9.729437,49.105293],"type":"Point"}
}