{
  "type": "Feature",
  "properties": {
    "iso:country":"DE",
    "sg:address":"Strindbergstr. 33",
    "sg:city":"M\u00fcnchen",
    "sg:phone":"+49 89/886450",
    "sg:postcode":"81241",
    "sg:province":"Bayern",
    "wof:name":"Am Knie",
    "wof:placetype":"venue"
},
  "geometry": {"coordinates":[11.4656190872,48.1444549561],"type":"Point"}
}