{
  "type": "Feature",
  "properties": {
    "iso:country":"DE",
    "sg:address":"Elisabethenstr. 32",
    "sg:city":"Stuttgart",
    "sg:phone":"+49 711/635833",
    "sg:postcode":"70197",
    "sg:province":"Baden-W\u00fcrttemberg",
    "wof:name":"Kath. Pfarramt St. Elisabeth",
    "wof:placetype":"venue"
},
  "geometry": {"coordinates":[9.1556100845,48.7742843628],"type":"Point"}
}