{
  "type": "Feature",
  "properties": {
    "iso:country":"DE",
    "sg:address":"An der Trift 10",
    "sg:city":"Borchen",
    "sg:phone":"+49 5293",
    "sg:postcode":"33178",
    "sg:province":"Nordrhein-Westfalen",
    "wof:name":"Canoe Dreams - Infos Rund Um Den Kanusport",
    "wof:placetype":"venue"
},
  "geometry": {"coordinates":[8.837,51.667881],"type":"Point"}
}