{
  "type": "Feature",
  "properties": {
    "iso:country":"DE",
    "sg:address":"Preilipper Str. 8",
    "sg:city":"Rudolstadt",
    "sg:phone":"+49 3672/352101",
    "sg:postcode":"07407",
    "sg:province":"Th\u00fcringen",
    "wof:name":"Saale-flora Zierpflanzenhandel Inh. Erich Kellner",
    "wof:placetype":"venue"
},
  "geometry": {"coordinates":[11.323957,50.682693],"type":"Point"}
}