{
  "type": "Feature",
  "properties": {
    "iso:country":"DE",
    "sg:address":"Theodor-Heuss-Str. 22",
    "sg:city":"Langenhagen",
    "sg:phone":"+49 511/733342",
    "sg:postcode":"30853",
    "sg:province":"Niedersachsen",
    "wof:name":"Ideal-heizk\u00f6rper- Verkleidungen Gmbh",
    "wof:placetype":"venue"
},
  "geometry": {"coordinates":[9.7579288483,52.4508018494],"type":"Point"}
}