{
  "type": "Feature",
  "properties": {
    "iso:country":"DE",
    "sg:address":"Rheinauer Str. 13",
    "sg:city":"Jestetten",
    "sg:phone":"+49 7745/5787",
    "sg:postcode":"79798",
    "sg:province":"Baden-W\u00fcrttemberg",
    "wof:name":"A. Schur",
    "wof:placetype":"venue"
},
  "geometry": {"coordinates":[8.599223,47.655289],"type":"Point"}
}