{
  "type": "Feature",
  "properties": {
    "iso:country":"DE",
    "sg:address":"R\u00fcsselsheimer Str 22",
    "sg:city":"Frankfurt",
    "sg:phone":"+49 69/739960",
    "sg:postcode":"60326",
    "sg:province":"Hessen",
    "wof:name":"Sodexho Pass Gmbh",
    "wof:placetype":"venue"
},
  "geometry": {"coordinates":[8.620514,50.102318],"type":"Point"}
}