{
  "type": "Feature",
  "properties": {
    "iso:country":"DE",
    "sg:address":"Hinter dem Lindenberg 7",
    "sg:city":"Neustadt",
    "sg:phone":"+49 5036/611",
    "sg:postcode":"31535",
    "sg:province":"Niedersachsen",
    "wof:name":"Wilh. Vogeler",
    "wof:placetype":"venue"
},
  "geometry": {"coordinates":[9.284656,52.483055],"type":"Point"}
}