{
  "type": "Feature",
  "properties": {
    "iso:country":"DE",
    "sg:address":"Ernst-Th\u00e4lmann-Str. 10",
    "sg:city":"Unterwellenborn",
    "sg:postcode":"07333",
    "sg:province":"Th\u00fcringen",
    "wof:name":"B. Sch\u00e4ffler",
    "wof:placetype":"venue"
},
  "geometry": {"coordinates":[11.426444,50.65683],"type":"Point"}
}