{
  "type": "Feature",
  "properties": {
    "iso:country":"DE",
    "sg:address":"Kirchstr. 12",
    "sg:city":"Eschenbach",
    "sg:phone":"+49 7161/949654",
    "sg:postcode":"73107",
    "sg:province":"Baden-W\u00fcrttemberg",
    "wof:name":"Haisch Kran E. K.",
    "wof:placetype":"venue"
},
  "geometry": {"coordinates":[9.6690454483,48.6585235596],"type":"Point"}
}