{
  "type": "Feature",
  "properties": {
    "iso:country":"DE",
    "sg:address":"Salbker Chaussee 6",
    "sg:city":"Magdeburg",
    "sg:phone":"+49 391/48529",
    "sg:postcode":"39116",
    "sg:province":"Sachsen-Anhalt",
    "wof:name":"Fred Reinhardt",
    "wof:placetype":"venue"
},
  "geometry": {"coordinates":[11.58415,52.083302],"type":"Point"}
}