{
  "type": "Feature",
  "properties": {
    "iso:country":"DE",
    "sg:address":"Karl-Michel-Str. 66",
    "sg:city":"Remscheid",
    "sg:phone":"+49 2191/72530",
    "sg:postcode":"42857",
    "sg:province":"Nordrhein-Westfalen",
    "wof:name":"Puenktchen Baeren",
    "wof:placetype":"venue"
},
  "geometry": {"coordinates":[7.1795010567,51.1729621887],"type":"Point"}
}