{
  "type": "Feature",
  "properties": {
    "iso:country":"DE",
    "sg:address":"Potsdamer Str. 2",
    "sg:city":"Gro\u00df Kreutz",
    "sg:phone":"+49 33207/32257",
    "sg:postcode":"14550",
    "sg:province":"Brandenburg",
    "wof:name":"Heino Fischer",
    "wof:placetype":"venue"
},
  "geometry": {"coordinates":[12.810941,52.399082],"type":"Point"}
}