{
  "type": "Feature",
  "properties": {
    "iso:country":"DE",
    "sg:address":"Stuttgarter Str. 96",
    "sg:city":"Waiblingen",
    "sg:phone":"+49 7151/563224",
    "sg:postcode":"71332",
    "sg:province":"Baden-W\u00fcrttemberg",
    "wof:name":"Oks Ing. B\u00fcro",
    "wof:placetype":"venue"
},
  "geometry": {"coordinates":[9.3027248383,48.823841095],"type":"Point"}
}