{
  "type": "Feature",
  "properties": {
    "iso:country":"DE",
    "sg:address":"Gartenstr. 43",
    "sg:city":"Blumberg",
    "sg:phone":"+49 7702/769",
    "sg:postcode":"78176",
    "sg:province":"Baden-W\u00fcrttemberg",
    "wof:name":"Alfred Mauri",
    "wof:placetype":"venue"
},
  "geometry": {"coordinates":[8.531202,47.837284],"type":"Point"}
}