{
  "type": "Feature",
  "properties": {
    "iso:country":"DE",
    "sg:address":"Unterstadtstr. 26",
    "sg:city":"Meersburg",
    "sg:phone":"+49 7532/5480",
    "sg:postcode":"88709",
    "sg:province":"Baden-W\u00fcrttemberg",
    "wof:name":"Hotel Rauchfang",
    "wof:placetype":"venue"
},
  "geometry": {"coordinates":[9.2708120346,47.6928405762],"type":"Point"}
}