{
  "type": "Feature",
  "properties": {
    "iso:country":"DE",
    "sg:address":"Asternweg 31",
    "sg:city":"Volkach",
    "sg:phone":"+49 9381/4822",
    "sg:postcode":"97332",
    "sg:province":"Bayern",
    "wof:name":"Dachdeckerei Wilde Gmbh",
    "wof:placetype":"venue"
},
  "geometry": {"coordinates":[10.239634,49.858494],"type":"Point"}
}