{
  "type": "Feature",
  "properties": {
    "iso:country":"DE",
    "sg:address":"Entenseestr. 4",
    "sg:city":"R\u00fcckersdorf",
    "sg:phone":"+49 911/9578094",
    "sg:postcode":"90607",
    "sg:province":"Bayern",
    "wof:name":"Peter",
    "wof:placetype":"venue"
},
  "geometry": {"coordinates":[11.238011,49.493069],"type":"Point"}
}