{
  "type": "Feature",
  "properties": {
    "iso:country":"DE",
    "sg:address":"Dorfseestr. 21",
    "sg:city":"Bischberg",
    "sg:phone":"+49 951/66831",
    "sg:postcode":"96120",
    "sg:province":"Bayern",
    "wof:name":"Rainer Schw\u00e4gler Heilpraktiker",
    "wof:placetype":"venue"
},
  "geometry": {"coordinates":[10.8062868118,49.8985404968],"type":"Point"}
}