{
  "type": "Feature",
  "properties": {
    "iso:country":"DE",
    "sg:address":"Schlo\u00dfstr. 40",
    "sg:city":"Berlin",
    "sg:postcode":"12165",
    "sg:province":"Berlin",
    "wof:name":"Haberent Schweizer Viertel Prima Casa Gmbh",
    "wof:placetype":"venue"
},
  "geometry": {"coordinates":[13.319848,52.456406],"type":"Point"}
}