{
  "type": "Feature",
  "properties": {
    "iso:country":"DE",
    "sg:address":"Bismarckstr. 43",
    "sg:city":"Wangerland",
    "sg:phone":"+49 4463/5326",
    "sg:postcode":"26434",
    "sg:province":"Niedersachsen",
    "wof:name":"Ernst Leiner",
    "wof:placetype":"venue"
},
  "geometry": {"coordinates":[7.924447,53.663425],"type":"Point"}
}