{
  "type": "Feature",
  "properties": {
    "iso:country":"DE",
    "sg:address":"Stralsunder Str. 2",
    "sg:city":"Marlow",
    "sg:phone":"+49 38221/340",
    "sg:postcode":"18337",
    "sg:province":"Mecklenburg-Vorpommern",
    "wof:name":"Klaus Stiegler",
    "wof:placetype":"venue"
},
  "geometry": {"coordinates":[12.574211,54.154964],"type":"Point"}
}