{
  "type": "Feature",
  "properties": {
    "iso:country":"DE",
    "sg:address":"Im Gewerbegebiet 5",
    "sg:city":"W\u00e4schenbeuren",
    "sg:postcode":"73116",
    "sg:province":"Baden-W\u00fcrttemberg",
    "wof:name":"Euro Holz Ag",
    "wof:placetype":"venue"
},
  "geometry": {"coordinates":[9.694560051,48.7610282898],"type":"Point"}
}