{
  "type": "Feature",
  "properties": {
    "iso:country":"DE",
    "sg:address":"Eschenau 7b",
    "sg:city":"Unterthingau",
    "sg:phone":"+49 8377/974050",
    "sg:postcode":"87647",
    "sg:province":"Bayern",
    "wof:name":"S\u00fcd-west Hydraulik Gmbh",
    "wof:placetype":"venue"
},
  "geometry": {"coordinates":[10.483122,47.789925],"type":"Point"}
}