{
  "type": "Feature",
  "properties": {
    "iso:country":"DE",
    "sg:address":"Ploggenseering 7",
    "sg:city":"Grevesm\u00fchlen",
    "sg:phone":"+49 3881/711612",
    "sg:postcode":"23936",
    "sg:province":"Mecklenburg-Vorpommern",
    "wof:name":"Telekom Vo\u00df & Partner",
    "wof:placetype":"venue"
},
  "geometry": {"coordinates":[11.1923847198,53.8675231934],"type":"Point"}
}