{
  "type": "Feature",
  "properties": {
    "iso:country":"DE",
    "sg:address":"M\u00fchlweg 12",
    "sg:city":"Weinolsheim",
    "sg:phone":"+49 6249/2606",
    "sg:postcode":"55278",
    "sg:province":"Rheinland-Pfalz",
    "wof:name":"H. J. Keller",
    "wof:placetype":"venue"
},
  "geometry": {"coordinates":[8.270357132,49.8170623779],"type":"Point"}
}