{
  "type": "Feature",
  "properties": {
    "iso:country":"DE",
    "sg:address":"Bonhoefferstr. 5",
    "sg:city":"Trier",
    "sg:phone":"+49 651/32900",
    "sg:postcode":"54296",
    "sg:province":"Rheinland-Pfalz",
    "wof:name":"H.-k. Schmitt Bildhauer",
    "wof:placetype":"venue"
},
  "geometry": {"coordinates":[6.660188,49.728748],"type":"Point"}
}