{
  "type": "Feature",
  "properties": {
    "iso:country":"DE",
    "sg:address":"Maximilianstr. 17",
    "sg:city":"Bayreuth",
    "sg:phone":"+49 921/64944",
    "sg:postcode":"95444",
    "sg:province":"Bayern",
    "wof:name":"Heinrich Hensel Gmbh",
    "wof:placetype":"venue"
},
  "geometry": {"coordinates":[11.576147,49.943783],"type":"Point"}
}