{
  "type": "Feature",
  "properties": {
    "iso:country":"DE",
    "sg:address":"Mathias-Kerz-Str. 27",
    "sg:city":"Mainz",
    "sg:phone":"+49 6131/504060",
    "sg:postcode":"55129",
    "sg:province":"Rheinland-Pfalz",
    "wof:name":"Peter Fr\u00e4dert Heilpr\u00e4ktiker",
    "wof:placetype":"venue"
},
  "geometry": {"coordinates":[8.2834320068,49.9638938904],"type":"Point"}
}