{
  "type": "Feature",
  "properties": {
    "iso:country":"DE",
    "sg:address":"Am Roten Berg 16",
    "sg:city":"Obersontheim",
    "sg:phone":"+49 7973/6806",
    "sg:postcode":"74423",
    "sg:province":"Baden-W\u00fcrttemberg",
    "wof:name":"Christa Setzer",
    "wof:placetype":"venue"
},
  "geometry": {"coordinates":[9.8318567276,49.0555343628],"type":"Point"}
}