{
  "type": "Feature",
  "properties": {
    "iso:country":"DE",
    "sg:address":"Wrangellstr. 14 a",
    "sg:city":"Stuttgart",
    "sg:phone":"+49 711/454763",
    "sg:postcode":"70599",
    "sg:province":"Baden-W\u00fcrttemberg",
    "wof:name":"R\u00fcdiger Stroh",
    "wof:placetype":"venue"
},
  "geometry": {"coordinates":[9.2032623291,48.7132148743],"type":"Point"}
}