{
  "type": "Feature",
  "properties": {
    "iso:country":"DE",
    "sg:address":"Wattstr. 17",
    "sg:city":"Stuttgart",
    "sg:phone":"+49 711/8261176",
    "sg:postcode":"70435",
    "sg:province":"Baden-W\u00fcrttemberg",
    "wof:name":"J\u00fcrgen Kettel Heizung & Sanit\u00e4r Gmbh",
    "wof:placetype":"venue"
},
  "geometry": {"coordinates":[9.164201,48.82872],"type":"Point"}
}