{
  "type": "Feature",
  "properties": {
    "iso:country":"DE",
    "sg:address":"Maybachstr. 4",
    "sg:city":"Dreieich",
    "sg:phone":"+49 6103/34009",
    "sg:postcode":"63303",
    "sg:province":"Hessen",
    "wof:name":"E. L. Luther Gmbh & Co. Kg",
    "wof:placetype":"venue"
},
  "geometry": {"coordinates":[8.6963195801,50.028629303],"type":"Point"}
}