{
  "type": "Feature",
  "properties": {
    "iso:country":"DE",
    "sg:address":"Mommsenstr. 150",
    "sg:city":"K\u00f6ln",
    "sg:phone":"+49 221/9439730",
    "sg:postcode":"50935",
    "sg:province":"Nordrhein-Westfalen",
    "wof:name":"Mag Marketing Und Absatz F\u00fcr Grundbesitz Gmbh",
    "wof:placetype":"venue"
},
  "geometry": {"coordinates":[6.90323,50.924911],"type":"Point"}
}