{
  "type": "Feature",
  "properties": {
    "iso:country":"DE",
    "sg:address":"Rhauderwieke 28",
    "sg:city":"Rhauderfehn",
    "sg:phone":"+49 4952/81786",
    "sg:postcode":"26817",
    "sg:province":"Niedersachsen",
    "wof:name":"Mtm-bauelemente- Vertriebs Gmbh",
    "wof:placetype":"venue"
},
  "geometry": {"coordinates":[7.570612,53.138504],"type":"Point"}
}