{
  "type": "Feature",
  "properties": {
    "iso:country":"DE",
    "sg:address":"An der Hauptwache 7",
    "sg:city":"Frankfurt",
    "sg:phone":"+49 69/284916",
    "sg:postcode":"60313",
    "sg:province":"Hessen",
    "wof:name":"Reinhard Hein Rechtsanwalt",
    "wof:placetype":"venue"
},
  "geometry": {"coordinates":[8.6783504486,50.1140785217],"type":"Point"}
}