{
  "type": "Feature",
  "properties": {
    "iso:country":"DE",
    "sg:address":"Sonnenstr. 6",
    "sg:city":"Schwabhausen",
    "sg:phone":"+49 8138/8705",
    "sg:postcode":"85247",
    "sg:province":"Bayern",
    "wof:name":"Schlosser",
    "wof:placetype":"venue"
},
  "geometry": {"coordinates":[11.3497867584,48.3076400757],"type":"Point"}
}