{
  "type": "Feature",
  "properties": {
    "iso:country":"DE",
    "sg:address":"Schanzenstr. 10",
    "sg:city":"Pirmasens",
    "sg:postcode":"66955",
    "sg:province":"Rheinland-Pfalz",
    "wof:name":"R\u00f6hm Fliesenverlegungs Gmbh",
    "wof:placetype":"venue"
},
  "geometry": {"coordinates":[7.6021089554,49.1943435669],"type":"Point"}
}