{
  "type": "Feature",
  "properties": {
    "iso:country":"DE",
    "sg:address":"An der Schmiede 10",
    "sg:city":"Rosengarten",
    "sg:phone":"+49 4108/8251",
    "sg:postcode":"21224",
    "sg:province":"Niedersachsen",
    "wof:name":"Egon Kn\u00fcppel Steuerberater",
    "wof:placetype":"venue"
},
  "geometry": {"coordinates":[9.9005937576,53.3850479126],"type":"Point"}
}