{
  "type": "Feature",
  "properties": {
    "iso:country":"DE",
    "sg:address":"Bleichstr. 20",
    "sg:city":"Greifswald",
    "sg:phone":"+49 3834/897226",
    "sg:postcode":"17489",
    "sg:province":"Mecklenburg-Vorpommern",
    "wof:name":"Hanse Bau- Und Sanierungsgesellschaft Mbh",
    "wof:placetype":"venue"
},
  "geometry": {"coordinates":[13.385796,54.091412],"type":"Point"}
}