{
  "type": "Feature",
  "properties": {
    "iso:country":"DE",
    "sg:address":"Achternstr. 21",
    "sg:city":"Oldenburg",
    "sg:phone":"+49 441/219140",
    "sg:postcode":"26122",
    "sg:province":"Niedersachsen",
    "wof:name":"Laserzentrum Dermatologie Oldenburg Gmbh Co. Kg",
    "wof:placetype":"venue"
},
  "geometry": {"coordinates":[8.215301,53.138687],"type":"Point"}
}