{
  "type": "Feature",
  "properties": {
    "iso:country":"DE",
    "sg:address":"H\u00f6llbergstr. 25",
    "sg:city":"M\u00fcllheim",
    "sg:phone":"+49 7631/13499",
    "sg:postcode":"79379",
    "sg:province":"Baden-W\u00fcrttemberg",
    "wof:name":"Ev. Pfarramt Gem. H\u00fcgelheim",
    "wof:placetype":"venue"
},
  "geometry": {"coordinates":[7.6244997978,47.8300666809],"type":"Point"}
}