{
  "type": "Feature",
  "properties": {
    "iso:country":"DE",
    "sg:address":"Glauchauer Str. 13",
    "sg:city":"St. Egidien",
    "sg:phone":"+49 3763/15240",
    "sg:postcode":"09356",
    "sg:province":"Sachsen",
    "wof:name":"Landgasthof Und Pension",
    "wof:placetype":"venue"
},
  "geometry": {"coordinates":[12.6153078079,50.785369873],"type":"Point"}
}