{
  "type": "Feature",
  "properties": {
    "iso:country":"DE",
    "sg:address":"Gottlieb-Daimler-Str. 15",
    "sg:city":"Bad W\u00f6rishofen",
    "sg:phone":"+49 8247/33021",
    "sg:postcode":"86825",
    "sg:province":"Bayern",
    "wof:name":"Dinea Gastronomie Gmbh",
    "wof:placetype":"venue"
},
  "geometry": {"coordinates":[10.598891,48.021946],"type":"Point"}
}