{
  "type": "Feature",
  "properties": {
    "iso:country":"DE",
    "sg:address":"Buttmannstr. 10",
    "sg:city":"Berlin",
    "sg:phone":"+49 30/4628090",
    "sg:postcode":"13357",
    "sg:province":"Berlin",
    "wof:name":"Thomas Warmbein",
    "wof:placetype":"venue"
},
  "geometry": {"coordinates":[13.3776416779,52.5513687134],"type":"Point"}
}