{
  "type": "Feature",
  "properties": {
    "iso:country":"DE",
    "sg:address":"Str\u00f6bitzer Schulstr. 8",
    "sg:city":"Cottbus",
    "sg:phone":"+49 355/790009",
    "sg:postcode":"03046",
    "sg:province":"Brandenburg",
    "wof:name":"Walther Rohrleitungsbau Gmbh",
    "wof:placetype":"venue"
},
  "geometry": {"coordinates":[14.3024091721,51.7528152466],"type":"Point"}
}