{
  "type": "Feature",
  "properties": {
    "iso:country":"DE",
    "sg:address":"31675",
    "sg:city":"B\u00fcckeburg",
    "sg:phone":"+49 5722/4251",
    "sg:postcode":"31675",
    "sg:province":"Niedersachsen",
    "wof:name":"Deutsche Bahn Ag",
    "wof:placetype":"venue"
},
  "geometry": {"coordinates":[9.0316400528,52.2930412292],"type":"Point"}
}