{
  "type": "Feature",
  "properties": {
    "iso:country":"DE",
    "sg:address":"Unterer Markt 30",
    "sg:city":"Kemnath",
    "sg:phone":"+49 9642/2487",
    "sg:postcode":"95478",
    "sg:province":"Bayern",
    "wof:name":"Josef Reichenberger",
    "wof:placetype":"venue"
},
  "geometry": {"coordinates":[11.95129,49.864372],"type":"Point"}
}