{
  "type": "Feature",
  "properties": {
    "iso:country":"DE",
    "sg:address":"Maarende 17",
    "sg:city":"Linnich",
    "sg:phone":"+49 2462/6374",
    "sg:postcode":"52441",
    "sg:province":"Nordrhein-Westfalen",
    "wof:name":"Hans Meuser",
    "wof:placetype":"venue"
},
  "geometry": {"coordinates":[6.2185292244,50.9622192383],"type":"Point"}
}