{
  "type": "Feature",
  "properties": {
    "iso:country":"DE",
    "sg:address":"Geiersgraben 2-6",
    "sg:city":"Kaifenheim",
    "sg:postcode":"56761",
    "sg:province":"Rheinland-Pfalz",
    "wof:name":"Josef Wilhelmy",
    "wof:placetype":"venue"
},
  "geometry": {"coordinates":[7.2229361534,50.2463684082],"type":"Point"}
}