{
  "type": "Feature",
  "properties": {
    "iso:country":"DE",
    "sg:address":"Wilhelmstr. 24",
    "sg:city":"Ebersbach",
    "sg:phone":"+49 7163/3305",
    "sg:postcode":"73061",
    "sg:province":"Baden-W\u00fcrttemberg",
    "wof:name":"Manfred Merkle",
    "wof:placetype":"venue"
},
  "geometry": {"coordinates":[9.5293998718,48.7162208557],"type":"Point"}
}