{
  "type": "Feature",
  "properties": {
    "iso:country":"DE",
    "sg:address":"Pischekstr 17a",
    "sg:city":"Stuttgart",
    "sg:phone":"+49 711/242551",
    "sg:postcode":"70184",
    "sg:province":"Baden-W\u00fcrttemberg",
    "wof:name":"Service-werbung Dr. Kummer + Doll Gmbh",
    "wof:placetype":"venue"
},
  "geometry": {"coordinates":[9.19425,48.767807],"type":"Point"}
}