{
  "type": "Feature",
  "properties": {
    "iso:country":"DE",
    "sg:address":"Bergwiese 7",
    "sg:city":"Neunkirchen-Seelscheid",
    "sg:phone":"+49 2247/971256",
    "sg:postcode":"53819",
    "sg:province":"Nordrhein-Westfalen",
    "wof:name":"Spohr Ingenieur",
    "wof:placetype":"venue"
},
  "geometry": {"coordinates":[7.3326969147,50.8716964722],"type":"Point"}
}