{
  "type": "Feature",
  "properties": {
    "iso:country":"DE",
    "sg:address":"Am Sch\u00f6nenberg 14",
    "sg:city":"Lenzkirch",
    "sg:phone":"+49 7653/1281",
    "sg:postcode":"79853",
    "sg:province":"Baden-W\u00fcrttemberg",
    "wof:name":"Power Sound Machine Veranstaltungstechnik - Messe",
    "wof:placetype":"venue"
},
  "geometry": {"coordinates":[8.226047,47.859303],"type":"Point"}
}