{
  "type": "Feature",
  "properties": {
    "iso:country":"DE",
    "sg:address":"Zeisigweg 2",
    "sg:city":"W\u00fcrselen",
    "sg:phone":"+49 2405/83918",
    "sg:postcode":"52146",
    "sg:province":"Nordrhein-Westfalen",
    "wof:name":"Z. Ganic",
    "wof:placetype":"venue"
},
  "geometry": {"coordinates":[6.121279,50.821224],"type":"Point"}
}