{
  "type": "Feature",
  "properties": {
    "iso:country":"DE",
    "sg:address":"Hohensteiner Str. 135",
    "sg:city":"Callenberg",
    "sg:postcode":"09337",
    "sg:province":"Sachsen",
    "wof:name":"Chs-immobilienverwaltungs-gmbh",
    "wof:placetype":"venue"
},
  "geometry": {"coordinates":[12.7050485611,50.8292541504],"type":"Point"}
}