{
  "type": "Feature",
  "properties": {
    "iso:country":"DE",
    "sg:address":"Elsteraue 3",
    "sg:city":"Bad K\u00f6stritz",
    "sg:phone":"+49 36605/84002",
    "sg:postcode":"07586",
    "sg:province":"Th\u00fcringen",
    "wof:name":"V. Tabaczek Immobilienmakler",
    "wof:placetype":"venue"
},
  "geometry": {"coordinates":[12.0213317871,50.9285964966],"type":"Point"}
}