{
  "type": "Feature",
  "properties": {
    "iso:country":"DE",
    "sg:address":"Tregenstr. 6",
    "sg:city":"L\u00f6ffingen",
    "sg:phone":"+49 7707/318",
    "sg:postcode":"79843",
    "sg:province":"Baden-W\u00fcrttemberg",
    "wof:name":"Pension R\u00f6mischer Hof",
    "wof:placetype":"venue"
},
  "geometry": {"coordinates":[8.405921936,47.8829994202],"type":"Point"}
}