{
  "type": "Feature",
  "properties": {
    "iso:country":"DE",
    "sg:address":"Vogelstr. 11",
    "sg:city":"Puschendorf",
    "sg:phone":"+49 9101/1338",
    "sg:postcode":"90617",
    "sg:province":"Bayern",
    "wof:name":"Bertram Schacher",
    "wof:placetype":"venue"
},
  "geometry": {"coordinates":[10.8300218582,49.5266647339],"type":"Point"}
}