{
  "type": "Feature",
  "properties": {
    "iso:country":"DE",
    "sg:address":"Kirchplatz 2",
    "sg:city":"Wolfach",
    "sg:phone":"+49 7834/6742",
    "sg:postcode":"77709",
    "sg:province":"Baden-W\u00fcrttemberg",
    "wof:name":"Sozialstation Kinzig-gutachtal",
    "wof:placetype":"venue"
},
  "geometry": {"coordinates":[8.222399,48.298805],"type":"Point"}
}