{
  "type": "Feature",
  "properties": {
    "iso:country":"DE",
    "sg:address":"Furschweilerstr. 51",
    "sg:city":"Namborn",
    "sg:phone":"+49 6857/293",
    "sg:postcode":"66640",
    "sg:province":"Saarland",
    "wof:name":"Hans Berwanger Architekt",
    "wof:placetype":"venue"
},
  "geometry": {"coordinates":[7.166893,49.51503],"type":"Point"}
}