{
  "type": "Feature",
  "properties": {
    "iso:country":"DE",
    "sg:address":"Eislebener Str. 13",
    "sg:city":"Berlin",
    "sg:postcode":"10789",
    "sg:province":"Berlin",
    "wof:name":"Touristik-unternehmens- Beratung Oliver Eisele",
    "wof:placetype":"venue"
},
  "geometry": {"coordinates":[13.3334970474,52.5008087158],"type":"Point"}
}