{
  "type": "Feature",
  "properties": {
    "iso:country":"DE",
    "sg:address":"Hauptstr. 114",
    "sg:city":"Meckesheim",
    "sg:postcode":"74909",
    "sg:province":"Baden-W\u00fcrttemberg",
    "wof:name":"Bepomed Gmbh",
    "wof:placetype":"venue"
},
  "geometry": {"coordinates":[8.8467712402,49.3326835632],"type":"Point"}
}