{
  "type": "Feature",
  "properties": {
    "iso:country":"DE",
    "sg:address":"Masurenstr. 1 a",
    "sg:city":"Berlin",
    "sg:phone":"+49 30/4726356",
    "sg:postcode":"13189",
    "sg:province":"Berlin",
    "wof:name":"Horst Albrecht",
    "wof:placetype":"venue"
},
  "geometry": {"coordinates":[13.412281,52.562843],"type":"Point"}
}