{
  "type": "Feature",
  "properties": {
    "iso:country":"DE",
    "sg:address":"Goslarer Platz 5",
    "sg:city":"Berlin",
    "sg:phone":"+49 30/3457864",
    "sg:postcode":"10589",
    "sg:province":"Berlin",
    "wof:name":"B\u00fcrgerbr\u00e4u-lokal-wat",
    "wof:placetype":"venue"
},
  "geometry": {"coordinates":[13.3132066727,52.5248451233],"type":"Point"}
}