{
  "type": "Feature",
  "properties": {
    "iso:country":"DE",
    "sg:address":"Augrund 2",
    "sg:city":"Sinsheim",
    "sg:phone":"+49 7261/2188",
    "sg:postcode":"74889",
    "sg:province":"Baden-W\u00fcrttemberg",
    "wof:name":"Restaurant Villa Italia",
    "wof:placetype":"venue"
},
  "geometry": {"coordinates":[8.8404712677,49.2458343506],"type":"Point"}
}