{
  "type": "Feature",
  "properties": {
    "iso:country":"DE",
    "sg:address":"Am Sch\u00f6nenkamp 110",
    "sg:city":"D\u00fcsseldorf",
    "sg:phone":"+49 211/7498225",
    "sg:postcode":"40599",
    "sg:province":"Nordrhein-Westfalen",
    "wof:name":"Bertram Lenniger Masseur",
    "wof:placetype":"venue"
},
  "geometry": {"coordinates":[6.871826,51.182499],"type":"Point"}
}