{
  "type": "Feature",
  "properties": {
    "iso:country":"DE",
    "sg:address":"Kreisstr. 53",
    "sg:city":"Witten",
    "sg:phone":"+49 2302/428030",
    "sg:postcode":"58453",
    "sg:province":"Nordrhein-Westfalen",
    "wof:name":"Wende Witten Gmbh & Co. Kg",
    "wof:placetype":"venue"
},
  "geometry": {"coordinates":[7.3876,51.448616],"type":"Point"}
}