{
  "type": "Feature",
  "properties": {
    "iso:country":"DE",
    "sg:address":"G\u00e4rtnerstr. 29",
    "sg:city":"Wedel",
    "sg:phone":"+49 4103/83560",
    "sg:postcode":"22880",
    "sg:province":"Schleswig-Holstein",
    "wof:name":"Franz Diercks",
    "wof:placetype":"venue"
},
  "geometry": {"coordinates":[9.69715,53.587723],"type":"Point"}
}