{
  "type": "Feature",
  "properties": {
    "iso:country":"DE",
    "sg:address":"Marktstr. 16",
    "sg:city":"Weimar",
    "sg:phone":"+49 3643/202188",
    "sg:postcode":"99423",
    "sg:province":"Th\u00fcringen",
    "wof:name":"Foto City Color",
    "wof:placetype":"venue"
},
  "geometry": {"coordinates":[11.3281869888,50.9799308777],"type":"Point"}
}