{
  "type": "Feature",
  "properties": {
    "iso:country":"DE",
    "sg:address":"Im Tal 3",
    "sg:city":"\u00dchlingen-Birkendorf",
    "sg:phone":"+49 7743/229",
    "sg:postcode":"79777",
    "sg:province":"Baden-W\u00fcrttemberg",
    "wof:name":"Braun Holzwerk Inh. Josef Hermann Braun",
    "wof:placetype":"venue"
},
  "geometry": {"coordinates":[8.3127765656,47.7442970276],"type":"Point"}
}