{
  "type": "Feature",
  "properties": {
    "iso:country":"DE",
    "sg:address":"Richolfstr. 33",
    "sg:city":"Wertheim",
    "sg:phone":"+49 9342/23866",
    "sg:postcode":"97877",
    "sg:province":"Baden-W\u00fcrttemberg",
    "wof:name":"T. Gress",
    "wof:placetype":"venue"
},
  "geometry": {"coordinates":[9.5343961716,49.7282562256],"type":"Point"}
}