{
  "type": "Feature",
  "properties": {
    "iso:country":"DE",
    "sg:address":"Herzogs\u00e4ge 2",
    "sg:city":"Prackenbach",
    "sg:phone":"+49 9942/8583",
    "sg:postcode":"94267",
    "sg:province":"Bayern",
    "wof:name":"S\u00e4gewerk Kopp Inh. Sonja Eidenschink",
    "wof:placetype":"venue"
},
  "geometry": {"coordinates":[12.8156089783,49.0684509277],"type":"Point"}
}