{
  "type": "Feature",
  "properties": {
    "iso:country":"DE",
    "sg:address":"Litzelhorststra\u00dfe 51",
    "sg:city":"Herxheim",
    "sg:postcode":"76863",
    "sg:province":"Rheinland-Pfalz",
    "wof:name":"Elmar Weiller, B\u00fcrgermeister Von Herxheim",
    "wof:placetype":"venue"
},
  "geometry": {"coordinates":[8.218044,49.14315],"type":"Point"}
}