{
  "type": "Feature",
  "properties": {
    "iso:country":"DE",
    "sg:address":"Salmstr. 8",
    "sg:city":"Kl\u00fcsserath",
    "sg:phone":"+49 6507/93510",
    "sg:postcode":"54340",
    "sg:province":"Rheinland-Pfalz",
    "wof:name":"Hotel-restaurant Zum Rebstock Gmbh",
    "wof:placetype":"venue"
},
  "geometry": {"coordinates":[6.8444619179,49.8422546387],"type":"Point"}
}