{
  "type": "Feature",
  "properties": {
    "iso:country":"DE",
    "sg:address":"Ballindamm 17",
    "sg:city":"Hamburg",
    "sg:postcode":"20095",
    "sg:province":"Hamburg",
    "wof:name":"Hanseatic Schiffahrt Beteiligungsgesellschaft Mbh",
    "wof:placetype":"venue"
},
  "geometry": {"coordinates":[9.998526,53.553928],"type":"Point"}
}