{
  "type": "Feature",
  "properties": {
    "iso:country":"DE",
    "sg:address":"Bahnhofstr. 59",
    "sg:city":"Groitzsch",
    "sg:postcode":"04539",
    "sg:province":"Sachsen",
    "wof:name":"Haus Bau G & P Gmbh",
    "wof:placetype":"venue"
},
  "geometry": {"coordinates":[12.286825,51.15593],"type":"Point"}
}