{
  "type": "Feature",
  "properties": {
    "iso:country":"DE",
    "sg:address":"Klettwitzer Str 9",
    "sg:city":"Annah\u00fctte",
    "sg:phone":"+49 35754/9512",
    "sg:postcode":"01994",
    "sg:province":"Brandenburg",
    "wof:name":"Ackermann Bauelemente Gmbh",
    "wof:placetype":"venue"
},
  "geometry": {"coordinates":[13.8967323303,51.5591316223],"type":"Point"}
}