{
  "type": "Feature",
  "properties": {
    "iso:country":"DE",
    "sg:address":"Zei\u00dfstr. 9",
    "sg:city":"Ditzingen",
    "sg:phone":"+49 7156/17132",
    "sg:postcode":"71254",
    "sg:province":"Baden-W\u00fcrttemberg",
    "wof:name":"Ramo Import & Export Gmbh",
    "wof:placetype":"venue"
},
  "geometry": {"coordinates":[9.0807056427,48.8194313049],"type":"Point"}
}