{
  "type": "Feature",
  "properties": {
    "iso:country":"DE",
    "sg:address":"Ostlandstr. 28",
    "sg:city":"Cadolzburg",
    "sg:phone":"+49 9103/7667",
    "sg:postcode":"90556",
    "sg:province":"Bayern",
    "wof:name":"N. K. G. Sondermaschinenbau Gmbh",
    "wof:placetype":"venue"
},
  "geometry": {"coordinates":[10.863381,49.462349],"type":"Point"}
}