{
  "type": "Feature",
  "properties": {
    "iso:country":"DE",
    "sg:address":"Schwanenstr. 16a",
    "sg:city":"Bocholt",
    "sg:phone":"+49 2871/44552",
    "sg:postcode":"46399",
    "sg:province":"Nordrhein-Westfalen",
    "wof:name":"Master Music Handels- Und Verwaltungs Gmbh",
    "wof:placetype":"venue"
},
  "geometry": {"coordinates":[6.6010990143,51.8395996094],"type":"Point"}
}