{
  "type": "Feature",
  "properties": {
    "iso:country":"DE",
    "sg:address":"L\u00fcnener Str. 31",
    "sg:city":"Hamm",
    "sg:phone":"+49 2381/438443",
    "sg:postcode":"59077",
    "sg:province":"Nordrhein-Westfalen",
    "wof:name":"Sievering Agrarhandels Gmbh",
    "wof:placetype":"venue"
},
  "geometry": {"coordinates":[7.725556,51.662266],"type":"Point"}
}