{
  "type": "Feature",
  "properties": {
    "iso:country":"DE",
    "sg:address":"Kegelbann 26",
    "sg:city":"Lahnau",
    "sg:phone":"+49 6441/96111",
    "sg:postcode":"35633",
    "sg:province":"Hessen",
    "wof:name":"G\u00fcnther Stawinski Finanzberater",
    "wof:placetype":"venue"
},
  "geometry": {"coordinates":[8.5817699432,50.5778656006],"type":"Point"}
}