{
  "type": "Feature",
  "properties": {
    "iso:country":"DE",
    "sg:address":"Gro\u00dfes St\u00fcck 85",
    "sg:city":"Ense",
    "sg:postcode":"59469",
    "sg:province":"Nordrhein-Westfalen",
    "wof:name":"Szerement Mineral\u00f6lvertrieb & Transport Gmbh",
    "wof:placetype":"venue"
},
  "geometry": {"coordinates":[8.0057897568,51.4946708679],"type":"Point"}
}