{
  "type": "Feature",
  "properties": {
    "iso:country":"DE",
    "sg:address":"Blutstr. 24",
    "sg:city":"Parchim",
    "sg:phone":"+49 3871/212545",
    "sg:postcode":"19370",
    "sg:province":"Mecklenburg-Vorpommern",
    "wof:name":"Dietrich Ahnsorge",
    "wof:placetype":"venue"
},
  "geometry": {"coordinates":[11.846469,53.427418],"type":"Point"}
}