{
  "type": "Feature",
  "properties": {
    "iso:country":"DE",
    "sg:address":"Schnurgasse 5",
    "sg:city":"K\u00fcnzelsau",
    "sg:phone":"+49 7940/8304",
    "sg:postcode":"74653",
    "sg:province":"Baden-W\u00fcrttemberg",
    "wof:name":"Pension Engel",
    "wof:placetype":"venue"
},
  "geometry": {"coordinates":[9.6898136139,49.2788963318],"type":"Point"}
}