{
  "type": "Feature",
  "properties": {
    "iso:country":"DE",
    "sg:address":"Dieselstr. 14",
    "sg:city":"Ober-M\u00f6rlen",
    "sg:phone":"+49 4960/025111",
    "sg:postcode":"61239",
    "sg:province":"Hessen",
    "wof:name":"Bruno Geyer Werkzeugbau",
    "wof:placetype":"venue"
},
  "geometry": {"coordinates":[8.6933898926,50.3630905151],"type":"Point"}
}