{
  "type": "Feature",
  "properties": {
    "iso:country":"DE",
    "sg:address":"Im Handschuhteich 27",
    "sg:city":"Hinterweidenthal",
    "sg:phone":"+49 6396/371",
    "sg:postcode":"66999",
    "sg:province":"Rheinland-Pfalz",
    "wof:name":"Cafe U. Pilsstube Am Spielpark",
    "wof:placetype":"venue"
},
  "geometry": {"coordinates":[7.748589,49.196545],"type":"Point"}
}