{
  "type": "Feature",
  "properties": {
    "iso:country":"DE",
    "sg:address":"Lange Gasse 12",
    "sg:city":"Zw\u00f6nitz",
    "sg:phone":"+49 37754/2722",
    "sg:postcode":"08297",
    "sg:province":"Sachsen",
    "wof:name":"M. Viehweger",
    "wof:placetype":"venue"
},
  "geometry": {"coordinates":[12.8112325668,50.630153656],"type":"Point"}
}