{
  "type": "Feature",
  "properties": {
    "iso:country":"DE",
    "sg:address":"D\u00fcrnauer Weg 29",
    "sg:city":"Stuttgart",
    "sg:postcode":"70599",
    "sg:province":"Baden-W\u00fcrttemberg",
    "wof:name":"Hipo U. Software Gmbh",
    "wof:placetype":"venue"
},
  "geometry": {"coordinates":[9.2025642395,48.7252845764],"type":"Point"}
}