{
  "type": "Feature",
  "properties": {
    "iso:country":"DE",
    "sg:address":"Waldstr. 27",
    "sg:city":"Erlensee",
    "sg:phone":"+49 6183/75988",
    "sg:postcode":"63526",
    "sg:province":"Hessen",
    "wof:name":"E. Heeg",
    "wof:placetype":"venue"
},
  "geometry": {"coordinates":[8.9792470932,50.1597938538],"type":"Point"}
}