{
  "type": "Feature",
  "properties": {
    "iso:country":"DE",
    "sg:address":"Pfarrer-Egger-Str. 3",
    "sg:city":"Hohenkammer",
    "sg:phone":"+49 8137/8379",
    "sg:postcode":"85411",
    "sg:province":"Bayern",
    "wof:name":"Johann Bernhart Gmbh",
    "wof:placetype":"venue"
},
  "geometry": {"coordinates":[11.52522,48.425457],"type":"Point"}
}