{
  "type": "Feature",
  "properties": {
    "iso:country":"DE",
    "sg:address":"Theodor-Storm-Str. 43 c",
    "sg:city":"Bad Segeberg",
    "sg:phone":"+49 4551/2419",
    "sg:postcode":"23795",
    "sg:province":"Schleswig-Holstein",
    "wof:name":"Michael Blum",
    "wof:placetype":"venue"
},
  "geometry": {"coordinates":[10.296187,53.9328],"type":"Point"}
}