{
  "type": "Feature",
  "properties": {
    "iso:country":"DE",
    "sg:address":"Eichwaldstr 25",
    "sg:city":"Kassel",
    "sg:phone":"+49 561/56660",
    "sg:postcode":"34123",
    "sg:province":"Hessen",
    "wof:name":"Buch- Und Offsetdruckerei Helmuth Melzer",
    "wof:placetype":"venue"
},
  "geometry": {"coordinates":[9.530328,51.309727],"type":"Point"}
}