{
  "type": "Feature",
  "properties": {
    "iso:country":"DE",
    "sg:address":"Poststr. 33",
    "sg:city":"Burweg",
    "sg:phone":"+49 4144/5236",
    "sg:postcode":"21709",
    "sg:province":"Niedersachsen",
    "wof:name":"Volksbank Himmelpforten Zweign",
    "wof:placetype":"venue"
},
  "geometry": {"coordinates":[9.306189,53.613789],"type":"Point"}
}