{
  "type": "Feature",
  "properties": {
    "iso:country":"DE",
    "sg:address":"Solgerstr. 17",
    "sg:city":"N\u00fcrnberg",
    "sg:phone":"+49 911/270515",
    "sg:postcode":"90429",
    "sg:province":"Bayern",
    "wof:name":"O. Heinl",
    "wof:placetype":"venue"
},
  "geometry": {"coordinates":[11.0624551773,49.4525718689],"type":"Point"}
}