{
  "type": "Feature",
  "properties": {
    "iso:country":"DE",
    "sg:address":"Stiftstr. 5a",
    "sg:city":"Bocholt",
    "sg:phone":"+49 2871/43809",
    "sg:postcode":"46395",
    "sg:province":"Nordrhein-Westfalen",
    "wof:name":"Josef Stahl",
    "wof:placetype":"venue"
},
  "geometry": {"coordinates":[6.594045,51.835697],"type":"Point"}
}