{
  "type": "Feature",
  "properties": {
    "iso:country":"DE",
    "sg:address":"Lierbachstr.",
    "sg:city":"Oppenau",
    "sg:phone":"+49 7804/3181",
    "sg:postcode":"77728",
    "sg:province":"Baden-W\u00fcrttemberg",
    "wof:name":"Maierhof",
    "wof:placetype":"venue"
},
  "geometry": {"coordinates":[8.186914444,48.4944496155],"type":"Point"}
}