{
  "type": "Feature",
  "properties": {
    "iso:country":"DE",
    "sg:address":"Bernardstrasse 14",
    "sg:city":"Offenbach",
    "sg:phone":"+49 69",
    "sg:postcode":"63067",
    "sg:province":"Hessen",
    "wof:name":"Faub Fit F\u00fcr Ausbildung Und Beruf",
    "wof:placetype":"venue"
},
  "geometry": {"coordinates":[8.75605,50.107841],"type":"Point"}
}