{
  "type": "Feature",
  "properties": {
    "iso:country":"DE",
    "sg:address":"Dorfstr. 31",
    "sg:city":"Bramstedt",
    "sg:phone":"+49 4746/6061",
    "sg:postcode":"27628",
    "sg:province":"Niedersachsen",
    "wof:name":"Gasthof Bauernsch\u00e4nke",
    "wof:placetype":"venue"
},
  "geometry": {"coordinates":[8.6921043396,53.3662834167],"type":"Point"}
}