{
  "type": "Feature",
  "properties": {
    "iso:country":"DE",
    "sg:address":"Melsunger Str. 28",
    "sg:city":"Fuldabr\u00fcck",
    "sg:phone":"+49 5665/40367",
    "sg:postcode":"34277",
    "sg:province":"Hessen",
    "wof:name":"S\u00f6hrehof",
    "wof:placetype":"venue"
},
  "geometry": {"coordinates":[9.499710083,51.2645454407],"type":"Point"}
}