{
  "type": "Feature",
  "properties": {
    "iso:country":"DE",
    "sg:address":"Plan 5",
    "sg:city":"Himmelsberg",
    "sg:phone":"+49 36330/60307",
    "sg:postcode":"99713",
    "sg:province":"Th\u00fcringen",
    "wof:name":"Peter Madel Rechtsanwalt",
    "wof:placetype":"venue"
},
  "geometry": {"coordinates":[10.7280225754,51.3358802795],"type":"Point"}
}