{
  "type": "Feature",
  "properties": {
    "iso:country":"DE",
    "sg:address":"Marlow 2",
    "sg:city":"Sagard",
    "sg:phone":"+49 38302/2114",
    "sg:postcode":"18551",
    "sg:province":"Mecklenburg-Vorpommern",
    "wof:name":"Insel-k\u00fcchen Gmbh",
    "wof:placetype":"venue"
},
  "geometry": {"coordinates":[13.549632,54.533928],"type":"Point"}
}