{
  "type": "Feature",
  "properties": {
    "iso:country":"DE",
    "sg:address":"Alzenauer Str. 21a",
    "sg:city":"Rodenbach",
    "sg:phone":"+49 6184/50646",
    "sg:postcode":"63517",
    "sg:province":"Hessen",
    "wof:name":"E. B\u00f6hmert Fotoapparate Und Bedarf",
    "wof:placetype":"venue"
},
  "geometry": {"coordinates":[9.0271120071,50.141708374],"type":"Point"}
}