{
  "type": "Feature",
  "properties": {
    "iso:country":"DE",
    "sg:address":"Fasanenstr. 4",
    "sg:city":"Lauf",
    "sg:phone":"+49 9123/3791",
    "sg:postcode":"91207",
    "sg:province":"Bayern",
    "wof:name":"Werner Lenz Architekt",
    "wof:placetype":"venue"
},
  "geometry": {"coordinates":[11.293124,49.506672],"type":"Point"}
}