{
  "type": "Feature",
  "properties": {
    "iso:country":"DE",
    "sg:address":"Br\u00fcner Landstr. 20",
    "sg:city":"Wesel",
    "sg:phone":"+49 281/53556",
    "sg:postcode":"46485",
    "sg:province":"Nordrhein-Westfalen",
    "wof:name":"Am Treppchen",
    "wof:placetype":"venue"
},
  "geometry": {"coordinates":[6.6307082176,51.6660957336],"type":"Point"}
}