{
  "type": "Feature",
  "properties": {
    "iso:country":"DE",
    "sg:address":"Grabenstr. 40",
    "sg:city":"Greven",
    "sg:phone":"+49 2571/952900",
    "sg:postcode":"48268",
    "sg:province":"Nordrhein-Westfalen",
    "wof:name":"Aviation Assistance Gmbh",
    "wof:placetype":"venue"
},
  "geometry": {"coordinates":[7.620762825,52.0900230408],"type":"Point"}
}