{
  "type": "Feature",
  "properties": {
    "iso:country":"DE",
    "sg:address":"Jahnstr. 7",
    "sg:city":"Mittenaar",
    "sg:phone":"+49 2772/62210",
    "sg:postcode":"35756",
    "sg:province":"Hessen",
    "wof:name":"Helmut Sch\u00e4fer",
    "wof:placetype":"venue"
},
  "geometry": {"coordinates":[8.367702,50.682987],"type":"Point"}
}