{
  "type": "Feature",
  "properties": {
    "iso:country":"DE",
    "sg:address":"Willinger Str. 1",
    "sg:city":"Korbach",
    "sg:phone":"+49 5631/63196",
    "sg:postcode":"34497",
    "sg:province":"Hessen",
    "wof:name":"Karl-heinz Herzog",
    "wof:placetype":"venue"
},
  "geometry": {"coordinates":[8.828432,51.289173],"type":"Point"}
}