{
  "type": "Feature",
  "properties": {
    "iso:country":"DE",
    "sg:address":"Langenstr. 75",
    "sg:city":"Bremen",
    "sg:phone":"+49 421/171552",
    "sg:postcode":"28195",
    "sg:province":"Bremen",
    "wof:name":"Bw-center Handels Gmbh",
    "wof:placetype":"venue"
},
  "geometry": {"coordinates":[8.799131,53.078911],"type":"Point"}
}