{
  "type": "Feature",
  "properties": {
    "iso:country":"DE",
    "sg:address":"Im Kamp 8",
    "sg:city":"Werdohl",
    "sg:phone":"+49 2392/722074",
    "sg:postcode":"58791",
    "sg:province":"Nordrhein-Westfalen",
    "wof:name":"Qualitaetsmanagementberatung Udo Heutelbeck Gbr",
    "wof:placetype":"venue"
},
  "geometry": {"coordinates":[7.758998,51.236599],"type":"Point"}
}