{
  "type": "Feature",
  "properties": {
    "iso:country":"DE",
    "sg:address":"H\u00fcttenges\u00e4\u00dfer Str. 2",
    "sg:city":"Hammersbach",
    "sg:phone":"+49 6185/1672",
    "sg:postcode":"63546",
    "sg:province":"Hessen",
    "wof:name":"Karin Gl\u00e4nzer",
    "wof:placetype":"venue"
},
  "geometry": {"coordinates":[8.9910707474,50.2211227417],"type":"Point"}
}