{
  "type": "Feature",
  "properties": {
    "iso:country":"DE",
    "sg:address":"Warendorfer-Str. 12a",
    "sg:city":"M\u00fcnster",
    "sg:phone":"+49 251/9879637",
    "sg:postcode":"48145",
    "sg:province":"Nordrhein-Westfalen",
    "wof:name":"Male",
    "wof:placetype":"venue"
},
  "geometry": {"coordinates":[7.6379981041,51.9616394043],"type":"Point"}
}