{
  "type": "Feature",
  "properties": {
    "iso:country":"DE",
    "sg:address":"Ringofenstr. 39",
    "sg:city":"Dortmund",
    "sg:postcode":"44287",
    "sg:province":"Nordrhein-Westfalen",
    "wof:name":"Weyler Elektrotechnik Und Steuerungsbau Gmbh",
    "wof:placetype":"venue"
},
  "geometry": {"coordinates":[7.549422,51.495316],"type":"Point"}
}