{
  "type": "Feature",
  "properties": {
    "iso:country":"DE",
    "sg:address":"Nimsweg 5",
    "sg:city":"Giesdorf",
    "sg:phone":"+49 6551/898",
    "sg:postcode":"54614",
    "sg:province":"Rheinland-Pfalz",
    "wof:name":"Ngl Nimstaler Getr\u00e4nkehandel Lentz Verwaltungs Gmbh",
    "wof:placetype":"venue"
},
  "geometry": {"coordinates":[6.4513750076,50.1801795959],"type":"Point"}
}