{
  "type": "Feature",
  "properties": {
    "iso:country":"DE",
    "sg:address":"Scharitzkehlstr. 2",
    "sg:city":"Berchtesgaden",
    "sg:phone":"+49 8652/4257",
    "sg:postcode":"83471",
    "sg:province":"Bayern",
    "wof:name":"Sonneck",
    "wof:placetype":"venue"
},
  "geometry": {"coordinates":[13.0221700668,47.6219406128],"type":"Point"}
}