{
  "type": "Feature",
  "properties": {
    "iso:country":"DE",
    "sg:address":"Oberdie\u00dfemer Str 15",
    "sg:city":"Krefeld",
    "sg:phone":"+49 2151/8255",
    "sg:postcode":"47805",
    "sg:province":"Nordrhein-Westfalen",
    "wof:name":"Pcb Printed Circuit Boards Gmbh",
    "wof:placetype":"venue"
},
  "geometry": {"coordinates":[6.5807681084,51.3281555176],"type":"Point"}
}