{
  "type": "Feature",
  "properties": {
    "iso:country":"DE",
    "sg:address":"Darmst\u00e4dter Str. 39",
    "sg:city":"Ober-Ramstadt",
    "sg:phone":"+49 6154/2195",
    "sg:postcode":"64372",
    "sg:province":"Hessen",
    "wof:name":"Judith Renz",
    "wof:placetype":"venue"
},
  "geometry": {"coordinates":[8.74771,49.826733],"type":"Point"}
}