{
  "type": "Feature",
  "properties": {
    "iso:country":"DE",
    "sg:address":"M\u00fchlstr. 2",
    "sg:city":"Gro\u00dfrudestedt",
    "sg:phone":"+49 36204/60032",
    "sg:postcode":"99195",
    "sg:province":"Th\u00fcringen",
    "wof:name":"Landb\u00e4ckerei Thieme Gmbh",
    "wof:placetype":"venue"
},
  "geometry": {"coordinates":[11.101069,51.09116],"type":"Point"}
}