{
  "type": "Feature",
  "properties": {
    "iso:country":"DE",
    "sg:address":"Staufenstr. 8-3",
    "sg:city":"Rechberghausen",
    "sg:phone":"+49 7161/52609",
    "sg:postcode":"73098",
    "sg:province":"Baden-W\u00fcrttemberg",
    "wof:name":"Herbert Weissinger",
    "wof:placetype":"venue"
},
  "geometry": {"coordinates":[9.6435260773,48.733039856],"type":"Point"}
}