{
  "type": "Feature",
  "properties": {
    "iso:country":"DE",
    "sg:address":"Lange Gasse 12",
    "sg:city":"Geislingen",
    "sg:phone":"+49 7331/44542",
    "sg:postcode":"73312",
    "sg:province":"Baden-W\u00fcrttemberg",
    "wof:name":"Bosporus",
    "wof:placetype":"venue"
},
  "geometry": {"coordinates":[9.8415670395,48.6150817871],"type":"Point"}
}