{
  "type": "Feature",
  "properties": {
    "iso:country":"DE",
    "sg:address":"Schleusinger Str. 43",
    "sg:city":"Suhl",
    "sg:phone":"+49 3681/306861",
    "sg:postcode":"98527",
    "sg:province":"Th\u00fcringen",
    "wof:name":"Es-consulting Gmbh",
    "wof:placetype":"venue"
},
  "geometry": {"coordinates":[10.6917657852,50.6027488708],"type":"Point"}
}