{
  "type": "Feature",
  "properties": {
    "iso:country":"DE",
    "sg:address":"Bastianstr. 16",
    "sg:city":"Westerland",
    "sg:phone":"+49 4651/6483",
    "sg:postcode":"25980",
    "sg:province":"Schleswig-Holstein",
    "wof:name":"Hotel Seerose",
    "wof:placetype":"venue"
},
  "geometry": {"coordinates":[8.3138971329,54.9091644287],"type":"Point"}
}