{
  "type": "Feature",
  "properties": {
    "iso:country":"DE",
    "sg:address":"Bahnhofstr. 15",
    "sg:city":"Schkeuditz",
    "sg:phone":"+49 34204/62967",
    "sg:postcode":"04435",
    "sg:province":"Sachsen",
    "wof:name":"W. Schwarze",
    "wof:placetype":"venue"
},
  "geometry": {"coordinates":[12.2218999863,51.3976898193],"type":"Point"}
}