{
  "type": "Feature",
  "properties": {
    "iso:country":"DE",
    "sg:address":"Industriestr. 26",
    "sg:city":"Weeze",
    "sg:phone":"+49 2837/7929",
    "sg:postcode":"47652",
    "sg:province":"Nordrhein-Westfalen",
    "wof:name":"G\u00fcnter L\u00fccke Autolackierei Gmbh",
    "wof:placetype":"venue"
},
  "geometry": {"coordinates":[6.209325,51.623463],"type":"Point"}
}