{
  "type": "Feature",
  "properties": {
    "iso:country":"DE",
    "sg:address":"An der Bahn 5",
    "sg:city":"Unsleben",
    "sg:phone":"+49 9773/890042",
    "sg:postcode":"97618",
    "sg:province":"Bayern",
    "wof:name":"Dietz & Lehnert Fliesen Gmbh",
    "wof:placetype":"venue"
},
  "geometry": {"coordinates":[10.1718454361,50.3150367737],"type":"Point"}
}