{
  "type": "Feature",
  "properties": {
    "iso:country":"DE",
    "sg:address":"Werner-Von-Siemens-Str. 42-44",
    "sg:city":"Bruchsal",
    "sg:phone":"+49 4972/5180402",
    "sg:postcode":"76646",
    "sg:province":"Baden-W\u00fcrttemberg",
    "wof:name":"Sfv Sch\u00c4fer Gmbh & Co. Kg",
    "wof:placetype":"venue"
},
  "geometry": {"coordinates":[8.58262,49.128548],"type":"Point"}
}