{
  "type": "Feature",
  "properties": {
    "iso:country":"DE",
    "sg:address":"Am Falkenberg 125",
    "sg:city":"Berlin",
    "sg:phone":"+49 30/67989554",
    "sg:postcode":"12524",
    "sg:province":"Berlin",
    "wof:name":"Privatpraxis Dermatologie Dr. Med. Roesler",
    "wof:placetype":"venue"
},
  "geometry": {"coordinates":[13.570035,52.410805],"type":"Point"}
}