{
  "type": "Feature",
  "properties": {
    "iso:country":"DE",
    "sg:address":"Marktplatz 4",
    "sg:city":"Kupferberg",
    "sg:postcode":"95362",
    "sg:province":"Bayern",
    "wof:name":"Hospital-stiftung Kupferberg",
    "wof:placetype":"venue"
},
  "geometry": {"coordinates":[11.5767183304,50.1391792297],"type":"Point"}
}