{
  "type": "Feature",
  "properties": {
    "iso:country":"DE",
    "sg:address":"Friedrichstr. 12",
    "sg:city":"Schwerin",
    "sg:phone":"+49 385/565066",
    "sg:postcode":"19055",
    "sg:province":"Mecklenburg-Vorpommern",
    "wof:name":"P. Lasch",
    "wof:placetype":"venue"
},
  "geometry": {"coordinates":[11.414552,53.63063],"type":"Point"}
}