{
  "type": "Feature",
  "properties": {
    "iso:country":"DE",
    "sg:address":"Leipziger Str.",
    "sg:city":"Wuppertal",
    "sg:phone":"+49 202/704051",
    "sg:postcode":"42109",
    "sg:province":"Nordrhein-Westfalen",
    "wof:name":"Facom Gmbh",
    "wof:placetype":"venue"
},
  "geometry": {"coordinates":[7.148712,51.275906],"type":"Point"}
}