{
  "type": "Feature",
  "properties": {
    "iso:country":"DE",
    "sg:address":"Bachwiesenstr. 7",
    "sg:city":"M\u00fcnsingen",
    "sg:phone":"+49 7381/182115",
    "sg:postcode":"72525",
    "sg:province":"Baden-W\u00fcrttemberg",
    "wof:name":"Stadtarchiv",
    "wof:placetype":"venue"
},
  "geometry": {"coordinates":[9.492391,48.412621],"type":"Point"}
}