{
  "type": "Feature",
  "properties": {
    "iso:country":"DE",
    "sg:address":"Fleeth\u00f6rn 1-3",
    "sg:city":"Kiel",
    "sg:phone":"+49 431/9030",
    "sg:postcode":"24103",
    "sg:province":"Schleswig-Holstein",
    "wof:name":"Dr. Curt Heinrich Nachfolger Gmbh",
    "wof:placetype":"venue"
},
  "geometry": {"coordinates":[10.134317,54.321564],"type":"Point"}
}