{
  "type": "Feature",
  "properties": {
    "iso:country":"DE",
    "sg:address":"Foppenkamp 2",
    "sg:city":"Lengerich",
    "sg:phone":"+49 5904/93200",
    "sg:postcode":"49838",
    "sg:province":"Niedersachsen",
    "wof:name":"Tischlerei Goos Gmbh",
    "wof:placetype":"venue"
},
  "geometry": {"coordinates":[7.5385,52.537601],"type":"Point"}
}