{
  "type": "Feature",
  "properties": {
    "iso:country":"DE",
    "sg:address":"Am Kindergarten 16",
    "sg:city":"Schwabenheim",
    "sg:phone":"+49 6130/944050",
    "sg:postcode":"55270",
    "sg:province":"Rheinland-Pfalz",
    "wof:name":"Helfende Hand Private Krankenpflege Gmbh",
    "wof:placetype":"venue"
},
  "geometry": {"coordinates":[8.094201,49.926014],"type":"Point"}
}