{
  "type": "Feature",
  "properties": {
    "iso:country":"DE",
    "sg:address":"Reckstr. 1",
    "sg:city":"Betzenweiler",
    "sg:phone":"+49 7374/180",
    "sg:postcode":"88422",
    "sg:province":"Baden-W\u00fcrttemberg",
    "wof:name":"Reck Maschinenbau Gmbh",
    "wof:placetype":"venue"
},
  "geometry": {"coordinates":[9.56838,48.118843],"type":"Point"}
}