{
  "type": "Feature",
  "properties": {
    "iso:country":"DE",
    "sg:address":"Ardeystr. 316",
    "sg:city":"Witten",
    "sg:phone":"+49 2302/80540",
    "sg:postcode":"58453",
    "sg:province":"Nordrhein-Westfalen",
    "wof:name":"W. Langohr",
    "wof:placetype":"venue"
},
  "geometry": {"coordinates":[7.407319,51.434242],"type":"Point"}
}