{
  "type": "Feature",
  "properties": {
    "iso:country":"DE",
    "sg:address":"Hardtstr. 17",
    "sg:city":"Villingen-Schwenningen",
    "sg:phone":"+49 7720/5565",
    "sg:postcode":"78054",
    "sg:province":"Baden-W\u00fcrttemberg",
    "wof:name":"P. Christ",
    "wof:placetype":"venue"
},
  "geometry": {"coordinates":[8.5235834122,48.0569610596],"type":"Point"}
}