{
  "type": "Feature",
  "properties": {
    "iso:country":"DE",
    "sg:address":"Iltisplatz 1",
    "sg:city":"Lingen",
    "sg:phone":"+49 591/72296",
    "sg:postcode":"49811",
    "sg:province":"Niedersachsen",
    "wof:name":"Werner Haberland Ingenieur",
    "wof:placetype":"venue"
},
  "geometry": {"coordinates":[7.3636431694,52.523223877],"type":"Point"}
}