{
  "type": "Feature",
  "properties": {
    "iso:country":"DE",
    "sg:address":"Solinger Str. 24 A",
    "sg:city":"Leichlingen",
    "sg:phone":"+49 2174/3401",
    "sg:postcode":"42799",
    "sg:province":"Nordrhein-Westfalen",
    "wof:name":"U. Manka",
    "wof:placetype":"venue"
},
  "geometry": {"coordinates":[7.110994,51.117771],"type":"Point"}
}