{
  "type": "Feature",
  "properties": {
    "iso:country":"DE",
    "sg:address":"Schl\u00e4gelstr. 53",
    "sg:city":"Oberhausen",
    "sg:phone":"+49 208/800200",
    "sg:postcode":"46045",
    "sg:province":"Nordrhein-Westfalen",
    "wof:name":"F. Hasselbach",
    "wof:placetype":"venue"
},
  "geometry": {"coordinates":[6.847491,51.463886],"type":"Point"}
}