{
  "type": "Feature",
  "properties": {
    "iso:country":"DE",
    "sg:address":"Abtsg\u00e4\u00dfchen 8",
    "sg:city":"Frankfurt",
    "sg:phone":"+49 69/626310",
    "sg:postcode":"60594",
    "sg:province":"Hessen",
    "wof:name":"Restaurant Royal Bombay Palace No 1",
    "wof:placetype":"venue"
},
  "geometry": {"coordinates":[8.6885967255,50.1044082642],"type":"Point"}
}