{
  "type": "Feature",
  "properties": {
    "iso:country":"DE",
    "sg:address":"Ziegeleiweg 13",
    "sg:city":"Crimmitschau",
    "sg:phone":"+49 3762/95540",
    "sg:postcode":"08451",
    "sg:province":"Sachsen",
    "wof:name":"Holm Gr\u00fcnenburg",
    "wof:placetype":"venue"
},
  "geometry": {"coordinates":[12.406984,50.815372],"type":"Point"}
}