{
  "type": "Feature",
  "properties": {
    "iso:country":"DE",
    "sg:address":"Alte Rathausstr. 2-4",
    "sg:city":"Gummersbach",
    "sg:phone":"+49 2261/22011",
    "sg:postcode":"51643",
    "sg:province":"Nordrhein-Westfalen",
    "wof:name":"Konrad Hacker Rechtsanwalt",
    "wof:placetype":"venue"
},
  "geometry": {"coordinates":[7.5658421516,51.0274124146],"type":"Point"}
}