{
  "type": "Feature",
  "properties": {
    "iso:country":"DE",
    "sg:address":"Groppenbrucher Str. 82",
    "sg:city":"Dortmund",
    "sg:phone":"+49 231/338316",
    "sg:postcode":"44359",
    "sg:province":"Nordrhein-Westfalen",
    "wof:name":"T. K\u00fcnne",
    "wof:placetype":"venue"
},
  "geometry": {"coordinates":[7.3905210495,51.5857543945],"type":"Point"}
}