{
  "type": "Feature",
  "properties": {
    "iso:country":"DE",
    "sg:address":"Orthstr. 1",
    "sg:city":"Chemnitz",
    "sg:phone":"+49 371/414326",
    "sg:postcode":"09131",
    "sg:province":"Sachsen",
    "wof:name":"Ingolf Dietze",
    "wof:placetype":"venue"
},
  "geometry": {"coordinates":[12.9448919296,50.8522491455],"type":"Point"}
}