{
  "type": "Feature",
  "properties": {
    "iso:country":"DE",
    "sg:address":"Am Mannstein 15",
    "sg:city":"Kelkheim",
    "sg:postcode":"65779",
    "sg:province":"Hessen",
    "wof:name":"M2l Gesellschaft F\u00fcr Finanzierungsl\u00f6sungen Mbh",
    "wof:placetype":"venue"
},
  "geometry": {"coordinates":[8.4257440567,50.1431846619],"type":"Point"}
}