{
  "type": "Feature",
  "properties": {
    "iso:country":"DE",
    "sg:address":"Weinberg 46",
    "sg:city":"Soltau",
    "sg:phone":"+49 5191/840",
    "sg:postcode":"29614",
    "sg:province":"Niedersachsen",
    "wof:name":"Stadtwerke Soltau Gmbh",
    "wof:placetype":"venue"
},
  "geometry": {"coordinates":[9.822722,52.984928],"type":"Point"}
}