{
  "type": "Feature",
  "properties": {
    "iso:country":"DE",
    "sg:address":"Hoffnung 69",
    "sg:city":"Glauchau",
    "sg:phone":"+49 3763/17060",
    "sg:postcode":"08371",
    "sg:province":"Sachsen",
    "wof:name":"Landesversicherungs- Anstalt Sachsen",
    "wof:placetype":"venue"
},
  "geometry": {"coordinates":[12.5448656082,50.8208007812],"type":"Point"}
}