{
  "type": "Feature",
  "properties": {
    "iso:country":"DE",
    "sg:address":"Hubertusstr. 77",
    "sg:city":"Minden",
    "sg:postcode":"32429",
    "sg:province":"Nordrhein-Westfalen",
    "wof:name":"Gradwell K\u00fcchenmontagen Gmbh",
    "wof:placetype":"venue"
},
  "geometry": {"coordinates":[8.877256,52.278278],"type":"Point"}
}