{
  "type": "Feature",
  "properties": {
    "iso:country":"DE",
    "sg:address":"St.-Martin-Str. 18",
    "sg:city":"Sche\u00dflitz",
    "sg:phone":"+49 9542/7415",
    "sg:postcode":"96110",
    "sg:province":"Bayern",
    "wof:name":"Confiserie Storath- Pralinenmanufaktur",
    "wof:placetype":"venue"
},
  "geometry": {"coordinates":[11.073636055,50.0110816956],"type":"Point"}
}