{
  "type": "Feature",
  "properties": {
    "iso:country":"DE",
    "sg:address":"Aschaffenburger Str. 161",
    "sg:city":"Waldaschaff",
    "sg:phone":"+49 6095/994681",
    "sg:postcode":"63857",
    "sg:province":"Bayern",
    "wof:name":"W. M\u00fcller",
    "wof:placetype":"venue"
},
  "geometry": {"coordinates":[9.28503,49.977959],"type":"Point"}
}