{
  "type": "Feature",
  "properties": {
    "iso:country":"DE",
    "sg:address":"Krankenhausweg 10",
    "sg:city":"Riedlingen",
    "sg:phone":"+49 7371/3520",
    "sg:postcode":"88499",
    "sg:province":"Baden-W\u00fcrttemberg",
    "wof:name":"A. Wetzel-schneider Rechtsanw\u00e4ltin",
    "wof:placetype":"venue"
},
  "geometry": {"coordinates":[9.4762563705,48.1567687988],"type":"Point"}
}