{
  "type": "Feature",
  "properties": {
    "iso:country":"DE",
    "sg:address":"Bonnstra\u00dfe 469",
    "sg:city":"Huerth",
    "sg:phone":"+49 2233",
    "sg:postcode":"50354",
    "sg:province":"Nordrhein-Westfalen",
    "wof:name":"Mcr Ton & Lichtservice",
    "wof:placetype":"venue"
},
  "geometry": {"coordinates":[6.90288,50.854546],"type":"Point"}
}