{
  "type": "Feature",
  "properties": {
    "iso:country":"DE",
    "sg:address":"Zweigstr. 2",
    "sg:city":"Starnberg",
    "sg:phone":"+49 8151/21182",
    "sg:postcode":"82319",
    "sg:province":"Bayern",
    "wof:name":"Peter Stoll",
    "wof:placetype":"venue"
},
  "geometry": {"coordinates":[11.3429441452,47.997177124],"type":"Point"}
}