{
  "type": "Feature",
  "properties": {
    "iso:country":"DE",
    "sg:address":"Am Fischweiher",
    "sg:city":"Rutsweiler",
    "sg:phone":"+49 6381/7153",
    "sg:postcode":"66887",
    "sg:province":"Rheinland-Pfalz",
    "wof:name":"Helmut Seyl",
    "wof:placetype":"venue"
},
  "geometry": {"coordinates":[7.509622097,49.6068763733],"type":"Point"}
}