{
  "type": "Feature",
  "properties": {
    "iso:country":"DE",
    "sg:address":"Lelei 3",
    "sg:city":"Essen",
    "sg:phone":"+49 201/462131",
    "sg:postcode":"45259",
    "sg:province":"Nordrhein-Westfalen",
    "wof:name":"Ewald Dresen Farben U.tapeten",
    "wof:placetype":"venue"
},
  "geometry": {"coordinates":[7.065823,51.400898],"type":"Point"}
}