{
  "type": "Feature",
  "properties": {
    "iso:country":"DE",
    "sg:address":"Lindenufer 39",
    "sg:city":"Berlin",
    "sg:phone":"+49 30/35302411",
    "sg:postcode":"13597",
    "sg:province":"Berlin",
    "wof:name":"E-v-b",
    "wof:placetype":"venue"
},
  "geometry": {"coordinates":[13.203845,52.53511],"type":"Point"}
}