{
  "type": "Feature",
  "properties": {
    "iso:country":"DE",
    "sg:address":"Ludwigsplatz 1",
    "sg:city":"Alsfeld",
    "sg:phone":"+49 6631/96560",
    "sg:postcode":"36304",
    "sg:province":"Hessen",
    "wof:name":"Deutsche Post Ag",
    "wof:placetype":"venue"
},
  "geometry": {"coordinates":[9.2699546814,50.7530250549],"type":"Point"}
}