{
  "type": "Feature",
  "properties": {
    "iso:country":"DE",
    "sg:address":"Radeburger Str. 108",
    "sg:city":"Ottendorf-Okrilla",
    "sg:postcode":"01458",
    "sg:province":"Sachsen",
    "wof:name":"Reinhold Bauer",
    "wof:placetype":"venue"
},
  "geometry": {"coordinates":[13.808093,51.180618],"type":"Point"}
}