{
  "type": "Feature",
  "properties": {
    "iso:country":"DE",
    "sg:address":"Friemarer Str.38",
    "sg:city":"Gotha",
    "sg:phone":"+49 3621",
    "sg:postcode":"99867",
    "sg:province":"Th\u00fcringen",
    "wof:name":"Magic Hair Line",
    "wof:placetype":"venue"
},
  "geometry": {"coordinates":[10.7162513733,50.9546852112],"type":"Point"}
}