{
  "type": "Feature",
  "properties": {
    "iso:country":"DE",
    "sg:address":"Rosenstr. 22",
    "sg:city":"Marienhafe",
    "sg:phone":"+49 4934/7090",
    "sg:postcode":"26529",
    "sg:province":"Niedersachsen",
    "wof:name":"Fitnesstreff Sunshine",
    "wof:placetype":"venue"
},
  "geometry": {"coordinates":[7.276184082,53.5207481384],"type":"Point"}
}