{
  "type": "Feature",
  "properties": {
    "iso:country":"DE",
    "sg:address":"Stahltwiete 21",
    "sg:city":"Hamburg",
    "sg:phone":"+49 40/8533390",
    "sg:postcode":"22761",
    "sg:province":"Hamburg",
    "wof:name":"Alles F\u00fcr Einen Guten Umzug",
    "wof:placetype":"venue"
},
  "geometry": {"coordinates":[9.9261207581,53.5631370544],"type":"Point"}
}