{
  "type": "Feature",
  "properties": {
    "iso:country":"DE",
    "sg:address":"Nebelhorn 20",
    "sg:city":"Oberstdorf",
    "sg:phone":"+49 8322/4313",
    "sg:postcode":"87561",
    "sg:province":"Bayern",
    "wof:name":"Schmidle",
    "wof:placetype":"venue"
},
  "geometry": {"coordinates":[10.2810726166,47.40782547],"type":"Point"}
}