{
  "type": "Feature",
  "properties": {
    "iso:country":"DE",
    "sg:address":"Kirchgasse 5",
    "sg:city":"Schonungen",
    "sg:phone":"+49 9727/431",
    "sg:postcode":"97453",
    "sg:province":"Bayern",
    "wof:name":"B. May",
    "wof:placetype":"venue"
},
  "geometry": {"coordinates":[10.3028030396,50.0513687134],"type":"Point"}
}