{
  "type": "Feature",
  "properties": {
    "iso:country":"DE",
    "sg:address":"Kastanienweg 7",
    "sg:city":"Stendal",
    "sg:phone":"+49 3931/213120",
    "sg:postcode":"39576",
    "sg:province":"Sachsen-Anhalt",
    "wof:name":"Bernd Eich",
    "wof:placetype":"venue"
},
  "geometry": {"coordinates":[11.8470020294,52.621547699],"type":"Point"}
}