{
  "type": "Feature",
  "properties": {
    "iso:country":"DE",
    "sg:address":"Ibersheimer Str. 55",
    "sg:city":"Worms",
    "sg:phone":"+49 6242/7607",
    "sg:postcode":"67550",
    "sg:province":"Rheinland-Pfalz",
    "wof:name":"Hans Metzen",
    "wof:placetype":"venue"
},
  "geometry": {"coordinates":[8.3301210403,49.6581878662],"type":"Point"}
}