{
  "type": "Feature",
  "properties": {
    "iso:country":"DE",
    "sg:address":"Tr\u00e4nkestr. 14",
    "sg:city":"Eggersdorf",
    "sg:phone":"+49 3928/82361",
    "sg:postcode":"39221",
    "sg:province":"Sachsen-Anhalt",
    "wof:name":"Imbiss-kiosk Inh. G\u00fcnther Ackermann",
    "wof:placetype":"venue"
},
  "geometry": {"coordinates":[11.7114276886,51.9762268066],"type":"Point"}
}