{
  "type": "Feature",
  "properties": {
    "iso:country":"DE",
    "sg:address":"Wegenerstr. 10-11",
    "sg:city":"Berlin",
    "sg:phone":"+49 30/8649170",
    "sg:postcode":"10713",
    "sg:province":"Berlin",
    "wof:name":"H. Hartel Und D. Schindofski Steuerberater",
    "wof:placetype":"venue"
},
  "geometry": {"coordinates":[13.3169307709,52.4891433716],"type":"Point"}
}