{
  "type": "Feature",
  "properties": {
    "iso:country":"DE",
    "sg:address":"S\u00fcdstr. 55",
    "sg:city":"Halle",
    "sg:phone":"+49 345/1202098",
    "sg:postcode":"06110",
    "sg:province":"Sachsen-Anhalt",
    "wof:name":"Lab Bautr\u00e4ger Gmbh",
    "wof:placetype":"venue"
},
  "geometry": {"coordinates":[11.976872,51.473331],"type":"Point"}
}