{
  "type": "Feature",
  "properties": {
    "iso:country":"DE",
    "sg:address":"Martinistr. 25",
    "sg:city":"Ahaus",
    "sg:phone":"+49 2561/3278",
    "sg:postcode":"48683",
    "sg:province":"Nordrhein-Westfalen",
    "wof:name":"Pieper Bau Gmbh",
    "wof:placetype":"venue"
},
  "geometry": {"coordinates":[6.977618,52.090237],"type":"Point"}
}