{
  "type": "Feature",
  "properties": {
    "iso:country":"DE",
    "sg:address":"Morsdorfer Str. 14",
    "sg:city":"K\u00f6ln",
    "sg:phone":"+49 221/431927",
    "sg:postcode":"50935",
    "sg:province":"Nordrhein-Westfalen",
    "wof:name":"Dr. Richard J. Keutner Rechtsanwalt",
    "wof:placetype":"venue"
},
  "geometry": {"coordinates":[6.8962311745,50.926361084],"type":"Point"}
}