{
  "type": "Feature",
  "properties": {
    "iso:country":"DE",
    "sg:address":"Rimbachstr. 13",
    "sg:city":"Suhl",
    "sg:phone":"+49 3681/722995",
    "sg:postcode":"98527",
    "sg:province":"Th\u00fcringen",
    "wof:name":"Portraitstudio",
    "wof:placetype":"venue"
},
  "geometry": {"coordinates":[10.6939401627,50.6095962524],"type":"Point"}
}