{
  "type": "Feature",
  "properties": {
    "iso:country":"DE",
    "sg:address":"Schulerstr. 9",
    "sg:city":"Hechingen",
    "sg:postcode":"72379",
    "sg:province":"Baden-W\u00fcrttemberg",
    "wof:name":"A. I. T. Conzelmann Taxi Und Mietwagen",
    "wof:placetype":"venue"
},
  "geometry": {"coordinates":[8.915845871,48.3486633301],"type":"Point"}
}