{
  "type": "Feature",
  "properties": {
    "iso:country":"DE",
    "sg:address":"Lindenstr. 18",
    "sg:city":"Rahnsdorf",
    "sg:phone":"+49 34924",
    "sg:postcode":"06895",
    "sg:province":"Sachsen-Anhalt",
    "wof:name":"Gest\u00fct Falkenhof",
    "wof:placetype":"venue"
},
  "geometry": {"coordinates":[12.7844867706,51.9462203979],"type":"Point"}
}