{
  "type": "Feature",
  "properties": {
    "iso:country":"DE",
    "sg:address":"Bauhof 7",
    "sg:city":"R\u00f6tz",
    "sg:phone":"+49 9976/322",
    "sg:postcode":"92444",
    "sg:province":"Bayern",
    "wof:name":"Hotel-pension Bergfried",
    "wof:placetype":"venue"
},
  "geometry": {"coordinates":[12.5029611588,49.3523483276],"type":"Point"}
}