{
  "type": "Feature",
  "properties": {
    "iso:country":"DE",
    "sg:address":"Am Jachthafen",
    "sg:city":"Heiligenhafen",
    "sg:phone":"+49 4362/2833",
    "sg:postcode":"23774",
    "sg:province":"Schleswig-Holstein",
    "wof:name":"Oliver Leu Ohg",
    "wof:placetype":"venue"
},
  "geometry": {"coordinates":[10.9830379486,54.3745117188],"type":"Point"}
}