{
  "type": "Feature",
  "properties": {
    "iso:country":"DE",
    "sg:address":"Europaring 5a",
    "sg:city":"Ratingen",
    "sg:phone":"+49 2102/86660",
    "sg:postcode":"40878",
    "sg:province":"Nordrhein-Westfalen",
    "wof:name":"Securat Die Asset Management Gmbh",
    "wof:placetype":"venue"
},
  "geometry": {"coordinates":[6.8532371521,51.2938957214],"type":"Point"}
}