{
  "type": "Feature",
  "properties": {
    "iso:country":"DE",
    "sg:address":"Alte Poststr. 16",
    "sg:city":"Freudenstadt",
    "sg:phone":"+49 7441/9195070",
    "sg:postcode":"72250",
    "sg:province":"Baden-W\u00fcrttemberg",
    "wof:name":"F. Kirchhoff Strassenbau Gmbh & Co. Kg",
    "wof:placetype":"venue"
},
  "geometry": {"coordinates":[8.4451828003,48.465461731],"type":"Point"}
}