{
  "type": "Feature",
  "properties": {
    "iso:country":"DE",
    "sg:address":"Ludwigshain 25a",
    "sg:city":"Weisenheim am Sand",
    "sg:phone":"+49 6353/2289",
    "sg:postcode":"67256",
    "sg:province":"Rheinland-Pfalz",
    "wof:name":"Friedrich Hofmann",
    "wof:placetype":"venue"
},
  "geometry": {"coordinates":[8.2474746704,49.5174331665],"type":"Point"}
}