{
  "type": "Feature",
  "properties": {
    "iso:country":"DE",
    "sg:address":"Ulrichsplatz 12",
    "sg:city":"Augsburg",
    "sg:phone":"+49 821/509710",
    "sg:postcode":"86150",
    "sg:province":"Bayern",
    "wof:name":"Altstadt Immobilien Verwaltungsges. Mbh",
    "wof:placetype":"venue"
},
  "geometry": {"coordinates":[10.9001092911,48.3623313904],"type":"Point"}
}