{
  "type": "Feature",
  "properties": {
    "iso:country":"DE",
    "sg:address":"Greteneck 2",
    "sg:city":"Kehl",
    "sg:phone":"+49 7853/201",
    "sg:postcode":"77694",
    "sg:province":"Baden-W\u00fcrttemberg",
    "wof:name":"Ochsen",
    "wof:placetype":"venue"
},
  "geometry": {"coordinates":[7.904692173,48.6096878052],"type":"Point"}
}