{
  "type": "Feature",
  "properties": {
    "iso:country":"DE",
    "sg:address":"Am Ochsenmarkt 35",
    "sg:city":"Flensburg",
    "sg:phone":"+49 461/51973",
    "sg:postcode":"24937",
    "sg:province":"Schleswig-Holstein",
    "wof:name":"St. Michael Apotheke",
    "wof:placetype":"venue"
},
  "geometry": {"coordinates":[9.417589,54.782017],"type":"Point"}
}