{
  "type": "Feature",
  "properties": {
    "iso:country":"DE",
    "sg:address":"Bgm.-Heukamp-Str.",
    "sg:city":"Cloppenburg",
    "sg:phone":"+49 4944/715711",
    "sg:postcode":"49661",
    "sg:province":"Niedersachsen",
    "wof:name":"Ostendorf Gmbh",
    "wof:placetype":"venue"
},
  "geometry": {"coordinates":[8.0474424362,52.8477363586],"type":"Point"}
}