{
  "type": "Feature",
  "properties": {
    "iso:country":"DE",
    "sg:address":"Dompfaffweg 10",
    "sg:city":"N\u00fcrnberg",
    "sg:phone":"+49 911/4469928",
    "sg:postcode":"90455",
    "sg:province":"Bayern",
    "wof:name":"Eureal Grundst\u00fccksges. Mbh",
    "wof:placetype":"venue"
},
  "geometry": {"coordinates":[11.071818,49.377449],"type":"Point"}
}