{
  "type": "Feature",
  "properties": {
    "iso:country":"DE",
    "sg:address":"Eisenberger Str. 9",
    "sg:city":"Schk\u00f6len",
    "sg:phone":"+49 36694/22523",
    "sg:postcode":"07619",
    "sg:province":"Th\u00fcringen",
    "wof:name":"E. Taubert",
    "wof:placetype":"venue"
},
  "geometry": {"coordinates":[11.823678,51.041733],"type":"Point"}
}