{
  "type": "Feature",
  "properties": {
    "iso:country":"DE",
    "sg:address":"Ernst-Th\u00e4lmann-Str. 1",
    "sg:city":"Gro\u00dfdubrau",
    "sg:phone":"+49 35934/8852",
    "sg:postcode":"02694",
    "sg:province":"Sachsen",
    "wof:name":"Hartmut Schuster",
    "wof:placetype":"venue"
},
  "geometry": {"coordinates":[14.4627332687,51.2552261353],"type":"Point"}
}