{
  "type": "Feature",
  "properties": {
    "iso:country":"DE",
    "sg:address":"Hauberner Ring 6",
    "sg:city":"Frankenberg",
    "sg:phone":"+49 6451/9031",
    "sg:postcode":"35066",
    "sg:province":"Hessen",
    "wof:name":"S-landesimmobilien Gmbh",
    "wof:placetype":"venue"
},
  "geometry": {"coordinates":[8.8114032745,51.0611877441],"type":"Point"}
}