{
  "type": "Feature",
  "properties": {
    "iso:country":"DE",
    "sg:address":"Willighausen 2",
    "sg:city":"Fa\u00dfberg",
    "sg:postcode":"29328",
    "sg:province":"Niedersachsen",
    "wof:name":"Ernst Tewes",
    "wof:placetype":"venue"
},
  "geometry": {"coordinates":[10.090036,52.861988],"type":"Point"}
}