{
  "type": "Feature",
  "properties": {
    "iso:country":"DE",
    "sg:address":"Loewestr. 3",
    "sg:city":"Hilden",
    "sg:phone":"+49 2103/41235",
    "sg:postcode":"40724",
    "sg:province":"Nordrhein-Westfalen",
    "wof:name":"Uschis Bierstube",
    "wof:placetype":"venue"
},
  "geometry": {"coordinates":[6.9280629158,51.1798858643],"type":"Point"}
}