{
  "type": "Feature",
  "properties": {
    "iso:country":"DE",
    "sg:address":"Graf-Bernadotte-Str. 16",
    "sg:city":"Kempen",
    "sg:phone":"+49 2152/50293",
    "sg:postcode":"47906",
    "sg:province":"Nordrhein-Westfalen",
    "wof:name":"Werner Bauer Detektei",
    "wof:placetype":"venue"
},
  "geometry": {"coordinates":[6.4077420235,51.3729782104],"type":"Point"}
}