{
  "type": "Feature",
  "properties": {
    "iso:country":"DE",
    "sg:address":"Ladehofstr. 28",
    "sg:city":"Regensburg",
    "sg:phone":"+49 941/464410",
    "sg:postcode":"93049",
    "sg:province":"Bayern",
    "wof:name":"Wolfgang Ortkras Und Dorothea Segas",
    "wof:placetype":"venue"
},
  "geometry": {"coordinates":[12.0819005966,49.013671875],"type":"Point"}
}