{
  "type": "Feature",
  "properties": {
    "iso:country":"DE",
    "sg:address":"N\u00fcrnberger Str. 27",
    "sg:city":"Hersbruck",
    "sg:phone":"+49 9151/823713",
    "sg:postcode":"91217",
    "sg:province":"Bayern",
    "wof:name":"Udo`s Gitarrenschuppen Udo Priner",
    "wof:placetype":"venue"
},
  "geometry": {"coordinates":[11.4247589111,49.5096321106],"type":"Point"}
}