{
  "type": "Feature",
  "properties": {
    "iso:country":"DE",
    "sg:address":"Bahnhofstr. 27",
    "sg:city":"Eitorf",
    "sg:phone":"+49 2243/3956",
    "sg:postcode":"53783",
    "sg:province":"Nordrhein-Westfalen",
    "wof:name":"K.h. Land",
    "wof:placetype":"venue"
},
  "geometry": {"coordinates":[7.4473180771,50.7726631165],"type":"Point"}
}