{
  "type": "Feature",
  "properties": {
    "iso:country":"DE",
    "sg:address":"Obere Hilsstr. 1",
    "sg:city":"Gr\u00fcnenplan",
    "sg:phone":"+49 5187/75777",
    "sg:postcode":"31073",
    "sg:province":"Niedersachsen",
    "wof:name":"Conrad Lampe",
    "wof:placetype":"venue"
},
  "geometry": {"coordinates":[9.7419729233,51.9545021057],"type":"Point"}
}