{
  "type": "Feature",
  "properties": {
    "iso:country":"DE",
    "sg:address":"Am Hegefeld 3 d",
    "sg:city":"Kl\u00f6tze",
    "sg:postcode":"38486",
    "sg:province":"Sachsen-Anhalt",
    "wof:name":"Aldi Gmbh & Co. Kg",
    "wof:placetype":"venue"
},
  "geometry": {"coordinates":[11.1724452972,52.6283454895],"type":"Point"}
}