{
  "type": "Feature",
  "properties": {
    "iso:country":"DE",
    "sg:address":"Alte Dorfstr. 50",
    "sg:city":"Probsteierhagen",
    "sg:phone":"+49 4348/7999",
    "sg:postcode":"24253",
    "sg:province":"Schleswig-Holstein",
    "wof:name":"Altes Probsteier Cafe",
    "wof:placetype":"venue"
},
  "geometry": {"coordinates":[10.2889204025,54.362865448],"type":"Point"}
}