{
  "type": "Feature",
  "properties": {
    "iso:country":"DE",
    "sg:address":"Eilener Weg 6",
    "sg:city":"Niederzier",
    "sg:phone":"+49 2428/3231",
    "sg:postcode":"52382",
    "sg:province":"Nordrhein-Westfalen",
    "wof:name":"H.-j. Schmitz Heiz\u00f6lhandlung",
    "wof:placetype":"venue"
},
  "geometry": {"coordinates":[6.4205098152,50.8782463074],"type":"Point"}
}