{
  "type": "Feature",
  "properties": {
    "iso:country":"DE",
    "sg:address":"Storkower Str. 113",
    "sg:city":"Berlin",
    "sg:phone":"+49 30/4212219",
    "sg:postcode":"10407",
    "sg:province":"Berlin",
    "wof:name":"Bsfl Bau Service Gmbh",
    "wof:placetype":"venue"
},
  "geometry": {"coordinates":[13.453052,52.53616],"type":"Point"}
}