{
  "type": "Feature",
  "properties": {
    "iso:country":"DE",
    "sg:address":"Meiner Weg 11",
    "sg:city":"Schwerte",
    "sg:phone":"+49 2304/61066",
    "sg:postcode":"58239",
    "sg:province":"Nordrhein-Westfalen",
    "wof:name":"Sbw Sozial Betreutes Wohnen Gemeinn\u00fctzige Gmbh",
    "wof:placetype":"venue"
},
  "geometry": {"coordinates":[7.53037,51.420101],"type":"Point"}
}