{
  "type": "Feature",
  "properties": {
    "iso:country":"DE",
    "sg:address":"Carl-Peters-Str. 11",
    "sg:city":"Soltau",
    "sg:phone":"+49 5191/3714",
    "sg:postcode":"29614",
    "sg:province":"Niedersachsen",
    "wof:name":"Marianne Otte",
    "wof:placetype":"venue"
},
  "geometry": {"coordinates":[9.8345079422,52.9919815063],"type":"Point"}
}