{
  "type": "Feature",
  "properties": {
    "iso:country":"DE",
    "sg:address":"Industriestr. 20",
    "sg:city":"Bremen",
    "sg:phone":"+49 421/51560",
    "sg:postcode":"28199",
    "sg:province":"Bremen",
    "wof:name":"Woll Sb Markt",
    "wof:placetype":"venue"
},
  "geometry": {"coordinates":[8.777779,53.061699],"type":"Point"}
}