{
  "type": "Feature",
  "properties": {
    "iso:country":"DE",
    "sg:address":"Wilhelm-Leuschner-Str. 22",
    "sg:city":"Worms",
    "sg:phone":"+49 6241/920920",
    "sg:postcode":"67547",
    "sg:province":"Rheinland-Pfalz",
    "wof:name":"Kurt Und G\u00fcnter Wilde",
    "wof:placetype":"venue"
},
  "geometry": {"coordinates":[8.3586015701,49.6337394714],"type":"Point"}
}