{
  "type": "Feature",
  "properties": {
    "iso:country":"DE",
    "sg:address":"Alte G\u00e4rtnerei 22",
    "sg:city":"Mainz",
    "sg:postcode":"55128",
    "sg:province":"Rheinland-Pfalz",
    "wof:name":"Suntec Gmbh",
    "wof:placetype":"venue"
},
  "geometry": {"coordinates":[8.23614,49.977058],"type":"Point"}
}