{
  "type": "Feature",
  "properties": {
    "iso:country":"DE",
    "sg:address":"Bertelsdorfer Weg 5",
    "sg:city":"Lautertal",
    "sg:phone":"+49 9561/60498",
    "sg:postcode":"96486",
    "sg:province":"Bayern",
    "wof:name":"E. Und S. Hofmann",
    "wof:placetype":"venue"
},
  "geometry": {"coordinates":[10.970776,50.293621],"type":"Point"}
}