{
  "type": "Feature",
  "properties": {
    "iso:country":"DE",
    "sg:address":"Pfluggasse 8",
    "sg:city":"Ulm",
    "sg:phone":"+49 731/63191",
    "sg:postcode":"89073",
    "sg:province":"Baden-W\u00fcrttemberg",
    "wof:name":"Heinrich Haas",
    "wof:placetype":"venue"
},
  "geometry": {"coordinates":[9.9943141937,48.3994293213],"type":"Point"}
}