{
  "type": "Feature",
  "properties": {
    "iso:country":"DE",
    "sg:address":"Rickbruch 2",
    "sg:city":"Extertal",
    "sg:phone":"+49 5754/352",
    "sg:postcode":"32699",
    "sg:province":"Nordrhein-Westfalen",
    "wof:name":"Friedrich Quakernack",
    "wof:placetype":"venue"
},
  "geometry": {"coordinates":[9.102466,52.118385],"type":"Point"}
}