{
  "type": "Feature",
  "properties": {
    "iso:country":"DE",
    "sg:address":"Heinrich-L\u00f6we-Weg 24",
    "sg:city":"M\u00fcnster",
    "sg:phone":"+49 251/624553",
    "sg:postcode":"48167",
    "sg:province":"Nordrhein-Westfalen",
    "wof:name":"Teuber",
    "wof:placetype":"venue"
},
  "geometry": {"coordinates":[7.7266321182,51.9158401489],"type":"Point"}
}