{
  "type": "Feature",
  "properties": {
    "iso:country":"DE",
    "sg:address":"Rothenbaumchaussee 148",
    "sg:city":"Hamburg",
    "sg:phone":"+49 40/4505265",
    "sg:postcode":"20149",
    "sg:province":"Hamburg",
    "wof:name":"Mendes",
    "wof:placetype":"venue"
},
  "geometry": {"coordinates":[9.9891471863,53.5778388977],"type":"Point"}
}