{
  "type": "Feature",
  "properties": {
    "iso:country":"DE",
    "sg:address":"Karlstr. 13",
    "sg:city":"Gaildorf",
    "sg:phone":"+49 7971/335",
    "sg:postcode":"74405",
    "sg:province":"Baden-W\u00fcrttemberg",
    "wof:name":"Sonnen-lichtspiele",
    "wof:placetype":"venue"
},
  "geometry": {"coordinates":[9.771027565,48.9998550415],"type":"Point"}
}