{
  "type": "Feature",
  "properties": {
    "iso:country":"DE",
    "sg:address":"Von-Harnack-Str. 98",
    "sg:city":"Merseburg",
    "sg:phone":"+49 3461/210854",
    "sg:postcode":"06217",
    "sg:province":"Sachsen-Anhalt",
    "wof:name":"Hans Niedermeyer",
    "wof:placetype":"venue"
},
  "geometry": {"coordinates":[11.984938,51.365044],"type":"Point"}
}