{
  "type": "Feature",
  "properties": {
    "iso:country":"DE",
    "sg:address":"K\u00f6lner Str. 109",
    "sg:city":"Troisdorf",
    "sg:phone":"+49 2241",
    "sg:postcode":"53840",
    "sg:province":"Nordrhein-Westfalen",
    "wof:name":"Parketthaus",
    "wof:placetype":"venue"
},
  "geometry": {"coordinates":[7.1538357735,50.8162498474],"type":"Point"}
}