{
  "type": "Feature",
  "properties": {
    "iso:country":"DE",
    "sg:address":"Kl\u00fcver Kamp 1",
    "sg:city":"Kal\u00fcbbe",
    "sg:phone":"+49 4526/1323",
    "sg:postcode":"24326",
    "sg:province":"Schleswig-Holstein",
    "wof:name":"Dieter Saggau",
    "wof:placetype":"venue"
},
  "geometry": {"coordinates":[10.2919101715,54.1215667725],"type":"Point"}
}