{
  "type": "Feature",
  "properties": {
    "iso:country":"DE",
    "sg:address":"Allensteiner Str. 14",
    "sg:city":"Kehl",
    "sg:phone":"+49 7851/481433",
    "sg:postcode":"77694",
    "sg:province":"Baden-W\u00fcrttemberg",
    "wof:name":"Billard Club",
    "wof:placetype":"venue"
},
  "geometry": {"coordinates":[7.817076,48.577564],"type":"Point"}
}