{
  "type": "Feature",
  "properties": {
    "iso:country":"DE",
    "sg:address":"Hamburger Str. 47",
    "sg:city":"Hamburg",
    "sg:postcode":"22083",
    "sg:province":"Hamburg",
    "wof:name":"Deutsche Telekom Ag",
    "wof:placetype":"venue"
},
  "geometry": {"coordinates":[10.0339069366,53.5744781494],"type":"Point"}
}