{
  "type": "Feature",
  "properties": {
    "iso:country":"DE",
    "sg:address":"Holzbr\u00fcnnlstr. 13",
    "sg:city":"Haag",
    "sg:phone":"+49 8167/1684",
    "sg:postcode":"85410",
    "sg:province":"Bayern",
    "wof:name":"Johann Geier Gmbh",
    "wof:placetype":"venue"
},
  "geometry": {"coordinates":[11.824149,48.459644],"type":"Point"}
}