{
  "type": "Feature",
  "properties": {
    "iso:country":"DE",
    "sg:address":"Kraftsdorfer Str. 8",
    "sg:city":"Reichenbach",
    "sg:phone":"+49 36601/84100",
    "sg:postcode":"07629",
    "sg:province":"Th\u00fcringen",
    "wof:name":"Porzellanmalerei Sch\u00f6nknecht Inh. Karin Sch\u00f6nknecht",
    "wof:placetype":"venue"
},
  "geometry": {"coordinates":[11.8892345428,50.8728294373],"type":"Point"}
}