{
  "type": "Feature",
  "properties": {
    "iso:country":"DE",
    "sg:address":"Silberpappelstr. 18",
    "sg:city":"M\u00fcnchen",
    "sg:phone":"+49 89/3514352",
    "sg:postcode":"80935",
    "sg:province":"Bayern",
    "wof:name":"Kurt Fuhrmann Kunststoffwaren-eh.",
    "wof:placetype":"venue"
},
  "geometry": {"coordinates":[11.5513420105,48.1994171143],"type":"Point"}
}