{
  "type": "Feature",
  "properties": {
    "iso:country":"DE",
    "sg:address":"Kaiserstr. 32",
    "sg:city":"Mainz",
    "sg:phone":"+49 6131/234472",
    "sg:postcode":"55116",
    "sg:province":"Rheinland-Pfalz",
    "wof:name":"P & M Computersysteme Gmbh",
    "wof:placetype":"venue"
},
  "geometry": {"coordinates":[8.2642011642,50.004360199],"type":"Point"}
}