{
  "type": "Feature",
  "properties": {
    "iso:country":"DE",
    "sg:address":"Sta\u00dffurter Str. 29",
    "sg:city":"Hecklingen",
    "sg:phone":"+49 3925/281142",
    "sg:postcode":"39444",
    "sg:province":"Sachsen-Anhalt",
    "wof:name":"Rita Bringer",
    "wof:placetype":"venue"
},
  "geometry": {"coordinates":[11.537566,51.849998],"type":"Point"}
}