{
  "type": "Feature",
  "properties": {
    "iso:country":"DE",
    "sg:address":"Heinrich-Wendt-Weg 2",
    "sg:city":"Rosengarten",
    "sg:phone":"+49 40/7962527",
    "sg:postcode":"21224",
    "sg:province":"Niedersachsen",
    "wof:name":"Michael Kanebley Finanzberater",
    "wof:placetype":"venue"
},
  "geometry": {"coordinates":[9.8907022476,53.4377212524],"type":"Point"}
}