{
  "type": "Feature",
  "properties": {
    "iso:country":"DE",
    "sg:address":"Meisenweg 32",
    "sg:city":"Ahrensburg",
    "sg:phone":"+49 4102/55044",
    "sg:postcode":"22926",
    "sg:province":"Schleswig-Holstein",
    "wof:name":"Prof. Dr. W. Hummeltenberg Und Dr. R. Hummeltenberg",
    "wof:placetype":"venue"
},
  "geometry": {"coordinates":[10.2310419083,53.6468048096],"type":"Point"}
}