{
  "type": "Feature",
  "properties": {
    "iso:country":"DE",
    "sg:address":"Stra\u00dfe 1 3",
    "sg:city":"Berlin",
    "sg:phone":"+49 30/4781645",
    "sg:postcode":"13089",
    "sg:province":"Berlin",
    "wof:name":"Ce-consumer Elektronik Frank R\u00f6der",
    "wof:placetype":"venue"
},
  "geometry": {"coordinates":[13.440362,52.581364],"type":"Point"}
}