{
  "type": "Feature",
  "properties": {
    "iso:country":"DE",
    "sg:address":"Adelshofer Str. 17",
    "sg:city":"Eppingen",
    "sg:phone":"+49 7262/1668",
    "sg:postcode":"75031",
    "sg:province":"Baden-W\u00fcrttemberg",
    "wof:name":"Dr. Hans-j\u00f6rg Gebhard",
    "wof:placetype":"venue"
},
  "geometry": {"coordinates":[8.9076900482,49.1388587952],"type":"Point"}
}