{
  "type": "Feature",
  "properties": {
    "iso:country":"DE",
    "sg:address":"Untermarkt 14",
    "sg:city":"M\u00fchlhausen",
    "sg:phone":"+49 36014/26210",
    "sg:postcode":"99974",
    "sg:province":"Th\u00fcringen",
    "wof:name":"Elektro Moschcau",
    "wof:placetype":"venue"
},
  "geometry": {"coordinates":[10.4600791931,51.207157135],"type":"Point"}
}