{
  "type": "Feature",
  "properties": {
    "iso:country":"DE",
    "sg:address":"Industriestr. 3",
    "sg:city":"Winterbach",
    "sg:phone":"+49 7181/74461",
    "sg:postcode":"73650",
    "sg:province":"Baden-W\u00fcrttemberg",
    "wof:name":"Dieter Kreb",
    "wof:placetype":"venue"
},
  "geometry": {"coordinates":[9.478078,48.804089],"type":"Point"}
}