{
  "type": "Feature",
  "properties": {
    "iso:country":"DE",
    "sg:address":"Zum Fischteich 10",
    "sg:city":"Stemwede",
    "sg:phone":"+49 5745/96930",
    "sg:postcode":"32351",
    "sg:province":"Nordrhein-Westfalen",
    "wof:name":"A. Kirchhoff Gmbh & Co. Kg",
    "wof:placetype":"venue"
},
  "geometry": {"coordinates":[8.478273,52.407295],"type":"Point"}
}