{
  "type": "Feature",
  "properties": {
    "iso:country":"DE",
    "sg:address":"Schlo\u00dfstr. 28",
    "sg:city":"Plauen",
    "sg:phone":"+49 3741/221031",
    "sg:postcode":"08523",
    "sg:province":"Sachsen",
    "wof:name":"F. Haupt Immobilienmakler",
    "wof:placetype":"venue"
},
  "geometry": {"coordinates":[12.1421985626,50.4968223572],"type":"Point"}
}