{
  "type": "Feature",
  "properties": {
    "iso:country":"DE",
    "sg:address":"Hofstr. 93",
    "sg:city":"Viersen",
    "sg:phone":"+49 2162/15931",
    "sg:postcode":"41747",
    "sg:province":"Nordrhein-Westfalen",
    "wof:name":"Emil Matej",
    "wof:placetype":"venue"
},
  "geometry": {"coordinates":[6.378661,51.259624],"type":"Point"}
}