{
  "type": "Feature",
  "properties": {
    "iso:country":"DE",
    "sg:address":"Wasserstr. 3",
    "sg:city":"Sarstedt",
    "sg:phone":"+49 5066/61170",
    "sg:postcode":"31157",
    "sg:province":"Niedersachsen",
    "wof:name":"Hans-henning Brandes",
    "wof:placetype":"venue"
},
  "geometry": {"coordinates":[9.820948,52.236706],"type":"Point"}
}