{
  "type": "Feature",
  "properties": {
    "iso:country":"DE",
    "sg:address":"Tannh\u00f6f 16",
    "sg:city":"Biederbach",
    "sg:phone":"+49 7682/1603",
    "sg:postcode":"79215",
    "sg:province":"Baden-W\u00fcrttemberg",
    "wof:name":"Klaus Wernet Gmbh",
    "wof:placetype":"venue"
},
  "geometry": {"coordinates":[8.0420722961,48.1938171387],"type":"Point"}
}