{
  "type": "Feature",
  "properties": {
    "iso:country":"DE",
    "sg:address":"Aljezurstr. 19",
    "sg:city":"K\u00fcrnach",
    "sg:phone":"+49 9367/8457",
    "sg:postcode":"97273",
    "sg:province":"Bayern",
    "wof:name":"G. W. K. Immobilienb\u00f6rse E. K.",
    "wof:placetype":"venue"
},
  "geometry": {"coordinates":[10.0437097549,49.8410644531],"type":"Point"}
}