{
  "type": "Feature",
  "properties": {
    "iso:country":"DE",
    "sg:address":"Bonner Str. 25",
    "sg:city":"Meckenheim",
    "sg:phone":"+49 2225/10658",
    "sg:postcode":"53340",
    "sg:province":"Nordrhein-Westfalen",
    "wof:name":"Kutscherstube",
    "wof:placetype":"venue"
},
  "geometry": {"coordinates":[7.0215010643,50.6277389526],"type":"Point"}
}