{
  "type": "Feature",
  "properties": {
    "iso:country":"DE",
    "sg:address":"Eichsfelder Str. 2",
    "sg:city":"Neu-Eichenberg",
    "sg:phone":"+49 5542/3167",
    "sg:postcode":"37249",
    "sg:province":"Hessen",
    "wof:name":"J\u00fcrgen Bartels",
    "wof:placetype":"venue"
},
  "geometry": {"coordinates":[9.9227104187,51.3771133423],"type":"Point"}
}