{
  "type": "Feature",
  "properties": {
    "iso:country":"DE",
    "sg:address":"Steuerwalder Str. 162",
    "sg:city":"Hildesheim",
    "sg:phone":"+49 5121/513121",
    "sg:postcode":"31137",
    "sg:province":"Niedersachsen",
    "wof:name":"R. Kirchhoff",
    "wof:placetype":"venue"
},
  "geometry": {"coordinates":[9.936819,52.169796],"type":"Point"}
}