{
  "type": "Feature",
  "properties": {
    "iso:country":"DE",
    "sg:address":"Riedstr. 8",
    "sg:city":"Wilhelmsdorf",
    "sg:phone":"+49 7503/377",
    "sg:postcode":"88271",
    "sg:province":"Baden-W\u00fcrttemberg",
    "wof:name":"Karl Reichle",
    "wof:placetype":"venue"
},
  "geometry": {"coordinates":[9.3992834091,47.873134613],"type":"Point"}
}