{
  "type": "Feature",
  "properties": {
    "iso:country":"DE",
    "sg:address":"Am Gro\u00dfen Wallgraben 17",
    "sg:city":"Schwalmstadt",
    "sg:phone":"+49 6691/4301",
    "sg:postcode":"34613",
    "sg:province":"Hessen",
    "wof:name":"Reinhard Vogel",
    "wof:placetype":"venue"
},
  "geometry": {"coordinates":[9.2321090698,50.9116821289],"type":"Point"}
}