{
  "type": "Feature",
  "properties": {
    "iso:country":"DE",
    "sg:address":"Spelzenstr. 3",
    "sg:city":"Mannheim",
    "sg:phone":"+49 621/374710",
    "sg:postcode":"68167",
    "sg:province":"Baden-W\u00fcrttemberg",
    "wof:name":"Barbara Friedrich",
    "wof:placetype":"venue"
},
  "geometry": {"coordinates":[8.472281,49.499115],"type":"Point"}
}