{
  "type": "Feature",
  "properties": {
    "iso:country":"DE",
    "sg:address":"H\u00f6cherbergstr. 157",
    "sg:city":"Bexbach",
    "sg:phone":"+49 6826/81645",
    "sg:postcode":"66450",
    "sg:province":"Saarland",
    "wof:name":"Lothar M\u00fcller",
    "wof:placetype":"venue"
},
  "geometry": {"coordinates":[7.2660579681,49.37292099],"type":"Point"}
}