{
  "type": "Feature",
  "properties": {
    "iso:country":"DE",
    "sg:address":"Alte Str.",
    "sg:city":"G\u00f6rsbach",
    "sg:phone":"+49 36333/70284",
    "sg:postcode":"99765",
    "sg:province":"Th\u00fcringen",
    "wof:name":"Agrarproduktion Goldene Aue Gmbh",
    "wof:placetype":"venue"
},
  "geometry": {"coordinates":[10.939635,51.464066],"type":"Point"}
}