{
  "type": "Feature",
  "properties": {
    "iso:country":"DE",
    "sg:address":"Schabenberg 10",
    "sg:city":"Pfaffenhofen/Ilm",
    "sg:phone":"+49 8441/4981274",
    "sg:postcode":"85276",
    "sg:province":"Bayern",
    "wof:name":"G\u00fcrtlerei Gr\u00fcger",
    "wof:placetype":"venue"
},
  "geometry": {"coordinates":[11.440499,48.532974],"type":"Point"}
}