{
  "type": "Feature",
  "properties": {
    "iso:country":"DE",
    "sg:address":"Hauptstr. 48",
    "sg:city":"Handeloh",
    "sg:phone":"+49 4188/7350",
    "sg:postcode":"21256",
    "sg:province":"Niedersachsen",
    "wof:name":"Volksbank Buchholz Eg",
    "wof:placetype":"venue"
},
  "geometry": {"coordinates":[9.845846,53.242443],"type":"Point"}
}