{
  "type": "Feature",
  "properties": {
    "iso:country":"DE",
    "sg:address":"Koepestr. 10-12",
    "sg:city":"Erkelenz",
    "sg:postcode":"41812",
    "sg:province":"Nordrhein-Westfalen",
    "wof:name":"Dawi Verwaltungs Gmbh",
    "wof:placetype":"venue"
},
  "geometry": {"coordinates":[6.326003,51.074547],"type":"Point"}
}