{
  "type": "Feature",
  "properties": {
    "iso:country":"DE",
    "sg:address":"Vockestr. 14",
    "sg:city":"Haar",
    "sg:postcode":"85540",
    "sg:province":"Bayern",
    "wof:name":"Rodler It-consulting Gmbh",
    "wof:placetype":"venue"
},
  "geometry": {"coordinates":[11.7370786667,48.106678009],"type":"Point"}
}