{
  "type": "Feature",
  "properties": {
    "iso:country":"DE",
    "sg:address":"Mirander Str. 21",
    "sg:city":"Korntal-M\u00fcnchingen",
    "sg:phone":"+49 711/8399510",
    "sg:postcode":"70825",
    "sg:province":"Baden-W\u00fcrttemberg",
    "wof:name":"Comdata B\u00fcrogestaltung Gmbh",
    "wof:placetype":"venue"
},
  "geometry": {"coordinates":[9.120647,48.831177],"type":"Point"}
}