{
  "type": "Feature",
  "properties": {
    "iso:country":"DE",
    "sg:address":"Werderstr. 2",
    "sg:city":"Niemegk",
    "sg:phone":"+49 33843/6220",
    "sg:postcode":"14823",
    "sg:province":"Brandenburg",
    "wof:name":"Eng Elektro Niemegk Gmbh",
    "wof:placetype":"venue"
},
  "geometry": {"coordinates":[12.6863555908,52.0771865845],"type":"Point"}
}