{
  "type": "Feature",
  "properties": {
    "iso:country":"DE",
    "sg:address":"Hansestr. 25",
    "sg:city":"Braunschweig",
    "sg:phone":"+49 531/316719",
    "sg:postcode":"38112",
    "sg:province":"Niedersachsen",
    "wof:name":"Bahr Baumarkt",
    "wof:placetype":"venue"
},
  "geometry": {"coordinates":[10.506529808,52.3086891174],"type":"Point"}
}