{
  "type": "Feature",
  "properties": {
    "iso:country":"DE",
    "sg:address":"Hitdorfer Kirchweg 25-27",
    "sg:city":"Leverkusen",
    "sg:phone":"+49 2173/40461",
    "sg:postcode":"51371",
    "sg:province":"Nordrhein-Westfalen",
    "wof:name":"Wero Plast Gmbh",
    "wof:placetype":"venue"
},
  "geometry": {"coordinates":[6.926439,51.056946],"type":"Point"}
}