{
  "type": "Feature",
  "properties": {
    "iso:country":"DE",
    "sg:address":"Insel 9a",
    "sg:city":"Zella-Mehlis",
    "sg:phone":"+49 3682/482856",
    "sg:postcode":"98544",
    "sg:province":"Th\u00fcringen",
    "wof:name":"Carl Greiner Gmbh",
    "wof:placetype":"venue"
},
  "geometry": {"coordinates":[10.651405,50.658913],"type":"Point"}
}