{
  "type": "Feature",
  "properties": {
    "iso:country":"DE",
    "sg:address":"Contrescarpe 52",
    "sg:city":"Bremen",
    "sg:phone":"+49 421/323020",
    "sg:postcode":"28195",
    "sg:province":"Bremen",
    "wof:name":"S. Brumloop Architekt",
    "wof:placetype":"venue"
},
  "geometry": {"coordinates":[8.813475,53.077785],"type":"Point"}
}