{
  "type": "Feature",
  "properties": {
    "iso:country":"DE",
    "sg:address":"Industriestr. 94",
    "sg:city":"Langenfeld",
    "sg:phone":"+49 2173/250202",
    "sg:postcode":"40764",
    "sg:province":"Nordrhein-Westfalen",
    "wof:name":"Autolackiererei Dernen Gmbh",
    "wof:placetype":"venue"
},
  "geometry": {"coordinates":[6.9554548264,51.1266517639],"type":"Point"}
}