{
  "type": "Feature",
  "properties": {
    "iso:country":"DE",
    "sg:address":"Geigerstr. 75",
    "sg:city":"N\u00fcrnberg",
    "sg:phone":"+49 911/6383272",
    "sg:postcode":"90453",
    "sg:province":"Bayern",
    "wof:name":"A. Fischer",
    "wof:placetype":"venue"
},
  "geometry": {"coordinates":[11.0330047607,49.3906860352],"type":"Point"}
}