{
  "type": "Feature",
  "properties": {
    "iso:country":"DE",
    "sg:address":"Veltener Chaussee",
    "sg:city":"Borgsdorf",
    "sg:postcode":"16556",
    "sg:province":"Brandenburg",
    "wof:name":"Lst Freizeitgestaltungs Gmbh",
    "wof:placetype":"venue"
},
  "geometry": {"coordinates":[13.268494606,52.7061500549],"type":"Point"}
}