{
  "type": "Feature",
  "properties": {
    "iso:country":"DE",
    "sg:address":"Mergentheimer Str. 26",
    "sg:city":"W\u00fcrzburg",
    "sg:phone":"+49 931/87670",
    "sg:postcode":"97082",
    "sg:province":"Bayern",
    "wof:name":"Frank-peter Hohmann Rechtsanwalt",
    "wof:placetype":"venue"
},
  "geometry": {"coordinates":[9.9246263504,49.7848701477],"type":"Point"}
}