{
  "type": "Feature",
  "properties": {
    "iso:country":"DE",
    "sg:address":"Weinbergstr. 3",
    "sg:city":"Gochsheim",
    "sg:phone":"+49 9721/63331",
    "sg:postcode":"97469",
    "sg:province":"Bayern",
    "wof:name":"B\u00fcchner & R\u00e4th Gmbh",
    "wof:placetype":"venue"
},
  "geometry": {"coordinates":[10.283908,50.022701],"type":"Point"}
}