{
  "type": "Feature",
  "properties": {
    "iso:country":"DE",
    "sg:address":"Stettener Str. 2 a",
    "sg:city":"Prien",
    "sg:phone":"+49 8051/89988",
    "sg:postcode":"83209",
    "sg:province":"Bayern",
    "wof:name":"H. Bromberg Immobilienmakler",
    "wof:placetype":"venue"
},
  "geometry": {"coordinates":[12.316447258,47.8458137512],"type":"Point"}
}