{
  "type": "Feature",
  "properties": {
    "iso:country":"DE",
    "sg:address":"Schussenrieder Str. 61",
    "sg:city":"Bad Buchau",
    "sg:phone":"+49 7582/2927",
    "sg:postcode":"88422",
    "sg:province":"Baden-W\u00fcrttemberg",
    "wof:name":"Pizzeria Buchauer Hof",
    "wof:placetype":"venue"
},
  "geometry": {"coordinates":[9.6137828827,48.061504364],"type":"Point"}
}