{
  "type": "Feature",
  "properties": {
    "iso:country":"DE",
    "sg:address":"Speckenstr. 2",
    "sg:city":"Dorum",
    "sg:phone":"+49 4742/2031",
    "sg:postcode":"27632",
    "sg:province":"Niedersachsen",
    "wof:name":"L\u00f6wen-apotheke",
    "wof:placetype":"venue"
},
  "geometry": {"coordinates":[8.567427,53.687992],"type":"Point"}
}