{
  "type": "Feature",
  "properties": {
    "iso:country":"DE",
    "sg:address":"Finkenweg 6",
    "sg:city":"Sch\u00f6nbrunn",
    "sg:phone":"+49 6262/2308",
    "sg:postcode":"69436",
    "sg:province":"Baden-W\u00fcrttemberg",
    "wof:name":"Lector Computersysteme Gmbh",
    "wof:placetype":"venue"
},
  "geometry": {"coordinates":[8.9177103043,49.3940315247],"type":"Point"}
}