{
  "type": "Feature",
  "properties": {
    "iso:country":"DE",
    "sg:address":"Herdweg 7",
    "sg:city":"H\u00fcttisheim",
    "sg:phone":"+49 7305/6810",
    "sg:postcode":"89185",
    "sg:province":"Baden-W\u00fcrttemberg",
    "wof:name":"Alfred Magg",
    "wof:placetype":"venue"
},
  "geometry": {"coordinates":[9.9461946487,48.2763175964],"type":"Point"}
}