{
  "type": "Feature",
  "properties": {
    "iso:country":"DE",
    "sg:address":"Bayreuther Str. 8",
    "sg:city":"Kirchenthumbach",
    "sg:phone":"+49 9647/421",
    "sg:postcode":"91281",
    "sg:province":"Bayern",
    "wof:name":"F. Sporer",
    "wof:placetype":"venue"
},
  "geometry": {"coordinates":[11.7251529694,49.7501945496],"type":"Point"}
}