{
  "type": "Feature",
  "properties": {
    "iso:country":"DE",
    "sg:address":"An der Bahn 2",
    "sg:city":"Bergen",
    "sg:phone":"+49 5051/4760",
    "sg:postcode":"29303",
    "sg:province":"Niedersachsen",
    "wof:name":"G\u00fcnter Borchardt Gmbh & Co. Kg",
    "wof:placetype":"venue"
},
  "geometry": {"coordinates":[9.9742660522,52.8105163574],"type":"Point"}
}