{
  "type": "Feature",
  "properties": {
    "iso:country":"DE",
    "sg:address":"Bergstr. 9",
    "sg:city":"Dorfhain",
    "sg:phone":"+49 35055/61841",
    "sg:postcode":"01738",
    "sg:province":"Sachsen",
    "wof:name":"Hans Ebert",
    "wof:placetype":"venue"
},
  "geometry": {"coordinates":[13.567287,50.932735],"type":"Point"}
}