{
  "type": "Feature",
  "properties": {
    "iso:country":"DE",
    "sg:address":"Industriestr. 3",
    "sg:city":"Waldmohr",
    "sg:phone":"+49 6373/81480",
    "sg:postcode":"66914",
    "sg:province":"Rheinland-Pfalz",
    "wof:name":"Metronic Gr\u00fcnenwald Ohg",
    "wof:placetype":"venue"
},
  "geometry": {"coordinates":[7.3462262154,49.3832702637],"type":"Point"}
}