{
  "type": "Feature",
  "properties": {
    "iso:country":"DE",
    "sg:address":"Rathausstr. 54",
    "sg:city":"Wittenberge",
    "sg:phone":"+49 3877/68117",
    "sg:postcode":"19322",
    "sg:province":"Brandenburg",
    "wof:name":"Heike Sch\u00f6nfu\u00df",
    "wof:placetype":"venue"
},
  "geometry": {"coordinates":[11.7574491501,52.9961509705],"type":"Point"}
}