{
  "type": "Feature",
  "properties": {
    "iso:country":"DE",
    "sg:address":"Breitlerstr. 72",
    "sg:city":"Bad Sobernheim",
    "sg:phone":"+49 6751/2390",
    "sg:postcode":"55566",
    "sg:province":"Rheinland-Pfalz",
    "wof:name":"M. Hammel",
    "wof:placetype":"venue"
},
  "geometry": {"coordinates":[7.628387,49.786026],"type":"Point"}
}