{
  "type": "Feature",
  "properties": {
    "iso:country":"DE",
    "sg:address":"Frankfurter Str. 10-14",
    "sg:city":"Eschborn",
    "sg:postcode":"65760",
    "sg:province":"Hessen",
    "wof:name":"Penta Hotel-managementges. Mbh",
    "wof:placetype":"venue"
},
  "geometry": {"coordinates":[8.5667695999,50.1321792603],"type":"Point"}
}