{
  "type": "Feature",
  "properties": {
    "iso:country":"DE",
    "sg:address":"Karlstr. 10",
    "sg:city":"Arnsberg",
    "sg:postcode":"59755",
    "sg:province":"Nordrhein-Westfalen",
    "wof:name":"Planungsb\u00fcro Keggenhoff Und Partner",
    "wof:placetype":"venue"
},
  "geometry": {"coordinates":[7.96654,51.45187],"type":"Point"}
}