{
  "type": "Feature",
  "properties": {
    "iso:country":"DE",
    "sg:address":"Lange Str. 40",
    "sg:city":"Glattbach",
    "sg:phone":"+49 6021/42467",
    "sg:postcode":"63864",
    "sg:province":"Bayern",
    "wof:name":"Kath. Pfarramt",
    "wof:placetype":"venue"
},
  "geometry": {"coordinates":[9.1479082108,50.0048027039],"type":"Point"}
}