{
  "type": "Feature",
  "properties": {
    "iso:country":"DE",
    "sg:address":"Lenaustr. 10",
    "sg:city":"Andernach",
    "sg:phone":"+49 2632/46941",
    "sg:postcode":"56626",
    "sg:province":"Rheinland-Pfalz",
    "wof:name":"Vulkan Satz Und Repro Ohg Alfasser & Baldauf",
    "wof:placetype":"venue"
},
  "geometry": {"coordinates":[7.4175238609,50.4298667908],"type":"Point"}
}