{
  "type": "Feature",
  "properties": {
    "iso:country":"DE",
    "sg:address":"Margaretenh\u00f6he 19",
    "sg:city":"Mudersbach",
    "sg:phone":"+49 271/381041",
    "sg:postcode":"57555",
    "sg:province":"Rheinland-Pfalz",
    "wof:name":"Friedrich Steiner",
    "wof:placetype":"venue"
},
  "geometry": {"coordinates":[7.956114769,50.8312072754],"type":"Point"}
}