{
  "type": "Feature",
  "properties": {
    "iso:country":"DE",
    "sg:address":"Wildsachsener Str. 16",
    "sg:city":"Hofheim",
    "sg:phone":"+49 6192/3512",
    "sg:postcode":"65719",
    "sg:province":"Hessen",
    "wof:name":"Kleintierzuchtverein Diedenbergen",
    "wof:placetype":"venue"
},
  "geometry": {"coordinates":[8.4166612625,50.0622673035],"type":"Point"}
}