{
  "type": "Feature",
  "properties": {
    "iso:country":"DE",
    "sg:address":"Schlo\u00df H\u00fclchrath",
    "sg:city":"Grevenbroich",
    "sg:phone":"+49 2182/60987",
    "sg:postcode":"41516",
    "sg:province":"Nordrhein-Westfalen",
    "wof:name":"C. Wennmacher Rechtsanwalt",
    "wof:placetype":"venue"
},
  "geometry": {"coordinates":[6.6573572159,51.1242294312],"type":"Point"}
}