{
  "type": "Feature",
  "properties": {
    "iso:country":"DE",
    "sg:address":"Luruper Hauptstr. 251",
    "sg:city":"Hamburg",
    "sg:phone":"+49 40/8317327",
    "sg:postcode":"22547",
    "sg:province":"Hamburg",
    "wof:name":"Spedition Friedrich M\u00fcller Ohg",
    "wof:placetype":"venue"
},
  "geometry": {"coordinates":[9.861328125,53.5977287292],"type":"Point"}
}