{
  "type": "Feature",
  "properties": {
    "iso:country":"DE",
    "sg:address":"Friedenstr. 19",
    "sg:city":"Pforzheim",
    "sg:postcode":"75173",
    "sg:province":"Baden-W\u00fcrttemberg",
    "wof:name":"Rolf Johannes Lauterbach Kg",
    "wof:placetype":"venue"
},
  "geometry": {"coordinates":[8.6931934357,48.883190155],"type":"Point"}
}