{
  "type": "Feature",
  "properties": {
    "iso:country":"DE",
    "sg:address":"Schwerblm\u00fchle 4",
    "sg:city":"Prem",
    "sg:phone":"+49 4975/6493200",
    "sg:postcode":"86984",
    "sg:province":"Bayern",
    "wof:name":"Gebr. Josef U. Paul Merk Holzbau - Saegewerk-gmbh",
    "wof:placetype":"venue"
},
  "geometry": {"coordinates":[9.8666343689,47.952922821],"type":"Point"}
}