{
  "type": "Feature",
  "properties": {
    "iso:country":"DE",
    "sg:address":"Richard-Wagner-Str. 117",
    "sg:city":"Offenbach",
    "sg:phone":"+49 69/834631",
    "sg:postcode":"63069",
    "sg:province":"Hessen",
    "wof:name":"Ev. Pfarramt Lauterborn I",
    "wof:placetype":"venue"
},
  "geometry": {"coordinates":[8.7557058334,50.0833396912],"type":"Point"}
}