{
  "type": "Feature",
  "properties": {
    "iso:country":"DE",
    "sg:address":"Hauptstr. 57",
    "sg:city":"Mengerskirchen",
    "sg:phone":"+49 6476/8855",
    "sg:postcode":"35794",
    "sg:province":"Hessen",
    "wof:name":"M. Hastrich",
    "wof:placetype":"venue"
},
  "geometry": {"coordinates":[8.154071,50.564484],"type":"Point"}
}