{
  "type": "Feature",
  "properties": {
    "iso:country":"DE",
    "sg:address":"Tischlereistr 1",
    "sg:city":"Liebsch\u00fctzberg",
    "sg:phone":"+49 3435/67150",
    "sg:postcode":"04758",
    "sg:province":"Sachsen",
    "wof:name":"Eduard Gehr Fensterfertigung U. T\u00fcrenbau, Ladenbau U. Objekteinrichtung",
    "wof:placetype":"venue"
},
  "geometry": {"coordinates":[13.111285,51.321861],"type":"Point"}
}