{
  "type": "Feature",
  "properties": {
    "iso:country":"DE",
    "sg:address":"Wilhelmshavener Heerstr. 65",
    "sg:city":"Oldenburg",
    "sg:phone":"+49 441/93550",
    "sg:postcode":"26125",
    "sg:province":"Niedersachsen",
    "wof:name":"Erich Hinsche K\u00e4lte- Klima- K\u00fcchen Produktions- Und",
    "wof:placetype":"venue"
},
  "geometry": {"coordinates":[8.22957,53.174343],"type":"Point"}
}