{
  "type": "Feature",
  "properties": {
    "iso:country":"DE",
    "sg:address":"Sachsenberger Str. 22",
    "sg:city":"Frankenberg",
    "sg:phone":"+49 6451/8286",
    "sg:postcode":"35066",
    "sg:province":"Hessen",
    "wof:name":"Werner Schmidt",
    "wof:placetype":"venue"
},
  "geometry": {"coordinates":[8.7993373871,51.08360672],"type":"Point"}
}