{
  "type": "Feature",
  "properties": {
    "iso:country":"DE",
    "sg:address":"S\u00fcd-Chemie-Str. 3",
    "sg:city":"Kelheim",
    "sg:postcode":"93309",
    "sg:province":"Bayern",
    "wof:name":"Rvb Ges. F\u00fcr Recycling Verwertung U. Beseitigung",
    "wof:placetype":"venue"
},
  "geometry": {"coordinates":[11.9121322632,48.9040870667],"type":"Point"}
}