{
  "type": "Feature",
  "properties": {
    "iso:country":"DE",
    "sg:address":"Parkstr. 52",
    "sg:city":"Hude",
    "sg:phone":"+49 4408/60707",
    "sg:postcode":"27798",
    "sg:province":"Niedersachsen",
    "wof:name":"Diakonie-sozialstation",
    "wof:placetype":"venue"
},
  "geometry": {"coordinates":[8.456713,53.113728],"type":"Point"}
}