{
  "type": "Feature",
  "properties": {
    "iso:country":"DE",
    "sg:address":"Schwarzwaldstr. 31",
    "sg:city":"Heidelberg",
    "sg:phone":"+49 6221/720071",
    "sg:postcode":"69124",
    "sg:province":"Baden-W\u00fcrttemberg",
    "wof:name":"Dr. Med. Anselmus Thimm Arzt F\u00fcr Allgemeinmedizin",
    "wof:placetype":"venue"
},
  "geometry": {"coordinates":[8.6592760086,49.3805541992],"type":"Point"}
}