{
  "type": "Feature",
  "properties": {
    "iso:country":"DE",
    "sg:address":"Auf der Kr\u00e4h 2",
    "sg:city":"L\u00f6f",
    "sg:phone":"+49 2605/1703",
    "sg:postcode":"56332",
    "sg:province":"Rheinland-Pfalz",
    "wof:name":"Landhaus Kr\u00e4hennest Inh. Erwin Stenger",
    "wof:placetype":"venue"
},
  "geometry": {"coordinates":[7.4419789314,50.2311553955],"type":"Point"}
}