{
  "type": "Feature",
  "properties": {
    "iso:country":"DE",
    "sg:address":"Gerhard-Rohlfs-Str. 54c",
    "sg:city":"Bremen",
    "sg:phone":"+49 421/667011",
    "sg:postcode":"28757",
    "sg:province":"Bremen",
    "wof:name":"Bermpohl-apotheke",
    "wof:placetype":"venue"
},
  "geometry": {"coordinates":[8.614301,53.174149],"type":"Point"}
}