{
  "type": "Feature",
  "properties": {
    "iso:country":"DE",
    "sg:address":"Kirchbrunnenstr. 11",
    "sg:city":"Heilbronn",
    "sg:phone":"+49 7131/84013",
    "sg:postcode":"74072",
    "sg:province":"Baden-W\u00fcrttemberg",
    "wof:name":"Heilbronner Teeladen",
    "wof:placetype":"venue"
},
  "geometry": {"coordinates":[9.2172260284,49.141582489],"type":"Point"}
}