{
  "type": "Feature",
  "properties": {
    "iso:country":"DE",
    "sg:address":"Bahnhofstr. 4",
    "sg:city":"Extertal",
    "sg:phone":"+49 5262/4959",
    "sg:postcode":"32699",
    "sg:province":"Nordrhein-Westfalen",
    "wof:name":"B. & B.",
    "wof:placetype":"venue"
},
  "geometry": {"coordinates":[9.121743,52.068546],"type":"Point"}
}