{
  "type": "Feature",
  "properties": {
    "iso:country":"DE",
    "sg:address":"Alte Dorfstr. 11",
    "sg:city":"Estorf",
    "sg:phone":"+49 5025/397",
    "sg:postcode":"31629",
    "sg:province":"Niedersachsen",
    "wof:name":"Peter Springer",
    "wof:placetype":"venue"
},
  "geometry": {"coordinates":[9.138244,52.589954],"type":"Point"}
}