{
  "type": "Feature",
  "properties": {
    "iso:country":"DE",
    "sg:address":"Gellertstr. 39",
    "sg:city":"Karlsruhe",
    "sg:phone":"+49 721/551328",
    "sg:postcode":"76185",
    "sg:province":"Baden-W\u00fcrttemberg",
    "wof:name":"Alten- Und Pflegeheim Schmitz",
    "wof:placetype":"venue"
},
  "geometry": {"coordinates":[8.365961,49.010464],"type":"Point"}
}