{
  "type": "Feature",
  "properties": {
    "iso:country":"DE",
    "sg:address":"Dechant-Spr\u00fcnken-Str. 24",
    "sg:city":"Emmerich",
    "sg:phone":"+49 2822/51834",
    "sg:postcode":"46446",
    "sg:province":"Nordrhein-Westfalen",
    "wof:name":"Heinrich Van Holt",
    "wof:placetype":"venue"
},
  "geometry": {"coordinates":[6.264091,51.841663],"type":"Point"}
}