{
  "type": "Feature",
  "properties": {
    "iso:country":"DE",
    "sg:address":"Helmstedter Str. 35",
    "sg:city":"Braunschweig",
    "sg:phone":"+49 531/796608",
    "sg:postcode":"38102",
    "sg:province":"Niedersachsen",
    "wof:name":"B. Brandes",
    "wof:placetype":"venue"
},
  "geometry": {"coordinates":[10.545290947,52.2582702637],"type":"Point"}
}