{
  "type": "Feature",
  "properties": {
    "iso:country":"DE",
    "sg:address":"Dortmunder Str. 144",
    "sg:city":"Castrop-Rauxel",
    "sg:phone":"+49 2305/23023",
    "sg:postcode":"44577",
    "sg:province":"Nordrhein-Westfalen",
    "wof:name":"Gl\u00fcckauf-apotheke",
    "wof:placetype":"venue"
},
  "geometry": {"coordinates":[7.330944,51.542797],"type":"Point"}
}