{
  "type": "Feature",
  "properties": {
    "iso:country":"DE",
    "sg:address":"Sandwiesenstr. 1",
    "sg:city":"Waiblingen",
    "sg:phone":"+49 7151/37658",
    "sg:postcode":"71334",
    "sg:province":"Baden-W\u00fcrttemberg",
    "wof:name":"J\u00f6rn-udo Baur Arzt F\u00fcr Allgemeinmedizin",
    "wof:placetype":"venue"
},
  "geometry": {"coordinates":[9.3449497223,48.8207817078],"type":"Point"}
}