{
  "type": "Feature",
  "properties": {
    "iso:country":"DE",
    "sg:address":"Am Waldessaum 10",
    "sg:city":"Altenburg",
    "sg:postcode":"04600",
    "sg:province":"Th\u00fcringen",
    "wof:name":"Mzla Gmbh",
    "wof:placetype":"venue"
},
  "geometry": {"coordinates":[12.4408302307,50.9722175598],"type":"Point"}
}