{
  "type": "Feature",
  "properties": {
    "iso:country":"DE",
    "sg:address":"Schulstr. 17",
    "sg:city":"Schleching",
    "sg:phone":"+49 8649/500",
    "sg:postcode":"83259",
    "sg:province":"Bayern",
    "wof:name":"Ernst Daxberger",
    "wof:placetype":"venue"
},
  "geometry": {"coordinates":[12.392539978,47.7189292908],"type":"Point"}
}