{
  "type": "Feature",
  "properties": {
    "iso:country":"DE",
    "sg:address":"Blumenstr. 5",
    "sg:city":"Osthofen",
    "sg:phone":"+49 6242/7296",
    "sg:postcode":"67574",
    "sg:province":"Rheinland-Pfalz",
    "wof:name":"U. May Immobilienmakler",
    "wof:placetype":"venue"
},
  "geometry": {"coordinates":[8.3289680481,49.7053947449],"type":"Point"}
}