{
  "type": "Feature",
  "properties": {
    "iso:country":"DE",
    "sg:address":"Hirsauer Str.",
    "sg:city":"Offenbach-Hundheim",
    "sg:phone":"+49 6382/6447",
    "sg:postcode":"67749",
    "sg:province":"Rheinland-Pfalz",
    "wof:name":"Vfr Hundheim Fu\u00dfballverein",
    "wof:placetype":"venue"
},
  "geometry": {"coordinates":[7.540312767,49.6166419983],"type":"Point"}
}