{
  "type": "Feature",
  "properties": {
    "iso:country":"DE",
    "sg:address":"Silostr. 22",
    "sg:city":"J\u00fcchen",
    "sg:postcode":"41363",
    "sg:province":"Nordrhein-Westfalen",
    "wof:name":"Ggw Gesellschaft Genossen- Schaftlicher Warengesch\u00e4fte",
    "wof:placetype":"venue"
},
  "geometry": {"coordinates":[6.49633,51.09721],"type":"Point"}
}