{
  "type": "Feature",
  "properties": {
    "iso:country":"DE",
    "sg:address":"Eichenweg 1",
    "sg:city":"N\u00fcrtingen",
    "sg:phone":"+49 7022/32124",
    "sg:postcode":"72622",
    "sg:province":"Baden-W\u00fcrttemberg",
    "wof:name":"Sl Haus- Und Eigentums- Verwaltung S. Leopold",
    "wof:placetype":"venue"
},
  "geometry": {"coordinates":[9.3364629745,48.6216773987],"type":"Point"}
}