{
  "type": "Feature",
  "properties": {
    "iso:country":"DE",
    "sg:address":"Grimmaische Str. 37",
    "sg:city":"Nerchau",
    "sg:phone":"+49 34382/41316",
    "sg:postcode":"04685",
    "sg:province":"Sachsen",
    "wof:name":"Stefanie Stutte Steuerberaterin Und",
    "wof:placetype":"venue"
},
  "geometry": {"coordinates":[12.7935085297,51.2660064697],"type":"Point"}
}