{
  "type": "Feature",
  "properties": {
    "iso:country":"DE",
    "sg:address":"Wittenberger Str. 21",
    "sg:city":"Berlin",
    "sg:phone":"+49 30/9329119",
    "sg:postcode":"12689",
    "sg:province":"Berlin",
    "wof:name":"Dr. Med. Michael Klauck Arzt F\u00fcr Allgemeinmedizin",
    "wof:placetype":"venue"
},
  "geometry": {"coordinates":[13.5671062469,52.5649833679],"type":"Point"}
}