{
  "type": "Feature",
  "properties": {
    "iso:country":"DE",
    "sg:address":"Triftstr. 126",
    "sg:city":"Kleve",
    "sg:phone":"+49 2821/75400",
    "sg:postcode":"47533",
    "sg:province":"Nordrhein-Westfalen",
    "wof:name":"Syntek Grund- Und Projektentwicklung Gmbh",
    "wof:placetype":"venue"
},
  "geometry": {"coordinates":[6.1320371628,51.7734832764],"type":"Point"}
}