{
  "type": "Feature",
  "properties": {
    "iso:country":"DE",
    "sg:address":"Fritz am Sand 1",
    "sg:city":"Ruhpolding",
    "sg:phone":"+49 8663/8840",
    "sg:postcode":"83324",
    "sg:province":"Bayern",
    "wof:name":"Gasthof Fritz Am Sand",
    "wof:placetype":"venue"
},
  "geometry": {"coordinates":[12.6628637314,47.7315177917],"type":"Point"}
}