{
  "type": "Feature",
  "properties": {
    "iso:country":"DE",
    "sg:address":"Konrad-Adenauer-Platz 10",
    "sg:city":"M\u00fchlacker",
    "sg:phone":"+49 7041/45711",
    "sg:postcode":"75417",
    "sg:province":"Baden-W\u00fcrttemberg",
    "wof:name":"Flipp In",
    "wof:placetype":"venue"
},
  "geometry": {"coordinates":[8.8395261765,48.9462203979],"type":"Point"}
}