{
  "type": "Feature",
  "properties": {
    "iso:country":"DE",
    "sg:address":"Erkelenzer Str. 48",
    "sg:city":"Wassenberg",
    "sg:phone":"+49 2432/3549",
    "sg:postcode":"41849",
    "sg:province":"Nordrhein-Westfalen",
    "wof:name":"Pension Goertz",
    "wof:placetype":"venue"
},
  "geometry": {"coordinates":[6.1715559959,51.1029472351],"type":"Point"}
}