{
  "type": "Feature",
  "properties": {
    "iso:country":"DE",
    "sg:address":"Weidestr. 8",
    "sg:city":"Hamburg",
    "sg:phone":"+49 40/295634",
    "sg:postcode":"22083",
    "sg:province":"Hamburg",
    "wof:name":"G. Abitz",
    "wof:placetype":"venue"
},
  "geometry": {"coordinates":[10.0390853882,53.5805091858],"type":"Point"}
}