{
  "type": "Feature",
  "properties": {
    "iso:country":"DE",
    "sg:address":"Nerzweg 4",
    "sg:city":"Hamm",
    "sg:phone":"+49 2381/81450",
    "sg:postcode":"59071",
    "sg:province":"Nordrhein-Westfalen",
    "wof:name":"Harry Gallert",
    "wof:placetype":"venue"
},
  "geometry": {"coordinates":[7.872592,51.693356],"type":"Point"}
}