{
  "type": "Feature",
  "properties": {
    "iso:country":"DE",
    "sg:address":"Knappenstr. 80",
    "sg:city":"Sulzbach",
    "sg:phone":"+49 6897/53369",
    "sg:postcode":"66280",
    "sg:province":"Saarland",
    "wof:name":"Rosel Becker",
    "wof:placetype":"venue"
},
  "geometry": {"coordinates":[7.061395,49.309929],"type":"Point"}
}