{
  "type": "Feature",
  "properties": {
    "iso:country":"DE",
    "sg:address":"Lilistr. 83b-c",
    "sg:city":"Offenbach",
    "sg:phone":"+49 69/8297630",
    "sg:postcode":"63067",
    "sg:province":"Hessen",
    "wof:name":"World Design & Trade Co. Limited",
    "wof:placetype":"venue"
},
  "geometry": {"coordinates":[8.7428503036,50.1069412231],"type":"Point"}
}