{
  "type": "Feature",
  "properties": {
    "iso:country":"DE",
    "sg:address":"Kreisstr. 90a",
    "sg:city":"Selm",
    "sg:phone":"+49 2592/981000",
    "sg:postcode":"59379",
    "sg:province":"Nordrhein-Westfalen",
    "wof:name":"Zarfl",
    "wof:placetype":"venue"
},
  "geometry": {"coordinates":[7.4674749374,51.6864356995],"type":"Point"}
}