{
  "type": "Feature",
  "properties": {
    "iso:country":"DE",
    "sg:address":"Kirchstr. 7 b",
    "sg:city":"R\u00fcdesheim am Rhein",
    "sg:phone":"+49 6722/48592",
    "sg:postcode":"65385",
    "sg:province":"Hessen",
    "wof:name":"V. M\u00fcller",
    "wof:placetype":"venue"
},
  "geometry": {"coordinates":[7.9252519608,49.979434967],"type":"Point"}
}