{
  "type": "Feature",
  "properties": {
    "iso:country":"DE",
    "sg:address":"Maximilianstr.",
    "sg:city":"Memmingen",
    "sg:phone":"+49 8331/4228",
    "sg:postcode":"87700",
    "sg:province":"Bayern",
    "wof:name":"Reinhold-fashion",
    "wof:placetype":"venue"
},
  "geometry": {"coordinates":[10.1852169037,47.9855766296],"type":"Point"}
}