{
  "type": "Feature",
  "properties": {
    "iso:country":"DE",
    "sg:address":"Marktplatz 3",
    "sg:city":"Holzkirchen",
    "sg:phone":"+49 8024/99980",
    "sg:postcode":"83607",
    "sg:province":"Bayern",
    "wof:name":"S. Jennerwein",
    "wof:placetype":"venue"
},
  "geometry": {"coordinates":[11.7022562027,47.8773536682],"type":"Point"}
}