{
  "type": "Feature",
  "properties": {
    "iso:country":"DE",
    "sg:address":"M\u00fclheimer Str. 1",
    "sg:city":"Troisdorf",
    "sg:phone":"+49 2241/8770",
    "sg:postcode":"53840",
    "sg:province":"Nordrhein-Westfalen",
    "wof:name":"Die Firma Rent A Bureau Gesellsch. F. B\u00fcroservice Mbh",
    "wof:placetype":"venue"
},
  "geometry": {"coordinates":[7.146376133,50.8181381226],"type":"Point"}
}