{
  "type": "Feature",
  "properties": {
    "iso:country":"DE",
    "sg:address":"M\u00fcnstereifeler Str. 2",
    "sg:city":"Euskirchen",
    "sg:phone":"+49 2251/6071",
    "sg:postcode":"53879",
    "sg:province":"Nordrhein-Westfalen",
    "wof:name":"Jakob Frings Kg",
    "wof:placetype":"venue"
},
  "geometry": {"coordinates":[6.787499,50.656452],"type":"Point"}
}