{
  "type": "Feature",
  "properties": {
    "iso:country":"DE",
    "sg:address":"Waldstr. 33",
    "sg:city":"Ostseebad Prerow",
    "sg:phone":"+49 38233/327",
    "sg:postcode":"18375",
    "sg:province":"Mecklenburg-Vorpommern",
    "wof:name":"Pension Linde",
    "wof:placetype":"venue"
},
  "geometry": {"coordinates":[12.5640306473,54.4475784302],"type":"Point"}
}