{
  "type": "Feature",
  "properties": {
    "iso:country":"DE",
    "sg:address":"Leher Landstr. 4",
    "sg:city":"Langen",
    "sg:phone":"+49 4743/5077",
    "sg:postcode":"27607",
    "sg:province":"Niedersachsen",
    "wof:name":"Detlef Harders",
    "wof:placetype":"venue"
},
  "geometry": {"coordinates":[8.5948381424,53.6072235107],"type":"Point"}
}