{
  "type": "Feature",
  "properties": {
    "iso:country":"DE",
    "sg:address":"Hauptstr. 45",
    "sg:city":"Bermbach",
    "sg:phone":"+49 36967/5537",
    "sg:postcode":"36419",
    "sg:province":"Th\u00fcringen",
    "wof:name":"Fridolin Nensel",
    "wof:placetype":"venue"
},
  "geometry": {"coordinates":[10.597556,50.676571],"type":"Point"}
}