{
  "type": "Feature",
  "properties": {
    "iso:country":"DE",
    "sg:address":"R\u00f6hrigstr. 12",
    "sg:city":"Kuppenheim",
    "sg:phone":"+49 7225/3773",
    "sg:postcode":"76456",
    "sg:province":"Baden-W\u00fcrttemberg",
    "wof:name":"Erich Riedinger",
    "wof:placetype":"venue"
},
  "geometry": {"coordinates":[8.2847499847,48.8244018555],"type":"Point"}
}