{
  "type": "Feature",
  "properties": {
    "iso:country":"DE",
    "sg:address":"Bonner Str.328",
    "sg:city":"K\u00f6ln",
    "sg:postcode":"50968",
    "sg:province":"Nordrhein-Westfalen",
    "wof:name":"Etu Datentechnik Umbach",
    "wof:placetype":"venue"
},
  "geometry": {"coordinates":[6.964259,50.904186],"type":"Point"}
}