{
  "type": "Feature",
  "properties": {
    "iso:country":"DE",
    "sg:address":"Marktplatz 9",
    "sg:city":"Baienfurt",
    "sg:phone":"+49 751/554276",
    "sg:postcode":"88255",
    "sg:province":"Baden-W\u00fcrttemberg",
    "wof:name":"Wiko Haus Der K\u00fcchen",
    "wof:placetype":"venue"
},
  "geometry": {"coordinates":[9.651473999,47.8278503418],"type":"Point"}
}