{
  "type": "Feature",
  "properties": {
    "iso:country":"DE",
    "sg:address":"Damaschkestr. 12",
    "sg:city":"Berlin",
    "sg:phone":"+49 30/3231713",
    "sg:postcode":"10711",
    "sg:province":"Berlin",
    "wof:name":"Gastst\u00e4tte Fingerhut",
    "wof:placetype":"venue"
},
  "geometry": {"coordinates":[13.301112175,52.5001754761],"type":"Point"}
}