{
  "type": "Feature",
  "properties": {
    "iso:country":"DE",
    "sg:address":"M\u00fcllerstr. 31",
    "sg:city":"Berlin",
    "sg:phone":"+49 30/4551854",
    "sg:postcode":"13353",
    "sg:province":"Berlin",
    "wof:name":"Runners Point",
    "wof:placetype":"venue"
},
  "geometry": {"coordinates":[13.356867,52.547932],"type":"Point"}
}