{
  "type": "Feature",
  "properties": {
    "iso:country":"DE",
    "sg:address":"In den Seewiesen 13",
    "sg:city":"Edenkoben",
    "sg:postcode":"67480",
    "sg:province":"Rheinland-Pfalz",
    "wof:name":"Kopetschny Gmbh",
    "wof:placetype":"venue"
},
  "geometry": {"coordinates":[8.1464719772,49.2832450867],"type":"Point"}
}