{
  "type": "Feature",
  "properties": {
    "iso:country":"DE",
    "sg:address":"Hoher Hof 11",
    "sg:city":"Wendeburg",
    "sg:phone":"+49 5303/2721",
    "sg:postcode":"38176",
    "sg:province":"Niedersachsen",
    "wof:name":"Hinze Gmbh",
    "wof:placetype":"venue"
},
  "geometry": {"coordinates":[10.394816,52.330669],"type":"Point"}
}