{
  "type": "Feature",
  "properties": {
    "iso:country":"DE",
    "sg:address":"Hufenweg 8",
    "sg:city":"Ribnitz-Damgarten",
    "sg:phone":"+49 3821/2565",
    "sg:postcode":"18311",
    "sg:province":"Mecklenburg-Vorpommern",
    "wof:name":"Horst Neu",
    "wof:placetype":"venue"
},
  "geometry": {"coordinates":[12.4210796356,54.238910675],"type":"Point"}
}