{
  "type": "Feature",
  "properties": {
    "iso:country":"DE",
    "sg:address":"Denkinger Stra\u00dfe 17",
    "sg:city":"Aldingen",
    "sg:phone":"+49 7424/85173",
    "sg:postcode":"78554",
    "sg:province":"Baden-W\u00fcrttemberg",
    "wof:name":"Iglu-bau Gbr",
    "wof:placetype":"venue"
},
  "geometry": {"coordinates":[8.7192687988,48.0965080261],"type":"Point"}
}