{
  "type": "Feature",
  "properties": {
    "iso:country":"DE",
    "sg:address":"Merret-Lassen-Wai 6",
    "sg:city":"Rantum",
    "sg:postcode":"25980",
    "sg:province":"Schleswig-Holstein",
    "wof:name":"Alte Strandvogtei Grundst\u00fccksverwaltungsges. Mbh",
    "wof:placetype":"venue"
},
  "geometry": {"coordinates":[8.2971611023,54.8460159302],"type":"Point"}
}