{
  "type": "Feature",
  "properties": {
    "iso:country":"DE",
    "sg:address":"Reinerstr. 24",
    "sg:city":"Heilbronn",
    "sg:phone":"+49 7131/488020",
    "sg:postcode":"74080",
    "sg:province":"Baden-W\u00fcrttemberg",
    "wof:name":"Wiese Frischdienst Gmbh & Co. Kg",
    "wof:placetype":"venue"
},
  "geometry": {"coordinates":[9.161157608,49.1432228088],"type":"Point"}
}