{
  "type": "Feature",
  "properties": {
    "iso:country":"DE",
    "sg:address":"Gottesweg 13",
    "sg:city":"K\u00f6ln",
    "sg:phone":"+49 221/363669",
    "sg:postcode":"50969",
    "sg:province":"Nordrhein-Westfalen",
    "wof:name":"Elektro-brauns",
    "wof:placetype":"venue"
},
  "geometry": {"coordinates":[6.944052,50.910458],"type":"Point"}
}