{
  "type": "Feature",
  "properties": {
    "iso:country":"DE",
    "sg:address":"Jagowstr. 9",
    "sg:city":"Berlin",
    "sg:phone":"+49 30/3923680",
    "sg:postcode":"10555",
    "sg:province":"Berlin",
    "wof:name":"Citex M. Karademiz",
    "wof:placetype":"venue"
},
  "geometry": {"coordinates":[13.334104538,52.5219345093],"type":"Point"}
}