{
  "type": "Feature",
  "properties": {
    "iso:country":"DE",
    "sg:address":"Sta\u00dffurter Str. 37",
    "sg:city":"Neundorf",
    "sg:postcode":"39418",
    "sg:province":"Sachsen-Anhalt",
    "wof:name":"Kohlehandel Gmbh",
    "wof:placetype":"venue"
},
  "geometry": {"coordinates":[11.576241,51.82732],"type":"Point"}
}