{
  "type": "Feature",
  "properties": {
    "iso:country":"DE",
    "sg:address":"Forellenhof",
    "sg:city":"Moringen",
    "sg:phone":"+49 5555/99300",
    "sg:postcode":"37186",
    "sg:province":"Niedersachsen",
    "wof:name":"Fischtechnik Fredelsloh Gmbh",
    "wof:placetype":"venue"
},
  "geometry": {"coordinates":[9.871285,51.701244],"type":"Point"}
}