{
  "type": "Feature",
  "properties": {
    "iso:country":"DE",
    "sg:address":"Rohrbacher Str. 18",
    "sg:city":"Heidelberg",
    "sg:phone":"+49 6221/22642",
    "sg:postcode":"69115",
    "sg:province":"Baden-W\u00fcrttemberg",
    "wof:name":"Sobiella & Georgi Steuerberatungsges. Mbh",
    "wof:placetype":"venue"
},
  "geometry": {"coordinates":[8.6924247742,49.4056663513],"type":"Point"}
}