{
  "type": "Feature",
  "properties": {
    "iso:country":"DE",
    "sg:address":"Obere Maingasse 7a",
    "sg:city":"Veitsh\u00f6chheim",
    "sg:phone":"+49 931/94272",
    "sg:postcode":"97209",
    "sg:province":"Bayern",
    "wof:name":"Weinstube Zur Alten F\u00e4hre",
    "wof:placetype":"venue"
},
  "geometry": {"coordinates":[9.8699321747,49.8310546875],"type":"Point"}
}