{
  "type": "Feature",
  "properties": {
    "iso:country":"DE",
    "sg:address":"Leininger Str. 3",
    "sg:city":"Kaiserslautern",
    "sg:phone":"+49 631/60890",
    "sg:postcode":"67657",
    "sg:province":"Rheinland-Pfalz",
    "wof:name":"Dietmar Stork Architekt",
    "wof:placetype":"venue"
},
  "geometry": {"coordinates":[7.774567,49.454208],"type":"Point"}
}