{
  "type": "Feature",
  "properties": {
    "iso:country":"DE",
    "sg:address":"Pillnitzer Landstr. 303",
    "sg:city":"Dresden",
    "sg:phone":"+49 351/2618595",
    "sg:postcode":"01326",
    "sg:province":"Sachsen",
    "wof:name":"Lothar Naujoks",
    "wof:placetype":"venue"
},
  "geometry": {"coordinates":[13.85839,51.017109],"type":"Point"}
}