{
  "type": "Feature",
  "properties": {
    "iso:country":"DE",
    "sg:address":"Lengerm\u00fchle 1",
    "sg:city":"Essenbach",
    "sg:phone":"+49 8703/2233",
    "sg:postcode":"84051",
    "sg:province":"Bayern",
    "wof:name":"J. Koop",
    "wof:placetype":"venue"
},
  "geometry": {"coordinates":[12.2007074356,48.5784339905],"type":"Point"}
}