{
  "type": "Feature",
  "properties": {
    "iso:country":"DE",
    "sg:address":"Radelandweg 4-6",
    "sg:city":"Neustrelitz",
    "sg:phone":"+49 3981/421010",
    "sg:postcode":"17235",
    "sg:province":"Mecklenburg-Vorpommern",
    "wof:name":"Verkehrsges. Mecklenburg- Strelitz Mbh Vms",
    "wof:placetype":"venue"
},
  "geometry": {"coordinates":[13.073231,53.3549],"type":"Point"}
}