{
  "type": "Feature",
  "properties": {
    "iso:country":"DE",
    "sg:address":"Cappelstr. 46",
    "sg:city":"Lippstadt",
    "sg:phone":"+49 2941/97380",
    "sg:postcode":"59555",
    "sg:province":"Nordrhein-Westfalen",
    "wof:name":"Henrich Und Dirksmeier Rechtsanw\u00e4lte",
    "wof:placetype":"venue"
},
  "geometry": {"coordinates":[8.3429670334,51.6737518311],"type":"Point"}
}