{
  "type": "Feature",
  "properties": {
    "iso:country":"DE",
    "sg:address":"Martinstr. 6",
    "sg:city":"Leipzig",
    "sg:phone":"+49 341/2615577",
    "sg:postcode":"04318",
    "sg:province":"Sachsen",
    "wof:name":"Gesellschaft F\u00fcr Freiraum- Stadt- Und",
    "wof:placetype":"venue"
},
  "geometry": {"coordinates":[12.412412,51.334126],"type":"Point"}
}