{
  "type": "Feature",
  "properties": {
    "iso:country":"DE",
    "sg:address":"Pfarrstr. 58",
    "sg:city":"Hannover",
    "sg:phone":"+49 511/2348516",
    "sg:postcode":"30459",
    "sg:province":"Niedersachsen",
    "wof:name":"L\u00f6wenmaul - Lese-ecke, Katzen, Rezepte Und Mehr",
    "wof:placetype":"venue"
},
  "geometry": {"coordinates":[9.7259111404,52.3471260071],"type":"Point"}
}