{
  "type": "Feature",
  "properties": {
    "iso:country":"DE",
    "sg:address":"Tannenweg 6",
    "sg:city":"Dresden",
    "sg:phone":"+49 351/2812963",
    "sg:postcode":"01257",
    "sg:province":"Sachsen",
    "wof:name":"Ebe Bernd Engst Gmbh",
    "wof:placetype":"venue"
},
  "geometry": {"coordinates":[13.8068990707,51.0005760193],"type":"Point"}
}