{
  "type": "Feature",
  "properties": {
    "iso:country":"DE",
    "sg:address":"Alpentalstr. 8",
    "sg:city":"Bayerisch Gmain",
    "sg:phone":"+49 8651/64996",
    "sg:postcode":"83457",
    "sg:province":"Bayern",
    "wof:name":"J\u00f6rg Gr\u00f6ssler Gmbh",
    "wof:placetype":"venue"
},
  "geometry": {"coordinates":[12.8964366913,47.7174491882],"type":"Point"}
}