{
  "type": "Feature",
  "properties": {
    "iso:country":"DE",
    "sg:address":"Borsbergstr. 6",
    "sg:city":"Dresden",
    "sg:phone":"+49 351/4419698",
    "sg:postcode":"01309",
    "sg:province":"Sachsen",
    "wof:name":"Katrin Scharfenberg",
    "wof:placetype":"venue"
},
  "geometry": {"coordinates":[13.773482,51.046051],"type":"Point"}
}