{
  "type": "Feature",
  "properties": {
    "iso:country":"DE",
    "sg:address":"Z\u00e4hringer Str. 58",
    "sg:city":"Mannheim",
    "sg:phone":"+49 621/4817771",
    "sg:postcode":"68239",
    "sg:province":"Baden-W\u00fcrttemberg",
    "wof:name":"Peter Martin Kramer Rechtsanwalt",
    "wof:placetype":"venue"
},
  "geometry": {"coordinates":[8.558927536,49.4658317566],"type":"Point"}
}