{
  "type": "Feature",
  "properties": {
    "iso:country":"DE",
    "sg:address":"Pischdorf 20",
    "sg:city":"Guteneck",
    "sg:postcode":"92543",
    "sg:province":"Bayern",
    "wof:name":"Johann Sch\u00e4ffer Gmbh",
    "wof:placetype":"venue"
},
  "geometry": {"coordinates":[12.308813,49.461075],"type":"Point"}
}