{
  "type": "Feature",
  "properties": {
    "iso:country":"DE",
    "sg:address":"Finsinger Str. 84",
    "sg:city":"Markt Schwaben",
    "sg:phone":"+49 8121/5726",
    "sg:postcode":"85570",
    "sg:province":"Bayern",
    "wof:name":"Franz Hechtel",
    "wof:placetype":"venue"
},
  "geometry": {"coordinates":[11.85789,48.199299],"type":"Point"}
}