{
  "type": "Feature",
  "properties": {
    "iso:country":"DE",
    "sg:address":"Gartenstr 7",
    "sg:city":"Neukirchen",
    "sg:phone":"+49 3762/42950",
    "sg:postcode":"08459",
    "sg:province":"Sachsen",
    "wof:name":"H\u00f6lzel",
    "wof:placetype":"venue"
},
  "geometry": {"coordinates":[12.3732013702,50.7889671326],"type":"Point"}
}