{
  "type": "Feature",
  "properties": {
    "iso:country":"DE",
    "sg:address":"Schedelstr. 7",
    "sg:city":"M\u00fcnchen",
    "sg:phone":"+49 89/5705183",
    "sg:postcode":"80686",
    "sg:province":"Bayern",
    "wof:name":"Cede Elektroanlagen Gmbh",
    "wof:placetype":"venue"
},
  "geometry": {"coordinates":[11.517003,48.138187],"type":"Point"}
}