{
  "type": "Feature",
  "properties": {
    "iso:country":"DE",
    "sg:address":"Gederner Str. 9",
    "sg:city":"Hirzenhain",
    "sg:phone":"+49 4960/452085",
    "sg:postcode":"63697",
    "sg:province":"Hessen",
    "wof:name":"Moses",
    "wof:placetype":"venue"
},
  "geometry": {"coordinates":[9.145067215,50.399559021],"type":"Point"}
}