{
  "type": "Feature",
  "properties": {
    "iso:country":"DE",
    "sg:address":"Unter den Linden 18 b",
    "sg:city":"Stelle",
    "sg:phone":"+49 4174/6158",
    "sg:postcode":"21435",
    "sg:province":"Niedersachsen",
    "wof:name":"Gemeindeb\u00fccherei Stelle",
    "wof:placetype":"venue"
},
  "geometry": {"coordinates":[10.111099,53.379791],"type":"Point"}
}