{
  "type": "Feature",
  "properties": {
    "iso:country":"DE",
    "sg:address":"Wacholderstr. 32",
    "sg:city":"D\u00fcsseldorf",
    "sg:phone":"+49 203/740382",
    "sg:postcode":"40489",
    "sg:province":"Nordrhein-Westfalen",
    "wof:name":"Bruno Berendt Gmbh",
    "wof:placetype":"venue"
},
  "geometry": {"coordinates":[6.7819900513,51.323802948],"type":"Point"}
}