{
  "type": "Feature",
  "properties": {
    "iso:country":"DE",
    "sg:address":"Bestener Str. 1",
    "sg:city":"Eggerm\u00fchlen",
    "sg:phone":"+49 5462/1949",
    "sg:postcode":"49577",
    "sg:province":"Niedersachsen",
    "wof:name":"Dieter Sch\u00e4fer",
    "wof:placetype":"venue"
},
  "geometry": {"coordinates":[7.8706550598,52.5409965515],"type":"Point"}
}