{
  "type": "Feature",
  "properties": {
    "iso:country":"DE",
    "sg:address":"M\u00fcnchenstr. 35",
    "sg:city":"Braunschweig",
    "sg:phone":"+49 531/846424",
    "sg:postcode":"38120",
    "sg:province":"Niedersachsen",
    "wof:name":"Work-out-fitness-gmbh",
    "wof:placetype":"venue"
},
  "geometry": {"coordinates":[10.4873857498,52.2485427856],"type":"Point"}
}