{
  "type": "Feature",
  "properties": {
    "iso:country":"DE",
    "sg:address":"Saseler Chaussee 30a",
    "sg:city":"Hamburg",
    "sg:phone":"+49 40/6402898",
    "sg:postcode":"22391",
    "sg:province":"Hamburg",
    "wof:name":"Spielo-treff Automatenbetriebs Gmbh",
    "wof:placetype":"venue"
},
  "geometry": {"coordinates":[10.0929107666,53.6363487244],"type":"Point"}
}