{
  "type": "Feature",
  "properties": {
    "iso:country":"DE",
    "sg:address":"Wahnfriedstr. 28 A",
    "sg:city":"Berlin",
    "sg:postcode":"13465",
    "sg:province":"Berlin",
    "wof:name":"Mobile Hauskrankenpflege Marion Waszak Gmbh",
    "wof:placetype":"venue"
},
  "geometry": {"coordinates":[13.283653,52.636814],"type":"Point"}
}