{
  "type": "Feature",
  "properties": {
    "iso:country":"DE",
    "sg:address":"Reinbeker Str. 1",
    "sg:city":"Barsb\u00fcttel",
    "sg:postcode":"22885",
    "sg:province":"Schleswig-Holstein",
    "wof:name":"Acd-seemann & Paul Gmbh",
    "wof:placetype":"venue"
},
  "geometry": {"coordinates":[10.228891,53.561192],"type":"Point"}
}