{
  "type": "Feature",
  "properties": {
    "iso:country":"DE",
    "sg:address":"Scharebenstr. 20",
    "sg:city":"Arnbruck",
    "sg:postcode":"93471",
    "sg:province":"Bayern",
    "wof:name":"Schnellimbi\u00df G. P\u00f6llmann",
    "wof:placetype":"venue"
},
  "geometry": {"coordinates":[13.0120859146,49.1350212097],"type":"Point"}
}