{
  "type": "Feature",
  "properties": {
    "iso:country":"DE",
    "sg:address":"Stolzestr. 2",
    "sg:city":"Hannover",
    "sg:phone":"+49 511/818009",
    "sg:postcode":"30171",
    "sg:province":"Niedersachsen",
    "wof:name":"Rolf Gehrcke Architekt",
    "wof:placetype":"venue"
},
  "geometry": {"coordinates":[9.758952,52.369892],"type":"Point"}
}