{
  "type": "Feature",
  "properties": {
    "iso:country":"DE",
    "sg:address":"Alter Grenzweg 1",
    "sg:city":"Soltau",
    "sg:phone":"+49 5191/4820",
    "sg:postcode":"29614",
    "sg:province":"Niedersachsen",
    "wof:name":"Obenauf Gmbh",
    "wof:placetype":"venue"
},
  "geometry": {"coordinates":[9.82614,52.978722],"type":"Point"}
}