{
  "type": "Feature",
  "properties": {
    "iso:country":"DE",
    "sg:address":"Karlstr. 18",
    "sg:city":"Laichingen",
    "sg:phone":"+49 7333/5105",
    "sg:postcode":"89150",
    "sg:province":"Baden-W\u00fcrttemberg",
    "wof:name":"Walter Ostertag",
    "wof:placetype":"venue"
},
  "geometry": {"coordinates":[9.687013,48.487686],"type":"Point"}
}