{
  "type": "Feature",
  "properties": {
    "iso:country":"DE",
    "sg:address":"Berliner Str. 922",
    "sg:city":"K\u00f6ln",
    "sg:postcode":"51069",
    "sg:province":"Nordrhein-Westfalen",
    "wof:name":"Image Mode-vertriebs Gmbh",
    "wof:placetype":"venue"
},
  "geometry": {"coordinates":[7.0386462212,50.9996643066],"type":"Point"}
}