{
  "type": "Feature",
  "properties": {
    "iso:country":"DE",
    "sg:address":"Duisburger Str. 30",
    "sg:city":"Ratingen",
    "sg:postcode":"40885",
    "sg:province":"Nordrhein-Westfalen",
    "wof:name":"Holscot Deutschland Zweigniederl. Der Holscot",
    "wof:placetype":"venue"
},
  "geometry": {"coordinates":[6.8243489265,51.3470458984],"type":"Point"}
}