{
  "type": "Feature",
  "properties": {
    "iso:country":"DE",
    "sg:address":"Eichendorffstr. 20",
    "sg:city":"Neu-Isenburg",
    "sg:phone":"+49 6102/31582",
    "sg:postcode":"63263",
    "sg:province":"Hessen",
    "wof:name":"Andreas Jauris",
    "wof:placetype":"venue"
},
  "geometry": {"coordinates":[8.6998062134,50.0534820557],"type":"Point"}
}