{
  "type": "Feature",
  "properties": {
    "iso:country":"DE",
    "sg:address":"Bonner Str. 2b",
    "sg:city":"Leverkusen",
    "sg:phone":"+49 2171/43390",
    "sg:postcode":"51379",
    "sg:province":"Nordrhein-Westfalen",
    "wof:name":"S Und W Bauplanung Gmbh",
    "wof:placetype":"venue"
},
  "geometry": {"coordinates":[6.990828,51.066322],"type":"Point"}
}