{
  "type": "Feature",
  "properties": {
    "iso:country":"DE",
    "sg:address":"Grefratherstr. 21",
    "sg:city":"Neuss",
    "sg:phone":"+49 2131",
    "sg:postcode":"41464",
    "sg:province":"Nordrhein-Westfalen",
    "wof:name":"Ferien Im Allgaeu Gbr Ferienwohnpark Missen Wilhams",
    "wof:placetype":"venue"
},
  "geometry": {"coordinates":[6.6820240021,51.1876983643],"type":"Point"}
}