{
  "type": "Feature",
  "properties": {
    "iso:country":"DE",
    "sg:address":"Zur Dorfeiche 22",
    "sg:city":"Undeloh",
    "sg:phone":"+49 4189/476",
    "sg:postcode":"21274",
    "sg:province":"Niedersachsen",
    "wof:name":"Heidehof",
    "wof:placetype":"venue"
},
  "geometry": {"coordinates":[9.9813671112,53.1984214783],"type":"Point"}
}