{
  "type": "Feature",
  "properties": {
    "iso:country":"DE",
    "sg:address":"Ramsacher Str. 7",
    "sg:city":"Sch\u00f6ffelding",
    "sg:phone":"+49 8193/997370",
    "sg:postcode":"86949",
    "sg:province":"Bayern",
    "wof:name":"Stino Excellence In Multi Media Content",
    "wof:placetype":"venue"
},
  "geometry": {"coordinates":[10.989645,48.066048],"type":"Point"}
}