{
  "type": "Feature",
  "properties": {
    "iso:country":"DE",
    "sg:address":"Alt-Hartmannsdorfer Str. 11",
    "sg:city":"Spreenhagen",
    "sg:phone":"+49 33633/65208",
    "sg:postcode":"15528",
    "sg:province":"Brandenburg",
    "wof:name":"Wilhelm Haase",
    "wof:placetype":"venue"
},
  "geometry": {"coordinates":[13.87095,52.341785],"type":"Point"}
}