{
  "type": "Feature",
  "properties": {
    "iso:country":"DE",
    "sg:address":"Holzhausen 25",
    "sg:city":"Griesst\u00e4tt",
    "sg:phone":"+49 8038/774",
    "sg:postcode":"83556",
    "sg:province":"Bayern",
    "wof:name":"Heinrich Axhausen",
    "wof:placetype":"venue"
},
  "geometry": {"coordinates":[12.17397,47.973919],"type":"Point"}
}