{
  "type": "Feature",
  "properties": {
    "iso:country":"DE",
    "sg:address":"Leibnizufer 17 a",
    "sg:city":"Hannover",
    "sg:phone":"+49 511/12609100",
    "sg:postcode":"30169",
    "sg:province":"Niedersachsen",
    "wof:name":"Clemensburse E. V. Studentenwohnheim",
    "wof:placetype":"venue"
},
  "geometry": {"coordinates":[9.7280158997,52.3734512329],"type":"Point"}
}