{
  "type": "Feature",
  "properties": {
    "iso:country":"DE",
    "sg:address":"M\u00fcnchener Str 52",
    "sg:city":"Pullach",
    "sg:phone":"+49 89/7442090",
    "sg:postcode":"82049",
    "sg:province":"Bayern",
    "wof:name":"Laprint Gmbh",
    "wof:placetype":"venue"
},
  "geometry": {"coordinates":[11.519558,48.066063],"type":"Point"}
}