{
  "type": "Feature",
  "properties": {
    "iso:country":"DE",
    "sg:address":"Hansestr. 88",
    "sg:city":"Braunschweig",
    "sg:postcode":"38112",
    "sg:province":"Niedersachsen",
    "wof:name":"Wittig Hallenbau Gmbh",
    "wof:placetype":"venue"
},
  "geometry": {"coordinates":[10.5086221695,52.309337616],"type":"Point"}
}