{
  "type": "Feature",
  "properties": {
    "iso:country":"DE",
    "sg:address":"Overhoffstr. 33-35",
    "sg:city":"Dortmund",
    "sg:phone":"+49 4952/073398",
    "sg:postcode":"44379",
    "sg:province":"Nordrhein-Westfalen",
    "wof:name":"Klaus Fulland Gmbh",
    "wof:placetype":"venue"
},
  "geometry": {"coordinates":[8.5757904053,51.9087600708],"type":"Point"}
}