{
  "type": "Feature",
  "properties": {
    "iso:country":"DE",
    "sg:address":"Fr\u00fchlingstr. 26a",
    "sg:city":"Baldham",
    "sg:phone":"+49 8106/5856",
    "sg:postcode":"85598",
    "sg:province":"Bayern",
    "wof:name":"Hellmut Mayr",
    "wof:placetype":"venue"
},
  "geometry": {"coordinates":[11.7930498123,48.0983543396],"type":"Point"}
}