{
  "type": "Feature",
  "properties": {
    "iso:country":"DE",
    "sg:address":"Herzebrocker Stra\u00dfe 58a",
    "sg:city":"G\u00fctersloh",
    "sg:phone":"+49 5241/237051",
    "sg:postcode":"33330",
    "sg:province":"Nordrhein-Westfalen",
    "wof:name":"Prima Reklame",
    "wof:placetype":"venue"
},
  "geometry": {"coordinates":[8.363127,51.904202],"type":"Point"}
}