{
  "type": "Feature",
  "properties": {
    "iso:country":"DE",
    "sg:address":"Schwalmstr. 11",
    "sg:city":"Viersen",
    "sg:postcode":"41748",
    "sg:province":"Nordrhein-Westfalen",
    "wof:name":"Dataadvance Gmbh",
    "wof:placetype":"venue"
},
  "geometry": {"coordinates":[6.3656139374,51.235080719],"type":"Point"}
}