{
  "type": "Feature",
  "properties": {
    "iso:country":"DE",
    "sg:address":"Hauptstr. 67",
    "sg:city":"Haunetal",
    "sg:phone":"+49 4966/7392010",
    "sg:postcode":"36166",
    "sg:province":"Hessen",
    "wof:name":"Metalltechnik Haunetal Gmbh & Co. Kg",
    "wof:placetype":"venue"
},
  "geometry": {"coordinates":[9.6990747452,50.7727584839],"type":"Point"}
}