{
  "type": "Feature",
  "properties": {
    "iso:country":"DE",
    "sg:address":"Untere Stadt 11",
    "sg:city":"Vilsbiburg",
    "sg:phone":"+49 8741/4991",
    "sg:postcode":"84137",
    "sg:province":"Bayern",
    "wof:name":"Metropolis",
    "wof:placetype":"venue"
},
  "geometry": {"coordinates":[12.3574314117,48.4474372864],"type":"Point"}
}