{
  "type": "Feature",
  "properties": {
    "iso:country":"DE",
    "sg:address":"Zum Kellerbach 48",
    "sg:city":"Schwerte",
    "sg:postcode":"58239",
    "sg:province":"Nordrhein-Westfalen",
    "wof:name":"Institut F\u00fcr Wasser- Forschung",
    "wof:placetype":"venue"
},
  "geometry": {"coordinates":[7.6339011192,51.459526062],"type":"Point"}
}