{
  "type": "Feature",
  "properties": {
    "iso:country":"DE",
    "sg:address":"Denkmalsplatz 3",
    "sg:city":"Elsterwerda",
    "sg:phone":"+49 3533/2632",
    "sg:postcode":"04910",
    "sg:province":"Brandenburg",
    "wof:name":"Pf\u00f6rtner",
    "wof:placetype":"venue"
},
  "geometry": {"coordinates":[13.52234,51.459572],"type":"Point"}
}