{
  "type": "Feature",
  "properties": {
    "iso:country":"DE",
    "sg:address":"Jederschwing 1",
    "sg:city":"Eging",
    "sg:phone":"+49 8544/533",
    "sg:postcode":"94535",
    "sg:province":"Bayern",
    "wof:name":"Alois Luger Zimmerei - Holzbau Gmbh",
    "wof:placetype":"venue"
},
  "geometry": {"coordinates":[13.2288751602,48.7025299072],"type":"Point"}
}