{
  "type": "Feature",
  "properties": {
    "iso:country":"DE",
    "sg:address":"Hufschlag 14",
    "sg:city":"Maxh\u00fctte-Haidhof",
    "sg:phone":"+49 9471/21111",
    "sg:postcode":"93142",
    "sg:province":"Bayern",
    "wof:name":"Schnupferverein P\u00f6landler G\u00fcnther Seidl",
    "wof:placetype":"venue"
},
  "geometry": {"coordinates":[12.0784502029,49.1582374573],"type":"Point"}
}