{
  "type": "Feature",
  "properties": {
    "iso:country":"DE",
    "sg:address":"Obermeidericher Str. 55 A",
    "sg:city":"Oberhausen",
    "sg:phone":"+49 208/845970",
    "sg:postcode":"46049",
    "sg:province":"Nordrhein-Westfalen",
    "wof:name":"Travertino-marmor Gmbh",
    "wof:placetype":"venue"
},
  "geometry": {"coordinates":[6.8172841072,51.4654884338],"type":"Point"}
}