{
  "type": "Feature",
  "properties": {
    "iso:country":"DE",
    "sg:address":"Gartenfeldstr. 23",
    "sg:city":"Wenden",
    "sg:phone":"+49 2762/1451",
    "sg:postcode":"57482",
    "sg:province":"Nordrhein-Westfalen",
    "wof:name":"J. Willecke",
    "wof:placetype":"venue"
},
  "geometry": {"coordinates":[7.866054,50.968857],"type":"Point"}
}