{
  "type": "Feature",
  "properties": {
    "iso:country":"DE",
    "sg:address":"Goethestr. 20",
    "sg:city":"Heilbronn",
    "sg:phone":"+49 7131/161131",
    "sg:postcode":"74076",
    "sg:province":"Baden-W\u00fcrttemberg",
    "wof:name":"Maya Belle Privatdetektei",
    "wof:placetype":"venue"
},
  "geometry": {"coordinates":[9.231696,49.142712],"type":"Point"}
}