{
  "type": "Feature",
  "properties": {
    "iso:country":"DE",
    "sg:address":"Marburger Ring 27",
    "sg:city":"Kirchhain",
    "sg:phone":"+49 6422/4810",
    "sg:postcode":"35274",
    "sg:province":"Hessen",
    "wof:name":"Willi Hofmann",
    "wof:placetype":"venue"
},
  "geometry": {"coordinates":[8.865978,50.810146],"type":"Point"}
}