{
  "type": "Feature",
  "properties": {
    "iso:country":"DE",
    "sg:address":"Lindenstr. 22",
    "sg:city":"Dautphetal",
    "sg:phone":"+49 6466/429",
    "sg:postcode":"35232",
    "sg:province":"Hessen",
    "wof:name":"Rhodos Taverne",
    "wof:placetype":"venue"
},
  "geometry": {"coordinates":[8.5460453033,50.857334137],"type":"Point"}
}