{
  "type": "Feature",
  "properties": {
    "iso:country":"DE",
    "sg:address":"Margarethenhain 7",
    "sg:city":"Espenhain",
    "sg:postcode":"04579",
    "sg:province":"Sachsen",
    "wof:name":"Sl S\u00fcdraum Leipzig Gmbh",
    "wof:placetype":"venue"
},
  "geometry": {"coordinates":[12.479994,51.182182],"type":"Point"}
}