{
  "type": "Feature",
  "properties": {
    "iso:country":"DE",
    "sg:address":"Hanauer Str. 58",
    "sg:city":"M\u00fcnchen",
    "sg:phone":"+49 89/143390",
    "sg:postcode":"80993",
    "sg:province":"Bayern",
    "wof:name":"Gmx Ag",
    "wof:placetype":"venue"
},
  "geometry": {"coordinates":[11.52965,48.182072],"type":"Point"}
}