{
  "type": "Feature",
  "properties": {
    "iso:country":"DE",
    "sg:address":"K\u00f6nigsberger Str. 12",
    "sg:city":"Albersdorf",
    "sg:postcode":"25767",
    "sg:province":"Schleswig-Holstein",
    "wof:name":"Paulsen Massivhaus Gmbh",
    "wof:placetype":"venue"
},
  "geometry": {"coordinates":[9.2988939285,54.1468391418],"type":"Point"}
}