{
  "type": "Feature",
  "properties": {
    "iso:country":"DE",
    "sg:address":"Graf-Recke-Str. 103",
    "sg:city":"D\u00fcsseldorf",
    "sg:phone":"+49 211/684693",
    "sg:postcode":"40239",
    "sg:province":"Nordrhein-Westfalen",
    "wof:name":"Bistro Pinguin",
    "wof:placetype":"venue"
},
  "geometry": {"coordinates":[6.8137788773,51.2426109314],"type":"Point"}
}