{
  "type": "Feature",
  "properties": {
    "iso:country":"DE",
    "sg:address":"Neue Str. 6",
    "sg:city":"F\u00fcrstenberg",
    "sg:phone":"+49 5271/5104",
    "sg:postcode":"37699",
    "sg:province":"Niedersachsen",
    "wof:name":"Fleischerei W. Kadel Gmbh",
    "wof:placetype":"venue"
},
  "geometry": {"coordinates":[9.400472641,51.7309188843],"type":"Point"}
}