{
  "type": "Feature",
  "properties": {
    "iso:country":"DE",
    "sg:address":"Industriestrasse 59",
    "sg:city":"Castrop-Rauxel",
    "sg:phone":"+49 4902/3679990",
    "sg:postcode":"44577",
    "sg:province":"Nordrhein-Westfalen",
    "wof:name":"M & M Dienstleistungen - Geb\u00e4udereinigung, Glasreinigung, ..",
    "wof:placetype":"venue"
},
  "geometry": {"coordinates":[7.296185,51.599644],"type":"Point"}
}