{
  "type": "Feature",
  "properties": {
    "iso:country":"DE",
    "sg:address":"Leipziger Allee 26",
    "sg:city":"Wolfenb\u00fcttel",
    "sg:phone":"+49 5331/61749",
    "sg:postcode":"38300",
    "sg:province":"Niedersachsen",
    "wof:name":"Fischerbr\u00fccke Inh. Hermann Schmidt",
    "wof:placetype":"venue"
},
  "geometry": {"coordinates":[10.5912179947,52.1515235901],"type":"Point"}
}