{
  "type": "Feature",
  "properties": {
    "iso:country":"DE",
    "sg:address":"Wiesenstr 13",
    "sg:city":"Zell",
    "sg:phone":"+49 7625/92530",
    "sg:postcode":"79669",
    "sg:province":"Baden-W\u00fcrttemberg",
    "wof:name":"Fessmann & Hecker Gmbh & Co Kg",
    "wof:placetype":"venue"
},
  "geometry": {"coordinates":[7.847536,47.704254],"type":"Point"}
}