{
  "type": "Feature",
  "properties": {
    "iso:country":"DE",
    "sg:address":"Bahnstr. 20",
    "sg:city":"Ellerstadt",
    "sg:phone":"+49 6237/3492",
    "sg:postcode":"67158",
    "sg:province":"Rheinland-Pfalz",
    "wof:name":"Karl Weilbrenner Weinanbau",
    "wof:placetype":"venue"
},
  "geometry": {"coordinates":[8.2565860748,49.4625282288],"type":"Point"}
}