{
  "type": "Feature",
  "properties": {
    "iso:country":"DE",
    "sg:address":"Friedrich-Ebert-Str. 14",
    "sg:city":"L\u00f6wenberg",
    "sg:phone":"+49 33094/50302",
    "sg:postcode":"16775",
    "sg:province":"Brandenburg",
    "wof:name":"Lebensmittel",
    "wof:placetype":"venue"
},
  "geometry": {"coordinates":[13.1527433395,52.8970565796],"type":"Point"}
}