{
  "type": "Feature",
  "properties": {
    "iso:country":"DE",
    "sg:address":"Sepp-Verscht-Str. 1",
    "sg:city":"Gro\u00dfp\u00f6sna",
    "sg:phone":"+49 34297/12310",
    "sg:postcode":"04463",
    "sg:province":"Sachsen",
    "wof:name":"Annette Mletschak",
    "wof:placetype":"venue"
},
  "geometry": {"coordinates":[12.4990301132,51.2654914856],"type":"Point"}
}