{
  "type": "Feature",
  "properties": {
    "iso:country":"DE",
    "sg:address":"Belmsdorfer Str. 31",
    "sg:city":"Bischofswerda",
    "sg:phone":"+49 3594/7530",
    "sg:postcode":"01877",
    "sg:province":"Sachsen",
    "wof:name":"Dresdner Herrenmode Gmbh",
    "wof:placetype":"venue"
},
  "geometry": {"coordinates":[14.1918897629,51.1239089966],"type":"Point"}
}