{
  "type": "Feature",
  "properties": {
    "iso:country":"DE",
    "sg:address":"Birgenweg 4",
    "sg:city":"Erfurt",
    "sg:phone":"+49 361/2259472",
    "sg:postcode":"99094",
    "sg:province":"Th\u00fcringen",
    "wof:name":"English Institut F\u00fcr Internationale Studien Dr.j\u00fcrgen Mulert",
    "wof:placetype":"venue"
},
  "geometry": {"coordinates":[10.9824466705,50.9603538513],"type":"Point"}
}