{
  "type": "Feature",
  "properties": {
    "iso:country":"DE",
    "sg:address":"Albert-Drosihn-Str. 9",
    "sg:city":"Aschersleben",
    "sg:phone":"+49 3473/911507",
    "sg:postcode":"06449",
    "sg:province":"Sachsen-Anhalt",
    "wof:name":"B. I. G. Sicherheit Gmbh",
    "wof:placetype":"venue"
},
  "geometry": {"coordinates":[11.4661903381,51.7497596741],"type":"Point"}
}