{
  "type": "Feature",
  "properties": {
    "iso:country":"DE",
    "sg:address":"Dahlmannstr. 41",
    "sg:city":"Wismar",
    "sg:phone":"+49 3841/211018",
    "sg:postcode":"23966",
    "sg:province":"Mecklenburg-Vorpommern",
    "wof:name":"Egon Magholder",
    "wof:placetype":"venue"
},
  "geometry": {"coordinates":[11.456732,53.891251],"type":"Point"}
}