{
  "type": "Feature",
  "properties": {
    "iso:country":"DE",
    "sg:address":"T\u00fc\u00dflinger Str. 2",
    "sg:city":"Alt\u00f6tting",
    "sg:phone":"+49 8671/85302",
    "sg:postcode":"84503",
    "sg:province":"Bayern",
    "wof:name":"Peter Kneip",
    "wof:placetype":"venue"
},
  "geometry": {"coordinates":[12.658458,48.224991],"type":"Point"}
}