{
  "type": "Feature",
  "properties": {
    "iso:country":"DE",
    "sg:address":"Ingolst\u00e4dter Str. 16",
    "sg:city":"Pfaffenhofen",
    "sg:phone":"+49 8441/8748",
    "sg:postcode":"85276",
    "sg:province":"Bayern",
    "wof:name":"Michael Hausl Rechtsanwalt",
    "wof:placetype":"venue"
},
  "geometry": {"coordinates":[11.5073537827,48.5314064026],"type":"Point"}
}