{
  "type": "Feature",
  "properties": {
    "iso:country":"DE",
    "sg:address":"Rieden",
    "sg:city":"Die\u00dfen",
    "sg:phone":"+49 8807/7340",
    "sg:postcode":"86911",
    "sg:province":"Bayern",
    "wof:name":"R. Benesch",
    "wof:placetype":"venue"
},
  "geometry": {"coordinates":[11.0690097809,47.9881095886],"type":"Point"}
}