{
  "type": "Feature",
  "properties": {
    "iso:country":"DE",
    "sg:address":"Kirchberg 38",
    "sg:city":"Hainsfarth",
    "sg:phone":"+49 9082/8390",
    "sg:postcode":"86744",
    "sg:province":"Bayern",
    "wof:name":"Albert Grygar",
    "wof:placetype":"venue"
},
  "geometry": {"coordinates":[10.622895,48.96196],"type":"Point"}
}