{
  "type": "Feature",
  "properties": {
    "iso:country":"DE",
    "sg:address":"Sch\u00fcttorfer Str. 45",
    "sg:city":"Emsb\u00fcren",
    "sg:phone":"+49 5903/268",
    "sg:postcode":"48488",
    "sg:province":"Niedersachsen",
    "wof:name":"H. Ratering Gasthaus Zum Schlagboom",
    "wof:placetype":"venue"
},
  "geometry": {"coordinates":[7.2814297676,52.3808708191],"type":"Point"}
}