{
  "type": "Feature",
  "properties": {
    "iso:country":"DE",
    "sg:address":"Am Linder Kreuz 43",
    "sg:city":"K\u00f6ln",
    "sg:phone":"+49 2203/67168",
    "sg:postcode":"51147",
    "sg:province":"Nordrhein-Westfalen",
    "wof:name":"Bu\u00df Sondermaschinen Gmbh",
    "wof:placetype":"venue"
},
  "geometry": {"coordinates":[7.099505,50.8475],"type":"Point"}
}