{
  "type": "Feature",
  "properties": {
    "iso:country":"DE",
    "sg:address":"Langst\u00e4dter Str. 7",
    "sg:city":"Schaafheim",
    "sg:phone":"+49 6073/9491",
    "sg:postcode":"64850",
    "sg:province":"Hessen",
    "wof:name":"F. Orth",
    "wof:placetype":"venue"
},
  "geometry": {"coordinates":[9.0020246506,49.9220352173],"type":"Point"}
}