{
  "type": "Feature",
  "properties": {
    "iso:country":"DE",
    "sg:address":"Daimlerstar\u00dfe 17",
    "sg:city":"Bad Salzuflen",
    "sg:postcode":"32101",
    "sg:province":"Nordrhein-Westfalen",
    "wof:name":"Sex Unzensiert",
    "wof:placetype":"venue"
},
  "geometry": {"coordinates":[8.74898,52.082432],"type":"Point"}
}