{
  "type": "Feature",
  "properties": {
    "iso:country":"DE",
    "sg:address":"Lindenstr. 21",
    "sg:city":"Bad Saulgau",
    "sg:phone":"+49 7581/7392",
    "sg:postcode":"88348",
    "sg:province":"Baden-W\u00fcrttemberg",
    "wof:name":"U. Braun",
    "wof:placetype":"venue"
},
  "geometry": {"coordinates":[9.49635,48.016151],"type":"Point"}
}