{
  "type": "Feature",
  "properties": {
    "iso:country":"DE",
    "sg:address":"Biberger Str. 89",
    "sg:city":"Unterhaching",
    "sg:phone":"+49 89/6114141",
    "sg:postcode":"82008",
    "sg:province":"Bayern",
    "wof:name":"Alpina Dental",
    "wof:placetype":"venue"
},
  "geometry": {"coordinates":[11.620474,48.072723],"type":"Point"}
}