{
  "type": "Feature",
  "properties": {
    "iso:country":"DE",
    "sg:address":"Spandauer Damm 52",
    "sg:city":"Berlin",
    "sg:phone":"+49 30/3225549",
    "sg:postcode":"14059",
    "sg:province":"Berlin",
    "wof:name":"Condor Grundst\u00fccksver- Waltungs- Und",
    "wof:placetype":"venue"
},
  "geometry": {"coordinates":[13.2893152237,52.5191116333],"type":"Point"}
}