{
  "type": "Feature",
  "properties": {
    "iso:country":"DE",
    "sg:address":"Hubertusdamm 38",
    "sg:city":"Potsdam",
    "sg:phone":"+49 331/624219",
    "sg:postcode":"14480",
    "sg:province":"Brandenburg",
    "wof:name":"Brigitte Ring",
    "wof:placetype":"venue"
},
  "geometry": {"coordinates":[13.1347799301,52.3844985962],"type":"Point"}
}