{
  "type": "Feature",
  "properties": {
    "iso:country":"DE",
    "sg:address":"Am Stadtgraben 19",
    "sg:city":"Wunstorf",
    "sg:phone":"+49 5031/95420",
    "sg:postcode":"31515",
    "sg:province":"Niedersachsen",
    "wof:name":"Atlantis-die Reiseprofis Gmbh",
    "wof:placetype":"venue"
},
  "geometry": {"coordinates":[9.4295043945,52.4267730713],"type":"Point"}
}