{
  "type": "Feature",
  "properties": {
    "iso:country":"DE",
    "sg:address":"Rintelner Str. 85",
    "sg:city":"Lemgo",
    "sg:phone":"+49 5261/2111",
    "sg:postcode":"32657",
    "sg:province":"Nordrhein-Westfalen",
    "wof:name":"Kreiskrankenhaus Lemgo",
    "wof:placetype":"venue"
},
  "geometry": {"coordinates":[8.902425,52.036549],"type":"Point"}
}