{
  "type": "Feature",
  "properties": {
    "iso:country":"DE",
    "sg:address":"Dyck Nr. 8",
    "sg:city":"Nettetal",
    "sg:phone":"+49 4921/5360051",
    "sg:postcode":"41334",
    "sg:province":"Nordrhein-Westfalen",
    "wof:name":"Glb Ges. F\u00dcr Landschafts- Ung Baumpflege Mbh",
    "wof:placetype":"venue"
},
  "geometry": {"coordinates":[6.27778,51.306351],"type":"Point"}
}