{
  "type": "Feature",
  "properties": {
    "iso:country":"DE",
    "sg:address":"Teichgasse",
    "sg:city":"Freiberg",
    "sg:postcode":"09599",
    "sg:province":"Sachsen",
    "wof:name":"Campingplatz Freiburg",
    "wof:placetype":"venue"
},
  "geometry": {"coordinates":[13.335911,50.910965],"type":"Point"}
}