{
  "type": "Feature",
  "properties": {
    "iso:country":"DE",
    "sg:address":"Hohenberg 2",
    "sg:city":"Regnitzlosau",
    "sg:phone":"+49 9294/267",
    "sg:postcode":"95194",
    "sg:province":"Bayern",
    "wof:name":"Gerhard Gr\u00e4\u00dfel",
    "wof:placetype":"venue"
},
  "geometry": {"coordinates":[12.047561,50.301353],"type":"Point"}
}