{
  "type": "Feature",
  "properties": {
    "iso:country":"DE",
    "sg:address":"Edewechter Landstr. 28",
    "sg:city":"Oldenburg",
    "sg:phone":"+49 441/951960",
    "sg:postcode":"26131",
    "sg:province":"Niedersachsen",
    "wof:name":"Versicherungsfachmann Michael Aldenhoff E. K.",
    "wof:placetype":"venue"
},
  "geometry": {"coordinates":[8.1838064194,53.1321220398],"type":"Point"}
}