{
  "type": "Feature",
  "properties": {
    "iso:country":"DE",
    "sg:address":"Adlerring 23",
    "sg:city":"Villingen-Schwenningen",
    "sg:phone":"+49 7721/63350",
    "sg:postcode":"78048",
    "sg:province":"Baden-W\u00fcrttemberg",
    "wof:name":"W. Puhlmann",
    "wof:placetype":"venue"
},
  "geometry": {"coordinates":[8.4761161804,48.0646705627],"type":"Point"}
}