{
  "type": "Feature",
  "properties": {
    "iso:country":"DE",
    "sg:address":"Schulstr. 13",
    "sg:city":"Gauting",
    "sg:phone":"+49 89/8958089",
    "sg:postcode":"82131",
    "sg:province":"Bayern",
    "wof:name":"Huttner Und Hosszu",
    "wof:placetype":"venue"
},
  "geometry": {"coordinates":[11.3770532608,48.0648536682],"type":"Point"}
}