{
  "type": "Feature",
  "properties": {
    "iso:country":"DE",
    "sg:address":"Ortsstr. 37",
    "sg:city":"Gro\u00dfkochberg",
    "sg:phone":"+49 36743/30067",
    "sg:postcode":"07407",
    "sg:province":"Th\u00fcringen",
    "wof:name":"Brunner & K\u00f6pke Kg",
    "wof:placetype":"venue"
},
  "geometry": {"coordinates":[11.356494,50.774715],"type":"Point"}
}