{
  "type": "Feature",
  "properties": {
    "iso:country":"DE",
    "sg:address":"Knarrberg 81 a",
    "sg:city":"Dessau",
    "sg:phone":"+49 340/619427",
    "sg:postcode":"06846",
    "sg:province":"Sachsen-Anhalt",
    "wof:name":"Verein Freie Altenarbeit Jung Und Alt E. V.",
    "wof:placetype":"venue"
},
  "geometry": {"coordinates":[12.2195158005,51.8517799377],"type":"Point"}
}