{
  "type": "Feature",
  "properties": {
    "iso:country":"DE",
    "sg:address":"Klein-Haddorf 2",
    "sg:city":"Wettringen",
    "sg:phone":"+49 2557/202",
    "sg:postcode":"48493",
    "sg:province":"Nordrhein-Westfalen",
    "wof:name":"Hermann Schubert Gmbh",
    "wof:placetype":"venue"
},
  "geometry": {"coordinates":[7.2816438675,52.2592658997],"type":"Point"}
}