{
  "type": "Feature",
  "properties": {
    "iso:country":"DE",
    "sg:address":"Weberstr. 90",
    "sg:city":"Elz",
    "sg:phone":"+49 6431/580000",
    "sg:postcode":"65604",
    "sg:province":"Hessen",
    "wof:name":"Hans-j\u00f6rg M\u00fcller",
    "wof:placetype":"venue"
},
  "geometry": {"coordinates":[8.0238294601,50.4132118225],"type":"Point"}
}