{
  "type": "Feature",
  "properties": {
    "iso:country":"DE",
    "sg:address":"Hochstr. 1",
    "sg:city":"Erkelenz",
    "sg:phone":"+49 2431/3152",
    "sg:postcode":"41812",
    "sg:province":"Nordrhein-Westfalen",
    "wof:name":"A. Hoeren",
    "wof:placetype":"venue"
},
  "geometry": {"coordinates":[6.2482638359,51.0830535889],"type":"Point"}
}