{
  "type": "Feature",
  "properties": {
    "iso:country":"DE",
    "sg:address":"Bismarckstr. 3",
    "sg:city":"Weil im Sch\u00f6nbuch",
    "sg:phone":"+49 7157/61119",
    "sg:postcode":"71093",
    "sg:province":"Baden-W\u00fcrttemberg",
    "wof:name":"Eugen Maier",
    "wof:placetype":"venue"
},
  "geometry": {"coordinates":[9.0580787659,48.6214103699],"type":"Point"}
}