{
  "type": "Feature",
  "properties": {
    "iso:country":"DE",
    "sg:address":"D\u00fcppelstr. 102",
    "sg:city":"Oberhausen",
    "sg:phone":"+49 208/26775",
    "sg:postcode":"46045",
    "sg:province":"Nordrhein-Westfalen",
    "wof:name":"U. Volles Steuerberater",
    "wof:placetype":"venue"
},
  "geometry": {"coordinates":[6.8589658737,51.4663696289],"type":"Point"}
}