{
  "type": "Feature",
  "properties": {
    "iso:country":"DE",
    "sg:address":"W\u00f6rishofer Str. 75 A",
    "sg:city":"T\u00fcrkheim",
    "sg:phone":"+49 8245/1440",
    "sg:postcode":"86842",
    "sg:province":"Bayern",
    "wof:name":"Transportbeton Dachser Gmbh & Co. Kg",
    "wof:placetype":"venue"
},
  "geometry": {"coordinates":[10.6369419098,48.0553894043],"type":"Point"}
}