{
  "type": "Feature",
  "properties": {
    "iso:country":"DE",
    "sg:address":"Freisinger Str. 40",
    "sg:city":"Erding",
    "sg:phone":"+49 8122/902502",
    "sg:postcode":"85435",
    "sg:province":"Bayern",
    "wof:name":"Pointner Bauunternehmung Gmbh",
    "wof:placetype":"venue"
},
  "geometry": {"coordinates":[11.9024333954,48.3125305176],"type":"Point"}
}