{
  "type": "Feature",
  "properties": {
    "iso:country":"DE",
    "sg:address":"Dalbergsweg 9",
    "sg:city":"Erfurt",
    "sg:phone":"+49 361/2258777",
    "sg:postcode":"99084",
    "sg:province":"Th\u00fcringen",
    "wof:name":"Blumen & Floristik",
    "wof:placetype":"venue"
},
  "geometry": {"coordinates":[11.023325,50.971249],"type":"Point"}
}