{
  "type": "Feature",
  "properties": {
    "iso:country":"DE",
    "sg:address":"Waidmannsluster Damm 50",
    "sg:city":"Berlin",
    "sg:phone":"+49 30/4331304",
    "sg:postcode":"13509",
    "sg:province":"Berlin",
    "wof:name":"Restaurant 50",
    "wof:placetype":"venue"
},
  "geometry": {"coordinates":[13.2980298996,52.5980415344],"type":"Point"}
}