{
  "type": "Feature",
  "properties": {
    "iso:country":"DE",
    "sg:address":"Dorstener Str. 340",
    "sg:city":"Oberhausen",
    "sg:phone":"+49 208/600586",
    "sg:postcode":"46119",
    "sg:province":"Nordrhein-Westfalen",
    "wof:name":"R. Kru\u00df",
    "wof:placetype":"venue"
},
  "geometry": {"coordinates":[6.868105,51.5261],"type":"Point"}
}