{
  "type": "Feature",
  "properties": {
    "iso:country":"DE",
    "sg:address":"Poststr. 6",
    "sg:city":"\u00dcbach-Palenberg",
    "sg:phone":"+49 2451/47671",
    "sg:postcode":"52531",
    "sg:province":"Nordrhein-Westfalen",
    "wof:name":"J. Dremmen",
    "wof:placetype":"venue"
},
  "geometry": {"coordinates":[6.10144,50.926689],"type":"Point"}
}