{
  "type": "Feature",
  "properties": {
    "iso:country":"DE",
    "sg:address":"H\u00f6henstr. 12",
    "sg:city":"Frensdorf",
    "sg:phone":"+49 9502/7233",
    "sg:postcode":"96158",
    "sg:province":"Bayern",
    "wof:name":"Sabine Diroll Heilpraktikterin",
    "wof:placetype":"venue"
},
  "geometry": {"coordinates":[10.8666753769,49.8151626587],"type":"Point"}
}