{
  "type": "Feature",
  "properties": {
    "iso:country":"DE",
    "sg:address":"Graf-von-Galen-Str. 98",
    "sg:city":"Heinsberg",
    "sg:phone":"+49 2452/61000",
    "sg:postcode":"52525",
    "sg:province":"Nordrhein-Westfalen",
    "wof:name":"Gottfried Lintzen Inh. Gerda-maria Schulte",
    "wof:placetype":"venue"
},
  "geometry": {"coordinates":[6.149386,51.059811],"type":"Point"}
}