{
  "type": "Feature",
  "properties": {
    "iso:country":"DE",
    "sg:address":"Bahnhofstr. 2",
    "sg:city":"Kl\u00f6tze",
    "sg:postcode":"38486",
    "sg:province":"Sachsen-Anhalt",
    "wof:name":"L\u00f6wen-drogerie",
    "wof:placetype":"venue"
},
  "geometry": {"coordinates":[11.161117,52.626316],"type":"Point"}
}