{
  "type": "Feature",
  "properties": {
    "iso:country":"DE",
    "sg:address":"Hahnenpassage",
    "sg:city":"Kerpen",
    "sg:phone":"+49 2237/53166",
    "sg:postcode":"50171",
    "sg:province":"Nordrhein-Westfalen",
    "wof:name":"Almut Przybilla",
    "wof:placetype":"venue"
},
  "geometry": {"coordinates":[6.693081,50.872066],"type":"Point"}
}