{
  "type": "Feature",
  "properties": {
    "iso:country":"DE",
    "sg:address":"Berliner Allee 20",
    "sg:city":"Wassenberg",
    "sg:phone":"+49 2432/3067",
    "sg:postcode":"41849",
    "sg:province":"Nordrhein-Westfalen",
    "wof:name":"Theo Und Matthias Cohnen Ingenieure",
    "wof:placetype":"venue"
},
  "geometry": {"coordinates":[6.162598,51.093189],"type":"Point"}
}