{
  "type": "Feature",
  "properties": {
    "iso:country":"DE",
    "sg:address":"W\u00fcstener Str. 70",
    "sg:city":"Bad Salzuflen",
    "sg:phone":"+49 5222/10619",
    "sg:postcode":"32108",
    "sg:province":"Nordrhein-Westfalen",
    "wof:name":"Ludger Cramer",
    "wof:placetype":"venue"
},
  "geometry": {"coordinates":[8.765692,52.094425],"type":"Point"}
}