{
  "type": "Feature",
  "properties": {
    "iso:country":"DE",
    "sg:address":"Antonstr. 18",
    "sg:city":"Dresden",
    "sg:phone":"+49 351/8045861",
    "sg:postcode":"01097",
    "sg:province":"Sachsen",
    "wof:name":"Metzgerei Huber",
    "wof:placetype":"venue"
},
  "geometry": {"coordinates":[13.7422771454,51.0648078918],"type":"Point"}
}