{
  "type": "Feature",
  "properties": {
    "iso:country":"DE",
    "sg:address":"Kammerwald 62",
    "sg:city":"Hellenthal",
    "sg:phone":"+49 2482/2459",
    "sg:postcode":"53940",
    "sg:province":"Nordrhein-Westfalen",
    "wof:name":"Ursula Breuer-schosnig Krankengymnastin",
    "wof:placetype":"venue"
},
  "geometry": {"coordinates":[6.465805,50.486553],"type":"Point"}
}