{
  "type": "Feature",
  "properties": {
    "iso:country":"DE",
    "sg:address":"Schiede 16",
    "sg:city":"Limburg",
    "sg:phone":"+49 6431/23411",
    "sg:postcode":"65549",
    "sg:province":"Hessen",
    "wof:name":"L. P\u00f6rtner",
    "wof:placetype":"venue"
},
  "geometry": {"coordinates":[8.058967,50.388069],"type":"Point"}
}