{
  "type": "Feature",
  "properties": {
    "iso:country":"DE",
    "sg:city":"Ebermannsdorf",
    "sg:phone":"+49 9624/2220",
    "sg:postcode":"92263",
    "sg:province":"Bayern",
    "wof:name":"Kreissparkasse",
    "wof:placetype":"venue"
},
  "geometry": {"coordinates":[11.939943,49.391846],"type":"Point"}
}