{
  "type": "Feature",
  "properties": {
    "iso:country":"DE",
    "sg:address":"Lothringer Str. 64",
    "sg:city":"Pirmasens",
    "sg:phone":"+49 6331/21120",
    "sg:postcode":"66955",
    "sg:province":"Rheinland-Pfalz",
    "wof:name":"H.-j. Elig Und F. Hornung Steuerberater",
    "wof:placetype":"venue"
},
  "geometry": {"coordinates":[7.600689888,49.1764335632],"type":"Point"}
}