{
  "type": "Feature",
  "properties": {
    "iso:country":"DE",
    "sg:address":"Bahnhofstr. 39",
    "sg:city":"Hetzerath",
    "sg:phone":"+49 6508/230",
    "sg:postcode":"54523",
    "sg:province":"Rheinland-Pfalz",
    "wof:name":"Hermann K\u00e4mper Architekt",
    "wof:placetype":"venue"
},
  "geometry": {"coordinates":[6.806891,49.878197],"type":"Point"}
}