{
  "type": "Feature",
  "properties": {
    "iso:country":"DE",
    "sg:address":"Ottengr\u00fcner Str. 86",
    "sg:city":"Helmbrechts",
    "sg:phone":"+49 9252/99050",
    "sg:postcode":"95233",
    "sg:province":"Bayern",
    "wof:name":"Fritsche Accessoires Gmbh & Co. Kg",
    "wof:placetype":"venue"
},
  "geometry": {"coordinates":[11.7168560028,50.230178833],"type":"Point"}
}