{
  "type": "Feature",
  "properties": {
    "iso:country":"DE",
    "sg:address":"Kr\u00fcgerstr. 1",
    "sg:city":"Bad Wildungen",
    "sg:phone":"+49 5621/5230",
    "sg:postcode":"34537",
    "sg:province":"Hessen",
    "wof:name":"M\u00fcller Gmbh",
    "wof:placetype":"venue"
},
  "geometry": {"coordinates":[9.116981,51.118176],"type":"Point"}
}