{
  "type": "Feature",
  "properties": {
    "iso:country":"DE",
    "sg:address":"Schillerplatz 20",
    "sg:city":"Mainz",
    "sg:phone":"+49 6131/232605",
    "sg:postcode":"55116",
    "sg:province":"Rheinland-Pfalz",
    "wof:name":"Reuter Gmbh",
    "wof:placetype":"venue"
},
  "geometry": {"coordinates":[8.2672834396,49.9987983704],"type":"Point"}
}