{
  "type": "Feature",
  "properties": {
    "iso:country":"DE",
    "sg:address":"L\u00f6hrstr. 103-105",
    "sg:city":"Koblenz",
    "sg:phone":"+49 261/17041",
    "sg:postcode":"56068",
    "sg:province":"Rheinland-Pfalz",
    "wof:name":"B & H Freizeitbetriebe Burchard Ohg",
    "wof:placetype":"venue"
},
  "geometry": {"coordinates":[7.590731144,50.3552093506],"type":"Point"}
}