{
  "type": "Feature",
  "properties": {
    "iso:country":"DE",
    "sg:address":"R\u00f6merstr. 32",
    "sg:city":"Heidelberg",
    "sg:phone":"+49 6221/167140",
    "sg:postcode":"69115",
    "sg:province":"Baden-W\u00fcrttemberg",
    "wof:name":"Victoria Versicherungen Service-center",
    "wof:placetype":"venue"
},
  "geometry": {"coordinates":[8.6845474243,49.4035644531],"type":"Point"}
}