{
  "type": "Feature",
  "properties": {
    "iso:country":"DE",
    "sg:address":"Friedrich-Blink-Str. 3",
    "sg:city":"Epfenbach",
    "sg:phone":"+49 7263/8315",
    "sg:postcode":"74925",
    "sg:province":"Baden-W\u00fcrttemberg",
    "wof:name":"R.-m. Hafner",
    "wof:placetype":"venue"
},
  "geometry": {"coordinates":[8.909779,49.33905],"type":"Point"}
}