{
  "type": "Feature",
  "properties": {
    "iso:country":"DE",
    "sg:address":"Schlosserstr. 20 A",
    "sg:city":"Stuttgart",
    "sg:phone":"+49 711/6491111",
    "sg:postcode":"70180",
    "sg:province":"Baden-W\u00fcrttemberg",
    "wof:name":"Gangway Winter",
    "wof:placetype":"venue"
},
  "geometry": {"coordinates":[9.1763677597,48.7696456909],"type":"Point"}
}