{
  "type": "Feature",
  "properties": {
    "iso:country":"DE",
    "sg:address":"Wielandstr. 43",
    "sg:city":"Limburgerhof",
    "sg:phone":"+49 6236/8435",
    "sg:postcode":"67117",
    "sg:province":"Rheinland-Pfalz",
    "wof:name":"Wilhelm Tremmel Architekt",
    "wof:placetype":"venue"
},
  "geometry": {"coordinates":[8.384182,49.425316],"type":"Point"}
}