{
  "type": "Feature",
  "properties": {
    "iso:country":"DE",
    "sg:address":"Goethestr. 16",
    "sg:city":"St. Georgen",
    "sg:phone":"+49 7724/6219",
    "sg:postcode":"78112",
    "sg:province":"Baden-W\u00fcrttemberg",
    "wof:name":"Gebr. Kieninger Gmbh",
    "wof:placetype":"venue"
},
  "geometry": {"coordinates":[8.332807,48.130032],"type":"Point"}
}