{
  "type": "Feature",
  "properties": {
    "iso:country":"DE",
    "sg:address":"L\u00fcckshofstr. 16",
    "sg:city":"Gelsenkirchen",
    "sg:postcode":"45891",
    "sg:province":"Nordrhein-Westfalen",
    "wof:name":"Dieter Galla E. K.",
    "wof:placetype":"venue"
},
  "geometry": {"coordinates":[7.083586216,51.5725708008],"type":"Point"}
}