{
  "type": "Feature",
  "properties": {
    "iso:country":"DE",
    "sg:address":"Uerdinger Str. 252",
    "sg:city":"Krefeld",
    "sg:phone":"+49 2151/597493",
    "sg:postcode":"47800",
    "sg:province":"Nordrhein-Westfalen",
    "wof:name":"Ulla Schreiber Und Hessler Architekten",
    "wof:placetype":"venue"
},
  "geometry": {"coordinates":[6.588711,51.339088],"type":"Point"}
}