{
  "type": "Feature",
  "properties": {
    "iso:country":"DE",
    "sg:address":"Antwerpener Str. 63",
    "sg:city":"K\u00f6ln",
    "sg:phone":"+49 221/520601",
    "sg:postcode":"50672",
    "sg:province":"Nordrhein-Westfalen",
    "wof:name":"Tex-bar Bq",
    "wof:placetype":"venue"
},
  "geometry": {"coordinates":[6.933038,50.939964],"type":"Point"}
}