{
  "type": "Feature",
  "properties": {
    "iso:country":"DE",
    "sg:address":"Im Neugarten 5b",
    "sg:city":"Salmtal",
    "sg:phone":"+49 6578/7209",
    "sg:postcode":"54528",
    "sg:province":"Rheinland-Pfalz",
    "wof:name":"W. Munckwitz Bedachungen Gmbh",
    "wof:placetype":"venue"
},
  "geometry": {"coordinates":[6.834874,49.925152],"type":"Point"}
}