{
  "type": "Feature",
  "properties": {
    "iso:country":"DE",
    "sg:address":"Geheimrat-Ebert-Str 12",
    "sg:city":"Goslar",
    "sg:phone":"+49 5321/7030",
    "sg:postcode":"38640",
    "sg:province":"Niedersachsen",
    "wof:name":"Fels-werke Gmbh",
    "wof:placetype":"venue"
},
  "geometry": {"coordinates":[10.430902,51.911949],"type":"Point"}
}