{
  "type": "Feature",
  "properties": {
    "iso:country":"DE",
    "sg:address":"Dr.-Zinn-Weg 16",
    "sg:city":"Eberswalde",
    "sg:phone":"+49 3334/22895",
    "sg:postcode":"16225",
    "sg:province":"Brandenburg",
    "wof:name":"Prof. Dr. Med. G\u00fcnter Hoffmann",
    "wof:placetype":"venue"
},
  "geometry": {"coordinates":[13.828665,52.851948],"type":"Point"}
}