{
  "type": "Feature",
  "properties": {
    "iso:country":"DE",
    "sg:address":"Dieselstr. 31",
    "sg:city":"Offenbach",
    "sg:phone":"+49 69/9842190",
    "sg:postcode":"63071",
    "sg:province":"Hessen",
    "wof:name":"Glasbau Frommen Kg",
    "wof:placetype":"venue"
},
  "geometry": {"coordinates":[8.7924003601,50.1006584167],"type":"Point"}
}