{
  "type": "Feature",
  "properties": {
    "iso:country":"DE",
    "sg:address":"Alteburger Str. 292",
    "sg:city":"K\u00f6ln",
    "sg:phone":"+49 221/384443",
    "sg:postcode":"50968",
    "sg:province":"Nordrhein-Westfalen",
    "wof:name":"Christine John",
    "wof:placetype":"venue"
},
  "geometry": {"coordinates":[6.9738330841,50.9079017639],"type":"Point"}
}