{
  "type": "Feature",
  "properties": {
    "iso:country":"DE",
    "sg:address":"Groner Str. 17b",
    "sg:city":"G\u00f6ttingen",
    "sg:phone":"+49 551/44433",
    "sg:postcode":"37073",
    "sg:province":"Niedersachsen",
    "wof:name":"Wein-wirtschaft Vinum",
    "wof:placetype":"venue"
},
  "geometry": {"coordinates":[9.9324674606,51.5320510864],"type":"Point"}
}