{
  "type": "Feature",
  "properties": {
    "iso:country":"DE",
    "sg:address":"Edelwei\u00dfweg 11 D",
    "sg:city":"Hamburg",
    "sg:phone":"+49 40/575196",
    "sg:postcode":"22523",
    "sg:province":"Hamburg",
    "wof:name":"Heinz Brodersen Architekt",
    "wof:placetype":"venue"
},
  "geometry": {"coordinates":[9.887328,53.609669],"type":"Point"}
}