{
  "type": "Feature",
  "properties": {
    "iso:country":"DE",
    "sg:address":"Steinhammerstr. 135",
    "sg:city":"Dortmund",
    "sg:phone":"+49 231/61150",
    "sg:postcode":"44379",
    "sg:province":"Nordrhein-Westfalen",
    "wof:name":"Bockhalle",
    "wof:placetype":"venue"
},
  "geometry": {"coordinates":[7.3662781715,51.4992713928],"type":"Point"}
}