{
  "type": "Feature",
  "properties": {
    "iso:country":"DE",
    "sg:address":"Hundsr\u00fcckstr.39",
    "sg:city":"Korschenbroich",
    "sg:postcode":"41352",
    "sg:province":"Nordrhein-Westfalen",
    "wof:name":"Aufmassbuero Ewald",
    "wof:placetype":"venue"
},
  "geometry": {"coordinates":[6.5661478043,51.190158844],"type":"Point"}
}