{
  "type": "Feature",
  "properties": {
    "iso:country":"DE",
    "sg:address":"Grenzweg 30",
    "sg:city":"Rees",
    "sg:phone":"+49 2851/6534",
    "sg:postcode":"46459",
    "sg:province":"Nordrhein-Westfalen",
    "wof:name":"Wilhelm Angenendt",
    "wof:placetype":"venue"
},
  "geometry": {"coordinates":[6.408557,51.817818],"type":"Point"}
}