{
  "type": "Feature",
  "properties": {
    "iso:country":"DE",
    "sg:address":"Trochtelfinger Str. 7",
    "sg:city":"Gammertingen",
    "sg:phone":"+49 7574/2160",
    "sg:postcode":"72501",
    "sg:province":"Baden-W\u00fcrttemberg",
    "wof:name":"Thomas Hummel",
    "wof:placetype":"venue"
},
  "geometry": {"coordinates":[9.276506,48.264709],"type":"Point"}
}