{
  "type": "Feature",
  "properties": {
    "iso:country":"DE",
    "sg:address":"Beithenerstr. 13",
    "sg:city":"Troisdorf",
    "sg:phone":"+49 2241/400184",
    "sg:postcode":"53842",
    "sg:province":"Nordrhein-Westfalen",
    "wof:name":"Image Market",
    "wof:placetype":"venue"
},
  "geometry": {"coordinates":[7.131949,50.815231],"type":"Point"}
}