{
  "type": "Feature",
  "properties": {
    "iso:country":"DE",
    "sg:address":"Heiligenweg 1",
    "sg:city":"Feldatal",
    "sg:phone":"+49 6645/1672",
    "sg:postcode":"36325",
    "sg:province":"Hessen",
    "wof:name":"Erhard Nicklaus",
    "wof:placetype":"venue"
},
  "geometry": {"coordinates":[9.178305,50.617016],"type":"Point"}
}