{
  "type": "Feature",
  "properties": {
    "iso:country":"DE",
    "sg:address":"Beim Schlump 13a",
    "sg:city":"Hamburg",
    "sg:phone":"+49 40/4108465",
    "sg:postcode":"20144",
    "sg:province":"Hamburg",
    "wof:name":"E. Haase",
    "wof:placetype":"venue"
},
  "geometry": {"coordinates":[9.976805687,53.5711135864],"type":"Point"}
}