{
  "type": "Feature",
  "properties": {
    "iso:country":"DE",
    "sg:address":"Haigerer Str. 45",
    "sg:city":"Haiger",
    "sg:phone":"+49 2773/4727",
    "sg:postcode":"35708",
    "sg:province":"Hessen",
    "wof:name":"H. F. Grimm Ingenieur",
    "wof:placetype":"venue"
},
  "geometry": {"coordinates":[8.2053670883,50.7916526794],"type":"Point"}
}