{
  "type": "Feature",
  "properties": {
    "iso:country":"DE",
    "sg:address":"K\u00fctzhofweg 2",
    "sg:city":"Krefeld",
    "sg:phone":"+49 2151/754220",
    "sg:postcode":"47803",
    "sg:province":"Nordrhein-Westfalen",
    "wof:name":"Wolfgang Clae\u00dfens Architekt",
    "wof:placetype":"venue"
},
  "geometry": {"coordinates":[6.526754,51.360241],"type":"Point"}
}