{
  "type": "Feature",
  "properties": {
    "iso:country":"DE",
    "sg:address":"Zollbr\u00fcckenstr. 93c",
    "sg:city":"Sonneberg",
    "sg:phone":"+49 3675/803343",
    "sg:postcode":"96515",
    "sg:province":"Th\u00fcringen",
    "wof:name":"Dieter Malter Anlageberater",
    "wof:placetype":"venue"
},
  "geometry": {"coordinates":[11.1503925323,50.3698997498],"type":"Point"}
}