{
  "type": "Feature",
  "properties": {
    "iso:country":"DE",
    "sg:address":"Schubertstr. 21",
    "sg:city":"Dillingen",
    "sg:phone":"+49 6831/704025",
    "sg:postcode":"66763",
    "sg:province":"Saarland",
    "wof:name":"U. Lauer-kussani",
    "wof:placetype":"venue"
},
  "geometry": {"coordinates":[6.7244920731,49.3513908386],"type":"Point"}
}