{
  "type": "Feature",
  "properties": {
    "iso:country":"DE",
    "sg:address":"Hannoversche Str. 92",
    "sg:city":"Nienburg",
    "sg:phone":"+49 5021/912929",
    "sg:postcode":"31582",
    "sg:province":"Niedersachsen",
    "wof:name":"Nws Wach & Sicherheit Nienburg Gmbh",
    "wof:placetype":"venue"
},
  "geometry": {"coordinates":[9.2228288651,52.6279029846],"type":"Point"}
}