{
  "type": "Feature",
  "properties": {
    "iso:country":"DE",
    "sg:address":"Hirschtalstrasse 3",
    "sg:city":"Enzkl\u00f6sterle",
    "sg:phone":"+49 7085/7615",
    "sg:postcode":"75337",
    "sg:province":"Baden-W\u00fcrttemberg",
    "wof:name":"Campingplatz M\u00fcllerwiese",
    "wof:placetype":"venue"
},
  "geometry": {"coordinates":[8.4688158035,48.6665687561],"type":"Point"}
}