{
  "type": "Feature",
  "properties": {
    "iso:country":"DE",
    "sg:address":"Asterweg 3",
    "sg:city":"Langg\u00f6ns",
    "sg:phone":"+49 6403/71099",
    "sg:postcode":"35428",
    "sg:province":"Hessen",
    "wof:name":"Winter & Schulz Wohnbau Und Vertriebs Gmbh",
    "wof:placetype":"venue"
},
  "geometry": {"coordinates":[8.6721639633,50.4924736023],"type":"Point"}
}