{
  "type": "Feature",
  "properties": {
    "iso:country":"DE",
    "sg:address":"Frankfurter Str. 29",
    "sg:city":"K\u00f6ln",
    "sg:phone":"+49 221/614130",
    "sg:postcode":"51065",
    "sg:province":"Nordrhein-Westfalen",
    "wof:name":"Ulrike Lindau",
    "wof:placetype":"venue"
},
  "geometry": {"coordinates":[7.00679,50.960831],"type":"Point"}
}