{
  "type": "Feature",
  "properties": {
    "iso:country":"DE",
    "sg:address":"Exerzierstr. 14",
    "sg:city":"Berlin",
    "sg:phone":"+49 30/4658005",
    "sg:postcode":"13357",
    "sg:province":"Berlin",
    "wof:name":"Jupiter Fernsehdienst Gmbh",
    "wof:placetype":"venue"
},
  "geometry": {"coordinates":[13.3749456406,52.5539855957],"type":"Point"}
}