{
  "type": "Feature",
  "properties": {
    "iso:country":"DE",
    "sg:address":"Anton-Bruckner-Str 1/W",
    "sg:city":"Sch\u00f6nwald",
    "sg:phone":"+49 7722/4613",
    "sg:postcode":"78141",
    "sg:province":"Baden-W\u00fcrttemberg",
    "wof:name":"Gebr. Allgaier",
    "wof:placetype":"venue"
},
  "geometry": {"coordinates":[8.19503,48.105709],"type":"Point"}
}