{
  "type": "Feature",
  "properties": {
    "iso:country":"DE",
    "sg:address":"Dorfstr. 12",
    "sg:city":"Oberostendorf",
    "sg:postcode":"86869",
    "sg:province":"Bayern",
    "wof:name":"Gooroo Deutschland Ag",
    "wof:placetype":"venue"
},
  "geometry": {"coordinates":[10.732152,47.948891],"type":"Point"}
}