{
  "type": "Feature",
  "properties": {
    "iso:country":"DE",
    "sg:address":"Aichtalstr. 14",
    "sg:city":"Holzgerlingen",
    "sg:phone":"+49 7031/740861",
    "sg:postcode":"71088",
    "sg:province":"Baden-W\u00fcrttemberg",
    "wof:name":"Mar-software Manfred Ruf",
    "wof:placetype":"venue"
},
  "geometry": {"coordinates":[9.0275669098,48.6420440674],"type":"Point"}
}