{
  "type": "Feature",
  "properties": {
    "iso:country":"DE",
    "sg:address":"Zur Tuchbleiche 4",
    "sg:city":"Wiesloch",
    "sg:phone":"+49 6222/92320",
    "sg:postcode":"69168",
    "sg:province":"Baden-W\u00fcrttemberg",
    "wof:name":"Dombrowski Massivhaus Gmbh",
    "wof:placetype":"venue"
},
  "geometry": {"coordinates":[8.699046,49.291473],"type":"Point"}
}