{
  "type": "Feature",
  "properties": {
    "iso:country":"DE",
    "sg:address":"Kurf\u00fcrstendamm 69",
    "sg:city":"Berlin",
    "sg:phone":"+49 30/8819123",
    "sg:postcode":"10707",
    "sg:province":"Berlin",
    "wof:name":"Blankenberg Floristik",
    "wof:placetype":"venue"
},
  "geometry": {"coordinates":[13.307586,52.500278],"type":"Point"}
}