{
  "type": "Feature",
  "properties": {
    "iso:country":"DE",
    "sg:address":"Frankfurter Str. 29",
    "sg:city":"Seligenstadt",
    "sg:phone":"+49 6182/3670",
    "sg:postcode":"63500",
    "sg:province":"Hessen",
    "wof:name":"Hubert Reichenbach",
    "wof:placetype":"venue"
},
  "geometry": {"coordinates":[8.971799,50.044182],"type":"Point"}
}