{
  "type": "Feature",
  "properties": {
    "iso:country":"DE",
    "sg:address":"Esslinger Str. 9",
    "sg:city":"Unterensingen",
    "sg:phone":"+49 7022/65151",
    "sg:postcode":"72669",
    "sg:province":"Baden-W\u00fcrttemberg",
    "wof:name":"Baslers Sportswear",
    "wof:placetype":"venue"
},
  "geometry": {"coordinates":[9.355741,48.656582],"type":"Point"}
}