{
  "type": "Feature",
  "properties": {
    "iso:country":"DE",
    "sg:address":"Im Wolfbusch 50",
    "sg:city":"Stuttgart",
    "sg:phone":"+49 711/865324",
    "sg:postcode":"70499",
    "sg:province":"Baden-W\u00fcrttemberg",
    "wof:name":"Herbert Heuzeroth",
    "wof:placetype":"venue"
},
  "geometry": {"coordinates":[9.110523,48.807228],"type":"Point"}
}