{
  "type": "Feature",
  "properties": {
    "iso:country":"DE",
    "sg:address":"Carl-Bertelsmann-Str. 161 k",
    "sg:city":"G\u00fctersloh",
    "sg:phone":"+49 5241/800",
    "sg:postcode":"33332",
    "sg:province":"Nordrhein-Westfalen",
    "wof:name":"Bertelsmann Kalender Und Promotion Service Gmbh",
    "wof:placetype":"venue"
},
  "geometry": {"coordinates":[8.409353,51.894035],"type":"Point"}
}