{
  "type": "Feature",
  "properties": {
    "iso:country":"DE",
    "sg:address":"Rh\u00f6nstr. 9 a",
    "sg:city":"Taunusstein",
    "sg:phone":"+49 6128/44212",
    "sg:postcode":"65232",
    "sg:province":"Hessen",
    "wof:name":"Bernhard Muschlien Heilpraktiker",
    "wof:placetype":"venue"
},
  "geometry": {"coordinates":[8.1406936646,50.1306266785],"type":"Point"}
}