{
  "type": "Feature",
  "properties": {
    "iso:country":"DE",
    "sg:address":"Hauptstr. 11",
    "sg:city":"Lippetal",
    "sg:phone":"+49 2527/1401",
    "sg:postcode":"59510",
    "sg:province":"Nordrhein-Westfalen",
    "wof:name":"Pizzeria Mamma Mia",
    "wof:placetype":"venue"
},
  "geometry": {"coordinates":[8.039689064,51.6645202637],"type":"Point"}
}