{
  "type": "Feature",
  "properties": {
    "iso:country":"DE",
    "sg:address":"Stapper Str 36-38",
    "sg:city":"Heinsberg",
    "sg:phone":"+49 2452/89741",
    "sg:postcode":"52525",
    "sg:province":"Nordrhein-Westfalen",
    "wof:name":"K\u00fcppers Polsterm\u00f6bel Gmbh",
    "wof:placetype":"venue"
},
  "geometry": {"coordinates":[6.0815320015,51.0790405273],"type":"Point"}
}