{
  "type": "Feature",
  "properties": {
    "iso:country":"DE",
    "sg:address":"Hofbr\u00fchl 3",
    "sg:city":"Babenhausen",
    "sg:phone":"+49 8333/1262",
    "sg:postcode":"87727",
    "sg:province":"Bayern",
    "wof:name":"A. Engel",
    "wof:placetype":"venue"
},
  "geometry": {"coordinates":[10.25046,48.144936],"type":"Point"}
}