{
  "type": "Feature",
  "properties": {
    "iso:country":"DE",
    "sg:address":"Elisabeth-Selbert-Str. 13",
    "sg:city":"Moers",
    "sg:phone":"+49 2841/45852",
    "sg:postcode":"47445",
    "sg:province":"Nordrhein-Westfalen",
    "wof:name":"W. Maschke Architekt",
    "wof:placetype":"venue"
},
  "geometry": {"coordinates":[6.615675,51.485264],"type":"Point"}
}