{
  "type": "Feature",
  "properties": {
    "iso:country":"DE",
    "sg:address":"Flughafenstr. 217",
    "sg:city":"Dortmund",
    "sg:phone":"+49 231/258081",
    "sg:postcode":"44309",
    "sg:province":"Nordrhein-Westfalen",
    "wof:name":"Heinz Hanke",
    "wof:placetype":"venue"
},
  "geometry": {"coordinates":[7.540666,51.53833],"type":"Point"}
}