{
  "type": "Feature",
  "properties": {
    "iso:country":"DE",
    "sg:address":"Dohler Str. 152",
    "sg:city":"M\u00f6nchengladbach",
    "sg:phone":"+49 2166/41349",
    "sg:postcode":"41238",
    "sg:province":"Nordrhein-Westfalen",
    "wof:name":"Dubrovnik",
    "wof:placetype":"venue"
},
  "geometry": {"coordinates":[6.4624629021,51.179397583],"type":"Point"}
}