{
  "type": "Feature",
  "properties": {
    "iso:country":"DE",
    "sg:address":"Humboldtstr. 11-14",
    "sg:city":"Spaichingen",
    "sg:phone":"+49 2241/310450",
    "sg:postcode":"78549",
    "sg:province":"Baden-W\u00fcrttemberg",
    "wof:name":"W+w W\u00c4rmeme\u00dfdienstwolfgang Hirschmann",
    "wof:placetype":"venue"
},
  "geometry": {"coordinates":[7.140804,50.779606],"type":"Point"}
}