{
  "type": "Feature",
  "properties": {
    "iso:country":"DE",
    "sg:address":"Stollengasse 17",
    "sg:city":"Rothenburg",
    "sg:phone":"+49 9861/92587",
    "sg:postcode":"91541",
    "sg:province":"Bayern",
    "wof:name":"Image Design-gesellschaft F\u00fcr Innovative Medien-systeme Und",
    "wof:placetype":"venue"
},
  "geometry": {"coordinates":[10.1823511124,49.3782653809],"type":"Point"}
}