{
  "type": "Feature",
  "properties": {
    "iso:country":"DE",
    "sg:address":"Lindenallee 3",
    "sg:city":"Luisenthal",
    "sg:phone":"+49 36257/40050",
    "sg:postcode":"99885",
    "sg:province":"Th\u00fcringen",
    "wof:name":"M\u00f6ller Engineering Gmbh",
    "wof:placetype":"venue"
},
  "geometry": {"coordinates":[10.7260942459,50.7911872864],"type":"Point"}
}