{
  "type": "Feature",
  "properties": {
    "iso:country":"DE",
    "sg:address":"Br\u00fcckenweg 8",
    "sg:city":"Attendorn",
    "sg:phone":"+49 2722/50031",
    "sg:postcode":"57439",
    "sg:province":"Nordrhein-Westfalen",
    "wof:name":"Technozon-apparatebau Gmbh",
    "wof:placetype":"venue"
},
  "geometry": {"coordinates":[7.926259,51.131664],"type":"Point"}
}