{
  "type": "Feature",
  "properties": {
    "iso:country":"DE",
    "sg:address":"Stursberg II 13",
    "sg:city":"Remscheid",
    "sg:postcode":"42899",
    "sg:province":"Nordrhein-Westfalen",
    "wof:name":"Tillmanns Schreinereibedarf Znl D. Heller & K\u00f6ster",
    "wof:placetype":"venue"
},
  "geometry": {"coordinates":[7.215365,51.197815],"type":"Point"}
}