{
  "type": "Feature",
  "properties": {
    "iso:country":"DE",
    "sg:address":"Uelzener Str.1",
    "sg:city":"Melbeck",
    "sg:phone":"+49 4134",
    "sg:postcode":"21406",
    "sg:province":"Niedersachsen",
    "wof:name":"Auto Team Melbeck",
    "wof:placetype":"venue"
},
  "geometry": {"coordinates":[10.406664,53.181664],"type":"Point"}
}