{
  "type": "Feature",
  "properties": {
    "iso:country":"DE",
    "sg:address":"Gleidinger Str 15",
    "sg:city":"Laatzen",
    "sg:phone":"+49 4951/022690",
    "sg:postcode":"30880",
    "sg:province":"Niedersachsen",
    "wof:name":"Kreissparkasse Hannover",
    "wof:placetype":"venue"
},
  "geometry": {"coordinates":[9.88658,52.28009],"type":"Point"}
}