{
  "type": "Feature",
  "properties": {
    "iso:country":"DE",
    "sg:address":"Wandlhamerstr. 31",
    "sg:city":"Gr\u00e4felfing",
    "sg:phone":"+49 89/8980450",
    "sg:postcode":"82166",
    "sg:province":"Bayern",
    "wof:name":"Weiss Klimatechnik Gmbh",
    "wof:placetype":"venue"
},
  "geometry": {"coordinates":[11.4368581772,48.121711731],"type":"Point"}
}