{
  "type": "Feature",
  "properties": {
    "iso:country":"DE",
    "sg:address":"Auenstr. 10",
    "sg:city":"R\u00f6hrmoos",
    "sg:phone":"+49 8139/92455",
    "sg:postcode":"85244",
    "sg:province":"Bayern",
    "wof:name":"Marschall Immobilienmakler",
    "wof:placetype":"venue"
},
  "geometry": {"coordinates":[11.4425430298,48.328830719],"type":"Point"}
}