{
  "type": "Feature",
  "properties": {
    "iso:country":"DE",
    "sg:address":"Im Gewerbepark 9",
    "sg:city":"Regensburg",
    "sg:phone":"+49 941/45660",
    "sg:postcode":"93059",
    "sg:province":"Bayern",
    "wof:name":"I. Franz",
    "wof:placetype":"venue"
},
  "geometry": {"coordinates":[12.125076,49.030472],"type":"Point"}
}