{
  "type": "Feature",
  "properties": {
    "iso:country":"DE",
    "sg:address":"Bisseser Str. 42",
    "sg:city":"Echzell",
    "sg:phone":"+49 6008/510",
    "sg:postcode":"61209",
    "sg:province":"Hessen",
    "wof:name":"M\u00f6bs-raumausstattung Gmbh",
    "wof:placetype":"venue"
},
  "geometry": {"coordinates":[8.893807,50.391209],"type":"Point"}
}