{
  "type": "Feature",
  "properties": {
    "iso:country":"DE",
    "sg:address":"Hochstr. 61",
    "sg:city":"Gladbeck",
    "sg:phone":"+49 2043/66528",
    "sg:postcode":"45964",
    "sg:province":"Nordrhein-Westfalen",
    "wof:name":"B. Arda",
    "wof:placetype":"venue"
},
  "geometry": {"coordinates":[6.995279789,51.574180603],"type":"Point"}
}