{
  "type": "Feature",
  "properties": {
    "iso:country":"DE",
    "sg:address":"Quellenring 14",
    "sg:city":"Bad Orb",
    "sg:postcode":"63619",
    "sg:province":"Hessen",
    "wof:name":"Hochbau Engel Gmbh",
    "wof:placetype":"venue"
},
  "geometry": {"coordinates":[9.3501577377,50.225353241],"type":"Point"}
}