{
  "type": "Feature",
  "properties": {
    "iso:country":"DE",
    "sg:address":"Amremberg 24",
    "sg:city":"Dortmund",
    "sg:phone":"+49 4923/1553816",
    "sg:postcode":"44363",
    "sg:province":"Nordrhein-Westfalen",
    "wof:name":"Msb Maschinenbau & Industrieanlagen Gmbh",
    "wof:placetype":"venue"
},
  "geometry": {"coordinates":[7.5118842125,51.4931373596],"type":"Point"}
}