{
  "type": "Feature",
  "properties": {
    "iso:country":"DE",
    "sg:address":"Im Zillgen 56",
    "sg:city":"Rhens",
    "sg:phone":"+49 2628/2787",
    "sg:postcode":"56321",
    "sg:province":"Rheinland-Pfalz",
    "wof:name":"Ulrich Breidbach",
    "wof:placetype":"venue"
},
  "geometry": {"coordinates":[7.613285,50.278328],"type":"Point"}
}