{
  "type": "Feature",
  "properties": {
    "iso:country":"DE",
    "sg:address":"Wilhelmstr. 34",
    "sg:city":"Remscheid",
    "sg:phone":"+49 2191/11103",
    "sg:postcode":"42853",
    "sg:province":"Nordrhein-Westfalen",
    "wof:name":"Sozialberatungsstelle Caritasverband",
    "wof:placetype":"venue"
},
  "geometry": {"coordinates":[7.180033,51.187145],"type":"Point"}
}