{
  "type": "Feature",
  "properties": {
    "iso:country":"DE",
    "sg:address":"Wingershofer Str. 24",
    "sg:city":"Amberg",
    "sg:phone":"+49 9621/21089",
    "sg:postcode":"92224",
    "sg:province":"Bayern",
    "wof:name":"Dos Computersysteme Gmbh",
    "wof:placetype":"venue"
},
  "geometry": {"coordinates":[11.8581933975,49.4396781921],"type":"Point"}
}