{
  "type": "Feature",
  "properties": {
    "iso:country":"DE",
    "sg:address":"Ernst-Th\u00e4lmann-Str. 1",
    "sg:city":"Selmsdorf",
    "sg:phone":"+49 38823/21305",
    "sg:postcode":"23923",
    "sg:province":"Mecklenburg-Vorpommern",
    "wof:name":"Hans-heinrich Kleinfeld",
    "wof:placetype":"venue"
},
  "geometry": {"coordinates":[10.860322,53.881451],"type":"Point"}
}