{
  "type": "Feature",
  "properties": {
    "iso:country":"DE",
    "sg:address":"Zum Niepmannshof 5",
    "sg:city":"Kamp-Lintfort",
    "sg:postcode":"47475",
    "sg:province":"Nordrhein-Westfalen",
    "wof:name":"Euroteam Deutschland Gmbh",
    "wof:placetype":"venue"
},
  "geometry": {"coordinates":[6.5416369438,51.4817619324],"type":"Point"}
}