{
  "type": "Feature",
  "properties": {
    "iso:country":"DE",
    "sg:address":"Zwetschenstr. 18",
    "sg:city":"Espelkamp",
    "sg:phone":"+49 5743/1361",
    "sg:postcode":"32339",
    "sg:province":"Nordrhein-Westfalen",
    "wof:name":"Fritz L\u00f6mker",
    "wof:placetype":"venue"
},
  "geometry": {"coordinates":[8.64415,52.36034],"type":"Point"}
}