{
  "type": "Feature",
  "properties": {
    "iso:country":"DE",
    "sg:address":"Herderstr. 19",
    "sg:city":"Heiligenhaus",
    "sg:phone":"+49 2056/5088",
    "sg:postcode":"42579",
    "sg:province":"Nordrhein-Westfalen",
    "wof:name":"Michael Jelitto Gmbh",
    "wof:placetype":"venue"
},
  "geometry": {"coordinates":[7.004113,51.328903],"type":"Point"}
}