{
  "type": "Feature",
  "properties": {
    "iso:country":"DE",
    "sg:address":"Zum Kalkofen 21",
    "sg:city":"Attendorn",
    "sg:postcode":"57439",
    "sg:province":"Nordrhein-Westfalen",
    "wof:name":"H\u00f6ffer & W\u00fcllner Verwaltungs- Gmbh",
    "wof:placetype":"venue"
},
  "geometry": {"coordinates":[7.9560379982,51.1081848145],"type":"Point"}
}