{
  "type": "Feature",
  "properties": {
    "iso:country":"DE",
    "sg:address":"Masurenallee 4-6",
    "sg:city":"Berlin",
    "sg:phone":"+49 30/3010380",
    "sg:postcode":"14057",
    "sg:province":"Berlin",
    "wof:name":"Zentral-omnibusbahnhof Berlin Gmbh",
    "wof:placetype":"venue"
},
  "geometry": {"coordinates":[13.2795143127,52.5069046021],"type":"Point"}
}