{
  "type": "Feature",
  "properties": {
    "iso:country":"DE",
    "sg:address":"Sebastian-Mutschelle-Str. 9",
    "sg:city":"Allershausen",
    "sg:phone":"+49 8166/5203",
    "sg:postcode":"85391",
    "sg:province":"Bayern",
    "wof:name":"Fredl Bau Innen- Und Au\u00dfenputz Gmbh",
    "wof:placetype":"venue"
},
  "geometry": {"coordinates":[11.593761,48.42701],"type":"Point"}
}