{
  "type": "Feature",
  "properties": {
    "iso:country":"DE",
    "sg:address":"Pullenhofen 12",
    "sg:city":"Bruck",
    "sg:postcode":"85567",
    "sg:province":"Bayern",
    "wof:name":"Sekeyde Gmbh",
    "wof:placetype":"venue"
},
  "geometry": {"coordinates":[11.9125299454,48.0299110413],"type":"Point"}
}