{
  "type": "Feature",
  "properties": {
    "iso:country":"DE",
    "sg:address":"Brockhauser Weg 41",
    "sg:city":"L\u00fcdenscheid",
    "sg:phone":"+49 2351/50430",
    "sg:postcode":"58507",
    "sg:province":"Nordrhein-Westfalen",
    "wof:name":"Gevelndorfer Krug",
    "wof:placetype":"venue"
},
  "geometry": {"coordinates":[7.6221618652,51.2406845093],"type":"Point"}
}