{
  "type": "Feature",
  "properties": {
    "iso:country":"DE",
    "sg:address":"An der Gronau 2",
    "sg:city":"Ellerau",
    "sg:phone":"+49 4106/76850",
    "sg:postcode":"25479",
    "sg:province":"Schleswig-Holstein",
    "wof:name":"Ssb Versicherungsmakler Gmbh",
    "wof:placetype":"venue"
},
  "geometry": {"coordinates":[9.9140062332,53.7479133606],"type":"Point"}
}