{
  "type": "Feature",
  "properties": {
    "iso:country":"DE",
    "sg:address":"Siegfried-Flack-Str. 3",
    "sg:city":"Altenburg",
    "sg:phone":"+49 3447/834045",
    "sg:postcode":"04600",
    "sg:province":"Th\u00fcringen",
    "wof:name":"J\u00fcrgen Klaus",
    "wof:placetype":"venue"
},
  "geometry": {"coordinates":[12.424391,51.004269],"type":"Point"}
}