{
  "type": "Feature",
  "properties": {
    "iso:country":"DE",
    "sg:address":"Im Ehlried 1",
    "sg:city":"Lorsch",
    "sg:phone":"+49 6251/54506",
    "sg:postcode":"64653",
    "sg:province":"Hessen",
    "wof:name":"Centercourt",
    "wof:placetype":"venue"
},
  "geometry": {"coordinates":[8.5733671188,49.6383934021],"type":"Point"}
}