{
  "type": "Feature",
  "properties": {
    "iso:country":"DE",
    "sg:address":"Schlo\u00dfstr. 98",
    "sg:city":"Olching",
    "sg:phone":"+49 8142/18739",
    "sg:postcode":"82140",
    "sg:province":"Bayern",
    "wof:name":"Erich Grimm Architekt",
    "wof:placetype":"venue"
},
  "geometry": {"coordinates":[11.31522,48.20924],"type":"Point"}
}