{
  "type": "Feature",
  "properties": {
    "iso:country":"DE",
    "sg:address":"Benninghofer Weg 1",
    "sg:city":"Mettmann",
    "sg:phone":"+49 2104/917807",
    "sg:postcode":"40822",
    "sg:province":"Nordrhein-Westfalen",
    "wof:name":"R\u00f6ttgerding Gmbh",
    "wof:placetype":"venue"
},
  "geometry": {"coordinates":[6.991772,51.248817],"type":"Point"}
}