{
  "type": "Feature",
  "properties": {
    "iso:country":"DE",
    "sg:address":"Wolfsbachweg 10",
    "sg:city":"Essen",
    "sg:phone":"+49 201/412924",
    "sg:postcode":"45133",
    "sg:province":"Nordrhein-Westfalen",
    "wof:name":"F. W. Pepperhoff",
    "wof:placetype":"venue"
},
  "geometry": {"coordinates":[6.9876441956,51.4015235901],"type":"Point"}
}