{
  "type": "Feature",
  "properties": {
    "iso:country":"DE",
    "sg:address":"Bilholtstr. 30",
    "sg:city":"Olfen",
    "sg:phone":"+49 2595/1238",
    "sg:postcode":"59399",
    "sg:province":"Nordrhein-Westfalen",
    "wof:name":"Bernhard Oeding-erdel",
    "wof:placetype":"venue"
},
  "geometry": {"coordinates":[7.38226,51.708485],"type":"Point"}
}