{
  "type": "Feature",
  "properties": {
    "iso:country":"DE",
    "sg:address":"Ziemerweg 14",
    "sg:city":"Idstein",
    "sg:phone":"+49 6126/55568",
    "sg:postcode":"65510",
    "sg:province":"Hessen",
    "wof:name":"Friedhelm Dohrmann Ingenieurb\u00fcro",
    "wof:placetype":"venue"
},
  "geometry": {"coordinates":[8.263674,50.224052],"type":"Point"}
}