{
  "type": "Feature",
  "properties": {
    "iso:country":"DE",
    "sg:address":"Oberstr. 91",
    "sg:city":"Hamburg",
    "sg:postcode":"20149",
    "sg:province":"Hamburg",
    "wof:name":"Mos Hamburg Beteiligungsgesellschaft Mbh",
    "wof:placetype":"venue"
},
  "geometry": {"coordinates":[9.988121,53.577789],"type":"Point"}
}