{
  "type": "Feature",
  "properties": {
    "iso:country":"DE",
    "sg:address":"Muffeter Weg 53",
    "sg:city":"Aachen",
    "sg:phone":"+49 241/85255",
    "sg:postcode":"52072",
    "sg:province":"Nordrhein-Westfalen",
    "wof:name":"A. Meinke",
    "wof:placetype":"venue"
},
  "geometry": {"coordinates":[6.060594,50.774376],"type":"Point"}
}