{
  "type": "Feature",
  "properties": {
    "iso:country":"DE",
    "sg:address":"Neust\u00e4dter Str. 42",
    "sg:city":"Wagenfeld",
    "sg:phone":"+49 5444/713",
    "sg:postcode":"49419",
    "sg:province":"Niedersachsen",
    "wof:name":"Helmut Kleinhans",
    "wof:placetype":"venue"
},
  "geometry": {"coordinates":[8.578821,52.565987],"type":"Point"}
}