{
  "type": "Feature",
  "properties": {
    "iso:country":"DE",
    "sg:address":"Haubachstr. 17",
    "sg:city":"Berlin",
    "sg:phone":"+49 30/3418047",
    "sg:postcode":"10585",
    "sg:province":"Berlin",
    "wof:name":"Plan Immobilienquelle Gmbh",
    "wof:placetype":"venue"
},
  "geometry": {"coordinates":[13.3039884567,52.5154380798],"type":"Point"}
}