{
  "type": "Feature",
  "properties": {
    "iso:country":"DE",
    "sg:address":"Obere M\u00fchle 41-45",
    "sg:city":"Iserlohn",
    "sg:postcode":"58644",
    "sg:province":"Nordrhein-Westfalen",
    "wof:name":"Getr\u00e4nkesupermarkt Spathmann Kg",
    "wof:placetype":"venue"
},
  "geometry": {"coordinates":[7.7037658691,51.3682861328],"type":"Point"}
}