{
  "type": "Feature",
  "properties": {
    "iso:country":"DE",
    "sg:address":"Alexander-Puschkin-Platz 1",
    "sg:city":"Dresden",
    "sg:phone":"+49 351/4410156",
    "sg:postcode":"01127",
    "sg:province":"Sachsen",
    "wof:name":"J\u00f6rg Mussoter Steuerberater Und",
    "wof:placetype":"venue"
},
  "geometry": {"coordinates":[13.7294282913,51.070476532],"type":"Point"}
}