{
  "type": "Feature",
  "properties": {
    "iso:country":"DE",
    "sg:address":"Pastor-B\u00f6litz-Str. 1",
    "sg:city":"Wesel",
    "sg:phone":"+49 281/29567",
    "sg:postcode":"46483",
    "sg:province":"Nordrhein-Westfalen",
    "wof:name":"Harald Pridat",
    "wof:placetype":"venue"
},
  "geometry": {"coordinates":[6.611987114,51.6563606262],"type":"Point"}
}