{
  "type": "Feature",
  "properties": {
    "iso:country":"DE",
    "sg:address":"Billerbecker Str. 10",
    "sg:city":"D\u00fclmen",
    "sg:phone":"+49 2594/2342",
    "sg:postcode":"48249",
    "sg:province":"Nordrhein-Westfalen",
    "wof:name":"Otto Dinand",
    "wof:placetype":"venue"
},
  "geometry": {"coordinates":[7.282790184,51.8366355896],"type":"Point"}
}