{
  "type": "Feature",
  "properties": {
    "iso:country":"DE",
    "sg:address":"L\u00fctte Raak 6",
    "sg:city":"Hamburg",
    "sg:phone":"+49 40/5206390",
    "sg:postcode":"22417",
    "sg:province":"Hamburg",
    "wof:name":"Horst Rabe",
    "wof:placetype":"venue"
},
  "geometry": {"coordinates":[10.026608,53.656715],"type":"Point"}
}