{
  "type": "Feature",
  "properties": {
    "iso:country":"DE",
    "sg:address":"Kirchgasse 3",
    "sg:city":"Volxheim",
    "sg:phone":"+49 6703/776",
    "sg:postcode":"55546",
    "sg:province":"Rheinland-Pfalz",
    "wof:name":"Manfred Kalow",
    "wof:placetype":"venue"
},
  "geometry": {"coordinates":[7.928736,49.817135],"type":"Point"}
}