{
  "type": "Feature",
  "properties": {
    "iso:country":"DE",
    "sg:address":"Mendener Landstr. 70",
    "sg:city":"Iserlohn",
    "sg:phone":"+49 2371/62052",
    "sg:postcode":"58636",
    "sg:province":"Nordrhein-Westfalen",
    "wof:name":"Benscheidt & Knips Ohg",
    "wof:placetype":"venue"
},
  "geometry": {"coordinates":[7.7097620964,51.3767814636],"type":"Point"}
}