{
  "type": "Feature",
  "properties": {
    "iso:country":"DE",
    "sg:address":"Wendlandstr. 2",
    "sg:city":"Uelzen",
    "sg:phone":"+49 581/42245",
    "sg:postcode":"29525",
    "sg:province":"Niedersachsen",
    "wof:name":"Walter-heinz L\u00fcck",
    "wof:placetype":"venue"
},
  "geometry": {"coordinates":[10.5916223526,52.9699401855],"type":"Point"}
}