{
  "type": "Feature",
  "properties": {
    "iso:country":"DE",
    "sg:address":"Itzehoer Str. 9",
    "sg:city":"D\u00e4geling",
    "sg:phone":"+49 4821/83225",
    "sg:postcode":"25578",
    "sg:province":"Schleswig-Holstein",
    "wof:name":"P. L\u00fcders",
    "wof:placetype":"venue"
},
  "geometry": {"coordinates":[9.529125,53.876076],"type":"Point"}
}