{
  "type": "Feature",
  "properties": {
    "iso:country":"DE",
    "sg:address":"Kortumstr. 129",
    "sg:city":"Bochum",
    "sg:phone":"+49 234/685420",
    "sg:postcode":"44787",
    "sg:province":"Nordrhein-Westfalen",
    "wof:name":"B\u00f6ning",
    "wof:placetype":"venue"
},
  "geometry": {"coordinates":[7.2186021805,51.4845161438],"type":"Point"}
}