{
  "type": "Feature",
  "properties": {
    "iso:country":"DE",
    "sg:address":"Repperndorfer Str. 1",
    "sg:city":"Kitzingen",
    "sg:phone":"+49 9321/920636",
    "sg:postcode":"97318",
    "sg:province":"Bayern",
    "wof:name":"Plus Warenhandels Gmbh & Co. Ohg",
    "wof:placetype":"venue"
},
  "geometry": {"coordinates":[10.152806282,49.7384109497],"type":"Point"}
}