{
  "type": "Feature",
  "properties": {
    "iso:country":"DE",
    "sg:address":"Brunnenstr. 21",
    "sg:city":"Bad Wildungen",
    "sg:phone":"+49 5621/2501",
    "sg:postcode":"34537",
    "sg:province":"Hessen",
    "wof:name":"R\u00f6diger Gmbh & Co. Kg Textil- Und Kaufhaus",
    "wof:placetype":"venue"
},
  "geometry": {"coordinates":[9.124907,51.119743],"type":"Point"}
}