{
  "type": "Feature",
  "properties": {
    "iso:country":"DE",
    "sg:address":"Franz-Heldmann-Str. 58",
    "sg:city":"Tirschenreuth",
    "sg:phone":"+49 9631/1237",
    "sg:postcode":"95643",
    "sg:province":"Bayern",
    "wof:name":"Magnitz Gmbh",
    "wof:placetype":"venue"
},
  "geometry": {"coordinates":[12.315612,49.883999],"type":"Point"}
}