{
  "type": "Feature",
  "properties": {
    "iso:country":"DE",
    "sg:address":"Tibergasse 2",
    "sg:city":"D\u00fclmen",
    "sg:phone":"+49 2594/5018",
    "sg:postcode":"48249",
    "sg:province":"Nordrhein-Westfalen",
    "wof:name":"Klaus Schlieker-k\u00f6nig Rechtsanwalt",
    "wof:placetype":"venue"
},
  "geometry": {"coordinates":[7.2757048607,51.8300743103],"type":"Point"}
}