{
  "type": "Feature",
  "properties": {
    "iso:country":"DE",
    "sg:address":"Humlanger Str. 20",
    "sg:city":"H\u00fcttisheim",
    "sg:phone":"+49 7305/932870",
    "sg:postcode":"89185",
    "sg:province":"Baden-W\u00fcrttemberg",
    "wof:name":"K. N. O. L. L. E. K.",
    "wof:placetype":"venue"
},
  "geometry": {"coordinates":[9.946754,48.28207],"type":"Point"}
}