{
  "type": "Feature",
  "properties": {
    "iso:country":"DE",
    "sg:address":"Im Gewerbepark 16",
    "sg:city":"Regensburg",
    "sg:phone":"+49 941/4908320",
    "sg:postcode":"93059",
    "sg:province":"Bayern",
    "wof:name":"Bhb Exklusiv Gardinen- Handels Gmbh",
    "wof:placetype":"venue"
},
  "geometry": {"coordinates":[12.1256284714,49.0301017761],"type":"Point"}
}