{
  "type": "Feature",
  "properties": {
    "iso:country":"DE",
    "sg:address":"Maarstr. 25",
    "sg:city":"Trier",
    "sg:phone":"+49 651/28222",
    "sg:postcode":"54292",
    "sg:province":"Rheinland-Pfalz",
    "wof:name":"Stolz Und Kintzinger Architekten",
    "wof:placetype":"venue"
},
  "geometry": {"coordinates":[6.645205,49.76247],"type":"Point"}
}