{
  "type": "Feature",
  "properties": {
    "iso:country":"DE",
    "sg:address":"Grubenkopf 16 a",
    "sg:city":"Hermeskeil",
    "sg:phone":"+49 6503/6588",
    "sg:postcode":"54411",
    "sg:province":"Rheinland-Pfalz",
    "wof:name":"Faba Plast Gmbh",
    "wof:placetype":"venue"
},
  "geometry": {"coordinates":[6.9376211166,49.6588630676],"type":"Point"}
}