{
  "type": "Feature",
  "properties": {
    "iso:country":"DE",
    "sg:address":"Harth\u00f6fl 1",
    "sg:city":"Nittenau",
    "sg:postcode":"93149",
    "sg:province":"Bayern",
    "wof:name":"Bauerngemeinschaft Regenknie E. V.",
    "wof:placetype":"venue"
},
  "geometry": {"coordinates":[12.2023601532,49.1980476379],"type":"Point"}
}