{
  "type": "Feature",
  "properties": {
    "iso:country":"DE",
    "sg:address":"Alter Flughafen 21",
    "sg:city":"Hannover",
    "sg:phone":"+49 511/631036",
    "sg:postcode":"30179",
    "sg:province":"Niedersachsen",
    "wof:name":"Wilke-s\u00e4urebau Hermann Wilke",
    "wof:placetype":"venue"
},
  "geometry": {"coordinates":[9.7498083115,52.4178009033],"type":"Point"}
}