{
  "type": "Feature",
  "properties": {
    "iso:country":"DE",
    "sg:address":"Offenburger Str. 1",
    "sg:city":"Karlsruhe",
    "sg:phone":"+49 721/9887011",
    "sg:postcode":"76199",
    "sg:province":"Baden-W\u00fcrttemberg",
    "wof:name":"Darko Stevcic Architekt",
    "wof:placetype":"venue"
},
  "geometry": {"coordinates":[8.40124,48.987038],"type":"Point"}
}