{
  "type": "Feature",
  "properties": {
    "iso:country":"DE",
    "sg:address":"Klopstockstr. 14",
    "sg:city":"D\u00fcsseldorf",
    "sg:phone":"+49 211/133073",
    "sg:postcode":"40237",
    "sg:province":"Nordrhein-Westfalen",
    "wof:name":"Rolf Wegener Gmbh & Co. Kg",
    "wof:placetype":"venue"
},
  "geometry": {"coordinates":[6.8134608269,51.2406616211],"type":"Point"}
}