{
  "type": "Feature",
  "properties": {
    "iso:country":"DE",
    "sg:address":"Dangaster Str. 84a",
    "sg:city":"Varel",
    "sg:phone":"+49 4451/965858",
    "sg:postcode":"26316",
    "sg:province":"Niedersachsen",
    "wof:name":"Arno Hasselder Bauunternehmen Gmbh",
    "wof:placetype":"venue"
},
  "geometry": {"coordinates":[8.1213855743,53.4127159119],"type":"Point"}
}