{
  "type": "Feature",
  "properties": {
    "iso:country":"DE",
    "sg:address":"Karl-Marx-Str. 3",
    "sg:city":"Bautzen",
    "sg:phone":"+49 3591/49740",
    "sg:postcode":"02625",
    "sg:province":"Sachsen",
    "wof:name":"Greulich Und Collegen Rechtsanw\u00e4lte",
    "wof:placetype":"venue"
},
  "geometry": {"coordinates":[14.4279203415,51.1792411804],"type":"Point"}
}