{
  "type": "Feature",
  "properties": {
    "iso:country":"DE",
    "sg:address":"Am Stubbenberg 1",
    "sg:city":"Appel",
    "sg:phone":"+49 4165/80361",
    "sg:postcode":"21279",
    "sg:province":"Niedersachsen",
    "wof:name":"Hansdietrich Scheruhn",
    "wof:placetype":"venue"
},
  "geometry": {"coordinates":[9.7442846298,53.3904037476],"type":"Point"}
}