{
  "type": "Feature",
  "properties": {
    "iso:country":"DE",
    "sg:address":"Telemannstr. 13",
    "sg:city":"Frankfurt",
    "sg:phone":"+49 69/97202597",
    "sg:postcode":"60323",
    "sg:province":"Hessen",
    "wof:name":"W. K\u00f6hler",
    "wof:placetype":"venue"
},
  "geometry": {"coordinates":[8.6694440842,50.1204833984],"type":"Point"}
}