{
  "type": "Feature",
  "properties": {
    "iso:country":"DE",
    "sg:address":"Hansestr. 10",
    "sg:city":"Bremen",
    "sg:phone":"+49 421/386080",
    "sg:postcode":"28217",
    "sg:province":"Bremen",
    "wof:name":"Bellmann_schloss U. Beschlag Handels Gmbh",
    "wof:placetype":"venue"
},
  "geometry": {"coordinates":[8.785729,53.089378],"type":"Point"}
}