{
  "type": "Feature",
  "properties": {
    "iso:country":"DE",
    "sg:address":"Londorfer Str. 23",
    "sg:city":"Allendorf",
    "sg:phone":"+49 6407/8668",
    "sg:postcode":"35469",
    "sg:province":"Hessen",
    "wof:name":"Manfred Platz",
    "wof:placetype":"venue"
},
  "geometry": {"coordinates":[8.8260478973,50.6776123047],"type":"Point"}
}