{
  "type": "Feature",
  "properties": {
    "iso:country":"DE",
    "sg:address":"Rheinstr. 73",
    "sg:city":"Neuwied",
    "sg:phone":"+49 2631/39120",
    "sg:postcode":"56564",
    "sg:province":"Rheinland-Pfalz",
    "wof:name":"Josef Happ & Partner Planungsgesellschaft Mbh",
    "wof:placetype":"venue"
},
  "geometry": {"coordinates":[7.460015,50.423672],"type":"Point"}
}