{
  "type": "Feature",
  "properties": {
    "iso:country":"DE",
    "sg:address":"Lehmbauweg 11",
    "sg:city":"Kirchlengern",
    "sg:phone":"+49 5223/83543",
    "sg:postcode":"32278",
    "sg:province":"Nordrhein-Westfalen",
    "wof:name":"Hans R\u00fchms",
    "wof:placetype":"venue"
},
  "geometry": {"coordinates":[8.631998,52.186069],"type":"Point"}
}