{
  "type": "Feature",
  "properties": {
    "iso:country":"DE",
    "sg:address":"99974",
    "sg:city":"M\u00fchlhausen",
    "sg:postcode":"99974",
    "sg:province":"Th\u00fcringen",
    "wof:name":"Raiffeisenbank M\u00fchlhausen-affing Eg",
    "wof:placetype":"venue"
},
  "geometry": {"coordinates":[10.45919,51.259289],"type":"Point"}
}