{
  "type": "Feature",
  "properties": {
    "iso:country":"DE",
    "sg:address":"Blumenstr. 56-1",
    "sg:city":"Magstadt",
    "sg:phone":"+49 7159/44765",
    "sg:postcode":"71106",
    "sg:province":"Baden-W\u00fcrttemberg",
    "wof:name":"Dudelsack",
    "wof:placetype":"venue"
},
  "geometry": {"coordinates":[8.9753484726,48.7454299927],"type":"Point"}
}