{
  "type": "Feature",
  "properties": {
    "iso:country":"DE",
    "sg:address":"Dorfstr. 14",
    "sg:city":"Ammerbuch",
    "sg:phone":"+49 7073/6418",
    "sg:postcode":"72119",
    "sg:province":"Baden-W\u00fcrttemberg",
    "wof:name":"Marianne Mildner Heilpraktikerin",
    "wof:placetype":"venue"
},
  "geometry": {"coordinates":[8.9629650116,48.5261077881],"type":"Point"}
}