{
  "type": "Feature",
  "properties": {
    "iso:country":"DE",
    "sg:address":"Schulzengrundstra\u00dfe 19",
    "sg:city":"Westerngrund",
    "sg:phone":"+49 160 1501144",
    "sg:postcode":"63825",
    "sg:province":"Bayern",
    "wof:name":"Prb - Jochen Bachmann",
    "wof:placetype":"venue"
},
  "geometry": {"coordinates":[9.246205,50.116947],"type":"Point"}
}