{
  "type": "Feature",
  "properties": {
    "iso:country":"DE",
    "sg:address":"In den Wald\u00e4ckern 20",
    "sg:city":"M\u00fchlacker",
    "sg:phone":"+49 7041/2582",
    "sg:postcode":"75417",
    "sg:province":"Baden-W\u00fcrttemberg",
    "wof:name":"Karl Gommel Gmbh - Zimmerei Treppenbau -",
    "wof:placetype":"venue"
},
  "geometry": {"coordinates":[8.875609,48.952496],"type":"Point"}
}