{
  "type": "Feature",
  "properties": {
    "iso:country":"DE",
    "sg:address":"Marktstr. 15a",
    "sg:city":"Leinfelden-Echterdingen",
    "sg:phone":"+49 711/751396",
    "sg:postcode":"70771",
    "sg:province":"Baden-W\u00fcrttemberg",
    "wof:name":"Gerhard Grau",
    "wof:placetype":"venue"
},
  "geometry": {"coordinates":[9.139732,48.697124],"type":"Point"}
}