{
  "type": "Feature",
  "properties": {
    "iso:country":"DE",
    "sg:address":"Finkenschlag 14",
    "sg:city":"F\u00fcrth",
    "sg:phone":"+49 911/739050",
    "sg:postcode":"90766",
    "sg:province":"Bayern",
    "wof:name":"Elise Neum\u00fcller",
    "wof:placetype":"venue"
},
  "geometry": {"coordinates":[10.972259,49.487885],"type":"Point"}
}