{
  "type": "Feature",
  "properties": {
    "iso:country":"DE",
    "sg:address":"Lindberghstr. 5",
    "sg:city":"Langenfeld",
    "sg:phone":"+49 2173/78486",
    "sg:postcode":"40764",
    "sg:province":"Nordrhein-Westfalen",
    "wof:name":"Peter Riechert Finanzberater",
    "wof:placetype":"venue"
},
  "geometry": {"coordinates":[6.9443368912,51.1110572815],"type":"Point"}
}