{
  "type": "Feature",
  "properties": {
    "iso:country":"DE",
    "sg:address":"Marktplatz 11",
    "sg:city":"Bad Buchau",
    "sg:postcode":"88422",
    "sg:province":"Baden-W\u00fcrttemberg",
    "wof:name":"Elektro V\u00f6tsch Gmbh",
    "wof:placetype":"venue"
},
  "geometry": {"coordinates":[9.610117,48.065964],"type":"Point"}
}