{
  "type": "Feature",
  "properties": {
    "iso:country":"DE",
    "sg:address":"Buchhornplatz 6",
    "sg:city":"Friedrichshafen",
    "sg:phone":"+49 7541/23884",
    "sg:postcode":"88045",
    "sg:province":"Baden-W\u00fcrttemberg",
    "wof:name":"Benetton",
    "wof:placetype":"venue"
},
  "geometry": {"coordinates":[9.481983,47.650963],"type":"Point"}
}