{
  "type": "Feature",
  "properties": {
    "iso:country":"DE",
    "sg:address":"Pariser Platz 32",
    "sg:city":"K\u00f6ln",
    "sg:phone":"+49 221/708365",
    "sg:postcode":"50765",
    "sg:province":"Nordrhein-Westfalen",
    "wof:name":"Ev. Pfarramt Neue Stadt",
    "wof:placetype":"venue"
},
  "geometry": {"coordinates":[6.8987388611,51.0226593018],"type":"Point"}
}