{
  "type": "Feature",
  "properties": {
    "iso:country":"DE",
    "sg:address":"Marktstr. 6",
    "sg:city":"Plochingen",
    "sg:phone":"+49 7153/27326",
    "sg:postcode":"73207",
    "sg:province":"Baden-W\u00fcrttemberg",
    "wof:name":"Druck & Service",
    "wof:placetype":"venue"
},
  "geometry": {"coordinates":[9.416124,48.710629],"type":"Point"}
}