{
  "type": "Feature",
  "properties": {
    "iso:country":"DE",
    "sg:address":"Hamburger Str 12",
    "sg:city":"Lauenburg",
    "sg:phone":"+49 4153/2406",
    "sg:postcode":"21481",
    "sg:province":"Schleswig-Holstein",
    "wof:name":"Druckerei Gebr. Borchers",
    "wof:placetype":"venue"
},
  "geometry": {"coordinates":[10.5528402328,53.3740119934],"type":"Point"}
}