{
  "type": "Feature",
  "properties": {
    "iso:country":"DE",
    "sg:address":"Am Kocherbach 25",
    "sg:city":"Wald-Michelbach",
    "sg:phone":"+49 6207/3150",
    "sg:postcode":"69483",
    "sg:province":"Hessen",
    "wof:name":"Katharina Kohl",
    "wof:placetype":"venue"
},
  "geometry": {"coordinates":[8.8334035873,49.599773407],"type":"Point"}
}