{
  "type": "Feature",
  "properties": {
    "iso:country":"DE",
    "sg:address":"Bl\u00fccherstr. 8",
    "sg:city":"Leipzig",
    "sg:phone":"+49 341/9012244",
    "sg:postcode":"04159",
    "sg:province":"Sachsen",
    "wof:name":"Wolfgang Gruhle",
    "wof:placetype":"venue"
},
  "geometry": {"coordinates":[12.3467187881,51.3684883118],"type":"Point"}
}