{
  "type": "Feature",
  "properties": {
    "iso:country":"DE",
    "sg:address":"Marktstr. 39",
    "sg:city":"Leutkirch",
    "sg:phone":"+49 7561/914239",
    "sg:postcode":"88299",
    "sg:province":"Baden-W\u00fcrttemberg",
    "wof:name":"Euro Imbi\u00df",
    "wof:placetype":"venue"
},
  "geometry": {"coordinates":[10.0236148834,47.827545166],"type":"Point"}
}