{
  "type": "Feature",
  "properties": {
    "iso:country":"DE",
    "sg:address":"Gro\u00dfer Graben 16",
    "sg:city":"Walsrode",
    "sg:phone":"+49 5161/910452",
    "sg:postcode":"29664",
    "sg:province":"Niedersachsen",
    "wof:name":"Heinrich D\u00fcck Innenarchitekt Und Architekt",
    "wof:placetype":"venue"
},
  "geometry": {"coordinates":[9.590595,52.861618],"type":"Point"}
}