{
  "type": "Feature",
  "properties": {
    "iso:country":"DE",
    "sg:address":"Br\u00fcckenort 11",
    "sg:city":"Bramsche",
    "sg:phone":"+49 5461/4405",
    "sg:postcode":"49565",
    "sg:province":"Niedersachsen",
    "wof:name":"Grondel-zoo Inh. Jarosch Von Biene",
    "wof:placetype":"venue"
},
  "geometry": {"coordinates":[7.98182,52.40686],"type":"Point"}
}