{
  "type": "Feature",
  "properties": {
    "iso:country":"DE",
    "sg:address":"Alleestr. 13",
    "sg:city":"Montabaur",
    "sg:phone":"+49 2602/180180",
    "sg:postcode":"56410",
    "sg:province":"Rheinland-Pfalz",
    "wof:name":"Niemann Und Niemann Rechtsanw\u00e4lte",
    "wof:placetype":"venue"
},
  "geometry": {"coordinates":[7.83233881,50.4382972717],"type":"Point"}
}