{
  "type": "Feature",
  "properties": {
    "iso:country":"DE",
    "sg:address":"L\u00fcbbertorwall 1",
    "sg:city":"Herford",
    "sg:phone":"+49 5221/15163",
    "sg:postcode":"32052",
    "sg:province":"Nordrhein-Westfalen",
    "wof:name":"Helga Hutmacher",
    "wof:placetype":"venue"
},
  "geometry": {"coordinates":[8.676111,52.118359],"type":"Point"}
}