{
  "type": "Feature",
  "properties": {
    "iso:country":"DE",
    "sg:address":"Futterstr. 17",
    "sg:city":"Saarbr\u00fccken",
    "sg:phone":"+49 681/31853",
    "sg:postcode":"66111",
    "sg:province":"Saarland",
    "wof:name":"Anatolij Krawtschenko Ballettschule",
    "wof:placetype":"venue"
},
  "geometry": {"coordinates":[6.9946317673,49.2364768982],"type":"Point"}
}