{
  "type": "Feature",
  "properties": {
    "iso:country":"DE",
    "sg:address":"Aiblinger Str. 50",
    "sg:city":"Bad Feilnbach",
    "sg:phone":"+49 8066/368",
    "sg:postcode":"83075",
    "sg:province":"Bayern",
    "wof:name":"Kath. Pfarramt St. Micahel",
    "wof:placetype":"venue"
},
  "geometry": {"coordinates":[12.047454834,47.7615089417],"type":"Point"}
}