{
  "type": "Feature",
  "properties": {
    "iso:country":"DE",
    "sg:address":"Unterwestegg 25",
    "sg:city":"Riezlern",
    "sg:phone":"+49 8329/5946",
    "sg:postcode":"87567",
    "sg:province":"Bayern",
    "wof:name":"Kleinwalsertal Online",
    "wof:placetype":"venue"
},
  "geometry": {"coordinates":[-106.0361480713,35.950378418],"type":"Point"}
}