{
  "type": "Feature",
  "properties": {
    "iso:country":"DE",
    "sg:address":"Wahnfriedstr. 48",
    "sg:city":"Berlin",
    "sg:phone":"+49 30/4014461",
    "sg:postcode":"13465",
    "sg:province":"Berlin",
    "wof:name":"S. Kupke",
    "wof:placetype":"venue"
},
  "geometry": {"coordinates":[13.28279,52.638428],"type":"Point"}
}