{
  "type": "Feature",
  "properties": {
    "iso:country":"DE",
    "sg:address":"Liesetal 17",
    "sg:city":"Hallenberg",
    "sg:phone":"+49 2984/8136",
    "sg:postcode":"59969",
    "sg:province":"Nordrhein-Westfalen",
    "wof:name":"H. -w. U. A. Gewehr",
    "wof:placetype":"venue"
},
  "geometry": {"coordinates":[8.6090803146,51.1414642334],"type":"Point"}
}