{
  "type": "Feature",
  "properties": {
    "iso:country":"DE",
    "sg:address":"Angerm\u00fcnder Str.",
    "sg:city":"Eberswalde",
    "sg:phone":"+49 3334/25860",
    "sg:postcode":"16227",
    "sg:province":"Brandenburg",
    "wof:name":"M\u00e4rkischer Verkehrsbau Gmbh",
    "wof:placetype":"venue"
},
  "geometry": {"coordinates":[13.736515,52.843025],"type":"Point"}
}