{
  "type": "Feature",
  "properties": {
    "iso:country":"DE",
    "sg:address":"Olympiastr. 1",
    "sg:city":"Starnberg",
    "sg:phone":"+49 8151/14471",
    "sg:postcode":"82319",
    "sg:province":"Bayern",
    "wof:name":"Pentenrieder Gmbh & Co. Grundst\u00fccks Kg",
    "wof:placetype":"venue"
},
  "geometry": {"coordinates":[11.4240703583,48.0281410217],"type":"Point"}
}