{
  "type": "Feature",
  "properties": {
    "iso:country":"DE",
    "sg:address":"Mozartstr. 15",
    "sg:city":"M\u00fcnchen",
    "sg:phone":"+49 89/5438466",
    "sg:postcode":"80336",
    "sg:province":"Bayern",
    "wof:name":"Franz-xaver Wittl Rechtsanwalt",
    "wof:placetype":"venue"
},
  "geometry": {"coordinates":[11.5553779602,48.1298904419],"type":"Point"}
}