{
  "type": "Feature",
  "properties": {
    "iso:country":"DE",
    "sg:address":"Turmstr. 38",
    "sg:city":"Neu-Ulm",
    "sg:phone":"+49 731/722789",
    "sg:postcode":"89231",
    "sg:province":"Bayern",
    "wof:name":"Nachtschicht",
    "wof:placetype":"venue"
},
  "geometry": {"coordinates":[10.0025196075,48.3904914856],"type":"Point"}
}