{
  "type": "Feature",
  "properties": {
    "iso:country":"DE",
    "sg:address":"Rother Str. 18",
    "sg:city":"Allersberg",
    "sg:phone":"+49 9176/7179",
    "sg:postcode":"90584",
    "sg:province":"Bayern",
    "wof:name":"R. Kienlein Gmbh",
    "wof:placetype":"venue"
},
  "geometry": {"coordinates":[11.2281904221,49.2507324219],"type":"Point"}
}