{
  "type": "Feature",
  "properties": {
    "iso:country":"DE",
    "sg:address":"Blumenstr. 58",
    "sg:city":"Esslingen",
    "sg:phone":"+49 711/3166977",
    "sg:postcode":"73728",
    "sg:province":"Baden-W\u00fcrttemberg",
    "wof:name":"Yves Gschwind",
    "wof:placetype":"venue"
},
  "geometry": {"coordinates":[9.3170833588,48.7392807007],"type":"Point"}
}