{
  "type": "Feature",
  "properties": {
    "iso:country":"DE",
    "sg:address":"Am Alten Graben 6",
    "sg:city":"Oppach",
    "sg:phone":"+49 35872/32761",
    "sg:postcode":"02736",
    "sg:province":"Sachsen",
    "wof:name":"Gerhard Helm",
    "wof:placetype":"venue"
},
  "geometry": {"coordinates":[14.49856,51.05621],"type":"Point"}
}