{
  "type": "Feature",
  "properties": {
    "iso:country":"DE",
    "sg:address":"John-F.-Kennedy-Str. 110",
    "sg:city":"Zweibr\u00fccken",
    "sg:phone":"+49 6332/44471",
    "sg:postcode":"66482",
    "sg:province":"Rheinland-Pfalz",
    "wof:name":"Volker Und Patrick Burkhardt",
    "wof:placetype":"venue"
},
  "geometry": {"coordinates":[7.4031839371,49.2563858032],"type":"Point"}
}