{
  "type": "Feature",
  "properties": {
    "iso:country":"DE",
    "sg:address":"Hohlweg 6",
    "sg:city":"Versmold",
    "sg:phone":"+49 5423/2302",
    "sg:postcode":"33775",
    "sg:province":"Nordrhein-Westfalen",
    "wof:name":"Friedrich Beckmann",
    "wof:placetype":"venue"
},
  "geometry": {"coordinates":[8.1604766846,52.0416412354],"type":"Point"}
}