{
  "type": "Feature",
  "properties": {
    "iso:country":"DE",
    "sg:address":"Hullmanns Damm 15",
    "sg:city":"Lengerich",
    "sg:phone":"+49 5481/94540",
    "sg:postcode":"49525",
    "sg:province":"Nordrhein-Westfalen",
    "wof:name":"B. Lewedag Beteiligungs Gmbh",
    "wof:placetype":"venue"
},
  "geometry": {"coordinates":[7.861256,52.176777],"type":"Point"}
}