{
  "type": "Feature",
  "properties": {
    "iso:country":"DE",
    "sg:address":"Nagoldstr. 51",
    "sg:city":"Stuttgart",
    "sg:phone":"+49 711/59094",
    "sg:postcode":"70376",
    "sg:province":"Baden-W\u00fcrttemberg",
    "wof:name":"Architekten Und Stadtplaner Schauer Und Wiorkowski",
    "wof:placetype":"venue"
},
  "geometry": {"coordinates":[9.218827,48.820423],"type":"Point"}
}