{
  "type": "Feature",
  "properties": {
    "iso:country":"DE",
    "sg:address":"Alfred-Delp-Weg 8",
    "sg:city":"Dietzenbach",
    "sg:phone":"+49 6074/44973",
    "sg:postcode":"63128",
    "sg:province":"Hessen",
    "wof:name":"Renate H\u00f6fner-opl",
    "wof:placetype":"venue"
},
  "geometry": {"coordinates":[8.785312,50.029015],"type":"Point"}
}