{
  "type": "Feature",
  "properties": {
    "iso:country":"DE",
    "sg:address":"Leipziger Str. 117",
    "sg:city":"Grimma",
    "sg:phone":"+49 3437/910357",
    "sg:postcode":"04668",
    "sg:province":"Sachsen",
    "wof:name":"Muldental - Assekuranz Versicherungsmakler Gmbh",
    "wof:placetype":"venue"
},
  "geometry": {"coordinates":[12.7024106979,51.2316398621],"type":"Point"}
}