{
  "type": "Feature",
  "properties": {
    "iso:country":"DE",
    "sg:address":"Wilhelm-St\u00f6ppler-Platz 3",
    "sg:city":"Koblenz",
    "sg:phone":"+49 261/806000",
    "sg:postcode":"56070",
    "sg:province":"Rheinland-Pfalz",
    "wof:name":"Satz & Grafik-studio Alex Gmbh",
    "wof:placetype":"venue"
},
  "geometry": {"coordinates":[7.5938391685,50.3673057556],"type":"Point"}
}