{
  "type": "Feature",
  "properties": {
    "iso:country":"DE",
    "sg:address":"Pforzheimer Str. 31",
    "sg:city":"Ettlingen",
    "sg:phone":"+49 7243/54950",
    "sg:postcode":"76275",
    "sg:province":"Baden-W\u00fcrttemberg",
    "wof:name":"Diakonie Im Landkreis Karlsruhe Ggmbh",
    "wof:placetype":"venue"
},
  "geometry": {"coordinates":[8.4124755859,48.9418754578],"type":"Point"}
}