{
  "type": "Feature",
  "properties": {
    "iso:country":"DE",
    "sg:address":"Weinbergstr. 68",
    "sg:city":"Oberursel",
    "sg:phone":"+49 6172/33161",
    "sg:postcode":"61440",
    "sg:province":"Hessen",
    "wof:name":"K.-j. Feuer",
    "wof:placetype":"venue"
},
  "geometry": {"coordinates":[8.5830430984,50.2271957397],"type":"Point"}
}