{
  "type": "Feature",
  "properties": {
    "iso:country":"DE",
    "sg:address":"Illerzeller Str. 141",
    "sg:city":"V\u00f6hringen",
    "sg:phone":"+49 7306/32313",
    "sg:postcode":"89269",
    "sg:province":"Bayern",
    "wof:name":"R. Und B. G\u00f6rmiller",
    "wof:placetype":"venue"
},
  "geometry": {"coordinates":[10.0693597794,48.2858467102],"type":"Point"}
}