{
  "type": "Feature",
  "properties": {
    "iso:country":"DE",
    "sg:address":"Altmarkt 23",
    "sg:city":"Bischofswerda",
    "sg:phone":"+49 3594/716230",
    "sg:postcode":"01877",
    "sg:province":"Sachsen",
    "wof:name":"Bierstube",
    "wof:placetype":"venue"
},
  "geometry": {"coordinates":[14.1795625687,51.1273155212],"type":"Point"}
}