{
  "type": "Feature",
  "properties": {
    "iso:country":"DE",
    "sg:address":"Klosterstr. 81",
    "sg:city":"D\u00fcsseldorf",
    "sg:phone":"+49 211/1640842",
    "sg:postcode":"40211",
    "sg:province":"Nordrhein-Westfalen",
    "wof:name":"Asko Holding Gmbh",
    "wof:placetype":"venue"
},
  "geometry": {"coordinates":[6.792519,51.223869],"type":"Point"}
}