{
  "type": "Feature",
  "properties": {
    "iso:country":"DE",
    "sg:address":"Sandstr. 112",
    "sg:city":"Siegen",
    "sg:phone":"+49 271/51212",
    "sg:postcode":"57072",
    "sg:province":"Nordrhein-Westfalen",
    "wof:name":"K. Schnutz",
    "wof:placetype":"venue"
},
  "geometry": {"coordinates":[8.0262012482,50.8800773621],"type":"Point"}
}