{
  "type": "Feature",
  "properties": {
    "iso:country":"DE",
    "sg:address":"Sch\u00f6nwohlder Str. 2",
    "sg:city":"Mielkendorf",
    "sg:postcode":"24247",
    "sg:province":"Schleswig-Holstein",
    "wof:name":"H.g. Beratungsgesellschaft Mbh",
    "wof:placetype":"venue"
},
  "geometry": {"coordinates":[10.014491,54.294224],"type":"Point"}
}