{
  "type": "Feature",
  "properties": {
    "iso:country":"DE",
    "sg:address":"Radolfzeller Str. 1",
    "sg:city":"Allensbach",
    "sg:postcode":"78476",
    "sg:province":"Baden-W\u00fcrttemberg",
    "wof:name":"Gemeinde Und Pfarrb\u00fccherei",
    "wof:placetype":"venue"
},
  "geometry": {"coordinates":[9.0646,47.716831],"type":"Point"}
}