{
  "type": "Feature",
  "properties": {
    "iso:country":"DE",
    "sg:address":"Schagern 26",
    "sg:city":"Horstmar",
    "sg:phone":"+49 2558/93810",
    "sg:postcode":"48612",
    "sg:province":"Nordrhein-Westfalen",
    "wof:name":"Terkuhlen-fensterbau Gmbh",
    "wof:placetype":"venue"
},
  "geometry": {"coordinates":[7.27301,52.058632],"type":"Point"}
}