{
  "type": "Feature",
  "properties": {
    "iso:country":"DE",
    "sg:address":"Leipziger Str. 77",
    "sg:city":"Zittau",
    "sg:phone":"+49 3583/706360",
    "sg:postcode":"02763",
    "sg:province":"Sachsen",
    "wof:name":"Marathon-athen",
    "wof:placetype":"venue"
},
  "geometry": {"coordinates":[14.8146705627,50.9029541016],"type":"Point"}
}