{
  "type": "Feature",
  "properties": {
    "iso:country":"DE",
    "sg:address":"Kirchstr. 9",
    "sg:city":"Bad Pyrmont",
    "sg:phone":"+49 5281/8162",
    "sg:postcode":"31812",
    "sg:province":"Niedersachsen",
    "wof:name":"Residenz",
    "wof:placetype":"venue"
},
  "geometry": {"coordinates":[9.254427,51.985775],"type":"Point"}
}