{
  "type": "Feature",
  "properties": {
    "iso:country":"DE",
    "sg:address":"Eschbacher Weg 19",
    "sg:city":"Esslingen",
    "sg:phone":"+49 711/3459600",
    "sg:postcode":"73734",
    "sg:province":"Baden-W\u00fcrttemberg",
    "wof:name":"Druck & Media Gmbh",
    "wof:placetype":"venue"
},
  "geometry": {"coordinates":[9.3286895752,48.7132759094],"type":"Point"}
}