{
  "type": "Feature",
  "properties": {
    "iso:country":"DE",
    "sg:address":"Gl\u00fcck-Auf-Str. 13",
    "sg:city":"Wennigsen",
    "sg:phone":"+49 5109/6539",
    "sg:postcode":"30974",
    "sg:province":"Niedersachsen",
    "wof:name":"Hilchenbach Kg Werbegeschenk-handlung",
    "wof:placetype":"venue"
},
  "geometry": {"coordinates":[9.612121582,52.2493782043],"type":"Point"}
}