{
  "type": "Feature",
  "properties": {
    "iso:country":"DE",
    "sg:address":"Justus-von-Liebig-Str 5",
    "sg:city":"Sulzbach",
    "sg:phone":"+49 6897/5070",
    "sg:postcode":"66280",
    "sg:province":"Saarland",
    "wof:name":"Decoma Germany Gmbh",
    "wof:placetype":"venue"
},
  "geometry": {"coordinates":[7.081187,49.291439],"type":"Point"}
}