{
  "type": "Feature",
  "properties": {
    "iso:country":"DE",
    "sg:address":"Uferstr. 23",
    "sg:city":"Eisenach",
    "sg:phone":"+49 3691/75428",
    "sg:postcode":"99817",
    "sg:province":"Th\u00fcringen",
    "wof:name":"Automot Gmbh Bleicherode",
    "wof:placetype":"venue"
},
  "geometry": {"coordinates":[10.328729,50.977734],"type":"Point"}
}