{
  "type": "Feature",
  "properties": {
    "iso:country":"DE",
    "sg:address":"Gro\u00dfe Kienheide 11",
    "sg:city":"Dessau",
    "sg:phone":"+49 340/616443",
    "sg:postcode":"06846",
    "sg:province":"Sachsen-Anhalt",
    "wof:name":"Ingeburg Schneider",
    "wof:placetype":"venue"
},
  "geometry": {"coordinates":[12.21261,51.846825],"type":"Point"}
}