{
  "type": "Feature",
  "properties": {
    "iso:country":"DE",
    "sg:address":"Iversheimer Str. 27",
    "sg:city":"Mechernich",
    "sg:phone":"+49 2256/7733",
    "sg:postcode":"53894",
    "sg:province":"Nordrhein-Westfalen",
    "wof:name":"Peter Bauchwitz Komponist",
    "wof:placetype":"venue"
},
  "geometry": {"coordinates":[6.7414259911,50.5958557129],"type":"Point"}
}