{
  "type": "Feature",
  "properties": {
    "iso:country":"DE",
    "sg:address":"Euskirchener Str. 41",
    "sg:city":"Nettersheim",
    "sg:phone":"+49 2440/203",
    "sg:postcode":"53947",
    "sg:province":"Nordrhein-Westfalen",
    "wof:name":"Alois Jaax",
    "wof:placetype":"venue"
},
  "geometry": {"coordinates":[6.7108988762,50.4727478027],"type":"Point"}
}