{
  "type": "Feature",
  "properties": {
    "iso:country":"DE",
    "sg:address":"Karl-Hermann-Flach-Str. 32",
    "sg:city":"Oberursel",
    "sg:phone":"+49 6171/63790",
    "sg:postcode":"61440",
    "sg:province":"Hessen",
    "wof:name":"Rola Hard- Und Softwareberatungs Gmbh",
    "wof:placetype":"venue"
},
  "geometry": {"coordinates":[8.5954761505,50.2042388916],"type":"Point"}
}