{
  "type": "Feature",
  "properties": {
    "iso:country":"DE",
    "sg:address":"Sch\u00f6nebergstr. 8",
    "sg:city":"Bellenberg",
    "sg:phone":"+49 7306/5421",
    "sg:postcode":"89287",
    "sg:province":"Bayern",
    "wof:name":"Alois Vitzthum",
    "wof:placetype":"venue"
},
  "geometry": {"coordinates":[10.0865240097,48.2565574646],"type":"Point"}
}