{
  "type": "Feature",
  "properties": {
    "iso:country":"DE",
    "sg:address":"Am Altersbach 14",
    "sg:city":"Breitenberg",
    "sg:phone":"+49 8584/872",
    "sg:postcode":"94139",
    "sg:province":"Bayern",
    "wof:name":"R. Kremsreiter",
    "wof:placetype":"venue"
},
  "geometry": {"coordinates":[13.7497901917,48.6923484802],"type":"Point"}
}