{
  "type": "Feature",
  "properties": {
    "iso:country":"DE",
    "sg:address":"Maximilianstr. 43",
    "sg:city":"Bayreuth",
    "sg:phone":"+49 921/761894",
    "sg:postcode":"95444",
    "sg:province":"Bayern",
    "wof:name":"K. M\u00fcller",
    "wof:placetype":"venue"
},
  "geometry": {"coordinates":[11.5743284225,49.9444084167],"type":"Point"}
}