{
  "type": "Feature",
  "properties": {
    "iso:country":"DE",
    "sg:address":"Kehn 35",
    "sg:city":"T\u00f6nisvorst",
    "sg:phone":"+49 2156/8521",
    "sg:postcode":"47918",
    "sg:province":"Nordrhein-Westfalen",
    "wof:name":"Fotofix Schnell-automaten Gmbh",
    "wof:placetype":"venue"
},
  "geometry": {"coordinates":[6.4551720619,51.3075523376],"type":"Point"}
}