{
  "type": "Feature",
  "properties": {
    "iso:country":"DE",
    "sg:address":"Kollbach",
    "sg:city":"Gangkofen",
    "sg:phone":"+49 8735/250",
    "sg:postcode":"84140",
    "sg:province":"Bayern",
    "wof:name":"D. Und M. Klinke",
    "wof:placetype":"venue"
},
  "geometry": {"coordinates":[12.5454416275,48.4284133911],"type":"Point"}
}