{
  "type": "Feature",
  "properties": {
    "iso:country":"DE",
    "sg:address":"Liebermannstr. 14",
    "sg:city":"Heilbad Heiligenstadt",
    "sg:phone":"+49 3606/605959",
    "sg:postcode":"37308",
    "sg:province":"Th\u00fcringen",
    "wof:name":"W. Bl\u00f6ck",
    "wof:placetype":"venue"
},
  "geometry": {"coordinates":[10.1352396011,51.3818054199],"type":"Point"}
}