{
  "type": "Feature",
  "properties": {
    "iso:country":"DE",
    "sg:address":"Alte Landstr. 1",
    "sg:city":"Idstedt",
    "sg:postcode":"24879",
    "sg:province":"Schleswig-Holstein",
    "wof:name":"Hansen Entsorgungs Gmbh",
    "wof:placetype":"venue"
},
  "geometry": {"coordinates":[9.4955739975,54.5750541687],"type":"Point"}
}