{
  "type": "Feature",
  "properties": {
    "iso:country":"DE",
    "sg:address":"Schillerstr. 116",
    "sg:city":"Marl",
    "sg:phone":"+49 2365/501606",
    "sg:postcode":"45768",
    "sg:province":"Nordrhein-Westfalen",
    "wof:name":"Jens-peter Schmidt Rechtsanwalt",
    "wof:placetype":"venue"
},
  "geometry": {"coordinates":[7.0850958824,51.6564331055],"type":"Point"}
}