{
  "type": "Feature",
  "properties": {
    "iso:country":"DE",
    "sg:address":"Albert-Fritz-Str. 34",
    "sg:city":"Heidelberg",
    "sg:phone":"+49 6221/783280",
    "sg:postcode":"69124",
    "sg:province":"Baden-W\u00fcrttemberg",
    "wof:name":"Claus Bung Gmbh",
    "wof:placetype":"venue"
},
  "geometry": {"coordinates":[8.6680030823,49.3826293945],"type":"Point"}
}