{
  "type": "Feature",
  "properties": {
    "iso:country":"DE",
    "sg:address":"Friedrichstr. 15a",
    "sg:city":"Herbolzheim",
    "sg:phone":"+49 7643/8885",
    "sg:postcode":"79336",
    "sg:province":"Baden-W\u00fcrttemberg",
    "wof:name":"Guths Tortenkutsche",
    "wof:placetype":"venue"
},
  "geometry": {"coordinates":[7.773959,48.221668],"type":"Point"}
}