{
  "type": "Feature",
  "properties": {
    "iso:country":"DE",
    "sg:address":"M\u00fclgaustr. 259",
    "sg:city":"M\u00f6nchengladbach",
    "sg:phone":"+49 2166/120278",
    "sg:postcode":"41199",
    "sg:province":"Nordrhein-Westfalen",
    "wof:name":"Black And White",
    "wof:placetype":"venue"
},
  "geometry": {"coordinates":[6.4565148354,51.147480011],"type":"Point"}
}