{
  "type": "Feature",
  "properties": {
    "iso:country":"DE",
    "sg:address":"Trierer Str. 159",
    "sg:city":"N\u00fcrnberg",
    "sg:phone":"+49 911/487414",
    "sg:postcode":"90469",
    "sg:province":"Bayern",
    "wof:name":"Agip Deutschland Ag",
    "wof:placetype":"venue"
},
  "geometry": {"coordinates":[11.1095542908,49.4069976807],"type":"Point"}
}