{
  "type": "Feature",
  "properties": {
    "iso:country":"DE",
    "sg:address":"D\u00fcsseldorfer Str. 20",
    "sg:city":"D\u00fcsseldorf",
    "sg:phone":"+49 211/578287",
    "sg:postcode":"40545",
    "sg:province":"Nordrhein-Westfalen",
    "wof:name":"Henry R. Kubick Gmbh",
    "wof:placetype":"venue"
},
  "geometry": {"coordinates":[6.7567801476,51.2272529602],"type":"Point"}
}