{
  "type": "Feature",
  "properties": {
    "iso:country":"DE",
    "sg:address":"Im Loh 10",
    "sg:city":"P\u00f6\u00dfneck",
    "sg:phone":"+49 3647/421889",
    "sg:postcode":"07381",
    "sg:province":"Th\u00fcringen",
    "wof:name":"Horst Grimm",
    "wof:placetype":"venue"
},
  "geometry": {"coordinates":[11.5922994614,50.7010917664],"type":"Point"}
}