{
  "type": "Feature",
  "properties": {
    "iso:country":"DE",
    "sg:address":"Raiffeisenstr. 2",
    "sg:city":"Segnitz",
    "sg:phone":"+49 9332/1313",
    "sg:postcode":"97340",
    "sg:province":"Bayern",
    "wof:name":"Volksbank Raiffeisenbank Kitzingen, Eg",
    "wof:placetype":"venue"
},
  "geometry": {"coordinates":[10.143004,49.674763],"type":"Point"}
}