{
  "type": "Feature",
  "properties": {
    "iso:country":"DE",
    "sg:address":"Hohweg 4",
    "sg:city":"Bremen",
    "sg:phone":"+49 421/383326",
    "sg:postcode":"28219",
    "sg:province":"Bremen",
    "wof:name":"Brokop-stahlbau Ohg",
    "wof:placetype":"venue"
},
  "geometry": {"coordinates":[8.795143,53.105564],"type":"Point"}
}