{
  "type": "Feature",
  "properties": {
    "iso:country":"DE",
    "sg:address":"Friedenstr. 20",
    "sg:city":"Westerheim",
    "sg:phone":"+49 7333/4924",
    "sg:postcode":"72589",
    "sg:province":"Baden-W\u00fcrttemberg",
    "wof:name":"H. Kneer",
    "wof:placetype":"venue"
},
  "geometry": {"coordinates":[9.6277084351,48.5164527893],"type":"Point"}
}