{
  "type": "Feature",
  "properties": {
    "iso:country":"DE",
    "sg:address":"Vorderstr. 121",
    "sg:city":"Hollern-Twielenfleth",
    "sg:phone":"+49 4141/7135",
    "sg:postcode":"21723",
    "sg:province":"Niedersachsen",
    "wof:name":"Peter Cordes",
    "wof:placetype":"venue"
},
  "geometry": {"coordinates":[9.538099,53.598766],"type":"Point"}
}