{
  "type": "Feature",
  "properties": {
    "iso:country":"DE",
    "sg:address":"Merkenicher Str. 173",
    "sg:city":"K\u00f6ln",
    "sg:phone":"+49 221/7121080",
    "sg:postcode":"50735",
    "sg:province":"Nordrhein-Westfalen",
    "wof:name":"Auto Klein Kfz-handel & Reparatur Gmbh",
    "wof:placetype":"venue"
},
  "geometry": {"coordinates":[6.9601,50.996441],"type":"Point"}
}