{
  "type": "Feature",
  "properties": {
    "iso:country":"DE",
    "sg:address":"Backhausstr. 8",
    "sg:city":"Schwabenheim",
    "sg:phone":"+49 6130/1350",
    "sg:postcode":"55270",
    "sg:province":"Rheinland-Pfalz",
    "wof:name":"Herbert Martin Gmbh",
    "wof:placetype":"venue"
},
  "geometry": {"coordinates":[8.0958042145,49.931552887],"type":"Point"}
}