{
  "type": "Feature",
  "properties": {
    "iso:country":"DE",
    "sg:address":"Gr\u00fcnenthal 26",
    "sg:city":"Aachen",
    "sg:postcode":"52072",
    "sg:province":"Nordrhein-Westfalen",
    "wof:name":"Scient X Handelsges. Mbh",
    "wof:placetype":"venue"
},
  "geometry": {"coordinates":[6.050827,50.811317],"type":"Point"}
}