{
  "type": "Feature",
  "properties": {
    "iso:country":"DE",
    "sg:address":"Mommsenstr. 47",
    "sg:city":"Berlin",
    "sg:phone":"+49 30/3279330",
    "sg:postcode":"10629",
    "sg:province":"Berlin",
    "wof:name":"Hayn & Willemeit Gbr",
    "wof:placetype":"venue"
},
  "geometry": {"coordinates":[13.309134,52.503384],"type":"Point"}
}