{
  "type": "Feature",
  "properties": {
    "iso:country":"DE",
    "sg:address":"Landsberger Allee 399",
    "sg:city":"Berlin",
    "sg:postcode":"12681",
    "sg:province":"Berlin",
    "wof:name":"Service Zentrale Sz Gmbh",
    "wof:placetype":"venue"
},
  "geometry": {"coordinates":[13.536041,52.539589],"type":"Point"}
}