{
  "type": "Feature",
  "properties": {
    "iso:country":"DE",
    "sg:address":"Berliner Ring 16",
    "sg:city":"Hohenwestedt",
    "sg:phone":"+49 4871/1248",
    "sg:postcode":"24594",
    "sg:province":"Schleswig-Holstein",
    "wof:name":"Gretel Weber Und Fritz Wisch",
    "wof:placetype":"venue"
},
  "geometry": {"coordinates":[9.666686,54.097507],"type":"Point"}
}