{
  "type": "Feature",
  "properties": {
    "iso:country":"DE",
    "sg:address":"Brunnenstr. 14",
    "sg:city":"Ernst",
    "sg:phone":"+49 2671/3031",
    "sg:postcode":"56814",
    "sg:province":"Rheinland-Pfalz",
    "wof:name":"Paul Michels",
    "wof:placetype":"venue"
},
  "geometry": {"coordinates":[7.229205,50.143394],"type":"Point"}
}