{
  "type": "Feature",
  "properties": {
    "iso:country":"DE",
    "sg:address":"K\u00e4ferbach 8",
    "sg:city":"Ansbach",
    "sg:phone":"+49 9825/5455",
    "sg:postcode":"91522",
    "sg:province":"Bayern",
    "wof:name":"Gerhard Stumpf",
    "wof:placetype":"venue"
},
  "geometry": {"coordinates":[10.48774,49.272461],"type":"Point"}
}