{
  "type": "Feature",
  "properties": {
    "iso:country":"DE",
    "sg:address":"Rothenburger Str. 16",
    "sg:city":"Feuchtwangen",
    "sg:phone":"+49 9852/1586",
    "sg:postcode":"91555",
    "sg:province":"Bayern",
    "wof:name":"Erna Hezel Architekt",
    "wof:placetype":"venue"
},
  "geometry": {"coordinates":[10.329126,49.170551],"type":"Point"}
}