{
  "type": "Feature",
  "properties": {
    "iso:country":"DE",
    "sg:address":"Auf dem G\u00fcterbahnhof Hermsdorf",
    "sg:city":"Berlin",
    "sg:phone":"+49 30/40541566",
    "sg:postcode":"13467",
    "sg:province":"Berlin",
    "wof:name":"Willkommen Beim Nordberliner Brunnenversand",
    "wof:placetype":"venue"
},
  "geometry": {"coordinates":[13.317525,52.614906],"type":"Point"}
}