{
  "type": "Feature",
  "properties": {
    "iso:country":"DE",
    "sg:address":"Robert-Schuman-Str.",
    "sg:city":"Bergisch Gladbach",
    "sg:postcode":"51469",
    "sg:province":"Nordrhein-Westfalen",
    "wof:name":"Hit",
    "wof:placetype":"venue"
},
  "geometry": {"coordinates":[7.1238050461,50.9759597778],"type":"Point"}
}