{
  "type": "Feature",
  "properties": {
    "iso:country":"DE",
    "sg:address":"Blumenstr. 26",
    "sg:city":"Hirschau",
    "sg:phone":"+49 9622/2749",
    "sg:postcode":"92242",
    "sg:province":"Bayern",
    "wof:name":"Ida Knietsch-hammer Hebamme",
    "wof:placetype":"venue"
},
  "geometry": {"coordinates":[11.943157,49.549999],"type":"Point"}
}