{
  "type": "Feature",
  "properties": {
    "iso:country":"DE",
    "sg:address":"Raiffeisenstr. 12 a",
    "sg:city":"Saaldorf-Surheim",
    "sg:phone":"+49 8654/62417",
    "sg:postcode":"83416",
    "sg:province":"Bayern",
    "wof:name":"Herbert Heinrich Wohnbau Und Immobilien Gmbh",
    "wof:placetype":"venue"
},
  "geometry": {"coordinates":[12.93123,47.869984],"type":"Point"}
}