{
  "type": "Feature",
  "properties": {
    "iso:country":"DE",
    "sg:address":"Sch\u00f6nebecker Str. 48",
    "sg:city":"Wuppertal",
    "sg:phone":"+49 202/87296",
    "sg:postcode":"42283",
    "sg:province":"Nordrhein-Westfalen",
    "wof:name":"Werner Schmoll Architekt",
    "wof:placetype":"venue"
},
  "geometry": {"coordinates":[7.179028,51.273045],"type":"Point"}
}