{
  "type": "Feature",
  "properties": {
    "iso:country":"DE",
    "sg:address":"Talstr. 21",
    "sg:city":"Solingen",
    "sg:phone":"+49 212/74518",
    "sg:postcode":"42697",
    "sg:province":"Nordrhein-Westfalen",
    "wof:name":"Karl Kaspar Gmbh",
    "wof:placetype":"venue"
},
  "geometry": {"coordinates":[7.001253,51.159702],"type":"Point"}
}