{
  "type": "Feature",
  "properties": {
    "iso:country":"DE",
    "sg:address":"T\u00f6rringstr. 21",
    "sg:city":"Fridolfing",
    "sg:postcode":"83413",
    "sg:province":"Bayern",
    "wof:name":"Iht Systemtechnik Gmbh",
    "wof:placetype":"venue"
},
  "geometry": {"coordinates":[12.8174915314,47.9990501404],"type":"Point"}
}