{
  "type": "Feature",
  "properties": {
    "iso:country":"DE",
    "sg:address":"Bleichstra\u00dfe 34",
    "sg:city":"Wiesbaden",
    "sg:phone":"+49 611/301831",
    "sg:postcode":"65183",
    "sg:province":"Hessen",
    "wof:name":"Krieger Technische Hausger\u00e4te",
    "wof:placetype":"venue"
},
  "geometry": {"coordinates":[8.2318763733,50.080581665],"type":"Point"}
}