{
  "type": "Feature",
  "properties": {
    "iso:country":"DE",
    "sg:address":"Justus-Liebig-Str. 6/8",
    "sg:city":"Kaarst",
    "sg:phone":"+49 2131/757400",
    "sg:postcode":"41564",
    "sg:province":"Nordrhein-Westfalen",
    "wof:name":"Rudolf Nieberding Gmbh",
    "wof:placetype":"venue"
},
  "geometry": {"coordinates":[6.614002,51.196766],"type":"Point"}
}