{
  "type": "Feature",
  "properties": {
    "iso:country":"DE",
    "sg:address":"Brucknerstr. 11",
    "sg:city":"M\u00fcnchen",
    "sg:phone":"+49 89/472851",
    "sg:postcode":"81677",
    "sg:province":"Bayern",
    "wof:name":"Herbert Poinvogel Elektroinstallation",
    "wof:placetype":"venue"
},
  "geometry": {"coordinates":[11.611887,48.139557],"type":"Point"}
}