{
  "type": "Feature",
  "properties": {
    "iso:country":"DE",
    "sg:address":"Gro\u00dfflecken 29",
    "sg:city":"Neum\u00fcnster",
    "sg:phone":"+49 4321/44064",
    "sg:postcode":"24534",
    "sg:province":"Schleswig-Holstein",
    "wof:name":"Auch & Kneidl",
    "wof:placetype":"venue"
},
  "geometry": {"coordinates":[9.9866456985,54.0721168518],"type":"Point"}
}