{
  "type": "Feature",
  "properties": {
    "iso:country":"DE",
    "sg:address":"Dr.-Kessel-Str. 24",
    "sg:city":"Ratingen",
    "sg:phone":"+49 2102/82454",
    "sg:postcode":"40878",
    "sg:province":"Nordrhein-Westfalen",
    "wof:name":"Dr. K\u00f6nig",
    "wof:placetype":"venue"
},
  "geometry": {"coordinates":[6.8537611961,51.2883148193],"type":"Point"}
}