{
  "type": "Feature",
  "properties": {
    "iso:country":"DE",
    "sg:address":"Markt 4",
    "sg:city":"Haltern",
    "sg:phone":"+49 2364/2151",
    "sg:postcode":"45721",
    "sg:province":"Nordrhein-Westfalen",
    "wof:name":"J. Pieper",
    "wof:placetype":"venue"
},
  "geometry": {"coordinates":[7.187461853,51.7430305481],"type":"Point"}
}