{
  "type": "Feature",
  "properties": {
    "iso:country":"DE",
    "sg:address":"Holzheimerstr. 8",
    "sg:city":"Passau",
    "sg:phone":"+49 851/755080",
    "sg:postcode":"94032",
    "sg:province":"Bayern",
    "wof:name":"Minimal",
    "wof:placetype":"venue"
},
  "geometry": {"coordinates":[13.4327259064,48.5707817078],"type":"Point"}
}