{
  "type": "Feature",
  "properties": {
    "iso:country":"DE",
    "sg:address":"Frankenstr. 16",
    "sg:city":"Weinolsheim",
    "sg:phone":"+49 6249/1523",
    "sg:postcode":"55278",
    "sg:province":"Rheinland-Pfalz",
    "wof:name":"Heribert Und Monika Acker",
    "wof:placetype":"venue"
},
  "geometry": {"coordinates":[8.2695302963,49.8182296753],"type":"Point"}
}