{
  "type": "Feature",
  "properties": {
    "iso:country":"DE",
    "sg:address":"Klostergasse 6",
    "sg:city":"Neu\u00f6tting",
    "sg:phone":"+49 8671/20205",
    "sg:postcode":"84524",
    "sg:province":"Bayern",
    "wof:name":"Werner Brodmann Architekten",
    "wof:placetype":"venue"
},
  "geometry": {"coordinates":[12.688552,48.239529],"type":"Point"}
}