{
  "type": "Feature",
  "properties": {
    "iso:country":"DE",
    "sg:address":"Eiler Str. 107 a",
    "sg:city":"K\u00f6ln",
    "sg:phone":"+49 221/861468",
    "sg:postcode":"51107",
    "sg:province":"Nordrhein-Westfalen",
    "wof:name":"Sanitax Gmbh Wc-vermietung",
    "wof:placetype":"venue"
},
  "geometry": {"coordinates":[7.081785202,50.9185218811],"type":"Point"}
}