{
  "type": "Feature",
  "properties": {
    "iso:country":"DE",
    "sg:address":"Hohenzollernstr. 14",
    "sg:city":"V\u00f6lklingen",
    "sg:phone":"+49 6898/21376",
    "sg:postcode":"66333",
    "sg:province":"Saarland",
    "wof:name":"Udo Minder Steuerberater",
    "wof:placetype":"venue"
},
  "geometry": {"coordinates":[6.8605008125,49.2518501282],"type":"Point"}
}