{
  "type": "Feature",
  "properties": {
    "iso:country":"DE",
    "sg:address":"Sch\u00fctzenstr. 5",
    "sg:city":"D\u00fclmen",
    "sg:phone":"+49 2590/91710",
    "sg:postcode":"48249",
    "sg:province":"Nordrhein-Westfalen",
    "wof:name":"Werner Austermann Gmbh",
    "wof:placetype":"venue"
},
  "geometry": {"coordinates":[7.4047250748,51.8438606262],"type":"Point"}
}