{
  "type": "Feature",
  "properties": {
    "iso:country":"DE",
    "sg:address":"Eigelsberger Str. 7",
    "sg:city":"Oberviechtach",
    "sg:phone":"+49 9671/1464",
    "sg:postcode":"92526",
    "sg:province":"Bayern",
    "wof:name":"Peter L\u00f6hlein",
    "wof:placetype":"venue"
},
  "geometry": {"coordinates":[12.4184122086,49.4544754028],"type":"Point"}
}