{
  "type": "Feature",
  "properties": {
    "iso:country":"DE",
    "sg:address":"Kaufweg 2",
    "sg:city":"Bielefeld",
    "sg:phone":"+49 5205/70673",
    "sg:postcode":"33689",
    "sg:province":"Nordrhein-Westfalen",
    "wof:name":"Union-klause",
    "wof:placetype":"venue"
},
  "geometry": {"coordinates":[8.5808649063,51.9398651123],"type":"Point"}
}