{
  "type": "Feature",
  "properties": {
    "iso:country":"DE",
    "sg:address":"Kugelb\u00fchlstr. 32a",
    "sg:city":"Roth",
    "sg:phone":"+49 9171/5038",
    "sg:postcode":"91154",
    "sg:province":"Bayern",
    "wof:name":"Ingrid Riedel Rechtsanw\u00e4ltin",
    "wof:placetype":"venue"
},
  "geometry": {"coordinates":[11.0922851562,49.2461471558],"type":"Point"}
}