{
  "type": "Feature",
  "properties": {
    "iso:country":"DE",
    "sg:address":"Bornaische Str. 23",
    "sg:city":"Leipzig",
    "sg:phone":"+49 341/3013941",
    "sg:postcode":"04277",
    "sg:province":"Sachsen",
    "wof:name":"H. Luft",
    "wof:placetype":"venue"
},
  "geometry": {"coordinates":[12.378185,51.308075],"type":"Point"}
}