{
  "type": "Feature",
  "properties": {
    "iso:country":"DE",
    "sg:address":"B\u00f6rnestr. 10",
    "sg:city":"D\u00fcsseldorf",
    "sg:phone":"+49 211/166700",
    "sg:postcode":"40211",
    "sg:province":"Nordrhein-Westfalen",
    "wof:name":"J\u00fcrgen Krug Rechtsanwalt",
    "wof:placetype":"venue"
},
  "geometry": {"coordinates":[6.791618824,51.2272109985],"type":"Point"}
}