{
  "type": "Feature",
  "properties": {
    "iso:country":"DE",
    "sg:address":"Heilmannstra\u00dfe 19",
    "sg:city":"M\u00fcnchen - Pullach",
    "sg:phone":"+49 89",
    "sg:postcode":"82049",
    "sg:province":"Bayern",
    "wof:name":"1a - R.s.reisemobilvermietung",
    "wof:placetype":"venue"
},
  "geometry": {"coordinates":[11.5263729095,48.0592308044],"type":"Point"}
}