{
  "type": "Feature",
  "properties": {
    "iso:country":"DE",
    "sg:address":"Tegernseer Landstr. 43",
    "sg:city":"Sauerlach",
    "sg:phone":"+49 8104/1078",
    "sg:postcode":"82054",
    "sg:province":"Bayern",
    "wof:name":"Exacta Waltraud Schrott Gmbh",
    "wof:placetype":"venue"
},
  "geometry": {"coordinates":[11.6537637711,47.967628479],"type":"Point"}
}