{
  "type": "Feature",
  "properties": {
    "iso:country":"DE",
    "sg:address":"Bielefelder Str. 165",
    "sg:city":"Paderborn",
    "sg:phone":"+49 5254/7351",
    "sg:postcode":"33104",
    "sg:province":"Nordrhein-Westfalen",
    "wof:name":"Alte Waage",
    "wof:placetype":"venue"
},
  "geometry": {"coordinates":[8.7113780975,51.7780647278],"type":"Point"}
}