{
  "type": "Feature",
  "properties": {
    "iso:country":"DE",
    "sg:address":"Dorfstr. 35",
    "sg:city":"H\u00e4uslingen",
    "sg:postcode":"27336",
    "sg:province":"Niedersachsen",
    "wof:name":"Privatunterst\u00fctzungsverein D. Arbeiter D.torfitwerke E.v.",
    "wof:placetype":"venue"
},
  "geometry": {"coordinates":[9.3856096268,52.8033103943],"type":"Point"}
}