{
  "type": "Feature",
  "properties": {
    "iso:country":"DE",
    "sg:address":"Billstra\u00dfe 41",
    "sg:city":"Hamburg",
    "sg:phone":"+49 40",
    "sg:postcode":"20539",
    "sg:province":"Hamburg",
    "wof:name":"Kfz-innung Hamburg",
    "wof:placetype":"venue"
},
  "geometry": {"coordinates":[10.037212,53.541344],"type":"Point"}
}