{
  "type": "Feature",
  "properties": {
    "iso:country":"DE",
    "sg:address":"Clara-Zetkin-Str. 26",
    "sg:city":"Erfurt",
    "sg:phone":"+49 361/3733767",
    "sg:postcode":"99099",
    "sg:province":"Th\u00fcringen",
    "wof:name":"G\u00fcnter Sturm Garten- Und",
    "wof:placetype":"venue"
},
  "geometry": {"coordinates":[11.041856,50.968121],"type":"Point"}
}