{
  "type": "Feature",
  "properties": {
    "iso:country":"DE",
    "sg:address":"Paradiesstr. 12",
    "sg:city":"Schw\u00e4bisch Gm\u00fcnd",
    "sg:phone":"+49 7171/60060",
    "sg:postcode":"73525",
    "sg:province":"Baden-W\u00fcrttemberg",
    "wof:name":"Remsdruckerei Sigg, H\u00e4rtel & Co.",
    "wof:placetype":"venue"
},
  "geometry": {"coordinates":[9.7978096008,48.797039032],"type":"Point"}
}