{
  "type": "Feature",
  "properties": {
    "iso:country":"DE",
    "sg:address":"Turmstr. 62",
    "sg:city":"Penzlin",
    "sg:phone":"+49 3962/210224",
    "sg:postcode":"17217",
    "sg:province":"Mecklenburg-Vorpommern",
    "wof:name":"Gabriele Jaeger",
    "wof:placetype":"venue"
},
  "geometry": {"coordinates":[13.0877161026,53.5046157837],"type":"Point"}
}