{
  "type": "Feature",
  "properties": {
    "iso:country":"DE",
    "sg:address":"Furtmayrstr. 30b",
    "sg:city":"Regensburg",
    "sg:phone":"+49 941/76781",
    "sg:postcode":"93053",
    "sg:province":"Bayern",
    "wof:name":"Evis",
    "wof:placetype":"venue"
},
  "geometry": {"coordinates":[12.111410141,49.0089263916],"type":"Point"}
}