{
  "type": "Feature",
  "properties": {
    "iso:country":"DE",
    "sg:address":"Siedlerstr. 4",
    "sg:city":"Mainz",
    "sg:phone":"+49 6131/686714",
    "sg:postcode":"55120",
    "sg:province":"Rheinland-Pfalz",
    "wof:name":"B. Dietl",
    "wof:placetype":"venue"
},
  "geometry": {"coordinates":[8.2227611542,50.0151329041],"type":"Point"}
}