{
  "type": "Feature",
  "properties": {
    "iso:country":"DE",
    "sg:address":"Hirtreut 27",
    "sg:city":"Perlesreut",
    "sg:phone":"+49 8555/378",
    "sg:postcode":"94157",
    "sg:province":"Bayern",
    "wof:name":"J. Fischer",
    "wof:placetype":"venue"
},
  "geometry": {"coordinates":[13.431814,48.762672],"type":"Point"}
}