{
  "type": "Feature",
  "properties": {
    "iso:country":"DE",
    "sg:address":"M\u00f6nkhofer Weg 40",
    "sg:city":"L\u00fcbeck",
    "sg:phone":"+49 451/597484",
    "sg:postcode":"23562",
    "sg:province":"Schleswig-Holstein",
    "wof:name":"Otto St\u00e4\u00df",
    "wof:placetype":"venue"
},
  "geometry": {"coordinates":[10.6988,53.850849],"type":"Point"}
}