{
  "type": "Feature",
  "properties": {
    "iso:country":"DE",
    "sg:address":"Rilkestr. 18",
    "sg:city":"Markkleeberg",
    "sg:phone":"+49 341/3380302",
    "sg:postcode":"04416",
    "sg:province":"Sachsen",
    "wof:name":"Hans-dieter Hartung Ingenieur",
    "wof:placetype":"venue"
},
  "geometry": {"coordinates":[12.4015979767,51.2749214172],"type":"Point"}
}