{
  "type": "Feature",
  "properties": {
    "iso:country":"DE",
    "sg:address":"Bismarckstr. 34",
    "sg:city":"Buseck",
    "sg:phone":"+49 6408/4688",
    "sg:postcode":"35418",
    "sg:province":"Hessen",
    "wof:name":"H. Lampe Maschinen",
    "wof:placetype":"venue"
},
  "geometry": {"coordinates":[8.782687,50.60915],"type":"Point"}
}