{
  "type": "Feature",
  "properties": {
    "iso:country":"DE",
    "sg:address":"Am Feilbergbach 4",
    "sg:city":"Kempten",
    "sg:phone":"+49 831/21464",
    "sg:postcode":"87439",
    "sg:province":"Bayern",
    "wof:name":"Lothar Pfluger",
    "wof:placetype":"venue"
},
  "geometry": {"coordinates":[10.302216,47.721775],"type":"Point"}
}