{
  "type": "Feature",
  "properties": {
    "iso:country":"DE",
    "sg:address":"Schillerstr. 19",
    "sg:city":"Montabaur",
    "sg:phone":"+49 2602/90493",
    "sg:postcode":"56410",
    "sg:province":"Rheinland-Pfalz",
    "wof:name":"E. Compes",
    "wof:placetype":"venue"
},
  "geometry": {"coordinates":[7.839099,50.437557],"type":"Point"}
}