{
  "type": "Feature",
  "properties": {
    "iso:country":"DE",
    "sg:address":"Hochwiesle 46",
    "sg:city":"Zimmern",
    "sg:phone":"+49 741/31424",
    "sg:postcode":"78658",
    "sg:province":"Baden-W\u00fcrttemberg",
    "wof:name":"Wild Bedachungen Gmbh",
    "wof:placetype":"venue"
},
  "geometry": {"coordinates":[8.585095,48.169991],"type":"Point"}
}