{
  "type": "Feature",
  "properties": {
    "iso:country":"DE",
    "sg:address":"Heidelberger Landstrasse 202",
    "sg:city":"Darmstadt",
    "sg:phone":"+49 6151/339177",
    "sg:postcode":"64297",
    "sg:province":"Hessen",
    "wof:name":"Aa Haus Der Briefmarke",
    "wof:placetype":"venue"
},
  "geometry": {"coordinates":[8.6442279816,49.8191833496],"type":"Point"}
}