{
  "type": "Feature",
  "properties": {
    "iso:country":"DE",
    "sg:address":"An der Reegt 4-8",
    "sg:city":"Bielefeld",
    "sg:phone":"+49 521/82189",
    "sg:postcode":"33611",
    "sg:province":"Nordrhein-Westfalen",
    "wof:name":"Blumen-brinkk\u00f6tter",
    "wof:placetype":"venue"
},
  "geometry": {"coordinates":[8.546961,52.056248],"type":"Point"}
}