{
  "type": "Feature",
  "properties": {
    "iso:country":"DE",
    "sg:address":"Kaiser-Joseph-Str. 170",
    "sg:city":"Freiburg",
    "sg:phone":"+49 4976/1278026",
    "sg:postcode":"79098",
    "sg:province":"Baden-W\u00fcrttemberg",
    "wof:name":"Cc-bank Ag",
    "wof:placetype":"venue"
},
  "geometry": {"coordinates":[7.852141,47.997242],"type":"Point"}
}