{
  "type": "Feature",
  "properties": {
    "iso:country":"DE",
    "sg:address":"Piesporter Str. 12",
    "sg:city":"Klausen",
    "sg:phone":"+49 6578/507",
    "sg:postcode":"54524",
    "sg:province":"Rheinland-Pfalz",
    "wof:name":"Fritz Freudenreich",
    "wof:placetype":"venue"
},
  "geometry": {"coordinates":[6.8846879005,49.9018745422],"type":"Point"}
}