{
  "type": "Feature",
  "properties": {
    "iso:country":"DE",
    "sg:address":"Hauptstr. 29",
    "sg:city":"Herschberg",
    "sg:phone":"+49 6375/1499",
    "sg:postcode":"66919",
    "sg:province":"Rheinland-Pfalz",
    "wof:name":"Alfred Schmitt",
    "wof:placetype":"venue"
},
  "geometry": {"coordinates":[7.544392,49.304916],"type":"Point"}
}