{
  "type": "Feature",
  "properties": {
    "iso:country":"DE",
    "sg:address":"wesedrfzui",
    "sg:city":"dzbijn",
    "sg:phone":"+49 58451265876456",
    "sg:postcode":"46516",
    "wof:name":"Chirurgie",
    "wof:placetype":"venue"
},
  "geometry": {"coordinates":[-85.93013,41.665039],"type":"Point"}
}