{
  "type": "Feature",
  "properties": {
    "iso:country":"DE",
    "sg:address":"Winklerstr. 14a",
    "sg:city":"Eibenstock",
    "sg:phone":"+49 37752/2729",
    "sg:postcode":"08309",
    "sg:province":"Sachsen",
    "wof:name":"S. Zitterbarth",
    "wof:placetype":"venue"
},
  "geometry": {"coordinates":[12.5936441422,50.4934272766],"type":"Point"}
}