{
  "type": "Feature",
  "properties": {
    "iso:country":"DE",
    "sg:address":"Solinger Str. 174",
    "sg:city":"Langenfeld",
    "sg:phone":"+49 2173/23399",
    "sg:postcode":"40764",
    "sg:province":"Nordrhein-Westfalen",
    "wof:name":"Dr. C. Roth-m\u00fcller",
    "wof:placetype":"venue"
},
  "geometry": {"coordinates":[6.9617657661,51.1152610779],"type":"Point"}
}