{
  "type": "Feature",
  "properties": {
    "iso:country":"DE",
    "sg:address":"Kornhain 8 A",
    "sg:city":"K\u00fchren-Burkartshain",
    "sg:phone":"+49 3425/921552",
    "sg:postcode":"04808",
    "sg:province":"Sachsen",
    "wof:name":"Heidi Zimpel",
    "wof:placetype":"venue"
},
  "geometry": {"coordinates":[12.7918653488,51.3923568726],"type":"Point"}
}