{
  "type": "Feature",
  "properties": {
    "iso:country":"DE",
    "sg:address":"Ausschl\u00e4ger Billdeich 62-64",
    "sg:city":"Hamburg",
    "sg:phone":"+49 40/788160",
    "sg:postcode":"20539",
    "sg:province":"Hamburg",
    "wof:name":"Schl\u00fcter S\u00f6hne Industrie- Vertriebs Gmbh",
    "wof:placetype":"venue"
},
  "geometry": {"coordinates":[10.046695,53.529797],"type":"Point"}
}