{
  "type": "Feature",
  "properties": {
    "iso:country":"DE",
    "sg:address":"Bismarckstr. 72",
    "sg:city":"D\u00fcsseldorf",
    "sg:phone":"+49 211/357111",
    "sg:postcode":"40210",
    "sg:province":"Nordrhein-Westfalen",
    "wof:name":"Werner Conen Heilpraktiker",
    "wof:placetype":"venue"
},
  "geometry": {"coordinates":[6.7879948616,51.2215461731],"type":"Point"}
}