{
  "type": "Feature",
  "properties": {
    "iso:country":"DE",
    "sg:address":"Andreasstr. 1",
    "sg:city":"Wangen",
    "sg:phone":"+49 7522/6837",
    "sg:postcode":"88239",
    "sg:province":"Baden-W\u00fcrttemberg",
    "wof:name":"Kath. Pfarramt Niederwangen",
    "wof:placetype":"venue"
},
  "geometry": {"coordinates":[9.7998743057,47.6714706421],"type":"Point"}
}