{
  "type": "Feature",
  "properties": {
    "iso:country":"DE",
    "sg:address":"Donaustr. 12",
    "sg:city":"Ludwigsburg",
    "sg:phone":"+49 7141/89020",
    "sg:postcode":"71638",
    "sg:province":"Baden-W\u00fcrttemberg",
    "wof:name":"Ev. Pfarramt Martinskirche",
    "wof:placetype":"venue"
},
  "geometry": {"coordinates":[9.2152748108,48.8795013428],"type":"Point"}
}