{
  "type": "Feature",
  "properties": {
    "iso:country":"DE",
    "sg:address":"Frankfurter Str. 39",
    "sg:city":"Offenbach",
    "sg:phone":"+49 69/819945",
    "sg:postcode":"63065",
    "sg:province":"Hessen",
    "wof:name":"Pomme Moden Gmbh",
    "wof:placetype":"venue"
},
  "geometry": {"coordinates":[8.760257,50.105061],"type":"Point"}
}