{
  "type": "Feature",
  "properties": {
    "iso:country":"DE",
    "sg:address":"Beethovenstr. 22",
    "sg:city":"Rostock",
    "sg:postcode":"18069",
    "sg:province":"Mecklenburg-Vorpommern",
    "wof:name":"Grill Und Meer Kg",
    "wof:placetype":"venue"
},
  "geometry": {"coordinates":[12.0904312134,54.0965805054],"type":"Point"}
}