{
  "type": "Feature",
  "properties": {
    "iso:country":"DE",
    "sg:address":"D\u00f6nhoffstr. 2",
    "sg:city":"Berlin",
    "sg:phone":"+49 30/5098790",
    "sg:postcode":"10318",
    "sg:province":"Berlin",
    "wof:name":"Karlshorster-apotheke",
    "wof:placetype":"venue"
},
  "geometry": {"coordinates":[13.52479,52.482613],"type":"Point"}
}