{
  "type": "Feature",
  "properties": {
    "iso:country":"DE",
    "sg:address":"Carl-Schurz-Str. 11",
    "sg:city":"Br\u00fchl",
    "sg:phone":"+49 2232/941685",
    "sg:postcode":"50321",
    "sg:province":"Nordrhein-Westfalen",
    "wof:name":"Season Import-export Gmbh",
    "wof:placetype":"venue"
},
  "geometry": {"coordinates":[6.9010882378,50.8280220032],"type":"Point"}
}