{
  "type": "Feature",
  "properties": {
    "iso:country":"DE",
    "sg:address":"Taxisstr. 20",
    "sg:city":"Rosenheim",
    "sg:phone":"+49 8031/288121",
    "sg:postcode":"83024",
    "sg:province":"Bayern",
    "wof:name":"Rowood Holzhandlung Gmbh",
    "wof:placetype":"venue"
},
  "geometry": {"coordinates":[12.1105127335,47.8615036011],"type":"Point"}
}