{
  "type": "Feature",
  "properties": {
    "iso:country":"DE",
    "sg:address":"M\u00fcnsterstr. 31",
    "sg:city":"G\u00fctersloh",
    "sg:phone":"+49 5241/16300",
    "sg:postcode":"33330",
    "sg:province":"Nordrhein-Westfalen",
    "wof:name":"Fototreff Siervers & Hohendorf Gmbh",
    "wof:placetype":"venue"
},
  "geometry": {"coordinates":[8.3756065369,51.9069747925],"type":"Point"}
}