{
  "type": "Feature",
  "properties": {
    "iso:country":"DE",
    "sg:address":"Am Bach 5",
    "sg:city":"Urbich",
    "sg:phone":"+49 361/4211573",
    "sg:postcode":"99198",
    "sg:province":"Th\u00fcringen",
    "wof:name":"Matthias Schicker Dental Gmbh",
    "wof:placetype":"venue"
},
  "geometry": {"coordinates":[11.1528053284,50.9695091248],"type":"Point"}
}