{
  "type": "Feature",
  "properties": {
    "iso:country":"DE",
    "sg:address":"Henrik-Ibsen-Str. 26",
    "sg:city":"Rostock",
    "sg:postcode":"18106",
    "sg:province":"Mecklenburg-Vorpommern",
    "wof:name":"K\u00fcstenportal J\u00fcrgen Truschzenski E. K.",
    "wof:placetype":"venue"
},
  "geometry": {"coordinates":[12.0601797104,54.1196136475],"type":"Point"}
}