{
  "type": "Feature",
  "properties": {
    "iso:country":"DE",
    "sg:address":"Walderbenweg 16",
    "sg:city":"Duisburg",
    "sg:phone":"+49 203/766120",
    "sg:postcode":"47269",
    "sg:province":"Nordrhein-Westfalen",
    "wof:name":"Peter Wehner",
    "wof:placetype":"venue"
},
  "geometry": {"coordinates":[6.781853,51.370461],"type":"Point"}
}