{
  "type": "Feature",
  "properties": {
    "iso:country":"DE",
    "sg:address":"Kelheimer Str. 14",
    "sg:city":"Neustadt",
    "sg:phone":"+49 9445/7481",
    "sg:postcode":"93333",
    "sg:province":"Bayern",
    "wof:name":"Johann Lohr",
    "wof:placetype":"venue"
},
  "geometry": {"coordinates":[11.7640247345,48.8622055054],"type":"Point"}
}