{
  "type": "Feature",
  "properties": {
    "iso:country":"DE",
    "sg:address":"Sulzbacher Str. 63",
    "sg:city":"N\u00fcrnberg",
    "sg:postcode":"90489",
    "sg:province":"Bayern",
    "wof:name":"Sps Service Partner Security Gmbh",
    "wof:placetype":"venue"
},
  "geometry": {"coordinates":[11.0971632004,49.4590911865],"type":"Point"}
}