{
  "type": "Feature",
  "properties": {
    "iso:country":"DE",
    "sg:address":"Carsten-B\u00f6rger-Str. 6",
    "sg:city":"Bremerhaven",
    "sg:phone":"+49 471/71035",
    "sg:postcode":"27572",
    "sg:province":"Bremen",
    "wof:name":"Wendeln Brot- Und Backwaren Gmbh & Co. Kg",
    "wof:placetype":"venue"
},
  "geometry": {"coordinates":[8.599183,53.49382],"type":"Point"}
}