{
  "type": "Feature",
  "properties": {
    "iso:country":"DE",
    "sg:address":"Ziegelstr. 25",
    "sg:city":"Drochtersen",
    "sg:phone":"+49 4148/1588",
    "sg:postcode":"21706",
    "sg:province":"Niedersachsen",
    "wof:name":"Reederei Ms Golf Rolf Witt Kg",
    "wof:placetype":"venue"
},
  "geometry": {"coordinates":[9.444393158,53.6850814819],"type":"Point"}
}