{
  "type": "Feature",
  "properties": {
    "iso:country":"DE",
    "sg:address":"Zum Storchennest 1",
    "sg:city":"Neustadt",
    "sg:phone":"+49 5072/1275",
    "sg:postcode":"31535",
    "sg:province":"Niedersachsen",
    "wof:name":"Dieter Querfeld-rabe",
    "wof:placetype":"venue"
},
  "geometry": {"coordinates":[9.538974,52.587368],"type":"Point"}
}