{
  "type": "Feature",
  "properties": {
    "iso:country":"DE",
    "sg:address":"Hauptstr. 66",
    "sg:city":"Triberg",
    "sg:phone":"+49 7722/5067",
    "sg:postcode":"78098",
    "sg:province":"Baden-W\u00fcrttemberg",
    "wof:name":"Brigau Inh. Helmut Plagemann",
    "wof:placetype":"venue"
},
  "geometry": {"coordinates":[8.23166,48.13039],"type":"Point"}
}