{
  "type": "Feature",
  "properties": {
    "iso:country":"DE",
    "sg:address":"Ottogart M\u00fchlmann Stra\u00dfe 9",
    "sg:city":"Jena",
    "sg:phone":"+49 36428",
    "sg:postcode":"07767",
    "sg:province":"Th\u00fcringen",
    "wof:name":"Cgiscripte.com, Die Serviceseite F\u00fcr Webmaster",
    "wof:placetype":"venue"
},
  "geometry": {"coordinates":[-92.158432,31.693001],"type":"Point"}
}