{
  "type": "Feature",
  "properties": {
    "iso:country":"DE",
    "sg:address":"Poststr. 8",
    "sg:city":"Freiburg",
    "sg:phone":"+49 761/386490",
    "sg:postcode":"79098",
    "sg:province":"Baden-W\u00fcrttemberg",
    "wof:name":"Privat Hotel Minerva",
    "wof:placetype":"venue"
},
  "geometry": {"coordinates":[7.8451209068,47.9979667664],"type":"Point"}
}