{
  "type": "Feature",
  "properties": {
    "iso:country":"DE",
    "sg:address":"Ehrenfried-Jopp-Str 59",
    "sg:city":"F\u00fcrstenwalde",
    "sg:phone":"+49 3361/372101",
    "sg:postcode":"15517",
    "sg:province":"Brandenburg",
    "wof:name":"Statron Ger\u00e4tetechnik Gmbh",
    "wof:placetype":"venue"
},
  "geometry": {"coordinates":[14.070325,52.366013],"type":"Point"}
}