{
  "type": "Feature",
  "properties": {
    "iso:country":"DE",
    "sg:address":"Hauptstr. 47",
    "sg:city":"Ha\u00dffurt",
    "sg:phone":"+49 9521/1387",
    "sg:postcode":"97437",
    "sg:province":"Bayern",
    "wof:name":"Landesbausparkasse Beratungsstelle",
    "wof:placetype":"venue"
},
  "geometry": {"coordinates":[10.505508,50.031322],"type":"Point"}
}