{
  "type": "Feature",
  "properties": {
    "iso:country":"DE",
    "sg:address":"Indestr. 139",
    "sg:city":"Eschweiler",
    "sg:phone":"+49 2403/29898",
    "sg:postcode":"52249",
    "sg:province":"Nordrhein-Westfalen",
    "wof:name":"Rudolf Conrads Architekt",
    "wof:placetype":"venue"
},
  "geometry": {"coordinates":[6.273091,50.817345],"type":"Point"}
}