{
  "type": "Feature",
  "properties": {
    "iso:country":"DE",
    "sg:address":"Gerhard-Sch\u00fcmmer-Str. 7",
    "sg:city":"Geilenkirchen",
    "sg:phone":"+49 2451/1560",
    "sg:postcode":"52511",
    "sg:province":"Nordrhein-Westfalen",
    "wof:name":"K. Buschmann Ingenieur",
    "wof:placetype":"venue"
},
  "geometry": {"coordinates":[6.1281719208,50.9656219482],"type":"Point"}
}