{
  "type": "Feature",
  "properties": {
    "iso:country":"DE",
    "sg:address":"Hausweilerweg 1",
    "sg:city":"Weilerswist",
    "sg:phone":"+49 2254/3189",
    "sg:postcode":"53919",
    "sg:province":"Nordrhein-Westfalen",
    "wof:name":"Bernhard Adorf",
    "wof:placetype":"venue"
},
  "geometry": {"coordinates":[6.852285,50.708435],"type":"Point"}
}