{
  "type": "Feature",
  "properties": {
    "iso:country":"DE",
    "sg:address":"Am Oberfeld 4",
    "sg:city":"Darmstadt",
    "sg:phone":"+49 6151/784501",
    "sg:postcode":"64287",
    "sg:province":"Hessen",
    "wof:name":"Lehmann Und Piesker Architekten",
    "wof:placetype":"venue"
},
  "geometry": {"coordinates":[8.674101,49.879841],"type":"Point"}
}