{
  "type": "Feature",
  "properties": {
    "iso:country":"DE",
    "sg:address":"Oberstr. 38",
    "sg:city":"Krefeld",
    "sg:phone":"+49 2151/481485",
    "sg:postcode":"47829",
    "sg:province":"Nordrhein-Westfalen",
    "wof:name":"Pistoletti",
    "wof:placetype":"venue"
},
  "geometry": {"coordinates":[6.649728775,51.3522071838],"type":"Point"}
}