{
  "type": "Feature",
  "properties": {
    "iso:country":"DE",
    "sg:address":"Hohenburger Str. 5",
    "sg:city":"Kastl",
    "sg:phone":"+49 9625/91296",
    "sg:postcode":"92280",
    "sg:province":"Bayern",
    "wof:name":"Reinhard Maag",
    "wof:placetype":"venue"
},
  "geometry": {"coordinates":[11.6812391281,49.3691520691],"type":"Point"}
}