{
  "type": "Feature",
  "properties": {
    "iso:country":"DE",
    "sg:address":"Allmendweg 6",
    "sg:city":"Meersburg",
    "sg:phone":"+49 7532/6483",
    "sg:postcode":"88709",
    "sg:province":"Baden-W\u00fcrttemberg",
    "wof:name":"Pfau Gmbh",
    "wof:placetype":"venue"
},
  "geometry": {"coordinates":[9.279279,47.698441],"type":"Point"}
}