{
  "type": "Feature",
  "properties": {
    "iso:country":"DE",
    "sg:address":"St.-Leoner-Str. 8",
    "sg:city":"Neulu\u00dfheim",
    "sg:phone":"+49 6205/397127",
    "sg:postcode":"68809",
    "sg:province":"Baden-W\u00fcrttemberg",
    "wof:name":"Gemeindebibliothek Alte Schule",
    "wof:placetype":"venue"
},
  "geometry": {"coordinates":[8.523841,49.293159],"type":"Point"}
}