{
  "type": "Feature",
  "properties": {
    "iso:country":"DE",
    "sg:address":"Vogelsbergstr. 22",
    "sg:city":"Glauburg-Stockheim",
    "sg:phone":"+49 6041/1093",
    "sg:postcode":"63695",
    "sg:province":"Hessen",
    "wof:name":"A. Graf",
    "wof:placetype":"venue"
},
  "geometry": {"coordinates":[9.01646,50.328629],"type":"Point"}
}