{
  "type": "Feature",
  "properties": {
    "iso:country":"DE",
    "sg:address":"Warmsen 141",
    "sg:city":"Warmsen",
    "sg:phone":"+49 5767/1708",
    "sg:postcode":"31606",
    "sg:province":"Niedersachsen",
    "wof:name":"Karl Meyer",
    "wof:placetype":"venue"
},
  "geometry": {"coordinates":[8.850938797,52.4531021118],"type":"Point"}
}