{
  "type": "Feature",
  "properties": {
    "iso:country":"DE",
    "sg:address":"Hohe Str. 17",
    "sg:city":"P\u00f6\u00dfneck",
    "sg:phone":"+49 3647/417889",
    "sg:postcode":"07381",
    "sg:province":"Th\u00fcringen",
    "wof:name":"G. Daum Immobilienmakler",
    "wof:placetype":"venue"
},
  "geometry": {"coordinates":[11.5895557404,50.6969985962],"type":"Point"}
}