{
  "type": "Feature",
  "properties": {
    "iso:country":"DE",
    "sg:address":"Lehmwohldstr. 9",
    "sg:city":"Itzehoe",
    "sg:phone":"+49 4821/73980",
    "sg:postcode":"25524",
    "sg:province":"Schleswig-Holstein",
    "wof:name":"U. Schwartkop Und C. J. Jaeckel",
    "wof:placetype":"venue"
},
  "geometry": {"coordinates":[9.5057783127,53.9327049255],"type":"Point"}
}