{
  "type": "Feature",
  "properties": {
    "iso:country":"DE",
    "sg:address":"Bolsehler Str. 998",
    "sg:city":"Husum",
    "sg:phone":"+49 5027/225",
    "sg:postcode":"31632",
    "sg:province":"Niedersachsen",
    "wof:name":"Henne & S\u00f6hne Gmbh",
    "wof:placetype":"venue"
},
  "geometry": {"coordinates":[9.2600603104,52.5643692017],"type":"Point"}
}