{
  "type": "Feature",
  "properties": {
    "iso:country":"DE",
    "sg:address":"Schallerauweg 4",
    "sg:city":"Sonneberg",
    "sg:phone":"+49 3675/702161",
    "sg:postcode":"96515",
    "sg:province":"Th\u00fcringen",
    "wof:name":"Siegfried G\u00fctschow",
    "wof:placetype":"venue"
},
  "geometry": {"coordinates":[11.165678,50.357357],"type":"Point"}
}