{
  "type": "Feature",
  "properties": {
    "iso:country":"DE",
    "sg:address":"Isener Str. 26",
    "sg:city":"Sankt Wolfgang",
    "sg:phone":"+49 8085/332",
    "sg:postcode":"84427",
    "sg:province":"Bayern",
    "wof:name":"Franz Fischer Gmbh",
    "wof:placetype":"venue"
},
  "geometry": {"coordinates":[12.13556,48.219814],"type":"Point"}
}