{
  "type": "Feature",
  "properties": {
    "iso:country":"DE",
    "sg:address":"Ostwall 28",
    "sg:city":"Uedem",
    "sg:phone":"+49 2825/10201",
    "sg:postcode":"47589",
    "sg:province":"Nordrhein-Westfalen",
    "wof:name":"Ingo Und Elisabeth Paetsch",
    "wof:placetype":"venue"
},
  "geometry": {"coordinates":[6.2746949196,51.6669807434],"type":"Point"}
}