{
  "type": "Feature",
  "properties": {
    "iso:country":"DE",
    "sg:address":"Wiesdorfer Platz 56",
    "sg:city":"Leverkusen",
    "sg:phone":"+49 214/830530",
    "sg:postcode":"51373",
    "sg:province":"Nordrhein-Westfalen",
    "wof:name":"Dr. Friedrich Middelhauve Gmbh & Co. Kg",
    "wof:placetype":"venue"
},
  "geometry": {"coordinates":[6.984498024,51.0320701599],"type":"Point"}
}