{
  "type": "Feature",
  "properties": {
    "iso:country":"DE",
    "sg:address":"Dorfheimstr. 7",
    "sg:city":"Gschwend",
    "sg:phone":"+49 7972/5708",
    "sg:postcode":"74417",
    "sg:province":"Baden-W\u00fcrttemberg",
    "wof:name":"Karl Und Otto Mursch",
    "wof:placetype":"venue"
},
  "geometry": {"coordinates":[9.733597,48.960564],"type":"Point"}
}