{"geometry":{"type":"Point","coordinates":[6.778311,51.224606]},"type":"Feature","id":102560705,"bbox":[6.778311,51.224606,6.778311,51.224606],"properties":{"sg:province":"Nordrhein-Westfalen","geom:longitude":6.778311,"wof:breaches":[],"sg:href":"http://api.simplegeo.com/1.0/features/SG_2MFsgBjDL1ibjn9muRNPvS_51.224606_6.778311@1306268793.json","sg:owner":"simplegeo","sg:postcode":"40212","geom:latitude":51.224606,"sg:classifiers":[],"sg:address":"K\u00f6nigsall. 21-23::","sg:phone":"+49 4921/19100","wof:hierarchy":[{"venue_id":102560705,"region_id":85682513,"country_id":85633111,"locality_id":101748671,"county_id":102063759,"neighbourhood_id":85795219}],"geom:area":0.000000,"sg:city":"D\u00fcsseldorf","wof:lastmodified":1438093335,"iso:country":"DE","wof:geomhash":"5127c98b9ade0785292bc21a29ae5742","wof:name":"Trinkaus & Burkhardt Kgaa","wof:belongsto":[85682513,85633111,101748671,102063759,85795219],"src:geom":"simplegeo","wof:placetype":"venue","wof:supersedes":[],"wof:id":102560705,"wof:superseded_by":[],"wof:concordances":{"sg:id":"SG_2MFsgBjDL1ibjn9muRNPvS_51.224606_6.778311@1306268793"},"wof:parent_id":85795219}}