{
  "type": "Feature",
  "properties": {
    "iso:country":"DE",
    "sg:address":"Kampesbreite 12",
    "sg:city":"Espenau",
    "sg:phone":"+49 5673/2160",
    "sg:postcode":"34314",
    "sg:province":"Hessen",
    "wof:name":"C. Gossmann",
    "wof:placetype":"venue"
},
  "geometry": {"coordinates":[9.4539890289,51.3853645325],"type":"Point"}
}