{
  "type": "Feature",
  "properties": {
    "iso:country":"DE",
    "sg:address":"Graslitzer Str. 2",
    "sg:city":"Neutraubling",
    "sg:postcode":"93073",
    "sg:province":"Bayern",
    "wof:name":"Riembauer Gmbh",
    "wof:placetype":"venue"
},
  "geometry": {"coordinates":[12.18061,48.974422],"type":"Point"}
}