{
  "type": "Feature",
  "properties": {
    "iso:country":"DE",
    "sg:address":"Prof.-Springer-Str. 10",
    "sg:city":"Zwiesel",
    "sg:phone":"+49 9922/4505",
    "sg:postcode":"94227",
    "sg:province":"Bayern",
    "wof:name":"Heinz M. Hof Steuerberater",
    "wof:placetype":"venue"
},
  "geometry": {"coordinates":[13.2416419983,49.0211906433],"type":"Point"}
}