{
  "type": "Feature",
  "properties": {
    "iso:country":"DE",
    "sg:address":"St. Wolfgangstr. 49",
    "sg:city":"Rauenberg",
    "sg:phone":"+49 7253/26906",
    "sg:postcode":"69231",
    "sg:province":"Baden-W\u00fcrttemberg",
    "wof:name":"Kernoelman",
    "wof:placetype":"venue"
},
  "geometry": {"coordinates":[8.6770248413,49.2534637451],"type":"Point"}
}