{
  "type": "Feature",
  "properties": {
    "iso:country":"DE",
    "sg:address":"Hauptstr. 37 a",
    "sg:city":"Rausdorf",
    "sg:phone":"+49 4154/6107",
    "sg:postcode":"22929",
    "sg:province":"Schleswig-Holstein",
    "wof:name":"Ernst Burmeister",
    "wof:placetype":"venue"
},
  "geometry": {"coordinates":[10.333759,53.586025],"type":"Point"}
}