{
  "type": "Feature",
  "properties": {
    "iso:country":"DE",
    "sg:address":"Westerstr. 23a",
    "sg:city":"Dingen",
    "sg:postcode":"25715",
    "sg:province":"Schleswig-Holstein",
    "wof:name":"Wolf B\u00fcro F\u00fcr Bautechnik Gmbh",
    "wof:placetype":"venue"
},
  "geometry": {"coordinates":[9.141845,53.966106],"type":"Point"}
}