{
  "type": "Feature",
  "properties": {
    "iso:country":"DE",
    "sg:address":"Habachstr. 11",
    "sg:city":"Netphen",
    "sg:phone":"+49 2737/591555",
    "sg:postcode":"57250",
    "sg:province":"Nordrhein-Westfalen",
    "wof:name":"Digital Sat Shop F\u00fcr Digitale Satellitentechnik",
    "wof:placetype":"venue"
},
  "geometry": {"coordinates":[8.1462,50.878609],"type":"Point"}
}