{
  "type": "Feature",
  "properties": {
    "iso:country":"DE",
    "sg:address":"Dr.-Josef-Hastreiter-Str. 21",
    "sg:city":"Dingolfing",
    "sg:phone":"+49 8731/31380",
    "sg:postcode":"84130",
    "sg:province":"Bayern",
    "wof:name":"Gewerbe-treuhand Gmbh",
    "wof:placetype":"venue"
},
  "geometry": {"coordinates":[12.5030145645,48.6312026978],"type":"Point"}
}