{
  "type": "Feature",
  "properties": {
    "iso:country":"DE",
    "sg:address":"Mittelpromenade 2",
    "sg:city":"Ostseebad Boltenhagen",
    "sg:postcode":"23946",
    "sg:province":"Mecklenburg-Vorpommern",
    "wof:name":"Appartementwohnung Im Ostseebad Boltenhagen",
    "wof:placetype":"venue"
},
  "geometry": {"coordinates":[11.207734,53.945484],"type":"Point"}
}