{
  "type": "Feature",
  "properties": {
    "iso:country":"DE",
    "sg:address":"B\u00fclt 2",
    "sg:city":"D\u00fclmen",
    "sg:postcode":"48249",
    "sg:province":"Nordrhein-Westfalen",
    "wof:name":"Kath. \u00f6ffentliche Bibliohtek St. Viktor",
    "wof:placetype":"venue"
},
  "geometry": {"coordinates":[7.278389,51.829197],"type":"Point"}
}