{
  "type": "Feature",
  "properties": {
    "iso:country":"DE",
    "sg:address":"Franzstr. 8",
    "sg:city":"Duisburg",
    "sg:phone":"+49 203/491228",
    "sg:postcode":"47179",
    "sg:province":"Nordrhein-Westfalen",
    "wof:name":"H\u00fcsken Gmbh & Co. Kg",
    "wof:placetype":"venue"
},
  "geometry": {"coordinates":[6.7401890755,51.5265846252],"type":"Point"}
}