{
  "type": "Feature",
  "properties": {
    "iso:country":"DE",
    "sg:address":"Hauptstr. 19",
    "sg:city":"Kleve",
    "sg:phone":"+49 4836/8405",
    "sg:postcode":"25779",
    "sg:province":"Schleswig-Holstein",
    "wof:name":"Dithmarscher Hof",
    "wof:placetype":"venue"
},
  "geometry": {"coordinates":[9.124833107,54.2955245972],"type":"Point"}
}