{
  "type": "Feature",
  "properties": {
    "iso:country":"DE",
    "sg:address":"Breitscheidstr. 19",
    "sg:city":"Neustadt-Glewe",
    "sg:phone":"+49 38757/22231",
    "sg:postcode":"19306",
    "sg:province":"Mecklenburg-Vorpommern",
    "wof:name":"Arno D\u00f6ll",
    "wof:placetype":"venue"
},
  "geometry": {"coordinates":[11.5854330063,53.3829841614],"type":"Point"}
}