{
  "type": "Feature",
  "properties": {
    "iso:country":"DE",
    "sg:address":"Paulusstr. 9",
    "sg:city":"Worms",
    "sg:phone":"+49 6241/22664",
    "sg:postcode":"67547",
    "sg:province":"Rheinland-Pfalz",
    "wof:name":"P. Br\u00fchan",
    "wof:placetype":"venue"
},
  "geometry": {"coordinates":[8.366292,49.631081],"type":"Point"}
}