{
  "type": "Feature",
  "properties": {
    "iso:country":"DE",
    "sg:address":"Vorkamp 32",
    "sg:city":"M\u00f6lln",
    "sg:phone":"+49 4542/2493",
    "sg:postcode":"23879",
    "sg:province":"Schleswig-Holstein",
    "wof:name":"Spedition Dechow M\u00f6beltransporte Lagerung",
    "wof:placetype":"venue"
},
  "geometry": {"coordinates":[10.6772708893,53.6203804016],"type":"Point"}
}