{
  "type": "Feature",
  "properties": {
    "iso:country":"DE",
    "sg:address":"Adenauerstr. 21",
    "sg:city":"M\u00fchlhausen",
    "sg:phone":"+49 6222/61270",
    "sg:postcode":"69242",
    "sg:province":"Baden-W\u00fcrttemberg",
    "wof:name":"Chenal Optik- Schmuck-",
    "wof:placetype":"venue"
},
  "geometry": {"coordinates":[8.7284240723,49.2459487915],"type":"Point"}
}