{
  "type": "Feature",
  "properties": {
    "iso:country":"DE",
    "sg:address":"Zur Rau 21",
    "sg:city":"Morbach",
    "sg:phone":"+49 6533/2093",
    "sg:postcode":"54497",
    "sg:province":"Rheinland-Pfalz",
    "wof:name":"K\u00e4lte Klima Sze\u00dfny Gmbh",
    "wof:placetype":"venue"
},
  "geometry": {"coordinates":[7.1463971138,49.8185424805],"type":"Point"}
}