{
  "type": "Feature",
  "properties": {
    "iso:country":"DE",
    "sg:address":"Alte Bahnhofstr. 13",
    "sg:city":"P\u00f6cking",
    "sg:phone":"+49 8157/8219",
    "sg:postcode":"82343",
    "sg:province":"Bayern",
    "wof:name":"M. Eggenhofer Heissmangel",
    "wof:placetype":"venue"
},
  "geometry": {"coordinates":[11.305059433,47.9686203003],"type":"Point"}
}