{
  "type": "Feature",
  "properties": {
    "iso:country":"DE",
    "sg:address":"Frohschammerstr. 14",
    "sg:city":"M\u00fcnchen",
    "sg:phone":"+49 89/35651836",
    "sg:postcode":"80807",
    "sg:province":"Bayern",
    "wof:name":"Coyote Online",
    "wof:placetype":"venue"
},
  "geometry": {"coordinates":[11.568776,48.178947],"type":"Point"}
}