{
  "type": "Feature",
  "properties": {
    "iso:country":"DE",
    "sg:address":"Fischertwiete 2",
    "sg:city":"Hamburg",
    "sg:postcode":"20095",
    "sg:province":"Hamburg",
    "wof:name":"Hansen Creativ Agentur F\u00fcr Werbung Kommunikations-",
    "wof:placetype":"venue"
},
  "geometry": {"coordinates":[10.00159,53.548302],"type":"Point"}
}