{
  "type": "Feature",
  "properties": {
    "iso:country":"DE",
    "sg:address":"Waldfrieden 3 a",
    "sg:city":"Zerf",
    "sg:phone":"+49 6587/7409",
    "sg:postcode":"54314",
    "sg:province":"Rheinland-Pfalz",
    "wof:name":"K. Und M. Jung",
    "wof:placetype":"venue"
},
  "geometry": {"coordinates":[6.677176,49.584126],"type":"Point"}
}