{
  "type": "Feature",
  "properties": {
    "iso:country":"DE",
    "sg:address":"L\u00f6nsstr. 5",
    "sg:city":"K\u00f6ln",
    "sg:phone":"+49 2234/944934",
    "sg:postcode":"50858",
    "sg:province":"Nordrhein-Westfalen",
    "wof:name":"Relations & More E. K.",
    "wof:placetype":"venue"
},
  "geometry": {"coordinates":[6.8381490707,50.9405822754],"type":"Point"}
}