{
  "type": "Feature",
  "properties": {
    "iso:country":"DE",
    "sg:address":"Thielallee 11",
    "sg:city":"Berlin",
    "sg:postcode":"14195",
    "sg:province":"Berlin",
    "wof:name":"Fondazione Incontri Europei Europ\u00e4ische",
    "wof:placetype":"venue"
},
  "geometry": {"coordinates":[13.2856912613,52.4561805725],"type":"Point"}
}