{
  "type": "Feature",
  "properties": {
    "iso:country":"DE",
    "sg:address":"Lindenstra\u00dfe 6",
    "sg:city":"L\u00fcneburg",
    "sg:phone":"+49 41314775547756",
    "sg:postcode":"21335",
    "sg:province":"Niedersachsen",
    "wof:name":"American Pizza Service - Aps",
    "wof:placetype":"venue"
},
  "geometry": {"coordinates":[10.4048099518,53.2425994873],"type":"Point"}
}