{
  "type": "Feature",
  "properties": {
    "iso:country":"DE",
    "sg:address":"Forstweg 4",
    "sg:city":"Bremsdorf",
    "sg:postcode":"15890",
    "sg:province":"Brandenburg",
    "wof:name":"Helms Gmbh",
    "wof:placetype":"venue"
},
  "geometry": {"coordinates":[14.4873485565,52.1406326294],"type":"Point"}
}