{
  "type": "Feature",
  "properties": {
    "iso:country":"DE",
    "sg:address":"Seining 7",
    "sg:city":"Tiefenbach",
    "sg:phone":"+49 8546/2521",
    "sg:postcode":"94113",
    "sg:province":"Bayern",
    "wof:name":"Herbert Bauer",
    "wof:placetype":"venue"
},
  "geometry": {"coordinates":[13.329886,48.660625],"type":"Point"}
}