{
  "type": "Feature",
  "properties": {
    "iso:country":"DE",
    "sg:address":"Unfaltstr. 7",
    "sg:city":"F\u00fcrstenfeldbruck",
    "sg:postcode":"82256",
    "sg:province":"Bayern",
    "wof:name":"Deutsche Telekom T-punkt",
    "wof:placetype":"venue"
},
  "geometry": {"coordinates":[11.2494125366,48.1798667908],"type":"Point"}
}