{
  "type": "Feature",
  "properties": {
    "iso:country":"DE",
    "sg:address":"Merklinghauser Str. 12",
    "sg:city":"Hallenberg",
    "sg:phone":"+49 2984/8680",
    "sg:postcode":"59969",
    "sg:province":"Nordrhein-Westfalen",
    "wof:name":"Gastst\u00e4tte Peter Beumer",
    "wof:placetype":"venue"
},
  "geometry": {"coordinates":[8.6229228973,51.1106452942],"type":"Point"}
}