{
  "type": "Feature",
  "properties": {
    "iso:country":"DE",
    "sg:address":"Grevesm\u00fchlenweg 1",
    "sg:city":"L\u00fcbeck",
    "sg:phone":"+49 451",
    "sg:postcode":"23564",
    "sg:province":"Schleswig-Holstein",
    "wof:name":"Www.scootertechno.de",
    "wof:placetype":"venue"
},
  "geometry": {"coordinates":[10.736278,53.847046],"type":"Point"}
}