{
  "type": "Feature",
  "properties": {
    "iso:country":"DE",
    "sg:address":"Hans-Adolf-Str. 8",
    "sg:city":"Pl\u00f6n",
    "sg:phone":"+49 4522/2808",
    "sg:postcode":"24306",
    "sg:province":"Schleswig-Holstein",
    "wof:name":"Robert Weber",
    "wof:placetype":"venue"
},
  "geometry": {"coordinates":[10.4100656509,54.1585044861],"type":"Point"}
}