{
  "type": "Feature",
  "properties": {
    "iso:country":"DE",
    "sg:address":"Waldnieler Str. 97 a",
    "sg:city":"Viersen",
    "sg:phone":"+49 2162/40724",
    "sg:postcode":"41751",
    "sg:province":"Nordrhein-Westfalen",
    "wof:name":"Karl Kirchhofer",
    "wof:placetype":"venue"
},
  "geometry": {"coordinates":[6.308444,51.233028],"type":"Point"}
}