{
  "type": "Feature",
  "properties": {
    "iso:country":"DE",
    "sg:address":"Rottpark 22",
    "sg:city":"Pfarrkirchen",
    "sg:phone":"+49 8561/23660",
    "sg:postcode":"84347",
    "sg:province":"Bayern",
    "wof:name":"Christa Wellenhofer Apotheke Im Turm E. K.",
    "wof:placetype":"venue"
},
  "geometry": {"coordinates":[12.943095,48.423306],"type":"Point"}
}