{
  "type": "Feature",
  "properties": {
    "iso:country":"DE",
    "sg:address":"Badstr 26",
    "sg:city":"Waldshut-Tiengen",
    "sg:phone":"+49 7741/92250",
    "sg:postcode":"79761",
    "sg:province":"Baden-W\u00fcrttemberg",
    "wof:name":"Gt Elektrotechnische Produkte Gmbh",
    "wof:placetype":"venue"
},
  "geometry": {"coordinates":[8.264033,47.630306],"type":"Point"}
}