{
  "type": "Feature",
  "properties": {
    "iso:country":"DE",
    "sg:address":"Rheinstr. 2",
    "sg:city":"L\u00f6rzweiler",
    "sg:phone":"+49 6138/6263",
    "sg:postcode":"55296",
    "sg:province":"Rheinland-Pfalz",
    "wof:name":"Willi Hochhaus",
    "wof:placetype":"venue"
},
  "geometry": {"coordinates":[8.2987689972,49.8999900818],"type":"Point"}
}