{
  "type": "Feature",
  "properties": {
    "iso:country":"DE",
    "sg:address":"Bruchweg 96",
    "sg:city":"Kaarst",
    "sg:postcode":"41564",
    "sg:province":"Nordrhein-Westfalen",
    "wof:name":"Drei Satz Werbe- Produktions Gmbh",
    "wof:placetype":"venue"
},
  "geometry": {"coordinates":[6.6300320625,51.2153205872],"type":"Point"}
}