{
  "type": "Feature",
  "properties": {
    "iso:country":"DE",
    "sg:address":"Reiherweg 5",
    "sg:city":"Aurich",
    "sg:phone":"+49 4941/67151",
    "sg:postcode":"26603",
    "sg:province":"Niedersachsen",
    "wof:name":"U. Wiemken",
    "wof:placetype":"venue"
},
  "geometry": {"coordinates":[7.489716,53.458492],"type":"Point"}
}