{
  "type": "Feature",
  "properties": {
    "iso:country":"DE",
    "sg:address":"Innebergweg 5",
    "sg:city":"Piding",
    "sg:phone":"+49 8651/63145",
    "sg:postcode":"83451",
    "sg:province":"Bayern",
    "wof:name":"Georg Sch\u00f6ndorfer",
    "wof:placetype":"venue"
},
  "geometry": {"coordinates":[12.905051,47.772709],"type":"Point"}
}