{
  "type": "Feature",
  "properties": {
    "iso:country":"DE",
    "sg:address":"Frankfurter Landstr. 1",
    "sg:city":"Hanau",
    "sg:phone":"+49 6181/12496",
    "sg:postcode":"63452",
    "sg:province":"Hessen",
    "wof:name":"Fritz Reichert & Sohn Gmbh & Co. Kg",
    "wof:placetype":"venue"
},
  "geometry": {"coordinates":[8.9092473984,50.1388587952],"type":"Point"}
}