{
  "type": "Feature",
  "properties": {
    "iso:country":"DE",
    "sg:address":"Naumburger Str. 11",
    "sg:city":"Hermsdorf",
    "sg:phone":"+49 36601/41416",
    "sg:postcode":"07629",
    "sg:province":"Th\u00fcringen",
    "wof:name":"Viola Grommas",
    "wof:placetype":"venue"
},
  "geometry": {"coordinates":[11.853988,50.899113],"type":"Point"}
}