{
  "type": "Feature",
  "properties": {
    "iso:country":"DE",
    "sg:address":"K\u00f6lner Str. 52",
    "sg:city":"Grevenbroich",
    "sg:postcode":"41515",
    "sg:province":"Nordrhein-Westfalen",
    "wof:name":"Stephan Flassak Inh. Monika Keil E. K.",
    "wof:placetype":"venue"
},
  "geometry": {"coordinates":[6.5917301178,51.0878067017],"type":"Point"}
}