{
  "type": "Feature",
  "properties": {
    "iso:country":"DE",
    "sg:address":"Goethestr. 1",
    "sg:city":"Nittendorf",
    "sg:phone":"+49 9404/962816",
    "sg:postcode":"93152",
    "sg:province":"Bayern",
    "wof:name":"H. Neuhoff",
    "wof:placetype":"venue"
},
  "geometry": {"coordinates":[11.9563312531,49.021812439],"type":"Point"}
}