{
  "type": "Feature",
  "properties": {
    "iso:country":"DE",
    "sg:address":"Am Steinacker 45",
    "sg:city":"Dresden",
    "sg:phone":"+49 351/8906092",
    "sg:postcode":"01109",
    "sg:province":"Sachsen",
    "wof:name":"P. Saupe",
    "wof:placetype":"venue"
},
  "geometry": {"coordinates":[13.766534,51.12133],"type":"Point"}
}