{
  "type": "Feature",
  "properties": {
    "iso:country":"DE",
    "sg:address":"Ginsterweg 1",
    "sg:city":"Bergkamen",
    "sg:phone":"+49 2307/83466",
    "sg:postcode":"59192",
    "sg:province":"Nordrhein-Westfalen",
    "wof:name":"Siegfried Ackmann Architekt",
    "wof:placetype":"venue"
},
  "geometry": {"coordinates":[7.668751,51.624954],"type":"Point"}
}