{
  "type": "Feature",
  "properties": {
    "iso:country":"DE",
    "sg:address":"Bellevue 62::",
    "sg:city":"Hamburg",
    "sg:phone":"+49 40/2783960",
    "sg:postcode":"22301",
    "sg:province":"Hamburg",
    "wof:name":"Peter Sch\u00dcler & Co Gmbh",
    "wof:placetype":"venue"
},
  "geometry": {"coordinates":[10.002926,53.583206],"type":"Point"}
}