{
  "type": "Feature",
  "properties": {
    "iso:country":"DE",
    "sg:city":"Drangstedt",
    "sg:phone":"+49 4704/2093",
    "sg:postcode":"27624",
    "sg:province":"Niedersachsen",
    "wof:name":"Friedrich Eggers",
    "wof:placetype":"venue"
},
  "geometry": {"coordinates":[8.751463,53.613117],"type":"Point"}
}