{
  "type": "Feature",
  "properties": {
    "iso:country":"DE",
    "sg:address":"Miquelstr. 50",
    "sg:city":"Berlin",
    "sg:phone":"+49 30/8324633",
    "sg:postcode":"14195",
    "sg:province":"Berlin",
    "wof:name":"Christiane Weber-ollk",
    "wof:placetype":"venue"
},
  "geometry": {"coordinates":[13.2884101868,52.4697532654],"type":"Point"}
}