{
  "type": "Feature",
  "properties": {
    "iso:country":"DE",
    "sg:address":"Hindenburgallee 12",
    "sg:city":"Gehrden",
    "sg:postcode":"30989",
    "sg:province":"Niedersachsen",
    "wof:name":"Isis Gmbh",
    "wof:placetype":"venue"
},
  "geometry": {"coordinates":[9.597945,52.308559],"type":"Point"}
}