{
  "type": "Feature",
  "properties": {
    "iso:country":"DE",
    "sg:address":"Scheifendahl 74",
    "sg:city":"Heinsberg",
    "sg:phone":"+49 2452/3536",
    "sg:postcode":"52525",
    "sg:province":"Nordrhein-Westfalen",
    "wof:name":"Heinrich Habitz",
    "wof:placetype":"venue"
},
  "geometry": {"coordinates":[6.075288,51.033215],"type":"Point"}
}