{
  "type": "Feature",
  "properties": {
    "iso:country":"DE",
    "sg:address":"Stickenweg 12",
    "sg:city":"Diemelstadt",
    "sg:phone":"+49 5694/677",
    "sg:postcode":"34474",
    "sg:province":"Hessen",
    "wof:name":"Willy Bressem",
    "wof:placetype":"venue"
},
  "geometry": {"coordinates":[9.050039,51.445087],"type":"Point"}
}