{
  "type": "Feature",
  "properties": {
    "iso:country":"DE",
    "sg:address":"Hochallee 130",
    "sg:city":"Hamburg",
    "sg:phone":"+49 40/470074",
    "sg:postcode":"20149",
    "sg:province":"Hamburg",
    "wof:name":"Reiseb\u00fcro Die Neue Hanse Gmbh",
    "wof:placetype":"venue"
},
  "geometry": {"coordinates":[9.9852485657,53.5830345154],"type":"Point"}
}