{
  "type": "Feature",
  "properties": {
    "iso:country":"DE",
    "sg:address":"Reiherweg 3",
    "sg:city":"Dettingen",
    "sg:phone":"+49 7123/7668",
    "sg:postcode":"72581",
    "sg:province":"Baden-W\u00fcrttemberg",
    "wof:name":"Naturfreundehaus Hans M}nzing",
    "wof:placetype":"venue"
},
  "geometry": {"coordinates":[9.3576250076,48.5300483704],"type":"Point"}
}