{
  "type": "Feature",
  "properties": {
    "iso:country":"DE",
    "sg:address":"Vorster Str. 18",
    "sg:city":"T\u00f6nisvorst",
    "sg:phone":"+49 2151/790475",
    "sg:postcode":"47918",
    "sg:province":"Nordrhein-Westfalen",
    "wof:name":"Josef Peters",
    "wof:placetype":"venue"
},
  "geometry": {"coordinates":[6.469416,51.316624],"type":"Point"}
}