{
  "type": "Feature",
  "properties": {
    "iso:country":"DE",
    "sg:address":"Ludwigstr. 23",
    "sg:city":"Bad Reichenhall",
    "sg:phone":"+49 8651/97380",
    "sg:postcode":"83435",
    "sg:province":"Bayern",
    "wof:name":"Kaufhaus Juhasz Gmbh & Co. Kg",
    "wof:placetype":"venue"
},
  "geometry": {"coordinates":[12.879029,47.724442],"type":"Point"}
}