{
  "type": "Feature",
  "properties": {
    "iso:country":"DE",
    "sg:address":"Friedrichstr. 13",
    "sg:city":"Neuhausen",
    "sg:phone":"+49 7158/8101",
    "sg:postcode":"73765",
    "sg:province":"Baden-W\u00fcrttemberg",
    "wof:name":"G\u00fcnther Weber",
    "wof:placetype":"venue"
},
  "geometry": {"coordinates":[9.281435,48.67984],"type":"Point"}
}