{
  "type": "Feature",
  "properties": {
    "iso:country":"DE",
    "sg:address":"Stargarder Str. 74",
    "sg:city":"Berlin",
    "sg:phone":"+49 30/4458499",
    "sg:postcode":"10437",
    "sg:province":"Berlin",
    "wof:name":"Gy\u00f6ngyl Blank",
    "wof:placetype":"venue"
},
  "geometry": {"coordinates":[13.4173069,52.5470123291],"type":"Point"}
}