{
  "type": "Feature",
  "properties": {
    "iso:country":"DE",
    "sg:address":"Leipziger Str. 49",
    "sg:city":"Grimma",
    "sg:phone":"+49 3437/911411",
    "sg:postcode":"04668",
    "sg:province":"Sachsen",
    "wof:name":"Restaurant Jin Shan",
    "wof:placetype":"venue"
},
  "geometry": {"coordinates":[12.7155265808,51.2313766479],"type":"Point"}
}