{
  "type": "Feature",
  "properties": {
    "iso:country":"DE",
    "sg:address":"Ostbahnstr. 26",
    "sg:city":"Landau",
    "sg:phone":"+49 4963/4186027",
    "sg:postcode":"76829",
    "sg:province":"Rheinland-Pfalz",
    "wof:name":"Sparda-bank Mainz Eg",
    "wof:placetype":"venue"
},
  "geometry": {"coordinates":[8.122631,49.197792],"type":"Point"}
}