{
  "type": "Feature",
  "properties": {
    "iso:country":"DE",
    "sg:address":"Karl-Stieler-Str. 4",
    "sg:city":"Ottobrunn",
    "sg:phone":"+49 89/66002802",
    "sg:postcode":"85521",
    "sg:province":"Bayern",
    "wof:name":"Volker Rhein",
    "wof:placetype":"venue"
},
  "geometry": {"coordinates":[11.6806707382,48.0632286072],"type":"Point"}
}