{
  "type": "Feature",
  "properties": {
    "iso:country":"DE",
    "sg:address":"B\u00e4ckerstr. 35",
    "sg:city":"Minden",
    "sg:phone":"+49 571/23619",
    "sg:postcode":"32423",
    "sg:province":"Nordrhein-Westfalen",
    "wof:name":"Orsay",
    "wof:placetype":"venue"
},
  "geometry": {"coordinates":[8.918749,52.29018],"type":"Point"}
}