{
  "type": "Feature",
  "properties": {
    "iso:country":"DE",
    "sg:address":"Klingweg 6",
    "sg:city":"Worms",
    "sg:phone":"+49 6241/75873",
    "sg:postcode":"67549",
    "sg:province":"Rheinland-Pfalz",
    "wof:name":"G\u00fcnter Zimmer",
    "wof:placetype":"venue"
},
  "geometry": {"coordinates":[8.3362398148,49.6399002075],"type":"Point"}
}