{
  "type": "Feature",
  "properties": {
    "iso:country":"DE",
    "sg:address":"Hauptstr. 17",
    "sg:city":"Fl\u00f6rsbachtal",
    "sg:phone":"+49 6057/1268",
    "sg:postcode":"63639",
    "sg:province":"Hessen",
    "wof:name":"Heinz Gl\u00fcck Verm\u00f6gensberater",
    "wof:placetype":"venue"
},
  "geometry": {"coordinates":[9.4800395966,50.1277732849],"type":"Point"}
}