{
  "type": "Feature",
  "properties": {
    "iso:country":"DE",
    "sg:address":"Blaufelder Str. 42",
    "sg:city":"Wallhausen",
    "sg:phone":"+49 7955/2270",
    "sg:postcode":"74599",
    "sg:province":"Baden-W\u00fcrttemberg",
    "wof:name":"W. Flurer Gmbh",
    "wof:placetype":"venue"
},
  "geometry": {"coordinates":[10.064317,49.214031],"type":"Point"}
}