{
  "type": "Feature",
  "properties": {
    "iso:country":"DE",
    "sg:address":"Sch\u00f6ttenstr. 20",
    "sg:city":"Neukirchen-Vluyn",
    "sg:postcode":"47506",
    "sg:province":"Nordrhein-Westfalen",
    "wof:name":"Anonyme Konfliktberatung Per Telefon Oder E-mail",
    "wof:placetype":"venue"
},
  "geometry": {"coordinates":[6.527339,51.436462],"type":"Point"}
}