{
  "type": "Feature",
  "properties": {
    "iso:country":"DE",
    "sg:address":"Burgstr. 36",
    "sg:city":"Lathen",
    "sg:phone":"+49 5933/277",
    "sg:postcode":"49762",
    "sg:province":"Niedersachsen",
    "wof:name":"Rudolf Sanen",
    "wof:placetype":"venue"
},
  "geometry": {"coordinates":[7.3128261566,52.8637390137],"type":"Point"}
}