{
  "type": "Feature",
  "properties": {
    "iso:country":"DE",
    "sg:address":"Ganghoferstr. 3",
    "sg:city":"Ottobrunn",
    "sg:phone":"+49 89/6099705",
    "sg:postcode":"85521",
    "sg:province":"Bayern",
    "wof:name":"Kubetex Gmbh Vertriebsges. F. Kunststoffbe-",
    "wof:placetype":"venue"
},
  "geometry": {"coordinates":[11.673871994,48.0645561218],"type":"Point"}
}