{
  "type": "Feature",
  "properties": {
    "iso:country":"DE",
    "sg:address":"Neuhauser Str.7",
    "sg:city":"Leer",
    "sg:phone":"+49 491",
    "sg:postcode":"26789",
    "sg:province":"Niedersachsen",
    "wof:name":"Pks Gmbh",
    "wof:placetype":"venue"
},
  "geometry": {"coordinates":[7.4276099205,53.266418457],"type":"Point"}
}