{
  "type": "Feature",
  "properties": {
    "iso:country":"DE",
    "sg:address":"M\u00fcllergasse 17",
    "sg:city":"Roetgen",
    "sg:phone":"+49 2471/3329",
    "sg:postcode":"52159",
    "sg:province":"Nordrhein-Westfalen",
    "wof:name":"Bodo Schlamp Vom Hofe Architekt",
    "wof:placetype":"venue"
},
  "geometry": {"coordinates":[6.207083,50.64801],"type":"Point"}
}