{
  "type": "Feature",
  "properties": {
    "iso:country":"DE",
    "sg:address":"Kirchstr. 1",
    "sg:city":"Lohmar",
    "sg:phone":"+49 2246/1020",
    "sg:postcode":"53797",
    "sg:province":"Nordrhein-Westfalen",
    "wof:name":"Merck Eurolab Gmbh",
    "wof:placetype":"venue"
},
  "geometry": {"coordinates":[7.209211,50.839806],"type":"Point"}
}