{
  "type": "Feature",
  "properties": {
    "iso:country":"DE",
    "sg:address":"Eichholzstr. 1",
    "sg:city":"Hopsten",
    "sg:phone":"+49 5457/1287",
    "sg:postcode":"48496",
    "sg:province":"Nordrhein-Westfalen",
    "wof:name":"Finke-bau-projekt- Corporation Gmbh",
    "wof:placetype":"venue"
},
  "geometry": {"coordinates":[7.6108880043,52.4463233948],"type":"Point"}
}