{
  "type": "Feature",
  "properties": {
    "iso:country":"DE",
    "sg:address":"Rudersdorfer Str. 18",
    "sg:city":"Wilnsdorf",
    "sg:phone":"+49 4927/392544",
    "sg:postcode":"57234",
    "sg:province":"Nordrhein-Westfalen",
    "wof:name":"Bernd Kreitzberg",
    "wof:placetype":"venue"
},
  "geometry": {"coordinates":[8.113132,50.821106],"type":"Point"}
}