{
  "type": "Feature",
  "properties": {
    "iso:country":"DE",
    "sg:address":"Leipziger Str. 22",
    "sg:city":"Kassel",
    "sg:phone":"+49 561/572144",
    "sg:postcode":"34125",
    "sg:province":"Hessen",
    "wof:name":"Deutsche Shell Ag",
    "wof:placetype":"venue"
},
  "geometry": {"coordinates":[9.5108613968,51.3116950989],"type":"Point"}
}