{
  "type": "Feature",
  "properties": {
    "iso:country":"DE",
    "sg:address":"Auf dem Werder 32",
    "sg:city":"Ro\u00dfwein",
    "sg:phone":"+49 34322/43363",
    "sg:postcode":"04741",
    "sg:province":"Sachsen",
    "wof:name":"Muldenklause",
    "wof:placetype":"venue"
},
  "geometry": {"coordinates":[13.1851882935,51.0628166199],"type":"Point"}
}