{
  "type": "Feature",
  "properties": {
    "iso:country":"DE",
    "sg:address":"Echinger Str. 12a",
    "sg:city":"Unterschlei\u00dfheim",
    "sg:phone":"+49 89/54558257",
    "sg:postcode":"85716",
    "sg:province":"Bayern",
    "wof:name":"Enviroplan Abfallentsorgung Und Umweltberatung Gmbh",
    "wof:placetype":"venue"
},
  "geometry": {"coordinates":[11.58697,48.262535],"type":"Point"}
}