{
  "type": "Feature",
  "properties": {
    "iso:country":"DE",
    "sg:address":"N\u00e4geleinsgasse 3",
    "sg:city":"Neustadt",
    "sg:phone":"+49 9161/61424",
    "sg:postcode":"91413",
    "sg:province":"Bayern",
    "wof:name":"Farben-knauer Gro\u00df- Und Einzelhandel E. K.",
    "wof:placetype":"venue"
},
  "geometry": {"coordinates":[10.60306,49.577145],"type":"Point"}
}