{
  "type": "Feature",
  "properties": {
    "iso:country":"DE",
    "sg:address":"Engelstra\u00dfe 38",
    "sg:city":"Trier",
    "sg:phone":"+49 651/26459",
    "sg:postcode":"54292",
    "sg:province":"Rheinland-Pfalz",
    "wof:name":"Natu-pur Haarpflege Auf Nat\u00fcrlicher Basis",
    "wof:placetype":"venue"
},
  "geometry": {"coordinates":[6.6451768875,49.7621688843],"type":"Point"}
}