{
  "type": "Feature",
  "properties": {
    "iso:country":"DE",
    "sg:address":"Feuchtwanger Str. 101",
    "sg:city":"Ansbach",
    "sg:phone":"+49 981/461480",
    "sg:postcode":"91522",
    "sg:province":"Bayern",
    "wof:name":"Ditha Elektro- Fachgrosshandelshaus",
    "wof:placetype":"venue"
},
  "geometry": {"coordinates":[10.557009697,49.2924842834],"type":"Point"}
}