{
  "type": "Feature",
  "properties": {
    "iso:country":"DE",
    "sg:address":"Poststr. 11",
    "sg:city":"Trittau",
    "sg:phone":"+49 4154/841586",
    "sg:postcode":"22946",
    "sg:province":"Schleswig-Holstein",
    "wof:name":"Kloppenburg Gmbh & Co.",
    "wof:placetype":"venue"
},
  "geometry": {"coordinates":[10.409204,53.608955],"type":"Point"}
}