{
  "type": "Feature",
  "properties": {
    "iso:country":"DE",
    "sg:address":"Bei den K\u00e4mpen 9",
    "sg:city":"Seevetal",
    "sg:phone":"+49 4185/2146",
    "sg:postcode":"21220",
    "sg:province":"Niedersachsen",
    "wof:name":"Bruno Bierbaum Kg",
    "wof:placetype":"venue"
},
  "geometry": {"coordinates":[10.037745,53.384331],"type":"Point"}
}