{
  "type": "Feature",
  "properties": {
    "iso:country":"DE",
    "sg:address":"Pestalozzistr. 38",
    "sg:city":"Fellbach",
    "sg:phone":"+49 711/589804",
    "sg:postcode":"70736",
    "sg:province":"Baden-W\u00fcrttemberg",
    "wof:name":"M. Mische",
    "wof:placetype":"venue"
},
  "geometry": {"coordinates":[9.2757663727,48.816444397],"type":"Point"}
}