{
  "type": "Feature",
  "properties": {
    "iso:country":"DE",
    "sg:address":"Friedrichstr. 25",
    "sg:city":"Krefeld",
    "sg:phone":"+49 2151/8130",
    "sg:postcode":"47798",
    "sg:province":"Nordrhein-Westfalen",
    "wof:name":"Volksbank Krefeld, Von 1897 Eg",
    "wof:placetype":"venue"
},
  "geometry": {"coordinates":[6.561703,51.33445],"type":"Point"}
}