{
  "type": "Feature",
  "properties": {
    "iso:country":"DE",
    "sg:address":"Lebacher Str. 60",
    "sg:city":"Heusweiler",
    "sg:phone":"+49 4952/0789540",
    "sg:postcode":"66265",
    "sg:province":"Saarland",
    "wof:name":"Tenrit Sanit\u00c4r Gmbh",
    "wof:placetype":"venue"
},
  "geometry": {"coordinates":[8.6163330078,51.9031677246],"type":"Point"}
}