{
  "type": "Feature",
  "properties": {
    "iso:country":"DE",
    "sg:address":"M\u00fchlenhof",
    "sg:city":"Flensburg",
    "sg:phone":"+49 461/30273",
    "sg:postcode":"24943",
    "sg:province":"Schleswig-Holstein",
    "wof:name":"Inge Carlsen",
    "wof:placetype":"venue"
},
  "geometry": {"coordinates":[9.4504346848,54.7958488464],"type":"Point"}
}