{
  "type": "Feature",
  "properties": {
    "iso:country":"DE",
    "sg:address":"Burggasse 3",
    "sg:city":"Zusmarshausen",
    "sg:phone":"+49 8291/1773",
    "sg:postcode":"86441",
    "sg:province":"Bayern",
    "wof:name":"F. Hintermayr",
    "wof:placetype":"venue"
},
  "geometry": {"coordinates":[10.59491539,48.3992614746],"type":"Point"}
}