{
  "type": "Feature",
  "properties": {
    "iso:country":"DE",
    "sg:address":"Bokeler Dorfstr. 10",
    "sg:city":"Sprakensehl",
    "sg:phone":"+49 5837/822",
    "sg:postcode":"29365",
    "sg:province":"Niedersachsen",
    "wof:name":"Albert Fischer",
    "wof:placetype":"venue"
},
  "geometry": {"coordinates":[10.54289,52.806568],"type":"Point"}
}