{
  "type": "Feature",
  "properties": {
    "iso:country":"DE",
    "sg:address":"Schlangenbader Str. 15",
    "sg:city":"Berlin",
    "sg:phone":"+49 30/8234387",
    "sg:postcode":"14197",
    "sg:province":"Berlin",
    "wof:name":"Tydda & Tydda Handel Und Herst. Von Innov. Drogerie-",
    "wof:placetype":"venue"
},
  "geometry": {"coordinates":[13.3079719543,52.4744262695],"type":"Point"}
}