{
  "type": "Feature",
  "properties": {
    "iso:country":"DE",
    "sg:address":"Buckower Damm 232",
    "sg:city":"Berlin",
    "sg:phone":"+49 30/6041485",
    "sg:postcode":"12349",
    "sg:province":"Berlin",
    "wof:name":"Medley-club",
    "wof:placetype":"venue"
},
  "geometry": {"coordinates":[13.4370059967,52.4229698181],"type":"Point"}
}