{
  "type": "Feature",
  "properties": {
    "iso:country":"DE",
    "sg:address":"Marienthaler Str. 156a",
    "sg:city":"Walbeck",
    "sg:phone":"+49 39061/2571",
    "sg:postcode":"39356",
    "sg:province":"Sachsen-Anhalt",
    "wof:name":"Sigrid Wolke",
    "wof:placetype":"venue"
},
  "geometry": {"coordinates":[11.0610294342,52.2790908813],"type":"Point"}
}