{
  "type": "Feature",
  "properties": {
    "iso:country":"DE",
    "sg:address":"Wilhelmstr. 15",
    "sg:city":"Backnang",
    "sg:phone":"+49 7191/64380",
    "sg:postcode":"71522",
    "sg:province":"Baden-W\u00fcrttemberg",
    "wof:name":"Grill-schorsch-engel",
    "wof:placetype":"venue"
},
  "geometry": {"coordinates":[9.4251832962,48.9453887939],"type":"Point"}
}