{
  "type": "Feature",
  "properties": {
    "iso:country":"DE",
    "sg:address":"Harthaer Str. 3",
    "sg:city":"Dorfhain",
    "sg:phone":"+49 35055/61855",
    "sg:postcode":"01738",
    "sg:province":"Sachsen",
    "wof:name":"Werner Fleischer",
    "wof:placetype":"venue"
},
  "geometry": {"coordinates":[13.559505,50.939114],"type":"Point"}
}