{
  "type": "Feature",
  "properties": {
    "iso:country":"DE",
    "sg:address":"Eythstr. 37",
    "sg:city":"K\u00f6ln",
    "sg:phone":"+49 221/857749",
    "sg:postcode":"51103",
    "sg:province":"Nordrhein-Westfalen",
    "wof:name":"C. Hinzmann",
    "wof:placetype":"venue"
},
  "geometry": {"coordinates":[7.0103969574,50.9411506653],"type":"Point"}
}