{
  "type": "Feature",
  "properties": {
    "iso:country":"DE",
    "sg:address":"Op de Solt 42",
    "sg:city":"Hamburg",
    "sg:phone":"+49 40/60680770",
    "sg:postcode":"22391",
    "sg:province":"Hamburg",
    "wof:name":"Cordes Vertriebs- Gesellschaft Mbh",
    "wof:placetype":"venue"
},
  "geometry": {"coordinates":[10.0851316452,53.6337127686],"type":"Point"}
}