{
  "type": "Feature",
  "properties": {
    "iso:country":"DE",
    "sg:address":"Sch\u00e4ftersheimer Str. 39",
    "sg:city":"Weikersheim",
    "sg:phone":"+49 7934/3034",
    "sg:postcode":"97990",
    "sg:province":"Baden-W\u00fcrttemberg",
    "wof:name":"Wolf Electronic Gmbh",
    "wof:placetype":"venue"
},
  "geometry": {"coordinates":[9.901407,49.487831],"type":"Point"}
}