{
  "type": "Feature",
  "properties": {
    "iso:country":"DE",
    "sg:address":"Reichenhaller Str. 59",
    "sg:city":"Berlin",
    "sg:postcode":"14199",
    "sg:province":"Berlin",
    "wof:name":"As Auto Service Gesellschaft F\u00fcr Fahrzeugpflege Und",
    "wof:placetype":"venue"
},
  "geometry": {"coordinates":[13.2926645279,52.4773254395],"type":"Point"}
}