{
  "type": "Feature",
  "properties": {
    "iso:country":"DE",
    "sg:address":"Prager Str. 71",
    "sg:city":"Sch\u00f6nebeck",
    "sg:phone":"+49 3928/845930",
    "sg:postcode":"39218",
    "sg:province":"Sachsen-Anhalt",
    "wof:name":"Lebenshilfe B\u00f6rdeland Gemeinn\u00fctzige Gmbh",
    "wof:placetype":"venue"
},
  "geometry": {"coordinates":[11.73564,52.01022],"type":"Point"}
}