{
  "type": "Feature",
  "properties": {
    "iso:country":"DE",
    "sg:address":"Garvensstr. 5",
    "sg:city":"Hannover",
    "sg:phone":"+49 511/87030",
    "sg:postcode":"30519",
    "sg:province":"Niedersachsen",
    "wof:name":"J. Helmke & Co.",
    "wof:placetype":"venue"
},
  "geometry": {"coordinates":[9.785778,52.325169],"type":"Point"}
}