{
  "type": "Feature",
  "properties": {
    "iso:country":"DE",
    "sg:address":"Raun 13",
    "sg:city":"Nidda",
    "sg:phone":"+49 6043/6868",
    "sg:postcode":"63667",
    "sg:province":"Hessen",
    "wof:name":"Sams Wein & Spirituosen Gmbh",
    "wof:placetype":"venue"
},
  "geometry": {"coordinates":[9.0090465546,50.4121017456],"type":"Point"}
}