{
  "type": "Feature",
  "properties": {
    "iso:country":"DE",
    "sg:address":"Johann-Breuker-Platz 4",
    "sg:city":"Bottrop",
    "sg:phone":"+49 2045/5015",
    "sg:postcode":"46244",
    "sg:province":"Nordrhein-Westfalen",
    "wof:name":"H. Kl\u00e4sener",
    "wof:placetype":"venue"
},
  "geometry": {"coordinates":[6.921265,51.602901],"type":"Point"}
}