{
  "type": "Feature",
  "properties": {
    "iso:country":"DE",
    "sg:address":"Helmholtzplatz 11",
    "sg:city":"K\u00f6ln",
    "sg:phone":"+49 221",
    "sg:postcode":"50825",
    "sg:province":"Nordrhein-Westfalen",
    "wof:name":"Internet Jugendcafe Cologne (ijc)",
    "wof:placetype":"venue"
},
  "geometry": {"coordinates":[6.9030308723,50.9541473389],"type":"Point"}
}