{
  "type": "Feature",
  "properties": {
    "iso:country":"DE",
    "sg:address":"Stahlwerkstr. 197",
    "sg:city":"Apen",
    "sg:phone":"+49 4489/5725",
    "sg:postcode":"26689",
    "sg:province":"Niedersachsen",
    "wof:name":"Jan De Vries",
    "wof:placetype":"venue"
},
  "geometry": {"coordinates":[7.796757,53.255108],"type":"Point"}
}