{
  "type": "Feature",
  "properties": {
    "iso:country":"DE",
    "sg:address":"Bergstr. 25",
    "sg:city":"Erndtebr\u00fcck",
    "sg:phone":"+49 2753/2167",
    "sg:postcode":"57339",
    "sg:province":"Nordrhein-Westfalen",
    "wof:name":"Hans Dieter Birkelbach",
    "wof:placetype":"venue"
},
  "geometry": {"coordinates":[8.255559,50.986584],"type":"Point"}
}