{
  "type": "Feature",
  "properties": {
    "iso:country":"DE",
    "sg:address":"Waldstr 42",
    "sg:city":"Aichwald",
    "sg:phone":"+49 711/36990",
    "sg:postcode":"73773",
    "sg:province":"Baden-W\u00fcrttemberg",
    "wof:name":"Eugen Rehm Esslinger Fleischwaren Gmbh & Co Kg",
    "wof:placetype":"venue"
},
  "geometry": {"coordinates":[9.380052,48.749428],"type":"Point"}
}