{
  "type": "Feature",
  "properties": {
    "iso:country":"DE",
    "sg:address":"Klosterstr. 5",
    "sg:city":"Ernst",
    "sg:phone":"+49 2671/8391",
    "sg:postcode":"56814",
    "sg:province":"Rheinland-Pfalz",
    "wof:name":"Horst M\u00fcller",
    "wof:placetype":"venue"
},
  "geometry": {"coordinates":[7.2206149101,50.143497467],"type":"Point"}
}