{
  "type": "Feature",
  "properties": {
    "iso:country":"DE",
    "sg:address":"Fr\u00fchlingstr. 11",
    "sg:city":"Passau",
    "sg:phone":"+49 851/6245",
    "sg:postcode":"94032",
    "sg:province":"Bayern",
    "wof:name":"Rudolf Wieninger",
    "wof:placetype":"venue"
},
  "geometry": {"coordinates":[13.4352083206,48.5713233948],"type":"Point"}
}