{
  "type": "Feature",
  "properties": {
    "iso:country":"DE",
    "sg:address":"Schachtstr. 71",
    "sg:city":"Ahlen",
    "sg:phone":"+49 2382/989970",
    "sg:postcode":"59229",
    "sg:province":"Nordrhein-Westfalen",
    "wof:name":"Veloton - Braunsmann - Haastert Ohg",
    "wof:placetype":"venue"
},
  "geometry": {"coordinates":[7.9166808128,51.7553901672],"type":"Point"}
}