{
  "type": "Feature",
  "properties": {
    "iso:country":"DE",
    "sg:address":"Am Hexenteich 17",
    "sg:city":"Borgentreich",
    "sg:phone":"+49 5643/8344",
    "sg:postcode":"34434",
    "sg:province":"Nordrhein-Westfalen",
    "wof:name":"Ursula Guss",
    "wof:placetype":"venue"
},
  "geometry": {"coordinates":[9.3165311813,51.569229126],"type":"Point"}
}