{
  "type": "Feature",
  "properties": {
    "iso:country":"DE",
    "sg:address":"Riemannstr. 13",
    "sg:city":"Berlin",
    "sg:postcode":"10961",
    "sg:province":"Berlin",
    "wof:name":"Wolters Montage Gmbh",
    "wof:placetype":"venue"
},
  "geometry": {"coordinates":[13.392055,52.490433],"type":"Point"}
}