{
  "type": "Feature",
  "properties": {
    "iso:country":"DE",
    "sg:address":"Darast",
    "sg:city":"Bad Gr\u00f6nenbach",
    "sg:phone":"+49 8334/816",
    "sg:postcode":"87730",
    "sg:province":"Bayern",
    "wof:name":"Kutter Gmbh",
    "wof:placetype":"venue"
},
  "geometry": {"coordinates":[10.222581,47.908054],"type":"Point"}
}