{
  "type": "Feature",
  "properties": {
    "iso:country":"DE",
    "sg:address":"Schulweg 4",
    "sg:city":"Tittmoning",
    "sg:phone":"+49 8683/618",
    "sg:postcode":"84529",
    "sg:province":"Bayern",
    "wof:name":"Kath. Pfarramt St. Martin",
    "wof:placetype":"venue"
},
  "geometry": {"coordinates":[12.7662982941,48.0611953735],"type":"Point"}
}