{
  "type": "Feature",
  "properties": {
    "iso:country":"DE",
    "sg:address":"Simmersbach 12",
    "sg:city":"Ottenh\u00f6fen",
    "sg:phone":"+49 7842/2155",
    "sg:postcode":"77883",
    "sg:province":"Baden-W\u00fcrttemberg",
    "wof:name":"Franz R\u00f6sch",
    "wof:placetype":"venue"
},
  "geometry": {"coordinates":[8.142093,48.564236],"type":"Point"}
}