{
  "type": "Feature",
  "properties": {
    "iso:country":"DE",
    "sg:address":"Speicherstr. 11",
    "sg:city":"G\u00fcstrow",
    "sg:phone":"+49 3843/7510",
    "sg:postcode":"18273",
    "sg:province":"Mecklenburg-Vorpommern",
    "wof:name":"Mqd Qualit\u00e4tspr\u00fcfungs- Und Dienstleistungsgesellschaft",
    "wof:placetype":"venue"
},
  "geometry": {"coordinates":[12.1649827957,53.8032951355],"type":"Point"}
}