{
  "type": "Feature",
  "properties": {
    "iso:country":"DE",
    "sg:address":"Grootmoor 146",
    "sg:city":"Hamburg",
    "sg:phone":"+49 40/6405747",
    "sg:postcode":"22175",
    "sg:province":"Hamburg",
    "wof:name":"Fuhlbr\u00fcck Gmbh",
    "wof:placetype":"venue"
},
  "geometry": {"coordinates":[10.1095132828,53.633556366],"type":"Point"}
}