{
  "type": "Feature",
  "properties": {
    "iso:country":"DE",
    "sg:address":"Schwanhof 7",
    "sg:city":"Postm\u00fcnster",
    "sg:phone":"+49 8561/1574",
    "sg:postcode":"84389",
    "sg:province":"Bayern",
    "wof:name":"H. Fischer",
    "wof:placetype":"venue"
},
  "geometry": {"coordinates":[12.875115,48.425476],"type":"Point"}
}