{
  "type": "Feature",
  "properties": {
    "iso:country":"DE",
    "sg:address":"Poststr. 5",
    "sg:city":"Menden",
    "sg:phone":"+49 4923/7393560",
    "sg:postcode":"58706",
    "sg:province":"Nordrhein-Westfalen",
    "wof:name":"M\u00c4rkische Bank Eg",
    "wof:placetype":"venue"
},
  "geometry": {"coordinates":[7.790821,51.438915],"type":"Point"}
}