{
  "type": "Feature",
  "properties": {
    "iso:country":"DE",
    "sg:address":"Schlei\u00dfheimer Str. 395",
    "sg:city":"M\u00fcnchen",
    "sg:phone":"+49 89/35465848",
    "sg:postcode":"80935",
    "sg:province":"Bayern",
    "wof:name":"T. Amann",
    "wof:placetype":"venue"
},
  "geometry": {"coordinates":[11.563985,48.200741],"type":"Point"}
}