{
  "type": "Feature",
  "properties": {
    "iso:country":"DE",
    "sg:address":"K\u00f6lner Str 11",
    "sg:city":"Frechen",
    "sg:phone":"+49 2234/273566",
    "sg:postcode":"50226",
    "sg:province":"Nordrhein-Westfalen",
    "wof:name":"Ingenieurb\u00fcro Filz-m\u00fcller",
    "wof:placetype":"venue"
},
  "geometry": {"coordinates":[6.816409,50.910095],"type":"Point"}
}