{
  "type": "Feature",
  "properties": {
    "iso:country":"DE",
    "sg:address":"Aegidistr. 77",
    "sg:city":"Bottrop",
    "sg:phone":"+49 2041/32633",
    "sg:postcode":"46238",
    "sg:province":"Nordrhein-Westfalen",
    "wof:name":"Silz",
    "wof:placetype":"venue"
},
  "geometry": {"coordinates":[6.9502701759,51.5384559631],"type":"Point"}
}