{
  "type": "Feature",
  "properties": {
    "iso:country":"DE",
    "sg:address":"Hauptstr. 36",
    "sg:city":"Saarbr\u00fccken",
    "sg:phone":"+49 6893/1887",
    "sg:postcode":"66130",
    "sg:province":"Saarland",
    "wof:name":"Harry Hoffmann",
    "wof:placetype":"venue"
},
  "geometry": {"coordinates":[7.0997161865,49.1917495728],"type":"Point"}
}