{
  "type": "Feature",
  "properties": {
    "iso:country":"DE",
    "sg:address":"Zur Dreispitz 1",
    "sg:city":"Burbach",
    "sg:phone":"+49 2736/3207",
    "sg:postcode":"57299",
    "sg:province":"Nordrhein-Westfalen",
    "wof:name":"Anneliese Michel",
    "wof:placetype":"venue"
},
  "geometry": {"coordinates":[8.134379,50.723488],"type":"Point"}
}