{
  "type": "Feature",
  "properties": {
    "iso:country":"DE",
    "sg:address":"Adolf-Kolping-Str. 22",
    "sg:city":"D\u00fcsseldorf",
    "sg:phone":"+49 211/7000469",
    "sg:postcode":"40593",
    "sg:province":"Nordrhein-Westfalen",
    "wof:name":"K\u00fcnstler- & Show-service Roland Br\u00fcggen",
    "wof:placetype":"venue"
},
  "geometry": {"coordinates":[6.881061,51.146729],"type":"Point"}
}