{
  "type": "Feature",
  "properties": {
    "iso:country":"DE",
    "sg:address":"Machtlfinger Str. 21",
    "sg:city":"M\u00fcnchen",
    "sg:phone":"+49 89/784505",
    "sg:postcode":"81379",
    "sg:province":"Bayern",
    "wof:name":"Baierl & Partner Ges. F\u00fcr Software-entwicklung Mbh",
    "wof:placetype":"venue"
},
  "geometry": {"coordinates":[11.514191,48.095276],"type":"Point"}
}