{
  "type": "Feature",
  "properties": {
    "iso:country":"DE",
    "sg:address":"Milchmarkt 9",
    "sg:city":"Rothenburg",
    "sg:phone":"+49 9861/5841",
    "sg:postcode":"91541",
    "sg:province":"Bayern",
    "wof:name":"Frieda Krau\u00df",
    "wof:placetype":"venue"
},
  "geometry": {"coordinates":[10.1806945801,49.3773574829],"type":"Point"}
}