{
  "type": "Feature",
  "properties": {
    "iso:country":"DE",
    "sg:address":"Keplerstr. 11",
    "sg:city":"Bremen",
    "sg:phone":"+49 421/73420",
    "sg:postcode":"28203",
    "sg:province":"Bremen",
    "wof:name":"Manfred C\u00e4sar",
    "wof:placetype":"venue"
},
  "geometry": {"coordinates":[8.8282032013,53.0755729675],"type":"Point"}
}