{
  "type": "Feature",
  "properties": {
    "iso:country":"DE",
    "sg:address":"Potsdamer Str. 7",
    "sg:city":"Zierenberg",
    "sg:phone":"+49 5606/2560",
    "sg:postcode":"34289",
    "sg:province":"Hessen",
    "wof:name":"M. Schreckert",
    "wof:placetype":"venue"
},
  "geometry": {"coordinates":[9.3145236969,51.3720626831],"type":"Point"}
}