{
  "type": "Feature",
  "properties": {
    "iso:country":"DE",
    "sg:address":"Am Eichenhain 3",
    "sg:city":"Eging",
    "sg:phone":"+49 8544/7260",
    "sg:postcode":"94535",
    "sg:province":"Bayern",
    "wof:name":"J. K\u00f6ck",
    "wof:placetype":"venue"
},
  "geometry": {"coordinates":[13.2683296204,48.7079925537],"type":"Point"}
}