{
  "type": "Feature",
  "properties": {
    "iso:country":"DE",
    "sg:address":"Gasserstr. 11",
    "sg:city":"Dautphetal",
    "sg:phone":"+49 6468/912970",
    "sg:postcode":"35232",
    "sg:province":"Hessen",
    "wof:name":"W. Gerlach",
    "wof:placetype":"venue"
},
  "geometry": {"coordinates":[8.527736,50.815269],"type":"Point"}
}