{
  "type": "Feature",
  "properties": {
    "iso:country":"DE",
    "sg:address":"Kamener Str. 83",
    "sg:city":"Hamm",
    "sg:phone":"+49 2381/400684",
    "sg:postcode":"59077",
    "sg:province":"Nordrhein-Westfalen",
    "wof:name":"Clemens Empting",
    "wof:placetype":"venue"
},
  "geometry": {"coordinates":[7.732488,51.631573],"type":"Point"}
}