{
  "type": "Feature",
  "properties": {
    "iso:country":"DE",
    "sg:address":"Dorfstr. 102 a",
    "sg:city":"Radensleben",
    "sg:phone":"+49 33925/70252",
    "sg:postcode":"16818",
    "sg:province":"Brandenburg",
    "wof:name":"Landwirtschafts- Gesellschaft Mbh",
    "wof:placetype":"venue"
},
  "geometry": {"coordinates":[12.9040727615,52.8863372803],"type":"Point"}
}