{
  "type": "Feature",
  "properties": {
    "iso:country":"DE",
    "sg:address":"Ahornweg 4",
    "sg:city":"Forchheim",
    "sg:phone":"+49 9191/32144",
    "sg:postcode":"91301",
    "sg:province":"Bayern",
    "wof:name":"J. Steinmetz",
    "wof:placetype":"venue"
},
  "geometry": {"coordinates":[11.0472488403,49.7242469788],"type":"Point"}
}