{
  "type": "Feature",
  "properties": {
    "iso:country":"DE",
    "sg:address":"Schlossplatz 4",
    "sg:city":"Usingen",
    "sg:phone":"+49 4960/8124243",
    "sg:postcode":"61250",
    "sg:province":"Hessen",
    "wof:name":"Nassauische Sparkasse",
    "wof:placetype":"venue"
},
  "geometry": {"coordinates":[8.537209,50.333794],"type":"Point"}
}