{
  "type": "Feature",
  "properties": {
    "iso:country":"DE",
    "sg:address":"Bahnhofstr. 13",
    "sg:city":"Westoverledingen",
    "sg:phone":"+49 4955/5304",
    "sg:postcode":"26810",
    "sg:province":"Niedersachsen",
    "wof:name":"Dr. Med. Reiner Gl\u00e4\u00dfgen Arzt F\u00fcr Allgemeinmedizin",
    "wof:placetype":"venue"
},
  "geometry": {"coordinates":[7.4503722191,53.1661987305],"type":"Point"}
}