{
  "type": "Feature",
  "properties": {
    "iso:country":"DE",
    "sg:address":"Mittelstr. 7",
    "sg:city":"Hadamar",
    "sg:phone":"+49 6433/3497",
    "sg:postcode":"65589",
    "sg:province":"Hessen",
    "wof:name":"Toni Breithecker",
    "wof:placetype":"venue"
},
  "geometry": {"coordinates":[8.06205,50.473019],"type":"Point"}
}