{
  "type": "Feature",
  "properties": {
    "iso:country":"DE",
    "sg:address":"Schmiedestr. 17",
    "sg:city":"Schwerin",
    "sg:phone":"+49 385/5572021",
    "sg:postcode":"19053",
    "sg:province":"Mecklenburg-Vorpommern",
    "wof:name":"Photo Dose Gmbh",
    "wof:placetype":"venue"
},
  "geometry": {"coordinates":[11.4132881165,53.6292572021],"type":"Point"}
}