{
  "type": "Feature",
  "properties": {
    "iso:country":"DE",
    "sg:address":"M\u00f6rfelder Landstr. 255",
    "sg:city":"Frankfurt",
    "sg:phone":"+49 69/63153810",
    "sg:postcode":"60598",
    "sg:province":"Hessen",
    "wof:name":"Hans-joachim Dopp",
    "wof:placetype":"venue"
},
  "geometry": {"coordinates":[8.6691303253,50.088508606],"type":"Point"}
}