{
  "type": "Feature",
  "properties": {
    "iso:country":"DE",
    "sg:address":"Godorfer Hauptstr. 41",
    "sg:city":"K\u00f6ln",
    "sg:phone":"+49 2236/82139",
    "sg:postcode":"50997",
    "sg:province":"Nordrhein-Westfalen",
    "wof:name":"Schilder Schuh E. K.",
    "wof:placetype":"venue"
},
  "geometry": {"coordinates":[6.974537,50.857685],"type":"Point"}
}