{
  "type": "Feature",
  "properties": {
    "iso:country":"DE",
    "sg:address":"Benzstr. 3",
    "sg:city":"Aalen",
    "sg:phone":"+49 7361/45681",
    "sg:postcode":"73431",
    "sg:province":"Baden-W\u00fcrttemberg",
    "wof:name":"Soydinc",
    "wof:placetype":"venue"
},
  "geometry": {"coordinates":[10.0700139999,48.8258666992],"type":"Point"}
}