{
  "type": "Feature",
  "properties": {
    "iso:country":"DE",
    "sg:address":"Bochumer Str. 7",
    "sg:city":"Wuppertal",
    "sg:phone":"+49 202/660408",
    "sg:postcode":"42279",
    "sg:province":"Nordrhein-Westfalen",
    "wof:name":"Druckluft-anlagen Heckhoff Gmbh",
    "wof:placetype":"venue"
},
  "geometry": {"coordinates":[7.248033,51.297215],"type":"Point"}
}