{
  "type": "Feature",
  "properties": {
    "iso:country":"DE",
    "sg:address":"Neckarauer Str. 34",
    "sg:city":"Mannheim",
    "sg:phone":"+49 621/858620",
    "sg:postcode":"68199",
    "sg:province":"Baden-W\u00fcrttemberg",
    "wof:name":"Lianne Reiss Rechtsanw\u00e4ltin",
    "wof:placetype":"venue"
},
  "geometry": {"coordinates":[8.4920597076,49.4594306946],"type":"Point"}
}