{
  "type": "Feature",
  "properties": {
    "iso:country":"DE",
    "sg:address":"Marienstr. 32",
    "sg:city":"Hannover",
    "sg:phone":"+49 511/816661",
    "sg:postcode":"30171",
    "sg:province":"Niedersachsen",
    "wof:name":"Dagmar Engelbrecht",
    "wof:placetype":"venue"
},
  "geometry": {"coordinates":[9.7475004196,52.3690299988],"type":"Point"}
}