{
  "type": "Feature",
  "properties": {
    "iso:country":"DE",
    "sg:address":"Drochterser Str. 3",
    "sg:city":"Drochtersen",
    "sg:phone":"+49 4143/1440",
    "sg:postcode":"21706",
    "sg:province":"Niedersachsen",
    "wof:name":"Kehdinger Fotolabor Zielke Ohg",
    "wof:placetype":"venue"
},
  "geometry": {"coordinates":[9.3598918915,53.6761322021],"type":"Point"}
}