{
  "type": "Feature",
  "properties": {
    "iso:country":"DE",
    "sg:address":"Sommerberg Str. 3",
    "sg:city":"Suhl",
    "sg:phone":"+49 4936/8139520",
    "sg:postcode":"98529",
    "sg:province":"Th\u00fcringen",
    "wof:name":"Abc Floristik Berthold Michalski",
    "wof:placetype":"venue"
},
  "geometry": {"coordinates":[10.70555,50.580524],"type":"Point"}
}