{
  "type": "Feature",
  "properties": {
    "iso:country":"DE",
    "sg:address":"Zweite Gewanne 28",
    "sg:city":"Dormagen",
    "sg:phone":"+49 2133/80303",
    "sg:postcode":"41540",
    "sg:province":"Nordrhein-Westfalen",
    "wof:name":"Adolf Rohde Gmbh Bauunternehmen",
    "wof:placetype":"venue"
},
  "geometry": {"coordinates":[6.781968,51.077194],"type":"Point"}
}