{
  "type": "Feature",
  "properties": {
    "iso:country":"DE",
    "sg:address":"K\u00f6nigsberger Str. 3 a",
    "sg:city":"Northeim",
    "sg:phone":"+49 5551/2491",
    "sg:postcode":"37154",
    "sg:province":"Niedersachsen",
    "wof:name":"Elektro-voss Gmbh",
    "wof:placetype":"venue"
},
  "geometry": {"coordinates":[9.988038,51.698647],"type":"Point"}
}