{
  "type": "Feature",
  "properties": {
    "iso:country":"DE",
    "sg:address":"Tauernstr. 6",
    "sg:city":"Wiesbaden",
    "sg:phone":"+49 611/465140",
    "sg:postcode":"65199",
    "sg:province":"Hessen",
    "wof:name":"Dieter Bohlig Ingenieur",
    "wof:placetype":"venue"
},
  "geometry": {"coordinates":[8.1935482025,50.086769104],"type":"Point"}
}