{
  "type": "Feature",
  "properties": {
    "iso:country":"DE",
    "sg:address":"R\u00f6hrstr. 7",
    "sg:city":"Ober-Ramstadt",
    "sg:phone":"+49 4961/546390",
    "sg:postcode":"64372",
    "sg:province":"Hessen",
    "wof:name":"Partner - Gmbh Verbund F. Reifenfachh\u00c4ndler",
    "wof:placetype":"venue"
},
  "geometry": {"coordinates":[8.7549772263,49.8206558228],"type":"Point"}
}