{
  "type": "Feature",
  "properties": {
    "iso:country":"DE",
    "sg:address":"Am Kirchberg 16",
    "sg:city":"Neus\u00e4\u00df",
    "sg:phone":"+49 821/483253",
    "sg:postcode":"86356",
    "sg:province":"Bayern",
    "wof:name":"Heinrich Pfaud Ing. Agr.",
    "wof:placetype":"venue"
},
  "geometry": {"coordinates":[10.796237,48.388321],"type":"Point"}
}