{
  "type": "Feature",
  "properties": {
    "iso:country":"DE",
    "sg:address":"Treiberstr. 9",
    "sg:city":"Wedemark",
    "sg:phone":"+49 5130/3844",
    "sg:postcode":"30900",
    "sg:province":"Niedersachsen",
    "wof:name":"Friedrich Meine-hapke",
    "wof:placetype":"venue"
},
  "geometry": {"coordinates":[9.690044,52.584377],"type":"Point"}
}