{
  "type": "Feature",
  "properties": {
    "iso:country":"DE",
    "sg:address":"Otto-Lilienthal-Str. 14g",
    "sg:city":"Dinslaken",
    "sg:phone":"+49 2064/43850",
    "sg:postcode":"46539",
    "sg:province":"Nordrhein-Westfalen",
    "wof:name":"Brenner & Co. Pijpleidingsbouw Gmbh",
    "wof:placetype":"venue"
},
  "geometry": {"coordinates":[6.7543821335,51.5645294189],"type":"Point"}
}