{
  "type": "Feature",
  "properties": {
    "iso:country":"DE",
    "sg:address":"Gerstedter Weg",
    "sg:city":"Salzwedel",
    "sg:postcode":"29410",
    "sg:province":"Sachsen-Anhalt",
    "wof:name":"Fritz Tack",
    "wof:placetype":"venue"
},
  "geometry": {"coordinates":[11.12894,52.852779],"type":"Point"}
}