{
  "type": "Feature",
  "properties": {
    "iso:country":"DE",
    "sg:address":"Gustav-Ullrich-Str. 13",
    "sg:city":"Bellheim",
    "sg:phone":"+49 7272/2430",
    "sg:postcode":"76756",
    "sg:province":"Rheinland-Pfalz",
    "wof:name":"Gottfried Reichling",
    "wof:placetype":"venue"
},
  "geometry": {"coordinates":[8.288213,49.189121],"type":"Point"}
}