{
  "type": "Feature",
  "properties": {
    "iso:country":"DE",
    "sg:address":"Alte Str. 8",
    "sg:city":"Fuchsm\u00fchl",
    "sg:phone":"+49 9634/8338",
    "sg:postcode":"95689",
    "sg:province":"Bayern",
    "wof:name":"Roswitha Lippert",
    "wof:placetype":"venue"
},
  "geometry": {"coordinates":[12.148938179,49.9191970825],"type":"Point"}
}