{
  "type": "Feature",
  "properties": {
    "iso:country":"DE",
    "sg:address":"Am Geiersbach 7",
    "sg:city":"Wunsiedel",
    "sg:phone":"+49 9232/1041",
    "sg:postcode":"95632",
    "sg:province":"Bayern",
    "wof:name":"Speditionsgesellschaft Westmark Gmbh",
    "wof:placetype":"venue"
},
  "geometry": {"coordinates":[11.9657335281,50.0233955383],"type":"Point"}
}