{
  "type": "Feature",
  "properties": {
    "iso:country":"DE",
    "sg:address":"Schwedenweg 6",
    "sg:city":"L\u00fcbstorf",
    "sg:phone":"+49 3867/6786",
    "sg:postcode":"19069",
    "sg:province":"Mecklenburg-Vorpommern",
    "wof:name":"Dr. Med. A. Stieber-schmidt",
    "wof:placetype":"venue"
},
  "geometry": {"coordinates":[11.4021501541,53.7274894714],"type":"Point"}
}