{
  "type": "Feature",
  "properties": {
    "iso:country":"DE",
    "sg:address":"Dgz-Ring 7",
    "sg:city":"Berlin",
    "sg:phone":"+49 4930/4710532",
    "sg:postcode":"13086",
    "sg:province":"Berlin",
    "wof:name":"Mitsubishi Elektric Europe Gmbh",
    "wof:placetype":"venue"
},
  "geometry": {"coordinates":[13.439826,52.559025],"type":"Point"}
}