{
  "type": "Feature",
  "properties": {
    "iso:country":"DE",
    "sg:address":"Carl-Holtschneider-Str. 22",
    "sg:city":"Dortmund",
    "sg:postcode":"44145",
    "sg:province":"Nordrhein-Westfalen",
    "wof:name":"Huana-home.htm",
    "wof:placetype":"venue"
},
  "geometry": {"coordinates":[7.461906,51.528793],"type":"Point"}
}