{
  "type": "Feature",
  "properties": {
    "iso:country":"DE",
    "sg:address":"Am Knick 20",
    "sg:city":"Oststeinbek",
    "sg:phone":"+49 40/7122025",
    "sg:postcode":"22113",
    "sg:province":"Schleswig-Holstein",
    "wof:name":"Hans Gottsberg Gmbh",
    "wof:placetype":"venue"
},
  "geometry": {"coordinates":[10.159539,53.551914],"type":"Point"}
}