{
  "type": "Feature",
  "properties": {
    "iso:country":"DE",
    "sg:address":"Oberdorf 9",
    "sg:city":"Nentershausen",
    "sg:phone":"+49 6627/245",
    "sg:postcode":"36214",
    "sg:province":"Hessen",
    "wof:name":"Gastst\u00e4tte Georg Landgrebe",
    "wof:placetype":"venue"
},
  "geometry": {"coordinates":[7.9321341515,50.4218482971],"type":"Point"}
}