{
  "type": "Feature",
  "properties": {
    "iso:country":"DE",
    "sg:address":"Hermannstr. 151",
    "sg:city":"Berlin",
    "sg:phone":"+49 30/6251523",
    "sg:postcode":"12051",
    "sg:province":"Berlin",
    "wof:name":"New-china",
    "wof:placetype":"venue"
},
  "geometry": {"coordinates":[13.4326620102,52.4655685425],"type":"Point"}
}