{
  "type": "Feature",
  "properties": {
    "iso:country":"DE",
    "sg:address":"Dietringer Str. 26",
    "sg:city":"Rieden",
    "sg:phone":"+49 8362/1605",
    "sg:postcode":"87669",
    "sg:province":"Bayern",
    "wof:name":"Max Streif",
    "wof:placetype":"venue"
},
  "geometry": {"coordinates":[10.71444,47.619541],"type":"Point"}
}