{
  "type": "Feature",
  "properties": {
    "iso:country":"DE",
    "sg:address":"Erzbach 2",
    "sg:city":"Biberach",
    "sg:phone":"+49 7835/7424",
    "sg:postcode":"77781",
    "sg:province":"Baden-W\u00fcrttemberg",
    "wof:name":"Georg Huber",
    "wof:placetype":"venue"
},
  "geometry": {"coordinates":[8.013166,48.343018],"type":"Point"}
}