{
  "type": "Feature",
  "properties": {
    "iso:country":"DE",
    "sg:address":"Butzentalweg 22",
    "sg:city":"Ulm",
    "sg:phone":"+49 7304/7540",
    "sg:postcode":"89081",
    "sg:province":"Baden-W\u00fcrttemberg",
    "wof:name":"Tiefenbach Immobilienmakler",
    "wof:placetype":"venue"
},
  "geometry": {"coordinates":[9.9011144638,48.3801269531],"type":"Point"}
}