{
  "type": "Feature",
  "properties": {
    "iso:country":"DE",
    "sg:address":"Wolfgang-Zimmerer-Str. 4",
    "sg:city":"Neufahrn",
    "sg:phone":"+49 89/9919130",
    "sg:postcode":"85375",
    "sg:province":"Bayern",
    "wof:name":"Druckerei Gerber & Ulleweit Gmbh",
    "wof:placetype":"venue"
},
  "geometry": {"coordinates":[11.7480783463,48.1523475647],"type":"Point"}
}