{
  "type": "Feature",
  "properties": {
    "iso:country":"DE",
    "sg:address":"Ludwigstr. 39",
    "sg:city":"L\u00fcbbecke",
    "sg:phone":"+49 5741/20964",
    "sg:postcode":"32312",
    "sg:province":"Nordrhein-Westfalen",
    "wof:name":"Andreas Bayer Finanzberater",
    "wof:placetype":"venue"
},
  "geometry": {"coordinates":[8.6063365936,52.314666748],"type":"Point"}
}