{
  "type": "Feature",
  "properties": {
    "iso:country":"DE",
    "sg:address":"Bahnhofstr. 73",
    "sg:city":"Mammendorf",
    "sg:phone":"+49 8145/232",
    "sg:postcode":"82291",
    "sg:province":"Bayern",
    "wof:name":"Selmayr & S\u00f6hne Gmbh",
    "wof:placetype":"venue"
},
  "geometry": {"coordinates":[11.1729335785,48.2122993469],"type":"Point"}
}