{
  "type": "Feature",
  "properties": {
    "iso:country":"DE",
    "sg:address":"Sambachweg 5",
    "sg:city":"Schweinfurt",
    "sg:phone":"+49 9721/33503",
    "sg:postcode":"97422",
    "sg:province":"Bayern",
    "wof:name":"Karl-heinz Pfister",
    "wof:placetype":"venue"
},
  "geometry": {"coordinates":[10.2518997192,50.0696754456],"type":"Point"}
}