{
  "type": "Feature",
  "properties": {
    "iso:country":"DE",
    "sg:address":"Hopfenweg 11",
    "sg:city":"Ro\u00dftal",
    "sg:phone":"+49 9127/9261",
    "sg:postcode":"90574",
    "sg:province":"Bayern",
    "wof:name":"Anni Peipp",
    "wof:placetype":"venue"
},
  "geometry": {"coordinates":[10.87589,49.396858],"type":"Point"}
}