{
  "type": "Feature",
  "properties": {
    "iso:country":"DE",
    "sg:address":"Hebbelstr. 9",
    "sg:city":"R\u00f6srath",
    "sg:phone":"+49 2205/3632",
    "sg:postcode":"51503",
    "sg:province":"Nordrhein-Westfalen",
    "wof:name":"H\u00fcttl Gmbh",
    "wof:placetype":"venue"
},
  "geometry": {"coordinates":[7.1731328964,50.8966789246],"type":"Point"}
}