{
  "type": "Feature",
  "properties": {
    "iso:country":"DE",
    "sg:address":"Austr. 1",
    "sg:city":"Augsburg",
    "sg:phone":"+49 821/412047",
    "sg:postcode":"86153",
    "sg:province":"Bayern",
    "wof:name":"Gebr. Gleich Ohg",
    "wof:placetype":"venue"
},
  "geometry": {"coordinates":[10.887501,48.385738],"type":"Point"}
}