{
  "type": "Feature",
  "properties": {
    "iso:country":"DE",
    "sg:address":"Hauptstr. 24",
    "sg:city":"Triebes",
    "sg:postcode":"07950",
    "sg:province":"Th\u00fcringen",
    "wof:name":"Transconsult Gmbh",
    "wof:placetype":"venue"
},
  "geometry": {"coordinates":[12.0207500458,50.6845855713],"type":"Point"}
}