{
  "type": "Feature",
  "properties": {
    "iso:country":"DE",
    "sg:address":"Luisenstr. 3",
    "sg:city":"Br\u00fchl",
    "sg:postcode":"50321",
    "sg:province":"Nordrhein-Westfalen",
    "wof:name":"Moldenhauer & Cie. Immobilien Gmbh",
    "wof:placetype":"venue"
},
  "geometry": {"coordinates":[8.5344495773,49.3973236084],"type":"Point"}
}