{
  "type": "Feature",
  "properties": {
    "iso:country":"DE",
    "sg:address":"Siedlung 13",
    "sg:city":"Oldendorf",
    "sg:postcode":"21726",
    "sg:province":"Niedersachsen",
    "wof:name":"Pankau Service Gmbh",
    "wof:placetype":"venue"
},
  "geometry": {"coordinates":[9.278676,53.564194],"type":"Point"}
}