{
  "type": "Feature",
  "properties": {
    "iso:country":"DE",
    "sg:address":"Im Rothkopf 9",
    "sg:city":"Oberursel",
    "sg:postcode":"61440",
    "sg:province":"Hessen",
    "wof:name":"Amiapo Gmbh",
    "wof:placetype":"venue"
},
  "geometry": {"coordinates":[8.5480833054,50.2173538208],"type":"Point"}
}