{
  "type": "Feature",
  "properties": {
    "iso:country":"DE",
    "sg:address":"Ludwigsluster Chaussee 1",
    "sg:city":"Parchim",
    "sg:phone":"+49 3871/414525",
    "sg:postcode":"19370",
    "sg:province":"Mecklenburg-Vorpommern",
    "wof:name":"Norddeutsche Saat- Und Pflanzgut Ag",
    "wof:placetype":"venue"
},
  "geometry": {"coordinates":[11.816206,53.426079],"type":"Point"}
}