{
  "type": "Feature",
  "properties": {
    "iso:country":"DE",
    "sg:address":"Kirchplatz 2",
    "sg:city":"Liebenau",
    "sg:phone":"+49 5676/1718",
    "sg:postcode":"34396",
    "sg:province":"Hessen",
    "wof:name":"Ratskeller Inh. Ingeborg Richts",
    "wof:placetype":"venue"
},
  "geometry": {"coordinates":[9.2823057175,51.4959793091],"type":"Point"}
}