{
  "type": "Feature",
  "properties": {
    "iso:country":"DE",
    "sg:address":"Gem\u00fcnden",
    "sg:city":"Gem\u00fcnden",
    "sg:phone":"+49 9351/800247",
    "sg:postcode":"97737",
    "sg:province":"Bayern",
    "wof:name":"Raiffeisenbank Gem\u00fcnden & Umgebung",
    "wof:placetype":"venue"
},
  "geometry": {"coordinates":[9.67295,50.053631],"type":"Point"}
}