{
  "type": "Feature",
  "properties": {
    "iso:country":"DE",
    "sg:address":"Obentrautstr. 36",
    "sg:city":"Berlin",
    "sg:phone":"+49 30/2167652",
    "sg:postcode":"10963",
    "sg:province":"Berlin",
    "wof:name":"Dr. Oscar Frohne Ingenieur",
    "wof:placetype":"venue"
},
  "geometry": {"coordinates":[13.384979248,52.4968185425],"type":"Point"}
}