{
  "type": "Feature",
  "properties": {
    "iso:country":"DE",
    "sg:address":"Hasen\u00e4ckerstr. 43",
    "sg:city":"Leutenbach",
    "sg:phone":"+49 7195/92880",
    "sg:postcode":"71397",
    "sg:province":"Baden-W\u00fcrttemberg",
    "wof:name":"Kurt Messmer",
    "wof:placetype":"venue"
},
  "geometry": {"coordinates":[9.3662548065,48.8959960938],"type":"Point"}
}