{
  "type": "Feature",
  "properties": {
    "iso:country":"DE",
    "sg:address":"Hohenstaufenrg. 42",
    "sg:city":"K\u00f6ln",
    "sg:phone":"+49 4922/1339010",
    "sg:postcode":"50674",
    "sg:province":"Nordrhein-Westfalen",
    "wof:name":"Oliver Schrott Kommunikation Gmbh",
    "wof:placetype":"venue"
},
  "geometry": {"coordinates":[6.94059,50.932247],"type":"Point"}
}