{
  "type": "Feature",
  "properties": {
    "iso:country":"DE",
    "sg:address":"Michelsheide 3",
    "sg:city":"Kempen",
    "sg:phone":"+49 2845/8227",
    "sg:postcode":"47906",
    "sg:province":"Nordrhein-Westfalen",
    "wof:name":"Peter G\u00e4tjen Architekt",
    "wof:placetype":"venue"
},
  "geometry": {"coordinates":[6.510549,51.411739],"type":"Point"}
}