{
  "type": "Feature",
  "properties": {
    "iso:country":"DE",
    "sg:address":"Huckarder Str. 114",
    "sg:city":"Dortmund",
    "sg:phone":"+49 231/7214407",
    "sg:postcode":"44147",
    "sg:province":"Nordrhein-Westfalen",
    "wof:name":"Peter Schwickert E. K.",
    "wof:placetype":"venue"
},
  "geometry": {"coordinates":[7.4299340248,51.5197753906],"type":"Point"}
}