{
  "type": "Feature",
  "properties": {
    "iso:country":"DE",
    "sg:address":"Hauptstr. 229",
    "sg:city":"Heiligenhaus",
    "sg:phone":"+49 2056/60068",
    "sg:postcode":"42579",
    "sg:province":"Nordrhein-Westfalen",
    "wof:name":"Harald Schulz",
    "wof:placetype":"venue"
},
  "geometry": {"coordinates":[6.9645929337,51.3252563477],"type":"Point"}
}