{
  "type": "Feature",
  "properties": {
    "iso:country":"DE",
    "sg:address":"Hadenbrok 10",
    "sg:city":"Reken",
    "sg:phone":"+49 2863/8103",
    "sg:postcode":"48734",
    "sg:province":"Nordrhein-Westfalen",
    "wof:name":"Richard Moschner",
    "wof:placetype":"venue"
},
  "geometry": {"coordinates":[7.052941,51.881538],"type":"Point"}
}