{
  "type": "Feature",
  "properties": {
    "iso:country":"DE",
    "sg:address":"Hauptstr. 48",
    "sg:city":"Eisenach",
    "sg:phone":"+49 3691/892507",
    "sg:postcode":"99817",
    "sg:province":"Th\u00fcringen",
    "wof:name":"M. M\u00f6nner",
    "wof:placetype":"venue"
},
  "geometry": {"coordinates":[10.308033,51.005146],"type":"Point"}
}