{
  "type": "Feature",
  "properties": {
    "iso:country":"DE",
    "sg:address":"Bornsiepen 3",
    "sg:city":"Remscheid",
    "sg:phone":"+49 2191/388933",
    "sg:postcode":"42859",
    "sg:province":"Nordrhein-Westfalen",
    "wof:name":"Provinzial Versicherung J. Sauer",
    "wof:placetype":"venue"
},
  "geometry": {"coordinates":[7.2269058228,51.1720733643],"type":"Point"}
}