{
  "type": "Feature",
  "properties": {
    "iso:country":"DE",
    "sg:address":"Poststr. 2-4",
    "sg:city":"Bad Mergentheim",
    "sg:postcode":"97980",
    "sg:province":"Baden-W\u00fcrttemberg",
    "wof:name":"Victroria Weine Otto Geisel E. K.",
    "wof:placetype":"venue"
},
  "geometry": {"coordinates":[9.7719869614,49.4932594299],"type":"Point"}
}