{
  "type": "Feature",
  "properties": {
    "iso:country":"DE",
    "sg:address":"Kurt-Bittel-Str. 8",
    "sg:city":"Heidenheim",
    "sg:postcode":"89518",
    "sg:province":"Baden-W\u00fcrttemberg",
    "wof:name":"Albrecht Buchwald",
    "wof:placetype":"venue"
},
  "geometry": {"coordinates":[10.1539640427,48.6807785034],"type":"Point"}
}