{
  "type": "Feature",
  "properties": {
    "iso:country":"DE",
    "sg:address":"Postfach 1164:: 35448 Heuchelheim:: Germany.^^Jahnstr 4-8::",
    "sg:city":"Heuchelheim",
    "sg:phone":"+49 641/60560",
    "sg:postcode":"35452",
    "sg:province":"Hessen",
    "wof:name":"Volksbank Heuchelheim Eg",
    "wof:placetype":"venue"
},
  "geometry": {"coordinates":[8.631212,50.584152],"type":"Point"}
}