{
  "type": "Feature",
  "properties": {
    "iso:country":"DE",
    "sg:address":"Im Dorfe 1",
    "sg:city":"Frielendorf",
    "sg:phone":"+49 5684/7484",
    "sg:postcode":"34621",
    "sg:province":"Hessen",
    "wof:name":"Kutscher Keller",
    "wof:placetype":"venue"
},
  "geometry": {"coordinates":[9.2998628616,50.9758224487],"type":"Point"}
}