{
  "type": "Feature",
  "properties": {
    "iso:country":"DE",
    "sg:address":"Baumschulallee 39",
    "sg:city":"Bonn",
    "sg:postcode":"53115",
    "sg:province":"Nordrhein-Westfalen",
    "wof:name":"Contrast Plakat Service Verwaltungs Gmbh",
    "wof:placetype":"venue"
},
  "geometry": {"coordinates":[7.091902,50.730774],"type":"Point"}
}