{
  "type": "Feature",
  "properties": {
    "iso:country":"DE",
    "sg:address":"Buchholz 11",
    "sg:city":"Sundern",
    "sg:phone":"+49 2933/780220",
    "sg:postcode":"59846",
    "sg:province":"Nordrhein-Westfalen",
    "wof:name":"Brisant Beschlag",
    "wof:placetype":"venue"
},
  "geometry": {"coordinates":[7.991523,51.323044],"type":"Point"}
}