{
  "type": "Feature",
  "properties": {
    "iso:country":"DE",
    "sg:address":"Sadelerstr. 1",
    "sg:city":"M\u00fcnchen",
    "sg:phone":"+49 89/1571905",
    "sg:postcode":"80638",
    "sg:province":"Bayern",
    "wof:name":"Monika Ott",
    "wof:placetype":"venue"
},
  "geometry": {"coordinates":[11.52047,48.164413],"type":"Point"}
}