{
  "type": "Feature",
  "properties": {
    "iso:country":"DE",
    "sg:address":"Gewerbestra\u00dfe 6",
    "sg:city":"Rummingen",
    "sg:phone":"+49 7621/84712",
    "sg:postcode":"79595",
    "sg:province":"Baden-W\u00fcrttemberg",
    "wof:name":"B\u00f6hringer U. Schw\u00f6ble Gmbh Automatendreherei",
    "wof:placetype":"venue"
},
  "geometry": {"coordinates":[7.638010025,47.6414527893],"type":"Point"}
}