{
  "type": "Feature",
  "properties": {
    "iso:country":"DE",
    "sg:address":"Schlo\u00dfstr. 12",
    "sg:city":"Schwerin",
    "sg:phone":"+49 385/591450",
    "sg:postcode":"19053",
    "sg:province":"Mecklenburg-Vorpommern",
    "wof:name":"Drk-projektgruppe Nord Gmbh",
    "wof:placetype":"venue"
},
  "geometry": {"coordinates":[11.414445,53.627296],"type":"Point"}
}