{
  "type": "Feature",
  "properties": {
    "iso:country":"DE",
    "sg:address":"Am Ziegelholz 17",
    "sg:city":"M\u00f6lln",
    "sg:phone":"+49 4542/87798",
    "sg:postcode":"23879",
    "sg:province":"Schleswig-Holstein",
    "wof:name":"Holger Burmester",
    "wof:placetype":"venue"
},
  "geometry": {"coordinates":[10.6832208633,53.6332054138],"type":"Point"}
}