{
  "type": "Feature",
  "properties": {
    "iso:country":"DE",
    "sg:address":"Ebertusstr. 10",
    "sg:city":"Frankfurt",
    "sg:phone":"+49 335/504906",
    "sg:postcode":"15234",
    "sg:province":"Brandenburg",
    "wof:name":"Oder-trans Rogall Gmbh",
    "wof:placetype":"venue"
},
  "geometry": {"coordinates":[14.5377063751,52.3411865234],"type":"Point"}
}