{
  "type": "Feature",
  "properties": {
    "iso:country":"DE",
    "sg:address":"Heimerichstr. 7",
    "sg:city":"N\u00fcrnberg",
    "sg:phone":"+49 911/993300",
    "sg:postcode":"90419",
    "sg:province":"Bayern",
    "wof:name":"Michael-bauer-heim",
    "wof:placetype":"venue"
},
  "geometry": {"coordinates":[11.066384,49.463581],"type":"Point"}
}