{
  "type": "Feature",
  "properties": {
    "iso:country":"DE",
    "sg:address":"K\u00f6nigstr. 47",
    "sg:city":"Rottenburg",
    "sg:phone":"+49 7472/25700",
    "sg:postcode":"72108",
    "sg:province":"Baden-W\u00fcrttemberg",
    "wof:name":"Karin Widmaier",
    "wof:placetype":"venue"
},
  "geometry": {"coordinates":[8.9323034286,48.4756622314],"type":"Point"}
}