{
  "type": "Feature",
  "properties": {
    "iso:country":"DE",
    "sg:address":"Raiffeisenstr. 7",
    "sg:city":"Usingen",
    "sg:phone":"+49 6081/66916",
    "sg:postcode":"61250",
    "sg:province":"Hessen",
    "wof:name":"Mora Transformatoren Gmbh",
    "wof:placetype":"venue"
},
  "geometry": {"coordinates":[8.5226984024,50.3319511414],"type":"Point"}
}