{
  "type": "Feature",
  "properties": {
    "iso:country":"DE",
    "sg:address":"Sudetenstr. 13",
    "sg:city":"Geretsried",
    "sg:phone":"+49 8171/31273",
    "sg:postcode":"82538",
    "sg:province":"Bayern",
    "wof:name":"Stern-apotheke",
    "wof:placetype":"venue"
},
  "geometry": {"coordinates":[11.483156,47.85841],"type":"Point"}
}