{
  "type": "Feature",
  "properties": {
    "iso:country":"DE",
    "sg:address":"Reckr\u00f6der Weg 9",
    "sg:city":"Eiterfeld",
    "sg:phone":"+49 6672/215",
    "sg:postcode":"36132",
    "sg:province":"Hessen",
    "wof:name":"Zur Sonne",
    "wof:placetype":"venue"
},
  "geometry": {"coordinates":[9.7839479446,50.7641830444],"type":"Point"}
}