{
  "type": "Feature",
  "properties": {
    "iso:country":"DE",
    "sg:address":"Basler Str. 88",
    "sg:city":"Freiburg",
    "sg:postcode":"79115",
    "sg:province":"Baden-W\u00fcrttemberg",
    "wof:name":"Freiburger Presseball Gmbh",
    "wof:placetype":"venue"
},
  "geometry": {"coordinates":[7.828957,47.985336],"type":"Point"}
}