{
  "type": "Feature",
  "properties": {
    "iso:country":"DE",
    "sg:address":"Fliegerstr. 1",
    "sg:city":"Hannover",
    "sg:phone":"+49 511/630014",
    "sg:postcode":"30179",
    "sg:province":"Niedersachsen",
    "wof:name":"Data Elektronik Gmbh",
    "wof:placetype":"venue"
},
  "geometry": {"coordinates":[9.7364816666,52.412940979],"type":"Point"}
}