{
  "type": "Feature",
  "properties": {
    "iso:country":"DE",
    "sg:address":"Ostring",
    "sg:city":"Rottendorf",
    "sg:postcode":"97228",
    "sg:province":"Bayern",
    "wof:name":"Texlog Gmbh",
    "wof:placetype":"venue"
},
  "geometry": {"coordinates":[10.036887,49.791767],"type":"Point"}
}