{
  "type": "Feature",
  "properties": {
    "iso:country":"DE",
    "sg:address":"Kaltenborner Str. 172",
    "sg:city":"Guben",
    "sg:phone":"+49 3561/3396",
    "sg:postcode":"03172",
    "sg:province":"Brandenburg",
    "wof:name":"Kr\u00e4henbusch",
    "wof:placetype":"venue"
},
  "geometry": {"coordinates":[14.6938896179,51.9377784729],"type":"Point"}
}