{
  "type": "Feature",
  "properties": {
    "iso:country":"DE",
    "sg:address":"Sch\u00fctzenwaldweg 7la",
    "sg:city":"L\u00f6rrach",
    "sg:phone":"+49 7621/82793",
    "sg:postcode":"79540",
    "sg:province":"Baden-W\u00fcrttemberg",
    "wof:name":"Biehler Sailer & Co. Gmbh",
    "wof:placetype":"venue"
},
  "geometry": {"coordinates":[7.666329,47.60939],"type":"Point"}
}