{
  "type": "Feature",
  "properties": {
    "iso:country":"DE",
    "sg:address":"Niendorfer Marktplatz 5a",
    "sg:city":"Hamburg",
    "sg:phone":"+49 40/585845",
    "sg:postcode":"22459",
    "sg:province":"Hamburg",
    "wof:name":"L.a.s Pizza Drive",
    "wof:placetype":"venue"
},
  "geometry": {"coordinates":[9.949606,53.617706],"type":"Point"}
}