{
  "type": "Feature",
  "properties": {
    "iso:country":"DE",
    "sg:address":"Westend 36",
    "sg:city":"Bocholt",
    "sg:phone":"+49 2871/27710",
    "sg:postcode":"46399",
    "sg:province":"Nordrhein-Westfalen",
    "wof:name":"Unis Verwaltungsges. Mbh",
    "wof:placetype":"venue"
},
  "geometry": {"coordinates":[6.6040091515,51.8394584656],"type":"Point"}
}