{
  "type": "Feature",
  "properties": {
    "iso:country":"DE",
    "sg:address":"Hauptstr. 67",
    "sg:city":"B\u00f6hl-Iggelheim",
    "sg:phone":"+49 6324/64234",
    "sg:postcode":"67459",
    "sg:province":"Rheinland-Pfalz",
    "wof:name":"Eisdiele Rimini",
    "wof:placetype":"venue"
},
  "geometry": {"coordinates":[8.296157,49.386375],"type":"Point"}
}