{
  "type": "Feature",
  "properties": {
    "iso:country":"DE",
    "sg:address":"Kronacher Str. 50",
    "sg:city":"Bamberg",
    "sg:phone":"+49 951/47027",
    "sg:postcode":"96052",
    "sg:province":"Bayern",
    "wof:name":"Heinrich Wetz",
    "wof:placetype":"venue"
},
  "geometry": {"coordinates":[10.9042568207,49.9205169678],"type":"Point"}
}