{
  "type": "Feature",
  "properties": {
    "iso:country":"DE",
    "sg:address":"Arnold-Zweig-Str. 1",
    "sg:city":"Halle",
    "sg:phone":"+49 345/6949674",
    "sg:postcode":"06126",
    "sg:province":"Sachsen-Anhalt",
    "wof:name":"Dieter Weber",
    "wof:placetype":"venue"
},
  "geometry": {"coordinates":[11.90389,51.475765],"type":"Point"}
}