{
  "type": "Feature",
  "properties": {
    "iso:country":"DE",
    "sg:address":"Thaliaweg 13",
    "sg:city":"Berlin",
    "sg:phone":"+49 30/76680007",
    "sg:postcode":"12249",
    "sg:province":"Berlin",
    "wof:name":"Gustav Rosenke Gmbh",
    "wof:placetype":"venue"
},
  "geometry": {"coordinates":[13.345111,52.434319],"type":"Point"}
}