{
  "type": "Feature",
  "properties": {
    "iso:country":"DE",
    "sg:address":"Altenaustr. 4",
    "sg:city":"Bad Pyrmont",
    "sg:phone":"+49 5281/2537",
    "sg:postcode":"31812",
    "sg:province":"Niedersachsen",
    "wof:name":"Detlef Schulz Steuerberater",
    "wof:placetype":"venue"
},
  "geometry": {"coordinates":[9.255777359,51.9849472046],"type":"Point"}
}