{
  "type": "Feature",
  "properties": {
    "iso:country":"DE",
    "sg:address":"Freiherr-vom-Stein-Allee 8",
    "sg:city":"Rheda-Wiedenbr\u00fcck",
    "sg:phone":"+49 5242/44523",
    "sg:postcode":"33378",
    "sg:province":"Nordrhein-Westfalen",
    "wof:name":"Agentur F\u00fcr Werbung Und Verkaufsf\u00f6rderung Gerhard Zink",
    "wof:placetype":"venue"
},
  "geometry": {"coordinates":[8.3155403137,51.8611297607],"type":"Point"}
}