{
  "type": "Feature",
  "properties": {
    "iso:country":"DE",
    "sg:address":"Freisinger Str. 2",
    "sg:city":"Mainburg",
    "sg:postcode":"84048",
    "sg:province":"Bayern",
    "wof:name":"Epikur Handels- Gmbh",
    "wof:placetype":"venue"
},
  "geometry": {"coordinates":[11.7796993256,48.6408348083],"type":"Point"}
}