{
  "type": "Feature",
  "properties": {
    "iso:country":"DE",
    "sg:address":"Holzweg 18",
    "sg:city":"Borgholzhausen",
    "sg:phone":"+49 5425/6619",
    "sg:postcode":"33829",
    "sg:province":"Nordrhein-Westfalen",
    "wof:name":"Heinrich Bu\u00dfmeyer",
    "wof:placetype":"venue"
},
  "geometry": {"coordinates":[8.22952,52.088501],"type":"Point"}
}