{
  "type": "Feature",
  "properties": {
    "iso:country":"DE",
    "sg:address":"Bruchstr. 54",
    "sg:city":"Gevelsberg",
    "sg:phone":"+49 2339/5955",
    "sg:postcode":"58285",
    "sg:province":"Nordrhein-Westfalen",
    "wof:name":"Neumann",
    "wof:placetype":"venue"
},
  "geometry": {"coordinates":[7.3115792274,51.3241195679],"type":"Point"}
}