{
  "type": "Feature",
  "properties": {
    "iso:country":"DE",
    "sg:address":"Kaiserstr. 31",
    "sg:city":"Minden",
    "sg:phone":"+49 571/36676",
    "sg:postcode":"32423",
    "sg:province":"Nordrhein-Westfalen",
    "wof:name":"Detektei Audesi E. Kfr.",
    "wof:placetype":"venue"
},
  "geometry": {"coordinates":[8.932267,52.289448],"type":"Point"}
}