{
  "type": "Feature",
  "properties": {
    "iso:country":"DE",
    "sg:address":"Hansgasse 1",
    "sg:city":"Crailsheim",
    "sg:phone":"+49 7951/8207",
    "sg:postcode":"74564",
    "sg:province":"Baden-W\u00fcrttemberg",
    "wof:name":"Hirsch",
    "wof:placetype":"venue"
},
  "geometry": {"coordinates":[10.0609426498,49.0938720703],"type":"Point"}
}