{
  "type": "Feature",
  "properties": {
    "iso:country":"DE",
    "sg:address":"Pr\u00e4sidentenstr. 46",
    "sg:city":"Bergkamen",
    "sg:phone":"+49 2307/82938",
    "sg:postcode":"59192",
    "sg:province":"Nordrhein-Westfalen",
    "wof:name":"Neckermann Reiseb\u00fcro",
    "wof:placetype":"venue"
},
  "geometry": {"coordinates":[7.6405358315,51.6208496094],"type":"Point"}
}