{
  "type": "Feature",
  "properties": {
    "iso:country":"DE",
    "sg:address":"R\u00fcgenwalder Str. 18",
    "sg:city":"Heiligenhafen",
    "sg:phone":"+49 4362/5878",
    "sg:postcode":"23774",
    "sg:province":"Schleswig-Holstein",
    "wof:name":"Seefahrerverein Heiligenhafen E. V.",
    "wof:placetype":"venue"
},
  "geometry": {"coordinates":[11.0102586746,54.3690567017],"type":"Point"}
}