{
  "type": "Feature",
  "properties": {
    "iso:country":"DE",
    "sg:address":"Ronnebergstr. 2 a",
    "sg:city":"L\u00fctjenburg",
    "sg:phone":"+49 4381/7425",
    "sg:postcode":"24321",
    "sg:province":"Schleswig-Holstein",
    "wof:name":"Helmut Schr\u00f6der Steuerberater",
    "wof:placetype":"venue"
},
  "geometry": {"coordinates":[10.5863866806,54.2899551392],"type":"Point"}
}