{
  "type": "Feature",
  "properties": {
    "iso:country":"DE",
    "sg:address":"Hildebrandstr. 16",
    "sg:city":"M\u00fcnchen",
    "sg:phone":"+49 89/155979",
    "sg:postcode":"80637",
    "sg:province":"Bayern",
    "wof:name":"Dipl.-ing. Gerhard H\u00f6fle Ingenieur Und Architekt",
    "wof:placetype":"venue"
},
  "geometry": {"coordinates":[11.535829,48.170616],"type":"Point"}
}