{
  "type": "Feature",
  "properties": {
    "iso:country":"DE",
    "sg:address":"Nr. 49",
    "sg:city":"Liebstedt",
    "sg:postcode":"99510",
    "sg:province":"Th\u00fcringen",
    "wof:name":"Ratskeller Liebstedt",
    "wof:placetype":"venue"
},
  "geometry": {"coordinates":[11.509604454,51.0231628418],"type":"Point"}
}