{
  "type": "Feature",
  "properties": {
    "iso:country":"DE",
    "sg:address":"Wa\u00dfmannsdorfer Chaussee 1",
    "sg:city":"Berlin",
    "sg:postcode":"12355",
    "sg:province":"Berlin",
    "wof:name":"Physio Med Gmbh",
    "wof:placetype":"venue"
},
  "geometry": {"coordinates":[13.4960317612,52.4150352478],"type":"Point"}
}