{
  "type": "Feature",
  "properties": {
    "iso:country":"DE",
    "sg:address":"Aachener Str. 32",
    "sg:city":"Wesseling",
    "sg:phone":"+49 2236/947472",
    "sg:postcode":"50389",
    "sg:province":"Nordrhein-Westfalen",
    "wof:name":"T. Frisch",
    "wof:placetype":"venue"
},
  "geometry": {"coordinates":[6.9650249481,50.8192596436],"type":"Point"}
}