{
  "type": "Feature",
  "properties": {
    "iso:country":"DE",
    "sg:address":"Neue Schulstr 27",
    "sg:city":"Ortenberg",
    "sg:phone":"+49 6046/940115",
    "sg:postcode":"63683",
    "sg:province":"Hessen",
    "wof:name":"Bergheimer Stahlhallen Konstruktions- U. Vertriebs Gmbh",
    "wof:placetype":"venue"
},
  "geometry": {"coordinates":[9.0899400711,50.3476486206],"type":"Point"}
}