{
  "type": "Feature",
  "properties": {
    "iso:country":"DE",
    "sg:address":"Karl-Schurz-Str. 10",
    "sg:city":"Paderborn",
    "sg:phone":"+49 5251/529225",
    "sg:postcode":"33100",
    "sg:province":"Nordrhein-Westfalen",
    "wof:name":"M. Kloht",
    "wof:placetype":"venue"
},
  "geometry": {"coordinates":[8.7869825363,51.7289276123],"type":"Point"}
}