{
  "type": "Feature",
  "properties": {
    "iso:country":"DE",
    "sg:address":"Asbach",
    "sg:city":"Rotthalm\u00fcnster",
    "sg:phone":"+49 8533/1612",
    "sg:postcode":"94094",
    "sg:province":"Bayern",
    "wof:name":"C. Und S. Streichsbier",
    "wof:placetype":"venue"
},
  "geometry": {"coordinates":[13.207108,48.394939],"type":"Point"}
}