{
  "type": "Feature",
  "properties": {
    "iso:country":"DE",
    "sg:address":"Stolberger Str 374",
    "sg:city":"K\u00f6ln",
    "sg:phone":"+49 221/49050",
    "sg:postcode":"50933",
    "sg:province":"Nordrhein-Westfalen",
    "wof:name":"Robert Bosch Gmbh",
    "wof:placetype":"venue"
},
  "geometry": {"coordinates":[6.884726,50.943172],"type":"Point"}
}