{
  "type": "Feature",
  "properties": {
    "iso:country":"DE",
    "sg:address":"Am Knill 25a",
    "sg:city":"Hamburg",
    "sg:phone":"+49 40/6433224",
    "sg:postcode":"22147",
    "sg:province":"Hamburg",
    "wof:name":"Enjoy The Movies M\u00e4nnel & M\u00f6ller Ohg",
    "wof:placetype":"venue"
},
  "geometry": {"coordinates":[10.1281318665,53.6059341431],"type":"Point"}
}