{
  "type": "Feature",
  "properties": {
    "iso:country":"DE",
    "sg:address":"Wichernstr. 3",
    "sg:city":"Rastatt",
    "sg:phone":"+49 7222/33317",
    "sg:postcode":"76437",
    "sg:province":"Baden-W\u00fcrttemberg",
    "wof:name":"Verein F\u00fcr Schiffsmodellbau Kurt Hetzel",
    "wof:placetype":"venue"
},
  "geometry": {"coordinates":[8.2048625946,48.8437461853],"type":"Point"}
}