{
  "type": "Feature",
  "properties": {
    "iso:country":"DE",
    "sg:address":"Vaihinger Markt 29",
    "sg:city":"Stuttgart",
    "sg:phone":"+49 711/7353145",
    "sg:postcode":"70563",
    "sg:province":"Baden-W\u00fcrttemberg",
    "wof:name":"Express",
    "wof:placetype":"venue"
},
  "geometry": {"coordinates":[9.1113653183,48.7302093506],"type":"Point"}
}