{
  "type": "Feature",
  "properties": {
    "iso:country":"DE",
    "sg:address":"Ringstr. 83",
    "sg:city":"Neuwied",
    "sg:phone":"+49 2631/357261",
    "sg:postcode":"56564",
    "sg:province":"Rheinland-Pfalz",
    "wof:name":"Gabriele Kr\u00fcger",
    "wof:placetype":"venue"
},
  "geometry": {"coordinates":[7.47409,50.436649],"type":"Point"}
}