{
  "type": "Feature",
  "properties": {
    "iso:country":"DE",
    "sg:address":"Burgunderweg 4",
    "sg:city":"Schriesheim",
    "sg:phone":"+49 6203/65283",
    "sg:postcode":"69198",
    "sg:province":"Baden-W\u00fcrttemberg",
    "wof:name":"R. Muley Architektin",
    "wof:placetype":"venue"
},
  "geometry": {"coordinates":[8.667554,49.469982],"type":"Point"}
}