{
  "type": "Feature",
  "properties": {
    "iso:country":"DE",
    "sg:address":"Vitusstr. 14",
    "sg:city":"M\u00f6nchengladbach",
    "sg:phone":"+49 2161/354570",
    "sg:postcode":"41061",
    "sg:province":"Nordrhein-Westfalen",
    "wof:name":"Jachmann Druck Gmbh",
    "wof:placetype":"venue"
},
  "geometry": {"coordinates":[6.432404,51.189457],"type":"Point"}
}