{
  "type": "Feature",
  "properties": {
    "iso:country":"DE",
    "sg:address":"Ohmstr. 5",
    "sg:city":"Dachau",
    "sg:phone":"+49 8131/10568",
    "sg:postcode":"85221",
    "sg:province":"Bayern",
    "wof:name":"Anton Gottschalk",
    "wof:placetype":"venue"
},
  "geometry": {"coordinates":[11.4764442444,48.2669487],"type":"Point"}
}