{
  "type": "Feature",
  "properties": {
    "iso:country":"DE",
    "sg:address":"Hindenburgstr. 3",
    "sg:city":"Delmenhorst",
    "sg:phone":"+49 4221/71430",
    "sg:postcode":"27751",
    "sg:province":"Niedersachsen",
    "wof:name":"Finnendahl Vergn\u00fcgungsbetriebe Gmbh",
    "wof:placetype":"venue"
},
  "geometry": {"coordinates":[8.67946,53.055511],"type":"Point"}
}