{
  "type": "Feature",
  "properties": {
    "iso:country":"DE",
    "sg:address":"Glockenberg 16",
    "sg:city":"Kirchdorf",
    "sg:phone":"+49 4273/1310",
    "sg:postcode":"27245",
    "sg:province":"Niedersachsen",
    "wof:name":"Gemeindeb\u00fccherei Mittelpunktschule",
    "wof:placetype":"venue"
},
  "geometry": {"coordinates":[8.840386,52.593872],"type":"Point"}
}