{
  "type": "Feature",
  "properties": {
    "iso:country":"DE",
    "sg:address":"Wallensteinstr. 4",
    "sg:city":"Erlangen",
    "sg:phone":"+49 9131/990730",
    "sg:postcode":"91056",
    "sg:province":"Bayern",
    "wof:name":"Renninger",
    "wof:placetype":"venue"
},
  "geometry": {"coordinates":[10.9528827667,49.5559921265],"type":"Point"}
}