{
  "type": "Feature",
  "properties": {
    "iso:country":"DE",
    "sg:address":"Wetzlarer Weg 1",
    "sg:city":"Bad Endbach",
    "sg:postcode":"35080",
    "sg:province":"Hessen",
    "wof:name":"Aldi Gmbh & Co. Kg",
    "wof:placetype":"venue"
},
  "geometry": {"coordinates":[8.459113121,50.7538223267],"type":"Point"}
}