{
  "type": "Feature",
  "properties": {
    "iso:country":"DE",
    "sg:address":"Bahnhofstr. 7",
    "sg:city":"Zeltingen-Rachtig",
    "sg:phone":"+49 6532/4723",
    "sg:postcode":"54492",
    "sg:province":"Rheinland-Pfalz",
    "wof:name":"Karl-heinz L\u00e4nger",
    "wof:placetype":"venue"
},
  "geometry": {"coordinates":[7.0027728081,49.9604568481],"type":"Point"}
}