{
  "type": "Feature",
  "properties": {
    "iso:country":"DE",
    "sg:address":"Kehrhofstr. 4",
    "sg:city":"K\u00f6nigsmoos",
    "sg:phone":"+49 8433/205",
    "sg:postcode":"86669",
    "sg:province":"Bayern",
    "wof:name":"Erhard Bolleininger",
    "wof:placetype":"venue"
},
  "geometry": {"coordinates":[11.196582,48.676071],"type":"Point"}
}