{
  "type": "Feature",
  "properties": {
    "iso:country":"DE",
    "sg:address":"Im Herrengarten 8",
    "sg:city":"Bad Berleburg",
    "sg:phone":"+49 2751/3966",
    "sg:postcode":"57319",
    "sg:province":"Nordrhein-Westfalen",
    "wof:name":"Capitol-theater",
    "wof:placetype":"venue"
},
  "geometry": {"coordinates":[8.3919487,51.050491333],"type":"Point"}
}