{
  "type": "Feature",
  "properties": {
    "iso:country":"DE",
    "sg:address":"Wendenstra\u00dfe 2",
    "sg:city":"Braunschweig",
    "sg:phone":"+49 531/40414",
    "sg:postcode":"38100",
    "sg:province":"Niedersachsen",
    "wof:name":"Tee-studio Arno Schilling",
    "wof:placetype":"venue"
},
  "geometry": {"coordinates":[10.5241317749,52.2680740356],"type":"Point"}
}