{
  "type": "Feature",
  "properties": {
    "iso:country":"DE",
    "sg:address":"Br\u00fcckenstr. 14a",
    "sg:city":"L\u00f6rrach",
    "sg:phone":"+49 7621/52349",
    "sg:postcode":"79541",
    "sg:province":"Baden-W\u00fcrttemberg",
    "wof:name":"M. Und H. Wetzel",
    "wof:placetype":"venue"
},
  "geometry": {"coordinates":[7.694775,47.641037],"type":"Point"}
}