{
  "type": "Feature",
  "properties": {
    "iso:country":"DE",
    "sg:address":"Tungerloh-Pr\u00f6bsting 47",
    "sg:city":"Gescher",
    "sg:phone":"+49 2542/1654",
    "sg:postcode":"48712",
    "sg:province":"Nordrhein-Westfalen",
    "wof:name":"Josef Menker",
    "wof:placetype":"venue"
},
  "geometry": {"coordinates":[7.052572,51.928394],"type":"Point"}
}