{
  "type": "Feature",
  "properties": {
    "iso:country":"DE",
    "sg:address":"Remscheider Str. 113",
    "sg:city":"Wuppertal",
    "sg:phone":"+49 202/464051",
    "sg:postcode":"42369",
    "sg:province":"Nordrhein-Westfalen",
    "wof:name":"Tara Paletten-handel- Und Reparaturdienst Gmbh",
    "wof:placetype":"venue"
},
  "geometry": {"coordinates":[7.2057700157,51.216381073],"type":"Point"}
}