{
  "type": "Feature",
  "properties": {
    "iso:country":"DE",
    "sg:address":"Am Bahnhof 8",
    "sg:city":"Zwickau",
    "sg:phone":"+49 375/281041",
    "sg:postcode":"08056",
    "sg:province":"Sachsen",
    "wof:name":"Mauritius-stube Inh. Anna Hesel-kainz",
    "wof:placetype":"venue"
},
  "geometry": {"coordinates":[12.4794483185,50.7165298462],"type":"Point"}
}