{
  "type": "Feature",
  "properties": {
    "iso:country":"DE",
    "sg:address":"In den Rohrwiesen 6",
    "sg:city":"Homburg",
    "sg:phone":"+49 6841/72121",
    "sg:postcode":"66424",
    "sg:province":"Saarland",
    "wof:name":"Spezi Fliesenmarkt Homburg Gmbh",
    "wof:placetype":"venue"
},
  "geometry": {"coordinates":[7.3431549072,49.335609436],"type":"Point"}
}