{
  "type": "Feature",
  "properties": {
    "iso:country":"DE",
    "sg:address":"Alperheide 43",
    "sg:city":"Willich",
    "sg:phone":"+49 2154/2431",
    "sg:postcode":"47877",
    "sg:province":"Nordrhein-Westfalen",
    "wof:name":"Steppen",
    "wof:placetype":"venue"
},
  "geometry": {"coordinates":[6.5592589378,51.270866394],"type":"Point"}
}