{
  "type": "Feature",
  "properties": {
    "iso:country":"DE",
    "sg:address":"Mittelgasse 15",
    "sg:city":"V\u00f6hl",
    "sg:phone":"+49 5635/9218",
    "sg:postcode":"34516",
    "sg:province":"Hessen",
    "wof:name":"M. Demmer",
    "wof:placetype":"venue"
},
  "geometry": {"coordinates":[8.946513,51.206573],"type":"Point"}
}