{
  "type": "Feature",
  "properties": {
    "iso:country":"DE",
    "sg:address":"Siemensstr 12",
    "sg:city":"Pulheim",
    "sg:phone":"+49 2238/965570",
    "sg:postcode":"50259",
    "sg:province":"Nordrhein-Westfalen",
    "wof:name":"Schmitz Stoffe Gmbh",
    "wof:placetype":"venue"
},
  "geometry": {"coordinates":[6.821996212,50.9891471863],"type":"Point"}
}