{
  "type": "Feature",
  "properties": {
    "iso:country":"DE",
    "sg:address":"Schlo\u00dfallee 15",
    "sg:city":"Burgsinn",
    "sg:phone":"+49 9356/2683",
    "sg:postcode":"97775",
    "sg:province":"Bayern",
    "wof:name":"Roswitha Freiin Von Th\u00fcngen",
    "wof:placetype":"venue"
},
  "geometry": {"coordinates":[9.6555080414,50.1579284668],"type":"Point"}
}