{
  "type": "Feature",
  "properties": {
    "iso:country":"DE",
    "sg:address":"Auf der Breit 11",
    "sg:city":"Karlsruhe",
    "sg:phone":"+49 721/94983",
    "sg:postcode":"76227",
    "sg:province":"Baden-W\u00fcrttemberg",
    "wof:name":"Tmf Food Industries Verwaltungsges. Mbh",
    "wof:placetype":"venue"
},
  "geometry": {"coordinates":[8.47752,49.018143],"type":"Point"}
}