{
  "type": "Feature",
  "properties": {
    "iso:country":"DE",
    "sg:address":"Am Galgengr\u00fcble 17",
    "sg:city":"Wolfegg",
    "sg:phone":"+49 7527/960945",
    "sg:postcode":"88364",
    "sg:province":"Baden-W\u00fcrttemberg",
    "wof:name":"A. Ivan",
    "wof:placetype":"venue"
},
  "geometry": {"coordinates":[9.7961463928,47.8182678223],"type":"Point"}
}