{
  "type": "Feature",
  "properties": {
    "iso:country":"DE",
    "sg:address":"Gaimersheimer Str. 8",
    "sg:city":"Wettstetten",
    "sg:phone":"+49 8406/351",
    "sg:postcode":"85139",
    "sg:province":"Bayern",
    "wof:name":"Rudolf Maurer",
    "wof:placetype":"venue"
},
  "geometry": {"coordinates":[11.393047,48.843361],"type":"Point"}
}