{
  "type": "Feature",
  "properties": {
    "iso:country":"DE",
    "sg:address":"Hanns-Klemm-Str. 24",
    "sg:city":"B\u00f6blingen",
    "sg:phone":"+49 7031/461560",
    "sg:postcode":"71034",
    "sg:province":"Baden-W\u00fcrttemberg",
    "wof:name":"Paul Kommunikationstechnik Gmbh",
    "wof:placetype":"venue"
},
  "geometry": {"coordinates":[8.9861850739,48.6823005676],"type":"Point"}
}