{
  "type": "Feature",
  "properties": {
    "iso:country":"DE",
    "sg:address":"R\u00f6ntgenstr. 10",
    "sg:city":"Bottrop",
    "sg:phone":"+49 2041/22535",
    "sg:postcode":"46242",
    "sg:province":"Nordrhein-Westfalen",
    "wof:name":"P. Eberhardt",
    "wof:placetype":"venue"
},
  "geometry": {"coordinates":[6.90796,51.517307],"type":"Point"}
}