{
  "type": "Feature",
  "properties": {
    "iso:country":"DE",
    "sg:address":"Merkur-Allee 12",
    "sg:city":"Espelkamp",
    "sg:phone":"+49 5772/3312",
    "sg:postcode":"32339",
    "sg:province":"Nordrhein-Westfalen",
    "wof:name":"Friedrich Lohmeier",
    "wof:placetype":"venue"
},
  "geometry": {"coordinates":[8.6322746277,52.3734207153],"type":"Point"}
}