{
  "type": "Feature",
  "properties": {
    "iso:country":"DE",
    "sg:address":"Goseburgstr. 25 - 39",
    "sg:city":"L\u00fcneburg",
    "sg:phone":"+49 4941/3130010",
    "sg:postcode":"21339",
    "sg:province":"Niedersachsen",
    "wof:name":"Kommanditgesellschaft Nord-zentra Erfrischungsgetraenke Gmbh & Co",
    "wof:placetype":"venue"
},
  "geometry": {"coordinates":[10.418439,53.264595],"type":"Point"}
}