{
  "type": "Feature",
  "properties": {
    "iso:country":"DE",
    "sg:address":"Kirchstr. 24",
    "sg:city":"Ringleben",
    "sg:phone":"+49 36201/60064",
    "sg:postcode":"99189",
    "sg:province":"Th\u00fcringen",
    "wof:name":"Andreas Mann",
    "wof:placetype":"venue"
},
  "geometry": {"coordinates":[10.954722,51.104847],"type":"Point"}
}