{
  "type": "Feature",
  "properties": {
    "iso:country":"DE",
    "sg:address":"Sandweg 12",
    "sg:city":"Jesteburg",
    "sg:phone":"+49 4181/8581",
    "sg:postcode":"21266",
    "sg:province":"Niedersachsen",
    "wof:name":"Christel Reichert",
    "wof:placetype":"venue"
},
  "geometry": {"coordinates":[9.9143180847,53.3136863708],"type":"Point"}
}