{
  "type": "Feature",
  "properties": {
    "iso:country":"DE",
    "sg:address":"Postfach 1109:: 88070 Meckenbeuren:: Germany.^^Hauptstr 9-13::",
    "sg:city":"Meckenbeuren",
    "sg:phone":"+49 7542/13111313",
    "sg:postcode":"88074",
    "sg:province":"Baden-W\u00fcrttemberg",
    "wof:name":"Genossenschaftsbank Meckenbeuren Eg",
    "wof:placetype":"venue"
},
  "geometry": {"coordinates":[9.562686,47.699963],"type":"Point"}
}