{
  "type": "Feature",
  "properties": {
    "iso:country":"DE",
    "sg:address":"Merkurstr. 35",
    "sg:city":"Stuttgart",
    "sg:phone":"+49 711/741914",
    "sg:postcode":"70565",
    "sg:province":"Baden-W\u00fcrttemberg",
    "wof:name":"Utz Bau Gmbh",
    "wof:placetype":"venue"
},
  "geometry": {"coordinates":[9.10895,48.715069],"type":"Point"}
}