{
  "type": "Feature",
  "properties": {
    "iso:country":"DE",
    "sg:address":"Sternenhof",
    "sg:city":"Bremen",
    "sg:postcode":"28217",
    "sg:province":"Bremen",
    "wof:name":"Verein Deutscher Dispacheuse E.v.",
    "wof:placetype":"venue"
},
  "geometry": {"coordinates":[8.7922210693,53.0869026184],"type":"Point"}
}