{
  "type": "Feature",
  "properties": {
    "iso:country":"DE",
    "sg:address":"Im See 4",
    "sg:city":"Schmidgaden",
    "sg:phone":"+49 9438/296",
    "sg:postcode":"92546",
    "sg:province":"Bayern",
    "wof:name":"Bernd Leistico Ingenieur",
    "wof:placetype":"venue"
},
  "geometry": {"coordinates":[12.0535326004,49.4334640503],"type":"Point"}
}