{
  "type": "Feature",
  "properties": {
    "iso:country":"DE",
    "sg:address":"Margaretenstr. 2",
    "sg:city":"Berlin",
    "sg:phone":"+49 30/5252378",
    "sg:postcode":"10317",
    "sg:province":"Berlin",
    "wof:name":"Tatios Agopian",
    "wof:placetype":"venue"
},
  "geometry": {"coordinates":[13.4963655472,52.5079421997],"type":"Point"}
}