{
  "type": "Feature",
  "properties": {
    "iso:country":"DE",
    "sg:address":"L\u00f6hdorfer Str. 12",
    "sg:city":"Solingen",
    "sg:postcode":"42699",
    "sg:province":"Nordrhein-Westfalen",
    "wof:name":"Schwan Glas Gmbh",
    "wof:placetype":"venue"
},
  "geometry": {"coordinates":[7.0335469246,51.1608352661],"type":"Point"}
}