{
  "type": "Feature",
  "properties": {
    "iso:country":"DE",
    "sg:address":"Kirchberg 6",
    "sg:city":"Osthofen",
    "sg:phone":"+49 6242/2169",
    "sg:postcode":"67574",
    "sg:province":"Rheinland-Pfalz",
    "wof:name":"M. Lorey",
    "wof:placetype":"venue"
},
  "geometry": {"coordinates":[8.320432,49.703083],"type":"Point"}
}