{
  "type": "Feature",
  "properties": {
    "iso:country":"DE",
    "sg:address":"Kleinenbroicher Str. 48",
    "sg:city":"Kaarst",
    "sg:phone":"+49 2131/958171",
    "sg:postcode":"41564",
    "sg:province":"Nordrhein-Westfalen",
    "wof:name":"Maximiliane St\u00f6ckel Rechtsanw\u00e4ltin",
    "wof:placetype":"venue"
},
  "geometry": {"coordinates":[6.5748381615,51.2122344971],"type":"Point"}
}