{
  "type": "Feature",
  "properties": {
    "iso:country":"DE",
    "sg:address":"Hermannstr. 22",
    "sg:city":"Tuttlingen",
    "sg:phone":"+49 7461/3490",
    "sg:postcode":"78532",
    "sg:province":"Baden-W\u00fcrttemberg",
    "wof:name":"Walter Schupp",
    "wof:placetype":"venue"
},
  "geometry": {"coordinates":[8.8231172562,47.9886054993],"type":"Point"}
}