{
  "type": "Feature",
  "properties": {
    "iso:country":"DE",
    "sg:address":"Hauptstr. 34",
    "sg:city":"Zella-Mehlis",
    "sg:phone":"+49 3682/43526",
    "sg:postcode":"98544",
    "sg:province":"Th\u00fcringen",
    "wof:name":"M. Schreiber",
    "wof:placetype":"venue"
},
  "geometry": {"coordinates":[10.659251,50.658203],"type":"Point"}
}