{
  "type": "Feature",
  "properties": {
    "iso:country":"DE",
    "sg:address":"Schulstr. 4",
    "sg:city":"Bockhorst",
    "sg:phone":"+49 4967/355",
    "sg:postcode":"26897",
    "sg:province":"Niedersachsen",
    "wof:name":"Volksbank Esterwegen Eg",
    "wof:placetype":"venue"
},
  "geometry": {"coordinates":[7.574565,53.027416],"type":"Point"}
}