{
  "type": "Feature",
  "properties": {
    "iso:country":"DE",
    "sg:address":"Presselstra\u00dfe 12A",
    "sg:city":"Berlin",
    "sg:phone":"+49 30/79782960",
    "sg:postcode":"12167",
    "sg:province":"Berlin",
    "wof:name":"Haua & Bau Service Gbr",
    "wof:placetype":"venue"
},
  "geometry": {"coordinates":[13.3394174576,52.4494285583],"type":"Point"}
}