{
  "type": "Feature",
  "properties": {
    "iso:country":"DE",
    "sg:address":"Landstr. 32",
    "sg:city":"Wieslet",
    "sg:phone":"+49 7622/2553",
    "sg:postcode":"79699",
    "sg:province":"Baden-W\u00fcrttemberg",
    "wof:name":"Restaurant Sonne",
    "wof:placetype":"venue"
},
  "geometry": {"coordinates":[7.7982230186,47.6895217896],"type":"Point"}
}