{
  "type": "Feature",
  "properties": {
    "iso:country":"DE",
    "sg:address":"Alpener Str. 71a",
    "sg:city":"Sonsbeck",
    "sg:phone":"+49 2838/91510",
    "sg:postcode":"47665",
    "sg:province":"Nordrhein-Westfalen",
    "wof:name":"Becker Klinker",
    "wof:placetype":"venue"
},
  "geometry": {"coordinates":[6.385529995,51.6003608704],"type":"Point"}
}