{
  "type": "Feature",
  "properties": {
    "iso:country":"DE",
    "sg:address":"H\u00f6henfeldstr. 6 a",
    "sg:city":"Landshut",
    "sg:phone":"+49 871/43755",
    "sg:postcode":"84036",
    "sg:province":"Bayern",
    "wof:name":"G\u00fcnter Saffer Gmbh",
    "wof:placetype":"venue"
},
  "geometry": {"coordinates":[12.1435079575,48.5163192749],"type":"Point"}
}