{
  "type": "Feature",
  "properties": {
    "iso:country":"DE",
    "sg:address":"Borsigstr. 13",
    "sg:city":"Rodgau",
    "sg:phone":"+49 6106/772166",
    "sg:postcode":"63110",
    "sg:province":"Hessen",
    "wof:name":"Nik Huber",
    "wof:placetype":"venue"
},
  "geometry": {"coordinates":[8.8616600037,49.9927177429],"type":"Point"}
}