{
  "type": "Feature",
  "properties": {
    "iso:country":"DE",
    "sg:address":"Dorfstr. 3",
    "sg:city":"Sereetz",
    "sg:phone":"+49 451/392695",
    "sg:postcode":"23611",
    "sg:province":"Schleswig-Holstein",
    "wof:name":"K.-d. Drechsler",
    "wof:placetype":"venue"
},
  "geometry": {"coordinates":[10.734201,53.92033],"type":"Point"}
}