{
  "type": "Feature",
  "properties": {
    "iso:country":"DE",
    "sg:address":"Vahrer Str. 206",
    "sg:city":"Bremen",
    "sg:postcode":"28329",
    "sg:province":"Bremen",
    "wof:name":"Beta Grundst\u00fccks-gmbh",
    "wof:placetype":"venue"
},
  "geometry": {"coordinates":[8.8899,53.080204],"type":"Point"}
}