{
  "type": "Feature",
  "properties": {
    "iso:country":"DE",
    "sg:address":"Seewiesenweg 16",
    "sg:city":"Dresden",
    "sg:phone":"+49 351/8301110",
    "sg:postcode":"01139",
    "sg:province":"Sachsen",
    "wof:name":"Dieter Kost",
    "wof:placetype":"venue"
},
  "geometry": {"coordinates":[13.6805095673,51.0893249512],"type":"Point"}
}