{
  "type": "Feature",
  "properties": {
    "iso:country":"DE",
    "sg:address":"Niederauer Str.15",
    "sg:city":"Dresden",
    "sg:phone":"+49 351/4967148",
    "sg:postcode":"01127",
    "sg:province":"Sachsen",
    "wof:name":"Spynet-spionage-abwehr-spezialelektronik",
    "wof:placetype":"venue"
},
  "geometry": {"coordinates":[13.741908,51.083088],"type":"Point"}
}