{
  "type": "Feature",
  "properties": {
    "iso:country":"DE",
    "sg:address":"Meidericher Str. 67",
    "sg:city":"M\u00fclheim",
    "sg:phone":"+49 208/990544",
    "sg:postcode":"45476",
    "sg:province":"Nordrhein-Westfalen",
    "wof:name":"Itt Fleygt Pumpen Gmbh",
    "wof:placetype":"venue"
},
  "geometry": {"coordinates":[6.844496,51.454086],"type":"Point"}
}