{
  "type": "Feature",
  "properties": {
    "iso:country":"DE",
    "sg:address":"Talstr. 30-31",
    "sg:city":"Goslar",
    "sg:phone":"+49 5321/61122",
    "sg:postcode":"38642",
    "sg:province":"Niedersachsen",
    "wof:name":"Ing. Gerhard Bielstein",
    "wof:placetype":"venue"
},
  "geometry": {"coordinates":[10.479974,51.894485],"type":"Point"}
}