{
  "type": "Feature",
  "properties": {
    "iso:country":"DE",
    "sg:address":"Liebigstr. 9",
    "sg:city":"Landshut",
    "sg:phone":"+49 871/973950",
    "sg:postcode":"84030",
    "sg:province":"Bayern",
    "wof:name":"Konrad Gmbh",
    "wof:placetype":"venue"
},
  "geometry": {"coordinates":[12.1472921371,48.5523338318],"type":"Point"}
}