{
  "type": "Feature",
  "properties": {
    "iso:country":"DE",
    "sg:address":"Marktplatz 4",
    "sg:city":"Wackersdorf",
    "sg:phone":"+49 9431/51682",
    "sg:postcode":"92442",
    "sg:province":"Bayern",
    "wof:name":"Gastst\u00e4tte B\u00f6sl",
    "wof:placetype":"venue"
},
  "geometry": {"coordinates":[12.1749410629,49.3105735779],"type":"Point"}
}