{
  "type": "Feature",
  "properties": {
    "iso:country":"DE",
    "sg:address":"B\u00fcltstr. 9",
    "sg:city":"Ochtrup",
    "sg:phone":"+49 2553/1859",
    "sg:postcode":"48607",
    "sg:province":"Nordrhein-Westfalen",
    "wof:name":"Antonio Falchi",
    "wof:placetype":"venue"
},
  "geometry": {"coordinates":[7.188593,52.210423],"type":"Point"}
}