{
  "type": "Feature",
  "properties": {
    "iso:country":"DE",
    "sg:address":"Wernigeroder Weg 26",
    "sg:city":"Hannover",
    "sg:phone":"+49 511/7500980",
    "sg:postcode":"30419",
    "sg:province":"Niedersachsen",
    "wof:name":"Birkenhof Ambulante Pflege- Dienste Gemeinn\u00fctzige Gmbh",
    "wof:placetype":"venue"
},
  "geometry": {"coordinates":[9.692963,52.405247],"type":"Point"}
}