{
  "type": "Feature",
  "properties": {
    "iso:country":"DE",
    "sg:address":"Karl-Theodor-Str. 83",
    "sg:city":"M\u00fcnchen",
    "sg:phone":"+49 89/3071411",
    "sg:postcode":"80796",
    "sg:province":"Bayern",
    "wof:name":"Monte Video Ges. F\u00fcr Bild- Und Tontr\u00e4ger Mbh",
    "wof:placetype":"venue"
},
  "geometry": {"coordinates":[11.5730581284,48.1671028137],"type":"Point"}
}