{
  "type": "Feature",
  "properties": {
    "iso:country":"DE",
    "sg:address":"Eduard-Bilz-Str. 21",
    "sg:city":"Radebeul",
    "sg:phone":"+49 351/8301249",
    "sg:postcode":"01445",
    "sg:province":"Sachsen",
    "wof:name":"Hartmut Ebert",
    "wof:placetype":"venue"
},
  "geometry": {"coordinates":[13.676982,51.105347],"type":"Point"}
}