{
  "type": "Feature",
  "properties": {
    "iso:country":"DE",
    "sg:address":"Schlo\u00dfstr. 25",
    "sg:city":"Knetzgau",
    "sg:phone":"+49 9527/7381",
    "sg:postcode":"97478",
    "sg:province":"Bayern",
    "wof:name":"Detlev Weing\u00e4rtner",
    "wof:placetype":"venue"
},
  "geometry": {"coordinates":[10.4774141312,49.966835022],"type":"Point"}
}