{
  "type": "Feature",
  "properties": {
    "iso:country":"DE",
    "sg:address":"Sophienstr. 64",
    "sg:city":"Karlsruhe",
    "sg:phone":"+49 721/24197",
    "sg:postcode":"76133",
    "sg:province":"Baden-W\u00fcrttemberg",
    "wof:name":"Helena Antonato",
    "wof:placetype":"venue"
},
  "geometry": {"coordinates":[8.3874988556,49.0077590942],"type":"Point"}
}