{
  "type": "Feature",
  "properties": {
    "iso:country":"DE",
    "sg:address":"Ernst-Th\u00e4lmann-Str. 10 a",
    "sg:city":"Rehna",
    "sg:phone":"+49 38872/53372",
    "sg:postcode":"19217",
    "sg:province":"Mecklenburg-Vorpommern",
    "wof:name":"Reinald Ihde",
    "wof:placetype":"venue"
},
  "geometry": {"coordinates":[11.0526313782,53.7758140564],"type":"Point"}
}