{
  "type": "Feature",
  "properties": {
    "iso:country":"DE",
    "sg:address":"Br\u00fcckstr. 22",
    "sg:city":"Bochum",
    "sg:phone":"+49 234/13247",
    "sg:postcode":"44787",
    "sg:province":"Nordrhein-Westfalen",
    "wof:name":"Pizzeria Ristorante Acquario",
    "wof:placetype":"venue"
},
  "geometry": {"coordinates":[7.2184419632,51.4835472107],"type":"Point"}
}