{
  "type": "Feature",
  "properties": {
    "iso:country":"DE",
    "sg:address":"Marktplatz 3",
    "sg:city":"Die\u00dfen",
    "sg:phone":"+49 8807/91379",
    "sg:postcode":"86911",
    "sg:province":"Bayern",
    "wof:name":"Eiscafe Michelangelo",
    "wof:placetype":"venue"
},
  "geometry": {"coordinates":[11.103164,47.94775],"type":"Point"}
}