{
  "type": "Feature",
  "properties": {
    "iso:country":"DE",
    "sg:address":"Eschenstr. 66",
    "sg:city":"Taufkirchen",
    "sg:phone":"+49 89/6141640",
    "sg:postcode":"82024",
    "sg:province":"Bayern",
    "wof:name":"Ist Innovative Softeare Technologie Gmbh",
    "wof:placetype":"venue"
},
  "geometry": {"coordinates":[11.6055736542,48.0515518188],"type":"Point"}
}