{
  "type": "Feature",
  "properties": {
    "iso:country":"DE",
    "sg:address":"Am Gei\u00dfet 1",
    "sg:city":"Schwarzenfeld",
    "sg:postcode":"92521",
    "sg:province":"Bayern",
    "wof:name":"Peros Media Gmbh",
    "wof:placetype":"venue"
},
  "geometry": {"coordinates":[12.13194,49.394562],"type":"Point"}
}