{
  "type": "Feature",
  "properties": {
    "iso:country":"DE",
    "sg:address":"Bahnhofstr. 5",
    "sg:city":"Aalen",
    "sg:phone":"+49 7361/680875",
    "sg:postcode":"73430",
    "sg:province":"Baden-W\u00fcrttemberg",
    "wof:name":"Harald Uttenlauch",
    "wof:placetype":"venue"
},
  "geometry": {"coordinates":[10.0946598053,48.8386154175],"type":"Point"}
}