{
  "type": "Feature",
  "properties": {
    "iso:country":"DE",
    "sg:address":"Wilhelmsh\u00e4user Str. 64/66",
    "sg:city":"Hann. M\u00fcnden",
    "sg:phone":"+49 5541/791",
    "sg:postcode":"34346",
    "sg:province":"Niedersachsen",
    "wof:name":"C. F. Schr\u00f6der Schleifmittelwerke Gmbh",
    "wof:placetype":"venue"
},
  "geometry": {"coordinates":[9.6430339813,51.4087257385],"type":"Point"}
}