{
  "type": "Feature",
  "properties": {
    "iso:country":"DE",
    "sg:address":"Bahnhofstr. 19",
    "sg:city":"Oederan",
    "sg:phone":"+49 37292/60219",
    "sg:postcode":"09569",
    "sg:province":"Sachsen",
    "wof:name":"Claus Richter",
    "wof:placetype":"venue"
},
  "geometry": {"coordinates":[13.173148,50.858192],"type":"Point"}
}