{
  "type": "Feature",
  "properties": {
    "iso:country":"DE",
    "sg:address":"Kirchgasse 17",
    "sg:city":"Mainz",
    "sg:phone":"+49 6131/471615",
    "sg:postcode":"55126",
    "sg:province":"Rheinland-Pfalz",
    "wof:name":"F\u00f6rsterklause",
    "wof:placetype":"venue"
},
  "geometry": {"coordinates":[8.1734657288,49.9861679077],"type":"Point"}
}