{
  "type": "Feature",
  "properties": {
    "iso:country":"DE",
    "sg:address":"Thierschstr. 21",
    "sg:city":"M\u00fcnchen",
    "sg:phone":"+49 89/21938550",
    "sg:postcode":"80538",
    "sg:province":"Bayern",
    "wof:name":"J\u00fcrgen Bode Rechtsanwalt",
    "wof:placetype":"venue"
},
  "geometry": {"coordinates":[11.5860996246,48.1347694397],"type":"Point"}
}