{
  "type": "Feature",
  "properties": {
    "iso:country":"DE",
    "sg:address":"K\u00f6llner Str 14",
    "sg:city":"Riegelsberg",
    "sg:phone":"+49 6806/922153",
    "sg:postcode":"66292",
    "sg:province":"Saarland",
    "wof:name":"Arthur Martini Gmbh",
    "wof:placetype":"venue"
},
  "geometry": {"coordinates":[6.927591,49.29763],"type":"Point"}
}