{
  "type": "Feature",
  "properties": {
    "iso:country":"DE",
    "sg:address":"Flinkenberg 15",
    "sg:city":"Schwedt",
    "sg:postcode":"16303",
    "sg:province":"Brandenburg",
    "wof:name":"A. Schmidt",
    "wof:placetype":"venue"
},
  "geometry": {"coordinates":[14.285375,53.057064],"type":"Point"}
}