{
  "type": "Feature",
  "properties": {
    "iso:country":"DE",
    "sg:address":"Thorwaldsenstr. 31",
    "sg:city":"M\u00fcnchen",
    "sg:phone":"+49 89/12391342",
    "sg:postcode":"80335",
    "sg:province":"Bayern",
    "wof:name":"Balance Welless For Women",
    "wof:placetype":"venue"
},
  "geometry": {"coordinates":[11.547164917,48.1515235901],"type":"Point"}
}