{
  "type": "Feature",
  "properties": {
    "iso:country":"DE",
    "sg:address":"Inselbergstr. 22",
    "sg:city":"Brotterode",
    "sg:phone":"+49 36840/30221",
    "sg:postcode":"98599",
    "sg:province":"Th\u00fcringen",
    "wof:name":"E. Wagner",
    "wof:placetype":"venue"
},
  "geometry": {"coordinates":[10.4427042007,50.824886322],"type":"Point"}
}