{
  "type": "Feature",
  "properties": {
    "iso:country":"DE",
    "sg:address":"Marienplatz 5",
    "sg:city":"Wolnzach",
    "sg:phone":"+49 8441/8510",
    "sg:postcode":"85283",
    "sg:province":"Bayern",
    "wof:name":"Volksbank Pfaffenhofen/ilm Eg",
    "wof:placetype":"venue"
},
  "geometry": {"coordinates":[11.505592,48.500454],"type":"Point"}
}