{
  "type": "Feature",
  "properties": {
    "iso:country":"DE",
    "sg:address":"Willem-van-Vloten-Str. 13-15",
    "sg:city":"Dortmund",
    "sg:phone":"+49 231/419030",
    "sg:postcode":"44263",
    "sg:province":"Nordrhein-Westfalen",
    "wof:name":"Oevermann Gmbh & Co.",
    "wof:placetype":"venue"
},
  "geometry": {"coordinates":[7.493638,51.494415],"type":"Point"}
}