{
  "type": "Feature",
  "properties": {
    "iso:country":"DE",
    "sg:address":"Bahnhofstr. 22",
    "sg:city":"Sch\u00f6nsee",
    "sg:phone":"+49 9674/92010",
    "sg:postcode":"92539",
    "sg:province":"Bayern",
    "wof:name":"Raiffeisen Waren Und Dienstleistungs Gmbh",
    "wof:placetype":"venue"
},
  "geometry": {"coordinates":[12.537554,49.510639],"type":"Point"}
}