{
  "type": "Feature",
  "properties": {
    "iso:country":"DE",
    "sg:address":"Postfach",
    "sg:city":"K\u00f6nigslutter",
    "sg:phone":"+49 5353/192171",
    "sg:postcode":"38150",
    "wof:name":"Frei- Und Hallenbad Sportzentrum",
    "wof:placetype":"venue"
},
  "geometry": {"coordinates":[10.822259903,52.247718811],"type":"Point"}
}