{
  "type": "Feature",
  "properties": {
    "iso:country":"DE",
    "sg:address":"Schallershofer Str. 137",
    "sg:city":"Erlangen",
    "sg:phone":"+49 9131/79710",
    "sg:postcode":"91056",
    "sg:province":"Bayern",
    "wof:name":"Hummert Bauhandwerks- Und Dienstleistungs Gmbh",
    "wof:placetype":"venue"
},
  "geometry": {"coordinates":[10.9740962982,49.5790252686],"type":"Point"}
}