{
  "type": "Feature",
  "properties": {
    "iso:country":"DE",
    "sg:address":"Bahnhofstr. 37",
    "sg:city":"Obertshausen",
    "sg:phone":"+49 6104/44759",
    "sg:postcode":"63179",
    "sg:province":"Hessen",
    "wof:name":"Bierbrunnen",
    "wof:placetype":"venue"
},
  "geometry": {"coordinates":[8.8514528275,50.0731658936],"type":"Point"}
}