{
  "type": "Feature",
  "properties": {
    "iso:country":"DE",
    "sg:address":"Waldstr. 39",
    "sg:city":"Lingen",
    "sg:postcode":"49808",
    "sg:province":"Niedersachsen",
    "wof:name":"Noell Gmbh",
    "wof:placetype":"venue"
},
  "geometry": {"coordinates":[7.3210611343,52.5300750732],"type":"Point"}
}