{
  "type": "Feature",
  "properties": {
    "iso:country":"DE",
    "sg:address":"Baarentelgenstr. 15",
    "sg:city":"Rheine",
    "sg:phone":"+49 5971/808080",
    "sg:postcode":"48432",
    "sg:province":"Nordrhein-Westfalen",
    "wof:name":"Firma Krimphoff Und Schulte Gmbh",
    "wof:placetype":"venue"
},
  "geometry": {"coordinates":[7.4435,52.310951],"type":"Point"}
}