{
  "type": "Feature",
  "properties": {
    "iso:country":"DE",
    "sg:address":"Sachsentor 31",
    "sg:city":"Hamburg",
    "sg:phone":"+49 40/7218076",
    "sg:postcode":"21029",
    "sg:province":"Hamburg",
    "wof:name":"Helmuth Schlingemann Architekt",
    "wof:placetype":"venue"
},
  "geometry": {"coordinates":[10.2132,53.487995],"type":"Point"}
}