{
  "type": "Feature",
  "properties": {
    "iso:country":"DE",
    "sg:address":"Kleines Feldlein 1",
    "sg:city":"Sinsheim",
    "sg:phone":"+49 7261/9300",
    "sg:postcode":"74889",
    "sg:province":"Baden-W\u00fcrttemberg",
    "wof:name":"Werbe- U. Verpackungsdienst Gmbh",
    "wof:placetype":"venue"
},
  "geometry": {"coordinates":[8.850447,49.248741],"type":"Point"}
}