{
  "type": "Feature",
  "properties": {
    "iso:country":"DE",
    "sg:address":"Waldstr. 16",
    "sg:city":"M\u00fcnchenbernsdorf",
    "sg:phone":"+49 36604/2332",
    "sg:postcode":"07589",
    "sg:province":"Th\u00fcringen",
    "wof:name":"Reinhard Seliger",
    "wof:placetype":"venue"
},
  "geometry": {"coordinates":[11.925061,50.821213],"type":"Point"}
}