{
  "type": "Feature",
  "properties": {
    "iso:country":"DE",
    "sg:address":"Magnusstr. 40",
    "sg:city":"Kempten",
    "sg:phone":"+49 831/65912",
    "sg:postcode":"87437",
    "sg:province":"Bayern",
    "wof:name":"A. Sussbauer Schornsteinfeger",
    "wof:placetype":"venue"
},
  "geometry": {"coordinates":[10.3241796494,47.7073287964],"type":"Point"}
}