{
  "type": "Feature",
  "properties": {
    "iso:country":"DE",
    "sg:address":"Breitwiesenstr. 45",
    "sg:city":"Metzingen",
    "sg:phone":"+49 7123/2251",
    "sg:postcode":"72555",
    "sg:province":"Baden-W\u00fcrttemberg",
    "wof:name":"Georg Schmid Gmbh",
    "wof:placetype":"venue"
},
  "geometry": {"coordinates":[9.274902,48.537514],"type":"Point"}
}