{
  "type": "Feature",
  "properties": {
    "iso:country":"DE",
    "sg:address":"Rheinstr. 9a",
    "sg:city":"H\u00fcckelhoven",
    "sg:phone":"+49 2433/97790",
    "sg:postcode":"41836",
    "sg:province":"Nordrhein-Westfalen",
    "wof:name":"Josten Tortechnik Gmbh",
    "wof:placetype":"venue"
},
  "geometry": {"coordinates":[6.212932,51.052235],"type":"Point"}
}