{
  "type": "Feature",
  "properties": {
    "iso:country":"DE",
    "sg:address":"Carl-Zeiss-Str. 2",
    "sg:city":"Leonberg",
    "sg:phone":"+49 7152/999660",
    "sg:postcode":"71229",
    "sg:province":"Baden-W\u00fcrttemberg",
    "wof:name":"Music & Light Design Gmbh",
    "wof:placetype":"venue"
},
  "geometry": {"coordinates":[8.982555,48.809509],"type":"Point"}
}