{
  "type": "Feature",
  "properties": {
    "iso:country":"DE",
    "sg:address":"Kimplerstr. 284",
    "sg:city":"Krefeld",
    "sg:phone":"+49 2151/37350",
    "sg:postcode":"47807",
    "sg:province":"Nordrhein-Westfalen",
    "wof:name":"Dr\u00e4gerwerk Ag",
    "wof:placetype":"venue"
},
  "geometry": {"coordinates":[6.571912,51.306149],"type":"Point"}
}