{
  "type": "Feature",
  "properties": {
    "iso:country":"DE",
    "sg:address":"Lindenstr. 31",
    "sg:city":"Stade",
    "sg:phone":"+49 4141/981395",
    "sg:postcode":"21684",
    "sg:province":"Niedersachsen",
    "wof:name":"Us-travel-service",
    "wof:placetype":"venue"
},
  "geometry": {"coordinates":[9.4261159897,53.5855293274],"type":"Point"}
}