{
  "type": "Feature",
  "properties": {
    "iso:country":"DE",
    "sg:address":"Mainzer Str. 22-24",
    "sg:city":"Remagen",
    "sg:postcode":"53424",
    "sg:province":"Rheinland-Pfalz",
    "wof:name":"Deutsch-chinesiche Bildungs- Kultur- Und Wirtschafts Gmbh",
    "wof:placetype":"venue"
},
  "geometry": {"coordinates":[7.205816,50.637028],"type":"Point"}
}