{
  "type": "Feature",
  "properties": {
    "iso:country":"DE",
    "sg:address":"Rh\u00f6nstr. 9",
    "sg:city":"Wiesbaden",
    "sg:phone":"+49 611/9854546",
    "sg:postcode":"65187",
    "sg:province":"Hessen",
    "wof:name":"Arcotecta Bautr\u00e4ger Gmbh",
    "wof:placetype":"venue"
},
  "geometry": {"coordinates":[8.2441616058,50.059223175],"type":"Point"}
}