{
  "type": "Feature",
  "properties": {
    "iso:country":"DE",
    "sg:address":"G\u00fcterstr. 17/3",
    "sg:city":"Wiesloch",
    "sg:phone":"+49 6222/380355",
    "sg:postcode":"69168",
    "sg:province":"Baden-W\u00fcrttemberg",
    "wof:name":"Am Production Gmbh",
    "wof:placetype":"venue"
},
  "geometry": {"coordinates":[8.6947374344,49.2904129028],"type":"Point"}
}