{
  "type": "Feature",
  "properties": {
    "iso:country":"DE",
    "sg:address":"K\u00f6lner Str 68",
    "sg:city":"Burscheid",
    "sg:postcode":"51399",
    "sg:province":"Nordrhein-Westfalen",
    "wof:name":"Wenger - Mobile Technik Und B\u00fchnensysteme",
    "wof:placetype":"venue"
},
  "geometry": {"coordinates":[7.1576280594,51.1042098999],"type":"Point"}
}