{
  "type": "Feature",
  "properties": {
    "iso:country":"DE",
    "sg:address":"Im G\u00e4rtel 7",
    "sg:city":"F\u00fcrth",
    "sg:phone":"+49 6253/932059",
    "sg:postcode":"64658",
    "sg:province":"Hessen",
    "wof:name":"Cl. Fr\u00f6hlich Heilpraktiker",
    "wof:placetype":"venue"
},
  "geometry": {"coordinates":[8.7568321228,49.6578140259],"type":"Point"}
}