{
  "type": "Feature",
  "properties": {
    "iso:country":"DE",
    "sg:address":"Am Pennworthmoor 33",
    "sg:city":"Cuxhaven",
    "sg:postcode":"27476",
    "sg:province":"Niedersachsen",
    "wof:name":"Deutsch-russische Gesellschaft Cuxhaven E. V.",
    "wof:placetype":"venue"
},
  "geometry": {"coordinates":[8.6287355423,53.8630447388],"type":"Point"}
}