{
  "type": "Feature",
  "properties": {
    "iso:country":"DE",
    "sg:address":"Eggenpfad 8",
    "sg:city":"Werdohl",
    "sg:phone":"+49 2392/2040",
    "sg:postcode":"58791",
    "sg:province":"Nordrhein-Westfalen",
    "wof:name":"Magie Und Zauberei Frank Baroth",
    "wof:placetype":"venue"
},
  "geometry": {"coordinates":[7.76595,51.258808],"type":"Point"}
}