{
  "type": "Feature",
  "properties": {
    "iso:country":"DE",
    "sg:address":"Saarbr\u00fccker Str. 22 a",
    "sg:city":"Mandelbachtal",
    "sg:phone":"+49 6803/3534",
    "sg:postcode":"66399",
    "sg:province":"Saarland",
    "wof:name":"W. Maass",
    "wof:placetype":"venue"
},
  "geometry": {"coordinates":[7.1606888771,49.2172851562],"type":"Point"}
}