{
  "type": "Feature",
  "properties": {
    "iso:country":"DE",
    "sg:address":"Utestr. 55",
    "sg:city":"Bonn",
    "sg:phone":"+49 228/342942",
    "sg:postcode":"53179",
    "sg:province":"Nordrhein-Westfalen",
    "wof:name":"Deutsche Stiftung F\u00fcr Poli- Tische Bildung Und V\u00f6lker-",
    "wof:placetype":"venue"
},
  "geometry": {"coordinates":[7.1913890839,50.6639137268],"type":"Point"}
}