{
  "type": "Feature",
  "properties": {
    "iso:country":"DE",
    "sg:address":"Na\u00df\u00e4ckerstr. 12",
    "sg:city":"P\u00f6\u00dfneck",
    "sg:phone":"+49 3647/42550",
    "sg:postcode":"07381",
    "sg:province":"Th\u00fcringen",
    "wof:name":"P. Kuhlmann Und Helga S\u00e4nger Steuerberater",
    "wof:placetype":"venue"
},
  "geometry": {"coordinates":[11.6253223419,50.6999053955],"type":"Point"}
}