{
  "type": "Feature",
  "properties": {
    "iso:country":"DE",
    "sg:address":"Wittener Str. 80 c",
    "sg:city":"Wuppertal",
    "sg:phone":"+49 202/667553",
    "sg:postcode":"42279",
    "sg:province":"Nordrhein-Westfalen",
    "wof:name":"Rosemarie Klein",
    "wof:placetype":"venue"
},
  "geometry": {"coordinates":[7.2370448112,51.2918128967],"type":"Point"}
}