{
  "type": "Feature",
  "properties": {
    "iso:country":"DE",
    "sg:address":"Kuglerweg 11",
    "sg:city":"Fuchsm\u00fchl",
    "sg:phone":"+49 9634/625",
    "sg:postcode":"95689",
    "sg:province":"Bayern",
    "wof:name":"Xaver Bayer",
    "wof:placetype":"venue"
},
  "geometry": {"coordinates":[12.1417694092,49.9192352295],"type":"Point"}
}