{
  "type": "Feature",
  "properties": {
    "iso:country":"DE",
    "sg:address":"Johann-Wilhelm-Lindlar-Str. 9",
    "sg:city":"Bergisch Gladbach",
    "sg:phone":"+49 2202/9369010",
    "sg:postcode":"51465",
    "sg:province":"Nordrhein-Westfalen",
    "wof:name":"Informa Gmbh",
    "wof:placetype":"venue"
},
  "geometry": {"coordinates":[7.1257400513,50.9913063049],"type":"Point"}
}