{
  "type": "Feature",
  "properties": {
    "iso:country":"DE",
    "sg:address":"Marstallstr. 12",
    "sg:city":"Erfurt",
    "sg:phone":"+49 361/6464666",
    "sg:postcode":"99084",
    "sg:province":"Th\u00fcringen",
    "wof:name":"Das Die Live",
    "wof:placetype":"venue"
},
  "geometry": {"coordinates":[11.0277204514,50.9745635986],"type":"Point"}
}