{
  "type": "Feature",
  "properties": {
    "iso:country":"DE",
    "sg:address":"Sigsfeldstr. 8",
    "sg:city":"Aachen",
    "sg:phone":"+49 241/520088",
    "sg:postcode":"52078",
    "sg:province":"Nordrhein-Westfalen",
    "wof:name":"Heinz Gier Gmbh",
    "wof:placetype":"venue"
},
  "geometry": {"coordinates":[6.1671528816,50.7625312805],"type":"Point"}
}