{
  "type": "Feature",
  "properties": {
    "iso:country":"DE",
    "sg:address":"L\u00f6wenweg 2",
    "sg:city":"Albstadt",
    "sg:phone":"+49 7431/71443",
    "sg:postcode":"72458",
    "sg:province":"Baden-W\u00fcrttemberg",
    "wof:name":"Nando P\u00fcrzel Praxis F\u00fcr Krankengymnastik",
    "wof:placetype":"venue"
},
  "geometry": {"coordinates":[9.005326,48.212383],"type":"Point"}
}