{
  "type": "Feature",
  "properties": {
    "iso:country":"DE",
    "sg:address":"Illertisser Str. 2",
    "sg:city":"Buch",
    "sg:phone":"+49 7343/96050",
    "sg:postcode":"89290",
    "sg:province":"Bayern",
    "wof:name":"Alois Sauter Landesprodukten- Gro\u00dfhandlung Gmbh & Co.",
    "wof:placetype":"venue"
},
  "geometry": {"coordinates":[10.175253,48.234928],"type":"Point"}
}