{
  "type": "Feature",
  "properties": {
    "iso:country":"DE",
    "sg:address":"Lange Wiese 7",
    "sg:city":"Haren",
    "sg:postcode":"49733",
    "sg:province":"Niedersachsen",
    "wof:name":"Tesch Bereederungsges. Mbh",
    "wof:placetype":"venue"
},
  "geometry": {"coordinates":[7.234239,52.792149],"type":"Point"}
}