{
  "type": "Feature",
  "properties": {
    "iso:country":"DE",
    "sg:address":"Nikolaistr. 1",
    "sg:city":"Gardelegen",
    "sg:phone":"+49 3907/2530",
    "sg:postcode":"39638",
    "sg:province":"Sachsen-Anhalt",
    "wof:name":"Annas Mode F\u00fcr Kids",
    "wof:placetype":"venue"
},
  "geometry": {"coordinates":[11.3916845322,52.5266571045],"type":"Point"}
}