{
  "type": "Feature",
  "properties": {
    "iso:country":"DE",
    "sg:address":"Sch\u00fctzengasse 2",
    "sg:city":"Weimar",
    "sg:phone":"+49 3643/904323",
    "sg:postcode":"99423",
    "sg:province":"Th\u00fcringen",
    "wof:name":"Sch\u00fctzengasse Freundeskreis E. V.",
    "wof:placetype":"venue"
},
  "geometry": {"coordinates":[11.3262844086,50.9791488647],"type":"Point"}
}