{
  "type": "Feature",
  "properties": {
    "iso:country":"DE",
    "sg:address":"R\u00f6hrsdorfer Str. 4",
    "sg:city":"Dresden",
    "sg:phone":"+49 351/2849370",
    "sg:postcode":"01257",
    "sg:province":"Sachsen",
    "wof:name":"M. Schmidt Und W. Patzig Immobilienmakler",
    "wof:placetype":"venue"
},
  "geometry": {"coordinates":[13.8060321808,50.9865531921],"type":"Point"}
}