{
  "type": "Feature",
  "properties": {
    "iso:country":"DE",
    "sg:address":"Luciaweg",
    "sg:city":"Stolberg",
    "sg:phone":"+49 2402/82250",
    "sg:postcode":"52222",
    "sg:province":"Nordrhein-Westfalen",
    "wof:name":"Heimat- Und Handwerks- Museum Stolberg",
    "wof:placetype":"venue"
},
  "geometry": {"coordinates":[6.233441,50.766808],"type":"Point"}
}