{
  "type": "Feature",
  "properties": {
    "iso:country":"DE",
    "sg:address":"Postfach 57",
    "sg:city":"Kaufering",
    "sg:postcode":"86912",
    "sg:province":"Bayern",
    "wof:name":"Dt. Hilti Gmbh Werkzeuge",
    "wof:placetype":"venue"
},
  "geometry": {"coordinates":[10.861161,48.086857],"type":"Point"}
}