{
  "type": "Feature",
  "properties": {
    "iso:country":"DE",
    "sg:address":"Egen 27",
    "sg:city":"Sprockh\u00f6vel",
    "sg:phone":"+49 202/523783",
    "sg:postcode":"45549",
    "sg:province":"Nordrhein-Westfalen",
    "wof:name":"C. Frenzel",
    "wof:placetype":"venue"
},
  "geometry": {"coordinates":[7.209498,51.316261],"type":"Point"}
}