{
  "type": "Feature",
  "properties": {
    "iso:country":"DE",
    "sg:address":"Wolfener Str. 32-34",
    "sg:city":"Berlin",
    "sg:phone":"+49 30/9366880",
    "sg:postcode":"12681",
    "sg:province":"Berlin",
    "wof:name":"Nico Gmbh",
    "wof:placetype":"venue"
},
  "geometry": {"coordinates":[13.5514135361,52.5606231689],"type":"Point"}
}