{
  "type": "Feature",
  "properties": {
    "iso:country":"DE",
    "sg:address":"Slippen 2 a",
    "sg:city":"Achim",
    "sg:phone":"+49 4202/881104",
    "sg:postcode":"28832",
    "sg:province":"Niedersachsen",
    "wof:name":"Dorota Pl\u00f6tzwich",
    "wof:placetype":"venue"
},
  "geometry": {"coordinates":[8.9644775391,53.0308113098],"type":"Point"}
}