{
  "type": "Feature",
  "properties": {
    "iso:country":"DE",
    "sg:address":"Neckarstr. 20",
    "sg:city":"Horb",
    "sg:phone":"+49 7451/2353",
    "sg:postcode":"72160",
    "sg:province":"Baden-W\u00fcrttemberg",
    "wof:name":"J. Haipt",
    "wof:placetype":"venue"
},
  "geometry": {"coordinates":[8.6913700104,48.4442596436],"type":"Point"}
}