{
  "type": "Feature",
  "properties": {
    "iso:country":"DE",
    "sg:address":"Nordbeckenstr. 17 B",
    "sg:city":"Karlsruhe",
    "sg:phone":"+49 721/551961",
    "sg:postcode":"76189",
    "sg:province":"Baden-W\u00fcrttemberg",
    "wof:name":"Kloeckner & Co. Mineral\u00f6lgrosshandel",
    "wof:placetype":"venue"
},
  "geometry": {"coordinates":[8.3168649673,49.0170593262],"type":"Point"}
}