{
  "type": "Feature",
  "properties": {
    "iso:country":"DE",
    "sg:address":"Nachtigallenweg 24",
    "sg:city":"Lauenburg",
    "sg:phone":"+49 4153/54577",
    "sg:postcode":"21481",
    "sg:province":"Schleswig-Holstein",
    "wof:name":"Volker Maahs",
    "wof:placetype":"venue"
},
  "geometry": {"coordinates":[10.5317239761,53.3747940063],"type":"Point"}
}