{
  "type": "Feature",
  "properties": {
    "iso:country":"DE",
    "sg:address":"Niehler Str. 1",
    "sg:city":"K\u00f6ln",
    "sg:phone":"+49 221/7391346",
    "sg:postcode":"50670",
    "sg:province":"Nordrhein-Westfalen",
    "wof:name":"H. Und M. M\u00fchlenz Gmbh",
    "wof:placetype":"venue"
},
  "geometry": {"coordinates":[6.9574651718,50.9561729431],"type":"Point"}
}