{
  "type": "Feature",
  "properties": {
    "iso:country":"DE",
    "sg:address":"Lange Str. 11",
    "sg:city":"Crailsheim",
    "sg:phone":"+49 7951/8134",
    "sg:postcode":"74564",
    "sg:province":"Baden-W\u00fcrttemberg",
    "wof:name":"Dr. Med. Manfred Nettlau Arzt F\u00fcr Innere Medizin",
    "wof:placetype":"venue"
},
  "geometry": {"coordinates":[10.0712089539,49.1363945007],"type":"Point"}
}