{
  "type": "Feature",
  "properties": {
    "iso:country":"DE",
    "sg:address":"Hauptstr. 38",
    "sg:city":"Esterwegen",
    "sg:phone":"+49 5955/9191",
    "sg:postcode":"26897",
    "sg:province":"Niedersachsen",
    "wof:name":"Optik Berens & Rolfes Gmbh",
    "wof:placetype":"venue"
},
  "geometry": {"coordinates":[7.6337828636,52.9924583435],"type":"Point"}
}