{
  "type": "Feature",
  "properties": {
    "iso:country":"DE",
    "sg:address":"Premsliner Str. 30",
    "sg:city":"Gl\u00f6vzin",
    "sg:postcode":"19357",
    "sg:province":"Brandenburg",
    "wof:name":"Onyx Bau Gmbh",
    "wof:placetype":"venue"
},
  "geometry": {"coordinates":[11.785339,53.133278],"type":"Point"}
}