{
  "type": "Feature",
  "properties": {
    "iso:country":"DE",
    "sg:address":"Leipziger Str. 16",
    "sg:city":"Hachenburg",
    "sg:phone":"+49 2662/50555",
    "sg:postcode":"57627",
    "sg:province":"Rheinland-Pfalz",
    "wof:name":"Thomas Orthey",
    "wof:placetype":"venue"
},
  "geometry": {"coordinates":[7.8292441368,50.6617355347],"type":"Point"}
}