{
  "type": "Feature",
  "properties": {
    "iso:country":"DE",
    "sg:address":"Wickenweg 9",
    "sg:city":"Kirchlinteln",
    "sg:phone":"+49 4236/94091",
    "sg:postcode":"27308",
    "sg:province":"Niedersachsen",
    "wof:name":"Biedermann Consulting Gmbh",
    "wof:placetype":"venue"
},
  "geometry": {"coordinates":[9.321566,52.938129],"type":"Point"}
}