{
  "type": "Feature",
  "properties": {
    "iso:country":"DE",
    "sg:address":"Kreienhoop 143",
    "sg:city":"Hamburg",
    "sg:phone":"+49 40/60299308",
    "sg:postcode":"22399",
    "sg:province":"Hamburg",
    "wof:name":"Renergy Entsorgungsmanagement Und Rohstoffhandel Gmbh",
    "wof:placetype":"venue"
},
  "geometry": {"coordinates":[10.067561,53.674534],"type":"Point"}
}