{
  "type": "Feature",
  "properties": {
    "iso:country":"DE",
    "sg:address":"Hauptstr. 79",
    "sg:city":"Heidelberg",
    "sg:phone":"+49 6221/21275",
    "sg:postcode":"69117",
    "sg:province":"Baden-W\u00fcrttemberg",
    "wof:name":"P. Von Traitteur Rechtsanwalt",
    "wof:placetype":"venue"
},
  "geometry": {"coordinates":[8.7014198303,49.4111175537],"type":"Point"}
}