{
  "type": "Feature",
  "properties": {
    "iso:country":"DE",
    "sg:address":"Alter Kirchweg 25",
    "sg:city":"Meerbusch",
    "sg:phone":"+49 2132/4324",
    "sg:postcode":"40667",
    "sg:province":"Nordrhein-Westfalen",
    "wof:name":"Berking Kg",
    "wof:placetype":"venue"
},
  "geometry": {"coordinates":[6.6964092255,51.2511291504],"type":"Point"}
}