{
  "type": "Feature",
  "properties": {
    "iso:country":"DE",
    "sg:address":"Ziergartenstr. 5",
    "sg:city":"Bad Wildungen",
    "sg:phone":"+49 5621/78988",
    "sg:postcode":"34537",
    "sg:province":"Hessen",
    "wof:name":"G\u00e4stehaus Wollmert Gbr",
    "wof:placetype":"venue"
},
  "geometry": {"coordinates":[9.0777683258,51.110534668],"type":"Point"}
}