{
  "type": "Feature",
  "properties": {
    "iso:country":"DE",
    "sg:address":"Anhalter Str. 97",
    "sg:city":"Herzberg",
    "sg:phone":"+49 3535/5189",
    "sg:postcode":"04916",
    "sg:province":"Brandenburg",
    "wof:name":"G\u00fcnter Thees",
    "wof:placetype":"venue"
},
  "geometry": {"coordinates":[13.209546,51.682007],"type":"Point"}
}