{
  "type": "Feature",
  "properties": {
    "iso:country":"DE",
    "sg:address":"Am Schinderwasen 2",
    "sg:city":"Blaustein",
    "sg:phone":"+49 7304/7950",
    "sg:postcode":"89134",
    "sg:province":"Baden-W\u00fcrttemberg",
    "wof:name":"Olympia Gmbh",
    "wof:placetype":"venue"
},
  "geometry": {"coordinates":[9.927148819,48.41223526],"type":"Point"}
}