{
  "type": "Feature",
  "properties": {
    "iso:country":"DE",
    "sg:address":"Lipaer Str. 14b",
    "sg:city":"Berlin",
    "sg:phone":"+49 30/8343680",
    "sg:postcode":"12203",
    "sg:province":"Berlin",
    "wof:name":"Ka Te Grundbesitz Verwaltungs Gmbh",
    "wof:placetype":"venue"
},
  "geometry": {"coordinates":[13.312988,52.445511],"type":"Point"}
}