{
  "type": "Feature",
  "properties": {
    "iso:country":"DE",
    "sg:address":"Rohrammerweg 10 a",
    "sg:city":"Isernhagen",
    "sg:phone":"+49 511/613046",
    "sg:postcode":"30916",
    "sg:province":"Niedersachsen",
    "wof:name":"Manfred M\u00fcller Industrievertretungen Gmbh",
    "wof:placetype":"venue"
},
  "geometry": {"coordinates":[9.8371219635,52.4340133667],"type":"Point"}
}