{
  "type": "Feature",
  "properties": {
    "iso:country":"DE",
    "sg:address":"August-Bebel-Str 165a",
    "sg:city":"Beierfeld",
    "sg:phone":"+49 37362/8228",
    "sg:postcode":"08340",
    "sg:province":"Sachsen",
    "wof:name":"Theo Lorenz",
    "wof:placetype":"venue"
},
  "geometry": {"coordinates":[13.4427032471,50.6319503784],"type":"Point"}
}