{
  "type": "Feature",
  "properties": {
    "iso:country":"DE",
    "sg:address":"Birkenweg 6",
    "sg:city":"Hahnbach",
    "sg:phone":"+49 9664/95050",
    "sg:postcode":"92256",
    "sg:province":"Bayern",
    "wof:name":"Karl Standecker",
    "wof:placetype":"venue"
},
  "geometry": {"coordinates":[11.798727,49.526615],"type":"Point"}
}