{
  "type": "Feature",
  "properties": {
    "iso:country":"DE",
    "sg:address":"Hauptstr. 15",
    "sg:city":"Drebach",
    "sg:phone":"+49 37341/7167",
    "sg:postcode":"09430",
    "sg:province":"Sachsen",
    "wof:name":"Helmut Weber",
    "wof:placetype":"venue"
},
  "geometry": {"coordinates":[13.025761,50.6842],"type":"Point"}
}