{
  "type": "Feature",
  "properties": {
    "iso:country":"DE",
    "sg:address":"Diekamp 47",
    "sg:city":"Warendorf",
    "sg:phone":"+49 2581/782184",
    "sg:postcode":"48231",
    "sg:province":"Nordrhein-Westfalen",
    "wof:name":"R. Perlewitz Rechtsanwalt",
    "wof:placetype":"venue"
},
  "geometry": {"coordinates":[7.9908161163,51.9456443787],"type":"Point"}
}