{
  "type": "Feature",
  "properties": {
    "iso:country":"DE",
    "sg:address":"Ludwigstr. 42",
    "sg:city":"Saarbr\u00fccken",
    "sg:phone":"+49 681/473035",
    "sg:postcode":"66115",
    "sg:province":"Saarland",
    "wof:name":"Medtec Medizinische Technik Handels Gmbh",
    "wof:placetype":"venue"
},
  "geometry": {"coordinates":[6.9758319855,49.2392539978],"type":"Point"}
}