{
  "type": "Feature",
  "properties": {
    "iso:country":"DE",
    "sg:address":"Rottmannstr. 48",
    "sg:city":"Heidelberg",
    "sg:phone":"+49 6221/475772",
    "sg:postcode":"69121",
    "sg:province":"Baden-W\u00fcrttemberg",
    "wof:name":"Ip 20 Inbauteile M\u00f6bel Nach Mass",
    "wof:placetype":"venue"
},
  "geometry": {"coordinates":[8.6837053299,49.4262542725],"type":"Point"}
}