{
  "type": "Feature",
  "properties": {
    "iso:country":"DE",
    "sg:address":"Kientenstr. 15",
    "sg:city":"Albstadt",
    "sg:phone":"+49 7431/90030",
    "sg:postcode":"72458",
    "sg:province":"Baden-W\u00fcrttemberg",
    "wof:name":"Computer Haug Gmbh",
    "wof:placetype":"venue"
},
  "geometry": {"coordinates":[9.012061,48.210735],"type":"Point"}
}