{
  "type": "Feature",
  "properties": {
    "iso:country":"DE",
    "sg:address":"Mahdentalstr. 94",
    "sg:city":"Sindelfingen",
    "sg:postcode":"71065",
    "sg:province":"Baden-W\u00fcrttemberg",
    "wof:name":"Cp Print Gmbh",
    "wof:placetype":"venue"
},
  "geometry": {"coordinates":[9.030511,48.706955],"type":"Point"}
}