{
  "type": "Feature",
  "properties": {
    "iso:country":"DE",
    "sg:address":"Morjansbusch 80",
    "sg:city":"M\u00f6nchengladbach",
    "sg:postcode":"41239",
    "sg:province":"Nordrhein-Westfalen",
    "wof:name":"Dahmen Baustahl- Armierungen Gmbh",
    "wof:placetype":"venue"
},
  "geometry": {"coordinates":[6.4179348946,51.1618461609],"type":"Point"}
}