{
  "type": "Feature",
  "properties": {
    "iso:country":"DE",
    "sg:address":"Welschenweg 19a",
    "sg:city":"Oerlinghausen",
    "sg:phone":"+49 5202/490222",
    "sg:postcode":"33813",
    "sg:province":"Nordrhein-Westfalen",
    "wof:name":"Loro Bau Und Immobilien- Verwaltung Gmbh",
    "wof:placetype":"venue"
},
  "geometry": {"coordinates":[8.663765,51.953217],"type":"Point"}
}