{
  "type": "Feature",
  "properties": {
    "iso:country":"DE",
    "sg:address":"G\u00fcterstr. 34",
    "sg:city":"Wilhelmshaven",
    "sg:phone":"+49 4421/75600",
    "sg:postcode":"26389",
    "sg:province":"Niedersachsen",
    "wof:name":"Michalczyk Elektroanlagen Verwaltungs Gmbh",
    "wof:placetype":"venue"
},
  "geometry": {"coordinates":[8.0787000656,53.521648407],"type":"Point"}
}