{
  "type": "Feature",
  "properties": {
    "iso:country":"DE",
    "sg:address":"Biberweg 9",
    "sg:city":"Troisdorf",
    "sg:phone":"+49 2241/946019",
    "sg:postcode":"53842",
    "sg:province":"Nordrhein-Westfalen",
    "wof:name":"Backservice Constance",
    "wof:placetype":"venue"
},
  "geometry": {"coordinates":[7.108467,50.829174],"type":"Point"}
}