{
  "type": "Feature",
  "properties": {
    "iso:country":"DE",
    "sg:address":"Ismaninger Str. 7",
    "sg:city":"M\u00fcnchen",
    "sg:phone":"+49 89/4191026",
    "sg:postcode":"81675",
    "sg:province":"Bayern",
    "wof:name":"Bestattungsinstitut Denk Gmbh & Co. Kg",
    "wof:placetype":"venue"
},
  "geometry": {"coordinates":[11.597961,48.136574],"type":"Point"}
}