{
  "type": "Feature",
  "properties": {
    "iso:country":"DE",
    "sg:address":"B\u00e4renburger Str. 19",
    "sg:city":"Altenberg",
    "sg:postcode":"01773",
    "sg:province":"Sachsen",
    "wof:name":"Rainer Frenzel",
    "wof:placetype":"venue"
},
  "geometry": {"coordinates":[13.7306900024,50.8010139465],"type":"Point"}
}