{
  "type": "Feature",
  "properties": {
    "iso:country":"DE",
    "sg:address":"Moltkestr. 10",
    "sg:city":"Schwelm",
    "sg:phone":"+49 2336/3326",
    "sg:postcode":"58332",
    "sg:province":"Nordrhein-Westfalen",
    "wof:name":"H. Heim Rechtsanw\u00e4lte",
    "wof:placetype":"venue"
},
  "geometry": {"coordinates":[7.2953019142,51.2869148254],"type":"Point"}
}