{
  "type": "Feature",
  "properties": {
    "iso:country":"DE",
    "sg:address":"Obermarkt 44",
    "sg:city":"Mittenwald",
    "sg:phone":"+49 8823/5876",
    "sg:postcode":"82481",
    "sg:province":"Bayern",
    "wof:name":"Gottfried Rieder",
    "wof:placetype":"venue"
},
  "geometry": {"coordinates":[11.2600641251,47.4405822754],"type":"Point"}
}