{
  "type": "Feature",
  "properties": {
    "iso:country":"DE",
    "sg:address":"Meisastr. 42",
    "sg:city":"Mei\u00dfen",
    "sg:phone":"+49 3521/457873",
    "sg:postcode":"01662",
    "sg:province":"Sachsen",
    "wof:name":"Mpm Saxonia - Manufactur F\u00fcr Porzellanmalerei & K\u00fcnstl. De-",
    "wof:placetype":"venue"
},
  "geometry": {"coordinates":[13.4644260406,51.1655921936],"type":"Point"}
}