{
  "type": "Feature",
  "properties": {
    "iso:country":"DE",
    "sg:address":"Scheurlstr. 5",
    "sg:city":"N\u00fcrnberg",
    "sg:phone":"+49 911/4719797",
    "sg:postcode":"90478",
    "sg:province":"Bayern",
    "wof:name":"Paul Slavik Architekt",
    "wof:placetype":"venue"
},
  "geometry": {"coordinates":[11.089482,49.445709],"type":"Point"}
}