{
  "type": "Feature",
  "properties": {
    "iso:country":"DE",
    "sg:address":"Stadtring 15",
    "sg:city":"Bielefeld",
    "sg:phone":"+49 521/942360",
    "sg:postcode":"33647",
    "sg:province":"Nordrhein-Westfalen",
    "wof:name":"Karl-heinz Lipski Und Klaus-dieter Grothus",
    "wof:placetype":"venue"
},
  "geometry": {"coordinates":[8.5193214417,51.9817199707],"type":"Point"}
}