{
  "type": "Feature",
  "properties": {
    "iso:country":"DE",
    "sg:address":"Kreisstr. 80",
    "sg:city":"Wahlhausen",
    "sg:postcode":"37318",
    "sg:province":"Th\u00fcringen",
    "wof:name":"Adib Agrar- Dienstleis- Tungs- Industrie- Und",
    "wof:placetype":"venue"
},
  "geometry": {"coordinates":[9.97737,51.294853],"type":"Point"}
}