{
  "type": "Feature",
  "properties": {
    "iso:country":"DE",
    "sg:address":"Kirnsteinstr. 15",
    "sg:city":"Rosenheim",
    "sg:phone":"+49 8031/66653",
    "sg:postcode":"83026",
    "sg:province":"Bayern",
    "wof:name":"Generalagentur Baier & Sohn",
    "wof:placetype":"venue"
},
  "geometry": {"coordinates":[12.1117677689,47.8311958313],"type":"Point"}
}