{
  "type": "Feature",
  "properties": {
    "iso:country":"DE",
    "sg:address":"Synagogenstr. 12",
    "sg:city":"Witten",
    "sg:phone":"+49 2302/56025",
    "sg:postcode":"58452",
    "sg:province":"Nordrhein-Westfalen",
    "wof:name":"U. Reinecke Schilder Und Lichtreklame",
    "wof:placetype":"venue"
},
  "geometry": {"coordinates":[7.331831,51.441479],"type":"Point"}
}