{
  "type": "Feature",
  "properties": {
    "iso:country":"DE",
    "sg:address":"Am Struckteich 4",
    "sg:city":"Zarpen",
    "sg:phone":"+49 4533/1286",
    "sg:postcode":"23619",
    "sg:province":"Schleswig-Holstein",
    "wof:name":"K\u00f6hler Und Partner Ingenieure Maschinen- Und",
    "wof:placetype":"venue"
},
  "geometry": {"coordinates":[10.5141353607,53.8735771179],"type":"Point"}
}