{
  "type": "Feature",
  "properties": {
    "iso:country":"DE",
    "sg:address":"Zu den Lippewiesen 1",
    "sg:city":"Haltern",
    "sg:phone":"+49 2364/2625",
    "sg:postcode":"45721",
    "sg:province":"Nordrhein-Westfalen",
    "wof:name":"Heinz Kohl Gmbh",
    "wof:placetype":"venue"
},
  "geometry": {"coordinates":[7.186803,51.73262],"type":"Point"}
}