{
  "type": "Feature",
  "properties": {
    "iso:country":"DE",
    "sg:address":"H\u00fclsdonker Str. 7",
    "sg:city":"Moers",
    "sg:phone":"+49 2841/18306",
    "sg:postcode":"47441",
    "sg:province":"Nordrhein-Westfalen",
    "wof:name":"Pizza Taxi Arcobaleno",
    "wof:placetype":"venue"
},
  "geometry": {"coordinates":[6.620039,51.452522],"type":"Point"}
}