{
  "type": "Feature",
  "properties": {
    "iso:country":"DE",
    "sg:address":"Brauhausstr. 1",
    "sg:city":"Mei\u00dfen",
    "sg:phone":"+49 3521/733705",
    "sg:postcode":"01662",
    "sg:province":"Sachsen",
    "wof:name":"Gottfried Bastian",
    "wof:placetype":"venue"
},
  "geometry": {"coordinates":[13.4825153351,51.1619911194],"type":"Point"}
}