{
  "type": "Feature",
  "properties": {
    "iso:country":"DE",
    "sg:address":"Wei\u00dfdornweg 12",
    "sg:city":"Gleichen",
    "sg:phone":"+49 5592/1888",
    "sg:postcode":"37130",
    "sg:province":"Niedersachsen",
    "wof:name":"Indako Internet-daten- Und Kommunikationstechnik Gmbh",
    "wof:placetype":"venue"
},
  "geometry": {"coordinates":[9.985724,51.472664],"type":"Point"}
}