{
  "type": "Feature",
  "properties": {
    "iso:country":"DE",
    "sg:address":"Leopoldstr. 8",
    "sg:city":"Marktredwitz",
    "sg:phone":"+49 9231/5995",
    "sg:postcode":"95615",
    "sg:province":"Bayern",
    "wof:name":"Holz",
    "wof:placetype":"venue"
},
  "geometry": {"coordinates":[12.083113,49.999832],"type":"Point"}
}