{
  "type": "Feature",
  "properties": {
    "iso:country":"DE",
    "sg:address":"Flaper Schulweg 44",
    "sg:city":"Kirchhundem",
    "sg:phone":"+49 2723/3464",
    "sg:postcode":"57399",
    "sg:province":"Nordrhein-Westfalen",
    "wof:name":"A. Grap",
    "wof:placetype":"venue"
},
  "geometry": {"coordinates":[8.092118,51.078903],"type":"Point"}
}