{
  "type": "Feature",
  "properties": {
    "iso:country":"DE",
    "sg:address":"Bahnhofsweg 11",
    "sg:city":"Rinteln",
    "sg:phone":"+49 5751/5141",
    "sg:postcode":"31737",
    "sg:province":"Niedersachsen",
    "wof:name":"Manfred Backer",
    "wof:placetype":"venue"
},
  "geometry": {"coordinates":[9.0792760849,52.1961555481],"type":"Point"}
}