{
  "type": "Feature",
  "properties": {
    "iso:country":"DE",
    "sg:address":"Igelweg 12",
    "sg:city":"Monheim",
    "sg:phone":"+49 2173/32655",
    "sg:postcode":"40789",
    "sg:province":"Nordrhein-Westfalen",
    "wof:name":"A. Wandtke",
    "wof:placetype":"venue"
},
  "geometry": {"coordinates":[6.904537,51.097862],"type":"Point"}
}