{
  "type": "Feature",
  "properties": {
    "iso:country":"DE",
    "sg:address":"Warburgring 67",
    "sg:city":"Homburg",
    "sg:phone":"+49 6841/12134",
    "sg:postcode":"66424",
    "sg:province":"Saarland",
    "wof:name":"Q New Services Ag",
    "wof:placetype":"venue"
},
  "geometry": {"coordinates":[7.3371658325,49.3054733276],"type":"Point"}
}