{
  "type": "Feature",
  "properties": {
    "iso:country":"DE",
    "sg:address":"H\u00f6llentalstr. 37",
    "sg:city":"Freiburg",
    "sg:phone":"+49 761/65132",
    "sg:postcode":"79117",
    "sg:province":"Baden-W\u00fcrttemberg",
    "wof:name":"Josef Hohler",
    "wof:placetype":"venue"
},
  "geometry": {"coordinates":[7.9021430016,47.9798622131],"type":"Point"}
}