{
  "type": "Feature",
  "properties": {
    "iso:country":"DE",
    "sg:address":"Woschkower Weg 10",
    "sg:city":"Gro\u00dfr\u00e4schen",
    "sg:phone":"+49 4935/753290",
    "sg:postcode":"01983",
    "sg:province":"Brandenburg",
    "wof:name":"Starz Gmbh",
    "wof:placetype":"venue"
},
  "geometry": {"coordinates":[14.023784,51.593678],"type":"Point"}
}