{
  "type": "Feature",
  "properties": {
    "iso:country":"DE",
    "sg:address":"Gartenstr. 10",
    "sg:city":"Gelenau",
    "sg:phone":"+49 37297/7231",
    "sg:postcode":"09423",
    "sg:province":"Sachsen",
    "wof:name":"K. Salmonat",
    "wof:placetype":"venue"
},
  "geometry": {"coordinates":[12.983492,50.715851],"type":"Point"}
}