{
  "type": "Feature",
  "properties": {
    "iso:country":"DE",
    "sg:address":"Hauptstr. 39",
    "sg:city":"Sohren",
    "sg:phone":"+49 6543/2139",
    "sg:postcode":"55487",
    "sg:province":"Rheinland-Pfalz",
    "wof:name":"Walter D\u00f6rn",
    "wof:placetype":"venue"
},
  "geometry": {"coordinates":[7.3059029579,49.930721283],"type":"Point"}
}