{
  "type": "Feature",
  "properties": {
    "iso:country":"DE",
    "sg:address":"Gutenbergstr. 1",
    "sg:city":"Ostrhauderfehn",
    "sg:postcode":"26842",
    "sg:province":"Niedersachsen",
    "wof:name":"Windpark Moorgut Ostrhauderfehn Gmbh & Co. Kg",
    "wof:placetype":"venue"
},
  "geometry": {"coordinates":[7.6215977669,53.1373443604],"type":"Point"}
}