{
  "type": "Feature",
  "properties": {
    "iso:country":"DE",
    "sg:address":"Eppaner Str. 6 a",
    "sg:city":"Augsburg",
    "sg:phone":"+49 821/720800",
    "sg:postcode":"86165",
    "sg:province":"Bayern",
    "wof:name":"Br\u00fchl Acryl Design",
    "wof:placetype":"venue"
},
  "geometry": {"coordinates":[10.9428243637,48.3796272278],"type":"Point"}
}