{
  "type": "Feature",
  "properties": {
    "iso:country":"DE",
    "sg:address":"Heimbacher Weg",
    "sg:city":"Meisenheim",
    "sg:postcode":"55590",
    "sg:province":"Rheinland-Pfalz",
    "wof:name":"Rewi-regionaler Wirtschafts- Informationsdienst Gmbh",
    "wof:placetype":"venue"
},
  "geometry": {"coordinates":[7.6620287895,49.7130393982],"type":"Point"}
}