{
  "type": "Feature",
  "properties": {
    "iso:country":"DE",
    "sg:address":"Baumstr. 3638",
    "sg:city":"Solingen",
    "sg:phone":"+49 212/10011",
    "sg:postcode":"42651",
    "sg:province":"Nordrhein-Westfalen",
    "wof:name":"Hoppe & Cie. Inh. Helmut Giesen",
    "wof:placetype":"venue"
},
  "geometry": {"coordinates":[7.09273,51.17329],"type":"Point"}
}