{
  "type": "Feature",
  "properties": {
    "iso:country":"DE",
    "sg:address":"Lange Str. 95",
    "sg:city":"Arnis",
    "sg:postcode":"24399",
    "sg:province":"Schleswig-Holstein",
    "wof:name":"Nautical Publications Gmbh",
    "wof:placetype":"venue"
},
  "geometry": {"coordinates":[9.93041,54.629826],"type":"Point"}
}