{
  "type": "Feature",
  "properties": {
    "iso:country":"DE",
    "sg:address":"Vaalser Str. 17",
    "sg:city":"Aachen",
    "sg:phone":"+49 241/72011",
    "sg:postcode":"52064",
    "sg:province":"Nordrhein-Westfalen",
    "wof:name":"Helmer Und Seiler",
    "wof:placetype":"venue"
},
  "geometry": {"coordinates":[6.07373,50.770741],"type":"Point"}
}