{
  "type": "Feature",
  "properties": {
    "iso:country":"DE",
    "sg:address":"Schaapkamp 25",
    "sg:city":"Gro\u00dfhansdorf",
    "sg:phone":"+49 4102/67312",
    "sg:postcode":"22927",
    "sg:province":"Schleswig-Holstein",
    "wof:name":"Global Grundbesitz Und Verwaltung Gmbh",
    "wof:placetype":"venue"
},
  "geometry": {"coordinates":[10.2877988815,53.6650810242],"type":"Point"}
}