{
  "type": "Feature",
  "properties": {
    "iso:country":"DE",
    "sg:address":"Am Marienpfad 55",
    "sg:city":"Mainz",
    "sg:postcode":"55128",
    "sg:province":"Rheinland-Pfalz",
    "wof:name":"Yukon Investments Gmbh",
    "wof:placetype":"venue"
},
  "geometry": {"coordinates":[8.25228,49.980469],"type":"Point"}
}