{
  "type": "Feature",
  "properties": {
    "iso:country":"DE",
    "sg:address":"Vorsetzen 53",
    "sg:city":"Hamburg",
    "sg:phone":"+49 40/3193971",
    "sg:postcode":"20459",
    "sg:province":"Hamburg",
    "wof:name":"Ulrike Donat Rechtsanw\u00e4ltin",
    "wof:placetype":"venue"
},
  "geometry": {"coordinates":[9.9761209488,53.544670105],"type":"Point"}
}