{
  "type": "Feature",
  "properties": {
    "iso:country":"DE",
    "sg:address":"Marktplatz 11",
    "sg:city":"Darmstadt",
    "sg:phone":"+49 6151/21441",
    "sg:postcode":"64283",
    "sg:province":"Hessen",
    "wof:name":"Ingrid Bachmann Farm Naturkost",
    "wof:placetype":"venue"
},
  "geometry": {"coordinates":[8.6560163498,49.8725166321],"type":"Point"}
}