{
  "type": "Feature",
  "properties": {
    "iso:country":"DE",
    "sg:address":"Anton-Esser-Str. 1",
    "sg:city":"Lindlar",
    "sg:phone":"+49 2266/470981",
    "sg:postcode":"51789",
    "sg:province":"Nordrhein-Westfalen",
    "wof:name":"G\u00fcnter Rocholz Steuerberater",
    "wof:placetype":"venue"
},
  "geometry": {"coordinates":[7.3782539368,51.0487060547],"type":"Point"}
}