{
  "type": "Feature",
  "properties": {
    "iso:country":"DE",
    "sg:address":"Am Dreifaltigkeitskloster 26",
    "sg:city":"Krefeld",
    "sg:phone":"+49 2151/315018",
    "sg:postcode":"47807",
    "sg:province":"Nordrhein-Westfalen",
    "wof:name":"V\u00f6llm Verwaltungs-gmbh",
    "wof:placetype":"venue"
},
  "geometry": {"coordinates":[6.575294,51.315487],"type":"Point"}
}