{
  "type": "Feature",
  "properties": {
    "iso:country":"DE",
    "sg:address":"Esteweg 1",
    "sg:city":"Hollenstedt",
    "sg:phone":"+49 4165/80539",
    "sg:postcode":"21279",
    "sg:province":"Niedersachsen",
    "wof:name":"Helmut Stemmann",
    "wof:placetype":"venue"
},
  "geometry": {"coordinates":[9.712637,53.386173],"type":"Point"}
}