{
  "type": "Feature",
  "properties": {
    "iso:country":"DE",
    "sg:address":"Langgasse 22-24",
    "sg:city":"Butzbach",
    "sg:phone":"+49 6033/96470",
    "sg:postcode":"35510",
    "sg:province":"Hessen",
    "wof:name":"Tbe Habermehl Anlagenbau Gmbh & Co. Kg",
    "wof:placetype":"venue"
},
  "geometry": {"coordinates":[8.672465,50.433167],"type":"Point"}
}