{
  "type": "Feature",
  "properties": {
    "iso:country":"DE",
    "sg:address":"Wernigeroder Str. 39",
    "sg:city":"Zepernick",
    "sg:phone":"+49 30/9444717",
    "sg:postcode":"16341",
    "sg:province":"Brandenburg",
    "wof:name":"Joachim Martin Gmbh",
    "wof:placetype":"venue"
},
  "geometry": {"coordinates":[13.551536,52.650215],"type":"Point"}
}