{
  "type": "Feature",
  "properties": {
    "iso:country":"DE",
    "sg:address":"Admiral-Hipper-Str. 15",
    "sg:city":"Weilheim",
    "sg:phone":"+49 881/61808",
    "sg:postcode":"82362",
    "sg:province":"Bayern",
    "wof:name":"Alfred Bogen Inh. Irmela Dietlmeier",
    "wof:placetype":"venue"
},
  "geometry": {"coordinates":[11.1438980103,47.8391838074],"type":"Point"}
}