{
  "type": "Feature",
  "properties": {
    "iso:country":"DE",
    "sg:address":"Hauptstr. 17",
    "sg:city":"Gernsbach",
    "sg:phone":"+49 7224/7902",
    "sg:postcode":"76593",
    "sg:province":"Baden-W\u00fcrttemberg",
    "wof:name":"Brezelkorb",
    "wof:placetype":"venue"
},
  "geometry": {"coordinates":[8.3345861435,48.7636604309],"type":"Point"}
}