{
  "type": "Feature",
  "properties": {
    "iso:country":"DE",
    "sg:address":"Kapellstr. 21",
    "sg:city":"Albstadt",
    "sg:phone":"+49 7431/51459",
    "sg:postcode":"72458",
    "sg:province":"Baden-W\u00fcrttemberg",
    "wof:name":"S. Fu\u00df",
    "wof:placetype":"venue"
},
  "geometry": {"coordinates":[9.0251026154,48.2132072449],"type":"Point"}
}