{
  "type": "Feature",
  "properties": {
    "iso:country":"DE",
    "sg:address":"K\u00e4mmereigasse 10",
    "sg:city":"Bayreuth",
    "sg:phone":"+49 921/64455",
    "sg:postcode":"95444",
    "sg:province":"Bayern",
    "wof:name":"Folie Douce",
    "wof:placetype":"venue"
},
  "geometry": {"coordinates":[11.5740623474,49.9439811707],"type":"Point"}
}