{
  "type": "Feature",
  "properties": {
    "iso:country":"DE",
    "sg:address":"In den Obstwiesen 92",
    "sg:city":"Berg",
    "sg:phone":"+49 751/5577801",
    "sg:postcode":"88276",
    "sg:province":"Baden-W\u00fcrttemberg",
    "wof:name":"Phi Philipp Haudek Informatik Gmbh",
    "wof:placetype":"venue"
},
  "geometry": {"coordinates":[9.5995607376,47.826171875],"type":"Point"}
}