{
  "type": "Feature",
  "properties": {
    "iso:country":"DE",
    "sg:address":"Kirchheimer Str. 24",
    "sg:city":"Dackenheim",
    "sg:phone":"+49 6353/3615",
    "sg:postcode":"67273",
    "sg:province":"Rheinland-Pfalz",
    "wof:name":"G\u00e4stehaus Manfred Herr",
    "wof:placetype":"venue"
},
  "geometry": {"coordinates":[8.184211731,49.5226364136],"type":"Point"}
}