{
  "type": "Feature",
  "properties": {
    "iso:country":"DE",
    "sg:address":"Breite Str. 24",
    "sg:city":"Potsdam",
    "sg:phone":"+49 331/974117",
    "sg:postcode":"14467",
    "sg:province":"Brandenburg",
    "wof:name":"Seerose Club Maritim",
    "wof:placetype":"venue"
},
  "geometry": {"coordinates":[13.058634758,52.3998641968],"type":"Point"}
}