{
  "type": "Feature",
  "properties": {
    "iso:country":"DE",
    "sg:address":"Bahnhofstr. 32",
    "sg:city":"Treuen",
    "sg:phone":"+49 37468/2841",
    "sg:postcode":"08233",
    "sg:province":"Sachsen",
    "wof:name":"R. Barthel",
    "wof:placetype":"venue"
},
  "geometry": {"coordinates":[12.3012161255,50.5453262329],"type":"Point"}
}