{
  "type": "Feature",
  "properties": {
    "iso:country":"DE",
    "sg:address":"F\u00e4hrstr. 5a",
    "sg:city":"Ludwigsburg",
    "sg:phone":"+49 7141/55979",
    "sg:postcode":"71642",
    "sg:province":"Baden-W\u00fcrttemberg",
    "wof:name":"Dietmar Eichler",
    "wof:placetype":"venue"
},
  "geometry": {"coordinates":[9.219527,48.911816],"type":"Point"}
}