{
  "type": "Feature",
  "properties": {
    "iso:country":"DE",
    "sg:address":"Gerhart-Hauptmann-Ring 7",
    "sg:city":"Selm",
    "sg:phone":"+49 2592/3600",
    "sg:postcode":"59379",
    "sg:province":"Nordrhein-Westfalen",
    "wof:name":"Ok Zeichenb\u00fcro F\u00fcr Elektrotechnik Gmbh",
    "wof:placetype":"venue"
},
  "geometry": {"coordinates":[7.4506177902,51.697555542],"type":"Point"}
}