{
  "type": "Feature",
  "properties": {
    "iso:country":"DE",
    "sg:address":"Keltenweg 2",
    "sg:city":"Au",
    "sg:phone":"+49 8752/7966",
    "sg:postcode":"84072",
    "sg:province":"Bayern",
    "wof:name":"Spaghetti Rapido Teigwarenmaschinen Gmbh",
    "wof:placetype":"venue"
},
  "geometry": {"coordinates":[11.748307,48.555695],"type":"Point"}
}