{
  "type": "Feature",
  "properties": {
    "iso:country":"DE",
    "sg:address":"Wolfstr. 5",
    "sg:city":"B\u00fcrstadt",
    "sg:phone":"+49 6206/8035",
    "sg:postcode":"68642",
    "sg:province":"Hessen",
    "wof:name":"Franz Held",
    "wof:placetype":"venue"
},
  "geometry": {"coordinates":[8.4668474197,49.6432647705],"type":"Point"}
}