{
  "type": "Feature",
  "properties": {
    "iso:country":"DE",
    "sg:address":"Bopparder Str. 39",
    "sg:city":"Kastellaun",
    "sg:postcode":"56288",
    "sg:province":"Rheinland-Pfalz",
    "wof:name":"Brust Service Center E. K.",
    "wof:placetype":"venue"
},
  "geometry": {"coordinates":[7.444199,50.073395],"type":"Point"}
}