{
  "type": "Feature",
  "properties": {
    "iso:country":"DE",
    "sg:address":"Dillsteiner Str. 14",
    "sg:city":"Pforzheim",
    "sg:phone":"+49 7231/29700",
    "sg:postcode":"75173",
    "sg:province":"Baden-W\u00fcrttemberg",
    "wof:name":"G. Eickele",
    "wof:placetype":"venue"
},
  "geometry": {"coordinates":[8.696921,48.888512],"type":"Point"}
}