{
  "type": "Feature",
  "properties": {
    "iso:country":"DE",
    "sg:address":"Bornstr. 7",
    "sg:city":"Eschenburg",
    "sg:phone":"+49 2774/6172",
    "sg:postcode":"35713",
    "sg:province":"Hessen",
    "wof:name":"Paul Schneider",
    "wof:placetype":"venue"
},
  "geometry": {"coordinates":[8.335575,50.809349],"type":"Point"}
}