{
  "type": "Feature",
  "properties": {
    "iso:country":"DE",
    "sg:address":"Biesengrundbreite 1",
    "sg:city":"M\u00f6ser",
    "sg:phone":"+49 39222/2478",
    "sg:postcode":"39291",
    "sg:province":"Sachsen-Anhalt",
    "wof:name":"Ruth Altenkirch",
    "wof:placetype":"venue"
},
  "geometry": {"coordinates":[11.782761,52.214886],"type":"Point"}
}