{
  "type": "Feature",
  "properties": {
    "iso:country":"DE",
    "sg:address":"Dorfstra\u00dfe",
    "sg:city":"Niederdorf",
    "sg:phone":"+49 37296/404980",
    "sg:postcode":"09366",
    "sg:province":"Sachsen",
    "wof:name":"Nh-haustechnik Heizung, Sanit\u00e4r, L\u00fcftung Und Klima",
    "wof:placetype":"venue"
},
  "geometry": {"coordinates":[12.7868518829,50.7204208374],"type":"Point"}
}