{
  "type": "Feature",
  "properties": {
    "iso:country":"DE",
    "sg:address":"Ostergrube 13",
    "sg:city":"Hannover",
    "sg:phone":"+49 511/9525912",
    "sg:postcode":"30559",
    "sg:province":"Niedersachsen",
    "wof:name":"Glasdachges. Mbh",
    "wof:placetype":"venue"
},
  "geometry": {"coordinates":[9.861082077,52.3616638184],"type":"Point"}
}