{
  "type": "Feature",
  "properties": {
    "iso:country":"DE",
    "sg:address":"Seebadallee 46",
    "sg:city":"Rangsdorf",
    "sg:phone":"+49 30/2137662",
    "sg:postcode":"15834",
    "sg:province":"Brandenburg",
    "wof:name":"Dieter Mikolai",
    "wof:placetype":"venue"
},
  "geometry": {"coordinates":[13.425278,52.292145],"type":"Point"}
}