{
  "type": "Feature",
  "properties": {
    "iso:country":"DE",
    "sg:address":"Lindenstr. 14",
    "sg:city":"Daun",
    "sg:phone":"+49 6592/2239",
    "sg:postcode":"54550",
    "sg:province":"Rheinland-Pfalz",
    "wof:name":"Schneider Druck Gmbh",
    "wof:placetype":"venue"
},
  "geometry": {"coordinates":[6.831065,50.195728],"type":"Point"}
}