{
  "type": "Feature",
  "properties": {
    "iso:country":"DE",
    "sg:address":"Forststr. 14",
    "sg:city":"Baiersbronn",
    "sg:phone":"+49 7442/84510",
    "sg:postcode":"72270",
    "sg:province":"Baden-W\u00fcrttemberg",
    "wof:name":"Haus Am Kurgarten",
    "wof:placetype":"venue"
},
  "geometry": {"coordinates":[8.3740062714,48.5028190613],"type":"Point"}
}