{
  "type": "Feature",
  "properties": {
    "iso:country":"DE",
    "sg:address":"Schulstr. 14 c",
    "sg:city":"J\u00e4mlitz",
    "sg:phone":"+49 35771/55587",
    "sg:postcode":"03130",
    "sg:province":"Brandenburg",
    "wof:name":"U. Guder",
    "wof:placetype":"venue"
},
  "geometry": {"coordinates":[14.663772583,51.5699653625],"type":"Point"}
}