{
  "type": "Feature",
  "properties": {
    "iso:country":"DE",
    "sg:address":"Lindenplatz 4",
    "sg:city":"Miesbach",
    "sg:phone":"+49 8025/3762",
    "sg:postcode":"83714",
    "sg:province":"Bayern",
    "wof:name":"Kurt Holzfurtner",
    "wof:placetype":"venue"
},
  "geometry": {"coordinates":[11.829827,47.787384],"type":"Point"}
}