{
  "type": "Feature",
  "properties": {
    "iso:country":"DE",
    "sg:address":"Frauensteigstr. 26",
    "sg:city":"Buchenbach",
    "sg:phone":"+49 7661/62547",
    "sg:postcode":"79256",
    "sg:province":"Baden-W\u00fcrttemberg",
    "wof:name":"Widmann Geb\u00e4udereinigungs- Und Geb\u00e4udedienstl. Gmbh",
    "wof:placetype":"venue"
},
  "geometry": {"coordinates":[8.003179,47.960686],"type":"Point"}
}