{
  "type": "Feature",
  "properties": {
    "iso:country":"DE",
    "sg:address":"Hauptstr. 86",
    "sg:city":"Wormstedt",
    "sg:phone":"+49 36464/280",
    "sg:postcode":"99510",
    "sg:province":"Th\u00fcringen",
    "wof:name":"R & R Medizin- Technische Ger\u00e4te Gmbh",
    "wof:placetype":"venue"
},
  "geometry": {"coordinates":[11.509604,51.023163],"type":"Point"}
}