{
  "type": "Feature",
  "properties": {
    "iso:country":"DE",
    "sg:address":"Bistard 21",
    "sg:city":"Viersen",
    "sg:phone":"+49 2162/41170",
    "sg:postcode":"41751",
    "sg:province":"Nordrhein-Westfalen",
    "wof:name":"Maria Eulenpesch",
    "wof:placetype":"venue"
},
  "geometry": {"coordinates":[6.333804,51.276508],"type":"Point"}
}