{
  "type": "Feature",
  "properties": {
    "iso:country":"DE",
    "sg:address":"Melchersstr. 80",
    "sg:city":"M\u00fcnster",
    "sg:postcode":"48149",
    "sg:province":"Nordrhein-Westfalen",
    "wof:name":"Wollversand Wolfgang Hesse",
    "wof:placetype":"venue"
},
  "geometry": {"coordinates":[7.614216,51.971558],"type":"Point"}
}