{
  "type": "Feature",
  "properties": {
    "iso:country":"DE",
    "sg:address":"Petersplatz 4",
    "sg:city":"Piding",
    "sg:phone":"+49 8651/4593",
    "sg:postcode":"83451",
    "sg:province":"Bayern",
    "wof:name":"G\u00e4stehaus Anna Gruber",
    "wof:placetype":"venue"
},
  "geometry": {"coordinates":[12.9121322632,47.7698173523],"type":"Point"}
}