{
  "type": "Feature",
  "properties": {
    "iso:country":"DE",
    "sg:address":"Maximiliansh\u00f6he 12a",
    "sg:city":"Garmisch-Partenkirchen",
    "sg:postcode":"82467",
    "sg:province":"Bayern",
    "wof:name":"K. Hain",
    "wof:placetype":"venue"
},
  "geometry": {"coordinates":[11.0654268265,47.4933433533],"type":"Point"}
}