{
  "type": "Feature",
  "properties": {
    "iso:country":"DE",
    "sg:address":"Veit-Sto\u00df-Str. 16",
    "sg:city":"Schweinfurt",
    "sg:postcode":"97422",
    "sg:province":"Bayern",
    "wof:name":"Isc Sportmanagement Ohg",
    "wof:placetype":"venue"
},
  "geometry": {"coordinates":[10.2344827652,50.0715065002],"type":"Point"}
}