{
  "type": "Feature",
  "properties": {
    "iso:country":"DE",
    "sg:address":"Wilhelm-Gericke-Str. 18",
    "sg:city":"Berlin",
    "sg:phone":"+49 30/4629659",
    "sg:postcode":"13437",
    "sg:province":"Berlin",
    "wof:name":"Michael & Maria Kaljushni",
    "wof:placetype":"venue"
},
  "geometry": {"coordinates":[13.3357143402,52.5851325989],"type":"Point"}
}