{
  "type": "Feature",
  "properties": {
    "iso:country":"DE",
    "sg:address":"Sonnenb\u00fchl 5",
    "sg:city":"Bad Waldsee",
    "sg:postcode":"88339",
    "sg:province":"Baden-W\u00fcrttemberg",
    "wof:name":"Amo Management Gmbh",
    "wof:placetype":"venue"
},
  "geometry": {"coordinates":[9.728285,47.894955],"type":"Point"}
}