{
  "type": "Feature",
  "properties": {
    "iso:country":"DE",
    "sg:address":"Bahnhofstr. 17",
    "sg:city":"Holle",
    "sg:phone":"+49 5062/385",
    "sg:postcode":"31188",
    "sg:province":"Niedersachsen",
    "wof:name":"Hotel-restaurant J\u00e4gerhof",
    "wof:placetype":"venue"
},
  "geometry": {"coordinates":[10.1515331268,52.0942611694],"type":"Point"}
}