{
  "type": "Feature",
  "properties": {
    "iso:country":"DE",
    "sg:address":"Bachgasse 27",
    "sg:city":"Tanna",
    "sg:phone":"+49 36646/21483",
    "sg:postcode":"07922",
    "sg:province":"Th\u00fcringen",
    "wof:name":"Albert Rabe",
    "wof:placetype":"venue"
},
  "geometry": {"coordinates":[11.854298,50.492813],"type":"Point"}
}