{
  "type": "Feature",
  "properties": {
    "iso:country":"DE",
    "sg:address":"Kunaustr. 1",
    "sg:city":"Hamburg",
    "sg:phone":"+49 40/6013785",
    "sg:postcode":"22393",
    "sg:province":"Hamburg",
    "wof:name":"Fridericus-apotheke",
    "wof:placetype":"venue"
},
  "geometry": {"coordinates":[10.110623,53.652969],"type":"Point"}
}