{
  "type": "Feature",
  "properties": {
    "iso:country":"DE",
    "sg:address":"Streitauer Hauptstr. 40",
    "sg:city":"Gefrees",
    "sg:phone":"+49 9254/427",
    "sg:postcode":"95482",
    "sg:province":"Bayern",
    "wof:name":"A. Opel",
    "wof:placetype":"venue"
},
  "geometry": {"coordinates":[11.7031621933,50.1143951416],"type":"Point"}
}