{
  "type": "Feature",
  "properties": {
    "iso:country":"DE",
    "sg:address":"Oberstr. 26",
    "sg:city":"Ratingen",
    "sg:phone":"+49 2102/22808",
    "sg:postcode":"40878",
    "sg:province":"Nordrhein-Westfalen",
    "wof:name":"Pollmeier",
    "wof:placetype":"venue"
},
  "geometry": {"coordinates":[6.8516311646,51.2978057861],"type":"Point"}
}