{
  "type": "Feature",
  "properties": {
    "iso:country":"DE",
    "sg:address":"Pinneberger Str. 71",
    "sg:city":"Wedel",
    "sg:phone":"+49 4103/2278",
    "sg:postcode":"22880",
    "sg:province":"Schleswig-Holstein",
    "wof:name":"Heinrich Bosch Inh. Claus Eydeler",
    "wof:placetype":"venue"
},
  "geometry": {"coordinates":[9.707915,53.589352],"type":"Point"}
}