{
  "type": "Feature",
  "properties": {
    "iso:country":"DE",
    "sg:address":"Am Ohlendorffturm 31",
    "sg:city":"Hamburg",
    "sg:phone":"+49 40/6739780",
    "sg:postcode":"22149",
    "sg:province":"Hamburg",
    "wof:name":"Biehler Production Wolfgang M. Biehler",
    "wof:placetype":"venue"
},
  "geometry": {"coordinates":[10.1690683365,53.5956230164],"type":"Point"}
}