{
  "type": "Feature",
  "properties": {
    "iso:country":"DE",
    "sg:address":"Teichstr. 8",
    "sg:city":"Pirmasens",
    "sg:phone":"+49 6331/245339",
    "sg:postcode":"66953",
    "sg:province":"Rheinland-Pfalz",
    "wof:name":"Ms Leasefinance Finanzierungs- Vermittlung Und Leasing",
    "wof:placetype":"venue"
},
  "geometry": {"coordinates":[7.5995459557,49.2030334473],"type":"Point"}
}