{
  "type": "Feature",
  "properties": {
    "iso:country":"DE",
    "sg:address":"Albstr. 92",
    "sg:city":"Ulm",
    "sg:phone":"+49 731/1740",
    "sg:postcode":"89081",
    "sg:province":"Baden-W\u00fcrttemberg",
    "wof:name":"M\u00fcller & Schneider Immobilienverwaltungs",
    "wof:placetype":"venue"
},
  "geometry": {"coordinates":[9.9852027893,48.4283065796],"type":"Point"}
}