{
  "type": "Feature",
  "properties": {
    "iso:country":"DE",
    "sg:address":"Ingelheimer Str. 2",
    "sg:city":"Essen",
    "sg:phone":"+49 201/755748",
    "sg:postcode":"45145",
    "sg:province":"Nordrhein-Westfalen",
    "wof:name":"Pizzeria Nuova Italia",
    "wof:placetype":"venue"
},
  "geometry": {"coordinates":[6.9689440727,51.4474563599],"type":"Point"}
}