{
  "type": "Feature",
  "properties": {
    "iso:country":"DE",
    "sg:address":"Spelzengasse 13",
    "sg:city":"Bischofsheim",
    "sg:phone":"+49 6144",
    "sg:postcode":"65474",
    "sg:province":"Hessen",
    "wof:name":"Komitee-kappen",
    "wof:placetype":"venue"
},
  "geometry": {"coordinates":[8.359397,49.989311],"type":"Point"}
}