{
  "type": "Feature",
  "properties": {
    "iso:country":"DE",
    "sg:address":"Hauptstr. 41",
    "sg:city":"A\u00dflar",
    "sg:phone":"+49 6443/9542",
    "sg:postcode":"35614",
    "sg:province":"Hessen",
    "wof:name":"Aral Ag",
    "wof:placetype":"venue"
},
  "geometry": {"coordinates":[8.4623603821,50.5907592773],"type":"Point"}
}