{
  "type": "Feature",
  "properties": {
    "iso:country":"DE",
    "sg:address":"Niederflurstr. 3",
    "sg:city":"Zeltingen-Rachtig",
    "sg:phone":"+49 6532/2021",
    "sg:postcode":"54492",
    "sg:province":"Rheinland-Pfalz",
    "wof:name":"Jos. Knoop",
    "wof:placetype":"venue"
},
  "geometry": {"coordinates":[7.0104842186,49.9754829407],"type":"Point"}
}