{
  "type": "Feature",
  "properties": {
    "iso:country":"DE",
    "sg:address":"Margaretenstr. 22",
    "sg:city":"Friedeburg",
    "sg:phone":"+49 4465/1713",
    "sg:postcode":"26446",
    "sg:province":"Niedersachsen",
    "wof:name":"Reinhard Saadthoff",
    "wof:placetype":"venue"
},
  "geometry": {"coordinates":[7.8286671638,53.4558677673],"type":"Point"}
}