{
  "type": "Feature",
  "properties": {
    "iso:country":"DE",
    "sg:address":"Blumenstr 4",
    "sg:city":"Waldaschaff",
    "sg:phone":"+49 6095/97120",
    "sg:postcode":"63857",
    "sg:province":"Bayern",
    "wof:name":"Ubn Untermain Business Networks Gmbh",
    "wof:placetype":"venue"
},
  "geometry": {"coordinates":[9.290185,49.974388],"type":"Point"}
}