{
  "type": "Feature",
  "properties": {
    "iso:country":"DE",
    "sg:address":"Wilhelm-Leuschner-Str. 48",
    "sg:city":"Darmstadt",
    "sg:phone":"+49 6151/997076",
    "sg:postcode":"64293",
    "sg:province":"Hessen",
    "wof:name":"Zur Zwiebel",
    "wof:placetype":"venue"
},
  "geometry": {"coordinates":[8.6452684402,49.8801078796],"type":"Point"}
}