{
  "type": "Feature",
  "properties": {
    "iso:country":"DE",
    "sg:address":"Marktplatz 5",
    "sg:city":"Lichtenfels",
    "sg:phone":"+49 9571/795134",
    "sg:postcode":"96215",
    "sg:province":"Bayern",
    "wof:name":"Stadtarchiv",
    "wof:placetype":"venue"
},
  "geometry": {"coordinates":[11.063528,50.145805],"type":"Point"}
}