{
  "type": "Feature",
  "properties": {
    "iso:country":"DE",
    "sg:address":"Gro\u00dfe Str. 46",
    "sg:city":"Dissen",
    "sg:postcode":"49201",
    "sg:province":"Niedersachsen",
    "wof:name":"Moden Borghaus Inh. Anna Borghaus E. Kfr.",
    "wof:placetype":"venue"
},
  "geometry": {"coordinates":[8.2003135681,52.1143226624],"type":"Point"}
}