{
  "type": "Feature",
  "properties": {
    "iso:country":"DE",
    "sg:address":"Jan-Oeltjen-Str. 15",
    "sg:city":"Oldenburg",
    "sg:phone":"+49 441/44522",
    "sg:postcode":"26133",
    "sg:province":"Niedersachsen",
    "wof:name":"Gisela Und Walter Meyer",
    "wof:placetype":"venue"
},
  "geometry": {"coordinates":[8.2198095322,53.1070289612],"type":"Point"}
}