{
  "type": "Feature",
  "properties": {
    "iso:country":"DE",
    "sg:address":"Waldstr. 18",
    "sg:city":"Walzbachtal",
    "sg:phone":"+49 7203/1889",
    "sg:postcode":"75045",
    "sg:province":"Baden-W\u00fcrttemberg",
    "wof:name":"Maria Stude Hebamme",
    "wof:placetype":"venue"
},
  "geometry": {"coordinates":[8.581872,49.029663],"type":"Point"}
}