{
  "type": "Feature",
  "properties": {
    "iso:country":"DE",
    "sg:address":"Danziger Str. 215",
    "sg:city":"Berlin",
    "sg:postcode":"10407",
    "sg:province":"Berlin",
    "wof:name":"Dr. Rolf Buber",
    "wof:placetype":"venue"
},
  "geometry": {"coordinates":[13.445059,52.529255],"type":"Point"}
}