{
  "type": "Feature",
  "properties": {
    "iso:country":"DE",
    "sg:address":"Im Blumengarten",
    "sg:city":"Bexbach",
    "sg:phone":"+49 6826/2032",
    "sg:postcode":"66450",
    "sg:province":"Saarland",
    "wof:name":"Restaurant Blumengarten",
    "wof:placetype":"venue"
},
  "geometry": {"coordinates":[7.2596287727,49.3410987854],"type":"Point"}
}