{
  "type": "Feature",
  "properties": {
    "iso:country":"DE",
    "sg:address":"Friesische Str. 92",
    "sg:city":"Flensburg",
    "sg:phone":"+49 461/57600",
    "sg:postcode":"24937",
    "sg:province":"Schleswig-Holstein",
    "wof:name":"G\u00fcnther Burow",
    "wof:placetype":"venue"
},
  "geometry": {"coordinates":[9.423028,54.780308],"type":"Point"}
}