{
  "type": "Feature",
  "properties": {
    "iso:country":"DE",
    "sg:address":"Wurzner Str. 31 b",
    "sg:city":"Taucha",
    "sg:phone":"+49 34298/68816",
    "sg:postcode":"04425",
    "sg:province":"Sachsen",
    "wof:name":"Hans-peter Grothe Ingenieur",
    "wof:placetype":"venue"
},
  "geometry": {"coordinates":[12.5106,51.377899],"type":"Point"}
}