{
  "type": "Feature",
  "properties": {
    "iso:country":"DE",
    "sg:address":"Darritzer Str. 132",
    "sg:city":"Kr\u00e4nzlin",
    "sg:postcode":"16818",
    "sg:province":"Brandenburg",
    "wof:name":"A. Ehmke",
    "wof:placetype":"venue"
},
  "geometry": {"coordinates":[12.705075264,52.9195289612],"type":"Point"}
}