{
  "type": "Feature",
  "properties": {
    "iso:country":"DE",
    "sg:address":"Moritzburger Str. 69",
    "sg:city":"Coswig",
    "sg:phone":"+49 3523/72795",
    "sg:postcode":"01640",
    "sg:province":"Sachsen",
    "wof:name":"Pepes Taverne",
    "wof:placetype":"venue"
},
  "geometry": {"coordinates":[13.5888786316,51.1382827759],"type":"Point"}
}