{
  "type": "Feature",
  "properties": {
    "iso:country":"DE",
    "sg:address":"Maiersbach 3",
    "sg:city":"Gersfeld",
    "sg:phone":"+49 6654/596",
    "sg:postcode":"36129",
    "sg:province":"Hessen",
    "wof:name":"Pension Erlengrund",
    "wof:placetype":"venue"
},
  "geometry": {"coordinates":[9.9042072296,50.4659538269],"type":"Point"}
}