{
  "type": "Feature",
  "properties": {
    "iso:country":"DE",
    "sg:address":"Kremper Str. 4",
    "sg:city":"Hamburg",
    "sg:phone":"+49 40/4206767",
    "sg:postcode":"20251",
    "sg:province":"Hamburg",
    "wof:name":"Lietfien Consulting Gmbh",
    "wof:placetype":"venue"
},
  "geometry": {"coordinates":[9.976104,53.583797],"type":"Point"}
}