{
  "type": "Feature",
  "properties": {
    "iso:country":"DE",
    "sg:address":"Sigraser Str. 10",
    "sg:city":"Edelsfeld",
    "sg:phone":"+49 9665/8178",
    "sg:postcode":"92265",
    "sg:province":"Bayern",
    "wof:name":"Sibo Seniorenwohnheime Immobilien Bau- Und Objekt-",
    "wof:placetype":"venue"
},
  "geometry": {"coordinates":[11.6951150894,49.5784034729],"type":"Point"}
}