{
  "type": "Feature",
  "properties": {
    "iso:country":"DE",
    "sg:address":"Hamburger Str. 18 a",
    "sg:city":"Wiefelstede",
    "sg:phone":"+49 4402/960213",
    "sg:postcode":"26215",
    "sg:province":"Niedersachsen",
    "wof:name":"Jens Reese",
    "wof:placetype":"venue"
},
  "geometry": {"coordinates":[8.1235494614,53.2582435608],"type":"Point"}
}