{
  "type": "Feature",
  "properties": {
    "iso:country":"DE",
    "sg:address":"Buchholzstr. 95",
    "sg:city":"Bergisch Gladbach",
    "sg:phone":"+49 2202/50206",
    "sg:postcode":"51469",
    "sg:province":"Nordrhein-Westfalen",
    "wof:name":"Igl Ingenieurges. Limburg Mbh",
    "wof:placetype":"venue"
},
  "geometry": {"coordinates":[7.111088,50.990723],"type":"Point"}
}