{
  "type": "Feature",
  "properties": {
    "iso:country":"DE",
    "sg:address":"Am Musenberg 2",
    "sg:city":"Georgsmarienh\u00fctte",
    "sg:phone":"+49 5401/5253",
    "sg:postcode":"49124",
    "sg:province":"Niedersachsen",
    "wof:name":"Victoria",
    "wof:placetype":"venue"
},
  "geometry": {"coordinates":[8.0825910568,52.1883926392],"type":"Point"}
}