{
  "type": "Feature",
  "properties": {
    "iso:country":"DE",
    "sg:address":"Frankfurter Str. 6",
    "sg:city":"Niedernhausen",
    "sg:phone":"+49 4979/1950580",
    "sg:postcode":"65527",
    "sg:province":"Hessen",
    "wof:name":"Stego - Elektrotechnik Gmbh",
    "wof:placetype":"venue"
},
  "geometry": {"coordinates":[9.701776,49.100491],"type":"Point"}
}