{
  "type": "Feature",
  "properties": {
    "iso:country":"DE",
    "sg:address":"J\u00e4gersberg 20",
    "sg:city":"Markt Taschendorf",
    "sg:phone":"+49 9552/921070",
    "sg:postcode":"91480",
    "sg:province":"Bayern",
    "wof:name":"Detewe-deutsche Telephonwerke Ag & Co.",
    "wof:placetype":"venue"
},
  "geometry": {"coordinates":[10.551399231,49.7047615051],"type":"Point"}
}