{
  "type": "Feature",
  "properties": {
    "iso:country":"DE",
    "sg:address":"Villinger Str. 13",
    "sg:city":"Bad D\u00fcrrheim",
    "sg:phone":"+49 7706/733",
    "sg:postcode":"78073",
    "sg:province":"Baden-W\u00fcrttemberg",
    "wof:name":"W. Schneider",
    "wof:placetype":"venue"
},
  "geometry": {"coordinates":[8.611044,47.971218],"type":"Point"}
}