{
  "type": "Feature",
  "properties": {
    "iso:country":"DE",
    "sg:address":"Steinauer Str. 35",
    "sg:city":"Steinau",
    "sg:phone":"+49 6667/455",
    "sg:postcode":"36396",
    "sg:province":"Hessen",
    "wof:name":"Josef Hohmann",
    "wof:placetype":"venue"
},
  "geometry": {"coordinates":[9.4230451584,50.3645820618],"type":"Point"}
}