{
  "type": "Feature",
  "properties": {
    "iso:country":"DE",
    "sg:address":"St.-Annen-Str. 26",
    "sg:city":"Brandenburg",
    "sg:phone":"+49 3381/224348",
    "sg:postcode":"14776",
    "sg:province":"Brandenburg",
    "wof:name":"Haus Des Handwerks",
    "wof:placetype":"venue"
},
  "geometry": {"coordinates":[12.5647888184,52.4077339172],"type":"Point"}
}