{
  "type": "Feature",
  "properties": {
    "iso:country":"DE",
    "sg:address":"August-Thyssen-Str 12",
    "sg:city":"Kaarst",
    "sg:phone":"+49 8066/1775",
    "sg:postcode":"41564",
    "sg:province":"Nordrhein-Westfalen",
    "wof:name":"Forster",
    "wof:placetype":"venue"
},
  "geometry": {"coordinates":[12.007698,47.773548],"type":"Point"}
}