{
  "type": "Feature",
  "properties": {
    "iso:country":"DE",
    "sg:address":"Torstr. 9 a",
    "sg:city":"Wolfhagen",
    "sg:phone":"+49 5692/4120",
    "sg:postcode":"34466",
    "sg:province":"Hessen",
    "wof:name":"R. Abel Versicherung",
    "wof:placetype":"venue"
},
  "geometry": {"coordinates":[9.1724843979,51.3263244629],"type":"Point"}
}