{
  "type": "Feature",
  "properties": {
    "iso:country":"DE",
    "sg:address":"Gerichtsstr. 2",
    "sg:city":"Wolfhagen",
    "sg:phone":"+49 5692/7827",
    "sg:postcode":"34466",
    "sg:province":"Hessen",
    "wof:name":"Cafe Am Kornmarkt",
    "wof:placetype":"venue"
},
  "geometry": {"coordinates":[9.170578,51.325569],"type":"Point"}
}