{
  "type": "Feature",
  "properties": {
    "iso:country":"DE",
    "sg:address":"Riedstr. 16",
    "sg:city":"Rodenbach",
    "sg:phone":"+49 6184/50767",
    "sg:postcode":"63517",
    "sg:province":"Hessen",
    "wof:name":"Wilfried Mook Architekt",
    "wof:placetype":"venue"
},
  "geometry": {"coordinates":[9.019395,50.14666],"type":"Point"}
}