{
  "type": "Feature",
  "properties": {
    "iso:country":"DE",
    "sg:address":"Lange Striepen 48",
    "sg:city":"Hamburg",
    "sg:phone":"+49 40/7967240",
    "sg:postcode":"21147",
    "sg:province":"Hamburg",
    "wof:name":"M. Greve",
    "wof:placetype":"venue"
},
  "geometry": {"coordinates":[9.886856,53.476978],"type":"Point"}
}