{
  "type": "Feature",
  "properties": {
    "iso:country":"DE",
    "sg:address":"Vorstadtstr. 22",
    "sg:city":"Saarbr\u00fccken",
    "sg:phone":"+49 681/53886",
    "sg:postcode":"66117",
    "sg:province":"Saarland",
    "wof:name":"Schlo\u00dfbrunnen",
    "wof:placetype":"venue"
},
  "geometry": {"coordinates":[6.9859728813,49.2319946289],"type":"Point"}
}