{
  "type": "Feature",
  "properties": {
    "iso:country":"DE",
    "sg:address":"Uhlstr. 80",
    "sg:city":"Br\u00fchl",
    "sg:phone":"+49 2232/42270",
    "sg:postcode":"50321",
    "sg:province":"Nordrhein-Westfalen",
    "wof:name":"Parcelsus-apotheke",
    "wof:placetype":"venue"
},
  "geometry": {"coordinates":[6.902079,50.826492],"type":"Point"}
}