{
  "type": "Feature",
  "properties": {
    "iso:country":"DE",
    "sg:address":"S\u00fcdstr. 9",
    "sg:city":"Aachen",
    "sg:phone":"+49 4924/144776",
    "sg:postcode":"52064",
    "sg:province":"Nordrhein-Westfalen",
    "wof:name":"Tina T\u00d6ller",
    "wof:placetype":"venue"
},
  "geometry": {"coordinates":[6.0815358162,50.7682762146],"type":"Point"}
}