{
  "type": "Feature",
  "properties": {
    "iso:country":"DE",
    "sg:address":"Kohlberger Str. 16",
    "sg:city":"Windeck",
    "sg:phone":"+49 2292/5380",
    "sg:postcode":"51570",
    "sg:province":"Nordrhein-Westfalen",
    "wof:name":"Restaurant Op D R Birke",
    "wof:placetype":"venue"
},
  "geometry": {"coordinates":[7.6286668777,50.8152008057],"type":"Point"}
}