{
  "type": "Feature",
  "properties": {
    "iso:country":"DE",
    "sg:address":"B\u00fchrener Str. 25",
    "sg:city":"Niemetal",
    "sg:phone":"+49 5502/999461",
    "sg:postcode":"37127",
    "sg:province":"Niedersachsen",
    "wof:name":"R.g.-euro Consult Gmbh",
    "wof:placetype":"venue"
},
  "geometry": {"coordinates":[9.7048797607,51.5005683899],"type":"Point"}
}