{
  "type": "Feature",
  "properties": {
    "iso:country":"DE",
    "sg:address":"M\u00fcnchener Str. 67",
    "sg:city":"Freilassing",
    "sg:phone":"+49 8654/62121",
    "sg:postcode":"83395",
    "sg:province":"Bayern",
    "wof:name":"Camaro Handels Gmbh",
    "wof:placetype":"venue"
},
  "geometry": {"coordinates":[12.969469,47.843178],"type":"Point"}
}