{
  "type": "Feature",
  "properties": {
    "iso:country":"DE",
    "sg:address":"Baumschulenstr. 11",
    "sg:city":"Linsengericht",
    "sg:phone":"+49 6051/71486",
    "sg:postcode":"63589",
    "sg:province":"Hessen",
    "wof:name":"Konrad Kimmig",
    "wof:placetype":"venue"
},
  "geometry": {"coordinates":[9.1883,50.192474],"type":"Point"}
}