{
  "type": "Feature",
  "properties": {
    "iso:country":"DE",
    "sg:address":"Am Barkhof",
    "sg:city":"Osterholz-Scharmbeck",
    "sg:phone":"+49 4791/94030",
    "sg:postcode":"27711",
    "sg:province":"Niedersachsen",
    "wof:name":"Allwetterbad",
    "wof:placetype":"venue"
},
  "geometry": {"coordinates":[8.7878923416,53.2253570557],"type":"Point"}
}