{
  "type": "Feature",
  "properties": {
    "iso:country":"DE",
    "sg:address":"Wei\u00dfachdamm 8",
    "sg:city":"Rottach-Egern",
    "sg:phone":"+49 8022/82509",
    "sg:postcode":"83700",
    "sg:province":"Bayern",
    "wof:name":"Gusimex Handels- Gmbh",
    "wof:placetype":"venue"
},
  "geometry": {"coordinates":[11.743397,47.694553],"type":"Point"}
}