{
  "type": "Feature",
  "properties": {
    "iso:country":"DE",
    "sg:address":"Bergh\u00e4user 4",
    "sg:city":"Stolpen",
    "sg:phone":"+49 35973/24184",
    "sg:postcode":"01833",
    "sg:province":"Sachsen",
    "wof:name":"J. Venus",
    "wof:placetype":"venue"
},
  "geometry": {"coordinates":[14.0723819733,51.0473365784],"type":"Point"}
}