{
  "type": "Feature",
  "properties": {
    "iso:country":"DE",
    "sg:address":"Von-Eichendorff-Str. 18",
    "sg:city":"Bad Grund",
    "sg:phone":"+49 5327/2072",
    "sg:postcode":"37539",
    "sg:province":"Niedersachsen",
    "wof:name":"Hotel Pension Berlin",
    "wof:placetype":"venue"
},
  "geometry": {"coordinates":[10.2459897995,51.8096313477],"type":"Point"}
}