{
  "type": "Feature",
  "properties": {
    "iso:country":"DE",
    "sg:address":"Industriestr. 9",
    "sg:city":"Sontheim",
    "sg:phone":"+49 7325",
    "sg:postcode":"89567",
    "sg:province":"Baden-W\u00fcrttemberg",
    "wof:name":"Erich Joas, Auto-center-service",
    "wof:placetype":"venue"
},
  "geometry": {"coordinates":[10.2990150452,48.5461196899],"type":"Point"}
}