{
  "type": "Feature",
  "properties": {
    "iso:country":"DE",
    "sg:address":"Kirchgasse 2",
    "sg:city":"Arnstadt",
    "sg:phone":"+49 3628/78202",
    "sg:postcode":"99310",
    "sg:province":"Th\u00fcringen",
    "wof:name":"Fotostudio Sallatsch",
    "wof:placetype":"venue"
},
  "geometry": {"coordinates":[10.9461622238,50.8332672119],"type":"Point"}
}