{
  "type": "Feature",
  "properties": {
    "iso:country":"DE",
    "sg:city":"M\u00fcnchen",
    "sg:postcode":"80807",
    "sg:province":"Bayern",
    "wof:name":"Backstage Creative Lightdesign Gmbh",
    "wof:placetype":"venue"
},
  "geometry": {"coordinates":[11.57305,48.182259],"type":"Point"}
}