{
  "type": "Feature",
  "properties": {
    "iso:country":"DE",
    "sg:address":"Untergriesheimer Weg 9",
    "sg:city":"Bad Friedrichshall",
    "sg:phone":"+49 7136/5368",
    "sg:postcode":"74177",
    "sg:province":"Baden-W\u00fcrttemberg",
    "wof:name":"Restaurant Panorama",
    "wof:placetype":"venue"
},
  "geometry": {"coordinates":[9.2267904282,49.2460289001],"type":"Point"}
}