{
  "type": "Feature",
  "properties": {
    "iso:country":"DE",
    "sg:address":"Landshuter Str. 7",
    "sg:city":"Erding",
    "sg:phone":"+49 8122/8017",
    "sg:postcode":"85435",
    "sg:province":"Bayern",
    "wof:name":"Fr\u00f6schls Modellbau & Technik",
    "wof:placetype":"venue"
},
  "geometry": {"coordinates":[11.90916,48.30624],"type":"Point"}
}