{
  "type": "Feature",
  "properties": {
    "iso:country":"DE",
    "sg:address":"Hermannstr. 70",
    "sg:city":"M\u00fclheim",
    "sg:phone":"+49 208/420818",
    "sg:postcode":"45479",
    "sg:province":"Nordrhein-Westfalen",
    "wof:name":"Dieter Hocks",
    "wof:placetype":"venue"
},
  "geometry": {"coordinates":[6.8543510437,51.4227142334],"type":"Point"}
}