{
  "type": "Feature",
  "properties": {
    "iso:country":"DE",
    "sg:address":"Gravenbruchweg 56",
    "sg:city":"Offenbach",
    "sg:postcode":"63069",
    "sg:province":"Hessen",
    "wof:name":"Gun Power Gmbh",
    "wof:placetype":"venue"
},
  "geometry": {"coordinates":[8.76085186,50.0809326172],"type":"Point"}
}