{
  "type": "Feature",
  "properties": {
    "iso:country":"DE",
    "sg:address":"Br\u00fccktor 1",
    "sg:city":"Kleve",
    "sg:phone":"+49 2821/23432",
    "sg:postcode":"47533",
    "sg:province":"Nordrhein-Westfalen",
    "wof:name":"Verweyen",
    "wof:placetype":"venue"
},
  "geometry": {"coordinates":[6.1431589127,51.7880821228],"type":"Point"}
}