{
  "type": "Feature",
  "properties": {
    "iso:country":"DE",
    "sg:address":"Galgenberg 4",
    "sg:city":"Schonungen",
    "sg:phone":"+49 9721/75720",
    "sg:postcode":"97453",
    "sg:province":"Bayern",
    "wof:name":"Ostendorp Gbr",
    "wof:placetype":"venue"
},
  "geometry": {"coordinates":[10.311548233,50.0516853333],"type":"Point"}
}