{
  "type": "Feature",
  "properties": {
    "iso:country":"DE",
    "sg:address":"Ludwig-Roselius-Allee 106",
    "sg:city":"Bremen",
    "sg:phone":"+49 421/477863",
    "sg:postcode":"28329",
    "sg:province":"Bremen",
    "wof:name":"Horst Behrens",
    "wof:placetype":"venue"
},
  "geometry": {"coordinates":[8.89151,53.071609],"type":"Point"}
}