{
  "type": "Feature",
  "properties": {
    "iso:country":"DE",
    "sg:address":"Am Rosenanger 81",
    "sg:city":"Berlin",
    "sg:phone":"+49 30/4014080",
    "sg:postcode":"13465",
    "sg:province":"Berlin",
    "wof:name":"Alterna Kontor F\u00fcr Antike \u00d6fen Gmbh",
    "wof:placetype":"venue"
},
  "geometry": {"coordinates":[13.308306694,52.6297912598],"type":"Point"}
}