{
  "type": "Feature",
  "properties": {
    "iso:country":"DE",
    "sg:address":"Ahornstr.26",
    "sg:city":"Bodnegg",
    "sg:phone":"+49 7520",
    "sg:postcode":"88285",
    "sg:province":"Baden-W\u00fcrttemberg",
    "wof:name":"Krauss Gmbh Winterg\u00e4rten,verglasung",
    "wof:placetype":"venue"
},
  "geometry": {"coordinates":[9.69871521,47.7286338806],"type":"Point"}
}