{
  "type": "Feature",
  "properties": {
    "iso:country":"DE",
    "sg:address":"Deutsch-Ritter-Allee 23",
    "sg:city":"Grevenbroich",
    "sg:phone":"+49 2181/43686",
    "sg:postcode":"41515",
    "sg:province":"Nordrhein-Westfalen",
    "wof:name":"H. P. Linges",
    "wof:placetype":"venue"
},
  "geometry": {"coordinates":[6.569166,51.087502],"type":"Point"}
}