{
  "type": "Feature",
  "properties": {
    "iso:country":"DE",
    "sg:address":"Breslauer Str. 10",
    "sg:city":"Werne",
    "sg:phone":"+49 2389/533470",
    "sg:postcode":"59368",
    "sg:province":"Nordrhein-Westfalen",
    "wof:name":"Thoenes, Schweisstechnik",
    "wof:placetype":"venue"
},
  "geometry": {"coordinates":[7.6547021866,51.6641426086],"type":"Point"}
}