{
  "type": "Feature",
  "properties": {
    "iso:country":"DE",
    "sg:address":"Gewerbestr. 14",
    "sg:city":"Rheinfelden",
    "sg:postcode":"79618",
    "sg:province":"Baden-W\u00fcrttemberg",
    "wof:name":"S & W Verm\u00f6gens- Und Be- Teiligungs Gmbh & Co.",
    "wof:placetype":"venue"
},
  "geometry": {"coordinates":[7.7343420982,47.5478286743],"type":"Point"}
}