{
  "type": "Feature",
  "properties": {
    "iso:country":"DE",
    "sg:address":"Dorfstr. 42",
    "sg:city":"Gladigau",
    "sg:phone":"+49 39392/81348",
    "sg:postcode":"39606",
    "sg:province":"Sachsen-Anhalt",
    "wof:name":"Alwin K\u00fchne",
    "wof:placetype":"venue"
},
  "geometry": {"coordinates":[11.575067,52.77322],"type":"Point"}
}