{
  "type": "Feature",
  "properties": {
    "iso:country":"DE",
    "sg:address":"Neue Zeile 6",
    "sg:city":"Kaufbeuren",
    "sg:phone":"+49 8341/62610",
    "sg:postcode":"87600",
    "sg:province":"Bayern",
    "wof:name":"Pps Schwanda-dienstleistungs- Und Beratungs Gmbh",
    "wof:placetype":"venue"
},
  "geometry": {"coordinates":[10.620256,47.880817],"type":"Point"}
}