{
  "type": "Feature",
  "properties": {
    "iso:country":"DE",
    "sg:address":"Br\u00fcsseler Str. 44",
    "sg:city":"K\u00f6ln",
    "sg:phone":"+49 221/251815",
    "sg:postcode":"50674",
    "sg:province":"Nordrhein-Westfalen",
    "wof:name":"K\u00f6lsche Chinese",
    "wof:placetype":"venue"
},
  "geometry": {"coordinates":[6.9347867966,50.9363441467],"type":"Point"}
}