{
  "type": "Feature",
  "properties": {
    "iso:country":"DE",
    "sg:address":"Geibelstr. 15",
    "sg:city":"Neuss",
    "sg:phone":"+49 2137/2509",
    "sg:postcode":"41469",
    "sg:province":"Nordrhein-Westfalen",
    "wof:name":"Marie-luise Overlack-gotzes Masseurin",
    "wof:placetype":"venue"
},
  "geometry": {"coordinates":[6.731693,51.155079],"type":"Point"}
}