{
  "type": "Feature",
  "properties": {
    "iso:country":"DE",
    "sg:address":"Fleischhauerstr. 90",
    "sg:city":"L\u00fcbeck",
    "sg:phone":"+49 451/706774",
    "sg:postcode":"23552",
    "sg:province":"Schleswig-Holstein",
    "wof:name":"Sherry Und Port",
    "wof:placetype":"venue"
},
  "geometry": {"coordinates":[10.6920404434,53.8660011292],"type":"Point"}
}