{
  "type": "Feature",
  "properties": {
    "iso:country":"DE",
    "sg:address":"Industriestr. 10",
    "sg:city":"Winnenden",
    "sg:phone":"+49 7195/72930",
    "sg:postcode":"71364",
    "sg:province":"Baden-W\u00fcrttemberg",
    "wof:name":"Baumgart Gmbh",
    "wof:placetype":"venue"
},
  "geometry": {"coordinates":[9.4357843399,48.8598403931],"type":"Point"}
}