{
  "type": "Feature",
  "properties": {
    "iso:country":"DE",
    "sg:address":"Bachstr. 18",
    "sg:city":"Stutensee",
    "sg:phone":"+49 7244/96358",
    "sg:postcode":"76297",
    "sg:province":"Baden-W\u00fcrttemberg",
    "wof:name":"Mathias Scherer",
    "wof:placetype":"venue"
},
  "geometry": {"coordinates":[8.471904,49.058891],"type":"Point"}
}