{
  "type": "Feature",
  "properties": {
    "iso:country":"DE",
    "sg:address":"August-Hirsch-Str. 10",
    "sg:city":"Duisburg",
    "sg:phone":"+49 203/809920",
    "sg:postcode":"47119",
    "sg:province":"Nordrhein-Westfalen",
    "wof:name":"Teleport Duisburg Gmbh",
    "wof:placetype":"venue"
},
  "geometry": {"coordinates":[6.7396669388,51.4482917786],"type":"Point"}
}