{
  "type": "Feature",
  "properties": {
    "iso:country":"DE",
    "sg:address":"Ernst-Schneider-Str. 5",
    "sg:city":"Heppenheim",
    "sg:phone":"+49 6252/5392",
    "sg:postcode":"64646",
    "sg:province":"Hessen",
    "wof:name":"Koch & Bauer",
    "wof:placetype":"venue"
},
  "geometry": {"coordinates":[8.6370954514,49.6418991089],"type":"Point"}
}