{
  "type": "Feature",
  "properties": {
    "iso:country":"DE",
    "sg:address":"Hangstr. 8",
    "sg:city":"Gauting",
    "sg:phone":"+49 89/8504351",
    "sg:postcode":"82131",
    "sg:province":"Bayern",
    "wof:name":"Wolfgang K\u00f6th",
    "wof:placetype":"venue"
},
  "geometry": {"coordinates":[11.3795413971,48.0690116882],"type":"Point"}
}