{
  "type": "Feature",
  "properties": {
    "iso:country":"DE",
    "sg:address":"Gro\u00dfer Kamp 6-8",
    "sg:city":"Lage",
    "sg:phone":"+49 5232/65982",
    "sg:postcode":"32791",
    "sg:province":"Nordrhein-Westfalen",
    "wof:name":"Karl Heinrich Sch\u00e4fer Gmbh",
    "wof:placetype":"venue"
},
  "geometry": {"coordinates":[8.846646,51.985703],"type":"Point"}
}