{
  "type": "Feature",
  "properties": {
    "iso:country":"DE",
    "sg:address":"Arnsdorfer Str. 55",
    "sg:city":"Jessen",
    "sg:phone":"+49 3537/26050",
    "sg:postcode":"06917",
    "sg:province":"Sachsen-Anhalt",
    "wof:name":"Baustoffgro\u00dfhandel Gmbh",
    "wof:placetype":"venue"
},
  "geometry": {"coordinates":[12.8246116638,51.7881736755],"type":"Point"}
}