{
  "type": "Feature",
  "properties": {
    "iso:country":"DE",
    "sg:address":"Rosenweg 7",
    "sg:city":"Bergen",
    "sg:phone":"+49 37463/89886",
    "sg:postcode":"08239",
    "sg:province":"Sachsen",
    "wof:name":"Gerbeth & R\u00f6her",
    "wof:placetype":"venue"
},
  "geometry": {"coordinates":[12.27143,50.472542],"type":"Point"}
}