{
  "type": "Feature",
  "properties": {
    "iso:country":"DE",
    "sg:address":"Kaulberg",
    "sg:city":"Schl\u00fcsselfeld",
    "sg:postcode":"96132",
    "sg:province":"Bayern",
    "wof:name":"Von P\u00f6llnitzsche Gutsverwaltung",
    "wof:placetype":"venue"
},
  "geometry": {"coordinates":[10.5634784698,49.7742004395],"type":"Point"}
}