{
  "type": "Feature",
  "properties": {
    "iso:country":"DE",
    "sg:address":"Dietrich-Bonhoeffer-Str.",
    "sg:city":"Glauchau",
    "sg:postcode":"08371",
    "sg:province":"Sachsen",
    "wof:name":"Gardinen-studio A. B\u00f6hmer",
    "wof:placetype":"venue"
},
  "geometry": {"coordinates":[12.5480833054,50.8224105835],"type":"Point"}
}