{
  "type": "Feature",
  "properties": {
    "iso:country":"DE",
    "sg:address":"Sch\u00f6neck 7",
    "sg:city":"Langdorf",
    "sg:phone":"+49 9921/2981",
    "sg:postcode":"94264",
    "sg:province":"Bayern",
    "wof:name":"R. Kagerbauer",
    "wof:placetype":"venue"
},
  "geometry": {"coordinates":[13.12336,49.010399],"type":"Point"}
}