{
  "type": "Feature",
  "properties": {
    "iso:country":"DE",
    "sg:address":"Itzenplitzstr. 34",
    "sg:city":"Schiffweiler",
    "sg:phone":"+49 6821/6147",
    "sg:postcode":"66578",
    "sg:province":"Saarland",
    "wof:name":"Ev. Pfarramt Heiligenwald",
    "wof:placetype":"venue"
},
  "geometry": {"coordinates":[7.0921020508,49.3549766541],"type":"Point"}
}