{
  "type": "Feature",
  "properties": {
    "iso:country":"DE",
    "sg:address":"Grabenstr. 3",
    "sg:city":"Plettenberg",
    "sg:phone":"+49 2391/54351",
    "sg:postcode":"58840",
    "sg:province":"Nordrhein-Westfalen",
    "wof:name":"Gerd Stremel",
    "wof:placetype":"venue"
},
  "geometry": {"coordinates":[7.868573,51.235123],"type":"Point"}
}