{
  "type": "Feature",
  "properties": {
    "iso:country":"DE",
    "sg:address":"Langer Markt 15",
    "sg:city":"Hermeskeil",
    "sg:phone":"+49 6503/1084",
    "sg:postcode":"54411",
    "sg:province":"Rheinland-Pfalz",
    "wof:name":"Stadtb\u00fccherei Hermeskeil",
    "wof:placetype":"venue"
},
  "geometry": {"coordinates":[6.946148,49.655266],"type":"Point"}
}