{
  "type": "Feature",
  "properties": {
    "iso:country":"DE",
    "sg:address":"D\u00f6beritzer Weg 3",
    "sg:city":"Dallgow",
    "sg:phone":"+49 3322/282100",
    "sg:postcode":"14624",
    "sg:province":"Brandenburg",
    "wof:name":"Kaufmarkt",
    "wof:placetype":"venue"
},
  "geometry": {"coordinates":[13.1153879166,52.5202789307],"type":"Point"}
}