{
  "type": "Feature",
  "properties": {
    "iso:country":"DE",
    "sg:address":"Turbinenstr. 8",
    "sg:city":"Stuttgart",
    "sg:phone":"+49 711/831597",
    "sg:postcode":"70499",
    "sg:province":"Baden-W\u00fcrttemberg",
    "wof:name":"Fliesen-dautel Karl-heinz Dautel",
    "wof:placetype":"venue"
},
  "geometry": {"coordinates":[9.1064147949,48.8232383728],"type":"Point"}
}