{
  "type": "Feature",
  "properties": {
    "iso:country":"DE",
    "sg:address":"Wilhelmstr. 10",
    "sg:city":"D\u00fcren",
    "sg:phone":"+49 2421/10673",
    "sg:postcode":"52349",
    "sg:province":"Nordrhein-Westfalen",
    "wof:name":"Hinkel Haushalt Gmbh",
    "wof:placetype":"venue"
},
  "geometry": {"coordinates":[6.4821591377,50.8023338318],"type":"Point"}
}