{
  "type": "Feature",
  "properties": {
    "iso:country":"DE",
    "sg:address":"Auf dem Gellenkamp 5",
    "sg:city":"Hagen",
    "sg:phone":"+49 2331/41162",
    "sg:postcode":"58135",
    "sg:province":"Nordrhein-Westfalen",
    "wof:name":"J\u00fcrgen Schicht",
    "wof:placetype":"venue"
},
  "geometry": {"coordinates":[7.427025,51.33783],"type":"Point"}
}