{
  "type": "Feature",
  "properties": {
    "iso:country":"DE",
    "sg:address":"Eisenacher Str. 89",
    "sg:city":"Berlin",
    "sg:phone":"+49 30/2132949",
    "sg:postcode":"10781",
    "sg:province":"Berlin",
    "wof:name":"Karsten Antelmann Architekt",
    "wof:placetype":"venue"
},
  "geometry": {"coordinates":[13.349411,52.490818],"type":"Point"}
}