{
  "type": "Feature",
  "properties": {
    "iso:country":"DE",
    "sg:address":"Luitpoldstr. 6",
    "sg:city":"Lauf",
    "sg:phone":"+49 9123/83211",
    "sg:postcode":"91207",
    "sg:province":"Bayern",
    "wof:name":"Silvia Wallner",
    "wof:placetype":"venue"
},
  "geometry": {"coordinates":[11.281465,49.507725],"type":"Point"}
}