{
  "type": "Feature",
  "properties": {
    "iso:country":"DE",
    "sg:address":"Germaniastr. 37",
    "sg:city":"M\u00fcnchen",
    "sg:postcode":"80805",
    "sg:province":"Bayern",
    "wof:name":"V20 - Visions To Order Gmbh",
    "wof:placetype":"venue"
},
  "geometry": {"coordinates":[11.5879793167,48.1689567566],"type":"Point"}
}