{
  "type": "Feature",
  "properties": {
    "iso:country":"DE",
    "sg:address":"Willy-Brandt-Str. 30",
    "sg:city":"Stuttgart",
    "sg:phone":"+49 711/20202432",
    "sg:postcode":"70173",
    "sg:province":"Baden-W\u00fcrttemberg",
    "wof:name":"Neckarstube",
    "wof:placetype":"venue"
},
  "geometry": {"coordinates":[9.188750267,48.7835693359],"type":"Point"}
}