{
  "type": "Feature",
  "properties": {
    "iso:country":"DE",
    "sg:address":"Lilienweg 25",
    "sg:city":"Halberstadt",
    "sg:phone":"+49 3941/441906",
    "sg:postcode":"38820",
    "sg:province":"Sachsen-Anhalt",
    "wof:name":"Kleintiercenter Soltau",
    "wof:placetype":"venue"
},
  "geometry": {"coordinates":[11.024564,51.913738],"type":"Point"}
}