{
  "type": "Feature",
  "properties": {
    "iso:country":"DE",
    "sg:address":"Wahmstr. 32",
    "sg:city":"L\u00fcbeck",
    "sg:phone":"+49 451/77730",
    "sg:postcode":"23552",
    "sg:province":"Schleswig-Holstein",
    "wof:name":"World Of Sex Handels Gmbh",
    "wof:placetype":"venue"
},
  "geometry": {"coordinates":[10.68749,53.865147],"type":"Point"}
}