{
  "type": "Feature",
  "properties": {
    "iso:country":"DE",
    "sg:address":"Winzenheimer Stra\u00dfe 12",
    "sg:city":"Bretzenheim",
    "sg:phone":"+49 671/8459461",
    "sg:postcode":"55559",
    "sg:province":"Rheinland-Pfalz",
    "wof:name":"Bassboxen Und Bassanlagen F\u00fcr Profis",
    "wof:placetype":"venue"
},
  "geometry": {"coordinates":[7.893955,49.876209],"type":"Point"}
}