{
  "type": "Feature",
  "properties": {
    "iso:country":"DE",
    "sg:address":"Huyssenallee 40",
    "sg:city":"Essen",
    "sg:phone":"+49 201/234556",
    "sg:postcode":"45128",
    "sg:province":"Nordrhein-Westfalen",
    "wof:name":"Sven Simon Fotoagentur Gmbh & Co. Pressefoto Kg",
    "wof:placetype":"venue"
},
  "geometry": {"coordinates":[7.0099029541,51.4474449158],"type":"Point"}
}