{
  "type": "Feature",
  "properties": {
    "iso:country":"DE",
    "sg:address":"Theodor-Storm-Str. 19",
    "sg:city":"Halle",
    "sg:phone":"+49 345/6874548",
    "sg:postcode":"06126",
    "sg:province":"Sachsen-Anhalt",
    "wof:name":"G\u00f6tze Speditions Gmbh",
    "wof:placetype":"venue"
},
  "geometry": {"coordinates":[11.9079761505,51.4763755798],"type":"Point"}
}