{
  "type": "Feature",
  "properties": {
    "iso:country":"DE",
    "sg:address":"Parkstr. 55",
    "sg:city":"Horn-Bad Meinberg",
    "sg:postcode":"32805",
    "sg:province":"Nordrhein-Westfalen",
    "wof:name":"Bad-apotheke Inh. Dr. Joachim Triebe E. K.",
    "wof:placetype":"venue"
},
  "geometry": {"coordinates":[8.98187,51.89447],"type":"Point"}
}