{
  "type": "Feature",
  "properties": {
    "iso:country":"DE",
    "sg:address":"Am Griesfeld 33",
    "sg:city":"Alling",
    "sg:phone":"+49 8141/4041790",
    "sg:postcode":"82239",
    "sg:province":"Bayern",
    "wof:name":"Meltem W\u00e4rmer\u00fcckgewinnung Gmbh & Co Kg",
    "wof:placetype":"venue"
},
  "geometry": {"coordinates":[11.306145668,48.1414871216],"type":"Point"}
}