{
  "type": "Feature",
  "properties": {
    "iso:country":"DE",
    "sg:address":"Traubenstr. 19",
    "sg:city":"Zirndorf",
    "sg:phone":"+49 9127/57424",
    "sg:postcode":"90513",
    "sg:province":"Bayern",
    "wof:name":"Party Service Ascherl",
    "wof:placetype":"venue"
},
  "geometry": {"coordinates":[10.898757,49.425133],"type":"Point"}
}