{
  "type": "Feature",
  "properties": {
    "iso:country":"DE",
    "sg:address":"Urbanstr. 115",
    "sg:city":"Berlin",
    "sg:phone":"+49 30/7748215",
    "sg:postcode":"10967",
    "sg:province":"Berlin",
    "wof:name":"Pfister & Partner Gmbh",
    "wof:placetype":"venue"
},
  "geometry": {"coordinates":[13.4184131622,52.4905662537],"type":"Point"}
}