{
  "type": "Feature",
  "properties": {
    "iso:country":"DE",
    "sg:address":"Neuheidlesweg 5",
    "sg:city":"Pfaffenhofen",
    "sg:phone":"+49 7302/6557",
    "sg:postcode":"89284",
    "sg:province":"Bayern",
    "wof:name":"J. Zeller Jun.",
    "wof:placetype":"venue"
},
  "geometry": {"coordinates":[10.153039,48.377045],"type":"Point"}
}