{
  "type": "Feature",
  "properties": {
    "iso:country":"DE",
    "sg:address":"Torfeldweg 3",
    "sg:city":"Neuenb\u00fcrg",
    "sg:phone":"+49 7082/3592",
    "sg:postcode":"75305",
    "sg:province":"Baden-W\u00fcrttemberg",
    "wof:name":"Erich K\u00f6nig",
    "wof:placetype":"venue"
},
  "geometry": {"coordinates":[8.568726,48.86034],"type":"Point"}
}