{
  "type": "Feature",
  "properties": {
    "iso:country":"DE",
    "sg:address":"Rosinenstr. 32",
    "sg:city":"Dissen",
    "sg:postcode":"49201",
    "sg:province":"Niedersachsen",
    "wof:name":"Francisco Pinero Maine Be.- Und Entladen Von Fleisch",
    "wof:placetype":"venue"
},
  "geometry": {"coordinates":[8.20343,52.110718],"type":"Point"}
}