{
  "type": "Feature",
  "properties": {
    "iso:country":"DE",
    "sg:address":"Eisenbahnstr. 6",
    "sg:city":"Saarbr\u00fccken",
    "sg:phone":"+49 681/581108",
    "sg:postcode":"66117",
    "sg:province":"Saarland",
    "wof:name":"Korea Restaurant Seoul",
    "wof:placetype":"venue"
},
  "geometry": {"coordinates":[6.9881691933,49.2319831848],"type":"Point"}
}