{
  "type": "Feature",
  "properties": {
    "iso:country":"DE",
    "sg:address":"Wachauer Str. 33",
    "sg:city":"Markkleeberg",
    "sg:postcode":"04416",
    "sg:province":"Sachsen",
    "wof:name":"Max Byczkowski",
    "wof:placetype":"venue"
},
  "geometry": {"coordinates":[12.4059429169,51.2727241516],"type":"Point"}
}