{
  "type": "Feature",
  "properties": {
    "iso:country":"DE",
    "sg:address":"Einham 2",
    "sg:city":"Traunstein",
    "sg:postcode":"83278",
    "sg:province":"Bayern",
    "wof:name":"Checkers --- Check It Out @ Http://www.checkers.ch",
    "wof:placetype":"venue"
},
  "geometry": {"coordinates":[12.609239,47.862167],"type":"Point"}
}