{
  "type": "Feature",
  "properties": {
    "iso:country":"DE",
    "sg:address":"Neubertstr. 11",
    "sg:city":"Hamburg",
    "sg:phone":"+49 40/858587",
    "sg:postcode":"22087",
    "sg:province":"Hamburg",
    "wof:name":"Echo-flug Frank Reidelhuber",
    "wof:placetype":"venue"
},
  "geometry": {"coordinates":[10.029734,53.561916],"type":"Point"}
}