{
  "type": "Feature",
  "properties": {
    "iso:country":"DE",
    "sg:address":"Issigauer Str. 28",
    "sg:city":"Blankenberg",
    "sg:postcode":"07366",
    "sg:province":"Th\u00fcringen",
    "wof:name":"Dr. Med. Manfred S\u00fc\u00df",
    "wof:placetype":"venue"
},
  "geometry": {"coordinates":[11.720582,50.402252],"type":"Point"}
}