{
  "type": "Feature",
  "properties": {
    "iso:country":"DE",
    "sg:address":"Bebelplatz 2",
    "sg:city":"Freiberg",
    "sg:phone":"+49 3731/48990",
    "sg:postcode":"09599",
    "sg:province":"Sachsen",
    "wof:name":"Kaufland",
    "wof:placetype":"venue"
},
  "geometry": {"coordinates":[13.3398323059,50.914352417],"type":"Point"}
}