{
  "type": "Feature",
  "properties": {
    "iso:country":"DE",
    "sg:address":"Beerentalweg 84",
    "sg:city":"Hamburg",
    "sg:phone":"+49 40/79143067",
    "sg:postcode":"21077",
    "sg:province":"Hamburg",
    "wof:name":"Dagmar Reimann Rechtsanw\u00e4ltin",
    "wof:placetype":"venue"
},
  "geometry": {"coordinates":[9.9493408203,53.4489517212],"type":"Point"}
}