{
  "type": "Feature",
  "properties": {
    "iso:country":"DE",
    "sg:address":"Marienstr. 116",
    "sg:city":"Hannover",
    "sg:phone":"+49 511/858041",
    "sg:postcode":"30171",
    "sg:province":"Niedersachsen",
    "wof:name":"Bistro Centralpark",
    "wof:placetype":"venue"
},
  "geometry": {"coordinates":[9.7607803345,52.3702735901],"type":"Point"}
}