{
  "type": "Feature",
  "properties": {
    "iso:country":"DE",
    "sg:address":"Siegener Str 69",
    "sg:city":"Kreuztal",
    "sg:phone":"+49 7621/79000",
    "sg:postcode":"57223",
    "sg:province":"Nordrhein-Westfalen",
    "wof:name":"Rhenus-kleyling Gmbh & Co",
    "wof:placetype":"venue"
},
  "geometry": {"coordinates":[7.594709,47.59679],"type":"Point"}
}