{
  "type": "Feature",
  "properties": {
    "iso:country":"DE",
    "sg:address":"Dorfstr. 12",
    "sg:city":"Witzeeze",
    "sg:phone":"+49 4155/4848",
    "sg:postcode":"21514",
    "sg:province":"Schleswig-Holstein",
    "wof:name":"Haus Dorothea",
    "wof:placetype":"venue"
},
  "geometry": {"coordinates":[10.608057,53.450653],"type":"Point"}
}