{
  "type": "Feature",
  "properties": {
    "iso:country":"DE",
    "sg:address":"Schmiedstr. 10",
    "sg:city":"Weyarn",
    "sg:phone":"+49 8020/1092",
    "sg:postcode":"83629",
    "sg:province":"Bayern",
    "wof:name":"Auto-sifferlinger Gbr",
    "wof:placetype":"venue"
},
  "geometry": {"coordinates":[11.809229,47.848991],"type":"Point"}
}