{
  "type": "Feature",
  "properties": {
    "iso:country":"DE",
    "sg:address":"Burgunder Str. 20",
    "sg:city":"Gro\u00dfwallstadt",
    "sg:phone":"+49 4960/2222350",
    "sg:postcode":"63868",
    "sg:province":"Bayern",
    "wof:name":"Markert Damenmoden Gmbh",
    "wof:placetype":"venue"
},
  "geometry": {"coordinates":[9.155201,49.87822],"type":"Point"}
}