{
  "type": "Feature",
  "properties": {
    "iso:country":"DE",
    "sg:address":"Am Rang 22",
    "sg:city":"Marktredwitz",
    "sg:phone":"+49 9231/2852",
    "sg:postcode":"95615",
    "sg:province":"Bayern",
    "wof:name":"Hans-peter Wei\u00df",
    "wof:placetype":"venue"
},
  "geometry": {"coordinates":[12.084628,50.001598],"type":"Point"}
}