{
  "type": "Feature",
  "properties": {
    "iso:country":"DE",
    "sg:address":"Sperberweg 29-31",
    "sg:city":"Rodgau",
    "sg:phone":"+49 6106/822550",
    "sg:postcode":"63110",
    "sg:province":"Hessen",
    "wof:name":"Gro\u00dfe Gmbh",
    "wof:placetype":"venue"
},
  "geometry": {"coordinates":[8.8921136856,50.0155715942],"type":"Point"}
}