{
  "type": "Feature",
  "properties": {
    "iso:country":"DE",
    "sg:address":"Siemensstr. 9",
    "sg:city":"Speyer",
    "sg:phone":"+49 6232/35272",
    "sg:postcode":"67346",
    "sg:province":"Rheinland-Pfalz",
    "wof:name":"Skip Schwei\u00dftechnik Und Rohrleitungsbau F. Kraftwerke",
    "wof:placetype":"venue"
},
  "geometry": {"coordinates":[8.424385,49.331059],"type":"Point"}
}