{
  "type": "Feature",
  "properties": {
    "iso:country":"DE",
    "sg:address":"Peter-Soemer-Str. 17",
    "sg:city":"Lennestadt",
    "sg:phone":"+49 2721/20670",
    "sg:postcode":"57368",
    "sg:province":"Nordrhein-Westfalen",
    "wof:name":"W\u00fcrden Gmbh",
    "wof:placetype":"venue"
},
  "geometry": {"coordinates":[8.057510376,51.1546707153],"type":"Point"}
}