{
  "type": "Feature",
  "properties": {
    "iso:country":"DE",
    "sg:address":"Neuburger Str. 90",
    "sg:city":"Passau",
    "sg:phone":"+49 851/52101",
    "sg:postcode":"94032",
    "sg:province":"Bayern",
    "wof:name":"A. Pilger",
    "wof:placetype":"venue"
},
  "geometry": {"coordinates":[13.4399614334,48.5671463013],"type":"Point"}
}