{
  "type": "Feature",
  "properties": {
    "iso:country":"DE",
    "sg:address":"Marxheimer Platz 4",
    "sg:city":"Frankfurt",
    "sg:phone":"+49 69/781111",
    "sg:postcode":"60326",
    "sg:province":"Hessen",
    "wof:name":"Abflu\u00df-flott Fr\u00f6hlich Gmbh",
    "wof:placetype":"venue"
},
  "geometry": {"coordinates":[8.6193552017,50.1017417908],"type":"Point"}
}