{
  "type": "Feature",
  "properties": {
    "iso:country":"DE",
    "sg:address":"Hauptstr. 156",
    "sg:city":"Hemer",
    "sg:phone":"+49 2372/16744",
    "sg:postcode":"58675",
    "sg:province":"Nordrhein-Westfalen",
    "wof:name":"Hans Wiemann Inh. Eva-maria Tillmann",
    "wof:placetype":"venue"
},
  "geometry": {"coordinates":[7.766832,51.383541],"type":"Point"}
}