{
  "type": "Feature",
  "properties": {
    "iso:country":"DE",
    "sg:address":"Auf der Furth 12",
    "sg:city":"Werdohl",
    "sg:phone":"+49 2392/7864",
    "sg:postcode":"58791",
    "sg:province":"Nordrhein-Westfalen",
    "wof:name":"Ev. Pfarramt Friedensgemeinde",
    "wof:placetype":"venue"
},
  "geometry": {"coordinates":[7.7517609596,51.2338142395],"type":"Point"}
}