{
  "type": "Feature",
  "properties": {
    "iso:country":"DE",
    "sg:address":"Kirchstr. 12",
    "sg:city":"Oberhausen",
    "sg:phone":"+49 208/890695",
    "sg:postcode":"46117",
    "sg:province":"Nordrhein-Westfalen",
    "wof:name":"W. Specht",
    "wof:placetype":"venue"
},
  "geometry": {"coordinates":[6.886802,51.501701],"type":"Point"}
}