{
  "type": "Feature",
  "properties": {
    "iso:country":"DE",
    "sg:address":"Graslitzer Str. 26",
    "sg:city":"Waldkraiburg",
    "sg:phone":"+49 8638/4822",
    "sg:postcode":"84478",
    "sg:province":"Bayern",
    "wof:name":"Roland Than",
    "wof:placetype":"venue"
},
  "geometry": {"coordinates":[12.3942661285,48.2037162781],"type":"Point"}
}