{
  "type": "Feature",
  "properties": {
    "iso:country":"DE",
    "sg:address":"Bahnhofstr. 17",
    "sg:city":"Rothenburg",
    "sg:phone":"+49 9861/2944",
    "sg:postcode":"91541",
    "sg:province":"Bayern",
    "wof:name":"Bahnhofsbuchhandlung M\u00fcller",
    "wof:placetype":"venue"
},
  "geometry": {"coordinates":[14.9656639099,51.3336143494],"type":"Point"}
}