{
  "type": "Feature",
  "properties": {
    "iso:country":"DE",
    "sg:address":"Schlutterweg 48 a",
    "sg:city":"Delmenhorst",
    "sg:phone":"+49 4221/20966",
    "sg:postcode":"27755",
    "sg:province":"Niedersachsen",
    "wof:name":"Ist-integierte System Technik Inh. A. Gavriel-ben-zvi E. K.",
    "wof:placetype":"venue"
},
  "geometry": {"coordinates":[8.6176433563,53.0331382751],"type":"Point"}
}