{
  "type": "Feature",
  "properties": {
    "iso:country":"DE",
    "sg:address":"Margaretenstr. 13",
    "sg:city":"Berlin",
    "sg:postcode":"12203",
    "sg:province":"Berlin",
    "wof:name":"Dipl.-ing. Ch. Schmeier Gmbh",
    "wof:placetype":"venue"
},
  "geometry": {"coordinates":[13.29827,52.44574],"type":"Point"}
}