{
  "type": "Feature",
  "properties": {
    "iso:country":"DE",
    "sg:address":"Bergstr. 30",
    "sg:city":"Gro\u00dfengottern",
    "sg:phone":"+49 36022/96253",
    "sg:postcode":"99991",
    "sg:province":"Th\u00fcringen",
    "wof:name":"Ludwig Hill",
    "wof:placetype":"venue"
},
  "geometry": {"coordinates":[10.565854,51.149303],"type":"Point"}
}