{
  "type": "Feature",
  "properties": {
    "iso:country":"DE",
    "sg:address":"Am Berggarten 15",
    "sg:city":"Wiesbaden",
    "sg:phone":"+49 6122/12797",
    "sg:postcode":"65207",
    "sg:province":"Hessen",
    "wof:name":"Egon Voigtl\u00e4nder",
    "wof:placetype":"venue"
},
  "geometry": {"coordinates":[8.3383016586,50.1086730957],"type":"Point"}
}