{
  "type": "Feature",
  "properties": {
    "iso:country":"DE",
    "sg:address":"Wundramstr. 26",
    "sg:city":"Hemmingen",
    "sg:phone":"+49 511/232801",
    "sg:postcode":"30966",
    "sg:province":"Niedersachsen",
    "wof:name":"Jest\u00e4dt Und Gadow-jest\u00e4dt Rechtsanw\u00e4lte U. Steuerberater",
    "wof:placetype":"venue"
},
  "geometry": {"coordinates":[9.7305135727,52.3270645142],"type":"Point"}
}