{
  "type": "Feature",
  "properties": {
    "iso:country":"DE",
    "sg:address":"Wetzendorfer Str. 261",
    "sg:city":"N\u00fcrnberg",
    "sg:phone":"+49 911/330544",
    "sg:postcode":"90427",
    "sg:province":"Bayern",
    "wof:name":"W. Kaminski",
    "wof:placetype":"venue"
},
  "geometry": {"coordinates":[11.038779,49.470833],"type":"Point"}
}