{
  "type": "Feature",
  "properties": {
    "iso:country":"DE",
    "sg:address":"Liebigstr. 10",
    "sg:city":"Frankfurt",
    "sg:phone":"+49 69/721769",
    "sg:postcode":"60323",
    "sg:province":"Hessen",
    "wof:name":"Westenberger Und Bachmann Rechtsanw\u00e4lte",
    "wof:placetype":"venue"
},
  "geometry": {"coordinates":[8.6663188934,50.1184844971],"type":"Point"}
}