{
  "type": "Feature",
  "properties": {
    "iso:country":"DE",
    "sg:address":"Putbusser Str. 12",
    "sg:city":"Berlin",
    "sg:phone":"+49 30/4642018",
    "sg:postcode":"13355",
    "sg:province":"Berlin",
    "wof:name":"Ranke-oberschule Hugo-herrmann-b\u00fccherei",
    "wof:placetype":"venue"
},
  "geometry": {"coordinates":[13.3940248489,52.544303894],"type":"Point"}
}