{
  "type": "Feature",
  "properties": {
    "iso:country":"DE",
    "sg:address":"Breite Str. 30",
    "sg:city":"Celle",
    "sg:phone":"+49 5141/25063",
    "sg:postcode":"29221",
    "sg:province":"Niedersachsen",
    "wof:name":"Wilhelm Pippel",
    "wof:placetype":"venue"
},
  "geometry": {"coordinates":[10.072234,52.619453],"type":"Point"}
}