{
  "type": "Feature",
  "properties": {
    "iso:country":"DE",
    "sg:address":"Gartenstr. 14",
    "sg:city":"St. Leon-Rot",
    "sg:phone":"+49 6227/59693",
    "sg:postcode":"68789",
    "sg:province":"Baden-W\u00fcrttemberg",
    "wof:name":"Richard Feuerstein",
    "wof:placetype":"venue"
},
  "geometry": {"coordinates":[8.62681,49.266544],"type":"Point"}
}