{
  "type": "Feature",
  "properties": {
    "iso:country":"DE",
    "sg:address":"Schm\u00f6ckwitzer Str. 34",
    "sg:city":"Eichwalde",
    "sg:phone":"+49 30/6758454",
    "sg:postcode":"15732",
    "sg:province":"Brandenburg",
    "wof:name":"Stern",
    "wof:placetype":"venue"
},
  "geometry": {"coordinates":[13.6300344467,52.373374939],"type":"Point"}
}