{
  "type": "Feature",
  "properties": {
    "iso:country":"DE",
    "sg:address":"Carl-Scheele-Str. 16",
    "sg:city":"Berlin",
    "sg:phone":"+49 30/67806760",
    "sg:postcode":"12489",
    "sg:province":"Berlin",
    "wof:name":"Lumics Gmbh",
    "wof:placetype":"venue"
},
  "geometry": {"coordinates":[13.5247564316,52.4298439026],"type":"Point"}
}