{
  "type": "Feature",
  "properties": {
    "iso:country":"DE",
    "sg:address":"L\u00f6hrstr. 131",
    "sg:city":"Koblenz",
    "sg:phone":"+49 261/12598",
    "sg:postcode":"56068",
    "sg:province":"Rheinland-Pfalz",
    "wof:name":"Hans-j\u00fcrgen F\u00fchrer Franz Obst",
    "wof:placetype":"venue"
},
  "geometry": {"coordinates":[7.5896601677,50.3524589539],"type":"Point"}
}