{
  "type": "Feature",
  "properties": {
    "iso:country":"DE",
    "sg:address":"Juri-Gagarin-Str.",
    "sg:city":"Vetschau",
    "sg:postcode":"03226",
    "sg:province":"Brandenburg",
    "wof:name":"Vetschauer Industrieservice Gmbh",
    "wof:placetype":"venue"
},
  "geometry": {"coordinates":[14.08336,51.787704],"type":"Point"}
}