{
  "type": "Feature",
  "properties": {
    "iso:country":"DE",
    "sg:address":"Schulstr. 4",
    "sg:city":"Werben",
    "sg:phone":"+49 35603/70562",
    "sg:postcode":"03096",
    "sg:province":"Brandenburg",
    "wof:name":"Wolfgang Mokschau",
    "wof:placetype":"venue"
},
  "geometry": {"coordinates":[14.1856412888,51.8136253357],"type":"Point"}
}