{
  "type": "Feature",
  "properties": {
    "iso:country":"DE",
    "sg:address":"Ollerkamp 7",
    "sg:city":"Rastede",
    "sg:phone":"+49 4402/2503",
    "sg:postcode":"26180",
    "sg:province":"Niedersachsen",
    "wof:name":"H. Und W. Bunjes",
    "wof:placetype":"venue"
},
  "geometry": {"coordinates":[8.194297,53.243687],"type":"Point"}
}