{
  "type": "Feature",
  "properties": {
    "iso:country":"DE",
    "sg:address":"Striepenweg 10",
    "sg:city":"Hamburg",
    "sg:phone":"+49 40/7963104",
    "sg:postcode":"21147",
    "sg:province":"Hamburg",
    "wof:name":"Erwin G\u00f6rke",
    "wof:placetype":"venue"
},
  "geometry": {"coordinates":[9.88559,53.474232],"type":"Point"}
}