{
  "type": "Feature",
  "properties": {
    "iso:country":"DE",
    "sg:address":"Schubertstr. 9",
    "sg:city":"Beckum",
    "sg:phone":"+49 2521/821960",
    "sg:postcode":"59269",
    "sg:province":"Nordrhein-Westfalen",
    "wof:name":"M. Neumann",
    "wof:placetype":"venue"
},
  "geometry": {"coordinates":[8.0370349884,51.7454528809],"type":"Point"}
}