{
  "type": "Feature",
  "properties": {
    "iso:country":"DE",
    "sg:address":"Marienberger Str. 23",
    "sg:city":"Augustusburg",
    "sg:phone":"+49 37291/60809",
    "sg:postcode":"09573",
    "sg:province":"Sachsen",
    "wof:name":"Bernd Richter",
    "wof:placetype":"venue"
},
  "geometry": {"coordinates":[13.1015281677,50.8102531433],"type":"Point"}
}