{
  "type": "Feature",
  "properties": {
    "iso:country":"DE",
    "sg:address":"Leinpfad 12",
    "sg:city":"Ingelheim",
    "sg:phone":"+49 6132/84668",
    "sg:postcode":"55218",
    "sg:province":"Rheinland-Pfalz",
    "wof:name":"Rudi Bockius",
    "wof:placetype":"venue"
},
  "geometry": {"coordinates":[8.0319795609,49.9849243164],"type":"Point"}
}