{
  "type": "Feature",
  "properties": {
    "iso:country":"DE",
    "sg:address":"Talweg 3",
    "sg:city":"Bad Heilbrunn",
    "sg:phone":"+49 8046/8179",
    "sg:postcode":"83670",
    "sg:province":"Bayern",
    "wof:name":"Fremdenheim Resi Pischel",
    "wof:placetype":"venue"
},
  "geometry": {"coordinates":[11.4579715729,47.7490501404],"type":"Point"}
}