{
  "type": "Feature",
  "properties": {
    "iso:country":"DE",
    "sg:address":"Schwarze \u00c4cker 87",
    "sg:city":"K\u00fcrnach",
    "sg:postcode":"97273",
    "sg:province":"Bayern",
    "wof:name":"Gebr. Troll Gmbh",
    "wof:placetype":"venue"
},
  "geometry": {"coordinates":[10.0455560684,49.8428421021],"type":"Point"}
}