{
  "type": "Feature",
  "properties": {
    "iso:country":"DE",
    "sg:address":"Zu den Ferndorfwiesen 1",
    "sg:city":"Kreuztal",
    "sg:phone":"+49 2732/4001",
    "sg:postcode":"57223",
    "sg:province":"Nordrhein-Westfalen",
    "wof:name":"Holzhandlung Bald Gmbh",
    "wof:placetype":"venue"
},
  "geometry": {"coordinates":[8.0255880356,50.9585876465],"type":"Point"}
}