{
  "type": "Feature",
  "properties": {
    "iso:country":"DE",
    "sg:address":"Kr\u00fcllsdyk 13",
    "sg:city":"Krefeld",
    "sg:phone":"+49 2151/750982",
    "sg:postcode":"47803",
    "sg:province":"Nordrhein-Westfalen",
    "wof:name":"G. Meyer",
    "wof:placetype":"venue"
},
  "geometry": {"coordinates":[6.5550708771,51.3436698914],"type":"Point"}
}