{
  "type": "Feature",
  "properties": {
    "iso:country":"DE",
    "sg:address":"D\u00f6rrm\u00fchle 5",
    "sg:city":"Merzig",
    "sg:phone":"+49 4968/6193070",
    "sg:postcode":"66663",
    "sg:province":"Saarland",
    "wof:name":"Lku Luft-klima-umwelttechnik Gmbh",
    "wof:placetype":"venue"
},
  "geometry": {"coordinates":[6.63651,49.442039],"type":"Point"}
}