{
  "type": "Feature",
  "properties": {
    "iso:country":"DE",
    "sg:address":"Rankestr. 9",
    "sg:city":"Berlin",
    "sg:phone":"+49 30/8815308",
    "sg:postcode":"10789",
    "sg:province":"Berlin",
    "wof:name":"Hotel-pension Elite",
    "wof:placetype":"venue"
},
  "geometry": {"coordinates":[13.3329648972,52.5020141602],"type":"Point"}
}