{
  "type": "Feature",
  "properties": {
    "iso:country":"DE",
    "sg:address":"Holl\u00e4ndische Str. 128",
    "sg:city":"Vellmar",
    "sg:phone":"+49 561/824168",
    "sg:postcode":"34246",
    "sg:province":"Hessen",
    "wof:name":"N\u00fcndel Gmbh",
    "wof:placetype":"venue"
},
  "geometry": {"coordinates":[9.47535,51.345779],"type":"Point"}
}