{
  "type": "Feature",
  "properties": {
    "iso:country":"DE",
    "sg:address":"Kurf\u00fcrstenring 12-18",
    "sg:city":"Amberg",
    "sg:phone":"+49 9621/3710",
    "sg:postcode":"92224",
    "sg:province":"Bayern",
    "wof:name":"Deprag Schulz Gmbh & Co.",
    "wof:placetype":"venue"
},
  "geometry": {"coordinates":[11.8609838486,49.4432411194],"type":"Point"}
}