{
  "type": "Feature",
  "properties": {
    "iso:country":"DE",
    "sg:address":"Buschstr. 6",
    "sg:city":"Schwerin",
    "sg:phone":"+49 385/593330",
    "sg:postcode":"19053",
    "sg:province":"Mecklenburg-Vorpommern",
    "wof:name":"Com In Gesellschaft F\u00fcr Computer-software-service Mbh",
    "wof:placetype":"venue"
},
  "geometry": {"coordinates":[11.4132261276,53.6280403137],"type":"Point"}
}