{
  "type": "Feature",
  "properties": {
    "iso:country":"DE",
    "sg:address":"In der Bebie 10",
    "sg:city":"Hannover",
    "sg:phone":"+49 511/9524766",
    "sg:postcode":"30539",
    "sg:province":"Niedersachsen",
    "wof:name":"Unihelp.de- Alles Von Und F\u00fcr Studenten",
    "wof:placetype":"venue"
},
  "geometry": {"coordinates":[9.838051,52.352856],"type":"Point"}
}