{
  "type": "Feature",
  "properties": {
    "iso:country":"DE",
    "sg:address":"Elbestr. 2",
    "sg:city":"Oyten",
    "sg:phone":"+49 4207/803921",
    "sg:postcode":"28876",
    "sg:province":"Niedersachsen",
    "wof:name":"T. Schwiebert",
    "wof:placetype":"venue"
},
  "geometry": {"coordinates":[9.0143270493,53.0433578491],"type":"Point"}
}