{
  "type": "Feature",
  "properties": {
    "iso:country":"DE",
    "sg:address":"Schlesierstr. 19",
    "sg:city":"M\u00fcnchen",
    "sg:phone":"+49 89/683932",
    "sg:postcode":"81669",
    "sg:province":"Bayern",
    "wof:name":"Heinz Herbst",
    "wof:placetype":"venue"
},
  "geometry": {"coordinates":[11.6065597534,48.1142959595],"type":"Point"}
}