{
  "type": "Feature",
  "properties": {
    "iso:country":"DE",
    "sg:address":"Heinrich-Welken-Str. 3",
    "sg:city":"Hamm",
    "sg:phone":"+49 2385/441",
    "sg:postcode":"59069",
    "sg:province":"Nordrhein-Westfalen",
    "wof:name":"Sikkens Service",
    "wof:placetype":"venue"
},
  "geometry": {"coordinates":[7.852852,51.623127],"type":"Point"}
}