{
  "type": "Feature",
  "properties": {
    "iso:country":"DE",
    "sg:address":"August-Keiler-Str. 13",
    "sg:city":"Germersheim",
    "sg:postcode":"76726",
    "sg:province":"Rheinland-Pfalz",
    "wof:name":"Hgw Haus Grundst\u00fccks- Und Wohnungsverwaltung Gmbh",
    "wof:placetype":"venue"
},
  "geometry": {"coordinates":[8.3742609024,49.2123527527],"type":"Point"}
}