{
  "type": "Feature",
  "properties": {
    "iso:country":"DE",
    "sg:address":"Lanzstr. 2",
    "sg:city":"Heddesheim",
    "sg:postcode":"68542",
    "sg:province":"Baden-W\u00fcrttemberg",
    "wof:name":"Mhz-formen- Und Werkzeugbau Gmbh",
    "wof:placetype":"venue"
},
  "geometry": {"coordinates":[8.6347913742,49.5110931396],"type":"Point"}
}