{
  "type": "Feature",
  "properties": {
    "iso:country":"DE",
    "sg:address":"Industriestr. 10",
    "sg:city":"Hilpoltstein",
    "sg:phone":"+49 9174/9473",
    "sg:postcode":"91161",
    "sg:province":"Bayern",
    "wof:name":"Konrad Huber Gmbh",
    "wof:placetype":"venue"
},
  "geometry": {"coordinates":[11.186707,49.186474],"type":"Point"}
}