{
  "type": "Feature",
  "properties": {
    "iso:country":"DE",
    "sg:address":"Steinenbach",
    "sg:city":"Deggenhausertal",
    "sg:phone":"+49 7555/5554",
    "sg:postcode":"88693",
    "sg:province":"Baden-W\u00fcrttemberg",
    "wof:name":"W. Mayer Ingenieur",
    "wof:placetype":"venue"
},
  "geometry": {"coordinates":[9.3943529129,47.8068695068],"type":"Point"}
}