{
  "type": "Feature",
  "properties": {
    "iso:country":"DE",
    "sg:address":"Schwabenstr. 9",
    "sg:city":"Legau",
    "sg:phone":"+49 8330/911091",
    "sg:postcode":"87764",
    "sg:province":"Bayern",
    "wof:name":"Ganzer Gmbh",
    "wof:placetype":"venue"
},
  "geometry": {"coordinates":[10.1273298264,47.855796814],"type":"Point"}
}