{
  "type": "Feature",
  "properties": {
    "iso:country":"DE",
    "sg:address":"Darmst\u00e4dter Str. 14",
    "sg:city":"Ober-Ramstadt",
    "sg:phone":"+49 6154/2226",
    "sg:postcode":"64372",
    "sg:province":"Hessen",
    "wof:name":"Friedrich Katzenmeier",
    "wof:placetype":"venue"
},
  "geometry": {"coordinates":[8.7472085953,49.8300018311],"type":"Point"}
}