{
  "type": "Feature",
  "properties": {
    "iso:country":"DE",
    "sg:address":"Kleiansring 62",
    "sg:city":"D\u00fcsseldorf",
    "sg:phone":"+49 211/9406926",
    "sg:postcode":"40489",
    "sg:province":"Nordrhein-Westfalen",
    "wof:name":"Procar Carconcept Gmbh",
    "wof:placetype":"venue"
},
  "geometry": {"coordinates":[6.753882,51.298889],"type":"Point"}
}