{
  "type": "Feature",
  "properties": {
    "iso:country":"DE",
    "sg:address":"Gsteinacher Str. 14",
    "sg:city":"Schwarzenbruck",
    "sg:phone":"+49 9128/2399",
    "sg:postcode":"90592",
    "sg:province":"Bayern",
    "wof:name":"Rainer Haid Steuerberater",
    "wof:placetype":"venue"
},
  "geometry": {"coordinates":[11.2326631546,49.3577957153],"type":"Point"}
}