{
  "type": "Feature",
  "properties": {
    "iso:country":"DE",
    "sg:address":"Kaufering",
    "sg:city":"Kaufering",
    "sg:phone":"+49 8191/65790",
    "sg:postcode":"86916",
    "sg:province":"Bayern",
    "wof:name":"Raiffeisenbank Kaufering-landsberg",
    "wof:placetype":"venue"
},
  "geometry": {"coordinates":[10.87246,48.10144],"type":"Point"}
}