{
  "type": "Feature",
  "properties": {
    "iso:country":"DE",
    "sg:address":"Webergasse 26",
    "sg:city":"Wiesbaden",
    "sg:phone":"+49 611/844705",
    "sg:postcode":"65183",
    "sg:province":"Hessen",
    "wof:name":"Josef Rappl Augenoptiker",
    "wof:placetype":"venue"
},
  "geometry": {"coordinates":[8.2412061691,50.0848426819],"type":"Point"}
}