{
  "type": "Feature",
  "properties": {
    "iso:country":"DE",
    "sg:address":"Peterstr. 11",
    "sg:city":"Nordenham",
    "sg:phone":"+49 4731/6974",
    "sg:postcode":"26954",
    "sg:province":"Niedersachsen",
    "wof:name":"Pizzeria La Pergola",
    "wof:placetype":"venue"
},
  "geometry": {"coordinates":[8.4856672287,53.483833313],"type":"Point"}
}