{
  "type": "Feature",
  "properties": {
    "iso:country":"DE",
    "sg:address":"Obermoosstr. 58",
    "sg:city":"M\u00fcnchen",
    "sg:phone":"+49 89/3132650",
    "sg:postcode":"80995",
    "sg:province":"Bayern",
    "wof:name":"Anton Kronthaler",
    "wof:placetype":"venue"
},
  "geometry": {"coordinates":[11.522158,48.21067],"type":"Point"}
}