{
  "type": "Feature",
  "properties": {
    "iso:country":"DE",
    "sg:address":"Wilhelmstr. 55",
    "sg:city":"Betzdorf",
    "sg:phone":"+49 2741/27733",
    "sg:postcode":"57518",
    "sg:province":"Rheinland-Pfalz",
    "wof:name":"R. Remhof",
    "wof:placetype":"venue"
},
  "geometry": {"coordinates":[7.8682799339,50.7918395996],"type":"Point"}
}