{
  "type": "Feature",
  "properties": {
    "iso:country":"DE",
    "sg:address":"Saaruferstr. 17",
    "sg:city":"Saarbr\u00fccken",
    "sg:phone":"+49 681/948000",
    "sg:postcode":"66117",
    "sg:province":"Saarland",
    "wof:name":"Saarland-spielbank Gmbh",
    "wof:placetype":"venue"
},
  "geometry": {"coordinates":[6.9897699356,49.2359580994],"type":"Point"}
}