{
  "type": "Feature",
  "properties": {
    "iso:country":"DE",
    "sg:address":"Dorfstr. 17",
    "sg:city":"Stolpe",
    "sg:phone":"+49 3303/500723",
    "sg:postcode":"16540",
    "sg:province":"Brandenburg",
    "wof:name":"B. Hahn",
    "wof:placetype":"venue"
},
  "geometry": {"coordinates":[13.2571563721,52.6587142944],"type":"Point"}
}