{
  "type": "Feature",
  "properties": {
    "iso:country":"DE",
    "sg:address":"Lange Str. 82",
    "sg:city":"Detmold",
    "sg:phone":"+49 5231/37356",
    "sg:postcode":"32756",
    "sg:province":"Nordrhein-Westfalen",
    "wof:name":"Ada-grill",
    "wof:placetype":"venue"
},
  "geometry": {"coordinates":[8.8825540543,51.9376029968],"type":"Point"}
}