{
  "type": "Feature",
  "properties": {
    "iso:country":"DE",
    "sg:address":"Sch\u00f6nbergstr. 20",
    "sg:city":"Ostfildern",
    "sg:phone":"+49 711/451240",
    "sg:postcode":"73760",
    "sg:province":"Baden-W\u00fcrttemberg",
    "wof:name":"Simba Computer Systeme Gmbh",
    "wof:placetype":"venue"
},
  "geometry": {"coordinates":[9.2274923325,48.7241401672],"type":"Point"}
}