{
  "type": "Feature",
  "properties": {
    "iso:country":"DE",
    "sg:address":"Naumannstr. 79",
    "sg:city":"Berlin",
    "sg:phone":"+49 4930/7816435",
    "sg:postcode":"10829",
    "sg:province":"Berlin",
    "wof:name":"Gottschalk Druck @ Medien Gmbh",
    "wof:placetype":"venue"
},
  "geometry": {"coordinates":[13.3636693954,52.4799461365],"type":"Point"}
}