{
  "type": "Feature",
  "properties": {
    "iso:country":"DE",
    "sg:address":"Nibelungenstr. 41",
    "sg:city":"Lautertal",
    "sg:phone":"+49 6251/68273",
    "sg:postcode":"64686",
    "sg:province":"Hessen",
    "wof:name":"Otto Werner",
    "wof:placetype":"venue"
},
  "geometry": {"coordinates":[8.6682739258,49.7012519836],"type":"Point"}
}