{
  "type": "Feature",
  "properties": {
    "iso:country":"DE",
    "sg:address":"Nibelungenstr. 139",
    "sg:city":"Lautertal",
    "sg:phone":"+49 6251/69398",
    "sg:postcode":"64686",
    "sg:province":"Hessen",
    "wof:name":"L. Dude & Co.",
    "wof:placetype":"venue"
},
  "geometry": {"coordinates":[8.6781578064,49.7052116394],"type":"Point"}
}