{
  "type": "Feature",
  "properties": {
    "iso:country":"DE",
    "sg:address":"An der Stadtwiese 8",
    "sg:city":"Erbach",
    "sg:phone":"+49 6062/61959",
    "sg:postcode":"64711",
    "sg:province":"Hessen",
    "wof:name":"St\u00f6hr & Tischler B\u00fchnentechnik",
    "wof:placetype":"venue"
},
  "geometry": {"coordinates":[8.989176,49.66256],"type":"Point"}
}