{
  "type": "Feature",
  "properties": {
    "iso:country":"DE",
    "sg:address":"Waldstr 33a",
    "sg:city":"Neu-Isenburg",
    "sg:phone":"+49 6102/4027",
    "sg:postcode":"63263",
    "sg:province":"Hessen",
    "wof:name":"Dental-laboratorium Dr. Elbrecht Gmbh",
    "wof:placetype":"venue"
},
  "geometry": {"coordinates":[8.691607,50.056362],"type":"Point"}
}