{
  "type": "Feature",
  "properties": {
    "iso:country":"DE",
    "sg:address":"Bornstr. 22",
    "sg:city":"Dortmund",
    "sg:phone":"+49 231/5330326",
    "sg:postcode":"44135",
    "sg:province":"Nordrhein-Westfalen",
    "wof:name":"D.d. Dienstleistungen E. K.",
    "wof:placetype":"venue"
},
  "geometry": {"coordinates":[7.469255,51.51865],"type":"Point"}
}