{
  "type": "Feature",
  "properties": {
    "iso:country":"DE",
    "sg:address":"An de B\u00e4k 2",
    "sg:city":"Schulendorf",
    "sg:phone":"+49 4155/6635",
    "sg:postcode":"21516",
    "sg:province":"Schleswig-Holstein",
    "wof:name":"Ama Sch\u00f6ner Wohnen Vertriebsges. Mbh",
    "wof:placetype":"venue"
},
  "geometry": {"coordinates":[10.5664863586,53.4727745056],"type":"Point"}
}