{
  "type": "Feature",
  "properties": {
    "iso:country":"DE",
    "sg:address":"M\u00fchlgasse 7",
    "sg:city":"Wiesbaden",
    "sg:phone":"+49 611",
    "sg:postcode":"65183",
    "sg:province":"Hessen",
    "wof:name":"Handelsvertretungen",
    "wof:placetype":"venue"
},
  "geometry": {"coordinates":[8.2424230576,50.0834465027],"type":"Point"}
}