{
  "type": "Feature",
  "properties": {
    "iso:country":"DE",
    "sg:address":"Am Krappen 17",
    "sg:city":"Marburg",
    "sg:phone":"+49 6421/93270",
    "sg:postcode":"35037",
    "sg:province":"Hessen",
    "wof:name":"Manfred K\u00fcllmer Ingenieur",
    "wof:placetype":"venue"
},
  "geometry": {"coordinates":[8.7422332764,50.8041381836],"type":"Point"}
}