{
  "type": "Feature",
  "properties": {
    "iso:country":"DE",
    "sg:address":"Teutoburgiastr. 34",
    "sg:city":"Herne",
    "sg:phone":"+49 2323/31906",
    "sg:postcode":"44628",
    "sg:province":"Nordrhein-Westfalen",
    "wof:name":"Luigina Kurtz Textilien",
    "wof:placetype":"venue"
},
  "geometry": {"coordinates":[7.2742710114,51.5506362915],"type":"Point"}
}