{
  "type": "Feature",
  "properties": {
    "iso:country":"DE",
    "sg:address":"Hauptstr. 31",
    "sg:city":"Rosengarten",
    "sg:phone":"+49 4108/5910",
    "sg:postcode":"21224",
    "sg:province":"Niedersachsen",
    "wof:name":"Hotel-restaurant Holst Gmbh & Co.",
    "wof:placetype":"venue"
},
  "geometry": {"coordinates":[9.8892250061,53.4071350098],"type":"Point"}
}