{
  "type": "Feature",
  "properties": {
    "iso:country":"DE",
    "sg:address":"Hauzensteiner Str. 3",
    "sg:city":"Regenstauf",
    "sg:phone":"+49 9402/2383",
    "sg:postcode":"93128",
    "sg:province":"Bayern",
    "wof:name":"Reiseb\u00fcro Brandl Gmbh",
    "wof:placetype":"venue"
},
  "geometry": {"coordinates":[12.1284132004,49.1227684021],"type":"Point"}
}