{
  "type": "Feature",
  "properties": {
    "iso:country":"DE",
    "sg:address":"An den Platanen 7",
    "sg:city":"Duisburg",
    "sg:phone":"+49 203/6082844",
    "sg:postcode":"47279",
    "sg:province":"Nordrhein-Westfalen",
    "wof:name":"Wedau-online",
    "wof:placetype":"venue"
},
  "geometry": {"coordinates":[6.797733,51.392624],"type":"Point"}
}