{
  "type": "Feature",
  "properties": {
    "iso:country":"DE",
    "sg:address":"Schweinfurter Str. 29",
    "sg:city":"Aidhausen",
    "sg:phone":"+49 9526/315",
    "sg:postcode":"97491",
    "sg:province":"Bayern",
    "wof:name":"Fensterbau Albert Gmbh",
    "wof:placetype":"venue"
},
  "geometry": {"coordinates":[10.429638,50.152779],"type":"Point"}
}