{
  "type": "Feature",
  "properties": {
    "iso:country":"DE",
    "sg:address":"Damaschkestr. 12",
    "sg:city":"Moers",
    "sg:postcode":"47443",
    "sg:province":"Nordrhein-Westfalen",
    "wof:name":"Sidia Gmbh",
    "wof:placetype":"venue"
},
  "geometry": {"coordinates":[6.6708388329,51.4469146729],"type":"Point"}
}