{
  "type": "Feature",
  "properties": {
    "iso:country":"DE",
    "sg:address":"Breitestr. 1",
    "sg:city":"Engen",
    "sg:phone":"+49 4977/335090",
    "sg:postcode":"78234",
    "sg:province":"Baden-W\u00fcrttemberg",
    "wof:name":"Volksbank Eg",
    "wof:placetype":"venue"
},
  "geometry": {"coordinates":[8.772617,47.855473],"type":"Point"}
}