{
  "type": "Feature",
  "properties": {
    "iso:country":"DE",
    "sg:address":"Dreisesselstr. 45",
    "sg:city":"Neureichenau",
    "sg:phone":"+49 8583/2045",
    "sg:postcode":"94089",
    "sg:province":"Bayern",
    "wof:name":"Anton Weidinger",
    "wof:placetype":"venue"
},
  "geometry": {"coordinates":[13.743899,48.752647],"type":"Point"}
}