{
  "type": "Feature",
  "properties": {
    "iso:country":"DE",
    "sg:address":"Friedrichstr. 50",
    "sg:city":"Freudenstadt",
    "sg:phone":"+49 7441/4174",
    "sg:postcode":"72250",
    "sg:province":"Baden-W\u00fcrttemberg",
    "wof:name":"Oskar Burtscher",
    "wof:placetype":"venue"
},
  "geometry": {"coordinates":[8.40878582,48.4649009705],"type":"Point"}
}