{
  "type": "Feature",
  "properties": {
    "iso:country":"DE",
    "sg:address":"Wiesenstr. 29",
    "sg:city":"Eltville",
    "sg:phone":"+49 6123/72457",
    "sg:postcode":"65344",
    "sg:province":"Hessen",
    "wof:name":"Alfred Jakob",
    "wof:placetype":"venue"
},
  "geometry": {"coordinates":[8.1262102127,50.049659729],"type":"Point"}
}