{
  "type": "Feature",
  "properties": {
    "iso:country":"DE",
    "sg:address":"Schulstr. 16",
    "sg:city":"Kottenheim",
    "sg:phone":"+49 2651/947253",
    "sg:postcode":"56736",
    "sg:province":"Rheinland-Pfalz",
    "wof:name":"Wilma Konrad Steuerberaterin",
    "wof:placetype":"venue"
},
  "geometry": {"coordinates":[7.259428978,50.348361969],"type":"Point"}
}