{
  "type": "Feature",
  "properties": {
    "iso:country":"DE",
    "sg:address":"Killisfeldstr. 40 A",
    "sg:city":"Karlsruhe",
    "sg:postcode":"76227",
    "sg:province":"Baden-W\u00fcrttemberg",
    "wof:name":"Mass Cad Engineering Gmbh",
    "wof:placetype":"venue"
},
  "geometry": {"coordinates":[8.452516,48.996807],"type":"Point"}
}