{
  "type": "Feature",
  "properties": {
    "iso:country":"DE",
    "sg:address":"Birkengartenstr. 12",
    "sg:city":"Leverkusen",
    "sg:phone":"+49 214/4047580",
    "sg:postcode":"51373",
    "sg:province":"Nordrhein-Westfalen",
    "wof:name":"Sebastiano Landucci Tiefbau Gmbh",
    "wof:placetype":"venue"
},
  "geometry": {"coordinates":[6.986495018,51.028339386],"type":"Point"}
}