{
  "type": "Feature",
  "properties": {
    "iso:country":"DE",
    "sg:address":"Pfarrgasse 6",
    "sg:city":"R\u00f6dermark",
    "sg:phone":"+49 6074/90100",
    "sg:postcode":"63322",
    "sg:province":"Hessen",
    "wof:name":"Kath. Pfarramt St. Nazavius",
    "wof:placetype":"venue"
},
  "geometry": {"coordinates":[8.8266887665,49.9787712097],"type":"Point"}
}