{
  "type": "Feature",
  "properties": {
    "iso:country":"DE",
    "sg:address":"Dorfstr. 35",
    "sg:city":"Au",
    "sg:phone":"+49 761/402288",
    "sg:postcode":"79280",
    "sg:province":"Baden-W\u00fcrttemberg",
    "wof:name":"Stube",
    "wof:placetype":"venue"
},
  "geometry": {"coordinates":[7.8290581703,47.9556808472],"type":"Point"}
}