{
  "type": "Feature",
  "properties": {
    "iso:country":"DE",
    "sg:address":"Inselstr. 10",
    "sg:city":"Meckenbeuren",
    "sg:phone":"+49 7542/1675",
    "sg:postcode":"88074",
    "sg:province":"Baden-W\u00fcrttemberg",
    "wof:name":"Ernst Moser",
    "wof:placetype":"venue"
},
  "geometry": {"coordinates":[9.550077,47.701981],"type":"Point"}
}