{
  "type": "Feature",
  "properties": {
    "iso:country":"DE",
    "sg:address":"Uzstr. 26",
    "sg:city":"Ansbach",
    "sg:phone":"+49 981/3595",
    "sg:postcode":"91522",
    "sg:province":"Bayern",
    "wof:name":"Konditorei-cafe Linder",
    "wof:placetype":"venue"
},
  "geometry": {"coordinates":[10.571436,49.301407],"type":"Point"}
}