{
  "type": "Feature",
  "properties": {
    "iso:country":"DE",
    "sg:address":"Frohngasse 7",
    "sg:city":"Z\u00fclpich",
    "sg:phone":"+49 2251/51349",
    "sg:postcode":"53909",
    "sg:province":"Nordrhein-Westfalen",
    "wof:name":"Josef Zimmer",
    "wof:placetype":"venue"
},
  "geometry": {"coordinates":[6.739558,50.707256],"type":"Point"}
}