{
  "type": "Feature",
  "properties": {
    "iso:country":"DE",
    "sg:address":"Friedrichstr. 6",
    "sg:city":"D\u00fcsseldorf",
    "sg:phone":"+49 211/371118",
    "sg:postcode":"40217",
    "sg:province":"Nordrhein-Westfalen",
    "wof:name":"Dimitra Sciniti",
    "wof:placetype":"venue"
},
  "geometry": {"coordinates":[6.7771010399,51.2176017761],"type":"Point"}
}