{
  "type": "Feature",
  "properties": {
    "iso:country":"DE",
    "sg:address":"Alte Lohmarer Str. 59",
    "sg:city":"Siegburg",
    "sg:phone":"+49 2241/1220",
    "sg:postcode":"53721",
    "sg:province":"Nordrhein-Westfalen",
    "wof:name":"Dohle Handelsgruppe Systemberatung Gmbh",
    "wof:placetype":"venue"
},
  "geometry": {"coordinates":[7.21043396,50.8128128052],"type":"Point"}
}