{
  "type": "Feature",
  "properties": {
    "iso:country":"DE",
    "sg:address":"Bahnhofstr. 7",
    "sg:city":"Tirschenreuth",
    "sg:phone":"+49 9631/795533",
    "sg:postcode":"95643",
    "sg:province":"Bayern",
    "wof:name":"Kurt Robl Ergotherapeutsche Praxis",
    "wof:placetype":"venue"
},
  "geometry": {"coordinates":[12.334495,49.877983],"type":"Point"}
}