{
  "type": "Feature",
  "properties": {
    "iso:country":"DE",
    "sg:address":"Buersche Str. 11",
    "sg:city":"Osnabr\u00fcck",
    "sg:phone":"+49 541/4263",
    "sg:postcode":"49074",
    "sg:province":"Niedersachsen",
    "wof:name":"W. Borgstedt & Sohn Gmbh & Co. Kg",
    "wof:placetype":"venue"
},
  "geometry": {"coordinates":[8.056886673,52.2759857178],"type":"Point"}
}