{
  "type": "Feature",
  "properties": {
    "iso:country":"DE",
    "sg:address":"Hauptstr. 55",
    "sg:city":"B\u00fchl",
    "sg:phone":"+49 7223/948871",
    "sg:postcode":"77815",
    "sg:province":"Baden-W\u00fcrttemberg",
    "wof:name":"Der Kurier",
    "wof:placetype":"venue"
},
  "geometry": {"coordinates":[8.1362800598,48.6961555481],"type":"Point"}
}