{
  "type": "Feature",
  "properties": {
    "iso:country":"DE",
    "sg:address":"Friedensstr. 10",
    "sg:city":"Esslingen",
    "sg:phone":"+49 711/3168533",
    "sg:postcode":"73728",
    "sg:province":"Baden-W\u00fcrttemberg",
    "wof:name":"Manfred Haas",
    "wof:placetype":"venue"
},
  "geometry": {"coordinates":[9.315571785,48.7382621765],"type":"Point"}
}