{
  "type": "Feature",
  "properties": {
    "iso:country":"DE",
    "sg:address":"Jakob-Borchers-Str. 15",
    "sg:city":"Zetel",
    "sg:phone":"+49 4453/2470",
    "sg:postcode":"26340",
    "sg:province":"Niedersachsen",
    "wof:name":"J. De Boer",
    "wof:placetype":"venue"
},
  "geometry": {"coordinates":[7.974389,53.419834],"type":"Point"}
}