{
  "type": "Feature",
  "properties": {
    "iso:country":"DE",
    "sg:address":"W\u00fcrzburger Str. 16",
    "sg:city":"Frankfurt",
    "sg:phone":"+49 69/443505",
    "sg:postcode":"60385",
    "sg:province":"Hessen",
    "wof:name":"Karl Schmitt",
    "wof:placetype":"venue"
},
  "geometry": {"coordinates":[8.705164,50.122074],"type":"Point"}
}