{
  "type": "Feature",
  "properties": {
    "iso:country":"DE",
    "sg:address":"Neuhauser Str. 12",
    "sg:city":"Tosterglope",
    "sg:phone":"+49 5851/229",
    "sg:postcode":"21371",
    "sg:province":"Niedersachsen",
    "wof:name":"Johann-friedrich Saucke",
    "wof:placetype":"venue"
},
  "geometry": {"coordinates":[10.821926,53.209194],"type":"Point"}
}