{
  "type": "Feature",
  "properties": {
    "iso:country":"DE",
    "sg:address":"Gasthaushelmer 4",
    "sg:city":"Aurich",
    "sg:phone":"+49 4941/71476",
    "sg:postcode":"26607",
    "sg:province":"Niedersachsen",
    "wof:name":"Rolf Coordes",
    "wof:placetype":"venue"
},
  "geometry": {"coordinates":[7.4639701843,53.5106010437],"type":"Point"}
}