{
  "type": "Feature",
  "properties": {
    "iso:country":"DE",
    "sg:address":"Brehnaer Str. 2",
    "sg:city":"Landsberg",
    "sg:phone":"+49 34602/20713",
    "sg:postcode":"06188",
    "sg:province":"Sachsen-Anhalt",
    "wof:name":"Menksche Betonsteinwerke Gmbh & Co. Kg",
    "wof:placetype":"venue"
},
  "geometry": {"coordinates":[12.1051597595,51.5272598267],"type":"Point"}
}