{
  "type": "Feature",
  "properties": {
    "iso:country":"DE",
    "sg:address":"Winsener Stieg 15",
    "sg:city":"Hamburg",
    "sg:phone":"+49 40/7691780",
    "sg:postcode":"21079",
    "sg:province":"Hamburg",
    "wof:name":"Erich Henning Elektro-anlagen Gmbh",
    "wof:placetype":"venue"
},
  "geometry": {"coordinates":[9.986056,53.422543],"type":"Point"}
}