{
  "type": "Feature",
  "properties": {
    "iso:country":"DE",
    "sg:address":"Corrensstr. 38",
    "sg:city":"T\u00fcbingen",
    "sg:phone":"+49 7071/601229",
    "sg:postcode":"72076",
    "sg:province":"Baden-W\u00fcrttemberg",
    "wof:name":"Max-planck-institut F\u00fcr Biologie",
    "wof:placetype":"venue"
},
  "geometry": {"coordinates":[9.0614614487,48.5340499878],"type":"Point"}
}