{
  "type": "Feature",
  "properties": {
    "iso:country":"DE",
    "sg:address":"Leipziger Str. 82",
    "sg:city":"Glauchau",
    "sg:phone":"+49 3763/2596",
    "sg:postcode":"08371",
    "sg:province":"Sachsen",
    "wof:name":"Reinhard Heese",
    "wof:placetype":"venue"
},
  "geometry": {"coordinates":[12.5426111221,50.8202438354],"type":"Point"}
}