{
  "type": "Feature",
  "properties": {
    "iso:country":"DE",
    "sg:address":"Hauptstr. 17",
    "sg:city":"Neunheilingen",
    "sg:phone":"+49 36043/70271",
    "sg:postcode":"99947",
    "sg:province":"Th\u00fcringen",
    "wof:name":"Elga Hofmann",
    "wof:placetype":"venue"
},
  "geometry": {"coordinates":[10.6773386002,51.1933479309],"type":"Point"}
}