{
  "type": "Feature",
  "properties": {
    "iso:country":"DE",
    "sg:address":"Richard-Schirrmann-Weg 4",
    "sg:city":"M\u00fcnster",
    "sg:phone":"+49 251/521071",
    "sg:postcode":"48151",
    "sg:province":"Nordrhein-Westfalen",
    "wof:name":"Ulrich G. Haaring Und J. Willamowski",
    "wof:placetype":"venue"
},
  "geometry": {"coordinates":[7.614623,51.953762],"type":"Point"}
}