{
  "type": "Feature",
  "properties": {
    "iso:country":"DE",
    "sg:address":"Strandweg 46",
    "sg:city":"Selm",
    "sg:phone":"+49 2592/4075",
    "sg:postcode":"59379",
    "sg:province":"Nordrhein-Westfalen",
    "wof:name":"Josef Schrage",
    "wof:placetype":"venue"
},
  "geometry": {"coordinates":[7.431007,51.717457],"type":"Point"}
}