{
  "type": "Feature",
  "properties": {
    "iso:country":"DE",
    "sg:address":"Dominicusstr. 6",
    "sg:city":"Koblenz",
    "sg:phone":"+49 261/46742",
    "sg:postcode":"56073",
    "sg:province":"Rheinland-Pfalz",
    "wof:name":"Otto Hermann",
    "wof:placetype":"venue"
},
  "geometry": {"coordinates":[7.57569,50.354969],"type":"Point"}
}