{
  "type": "Feature",
  "properties": {
    "iso:country":"DE",
    "sg:address":"Irrgartenstr.",
    "sg:city":"Neunkirchen",
    "sg:phone":"+49 6821/22420",
    "sg:postcode":"66538",
    "sg:province":"Saarland",
    "wof:name":"Aldi",
    "wof:placetype":"venue"
},
  "geometry": {"coordinates":[7.1796112061,49.3432197571],"type":"Point"}
}