{
  "type": "Feature",
  "properties": {
    "iso:country":"DE",
    "sg:address":"Bahnhofstr. 101",
    "sg:city":"Nidderau",
    "sg:phone":"+49 6187/28130",
    "sg:postcode":"61130",
    "sg:province":"Hessen",
    "wof:name":"A. Nophut",
    "wof:placetype":"venue"
},
  "geometry": {"coordinates":[8.8826904297,50.2281303406],"type":"Point"}
}