{
  "type": "Feature",
  "properties": {
    "iso:country":"DE",
    "sg:address":"Alfred-Nobel-Str. 6",
    "sg:city":"Nauen",
    "sg:postcode":"14641",
    "sg:province":"Brandenburg",
    "wof:name":"Autohaus Nauen Verwaltungs Gmbh",
    "wof:placetype":"venue"
},
  "geometry": {"coordinates":[12.888665,52.596497],"type":"Point"}
}