{
  "type": "Feature",
  "properties": {
    "iso:country":"DE",
    "sg:address":"Barlachplatz 3",
    "sg:city":"Ratzeburg",
    "sg:phone":"+49 4541/3789",
    "sg:postcode":"23909",
    "sg:province":"Schleswig-Holstein",
    "wof:name":"Ernst-barlach-museum Altes Vaterhaus",
    "wof:placetype":"venue"
},
  "geometry": {"coordinates":[10.773264,53.698822],"type":"Point"}
}