{
  "type": "Feature",
  "properties": {
    "iso:country":"DE",
    "sg:address":"Koburger Str. 12",
    "sg:city":"Leipzig",
    "sg:phone":"+49 341/3913334",
    "sg:postcode":"04277",
    "sg:province":"Sachsen",
    "wof:name":"Wildparkgastst\u00e4tte",
    "wof:placetype":"venue"
},
  "geometry": {"coordinates":[12.3749103546,51.3127403259],"type":"Point"}
}