{
  "type": "Feature",
  "properties": {
    "iso:country":"DE",
    "sg:address":"Katharinental",
    "sg:city":"Dieterskirchen",
    "sg:phone":"+49 9672/1098",
    "sg:postcode":"92542",
    "sg:province":"Bayern",
    "wof:name":"G\u00e4stehaus L. Und Anny Meixner",
    "wof:placetype":"venue"
},
  "geometry": {"coordinates":[12.3923454285,49.389125824],"type":"Point"}
}