{
  "type": "Feature",
  "properties": {
    "iso:country":"DE",
    "sg:address":"Von-Richthofen-Str. 15",
    "sg:city":"Leipheim",
    "sg:phone":"+49 8221/7707",
    "sg:postcode":"89340",
    "sg:province":"Bayern",
    "wof:name":"Riedmann Schreibwaren B\u00fccher E. K.",
    "wof:placetype":"venue"
},
  "geometry": {"coordinates":[10.221663475,48.4489784241],"type":"Point"}
}