{
  "type": "Feature",
  "properties": {
    "iso:country":"DE",
    "sg:address":"Kokenhorststr. 4",
    "sg:city":"Burgwedel",
    "sg:postcode":"30938",
    "sg:province":"Niedersachsen",
    "wof:name":"Haweka Ag",
    "wof:placetype":"venue"
},
  "geometry": {"coordinates":[9.841745,52.489449],"type":"Point"}
}