{
  "type": "Feature",
  "properties": {
    "iso:country":"DE",
    "sg:address":"Horner Str. 5",
    "sg:city":"Bremerv\u00f6rde",
    "sg:phone":"+49 4761/6070",
    "sg:postcode":"27432",
    "sg:province":"Niedersachsen",
    "wof:name":"Dr. Med. Frank Illig",
    "wof:placetype":"venue"
},
  "geometry": {"coordinates":[9.1988182068,53.4738731384],"type":"Point"}
}