{
  "type": "Feature",
  "properties": {
    "iso:country":"DE",
    "sg:address":"Haselaischaftsweg 12",
    "sg:city":"Osnabr\u00fcck",
    "sg:phone":"+49 541/187862",
    "sg:postcode":"49088",
    "sg:province":"Niedersachsen",
    "wof:name":"Ernst Quest",
    "wof:placetype":"venue"
},
  "geometry": {"coordinates":[8.047225,52.292225],"type":"Point"}
}