{
  "type": "Feature",
  "properties": {
    "iso:country":"DE",
    "sg:address":"Kaiser-Wilhelm-Rg. 14",
    "sg:city":"M\u00fcnster",
    "sg:phone":"+49 4925/1933060",
    "sg:postcode":"48145",
    "sg:province":"Nordrhein-Westfalen",
    "wof:name":"Einkaufsges. Deutscher Getreidebrennereien (edg)",
    "wof:placetype":"venue"
},
  "geometry": {"coordinates":[7.646801,51.965092],"type":"Point"}
}