{
  "type": "Feature",
  "properties": {
    "iso:country":"DE",
    "sg:address":"August-Bebel-Str. 31",
    "sg:city":"Zschorlau",
    "sg:phone":"+49 3771/40459",
    "sg:postcode":"08321",
    "sg:province":"Sachsen",
    "wof:name":"Marien-apotheke E. Kfr.",
    "wof:placetype":"venue"
},
  "geometry": {"coordinates":[12.652113,50.569183],"type":"Point"}
}