{
  "type": "Feature",
  "properties": {
    "iso:country":"DE",
    "sg:address":"Rudolf-Breitscheid-Str. 13",
    "sg:city":"Luckenwalde",
    "sg:phone":"+49 3371/611483",
    "sg:postcode":"14943",
    "sg:province":"Brandenburg",
    "wof:name":"M & G Augenoptik",
    "wof:placetype":"venue"
},
  "geometry": {"coordinates":[13.1564149857,52.0835952759],"type":"Point"}
}