{
  "type": "Feature",
  "properties": {
    "iso:country":"DE",
    "sg:address":"Rodebachstr. 48",
    "sg:city":"Gangelt",
    "sg:phone":"+49 2454/6700",
    "sg:postcode":"52538",
    "sg:province":"Nordrhein-Westfalen",
    "wof:name":"Rudi Plum",
    "wof:placetype":"venue"
},
  "geometry": {"coordinates":[6.0331587791,50.9874839783],"type":"Point"}
}