{
  "type": "Feature",
  "properties": {
    "iso:country":"DE",
    "sg:address":"Hermann-Baxmann-Weg 4",
    "sg:city":"Hemmingen",
    "sg:postcode":"30966",
    "sg:province":"Niedersachsen",
    "wof:name":"Marianne Garbe Damenh\u00fcte",
    "wof:placetype":"venue"
},
  "geometry": {"coordinates":[9.7102251053,52.2812385559],"type":"Point"}
}