{
  "type": "Feature",
  "properties": {
    "iso:country":"DE",
    "sg:address":"Donaustr. 50",
    "sg:city":"R\u00fcsselsheim",
    "sg:postcode":"65428",
    "sg:province":"Hessen",
    "wof:name":"Hermann Sauer Gmbh",
    "wof:placetype":"venue"
},
  "geometry": {"coordinates":[8.419709,49.987934],"type":"Point"}
}