{
  "type": "Feature",
  "properties": {
    "iso:country":"DE",
    "sg:address":"Poststr. 26",
    "sg:city":"Trittau",
    "sg:postcode":"22946",
    "sg:province":"Schleswig-Holstein",
    "wof:name":"Sl Serviceline Gmbh",
    "wof:placetype":"venue"
},
  "geometry": {"coordinates":[10.41137,53.60759],"type":"Point"}
}