{
  "type": "Feature",
  "properties": {
    "iso:country":"DE",
    "sg:address":"Hohe Warte",
    "sg:city":"Delligsen",
    "sg:phone":"+49 5181/5033",
    "sg:postcode":"31073",
    "sg:province":"Niedersachsen",
    "wof:name":"Aka Hils Klinkerwerke Gmbh",
    "wof:placetype":"venue"
},
  "geometry": {"coordinates":[9.7449064255,51.9795608521],"type":"Point"}
}