{
  "type": "Feature",
  "properties": {
    "iso:country":"DE",
    "sg:address":"Grabenstr. 12",
    "sg:city":"Giengen",
    "sg:phone":"+49 7324/2249",
    "sg:postcode":"89537",
    "sg:province":"Baden-W\u00fcrttemberg",
    "wof:name":"Hmb Gmbh",
    "wof:placetype":"venue"
},
  "geometry": {"coordinates":[10.2013111115,48.5985717773],"type":"Point"}
}