{
  "type": "Feature",
  "properties": {
    "iso:country":"DE",
    "sg:address":"Am Alten Schlo\u00df 11",
    "sg:city":"Homburg",
    "sg:phone":"+49 6841/15814",
    "sg:postcode":"66424",
    "sg:province":"Saarland",
    "wof:name":"Klaus Jung",
    "wof:placetype":"venue"
},
  "geometry": {"coordinates":[7.3738069534,49.309589386],"type":"Point"}
}