{
  "type": "Feature",
  "properties": {
    "iso:country":"DE",
    "sg:address":"Oststr. 17",
    "sg:city":"Birken-Honigsessen",
    "sg:phone":"+49 2742/969989",
    "sg:postcode":"57587",
    "sg:province":"Rheinland-Pfalz",
    "wof:name":"D. Blum",
    "wof:placetype":"venue"
},
  "geometry": {"coordinates":[7.740593,50.811474],"type":"Point"}
}