{
  "type": "Feature",
  "properties": {
    "iso:country":"DE",
    "sg:address":"Freiherr-vom-Stein-Str. 24-26",
    "sg:city":"Frankfurt",
    "sg:postcode":"60323",
    "sg:province":"Hessen",
    "wof:name":"Z-management Beratungs- Und Verwaltungsgesellschaft Mbh",
    "wof:placetype":"venue"
},
  "geometry": {"coordinates":[8.664371,50.120453],"type":"Point"}
}