{
  "type": "Feature",
  "properties": {
    "iso:country":"DE",
    "sg:address":"B\u00e4rndorfer Str. 25",
    "sg:city":"Regen",
    "sg:phone":"+49 9921/1859",
    "sg:postcode":"94209",
    "sg:province":"Bayern",
    "wof:name":"Johann Kopp",
    "wof:placetype":"venue"
},
  "geometry": {"coordinates":[13.1236133575,48.978012085],"type":"Point"}
}