{
  "type": "Feature",
  "properties": {
    "iso:country":"DE",
    "sg:address":"Ludwigstr. 55",
    "sg:city":"Klingenberg",
    "sg:phone":"+49 9372/10275",
    "sg:postcode":"63911",
    "sg:province":"Bayern",
    "wof:name":"Reifen Erbacher Handels Gmbh",
    "wof:placetype":"venue"
},
  "geometry": {"coordinates":[9.1788883209,49.7873878479],"type":"Point"}
}