{
  "type": "Feature",
  "properties": {
    "iso:country":"DE",
    "sg:address":"Im Tal 10",
    "sg:city":"Eurasburg",
    "sg:phone":"+49 8208/278",
    "sg:postcode":"86495",
    "sg:province":"Bayern",
    "wof:name":"Heinrich H\u00e4felein",
    "wof:placetype":"venue"
},
  "geometry": {"coordinates":[11.081789,48.334541],"type":"Point"}
}