{
  "type": "Feature",
  "properties": {
    "iso:country":"DE",
    "sg:address":"Alter Kirchplatz 4",
    "sg:city":"Aalen",
    "sg:phone":"+49 7336/166755",
    "sg:postcode":"73430",
    "sg:province":"Baden-W\u00fcrttemberg",
    "wof:name":"Buecherwurm Homepage",
    "wof:placetype":"venue"
},
  "geometry": {"coordinates":[10.093379,48.837635],"type":"Point"}
}