{
  "type": "Feature",
  "properties": {
    "iso:country":"DE",
    "sg:address":"Leinstr. 31",
    "sg:city":"Neustadt",
    "sg:phone":"+49 5032/61948",
    "sg:postcode":"31535",
    "sg:province":"Niedersachsen",
    "wof:name":"Elife",
    "wof:placetype":"venue"
},
  "geometry": {"coordinates":[9.4620571136,52.5065956116],"type":"Point"}
}