{
  "type": "Feature",
  "properties": {
    "iso:country":"DE",
    "sg:address":"Hainstr. 14 a",
    "sg:city":"Forchheim",
    "sg:postcode":"91301",
    "sg:province":"Bayern",
    "wof:name":"Menat Transport Service Verwaltungs Gmbh",
    "wof:placetype":"venue"
},
  "geometry": {"coordinates":[11.0699710846,49.7210502625],"type":"Point"}
}