{
  "type": "Feature",
  "properties": {
    "iso:country":"DE",
    "sg:address":"Wilmersdorfer Str. 79",
    "sg:city":"Berlin",
    "sg:phone":"+49 30/3249011",
    "sg:postcode":"10629",
    "sg:province":"Berlin",
    "wof:name":"Braun Schlockermann Und Partner",
    "wof:placetype":"venue"
},
  "geometry": {"coordinates":[13.307645,52.502247],"type":"Point"}
}