{
  "type": "Feature",
  "properties": {
    "iso:country":"DE",
    "sg:address":"Twentmannstr. 15",
    "sg:city":"Essen",
    "sg:phone":"+49 201/297161",
    "sg:postcode":"45141",
    "sg:province":"Nordrhein-Westfalen",
    "wof:name":"Josef Pfeifer",
    "wof:placetype":"venue"
},
  "geometry": {"coordinates":[7.030465,51.476616],"type":"Point"}
}