{
  "type": "Feature",
  "properties": {
    "iso:country":"DE",
    "sg:address":"Mittelstr. 31",
    "sg:city":"Hohenlockstedt",
    "sg:postcode":"25551",
    "sg:province":"Schleswig-Holstein",
    "wof:name":"Broxo-system Gmbh",
    "wof:placetype":"venue"
},
  "geometry": {"coordinates":[9.61325,53.962666],"type":"Point"}
}