{
  "type": "Feature",
  "properties": {
    "iso:country":"DE",
    "sg:address":"Dohnsener Str. 16",
    "sg:city":"Dohnsen",
    "sg:phone":"+49 5533/2266",
    "sg:postcode":"37620",
    "sg:province":"Niedersachsen",
    "wof:name":"Reinhard Franke",
    "wof:placetype":"venue"
},
  "geometry": {"coordinates":[9.572475,52.007763],"type":"Point"}
}