{
  "type": "Feature",
  "properties": {
    "iso:country":"DE",
    "sg:address":"Marktplatz 6",
    "sg:city":"Diez",
    "sg:phone":"+49 6432/3106",
    "sg:postcode":"65582",
    "sg:province":"Rheinland-Pfalz",
    "wof:name":"Horst Blum",
    "wof:placetype":"venue"
},
  "geometry": {"coordinates":[8.0083179474,50.3709068298],"type":"Point"}
}