{
  "type": "Feature",
  "properties": {
    "iso:country":"DE",
    "sg:address":"Blumenstr. 14",
    "sg:city":"Augsburg",
    "sg:phone":"+49 821/518126",
    "sg:postcode":"86152",
    "sg:province":"Bayern",
    "wof:name":"W. Frisch",
    "wof:placetype":"venue"
},
  "geometry": {"coordinates":[10.882853,48.372997],"type":"Point"}
}