{
  "type": "Feature",
  "properties": {
    "iso:country":"DE",
    "sg:address":"Schlesierstr. 12",
    "sg:city":"Borken",
    "sg:phone":"+49 5682/1241",
    "sg:postcode":"34582",
    "sg:province":"Hessen",
    "wof:name":"Vereinsgemeinschaft Kleinenglis",
    "wof:placetype":"venue"
},
  "geometry": {"coordinates":[9.2586755753,51.0739021301],"type":"Point"}
}