{
  "type": "Feature",
  "properties": {
    "iso:country":"DE",
    "sg:address":"Schillerstr. 14",
    "sg:city":"Lage",
    "sg:phone":"+49 5232/66439",
    "sg:postcode":"32791",
    "sg:province":"Nordrhein-Westfalen",
    "wof:name":"Das Sch\u00f6ne M\u00f6bel Thomas W\u00fclker",
    "wof:placetype":"venue"
},
  "geometry": {"coordinates":[8.8008079529,51.9890670776],"type":"Point"}
}