{
  "type": "Feature",
  "properties": {
    "iso:country":"DE",
    "sg:address":"Priegerpromenade 3",
    "sg:city":"Bad Kreuznach",
    "sg:phone":"+49 671/41034",
    "sg:postcode":"55543",
    "sg:province":"Rheinland-Pfalz",
    "wof:name":"Kurpension Weinmann",
    "wof:placetype":"venue"
},
  "geometry": {"coordinates":[7.8513841629,49.8363418579],"type":"Point"}
}