{
  "type": "Feature",
  "properties": {
    "iso:country":"DE",
    "sg:address":"K\u00fclsheimstr. 28",
    "sg:city":"F\u00fcrth",
    "sg:phone":"+49 911/751708",
    "sg:postcode":"90768",
    "sg:province":"Bayern",
    "wof:name":"Christine Lindl Heilpraktiker",
    "wof:placetype":"venue"
},
  "geometry": {"coordinates":[10.9165058136,49.4905967712],"type":"Point"}
}