{
  "type": "Feature",
  "properties": {
    "iso:country":"DE",
    "sg:address":"Schulstr. 3",
    "sg:city":"Ohlstadt",
    "sg:postcode":"82441",
    "sg:province":"Bayern",
    "wof:name":"Fichtner-bau Gmbh",
    "wof:placetype":"venue"
},
  "geometry": {"coordinates":[11.234906,47.634888],"type":"Point"}
}