{
  "type": "Feature",
  "properties": {
    "iso:country":"DE",
    "sg:address":"Roeckstr. 13",
    "sg:city":"L\u00fcbeck",
    "sg:phone":"+49 451/36031",
    "sg:postcode":"23568",
    "sg:province":"Schleswig-Holstein",
    "wof:name":"Wolfgang Hollensteiner Rechtsanwalt Und Notar",
    "wof:placetype":"venue"
},
  "geometry": {"coordinates":[10.698674202,53.8759078979],"type":"Point"}
}