{
  "type": "Feature",
  "properties": {
    "iso:country":"DE",
    "sg:address":"Passower Str. 2",
    "sg:city":"Berlin",
    "sg:phone":"+49 30/9281144",
    "sg:postcode":"13057",
    "sg:province":"Berlin",
    "wof:name":"Dr. Ingolf Vogt",
    "wof:placetype":"venue"
},
  "geometry": {"coordinates":[13.5328826904,52.5661392212],"type":"Point"}
}