{
  "type": "Feature",
  "properties": {
    "iso:country":"DE",
    "sg:address":"Augustinerstr. 50",
    "sg:city":"Mainz",
    "sg:phone":"+49 6131/229426",
    "sg:postcode":"55116",
    "sg:province":"Rheinland-Pfalz",
    "wof:name":"Bruno Raimer",
    "wof:placetype":"venue"
},
  "geometry": {"coordinates":[8.2740573883,49.9973716736],"type":"Point"}
}