{
  "type": "Feature",
  "properties": {
    "iso:country":"DE",
    "sg:address":"Brunneng\u00e4ssle 1",
    "sg:city":"Aspach",
    "sg:phone":"+49 7191/23295",
    "sg:postcode":"71546",
    "sg:province":"Baden-W\u00fcrttemberg",
    "wof:name":"Vereinsgastst\u00e4tte Tsv Bad Rietenau E. V.",
    "wof:placetype":"venue"
},
  "geometry": {"coordinates":[9.4072904587,48.9882850647],"type":"Point"}
}