{
  "type": "Feature",
  "properties": {
    "iso:country":"DE",
    "sg:address":"Markt 21",
    "sg:city":"Dornburg",
    "sg:phone":"+49 36427/209",
    "sg:postcode":"07778",
    "sg:province":"Th\u00fcringen",
    "wof:name":"Stadtarchiv",
    "wof:placetype":"venue"
},
  "geometry": {"coordinates":[11.665384,51.006516],"type":"Point"}
}