{
  "type": "Feature",
  "properties": {
    "iso:country":"DE",
    "sg:address":"Theodor-Heublein-Str. 18",
    "sg:city":"Kulmbach",
    "sg:phone":"+49 9221/93161",
    "sg:postcode":"95326",
    "sg:province":"Bayern",
    "wof:name":"Gerber Und Nickles Immobilien Gmbh",
    "wof:placetype":"venue"
},
  "geometry": {"coordinates":[11.412273407,50.1085395813],"type":"Point"}
}