{
  "type": "Feature",
  "properties": {
    "iso:country":"DE",
    "sg:address":"Herrenstr. 5",
    "sg:city":"Bad Wurzach",
    "sg:phone":"+49 7564/2833",
    "sg:postcode":"88410",
    "sg:province":"Baden-W\u00fcrttemberg",
    "wof:name":"Helmut Hohl Inh. Volker Hohl",
    "wof:placetype":"venue"
},
  "geometry": {"coordinates":[9.894689,47.908409],"type":"Point"}
}