{
  "type": "Feature",
  "properties": {
    "iso:country":"DE",
    "sg:address":"Dr.-C.-Otto-Str. 2",
    "sg:city":"Bochum",
    "sg:phone":"+49 234/492330",
    "sg:postcode":"44879",
    "sg:province":"Nordrhein-Westfalen",
    "wof:name":"Praxis Dr. Med. Kubischik \u00c4rzte F\u00fcr Allgmeinmedizin",
    "wof:placetype":"venue"
},
  "geometry": {"coordinates":[7.1602711678,51.4257659912],"type":"Point"}
}