{
  "type": "Feature",
  "properties": {
    "iso:country":"DE",
    "sg:address":"An der Hornsm\u00fchle 6",
    "sg:city":"Brensbach",
    "sg:phone":"+49 6161/464",
    "sg:postcode":"64395",
    "sg:province":"Hessen",
    "wof:name":"Wilhelm H\u00f6nig",
    "wof:placetype":"venue"
},
  "geometry": {"coordinates":[8.872697,49.774876],"type":"Point"}
}