{
  "type": "Feature",
  "properties": {
    "iso:country":"DE",
    "sg:address":"Ulhaus 63",
    "sg:city":"Langerwehe",
    "sg:phone":"+49 2423/2031",
    "sg:postcode":"52379",
    "sg:province":"Nordrhein-Westfalen",
    "wof:name":"Philipp Kutsch Gmbh",
    "wof:placetype":"venue"
},
  "geometry": {"coordinates":[6.3527398109,50.8188400269],"type":"Point"}
}