{
  "type": "Feature",
  "properties": {
    "iso:country":"DE",
    "sg:address":"Maisenbachsiedlung 4",
    "sg:city":"K\u00fclsheim",
    "sg:phone":"+49 9345/367",
    "sg:postcode":"97900",
    "sg:province":"Baden-W\u00fcrttemberg",
    "wof:name":"Georg Seubert",
    "wof:placetype":"venue"
},
  "geometry": {"coordinates":[9.59414,49.674171],"type":"Point"}
}