{
  "type": "Feature",
  "properties": {
    "iso:country":"DE",
    "sg:address":"Benediktusstr. 17",
    "sg:city":"Aachen",
    "sg:phone":"+49 241/520359",
    "sg:postcode":"52078",
    "sg:province":"Nordrhein-Westfalen",
    "wof:name":"Horst Drewanz Architekt",
    "wof:placetype":"venue"
},
  "geometry": {"coordinates":[6.16213,50.742828],"type":"Point"}
}