{
  "type": "Feature",
  "properties": {
    "iso:country":"DE",
    "sg:address":"Im Weingarten 3",
    "sg:city":"Bad Salzuflen",
    "sg:phone":"+49 5222/797938",
    "sg:postcode":"32107",
    "sg:province":"Nordrhein-Westfalen",
    "wof:name":"Strasas & Sommer Gmbh",
    "wof:placetype":"venue"
},
  "geometry": {"coordinates":[8.744092,52.060181],"type":"Point"}
}