{
  "type": "Feature",
  "properties": {
    "iso:country":"DE",
    "sg:address":"Cranachstr. 88",
    "sg:city":"Wolfenb\u00fcttel",
    "sg:phone":"+49 5331/65327",
    "sg:postcode":"38300",
    "sg:province":"Niedersachsen",
    "wof:name":"I. Borwik",
    "wof:placetype":"venue"
},
  "geometry": {"coordinates":[10.560425,52.150631],"type":"Point"}
}