{
  "type": "Feature",
  "properties": {
    "iso:country":"DE",
    "sg:address":"Am Ginsterberg",
    "sg:city":"Alsdorf",
    "sg:phone":"+49 2404/6088",
    "sg:postcode":"52477",
    "sg:province":"Nordrhein-Westfalen",
    "wof:name":"Vama Vereinigte Asphaltmisch- Werke Aachen Gmbh & Co. Kg",
    "wof:placetype":"venue"
},
  "geometry": {"coordinates":[6.1878919601,50.8495826721],"type":"Point"}
}