{
  "type": "Feature",
  "properties": {
    "iso:country":"DE",
    "sg:address":"Poststr. 2",
    "sg:city":"Detmold",
    "sg:phone":"+49 5231/29838",
    "sg:postcode":"32758",
    "sg:province":"Nordrhein-Westfalen",
    "wof:name":"Heilmann Inh. Thomas Ro\u00df",
    "wof:placetype":"venue"
},
  "geometry": {"coordinates":[8.88767,51.958969],"type":"Point"}
}