{
  "type": "Feature",
  "properties": {
    "iso:country":"DE",
    "sg:address":"Sebastian-Kneipp-Str. 18",
    "sg:city":"St\u00fctzerbach",
    "sg:phone":"+49 36784/50277",
    "sg:postcode":"98714",
    "sg:province":"Th\u00fcringen",
    "wof:name":"Goethehaus",
    "wof:placetype":"venue"
},
  "geometry": {"coordinates":[10.867648,50.63588],"type":"Point"}
}