{
  "type": "Feature",
  "properties": {
    "iso:country":"DE",
    "sg:address":"Dorfstr. 34",
    "sg:city":"Meerbusch",
    "sg:phone":"+49 2132/93330",
    "sg:postcode":"40667",
    "sg:province":"Nordrhein-Westfalen",
    "wof:name":"Dirk Becker Immobilien Gmbh",
    "wof:placetype":"venue"
},
  "geometry": {"coordinates":[6.6944570541,51.2529983521],"type":"Point"}
}