{
  "type": "Feature",
  "properties": {
    "iso:country":"DE",
    "sg:address":"Neuenhof 8",
    "sg:city":"Solingen",
    "sg:phone":"+49 212/2471064",
    "sg:postcode":"42657",
    "sg:province":"Nordrhein-Westfalen",
    "wof:name":"G. Van Der Felz",
    "wof:placetype":"venue"
},
  "geometry": {"coordinates":[7.0614318848,51.1519851685],"type":"Point"}
}