{
  "type": "Feature",
  "properties": {
    "iso:country":"DE",
    "sg:address":"Billwerder Ring 3",
    "sg:city":"Hamburg",
    "sg:phone":"+49 40/7349053",
    "sg:postcode":"21035",
    "sg:province":"Hamburg",
    "wof:name":"Pfensig & Wendorf Maschinenbau Und",
    "wof:placetype":"venue"
},
  "geometry": {"coordinates":[10.117956,53.495785],"type":"Point"}
}