{
  "type": "Feature",
  "properties": {
    "iso:country":"DE",
    "sg:address":"Sch\u00fctzenstr. 21",
    "sg:city":"Geseke",
    "sg:phone":"+49 2942/6044",
    "sg:postcode":"59590",
    "sg:province":"Nordrhein-Westfalen",
    "wof:name":"B\u00e4uerliche Bezugs- Und Absatzgenossenschaft",
    "wof:placetype":"venue"
},
  "geometry": {"coordinates":[8.4387922287,51.6349601746],"type":"Point"}
}