{
  "type": "Feature",
  "properties": {
    "iso:country":"DE",
    "sg:address":"Beckendorfstr. 8",
    "sg:city":"Bielefeld",
    "sg:postcode":"33739",
    "sg:province":"Nordrhein-Westfalen",
    "wof:name":"Extra",
    "wof:placetype":"venue"
},
  "geometry": {"coordinates":[8.479391098,52.0805358887],"type":"Point"}
}