{
  "type": "Feature",
  "properties": {
    "iso:country":"DE",
    "sg:address":"Am Bostenberg 8",
    "sg:city":"Parchim",
    "sg:phone":"+49 3871/442734",
    "sg:postcode":"19370",
    "sg:province":"Mecklenburg-Vorpommern",
    "wof:name":"Hans-joachim Sch\u00fctz",
    "wof:placetype":"venue"
},
  "geometry": {"coordinates":[11.831327,53.426552],"type":"Point"}
}