{
  "type": "Feature",
  "properties": {
    "iso:country":"DE",
    "sg:address":"Elmeloher Str. 93",
    "sg:city":"Ganderkesee",
    "sg:phone":"+49 4221/83111",
    "sg:postcode":"27777",
    "sg:province":"Niedersachsen",
    "wof:name":"Siltek Dental-labor Grundmann Gmbh",
    "wof:placetype":"venue"
},
  "geometry": {"coordinates":[8.5756502151,53.0658912659],"type":"Point"}
}