{
  "type": "Feature",
  "properties": {
    "iso:country":"DE",
    "sg:address":"Kirchstr. 45",
    "sg:city":"Freiburg",
    "sg:phone":"+49 761/71871",
    "sg:postcode":"79100",
    "sg:province":"Baden-W\u00fcrttemberg",
    "wof:name":"Lipps Ohg",
    "wof:placetype":"venue"
},
  "geometry": {"coordinates":[7.846452,47.985523],"type":"Point"}
}