{
  "type": "Feature",
  "properties": {
    "iso:country":"DE",
    "sg:address":"Kapuzinerstr. 4",
    "sg:city":"Saarlouis",
    "sg:phone":"+49 6831/160",
    "sg:postcode":"66740",
    "sg:province":"Saarland",
    "wof:name":"Krankenhausvollapotheke Der St.-elisabeth-klinik",
    "wof:placetype":"venue"
},
  "geometry": {"coordinates":[6.756318,49.31535],"type":"Point"}
}