{
  "type": "Feature",
  "properties": {
    "iso:country":"DE",
    "sg:address":"Fiedelerplatz 4",
    "sg:city":"Hannover",
    "sg:phone":"+49 511/8436474",
    "sg:postcode":"30519",
    "sg:province":"Niedersachsen",
    "wof:name":"Schmelz Gmbh & Co. Kg",
    "wof:placetype":"venue"
},
  "geometry": {"coordinates":[9.7641630173,52.3398780823],"type":"Point"}
}