{
  "type": "Feature",
  "properties": {
    "iso:country":"DE",
    "sg:address":"M\u00fcnsterstr. 7",
    "sg:city":"Castrop-Rauxel",
    "sg:phone":"+49 2305/358130",
    "sg:postcode":"44575",
    "sg:province":"Nordrhein-Westfalen",
    "wof:name":"Brockp\u00e4hler Und Hoffmann Rechtsanw\u00e4lte",
    "wof:placetype":"venue"
},
  "geometry": {"coordinates":[7.3102059364,51.5488777161],"type":"Point"}
}