{
  "type": "Feature",
  "properties": {
    "iso:country":"DE",
    "sg:address":"Markenstr. 22-24",
    "sg:city":"Gelsenkirchen",
    "sg:phone":"+49 209/9552117",
    "sg:postcode":"45899",
    "sg:province":"Nordrhein-Westfalen",
    "wof:name":"Plus",
    "wof:placetype":"venue"
},
  "geometry": {"coordinates":[7.0254359245,51.5310173035],"type":"Point"}
}