{
  "type": "Feature",
  "properties": {
    "iso:country":"DE",
    "sg:address":"Altendorf 6",
    "sg:city":"Boizenburg",
    "sg:phone":"+49 38847/53024",
    "sg:postcode":"19258",
    "sg:province":"Mecklenburg-Vorpommern",
    "wof:name":"C. Karsten Masseur",
    "wof:placetype":"venue"
},
  "geometry": {"coordinates":[10.724856,53.372047],"type":"Point"}
}