{
  "type": "Feature",
  "properties": {
    "iso:country":"DE",
    "sg:address":"Riphausstr.",
    "sg:city":"Waltrop",
    "sg:phone":"+49 2309/930208",
    "sg:postcode":"45731",
    "sg:province":"Nordrhein-Westfalen",
    "wof:name":"Heimatmuseum Waltrop",
    "wof:placetype":"venue"
},
  "geometry": {"coordinates":[7.412255,51.625534],"type":"Point"}
}