{
  "type": "Feature",
  "properties": {
    "iso:country":"DE",
    "sg:address":"Industriestr. 2",
    "sg:city":"Altenm\u00fcnster",
    "sg:phone":"+49 8295/1094",
    "sg:postcode":"86450",
    "sg:province":"Bayern",
    "wof:name":"Transportbeton Henn- Hofen Gmbh & Co. Kg",
    "wof:placetype":"venue"
},
  "geometry": {"coordinates":[10.591794014,48.4784355164],"type":"Point"}
}