{
  "type": "Feature",
  "properties": {
    "iso:country":"DE",
    "sg:address":"R\u00fcdickenstr. 14",
    "sg:city":"Berlin",
    "sg:phone":"+49 30/9245007",
    "sg:postcode":"13053",
    "sg:province":"Berlin",
    "wof:name":"Hans-g. Schellheimer Heilpraktiker",
    "wof:placetype":"venue"
},
  "geometry": {"coordinates":[13.5061941147,52.5618896484],"type":"Point"}
}