{
  "type": "Feature",
  "properties": {
    "iso:country":"DE",
    "sg:address":"Kniestedter Str. 54",
    "sg:city":"Salzgitter",
    "sg:phone":"+49 5341/393500",
    "sg:postcode":"38259",
    "sg:province":"Niedersachsen",
    "wof:name":"Trios-second- Hand- Shop",
    "wof:placetype":"venue"
},
  "geometry": {"coordinates":[10.372184,52.054394],"type":"Point"}
}