{
  "type": "Feature",
  "properties": {
    "iso:country":"DE",
    "sg:address":"Hauptstr. 3",
    "sg:city":"Burladingen",
    "sg:phone":"+49 7475/561",
    "sg:postcode":"72393",
    "sg:province":"Baden-W\u00fcrttemberg",
    "wof:name":"Helmut Rieber",
    "wof:placetype":"venue"
},
  "geometry": {"coordinates":[9.110089,48.289417],"type":"Point"}
}