{
  "type": "Feature",
  "properties": {
    "iso:country":"DE",
    "sg:address":"St.-Jobser-Str. 47a",
    "sg:city":"W\u00fcrselen",
    "sg:phone":"+49 2405/46950",
    "sg:postcode":"52146",
    "sg:province":"Nordrhein-Westfalen",
    "wof:name":"Steinhauer Elektromaschinen Gmbh",
    "wof:placetype":"venue"
},
  "geometry": {"coordinates":[6.158351,50.807404],"type":"Point"}
}