{
  "type": "Feature",
  "properties": {
    "iso:country":"DE",
    "sg:address":"Waldstr. 10",
    "sg:city":"Heistenbach",
    "sg:postcode":"65558",
    "sg:province":"Rheinland-Pfalz",
    "wof:name":"Up Consult Gmbh",
    "wof:placetype":"venue"
},
  "geometry": {"coordinates":[7.982521,50.381626],"type":"Point"}
}