{
  "type": "Feature",
  "properties": {
    "iso:country":"DE",
    "sg:address":"Chamissostr. 17",
    "sg:city":"Hameln",
    "sg:phone":"+49 5151/941395",
    "sg:postcode":"31785",
    "sg:province":"Niedersachsen",
    "wof:name":"Hermann J. Tellers",
    "wof:placetype":"venue"
},
  "geometry": {"coordinates":[9.355219841,52.1124649048],"type":"Point"}
}