{
  "type": "Feature",
  "properties": {
    "iso:country":"DE",
    "sg:address":"Lindenstr. 3",
    "sg:city":"Renningen",
    "sg:phone":"+49 7159/920676",
    "sg:postcode":"71272",
    "sg:province":"Baden-W\u00fcrttemberg",
    "wof:name":"M\u00fcller Und Orlishausen",
    "wof:placetype":"venue"
},
  "geometry": {"coordinates":[8.9352273941,48.7703971863],"type":"Point"}
}