{
  "type": "Feature",
  "properties": {
    "iso:country":"DE",
    "sg:address":"Waisenhausstr. 45",
    "sg:city":"M\u00fcnchen",
    "sg:phone":"+49 89/1574063",
    "sg:postcode":"80637",
    "sg:province":"Bayern",
    "wof:name":"Comdata Computer Und Computer- Zubeh\u00f6r Vertriebsges. Mbh",
    "wof:placetype":"venue"
},
  "geometry": {"coordinates":[11.5289316177,48.1626815796],"type":"Point"}
}