{
  "type": "Feature",
  "properties": {
    "iso:country":"DE",
    "sg:address":"Am Markt 12",
    "sg:city":"Sittensen",
    "sg:phone":"+49 4282/1025",
    "sg:postcode":"27419",
    "sg:province":"Niedersachsen",
    "wof:name":"Gerda Barthel Immobilienmaklerin",
    "wof:placetype":"venue"
},
  "geometry": {"coordinates":[9.5046272278,53.2768440247],"type":"Point"}
}