{
  "type": "Feature",
  "properties": {
    "iso:country":"DE",
    "sg:address":"Dobberziner Str. 65a",
    "sg:city":"Perleberg",
    "sg:phone":"+49 3876/613088",
    "sg:postcode":"19348",
    "sg:province":"Brandenburg",
    "wof:name":"Wohnungsgenossenschaft Perleberg Eg",
    "wof:placetype":"venue"
},
  "geometry": {"coordinates":[11.8685188293,53.0701675415],"type":"Point"}
}