{
  "type": "Feature",
  "properties": {
    "iso:country":"DE",
    "sg:address":"Markt 6",
    "sg:city":"Bad M\u00fcnstereifel",
    "sg:phone":"+49 2253/6674",
    "sg:postcode":"53902",
    "sg:province":"Nordrhein-Westfalen",
    "wof:name":"Buchhandlung Schulte Inh. Brigitte Crump-schoo\u00df",
    "wof:placetype":"venue"
},
  "geometry": {"coordinates":[6.7633671761,50.5536956787],"type":"Point"}
}