{
  "type": "Feature",
  "properties": {
    "iso:country":"DE",
    "sg:address":"Klarenbachstr. 1-4",
    "sg:city":"Berlin",
    "sg:phone":"+49 30/78704006",
    "sg:postcode":"10553",
    "sg:province":"Berlin",
    "wof:name":"Meta Elektronik Gmbh",
    "wof:placetype":"venue"
},
  "geometry": {"coordinates":[13.3180713654,52.5264625549],"type":"Point"}
}