{
  "type": "Feature",
  "properties": {
    "iso:country":"DE",
    "sg:address":"Hammer-Tannen-Str. 24",
    "sg:city":"Hasel\u00fcnne",
    "sg:phone":"+49 5961/6765",
    "sg:postcode":"49740",
    "sg:province":"Niedersachsen",
    "wof:name":"R. Und M. Schulte",
    "wof:placetype":"venue"
},
  "geometry": {"coordinates":[7.4642491341,52.6597938538],"type":"Point"}
}