{
  "type": "Feature",
  "properties": {
    "iso:country":"DE",
    "sg:city":"Schlammersdorf",
    "sg:phone":"+49 9205/375",
    "sg:postcode":"95519",
    "sg:province":"Bayern",
    "wof:name":"Sparkasse",
    "wof:placetype":"venue"
},
  "geometry": {"coordinates":[11.735355,49.802059],"type":"Point"}
}