{
  "type": "Feature",
  "properties": {
    "iso:country":"DE",
    "sg:address":"88167",
    "sg:city":"Stiefenhofen",
    "sg:postcode":"88167",
    "sg:province":"Bayern",
    "wof:name":"Raiffeisenbank Stiefenhofen Eg",
    "wof:placetype":"venue"
},
  "geometry": {"coordinates":[10.003407,47.59243],"type":"Point"}
}