{
  "type": "Feature",
  "properties": {
    "iso:country":"DE",
    "sg:address":"Schlachte 41",
    "sg:city":"Bremen",
    "sg:phone":"+49 421/201080",
    "sg:postcode":"28195",
    "sg:province":"Bremen",
    "wof:name":"\u00c4rzte Und Apotheker Immobiliengesellschaft",
    "wof:placetype":"venue"
},
  "geometry": {"coordinates":[8.79774189,53.0790023804],"type":"Point"}
}