{
  "type": "Feature",
  "properties": {
    "iso:country":"DE",
    "sg:address":"Schauener Weg 8",
    "sg:city":"Veckenstedt",
    "sg:phone":"+49 39451/879",
    "sg:postcode":"38871",
    "sg:province":"Sachsen-Anhalt",
    "wof:name":"J\u00fcrgen Brasche",
    "wof:placetype":"venue"
},
  "geometry": {"coordinates":[10.727615,51.903912],"type":"Point"}
}