{
  "type": "Feature",
  "properties": {
    "iso:country":"DE",
    "sg:address":"R\u00f6merweg 2",
    "sg:city":"Schlangen",
    "sg:phone":"+49 5252/82009",
    "sg:postcode":"33189",
    "sg:province":"Nordrhein-Westfalen",
    "wof:name":"Arthur Schr\u00f6der Steuerberater",
    "wof:placetype":"venue"
},
  "geometry": {"coordinates":[8.8364667892,51.8379249573],"type":"Point"}
}