{
  "type": "Feature",
  "properties": {
    "iso:country":"DE",
    "sg:address":"Gasthausstr. 5",
    "sg:city":"Xanten",
    "sg:phone":"+49 2801/77600",
    "sg:postcode":"46509",
    "sg:province":"Nordrhein-Westfalen",
    "wof:name":"Pec Bau Projekt- Entwicklungs- Center Gmbh",
    "wof:placetype":"venue"
},
  "geometry": {"coordinates":[6.454008,51.66037],"type":"Point"}
}