{
  "type": "Feature",
  "properties": {
    "iso:country":"DE",
    "sg:address":"Herretshofer Str. 8",
    "sg:city":"Kirchhaslach",
    "sg:phone":"+49 8333/2953",
    "sg:postcode":"87755",
    "sg:province":"Bayern",
    "wof:name":"Mathias G\u00f6ttinger",
    "wof:placetype":"venue"
},
  "geometry": {"coordinates":[10.31059,48.150936],"type":"Point"}
}