{
  "type": "Feature",
  "properties": {
    "iso:country":"DE",
    "sg:address":"Herrnstr. 10",
    "sg:city":"Moosburg",
    "sg:phone":"+49 8761/70550",
    "sg:postcode":"85368",
    "sg:province":"Bayern",
    "wof:name":"Parf\u00fcmerie Aurel Howerka",
    "wof:placetype":"venue"
},
  "geometry": {"coordinates":[11.936375,48.49445],"type":"Point"}
}