{
  "type": "Feature",
  "properties": {
    "iso:country":"DE",
    "sg:address":"Bindestr. 7",
    "sg:city":"L\u00fcnen",
    "sg:phone":"+49 4923/0648775",
    "sg:postcode":"44532",
    "sg:province":"Nordrhein-Westfalen",
    "wof:name":"Element- Lichtwerbung Gmbh",
    "wof:placetype":"venue"
},
  "geometry": {"coordinates":[7.5519580841,51.6003799438],"type":"Point"}
}