{
  "type": "Feature",
  "properties": {
    "iso:country":"DE",
    "sg:address":"Stra\u00dfe der Einheit 76",
    "sg:city":"Jatznick",
    "sg:phone":"+49 39741/80558",
    "sg:postcode":"17309",
    "sg:province":"Mecklenburg-Vorpommern",
    "wof:name":"Jatznicker Hof",
    "wof:placetype":"venue"
},
  "geometry": {"coordinates":[13.9381532669,53.582824707],"type":"Point"}
}