{
  "type": "Feature",
  "properties": {
    "iso:country":"DE",
    "sg:address":"Annenstr. 102",
    "sg:city":"Witten",
    "sg:phone":"+49 2302/699985",
    "sg:postcode":"58453",
    "sg:province":"Nordrhein-Westfalen",
    "wof:name":"G\u00fcrb\u00fcz Tursun Architekt",
    "wof:placetype":"venue"
},
  "geometry": {"coordinates":[7.366529,51.444244],"type":"Point"}
}