{
  "type": "Feature",
  "properties": {
    "iso:country":"DE",
    "sg:address":"Karl-Marx-Str. 17",
    "sg:city":"Braunsdorf",
    "sg:postcode":"01737",
    "sg:province":"Sachsen",
    "wof:name":"Christian Matzke",
    "wof:placetype":"venue"
},
  "geometry": {"coordinates":[13.013206,50.867123],"type":"Point"}
}