{
  "type": "Feature",
  "properties": {
    "iso:country":"DE",
    "sg:address":"Veestherrnweg 12",
    "sg:city":"Munster",
    "sg:phone":"+49 5192/99180",
    "sg:postcode":"29633",
    "sg:province":"Niedersachsen",
    "wof:name":"Rolf Arlt",
    "wof:placetype":"venue"
},
  "geometry": {"coordinates":[10.0859508514,52.9874763489],"type":"Point"}
}