{
  "type": "Feature",
  "properties": {
    "iso:country":"DE",
    "sg:address":"Hechtseestr. 6",
    "sg:city":"Rosenheim",
    "sg:phone":"+49 8031/33562",
    "sg:postcode":"83022",
    "sg:province":"Bayern",
    "wof:name":"Reinigung Ehrenb\u00f6ck Gmbh",
    "wof:placetype":"venue"
},
  "geometry": {"coordinates":[12.1333665848,47.8474845886],"type":"Point"}
}