{
  "type": "Feature",
  "properties": {
    "iso:country":"DE",
    "sg:address":"Speyerer Str. 105",
    "sg:city":"Harthausen",
    "sg:phone":"+49 6344/939703",
    "sg:postcode":"67376",
    "sg:province":"Rheinland-Pfalz",
    "wof:name":"M.s.t. Maschinenbau Und Service-team Gmbh",
    "wof:placetype":"venue"
},
  "geometry": {"coordinates":[8.351393,49.298485],"type":"Point"}
}