{
  "type": "Feature",
  "properties": {
    "iso:country":"DE",
    "sg:address":"Rosentwiete 34",
    "sg:city":"Brande-H\u00f6rnerkirchen",
    "sg:phone":"+49 4127/456",
    "sg:postcode":"25364",
    "sg:province":"Schleswig-Holstein",
    "wof:name":"Peter Und E. Leisching Ohg",
    "wof:placetype":"venue"
},
  "geometry": {"coordinates":[9.7046670914,53.8508758545],"type":"Point"}
}