{
  "type": "Feature",
  "properties": {
    "iso:country":"DE",
    "sg:address":"Josef-Schregel-Str. 64 d",
    "sg:city":"D\u00fcren",
    "sg:phone":"+49 2421/41702",
    "sg:postcode":"52349",
    "sg:province":"Nordrhein-Westfalen",
    "wof:name":"Peter Thelen",
    "wof:placetype":"venue"
},
  "geometry": {"coordinates":[6.4802818298,50.8084754944],"type":"Point"}
}