{
  "type": "Feature",
  "properties": {
    "iso:country":"DE",
    "sg:address":"Dammer Feld 12",
    "sg:city":"Engelskirchen",
    "sg:phone":"+49 2263/951087",
    "sg:postcode":"51766",
    "sg:province":"Nordrhein-Westfalen",
    "wof:name":"Implantate Dental Systeme Wagner",
    "wof:placetype":"venue"
},
  "geometry": {"coordinates":[7.445124,51.001522],"type":"Point"}
}