{
  "type": "Feature",
  "properties": {
    "iso:country":"DE",
    "sg:address":"Rathausplatz 7",
    "sg:city":"Elsfleth",
    "sg:phone":"+49 4404/2086",
    "sg:postcode":"26931",
    "sg:province":"Niedersachsen",
    "wof:name":"Transcon Beteiligungsges. Mbh",
    "wof:placetype":"venue"
},
  "geometry": {"coordinates":[8.464111,53.235676],"type":"Point"}
}