{
  "type": "Feature",
  "properties": {
    "iso:country":"DE",
    "sg:address":"Brunnenstr. 21",
    "sg:city":"L\u00fcbben",
    "sg:postcode":"15907",
    "sg:province":"Brandenburg",
    "wof:name":"Modehaus Tessou",
    "wof:placetype":"venue"
},
  "geometry": {"coordinates":[13.87234,51.93903],"type":"Point"}
}