{
  "type": "Feature",
  "properties": {
    "iso:country":"DE",
    "sg:address":"Am Markt 7",
    "sg:city":"Castrop-Rauxel",
    "sg:phone":"+49 2305/25011",
    "sg:postcode":"44575",
    "sg:province":"Nordrhein-Westfalen",
    "wof:name":"Blumen-risse Gmbh & Co. Kg",
    "wof:placetype":"venue"
},
  "geometry": {"coordinates":[7.313623,51.552391],"type":"Point"}
}