{
  "type": "Feature",
  "properties": {
    "iso:country":"DE",
    "sg:address":"Poststr. 8",
    "sg:city":"Fallingbostel",
    "sg:phone":"+49 5163/400",
    "sg:postcode":"29683",
    "sg:province":"Niedersachsen",
    "wof:name":"Konrad Narjes",
    "wof:placetype":"venue"
},
  "geometry": {"coordinates":[9.769136,52.899239],"type":"Point"}
}