{
  "type": "Feature",
  "properties": {
    "iso:country":"DE",
    "sg:address":"Wolfsittard 113",
    "sg:city":"M\u00f6nchengladbach",
    "sg:postcode":"41179",
    "sg:province":"Nordrhein-Westfalen",
    "wof:name":"Thomas Jansen",
    "wof:placetype":"venue"
},
  "geometry": {"coordinates":[6.3718547821,51.1754570007],"type":"Point"}
}