{
  "type": "Feature",
  "properties": {
    "iso:country":"DE",
    "sg:address":"Hinterer M\u00fchlweg 21",
    "sg:city":"Regensburg",
    "sg:phone":"+49 941/71192",
    "sg:postcode":"93053",
    "sg:province":"Bayern",
    "wof:name":"Franz Bauer",
    "wof:placetype":"venue"
},
  "geometry": {"coordinates":[12.1162605286,48.999671936],"type":"Point"}
}