{
  "type": "Feature",
  "properties": {
    "iso:country":"DE",
    "sg:address":"Heumadwiesenweg 9",
    "sg:city":"Ebersbach",
    "sg:phone":"+49 7163/2455",
    "sg:postcode":"73061",
    "sg:province":"Baden-W\u00fcrttemberg",
    "wof:name":"Hans-joachim Damrau Architekt",
    "wof:placetype":"venue"
},
  "geometry": {"coordinates":[9.510071,48.729958],"type":"Point"}
}