{
  "type": "Feature",
  "properties": {
    "iso:country":"DE",
    "sg:address":"Buchenweg 2",
    "sg:city":"Wadersloh",
    "sg:phone":"+49 2520/94405",
    "sg:postcode":"59329",
    "sg:province":"Nordrhein-Westfalen",
    "wof:name":"Bredenh\u00f6ller Landtechnik Ohg",
    "wof:placetype":"venue"
},
  "geometry": {"coordinates":[8.148929,51.758427],"type":"Point"}
}