{
  "type": "Feature",
  "properties": {
    "iso:country":"DE",
    "sg:address":"Wiesbadener Str. 15",
    "sg:city":"Limburg",
    "sg:postcode":"65549",
    "sg:province":"Hessen",
    "wof:name":"Ifab Technik Ggmbh",
    "wof:placetype":"venue"
},
  "geometry": {"coordinates":[8.077921,50.375763],"type":"Point"}
}