{
  "type": "Feature",
  "properties": {
    "iso:country":"DE",
    "sg:address":"Regensburger Str. 8",
    "sg:city":"W\u00f6rth",
    "sg:phone":"+49 9482/1558",
    "sg:postcode":"93086",
    "sg:province":"Bayern",
    "wof:name":"Martin Eicher Notar",
    "wof:placetype":"venue"
},
  "geometry": {"coordinates":[12.3987693787,49.0001220703],"type":"Point"}
}