{
  "type": "Feature",
  "properties": {
    "iso:country":"DE",
    "sg:address":"Ernst-Th\u00e4lmann-Str. 58",
    "sg:city":"Br\u00fcck",
    "sg:phone":"+49 33844/422",
    "sg:postcode":"14822",
    "sg:province":"Brandenburg",
    "wof:name":"M\u00e4rkische Apotheke Br\u00fcck Inh. Kirk Berger",
    "wof:placetype":"venue"
},
  "geometry": {"coordinates":[12.761205,52.194118],"type":"Point"}
}