{
  "type": "Feature",
  "properties": {
    "iso:country":"DE",
    "sg:address":"Schafheitlinstr. 17",
    "sg:city":"Weingarten",
    "sg:phone":"+49 751/43253",
    "sg:postcode":"88250",
    "sg:province":"Baden-W\u00fcrttemberg",
    "wof:name":"Krebs",
    "wof:placetype":"venue"
},
  "geometry": {"coordinates":[9.635031,47.810677],"type":"Point"}
}