{
  "type": "Feature",
  "properties": {
    "iso:country":"DE",
    "sg:address":"Asterweg 46",
    "sg:city":"Gie\u00dfen",
    "sg:phone":"+49 641/389759",
    "sg:postcode":"35390",
    "sg:province":"Hessen",
    "wof:name":"Istanbul",
    "wof:placetype":"venue"
},
  "geometry": {"coordinates":[8.6756162643,50.5917167664],"type":"Point"}
}