{
  "type": "Feature",
  "properties": {
    "iso:country":"DE",
    "sg:address":"Am Rathaus 13b",
    "sg:city":"Erlensee",
    "sg:postcode":"63526",
    "sg:province":"Hessen",
    "wof:name":"Shk Service Ggmbh",
    "wof:placetype":"venue"
},
  "geometry": {"coordinates":[8.98203,50.164383],"type":"Point"}
}