{
  "type": "Feature",
  "properties": {
    "iso:country":"DE",
    "sg:address":"Sollner Str. 15",
    "sg:city":"M\u00fcnchen",
    "sg:phone":"+49 89/7911795",
    "sg:postcode":"81479",
    "sg:province":"Bayern",
    "wof:name":"Pvs Verm\u00f6gensverwaltungs- Gmbh",
    "wof:placetype":"venue"
},
  "geometry": {"coordinates":[11.5277471542,48.0841178894],"type":"Point"}
}