{
  "type": "Feature",
  "properties": {
    "iso:country":"DE",
    "sg:address":"Kummersberg 8",
    "sg:city":"Zittau",
    "sg:phone":"+49 3583/510717",
    "sg:postcode":"02763",
    "sg:province":"Sachsen",
    "wof:name":"Hotel Restaurant Bergschl\u00f6\u00dfchen",
    "wof:placetype":"venue"
},
  "geometry": {"coordinates":[14.7925834656,50.9015693665],"type":"Point"}
}