{
  "type": "Feature",
  "properties": {
    "iso:country":"DE",
    "sg:address":"Ludwigshafener Str. 49",
    "sg:city":"Neuhofen",
    "sg:phone":"+49 6236/55739",
    "sg:postcode":"67141",
    "sg:province":"Rheinland-Pfalz",
    "wof:name":"Pinte Bistro",
    "wof:placetype":"venue"
},
  "geometry": {"coordinates":[8.4256744385,49.4243583679],"type":"Point"}
}