{
  "type": "Feature",
  "properties": {
    "iso:country":"DE",
    "sg:address":"Hauptstr. 27",
    "sg:city":"Spreenhagen",
    "sg:phone":"+49 33633/216",
    "sg:postcode":"15528",
    "sg:province":"Brandenburg",
    "wof:name":"Gasthaus Paesch",
    "wof:placetype":"venue"
},
  "geometry": {"coordinates":[13.8780384064,52.3406181335],"type":"Point"}
}