{
  "type": "Feature",
  "properties": {
    "iso:country":"DE",
    "sg:address":"Ortwisch 48",
    "sg:city":"Bremen",
    "sg:phone":"+49 421/483587",
    "sg:postcode":"28307",
    "sg:province":"Bremen",
    "wof:name":"Kleintierzuchtverein Hansestadt Bremen E. V.",
    "wof:placetype":"venue"
},
  "geometry": {"coordinates":[8.9216566086,53.0436248779],"type":"Point"}
}