{
  "type": "Feature",
  "properties": {
    "iso:country":"DE",
    "sg:address":"Chemiestr. 15",
    "sg:city":"Halle",
    "sg:phone":"+49 345/7709515",
    "sg:postcode":"06132",
    "sg:province":"Sachsen-Anhalt",
    "wof:name":"Asab Ammendorfer Stahl- Und Anlagenbau Gmbh",
    "wof:placetype":"venue"
},
  "geometry": {"coordinates":[11.994521,51.439087],"type":"Point"}
}