{
  "type": "Feature",
  "properties": {
    "iso:country":"DE",
    "sg:address":"Friedensallee 1",
    "sg:city":"Borgsdorf",
    "sg:phone":"+49 3303/502396",
    "sg:postcode":"16556",
    "sg:province":"Brandenburg",
    "wof:name":"F. Schulze",
    "wof:placetype":"venue"
},
  "geometry": {"coordinates":[13.2788000107,52.7143211365],"type":"Point"}
}