{
  "type": "Feature",
  "properties": {
    "iso:country":"DE",
    "sg:address":"Wilhelm-Klemm-Str. 21",
    "sg:city":"Ebeleben",
    "sg:phone":"+49 36020/72904",
    "sg:postcode":"99713",
    "sg:province":"Th\u00fcringen",
    "wof:name":"S & B Sanierungs- Und Bedachungs Gmbh",
    "wof:placetype":"venue"
},
  "geometry": {"coordinates":[10.738449,51.280167],"type":"Point"}
}