{
  "type": "Feature",
  "properties": {
    "iso:country":"DE",
    "sg:address":"Sieglarer Str. 119",
    "sg:city":"Troisdorf",
    "sg:phone":"+49 2241/805251",
    "sg:postcode":"53842",
    "sg:province":"Nordrhein-Westfalen",
    "wof:name":"Monika Ferlantis",
    "wof:placetype":"venue"
},
  "geometry": {"coordinates":[7.1409130096,50.8105697632],"type":"Point"}
}