{
  "type": "Feature",
  "properties": {
    "iso:country":"DE",
    "sg:address":"Lustgartenbreite",
    "sg:city":"Erxleben",
    "sg:phone":"+49 39052/8032",
    "sg:postcode":"39343",
    "sg:province":"Sachsen-Anhalt",
    "wof:name":"Next-folien Gmbh",
    "wof:placetype":"venue"
},
  "geometry": {"coordinates":[11.2466001511,52.2144737244],"type":"Point"}
}