{
  "type": "Feature",
  "properties": {
    "iso:country":"DE",
    "sg:address":"Hauptstr. 15",
    "sg:city":"Blankenstein",
    "sg:phone":"+49 36642/22334",
    "sg:postcode":"07366",
    "sg:province":"Th\u00fcringen",
    "wof:name":"Peter Och Rechtsanwalt",
    "wof:placetype":"venue"
},
  "geometry": {"coordinates":[11.698559761,50.4011383057],"type":"Point"}
}