{
  "type": "Feature",
  "properties": {
    "iso:country":"DE",
    "sg:address":"Dechantengrund 1",
    "sg:city":"Naumburg",
    "sg:phone":"+49 3445/78300",
    "sg:postcode":"06618",
    "sg:province":"Sachsen-Anhalt",
    "wof:name":"Mur-stahlbau Gmbh",
    "wof:placetype":"venue"
},
  "geometry": {"coordinates":[11.8246002197,51.1581001282],"type":"Point"}
}