{
  "type": "Feature",
  "properties": {
    "iso:country":"DE",
    "sg:address":"Hogenestweg 17",
    "sg:city":"Berlin",
    "sg:phone":"+49 30/66720291",
    "sg:postcode":"12353",
    "sg:province":"Berlin",
    "wof:name":"Wgs Werkzeugmaschinen- Und Ger\u00e4teservice Gmbh",
    "wof:placetype":"venue"
},
  "geometry": {"coordinates":[13.4435825348,52.4213256836],"type":"Point"}
}