{
  "type": "Feature",
  "properties": {
    "iso:country":"DE",
    "sg:address":"Bamberger Str. 94",
    "sg:city":"Lichtenfels",
    "sg:phone":"+49 9571/1717",
    "sg:postcode":"96215",
    "sg:province":"Bayern",
    "wof:name":"Toom-baumarkt",
    "wof:placetype":"venue"
},
  "geometry": {"coordinates":[11.0548429489,50.1430587769],"type":"Point"}
}