{
  "type": "Feature",
  "properties": {
    "iso:country":"DE",
    "sg:address":"Sohl 2",
    "sg:city":"H\u00fcckeswagen",
    "sg:phone":"+49 2192/7061",
    "sg:postcode":"42499",
    "sg:province":"Nordrhein-Westfalen",
    "wof:name":"Kurt Hebbinghaus",
    "wof:placetype":"venue"
},
  "geometry": {"coordinates":[7.330604,51.133484],"type":"Point"}
}