{
  "type": "Feature",
  "properties": {
    "iso:country":"DE",
    "sg:address":"Bahnhofstr. 23",
    "sg:city":"Rabenau",
    "sg:phone":"+49 351/4602061",
    "sg:postcode":"01734",
    "sg:province":"Sachsen",
    "wof:name":"Willkommen Bei Der Rabenauer M\u00fchle!",
    "wof:placetype":"venue"
},
  "geometry": {"coordinates":[13.633572,50.963421],"type":"Point"}
}