{
  "type": "Feature",
  "properties": {
    "iso:country":"DE",
    "sg:address":"Alte Chaussee 17",
    "sg:city":"Brunsb\u00fcttel",
    "sg:postcode":"25541",
    "sg:province":"Schleswig-Holstein",
    "wof:name":"Asp Arbeits- Und Elektrik- Service F\u00fcr Projekte Gmbh",
    "wof:placetype":"venue"
},
  "geometry": {"coordinates":[9.158367157,53.8947410583],"type":"Point"}
}