{
  "type": "Feature",
  "properties": {
    "iso:country":"DE",
    "sg:address":"Freiberger Str. 10",
    "sg:city":"Marienberg",
    "sg:phone":"+49 3735/22051",
    "sg:postcode":"09496",
    "sg:province":"Sachsen",
    "wof:name":"Helfried Freier",
    "wof:placetype":"venue"
},
  "geometry": {"coordinates":[13.1653814316,50.6513252258],"type":"Point"}
}