{
  "type": "Feature",
  "properties": {
    "iso:country":"DE",
    "sg:address":"Eschent\u00fcner",
    "sg:city":"Hage",
    "sg:phone":"+49 4931/7290",
    "sg:postcode":"26524",
    "sg:province":"Niedersachsen",
    "wof:name":"Paul Deutschl\u00e4nder",
    "wof:placetype":"venue"
},
  "geometry": {"coordinates":[7.289424,53.604198],"type":"Point"}
}