{
  "type": "Feature",
  "properties": {
    "iso:country":"DE",
    "sg:address":"Lilienthalstr. 28",
    "sg:city":"Berlin",
    "sg:phone":"+49 30/6918033",
    "sg:postcode":"10965",
    "sg:province":"Berlin",
    "wof:name":"Hilfe Information Vermittlung Gemeinn\u00fctzige Gesellschaft F\u00fcr",
    "wof:placetype":"venue"
},
  "geometry": {"coordinates":[13.4073896408,52.4865112305],"type":"Point"}
}