{
  "type": "Feature",
  "properties": {
    "iso:country":"DE",
    "sg:address":"Herborner Str. 11",
    "sg:city":"Driedorf",
    "sg:phone":"+49 2775/7606",
    "sg:postcode":"35759",
    "sg:province":"Hessen",
    "wof:name":"Wilfried Schneider Ingenieur",
    "wof:placetype":"venue"
},
  "geometry": {"coordinates":[8.1905193329,50.6366539001],"type":"Point"}
}