{
  "type": "Feature",
  "properties": {
    "iso:country":"DE",
    "sg:address":"Beethovenstr. 6",
    "sg:city":"Sch\u00f6nhausen",
    "sg:phone":"+49 39323/347",
    "sg:postcode":"39524",
    "sg:province":"Sachsen-Anhalt",
    "wof:name":"Raiffeisenbank",
    "wof:placetype":"venue"
},
  "geometry": {"coordinates":[12.040306,52.581646],"type":"Point"}
}