{
  "type": "Feature",
  "properties": {
    "iso:country":"DE",
    "sg:address":"Poazlgasteig 5",
    "sg:city":"Dietramszell",
    "sg:postcode":"83623",
    "sg:province":"Bayern",
    "wof:name":"Markt-kommunikation Gesellschaft F\u00fcr",
    "wof:placetype":"venue"
},
  "geometry": {"coordinates":[11.5847730637,47.8450775146],"type":"Point"}
}