{
  "type": "Feature",
  "properties": {
    "iso:country":"DE",
    "sg:address":"Untere Wei\u00dflach 10",
    "sg:city":"Rodenbach",
    "sg:phone":"+49 6374/3403",
    "sg:postcode":"67688",
    "sg:province":"Rheinland-Pfalz",
    "wof:name":"T. Hort",
    "wof:placetype":"venue"
},
  "geometry": {"coordinates":[7.6453061104,49.4690628052],"type":"Point"}
}