{
  "type": "Feature",
  "properties": {
    "iso:country":"DE",
    "sg:address":"Marktstr. 3 a",
    "sg:city":"Arnsberg",
    "sg:phone":"+49 2932/52215",
    "sg:postcode":"59759",
    "sg:province":"Nordrhein-Westfalen",
    "wof:name":"Eis-cafe San Marco",
    "wof:placetype":"venue"
},
  "geometry": {"coordinates":[11.374333,48.924362],"type":"Point"}
}