{
  "type": "Feature",
  "properties": {
    "iso:country":"DE",
    "sg:address":"Altdorferstr. 7",
    "sg:city":"Tegernheim",
    "sg:phone":"+49 9403/1386",
    "sg:postcode":"93105",
    "sg:province":"Bayern",
    "wof:name":"Stefan Gepperth Bauingenieur",
    "wof:placetype":"venue"
},
  "geometry": {"coordinates":[12.1696405411,49.0232810974],"type":"Point"}
}