{
  "type": "Feature",
  "properties": {
    "iso:country":"DE",
    "sg:address":"Burgstallstr. 9",
    "sg:city":"Gruibingen",
    "sg:phone":"+49 7335/6656",
    "sg:postcode":"73344",
    "sg:province":"Baden-W\u00fcrttemberg",
    "wof:name":"G. Und M. Lamaschansky",
    "wof:placetype":"venue"
},
  "geometry": {"coordinates":[9.6440496445,48.5927581787],"type":"Point"}
}