{
  "type": "Feature",
  "properties": {
    "iso:country":"DE",
    "sg:address":"Enge Gasse 15",
    "sg:city":"Eschwege",
    "sg:phone":"+49 5651/31146",
    "sg:postcode":"37269",
    "sg:province":"Hessen",
    "wof:name":"Sanit\u00e4tsfachgesch\u00e4ft Pfaff Inh. Dieter Sumbach",
    "wof:placetype":"venue"
},
  "geometry": {"coordinates":[10.056524,51.187222],"type":"Point"}
}