{
  "type": "Feature",
  "properties": {
    "iso:country":"DE",
    "sg:address":"Hof Trages",
    "sg:city":"Freigericht",
    "sg:phone":"+49 6055/7540",
    "sg:postcode":"63579",
    "sg:province":"Hessen",
    "wof:name":"Gfvu Gesellschaft Zur F\u00f6rderung Des Verursacher-",
    "wof:placetype":"venue"
},
  "geometry": {"coordinates":[9.092464447,50.122543335],"type":"Point"}
}