{
  "type": "Feature",
  "properties": {
    "iso:country":"DE",
    "sg:address":"Mittelberg 4",
    "sg:city":"Wermelskirchen",
    "sg:phone":"+49 2196/80640",
    "sg:postcode":"42929",
    "sg:province":"Nordrhein-Westfalen",
    "wof:name":"Oskar Winterhagen",
    "wof:placetype":"venue"
},
  "geometry": {"coordinates":[7.253042,51.088367],"type":"Point"}
}