{
  "type": "Feature",
  "properties": {
    "iso:country":"DE",
    "sg:address":"Corneliusstr. 88",
    "sg:city":"D\u00fcsseldorf",
    "sg:phone":"+49 211/374972",
    "sg:postcode":"40215",
    "sg:province":"Nordrhein-Westfalen",
    "wof:name":"Hongkong China-imbiss",
    "wof:placetype":"venue"
},
  "geometry": {"coordinates":[6.7830061913,51.2125701904],"type":"Point"}
}