{
  "type": "Feature",
  "properties": {
    "iso:country":"DE",
    "sg:address":"Feursstr. 26",
    "sg:city":"Olching",
    "sg:phone":"+49 8142/15465",
    "sg:postcode":"82140",
    "sg:province":"Bayern",
    "wof:name":"H. Gareis",
    "wof:placetype":"venue"
},
  "geometry": {"coordinates":[11.339741,48.213253],"type":"Point"}
}