{
  "type": "Feature",
  "properties": {
    "iso:country":"DE",
    "sg:address":"Auf dem Baggersand 15 -17",
    "sg:city":"L\u00fcbeck",
    "sg:phone":"+49 4502/75755",
    "sg:postcode":"23570",
    "sg:province":"Schleswig-Holstein",
    "wof:name":"Park & Sail Gmbh",
    "wof:placetype":"venue"
},
  "geometry": {"coordinates":[10.858257,53.955536],"type":"Point"}
}