{
  "type": "Feature",
  "properties": {
    "iso:country":"DE",
    "sg:address":"Harikseeweg 48",
    "sg:city":"Schwalmtal",
    "sg:postcode":"41366",
    "sg:province":"Nordrhein-Westfalen",
    "wof:name":"Stein-grafik Stm Gmbh",
    "wof:placetype":"venue"
},
  "geometry": {"coordinates":[6.2255420685,51.2225379944],"type":"Point"}
}