{
  "type": "Feature",
  "properties": {
    "iso:country":"DE",
    "sg:address":"Peuter Elbdeich 45",
    "sg:city":"Hamburg",
    "sg:phone":"+49 40/7804370",
    "sg:postcode":"20539",
    "sg:province":"Hamburg",
    "wof:name":"Herbert Neumann Gmbh",
    "wof:placetype":"venue"
},
  "geometry": {"coordinates":[10.042807579,53.5240898132],"type":"Point"}
}