{
  "type": "Feature",
  "properties": {
    "iso:country":"DE",
    "sg:address":"Brunnenstr. 10",
    "sg:city":"Seebad Heringsdorf",
    "sg:postcode":"17424",
    "sg:province":"Mecklenburg-Vorpommern",
    "wof:name":"U. Pilgrim",
    "wof:placetype":"venue"
},
  "geometry": {"coordinates":[14.164821,53.953651],"type":"Point"}
}