{
  "type": "Feature",
  "properties": {
    "iso:country":"DE",
    "sg:address":"Bahnhofstr. 8",
    "sg:city":"Aschau",
    "sg:phone":"+49 8052/316",
    "sg:postcode":"83229",
    "sg:province":"Bayern",
    "wof:name":"Schlo\u00df-apotheke",
    "wof:placetype":"venue"
},
  "geometry": {"coordinates":[12.260409,47.683472],"type":"Point"}
}