{
  "type": "Feature",
  "properties": {
    "iso:country":"DE",
    "sg:address":"Karoxbosteler Chaussee 44",
    "sg:city":"Seevetal",
    "sg:phone":"+49 4105/2324",
    "sg:postcode":"21218",
    "sg:province":"Niedersachsen",
    "wof:name":"G\u00fcnter Firzlaff",
    "wof:placetype":"venue"
},
  "geometry": {"coordinates":[10.007569313,53.3943328857],"type":"Point"}
}