{
  "type": "Feature",
  "properties": {
    "iso:country":"DE",
    "sg:address":"Rul\u00e4nderweg 34",
    "sg:city":"Weingarten",
    "sg:phone":"+49 7244/4752",
    "sg:postcode":"76356",
    "sg:province":"Baden-W\u00fcrttemberg",
    "wof:name":"Wenglein & Ruggaber Gmbh",
    "wof:placetype":"venue"
},
  "geometry": {"coordinates":[8.5427865982,49.0522537231],"type":"Point"}
}