{
  "type": "Feature",
  "properties": {
    "iso:country":"DE",
    "sg:address":"Bremer Heerstr. 123 a",
    "sg:city":"Oldenburg",
    "sg:phone":"+49 441/201617",
    "sg:postcode":"26135",
    "sg:province":"Niedersachsen",
    "wof:name":"Uwe Schillm\u00fcller Tennislehrer",
    "wof:placetype":"venue"
},
  "geometry": {"coordinates":[8.2412137985,53.1263389587],"type":"Point"}
}