{
  "type": "Feature",
  "properties": {
    "iso:country":"DE",
    "sg:address":"Hauptstr. 20::",
    "sg:city":"Alfhausen",
    "sg:phone":"+49 4954/6496000",
    "sg:postcode":"49594",
    "sg:province":"Niedersachsen",
    "wof:name":"Raiffeisenbank Eg",
    "wof:placetype":"venue"
},
  "geometry": {"coordinates":[7.950736,52.501907],"type":"Point"}
}