{
  "type": "Feature",
  "properties": {
    "iso:country":"DE",
    "sg:address":"Hauptplatz 1",
    "sg:city":"Hohenfurch",
    "sg:phone":"+49 8861/7078",
    "sg:postcode":"86978",
    "sg:province":"Bayern",
    "wof:name":"Kreissparkasse Schongau",
    "wof:placetype":"venue"
},
  "geometry": {"coordinates":[10.895959,47.848598],"type":"Point"}
}