{
  "type": "Feature",
  "properties": {
    "iso:country":"DE",
    "sg:address":"Frankfurter Str. 42",
    "sg:city":"Seelow",
    "sg:phone":"+49 3346/843753",
    "sg:postcode":"15306",
    "sg:province":"Brandenburg",
    "wof:name":"M. Borchardt",
    "wof:placetype":"venue"
},
  "geometry": {"coordinates":[14.38448,52.527409],"type":"Point"}
}