{
  "type": "Feature",
  "properties": {
    "iso:country":"DE",
    "sg:address":"Hauptstr. 31",
    "sg:city":"Damme",
    "sg:phone":"+49 5491/7359",
    "sg:postcode":"49401",
    "sg:province":"Niedersachsen",
    "wof:name":"Volks- Und Jugendb\u00fccherei I.d. Grundschule R\u00fcschendorf",
    "wof:placetype":"venue"
},
  "geometry": {"coordinates":[8.265768,52.521851],"type":"Point"}
}