{
  "type": "Feature",
  "properties": {
    "iso:country":"DE",
    "sg:address":"Am Stadtwalde 79",
    "sg:city":"Rheine",
    "sg:phone":"+49 5971/805924",
    "sg:postcode":"48432",
    "sg:province":"Nordrhein-Westfalen",
    "wof:name":"Micheel Verwaltungs Gmbh",
    "wof:placetype":"venue"
},
  "geometry": {"coordinates":[7.4522848129,52.3027420044],"type":"Point"}
}