{
  "type": "Feature",
  "properties": {
    "iso:country":"DE",
    "sg:address":"Schusterkamp 9",
    "sg:city":"Schmalfeld",
    "sg:phone":"+49 4191/959654",
    "sg:postcode":"24640",
    "sg:province":"Schleswig-Holstein",
    "wof:name":"Karl Ha\u00df",
    "wof:placetype":"venue"
},
  "geometry": {"coordinates":[9.980497,53.878029],"type":"Point"}
}