{
  "type": "Feature",
  "properties": {
    "iso:country":"DE",
    "sg:address":"B\u00f6brachm\u00fchle",
    "sg:city":"B\u00f6brach",
    "sg:phone":"+49 9923/1623",
    "sg:postcode":"94255",
    "sg:province":"Bayern",
    "wof:name":"X. Ebner",
    "wof:placetype":"venue"
},
  "geometry": {"coordinates":[13.0341129303,49.0470466614],"type":"Point"}
}