{
  "type": "Feature",
  "properties": {
    "iso:country":"DE",
    "sg:address":"Eickhofer Str. 16",
    "sg:city":"Warnow",
    "sg:postcode":"18249",
    "sg:province":"Mecklenburg-Vorpommern",
    "wof:name":"Moser",
    "wof:placetype":"venue"
},
  "geometry": {"coordinates":[11.885233,53.785393],"type":"Point"}
}