{
  "type": "Feature",
  "properties": {
    "iso:country":"DE",
    "sg:address":"Ax\u00f6der Ring 36",
    "sg:city":"Eggenfelden",
    "sg:phone":"+49 8721/1374",
    "sg:postcode":"84307",
    "sg:province":"Bayern",
    "wof:name":"Robert Sammer",
    "wof:placetype":"venue"
},
  "geometry": {"coordinates":[12.7584886551,48.4100036621],"type":"Point"}
}