{
  "type": "Feature",
  "properties": {
    "iso:country":"DE",
    "sg:address":"Heugrundstr. 6",
    "sg:city":"Sensbachtal",
    "sg:phone":"+49 6068/753",
    "sg:postcode":"64759",
    "sg:province":"Hessen",
    "wof:name":"Reinhold K\u00f6rber Gmbh",
    "wof:placetype":"venue"
},
  "geometry": {"coordinates":[9.0131,49.51865],"type":"Point"}
}