{
  "type": "Feature",
  "properties": {
    "iso:country":"DE",
    "sg:address":"Neufeldstr. 9",
    "sg:city":"Kuppenheim",
    "sg:phone":"+49 7222/41674",
    "sg:postcode":"76456",
    "sg:province":"Baden-W\u00fcrttemberg",
    "wof:name":"Gerhard K\u00fcst",
    "wof:placetype":"venue"
},
  "geometry": {"coordinates":[8.2468338013,48.8376846313],"type":"Point"}
}