{
  "type": "Feature",
  "properties": {
    "iso:country":"DE",
    "sg:address":"Talstr. 10-2",
    "sg:city":"B\u00f6nnigheim",
    "sg:phone":"+49 7143/22400",
    "sg:postcode":"74357",
    "sg:province":"Baden-W\u00fcrttemberg",
    "wof:name":"H. Kurz Und J. Peukert",
    "wof:placetype":"venue"
},
  "geometry": {"coordinates":[9.1229810715,49.0398216248],"type":"Point"}
}