{
  "type": "Feature",
  "properties": {
    "iso:country":"DE",
    "sg:address":"Ruhesteinstr. 173",
    "sg:city":"Baiersbronn",
    "sg:phone":"+49 7442/84390",
    "sg:postcode":"72270",
    "sg:province":"Baden-W\u00fcrttemberg",
    "wof:name":"Ludwig Z\u00fcfle Holzwerk Gmbh",
    "wof:placetype":"venue"
},
  "geometry": {"coordinates":[8.3615999222,48.5095596313],"type":"Point"}
}