{
  "type": "Feature",
  "properties": {
    "iso:country":"DE",
    "sg:address":"Georg-Sasse-Str 43",
    "sg:city":"Ammersbek",
    "sg:phone":"+49 40/6056710",
    "sg:postcode":"22949",
    "sg:province":"Schleswig-Holstein",
    "wof:name":"Fihumin-gesellschaft M.b.h.",
    "wof:placetype":"venue"
},
  "geometry": {"coordinates":[10.151337,53.675747],"type":"Point"}
}