{
  "type": "Feature",
  "properties": {
    "iso:country":"DE",
    "sg:address":"Neustadter Str. 26",
    "sg:city":"Coburg",
    "sg:phone":"+49 9561/8680",
    "sg:postcode":"96450",
    "sg:province":"Bayern",
    "wof:name":"R\u00e4der-beteiligungsges. Mbh",
    "wof:placetype":"venue"
},
  "geometry": {"coordinates":[10.969556,50.271763],"type":"Point"}
}