{
  "type": "Feature",
  "properties": {
    "iso:country":"DE",
    "sg:address":"Am Schlachthof 9",
    "sg:city":"L\u00fcneburg",
    "sg:phone":"+49 4131/187148",
    "sg:postcode":"21339",
    "sg:province":"Niedersachsen",
    "wof:name":"Bahr Baumarkt",
    "wof:placetype":"venue"
},
  "geometry": {"coordinates":[10.425141,53.270706],"type":"Point"}
}