{
  "type": "Feature",
  "properties": {
    "iso:country":"DE",
    "sg:address":"Urspringer Weg 1",
    "sg:city":"Roden",
    "sg:phone":"+49 9396/1205",
    "sg:postcode":"97849",
    "sg:province":"Bayern",
    "wof:name":"M. Weyer",
    "wof:placetype":"venue"
},
  "geometry": {"coordinates":[9.6237888336,49.9185447693],"type":"Point"}
}