{
  "type": "Feature",
  "properties": {
    "iso:country":"DE",
    "sg:address":"Berkener Str. 76",
    "sg:city":"Schorndorf",
    "sg:phone":"+49 7181/3539",
    "sg:postcode":"73614",
    "sg:province":"Baden-W\u00fcrttemberg",
    "wof:name":"Edgar Krause Cad-konstruktionsges. Mbh",
    "wof:placetype":"venue"
},
  "geometry": {"coordinates":[9.571513,48.766739],"type":"Point"}
}