{
  "type": "Feature",
  "properties": {
    "iso:country":"DE",
    "sg:address":"Westfalendamm 35",
    "sg:city":"Dortmund",
    "sg:phone":"+49 231/421566",
    "sg:postcode":"44141",
    "sg:province":"Nordrhein-Westfalen",
    "wof:name":"Innocom",
    "wof:placetype":"venue"
},
  "geometry": {"coordinates":[7.4862141609,51.5010147095],"type":"Point"}
}