{
  "type": "Feature",
  "properties": {
    "iso:country":"DE",
    "sg:address":"Am Lehmteich 9",
    "sg:city":"Oelsnitz",
    "sg:phone":"+49 37421/4600",
    "sg:postcode":"08606",
    "sg:province":"Sachsen",
    "wof:name":"Tul Tec Ges.f. Transport Um- Schlag-u. Lastaufnahmem.mbh",
    "wof:placetype":"venue"
},
  "geometry": {"coordinates":[12.191737175,50.4343528748],"type":"Point"}
}