{
  "type": "Feature",
  "properties": {
    "iso:country":"DE",
    "sg:address":"B\u00e4rensteinstr. 16",
    "sg:city":"Berlin",
    "sg:phone":"+49 30/5417875",
    "sg:postcode":"12685",
    "sg:province":"Berlin",
    "wof:name":"Lars Franke",
    "wof:placetype":"venue"
},
  "geometry": {"coordinates":[13.5668077469,52.5415534973],"type":"Point"}
}