{
  "type": "Feature",
  "properties": {
    "iso:country":"DE",
    "sg:address":"Im Schosseifen 8",
    "sg:city":"Eschenburg",
    "sg:phone":"+49 2774/51914",
    "sg:postcode":"35713",
    "sg:province":"Hessen",
    "wof:name":"Waldesruh",
    "wof:placetype":"venue"
},
  "geometry": {"coordinates":[8.3286819458,50.8227157593],"type":"Point"}
}