{
  "type": "Feature",
  "properties": {
    "iso:country":"DE",
    "sg:address":"Oberend 22",
    "sg:city":"Sche\u00dflitz",
    "sg:phone":"+49 9542/8022",
    "sg:postcode":"96110",
    "sg:province":"Bayern",
    "wof:name":"Wilhelm Vogt Gmbh",
    "wof:placetype":"venue"
},
  "geometry": {"coordinates":[11.0368337631,49.9772758484],"type":"Point"}
}