{
  "type": "Feature",
  "properties": {
    "iso:country":"DE",
    "sg:address":"Herdweg 122",
    "sg:city":"Darmstadt",
    "sg:postcode":"64287",
    "sg:province":"Hessen",
    "wof:name":"Ki Sollar Ki Sollar Kg",
    "wof:placetype":"venue"
},
  "geometry": {"coordinates":[8.668929,49.867466],"type":"Point"}
}