{
  "type": "Feature",
  "properties": {
    "iso:country":"DE",
    "sg:address":"Klosterstr. 12",
    "sg:city":"Walld\u00fcrn",
    "sg:postcode":"74731",
    "sg:province":"Baden-W\u00fcrttemberg",
    "wof:name":"Textil-gehrig Gmbh",
    "wof:placetype":"venue"
},
  "geometry": {"coordinates":[9.366745,49.584064],"type":"Point"}
}