{
  "type": "Feature",
  "properties": {
    "iso:country":"DE",
    "sg:address":"Industriestr. 4",
    "sg:city":"Geyer",
    "sg:phone":"+49 4937/346620",
    "sg:postcode":"09468",
    "sg:province":"Sachsen",
    "wof:name":"Kunert Werke Gmbh",
    "wof:placetype":"venue"
},
  "geometry": {"coordinates":[12.929831,50.624588],"type":"Point"}
}