{
  "type": "Feature",
  "properties": {
    "iso:country":"DE",
    "sg:address":"Buxtehuder Str. 82",
    "sg:city":"Hamburg",
    "sg:phone":"+49 40/7001660",
    "sg:postcode":"21073",
    "sg:province":"Hamburg",
    "wof:name":"Rolf Dankers Verwaltungs- Gmbh",
    "wof:placetype":"venue"
},
  "geometry": {"coordinates":[9.9666976929,53.4685554504],"type":"Point"}
}