{
  "type": "Feature",
  "properties": {
    "iso:country":"DE",
    "sg:address":"Hirschbergstr. 7",
    "sg:city":"Hindelang",
    "sg:phone":"+49 8324/485",
    "sg:postcode":"87541",
    "sg:province":"Bayern",
    "wof:name":"Gerhard Scholl",
    "wof:placetype":"venue"
},
  "geometry": {"coordinates":[10.3844356537,47.5045776367],"type":"Point"}
}