{
  "type": "Feature",
  "properties": {
    "iso:country":"DE",
    "sg:address":"Langemarckstr. 21",
    "sg:city":"Bad Wildungen",
    "sg:phone":"+49 5621/73208",
    "sg:postcode":"34537",
    "sg:province":"Hessen",
    "wof:name":"Schlo\u00df Friedrichstein Fa. Martin",
    "wof:placetype":"venue"
},
  "geometry": {"coordinates":[9.105661,51.112617],"type":"Point"}
}