{
  "type": "Feature",
  "properties": {
    "iso:country":"DE",
    "sg:address":"Am Anger 55",
    "sg:city":"Hamb\u00fchren",
    "sg:phone":"+49 5084/6885",
    "sg:postcode":"29313",
    "sg:province":"Niedersachsen",
    "wof:name":"Hans-joachim Wallentowitz",
    "wof:placetype":"venue"
},
  "geometry": {"coordinates":[9.932268,52.641842],"type":"Point"}
}