{
  "type": "Feature",
  "properties": {
    "iso:country":"DE",
    "sg:address":"Trappenbergstr. 11",
    "sg:city":"Essen",
    "sg:phone":"+49 201/441621",
    "sg:postcode":"45134",
    "sg:province":"Nordrhein-Westfalen",
    "wof:name":"Herbert Endre\u00df Ingenieur",
    "wof:placetype":"venue"
},
  "geometry": {"coordinates":[7.023955822,51.4156799316],"type":"Point"}
}