{
  "type": "Feature",
  "properties": {
    "iso:country":"DE",
    "sg:address":"Buttermarkt 14",
    "sg:city":"Fulda",
    "sg:phone":"+49 661/72704",
    "sg:postcode":"36037",
    "sg:province":"Hessen",
    "wof:name":"Emmy Volkmar",
    "wof:placetype":"venue"
},
  "geometry": {"coordinates":[9.6780691147,50.5505027771],"type":"Point"}
}