{
  "type": "Feature",
  "properties": {
    "iso:country":"DE",
    "sg:address":"Sprengelstr. 3 a",
    "sg:city":"Burgdorf",
    "sg:phone":"+49 5136/89180",
    "sg:postcode":"31303",
    "sg:province":"Niedersachsen",
    "wof:name":"Bauma-stein Gmbh & Co. Kg",
    "wof:placetype":"venue"
},
  "geometry": {"coordinates":[9.9808139801,52.466796875],"type":"Point"}
}