{
  "type": "Feature",
  "properties": {
    "iso:country":"DE",
    "sg:address":"Bahnhofstr. 2 a",
    "sg:city":"Leverkusen",
    "sg:phone":"+49 2171/400994",
    "sg:postcode":"51379",
    "sg:province":"Nordrhein-Westfalen",
    "wof:name":"Redaktion Rheinische Post",
    "wof:placetype":"venue"
},
  "geometry": {"coordinates":[7.0038881302,51.0663528442],"type":"Point"}
}