{
  "type": "Feature",
  "properties": {
    "iso:country":"DE",
    "sg:address":"Vordergasse 32",
    "sg:city":"Hirschberg",
    "sg:phone":"+49 6201/51453",
    "sg:postcode":"69493",
    "sg:province":"Baden-W\u00fcrttemberg",
    "wof:name":"Katholisches Pfarramt St. Johann B.",
    "wof:placetype":"venue"
},
  "geometry": {"coordinates":[8.665596962,49.5000991821],"type":"Point"}
}