{
  "type": "Feature",
  "properties": {
    "iso:country":"DE",
    "sg:address":"Senefelderstr. 7",
    "sg:city":"Paderborn",
    "sg:postcode":"33100",
    "sg:province":"Nordrhein-Westfalen",
    "wof:name":"Seiko Gmbh",
    "wof:placetype":"venue"
},
  "geometry": {"coordinates":[8.7870693207,51.7342758179],"type":"Point"}
}