{
  "type": "Feature",
  "properties": {
    "iso:country":"DE",
    "sg:address":"Marktplatz 3",
    "sg:city":"B\u00f6nen",
    "sg:phone":"+49 2383/1600",
    "sg:postcode":"59199",
    "sg:province":"Nordrhein-Westfalen",
    "wof:name":"Kovacs",
    "wof:placetype":"venue"
},
  "geometry": {"coordinates":[7.745441,51.596172],"type":"Point"}
}