{
  "type": "Feature",
  "properties": {
    "iso:country":"DE",
    "sg:address":"Hainitzer Str. 29",
    "sg:city":"Obergurig",
    "sg:phone":"+49 35938/51909",
    "sg:postcode":"02692",
    "sg:province":"Sachsen",
    "wof:name":"Gabriele Klaubert",
    "wof:placetype":"venue"
},
  "geometry": {"coordinates":[14.4239902496,51.1287307739],"type":"Point"}
}