{
  "type": "Feature",
  "properties": {
    "iso:country":"DE",
    "sg:address":"Hauptstr. 248",
    "sg:city":"R\u00f6srath",
    "sg:postcode":"51503",
    "sg:province":"Nordrhein-Westfalen",
    "wof:name":"Ursula Busch-zenk",
    "wof:placetype":"venue"
},
  "geometry": {"coordinates":[7.197311,50.913994],"type":"Point"}
}