{
  "type": "Feature",
  "properties": {
    "iso:country":"DE",
    "sg:address":"Sonnenstr. 30-31",
    "sg:city":"M\u00fcnster",
    "sg:phone":"+49 251/54762",
    "sg:postcode":"48143",
    "sg:province":"Nordrhein-Westfalen",
    "wof:name":"Walter Fliss",
    "wof:placetype":"venue"
},
  "geometry": {"coordinates":[7.633404,51.96373],"type":"Point"}
}