{
  "type": "Feature",
  "properties": {
    "iso:country":"DE",
    "sg:address":"Neue Rabenstr. 15",
    "sg:city":"Hamburg",
    "sg:phone":"+49 40/41240",
    "sg:postcode":"20354",
    "sg:province":"Hamburg",
    "wof:name":"Hansa Beteiligungs-gmbh",
    "wof:placetype":"venue"
},
  "geometry": {"coordinates":[9.993187,53.561047],"type":"Point"}
}