{
  "type": "Feature",
  "properties": {
    "iso:country":"DE",
    "sg:address":"Karl-Marx-Str. 264",
    "sg:city":"Berlin",
    "sg:phone":"+49 30/6852093",
    "sg:postcode":"12057",
    "sg:province":"Berlin",
    "wof:name":"Avis",
    "wof:placetype":"venue"
},
  "geometry": {"coordinates":[13.442345,52.465351],"type":"Point"}
}