{
  "type": "Feature",
  "properties": {
    "iso:country":"DE",
    "sg:address":"Bahnhofstr. 2",
    "sg:city":"Bitburg",
    "sg:postcode":"54634",
    "sg:province":"Rheinland-Pfalz",
    "wof:name":"Theodor Riewer",
    "wof:placetype":"venue"
},
  "geometry": {"coordinates":[6.5238170624,49.9675178528],"type":"Point"}
}