{
  "type": "Feature",
  "properties": {
    "iso:country":"DE",
    "sg:address":"Untere R\u00f6merstr. 34",
    "sg:city":"Aholming",
    "sg:phone":"+49 9938/473",
    "sg:postcode":"94527",
    "sg:province":"Bayern",
    "wof:name":"Marlene H\u00f6tzl",
    "wof:placetype":"venue"
},
  "geometry": {"coordinates":[12.918404,48.734161],"type":"Point"}
}