{
  "type": "Feature",
  "properties": {
    "iso:country":"DE",
    "sg:address":"Bellinostr. 87",
    "sg:city":"Reutlingen",
    "sg:phone":"+49 7121/24410",
    "sg:postcode":"72764",
    "sg:province":"Baden-W\u00fcrttemberg",
    "wof:name":"Ursula Epp Krankengymnastin",
    "wof:placetype":"venue"
},
  "geometry": {"coordinates":[9.212063,48.480804],"type":"Point"}
}