{
  "type": "Feature",
  "properties": {
    "iso:country":"DE",
    "sg:address":"Moorstr. 1",
    "sg:city":"M\u00fcden",
    "sg:phone":"+49 5375/1221",
    "sg:postcode":"38539",
    "sg:province":"Niedersachsen",
    "wof:name":"Albert Stock",
    "wof:placetype":"venue"
},
  "geometry": {"coordinates":[10.40626,52.552109],"type":"Point"}
}