{
  "type": "Feature",
  "properties": {
    "iso:country":"DE",
    "sg:address":"Dorfstr. 34",
    "sg:city":"Rieseby",
    "sg:phone":"+49 4355/322",
    "sg:postcode":"24354",
    "sg:province":"Schleswig-Holstein",
    "wof:name":"Elektro Reimer Gmbh",
    "wof:placetype":"venue"
},
  "geometry": {"coordinates":[9.813763,54.541748],"type":"Point"}
}