{
  "type": "Feature",
  "properties": {
    "iso:country":"DE",
    "sg:address":"Friedrichstr. 4",
    "sg:city":"Fulda",
    "sg:phone":"+49 661/241175",
    "sg:postcode":"36037",
    "sg:province":"Hessen",
    "wof:name":"I. Heier",
    "wof:placetype":"venue"
},
  "geometry": {"coordinates":[9.6759748459,50.5519561768],"type":"Point"}
}