{
  "type": "Feature",
  "properties": {
    "iso:country":"DE",
    "sg:address":"Langendorfer Str. 125",
    "sg:city":"Neuwied",
    "sg:phone":"+49 2631/24895",
    "sg:postcode":"56564",
    "sg:province":"Rheinland-Pfalz",
    "wof:name":"K. Jechel Kg",
    "wof:placetype":"venue"
},
  "geometry": {"coordinates":[7.4602718353,50.4285697937],"type":"Point"}
}