{
  "type": "Feature",
  "properties": {
    "iso:country":"DE",
    "sg:address":"Ottensteiner Brook 2",
    "sg:city":"Ahaus",
    "sg:phone":"+49 2561/987398",
    "sg:postcode":"48683",
    "sg:province":"Nordrhein-Westfalen",
    "wof:name":"J. Buning Westfalen-tankstelle",
    "wof:placetype":"venue"
},
  "geometry": {"coordinates":[6.911261,52.07164],"type":"Point"}
}