{
  "type": "Feature",
  "properties": {
    "iso:country":"DE",
    "sg:address":"J\u00e4gerweg 18",
    "sg:city":"Reutlingen",
    "sg:phone":"+49 7121/493124",
    "sg:postcode":"72766",
    "sg:province":"Baden-W\u00fcrttemberg",
    "wof:name":"Helmut Veith Ingenieur",
    "wof:placetype":"venue"
},
  "geometry": {"coordinates":[9.2400331497,48.5131149292],"type":"Point"}
}