{
  "type": "Feature",
  "properties": {
    "iso:country":"DE",
    "sg:address":"Bergstr. 1",
    "sg:city":"R\u00fcdersdorf",
    "sg:phone":"+49 33638/2618",
    "sg:postcode":"15562",
    "sg:province":"Brandenburg",
    "wof:name":"B\u00e4rbel Hutfilz",
    "wof:placetype":"venue"
},
  "geometry": {"coordinates":[13.7954807281,52.4686927795],"type":"Point"}
}