{
  "type": "Feature",
  "properties": {
    "iso:country":"DE",
    "sg:address":"Im Wasen 12",
    "sg:city":"Blaichach",
    "sg:phone":"+49 8321/81074",
    "sg:postcode":"87544",
    "sg:province":"Bayern",
    "wof:name":"Geo-consult Sauter & St\u00fcber Gmbh",
    "wof:placetype":"venue"
},
  "geometry": {"coordinates":[10.258499,47.528271],"type":"Point"}
}