{
  "type": "Feature",
  "properties": {
    "iso:country":"DE",
    "sg:address":"Oststr. 34",
    "sg:city":"Leipzig",
    "sg:postcode":"04317",
    "sg:province":"Sachsen",
    "wof:name":"Prof. Siegfried Ratzlaff",
    "wof:placetype":"venue"
},
  "geometry": {"coordinates":[12.401959,51.332134],"type":"Point"}
}