{
  "type": "Feature",
  "properties": {
    "iso:country":"DE",
    "sg:address":"Bad W\u00f6rishofer Str. 5",
    "sg:city":"Mindelheim",
    "sg:phone":"+49 8261/20027",
    "sg:postcode":"87719",
    "sg:province":"Bayern",
    "wof:name":"Gudrun Decker",
    "wof:placetype":"venue"
},
  "geometry": {"coordinates":[10.4917068481,48.0454025269],"type":"Point"}
}