{
  "type": "Feature",
  "properties": {
    "iso:country":"DE",
    "sg:address":"Hummelweg 50",
    "sg:city":"Kassel",
    "sg:phone":"+49 561/811858",
    "sg:postcode":"34125",
    "sg:province":"Hessen",
    "wof:name":"Ev. Pfarramt Vers\u00f6hnungskirche",
    "wof:placetype":"venue"
},
  "geometry": {"coordinates":[9.5195198059,51.3357925415],"type":"Point"}
}