{
  "type": "Feature",
  "properties": {
    "iso:country":"DE",
    "sg:address":"Raiffeisenstr. 4",
    "sg:city":"Goldkronach",
    "sg:phone":"+49 9208/588051",
    "sg:postcode":"95497",
    "sg:province":"Bayern",
    "wof:name":"Gafo Gbr",
    "wof:placetype":"venue"
},
  "geometry": {"coordinates":[11.6602020264,49.9959602356],"type":"Point"}
}