{
  "type": "Feature",
  "properties": {
    "iso:country":"DE",
    "sg:address":"Hauptstra\u00dfe 13",
    "sg:city":"Schlo\u00df Holte-Stukenbrock",
    "sg:phone":"+49 5207/95210",
    "sg:postcode":"33758",
    "sg:province":"Nordrhein-Westfalen",
    "wof:name":"Gasthof Zur Post",
    "wof:placetype":"venue"
},
  "geometry": {"coordinates":[8.6580286026,51.9117393494],"type":"Point"}
}