{
  "type": "Feature",
  "properties": {
    "iso:country":"DE",
    "sg:address":"Edekastr. 7",
    "sg:city":"Buseck",
    "sg:phone":"+49 6408/90350",
    "sg:postcode":"35418",
    "sg:province":"Hessen",
    "wof:name":"Drachengas Propangasvertriebsstelle",
    "wof:placetype":"venue"
},
  "geometry": {"coordinates":[8.8024721146,50.6013450623],"type":"Point"}
}