{
  "type": "Feature",
  "properties": {
    "iso:country":"DE",
    "sg:address":"Petrinistr. 5",
    "sg:city":"W\u00fcrzburg",
    "sg:phone":"+49 931/2704310",
    "sg:postcode":"97080",
    "sg:province":"Bayern",
    "wof:name":"Rsb Pro Gmbh",
    "wof:placetype":"venue"
},
  "geometry": {"coordinates":[9.946323,49.802074],"type":"Point"}
}