{
  "type": "Feature",
  "properties": {
    "iso:country":"DE",
    "sg:address":"S\u00fcdallee 6",
    "sg:city":"Zschepplin",
    "sg:phone":"+49 34242/5350",
    "sg:postcode":"04838",
    "sg:province":"Sachsen",
    "wof:name":"Mbl Bauelemente Schabehorn Gmbh",
    "wof:placetype":"venue"
},
  "geometry": {"coordinates":[12.593856,51.530392],"type":"Point"}
}