{
  "type": "Feature",
  "properties": {
    "iso:country":"DE",
    "sg:address":"Dresdner Str. 22",
    "sg:city":"M\u00fclsen",
    "sg:postcode":"08132",
    "sg:province":"Sachsen",
    "wof:name":"Heissmangel",
    "wof:placetype":"venue"
},
  "geometry": {"coordinates":[12.5698757172,50.7365646362],"type":"Point"}
}