{
  "type": "Feature",
  "properties": {
    "iso:country":"DE",
    "sg:address":"Brunnenstr. 6",
    "sg:city":"Osterhofen",
    "sg:phone":"+49 9932/3035",
    "sg:postcode":"94486",
    "sg:province":"Bayern",
    "wof:name":"Georg Well",
    "wof:placetype":"venue"
},
  "geometry": {"coordinates":[12.974475,48.659615],"type":"Point"}
}