{
  "type": "Feature",
  "properties": {
    "iso:country":"DE",
    "sg:address":"Bielertstr. 14",
    "sg:city":"Leverkusen",
    "sg:phone":"+49 2171/400537",
    "sg:postcode":"51379",
    "sg:province":"Nordrhein-Westfalen",
    "wof:name":"Ev. Pfarramt Bielert",
    "wof:placetype":"venue"
},
  "geometry": {"coordinates":[7.0011849403,51.0711936951],"type":"Point"}
}