{
  "type": "Feature",
  "properties": {
    "iso:country":"DE",
    "sg:address":"Im G\u00e4\u00dfle 8",
    "sg:city":"Albstadt",
    "sg:phone":"+49 7435/1424",
    "sg:postcode":"72459",
    "sg:province":"Baden-W\u00fcrttemberg",
    "wof:name":"Georg Graf Bauschlosserei",
    "wof:placetype":"venue"
},
  "geometry": {"coordinates":[8.930997,48.241261],"type":"Point"}
}