{
  "type": "Feature",
  "properties": {
    "iso:country":"DE",
    "sg:address":"Siemensstr. 10",
    "sg:city":"Ratingen",
    "sg:postcode":"40885",
    "sg:province":"Nordrhein-Westfalen",
    "wof:name":"Delaron Gesellschaft F\u00fcr Liegenschaften Mbh",
    "wof:placetype":"venue"
},
  "geometry": {"coordinates":[6.8262248039,51.3487205505],"type":"Point"}
}