{
  "type": "Feature",
  "properties": {
    "iso:country":"DE",
    "sg:address":"Wilhelm-Schmid-Str. 24",
    "sg:city":"Brackenheim",
    "sg:phone":"+49 7135/2928",
    "sg:postcode":"74336",
    "sg:province":"Baden-W\u00fcrttemberg",
    "wof:name":"K.-h. Und U. Flinspach",
    "wof:placetype":"venue"
},
  "geometry": {"coordinates":[9.083984,49.067009],"type":"Point"}
}