{
  "type": "Feature",
  "properties": {
    "iso:country":"DE",
    "sg:address":"Nordmeerstr. 70",
    "sg:city":"L\u00fcbeck",
    "sg:postcode":"23570",
    "sg:province":"Schleswig-Holstein",
    "wof:name":"Ungeth\u00fcm Ohg",
    "wof:placetype":"venue"
},
  "geometry": {"coordinates":[10.8607616425,53.9660797119],"type":"Point"}
}