{
  "type": "Feature",
  "properties": {
    "iso:country":"DE",
    "sg:address":"Stra\u00dfe des Friedens",
    "sg:city":"Apolda",
    "sg:postcode":"99510",
    "sg:province":"Th\u00fcringen",
    "wof:name":"Aldi Gmbh & Co. Kg",
    "wof:placetype":"venue"
},
  "geometry": {"coordinates":[11.5113801956,51.0225067139],"type":"Point"}
}