{
  "type": "Feature",
  "properties": {
    "iso:country":"DE",
    "sg:address":"Wolfengasse 5",
    "sg:city":"Friedberg",
    "sg:phone":"+49 6031/5738",
    "sg:postcode":"61169",
    "sg:province":"Hessen",
    "wof:name":"Bottega Della Pasta",
    "wof:placetype":"venue"
},
  "geometry": {"coordinates":[8.7542743683,50.3365898132],"type":"Point"}
}