{
  "type": "Feature",
  "properties": {
    "iso:country":"DE",
    "sg:address":"Universit\u00e4tsstr. 2",
    "sg:city":"Witten",
    "sg:phone":"+49 2302/24044",
    "sg:postcode":"58455",
    "sg:province":"Nordrhein-Westfalen",
    "wof:name":"Greif-reisen A. Manthey Gmbh",
    "wof:placetype":"venue"
},
  "geometry": {"coordinates":[7.3080358505,51.4406051636],"type":"Point"}
}