{
  "type": "Feature",
  "properties": {
    "iso:country":"DE",
    "sg:address":"Freisenbruch 4",
    "sg:city":"Bochum",
    "sg:phone":"+49 2327/59613",
    "sg:postcode":"44867",
    "sg:province":"Nordrhein-Westfalen",
    "wof:name":"Joachim Renzel",
    "wof:placetype":"venue"
},
  "geometry": {"coordinates":[7.128151,51.45462],"type":"Point"}
}