{
  "type": "Feature",
  "properties": {
    "iso:country":"DE",
    "sg:address":"Waldeckweg 8",
    "sg:city":"Nagold",
    "sg:phone":"+49 7452",
    "sg:postcode":"72202",
    "sg:province":"Baden-W\u00fcrttemberg",
    "wof:name":"Clown Clip",
    "wof:placetype":"venue"
},
  "geometry": {"coordinates":[8.73,48.553753],"type":"Point"}
}