{
  "type": "Feature",
  "properties": {
    "iso:country":"DE",
    "sg:address":"\u00d6sterreicher Str. 23",
    "sg:city":"Dresden",
    "sg:phone":"+49 351/2591130",
    "sg:postcode":"01279",
    "sg:province":"Sachsen",
    "wof:name":"Dieter Forberger",
    "wof:placetype":"venue"
},
  "geometry": {"coordinates":[13.8359594345,51.0268516541],"type":"Point"}
}