{
  "type": "Feature",
  "properties": {
    "iso:country":"DE",
    "sg:address":"Wittichstr. 5",
    "sg:city":"Darmstadt",
    "sg:phone":"+49 6151/899964",
    "sg:postcode":"64295",
    "sg:province":"Hessen",
    "wof:name":"Junghans Grundst\u00fccksges. Mbh & Co. Kg",
    "wof:placetype":"venue"
},
  "geometry": {"coordinates":[8.6288337708,49.8634223938],"type":"Point"}
}