{
  "type": "Feature",
  "properties": {
    "iso:country":"DE",
    "sg:address":"Schwabacher Str. 48",
    "sg:city":"F\u00fcrth",
    "sg:phone":"+49 911/9774670",
    "sg:postcode":"90762",
    "sg:province":"Bayern",
    "wof:name":"Stempel Eckstein Gmbh",
    "wof:placetype":"venue"
},
  "geometry": {"coordinates":[10.988017,49.472439],"type":"Point"}
}