{
  "type": "Feature",
  "properties": {
    "iso:country":"DE",
    "sg:address":"D\u00fcsseldorfer Str. 14",
    "sg:city":"Frankfurt",
    "sg:phone":"+49 69/2380688",
    "sg:postcode":"60329",
    "sg:province":"Hessen",
    "wof:name":"Garuda Indonesian Airways",
    "wof:placetype":"venue"
},
  "geometry": {"coordinates":[8.662024,50.109074],"type":"Point"}
}