{
  "type": "Feature",
  "properties": {
    "iso:country":"DE",
    "sg:address":"Lehmwandlungsweg 16",
    "sg:city":"Nienburg",
    "sg:phone":"+49 5021/912848",
    "sg:postcode":"31582",
    "sg:province":"Niedersachsen",
    "wof:name":"Wohnpark Nienburg Gmbh",
    "wof:placetype":"venue"
},
  "geometry": {"coordinates":[9.2195672989,52.6258010864],"type":"Point"}
}