{
  "type": "Feature",
  "properties": {
    "iso:country":"DE",
    "sg:address":"Hohenlinden 1",
    "sg:city":"\u00dcberlingen",
    "sg:phone":"+49 7551/61452",
    "sg:postcode":"88662",
    "sg:province":"Baden-W\u00fcrttemberg",
    "wof:name":"Georg Schmid",
    "wof:placetype":"venue"
},
  "geometry": {"coordinates":[9.13604,47.80275],"type":"Point"}
}