{
  "type": "Feature",
  "properties": {
    "iso:country":"DE",
    "sg:address":"Im K\u00e4pfle 4",
    "sg:city":"Aidlingen-Deufringen",
    "sg:postcode":"71134",
    "sg:province":"Baden-W\u00fcrttemberg",
    "wof:name":"Haus-grasy.de",
    "wof:placetype":"venue"
},
  "geometry": {"coordinates":[8.859644,48.679001],"type":"Point"}
}