{
  "type": "Feature",
  "properties": {
    "iso:country":"DE",
    "sg:address":"Hauptstr. 31",
    "sg:city":"Meitingen",
    "sg:phone":"+49 8271/2348",
    "sg:postcode":"86405",
    "sg:province":"Bayern",
    "wof:name":"Neue Post",
    "wof:placetype":"venue"
},
  "geometry": {"coordinates":[10.8498706818,48.5442276001],"type":"Point"}
}