{
  "type": "Feature",
  "properties": {
    "iso:country":"DE",
    "sg:address":"S\u00fchlener Str. 1",
    "sg:city":"Wakendorf I",
    "sg:postcode":"23845",
    "sg:province":"Schleswig-Holstein",
    "wof:name":"Euro Con Waren- Und Vermitt- Lungs Gmbh",
    "wof:placetype":"venue"
},
  "geometry": {"coordinates":[10.3554725647,53.863067627],"type":"Point"}
}