{
  "type": "Feature",
  "properties": {
    "iso:country":"DE",
    "sg:address":"Bitzenstr. 66",
    "sg:city":"Hungen",
    "sg:phone":"+49 6402/6856",
    "sg:postcode":"35410",
    "sg:province":"Hessen",
    "wof:name":"Salzer Und Gunkel",
    "wof:placetype":"venue"
},
  "geometry": {"coordinates":[8.901627,50.474155],"type":"Point"}
}