{
  "type": "Feature",
  "properties": {
    "iso:country":"DE",
    "sg:address":"Hauptstr. 41",
    "sg:city":"Homburg",
    "sg:phone":"+49 6848/1500",
    "sg:postcode":"66424",
    "sg:province":"Saarland",
    "wof:name":"Friedrich Zenker Elektroinstallation",
    "wof:placetype":"venue"
},
  "geometry": {"coordinates":[7.321299,49.267696],"type":"Point"}
}