{
  "type": "Feature",
  "properties": {
    "iso:country":"DE",
    "sg:address":"Rosental 2",
    "sg:city":"Burkersdorf",
    "sg:phone":"+49 4937/3248030",
    "sg:postcode":"09629",
    "sg:province":"Sachsen",
    "wof:name":"Kreative Verpackungen Von Trillenberg",
    "wof:placetype":"venue"
},
  "geometry": {"coordinates":[13.333354,51.000332],"type":"Point"}
}