{
  "type": "Feature",
  "properties": {
    "iso:country":"DE",
    "sg:address":"Stuttgarter Str. 72",
    "sg:city":"Schwieberdingen",
    "sg:phone":"+49 7150/31310",
    "sg:postcode":"71701",
    "sg:province":"Baden-W\u00fcrttemberg",
    "wof:name":"Karl Eberle",
    "wof:placetype":"venue"
},
  "geometry": {"coordinates":[9.081026,48.874859],"type":"Point"}
}