{
  "type": "Feature",
  "properties": {
    "iso:country":"DE",
    "sg:address":"Sch\u00f6nlind 2a",
    "sg:city":"Neukirchen",
    "sg:phone":"+49 9663/2674",
    "sg:postcode":"92259",
    "sg:province":"Bayern",
    "wof:name":"Gerhard Luber Ingenieur",
    "wof:placetype":"venue"
},
  "geometry": {"coordinates":[11.6528291702,49.5180015564],"type":"Point"}
}