{
  "type": "Feature",
  "properties": {
    "iso:country":"DE",
    "sg:address":"Bilsteinweg 1",
    "sg:city":"Lohfelden",
    "sg:phone":"+49 561/519195",
    "sg:postcode":"34253",
    "sg:province":"Hessen",
    "wof:name":"Fritz Henschel",
    "wof:placetype":"venue"
},
  "geometry": {"coordinates":[9.551357,51.286098],"type":"Point"}
}