{
  "type": "Feature",
  "properties": {
    "iso:country":"DE",
    "sg:address":"Hamburger Str. 48-50",
    "sg:city":"Henstedt-Ulzburg",
    "sg:phone":"+49 4193/969531",
    "sg:postcode":"24558",
    "sg:province":"Schleswig-Holstein",
    "wof:name":"Sixt Budget Autovermietung",
    "wof:placetype":"venue"
},
  "geometry": {"coordinates":[9.977642,53.786053],"type":"Point"}
}