{
  "type": "Feature",
  "properties": {
    "iso:country":"DE",
    "sg:address":"Mainstr. 5",
    "sg:city":"Dessau",
    "sg:phone":"+49 340/614143",
    "sg:postcode":"06846",
    "sg:province":"Sachsen-Anhalt",
    "wof:name":"Agthe-k\u00fcchenhandel Karl-heinz Agthe",
    "wof:placetype":"venue"
},
  "geometry": {"coordinates":[12.2285661697,51.8467254639],"type":"Point"}
}