{
  "type": "Feature",
  "properties": {
    "iso:country":"DE",
    "sg:address":"Am Borberg 1",
    "sg:city":"Kirchberg",
    "sg:phone":"+49 37602/65808",
    "sg:postcode":"08107",
    "sg:province":"Sachsen",
    "wof:name":"Frank Weck",
    "wof:placetype":"venue"
},
  "geometry": {"coordinates":[12.5142402649,50.6228027344],"type":"Point"}
}