{
  "type": "Feature",
  "properties": {
    "iso:country":"DE",
    "sg:address":"Regensburger Str. 3",
    "sg:city":"Geisenfeld",
    "sg:phone":"+49 8452/413",
    "sg:postcode":"85290",
    "sg:province":"Bayern",
    "wof:name":"Michael Fr\u00f6schl",
    "wof:placetype":"venue"
},
  "geometry": {"coordinates":[11.6128396988,48.6861114502],"type":"Point"}
}