{
  "type": "Feature",
  "properties": {
    "iso:country":"DE",
    "sg:address":"Studtstr. 1",
    "sg:city":"Bad Kreuznach",
    "sg:postcode":"55543",
    "sg:province":"Rheinland-Pfalz",
    "wof:name":"Studt Gmbh",
    "wof:placetype":"venue"
},
  "geometry": {"coordinates":[7.881452,49.832432],"type":"Point"}
}