{
  "type": "Feature",
  "properties": {
    "iso:country":"DE",
    "sg:address":"Speckweg 23",
    "sg:city":"Mannheim",
    "sg:phone":"+49 621/752116",
    "sg:postcode":"68305",
    "sg:province":"Baden-W\u00fcrttemberg",
    "wof:name":"Sandys Jeans Shop",
    "wof:placetype":"venue"
},
  "geometry": {"coordinates":[8.485583,49.523808],"type":"Point"}
}