{
  "type": "Feature",
  "properties": {
    "iso:country":"DE",
    "sg:address":"Mendelssohnstr. 37",
    "sg:city":"Baldham",
    "sg:phone":"+49 8106/8233",
    "sg:postcode":"85598",
    "sg:province":"Bayern",
    "wof:name":"Richard Mann Architekt",
    "wof:placetype":"venue"
},
  "geometry": {"coordinates":[11.788144,48.107967],"type":"Point"}
}