{
  "type": "Feature",
  "properties": {
    "iso:country":"DE",
    "sg:address":"Bentheimer Str 66",
    "sg:city":"Nordhorn",
    "sg:phone":"+49 5921/994225",
    "sg:postcode":"48529",
    "sg:province":"Niedersachsen",
    "wof:name":"Tcp Pr\u00fcftechnik Gmbh Trading-consulting-progress",
    "wof:placetype":"venue"
},
  "geometry": {"coordinates":[7.073471,52.428383],"type":"Point"}
}