{
  "type": "Feature",
  "properties": {
    "iso:country":"DE",
    "sg:address":"Rathausweg 6",
    "sg:city":"Ertingen",
    "sg:phone":"+49 7371/5156",
    "sg:postcode":"88521",
    "sg:province":"Baden-W\u00fcrttemberg",
    "wof:name":"Karl Ummenhofer Gmbh",
    "wof:placetype":"venue"
},
  "geometry": {"coordinates":[9.4821271896,48.1191291809],"type":"Point"}
}