{
  "type": "Feature",
  "properties": {
    "iso:country":"DE",
    "sg:address":"Wickersbacher Weg 21",
    "sg:city":"Siegen",
    "sg:phone":"+49 271/370196",
    "sg:postcode":"57072",
    "sg:province":"Nordrhein-Westfalen",
    "wof:name":"Wilhelm Flender",
    "wof:placetype":"venue"
},
  "geometry": {"coordinates":[7.980681,50.890129],"type":"Point"}
}