{
  "type": "Feature",
  "properties": {
    "iso:country":"DE",
    "sg:address":"Brarupholz",
    "sg:city":"Scheggerott",
    "sg:phone":"+49 4641/2637",
    "sg:postcode":"24392",
    "sg:province":"Schleswig-Holstein",
    "wof:name":"H.-w. Saxer",
    "wof:placetype":"venue"
},
  "geometry": {"coordinates":[9.79119,54.679787],"type":"Point"}
}