{
  "type": "Feature",
  "properties": {
    "iso:country":"DE",
    "sg:address":"Kirchweg 3",
    "sg:city":"Buchenberg",
    "sg:postcode":"87474",
    "sg:province":"Bayern",
    "wof:name":"Katholisches Pfarramt St. Martin",
    "wof:placetype":"venue"
},
  "geometry": {"coordinates":[10.1194820404,47.7166404724],"type":"Point"}
}