{
  "type": "Feature",
  "properties": {
    "iso:country":"DE",
    "sg:address":"Gr\u00fcnholderstr. 4",
    "sg:city":"Gablingen",
    "sg:phone":"+49 8230/7384",
    "sg:postcode":"86456",
    "sg:province":"Bayern",
    "wof:name":"Kreissparkasse Augsburg",
    "wof:placetype":"venue"
},
  "geometry": {"coordinates":[10.820795,48.455814],"type":"Point"}
}