{
  "type": "Feature",
  "properties": {
    "iso:country":"DE",
    "sg:address":"Neusser Str. 419",
    "sg:city":"K\u00f6ln",
    "sg:postcode":"50733",
    "sg:province":"Nordrhein-Westfalen",
    "wof:name":"Teg Thewaldt Elektro- Gro\u00dfhandel Gmbh & Co. Kg",
    "wof:placetype":"venue"
},
  "geometry": {"coordinates":[6.9514908791,50.9715690613],"type":"Point"}
}