{
  "type": "Feature",
  "properties": {
    "iso:country":"DE",
    "sg:address":"Gro\u00dfbeerenstr. 128",
    "sg:city":"Potsdam",
    "sg:phone":"+49 331/7481000",
    "sg:postcode":"14482",
    "sg:province":"Brandenburg",
    "wof:name":"Foto-hannemann Inh. Lutz Hannemann",
    "wof:placetype":"venue"
},
  "geometry": {"coordinates":[13.108874321,52.3860816956],"type":"Point"}
}