{
  "type": "Feature",
  "properties": {
    "iso:country":"DE",
    "sg:address":"Rennstr. 16",
    "sg:city":"Esslingen",
    "sg:phone":"+49 711/31904122",
    "sg:postcode":"73728",
    "sg:province":"Baden-W\u00fcrttemberg",
    "wof:name":"Heinrich-mayer-haus Elektromuseum Neckarwerke",
    "wof:placetype":"venue"
},
  "geometry": {"coordinates":[9.318254,48.73241],"type":"Point"}
}