{
  "type": "Feature",
  "properties": {
    "iso:country":"DE",
    "sg:address":"Schellgasse 22",
    "sg:city":"Billigheim-Ingenheim",
    "sg:phone":"+49 6349/929383",
    "sg:postcode":"76831",
    "sg:province":"Rheinland-Pfalz",
    "wof:name":"Kurt Merkel",
    "wof:placetype":"venue"
},
  "geometry": {"coordinates":[8.0832080841,49.13489151],"type":"Point"}
}