{
  "type": "Feature",
  "properties": {
    "iso:country":"DE",
    "sg:address":"Untere Hofmark 4",
    "sg:city":"Grattersdorf",
    "sg:phone":"+49 9904/931",
    "sg:postcode":"94541",
    "sg:province":"Bayern",
    "wof:name":"Sonnenwald-reisen Georg Arbinger",
    "wof:placetype":"venue"
},
  "geometry": {"coordinates":[13.1514482498,48.8045387268],"type":"Point"}
}