{
  "type": "Feature",
  "properties": {
    "iso:country":"DE",
    "sg:address":"Scharnhauser Str. 25",
    "sg:city":"Ostfildern",
    "sg:phone":"+49 711/442070",
    "sg:postcode":"73760",
    "sg:province":"Baden-W\u00fcrttemberg",
    "wof:name":"Leitstelle F\u00fcr \u00e4ltere Menschen In Ostfildern",
    "wof:placetype":"venue"
},
  "geometry": {"coordinates":[9.25532,48.7248],"type":"Point"}
}