{
  "type": "Feature",
  "properties": {
    "iso:country":"DE",
    "sg:address":"Volkeningstr. 15",
    "sg:city":"Essen",
    "sg:phone":"+49 201/202000",
    "sg:postcode":"45139",
    "sg:province":"Nordrhein-Westfalen",
    "wof:name":"Ambulanter Fachpflegedienst Arche Noah",
    "wof:placetype":"venue"
},
  "geometry": {"coordinates":[7.024013,51.457546],"type":"Point"}
}