{
  "type": "Feature",
  "properties": {
    "iso:country":"DE",
    "sg:address":"Theodor-Heuss-Allee 38",
    "sg:city":"Hennef",
    "sg:phone":"+49 2242/92990",
    "sg:postcode":"53773",
    "sg:province":"Nordrhein-Westfalen",
    "wof:name":"Bpm-medical Ag",
    "wof:placetype":"venue"
},
  "geometry": {"coordinates":[7.272101,50.774418],"type":"Point"}
}