{
  "type": "Feature",
  "properties": {
    "iso:country":"DE",
    "sg:address":"Wagenweg 15",
    "sg:city":"Aurich",
    "sg:postcode":"26603",
    "sg:province":"Niedersachsen",
    "wof:name":"Schuhdepot Bockstiegel",
    "wof:placetype":"venue"
},
  "geometry": {"coordinates":[7.4697761536,53.4761505127],"type":"Point"}
}