{
  "type": "Feature",
  "properties": {
    "iso:country":"DE",
    "sg:address":"Dielbornstr.",
    "sg:city":"Berg",
    "sg:phone":"+49 2643/8131",
    "sg:postcode":"53505",
    "sg:province":"Rheinland-Pfalz",
    "wof:name":"Hotel Kalenborner H\u00f6he",
    "wof:placetype":"venue"
},
  "geometry": {"coordinates":[6.9439067841,50.5257377625],"type":"Point"}
}