{
  "type": "Feature",
  "properties": {
    "iso:country":"DE",
    "sg:address":"Antonienstr. 5",
    "sg:city":"Aschersleben",
    "sg:phone":"+49 3473/809388",
    "sg:postcode":"06449",
    "sg:province":"Sachsen-Anhalt",
    "wof:name":"Ascania-apotheke Inh. Grit Diron",
    "wof:placetype":"venue"
},
  "geometry": {"coordinates":[11.464806,51.762047],"type":"Point"}
}