{
  "type": "Feature",
  "properties": {
    "iso:country":"DE",
    "sg:address":"Theaterplatz 3",
    "sg:city":"Aachen",
    "sg:phone":"+49 241/35111",
    "sg:postcode":"52062",
    "sg:province":"Nordrhein-Westfalen",
    "wof:name":"Leonidas Pralinen",
    "wof:placetype":"venue"
},
  "geometry": {"coordinates":[6.086933136,50.7730140686],"type":"Point"}
}