{
  "type": "Feature",
  "properties": {
    "iso:country":"DE",
    "sg:address":"Neubr\u00fccker Weg",
    "sg:city":"Didderse",
    "sg:phone":"+49 5373/2486",
    "sg:postcode":"38530",
    "sg:province":"Niedersachsen",
    "wof:name":"Sportgastst\u00e4tte",
    "wof:placetype":"venue"
},
  "geometry": {"coordinates":[10.413725853,52.3806762695],"type":"Point"}
}