{
  "type": "Feature",
  "properties": {
    "iso:country":"DE",
    "sg:address":"Leinenweberstr. 3",
    "sg:city":"K\u00f6ln",
    "sg:phone":"+49 221/2405852",
    "sg:postcode":"50769",
    "sg:province":"Nordrhein-Westfalen",
    "wof:name":"Hydrotrest Spolka Akcyjna Bauunternehmung",
    "wof:placetype":"venue"
},
  "geometry": {"coordinates":[6.862246,51.06596],"type":"Point"}
}