{
  "type": "Feature",
  "properties": {
    "iso:country":"DE",
    "sg:address":"Haarbeckstr. 2",
    "sg:city":"Neukirchen-Vluyn",
    "sg:phone":"+49 2845/31419",
    "sg:postcode":"47506",
    "sg:province":"Nordrhein-Westfalen",
    "wof:name":"Heinz Kaiser",
    "wof:placetype":"venue"
},
  "geometry": {"coordinates":[6.569398,51.449028],"type":"Point"}
}