{
  "type": "Feature",
  "properties": {
    "iso:country":"DE",
    "sg:address":"Industriestr. 9",
    "sg:city":"Schwandorf",
    "sg:phone":"+49 9431/51371",
    "sg:postcode":"92421",
    "sg:province":"Bayern",
    "wof:name":"Thyssen Krupp Materials Ag",
    "wof:placetype":"venue"
},
  "geometry": {"coordinates":[12.1012449265,49.3120536804],"type":"Point"}
}