{
  "type": "Feature",
  "properties": {
    "iso:country":"DE",
    "sg:address":"Innere Brucker Str. 11",
    "sg:city":"Erlangen",
    "sg:phone":"+49 9131/27350",
    "sg:postcode":"91054",
    "sg:province":"Bayern",
    "wof:name":"Western Store Anna Schulz",
    "wof:placetype":"venue"
},
  "geometry": {"coordinates":[11.002575,49.597954],"type":"Point"}
}