{
  "type": "Feature",
  "properties": {
    "iso:country":"DE",
    "sg:address":"Bismarckstr. 70",
    "sg:city":"Aachen",
    "sg:postcode":"52066",
    "sg:province":"Nordrhein-Westfalen",
    "wof:name":"Eisenbahnmuseum Asbach/westerwald",
    "wof:placetype":"venue"
},
  "geometry": {"coordinates":[6.104498,50.768604],"type":"Point"}
}