{
  "type": "Feature",
  "properties": {
    "iso:country":"DE",
    "sg:address":"Industriestr. 10",
    "sg:city":"Bechhofen",
    "sg:phone":"+49 9822/82770",
    "sg:postcode":"91572",
    "sg:province":"Bayern",
    "wof:name":"Lind\u00f6rfer Frischdienst Gmbh",
    "wof:placetype":"venue"
},
  "geometry": {"coordinates":[10.5608825684,49.1631622314],"type":"Point"}
}