{
  "type": "Feature",
  "properties": {
    "iso:country":"DE",
    "sg:address":"Kirchstr. 12",
    "sg:city":"Riedstadt",
    "sg:phone":"+49 6158/975511",
    "sg:postcode":"64560",
    "sg:province":"Hessen",
    "wof:name":"Gemeindeb\u00fccherei Ortsteil Leeheim",
    "wof:placetype":"venue"
},
  "geometry": {"coordinates":[8.444412,49.85717],"type":"Point"}
}