{
  "type": "Feature",
  "properties": {
    "iso:country":"DE",
    "sg:address":"Flattigstr. 23",
    "sg:city":"Greu\u00dfen",
    "sg:phone":"+49 3636/700003",
    "sg:postcode":"99718",
    "sg:province":"Th\u00fcringen",
    "wof:name":"Hett",
    "wof:placetype":"venue"
},
  "geometry": {"coordinates":[10.940268,51.23341],"type":"Point"}
}