{
  "type": "Feature",
  "properties": {
    "iso:country":"DE",
    "sg:address":"Alter Bachweg 9",
    "sg:city":"Bammental",
    "sg:phone":"+49 6223/5176",
    "sg:postcode":"69245",
    "sg:province":"Baden-W\u00fcrttemberg",
    "wof:name":"Draxler Gmbh",
    "wof:placetype":"venue"
},
  "geometry": {"coordinates":[8.7732191086,49.3502388],"type":"Point"}
}