{
  "type": "Feature",
  "properties": {
    "iso:country":"DE",
    "sg:address":"Kirchstr. 6",
    "sg:city":"Kerpen",
    "sg:phone":"+49 2237/3736",
    "sg:postcode":"50171",
    "sg:province":"Nordrhein-Westfalen",
    "wof:name":"G. Lampel",
    "wof:placetype":"venue"
},
  "geometry": {"coordinates":[6.6943130493,50.8691673279],"type":"Point"}
}