{
  "type": "Feature",
  "properties": {
    "iso:country":"DE",
    "sg:address":"Westenfelder Str. 25",
    "sg:city":"Sundern",
    "sg:phone":"+49 2933/2255",
    "sg:postcode":"59846",
    "sg:province":"Nordrhein-Westfalen",
    "wof:name":"Katholisches Pfarramt St. Agatha",
    "wof:placetype":"venue"
},
  "geometry": {"coordinates":[8.0476703644,51.3247070312],"type":"Point"}
}