{
  "type": "Feature",
  "properties": {
    "iso:country":"DE",
    "sg:address":"Teichstr. 5",
    "sg:city":"Neutraubling",
    "sg:phone":"+49 9401/7751",
    "sg:postcode":"93073",
    "sg:province":"Bayern",
    "wof:name":"Sparkasse Neutraubling",
    "wof:placetype":"venue"
},
  "geometry": {"coordinates":[12.19231,48.990215],"type":"Point"}
}