{
  "type": "Feature",
  "properties": {
    "iso:country":"DE",
    "sg:address":"Freiberger Str. 14",
    "sg:city":"Leipzig",
    "sg:phone":"+49 341/9211006",
    "sg:postcode":"04349",
    "sg:province":"Sachsen",
    "wof:name":"Jens Exner",
    "wof:placetype":"venue"
},
  "geometry": {"coordinates":[12.432932,51.375294],"type":"Point"}
}