{
  "type": "Feature",
  "properties": {
    "iso:country":"DE",
    "sg:address":"Vierradener Str. 32",
    "sg:city":"Schwedt",
    "sg:phone":"+49 3332/516965",
    "sg:postcode":"16303",
    "sg:province":"Brandenburg",
    "wof:name":"Lohnsteuerhilfeverein E. V.",
    "wof:placetype":"venue"
},
  "geometry": {"coordinates":[14.2865400314,53.0567588806],"type":"Point"}
}