{
  "type": "Feature",
  "properties": {
    "iso:country":"DE",
    "sg:address":"Bergstr. 4",
    "sg:city":"Bad Bevensen",
    "sg:phone":"+49 5821/3004",
    "sg:postcode":"29549",
    "sg:province":"Niedersachsen",
    "wof:name":"Rotary-club L\u00fcneburg Hermann Frankl",
    "wof:placetype":"venue"
},
  "geometry": {"coordinates":[10.580288887,53.0790405273],"type":"Point"}
}