{
  "type": "Feature",
  "properties": {
    "iso:country":"DE",
    "sg:address":"Herbststr. 9",
    "sg:city":"Sauerlach",
    "sg:phone":"+49 8104/1403",
    "sg:postcode":"82054",
    "sg:province":"Bayern",
    "wof:name":"Herbert Hasler",
    "wof:placetype":"venue"
},
  "geometry": {"coordinates":[11.6603755951,47.9722938538],"type":"Point"}
}