{
  "type": "Feature",
  "properties": {
    "iso:country":"DE",
    "sg:address":"Johann-Sebastian-Bach-Platz 22",
    "sg:city":"Ansbach",
    "sg:phone":"+49 981/5504",
    "sg:postcode":"91522",
    "sg:province":"Bayern",
    "wof:name":"Garant Bautr\u00e4ger Gesellschaft F\u00fcr Kosten-",
    "wof:placetype":"venue"
},
  "geometry": {"coordinates":[10.574642,49.302372],"type":"Point"}
}