{
  "type": "Feature",
  "properties": {
    "iso:country":"DE",
    "sg:address":"Schottstr. 2",
    "sg:city":"Gie\u00dfen",
    "sg:postcode":"35390",
    "sg:province":"Hessen",
    "wof:name":"Tropeninstitut",
    "wof:placetype":"venue"
},
  "geometry": {"coordinates":[8.6775617599,50.5909576416],"type":"Point"}
}