{
  "type": "Feature",
  "properties": {
    "iso:country":"DE",
    "sg:address":"Wilhelmshavener Str. 5",
    "sg:city":"Kiel",
    "sg:phone":"+49 431/8950039",
    "sg:postcode":"24105",
    "sg:province":"Schleswig-Holstein",
    "wof:name":"Dirk Scheelje",
    "wof:placetype":"venue"
},
  "geometry": {"coordinates":[10.1374168396,54.338886261],"type":"Point"}
}