{
  "type": "Feature",
  "properties": {
    "iso:country":"DE",
    "sg:address":"Schmittmannstr. 17",
    "sg:city":"Dernau",
    "sg:phone":"+49 2643/7033",
    "sg:postcode":"53507",
    "sg:province":"Rheinland-Pfalz",
    "wof:name":"Walter Hansen Weinanbau",
    "wof:placetype":"venue"
},
  "geometry": {"coordinates":[7.0425162315,50.5323867798],"type":"Point"}
}