{
  "type": "Feature",
  "properties": {
    "iso:country":"DE",
    "sg:address":"Ederstr. 33",
    "sg:city":"Edertal",
    "sg:postcode":"34549",
    "sg:province":"Hessen",
    "wof:name":"B\u00e4nfer Verwaltungs Gmbh",
    "wof:placetype":"venue"
},
  "geometry": {"coordinates":[9.061709404,51.1782569885],"type":"Point"}
}