{
  "type": "Feature",
  "properties": {
    "iso:country":"DE",
    "sg:address":"Schlutuper Str. 15",
    "sg:city":"L\u00fcbeck",
    "sg:phone":"+49 451/64872",
    "sg:postcode":"23566",
    "sg:province":"Schleswig-Holstein",
    "wof:name":"Karl-heinz Abel",
    "wof:placetype":"venue"
},
  "geometry": {"coordinates":[10.72064,53.864574],"type":"Point"}
}