{
  "type": "Feature",
  "properties": {
    "iso:country":"DE",
    "sg:address":"Am Rittergut 2",
    "sg:city":"L\u00f6bitz",
    "sg:phone":"+49 34422/22477",
    "sg:postcode":"06618",
    "sg:province":"Sachsen-Anhalt",
    "wof:name":"Kionke",
    "wof:placetype":"venue"
},
  "geometry": {"coordinates":[11.9110679626,51.0812416077],"type":"Point"}
}