{
  "type": "Feature",
  "properties": {
    "iso:country":"DE",
    "sg:address":"Am Lautstein 1",
    "sg:city":"Idstein",
    "sg:phone":"+49 6126/2412",
    "sg:postcode":"65510",
    "sg:province":"Hessen",
    "wof:name":"Ewald Wendland",
    "wof:placetype":"venue"
},
  "geometry": {"coordinates":[8.327711,50.21973],"type":"Point"}
}