{
  "type": "Feature",
  "properties": {
    "iso:country":"DE",
    "sg:address":"Ortinstr. 30",
    "sg:city":"K\u00f6nigsfeld",
    "sg:phone":"+49 7725/7739",
    "sg:postcode":"78126",
    "sg:province":"Baden-W\u00fcrttemberg",
    "wof:name":"W. Knoblauch Und Partner Architekten",
    "wof:placetype":"venue"
},
  "geometry": {"coordinates":[8.450443,48.143173],"type":"Point"}
}