{
  "type": "Feature",
  "properties": {
    "iso:country":"DE",
    "sg:address":"Thomas-Mann-Str. 19",
    "sg:city":"Hamburg",
    "sg:phone":"+49 40/6400866",
    "sg:postcode":"22175",
    "sg:province":"Hamburg",
    "wof:name":"Georg Langecker W\u00e4schereianlagen E. K.",
    "wof:placetype":"venue"
},
  "geometry": {"coordinates":[10.116825,53.62711],"type":"Point"}
}