{
  "type": "Feature",
  "properties": {
    "iso:country":"DE",
    "sg:address":"K\u00fchlbrunnenweg 25",
    "sg:city":"St. Georgen",
    "sg:phone":"+49 7724/82476",
    "sg:postcode":"78112",
    "sg:province":"Baden-W\u00fcrttemberg",
    "wof:name":"Rudolf Tress Grabdenkm\u00e4ler",
    "wof:placetype":"venue"
},
  "geometry": {"coordinates":[8.3273897171,48.1297950745],"type":"Point"}
}