{
  "type": "Feature",
  "properties": {
    "iso:country":"DE",
    "sg:address":"Oerlinghauser Str. 180",
    "sg:city":"Bielefeld",
    "sg:phone":"+49 5202/3279",
    "sg:postcode":"33699",
    "sg:province":"Nordrhein-Westfalen",
    "wof:name":"Karl-heinz H\u00f6lken",
    "wof:placetype":"venue"
},
  "geometry": {"coordinates":[8.633063,51.973019],"type":"Point"}
}