{
  "type": "Feature",
  "properties": {
    "iso:country":"DE",
    "sg:address":"Bahnhofstr. 21",
    "sg:city":"Ismaning",
    "sg:phone":"+49 89/968873",
    "sg:postcode":"85737",
    "sg:province":"Bayern",
    "wof:name":"Max Kraus",
    "wof:placetype":"venue"
},
  "geometry": {"coordinates":[11.671331,48.224865],"type":"Point"}
}