{
  "type": "Feature",
  "properties": {
    "iso:country":"DE",
    "sg:address":"Rochlitzer Str. 126",
    "sg:city":"Erlau",
    "sg:postcode":"09306",
    "sg:province":"Sachsen",
    "wof:name":"Maschinen- Und Betriebshilfe- Ring Rochlitz E. V.",
    "wof:placetype":"venue"
},
  "geometry": {"coordinates":[12.944605,51.009415],"type":"Point"}
}