{
  "type": "Feature",
  "properties": {
    "iso:country":"DE",
    "sg:address":"Ziegelbrennerstr. 4",
    "sg:city":"Bremen",
    "sg:phone":"+49 4942/1839670",
    "sg:postcode":"28279",
    "sg:province":"Bremen",
    "wof:name":"Ziehmann Elektrotechnik Gmbh",
    "wof:placetype":"venue"
},
  "geometry": {"coordinates":[8.850403,53.049129],"type":"Point"}
}