{
  "type": "Feature",
  "properties": {
    "iso:country":"DE",
    "sg:address":"Saarwiesenstr.",
    "sg:city":"V\u00f6lklingen",
    "sg:phone":"+49 6898/16071",
    "sg:postcode":"66333",
    "sg:province":"Saarland",
    "wof:name":"Zentramont Baustoff- Mischanlage Gmbh",
    "wof:placetype":"venue"
},
  "geometry": {"coordinates":[6.86463,49.245266],"type":"Point"}
}