{
  "type": "Feature",
  "properties": {
    "iso:country":"DE",
    "sg:address":"Am Springintgut 21 a",
    "sg:city":"L\u00fcneburg",
    "sg:phone":"+49 4131/760808",
    "sg:postcode":"21335",
    "sg:province":"Niedersachsen",
    "wof:name":"Gaack & Partner",
    "wof:placetype":"venue"
},
  "geometry": {"coordinates":[10.4003601074,53.2522315979],"type":"Point"}
}