{
  "type": "Feature",
  "properties": {
    "iso:country":"DE",
    "sg:address":"August-Bebel-Str. 87",
    "sg:city":"Stollberg",
    "sg:phone":"+49 37296/3208",
    "sg:postcode":"09366",
    "sg:province":"Sachsen",
    "wof:name":"G. Bochmann",
    "wof:placetype":"venue"
},
  "geometry": {"coordinates":[12.7644,50.669941],"type":"Point"}
}