{
  "type": "Feature",
  "properties": {
    "iso:country":"DE",
    "sg:address":"Zum Grenzgraben 7",
    "sg:city":"Ubstadt-Weiher",
    "sg:phone":"+49 7251/68274",
    "sg:postcode":"76698",
    "sg:province":"Baden-W\u00fcrttemberg",
    "wof:name":"Peter Wiedemann",
    "wof:placetype":"venue"
},
  "geometry": {"coordinates":[8.6237821579,49.1722946167],"type":"Point"}
}