{
  "type": "Feature",
  "properties": {
    "iso:country":"DE",
    "sg:address":"Dorstener Str. 5",
    "sg:city":"Raesfeld",
    "sg:phone":"+49 2865/10555",
    "sg:postcode":"46348",
    "sg:province":"Nordrhein-Westfalen",
    "wof:name":"Hubert Hinzelmann",
    "wof:placetype":"venue"
},
  "geometry": {"coordinates":[6.841284,51.769196],"type":"Point"}
}