{
  "type": "Feature",
  "properties": {
    "iso:country":"DE",
    "sg:address":"Am Seedamm 6",
    "sg:city":"T\u00fcbingen",
    "sg:phone":"+49 7071/82053",
    "sg:postcode":"72074",
    "sg:province":"Baden-W\u00fcrttemberg",
    "wof:name":"Efo Erwin Fode Vertriebs-gmbh",
    "wof:placetype":"venue"
},
  "geometry": {"coordinates":[9.1022281647,48.547077179],"type":"Point"}
}