{
  "type": "Feature",
  "properties": {
    "iso:country":"DE",
    "sg:address":"Herzogstr. 12",
    "sg:city":"M\u00fcnchen",
    "sg:postcode":"80803",
    "sg:province":"Bayern",
    "wof:name":"Astrid Moeller Rechte Verwertungs Gmbh",
    "wof:placetype":"venue"
},
  "geometry": {"coordinates":[11.5841331482,48.1623420715],"type":"Point"}
}