{
  "type": "Feature",
  "properties": {
    "iso:country":"DE",
    "sg:address":"Beethovenallee 12a",
    "sg:city":"Bonn",
    "sg:phone":"+49 228/820090",
    "sg:postcode":"53173",
    "sg:province":"Nordrhein-Westfalen",
    "wof:name":"Konsularabteilung Des Volksb\u00fcros Von Libyen",
    "wof:placetype":"venue"
},
  "geometry": {"coordinates":[7.1577701569,50.686832428],"type":"Point"}
}