{
  "type": "Feature",
  "properties": {
    "iso:country":"DE",
    "sg:address":"Fischergrube 23",
    "sg:city":"L\u00fcbeck",
    "sg:phone":"+49 451/75456",
    "sg:postcode":"23552",
    "sg:province":"Schleswig-Holstein",
    "wof:name":"Fischers Clubn Pub",
    "wof:placetype":"venue"
},
  "geometry": {"coordinates":[10.685792923,53.8704452515],"type":"Point"}
}