{
  "type": "Feature",
  "properties": {
    "iso:country":"DE",
    "sg:address":"Berliner Str. 46",
    "sg:city":"Hennigsdorf",
    "sg:phone":"+49 3302/50470",
    "sg:postcode":"16761",
    "sg:province":"Brandenburg",
    "wof:name":"Bergsdorf Und Knaust",
    "wof:placetype":"venue"
},
  "geometry": {"coordinates":[13.205332756,52.6450653076],"type":"Point"}
}