{
  "type": "Feature",
  "properties": {
    "iso:country":"DE",
    "sg:address":"Echinger Str. 12",
    "sg:city":"Neufahrn",
    "sg:phone":"+49 8165/939962",
    "sg:postcode":"85375",
    "sg:province":"Bayern",
    "wof:name":"Ugr Travel-service Gmbh Urlaubs- Und Gesch\u00e4fts-",
    "wof:placetype":"venue"
},
  "geometry": {"coordinates":[11.6616258621,48.3123092651],"type":"Point"}
}