{
  "type": "Feature",
  "properties": {
    "iso:country":"DE",
    "sg:address":"Niederstadt 22",
    "sg:city":"Sontra",
    "sg:phone":"+49 5653/7841",
    "sg:postcode":"36205",
    "sg:province":"Hessen",
    "wof:name":"M. Fernau & Sohn Gmbh & Co. Kg",
    "wof:placetype":"venue"
},
  "geometry": {"coordinates":[9.935874939,51.0707626343],"type":"Point"}
}