{
  "type": "Feature",
  "properties": {
    "iso:country":"DE",
    "sg:address":"Kettelerstr. 23",
    "sg:city":"Seligenstadt",
    "sg:phone":"+49 7666/2225",
    "sg:postcode":"63500",
    "sg:province":"Hessen",
    "wof:name":"U. Wolz",
    "wof:placetype":"venue"
},
  "geometry": {"coordinates":[9.001813,50.040783],"type":"Point"}
}