{
  "type": "Feature",
  "properties": {
    "iso:country":"DE",
    "sg:address":"Stotzstr. 35",
    "sg:city":"Kornwestheim",
    "sg:phone":"+49 7154/24178",
    "sg:postcode":"70806",
    "sg:province":"Baden-W\u00fcrttemberg",
    "wof:name":"Ulrich Hoch",
    "wof:placetype":"venue"
},
  "geometry": {"coordinates":[9.181715,48.861012],"type":"Point"}
}