{
  "type": "Feature",
  "properties": {
    "iso:country":"DE",
    "sg:address":"Erich-Wolf-Str. 18",
    "sg:city":"Hausen",
    "sg:phone":"+49 6022/25653",
    "sg:postcode":"63840",
    "sg:province":"Bayern",
    "wof:name":"Verhoeven Handelsgesellschaft Mbh",
    "wof:placetype":"venue"
},
  "geometry": {"coordinates":[9.2127819061,49.8742179871],"type":"Point"}
}