{
  "type": "Feature",
  "properties": {
    "iso:country":"DE",
    "sg:address":"S\u00fcdring 124",
    "sg:city":"Mainz",
    "sg:phone":"+49 6131/331179",
    "sg:postcode":"55128",
    "sg:province":"Rheinland-Pfalz",
    "wof:name":"Wolfgang Mayer Rechtsanwalt",
    "wof:placetype":"venue"
},
  "geometry": {"coordinates":[8.242931366,49.9719161987],"type":"Point"}
}