{
  "type": "Feature",
  "properties": {
    "iso:country":"DE",
    "sg:address":"Kurzhuberstr. 2",
    "sg:city":"M\u00fcnchen",
    "sg:phone":"+49 89/421189",
    "sg:postcode":"81825",
    "sg:province":"Bayern",
    "wof:name":"Objekta Produktions- Und Handelsgesellschaft F\u00fcr",
    "wof:placetype":"venue"
},
  "geometry": {"coordinates":[11.665796,48.121967],"type":"Point"}
}