{
  "type": "Feature",
  "properties": {
    "iso:country":"DE",
    "sg:address":"Von-Tresckow-Str. 10",
    "sg:city":"Fulda",
    "sg:phone":"+49 661/64900",
    "sg:postcode":"36037",
    "sg:province":"Hessen",
    "wof:name":"Erich Pabsch Ingenieur",
    "wof:placetype":"venue"
},
  "geometry": {"coordinates":[9.6970367432,50.5596923828],"type":"Point"}
}