{
  "type": "Feature",
  "properties": {
    "iso:country":"DE",
    "sg:address":"Prinzregentenstr. 94",
    "sg:city":"Rosenheim",
    "sg:phone":"+49 8031/88030",
    "sg:postcode":"83024",
    "sg:province":"Bayern",
    "wof:name":"Vergleichszahlen F\u00fcr Berechnung Privater Leistung",
    "wof:placetype":"venue"
},
  "geometry": {"coordinates":[12.106355,47.86422],"type":"Point"}
}