{
  "type": "Feature",
  "properties": {
    "iso:country":"DE",
    "sg:address":"Pestalozzistr. 22",
    "sg:city":"Frankfurt",
    "sg:phone":"+49 69/455801",
    "sg:postcode":"60385",
    "sg:province":"Hessen",
    "wof:name":"Alexander M\u00fcller",
    "wof:placetype":"venue"
},
  "geometry": {"coordinates":[8.7137928009,50.1271629333],"type":"Point"}
}