{
  "type": "Feature",
  "properties": {
    "iso:country":"DE",
    "sg:address":"Winterberger Str. 36",
    "sg:city":"Lennestadt",
    "sg:phone":"+49 2723/91520",
    "sg:postcode":"57368",
    "sg:province":"Nordrhein-Westfalen",
    "wof:name":"Hotel Voss",
    "wof:placetype":"venue"
},
  "geometry": {"coordinates":[8.1659173965,51.1175804138],"type":"Point"}
}