{
  "type": "Feature",
  "properties": {
    "iso:country":"DE",
    "sg:address":"Blumenstr. 6",
    "sg:city":"Waldaschaff",
    "sg:phone":"+49 6095/2866",
    "sg:postcode":"63857",
    "sg:province":"Bayern",
    "wof:name":"Bauteam Ab Gmbh",
    "wof:placetype":"venue"
},
  "geometry": {"coordinates":[9.29053,49.974174],"type":"Point"}
}