{
  "type": "Feature",
  "properties": {
    "iso:country":"DE",
    "sg:address":"Bismarckstr. 83",
    "sg:city":"Berlin",
    "sg:phone":"+49 30/31868850",
    "sg:postcode":"10627",
    "sg:province":"Berlin",
    "wof:name":"City-gate Immobilien Gmbh",
    "wof:placetype":"venue"
},
  "geometry": {"coordinates":[13.3061084747,52.5113563538],"type":"Point"}
}