{
  "type": "Feature",
  "properties": {
    "iso:country":"DE",
    "sg:address":"Hebelstr. 4",
    "sg:city":"Ebersbach",
    "sg:phone":"+49 7163/4658",
    "sg:postcode":"73061",
    "sg:province":"Baden-W\u00fcrttemberg",
    "wof:name":"B. Geyer Immobilienmakler",
    "wof:placetype":"venue"
},
  "geometry": {"coordinates":[9.5404901505,48.7105140686],"type":"Point"}
}