{
  "type": "Feature",
  "properties": {
    "iso:country":"DE",
    "sg:address":"Auf der H\u00fcls 205",
    "sg:city":"Aachen",
    "sg:postcode":"52068",
    "sg:province":"Nordrhein-Westfalen",
    "wof:name":"Junghans Wolle",
    "wof:placetype":"venue"
},
  "geometry": {"coordinates":[6.134736,50.780426],"type":"Point"}
}