{
  "type": "Feature",
  "properties": {
    "iso:country":"DE",
    "sg:address":"Am Tipkenhoog 7",
    "sg:city":"Sylt-Ost",
    "sg:postcode":"25980",
    "sg:province":"Schleswig-Holstein",
    "wof:name":"Labor F\u00fcr Technik Dr. Beyschlag Gmbh",
    "wof:placetype":"venue"
},
  "geometry": {"coordinates":[8.376999,54.892738],"type":"Point"}
}