{
  "type": "Feature",
  "properties": {
    "iso:country":"DE",
    "sg:address":"Bayreuther Str. 46",
    "sg:city":"Gr\u00e4fenberg",
    "sg:phone":"+49 9192/1495",
    "sg:postcode":"91322",
    "sg:province":"Bayern",
    "wof:name":"Schmidt-transporte Ohg",
    "wof:placetype":"venue"
},
  "geometry": {"coordinates":[11.2599382401,49.6461791992],"type":"Point"}
}