{
  "type": "Feature",
  "properties": {
    "iso:country":"DE",
    "sg:address":"Gl\u00fcckaufstr. 45",
    "sg:city":"Dortmund",
    "sg:phone":"+49 231/8400100",
    "sg:postcode":"44145",
    "sg:province":"Nordrhein-Westfalen",
    "wof:name":"Roland Transport Gmbh",
    "wof:placetype":"venue"
},
  "geometry": {"coordinates":[7.4640197754,51.5264091492],"type":"Point"}
}