{
  "type": "Feature",
  "properties": {
    "iso:country":"DE",
    "sg:address":"Holzgraben 17 - 19",
    "sg:city":"Aachen",
    "sg:phone":"+49 241/28851",
    "sg:postcode":"52062",
    "sg:province":"Nordrhein-Westfalen",
    "wof:name":"Uhren Posmik Gmbh",
    "wof:placetype":"venue"
},
  "geometry": {"coordinates":[6.088039875,50.775718689],"type":"Point"}
}