{
  "type": "Feature",
  "properties": {
    "iso:country":"DE",
    "sg:address":"Plettenbergstr. 40",
    "sg:city":"Stuttgart",
    "sg:phone":"+49 711/4800663",
    "sg:postcode":"70186",
    "sg:province":"Baden-W\u00fcrttemberg",
    "wof:name":"Ois Ortmann E. K.",
    "wof:placetype":"venue"
},
  "geometry": {"coordinates":[9.2163228989,48.7784347534],"type":"Point"}
}