{
  "type": "Feature",
  "properties": {
    "iso:country":"DE",
    "sg:address":"K\u00e4hlerstr. 1",
    "sg:city":"Buxtehude",
    "sg:phone":"+49 4161/81665",
    "sg:postcode":"21614",
    "sg:province":"Niedersachsen",
    "wof:name":"Klaus-hinrich Behnken",
    "wof:placetype":"venue"
},
  "geometry": {"coordinates":[9.680179,53.467205],"type":"Point"}
}