{
  "type": "Feature",
  "properties": {
    "iso:country":"DE",
    "sg:address":"Aresinger Str. 2 a",
    "sg:city":"T\u00fcrkenfeld",
    "sg:postcode":"82299",
    "sg:province":"Bayern",
    "wof:name":"Cnb Gesellschaft F\u00fcr Computer- Und Netzwerkbetreuung Mbh",
    "wof:placetype":"venue"
},
  "geometry": {"coordinates":[11.0827283859,48.1056556702],"type":"Point"}
}