{
  "type": "Feature",
  "properties": {
    "iso:country":"DE",
    "sg:address":"Reeseberg 62",
    "sg:city":"Hamburg",
    "sg:phone":"+49 40/7633131",
    "sg:postcode":"21079",
    "sg:province":"Hamburg",
    "wof:name":"Reeseberg-apotheke",
    "wof:placetype":"venue"
},
  "geometry": {"coordinates":[9.993866,53.446239],"type":"Point"}
}