{
  "type": "Feature",
  "properties": {
    "iso:country":"DE",
    "sg:address":"Keusgasse 37",
    "sg:city":"Roetgen",
    "sg:phone":"+49 2471/2420",
    "sg:postcode":"52159",
    "sg:province":"Nordrhein-Westfalen",
    "wof:name":"Dieter Lux",
    "wof:placetype":"venue"
},
  "geometry": {"coordinates":[6.21139,50.646721],"type":"Point"}
}