{
  "type": "Feature",
  "properties": {
    "iso:country":"DE",
    "sg:address":"Waldstr 8",
    "sg:city":"Karlsruhe",
    "sg:phone":"+49 721/20724",
    "sg:postcode":"76133",
    "sg:province":"Baden-W\u00fcrttemberg",
    "wof:name":"Druckerei Else Berenz",
    "wof:placetype":"venue"
},
  "geometry": {"coordinates":[8.3992767334,49.0111732483],"type":"Point"}
}