{
  "type": "Feature",
  "properties": {
    "iso:country":"DE",
    "sg:address":"Braker Mitte 9",
    "sg:city":"Lemgo",
    "sg:phone":"+49 5261/88412",
    "sg:postcode":"32657",
    "sg:province":"Nordrhein-Westfalen",
    "wof:name":"Petra Br\u00e4chtker",
    "wof:placetype":"venue"
},
  "geometry": {"coordinates":[8.9210882187,52.016368866],"type":"Point"}
}