{
  "type": "Feature",
  "properties": {
    "iso:country":"DE",
    "sg:address":"Wartburgstr. 52",
    "sg:city":"Berlin",
    "sg:phone":"+49 30/7842616",
    "sg:postcode":"10823",
    "sg:province":"Berlin",
    "wof:name":"T. Hernadi Und B. Janitzek Architekten",
    "wof:placetype":"venue"
},
  "geometry": {"coordinates":[13.3513031006,52.4873199463],"type":"Point"}
}