{
  "type": "Feature",
  "properties": {
    "iso:country":"DE",
    "sg:address":"Nelkenweg 6",
    "sg:city":"Linden",
    "sg:phone":"+49 6403/63610",
    "sg:postcode":"35440",
    "sg:province":"Hessen",
    "wof:name":"Lieselotte Roth Krankengymnastin",
    "wof:placetype":"venue"
},
  "geometry": {"coordinates":[8.68099,50.530479],"type":"Point"}
}