{
  "type": "Feature",
  "properties": {
    "iso:country":"DE",
    "sg:address":"Hegelstr. 51",
    "sg:city":"Stuttgart",
    "sg:postcode":"70174",
    "sg:province":"Baden-W\u00fcrttemberg",
    "wof:name":"Verwaltungsgesellschaft Hafner Gmbh",
    "wof:placetype":"venue"
},
  "geometry": {"coordinates":[9.160867,48.784298],"type":"Point"}
}