{
  "type": "Feature",
  "properties": {
    "iso:country":"DE",
    "sg:address":"Frankfurter Str. 43",
    "sg:city":"Kelkheim",
    "sg:phone":"+49 6195/73251",
    "sg:postcode":"65779",
    "sg:province":"Hessen",
    "wof:name":"City Club",
    "wof:placetype":"venue"
},
  "geometry": {"coordinates":[8.452138,50.13414],"type":"Point"}
}