{
  "type": "Feature",
  "properties": {
    "iso:country":"DE",
    "sg:address":"Schultenstr. 2",
    "sg:city":"Mettingen",
    "sg:phone":"+49 5452/2389",
    "sg:postcode":"49497",
    "sg:province":"Nordrhein-Westfalen",
    "wof:name":"Gustav Philipp",
    "wof:placetype":"venue"
},
  "geometry": {"coordinates":[7.781249,52.319546],"type":"Point"}
}