{
  "type": "Feature",
  "properties": {
    "iso:country":"DE",
    "sg:address":"Neuetorstr. 5",
    "sg:city":"Hameln",
    "sg:phone":"+49 5151/560791",
    "sg:postcode":"31785",
    "sg:province":"Niedersachsen",
    "wof:name":"Balk",
    "wof:placetype":"venue"
},
  "geometry": {"coordinates":[9.355725,52.106812],"type":"Point"}
}