{
  "type": "Feature",
  "properties": {
    "iso:country":"DE",
    "sg:address":"Robert-Bosch-Str. 19",
    "sg:city":"Waldstetten",
    "sg:phone":"+49 7171/949383",
    "sg:postcode":"73550",
    "sg:province":"Baden-W\u00fcrttemberg",
    "wof:name":"Motiv Schmuck Gmbh",
    "wof:placetype":"venue"
},
  "geometry": {"coordinates":[9.833729744,48.7701301575],"type":"Point"}
}