{
  "type": "Feature",
  "properties": {
    "iso:country":"DE",
    "sg:address":"Steinstr. 41",
    "sg:city":"Kaiserslautern",
    "sg:phone":"+49 631/92807",
    "sg:postcode":"67657",
    "sg:province":"Rheinland-Pfalz",
    "wof:name":"Tao Zahner",
    "wof:placetype":"venue"
},
  "geometry": {"coordinates":[7.774037,49.447174],"type":"Point"}
}