{
  "type": "Feature",
  "properties": {
    "iso:country":"DE",
    "sg:address":"Saumweg 13a",
    "sg:city":"Illertissen",
    "sg:phone":"+49 7303/2722",
    "sg:postcode":"89257",
    "sg:province":"Bayern",
    "wof:name":"G. Schrapp Kg",
    "wof:placetype":"venue"
},
  "geometry": {"coordinates":[10.0997934341,48.2294120789],"type":"Point"}
}