{
  "type": "Feature",
  "properties": {
    "iso:country":"DE",
    "sg:address":"Amthausstr. 1",
    "sg:city":"Karlsruhe",
    "sg:phone":"+49 721/919500",
    "sg:postcode":"76227",
    "sg:province":"Baden-W\u00fcrttemberg",
    "wof:name":"Reiseb\u00fcro Ronald Blattner Gmbh & Co. Kg",
    "wof:placetype":"venue"
},
  "geometry": {"coordinates":[8.471830368,48.9990882874],"type":"Point"}
}