{
  "type": "Feature",
  "properties": {
    "iso:country":"DE",
    "sg:address":"Am Anger 2",
    "sg:city":"Bad K\u00f6nigshofen",
    "sg:phone":"+49 9761/39056",
    "sg:postcode":"97631",
    "sg:province":"Bayern",
    "wof:name":"Michael Heusinger",
    "wof:placetype":"venue"
},
  "geometry": {"coordinates":[10.46766,50.29932],"type":"Point"}
}