{
  "type": "Feature",
  "properties": {
    "iso:country":"DE",
    "sg:address":"Ledermarkt 1",
    "sg:city":"Dinkelsb\u00fchl",
    "sg:phone":"+49 9851/2125",
    "sg:postcode":"91550",
    "sg:province":"Bayern",
    "wof:name":"Rainer Foltin Rechtsanwalt",
    "wof:placetype":"venue"
},
  "geometry": {"coordinates":[10.3205852509,49.0689735413],"type":"Point"}
}