{
  "type": "Feature",
  "properties": {
    "iso:country":"DE",
    "sg:address":"Essenberger Str. 193d",
    "sg:city":"Moers",
    "sg:phone":"+49 2841/502876",
    "sg:postcode":"47443",
    "sg:province":"Nordrhein-Westfalen",
    "wof:name":"Paul Otto",
    "wof:placetype":"venue"
},
  "geometry": {"coordinates":[6.6711101532,51.4443893433],"type":"Point"}
}