{
  "type": "Feature",
  "properties": {
    "iso:country":"DE",
    "sg:address":"Gartenstr. 12",
    "sg:city":"Fellbach",
    "sg:phone":"+49 711/581574",
    "sg:postcode":"70734",
    "sg:province":"Baden-W\u00fcrttemberg",
    "wof:name":"Rolf W\u00e4lde",
    "wof:placetype":"venue"
},
  "geometry": {"coordinates":[9.276,48.802505],"type":"Point"}
}