{
  "type": "Feature",
  "properties": {
    "iso:country":"DE",
    "sg:address":"Am Rathaus 6",
    "sg:city":"Steinbach",
    "sg:phone":"+49 6171/85510",
    "sg:postcode":"61449",
    "sg:province":"Hessen",
    "wof:name":"Stephan Wietschorke",
    "wof:placetype":"venue"
},
  "geometry": {"coordinates":[8.5764331818,50.1676139832],"type":"Point"}
}