{
  "type": "Feature",
  "properties": {
    "iso:country":"DE",
    "sg:address":"Bayertra\u00dfe 6",
    "sg:city":"Duisburg",
    "sg:phone":"+49 2151/402199",
    "sg:postcode":"47239",
    "sg:province":"Nordrhein-Westfalen",
    "wof:name":"Kostenlose Sms - Klingelt\u00f6ne & Logos",
    "wof:placetype":"venue"
},
  "geometry": {"coordinates":[6.659414,51.397518],"type":"Point"}
}