{
  "type": "Feature",
  "properties": {
    "iso:country":"DE",
    "sg:address":"D\u00f6rnhagener Str. 5",
    "sg:city":"Guxhagen",
    "sg:phone":"+49 5665/2037",
    "sg:postcode":"34302",
    "sg:province":"Hessen",
    "wof:name":"Schwanen-apotheke Rudolf Verres",
    "wof:placetype":"venue"
},
  "geometry": {"coordinates":[9.482556,51.204819],"type":"Point"}
}