{
  "type": "Feature",
  "properties": {
    "iso:country":"DE",
    "sg:address":"Pillauer Str. 72",
    "sg:city":"Hamburg",
    "sg:phone":"+49 40/6958058",
    "sg:postcode":"22047",
    "sg:province":"Hamburg",
    "wof:name":"Dezent Nadia Meyer E. Kfr.",
    "wof:placetype":"venue"
},
  "geometry": {"coordinates":[10.0876808167,53.5943641663],"type":"Point"}
}