{
  "type": "Feature",
  "properties": {
    "iso:country":"DE",
    "sg:address":"Osterlange 9",
    "sg:city":"Elxleben",
    "sg:phone":"+49 36201/8120",
    "sg:postcode":"99189",
    "sg:province":"Th\u00fcringen",
    "wof:name":"Jungheinrich Ag",
    "wof:placetype":"venue"
},
  "geometry": {"coordinates":[10.9402866364,51.0488166809],"type":"Point"}
}