{
  "type": "Feature",
  "properties": {
    "iso:country":"DE",
    "sg:address":"K\u00fcchelstr. 1 A",
    "sg:city":"Bamberg",
    "sg:phone":"+49 951/203385",
    "sg:postcode":"96047",
    "sg:province":"Bayern",
    "wof:name":"Dr. Med. Ernst Trebin",
    "wof:placetype":"venue"
},
  "geometry": {"coordinates":[10.8983602524,49.8895111084],"type":"Point"}
}