{
  "type": "Feature",
  "properties": {
    "iso:country":"DE",
    "sg:address":"Kirchenstr. 10",
    "sg:city":"Elztal",
    "sg:phone":"+49 6261/2765",
    "sg:postcode":"74834",
    "sg:province":"Baden-W\u00fcrttemberg",
    "wof:name":"Katholisches Pfarramt St. Maria",
    "wof:placetype":"venue"
},
  "geometry": {"coordinates":[9.1920089722,49.3845062256],"type":"Point"}
}