{
  "type": "Feature",
  "properties": {
    "iso:country":"DE",
    "sg:address":"Pfullendorfer Str. 38",
    "sg:city":"Krauchenwies",
    "sg:phone":"+49 7576/843",
    "sg:postcode":"72505",
    "sg:province":"Baden-W\u00fcrttemberg",
    "wof:name":"Ralph Lutz",
    "wof:placetype":"venue"
},
  "geometry": {"coordinates":[9.2611732483,47.9818687439],"type":"Point"}
}