{
  "type": "Feature",
  "properties": {
    "iso:country":"DE",
    "sg:address":"Wunsiedler Str 14",
    "sg:city":"Kemnath",
    "sg:phone":"+49 9642/70990",
    "sg:postcode":"95478",
    "sg:province":"Bayern",
    "wof:name":"Edi Ganssm\u00fcller Vertriebs Gmbh",
    "wof:placetype":"venue"
},
  "geometry": {"coordinates":[11.8914260864,49.8722343445],"type":"Point"}
}