{
  "type": "Feature",
  "properties": {
    "iso:country":"DE",
    "sg:address":"Hochburger Str. 25",
    "sg:city":"Emmendingen",
    "sg:postcode":"79312",
    "sg:province":"Baden-W\u00fcrttemberg",
    "wof:name":"Oliver Gottschling Gmbh",
    "wof:placetype":"venue"
},
  "geometry": {"coordinates":[7.8539948463,48.1209754944],"type":"Point"}
}