{
  "type": "Feature",
  "properties": {
    "iso:country":"DE",
    "sg:address":"Sandbauernhof",
    "sg:city":"L\u00fcbow",
    "sg:phone":"+49 3841/785830",
    "sg:postcode":"23972",
    "sg:province":"Mecklenburg-Vorpommern",
    "wof:name":"Acalor Technik Scheel Kg",
    "wof:placetype":"venue"
},
  "geometry": {"coordinates":[11.465007,53.842522],"type":"Point"}
}