{
  "type": "Feature",
  "properties": {
    "iso:country":"DE",
    "sg:address":"Schwibbogenplatz 2c",
    "sg:city":"Augsburg",
    "sg:phone":"+49 821/556552",
    "sg:postcode":"86153",
    "sg:province":"Bayern",
    "wof:name":"Rudolf Jarschel \u00dcbersetzungsb\u00fcro",
    "wof:placetype":"venue"
},
  "geometry": {"coordinates":[10.905627,48.362652],"type":"Point"}
}