{
  "type": "Feature",
  "properties": {
    "iso:country":"DE",
    "sg:address":"Hermannstr. 7",
    "sg:city":"Lauchr\u00f6den",
    "sg:phone":"+49 36927/90729",
    "sg:postcode":"99819",
    "sg:province":"Th\u00fcringen",
    "wof:name":"Horst Wendorff",
    "wof:placetype":"venue"
},
  "geometry": {"coordinates":[10.156143,50.991753],"type":"Point"}
}