{
  "type": "Feature",
  "properties": {
    "iso:country":"DE",
    "sg:address":"Im Gewerbepark 19 A",
    "sg:city":"Regensburg",
    "sg:phone":"+49 941/47059",
    "sg:postcode":"93059",
    "sg:province":"Bayern",
    "wof:name":"Leop. Siegle Gmbh & Co.",
    "wof:placetype":"venue"
},
  "geometry": {"coordinates":[12.125785,49.03001],"type":"Point"}
}