{
  "type": "Feature",
  "properties": {
    "iso:country":"DE",
    "sg:address":"Ferdinand-von-Steinbeis-Ring 13",
    "sg:city":"Sternenfels",
    "sg:phone":"+49 7045/96170",
    "sg:postcode":"75447",
    "sg:province":"Baden-W\u00fcrttemberg",
    "wof:name":"Ober\u00fcber Pr\u00e4zison Gmbh",
    "wof:placetype":"venue"
},
  "geometry": {"coordinates":[8.842247,49.053837],"type":"Point"}
}