{
  "type": "Feature",
  "properties": {
    "iso:country":"DE",
    "sg:address":"Weststr. 30-34",
    "sg:city":"Aachen",
    "sg:phone":"+49 241/88770",
    "sg:postcode":"52074",
    "sg:province":"Nordrhein-Westfalen",
    "wof:name":"Ludwig Mohren Kg",
    "wof:placetype":"venue"
},
  "geometry": {"coordinates":[6.0606241226,50.7714767456],"type":"Point"}
}