{
  "type": "Feature",
  "properties": {
    "iso:country":"DE",
    "sg:address":"Weg Beim J\u00e4ger 206",
    "sg:city":"Hamburg",
    "sg:phone":"+49 40/500670",
    "sg:postcode":"22335",
    "sg:province":"Hamburg",
    "wof:name":"J.h. Bachmann Gmbh",
    "wof:placetype":"venue"
},
  "geometry": {"coordinates":[10.0070199966,53.6230583191],"type":"Point"}
}