{
  "type": "Feature",
  "properties": {
    "iso:country":"DE",
    "sg:address":"Im Bungert 10",
    "sg:city":"Nittel",
    "sg:phone":"+49 6584/592",
    "sg:postcode":"54453",
    "sg:province":"Rheinland-Pfalz",
    "wof:name":"Wolfgang Billen Steuerberater",
    "wof:placetype":"venue"
},
  "geometry": {"coordinates":[6.4497461319,49.6503677368],"type":"Point"}
}