{
  "type": "Feature",
  "properties": {
    "iso:country":"DE",
    "sg:address":"Melibocusstr. 35B",
    "sg:city":"Frankfurt",
    "sg:phone":"+49 69/6771333",
    "sg:postcode":"60528",
    "sg:province":"Hessen",
    "wof:name":"Eiscafe San Marco",
    "wof:placetype":"venue"
},
  "geometry": {"coordinates":[8.638665,50.084145],"type":"Point"}
}