{
  "type": "Feature",
  "properties": {
    "iso:country":"DE",
    "sg:address":"Erasmusstr. 15",
    "sg:city":"D\u00fcsseldorf",
    "sg:postcode":"40223",
    "sg:province":"Nordrhein-Westfalen",
    "wof:name":"Karpat Gmbh",
    "wof:placetype":"venue"
},
  "geometry": {"coordinates":[6.782597065,51.2073707581],"type":"Point"}
}