{
  "type": "Feature",
  "properties": {
    "iso:country":"DE",
    "sg:address":"Ismaninger Str. 76",
    "sg:city":"M\u00fcnchen",
    "sg:phone":"+49 89/9829453",
    "sg:postcode":"81675",
    "sg:province":"Bayern",
    "wof:name":"Bernd Von Dewitz",
    "wof:placetype":"venue"
},
  "geometry": {"coordinates":[11.6015853882,48.1437988281],"type":"Point"}
}