{
  "type": "Feature",
  "properties": {
    "iso:country":"DE",
    "sg:address":"Bahnhofstr. 7",
    "sg:city":"Allendorf",
    "sg:phone":"+49 6452/1800",
    "sg:postcode":"35108",
    "sg:province":"Hessen",
    "wof:name":"Edertal-apotheke",
    "wof:placetype":"venue"
},
  "geometry": {"coordinates":[8.672381,51.026562],"type":"Point"}
}