{
  "type": "Feature",
  "properties": {
    "iso:country":"DE",
    "sg:address":"Dorfstr. 6",
    "sg:city":"Delingsdorf",
    "sg:phone":"+49 4532/6930",
    "sg:postcode":"22941",
    "sg:province":"Schleswig-Holstein",
    "wof:name":"G\u00e4stehaus J\u00fcrgen K\u00e4selau",
    "wof:placetype":"venue"
},
  "geometry": {"coordinates":[10.2541284561,53.7087364197],"type":"Point"}
}