{
  "type": "Feature",
  "properties": {
    "iso:country":"DE",
    "sg:address":"Ottmaringer Str. 1a",
    "sg:city":"Kissing",
    "sg:phone":"+49 8233",
    "sg:postcode":"86438",
    "sg:province":"Bayern",
    "wof:name":"Brunner Baumfaellungen",
    "wof:placetype":"venue"
},
  "geometry": {"coordinates":[10.990522,48.298954],"type":"Point"}
}