{
  "type": "Feature",
  "properties": {
    "iso:country":"DE",
    "sg:address":"Wirtsgasse 7",
    "sg:city":"Buch a. Wald",
    "sg:phone":"+49 9867/1824",
    "sg:postcode":"91592",
    "sg:province":"Bayern",
    "wof:name":"Fun Pizzeria Alter Schwan",
    "wof:placetype":"venue"
},
  "geometry": {"coordinates":[-69.1025466919,44.4961700439],"type":"Point"}
}