{
  "type": "Feature",
  "properties": {
    "iso:country":"DE",
    "sg:address":"Bergstr. 11",
    "sg:city":"Stockelsdorf",
    "sg:postcode":"23617",
    "sg:province":"Schleswig-Holstein",
    "wof:name":"W. Ziolek",
    "wof:placetype":"venue"
},
  "geometry": {"coordinates":[10.6557970047,53.9009513855],"type":"Point"}
}