{
  "type": "Feature",
  "properties": {
    "iso:country":"DE",
    "sg:address":"An der Hummerei 8",
    "sg:city":"Lichtenfels",
    "sg:phone":"+49 9571/3290",
    "sg:postcode":"96215",
    "sg:province":"Bayern",
    "wof:name":"Gefl\u00fcgelzuchtverein Lichtenfels",
    "wof:placetype":"venue"
},
  "geometry": {"coordinates":[11.0586929321,50.1340408325],"type":"Point"}
}