{
  "type": "Feature",
  "properties": {
    "iso:country":"DE",
    "sg:address":"Im Alten Bruch 36",
    "sg:city":"Duisburg",
    "sg:phone":"+49 203/781101",
    "sg:postcode":"47259",
    "sg:province":"Nordrhein-Westfalen",
    "wof:name":"Ray \u00d6l- & Gasbrenner Gmbh",
    "wof:placetype":"venue"
},
  "geometry": {"coordinates":[6.7550039291,51.3712882996],"type":"Point"}
}