{
  "type": "Feature",
  "properties": {
    "iso:country":"DE",
    "sg:address":"Busenh\u00fcbel 6a",
    "sg:city":"Weilerbach",
    "sg:phone":"+49 6374/2194",
    "sg:postcode":"67685",
    "sg:province":"Rheinland-Pfalz",
    "wof:name":"Michael M\u00fcller Massagepraxis",
    "wof:placetype":"venue"
},
  "geometry": {"coordinates":[7.628875,49.482346],"type":"Point"}
}