{
  "type": "Feature",
  "properties": {
    "iso:country":"DE",
    "sg:address":"Canthalstr. 6-8",
    "sg:city":"Hanau",
    "sg:postcode":"63450",
    "sg:province":"Hessen",
    "wof:name":"Elmatic Gmbh",
    "wof:placetype":"venue"
},
  "geometry": {"coordinates":[8.9149513245,50.1229324341],"type":"Point"}
}