{
  "type": "Feature",
  "properties": {
    "iso:country":"DE",
    "sg:address":"Klosterberg 4",
    "sg:city":"Au",
    "sg:phone":"+49 8752/214",
    "sg:postcode":"84072",
    "sg:province":"Bayern",
    "wof:name":"Marien-apotheke",
    "wof:placetype":"venue"
},
  "geometry": {"coordinates":[11.743504,48.558079],"type":"Point"}
}