{
  "type": "Feature",
  "properties": {
    "iso:country":"DE",
    "sg:address":"Bembergstr. 11",
    "sg:city":"Hemer",
    "sg:phone":"+49 2372/94820",
    "sg:postcode":"58675",
    "sg:province":"Nordrhein-Westfalen",
    "wof:name":"Tewes Immobilienmakler",
    "wof:placetype":"venue"
},
  "geometry": {"coordinates":[7.755010128,51.3924102783],"type":"Point"}
}