{
  "type": "Feature",
  "properties": {
    "iso:country":"DE",
    "sg:address":"Hauptstr. 81",
    "sg:city":"Bielefeld",
    "sg:phone":"+49 521/443963",
    "sg:postcode":"33647",
    "sg:province":"Nordrhein-Westfalen",
    "wof:name":"K. Sprengel Und Keitel Rechtsanw\u00e4lte Und Notar",
    "wof:placetype":"venue"
},
  "geometry": {"coordinates":[8.5111341476,51.9903068542],"type":"Point"}
}