{
  "type": "Feature",
  "properties": {
    "iso:country":"DE",
    "sg:address":"Seewiesenstr. 9",
    "sg:city":"Backnang",
    "sg:phone":"+49 7191/84946",
    "sg:postcode":"71522",
    "sg:province":"Baden-W\u00fcrttemberg",
    "wof:name":"Walter Schock",
    "wof:placetype":"venue"
},
  "geometry": {"coordinates":[9.4758205414,48.9590454102],"type":"Point"}
}