{
  "type": "Feature",
  "properties": {
    "iso:country":"DE",
    "sg:address":"Badorfer Str. 117",
    "sg:city":"Br\u00fchl",
    "sg:phone":"+49 2232/31723",
    "sg:postcode":"50321",
    "sg:province":"Nordrhein-Westfalen",
    "wof:name":"Kath. Pfarramt St. Pantaleon",
    "wof:placetype":"venue"
},
  "geometry": {"coordinates":[6.8920397758,50.8089790344],"type":"Point"}
}