{
  "type": "Feature",
  "properties": {
    "iso:country":"DE",
    "sg:address":"Hans-B\u00f6ckler-Str. 20",
    "sg:city":"Duisburg",
    "sg:phone":"+49 2065/30913",
    "sg:postcode":"47226",
    "sg:province":"Nordrhein-Westfalen",
    "wof:name":"Globus-apotheke Detlef Dittrich E. K.",
    "wof:placetype":"venue"
},
  "geometry": {"coordinates":[6.717894,51.409492],"type":"Point"}
}