{
  "type": "Feature",
  "properties": {
    "iso:country":"DE",
    "sg:address":"Miesbacher Str. 3",
    "sg:city":"Schliersee",
    "sg:phone":"+49 8026/4346",
    "sg:postcode":"83727",
    "sg:province":"Bayern",
    "wof:name":"Helena Tiefenbacher-leitner Rechtsanw\u00e4ltin",
    "wof:placetype":"venue"
},
  "geometry": {"coordinates":[11.8607053757,47.7361221313],"type":"Point"}
}