{
  "type": "Feature",
  "properties": {
    "iso:country":"DE",
    "sg:address":"G\u00fctersloher Str 326",
    "sg:city":"Bielefeld",
    "sg:phone":"+49 521/4173070",
    "sg:postcode":"33649",
    "sg:province":"Nordrhein-Westfalen",
    "wof:name":"Belu Gmbh",
    "wof:placetype":"venue"
},
  "geometry": {"coordinates":[8.461241,51.968399],"type":"Point"}
}