{
  "type": "Feature",
  "properties": {
    "iso:country":"DE",
    "sg:address":"Einh\u00e4user Landstr. 2-8",
    "sg:city":"Lorsch",
    "sg:phone":"+49 6251/5021",
    "sg:postcode":"64653",
    "sg:province":"Hessen",
    "wof:name":"Franz Josef Blust",
    "wof:placetype":"venue"
},
  "geometry": {"coordinates":[8.560187,49.657997],"type":"Point"}
}