{
  "type": "Feature",
  "properties": {
    "iso:country":"DE",
    "sg:address":"Bahnhofstr. 63-65",
    "sg:city":"Schwelm",
    "sg:phone":"+49 2336/49090",
    "sg:postcode":"58332",
    "sg:province":"Nordrhein-Westfalen",
    "wof:name":"H\u00fcls",
    "wof:placetype":"venue"
},
  "geometry": {"coordinates":[7.2895359993,51.2885131836],"type":"Point"}
}