{
  "type": "Feature",
  "properties": {
    "iso:country":"DE",
    "sg:address":"Wendenschlo\u00dfstr. 340",
    "sg:city":"Berlin",
    "sg:postcode":"12557",
    "sg:province":"Berlin",
    "wof:name":"Klaus-peter Seidel",
    "wof:placetype":"venue"
},
  "geometry": {"coordinates":[13.5854625702,52.4265136719],"type":"Point"}
}