{
  "type": "Feature",
  "properties": {
    "iso:country":"DE",
    "sg:address":"Braunlandweg 5",
    "sg:city":"Ulm",
    "sg:phone":"+49 731/263420",
    "sg:postcode":"89075",
    "sg:province":"Baden-W\u00fcrttemberg",
    "wof:name":"Restaurant Panorama",
    "wof:placetype":"venue"
},
  "geometry": {"coordinates":[10.0068740845,48.4193305969],"type":"Point"}
}