{
  "type": "Feature",
  "properties": {
    "iso:country":"DE",
    "sg:address":"Zur Teerhofsinsel 12",
    "sg:city":"L\u00fcbeck",
    "sg:phone":"+49 451/2801969",
    "sg:postcode":"23554",
    "sg:province":"Schleswig-Holstein",
    "wof:name":"Overdeck-beschichtungs- Systeme Vertriebs- Und",
    "wof:placetype":"venue"
},
  "geometry": {"coordinates":[10.696972847,53.9041786194],"type":"Point"}
}