{
  "type": "Feature",
  "properties": {
    "iso:country":"DE",
    "sg:address":"Bahnstr. 2",
    "sg:city":"Friedrichsdorf",
    "sg:phone":"+49 6172/71696",
    "sg:postcode":"61381",
    "sg:province":"Hessen",
    "wof:name":"Inge Eichhorn",
    "wof:placetype":"venue"
},
  "geometry": {"coordinates":[8.6396989822,50.2553367615],"type":"Point"}
}