{
  "type": "Feature",
  "properties": {
    "iso:country":"DE",
    "sg:address":"Lindenallee 1",
    "sg:city":"Alpen",
    "sg:phone":"+49 2802/7871",
    "sg:postcode":"46519",
    "sg:province":"Nordrhein-Westfalen",
    "wof:name":"Norbert B\u00fcsch",
    "wof:placetype":"venue"
},
  "geometry": {"coordinates":[6.51117,51.575291],"type":"Point"}
}