{
  "type": "Feature",
  "properties": {
    "iso:country":"DE",
    "sg:address":"Mundsburger Damm 58",
    "sg:city":"Hamburg",
    "sg:phone":"+49 40/2270909",
    "sg:postcode":"22087",
    "sg:province":"Hamburg",
    "wof:name":"Tk-scampi G\u00fcnther Maretzky",
    "wof:placetype":"venue"
},
  "geometry": {"coordinates":[10.0259885788,53.5693778992],"type":"Point"}
}