{
  "type": "Feature",
  "properties": {
    "iso:country":"DE",
    "sg:address":"Arthur-Hoffmann-Str. 151",
    "sg:city":"Leipzig",
    "sg:phone":"+49 341/321436",
    "sg:postcode":"04277",
    "sg:province":"Sachsen",
    "wof:name":"Gerhard Nolte",
    "wof:placetype":"venue"
},
  "geometry": {"coordinates":[12.378766,51.313702],"type":"Point"}
}