{
  "type": "Feature",
  "properties": {
    "iso:country":"DE",
    "sg:address":"Vagedesstr. 12-14",
    "sg:city":"Krefeld",
    "sg:phone":"+49 2151/28992",
    "sg:postcode":"47798",
    "sg:province":"Nordrhein-Westfalen",
    "wof:name":"Autositze Und Mehr Oldtimerservice Gmbh",
    "wof:placetype":"venue"
},
  "geometry": {"coordinates":[6.559773,51.337044],"type":"Point"}
}