{
  "type": "Feature",
  "properties": {
    "iso:country":"DE",
    "sg:address":"Lilienstr. 9",
    "sg:city":"Aurich",
    "sg:phone":"+49 4941/10003",
    "sg:postcode":"26603",
    "sg:province":"Niedersachsen",
    "wof:name":"M. Ahsendorf",
    "wof:placetype":"venue"
},
  "geometry": {"coordinates":[7.4813890457,53.4705352783],"type":"Point"}
}