{
  "type": "Feature",
  "properties": {
    "iso:country":"DE",
    "sg:address":"Alterlanger Str. 4",
    "sg:city":"Erlangen",
    "sg:phone":"+49 9131/41689",
    "sg:postcode":"91056",
    "sg:province":"Bayern",
    "wof:name":"Georg Weller",
    "wof:placetype":"venue"
},
  "geometry": {"coordinates":[10.987738,49.601833],"type":"Point"}
}