{
  "type": "Feature",
  "properties": {
    "iso:country":"DE",
    "sg:address":"Neugasse 52",
    "sg:city":"Winnweiler",
    "sg:phone":"+49 6302/2072",
    "sg:postcode":"67722",
    "sg:province":"Rheinland-Pfalz",
    "wof:name":"Rudolf Ranke",
    "wof:placetype":"venue"
},
  "geometry": {"coordinates":[7.850506,49.566299],"type":"Point"}
}