{
  "type": "Feature",
  "properties": {
    "iso:country":"DE",
    "sg:address":"Gr\u00fcnwalder Str. 14 d",
    "sg:city":"M\u00fcnchen",
    "sg:phone":"+49 89/6517200",
    "sg:postcode":"81547",
    "sg:province":"Bayern",
    "wof:name":"China-restaurant Fat-tsoi",
    "wof:placetype":"venue"
},
  "geometry": {"coordinates":[11.5742149353,48.1090431213],"type":"Point"}
}