{
  "type": "Feature",
  "properties": {
    "iso:country":"DE",
    "sg:address":"Marienstr. 2",
    "sg:city":"Pegnitz",
    "sg:phone":"+49 9241/6121",
    "sg:postcode":"91257",
    "sg:province":"Bayern",
    "wof:name":"Pizzeria Italia",
    "wof:placetype":"venue"
},
  "geometry": {"coordinates":[11.5500097275,49.7538871765],"type":"Point"}
}