{
  "type": "Feature",
  "properties": {
    "iso:country":"DE",
    "sg:address":"El-Lissitzky-Str. 1",
    "sg:city":"Darmstadt",
    "sg:postcode":"64287",
    "sg:province":"Hessen",
    "wof:name":"Itl-institut F\u00fcr Trocken- Und Leichtbau Ggmbh",
    "wof:placetype":"venue"
},
  "geometry": {"coordinates":[8.6764917374,49.8608856201],"type":"Point"}
}