{
  "type": "Feature",
  "properties": {
    "iso:country":"DE",
    "sg:address":"Gabelsbergerstr. 31",
    "sg:city":"Offenbach",
    "sg:postcode":"63069",
    "sg:province":"Hessen",
    "wof:name":"Kv Und Sa Hoch- Und Tief- Bau Gmbh",
    "wof:placetype":"venue"
},
  "geometry": {"coordinates":[8.7643117905,50.0953979492],"type":"Point"}
}