{
  "type": "Feature",
  "properties": {
    "iso:country":"DE",
    "sg:address":"Theaterstr. 23",
    "sg:city":"Luckenwalde",
    "sg:phone":"+49 3371/620177",
    "sg:postcode":"14943",
    "sg:province":"Brandenburg",
    "wof:name":"Linden-apotheke Inh. Gabriele Thomas",
    "wof:placetype":"venue"
},
  "geometry": {"coordinates":[13.178088,52.08596],"type":"Point"}
}