{
  "type": "Feature",
  "properties": {
    "iso:country":"DE",
    "sg:address":"Friedl\u00e4nder Str. 15",
    "sg:city":"Brunn",
    "sg:postcode":"17039",
    "sg:province":"Mecklenburg-Vorpommern",
    "wof:name":"Milchhof Brunn Gmbh",
    "wof:placetype":"venue"
},
  "geometry": {"coordinates":[13.370127,53.668762],"type":"Point"}
}