{
  "type": "Feature",
  "properties": {
    "iso:country":"DE",
    "sg:address":"Kettiger Str. 3",
    "sg:city":"Saffig",
    "sg:phone":"+49 2625/4274",
    "sg:postcode":"56648",
    "sg:province":"Rheinland-Pfalz",
    "wof:name":"Peter R\u00f6ttgen",
    "wof:placetype":"venue"
},
  "geometry": {"coordinates":[7.4208211899,50.3813209534],"type":"Point"}
}