{
  "type": "Feature",
  "properties": {
    "iso:country":"DE",
    "sg:address":"Ketzberger Str. 45",
    "sg:city":"Solingen",
    "sg:phone":"+49 212/2541225",
    "sg:postcode":"42653",
    "sg:province":"Nordrhein-Westfalen",
    "wof:name":"Eurosound Gmbh",
    "wof:placetype":"venue"
},
  "geometry": {"coordinates":[7.0801739693,51.1936988831],"type":"Point"}
}