{
  "type": "Feature",
  "properties": {
    "iso:country":"DE",
    "sg:address":"Vollmarsgasse 12",
    "sg:city":"Lohmar",
    "sg:phone":"+49 2246/912591",
    "sg:postcode":"53797",
    "sg:province":"Nordrhein-Westfalen",
    "wof:name":"Sds Schreier Schwei\u00dftechnik Und Dienstleistung Gmbh",
    "wof:placetype":"venue"
},
  "geometry": {"coordinates":[7.2178449631,50.8470649719],"type":"Point"}
}