{
  "type": "Feature",
  "properties": {
    "iso:country":"DE",
    "sg:address":"Darmst\u00e4dter Landstr. 19",
    "sg:city":"Weiterstadt",
    "sg:phone":"+49 6150/52402",
    "sg:postcode":"64331",
    "sg:province":"Hessen",
    "wof:name":"Ev. Pfarramt Gem. Gr\u00e4fenhausen",
    "wof:placetype":"venue"
},
  "geometry": {"coordinates":[8.5819311142,49.9056053162],"type":"Point"}
}