{
  "type": "Feature",
  "properties": {
    "iso:country":"DE",
    "sg:address":"Dorfstr. 12",
    "sg:city":"Erkrath",
    "sg:phone":"+49 2104/40188",
    "sg:postcode":"40699",
    "sg:province":"Nordrhein-Westfalen",
    "wof:name":"E. Zawadzki",
    "wof:placetype":"venue"
},
  "geometry": {"coordinates":[6.9680490494,51.213394165],"type":"Point"}
}