{
  "type": "Feature",
  "properties": {
    "iso:country":"DE",
    "sg:address":"Albstr. 34",
    "sg:city":"Me\u00dfstetten",
    "sg:phone":"+49 7431/90666",
    "sg:postcode":"72469",
    "sg:province":"Baden-W\u00fcrttemberg",
    "wof:name":"Manfred Stingel",
    "wof:placetype":"venue"
},
  "geometry": {"coordinates":[8.974084,48.184418],"type":"Point"}
}