{
  "type": "Feature",
  "properties": {
    "iso:country":"DE",
    "sg:address":"Tzschirnerstr. 13",
    "sg:city":"Bautzen",
    "sg:phone":"+49 3591/491026",
    "sg:postcode":"02625",
    "sg:province":"Sachsen",
    "wof:name":"Petersen Und Neumann Rechtsanw\u00e4lte",
    "wof:placetype":"venue"
},
  "geometry": {"coordinates":[14.4277772903,51.1745643616],"type":"Point"}
}