{
  "type": "Feature",
  "properties": {
    "iso:country":"DE",
    "sg:address":"Jahnstr. 30",
    "sg:city":"Ludwigshafen",
    "sg:phone":"+49 621/653161",
    "sg:postcode":"67069",
    "sg:province":"Rheinland-Pfalz",
    "wof:name":"Lothar Rathner",
    "wof:placetype":"venue"
},
  "geometry": {"coordinates":[8.401225,49.515926],"type":"Point"}
}