{
  "type": "Feature",
  "properties": {
    "iso:country":"DE",
    "sg:address":"Dorfstr. 43 a",
    "sg:city":"Rietzel",
    "sg:phone":"+49 39223/495",
    "sg:postcode":"39291",
    "sg:province":"Sachsen-Anhalt",
    "wof:name":"Boral Ihleburg Gmbh",
    "wof:placetype":"venue"
},
  "geometry": {"coordinates":[12.019490242,52.2781181335],"type":"Point"}
}