{
  "type": "Feature",
  "properties": {
    "iso:country":"DE",
    "sg:address":"Am K\u00f6llnischen Park 5",
    "sg:city":"Berlin",
    "sg:phone":"+49 30/308660",
    "sg:postcode":"10179",
    "sg:province":"Berlin",
    "wof:name":"M\u00e4rkisches Museum",
    "wof:placetype":"venue"
},
  "geometry": {"coordinates":[13.415201,52.51366],"type":"Point"}
}