{
  "type": "Feature",
  "properties": {
    "iso:country":"DE",
    "sg:address":"Am B\u00fcschchen 4",
    "sg:city":"Duisburg",
    "sg:phone":"+49 203/491081",
    "sg:postcode":"47179",
    "sg:province":"Nordrhein-Westfalen",
    "wof:name":"Johann Zimmermann",
    "wof:placetype":"venue"
},
  "geometry": {"coordinates":[6.744353,51.530605],"type":"Point"}
}