{
  "type": "Feature",
  "properties": {
    "iso:country":"DE",
    "sg:address":"Hauptstr. 58",
    "sg:city":"Wittorf",
    "sg:phone":"+49 4133/7219",
    "sg:postcode":"21357",
    "sg:province":"Niedersachsen",
    "wof:name":"Fehlhabers Gasthaus Inh. G. Bardowicks",
    "wof:placetype":"venue"
},
  "geometry": {"coordinates":[10.3628044128,53.3290023804],"type":"Point"}
}