{
  "type": "Feature",
  "properties": {
    "iso:country":"DE",
    "sg:address":"Nienburger Str. 16",
    "sg:city":"Bernburg",
    "sg:phone":"+49 3471/352420",
    "sg:postcode":"06406",
    "sg:province":"Sachsen-Anhalt",
    "wof:name":"Pr Catering And Services Gmbh & Co. Kg",
    "wof:placetype":"venue"
},
  "geometry": {"coordinates":[11.738849,51.802158],"type":"Point"}
}