{
  "type": "Feature",
  "properties": {
    "iso:country":"DE",
    "sg:address":"Reeperbahn 25",
    "sg:city":"Hamburg",
    "sg:phone":"+49 40/316386",
    "sg:postcode":"20359",
    "sg:province":"Hamburg",
    "wof:name":"P. Belessis",
    "wof:placetype":"venue"
},
  "geometry": {"coordinates":[9.966050148,53.5500564575],"type":"Point"}
}