{
  "type": "Feature",
  "properties": {
    "iso:country":"DE",
    "sg:address":"Uhlenhorst 49",
    "sg:city":"Schwarzenbek",
    "sg:phone":"+49 4151/4843",
    "sg:postcode":"21493",
    "sg:province":"Schleswig-Holstein",
    "wof:name":"Herbert Thater",
    "wof:placetype":"venue"
},
  "geometry": {"coordinates":[10.4839744568,53.4951171875],"type":"Point"}
}