{
  "type": "Feature",
  "properties": {
    "iso:country":"DE",
    "sg:address":"Kasseler Str. 27",
    "sg:city":"Gudensberg",
    "sg:phone":"+49 5603/1327",
    "sg:postcode":"34281",
    "sg:province":"Hessen",
    "wof:name":"Detlev Hohmann",
    "wof:placetype":"venue"
},
  "geometry": {"coordinates":[9.372046,51.179504],"type":"Point"}
}