{
  "type": "Feature",
  "properties": {
    "iso:country":"DE",
    "sg:address":"Hauptstr. 13",
    "sg:city":"Bad W\u00f6rishofen",
    "sg:phone":"+49 8247/2831",
    "sg:postcode":"86825",
    "sg:province":"Bayern",
    "wof:name":"A. De Crignis Edle Kr\u00e4uterkosmetik",
    "wof:placetype":"venue"
},
  "geometry": {"coordinates":[10.595121,48.005497],"type":"Point"}
}