{
  "type": "Feature",
  "properties": {
    "iso:country":"DE",
    "sg:address":"Ernst-Th\u00e4lmann-Str. 96",
    "sg:city":"Kalbe",
    "sg:phone":"+49 39080/2061",
    "sg:postcode":"39624",
    "sg:province":"Sachsen-Anhalt",
    "wof:name":"K. Hupe",
    "wof:placetype":"venue"
},
  "geometry": {"coordinates":[11.553529,52.719807],"type":"Point"}
}