{
  "type": "Feature",
  "properties": {
    "iso:country":"DE",
    "sg:address":"Grimmestr. 77",
    "sg:city":"Arnsberg",
    "sg:phone":"+49 2931/6016",
    "sg:postcode":"59821",
    "sg:province":"Nordrhein-Westfalen",
    "wof:name":"Gastst\u00e4tte G. Uri",
    "wof:placetype":"venue"
},
  "geometry": {"coordinates":[8.0652599335,51.4104003906],"type":"Point"}
}