{
  "type": "Feature",
  "properties": {
    "iso:country":"DE",
    "sg:address":"Konrad-Adenauer-Str. 105",
    "sg:city":"Wachtberg",
    "sg:phone":"+49 228/346731",
    "sg:postcode":"53343",
    "sg:province":"Nordrhein-Westfalen",
    "wof:name":"Karl Wolf",
    "wof:placetype":"venue"
},
  "geometry": {"coordinates":[7.176425,50.641033],"type":"Point"}
}