{
  "type": "Feature",
  "properties": {
    "iso:country":"DE",
    "sg:address":"18.-M\u00e4rz-Str. 19",
    "sg:city":"Gotha",
    "sg:postcode":"99867",
    "sg:province":"Th\u00fcringen",
    "wof:name":"Rad-art Humbek & Co. Kg",
    "wof:placetype":"venue"
},
  "geometry": {"coordinates":[10.695351,50.943504],"type":"Point"}
}