{
  "type": "Feature",
  "properties": {
    "iso:country":"DE",
    "sg:address":"Alban-Stolz-Str. 16",
    "sg:city":"Freiburg",
    "sg:phone":"+49 761/552444",
    "sg:postcode":"79108",
    "sg:province":"Baden-W\u00fcrttemberg",
    "wof:name":"Versorgungsanstalt F. \u00c4rzte Zahn\u00e4rzte Und Tier\u00e4rzte",
    "wof:placetype":"venue"
},
  "geometry": {"coordinates":[7.8576440811,48.0240821838],"type":"Point"}
}