{
  "type": "Feature",
  "properties": {
    "iso:country":"DE",
    "sg:address":"Ruwerstr 8",
    "sg:city":"Neuss",
    "sg:phone":"+49 2131/298870",
    "sg:postcode":"41464",
    "sg:province":"Nordrhein-Westfalen",
    "wof:name":"Eurofol Gmbh",
    "wof:placetype":"venue"
},
  "geometry": {"coordinates":[6.680956,51.184338],"type":"Point"}
}