{
  "type": "Feature",
  "properties": {
    "iso:country":"DE",
    "sg:address":"Philipp-Reis-Weg 5",
    "sg:city":"Kiel",
    "sg:phone":"+49 431/60070",
    "sg:postcode":"24148",
    "sg:province":"Schleswig-Holstein",
    "wof:name":"Hfg Hagenuk Faively Gmbh",
    "wof:placetype":"venue"
},
  "geometry": {"coordinates":[10.182045,54.319359],"type":"Point"}
}