{
  "type": "Feature",
  "properties": {
    "iso:country":"DE",
    "sg:address":"Philipsbornstr. 56",
    "sg:city":"Hannover",
    "sg:phone":"+49 511/3506127",
    "sg:postcode":"30165",
    "sg:province":"Niedersachsen",
    "wof:name":"Bl\u00fctenzauber S. Manthey",
    "wof:placetype":"venue"
},
  "geometry": {"coordinates":[9.729456,52.393501],"type":"Point"}
}