{
  "type": "Feature",
  "properties": {
    "iso:country":"DE",
    "sg:address":"Am Hellteich 25",
    "sg:city":"Walsrode",
    "sg:phone":"+49 5161/5872",
    "sg:postcode":"29664",
    "sg:province":"Niedersachsen",
    "wof:name":"Sahli Gmbh Eisen-metall-kfz- Und",
    "wof:placetype":"venue"
},
  "geometry": {"coordinates":[9.604719,52.871414],"type":"Point"}
}