{
  "type": "Feature",
  "properties": {
    "iso:country":"DE",
    "sg:address":"In der Humes 6b",
    "sg:city":"Quierschied",
    "sg:phone":"+49 6897/65666",
    "sg:postcode":"66287",
    "sg:province":"Saarland",
    "wof:name":"Pizza Heimservice Da Tony",
    "wof:placetype":"venue"
},
  "geometry": {"coordinates":[7.053811,49.327564],"type":"Point"}
}