{
  "type": "Feature",
  "properties": {
    "iso:country":"DE",
    "sg:address":"Landhausstr. 23",
    "sg:city":"Freudenstadt",
    "sg:phone":"+49 7441/7478",
    "sg:postcode":"72250",
    "sg:province":"Baden-W\u00fcrttemberg",
    "wof:name":"Hans Joachim Scharff",
    "wof:placetype":"venue"
},
  "geometry": {"coordinates":[8.4165039062,48.4599151611],"type":"Point"}
}