{
  "type": "Feature",
  "properties": {
    "iso:country":"DE",
    "sg:address":"Allg\u00e4uer Str. 26",
    "sg:city":"Pfronten",
    "sg:phone":"+49 8363/6777",
    "sg:postcode":"87459",
    "sg:province":"Bayern",
    "wof:name":"Pfrontner Geschenk- Und Schreibwaren Gmbh",
    "wof:placetype":"venue"
},
  "geometry": {"coordinates":[10.5600557327,47.5831985474],"type":"Point"}
}