{
  "type": "Feature",
  "properties": {
    "iso:country":"DE",
    "sg:address":"M\u00fchlenseite 5",
    "sg:city":"Korbach",
    "sg:phone":"+49 5631/2362",
    "sg:postcode":"34497",
    "sg:province":"Hessen",
    "wof:name":"Wolfgang Hochbein",
    "wof:placetype":"venue"
},
  "geometry": {"coordinates":[8.864215,51.234463],"type":"Point"}
}