{
  "type": "Feature",
  "properties": {
    "iso:country":"DE",
    "sg:address":"Speestr. 94",
    "sg:city":"Ratingen",
    "sg:phone":"+49 2102/33258",
    "sg:postcode":"40885",
    "sg:province":"Nordrhein-Westfalen",
    "wof:name":"Britta Soba",
    "wof:placetype":"venue"
},
  "geometry": {"coordinates":[6.841504097,51.3386230469],"type":"Point"}
}