{
  "type": "Feature",
  "properties": {
    "iso:country":"DE",
    "sg:address":"Zeppelinstr. 45",
    "sg:city":"Potsdam",
    "sg:phone":"+49 331/900027",
    "sg:postcode":"14471",
    "sg:province":"Brandenburg",
    "wof:name":"Zefa Bau Gmbh",
    "wof:placetype":"venue"
},
  "geometry": {"coordinates":[13.0333490372,52.391658783],"type":"Point"}
}