{
  "type": "Feature",
  "properties": {
    "iso:country":"DE",
    "sg:address":"Lilienthalstr. 15",
    "sg:city":"Hannover",
    "sg:phone":"+49 511/634146",
    "sg:postcode":"30179",
    "sg:province":"Niedersachsen",
    "wof:name":"Data Paper Ullrich Forms Gmbh",
    "wof:placetype":"venue"
},
  "geometry": {"coordinates":[9.7379751205,52.4193000793],"type":"Point"}
}