{
  "type": "Feature",
  "properties": {
    "iso:country":"DE",
    "sg:address":"Rathausstr. 45 a",
    "sg:city":"Wiesbaden",
    "sg:phone":"+49 611/608767",
    "sg:postcode":"65203",
    "sg:province":"Hessen",
    "wof:name":"Renate Baltrusch Heilpraktikerin",
    "wof:placetype":"venue"
},
  "geometry": {"coordinates":[8.2391633987,50.0400772095],"type":"Point"}
}