{
  "type": "Feature",
  "properties": {
    "iso:country":"DE",
    "sg:address":"B\u00fclowstr. 10",
    "sg:city":"Wilhelmshaven",
    "sg:phone":"+49 4421/33737",
    "sg:postcode":"26384",
    "sg:province":"Niedersachsen",
    "wof:name":"Johannes Eilts",
    "wof:placetype":"venue"
},
  "geometry": {"coordinates":[8.11922,53.528152],"type":"Point"}
}