{
  "type": "Feature",
  "properties": {
    "iso:country":"DE",
    "sg:address":"Industriestr. 10",
    "sg:city":"Spalt",
    "sg:phone":"+49 9175/301",
    "sg:postcode":"91174",
    "sg:province":"Bayern",
    "wof:name":"Baustoff Oertl Inh. Thomas Miehling E. K.",
    "wof:placetype":"venue"
},
  "geometry": {"coordinates":[10.929466,49.173405],"type":"Point"}
}