{
  "type": "Feature",
  "properties": {
    "iso:country":"DE",
    "sg:address":"Ziegelwaldstr 8-10",
    "sg:city":"Lorch",
    "sg:phone":"+49 7172/4081",
    "sg:postcode":"73547",
    "sg:province":"Baden-W\u00fcrttemberg",
    "wof:name":"Joos Metallveredelung Gmbh",
    "wof:placetype":"venue"
},
  "geometry": {"coordinates":[9.70398,48.795052],"type":"Point"}
}