{
  "type": "Feature",
  "properties": {
    "iso:country":"DE",
    "sg:address":"Erfstr. 26",
    "sg:city":"B\u00fcrgstadt",
    "sg:phone":"+49 9371/2036",
    "sg:postcode":"63927",
    "sg:province":"Bayern",
    "wof:name":"Schloth S Backstube Gmbh",
    "wof:placetype":"venue"
},
  "geometry": {"coordinates":[9.277836,49.707127],"type":"Point"}
}