{
  "type": "Feature",
  "properties": {
    "iso:country":"DE",
    "sg:address":"Am Isental 22",
    "sg:city":"Isen",
    "sg:phone":"+49 8083/9373",
    "sg:postcode":"84424",
    "sg:province":"Bayern",
    "wof:name":"Alexander Voges Rechtsanwalt",
    "wof:placetype":"venue"
},
  "geometry": {"coordinates":[12.0516004562,48.2059211731],"type":"Point"}
}