{
  "type": "Feature",
  "properties": {
    "iso:country":"DE",
    "sg:address":"Werftstr. 1",
    "sg:city":"Marienwerder",
    "sg:phone":"+49 3335/44460",
    "sg:postcode":"16348",
    "sg:province":"Brandenburg",
    "wof:name":"Herbert Schumacher",
    "wof:placetype":"venue"
},
  "geometry": {"coordinates":[13.605353,52.848801],"type":"Point"}
}