{
  "type": "Feature",
  "properties": {
    "iso:country":"DE",
    "sg:address":"Wilhelmshavener Str. 3",
    "sg:city":"Bremerhaven",
    "sg:phone":"+49 471/3087001",
    "sg:postcode":"27570",
    "sg:province":"Bremen",
    "wof:name":"All In Gastro Gmbh",
    "wof:placetype":"venue"
},
  "geometry": {"coordinates":[8.585395,53.536976],"type":"Point"}
}