{
  "type": "Feature",
  "properties": {
    "iso:country":"DE",
    "sg:address":"Bundesstr. 19",
    "sg:city":"Theres",
    "sg:phone":"+49 9521/8243",
    "sg:postcode":"97531",
    "sg:province":"Bayern",
    "wof:name":"Gutsschenke",
    "wof:placetype":"venue"
},
  "geometry": {"coordinates":[10.4489631653,50.017578125],"type":"Point"}
}