{
  "type": "Feature",
  "properties": {
    "iso:country":"DE",
    "sg:address":"Kastorstr. 44",
    "sg:city":"Heidenheim",
    "sg:phone":"+49 7321/44425",
    "sg:postcode":"89518",
    "sg:province":"Baden-W\u00fcrttemberg",
    "wof:name":"H. K\u00fcbler Malerei",
    "wof:placetype":"venue"
},
  "geometry": {"coordinates":[10.145198,48.679806],"type":"Point"}
}