{
  "type": "Feature",
  "properties": {
    "iso:country":"DE",
    "sg:address":"Sch\u00e4fflerstr. 10",
    "sg:city":"Pfarrkirchen",
    "sg:phone":"+49 8561/910284",
    "sg:postcode":"84347",
    "sg:province":"Bayern",
    "wof:name":"Karl-heinz Steiner",
    "wof:placetype":"venue"
},
  "geometry": {"coordinates":[12.94348,48.430965],"type":"Point"}
}