{
  "type": "Feature",
  "properties": {
    "iso:country":"DE",
    "sg:address":"Bismarckstr. 4",
    "sg:city":"Neuhausen",
    "sg:phone":"+49 7158/1770",
    "sg:postcode":"73765",
    "sg:province":"Baden-W\u00fcrttemberg",
    "wof:name":"Redaktion Entscheidung Verlag H\u00e4nssler",
    "wof:placetype":"venue"
},
  "geometry": {"coordinates":[9.2861032486,48.6800880432],"type":"Point"}
}