{
  "type": "Feature",
  "properties": {
    "iso:country":"DE",
    "sg:address":"Am Dreisberg 12",
    "sg:city":"Bielefeld",
    "sg:phone":"+49 521/15704",
    "sg:postcode":"33617",
    "sg:province":"Nordrhein-Westfalen",
    "wof:name":"Dietrich Martini Steuerberater",
    "wof:placetype":"venue"
},
  "geometry": {"coordinates":[8.5099143982,52.0035934448],"type":"Point"}
}