{
  "type": "Feature",
  "properties": {
    "iso:country":"DE",
    "sg:address":"Oberh\u00e4userstr. 108",
    "sg:city":"Ansbach",
    "sg:phone":"+49 981/61418",
    "sg:postcode":"91522",
    "sg:province":"Bayern",
    "wof:name":"R. Wiesinger",
    "wof:placetype":"venue"
},
  "geometry": {"coordinates":[10.5577716827,49.2916526794],"type":"Point"}
}