{
  "type": "Feature",
  "properties": {
    "iso:country":"DE",
    "sg:address":"Mercatostr. 43",
    "sg:city":"Geesthacht",
    "sg:phone":"+49 4941/5279494",
    "sg:postcode":"21502",
    "sg:province":"Schleswig-Holstein",
    "wof:name":"Harnisch-kunststoffe",
    "wof:placetype":"venue"
},
  "geometry": {"coordinates":[10.3569879532,53.4559631348],"type":"Point"}
}