{
  "type": "Feature",
  "properties": {
    "iso:country":"DE",
    "sg:address":"Grefrather Str. 183",
    "sg:city":"Viersen",
    "sg:phone":"+49 2162/6377",
    "sg:postcode":"41749",
    "sg:province":"Nordrhein-Westfalen",
    "wof:name":"Kath. \u00f6ffentliche Bibliothek St. Franziskus",
    "wof:placetype":"venue"
},
  "geometry": {"coordinates":[6.35623,51.30584],"type":"Point"}
}