{
  "type": "Feature",
  "properties": {
    "iso:country":"DE",
    "sg:address":"Eickener Str. 45",
    "sg:city":"Hattingen",
    "sg:phone":"+49 2324/50000",
    "sg:postcode":"45525",
    "sg:province":"Nordrhein-Westfalen",
    "wof:name":"Reuschling Entwicklungs- Und Verwaltungsges. Mbh",
    "wof:placetype":"venue"
},
  "geometry": {"coordinates":[7.171977,51.39695],"type":"Point"}
}