{
  "type": "Feature",
  "properties": {
    "iso:country":"DE",
    "sg:address":"Wullener Feld 7a",
    "sg:city":"Witten",
    "sg:phone":"+49 2302/698283",
    "sg:postcode":"58454",
    "sg:province":"Nordrhein-Westfalen",
    "wof:name":"R\u00fcdiger Und Volker Pfannkuche Architekten",
    "wof:placetype":"venue"
},
  "geometry": {"coordinates":[7.358867,51.456417],"type":"Point"}
}