{
  "type": "Feature",
  "properties": {
    "iso:country":"DE",
    "sg:address":"Hungener Str. 15",
    "sg:city":"Lich",
    "sg:phone":"+49 6404/7544",
    "sg:postcode":"35423",
    "sg:province":"Hessen",
    "wof:name":"M. Messbacher",
    "wof:placetype":"venue"
},
  "geometry": {"coordinates":[8.818821907,50.5146942139],"type":"Point"}
}