{
  "type": "Feature",
  "properties": {
    "iso:country":"DE",
    "sg:address":"Vorwerksgasse 11",
    "sg:city":"Weimar",
    "sg:phone":"+49 3643/501378",
    "sg:postcode":"99423",
    "sg:province":"Th\u00fcringen",
    "wof:name":"Viola Paschke",
    "wof:placetype":"venue"
},
  "geometry": {"coordinates":[11.330985,50.981285],"type":"Point"}
}