{
  "type": "Feature",
  "properties": {
    "iso:country":"DE",
    "sg:address":"Burggasse 20",
    "sg:city":"Rothenburg",
    "sg:phone":"+49 9861/2622",
    "sg:postcode":"91541",
    "sg:province":"Bayern",
    "wof:name":"Kath. Pfarramt Gem. Gebsattel",
    "wof:placetype":"venue"
},
  "geometry": {"coordinates":[10.1757450104,49.3761253357],"type":"Point"}
}