{
  "type": "Feature",
  "properties": {
    "iso:country":"DE",
    "sg:address":"Rabenauer Str. 14",
    "sg:city":"Freital",
    "sg:phone":"+49 351/6413063",
    "sg:postcode":"01705",
    "sg:province":"Sachsen",
    "wof:name":"Peter Ludewig",
    "wof:placetype":"venue"
},
  "geometry": {"coordinates":[13.6311759949,50.9820747375],"type":"Point"}
}