{
  "type": "Feature",
  "properties": {
    "iso:country":"DE",
    "sg:address":"Holder\u00e4ckerstr. 1",
    "sg:city":"Stuttgart",
    "sg:phone":"+49 711/8661137",
    "sg:postcode":"70499",
    "sg:province":"Baden-W\u00fcrttemberg",
    "wof:name":"Martin Weitbrecht Rohrleitungsbau Gmbh",
    "wof:placetype":"venue"
},
  "geometry": {"coordinates":[9.100838,48.823856],"type":"Point"}
}