{
  "type": "Feature",
  "properties": {
    "iso:country":"DE",
    "sg:address":"Im Hohen Acker 7",
    "sg:city":"Deidesheim",
    "sg:postcode":"67146",
    "sg:province":"Rheinland-Pfalz",
    "wof:name":"Bikosoft Datenverarbeitung Gmbh",
    "wof:placetype":"venue"
},
  "geometry": {"coordinates":[8.2025966644,49.4069480896],"type":"Point"}
}