{
  "type": "Feature",
  "properties": {
    "iso:country":"DE",
    "sg:address":"Nordring 29",
    "sg:city":"Hofheim",
    "sg:phone":"+49 6192/96550",
    "sg:postcode":"65719",
    "sg:province":"Hessen",
    "wof:name":"Samas Electronic Gmbh",
    "wof:placetype":"venue"
},
  "geometry": {"coordinates":[8.4603767395,50.0936851501],"type":"Point"}
}