{
  "type": "Feature",
  "properties": {
    "iso:country":"DE",
    "sg:address":"Pyrmonter Str. 51",
    "sg:city":"Horn-Bad Meinberg",
    "sg:postcode":"32805",
    "sg:province":"Nordrhein-Westfalen",
    "wof:name":"Walter Moek",
    "wof:placetype":"venue"
},
  "geometry": {"coordinates":[8.9981136322,51.8954696655],"type":"Point"}
}