{
  "type": "Feature",
  "properties": {
    "iso:country":"DE",
    "sg:address":"Lange Str. 38",
    "sg:city":"Parchim",
    "sg:phone":"+49 3871/267218",
    "sg:postcode":"19370",
    "sg:province":"Mecklenburg-Vorpommern",
    "wof:name":"U. S\u00fcfke",
    "wof:placetype":"venue"
},
  "geometry": {"coordinates":[11.844647,53.428101],"type":"Point"}
}