{
  "type": "Feature",
  "properties": {
    "iso:country":"DE",
    "sg:address":"Schulstr. 12",
    "sg:city":"Weil der Stadt",
    "sg:phone":"+49 7234",
    "sg:postcode":"71263",
    "sg:province":"Baden-W\u00fcrttemberg",
    "wof:name":"Jump & Fun Factory",
    "wof:placetype":"venue"
},
  "geometry": {"coordinates":[8.8162117004,48.7759971619],"type":"Point"}
}