{
  "type": "Feature",
  "properties": {
    "iso:country":"DE",
    "sg:address":"Sandhaar 2",
    "sg:city":"Rheine",
    "sg:phone":"+49 5975/8004",
    "sg:postcode":"48432",
    "sg:province":"Nordrhein-Westfalen",
    "wof:name":"Ulrich Rau\u00df Architekt",
    "wof:placetype":"venue"
},
  "geometry": {"coordinates":[7.481039,52.212952],"type":"Point"}
}