{
  "type": "Feature",
  "properties": {
    "iso:country":"DE",
    "sg:address":"Markt 5",
    "sg:city":"Sch\u00f6ningen",
    "sg:phone":"+49 5352/8283",
    "sg:postcode":"38364",
    "sg:province":"Niedersachsen",
    "wof:name":"Crazy-hair",
    "wof:placetype":"venue"
},
  "geometry": {"coordinates":[10.9682788849,52.1396598816],"type":"Point"}
}