{
  "type": "Feature",
  "properties": {
    "iso:country":"DE",
    "sg:address":"Heinkenstr.1",
    "sg:city":"Langenhagen",
    "sg:postcode":"30851",
    "sg:province":"Niedersachsen",
    "wof:name":"Sparta Langenhagen",
    "wof:placetype":"venue"
},
  "geometry": {"coordinates":[9.7264451981,52.4368515015],"type":"Point"}
}