{
  "type": "Feature",
  "properties": {
    "iso:country":"DE",
    "sg:address":"Leonberger Str. 41",
    "sg:city":"Weissach",
    "sg:phone":"+49 7044/32530",
    "sg:postcode":"71287",
    "sg:province":"Baden-W\u00fcrttemberg",
    "wof:name":"Ulrich Auracher",
    "wof:placetype":"venue"
},
  "geometry": {"coordinates":[8.9113750458,48.8315429688],"type":"Point"}
}