{
  "type": "Feature",
  "properties": {
    "iso:country":"DE",
    "sg:address":"Wormser Str. 50",
    "sg:city":"Offstein",
    "sg:phone":"+49 6243/7552",
    "sg:postcode":"67591",
    "sg:province":"Rheinland-Pfalz",
    "wof:name":"Rolf Lahr",
    "wof:placetype":"venue"
},
  "geometry": {"coordinates":[8.2430944443,49.6054801941],"type":"Point"}
}