{
  "type": "Feature",
  "properties": {
    "iso:country":"DE",
    "sg:address":"Wacholderkamp 9",
    "sg:city":"Hagen",
    "sg:phone":"+49 2331/586706",
    "sg:postcode":"58093",
    "sg:province":"Nordrhein-Westfalen",
    "wof:name":"Kortung & Klose Gmbh",
    "wof:placetype":"venue"
},
  "geometry": {"coordinates":[7.513693,51.352219],"type":"Point"}
}