{
  "type": "Feature",
  "properties": {
    "iso:country":"DE",
    "sg:address":"Bahnhof 2",
    "sg:city":"Beimerstetten",
    "sg:phone":"+49 7348/948754",
    "sg:postcode":"89179",
    "sg:province":"Baden-W\u00fcrttemberg",
    "wof:name":"G. Mierdel",
    "wof:placetype":"venue"
},
  "geometry": {"coordinates":[9.9768486023,48.4809989929],"type":"Point"}
}