{
  "type": "Feature",
  "properties": {
    "iso:country":"DE",
    "sg:address":"Nierentrop 5",
    "sg:city":"Schmallenberg",
    "sg:phone":"+49 2971/86453",
    "sg:postcode":"57392",
    "sg:province":"Nordrhein-Westfalen",
    "wof:name":"Pension Anton Beste",
    "wof:placetype":"venue"
},
  "geometry": {"coordinates":[8.251663208,51.2293243408],"type":"Point"}
}