{
  "type": "Feature",
  "properties": {
    "iso:country":"DE",
    "sg:address":"Am Sonnenlehen 12",
    "sg:city":"Aachen",
    "sg:phone":"+49 241/930472",
    "sg:postcode":"52072",
    "sg:province":"Nordrhein-Westfalen",
    "wof:name":"Aia Aerodynamische Ingenieurgesellschaft Mbh",
    "wof:placetype":"venue"
},
  "geometry": {"coordinates":[6.0632119179,50.8102455139],"type":"Point"}
}