{
  "type": "Feature",
  "properties": {
    "iso:country":"DE",
    "sg:address":"Professor-Bamann-Str. 8",
    "sg:city":"Gundelfingen",
    "sg:phone":"+49 9073/2502",
    "sg:postcode":"89423",
    "sg:province":"Bayern",
    "wof:name":"E. W\u00f6lz",
    "wof:placetype":"venue"
},
  "geometry": {"coordinates":[10.36937,48.55323],"type":"Point"}
}