{
  "type": "Feature",
  "properties": {
    "iso:country":"DE",
    "sg:address":"Hauptstra\u00dfe 92",
    "sg:city":"K\u00e4ndler",
    "sg:phone":"+49 3722/88366",
    "sg:postcode":"09247",
    "sg:province":"Sachsen",
    "wof:name":"Technikshop",
    "wof:placetype":"venue"
},
  "geometry": {"coordinates":[12.805518,50.861092],"type":"Point"}
}