{
  "type": "Feature",
  "properties": {
    "iso:country":"DE",
    "sg:address":"Gigler 1",
    "sg:city":"Bad Birnbach",
    "sg:phone":"+49 8563/593",
    "sg:postcode":"84364",
    "sg:province":"Bayern",
    "wof:name":"Pension Gigler",
    "wof:placetype":"venue"
},
  "geometry": {"coordinates":[13.0743999481,48.4537467957],"type":"Point"}
}