{
  "type": "Feature",
  "properties": {
    "iso:country":"DE",
    "sg:address":"Konrad-Wolf-Str. 33",
    "sg:city":"Berlin",
    "sg:phone":"+49 30/9711658",
    "sg:postcode":"13055",
    "sg:province":"Berlin",
    "wof:name":"Barbara Plehn",
    "wof:placetype":"venue"
},
  "geometry": {"coordinates":[13.474114,52.53614],"type":"Point"}
}