{
  "type": "Feature",
  "properties": {
    "iso:country":"DE",
    "sg:address":"Harthauser Str. 34",
    "sg:city":"M\u00fcnchen",
    "sg:phone":"+49 89/6423150",
    "sg:postcode":"81545",
    "sg:province":"Bayern",
    "wof:name":"H. Rach Architekt",
    "wof:placetype":"venue"
},
  "geometry": {"coordinates":[11.549771,48.086838],"type":"Point"}
}