{
  "type": "Feature",
  "properties": {
    "iso:country":"DE",
    "sg:address":"T\u00f6nnishof 3",
    "sg:city":"Moringen",
    "sg:phone":"+49 4955/55347",
    "sg:postcode":"37186",
    "sg:province":"Niedersachsen",
    "wof:name":"Kiel Keramik Gmbh",
    "wof:placetype":"venue"
},
  "geometry": {"coordinates":[9.788627,51.716686],"type":"Point"}
}