{
  "type": "Feature",
  "properties": {
    "iso:country":"DE",
    "sg:address":"Uhlstr. 123",
    "sg:city":"Br\u00fchl",
    "sg:phone":"+49 2232/410245",
    "sg:postcode":"50321",
    "sg:province":"Nordrhein-Westfalen",
    "wof:name":"U. Brell",
    "wof:placetype":"venue"
},
  "geometry": {"coordinates":[6.9006009102,50.8250312805],"type":"Point"}
}