{
  "type": "Feature",
  "properties": {
    "iso:country":"DE",
    "sg:address":"Klein Flottbeker Weg 18a",
    "sg:city":"Hamburg",
    "sg:phone":"+49 40/8811328",
    "sg:postcode":"22605",
    "sg:province":"Hamburg",
    "wof:name":"Ursula Stahnke",
    "wof:placetype":"venue"
},
  "geometry": {"coordinates":[9.888261795,53.55235672],"type":"Point"}
}