{
  "type": "Feature",
  "properties": {
    "iso:country":"DE",
    "sg:address":"Spreewalder Str. 6",
    "sg:city":"Dresden",
    "sg:postcode":"01239",
    "sg:province":"Sachsen",
    "wof:name":"J\u00f6rg Seidel",
    "wof:placetype":"venue"
},
  "geometry": {"coordinates":[13.7946567535,51.0058517456],"type":"Point"}
}