{
  "type": "Feature",
  "properties": {
    "iso:country":"DE",
    "sg:address":"Kirchweg 8",
    "sg:city":"Maierh\u00f6fen",
    "sg:phone":"+49 8383/553",
    "sg:postcode":"88167",
    "sg:province":"Bayern",
    "wof:name":"Andreas G\u00f6hl B\u00e4ckerei",
    "wof:placetype":"venue"
},
  "geometry": {"coordinates":[10.05188,47.652699],"type":"Point"}
}