{
  "type": "Feature",
  "properties": {
    "iso:country":"DE",
    "sg:address":"Bromberger Str. 16",
    "sg:city":"D\u00fcsseldorf",
    "sg:phone":"+49 211/741595",
    "sg:postcode":"40599",
    "sg:province":"Nordrhein-Westfalen",
    "wof:name":"Koch Und Fries Rechtsanw\u00e4lte",
    "wof:placetype":"venue"
},
  "geometry": {"coordinates":[6.8683180809,51.1751213074],"type":"Point"}
}