{
  "type": "Feature",
  "properties": {
    "iso:country":"DE",
    "sg:address":"Herrenstr. 30",
    "sg:city":"Wangen",
    "sg:phone":"+49 7522/6449",
    "sg:postcode":"88239",
    "sg:province":"Baden-W\u00fcrttemberg",
    "wof:name":"Capri",
    "wof:placetype":"venue"
},
  "geometry": {"coordinates":[9.833728,47.687393],"type":"Point"}
}