{
  "type": "Feature",
  "properties": {
    "iso:country":"DE",
    "sg:address":"Am Tulpenbrunnen 4",
    "sg:city":"Halle",
    "sg:phone":"+49 345/6949975",
    "sg:postcode":"06122",
    "sg:province":"Sachsen-Anhalt",
    "wof:name":"Apotheke Am Tulpenbrunnen",
    "wof:placetype":"venue"
},
  "geometry": {"coordinates":[11.93326,51.483501],"type":"Point"}
}