{
  "type": "Feature",
  "properties": {
    "iso:country":"DE",
    "sg:address":"Katharinenstr. 22",
    "sg:city":"Hildesheim",
    "sg:phone":"+49 5121/37355",
    "sg:postcode":"31135",
    "sg:province":"Niedersachsen",
    "wof:name":"Wilfried Rumpf",
    "wof:placetype":"venue"
},
  "geometry": {"coordinates":[9.9606161118,52.1570091248],"type":"Point"}
}