{
  "type": "Feature",
  "properties": {
    "iso:country":"DE",
    "sg:address":"Hans-B\u00f6ckler-Str. 5",
    "sg:city":"L\u00fcdinghausen",
    "sg:phone":"+49 2591/3700",
    "sg:postcode":"59348",
    "sg:province":"Nordrhein-Westfalen",
    "wof:name":"Gerhard Zilian",
    "wof:placetype":"venue"
},
  "geometry": {"coordinates":[7.424567,51.764538],"type":"Point"}
}