{
  "type": "Feature",
  "properties": {
    "iso:country":"DE",
    "sg:address":"Kumpfm\u00fchle",
    "sg:city":"Rechtmehring",
    "sg:phone":"+49 8076/8113",
    "sg:postcode":"83562",
    "sg:province":"Bayern",
    "wof:name":"Walter Tiefel Steuerberater",
    "wof:placetype":"venue"
},
  "geometry": {"coordinates":[12.16685009,48.1233787537],"type":"Point"}
}