{
  "type": "Feature",
  "properties": {
    "iso:country":"DE",
    "sg:address":"Simon-Schweizer-Str. 7",
    "sg:city":"Rottenburg",
    "sg:phone":"+49 7472/21162",
    "sg:postcode":"72108",
    "sg:province":"Baden-W\u00fcrttemberg",
    "wof:name":"A. Lohm\u00fcller",
    "wof:placetype":"venue"
},
  "geometry": {"coordinates":[8.9405374527,48.4776649475],"type":"Point"}
}