{
  "type": "Feature",
  "properties": {
    "iso:country":"DE",
    "sg:address":"Dahler Heide 19",
    "sg:city":"Paderborn",
    "sg:postcode":"33100",
    "sg:province":"Nordrhein-Westfalen",
    "wof:name":"Shg Service- Und Handelsges. F\u00fcr Soziale Einrichtungen Mbh",
    "wof:placetype":"venue"
},
  "geometry": {"coordinates":[8.8305768967,51.7042579651],"type":"Point"}
}