{
  "type": "Feature",
  "properties": {
    "iso:country":"DE",
    "sg:address":"Kandeler Weg 5",
    "sg:city":"Berlin",
    "sg:phone":"+49 30/3713860",
    "sg:postcode":"13583",
    "sg:province":"Berlin",
    "wof:name":"Demetros Anastasatos Bildhauer",
    "wof:placetype":"venue"
},
  "geometry": {"coordinates":[13.18506,52.542572],"type":"Point"}
}