{
  "type": "Feature",
  "properties": {
    "iso:country":"DE",
    "sg:address":"Lindenstr. 42",
    "sg:city":"Kefenrod",
    "sg:phone":"+49 6049/1370",
    "sg:postcode":"63699",
    "sg:province":"Hessen",
    "wof:name":"Pizzeria Lindenhof",
    "wof:placetype":"venue"
},
  "geometry": {"coordinates":[9.164937973,50.3523139954],"type":"Point"}
}