{
  "type": "Feature",
  "properties": {
    "iso:country":"DE",
    "sg:address":"Sperberh\u00f6he 20",
    "sg:city":"Arnsberg",
    "sg:phone":"+49 2932/96660",
    "sg:postcode":"59759",
    "sg:province":"Nordrhein-Westfalen",
    "wof:name":"Hans-j\u00fcrgen Wilbat Steuerberater",
    "wof:placetype":"venue"
},
  "geometry": {"coordinates":[7.9791798592,51.4304695129],"type":"Point"}
}