{
  "type": "Feature",
  "properties": {
    "iso:country":"DE",
    "sg:address":"Klippeneck 4",
    "sg:city":"Denkingen",
    "sg:postcode":"78588",
    "sg:province":"Baden-W\u00fcrttemberg",
    "wof:name":"Klippeneck Wei\u00df Gmbh",
    "wof:placetype":"venue"
},
  "geometry": {"coordinates":[8.7406902313,48.1052589417],"type":"Point"}
}