{
  "type": "Feature",
  "properties": {
    "iso:country":"DE",
    "sg:address":"Dammstr. 2",
    "sg:city":"Oberndorf",
    "sg:phone":"+49 7423/2097",
    "sg:postcode":"78727",
    "sg:province":"Baden-W\u00fcrttemberg",
    "wof:name":"Pfisterer Gmbh",
    "wof:placetype":"venue"
},
  "geometry": {"coordinates":[8.575045,48.306438],"type":"Point"}
}