{
  "type": "Feature",
  "properties": {
    "iso:country":"DE",
    "sg:address":"M\u00fchlmahdweg 25 A",
    "sg:city":"Augsburg",
    "sg:phone":"+49 821/748290",
    "sg:postcode":"86167",
    "sg:province":"Bayern",
    "wof:name":"Walter Betonsanierung Und Erhaltung Gmbh",
    "wof:placetype":"venue"
},
  "geometry": {"coordinates":[10.929702,48.390724],"type":"Point"}
}