{
  "type": "Feature",
  "properties": {
    "iso:country":"DE",
    "sg:address":"Westerlandstr. 1 a",
    "sg:city":"Berlin",
    "sg:phone":"+49 30/4726975",
    "sg:postcode":"13189",
    "sg:province":"Berlin",
    "wof:name":"Monika M\u00f6nch",
    "wof:placetype":"venue"
},
  "geometry": {"coordinates":[13.41459,52.557777],"type":"Point"}
}