{
  "type": "Feature",
  "properties": {
    "iso:country":"DE",
    "sg:address":"Nordstr. 63",
    "sg:city":"Seifhennersdorf",
    "sg:phone":"+49 3586/404809",
    "sg:postcode":"02782",
    "sg:province":"Sachsen",
    "wof:name":"Agrargenossenschaft Seifhennersdorf Eg",
    "wof:placetype":"venue"
},
  "geometry": {"coordinates":[14.593443,50.937805],"type":"Point"}
}