{
  "type": "Feature",
  "properties": {
    "iso:country":"DE",
    "sg:address":"Bachweg 7",
    "sg:city":"Oberrieden",
    "sg:phone":"+49 8265/421",
    "sg:postcode":"87769",
    "sg:province":"Bayern",
    "wof:name":"Rudolf Richter",
    "wof:placetype":"venue"
},
  "geometry": {"coordinates":[10.426495,48.091351],"type":"Point"}
}