{
  "type": "Feature",
  "properties": {
    "iso:country":"DE",
    "sg:address":"Markstiege 20",
    "sg:city":"Borken",
    "sg:phone":"+49 2861/3267",
    "sg:postcode":"46325",
    "sg:province":"Nordrhein-Westfalen",
    "wof:name":"Helmut Osing",
    "wof:placetype":"venue"
},
  "geometry": {"coordinates":[6.868759,51.857166],"type":"Point"}
}