{
  "type": "Feature",
  "properties": {
    "iso:country":"DE",
    "sg:address":"Mattenweg 6",
    "sg:city":"Kirchzarten",
    "sg:phone":"+49 7661/5937",
    "sg:postcode":"79199",
    "sg:province":"Baden-W\u00fcrttemberg",
    "wof:name":"Wilbirg Schwarz",
    "wof:placetype":"venue"
},
  "geometry": {"coordinates":[7.964832,47.962994],"type":"Point"}
}