{
  "type": "Feature",
  "properties": {
    "iso:country":"DE",
    "sg:address":"Gertrudisstr. 18",
    "sg:city":"Solingen",
    "sg:phone":"+49 212/549116",
    "sg:postcode":"42651",
    "sg:province":"Nordrhein-Westfalen",
    "wof:name":"Hubert Haacken",
    "wof:placetype":"venue"
},
  "geometry": {"coordinates":[7.089415,51.179283],"type":"Point"}
}