{
  "type": "Feature",
  "properties": {
    "iso:country":"DE",
    "sg:address":"Poststr. 6",
    "sg:city":"Friedenfels",
    "sg:postcode":"95688",
    "sg:province":"Bayern",
    "wof:name":"B\u00e4ckerei Und Lebensmittel Johann Stangl E. Kfm.",
    "wof:placetype":"venue"
},
  "geometry": {"coordinates":[12.103603,49.880253],"type":"Point"}
}