{
  "type": "Feature",
  "properties": {
    "iso:country":"DE",
    "sg:address":"Im Weikert 5",
    "sg:city":"Koblenz",
    "sg:phone":"+49 261/26587",
    "sg:postcode":"56072",
    "sg:province":"Rheinland-Pfalz",
    "wof:name":"M. Schmitz",
    "wof:placetype":"venue"
},
  "geometry": {"coordinates":[7.51814,50.365688],"type":"Point"}
}