{
  "type": "Feature",
  "properties": {
    "iso:country":"DE",
    "sg:address":"Am Sandershof 19",
    "sg:city":"Recklinghausen",
    "sg:phone":"+49 2361/45522",
    "sg:postcode":"45665",
    "sg:province":"Nordrhein-Westfalen",
    "wof:name":"Akkordeon-service-station Ludger Kosel",
    "wof:placetype":"venue"
},
  "geometry": {"coordinates":[7.2057490349,51.6107978821],"type":"Point"}
}