{
  "type": "Feature",
  "properties": {
    "iso:country":"DE",
    "sg:address":"Gisselberger Str. 31",
    "sg:city":"Marburg",
    "sg:phone":"+49 6421/99050",
    "sg:postcode":"35037",
    "sg:province":"Hessen",
    "wof:name":"Heinz Wagner Wirtschaftspr\u00fcfer",
    "wof:placetype":"venue"
},
  "geometry": {"coordinates":[8.7602796555,50.7960739136],"type":"Point"}
}