{
  "type": "Feature",
  "properties": {
    "iso:country":"DE",
    "sg:address":"Neue Rottenburger Str. 37",
    "sg:city":"Hechingen",
    "sg:phone":"+49 7471/1860",
    "sg:postcode":"72379",
    "sg:province":"Baden-W\u00fcrttemberg",
    "wof:name":"Gebr. Biedermann Gmbh",
    "wof:placetype":"venue"
},
  "geometry": {"coordinates":[8.960583,48.369846],"type":"Point"}
}