{
  "type": "Feature",
  "properties": {
    "iso:country":"DE",
    "sg:address":"Ettishofer Str. 8-10",
    "sg:city":"Weingarten",
    "sg:phone":"+49 751/561320",
    "sg:postcode":"88250",
    "sg:province":"Baden-W\u00fcrttemberg",
    "wof:name":"Buck Engineering Umwelttechnik Gmbh",
    "wof:placetype":"venue"
},
  "geometry": {"coordinates":[9.6337013245,47.8129005432],"type":"Point"}
}