{
  "type": "Feature",
  "properties": {
    "iso:country":"DE",
    "sg:address":"Mersch 5",
    "sg:city":"Telgte",
    "sg:phone":"+49 2504/8673",
    "sg:postcode":"48291",
    "sg:province":"Nordrhein-Westfalen",
    "wof:name":"August B\u00e4umer",
    "wof:placetype":"venue"
},
  "geometry": {"coordinates":[7.782196,52.017544],"type":"Point"}
}