{
  "type": "Feature",
  "properties": {
    "iso:country":"DE",
    "sg:address":"Wolfertshofen",
    "sg:city":"Heimenkirch",
    "sg:phone":"+49 8381/7643",
    "sg:postcode":"88178",
    "sg:province":"Bayern",
    "wof:name":"Pension Stephan Baldauf",
    "wof:placetype":"venue"
},
  "geometry": {"coordinates":[9.9293889999,47.6418457031],"type":"Point"}
}