{
  "type": "Feature",
  "properties": {
    "iso:country":"DE",
    "sg:address":"Pipinstr. 26",
    "sg:city":"Altom\u00fcnster",
    "sg:phone":"+49 8254/565",
    "sg:postcode":"85250",
    "sg:province":"Bayern",
    "wof:name":"Eichner Verbundplatten Vertriebs Gmbh",
    "wof:placetype":"venue"
},
  "geometry": {"coordinates":[11.292886734,48.4092674255],"type":"Point"}
}