{
  "type": "Feature",
  "properties": {
    "iso:country":"DE",
    "sg:address":"Tilsiter Str. 11",
    "sg:city":"Biebergem\u00fcnd",
    "sg:phone":"+49 6050/8177",
    "sg:postcode":"63599",
    "sg:province":"Hessen",
    "wof:name":"Robert Kunkel",
    "wof:placetype":"venue"
},
  "geometry": {"coordinates":[9.2584180832,50.2301445007],"type":"Point"}
}