{
  "type": "Feature",
  "properties": {
    "iso:country":"DE",
    "sg:address":"Heidenheimer Str. 19",
    "sg:city":"Heidenheim",
    "sg:phone":"+49 7321/61203",
    "sg:postcode":"89520",
    "sg:province":"Baden-W\u00fcrttemberg",
    "wof:name":"Josef Kasteleiner",
    "wof:placetype":"venue"
},
  "geometry": {"coordinates":[10.1592578888,48.7044143677],"type":"Point"}
}