{
  "type": "Feature",
  "properties": {
    "iso:country":"DE",
    "sg:address":"Hauptstr. 15",
    "sg:city":"H\u00fcsby",
    "sg:phone":"+49 4621/4790",
    "sg:postcode":"24850",
    "sg:province":"Schleswig-Holstein",
    "wof:name":"Restaurant Dorfkrug",
    "wof:placetype":"venue"
},
  "geometry": {"coordinates":[9.4855709076,54.4987602234],"type":"Point"}
}