{
  "type": "Feature",
  "properties": {
    "iso:country":"DE",
    "sg:address":"Moskauer Platz 15",
    "sg:city":"Erfurt",
    "sg:phone":"+49 361/734799",
    "sg:postcode":"99091",
    "sg:province":"Th\u00fcringen",
    "wof:name":"Senf Linke Exner Und Roeseler Masseure",
    "wof:placetype":"venue"
},
  "geometry": {"coordinates":[11.000065,51.008129],"type":"Point"}
}