{
  "type": "Feature",
  "properties": {
    "iso:country":"DE",
    "sg:address":"Ulrichstr. 95",
    "sg:city":"M\u00f6ssingen",
    "sg:phone":"+49 4920/2595050",
    "sg:postcode":"72116",
    "sg:province":"Baden-W\u00fcrttemberg",
    "wof:name":"Hans Klein Gmbh & Co. Elektronik",
    "wof:placetype":"venue"
},
  "geometry": {"coordinates":[7.206833,51.275494],"type":"Point"}
}