{
  "type": "Feature",
  "properties": {
    "iso:country":"DE",
    "sg:address":"Cronenberger Str. 28",
    "sg:city":"Solingen",
    "sg:phone":"+49 212/200868",
    "sg:postcode":"42651",
    "sg:province":"Nordrhein-Westfalen",
    "wof:name":"C. Gr\u00e4f",
    "wof:placetype":"venue"
},
  "geometry": {"coordinates":[7.085706,51.175358],"type":"Point"}
}