{
  "type": "Feature",
  "properties": {
    "iso:country":"DE",
    "sg:address":"Lissenstr. 6",
    "sg:city":"Karlsruhe",
    "sg:phone":"+49 721/495481",
    "sg:postcode":"76227",
    "sg:province":"Baden-W\u00fcrttemberg",
    "wof:name":"H. Rapp",
    "wof:placetype":"venue"
},
  "geometry": {"coordinates":[8.454329,48.995472],"type":"Point"}
}