{
  "type": "Feature",
  "properties": {
    "iso:country":"DE",
    "sg:address":"Mozartstr. 28",
    "sg:city":"Wei\u00dfenhorn",
    "sg:phone":"+49 7309/5129",
    "sg:postcode":"89264",
    "sg:province":"Bayern",
    "wof:name":"Heduga-garncontor Gmbh",
    "wof:placetype":"venue"
},
  "geometry": {"coordinates":[10.1731529236,48.3022193909],"type":"Point"}
}