{
  "type": "Feature",
  "properties": {
    "iso:country":"DE",
    "sg:address":"Ulmenweg 41",
    "sg:city":"Mannheim",
    "sg:phone":"+49 621/3069068",
    "sg:postcode":"68167",
    "sg:province":"Baden-W\u00fcrttemberg",
    "wof:name":"G. K\u00f6lling",
    "wof:placetype":"venue"
},
  "geometry": {"coordinates":[8.489676,49.505592],"type":"Point"}
}