{
  "type": "Feature",
  "properties": {
    "iso:country":"DE",
    "sg:address":"Rautheimer Str. 10-11",
    "sg:city":"Braunschweig",
    "sg:phone":"+49 531/74454",
    "sg:postcode":"38126",
    "sg:province":"Niedersachsen",
    "wof:name":"Henry Heitmann Bw-kantine",
    "wof:placetype":"venue"
},
  "geometry": {"coordinates":[10.5712738037,52.250415802],"type":"Point"}
}