{
  "type": "Feature",
  "properties": {
    "iso:country":"DE",
    "sg:address":"Alfred-Krupp-Weg 4-6",
    "sg:city":"M\u00fcnster",
    "sg:phone":"+49 4925/1526432",
    "sg:postcode":"48153",
    "sg:province":"Nordrhein-Westfalen",
    "wof:name":"Greshake Karosserie-undfahrzeugbau",
    "wof:placetype":"venue"
},
  "geometry": {"coordinates":[7.6313967705,51.9457969666],"type":"Point"}
}