{
  "type": "Feature",
  "properties": {
    "iso:country":"DE",
    "sg:address":"Speyerer Str. 4",
    "sg:city":"Neuhofen",
    "sg:phone":"+49 6236/55429",
    "sg:postcode":"67141",
    "sg:province":"Rheinland-Pfalz",
    "wof:name":"Taverna Plaka",
    "wof:placetype":"venue"
},
  "geometry": {"coordinates":[8.4301548004,49.4215011597],"type":"Point"}
}