{
  "type": "Feature",
  "properties": {
    "iso:country":"DE",
    "sg:address":"K\u00f6lner Str. 275",
    "sg:city":"M\u00fclheim",
    "sg:phone":"+49 208/4669360",
    "sg:postcode":"45481",
    "sg:province":"Nordrhein-Westfalen",
    "wof:name":"S. T. E. P. Gmbh",
    "wof:placetype":"venue"
},
  "geometry": {"coordinates":[6.862762928,51.3785705566],"type":"Point"}
}