{
  "type": "Feature",
  "properties": {
    "iso:country":"DE",
    "sg:address":"Seestr. 7",
    "sg:city":"Gr\u00f6mitz",
    "sg:phone":"+49 4562/4352",
    "sg:postcode":"23743",
    "sg:province":"Schleswig-Holstein",
    "wof:name":"H\u00fcning & Sohn Kg",
    "wof:placetype":"venue"
},
  "geometry": {"coordinates":[10.961166,54.147091],"type":"Point"}
}