{
  "type": "Feature",
  "properties": {
    "iso:country":"DE",
    "sg:address":"Osterstr. 13",
    "sg:city":"Cloppenburg",
    "sg:phone":"+49 4471/6606",
    "sg:postcode":"49661",
    "sg:province":"Niedersachsen",
    "wof:name":"August Reudink Immobilienmakler",
    "wof:placetype":"venue"
},
  "geometry": {"coordinates":[8.0441532135,52.848575592],"type":"Point"}
}