{
  "type": "Feature",
  "properties": {
    "iso:country":"DE",
    "sg:address":"Turmstr. 22",
    "sg:city":"Zellingen",
    "sg:phone":"+49 9364/9926",
    "sg:postcode":"97225",
    "sg:province":"Bayern",
    "wof:name":"Edwin Endres",
    "wof:placetype":"venue"
},
  "geometry": {"coordinates":[9.8164548874,49.8979873657],"type":"Point"}
}