{
  "type": "Feature",
  "properties": {
    "iso:country":"DE",
    "sg:address":"Breslauer Str. 60 a",
    "sg:city":"Weinheim",
    "sg:phone":"+49 6201/14563",
    "sg:postcode":"69469",
    "sg:province":"Baden-W\u00fcrttemberg",
    "wof:name":"Stadtbibliothek",
    "wof:placetype":"venue"
},
  "geometry": {"coordinates":[8.653558,49.542889],"type":"Point"}
}