{
  "type": "Feature",
  "properties": {
    "iso:country":"DE",
    "sg:address":"Wernigeroder Str. 7",
    "sg:city":"Bremen",
    "sg:phone":"+49 421/492274",
    "sg:postcode":"28205",
    "sg:province":"Bremen",
    "wof:name":"Heinz Klatt",
    "wof:placetype":"venue"
},
  "geometry": {"coordinates":[8.8425798416,53.0685462952],"type":"Point"}
}