{
  "type": "Feature",
  "properties": {
    "iso:country":"DE",
    "sg:address":"Kasseler Str. 26a",
    "sg:city":"Halle",
    "sg:phone":"+49 345/7758680",
    "sg:postcode":"06132",
    "sg:province":"Sachsen-Anhalt",
    "wof:name":"Gfw Gesellschaft F\u00fcr Wasser- Aufbereitung Mbh",
    "wof:placetype":"venue"
},
  "geometry": {"coordinates":[11.9798030853,51.4456367493],"type":"Point"}
}