{
  "type": "Feature",
  "properties": {
    "iso:country":"DE",
    "sg:address":"Industriestrasse 4",
    "sg:city":"Halver",
    "sg:phone":"+49 2353",
    "sg:postcode":"58553",
    "sg:province":"Nordrhein-Westfalen",
    "wof:name":"Gerhard K\u00f6ster",
    "wof:placetype":"venue"
},
  "geometry": {"coordinates":[7.5045938492,51.1966094971],"type":"Point"}
}