{
  "type": "Feature",
  "properties": {
    "iso:country":"DE",
    "sg:address":"M\u00fchlenstr. 15",
    "sg:city":"Apen",
    "sg:phone":"+49 4489/1770",
    "sg:postcode":"26689",
    "sg:province":"Niedersachsen",
    "wof:name":"Hermann Lott Auktionator Und Grundst\u00fccksmakler Kg",
    "wof:placetype":"venue"
},
  "geometry": {"coordinates":[7.7793412209,53.2005844116],"type":"Point"}
}