{
  "type": "Feature",
  "properties": {
    "iso:country":"DE",
    "sg:address":"Sonnenbergstr. 1",
    "sg:city":"Freden",
    "sg:phone":"+49 5184/7065",
    "sg:postcode":"31084",
    "sg:province":"Niedersachsen",
    "wof:name":"Helmut Wilhelm Inh. Martin Lichtenberg",
    "wof:placetype":"venue"
},
  "geometry": {"coordinates":[9.902628,51.927956],"type":"Point"}
}