{
  "type": "Feature",
  "properties": {
    "iso:country":"DE",
    "sg:address":"Kirchstr. 19",
    "sg:city":"Baesweiler",
    "sg:phone":"+49 2401/2757",
    "sg:postcode":"52499",
    "sg:province":"Nordrhein-Westfalen",
    "wof:name":"Orthop\u00e4die-haus Dreschers Gmbh",
    "wof:placetype":"venue"
},
  "geometry": {"coordinates":[6.1851620674,50.904384613],"type":"Point"}
}