{
  "type": "Feature",
  "properties": {
    "iso:country":"DE",
    "sg:address":"Raiffeisenstr. 11",
    "sg:city":"Heede",
    "sg:postcode":"26892",
    "sg:province":"Niedersachsen",
    "wof:name":"Friedhelm Hilgefort Fliesen U. Naturstein Gmbh",
    "wof:placetype":"venue"
},
  "geometry": {"coordinates":[7.2982702255,52.9914398193],"type":"Point"}
}