{
  "type": "Feature",
  "properties": {
    "iso:country":"DE",
    "sg:address":"Dieselstr. 3",
    "sg:city":"Graben-Neudorf",
    "sg:postcode":"76676",
    "sg:province":"Baden-W\u00fcrttemberg",
    "wof:name":"Capek Gmbh",
    "wof:placetype":"venue"
},
  "geometry": {"coordinates":[8.49458,49.15868],"type":"Point"}
}