{
  "type": "Feature",
  "properties": {
    "iso:country":"DE",
    "sg:address":"Kanzleistr. 17",
    "sg:city":"Hamburg",
    "sg:phone":"+49 40/828462",
    "sg:postcode":"22609",
    "sg:province":"Hamburg",
    "wof:name":"Julius C. Andresen Garten- Und",
    "wof:placetype":"venue"
},
  "geometry": {"coordinates":[9.851259,53.55357],"type":"Point"}
}