{
  "type": "Feature",
  "properties": {
    "iso:country":"DE",
    "sg:address":"M\u00e4dewalder Weg 49",
    "sg:city":"Berlin",
    "sg:phone":"+49 30/56498492",
    "sg:postcode":"12621",
    "sg:province":"Berlin",
    "wof:name":"Bernd Scheuner",
    "wof:placetype":"venue"
},
  "geometry": {"coordinates":[13.5873441696,52.5099334717],"type":"Point"}
}