{
  "type": "Feature",
  "properties": {
    "iso:country":"DE",
    "sg:address":"Otolfstr. 3",
    "sg:city":"Bad Mergentheim",
    "sg:phone":"+49 7931/51107",
    "sg:postcode":"97980",
    "sg:province":"Baden-W\u00fcrttemberg",
    "wof:name":"Praxis Dr. Med. Br\u00fcckner Und St\u00fcber-br\u00fcckner",
    "wof:placetype":"venue"
},
  "geometry": {"coordinates":[9.7537374496,49.5147857666],"type":"Point"}
}