{
  "type": "Feature",
  "properties": {
    "iso:country":"DE",
    "sg:address":"Hauptstr. 47",
    "sg:city":"Albbruck",
    "sg:postcode":"79774",
    "sg:province":"Baden-W\u00fcrttemberg",
    "wof:name":"Ga\u00dfmann",
    "wof:placetype":"venue"
},
  "geometry": {"coordinates":[8.0961141586,47.6035385132],"type":"Point"}
}