{
  "type": "Feature",
  "properties": {
    "iso:country":"DE",
    "sg:address":"Schulstr. 55",
    "sg:city":"Esslingen",
    "sg:phone":"+49 711/3452739",
    "sg:postcode":"73734",
    "sg:province":"Baden-W\u00fcrttemberg",
    "wof:name":"Bartsch Und Weindl",
    "wof:placetype":"venue"
},
  "geometry": {"coordinates":[9.3246498108,48.716594696],"type":"Point"}
}