{
  "type": "Feature",
  "properties": {
    "iso:country":"DE",
    "sg:address":"Kufsteiner Str. 1",
    "sg:city":"Oberaudorf",
    "sg:phone":"+49 8033/1435",
    "sg:postcode":"83080",
    "sg:province":"Bayern",
    "wof:name":"Mode- Und Trachtenhaus Rechenauer Gmbh",
    "wof:placetype":"venue"
},
  "geometry": {"coordinates":[12.1724185944,47.6475448608],"type":"Point"}
}