{
  "type": "Feature",
  "properties": {
    "iso:country":"DE",
    "sg:address":"Bahnhofstr. 3",
    "sg:city":"Steinfeld",
    "sg:phone":"+49 5492/1352",
    "sg:postcode":"49439",
    "sg:province":"Niedersachsen",
    "wof:name":"Norbert Honkomp",
    "wof:placetype":"venue"
},
  "geometry": {"coordinates":[8.035473,49.048988],"type":"Point"}
}