{
  "type": "Feature",
  "properties": {
    "iso:country":"DE",
    "sg:address":"Dachauer Str. 5",
    "sg:city":"M\u00fcnchen",
    "sg:phone":"+49 89/56763845",
    "sg:postcode":"80335",
    "sg:province":"Bayern",
    "wof:name":"Frau Friedl Groh Kosmetik Gmbh",
    "wof:placetype":"venue"
},
  "geometry": {"coordinates":[11.560191,48.142025],"type":"Point"}
}