{
  "type": "Feature",
  "properties": {
    "iso:country":"DE",
    "sg:address":"Am Trimbuschhof 1",
    "sg:city":"Herne",
    "sg:phone":"+49 2323/50460",
    "sg:postcode":"44628",
    "sg:province":"Nordrhein-Westfalen",
    "wof:name":"Walter Kalisch",
    "wof:placetype":"venue"
},
  "geometry": {"coordinates":[7.238989,51.547337],"type":"Point"}
}