{
  "type": "Feature",
  "properties": {
    "iso:country":"DE",
    "sg:address":"Kappel 41",
    "sg:city":"Hiltpoltstein",
    "sg:phone":"+49 9192/8534",
    "sg:postcode":"91355",
    "sg:province":"Bayern",
    "wof:name":"Georg Deinhardt",
    "wof:placetype":"venue"
},
  "geometry": {"coordinates":[11.300891,49.662006],"type":"Point"}
}