{
  "type": "Feature",
  "properties": {
    "iso:country":"DE",
    "sg:address":"Hauptstr. 37",
    "sg:city":"M\u00fclheim-K\u00e4rlich",
    "sg:phone":"+49 2630/4354",
    "sg:postcode":"56218",
    "sg:province":"Rheinland-Pfalz",
    "wof:name":"Bauunternehmung Hefter Gmbh & Co. Kg",
    "wof:placetype":"venue"
},
  "geometry": {"coordinates":[7.48272,50.388779],"type":"Point"}
}