{
  "type": "Feature",
  "properties": {
    "iso:country":"DE",
    "sg:address":"Dorfstr. 21",
    "sg:city":"Gadegast",
    "sg:phone":"+49 35387/42341",
    "sg:postcode":"06918",
    "sg:province":"Sachsen-Anhalt",
    "wof:name":"Bauunternehmung Axel Rietdorf",
    "wof:placetype":"venue"
},
  "geometry": {"coordinates":[12.890395,51.890873],"type":"Point"}
}