{
  "type": "Feature",
  "properties": {
    "iso:country":"DE",
    "sg:address":"Schau ins Land 26",
    "sg:city":"Bergisch Gladbach",
    "sg:postcode":"51429",
    "sg:province":"Nordrhein-Westfalen",
    "wof:name":"Krhg Grundbesitz- Verwaltungs Gmbh & Co. Kg",
    "wof:placetype":"venue"
},
  "geometry": {"coordinates":[7.1652121544,50.9660797119],"type":"Point"}
}