{
  "type": "Feature",
  "properties": {
    "iso:country":"DE",
    "sg:address":"Bahnhofstr. 3",
    "sg:city":"Schrobenhausen",
    "sg:phone":"+49 8252/883088",
    "sg:postcode":"86529",
    "sg:province":"Bayern",
    "wof:name":"Sob Telefon-center",
    "wof:placetype":"venue"
},
  "geometry": {"coordinates":[11.2637062073,48.5635032654],"type":"Point"}
}