{
  "type": "Feature",
  "properties": {
    "iso:country":"DE",
    "sg:address":"Margueritenweg 25",
    "sg:city":"H\u00fcrth",
    "sg:phone":"+49 2233/77106",
    "sg:postcode":"50354",
    "sg:province":"Nordrhein-Westfalen",
    "wof:name":"Werner Kriechel",
    "wof:placetype":"venue"
},
  "geometry": {"coordinates":[6.900088,50.878471],"type":"Point"}
}