{
  "type": "Feature",
  "properties": {
    "iso:country":"DE",
    "sg:address":"Roteichenstr. 5",
    "sg:city":"Wiesenburg",
    "sg:phone":"+49 33849/50045",
    "sg:postcode":"14827",
    "sg:province":"Brandenburg",
    "wof:name":"Potsdam Medizintechnik Gmbh",
    "wof:placetype":"venue"
},
  "geometry": {"coordinates":[12.465846,52.116619],"type":"Point"}
}