{
  "type": "Feature",
  "properties": {
    "iso:country":"DE",
    "sg:address":"Toeplerstr. 23",
    "sg:city":"Dresden",
    "sg:postcode":"01279",
    "sg:province":"Sachsen",
    "wof:name":"H. Heinrich",
    "wof:placetype":"venue"
},
  "geometry": {"coordinates":[13.822842598,51.0303077698],"type":"Point"}
}