{
  "type": "Feature",
  "properties": {
    "iso:country":"DE",
    "sg:address":"Gartenstr. 2",
    "sg:city":"Hameln",
    "sg:phone":"+49 5151/42141",
    "sg:postcode":"31785",
    "sg:province":"Niedersachsen",
    "wof:name":"Karin L\u00fccke-b\u00e4der Rechtsanw\u00e4ltin Und Notarin",
    "wof:placetype":"venue"
},
  "geometry": {"coordinates":[9.3617963791,52.1086044312],"type":"Point"}
}