{
  "type": "Feature",
  "properties": {
    "iso:country":"DE",
    "sg:address":"Wallrain 3",
    "sg:city":"Seck",
    "sg:phone":"+49 2664/207",
    "sg:postcode":"56479",
    "sg:province":"Rheinland-Pfalz",
    "wof:name":"W. Mercy Chem. Techn. Produkte",
    "wof:placetype":"venue"
},
  "geometry": {"coordinates":[8.0455656052,50.5782165527],"type":"Point"}
}