{
  "type": "Feature",
  "properties": {
    "iso:country":"DE",
    "sg:address":"Kreuznacher Str. 51",
    "sg:city":"K\u00f6ln",
    "sg:phone":"+49 221/385925",
    "sg:postcode":"50968",
    "sg:province":"Nordrhein-Westfalen",
    "wof:name":"Bernhard Heister",
    "wof:placetype":"venue"
},
  "geometry": {"coordinates":[6.9546380043,50.9070625305],"type":"Point"}
}