{
  "type": "Feature",
  "properties": {
    "iso:country":"DE",
    "sg:address":"L\u00f6nsstr. 6",
    "sg:city":"Borken",
    "sg:phone":"+49 2862/2551",
    "sg:postcode":"46325",
    "sg:province":"Nordrhein-Westfalen",
    "wof:name":"Alfred Lanfer Elektroinstallation",
    "wof:placetype":"venue"
},
  "geometry": {"coordinates":[6.856529,51.911324],"type":"Point"}
}