{
  "type": "Feature",
  "properties": {
    "iso:country":"DE",
    "sg:address":"Bismarckstr. 1",
    "sg:city":"Emmendingen",
    "sg:phone":"+49 7641/5850",
    "sg:postcode":"79312",
    "sg:province":"Baden-W\u00fcrttemberg",
    "wof:name":"Wehrle - Werk Pro-service Gmbh",
    "wof:placetype":"venue"
},
  "geometry": {"coordinates":[7.852271,48.119774],"type":"Point"}
}