{
  "type": "Feature",
  "properties": {
    "iso:country":"DE",
    "sg:address":"Ellrichsh\u00e4user Hauptstr. 14",
    "sg:city":"Satteldorf",
    "sg:phone":"+49 7950/513",
    "sg:postcode":"74589",
    "sg:province":"Baden-W\u00fcrttemberg",
    "wof:name":"Gasthaus Friedrich Seckel",
    "wof:placetype":"venue"
},
  "geometry": {"coordinates":[10.0864667892,49.1700668335],"type":"Point"}
}