{
  "type": "Feature",
  "properties": {
    "iso:country":"DE",
    "sg:address":"Am Steger 7",
    "sg:city":"Dautphetal",
    "sg:phone":"+49 6468/7063",
    "sg:postcode":"35232",
    "sg:province":"Hessen",
    "wof:name":"Hans Peter B\u00f6sser",
    "wof:placetype":"venue"
},
  "geometry": {"coordinates":[8.523815,50.808464],"type":"Point"}
}