{
  "type": "Feature",
  "properties": {
    "iso:country":"DE",
    "sg:address":"Tiroler Str. 38",
    "sg:city":"Frankfurt",
    "sg:phone":"+49 69/635015",
    "sg:postcode":"60596",
    "sg:province":"Hessen",
    "wof:name":"Cat Werbeagentur Gmbh",
    "wof:placetype":"venue"
},
  "geometry": {"coordinates":[8.6764135361,50.0946350098],"type":"Point"}
}