{
  "type": "Feature",
  "properties": {
    "iso:country":"DE",
    "sg:address":"Heinestr. 7 b",
    "sg:city":"W\u00fcrzburg",
    "sg:postcode":"97070",
    "sg:province":"Bayern",
    "wof:name":"Sachwert-plus Objektbauges. Mbh",
    "wof:placetype":"venue"
},
  "geometry": {"coordinates":[9.937284,49.79821],"type":"Point"}
}