{
  "type": "Feature",
  "properties": {
    "iso:country":"DE",
    "sg:address":"Flottmoorring 49",
    "sg:city":"Kaltenkirchen",
    "sg:phone":"+49 4191/60866",
    "sg:postcode":"24568",
    "sg:province":"Schleswig-Holstein",
    "wof:name":"Sebastian Ufert",
    "wof:placetype":"venue"
},
  "geometry": {"coordinates":[9.9544200897,53.8303604126],"type":"Point"}
}