{
  "type": "Feature",
  "properties": {
    "iso:country":"DE",
    "sg:address":"Speyerstr. 21",
    "sg:city":"Offenbach",
    "sg:phone":"+49 69/813394",
    "sg:postcode":"63065",
    "sg:province":"Hessen",
    "wof:name":"Speyer Eck",
    "wof:placetype":"venue"
},
  "geometry": {"coordinates":[8.7595653534,50.1096496582],"type":"Point"}
}