{
  "type": "Feature",
  "properties": {
    "iso:country":"DE",
    "sg:address":"Weseler Str. 84",
    "sg:city":"Voerde",
    "sg:phone":"+49 281/4770",
    "sg:postcode":"46562",
    "sg:province":"Nordrhein-Westfalen",
    "wof:name":"M\u00fcller & Co. Ohg",
    "wof:placetype":"venue"
},
  "geometry": {"coordinates":[6.6209778786,51.6222267151],"type":"Point"}
}