{
  "type": "Feature",
  "properties": {
    "iso:country":"DE",
    "sg:address":"Appelhofstr. 5",
    "sg:city":"Ascheberg",
    "sg:phone":"+49 2593/95990",
    "sg:postcode":"59387",
    "sg:province":"Nordrhein-Westfalen",
    "wof:name":"H. Nitsche",
    "wof:placetype":"venue"
},
  "geometry": {"coordinates":[7.6199140549,51.7899627686],"type":"Point"}
}