{
  "type": "Feature",
  "properties": {
    "iso:country":"DE",
    "sg:city":"Tonna",
    "sg:phone":"+49 36042/79141",
    "sg:postcode":"99958",
    "sg:province":"Th\u00fcringen",
    "wof:name":"Brigitte Weber",
    "wof:placetype":"venue"
},
  "geometry": {"coordinates":[10.73074,51.09026],"type":"Point"}
}