{
  "type": "Feature",
  "properties": {
    "iso:country":"DE",
    "sg:address":"G\u00f6rlitzer Str. 33",
    "sg:city":"L\u00f6bau",
    "sg:phone":"+49 3585/862807",
    "sg:postcode":"02708",
    "sg:province":"Sachsen",
    "wof:name":"Christian Pr\u00e4kelt",
    "wof:placetype":"venue"
},
  "geometry": {"coordinates":[14.68132,51.10199],"type":"Point"}
}