{
  "type": "Feature",
  "properties": {
    "iso:country":"DE",
    "sg:address":"Parkaue 35",
    "sg:city":"Berlin",
    "sg:phone":"+49 30/5597169",
    "sg:postcode":"10367",
    "sg:province":"Berlin",
    "wof:name":"Peter Kn\u00f6rnschild",
    "wof:placetype":"venue"
},
  "geometry": {"coordinates":[13.4792289734,52.5168304443],"type":"Point"}
}