{
  "type": "Feature",
  "properties": {
    "iso:country":"DE",
    "sg:address":"Hohenzollernstr. 31",
    "sg:city":"Ludwigshafen",
    "sg:phone":"+49 621/624103",
    "sg:postcode":"67063",
    "sg:province":"Rheinland-Pfalz",
    "wof:name":"Reinhart Schoch",
    "wof:placetype":"venue"
},
  "geometry": {"coordinates":[8.423388,49.48978],"type":"Point"}
}