{
  "type": "Feature",
  "properties": {
    "iso:country":"DE",
    "sg:address":"Hertzstr. 19",
    "sg:city":"Leinefelde",
    "sg:postcode":"37327",
    "sg:province":"Th\u00fcringen",
    "wof:name":"Bbvk Beratungs Gmbh",
    "wof:placetype":"venue"
},
  "geometry": {"coordinates":[10.3272094727,51.3799591064],"type":"Point"}
}