{
  "type": "Feature",
  "properties": {
    "iso:country":"DE",
    "sg:address":"Tannenbergstr. 24",
    "sg:city":"Kitzingen",
    "sg:phone":"+49 9321/33147",
    "sg:postcode":"97318",
    "sg:province":"Bayern",
    "wof:name":"C\u00e4cilie Rollinger",
    "wof:placetype":"venue"
},
  "geometry": {"coordinates":[10.187212944,49.7349586487],"type":"Point"}
}