{
  "type": "Feature",
  "properties": {
    "iso:country":"DE",
    "sg:address":"Grillparzerstr. 57",
    "sg:city":"Frankfurt",
    "sg:postcode":"60320",
    "sg:province":"Hessen",
    "wof:name":"Du-wal Gmbh",
    "wof:placetype":"venue"
},
  "geometry": {"coordinates":[8.666569,50.141827],"type":"Point"}
}