{
  "type": "Feature",
  "properties": {
    "iso:country":"DE",
    "sg:address":"Kurze Str. 2",
    "sg:city":"Meyenburg",
    "sg:phone":"+49 33968/80686",
    "sg:postcode":"16945",
    "sg:province":"Brandenburg",
    "wof:name":"Friedemann Wittkopf",
    "wof:placetype":"venue"
},
  "geometry": {"coordinates":[12.2421092987,53.3118515015],"type":"Point"}
}