{
  "type": "Feature",
  "properties": {
    "iso:country":"DE",
    "sg:address":"Sulburgring 52",
    "sg:city":"Bad Driburg",
    "sg:phone":"+49 5253/940490",
    "sg:postcode":"33014",
    "sg:province":"Nordrhein-Westfalen",
    "wof:name":"Asa  F\u00fcr Leute, Die Nach Den Sternen Greifen!",
    "wof:placetype":"venue"
},
  "geometry": {"coordinates":[9.0178852081,51.7234535217],"type":"Point"}
}