{
  "type": "Feature",
  "properties": {
    "iso:country":"DE",
    "sg:address":"Weinbergstr. 26",
    "sg:city":"Bad Wildungen",
    "sg:phone":"+49 5621/2632",
    "sg:postcode":"34537",
    "sg:province":"Hessen",
    "wof:name":"Wolfgang Pape Architekt",
    "wof:placetype":"venue"
},
  "geometry": {"coordinates":[9.119846,51.125023],"type":"Point"}
}