{
  "type": "Feature",
  "properties": {
    "iso:country":"DE",
    "sg:address":"Dorpweg 10",
    "sg:city":"Wuppertal",
    "sg:phone":"+49 202/713609",
    "sg:postcode":"42115",
    "sg:province":"Nordrhein-Westfalen",
    "wof:name":"Wolfgang Besse Architekt",
    "wof:placetype":"venue"
},
  "geometry": {"coordinates":[7.11546,51.260361],"type":"Point"}
}