{
  "type": "Feature",
  "properties": {
    "iso:country":"DE",
    "sg:address":"Am F\u00f6rsterberg 24",
    "sg:city":"Burgdorf",
    "sg:phone":"+49 5136/5323",
    "sg:postcode":"31303",
    "sg:province":"Niedersachsen",
    "wof:name":"A. Knels",
    "wof:placetype":"venue"
},
  "geometry": {"coordinates":[10.014742,52.442207],"type":"Point"}
}