{
  "type": "Feature",
  "properties": {
    "iso:country":"DE",
    "sg:address":"Ludwig-F\u00fcssl-Str. 7",
    "sg:city":"Garching",
    "sg:phone":"+49 8634/66248",
    "sg:postcode":"84518",
    "sg:province":"Bayern",
    "wof:name":"Annerose Theil Rechtsanw\u00e4ltin",
    "wof:placetype":"venue"
},
  "geometry": {"coordinates":[12.5893821716,48.135559082],"type":"Point"}
}