{
  "type": "Feature",
  "properties": {
    "iso:country":"DE",
    "sg:address":"L\u00fcbecker Str. 80",
    "sg:city":"Hamburg",
    "sg:phone":"+49 40/2505290",
    "sg:postcode":"22087",
    "sg:province":"Hamburg",
    "wof:name":"Sabinas Nagestudio",
    "wof:placetype":"venue"
},
  "geometry": {"coordinates":[10.030804,53.560848],"type":"Point"}
}