{
  "type": "Feature",
  "properties": {
    "iso:country":"DE",
    "sg:address":"Barer Str 9",
    "sg:city":"M\u00fcnchen",
    "sg:phone":"+49 89/28628382",
    "sg:postcode":"80333",
    "sg:province":"Bayern",
    "wof:name":"Vff Verwertungsgesellschaft Der Film- Und Fernsehproduzenten Mbh",
    "wof:placetype":"venue"
},
  "geometry": {"coordinates":[11.5679063797,48.1430740356],"type":"Point"}
}