{
  "type": "Feature",
  "properties": {
    "iso:country":"DE",
    "sg:address":"Hainleite 15",
    "sg:city":"Bad Alexandersbad",
    "sg:phone":"+49 9232/6998",
    "sg:postcode":"95680",
    "sg:province":"Bayern",
    "wof:name":"Johanna Stangl Heilpraktikerin",
    "wof:placetype":"venue"
},
  "geometry": {"coordinates":[12.0188446045,50.0134811401],"type":"Point"}
}