{
  "type": "Feature",
  "properties": {
    "iso:country":"DE",
    "sg:address":"Hanauer Landstr. 4",
    "sg:city":"Frankfurt",
    "sg:phone":"+49 69/446801",
    "sg:postcode":"60314",
    "sg:province":"Hessen",
    "wof:name":"Ostend-apotheke",
    "wof:placetype":"venue"
},
  "geometry": {"coordinates":[8.695359,50.113274],"type":"Point"}
}