{
  "type": "Feature",
  "properties": {
    "iso:country":"DE",
    "sg:address":"Erdinger Str. 2 a",
    "sg:city":"Neufahrn",
    "sg:phone":"+49 8165/65218",
    "sg:postcode":"85375",
    "sg:province":"Bayern",
    "wof:name":"J. K\u00f6hn",
    "wof:placetype":"venue"
},
  "geometry": {"coordinates":[11.66225,48.316921],"type":"Point"}
}