{
  "type": "Feature",
  "properties": {
    "iso:country":"DE",
    "sg:address":"Kornwestheimer Str. 46",
    "sg:city":"Korntal-M\u00fcnchingen",
    "sg:phone":"+49 7150/92060",
    "sg:postcode":"70825",
    "sg:province":"Baden-W\u00fcrttemberg",
    "wof:name":"Fashy Gmbh",
    "wof:placetype":"venue"
},
  "geometry": {"coordinates":[9.1153001785,48.8530311584],"type":"Point"}
}