{
  "type": "Feature",
  "properties": {
    "iso:country":"DE",
    "sg:address":"Bonhoefferstr. 3",
    "sg:city":"Hannover",
    "sg:phone":"+49 511/467928",
    "sg:postcode":"30457",
    "sg:province":"Niedersachsen",
    "wof:name":"H. M\u00fcller",
    "wof:placetype":"venue"
},
  "geometry": {"coordinates":[9.68774,52.3423],"type":"Point"}
}