{
  "type": "Feature",
  "properties": {
    "iso:country":"DE",
    "sg:address":"Alt Griesheim 15",
    "sg:city":"Frankfurt",
    "sg:phone":"+49 69/388472",
    "sg:postcode":"65933",
    "sg:province":"Hessen",
    "wof:name":"Anne Sengel",
    "wof:placetype":"venue"
},
  "geometry": {"coordinates":[8.6077880859,50.0909500122],"type":"Point"}
}