{
  "type": "Feature",
  "properties": {
    "iso:country":"DE",
    "sg:address":"Kieler Str 157-161",
    "sg:city":"Hamburg",
    "sg:phone":"+49 40/8080700",
    "sg:postcode":"22769",
    "sg:province":"Hamburg",
    "wof:name":"Uptrade Service Gmbh",
    "wof:placetype":"venue"
},
  "geometry": {"coordinates":[9.948145,53.568043],"type":"Point"}
}