{
  "type": "Feature",
  "properties": {
    "iso:country":"DE",
    "sg:address":"Hornstr. 13",
    "sg:city":"Z\u00fclpich",
    "sg:phone":"+49 2252/6026",
    "sg:postcode":"53909",
    "sg:province":"Nordrhein-Westfalen",
    "wof:name":"Josef Keldenich",
    "wof:placetype":"venue"
},
  "geometry": {"coordinates":[6.6443428993,50.6441993713],"type":"Point"}
}