{
  "type": "Feature",
  "properties": {
    "iso:country":"DE",
    "sg:address":"Am Sommerberg 7",
    "sg:city":"Simonswald",
    "sg:phone":"+49 7683/429",
    "sg:postcode":"79263",
    "sg:province":"Baden-W\u00fcrttemberg",
    "wof:name":"Hubert Wehrle",
    "wof:placetype":"venue"
},
  "geometry": {"coordinates":[8.0616149902,48.1057815552],"type":"Point"}
}