{
  "type": "Feature",
  "properties": {
    "iso:country":"DE",
    "sg:address":"Ebniseestr. 12",
    "sg:city":"Stuttgart",
    "sg:phone":"+49 711/321108",
    "sg:postcode":"70329",
    "sg:province":"Baden-W\u00fcrttemberg",
    "wof:name":"Kath. Pfarramt St. Franziskus",
    "wof:placetype":"venue"
},
  "geometry": {"coordinates":[9.2664737701,48.767829895],"type":"Point"}
}