{
  "type": "Feature",
  "properties": {
    "iso:country":"DE",
    "sg:address":"Hauptstr. 29",
    "sg:city":"K\u00fchlenthal",
    "sg:phone":"+49 8273/2182",
    "sg:postcode":"86707",
    "sg:province":"Bayern",
    "wof:name":"A. Lindermeir",
    "wof:placetype":"venue"
},
  "geometry": {"coordinates":[10.8224582672,48.5643005371],"type":"Point"}
}