{
  "type": "Feature",
  "properties": {
    "iso:country":"DE",
    "sg:address":"Bahnhofstr. 39",
    "sg:city":"Eggolsheim",
    "sg:phone":"+49 9545/7399",
    "sg:postcode":"91330",
    "sg:province":"Bayern",
    "wof:name":"Thomas Laugner",
    "wof:placetype":"venue"
},
  "geometry": {"coordinates":[11.0492801666,49.7711181641],"type":"Point"}
}