{
  "type": "Feature",
  "properties": {
    "iso:country":"DE",
    "sg:address":"Dr.-Max-Breitung-Str. 14",
    "sg:city":"Plauen",
    "sg:phone":"+49 3741/441584",
    "sg:postcode":"08529",
    "sg:province":"Sachsen",
    "wof:name":"Manfred Bredow",
    "wof:placetype":"venue"
},
  "geometry": {"coordinates":[12.1631059647,50.4961471558],"type":"Point"}
}