{
  "type": "Feature",
  "properties": {
    "iso:country":"DE",
    "sg:address":"Breite Str. 42",
    "sg:city":"Pirna",
    "sg:phone":"+49 3501/528529",
    "sg:postcode":"01796",
    "sg:province":"Sachsen",
    "wof:name":"Ralf Grahl",
    "wof:placetype":"venue"
},
  "geometry": {"coordinates":[13.9389228821,50.9604263306],"type":"Point"}
}