{
  "type": "Feature",
  "properties": {
    "iso:country":"DE",
    "sg:address":"Zur Pfingstweide 2",
    "sg:city":"Siegbach",
    "sg:phone":"+49 2778/431",
    "sg:postcode":"35768",
    "sg:province":"Hessen",
    "wof:name":"Esther Jung",
    "wof:placetype":"venue"
},
  "geometry": {"coordinates":[8.428718,50.720188],"type":"Point"}
}