{
  "type": "Feature",
  "properties": {
    "iso:country":"DE",
    "sg:address":"Junkersstr. 6a",
    "sg:city":"Viernheim",
    "sg:phone":"+49 6204/8257",
    "sg:postcode":"68519",
    "sg:province":"Hessen",
    "wof:name":"Weidner & Helfrich Gmbh",
    "wof:placetype":"venue"
},
  "geometry": {"coordinates":[8.591878891,49.5459213257],"type":"Point"}
}