{
  "type": "Feature",
  "properties": {
    "iso:country":"DE",
    "sg:address":"Poststr. 14-16",
    "sg:city":"Hamburg",
    "sg:phone":"+49 40/367251",
    "sg:postcode":"20354",
    "sg:province":"Hamburg",
    "wof:name":"Willi Brockmann Ingenieur",
    "wof:placetype":"venue"
},
  "geometry": {"coordinates":[9.9897727966,53.5536079407],"type":"Point"}
}