{
  "type": "Feature",
  "properties": {
    "iso:country":"DE",
    "sg:address":"Heitkamp 15",
    "sg:city":"Haltern",
    "sg:phone":"+49 2364/169031",
    "sg:postcode":"45721",
    "sg:province":"Nordrhein-Westfalen",
    "wof:name":"Hiemisch Kg",
    "wof:placetype":"venue"
},
  "geometry": {"coordinates":[7.13092,51.754009],"type":"Point"}
}