{
  "type": "Feature",
  "properties": {
    "iso:country":"DE",
    "sg:address":"Ahornweg 27",
    "sg:city":"Altdorf",
    "sg:phone":"+49 7031/602720",
    "sg:postcode":"71155",
    "sg:province":"Baden-W\u00fcrttemberg",
    "wof:name":"Claus D. M\u00fcller-hengstenberg Rechtsanwalt",
    "wof:placetype":"venue"
},
  "geometry": {"coordinates":[8.9883346558,48.6326713562],"type":"Point"}
}