{
  "type": "Feature",
  "properties": {
    "iso:country":"DE",
    "sg:address":"Schneeberger Str. 39",
    "sg:city":"Stollberg",
    "sg:phone":"+49 37296/2669",
    "sg:postcode":"09366",
    "sg:province":"Sachsen",
    "wof:name":"Heini K\u00e4stner",
    "wof:placetype":"venue"
},
  "geometry": {"coordinates":[12.771116,50.694897],"type":"Point"}
}