{
  "type": "Feature",
  "properties": {
    "iso:country":"DE",
    "sg:address":"Dieselstr. 48",
    "sg:city":"Meppen",
    "sg:phone":"+49 5931/8326",
    "sg:postcode":"49716",
    "sg:province":"Niedersachsen",
    "wof:name":"Zeppelin Baumaschinen",
    "wof:placetype":"venue"
},
  "geometry": {"coordinates":[7.29958,52.657005],"type":"Point"}
}