{
  "type": "Feature",
  "properties": {
    "iso:country":"DE",
    "sg:address":"Rathausplatz 1",
    "sg:city":"Gelenau",
    "sg:postcode":"09423",
    "sg:province":"Sachsen",
    "wof:name":"Gelenauer Wohnungs Gmbh",
    "wof:placetype":"venue"
},
  "geometry": {"coordinates":[12.9841051102,50.7132148743],"type":"Point"}
}