{
  "type": "Feature",
  "properties": {
    "iso:country":"DE",
    "sg:address":"Wi\u00dfstr. 26",
    "sg:city":"Dortmund",
    "sg:phone":"+49 231/572292",
    "sg:postcode":"44137",
    "sg:province":"Nordrhein-Westfalen",
    "wof:name":"Blumen-risse Gmbh & Co. Kg",
    "wof:placetype":"venue"
},
  "geometry": {"coordinates":[7.46487,51.512085],"type":"Point"}
}