{
  "type": "Feature",
  "properties": {
    "iso:country":"DE",
    "sg:address":"Im Wasen 6",
    "sg:city":"Hohenstein",
    "sg:phone":"+49 7387/98162",
    "sg:postcode":"72531",
    "sg:province":"Baden-W\u00fcrttemberg",
    "wof:name":"W. Maier",
    "wof:placetype":"venue"
},
  "geometry": {"coordinates":[9.338549614,48.3570251465],"type":"Point"}
}