{
  "type": "Feature",
  "properties": {
    "iso:country":"DE",
    "sg:address":"Oberer B\u00fcrgla\u00df 12",
    "sg:city":"Coburg",
    "sg:phone":"+49 9561/75774",
    "sg:postcode":"96450",
    "sg:province":"Bayern",
    "wof:name":"B\u00fcrgla\u00dfsch\u00e4nke",
    "wof:placetype":"venue"
},
  "geometry": {"coordinates":[10.9670267105,50.2606582642],"type":"Point"}
}