{
  "type": "Feature",
  "properties": {
    "iso:country":"DE",
    "sg:address":"L\u00fcbecker Str. 24",
    "sg:city":"Sch\u00f6nberg",
    "sg:phone":"+49 38828/24321",
    "sg:postcode":"23923",
    "sg:province":"Mecklenburg-Vorpommern",
    "wof:name":"Dieter Zepuntke",
    "wof:placetype":"venue"
},
  "geometry": {"coordinates":[10.928572,53.850349],"type":"Point"}
}