{
  "type": "Feature",
  "properties": {
    "iso:country":"DE",
    "sg:address":"Schanzenstr. 19",
    "sg:city":"Kassel",
    "sg:phone":"+49 561/67305",
    "sg:postcode":"34130",
    "sg:province":"Hessen",
    "wof:name":"B. Dietrich",
    "wof:placetype":"venue"
},
  "geometry": {"coordinates":[9.442713,51.32338],"type":"Point"}
}