{
  "type": "Feature",
  "properties": {
    "iso:country":"DE",
    "sg:address":"An der Feuerwache 3-5",
    "sg:city":"Garbsen",
    "sg:phone":"+49 5137/121944",
    "sg:postcode":"30823",
    "sg:province":"Niedersachsen",
    "wof:name":"Dr. S. Burmester Und K. Sellmann Ingenieurges. Mbh",
    "wof:placetype":"venue"
},
  "geometry": {"coordinates":[9.6083288193,52.4085121155],"type":"Point"}
}