{
  "type": "Feature",
  "properties": {
    "iso:country":"DE",
    "sg:address":"Winnweg 7",
    "sg:city":"Falkenstein",
    "sg:phone":"+49 3745/70542",
    "sg:postcode":"08223",
    "sg:province":"Sachsen",
    "wof:name":"J\u00fcrgen Fritzsch",
    "wof:placetype":"venue"
},
  "geometry": {"coordinates":[12.357336998,50.4663276672],"type":"Point"}
}