{
  "type": "Feature",
  "properties": {
    "iso:country":"DE",
    "sg:address":"N\u00f6rdliche Ringstr. 76",
    "sg:city":"Langen",
    "sg:phone":"+49 6103/51355",
    "sg:postcode":"63225",
    "sg:province":"Hessen",
    "wof:name":"Alexander Vogt",
    "wof:placetype":"venue"
},
  "geometry": {"coordinates":[8.6668539047,49.993183136],"type":"Point"}
}