{
  "type": "Feature",
  "properties": {
    "iso:country":"DE",
    "sg:address":"Robert-Bosch-Str. 3-7",
    "sg:city":"Riemerling",
    "sg:postcode":"85521",
    "sg:province":"Bayern",
    "wof:name":"National Computer Systems Gmbh",
    "wof:placetype":"venue"
},
  "geometry": {"coordinates":[11.6755104065,48.0561790466],"type":"Point"}
}