{
  "type": "Feature",
  "properties": {
    "iso:country":"DE",
    "sg:address":"Gerresheimer Str. 230",
    "sg:city":"Hilden",
    "sg:phone":"+49 2103/94310",
    "sg:postcode":"40721",
    "sg:province":"Nordrhein-Westfalen",
    "wof:name":"Herbert Sommermeier Steuerberater",
    "wof:placetype":"venue"
},
  "geometry": {"coordinates":[6.9254989624,51.1831588745],"type":"Point"}
}