{
  "type": "Feature",
  "properties": {
    "iso:country":"DE",
    "sg:address":"Weender Str. 31",
    "sg:city":"G\u00f6ttingen",
    "sg:phone":"+49 551/42500",
    "sg:postcode":"37073",
    "sg:province":"Niedersachsen",
    "wof:name":"Mondo Textilvertriebsges. Mbh",
    "wof:placetype":"venue"
},
  "geometry": {"coordinates":[9.9349861145,51.5344085693],"type":"Point"}
}