{
  "type": "Feature",
  "properties": {
    "iso:country":"DE",
    "sg:address":"Wilkestr. 2",
    "sg:city":"Berlin",
    "sg:phone":"+49 30/43840",
    "sg:postcode":"13507",
    "sg:province":"Berlin",
    "wof:name":"Hotel Am Tegeler See",
    "wof:placetype":"venue"
},
  "geometry": {"coordinates":[13.2750558853,52.5886993408],"type":"Point"}
}