{
  "type": "Feature",
  "properties": {
    "iso:country":"DE",
    "sg:address":"Gerlingser Weg 12 a",
    "sg:city":"Iserlohn",
    "sg:postcode":"58638",
    "sg:province":"Nordrhein-Westfalen",
    "wof:name":"Gisa Automation Gemke & S\u00e4nger Ohg",
    "wof:placetype":"venue"
},
  "geometry": {"coordinates":[7.6891851425,51.3752403259],"type":"Point"}
}