{
  "type": "Feature",
  "properties": {
    "iso:country":"DE",
    "sg:address":"Hallorenring 2",
    "sg:city":"Halle",
    "sg:phone":"+49 345/2021031",
    "sg:postcode":"06108",
    "sg:province":"Sachsen-Anhalt",
    "wof:name":"Hallmarkt-drogerie",
    "wof:placetype":"venue"
},
  "geometry": {"coordinates":[11.965827,51.482403],"type":"Point"}
}