{
  "type": "Feature",
  "properties": {
    "iso:country":"DE",
    "sg:address":"Talstr. 3",
    "sg:city":"Wedemark",
    "sg:phone":"+49 5130/2767",
    "sg:postcode":"30900",
    "sg:province":"Niedersachsen",
    "wof:name":"Christian Zu Lynar",
    "wof:placetype":"venue"
},
  "geometry": {"coordinates":[9.688046,52.550549],"type":"Point"}
}