{
  "type": "Feature",
  "properties": {
    "iso:country":"DE",
    "sg:address":"Charlottenstr. 62",
    "sg:city":"D\u00fcsseldorf",
    "sg:postcode":"40210",
    "sg:province":"Nordrhein-Westfalen",
    "wof:name":"Freelance Graphx Gmbh",
    "wof:placetype":"venue"
},
  "geometry": {"coordinates":[6.788339138,51.2216758728],"type":"Point"}
}