{
  "type": "Feature",
  "properties": {
    "iso:country":"DE",
    "sg:address":"Bonnstr. 93",
    "sg:city":"Br\u00fchl",
    "sg:phone":"+49 2232/47499",
    "sg:postcode":"50321",
    "sg:province":"Nordrhein-Westfalen",
    "wof:name":"Karl-heinz Hannes Gmbh",
    "wof:placetype":"venue"
},
  "geometry": {"coordinates":[6.904129,50.82103],"type":"Point"}
}