{
  "type": "Feature",
  "properties": {
    "iso:country":"DE",
    "sg:address":"H\u00f6hlenweg 12",
    "sg:city":"Goslar",
    "sg:phone":"+49 5321/335555",
    "sg:postcode":"38642",
    "sg:province":"Niedersachsen",
    "wof:name":"Edv-optik-partner Gmbh",
    "wof:placetype":"venue"
},
  "geometry": {"coordinates":[10.4801702499,51.8998031616],"type":"Point"}
}