{
  "type": "Feature",
  "properties": {
    "iso:country":"DE",
    "sg:address":"Ortsstr. 27",
    "sg:city":"Landsendorf",
    "sg:phone":"+49 36734/22535",
    "sg:postcode":"07338",
    "sg:province":"Th\u00fcringen",
    "wof:name":"Erhard W\u00f6ckel",
    "wof:placetype":"venue"
},
  "geometry": {"coordinates":[11.5125169754,50.5510406494],"type":"Point"}
}