{
  "type": "Feature",
  "properties": {
    "iso:country":"DE",
    "sg:address":"Gro\u00dfhurdener Berg 30",
    "sg:city":"Overath",
    "sg:postcode":"51491",
    "sg:province":"Nordrhein-Westfalen",
    "wof:name":"Gabriele Menkhaus Schreinerei Gmbh",
    "wof:placetype":"venue"
},
  "geometry": {"coordinates":[7.245991,50.954277],"type":"Point"}
}