{
  "type": "Feature",
  "properties": {
    "iso:country":"DE",
    "sg:address":"Neue Reihe 2",
    "sg:city":"K\u00fchlungsborn",
    "sg:phone":"+49 38293/6156",
    "sg:postcode":"18225",
    "sg:province":"Mecklenburg-Vorpommern",
    "wof:name":"Molli-eck Inh. Karin Stange",
    "wof:placetype":"venue"
},
  "geometry": {"coordinates":[11.7524528503,54.141368866],"type":"Point"}
}