{
  "type": "Feature",
  "properties": {
    "iso:country":"DE",
    "sg:address":"Plettenberger Str. 50",
    "sg:city":"Melle",
    "sg:phone":"+49 5422/43074",
    "sg:postcode":"49324",
    "sg:province":"Niedersachsen",
    "wof:name":"Oswald Hebisch",
    "wof:placetype":"venue"
},
  "geometry": {"coordinates":[8.33485,52.200348],"type":"Point"}
}