{
  "type": "Feature",
  "properties": {
    "iso:country":"DE",
    "sg:address":"Kirchstr. 18",
    "sg:city":"Essingen",
    "sg:phone":"+49 6347/8076",
    "sg:postcode":"76879",
    "sg:province":"Rheinland-Pfalz",
    "wof:name":"Horst Doppler",
    "wof:placetype":"venue"
},
  "geometry": {"coordinates":[8.175248,49.234962],"type":"Point"}
}