{
  "type": "Feature",
  "properties": {
    "iso:country":"DE",
    "sg:address":"Im Tr\u00e4nental 20",
    "sg:city":"Hauzenberg",
    "sg:phone":"+49 8586/1286",
    "sg:postcode":"94051",
    "sg:province":"Bayern",
    "wof:name":"Capitol",
    "wof:placetype":"venue"
},
  "geometry": {"coordinates":[13.620675,48.651966],"type":"Point"}
}