{
  "type": "Feature",
  "properties": {
    "iso:country":"DE",
    "sg:address":"Ulanenstr. 18",
    "sg:city":"Fulda",
    "sg:phone":"+49 661/44945",
    "sg:postcode":"36041",
    "sg:province":"Hessen",
    "wof:name":"H. Krack",
    "wof:placetype":"venue"
},
  "geometry": {"coordinates":[9.6531066895,50.5166969299],"type":"Point"}
}