{
  "type": "Feature",
  "properties": {
    "iso:country":"DE",
    "sg:address":"Gartroper Str. 13",
    "sg:city":"Duisburg",
    "sg:phone":"+49 203/412008",
    "sg:postcode":"47138",
    "sg:province":"Nordrhein-Westfalen",
    "wof:name":"Balkenhol Gmbh",
    "wof:placetype":"venue"
},
  "geometry": {"coordinates":[6.807474,51.471558],"type":"Point"}
}