{
  "type": "Feature",
  "properties": {
    "iso:country":"DE",
    "sg:address":"Achenbachstr. 6",
    "sg:city":"D\u00fcsseldorf",
    "sg:phone":"+49 211/661212",
    "sg:postcode":"40237",
    "sg:province":"Nordrhein-Westfalen",
    "wof:name":"Ch. Bonk",
    "wof:placetype":"venue"
},
  "geometry": {"coordinates":[6.807226,51.231895],"type":"Point"}
}