{
  "type": "Feature",
  "properties": {
    "iso:country":"DE",
    "sg:address":"M\u00fcllerstr. 51",
    "sg:city":"M\u00fcnchen",
    "sg:phone":"+49 89/2604630",
    "sg:postcode":"80469",
    "sg:province":"Bayern",
    "wof:name":"Georg Kellner",
    "wof:placetype":"venue"
},
  "geometry": {"coordinates":[11.5673599243,48.1319389343],"type":"Point"}
}