{
  "type": "Feature",
  "properties": {
    "iso:country":"DE",
    "sg:address":"Benderstr. 45",
    "sg:city":"D\u00fcsseldorf",
    "sg:phone":"+49 211/295122",
    "sg:postcode":"40625",
    "sg:province":"Nordrhein-Westfalen",
    "wof:name":"Heinrich Hamschmidt",
    "wof:placetype":"venue"
},
  "geometry": {"coordinates":[6.8553538322,51.2374267578],"type":"Point"}
}