{
  "type": "Feature",
  "properties": {
    "iso:country":"DE",
    "sg:address":"Haydnallee 6",
    "sg:city":"Reilingen",
    "sg:phone":"+49 6205/17223",
    "sg:postcode":"68799",
    "sg:province":"Baden-W\u00fcrttemberg",
    "wof:name":"K.-p. Grandenburger Rechtsanwalt",
    "wof:placetype":"venue"
},
  "geometry": {"coordinates":[8.5571813583,49.2916297913],"type":"Point"}
}