{
  "type": "Feature",
  "properties": {
    "iso:country":"DE",
    "sg:address":"Athosstr. 22a",
    "sg:city":"M\u00fcnchen",
    "sg:phone":"+49 89/646979",
    "sg:postcode":"81545",
    "sg:province":"Bayern",
    "wof:name":"Karlheinz Maciuga Pharmakaufmann",
    "wof:placetype":"venue"
},
  "geometry": {"coordinates":[11.5722703934,48.0933265686],"type":"Point"}
}