{
  "type": "Feature",
  "properties": {
    "iso:country":"DE",
    "sg:address":"Plazerstr. 2",
    "sg:city":"M\u00fcnchen",
    "sg:phone":"+49 89/718546",
    "sg:postcode":"81375",
    "sg:province":"Bayern",
    "wof:name":"H. W. Nothofer",
    "wof:placetype":"venue"
},
  "geometry": {"coordinates":[11.500021,48.115192],"type":"Point"}
}