{
  "type": "Feature",
  "properties": {
    "iso:country":"DE",
    "sg:address":"Fischerhof 31",
    "sg:city":"Hannover",
    "sg:phone":"+49 511/445153",
    "sg:postcode":"30449",
    "sg:province":"Niedersachsen",
    "wof:name":"Heinz Gausmann Ankauf Von Rohpro-",
    "wof:placetype":"venue"
},
  "geometry": {"coordinates":[9.705332756,52.3552742004],"type":"Point"}
}