{
  "type": "Feature",
  "properties": {
    "iso:country":"DE",
    "sg:address":"Masurenweg 40",
    "sg:city":"Waiblingen",
    "sg:phone":"+49 7151/18478",
    "sg:postcode":"71332",
    "sg:province":"Baden-W\u00fcrttemberg",
    "wof:name":"Saiten Fell & Firlefanz Co Angelika Maier",
    "wof:placetype":"venue"
},
  "geometry": {"coordinates":[9.3026170731,48.8179168701],"type":"Point"}
}