{
  "type": "Feature",
  "properties": {
    "iso:country":"DE",
    "sg:address":"F\u00fcnfhausenstr. 1",
    "sg:city":"Springe",
    "sg:phone":"+49 5041/2437",
    "sg:postcode":"31832",
    "sg:province":"Niedersachsen",
    "wof:name":"Becker & Fl\u00f6ge Augenoptiker",
    "wof:placetype":"venue"
},
  "geometry": {"coordinates":[9.5547294617,52.2090148926],"type":"Point"}
}