{
  "type": "Feature",
  "properties": {
    "iso:country":"DE",
    "sg:address":"Ziegelhofer Weg 2",
    "sg:city":"Quarnbek",
    "sg:phone":"+49 4340/8081",
    "sg:postcode":"24107",
    "sg:province":"Schleswig-Holstein",
    "wof:name":"Geotest Dr. A. Palasis Gmbh",
    "wof:placetype":"venue"
},
  "geometry": {"coordinates":[9.9978713989,54.3346824646],"type":"Point"}
}