{
  "type": "Feature",
  "properties": {
    "iso:country":"DE",
    "sg:address":"K\u00f6penicker Str. 115a",
    "sg:city":"Berlin",
    "sg:phone":"+49 30/5145804",
    "sg:postcode":"12683",
    "sg:province":"Berlin",
    "wof:name":"Pension Kurstation",
    "wof:placetype":"venue"
},
  "geometry": {"coordinates":[13.5630302429,52.495262146],"type":"Point"}
}