{
  "type": "Feature",
  "properties": {
    "iso:country":"DE",
    "sg:address":"Funkschneise 5",
    "sg:city":"Bremen",
    "sg:phone":"+49 421/410990",
    "sg:postcode":"28309",
    "sg:province":"Bremen",
    "wof:name":"Bresat Gmbh",
    "wof:placetype":"venue"
},
  "geometry": {"coordinates":[8.9034385681,53.0506324768],"type":"Point"}
}