{
  "type": "Feature",
  "properties": {
    "iso:country":"DE",
    "sg:address":"M\u00fcnchnerstr. 72",
    "sg:city":"Unterf\u00f6hring",
    "sg:phone":"+49 89/9503935",
    "sg:postcode":"85774",
    "sg:province":"Bayern",
    "wof:name":"Claus Mayerhofer Steuerberater",
    "wof:placetype":"venue"
},
  "geometry": {"coordinates":[11.6410150528,48.1926727295],"type":"Point"}
}