{
  "type": "Feature",
  "properties": {
    "iso:country":"DE",
    "sg:city":"Hamburg",
    "sg:postcode":"22415",
    "sg:province":"Hamburg",
    "wof:name":"Cosmobehn - Astrologie B\u00f6rse",
    "wof:placetype":"venue"
},
  "geometry": {"coordinates":[10.01221,53.646515],"type":"Point"}
}