{
  "type": "Feature",
  "properties": {
    "iso:country":"DE",
    "sg:address":"Mainzer Str. 129",
    "sg:city":"Oppenheim",
    "sg:phone":"+49 6133/2302",
    "sg:postcode":"55276",
    "sg:province":"Rheinland-Pfalz",
    "wof:name":"J. Senfter",
    "wof:placetype":"venue"
},
  "geometry": {"coordinates":[8.3555555344,49.8593139648],"type":"Point"}
}