{
  "type": "Feature",
  "properties": {
    "iso:country":"DE",
    "sg:address":"Westendorf 28",
    "sg:city":"Halberstadt",
    "sg:phone":"+49 3941/441814",
    "sg:postcode":"38820",
    "sg:province":"Sachsen-Anhalt",
    "wof:name":"G. Obst",
    "wof:placetype":"venue"
},
  "geometry": {"coordinates":[11.046235,51.89463],"type":"Point"}
}