{
  "type": "Feature",
  "properties": {
    "iso:country":"DE",
    "sg:address":"Rosenstr. 14",
    "sg:city":"Bad W\u00fcnnenberg",
    "sg:phone":"+49 2953/8817",
    "sg:postcode":"33181",
    "sg:province":"Nordrhein-Westfalen",
    "wof:name":"Loer & Schmidtmeier Innenausbau Gmbh",
    "wof:placetype":"venue"
},
  "geometry": {"coordinates":[8.699466,51.522015],"type":"Point"}
}