{
  "type": "Feature",
  "properties": {
    "iso:country":"DE",
    "sg:address":"Duvenstedter Damm 48",
    "sg:city":"Hamburg",
    "sg:phone":"+49 40/6070310",
    "sg:postcode":"22397",
    "sg:province":"Hamburg",
    "wof:name":"Aral Ag",
    "wof:placetype":"venue"
},
  "geometry": {"coordinates":[10.1128330231,53.706817627],"type":"Point"}
}