{
  "type": "Feature",
  "properties": {
    "iso:country":"DE",
    "sg:address":"Relystr. 37",
    "sg:city":"Michelstadt",
    "sg:phone":"+49 6061/5660",
    "sg:postcode":"64720",
    "sg:province":"Hessen",
    "wof:name":"Tanzschule Hinkelbein",
    "wof:placetype":"venue"
},
  "geometry": {"coordinates":[8.9921789169,49.6723747253],"type":"Point"}
}