{
  "type": "Feature",
  "properties": {
    "iso:country":"DE",
    "sg:address":"Ulmenstr. 11",
    "sg:city":"Lichtenfels",
    "sg:phone":"+49 9571/3211",
    "sg:postcode":"96215",
    "sg:province":"Bayern",
    "wof:name":"Ernita Habermann",
    "wof:placetype":"venue"
},
  "geometry": {"coordinates":[11.0268735886,50.1297950745],"type":"Point"}
}