{
  "type": "Feature",
  "properties": {
    "iso:country":"DE",
    "sg:address":"Erlbachstr. 33",
    "sg:city":"M\u00fcnchen",
    "sg:phone":"+49 89/8642157",
    "sg:postcode":"81249",
    "sg:province":"Bayern",
    "wof:name":"G\u00fcnter Schulz Architekt",
    "wof:placetype":"venue"
},
  "geometry": {"coordinates":[11.39039,48.176304],"type":"Point"}
}