{
  "type": "Feature",
  "properties": {
    "iso:country":"DE",
    "sg:address":"Tradtstr. 3-5",
    "sg:city":"Furth im Wald",
    "sg:postcode":"93437",
    "sg:province":"Bayern",
    "wof:name":"Reiseb\u00fcro Wolff Gmbh",
    "wof:placetype":"venue"
},
  "geometry": {"coordinates":[12.8392686844,49.3092880249],"type":"Point"}
}