{
  "type": "Feature",
  "properties": {
    "iso:country":"DE",
    "sg:address":"Lange Str. 22",
    "sg:city":"Malsch",
    "sg:phone":"+49 7246/8141",
    "sg:postcode":"76316",
    "sg:province":"Baden-W\u00fcrttemberg",
    "wof:name":"Kurt Ort",
    "wof:placetype":"venue"
},
  "geometry": {"coordinates":[8.334501,48.880474],"type":"Point"}
}