{
  "type": "Feature",
  "properties": {
    "iso:country":"DE",
    "sg:address":"In der Breite 8",
    "sg:city":"Gammelshausen",
    "sg:phone":"+49 7164/2921",
    "sg:postcode":"73108",
    "sg:province":"Baden-W\u00fcrttemberg",
    "wof:name":"Franz Klement Elektromeister",
    "wof:placetype":"venue"
},
  "geometry": {"coordinates":[9.648813,48.642059],"type":"Point"}
}