{
  "type": "Feature",
  "properties": {
    "iso:country":"DE",
    "sg:address":"Br\u00fcder-Grimm-Str. 4",
    "sg:city":"Rotenburg",
    "sg:phone":"+49 6623/3021",
    "sg:postcode":"36199",
    "sg:province":"Hessen",
    "wof:name":"Bolte",
    "wof:placetype":"venue"
},
  "geometry": {"coordinates":[9.73025,51.016251],"type":"Point"}
}