{
  "type": "Feature",
  "properties": {
    "iso:country":"DE",
    "sg:address":"Koblenzer Str. 16",
    "sg:city":"Nentershausen",
    "sg:postcode":"56412",
    "sg:province":"Rheinland-Pfalz",
    "wof:name":"Cecon Finanzmanagement Gmbh",
    "wof:placetype":"venue"
},
  "geometry": {"coordinates":[7.935085,50.420177],"type":"Point"}
}