{
  "type": "Feature",
  "properties": {
    "iso:country":"DE",
    "sg:address":"Feuerbachstr. 25",
    "sg:city":"R\u00fcsselsheim",
    "sg:phone":"+49 6142/57442",
    "sg:postcode":"65428",
    "sg:province":"Hessen",
    "wof:name":"Das Pferd",
    "wof:placetype":"venue"
},
  "geometry": {"coordinates":[8.445429,49.989662],"type":"Point"}
}