{
  "type": "Feature",
  "properties": {
    "iso:country":"DE",
    "sg:address":"Anstedt 13",
    "sg:city":"Scholen",
    "sg:phone":"+49 4275/475",
    "sg:postcode":"27251",
    "sg:province":"Niedersachsen",
    "wof:name":"Michael Wolf",
    "wof:placetype":"venue"
},
  "geometry": {"coordinates":[8.761101,52.725185],"type":"Point"}
}