{
  "type": "Feature",
  "properties": {
    "iso:country":"DE",
    "sg:address":"Curschmannstr. 7",
    "sg:city":"Hamburg",
    "sg:phone":"+49 40/474763",
    "sg:postcode":"20251",
    "sg:province":"Hamburg",
    "wof:name":"Horst Peters Architekt",
    "wof:placetype":"venue"
},
  "geometry": {"coordinates":[9.980731,53.585228],"type":"Point"}
}