{
  "type": "Feature",
  "properties": {
    "iso:country":"DE",
    "sg:address":"Mierendorffstr. 20",
    "sg:city":"Weinheim",
    "sg:phone":"+49 6201/13320",
    "sg:postcode":"69469",
    "sg:province":"Baden-W\u00fcrttemberg",
    "wof:name":"Schmiedel Backbetriebe Gmbh",
    "wof:placetype":"venue"
},
  "geometry": {"coordinates":[8.659596,49.543655],"type":"Point"}
}