{
  "type": "Feature",
  "properties": {
    "iso:country":"DE",
    "sg:address":"Frohnhofplatz 6",
    "sg:city":"K\u00f6ln",
    "sg:phone":"+49 221/482960",
    "sg:postcode":"50858",
    "sg:province":"Nordrhein-Westfalen",
    "wof:name":"Bernhard Schiffer",
    "wof:placetype":"venue"
},
  "geometry": {"coordinates":[6.856073,50.926544],"type":"Point"}
}