{
  "type": "Feature",
  "properties": {
    "iso:country":"DE",
    "sg:address":"Br\u00fcckenplatz 10",
    "sg:city":"Arnsberg",
    "sg:phone":"+49 2931/10705",
    "sg:postcode":"59821",
    "sg:province":"Nordrhein-Westfalen",
    "wof:name":"Mechthild Humpert",
    "wof:placetype":"venue"
},
  "geometry": {"coordinates":[8.068482,51.396221],"type":"Point"}
}