{
  "type": "Feature",
  "properties": {
    "iso:country":"DE",
    "sg:address":"H\u00fclsingsweg 1",
    "sg:city":"Bohmte",
    "sg:phone":"+49 5475/217",
    "sg:postcode":"49163",
    "sg:province":"Niedersachsen",
    "wof:name":"F. H\u00fclsing",
    "wof:placetype":"venue"
},
  "geometry": {"coordinates":[8.282132,52.453129],"type":"Point"}
}