{
  "type": "Feature",
  "properties": {
    "iso:country":"DE",
    "sg:address":"Vo\u00dfheider Str. 120",
    "sg:city":"Goch",
    "sg:phone":"+49 2823/7110",
    "sg:postcode":"47574",
    "sg:province":"Nordrhein-Westfalen",
    "wof:name":"K\u00fcppers-k\u00f6bes",
    "wof:placetype":"venue"
},
  "geometry": {"coordinates":[6.1727762222,51.6743164062],"type":"Point"}
}