{
  "type": "Feature",
  "properties": {
    "iso:country":"DE",
    "sg:address":"Tegederstr. 32",
    "sg:city":"M\u00fcnster",
    "sg:postcode":"48145",
    "sg:province":"Nordrhein-Westfalen",
    "wof:name":"P. Zahedi Ingenieur",
    "wof:placetype":"venue"
},
  "geometry": {"coordinates":[7.6567611694,51.9657554626],"type":"Point"}
}