{
  "type": "Feature",
  "properties": {
    "iso:country":"DE",
    "sg:address":"K\u00f6lner Str. 232",
    "sg:city":"M\u00fclheim",
    "sg:phone":"+49 208/485081",
    "sg:postcode":"45481",
    "sg:province":"Nordrhein-Westfalen",
    "wof:name":"Wvg Caravan-park Thrun Gmbh",
    "wof:placetype":"venue"
},
  "geometry": {"coordinates":[6.864641,51.38306],"type":"Point"}
}