{
  "type": "Feature",
  "properties": {
    "iso:country":"DE",
    "sg:address":"Obere M\u00fchlstr. 81",
    "sg:city":"Darmstadt",
    "sg:phone":"+49 6151/371134",
    "sg:postcode":"64291",
    "sg:province":"Hessen",
    "wof:name":"Heinz Appel",
    "wof:placetype":"venue"
},
  "geometry": {"coordinates":[8.664195,49.919933],"type":"Point"}
}