{
  "type": "Feature",
  "properties": {
    "iso:country":"DE",
    "sg:address":"Bergstr. 24",
    "sg:city":"Kumhausen",
    "sg:phone":"+49 871/42637",
    "sg:postcode":"84036",
    "sg:province":"Bayern",
    "wof:name":"Stelzer Ingenieurb\u00fcro",
    "wof:placetype":"venue"
},
  "geometry": {"coordinates":[12.1581783295,48.5116996765],"type":"Point"}
}