{
  "type": "Feature",
  "properties": {
    "iso:country":"DE",
    "sg:address":"Kleine Kirchstr. 8",
    "sg:city":"Nienburg",
    "sg:phone":"+49 5021/7868",
    "sg:postcode":"31582",
    "sg:province":"Niedersachsen",
    "wof:name":"B. Tsombanidou",
    "wof:placetype":"venue"
},
  "geometry": {"coordinates":[9.2076330185,52.6383247375],"type":"Point"}
}