{
  "type": "Feature",
  "properties": {
    "iso:country":"DE",
    "sg:address":"D\u00fcsseldorfer Str. 71 B",
    "sg:city":"Meerbusch",
    "sg:phone":"+49 2132/740",
    "sg:postcode":"40667",
    "sg:province":"Nordrhein-Westfalen",
    "wof:name":"Citi Mitarbeiter- Beteiligungsgesellschaft Mbh",
    "wof:placetype":"venue"
},
  "geometry": {"coordinates":[6.695874,51.245258],"type":"Point"}
}