{
  "type": "Feature",
  "properties": {
    "iso:country":"DE",
    "sg:address":"Herdentorsteinweg 41",
    "sg:city":"Bremen",
    "sg:phone":"+49 421/171714",
    "sg:postcode":"28195",
    "sg:province":"Bremen",
    "wof:name":"Bremme Und Sch\u00e4fer Rechtsanw\u00e4lte",
    "wof:placetype":"venue"
},
  "geometry": {"coordinates":[8.8117675781,53.08070755],"type":"Point"}
}