{
  "type": "Feature",
  "properties": {
    "iso:country":"DE",
    "sg:address":"Wolfshalde 81/1",
    "sg:city":"Ebersbach",
    "sg:postcode":"73061",
    "sg:province":"Baden-W\u00fcrttemberg",
    "wof:name":"Lm 43 Verwaltungsges. Mbh",
    "wof:placetype":"venue"
},
  "geometry": {"coordinates":[9.5156316757,48.7182121277],"type":"Point"}
}