{
  "type": "Feature",
  "properties": {
    "iso:country":"DE",
    "sg:address":"Alte Salzdahlumer Str. 200",
    "sg:city":"Braunschweig",
    "sg:phone":"+49 531/67592",
    "sg:postcode":"38124",
    "sg:province":"Niedersachsen",
    "wof:name":"Heinz Dunkel Architekt",
    "wof:placetype":"venue"
},
  "geometry": {"coordinates":[10.534921,52.24342],"type":"Point"}
}