{
  "type": "Feature",
  "properties": {
    "iso:country":"DE",
    "sg:address":"Kaiser-Wilhelm-Ring 17-21",
    "sg:city":"K\u00f6ln",
    "sg:phone":"+49 221/57450",
    "sg:postcode":"50672",
    "sg:province":"Nordrhein-Westfalen",
    "wof:name":"Rheinhyp Rheinische Hypothekenbank Ag",
    "wof:placetype":"venue"
},
  "geometry": {"coordinates":[6.9407258034,50.9436683655],"type":"Point"}
}