{
  "type": "Feature",
  "properties": {
    "iso:country":"DE",
    "sg:address":"Kokenauers Kamp 29",
    "sg:city":"Burgwedel",
    "sg:phone":"+49 5139/1633",
    "sg:postcode":"30938",
    "sg:province":"Niedersachsen",
    "wof:name":"Ruth K\u00fcttner",
    "wof:placetype":"venue"
},
  "geometry": {"coordinates":[9.863957,52.493298],"type":"Point"}
}