{
  "type": "Feature",
  "properties": {
    "iso:country":"DE",
    "sg:address":"Bergstr. 6",
    "sg:city":"Schorndorf",
    "sg:phone":"+49 7181/5622",
    "sg:postcode":"73614",
    "sg:province":"Baden-W\u00fcrttemberg",
    "wof:name":"Friedrich Schwarz",
    "wof:placetype":"venue"
},
  "geometry": {"coordinates":[9.5469350815,48.8443450928],"type":"Point"}
}