{
  "type": "Feature",
  "properties": {
    "iso:country":"DE",
    "sg:address":"D\u00fcrener Str. 393",
    "sg:city":"K\u00f6ln",
    "sg:postcode":"50935",
    "sg:province":"Nordrhein-Westfalen",
    "wof:name":"Dbi Der Einkaufsring E. K.",
    "wof:placetype":"venue"
},
  "geometry": {"coordinates":[6.890992,50.924862],"type":"Point"}
}