{
  "type": "Feature",
  "properties": {
    "iso:country":"DE",
    "sg:address":"Georgenstr. 61",
    "sg:city":"M\u00fcnchen",
    "sg:phone":"+49 89/596156",
    "sg:postcode":"80799",
    "sg:province":"Bayern",
    "wof:name":"Ehg - Handelsgesellschaft Entwicklung Von Marketing-",
    "wof:placetype":"venue"
},
  "geometry": {"coordinates":[11.5717840195,48.156036377],"type":"Point"}
}