{
  "type": "Feature",
  "properties": {
    "iso:country":"DE",
    "sg:address":"Marktstr. 23",
    "sg:city":"T\u00f6nisvorst",
    "sg:phone":"+49 2151/796234",
    "sg:postcode":"47918",
    "sg:province":"Nordrhein-Westfalen",
    "wof:name":"Alt St.-t\u00f6nis",
    "wof:placetype":"venue"
},
  "geometry": {"coordinates":[6.4907841682,51.3214607239],"type":"Point"}
}