{
  "type": "Feature",
  "properties": {
    "iso:country":"DE",
    "sg:address":"Kirchenallee 3 B",
    "sg:city":"Buchholz",
    "sg:postcode":"21244",
    "sg:province":"Niedersachsen",
    "wof:name":"Kirchengemeinde Spr\u00f6tze",
    "wof:placetype":"venue"
},
  "geometry": {"coordinates":[9.8067569733,53.3089637756],"type":"Point"}
}