{
  "type": "Feature",
  "properties": {
    "iso:country":"DE",
    "sg:address":"Blauenkrog 7",
    "sg:city":"Scharbeutz",
    "sg:phone":"+49 4524/70740",
    "sg:postcode":"23684",
    "sg:province":"Schleswig-Holstein",
    "wof:name":"Klingberger Bau Gmbh",
    "wof:placetype":"venue"
},
  "geometry": {"coordinates":[10.657374,54.040768],"type":"Point"}
}