{
  "type": "Feature",
  "properties": {
    "iso:country":"DE",
    "sg:address":"Ringweg 3",
    "sg:city":"Kre\u00dfberg",
    "sg:postcode":"74594",
    "sg:province":"Baden-W\u00fcrttemberg",
    "wof:name":"Midas Management- Und Beteiligungs Gmbh",
    "wof:placetype":"venue"
},
  "geometry": {"coordinates":[10.17226,49.158615],"type":"Point"}
}