{
  "type": "Feature",
  "properties": {
    "iso:country":"DE",
    "sg:address":"Am Wehrhahn 100",
    "sg:city":"D\u00fcsseldorf",
    "sg:phone":"+49 211/17711200",
    "sg:postcode":"40211",
    "sg:province":"Nordrhein-Westfalen",
    "wof:name":"Cornelsen Verlag Schwann Girardet Verwalt. Gmbh",
    "wof:placetype":"venue"
},
  "geometry": {"coordinates":[6.7966961861,51.2297859192],"type":"Point"}
}