{
  "type": "Feature",
  "properties": {
    "iso:country":"DE",
    "sg:address":"Bendenweg 44 a",
    "sg:city":"Bad M\u00fcnstereifel",
    "sg:phone":"+49 2253/3046",
    "sg:postcode":"53902",
    "sg:province":"Nordrhein-Westfalen",
    "wof:name":"E. A. G. Elektro Anlagenbau Gmbh",
    "wof:placetype":"venue"
},
  "geometry": {"coordinates":[6.7645797729,50.5738601685],"type":"Point"}
}