{
  "type": "Feature",
  "properties": {
    "iso:country":"DE",
    "sg:address":"Westfalenstr. 27",
    "sg:city":"Troisdorf",
    "sg:phone":"+49 2241/391039",
    "sg:postcode":"53844",
    "sg:province":"Nordrhein-Westfalen",
    "wof:name":"U. Sa\u00df Rechtsanwalt",
    "wof:placetype":"venue"
},
  "geometry": {"coordinates":[7.1197729111,50.8113441467],"type":"Point"}
}