{
  "type": "Feature",
  "properties": {
    "iso:country":"DE",
    "sg:address":"Neustr. 70",
    "sg:city":"Sontheim",
    "sg:phone":"+49 7325/3660",
    "sg:postcode":"89567",
    "sg:province":"Baden-W\u00fcrttemberg",
    "wof:name":"Erich Diepold",
    "wof:placetype":"venue"
},
  "geometry": {"coordinates":[10.292224,48.550743],"type":"Point"}
}