{
  "type": "Feature",
  "properties": {
    "iso:country":"DE",
    "sg:address":"Alpenstr. 29",
    "sg:city":"Bobingen",
    "sg:phone":"+49 8234/902203",
    "sg:postcode":"86399",
    "sg:province":"Bayern",
    "wof:name":"Information, Links, Hardware, Software, B\u00fccher",
    "wof:placetype":"venue"
},
  "geometry": {"coordinates":[10.825674,48.262024],"type":"Point"}
}