{
  "type": "Feature",
  "properties": {
    "iso:country":"DE",
    "sg:address":"Schwalbenstr. 11",
    "sg:city":"Schwerin",
    "sg:phone":"+49 385/711782",
    "sg:postcode":"19057",
    "sg:province":"Mecklenburg-Vorpommern",
    "wof:name":"Karl Danielis",
    "wof:placetype":"venue"
},
  "geometry": {"coordinates":[11.3753671646,53.6297798157],"type":"Point"}
}