{
  "type": "Feature",
  "properties": {
    "iso:country":"DE",
    "sg:address":"Clara-Zetkin-Str. 26",
    "sg:city":"Beelitz",
    "sg:phone":"+49 33204/42546",
    "sg:postcode":"14547",
    "sg:province":"Brandenburg",
    "wof:name":"Petra Pieczonka",
    "wof:placetype":"venue"
},
  "geometry": {"coordinates":[12.972303,52.236641],"type":"Point"}
}