{
  "type": "Feature",
  "properties": {
    "iso:country":"DE",
    "sg:address":"Bergstr. 4",
    "sg:city":"Wettringen",
    "sg:phone":"+49 2557/1232",
    "sg:postcode":"48493",
    "sg:province":"Nordrhein-Westfalen",
    "wof:name":"Gastst\u00e4tte Anni Eilers",
    "wof:placetype":"venue"
},
  "geometry": {"coordinates":[7.3192129135,52.2098503113],"type":"Point"}
}