{
  "type": "Feature",
  "properties": {
    "iso:country":"DE",
    "sg:address":"Hopfengarten 15",
    "sg:city":"Cremlingen",
    "sg:phone":"+49 5306/5011",
    "sg:postcode":"38162",
    "sg:province":"Niedersachsen",
    "wof:name":"Volkmar Fischer",
    "wof:placetype":"venue"
},
  "geometry": {"coordinates":[10.6255578995,52.2719078064],"type":"Point"}
}