{
  "type": "Feature",
  "properties": {
    "iso:country":"DE",
    "sg:address":"Stromberger Str. 39",
    "sg:city":"Weiler",
    "sg:phone":"+49 6721/33639",
    "sg:postcode":"55413",
    "sg:province":"Rheinland-Pfalz",
    "wof:name":"Eugen Und Marianne Bootz",
    "wof:placetype":"venue"
},
  "geometry": {"coordinates":[7.8487958908,50.0106658936],"type":"Point"}
}