{
  "type": "Feature",
  "properties": {
    "iso:country":"DE",
    "sg:address":"An der Ling 27",
    "sg:city":"K\u00f6ln",
    "sg:postcode":"50739",
    "sg:province":"Nordrhein-Westfalen",
    "wof:name":"Linggao Gmbh",
    "wof:placetype":"venue"
},
  "geometry": {"coordinates":[6.91331,50.992592],"type":"Point"}
}