{
  "type": "Feature",
  "properties": {
    "iso:country":"DE",
    "sg:address":"Louise-Seidler-Str. 23",
    "sg:city":"Dresden",
    "sg:phone":"+49 351/4767357",
    "sg:postcode":"01217",
    "sg:province":"Sachsen",
    "wof:name":"Lothar D\u00f6rffel",
    "wof:placetype":"venue"
},
  "geometry": {"coordinates":[13.7517614365,51.0207290649],"type":"Point"}
}