{
  "type": "Feature",
  "properties": {
    "iso:country":"DE",
    "sg:address":"Kornbergweg 45",
    "sg:city":"Peine",
    "sg:phone":"+49 5171/3585",
    "sg:postcode":"31224",
    "sg:province":"Niedersachsen",
    "wof:name":"Lutz Bolte",
    "wof:placetype":"venue"
},
  "geometry": {"coordinates":[10.227722168,52.3308181763],"type":"Point"}
}