{
  "type": "Feature",
  "properties": {
    "iso:country":"DE",
    "sg:address":"Schulplatz 9",
    "sg:city":"Heidelberg",
    "sg:postcode":"69123",
    "sg:province":"Baden-W\u00fcrttemberg",
    "wof:name":"Redaktion Vereins-nachrichten Turn- Und Sportverein 1949",
    "wof:placetype":"venue"
},
  "geometry": {"coordinates":[8.6459646225,49.4004211426],"type":"Point"}
}