{
  "type": "Feature",
  "properties": {
    "iso:country":"DE",
    "sg:address":"Davenstedter Holz 30",
    "sg:city":"Hannover",
    "sg:phone":"+49 511/480230",
    "sg:postcode":"30455",
    "sg:province":"Niedersachsen",
    "wof:name":"Erika Boroski",
    "wof:placetype":"venue"
},
  "geometry": {"coordinates":[9.6645641327,52.3701286316],"type":"Point"}
}