{
  "type": "Feature",
  "properties": {
    "iso:country":"DE",
    "sg:address":"Lindenstr. 39",
    "sg:city":"Neubrandenburg",
    "sg:postcode":"17033",
    "sg:province":"Mecklenburg-Vorpommern",
    "wof:name":"Automation Und Software G\u00fcnther Tausch Gmbh",
    "wof:placetype":"venue"
},
  "geometry": {"coordinates":[13.2605352402,53.5374603271],"type":"Point"}
}