{
  "type": "Feature",
  "properties": {
    "iso:country":"DE",
    "sg:address":"Riffhaldenweg 31",
    "sg:city":"Triberg",
    "sg:phone":"+49 7722/4708",
    "sg:postcode":"78098",
    "sg:province":"Baden-W\u00fcrttemberg",
    "wof:name":"G\u00e4stehaus Riffhalde",
    "wof:placetype":"venue"
},
  "geometry": {"coordinates":[8.2314157486,48.1317901611],"type":"Point"}
}