{
  "type": "Feature",
  "properties": {
    "iso:country":"DE",
    "sg:address":"An der Emsbr\u00fccke 13",
    "sg:city":"Leer",
    "sg:phone":"+49 491/3874",
    "sg:postcode":"26789",
    "sg:province":"Niedersachsen",
    "wof:name":"Uwe Blank",
    "wof:placetype":"venue"
},
  "geometry": {"coordinates":[7.4330620766,53.2159996033],"type":"Point"}
}