{
  "type": "Feature",
  "properties": {
    "iso:country":"DE",
    "sg:address":"Rheinstr. 2",
    "sg:city":"Weisweil",
    "sg:phone":"+49 7646/913232",
    "sg:postcode":"79367",
    "sg:province":"Baden-W\u00fcrttemberg",
    "wof:name":"J. Kurpjuweit",
    "wof:placetype":"venue"
},
  "geometry": {"coordinates":[7.674726,48.198277],"type":"Point"}
}