{
  "type": "Feature",
  "properties": {
    "iso:country":"DE",
    "sg:address":"K\u00f6lner Str. 44",
    "sg:city":"Frankfurt",
    "sg:phone":"+49 69/735788",
    "sg:postcode":"60327",
    "sg:province":"Hessen",
    "wof:name":"Wacker Consult Gmbh",
    "wof:placetype":"venue"
},
  "geometry": {"coordinates":[8.6481599808,50.1075744629],"type":"Point"}
}