{
  "type": "Feature",
  "properties": {
    "iso:country":"DE",
    "sg:address":"Eckenheimer Landstr. 192",
    "sg:city":"Frankfurt",
    "sg:phone":"+49 69/592430",
    "sg:postcode":"60320",
    "sg:province":"Hessen",
    "wof:name":"Blumen Am Hauptfriedhof A. R\u00fcckwardt",
    "wof:placetype":"venue"
},
  "geometry": {"coordinates":[8.684385,50.135464],"type":"Point"}
}