{
  "type": "Feature",
  "properties": {
    "iso:country":"DE",
    "sg:address":"Hindenburgring Nord 1",
    "sg:city":"Kitzingen",
    "sg:phone":"+49 9321/22445",
    "sg:postcode":"97318",
    "sg:province":"Bayern",
    "wof:name":"Hartner Und Ernst",
    "wof:placetype":"venue"
},
  "geometry": {"coordinates":[10.155579,49.738197],"type":"Point"}
}