{
  "type": "Feature",
  "properties": {
    "iso:country":"DE",
    "sg:address":"Hockenheimer Str. 66",
    "sg:city":"Altlu\u00dfheim",
    "sg:phone":"+49 6205/392624",
    "sg:postcode":"68804",
    "sg:province":"Baden-W\u00fcrttemberg",
    "wof:name":"Rheinfranken-halle",
    "wof:placetype":"venue"
},
  "geometry": {"coordinates":[8.5045490265,49.3049850464],"type":"Point"}
}