{
  "type": "Feature",
  "properties": {
    "iso:country":"DE",
    "sg:address":"Buchenhofener Str. 33",
    "sg:city":"Wuppertal",
    "sg:phone":"+49 202/785454",
    "sg:postcode":"42329",
    "sg:province":"Nordrhein-Westfalen",
    "wof:name":"Maler-einkauf Rhein-ruhr Eg",
    "wof:placetype":"venue"
},
  "geometry": {"coordinates":[7.1087508202,51.2262496948],"type":"Point"}
}