{
  "type": "Feature",
  "properties": {
    "iso:country":"DE",
    "sg:address":"D\u00fcrnhauser Str. 10",
    "sg:city":"Habach",
    "sg:phone":"+49 8847/697259",
    "sg:postcode":"82392",
    "sg:province":"Bayern",
    "wof:name":"Oberland Arms Hainich & Satzinger Ohg",
    "wof:placetype":"venue"
},
  "geometry": {"coordinates":[11.2827711105,47.7295188904],"type":"Point"}
}