{
  "type": "Feature",
  "properties": {
    "iso:country":"DE",
    "sg:address":"Am Goldbach 29",
    "sg:city":"Obermaiselstein",
    "sg:phone":"+49 8326/1786",
    "sg:postcode":"87538",
    "sg:province":"Bayern",
    "wof:name":"Peter Schneider Gmbh",
    "wof:placetype":"venue"
},
  "geometry": {"coordinates":[10.2466583252,47.4440383911],"type":"Point"}
}