{
  "type": "Feature",
  "properties": {
    "iso:country":"DE",
    "sg:address":"L\u00e4rchenweg 1",
    "sg:city":"Obertraubling",
    "sg:phone":"+49 9401/5683",
    "sg:postcode":"93083",
    "sg:province":"Bayern",
    "wof:name":"Helmut Hacker",
    "wof:placetype":"venue"
},
  "geometry": {"coordinates":[12.149107,48.961994],"type":"Point"}
}