{
  "type": "Feature",
  "properties": {
    "iso:country":"DE",
    "sg:address":"F\u00fcrstenfelder Str. 11",
    "sg:city":"M\u00fcnchen",
    "sg:phone":"+49 89/266304",
    "sg:postcode":"80331",
    "sg:province":"Bayern",
    "wof:name":"Max Gruber",
    "wof:placetype":"venue"
},
  "geometry": {"coordinates":[11.572716,48.137005],"type":"Point"}
}