{
  "type": "Feature",
  "properties": {
    "iso:country":"DE",
    "sg:address":"Gardessener Str. 32",
    "sg:city":"Cremlingen",
    "sg:phone":"+49 5306/2353",
    "sg:postcode":"38162",
    "sg:province":"Niedersachsen",
    "wof:name":"Christian Dietz",
    "wof:placetype":"venue"
},
  "geometry": {"coordinates":[10.697468,52.266804],"type":"Point"}
}