{
  "type": "Feature",
  "properties": {
    "iso:country":"DE",
    "sg:address":"Markt 1",
    "sg:city":"Mutzschen",
    "sg:phone":"+49 34385/51256",
    "sg:postcode":"04688",
    "sg:province":"Sachsen",
    "wof:name":"Kronen-apotheke Inh. Lutz H\u00fcnermund",
    "wof:placetype":"venue"
},
  "geometry": {"coordinates":[12.887203,51.260536],"type":"Point"}
}