{
  "type": "Feature",
  "properties": {
    "iso:country":"DE",
    "sg:address":"Diewergarten",
    "sg:city":"Kelberg",
    "sg:phone":"+49 2692/92030",
    "sg:postcode":"53539",
    "sg:province":"Rheinland-Pfalz",
    "wof:name":"Plamex Maschinenbau Gmbh",
    "wof:placetype":"venue"
},
  "geometry": {"coordinates":[6.923233,50.288506],"type":"Point"}
}