{
  "type": "Feature",
  "properties": {
    "iso:country":"DE",
    "sg:address":"Tannenweg",
    "sg:city":"Rees",
    "sg:phone":"+49 2851/7724",
    "sg:postcode":"46459",
    "sg:province":"Nordrhein-Westfalen",
    "wof:name":"Bdk Reisen",
    "wof:placetype":"venue"
},
  "geometry": {"coordinates":[6.379325,51.770226],"type":"Point"}
}