{
  "type": "Feature",
  "properties": {
    "iso:country":"DE",
    "sg:address":"Westenmauer 49",
    "sg:city":"Kamen",
    "sg:phone":"+49 2307/12959",
    "sg:postcode":"59174",
    "sg:province":"Nordrhein-Westfalen",
    "wof:name":"Haus Recker",
    "wof:placetype":"venue"
},
  "geometry": {"coordinates":[7.65670681,51.5928115845],"type":"Point"}
}