{
  "type": "Feature",
  "properties": {
    "iso:country":"DE",
    "sg:address":"Bielefelder Str. 58",
    "sg:city":"Lennestadt",
    "sg:phone":"+49 2721/20294",
    "sg:postcode":"57368",
    "sg:province":"Nordrhein-Westfalen",
    "wof:name":"Gert Breiting",
    "wof:placetype":"venue"
},
  "geometry": {"coordinates":[8.06935215,51.1488075256],"type":"Point"}
}