{
  "type": "Feature",
  "properties": {
    "iso:country":"DE",
    "sg:address":"Waldstr. 21",
    "sg:city":"Hohenstein",
    "sg:postcode":"65329",
    "sg:province":"Hessen",
    "wof:name":"Procasa Immobilienmanagement Inh. Gabi Nitsch E. K.",
    "wof:placetype":"venue"
},
  "geometry": {"coordinates":[8.131731987,50.2045059204],"type":"Point"}
}