{
  "type": "Feature",
  "properties": {
    "iso:country":"DE",
    "sg:address":"Gertrudisstr. 8",
    "sg:city":"Solingen",
    "sg:phone":"+49 212/51418",
    "sg:postcode":"42651",
    "sg:province":"Nordrhein-Westfalen",
    "wof:name":"Wilhelm K\u00f6nig",
    "wof:placetype":"venue"
},
  "geometry": {"coordinates":[7.0887317657,51.1796531677],"type":"Point"}
}