{
  "type": "Feature",
  "properties": {
    "iso:country":"DE",
    "sg:address":"Zeppelinstr. 14",
    "sg:city":"Ostfildern",
    "sg:phone":"+49 711/4587093",
    "sg:postcode":"73760",
    "sg:province":"Baden-W\u00fcrttemberg",
    "wof:name":"V\u00f6lmle & Rickert Gmbh & Co. Kg",
    "wof:placetype":"venue"
},
  "geometry": {"coordinates":[9.2281637192,48.7230873108],"type":"Point"}
}