{
  "type": "Feature",
  "properties": {
    "iso:country":"DE",
    "sg:address":"B\u00fcckebergstr. 8",
    "sg:city":"Hee\u00dfen",
    "sg:phone":"+49 5722/84396",
    "sg:postcode":"31707",
    "sg:province":"Niedersachsen",
    "wof:name":"Bdv Hee\u00dfen Josef Bernert",
    "wof:placetype":"venue"
},
  "geometry": {"coordinates":[9.1074724197,52.2341880798],"type":"Point"}
}