{
  "type": "Feature",
  "properties": {
    "iso:country":"DE",
    "sg:address":"Berliner Str. 53",
    "sg:city":"Fehrbellin",
    "sg:postcode":"16833",
    "sg:province":"Brandenburg",
    "wof:name":"Dieter Tack",
    "wof:placetype":"venue"
},
  "geometry": {"coordinates":[12.78671,52.805508],"type":"Point"}
}