{
  "type": "Feature",
  "properties": {
    "iso:country":"DE",
    "sg:address":"Amselweg 21",
    "sg:city":"Adendorf",
    "sg:phone":"+49 4131/18302",
    "sg:postcode":"21365",
    "sg:province":"Niedersachsen",
    "wof:name":"Heinz Korittke",
    "wof:placetype":"venue"
},
  "geometry": {"coordinates":[10.436603,53.279892],"type":"Point"}
}