{
  "type": "Feature",
  "properties": {
    "iso:country":"DE",
    "sg:address":"Marburger Str. 17",
    "sg:city":"Berlin",
    "sg:phone":"+49 30/21968374",
    "sg:postcode":"10789",
    "sg:province":"Berlin",
    "wof:name":"Luxury Shoes Vertriebsges. Mbh",
    "wof:placetype":"venue"
},
  "geometry": {"coordinates":[13.337557,52.503315],"type":"Point"}
}