{
  "type": "Feature",
  "properties": {
    "iso:country":"DE",
    "sg:address":"Steinstr. 35",
    "sg:city":"Brandenburg",
    "sg:phone":"+49 3381/224144",
    "sg:postcode":"14776",
    "sg:province":"Brandenburg",
    "wof:name":"Friseur Und Kosmetik Gmbh",
    "wof:placetype":"venue"
},
  "geometry": {"coordinates":[12.5584440231,52.4061965942],"type":"Point"}
}