{
  "type": "Feature",
  "properties": {
    "iso:country":"DE",
    "sg:address":"Am Gro\u00dfen Geeren 67",
    "sg:city":"Ritterhude",
    "sg:phone":"+49 4292/1393",
    "sg:postcode":"27721",
    "sg:province":"Niedersachsen",
    "wof:name":"A. Grubert Drogerie",
    "wof:placetype":"venue"
},
  "geometry": {"coordinates":[8.747034,53.188435],"type":"Point"}
}