{
  "type": "Feature",
  "properties": {
    "iso:country":"DE",
    "sg:address":"Bettenried 8",
    "sg:city":"Ofterschwang",
    "sg:phone":"+49 8321/85423",
    "sg:postcode":"87527",
    "sg:province":"Bayern",
    "wof:name":"E. Schidlowski Versandgesch\u00e4ft",
    "wof:placetype":"venue"
},
  "geometry": {"coordinates":[10.2424650192,47.5071220398],"type":"Point"}
}