{
  "type": "Feature",
  "properties": {
    "iso:country":"DE",
    "sg:address":"Heinsestr. 25",
    "sg:city":"Berlin",
    "sg:phone":"+49 30/4044945",
    "sg:postcode":"13467",
    "sg:province":"Berlin",
    "wof:name":"Neptun-apotheke",
    "wof:placetype":"venue"
},
  "geometry": {"coordinates":[13.308114,52.615532],"type":"Point"}
}