{
  "type": "Feature",
  "properties": {
    "iso:country":"DE",
    "sg:address":"Erdersche Str. 26",
    "sg:city":"Kalletal",
    "sg:phone":"+49 5733/2411",
    "sg:postcode":"32689",
    "sg:province":"Nordrhein-Westfalen",
    "wof:name":"Erwin Potthast Elektroinstallation",
    "wof:placetype":"venue"
},
  "geometry": {"coordinates":[8.935376,52.18277],"type":"Point"}
}