{
  "type": "Feature",
  "properties": {
    "iso:country":"DE",
    "sg:address":"Calwer Str. 11",
    "sg:city":"Stuttgart",
    "sg:phone":"+49 711/294267",
    "sg:postcode":"70173",
    "sg:province":"Baden-W\u00fcrttemberg",
    "wof:name":"Restaurant Kegelcenter",
    "wof:placetype":"venue"
},
  "geometry": {"coordinates":[9.1748228073,48.7767944336],"type":"Point"}
}