{
  "type": "Feature",
  "properties": {
    "iso:country":"DE",
    "sg:address":"Herrenberger Str. 34",
    "sg:city":"T\u00fcbingen",
    "sg:phone":"+49 7071/43386",
    "sg:postcode":"72070",
    "sg:province":"Baden-W\u00fcrttemberg",
    "wof:name":"Restaurant Marquardtei",
    "wof:placetype":"venue"
},
  "geometry": {"coordinates":[9.0472316742,48.523979187],"type":"Point"}
}