{
  "type": "Feature",
  "properties": {
    "iso:country":"DE",
    "sg:address":"Kurtalstr. 83-85",
    "sg:city":"Bad Bergzabern",
    "sg:phone":"+49 6343/9420",
    "sg:postcode":"76887",
    "sg:province":"Rheinland-Pfalz",
    "wof:name":"Sot Verm\u00f6gensverwaltungs Gmbh",
    "wof:placetype":"venue"
},
  "geometry": {"coordinates":[7.9718680382,49.1020698547],"type":"Point"}
}