{
  "type": "Feature",
  "properties": {
    "iso:country":"DE",
    "sg:address":"Neustrelitzer Str. 4",
    "sg:city":"D\u00fcsseldorf",
    "sg:phone":"+49 211/704986",
    "sg:postcode":"40595",
    "sg:province":"Nordrhein-Westfalen",
    "wof:name":"Gerd Neuhaus Drogerist",
    "wof:placetype":"venue"
},
  "geometry": {"coordinates":[6.896188,51.149883],"type":"Point"}
}