{
  "type": "Feature",
  "properties": {
    "iso:country":"DE",
    "sg:address":"Seeleitenstr. 27",
    "sg:city":"Weitramsdorf",
    "sg:phone":"+49 9567/921092",
    "sg:postcode":"96479",
    "sg:province":"Bayern",
    "wof:name":"Gunter Br\u00fcckner Gmbh",
    "wof:placetype":"venue"
},
  "geometry": {"coordinates":[10.870347023,50.2368278503],"type":"Point"}
}