{
  "type": "Feature",
  "properties": {
    "iso:country":"DE",
    "sg:address":"Bleibtreustr. 33",
    "sg:city":"Berlin",
    "sg:phone":"+49 30/8859340",
    "sg:postcode":"10707",
    "sg:province":"Berlin",
    "wof:name":"Gg-grundfonds Immobilien- Management Gmbh",
    "wof:placetype":"venue"
},
  "geometry": {"coordinates":[13.319527,52.500751],"type":"Point"}
}