{
  "type": "Feature",
  "properties": {
    "iso:country":"DE",
    "sg:address":"Reinh\u00e4user Str. 8",
    "sg:city":"Gleichen",
    "sg:phone":"+49 551/791970",
    "sg:postcode":"37130",
    "sg:province":"Niedersachsen",
    "wof:name":"Walter B\u00e4te",
    "wof:placetype":"venue"
},
  "geometry": {"coordinates":[9.9754495621,51.486114502],"type":"Point"}
}