{
  "type": "Feature",
  "properties": {
    "iso:country":"DE",
    "sg:address":"H\u00e4ringstein 6",
    "sg:city":"Albstadt",
    "sg:phone":"+49 7431/2572",
    "sg:postcode":"72458",
    "sg:province":"Baden-W\u00fcrttemberg",
    "wof:name":"Ev. Method. Pfarramt",
    "wof:placetype":"venue"
},
  "geometry": {"coordinates":[9.0296583176,48.2148628235],"type":"Point"}
}