{
  "type": "Feature",
  "properties": {
    "iso:country":"DE",
    "sg:address":"Semmelstr. 63",
    "sg:city":"W\u00fcrzburg",
    "sg:phone":"+49 931/51259",
    "sg:postcode":"97070",
    "sg:province":"Bayern",
    "wof:name":"Eberhard R\u00fcb",
    "wof:placetype":"venue"
},
  "geometry": {"coordinates":[9.9380970001,49.797744751],"type":"Point"}
}