{
  "type": "Feature",
  "properties": {
    "iso:country":"DE",
    "sg:address":"Bahnhofstr. 8",
    "sg:city":"Warstein",
    "sg:phone":"+49 2902/71030",
    "sg:postcode":"59581",
    "sg:province":"Nordrhein-Westfalen",
    "wof:name":"Hubert B\u00f6lling",
    "wof:placetype":"venue"
},
  "geometry": {"coordinates":[8.335991,51.485634],"type":"Point"}
}