{
  "type": "Feature",
  "properties": {
    "iso:country":"DE",
    "sg:address":"Am Wall 10",
    "sg:city":"Schillingsf\u00fcrst",
    "sg:phone":"+49 9868/7406",
    "sg:postcode":"91583",
    "sg:province":"Bayern",
    "wof:name":"Weinstube Schlo\u00dfcafe",
    "wof:placetype":"venue"
},
  "geometry": {"coordinates":[10.2604160309,49.2897262573],"type":"Point"}
}