{
  "type": "Feature",
  "properties": {
    "iso:country":"DE",
    "sg:address":"Bornh\u00f6vedstr. 47",
    "sg:city":"Schwerin",
    "sg:phone":"+49 385/5574556",
    "sg:postcode":"19055",
    "sg:province":"Mecklenburg-Vorpommern",
    "wof:name":"Dr. Dieckmann Immobilienmakler",
    "wof:placetype":"venue"
},
  "geometry": {"coordinates":[11.4296779633,53.6352996826],"type":"Point"}
}