{
  "type": "Feature",
  "properties": {
    "iso:country":"DE",
    "sg:address":"Am Thorn 10",
    "sg:city":"Minden",
    "sg:phone":"+49 571/41991",
    "sg:postcode":"32425",
    "sg:province":"Nordrhein-Westfalen",
    "wof:name":"Helmut Altvater",
    "wof:placetype":"venue"
},
  "geometry": {"coordinates":[8.86816,52.314629],"type":"Point"}
}