{
  "type": "Feature",
  "properties": {
    "iso:country":"DE",
    "sg:address":"Kiefernstr. 20",
    "sg:city":"Cottbus",
    "sg:phone":"+49 355/532408",
    "sg:postcode":"03048",
    "sg:province":"Brandenburg",
    "wof:name":"Ronald Kirst",
    "wof:placetype":"venue"
},
  "geometry": {"coordinates":[14.299846,51.728703],"type":"Point"}
}