{
  "type": "Feature",
  "properties": {
    "iso:country":"DE",
    "sg:address":"Marktstr. 2",
    "sg:city":"Neukirchen",
    "sg:phone":"+49 9947/1255",
    "sg:postcode":"93453",
    "sg:province":"Bayern",
    "wof:name":"Kurt Kling Notar",
    "wof:placetype":"venue"
},
  "geometry": {"coordinates":[12.9703845978,49.2592849731],"type":"Point"}
}