{
  "type": "Feature",
  "properties": {
    "iso:country":"DE",
    "sg:address":"Weinbergstr. 25",
    "sg:city":"Oberursel",
    "sg:phone":"+49 6171/37294",
    "sg:postcode":"61440",
    "sg:province":"Hessen",
    "wof:name":"Ev. Pfarramt Oberstedten",
    "wof:placetype":"venue"
},
  "geometry": {"coordinates":[8.5808744431,50.2272224426],"type":"Point"}
}