{
  "type": "Feature",
  "properties": {
    "iso:country":"DE",
    "sg:address":"Kreuzweg 3",
    "sg:city":"Hasel\u00fcnne",
    "sg:phone":"+49 5961/94310",
    "sg:postcode":"49740",
    "sg:province":"Niedersachsen",
    "wof:name":"G\u00f6diker Gmbh",
    "wof:placetype":"venue"
},
  "geometry": {"coordinates":[7.49681,52.67572],"type":"Point"}
}