{
  "type": "Feature",
  "properties": {
    "iso:country":"DE",
    "sg:address":"Wetzelstr. 1",
    "sg:city":"M\u00fcnchen",
    "sg:phone":"+49 89/74979200",
    "sg:postcode":"81479",
    "sg:province":"Bayern",
    "wof:name":"Parf\u00fcmerie Yaska",
    "wof:placetype":"venue"
},
  "geometry": {"coordinates":[11.519721,48.07766],"type":"Point"}
}