{
  "type": "Feature",
  "properties": {
    "iso:country":"DE",
    "sg:address":"Hauptstr. 41",
    "sg:city":"Aulendorf",
    "sg:phone":"+49 7525/911160",
    "sg:postcode":"88326",
    "sg:province":"Baden-W\u00fcrttemberg",
    "wof:name":"Sv Versicherung Ag",
    "wof:placetype":"venue"
},
  "geometry": {"coordinates":[9.6378650665,47.953792572],"type":"Point"}
}