{
  "type": "Feature",
  "properties": {
    "iso:country":"DE",
    "sg:address":"T\u00fcngentaler Str. 2",
    "sg:city":"Schw\u00e4bisch Hall",
    "sg:phone":"+49 791/2769",
    "sg:postcode":"74523",
    "sg:province":"Baden-W\u00fcrttemberg",
    "wof:name":"Foto Weller Gmbh",
    "wof:placetype":"venue"
},
  "geometry": {"coordinates":[9.7476119995,49.1119537354],"type":"Point"}
}