{
  "type": "Feature",
  "properties": {
    "iso:country":"DE",
    "sg:address":"Schondorf",
    "sg:city":"Schondorf",
    "sg:phone":"+49 8192/1066",
    "sg:postcode":"86938",
    "sg:province":"Bayern",
    "wof:name":"Volksbank Die\u00dfen Eg",
    "wof:placetype":"venue"
},
  "geometry": {"coordinates":[11.09128,48.052528],"type":"Point"}
}