{
  "type": "Feature",
  "properties": {
    "iso:country":"DE",
    "sg:address":"Waldmeisterstr. 47",
    "sg:city":"M\u00fcnchen",
    "sg:phone":"+49 89/3517294",
    "sg:postcode":"80935",
    "sg:province":"Bayern",
    "wof:name":"Wolfgang Kletter Werkzeuge",
    "wof:placetype":"venue"
},
  "geometry": {"coordinates":[11.547961235,48.197845459],"type":"Point"}
}