{
  "type": "Feature",
  "properties": {
    "iso:country":"DE",
    "sg:address":"Hauensteinstr. 7",
    "sg:city":"Bad S\u00e4ckingen",
    "sg:phone":"+49 7761/56880",
    "sg:postcode":"79713",
    "sg:province":"Baden-W\u00fcrttemberg",
    "wof:name":"Gutmann Und Hansmann Rechtsanw\u00e4lte",
    "wof:placetype":"venue"
},
  "geometry": {"coordinates":[7.9456849098,47.5516967773],"type":"Point"}
}