{
  "type": "Feature",
  "properties": {
    "iso:country":"DE",
    "sg:address":"Alpenstr. 16",
    "sg:city":"Augsburg",
    "sg:phone":"+49 821/583118",
    "sg:postcode":"86159",
    "sg:province":"Bayern",
    "wof:name":"Ristorante La Gondola",
    "wof:placetype":"venue"
},
  "geometry": {"coordinates":[10.8955974579,48.3579597473],"type":"Point"}
}