{
  "type": "Feature",
  "properties": {
    "iso:country":"DE",
    "sg:address":"Ulmenweg 12",
    "sg:city":"Ro\u00dfdorf",
    "sg:phone":"+49 6071/44293",
    "sg:postcode":"64380",
    "sg:province":"Hessen",
    "wof:name":"J\u00f6rg Wellmann Gmbh",
    "wof:placetype":"venue"
},
  "geometry": {"coordinates":[8.779951,49.868607],"type":"Point"}
}