{
  "type": "Feature",
  "properties": {
    "iso:country":"DE",
    "sg:address":"Rudolf-Krahl-Str. 38",
    "sg:city":"Chemnitz",
    "sg:phone":"+49 371/362095",
    "sg:postcode":"09116",
    "sg:province":"Sachsen",
    "wof:name":"S\u00e4chs.-vogtl. Bierhof",
    "wof:placetype":"venue"
},
  "geometry": {"coordinates":[12.8767127991,50.837562561],"type":"Point"}
}