{
  "type": "Feature",
  "properties": {
    "iso:country":"DE",
    "sg:address":"Ringstr. 7",
    "sg:city":"Rehm-Flehde-Bargen",
    "sg:phone":"+49 4837/288",
    "sg:postcode":"25776",
    "sg:province":"Schleswig-Holstein",
    "wof:name":"Johann-hinrich Hansen",
    "wof:placetype":"venue"
},
  "geometry": {"coordinates":[9.050222,54.27475],"type":"Point"}
}