{
  "type": "Feature",
  "properties": {
    "iso:country":"DE",
    "sg:address":"Sackelhauser Str. 13",
    "sg:city":"Wannweil",
    "sg:phone":"+49 7121/577243",
    "sg:postcode":"72827",
    "sg:province":"Baden-W\u00fcrttemberg",
    "wof:name":"I.-l. Hallabrin",
    "wof:placetype":"venue"
},
  "geometry": {"coordinates":[9.1529998779,48.5106582642],"type":"Point"}
}