{
  "type": "Feature",
  "properties": {
    "iso:country":"DE",
    "sg:address":"Waisenhofstr. 39",
    "sg:city":"Kiel",
    "sg:phone":"+49 431/96111",
    "sg:postcode":"24103",
    "sg:province":"Schleswig-Holstein",
    "wof:name":"T. Boos",
    "wof:placetype":"venue"
},
  "geometry": {"coordinates":[10.1283874512,54.3232460022],"type":"Point"}
}