{
  "type": "Feature",
  "properties": {
    "iso:country":"DE",
    "sg:address":"Mittertorstr. 9",
    "sg:city":"Mainburg",
    "sg:phone":"+49 8751/2026",
    "sg:postcode":"84048",
    "sg:province":"Bayern",
    "wof:name":"Eva Aschenbrenner",
    "wof:placetype":"venue"
},
  "geometry": {"coordinates":[11.785726,48.641609],"type":"Point"}
}