{
  "type": "Feature",
  "properties": {
    "iso:country":"DE",
    "sg:address":"Klosterstr. 50",
    "sg:city":"Br\u00fcggen",
    "sg:phone":"+49 2163/5285",
    "sg:postcode":"41379",
    "sg:province":"Nordrhein-Westfalen",
    "wof:name":"Burgcafe T\u00f6nnissen Gmbh",
    "wof:placetype":"venue"
},
  "geometry": {"coordinates":[6.182722,51.241005],"type":"Point"}
}