{
  "type": "Feature",
  "properties": {
    "iso:country":"DE",
    "sg:address":"M\u00fchlgasse 3",
    "sg:city":"Werbach",
    "sg:phone":"+49 9348/257",
    "sg:postcode":"97956",
    "sg:province":"Baden-W\u00fcrttemberg",
    "wof:name":"Elektro He\u00df",
    "wof:placetype":"venue"
},
  "geometry": {"coordinates":[9.6151723862,49.7034721375],"type":"Point"}
}