{
  "type": "Feature",
  "properties": {
    "iso:country":"DE",
    "sg:address":"Bahnhofplatz 2",
    "sg:city":"Bad Reichenhall",
    "sg:phone":"+49 8651/2556",
    "sg:postcode":"83435",
    "sg:province":"Bayern",
    "wof:name":"Anton Guggenberger",
    "wof:placetype":"venue"
},
  "geometry": {"coordinates":[12.8823671341,47.7313117981],"type":"Point"}
}