{
  "type": "Feature",
  "properties": {
    "iso:country":"DE",
    "sg:address":"Am Kirchenfeld 18",
    "sg:city":"Dortmund",
    "sg:phone":"+49 231/3798686",
    "sg:postcode":"44357",
    "sg:province":"Nordrhein-Westfalen",
    "wof:name":"Gastst\u00e4tte Alt Bodelschwingh",
    "wof:placetype":"venue"
},
  "geometry": {"coordinates":[7.3690929413,51.5502510071],"type":"Point"}
}