{
  "type": "Feature",
  "properties": {
    "iso:country":"DE",
    "sg:address":"Burgfriedenstr. 16 a",
    "sg:city":"Runkel",
    "sg:phone":"+49 6431/72655",
    "sg:postcode":"65594",
    "sg:province":"Hessen",
    "wof:name":"Pfalz-apotheke",
    "wof:placetype":"venue"
},
  "geometry": {"coordinates":[8.09446,50.414955],"type":"Point"}
}