{
  "type": "Feature",
  "properties": {
    "iso:country":"DE",
    "sg:address":"Teltower Damm 209",
    "sg:city":"Berlin",
    "sg:phone":"+49 30/8156006",
    "sg:postcode":"14167",
    "sg:province":"Berlin",
    "wof:name":"Gerhard Sch\u00fclmann",
    "wof:placetype":"venue"
},
  "geometry": {"coordinates":[13.2664833069,52.4148025513],"type":"Point"}
}