{
  "type": "Feature",
  "properties": {
    "iso:country":"DE",
    "sg:address":"Am Alten Wasserwerk 1 a",
    "sg:city":"Kevelaer",
    "sg:phone":"+49 2832/7173",
    "sg:postcode":"47623",
    "sg:province":"Nordrhein-Westfalen",
    "wof:name":"Ludger Ko\u00dfmann",
    "wof:placetype":"venue"
},
  "geometry": {"coordinates":[6.230544,51.583912],"type":"Point"}
}