{
  "type": "Feature",
  "properties": {
    "iso:country":"DE",
    "sg:address":"Eisfelder Str. 26",
    "sg:city":"Neuhaus",
    "sg:phone":"+49 3679/7740",
    "sg:postcode":"98724",
    "sg:province":"Th\u00fcringen",
    "wof:name":"A. C. Hotel Schieferhof",
    "wof:placetype":"venue"
},
  "geometry": {"coordinates":[11.1350793839,50.5085830688],"type":"Point"}
}