{
  "type": "Feature",
  "properties": {
    "iso:country":"DE",
    "sg:address":"J\u00e4gerholzweg 24",
    "sg:city":"Weil im Sch\u00f6nbuch",
    "sg:phone":"+49 7031/652565",
    "sg:postcode":"71093",
    "sg:province":"Baden-W\u00fcrttemberg",
    "wof:name":"Restaurant J\u00e4gerholz",
    "wof:placetype":"venue"
},
  "geometry": {"coordinates":[9.0505018234,48.6370506287],"type":"Point"}
}