{
  "type": "Feature",
  "properties": {
    "iso:country":"DE",
    "sg:address":"Robert-G\u00e4rtner-Str. 11",
    "sg:city":"Burgst\u00e4dt",
    "sg:phone":"+49 3724/2109",
    "sg:postcode":"09217",
    "sg:province":"Sachsen",
    "wof:name":"U. Schott",
    "wof:placetype":"venue"
},
  "geometry": {"coordinates":[12.808321,50.918999],"type":"Point"}
}