{
  "type": "Feature",
  "properties": {
    "iso:country":"DE",
    "sg:address":"Promenade 35",
    "sg:city":"Oschatz",
    "sg:phone":"+49 3435/623300",
    "sg:postcode":"04758",
    "sg:province":"Sachsen",
    "wof:name":"Michael Gorki Rechtsanwalt",
    "wof:placetype":"venue"
},
  "geometry": {"coordinates":[13.1081800461,51.3000297546],"type":"Point"}
}