{
  "type": "Feature",
  "properties": {
    "iso:country":"DE",
    "sg:address":"Steinbeisstr. 13",
    "sg:city":"B\u00f6blingen",
    "sg:phone":"+49 7031/211680",
    "sg:postcode":"71034",
    "sg:province":"Baden-W\u00fcrttemberg",
    "wof:name":"Sparkassen Versicherung Dieter Schmid",
    "wof:placetype":"venue"
},
  "geometry": {"coordinates":[9.0063199997,48.6816482544],"type":"Point"}
}