{
  "type": "Feature",
  "properties": {
    "iso:country":"DE",
    "sg:address":"Pickardstr. 17",
    "sg:city":"Saarwellingen",
    "sg:phone":"+49 6838/4536",
    "sg:postcode":"66793",
    "sg:province":"Saarland",
    "wof:name":"Joachim Klaus",
    "wof:placetype":"venue"
},
  "geometry": {"coordinates":[6.873086,49.361801],"type":"Point"}
}