{
  "type": "Feature",
  "properties": {
    "iso:country":"DE",
    "sg:address":"Industriestr. 57",
    "sg:city":"Lehrte",
    "sg:phone":"+49 5132/83390",
    "sg:postcode":"31275",
    "sg:province":"Niedersachsen",
    "wof:name":"Deutsche Doka Schalungstechnik Gmbh",
    "wof:placetype":"venue"
},
  "geometry": {"coordinates":[10.007951,52.379398],"type":"Point"}
}