{
  "type": "Feature",
  "properties": {
    "iso:country":"DE",
    "sg:address":"Lageschestr.232",
    "sg:city":"Detmold",
    "sg:postcode":"32758",
    "sg:province":"Nordrhein-Westfalen",
    "wof:name":"Biermann-web.de Und Im Bad Ist Alles Ok",
    "wof:placetype":"venue"
},
  "geometry": {"coordinates":[8.7822,51.946358],"type":"Point"}
}