{
  "type": "Feature",
  "properties": {
    "iso:country":"DE",
    "sg:address":"St.-Christophorus-Str. 3",
    "sg:city":"Erfurt",
    "sg:phone":"+49 361/74323",
    "sg:postcode":"99092",
    "sg:province":"Th\u00fcringen",
    "wof:name":"Dekra Automobil Gmbh",
    "wof:placetype":"venue"
},
  "geometry": {"coordinates":[11.0013380051,50.9907455444],"type":"Point"}
}