{
  "type": "Feature",
  "properties": {
    "iso:country":"DE",
    "sg:address":"Fliederweg 3",
    "sg:city":"Reit im Winkl",
    "sg:phone":"+49 8640/8842",
    "sg:postcode":"83242",
    "sg:province":"Bayern",
    "wof:name":"Real-immobilien Johann Johannides",
    "wof:placetype":"venue"
},
  "geometry": {"coordinates":[12.4831008911,47.6762084961],"type":"Point"}
}