{
  "type": "Feature",
  "properties": {
    "iso:country":"DE",
    "sg:address":"Schweinauer Hauptstr. 116",
    "sg:city":"N\u00fcrnberg",
    "sg:phone":"+49 911/661980",
    "sg:postcode":"90441",
    "sg:province":"Bayern",
    "wof:name":"Zigarren-eckert Heinrich Eckert",
    "wof:placetype":"venue"
},
  "geometry": {"coordinates":[11.04255867,49.427482605],"type":"Point"}
}