{
  "type": "Feature",
  "properties": {
    "iso:country":"DE",
    "sg:address":"Bischofswerdaer Str. 6",
    "sg:city":"Neustadt",
    "sg:phone":"+49 3596/604400",
    "sg:postcode":"01844",
    "sg:province":"Sachsen",
    "wof:name":"Erhard Beyer",
    "wof:placetype":"venue"
},
  "geometry": {"coordinates":[14.21622,51.026199],"type":"Point"}
}