{
  "type": "Feature",
  "properties": {
    "iso:country":"DE",
    "sg:address":"Gronauer Weg 21",
    "sg:city":"Karben",
    "sg:phone":"+49 6039/3447",
    "sg:postcode":"61184",
    "sg:province":"Hessen",
    "wof:name":"B\u00fcdas B\u00fcro- Und Daten- Verarbeitungsservice Gmbh",
    "wof:placetype":"venue"
},
  "geometry": {"coordinates":[8.789536,50.212437],"type":"Point"}
}