{
  "type": "Feature",
  "properties": {
    "iso:country":"DE",
    "sg:address":"Elsassergasse 10",
    "sg:city":"Dinkelsb\u00fchl",
    "sg:phone":"+49 9851/2261",
    "sg:postcode":"91550",
    "sg:province":"Bayern",
    "wof:name":"Josef Laugner",
    "wof:placetype":"venue"
},
  "geometry": {"coordinates":[10.3179559708,49.0703201294],"type":"Point"}
}