{
  "type": "Feature",
  "properties": {
    "iso:country":"DE",
    "sg:address":"Br\u00fchlgasse 23a",
    "sg:city":"Eigeltingen",
    "sg:postcode":"78253",
    "sg:province":"Baden-W\u00fcrttemberg",
    "wof:name":"Daniel Hermann Webdesign",
    "wof:placetype":"venue"
},
  "geometry": {"coordinates":[8.883951,47.894711],"type":"Point"}
}