{
  "type": "Feature",
  "properties": {
    "iso:country":"DE",
    "sg:address":"Industriestr. 1",
    "sg:city":"Schenefeld",
    "sg:phone":"+49 40/8305303",
    "sg:postcode":"22869",
    "sg:province":"Schleswig-Holstein",
    "wof:name":"Lilas",
    "wof:placetype":"venue"
},
  "geometry": {"coordinates":[9.838038,53.60096],"type":"Point"}
}