{
  "type": "Feature",
  "properties": {
    "iso:country":"DE",
    "sg:address":"Zur Kleinheck 4",
    "sg:city":"Birlenbach",
    "sg:phone":"+49 6432/81588",
    "sg:postcode":"65626",
    "sg:province":"Rheinland-Pfalz",
    "wof:name":"C. Roos Und H. Peters Immobilienmakler",
    "wof:placetype":"venue"
},
  "geometry": {"coordinates":[7.9999008179,50.3608207703],"type":"Point"}
}