{
  "type": "Feature",
  "properties": {
    "iso:country":"DE",
    "sg:address":"Hauptstr. 33",
    "sg:city":"Abtsgm\u00fcnd",
    "sg:phone":"+49 7366/6359",
    "sg:postcode":"73453",
    "sg:province":"Baden-W\u00fcrttemberg",
    "wof:name":"Apotheke Abtsgm\u00fcnd Apotheker Wolfgang",
    "wof:placetype":"venue"
},
  "geometry": {"coordinates":[10.005637,48.893658],"type":"Point"}
}