{
  "type": "Feature",
  "properties": {
    "iso:country":"DE",
    "sg:address":"Weil",
    "sg:city":"Weil",
    "sg:phone":"+49 7621/6721",
    "sg:postcode":"79576",
    "sg:province":"Baden-W\u00fcrttemberg",
    "wof:name":"Raiffeisenbank Markgr\u00e4flerland Eg",
    "wof:placetype":"venue"
},
  "geometry": {"coordinates":[7.60826,47.605469],"type":"Point"}
}