{
  "type": "Feature",
  "properties": {
    "iso:country":"DE",
    "sg:address":"Bergstr. 53",
    "sg:city":"Rheine",
    "sg:phone":"+49 5971/64306",
    "sg:postcode":"48429",
    "sg:province":"Nordrhein-Westfalen",
    "wof:name":"Horst Bietmann",
    "wof:placetype":"venue"
},
  "geometry": {"coordinates":[7.4533967972,52.2956199646],"type":"Point"}
}