{
  "type": "Feature",
  "properties": {
    "iso:country":"DE",
    "sg:address":"Schessingh\u00e4user Weg 10",
    "sg:city":"Nienburg",
    "sg:phone":"+49 5021/97410",
    "sg:postcode":"31582",
    "sg:province":"Niedersachsen",
    "wof:name":"G\u00f6pfert Bauunternehmen Gmbh",
    "wof:placetype":"venue"
},
  "geometry": {"coordinates":[9.2414951324,52.6160812378],"type":"Point"}
}