{
  "type": "Feature",
  "properties": {
    "iso:country":"DE",
    "sg:address":"An Der Autobahn 29-33",
    "sg:city":"Oyten",
    "sg:phone":"+49 4942/07660",
    "sg:postcode":"28876",
    "sg:province":"Niedersachsen",
    "wof:name":"Unimet Zentrallager Nord Gmbh & Co. Handels Kg",
    "wof:placetype":"venue"
},
  "geometry": {"coordinates":[9.045589447,53.0553703308],"type":"Point"}
}