{
  "type": "Feature",
  "properties": {
    "iso:country":"DE",
    "sg:address":"Stahlgruberring 41",
    "sg:city":"M\u00fcnchen",
    "sg:phone":"+49 89/429099",
    "sg:postcode":"81829",
    "sg:province":"Bayern",
    "wof:name":"Alois Fetzer Gmbh",
    "wof:placetype":"venue"
},
  "geometry": {"coordinates":[11.6701622009,48.1346549988],"type":"Point"}
}