{
  "type": "Feature",
  "properties": {
    "iso:country":"DE",
    "sg:address":"Eichbergstr. 6",
    "sg:city":"Rott",
    "sg:phone":"+49 8869/438",
    "sg:postcode":"86935",
    "sg:province":"Bayern",
    "wof:name":"Harry Kunz",
    "wof:placetype":"venue"
},
  "geometry": {"coordinates":[10.9694700241,47.9105796814],"type":"Point"}
}