{
  "type": "Feature",
  "properties": {
    "iso:country":"DE",
    "sg:address":"Elsiger Str. 28",
    "sg:city":"Euskirchen",
    "sg:phone":"+49 2251/4441",
    "sg:postcode":"53881",
    "sg:province":"Nordrhein-Westfalen",
    "wof:name":"Karl Gr\u00e4f",
    "wof:placetype":"venue"
},
  "geometry": {"coordinates":[6.741214,50.666969],"type":"Point"}
}