{
  "type": "Feature",
  "properties": {
    "iso:country":"DE",
    "sg:address":"Altengammer Hausdeich 80",
    "sg:city":"Hamburg",
    "sg:phone":"+49 40/7235432",
    "sg:postcode":"21039",
    "sg:province":"Hamburg",
    "wof:name":"Hartmut Odemann",
    "wof:placetype":"venue"
},
  "geometry": {"coordinates":[10.247829,53.43084],"type":"Point"}
}