{
  "type": "Feature",
  "properties": {
    "iso:country":"DE",
    "sg:address":"Gro\u00dflellenfeld 111",
    "sg:city":"Arberg",
    "sg:phone":"+49 9836/286",
    "sg:postcode":"91722",
    "sg:province":"Bayern",
    "wof:name":"F. Holzschuh",
    "wof:placetype":"venue"
},
  "geometry": {"coordinates":[10.6415510178,49.1142921448],"type":"Point"}
}