{
  "type": "Feature",
  "properties": {
    "iso:country":"DE",
    "sg:address":"Poststr. 15",
    "sg:city":"Beverstedt",
    "sg:phone":"+49 4747/444",
    "sg:postcode":"27616",
    "sg:province":"Niedersachsen",
    "wof:name":"H. Noe",
    "wof:placetype":"venue"
},
  "geometry": {"coordinates":[8.821399,53.435261],"type":"Point"}
}