{
  "type": "Feature",
  "properties": {
    "iso:country":"DE",
    "sg:city":"M\u00fcnster",
    "sg:postcode":"48167",
    "sg:province":"Nordrhein-Westfalen",
    "wof:name":"Tanzsportclub - Club Prinzipal M\u00fcnster E.v.",
    "wof:placetype":"venue"
},
  "geometry": {"coordinates":[7.726632,51.91584],"type":"Point"}
}