{
  "type": "Feature",
  "properties": {
    "iso:country":"DE",
    "sg:address":"Uhlandstr. 4",
    "sg:city":"Remshalden",
    "sg:phone":"+49 7151/72486",
    "sg:postcode":"73630",
    "sg:province":"Baden-W\u00fcrttemberg",
    "wof:name":"A. M\u00fcller",
    "wof:placetype":"venue"
},
  "geometry": {"coordinates":[9.418311,48.809902],"type":"Point"}
}