{
  "type": "Feature",
  "properties": {
    "iso:country":"DE",
    "sg:address":"Kellerweg 23",
    "sg:city":"M\u00f6gglingen",
    "sg:phone":"+49 7174/7414",
    "sg:postcode":"73563",
    "sg:province":"Baden-W\u00fcrttemberg",
    "wof:name":"Eas Patent-und Knowhow- Verwertungs-gmbh",
    "wof:placetype":"venue"
},
  "geometry": {"coordinates":[9.9529151917,48.8259773254],"type":"Point"}
}