{
  "type": "Feature",
  "properties": {
    "iso:country":"DE",
    "sg:address":"Am Wiesenberg 11",
    "sg:city":"R\u00fcthen",
    "sg:phone":"+49 2952/3953",
    "sg:postcode":"59602",
    "sg:province":"Nordrhein-Westfalen",
    "wof:name":"S. Und A. Fritzlar Gbr",
    "wof:placetype":"venue"
},
  "geometry": {"coordinates":[8.468054,51.524586],"type":"Point"}
}