{
  "type": "Feature",
  "properties": {
    "iso:country":"DE",
    "sg:address":"Bahnhofstr. 11",
    "sg:city":"Langenau",
    "sg:phone":"+49 7345/5259",
    "sg:postcode":"89129",
    "sg:province":"Baden-W\u00fcrttemberg",
    "wof:name":"Erika G\u00f6pel-saur Und Dieter Saur",
    "wof:placetype":"venue"
},
  "geometry": {"coordinates":[10.122384,48.498005],"type":"Point"}
}