{
  "type": "Feature",
  "properties": {
    "iso:country":"DE",
    "sg:address":"Birkenweg 34",
    "sg:city":"Bad Vilbel",
    "sg:postcode":"61118",
    "sg:province":"Hessen",
    "wof:name":"Sie-moden M. Cremer",
    "wof:placetype":"venue"
},
  "geometry": {"coordinates":[8.74527,50.17474],"type":"Point"}
}