{
  "type": "Feature",
  "properties": {
    "iso:country":"DE",
    "sg:address":"Kuckenberg 10",
    "sg:city":"Burscheid",
    "sg:phone":"+49 2174/64657",
    "sg:postcode":"51399",
    "sg:province":"Nordrhein-Westfalen",
    "wof:name":"Heidrun Brockmann-riegel Immobilienmakler",
    "wof:placetype":"venue"
},
  "geometry": {"coordinates":[7.0875201225,51.0858383179],"type":"Point"}
}