{
  "type": "Feature",
  "properties": {
    "iso:country":"DE",
    "sg:address":"Johann-Strau\u00df-Str. 22",
    "sg:city":"Filderstadt",
    "sg:phone":"+49 7158/64294",
    "sg:postcode":"70794",
    "sg:province":"Baden-W\u00fcrttemberg",
    "wof:name":"Geigenm\u00fcller & Buchweitz",
    "wof:placetype":"venue"
},
  "geometry": {"coordinates":[9.248245,48.649658],"type":"Point"}
}