{
  "type": "Feature",
  "properties": {
    "iso:country":"DE",
    "sg:address":"Beethovenstr. 3",
    "sg:city":"Schmelz",
    "sg:phone":"+49 6887/2516",
    "sg:postcode":"66839",
    "sg:province":"Saarland",
    "wof:name":"Frieda Jost Hebamme",
    "wof:placetype":"venue"
},
  "geometry": {"coordinates":[6.844248,49.447861],"type":"Point"}
}