{
  "type": "Feature",
  "properties": {
    "iso:country":"DE",
    "sg:address":"Triebstr. 1",
    "sg:city":"W\u00e4chtersbach",
    "sg:phone":"+49 6053/9193",
    "sg:postcode":"63607",
    "sg:province":"Hessen",
    "wof:name":"Maria Werth Eisenwaren",
    "wof:placetype":"venue"
},
  "geometry": {"coordinates":[9.30248,50.277679],"type":"Point"}
}