{
  "type": "Feature",
  "properties": {
    "iso:country":"DE",
    "sg:address":"St.-Elisabeth-Str. 3",
    "sg:city":"Koblenz",
    "sg:phone":"+49 261/460920",
    "sg:postcode":"56073",
    "sg:province":"Rheinland-Pfalz",
    "wof:name":"Centramed Medizintechnik Handelsges. Mbh & Co. Kg",
    "wof:placetype":"venue"
},
  "geometry": {"coordinates":[7.583061,50.359825],"type":"Point"}
}