{
  "type": "Feature",
  "properties": {
    "iso:country":"DE",
    "sg:address":"Huntloser Str. 311",
    "sg:city":"Wardenburg",
    "sg:phone":"+49 4407/5555",
    "sg:postcode":"26203",
    "sg:province":"Niedersachsen",
    "wof:name":"Fa. Farmservice Inh. Sietse Betten",
    "wof:placetype":"venue"
},
  "geometry": {"coordinates":[8.23105,53.029491],"type":"Point"}
}