{
  "type": "Feature",
  "properties": {
    "iso:country":"DE",
    "sg:address":"Kirchstr. 8",
    "sg:city":"Emsdetten",
    "sg:phone":"+49 2572/97686",
    "sg:postcode":"48282",
    "sg:province":"Nordrhein-Westfalen",
    "wof:name":"Herbert Uhde Immobilienmakler",
    "wof:placetype":"venue"
},
  "geometry": {"coordinates":[7.5285310745,52.1746749878],"type":"Point"}
}