{
  "type": "Feature",
  "properties": {
    "iso:country":"DE",
    "sg:address":"Riedmattenstr 3",
    "sg:city":"V\u00f6rstetten",
    "sg:phone":"+49 7666/3975",
    "sg:postcode":"79279",
    "sg:province":"Baden-W\u00fcrttemberg",
    "wof:name":"Gastro-ambiente-wendler",
    "wof:placetype":"venue"
},
  "geometry": {"coordinates":[7.848747,48.060951],"type":"Point"}
}