{
  "type": "Feature",
  "properties": {
    "iso:country":"DE",
    "sg:address":"Industriestr. 10",
    "sg:city":"Herrieden",
    "sg:phone":"+49 9825/9400",
    "sg:postcode":"91567",
    "sg:province":"Bayern",
    "wof:name":"Gebr. Jechnerer Gmbh Franken-fenster",
    "wof:placetype":"venue"
},
  "geometry": {"coordinates":[10.507344,49.234554],"type":"Point"}
}