{
  "type": "Feature",
  "properties": {
    "iso:country":"DE",
    "sg:address":"Schillingstr. 15",
    "sg:city":"Worms",
    "sg:phone":"+49 6241/75379",
    "sg:postcode":"67549",
    "sg:province":"Rheinland-Pfalz",
    "wof:name":"Walter W\u00fcrfel Architekt",
    "wof:placetype":"venue"
},
  "geometry": {"coordinates":[8.331634,49.636623],"type":"Point"}
}