{
  "type": "Feature",
  "properties": {
    "iso:country":"DE",
    "sg:address":"Zum Freibad 80",
    "sg:city":"Luckenwalde",
    "sg:phone":"+49 3371/611922",
    "sg:postcode":"14943",
    "sg:province":"Brandenburg",
    "wof:name":"Horst Marquardt",
    "wof:placetype":"venue"
},
  "geometry": {"coordinates":[13.172544,52.078796],"type":"Point"}
}