{
  "type": "Feature",
  "properties": {
    "iso:country":"DE",
    "sg:address":"Leo-Graetz-Str. 3",
    "sg:city":"M\u00fcnchen",
    "sg:phone":"+49 89/78749055",
    "sg:postcode":"81379",
    "sg:province":"Bayern",
    "wof:name":"S. E. P. Gesellschaft F\u00fcr Technische Beratung",
    "wof:placetype":"venue"
},
  "geometry": {"coordinates":[11.5194454193,48.1008834839],"type":"Point"}
}