{
  "type": "Feature",
  "properties": {
    "iso:country":"DE",
    "sg:address":"Schwalkenberg",
    "sg:city":"R\u00f6mnitz",
    "sg:phone":"+49 4541/7566",
    "sg:postcode":"23909",
    "sg:province":"Schleswig-Holstein",
    "wof:name":"Campingplatz Schwalkenberg",
    "wof:placetype":"venue"
},
  "geometry": {"coordinates":[10.768997,53.699306],"type":"Point"}
}