{
  "type": "Feature",
  "properties": {
    "iso:country":"DE",
    "sg:address":"Luhrgasse 5",
    "sg:city":"Winden",
    "sg:phone":"+49 7682/1526",
    "sg:postcode":"79297",
    "sg:province":"Baden-W\u00fcrttemberg",
    "wof:name":"Josef Emler",
    "wof:placetype":"venue"
},
  "geometry": {"coordinates":[8.0403203964,48.1537475586],"type":"Point"}
}