{
  "type": "Feature",
  "properties": {
    "iso:country":"DE",
    "sg:address":"Walchstr. 15",
    "sg:city":"Naila",
    "sg:postcode":"95119",
    "sg:province":"Bayern",
    "wof:name":"Direkt",
    "wof:placetype":"venue"
},
  "geometry": {"coordinates":[11.7089300156,50.3305969238],"type":"Point"}
}