{
  "type": "Feature",
  "properties": {
    "iso:country":"DE",
    "sg:address":"Weserstr. 11",
    "sg:city":"Raunheim",
    "sg:postcode":"65479",
    "sg:province":"Hessen",
    "wof:name":"Baudekoration Tvb Gmbh",
    "wof:placetype":"venue"
},
  "geometry": {"coordinates":[8.442374,50.006012],"type":"Point"}
}