{
  "type": "Feature",
  "properties": {
    "iso:country":"DE",
    "sg:address":"Oststr. 11",
    "sg:city":"Remscheid",
    "sg:phone":"+49 2191/31678",
    "sg:postcode":"42859",
    "sg:province":"Nordrhein-Westfalen",
    "wof:name":"E. Schmitz Heissmangel",
    "wof:placetype":"venue"
},
  "geometry": {"coordinates":[7.2213439941,51.1751365662],"type":"Point"}
}