{
  "type": "Feature",
  "properties": {
    "iso:country":"DE",
    "sg:address":"Peslm\u00fcllerstr. 13",
    "sg:city":"M\u00fcnchen",
    "sg:phone":"+49 89/88919208",
    "sg:postcode":"81243",
    "sg:province":"Bayern",
    "wof:name":"Netcomm Gmbh",
    "wof:placetype":"venue"
},
  "geometry": {"coordinates":[11.445455,48.141365],"type":"Point"}
}