{
  "type": "Feature",
  "properties": {
    "iso:country":"DE",
    "sg:address":"Oedter Str. 51",
    "sg:city":"Kempen",
    "sg:phone":"+49 2152/3681",
    "sg:postcode":"47906",
    "sg:province":"Nordrhein-Westfalen",
    "wof:name":"Esso Station",
    "wof:placetype":"venue"
},
  "geometry": {"coordinates":[6.4135251045,51.3557815552],"type":"Point"}
}