{
  "type": "Feature",
  "properties": {
    "iso:country":"DE",
    "sg:address":"In der Rose 4",
    "sg:city":"Reichshof",
    "sg:postcode":"51580",
    "sg:province":"Nordrhein-Westfalen",
    "wof:name":"Gerd Taufenbach",
    "wof:placetype":"venue"
},
  "geometry": {"coordinates":[7.761711,50.968498],"type":"Point"}
}