{
  "type": "Feature",
  "properties": {
    "iso:country":"DE",
    "sg:address":"Biegenhofstr. 18",
    "sg:city":"Hallstadt",
    "sg:phone":"+49 951/601703",
    "sg:postcode":"96103",
    "sg:province":"Bayern",
    "wof:name":"K. Stumpf",
    "wof:placetype":"venue"
},
  "geometry": {"coordinates":[10.870724678,49.9181785583],"type":"Point"}
}