{
  "type": "Feature",
  "properties": {
    "iso:country":"DE",
    "sg:address":"Auchtertstr. 12",
    "sg:city":"Grafenberg",
    "sg:phone":"+49 7123/35300",
    "sg:postcode":"72661",
    "sg:province":"Baden-W\u00fcrttemberg",
    "wof:name":"Reiterst\u00fcble",
    "wof:placetype":"venue"
},
  "geometry": {"coordinates":[9.3092803955,48.5689659119],"type":"Point"}
}