{
  "type": "Feature",
  "properties": {
    "iso:country":"DE",
    "sg:address":"Hauptstr. 47",
    "sg:city":"Bottrop",
    "sg:postcode":"46244",
    "sg:province":"Nordrhein-Westfalen",
    "wof:name":"La Botte",
    "wof:placetype":"venue"
},
  "geometry": {"coordinates":[6.922358036,51.6039466858],"type":"Point"}
}