{
  "type": "Feature",
  "properties": {
    "iso:country":"DE",
    "sg:address":"Anspacher Str. 56",
    "sg:city":"Bad Homburg",
    "sg:phone":"+49 6172/32386",
    "sg:postcode":"61350",
    "sg:province":"Hessen",
    "wof:name":"Reinhard Reiffen Architekt",
    "wof:placetype":"venue"
},
  "geometry": {"coordinates":[8.59249,50.241177],"type":"Point"}
}