{
  "type": "Feature",
  "properties": {
    "iso:country":"DE",
    "sg:address":"Deutsche Str. 13",
    "sg:city":"Saarlouis",
    "sg:phone":"+49 4968/311395",
    "sg:postcode":"66740",
    "sg:province":"Saarland",
    "wof:name":"Commerz-credit-bank Ag",
    "wof:placetype":"venue"
},
  "geometry": {"coordinates":[6.749238,49.316307],"type":"Point"}
}