{
  "type": "Feature",
  "properties": {
    "iso:country":"DE",
    "sg:address":"Weitlingstr. 48",
    "sg:city":"Berlin",
    "sg:phone":"+49 30/5252014",
    "sg:postcode":"10317",
    "sg:province":"Berlin",
    "wof:name":"G\u00f6dicke U. A. Gbr",
    "wof:placetype":"venue"
},
  "geometry": {"coordinates":[13.4961919785,52.5069351196],"type":"Point"}
}