{
  "type": "Feature",
  "properties": {
    "iso:country":"DE",
    "sg:address":"Eichendorffplatz 10a",
    "sg:city":"M\u00fcnchen",
    "sg:postcode":"81369",
    "sg:province":"Bayern",
    "wof:name":"Ima-gmbh Verwertung Nat. Und Int. Urheberrechte",
    "wof:placetype":"venue"
},
  "geometry": {"coordinates":[11.524541,48.113499],"type":"Point"}
}