{
  "type": "Feature",
  "properties": {
    "iso:country":"DE",
    "sg:address":"Br\u00fchl 9",
    "sg:city":"Leipzig",
    "sg:phone":"+49 341/2122183",
    "sg:postcode":"04109",
    "sg:province":"Sachsen",
    "wof:name":"Gesellschaft F\u00fcr Intern. Handel Deutschland Mbh",
    "wof:placetype":"venue"
},
  "geometry": {"coordinates":[12.3757610321,51.343170166],"type":"Point"}
}