{
  "type": "Feature",
  "properties": {
    "iso:country":"DE",
    "sg:address":"Neue Str. 3",
    "sg:city":"Bleicherode",
    "sg:phone":"+49 36338/42565",
    "sg:postcode":"99752",
    "sg:province":"Th\u00fcringen",
    "wof:name":"L\u00f6blein Nordth\u00fcringer Fleischwaren Gmbh",
    "wof:placetype":"venue"
},
  "geometry": {"coordinates":[10.5696163177,51.4379959106],"type":"Point"}
}