{
  "type": "Feature",
  "properties": {
    "iso:country":"DE",
    "sg:address":"Schwarzwaldstr. 37",
    "sg:city":"L\u00f6rrach",
    "sg:phone":"+49 7621/2833",
    "sg:postcode":"79539",
    "sg:province":"Baden-W\u00fcrttemberg",
    "wof:name":"Hermann Weiss Elektromeister",
    "wof:placetype":"venue"
},
  "geometry": {"coordinates":[7.667472,47.619171],"type":"Point"}
}