{
  "type": "Feature",
  "properties": {
    "iso:country":"DE",
    "sg:address":"Steinbitz 7",
    "sg:city":"Westerburg",
    "sg:phone":"+49 2663/8451",
    "sg:postcode":"56457",
    "sg:province":"Rheinland-Pfalz",
    "wof:name":"Anita Roller",
    "wof:placetype":"venue"
},
  "geometry": {"coordinates":[7.9723229408,50.5541801453],"type":"Point"}
}