{
  "type": "Feature",
  "properties": {
    "iso:country":"DE",
    "sg:address":"K\u00fcferweg 7",
    "sg:city":"Mainz",
    "sg:phone":"+49 6131/72610",
    "sg:postcode":"55128",
    "sg:province":"Rheinland-Pfalz",
    "wof:name":"Fitform Herstellung Und Vertrieb Helga Karell",
    "wof:placetype":"venue"
},
  "geometry": {"coordinates":[8.2394104004,49.970867157],"type":"Point"}
}