{
  "type": "Feature",
  "properties": {
    "iso:country":"DE",
    "sg:address":"Ringstr. 24",
    "sg:city":"Oberschlei\u00dfheim",
    "sg:phone":"+49 89/3175087",
    "sg:postcode":"85764",
    "sg:province":"Bayern",
    "wof:name":"Herta Hahn Regalsysteme",
    "wof:placetype":"venue"
},
  "geometry": {"coordinates":[11.545083,48.251972],"type":"Point"}
}