{
  "type": "Feature",
  "properties": {
    "iso:country":"DE",
    "sg:address":"Grunaer Weg 3",
    "sg:city":"Dresden",
    "sg:phone":"+49 351/2561227",
    "sg:postcode":"01277",
    "sg:province":"Sachsen",
    "wof:name":"Horst Lange",
    "wof:placetype":"venue"
},
  "geometry": {"coordinates":[13.777621,51.028542],"type":"Point"}
}