{
  "type": "Feature",
  "properties": {
    "iso:country":"DE",
    "sg:address":"Pionierstr. 79",
    "sg:city":"Berlin",
    "sg:phone":"+49 30/3722442",
    "sg:postcode":"13589",
    "sg:province":"Berlin",
    "wof:name":"Richard Glase & Co. Gmbh",
    "wof:placetype":"venue"
},
  "geometry": {"coordinates":[13.1810312271,52.5526428223],"type":"Point"}
}