{
  "type": "Feature",
  "properties": {
    "iso:country":"DE",
    "sg:address":"Ludwig-Erhard-Str. 7",
    "sg:city":"Gieboldehausen",
    "sg:postcode":"37434",
    "sg:province":"Niedersachsen",
    "wof:name":"I. Dsz Dentales Service Zentrum Verwaltungs Gmbh",
    "wof:placetype":"venue"
},
  "geometry": {"coordinates":[10.2040519714,51.6034622192],"type":"Point"}
}