{
  "type": "Feature",
  "properties": {
    "iso:country":"DE",
    "sg:address":"Bergstr. 16",
    "sg:city":"Weferlingen",
    "sg:phone":"+49 39061/2385",
    "sg:postcode":"39356",
    "sg:province":"Sachsen-Anhalt",
    "wof:name":"Zur Sonne Inh. Anke H\u00f6ltge",
    "wof:placetype":"venue"
},
  "geometry": {"coordinates":[11.0582990646,52.3162612915],"type":"Point"}
}