{
  "type": "Feature",
  "properties": {
    "iso:country":"DE",
    "sg:address":"Feldblumenweg 3",
    "sg:city":"Dortmund",
    "sg:postcode":"44267",
    "sg:province":"Nordrhein-Westfalen",
    "wof:name":"Arith Med Gmbh",
    "wof:placetype":"venue"
},
  "geometry": {"coordinates":[7.528079,51.442905],"type":"Point"}
}