{
  "type": "Feature",
  "properties": {
    "iso:country":"DE",
    "sg:address":"Ringstr. 4",
    "sg:city":"Wusterhausen",
    "sg:phone":"+49 33979/15851",
    "sg:postcode":"16868",
    "sg:province":"Brandenburg",
    "wof:name":"Abg Asphaltbau Gmbh",
    "wof:placetype":"venue"
},
  "geometry": {"coordinates":[12.5322618484,52.8327140808],"type":"Point"}
}