{
  "type": "Feature",
  "properties": {
    "iso:country":"DE",
    "sg:address":"Erkelenzer Str. 23",
    "sg:city":"Titz",
    "sg:phone":"+49 2463/8613",
    "sg:postcode":"52445",
    "sg:province":"Nordrhein-Westfalen",
    "wof:name":"W. Eschenbr\u00fccher",
    "wof:placetype":"venue"
},
  "geometry": {"coordinates":[6.387956,51.008133],"type":"Point"}
}