{
  "type": "Feature",
  "properties": {
    "iso:country":"DE",
    "sg:address":"Ubierring 50",
    "sg:city":"K\u00f6ln",
    "sg:postcode":"50678",
    "sg:province":"Nordrhein-Westfalen",
    "wof:name":"Iib Internationale Infra- Struktur- Und Investitions-",
    "wof:placetype":"venue"
},
  "geometry": {"coordinates":[6.9649810791,50.9216346741],"type":"Point"}
}