{
  "type": "Feature",
  "properties": {
    "iso:country":"DE",
    "sg:address":"Margaretenstr. 10",
    "sg:city":"Wuppertal",
    "sg:phone":"+49 202/88889",
    "sg:postcode":"42285",
    "sg:province":"Nordrhein-Westfalen",
    "wof:name":"Gfi Gesellschaft F\u00fcr Industriebedarf Mbh",
    "wof:placetype":"venue"
},
  "geometry": {"coordinates":[7.177478,51.257668],"type":"Point"}
}