{
  "type": "Feature",
  "properties": {
    "iso:country":"DE",
    "sg:address":"Zuschka 31",
    "sg:city":"Cottbus",
    "sg:phone":"+49 355/870276",
    "sg:postcode":"03044",
    "sg:province":"Brandenburg",
    "wof:name":"Martin Wobser",
    "wof:placetype":"venue"
},
  "geometry": {"coordinates":[14.3424263,51.7853965759],"type":"Point"}
}