{
  "type": "Feature",
  "properties": {
    "iso:country":"DE",
    "sg:address":"Hauptstr. 95",
    "sg:city":"Remchingen",
    "sg:phone":"+49 7232/372283",
    "sg:postcode":"75196",
    "sg:province":"Baden-W\u00fcrttemberg",
    "wof:name":"Roland Stucky & K.-h. Rosswag",
    "wof:placetype":"venue"
},
  "geometry": {"coordinates":[8.571266,48.951462],"type":"Point"}
}