{
  "type": "Feature",
  "properties": {
    "iso:country":"DE",
    "sg:address":"Bad Sodener Str. 40",
    "sg:city":"Bad Soden-Salm\u00fcnster",
    "sg:phone":"+49 6056/8081",
    "sg:postcode":"63628",
    "sg:province":"Hessen",
    "wof:name":"Haus Der Handarbeit Paul Von Liebieg",
    "wof:placetype":"venue"
},
  "geometry": {"coordinates":[9.370509,50.28236],"type":"Point"}
}