{
  "type": "Feature",
  "properties": {
    "iso:country":"DE",
    "sg:address":"Dresdner Str. 43",
    "sg:city":"Radebeul",
    "sg:phone":"+49 351/8303016",
    "sg:postcode":"01445",
    "sg:province":"Sachsen",
    "wof:name":"R. Leckelt",
    "wof:placetype":"venue"
},
  "geometry": {"coordinates":[13.6818027496,51.0941925049],"type":"Point"}
}