{
  "type": "Feature",
  "properties": {
    "iso:country":"DE",
    "sg:address":"Heinestr. 30",
    "sg:city":"R\u00f6tha",
    "sg:phone":"+49 34206/54775",
    "sg:postcode":"04571",
    "sg:province":"Sachsen",
    "wof:name":"Udo Meinelt",
    "wof:placetype":"venue"
},
  "geometry": {"coordinates":[12.410868,51.202309],"type":"Point"}
}