{
  "type": "Feature",
  "properties": {
    "iso:country":"DE",
    "sg:city":"Malsch",
    "sg:phone":"+49 4972/5321710",
    "sg:postcode":"76316",
    "sg:province":"Baden-W\u00fcrttemberg",
    "wof:name":"Bezirkssparkasse Wiesloch",
    "wof:placetype":"venue"
},
  "geometry": {"coordinates":[8.334501,48.880474],"type":"Point"}
}