{
  "type": "Feature",
  "properties": {
    "iso:country":"DE",
    "sg:address":"Rietheimer Str. 18",
    "sg:city":"Villingen-Schwenningen",
    "sg:phone":"+49 7721/21482",
    "sg:postcode":"78050",
    "sg:province":"Baden-W\u00fcrttemberg",
    "wof:name":"Gretel G\u00f6tz",
    "wof:placetype":"venue"
},
  "geometry": {"coordinates":[8.460436821,48.0487442017],"type":"Point"}
}