{
  "type": "Feature",
  "properties": {
    "iso:country":"DE",
    "sg:address":"Rennweg 27 a",
    "sg:city":"Dortmund",
    "sg:phone":"+49 231/253969",
    "sg:postcode":"44143",
    "sg:province":"Nordrhein-Westfalen",
    "wof:name":"G. Werner",
    "wof:placetype":"venue"
},
  "geometry": {"coordinates":[7.52377,51.511082],"type":"Point"}
}