{
  "type": "Feature",
  "properties": {
    "iso:country":"DE",
    "sg:address":"Waitzstr. 26",
    "sg:city":"Berlin",
    "sg:phone":"+49 30/3246196",
    "sg:postcode":"10629",
    "sg:province":"Berlin",
    "wof:name":"Michel Feith Architekt",
    "wof:placetype":"venue"
},
  "geometry": {"coordinates":[13.30593,52.503117],"type":"Point"}
}