{
  "type": "Feature",
  "properties": {
    "iso:country":"DE",
    "sg:address":"Tiergartenstr. 34",
    "sg:city":"Waltershausen",
    "sg:phone":"+49 3622/902113",
    "sg:postcode":"99880",
    "sg:province":"Th\u00fcringen",
    "wof:name":"Manfred Meier",
    "wof:placetype":"venue"
},
  "geometry": {"coordinates":[10.554422,50.903027],"type":"Point"}
}