{
  "type": "Feature",
  "properties": {
    "iso:country":"DE",
    "sg:address":"H\u00f6henweg 42",
    "sg:city":"M\u00fcnsing",
    "sg:phone":"+49 8177/8622",
    "sg:postcode":"82541",
    "sg:province":"Bayern",
    "wof:name":"Karl Diem Architekt",
    "wof:placetype":"venue"
},
  "geometry": {"coordinates":[11.345366,47.907581],"type":"Point"}
}