{
  "type": "Feature",
  "properties": {
    "iso:country":"DE",
    "sg:address":"Emil-Thomas-Str. 1",
    "sg:city":"Kirchberg",
    "sg:phone":"+49 6763/960700",
    "sg:postcode":"55481",
    "sg:province":"Rheinland-Pfalz",
    "wof:name":"Neukauf",
    "wof:placetype":"venue"
},
  "geometry": {"coordinates":[7.3840098381,49.9248313904],"type":"Point"}
}