{
  "type": "Feature",
  "properties": {
    "iso:country":"DE",
    "sg:address":"Darmst\u00e4dter Str. 4",
    "sg:city":"Pfungstadt",
    "sg:phone":"+49 6157/2244",
    "sg:postcode":"64319",
    "sg:province":"Hessen",
    "wof:name":"Albert Kistinger",
    "wof:placetype":"venue"
},
  "geometry": {"coordinates":[8.564116,49.807888],"type":"Point"}
}