{
  "type": "Feature",
  "properties": {
    "iso:country":"DE",
    "sg:address":"Leipziger Str. 19a",
    "sg:city":"Rackwitz",
    "sg:postcode":"04519",
    "sg:province":"Sachsen",
    "wof:name":"Msd May Sicherheits- Dienstleistungen Gmbh",
    "wof:placetype":"venue"
},
  "geometry": {"coordinates":[12.3744907379,51.4350318909],"type":"Point"}
}