{
  "type": "Feature",
  "properties": {
    "iso:country":"DE",
    "sg:address":"Mannheimer Str. 103",
    "sg:city":"Graben-Neudorf",
    "sg:phone":"+49 7255/6634",
    "sg:postcode":"76676",
    "sg:province":"Baden-W\u00fcrttemberg",
    "wof:name":"Hosenladen",
    "wof:placetype":"venue"
},
  "geometry": {"coordinates":[8.497364,49.176311],"type":"Point"}
}