{
  "type": "Feature",
  "properties": {
    "iso:country":"DE",
    "sg:address":"Leipziger Str. 158",
    "sg:city":"Kassel",
    "sg:phone":"+49 561/50931",
    "sg:postcode":"34123",
    "sg:province":"Hessen",
    "wof:name":"H. M\u00f6ller",
    "wof:placetype":"venue"
},
  "geometry": {"coordinates":[9.530587,51.303741],"type":"Point"}
}