{
  "type": "Feature",
  "properties": {
    "iso:country":"DE",
    "sg:address":"Hauptstr. 12",
    "sg:city":"Gefrees",
    "sg:phone":"+49 9254/9700",
    "sg:postcode":"95482",
    "sg:province":"Bayern",
    "wof:name":"Herold & Co Gmbh",
    "wof:placetype":"venue"
},
  "geometry": {"coordinates":[11.73515,50.095184],"type":"Point"}
}