{
  "type": "Feature",
  "properties": {
    "iso:country":"DE",
    "sg:address":"Schnepfenhain 8",
    "sg:city":"M\u00fccke",
    "sg:phone":"+49 6400/1361",
    "sg:postcode":"35325",
    "sg:province":"Hessen",
    "wof:name":"Reiner Irzinger",
    "wof:placetype":"venue"
},
  "geometry": {"coordinates":[9.1157922745,50.6134414673],"type":"Point"}
}