{
  "type": "Feature",
  "properties": {
    "iso:country":"DE",
    "sg:address":"Martin-Luther-Str. 23",
    "sg:city":"Gem\u00fcnden",
    "sg:phone":"+49 6453/7469",
    "sg:postcode":"35285",
    "sg:province":"Hessen",
    "wof:name":"U. Eckel",
    "wof:placetype":"venue"
},
  "geometry": {"coordinates":[8.9607172012,50.9707489014],"type":"Point"}
}