{
  "type": "Feature",
  "properties": {
    "iso:country":"DE",
    "sg:address":"Zenettistr. 49",
    "sg:city":"M\u00fcnchen",
    "sg:phone":"+49 89/772487",
    "sg:postcode":"80337",
    "sg:province":"Bayern",
    "wof:name":"C. Dobler",
    "wof:placetype":"venue"
},
  "geometry": {"coordinates":[11.552822,48.12645],"type":"Point"}
}