{
  "type": "Feature",
  "properties": {
    "iso:country":"DE",
    "sg:address":"Poppenreuther Str. 19",
    "sg:city":"F\u00fcrth",
    "sg:phone":"+49 911/7903728",
    "sg:postcode":"90765",
    "sg:province":"Bayern",
    "wof:name":"Aral Ag",
    "wof:placetype":"venue"
},
  "geometry": {"coordinates":[11.0006313324,49.4810256958],"type":"Point"}
}