{
  "type": "Feature",
  "properties": {
    "iso:country":"DE",
    "sg:address":"Altmarkt 14",
    "sg:city":"Zeitz",
    "sg:phone":"+49 3441/251537",
    "sg:postcode":"06712",
    "sg:province":"Sachsen-Anhalt",
    "wof:name":"Sankopie",
    "wof:placetype":"venue"
},
  "geometry": {"coordinates":[12.136156,51.049641],"type":"Point"}
}