{
  "type": "Feature",
  "properties": {
    "iso:country":"DE",
    "sg:address":"Erdbrucher Str. 19",
    "sg:city":"Blomberg",
    "sg:phone":"+49 5236/1741",
    "sg:postcode":"32825",
    "sg:province":"Nordrhein-Westfalen",
    "wof:name":"K\u00fchn-k\u00fcchen",
    "wof:placetype":"venue"
},
  "geometry": {"coordinates":[9.0118045807,51.9696578979],"type":"Point"}
}