{
  "type": "Feature",
  "properties": {
    "iso:country":"DE",
    "sg:address":"Nieder-Ramst\u00e4dter Str. 57B",
    "sg:city":"Darmstadt",
    "sg:phone":"+49 6151/43245",
    "sg:postcode":"64287",
    "sg:province":"Hessen",
    "wof:name":"M. Feichtinger",
    "wof:placetype":"venue"
},
  "geometry": {"coordinates":[8.662248,49.869026],"type":"Point"}
}