{
  "type": "Feature",
  "properties": {
    "iso:country":"DE",
    "sg:address":"Waldweg 51",
    "sg:city":"Schermbeck",
    "sg:phone":"+49 2853/650",
    "sg:postcode":"46514",
    "sg:province":"Nordrhein-Westfalen",
    "wof:name":"Jowi Holz-innenausbau Gmbh",
    "wof:placetype":"venue"
},
  "geometry": {"coordinates":[6.8430762291,51.7011451721],"type":"Point"}
}