{
  "type": "Feature",
  "properties": {
    "iso:country":"DE",
    "sg:address":"Rebenstr. 9 a",
    "sg:city":"Mannheim",
    "sg:phone":"+49 621/735490",
    "sg:postcode":"68309",
    "sg:province":"Baden-W\u00fcrttemberg",
    "wof:name":"Railimpex Johannes Scheurich Gmbh",
    "wof:placetype":"venue"
},
  "geometry": {"coordinates":[8.517455,49.509628],"type":"Point"}
}