{
  "type": "Feature",
  "properties": {
    "iso:country":"DE",
    "sg:address":"Wamslerstr 5",
    "sg:city":"M\u00fcnchen",
    "sg:phone":"+49 89/4515900",
    "sg:postcode":"81829",
    "sg:province":"Bayern",
    "wof:name":"Industrie Technik Ips Gmbh",
    "wof:placetype":"venue"
},
  "geometry": {"coordinates":[11.66102314,48.1360664368],"type":"Point"}
}