{
  "type": "Feature",
  "properties": {
    "iso:country":"DE",
    "sg:address":"An der Hochschule 7",
    "sg:city":"Germersheim",
    "sg:phone":"+49 7274/2637",
    "sg:postcode":"76726",
    "sg:province":"Rheinland-Pfalz",
    "wof:name":"Hermann Lippler",
    "wof:placetype":"venue"
},
  "geometry": {"coordinates":[8.372139,49.215988],"type":"Point"}
}