{
  "type": "Feature",
  "properties": {
    "iso:country":"DE",
    "sg:address":"Bogenweg 4",
    "sg:city":"Neunkirchen",
    "sg:phone":"+49 9378/99535",
    "sg:postcode":"63930",
    "sg:province":"Bayern",
    "wof:name":"Essert Gmbh",
    "wof:placetype":"venue"
},
  "geometry": {"coordinates":[9.3762788773,49.6884727478],"type":"Point"}
}