{
  "type": "Feature",
  "properties": {
    "iso:country":"DE",
    "sg:address":"Kolpingstr. 39",
    "sg:city":"Menden",
    "sg:phone":"+49 2373/5243",
    "sg:postcode":"58706",
    "sg:province":"Nordrhein-Westfalen",
    "wof:name":"Peter Krabus",
    "wof:placetype":"venue"
},
  "geometry": {"coordinates":[7.7991957664,51.4345970154],"type":"Point"}
}