{
  "type": "Feature",
  "properties": {
    "iso:country":"DE",
    "sg:address":"Lehnerstr. 14",
    "sg:city":"M\u00fclheim",
    "sg:phone":"+49 208/481737",
    "sg:postcode":"45481",
    "sg:province":"Nordrhein-Westfalen",
    "wof:name":"Brandin",
    "wof:placetype":"venue"
},
  "geometry": {"coordinates":[6.872186,51.405231],"type":"Point"}
}