{
  "type": "Feature",
  "properties": {
    "iso:country":"DE",
    "sg:address":"Industriestr. 4",
    "sg:city":"Auenwald",
    "sg:phone":"+49 7191/367550",
    "sg:postcode":"71549",
    "sg:province":"Baden-W\u00fcrttemberg",
    "wof:name":"Dkt-dachabdichtungs Gmbh",
    "wof:placetype":"venue"
},
  "geometry": {"coordinates":[9.4987201691,48.9454498291],"type":"Point"}
}