{
  "type": "Feature",
  "properties": {
    "iso:country":"DE",
    "sg:address":"Uferstr. 55",
    "sg:city":"Mainz",
    "sg:phone":"+49 6131/236262",
    "sg:postcode":"55116",
    "sg:province":"Rheinland-Pfalz",
    "wof:name":"A & O Kommunikations Gmbh",
    "wof:placetype":"venue"
},
  "geometry": {"coordinates":[8.2780723572,50.0002555847],"type":"Point"}
}