{
  "type": "Feature",
  "properties": {
    "iso:country":"DE",
    "sg:address":"Alicenplatz 6",
    "sg:city":"Mainz",
    "sg:phone":"+49 6131/224420",
    "sg:postcode":"55116",
    "sg:province":"Rheinland-Pfalz",
    "wof:name":"Raum",
    "wof:placetype":"venue"
},
  "geometry": {"coordinates":[8.260233,50.000916],"type":"Point"}
}