{
  "type": "Feature",
  "properties": {
    "iso:country":"DE",
    "sg:address":"Stra\u00dfe der Jugend 21",
    "sg:city":"R\u00fcdersdorf",
    "sg:phone":"+49 33638/2380",
    "sg:postcode":"15562",
    "sg:province":"Brandenburg",
    "wof:name":"J\u00fcrgen Sch\u00e4fer",
    "wof:placetype":"venue"
},
  "geometry": {"coordinates":[13.779436,52.471813],"type":"Point"}
}