{
  "type": "Feature",
  "properties": {
    "iso:country":"DE",
    "sg:address":"Tempelhofer Weg 98-100",
    "sg:city":"Berlin",
    "sg:phone":"+49 30/6061061",
    "sg:postcode":"12347",
    "sg:province":"Berlin",
    "wof:name":"Adf Automatische Dreherei Und Fassonteile Knie\u00df",
    "wof:placetype":"venue"
},
  "geometry": {"coordinates":[13.434148,52.451176],"type":"Point"}
}