{
  "type": "Feature",
  "properties": {
    "iso:country":"DE",
    "sg:address":"Industriering 10 a",
    "sg:city":"Lohne",
    "sg:phone":"+49 4442/937616",
    "sg:postcode":"49393",
    "sg:province":"Niedersachsen",
    "wof:name":"Kvt Beteiligungs- Und Verwaltungs Gmbh",
    "wof:placetype":"venue"
},
  "geometry": {"coordinates":[8.195716,52.659065],"type":"Point"}
}