{
  "type": "Feature",
  "properties": {
    "iso:country":"DE",
    "sg:address":"N\u00fcrnberger Str. 2",
    "sg:city":"F\u00fcrth",
    "sg:postcode":"90762",
    "sg:province":"Bayern",
    "wof:name":"Alpha One Sports Gmbh",
    "wof:placetype":"venue"
},
  "geometry": {"coordinates":[10.9933776855,49.4722862244],"type":"Point"}
}