{
  "type": "Feature",
  "properties": {
    "iso:country":"DE",
    "sg:address":"August-Bebel-Str. 5",
    "sg:city":"Osterburg",
    "sg:phone":"+49 3937/2272",
    "sg:postcode":"39606",
    "sg:province":"Sachsen-Anhalt",
    "wof:name":"Rainer L\u00fccke",
    "wof:placetype":"venue"
},
  "geometry": {"coordinates":[11.754894,52.784298],"type":"Point"}
}