{
  "type": "Feature",
  "properties": {
    "iso:country":"DE",
    "sg:address":"Am Ring 8",
    "sg:city":"Scheinfeld",
    "sg:phone":"+49 9162/591",
    "sg:postcode":"91443",
    "sg:province":"Bayern",
    "wof:name":"August Schmitt",
    "wof:placetype":"venue"
},
  "geometry": {"coordinates":[10.4639806747,49.6697311401],"type":"Point"}
}