{
  "type": "Feature",
  "properties": {
    "iso:country":"DE",
    "sg:address":"Neuenh\u00f6fer Allee 19 a",
    "sg:city":"K\u00f6ln",
    "sg:phone":"+49 221/366502",
    "sg:postcode":"50937",
    "sg:province":"Nordrhein-Westfalen",
    "wof:name":"K.-h. Zwingmann Restaurator",
    "wof:placetype":"venue"
},
  "geometry": {"coordinates":[6.9191808701,50.9118003845],"type":"Point"}
}