{
  "type": "Feature",
  "properties": {
    "iso:country":"DE",
    "sg:address":"Bertha-von-Suttner-Str. 9",
    "sg:city":"Magdeburg",
    "sg:phone":"+49 391/7333118",
    "sg:postcode":"39108",
    "sg:province":"Sachsen-Anhalt",
    "wof:name":"Volker Trube Rechtsanwalt",
    "wof:placetype":"venue"
},
  "geometry": {"coordinates":[11.6244306564,52.1374053955],"type":"Point"}
}