{
  "type": "Feature",
  "properties": {
    "iso:country":"DE",
    "sg:address":"Jenaprie\u00dfnitzer Str. 35",
    "sg:city":"Jena",
    "sg:phone":"+49 3641/444947",
    "sg:postcode":"07749",
    "sg:province":"Th\u00fcringen",
    "wof:name":"Kurt Hempel",
    "wof:placetype":"venue"
},
  "geometry": {"coordinates":[11.609838,50.931873],"type":"Point"}
}