{
  "type": "Feature",
  "properties": {
    "iso:country":"DE",
    "sg:address":"Lindauer Str. 6",
    "sg:city":"Oberstaufen",
    "sg:phone":"+49 8386/7393",
    "sg:postcode":"87534",
    "sg:province":"Bayern",
    "wof:name":"Max Klemm",
    "wof:placetype":"venue"
},
  "geometry": {"coordinates":[10.0213909149,47.554851532],"type":"Point"}
}