{
  "type": "Feature",
  "properties": {
    "iso:country":"DE",
    "sg:address":"Martinusplatz 11",
    "sg:city":"Erftstadt",
    "sg:postcode":"50374",
    "sg:province":"Nordrhein-Westfalen",
    "wof:name":"Kath. \u00d6ffentliche Bibliothek St. Martinus",
    "wof:placetype":"venue"
},
  "geometry": {"coordinates":[6.78788,50.83979],"type":"Point"}
}