{
  "type": "Feature",
  "properties": {
    "iso:country":"DE",
    "sg:address":"Bachstra\u00dfe 1",
    "sg:city":"T\u00fcrkheim",
    "sg:phone":"+49 172 8706378",
    "sg:postcode":"86842",
    "sg:province":"Bayern",
    "wof:name":"Entwurf, Design & Werbung Schedler - 86842 T\u00fcrkheim",
    "wof:placetype":"venue"
},
  "geometry": {"coordinates":[10.64277,48.062962],"type":"Point"}
}