{
  "type": "Feature",
  "properties": {
    "iso:country":"DE",
    "sg:address":"Wacholderstr. 15",
    "sg:city":"Rheinm\u00fcnster",
    "sg:phone":"+49 7227/4794",
    "sg:postcode":"77836",
    "sg:province":"Baden-W\u00fcrttemberg",
    "wof:name":"C. Weber Und A. Geiges Architekten",
    "wof:placetype":"venue"
},
  "geometry": {"coordinates":[8.053606,48.779156],"type":"Point"}
}