{
  "type": "Feature",
  "properties": {
    "iso:country":"DE",
    "sg:address":"Bahnhofstr. 24",
    "sg:city":"Benneckenstein",
    "sg:phone":"+49 39457/2216",
    "sg:postcode":"38877",
    "sg:province":"Sachsen-Anhalt",
    "wof:name":"Thomas Eckardt",
    "wof:placetype":"venue"
},
  "geometry": {"coordinates":[10.7161750793,51.6708755493],"type":"Point"}
}