{
  "type": "Feature",
  "properties": {
    "iso:country":"DE",
    "sg:address":"Neue Str.",
    "sg:city":"Emmerthal",
    "sg:phone":"+49 5155/7086",
    "sg:postcode":"31860",
    "sg:province":"Niedersachsen",
    "wof:name":"Schwimmhalle Emmerthal",
    "wof:placetype":"venue"
},
  "geometry": {"coordinates":[9.3917312622,52.0442733765],"type":"Point"}
}