{
  "type": "Feature",
  "properties": {
    "iso:country":"DE",
    "sg:address":"Anholter Str. 7",
    "sg:city":"Rees",
    "sg:phone":"+49 2851/8400",
    "sg:postcode":"46459",
    "sg:province":"Nordrhein-Westfalen",
    "wof:name":"Puszta",
    "wof:placetype":"venue"
},
  "geometry": {"coordinates":[6.4133419991,51.8130722046],"type":"Point"}
}