{
  "type": "Feature",
  "properties": {
    "iso:country":"DE",
    "sg:address":"Am Rabenstein 51",
    "sg:city":"Bad Homburg",
    "sg:phone":"+49 6172/81994",
    "sg:postcode":"61350",
    "sg:province":"Hessen",
    "wof:name":"Erich Wohl Technisches B\u00fcro",
    "wof:placetype":"venue"
},
  "geometry": {"coordinates":[8.615556,50.243599],"type":"Point"}
}