{
  "type": "Feature",
  "properties": {
    "iso:country":"DE",
    "sg:address":"Bahnhofstr. 9",
    "sg:city":"Berchtesgaden",
    "sg:phone":"+49 8652/2614",
    "sg:postcode":"83471",
    "sg:province":"Bayern",
    "wof:name":"Ludwig Schr\u00f6er",
    "wof:placetype":"venue"
},
  "geometry": {"coordinates":[13.0037889481,47.6314468384],"type":"Point"}
}