{
  "type": "Feature",
  "properties": {
    "iso:country":"DE",
    "sg:address":"Neue Dorfstr. 3",
    "sg:city":"Wardow",
    "sg:phone":"+49 38459/32842",
    "sg:postcode":"18299",
    "sg:province":"Mecklenburg-Vorpommern",
    "wof:name":"Egbert Bl\u00dcmke",
    "wof:placetype":"venue"
},
  "geometry": {"coordinates":[12.3915691376,53.9583244324],"type":"Point"}
}