{
  "type": "Feature",
  "properties": {
    "iso:country":"DE",
    "sg:address":"Sittenbachstr. 2",
    "sg:city":"Odelzhausen",
    "sg:phone":"+49 8134/1324",
    "sg:postcode":"85235",
    "sg:province":"Bayern",
    "wof:name":"Dipl.ing. Johann Ilmberger Architekt",
    "wof:placetype":"venue"
},
  "geometry": {"coordinates":[11.228332,48.329632],"type":"Point"}
}