{
  "type": "Feature",
  "properties": {
    "iso:country":"DE",
    "sg:address":"Bahnhofstr. 21",
    "sg:city":"Hemmingen",
    "sg:phone":"+49 7150/959863",
    "sg:postcode":"71282",
    "sg:province":"Baden-W\u00fcrttemberg",
    "wof:name":"P. Kleinberger Ingenieur",
    "wof:placetype":"venue"
},
  "geometry": {"coordinates":[9.0298099518,48.866809845],"type":"Point"}
}