{
  "type": "Feature",
  "properties": {
    "iso:country":"DE",
    "sg:address":"Stra\u00dfe nach Apollensdorf 29",
    "sg:city":"M\u00f6llensdorf",
    "sg:phone":"+49 34903/62746",
    "sg:postcode":"06869",
    "sg:province":"Sachsen-Anhalt",
    "wof:name":"Karl-heinz Schr\u00f6ter",
    "wof:placetype":"venue"
},
  "geometry": {"coordinates":[12.5358896255,51.9158973694],"type":"Point"}
}