{
  "type": "Feature",
  "properties": {
    "iso:country":"DE",
    "sg:address":"Altengammer Hauptdeich 68",
    "sg:city":"Hamburg",
    "sg:phone":"+49 40/7235298",
    "sg:postcode":"21039",
    "sg:province":"Hamburg",
    "wof:name":"Hans Hartung",
    "wof:placetype":"venue"
},
  "geometry": {"coordinates":[10.302329,53.438305],"type":"Point"}
}