{
  "type": "Feature",
  "properties": {
    "iso:country":"DE",
    "sg:address":"Hospitalstr. 2",
    "sg:city":"Ochtrup",
    "sg:phone":"+49 2553/98535",
    "sg:postcode":"48607",
    "sg:province":"Nordrhein-Westfalen",
    "wof:name":"Christine Leusbrock",
    "wof:placetype":"venue"
},
  "geometry": {"coordinates":[7.189241,52.211479],"type":"Point"}
}