{
  "type": "Feature",
  "properties": {
    "iso:country":"DE",
    "sg:address":"Westerladekop 22",
    "sg:city":"Jork",
    "sg:phone":"+49 4162/7162",
    "sg:postcode":"21635",
    "sg:province":"Niedersachsen",
    "wof:name":"Gerd Schuback",
    "wof:placetype":"venue"
},
  "geometry": {"coordinates":[9.6659002304,53.5198402405],"type":"Point"}
}