{
  "type": "Feature",
  "properties": {
    "iso:country":"DE",
    "sg:address":"Ackendorfer Weg 12",
    "sg:city":"Gutenswegen",
    "sg:phone":"+49 39202/61672",
    "sg:postcode":"39326",
    "sg:province":"Sachsen-Anhalt",
    "wof:name":"G. List Bau Gmbh",
    "wof:placetype":"venue"
},
  "geometry": {"coordinates":[11.4912290573,52.2299766541],"type":"Point"}
}