{
  "type": "Feature",
  "properties": {
    "iso:country":"DE",
    "sg:address":"Rottstr. 4-6",
    "sg:city":"Bochum",
    "sg:phone":"+49 234/66638",
    "sg:postcode":"44793",
    "sg:province":"Nordrhein-Westfalen",
    "wof:name":"Hagu Ges. F. Freizeit U. Unterhaltung Mbh",
    "wof:placetype":"venue"
},
  "geometry": {"coordinates":[7.213548,51.479221],"type":"Point"}
}