{
  "type": "Feature",
  "properties": {
    "iso:country":"DE",
    "sg:address":"J\u00fcterboger Chaussee 21",
    "sg:city":"Dahme",
    "sg:phone":"+49 35451/8149",
    "sg:postcode":"15936",
    "sg:province":"Brandenburg",
    "wof:name":"L\u00fcderitz",
    "wof:placetype":"venue"
},
  "geometry": {"coordinates":[13.4085102081,51.8687171936],"type":"Point"}
}