{
  "type": "Feature",
  "properties": {
    "iso:country":"DE",
    "sg:address":"Altendorfer Str. 103",
    "sg:city":"Essen",
    "sg:phone":"+49 201/1882763",
    "sg:postcode":"45143",
    "sg:province":"Nordrhein-Westfalen",
    "wof:name":"Redaktion Krupp Aktuell Friedrich Krupp",
    "wof:placetype":"venue"
},
  "geometry": {"coordinates":[6.9946799278,51.4588546753],"type":"Point"}
}