{
  "type": "Feature",
  "properties": {
    "iso:country":"DE",
    "sg:address":"Am Bahnhof",
    "sg:city":"Pretzsch",
    "sg:postcode":"06909",
    "sg:province":"Sachsen-Anhalt",
    "wof:name":"Formst\u00fcckwerkstatt",
    "wof:placetype":"venue"
},
  "geometry": {"coordinates":[12.7901201248,51.7155265808],"type":"Point"}
}