{
  "type": "Feature",
  "properties": {
    "iso:country":"DE",
    "sg:city":"Kaltenkirchen",
    "sg:phone":"+49 4191/7790060",
    "sg:postcode":"24568",
    "sg:province":"Schleswig-Holstein",
    "wof:name":"Walter Dienstleistungen",
    "wof:placetype":"venue"
},
  "geometry": {"coordinates":[9.959797,53.838127],"type":"Point"}
}