{
  "type": "Feature",
  "properties": {
    "iso:country":"DE",
    "sg:address":"W\u00fcschheimer Str. 25",
    "sg:city":"Euskirchen",
    "sg:phone":"+49 2251/4212",
    "sg:postcode":"53881",
    "sg:province":"Nordrhein-Westfalen",
    "wof:name":"Prof. Anton Berger",
    "wof:placetype":"venue"
},
  "geometry": {"coordinates":[6.813257,50.689327],"type":"Point"}
}