{
  "type": "Feature",
  "properties": {
    "iso:country":"DE",
    "sg:address":"Bahnhofstr. 5",
    "sg:city":"Bad Feilnbach",
    "sg:postcode":"83075",
    "sg:province":"Bayern",
    "wof:name":"Intereressengemeinschaft Moorentsorgung",
    "wof:placetype":"venue"
},
  "geometry": {"coordinates":[12.0099077225,47.7734985352],"type":"Point"}
}