{
  "type": "Feature",
  "properties": {
    "iso:country":"DE",
    "sg:address":"Gro\u00df-Buchholzer Kirchweg 67",
    "sg:city":"Hannover",
    "sg:phone":"+49 511/5498687",
    "sg:postcode":"30655",
    "sg:province":"Niedersachsen",
    "wof:name":"Friedrich Ernst Gmbh",
    "wof:placetype":"venue"
},
  "geometry": {"coordinates":[9.8044366837,52.4003982544],"type":"Point"}
}