{
  "type": "Feature",
  "properties": {
    "iso:country":"DE",
    "sg:address":"Unterbachstr. 1",
    "sg:city":"Ediger-Eller",
    "sg:phone":"+49 2675/736",
    "sg:postcode":"56814",
    "sg:province":"Rheinland-Pfalz",
    "wof:name":"Klemens Probst Weinanbau",
    "wof:placetype":"venue"
},
  "geometry": {"coordinates":[7.1595191956,50.0935707092],"type":"Point"}
}