{
  "type": "Feature",
  "properties": {
    "iso:country":"DE",
    "sg:address":"Schwalbenhof 1",
    "sg:city":"Gr\u00fcnsfeld",
    "sg:phone":"+49 9346/95300",
    "sg:postcode":"97947",
    "sg:province":"Baden-W\u00fcrttemberg",
    "wof:name":"Hs Umformtechnik Gmbh",
    "wof:placetype":"venue"
},
  "geometry": {"coordinates":[9.753815,49.639183],"type":"Point"}
}