{
  "type": "Feature",
  "properties": {
    "iso:country":"DE",
    "sg:address":"Postfach",
    "sg:city":"Mosbach",
    "sg:phone":"+49 6261/7936",
    "sg:postcode":"74801",
    "sg:province":"Baden-W\u00fcrttemberg",
    "wof:name":"Kuhn",
    "wof:placetype":"venue"
},
  "geometry": {"coordinates":[9.14587,49.351978],"type":"Point"}
}