{
  "type": "Feature",
  "properties": {
    "iso:country":"DE",
    "sg:address":"Mooswaldweg 4",
    "sg:city":"Titisee-Neustadt",
    "sg:postcode":"79822",
    "sg:province":"Baden-W\u00fcrttemberg",
    "wof:name":"Country U. Mode Gmbh & Co. Textileinkaufs Kg",
    "wof:placetype":"venue"
},
  "geometry": {"coordinates":[8.1483659744,47.9007911682],"type":"Point"}
}