{
  "type": "Feature",
  "properties": {
    "iso:country":"DE",
    "sg:address":"Marktplatz 22",
    "sg:city":"Lauf",
    "sg:phone":"+49 9123/2319",
    "sg:postcode":"91207",
    "sg:province":"Bayern",
    "wof:name":"Der Tabakladen Georg Kuhnd\u00f6rfer Nachf. Gmbh",
    "wof:placetype":"venue"
},
  "geometry": {"coordinates":[11.2819499969,49.5121688843],"type":"Point"}
}