{
  "type": "Feature",
  "properties": {
    "iso:country":"DE",
    "sg:address":"S\u00fcdring 38",
    "sg:city":"G\u00fctersloh",
    "sg:phone":"+49 5241/905386",
    "sg:postcode":"33332",
    "sg:province":"Nordrhein-Westfalen",
    "wof:name":"Dumschat",
    "wof:placetype":"venue"
},
  "geometry": {"coordinates":[8.369436,51.890251],"type":"Point"}
}