{
  "type": "Feature",
  "properties": {
    "iso:country":"DE",
    "sg:address":"Unterdorf 1",
    "sg:city":"Melsungen",
    "sg:phone":"+49 5661/2307",
    "sg:postcode":"34212",
    "sg:province":"Hessen",
    "wof:name":"Helmut Rudolf Gmbh",
    "wof:placetype":"venue"
},
  "geometry": {"coordinates":[9.5482997894,51.1541404724],"type":"Point"}
}