{
  "type": "Feature",
  "properties": {
    "iso:country":"DE",
    "sg:address":"Wasserturmstr. 4",
    "sg:city":"Erlangen",
    "sg:phone":"+49 9131/21816",
    "sg:postcode":"91054",
    "sg:province":"Bayern",
    "wof:name":"Wolfgang Heim",
    "wof:placetype":"venue"
},
  "geometry": {"coordinates":[11.003585,49.599167],"type":"Point"}
}