{
  "type": "Feature",
  "properties": {
    "iso:country":"DE",
    "sg:address":"Rheinstr. 22",
    "sg:city":"Bendorf",
    "sg:phone":"+49 2622/3335",
    "sg:postcode":"56170",
    "sg:province":"Rheinland-Pfalz",
    "wof:name":"Chr. Euler",
    "wof:placetype":"venue"
},
  "geometry": {"coordinates":[7.5747919083,50.4183311462],"type":"Point"}
}