{
  "type": "Feature",
  "properties": {
    "iso:country":"DE",
    "sg:address":"Viereckweg 34",
    "sg:city":"Berlin",
    "sg:phone":"+49 30/9497238",
    "sg:postcode":"13125",
    "sg:province":"Berlin",
    "wof:name":"Dr. Med. Ekkehard Sielaff",
    "wof:placetype":"venue"
},
  "geometry": {"coordinates":[13.500611,52.64222],"type":"Point"}
}