{
  "type": "Feature",
  "properties": {
    "iso:country":"DE",
    "sg:address":"Schrotzhofen",
    "sg:city":"Beratzhausen",
    "sg:phone":"+49 9493/654",
    "sg:postcode":"93176",
    "sg:province":"Bayern",
    "wof:name":"Johann Rappl",
    "wof:placetype":"venue"
},
  "geometry": {"coordinates":[11.829665,49.151962],"type":"Point"}
}