{
  "type": "Feature",
  "properties": {
    "iso:country":"DE",
    "sg:address":"Dorfstr. 49",
    "sg:city":"Sch\u00f6nbeck",
    "sg:phone":"+49 3968/210259",
    "sg:postcode":"17349",
    "sg:province":"Mecklenburg-Vorpommern",
    "wof:name":"A. Glinka",
    "wof:placetype":"venue"
},
  "geometry": {"coordinates":[13.5714149475,53.5761604309],"type":"Point"}
}