{
  "type": "Feature",
  "properties": {
    "iso:country":"DE",
    "sg:address":"Hauptstr. 47",
    "sg:city":"Waldorf",
    "sg:phone":"+49 2636/7042",
    "sg:postcode":"53498",
    "sg:province":"Rheinland-Pfalz",
    "wof:name":"Kreissparkasse Ahrweiler",
    "wof:placetype":"venue"
},
  "geometry": {"coordinates":[7.231546,50.486095],"type":"Point"}
}