{
  "type": "Feature",
  "properties": {
    "iso:country":"DE",
    "sg:address":"Westerhamer Weg 6",
    "sg:city":"Taufkirchen",
    "sg:phone":"+49 89/6140996",
    "sg:postcode":"82024",
    "sg:province":"Bayern",
    "wof:name":"Andreas Geipel Rechtsanwalt",
    "wof:placetype":"venue"
},
  "geometry": {"coordinates":[11.6117124557,48.0471458435],"type":"Point"}
}