{
  "type": "Feature",
  "properties": {
    "iso:country":"DE",
    "sg:address":"Mattenmoorstr. 4",
    "sg:city":"Seevetal",
    "sg:phone":"+49 40/75116500",
    "sg:postcode":"21217",
    "sg:province":"Niedersachsen",
    "wof:name":"Eiscafe Italia",
    "wof:placetype":"venue"
},
  "geometry": {"coordinates":[10.0223,53.429474],"type":"Point"}
}