{
  "type": "Feature",
  "properties": {
    "iso:country":"DE",
    "sg:address":"Am Waldacker 4",
    "sg:city":"Frankfurt",
    "sg:postcode":"60388",
    "sg:province":"Hessen",
    "wof:name":"Convent-invest Immobilien- Und Beteiligungsges. Mbh",
    "wof:placetype":"venue"
},
  "geometry": {"coordinates":[8.752066,50.142422],"type":"Point"}
}