{
  "type": "Feature",
  "properties": {
    "iso:country":"DE",
    "sg:address":"Schillerstr. 18",
    "sg:city":"Selb",
    "sg:postcode":"95100",
    "sg:province":"Bayern",
    "wof:name":"Plo\u00df Verwaltungs-gmbh",
    "wof:placetype":"venue"
},
  "geometry": {"coordinates":[12.13022995,50.1708717346],"type":"Point"}
}