{
  "type": "Feature",
  "properties": {
    "iso:country":"DE",
    "sg:address":"Falltorstr. 7",
    "sg:city":"Bruchk\u00f6bel",
    "sg:phone":"+49 6181/72003",
    "sg:postcode":"63486",
    "sg:province":"Hessen",
    "wof:name":"Ulrich Will Rechtsanwalt",
    "wof:placetype":"venue"
},
  "geometry": {"coordinates":[8.9119224548,50.2013511658],"type":"Point"}
}