{
  "type": "Feature",
  "properties": {
    "iso:country":"DE",
    "sg:address":"Platenmeisterstr. 47",
    "sg:city":"Uelzen",
    "sg:postcode":"29525",
    "sg:province":"Niedersachsen",
    "wof:name":"Blindenwerkst\u00e4tte",
    "wof:placetype":"venue"
},
  "geometry": {"coordinates":[10.585488,52.960201],"type":"Point"}
}