{
  "type": "Feature",
  "properties": {
    "iso:country":"DE",
    "sg:address":"Bramfelder Chaussee 242",
    "sg:city":"Hamburg",
    "sg:phone":"+49 40/6419892",
    "sg:postcode":"22177",
    "sg:province":"Hamburg",
    "wof:name":"Sybille Abrahams Rechtsanw\u00e4ltin",
    "wof:placetype":"venue"
},
  "geometry": {"coordinates":[10.0755367279,53.6129570007],"type":"Point"}
}