{
  "type": "Feature",
  "properties": {
    "iso:country":"DE",
    "sg:address":"Sch\u00e4ferstr. 13",
    "sg:city":"Karlsruhe",
    "sg:phone":"+49 721/681100",
    "sg:postcode":"76139",
    "sg:province":"Baden-W\u00fcrttemberg",
    "wof:name":"Ev. Pfarramt Laurentiusgem.",
    "wof:placetype":"venue"
},
  "geometry": {"coordinates":[8.4605398178,49.0282707214],"type":"Point"}
}