{
  "type": "Feature",
  "properties": {
    "iso:country":"DE",
    "sg:address":"In den Kiefern 2",
    "sg:city":"Schwanewede",
    "sg:phone":"+49 4209/1239",
    "sg:postcode":"28790",
    "sg:province":"Niedersachsen",
    "wof:name":"Bornsiep Hebamme",
    "wof:placetype":"venue"
},
  "geometry": {"coordinates":[8.586284,53.220894],"type":"Point"}
}