{
  "type": "Feature",
  "properties": {
    "iso:country":"DE",
    "sg:address":"K\u00f6nigsberger Str. 34",
    "sg:city":"Wipperf\u00fcrth",
    "sg:phone":"+49 2267/5315",
    "sg:postcode":"51688",
    "sg:province":"Nordrhein-Westfalen",
    "wof:name":"Klaus Fr\u00f6\u00dfler",
    "wof:placetype":"venue"
},
  "geometry": {"coordinates":[7.3985929489,51.1213188171],"type":"Point"}
}