{
  "type": "Feature",
  "properties": {
    "iso:country":"DE",
    "sg:address":"Hammerweg 12",
    "sg:city":"Weiden",
    "sg:phone":"+49 961/32859",
    "sg:postcode":"92637",
    "sg:province":"Bayern",
    "wof:name":"Radsport Russ Gmbh",
    "wof:placetype":"venue"
},
  "geometry": {"coordinates":[12.166224,49.687637],"type":"Point"}
}