{
  "type": "Feature",
  "properties": {
    "iso:country":"DE",
    "sg:address":"Rathausstr. 19",
    "sg:city":"Gaggenau",
    "sg:phone":"+49 7225/73126",
    "sg:postcode":"76571",
    "sg:province":"Baden-W\u00fcrttemberg",
    "wof:name":"Peter Mahler Ingenieur",
    "wof:placetype":"venue"
},
  "geometry": {"coordinates":[8.3065891266,48.8137931824],"type":"Point"}
}