{
  "type": "Feature",
  "properties": {
    "iso:country":"DE",
    "sg:address":"Greifswalder Str. 1",
    "sg:city":"Tornesch",
    "sg:postcode":"25436",
    "sg:province":"Schleswig-Holstein",
    "wof:name":"Gesch\u00e4ftsf\u00fchrung Kmm Varial Beratungs- Gmbh",
    "wof:placetype":"venue"
},
  "geometry": {"coordinates":[9.7190341949,53.6999816895],"type":"Point"}
}