{
  "type": "Feature",
  "properties": {
    "iso:country":"DE",
    "sg:address":"Felsens\u00e4gm\u00fchle",
    "sg:city":"Leonberg",
    "sg:phone":"+49 7195/71520",
    "sg:postcode":"71229",
    "sg:province":"Baden-W\u00fcrttemberg",
    "wof:name":"Michael Wagner",
    "wof:placetype":"venue"
},
  "geometry": {"coordinates":[9.004117012,48.8075485229],"type":"Point"}
}