{
  "type": "Feature",
  "properties": {
    "iso:country":"DE",
    "sg:address":"Bahnhofstr. 1",
    "sg:city":"Neustadt",
    "sg:phone":"+49 6321/926892",
    "sg:postcode":"67434",
    "sg:province":"Rheinland-Pfalz",
    "wof:name":"Tourist Kongre\u00df Und Saalbau Gmbh",
    "wof:placetype":"venue"
},
  "geometry": {"coordinates":[8.138952,49.350601],"type":"Point"}
}