{
  "type": "Feature",
  "properties": {
    "iso:country":"DE",
    "sg:address":"Schr\u00f6derstr.13",
    "sg:city":"L\u00fcneburg",
    "sg:phone":"+49 4131/41445",
    "sg:postcode":"21335",
    "sg:province":"Niedersachsen",
    "wof:name":"Schulzundkamp",
    "wof:placetype":"venue"
},
  "geometry": {"coordinates":[10.406725,53.248604],"type":"Point"}
}