{
  "type": "Feature",
  "properties": {
    "iso:country":"DE",
    "sg:address":"Friedrich-Engels-Str. 30",
    "sg:city":"D\u00fcsseldorf",
    "sg:phone":"+49 211/279034",
    "sg:postcode":"40627",
    "sg:province":"Nordrhein-Westfalen",
    "wof:name":"Lothar Steinbrink Ingenieur",
    "wof:placetype":"venue"
},
  "geometry": {"coordinates":[6.8651337624,51.2103233337],"type":"Point"}
}