{
  "type": "Feature",
  "properties": {
    "iso:country":"DE",
    "sg:address":"Hohlstr. 41",
    "sg:city":"Neunkirchen",
    "sg:phone":"+49 6821/88150",
    "sg:postcode":"66538",
    "sg:province":"Saarland",
    "wof:name":"Olympia",
    "wof:placetype":"venue"
},
  "geometry": {"coordinates":[7.1831698418,49.3381385803],"type":"Point"}
}