{
  "type": "Feature",
  "properties": {
    "iso:country":"DE",
    "sg:address":"Bergstr. 12",
    "sg:city":"Taufkirchen",
    "sg:phone":"+49 89/30777737",
    "sg:postcode":"82024",
    "sg:province":"Bayern",
    "wof:name":"Media And More Gmbh",
    "wof:placetype":"venue"
},
  "geometry": {"coordinates":[11.6156482697,48.0321998596],"type":"Point"}
}