{
  "type": "Feature",
  "properties": {
    "iso:country":"DE",
    "sg:address":"Gartenweg 3",
    "sg:city":"Langewiesen",
    "sg:phone":"+49 3677/61697",
    "sg:postcode":"98704",
    "sg:province":"Th\u00fcringen",
    "wof:name":"Thomas Merten",
    "wof:placetype":"venue"
},
  "geometry": {"coordinates":[10.9686307907,50.6704177856],"type":"Point"}
}