{
  "type": "Feature",
  "properties": {
    "iso:country":"DE",
    "sg:address":"Wichsenstein 6",
    "sg:city":"G\u00f6\u00dfweinstein",
    "sg:phone":"+49 9197/727",
    "sg:postcode":"91327",
    "sg:province":"Bayern",
    "wof:name":"Otto K\u00fcttner Ingenieur",
    "wof:placetype":"venue"
},
  "geometry": {"coordinates":[11.2672052383,49.7377243042],"type":"Point"}
}