{
  "type": "Feature",
  "properties": {
    "iso:country":"DE",
    "sg:address":"Birkenweg 20",
    "sg:city":"Sch\u00f6nbrunn",
    "sg:phone":"+49 6262/6796",
    "sg:postcode":"69436",
    "sg:province":"Baden-W\u00fcrttemberg",
    "wof:name":"Dr. Hubert Theile Tierarzt",
    "wof:placetype":"venue"
},
  "geometry": {"coordinates":[8.9290771484,49.3921852112],"type":"Point"}
}