{
  "type": "Feature",
  "properties": {
    "iso:country":"DE",
    "sg:address":"Hubertusstr. 53",
    "sg:city":"Leipzig",
    "sg:phone":"+49 341/328422",
    "sg:postcode":"04249",
    "sg:province":"Sachsen",
    "wof:name":"Repro Service Leipzig",
    "wof:placetype":"venue"
},
  "geometry": {"coordinates":[12.3069324493,51.2813224792],"type":"Point"}
}