{
  "type": "Feature",
  "properties": {
    "iso:country":"DE",
    "sg:address":"Alter Schulweg 1",
    "sg:city":"Ellefeld",
    "sg:phone":"+49 3745/70168",
    "sg:postcode":"08236",
    "sg:province":"Sachsen",
    "wof:name":"Vogtland Grabmale",
    "wof:placetype":"venue"
},
  "geometry": {"coordinates":[12.390335083,50.4842300415],"type":"Point"}
}