{
  "type": "Feature",
  "properties": {
    "iso:country":"DE",
    "sg:address":"Femeweg 12",
    "sg:city":"Essen",
    "sg:phone":"+49 5434/2525",
    "sg:postcode":"49632",
    "sg:province":"Niedersachsen",
    "wof:name":"Doris Klatte",
    "wof:placetype":"venue"
},
  "geometry": {"coordinates":[7.928955,52.721455],"type":"Point"}
}