{
  "type": "Feature",
  "properties": {
    "iso:country":"DE",
    "sg:address":"Erlenbacher Str.",
    "sg:city":"Erbach",
    "sg:phone":"+49 6062/3567",
    "sg:postcode":"64711",
    "sg:province":"Hessen",
    "wof:name":"Johann Dingeldey",
    "wof:placetype":"venue"
},
  "geometry": {"coordinates":[8.9988927841,49.6543998718],"type":"Point"}
}