{
  "type": "Feature",
  "properties": {
    "iso:country":"DE",
    "sg:address":"Braasstr. 32",
    "sg:city":"Rinteln",
    "sg:phone":"+49 5751/957155",
    "sg:postcode":"31737",
    "sg:province":"Niedersachsen",
    "wof:name":"Kr\u00fcgel",
    "wof:placetype":"venue"
},
  "geometry": {"coordinates":[9.082038,52.168812],"type":"Point"}
}