{
  "type": "Feature",
  "properties": {
    "iso:country":"DE",
    "sg:address":"Untere Dorfgasse",
    "sg:city":"Kelheim",
    "sg:phone":"+49 9441/8456",
    "sg:postcode":"93309",
    "sg:province":"Bayern",
    "wof:name":"M. Kohlmann",
    "wof:placetype":"venue"
},
  "geometry": {"coordinates":[11.9002895355,48.9060287476],"type":"Point"}
}