{
  "type": "Feature",
  "properties": {
    "iso:country":"DE",
    "sg:address":"Dossenbergerstr. 5",
    "sg:city":"Bobingen",
    "sg:phone":"+49 8203/5889",
    "sg:postcode":"86399",
    "sg:province":"Bayern",
    "wof:name":"M. Nerlinger",
    "wof:placetype":"venue"
},
  "geometry": {"coordinates":[10.7272891998,48.2598457336],"type":"Point"}
}