{
  "type": "Feature",
  "properties": {
    "iso:country":"DE",
    "sg:address":"Fr\u00f6belstr. 81",
    "sg:city":"K\u00f6ln",
    "sg:postcode":"50767",
    "sg:province":"Nordrhein-Westfalen",
    "wof:name":"Medsynergy Gmbh",
    "wof:placetype":"venue"
},
  "geometry": {"coordinates":[6.8670949936,50.9984855652],"type":"Point"}
}