{
  "type": "Feature",
  "properties": {
    "iso:country":"DE",
    "sg:address":"Ritter-Wulf-Platz 3",
    "sg:city":"Schwarzenbek",
    "sg:phone":"+49 4151/6684",
    "sg:postcode":"21493",
    "sg:province":"Schleswig-Holstein",
    "wof:name":"Alanya",
    "wof:placetype":"venue"
},
  "geometry": {"coordinates":[10.4778261185,53.5030479431],"type":"Point"}
}