{
  "type": "Feature",
  "properties": {
    "iso:country":"DE",
    "sg:address":"Westmarkstr. 33",
    "sg:city":"Bar\u00dfel",
    "sg:phone":"+49 4499/7956",
    "sg:postcode":"26676",
    "sg:province":"Niedersachsen",
    "wof:name":"Hermann Kruse Architekt",
    "wof:placetype":"venue"
},
  "geometry": {"coordinates":[7.751921,53.148872],"type":"Point"}
}