{
  "type": "Feature",
  "properties": {
    "iso:country":"DE",
    "sg:address":"Bornaische Str. 21",
    "sg:city":"Leipzig",
    "sg:phone":"+49 341/47777323",
    "sg:postcode":"04277",
    "sg:province":"Sachsen",
    "wof:name":"Montagefuchs Gmbh Bausanierungs Gmbh",
    "wof:placetype":"venue"
},
  "geometry": {"coordinates":[12.377914,51.308163],"type":"Point"}
}