{
  "type": "Feature",
  "properties": {
    "iso:country":"DE",
    "sg:address":"An der Kreuzheck 1",
    "sg:city":"Frankfurt",
    "sg:phone":"+49 69/35355066",
    "sg:postcode":"60529",
    "sg:province":"Hessen",
    "wof:name":"Eska Leasing- Und Handels Gmbh",
    "wof:placetype":"venue"
},
  "geometry": {"coordinates":[8.5746078491,50.0826454163],"type":"Point"}
}