{
  "type": "Feature",
  "properties": {
    "iso:country":"DE",
    "sg:address":"Kleine Marktstr. 1",
    "sg:city":"Fulda",
    "sg:phone":"+49 661/75153",
    "sg:postcode":"36037",
    "sg:province":"Hessen",
    "wof:name":"Atelier Juwel Inh. Horst Simon",
    "wof:placetype":"venue"
},
  "geometry": {"coordinates":[9.6778945923,50.5506248474],"type":"Point"}
}