{
  "type": "Feature",
  "properties": {
    "iso:country":"DE",
    "sg:address":"Herzogstr. 14",
    "sg:city":"Viersen",
    "sg:phone":"+49 2162/31917",
    "sg:postcode":"41747",
    "sg:province":"Nordrhein-Westfalen",
    "wof:name":"Ewald Schwiers",
    "wof:placetype":"venue"
},
  "geometry": {"coordinates":[6.3889718056,51.2629966736],"type":"Point"}
}