{
  "type": "Feature",
  "properties": {
    "iso:country":"DE",
    "sg:address":"Hindenburgstr. 18",
    "sg:city":"Ostfildern",
    "sg:phone":"+49 711/3482133",
    "sg:postcode":"73760",
    "sg:province":"Baden-W\u00fcrttemberg",
    "wof:name":"Bluez",
    "wof:placetype":"venue"
},
  "geometry": {"coordinates":[9.297893,48.714104],"type":"Point"}
}