{
  "type": "Feature",
  "properties": {
    "iso:country":"DE",
    "sg:address":"Horber Str 36",
    "sg:city":"Haiterbach",
    "sg:phone":"+49 7456/93970",
    "sg:postcode":"72221",
    "sg:province":"Baden-W\u00fcrttemberg",
    "wof:name":"Martin Ruoss, Inh. Eugen Luz Gmbh & Co Wohnm\u00f6bel Kg",
    "wof:placetype":"venue"
},
  "geometry": {"coordinates":[8.647328,48.51984],"type":"Point"}
}