{
  "type": "Feature",
  "properties": {
    "iso:country":"DE",
    "sg:address":"Schillerstr. 25",
    "sg:city":"Lich",
    "sg:phone":"+49 6404/90244",
    "sg:postcode":"35423",
    "sg:province":"Hessen",
    "wof:name":"Ingwis Datentechnik Gmbh",
    "wof:placetype":"venue"
},
  "geometry": {"coordinates":[8.8102636337,50.5256729126],"type":"Point"}
}