{
  "type": "Feature",
  "properties": {
    "iso:country":"DE",
    "sg:address":"Am Albertsberg 7",
    "sg:city":"Eppingen",
    "sg:phone":"+49 7262/912583",
    "sg:postcode":"75031",
    "sg:province":"Baden-W\u00fcrttemberg",
    "wof:name":"Deco Gasger\u00e4te-vertriebs Gmbh",
    "wof:placetype":"venue"
},
  "geometry": {"coordinates":[8.9102201462,49.1423072815],"type":"Point"}
}