{
  "type": "Feature",
  "properties": {
    "iso:country":"DE",
    "sg:address":"Beunestr. 15",
    "sg:city":"Frankfurt",
    "sg:phone":"+49 69/398415",
    "sg:postcode":"65934",
    "sg:province":"Hessen",
    "wof:name":"K.-h. Born",
    "wof:placetype":"venue"
},
  "geometry": {"coordinates":[8.566462,50.099781],"type":"Point"}
}