{
  "type": "Feature",
  "properties": {
    "iso:country":"DE",
    "sg:address":"Br\u00fcckenstr. 7",
    "sg:city":"Gro\u00dfbottwar",
    "sg:phone":"+49 7148/2658",
    "sg:postcode":"71723",
    "sg:province":"Baden-W\u00fcrttemberg",
    "wof:name":"Bottwarstube Hof Und Lembach",
    "wof:placetype":"venue"
},
  "geometry": {"coordinates":[9.311006546,49.0104598999],"type":"Point"}
}