{
  "type": "Feature",
  "properties": {
    "iso:country":"DE",
    "sg:address":"Leipziger Str. 106",
    "sg:city":"Crimmitschau",
    "sg:phone":"+49 3762/2722",
    "sg:postcode":"08451",
    "sg:province":"Sachsen",
    "wof:name":"Helga Ritter",
    "wof:placetype":"venue"
},
  "geometry": {"coordinates":[12.3880596161,50.8250389099],"type":"Point"}
}