{
  "type": "Feature",
  "properties": {
    "iso:country":"DE",
    "sg:address":"Marktpassage",
    "sg:city":"Schlema",
    "sg:phone":"+49 3772/22784",
    "sg:postcode":"08301",
    "sg:province":"Sachsen",
    "wof:name":"U. Schiffner",
    "wof:placetype":"venue"
},
  "geometry": {"coordinates":[12.669575,50.598965],"type":"Point"}
}