{
  "type": "Feature",
  "properties": {
    "iso:country":"DE",
    "sg:address":"Friedrich-von-Schiller-Str. 7",
    "sg:city":"Bayreuth",
    "sg:postcode":"95444",
    "sg:province":"Bayern",
    "wof:name":"Eb Textilhandels Gmbh",
    "wof:placetype":"venue"
},
  "geometry": {"coordinates":[11.5775251389,49.9500427246],"type":"Point"}
}