{
  "type": "Feature",
  "properties": {
    "iso:country":"DE",
    "sg:address":"Hauptstr. 400",
    "sg:city":"Weil am Rhein",
    "sg:phone":"+49 7621/799350",
    "sg:postcode":"79576",
    "sg:province":"Baden-W\u00fcrttemberg",
    "wof:name":"Neukauf Markt",
    "wof:placetype":"venue"
},
  "geometry": {"coordinates":[7.5975899696,47.5905609131],"type":"Point"}
}