{
  "type": "Feature",
  "properties": {
    "iso:country":"DE",
    "sg:address":"Dieselstr. 5",
    "sg:city":"Kronberg",
    "sg:phone":"+49 6173/930930",
    "sg:postcode":"61476",
    "sg:province":"Hessen",
    "wof:name":"Jahn Rechtsanwalt",
    "wof:placetype":"venue"
},
  "geometry": {"coordinates":[8.5495376587,50.1775779724],"type":"Point"}
}