{
  "type": "Feature",
  "properties": {
    "iso:country":"DE",
    "sg:address":"Fulgengrund 3",
    "sg:city":"K\u00fchlungsborn",
    "sg:postcode":"18225",
    "sg:province":"Mecklenburg-Vorpommern",
    "wof:name":"Online Professionell.de Gmbh",
    "wof:placetype":"venue"
},
  "geometry": {"coordinates":[11.767022,54.146576],"type":"Point"}
}