{
  "type": "Feature",
  "properties": {
    "iso:country":"DE",
    "sg:address":"Kreuzstr. 16",
    "sg:city":"Weener",
    "sg:phone":"+49 4951/2921",
    "sg:postcode":"26826",
    "sg:province":"Niedersachsen",
    "wof:name":"H. Und E. Buisenga",
    "wof:placetype":"venue"
},
  "geometry": {"coordinates":[7.3468179703,53.1601600647],"type":"Point"}
}