{
  "type": "Feature",
  "properties": {
    "iso:country":"DE",
    "sg:address":"Bahnhofstr. 52",
    "sg:city":"Neu-Eichenberg",
    "sg:phone":"+49 5542/3161",
    "sg:postcode":"37249",
    "sg:province":"Hessen",
    "wof:name":"K. Orth Obstanbau",
    "wof:placetype":"venue"
},
  "geometry": {"coordinates":[9.9153642654,51.3749923706],"type":"Point"}
}