{
  "type": "Feature",
  "properties": {
    "iso:country":"DE",
    "sg:address":"Hauptstr. 11",
    "sg:city":"Scheid",
    "sg:phone":"+49 6557/92050",
    "sg:postcode":"54611",
    "sg:province":"Rheinland-Pfalz",
    "wof:name":"Marianne Ofer Messebau",
    "wof:placetype":"venue"
},
  "geometry": {"coordinates":[6.426048,50.358109],"type":"Point"}
}