{
  "type": "Feature",
  "properties": {
    "iso:country":"DE",
    "sg:address":"Dornierstr 67-69",
    "sg:city":"Straubing",
    "sg:phone":"+49 9421/18470",
    "sg:postcode":"94315",
    "sg:province":"Bayern",
    "wof:name":"Ertl Gmbh",
    "wof:placetype":"venue"
},
  "geometry": {"coordinates":[12.631128,48.885029],"type":"Point"}
}