{
  "type": "Feature",
  "properties": {
    "iso:country":"DE",
    "sg:address":"Augsburger Str. 20",
    "sg:city":"Zeuthen",
    "sg:phone":"+49 33762/70128",
    "sg:postcode":"15738",
    "sg:province":"Brandenburg",
    "wof:name":"Andreas Swinka",
    "wof:placetype":"venue"
},
  "geometry": {"coordinates":[13.633418,52.367004],"type":"Point"}
}