{
  "type": "Feature",
  "properties": {
    "iso:country":"DE",
    "sg:address":"K\u00f6nigsberger Str. 4",
    "sg:city":"Frankfurt",
    "sg:phone":"+49 4961/7378119",
    "sg:postcode":"60487",
    "sg:province":"Hessen",
    "wof:name":"Kronberger Offsetdruck Gmbh",
    "wof:placetype":"venue"
},
  "geometry": {"coordinates":[8.5126047134,50.1777305603],"type":"Point"}
}