{
  "type": "Feature",
  "properties": {
    "iso:country":"DE",
    "sg:address":"Hauptstr. 26",
    "sg:city":"Memmelsdorf",
    "sg:phone":"+49 951/44206",
    "sg:postcode":"96117",
    "sg:province":"Bayern",
    "wof:name":"Alfred Pickel",
    "wof:placetype":"venue"
},
  "geometry": {"coordinates":[10.954832077,49.9326896667],"type":"Point"}
}