{
  "type": "Feature",
  "properties": {
    "iso:country":"DE",
    "sg:address":"St.-T\u00f6nnis-Str. 23",
    "sg:city":"K\u00f6ln",
    "sg:phone":"+49 221/783888",
    "sg:postcode":"50769",
    "sg:province":"Nordrhein-Westfalen",
    "wof:name":"Paul-heinz Wirtz Textilien",
    "wof:placetype":"venue"
},
  "geometry": {"coordinates":[6.8654642105,51.0649833679],"type":"Point"}
}