{
  "type": "Feature",
  "properties": {
    "iso:country":"DE",
    "sg:address":"Dietkirchenstr. 24",
    "sg:city":"Bonn",
    "sg:phone":"+49 228/634414",
    "sg:postcode":"53111",
    "sg:province":"Nordrhein-Westfalen",
    "wof:name":"Gerhard Ellinghaus Steuerberater",
    "wof:placetype":"venue"
},
  "geometry": {"coordinates":[7.0954451561,50.7431564331],"type":"Point"}
}