{
  "type": "Feature",
  "properties": {
    "iso:country":"DE",
    "sg:address":"Hohe Str 36",
    "sg:city":"Weinb\u00f6hla",
    "sg:phone":"+49 35243/32116",
    "sg:postcode":"01689",
    "sg:province":"Sachsen",
    "wof:name":"Teka-saunabau Gmbh",
    "wof:placetype":"venue"
},
  "geometry": {"coordinates":[13.5930118561,51.1655845642],"type":"Point"}
}