{
  "type": "Feature",
  "properties": {
    "iso:country":"DE",
    "sg:address":"Oberdorfstr. 5a",
    "sg:city":"Mei\u00dfenheim",
    "sg:phone":"+49 7824/2430",
    "sg:postcode":"77974",
    "sg:province":"Baden-W\u00fcrttemberg",
    "wof:name":"Werner Heim",
    "wof:placetype":"venue"
},
  "geometry": {"coordinates":[7.77351,48.407822],"type":"Point"}
}