{
  "type": "Feature",
  "properties": {
    "iso:country":"DE",
    "sg:address":"Weststr. 37",
    "sg:city":"Schmallenberg",
    "sg:phone":"+49 2972/2620",
    "sg:postcode":"57392",
    "sg:province":"Nordrhein-Westfalen",
    "wof:name":"Peter Walach Architekt",
    "wof:placetype":"venue"
},
  "geometry": {"coordinates":[8.284423,51.148117],"type":"Point"}
}