{
  "type": "Feature",
  "properties": {
    "iso:country":"DE",
    "sg:address":"Schulstr. 4",
    "sg:city":"Weyhe",
    "sg:phone":"+49 421/803547",
    "sg:postcode":"28844",
    "sg:province":"Niedersachsen",
    "wof:name":"Albert Hattesohl Architekt",
    "wof:placetype":"venue"
},
  "geometry": {"coordinates":[8.819805,52.988522],"type":"Point"}
}