{
  "type": "Feature",
  "properties": {
    "iso:country":"DE",
    "sg:address":"Gartenstr. 19",
    "sg:city":"Bad Friedrichshall",
    "sg:phone":"+49 7136/24312",
    "sg:postcode":"74177",
    "sg:province":"Baden-W\u00fcrttemberg",
    "wof:name":"B. Und R. Schneider",
    "wof:placetype":"venue"
},
  "geometry": {"coordinates":[9.21492,49.224274],"type":"Point"}
}