{
  "type": "Feature",
  "properties": {
    "iso:country":"DE",
    "sg:address":"Ch\u00f6rauer Str. 46",
    "sg:city":"Dessau",
    "sg:phone":"+49 340/511983",
    "sg:postcode":"06847",
    "sg:province":"Sachsen-Anhalt",
    "wof:name":"C. Witte",
    "wof:placetype":"venue"
},
  "geometry": {"coordinates":[12.1536912918,51.8086090088],"type":"Point"}
}