{
  "type": "Feature",
  "properties": {
    "iso:country":"DE",
    "sg:address":"Hans-Sachs-Str. 17",
    "sg:city":"Chemnitz",
    "sg:phone":"+49 371/515754",
    "sg:postcode":"09126",
    "sg:province":"Sachsen",
    "wof:name":"U. Seidler Immobilienmakler",
    "wof:placetype":"venue"
},
  "geometry": {"coordinates":[12.9356040955,50.8288002014],"type":"Point"}
}