{
  "type": "Feature",
  "properties": {
    "iso:country":"DE",
    "sg:address":"L\u00e4rchenweg 4",
    "sg:city":"Niedernhausen",
    "sg:phone":"+49 6127/3790",
    "sg:postcode":"65527",
    "sg:province":"Hessen",
    "wof:name":"Edith Dietz Steuerberaterin",
    "wof:placetype":"venue"
},
  "geometry": {"coordinates":[8.3299026489,50.171421051],"type":"Point"}
}