{
  "type": "Feature",
  "properties": {
    "iso:country":"DE",
    "sg:address":"Wurzacher Str. 44",
    "sg:city":"Bad Waldsee",
    "sg:phone":"+49 7524/2505",
    "sg:postcode":"88339",
    "sg:province":"Baden-W\u00fcrttemberg",
    "wof:name":"Gastst\u00e4tte Wilder Mann",
    "wof:placetype":"venue"
},
  "geometry": {"coordinates":[9.7592983246,47.9196472168],"type":"Point"}
}