{
  "type": "Feature",
  "properties": {
    "iso:country":"DE",
    "sg:address":"M\u00fchlstr. 2",
    "sg:city":"Gernsheim",
    "sg:phone":"+49 6258/2422",
    "sg:postcode":"64579",
    "sg:province":"Hessen",
    "wof:name":"Maria Goetz",
    "wof:placetype":"venue"
},
  "geometry": {"coordinates":[8.4847249985,49.7490463257],"type":"Point"}
}