{
  "type": "Feature",
  "properties": {
    "iso:country":"DE",
    "sg:address":"Ottenlock 8",
    "sg:city":"Wunstorf",
    "sg:phone":"+49 5033/1541",
    "sg:postcode":"31515",
    "sg:province":"Niedersachsen",
    "wof:name":"Pension Haus Ottenlock",
    "wof:placetype":"venue"
},
  "geometry": {"coordinates":[9.3580541611,52.4547691345],"type":"Point"}
}