{
  "type": "Feature",
  "properties": {
    "iso:country":"DE",
    "sg:address":"Pestalozzistr. 5",
    "sg:city":"A\u00dflar",
    "sg:phone":"+49 6441/81519",
    "sg:postcode":"35614",
    "sg:province":"Hessen",
    "wof:name":"Onkel Adolf",
    "wof:placetype":"venue"
},
  "geometry": {"coordinates":[8.4614925385,50.5938262939],"type":"Point"}
}