{
  "type": "Feature",
  "properties": {
    "iso:country":"DE",
    "sg:address":"Lange Str. 20",
    "sg:city":"Ganderkesee",
    "sg:phone":"+49 4222/2501",
    "sg:postcode":"27777",
    "sg:province":"Niedersachsen",
    "wof:name":"Reisedienst Thiemann Inh. Werner Thiemann",
    "wof:placetype":"venue"
},
  "geometry": {"coordinates":[8.5507516861,53.0305480957],"type":"Point"}
}