{
  "type": "Feature",
  "properties": {
    "iso:country":"DE",
    "sg:address":"Goethestr. 18",
    "sg:city":"Eberswalde",
    "sg:phone":"+49 3334/236037",
    "sg:postcode":"16225",
    "sg:province":"Brandenburg",
    "wof:name":"Die 2 K\u00fcchenwelt Gmbh",
    "wof:placetype":"venue"
},
  "geometry": {"coordinates":[13.820399,52.830769],"type":"Point"}
}