{
  "type": "Feature",
  "properties": {
    "iso:country":"DE",
    "sg:address":"Streitburg 108",
    "sg:city":"Wiesenttal",
    "sg:phone":"+49 9196/325",
    "sg:postcode":"91346",
    "sg:province":"Bayern",
    "wof:name":"Adlerbrennerei Sch\u00fctz Inh. M. M. Pircher",
    "wof:placetype":"venue"
},
  "geometry": {"coordinates":[11.2195901871,49.8144798279],"type":"Point"}
}