{
  "type": "Feature",
  "properties": {
    "iso:country":"DE",
    "sg:address":"Platanenallee 64",
    "sg:city":"\u00d6hringen",
    "sg:phone":"+49 7941/34093",
    "sg:postcode":"74613",
    "sg:province":"Baden-W\u00fcrttemberg",
    "wof:name":"H\u00f6llger Bausysteme Gmbh",
    "wof:placetype":"venue"
},
  "geometry": {"coordinates":[9.5077943802,49.1913108826],"type":"Point"}
}