{
  "type": "Feature",
  "properties": {
    "iso:country":"DE",
    "sg:address":"Paulsborner Str. 22",
    "sg:city":"Berlin",
    "sg:phone":"+49 30/8927927",
    "sg:postcode":"10709",
    "sg:province":"Berlin",
    "wof:name":"Kurt Hoppe",
    "wof:placetype":"venue"
},
  "geometry": {"coordinates":[13.297383,52.493252],"type":"Point"}
}