{
  "type": "Feature",
  "properties": {
    "iso:country":"DE",
    "sg:address":"M\u00fchle 53 1/3",
    "sg:city":"Jachenau",
    "sg:phone":"+49 8043/365",
    "sg:postcode":"83676",
    "sg:province":"Bayern",
    "wof:name":"Anton Rinner Elektroinstallation",
    "wof:placetype":"venue"
},
  "geometry": {"coordinates":[11.434743,47.605785],"type":"Point"}
}