{
  "type": "Feature",
  "properties": {
    "iso:country":"DE",
    "sg:address":"Zur Wasserburg 25",
    "sg:city":"Langenfeld",
    "sg:phone":"+49 212/6844",
    "sg:postcode":"40764",
    "sg:province":"Nordrhein-Westfalen",
    "wof:name":"Alfred Kirsten Architekt",
    "wof:placetype":"venue"
},
  "geometry": {"coordinates":[6.992871,51.136044],"type":"Point"}
}