{
  "type": "Feature",
  "properties": {
    "iso:country":"DE",
    "sg:address":"Rathausplatz 3",
    "sg:city":"Ingolstadt",
    "sg:phone":"+49 841/17981",
    "sg:postcode":"85049",
    "sg:province":"Bayern",
    "wof:name":"Armin Ru\u00df Rechtsanwalt",
    "wof:placetype":"venue"
},
  "geometry": {"coordinates":[11.4248390198,48.7627639771],"type":"Point"}
}