{
  "type": "Feature",
  "properties": {
    "iso:country":"DE",
    "sg:address":"Waitzinger Wiese 1",
    "sg:city":"Landsberg",
    "sg:postcode":"86899",
    "sg:province":"Bayern",
    "wof:name":"Haspo Veranstaltungs Gmbh",
    "wof:placetype":"venue"
},
  "geometry": {"coordinates":[10.871503,48.05666],"type":"Point"}
}