{
  "type": "Feature",
  "properties": {
    "iso:country":"DE",
    "sg:address":"Blautopfstr.",
    "sg:city":"Blaubeuren",
    "sg:phone":"+49 7344/921027",
    "sg:postcode":"89143",
    "sg:province":"Baden-W\u00fcrttemberg",
    "wof:name":"Historische Hammerschmiede",
    "wof:placetype":"venue"
},
  "geometry": {"coordinates":[9.783695,48.415222],"type":"Point"}
}