{
  "type": "Feature",
  "properties": {
    "iso:country":"DE",
    "sg:address":"\u00dcber der Bahn 6",
    "sg:city":"Grebenstein",
    "sg:phone":"+49 5674/925630",
    "sg:postcode":"34393",
    "sg:province":"Hessen",
    "wof:name":"Sig-technik Werkzeug Gmbh",
    "wof:placetype":"venue"
},
  "geometry": {"coordinates":[9.4209785461,51.4492454529],"type":"Point"}
}