{
  "type": "Feature",
  "properties": {
    "iso:country":"DE",
    "sg:address":"Dr.-Wachsmann-Str.",
    "sg:city":"Zinnowitz",
    "sg:phone":"+49 38377/40828",
    "sg:postcode":"17454",
    "sg:province":"Mecklenburg-Vorpommern",
    "wof:name":"G. Czassny",
    "wof:placetype":"venue"
},
  "geometry": {"coordinates":[13.9086942673,54.079082489],"type":"Point"}
}