{
  "type": "Feature",
  "properties": {
    "iso:country":"DE",
    "sg:address":"Siemensstr.9",
    "sg:city":"Berlin",
    "sg:phone":"+49 30/79785790",
    "sg:postcode":"12247",
    "sg:province":"Berlin",
    "wof:name":"Timetrax*** Gesellschaft F\u00fcr Webdesign",
    "wof:placetype":"venue"
},
  "geometry": {"coordinates":[13.3404684067,52.4457740784],"type":"Point"}
}