{
  "type": "Feature",
  "properties": {
    "iso:country":"DE",
    "sg:address":"Reinerzer Ring 78",
    "sg:city":"L\u00fcdenscheid",
    "sg:phone":"+49 2351/8855",
    "sg:postcode":"58511",
    "sg:province":"Nordrhein-Westfalen",
    "wof:name":"Ows Bauplanungs- Und Beratungs Gmbh",
    "wof:placetype":"venue"
},
  "geometry": {"coordinates":[7.655105,51.224628],"type":"Point"}
}