{
  "type": "Feature",
  "properties": {
    "iso:country":"DE",
    "sg:address":"R\u00fcsgen 10",
    "sg:city":"Schwalmtal",
    "sg:phone":"+49 2163/5792898",
    "sg:postcode":"41366",
    "sg:province":"Nordrhein-Westfalen",
    "wof:name":"Lohmann Industrie-elektronik Taupunkt- Und Feuchtemesstechnik Gbr",
    "wof:placetype":"venue"
},
  "geometry": {"coordinates":[6.260563,51.213936],"type":"Point"}
}