{
  "type": "Feature",
  "properties": {
    "iso:country":"DE",
    "sg:address":"Westring 99",
    "sg:city":"Salzkotten",
    "sg:phone":"+49 5258/3256",
    "sg:postcode":"33154",
    "sg:province":"Nordrhein-Westfalen",
    "wof:name":"Uellendahl Und Partner",
    "wof:placetype":"venue"
},
  "geometry": {"coordinates":[8.593595,51.665569],"type":"Point"}
}