{
  "type": "Feature",
  "properties": {
    "iso:country":"DE",
    "sg:address":"Niederrheinische Str. 8",
    "sg:city":"Stadtallendorf",
    "sg:phone":"+49 6428/2955",
    "sg:postcode":"35260",
    "sg:province":"Hessen",
    "wof:name":"R. Pawelczyk Immobilienmakler",
    "wof:placetype":"venue"
},
  "geometry": {"coordinates":[9.0197486877,50.8265571594],"type":"Point"}
}