{
  "type": "Feature",
  "properties": {
    "iso:country":"DE",
    "sg:address":"T\u00f6pferstr. 64",
    "sg:city":"Joachimsthal",
    "sg:postcode":"16247",
    "sg:province":"Brandenburg",
    "wof:name":"Uwe Welck",
    "wof:placetype":"venue"
},
  "geometry": {"coordinates":[13.752598,52.977386],"type":"Point"}
}