{
  "type": "Feature",
  "properties": {
    "iso:country":"DE",
    "sg:address":"Wedenhofstr. 7",
    "sg:city":"Traben-Trarbach",
    "sg:phone":"+49 6541/6279",
    "sg:postcode":"56841",
    "sg:province":"Rheinland-Pfalz",
    "wof:name":"Wilhelm Heydt",
    "wof:placetype":"venue"
},
  "geometry": {"coordinates":[7.1040477753,49.9778938293],"type":"Point"}
}