{
  "type": "Feature",
  "properties": {
    "iso:country":"DE",
    "sg:address":"F\u00fcnfhausenstr.",
    "sg:city":"Springe",
    "sg:phone":"+49 5041/63116",
    "sg:postcode":"31832",
    "sg:province":"Niedersachsen",
    "wof:name":"Modea Gmbh & Co.",
    "wof:placetype":"venue"
},
  "geometry": {"coordinates":[9.554703,52.209377],"type":"Point"}
}