{
  "type": "Feature",
  "properties": {
    "iso:country":"DE",
    "sg:address":"Simrockstr. 1",
    "sg:city":"Neuss",
    "sg:phone":"+49 2131/42261",
    "sg:postcode":"41464",
    "sg:province":"Nordrhein-Westfalen",
    "wof:name":"Haus Simrock",
    "wof:placetype":"venue"
},
  "geometry": {"coordinates":[6.6950650215,51.1917304993],"type":"Point"}
}