{
  "type": "Feature",
  "properties": {
    "iso:country":"DE",
    "sg:address":"Wiesenweg 10",
    "sg:city":"Berlin",
    "sg:phone":"+49 30/76942100",
    "sg:postcode":"12247",
    "sg:province":"Berlin",
    "wof:name":"Mediport Venture Fonds Gmbh",
    "wof:placetype":"venue"
},
  "geometry": {"coordinates":[13.328204,52.441547],"type":"Point"}
}