{
  "type": "Feature",
  "properties": {
    "iso:country":"DE",
    "sg:address":"Brucknerstr. 36",
    "sg:city":"Berlin",
    "sg:phone":"+49 30/77190850",
    "sg:postcode":"12247",
    "sg:province":"Berlin",
    "wof:name":"Eberhard Goltz Ingenieur",
    "wof:placetype":"venue"
},
  "geometry": {"coordinates":[13.339532,52.440838],"type":"Point"}
}