{
  "type": "Feature",
  "properties": {
    "iso:country":"DE",
    "sg:address":"Dehnitzer Weg 4b",
    "sg:city":"Wurzen",
    "sg:phone":"+49 3425/813100",
    "sg:postcode":"04808",
    "sg:province":"Sachsen",
    "wof:name":"Sihag - S\u00e4chsische Industrieg\u00fcter Gmbh",
    "wof:placetype":"venue"
},
  "geometry": {"coordinates":[12.733679,51.362358],"type":"Point"}
}