{
  "type": "Feature",
  "properties": {
    "iso:country":"DE",
    "sg:address":"Br\u00fcckenstr. 41",
    "sg:city":"Rheine",
    "sg:phone":"+49 5975/92760",
    "sg:postcode":"48432",
    "sg:province":"Nordrhein-Westfalen",
    "wof:name":"Heinrich B\u00f6sker",
    "wof:placetype":"venue"
},
  "geometry": {"coordinates":[7.5187768936,52.2382850647],"type":"Point"}
}