{
  "type": "Feature",
  "properties": {
    "iso:country":"DE",
    "sg:address":"Gl\u00fcsinger Str. 20",
    "sg:city":"Seevetal",
    "sg:phone":"+49 40/7683388",
    "sg:postcode":"21217",
    "sg:province":"Niedersachsen",
    "wof:name":"Apotheke Im Seevetal",
    "wof:placetype":"venue"
},
  "geometry": {"coordinates":[10.021279,53.420322],"type":"Point"}
}