{
  "type": "Feature",
  "properties": {
    "iso:country":"DE",
    "sg:address":"Zaunk\u00f6nigstr.18",
    "sg:city":"Ottobrunn",
    "sg:phone":"+49 89/60806988",
    "sg:postcode":"85521",
    "sg:province":"Bayern",
    "wof:name":"Animationsjobs, Tom Beivers",
    "wof:placetype":"venue"
},
  "geometry": {"coordinates":[11.6653652191,48.0580596924],"type":"Point"}
}