{
  "type": "Feature",
  "properties": {
    "iso:country":"DE",
    "sg:address":"Talstr. 3",
    "sg:city":"Hohberg",
    "sg:phone":"+49 7808/583",
    "sg:postcode":"77749",
    "sg:province":"Baden-W\u00fcrttemberg",
    "wof:name":"Kath. Pfarramt St. Carolus",
    "wof:placetype":"venue"
},
  "geometry": {"coordinates":[7.9383168221,48.3992385864],"type":"Point"}
}