{
  "type": "Feature",
  "properties": {
    "iso:country":"DE",
    "sg:address":"Hauptstr. 16",
    "sg:city":"Strigleben",
    "sg:phone":"+49 38782/40271",
    "sg:postcode":"19348",
    "sg:province":"Brandenburg",
    "wof:name":"Monika Putbrese",
    "wof:placetype":"venue"
},
  "geometry": {"coordinates":[11.934705,53.152611],"type":"Point"}
}