{
  "type": "Feature",
  "properties": {
    "iso:country":"DE",
    "sg:address":"Borner Str. 49",
    "sg:city":"Br\u00fcggen",
    "sg:phone":"+49 2163/6067",
    "sg:postcode":"41379",
    "sg:province":"Nordrhein-Westfalen",
    "wof:name":"Klaus Wilms Rechtsanwalt",
    "wof:placetype":"venue"
},
  "geometry": {"coordinates":[6.189057827,51.2433242798],"type":"Point"}
}