{
  "type": "Feature",
  "properties": {
    "iso:country":"DE",
    "sg:address":"Dickerstr. 119a",
    "sg:city":"Dinslaken",
    "sg:phone":"+49 2064/93237",
    "sg:postcode":"46539",
    "sg:province":"Nordrhein-Westfalen",
    "wof:name":"Ulla Middendorf Steuerberaterin",
    "wof:placetype":"venue"
},
  "geometry": {"coordinates":[6.7789120674,51.5767211914],"type":"Point"}
}