{
  "type": "Feature",
  "properties": {
    "iso:country":"DE",
    "sg:address":"An der Kirche 15",
    "sg:city":"K\u00fcsten",
    "sg:phone":"+49 5841/3260",
    "sg:postcode":"29482",
    "sg:province":"Niedersachsen",
    "wof:name":"Ev. Pfarramt Meuchefitz-k\u00fcsten-krummasel",
    "wof:placetype":"venue"
},
  "geometry": {"coordinates":[11.0643253326,52.976234436],"type":"Point"}
}