{
  "type": "Feature",
  "properties": {
    "iso:country":"DE",
    "sg:address":"G\u00fcrzenicher Str. 3",
    "sg:city":"D\u00fcren",
    "sg:phone":"+49 2421/65920",
    "sg:postcode":"52355",
    "sg:province":"Nordrhein-Westfalen",
    "wof:name":"Hofer & Sohn Gmbh",
    "wof:placetype":"venue"
},
  "geometry": {"coordinates":[6.464171,50.790054],"type":"Point"}
}