{
  "type": "Feature",
  "properties": {
    "iso:country":"DE",
    "sg:address":"Brachvogelweg 25",
    "sg:city":"Oldenburg",
    "sg:phone":"+49 441/41463",
    "sg:postcode":"26133",
    "sg:province":"Niedersachsen",
    "wof:name":"Heinrich Diepenbrock Ingenieur",
    "wof:placetype":"venue"
},
  "geometry": {"coordinates":[8.2342767715,53.1199951172],"type":"Point"}
}