{
  "type": "Feature",
  "properties": {
    "iso:country":"DE",
    "sg:address":"Rathausstr. 38",
    "sg:city":"Burgstetten",
    "sg:phone":"+49 7191/61650",
    "sg:postcode":"71576",
    "sg:province":"Baden-W\u00fcrttemberg",
    "wof:name":"Richard Schwaderer",
    "wof:placetype":"venue"
},
  "geometry": {"coordinates":[9.3750572205,48.929271698],"type":"Point"}
}