{
  "type": "Feature",
  "properties": {
    "iso:country":"DE",
    "sg:address":"Mosenstr. 1",
    "sg:city":"Markneukirchen",
    "sg:phone":"+49 37422/2519",
    "sg:postcode":"08258",
    "sg:province":"Sachsen",
    "wof:name":"Bianka K\u00fcnzel",
    "wof:placetype":"venue"
},
  "geometry": {"coordinates":[12.3272638321,50.3140602112],"type":"Point"}
}