{
  "type": "Feature",
  "properties": {
    "iso:country":"DE",
    "sg:address":"Steinenberg",
    "sg:city":"Bad Waldsee",
    "sg:phone":"+49 7524/5757",
    "sg:postcode":"88339",
    "sg:province":"Baden-W\u00fcrttemberg",
    "wof:name":"Alfred Kremmler",
    "wof:placetype":"venue"
},
  "geometry": {"coordinates":[9.749383,47.94009],"type":"Point"}
}