{
  "type": "Feature",
  "properties": {
    "iso:country":"DE",
    "sg:address":"Haidenkofener Str 16",
    "sg:city":"Wallersdorf",
    "sg:phone":"+49 9933/902225",
    "sg:postcode":"94522",
    "sg:province":"Bayern",
    "wof:name":"Wms Wagner Gmbh",
    "wof:placetype":"venue"
},
  "geometry": {"coordinates":[12.7109508514,48.7397270203],"type":"Point"}
}