{
  "type": "Feature",
  "properties": {
    "iso:country":"DE",
    "sg:address":"Haigstr. 3",
    "sg:city":"Knetzgau",
    "sg:phone":"+49 9527/1790",
    "sg:postcode":"97478",
    "sg:province":"Bayern",
    "wof:name":"Roland Roth",
    "wof:placetype":"venue"
},
  "geometry": {"coordinates":[10.546811,49.994949],"type":"Point"}
}