{
  "type": "Feature",
  "properties": {
    "iso:country":"DE",
    "sg:address":"Am Berg 6",
    "sg:city":"Halfing",
    "sg:phone":"+49 8055/8712",
    "sg:postcode":"83128",
    "sg:province":"Bayern",
    "wof:name":"Franz Plenert",
    "wof:placetype":"venue"
},
  "geometry": {"coordinates":[12.283267,47.952091],"type":"Point"}
}