{
  "type": "Feature",
  "properties": {
    "iso:country":"DE",
    "sg:address":"S\u00fcderweg 10",
    "sg:city":"Lentf\u00f6hrden",
    "sg:phone":"+49 4192/4571",
    "sg:postcode":"24632",
    "sg:province":"Schleswig-Holstein",
    "wof:name":"Wentzien Und Pump",
    "wof:placetype":"venue"
},
  "geometry": {"coordinates":[9.886753,53.868214],"type":"Point"}
}