{
  "type": "Feature",
  "properties": {
    "iso:country":"DE",
    "sg:address":"Papeneschstr 6",
    "sg:city":"Steinfurt",
    "sg:phone":"+49 2552/93930",
    "sg:postcode":"48565",
    "sg:province":"Nordrhein-Westfalen",
    "wof:name":"Werbeagentur Manfred Willers",
    "wof:placetype":"venue"
},
  "geometry": {"coordinates":[7.4092,52.118046],"type":"Point"}
}