{
  "type": "Feature",
  "properties": {
    "iso:country":"DE",
    "sg:address":"Mittlerer Dallenbergweg 49",
    "sg:city":"W\u00fcrzburg",
    "sg:phone":"+49 931/887884",
    "sg:postcode":"97082",
    "sg:province":"Bayern",
    "wof:name":"Vereinsgastst\u00e4tte Kickers",
    "wof:placetype":"venue"
},
  "geometry": {"coordinates":[9.9315471649,49.7669754028],"type":"Point"}
}