{
  "type": "Feature",
  "properties": {
    "iso:country":"DE",
    "sg:address":"Gro\u00dfe Sankt Ilsenstr. 14",
    "sg:city":"Salzwedel",
    "sg:phone":"+49 3901/422310",
    "sg:postcode":"29410",
    "sg:province":"Sachsen-Anhalt",
    "wof:name":"Christian Ippig Rechtsanwalt",
    "wof:placetype":"venue"
},
  "geometry": {"coordinates":[11.1557016373,52.8510780334],"type":"Point"}
}