{
  "type": "Feature",
  "properties": {
    "iso:country":"DE",
    "sg:address":"Bismarckstr. 6",
    "sg:city":"Einbeck",
    "sg:phone":"+49 5561/2411",
    "sg:postcode":"37574",
    "sg:province":"Niedersachsen",
    "wof:name":"H. Beyer-ahrens Steuerberater",
    "wof:placetype":"venue"
},
  "geometry": {"coordinates":[9.868024826,51.8137702942],"type":"Point"}
}