{
  "type": "Feature",
  "properties": {
    "iso:country":"DE",
    "sg:address":"Im Oberdorf 20",
    "sg:city":"Lehre",
    "sg:phone":"+49 5309/99010",
    "sg:postcode":"38165",
    "sg:province":"Niedersachsen",
    "wof:name":"T. Scharner Gmbh",
    "wof:placetype":"venue"
},
  "geometry": {"coordinates":[10.6398715973,52.3162994385],"type":"Point"}
}