{
  "type": "Feature",
  "properties": {
    "iso:country":"DE",
    "sg:address":"Dieselstr. 3",
    "sg:city":"Ulm",
    "sg:phone":"+49 4973/140970",
    "sg:postcode":"89079",
    "sg:province":"Baden-W\u00fcrttemberg",
    "wof:name":"Uzin Utz Ag",
    "wof:placetype":"venue"
},
  "geometry": {"coordinates":[9.945536,48.360538],"type":"Point"}
}