{
  "type": "Feature",
  "properties": {
    "iso:country":"DE",
    "sg:address":"Nikolausstr. 36",
    "sg:city":"Trier",
    "sg:phone":"+49 651/75669",
    "sg:postcode":"54290",
    "sg:province":"Rheinland-Pfalz",
    "wof:name":"Heribert Heckmann",
    "wof:placetype":"venue"
},
  "geometry": {"coordinates":[6.632855,49.747135],"type":"Point"}
}