{
  "type": "Feature",
  "properties": {
    "iso:country":"DE",
    "sg:address":"Erlm\u00fchle 2",
    "sg:city":"Neumark",
    "sg:phone":"+49 37600/3454",
    "sg:postcode":"08496",
    "sg:province":"Sachsen",
    "wof:name":"Anita Langheinrich",
    "wof:placetype":"venue"
},
  "geometry": {"coordinates":[12.372335434,50.6698379517],"type":"Point"}
}