{
  "type": "Feature",
  "properties": {
    "iso:country":"DE",
    "sg:address":"Bernbacher Str. 16",
    "sg:city":"Bidingen",
    "sg:phone":"+49 8348/262",
    "sg:postcode":"87651",
    "sg:province":"Bayern",
    "wof:name":"F. Hutler",
    "wof:placetype":"venue"
},
  "geometry": {"coordinates":[10.7215662003,47.8300895691],"type":"Point"}
}