{
  "type": "Feature",
  "properties": {
    "iso:country":"DE",
    "sg:address":"Klever Str. 33",
    "sg:city":"D\u00fcsseldorf",
    "sg:phone":"+49 211/4910396",
    "sg:postcode":"40477",
    "sg:province":"Nordrhein-Westfalen",
    "wof:name":"Horst Ordenbach Architekt",
    "wof:placetype":"venue"
},
  "geometry": {"coordinates":[6.776242,51.240246],"type":"Point"}
}