{
  "type": "Feature",
  "properties": {
    "iso:country":"DE",
    "sg:address":"Stingstr. 26",
    "sg:city":"Balingen",
    "sg:phone":"+49 7433/22903",
    "sg:postcode":"72336",
    "sg:province":"Baden-W\u00fcrttemberg",
    "wof:name":"Rolf E. Br\u00fcckner Rechtsanwalt",
    "wof:placetype":"venue"
},
  "geometry": {"coordinates":[8.8552970886,48.2711334229],"type":"Point"}
}