{
  "type": "Feature",
  "properties": {
    "iso:country":"DE",
    "sg:address":"Altenbergerstr. 12",
    "sg:city":"K\u00f6ln",
    "sg:phone":"+49 180 3 8878875",
    "sg:postcode":"50668",
    "sg:province":"Nordrhein-Westfalen",
    "wof:name":"Forum Betriebskrankenkasse",
    "wof:placetype":"venue"
},
  "geometry": {"coordinates":[6.95899,50.944427],"type":"Point"}
}