{
  "type": "Feature",
  "properties": {
    "iso:country":"DE",
    "sg:address":"An Pater und Nonne 25",
    "sg:city":"Iserlohn",
    "sg:phone":"+49 2374/2184",
    "sg:postcode":"58642",
    "sg:province":"Nordrhein-Westfalen",
    "wof:name":"Christian Behle",
    "wof:placetype":"venue"
},
  "geometry": {"coordinates":[7.628449,51.364784],"type":"Point"}
}