{
  "type": "Feature",
  "properties": {
    "iso:country":"DE",
    "sg:address":"Mendener Str. 4",
    "sg:city":"Arnsberg",
    "sg:phone":"+49 2932/7788",
    "sg:postcode":"59755",
    "sg:province":"Nordrhein-Westfalen",
    "wof:name":"Karel Paassen",
    "wof:placetype":"venue"
},
  "geometry": {"coordinates":[7.9586,51.454342],"type":"Point"}
}