{
  "type": "Feature",
  "properties": {
    "iso:country":"DE",
    "sg:address":"Scheidertalstr. 34",
    "sg:city":"Taunusstein",
    "sg:phone":"+49 6128/23011",
    "sg:postcode":"65232",
    "sg:province":"Hessen",
    "wof:name":"Lothar Wibbing Ingenieur",
    "wof:placetype":"venue"
},
  "geometry": {"coordinates":[8.1547832489,50.1454238892],"type":"Point"}
}