{
  "type": "Feature",
  "properties": {
    "iso:country":"DE",
    "sg:address":"Lattenkamp 3",
    "sg:city":"Schleswig",
    "sg:postcode":"24837",
    "sg:province":"Schleswig-Holstein",
    "wof:name":"Aldi Gmbh & Co. Kg",
    "wof:placetype":"venue"
},
  "geometry": {"coordinates":[9.5295219421,54.5303153992],"type":"Point"}
}