{
  "type": "Feature",
  "properties": {
    "iso:country":"DE",
    "sg:address":"Kastanienstr 1",
    "sg:city":"Apen",
    "sg:phone":"+49 4489/935729",
    "sg:postcode":"26689",
    "sg:province":"Niedersachsen",
    "wof:name":"Ahk-preisbrecher Fahrzeugteile-versand Gro\u00df- Und Einzelhandel",
    "wof:placetype":"venue"
},
  "geometry": {"coordinates":[7.763885,53.221561],"type":"Point"}
}