{
  "type": "Feature",
  "properties": {
    "iso:country":"DE",
    "sg:address":"Wohlfahrtstr. 125",
    "sg:city":"Bochum",
    "sg:phone":"+49 234/977180",
    "sg:postcode":"44799",
    "sg:province":"Nordrhein-Westfalen",
    "wof:name":"Elmer Gmbh & Co.",
    "wof:placetype":"venue"
},
  "geometry": {"coordinates":[7.2237181664,51.4526405334],"type":"Point"}
}