{
  "type": "Feature",
  "properties": {
    "iso:country":"DE",
    "sg:address":"Wilhelm-K\u00fclz-Platz 10",
    "sg:city":"Chemnitz",
    "sg:phone":"+49 371/415806",
    "sg:postcode":"09113",
    "sg:province":"Sachsen",
    "wof:name":"Lukas-apotheke Brigitte M\u00fcller E. Kfr.",
    "wof:placetype":"venue"
},
  "geometry": {"coordinates":[12.929738,50.846336],"type":"Point"}
}