{
  "type": "Feature",
  "properties": {
    "iso:country":"DE",
    "sg:address":"Hauptstr. 27",
    "sg:city":"Pfullendorf",
    "sg:phone":"+49 7552/1479",
    "sg:postcode":"88630",
    "sg:province":"Baden-W\u00fcrttemberg",
    "wof:name":"A. Allgaier",
    "wof:placetype":"venue"
},
  "geometry": {"coordinates":[9.256346,47.924465],"type":"Point"}
}