{
  "type": "Feature",
  "properties": {
    "iso:country":"DE",
    "sg:address":"S\u00fcdliche Hauptstr. 12",
    "sg:city":"Rottach-Egern",
    "sg:phone":"+49 8022/6333",
    "sg:postcode":"83700",
    "sg:province":"Bayern",
    "wof:name":"Drachenflugschule Tegernseer Tal",
    "wof:placetype":"venue"
},
  "geometry": {"coordinates":[11.7695732117,47.6891441345],"type":"Point"}
}