{
  "type": "Feature",
  "properties": {
    "iso:country":"DE",
    "sg:address":"Mozartstra\u00dfe 19",
    "sg:city":"K\u00f6ln",
    "sg:phone":"+49 221/237787",
    "sg:postcode":"50674",
    "sg:province":"Nordrhein-Westfalen",
    "wof:name":"Edition Cologne - Konzeptagentur F\u00fcr Marketing & Verlag",
    "wof:placetype":"venue"
},
  "geometry": {"coordinates":[6.936877,50.932926],"type":"Point"}
}