{
  "type": "Feature",
  "properties": {
    "iso:country":"DE",
    "sg:address":"Friedrich-Ebert-Str. 7",
    "sg:city":"Flensburg",
    "sg:phone":"+49 461/141740",
    "sg:postcode":"24937",
    "sg:province":"Schleswig-Holstein",
    "wof:name":"Forward Productions Ton- Und Filmproductions",
    "wof:placetype":"venue"
},
  "geometry": {"coordinates":[9.4379653931,54.7810401917],"type":"Point"}
}