{
  "type": "Feature",
  "properties": {
    "iso:country":"DE",
    "sg:address":"Zuger Str 24",
    "sg:city":"Brand-Erbisdorf",
    "sg:phone":"+49 37322/3441",
    "sg:postcode":"09618",
    "sg:province":"Sachsen",
    "wof:name":"Tb Transportbeton Gmbh & Co Kg",
    "wof:placetype":"venue"
},
  "geometry": {"coordinates":[13.3260698318,50.8706016541],"type":"Point"}
}