{
  "type": "Feature",
  "properties": {
    "iso:country":"DE",
    "sg:address":"Berliner Str. 157",
    "sg:city":"Salzgitter",
    "sg:phone":"+49 5341/63180",
    "sg:postcode":"38226",
    "sg:province":"Niedersachsen",
    "wof:name":"Er-kan",
    "wof:placetype":"venue"
},
  "geometry": {"coordinates":[10.3354187012,52.1628189087],"type":"Point"}
}