{
  "type": "Feature",
  "properties": {
    "iso:country":"DE",
    "sg:address":"Rondorfer Str. 23-25",
    "sg:city":"H\u00fcrth",
    "sg:postcode":"50354",
    "sg:province":"Nordrhein-Westfalen",
    "wof:name":"Maschinenbau Hoffmann Gmbh",
    "wof:placetype":"venue"
},
  "geometry": {"coordinates":[6.906918,50.893188],"type":"Point"}
}