{
  "type": "Feature",
  "properties": {
    "iso:country":"DE",
    "sg:address":"Unterdorf 19",
    "sg:city":"B\u00fcttelborn",
    "sg:phone":"+49 6152/4460",
    "sg:postcode":"64572",
    "sg:province":"Hessen",
    "wof:name":"Ludwig Bausch",
    "wof:placetype":"venue"
},
  "geometry": {"coordinates":[8.5461750031,49.9286308289],"type":"Point"}
}