{
  "type": "Feature",
  "properties": {
    "iso:country":"DE",
    "sg:address":"Wilhelmsh\u00e4user Str. 105",
    "sg:city":"Hann. M\u00fcnden",
    "sg:phone":"+49 5541/12122",
    "sg:postcode":"34346",
    "sg:province":"Niedersachsen",
    "wof:name":"Honsel Mineral\u00f6lvertriebs Gmbh",
    "wof:placetype":"venue"
},
  "geometry": {"coordinates":[9.6395759583,51.405128479],"type":"Point"}
}