{
  "type": "Feature",
  "properties": {
    "iso:country":"DE",
    "sg:address":"Klausnerring 16",
    "sg:city":"Kirchheim",
    "sg:phone":"+49 89/9911901",
    "sg:postcode":"85551",
    "sg:province":"Bayern",
    "wof:name":"Multimon Industrieanlagen Gmbh",
    "wof:placetype":"venue"
},
  "geometry": {"coordinates":[11.743179,48.152359],"type":"Point"}
}