{
  "type": "Feature",
  "properties": {
    "iso:country":"DE",
    "sg:address":"Hauptstr. 1",
    "sg:city":"Hilbersdorf",
    "sg:phone":"+49 3731/34428",
    "sg:postcode":"09627",
    "sg:province":"Sachsen",
    "wof:name":"Matthies",
    "wof:placetype":"venue"
},
  "geometry": {"coordinates":[13.39022,50.91124],"type":"Point"}
}