{
  "type": "Feature",
  "properties": {
    "iso:country":"DE",
    "sg:address":"Z\u00f6llnerstr. 25",
    "sg:city":"Overath",
    "sg:phone":"+49 2204/73473",
    "sg:postcode":"51491",
    "sg:province":"Nordrhein-Westfalen",
    "wof:name":"K. H. Arand",
    "wof:placetype":"venue"
},
  "geometry": {"coordinates":[7.223965168,50.9486274719],"type":"Point"}
}