{
  "type": "Feature",
  "properties": {
    "iso:country":"DE",
    "sg:address":"Paracelsusstr. 56",
    "sg:city":"Leinfelden-Echterdingen",
    "sg:postcode":"70771",
    "sg:province":"Baden-W\u00fcrttemberg",
    "wof:name":"Naturleder Vertriebs-gmbh",
    "wof:placetype":"venue"
},
  "geometry": {"coordinates":[9.1134967804,48.7078933716],"type":"Point"}
}