{
  "type": "Feature",
  "properties": {
    "iso:country":"DE",
    "sg:address":"Krayer Str. 23",
    "sg:city":"Bochum",
    "sg:phone":"+49 2327/320372",
    "sg:postcode":"44866",
    "sg:province":"Nordrhein-Westfalen",
    "wof:name":"Leither Eck",
    "wof:placetype":"venue"
},
  "geometry": {"coordinates":[7.1094770432,51.4819641113],"type":"Point"}
}