{
  "type": "Feature",
  "properties": {
    "iso:country":"DE",
    "sg:address":"Rotk\u00e4ppchenweg 57",
    "sg:city":"Hattersheim",
    "sg:phone":"+49 6190/5672",
    "sg:postcode":"65795",
    "sg:province":"Hessen",
    "wof:name":"Strubel Arbeitssicherheit Gmbh",
    "wof:placetype":"venue"
},
  "geometry": {"coordinates":[8.485128,50.055901],"type":"Point"}
}