{
  "type": "Feature",
  "properties": {
    "iso:country":"DE",
    "sg:address":"Herrnstr. 10",
    "sg:city":"Neustadt",
    "sg:phone":"+49 9445/466",
    "sg:postcode":"93333",
    "sg:province":"Bayern",
    "wof:name":"Neukauf",
    "wof:placetype":"venue"
},
  "geometry": {"coordinates":[11.7414798737,48.8140411377],"type":"Point"}
}