{
  "type": "Feature",
  "properties": {
    "iso:country":"DE",
    "sg:address":"Erderstr. 10 a",
    "sg:city":"Hannover",
    "sg:phone":"+49 511/2109686",
    "sg:postcode":"30451",
    "sg:province":"Niedersachsen",
    "wof:name":"Symetrik Schuh- Und Lederwaren Gmbh",
    "wof:placetype":"venue"
},
  "geometry": {"coordinates":[9.7030363083,52.3762512207],"type":"Point"}
}