{
  "type": "Feature",
  "properties": {
    "iso:country":"DE",
    "sg:address":"Ringstr. 23",
    "sg:city":"Mauer",
    "sg:phone":"+49 6226/60547",
    "sg:postcode":"69256",
    "sg:province":"Baden-W\u00fcrttemberg",
    "wof:name":"Carolin Hoffmann",
    "wof:placetype":"venue"
},
  "geometry": {"coordinates":[8.7978696823,49.339050293],"type":"Point"}
}