{
  "type": "Feature",
  "properties": {
    "iso:country":"DE",
    "sg:address":"H\u00f6rwarthstr. 13",
    "sg:city":"M\u00fcnchen",
    "sg:phone":"+49 89/362183",
    "sg:postcode":"80804",
    "sg:province":"Bayern",
    "wof:name":"Albrecht Hengstenberg",
    "wof:placetype":"venue"
},
  "geometry": {"coordinates":[11.5840616226,48.1686477661],"type":"Point"}
}