{
  "type": "Feature",
  "properties": {
    "iso:country":"DE",
    "sg:address":"Reutlinger Str. 22-24",
    "sg:city":"Neuffen",
    "sg:postcode":"72639",
    "sg:province":"Baden-W\u00fcrttemberg",
    "wof:name":"Walo-bautr\u00e4ger Gmbh",
    "wof:placetype":"venue"
},
  "geometry": {"coordinates":[9.371687,48.555344],"type":"Point"}
}