{
  "type": "Feature",
  "properties": {
    "iso:country":"DE",
    "sg:address":"L\u00e4rchenweg 23",
    "sg:city":"D\u00fcsseldorf",
    "sg:phone":"+49 211/741063",
    "sg:postcode":"40599",
    "sg:province":"Nordrhein-Westfalen",
    "wof:name":"Rheinische Schule F\u00fcr Sehbehinderte",
    "wof:placetype":"venue"
},
  "geometry": {"coordinates":[6.877120018,51.1756095886],"type":"Point"}
}