{
  "type": "Feature",
  "properties": {
    "iso:country":"DE",
    "sg:address":"Konzerbr\u00fcck 31",
    "sg:city":"Konz",
    "sg:phone":"+49 6501/16984",
    "sg:postcode":"54329",
    "sg:province":"Rheinland-Pfalz",
    "wof:name":"Karl Peter Gmbh",
    "wof:placetype":"venue"
},
  "geometry": {"coordinates":[6.5658431053,49.6936225891],"type":"Point"}
}