{
  "type": "Feature",
  "properties": {
    "iso:country":"DE",
    "sg:city":"Odelzhausen",
    "sg:phone":"+49 8134/6410",
    "sg:postcode":"85235",
    "sg:province":"Bayern",
    "wof:name":"Volksbank Raiffeisenbank Dachau Eg",
    "wof:placetype":"venue"
},
  "geometry": {"coordinates":[11.199465,48.308781],"type":"Point"}
}