{
  "type": "Feature",
  "properties": {
    "iso:country":"DE",
    "sg:address":"Preysingplatz 18",
    "sg:city":"Plattling",
    "sg:phone":"+49 9931/2421",
    "sg:postcode":"94447",
    "sg:province":"Bayern",
    "wof:name":"Volksbank Straubing Eg",
    "wof:placetype":"venue"
},
  "geometry": {"coordinates":[12.872869,48.777542],"type":"Point"}
}