{
  "type": "Feature",
  "properties": {
    "iso:country":"DE",
    "sg:address":"Freiheit 23",
    "sg:city":"Gudensberg",
    "sg:phone":"+49 5603/2210",
    "sg:postcode":"34281",
    "sg:province":"Hessen",
    "wof:name":"W. Schmidt",
    "wof:placetype":"venue"
},
  "geometry": {"coordinates":[9.366393,51.179062],"type":"Point"}
}