{
  "type": "Feature",
  "properties": {
    "iso:country":"DE",
    "sg:address":"Gr\u00f6bziger Str. 4",
    "sg:city":"Gr\u00f6bzig",
    "sg:phone":"+49 34976/22271",
    "sg:postcode":"06388",
    "sg:province":"Sachsen-Anhalt",
    "wof:name":"Inge Sch\u00f6ne",
    "wof:placetype":"venue"
},
  "geometry": {"coordinates":[11.8919229507,51.6674118042],"type":"Point"}
}