{
  "type": "Feature",
  "properties": {
    "iso:country":"DE",
    "sg:address":"Am Lehmfeld 6",
    "sg:city":"Meppen",
    "sg:phone":"+49 5931/16141",
    "sg:postcode":"49716",
    "sg:province":"Niedersachsen",
    "wof:name":"Heinrich Knuck",
    "wof:placetype":"venue"
},
  "geometry": {"coordinates":[7.2759990692,52.6977119446],"type":"Point"}
}