{
  "type": "Feature",
  "properties": {
    "iso:country":"DE",
    "sg:address":"Oedter Str. 86",
    "sg:city":"T\u00f6nisvorst",
    "sg:phone":"+49 2156/7001",
    "sg:postcode":"47918",
    "sg:province":"Nordrhein-Westfalen",
    "wof:name":"Van De Sandt",
    "wof:placetype":"venue"
},
  "geometry": {"coordinates":[6.4102377892,51.305557251],"type":"Point"}
}