{
  "type": "Feature",
  "properties": {
    "iso:country":"DE",
    "sg:address":"Fuhrmanns Birken 11",
    "sg:city":"Celle",
    "sg:phone":"+49 5141/382722",
    "sg:postcode":"29223",
    "sg:province":"Niedersachsen",
    "wof:name":"K\u00fcchen Und Hausger\u00e4te Fischer & Micheel Gmbh",
    "wof:placetype":"venue"
},
  "geometry": {"coordinates":[10.1178398132,52.6344985962],"type":"Point"}
}