{
  "type": "Feature",
  "properties": {
    "iso:country":"DE",
    "sg:address":"Karlstal 14",
    "sg:city":"Kiel",
    "sg:phone":"+49 431/7399015",
    "sg:postcode":"24143",
    "sg:province":"Schleswig-Holstein",
    "wof:name":"Speedy Express Overnight Gmbh",
    "wof:placetype":"venue"
},
  "geometry": {"coordinates":[10.1411838531,54.3111038208],"type":"Point"}
}