{
  "type": "Feature",
  "properties": {
    "iso:country":"DE",
    "sg:address":"Schlo\u00dfberg 18",
    "sg:city":"Riedlingen",
    "sg:postcode":"88499",
    "sg:province":"Baden-W\u00fcrttemberg",
    "wof:name":"Espada E. K.",
    "wof:placetype":"venue"
},
  "geometry": {"coordinates":[9.4764652252,48.1264953613],"type":"Point"}
}