{
  "type": "Feature",
  "properties": {
    "iso:country":"DE",
    "sg:address":"Bahnhofstr. 51",
    "sg:city":"Tirschenreuth",
    "sg:phone":"+49 9631/800",
    "sg:postcode":"95643",
    "sg:province":"Bayern",
    "wof:name":"Hamm Ag",
    "wof:placetype":"venue"
},
  "geometry": {"coordinates":[12.327768,49.879631],"type":"Point"}
}