{
  "type": "Feature",
  "properties": {
    "iso:country":"DE",
    "sg:address":"H\u00e4genstr. 11",
    "sg:city":"Hannover",
    "sg:phone":"+49 511/584122",
    "sg:postcode":"30559",
    "sg:province":"Niedersachsen",
    "wof:name":"Tz-frischdienst F\u00fcr K\u00fchlprodukte Gmbh",
    "wof:placetype":"venue"
},
  "geometry": {"coordinates":[9.868975,52.36393],"type":"Point"}
}