{
  "type": "Feature",
  "properties": {
    "iso:country":"DE",
    "sg:address":"Mittelstr. 111",
    "sg:city":"Sankt Augustin",
    "sg:phone":"+49 2241/926750",
    "sg:postcode":"53757",
    "sg:province":"Nordrhein-Westfalen",
    "wof:name":"Wolfgang Hebler Rechtsanwalt",
    "wof:placetype":"venue"
},
  "geometry": {"coordinates":[7.1606998444,50.7861595154],"type":"Point"}
}