{
  "type": "Feature",
  "properties": {
    "iso:country":"DE",
    "sg:address":"Mertonstr. 17",
    "sg:city":"Frankfurt",
    "sg:phone":"+49 69/7983261",
    "sg:postcode":"60325",
    "sg:province":"Hessen",
    "wof:name":"Seminar F\u00fcr Logistik Und Verkehr",
    "wof:placetype":"venue"
},
  "geometry": {"coordinates":[8.652374,50.118107],"type":"Point"}
}