{
  "type": "Feature",
  "properties": {
    "iso:country":"DE",
    "sg:address":"Bussenstr 30",
    "sg:city":"D\u00fcrmentingen",
    "sg:phone":"+49 40/7004000",
    "sg:postcode":"88525",
    "sg:province":"Baden-W\u00fcrttemberg",
    "wof:name":"M\u00f6bel Meyn Gmbh",
    "wof:placetype":"venue"
},
  "geometry": {"coordinates":[9.786175,53.459682],"type":"Point"}
}