{
  "type": "Feature",
  "properties": {
    "iso:country":"DE",
    "sg:address":"Stegstr. 38",
    "sg:city":"Frankfurt",
    "sg:phone":"+49 69/625438",
    "sg:postcode":"60594",
    "sg:province":"Hessen",
    "wof:name":"Wilhelm M\u00fcller",
    "wof:placetype":"venue"
},
  "geometry": {"coordinates":[8.682748,50.104706],"type":"Point"}
}