{
  "type": "Feature",
  "properties": {
    "iso:country":"DE",
    "sg:address":"Allmendweg 11",
    "sg:city":"Waldshut-Tiengen",
    "sg:phone":"+49 7741/7538",
    "sg:postcode":"79761",
    "sg:province":"Baden-W\u00fcrttemberg",
    "wof:name":"Kleintierzuchtverein Tiengen Erich Keller",
    "wof:placetype":"venue"
},
  "geometry": {"coordinates":[8.2890462875,47.6358451843],"type":"Point"}
}