{
  "type": "Feature",
  "properties": {
    "iso:country":"DE",
    "sg:address":"Eich 1",
    "sg:city":"Wuppertal",
    "sg:postcode":"42349",
    "sg:province":"Nordrhein-Westfalen",
    "wof:name":"Boeckmann Verwaltungs Gmbh",
    "wof:placetype":"venue"
},
  "geometry": {"coordinates":[7.132237,51.203445],"type":"Point"}
}