{
  "type": "Feature",
  "properties": {
    "iso:country":"DE",
    "sg:address":"Jupiterstr. 13",
    "sg:city":"V\u00f6lklingen",
    "sg:phone":"+49 6898/25312",
    "sg:postcode":"66333",
    "sg:province":"Saarland",
    "wof:name":"C. Reif",
    "wof:placetype":"venue"
},
  "geometry": {"coordinates":[6.8658490181,49.2610282898],"type":"Point"}
}