{
  "type": "Feature",
  "properties": {
    "iso:country":"DE",
    "sg:address":"Gerberau 12",
    "sg:city":"Freiburg",
    "sg:phone":"+49 761/286608",
    "sg:postcode":"79098",
    "sg:province":"Baden-W\u00fcrttemberg",
    "wof:name":"Kie\u00dfling",
    "wof:placetype":"venue"
},
  "geometry": {"coordinates":[7.849676,47.99329],"type":"Point"}
}