{
  "type": "Feature",
  "properties": {
    "iso:country":"DE",
    "sg:address":"Colmarer Str. 11",
    "sg:city":"Weil am Rhein",
    "sg:phone":"+49 7621/79010",
    "sg:postcode":"79576",
    "sg:province":"Baden-W\u00fcrttemberg",
    "wof:name":"Fr\u00f6de Gmbh & Cie. Kg",
    "wof:placetype":"venue"
},
  "geometry": {"coordinates":[7.596598,47.596947],"type":"Point"}
}