{
  "type": "Feature",
  "properties": {
    "iso:country":"DE",
    "sg:address":"Carl-Zeiss-Str. 12",
    "sg:city":"Beckum",
    "sg:phone":"+49 2525/670",
    "sg:postcode":"59269",
    "sg:province":"Nordrhein-Westfalen",
    "wof:name":"R\u00f6tering & Kragelund Gmbh",
    "wof:placetype":"venue"
},
  "geometry": {"coordinates":[8.0048694611,51.7983016968],"type":"Point"}
}