{
  "type": "Feature",
  "properties": {
    "iso:country":"DE",
    "sg:address":"Wilflingstr 27",
    "sg:city":"Oberreichenbach",
    "sg:phone":"+49 7053/91096",
    "sg:postcode":"75394",
    "sg:province":"Baden-W\u00fcrttemberg",
    "wof:name":"Beckmann Etui Inh. Dirk Beckmann",
    "wof:placetype":"venue"
},
  "geometry": {"coordinates":[8.628235,48.723225],"type":"Point"}
}