{
  "type": "Feature",
  "properties": {
    "iso:country":"DE",
    "sg:address":"Tr\u00e4nkestr.",
    "sg:city":"Dahme",
    "sg:phone":"+49 35451/346",
    "sg:postcode":"15936",
    "sg:province":"Brandenburg",
    "wof:name":"B. Krause",
    "wof:placetype":"venue"
},
  "geometry": {"coordinates":[13.423198,51.867977],"type":"Point"}
}