{
  "type": "Feature",
  "properties": {
    "iso:country":"DE",
    "sg:address":"Am Kl\u00f6terbusch 5",
    "sg:city":"Buxtehude",
    "sg:phone":"+49 4161/84340",
    "sg:postcode":"21614",
    "sg:province":"Niedersachsen",
    "wof:name":"Gerhard Reimer",
    "wof:placetype":"venue"
},
  "geometry": {"coordinates":[9.6757249832,53.4593353271],"type":"Point"}
}