{
  "type": "Feature",
  "properties": {
    "iso:country":"DE",
    "sg:address":"Hopfauer Str.",
    "sg:city":"Sulz",
    "sg:phone":"+49 7454/4104",
    "sg:postcode":"72172",
    "sg:province":"Baden-W\u00fcrttemberg",
    "wof:name":"Vereinsgastst\u00e4tte Vereinsheim Sv-tc Hopfau",
    "wof:placetype":"venue"
},
  "geometry": {"coordinates":[8.5813684464,48.3839645386],"type":"Point"}
}