{
  "type": "Feature",
  "properties": {
    "iso:country":"DE",
    "sg:address":"Freyung 12",
    "sg:city":"Pfreimd",
    "sg:phone":"+49 9606/92060",
    "sg:postcode":"92536",
    "sg:province":"Bayern",
    "wof:name":"St. Barbara-apotheke",
    "wof:placetype":"venue"
},
  "geometry": {"coordinates":[12.182949,49.494236],"type":"Point"}
}