{
  "type": "Feature",
  "properties": {
    "iso:country":"DE",
    "sg:address":"Seestr. 14",
    "sg:city":"Radolfzell",
    "sg:phone":"+49 7732/971370",
    "sg:postcode":"78315",
    "sg:province":"Baden-W\u00fcrttemberg",
    "wof:name":"M. Eck Architekt",
    "wof:placetype":"venue"
},
  "geometry": {"coordinates":[8.970185,47.736801],"type":"Point"}
}