{
  "type": "Feature",
  "properties": {
    "iso:country":"DE",
    "sg:address":"In den Klippen 5",
    "sg:city":"Rinteln",
    "sg:phone":"+49 5152/3772",
    "sg:postcode":"31737",
    "sg:province":"Niedersachsen",
    "wof:name":"Pension K. Fauth",
    "wof:placetype":"venue"
},
  "geometry": {"coordinates":[9.1992292404,52.2041740417],"type":"Point"}
}