{
  "type": "Feature",
  "properties": {
    "iso:country":"DE",
    "sg:address":"Kirchenweg 6",
    "sg:city":"Rohrbach",
    "sg:phone":"+49 8442/8877",
    "sg:postcode":"85296",
    "sg:province":"Bayern",
    "wof:name":"Fritz Vachal",
    "wof:placetype":"venue"
},
  "geometry": {"coordinates":[11.560881,48.613289],"type":"Point"}
}