{
  "type": "Feature",
  "properties": {
    "iso:country":"DE",
    "sg:address":"Neutorstr. 11",
    "sg:city":"Breisach",
    "sg:phone":"+49 7667/1879",
    "sg:postcode":"79206",
    "sg:province":"Baden-W\u00fcrttemberg",
    "wof:name":"Radana J. Welz",
    "wof:placetype":"venue"
},
  "geometry": {"coordinates":[7.587197,48.026936],"type":"Point"}
}