{
  "type": "Feature",
  "properties": {
    "iso:country":"DE",
    "sg:address":"Langholter Str. 27",
    "sg:city":"Ostrhauderfehn",
    "sg:phone":"+49 4952/5689",
    "sg:postcode":"26842",
    "sg:province":"Niedersachsen",
    "wof:name":"Gerhard Berghaus Gmbh",
    "wof:placetype":"venue"
},
  "geometry": {"coordinates":[7.608798,53.113716],"type":"Point"}
}