{
  "type": "Feature",
  "properties": {
    "iso:country":"DE",
    "sg:address":"Werler Str. 20",
    "sg:city":"Arnsberg",
    "sg:phone":"+49 2932/24235",
    "sg:postcode":"59755",
    "sg:province":"Nordrhein-Westfalen",
    "wof:name":"Ralf B\u00fchner",
    "wof:placetype":"venue"
},
  "geometry": {"coordinates":[7.9617161751,51.4572715759],"type":"Point"}
}