{
  "type": "Feature",
  "properties": {
    "iso:country":"DE",
    "sg:address":"Rudolf-Diesel-Str. 1",
    "sg:city":"Hattorf",
    "sg:phone":"+49 5584/2701",
    "sg:postcode":"37197",
    "sg:province":"Niedersachsen",
    "wof:name":"Kara-grafische Systeme Gmbh",
    "wof:placetype":"venue"
},
  "geometry": {"coordinates":[10.243641,51.641235],"type":"Point"}
}