{
  "type": "Feature",
  "properties": {
    "iso:country":"DE",
    "sg:address":"Alsbacher Str. 15",
    "sg:city":"Zwingenberg",
    "sg:phone":"+49 6251/75948",
    "sg:postcode":"64673",
    "sg:province":"Hessen",
    "wof:name":"Ludwig M\u00e4rz",
    "wof:placetype":"venue"
},
  "geometry": {"coordinates":[8.6131057739,49.7268981934],"type":"Point"}
}