{
  "type": "Feature",
  "properties": {
    "iso:country":"DE",
    "sg:address":"Zur Alten F\u00e4hre 3",
    "sg:city":"Essen",
    "sg:phone":"+49 2054/3742",
    "sg:postcode":"45219",
    "sg:province":"Nordrhein-Westfalen",
    "wof:name":"Klaus Sch\u00e4fer",
    "wof:placetype":"venue"
},
  "geometry": {"coordinates":[6.934359,51.358952],"type":"Point"}
}