{
  "type": "Feature",
  "properties": {
    "iso:country":"DE",
    "sg:address":"Marktstr. 11",
    "sg:city":"Arnstein",
    "sg:phone":"+49 9363/6200",
    "sg:postcode":"97450",
    "sg:province":"Bayern",
    "wof:name":"Oswald Sch\u00f6nen Rechtsanwalt",
    "wof:placetype":"venue"
},
  "geometry": {"coordinates":[9.9687900543,49.9785079956],"type":"Point"}
}