{
  "type": "Feature",
  "properties": {
    "iso:country":"DE",
    "sg:address":"Hauptstr. 126",
    "sg:city":"Dietzhausen",
    "sg:postcode":"98530",
    "sg:province":"Th\u00fcringen",
    "wof:name":"Erich Nonn",
    "wof:placetype":"venue"
},
  "geometry": {"coordinates":[10.61129,50.600979],"type":"Point"}
}