{
  "type": "Feature",
  "properties": {
    "iso:country":"DE",
    "sg:address":"Detmolder Str. 17",
    "sg:city":"Bielefeld",
    "sg:phone":"+49 521/63033",
    "sg:postcode":"33604",
    "sg:province":"Nordrhein-Westfalen",
    "wof:name":"Hans-g. Speckenbach Architekt",
    "wof:placetype":"venue"
},
  "geometry": {"coordinates":[8.53952,52.010719],"type":"Point"}
}