{
  "type": "Feature",
  "properties": {
    "iso:country":"DE",
    "sg:address":"Moselufer 11",
    "sg:city":"\u00dcrzig",
    "sg:phone":"+49 6532/2433",
    "sg:postcode":"54539",
    "sg:province":"Rheinland-Pfalz",
    "wof:name":"Ruth Berres",
    "wof:placetype":"venue"
},
  "geometry": {"coordinates":[7.0039668083,49.9772491455],"type":"Point"}
}