{
  "type": "Feature",
  "properties": {
    "iso:country":"DE",
    "sg:address":"Kaiserswerther Str. 140",
    "sg:city":"D\u00fcsseldorf",
    "sg:phone":"+49 211/453230",
    "sg:postcode":"40474",
    "sg:province":"Nordrhein-Westfalen",
    "wof:name":"Peter Lochmann",
    "wof:placetype":"venue"
},
  "geometry": {"coordinates":[6.7699151039,51.2447624207],"type":"Point"}
}