{
  "type": "Feature",
  "properties": {
    "iso:country":"DE",
    "sg:address":"Saalfelder Str. 9a",
    "sg:city":"Leipzig",
    "sg:phone":"+49 341/4772056",
    "sg:postcode":"04179",
    "sg:province":"Sachsen",
    "wof:name":"Birgit Schmidt",
    "wof:placetype":"venue"
},
  "geometry": {"coordinates":[12.319560051,51.3304519653],"type":"Point"}
}