{
  "type": "Feature",
  "properties": {
    "iso:country":"DE",
    "sg:address":"Friedenstr. 82",
    "sg:city":"Gladbeck",
    "sg:phone":"+49 2043/22219",
    "sg:postcode":"45964",
    "sg:province":"Nordrhein-Westfalen",
    "wof:name":"Hlk Heizungs- L\u00fcftungs- Und Klimatechnik Gmbh",
    "wof:placetype":"venue"
},
  "geometry": {"coordinates":[6.9767432213,51.5723762512],"type":"Point"}
}