{
  "type": "Feature",
  "properties": {
    "iso:country":"DE",
    "sg:address":"Bahnhofstr. 30",
    "sg:city":"Wolfsburg",
    "sg:phone":"+49 5362/66230",
    "sg:postcode":"38442",
    "sg:province":"Niedersachsen",
    "wof:name":"Zimberg Optik",
    "wof:placetype":"venue"
},
  "geometry": {"coordinates":[10.716686,52.420601],"type":"Point"}
}