{
  "type": "Feature",
  "properties": {
    "iso:country":"DE",
    "sg:address":"Struthstr. 2",
    "sg:city":"Aura",
    "sg:phone":"+49 9356/5330",
    "sg:postcode":"97773",
    "sg:province":"Bayern",
    "wof:name":"F. Kreuzer",
    "wof:placetype":"venue"
},
  "geometry": {"coordinates":[9.5745649338,50.1737556458],"type":"Point"}
}