{
  "type": "Feature",
  "properties": {
    "iso:country":"DE",
    "sg:address":"Leineweberstr. 16",
    "sg:city":"Algermissen",
    "sg:phone":"+49 5126/474",
    "sg:postcode":"31191",
    "sg:province":"Niedersachsen",
    "wof:name":"Gastst\u00e4tte Otto Schm\u00fccker",
    "wof:placetype":"venue"
},
  "geometry": {"coordinates":[10.0120649338,52.2699661255],"type":"Point"}
}