{
  "type": "Feature",
  "properties": {
    "iso:country":"DE",
    "sg:address":"Bahnweg 10",
    "sg:city":"Mainz",
    "sg:phone":"+49 6131/957871",
    "sg:postcode":"55129",
    "sg:province":"Rheinland-Pfalz",
    "wof:name":"I. Schwinn-hammann",
    "wof:placetype":"venue"
},
  "geometry": {"coordinates":[8.2790107727,49.9648017883],"type":"Point"}
}