{
  "type": "Feature",
  "properties": {
    "iso:country":"DE",
    "sg:address":"Altenburger Str. 11",
    "sg:city":"Borna",
    "sg:phone":"+49 3433/203011",
    "sg:postcode":"04552",
    "sg:province":"Sachsen",
    "wof:name":"I. N\u00f6bel",
    "wof:placetype":"venue"
},
  "geometry": {"coordinates":[12.494186,51.1203],"type":"Point"}
}