{
  "type": "Feature",
  "properties": {
    "iso:country":"DE",
    "sg:address":"Mayener Str. 54",
    "sg:city":"Kehrig",
    "sg:phone":"+49 2651/72102",
    "sg:postcode":"56729",
    "sg:province":"Rheinland-Pfalz",
    "wof:name":"Johannes Schneider",
    "wof:placetype":"venue"
},
  "geometry": {"coordinates":[7.22276,50.284069],"type":"Point"}
}