{
  "type": "Feature",
  "properties": {
    "iso:country":"DE",
    "sg:address":"Kiefernweg 6",
    "sg:city":"Waldkirch",
    "sg:phone":"+49 7681/6610",
    "sg:postcode":"79183",
    "sg:province":"Baden-W\u00fcrttemberg",
    "wof:name":"Reinhard Kind",
    "wof:placetype":"venue"
},
  "geometry": {"coordinates":[7.9609088898,48.1087684631],"type":"Point"}
}