{
  "type": "Feature",
  "properties": {
    "iso:country":"DE",
    "sg:address":"Sepp-Heindl-Str 1",
    "sg:city":"Rosenheim",
    "sg:phone":"+49 8031/23970",
    "sg:postcode":"83026",
    "sg:province":"Bayern",
    "wof:name":"Drexler Gmbh",
    "wof:placetype":"venue"
},
  "geometry": {"coordinates":[12.083,47.843636],"type":"Point"}
}