{
  "type": "Feature",
  "properties": {
    "iso:country":"DE",
    "sg:address":"Kremmlerstr. 57",
    "sg:city":"Stuttgart",
    "sg:phone":"+49 711/7655819",
    "sg:postcode":"70597",
    "sg:province":"Baden-W\u00fcrttemberg",
    "wof:name":"Peter Kn\u00f6pfler Architekt",
    "wof:placetype":"venue"
},
  "geometry": {"coordinates":[9.145477,48.738853],"type":"Point"}
}