{
  "type": "Feature",
  "properties": {
    "iso:country":"DE",
    "sg:address":"Tessiner Str. 148",
    "sg:city":"M\u00fcnchen",
    "sg:phone":"+49 89/7459266",
    "sg:postcode":"81475",
    "sg:province":"Bayern",
    "wof:name":"M. Ortler Steuerberater",
    "wof:placetype":"venue"
},
  "geometry": {"coordinates":[11.4777708054,48.0920219421],"type":"Point"}
}