{
  "type": "Feature",
  "properties": {
    "iso:country":"DE",
    "sg:address":"Frankenstr. 7",
    "sg:city":"Giebelstadt",
    "sg:postcode":"97232",
    "sg:province":"Bayern",
    "wof:name":"Protomic Promotion Schopf & Gebhardt Gbr",
    "wof:placetype":"venue"
},
  "geometry": {"coordinates":[9.9423904419,49.6539726257],"type":"Point"}
}