{
  "type": "Feature",
  "properties": {
    "iso:country":"DE",
    "sg:address":"Markt 39",
    "sg:city":"Marktredwitz",
    "sg:phone":"+49 9231/2786",
    "sg:postcode":"95615",
    "sg:province":"Bayern",
    "wof:name":"Heinrich Meier",
    "wof:placetype":"venue"
},
  "geometry": {"coordinates":[12.086155,50.001137],"type":"Point"}
}