{
  "type": "Feature",
  "properties": {
    "iso:country":"DE",
    "sg:address":"Kemnather Str. 15",
    "sg:city":"Pressath",
    "sg:phone":"+49 9644/519",
    "sg:postcode":"92690",
    "sg:province":"Bayern",
    "wof:name":"A. Und M. Frimberger Heissmangel",
    "wof:placetype":"venue"
},
  "geometry": {"coordinates":[11.9304828644,49.7717704773],"type":"Point"}
}