{
  "type": "Feature",
  "properties": {
    "iso:country":"DE",
    "sg:address":"Dieselstr. 13",
    "sg:city":"Pulheim",
    "sg:phone":"+49 2238/965010",
    "sg:postcode":"50259",
    "sg:province":"Nordrhein-Westfalen",
    "wof:name":"Wmb Weber-mitarbeiter Beteiligungs Gmbh",
    "wof:placetype":"venue"
},
  "geometry": {"coordinates":[6.821858,50.988251],"type":"Point"}
}