{
  "type": "Feature",
  "properties": {
    "iso:country":"DE",
    "sg:address":"Stiller Gasse 20",
    "sg:city":"Schmalkalden",
    "sg:phone":"+49 3683/403493",
    "sg:postcode":"98574",
    "sg:province":"Th\u00fcringen",
    "wof:name":"Ernst Bamberger Inh. Christa Leyh",
    "wof:placetype":"venue"
},
  "geometry": {"coordinates":[10.454120636,50.7208442688],"type":"Point"}
}