{
  "type": "Feature",
  "properties": {
    "iso:country":"DE",
    "sg:address":"L\u00e4rchenweg 20",
    "sg:city":"Bad Nauheim",
    "sg:phone":"+49 6032/920010",
    "sg:postcode":"61231",
    "sg:province":"Hessen",
    "wof:name":"Procure Invest-beratung Ges. F. Private Verm\u00f6gens- Und",
    "wof:placetype":"venue"
},
  "geometry": {"coordinates":[8.7214050293,50.3527832031],"type":"Point"}
}