{
  "type": "Feature",
  "properties": {
    "iso:country":"DE",
    "sg:address":"Wald-Michelbacher-Str. 2",
    "sg:city":"Hirschhorn",
    "sg:phone":"+49 6272/93080",
    "sg:postcode":"69434",
    "sg:province":"Baden-W\u00fcrttemberg",
    "wof:name":"Hans Mayr Gmbh & Co. Kg",
    "wof:placetype":"venue"
},
  "geometry": {"coordinates":[8.8533735275,49.4699211121],"type":"Point"}
}