{
  "type": "Feature",
  "properties": {
    "iso:country":"DE",
    "sg:address":"M\u00fchlenkamp 43",
    "sg:city":"Hamburg",
    "sg:phone":"+49 40/274019",
    "sg:postcode":"22303",
    "sg:province":"Hamburg",
    "wof:name":"Gerhart Ende Rechtsanwalt",
    "wof:placetype":"venue"
},
  "geometry": {"coordinates":[10.0106143951,53.5823326111],"type":"Point"}
}