{
  "type": "Feature",
  "properties": {
    "iso:country":"DE",
    "sg:address":"Kronenstr. 43",
    "sg:city":"Ensdorf",
    "sg:phone":"+49 6831/53718",
    "sg:postcode":"66806",
    "sg:province":"Saarland",
    "wof:name":"Mathias Jacob",
    "wof:placetype":"venue"
},
  "geometry": {"coordinates":[6.784827,49.308987],"type":"Point"}
}