{
  "type": "Feature",
  "properties": {
    "iso:country":"DE",
    "sg:address":"Bahnhofstr. 12",
    "sg:city":"Wienhausen",
    "sg:phone":"+49 5149/8091",
    "sg:postcode":"29342",
    "sg:province":"Niedersachsen",
    "wof:name":"Rainer Backhausen",
    "wof:placetype":"venue"
},
  "geometry": {"coordinates":[10.185241,52.577194],"type":"Point"}
}