{
  "type": "Feature",
  "properties": {
    "iso:country":"DE",
    "sg:address":"Kampstr. 15",
    "sg:city":"Iserlohn",
    "sg:phone":"+49 2374/4134",
    "sg:postcode":"58644",
    "sg:province":"Nordrhein-Westfalen",
    "wof:name":"Marion Schmidt",
    "wof:placetype":"venue"
},
  "geometry": {"coordinates":[7.640681,51.371967],"type":"Point"}
}