{
  "type": "Feature",
  "properties": {
    "iso:country":"DE",
    "sg:address":"Lintforter Str. 17",
    "sg:city":"Moers",
    "sg:phone":"+49 2841/72096",
    "sg:postcode":"47445",
    "sg:province":"Nordrhein-Westfalen",
    "wof:name":"I. Marbach",
    "wof:placetype":"venue"
},
  "geometry": {"coordinates":[6.590239,51.489506],"type":"Point"}
}