{
  "type": "Feature",
  "properties": {
    "iso:country":"DE",
    "sg:address":"Lindenstr. 1-3",
    "sg:city":"Kleve",
    "sg:postcode":"47533",
    "sg:province":"Nordrhein-Westfalen",
    "wof:name":"Scandic Gmbh",
    "wof:placetype":"venue"
},
  "geometry": {"coordinates":[6.1519160271,51.795173645],"type":"Point"}
}