{
  "type": "Feature",
  "properties": {
    "iso:country":"DE",
    "sg:city":"Schwarzenbruck",
    "sg:postcode":"90592",
    "sg:province":"Bayern",
    "wof:name":"Rh Deponie Konsor- Tialgesellschaft Mbh",
    "wof:placetype":"venue"
},
  "geometry": {"coordinates":[11.250372,49.360847],"type":"Point"}
}