{
  "type": "Feature",
  "properties": {
    "iso:country":"DE",
    "sg:address":"Alleestr. 39",
    "sg:city":"Riesa",
    "sg:phone":"+49 3525/734675",
    "sg:postcode":"01591",
    "sg:province":"Sachsen",
    "wof:name":"Herbert K\u00e4mmerer & S\u00f6hne Gmbh",
    "wof:placetype":"venue"
},
  "geometry": {"coordinates":[13.2700071335,51.3207435608],"type":"Point"}
}