{
  "type": "Feature",
  "properties": {
    "iso:country":"DE",
    "sg:address":"Westergasse 16",
    "sg:city":"Winterbach",
    "sg:phone":"+49 7181/74444",
    "sg:postcode":"73650",
    "sg:province":"Baden-W\u00fcrttemberg",
    "wof:name":"Werner Mertz",
    "wof:placetype":"venue"
},
  "geometry": {"coordinates":[9.4780550003,48.7993736267],"type":"Point"}
}