{
  "type": "Feature",
  "properties": {
    "iso:country":"DE",
    "sg:address":"August-Bebel-Str. 2",
    "sg:city":"Schollene",
    "sg:phone":"+49 39389/41128",
    "sg:postcode":"14715",
    "sg:province":"Brandenburg",
    "wof:name":"Birgit Prause",
    "wof:placetype":"venue"
},
  "geometry": {"coordinates":[-78.1518707275,42.0723609924],"type":"Point"}
}