{
  "type": "Feature",
  "properties": {
    "iso:country":"DE",
    "sg:address":"\u00c4u\u00dfere Leutkircher Str. 5",
    "sg:city":"Altusried",
    "sg:phone":"+49 8373/392",
    "sg:postcode":"87452",
    "sg:province":"Bayern",
    "wof:name":"Gebhard Kiechle",
    "wof:placetype":"venue"
},
  "geometry": {"coordinates":[10.206365,47.807056],"type":"Point"}
}