{
  "type": "Feature",
  "properties": {
    "iso:country":"DE",
    "sg:address":"Kritenbarg 18",
    "sg:city":"Hamburg",
    "sg:phone":"+49 40/5366178",
    "sg:postcode":"22391",
    "sg:province":"Hamburg",
    "wof:name":"Hans Georg Beike Gmbh",
    "wof:placetype":"venue"
},
  "geometry": {"coordinates":[10.0884065628,53.6532554626],"type":"Point"}
}