{
  "type": "Feature",
  "properties": {
    "iso:country":"DE",
    "sg:address":"Ritterstr. 27",
    "sg:city":"K\u00f6ln",
    "sg:phone":"+49 221/1390853",
    "sg:postcode":"50668",
    "sg:province":"Nordrhein-Westfalen",
    "wof:name":"Rittersch\u00e4nke",
    "wof:placetype":"venue"
},
  "geometry": {"coordinates":[6.9520139694,50.9471626282],"type":"Point"}
}