{
  "type": "Feature",
  "properties": {
    "iso:country":"DE",
    "sg:address":"Hofmannstr. 11",
    "sg:city":"Wetzlar",
    "sg:phone":"+49 6441/25991",
    "sg:postcode":"35580",
    "sg:province":"Hessen",
    "wof:name":"Hofmann",
    "wof:placetype":"venue"
},
  "geometry": {"coordinates":[8.4923086166,50.5319671631],"type":"Point"}
}