{
  "type": "Feature",
  "properties": {
    "iso:country":"DE",
    "sg:address":"Bodenheimer Str.12",
    "sg:city":"Mainz",
    "sg:phone":"+49 6131/999927",
    "sg:postcode":"55129",
    "sg:province":"Rheinland-Pfalz",
    "wof:name":"Abtauchen Bei Der Padi Tauchschule Tauchertreff Mz",
    "wof:placetype":"venue"
},
  "geometry": {"coordinates":[8.285651,49.969669],"type":"Point"}
}