{
  "type": "Feature",
  "properties": {
    "iso:country":"DE",
    "sg:address":"Georg-Benjamin-Str. 35",
    "sg:city":"Berlin",
    "sg:postcode":"13125",
    "sg:province":"Berlin",
    "wof:name":"Dr. Med. Martina Behlke",
    "wof:placetype":"venue"
},
  "geometry": {"coordinates":[13.501804,52.628704],"type":"Point"}
}