{
  "type": "Feature",
  "properties": {
    "iso:country":"DE",
    "sg:address":"Waagestr. 13",
    "sg:city":"Osterode",
    "sg:phone":"+49 5522/5164",
    "sg:postcode":"37520",
    "sg:province":"Niedersachsen",
    "wof:name":"A. Becker",
    "wof:placetype":"venue"
},
  "geometry": {"coordinates":[10.252504,51.726871],"type":"Point"}
}