{
  "type": "Feature",
  "properties": {
    "iso:country":"DE",
    "sg:address":"Fritz-Fritzsche-Str. 13",
    "sg:city":"Chemnitz",
    "sg:phone":"+49 371/2600145",
    "sg:postcode":"09123",
    "sg:province":"Sachsen",
    "wof:name":"D. Wiedensee",
    "wof:placetype":"venue"
},
  "geometry": {"coordinates":[12.891005,50.786709],"type":"Point"}
}