{
  "type": "Feature",
  "properties": {
    "iso:country":"DE",
    "sg:address":"Hauptstr. 27",
    "sg:city":"Heitersheim",
    "sg:phone":"+49 7634/2216",
    "sg:postcode":"79423",
    "sg:province":"Baden-W\u00fcrttemberg",
    "wof:name":"Bernhard Gramelspacher",
    "wof:placetype":"venue"
},
  "geometry": {"coordinates":[7.6645140648,47.8720359802],"type":"Point"}
}