{
  "type": "Feature",
  "properties": {
    "iso:country":"DE",
    "sg:address":"Moerser Str. 244",
    "sg:city":"Kamp-Lintfort",
    "sg:phone":"+49 2842/2169",
    "sg:postcode":"47475",
    "sg:province":"Nordrhein-Westfalen",
    "wof:name":"Muysers Kg",
    "wof:placetype":"venue"
},
  "geometry": {"coordinates":[6.5471510887,51.5020141602],"type":"Point"}
}