{
  "type": "Feature",
  "properties": {
    "iso:country":"DE",
    "sg:address":"Reinbeker Redder 28",
    "sg:city":"Hamburg",
    "sg:phone":"+49 40/6956266",
    "sg:postcode":"21031",
    "sg:province":"Hamburg",
    "wof:name":"Walter-d. K\u00f6llner",
    "wof:placetype":"venue"
},
  "geometry": {"coordinates":[10.1733798981,53.5130348206],"type":"Point"}
}