{
  "type": "Feature",
  "properties": {
    "iso:country":"DE",
    "sg:address":"Ludwigshafener Str. 2",
    "sg:city":"Mutterstadt",
    "sg:postcode":"67112",
    "sg:province":"Rheinland-Pfalz",
    "wof:name":"Ligutex Ohg",
    "wof:placetype":"venue"
},
  "geometry": {"coordinates":[8.3551673889,49.4423599243],"type":"Point"}
}