{
  "type": "Feature",
  "properties": {
    "iso:country":"DE",
    "sg:address":"Asternweg 1",
    "sg:city":"Hemsb\u00fcnde",
    "sg:phone":"+49 4266/1316",
    "sg:postcode":"27386",
    "sg:province":"Niedersachsen",
    "wof:name":"Klaus Schwiebert",
    "wof:placetype":"venue"
},
  "geometry": {"coordinates":[9.474933,53.089386],"type":"Point"}
}