{
  "type": "Feature",
  "properties": {
    "iso:country":"DE",
    "sg:address":"Carl-Benz-Str. 8",
    "sg:city":"Schwetzingen",
    "sg:phone":"+49 6202/12224",
    "sg:postcode":"68723",
    "sg:province":"Baden-W\u00fcrttemberg",
    "wof:name":"Wolfgang Sch\u00e4fer",
    "wof:placetype":"venue"
},
  "geometry": {"coordinates":[8.584893,49.376457],"type":"Point"}
}