{
  "type": "Feature",
  "properties": {
    "iso:country":"DE",
    "sg:address":"Drosselweg 68",
    "sg:city":"Niederkassel",
    "sg:phone":"+49 2208/1267",
    "sg:postcode":"53859",
    "sg:province":"Nordrhein-Westfalen",
    "wof:name":"W. Sigmund Augenoptiker",
    "wof:placetype":"venue"
},
  "geometry": {"coordinates":[7.0559239388,50.7882995605],"type":"Point"}
}