{
  "type": "Feature",
  "properties": {
    "iso:country":"DE",
    "sg:address":"Bismarckstr. 22",
    "sg:city":"Pegau",
    "sg:phone":"+49 34296/6706",
    "sg:postcode":"04523",
    "sg:province":"Sachsen",
    "wof:name":"Werner Sommer",
    "wof:placetype":"venue"
},
  "geometry": {"coordinates":[12.244663,51.165672],"type":"Point"}
}