{
  "type": "Feature",
  "properties": {
    "iso:country":"DE",
    "sg:address":"Drelsdorfer Str. 1",
    "sg:city":"Bredstedt",
    "sg:phone":"+49 4671/930494",
    "sg:postcode":"25821",
    "sg:province":"Schleswig-Holstein",
    "wof:name":"Schleswiger Versicherung",
    "wof:placetype":"venue"
},
  "geometry": {"coordinates":[8.9749002457,54.616569519],"type":"Point"}
}