{
  "type": "Feature",
  "properties": {
    "iso:country":"DE",
    "sg:address":"Graf-Salm-Str. 35",
    "sg:city":"Bedburg",
    "sg:phone":"+49 2272/930256",
    "sg:postcode":"50181",
    "sg:province":"Nordrhein-Westfalen",
    "wof:name":"Wolfgang Gr\u00f6be Ingenieur",
    "wof:placetype":"venue"
},
  "geometry": {"coordinates":[6.5760278702,50.9965782166],"type":"Point"}
}