{
  "type": "Feature",
  "properties": {
    "iso:country":"DE",
    "sg:address":"Douglasienweg 1",
    "sg:city":"Bad Hersfeld",
    "sg:phone":"+49 6621/65568",
    "sg:postcode":"36251",
    "sg:province":"Hessen",
    "wof:name":"W. Knies",
    "wof:placetype":"venue"
},
  "geometry": {"coordinates":[9.701435,50.846306],"type":"Point"}
}