{
  "type": "Feature",
  "properties": {
    "iso:country":"DE",
    "sg:address":"Schlo\u00dfstr. 2",
    "sg:city":"Winnenden",
    "sg:phone":"+49 7195/61423",
    "sg:postcode":"71364",
    "sg:province":"Baden-W\u00fcrttemberg",
    "wof:name":"S. Mayer",
    "wof:placetype":"venue"
},
  "geometry": {"coordinates":[9.398901,48.875999],"type":"Point"}
}