{
  "type": "Feature",
  "properties": {
    "iso:country":"DE",
    "sg:address":"Johann-Heinrich-Abt-Str. 4",
    "sg:city":"M\u00fcnchberg",
    "sg:phone":"+49 9251/5574",
    "sg:postcode":"95213",
    "sg:province":"Bayern",
    "wof:name":"I. B\u00f6rner Kg",
    "wof:placetype":"venue"
},
  "geometry": {"coordinates":[11.7920093536,50.1926689148],"type":"Point"}
}