{
  "type": "Feature",
  "properties": {
    "iso:country":"DE",
    "sg:address":"Duisburger Str. 289",
    "sg:city":"Duisburg",
    "sg:phone":"+49 2066/56655",
    "sg:postcode":"47198",
    "sg:province":"Nordrhein-Westfalen",
    "wof:name":"M. Miethe",
    "wof:placetype":"venue"
},
  "geometry": {"coordinates":[6.6992139816,51.4521751404],"type":"Point"}
}