{
  "type": "Feature",
  "properties": {
    "iso:country":"DE",
    "sg:address":"Brauckstr. 38",
    "sg:city":"Witten",
    "sg:phone":"+49 2302/9883",
    "sg:postcode":"58454",
    "sg:province":"Nordrhein-Westfalen",
    "wof:name":"Speer & Co Kraftverkehr Gmbh",
    "wof:placetype":"venue"
},
  "geometry": {"coordinates":[7.3911881447,51.4579238892],"type":"Point"}
}