{
  "type": "Feature",
  "properties": {
    "iso:country":"DE",
    "sg:address":"Hiddenhauser Str. 6",
    "sg:city":"Enger",
    "sg:postcode":"32130",
    "sg:province":"Nordrhein-Westfalen",
    "wof:name":"Specht Verwaltungs Gmbh",
    "wof:placetype":"venue"
},
  "geometry": {"coordinates":[8.5622367859,52.1428642273],"type":"Point"}
}