{
  "type": "Feature",
  "properties": {
    "iso:country":"DE",
    "sg:address":"M\u00fcnchner Str. 28",
    "sg:city":"Chemnitz",
    "sg:phone":"+49 371/4026240",
    "sg:postcode":"09130",
    "sg:province":"Sachsen",
    "wof:name":"Dr. Med. Ingrid Treuhoff",
    "wof:placetype":"venue"
},
  "geometry": {"coordinates":[12.952986,50.834324],"type":"Point"}
}