{
  "type": "Feature",
  "properties": {
    "iso:country":"DE",
    "sg:address":"Vorm Stichel 17",
    "sg:city":"Rodenbach",
    "sg:postcode":"63517",
    "sg:province":"Hessen",
    "wof:name":"Industriemeister Vereinigung E. V.",
    "wof:placetype":"venue"
},
  "geometry": {"coordinates":[9.0286855698,50.1435813904],"type":"Point"}
}