{
  "type": "Feature",
  "properties": {
    "iso:country":"DE",
    "sg:address":"Wei\u00dfenberg 16",
    "sg:city":"Edelsfeld",
    "sg:phone":"+49 9665/343",
    "sg:postcode":"92265",
    "sg:province":"Bayern",
    "wof:name":"Leonhard Raum Lebensmittel E H",
    "wof:placetype":"venue"
},
  "geometry": {"coordinates":[11.7259473801,49.5779647827],"type":"Point"}
}