{
  "type": "Feature",
  "properties": {
    "iso:country":"DE",
    "sg:address":"Hermann-Ehlers-Platz 1",
    "sg:city":"B\u00fcdelsdorf",
    "sg:phone":"+49 4331/36663",
    "sg:postcode":"24782",
    "sg:province":"Schleswig-Holstein",
    "wof:name":"G. Hansen Ingenieur",
    "wof:placetype":"venue"
},
  "geometry": {"coordinates":[9.6915340424,54.3156280518],"type":"Point"}
}