{
  "type": "Feature",
  "properties": {
    "iso:country":"DE",
    "sg:address":"Wildhagen 42",
    "sg:city":"Bielefeld",
    "sg:phone":"+49 521/102856",
    "sg:postcode":"33619",
    "sg:province":"Nordrhein-Westfalen",
    "wof:name":"Volker Seemann Tennislehrer",
    "wof:placetype":"venue"
},
  "geometry": {"coordinates":[8.47914505,52.0555305481],"type":"Point"}
}