{
  "type": "Feature",
  "properties": {
    "iso:country":"DE",
    "sg:address":"Schillerstr. 47",
    "sg:city":"Ketsch",
    "sg:postcode":"68775",
    "sg:province":"Baden-W\u00fcrttemberg",
    "wof:name":"H. Barsch Immobilienmakler",
    "wof:placetype":"venue"
},
  "geometry": {"coordinates":[8.5304346085,49.3640823364],"type":"Point"}
}