{
  "type": "Feature",
  "properties": {
    "iso:country":"DE",
    "sg:address":"Gr\u00e4fenau 50",
    "sg:city":"H\u00f6fen",
    "sg:phone":"+49 7081/5118",
    "sg:postcode":"75339",
    "sg:province":"Baden-W\u00fcrttemberg",
    "wof:name":"Peter Krauth Gmbh",
    "wof:placetype":"venue"
},
  "geometry": {"coordinates":[8.578169,48.791847],"type":"Point"}
}