{
  "type": "Feature",
  "properties": {
    "iso:country":"DE",
    "sg:address":"Lerchenweg 2",
    "sg:city":"W\u00fcrzburg",
    "sg:phone":"+49 931/75474",
    "sg:postcode":"97074",
    "sg:province":"Bayern",
    "wof:name":"R. U. J. Schwarz Gmbh",
    "wof:placetype":"venue"
},
  "geometry": {"coordinates":[9.9513282776,49.778793335],"type":"Point"}
}