{
  "type": "Feature",
  "properties": {
    "iso:country":"DE",
    "sg:address":"Rauenberger Str. 6",
    "sg:city":"Dielheim",
    "sg:phone":"+49 6222/73976",
    "sg:postcode":"69234",
    "sg:province":"Baden-W\u00fcrttemberg",
    "wof:name":"Herbert Freund",
    "wof:placetype":"venue"
},
  "geometry": {"coordinates":[8.7346696854,49.2821540833],"type":"Point"}
}