{
  "type": "Feature",
  "properties": {
    "iso:country":"DE",
    "sg:address":"W\u00f6hlerstr. 6",
    "sg:city":"Freiburg",
    "sg:phone":"+49 761/500081",
    "sg:postcode":"79108",
    "sg:province":"Baden-W\u00fcrttemberg",
    "wof:name":"Heidi Weber",
    "wof:placetype":"venue"
},
  "geometry": {"coordinates":[7.8511929512,48.0337333679],"type":"Point"}
}