{
  "type": "Feature",
  "properties": {
    "iso:country":"DE",
    "sg:address":"Marktplatz 16",
    "sg:city":"Aidenbach",
    "sg:phone":"+49 8543/2411",
    "sg:postcode":"94501",
    "sg:province":"Bayern",
    "wof:name":"Anton Herrndobler",
    "wof:placetype":"venue"
},
  "geometry": {"coordinates":[13.0876703262,48.5678253174],"type":"Point"}
}