{
  "type": "Feature",
  "properties": {
    "iso:country":"DE",
    "sg:address":"Bischofsweg 28",
    "sg:city":"Walchum",
    "sg:postcode":"26907",
    "sg:province":"Niedersachsen",
    "wof:name":"Edv Beratung Seifert Gmbh",
    "wof:placetype":"venue"
},
  "geometry": {"coordinates":[7.2716679573,52.9331855774],"type":"Point"}
}