{
  "type": "Feature",
  "properties": {
    "iso:country":"DE",
    "sg:address":"Am Steinberg 2a",
    "sg:city":"Gilching",
    "sg:phone":"+49 8105/24997",
    "sg:postcode":"82205",
    "sg:province":"Bayern",
    "wof:name":"K. K. Bautr\u00e4ger Gmbh",
    "wof:placetype":"venue"
},
  "geometry": {"coordinates":[11.303578,48.109489],"type":"Point"}
}