{
  "type": "Feature",
  "properties": {
    "iso:country":"DE",
    "sg:address":"Okerweg 25",
    "sg:city":"Kissenbr\u00fcck",
    "sg:phone":"+49 5337/948591",
    "sg:postcode":"38324",
    "sg:province":"Niedersachsen",
    "wof:name":"Rutzen & Scherer",
    "wof:placetype":"venue"
},
  "geometry": {"coordinates":[10.5717401505,52.1121101379],"type":"Point"}
}