{
  "type": "Feature",
  "properties": {
    "iso:country":"DE",
    "sg:address":"Markt 24",
    "sg:city":"Schlotheim",
    "sg:phone":"+49 36021/9170",
    "sg:postcode":"99994",
    "sg:province":"Th\u00fcringen",
    "wof:name":"Opg Immobilien Verwaltungs- Und Vertriebs Gmbh",
    "wof:placetype":"venue"
},
  "geometry": {"coordinates":[10.6559257507,51.2471618652],"type":"Point"}
}