{
  "type": "Feature",
  "properties": {
    "iso:country":"DE",
    "sg:address":"Merianhof 1",
    "sg:city":"Freiburg",
    "sg:phone":"+49 761/288351",
    "sg:postcode":"79104",
    "sg:province":"Baden-W\u00fcrttemberg",
    "wof:name":"E. Leonhard",
    "wof:placetype":"venue"
},
  "geometry": {"coordinates":[7.85075,47.998951],"type":"Point"}
}