{
  "type": "Feature",
  "properties": {
    "iso:country":"DE",
    "sg:address":"Rheinstr. 108",
    "sg:city":"Wiesbaden",
    "sg:phone":"+49 611/374198",
    "sg:postcode":"65185",
    "sg:province":"Hessen",
    "wof:name":"Andreas-apotheke",
    "wof:placetype":"venue"
},
  "geometry": {"coordinates":[8.230622,50.076965],"type":"Point"}
}