{
  "type": "Feature",
  "properties": {
    "iso:country":"DE",
    "sg:address":"Boisheimer Str. 134",
    "sg:city":"Viersen",
    "sg:phone":"+49 2162/56195",
    "sg:postcode":"41751",
    "sg:province":"Nordrhein-Westfalen",
    "wof:name":"Heinrich Nehlen",
    "wof:placetype":"venue"
},
  "geometry": {"coordinates":[6.3097,51.253189],"type":"Point"}
}