{
  "type": "Feature",
  "properties": {
    "iso:country":"DE",
    "sg:address":"Eichhornweg 2",
    "sg:city":"Blaustein",
    "sg:phone":"+49 7304/919350",
    "sg:postcode":"89134",
    "sg:province":"Baden-W\u00fcrttemberg",
    "wof:name":"Harder Industrie- Elektronik Gmbh",
    "wof:placetype":"venue"
},
  "geometry": {"coordinates":[9.866101265,48.4283828735],"type":"Point"}
}