{
  "type": "Feature",
  "properties": {
    "iso:country":"DE",
    "sg:address":"K\u00f6nigstuhlstr. 8",
    "sg:city":"Wiesbaden",
    "sg:phone":"+49 611/529525",
    "sg:postcode":"65193",
    "sg:province":"Hessen",
    "wof:name":"S. Hevert Dolmetscherb\u00fcro",
    "wof:placetype":"venue"
},
  "geometry": {"coordinates":[8.245802,50.092113],"type":"Point"}
}