{
  "type": "Feature",
  "properties": {
    "iso:country":"DE",
    "sg:address":"Alte Handelsstr. 39",
    "sg:city":"Attendorn",
    "sg:phone":"+49 2722/979083",
    "sg:postcode":"57439",
    "sg:province":"Nordrhein-Westfalen",
    "wof:name":"Guido L\u00fcck",
    "wof:placetype":"venue"
},
  "geometry": {"coordinates":[7.8708748817,51.1117286682],"type":"Point"}
}