{
  "type": "Feature",
  "properties": {
    "iso:country":"DE",
    "sg:address":"Hurdstr. 3",
    "sg:city":"Eschach",
    "sg:phone":"+49 7175/6536",
    "sg:postcode":"73569",
    "sg:province":"Baden-W\u00fcrttemberg",
    "wof:name":"Karl Maier",
    "wof:placetype":"venue"
},
  "geometry": {"coordinates":[9.874113,48.887669],"type":"Point"}
}