{
  "type": "Feature",
  "properties": {
    "iso:country":"DE",
    "sg:address":"Lohengrinstr. 4",
    "sg:city":"Wei\u00dfenhorn",
    "sg:phone":"+49 7309/919021",
    "sg:postcode":"89264",
    "sg:province":"Bayern",
    "wof:name":"Kesekamp",
    "wof:placetype":"venue"
},
  "geometry": {"coordinates":[10.1533679962,48.3093948364],"type":"Point"}
}