{
  "type": "Feature",
  "properties": {
    "iso:country":"DE",
    "sg:address":"Kalchreuther Str. 145 a",
    "sg:city":"N\u00fcrnberg",
    "sg:phone":"+49 911/524466",
    "sg:postcode":"90411",
    "sg:province":"Bayern",
    "wof:name":"G\u00fcnter Jung Industrie- Vertretungen Gmbh",
    "wof:placetype":"venue"
},
  "geometry": {"coordinates":[11.1099042892,49.5055046082],"type":"Point"}
}