{
  "type": "Feature",
  "properties": {
    "iso:country":"DE",
    "sg:address":"Reichenbach 2",
    "sg:city":"Nesselwang",
    "sg:phone":"+49 8361/92020",
    "sg:postcode":"87484",
    "sg:province":"Bayern",
    "wof:name":"Zum Alten Reichenbach",
    "wof:placetype":"venue"
},
  "geometry": {"coordinates":[10.4771461487,47.6163368225],"type":"Point"}
}