{
  "type": "Feature",
  "properties": {
    "iso:country":"DE",
    "sg:address":"Industriestr. 18",
    "sg:city":"Gr\u00f6benzell",
    "sg:phone":"+49 8142/6360",
    "sg:postcode":"82194",
    "sg:province":"Bayern",
    "wof:name":"Georg Mairiedl Mech. Werkstatt",
    "wof:placetype":"venue"
},
  "geometry": {"coordinates":[11.382653,48.189308],"type":"Point"}
}