{
  "type": "Feature",
  "properties": {
    "iso:country":"DE",
    "sg:address":"Am Hang 6",
    "sg:city":"Assamstadt",
    "sg:phone":"+49 6294/500",
    "sg:postcode":"97959",
    "sg:province":"Baden-W\u00fcrttemberg",
    "wof:name":"W. Niederle",
    "wof:placetype":"venue"
},
  "geometry": {"coordinates":[9.696573,49.430428],"type":"Point"}
}