{
  "type": "Feature",
  "properties": {
    "iso:country":"DE",
    "sg:address":"Am Markt 11",
    "sg:city":"Seehausen",
    "sg:phone":"+49 39386/2037",
    "sg:postcode":"39615",
    "sg:province":"Sachsen-Anhalt",
    "wof:name":"Volksbank Osterburg Eg",
    "wof:placetype":"venue"
},
  "geometry": {"coordinates":[11.753446,52.890663],"type":"Point"}
}