{
  "type": "Feature",
  "properties": {
    "iso:country":"DE",
    "sg:address":"Alte Northeimer Str. 7",
    "sg:city":"Osterode",
    "sg:phone":"+49 5522/90630",
    "sg:postcode":"37520",
    "sg:province":"Niedersachsen",
    "wof:name":"Haushalt Und Technik Gmbh & Co. Kg",
    "wof:placetype":"venue"
},
  "geometry": {"coordinates":[10.3089799881,51.6765785217],"type":"Point"}
}