{
  "type": "Feature",
  "properties": {
    "iso:country":"DE",
    "sg:address":"Fischmarkt 13 -16",
    "sg:city":"Erfurt",
    "sg:phone":"+49 361/67070",
    "sg:postcode":"99084",
    "sg:province":"Th\u00fcringen",
    "wof:name":"Red. Deutsche Handwerks Ztg.",
    "wof:placetype":"venue"
},
  "geometry": {"coordinates":[11.0286493301,50.9781646729],"type":"Point"}
}