{
  "type": "Feature",
  "properties": {
    "iso:country":"DE",
    "sg:address":"Leonrodstr. 33",
    "sg:city":"M\u00fcnchen",
    "sg:phone":"+49 89/185680",
    "sg:postcode":"80636",
    "sg:province":"Bayern",
    "wof:name":"Peter Br\u00fcning",
    "wof:placetype":"venue"
},
  "geometry": {"coordinates":[11.5383291245,48.1548843384],"type":"Point"}
}