{
  "type": "Feature",
  "properties": {
    "iso:country":"DE",
    "sg:address":"M\u00f6llner Str. 23",
    "sg:city":"Steinburg",
    "sg:phone":"+49 4534/657",
    "sg:postcode":"22964",
    "sg:province":"Schleswig-Holstein",
    "wof:name":"G\u00fcnter Rehr",
    "wof:placetype":"venue"
},
  "geometry": {"coordinates":[10.4122781754,53.7127990723],"type":"Point"}
}