{
  "type": "Feature",
  "properties": {
    "iso:country":"DE",
    "sg:address":"Hauptstr. 69",
    "sg:city":"Simmertal",
    "sg:phone":"+49 6754/571",
    "sg:postcode":"55618",
    "sg:province":"Rheinland-Pfalz",
    "wof:name":"Helmut He\u00df",
    "wof:placetype":"venue"
},
  "geometry": {"coordinates":[7.5216350555,49.8136482239],"type":"Point"}
}