{
  "type": "Feature",
  "properties": {
    "iso:country":"DE",
    "sg:address":"Am G\u00fcterbahnhof",
    "sg:city":"Reinheim",
    "sg:phone":"+49 6162/2401",
    "sg:postcode":"64354",
    "sg:province":"Hessen",
    "wof:name":"Ludwig Wagner Kg Mineral\u00f6lhandel",
    "wof:placetype":"venue"
},
  "geometry": {"coordinates":[8.8337402344,49.8320503235],"type":"Point"}
}