{
  "type": "Feature",
  "properties": {
    "iso:country":"DE",
    "sg:address":"Hildburghauser Str. 10D",
    "sg:city":"Berlin",
    "sg:phone":"+49 30/7216109",
    "sg:postcode":"12279",
    "sg:province":"Berlin",
    "wof:name":"R. Gottschlich",
    "wof:placetype":"venue"
},
  "geometry": {"coordinates":[13.358593,52.413197],"type":"Point"}
}