{
  "type": "Feature",
  "properties": {
    "iso:country":"DE",
    "sg:address":"P\u00fclziger Str. 2",
    "sg:city":"Cobbelsdorf",
    "sg:postcode":"06869",
    "sg:province":"Sachsen-Anhalt",
    "wof:name":"Cobbelsdorfer Trennwand- Systeme Gmbh",
    "wof:placetype":"venue"
},
  "geometry": {"coordinates":[12.535068,51.95808],"type":"Point"}
}