{
  "type": "Feature",
  "properties": {
    "iso:country":"DE",
    "sg:address":"Artelshofen 2",
    "sg:city":"Vorra",
    "sg:phone":"+49 9152/986555",
    "sg:postcode":"91247",
    "sg:province":"Bayern",
    "wof:name":"Erhard Brunner",
    "wof:placetype":"venue"
},
  "geometry": {"coordinates":[11.490901947,49.5559692383],"type":"Point"}
}