{
  "type": "Feature",
  "properties": {
    "iso:country":"DE",
    "sg:address":"Golzheimer Str. 120",
    "sg:city":"D\u00fcsseldorf",
    "sg:phone":"+49 211/347074",
    "sg:postcode":"40476",
    "sg:province":"Nordrhein-Westfalen",
    "wof:name":"Winfried J. Jokisch",
    "wof:placetype":"venue"
},
  "geometry": {"coordinates":[6.781677,51.245586],"type":"Point"}
}