{
  "type": "Feature",
  "properties": {
    "iso:country":"DE",
    "sg:address":"Winzerlaer Str 2a",
    "sg:city":"Jena",
    "sg:phone":"+49 3641/508400",
    "sg:postcode":"07745",
    "sg:province":"Th\u00fcringen",
    "wof:name":"Blei-institut Gesellschaft F\u00fcr Wohnraum- Und Umwelttoxikologie Mbh",
    "wof:placetype":"venue"
},
  "geometry": {"coordinates":[11.568708,50.907459],"type":"Point"}
}