{
  "type": "Feature",
  "properties": {
    "iso:country":"DE",
    "sg:address":"Kenenstr. 2",
    "sg:city":"Weimar",
    "sg:phone":"+49 6421/7173",
    "sg:postcode":"35096",
    "sg:province":"Hessen",
    "wof:name":"Rudolf Keil",
    "wof:placetype":"venue"
},
  "geometry": {"coordinates":[8.667418,50.743629],"type":"Point"}
}