{
  "type": "Feature",
  "properties": {
    "iso:country":"DE",
    "sg:address":"Kirchstr. 6",
    "sg:city":"Dienheim",
    "sg:phone":"+49 6133/4679",
    "sg:postcode":"55276",
    "sg:province":"Rheinland-Pfalz",
    "wof:name":"Armin Uhl",
    "wof:placetype":"venue"
},
  "geometry": {"coordinates":[8.3503627777,49.8382759094],"type":"Point"}
}