{
  "type": "Feature",
  "properties": {
    "iso:country":"DE",
    "sg:address":"Steinkirchen 4 1/2",
    "sg:city":"A\u00dfling",
    "sg:phone":"+49 8092/9914",
    "sg:postcode":"85617",
    "sg:province":"Bayern",
    "wof:name":"Hofmann & Vratny Ohg",
    "wof:placetype":"venue"
},
  "geometry": {"coordinates":[12.0078449249,47.9934425354],"type":"Point"}
}