{
  "type": "Feature",
  "properties": {
    "iso:country":"DE",
    "sg:address":"Kirchplatz 4",
    "sg:city":"Adorf",
    "sg:phone":"+49 37423/2227",
    "sg:postcode":"08626",
    "sg:province":"Sachsen",
    "wof:name":"W. Oettel",
    "wof:placetype":"venue"
},
  "geometry": {"coordinates":[12.2559633255,50.3203697205],"type":"Point"}
}