{
  "type": "Feature",
  "properties": {
    "iso:country":"DE",
    "sg:address":"Walkertshofen",
    "sg:city":"Attenhofen",
    "sg:phone":"+49 8753/583",
    "sg:postcode":"84091",
    "sg:province":"Bayern",
    "wof:name":"Gastst\u00e4tte Georg Rank",
    "wof:placetype":"venue"
},
  "geometry": {"coordinates":[11.8463001251,48.6503105164],"type":"Point"}
}