{
  "type": "Feature",
  "properties": {
    "iso:country":"DE",
    "sg:address":"Rosenstra\u00dfe 14",
    "sg:city":"\u00d6tigheim",
    "sg:phone":"+49 7222/154955",
    "sg:postcode":"76470",
    "sg:province":"Baden-W\u00fcrttemberg",
    "wof:name":"Schlenker Center Service Homepage",
    "wof:placetype":"venue"
},
  "geometry": {"coordinates":[8.238457,48.892147],"type":"Point"}
}