{
  "type": "Feature",
  "properties": {
    "iso:country":"DE",
    "sg:address":"Herrnstr. 10c",
    "sg:city":"Altenstadt",
    "sg:phone":"+49 6047/7890",
    "sg:postcode":"63674",
    "sg:province":"Hessen",
    "wof:name":"Christoph M\u00fcller Masseur",
    "wof:placetype":"venue"
},
  "geometry": {"coordinates":[8.93042,50.267452],"type":"Point"}
}