{
  "type": "Feature",
  "properties": {
    "iso:country":"DE",
    "sg:address":"Mittelstr. 4",
    "sg:city":"Plettenberg",
    "sg:postcode":"58840",
    "sg:province":"Nordrhein-Westfalen",
    "wof:name":"M\u00e4ser Sportswear Gmbh",
    "wof:placetype":"venue"
},
  "geometry": {"coordinates":[7.8686509132,51.2328987122],"type":"Point"}
}