{
  "type": "Feature",
  "properties": {
    "iso:country":"DE",
    "sg:address":"An Den Nahewiesen 5",
    "sg:city":"Langenlonsheim",
    "sg:phone":"+49 4967/0493300",
    "sg:postcode":"55450",
    "sg:province":"Rheinland-Pfalz",
    "wof:name":"Klug Handels- U. Transportgmbh",
    "wof:placetype":"venue"
},
  "geometry": {"coordinates":[7.901648,49.901947],"type":"Point"}
}