{
  "type": "Feature",
  "properties": {
    "iso:country":"DE",
    "sg:address":"Bodelschwingher Str. 121",
    "sg:city":"Dortmund",
    "sg:phone":"+49 231/37602",
    "sg:postcode":"44357",
    "sg:province":"Nordrhein-Westfalen",
    "wof:name":"Jumbo M\u00f6belhandels Gmbh",
    "wof:placetype":"venue"
},
  "geometry": {"coordinates":[7.381966114,51.5512313843],"type":"Point"}
}