{
  "type": "Feature",
  "properties": {
    "iso:country":"DE",
    "sg:city":"Zirndorf",
    "sg:postcode":"90513",
    "sg:province":"Bayern",
    "wof:name":"Global Statues Inc",
    "wof:placetype":"venue"
},
  "geometry": {"coordinates":[10.957815,49.442341],"type":"Point"}
}