{
  "type": "Feature",
  "properties": {
    "iso:country":"DE",
    "sg:address":"Schwalbenstr. 8",
    "sg:city":"R\u00f6dermark",
    "sg:phone":"+49 6074/50165",
    "sg:postcode":"63322",
    "sg:province":"Hessen",
    "wof:name":"Dorothea Hoffmann-zahn Ergotherapiepraxis",
    "wof:placetype":"venue"
},
  "geometry": {"coordinates":[8.78683,49.970753],"type":"Point"}
}