{
  "type": "Feature",
  "properties": {
    "iso:country":"DE",
    "sg:address":"Eichelsstr. 10",
    "sg:city":"Berka",
    "sg:postcode":"99837",
    "sg:province":"Th\u00fcringen",
    "wof:name":"Ev.-luth. Kirche Gospenroda",
    "wof:placetype":"venue"
},
  "geometry": {"coordinates":[10.1024646759,50.9075927734],"type":"Point"}
}