{
  "type": "Feature",
  "properties": {
    "iso:country":"DE",
    "sg:address":"Am Bahnhof 13",
    "sg:city":"Eggesin",
    "sg:phone":"+49 39779/27530",
    "sg:postcode":"17367",
    "sg:province":"Mecklenburg-Vorpommern",
    "wof:name":"C. Bremer",
    "wof:placetype":"venue"
},
  "geometry": {"coordinates":[14.0740623474,53.6811294556],"type":"Point"}
}