{
  "type": "Feature",
  "properties": {
    "iso:country":"DE",
    "sg:address":"Alicestr. 13",
    "sg:city":"Ober-Ramstadt",
    "sg:phone":"+49 6154/2215",
    "sg:postcode":"64372",
    "sg:province":"Hessen",
    "wof:name":"Manfred P. Daum",
    "wof:placetype":"venue"
},
  "geometry": {"coordinates":[8.747792,49.83078],"type":"Point"}
}