{
  "type": "Feature",
  "properties": {
    "iso:country":"DE",
    "sg:address":"Hauptstr. 49",
    "sg:city":"Dannewerk",
    "sg:postcode":"24867",
    "sg:province":"Schleswig-Holstein",
    "wof:name":"Marquardt & Diercks Gmbh",
    "wof:placetype":"venue"
},
  "geometry": {"coordinates":[9.50475,54.484791],"type":"Point"}
}