{
  "type": "Feature",
  "properties": {
    "iso:country":"DE",
    "sg:address":"Lindenallee 3",
    "sg:city":"Hessisch Lichtenau",
    "sg:phone":"+49 5602/2252",
    "sg:postcode":"37235",
    "sg:province":"Hessen",
    "wof:name":"Waldemar Simon",
    "wof:placetype":"venue"
},
  "geometry": {"coordinates":[9.7447299957,51.2205886841],"type":"Point"}
}