{
  "type": "Feature",
  "properties": {
    "iso:country":"DE",
    "sg:address":"Darmst\u00e4dter Str. 42",
    "sg:city":"R\u00fcsselsheim",
    "sg:phone":"+49 6142/62421",
    "sg:postcode":"65428",
    "sg:province":"Hessen",
    "wof:name":"Spiel & Hobby Inh. Peter Kromschr\u00f6der",
    "wof:placetype":"venue"
},
  "geometry": {"coordinates":[8.412686348,49.9890441895],"type":"Point"}
}