{
  "type": "Feature",
  "properties": {
    "iso:country":"DE",
    "sg:address":"Kirchstr 48",
    "sg:city":"Birnbach",
    "sg:phone":"+49 2681/70738",
    "sg:postcode":"57612",
    "sg:province":"Rheinland-Pfalz",
    "wof:name":"Smh Securitymanagement Heuzeroth",
    "wof:placetype":"venue"
},
  "geometry": {"coordinates":[7.590103,50.705029],"type":"Point"}
}