{
  "type": "Feature",
  "properties": {
    "iso:country":"DE",
    "sg:address":"Westfalenweg 296",
    "sg:city":"Wuppertal",
    "sg:phone":"+49 202/702462",
    "sg:postcode":"42111",
    "sg:province":"Nordrhein-Westfalen",
    "wof:name":"Wolfgang G. Sonneborn Architekt",
    "wof:placetype":"venue"
},
  "geometry": {"coordinates":[7.158891,51.287571],"type":"Point"}
}