{
  "type": "Feature",
  "properties": {
    "iso:country":"DE",
    "sg:address":"Bahnhofstr. 47",
    "sg:city":"Buchloe",
    "sg:phone":"+49 8241/5060",
    "sg:postcode":"86807",
    "sg:province":"Bayern",
    "wof:name":"Stadthotel",
    "wof:placetype":"venue"
},
  "geometry": {"coordinates":[10.7188405991,48.0341796875],"type":"Point"}
}