{
  "type": "Feature",
  "properties": {
    "iso:country":"DE",
    "sg:address":"Erbacher Str. 9",
    "sg:city":"Bensheim",
    "sg:phone":"+49 6251/3593",
    "sg:postcode":"64625",
    "sg:province":"Hessen",
    "wof:name":"Gerhard Sandner",
    "wof:placetype":"venue"
},
  "geometry": {"coordinates":[8.6230268478,49.6803779602],"type":"Point"}
}