{
  "type": "Feature",
  "properties": {
    "iso:country":"DE",
    "sg:address":"Heidestr. 18",
    "sg:city":"Voerde",
    "sg:phone":"+49 281/4908",
    "sg:postcode":"46562",
    "sg:province":"Nordrhein-Westfalen",
    "wof:name":"Richard M\u00fcnch",
    "wof:placetype":"venue"
},
  "geometry": {"coordinates":[6.6690411568,51.6267929077],"type":"Point"}
}