{
  "type": "Feature",
  "properties": {
    "iso:country":"DE",
    "sg:address":"Friedrichstr. 2",
    "sg:city":"Paderborn",
    "sg:phone":"+49 5251/22971",
    "sg:postcode":"33102",
    "sg:province":"Nordrhein-Westfalen",
    "wof:name":"Monpti",
    "wof:placetype":"venue"
},
  "geometry": {"coordinates":[8.7371730804,51.7128944397],"type":"Point"}
}