{
  "type": "Feature",
  "properties": {
    "iso:country":"DE",
    "sg:address":"Seifentalstr. 25",
    "sg:city":"Ehrenfriedersdorf",
    "sg:phone":"+49 37341/3518",
    "sg:postcode":"09427",
    "sg:province":"Sachsen",
    "wof:name":"Eli Clau\u00df",
    "wof:placetype":"venue"
},
  "geometry": {"coordinates":[12.978317,50.649197],"type":"Point"}
}