{
  "type": "Feature",
  "properties": {
    "iso:country":"DE",
    "sg:address":"Kelternstr. 14-16",
    "sg:city":"T\u00fcbingen",
    "sg:phone":"+49 7071/23356",
    "sg:postcode":"72070",
    "sg:province":"Baden-W\u00fcrttemberg",
    "wof:name":"Maurer Beteiligungs- Gesellschaft Mbh",
    "wof:placetype":"venue"
},
  "geometry": {"coordinates":[9.050534,48.522961],"type":"Point"}
}