{
  "type": "Feature",
  "properties": {
    "iso:country":"DE",
    "sg:address":"N\u00f6rdliche Gr\u00fcnauer Str. 1",
    "sg:city":"Neuburg",
    "sg:phone":"+49 8431/40456",
    "sg:postcode":"86633",
    "sg:province":"Bayern",
    "wof:name":"G\u00fcnter Olbrich",
    "wof:placetype":"venue"
},
  "geometry": {"coordinates":[11.2117443085,48.7376365662],"type":"Point"}
}