{
  "type": "Feature",
  "properties": {
    "iso:country":"DE",
    "sg:address":"Kaiserstr. 228",
    "sg:city":"Herten",
    "sg:phone":"+49 2366/36540",
    "sg:postcode":"45699",
    "sg:province":"Nordrhein-Westfalen",
    "wof:name":"Dietrich Vobker E. K.",
    "wof:placetype":"venue"
},
  "geometry": {"coordinates":[7.157803,51.602112],"type":"Point"}
}