{
  "type": "Feature",
  "properties": {
    "iso:country":"DE",
    "sg:address":"Ringbergstr. 105",
    "sg:city":"Suhl",
    "sg:postcode":"98528",
    "sg:province":"Th\u00fcringen",
    "wof:name":"Internet, Telekommunikation Und Mehr",
    "wof:placetype":"venue"
},
  "geometry": {"coordinates":[10.709052,50.629372],"type":"Point"}
}