{
  "type": "Feature",
  "properties": {
    "iso:country":"DE",
    "sg:address":"Wernersreuth",
    "sg:city":"Neusorg",
    "sg:phone":"+49 9234/294",
    "sg:postcode":"95700",
    "sg:province":"Bayern",
    "wof:name":"Leonhard K\u00f6nig",
    "wof:placetype":"venue"
},
  "geometry": {"coordinates":[11.9539709091,49.9185829163],"type":"Point"}
}