{
  "type": "Feature",
  "properties": {
    "iso:country":"DE",
    "sg:address":"Hettenshausener Str. 5",
    "sg:city":"Ilmm\u00fcnster",
    "sg:phone":"+49 8441/2201",
    "sg:postcode":"85304",
    "sg:province":"Bayern",
    "wof:name":"Kath. Pfarramt St. Johannes Baptist",
    "wof:placetype":"venue"
},
  "geometry": {"coordinates":[11.5029602051,48.4877624512],"type":"Point"}
}