{
  "type": "Feature",
  "properties": {
    "iso:country":"DE",
    "sg:address":"Unterer Talweg 133",
    "sg:city":"Augsburg",
    "sg:phone":"+49 821/881190",
    "sg:postcode":"86179",
    "sg:province":"Bayern",
    "wof:name":"Wolfgang Maier Steinmetzbetrieb",
    "wof:placetype":"venue"
},
  "geometry": {"coordinates":[10.8896112442,48.3099975586],"type":"Point"}
}