{
  "type": "Feature",
  "properties": {
    "iso:country":"DE",
    "sg:address":"\u00c4u\u00df M\u00fcnchener Str 132",
    "sg:city":"Rosenheim",
    "sg:phone":"+49 8031/12306",
    "sg:postcode":"83026",
    "sg:province":"Bayern",
    "wof:name":"Ralph Moser",
    "wof:placetype":"venue"
},
  "geometry": {"coordinates":[12.0810642242,47.8429412842],"type":"Point"}
}