{
  "type": "Feature",
  "properties": {
    "iso:country":"DE",
    "sg:address":"Andreas-Ke\u00dfler-Str. 22",
    "sg:city":"Zeil",
    "sg:phone":"+49 9524/7857",
    "sg:postcode":"97475",
    "sg:province":"Bayern",
    "wof:name":"G. Meyer",
    "wof:placetype":"venue"
},
  "geometry": {"coordinates":[10.5840320587,50.0196990967],"type":"Point"}
}