{
  "type": "Feature",
  "properties": {
    "iso:country":"DE",
    "sg:address":"Bremer Str. 13",
    "sg:city":"Bohmte",
    "sg:phone":"+49 5471/2656",
    "sg:postcode":"49163",
    "sg:province":"Niedersachsen",
    "wof:name":"Uwe M\u00f6llmann E. K.",
    "wof:placetype":"venue"
},
  "geometry": {"coordinates":[8.3092298508,52.3623504639],"type":"Point"}
}