{
  "type": "Feature",
  "properties": {
    "iso:country":"DE",
    "sg:address":"Georgswall 7 a",
    "sg:city":"Aurich",
    "sg:phone":"+49 4941/92940",
    "sg:postcode":"26603",
    "sg:province":"Niedersachsen",
    "wof:name":"Rub Gmbh Steuerberatungsgesellschaft",
    "wof:placetype":"venue"
},
  "geometry": {"coordinates":[7.4806032181,53.4676742554],"type":"Point"}
}