{
  "type": "Feature",
  "properties": {
    "iso:country":"DE",
    "sg:address":"Am Goldregen 9",
    "sg:city":"Flensburg",
    "sg:phone":"+49 461/311654",
    "sg:postcode":"24944",
    "sg:province":"Schleswig-Holstein",
    "wof:name":"Maria Strehlow",
    "wof:placetype":"venue"
},
  "geometry": {"coordinates":[9.482665062,54.803691864],"type":"Point"}
}