{
  "type": "Feature",
  "properties": {
    "iso:country":"DE",
    "sg:address":"Sch\u00f6nblick 17",
    "sg:city":"Rudersberg",
    "sg:phone":"+49 4971/833060",
    "sg:postcode":"73635",
    "sg:province":"Baden-W\u00fcrttemberg",
    "wof:name":"Adolf F\u00d6hl Gmbh & Co",
    "wof:placetype":"venue"
},
  "geometry": {"coordinates":[9.499669075,48.8647079468],"type":"Point"}
}