{
  "type": "Feature",
  "properties": {
    "iso:country":"DE",
    "sg:address":"Dornierstr. 2",
    "sg:city":"Birkenfeld",
    "sg:phone":"+49 9771/7848",
    "sg:postcode":"75217",
    "sg:province":"Baden-W\u00fcrttemberg",
    "wof:name":"Hohmann Gmbh & Co Kg Edelstahl-pr\u00c4zision",
    "wof:placetype":"venue"
},
  "geometry": {"coordinates":[10.224058,50.334145],"type":"Point"}
}