{
  "type": "Feature",
  "properties": {
    "iso:country":"DE",
    "sg:address":"Herbststr. 11",
    "sg:city":"Mering",
    "sg:phone":"+49 8233/4519",
    "sg:postcode":"86415",
    "sg:province":"Bayern",
    "wof:name":"Sigmund Reinbold",
    "wof:placetype":"venue"
},
  "geometry": {"coordinates":[10.9867582321,48.2616195679],"type":"Point"}
}