{
  "type": "Feature",
  "properties": {
    "iso:country":"DE",
    "sg:address":"Rebhuhnsteig 23",
    "sg:city":"Leipzig",
    "sg:phone":"+49 341/4283502",
    "sg:postcode":"04249",
    "sg:province":"Sachsen",
    "wof:name":"H. Rentsch",
    "wof:placetype":"venue"
},
  "geometry": {"coordinates":[12.310011,51.286346],"type":"Point"}
}