{
  "type": "Feature",
  "properties": {
    "iso:country":"DE",
    "sg:address":"Von-Soden-Str. 11 a",
    "sg:city":"N\u00fcrnberg",
    "sg:phone":"+49 911/984750",
    "sg:postcode":"90475",
    "sg:province":"Bayern",
    "wof:name":"Geos Gesellschaft F\u00fcr Den Einsatz Offener Systeme Mbh",
    "wof:placetype":"venue"
},
  "geometry": {"coordinates":[11.1755456924,49.4065132141],"type":"Point"}
}