{
  "type": "Feature",
  "properties": {
    "iso:country":"DE",
    "sg:address":"Sillensteder Str. 18",
    "sg:city":"Schortens",
    "sg:phone":"+49 4423/6308",
    "sg:postcode":"26419",
    "sg:province":"Niedersachsen",
    "wof:name":"Zur Tenne",
    "wof:placetype":"venue"
},
  "geometry": {"coordinates":[7.9911808968,53.5562744141],"type":"Point"}
}