{
  "type": "Feature",
  "properties": {
    "iso:country":"DE",
    "sg:address":"Kapellenstr. 8",
    "sg:city":"Ingelheim",
    "sg:phone":"+49 6725/3306",
    "sg:postcode":"55218",
    "sg:province":"Rheinland-Pfalz",
    "wof:name":"J. F. Trapp",
    "wof:placetype":"venue"
},
  "geometry": {"coordinates":[8.0110330582,49.9775428772],"type":"Point"}
}