{
  "type": "Feature",
  "properties": {
    "iso:country":"DE",
    "sg:address":"Frankfurter Str. 35",
    "sg:city":"Troisdorf",
    "sg:phone":"+49 2241/98330",
    "sg:postcode":"53840",
    "sg:province":"Nordrhein-Westfalen",
    "wof:name":"Kuttig Computeranwendungen Gmbh",
    "wof:placetype":"venue"
},
  "geometry": {"coordinates":[7.1686320305,50.8140869141],"type":"Point"}
}