{
  "type": "Feature",
  "properties": {
    "iso:country":"DE",
    "sg:address":"Karolinenstr. 29",
    "sg:city":"Ansbach",
    "sg:phone":"+49 981/14440",
    "sg:postcode":"91522",
    "sg:province":"Bayern",
    "wof:name":"Beratungsstelle Der Inneren Mission",
    "wof:placetype":"venue"
},
  "geometry": {"coordinates":[10.576684,49.300209],"type":"Point"}
}