{
  "type": "Feature",
  "properties": {
    "iso:country":"DE",
    "sg:address":"Hohenzollernstr. 17",
    "sg:city":"Troisdorf",
    "sg:phone":"+49 2241/73598",
    "sg:postcode":"53840",
    "sg:province":"Nordrhein-Westfalen",
    "wof:name":"Tomic Heizungsbau Gmbh",
    "wof:placetype":"venue"
},
  "geometry": {"coordinates":[7.1528167725,50.8175926208],"type":"Point"}
}