{
  "type": "Feature",
  "properties": {
    "iso:country":"DE",
    "sg:address":"Ferdinandstr. 26",
    "sg:city":"Hamburg",
    "sg:postcode":"20095",
    "sg:province":"Hamburg",
    "wof:name":"Ms Wasaborg Zachariassen Beteiligungs Gmbh & Co.",
    "wof:placetype":"venue"
},
  "geometry": {"coordinates":[9.998485,53.549885],"type":"Point"}
}