{
  "type": "Feature",
  "properties": {
    "iso:country":"DE",
    "sg:address":"Ha-Martin-Schleyer-Str 30 A",
    "sg:city":"Willich",
    "sg:postcode":"47877",
    "sg:province":"Nordrhein-Westfalen",
    "wof:name":"Assindia Enterprise Gmbh",
    "wof:placetype":"venue"
},
  "geometry": {"coordinates":[6.5193572044,51.2741127014],"type":"Point"}
}