{
  "type": "Feature",
  "properties": {
    "iso:country":"DE",
    "sg:address":"Michelfelder Str.",
    "sg:city":"Auerbach",
    "sg:phone":"+49 9643/1422",
    "sg:postcode":"91275",
    "sg:province":"Bayern",
    "wof:name":"Deuchler & Rupprecht",
    "wof:placetype":"venue"
},
  "geometry": {"coordinates":[11.6243581772,49.6958045959],"type":"Point"}
}