{
  "type": "Feature",
  "properties": {
    "iso:country":"DE",
    "sg:address":"Glauberger Str. 2",
    "sg:city":"Glauburg",
    "sg:phone":"+49 6041/247",
    "sg:postcode":"63695",
    "sg:province":"Hessen",
    "wof:name":"Glauburg-apotheke",
    "wof:placetype":"venue"
},
  "geometry": {"coordinates":[9.017988,50.323132],"type":"Point"}
}