{
  "type": "Feature",
  "properties": {
    "iso:country":"DE",
    "sg:address":"Stegerwaldstr. 73",
    "sg:city":"Hagen",
    "sg:phone":"+49 2331/61854",
    "sg:postcode":"58099",
    "sg:province":"Nordrhein-Westfalen",
    "wof:name":"Winfried Dorn",
    "wof:placetype":"venue"
},
  "geometry": {"coordinates":[7.4872498512,51.3937301636],"type":"Point"}
}