{
  "type": "Feature",
  "properties": {
    "iso:country":"DE",
    "sg:address":"Twixlumer Str. 60",
    "sg:city":"Emden",
    "sg:phone":"+49 4921/65278",
    "sg:postcode":"26723",
    "sg:province":"Niedersachsen",
    "wof:name":"Karl Remmers",
    "wof:placetype":"venue"
},
  "geometry": {"coordinates":[7.14175,53.367241],"type":"Point"}
}