{
  "type": "Feature",
  "properties": {
    "iso:country":"DE",
    "sg:address":"Dieselstr. 30",
    "sg:city":"Gerlingen",
    "sg:phone":"+49 7156/49976",
    "sg:postcode":"70839",
    "sg:province":"Baden-W\u00fcrttemberg",
    "wof:name":"Zebra Fashion Textil Vertriebs Gmbh",
    "wof:placetype":"venue"
},
  "geometry": {"coordinates":[9.0712013245,48.8070335388],"type":"Point"}
}