{
  "type": "Feature",
  "properties": {
    "iso:country":"DE",
    "sg:address":"Celtisstr. 16",
    "sg:city":"N\u00fcrnberg",
    "sg:phone":"+49 911/4467824",
    "sg:postcode":"90459",
    "sg:province":"Bayern",
    "wof:name":"Walter Lang",
    "wof:placetype":"venue"
},
  "geometry": {"coordinates":[11.0803012848,49.4435958862],"type":"Point"}
}