{
  "type": "Feature",
  "properties": {
    "iso:country":"DE",
    "sg:address":"Betznauer Str. 29",
    "sg:city":"Kressbronn",
    "sg:phone":"+49 7543/6587",
    "sg:postcode":"88079",
    "sg:province":"Baden-W\u00fcrttemberg",
    "wof:name":"Johannes J\u00e4ger Elektroinstallation",
    "wof:placetype":"venue"
},
  "geometry": {"coordinates":[9.599325,47.600494],"type":"Point"}
}