{
  "type": "Feature",
  "properties": {
    "iso:country":"DE",
    "sg:address":"Roggenstra\u00dfe 62",
    "sg:city":"Filderstadt",
    "sg:phone":"+49 4971/1776080",
    "sg:postcode":"70794",
    "sg:province":"Baden-W\u00fcrttemberg",
    "wof:name":"Sellers Technologies",
    "wof:placetype":"venue"
},
  "geometry": {"coordinates":[9.2070207596,48.6491279602],"type":"Point"}
}