{
  "type": "Feature",
  "properties": {
    "iso:country":"DE",
    "sg:address":"Harderstr. 7",
    "sg:city":"Senden",
    "sg:phone":"+49 7307/5350",
    "sg:postcode":"89250",
    "sg:province":"Bayern",
    "wof:name":"Elektro Baumg\u00e4rtner Gmbh Gf. Manfred Baumg\u00e4rtner",
    "wof:placetype":"venue"
},
  "geometry": {"coordinates":[10.045591,48.325947],"type":"Point"}
}