{
  "type": "Feature",
  "properties": {
    "iso:country":"DE",
    "sg:address":"Lohkoppelstr. 2c",
    "sg:city":"Hamburg",
    "sg:phone":"+49 40/292972",
    "sg:postcode":"22083",
    "sg:province":"Hamburg",
    "wof:name":"Thomas Altenberg Ingenieur",
    "wof:placetype":"venue"
},
  "geometry": {"coordinates":[10.041374,53.581379],"type":"Point"}
}