{
  "type": "Feature",
  "properties": {
    "iso:country":"DE",
    "sg:address":"Curiestr. 19",
    "sg:city":"Mainz",
    "sg:phone":"+49 6131/592577",
    "sg:postcode":"55129",
    "sg:province":"Rheinland-Pfalz",
    "wof:name":"Schomburg Gmbh",
    "wof:placetype":"venue"
},
  "geometry": {"coordinates":[8.2644386292,49.9695777893],"type":"Point"}
}