{
  "type": "Feature",
  "properties": {
    "iso:country":"DE",
    "sg:address":"Lutzh\u00f6fter Str. 1",
    "sg:city":"Grundhof",
    "sg:phone":"+49 4636/364",
    "sg:postcode":"24977",
    "sg:province":"Schleswig-Holstein",
    "wof:name":"H. Lass",
    "wof:placetype":"venue"
},
  "geometry": {"coordinates":[9.652536,54.772606],"type":"Point"}
}