{
  "type": "Feature",
  "properties": {
    "iso:country":"DE",
    "sg:address":"Weimarer Str. 17",
    "sg:city":"Berlin",
    "sg:phone":"+49 30/3134646",
    "sg:postcode":"10625",
    "sg:province":"Berlin",
    "wof:name":"G\u00fcnter Druschky",
    "wof:placetype":"venue"
},
  "geometry": {"coordinates":[13.3109426498,52.5074501038],"type":"Point"}
}