{
  "type": "Feature",
  "properties": {
    "iso:country":"DE",
    "sg:address":"Alt-Godshorn 91",
    "sg:city":"Langenhagen",
    "sg:phone":"+49 511/784337",
    "sg:postcode":"30855",
    "sg:province":"Niedersachsen",
    "wof:name":"Horst Wiechers",
    "wof:placetype":"venue"
},
  "geometry": {"coordinates":[9.703198,52.43861],"type":"Point"}
}