{
  "type": "Feature",
  "properties": {
    "iso:country":"DE",
    "sg:address":"Grubm\u00fchlerfeldstr. 52",
    "sg:city":"Gauting",
    "sg:postcode":"82131",
    "sg:province":"Bayern",
    "wof:name":"Bio-reformel Vertriebs Gmbh",
    "wof:placetype":"venue"
},
  "geometry": {"coordinates":[11.3870763779,48.0726280212],"type":"Point"}
}