{
  "type": "Feature",
  "properties": {
    "iso:country":"DE",
    "sg:address":"Schlo\u00dfplatz 5",
    "sg:city":"Hechingen",
    "sg:phone":"+49 7471/5051256",
    "sg:postcode":"72379",
    "sg:province":"Baden-W\u00fcrttemberg",
    "wof:name":"Psycho-soz. Beratungsstelle D. Diakonischen Werkes",
    "wof:placetype":"venue"
},
  "geometry": {"coordinates":[8.962933,48.353859],"type":"Point"}
}