{
  "type": "Feature",
  "properties": {
    "iso:country":"DE",
    "sg:address":"K\u00f6rnerstr. 2",
    "sg:city":"Riesa",
    "sg:phone":"+49 3525/733622",
    "sg:postcode":"01587",
    "sg:province":"Sachsen",
    "wof:name":"Maler Gmbh Frohes Schaffen",
    "wof:placetype":"venue"
},
  "geometry": {"coordinates":[13.282136,51.305454],"type":"Point"}
}