{
  "type": "Feature",
  "properties": {
    "iso:country":"DE",
    "sg:address":"M\u00fcnchner Str. 16",
    "sg:city":"Simbach",
    "sg:phone":"+49 8571/6850",
    "sg:postcode":"84359",
    "sg:province":"Bayern",
    "wof:name":"Fachmarkt Eisenwaren",
    "wof:placetype":"venue"
},
  "geometry": {"coordinates":[13.0236625671,48.2656097412],"type":"Point"}
}