{
  "type": "Feature",
  "properties": {
    "iso:country":"DE",
    "sg:address":"Breslauer Str. 10",
    "sg:city":"K\u00f6ln",
    "sg:phone":"+49 2234/71431",
    "sg:postcode":"50858",
    "sg:province":"Nordrhein-Westfalen",
    "wof:name":"Wolfgang Kuhlhoff Ingenieur",
    "wof:placetype":"venue"
},
  "geometry": {"coordinates":[6.8441410065,50.9368438721],"type":"Point"}
}