{
  "type": "Feature",
  "properties": {
    "iso:country":"DE",
    "sg:address":"Frauenrichter Str. 1",
    "sg:city":"Weiden",
    "sg:phone":"+49 961/44337",
    "sg:postcode":"92637",
    "sg:province":"Bayern",
    "wof:name":"Dr. H.-w.und L. Schnupfhagn Rechtsanw\u00e4lte",
    "wof:placetype":"venue"
},
  "geometry": {"coordinates":[12.1557998657,49.6726417542],"type":"Point"}
}