{
  "type": "Feature",
  "properties": {
    "iso:country":"DE",
    "sg:address":"Kornstr. 109",
    "sg:city":"Bremen",
    "sg:phone":"+49 421/552864",
    "sg:postcode":"28201",
    "sg:province":"Bremen",
    "wof:name":"Angelika Fricke",
    "wof:placetype":"venue"
},
  "geometry": {"coordinates":[8.8025684357,53.0632514954],"type":"Point"}
}