{
  "type": "Feature",
  "properties": {
    "iso:country":"DE",
    "sg:address":"Bahnhofstr. 17",
    "sg:city":"Paderborn",
    "sg:phone":"+49 5251/26086",
    "sg:postcode":"33102",
    "sg:province":"Nordrhein-Westfalen",
    "wof:name":"Tbv Transport-vertrieb Gmbh",
    "wof:placetype":"venue"
},
  "geometry": {"coordinates":[8.7432565689,51.7142524719],"type":"Point"}
}