{
  "type": "Feature",
  "properties": {
    "iso:country":"DE",
    "sg:address":"Scharrerstr. 23",
    "sg:city":"Grafenau",
    "sg:phone":"+49 8552/671",
    "sg:postcode":"94481",
    "sg:province":"Bayern",
    "wof:name":"Sanit\u00e4tshaus Altstadt Hans F\u00fcrst Gmbh",
    "wof:placetype":"venue"
},
  "geometry": {"coordinates":[13.3962945938,48.85704422],"type":"Point"}
}