{
  "type": "Feature",
  "properties": {
    "iso:country":"DE",
    "sg:address":"Weinberg 60",
    "sg:city":"Spremberg",
    "sg:phone":"+49 3563/94600",
    "sg:postcode":"03130",
    "sg:province":"Brandenburg",
    "wof:name":"H. Pruss",
    "wof:placetype":"venue"
},
  "geometry": {"coordinates":[14.393581,51.568874],"type":"Point"}
}