{
  "type": "Feature",
  "properties": {
    "iso:country":"DE",
    "sg:address":"Am Zehnthof 185",
    "sg:city":"Essen",
    "sg:phone":"+49 201/859000",
    "sg:postcode":"45307",
    "sg:province":"Nordrhein-Westfalen",
    "wof:name":"Stern Druck- Und Verlagsgesellschaft Mbh",
    "wof:placetype":"venue"
},
  "geometry": {"coordinates":[7.0700640678,51.4585838318],"type":"Point"}
}