{
  "type": "Feature",
  "properties": {
    "iso:country":"DE",
    "sg:address":"Am Steinkreuz 2",
    "sg:city":"Geyer",
    "sg:phone":"+49 37346/93786",
    "sg:postcode":"09468",
    "sg:province":"Sachsen",
    "wof:name":"Karl-thomas Stopp Rechtsanwalt",
    "wof:placetype":"venue"
},
  "geometry": {"coordinates":[12.9223871231,50.6282997131],"type":"Point"}
}