{
  "type": "Feature",
  "properties": {
    "iso:country":"DE",
    "sg:address":"Hauptstr. 35",
    "sg:city":"Gerolstein",
    "sg:phone":"+49 6591/5757",
    "sg:postcode":"54568",
    "sg:province":"Rheinland-Pfalz",
    "wof:name":"Ignaz M\u00fcller",
    "wof:placetype":"venue"
},
  "geometry": {"coordinates":[6.6655550003,50.2221717834],"type":"Point"}
}