{
  "type": "Feature",
  "properties": {
    "iso:country":"DE",
    "sg:address":"Lindenstr. 21",
    "sg:city":"Laubach",
    "sg:phone":"+49 6405/950820",
    "sg:postcode":"35321",
    "sg:province":"Hessen",
    "wof:name":"Michael Heinz",
    "wof:placetype":"venue"
},
  "geometry": {"coordinates":[8.9244146347,50.552532196],"type":"Point"}
}