{
  "type": "Feature",
  "properties": {
    "iso:country":"DE",
    "sg:address":"Vattmannstr. 6",
    "sg:city":"Paderborn",
    "sg:phone":"+49 5251/15600",
    "sg:postcode":"33100",
    "sg:province":"Nordrhein-Westfalen",
    "wof:name":"Hesse Gmbh",
    "wof:placetype":"venue"
},
  "geometry": {"coordinates":[8.7963171005,51.7262916565],"type":"Point"}
}