{
  "type": "Feature",
  "properties": {
    "iso:country":"DE",
    "sg:address":"Ronnenberger Str. 24",
    "sg:city":"Ronnenberg",
    "sg:phone":"+49 511/438943",
    "sg:postcode":"30952",
    "sg:province":"Niedersachsen",
    "wof:name":"Sport- Und Freizeitcentrum Empelde Verwaltungs-gmbh",
    "wof:placetype":"venue"
},
  "geometry": {"coordinates":[9.6653165817,52.3327865601],"type":"Point"}
}