{
  "type": "Feature",
  "properties": {
    "iso:country":"DE",
    "sg:address":"Gontermannstr.7 B",
    "sg:city":"Berlin",
    "sg:phone":"+49 30",
    "sg:postcode":"12101",
    "sg:province":"Berlin",
    "wof:name":"J.schnellbacher",
    "wof:placetype":"venue"
},
  "geometry": {"coordinates":[13.3718032837,52.4805755615],"type":"Point"}
}