{
  "type": "Feature",
  "properties": {
    "iso:country":"DE",
    "sg:address":"Erfurter Str. 37",
    "sg:city":"Kranichfeld",
    "sg:phone":"+49 36450/3810",
    "sg:postcode":"99448",
    "sg:province":"Th\u00fcringen",
    "wof:name":"Mps Baubeschlags- Gro\u00dfhandels Gmbh",
    "wof:placetype":"venue"
},
  "geometry": {"coordinates":[11.2071,50.863495],"type":"Point"}
}