{
  "type": "Feature",
  "properties": {
    "iso:country":"DE",
    "sg:address":"Bodelschwinghstr. 144",
    "sg:city":"Viersen",
    "sg:phone":"+49 2162/55652",
    "sg:postcode":"41751",
    "sg:province":"Nordrhein-Westfalen",
    "wof:name":"Peter Linnarz Architekt",
    "wof:placetype":"venue"
},
  "geometry": {"coordinates":[6.3471,51.254009],"type":"Point"}
}