{
  "type": "Feature",
  "properties": {
    "iso:country":"DE",
    "sg:address":"Werftstr. 57",
    "sg:city":"Senzig",
    "sg:phone":"+49 3375/901503",
    "sg:postcode":"15754",
    "sg:province":"Brandenburg",
    "wof:name":"Helmut Schubert Immobilien-senzig",
    "wof:placetype":"venue"
},
  "geometry": {"coordinates":[13.6712198257,52.2906913757],"type":"Point"}
}