{
  "type": "Feature",
  "properties": {
    "iso:country":"DE",
    "sg:address":"Hillegosser Str. 26",
    "sg:city":"Bielefeld",
    "sg:phone":"+49 521/332600",
    "sg:postcode":"33719",
    "sg:province":"Nordrhein-Westfalen",
    "wof:name":"Katholisches Pfarramt St. Hedwig",
    "wof:placetype":"venue"
},
  "geometry": {"coordinates":[8.6046142578,52.0305213928],"type":"Point"}
}