{
  "type": "Feature",
  "properties": {
    "iso:country":"DE",
    "sg:address":"Ludwig-Marum-Str. 19",
    "sg:city":"Karlsruhe",
    "sg:phone":"+49 721/848562",
    "sg:postcode":"76185",
    "sg:province":"Baden-W\u00fcrttemberg",
    "wof:name":"Adalbert K\u00e4fer",
    "wof:placetype":"venue"
},
  "geometry": {"coordinates":[8.3698558807,49.0135154724],"type":"Point"}
}