{
  "type": "Feature",
  "properties": {
    "iso:country":"DE",
    "sg:address":"Amalienstr. 33",
    "sg:city":"Dortmund",
    "sg:phone":"+49 231/162070",
    "sg:postcode":"44137",
    "sg:province":"Nordrhein-Westfalen",
    "wof:name":"Haus Bisplinghoff",
    "wof:placetype":"venue"
},
  "geometry": {"coordinates":[7.4551892281,51.510307312],"type":"Point"}
}