{
  "type": "Feature",
  "properties": {
    "iso:country":"DE",
    "sg:address":"R\u00f6merstr. 4",
    "sg:city":"Mainhardt",
    "sg:phone":"+49 7903/816",
    "sg:postcode":"74535",
    "sg:province":"Baden-W\u00fcrttemberg",
    "wof:name":"Gasthaus Alte Post",
    "wof:placetype":"venue"
},
  "geometry": {"coordinates":[9.5569581985,49.0816192627],"type":"Point"}
}