{
  "type": "Feature",
  "properties": {
    "iso:country":"DE",
    "sg:address":"Rudolf-Breitscheid-Str. 3",
    "sg:city":"Seebad Heringsdorf",
    "sg:phone":"+49 38378/31984",
    "sg:postcode":"17424",
    "sg:province":"Mecklenburg-Vorpommern",
    "wof:name":"Wei\u00dfes Schlo\u00df Hotel- Und Gastst\u00e4ttengesellschaft Mbh",
    "wof:placetype":"venue"
},
  "geometry": {"coordinates":[14.1623544693,53.9589653015],"type":"Point"}
}