{
  "type": "Feature",
  "properties": {
    "iso:country":"DE",
    "sg:address":"Karl-Liebknecht-Str. 60a",
    "sg:city":"Cottbus",
    "sg:phone":"+49 355/23855",
    "sg:postcode":"03046",
    "sg:province":"Brandenburg",
    "wof:name":"E. K\u00fcgler Ingenieur",
    "wof:placetype":"venue"
},
  "geometry": {"coordinates":[14.3035030365,51.7542800903],"type":"Point"}
}