{
  "type": "Feature",
  "properties": {
    "iso:country":"DE",
    "sg:address":"Esperlohstr. 31",
    "sg:city":"Rheine",
    "sg:phone":"+49 5971/64444",
    "sg:postcode":"48429",
    "sg:province":"Nordrhein-Westfalen",
    "wof:name":"Werbe-service",
    "wof:placetype":"venue"
},
  "geometry": {"coordinates":[7.461423,52.273911],"type":"Point"}
}