{
  "type": "Feature",
  "properties": {
    "iso:country":"DE",
    "sg:address":"Otto-Hahn-Weg 5",
    "sg:city":"Leinfelden-Echterdingen",
    "sg:phone":"+49 711/751112",
    "sg:postcode":"70771",
    "sg:province":"Baden-W\u00fcrttemberg",
    "wof:name":"Heinrich Herbrich",
    "wof:placetype":"venue"
},
  "geometry": {"coordinates":[9.143496,48.692089],"type":"Point"}
}