{
  "type": "Feature",
  "properties": {
    "iso:country":"DE",
    "sg:address":"Stra\u00dfe des Friedens 8",
    "sg:city":"Fehrbellin",
    "sg:phone":"+49 33932/71001",
    "sg:postcode":"16833",
    "sg:province":"Brandenburg",
    "wof:name":"K\u00f6ppen Und Wille",
    "wof:placetype":"venue"
},
  "geometry": {"coordinates":[12.7641448975,52.8092002869],"type":"Point"}
}