{
  "type": "Feature",
  "properties": {
    "iso:country":"DE",
    "sg:address":"Richard-Thieme-Str.1",
    "sg:city":"Grossr\u00f6hrsdorf",
    "sg:phone":"+49 4935/9523530",
    "sg:postcode":"01900",
    "sg:province":"Sachsen",
    "wof:name":"E.richard Thieme Gmbh",
    "wof:placetype":"venue"
},
  "geometry": {"coordinates":[14.027521,51.152889],"type":"Point"}
}