{
  "type": "Feature",
  "properties": {
    "iso:country":"DE",
    "sg:address":"Gutswiesenweg",
    "sg:city":"F\u00fcrstenwalde",
    "sg:postcode":"15517",
    "sg:province":"Brandenburg",
    "wof:name":"Tbg Kann Beton Verwaltungs Gmbh",
    "wof:placetype":"venue"
},
  "geometry": {"coordinates":[14.0879878998,52.3285560608],"type":"Point"}
}