{
  "type": "Feature",
  "properties": {
    "iso:country":"DE",
    "sg:address":"Flurstrasse 268",
    "sg:city":"Haan",
    "sg:phone":"+49 212/94476",
    "sg:postcode":"42781",
    "sg:province":"Nordrhein-Westfalen",
    "wof:name":"Sos Animal - Ilona Wessel",
    "wof:placetype":"venue"
},
  "geometry": {"coordinates":[6.971702,51.19614],"type":"Point"}
}