{
  "type": "Feature",
  "properties": {
    "iso:country":"DE",
    "sg:address":"S\u00f6gestr. 76",
    "sg:city":"Bremen",
    "sg:phone":"+49 421/168118",
    "sg:postcode":"28195",
    "sg:province":"Bremen",
    "wof:name":"D. Kuhlmann & Sohn",
    "wof:placetype":"venue"
},
  "geometry": {"coordinates":[8.8091096878,53.0788993835],"type":"Point"}
}