{
  "type": "Feature",
  "properties": {
    "iso:country":"DE",
    "sg:address":"Rathausplatz 4",
    "sg:city":"Herzogenrath",
    "sg:phone":"+49 2406/922121",
    "sg:postcode":"52134",
    "sg:province":"Nordrhein-Westfalen",
    "wof:name":"Rudolf Schwarz",
    "wof:placetype":"venue"
},
  "geometry": {"coordinates":[6.1009821892,50.8705673218],"type":"Point"}
}