{
  "type": "Feature",
  "properties": {
    "iso:country":"DE",
    "sg:address":"Talstr 2",
    "sg:city":"Mulda",
    "sg:phone":"+49 37320/840",
    "sg:postcode":"09619",
    "sg:province":"Sachsen",
    "wof:name":"Fenster- Und T\u00fcrenbau Mulda Gmbh",
    "wof:placetype":"venue"
},
  "geometry": {"coordinates":[13.4466152191,50.7989654541],"type":"Point"}
}