{
  "type": "Feature",
  "properties": {
    "iso:country":"DE",
    "sg:address":"Bahnhofstr. 1",
    "sg:city":"Eitorf",
    "sg:phone":"+49 2243/2894",
    "sg:postcode":"53783",
    "sg:province":"Nordrhein-Westfalen",
    "wof:name":"L\u00f6wen-apotheke Inh. Ursula-andrea Crombach",
    "wof:placetype":"venue"
},
  "geometry": {"coordinates":[7.449424,50.771614],"type":"Point"}
}