{
  "type": "Feature",
  "properties": {
    "iso:country":"DE",
    "sg:address":"Hauptstr. 57",
    "sg:city":"Langfurth",
    "sg:phone":"+49 9856/297",
    "sg:postcode":"91731",
    "sg:province":"Bayern",
    "wof:name":"Georg Rothenberger",
    "wof:placetype":"venue"
},
  "geometry": {"coordinates":[10.4552230835,49.1058502197],"type":"Point"}
}