{
  "type": "Feature",
  "properties": {
    "iso:country":"DE",
    "sg:address":"Salomon-Heine-Weg 42 b",
    "sg:city":"Hamburg",
    "sg:phone":"+49 40/335331",
    "sg:postcode":"20251",
    "sg:province":"Hamburg",
    "wof:name":"Hermann J. H. Voth Gmbh",
    "wof:placetype":"venue"
},
  "geometry": {"coordinates":[9.98913,53.599739],"type":"Point"}
}