{
  "type": "Feature",
  "properties": {
    "iso:country":"DE",
    "sg:address":"Buckelstr. 39",
    "sg:city":"Straubenhardt",
    "sg:phone":"+49 7082/2247",
    "sg:postcode":"75334",
    "sg:province":"Baden-W\u00fcrttemberg",
    "wof:name":"Marco Und Sandra Maier",
    "wof:placetype":"venue"
},
  "geometry": {"coordinates":[8.526614,48.844734],"type":"Point"}
}