{
  "type": "Feature",
  "properties": {
    "iso:country":"DE",
    "sg:address":"Niedenau 13-19",
    "sg:city":"Frankfurt",
    "sg:phone":"+49 4969/714030",
    "sg:postcode":"60325",
    "sg:province":"Hessen",
    "wof:name":"Arab Banking Corporation, Daus & Co. Gmbh",
    "wof:placetype":"venue"
},
  "geometry": {"coordinates":[8.663855,50.112144],"type":"Point"}
}