{
  "type": "Feature",
  "properties": {
    "iso:country":"DE",
    "sg:address":"Stolpener Str. 18",
    "sg:city":"Lohmen",
    "sg:phone":"+49 3501/588055",
    "sg:postcode":"01847",
    "sg:province":"Sachsen",
    "wof:name":"Kanne-trans - Transportbetrieb",
    "wof:placetype":"venue"
},
  "geometry": {"coordinates":[14.002358,50.992142],"type":"Point"}
}