{
  "type": "Feature",
  "properties": {
    "iso:country":"DE",
    "sg:address":"Gerberstr. 3",
    "sg:city":"Leipzig",
    "sg:phone":"+49 341/9803044",
    "sg:postcode":"04105",
    "sg:province":"Sachsen",
    "wof:name":"Mertens Consult Grosshandel",
    "wof:placetype":"venue"
},
  "geometry": {"coordinates":[12.376455307,51.3453216553],"type":"Point"}
}