{
  "type": "Feature",
  "properties": {
    "iso:country":"DE",
    "sg:address":"Mulden\u00e4ckerstr. 19",
    "sg:city":"Stuttgart",
    "sg:phone":"+49 711/539297",
    "sg:postcode":"70378",
    "sg:province":"Baden-W\u00fcrttemberg",
    "wof:name":"Johanna Vogt Heissmangel",
    "wof:placetype":"venue"
},
  "geometry": {"coordinates":[9.2369241714,48.834022522],"type":"Point"}
}