{
  "type": "Feature",
  "properties": {
    "iso:country":"DE",
    "sg:address":"Ravensburger Str. 51",
    "sg:city":"Bodnegg",
    "sg:phone":"+49 7520/2375",
    "sg:postcode":"88285",
    "sg:province":"Baden-W\u00fcrttemberg",
    "wof:name":"Georg H\u00e4nsler",
    "wof:placetype":"venue"
},
  "geometry": {"coordinates":[9.685228,47.710823],"type":"Point"}
}