{
  "type": "Feature",
  "properties": {
    "iso:country":"DE",
    "sg:address":"Bremer Str. 5",
    "sg:city":"Osnabr\u00fcck",
    "sg:phone":"+49 541/73011",
    "sg:postcode":"49084",
    "sg:province":"Niedersachsen",
    "wof:name":"G. Luhmann",
    "wof:placetype":"venue"
},
  "geometry": {"coordinates":[8.0696144104,52.2820587158],"type":"Point"}
}