{
  "type": "Feature",
  "properties": {
    "iso:country":"DE",
    "sg:address":"Rosa-Luxemburg-Str. 10",
    "sg:city":"Belzig",
    "sg:phone":"+49 33841/42647",
    "sg:postcode":"14806",
    "sg:province":"Brandenburg",
    "wof:name":"Christa Berg",
    "wof:placetype":"venue"
},
  "geometry": {"coordinates":[12.5906457901,52.1478309631],"type":"Point"}
}