{
  "type": "Feature",
  "properties": {
    "iso:country":"DE",
    "sg:address":"Mutzbroicher Str. 18 a",
    "sg:city":"Odenthal",
    "sg:phone":"+49 2202/78143",
    "sg:postcode":"51519",
    "sg:province":"Nordrhein-Westfalen",
    "wof:name":"Sila-signalbau Gmbh",
    "wof:placetype":"venue"
},
  "geometry": {"coordinates":[7.122236,51.013756],"type":"Point"}
}