{
  "type": "Feature",
  "properties": {
    "iso:country":"DE",
    "sg:address":"J\u00e4gerstr. 42",
    "sg:city":"Duisburg",
    "sg:phone":"+49 203/553288",
    "sg:postcode":"47166",
    "sg:province":"Nordrhein-Westfalen",
    "wof:name":"Dr. Med. Emel Ert\u00fcrk-lakes",
    "wof:placetype":"venue"
},
  "geometry": {"coordinates":[6.7681388855,51.4898109436],"type":"Point"}
}