{
  "type": "Feature",
  "properties": {
    "iso:country":"DE",
    "sg:address":"Dickswall 60",
    "sg:city":"M\u00fclheim",
    "sg:phone":"+49 208/308070",
    "sg:postcode":"45468",
    "sg:province":"Nordrhein-Westfalen",
    "wof:name":"Europcar",
    "wof:placetype":"venue"
},
  "geometry": {"coordinates":[6.890235,51.428886],"type":"Point"}
}