{
  "type": "Feature",
  "properties": {
    "iso:country":"DE",
    "sg:address":"Elbgaustr. 250",
    "sg:city":"Hamburg",
    "sg:phone":"+49 40/8400040",
    "sg:postcode":"22547",
    "sg:province":"Hamburg",
    "wof:name":"He W\u00e4getechnik Horst E\u00dfmann Gmbh",
    "wof:placetype":"venue"
},
  "geometry": {"coordinates":[9.8791503906,53.5909843445],"type":"Point"}
}