{
  "type": "Feature",
  "properties": {
    "iso:country":"DE",
    "sg:address":"Gro\u00dfe Str. 7",
    "sg:city":"Oyten",
    "sg:phone":"+49 4207/2707",
    "sg:postcode":"28876",
    "sg:province":"Niedersachsen",
    "wof:name":"Ernst Zur Jacobsm\u00fchlen",
    "wof:placetype":"venue"
},
  "geometry": {"coordinates":[9.069221,53.060242],"type":"Point"}
}