{
  "type": "Feature",
  "properties": {
    "iso:country":"DE",
    "sg:address":"Ahornallee 25",
    "sg:city":"Uslar",
    "sg:phone":"+49 5574/665",
    "sg:postcode":"37170",
    "sg:province":"Niedersachsen",
    "wof:name":"Karl Elias",
    "wof:placetype":"venue"
},
  "geometry": {"coordinates":[9.645616,51.575726],"type":"Point"}
}