{
  "type": "Feature",
  "properties": {
    "iso:country":"DE",
    "sg:address":"Schwesterngang 1",
    "sg:city":"Kamen",
    "sg:phone":"+49 2307/10049",
    "sg:postcode":"59174",
    "sg:province":"Nordrhein-Westfalen",
    "wof:name":"Ev. Pfarramt",
    "wof:placetype":"venue"
},
  "geometry": {"coordinates":[7.6592497826,51.5909996033],"type":"Point"}
}