{
  "type": "Feature",
  "properties": {
    "iso:country":"DE",
    "sg:address":"St. Annen 54",
    "sg:city":"Stadthagen",
    "sg:phone":"+49 5721/91656",
    "sg:postcode":"31655",
    "sg:province":"Niedersachsen",
    "wof:name":"G. Sundermeyer",
    "wof:placetype":"venue"
},
  "geometry": {"coordinates":[9.1936969757,52.3096046448],"type":"Point"}
}