{
  "type": "Feature",
  "properties": {
    "iso:country":"DE",
    "sg:address":"Buchenweg 30",
    "sg:city":"Reinfeld",
    "sg:phone":"+49 4533/3787",
    "sg:postcode":"23858",
    "sg:province":"Schleswig-Holstein",
    "wof:name":"Esn Edv Service Nord Gmbh",
    "wof:placetype":"venue"
},
  "geometry": {"coordinates":[10.5034294128,53.838924408],"type":"Point"}
}