{
  "type": "Feature",
  "properties": {
    "iso:country":"DE",
    "sg:address":"Friedrich Hebbel Ring 42",
    "sg:city":"24558 Henstedt-Ulzburg",
    "sg:phone":"+49 4193/77583",
    "sg:postcode":"24558",
    "sg:province":"Schleswig-Holstein",
    "wof:name":"German-x-mas",
    "wof:placetype":"venue"
},
  "geometry": {"coordinates":[10.0003175735,53.7506370544],"type":"Point"}
}