{
  "type": "Feature",
  "properties": {
    "iso:country":"DE",
    "sg:address":"Paul-Schwerin-Str. 5",
    "sg:city":"Frankfurt",
    "sg:phone":"+49 69/30851600",
    "sg:postcode":"65929",
    "sg:province":"Hessen",
    "wof:name":"Hotze Und Kollegen",
    "wof:placetype":"venue"
},
  "geometry": {"coordinates":[8.5471258163,50.1067771912],"type":"Point"}
}