{
  "type": "Feature",
  "properties": {
    "iso:country":"DE",
    "sg:address":"Schillerstr. 51",
    "sg:city":"Karlsruhe",
    "sg:phone":"+49 721/845284",
    "sg:postcode":"76135",
    "sg:province":"Baden-W\u00fcrttemberg",
    "wof:name":"Rolf Meinzer Malerbetrieb Inh. Nonnenmacher E. K.",
    "wof:placetype":"venue"
},
  "geometry": {"coordinates":[8.378519,49.006374],"type":"Point"}
}