{
  "type": "Feature",
  "properties": {
    "iso:country":"DE",
    "sg:address":"Fischergasse 3",
    "sg:city":"Triefenstein",
    "sg:phone":"+49 9395/531",
    "sg:postcode":"97855",
    "sg:province":"Bayern",
    "wof:name":"M. Und L. Eizenh\u00f6fer",
    "wof:placetype":"venue"
},
  "geometry": {"coordinates":[9.6032905579,49.8101081848],"type":"Point"}
}