{
  "type": "Feature",
  "properties": {
    "iso:country":"DE",
    "sg:address":"Bahnhofstr. 21",
    "sg:city":"Garmisch-Partenkirchen",
    "sg:phone":"+49 8821/73773",
    "sg:postcode":"82467",
    "sg:province":"Bayern",
    "wof:name":"Bernhard Und Christine Ostmann",
    "wof:placetype":"venue"
},
  "geometry": {"coordinates":[11.099347,47.491695],"type":"Point"}
}