{
  "type": "Feature",
  "properties": {
    "iso:country":"DE",
    "sg:address":"Bergstr. 11",
    "sg:city":"Burgwedel",
    "sg:phone":"+49 5139/7214",
    "sg:postcode":"30938",
    "sg:province":"Niedersachsen",
    "wof:name":"Alb. Lindemann",
    "wof:placetype":"venue"
},
  "geometry": {"coordinates":[9.880554,52.51059],"type":"Point"}
}