{
  "type": "Feature",
  "properties": {
    "iso:country":"DE",
    "sg:address":"Turnstr. 13",
    "sg:city":"Sontheim",
    "sg:phone":"+49 7325/5132",
    "sg:postcode":"89567",
    "sg:province":"Baden-W\u00fcrttemberg",
    "wof:name":"G. Schurr",
    "wof:placetype":"venue"
},
  "geometry": {"coordinates":[10.2931451797,48.5639724731],"type":"Point"}
}