{
  "type": "Feature",
  "properties": {
    "iso:country":"DE",
    "sg:address":"Oberwerder Damm 1-5",
    "sg:city":"Hamburg",
    "sg:postcode":"20539",
    "sg:province":"Hamburg",
    "wof:name":"Jennys World Ag",
    "wof:placetype":"venue"
},
  "geometry": {"coordinates":[10.029704,53.527828],"type":"Point"}
}