{
  "type": "Feature",
  "properties": {
    "iso:country":"DE",
    "sg:address":"T\u00f6ft 3",
    "sg:city":"Wyk",
    "sg:phone":"+49 4681/2601",
    "sg:postcode":"25938",
    "sg:province":"Schleswig-Holstein",
    "wof:name":"Armin Nahmens Ferrienhausvermietung",
    "wof:placetype":"venue"
},
  "geometry": {"coordinates":[8.5612878799,54.6945152283],"type":"Point"}
}