{
  "type": "Feature",
  "properties": {
    "iso:country":"DE",
    "sg:address":"M\u00f6hnestr. 2",
    "sg:city":"Hanau",
    "sg:phone":"+49 6181/15489",
    "sg:postcode":"63452",
    "sg:province":"Hessen",
    "wof:name":"Gefaco Gmbh",
    "wof:placetype":"venue"
},
  "geometry": {"coordinates":[8.937794,50.144928],"type":"Point"}
}