{
  "type": "Feature",
  "properties": {
    "iso:country":"DE",
    "sg:address":"Dr.-Willi-Bermann-Str. 14",
    "sg:city":"St. Andreasberg",
    "sg:phone":"+49 4955/82291",
    "sg:postcode":"37444",
    "sg:province":"Niedersachsen",
    "wof:name":"Volksbank Im Harz",
    "wof:placetype":"venue"
},
  "geometry": {"coordinates":[10.519655,51.711021],"type":"Point"}
}