{
  "type": "Feature",
  "properties": {
    "iso:country":"DE",
    "sg:address":"Borstr. 23",
    "sg:city":"Radebeul",
    "sg:phone":"+49 351/8302793",
    "sg:postcode":"01445",
    "sg:province":"Sachsen",
    "wof:name":"P\u00e4dagogisch-soziale Arbeits- Gemeinschaft E. V.",
    "wof:placetype":"venue"
},
  "geometry": {"coordinates":[13.649731636,51.1066894531],"type":"Point"}
}