{
  "type": "Feature",
  "properties": {
    "iso:country":"DE",
    "sg:address":"Stahlenstr. 36a",
    "sg:city":"Niederkassel",
    "sg:phone":"+49 2208/73452",
    "sg:postcode":"53859",
    "sg:province":"Nordrhein-Westfalen",
    "wof:name":"Blumen & Pflanzen Mohr Gmbh",
    "wof:placetype":"venue"
},
  "geometry": {"coordinates":[7.004093,50.830963],"type":"Point"}
}