{
  "type": "Feature",
  "properties": {
    "iso:country":"DE",
    "sg:address":"Munzeler Str. 25",
    "sg:city":"Hannover",
    "sg:phone":"+49 511/425025",
    "sg:postcode":"30459",
    "sg:province":"Niedersachsen",
    "wof:name":"Ledigenwohnheim Des Jugendsozialwerk E. V.",
    "wof:placetype":"venue"
},
  "geometry": {"coordinates":[9.7001657486,52.3450202942],"type":"Point"}
}