{
  "type": "Feature",
  "properties": {
    "iso:country":"DE",
    "sg:address":"Friedensh\u00f6he 22 a",
    "sg:city":"Hasbergen",
    "sg:phone":"+49 5405/4266",
    "sg:postcode":"49205",
    "sg:province":"Niedersachsen",
    "wof:name":"Stratemeier Akustik- Und Trockenbau Gmbh",
    "wof:placetype":"venue"
},
  "geometry": {"coordinates":[7.946213,52.236053],"type":"Point"}
}