{
  "type": "Feature",
  "properties": {
    "iso:country":"DE",
    "sg:address":"Blumenesch 18",
    "sg:city":"Osnabr\u00fcck",
    "sg:phone":"+49 541/433399",
    "sg:postcode":"49078",
    "sg:province":"Niedersachsen",
    "wof:name":"Helmut Andermann Architekt",
    "wof:placetype":"venue"
},
  "geometry": {"coordinates":[8.019754,52.269047],"type":"Point"}
}