{
  "type": "Feature",
  "properties": {
    "iso:country":"DE",
    "sg:address":"Diekamp 3",
    "sg:city":"Warendorf",
    "sg:phone":"+49 2581/2849",
    "sg:postcode":"48231",
    "sg:province":"Nordrhein-Westfalen",
    "wof:name":"Heribert M\u00f6llmann Architekt",
    "wof:placetype":"venue"
},
  "geometry": {"coordinates":[7.994857,51.948196],"type":"Point"}
}