{
  "type": "Feature",
  "properties": {
    "iso:country":"DE",
    "sg:address":"Im Meienthun 25",
    "sg:city":"Hamburg",
    "sg:phone":"+49 40/60950985",
    "sg:postcode":"22359",
    "sg:province":"Hamburg",
    "wof:name":"Frank Freese Hochbau- Tiefbau Gmbh",
    "wof:placetype":"venue"
},
  "geometry": {"coordinates":[10.1906633377,53.6424026489],"type":"Point"}
}