{
  "type": "Feature",
  "properties": {
    "iso:country":"DE",
    "sg:address":"Feldstr. 21",
    "sg:city":"Dreieich",
    "sg:phone":"+49 6103/985753",
    "sg:postcode":"63303",
    "sg:province":"Hessen",
    "wof:name":"King Verpackungsmaschinen Gmbh",
    "wof:placetype":"venue"
},
  "geometry": {"coordinates":[8.733078,50.000633],"type":"Point"}
}