{
  "type": "Feature",
  "properties": {
    "iso:country":"DE",
    "sg:address":"Wiesenring 16",
    "sg:city":"Fl\u00f6rsheim",
    "sg:phone":"+49 6145/33977",
    "sg:postcode":"65439",
    "sg:province":"Hessen",
    "wof:name":"Siegfried Petersen",
    "wof:placetype":"venue"
},
  "geometry": {"coordinates":[8.435606,50.040749],"type":"Point"}
}