{
  "type": "Feature",
  "properties": {
    "iso:country":"DE",
    "sg:address":"Handelsstr 1",
    "sg:city":"Ganderkesee",
    "sg:phone":"+49 4222/93060",
    "sg:postcode":"27777",
    "sg:province":"Niedersachsen",
    "wof:name":"Cetex-rheinfaser Gmbh",
    "wof:placetype":"venue"
},
  "geometry": {"coordinates":[8.534715,53.031876],"type":"Point"}
}