{
  "type": "Feature",
  "properties": {
    "iso:country":"DE",
    "sg:address":"Starenschleife 96",
    "sg:city":"Hamm",
    "sg:phone":"+49 2381/980280",
    "sg:postcode":"59071",
    "sg:province":"Nordrhein-Westfalen",
    "wof:name":"C. Hala Steuerberater",
    "wof:placetype":"venue"
},
  "geometry": {"coordinates":[7.873568058,51.6844329834],"type":"Point"}
}