{
  "type": "Feature",
  "properties": {
    "iso:country":"DE",
    "sg:address":"L\u00fcningsweg 1 a",
    "sg:city":"Hatten",
    "sg:phone":"+49 4481/92840",
    "sg:postcode":"26209",
    "sg:province":"Niedersachsen",
    "wof:name":"Hartmut Ricker Steuerberater",
    "wof:placetype":"venue"
},
  "geometry": {"coordinates":[8.2711143494,53.0611000061],"type":"Point"}
}