{
  "type": "Feature",
  "properties": {
    "iso:country":"DE",
    "sg:address":"Gratzm\u00fcllerstr. 3",
    "sg:city":"Augsburg",
    "sg:phone":"+49 821/151096",
    "sg:postcode":"86150",
    "sg:province":"Bayern",
    "wof:name":"Josef Spielbichler Rechtsanwalt",
    "wof:placetype":"venue"
},
  "geometry": {"coordinates":[10.893330574,48.361240387],"type":"Point"}
}