{
  "type": "Feature",
  "properties": {
    "iso:country":"DE",
    "sg:address":"Gustav-Heinemann-Str 41",
    "sg:city":"Schwerte",
    "sg:phone":"+49 5541/4747",
    "sg:postcode":"58239",
    "sg:province":"Nordrhein-Westfalen",
    "wof:name":"Gfm Ges.f\u00fcr Mikroelektronik Mbh & Co Kg",
    "wof:placetype":"venue"
},
  "geometry": {"coordinates":[9.6501731873,51.4304580688],"type":"Point"}
}