{
  "type": "Feature",
  "properties": {
    "iso:country":"DE",
    "sg:address":"Schrenkstr. 11",
    "sg:city":"Deggendorf",
    "sg:postcode":"94469",
    "sg:province":"Bayern",
    "wof:name":"Schmei\u00dfer Gmbh & Co. Kg",
    "wof:placetype":"venue"
},
  "geometry": {"coordinates":[12.9768838882,48.8484802246],"type":"Point"}
}