{
  "type": "Feature",
  "properties": {
    "iso:country":"DE",
    "sg:address":"Liebenberger Damm 25",
    "sg:city":"Neuholland",
    "sg:phone":"+49 33054/61464",
    "sg:postcode":"16515",
    "sg:province":"Brandenburg",
    "wof:name":"Bernd Ewert",
    "wof:placetype":"venue"
},
  "geometry": {"coordinates":[13.322948,52.859035],"type":"Point"}
}