{
  "type": "Feature",
  "properties": {
    "iso:country":"DE",
    "sg:address":"Vater-Jahn-Str. 1",
    "sg:city":"Zeitz",
    "sg:phone":"+49 3441/251562",
    "sg:postcode":"06712",
    "sg:province":"Sachsen-Anhalt",
    "wof:name":"Christel Holland",
    "wof:placetype":"venue"
},
  "geometry": {"coordinates":[12.1421785355,51.0458984375],"type":"Point"}
}