{
  "type": "Feature",
  "properties": {
    "iso:country":"DE",
    "sg:address":"Gsteinacher Str. 24",
    "sg:city":"Schwarzenbruck",
    "sg:phone":"+49 9128/13632",
    "sg:postcode":"90592",
    "sg:province":"Bayern",
    "wof:name":"Erhard Winterstein",
    "wof:placetype":"venue"
},
  "geometry": {"coordinates":[11.250371933,49.3608474731],"type":"Point"}
}