{
  "type": "Feature",
  "properties": {
    "iso:country":"DE",
    "sg:address":"Markt 28",
    "sg:city":"Straelen",
    "sg:phone":"+49 2834/464",
    "sg:postcode":"47638",
    "sg:province":"Nordrhein-Westfalen",
    "wof:name":"Zum Goldenen Herzen",
    "wof:placetype":"venue"
},
  "geometry": {"coordinates":[6.2669591904,51.4451560974],"type":"Point"}
}