{
  "type": "Feature",
  "properties": {
    "iso:country":"DE",
    "sg:address":"Steinbeker Hauptstr. 79",
    "sg:city":"Hamburg",
    "sg:phone":"+49 40/7131056",
    "sg:postcode":"22117",
    "sg:province":"Hamburg",
    "wof:name":"Steinbeker Reise-markt",
    "wof:placetype":"venue"
},
  "geometry": {"coordinates":[10.1258401871,53.5301399231],"type":"Point"}
}