{
  "type": "Feature",
  "properties": {
    "iso:country":"DE",
    "sg:address":"Sandgasse 17",
    "sg:city":"Aschaffenburg",
    "sg:phone":"+49 6021/27773",
    "sg:postcode":"63739",
    "sg:province":"Bayern",
    "wof:name":"Martins-apotheke In. Marion Eberle-mohy El Din",
    "wof:placetype":"venue"
},
  "geometry": {"coordinates":[9.147855,49.974705],"type":"Point"}
}