{
  "type": "Feature",
  "properties": {
    "iso:country":"DE",
    "sg:address":"Wimenweg 6",
    "sg:city":"Viersen",
    "sg:phone":"+49 2153/12340",
    "sg:postcode":"41751",
    "sg:province":"Nordrhein-Westfalen",
    "wof:name":"Jakob Hoersch",
    "wof:placetype":"venue"
},
  "geometry": {"coordinates":[6.2778391838,51.2747879028],"type":"Point"}
}