{
  "type": "Feature",
  "properties": {
    "iso:country":"DE",
    "sg:address":"Thomas-M\u00fcntzer-Str. 7",
    "sg:city":"Lehnitz",
    "sg:phone":"+49 3301/701548",
    "sg:postcode":"16565",
    "wof:name":"Dr. Angelika K\u00fcster Heilpraktikerin",
    "wof:placetype":"venue"
},
  "geometry": {"coordinates":[13.2648801804,52.7452774048],"type":"Point"}
}