{
  "type": "Feature",
  "properties": {
    "iso:country":"DE",
    "sg:address":"Leimgrubengasse 4",
    "sg:city":"Freiburg",
    "sg:phone":"+49 761/52393",
    "sg:postcode":"79104",
    "sg:province":"Baden-W\u00fcrttemberg",
    "wof:name":"Kopf Fliesenfachgesch\u00e4ft Gmbh",
    "wof:placetype":"venue"
},
  "geometry": {"coordinates":[7.8674840927,48.0238952637],"type":"Point"}
}