{
  "type": "Feature",
  "properties": {
    "iso:country":"DE",
    "sg:address":"Klever Str 342",
    "sg:city":"Goch",
    "sg:phone":"+49 2823/4519",
    "sg:postcode":"47574",
    "sg:province":"Nordrhein-Westfalen",
    "wof:name":"Vd1 Eco Sl",
    "wof:placetype":"venue"
},
  "geometry": {"coordinates":[6.15765,51.71035],"type":"Point"}
}