{
  "type": "Feature",
  "properties": {
    "iso:country":"DE",
    "sg:address":"Neum\u00e4rker Str. 4",
    "sg:city":"Helmstedt",
    "sg:phone":"+49 5351/40800",
    "sg:postcode":"38350",
    "sg:province":"Niedersachsen",
    "wof:name":"Walter Weichbrodt Vergn\u00fcgungsst\u00e4tte",
    "wof:placetype":"venue"
},
  "geometry": {"coordinates":[11.009151,52.227791],"type":"Point"}
}