{
  "type": "Feature",
  "properties": {
    "iso:country":"DE",
    "sg:address":"Schleusenstr 5",
    "sg:city":"Hattingen",
    "sg:phone":"+49 2324/92000",
    "sg:postcode":"45525",
    "sg:province":"Nordrhein-Westfalen",
    "wof:name":"Rauh-damm-stiller-partner Planungsgesellschaft Mbh",
    "wof:placetype":"venue"
},
  "geometry": {"coordinates":[7.1710557938,51.4034614563],"type":"Point"}
}