{
  "type": "Feature",
  "properties": {
    "iso:country":"DE",
    "sg:address":"Els\u00e4sser Str. 67",
    "sg:city":"Freiburg",
    "sg:phone":"+49 761/8095640",
    "sg:postcode":"79110",
    "sg:province":"Baden-W\u00fcrttemberg",
    "wof:name":"Restaurant Westtreff",
    "wof:placetype":"venue"
},
  "geometry": {"coordinates":[7.8243331909,48.0149421692],"type":"Point"}
}