{
  "type": "Feature",
  "properties": {
    "iso:country":"DE",
    "sg:address":"Sophienstr. 3",
    "sg:city":"Jena",
    "sg:phone":"+49 3641/826723",
    "sg:postcode":"07743",
    "sg:province":"Th\u00fcringen",
    "wof:name":"Amon Und Holtkamp Rechtsanw\u00e4lte",
    "wof:placetype":"venue"
},
  "geometry": {"coordinates":[11.5883398056,50.9314842224],"type":"Point"}
}