{
  "type": "Feature",
  "properties": {
    "iso:country":"DE",
    "sg:address":"Mecklenburger Weg 126",
    "sg:city":"Bremerhaven",
    "sg:phone":"+49 471/64535",
    "sg:postcode":"27578",
    "sg:province":"Bremen",
    "wof:name":"Hansa-apotheke",
    "wof:placetype":"venue"
},
  "geometry": {"coordinates":[8.617797,53.59338],"type":"Point"}
}