{
  "type": "Feature",
  "properties": {
    "iso:country":"DE",
    "sg:address":"L\u00f6bdergraben 23",
    "sg:city":"Jena",
    "sg:phone":"+49 3641/441712",
    "sg:postcode":"07743",
    "sg:province":"Th\u00fcringen",
    "wof:name":"A. Schmidt",
    "wof:placetype":"venue"
},
  "geometry": {"coordinates":[11.590665,50.927818],"type":"Point"}
}