{
  "type": "Feature",
  "properties": {
    "iso:country":"DE",
    "sg:address":"Friedelsheimer Str. 9",
    "sg:city":"Bad D\u00fcrkheim",
    "sg:phone":"+49 6322/63698",
    "sg:postcode":"67098",
    "sg:province":"Rheinland-Pfalz",
    "wof:name":"Werner F. Freunscht Weinanbau",
    "wof:placetype":"venue"
},
  "geometry": {"coordinates":[8.1742229462,49.45652771],"type":"Point"}
}