{
  "type": "Feature",
  "properties": {
    "iso:country":"DE",
    "sg:address":"Steinmauerweg 9e",
    "sg:city":"Lauf",
    "sg:phone":"+49 7841/25296",
    "sg:postcode":"77886",
    "sg:province":"Baden-W\u00fcrttemberg",
    "wof:name":"Metcon E. K.",
    "wof:placetype":"venue"
},
  "geometry": {"coordinates":[8.12854,48.65036],"type":"Point"}
}