{
  "type": "Feature",
  "properties": {
    "iso:country":"DE",
    "sg:address":"L\u00fcnener Str. 128",
    "sg:city":"Hamm",
    "sg:postcode":"59077",
    "sg:province":"Nordrhein-Westfalen",
    "wof:name":"Vvt-verm\u00f6gensverwaltungs- Und Treuhand-gmbh",
    "wof:placetype":"venue"
},
  "geometry": {"coordinates":[7.7381920815,51.6720199585],"type":"Point"}
}