{
  "type": "Feature",
  "properties": {
    "iso:country":"DE",
    "sg:address":"Glingestr. 95",
    "sg:city":"Finnentrop",
    "sg:phone":"+49 2395/16940",
    "sg:postcode":"57413",
    "sg:province":"Nordrhein-Westfalen",
    "wof:name":"Marlene Burkhardt Heilpraktikerin",
    "wof:placetype":"venue"
},
  "geometry": {"coordinates":[7.9642691612,51.2212257385],"type":"Point"}
}