{
  "type": "Feature",
  "properties": {
    "iso:country":"DE",
    "sg:address":"Stuttgarter Str. 53 Maichingen",
    "sg:city":"Sindelfingen",
    "sg:phone":"+49 4970/3173650",
    "sg:postcode":"71069",
    "sg:province":"Baden-W\u00fcrttemberg",
    "wof:name":"Getr\u00c4nkehandlung Klauss Gmbh",
    "wof:placetype":"venue"
},
  "geometry": {"coordinates":[8.964045,48.724449],"type":"Point"}
}