{
  "type": "Feature",
  "properties": {
    "iso:country":"DE",
    "sg:address":"Zum Ackerberg 29",
    "sg:city":"Braunschweig",
    "sg:phone":"+49 531/62696",
    "sg:postcode":"38126",
    "sg:province":"Niedersachsen",
    "wof:name":"Raumausstattungen K\u00f6pper In Braunschweig",
    "wof:placetype":"venue"
},
  "geometry": {"coordinates":[10.585805,52.23888],"type":"Point"}
}