{
  "type": "Feature",
  "properties": {
    "iso:country":"DE",
    "sg:address":"Stegerhof 1",
    "sg:city":"Gerolsbach",
    "sg:phone":"+49 8445/799",
    "sg:postcode":"85302",
    "sg:province":"Bayern",
    "wof:name":"Golfclub Gerolsbach E.v.",
    "wof:placetype":"venue"
},
  "geometry": {"coordinates":[11.3609075546,48.4942626953],"type":"Point"}
}