{
  "type": "Feature",
  "properties": {
    "iso:country":"DE",
    "sg:address":"Lutherstr. 39",
    "sg:city":"Lutherstadt Wittenberg",
    "sg:phone":"+49 3491/402620",
    "sg:postcode":"06886",
    "sg:province":"Sachsen-Anhalt",
    "wof:name":"B\u00c4ko Wittenberg B\u00e4cker- Und Konditoren Genossenschaft Eg",
    "wof:placetype":"venue"
},
  "geometry": {"coordinates":[12.631833,51.878517],"type":"Point"}
}