{
  "type": "Feature",
  "properties": {
    "iso:country":"DE",
    "sg:address":"Windthorststr. 20",
    "sg:city":"M\u00fcnster",
    "sg:phone":"+49 251/510270",
    "sg:postcode":"48143",
    "sg:province":"Nordrhein-Westfalen",
    "wof:name":"W\u00fcrttembergische Versicherung Ag",
    "wof:placetype":"venue"
},
  "geometry": {"coordinates":[7.6320710182,51.9574356079],"type":"Point"}
}