{
  "type": "Feature",
  "properties": {
    "iso:country":"DE",
    "sg:address":"Leydenallee 84",
    "sg:city":"Berlin",
    "sg:postcode":"12167",
    "sg:province":"Berlin",
    "wof:name":"Pro Block Service Gmbh",
    "wof:placetype":"venue"
},
  "geometry": {"coordinates":[13.3245449066,52.4535179138],"type":"Point"}
}