{
  "type": "Feature",
  "properties": {
    "iso:country":"DE",
    "sg:address":"Horster Allee 9",
    "sg:city":"Hilden",
    "sg:phone":"+49 2103/55530",
    "sg:postcode":"40721",
    "sg:province":"Nordrhein-Westfalen",
    "wof:name":"Milan Puskaric Rohrleitungsbau",
    "wof:placetype":"venue"
},
  "geometry": {"coordinates":[6.90751791,51.1545028687],"type":"Point"}
}