{
  "type": "Feature",
  "properties": {
    "iso:country":"DE",
    "sg:address":"Grenzwehr 57",
    "sg:city":"Bremen",
    "sg:phone":"+49 421/420116",
    "sg:postcode":"28325",
    "sg:province":"Bremen",
    "wof:name":"Wilhelm Hanemann Fleischereibedarf",
    "wof:placetype":"venue"
},
  "geometry": {"coordinates":[8.9373178482,53.0734901428],"type":"Point"}
}