{
  "type": "Feature",
  "properties": {
    "iso:country":"DE",
    "sg:address":"Im Dorfe 38",
    "sg:city":"Hetschburg",
    "sg:postcode":"99438",
    "sg:province":"Th\u00fcringen",
    "wof:name":"Andreas Schwarz",
    "wof:placetype":"venue"
},
  "geometry": {"coordinates":[11.298934,50.91275],"type":"Point"}
}