{
  "type": "Feature",
  "properties": {
    "iso:country":"DE",
    "sg:address":"Hans-Beimler-Str. 1-3",
    "sg:city":"Greifswald",
    "sg:postcode":"17491",
    "sg:province":"Mecklenburg-Vorpommern",
    "wof:name":"Systempartner Computer- Vertriebs Gmbh",
    "wof:placetype":"venue"
},
  "geometry": {"coordinates":[13.397644,54.088539],"type":"Point"}
}