{
  "type": "Feature",
  "properties": {
    "iso:country":"DE",
    "sg:address":"Kufsteiner Str. 36",
    "sg:city":"Duisburg",
    "sg:phone":"+49 203/701753",
    "sg:postcode":"47249",
    "sg:province":"Nordrhein-Westfalen",
    "wof:name":"Bernhard Weller",
    "wof:placetype":"venue"
},
  "geometry": {"coordinates":[6.763176918,51.3825492859],"type":"Point"}
}