{
  "type": "Feature",
  "properties": {
    "iso:country":"DE",
    "sg:address":"Kirchstr. 12",
    "sg:city":"M\u00f6ssingen",
    "sg:phone":"+49 7473/6258",
    "sg:postcode":"72116",
    "sg:province":"Baden-W\u00fcrttemberg",
    "wof:name":"Ev. Pfarramt Pancratius- Und Cyriacuskirche Talheim",
    "wof:placetype":"venue"
},
  "geometry": {"coordinates":[9.1104278564,48.3856430054],"type":"Point"}
}