{
  "type": "Feature",
  "properties": {
    "iso:country":"DE",
    "sg:address":"Waldstr. 24",
    "sg:city":"Sandhausen",
    "sg:phone":"+49 6224/82442",
    "sg:postcode":"69207",
    "sg:province":"Baden-W\u00fcrttemberg",
    "wof:name":"E. St\u00e4hle",
    "wof:placetype":"venue"
},
  "geometry": {"coordinates":[8.655602,49.341881],"type":"Point"}
}