{
  "type": "Feature",
  "properties": {
    "iso:country":"DE",
    "sg:address":"Berliner Str. 11",
    "sg:city":"Emmerthal",
    "sg:phone":"+49 5155/7873",
    "sg:postcode":"31860",
    "sg:province":"Niedersachsen",
    "wof:name":"Miramare-eiscafe",
    "wof:placetype":"venue"
},
  "geometry": {"coordinates":[9.387326,52.043301],"type":"Point"}
}