{
  "type": "Feature",
  "properties": {
    "iso:country":"DE",
    "sg:address":"Konstantinplatz 3",
    "sg:city":"M\u00f6nchengladbach",
    "sg:phone":"+49 2166/87437",
    "sg:postcode":"41238",
    "sg:province":"Nordrhein-Westfalen",
    "wof:name":"Apotheke Am Markt Rotraut Eglie E. Kfr.",
    "wof:placetype":"venue"
},
  "geometry": {"coordinates":[6.490136,51.155762],"type":"Point"}
}