{
  "type": "Feature",
  "properties": {
    "iso:country":"DE",
    "sg:address":"Memminger Str. 16",
    "sg:city":"Ottobeuren",
    "sg:phone":"+49 8332/236",
    "sg:postcode":"87724",
    "sg:province":"Bayern",
    "wof:name":"Plersch Inh. Monika Huith",
    "wof:placetype":"venue"
},
  "geometry": {"coordinates":[10.295582,47.943104],"type":"Point"}
}