{
  "type": "Feature",
  "properties": {
    "iso:country":"DE",
    "sg:address":"Goethestr. 73",
    "sg:city":"Wipperdorf",
    "sg:phone":"+49 36338/60591",
    "sg:postcode":"99752",
    "sg:province":"Th\u00fcringen",
    "wof:name":"Dieter Schmidt",
    "wof:placetype":"venue"
},
  "geometry": {"coordinates":[10.650055,51.453602],"type":"Point"}
}