{
  "type": "Feature",
  "properties": {
    "iso:country":"DE",
    "sg:address":"Rostocker Str. 55",
    "sg:city":"Bonn",
    "sg:phone":"+49 228/673677",
    "sg:postcode":"53117",
    "sg:province":"Nordrhein-Westfalen",
    "wof:name":"Manfred Werner",
    "wof:placetype":"venue"
},
  "geometry": {"coordinates":[7.0523281097,50.7640724182],"type":"Point"}
}