{
  "type": "Feature",
  "properties": {
    "iso:country":"DE",
    "sg:address":"Gartenstr. 6a",
    "sg:city":"Freyung",
    "sg:phone":"+49 8551/2156",
    "sg:postcode":"94078",
    "sg:province":"Bayern",
    "wof:name":"Heinz Herzig",
    "wof:placetype":"venue"
},
  "geometry": {"coordinates":[13.5516376495,48.8056983948],"type":"Point"}
}