{
  "type": "Feature",
  "properties": {
    "iso:country":"DE",
    "sg:address":"Dienerreihe 2",
    "sg:city":"Hamburg",
    "sg:postcode":"20457",
    "sg:province":"Hamburg",
    "wof:name":"Aldebaran Marine Research & Broadcast Redationb\u00fcro",
    "wof:placetype":"venue"
},
  "geometry": {"coordinates":[9.9993667603,53.5456047058],"type":"Point"}
}