{
  "type": "Feature",
  "properties": {
    "iso:country":"DE",
    "sg:address":"Wawerner Str. 1",
    "sg:city":"Lasel",
    "sg:postcode":"54612",
    "sg:province":"Rheinland-Pfalz",
    "wof:name":"Business Center Cardservice E. K.",
    "wof:placetype":"venue"
},
  "geometry": {"coordinates":[6.469799,50.114265],"type":"Point"}
}