{
  "type": "Feature",
  "properties": {
    "iso:country":"DE",
    "sg:address":"Kleine Seite 19",
    "sg:city":"Hainewalde",
    "sg:phone":"+49 35841/2042",
    "sg:postcode":"02779",
    "sg:province":"Sachsen",
    "wof:name":"Margita Heidrich",
    "wof:placetype":"venue"
},
  "geometry": {"coordinates":[14.704738,50.911079],"type":"Point"}
}