{
  "type": "Feature",
  "properties": {
    "iso:country":"DE",
    "sg:address":"Swalmener Str. 3",
    "sg:city":"Br\u00fcggen",
    "sg:phone":"+49 2163/95440",
    "sg:postcode":"41379",
    "sg:province":"Nordrhein-Westfalen",
    "wof:name":"Br\u00fcggener Gmbh",
    "wof:placetype":"venue"
},
  "geometry": {"coordinates":[6.1503591537,51.2421798706],"type":"Point"}
}