{
  "type": "Feature",
  "properties": {
    "iso:country":"DE",
    "sg:address":"Rheinstr. 44-46",
    "sg:city":"Berlin",
    "sg:phone":"+49 30/85999045",
    "sg:postcode":"12161",
    "sg:province":"Berlin",
    "wof:name":"Vinh-loi Asiatische Spezialit\u00e4ten Truong",
    "wof:placetype":"venue"
},
  "geometry": {"coordinates":[13.3301563263,52.4661331177],"type":"Point"}
}