{
  "type": "Feature",
  "properties": {
    "iso:country":"DE",
    "sg:address":"Hauptstr. 39",
    "sg:city":"Gorden",
    "sg:phone":"+49 35325/660",
    "sg:postcode":"03238",
    "sg:province":"Brandenburg",
    "wof:name":"Bierst\u00fcbchen",
    "wof:placetype":"venue"
},
  "geometry": {"coordinates":[13.6293373108,51.534412384],"type":"Point"}
}