{
  "type": "Feature",
  "properties": {
    "iso:country":"DE",
    "sg:address":"Gr\u00fcner Weg 16",
    "sg:city":"Adendorf",
    "sg:phone":"+49 4131/18300",
    "sg:postcode":"21365",
    "sg:province":"Niedersachsen",
    "wof:name":"Horst Ruthemann",
    "wof:placetype":"venue"
},
  "geometry": {"coordinates":[10.4350299835,53.2721748352],"type":"Point"}
}