{
  "type": "Feature",
  "properties": {
    "iso:country":"DE",
    "sg:address":"Horber Str. 1",
    "sg:city":"Empfingen",
    "sg:phone":"+49 7485/581",
    "sg:postcode":"72186",
    "sg:province":"Baden-W\u00fcrttemberg",
    "wof:name":"Marlene Gaus Masseurin",
    "wof:placetype":"venue"
},
  "geometry": {"coordinates":[8.708212,48.393116],"type":"Point"}
}