{
  "type": "Feature",
  "properties": {
    "iso:country":"DE",
    "sg:address":"Mainzer Str. 85",
    "sg:city":"Idar-Oberstein",
    "sg:phone":"+49 6781/94820",
    "sg:postcode":"55743",
    "sg:province":"Rheinland-Pfalz",
    "wof:name":"R. Fritsch",
    "wof:placetype":"venue"
},
  "geometry": {"coordinates":[7.306137085,49.7166633606],"type":"Point"}
}