{
  "type": "Feature",
  "properties": {
    "iso:country":"DE",
    "sg:address":"Kommandantenstr. 8",
    "sg:city":"Berlin",
    "sg:phone":"+49 30/8115835",
    "sg:postcode":"12205",
    "sg:province":"Berlin",
    "wof:name":"Dietrich D\u00f6pping Architekt",
    "wof:placetype":"venue"
},
  "geometry": {"coordinates":[13.293085,52.438835],"type":"Point"}
}