{
  "type": "Feature",
  "properties": {
    "iso:country":"DE",
    "sg:address":"Friedhofstr. 1",
    "sg:city":"Lichtenfels",
    "sg:phone":"+49 9571/2606",
    "sg:postcode":"96215",
    "sg:province":"Bayern",
    "wof:name":"Fritz Werner Grabdenkm\u00e4ler",
    "wof:placetype":"venue"
},
  "geometry": {"coordinates":[11.069732666,50.1455459595],"type":"Point"}
}