{
  "type": "Feature",
  "properties": {
    "iso:country":"DE",
    "sg:address":"Ziegeleiweg 28",
    "sg:city":"Oyten",
    "sg:phone":"+49 4207/4138",
    "sg:postcode":"28876",
    "sg:province":"Niedersachsen",
    "wof:name":"Johannes Jaxy",
    "wof:placetype":"venue"
},
  "geometry": {"coordinates":[9.007686,53.0788],"type":"Point"}
}