{
  "type": "Feature",
  "properties": {
    "iso:country":"DE",
    "sg:address":"Halmersreihe 11",
    "sg:city":"Sundern",
    "sg:phone":"+49 161 6209410",
    "sg:postcode":"59846",
    "sg:province":"Nordrhein-Westfalen",
    "wof:name":"Josef Hellhake-serres",
    "wof:placetype":"venue"
},
  "geometry": {"coordinates":[7.95292,51.28347],"type":"Point"}
}