{
  "type": "Feature",
  "properties": {
    "iso:country":"DE",
    "sg:address":"Zillestr. 69a",
    "sg:city":"Dortmund",
    "sg:phone":"+49 231/469008",
    "sg:postcode":"44265",
    "sg:province":"Nordrhein-Westfalen",
    "wof:name":"G. Lehmann",
    "wof:placetype":"venue"
},
  "geometry": {"coordinates":[7.4870400429,51.4738464355],"type":"Point"}
}