{
  "type": "Feature",
  "properties": {
    "iso:country":"DE",
    "sg:address":"Birkenriedstr. 14",
    "sg:city":"Stephanskirchen",
    "sg:phone":"+49 8036/4693",
    "sg:postcode":"83071",
    "sg:province":"Bayern",
    "wof:name":"Tr Immobilien Verwaltungs- Gmbh",
    "wof:placetype":"venue"
},
  "geometry": {"coordinates":[12.1623697281,47.8553886414],"type":"Point"}
}