{
  "type": "Feature",
  "properties": {
    "iso:country":"DE",
    "sg:address":"Neuendorfer Str. 102",
    "sg:city":"Berlin",
    "sg:phone":"+49 30/3336619",
    "sg:postcode":"13585",
    "sg:province":"Berlin",
    "wof:name":"K\u00e4the Ginter",
    "wof:placetype":"venue"
},
  "geometry": {"coordinates":[13.2056846619,52.5422782898],"type":"Point"}
}