{
  "type": "Feature",
  "properties": {
    "iso:country":"DE",
    "sg:address":"Tempelhofer Damm 186",
    "sg:city":"Berlin",
    "sg:phone":"+49 30/7525044",
    "sg:postcode":"12099",
    "sg:province":"Berlin",
    "wof:name":"Buchhandlung Alfred Menger Inh. Helga Von Sichart E. Kfr.",
    "wof:placetype":"venue"
},
  "geometry": {"coordinates":[13.384393692,52.4602127075],"type":"Point"}
}