{
  "type": "Feature",
  "properties": {
    "iso:country":"DE",
    "sg:address":"Dorfstr. 16A",
    "sg:city":"Beeskow",
    "sg:phone":"+49 3366/26379",
    "sg:postcode":"15848",
    "sg:province":"Brandenburg",
    "wof:name":"Gasthof Neuendorf",
    "wof:placetype":"venue"
},
  "geometry": {"coordinates":[14.195015,52.161545],"type":"Point"}
}