{
  "type": "Feature",
  "properties": {
    "iso:country":"DE",
    "sg:address":"Gotlindestr.",
    "sg:city":"Berlin",
    "sg:phone":"+49 30/5532336",
    "sg:postcode":"10365",
    "sg:province":"Berlin",
    "wof:name":"Bistro Im Arbeitsamt",
    "wof:placetype":"venue"
},
  "geometry": {"coordinates":[13.4918251038,52.5183258057],"type":"Point"}
}