{
  "type": "Feature",
  "properties": {
    "iso:country":"DE",
    "sg:address":"Am Tiefen Weg 8 c",
    "sg:city":"Hanau",
    "sg:postcode":"63454",
    "sg:province":"Hessen",
    "wof:name":"Kotax Gmbh",
    "wof:placetype":"venue"
},
  "geometry": {"coordinates":[8.894068,50.129391],"type":"Point"}
}