{
  "type": "Feature",
  "properties": {
    "iso:country":"DE",
    "sg:address":"Am Bach 24",
    "sg:city":"M\u00fcllheim",
    "sg:phone":"+49 7631/2902",
    "sg:postcode":"79379",
    "sg:province":"Baden-W\u00fcrttemberg",
    "wof:name":"B. Ziegler",
    "wof:placetype":"venue"
},
  "geometry": {"coordinates":[7.65923,47.832863],"type":"Point"}
}