{
  "type": "Feature",
  "properties": {
    "iso:country":"DE",
    "sg:address":"Dorfring 24",
    "sg:city":"Tangstedt",
    "sg:phone":"+49 4109/9088",
    "sg:postcode":"22889",
    "sg:province":"Schleswig-Holstein",
    "wof:name":"Sonnenschein",
    "wof:placetype":"venue"
},
  "geometry": {"coordinates":[10.0834522247,53.7316207886],"type":"Point"}
}