{
  "type": "Feature",
  "properties": {
    "iso:country":"DE",
    "sg:address":"Am G\u00fcterbahnhof 995",
    "sg:city":"Ro\u00dfla",
    "sg:phone":"+49 34651/2403",
    "sg:postcode":"06536",
    "sg:province":"Sachsen-Anhalt",
    "wof:name":"Raiffeisen Warengenossen- Schaft Mansfeld Eg",
    "wof:placetype":"venue"
},
  "geometry": {"coordinates":[11.061829567,51.4617195129],"type":"Point"}
}