{
  "type": "Feature",
  "properties": {
    "iso:country":"DE",
    "sg:address":"Hauptstr. 12",
    "sg:city":"Dernbach",
    "sg:phone":"+49 2602/81014",
    "sg:postcode":"56428",
    "sg:province":"Rheinland-Pfalz",
    "wof:name":"Westerwaldstuben",
    "wof:placetype":"venue"
},
  "geometry": {"coordinates":[7.5974378586,50.5432395935],"type":"Point"}
}