{
  "type": "Feature",
  "properties": {
    "iso:country":"DE",
    "sg:address":"Prenzlauer Allee 177",
    "sg:city":"Berlin",
    "sg:postcode":"10409",
    "sg:province":"Berlin",
    "wof:name":"Stumpfe Ecke",
    "wof:placetype":"venue"
},
  "geometry": {"coordinates":[13.4271841049,52.5451316833],"type":"Point"}
}