{
  "type": "Feature",
  "properties": {
    "iso:country":"DE",
    "sg:address":"Bahnhofstr. 31",
    "sg:city":"Dielheim",
    "sg:phone":"+49 6222/98030",
    "sg:postcode":"69234",
    "sg:province":"Baden-W\u00fcrttemberg",
    "wof:name":"Compro Gesellschaft F\u00fcr It Services Und Solutions Mbh",
    "wof:placetype":"venue"
},
  "geometry": {"coordinates":[8.7349033356,49.2845726013],"type":"Point"}
}