{
  "type": "Feature",
  "properties": {
    "iso:country":"DE",
    "sg:address":"Birkbuschgarten 3",
    "sg:city":"Berlin",
    "sg:phone":"+49 30/7712704",
    "sg:postcode":"12167",
    "sg:province":"Berlin",
    "wof:name":"Werner Kleist",
    "wof:placetype":"venue"
},
  "geometry": {"coordinates":[13.3291931152,52.4466972351],"type":"Point"}
}