{
  "type": "Feature",
  "properties": {
    "iso:country":"DE",
    "sg:address":"Nu\u00dfbacher Str 50",
    "sg:city":"Triberg",
    "sg:phone":"+49 6196/23560",
    "sg:postcode":"78098",
    "sg:province":"Baden-W\u00fcrttemberg",
    "wof:name":"Akh Spedition Gmbh",
    "wof:placetype":"venue"
},
  "geometry": {"coordinates":[8.511349678,50.1334228516],"type":"Point"}
}