{
  "type": "Feature",
  "properties": {
    "iso:country":"DE",
    "sg:address":"Jakobstr. 2",
    "sg:city":"Niederkassel",
    "sg:phone":"+49 2208/72928",
    "sg:postcode":"53859",
    "sg:province":"Nordrhein-Westfalen",
    "wof:name":"Erhard Janich",
    "wof:placetype":"venue"
},
  "geometry": {"coordinates":[7.047495842,50.7865867615],"type":"Point"}
}