{
  "type": "Feature",
  "properties": {
    "iso:country":"DE",
    "sg:address":"K\u00f6nigsberger Str. 10a",
    "sg:city":"Kitzingen",
    "sg:phone":"+49 9321/32850",
    "sg:postcode":"97318",
    "sg:province":"Bayern",
    "wof:name":"Kromer",
    "wof:placetype":"venue"
},
  "geometry": {"coordinates":[10.1812858582,49.7302246094],"type":"Point"}
}