{
  "type": "Feature",
  "properties": {
    "iso:country":"DE",
    "sg:address":"1120",
    "sg:city":"Nortrup",
    "sg:phone":"+49 5436/520",
    "sg:postcode":"49638",
    "sg:province":"Niedersachsen",
    "wof:name":"Kemper Fleischwaren Gmbh",
    "wof:placetype":"venue"
},
  "geometry": {"coordinates":[7.85922,52.61705],"type":"Point"}
}