{
  "type": "Feature",
  "properties": {
    "iso:country":"DE",
    "sg:address":"Linnicher Str. 11",
    "sg:city":"J\u00fclich",
    "sg:phone":"+49 2461/8081",
    "sg:postcode":"52428",
    "sg:province":"Nordrhein-Westfalen",
    "wof:name":"Kreuzer Und Partner Rechtsanw\u00e4lte",
    "wof:placetype":"venue"
},
  "geometry": {"coordinates":[6.3553318977,50.9275131226],"type":"Point"}
}