{
  "type": "Feature",
  "properties": {
    "iso:country":"DE",
    "sg:address":"Robert-Bosch-Str. 6-3",
    "sg:city":"Reutlingen",
    "sg:postcode":"72760",
    "sg:province":"Baden-W\u00fcrttemberg",
    "wof:name":"Malack Maler- Und Lackierbetrieb Gmbh",
    "wof:placetype":"venue"
},
  "geometry": {"coordinates":[9.21176,48.506828],"type":"Point"}
}