{
  "type": "Feature",
  "properties": {
    "iso:country":"DE",
    "sg:address":"Willibald-Gluck-Str. 2",
    "sg:city":"Neumarkt",
    "sg:phone":"+49 9181/48520",
    "sg:postcode":"92318",
    "sg:province":"Bayern",
    "wof:name":"M. Grau Ingenieur",
    "wof:placetype":"venue"
},
  "geometry": {"coordinates":[11.4725694656,49.2761497498],"type":"Point"}
}