{
  "type": "Feature",
  "properties": {
    "iso:country":"DE",
    "sg:address":"Goethepark 18",
    "sg:city":"Berlin",
    "sg:postcode":"10627",
    "sg:province":"Berlin",
    "wof:name":"Tricom Gmbh",
    "wof:placetype":"venue"
},
  "geometry": {"coordinates":[13.3023424149,52.5083274841],"type":"Point"}
}