{
  "type": "Feature",
  "properties": {
    "iso:country":"DE",
    "sg:address":"Espenstr. 6",
    "sg:city":"Wunsiedel",
    "sg:phone":"+49 9232/1550",
    "sg:postcode":"95632",
    "sg:province":"Bayern",
    "wof:name":"Tr\u00f6ger Isolierungen Gmbh",
    "wof:placetype":"venue"
},
  "geometry": {"coordinates":[12.030617,50.046349],"type":"Point"}
}