{
  "type": "Feature",
  "properties": {
    "iso:country":"DE",
    "sg:address":"Schmidts Breite 8",
    "sg:city":"Hamburg",
    "sg:phone":"+49 40/75665761",
    "sg:postcode":"21107",
    "sg:province":"Hamburg",
    "wof:name":"Metaproduct Produktions- Und Handels-gmbh",
    "wof:placetype":"venue"
},
  "geometry": {"coordinates":[9.987868309,53.4971122742],"type":"Point"}
}