{
  "type": "Feature",
  "properties": {
    "iso:country":"DE",
    "sg:address":"Heinestr. 11",
    "sg:city":"Hude",
    "sg:phone":"+49 4408/923103",
    "sg:postcode":"27798",
    "sg:province":"Niedersachsen",
    "wof:name":"Heinz Pargmann Immobilien- Verwaltungs Gmbh",
    "wof:placetype":"venue"
},
  "geometry": {"coordinates":[8.4586801529,53.0998039246],"type":"Point"}
}