{
  "type": "Feature",
  "properties": {
    "iso:country":"DE",
    "sg:address":"Ewaldstr. 88",
    "sg:city":"N\u00fcrnberg",
    "sg:phone":"+49 911/5988241",
    "sg:postcode":"90491",
    "sg:province":"Bayern",
    "wof:name":"Dr. Cord Gerold Brandis Rechtsanwalt",
    "wof:placetype":"venue"
},
  "geometry": {"coordinates":[11.1215600967,49.4722709656],"type":"Point"}
}