{
  "type": "Feature",
  "properties": {
    "iso:country":"DE",
    "sg:address":"Gro\u00dfe Ga\u00df 2 a",
    "sg:city":"Weil am Rhein",
    "sg:phone":"+49 7621/62340",
    "sg:postcode":"79576",
    "sg:province":"Baden-W\u00fcrttemberg",
    "wof:name":"Sparmarkt Heidemarie Spie\u00df",
    "wof:placetype":"venue"
},
  "geometry": {"coordinates":[7.6143870354,47.6149520874],"type":"Point"}
}