{
  "type": "Feature",
  "properties": {
    "iso:country":"DE",
    "sg:address":"Florastr. 11",
    "sg:city":"Essen",
    "sg:phone":"+49 201/450110",
    "sg:postcode":"45131",
    "sg:province":"Nordrhein-Westfalen",
    "wof:name":"J. Wiese",
    "wof:placetype":"venue"
},
  "geometry": {"coordinates":[7.0007019043,51.4268264771],"type":"Point"}
}