{
  "type": "Feature",
  "properties": {
    "iso:country":"DE",
    "sg:address":"Waldstr. 25",
    "sg:city":"Spremberg",
    "sg:postcode":"03130",
    "sg:province":"Brandenburg",
    "wof:name":"W. Tillack",
    "wof:placetype":"venue"
},
  "geometry": {"coordinates":[14.3759288788,51.5619773865],"type":"Point"}
}