{
  "type": "Feature",
  "properties": {
    "iso:country":"DE",
    "sg:address":"Els\u00e4sser Str. 14",
    "sg:city":"Aschaffenburg",
    "sg:phone":"+49 6021/219638",
    "sg:postcode":"63739",
    "sg:province":"Bayern",
    "wof:name":"Kosmetikstudio Rosi",
    "wof:placetype":"venue"
},
  "geometry": {"coordinates":[9.15999,49.982971],"type":"Point"}
}