{
  "type": "Feature",
  "properties": {
    "iso:country":"DE",
    "sg:address":"Industriestr. 26",
    "sg:city":"Neuhaus-Schierschnitz",
    "sg:phone":"+49 36764/72266",
    "sg:postcode":"96524",
    "sg:province":"Th\u00fcringen",
    "wof:name":"Renate Schulze",
    "wof:placetype":"venue"
},
  "geometry": {"coordinates":[11.243728,50.30917],"type":"Point"}
}