{
  "type": "Feature",
  "properties": {
    "iso:country":"DE",
    "sg:address":"Glenetalstr. 5",
    "sg:city":"Alfeld",
    "sg:phone":"+49 5181/81635",
    "sg:postcode":"31061",
    "sg:province":"Niedersachsen",
    "wof:name":"Werner S\u00fcrig",
    "wof:placetype":"venue"
},
  "geometry": {"coordinates":[9.7734851837,51.9961662292],"type":"Point"}
}