{
  "type": "Feature",
  "properties": {
    "iso:country":"DE",
    "sg:address":"Arnold-Sommerfeld-Ring 2",
    "sg:city":"Baesweiler",
    "sg:postcode":"52499",
    "sg:province":"Nordrhein-Westfalen",
    "wof:name":"Printed Circuit Board Service Gmbh",
    "wof:placetype":"venue"
},
  "geometry": {"coordinates":[6.17373,50.91851],"type":"Point"}
}