{
  "type": "Feature",
  "properties": {
    "iso:country":"DE",
    "sg:address":"Hauptstr. 77",
    "sg:city":"Steinheim",
    "sg:phone":"+49 7329/495",
    "sg:postcode":"89555",
    "sg:province":"Baden-W\u00fcrttemberg",
    "wof:name":"Lenis Blumenquelle",
    "wof:placetype":"venue"
},
  "geometry": {"coordinates":[10.059584,48.691517],"type":"Point"}
}