{
  "type": "Feature",
  "properties": {
    "iso:country":"DE",
    "sg:address":"Eysseneckstr. 4",
    "sg:city":"Frankfurt",
    "sg:postcode":"60322",
    "sg:province":"Hessen",
    "wof:name":"H & L Modehandels- Gmbh",
    "wof:placetype":"venue"
},
  "geometry": {"coordinates":[8.677246,50.127476],"type":"Point"}
}