{
  "type": "Feature",
  "properties": {
    "iso:country":"DE",
    "sg:address":"Mauerbergstr. 12",
    "sg:city":"Baden-Baden",
    "sg:phone":"+49 7223/57873",
    "sg:postcode":"76534",
    "sg:province":"Baden-W\u00fcrttemberg",
    "wof:name":"R\u00f6merkeller",
    "wof:placetype":"venue"
},
  "geometry": {"coordinates":[8.194149971,48.7177391052],"type":"Point"}
}