{
  "type": "Feature",
  "properties": {
    "iso:country":"DE",
    "sg:address":"Soltausredder 8",
    "sg:city":"Barsb\u00fcttel",
    "sg:phone":"+49 40/6702722",
    "sg:postcode":"22885",
    "sg:province":"Schleswig-Holstein",
    "wof:name":"Petra Soltau-wietzke",
    "wof:placetype":"venue"
},
  "geometry": {"coordinates":[10.162915,53.57008],"type":"Point"}
}