{
  "type": "Feature",
  "properties": {
    "iso:country":"DE",
    "sg:address":"Rosenfelder Strand",
    "sg:city":"Grube",
    "sg:phone":"+49 4364/222",
    "sg:postcode":"23749",
    "sg:province":"Schleswig-Holstein",
    "wof:name":"Fkk-freizeitanlagen- Betriebsges. Mbh",
    "wof:placetype":"venue"
},
  "geometry": {"coordinates":[11.07864,54.258068],"type":"Point"}
}