{
  "type": "Feature",
  "properties": {
    "iso:country":"DE",
    "sg:address":"Frankfurter Str. 53",
    "sg:city":"Bad Rothenfelde",
    "sg:phone":"+49 5424/1243",
    "sg:postcode":"49214",
    "sg:province":"Niedersachsen",
    "wof:name":"G. Wellmann Mech. Werkstatt",
    "wof:placetype":"venue"
},
  "geometry": {"coordinates":[8.164218,52.103806],"type":"Point"}
}