{
  "type": "Feature",
  "properties": {
    "iso:country":"DE",
    "sg:address":"Im Ort 3",
    "sg:city":"Oer-Erkenschwick",
    "sg:phone":"+49 2368/3651",
    "sg:postcode":"45739",
    "sg:province":"Nordrhein-Westfalen",
    "wof:name":"Heinrich Kellmann Ingenieur",
    "wof:placetype":"venue"
},
  "geometry": {"coordinates":[7.256321907,51.6354751587],"type":"Point"}
}