{
  "type": "Feature",
  "properties": {
    "iso:country":"DE",
    "sg:address":"Brunnengasse 19",
    "sg:city":"Mertingen",
    "sg:phone":"+49 9078/969850",
    "sg:postcode":"86690",
    "sg:province":"Bayern",
    "wof:name":"Autis Maschinenbau Gmbh",
    "wof:placetype":"venue"
},
  "geometry": {"coordinates":[10.8029642105,48.65782547],"type":"Point"}
}