{
  "type": "Feature",
  "properties": {
    "iso:country":"DE",
    "sg:address":"Hubertusstr. 76",
    "sg:city":"Castrop-Rauxel",
    "sg:phone":"+49 2305/61406",
    "sg:postcode":"44577",
    "sg:province":"Nordrhein-Westfalen",
    "wof:name":"Herbert Und Vera Weiner Binnenschiffahrtsunternehmen",
    "wof:placetype":"venue"
},
  "geometry": {"coordinates":[7.361162,51.531101],"type":"Point"}
}