{
  "type": "Feature",
  "properties": {
    "iso:country":"DE",
    "sg:address":"Werner-von-Siemens-Str. 3",
    "sg:city":"Rohrbach",
    "sg:phone":"+49 8442/953240",
    "sg:postcode":"85296",
    "sg:province":"Bayern",
    "wof:name":"Huber S Ink And Paper Gmbh",
    "wof:placetype":"venue"
},
  "geometry": {"coordinates":[11.576313,48.608376],"type":"Point"}
}