{
  "type": "Feature",
  "properties": {
    "iso:country":"DE",
    "sg:address":"Moerser Str. 20",
    "sg:city":"Meerbusch",
    "sg:phone":"+49 2132/10310",
    "sg:postcode":"40667",
    "sg:province":"Nordrhein-Westfalen",
    "wof:name":"E. Bl\u00fcggel Immobilienmakler",
    "wof:placetype":"venue"
},
  "geometry": {"coordinates":[6.6737098694,51.2643890381],"type":"Point"}
}