{
  "type": "Feature",
  "properties": {
    "iso:country":"DE",
    "sg:address":"Heinrich-Vogl-Str. 23",
    "sg:city":"Ebersberg",
    "sg:postcode":"85560",
    "sg:province":"Bayern",
    "wof:name":"Metzgerei Maisch Gmbh",
    "wof:placetype":"venue"
},
  "geometry": {"coordinates":[11.9677038193,48.07629776],"type":"Point"}
}