{
  "type": "Feature",
  "properties": {
    "iso:country":"DE",
    "sg:address":"Daimlerstr. 5",
    "sg:city":"Meckesheim",
    "sg:phone":"+49 6226/5550",
    "sg:postcode":"74909",
    "sg:province":"Baden-W\u00fcrttemberg",
    "wof:name":"Harnisch Gmbh",
    "wof:placetype":"venue"
},
  "geometry": {"coordinates":[8.805491,49.324219],"type":"Point"}
}