{
  "type": "Feature",
  "properties": {
    "iso:country":"DE",
    "sg:address":"Am Graswege 34",
    "sg:city":"Hannover",
    "sg:phone":"+49 511/9886064",
    "sg:postcode":"30169",
    "sg:province":"Niedersachsen",
    "wof:name":"Helge Beuthan Steuerberater",
    "wof:placetype":"venue"
},
  "geometry": {"coordinates":[9.7450666428,52.3598632812],"type":"Point"}
}