{
  "type": "Feature",
  "properties": {
    "iso:country":"DE",
    "sg:address":"Stoverner Str. 47",
    "sg:city":"Rheine",
    "sg:phone":"+49 5971/52276",
    "sg:postcode":"48431",
    "sg:province":"Nordrhein-Westfalen",
    "wof:name":"Zur Schleupe",
    "wof:placetype":"venue"
},
  "geometry": {"coordinates":[7.4151639938,52.2868843079],"type":"Point"}
}