{
  "type": "Feature",
  "properties": {
    "iso:country":"DE",
    "sg:address":"Zeithainer Str. 7",
    "sg:city":"Dresden",
    "sg:phone":"+49 351/8489574",
    "sg:postcode":"01127",
    "sg:province":"Sachsen",
    "wof:name":"Heinz B\u00f6hm",
    "wof:placetype":"venue"
},
  "geometry": {"coordinates":[13.729621,51.08107],"type":"Point"}
}