{
  "type": "Feature",
  "properties": {
    "iso:country":"DE",
    "sg:address":"D\u00f6rnichtweg 52",
    "sg:city":"Dresden",
    "sg:phone":"+49 351/882850",
    "sg:postcode":"01109",
    "sg:province":"Sachsen",
    "wof:name":"Detecon Deutsche Telepost Consulting Gmbh",
    "wof:placetype":"venue"
},
  "geometry": {"coordinates":[13.7784929276,51.1226959229],"type":"Point"}
}