{
  "type": "Feature",
  "properties": {
    "iso:country":"DE",
    "sg:address":"Altensenner Weg 75",
    "sg:city":"Herford",
    "sg:phone":"+49 5221/70348",
    "sg:postcode":"32052",
    "sg:province":"Nordrhein-Westfalen",
    "wof:name":"B\u00e4umer K\u00fcchen Gmbh",
    "wof:placetype":"venue"
},
  "geometry": {"coordinates":[8.650538,52.10062],"type":"Point"}
}