{
  "type": "Feature",
  "properties": {
    "iso:country":"DE",
    "sg:address":"Br\u00fchlstr. 21",
    "sg:city":"Gerabronn",
    "sg:phone":"+49 7952/5755",
    "sg:postcode":"74582",
    "sg:province":"Baden-W\u00fcrttemberg",
    "wof:name":"Rudolf Drascher Finanzberater",
    "wof:placetype":"venue"
},
  "geometry": {"coordinates":[9.9232254028,49.247882843],"type":"Point"}
}