{
  "type": "Feature",
  "properties": {
    "iso:country":"DE",
    "sg:address":"Castroper Str. 81",
    "sg:city":"Dortmund",
    "sg:phone":"+49 231/339198",
    "sg:postcode":"44357",
    "sg:province":"Nordrhein-Westfalen",
    "wof:name":"Wolfgang Thomann",
    "wof:placetype":"venue"
},
  "geometry": {"coordinates":[7.372906,51.568577],"type":"Point"}
}