{
  "type": "Feature",
  "properties": {
    "iso:country":"DE",
    "sg:address":"Unterd\u00fcrrbacher Str. 222",
    "sg:city":"W\u00fcrzburg",
    "sg:phone":"+49 931/13347",
    "sg:postcode":"97080",
    "sg:province":"Bayern",
    "wof:name":"Wohngesund Binner & Nowak Gmbh",
    "wof:placetype":"venue"
},
  "geometry": {"coordinates":[9.910978,49.808872],"type":"Point"}
}