{
  "type": "Feature",
  "properties": {
    "iso:country":"DE",
    "sg:address":"Stephanstr. 24",
    "sg:city":"N\u00fcrnberg",
    "sg:phone":"+49 911/468129",
    "sg:postcode":"90478",
    "sg:province":"Bayern",
    "wof:name":"Alaaddin Aslan",
    "wof:placetype":"venue"
},
  "geometry": {"coordinates":[11.0995416641,49.44581604],"type":"Point"}
}