{
  "type": "Feature",
  "properties": {
    "iso:country":"DE",
    "sg:address":"Weidenweg 33",
    "sg:city":"Weiterstadt",
    "sg:phone":"+49 6150/3136",
    "sg:postcode":"64331",
    "sg:province":"Hessen",
    "wof:name":"H. Morral Immobilienmakler",
    "wof:placetype":"venue"
},
  "geometry": {"coordinates":[8.6025323868,49.9038963318],"type":"Point"}
}