{
  "type": "Feature",
  "properties": {
    "iso:country":"DE",
    "sg:address":"Dorfplatz 13",
    "sg:city":"Zwiesel",
    "sg:phone":"+49 9922/9142",
    "sg:postcode":"94227",
    "sg:province":"Bayern",
    "wof:name":"Pension Rosenhof",
    "wof:placetype":"venue"
},
  "geometry": {"coordinates":[13.221953392,49.0319137573],"type":"Point"}
}