{
  "type": "Feature",
  "properties": {
    "iso:country":"DE",
    "sg:address":"Riestedter Str. 24",
    "sg:city":"Sangerhausen",
    "sg:postcode":"06526",
    "sg:province":"Sachsen-Anhalt",
    "wof:name":"Ev. Kirchenamt",
    "wof:placetype":"venue"
},
  "geometry": {"coordinates":[11.3039197922,51.474395752],"type":"Point"}
}