{
  "type": "Feature",
  "properties": {
    "iso:country":"DE",
    "sg:address":"Kyffh\u00e4user Str. 11 a",
    "sg:city":"Ro\u00dfla",
    "sg:phone":"+49 34651/2388",
    "sg:postcode":"06536",
    "sg:province":"Sachsen-Anhalt",
    "wof:name":"Bohrgesellschaft Ro\u00dfla Mbh",
    "wof:placetype":"venue"
},
  "geometry": {"coordinates":[11.073637,51.461143],"type":"Point"}
}