{
  "type": "Feature",
  "properties": {
    "iso:country":"DE",
    "sg:address":"Hohenzollernring 2",
    "sg:city":"Saarlouis",
    "sg:phone":"+49 6831/42044",
    "sg:postcode":"66740",
    "sg:province":"Saarland",
    "wof:name":"Gotzen Und Stein Rechtsanw\u00e4lte",
    "wof:placetype":"venue"
},
  "geometry": {"coordinates":[6.7543110847,49.3133049011],"type":"Point"}
}