{
  "type": "Feature",
  "properties": {
    "iso:country":"DE",
    "sg:address":"Badstr. 26",
    "sg:city":"Waiblingen",
    "sg:phone":"+49 7151/21591",
    "sg:postcode":"71334",
    "sg:province":"Baden-W\u00fcrttemberg",
    "wof:name":"Julias Bierquelle",
    "wof:placetype":"venue"
},
  "geometry": {"coordinates":[9.3139829636,48.8384628296],"type":"Point"}
}