{
  "type": "Feature",
  "properties": {
    "iso:country":"DE",
    "sg:address":"Waterkamp 2a",
    "sg:city":"Edewecht",
    "sg:phone":"+49 4405/6918",
    "sg:postcode":"26188",
    "sg:province":"Niedersachsen",
    "wof:name":"Biohof Himpsl",
    "wof:placetype":"venue"
},
  "geometry": {"coordinates":[7.948467,53.117065],"type":"Point"}
}