{
  "type": "Feature",
  "properties": {
    "iso:country":"DE",
    "sg:address":"Kr\u00e4nzliner Str. 32a",
    "sg:city":"Neuruppin",
    "sg:phone":"+49 3391/506248",
    "sg:postcode":"16816",
    "sg:province":"Brandenburg",
    "wof:name":"Neuruppiner Wohnungsbauges. Mbh",
    "wof:placetype":"venue"
},
  "geometry": {"coordinates":[12.7930135727,52.9221611023],"type":"Point"}
}