{
  "type": "Feature",
  "properties": {
    "iso:country":"DE",
    "sg:address":"Luise-Kiesselbach-Platz 34",
    "sg:city":"M\u00fcnchen",
    "sg:phone":"+49 89/7148644",
    "sg:postcode":"81377",
    "sg:province":"Bayern",
    "wof:name":"Laszio Benker Ingenieur",
    "wof:placetype":"venue"
},
  "geometry": {"coordinates":[11.5166769028,48.1125793457],"type":"Point"}
}