{
  "type": "Feature",
  "properties": {
    "iso:country":"DE",
    "sg:address":"Heerstr. 53",
    "sg:city":"Rottweil",
    "sg:postcode":"78628",
    "sg:province":"Baden-W\u00fcrttemberg",
    "wof:name":"Econie Werbeagentur Dennis Kr\u00fcger E. K.",
    "wof:placetype":"venue"
},
  "geometry": {"coordinates":[8.6338319778,48.1593360901],"type":"Point"}
}