{
  "type": "Feature",
  "properties": {
    "iso:country":"DE",
    "sg:address":"Beusselstra\u00dfe 71",
    "sg:city":"Berlin",
    "sg:phone":"+49 30/39104859",
    "sg:postcode":"10553",
    "sg:province":"Berlin",
    "wof:name":"Avantgarde Berlin",
    "wof:placetype":"venue"
},
  "geometry": {"coordinates":[13.328434,52.528358],"type":"Point"}
}