{
  "type": "Feature",
  "properties": {
    "iso:country":"DE",
    "sg:address":"Rathausstr. 18",
    "sg:city":"Bodolz",
    "sg:phone":"+49 8382/21893",
    "sg:postcode":"88131",
    "sg:province":"Bayern",
    "wof:name":"Hans Schneider",
    "wof:placetype":"venue"
},
  "geometry": {"coordinates":[9.663338,47.572247],"type":"Point"}
}