{
  "type": "Feature",
  "properties": {
    "iso:country":"DE",
    "sg:address":"Teinacher Str. 44-46",
    "sg:city":"Ludwigsburg",
    "sg:phone":"+49 7141/3050",
    "sg:postcode":"71634",
    "sg:province":"Baden-W\u00fcrttemberg",
    "wof:name":"Ludwigsburger Wach- Und Sicherheitsdienst",
    "wof:placetype":"venue"
},
  "geometry": {"coordinates":[9.1695842743,48.9036331177],"type":"Point"}
}