{
  "type": "Feature",
  "properties": {
    "iso:country":"DE",
    "sg:address":"Brassertstr. 89",
    "sg:city":"Marl",
    "sg:phone":"+49 2365/62286",
    "sg:postcode":"45768",
    "sg:province":"Nordrhein-Westfalen",
    "wof:name":"Barbara-apotheke",
    "wof:placetype":"venue"
},
  "geometry": {"coordinates":[7.083901,51.657543],"type":"Point"}
}