{
  "type": "Feature",
  "properties": {
    "iso:country":"DE",
    "sg:address":"St.-Vither-Str. 101",
    "sg:city":"Pr\u00fcm",
    "sg:phone":"+49 6551/95480",
    "sg:postcode":"54595",
    "sg:province":"Rheinland-Pfalz",
    "wof:name":"Moderner Baudedarf Ph. Messerich",
    "wof:placetype":"venue"
},
  "geometry": {"coordinates":[6.403797,50.192028],"type":"Point"}
}