{
  "type": "Feature",
  "properties": {
    "iso:country":"DE",
    "sg:address":"Steglitzer Str. 15",
    "sg:city":"Hamburg",
    "sg:phone":"+49 40/6731604",
    "sg:postcode":"22045",
    "sg:province":"Hamburg",
    "wof:name":"Ev. Pfarramt Ii Trinitatis-gemeinde",
    "wof:placetype":"venue"
},
  "geometry": {"coordinates":[10.1442222595,53.5822486877],"type":"Point"}
}