{
  "type": "Feature",
  "properties": {
    "iso:country":"DE",
    "sg:address":"Wechselsaater Weg 1",
    "sg:city":"Erkelenz",
    "sg:phone":"+49 2164/4039",
    "sg:postcode":"41812",
    "sg:province":"Nordrhein-Westfalen",
    "wof:name":"Josef Immeln",
    "wof:placetype":"venue"
},
  "geometry": {"coordinates":[6.3994579315,51.0465354919],"type":"Point"}
}