{
  "type": "Feature",
  "properties": {
    "iso:country":"DE",
    "sg:address":"Hittostr. 27",
    "sg:city":"Freising",
    "sg:phone":"+49 8161/92428",
    "sg:postcode":"85354",
    "sg:province":"Bayern",
    "wof:name":"F. Feller Gmbh",
    "wof:placetype":"venue"
},
  "geometry": {"coordinates":[11.7105751038,48.3965492249],"type":"Point"}
}