{
  "type": "Feature",
  "properties": {
    "iso:country":"DE",
    "sg:address":"Kaiserstr. 10",
    "sg:city":"N\u00fcrnberg",
    "sg:phone":"+49 911/2418792",
    "sg:postcode":"90403",
    "sg:province":"Bayern",
    "wof:name":"Escada Boutique",
    "wof:placetype":"venue"
},
  "geometry": {"coordinates":[11.075366,49.457733],"type":"Point"}
}