{
  "type": "Feature",
  "properties": {
    "iso:country":"DE",
    "sg:address":"Ringstr. 6",
    "sg:city":"Urmitz",
    "sg:phone":"+49 2630/8260",
    "sg:postcode":"56220",
    "sg:province":"Rheinland-Pfalz",
    "wof:name":"Ingrid H\u00f6fer-wosnitza",
    "wof:placetype":"venue"
},
  "geometry": {"coordinates":[7.5194759369,50.4154014587],"type":"Point"}
}