{
  "type": "Feature",
  "properties": {
    "iso:country":"DE",
    "sg:address":"Darmst\u00e4dter Str. 72",
    "sg:city":"M\u00fcnster",
    "sg:phone":"+49 6071/31106",
    "sg:postcode":"64839",
    "sg:province":"Hessen",
    "wof:name":"Kleiderfabrik Baumann Alexander",
    "wof:placetype":"venue"
},
  "geometry": {"coordinates":[8.8560810089,49.9191513062],"type":"Point"}
}