{
  "type": "Feature",
  "properties": {
    "iso:country":"DE",
    "sg:address":"Unser-Fritz-Str. 27",
    "sg:city":"Herne",
    "sg:phone":"+49 2325/74333",
    "sg:postcode":"44649",
    "sg:province":"Nordrhein-Westfalen",
    "wof:name":"Angelika Grillmaier",
    "wof:placetype":"venue"
},
  "geometry": {"coordinates":[7.1533069611,51.5411605835],"type":"Point"}
}