{
  "type": "Feature",
  "properties": {
    "iso:country":"DE",
    "sg:address":"Baltenstein 6",
    "sg:city":"Betzigau",
    "sg:postcode":"87488",
    "sg:province":"Bayern",
    "wof:name":"Kindererholungsheim Haus Baltenstein",
    "wof:placetype":"venue"
},
  "geometry": {"coordinates":[10.4029302597,47.7232894897],"type":"Point"}
}