{
  "type": "Feature",
  "properties": {
    "iso:country":"DE",
    "sg:address":"Unterf\u00fcrberger Str. 87",
    "sg:city":"F\u00fcrth",
    "sg:phone":"+49 911/729932",
    "sg:postcode":"90768",
    "sg:province":"Bayern",
    "wof:name":"Zur Villenkolonie",
    "wof:placetype":"venue"
},
  "geometry": {"coordinates":[10.9637947083,49.4731864929],"type":"Point"}
}