{
  "type": "Feature",
  "properties": {
    "iso:country":"DE",
    "sg:address":"B\u00fchlstr. 5",
    "sg:city":"Siegen",
    "sg:phone":"+49 271/355136",
    "sg:postcode":"57080",
    "sg:province":"Nordrhein-Westfalen",
    "wof:name":"Plate Feinkost Markus Stahl E. K.",
    "wof:placetype":"venue"
},
  "geometry": {"coordinates":[7.9861950874,50.8349647522],"type":"Point"}
}