{
  "type": "Feature",
  "properties": {
    "iso:country":"DE",
    "sg:address":"Hauptstr. 5",
    "sg:city":"Walthersdorf",
    "sg:phone":"+49 37344/8286",
    "sg:postcode":"09474",
    "sg:province":"Sachsen",
    "wof:name":"Pension Oehler",
    "wof:placetype":"venue"
},
  "geometry": {"coordinates":[12.9340896606,50.5083084106],"type":"Point"}
}