{
  "type": "Feature",
  "properties": {
    "iso:country":"DE",
    "sg:address":"Walterstr. 9",
    "sg:city":"Augsburg",
    "sg:postcode":"86153",
    "sg:province":"Bayern",
    "wof:name":"Eks Gmbh",
    "wof:placetype":"venue"
},
  "geometry": {"coordinates":[10.9165630341,48.3707771301],"type":"Point"}
}