{
  "type": "Feature",
  "properties": {
    "iso:country":"DE",
    "sg:address":"Am Spielberg 14",
    "sg:city":"Herxheimweyher",
    "sg:phone":"+49 7276/8640",
    "sg:postcode":"76863",
    "sg:province":"Rheinland-Pfalz",
    "wof:name":"K. W. Heim",
    "wof:placetype":"venue"
},
  "geometry": {"coordinates":[8.2491989136,49.152633667],"type":"Point"}
}