{
  "type": "Feature",
  "properties": {
    "iso:country":"DE",
    "sg:address":"Ludwigstr. 30",
    "sg:city":"Gie\u00dfen",
    "sg:phone":"+49 641/77939",
    "sg:postcode":"35390",
    "sg:province":"Hessen",
    "wof:name":"Taverne",
    "wof:placetype":"venue"
},
  "geometry": {"coordinates":[8.6767311096,50.5809364319],"type":"Point"}
}