{
  "type": "Feature",
  "properties": {
    "iso:country":"DE",
    "sg:address":"Hauptkanal Rechts 75",
    "sg:city":"Papenburg",
    "sg:postcode":"26871",
    "sg:province":"Niedersachsen",
    "wof:name":"Nordemsl\u00e4ndische Radiologie- Besitzgesellschaft",
    "wof:placetype":"venue"
},
  "geometry": {"coordinates":[7.3968701363,53.0774154663],"type":"Point"}
}