{
  "type": "Feature",
  "properties": {
    "iso:country":"DE",
    "sg:address":"Grunstedter Weg 5",
    "sg:city":"Nohra",
    "sg:phone":"+49 3643/829268",
    "sg:postcode":"99428",
    "sg:province":"Th\u00fcringen",
    "wof:name":"Helmreich Maler- Und Fassadensanierungs Gmbh",
    "wof:placetype":"venue"
},
  "geometry": {"coordinates":[11.267936,50.965244],"type":"Point"}
}