{
  "type": "Feature",
  "properties": {
    "iso:country":"DE",
    "sg:address":"Westring 15",
    "sg:city":"B\u00fcren",
    "sg:phone":"+49 2951/4477",
    "sg:postcode":"33142",
    "sg:province":"Nordrhein-Westfalen",
    "wof:name":"Raul Leichtbauhallen Gmbh",
    "wof:placetype":"venue"
},
  "geometry": {"coordinates":[8.530909,51.560799],"type":"Point"}
}