{
  "type": "Feature",
  "properties": {
    "iso:country":"DE",
    "sg:address":"Am T\u00f6nniesberg 14",
    "sg:city":"Hannover",
    "sg:phone":"+49 511/464637",
    "sg:postcode":"30453",
    "sg:province":"Niedersachsen",
    "wof:name":"Koch Pflanzenhandel Gmbh",
    "wof:placetype":"venue"
},
  "geometry": {"coordinates":[9.704422,52.351662],"type":"Point"}
}