{
  "type": "Feature",
  "properties": {
    "iso:country":"DE",
    "sg:address":"Bildstra\u00dfe 29",
    "sg:city":"Elsenfeld",
    "sg:phone":"+49 6022",
    "sg:postcode":"63820",
    "sg:province":"Bayern",
    "wof:name":"Fms - Motorradzubeh\u00f6r Und Streetfighterumbauten",
    "wof:placetype":"venue"
},
  "geometry": {"coordinates":[9.1615753174,49.8389205933],"type":"Point"}
}