{
  "type": "Feature",
  "properties": {
    "iso:country":"DE",
    "sg:address":"Dorfwiesenstr. 6",
    "sg:city":"Kirschweiler",
    "sg:phone":"+49 6781/33874",
    "sg:postcode":"55743",
    "sg:province":"Rheinland-Pfalz",
    "wof:name":"Kuno Becker",
    "wof:placetype":"venue"
},
  "geometry": {"coordinates":[7.244972,49.753708],"type":"Point"}
}