{
  "type": "Feature",
  "properties": {
    "iso:country":"DE",
    "sg:address":"Konstanzer Str. 11",
    "sg:city":"Berlin",
    "sg:phone":"+49 30/8814674",
    "sg:postcode":"10707",
    "sg:province":"Berlin",
    "wof:name":"G\u00fcnther & Co.",
    "wof:placetype":"venue"
},
  "geometry": {"coordinates":[13.3106851578,52.4954452515],"type":"Point"}
}