{
  "type": "Feature",
  "properties": {
    "iso:country":"DE",
    "sg:address":"Am Rosengarten 3",
    "sg:city":"Eutin",
    "sg:phone":"+49 4521/852120",
    "sg:postcode":"23701",
    "sg:province":"Schleswig-Holstein",
    "wof:name":"Jagdschl\u00f6\u00dfchen Am Ukleisee Stiftung Der Sparkasse",
    "wof:placetype":"venue"
},
  "geometry": {"coordinates":[10.6155605316,54.1378135681],"type":"Point"}
}