{
  "type": "Feature",
  "properties": {
    "iso:country":"DE",
    "sg:address":"Rheinsberger Str. 16",
    "sg:city":"Lindow",
    "sg:postcode":"16835",
    "sg:province":"Brandenburg",
    "wof:name":"R. Sellau",
    "wof:placetype":"venue"
},
  "geometry": {"coordinates":[12.985036,52.976624],"type":"Point"}
}