{
  "type": "Feature",
  "properties": {
    "iso:country":"DE",
    "sg:address":"Henschelstr. 9",
    "sg:city":"Maintal",
    "sg:phone":"+49 6181/491513",
    "sg:postcode":"63477",
    "sg:province":"Hessen",
    "wof:name":"R. Bernhard",
    "wof:placetype":"venue"
},
  "geometry": {"coordinates":[8.847989,50.143894],"type":"Point"}
}