{
  "type": "Feature",
  "properties": {
    "iso:country":"DE",
    "sg:address":"Hedingsener Str. 203",
    "sg:city":"Bad Oeynhausen",
    "sg:phone":"+49 5734/1694",
    "sg:postcode":"32549",
    "sg:province":"Nordrhein-Westfalen",
    "wof:name":"Gastst\u00e4tte Rudi D\u00fcker",
    "wof:placetype":"venue"
},
  "geometry": {"coordinates":[8.7827348709,52.2398262024],"type":"Point"}
}