{
  "type": "Feature",
  "properties": {
    "iso:country":"DE",
    "sg:address":"B\u00fcrgerweide 62",
    "sg:city":"Hamburg",
    "sg:phone":"+49 40/2503965",
    "sg:postcode":"20535",
    "sg:province":"Hamburg",
    "wof:name":"Treffpunkt Matic Radich",
    "wof:placetype":"venue"
},
  "geometry": {"coordinates":[10.0358705521,53.5580215454],"type":"Point"}
}