{
  "type": "Feature",
  "properties": {
    "iso:country":"DE",
    "sg:address":"Olfener Str. 113",
    "sg:city":"Selm",
    "sg:phone":"+49 2592/20022",
    "sg:postcode":"59379",
    "sg:province":"Nordrhein-Westfalen",
    "wof:name":"Taxi- Und Mietwagen Unger Gmbh",
    "wof:placetype":"venue"
},
  "geometry": {"coordinates":[7.4400119781,51.7072868347],"type":"Point"}
}