{
  "type": "Feature",
  "properties": {
    "iso:country":"DE",
    "sg:address":"Ratswaage 1",
    "sg:city":"Buttst\u00e4dt",
    "sg:phone":"+49 36373/40485",
    "sg:postcode":"99628",
    "sg:province":"Th\u00fcringen",
    "wof:name":"B. Francke",
    "wof:placetype":"venue"
},
  "geometry": {"coordinates":[11.4167985916,51.1230926514],"type":"Point"}
}