{
  "type": "Feature",
  "properties": {
    "iso:country":"DE",
    "sg:address":"Ringstr. 7",
    "sg:city":"Eschenbach",
    "sg:phone":"+49 7161/44043",
    "sg:postcode":"73107",
    "sg:province":"Baden-W\u00fcrttemberg",
    "wof:name":"Ullrich Keicher Innenarchitekt",
    "wof:placetype":"venue"
},
  "geometry": {"coordinates":[9.670588,48.653156],"type":"Point"}
}