{
  "type": "Feature",
  "properties": {
    "iso:country":"DE",
    "sg:address":"Luitpoldstr. 29",
    "sg:city":"Helmbrechts",
    "sg:phone":"+49 9252/91240",
    "sg:postcode":"95233",
    "sg:province":"Bayern",
    "wof:name":"Stadt-apotheke Inh. J\u00fcrgen Gigl",
    "wof:placetype":"venue"
},
  "geometry": {"coordinates":[11.717819,50.239807],"type":"Point"}
}