{
  "type": "Feature",
  "properties": {
    "iso:country":"DE",
    "sg:address":"Ringstr. 13",
    "sg:city":"Solms",
    "sg:phone":"+49 6442/7175",
    "sg:postcode":"35606",
    "sg:province":"Hessen",
    "wof:name":"Thomas Becker",
    "wof:placetype":"venue"
},
  "geometry": {"coordinates":[8.3977117538,50.556602478],"type":"Point"}
}