{
  "type": "Feature",
  "properties": {
    "iso:country":"DE",
    "sg:address":"Koblenzer Str. 149",
    "sg:city":"Mayen",
    "sg:phone":"+49 2651/43113",
    "sg:postcode":"56727",
    "sg:province":"Rheinland-Pfalz",
    "wof:name":"Kurt Welsch Karosseriebau Inh. Michael Dietz E. K.",
    "wof:placetype":"venue"
},
  "geometry": {"coordinates":[7.236427,50.32819],"type":"Point"}
}