{
  "type": "Feature",
  "properties": {
    "iso:country":"DE",
    "sg:address":"Heumarkt 11",
    "sg:city":"Volkmarsen",
    "sg:phone":"+49 5693/995384",
    "sg:postcode":"34471",
    "sg:province":"Hessen",
    "wof:name":"Martina Hohmann-michels",
    "wof:placetype":"venue"
},
  "geometry": {"coordinates":[9.1146326065,51.4110794067],"type":"Point"}
}