{
  "type": "Feature",
  "properties": {
    "iso:country":"DE",
    "sg:address":"Buchenweg 34",
    "sg:city":"Rudersberg",
    "sg:phone":"+49 7183/929484",
    "sg:postcode":"73635",
    "sg:province":"Baden-W\u00fcrttemberg",
    "wof:name":"Rudolf K\u00f6ngeter Steuerberater",
    "wof:placetype":"venue"
},
  "geometry": {"coordinates":[9.5176229477,48.8861732483],"type":"Point"}
}