{
  "type": "Feature",
  "properties": {
    "iso:country":"DE",
    "sg:address":"Bahnhofstr. 64",
    "sg:city":"Falkensee",
    "sg:phone":"+49 3322/3433",
    "sg:postcode":"14612",
    "sg:province":"Brandenburg",
    "wof:name":"Ep: Schoepe",
    "wof:placetype":"venue"
},
  "geometry": {"coordinates":[13.0932531357,52.5612792969],"type":"Point"}
}