{
  "type": "Feature",
  "properties": {
    "iso:country":"DE",
    "sg:address":"Friedrich-Ebert-Str. 44",
    "sg:city":"Nordenham",
    "sg:phone":"+49 4731/4202",
    "sg:postcode":"26954",
    "sg:province":"Niedersachsen",
    "wof:name":"Viktoria-apotheke",
    "wof:placetype":"venue"
},
  "geometry": {"coordinates":[8.485946,53.488499],"type":"Point"}
}