{
  "type": "Feature",
  "properties": {
    "iso:country":"DE",
    "sg:address":"Hans-Graf-Sponeck-Str. 29",
    "sg:city":"Germersheim",
    "sg:phone":"+49 7274/4029",
    "sg:postcode":"76726",
    "sg:province":"Rheinland-Pfalz",
    "wof:name":"Chr. Leukhardt Steuerberaterin",
    "wof:placetype":"venue"
},
  "geometry": {"coordinates":[8.3635921478,49.2120666504],"type":"Point"}
}