{
  "type": "Feature",
  "properties": {
    "iso:country":"DE",
    "sg:address":"Adalbertstr. 41d",
    "sg:city":"Aachen",
    "sg:phone":"+49 241/402363",
    "sg:postcode":"52062",
    "sg:province":"Nordrhein-Westfalen",
    "wof:name":"Yous Fashion Yuocef Sahraoui",
    "wof:placetype":"venue"
},
  "geometry": {"coordinates":[6.09047,50.77515],"type":"Point"}
}