{
  "type": "Feature",
  "properties": {
    "iso:country":"DE",
    "sg:address":"Hauptstr. 80",
    "sg:city":"Steinheim",
    "sg:phone":"+49 7329/6519",
    "sg:postcode":"89555",
    "sg:province":"Baden-W\u00fcrttemberg",
    "wof:name":"Heinz Fr\u00fcholz",
    "wof:placetype":"venue"
},
  "geometry": {"coordinates":[10.059461,48.691925],"type":"Point"}
}