{
  "type": "Feature",
  "properties": {
    "iso:country":"DE",
    "sg:address":"Rotebergstr. 8",
    "sg:city":"Neustadt",
    "sg:phone":"+49 6692/6502",
    "sg:postcode":"35279",
    "sg:province":"Hessen",
    "wof:name":"Wiegand Happel",
    "wof:placetype":"venue"
},
  "geometry": {"coordinates":[9.104422,50.899601],"type":"Point"}
}