{
  "type": "Feature",
  "properties": {
    "iso:country":"DE",
    "sg:address":"Am Sportfeld 3A",
    "sg:city":"Mainz",
    "sg:phone":"+49 6131/688905",
    "sg:postcode":"55124",
    "sg:province":"Rheinland-Pfalz",
    "wof:name":"Karlos Pilsstube",
    "wof:placetype":"venue"
},
  "geometry": {"coordinates":[8.2085037231,50.0074691772],"type":"Point"}
}