{
  "type": "Feature",
  "properties": {
    "iso:country":"DE",
    "sg:address":"Westliche Hauptstr. 33",
    "sg:city":"\u00d6stringen",
    "sg:phone":"+49 7259/2245",
    "sg:postcode":"76684",
    "sg:province":"Baden-W\u00fcrttemberg",
    "wof:name":"Musikexpre\u00df",
    "wof:placetype":"venue"
},
  "geometry": {"coordinates":[8.790743,49.175922],"type":"Point"}
}