{
  "type": "Feature",
  "properties": {
    "iso:country":"DE",
    "sg:address":"latte 23",
    "sg:city":"berlin",
    "sg:phone":"+49 30/90938408",
    "sg:postcode":"14089",
    "sg:province":"Berlin",
    "wof:name":"Erotikchat,sexcams,liveshows,gratiskontakte, Chat",
    "wof:placetype":"venue"
},
  "geometry": {"coordinates":[13.142568,52.453018],"type":"Point"}
}