{
  "type": "Feature",
  "properties": {
    "iso:country":"DE",
    "sg:address":"Grabengasse 10",
    "sg:city":"Wei\u00dfenstadt",
    "sg:phone":"+49 9253/1397",
    "sg:postcode":"95163",
    "sg:province":"Bayern",
    "wof:name":"Renate B\u00f6hm",
    "wof:placetype":"venue"
},
  "geometry": {"coordinates":[11.886737,50.102119],"type":"Point"}
}