{
  "type": "Feature",
  "properties": {
    "iso:country":"DE",
    "sg:address":"Schulstr. 9",
    "sg:city":"Glash\u00fctte",
    "sg:phone":"+49 35053/48536",
    "sg:postcode":"01768",
    "sg:province":"Sachsen",
    "wof:name":"Feinmechanik Glash\u00fctte Gmbh",
    "wof:placetype":"venue"
},
  "geometry": {"coordinates":[13.7774324417,50.8533973694],"type":"Point"}
}