{
  "type": "Feature",
  "properties": {
    "iso:country":"DE",
    "sg:address":"Keil 22",
    "sg:city":"Geesthacht",
    "sg:phone":"+49 4152/78194",
    "sg:postcode":"21502",
    "sg:province":"Schleswig-Holstein",
    "wof:name":"Traute Vo\u00df",
    "wof:placetype":"venue"
},
  "geometry": {"coordinates":[10.3679599762,53.4411125183],"type":"Point"}
}