{
  "type": "Feature",
  "properties": {
    "iso:country":"DE",
    "sg:address":"Kanzelweg 1",
    "sg:city":"Coburg",
    "sg:phone":"+49 9561/39435",
    "sg:postcode":"96450",
    "sg:province":"Bayern",
    "wof:name":"Hans-joachim Schulze",
    "wof:placetype":"venue"
},
  "geometry": {"coordinates":[10.9337825775,50.255897522],"type":"Point"}
}