{
  "type": "Feature",
  "properties": {
    "iso:country":"DE",
    "sg:address":"Ringstr. 42",
    "sg:city":"Taufkirchen",
    "sg:phone":"+49 8084/93100",
    "sg:postcode":"84416",
    "sg:province":"Bayern",
    "wof:name":"Wolfgang Kruse Steuerberater",
    "wof:placetype":"venue"
},
  "geometry": {"coordinates":[12.1277532578,48.3480300903],"type":"Point"}
}