{
  "type": "Feature",
  "properties": {
    "iso:country":"DE",
    "sg:address":"Fellbacher Str. 66",
    "sg:city":"Fellbach",
    "sg:phone":"+49 711/512298",
    "sg:postcode":"70736",
    "sg:province":"Baden-W\u00fcrttemberg",
    "wof:name":"Elmar Friz",
    "wof:placetype":"venue"
},
  "geometry": {"coordinates":[9.2657899857,48.8286590576],"type":"Point"}
}