{
  "type": "Feature",
  "properties": {
    "iso:country":"DE",
    "sg:address":"Trebbiner Str. 9",
    "sg:city":"Berlin",
    "sg:phone":"+49 30/25484133",
    "sg:postcode":"10963",
    "sg:province":"Berlin",
    "wof:name":"Historisches Archiv F\u00fcr Verkehr Und Technik",
    "wof:placetype":"venue"
},
  "geometry": {"coordinates":[13.37664,52.498585],"type":"Point"}
}