{
  "type": "Feature",
  "properties": {
    "iso:country":"DE",
    "sg:address":"Hofstr. 18",
    "sg:city":"Kirschweiler",
    "sg:phone":"+49 6781/31918",
    "sg:postcode":"55743",
    "sg:province":"Rheinland-Pfalz",
    "wof:name":"C. Und W. Stauer",
    "wof:placetype":"venue"
},
  "geometry": {"coordinates":[7.2385840416,49.7534255981],"type":"Point"}
}