{
  "type": "Feature",
  "properties": {
    "iso:country":"DE",
    "sg:address":"Heerstr. 1",
    "sg:city":"Hungen",
    "sg:phone":"+49 6402/2272",
    "sg:postcode":"35410",
    "sg:province":"Hessen",
    "wof:name":"Ernst Hoppe",
    "wof:placetype":"venue"
},
  "geometry": {"coordinates":[8.911153,50.518494],"type":"Point"}
}