{
  "type": "Feature",
  "properties": {
    "iso:country":"DE",
    "sg:address":"Hille-Mertens-Str. 47",
    "sg:city":"Lilienthal",
    "sg:phone":"+49 4298/698097",
    "sg:postcode":"28865",
    "sg:province":"Niedersachsen",
    "wof:name":"Baustudio Lilienthal Gmbh",
    "wof:placetype":"venue"
},
  "geometry": {"coordinates":[8.916147,53.155663],"type":"Point"}
}