{
  "type": "Feature",
  "properties": {
    "iso:country":"DE",
    "sg:address":"Weseloher Str. 2",
    "sg:city":"Engeln",
    "sg:phone":"+49 4247/477",
    "sg:postcode":"27305",
    "sg:province":"Niedersachsen",
    "wof:name":"Andreas Schmitz",
    "wof:placetype":"venue"
},
  "geometry": {"coordinates":[8.901699,52.804562],"type":"Point"}
}