{
  "type": "Feature",
  "properties": {
    "iso:country":"DE",
    "sg:address":"Thomas-Mann-Str. 6",
    "sg:city":"Rostock",
    "sg:postcode":"18055",
    "sg:province":"Mecklenburg-Vorpommern",
    "wof:name":"Dr. Med. Ulrich Helmke",
    "wof:placetype":"venue"
},
  "geometry": {"coordinates":[12.134037,54.080624],"type":"Point"}
}