{
  "type": "Feature",
  "properties": {
    "iso:country":"DE",
    "sg:address":"Gl\u00fcck-Auf-Weg 22",
    "sg:city":"Aue",
    "sg:phone":"+49 3771/551552",
    "sg:postcode":"08280",
    "sg:province":"Sachsen",
    "wof:name":"Gartenheim Gl\u00fcck Auf",
    "wof:placetype":"venue"
},
  "geometry": {"coordinates":[12.7012443542,50.5935440063],"type":"Point"}
}