{
  "type": "Feature",
  "properties": {
    "iso:country":"DE",
    "sg:address":"Friedenstr. 52",
    "sg:city":"Friedrichsthal",
    "sg:phone":"+49 6897/87301",
    "sg:postcode":"66299",
    "sg:province":"Saarland",
    "wof:name":"T. Hau",
    "wof:placetype":"venue"
},
  "geometry": {"coordinates":[7.10131,49.324432],"type":"Point"}
}