{
  "type": "Feature",
  "properties": {
    "iso:country":"DE",
    "sg:address":"Sch\u00f6nbornstr. 1/2",
    "sg:city":"W\u00fcrzburg",
    "sg:phone":"+49 931/3560700",
    "sg:postcode":"97070",
    "sg:province":"Bayern",
    "wof:name":"Bayerische Hypo- Und Vereinsbank Ag",
    "wof:placetype":"venue"
},
  "geometry": {"coordinates":[9.9307537079,49.7951774597],"type":"Point"}
}