{
  "type": "Feature",
  "properties": {
    "iso:country":"DE",
    "sg:address":"Walter-Gieseking-Str. 22",
    "sg:city":"Hannover",
    "sg:phone":"+49 511/2807122",
    "sg:postcode":"30159",
    "sg:province":"Niedersachsen",
    "wof:name":"Rudolf Von Bennigsen-stiftung",
    "wof:placetype":"venue"
},
  "geometry": {"coordinates":[9.7541389465,52.3713684082],"type":"Point"}
}