{
  "type": "Feature",
  "properties": {
    "iso:country":"DE",
    "sg:address":"Neuer Weg 2",
    "sg:city":"Eberbach",
    "sg:postcode":"69412",
    "sg:province":"Baden-W\u00fcrttemberg",
    "wof:name":"Grosso",
    "wof:placetype":"venue"
},
  "geometry": {"coordinates":[8.9837379456,49.4670333862],"type":"Point"}
}