{
  "type": "Feature",
  "properties": {
    "iso:country":"DE",
    "sg:address":"Weidenstr. 1",
    "sg:city":"Emmerich",
    "sg:phone":"+49 2822/4889",
    "sg:postcode":"46446",
    "sg:province":"Nordrhein-Westfalen",
    "wof:name":"H. Feldhaus",
    "wof:placetype":"venue"
},
  "geometry": {"coordinates":[6.205458,51.849716],"type":"Point"}
}