{
  "type": "Feature",
  "properties": {
    "iso:country":"DE",
    "sg:address":"Kewelsstr. 9",
    "sg:city":"Mettlach",
    "sg:phone":"+49 6868/1626",
    "sg:postcode":"66693",
    "sg:province":"Saarland",
    "wof:name":"Rohde & Patt Verlagsgesellschaft",
    "wof:placetype":"venue"
},
  "geometry": {"coordinates":[6.4982318878,49.4748840332],"type":"Point"}
}