{
  "type": "Feature",
  "properties": {
    "iso:country":"DE",
    "sg:address":"Turmstr. 43",
    "sg:city":"Neu-Ulm",
    "sg:phone":"+49 731/82020",
    "sg:postcode":"89231",
    "sg:province":"Bayern",
    "wof:name":"W. Miemietz Verlag",
    "wof:placetype":"venue"
},
  "geometry": {"coordinates":[10.0018005371,48.3901786804],"type":"Point"}
}