{
  "type": "Feature",
  "properties": {
    "iso:country":"DE",
    "sg:address":"Kirchstr. 13a",
    "sg:city":"Gro\u00dfrosseln",
    "sg:phone":"+49 6898/42243",
    "sg:postcode":"66352",
    "sg:province":"Saarland",
    "wof:name":"Gerhard Scheer",
    "wof:placetype":"venue"
},
  "geometry": {"coordinates":[6.8374199867,49.2053718567],"type":"Point"}
}