{
  "type": "Feature",
  "properties": {
    "iso:country":"DE",
    "sg:address":"Fritz-Reuter-Str. 11",
    "sg:city":"Berlin",
    "sg:phone":"+49 30/56698124",
    "sg:postcode":"12623",
    "sg:province":"Berlin",
    "wof:name":"Pebg Bauplanung Concept Gmbh",
    "wof:placetype":"venue"
},
  "geometry": {"coordinates":[13.613366,52.510799],"type":"Point"}
}