{
  "type": "Feature",
  "properties": {
    "iso:country":"DE",
    "sg:address":"Erich-Weinert-Str. 1",
    "sg:city":"Premnitz",
    "sg:phone":"+49 3386/289930",
    "sg:postcode":"14727",
    "sg:province":"Brandenburg",
    "wof:name":"Hummel Profi- Und Heimwerkerm\u00e4rkte",
    "wof:placetype":"venue"
},
  "geometry": {"coordinates":[12.3429660797,52.5287704468],"type":"Point"}
}