{
  "type": "Feature",
  "properties": {
    "iso:country":"DE",
    "sg:address":"Sch\u00f6nstr. 85",
    "sg:city":"M\u00fcnchen",
    "sg:phone":"+49 89/62500591",
    "sg:postcode":"81543",
    "sg:province":"Bayern",
    "wof:name":"Blumen-griebl",
    "wof:placetype":"venue"
},
  "geometry": {"coordinates":[11.561949,48.103905],"type":"Point"}
}