{
  "type": "Feature",
  "properties": {
    "iso:country":"DE",
    "sg:address":"Hauptstr. 192",
    "sg:city":"Heimbuchenthal",
    "sg:phone":"+49 6092/263",
    "sg:postcode":"63872",
    "sg:province":"Bayern",
    "wof:name":"Krone",
    "wof:placetype":"venue"
},
  "geometry": {"coordinates":[9.293633461,49.8824310303],"type":"Point"}
}