{
  "type": "Feature",
  "properties": {
    "iso:country":"DE",
    "sg:address":"Xantener Str. 22",
    "sg:city":"Meerbusch",
    "sg:phone":"+49 2159/7292",
    "sg:postcode":"40670",
    "sg:province":"Nordrhein-Westfalen",
    "wof:name":"Haus Baumeister",
    "wof:placetype":"venue"
},
  "geometry": {"coordinates":[6.6596589088,51.2858810425],"type":"Point"}
}