{
  "type": "Feature",
  "properties": {
    "iso:country":"DE",
    "sg:address":"B\u00fchren 15",
    "sg:city":"Breckerfeld",
    "sg:phone":"+49 2337/8657",
    "sg:postcode":"58339",
    "sg:province":"Nordrhein-Westfalen",
    "wof:name":"Breckfelder Stadtmuseum E. V. Hannelore Berninghaus",
    "wof:placetype":"venue"
},
  "geometry": {"coordinates":[7.513496,51.269958],"type":"Point"}
}