{
  "type": "Feature",
  "properties": {
    "iso:country":"DE",
    "sg:address":"Brunngasse 1",
    "sg:city":"Teugn",
    "sg:phone":"+49 9405/1721",
    "sg:postcode":"93356",
    "sg:province":"Bayern",
    "wof:name":"M. Knott",
    "wof:placetype":"venue"
},
  "geometry": {"coordinates":[12.015503,48.892834],"type":"Point"}
}