{
  "type": "Feature",
  "properties": {
    "iso:country":"DE",
    "sg:address":"Falkenseer Chaussee 21",
    "sg:city":"Berlin",
    "sg:phone":"+49 30/3721988",
    "sg:postcode":"13583",
    "sg:province":"Berlin",
    "wof:name":"Atlas-apotheke",
    "wof:placetype":"venue"
},
  "geometry": {"coordinates":[13.187632,52.547211],"type":"Point"}
}