{
  "type": "Feature",
  "properties": {
    "iso:country":"DE",
    "sg:address":"W\u00fcrttembergallee 26",
    "sg:city":"Berlin",
    "sg:phone":"+49 30/3046766",
    "sg:postcode":"14052",
    "sg:province":"Berlin",
    "wof:name":"Barbara Behrens Dolmetscherin",
    "wof:placetype":"venue"
},
  "geometry": {"coordinates":[13.263785,52.511047],"type":"Point"}
}