{
  "type": "Feature",
  "properties": {
    "iso:country":"DE",
    "sg:address":"Harvestehuder Weg 53",
    "sg:city":"Hamburg",
    "sg:postcode":"20149",
    "sg:province":"Hamburg",
    "wof:name":"Real Estate Venture Capital Gmbh",
    "wof:placetype":"venue"
},
  "geometry": {"coordinates":[9.997816,53.578045],"type":"Point"}
}