{
  "type": "Feature",
  "properties": {
    "iso:country":"DE",
    "sg:address":"Zum Pfaffenborn",
    "sg:city":"Birstein",
    "sg:phone":"+49 6054/8040",
    "sg:postcode":"63633",
    "sg:province":"Hessen",
    "wof:name":"Inside Werbungs- Und Vermittlungs Gmbh",
    "wof:placetype":"venue"
},
  "geometry": {"coordinates":[9.323633194,50.4381752014],"type":"Point"}
}