{
  "type": "Feature",
  "properties": {
    "iso:country":"DE",
    "sg:address":"Allee der Kosmonauten 67",
    "sg:city":"Berlin",
    "sg:phone":"+49 30/5427071",
    "sg:postcode":"12681",
    "sg:province":"Berlin",
    "wof:name":"Klub 2000",
    "wof:placetype":"venue"
},
  "geometry": {"coordinates":[13.543566,52.527836],"type":"Point"}
}