{
  "type": "Feature",
  "properties": {
    "iso:country":"DE",
    "sg:address":"Reinh\u00e4user Landstr. 25",
    "sg:city":"G\u00f6ttingen",
    "sg:phone":"+49 551/706273",
    "sg:postcode":"37083",
    "sg:province":"Niedersachsen",
    "wof:name":"S\u00fcd-apotheke",
    "wof:placetype":"venue"
},
  "geometry": {"coordinates":[9.939946,51.525089],"type":"Point"}
}