{
  "type": "Feature",
  "properties": {
    "iso:country":"DE",
    "sg:address":"Rudolf-Diesel-Str. 28",
    "sg:city":"Wesel",
    "sg:phone":"+49 4928/1952770",
    "sg:postcode":"46485",
    "sg:province":"Nordrhein-Westfalen",
    "wof:name":"Herco K\u00dchltechnik Hermanns & Co Gmbh",
    "wof:placetype":"venue"
},
  "geometry": {"coordinates":[6.669563,51.664566],"type":"Point"}
}