{
  "type": "Feature",
  "properties": {
    "iso:country":"DE",
    "sg:address":"Birkenstr. 1",
    "sg:city":"Bielefeld",
    "sg:phone":"+49 521/48596",
    "sg:postcode":"33649",
    "sg:province":"Nordrhein-Westfalen",
    "wof:name":"Caspers Dentaltechnik Gmbh",
    "wof:placetype":"venue"
},
  "geometry": {"coordinates":[8.462428,51.971596],"type":"Point"}
}