{
  "type": "Feature",
  "properties": {
    "iso:country":"DE",
    "sg:address":"Schlo\u00dfstra\u00dfe 11",
    "sg:city":"Gera",
    "sg:phone":"+49 365",
    "sg:postcode":"07545",
    "sg:province":"Th\u00fcringen",
    "wof:name":"Sparkasse Gera-greiz",
    "wof:placetype":"venue"
},
  "geometry": {"coordinates":[12.0802936554,50.8786621094],"type":"Point"}
}