{
  "type": "Feature",
  "properties": {
    "iso:country":"DE",
    "sg:address":"Saarbr\u00fccker Str. 211",
    "sg:city":"Saarbr\u00fccken",
    "sg:phone":"+49 6897/761108",
    "sg:postcode":"66125",
    "sg:province":"Saarland",
    "wof:name":"Gerd Jungmann Jun. Masseur",
    "wof:placetype":"venue"
},
  "geometry": {"coordinates":[7.03337,49.275288],"type":"Point"}
}