{
  "type": "Feature",
  "properties": {
    "iso:country":"DE",
    "sg:address":"Uferstr. 5 b",
    "sg:city":"Burg",
    "sg:phone":"+49 3921/944935",
    "sg:postcode":"39288",
    "sg:province":"Sachsen-Anhalt",
    "wof:name":"Alicke & Gnensch Gbr",
    "wof:placetype":"venue"
},
  "geometry": {"coordinates":[11.8399572372,52.2781295776],"type":"Point"}
}