{
  "type": "Feature",
  "properties": {
    "iso:country":"DE",
    "sg:address":"Hauptstr. 82",
    "sg:city":"Winnenden",
    "sg:phone":"+49 7195/74577",
    "sg:postcode":"71364",
    "sg:province":"Baden-W\u00fcrttemberg",
    "wof:name":"Wilhelm Eger",
    "wof:placetype":"venue"
},
  "geometry": {"coordinates":[9.430680275,48.8646316528],"type":"Point"}
}