{
  "type": "Feature",
  "properties": {
    "iso:country":"DE",
    "sg:address":"Dunantstr. 5",
    "sg:city":"Eppingen",
    "sg:phone":"+49 7262/912057",
    "sg:postcode":"75031",
    "sg:province":"Baden-W\u00fcrttemberg",
    "wof:name":"Clip Clap International Gmbh",
    "wof:placetype":"venue"
},
  "geometry": {"coordinates":[8.9187631607,49.1422195435],"type":"Point"}
}