{
  "type": "Feature",
  "properties": {
    "iso:country":"DE",
    "sg:address":"Im Rotental 10",
    "sg:city":"Polch",
    "sg:postcode":"56751",
    "sg:province":"Rheinland-Pfalz",
    "wof:name":"Flashpoint Ag",
    "wof:placetype":"venue"
},
  "geometry": {"coordinates":[7.305413,50.30817],"type":"Point"}
}