{
  "type": "Feature",
  "properties": {
    "iso:country":"DE",
    "sg:address":"Kemnather Str. 3",
    "sg:city":"Wunsiedel",
    "sg:phone":"+49 9232/2288",
    "sg:postcode":"95632",
    "sg:province":"Bayern",
    "wof:name":"Sozialberatungsstelle Kreis-caritassekretariat",
    "wof:placetype":"venue"
},
  "geometry": {"coordinates":[12.000817,50.035835],"type":"Point"}
}