{
  "type": "Feature",
  "properties": {
    "iso:country":"DE",
    "sg:address":"Krebsgasse 8",
    "sg:city":"K\u00f6ln",
    "sg:phone":"+49 221/2576547",
    "sg:postcode":"50667",
    "sg:province":"Nordrhein-Westfalen",
    "wof:name":"City Atelier",
    "wof:placetype":"venue"
},
  "geometry": {"coordinates":[6.9502019882,50.9368019104],"type":"Point"}
}