{
  "type": "Feature",
  "properties": {
    "iso:country":"DE",
    "sg:address":"Alfredstr. 35",
    "sg:city":"Freudenstadt",
    "sg:phone":"+49 7441/2448",
    "sg:postcode":"72250",
    "sg:province":"Baden-W\u00fcrttemberg",
    "wof:name":"J\u00fcrgen P. Rumpp Elektroinstallation",
    "wof:placetype":"venue"
},
  "geometry": {"coordinates":[8.409965,48.462105],"type":"Point"}
}