{
  "type": "Feature",
  "properties": {
    "iso:country":"DE",
    "sg:address":"Hauptstr. 28",
    "sg:city":"Herschbroich",
    "sg:phone":"+49 2691/7140",
    "sg:postcode":"53518",
    "sg:province":"Rheinland-Pfalz",
    "wof:name":"Erich Koch",
    "wof:placetype":"venue"
},
  "geometry": {"coordinates":[6.9711661339,50.3648529053],"type":"Point"}
}