{
  "type": "Feature",
  "properties": {
    "iso:country":"DE",
    "sg:address":"Ahornweg 32",
    "sg:city":"Gro\u00df-Gerau",
    "sg:phone":"+49 6152/59350",
    "sg:postcode":"64521",
    "sg:province":"Hessen",
    "wof:name":"Gecko Mode E. Tenne",
    "wof:placetype":"venue"
},
  "geometry": {"coordinates":[8.462589,49.904083],"type":"Point"}
}