{
  "type": "Feature",
  "properties": {
    "iso:country":"DE",
    "sg:address":"Am Stein 5",
    "sg:city":"Biebertal",
    "sg:phone":"+49 6446/509",
    "sg:postcode":"35444",
    "sg:province":"Hessen",
    "wof:name":"Hans-j\u00fcrgen Becker",
    "wof:placetype":"venue"
},
  "geometry": {"coordinates":[8.5742101669,50.6709976196],"type":"Point"}
}