{
  "type": "Feature",
  "properties": {
    "iso:country":"DE",
    "sg:address":"Surheimer Weg 3",
    "sg:city":"M\u00fcnchen",
    "sg:phone":"+49 89/781459",
    "sg:postcode":"81379",
    "sg:province":"Bayern",
    "wof:name":"Vereingastst\u00e4tte Vereinsheim",
    "wof:placetype":"venue"
},
  "geometry": {"coordinates":[11.5182971954,48.1039733887],"type":"Point"}
}