{
  "type": "Feature",
  "properties": {
    "iso:country":"DE",
    "sg:address":"B\u00fcro/Werk :Paul-Gruner-Str. 6-8",
    "sg:city":"Leipzig",
    "sg:phone":"+49 341/2138820",
    "sg:postcode":"04107",
    "sg:province":"Sachsen",
    "wof:name":"Mwl - Modellbahnwerkstatt Leipzig",
    "wof:placetype":"venue"
},
  "geometry": {"coordinates":[12.3806219101,51.3276786804],"type":"Point"}
}