{
  "type": "Feature",
  "properties": {
    "iso:country":"DE",
    "sg:address":"Neustr. 40",
    "sg:city":"Gronau",
    "sg:phone":"+49 2562/97900",
    "sg:postcode":"48599",
    "sg:province":"Nordrhein-Westfalen",
    "wof:name":"Kochl\u00f6ffel Gmbh",
    "wof:placetype":"venue"
},
  "geometry": {"coordinates":[7.0256309509,52.2109718323],"type":"Point"}
}