{
  "type": "Feature",
  "properties": {
    "iso:country":"DE",
    "sg:address":"Erlanger Str. 2",
    "sg:city":"Bayreuth",
    "sg:phone":"+49 921/512630",
    "sg:postcode":"95444",
    "sg:province":"Bayern",
    "wof:name":"Knutschfleck",
    "wof:placetype":"venue"
},
  "geometry": {"coordinates":[11.5691165924,49.9433860779],"type":"Point"}
}