{
  "type": "Feature",
  "properties": {
    "iso:country":"DE",
    "sg:address":"Daimlerstr. 9",
    "sg:city":"Gerlingen",
    "sg:postcode":"70839",
    "sg:province":"Baden-W\u00fcrttemberg",
    "wof:name":"Medpharm Verlag Gmbh",
    "wof:placetype":"venue"
},
  "geometry": {"coordinates":[9.0734548569,48.8032073975],"type":"Point"}
}