{
  "type": "Feature",
  "properties": {
    "iso:country":"DE",
    "sg:address":"Moylaender Strasse 17",
    "sg:city":"Bedburg-Hau",
    "sg:phone":"+49 2824/92828",
    "sg:postcode":"47551",
    "sg:province":"Nordrhein-Westfalen",
    "wof:name":"Gaultheria - Baumschulen J\u00fcrgen Kammann Gbr",
    "wof:placetype":"venue"
},
  "geometry": {"coordinates":[6.2207999229,51.7374534607],"type":"Point"}
}