{
  "type": "Feature",
  "properties": {
    "iso:country":"DE",
    "sg:address":"Bert-Brecht-Str. 68",
    "sg:city":"Karlsruhe",
    "sg:phone":"+49 721/573501",
    "sg:postcode":"76189",
    "sg:province":"Baden-W\u00fcrttemberg",
    "wof:name":"Badische Backstub Friedrich Und Erika Weber Gmbh",
    "wof:placetype":"venue"
},
  "geometry": {"coordinates":[8.339062,49.000286],"type":"Point"}
}