{
  "type": "Feature",
  "properties": {
    "iso:country":"DE",
    "sg:address":"Bachweg 21",
    "sg:city":"Oderwitz",
    "sg:phone":"+49 35842/27467",
    "sg:postcode":"02791",
    "sg:province":"Sachsen",
    "wof:name":"Volkshaus",
    "wof:placetype":"venue"
},
  "geometry": {"coordinates":[14.7340536118,50.9516906738],"type":"Point"}
}