{
  "type": "Feature",
  "properties": {
    "iso:country":"DE",
    "sg:address":"Berliner Str. 40",
    "sg:city":"Dresden",
    "sg:phone":"+49 351/867400",
    "sg:postcode":"01067",
    "sg:province":"Sachsen",
    "wof:name":"Bto B\u00fcrozentrum Gmbh",
    "wof:placetype":"venue"
},
  "geometry": {"coordinates":[13.714791,51.055744],"type":"Point"}
}