{
  "type": "Feature",
  "properties": {
    "iso:country":"DE",
    "sg:address":"Hegaustr. 24",
    "sg:city":"Singen",
    "sg:phone":"+49 7731/63688",
    "sg:postcode":"78224",
    "sg:province":"Baden-W\u00fcrttemberg",
    "wof:name":"Cafe Swiss Inn",
    "wof:placetype":"venue"
},
  "geometry": {"coordinates":[8.839252,47.759621],"type":"Point"}
}