{
  "type": "Feature",
  "properties": {
    "iso:country":"DE",
    "sg:address":"Ibrunnenstr. 9",
    "sg:city":"Lauchringen",
    "sg:phone":"+49 7741/670303",
    "sg:postcode":"79787",
    "sg:province":"Baden-W\u00fcrttemberg",
    "wof:name":"Bio-crom Gmbh",
    "wof:placetype":"venue"
},
  "geometry": {"coordinates":[8.296265,47.63203],"type":"Point"}
}