{
  "type": "Feature",
  "properties": {
    "iso:country":"DE",
    "sg:address":"Posener Weg 2",
    "sg:city":"Sersheim",
    "sg:phone":"+49 7042/33768",
    "sg:postcode":"74372",
    "sg:province":"Baden-W\u00fcrttemberg",
    "wof:name":"Bernhard Blumenthal",
    "wof:placetype":"venue"
},
  "geometry": {"coordinates":[9.0138597488,48.9556617737],"type":"Point"}
}