{
  "type": "Feature",
  "properties": {
    "iso:country":"DE",
    "sg:address":"Wilhelmstr. 17",
    "sg:city":"Br\u00fchl",
    "sg:phone":"+49 221/353335",
    "sg:postcode":"50321",
    "sg:province":"Nordrhein-Westfalen",
    "wof:name":"Dr. Hans Opel Rechtsanwalt",
    "wof:placetype":"venue"
},
  "geometry": {"coordinates":[6.9092230797,50.8321723938],"type":"Point"}
}