{
  "type": "Feature",
  "properties": {
    "iso:country":"DE",
    "sg:address":"Teichstr. 11",
    "sg:city":"Lieskau",
    "sg:postcode":"06120",
    "sg:province":"Sachsen-Anhalt",
    "wof:name":"Dr. Med. Inge Liebal",
    "wof:placetype":"venue"
},
  "geometry": {"coordinates":[11.862735,51.501259],"type":"Point"}
}