{
  "type": "Feature",
  "properties": {
    "iso:country":"DE",
    "sg:address":"Ludwig-Thoma-Str. 3",
    "sg:city":"Lichtenstein",
    "sg:phone":"+49 7129/4157",
    "sg:postcode":"72805",
    "sg:province":"Baden-W\u00fcrttemberg",
    "wof:name":"Klaus Neuberger",
    "wof:placetype":"venue"
},
  "geometry": {"coordinates":[9.2607727051,48.4381332397],"type":"Point"}
}