{
  "type": "Feature",
  "properties": {
    "iso:country":"DE",
    "sg:address":"Wildenbruchstr. 3",
    "sg:city":"Frankfurt",
    "sg:phone":"+49 335/5005434",
    "sg:postcode":"15230",
    "sg:province":"Brandenburg",
    "wof:name":"G\u00fcldendorfer Allinclusiv Maasivbau Gmbh",
    "wof:placetype":"venue"
},
  "geometry": {"coordinates":[14.533759,52.345833],"type":"Point"}
}