{
  "type": "Feature",
  "properties": {
    "iso:country":"DE",
    "sg:address":"Wahlenstr. 1",
    "sg:city":"Regensburg",
    "sg:phone":"+49 941/560608",
    "sg:postcode":"93047",
    "sg:province":"Bayern",
    "wof:name":"Pfaff-n\u00e4hzentrum Hermann Zausinger",
    "wof:placetype":"venue"
},
  "geometry": {"coordinates":[12.0957546234,49.0199737549],"type":"Point"}
}