{
  "type": "Feature",
  "properties": {
    "iso:country":"DE",
    "sg:address":"K\u00f6lner Str. 98",
    "sg:city":"Attendorn",
    "sg:phone":"+49 2722/959524",
    "sg:postcode":"57439",
    "sg:province":"Nordrhein-Westfalen",
    "wof:name":"Siepe-system-service W\u00e4scherei-textile-mietdienste",
    "wof:placetype":"venue"
},
  "geometry": {"coordinates":[7.8903021812,51.1186256409],"type":"Point"}
}