{
  "type": "Feature",
  "properties": {
    "iso:country":"DE",
    "sg:address":"Hermine-K\u00f6rner-Str. 2",
    "sg:city":"Baunatal",
    "sg:phone":"+49 561/949860",
    "sg:postcode":"34225",
    "sg:province":"Hessen",
    "wof:name":"Dipl. Ing.-horst Gajowski Gmbh",
    "wof:placetype":"venue"
},
  "geometry": {"coordinates":[9.4084148407,51.250541687],"type":"Point"}
}