{
  "type": "Feature",
  "properties": {
    "iso:country":"DE",
    "sg:address":"Ladenstr. 33-34",
    "sg:city":"Berlin",
    "sg:phone":"+49 30/8132165",
    "sg:postcode":"14169",
    "sg:province":"Berlin",
    "wof:name":"Albert Sch\u00e4ffler Elektromeister Gmbh",
    "wof:placetype":"venue"
},
  "geometry": {"coordinates":[13.253034,52.449844],"type":"Point"}
}