{
  "type": "Feature",
  "properties": {
    "iso:country":"DE",
    "sg:address":"Goethestr. 2",
    "sg:city":"Eching",
    "sg:postcode":"85386",
    "sg:province":"Bayern",
    "wof:name":"Elichem Gmbh",
    "wof:placetype":"venue"
},
  "geometry": {"coordinates":[11.6265439987,48.2988967896],"type":"Point"}
}