{
  "type": "Feature",
  "properties": {
    "iso:country":"DE",
    "sg:address":"Pichelsdorfer Str. 131",
    "sg:city":"Berlin",
    "sg:phone":"+49 162 4485619",
    "sg:postcode":"13595",
    "sg:province":"Berlin",
    "wof:name":"Pbc Jumpshot E. V.",
    "wof:placetype":"venue"
},
  "geometry": {"coordinates":[13.1962995529,52.5262184143],"type":"Point"}
}