{
  "type": "Feature",
  "properties": {
    "iso:country":"DE",
    "sg:address":"Keplerstr. 2",
    "sg:city":"Berlin",
    "sg:phone":"+49 30/5229240",
    "sg:postcode":"10589",
    "sg:province":"Berlin",
    "wof:name":"Colibri Dentalhandel Gmbh",
    "wof:placetype":"venue"
},
  "geometry": {"coordinates":[13.3046,52.527004],"type":"Point"}
}