{
  "type": "Feature",
  "properties": {
    "iso:country":"DE",
    "sg:address":"K\u00f6lner Str. 22",
    "sg:city":"Hagen",
    "sg:phone":"+49 2331/45228",
    "sg:postcode":"58135",
    "sg:province":"Nordrhein-Westfalen",
    "wof:name":"Orient-imbiss",
    "wof:placetype":"venue"
},
  "geometry": {"coordinates":[7.4210882187,51.347442627],"type":"Point"}
}