{
  "type": "Feature",
  "properties": {
    "iso:country":"DE",
    "sg:address":"Adlerstra\u00dfe 48",
    "sg:city":"M\u00f6nchengladbach",
    "sg:phone":"+49 2161/694920",
    "sg:postcode":"41066",
    "sg:province":"Nordrhein-Westfalen",
    "wof:name":"S H-analytik",
    "wof:placetype":"venue"
},
  "geometry": {"coordinates":[6.463247,51.223705],"type":"Point"}
}