{
  "type": "Feature",
  "properties": {
    "iso:country":"DE",
    "sg:address":"Ritzenb\u00fctteler Str. 108",
    "sg:city":"Lemwerder",
    "sg:phone":"+49 421/670826",
    "sg:postcode":"27809",
    "sg:province":"Niedersachsen",
    "wof:name":"Marian Dolny",
    "wof:placetype":"venue"
},
  "geometry": {"coordinates":[8.580556,53.167076],"type":"Point"}
}