{
  "type": "Feature",
  "properties": {
    "iso:country":"DE",
    "sg:address":"An der Meierei 1",
    "sg:city":"Gro\u00df Buchwald",
    "sg:phone":"+49 4322/9212",
    "sg:postcode":"24582",
    "sg:province":"Schleswig-Holstein",
    "wof:name":"Baugesch\u00e4ft Rixen Gmbh & Co. Kg",
    "wof:placetype":"venue"
},
  "geometry": {"coordinates":[10.0826,54.16357],"type":"Point"}
}