{
  "type": "Feature",
  "properties": {
    "iso:country":"DE",
    "sg:address":"Maenherstr. 8a",
    "sg:city":"M\u00fcnchen",
    "sg:phone":"+49 89/7195398",
    "sg:postcode":"81375",
    "sg:province":"Bayern",
    "wof:name":"Bautenschutz Famielec",
    "wof:placetype":"venue"
},
  "geometry": {"coordinates":[11.501186,48.125332],"type":"Point"}
}