{
  "type": "Feature",
  "properties": {
    "iso:country":"DE",
    "sg:address":"Biberweg 33",
    "sg:city":"Troisdorf",
    "sg:phone":"+49 2241/403515",
    "sg:postcode":"53842",
    "sg:province":"Nordrhein-Westfalen",
    "wof:name":"Georg Schreiber",
    "wof:placetype":"venue"
},
  "geometry": {"coordinates":[7.104393959,50.8287582397],"type":"Point"}
}