{
  "type": "Feature",
  "properties": {
    "iso:country":"DE",
    "sg:address":"Realschulstr. 5",
    "sg:city":"Gro\u00df-Umstadt",
    "sg:phone":"+49 6078/2276",
    "sg:postcode":"64823",
    "sg:province":"Hessen",
    "wof:name":"Odenw\u00e4lder Bote",
    "wof:placetype":"venue"
},
  "geometry": {"coordinates":[8.926285,49.868523],"type":"Point"}
}