{
  "type": "Feature",
  "properties": {
    "iso:country":"DE",
    "sg:address":"Zum Gimbacher Hof 1",
    "sg:city":"Kelkheim",
    "sg:phone":"+49 6195/911327",
    "sg:postcode":"65779",
    "sg:province":"Hessen",
    "wof:name":"Dr. Heinz Gensich Und Dieter Wirth",
    "wof:placetype":"venue"
},
  "geometry": {"coordinates":[8.426074028,50.1462364197],"type":"Point"}
}