{
  "type": "Feature",
  "properties": {
    "iso:country":"DE",
    "sg:address":"Reu\u00dfensteinstr. 125",
    "sg:city":"Kirchheim",
    "sg:phone":"+49 7021/54200",
    "sg:postcode":"73230",
    "sg:province":"Baden-W\u00fcrttemberg",
    "wof:name":"Jakob Hepp Mech. Werkstatt",
    "wof:placetype":"venue"
},
  "geometry": {"coordinates":[9.482733,48.642117],"type":"Point"}
}