{
  "type": "Feature",
  "properties": {
    "iso:country":"DE",
    "sg:address":"Stra\u00dfe Des Friedens 8-12",
    "sg:city":"Radeberg",
    "sg:phone":"+49 3528/443241",
    "sg:postcode":"01454",
    "sg:province":"Sachsen",
    "wof:name":"Jungrichter & Ringel Glasformenbau Radeberg Gmbh",
    "wof:placetype":"venue"
},
  "geometry": {"coordinates":[13.9108362198,51.1139297485],"type":"Point"}
}