{
  "type": "Feature",
  "properties": {
    "iso:country":"DE",
    "sg:address":"Gartenstr. 10",
    "sg:city":"Alflen",
    "sg:phone":"+49 2678/884",
    "sg:postcode":"56828",
    "sg:province":"Rheinland-Pfalz",
    "wof:name":"A. Kr\u00e4mer",
    "wof:placetype":"venue"
},
  "geometry": {"coordinates":[7.0392751694,50.1797790527],"type":"Point"}
}