{
  "type": "Feature",
  "properties": {
    "iso:country":"DE",
    "sg:address":"Eschollbr\u00fccker Str. 39",
    "sg:city":"Darmstadt",
    "sg:phone":"+49 6151/39960",
    "sg:postcode":"64295",
    "sg:province":"Hessen",
    "wof:name":"Fikentscher Verwaltungs Gmbh",
    "wof:placetype":"venue"
},
  "geometry": {"coordinates":[8.6320438385,49.8573532104],"type":"Point"}
}