{
  "type": "Feature",
  "properties": {
    "iso:country":"DE",
    "sg:address":"H\u00fcttenwerkstr. 16",
    "sg:city":"Dillingen",
    "sg:phone":"+49 6831/71373",
    "sg:postcode":"66763",
    "sg:province":"Saarland",
    "wof:name":"Europa-kino-3",
    "wof:placetype":"venue"
},
  "geometry": {"coordinates":[6.730252,49.353565],"type":"Point"}
}