{
  "type": "Feature",
  "properties": {
    "iso:country":"DE",
    "sg:address":"Neustr. 33 d",
    "sg:city":"Moers",
    "sg:phone":"+49 2841/25152",
    "sg:postcode":"47441",
    "sg:province":"Nordrhein-Westfalen",
    "wof:name":"Illing Kg",
    "wof:placetype":"venue"
},
  "geometry": {"coordinates":[6.6230249405,51.4522895813],"type":"Point"}
}