{
  "type": "Feature",
  "properties": {
    "iso:country":"DE",
    "sg:address":"Hochfeldstr. 63",
    "sg:city":"Bocholt",
    "sg:phone":"+49 2871/225265",
    "sg:postcode":"46397",
    "sg:province":"Nordrhein-Westfalen",
    "wof:name":"Rappelkiste",
    "wof:placetype":"venue"
},
  "geometry": {"coordinates":[6.6365680695,51.8348121643],"type":"Point"}
}