{
  "type": "Feature",
  "properties": {
    "iso:country":"DE",
    "sg:address":"Knapper Str. 89",
    "sg:city":"L\u00fcdenscheid",
    "sg:phone":"+49 2351/28211",
    "sg:postcode":"58507",
    "sg:province":"Nordrhein-Westfalen",
    "wof:name":"Klaus Bruns Heilpraktiker",
    "wof:placetype":"venue"
},
  "geometry": {"coordinates":[7.6235599518,51.2195129395],"type":"Point"}
}