{
  "type": "Feature",
  "properties": {
    "iso:country":"DE",
    "sg:address":"Marktplatz 11",
    "sg:city":"Pleystein",
    "sg:phone":"+49 9654/913188",
    "sg:postcode":"92714",
    "sg:province":"Bayern",
    "wof:name":"Eduard Strigl",
    "wof:placetype":"venue"
},
  "geometry": {"coordinates":[12.409118,49.645016],"type":"Point"}
}