{
  "type": "Feature",
  "properties": {
    "iso:country":"DE",
    "sg:address":"Serkenroder Str. 96",
    "sg:city":"Finnentrop",
    "sg:phone":"+49 2721/959703",
    "sg:postcode":"57413",
    "sg:province":"Nordrhein-Westfalen",
    "wof:name":"Gerhard Schmitt",
    "wof:placetype":"venue"
},
  "geometry": {"coordinates":[7.979321,51.175953],"type":"Point"}
}