{
  "type": "Feature",
  "properties": {
    "iso:country":"DE",
    "sg:address":"Maxim-Gorki-Str. 3",
    "sg:city":"Teltow",
    "sg:phone":"+49 3328/471713",
    "sg:postcode":"14513",
    "sg:province":"Brandenburg",
    "wof:name":"Progre\u00dfinstitut F\u00fcr Wirtschaftsforschung",
    "wof:placetype":"venue"
},
  "geometry": {"coordinates":[13.2952728271,52.4093742371],"type":"Point"}
}