{
  "type": "Feature",
  "properties": {
    "iso:country":"DE",
    "sg:address":"Sehnder Str. 21",
    "sg:city":"Sehnde",
    "sg:phone":"+49 5132/86920",
    "sg:postcode":"31319",
    "sg:province":"Niedersachsen",
    "wof:name":"Hotel-motel Grillhaus Steiner",
    "wof:placetype":"venue"
},
  "geometry": {"coordinates":[9.9282426834,52.3467788696],"type":"Point"}
}