{
  "type": "Feature",
  "properties": {
    "iso:country":"DE",
    "sg:address":"M\u00fcndersche Str. 19",
    "sg:city":"Bad M\u00fcnder",
    "sg:phone":"+49 5042/989034",
    "sg:postcode":"31848",
    "sg:province":"Niedersachsen",
    "wof:name":"Restaurant Hot Pot",
    "wof:placetype":"venue"
},
  "geometry": {"coordinates":[9.4288883209,52.2312889099],"type":"Point"}
}