{
  "type": "Feature",
  "properties": {
    "iso:country":"DE",
    "sg:address":"Krahnenstr 7-9",
    "sg:city":"K\u00f6ln",
    "sg:phone":"+49 221/67116767",
    "sg:postcode":"51063",
    "sg:province":"Nordrhein-Westfalen",
    "wof:name":"Reinsicht Gmbh",
    "wof:placetype":"venue"
},
  "geometry": {"coordinates":[7.000422,50.967182],"type":"Point"}
}