{
  "type": "Feature",
  "properties": {
    "iso:country":"DE",
    "sg:address":"Lessingstr. 20",
    "sg:city":"Zwickau",
    "sg:phone":"+49 375/281171",
    "sg:postcode":"08058",
    "sg:province":"Sachsen",
    "wof:name":"Franke Und Friedrich Architekten",
    "wof:placetype":"venue"
},
  "geometry": {"coordinates":[12.493311,50.726658],"type":"Point"}
}