{
  "type": "Feature",
  "properties": {
    "iso:country":"DE",
    "sg:address":"Miesgesweg 3 a",
    "sg:city":"Linz",
    "sg:phone":"+49 2644/3334",
    "sg:postcode":"53545",
    "sg:province":"Rheinland-Pfalz",
    "wof:name":"Ars Gmbh",
    "wof:placetype":"venue"
},
  "geometry": {"coordinates":[7.2958841324,50.5736160278],"type":"Point"}
}