{
  "type": "Feature",
  "properties": {
    "iso:country":"DE",
    "sg:address":"Kolpingstr. 10",
    "sg:city":"Wettringen",
    "sg:phone":"+49 2557/1289",
    "sg:postcode":"48493",
    "sg:province":"Nordrhein-Westfalen",
    "wof:name":"W. Hinterding",
    "wof:placetype":"venue"
},
  "geometry": {"coordinates":[7.3201909065,52.2092285156],"type":"Point"}
}