{
  "type": "Feature",
  "properties": {
    "iso:country":"DE",
    "sg:address":"Langhardtring 1",
    "sg:city":"Brackenheim",
    "sg:phone":"+49 7135/98540",
    "sg:postcode":"74336",
    "sg:province":"Baden-W\u00fcrttemberg",
    "wof:name":"Betz Und K\u00f6ppen",
    "wof:placetype":"venue"
},
  "geometry": {"coordinates":[9.0656270981,49.0816955566],"type":"Point"}
}