{
  "type": "Feature",
  "properties": {
    "iso:country":"DE",
    "sg:address":"R\u00f6dingsmarkt 39",
    "sg:city":"Hamburg",
    "sg:phone":"+49 40/3615710",
    "sg:postcode":"20459",
    "sg:province":"Hamburg",
    "wof:name":"Simplyst Ag",
    "wof:placetype":"venue"
},
  "geometry": {"coordinates":[9.9852809906,53.5459632874],"type":"Point"}
}