{
  "type": "Feature",
  "properties": {
    "iso:country":"DE",
    "sg:address":"Erzbergerstr. 22",
    "sg:city":"Wagh\u00e4usel",
    "sg:phone":"+49 7254/1367",
    "sg:postcode":"68753",
    "sg:province":"Baden-W\u00fcrttemberg",
    "wof:name":"Lothar Day",
    "wof:placetype":"venue"
},
  "geometry": {"coordinates":[8.5088577271,49.2244567871],"type":"Point"}
}