{
  "type": "Feature",
  "properties": {
    "iso:country":"DE",
    "sg:address":"Biebricher Allee 141",
    "sg:city":"Wiesbaden",
    "sg:phone":"+49 611/9812243",
    "sg:postcode":"65187",
    "sg:province":"Hessen",
    "wof:name":"Trend Personal- Und Dienst- Leistungen Wiesbaden Gmbh",
    "wof:placetype":"venue"
},
  "geometry": {"coordinates":[8.2432422638,50.0556488037],"type":"Point"}
}