{
  "type": "Feature",
  "properties": {
    "iso:country":"DE",
    "sg:address":"Preyersm\u00fchle 21",
    "sg:city":"Wermelskirchen",
    "sg:phone":"+49 2196/6345",
    "sg:postcode":"42929",
    "sg:province":"Nordrhein-Westfalen",
    "wof:name":"Preyersm\u00fchle",
    "wof:placetype":"venue"
},
  "geometry": {"coordinates":[7.2038002014,51.1549873352],"type":"Point"}
}