{
  "type": "Feature",
  "properties": {
    "iso:country":"DE",
    "sg:city":"Eichhorst",
    "sg:phone":"+49 3335/7211",
    "sg:postcode":"16244",
    "sg:province":"Brandenburg",
    "wof:name":"W. Bonk",
    "wof:placetype":"venue"
},
  "geometry": {"coordinates":[13.638664,52.890015],"type":"Point"}
}