{
  "type": "Feature",
  "properties": {
    "iso:country":"DE",
    "sg:address":"Dorfstr. 10",
    "sg:city":"Bodolz",
    "sg:phone":"+49 8382/25323",
    "sg:postcode":"88131",
    "sg:province":"Bayern",
    "wof:name":"Walter Schuster",
    "wof:placetype":"venue"
},
  "geometry": {"coordinates":[9.664669,47.56554],"type":"Point"}
}