{
  "type": "Feature",
  "properties": {
    "iso:country":"DE",
    "sg:address":"Neundorfer Str. 23",
    "sg:city":"Plauen",
    "sg:phone":"+49 3741/15230",
    "sg:postcode":"08523",
    "sg:province":"Sachsen",
    "wof:name":"City-hotel Inh. Frank Wand",
    "wof:placetype":"venue"
},
  "geometry": {"coordinates":[12.1279478073,50.4952468872],"type":"Point"}
}