{
  "type": "Feature",
  "properties": {
    "iso:country":"DE",
    "sg:address":"Nyland 11",
    "sg:city":"Tornesch",
    "sg:phone":"+49 4122/55545",
    "sg:postcode":"25436",
    "sg:province":"Schleswig-Holstein",
    "wof:name":"Ernst Kellhammer",
    "wof:placetype":"venue"
},
  "geometry": {"coordinates":[9.703874588,53.6888923645],"type":"Point"}
}