{
  "type": "Feature",
  "properties": {
    "iso:country":"DE",
    "sg:address":"Hattinger Str. 618",
    "sg:city":"Bochum",
    "sg:phone":"+49 234/471438",
    "sg:postcode":"44879",
    "sg:province":"Nordrhein-Westfalen",
    "wof:name":"Haus B\u00f6ving",
    "wof:placetype":"venue"
},
  "geometry": {"coordinates":[7.1803421974,51.436050415],"type":"Point"}
}