{
  "type": "Feature",
  "properties": {
    "iso:country":"DE",
    "sg:address":"Osterjork 101",
    "sg:city":"Jork",
    "sg:phone":"+49 4162/8133",
    "sg:postcode":"21635",
    "sg:province":"Niedersachsen",
    "wof:name":"R. Schuback",
    "wof:placetype":"venue"
},
  "geometry": {"coordinates":[9.6973371506,53.5291442871],"type":"Point"}
}