{
  "type": "Feature",
  "properties": {
    "iso:country":"DE",
    "sg:address":"Paradestr. 6",
    "sg:city":"Wuppertal",
    "sg:phone":"+49 202/445161",
    "sg:postcode":"42107",
    "sg:province":"Nordrhein-Westfalen",
    "wof:name":"Klotzsch & Co. Gmbh",
    "wof:placetype":"venue"
},
  "geometry": {"coordinates":[7.150157,51.263336],"type":"Point"}
}