{
  "type": "Feature",
  "properties": {
    "iso:country":"DE",
    "sg:address":"Rudolf-Diesel-Str. 7",
    "sg:city":"Freudenstadt",
    "sg:phone":"+49 7441/88770",
    "sg:postcode":"72250",
    "sg:province":"Baden-W\u00fcrttemberg",
    "wof:name":"G & M Merz Gmbh",
    "wof:placetype":"venue"
},
  "geometry": {"coordinates":[8.442023,48.463646],"type":"Point"}
}