{
  "type": "Feature",
  "properties": {
    "iso:country":"DE",
    "sg:address":"Seekamp 8",
    "sg:city":"Stein",
    "sg:postcode":"24235",
    "sg:province":"Schleswig-Holstein",
    "wof:name":"Kinderheim Ramm",
    "wof:placetype":"venue"
},
  "geometry": {"coordinates":[10.2716417313,54.4165840149],"type":"Point"}
}