{
  "type": "Feature",
  "properties": {
    "iso:country":"DE",
    "sg:address":"Gewerbegebiet 2",
    "sg:city":"P\u00f6lzig",
    "sg:phone":"+49 36695/21301",
    "sg:postcode":"07554",
    "sg:province":"Th\u00fcringen",
    "wof:name":"Stz Klingner Gmbh",
    "wof:placetype":"venue"
},
  "geometry": {"coordinates":[12.1845397949,50.9590415955],"type":"Point"}
}