{
  "type": "Feature",
  "properties": {
    "iso:country":"DE",
    "sg:address":"Eulenbergstr. 18",
    "sg:city":"Ellhofen",
    "sg:phone":"+49 7134/4849",
    "sg:postcode":"74248",
    "sg:province":"Baden-W\u00fcrttemberg",
    "wof:name":"Roland Schwarz Gmbh",
    "wof:placetype":"venue"
},
  "geometry": {"coordinates":[9.323177,49.145363],"type":"Point"}
}