{
  "type": "Feature",
  "properties": {
    "iso:country":"DE",
    "sg:address":"Hardenbergstr. 23b",
    "sg:city":"Hagen",
    "sg:phone":"+49 2331/84824",
    "sg:postcode":"58097",
    "sg:province":"Nordrhein-Westfalen",
    "wof:name":"Helga Mehringer",
    "wof:placetype":"venue"
},
  "geometry": {"coordinates":[7.486551,51.367188],"type":"Point"}
}