{
  "type": "Feature",
  "properties": {
    "iso:country":"DE",
    "sg:address":"Iltisstr. 164",
    "sg:city":"K\u00f6ln",
    "sg:postcode":"50825",
    "sg:province":"Nordrhein-Westfalen",
    "wof:name":"Neckermann Versand Ag",
    "wof:placetype":"venue"
},
  "geometry": {"coordinates":[6.9128022194,50.9648857117],"type":"Point"}
}