{
  "type": "Feature",
  "properties": {
    "iso:country":"DE",
    "sg:address":"R\u00f6merstr. 25",
    "sg:city":"Schleiden",
    "sg:phone":"+49 2444/2275",
    "sg:postcode":"53937",
    "sg:province":"Nordrhein-Westfalen",
    "wof:name":"Helmut Heiter",
    "wof:placetype":"venue"
},
  "geometry": {"coordinates":[6.46066,50.558399],"type":"Point"}
}