{
  "type": "Feature",
  "properties": {
    "iso:country":"DE",
    "sg:address":"Gl\u00fccksburger Str. 49",
    "sg:city":"Bremen",
    "sg:phone":"+49 421/14986",
    "sg:postcode":"28219",
    "sg:province":"Bremen",
    "wof:name":"Roland Leasing Gmbh",
    "wof:placetype":"venue"
},
  "geometry": {"coordinates":[8.7897024155,53.104019165],"type":"Point"}
}