{
  "type": "Feature",
  "properties": {
    "iso:country":"DE",
    "sg:address":"Hoferstr. 87",
    "sg:city":"Zwickau",
    "sg:phone":"+49 375/523505",
    "sg:postcode":"08060",
    "sg:province":"Sachsen",
    "wof:name":"Naturfreunde Marienthal",
    "wof:placetype":"venue"
},
  "geometry": {"coordinates":[12.4551124573,50.7172241211],"type":"Point"}
}