{
  "type": "Feature",
  "properties": {
    "iso:country":"DE",
    "sg:address":"Hegerdorfstr. 12",
    "sg:city":"Braunschweig",
    "sg:phone":"+49 5309/5532",
    "sg:postcode":"38108",
    "sg:province":"Niedersachsen",
    "wof:name":"Cheveux",
    "wof:placetype":"venue"
},
  "geometry": {"coordinates":[10.6060752869,52.3121414185],"type":"Point"}
}