{
  "type": "Feature",
  "properties": {
    "iso:country":"DE",
    "sg:address":"Falckensteinstr. 47",
    "sg:city":"Berlin",
    "sg:phone":"+49 30/6958053",
    "sg:postcode":"10997",
    "sg:province":"Berlin",
    "wof:name":"Rudolf W. Lipp Gmbh & Co.",
    "wof:placetype":"venue"
},
  "geometry": {"coordinates":[13.444707,52.50061],"type":"Point"}
}