{
  "type": "Feature",
  "properties": {
    "iso:country":"DE",
    "sg:address":"Alter Celler Weg 2",
    "sg:city":"Celle",
    "sg:phone":"+49 5141/95790",
    "sg:postcode":"29229",
    "sg:province":"Niedersachsen",
    "wof:name":"Wilfried Klatt Gmbh",
    "wof:placetype":"venue"
},
  "geometry": {"coordinates":[10.070594,52.645103],"type":"Point"}
}