{
  "type": "Feature",
  "properties": {
    "iso:country":"DE",
    "sg:address":"Erzbischof-J.-Godehard-Platz 1",
    "sg:city":"Springe",
    "sg:phone":"+49 5041/2289",
    "sg:postcode":"31832",
    "sg:province":"Niedersachsen",
    "wof:name":"Kath. Pfarramt Christ-k\u00f6nig",
    "wof:placetype":"venue"
},
  "geometry": {"coordinates":[9.5503730774,52.2094306946],"type":"Point"}
}