{
  "type": "Feature",
  "properties": {
    "iso:country":"DE",
    "sg:address":"Dieselstr. 10",
    "sg:city":"Glauchau",
    "sg:phone":"+49 3763/15142",
    "sg:postcode":"08371",
    "sg:province":"Sachsen",
    "wof:name":"Glauchauer Verkehrs- Technik Gmbh",
    "wof:placetype":"venue"
},
  "geometry": {"coordinates":[12.531855,50.840778],"type":"Point"}
}