{
  "type": "Feature",
  "properties": {
    "iso:country":"DE",
    "sg:address":"Wolkersdorfer Str. 28",
    "sg:city":"Burgwald",
    "sg:phone":"+49 6451/50000",
    "sg:postcode":"35099",
    "sg:province":"Hessen",
    "wof:name":"Schreck Kunststofftechnik Gmbh",
    "wof:placetype":"venue"
},
  "geometry": {"coordinates":[8.807331,51.02496],"type":"Point"}
}