{
  "type": "Feature",
  "properties": {
    "iso:country":"DE",
    "sg:address":"Rudolf-von-Langen-Str. 8",
    "sg:city":"M\u00fcnster",
    "sg:phone":"+49 251/293186",
    "sg:postcode":"48147",
    "sg:province":"Nordrhein-Westfalen",
    "wof:name":"Graf Von Westfalen Steuerberater",
    "wof:placetype":"venue"
},
  "geometry": {"coordinates":[7.6274428368,51.9683113098],"type":"Point"}
}