{
  "type": "Feature",
  "properties": {
    "iso:country":"DE",
    "sg:address":"Viktoriastr. 14 a",
    "sg:city":"Bad Kreuznach",
    "sg:phone":"+49 671/29777",
    "sg:postcode":"55543",
    "sg:province":"Rheinland-Pfalz",
    "wof:name":"S. Bilse",
    "wof:placetype":"venue"
},
  "geometry": {"coordinates":[7.8628029823,49.8450241089],"type":"Point"}
}