{
  "type": "Feature",
  "properties": {
    "iso:country":"DE",
    "sg:address":"Hauptstr. 79",
    "sg:city":"Hochdorf",
    "sg:phone":"+49 6231/929186",
    "sg:postcode":"67126",
    "sg:province":"Rheinland-Pfalz",
    "wof:name":"Az-design-bydidi",
    "wof:placetype":"venue"
},
  "geometry": {"coordinates":[8.2728176117,49.4168701172],"type":"Point"}
}