{
  "type": "Feature",
  "properties": {
    "iso:country":"DE",
    "sg:address":"Bachstelzenweg 3",
    "sg:city":"M\u00fcnchen",
    "sg:postcode":"80937",
    "sg:province":"Bayern",
    "wof:name":"Acit Gmbh",
    "wof:placetype":"venue"
},
  "geometry": {"coordinates":[11.5844049454,48.2043380737],"type":"Point"}
}