{
  "type": "Feature",
  "properties": {
    "iso:country":"DE",
    "sg:address":"Frankenthaler Str. 26",
    "sg:city":"Beindersheim",
    "sg:phone":"+49 6233/72959",
    "sg:postcode":"67259",
    "sg:province":"Rheinland-Pfalz",
    "wof:name":"Franz Butter",
    "wof:placetype":"venue"
},
  "geometry": {"coordinates":[8.310069,49.554005],"type":"Point"}
}