{
  "type": "Feature",
  "properties": {
    "iso:country":"DE",
    "sg:address":"Wei\u00dfer Garten 8",
    "sg:city":"Harzgerode",
    "sg:phone":"+49 39484/2587",
    "sg:postcode":"06493",
    "sg:province":"Sachsen-Anhalt",
    "wof:name":"Dagmar Matthes",
    "wof:placetype":"venue"
},
  "geometry": {"coordinates":[11.1401519775,51.6398582458],"type":"Point"}
}