{
  "type": "Feature",
  "properties": {
    "iso:country":"DE",
    "sg:address":"Westring 28-30",
    "sg:city":"Bochum",
    "sg:postcode":"44787",
    "sg:province":"Nordrhein-Westfalen",
    "wof:name":"Bakteriologisch Serologisches Institut",
    "wof:placetype":"venue"
},
  "geometry": {"coordinates":[7.2123260498,51.4826583862],"type":"Point"}
}