{
  "type": "Feature",
  "properties": {
    "iso:country":"DE",
    "sg:address":"Burgstr. 1",
    "sg:city":"Wittmund",
    "sg:phone":"+49 4462/5394",
    "sg:postcode":"26409",
    "sg:province":"Niedersachsen",
    "wof:name":"Hermann Feeken",
    "wof:placetype":"venue"
},
  "geometry": {"coordinates":[7.7829232216,53.5757369995],"type":"Point"}
}