{
  "type": "Feature",
  "properties": {
    "iso:country":"DE",
    "sg:address":"Rote-Land-Str. 34",
    "sg:city":"Diemelstadt",
    "sg:phone":"+49 5694/1031",
    "sg:postcode":"34474",
    "sg:province":"Hessen",
    "wof:name":"Friederich Kleinschmidt",
    "wof:placetype":"venue"
},
  "geometry": {"coordinates":[8.946808,51.452003],"type":"Point"}
}