{
  "type": "Feature",
  "properties": {
    "iso:country":"DE",
    "sg:address":"Diezer Str. 21",
    "sg:city":"Altendiez",
    "sg:phone":"+49 6432/81425",
    "sg:postcode":"65624",
    "sg:province":"Rheinland-Pfalz",
    "wof:name":"Karl Reh",
    "wof:placetype":"venue"
},
  "geometry": {"coordinates":[7.9856271744,50.3711128235],"type":"Point"}
}