{
  "type": "Feature",
  "properties": {
    "iso:country":"DE",
    "sg:address":"Schwarenbergstr. 84/A",
    "sg:city":"Stuttgart",
    "sg:phone":"+49 711/2622134",
    "sg:postcode":"70188",
    "sg:province":"Baden-W\u00fcrttemberg",
    "wof:name":"Gerd Jacob & Co.",
    "wof:placetype":"venue"
},
  "geometry": {"coordinates":[9.2020082474,48.7842407227],"type":"Point"}
}