{
  "type": "Feature",
  "properties": {
    "iso:country":"DE",
    "sg:address":"Elberfelder Str. 82",
    "sg:city":"Remscheid",
    "sg:phone":"+49 2191/23234",
    "sg:postcode":"42853",
    "sg:province":"Nordrhein-Westfalen",
    "wof:name":"F. Fuhrmann",
    "wof:placetype":"venue"
},
  "geometry": {"coordinates":[7.1874051094,51.1841163635],"type":"Point"}
}