{
  "type": "Feature",
  "properties": {
    "iso:country":"DE",
    "sg:address":"Kulturstr. 105",
    "sg:city":"Freising",
    "sg:phone":"+49 8161/9020",
    "sg:postcode":"85356",
    "sg:province":"Bayern",
    "wof:name":"Raytheon Deutschland Gmbh",
    "wof:placetype":"venue"
},
  "geometry": {"coordinates":[11.773501,48.398762],"type":"Point"}
}