{
  "type": "Feature",
  "properties": {
    "iso:country":"DE",
    "sg:address":"Nelkenweg 14",
    "sg:city":"Wolfratshausen",
    "sg:phone":"+49 8171/72956",
    "sg:postcode":"82515",
    "sg:province":"Bayern",
    "wof:name":"Megele Anlageberater",
    "wof:placetype":"venue"
},
  "geometry": {"coordinates":[11.4368677139,47.9149513245],"type":"Point"}
}