{
  "type": "Feature",
  "properties": {
    "iso:country":"DE",
    "sg:address":"Hauptstr. 38",
    "sg:city":"Monsheim",
    "sg:phone":"+49 6243/7215",
    "sg:postcode":"67590",
    "sg:province":"Rheinland-Pfalz",
    "wof:name":"Eckhard Seibel",
    "wof:placetype":"venue"
},
  "geometry": {"coordinates":[8.2080945969,49.6362876892],"type":"Point"}
}