{
  "type": "Feature",
  "properties": {
    "iso:country":"DE",
    "sg:address":"Bahnhofstr. 22",
    "sg:city":"Ludwigshafen",
    "sg:phone":"+49 621/528415",
    "sg:postcode":"67059",
    "sg:province":"Rheinland-Pfalz",
    "wof:name":"Na Und",
    "wof:placetype":"venue"
},
  "geometry": {"coordinates":[8.4443454742,49.4825592041],"type":"Point"}
}