{
  "type": "Feature",
  "properties": {
    "iso:country":"DE",
    "sg:address":"Zittenhofer Weg 26",
    "sg:city":"Grafenwiesen",
    "sg:phone":"+49 9941/8240",
    "sg:postcode":"93479",
    "sg:province":"Bayern",
    "wof:name":"Erich Illichmann",
    "wof:placetype":"venue"
},
  "geometry": {"coordinates":[12.8752002716,49.20154953],"type":"Point"}
}