{
  "type": "Feature",
  "properties": {
    "iso:country":"DE",
    "sg:address":"Wasserstr. 63",
    "sg:city":"Weeze",
    "sg:phone":"+49 2837/2005",
    "sg:postcode":"47652",
    "sg:province":"Nordrhein-Westfalen",
    "wof:name":"August Van Lier",
    "wof:placetype":"venue"
},
  "geometry": {"coordinates":[6.1977071762,51.6292915344],"type":"Point"}
}