{
  "type": "Feature",
  "properties": {
    "iso:country":"DE",
    "sg:address":"Frankfurter Chaussee 11",
    "sg:city":"Wriezen",
    "sg:phone":"+49 33456/34068",
    "sg:postcode":"16269",
    "sg:province":"Brandenburg",
    "wof:name":"Peter Anker",
    "wof:placetype":"venue"
},
  "geometry": {"coordinates":[14.134706,52.701694],"type":"Point"}
}