{
  "type": "Feature",
  "properties": {
    "iso:country":"DE",
    "sg:address":"Stammelner Str. 47",
    "sg:city":"Niederzier",
    "sg:phone":"+49 2428/6784",
    "sg:postcode":"52382",
    "sg:province":"Nordrhein-Westfalen",
    "wof:name":"Securitas-gilde Versicherungen",
    "wof:placetype":"venue"
},
  "geometry": {"coordinates":[6.4412198067,50.8534202576],"type":"Point"}
}