{
  "type": "Feature",
  "properties": {
    "iso:country":"DE",
    "sg:address":"Pfaffengasse 12-14",
    "sg:city":"Aschaffenburg",
    "sg:phone":"+49 6021/3560",
    "sg:postcode":"63739",
    "sg:province":"Bayern",
    "wof:name":"Hotel Dalberg",
    "wof:placetype":"venue"
},
  "geometry": {"coordinates":[9.1453552246,49.9744415283],"type":"Point"}
}