{
  "type": "Feature",
  "properties": {
    "iso:country":"DE",
    "sg:address":"Sechzig Str. 91",
    "sg:city":"Koeln",
    "sg:postcode":"50733",
    "sg:province":"Nordrhein-Westfalen",
    "wof:name":"Inter-market",
    "wof:placetype":"venue"
},
  "geometry": {"coordinates":[6.9448471069,50.9592323303],"type":"Point"}
}