{
  "type": "Feature",
  "properties": {
    "iso:country":"DE",
    "sg:address":"Schorndorfer Str. 16",
    "sg:city":"Winnenden",
    "sg:phone":"+49 7195/8431",
    "sg:postcode":"71364",
    "sg:province":"Baden-W\u00fcrttemberg",
    "wof:name":"A. Schlotterbeck \u00d6fen Und Herde",
    "wof:placetype":"venue"
},
  "geometry": {"coordinates":[9.4025230408,48.873916626],"type":"Point"}
}