{
  "type": "Feature",
  "properties": {
    "iso:country":"DE",
    "sg:address":"Kirchstr. 11",
    "sg:city":"Aspisheim",
    "sg:phone":"+49 6727/8553",
    "sg:postcode":"55459",
    "sg:province":"Rheinland-Pfalz",
    "wof:name":"Hagen Bollmann Gmbh",
    "wof:placetype":"venue"
},
  "geometry": {"coordinates":[7.983707,49.906918],"type":"Point"}
}