{
  "type": "Feature",
  "properties": {
    "iso:country":"DE",
    "sg:address":"Vor dem Celler Tor 46",
    "sg:city":"Burgdorf",
    "sg:phone":"+49 5136/800744",
    "sg:postcode":"31303",
    "sg:province":"Niedersachsen",
    "wof:name":"Mapac Wirtschafts- Beratungs Gmbh",
    "wof:placetype":"venue"
},
  "geometry": {"coordinates":[10.0124750137,52.4601364136],"type":"Point"}
}