{
  "type": "Feature",
  "properties": {
    "iso:country":"DE",
    "sg:address":"Volkmarser Str. 17",
    "sg:city":"Wolfhagen",
    "sg:phone":"+49 5606/3385",
    "sg:postcode":"34466",
    "sg:province":"Hessen",
    "wof:name":"Wilhelm Loose",
    "wof:placetype":"venue"
},
  "geometry": {"coordinates":[9.186745,51.38702],"type":"Point"}
}