{
  "type": "Feature",
  "properties": {
    "iso:country":"DE",
    "sg:address":"Heinestr. 5",
    "sg:city":"Templin",
    "sg:phone":"+49 3987/2789",
    "sg:postcode":"17268",
    "sg:province":"Brandenburg",
    "wof:name":"J. Schneider",
    "wof:placetype":"venue"
},
  "geometry": {"coordinates":[13.5046281815,53.120552063],"type":"Point"}
}