{
  "type": "Feature",
  "properties": {
    "iso:country":"DE",
    "sg:address":"Rosenthaler Weg 2",
    "sg:city":"Neetze",
    "sg:phone":"+49 5850/282",
    "sg:postcode":"21398",
    "sg:province":"Niedersachsen",
    "wof:name":"Ernst Klinge Immobilien Inh. Hans-j\u00fcrgen Riediger",
    "wof:placetype":"venue"
},
  "geometry": {"coordinates":[10.6246938705,53.2701377869],"type":"Point"}
}