{
  "type": "Feature",
  "properties": {
    "iso:country":"DE",
    "sg:address":"Hauptstr 28",
    "sg:city":"Sulzbach",
    "sg:phone":"+49 6196/74011",
    "sg:postcode":"65843",
    "sg:province":"Hessen",
    "wof:name":"Neon-lenz Gmbh",
    "wof:placetype":"venue"
},
  "geometry": {"coordinates":[7.7508997917,50.3020782471],"type":"Point"}
}