{
  "type": "Feature",
  "properties": {
    "iso:country":"DE",
    "sg:address":"Naheweinstr. 60",
    "sg:city":"Bretzenheim",
    "sg:phone":"+49 671/34887",
    "sg:postcode":"55559",
    "sg:province":"Rheinland-Pfalz",
    "wof:name":"Clemens Gl\u00f6ckner",
    "wof:placetype":"venue"
},
  "geometry": {"coordinates":[7.8973488808,49.8770904541],"type":"Point"}
}