{
  "type": "Feature",
  "properties": {
    "iso:country":"DE",
    "sg:address":"Gr\u00fcnauer Allee 24",
    "sg:city":"Leipzig",
    "sg:phone":"+49 341/4126076",
    "sg:postcode":"04209",
    "sg:province":"Sachsen",
    "wof:name":"Peter Ansorg",
    "wof:placetype":"venue"
},
  "geometry": {"coordinates":[12.3056201935,51.3188056946],"type":"Point"}
}