{
  "type": "Feature",
  "properties": {
    "iso:country":"DE",
    "sg:address":"Blumenberger Str. 143",
    "sg:city":"M\u00f6nchengladbach",
    "sg:postcode":"41061",
    "sg:province":"Nordrhein-Westfalen",
    "wof:name":"Btm Textilmaschinen Gmbh",
    "wof:placetype":"venue"
},
  "geometry": {"coordinates":[6.42193,51.187881],"type":"Point"}
}