{
  "type": "Feature",
  "properties": {
    "iso:country":"DE",
    "sg:address":"Heilbronner Str. 20",
    "sg:city":"Erlenbach",
    "sg:phone":"+49 7132/6586",
    "sg:postcode":"74235",
    "sg:province":"Baden-W\u00fcrttemberg",
    "wof:name":"Sulmtal",
    "wof:placetype":"venue"
},
  "geometry": {"coordinates":[9.2591285706,49.1713523865],"type":"Point"}
}