{
  "type": "Feature",
  "properties": {
    "iso:country":"DE",
    "sg:address":"Schulstr. 18",
    "sg:city":"N\u00fcmbrecht",
    "sg:phone":"+49 2293/7228",
    "sg:postcode":"51588",
    "sg:province":"Nordrhein-Westfalen",
    "wof:name":"Annegret Neuhof",
    "wof:placetype":"venue"
},
  "geometry": {"coordinates":[7.5388550758,50.9020271301],"type":"Point"}
}