{
  "type": "Feature",
  "properties": {
    "iso:country":"DE",
    "sg:address":"Nocherner Bach 17",
    "sg:city":"St. Goarshausen",
    "sg:phone":"+49 6771/94025",
    "sg:postcode":"56346",
    "sg:province":"Rheinland-Pfalz",
    "wof:name":"Sanddorn Produkte Der Gr\u00fcnen M\u00fchle",
    "wof:placetype":"venue"
},
  "geometry": {"coordinates":[7.7120299339,50.1567993164],"type":"Point"}
}