{
  "type": "Feature",
  "properties": {
    "iso:country":"DE",
    "sg:address":"Im Drosselhain 11",
    "sg:city":"Bergisch Gladbach",
    "sg:phone":"+49 2202/52917",
    "sg:postcode":"51467",
    "sg:province":"Nordrhein-Westfalen",
    "wof:name":"Klaus Jatho",
    "wof:placetype":"venue"
},
  "geometry": {"coordinates":[7.1124901772,51.0016860962],"type":"Point"}
}