{
  "type": "Feature",
  "properties": {
    "iso:country":"DE",
    "sg:address":"Schweinbach 23",
    "sg:city":"Pommersfelden",
    "sg:phone":"+49 9502/7382",
    "sg:postcode":"96178",
    "sg:province":"Bayern",
    "wof:name":"Baier",
    "wof:placetype":"venue"
},
  "geometry": {"coordinates":[10.8666439056,49.7671470642],"type":"Point"}
}