{
  "type": "Feature",
  "properties": {
    "iso:country":"DE",
    "sg:address":"Berliner Str 77",
    "sg:city":"Offenbach",
    "sg:phone":"+49 69/82000499",
    "sg:postcode":"63065",
    "sg:province":"Hessen",
    "wof:name":"Bfg Bank Ag",
    "wof:placetype":"venue"
},
  "geometry": {"coordinates":[8.762984,50.106152],"type":"Point"}
}