{
  "type": "Feature",
  "properties": {
    "iso:country":"DE",
    "sg:address":"Bismarckstr. 82",
    "sg:city":"Kaarst",
    "sg:phone":"+49 2131/602132",
    "sg:postcode":"41564",
    "sg:province":"Nordrhein-Westfalen",
    "wof:name":"P. D. Muschiol Gmbh",
    "wof:placetype":"venue"
},
  "geometry": {"coordinates":[6.6099672318,51.2160835266],"type":"Point"}
}