{
  "type": "Feature",
  "properties": {
    "iso:country":"DE",
    "sg:address":"Mainstr. 6",
    "sg:city":"Eltmann",
    "sg:phone":"+49 9522/70338",
    "sg:postcode":"97483",
    "sg:province":"Bayern",
    "wof:name":"Pflaum",
    "wof:placetype":"venue"
},
  "geometry": {"coordinates":[10.667157,49.972454],"type":"Point"}
}