{
  "type": "Feature",
  "properties": {
    "iso:country":"DE",
    "sg:address":"Muskauer Str. 51a",
    "sg:city":"Niesky",
    "sg:postcode":"02906",
    "sg:province":"Sachsen",
    "wof:name":"Gesellschaft Zur F\u00f6rderung Des Kfz-gewerbes Oberlausitz Mbh",
    "wof:placetype":"venue"
},
  "geometry": {"coordinates":[14.8263406754,51.3005065918],"type":"Point"}
}