{
  "type": "Feature",
  "properties": {
    "iso:country":"DE",
    "sg:address":"Isarauer Str. 77",
    "sg:city":"Aholming",
    "sg:phone":"+49 4936/4583480",
    "sg:postcode":"94527",
    "sg:province":"Bayern",
    "wof:name":"3e Gmbh Bad Berka",
    "wof:placetype":"venue"
},
  "geometry": {"coordinates":[11.278447,50.901913],"type":"Point"}
}