{
  "type": "Feature",
  "properties": {
    "iso:country":"DE",
    "sg:address":"Am Rapohl 20",
    "sg:city":"K\u00f6ln",
    "sg:phone":"+49 2234/77422",
    "sg:postcode":"50859",
    "sg:province":"Nordrhein-Westfalen",
    "wof:name":"Joseph Schmidt",
    "wof:placetype":"venue"
},
  "geometry": {"coordinates":[6.8226947784,50.936542511],"type":"Point"}
}