{
  "type": "Feature",
  "properties": {
    "iso:country":"DE",
    "sg:address":"August-Bebel-Str. 21",
    "sg:city":"Meerane",
    "sg:phone":"+49 3764/3289",
    "sg:postcode":"08393",
    "sg:province":"Sachsen",
    "wof:name":"Dr. Med. Gerd Simon",
    "wof:placetype":"venue"
},
  "geometry": {"coordinates":[12.464462,50.850918],"type":"Point"}
}