{
  "type": "Feature",
  "properties": {
    "iso:country":"DE",
    "sg:address":"Goetheweg 27",
    "sg:city":"Bleicherode",
    "sg:phone":"+49 36338/62476",
    "sg:postcode":"99752",
    "sg:province":"Th\u00fcringen",
    "wof:name":"Dr. Med. Reiner Wagner",
    "wof:placetype":"venue"
},
  "geometry": {"coordinates":[10.557979,51.444115],"type":"Point"}
}