{
  "type": "Feature",
  "properties": {
    "iso:country":"DE",
    "sg:address":"Birkenstr. 21",
    "sg:city":"Boppard",
    "sg:phone":"+49 6742/1261",
    "sg:postcode":"56154",
    "sg:province":"Rheinland-Pfalz",
    "wof:name":"F. Und P. Nick",
    "wof:placetype":"venue"
},
  "geometry": {"coordinates":[7.5307979584,50.2198562622],"type":"Point"}
}