{
  "type": "Feature",
  "properties": {
    "iso:country":"DE",
    "sg:address":"Froschlache 3",
    "sg:city":"Eschach",
    "sg:phone":"+49 7175/5869",
    "sg:postcode":"73569",
    "sg:province":"Baden-W\u00fcrttemberg",
    "wof:name":"Klaus Wiedmann",
    "wof:placetype":"venue"
},
  "geometry": {"coordinates":[9.872109,48.886162],"type":"Point"}
}