{
  "type": "Feature",
  "properties": {
    "iso:country":"DE",
    "sg:address":"Lindengrabenstr. 1",
    "sg:city":"Gevelsberg",
    "sg:phone":"+49 2332/13050",
    "sg:postcode":"58285",
    "sg:province":"Nordrhein-Westfalen",
    "wof:name":"Altfeld-bau Gmbh & Co. Kg Bautr\u00e4gergesellschaft",
    "wof:placetype":"venue"
},
  "geometry": {"coordinates":[7.3292708397,51.3150787354],"type":"Point"}
}