{
  "type": "Feature",
  "properties": {
    "iso:country":"DE",
    "sg:address":"Heidsieker Heide 107",
    "sg:city":"Bielefeld",
    "sg:phone":"+49 5206/8074",
    "sg:postcode":"33739",
    "sg:province":"Nordrhein-Westfalen",
    "wof:name":"Colltec Farbaufbereitungs Verwaltungs Und",
    "wof:placetype":"venue"
},
  "geometry": {"coordinates":[8.514035,52.097454],"type":"Point"}
}