{
  "type": "Feature",
  "properties": {
    "iso:country":"DE",
    "sg:address":"Eichental 25",
    "sg:city":"Krefeld",
    "sg:phone":"+49 180 5 554887",
    "sg:postcode":"47798",
    "sg:province":"Nordrhein-Westfalen",
    "wof:name":"Teenysline Die Geilsten Girls Im Web",
    "wof:placetype":"venue"
},
  "geometry": {"coordinates":[6.562957,51.340729],"type":"Point"}
}