{
  "type": "Feature",
  "properties": {
    "iso:country":"DE",
    "sg:address":"Gartenstr. 2",
    "sg:city":"Gengenbach",
    "sg:phone":"+49 7803/980540",
    "sg:postcode":"77723",
    "sg:province":"Baden-W\u00fcrttemberg",
    "wof:name":"Kirchliche Sozialstation St. Martin Gengenbach-",
    "wof:placetype":"venue"
},
  "geometry": {"coordinates":[8.013442,48.404984],"type":"Point"}
}