{
  "type": "Feature",
  "properties": {
    "iso:country":"DE",
    "sg:address":"Kanalstr. 9",
    "sg:city":"Heilbronn",
    "sg:phone":"+49 7131/44333",
    "sg:postcode":"74080",
    "sg:province":"Baden-W\u00fcrttemberg",
    "wof:name":"Tebo Teppichboden",
    "wof:placetype":"venue"
},
  "geometry": {"coordinates":[9.1985139847,49.1425514221],"type":"Point"}
}