{
  "type": "Feature",
  "properties": {
    "iso:country":"DE",
    "sg:address":"Bergstr. 116",
    "sg:city":"Lauterbach",
    "sg:phone":"+49 36924/42410",
    "sg:postcode":"99826",
    "sg:province":"Th\u00fcringen",
    "wof:name":"Robert Mader",
    "wof:placetype":"venue"
},
  "geometry": {"coordinates":[10.352654,51.069424],"type":"Point"}
}