{
  "type": "Feature",
  "properties": {
    "iso:country":"DE",
    "sg:address":"Ferdinand-von-Schill-Str. 2",
    "sg:city":"Geltow",
    "sg:postcode":"14542",
    "sg:province":"Brandenburg",
    "wof:name":"Vifa Unterst\u00fctzungskasse Gmbh",
    "wof:placetype":"venue"
},
  "geometry": {"coordinates":[12.9744033813,52.3603668213],"type":"Point"}
}