{
  "type": "Feature",
  "properties": {
    "iso:country":"DE",
    "sg:address":"Frankenstr. 11",
    "sg:city":"Oerlenbach",
    "sg:phone":"+49 9738/647",
    "sg:postcode":"97714",
    "sg:province":"Bayern",
    "wof:name":"Richard Bla\u00dfd\u00f6rfer Masseur",
    "wof:placetype":"venue"
},
  "geometry": {"coordinates":[10.120899,50.155964],"type":"Point"}
}