{
  "type": "Feature",
  "properties": {
    "iso:country":"DE",
    "sg:address":"Max-Planck-Str.",
    "sg:city":"Potsdam",
    "sg:phone":"+49 331/244691",
    "sg:postcode":"14473",
    "sg:province":"Brandenburg",
    "wof:name":"Schwimmhalle",
    "wof:placetype":"venue"
},
  "geometry": {"coordinates":[13.0633602142,52.3893814087],"type":"Point"}
}