{
  "type": "Feature",
  "properties": {
    "iso:country":"DE",
    "sg:address":"Geiststr. 9",
    "sg:city":"Halle",
    "sg:phone":"+49 345/2035475",
    "sg:postcode":"06108",
    "sg:province":"Sachsen-Anhalt",
    "wof:name":"Margot Funk Steuerberaterin",
    "wof:placetype":"venue"
},
  "geometry": {"coordinates":[11.9657382965,51.4885864258],"type":"Point"}
}