{
  "type": "Feature",
  "properties": {
    "iso:country":"DE",
    "sg:address":"Hauptstr. 167",
    "sg:city":"Sundern",
    "sg:postcode":"59846",
    "sg:province":"Nordrhein-Westfalen",
    "wof:name":"Handel Mit Schmiedeartikeln Kunstschmiede M. H\u00fcttemeister",
    "wof:placetype":"venue"
},
  "geometry": {"coordinates":[8.001882,51.332024],"type":"Point"}
}