{
  "type": "Feature",
  "properties": {
    "iso:country":"DE",
    "sg:address":"Steinfurter Str. 45",
    "sg:city":"M\u00fcnster",
    "sg:phone":"+49 251/279514",
    "sg:postcode":"48149",
    "sg:province":"Nordrhein-Westfalen",
    "wof:name":"G\u00fcnter B\u00f6hme Architekt",
    "wof:placetype":"venue"
},
  "geometry": {"coordinates":[7.610416,51.970413],"type":"Point"}
}