{
  "type": "Feature",
  "properties": {
    "iso:country":"DE",
    "sg:address":"Reithmayrstr.44",
    "sg:city":"Regensburg",
    "sg:phone":"+49 941/2803957",
    "sg:postcode":"93051",
    "sg:province":"Bayern",
    "wof:name":"Perecon Personal Recreation Consulting",
    "wof:placetype":"venue"
},
  "geometry": {"coordinates":[12.077057,49.009846],"type":"Point"}
}