{
  "type": "Feature",
  "properties": {
    "iso:country":"DE",
    "sg:address":"Stotzheimer Str. 106",
    "sg:city":"Euskirchen",
    "sg:phone":"+49 2251/61123",
    "sg:postcode":"53881",
    "sg:province":"Nordrhein-Westfalen",
    "wof:name":"Willi Und Maria B\u00fcrger Hotel- Und Gastst\u00e4ttenbetriebe Gmbh",
    "wof:placetype":"venue"
},
  "geometry": {"coordinates":[6.8111481667,50.6299667358],"type":"Point"}
}