{
  "type": "Feature",
  "properties": {
    "iso:country":"DE",
    "sg:address":"Crailsheimstr. 1",
    "sg:city":"R\u00f6delsee",
    "sg:phone":"+49 9323/3006",
    "sg:postcode":"97348",
    "sg:province":"Bayern",
    "wof:name":"Rudolf Wandler",
    "wof:placetype":"venue"
},
  "geometry": {"coordinates":[10.241848,49.729164],"type":"Point"}
}