{
  "type": "Feature",
  "properties": {
    "iso:country":"DE",
    "sg:address":"Grubenstr. 6",
    "sg:city":"Heiligenhaus",
    "sg:phone":"+49 2056/9140",
    "sg:postcode":"42579",
    "sg:province":"Nordrhein-Westfalen",
    "wof:name":"Goldschmidt Beteiligungs-gmbh",
    "wof:placetype":"venue"
},
  "geometry": {"coordinates":[6.951019,51.329605],"type":"Point"}
}