{
  "type": "Feature",
  "properties": {
    "iso:country":"DE",
    "sg:address":"Mendelstr. 9",
    "sg:city":"Neuss",
    "sg:phone":"+49 2131/82512",
    "sg:postcode":"41464",
    "sg:province":"Nordrhein-Westfalen",
    "wof:name":"Dr. Horst Mittelstaedt Rechtsanwalt",
    "wof:placetype":"venue"
},
  "geometry": {"coordinates":[6.6704292297,51.1877632141],"type":"Point"}
}