{
  "type": "Feature",
  "properties": {
    "iso:country":"DE",
    "sg:address":"Mainzer Str. 3",
    "sg:city":"Ludwigsh\u00f6he",
    "sg:phone":"+49 6249/8430",
    "sg:postcode":"55278",
    "sg:province":"Rheinland-Pfalz",
    "wof:name":"Dr. Becker",
    "wof:placetype":"venue"
},
  "geometry": {"coordinates":[8.3431777954,49.818069458],"type":"Point"}
}