{
  "type": "Feature",
  "properties": {
    "iso:country":"DE",
    "sg:address":"Unterspeltacher Str. 15",
    "sg:city":"Crailsheim",
    "sg:phone":"+49 7951/6761",
    "sg:postcode":"74564",
    "sg:province":"Baden-W\u00fcrttemberg",
    "wof:name":"Karl Bro\u00df",
    "wof:placetype":"venue"
},
  "geometry": {"coordinates":[10.0607204437,49.0926704407],"type":"Point"}
}