{
  "type": "Feature",
  "properties": {
    "iso:country":"DE",
    "sg:address":"Herrnbergstr. 17",
    "sg:city":"Wiesbaden",
    "sg:phone":"+49 611/942890",
    "sg:postcode":"65201",
    "sg:province":"Hessen",
    "wof:name":"Hotel Und Weinhaus Sinz",
    "wof:placetype":"venue"
},
  "geometry": {"coordinates":[8.1556816101,50.0621643066],"type":"Point"}
}