{
  "type": "Feature",
  "properties": {
    "iso:country":"DE",
    "sg:address":"Blumenstr. 1",
    "sg:city":"Heroldstatt",
    "sg:phone":"+49 7389/462",
    "sg:postcode":"72535",
    "sg:province":"Baden-W\u00fcrttemberg",
    "wof:name":"Wilhelm Hirschle",
    "wof:placetype":"venue"
},
  "geometry": {"coordinates":[9.673911,48.445282],"type":"Point"}
}