{
  "type": "Feature",
  "properties": {
    "iso:country":"DE",
    "sg:address":"Eichenhorst 8",
    "sg:city":"Pinneberg",
    "sg:phone":"+49 4101/62433",
    "sg:postcode":"25421",
    "sg:province":"Schleswig-Holstein",
    "wof:name":"Joachim Matthaei",
    "wof:placetype":"venue"
},
  "geometry": {"coordinates":[9.7973165512,53.6511764526],"type":"Point"}
}