{
  "type": "Feature",
  "properties": {
    "iso:country":"DE",
    "sg:address":"Wiesenweg 14",
    "sg:city":"Stammbach",
    "sg:phone":"+49 9256/258",
    "sg:postcode":"95236",
    "sg:province":"Bayern",
    "wof:name":"Leichauer Gmbh",
    "wof:placetype":"venue"
},
  "geometry": {"coordinates":[11.693692,50.141808],"type":"Point"}
}