{
  "type": "Feature",
  "properties": {
    "iso:country":"DE",
    "sg:address":"M\u00fcnchener Str. 153",
    "sg:city":"Ingolstadt",
    "sg:phone":"+49 841/77987",
    "sg:postcode":"85051",
    "sg:province":"Bayern",
    "wof:name":"Faltermeier & Langhammer Gmbh",
    "wof:placetype":"venue"
},
  "geometry": {"coordinates":[11.4374198914,48.737537384],"type":"Point"}
}