{
  "type": "Feature",
  "properties": {
    "iso:country":"DE",
    "sg:address":"Kurze Gasse 4",
    "sg:city":"Hindelang",
    "sg:phone":"+49 8324/2281",
    "sg:postcode":"87541",
    "sg:province":"Bayern",
    "wof:name":"G\u00e4stehaus R. Ried",
    "wof:placetype":"venue"
},
  "geometry": {"coordinates":[10.3862953186,47.5028457642],"type":"Point"}
}