{
  "type": "Feature",
  "properties": {
    "iso:country":"DE",
    "sg:address":"Kufsteiner Str. 109",
    "sg:city":"Rosenheim",
    "sg:postcode":"83022",
    "sg:province":"Bayern",
    "wof:name":"Golden Rainbow Vierte Verm\u00f6gensverwaltungs Ag",
    "wof:placetype":"venue"
},
  "geometry": {"coordinates":[12.1263904572,47.8477706909],"type":"Point"}
}