{
  "type": "Feature",
  "properties": {
    "iso:country":"DE",
    "sg:address":"Staigle 8",
    "sg:city":"K\u00f6nigsheim",
    "sg:phone":"+49 7429/99219",
    "sg:postcode":"78598",
    "sg:province":"Baden-W\u00fcrttemberg",
    "wof:name":"Radzuweit Beteiligungs- Und Verwaltungs Gmbh",
    "wof:placetype":"venue"
},
  "geometry": {"coordinates":[8.8633575439,48.1026573181],"type":"Point"}
}