{
  "type": "Feature",
  "properties": {
    "iso:country":"DE",
    "sg:address":"Kantorie 65 b",
    "sg:city":"Essen",
    "sg:postcode":"45134",
    "sg:province":"Nordrhein-Westfalen",
    "wof:name":"Gfb West Gesellschaft F\u00fcr Beteiligungen Mbh",
    "wof:placetype":"venue"
},
  "geometry": {"coordinates":[7.049632,51.419315],"type":"Point"}
}