{
  "type": "Feature",
  "properties": {
    "iso:country":"DE",
    "sg:address":"Hauptstr. 13",
    "sg:city":"Winterrieden",
    "sg:phone":"+49 8333/4262",
    "sg:postcode":"87785",
    "sg:province":"Bayern",
    "wof:name":"M. Haisch",
    "wof:placetype":"venue"
},
  "geometry": {"coordinates":[10.2261552811,48.1206054688],"type":"Point"}
}