{
  "type": "Feature",
  "properties": {
    "iso:country":"DE",
    "sg:address":"Erbacher Str. 14",
    "sg:city":"Taunusstein",
    "sg:phone":"+49 6128/44394",
    "sg:postcode":"65232",
    "sg:province":"Hessen",
    "wof:name":"Friedrich-b\u00fcromaschinen Inh. Volker-michael Menz",
    "wof:placetype":"venue"
},
  "geometry": {"coordinates":[8.1156949997,50.126663208],"type":"Point"}
}