{
  "type": "Feature",
  "properties": {
    "iso:country":"DE",
    "sg:address":"Kranenpohlstr. 12",
    "sg:city":"F\u00fcrstenau",
    "sg:phone":"+49 5901/3494",
    "sg:postcode":"49584",
    "sg:province":"Niedersachsen",
    "wof:name":"Stehpizza Bei Alfredo",
    "wof:placetype":"venue"
},
  "geometry": {"coordinates":[7.6682767868,52.5291442871],"type":"Point"}
}