{
  "type": "Feature",
  "properties": {
    "iso:country":"DE",
    "sg:address":"Pestalozzistr. 16",
    "sg:city":"Sankt Peter-Ording",
    "sg:phone":"+49 4863/5555",
    "sg:postcode":"25826",
    "sg:province":"Schleswig-Holstein",
    "wof:name":"Praxis Dr. Med. Gattermann",
    "wof:placetype":"venue"
},
  "geometry": {"coordinates":[8.6417770386,54.300239563],"type":"Point"}
}