{
  "type": "Feature",
  "properties": {
    "iso:country":"DE",
    "sg:address":"Anger 16",
    "sg:city":"Je\u00dfnitz",
    "sg:phone":"+49 3494/77511",
    "sg:postcode":"06800",
    "sg:province":"Sachsen-Anhalt",
    "wof:name":"Kurt Kunze",
    "wof:placetype":"venue"
},
  "geometry": {"coordinates":[12.303243,51.681171],"type":"Point"}
}