{
  "type": "Feature",
  "properties": {
    "iso:country":"DE",
    "sg:address":"Junkerstr. 2",
    "sg:city":"Tuttlingen",
    "sg:phone":"+49 7461/3680",
    "sg:postcode":"78532",
    "sg:province":"Baden-W\u00fcrttemberg",
    "wof:name":"A. Keller",
    "wof:placetype":"venue"
},
  "geometry": {"coordinates":[8.789981,47.97123],"type":"Point"}
}