{
  "type": "Feature",
  "properties": {
    "iso:country":"DE",
    "sg:address":"Sredzkistra\u00dfe 19A",
    "sg:city":"Berlin",
    "sg:phone":"+49 172 3020197",
    "sg:postcode":"10435",
    "sg:province":"Berlin",
    "wof:name":"Blabla Berlin",
    "wof:placetype":"venue"
},
  "geometry": {"coordinates":[13.4153766632,52.5385704041],"type":"Point"}
}