{
  "type": "Feature",
  "properties": {
    "iso:country":"DE",
    "sg:address":"B\u00f6rdeler Berg 4",
    "sg:city":"Dransfeld",
    "sg:phone":"+49 5502/91530",
    "sg:postcode":"37127",
    "sg:province":"Niedersachsen",
    "wof:name":"Van Waveren Saaten Gmbh",
    "wof:placetype":"venue"
},
  "geometry": {"coordinates":[9.768226,51.498661],"type":"Point"}
}