{
  "type": "Feature",
  "properties": {
    "iso:country":"DE",
    "sg:address":"Platanenallee 79",
    "sg:city":"Unna",
    "sg:phone":"+49 2303/690740",
    "sg:postcode":"59425",
    "sg:province":"Nordrhein-Westfalen",
    "wof:name":"Reto System Redoma E. K.",
    "wof:placetype":"venue"
},
  "geometry": {"coordinates":[7.689283,51.549007],"type":"Point"}
}