{
  "type": "Feature",
  "properties": {
    "iso:country":"DE",
    "sg:address":"Liegnitzer Str. 11",
    "sg:city":"Bad Kreuznach",
    "sg:phone":"+49 671/72934",
    "sg:postcode":"55543",
    "sg:province":"Rheinland-Pfalz",
    "wof:name":"Gustav Kannwischer Architekt",
    "wof:placetype":"venue"
},
  "geometry": {"coordinates":[7.870248,49.829472],"type":"Point"}
}