{
  "type": "Feature",
  "properties": {
    "iso:country":"DE",
    "sg:address":"Dreiangel 12",
    "sg:city":"Altenholz",
    "sg:phone":"+49 431/322104",
    "sg:postcode":"24161",
    "sg:province":"Schleswig-Holstein",
    "wof:name":"Hans J\u00fcrgensen Ingenieur",
    "wof:placetype":"venue"
},
  "geometry": {"coordinates":[10.1191987991,54.3939743042],"type":"Point"}
}