{
  "type": "Feature",
  "properties": {
    "iso:country":"DE",
    "sg:address":"Kreuznaaf 11",
    "sg:city":"Lohmar",
    "sg:phone":"+49 2246/92210",
    "sg:postcode":"53797",
    "sg:province":"Nordrhein-Westfalen",
    "wof:name":"Eks Erd-kanal-stra\u00dfenbau Gmbh",
    "wof:placetype":"venue"
},
  "geometry": {"coordinates":[7.2497320175,50.8636398315],"type":"Point"}
}