{
  "type": "Feature",
  "properties": {
    "iso:country":"DE",
    "sg:address":"Postfach 101307:: 30834 Langenhagen:: Germany.^^Sch\u00fctzenstr 2::",
    "sg:city":"Langenhagen",
    "sg:postcode":"30853",
    "sg:province":"Niedersachsen",
    "wof:name":"Ahc-holding Gmbh",
    "wof:placetype":"venue"
},
  "geometry": {"coordinates":[6.692358,50.873226],"type":"Point"}
}