{
  "type": "Feature",
  "properties": {
    "iso:country":"DE",
    "sg:address":"Lange Str. 4",
    "sg:city":"Walsrode",
    "sg:phone":"+49 5161/98110",
    "sg:postcode":"29664",
    "sg:province":"Niedersachsen",
    "wof:name":"Hotel-restaurant Kopp Inh. A. Kopp E. K.",
    "wof:placetype":"venue"
},
  "geometry": {"coordinates":[9.5948200226,52.8604736328],"type":"Point"}
}