{
  "type": "Feature",
  "properties": {
    "iso:country":"DE",
    "sg:address":"Wurtscheid 17",
    "sg:city":"Lindlar",
    "sg:phone":"+49 2266/7590",
    "sg:postcode":"51789",
    "sg:province":"Nordrhein-Westfalen",
    "wof:name":"Willi Prediger",
    "wof:placetype":"venue"
},
  "geometry": {"coordinates":[7.320505,50.997803],"type":"Point"}
}