{
  "type": "Feature",
  "properties": {
    "iso:country":"DE",
    "sg:address":"In Bisholder 5",
    "sg:city":"Koblenz",
    "sg:phone":"+49 261/48770",
    "sg:postcode":"56072",
    "sg:province":"Rheinland-Pfalz",
    "wof:name":"Gertrud Schneider",
    "wof:placetype":"venue"
},
  "geometry": {"coordinates":[7.5330681801,50.3346633911],"type":"Point"}
}