{
  "type": "Feature",
  "properties": {
    "iso:country":"DE",
    "sg:address":"Treherzer Str. 16",
    "sg:city":"Bad Wurzach",
    "sg:phone":"+49 7568/243",
    "sg:postcode":"88410",
    "sg:province":"Baden-W\u00fcrttemberg",
    "wof:name":"Xaver Nothelfer",
    "wof:placetype":"venue"
},
  "geometry": {"coordinates":[9.987455,47.947811],"type":"Point"}
}