{
  "type": "Feature",
  "properties": {
    "iso:country":"DE",
    "sg:address":"Blaichacher Str. 6",
    "sg:city":"M\u00fcnchen",
    "sg:phone":"+49 89/757568",
    "sg:postcode":"81476",
    "sg:province":"Bayern",
    "wof:name":"Gert Blass",
    "wof:placetype":"venue"
},
  "geometry": {"coordinates":[11.4928245544,48.0814628601],"type":"Point"}
}