{
  "type": "Feature",
  "properties": {
    "iso:country":"DE",
    "sg:address":"Neuer Weg 42",
    "sg:city":"Neuwied",
    "sg:postcode":"56567",
    "sg:province":"Rheinland-Pfalz",
    "wof:name":"Wilhelm Projahn Kg",
    "wof:placetype":"venue"
},
  "geometry": {"coordinates":[7.4735088348,50.4606323242],"type":"Point"}
}