{
  "type": "Feature",
  "properties": {
    "iso:country":"DE",
    "sg:address":"Eduardstr 1b",
    "sg:city":"Werdohl",
    "sg:phone":"+49 2392/13828",
    "sg:postcode":"58791",
    "sg:province":"Nordrhein-Westfalen",
    "wof:name":"S & O Maschinenbau Gmbh",
    "wof:placetype":"venue"
},
  "geometry": {"coordinates":[7.7448549271,51.2545280457],"type":"Point"}
}