{
  "type": "Feature",
  "properties": {
    "iso:country":"DE",
    "sg:address":"Karl-Marx-Str. 2",
    "sg:city":"Trusetal",
    "sg:phone":"+49 36840/81246",
    "sg:postcode":"98596",
    "sg:province":"Th\u00fcringen",
    "wof:name":"Felsenkeller",
    "wof:placetype":"venue"
},
  "geometry": {"coordinates":[10.4038448334,50.7809181213],"type":"Point"}
}