{
  "type": "Feature",
  "properties": {
    "iso:country":"DE",
    "sg:address":"Besenbinderhof 58",
    "sg:city":"Hamburg",
    "sg:phone":"+49 40/34952366",
    "sg:postcode":"20355",
    "sg:province":"Hamburg",
    "wof:name":"Bfg Bank Ag",
    "wof:placetype":"venue"
},
  "geometry": {"coordinates":[10.012613,53.550896],"type":"Point"}
}