{
  "type": "Feature",
  "properties": {
    "iso:country":"DE",
    "sg:address":"Friedhofstr. 55 a",
    "sg:city":"Stuttgart",
    "sg:phone":"+49 711/2579203",
    "sg:postcode":"70191",
    "sg:province":"Baden-W\u00fcrttemberg",
    "wof:name":"Schaller",
    "wof:placetype":"venue"
},
  "geometry": {"coordinates":[9.182848,48.793907],"type":"Point"}
}