{
  "type": "Feature",
  "properties": {
    "iso:country":"DE",
    "sg:address":"Bahnhofstr. 128",
    "sg:city":"Bad Berneck",
    "sg:phone":"+49 9273/96060",
    "sg:postcode":"95460",
    "sg:province":"Bayern",
    "wof:name":"Versicherungskammer Bayern Erich Popp",
    "wof:placetype":"venue"
},
  "geometry": {"coordinates":[11.6685676575,50.0444450378],"type":"Point"}
}