{
  "type": "Feature",
  "properties": {
    "iso:country":"DE",
    "sg:address":"Breiter Weg 71",
    "sg:city":"G\u00fcsen",
    "sg:phone":"+49 39344/255",
    "sg:postcode":"39317",
    "sg:province":"Sachsen-Anhalt",
    "wof:name":"Horst Schulz",
    "wof:placetype":"venue"
},
  "geometry": {"coordinates":[11.975835,52.341568],"type":"Point"}
}