{
  "type": "Feature",
  "properties": {
    "iso:country":"DE",
    "sg:address":"Kedenburgstr. 53-59",
    "sg:city":"Hamburg",
    "sg:phone":"+49 40/2201341",
    "sg:postcode":"22041",
    "sg:province":"Hamburg",
    "wof:name":"Gbm Malerwerkst\u00e4tten Gmbh",
    "wof:placetype":"venue"
},
  "geometry": {"coordinates":[10.088021,53.575211],"type":"Point"}
}