{
  "type": "Feature",
  "properties": {
    "iso:country":"DE",
    "sg:address":"Emmelner Str. 53",
    "sg:city":"Haren",
    "sg:phone":"+49 5932/2513",
    "sg:postcode":"49733",
    "sg:province":"Niedersachsen",
    "wof:name":"Ms Armin Schiffahrts- Verwaltungs Gmbh",
    "wof:placetype":"venue"
},
  "geometry": {"coordinates":[7.256571,52.790718],"type":"Point"}
}