{
  "type": "Feature",
  "properties": {
    "iso:country":"DE",
    "sg:address":"Beethovenstr. 7",
    "sg:city":"Hainburg",
    "sg:phone":"+49 6182/68031",
    "sg:postcode":"63512",
    "sg:province":"Hessen",
    "wof:name":"Stefan Mieth Steuerberater",
    "wof:placetype":"venue"
},
  "geometry": {"coordinates":[8.9364309311,50.077129364],"type":"Point"}
}