{
  "type": "Feature",
  "properties": {
    "iso:country":"DE",
    "sg:address":"Sudetenstr. 30",
    "sg:city":"Glauburg",
    "sg:phone":"+49 6041/6616",
    "sg:postcode":"63695",
    "sg:province":"Hessen",
    "wof:name":"Walter G\u00f6rtling",
    "wof:placetype":"venue"
},
  "geometry": {"coordinates":[9.015092,50.326546],"type":"Point"}
}