{
  "type": "Feature",
  "properties": {
    "iso:country":"DE",
    "sg:address":"Gewerbepark Keplerstr. 1",
    "sg:city":"Gera",
    "sg:postcode":"07549",
    "sg:province":"Th\u00fcringen",
    "wof:name":"Siegfried Theilig Inh. Andre Thelig",
    "wof:placetype":"venue"
},
  "geometry": {"coordinates":[12.06383,50.852928],"type":"Point"}
}