{
  "type": "Feature",
  "properties": {
    "iso:country":"DE",
    "sg:address":"Am Sch\u00e4ferhof 15",
    "sg:city":"Hann. M\u00fcnden",
    "sg:phone":"+49 5541/35011",
    "sg:postcode":"34346",
    "sg:province":"Niedersachsen",
    "wof:name":"Hanssen-blockhaus Gmbh",
    "wof:placetype":"venue"
},
  "geometry": {"coordinates":[9.6754255295,51.4025192261],"type":"Point"}
}