{
  "type": "Feature",
  "properties": {
    "iso:country":"DE",
    "sg:address":"B\u00fccklersstr. 9",
    "sg:city":"D\u00fcren",
    "sg:phone":"+49 2421/14074",
    "sg:postcode":"52351",
    "sg:province":"Nordrhein-Westfalen",
    "wof:name":"Ewald Klein Ingenieur",
    "wof:placetype":"venue"
},
  "geometry": {"coordinates":[6.4840798378,50.8077392578],"type":"Point"}
}