{
  "type": "Feature",
  "properties": {
    "iso:country":"DE",
    "sg:address":"Ah\u00e4user Weg 12-22",
    "sg:city":"Weilburg",
    "sg:phone":"+49 6471/3150",
    "sg:postcode":"35781",
    "sg:province":"Hessen",
    "wof:name":"Weilburger Coatings Gmbh",
    "wof:placetype":"venue"
},
  "geometry": {"coordinates":[8.2701721191,50.4875717163],"type":"Point"}
}