{
  "type": "Feature",
  "properties": {
    "iso:country":"DE",
    "sg:address":"Libellenstr. 89c",
    "sg:city":"Verl",
    "sg:postcode":"33415",
    "sg:province":"Nordrhein-Westfalen",
    "wof:name":"Stadtb\u00fccherei",
    "wof:placetype":"venue"
},
  "geometry": {"coordinates":[8.478261,51.889084],"type":"Point"}
}