{
  "type": "Feature",
  "properties": {
    "iso:country":"DE",
    "sg:address":"Zittauer Str. 23 b",
    "sg:city":"Kurort Jonsdorf",
    "sg:phone":"+49 35844/70176",
    "sg:postcode":"02796",
    "sg:province":"Sachsen",
    "wof:name":"Regina Lischke",
    "wof:placetype":"venue"
},
  "geometry": {"coordinates":[14.7144565582,50.8592147827],"type":"Point"}
}