{
  "type": "Feature",
  "properties": {
    "iso:country":"DE",
    "sg:address":"Karl-Gl\u00f6ckner Stra\u00dfe 21b",
    "sg:city":"Giessen",
    "sg:phone":"+49 641",
    "sg:postcode":"35394",
    "sg:province":"Hessen",
    "wof:name":"Uni-giessen Professur F\u00fcr Erwachsenenbildung",
    "wof:placetype":"venue"
},
  "geometry": {"coordinates":[8.69832,50.573029],"type":"Point"}
}