{
  "type": "Feature",
  "properties": {
    "iso:country":"DE",
    "sg:address":"Anger 15",
    "sg:city":"Erfurt",
    "sg:phone":"+49 361/5623929",
    "sg:postcode":"99084",
    "sg:province":"Th\u00fcringen",
    "wof:name":"La Mode Handelsgesellschaft Mbh",
    "wof:placetype":"venue"
},
  "geometry": {"coordinates":[11.0347223282,50.9762001038],"type":"Point"}
}