{
  "type": "Feature",
  "properties": {
    "iso:country":"DE",
    "sg:address":"Boschetsrieder Str. 130",
    "sg:city":"M\u00fcnchen",
    "sg:phone":"+49 89/782383",
    "sg:postcode":"81379",
    "sg:province":"Bayern",
    "wof:name":"S\u00fcdpark Konditorei",
    "wof:placetype":"venue"
},
  "geometry": {"coordinates":[11.5130691528,48.098285675],"type":"Point"}
}