{
  "type": "Feature",
  "properties": {
    "iso:country":"DE",
    "sg:address":"Blumenthalstr. 21",
    "sg:city":"Heidelberg",
    "sg:phone":"+49 6221/402632",
    "sg:postcode":"69120",
    "sg:province":"Baden-W\u00fcrttemberg",
    "wof:name":"Dr. Barbara Ansch\u00fctz Rechtsanw\u00e4ltin",
    "wof:placetype":"venue"
},
  "geometry": {"coordinates":[8.6870479584,49.4209938049],"type":"Point"}
}