{
  "type": "Feature",
  "properties": {
    "iso:country":"DE",
    "sg:address":"Am Dobbenacker 8",
    "sg:city":"Borkum",
    "sg:phone":"+49 4922/2932",
    "sg:postcode":"26757",
    "sg:province":"Niedersachsen",
    "wof:name":"Pension Haus Heike Inh. Sybille Fuchs",
    "wof:placetype":"venue"
},
  "geometry": {"coordinates":[6.6737828255,53.5886154175],"type":"Point"}
}