{
  "type": "Feature",
  "properties": {
    "iso:country":"DE",
    "sg:address":"Bahnhofstr. 76 - 78",
    "sg:city":"Schifferstadt",
    "sg:phone":"+49 6235/81091",
    "sg:postcode":"67105",
    "sg:province":"Rheinland-Pfalz",
    "wof:name":"Ludwig Kr\u00e4mer",
    "wof:placetype":"venue"
},
  "geometry": {"coordinates":[8.3704595566,49.3897666931],"type":"Point"}
}