{
  "type": "Feature",
  "properties": {
    "iso:country":"DE",
    "sg:address":"Keltenstr. 21 a",
    "sg:city":"D\u00fcren",
    "sg:phone":"+49 2421/72198",
    "sg:postcode":"52351",
    "sg:province":"Nordrhein-Westfalen",
    "wof:name":"J\u00fcrgen Lennartz Architekt",
    "wof:placetype":"venue"
},
  "geometry": {"coordinates":[6.50071,50.797699],"type":"Point"}
}