{
  "type": "Feature",
  "properties": {
    "iso:country":"DE",
    "sg:address":"Anglerstr. 7",
    "sg:city":"M\u00fcnchen",
    "sg:phone":"+49 89/5025562",
    "sg:postcode":"80339",
    "sg:province":"Bayern",
    "wof:name":"Rege Management Gmbh",
    "wof:placetype":"venue"
},
  "geometry": {"coordinates":[11.535733,48.133209],"type":"Point"}
}