{
  "type": "Feature",
  "properties": {
    "iso:country":"DE",
    "sg:address":"Rathausstr. 1a",
    "sg:city":"Wilnsdorf",
    "sg:phone":"+49 2739/4085",
    "sg:postcode":"57234",
    "sg:province":"Nordrhein-Westfalen",
    "wof:name":"Sparkasse Siegen",
    "wof:placetype":"venue"
},
  "geometry": {"coordinates":[8.10832,50.818539],"type":"Point"}
}