{
  "type": "Feature",
  "properties": {
    "iso:country":"DE",
    "sg:address":"An der E\u00dfseite 50",
    "sg:city":"Gronau",
    "sg:phone":"+49 2565/97521",
    "sg:postcode":"48599",
    "sg:province":"Nordrhein-Westfalen",
    "wof:name":"Sc Verwaltungs- Beteiligungs- Und",
    "wof:placetype":"venue"
},
  "geometry": {"coordinates":[7.0330319405,52.1984786987],"type":"Point"}
}