{
  "type": "Feature",
  "properties": {
    "iso:country":"DE",
    "sg:address":"Reinsdorfer Wg. 2-4",
    "sg:city":"Netzschkau",
    "sg:phone":"+49 4937/654920",
    "sg:postcode":"08491",
    "sg:province":"Sachsen",
    "wof:name":"Nema Airfin Gmbh",
    "wof:placetype":"venue"
},
  "geometry": {"coordinates":[12.243047,50.616001],"type":"Point"}
}