{
  "type": "Feature",
  "properties": {
    "iso:country":"DE",
    "sg:address":"Hauptstra\u00dfe 15",
    "sg:city":"Gebsattel",
    "sg:postcode":"91607",
    "sg:province":"Bayern",
    "wof:name":"Ferienwohnung Familie Christ In Franken, Bayern, Nahe Rothen",
    "wof:placetype":"venue"
},
  "geometry": {"coordinates":[10.201792717,49.3527259827],"type":"Point"}
}