{
  "type": "Feature",
  "properties": {
    "iso:country":"DE",
    "sg:address":"Binderstr. 29",
    "sg:city":"Hildesheim",
    "sg:phone":"+49 5121/35259",
    "sg:postcode":"31141",
    "sg:province":"Niedersachsen",
    "wof:name":"Schwedhelm Fliesenverlege Fachbetrieb Gmbh",
    "wof:placetype":"venue"
},
  "geometry": {"coordinates":[9.9579076767,52.1515083313],"type":"Point"}
}