{
  "type": "Feature",
  "properties": {
    "iso:country":"DE",
    "sg:address":"Kladdinger Str. 9a",
    "sg:city":"Stuhr",
    "sg:phone":"+49 421/5669420",
    "sg:postcode":"28816",
    "sg:province":"Niedersachsen",
    "wof:name":"Barbara Pitschke Architektin",
    "wof:placetype":"venue"
},
  "geometry": {"coordinates":[8.757494,53.031685],"type":"Point"}
}