{
  "type": "Feature",
  "properties": {
    "iso:country":"DE",
    "sg:address":"Oschatzer Str.",
    "sg:city":"Oschatz",
    "sg:phone":"+49 3435/622143",
    "sg:postcode":"04758",
    "sg:province":"Sachsen",
    "wof:name":"Tyczka Minol Gmbh",
    "wof:placetype":"venue"
},
  "geometry": {"coordinates":[13.0904245377,51.3167114258],"type":"Point"}
}