{
  "type": "Feature",
  "properties": {
    "iso:country":"DE",
    "sg:address":"Otterweg 73",
    "sg:city":"Baldham",
    "sg:phone":"+49 8106/4615",
    "sg:postcode":"85598",
    "sg:province":"Bayern",
    "wof:name":"Werner W. Haferkamp Gmbh",
    "wof:placetype":"venue"
},
  "geometry": {"coordinates":[11.7954549789,48.1009559631],"type":"Point"}
}