{
  "type": "Feature",
  "properties": {
    "iso:country":"DE",
    "sg:address":"Aachener Str. 25",
    "sg:city":"Solingen",
    "sg:phone":"+49 212/73595",
    "sg:postcode":"42697",
    "sg:province":"Nordrhein-Westfalen",
    "wof:name":"Kroatia Grill",
    "wof:placetype":"venue"
},
  "geometry": {"coordinates":[6.9979701042,51.1628265381],"type":"Point"}
}