{
  "type": "Feature",
  "properties": {
    "iso:country":"DE",
    "sg:address":"An der Reitbahn 3",
    "sg:city":"Stuhr",
    "sg:phone":"+49 421/891794",
    "sg:postcode":"28816",
    "sg:province":"Niedersachsen",
    "wof:name":"Fritz Rendigs",
    "wof:placetype":"venue"
},
  "geometry": {"coordinates":[8.7902030945,53.0021896362],"type":"Point"}
}