{
  "type": "Feature",
  "properties": {
    "iso:country":"DE",
    "sg:address":"Nachtweide 150",
    "sg:city":"Nauheim",
    "sg:phone":"+49 6152/961283",
    "sg:postcode":"64569",
    "sg:province":"Hessen",
    "wof:name":"Dr. A. Walczyk Architekt",
    "wof:placetype":"venue"
},
  "geometry": {"coordinates":[8.472227,49.959373],"type":"Point"}
}