{
  "type": "Feature",
  "properties": {
    "iso:country":"DE",
    "sg:address":"Gartenstr. 26",
    "sg:city":"Rimbach",
    "sg:phone":"+49 9941/1475",
    "sg:postcode":"93485",
    "sg:province":"Bayern",
    "wof:name":"A. Aschenbrenner",
    "wof:placetype":"venue"
},
  "geometry": {"coordinates":[12.8770551682,49.2316932678],"type":"Point"}
}