{
  "type": "Feature",
  "properties": {
    "iso:country":"DE",
    "sg:address":"G\u00fcntherstr. 31",
    "sg:city":"Sondershausen",
    "sg:phone":"+49 3632/57681",
    "sg:postcode":"99706",
    "sg:province":"Th\u00fcringen",
    "wof:name":"Ingo Laubvogel Notar",
    "wof:placetype":"venue"
},
  "geometry": {"coordinates":[10.8605480194,51.3678817749],"type":"Point"}
}