{
  "type": "Feature",
  "properties": {
    "iso:country":"DE",
    "sg:address":"Sommerichweg 6",
    "sg:city":"Eitorf",
    "sg:phone":"+49 2243/7500",
    "sg:postcode":"53783",
    "sg:province":"Nordrhein-Westfalen",
    "wof:name":"Hans-dieter Herkert Finanzberater",
    "wof:placetype":"venue"
},
  "geometry": {"coordinates":[7.4603981972,50.7494277954],"type":"Point"}
}