{
  "type": "Feature",
  "properties": {
    "iso:country":"DE",
    "sg:address":"Lecker Str. 14",
    "sg:city":"Achtrup",
    "sg:phone":"+49 4662/5577",
    "sg:postcode":"25917",
    "sg:province":"Schleswig-Holstein",
    "wof:name":"Mangnus Jessen",
    "wof:placetype":"venue"
},
  "geometry": {"coordinates":[9.0252714157,54.7891845703],"type":"Point"}
}