{
  "type": "Feature",
  "properties": {
    "iso:country":"DE",
    "sg:address":"Im Heggen 25",
    "sg:city":"Gangelt",
    "sg:phone":"+49 2454/6149",
    "sg:postcode":"52538",
    "sg:province":"Nordrhein-Westfalen",
    "wof:name":"Heinz Dieken",
    "wof:placetype":"venue"
},
  "geometry": {"coordinates":[6.0162677765,51.0192832947],"type":"Point"}
}