{
  "type": "Feature",
  "properties": {
    "iso:country":"DE",
    "sg:address":"Hainsbach 25",
    "sg:city":"Geiselh\u00f6ring",
    "sg:phone":"+49 9423/805",
    "sg:postcode":"94333",
    "sg:province":"Bayern",
    "wof:name":"Alfons Breu",
    "wof:placetype":"venue"
},
  "geometry": {"coordinates":[12.424219,48.804035],"type":"Point"}
}