{
  "type": "Feature",
  "properties": {
    "iso:country":"DE",
    "sg:address":"Am Brauberg 2",
    "sg:city":"Ballenstedt",
    "sg:phone":"+49 39483/8723",
    "sg:postcode":"06493",
    "sg:province":"Sachsen-Anhalt",
    "wof:name":"Restaurant Zum Brauberg",
    "wof:placetype":"venue"
},
  "geometry": {"coordinates":[11.221039772,51.7164154053],"type":"Point"}
}