{
  "type": "Feature",
  "properties": {
    "iso:country":"DE",
    "sg:address":"Stra\u00dfe der Einheit 57",
    "sg:city":"Schwarzenberg",
    "sg:phone":"+49 3774/20090",
    "sg:postcode":"08340",
    "sg:province":"Sachsen",
    "wof:name":"J. Wichert Immobilienmakler",
    "wof:placetype":"venue"
},
  "geometry": {"coordinates":[12.7732210159,50.547542572],"type":"Point"}
}