{
  "type": "Feature",
  "properties": {
    "iso:country":"DE",
    "sg:address":"Bauschanweg 7",
    "sg:city":"Rostock",
    "sg:phone":"+49 381/83435",
    "sg:postcode":"18069",
    "sg:province":"Mecklenburg-Vorpommern",
    "wof:name":"E. Ohm",
    "wof:placetype":"venue"
},
  "geometry": {"coordinates":[12.0829458237,54.1023101807],"type":"Point"}
}