{
  "type": "Feature",
  "properties": {
    "iso:country":"DE",
    "sg:address":"Kirchstr. 18",
    "sg:city":"Kirchhasel",
    "sg:phone":"+49 3672/424441",
    "sg:postcode":"07407",
    "sg:province":"Th\u00fcringen",
    "wof:name":"H & K Tischlerei Gmbh",
    "wof:placetype":"venue"
},
  "geometry": {"coordinates":[11.396736,50.728397],"type":"Point"}
}