{
  "type": "Feature",
  "properties": {
    "iso:country":"DE",
    "sg:address":"Kreuzwehrstr. 14",
    "sg:city":"Coburg",
    "sg:phone":"+49 9561/90063",
    "sg:postcode":"96450",
    "sg:province":"Bayern",
    "wof:name":"Kreuzwehrstuben",
    "wof:placetype":"venue"
},
  "geometry": {"coordinates":[10.9614095688,50.2644577026],"type":"Point"}
}