{
  "type": "Feature",
  "properties": {
    "iso:country":"DE",
    "sg:address":"Neuenhauser Str. 42",
    "sg:city":"Nordhorn",
    "sg:phone":"+49 5921/34593",
    "sg:postcode":"48529",
    "sg:province":"Niedersachsen",
    "wof:name":"Gerhard Sloot",
    "wof:placetype":"venue"
},
  "geometry": {"coordinates":[7.0666399002,52.4398880005],"type":"Point"}
}