{
  "type": "Feature",
  "properties": {
    "iso:country":"DE",
    "sg:address":"Kolm 7",
    "sg:city":"Eckernf\u00f6rde",
    "sg:phone":"+49 4351/73290",
    "sg:postcode":"24340",
    "sg:province":"Schleswig-Holstein",
    "wof:name":"Discothek K7 Eckernf\u00f6rde",
    "wof:placetype":"venue"
},
  "geometry": {"coordinates":[9.8372497559,54.4514694214],"type":"Point"}
}