{
  "type": "Feature",
  "properties": {
    "iso:country":"DE",
    "sg:address":"Haffkamp 19",
    "sg:city":"Kuddew\u00f6rde",
    "sg:phone":"+49 4154/3372",
    "sg:postcode":"22958",
    "sg:province":"Schleswig-Holstein",
    "wof:name":"Jens Tautz Masseur",
    "wof:placetype":"venue"
},
  "geometry": {"coordinates":[10.39504,53.57906],"type":"Point"}
}