{
  "type": "Feature",
  "properties": {
    "iso:country":"DE",
    "sg:address":"Schwarzenbacher Ring 1",
    "sg:city":"H\u00f6chstadt",
    "sg:phone":"+49 9193/3910",
    "sg:postcode":"91315",
    "sg:province":"Bayern",
    "wof:name":"Roland Niklas",
    "wof:placetype":"venue"
},
  "geometry": {"coordinates":[10.803011,49.694691],"type":"Point"}
}