{
  "type": "Feature",
  "properties": {
    "iso:country":"DE",
    "sg:address":"Andreestr. 10",
    "sg:city":"M\u00fcnchen",
    "sg:phone":"+49 89/1679104",
    "sg:postcode":"80634",
    "sg:province":"Bayern",
    "wof:name":"Creperie Neuhausen",
    "wof:placetype":"venue"
},
  "geometry": {"coordinates":[11.5295324326,48.1512489319],"type":"Point"}
}