{
  "type": "Feature",
  "properties": {
    "iso:country":"DE",
    "sg:address":"Grabenstr. 8",
    "sg:city":"Asbach",
    "sg:phone":"+49 2683/43556",
    "sg:postcode":"53567",
    "sg:province":"Rheinland-Pfalz",
    "wof:name":"Uwe Hammerschmidt",
    "wof:placetype":"venue"
},
  "geometry": {"coordinates":[7.4569277763,50.6871490479],"type":"Point"}
}