{
  "type": "Feature",
  "properties": {
    "iso:country":"DE",
    "sg:address":"Talbahnstr. 17",
    "sg:city":"Duisburg",
    "sg:phone":"+49 4920/3425229",
    "sg:postcode":"47137",
    "sg:province":"Nordrhein-Westfalen",
    "wof:name":"Wehner Web-technik",
    "wof:placetype":"venue"
},
  "geometry": {"coordinates":[6.7831091881,51.4745025635],"type":"Point"}
}