{
  "type": "Feature",
  "properties": {
    "iso:country":"DE",
    "sg:address":"Steinstr. 1",
    "sg:city":"Gifhorn",
    "sg:phone":"+49 5371/71531",
    "sg:postcode":"38518",
    "sg:province":"Niedersachsen",
    "wof:name":"Uhlich Holzbau Gmbh",
    "wof:placetype":"venue"
},
  "geometry": {"coordinates":[10.545863,52.487736],"type":"Point"}
}