{
  "type": "Feature",
  "properties": {
    "iso:country":"DE",
    "sg:address":"Bergham 3",
    "sg:city":"Polling",
    "sg:phone":"+49 8633/4858689",
    "sg:postcode":"84570",
    "sg:province":"Bayern",
    "wof:name":"Georg Wieser",
    "wof:placetype":"venue"
},
  "geometry": {"coordinates":[12.56192,48.198586],"type":"Point"}
}