{
  "type": "Feature",
  "properties": {
    "iso:country":"DE",
    "sg:address":"Puschkinstr. 9",
    "sg:city":"L\u00fcbben",
    "sg:phone":"+49 3546/4384",
    "sg:postcode":"15907",
    "sg:province":"Brandenburg",
    "wof:name":"Glig Handelsgesellschaft Mbh",
    "wof:placetype":"venue"
},
  "geometry": {"coordinates":[13.890506,51.937618],"type":"Point"}
}