{
  "type": "Feature",
  "properties": {
    "iso:country":"DE",
    "sg:address":"Rheinstr. 29",
    "sg:city":"Landau",
    "sg:phone":"+49 6341/86731",
    "sg:postcode":"76829",
    "sg:province":"Rheinland-Pfalz",
    "wof:name":"Otto Ludwig",
    "wof:placetype":"venue"
},
  "geometry": {"coordinates":[8.1239538193,49.1956291199],"type":"Point"}
}