{
  "type": "Feature",
  "properties": {
    "iso:country":"DE",
    "sg:address":"Frankfurter Str. 6",
    "sg:city":"Troisdorf",
    "sg:phone":"+49 2241/83385",
    "sg:postcode":"53840",
    "sg:province":"Nordrhein-Westfalen",
    "wof:name":"K. Hemmersbach Ingenieur",
    "wof:placetype":"venue"
},
  "geometry": {"coordinates":[7.1665220261,50.8145523071],"type":"Point"}
}