{
  "type": "Feature",
  "properties": {
    "iso:country":"DE",
    "sg:address":"Klingenstr. 31",
    "sg:city":"Leipzig",
    "sg:phone":"+49 341/476523",
    "sg:postcode":"04229",
    "sg:province":"Sachsen",
    "wof:name":"Feist & Wendt Elektromaschinenbau",
    "wof:placetype":"venue"
},
  "geometry": {"coordinates":[12.324299,51.321243],"type":"Point"}
}