{
  "type": "Feature",
  "properties": {
    "iso:country":"DE",
    "sg:address":"Rosengartenstr. 11",
    "sg:city":"Leonberg",
    "sg:phone":"+49 7152/47484",
    "sg:postcode":"71229",
    "sg:province":"Baden-W\u00fcrttemberg",
    "wof:name":"Bacher",
    "wof:placetype":"venue"
},
  "geometry": {"coordinates":[8.9856510162,48.762172699],"type":"Point"}
}