{
  "type": "Feature",
  "properties": {
    "iso:country":"DE",
    "sg:address":"Barbarastr. 5",
    "sg:city":"Bestwig",
    "sg:phone":"+49 2905/791",
    "sg:postcode":"59909",
    "sg:province":"Nordrhein-Westfalen",
    "wof:name":"Rolf Schl\u00fcter",
    "wof:placetype":"venue"
},
  "geometry": {"coordinates":[8.432604,51.324093],"type":"Point"}
}