{
  "type": "Feature",
  "properties": {
    "iso:country":"DE",
    "sg:address":"Storchenb\u00fchl 1",
    "sg:city":"Balingen",
    "sg:phone":"+49 7433/382030",
    "sg:postcode":"72336",
    "sg:province":"Baden-W\u00fcrttemberg",
    "wof:name":"J. Merz",
    "wof:placetype":"venue"
},
  "geometry": {"coordinates":[8.8361625671,48.2337608337],"type":"Point"}
}