{
  "type": "Feature",
  "properties": {
    "iso:country":"DE",
    "sg:address":"Freiling 5",
    "sg:city":"Bad Birnbach",
    "sg:phone":"+49 8565/259",
    "sg:postcode":"84364",
    "sg:province":"Bayern",
    "wof:name":"Landhotel Forellenhof",
    "wof:placetype":"venue"
},
  "geometry": {"coordinates":[13.0260028839,48.4692306519],"type":"Point"}
}