{
  "type": "Feature",
  "properties": {
    "iso:country":"DE",
    "sg:address":"K\u00f6nigsbacher Weg 29",
    "sg:city":"Walzbachtal",
    "sg:phone":"+49 7203/5336",
    "sg:postcode":"75045",
    "sg:province":"Baden-W\u00fcrttemberg",
    "wof:name":"Willi Goppelsr\u00f6der",
    "wof:placetype":"venue"
},
  "geometry": {"coordinates":[8.61255,49.004745],"type":"Point"}
}