{
  "type": "Feature",
  "properties": {
    "iso:country":"DE",
    "sg:address":"Sch\u00f6nower Str. 45",
    "sg:city":"Zepernick",
    "sg:phone":"+49 30/9442229",
    "sg:postcode":"16341",
    "sg:province":"Brandenburg",
    "wof:name":"Aqua-wasserbehandlung Gmbh",
    "wof:placetype":"venue"
},
  "geometry": {"coordinates":[13.53431,52.658169],"type":"Point"}
}