{
  "type": "Feature",
  "properties": {
    "iso:country":"DE",
    "sg:address":"Ernst-Ohlmer-Str. 20",
    "sg:city":"Hildesheim",
    "sg:phone":"+49 5121/42202",
    "sg:postcode":"31139",
    "sg:province":"Niedersachsen",
    "wof:name":"Erwin-robert Kasulke",
    "wof:placetype":"venue"
},
  "geometry": {"coordinates":[9.935012,52.138336],"type":"Point"}
}