{
  "type": "Feature",
  "properties": {
    "iso:country":"DE",
    "sg:address":"Weinstr. 46",
    "sg:city":"B\u00fchl",
    "sg:phone":"+49 7223/910900",
    "sg:postcode":"77815",
    "sg:province":"Baden-W\u00fcrttemberg",
    "wof:name":"Guido Hahn",
    "wof:placetype":"venue"
},
  "geometry": {"coordinates":[8.153596,48.711716],"type":"Point"}
}