{
  "type": "Feature",
  "properties": {
    "iso:country":"DE",
    "sg:address":"\u00dcberreiterstr. 14",
    "sg:city":"M\u00fcnchen",
    "sg:phone":"+49 89/8116232",
    "sg:postcode":"81247",
    "sg:province":"Bayern",
    "wof:name":"Art-muenchen",
    "wof:placetype":"venue"
},
  "geometry": {"coordinates":[11.4864177704,48.1656227112],"type":"Point"}
}