{
  "type": "Feature",
  "properties": {
    "iso:country":"DE",
    "sg:address":"Erlenweg 3",
    "sg:city":"Nesselwang",
    "sg:phone":"+49 8361/1428",
    "sg:postcode":"87484",
    "sg:province":"Bayern",
    "wof:name":"Valerie Weeber",
    "wof:placetype":"venue"
},
  "geometry": {"coordinates":[10.5048141479,47.6227722168],"type":"Point"}
}