{
  "type": "Feature",
  "properties": {
    "iso:country":"DE",
    "sg:address":"Oberer Baselblick 29",
    "sg:city":"Inzlingen",
    "sg:phone":"+49 7621/88305",
    "sg:postcode":"79594",
    "sg:province":"Baden-W\u00fcrttemberg",
    "wof:name":"Verein Zur Erhaltung Des Inzlinger Wasserschlo\u00dfes E. V.",
    "wof:placetype":"venue"
},
  "geometry": {"coordinates":[7.6874880791,47.58934021],"type":"Point"}
}