{
  "type": "Feature",
  "properties": {
    "iso:country":"DE",
    "sg:address":"Hauptstr. 63",
    "sg:city":"Berlingerode",
    "sg:phone":"+49 36071/96582",
    "sg:postcode":"37339",
    "sg:province":"Th\u00fcringen",
    "wof:name":"Fritz Hannemann",
    "wof:placetype":"venue"
},
  "geometry": {"coordinates":[10.236958,51.457443],"type":"Point"}
}