{
  "type": "Feature",
  "properties": {
    "iso:country":"DE",
    "sg:address":"Schm\u00e4inghook 36",
    "sg:city":"Ahaus",
    "sg:phone":"+49 2567/380",
    "sg:postcode":"48683",
    "sg:province":"Nordrhein-Westfalen",
    "wof:name":"Hotel-restaurant Golfhotel Ahaus",
    "wof:placetype":"venue"
},
  "geometry": {"coordinates":[6.9252181053,52.1112861633],"type":"Point"}
}