{
  "type": "Feature",
  "properties": {
    "iso:country":"DE",
    "sg:address":"Windesheimer Str. 14",
    "sg:city":"Bad Kreuznach",
    "sg:phone":"+49 671/27038",
    "sg:postcode":"55545",
    "sg:province":"Rheinland-Pfalz",
    "wof:name":"Waldemar M\u00fcller Ingenieur",
    "wof:placetype":"venue"
},
  "geometry": {"coordinates":[7.8639369011,49.8659477234],"type":"Point"}
}