{
  "type": "Feature",
  "properties": {
    "iso:country":"DE",
    "sg:address":"Rathausplatz 1",
    "sg:city":"Limbach-Oberfrohna",
    "sg:phone":"+49 3722/780",
    "sg:postcode":"09212",
    "sg:province":"Sachsen",
    "wof:name":"Tierpark Limbach-oberfrohna Amt 40",
    "wof:placetype":"venue"
},
  "geometry": {"coordinates":[12.76795,50.858467],"type":"Point"}
}