{
  "type": "Feature",
  "properties": {
    "iso:country":"DE",
    "sg:address":"Hohe Pforte 2 a",
    "sg:city":"K\u00f6ln",
    "sg:phone":"+49 221/21010210",
    "sg:postcode":"50676",
    "sg:province":"Nordrhein-Westfalen",
    "wof:name":"Gauditz Telekommunikation",
    "wof:placetype":"venue"
},
  "geometry": {"coordinates":[6.9564099312,50.932964325],"type":"Point"}
}