{
  "type": "Feature",
  "properties": {
    "iso:country":"DE",
    "sg:address":"Steilshooper Str. 309",
    "sg:city":"Hamburg",
    "sg:phone":"+49 40/6311285",
    "sg:postcode":"22309",
    "sg:province":"Hamburg",
    "wof:name":"Empire Handels- Und Automaten- Aufstellung Gmbh",
    "wof:placetype":"venue"
},
  "geometry": {"coordinates":[10.056014061,53.60679245],"type":"Point"}
}