{
  "type": "Feature",
  "properties": {
    "iso:country":"DE",
    "sg:address":"Rolgenmoos 11",
    "sg:city":"Horgenzell",
    "sg:phone":"+49 7504/291",
    "sg:postcode":"88263",
    "sg:province":"Baden-W\u00fcrttemberg",
    "wof:name":"Max Jehle",
    "wof:placetype":"venue"
},
  "geometry": {"coordinates":[9.5041027069,47.7685585022],"type":"Point"}
}