{
  "type": "Feature",
  "properties": {
    "iso:country":"DE",
    "sg:address":"Konradstr. 45 D",
    "sg:city":"Kamp-Lintfort",
    "sg:phone":"+49 2842/13194",
    "sg:postcode":"47475",
    "sg:province":"Nordrhein-Westfalen",
    "wof:name":"Ibs Gesellschaft F\u00fcr Bautenschutz Gmbh",
    "wof:placetype":"venue"
},
  "geometry": {"coordinates":[6.5396728516,51.5027542114],"type":"Point"}
}