{
  "type": "Feature",
  "properties": {
    "iso:country":"DE",
    "sg:address":"Belmer Str. 10",
    "sg:city":"Belm",
    "sg:phone":"+49 5406/2383",
    "sg:postcode":"49191",
    "sg:province":"Niedersachsen",
    "wof:name":"Finke Moden",
    "wof:placetype":"venue"
},
  "geometry": {"coordinates":[8.138361,52.300705],"type":"Point"}
}