{
  "type": "Feature",
  "properties": {
    "iso:country":"DE",
    "sg:address":"Hauptstr. 2",
    "sg:city":"Ventschow",
    "sg:phone":"+49 38484/60218",
    "sg:postcode":"19417",
    "sg:province":"Mecklenburg-Vorpommern",
    "wof:name":"Karl-ulrich Hopp",
    "wof:placetype":"venue"
},
  "geometry": {"coordinates":[11.581117,53.788818],"type":"Point"}
}