{
  "type": "Feature",
  "properties": {
    "iso:country":"DE",
    "sg:address":"Siemensstr. 11",
    "sg:city":"Glauchau",
    "sg:postcode":"08371",
    "sg:province":"Sachsen",
    "wof:name":"Solid Leasing Und Finanzvermittlungs Gmbh",
    "wof:placetype":"venue"
},
  "geometry": {"coordinates":[12.519667,50.833462],"type":"Point"}
}