{
  "type": "Feature",
  "properties": {
    "iso:country":"DE",
    "sg:address":"Elbestr. 11",
    "sg:city":"Fulda",
    "sg:phone":"+49 661/54484",
    "sg:postcode":"36041",
    "sg:province":"Hessen",
    "wof:name":"Josef Fr\u00f6hlich",
    "wof:placetype":"venue"
},
  "geometry": {"coordinates":[9.63754,50.561794],"type":"Point"}
}