{
  "type": "Feature",
  "properties": {
    "iso:country":"DE",
    "sg:address":"Braugasse 7",
    "sg:city":"Gie\u00dfen",
    "sg:postcode":"35390",
    "sg:province":"Hessen",
    "wof:name":"Institut F\u00fcr Landtechnik",
    "wof:placetype":"venue"
},
  "geometry": {"coordinates":[8.67815,50.58902],"type":"Point"}
}