{
  "type": "Feature",
  "properties": {
    "iso:country":"DE",
    "sg:address":"Auf der H\u00f6he 3",
    "sg:city":"Rehburg-Loccum",
    "sg:phone":"+49 5037/1318",
    "sg:postcode":"31547",
    "sg:province":"Niedersachsen",
    "wof:name":"Wilhelm Auhage",
    "wof:placetype":"venue"
},
  "geometry": {"coordinates":[9.25323,52.450825],"type":"Point"}
}