{
  "type": "Feature",
  "properties": {
    "iso:country":"DE",
    "sg:address":"Waldstr. 13",
    "sg:city":"Haundorf",
    "sg:phone":"+49 9837/95961",
    "sg:postcode":"91729",
    "sg:province":"Bayern",
    "wof:name":"B\u00e4ckerei-konditorei-cafe Zum Forstweiher Gmbh",
    "wof:placetype":"venue"
},
  "geometry": {"coordinates":[10.806026,49.147602],"type":"Point"}
}