{
  "type": "Feature",
  "properties": {
    "iso:country":"DE",
    "sg:address":"Dornaper Str. 16-18",
    "sg:city":"Wuppertal",
    "sg:postcode":"42327",
    "sg:province":"Nordrhein-Westfalen",
    "wof:name":"Interactive Consulting Associates Gmbh",
    "wof:placetype":"venue"
},
  "geometry": {"coordinates":[7.0595579147,51.2552452087],"type":"Point"}
}