{
  "type": "Feature",
  "properties": {
    "iso:country":"DE",
    "sg:address":"Klammstr. 14",
    "sg:city":"Garmisch-Partenkirchen",
    "sg:phone":"+49 8821/79699",
    "sg:postcode":"82467",
    "sg:province":"Bayern",
    "wof:name":"Grand-cafe",
    "wof:placetype":"venue"
},
  "geometry": {"coordinates":[11.0898666382,47.4921875],"type":"Point"}
}