{
  "type": "Feature",
  "properties": {
    "iso:country":"DE",
    "sg:address":"Knappenweg 8",
    "sg:city":"Eschweiler",
    "sg:phone":"+49 2403/52743",
    "sg:postcode":"52249",
    "sg:province":"Nordrhein-Westfalen",
    "wof:name":"Walter Bl\u00e4ser",
    "wof:placetype":"venue"
},
  "geometry": {"coordinates":[6.281768,50.834579],"type":"Point"}
}