{
  "type": "Feature",
  "properties": {
    "iso:country":"DE",
    "sg:address":"Fischergasse 3",
    "sg:city":"Wertheim",
    "sg:phone":"+49 9342/92450",
    "sg:postcode":"97877",
    "sg:province":"Baden-W\u00fcrttemberg",
    "wof:name":"W. V\u00f6lkl",
    "wof:placetype":"venue"
},
  "geometry": {"coordinates":[9.513715744,49.7600517273],"type":"Point"}
}