{
  "type": "Feature",
  "properties": {
    "iso:country":"DE",
    "sg:address":"Hubertusstr. 6",
    "sg:city":"Korschenbroich",
    "sg:phone":"+49 2161/641474",
    "sg:postcode":"41352",
    "sg:province":"Nordrhein-Westfalen",
    "wof:name":"W. Meuser",
    "wof:placetype":"venue"
},
  "geometry": {"coordinates":[6.5066628456,51.2077674866],"type":"Point"}
}