{
  "type": "Feature",
  "properties": {
    "iso:country":"DE",
    "sg:address":"Hauptstr. 57",
    "sg:city":"Tiefenbach",
    "sg:phone":"+49 8709/3757",
    "sg:postcode":"84184",
    "sg:province":"Bayern",
    "wof:name":"Birkle Thomer & Resch Gmbh",
    "wof:placetype":"venue"
},
  "geometry": {"coordinates":[12.1016111374,48.4995384216],"type":"Point"}
}