{
  "type": "Feature",
  "properties": {
    "iso:country":"DE",
    "sg:address":"Schlo\u00dfstr. 21",
    "sg:city":"Dexheim",
    "sg:phone":"+49 6133/58880",
    "sg:postcode":"55278",
    "sg:province":"Rheinland-Pfalz",
    "wof:name":"Willi Bub",
    "wof:placetype":"venue"
},
  "geometry": {"coordinates":[8.3189115524,49.8477249146],"type":"Point"}
}