{
  "type": "Feature",
  "properties": {
    "iso:country":"DE",
    "sg:address":"M\u00fchlstr. 102",
    "sg:city":"Walluf",
    "sg:phone":"+49 6123/72478",
    "sg:postcode":"65396",
    "sg:province":"Hessen",
    "wof:name":"Schipp & Sohn Gmbh",
    "wof:placetype":"venue"
},
  "geometry": {"coordinates":[8.1507701874,50.0385818481],"type":"Point"}
}