{
  "type": "Feature",
  "properties": {
    "iso:country":"DE",
    "sg:address":"M\u00fchlgasse 13",
    "sg:city":"Schwarzhausen",
    "sg:postcode":"99891",
    "sg:province":"Th\u00fcringen",
    "wof:name":"Anton Ohlig Bauunternehmen Th\u00fcringen Gmbh",
    "wof:placetype":"venue"
},
  "geometry": {"coordinates":[10.470441,50.899872],"type":"Point"}
}