{
  "type": "Feature",
  "properties": {
    "iso:country":"DE",
    "sg:address":"Seestr. 1",
    "sg:city":"Konstanz",
    "sg:postcode":"78464",
    "sg:province":"Baden-W\u00fcrttemberg",
    "wof:name":"Werner H\u00e4usler",
    "wof:placetype":"venue"
},
  "geometry": {"coordinates":[9.1800451279,47.6667442322],"type":"Point"}
}