{
  "type": "Feature",
  "properties": {
    "iso:country":"DE",
    "sg:address":"Reichartstr. 19a",
    "sg:city":"Gr\u00e4felfing",
    "sg:phone":"+49 89/853125",
    "sg:postcode":"82166",
    "sg:province":"Bayern",
    "wof:name":"Heinz-peter R\u00f6thlein Rechtsanwalt",
    "wof:placetype":"venue"
},
  "geometry": {"coordinates":[11.4296379089,48.1139717102],"type":"Point"}
}