{
  "type": "Feature",
  "properties": {
    "iso:country":"DE",
    "sg:address":"Kastanienweg 7",
    "sg:city":"Maikammer",
    "sg:phone":"+49 6321/952690",
    "sg:postcode":"67487",
    "sg:province":"Rheinland-Pfalz",
    "wof:name":"Lothar Textor Architekt",
    "wof:placetype":"venue"
},
  "geometry": {"coordinates":[8.128996,49.306396],"type":"Point"}
}