{
  "type": "Feature",
  "properties": {
    "iso:country":"DE",
    "sg:address":"Kart\u00e4userhof 13 -15",
    "sg:city":"K\u00f6ln",
    "sg:phone":"+49 221/313013",
    "sg:postcode":"50678",
    "sg:province":"Nordrhein-Westfalen",
    "wof:name":"\u00d6hv Ungarn Tours Gmbh",
    "wof:placetype":"venue"
},
  "geometry": {"coordinates":[6.9565410614,50.9233970642],"type":"Point"}
}