{
  "type": "Feature",
  "properties": {
    "iso:country":"DE",
    "sg:address":"Finkenweg 6",
    "sg:city":"B\u00e4chingen",
    "sg:phone":"+49 7325/3125",
    "sg:postcode":"89431",
    "sg:province":"Bayern",
    "wof:name":"Helmut Klau\u00dfer",
    "wof:placetype":"venue"
},
  "geometry": {"coordinates":[10.3212747574,48.5443000793],"type":"Point"}
}