{
  "type": "Feature",
  "properties": {
    "iso:country":"DE",
    "sg:address":"Bokelbergstr. 9",
    "sg:city":"Bremen",
    "sg:phone":"+49 421/651120",
    "sg:postcode":"28755",
    "sg:province":"Bremen",
    "wof:name":"Dieter Narloch",
    "wof:placetype":"venue"
},
  "geometry": {"coordinates":[8.6096811295,53.1784133911],"type":"Point"}
}