{
  "type": "Feature",
  "properties": {
    "iso:country":"DE",
    "sg:address":"Gau-Bickelheimer Str. 42",
    "sg:city":"Sprendlingen",
    "sg:phone":"+49 6701/1032",
    "sg:postcode":"55576",
    "sg:province":"Rheinland-Pfalz",
    "wof:name":"Heinz-georg Klosheim",
    "wof:placetype":"venue"
},
  "geometry": {"coordinates":[7.9891819954,49.8575134277],"type":"Point"}
}