{
  "type": "Feature",
  "properties": {
    "iso:country":"DE",
    "sg:address":"Braunschweiger Str. 139 b",
    "sg:city":"Gifhorn",
    "sg:phone":"+49 5371/56021",
    "sg:postcode":"38518",
    "sg:province":"Niedersachsen",
    "wof:name":"Tang Dynasty Gmbh",
    "wof:placetype":"venue"
},
  "geometry": {"coordinates":[10.5424251556,52.4656181335],"type":"Point"}
}