{
  "type": "Feature",
  "properties": {
    "iso:country":"DE",
    "sg:address":"Am Fiebig",
    "sg:city":"Thiendorf",
    "sg:phone":"+49 3521/4650",
    "sg:postcode":"01561",
    "sg:province":"Sachsen",
    "wof:name":"Imbau Industrielles Bauen Gmbh",
    "wof:placetype":"venue"
},
  "geometry": {"coordinates":[13.737208,51.296566],"type":"Point"}
}