{
  "type": "Feature",
  "properties": {
    "iso:country":"DE",
    "sg:address":"Senator-Behrens-Str. 7",
    "sg:city":"Alfeld",
    "sg:phone":"+49 5181/5526",
    "sg:postcode":"31061",
    "sg:province":"Niedersachsen",
    "wof:name":"P. Timm",
    "wof:placetype":"venue"
},
  "geometry": {"coordinates":[9.839119,51.991577],"type":"Point"}
}