{
  "type": "Feature",
  "properties": {
    "iso:country":"DE",
    "sg:address":"Am Alten Berg 59",
    "sg:city":"Niederstetten",
    "sg:phone":"+49 7932/7136",
    "sg:postcode":"97996",
    "sg:province":"Baden-W\u00fcrttemberg",
    "wof:name":"Kleintierz\u00fcchter Laudenbach Siegfried Friedrich",
    "wof:placetype":"venue"
},
  "geometry": {"coordinates":[9.9221658707,49.3989486694],"type":"Point"}
}