{
  "type": "Feature",
  "properties": {
    "iso:country":"DE",
    "sg:address":"Fabrikstr. 21c",
    "sg:city":"Reichenbach",
    "sg:phone":"+49 36601/85323",
    "sg:postcode":"07629",
    "sg:province":"Th\u00fcringen",
    "wof:name":"Gerd Wiesner",
    "wof:placetype":"venue"
},
  "geometry": {"coordinates":[11.8731660843,50.8651199341],"type":"Point"}
}