{
  "type": "Feature",
  "properties": {
    "iso:country":"DE",
    "sg:address":"Hohe Str. 2-16",
    "sg:city":"Oelde",
    "sg:phone":"+49 2522/63730",
    "sg:postcode":"59302",
    "sg:province":"Nordrhein-Westfalen",
    "wof:name":"Hagebaumarkt Wilhelm Linnemann",
    "wof:placetype":"venue"
},
  "geometry": {"coordinates":[8.1456403732,51.8302192688],"type":"Point"}
}