{
  "type": "Feature",
  "properties": {
    "iso:country":"DE",
    "sg:address":"Industriestr. 9",
    "sg:city":"Geeste",
    "sg:phone":"+49 5937/8224",
    "sg:postcode":"49744",
    "sg:province":"Niedersachsen",
    "wof:name":"A. M\u00f6ller",
    "wof:placetype":"venue"
},
  "geometry": {"coordinates":[7.221414,52.582661],"type":"Point"}
}