{
  "type": "Feature",
  "properties": {
    "iso:country":"DE",
    "sg:address":"Stolzestr. 10",
    "sg:city":"Erfurt",
    "sg:postcode":"99092",
    "sg:province":"Th\u00fcringen",
    "wof:name":"Henkel Bedachungen Gmbh",
    "wof:placetype":"venue"
},
  "geometry": {"coordinates":[11.0107555389,50.9801635742],"type":"Point"}
}