{
  "type": "Feature",
  "properties": {
    "iso:country":"DE",
    "sg:address":"Reinsburgstr. 114",
    "sg:city":"Stuttgart",
    "sg:phone":"+49 711/6152190",
    "sg:postcode":"70197",
    "sg:province":"Baden-W\u00fcrttemberg",
    "wof:name":"Galerie 103",
    "wof:placetype":"venue"
},
  "geometry": {"coordinates":[9.156661,48.768208],"type":"Point"}
}