{
  "type": "Feature",
  "properties": {
    "iso:country":"DE",
    "sg:address":"Forststr. 49",
    "sg:city":"Bodenw\u00f6hr",
    "sg:postcode":"92439",
    "sg:province":"Bayern",
    "wof:name":"Therap. Arbeitskreis Beh. Frauen",
    "wof:placetype":"venue"
},
  "geometry": {"coordinates":[12.32244,49.281059],"type":"Point"}
}