{
  "type": "Feature",
  "properties": {
    "iso:country":"DE",
    "sg:address":"Tinge 25",
    "sg:city":"Sch\u00f6ppingen",
    "sg:phone":"+49 2555/726",
    "sg:postcode":"48624",
    "sg:province":"Nordrhein-Westfalen",
    "wof:name":"Josef Wolfering",
    "wof:placetype":"venue"
},
  "geometry": {"coordinates":[7.2522931099,52.0820159912],"type":"Point"}
}