{
  "type": "Feature",
  "properties": {
    "iso:country":"DE",
    "sg:address":"Marktplatz 6",
    "sg:city":"Heilbad Heiligenstadt",
    "sg:postcode":"37308",
    "sg:province":"Th\u00fcringen",
    "wof:name":"Busunternehmen Weber Golden Star Gmbh",
    "wof:placetype":"venue"
},
  "geometry": {"coordinates":[10.13717556,51.376750946],"type":"Point"}
}