{
  "type": "Feature",
  "properties": {
    "iso:country":"DE",
    "sg:address":"Donatusstr. 153 A",
    "sg:city":"Pulheim",
    "sg:phone":"+49 2234/81047",
    "sg:postcode":"50259",
    "sg:province":"Nordrhein-Westfalen",
    "wof:name":"Piepenbrock Industriewartung Beteiligungs Und Verwaltungs-",
    "wof:placetype":"venue"
},
  "geometry": {"coordinates":[6.79909,50.960331],"type":"Point"}
}