{
  "type": "Feature",
  "properties": {
    "iso:country":"DE",
    "sg:address":"Lindenstr. 16",
    "sg:city":"Fellbach",
    "sg:phone":"+49 711/581371",
    "sg:postcode":"70734",
    "sg:province":"Baden-W\u00fcrttemberg",
    "wof:name":"Hans Mack",
    "wof:placetype":"venue"
},
  "geometry": {"coordinates":[9.273712,48.805714],"type":"Point"}
}