{
  "type": "Feature",
  "properties": {
    "iso:country":"DE",
    "sg:address":"Farmweg 4",
    "sg:city":"Dollgow",
    "sg:phone":"+49 33082/51291",
    "sg:postcode":"16775",
    "sg:province":"Brandenburg",
    "wof:name":"Kies- Und Betonwerk G\u00fcldenhof Gmbh",
    "wof:placetype":"venue"
},
  "geometry": {"coordinates":[13.1537227631,52.8973045349],"type":"Point"}
}