{
  "type": "Feature",
  "properties": {
    "iso:country":"DE",
    "sg:address":"Friedrichstr. 36",
    "sg:city":"Neuwied",
    "sg:phone":"+49 2631/8303",
    "sg:postcode":"56564",
    "sg:province":"Rheinland-Pfalz",
    "wof:name":"Bildungszentrum Neuwied Gmbh",
    "wof:placetype":"venue"
},
  "geometry": {"coordinates":[7.463087,50.427216],"type":"Point"}
}