{
  "type": "Feature",
  "properties": {
    "iso:country":"DE",
    "sg:address":"M\u00f6rikestr. 23",
    "sg:city":"Kirchheim",
    "sg:phone":"+49 7021/83552",
    "sg:postcode":"73230",
    "sg:province":"Baden-W\u00fcrttemberg",
    "wof:name":"Dieter Bezler",
    "wof:placetype":"venue"
},
  "geometry": {"coordinates":[9.4818220139,48.6378555298],"type":"Point"}
}