{
  "type": "Feature",
  "properties": {
    "iso:country":"DE",
    "sg:address":"Marburger Str. 6",
    "sg:city":"Wettenberg",
    "sg:phone":"+49 6406/1771",
    "sg:postcode":"35435",
    "sg:province":"Hessen",
    "wof:name":"K. Stroh Kohlen-handlung",
    "wof:placetype":"venue"
},
  "geometry": {"coordinates":[8.680786,50.633591],"type":"Point"}
}