{
  "type": "Feature",
  "properties": {
    "iso:country":"DE",
    "sg:address":"Theodor-Heuss-Str. 26",
    "sg:city":"Gummersbach",
    "sg:phone":"+49 2261/230035",
    "sg:postcode":"51645",
    "sg:province":"Nordrhein-Westfalen",
    "wof:name":"Archiv Des Deutschen Liberalismus",
    "wof:placetype":"venue"
},
  "geometry": {"coordinates":[7.5668082237,51.0051116943],"type":"Point"}
}