{
  "type": "Feature",
  "properties": {
    "iso:country":"DE",
    "sg:address":"Heidelberger Landstr. 214",
    "sg:city":"Darmstadt",
    "sg:phone":"+49 6151/593435",
    "sg:postcode":"64297",
    "sg:province":"Hessen",
    "wof:name":"W. Steindl",
    "wof:placetype":"venue"
},
  "geometry": {"coordinates":[8.6444101334,49.8183288574],"type":"Point"}
}