{
  "type": "Feature",
  "properties": {
    "iso:country":"DE",
    "sg:address":"Lange Str. 4-6",
    "sg:city":"Delmenhorst",
    "sg:phone":"+49 4221/13804",
    "sg:postcode":"27749",
    "sg:province":"Niedersachsen",
    "wof:name":"City-apotheke Inh. Johanna Timmermann",
    "wof:placetype":"venue"
},
  "geometry": {"coordinates":[8.625372,53.049831],"type":"Point"}
}