{
  "type": "Feature",
  "properties": {
    "iso:country":"DE",
    "sg:address":"Koblenzer Str. 106",
    "sg:city":"Mayen",
    "sg:phone":"+49 2651/48567",
    "sg:postcode":"56727",
    "sg:province":"Rheinland-Pfalz",
    "wof:name":"Restaurant Mc Donalds",
    "wof:placetype":"venue"
},
  "geometry": {"coordinates":[7.2368440628,50.3279151917],"type":"Point"}
}