{
  "type": "Feature",
  "properties": {
    "iso:country":"DE",
    "sg:address":"Am Vorort 8",
    "sg:city":"Bochum",
    "sg:phone":"+49 4923/4287691",
    "sg:postcode":"44894",
    "sg:province":"Nordrhein-Westfalen",
    "wof:name":"Ruhrland Stopfb\u00dcchsen-packung Gmbh",
    "wof:placetype":"venue"
},
  "geometry": {"coordinates":[7.295497,51.470577],"type":"Point"}
}