{
  "type": "Feature",
  "properties": {
    "iso:country":"DE",
    "sg:address":"Stockerhutweg 32",
    "sg:city":"Weiden",
    "sg:phone":"+49 961/23423",
    "sg:postcode":"92637",
    "sg:province":"Bayern",
    "wof:name":"Eduard Steinsd\u00f6rfer",
    "wof:placetype":"venue"
},
  "geometry": {"coordinates":[12.146066,49.675106],"type":"Point"}
}