{
  "type": "Feature",
  "properties": {
    "iso:country":"DE",
    "sg:address":"Stegerwaldstr. 15",
    "sg:city":"Frankfurt",
    "sg:phone":"+49 69/311721",
    "sg:postcode":"65929",
    "sg:province":"Hessen",
    "wof:name":"Franz Oberressl Elektroinstallation",
    "wof:placetype":"venue"
},
  "geometry": {"coordinates":[8.533651,50.110802],"type":"Point"}
}