{
  "type": "Feature",
  "properties": {
    "iso:country":"DE",
    "sg:address":"Steinhammerstr. 34",
    "sg:city":"Dortmund",
    "sg:phone":"+49 231/614779",
    "sg:postcode":"44379",
    "sg:province":"Nordrhein-Westfalen",
    "wof:name":"H. Sch\u00fcrmann Transportunternehmen Kg",
    "wof:placetype":"venue"
},
  "geometry": {"coordinates":[7.3781681061,51.5069541931],"type":"Point"}
}