{
  "type": "Feature",
  "properties": {
    "iso:country":"DE",
    "sg:address":"Kronenstr. 6",
    "sg:city":"Ettlingen",
    "sg:phone":"+49 7243/30023",
    "sg:postcode":"76275",
    "sg:province":"Baden-W\u00fcrttemberg",
    "wof:name":"Fips",
    "wof:placetype":"venue"
},
  "geometry": {"coordinates":[8.408464,48.941944],"type":"Point"}
}