{
  "type": "Feature",
  "properties": {
    "iso:country":"DE",
    "sg:address":"Rathaustra\u00dfe 9",
    "sg:city":"Gunningen",
    "sg:phone":"+49 7424/503688",
    "sg:postcode":"78594",
    "sg:province":"Baden-W\u00fcrttemberg",
    "wof:name":"G - P - G - Medical - Engineering - Medizintechnik",
    "wof:placetype":"venue"
},
  "geometry": {"coordinates":[8.699966,48.045158],"type":"Point"}
}