{
  "type": "Feature",
  "properties": {
    "iso:country":"DE",
    "sg:address":"Osterallee 198",
    "sg:city":"Flensburg",
    "sg:postcode":"24944",
    "sg:province":"Schleswig-Holstein",
    "wof:name":"Tennis-centrum-m\u00fcrwik Gmbh",
    "wof:placetype":"venue"
},
  "geometry": {"coordinates":[9.485854,54.804111],"type":"Point"}
}