{
  "type": "Feature",
  "properties": {
    "iso:country":"DE",
    "sg:address":"Erzgebirgische Str. 15",
    "sg:city":"Zwickau",
    "sg:phone":"+49 375/24757",
    "sg:postcode":"08056",
    "sg:province":"Sachsen",
    "wof:name":"Sven Metzner Verm\u00f6gensberater",
    "wof:placetype":"venue"
},
  "geometry": {"coordinates":[12.4833059311,50.7015266418],"type":"Point"}
}