{
  "type": "Feature",
  "properties": {
    "iso:country":"DE",
    "sg:address":"Klixstr. 13",
    "sg:city":"Berlin",
    "sg:phone":"+49 30/41702910",
    "sg:postcode":"13403",
    "sg:province":"Berlin",
    "wof:name":"Composite Food Linsler & Sieber Ohg",
    "wof:placetype":"venue"
},
  "geometry": {"coordinates":[13.3103866577,52.5705871582],"type":"Point"}
}