{
  "type": "Feature",
  "properties": {
    "iso:country":"DE",
    "sg:address":"B\u00f6hler Str. 21",
    "sg:city":"Dannstadt-Schauernheim",
    "sg:phone":"+49 6231/2412",
    "sg:postcode":"67125",
    "sg:province":"Rheinland-Pfalz",
    "wof:name":"G. Boida",
    "wof:placetype":"venue"
},
  "geometry": {"coordinates":[8.3188657761,49.4214668274],"type":"Point"}
}