{
  "type": "Feature",
  "properties": {
    "iso:country":"DE",
    "sg:address":"K\u00f6nig-Ludwig-Str. 6",
    "sg:city":"Wunstorf",
    "sg:postcode":"31515",
    "sg:province":"Niedersachsen",
    "wof:name":"Bauunternehmen H. Simon Gmbh",
    "wof:placetype":"venue"
},
  "geometry": {"coordinates":[9.446644,52.416992],"type":"Point"}
}