{
  "type": "Feature",
  "properties": {
    "iso:country":"DE",
    "sg:address":"Professor-Bier-Str. 95",
    "sg:city":"Bad Arolsen",
    "sg:phone":"+49 5691/2448",
    "sg:postcode":"34454",
    "sg:province":"Hessen",
    "wof:name":"G\u00fcnter Siefert",
    "wof:placetype":"venue"
},
  "geometry": {"coordinates":[9.007293,51.392128],"type":"Point"}
}