{
  "type": "Feature",
  "properties": {
    "iso:country":"DE",
    "sg:address":"Rieschstr. 8",
    "sg:city":"Frankenau",
    "sg:phone":"+49 6455/260",
    "sg:postcode":"35110",
    "sg:province":"Hessen",
    "wof:name":"Karl Werner",
    "wof:placetype":"venue"
},
  "geometry": {"coordinates":[8.9349298477,51.0916213989],"type":"Point"}
}