{
  "type": "Feature",
  "properties": {
    "iso:country":"DE",
    "sg:address":"Rethelstr. 41",
    "sg:city":"D\u00fcsseldorf",
    "sg:phone":"+49 211/662802",
    "sg:postcode":"40237",
    "sg:province":"Nordrhein-Westfalen",
    "wof:name":"Helmut Flatten Rechtsanwalt",
    "wof:placetype":"venue"
},
  "geometry": {"coordinates":[6.7980418205,51.2325286865],"type":"Point"}
}