{
  "type": "Feature",
  "properties": {
    "iso:country":"DE",
    "sg:city":"m\u00fcnchen",
    "sg:postcode":"85521",
    "sg:province":"Bayern",
    "wof:name":"Mtw-kundendienst Gmbh",
    "wof:placetype":"venue"
},
  "geometry": {"coordinates":[11.66213,48.063606],"type":"Point"}
}