{
  "type": "Feature",
  "properties": {
    "iso:country":"DE",
    "sg:city":"Berlin",
    "sg:postcode":"10179",
    "sg:province":"Berlin",
    "wof:name":"Www.boxen.com, Das Unabh\u00e4ngige Boxsportportal",
    "wof:placetype":"venue"
},
  "geometry": {"coordinates":[13.41559,52.512939],"type":"Point"}
}