{
  "type": "Feature",
  "properties": {
    "iso:country":"DE",
    "sg:address":"Dorfstr. 27",
    "sg:city":"Laage",
    "sg:phone":"+49 38459/36631",
    "sg:postcode":"18299",
    "sg:province":"Mecklenburg-Vorpommern",
    "wof:name":"Hlb Baumaschinen",
    "wof:placetype":"venue"
},
  "geometry": {"coordinates":[12.244488,53.887527],"type":"Point"}
}