{
  "type": "Feature",
  "properties": {
    "iso:country":"DE",
    "sg:address":"Merzhauser Str. 151",
    "sg:city":"Freiburg",
    "sg:phone":"+49 761/4570070",
    "sg:postcode":"79100",
    "sg:province":"Baden-W\u00fcrttemberg",
    "wof:name":"H. Sander Steuerberater",
    "wof:placetype":"venue"
},
  "geometry": {"coordinates":[7.8301310539,47.9778327942],"type":"Point"}
}