{
  "type": "Feature",
  "properties": {
    "iso:country":"DE",
    "sg:address":"Kreuzweg 6",
    "sg:city":"Hamburg",
    "sg:phone":"+49 40/2803606",
    "sg:postcode":"20099",
    "sg:province":"Hamburg",
    "wof:name":"Tusculum",
    "wof:placetype":"venue"
},
  "geometry": {"coordinates":[10.0135507584,53.5527610779],"type":"Point"}
}