{
  "type": "Feature",
  "properties": {
    "iso:country":"DE",
    "sg:address":"Schwarzbach 40 A",
    "sg:city":"Wuppertal",
    "sg:phone":"+49 202/641099",
    "sg:postcode":"42277",
    "sg:province":"Nordrhein-Westfalen",
    "wof:name":"Friedrich Kremer Jr. Inh.hans Kremer",
    "wof:placetype":"venue"
},
  "geometry": {"coordinates":[7.224808,51.277626],"type":"Point"}
}