{
  "type": "Feature",
  "properties": {
    "iso:country":"DE",
    "sg:address":"Georgstr. 37",
    "sg:city":"Meiningen",
    "sg:phone":"+49 3693/2635",
    "sg:postcode":"98617",
    "sg:province":"Th\u00fcringen",
    "wof:name":"Neumann",
    "wof:placetype":"venue"
},
  "geometry": {"coordinates":[10.415448,50.568157],"type":"Point"}
}