{
  "type": "Feature",
  "properties": {
    "iso:country":"DE",
    "sg:address":"Wilhelm-Stein-Weg 15",
    "sg:city":"Hamburg",
    "sg:phone":"+49 40/5382069",
    "sg:postcode":"22339",
    "sg:province":"Hamburg",
    "wof:name":"Horst Casten",
    "wof:placetype":"venue"
},
  "geometry": {"coordinates":[10.033157,53.646423],"type":"Point"}
}