{
  "type": "Feature",
  "properties": {
    "iso:country":"DE",
    "sg:address":"Von-Hessing-Str. 2",
    "sg:city":"Bad Kissingen",
    "sg:postcode":"97688",
    "sg:province":"Bayern",
    "wof:name":"Bau Art-gesellschaft F\u00fcr Anspruchsvolle Lebensr\u00e4ume Mbh",
    "wof:placetype":"venue"
},
  "geometry": {"coordinates":[10.078989,50.199898],"type":"Point"}
}