{
  "type": "Feature",
  "properties": {
    "iso:country":"DE",
    "sg:address":"Am G\u00fcterbahnhof 2 A",
    "sg:city":"Burgdorf",
    "sg:phone":"+49 5136/895277",
    "sg:postcode":"31303",
    "sg:province":"Niedersachsen",
    "wof:name":"Unlimited Licht Gmbh",
    "wof:placetype":"venue"
},
  "geometry": {"coordinates":[10.002903,52.449997],"type":"Point"}
}