{
  "type": "Feature",
  "properties": {
    "iso:country":"DE",
    "sg:address":"Am Jagdhaus 6",
    "sg:city":"Tabarz",
    "sg:phone":"+49 36259/58148",
    "sg:postcode":"99891",
    "sg:province":"Th\u00fcringen",
    "wof:name":"Siegfried Hildenhagen",
    "wof:placetype":"venue"
},
  "geometry": {"coordinates":[10.4800243378,50.8848228455],"type":"Point"}
}