{
  "type": "Feature",
  "properties": {
    "iso:country":"DE",
    "sg:address":"Schillerstr. 1",
    "sg:city":"Strausberg",
    "sg:phone":"+49 3341/311487",
    "sg:postcode":"15344",
    "sg:province":"Brandenburg",
    "wof:name":"Manfred Horn Ingenieur",
    "wof:placetype":"venue"
},
  "geometry": {"coordinates":[13.8689870834,52.5650215149],"type":"Point"}
}