{
  "type": "Feature",
  "properties": {
    "iso:country":"DE",
    "sg:address":"Schulstr. 9",
    "sg:city":"M\u00fcnchen",
    "sg:phone":"+49 89/165756",
    "sg:postcode":"80634",
    "sg:province":"Bayern",
    "wof:name":"La Bilancia Tr\u00fcffelhandels- Gmbh",
    "wof:placetype":"venue"
},
  "geometry": {"coordinates":[11.5342903137,48.1513900757],"type":"Point"}
}