{
  "type": "Feature",
  "properties": {
    "iso:country":"DE",
    "sg:address":"Friedensstr. 6",
    "sg:city":"Heidenau",
    "sg:phone":"+49 3529/514483",
    "sg:postcode":"01809",
    "sg:province":"Sachsen",
    "wof:name":"W. Klemmt",
    "wof:placetype":"venue"
},
  "geometry": {"coordinates":[13.86598,50.983669],"type":"Point"}
}