{
  "type": "Feature",
  "properties": {
    "iso:country":"DE",
    "sg:address":"Bahnhofstr. 38",
    "sg:city":"Rag\u00f6sen",
    "sg:phone":"+49 33846/41273",
    "sg:postcode":"14806",
    "sg:province":"Brandenburg",
    "wof:name":"B. Kn\u00f6nagel",
    "wof:placetype":"venue"
},
  "geometry": {"coordinates":[12.582605,52.237022],"type":"Point"}
}