{
  "type": "Feature",
  "properties": {
    "iso:country":"DE",
    "sg:address":"Rechte Brandstr. 15",
    "sg:city":"Augsburg",
    "sg:phone":"+49 821/707233",
    "sg:postcode":"86167",
    "sg:province":"Bayern",
    "wof:name":"Hans Widmann Metzgerei Gmbh",
    "wof:placetype":"venue"
},
  "geometry": {"coordinates":[10.917640686,48.3883018494],"type":"Point"}
}