{
  "type": "Feature",
  "properties": {
    "iso:country":"DE",
    "sg:address":"Timpestr. 8-10",
    "sg:city":"Essen",
    "sg:phone":"+49 201/380725",
    "sg:postcode":"45329",
    "sg:province":"Nordrhein-Westfalen",
    "wof:name":"Messebau Marke Gmbh",
    "wof:placetype":"venue"
},
  "geometry": {"coordinates":[7.009525,51.523697],"type":"Point"}
}