{
  "type": "Feature",
  "properties": {
    "iso:country":"DE",
    "sg:address":"Dinkelbauerweg 6",
    "sg:city":"Dinkelsb\u00fchl",
    "sg:phone":"+49 9851/2576",
    "sg:postcode":"91550",
    "sg:province":"Bayern",
    "wof:name":"Hans H\u00fcbner Steuerberater",
    "wof:placetype":"venue"
},
  "geometry": {"coordinates":[10.3229837418,49.0635643005],"type":"Point"}
}