{
  "type": "Feature",
  "properties": {
    "iso:country":"DE",
    "sg:address":"Leu\u00dflerstr. 4",
    "sg:city":"Karlsruhe",
    "sg:phone":"+49 721/405405",
    "sg:postcode":"76227",
    "sg:province":"Baden-W\u00fcrttemberg",
    "wof:name":"Auerhahn-apotheke",
    "wof:placetype":"venue"
},
  "geometry": {"coordinates":[8.460645,48.993],"type":"Point"}
}