{
  "type": "Feature",
  "properties": {
    "iso:country":"DE",
    "sg:address":"Hirschenweg 17",
    "sg:city":"Kirchseeon",
    "sg:phone":"+49 8091/56460",
    "sg:postcode":"85614",
    "sg:province":"Bayern",
    "wof:name":"Steuerberatungsgesellschaft Maximilian R\u00f6ck Dipl. Kfm.",
    "wof:placetype":"venue"
},
  "geometry": {"coordinates":[11.8696250916,48.081867218],"type":"Point"}
}