{
  "type": "Feature",
  "properties": {
    "iso:country":"DE",
    "sg:address":"Hinter den H\u00f6fen 7",
    "sg:city":"Bad M\u00fcnder",
    "sg:phone":"+49 5151/53553",
    "sg:postcode":"31848",
    "sg:province":"Niedersachsen",
    "wof:name":"Siegfried S\u00f6chting",
    "wof:placetype":"venue"
},
  "geometry": {"coordinates":[9.4555006027,52.1421737671],"type":"Point"}
}