{
  "type": "Feature",
  "properties": {
    "iso:country":"DE",
    "sg:address":"Berliner Str. 23",
    "sg:city":"K\u00f6nigslutter",
    "sg:phone":"+49 5353/8513",
    "sg:postcode":"38154",
    "sg:province":"Niedersachsen",
    "wof:name":"Hermann Theuerkauf",
    "wof:placetype":"venue"
},
  "geometry": {"coordinates":[10.818135,52.250126],"type":"Point"}
}