{
  "type": "Feature",
  "properties": {
    "iso:country":"DE",
    "sg:address":"Wandsbeker K\u00f6nigstr. 11",
    "sg:city":"Hamburg",
    "sg:phone":"+49 40/6524566",
    "sg:postcode":"22041",
    "sg:province":"Hamburg",
    "wof:name":"Gerhart Heick",
    "wof:placetype":"venue"
},
  "geometry": {"coordinates":[10.0639562607,53.5722236633],"type":"Point"}
}