{
  "type": "Feature",
  "properties": {
    "iso:country":"DE",
    "sg:address":"Hauptstr. 17",
    "sg:city":"Frickenhausen",
    "sg:phone":"+49 9331/651",
    "sg:postcode":"97252",
    "sg:province":"Bayern",
    "wof:name":"Restaurant Ehrbar Fr\u00e4nkische Weinstube",
    "wof:placetype":"venue"
},
  "geometry": {"coordinates":[10.0942344666,49.6708183289],"type":"Point"}
}