{
  "type": "Feature",
  "properties": {
    "iso:country":"DE",
    "sg:address":"Oesselser Str. 42",
    "sg:city":"Laatzen",
    "sg:phone":"+49 5102/894",
    "sg:postcode":"30880",
    "sg:province":"Niedersachsen",
    "wof:name":"H\u00e4mmerle Produktions Gmbh",
    "wof:placetype":"venue"
},
  "geometry": {"coordinates":[9.852101326,52.2744369507],"type":"Point"}
}