{
  "type": "Feature",
  "properties": {
    "iso:country":"DE",
    "sg:address":"Hornissenweg 2",
    "sg:city":"Augsburg",
    "sg:phone":"+49 821/91160",
    "sg:postcode":"86199",
    "sg:province":"Bayern",
    "wof:name":"Otto Heimerl",
    "wof:placetype":"venue"
},
  "geometry": {"coordinates":[10.857971,48.311199],"type":"Point"}
}