{
  "type": "Feature",
  "properties": {
    "iso:country":"DE",
    "sg:address":"Imberstr. 8",
    "sg:city":"Karlsruhe",
    "sg:phone":"+49 721/405132",
    "sg:postcode":"76227",
    "sg:province":"Baden-W\u00fcrttemberg",
    "wof:name":"Gunter Schorle",
    "wof:placetype":"venue"
},
  "geometry": {"coordinates":[8.469909,48.995495],"type":"Point"}
}