{
  "type": "Feature",
  "properties": {
    "iso:country":"DE",
    "sg:address":"Brunnenstr. 2",
    "sg:city":"Dorfprozelten",
    "sg:phone":"+49 9392/6317",
    "sg:postcode":"97904",
    "sg:province":"Bayern",
    "wof:name":"Hermann Umscheid",
    "wof:placetype":"venue"
},
  "geometry": {"coordinates":[9.3776941299,49.7791671753],"type":"Point"}
}