{
  "type": "Feature",
  "properties": {
    "iso:country":"DE",
    "sg:address":"Bahnhofstr. 7",
    "sg:city":"Steinwenden",
    "sg:phone":"+49 6371/50682",
    "sg:postcode":"66879",
    "sg:province":"Rheinland-Pfalz",
    "wof:name":"Zimmer Hochbau-tiefbau Gmbh",
    "wof:placetype":"venue"
},
  "geometry": {"coordinates":[7.5243430138,49.454460144],"type":"Point"}
}