{
  "type": "Feature",
  "properties": {
    "iso:country":"DE",
    "sg:address":"Langeneck 10",
    "sg:city":"Lenggries",
    "sg:phone":"+49 8042/2152",
    "sg:postcode":"83661",
    "sg:province":"Bayern",
    "wof:name":"Franz Baumgartner",
    "wof:placetype":"venue"
},
  "geometry": {"coordinates":[11.5811729431,47.6512451172],"type":"Point"}
}