{
  "type": "Feature",
  "properties": {
    "iso:country":"DE",
    "sg:address":"Steinbachstr. 53",
    "sg:city":"Aachen",
    "sg:phone":"+49 241/807390",
    "sg:postcode":"52074",
    "sg:province":"Nordrhein-Westfalen",
    "wof:name":"Werkzeugmaschinenlabor Der Rwth Aachen Lehrstuhl F.",
    "wof:placetype":"venue"
},
  "geometry": {"coordinates":[6.0461177826,50.7839126587],"type":"Point"}
}