{
  "type": "Feature",
  "properties": {
    "iso:country":"DE",
    "sg:address":"Moltkestr. 13",
    "sg:city":"Altenstadt",
    "sg:phone":"+49 8337/75301",
    "sg:postcode":"89281",
    "sg:province":"Bayern",
    "wof:name":"Robe Reinigungsmaschinen Handels - Gmbh",
    "wof:placetype":"venue"
},
  "geometry": {"coordinates":[10.1205348969,48.164806366],"type":"Point"}
}