{
  "type": "Feature",
  "properties": {
    "iso:country":"DE",
    "sg:address":"Bruno-Apitz-Strasse 31",
    "sg:city":"Weimar",
    "sg:phone":"+49 3643/410155",
    "sg:postcode":"99427",
    "sg:province":"Th\u00fcringen",
    "wof:name":"Die Fischerin",
    "wof:placetype":"venue"
},
  "geometry": {"coordinates":[11.333749,51.01479],"type":"Point"}
}