{
  "type": "Feature",
  "properties": {
    "iso:country":"DE",
    "sg:address":"Woltorfer Str. 118",
    "sg:city":"Peine",
    "sg:phone":"+49 5171/400219",
    "sg:postcode":"31224",
    "sg:province":"Niedersachsen",
    "wof:name":"Aircooperation Geb\u00e4udetechnik Gmbh",
    "wof:placetype":"venue"
},
  "geometry": {"coordinates":[10.2626237869,52.3156776428],"type":"Point"}
}