{
  "type": "Feature",
  "properties": {
    "iso:country":"DE",
    "sg:address":"Uelzener Str. 18",
    "sg:city":"Bienenb\u00fcttel",
    "sg:phone":"+49 5823/1466",
    "sg:postcode":"29553",
    "sg:province":"Niedersachsen",
    "wof:name":"Zur Alten Wasserm\u00fchle",
    "wof:placetype":"venue"
},
  "geometry": {"coordinates":[10.4921913147,53.139957428],"type":"Point"}
}