{
  "type": "Feature",
  "properties": {
    "iso:country":"DE",
    "sg:address":"Steinweg 55",
    "sg:city":"Gifhorn",
    "sg:phone":"+49 5371/53802",
    "sg:postcode":"38518",
    "sg:province":"Niedersachsen",
    "wof:name":"Sport Gigla",
    "wof:placetype":"venue"
},
  "geometry": {"coordinates":[10.547089,52.484356],"type":"Point"}
}