{
  "type": "Feature",
  "properties": {
    "iso:country":"DE",
    "sg:address":"Hagener Str. 15",
    "sg:city":"Gevelsberg",
    "sg:phone":"+49 2332/83039",
    "sg:postcode":"58285",
    "sg:province":"Nordrhein-Westfalen",
    "wof:name":"Ralf Brandenstein",
    "wof:placetype":"venue"
},
  "geometry": {"coordinates":[7.344504,51.321075],"type":"Point"}
}