{
  "type": "Feature",
  "properties": {
    "iso:country":"DE",
    "sg:address":"Kirschweg",
    "sg:city":"Magdeburg",
    "sg:phone":"+49 391/616366",
    "sg:postcode":"39118",
    "sg:province":"Sachsen-Anhalt",
    "wof:name":"Freibad S\u00fcd",
    "wof:placetype":"venue"
},
  "geometry": {"coordinates":[11.6034202576,52.0958251953],"type":"Point"}
}