{
  "type": "Feature",
  "properties": {
    "iso:country":"DE",
    "sg:address":"L\u00f6\u00dfnitzer Str. 45",
    "sg:city":"Reinsdorf",
    "sg:phone":"+49 375/295448",
    "sg:postcode":"08141",
    "sg:province":"Sachsen",
    "wof:name":"Drogerie Georgie Inh. Christine Barthel",
    "wof:placetype":"venue"
},
  "geometry": {"coordinates":[12.539151,50.694088],"type":"Point"}
}