{
  "type": "Feature",
  "properties": {
    "iso:country":"DE",
    "sg:address":"Am G\u00e4xwald 19",
    "sg:city":"Herxheim",
    "sg:phone":"+49 7276/919001",
    "sg:postcode":"76863",
    "sg:province":"Rheinland-Pfalz",
    "wof:name":"Holzh\u00e4user, Dachdeckerarbeiten, Asbestsanierung,",
    "wof:placetype":"venue"
},
  "geometry": {"coordinates":[8.237062,49.140507],"type":"Point"}
}