{
  "type": "Feature",
  "properties": {
    "iso:country":"DE",
    "sg:address":"Weinbergstr. 4",
    "sg:city":"Bensheim",
    "sg:phone":"+49 6251/76355",
    "sg:postcode":"64625",
    "sg:province":"Hessen",
    "wof:name":"Ulrich Meier Ingenieur",
    "wof:placetype":"venue"
},
  "geometry": {"coordinates":[8.6237421036,49.7046813965],"type":"Point"}
}