{
  "type": "Feature",
  "properties": {
    "iso:country":"DE",
    "sg:address":"Lahnstr. 27",
    "sg:city":"Gro\u00df-Gerau",
    "sg:phone":"+49 6152/54116",
    "sg:postcode":"64521",
    "sg:province":"Hessen",
    "wof:name":"Harald Maske Elektroinstallation",
    "wof:placetype":"venue"
},
  "geometry": {"coordinates":[8.483166,49.880947],"type":"Point"}
}