{
  "type": "Feature",
  "properties": {
    "iso:country":"DE",
    "sg:address":"K\u00f6nigstr. 7",
    "sg:city":"Dresden",
    "sg:phone":"+49 351/81720",
    "sg:postcode":"01097",
    "sg:province":"Sachsen",
    "wof:name":"Bhw Bausparkasse Ag",
    "wof:placetype":"venue"
},
  "geometry": {"coordinates":[13.741494,51.061291],"type":"Point"}
}