{
  "type": "Feature",
  "properties": {
    "iso:country":"DE",
    "sg:address":"Zur Alten Zollbr\u00fccke 6",
    "sg:city":"Sonthofen",
    "sg:phone":"+49 8321/2989",
    "sg:postcode":"87527",
    "sg:province":"Bayern",
    "wof:name":"Karlheinz Hegenbarth",
    "wof:placetype":"venue"
},
  "geometry": {"coordinates":[10.2611646652,47.5230293274],"type":"Point"}
}