{
  "type": "Feature",
  "properties": {
    "iso:country":"DE",
    "sg:address":"Albrecht-D\u00fcrer-Str. 35",
    "sg:city":"H\u00f6chstadt",
    "sg:phone":"+49 9193/3593",
    "sg:postcode":"91315",
    "sg:province":"Bayern",
    "wof:name":"Josef Staudigel",
    "wof:placetype":"venue"
},
  "geometry": {"coordinates":[10.816911,49.715435],"type":"Point"}
}