{
  "type": "Feature",
  "properties": {
    "iso:country":"DE",
    "sg:address":"Maybachstr. 2",
    "sg:city":"Riederich",
    "sg:phone":"+49 7123/34905",
    "sg:postcode":"72585",
    "sg:province":"Baden-W\u00fcrttemberg",
    "wof:name":"J. Etter Mech. Werkstatt",
    "wof:placetype":"venue"
},
  "geometry": {"coordinates":[9.259343,48.553844],"type":"Point"}
}