{
  "type": "Feature",
  "properties": {
    "iso:country":"DE",
    "sg:address":"Bleichstr. 6",
    "sg:city":"Hagen",
    "sg:phone":"+49 2331/338358",
    "sg:postcode":"58089",
    "sg:province":"Nordrhein-Westfalen",
    "wof:name":"Cicciu Gmbh",
    "wof:placetype":"venue"
},
  "geometry": {"coordinates":[7.4592480659,51.3539810181],"type":"Point"}
}