{
  "type": "Feature",
  "properties": {
    "iso:country":"DE",
    "sg:address":"Hofheimer Str. 7",
    "sg:city":"Schonungen",
    "sg:phone":"+49 9721/59283",
    "sg:postcode":"97453",
    "sg:province":"Bayern",
    "wof:name":"Herbert Wirth",
    "wof:placetype":"venue"
},
  "geometry": {"coordinates":[10.304273,50.052216],"type":"Point"}
}