{
  "type": "Feature",
  "properties": {
    "iso:country":"DE",
    "sg:address":"Bernstorffstr. 161",
    "sg:city":"Hamburg",
    "sg:phone":"+49 40/371313",
    "sg:postcode":"22767",
    "sg:province":"Hamburg",
    "wof:name":"Karl-heinz Imbeck Immobilienmakler",
    "wof:placetype":"venue"
},
  "geometry": {"coordinates":[9.959397316,53.5599555969],"type":"Point"}
}