{
  "type": "Feature",
  "properties": {
    "iso:country":"DE",
    "sg:address":"Breitmatte 50",
    "sg:city":"M\u00fcnstertal",
    "sg:phone":"+49 4976/361404",
    "sg:postcode":"79244",
    "sg:province":"Baden-W\u00fcrttemberg",
    "wof:name":"Hubert Pfefferle",
    "wof:placetype":"venue"
},
  "geometry": {"coordinates":[7.775932,47.858994],"type":"Point"}
}