{
  "type": "Feature",
  "properties": {
    "iso:country":"DE",
    "sg:address":"Georgenstr. 1",
    "sg:city":"Gersthofen",
    "sg:phone":"+49 821/2090550",
    "sg:postcode":"86368",
    "sg:province":"Bayern",
    "wof:name":"Gs Steuerungstechnik Gmbh",
    "wof:placetype":"venue"
},
  "geometry": {"coordinates":[10.8326711655,48.4224433899],"type":"Point"}
}