{
  "type": "Feature",
  "properties": {
    "iso:country":"DE",
    "sg:address":"Friedhofsdamm 8",
    "sg:city":"Preetz",
    "sg:phone":"+49 4342/3736",
    "sg:postcode":"24211",
    "sg:province":"Schleswig-Holstein",
    "wof:name":"Heinrich Und Peter Puls Grabdenkm\u00e4ler",
    "wof:placetype":"venue"
},
  "geometry": {"coordinates":[10.2767429352,54.2306671143],"type":"Point"}
}