{
  "type": "Feature",
  "properties": {
    "iso:country":"DE",
    "sg:address":"Saulgauer Str. 16",
    "sg:city":"Mittelbiberach",
    "sg:phone":"+49 7351/28835",
    "sg:postcode":"88441",
    "sg:province":"Baden-W\u00fcrttemberg",
    "wof:name":"Franz Popp",
    "wof:placetype":"venue"
},
  "geometry": {"coordinates":[9.759028,48.065254],"type":"Point"}
}