{
  "type": "Feature",
  "properties": {
    "iso:country":"DE",
    "sg:address":"Soonwaldstr. 13",
    "sg:city":"Monzingen",
    "sg:phone":"+49 6751/2537",
    "sg:postcode":"55569",
    "sg:province":"Rheinland-Pfalz",
    "wof:name":"Lauf",
    "wof:placetype":"venue"
},
  "geometry": {"coordinates":[7.5887708664,49.8001747131],"type":"Point"}
}