{
  "type": "Feature",
  "properties": {
    "iso:country":"DE",
    "sg:address":"Hauptstr. 13",
    "sg:city":"Schonach",
    "sg:phone":"+49 7722/96400",
    "sg:postcode":"78136",
    "sg:province":"Baden-W\u00fcrttemberg",
    "wof:name":"Strunskus",
    "wof:placetype":"venue"
},
  "geometry": {"coordinates":[8.240445137,48.147644043],"type":"Point"}
}