{
  "type": "Feature",
  "properties": {
    "iso:country":"DE",
    "sg:address":"Dresdener Str. 3",
    "sg:city":"Sohland",
    "sg:phone":"+49 35936/37072",
    "sg:postcode":"02689",
    "sg:province":"Sachsen",
    "wof:name":"R. Herold",
    "wof:placetype":"venue"
},
  "geometry": {"coordinates":[14.3816566467,51.0538291931],"type":"Point"}
}