{
  "type": "Feature",
  "properties": {
    "iso:country":"DE",
    "sg:address":"Wiesenstr. 84",
    "sg:city":"N\u00fcrnberg",
    "sg:phone":"+49 911/445871",
    "sg:postcode":"90459",
    "sg:province":"Bayern",
    "wof:name":"Dr. Theodor Engelhardt",
    "wof:placetype":"venue"
},
  "geometry": {"coordinates":[11.076611,49.440449],"type":"Point"}
}