{
  "type": "Feature",
  "properties": {
    "iso:country":"DE",
    "sg:address":"M\u00fchlthaler Weg 1",
    "sg:city":"Gauting",
    "sg:phone":"+49 89/8500888",
    "sg:postcode":"82131",
    "sg:province":"Bayern",
    "wof:name":"G. Nu\u00dfer",
    "wof:placetype":"venue"
},
  "geometry": {"coordinates":[11.33213,48.04287],"type":"Point"}
}