{
  "type": "Feature",
  "properties": {
    "iso:country":"DE",
    "sg:address":"Alte Frankfurter Str. 1",
    "sg:city":"Hachenburg",
    "sg:phone":"+49 2662/7583",
    "sg:postcode":"57627",
    "sg:province":"Rheinland-Pfalz",
    "wof:name":"Hotel Willi Hormann",
    "wof:placetype":"venue"
},
  "geometry": {"coordinates":[7.8316969872,50.6592025757],"type":"Point"}
}