{
  "type": "Feature",
  "properties": {
    "iso:country":"DE",
    "sg:address":"Neubr\u00fcckenstr. 72",
    "sg:city":"M\u00fcnster",
    "sg:phone":"+49 251/44242",
    "sg:postcode":"48143",
    "sg:province":"Nordrhein-Westfalen",
    "wof:name":"Hubert Kleyb\u00f6cker",
    "wof:placetype":"venue"
},
  "geometry": {"coordinates":[7.6280460358,51.9641723633],"type":"Point"}
}