{
  "type": "Feature",
  "properties": {
    "iso:country":"DE",
    "sg:address":"Im Schlatt 7",
    "sg:city":"Lohne",
    "sg:postcode":"49393",
    "sg:province":"Niedersachsen",
    "wof:name":"Llw Lohner Lackierwerk Gmbh",
    "wof:placetype":"venue"
},
  "geometry": {"coordinates":[8.2063512802,52.6657333374],"type":"Point"}
}