{
  "type": "Feature",
  "properties": {
    "iso:country":"DE",
    "sg:address":"Beethovenstr. 11",
    "sg:city":"Obertshausen",
    "sg:phone":"+49 6104/44788",
    "sg:postcode":"63179",
    "sg:province":"Hessen",
    "wof:name":"Wiegand",
    "wof:placetype":"venue"
},
  "geometry": {"coordinates":[8.8455657959,50.0700416565],"type":"Point"}
}