{
  "type": "Feature",
  "properties": {
    "iso:country":"DE",
    "sg:address":"Weingartenstr. 66",
    "sg:city":"Offenburg",
    "sg:phone":"+49 781/34973",
    "sg:postcode":"77654",
    "sg:province":"Baden-W\u00fcrttemberg",
    "wof:name":"Weingut Von U. Zu Frankenstein",
    "wof:placetype":"venue"
},
  "geometry": {"coordinates":[7.9641809464,48.4695663452],"type":"Point"}
}