{
  "type": "Feature",
  "properties": {
    "iso:country":"DE",
    "sg:address":"Schwarzburger Str. 45",
    "sg:city":"Neuhaus",
    "sg:phone":"+49 3679/722730",
    "sg:postcode":"98724",
    "sg:province":"Th\u00fcringen",
    "wof:name":"Johannes Michel Ingenieur",
    "wof:placetype":"venue"
},
  "geometry": {"coordinates":[11.1399707794,50.5130233765],"type":"Point"}
}