{
  "type": "Feature",
  "properties": {
    "iso:country":"DE",
    "sg:address":"Oelser Str. 43",
    "sg:city":"Bonn",
    "sg:phone":"+49 228/662124",
    "sg:postcode":"53117",
    "sg:province":"Nordrhein-Westfalen",
    "wof:name":"Trouw Ingenieurb\u00fcro",
    "wof:placetype":"venue"
},
  "geometry": {"coordinates":[7.0402698517,50.7545661926],"type":"Point"}
}