{
  "type": "Feature",
  "properties": {
    "iso:country":"DE",
    "sg:address":"Bertholdstr. 24",
    "sg:city":"Pforzheim",
    "sg:phone":"+49 7231/101648",
    "sg:postcode":"75177",
    "sg:province":"Baden-W\u00fcrttemberg",
    "wof:name":"Hugo Kraus",
    "wof:placetype":"venue"
},
  "geometry": {"coordinates":[8.705912,48.896152],"type":"Point"}
}