{
  "type": "Feature",
  "properties": {
    "iso:country":"DE",
    "sg:address":"Kurze Str. 41",
    "sg:city":"Grevenbroich",
    "sg:phone":"+49 2182/2337",
    "sg:postcode":"41516",
    "sg:province":"Nordrhein-Westfalen",
    "wof:name":"Kath. Pfarramt St. Clemens",
    "wof:placetype":"venue"
},
  "geometry": {"coordinates":[6.622964859,51.1279754639],"type":"Point"}
}