{
  "type": "Feature",
  "properties": {
    "iso:country":"DE",
    "sg:address":"Paracelsusweg 2",
    "sg:city":"Klingenthal",
    "sg:phone":"+49 37467/22406",
    "sg:postcode":"08248",
    "sg:province":"Sachsen",
    "wof:name":"Lothar Lucas",
    "wof:placetype":"venue"
},
  "geometry": {"coordinates":[12.48432,50.385269],"type":"Point"}
}