{
  "type": "Feature",
  "properties": {
    "iso:country":"DE",
    "sg:address":"Haingeraidestr. 1",
    "sg:city":"Eu\u00dferthal",
    "sg:phone":"+49 6345/919040",
    "sg:postcode":"76857",
    "sg:province":"Rheinland-Pfalz",
    "wof:name":"Sch\u00fcler Gmbh",
    "wof:placetype":"venue"
},
  "geometry": {"coordinates":[7.9769048691,49.2399253845],"type":"Point"}
}