{
  "type": "Feature",
  "properties": {
    "iso:country":"DE",
    "sg:address":"Kreutstr. 2",
    "sg:city":"Gro\u00dfweil",
    "sg:phone":"+49 8851/5915",
    "sg:postcode":"82439",
    "sg:province":"Bayern",
    "wof:name":"Ch. Rainer",
    "wof:placetype":"venue"
},
  "geometry": {"coordinates":[11.3027944565,47.6750106812],"type":"Point"}
}