{
  "type": "Feature",
  "properties": {
    "iso:country":"DE",
    "sg:address":"Albert-Einstein-Str 6",
    "sg:city":"Landsberg",
    "sg:phone":"+49 8191/21100",
    "sg:postcode":"86899",
    "sg:province":"Bayern",
    "wof:name":"Renosan Gmbh",
    "wof:placetype":"venue"
},
  "geometry": {"coordinates":[10.857185,48.068802],"type":"Point"}
}