{
  "type": "Feature",
  "properties": {
    "iso:country":"DE",
    "sg:address":"Wittenbergener Weg 2g",
    "sg:city":"Hamburg",
    "sg:phone":"+49 40/815340",
    "sg:postcode":"22559",
    "sg:province":"Hamburg",
    "wof:name":"Wolfgang Reiniger Architekt",
    "wof:placetype":"venue"
},
  "geometry": {"coordinates":[9.757829,53.580486],"type":"Point"}
}