{
  "type": "Feature",
  "properties": {
    "iso:country":"DE",
    "sg:address":"Sch\u00fctzenstr. 88",
    "sg:city":"Bad Neuenahr-Ahrweiler",
    "sg:phone":"+49 2641/35247",
    "sg:postcode":"53474",
    "sg:province":"Rheinland-Pfalz",
    "wof:name":"Brigitte R\u00f6nn Krankengymnastin",
    "wof:placetype":"venue"
},
  "geometry": {"coordinates":[7.1094,50.542278],"type":"Point"}
}