{
  "type": "Feature",
  "properties": {
    "iso:country":"DE",
    "sg:address":"Schilling-von-Canstatt-Str. 1",
    "sg:city":"Karlsruhe",
    "sg:phone":"+49 721/473132",
    "sg:postcode":"76228",
    "sg:province":"Baden-W\u00fcrttemberg",
    "wof:name":"Kupferkanne",
    "wof:placetype":"venue"
},
  "geometry": {"coordinates":[8.471616745,48.9652328491],"type":"Point"}
}