{
  "type": "Feature",
  "properties": {
    "iso:country":"DE",
    "sg:address":"S\u00fcringstr. 3",
    "sg:city":"Coesfeld",
    "sg:phone":"+49 2541/3660",
    "sg:postcode":"48653",
    "sg:province":"Nordrhein-Westfalen",
    "wof:name":"Leder Jannig-terwey Gmbh",
    "wof:placetype":"venue"
},
  "geometry": {"coordinates":[7.166299,51.944874],"type":"Point"}
}