{
  "type": "Feature",
  "properties": {
    "iso:country":"DE",
    "sg:address":"Hirschkamp 14",
    "sg:city":"Norderstedt",
    "sg:phone":"+49 40/5223088",
    "sg:postcode":"22846",
    "sg:province":"Schleswig-Holstein",
    "wof:name":"Kahlsdorf & Partner",
    "wof:placetype":"venue"
},
  "geometry": {"coordinates":[9.997526,53.716061],"type":"Point"}
}