{
  "type": "Feature",
  "properties": {
    "iso:country":"DE",
    "sg:address":"Bunsenstr. 6",
    "sg:city":"Ingolstadt",
    "sg:phone":"+49 841/6350",
    "sg:postcode":"85053",
    "sg:province":"Bayern",
    "wof:name":"Wack-chemie Dr. O.k. Gmbh",
    "wof:placetype":"venue"
},
  "geometry": {"coordinates":[11.4730005264,48.7417068481],"type":"Point"}
}