{
  "type": "Feature",
  "properties": {
    "iso:country":"DE",
    "sg:address":"An der Papierm\u00fchle 11",
    "sg:city":"Memmingen",
    "sg:phone":"+49 8331/92220",
    "sg:postcode":"87700",
    "sg:province":"Bayern",
    "wof:name":"Otra S\u00fcd Gmbh",
    "wof:placetype":"venue"
},
  "geometry": {"coordinates":[10.1975946426,47.9996681213],"type":"Point"}
}