{
  "type": "Feature",
  "properties": {
    "iso:country":"DE",
    "sg:address":"Brucknerstr. 16",
    "sg:city":"L\u00fcbbecke",
    "sg:phone":"+49 5741/9514",
    "sg:postcode":"32312",
    "sg:province":"Nordrhein-Westfalen",
    "wof:name":"Heinrich Grothe Masseur",
    "wof:placetype":"venue"
},
  "geometry": {"coordinates":[8.596711,52.308243],"type":"Point"}
}