{
  "type": "Feature",
  "properties": {
    "iso:country":"DE",
    "sg:address":"Baumwall",
    "sg:city":"Hamburg",
    "sg:postcode":"20459",
    "sg:province":"Hamburg",
    "wof:name":"Familiengesellschaft J. Jahr Gmbh & Co.",
    "wof:placetype":"venue"
},
  "geometry": {"coordinates":[9.981964,53.544434],"type":"Point"}
}