{
  "type": "Feature",
  "properties": {
    "iso:country":"DE",
    "sg:address":"Blaubeurer Str. 37",
    "sg:city":"Ulm",
    "sg:postcode":"89077",
    "sg:province":"Baden-W\u00fcrttemberg",
    "wof:name":"Pizzaexpress",
    "wof:placetype":"venue"
},
  "geometry": {"coordinates":[9.9723453522,48.4014396667],"type":"Point"}
}