{
  "type": "Feature",
  "properties": {
    "iso:country":"DE",
    "sg:address":"Siegburger Str. 35",
    "sg:city":"Sankt Augustin",
    "sg:postcode":"53757",
    "sg:province":"Nordrhein-Westfalen",
    "wof:name":"Cedros Gesellschaft F\u00fcr Datenverarbeitung Mbh",
    "wof:placetype":"venue"
},
  "geometry": {"coordinates":[7.1787829399,50.7876167297],"type":"Point"}
}