{
  "type": "Feature",
  "properties": {
    "iso:country":"DE",
    "sg:address":"Inselstr. 27",
    "sg:city":"Esslingen",
    "sg:phone":"+49 711/3160510",
    "sg:postcode":"73730",
    "sg:province":"Baden-W\u00fcrttemberg",
    "wof:name":"Iglu",
    "wof:placetype":"venue"
},
  "geometry": {"coordinates":[9.326587677,48.7263069153],"type":"Point"}
}