{
  "type": "Feature",
  "properties": {
    "iso:country":"DE",
    "sg:address":"Am Bornrain 4",
    "sg:city":"Kn\u00fcllwald",
    "sg:phone":"+49 5685/1817",
    "sg:postcode":"34593",
    "sg:province":"Hessen",
    "wof:name":"Kn\u00fcllwaldsch\u00e4nke",
    "wof:placetype":"venue"
},
  "geometry": {"coordinates":[9.5009336472,51.0339851379],"type":"Point"}
}