{
  "type": "Feature",
  "properties": {
    "iso:country":"DE",
    "sg:address":"Vorstadt 15",
    "sg:city":"Allersberg",
    "sg:phone":"+49 9176/242",
    "sg:postcode":"90584",
    "sg:province":"Bayern",
    "wof:name":"Hans Sturm",
    "wof:placetype":"venue"
},
  "geometry": {"coordinates":[11.238989,49.252663],"type":"Point"}
}