{
  "type": "Feature",
  "properties": {
    "iso:country":"DE",
    "sg:address":"Zeppelinweg 1 a",
    "sg:city":"M\u00f6lln",
    "sg:phone":"+49 4542/841041",
    "sg:postcode":"23879",
    "sg:province":"Schleswig-Holstein",
    "wof:name":"O. P. A. Bautr\u00e4ger- Und Handels Gmbh",
    "wof:placetype":"venue"
},
  "geometry": {"coordinates":[10.67415,53.606529],"type":"Point"}
}