{
  "type": "Feature",
  "properties": {
    "iso:country":"DE",
    "sg:address":"Reinerzaustr. 9",
    "sg:city":"Schenkenzell",
    "sg:phone":"+49 4978/36655",
    "sg:postcode":"77773",
    "sg:province":"Baden-W\u00fcrttemberg",
    "wof:name":"Bezirkssparkasse Wolfach",
    "wof:placetype":"venue"
},
  "geometry": {"coordinates":[8.370653,48.310963],"type":"Point"}
}