{
  "type": "Feature",
  "properties": {
    "iso:country":"DE",
    "sg:address":"Hauptstr. 13",
    "sg:city":"Offenburg",
    "sg:phone":"+49 781/24727",
    "sg:postcode":"77652",
    "sg:province":"Baden-W\u00fcrttemberg",
    "wof:name":"Pyramide",
    "wof:placetype":"venue"
},
  "geometry": {"coordinates":[7.944351,48.473713],"type":"Point"}
}