{
  "type": "Feature",
  "properties": {
    "iso:country":"DE",
    "sg:address":"K\u00f6nigsdamm 2",
    "sg:city":"Ratzeburg",
    "sg:phone":"+49 4541/880811",
    "sg:postcode":"23909",
    "sg:province":"Schleswig-Holstein",
    "wof:name":"Abfallwirtschaftsgesellschaft Herzogtum Lauenburg Mbh",
    "wof:placetype":"venue"
},
  "geometry": {"coordinates":[10.777728,53.698788],"type":"Point"}
}