{
  "type": "Feature",
  "properties": {
    "iso:country":"DE",
    "sg:address":"M\u00fchlweg 1",
    "sg:city":"B\u00fcrgel",
    "sg:phone":"+49 36692/21294",
    "sg:postcode":"07616",
    "sg:province":"Th\u00fcringen",
    "wof:name":"H. Rosemann",
    "wof:placetype":"venue"
},
  "geometry": {"coordinates":[11.74738,50.94035],"type":"Point"}
}