{
  "type": "Feature",
  "properties": {
    "iso:country":"DE",
    "sg:address":"Kurt-Schumacher-Allee 44-46",
    "sg:city":"Langenhagen",
    "sg:phone":"+49 511/722859",
    "sg:postcode":"30851",
    "sg:province":"Niedersachsen",
    "wof:name":"Hans-j\u00fcrgen Kuhn Masseur",
    "wof:placetype":"venue"
},
  "geometry": {"coordinates":[9.747902,52.436008],"type":"Point"}
}