{
  "type": "Feature",
  "properties": {
    "iso:country":"DE",
    "sg:address":"Steige 11",
    "sg:city":"Triefenstein",
    "sg:phone":"+49 9395/341",
    "sg:postcode":"97855",
    "sg:province":"Bayern",
    "wof:name":"H. Rohrmoser",
    "wof:placetype":"venue"
},
  "geometry": {"coordinates":[9.6205348969,49.7928657532],"type":"Point"}
}