{
  "type": "Feature",
  "properties": {
    "iso:country":"DE",
    "sg:address":"Offinger Str. 2",
    "sg:city":"Gundelfingen",
    "sg:phone":"+49 9073/508",
    "sg:postcode":"89423",
    "sg:province":"Bayern",
    "wof:name":"Gastst\u00e4tte Doris W\u00fcnsch",
    "wof:placetype":"venue"
},
  "geometry": {"coordinates":[10.3629627228,48.5228881836],"type":"Point"}
}