{
  "type": "Feature",
  "properties": {
    "iso:country":"DE",
    "sg:address":"Am Kervel 12 A",
    "sg:city":"Hilter",
    "sg:phone":"+49 5409/4252",
    "sg:postcode":"49176",
    "sg:province":"Niedersachsen",
    "wof:name":"B\u00f6ckenholt & Korte Architekten",
    "wof:placetype":"venue"
},
  "geometry": {"coordinates":[8.184525,52.19379],"type":"Point"}
}