{
  "type": "Feature",
  "properties": {
    "iso:country":"DE",
    "sg:address":"Gro\u00dfe Str. 72",
    "sg:city":"Strausberg",
    "sg:phone":"+49 3341/313991",
    "sg:postcode":"15344",
    "sg:province":"Brandenburg",
    "wof:name":"Granit Grundst\u00fccks- Und Bautr\u00e4ger Gmbh",
    "wof:placetype":"venue"
},
  "geometry": {"coordinates":[13.881862,52.577888],"type":"Point"}
}