{
  "type": "Feature",
  "properties": {
    "iso:country":"DE",
    "sg:address":"Richard-Dehmel-Str. 15",
    "sg:city":"Hamburg",
    "sg:phone":"+49 40",
    "sg:postcode":"22587",
    "sg:province":"Hamburg",
    "wof:name":"Timberwolf Productions -- Webdesign For Everyone",
    "wof:placetype":"venue"
},
  "geometry": {"coordinates":[9.798652,53.5634],"type":"Point"}
}