{
  "type": "Feature",
  "properties": {
    "iso:country":"DE",
    "sg:address":"D\u00f6renther Str. 29",
    "sg:city":"Tecklenburg",
    "sg:phone":"+49 5455/1770",
    "sg:postcode":"49545",
    "sg:province":"Nordrhein-Westfalen",
    "wof:name":"C. Und M. Wallmeier",
    "wof:placetype":"venue"
},
  "geometry": {"coordinates":[7.736674,52.221977],"type":"Point"}
}