{
  "type": "Feature",
  "properties": {
    "iso:country":"DE",
    "sg:address":"Am Fleth 4",
    "sg:city":"Gl\u00fcckstadt",
    "sg:phone":"+49 4124/980734",
    "sg:postcode":"25348",
    "sg:province":"Schleswig-Holstein",
    "wof:name":"Fleth 4",
    "wof:placetype":"venue"
},
  "geometry": {"coordinates":[9.4248361588,53.7867393494],"type":"Point"}
}