{
  "type": "Feature",
  "properties": {
    "iso:country":"DE",
    "sg:address":"Michelsberg 30",
    "sg:city":"Wiesbaden",
    "sg:phone":"+49 611/374623",
    "sg:postcode":"65183",
    "sg:province":"Hessen",
    "wof:name":"Karin Adam",
    "wof:placetype":"venue"
},
  "geometry": {"coordinates":[8.236613,50.083015],"type":"Point"}
}