{
  "type": "Feature",
  "properties": {
    "iso:country":"DE",
    "sg:address":"Gro\u00dfenhainer Str. 33",
    "sg:city":"Priestewitz",
    "sg:phone":"+49 3522/502920",
    "sg:postcode":"01561",
    "sg:province":"Sachsen",
    "wof:name":"Frank Creutz",
    "wof:placetype":"venue"
},
  "geometry": {"coordinates":[13.5088,51.25428],"type":"Point"}
}