{
  "type": "Feature",
  "properties": {
    "iso:country":"DE",
    "sg:address":"Kirchstr. 6",
    "sg:city":"Nusse",
    "sg:phone":"+49 4543/7171",
    "sg:postcode":"23896",
    "sg:province":"Schleswig-Holstein",
    "wof:name":"Birken-apotheke",
    "wof:placetype":"venue"
},
  "geometry": {"coordinates":[10.576266,53.658813],"type":"Point"}
}