{
  "type": "Feature",
  "properties": {
    "iso:country":"DE",
    "sg:address":"Mettener Str. 21",
    "sg:city":"Deggendorf",
    "sg:phone":"+49 991/370340",
    "sg:postcode":"94469",
    "sg:province":"Bayern",
    "wof:name":"Glas Klein Gmbh",
    "wof:placetype":"venue"
},
  "geometry": {"coordinates":[12.945031,48.835278],"type":"Point"}
}