{
  "type": "Feature",
  "properties": {
    "iso:country":"DE",
    "sg:address":"Maigl\u00f6ckchenstr. 26",
    "sg:city":"Berlin",
    "sg:phone":"+49 30/4231751",
    "sg:postcode":"10407",
    "sg:province":"Berlin",
    "wof:name":"Hartmut Krause Rechtsanwalt",
    "wof:placetype":"venue"
},
  "geometry": {"coordinates":[13.4597787857,52.5329704285],"type":"Point"}
}