{
  "type": "Feature",
  "properties": {
    "iso:country":"DE",
    "sg:address":"D\u00fcrerstr. 2",
    "sg:city":"Neu-Anspach",
    "sg:postcode":"61267",
    "sg:province":"Hessen",
    "wof:name":"Horus Tours Gmbh Reiseb\u00fcro",
    "wof:placetype":"venue"
},
  "geometry": {"coordinates":[8.5048160553,50.3004798889],"type":"Point"}
}