{
  "type": "Feature",
  "properties": {
    "iso:country":"DE",
    "sg:address":"Westerender Str.",
    "sg:city":"Gro\u00dfheide",
    "sg:phone":"+49 4938/216",
    "sg:postcode":"26532",
    "sg:province":"Niedersachsen",
    "wof:name":"Johann E. Siebelts",
    "wof:placetype":"venue"
},
  "geometry": {"coordinates":[7.364125,53.611015],"type":"Point"}
}