{
  "type": "Feature",
  "properties": {
    "iso:country":"DE",
    "sg:address":"B\u00f6hmerwaldstr. 46",
    "sg:city":"Waldkraiburg",
    "sg:postcode":"84478",
    "sg:province":"Bayern",
    "wof:name":"Wws Kg",
    "wof:placetype":"venue"
},
  "geometry": {"coordinates":[12.405036,48.202168],"type":"Point"}
}