{
  "type": "Feature",
  "properties": {
    "iso:country":"DE",
    "sg:address":"Katharinenstr. 10",
    "sg:city":"Hamburg",
    "sg:postcode":"20457",
    "sg:province":"Hamburg",
    "wof:name":"Av Agrar Versicherungsdienst Gmbh",
    "wof:placetype":"venue"
},
  "geometry": {"coordinates":[9.9909639359,53.5458450317],"type":"Point"}
}