{
  "type": "Feature",
  "properties": {
    "iso:country":"DE",
    "sg:address":"Raiffeisenstr. 14",
    "sg:city":"Leinfelden-Echterdingen",
    "sg:phone":"+49 711/458940",
    "sg:postcode":"70771",
    "sg:province":"Baden-W\u00fcrttemberg",
    "wof:name":"Ads-tec Automation Daten- Und Systemtechnik Gmbh",
    "wof:placetype":"venue"
},
  "geometry": {"coordinates":[9.128807,48.705753],"type":"Point"}
}