{
  "type": "Feature",
  "properties": {
    "iso:country":"DE",
    "sg:address":"Motorstr. 47",
    "sg:city":"Stuttgart",
    "sg:phone":"+49 711/1399370",
    "sg:postcode":"70499",
    "sg:province":"Baden-W\u00fcrttemberg",
    "wof:name":"Lohe Dienstleistungen Gmbh",
    "wof:placetype":"venue"
},
  "geometry": {"coordinates":[9.098153,48.825127],"type":"Point"}
}