{
  "type": "Feature",
  "properties": {
    "iso:country":"DE",
    "sg:address":"Kirchplatz 5",
    "sg:city":"Pullach",
    "sg:phone":"+49 89/7930921",
    "sg:postcode":"82049",
    "sg:province":"Bayern",
    "wof:name":"Cafe Dolce",
    "wof:placetype":"venue"
},
  "geometry": {"coordinates":[11.523205,48.056553],"type":"Point"}
}