{
  "type": "Feature",
  "properties": {
    "iso:country":"DE",
    "sg:address":"Bahnhofstr 11",
    "sg:city":"B\u00f6hlen",
    "sg:phone":"+49 34206/72722",
    "sg:postcode":"04564",
    "sg:province":"Sachsen",
    "wof:name":"Asg Dreger",
    "wof:placetype":"venue"
},
  "geometry": {"coordinates":[12.3842506409,51.2020568848],"type":"Point"}
}