{
  "type": "Feature",
  "properties": {
    "iso:country":"DE",
    "sg:address":"Wiesen",
    "sg:city":"Unterw\u00f6ssen",
    "sg:phone":"+49 8640/8704",
    "sg:postcode":"83246",
    "sg:province":"Bayern",
    "wof:name":"Camping Litzelau",
    "wof:placetype":"venue"
},
  "geometry": {"coordinates":[12.47791,47.735577],"type":"Point"}
}