{
  "type": "Feature",
  "properties": {
    "iso:country":"DE",
    "sg:address":"Alte Weinsteige 1 b",
    "sg:city":"Stuttgart",
    "sg:phone":"+49 711/6407493",
    "sg:postcode":"70180",
    "sg:province":"Baden-W\u00fcrttemberg",
    "wof:name":"Karl-rudolf Selbach Kameramann",
    "wof:placetype":"venue"
},
  "geometry": {"coordinates":[9.1693201065,48.7626075745],"type":"Point"}
}