{
  "type": "Feature",
  "properties": {
    "iso:country":"DE",
    "sg:city":"Solingen",
    "sg:postcode":"42657",
    "sg:province":"Nordrhein-Westfalen",
    "wof:name":"Whale Point Watersports Ltd",
    "wof:placetype":"venue"
},
  "geometry": {"coordinates":[7.08675,51.172161],"type":"Point"}
}