{
  "type": "Feature",
  "properties": {
    "iso:country":"DE",
    "sg:address":"Oberpfortstr. 20",
    "sg:city":"Ochtendung",
    "sg:phone":"+49 2625/1397",
    "sg:postcode":"56299",
    "sg:province":"Rheinland-Pfalz",
    "wof:name":"Manfred Hammes",
    "wof:placetype":"venue"
},
  "geometry": {"coordinates":[7.3916602135,50.3483009338],"type":"Point"}
}