{
  "type": "Feature",
  "properties": {
    "iso:country":"DE",
    "sg:address":"Friedrichshorst 18",
    "sg:city":"Beckum",
    "sg:phone":"+49 2525/2222",
    "sg:postcode":"59269",
    "sg:province":"Nordrhein-Westfalen",
    "wof:name":"B. Ahlmer Immobilienmakler",
    "wof:placetype":"venue"
},
  "geometry": {"coordinates":[8.0037164688,51.7880096436],"type":"Point"}
}