{
  "type": "Feature",
  "properties": {
    "iso:country":"DE",
    "sg:address":"Badenbergstr. 11",
    "sg:city":"Heidenheim",
    "sg:phone":"+49 7321/21942",
    "sg:postcode":"89520",
    "sg:province":"Baden-W\u00fcrttemberg",
    "wof:name":"Helmut Handte",
    "wof:placetype":"venue"
},
  "geometry": {"coordinates":[10.1705999374,48.6990127563],"type":"Point"}
}