{
  "type": "Feature",
  "properties": {
    "iso:country":"DE",
    "sg:address":"Richener Str. 15",
    "sg:city":"Eppingen",
    "sg:phone":"+49 7262/7076",
    "sg:postcode":"75031",
    "sg:province":"Baden-W\u00fcrttemberg",
    "wof:name":"H. L\u00f6w",
    "wof:placetype":"venue"
},
  "geometry": {"coordinates":[8.891123,49.168278],"type":"Point"}
}