{
  "type": "Feature",
  "properties": {
    "iso:country":"DE",
    "sg:address":"Bornheimer Landstr. 46",
    "sg:city":"Frankfurt",
    "sg:phone":"+49 69/433715",
    "sg:postcode":"60316",
    "sg:province":"Hessen",
    "wof:name":"Heydra Buchungs Service Gmbh",
    "wof:placetype":"venue"
},
  "geometry": {"coordinates":[8.694598,50.122807],"type":"Point"}
}