{
  "type": "Feature",
  "properties": {
    "iso:country":"DE",
    "sg:address":"Z\u00fcgelstr. 16",
    "sg:city":"M\u00fcnchen",
    "sg:phone":"+49 89/1419310",
    "sg:postcode":"80992",
    "sg:province":"Bayern",
    "wof:name":"Albrecht Bauer Messebau",
    "wof:placetype":"venue"
},
  "geometry": {"coordinates":[11.509996,48.174065],"type":"Point"}
}