{
  "type": "Feature",
  "properties": {
    "iso:country":"DE",
    "sg:address":"Dorfstr. 2",
    "sg:city":"Wahlstorf",
    "sg:phone":"+49 38733/20244",
    "sg:postcode":"19386",
    "sg:province":"Mecklenburg-Vorpommern",
    "wof:name":"Laatsch Reitstall",
    "wof:placetype":"venue"
},
  "geometry": {"coordinates":[12.0972280502,53.3613586426],"type":"Point"}
}