{
  "type": "Feature",
  "properties": {
    "iso:country":"DE",
    "sg:address":"Defreggerweg 3",
    "sg:city":"Regensburg",
    "sg:postcode":"93051",
    "sg:province":"Bayern",
    "wof:name":"Contrakta Immobilien- Vermittlung Gmbh & Co. Kg",
    "wof:placetype":"venue"
},
  "geometry": {"coordinates":[12.062169075,49.0089569092],"type":"Point"}
}