{
  "type": "Feature",
  "properties": {
    "iso:country":"DE",
    "sg:address":"Tullastr. 6",
    "sg:city":"Altlu\u00dfheim",
    "sg:phone":"+49 6205/37746",
    "sg:postcode":"68804",
    "sg:province":"Baden-W\u00fcrttemberg",
    "wof:name":"Orient",
    "wof:placetype":"venue"
},
  "geometry": {"coordinates":[8.4998130798,49.3030128479],"type":"Point"}
}