{
  "type": "Feature",
  "properties": {
    "iso:country":"DE",
    "sg:address":"Ringstra\u00dfe 38-44",
    "sg:city":"K\u00f6ln",
    "sg:postcode":"50996",
    "sg:province":"Nordrhein-Westfalen",
    "wof:name":"Volvo Deutschland Gmbh",
    "wof:placetype":"venue"
},
  "geometry": {"coordinates":[6.9945878983,50.8882217407],"type":"Point"}
}