{
  "type": "Feature",
  "properties": {
    "iso:country":"DE",
    "sg:address":"Leipziger Str. 36",
    "sg:city":"Meiningen",
    "sg:postcode":"98617",
    "sg:province":"Th\u00fcringen",
    "wof:name":"Siteforum Computer Gmbh",
    "wof:placetype":"venue"
},
  "geometry": {"coordinates":[10.4178590775,50.5794525146],"type":"Point"}
}