{
  "type": "Feature",
  "properties": {
    "iso:country":"DE",
    "sg:address":"Irscher Berg 38",
    "sg:city":"Trier",
    "sg:phone":"+49 651/17428",
    "sg:postcode":"54296",
    "sg:province":"Rheinland-Pfalz",
    "wof:name":"Dieter Jacobs",
    "wof:placetype":"venue"
},
  "geometry": {"coordinates":[6.6954460144,49.7282905579],"type":"Point"}
}