{
  "type": "Feature",
  "properties": {
    "iso:country":"DE",
    "sg:address":"Hohenstaufenring 2",
    "sg:city":"K\u00f6ln",
    "sg:phone":"+49 221/218529",
    "sg:postcode":"50674",
    "sg:province":"Nordrhein-Westfalen",
    "wof:name":"Parf\u00fcmerie-boutique Am Barbarossaplatz",
    "wof:placetype":"venue"
},
  "geometry": {"coordinates":[6.941736,50.929585],"type":"Point"}
}