{
  "type": "Feature",
  "properties": {
    "iso:country":"DE",
    "sg:address":"Wildensorger Str. 6",
    "sg:city":"Stegaurach",
    "sg:phone":"+49 951/9921240",
    "sg:postcode":"96135",
    "sg:province":"Bayern",
    "wof:name":"A. Und F. Popp",
    "wof:placetype":"venue"
},
  "geometry": {"coordinates":[10.8466482162,49.8633842468],"type":"Point"}
}