{
  "type": "Feature",
  "properties": {
    "iso:country":"DE",
    "sg:address":"Hauptstr. 31",
    "sg:city":"Sickte",
    "sg:phone":"+49 5305/1548",
    "sg:postcode":"38173",
    "sg:province":"Niedersachsen",
    "wof:name":"S. Reitmann",
    "wof:placetype":"venue"
},
  "geometry": {"coordinates":[10.6203460693,52.2210922241],"type":"Point"}
}