{
  "type": "Feature",
  "properties": {
    "iso:country":"DE",
    "sg:address":"Richard-Wagner-Str. 21",
    "sg:city":"Bad Sch\u00f6nborn",
    "sg:phone":"+49 7253/4115",
    "sg:postcode":"76669",
    "sg:province":"Baden-W\u00fcrttemberg",
    "wof:name":"Pension Josef Gander",
    "wof:placetype":"venue"
},
  "geometry": {"coordinates":[8.670416832,49.2217674255],"type":"Point"}
}