{
  "type": "Feature",
  "properties": {
    "iso:country":"DE",
    "sg:address":"Holzmarkt 4",
    "sg:city":"Freiburg",
    "sg:postcode":"79098",
    "sg:province":"Baden-W\u00fcrttemberg",
    "wof:name":"Institut F\u00fcr Forstbenutzung U. Forstliche Arbeitswissen-",
    "wof:placetype":"venue"
},
  "geometry": {"coordinates":[7.849407196,47.9920349121],"type":"Point"}
}