{
  "type": "Feature",
  "properties": {
    "iso:country":"DE",
    "sg:address":"Bahnhofstr. 37",
    "sg:city":"Deisenhofen",
    "sg:phone":"+49 89/6131736",
    "sg:postcode":"82041",
    "sg:province":"Bayern",
    "wof:name":"Glei\u00dfental-apotheke",
    "wof:placetype":"venue"
},
  "geometry": {"coordinates":[11.585342,48.01968],"type":"Point"}
}