{
  "type": "Feature",
  "properties": {
    "iso:country":"DE",
    "sg:address":"St\u00e4hlinweg 7",
    "sg:city":"Memmingen",
    "sg:phone":"+49 8331/65937",
    "sg:postcode":"87700",
    "sg:province":"Bayern",
    "wof:name":"Salger Grundst\u00fcck- Verwaltungs Gmbh",
    "wof:placetype":"venue"
},
  "geometry": {"coordinates":[10.169474,47.980972],"type":"Point"}
}