{
  "type": "Feature",
  "properties": {
    "iso:country":"DE",
    "sg:address":"Sterkrader Str. 187",
    "sg:city":"Bottrop",
    "sg:phone":"+49 2041/51464",
    "sg:postcode":"46242",
    "sg:province":"Nordrhein-Westfalen",
    "wof:name":"Hermann Elvermann",
    "wof:placetype":"venue"
},
  "geometry": {"coordinates":[6.897662,51.520367],"type":"Point"}
}