{
  "type": "Feature",
  "properties": {
    "iso:country":"DE",
    "sg:address":"Halberst\u00e4dter Chaussee 11",
    "sg:city":"Magdeburg",
    "sg:phone":"+49 391/6345006",
    "sg:postcode":"39116",
    "sg:province":"Sachsen-Anhalt",
    "wof:name":"Gerhard Wirth",
    "wof:placetype":"venue"
},
  "geometry": {"coordinates":[11.567171,52.087437],"type":"Point"}
}