{
  "type": "Feature",
  "properties": {
    "iso:country":"DE",
    "sg:address":"Sonnenstr. 12",
    "sg:city":"Braunschweig",
    "sg:phone":"+49 531/44461",
    "sg:postcode":"38100",
    "sg:province":"Niedersachsen",
    "wof:name":"G\u00fclden-apotheke",
    "wof:placetype":"venue"
},
  "geometry": {"coordinates":[10.513627,52.26263],"type":"Point"}
}