{
  "type": "Feature",
  "properties": {
    "iso:country":"DE",
    "sg:address":"An der B 182",
    "sg:city":"Rackith",
    "sg:phone":"+49 34927/7000",
    "sg:postcode":"06901",
    "sg:province":"Sachsen-Anhalt",
    "wof:name":"Awu Wittenberg Gmbh",
    "wof:placetype":"venue"
},
  "geometry": {"coordinates":[12.677069664,51.8046836853],"type":"Point"}
}