{
  "type": "Feature",
  "properties": {
    "iso:country":"DE",
    "sg:address":"Max-Planck-Str. 27",
    "sg:city":"Viernheim",
    "sg:phone":"+49 6204/3972",
    "sg:postcode":"68519",
    "sg:province":"Hessen",
    "wof:name":"Jean Beikert Inh. Kuno Beikert",
    "wof:placetype":"venue"
},
  "geometry": {"coordinates":[8.587313,49.551304],"type":"Point"}
}