{
  "type": "Feature",
  "properties": {
    "iso:country":"DE",
    "sg:address":"Vilsendorfer Str. 56",
    "sg:city":"Bielefeld",
    "sg:phone":"+49 5206/2271",
    "sg:postcode":"33739",
    "sg:province":"Nordrhein-Westfalen",
    "wof:name":"August B\u00f6ndel",
    "wof:placetype":"venue"
},
  "geometry": {"coordinates":[8.526669,52.091763],"type":"Point"}
}