{
  "type": "Feature",
  "properties": {
    "iso:country":"DE",
    "sg:address":"Im Dorfe 23",
    "sg:city":"Dortmund",
    "sg:phone":"+49 231/801861",
    "sg:postcode":"44339",
    "sg:province":"Nordrhein-Westfalen",
    "wof:name":"Katholisches Pfarramt St. Antonius",
    "wof:placetype":"venue"
},
  "geometry": {"coordinates":[7.4667711258,51.5775260925],"type":"Point"}
}