{
  "type": "Feature",
  "properties": {
    "iso:country":"DE",
    "sg:address":"Tituscorso 5 (Wohnung 321)",
    "sg:city":"Frankfurt",
    "sg:postcode":"60439",
    "sg:province":"Hessen",
    "wof:name":"Alka Gmbh",
    "wof:placetype":"venue"
},
  "geometry": {"coordinates":[8.6345281601,50.1572952271],"type":"Point"}
}