{
  "type": "Feature",
  "properties": {
    "iso:country":"DE",
    "sg:address":"Ritterstr. 43",
    "sg:city":"L\u00fcneburg",
    "sg:phone":"+49 4131/47372",
    "sg:postcode":"21335",
    "sg:province":"Niedersachsen",
    "wof:name":"H. Zewuhn Heilpraktiker",
    "wof:placetype":"venue"
},
  "geometry": {"coordinates":[10.4041700363,53.2454109192],"type":"Point"}
}