{
  "type": "Feature",
  "properties": {
    "iso:country":"DE",
    "sg:address":"Am Peitschenstein 12",
    "sg:city":"Creu\u00dfen",
    "sg:phone":"+49 9270/1631",
    "sg:postcode":"95473",
    "sg:province":"Bayern",
    "wof:name":"Erwin Lehr",
    "wof:placetype":"venue"
},
  "geometry": {"coordinates":[11.6260461807,49.8379440308],"type":"Point"}
}