{
  "type": "Feature",
  "properties": {
    "iso:country":"DE",
    "sg:address":"Fellericher M\u00fchle",
    "sg:city":"Tawern",
    "sg:phone":"+49 6501/600338",
    "sg:postcode":"54456",
    "sg:province":"Rheinland-Pfalz",
    "wof:name":"Peter Weyer Gmbh",
    "wof:placetype":"venue"
},
  "geometry": {"coordinates":[6.5053048134,49.6792640686],"type":"Point"}
}