{
  "type": "Feature",
  "properties": {
    "iso:country":"DE",
    "sg:address":"Kasparstr. 22",
    "sg:city":"H\u00fcrth",
    "sg:phone":"+49 2233/64799",
    "sg:postcode":"50354",
    "sg:province":"Nordrhein-Westfalen",
    "wof:name":"Special-effect-team Ruppala Gmbh",
    "wof:placetype":"venue"
},
  "geometry": {"coordinates":[6.894449234,50.9011421204],"type":"Point"}
}