{
  "type": "Feature",
  "properties": {
    "iso:country":"DE",
    "sg:address":"Emil-Nolde-Weg 10",
    "sg:city":"M\u00f6rfelden-Walldorf",
    "sg:postcode":"64546",
    "sg:province":"Hessen",
    "wof:name":"Train-invest Gmbh",
    "wof:placetype":"venue"
},
  "geometry": {"coordinates":[8.5601396561,49.9816207886],"type":"Point"}
}