{
  "type": "Feature",
  "properties": {
    "iso:country":"DE",
    "sg:address":"Kuhlmannsfeld 29",
    "sg:city":"Essen",
    "sg:phone":"+49 201/665592",
    "sg:postcode":"45355",
    "sg:province":"Nordrhein-Westfalen",
    "wof:name":"Rudolf Klein",
    "wof:placetype":"venue"
},
  "geometry": {"coordinates":[6.9527139664,51.4805183411],"type":"Point"}
}