{
  "type": "Feature",
  "properties": {
    "iso:country":"DE",
    "sg:address":"Grundweg 1",
    "sg:city":"L\u00fcbbecke",
    "sg:phone":"+49 5741/8189",
    "sg:postcode":"32312",
    "sg:province":"Nordrhein-Westfalen",
    "wof:name":"Friedh. B\u00f6kenheide",
    "wof:placetype":"venue"
},
  "geometry": {"coordinates":[8.5802412033,52.3013114929],"type":"Point"}
}