{
  "type": "Feature",
  "properties": {
    "iso:country":"DE",
    "sg:address":"In Steckenborn 68",
    "sg:city":"Simmerath",
    "sg:phone":"+49 2473/3991",
    "sg:postcode":"52152",
    "sg:province":"Nordrhein-Westfalen",
    "wof:name":"B. H\u00fclsbeck",
    "wof:placetype":"venue"
},
  "geometry": {"coordinates":[6.3551149368,50.6242370605],"type":"Point"}
}