{
  "type": "Feature",
  "properties": {
    "iso:country":"DE",
    "sg:address":"Wilhelm-Wolff-Str. 21",
    "sg:city":"Berlin",
    "sg:phone":"+49 30/91611071",
    "sg:postcode":"13156",
    "sg:province":"Berlin",
    "wof:name":"Kano Bau Gmbh & Co. Kg",
    "wof:placetype":"venue"
},
  "geometry": {"coordinates":[13.3945703506,52.5803222656],"type":"Point"}
}