{
  "type": "Feature",
  "properties": {
    "iso:country":"DE",
    "sg:address":"Sinziger Str. 17",
    "sg:city":"Remagen",
    "sg:phone":"+49 2642/22949",
    "sg:postcode":"53424",
    "sg:province":"Rheinland-Pfalz",
    "wof:name":"Ria Heydecke Steuerberaterin",
    "wof:placetype":"venue"
},
  "geometry": {"coordinates":[7.2355079651,50.5726776123],"type":"Point"}
}