{
  "type": "Feature",
  "properties": {
    "iso:country":"DE",
    "sg:address":"August-Gerhardt-Str. 18",
    "sg:city":"Runkel",
    "sg:phone":"+49 6482/4758",
    "sg:postcode":"65594",
    "sg:province":"Hessen",
    "wof:name":"Kath. Pfarramt",
    "wof:placetype":"venue"
},
  "geometry": {"coordinates":[8.1641702652,50.4035072327],"type":"Point"}
}