{
  "type": "Feature",
  "properties": {
    "iso:country":"DE",
    "sg:address":"Saarstr. 18",
    "sg:city":"Oldenburg",
    "sg:phone":"+49 441/83370",
    "sg:postcode":"26121",
    "sg:province":"Niedersachsen",
    "wof:name":"Helga Wulff Steuerberaterin",
    "wof:placetype":"venue"
},
  "geometry": {"coordinates":[8.2057523727,53.1505813599],"type":"Point"}
}