{
  "type": "Feature",
  "properties": {
    "iso:country":"DE",
    "sg:address":"Bergerstr. 197",
    "sg:city":"K\u00f6ln",
    "sg:postcode":"51145",
    "sg:province":"Nordrhein-Westfalen",
    "wof:name":"Formen Studio F\u00fcr Bauplanung Gmbh",
    "wof:placetype":"venue"
},
  "geometry": {"coordinates":[7.073235,50.892761],"type":"Point"}
}