{
  "type": "Feature",
  "properties": {
    "iso:country":"DE",
    "sg:address":"Marktplatz 12",
    "sg:city":"Memmingen",
    "sg:phone":"+49 8331/4168",
    "sg:postcode":"87700",
    "sg:province":"Bayern",
    "wof:name":"Iduna Bez. B\u00fchler Inh. Orlam\u00fcnder",
    "wof:placetype":"venue"
},
  "geometry": {"coordinates":[10.1802425385,47.9866981506],"type":"Point"}
}