{
  "type": "Feature",
  "properties": {
    "iso:country":"DE",
    "sg:address":"Friedensallee 91",
    "sg:city":"Zerbst",
    "sg:phone":"+49 3923/778021",
    "sg:postcode":"39261",
    "sg:province":"Sachsen-Anhalt",
    "wof:name":"Fl\u00fcgel Und Von Thadden Rechtsanw\u00e4lte",
    "wof:placetype":"venue"
},
  "geometry": {"coordinates":[12.0816602707,51.9558372498],"type":"Point"}
}