{
  "type": "Feature",
  "properties": {
    "iso:country":"DE",
    "sg:address":"Uns\u00f6ldstr. 12",
    "sg:city":"M\u00fcnchen",
    "sg:phone":"+49 89/225937",
    "sg:postcode":"80538",
    "sg:province":"Bayern",
    "wof:name":"Volker Wislicenus Architekt",
    "wof:placetype":"venue"
},
  "geometry": {"coordinates":[11.586694,48.141979],"type":"Point"}
}