{
  "type": "Feature",
  "properties": {
    "iso:country":"DE",
    "sg:address":"Oststr. 35",
    "sg:city":"Bochum",
    "sg:phone":"+49 2327/88657",
    "sg:postcode":"44866",
    "sg:province":"Nordrhein-Westfalen",
    "wof:name":"Marga Heinemann",
    "wof:placetype":"venue"
},
  "geometry": {"coordinates":[7.1362910271,51.4807777405],"type":"Point"}
}