{
  "type": "Feature",
  "properties": {
    "iso:country":"DE",
    "sg:address":"Kurierstr. 9",
    "sg:city":"Osterhofen",
    "sg:phone":"+49 9932/1452",
    "sg:postcode":"94486",
    "sg:province":"Bayern",
    "wof:name":"Gasthaus Kirschner",
    "wof:placetype":"venue"
},
  "geometry": {"coordinates":[12.9758367538,48.659072876],"type":"Point"}
}