{
  "type": "Feature",
  "properties": {
    "iso:country":"DE",
    "sg:address":"M\u00fcndelheimer Weg 25",
    "sg:city":"D\u00fcsseldorf",
    "sg:postcode":"40472",
    "sg:province":"Nordrhein-Westfalen",
    "wof:name":"Msb Logistik Gmbh",
    "wof:placetype":"venue"
},
  "geometry": {"coordinates":[6.793645,51.288532],"type":"Point"}
}