{
  "type": "Feature",
  "properties": {
    "iso:country":"DE",
    "sg:address":"Wilhelmsruher Damm 130",
    "sg:city":"Berlin",
    "sg:phone":"+49 30/40768819",
    "sg:postcode":"13439",
    "sg:province":"Berlin",
    "wof:name":"Manhattan",
    "wof:placetype":"venue"
},
  "geometry": {"coordinates":[13.355033,52.596775],"type":"Point"}
}