{
  "type": "Feature",
  "properties": {
    "iso:country":"DE",
    "sg:address":"Gr\u00fcne Str. 18",
    "sg:city":"Oldenburg",
    "sg:phone":"+49 441/25559",
    "sg:postcode":"26121",
    "sg:province":"Niedersachsen",
    "wof:name":"Peter Oltmanns",
    "wof:placetype":"venue"
},
  "geometry": {"coordinates":[8.2111005783,53.1442527771],"type":"Point"}
}