{
  "type": "Feature",
  "properties": {
    "iso:country":"DE",
    "sg:address":"Borngasse 2",
    "sg:city":"Hadamar",
    "sg:phone":"+49 6433/2991",
    "sg:postcode":"65589",
    "sg:province":"Hessen",
    "wof:name":"August Schweitzer",
    "wof:placetype":"venue"
},
  "geometry": {"coordinates":[8.0459890366,50.4490432739],"type":"Point"}
}