{
  "type": "Feature",
  "properties": {
    "iso:country":"DE",
    "sg:address":"Obergasse 5",
    "sg:city":"Appenheim",
    "sg:phone":"+49 6725/2930",
    "sg:postcode":"55437",
    "sg:province":"Rheinland-Pfalz",
    "wof:name":"Schweikard Reisen Gmbh",
    "wof:placetype":"venue"
},
  "geometry": {"coordinates":[8.0328083038,49.9298477173],"type":"Point"}
}