{
  "type": "Feature",
  "properties": {
    "iso:country":"DE",
    "sg:address":"S\u00fcdstr. 33",
    "sg:city":"Sankt Augustin",
    "sg:phone":"+49 2241/202023",
    "sg:postcode":"53757",
    "sg:province":"Nordrhein-Westfalen",
    "wof:name":"S\u00fcd-apotheke Inh. Heike Hertzel",
    "wof:placetype":"venue"
},
  "geometry": {"coordinates":[7.186408,50.780106],"type":"Point"}
}