{
  "type": "Feature",
  "properties": {
    "iso:country":"DE",
    "sg:address":"Heideweg 100",
    "sg:city":"Belm",
    "sg:phone":"+49 5406/1511",
    "sg:postcode":"49191",
    "sg:province":"Niedersachsen",
    "wof:name":"Fred Kr\u00fcwel",
    "wof:placetype":"venue"
},
  "geometry": {"coordinates":[8.1189517975,52.2976570129],"type":"Point"}
}