{
  "type": "Feature",
  "properties": {
    "iso:country":"DE",
    "sg:address":"Polziner Str. 6",
    "sg:city":"Malente",
    "sg:phone":"+49 4523/2126",
    "sg:postcode":"23714",
    "sg:province":"Schleswig-Holstein",
    "wof:name":"Erwin Wendt",
    "wof:placetype":"venue"
},
  "geometry": {"coordinates":[10.567128,54.17696],"type":"Point"}
}