{
  "type": "Feature",
  "properties": {
    "iso:country":"DE",
    "sg:address":"Matth\u00e4us-Herrmann-Platz 2",
    "sg:city":"N\u00fcrnberg",
    "sg:phone":"+49 911/868641",
    "sg:postcode":"90471",
    "sg:province":"Bayern",
    "wof:name":"Friedeberg",
    "wof:placetype":"venue"
},
  "geometry": {"coordinates":[11.1054878235,49.415271759],"type":"Point"}
}