{
  "type": "Feature",
  "properties": {
    "iso:country":"DE",
    "sg:address":"Kieler Str. 557",
    "sg:city":"Hamburg",
    "sg:phone":"+49 40/54779411",
    "sg:postcode":"22525",
    "sg:province":"Hamburg",
    "wof:name":"Gisela L\u00f6wer De Freyhofer Gmbh",
    "wof:placetype":"venue"
},
  "geometry": {"coordinates":[9.930425,53.590721],"type":"Point"}
}