{
  "type": "Feature",
  "properties": {
    "iso:country":"DE",
    "sg:address":"Nienstedter Str. 88",
    "sg:city":"Barsinghausen",
    "sg:phone":"+49 5105/8853",
    "sg:postcode":"30890",
    "sg:province":"Niedersachsen",
    "wof:name":"F. Kruse Kruse",
    "wof:placetype":"venue"
},
  "geometry": {"coordinates":[9.494234,52.278828],"type":"Point"}
}