{
  "type": "Feature",
  "properties": {
    "iso:country":"DE",
    "sg:address":"Ritter-von-Scheuring-Str. 20",
    "sg:city":"Salzweg",
    "sg:postcode":"94121",
    "sg:province":"Bayern",
    "wof:name":"Kermax Ag",
    "wof:placetype":"venue"
},
  "geometry": {"coordinates":[13.4828119278,48.6165275574],"type":"Point"}
}