{
  "type": "Feature",
  "properties": {
    "iso:country":"DE",
    "sg:address":"Wolframstr. 5",
    "sg:city":"Stuttgart",
    "sg:phone":"+49 711/2567199",
    "sg:postcode":"70191",
    "sg:province":"Baden-W\u00fcrttemberg",
    "wof:name":"Tunnelsch\u00e4nke",
    "wof:placetype":"venue"
},
  "geometry": {"coordinates":[9.1864461899,48.7905540466],"type":"Point"}
}