{
  "type": "Feature",
  "properties": {
    "iso:country":"DE",
    "sg:address":"In den Kl\u00f6tzen 3",
    "sg:city":"Schildow",
    "sg:phone":"+49 33056/89494",
    "sg:postcode":"16552",
    "sg:province":"Brandenburg",
    "wof:name":"G\u00fcnter Netzer",
    "wof:placetype":"venue"
},
  "geometry": {"coordinates":[13.3736286163,52.6457252502],"type":"Point"}
}