{
  "type": "Feature",
  "properties": {
    "iso:country":"DE",
    "sg:address":"H\u00f6wwell.3",
    "sg:city":"Rhede",
    "sg:phone":"+49 4928/7292920",
    "sg:postcode":"46414",
    "sg:province":"Nordrhein-Westfalen",
    "wof:name":"Paul Niehaus Spedition Gmbh & Co Kg",
    "wof:placetype":"venue"
},
  "geometry": {"coordinates":[6.7172269821,51.8272514343],"type":"Point"}
}