{
  "type": "Feature",
  "properties": {
    "iso:country":"DE",
    "sg:address":"Bauerngasse 7",
    "sg:city":"Wertingen",
    "sg:phone":"+49 8272/3154",
    "sg:postcode":"86637",
    "sg:province":"Bayern",
    "wof:name":"Josef Lutz",
    "wof:placetype":"venue"
},
  "geometry": {"coordinates":[10.683148,48.563534],"type":"Point"}
}