{
  "type": "Feature",
  "properties": {
    "iso:country":"DE",
    "sg:address":"Rathausufer 16-17",
    "sg:city":"D\u00fcsseldorf",
    "sg:phone":"+49 4921/1130900",
    "sg:postcode":"40213",
    "sg:province":"Nordrhein-Westfalen",
    "wof:name":"Red Cell Werbwagentur Gmbh & Co Kg",
    "wof:placetype":"venue"
},
  "geometry": {"coordinates":[6.769606,51.223751],"type":"Point"}
}