{
  "type": "Feature",
  "properties": {
    "iso:country":"DE",
    "sg:address":"Benediktinerweg 24",
    "sg:city":"Isny",
    "sg:phone":"+49 7562/2622",
    "sg:postcode":"88316",
    "sg:province":"Baden-W\u00fcrttemberg",
    "wof:name":"K.-e. Singer",
    "wof:placetype":"venue"
},
  "geometry": {"coordinates":[10.0613899231,47.6966400146],"type":"Point"}
}