{
  "type": "Feature",
  "properties": {
    "iso:country":"DE",
    "sg:address":"Industriestr. 6",
    "sg:city":"Winnenden",
    "sg:phone":"+49 7195/73830",
    "sg:postcode":"71364",
    "sg:province":"Baden-W\u00fcrttemberg",
    "wof:name":"T. Nagel",
    "wof:placetype":"venue"
},
  "geometry": {"coordinates":[9.4361343384,48.8603668213],"type":"Point"}
}