{
  "type": "Feature",
  "properties": {
    "iso:country":"DE",
    "sg:address":"Frankfurter Str. 43",
    "sg:city":"Unkel",
    "sg:phone":"+49 2224/902852",
    "sg:postcode":"53572",
    "sg:province":"Rheinland-Pfalz",
    "wof:name":"Cara-med Kranken- Und Altenpflegedienst Unkel",
    "wof:placetype":"venue"
},
  "geometry": {"coordinates":[7.215971,50.600311],"type":"Point"}
}