{
  "type": "Feature",
  "properties": {
    "iso:country":"DE",
    "sg:address":"Bernhard-G\u00f6ring-Str. 150",
    "sg:city":"Leipzig",
    "sg:phone":"+49 341/4778423",
    "sg:postcode":"04277",
    "sg:province":"Sachsen",
    "wof:name":"Pro Plant Service Gmbh",
    "wof:placetype":"venue"
},
  "geometry": {"coordinates":[12.376239,51.311886],"type":"Point"}
}