{
  "type": "Feature",
  "properties": {
    "iso:country":"DE",
    "sg:address":"Tsingtauer Str. 66",
    "sg:city":"M\u00fcnchen",
    "sg:phone":"+49 89/4301500",
    "sg:postcode":"81827",
    "sg:province":"Bayern",
    "wof:name":"Hans Dennerlein",
    "wof:placetype":"venue"
},
  "geometry": {"coordinates":[11.695534,48.103504],"type":"Point"}
}