{
  "type": "Feature",
  "properties": {
    "iso:country":"DE",
    "sg:address":"Im Bach 26",
    "sg:city":"Wechingen",
    "sg:phone":"+49 9085/265",
    "sg:postcode":"86759",
    "sg:province":"Bayern",
    "wof:name":"Trocknungsgemeinschaft Wechingen Eg",
    "wof:placetype":"venue"
},
  "geometry": {"coordinates":[10.608009,48.892532],"type":"Point"}
}