{
  "type": "Feature",
  "properties": {
    "iso:country":"DE",
    "sg:address":"Industriestr. 33",
    "sg:city":"Rheinbach",
    "sg:postcode":"53359",
    "sg:province":"Nordrhein-Westfalen",
    "wof:name":"Ic Quality Office Objektaus- Stattung Und Consult",
    "wof:placetype":"venue"
},
  "geometry": {"coordinates":[6.9518737793,50.6376724243],"type":"Point"}
}