{
  "type": "Feature",
  "properties": {
    "iso:country":"DE",
    "sg:address":"Kranichdamm 48",
    "sg:city":"Salzgitter",
    "sg:phone":"+49 5341/65834",
    "sg:postcode":"38226",
    "sg:province":"Niedersachsen",
    "wof:name":"A. Casparick",
    "wof:placetype":"venue"
},
  "geometry": {"coordinates":[10.3421430588,52.1723442078],"type":"Point"}
}