{
  "type": "Feature",
  "properties": {
    "iso:country":"DE",
    "sg:address":"Speyerer Str. 7",
    "sg:city":"Mutterstadt",
    "sg:postcode":"67112",
    "sg:province":"Rheinland-Pfalz",
    "wof:name":"Msb Paletten- Und Konkurswarenhandel Gmbh",
    "wof:placetype":"venue"
},
  "geometry": {"coordinates":[8.3553028107,49.4415817261],"type":"Point"}
}