{
  "type": "Feature",
  "properties": {
    "iso:country":"DE",
    "sg:address":"Neust\u00e4dter Str. 63",
    "sg:city":"N\u00fcrnberg",
    "sg:phone":"+49 911/3262886",
    "sg:postcode":"90431",
    "sg:province":"Bayern",
    "wof:name":"Rappelkiste Kinderladen",
    "wof:placetype":"venue"
},
  "geometry": {"coordinates":[11.0247840881,49.4554977417],"type":"Point"}
}