{
  "type": "Feature",
  "properties": {
    "iso:country":"DE",
    "sg:address":"H\u00e4ndelstr. 14",
    "sg:city":"Singen",
    "sg:phone":"+49 7731/43515",
    "sg:postcode":"78224",
    "sg:province":"Baden-W\u00fcrttemberg",
    "wof:name":"U. Franke",
    "wof:placetype":"venue"
},
  "geometry": {"coordinates":[8.8363456726,47.774105072],"type":"Point"}
}