{
  "type": "Feature",
  "properties": {
    "iso:country":"DE",
    "sg:address":"Weidenallee 59 Hs.4",
    "sg:city":"D-Hamburg",
    "sg:phone":"+49 40/4322561",
    "sg:postcode":"20357",
    "sg:province":"Hamburg",
    "wof:name":"Www.shicco.de",
    "wof:placetype":"venue"
},
  "geometry": {"coordinates":[9.96583,53.562263],"type":"Point"}
}