{
  "type": "Feature",
  "properties": {
    "iso:country":"DE",
    "sg:address":"Hebbelstr. 15",
    "sg:city":"Velbert",
    "sg:phone":"+49 2051/65787",
    "sg:postcode":"42549",
    "sg:province":"Nordrhein-Westfalen",
    "wof:name":"Tempo St\u00fcbchen",
    "wof:placetype":"venue"
},
  "geometry": {"coordinates":[7.0163660049,51.3310890198],"type":"Point"}
}