{
  "type": "Feature",
  "properties": {
    "iso:country":"DE",
    "sg:address":"Zusamstr. 8",
    "sg:city":"Augsburg",
    "sg:phone":"+49 821/720200",
    "sg:postcode":"86165",
    "sg:province":"Bayern",
    "wof:name":"Microwi Electronic Gmbh",
    "wof:placetype":"venue"
},
  "geometry": {"coordinates":[10.936097,48.376686],"type":"Point"}
}