{
  "type": "Feature",
  "properties": {
    "iso:country":"DE",
    "sg:address":"Jar\u00dfumer Str. 1",
    "sg:city":"Emden",
    "sg:phone":"+49 4921/51208",
    "sg:postcode":"26725",
    "sg:province":"Niedersachsen",
    "wof:name":"Karin Hagen",
    "wof:placetype":"venue"
},
  "geometry": {"coordinates":[7.240952,53.34029],"type":"Point"}
}