{
  "type": "Feature",
  "properties": {
    "iso:country":"DE",
    "sg:address":"Am Eichberg 6",
    "sg:city":"Achern",
    "sg:postcode":"77855",
    "sg:province":"Baden-W\u00fcrttemberg",
    "wof:name":"Kath. \u00d6ffentliche Bibliothek St. Bernhard",
    "wof:placetype":"venue"
},
  "geometry": {"coordinates":[8.052967,48.623745],"type":"Point"}
}