{
  "type": "Feature",
  "properties": {
    "iso:country":"DE",
    "sg:address":"Waldstr. 20 b",
    "sg:city":"Lingen",
    "sg:phone":"+49 591/6051",
    "sg:postcode":"49808",
    "sg:province":"Niedersachsen",
    "wof:name":"Verlagsdruckerei Martin Koopmann Gmbh",
    "wof:placetype":"venue"
},
  "geometry": {"coordinates":[7.318902,52.527206],"type":"Point"}
}