{
  "type": "Feature",
  "properties": {
    "iso:country":"DE",
    "sg:address":"L\u00fcneburger Landstr. 1",
    "sg:city":"Reppenstedt",
    "sg:phone":"+49 4131/64436",
    "sg:postcode":"21391",
    "sg:province":"Niedersachsen",
    "wof:name":"R. Kruse",
    "wof:placetype":"venue"
},
  "geometry": {"coordinates":[10.354307,53.247967],"type":"Point"}
}