{
  "type": "Feature",
  "properties": {
    "iso:country":"DE",
    "sg:address":"Neustr. 13",
    "sg:city":"Salmtal",
    "sg:phone":"+49 6578/265",
    "sg:postcode":"54528",
    "sg:province":"Rheinland-Pfalz",
    "wof:name":"Wilhelm Beicht Gmbh",
    "wof:placetype":"venue"
},
  "geometry": {"coordinates":[6.833326,49.923504],"type":"Point"}
}