{
  "type": "Feature",
  "properties": {
    "iso:country":"DE",
    "sg:address":"Hauptstr. 81",
    "sg:city":"Wietmarschen",
    "sg:phone":"+49 5908/8147",
    "sg:postcode":"49835",
    "sg:province":"Niedersachsen",
    "wof:name":"L. Zoder",
    "wof:placetype":"venue"
},
  "geometry": {"coordinates":[7.230627,52.507748],"type":"Point"}
}