{
  "type": "Feature",
  "properties": {
    "iso:country":"DE",
    "sg:address":"Pferdestr. 21",
    "sg:city":"J\u00fcterbog",
    "sg:phone":"+49 3372/402471",
    "sg:postcode":"14913",
    "sg:province":"Brandenburg",
    "wof:name":"Wolfgang Gro\u00dfe",
    "wof:placetype":"venue"
},
  "geometry": {"coordinates":[13.077515,51.990208],"type":"Point"}
}