{
  "type": "Feature",
  "properties": {
    "iso:country":"DE",
    "sg:address":"Lessingstr. 11",
    "sg:city":"Adorf",
    "sg:phone":"+49 37423/2652",
    "sg:postcode":"08626",
    "sg:province":"Sachsen",
    "wof:name":"Trauerhilfe Heimkehr Gmbh",
    "wof:placetype":"venue"
},
  "geometry": {"coordinates":[12.255679,50.318752],"type":"Point"}
}