{
  "type": "Feature",
  "properties": {
    "iso:country":"DE",
    "sg:address":"Gro\u00dfer Riedweg 9",
    "sg:city":"Worms",
    "sg:phone":"+49 6241/935070",
    "sg:postcode":"67551",
    "sg:province":"Rheinland-Pfalz",
    "wof:name":"Keller Gmbh",
    "wof:placetype":"venue"
},
  "geometry": {"coordinates":[8.3294620514,49.6036453247],"type":"Point"}
}