{
  "type": "Feature",
  "properties": {
    "iso:country":"DE",
    "sg:address":"Leipziger Str. 120",
    "sg:city":"Chemnitz",
    "sg:phone":"+49 4937/191790",
    "sg:postcode":"09114",
    "sg:province":"Sachsen",
    "wof:name":"Securitas Gmbh Wertdienste",
    "wof:placetype":"venue"
},
  "geometry": {"coordinates":[12.889661,50.851425],"type":"Point"}
}