{
  "type": "Feature",
  "properties": {
    "iso:country":"DE",
    "sg:address":"Lilienweg 1",
    "sg:city":"Ravensburg",
    "sg:phone":"+49 751/91872",
    "sg:postcode":"88213",
    "sg:province":"Baden-W\u00fcrttemberg",
    "wof:name":"Martin Lauber",
    "wof:placetype":"venue"
},
  "geometry": {"coordinates":[9.590348,47.778358],"type":"Point"}
}