{
  "type": "Feature",
  "properties": {
    "iso:country":"DE",
    "sg:address":"Stiftstr. 16",
    "sg:city":"Luckenwalde",
    "sg:phone":"+49 3371/632001",
    "sg:postcode":"14943",
    "sg:province":"Brandenburg",
    "wof:name":"Funktaxi Michael",
    "wof:placetype":"venue"
},
  "geometry": {"coordinates":[13.160677,52.086937],"type":"Point"}
}