{
  "type": "Feature",
  "properties": {
    "iso:country":"DE",
    "sg:address":"Gartenstr. 29",
    "sg:city":"Colmberg",
    "sg:postcode":"91598",
    "sg:province":"Bayern",
    "wof:name":"Birgits Music Service",
    "wof:placetype":"venue"
},
  "geometry": {"coordinates":[10.409922,49.356228],"type":"Point"}
}