{
  "type": "Feature",
  "properties": {
    "iso:country":"DE",
    "sg:address":"Schneegl\u00f6ckchenweg 15",
    "sg:city":"Hamburg",
    "sg:phone":"+49 40/69656830",
    "sg:postcode":"22047",
    "sg:province":"Hamburg",
    "wof:name":"Lemke Und Lichtenfeld Rechtsanw\u00e4lte",
    "wof:placetype":"venue"
},
  "geometry": {"coordinates":[10.0791978836,53.5859451294],"type":"Point"}
}