{
  "type": "Feature",
  "properties": {
    "iso:country":"DE",
    "sg:address":"Dr.-Otto-Eyrich-Str. 16",
    "sg:city":"Prien",
    "sg:phone":"+49 8051/2048",
    "sg:postcode":"83209",
    "sg:province":"Bayern",
    "wof:name":"Berger",
    "wof:placetype":"venue"
},
  "geometry": {"coordinates":[12.3518228531,47.8496055603],"type":"Point"}
}