{
  "type": "Feature",
  "properties": {
    "iso:country":"DE",
    "sg:address":"Kluskampstr. 17",
    "sg:city":"Lemgo",
    "sg:phone":"+49 5261/88554",
    "sg:postcode":"32657",
    "sg:province":"Nordrhein-Westfalen",
    "wof:name":"H. Sasse",
    "wof:placetype":"venue"
},
  "geometry": {"coordinates":[8.91785,52.027531],"type":"Point"}
}