{
  "type": "Feature",
  "properties": {
    "iso:country":"DE",
    "sg:address":"Hauptstr. 28",
    "sg:city":"Sehlem",
    "sg:phone":"+49 5060/2275",
    "sg:postcode":"31196",
    "sg:province":"Niedersachsen",
    "wof:name":"Hermann Warnecke",
    "wof:placetype":"venue"
},
  "geometry": {"coordinates":[9.9747219086,52.0116271973],"type":"Point"}
}