{
  "type": "Feature",
  "properties": {
    "iso:country":"DE",
    "sg:address":"Sudetenstr. 4",
    "sg:city":"Hagelstadt",
    "sg:phone":"+49 9453/252",
    "sg:postcode":"93095",
    "sg:province":"Bayern",
    "wof:name":"Gemeindeb\u00fccherei",
    "wof:placetype":"venue"
},
  "geometry": {"coordinates":[12.218605,48.895123],"type":"Point"}
}