{
  "type": "Feature",
  "properties": {
    "iso:country":"DE",
    "sg:address":"Lemgoer Str. 3",
    "sg:city":"Blomberg",
    "sg:phone":"+49 5235/8874",
    "sg:postcode":"32825",
    "sg:province":"Nordrhein-Westfalen",
    "wof:name":"Friedrich Niederkr\u00fcger",
    "wof:placetype":"venue"
},
  "geometry": {"coordinates":[9.04487,51.953617],"type":"Point"}
}