{
  "type": "Feature",
  "properties": {
    "iso:country":"DE",
    "sg:address":"Klostergasse 2 b",
    "sg:city":"Saalfeld",
    "sg:postcode":"07318",
    "sg:province":"Th\u00fcringen",
    "wof:name":"Bestattungen Und Trauerhilfe Velke Gmbh",
    "wof:placetype":"venue"
},
  "geometry": {"coordinates":[11.357886,50.648907],"type":"Point"}
}