{
  "type": "Feature",
  "properties": {
    "iso:country":"DE",
    "sg:address":"Albert-Schweitzer-Str. 16",
    "sg:city":"Kaufungen",
    "sg:phone":"+49 5605/6311",
    "sg:postcode":"34260",
    "sg:province":"Hessen",
    "wof:name":"Thomas Hohbein",
    "wof:placetype":"venue"
},
  "geometry": {"coordinates":[9.6001567841,51.2815742493],"type":"Point"}
}