{
  "type": "Feature",
  "properties": {
    "iso:country":"DE",
    "sg:address":"Obernstr. 16",
    "sg:city":"Bremen",
    "sg:phone":"+49 421/3379445",
    "sg:postcode":"28195",
    "sg:province":"Bremen",
    "wof:name":"Foot Locker Germany Gmbh",
    "wof:placetype":"venue"
},
  "geometry": {"coordinates":[8.805923,53.076721],"type":"Point"}
}