{
  "type": "Feature",
  "properties": {
    "iso:country":"DE",
    "sg:address":"Haldenloh 1",
    "sg:city":"Welden",
    "sg:phone":"+49 8293/221",
    "sg:postcode":"86465",
    "sg:province":"Bayern",
    "wof:name":"Otto Sch\u00e4fer",
    "wof:placetype":"venue"
},
  "geometry": {"coordinates":[10.6708784103,48.4644851685],"type":"Point"}
}