{
  "type": "Feature",
  "properties": {
    "iso:country":"DE",
    "sg:address":"Lindenstr. 10",
    "sg:city":"Bersenbr\u00fcck",
    "sg:phone":"+49 5439/92256",
    "sg:postcode":"49593",
    "sg:province":"Niedersachsen",
    "wof:name":"Steinkamp Immobilienmakler",
    "wof:placetype":"venue"
},
  "geometry": {"coordinates":[7.9448308945,52.5547180176],"type":"Point"}
}