{
  "type": "Feature",
  "properties": {
    "iso:country":"DE",
    "sg:address":"Ziegeleistr. 6",
    "sg:city":"Tutzing",
    "sg:phone":"+49 8158/99590",
    "sg:postcode":"82327",
    "sg:province":"Bayern",
    "wof:name":"Pemas Auto- Und Zweiradzubeh\u00f6r Gmbh",
    "wof:placetype":"venue"
},
  "geometry": {"coordinates":[11.2642679214,47.8959579468],"type":"Point"}
}