{
  "type": "Feature",
  "properties": {
    "iso:country":"DE",
    "sg:address":"Clara-Zetkin-Str. 33",
    "sg:city":"Oschersleben",
    "sg:phone":"+49 3949/4224",
    "sg:postcode":"39387",
    "sg:province":"Sachsen-Anhalt",
    "wof:name":"Walter Sch\u00f6nborn",
    "wof:placetype":"venue"
},
  "geometry": {"coordinates":[11.2197885513,52.0343933105],"type":"Point"}
}