{
  "type": "Feature",
  "properties": {
    "iso:country":"DE",
    "sg:address":"Wewerstr. 23",
    "sg:city":"Paderborn",
    "sg:phone":"+49 5254/60532",
    "sg:postcode":"33106",
    "sg:province":"Nordrhein-Westfalen",
    "wof:name":"Markus Happe Bedachungen Gmbh",
    "wof:placetype":"venue"
},
  "geometry": {"coordinates":[8.69274,51.727661],"type":"Point"}
}