{
  "type": "Feature",
  "properties": {
    "iso:country":"DE",
    "sg:address":"Sackgasse 28",
    "sg:city":"Stotternheim",
    "sg:phone":"+49 36204/70271",
    "sg:postcode":"99195",
    "sg:province":"Th\u00fcringen",
    "wof:name":"G. K\u00f6hler",
    "wof:placetype":"venue"
},
  "geometry": {"coordinates":[11.040652,51.055805],"type":"Point"}
}