{
  "type": "Feature",
  "properties": {
    "iso:country":"DE",
    "sg:address":"Kronacher Str. 5",
    "sg:city":"Ludwigsstadt",
    "sg:phone":"+49 9263/7886",
    "sg:postcode":"96337",
    "sg:province":"Bayern",
    "wof:name":"Frankenwaldgrillstube",
    "wof:placetype":"venue"
},
  "geometry": {"coordinates":[11.3896274567,50.4849586487],"type":"Point"}
}