{
  "type": "Feature",
  "properties": {
    "iso:country":"DE",
    "sg:address":"Schlo\u00dfstr. 15",
    "sg:city":"Hohenstein",
    "sg:phone":"+49 6120/4207",
    "sg:postcode":"65329",
    "sg:province":"Hessen",
    "wof:name":"Remo Malnar Architekt",
    "wof:placetype":"venue"
},
  "geometry": {"coordinates":[8.118638,50.228931],"type":"Point"}
}