{
  "type": "Feature",
  "properties": {
    "iso:country":"DE",
    "sg:address":"Schulstr. 13",
    "sg:city":"Gachenbach",
    "sg:postcode":"86565",
    "sg:province":"Bayern",
    "wof:name":"Pm Baub\u00fcro Gmbh",
    "wof:placetype":"venue"
},
  "geometry": {"coordinates":[11.230753,48.524864],"type":"Point"}
}