{
  "type": "Feature",
  "properties": {
    "iso:country":"DE",
    "sg:address":"Am S\u00fcnder 21",
    "sg:city":"Tiefthal",
    "sg:phone":"+49 36201/86876",
    "sg:postcode":"99189",
    "sg:province":"Th\u00fcringen",
    "wof:name":"Hauskrankenpflege Ines",
    "wof:placetype":"venue"
},
  "geometry": {"coordinates":[10.951114,51.018185],"type":"Point"}
}