{
  "type": "Feature",
  "properties": {
    "iso:country":"DE",
    "sg:address":"Gro\u00df Breesener Str. 69a",
    "sg:city":"Guben",
    "sg:phone":"+49 3561/431353",
    "sg:postcode":"03172",
    "sg:province":"Brandenburg",
    "wof:name":"D. Grimm",
    "wof:placetype":"venue"
},
  "geometry": {"coordinates":[14.7018413544,51.9833831787],"type":"Point"}
}