{
  "type": "Feature",
  "properties": {
    "iso:country":"DE",
    "sg:address":"Schulgutweg 21",
    "sg:city":"Auerbach",
    "sg:postcode":"09392",
    "sg:province":"Sachsen",
    "wof:name":"E & V Forst-service Gmbh",
    "wof:placetype":"venue"
},
  "geometry": {"coordinates":[12.9165792465,50.6857757568],"type":"Point"}
}