{
  "type": "Feature",
  "properties": {
    "iso:country":"DE",
    "sg:address":"Gewann Birkenrain 5",
    "sg:city":"Winnenden",
    "sg:phone":"+49 7195/174060",
    "sg:postcode":"71364",
    "sg:province":"Baden-W\u00fcrttemberg",
    "wof:name":"G. Bosch Immobilienmakler",
    "wof:placetype":"venue"
},
  "geometry": {"coordinates":[9.3951206207,48.8760757446],"type":"Point"}
}