{
  "type": "Feature",
  "properties": {
    "iso:country":"DE",
    "sg:address":"Untere Ohlingerstr. 20",
    "sg:city":"L\u00fcneburg",
    "sg:phone":"+49 4131/403324",
    "sg:postcode":"21335",
    "sg:province":"Niedersachsen",
    "wof:name":"Heinz Henschke Architekt",
    "wof:placetype":"venue"
},
  "geometry": {"coordinates":[10.402874,53.248455],"type":"Point"}
}