{
  "type": "Feature",
  "properties": {
    "iso:country":"DE",
    "sg:address":"Rudolf-Diesel-Str. 10 b",
    "sg:city":"Neustadt",
    "sg:phone":"+49 9161/62997",
    "sg:postcode":"91413",
    "sg:province":"Bayern",
    "wof:name":"Uwe Kerschbaum Gmbh",
    "wof:placetype":"venue"
},
  "geometry": {"coordinates":[10.637064,49.578056],"type":"Point"}
}