{
  "type": "Feature",
  "properties": {
    "iso:country":"DE",
    "sg:address":"Schulstr.",
    "sg:city":"Senftenberg",
    "sg:postcode":"01968",
    "sg:province":"Brandenburg",
    "wof:name":"R. B\u00e4de",
    "wof:placetype":"venue"
},
  "geometry": {"coordinates":[13.995254,51.517548],"type":"Point"}
}