{
  "type": "Feature",
  "properties": {
    "iso:country":"DE",
    "sg:address":"Niederfeld",
    "sg:city":"Binzen",
    "sg:phone":"+49 7621/669545",
    "sg:postcode":"79589",
    "sg:province":"Baden-W\u00fcrttemberg",
    "wof:name":"A. Schmitt",
    "wof:placetype":"venue"
},
  "geometry": {"coordinates":[7.607645,47.634781],"type":"Point"}
}