{
  "type": "Feature",
  "properties": {
    "iso:country":"DE",
    "sg:address":"Mozartweg 3",
    "sg:city":"Darmstadt",
    "sg:phone":"+49 6151/74528",
    "sg:postcode":"64287",
    "sg:province":"Hessen",
    "wof:name":"Martin Dehnhard Architekt Und Ingenieur",
    "wof:placetype":"venue"
},
  "geometry": {"coordinates":[8.678646,49.883419],"type":"Point"}
}