{
  "type": "Feature",
  "properties": {
    "iso:country":"DE",
    "sg:address":"Erlich 10",
    "sg:city":"Bad Steben",
    "sg:phone":"+49 9288/1717",
    "sg:postcode":"95138",
    "sg:province":"Bayern",
    "wof:name":"G\u00e4stehaus Haus Parkblick",
    "wof:placetype":"venue"
},
  "geometry": {"coordinates":[11.634806633,50.3681945801],"type":"Point"}
}