{
  "type": "Feature",
  "properties": {
    "iso:country":"DE",
    "sg:address":"Liebst\u00f6ckelweg 11",
    "sg:city":"Berlin",
    "sg:phone":"+49 30/4319376",
    "sg:postcode":"13503",
    "sg:province":"Berlin",
    "wof:name":"Wolfgang Krumnow",
    "wof:placetype":"venue"
},
  "geometry": {"coordinates":[13.2382984161,52.617401123],"type":"Point"}
}