{
  "type": "Feature",
  "properties": {
    "iso:country":"DE",
    "sg:address":"Byhlener Str. 1",
    "sg:city":"Cottbus",
    "sg:postcode":"03044",
    "sg:province":"Brandenburg",
    "wof:name":"Alpha Bautr\u00e4gergesellschaft Mbh",
    "wof:placetype":"venue"
},
  "geometry": {"coordinates":[14.326318,51.784512],"type":"Point"}
}