{
  "type": "Feature",
  "properties": {
    "iso:country":"DE",
    "sg:address":"Laplacestr. 1",
    "sg:city":"M\u00fcnchen",
    "sg:phone":"+49 89/981807",
    "sg:postcode":"81679",
    "sg:province":"Bayern",
    "wof:name":"Ophoff Treuhand- Und Verwaltungsgesellschaft Mbh",
    "wof:placetype":"venue"
},
  "geometry": {"coordinates":[11.6049766541,48.1473731995],"type":"Point"}
}