{
  "type": "Feature",
  "properties": {
    "iso:country":"DE",
    "sg:address":"Wallnerl\u00e4nde 9",
    "sg:city":"Deggendorf",
    "sg:phone":"+49 991/371000",
    "sg:postcode":"94469",
    "sg:province":"Bayern",
    "wof:name":"Zweckverband Donau-hafen",
    "wof:placetype":"venue"
},
  "geometry": {"coordinates":[12.9707069397,48.8164558411],"type":"Point"}
}