{
  "type": "Feature",
  "properties": {
    "iso:country":"DE",
    "sg:address":"Bachstr. 4",
    "sg:city":"Bad Breisig",
    "sg:phone":"+49 2633/471857",
    "sg:postcode":"53498",
    "sg:province":"Rheinland-Pfalz",
    "wof:name":"Ratsst\u00fcbchen",
    "wof:placetype":"venue"
},
  "geometry": {"coordinates":[7.2979869843,50.5097923279],"type":"Point"}
}