{
  "type": "Feature",
  "properties": {
    "iso:country":"DE",
    "sg:address":"Am Schlehenrech 31",
    "sg:city":"Reinheim",
    "sg:phone":"+49 6162/6205",
    "sg:postcode":"64354",
    "sg:province":"Hessen",
    "wof:name":"Stiebel Eltron & Co. Kg",
    "wof:placetype":"venue"
},
  "geometry": {"coordinates":[8.8461551666,49.8201026917],"type":"Point"}
}