{
  "type": "Feature",
  "properties": {
    "iso:country":"DE",
    "sg:address":"Ohlenfeldstr. 2",
    "sg:city":"Boppard",
    "sg:phone":"+49 6742/80000",
    "sg:postcode":"56154",
    "sg:province":"Rheinland-Pfalz",
    "wof:name":"Bukuma Krau\u00df Gmbh",
    "wof:placetype":"venue"
},
  "geometry": {"coordinates":[7.539694,50.215443],"type":"Point"}
}