{
  "type": "Feature",
  "properties": {
    "iso:country":"DE",
    "sg:address":"St\u00fcffeleck 6",
    "sg:city":"Hamburg",
    "sg:phone":"+49 40/6045305",
    "sg:postcode":"22359",
    "sg:province":"Hamburg",
    "wof:name":"A. Timmermann",
    "wof:placetype":"venue"
},
  "geometry": {"coordinates":[10.1428632736,53.6700325012],"type":"Point"}
}