{
  "type": "Feature",
  "properties": {
    "iso:country":"DE",
    "sg:address":"K\u00fcferstr. 56",
    "sg:city":"Willich",
    "sg:phone":"+49 2154/42074",
    "sg:postcode":"47877",
    "sg:province":"Nordrhein-Westfalen",
    "wof:name":"Heinrich Kreutzer",
    "wof:placetype":"venue"
},
  "geometry": {"coordinates":[6.557811,51.261414],"type":"Point"}
}