{
  "type": "Feature",
  "properties": {
    "iso:country":"DE",
    "sg:address":"Deisterallee 6",
    "sg:city":"Hameln",
    "sg:phone":"+49 5151/7419",
    "sg:postcode":"31785",
    "sg:province":"Niedersachsen",
    "wof:name":"Aug. Bicker Gmbh & Co.",
    "wof:placetype":"venue"
},
  "geometry": {"coordinates":[9.362428,52.10376],"type":"Point"}
}