{
  "type": "Feature",
  "properties": {
    "iso:country":"DE",
    "sg:address":"Otto-Hahn-Str. 27",
    "sg:city":"Borken",
    "sg:phone":"+49 2861/7643",
    "sg:postcode":"46325",
    "sg:province":"Nordrhein-Westfalen",
    "wof:name":"K\u00f6tters & Finke Haus- Hof Agrar-ger\u00e4te Gmbh",
    "wof:placetype":"venue"
},
  "geometry": {"coordinates":[6.8722448349,51.8565826416],"type":"Point"}
}