{
  "type": "Feature",
  "properties": {
    "iso:country":"DE",
    "sg:address":"Saarlandstr. 23",
    "sg:city":"Villingen-Schwenningen",
    "sg:phone":"+49 7721/24746",
    "sg:postcode":"78050",
    "sg:province":"Baden-W\u00fcrttemberg",
    "wof:name":"Praxis Dr. Med. Luft",
    "wof:placetype":"venue"
},
  "geometry": {"coordinates":[8.4513254166,48.0553398132],"type":"Point"}
}