{
  "type": "Feature",
  "properties": {
    "iso:country":"DE",
    "sg:address":"Palandsm\u00fchlenw. 14a",
    "sg:city":"Langelsheim",
    "sg:phone":"+49 4953/2691020",
    "sg:postcode":"38685",
    "sg:province":"Niedersachsen",
    "wof:name":"Kalesse Tiefkuehlkost Gmbh",
    "wof:placetype":"venue"
},
  "geometry": {"coordinates":[10.3639974594,51.9659996033],"type":"Point"}
}