{
  "type": "Feature",
  "properties": {
    "iso:country":"DE",
    "sg:address":"Wei\u00dfiger Str. 50",
    "sg:city":"Dresden",
    "sg:postcode":"01328",
    "sg:province":"Sachsen",
    "wof:name":"Agrarproduktionsgesellschaft Sch\u00f6nfelder Hochland",
    "wof:placetype":"venue"
},
  "geometry": {"coordinates":[13.9111671448,51.0447158813],"type":"Point"}
}