{
  "type": "Feature",
  "properties": {
    "iso:country":"DE",
    "sg:address":"Hellerhofstrasse 26",
    "sg:city":"Frankfurt",
    "sg:phone":"+49 69/97358984",
    "sg:postcode":"60327",
    "sg:province":"Hessen",
    "wof:name":"Urlaub Weltweit",
    "wof:placetype":"venue"
},
  "geometry": {"coordinates":[8.645808,50.10651],"type":"Point"}
}