{
  "type": "Feature",
  "properties": {
    "iso:country":"DE",
    "sg:address":"Okenstr. 103",
    "sg:city":"Offenburg",
    "sg:phone":"+49 4978/192270",
    "sg:postcode":"77652",
    "sg:province":"Baden-W\u00fcrttemberg",
    "wof:name":"Philipp Kirsch Gmbh",
    "wof:placetype":"venue"
},
  "geometry": {"coordinates":[7.947348,48.483978],"type":"Point"}
}