{
  "type": "Feature",
  "properties": {
    "iso:country":"DE",
    "sg:address":"Kramerstr. 23",
    "sg:city":"Memmingen",
    "sg:phone":"+49 8331/82315",
    "sg:postcode":"87700",
    "sg:province":"Bayern",
    "wof:name":"Eva Koch Gmbh",
    "wof:placetype":"venue"
},
  "geometry": {"coordinates":[10.182041,47.985119],"type":"Point"}
}