{
  "type": "Feature",
  "properties": {
    "iso:country":"DE",
    "sg:address":"Gutenbergstr. 4",
    "sg:city":"Harsewinkel",
    "sg:phone":"+49 2588/93040",
    "sg:postcode":"33428",
    "sg:province":"Nordrhein-Westfalen",
    "wof:name":"Gebr. Wippenhohn Papier- Und Schreibwaren",
    "wof:placetype":"venue"
},
  "geometry": {"coordinates":[8.1493272781,51.9747276306],"type":"Point"}
}