{
  "type": "Feature",
  "properties": {
    "iso:country":"DE",
    "sg:address":"Gr\u00f6nwohlder Weg 8",
    "sg:city":"Nehms",
    "sg:phone":"+49 4555/866",
    "sg:postcode":"23813",
    "sg:province":"Schleswig-Holstein",
    "wof:name":"Heinrich Krempien",
    "wof:placetype":"venue"
},
  "geometry": {"coordinates":[10.362533,54.026157],"type":"Point"}
}