{
  "type": "Feature",
  "properties": {
    "iso:country":"DE",
    "sg:address":"Luisenstr. 16",
    "sg:city":"Alsdorf",
    "sg:phone":"+49 2404/82957",
    "sg:postcode":"52477",
    "sg:province":"Nordrhein-Westfalen",
    "wof:name":"Prosoft Produktion Und Vertrieb Von Hard- Und",
    "wof:placetype":"venue"
},
  "geometry": {"coordinates":[6.1657691002,50.8736495972],"type":"Point"}
}