{
  "type": "Feature",
  "properties": {
    "iso:country":"DE",
    "sg:address":"Krottnaurerstr. 54",
    "sg:city":"Berlin",
    "sg:phone":"+49 30/8033967",
    "sg:postcode":"14129",
    "sg:province":"Berlin",
    "wof:name":"Harry Schnitger",
    "wof:placetype":"venue"
},
  "geometry": {"coordinates":[13.209158,52.429855],"type":"Point"}
}