{
  "type": "Feature",
  "properties": {
    "iso:country":"DE",
    "sg:address":"Zum Niederwald-Denkmal 14",
    "sg:city":"R\u00fcdesheim am Rhein",
    "sg:phone":"+49 6722/910150",
    "sg:postcode":"65385",
    "sg:province":"Hessen",
    "wof:name":"Georg Mahr Rechtsanwalt",
    "wof:placetype":"venue"
},
  "geometry": {"coordinates":[7.9250102043,49.9831428528],"type":"Point"}
}