{
  "type": "Feature",
  "properties": {
    "iso:country":"DE",
    "sg:address":"An der Markthalle 11",
    "sg:city":"Chemnitz",
    "sg:phone":"+49 371/671551",
    "sg:postcode":"09111",
    "sg:province":"Sachsen",
    "wof:name":"Roba Baustoffe Gmbh",
    "wof:placetype":"venue"
},
  "geometry": {"coordinates":[12.9163970947,50.8369445801],"type":"Point"}
}