{
  "type": "Feature",
  "properties": {
    "iso:country":"DE",
    "sg:address":"Aachener Str. 1009",
    "sg:city":"K\u00f6ln",
    "sg:phone":"+49 221/486897",
    "sg:postcode":"50858",
    "sg:province":"Nordrhein-Westfalen",
    "wof:name":"Wolfgang Bresinski",
    "wof:placetype":"venue"
},
  "geometry": {"coordinates":[6.8653759956,50.937625885],"type":"Point"}
}