{
  "type": "Feature",
  "properties": {
    "iso:country":"DE",
    "sg:address":"Dorfstr. 4",
    "sg:city":"Puchheim",
    "sg:phone":"+49 89/802510",
    "sg:postcode":"82178",
    "sg:province":"Bayern",
    "wof:name":"Katholisches Pfarramt Mari\u00e4 Himmelfahrt",
    "wof:placetype":"venue"
},
  "geometry": {"coordinates":[11.3483791351,48.1473121643],"type":"Point"}
}