{
  "type": "Feature",
  "properties": {
    "iso:country":"DE",
    "sg:address":"Lindwurmstr. 153",
    "sg:city":"M\u00fcnchen",
    "sg:phone":"+49 89/771052",
    "sg:postcode":"80337",
    "sg:province":"Bayern",
    "wof:name":"Brack-hotel-garni Gmbh",
    "wof:placetype":"venue"
},
  "geometry": {"coordinates":[11.5513648987,48.1258392334],"type":"Point"}
}