{
  "type": "Feature",
  "properties": {
    "iso:country":"DE",
    "sg:address":"Landauer Str. 23",
    "sg:city":"Bad Bergzabern",
    "sg:phone":"+49 6343/93390",
    "sg:postcode":"76887",
    "sg:province":"Rheinland-Pfalz",
    "wof:name":"Stadtwerke Bad Bergzabern Gmbh",
    "wof:placetype":"venue"
},
  "geometry": {"coordinates":[8.009714,49.105583],"type":"Point"}
}