{
  "type": "Feature",
  "properties": {
    "iso:country":"DE",
    "sg:address":"Waldstr. 10",
    "sg:city":"S\u00fclstorf",
    "sg:phone":"+49 3865/287",
    "sg:postcode":"19077",
    "sg:province":"Mecklenburg-Vorpommern",
    "wof:name":"W. Oldenburg",
    "wof:placetype":"venue"
},
  "geometry": {"coordinates":[11.4030885696,53.5292816162],"type":"Point"}
}