{
  "type": "Feature",
  "properties": {
    "iso:country":"DE",
    "sg:address":"Hohstattstr. 9",
    "sg:city":"H\u00fcffenhardt",
    "sg:phone":"+49 6268/316",
    "sg:postcode":"74928",
    "sg:province":"Baden-W\u00fcrttemberg",
    "wof:name":"Gerd Hei\u00df",
    "wof:placetype":"venue"
},
  "geometry": {"coordinates":[9.0814094543,49.292263031],"type":"Point"}
}