{
  "type": "Feature",
  "properties": {
    "iso:country":"DE",
    "sg:address":"Leopoldstr. 107-109",
    "sg:city":"Eggenstein-Leopoldshafen",
    "sg:phone":"+49 7247/7247",
    "sg:postcode":"76344",
    "sg:province":"Baden-W\u00fcrttemberg",
    "wof:name":"Karl Dreher Kg",
    "wof:placetype":"venue"
},
  "geometry": {"coordinates":[8.4039669037,49.0957183838],"type":"Point"}
}