{
  "type": "Feature",
  "properties": {
    "iso:country":"DE",
    "sg:address":"Marktplatz 4",
    "sg:city":"Weil im Sch\u00f6nbuch",
    "sg:phone":"+49 7157/61002",
    "sg:postcode":"71093",
    "sg:province":"Baden-W\u00fcrttemberg",
    "wof:name":"Sch\u00f6nbuch Collection M\u00f6belmarketing Gmbh",
    "wof:placetype":"venue"
},
  "geometry": {"coordinates":[9.060897,48.620964],"type":"Point"}
}