{
  "type": "Feature",
  "properties": {
    "iso:country":"DE",
    "sg:address":"Am Triftpark 31",
    "sg:city":"Berlin",
    "sg:postcode":"13437",
    "sg:province":"Berlin",
    "wof:name":"Verein F\u00fcr Wasser-boden",
    "wof:placetype":"venue"
},
  "geometry": {"coordinates":[13.3183050156,52.5909423828],"type":"Point"}
}