{
  "type": "Feature",
  "properties": {
    "iso:country":"DE",
    "sg:address":"Spitalhofstr. 99",
    "sg:city":"Passau",
    "sg:phone":"+49 851/95153",
    "sg:postcode":"94032",
    "sg:province":"Bayern",
    "wof:name":"Elro J. Rosenberger Elektro- Fachgrosshandels-gmbh",
    "wof:placetype":"venue"
},
  "geometry": {"coordinates":[13.421179,48.570183],"type":"Point"}
}