{
  "type": "Feature",
  "properties": {
    "iso:country":"DE",
    "sg:address":"Marktstr. 52",
    "sg:city":"Pasewalk",
    "sg:phone":"+49 3973/431356",
    "sg:postcode":"17309",
    "sg:province":"Mecklenburg-Vorpommern",
    "wof:name":"Europ\u00e4isches Reiseb\u00fcro Gmbh Reisewelt",
    "wof:placetype":"venue"
},
  "geometry": {"coordinates":[13.9911403656,53.5074310303],"type":"Point"}
}