{
  "type": "Feature",
  "properties": {
    "iso:country":"DE",
    "sg:address":"Siemensstr. 2",
    "sg:city":"Notzingen",
    "sg:phone":"+49 7023/70090",
    "sg:postcode":"73274",
    "sg:province":"Baden-W\u00fcrttemberg",
    "wof:name":"Lasercomb Laser Combination Systems Verwaltungs- Gmbh",
    "wof:placetype":"venue"
},
  "geometry": {"coordinates":[9.452379,48.669205],"type":"Point"}
}