{
  "type": "Feature",
  "properties": {
    "iso:country":"DE",
    "sg:address":"Steuerwalder Str. 97",
    "sg:city":"Hildesheim",
    "sg:phone":"+49 5121/59885",
    "sg:postcode":"31137",
    "sg:province":"Niedersachsen",
    "wof:name":"Dat Pr\u00fcf- Und Sch\u00e4tzungsstelle",
    "wof:placetype":"venue"
},
  "geometry": {"coordinates":[9.942357,52.165318],"type":"Point"}
}