{
  "type": "Feature",
  "properties": {
    "iso:country":"DE",
    "sg:address":"Freiligrathstr. 9",
    "sg:city":"Radebeul",
    "sg:postcode":"01445",
    "sg:province":"Sachsen",
    "wof:name":"Hg- Gmbh",
    "wof:placetype":"venue"
},
  "geometry": {"coordinates":[13.682913,51.10347],"type":"Point"}
}