{
  "type": "Feature",
  "properties": {
    "iso:country":"DE",
    "sg:address":"Echinger Str. 23",
    "sg:city":"Neufahrn",
    "sg:phone":"+49 8165/4081",
    "sg:postcode":"85375",
    "sg:province":"Bayern",
    "wof:name":"Hotel Krone",
    "wof:placetype":"venue"
},
  "geometry": {"coordinates":[11.658241272,48.3110198975],"type":"Point"}
}