{
  "type": "Feature",
  "properties": {
    "iso:country":"DE",
    "sg:address":"M\u00fchlenstr. 5",
    "sg:city":"Oldenburg",
    "sg:phone":"+49 441/14400",
    "sg:postcode":"26122",
    "sg:province":"Niedersachsen",
    "wof:name":"Johann Jeske",
    "wof:placetype":"venue"
},
  "geometry": {"coordinates":[8.216755,53.139355],"type":"Point"}
}