{
  "type": "Feature",
  "properties": {
    "iso:country":"DE",
    "sg:address":"Gro\u00dfflecken 4",
    "sg:city":"Neum\u00fcnster",
    "sg:phone":"+49 4321/44691",
    "sg:postcode":"24534",
    "sg:province":"Schleswig-Holstein",
    "wof:name":"Nieswandt Vertriebs- Gesellschaft F\u00fcr Singer",
    "wof:placetype":"venue"
},
  "geometry": {"coordinates":[9.9860496521,54.0727882385],"type":"Point"}
}