{
  "type": "Feature",
  "properties": {
    "iso:country":"DE",
    "sg:address":"Passauer Str. 62",
    "sg:city":"Winzer",
    "sg:phone":"+49 9901/2040",
    "sg:postcode":"94577",
    "sg:province":"Bayern",
    "wof:name":"Raiffeisenbank Winzer -- Hengersberg Eg",
    "wof:placetype":"venue"
},
  "geometry": {"coordinates":[13.074035,48.724449],"type":"Point"}
}