{
  "type": "Feature",
  "properties": {
    "iso:country":"DE",
    "sg:address":"Lotter Str. 1",
    "sg:city":"Lotte",
    "sg:postcode":"49504",
    "sg:province":"Nordrhein-Westfalen",
    "wof:name":"Elke Jannaber Beerdigungs- Institut Gmbh",
    "wof:placetype":"venue"
},
  "geometry": {"coordinates":[7.91561,52.274998],"type":"Point"}
}