{
  "type": "Feature",
  "properties": {
    "iso:country":"DE",
    "sg:address":"Windberg",
    "sg:city":"Kirchroth",
    "sg:postcode":"94356",
    "sg:province":"Bayern",
    "wof:name":"Klosterbibliothek Abtei Windberg",
    "wof:placetype":"venue"
},
  "geometry": {"coordinates":[12.54929,48.969139],"type":"Point"}
}