{
  "type": "Feature",
  "properties": {
    "iso:country":"DE",
    "sg:address":"Altk\u00f6nigstr. 4a",
    "sg:city":"K\u00f6nigstein",
    "sg:postcode":"61462",
    "sg:province":"Hessen",
    "wof:name":"Bath Room Badgestaltung Gmbh",
    "wof:placetype":"venue"
},
  "geometry": {"coordinates":[8.4673166275,50.1883544922],"type":"Point"}
}