{
  "type": "Feature",
  "properties": {
    "iso:country":"DE",
    "sg:address":"Strother Str. 6",
    "sg:city":"Korbach",
    "sg:phone":"+49 5631/3539",
    "sg:postcode":"34497",
    "sg:province":"Hessen",
    "wof:name":"Waffen - Brand",
    "wof:placetype":"venue"
},
  "geometry": {"coordinates":[8.8764886856,51.2733039856],"type":"Point"}
}