{
  "type": "Feature",
  "properties": {
    "iso:country":"DE",
    "sg:address":"Reeser Landstr. 14",
    "sg:city":"Wesel",
    "sg:phone":"+49 281/21000",
    "sg:postcode":"46483",
    "sg:province":"Nordrhein-Westfalen",
    "wof:name":"Hotel Zur Aue",
    "wof:placetype":"venue"
},
  "geometry": {"coordinates":[6.610145092,51.6633987427],"type":"Point"}
}