{
  "type": "Feature",
  "properties": {
    "iso:country":"DE",
    "sg:address":"Ingelheimer Str. 3",
    "sg:city":"Limbach-Oberfrohna",
    "sg:phone":"+49 3722/71990",
    "sg:postcode":"09212",
    "sg:province":"Sachsen",
    "wof:name":"J\u00fcrgen Schumacher Steuerberatungs Gmbh",
    "wof:placetype":"venue"
},
  "geometry": {"coordinates":[12.769867897,50.8557357788],"type":"Point"}
}