{
  "type": "Feature",
  "properties": {
    "iso:country":"DE",
    "sg:address":"Kleine Str. 11",
    "sg:city":"Magdeburg",
    "sg:postcode":"39108",
    "sg:province":"Sachsen-Anhalt",
    "wof:name":"Dr. Med. Bernd Dossow",
    "wof:placetype":"venue"
},
  "geometry": {"coordinates":[11.614769,52.124798],"type":"Point"}
}