{
  "type": "Feature",
  "properties": {
    "iso:country":"DE",
    "sg:address":"Rolandplatz 2",
    "sg:city":"Karlsruhe",
    "sg:phone":"+49 721/986890",
    "sg:postcode":"76135",
    "sg:province":"Baden-W\u00fcrttemberg",
    "wof:name":"Dv Direkt Beratungsges. F\u00fcr Informationssverarbeitung",
    "wof:placetype":"venue"
},
  "geometry": {"coordinates":[8.3765087128,48.9865531921],"type":"Point"}
}