{
  "type": "Feature",
  "properties": {
    "iso:country":"DE",
    "sg:address":"Parkplatz an der Post",
    "sg:city":"Tecklenburg",
    "sg:phone":"+49 5482/264",
    "sg:postcode":"49545",
    "sg:province":"Nordrhein-Westfalen",
    "wof:name":"Prigge",
    "wof:placetype":"venue"
},
  "geometry": {"coordinates":[7.8152852058,52.2196807861],"type":"Point"}
}