{
  "type": "Feature",
  "properties": {
    "iso:country":"DE",
    "sg:address":"Siemensstr. 62",
    "sg:city":"Korntal-M\u00fcnchingen",
    "sg:phone":"+49 7150/956262",
    "sg:postcode":"70825",
    "sg:province":"Baden-W\u00fcrttemberg",
    "wof:name":"Michelin Reifenwerke Kgaa",
    "wof:placetype":"venue"
},
  "geometry": {"coordinates":[9.113147,48.852119],"type":"Point"}
}