{
  "type": "Feature",
  "properties": {
    "iso:country":"DE",
    "sg:address":"Bremer Str. 48",
    "sg:city":"Riede",
    "sg:phone":"+49 4294/285",
    "sg:postcode":"27339",
    "sg:province":"Niedersachsen",
    "wof:name":"Friedel Dahme",
    "wof:placetype":"venue"
},
  "geometry": {"coordinates":[8.939434,52.970531],"type":"Point"}
}