{
  "type": "Feature",
  "properties": {
    "iso:country":"DE",
    "sg:address":"Bei den Kornschrannen 5",
    "sg:city":"N\u00f6rdlingen",
    "sg:postcode":"86720",
    "sg:province":"Bayern",
    "wof:name":"Der Reiseb\u00fcro An Der Alten Schranne Gmbh",
    "wof:placetype":"venue"
},
  "geometry": {"coordinates":[10.4910287857,48.8517951965],"type":"Point"}
}