{
  "type": "Feature",
  "properties": {
    "iso:country":"DE",
    "sg:address":"Karl-Simrock-Str. 7",
    "sg:city":"Erkrath",
    "sg:phone":"+49 211/253198",
    "sg:postcode":"40699",
    "sg:province":"Nordrhein-Westfalen",
    "wof:name":"A. Weller",
    "wof:placetype":"venue"
},
  "geometry": {"coordinates":[6.9197,51.20332],"type":"Point"}
}