{
  "type": "Feature",
  "properties": {
    "iso:country":"DE",
    "sg:address":"Kleberstr. 2",
    "sg:city":"Bamberg",
    "sg:phone":"+49 951/27069",
    "sg:postcode":"96047",
    "sg:province":"Bayern",
    "wof:name":"Cornelia Klein",
    "wof:placetype":"venue"
},
  "geometry": {"coordinates":[10.890691,49.895576],"type":"Point"}
}