{
  "type": "Feature",
  "properties": {
    "iso:country":"DE",
    "sg:address":"Dr.-Wigger-Str. 8",
    "sg:city":"Garmisch-Partenkirchen",
    "sg:postcode":"82467",
    "sg:province":"Bayern",
    "wof:name":"H. Stein Krankenhausbedarf",
    "wof:placetype":"venue"
},
  "geometry": {"coordinates":[11.114714,47.49033],"type":"Point"}
}