{
  "type": "Feature",
  "properties": {
    "iso:country":"DE",
    "sg:address":"Hauptstr. 406",
    "sg:city":"Krefeld",
    "sg:phone":"+49 2151/969960",
    "sg:postcode":"47809",
    "sg:province":"Nordrhein-Westfalen",
    "wof:name":"Big-bike Gmbh Krefeld",
    "wof:placetype":"venue"
},
  "geometry": {"coordinates":[6.630081,51.315987],"type":"Point"}
}