{
  "type": "Feature",
  "properties": {
    "iso:country":"DE",
    "sg:address":"Wilhelm-von-Scholz-Weg 2",
    "sg:city":"Konstanz",
    "sg:phone":"+49 7531/61163",
    "sg:postcode":"78464",
    "sg:province":"Baden-W\u00fcrttemberg",
    "wof:name":"Strandbad Jakob",
    "wof:placetype":"venue"
},
  "geometry": {"coordinates":[9.2087583542,47.6649398804],"type":"Point"}
}