{
  "type": "Feature",
  "properties": {
    "iso:country":"DE",
    "sg:address":"Ismaninger Str. 30",
    "sg:city":"Moosinning",
    "sg:phone":"+49 8123/350",
    "sg:postcode":"85452",
    "sg:province":"Bayern",
    "wof:name":"K. Hermann Ingenieur",
    "wof:placetype":"venue"
},
  "geometry": {"coordinates":[11.8279447556,48.2762565613],"type":"Point"}
}