{
  "type": "Feature",
  "properties": {
    "iso:country":"DE",
    "sg:address":"Lindhorstweg 36",
    "sg:city":"Berlin",
    "sg:postcode":"12487",
    "sg:province":"Berlin",
    "wof:name":"Vicon Software Service Gmbh",
    "wof:placetype":"venue"
},
  "geometry": {"coordinates":[13.502203,52.440136],"type":"Point"}
}