{
  "type": "Feature",
  "properties": {
    "iso:country":"DE",
    "sg:address":"Hennebergstr. 18",
    "sg:city":"M\u00fcnnerstadt",
    "sg:phone":"+49 9733/6414",
    "sg:postcode":"97702",
    "sg:province":"Bayern",
    "wof:name":"Bernd Streit",
    "wof:placetype":"venue"
},
  "geometry": {"coordinates":[10.1931266785,50.248790741],"type":"Point"}
}