{
  "type": "Feature",
  "properties": {
    "iso:country":"DE",
    "sg:address":"Br\u00fchlstr. 19",
    "sg:city":"Hannover",
    "sg:phone":"+49 511/13080",
    "sg:postcode":"30169",
    "sg:province":"Niedersachsen",
    "wof:name":"Sven Skorny Masseur",
    "wof:placetype":"venue"
},
  "geometry": {"coordinates":[9.724744,52.376461],"type":"Point"}
}