{
  "type": "Feature",
  "properties": {
    "iso:country":"DE",
    "sg:address":"Am M\u00fcnster 28",
    "sg:city":"Northeim",
    "sg:postcode":"37154",
    "sg:province":"Niedersachsen",
    "wof:name":"Deutsche Telekom T-punkt",
    "wof:placetype":"venue"
},
  "geometry": {"coordinates":[9.998506546,51.705329895],"type":"Point"}
}