{
  "type": "Feature",
  "properties": {
    "iso:country":"DE",
    "sg:address":"Dahlener Str. 201",
    "sg:city":"M\u00f6nchengladbach",
    "sg:phone":"+49 2166/31425",
    "sg:postcode":"41239",
    "sg:province":"Nordrhein-Westfalen",
    "wof:name":"Esso Deutschland Gmbh",
    "wof:placetype":"venue"
},
  "geometry": {"coordinates":[6.4289832115,51.1660270691],"type":"Point"}
}