{
  "type": "Feature",
  "properties": {
    "iso:country":"DE",
    "sg:address":"Altostr. 62",
    "sg:city":"M\u00fcnchen",
    "sg:phone":"+49 89/8634308",
    "sg:postcode":"81245",
    "sg:province":"Bayern",
    "wof:name":"Georg St\u00fcrzer",
    "wof:placetype":"venue"
},
  "geometry": {"coordinates":[11.413967,48.163155],"type":"Point"}
}