{
  "type": "Feature",
  "properties": {
    "iso:country":"DE",
    "sg:address":"Hauptstr. 85",
    "sg:city":"Bielefeld",
    "sg:phone":"+49 521/441346",
    "sg:postcode":"33647",
    "sg:province":"Nordrhein-Westfalen",
    "wof:name":"Carl Plassmann",
    "wof:placetype":"venue"
},
  "geometry": {"coordinates":[8.5108880997,51.9905052185],"type":"Point"}
}