{
  "type": "Feature",
  "properties": {
    "iso:country":"DE",
    "sg:address":"Schwabstr. 9",
    "sg:city":"Sigmaringen",
    "sg:phone":"+49 7571/13167",
    "sg:postcode":"72488",
    "sg:province":"Baden-W\u00fcrttemberg",
    "wof:name":"Otto Saible E. K. Inh. Hans Saible",
    "wof:placetype":"venue"
},
  "geometry": {"coordinates":[9.2176198959,48.0865249634],"type":"Point"}
}