{
  "type": "Feature",
  "properties": {
    "iso:country":"DE",
    "sg:address":"Liliencronstr. 23",
    "sg:city":"Frankfurt",
    "sg:phone":"+49 69/563023",
    "sg:postcode":"60320",
    "sg:province":"Hessen",
    "wof:name":"Schwanhaeuser Und Heck Rechtsanw\u00e4lte",
    "wof:placetype":"venue"
},
  "geometry": {"coordinates":[8.6670103073,50.1403503418],"type":"Point"}
}