{
  "type": "Feature",
  "properties": {
    "iso:country":"DE",
    "sg:address":"Am Kindergarten 6",
    "sg:city":"Bitburg",
    "sg:phone":"+49 6561/4194",
    "sg:postcode":"54634",
    "sg:province":"Rheinland-Pfalz",
    "wof:name":"Hubert Meyers",
    "wof:placetype":"venue"
},
  "geometry": {"coordinates":[6.556414,49.963722],"type":"Point"}
}