{
  "type": "Feature",
  "properties": {
    "iso:country":"DE",
    "sg:address":"Oheweg 14",
    "sg:city":"Gerdau",
    "sg:phone":"+49 5808/262",
    "sg:postcode":"29581",
    "sg:province":"Niedersachsen",
    "wof:name":"Kurt Rainer Arlt Elektromeister",
    "wof:placetype":"venue"
},
  "geometry": {"coordinates":[10.415883,52.962803],"type":"Point"}
}