{
  "type": "Feature",
  "properties": {
    "iso:country":"DE",
    "sg:address":"Rhaderweg 49",
    "sg:city":"Dortmund",
    "sg:phone":"+49 231/691110",
    "sg:postcode":"44388",
    "sg:province":"Nordrhein-Westfalen",
    "wof:name":"Norbert Z\u00f6llner Masseur",
    "wof:placetype":"venue"
},
  "geometry": {"coordinates":[7.329234,51.51799],"type":"Point"}
}