{
  "type": "Feature",
  "properties": {
    "iso:country":"DE",
    "sg:address":"Gartenstr. 1",
    "sg:city":"Bockenheim",
    "sg:phone":"+49 6359/40393",
    "sg:postcode":"67278",
    "sg:province":"Rheinland-Pfalz",
    "wof:name":"Simone Christ",
    "wof:placetype":"venue"
},
  "geometry": {"coordinates":[8.183517,49.610165],"type":"Point"}
}