{
  "type": "Feature",
  "properties": {
    "iso:country":"DE",
    "sg:address":"Pfarrer-Tischler-Str. 8",
    "sg:city":"Schmidgaden",
    "sg:phone":"+49 9438/1221",
    "sg:postcode":"92546",
    "sg:province":"Bayern",
    "wof:name":"Josef Delling",
    "wof:placetype":"venue"
},
  "geometry": {"coordinates":[12.055619,49.434258],"type":"Point"}
}