{
  "type": "Feature",
  "properties": {
    "iso:country":"DE",
    "sg:address":"Angerstr. 16",
    "sg:city":"Bovenden",
    "sg:postcode":"37120",
    "sg:province":"Niedersachsen",
    "wof:name":"Medcare Visions Beteiligungs- Und Verwaltungs Gmbh",
    "wof:placetype":"venue"
},
  "geometry": {"coordinates":[9.995483,51.606846],"type":"Point"}
}