{
  "type": "Feature",
  "properties": {
    "iso:country":"DE",
    "sg:address":"Gro\u00dfe Bleiche 29",
    "sg:city":"Mainz",
    "sg:phone":"+49 6131/270330",
    "sg:postcode":"55116",
    "sg:province":"Rheinland-Pfalz",
    "wof:name":"Johannes Gutenberg-buch- Handlung Dr. Josef A. Kohl",
    "wof:placetype":"venue"
},
  "geometry": {"coordinates":[8.2664327621,50.0023345947],"type":"Point"}
}