{
  "type": "Feature",
  "properties": {
    "iso:country":"DE",
    "sg:address":"Lemkenhafen 3",
    "sg:city":"Westfehmarn",
    "sg:phone":"+49 4372/991832",
    "sg:postcode":"23769",
    "sg:province":"Schleswig-Holstein",
    "wof:name":"Kolle's Fischpfanne",
    "wof:placetype":"venue"
},
  "geometry": {"coordinates":[11.0995397568,54.439781189],"type":"Point"}
}