{
  "type": "Feature",
  "properties": {
    "iso:country":"DE",
    "sg:address":"Hohenbrunner Weg 15",
    "sg:city":"Grasbrunn",
    "sg:phone":"+49 89/4606625",
    "sg:postcode":"85630",
    "sg:province":"Bayern",
    "wof:name":"Schreinerei M. Ramelmeier Gmbh",
    "wof:placetype":"venue"
},
  "geometry": {"coordinates":[11.736544,48.073784],"type":"Point"}
}