{
  "type": "Feature",
  "properties": {
    "iso:country":"DE",
    "sg:address":"Buchenweg 26",
    "sg:city":"Geesthacht",
    "sg:phone":"+49 4152/3778",
    "sg:postcode":"21502",
    "sg:province":"Schleswig-Holstein",
    "wof:name":"Anne Malachowski Steuerberaterin",
    "wof:placetype":"venue"
},
  "geometry": {"coordinates":[10.3732061386,53.4513244629],"type":"Point"}
}