{
  "type": "Feature",
  "properties": {
    "iso:country":"DE",
    "sg:city":"Kreuzau",
    "sg:postcode":"52372",
    "sg:province":"Nordrhein-Westfalen",
    "wof:name":"Hm & K Beteiligungs- Gesellschaft Mbh",
    "wof:placetype":"venue"
},
  "geometry": {"coordinates":[6.489158,50.74633],"type":"Point"}
}