{
  "type": "Feature",
  "properties": {
    "iso:country":"DE",
    "sg:address":"Himmelreichstr. 6",
    "sg:city":"Bergkirchen",
    "sg:phone":"+49 8131/87461",
    "sg:postcode":"85232",
    "sg:province":"Bayern",
    "wof:name":"Franz Zotz",
    "wof:placetype":"venue"
},
  "geometry": {"coordinates":[11.405475,48.24044],"type":"Point"}
}