{
  "type": "Feature",
  "properties": {
    "iso:country":"DE",
    "sg:address":"Hinter den Bergen 21",
    "sg:city":"Hockenheim",
    "sg:postcode":"68766",
    "sg:province":"Baden-W\u00fcrttemberg",
    "wof:name":"Heli Air Alpine Luftfahrtgesellschaft Mbh",
    "wof:placetype":"venue"
},
  "geometry": {"coordinates":[8.528651,49.328308],"type":"Point"}
}