{
  "type": "Feature",
  "properties": {
    "iso:country":"DE",
    "sg:address":"Frankfurter Str. 90",
    "sg:city":"Hennef",
    "sg:phone":"+49 2242/2570",
    "sg:postcode":"53773",
    "sg:province":"Nordrhein-Westfalen",
    "wof:name":"Stross-druck",
    "wof:placetype":"venue"
},
  "geometry": {"coordinates":[7.287031,50.774002],"type":"Point"}
}