{
  "type": "Feature",
  "properties": {
    "iso:country":"DE",
    "sg:address":"Dahlmannstra\u00dfe 20",
    "sg:city":"Frankfurt",
    "sg:phone":"+49 69",
    "sg:postcode":"60385",
    "sg:province":"Hessen",
    "wof:name":"Chris Kister Architekturfotografie",
    "wof:placetype":"venue"
},
  "geometry": {"coordinates":[8.708342,50.119354],"type":"Point"}
}