{
  "type": "Feature",
  "properties": {
    "iso:country":"DE",
    "sg:address":"Zwischen beiden Sielen 28",
    "sg:city":"Emden",
    "sg:phone":"+49 4921/26610",
    "sg:postcode":"26721",
    "sg:province":"Niedersachsen",
    "wof:name":"Christians Gmbh",
    "wof:placetype":"venue"
},
  "geometry": {"coordinates":[7.2045102119,53.368434906],"type":"Point"}
}