{
  "type": "Feature",
  "properties": {
    "iso:country":"DE",
    "sg:address":"Offenser Weg 7",
    "sg:city":"Heeslingen",
    "sg:phone":"+49 4281/5142",
    "sg:postcode":"27404",
    "sg:province":"Niedersachsen",
    "wof:name":"V. Grund",
    "wof:placetype":"venue"
},
  "geometry": {"coordinates":[9.332235,53.315552],"type":"Point"}
}