{
  "type": "Feature",
  "properties": {
    "iso:country":"DE",
    "sg:address":"An der Geeb 9",
    "sg:city":"Sulzbach",
    "sg:postcode":"63834",
    "sg:province":"Bayern",
    "wof:name":"Rawe Immobilien Und Wohnbau Gmbh",
    "wof:placetype":"venue"
},
  "geometry": {"coordinates":[9.153855,49.910622],"type":"Point"}
}