{
  "type": "Feature",
  "properties": {
    "iso:country":"DE",
    "sg:address":"Steinlach 8",
    "sg:city":"Allmendingen",
    "sg:phone":"+49 7384/431",
    "sg:postcode":"89604",
    "sg:province":"Baden-W\u00fcrttemberg",
    "wof:name":"Karl Kenntner",
    "wof:placetype":"venue"
},
  "geometry": {"coordinates":[9.6607313156,48.3529891968],"type":"Point"}
}