{
  "type": "Feature",
  "properties": {
    "iso:country":"DE",
    "sg:address":"Werner-Seelenbinder-Str. 70",
    "sg:city":"Brandenburg",
    "sg:phone":"+49 3381/301634",
    "sg:postcode":"14770",
    "sg:province":"Brandenburg",
    "wof:name":"N. Speer Rechtsanwalt",
    "wof:placetype":"venue"
},
  "geometry": {"coordinates":[12.5434808731,52.4221038818],"type":"Point"}
}