{
  "type": "Feature",
  "properties": {
    "iso:country":"DE",
    "sg:address":"Karlstr. 28",
    "sg:city":"Saarbr\u00fccken",
    "sg:phone":"+49 6898/81554",
    "sg:postcode":"66126",
    "sg:province":"Saarland",
    "wof:name":"Walter Thiel Gmbh",
    "wof:placetype":"venue"
},
  "geometry": {"coordinates":[6.911459,49.258125],"type":"Point"}
}