{
  "type": "Feature",
  "properties": {
    "iso:country":"DE",
    "sg:address":"Donnerburgstr. 18",
    "sg:city":"Denkte",
    "sg:phone":"+49 5331/65266",
    "sg:postcode":"38321",
    "sg:province":"Niedersachsen",
    "wof:name":"G. Isensee",
    "wof:placetype":"venue"
},
  "geometry": {"coordinates":[10.591566,52.142578],"type":"Point"}
}