{
  "type": "Feature",
  "properties": {
    "iso:country":"DE",
    "sg:address":"Auf der Insel 11",
    "sg:city":"Frankfurt",
    "sg:phone":"+49 69/785305",
    "sg:postcode":"60489",
    "sg:province":"Hessen",
    "wof:name":"Ev. Pfarramt Cyriakusgemeinde Pfarr Bz. S\u00fcd",
    "wof:placetype":"venue"
},
  "geometry": {"coordinates":[8.6136598587,50.1217269897],"type":"Point"}
}