{
  "type": "Feature",
  "properties": {
    "iso:country":"DE",
    "sg:address":"Max-Planck-Str. 14",
    "sg:city":"Kornwestheim",
    "sg:phone":"+49 4971/5482220",
    "sg:postcode":"70806",
    "sg:province":"Baden-W\u00fcrttemberg",
    "wof:name":"Druck + Verlag Wagner Gmbh & Co Kg",
    "wof:placetype":"venue"
},
  "geometry": {"coordinates":[9.1731338501,48.8539352417],"type":"Point"}
}