{
  "type": "Feature",
  "properties": {
    "iso:country":"DE",
    "sg:address":"Planckstr. 7",
    "sg:city":"Stuttgart",
    "sg:phone":"+49 711/462224",
    "sg:postcode":"70184",
    "sg:province":"Baden-W\u00fcrttemberg",
    "wof:name":"Helmut Diem Heilpraktiker",
    "wof:placetype":"venue"
},
  "geometry": {"coordinates":[9.201915741,48.7760734558],"type":"Point"}
}