{
  "type": "Feature",
  "properties": {
    "iso:country":"DE",
    "sg:address":"Taunusblick 14d",
    "sg:city":"Lahnstein",
    "sg:phone":"+49 2621/50204",
    "sg:postcode":"56112",
    "sg:province":"Rheinland-Pfalz",
    "wof:name":"Hans-j\u00fcrgen Hirsch",
    "wof:placetype":"venue"
},
  "geometry": {"coordinates":[7.646455,50.300381],"type":"Point"}
}