{
  "type": "Feature",
  "properties": {
    "iso:country":"DE",
    "sg:address":"Logestr. 33",
    "sg:city":"Beverstedt",
    "sg:phone":"+49 4747/8018",
    "sg:postcode":"27616",
    "sg:province":"Niedersachsen",
    "wof:name":"Dr. Med. Martin Emschermann",
    "wof:placetype":"venue"
},
  "geometry": {"coordinates":[8.822831,53.433029],"type":"Point"}
}