{
  "type": "Feature",
  "properties": {
    "iso:country":"DE",
    "sg:address":"Ortsstr. 17 a",
    "sg:city":"Schweinbach",
    "sg:phone":"+49 36734/28132",
    "sg:postcode":"07338",
    "sg:province":"Th\u00fcringen",
    "wof:name":"Sch\u00f6nherr Rastst\u00e4tte Gmbh",
    "wof:placetype":"venue"
},
  "geometry": {"coordinates":[11.4068956375,50.5647125244],"type":"Point"}
}