{
  "type": "Feature",
  "properties": {
    "iso:country":"DE",
    "sg:address":"Wollhausstr. 24/1",
    "sg:city":"Heilbronn",
    "sg:postcode":"74072",
    "sg:province":"Baden-W\u00fcrttemberg",
    "wof:name":"Dieter Eichelkraut",
    "wof:placetype":"venue"
},
  "geometry": {"coordinates":[9.2232913971,49.1389350891],"type":"Point"}
}