{
  "type": "Feature",
  "properties": {
    "iso:country":"DE",
    "sg:address":"Nordstr. 28",
    "sg:city":"Springe",
    "sg:phone":"+49 5044/985101",
    "sg:postcode":"31832",
    "sg:province":"Niedersachsen",
    "wof:name":"Ira P\u00f6litz Architektin",
    "wof:placetype":"venue"
},
  "geometry": {"coordinates":[9.552947,52.20998],"type":"Point"}
}