{
  "type": "Feature",
  "properties": {
    "iso:country":"DE",
    "sg:address":"Am Jachthafen",
    "sg:city":"Burg",
    "sg:phone":"+49 4371/6679",
    "sg:postcode":"23769",
    "sg:province":"Schleswig-Holstein",
    "wof:name":"Weilandt Verwaltungs Gmbh",
    "wof:placetype":"venue"
},
  "geometry": {"coordinates":[11.197016716,54.4362182617],"type":"Point"}
}