{
  "type": "Feature",
  "properties": {
    "iso:country":"DE",
    "sg:address":"Joliot-Curie-Str. 6",
    "sg:city":"Oranienburg",
    "sg:phone":"+49 3301/582007",
    "sg:postcode":"16515",
    "sg:province":"Brandenburg",
    "wof:name":"Pumpen Und Gebl\u00e4sewerk Gmbh",
    "wof:placetype":"venue"
},
  "geometry": {"coordinates":[13.2509145737,52.7421455383],"type":"Point"}
}