{
  "type": "Feature",
  "properties": {
    "iso:country":"DE",
    "sg:address":"Allerheiligenstr. 18",
    "sg:city":"Sulz",
    "sg:phone":"+49 7482/1285",
    "sg:postcode":"72172",
    "sg:province":"Baden-W\u00fcrttemberg",
    "wof:name":"Hermann Lutz & Co.",
    "wof:placetype":"venue"
},
  "geometry": {"coordinates":[8.6300630569,48.3883743286],"type":"Point"}
}