{
  "type": "Feature",
  "properties": {
    "iso:country":"DE",
    "sg:address":"Chattenweg 12",
    "sg:city":"Bad Homburg",
    "sg:phone":"+49 6172/44647",
    "sg:postcode":"61352",
    "sg:province":"Hessen",
    "wof:name":"Dr. Thomas Neumann",
    "wof:placetype":"venue"
},
  "geometry": {"coordinates":[8.65867,50.221539],"type":"Point"}
}