{
  "type": "Feature",
  "properties": {
    "iso:country":"DE",
    "sg:address":"Hauptstr. 17",
    "sg:city":"Rhaunen",
    "sg:phone":"+49 6544/1246",
    "sg:postcode":"55624",
    "sg:province":"Rheinland-Pfalz",
    "wof:name":"Pfeiffer",
    "wof:placetype":"venue"
},
  "geometry": {"coordinates":[7.347626,49.863522],"type":"Point"}
}