{
  "type": "Feature",
  "properties": {
    "iso:country":"DE",
    "sg:address":"Frankfurter Str. 45",
    "sg:city":"Dreieich",
    "sg:phone":"+49 6103/311310",
    "sg:postcode":"63303",
    "sg:province":"Hessen",
    "wof:name":"Emanuel Schaaf Heilpraktiker",
    "wof:placetype":"venue"
},
  "geometry": {"coordinates":[8.6957092285,50.0227432251],"type":"Point"}
}