{
  "type": "Feature",
  "properties": {
    "iso:country":"DE",
    "sg:address":"Markt 14",
    "sg:city":"Auma",
    "sg:phone":"+49 36626/20990",
    "sg:postcode":"07955",
    "sg:province":"Th\u00fcringen",
    "wof:name":"E. Scharrenweber",
    "wof:placetype":"venue"
},
  "geometry": {"coordinates":[11.89972,50.69957],"type":"Point"}
}