{
  "type": "Feature",
  "properties": {
    "iso:country":"DE",
    "sg:address":"Ludwigstr. 1",
    "sg:city":"Andernach",
    "sg:phone":"+49 2632/948123",
    "sg:postcode":"56626",
    "sg:province":"Rheinland-Pfalz",
    "wof:name":"Ronny Schwarz",
    "wof:placetype":"venue"
},
  "geometry": {"coordinates":[7.4071860313,50.4387359619],"type":"Point"}
}