{
  "type": "Feature",
  "properties": {
    "iso:country":"DE",
    "sg:address":"Oechelh\u00e4user Str. 3",
    "sg:city":"Dessau",
    "sg:postcode":"06846",
    "sg:province":"Sachsen-Anhalt",
    "wof:name":"Lauk\u00f6tter Dessau Gmbh",
    "wof:placetype":"venue"
},
  "geometry": {"coordinates":[12.2224597931,51.8331756592],"type":"Point"}
}