{
  "type": "Feature",
  "properties": {
    "iso:country":"DE",
    "sg:address":"Gartenstr. 37",
    "sg:city":"Gerstetten",
    "sg:phone":"+49 7323/3934",
    "sg:postcode":"89547",
    "sg:province":"Baden-W\u00fcrttemberg",
    "wof:name":"Beate Knobloch",
    "wof:placetype":"venue"
},
  "geometry": {"coordinates":[10.021224,48.623417],"type":"Point"}
}