{
  "type": "Feature",
  "properties": {
    "iso:country":"DE",
    "sg:address":"Gm\u00fcnder Str. 42",
    "sg:city":"Schorndorf",
    "sg:phone":"+49 7181/5224",
    "sg:postcode":"73614",
    "sg:province":"Baden-W\u00fcrttemberg",
    "wof:name":"Musikerinitiative Schorndorf E. V.",
    "wof:placetype":"venue"
},
  "geometry": {"coordinates":[9.5289096832,48.8036804199],"type":"Point"}
}