{
  "type": "Feature",
  "properties": {
    "iso:country":"DE",
    "sg:address":"Pfarrweg 8",
    "sg:city":"Hallenberg",
    "sg:postcode":"59969",
    "sg:province":"Nordrhein-Westfalen",
    "wof:name":"Pfarrb\u00fccherei Braunshagen",
    "wof:placetype":"venue"
},
  "geometry": {"coordinates":[8.679328,51.113358],"type":"Point"}
}