{
  "type": "Feature",
  "properties": {
    "iso:country":"DE",
    "sg:address":"H\u00e4ndelstr. 13",
    "sg:city":"Schwaig",
    "sg:phone":"+49 911/505015",
    "sg:postcode":"90571",
    "sg:province":"Bayern",
    "wof:name":"S\u00fcddeutsche Messerfabrik Alfred G\u00f6ttler",
    "wof:placetype":"venue"
},
  "geometry": {"coordinates":[11.211520195,49.4776763916],"type":"Point"}
}