{
  "type": "Feature",
  "properties": {
    "iso:country":"DE",
    "sg:address":"Sch\u00fctzenstr. 19",
    "sg:city":"L\u00f6rrach",
    "sg:phone":"+49 7621/2895",
    "sg:postcode":"79540",
    "sg:province":"Baden-W\u00fcrttemberg",
    "wof:name":"H. B\u00fcsch",
    "wof:placetype":"venue"
},
  "geometry": {"coordinates":[7.66483,47.609394],"type":"Point"}
}