{
  "type": "Feature",
  "properties": {
    "iso:country":"DE",
    "sg:address":"Ingolst\u00e4dter Str. 6",
    "sg:city":"Mainburg",
    "sg:phone":"+49 8751/1786",
    "sg:postcode":"84048",
    "sg:province":"Bayern",
    "wof:name":"Farbencenter Reiser Gmbh",
    "wof:placetype":"venue"
},
  "geometry": {"coordinates":[11.7789173126,48.6408500671],"type":"Point"}
}