{
  "type": "Feature",
  "properties": {
    "iso:country":"DE",
    "sg:address":"Friedrichstr. 59",
    "sg:city":"Neulu\u00dfheim",
    "sg:phone":"+49 6205/34396",
    "sg:postcode":"68809",
    "sg:province":"Baden-W\u00fcrttemberg",
    "wof:name":"Kuno Seeger",
    "wof:placetype":"venue"
},
  "geometry": {"coordinates":[8.5264396667,49.295249939],"type":"Point"}
}