{
  "type": "Feature",
  "properties": {
    "iso:country":"DE",
    "sg:address":"Dorfstr. 30",
    "sg:city":"Renthendorf",
    "sg:phone":"+49 36426/50487",
    "sg:postcode":"07646",
    "sg:province":"Th\u00fcringen",
    "wof:name":"Otto Grumbt",
    "wof:placetype":"venue"
},
  "geometry": {"coordinates":[11.846935,50.806103],"type":"Point"}
}