{
  "type": "Feature",
  "properties": {
    "iso:country":"DE",
    "sg:address":"Steiner Str. 27",
    "sg:city":"K\u00f6nigsbach-Stein",
    "sg:phone":"+49 7232/2448",
    "sg:postcode":"75203",
    "sg:province":"Baden-W\u00fcrttemberg",
    "wof:name":"Werner D\u00fcrrler Architekt",
    "wof:placetype":"venue"
},
  "geometry": {"coordinates":[8.617235,48.963707],"type":"Point"}
}