{
  "type": "Feature",
  "properties": {
    "iso:country":"DE",
    "sg:address":"Duvenstedter Damm 52 b",
    "sg:city":"Hamburg",
    "sg:phone":"+49 40/6074274",
    "sg:postcode":"22397",
    "sg:province":"Hamburg",
    "wof:name":"Vaf Versicherungs- Anlage- Und Finanzierungsvermittler Gmbh",
    "wof:placetype":"venue"
},
  "geometry": {"coordinates":[10.109000206,53.7078323364],"type":"Point"}
}