{
  "type": "Feature",
  "properties": {
    "iso:country":"DE",
    "sg:address":"Wiesenstr. 23",
    "sg:city":"Hagen",
    "sg:phone":"+49 2334/55916",
    "sg:postcode":"58119",
    "sg:province":"Nordrhein-Westfalen",
    "wof:name":"Horst Kurze",
    "wof:placetype":"venue"
},
  "geometry": {"coordinates":[7.5714921951,51.3625907898],"type":"Point"}
}