{
  "type": "Feature",
  "properties": {
    "iso:country":"DE",
    "sg:address":"Am Moos 18",
    "sg:city":"Neustadt",
    "sg:phone":"+49 9568/7866",
    "sg:postcode":"96465",
    "sg:province":"Bayern",
    "wof:name":"Irmgard Plotkowiak",
    "wof:placetype":"venue"
},
  "geometry": {"coordinates":[11.1141557693,50.3326416016],"type":"Point"}
}