{
  "type": "Feature",
  "properties": {
    "iso:country":"DE",
    "sg:address":"M\u00fchlenhauser Weg 30",
    "sg:city":"Bremen",
    "sg:phone":"+49 421/5288729",
    "sg:postcode":"28197",
    "sg:province":"Bremen",
    "wof:name":"A. Kerl Heissmangelbetrieb",
    "wof:placetype":"venue"
},
  "geometry": {"coordinates":[8.7730302811,53.0812149048],"type":"Point"}
}