{
  "type": "Feature",
  "properties": {
    "iso:country":"DE",
    "sg:address":"Luitpoldstr. 28",
    "sg:city":"Landstuhl",
    "sg:postcode":"66849",
    "sg:province":"Rheinland-Pfalz",
    "wof:name":"Kath. \u00d6ffentliche Bibliothek Heiliger Geist",
    "wof:placetype":"venue"
},
  "geometry": {"coordinates":[7.56595,49.411251],"type":"Point"}
}