{
  "type": "Feature",
  "properties": {
    "iso:country":"DE",
    "sg:address":"Schmiding 1",
    "sg:city":"Ainring",
    "sg:postcode":"83404",
    "sg:province":"Bayern",
    "wof:name":"Hufeisenclub Konrad Althammer",
    "wof:placetype":"venue"
},
  "geometry": {"coordinates":[12.9555921555,47.824924469],"type":"Point"}
}