{
  "type": "Feature",
  "properties": {
    "iso:country":"DE",
    "sg:address":"Rottannenweg 3",
    "sg:city":"Stuttgart",
    "sg:postcode":"70184",
    "sg:province":"Baden-W\u00fcrttemberg",
    "wof:name":"Menno Harms Gmbh International Management",
    "wof:placetype":"venue"
},
  "geometry": {"coordinates":[9.187997,48.766033],"type":"Point"}
}