{
  "type": "Feature",
  "properties": {
    "iso:country":"DE",
    "sg:address":"B\u00fcrgerm.-Prenn-Str. 34",
    "sg:city":"Unterhaching",
    "sg:phone":"+49 89/6251452",
    "sg:postcode":"82008",
    "sg:province":"Bayern",
    "wof:name":"Gerald Zitko",
    "wof:placetype":"venue"
},
  "geometry": {"coordinates":[11.6208238602,48.0589752197],"type":"Point"}
}