{
  "type": "Feature",
  "properties": {
    "iso:country":"DE",
    "sg:address":"Geranienstr. 21",
    "sg:city":"Leinfelden-Echterdingen",
    "sg:phone":"+49 711/752671",
    "sg:postcode":"70771",
    "sg:province":"Baden-W\u00fcrttemberg",
    "wof:name":"S. M\u00e4rz",
    "wof:placetype":"venue"
},
  "geometry": {"coordinates":[9.1395072937,48.6950683594],"type":"Point"}
}