{
  "type": "Feature",
  "properties": {
    "iso:country":"DE",
    "sg:address":"Alzenauer Str. 62",
    "sg:city":"M\u00f6mbris",
    "sg:phone":"+49 6029/996632",
    "sg:postcode":"63776",
    "sg:province":"Bayern",
    "wof:name":"Post",
    "wof:placetype":"venue"
},
  "geometry": {"coordinates":[9.1495084763,50.0864982605],"type":"Point"}
}