{
  "type": "Feature",
  "properties": {
    "iso:country":"DE",
    "sg:address":"Frankfurter Str. 3",
    "sg:city":"Usingen",
    "sg:phone":"+49 6081/2282",
    "sg:postcode":"61250",
    "sg:province":"Hessen",
    "wof:name":"Karl Henz",
    "wof:placetype":"venue"
},
  "geometry": {"coordinates":[8.54237,50.329773],"type":"Point"}
}