{
  "type": "Feature",
  "properties": {
    "iso:country":"DE",
    "sg:address":"Schulstr. 2",
    "sg:city":"Thedinghausen",
    "sg:phone":"+49 4204/7118",
    "sg:postcode":"27321",
    "sg:province":"Niedersachsen",
    "wof:name":"Henning Ravens",
    "wof:placetype":"venue"
},
  "geometry": {"coordinates":[9.021423,52.962448],"type":"Point"}
}