{
  "type": "Feature",
  "properties": {
    "iso:country":"DE",
    "sg:address":"Levenhausen 1",
    "sg:city":"Wipperf\u00fcrth",
    "sg:phone":"+49 2195/7770",
    "sg:postcode":"51688",
    "sg:province":"Nordrhein-Westfalen",
    "wof:name":"Georg Richard",
    "wof:placetype":"venue"
},
  "geometry": {"coordinates":[7.3961911201,51.1744422913],"type":"Point"}
}