{
  "type": "Feature",
  "properties": {
    "iso:country":"DE",
    "sg:address":"Mittellinie 49",
    "sg:city":"Bad Zwischenahn",
    "sg:phone":"+49 4486/2970",
    "sg:postcode":"26160",
    "sg:province":"Niedersachsen",
    "wof:name":"K. Kirchmann",
    "wof:placetype":"venue"
},
  "geometry": {"coordinates":[8.0741500854,53.1543197632],"type":"Point"}
}