{
  "type": "Feature",
  "properties": {
    "iso:country":"DE",
    "sg:address":"Abraham-Lincoln-Str. 21",
    "sg:city":"Wiesbaden",
    "sg:phone":"+49 611/973530",
    "sg:postcode":"65189",
    "sg:province":"Hessen",
    "wof:name":"Euro Lloyd Reiseb\u00fcro Gmbh",
    "wof:placetype":"venue"
},
  "geometry": {"coordinates":[8.2747364044,50.0654830933],"type":"Point"}
}