{
  "type": "Feature",
  "properties": {
    "iso:country":"DE",
    "sg:city":"Kassel",
    "sg:postcode":"34131",
    "sg:province":"Hessen",
    "wof:name":"Sex-liveshow",
    "wof:placetype":"venue"
},
  "geometry": {"coordinates":[9.40149,51.311508],"type":"Point"}
}