{
  "type": "Feature",
  "properties": {
    "iso:country":"DE",
    "sg:address":"Leipziger Str. 20",
    "sg:city":"Berlin",
    "sg:phone":"+49 30/2039160",
    "sg:postcode":"10117",
    "sg:province":"Berlin",
    "wof:name":"Sparky Beteiligungs- Und Verwaltungs Gmbh",
    "wof:placetype":"venue"
},
  "geometry": {"coordinates":[13.377151,52.509857],"type":"Point"}
}