{
  "type": "Feature",
  "properties": {
    "iso:country":"DE",
    "sg:address":"Am Siebrassenhof 41 a",
    "sg:city":"Bielefeld",
    "sg:phone":"+49 521/21143",
    "sg:postcode":"33605",
    "sg:province":"Nordrhein-Westfalen",
    "wof:name":"Gerhard Henrichsmeier Immobilienverwaltungs-",
    "wof:placetype":"venue"
},
  "geometry": {"coordinates":[8.5769262314,51.9974212646],"type":"Point"}
}