{
  "type": "Feature",
  "properties": {
    "iso:country":"DE",
    "sg:address":"Kaiserswerther Str. 49-51",
    "sg:city":"Ratingen",
    "sg:postcode":"40878",
    "sg:province":"Nordrhein-Westfalen",
    "wof:name":"Ice Industrial Components Export Amir Mikhail",
    "wof:placetype":"venue"
},
  "geometry": {"coordinates":[6.842107,51.300339],"type":"Point"}
}