{
  "type": "Feature",
  "properties": {
    "iso:country":"DE",
    "sg:address":"Georgenstr. 5",
    "sg:city":"Planegg",
    "sg:phone":"+49 89/8596179",
    "sg:postcode":"82152",
    "sg:province":"Bayern",
    "wof:name":"Hermann Merten",
    "wof:placetype":"venue"
},
  "geometry": {"coordinates":[11.4222688675,48.1069831848],"type":"Point"}
}