{
  "type": "Feature",
  "properties": {
    "iso:country":"DE",
    "sg:address":"Frankfurter Str. 3",
    "sg:city":"Herzberg",
    "sg:postcode":"04916",
    "sg:province":"Brandenburg",
    "wof:name":"Michael Lademann",
    "wof:placetype":"venue"
},
  "geometry": {"coordinates":[13.2475700378,51.6953697205],"type":"Point"}
}