{
  "type": "Feature",
  "properties": {
    "iso:country":"DE",
    "sg:address":"Wieser Weg 35",
    "sg:city":"Neuenrade",
    "sg:phone":"+49 2392/61515",
    "sg:postcode":"58809",
    "sg:province":"Nordrhein-Westfalen",
    "wof:name":"Andreas Und Birgit Gehrke",
    "wof:placetype":"venue"
},
  "geometry": {"coordinates":[7.768722,51.277805],"type":"Point"}
}