{
  "type": "Feature",
  "properties": {
    "iso:country":"DE",
    "sg:address":"Achalmstr. 20",
    "sg:city":"Leinfelden-Echterdingen",
    "sg:phone":"+49 711/7546261",
    "sg:postcode":"70771",
    "sg:province":"Baden-W\u00fcrttemberg",
    "wof:name":"J\u00fcrgen Schlayer",
    "wof:placetype":"venue"
},
  "geometry": {"coordinates":[9.118904,48.703129],"type":"Point"}
}