{
  "type": "Feature",
  "properties": {
    "iso:country":"DE",
    "sg:address":"Hauffstr. 4",
    "sg:city":"Oberriexingen",
    "sg:phone":"+49 7042/17496",
    "sg:postcode":"71739",
    "sg:province":"Baden-W\u00fcrttemberg",
    "wof:name":"W\u00e4scherei Und Reinigung Hohn Gmbh",
    "wof:placetype":"venue"
},
  "geometry": {"coordinates":[9.023100853,48.9267425537],"type":"Point"}
}