{
  "type": "Feature",
  "properties": {
    "iso:country":"DE",
    "sg:address":"Kantstr. 154",
    "sg:city":"Berlin",
    "sg:phone":"+49 30/3125313",
    "sg:postcode":"10623",
    "sg:province":"Berlin",
    "wof:name":"Kant Floristik Inhaber Yahaya Oladmir-gadim",
    "wof:placetype":"venue"
},
  "geometry": {"coordinates":[13.327687,52.50539],"type":"Point"}
}