{
  "type": "Feature",
  "properties": {
    "iso:country":"DE",
    "sg:address":"Zechenplatz 6",
    "sg:city":"Schlema",
    "sg:phone":"+49 3772/28237",
    "sg:postcode":"08301",
    "sg:province":"Sachsen",
    "wof:name":"Kurt Mehlhorn",
    "wof:placetype":"venue"
},
  "geometry": {"coordinates":[12.655426,50.600945],"type":"Point"}
}