{
  "type": "Feature",
  "properties": {
    "iso:country":"DE",
    "sg:address":"Blumenroder Str. 35",
    "sg:city":"R\u00f6dental",
    "sg:phone":"+49 9563/721084",
    "sg:postcode":"96472",
    "sg:province":"Bayern",
    "wof:name":"Kunststoffaufbereitung Blumenrod Gmbh",
    "wof:placetype":"venue"
},
  "geometry": {"coordinates":[11.0791110992,50.2722663879],"type":"Point"}
}