{
  "type": "Feature",
  "properties": {
    "iso:country":"DE",
    "sg:address":"Hauptstr. 622",
    "sg:city":"Saterland",
    "sg:phone":"+49 4498/655",
    "sg:postcode":"26683",
    "sg:province":"Niedersachsen",
    "wof:name":"Hans Kordes",
    "wof:placetype":"venue"
},
  "geometry": {"coordinates":[7.66704,53.122871],"type":"Point"}
}