{
  "type": "Feature",
  "properties": {
    "iso:country":"DE",
    "sg:address":"Hauptstr. 16",
    "sg:city":"Gars",
    "sg:phone":"+49 8073/1017",
    "sg:postcode":"83536",
    "sg:province":"Bayern",
    "wof:name":"Martin Schwarzenbeck Verwaltungs-gmbh",
    "wof:placetype":"venue"
},
  "geometry": {"coordinates":[12.276345253,48.1536712646],"type":"Point"}
}