{
  "type": "Feature",
  "properties": {
    "iso:country":"DE",
    "sg:address":"Wiesharder Markt 16",
    "sg:city":"Handewitt",
    "sg:phone":"+49 4608/970041",
    "sg:postcode":"24983",
    "sg:province":"Schleswig-Holstein",
    "wof:name":"Dan Natura M\u00f6bel- Handelsgesellschaft Mbh",
    "wof:placetype":"venue"
},
  "geometry": {"coordinates":[9.3238401413,54.7708587646],"type":"Point"}
}