{
  "type": "Feature",
  "properties": {
    "iso:country":"DE",
    "sg:address":"Van-Kinsbergen-Ring 9",
    "sg:city":"Neunkirchen",
    "sg:phone":"+49 2735/61233",
    "sg:postcode":"57290",
    "sg:province":"Nordrhein-Westfalen",
    "wof:name":"Gastst\u00e4tte Bosporus",
    "wof:placetype":"venue"
},
  "geometry": {"coordinates":[8.0143146515,50.799911499],"type":"Point"}
}