{
  "type": "Feature",
  "properties": {
    "iso:country":"DE",
    "sg:address":"Wiedehagen 28a",
    "sg:city":"M\u00fcnster",
    "sg:phone":"+49 251/71568",
    "sg:postcode":"48163",
    "sg:province":"Nordrhein-Westfalen",
    "wof:name":"Jos. Steffens",
    "wof:placetype":"venue"
},
  "geometry": {"coordinates":[7.58492,51.9282],"type":"Point"}
}