{
  "type": "Feature",
  "properties": {
    "iso:country":"DE",
    "sg:address":"Von-Humboldt-Str. 111",
    "sg:city":"Geilenkirchen",
    "sg:phone":"+49 2451/950900",
    "sg:postcode":"52511",
    "sg:province":"Nordrhein-Westfalen",
    "wof:name":"Moderner Baubedarf Handelsgesellschaft",
    "wof:placetype":"venue"
},
  "geometry": {"coordinates":[6.095758,50.980282],"type":"Point"}
}