{
  "type": "Feature",
  "properties": {
    "iso:country":"DE",
    "sg:address":"Gladbacher Str. 16",
    "sg:city":"Schwalmtal",
    "sg:phone":"+49 2163/4488",
    "sg:postcode":"41366",
    "sg:province":"Nordrhein-Westfalen",
    "wof:name":"Josef Wirtz",
    "wof:placetype":"venue"
},
  "geometry": {"coordinates":[6.2748570442,51.2123184204],"type":"Point"}
}