{
  "type": "Feature",
  "properties": {
    "iso:country":"DE",
    "sg:address":"Rapshagener Str. 10",
    "sg:city":"Falkenhagen",
    "sg:postcode":"16928",
    "sg:province":"Brandenburg",
    "wof:name":"Aa-tech Systems Advanced Airland-technology",
    "wof:placetype":"venue"
},
  "geometry": {"coordinates":[12.2074766159,53.2098999023],"type":"Point"}
}