{
  "type": "Feature",
  "properties": {
    "iso:country":"DE",
    "sg:address":"Br\u00fcckenstr. 5",
    "sg:city":"Melsungen",
    "sg:phone":"+49 5661/738118",
    "sg:postcode":"34212",
    "sg:province":"Hessen",
    "wof:name":"Gasthaus Alte Apotheke",
    "wof:placetype":"venue"
},
  "geometry": {"coordinates":[9.5448770523,51.1314430237],"type":"Point"}
}