{
  "type": "Feature",
  "properties": {
    "iso:country":"DE",
    "sg:address":"Alfred-Haude-Str. 31",
    "sg:city":"Neubrandenburg",
    "sg:phone":"+49 395/4223303",
    "sg:postcode":"17034",
    "sg:province":"Mecklenburg-Vorpommern",
    "wof:name":"Karl-heinz Laase",
    "wof:placetype":"venue"
},
  "geometry": {"coordinates":[13.283477,53.576485],"type":"Point"}
}