{
  "type": "Feature",
  "properties": {
    "iso:country":"DE",
    "sg:address":"Schlagwaldstr. 4",
    "sg:city":"Lo\u00dfburg",
    "sg:phone":"+49 7446/95330",
    "sg:postcode":"72290",
    "sg:province":"Baden-W\u00fcrttemberg",
    "wof:name":"Ars Automatisierung Regelung U. Steuerung Gesch\u00e4ftsf.- Und",
    "wof:placetype":"venue"
},
  "geometry": {"coordinates":[8.45355,48.411098],"type":"Point"}
}