{
  "type": "Feature",
  "properties": {
    "iso:country":"DE",
    "sg:address":"Schuhmarktplatz 11",
    "sg:city":"Oberndorf",
    "sg:phone":"+49 7423/6069",
    "sg:postcode":"78727",
    "sg:province":"Baden-W\u00fcrttemberg",
    "wof:name":"Dr. Michael Birke",
    "wof:placetype":"venue"
},
  "geometry": {"coordinates":[8.570351,48.290394],"type":"Point"}
}