{
  "type": "Feature",
  "properties": {
    "iso:country":"DE",
    "sg:address":"Boos-Fremery-Str. 28",
    "sg:city":"Heinsberg",
    "sg:phone":"+49 2452/62757",
    "sg:postcode":"52525",
    "sg:province":"Nordrhein-Westfalen",
    "wof:name":"Kreuz-apotheke",
    "wof:placetype":"venue"
},
  "geometry": {"coordinates":[6.144548,51.060085],"type":"Point"}
}