{
  "type": "Feature",
  "properties": {
    "iso:country":"DE",
    "sg:address":"Goldlackstr. 7-15",
    "sg:city":"Wuppertal",
    "sg:phone":"+49 202/467101",
    "sg:postcode":"42369",
    "sg:province":"Nordrhein-Westfalen",
    "wof:name":"Wagner Gesch\u00e4ftsf\u00fchrungs Gmbh",
    "wof:placetype":"venue"
},
  "geometry": {"coordinates":[7.198755,51.222572],"type":"Point"}
}