{
  "type": "Feature",
  "properties": {
    "iso:country":"DE",
    "sg:address":"Bogenstr. 27 B",
    "sg:city":"Stuttgart",
    "sg:phone":"+49 711/6875546",
    "sg:postcode":"70569",
    "sg:province":"Baden-W\u00fcrttemberg",
    "wof:name":"Eubanks Engineering & Co. Gmbh",
    "wof:placetype":"venue"
},
  "geometry": {"coordinates":[9.11894,48.743423],"type":"Point"}
}