{
  "type": "Feature",
  "properties": {
    "iso:country":"DE",
    "sg:address":"Carstensstr. 93",
    "sg:city":"Celle",
    "sg:phone":"+49 5141/941863",
    "sg:postcode":"29225",
    "sg:province":"Niedersachsen",
    "wof:name":"Paris De Ker",
    "wof:placetype":"venue"
},
  "geometry": {"coordinates":[10.0564155579,52.6109886169],"type":"Point"}
}