{
  "type": "Feature",
  "properties": {
    "iso:country":"DE",
    "sg:address":"Kaiserstr. 26",
    "sg:city":"Br\u00fchl",
    "sg:phone":"+49 2232/42981",
    "sg:postcode":"50321",
    "sg:province":"Nordrhein-Westfalen",
    "wof:name":"Reinhold Stavenhagen Drogerie Und Fotohaus",
    "wof:placetype":"venue"
},
  "geometry": {"coordinates":[6.903049,50.834293],"type":"Point"}
}