{
  "type": "Feature",
  "properties": {
    "iso:country":"DE",
    "sg:address":"BaWiS-BabyWindelService",
    "sg:city":"Neuburg/Donau",
    "sg:phone":"+49 8431",
    "sg:postcode":"86633",
    "sg:province":"Bayern",
    "wof:name":"Bawis-babywindelservice",
    "wof:placetype":"venue"
},
  "geometry": {"coordinates":[11.20463,48.745602],"type":"Point"}
}