{
  "type": "Feature",
  "properties": {
    "iso:country":"DE",
    "sg:address":"Domstr. 9-10",
    "sg:city":"Greifswald",
    "sg:postcode":"17489",
    "sg:province":"Mecklenburg-Vorpommern",
    "wof:name":"Universit\u00e4t Greifswald Fachgebiet Slawistik",
    "wof:placetype":"venue"
},
  "geometry": {"coordinates":[13.373312,54.09486],"type":"Point"}
}