{
  "type": "Feature",
  "properties": {
    "iso:country":"DE",
    "sg:address":"Weidener Str. 29",
    "sg:city":"Kohlberg",
    "sg:phone":"+49 9608/268",
    "sg:postcode":"92702",
    "sg:province":"Bayern",
    "wof:name":"Richard Roith",
    "wof:placetype":"venue"
},
  "geometry": {"coordinates":[12.0238046646,49.5957717896],"type":"Point"}
}