{
  "type": "Feature",
  "properties": {
    "iso:country":"DE",
    "sg:address":"Im B\u00fcchsenschall 10",
    "sg:city":"Mannheim",
    "sg:phone":"+49 621/472199",
    "sg:postcode":"68229",
    "sg:province":"Baden-W\u00fcrttemberg",
    "wof:name":"Gr\u00e4ff",
    "wof:placetype":"venue"
},
  "geometry": {"coordinates":[8.5726165771,49.4338684082],"type":"Point"}
}