{
  "type": "Feature",
  "properties": {
    "iso:country":"DE",
    "sg:address":"Bahnhofstr. 18",
    "sg:city":"Altenkirchen",
    "sg:phone":"+49 2681/6165",
    "sg:postcode":"57610",
    "sg:province":"Rheinland-Pfalz",
    "wof:name":"Heinz Grollius",
    "wof:placetype":"venue"
},
  "geometry": {"coordinates":[7.6398382187,50.6856231689],"type":"Point"}
}