{
  "type": "Feature",
  "properties": {
    "iso:country":"DE",
    "sg:address":"Pr\u00f6\u00dflstr. 21 g",
    "sg:city":"Weiden",
    "sg:phone":"+49 961/61886",
    "sg:postcode":"92637",
    "sg:province":"Bayern",
    "wof:name":"Raimund Neulinger Gmbh & Co. Vermittlungs Kg",
    "wof:placetype":"venue"
},
  "geometry": {"coordinates":[12.1563549042,49.6740264893],"type":"Point"}
}