{
  "type": "Feature",
  "properties": {
    "iso:country":"DE",
    "sg:address":"Naugarder Str. 39",
    "sg:city":"Berlin",
    "sg:phone":"+49 30/4248605",
    "sg:postcode":"10409",
    "sg:province":"Berlin",
    "wof:name":"Pro Bahn E. V.",
    "wof:placetype":"venue"
},
  "geometry": {"coordinates":[13.4378089905,52.5436897278],"type":"Point"}
}