{
  "type": "Feature",
  "properties": {
    "iso:country":"DE",
    "sg:address":"Schie\u00dfst\u00e4ttstr. 25",
    "sg:city":"M\u00fcnchen",
    "sg:phone":"+49 89/5401550",
    "sg:postcode":"80339",
    "sg:province":"Bayern",
    "wof:name":"Allnova Bau Gmbh",
    "wof:placetype":"venue"
},
  "geometry": {"coordinates":[11.5457429886,48.1355895996],"type":"Point"}
}