{
  "type": "Feature",
  "properties": {
    "iso:country":"DE",
    "sg:address":"Herwigsdorfer Str. 19",
    "sg:city":"Zittau",
    "sg:phone":"+49 3583/706933",
    "sg:postcode":"02763",
    "sg:province":"Sachsen",
    "wof:name":"Ergo Versicherungsgruppe Ag",
    "wof:placetype":"venue"
},
  "geometry": {"coordinates":[14.8003807068,50.9065361023],"type":"Point"}
}