{
  "type": "Feature",
  "properties": {
    "iso:country":"DE",
    "sg:address":"Jutastr. 18",
    "sg:city":"M\u00fcnchen",
    "sg:phone":"+49 89/184006",
    "sg:postcode":"80636",
    "sg:province":"Bayern",
    "wof:name":"Raimund Beil Architekt",
    "wof:placetype":"venue"
},
  "geometry": {"coordinates":[11.539509,48.15361],"type":"Point"}
}