{
  "type": "Feature",
  "properties": {
    "iso:country":"DE",
    "sg:address":"Dorstener Str. 185",
    "sg:city":"Bochum",
    "sg:phone":"+49 234/521404",
    "sg:postcode":"44809",
    "sg:province":"Nordrhein-Westfalen",
    "wof:name":"H. Rossbach Elektroinstallation",
    "wof:placetype":"venue"
},
  "geometry": {"coordinates":[7.194946,51.492352],"type":"Point"}
}