{
  "type": "Feature",
  "properties": {
    "iso:country":"DE",
    "sg:address":"Bolwinsweg 10-12",
    "sg:city":"Papenburg",
    "sg:postcode":"26871",
    "sg:province":"Niedersachsen",
    "wof:name":"Diy-fachmarkt Fritz Finke Gmbh & Co. Kg",
    "wof:placetype":"venue"
},
  "geometry": {"coordinates":[7.4408540726,53.0738067627],"type":"Point"}
}