{
  "type": "Feature",
  "properties": {
    "iso:country":"DE",
    "sg:address":"Trifelsstr. 8",
    "sg:city":"Mutterstadt",
    "sg:phone":"+49 6234/2386",
    "sg:postcode":"67112",
    "sg:province":"Rheinland-Pfalz",
    "wof:name":"Ev. Pfarramt Mutterstadt Pfarrbez. 2",
    "wof:placetype":"venue"
},
  "geometry": {"coordinates":[8.3491973877,49.4375343323],"type":"Point"}
}