{
  "type": "Feature",
  "properties": {
    "iso:country":"DE",
    "sg:address":"Vor der Pulverm\u00fchle 9",
    "sg:city":"Hanau",
    "sg:postcode":"63457",
    "sg:province":"Hessen",
    "wof:name":"Pioneer Sales Services Gmbh",
    "wof:placetype":"venue"
},
  "geometry": {"coordinates":[8.9585456848,50.1201858521],"type":"Point"}
}