{
  "type": "Feature",
  "properties": {
    "iso:country":"DE",
    "sg:address":"Alter Stadtberg 15",
    "sg:city":"Neu\u00f6tting",
    "sg:phone":"+49 8671/2303",
    "sg:postcode":"84524",
    "sg:province":"Bayern",
    "wof:name":"Pallaufwirt",
    "wof:placetype":"venue"
},
  "geometry": {"coordinates":[12.6812286377,48.2426719666],"type":"Point"}
}