{
  "type": "Feature",
  "properties": {
    "iso:country":"DE",
    "sg:address":"Hauptstr. 72",
    "sg:city":"D\u00fcren",
    "sg:phone":"+49 2421/53233",
    "sg:postcode":"52355",
    "sg:province":"Nordrhein-Westfalen",
    "wof:name":"Kohlen- Und Mineral\u00f6lhandlung Rudolf Feck Gmbh",
    "wof:placetype":"venue"
},
  "geometry": {"coordinates":[6.47649,50.767841],"type":"Point"}
}