{
  "type": "Feature",
  "properties": {
    "iso:country":"DE",
    "sg:address":"Platanenallee 14",
    "sg:city":"Gudensberg",
    "sg:phone":"+49 5603/5491",
    "sg:postcode":"34281",
    "sg:province":"Hessen",
    "wof:name":"Eduard Sinning Ergotherapiepraxis",
    "wof:placetype":"venue"
},
  "geometry": {"coordinates":[9.363347,51.172997],"type":"Point"}
}