{
  "type": "Feature",
  "properties": {
    "iso:country":"DE",
    "sg:address":"Br\u00fcckenstr. 58",
    "sg:city":"Ottweiler",
    "sg:phone":"+49 6858/443",
    "sg:postcode":"66564",
    "sg:province":"Saarland",
    "wof:name":"Kath. Pfarramt St. Michael",
    "wof:placetype":"venue"
},
  "geometry": {"coordinates":[7.2355480194,49.4173660278],"type":"Point"}
}