{
  "type": "Feature",
  "properties": {
    "iso:country":"DE",
    "sg:address":"H\u00e4ndelweg 50",
    "sg:city":"Kiel",
    "sg:phone":"+49 431/392816",
    "sg:postcode":"24159",
    "sg:province":"Schleswig-Holstein",
    "wof:name":"Bild Und Rahmen Im Studio Anne Gesellschaft Mbh",
    "wof:placetype":"venue"
},
  "geometry": {"coordinates":[10.156983,54.397411],"type":"Point"}
}