{
  "type": "Feature",
  "properties": {
    "iso:country":"DE",
    "sg:address":"Dachauer Str. 37",
    "sg:city":"M\u00fcnchen",
    "sg:phone":"+49 89/597715",
    "sg:postcode":"80335",
    "sg:province":"Bayern",
    "wof:name":"Travel Overland Gmbh",
    "wof:placetype":"venue"
},
  "geometry": {"coordinates":[11.5592536926,48.1453170776],"type":"Point"}
}