{
  "type": "Feature",
  "properties": {
    "iso:country":"DE",
    "sg:address":"F\u00fcrstenstr. 182",
    "sg:city":"Chemnitz",
    "sg:phone":"+49 371/71866",
    "sg:postcode":"09130",
    "sg:province":"Sachsen",
    "wof:name":"Hacker Gastro Gmbh",
    "wof:placetype":"venue"
},
  "geometry": {"coordinates":[12.960313,50.832932],"type":"Point"}
}