{
  "type": "Feature",
  "properties": {
    "iso:country":"DE",
    "sg:address":"Bahnhofstr. 77",
    "sg:city":"M\u00fchlheim",
    "sg:phone":"+49 6108/72868",
    "sg:postcode":"63165",
    "sg:province":"Hessen",
    "wof:name":"Alt Athen",
    "wof:placetype":"venue"
},
  "geometry": {"coordinates":[8.8356704712,50.1197547913],"type":"Point"}
}