{
  "type": "Feature",
  "properties": {
    "iso:country":"DE",
    "sg:address":"Am Sau\u00dfbach 5",
    "sg:city":"Mauth",
    "sg:phone":"+49 8557/1053",
    "sg:postcode":"94151",
    "sg:province":"Bayern",
    "wof:name":"Otmar Knaus",
    "wof:placetype":"venue"
},
  "geometry": {"coordinates":[13.6019420624,48.8865585327],"type":"Point"}
}