{
  "type": "Feature",
  "properties": {
    "iso:country":"DE",
    "sg:address":"Heinkelstr. 8",
    "sg:city":"Wuppertal",
    "sg:phone":"+49 202/80057",
    "sg:postcode":"42285",
    "sg:province":"Nordrhein-Westfalen",
    "wof:name":"Gothaer Versicherungen Gerd Damasch",
    "wof:placetype":"venue"
},
  "geometry": {"coordinates":[7.1683340073,51.2589645386],"type":"Point"}
}