{
  "type": "Feature",
  "properties": {
    "iso:country":"DE",
    "sg:address":"Saarbr\u00fccker Str. 38",
    "sg:city":"Saarlouis",
    "sg:phone":"+49 6831/88983",
    "sg:postcode":"66740",
    "sg:province":"Saarland",
    "wof:name":"Jm Immobilien",
    "wof:placetype":"venue"
},
  "geometry": {"coordinates":[6.7688179016,49.323802948],"type":"Point"}
}