{
  "type": "Feature",
  "properties": {
    "iso:country":"DE",
    "sg:address":"Heidelberger Landstr. 5",
    "sg:city":"Darmstadt",
    "sg:phone":"+49 6151/95600",
    "sg:postcode":"64297",
    "sg:province":"Hessen",
    "wof:name":"Ing.-b\u00fcro Kappes Gmbh",
    "wof:placetype":"venue"
},
  "geometry": {"coordinates":[8.6455516815,49.8414955139],"type":"Point"}
}