{
  "type": "Feature",
  "properties": {
    "iso:country":"DE",
    "sg:address":"Brunner Str. 1",
    "sg:city":"Kyritz",
    "sg:phone":"+49 33971/72011",
    "sg:postcode":"16866",
    "sg:province":"Brandenburg",
    "wof:name":"Klaus Hamann",
    "wof:placetype":"venue"
},
  "geometry": {"coordinates":[12.397142,52.938309],"type":"Point"}
}