{
  "type": "Feature",
  "properties": {
    "iso:country":"DE",
    "sg:address":"Unter der Lay 28",
    "sg:city":"Westerburg",
    "sg:phone":"+49 2663/4825",
    "sg:postcode":"56457",
    "sg:province":"Rheinland-Pfalz",
    "wof:name":"Dieter Sch\u00e4fer Ingenieur",
    "wof:placetype":"venue"
},
  "geometry": {"coordinates":[7.9874582291,50.5629844666],"type":"Point"}
}