{
  "type": "Feature",
  "properties": {
    "iso:country":"DE",
    "sg:address":"Ingerstr. 20",
    "sg:city":"T\u00f6nisvorst",
    "sg:phone":"+49 2151/938330",
    "sg:postcode":"47918",
    "sg:province":"Nordrhein-Westfalen",
    "wof:name":"G & G Comsoft Gmbh Edv Vertrieb",
    "wof:placetype":"venue"
},
  "geometry": {"coordinates":[6.486497879,51.3216781616],"type":"Point"}
}