{
  "type": "Feature",
  "properties": {
    "iso:country":"DE",
    "sg:address":"Albrecht-D\u00fcrer-Str. 16",
    "sg:city":"Erlabrunn",
    "sg:phone":"+49 9364/7593",
    "sg:postcode":"97250",
    "sg:province":"Bayern",
    "wof:name":"A. Sch\u00f6nbohm Und J. Jurkutat Finanzberater",
    "wof:placetype":"venue"
},
  "geometry": {"coordinates":[9.8452329636,49.8568496704],"type":"Point"}
}