{
  "type": "Feature",
  "properties": {
    "iso:country":"DE",
    "sg:address":"Ahornweg 4",
    "sg:city":"Meckesheim",
    "sg:postcode":"74909",
    "sg:province":"Baden-W\u00fcrttemberg",
    "wof:name":"Tc Treuhandges. Mbh",
    "wof:placetype":"venue"
},
  "geometry": {"coordinates":[8.8132019043,49.3130187988],"type":"Point"}
}