{
  "type": "Feature",
  "properties": {
    "iso:country":"DE",
    "sg:address":"Eduard-Kl\u00fcber-Str.",
    "sg:city":"Kaarst",
    "sg:phone":"+49 2131/756313",
    "sg:postcode":"41564",
    "sg:province":"Nordrhein-Westfalen",
    "wof:name":"Lvm-versicherungen Heinrich Dammer",
    "wof:placetype":"venue"
},
  "geometry": {"coordinates":[6.6081600189,51.1961402893],"type":"Point"}
}