{
  "type": "Feature",
  "properties": {
    "iso:country":"DE",
    "sg:address":"Tulpenstr. 5",
    "sg:city":"R\u00f6thenbach",
    "sg:postcode":"90552",
    "sg:province":"Bayern",
    "wof:name":"John Helsing Band",
    "wof:placetype":"venue"
},
  "geometry": {"coordinates":[11.2452602386,49.4860343933],"type":"Point"}
}