{
  "type": "Feature",
  "properties": {
    "iso:country":"DE",
    "sg:address":"V\u00f6cklinger Hang 26",
    "sg:city":"Essen",
    "sg:phone":"+49 201/266671",
    "sg:postcode":"45131",
    "sg:province":"Nordrhein-Westfalen",
    "wof:name":"Friedrich G. W. Schulte",
    "wof:placetype":"venue"
},
  "geometry": {"coordinates":[7.019139,51.432251],"type":"Point"}
}