{
  "type": "Feature",
  "properties": {
    "iso:country":"DE",
    "sg:address":"Am Reiherbusch 1",
    "sg:city":"Grevenbroich",
    "sg:phone":"+49 2182/825214",
    "sg:postcode":"41516",
    "sg:province":"Nordrhein-Westfalen",
    "wof:name":"Horst Beerscht Architekt",
    "wof:placetype":"venue"
},
  "geometry": {"coordinates":[6.65754,51.132912],"type":"Point"}
}