{
  "type": "Feature",
  "properties": {
    "iso:country":"DE",
    "sg:address":"Hamberger Ring",
    "sg:city":"Lohne",
    "sg:phone":"+49 4442/3496",
    "sg:postcode":"49393",
    "sg:province":"Niedersachsen",
    "wof:name":"Dieter Strasser",
    "wof:placetype":"venue"
},
  "geometry": {"coordinates":[8.250607,52.645473],"type":"Point"}
}