{
  "type": "Feature",
  "properties": {
    "iso:country":"DE",
    "sg:address":"Hirschbergstr. 11",
    "sg:city":"Holzkirchen",
    "sg:phone":"+49 8024/2460",
    "sg:postcode":"83607",
    "sg:province":"Bayern",
    "wof:name":"Susanne Halfmann Rechtsanw\u00e4ltin",
    "wof:placetype":"venue"
},
  "geometry": {"coordinates":[11.699010849,47.8724365234],"type":"Point"}
}