{
  "type": "Feature",
  "properties": {
    "iso:country":"DE",
    "sg:address":"Carmerstr. 8",
    "sg:city":"Berlin",
    "sg:phone":"+49 30/3136905",
    "sg:postcode":"10623",
    "sg:province":"Berlin",
    "wof:name":"Am Savignyplatz",
    "wof:placetype":"venue"
},
  "geometry": {"coordinates":[13.3232812881,52.5067329407],"type":"Point"}
}