{
  "type": "Feature",
  "properties": {
    "iso:country":"DE",
    "sg:address":"Ginsheimer Str. 1",
    "sg:city":"Ginsheim-Gustavsburg",
    "sg:postcode":"65462",
    "sg:province":"Hessen",
    "wof:name":"The Vision Web Germany Gmbh",
    "wof:placetype":"venue"
},
  "geometry": {"coordinates":[8.3196935654,49.9928474426],"type":"Point"}
}