{
  "type": "Feature",
  "properties": {
    "iso:country":"DE",
    "sg:address":"Generalweg 17",
    "sg:city":"L\u00fcbbecke",
    "sg:phone":"+49 5741/8294",
    "sg:postcode":"32312",
    "sg:province":"Nordrhein-Westfalen",
    "wof:name":"H. Fromme Versicherung",
    "wof:placetype":"venue"
},
  "geometry": {"coordinates":[8.5574626923,52.3101501465],"type":"Point"}
}