{
  "type": "Feature",
  "properties": {
    "iso:country":"DE",
    "sg:address":"Friedrich-Engels-Str. 63",
    "sg:city":"Luisenthal",
    "sg:phone":"+49 36257/40364",
    "sg:postcode":"99885",
    "sg:province":"Th\u00fcringen",
    "wof:name":"Hans-martin Triebel",
    "wof:placetype":"venue"
},
  "geometry": {"coordinates":[10.72929,50.769939],"type":"Point"}
}