{
  "type": "Feature",
  "properties": {
    "iso:country":"DE",
    "sg:address":"Wilhelmsh\u00f6her Allee 257",
    "sg:city":"Kassel",
    "sg:phone":"+49 561/31870",
    "sg:postcode":"34131",
    "sg:province":"Hessen",
    "wof:name":"Domicil Hotelges. Mbh",
    "wof:placetype":"venue"
},
  "geometry": {"coordinates":[9.4450435638,51.313495636],"type":"Point"}
}