{
  "type": "Feature",
  "properties": {
    "iso:country":"DE",
    "sg:address":"Pauwelsstr. 19",
    "sg:city":"Aachen",
    "sg:postcode":"52074",
    "sg:province":"Nordrhein-Westfalen",
    "wof:name":"Eike-industrie-designer",
    "wof:placetype":"venue"
},
  "geometry": {"coordinates":[6.047799,50.775749],"type":"Point"}
}