{
  "type": "Feature",
  "properties": {
    "iso:country":"DE",
    "sg:address":"Alter Blobach 39a",
    "sg:city":"M\u00fchlhausen",
    "sg:postcode":"99974",
    "sg:province":"Th\u00fcringen",
    "wof:name":"H. Gabriel",
    "wof:placetype":"venue"
},
  "geometry": {"coordinates":[10.4506607056,51.2134780884],"type":"Point"}
}