{
  "type": "Feature",
  "properties": {
    "iso:country":"DE",
    "sg:address":"Bahnhofstr. 6",
    "sg:city":"Auma",
    "sg:phone":"+49 36626/20536",
    "sg:postcode":"07955",
    "sg:province":"Th\u00fcringen",
    "wof:name":"Achim Heidrich",
    "wof:placetype":"venue"
},
  "geometry": {"coordinates":[11.895271,50.703152],"type":"Point"}
}