{
  "type": "Feature",
  "properties": {
    "iso:country":"DE",
    "sg:address":"Oberhandenzhofen 4",
    "sg:city":"Erdweg",
    "sg:postcode":"85253",
    "sg:province":"Bayern",
    "wof:name":"Agrarhandel Rabl Gmbh",
    "wof:placetype":"venue"
},
  "geometry": {"coordinates":[11.250129,48.317425],"type":"Point"}
}