{
  "type": "Feature",
  "properties": {
    "iso:country":"DE",
    "sg:address":"Adolfstr. 5",
    "sg:city":"Bonn",
    "sg:postcode":"53111",
    "sg:province":"Nordrhein-Westfalen",
    "wof:name":"Guerilla-medien Ohg",
    "wof:placetype":"venue"
},
  "geometry": {"coordinates":[7.0881299973,50.737285614],"type":"Point"}
}