{
  "type": "Feature",
  "properties": {
    "iso:country":"DE",
    "sg:address":"Adam-Karrillon-Str. 23",
    "sg:city":"Mainz",
    "sg:phone":"+49 6131/613026",
    "sg:postcode":"55118",
    "sg:province":"Rheinland-Pfalz",
    "wof:name":"Urschbach Und Wasserburg Rechtsanw\u00e4lte",
    "wof:placetype":"venue"
},
  "geometry": {"coordinates":[8.2639846802,50.0071411133],"type":"Point"}
}