{
  "type": "Feature",
  "properties": {
    "iso:country":"DE",
    "sg:address":"Clausstr. 1",
    "sg:city":"Bad Soden",
    "sg:phone":"+49 6196/23151",
    "sg:postcode":"65812",
    "sg:province":"Hessen",
    "wof:name":"C. George",
    "wof:placetype":"venue"
},
  "geometry": {"coordinates":[8.5010795593,50.1435813904],"type":"Point"}
}