{
  "type": "Feature",
  "properties": {
    "iso:country":"DE",
    "sg:address":"Von-Witzleben-Str. 30",
    "sg:city":"M\u00fcnster",
    "sg:phone":"+49 251/77111",
    "sg:postcode":"48151",
    "sg:province":"Nordrhein-Westfalen",
    "wof:name":"Ludger Wiens",
    "wof:placetype":"venue"
},
  "geometry": {"coordinates":[7.6088881493,51.9467277527],"type":"Point"}
}