{
  "type": "Feature",
  "properties": {
    "iso:country":"DE",
    "sg:address":"Reichsgrafenstr. 21",
    "sg:city":"Wuppertal",
    "sg:phone":"+49 202/426268",
    "sg:postcode":"42119",
    "sg:province":"Nordrhein-Westfalen",
    "wof:name":"Siegfried Unger Architekt",
    "wof:placetype":"venue"
},
  "geometry": {"coordinates":[7.145192,51.248508],"type":"Point"}
}