{
  "type": "Feature",
  "properties": {
    "iso:country":"DE",
    "sg:city":"Muenchen",
    "sg:postcode":"81247",
    "sg:province":"Bayern",
    "wof:name":"Couplecoaching - Interactive",
    "wof:placetype":"venue"
},
  "geometry": {"coordinates":[11.454238,48.173256],"type":"Point"}
}