{
  "type": "Feature",
  "properties": {
    "iso:country":"DE",
    "sg:address":"Heydenreichstr. 12",
    "sg:city":"Zittau",
    "sg:phone":"+49 3583/512143",
    "sg:postcode":"02763",
    "sg:province":"Sachsen",
    "wof:name":"Pension Dany",
    "wof:placetype":"venue"
},
  "geometry": {"coordinates":[14.7911806107,50.8952026367],"type":"Point"}
}