{
  "type": "Feature",
  "properties": {
    "iso:country":"DE",
    "sg:address":"Rheinstr. 2 - 3",
    "sg:city":"Berlin",
    "sg:phone":"+49 30/8513035",
    "sg:postcode":"12159",
    "sg:province":"Berlin",
    "wof:name":"Dresdner Bank",
    "wof:placetype":"venue"
},
  "geometry": {"coordinates":[13.334656,52.471275],"type":"Point"}
}