{
  "type": "Feature",
  "properties": {
    "iso:country":"DE",
    "sg:address":"Marienburger Str. 17",
    "sg:city":"K\u00f6ln",
    "sg:phone":"+49 221/937620",
    "sg:postcode":"50968",
    "sg:province":"Nordrhein-Westfalen",
    "wof:name":"Limex Im- Und Export Helmut Lingen Handelsgesell-",
    "wof:placetype":"venue"
},
  "geometry": {"coordinates":[6.9773797989,50.9016876221],"type":"Point"}
}