{
  "type": "Feature",
  "properties": {
    "iso:country":"DE",
    "sg:address":"Molkereiweg 2",
    "sg:city":"Heimertingen",
    "sg:phone":"+49 8335/215",
    "sg:postcode":"87751",
    "sg:province":"Bayern",
    "wof:name":"Gerhard Rauh",
    "wof:placetype":"venue"
},
  "geometry": {"coordinates":[10.152285,48.041245],"type":"Point"}
}