{
  "type": "Feature",
  "properties": {
    "iso:country":"DE",
    "sg:address":"Greifenberger Str. 21",
    "sg:city":"Albersdorf",
    "sg:phone":"+49 4835/950180",
    "sg:postcode":"25767",
    "sg:province":"Schleswig-Holstein",
    "wof:name":"Anlagen- Und Bausanierungs- Systeme Michael Schubert E. K.",
    "wof:placetype":"venue"
},
  "geometry": {"coordinates":[9.2937116623,54.1493606567],"type":"Point"}
}