{
  "type": "Feature",
  "properties": {
    "iso:country":"DE",
    "sg:address":"Frauenried 3",
    "sg:city":"Irschenberg",
    "sg:phone":"+49 8025/996812",
    "sg:postcode":"83737",
    "sg:province":"Bayern",
    "wof:name":"Improve Gmbh",
    "wof:placetype":"venue"
},
  "geometry": {"coordinates":[11.8721656799,47.8017196655],"type":"Point"}
}