{
  "type": "Feature",
  "properties": {
    "iso:country":"DE",
    "sg:address":"Zur Steinigheck 12",
    "sg:city":"Binsfeld",
    "sg:phone":"+49 6575/4848",
    "sg:postcode":"54518",
    "sg:province":"Rheinland-Pfalz",
    "wof:name":"J. Thielen",
    "wof:placetype":"venue"
},
  "geometry": {"coordinates":[6.709945,49.96299],"type":"Point"}
}