{
  "type": "Feature",
  "properties": {
    "iso:country":"DE",
    "sg:address":"Wendelsteiner Str. 16 b",
    "sg:city":"N\u00fcrnberg",
    "sg:phone":"+49 911/481966",
    "sg:postcode":"90469",
    "sg:province":"Bayern",
    "wof:name":"Krisch Gmbh",
    "wof:placetype":"venue"
},
  "geometry": {"coordinates":[11.100274086,49.4067993164],"type":"Point"}
}