{
  "type": "Feature",
  "properties": {
    "iso:country":"DE",
    "sg:address":"Sendelbach 24",
    "sg:city":"Durbach",
    "sg:phone":"+49 781/41974",
    "sg:postcode":"77770",
    "sg:province":"Baden-W\u00fcrttemberg",
    "wof:name":"Anton L. W\u00f6rner",
    "wof:placetype":"venue"
},
  "geometry": {"coordinates":[8.0178070068,48.4892845154],"type":"Point"}
}