{
  "type": "Feature",
  "properties": {
    "iso:country":"DE",
    "sg:address":"Wacholderstr.",
    "sg:city":"Wutha-Farnroda",
    "sg:postcode":"99848",
    "sg:province":"Th\u00fcringen",
    "wof:name":"Pension Sabine Schnorr",
    "wof:placetype":"venue"
},
  "geometry": {"coordinates":[10.3973388672,50.946395874],"type":"Point"}
}