{
  "type": "Feature",
  "properties": {
    "iso:country":"DE",
    "sg:address":"Am Hirschberg 18",
    "sg:city":"Weyarn",
    "sg:phone":"+49 8020/1524",
    "sg:postcode":"83629",
    "sg:province":"Bayern",
    "wof:name":"Steinle Ingenieurgesellschaft F\u00fcr Abwassertechnik Mbh",
    "wof:placetype":"venue"
},
  "geometry": {"coordinates":[11.8036708832,47.8558921814],"type":"Point"}
}