{
  "type": "Feature",
  "properties": {
    "iso:country":"DE",
    "sg:address":"Auf der Wacht 26",
    "sg:city":"Bad D\u00fcrkheim",
    "sg:phone":"+49 6322/8310",
    "sg:postcode":"67098",
    "sg:province":"Rheinland-Pfalz",
    "wof:name":"P. Wei\u00dfer",
    "wof:placetype":"venue"
},
  "geometry": {"coordinates":[8.162405,49.453178],"type":"Point"}
}