{
  "type": "Feature",
  "properties": {
    "iso:country":"DE",
    "sg:address":"Nordstr. 29",
    "sg:city":"Beckum",
    "sg:phone":"+49 2521/3226",
    "sg:postcode":"59269",
    "sg:province":"Nordrhein-Westfalen",
    "wof:name":"Paul Krick",
    "wof:placetype":"venue"
},
  "geometry": {"coordinates":[8.0408477783,51.7566070557],"type":"Point"}
}