{
  "type": "Feature",
  "properties": {
    "iso:country":"DE",
    "sg:address":"Wittelsbacherstr 20",
    "sg:city":"M\u00fcnchen",
    "sg:phone":"+49 89/2388570",
    "sg:postcode":"80469",
    "sg:province":"Bayern",
    "wof:name":"Dassel & Schumacher Werbeagentur Gmbh",
    "wof:placetype":"venue"
},
  "geometry": {"coordinates":[11.565815,48.122459],"type":"Point"}
}