{
  "type": "Feature",
  "properties": {
    "iso:country":"DE",
    "sg:address":"Frauengrund",
    "sg:city":"Ebern",
    "sg:phone":"+49 9531/465",
    "sg:postcode":"96106",
    "sg:province":"Bayern",
    "wof:name":"Walter Geng Bw-kantine",
    "wof:placetype":"venue"
},
  "geometry": {"coordinates":[10.7743396759,50.0945053101],"type":"Point"}
}