{
  "type": "Feature",
  "properties": {
    "iso:country":"DE",
    "sg:address":"Grenzstr. 122",
    "sg:city":"Bremen",
    "sg:phone":"+49 421/395297",
    "sg:postcode":"28217",
    "sg:province":"Bremen",
    "wof:name":"Arbeitslosen-zentrum Kontakt- Und Beratungsstelle",
    "wof:placetype":"venue"
},
  "geometry": {"coordinates":[8.780601,53.092861],"type":"Point"}
}