{
  "type": "Feature",
  "properties": {
    "iso:country":"DE",
    "sg:address":"Rudolf-Breitscheid-Str. 62",
    "sg:city":"Potsdam",
    "sg:phone":"+49 331/707869",
    "sg:postcode":"14482",
    "sg:province":"Brandenburg",
    "wof:name":"Alles F\u00fcr Ihr Ihre Ladeneinrichtung Bekommen Sie Bei Uns.",
    "wof:placetype":"venue"
},
  "geometry": {"coordinates":[13.0981731415,52.3921051025],"type":"Point"}
}