{
  "type": "Feature",
  "properties": {
    "iso:country":"DE",
    "sg:address":"Taufkirchener Str. 2",
    "sg:city":"Erding",
    "sg:phone":"+49 8122/18200",
    "sg:postcode":"85435",
    "sg:province":"Bayern",
    "wof:name":"Sigrid Und K. Steines",
    "wof:placetype":"venue"
},
  "geometry": {"coordinates":[11.9200315475,48.3040275574],"type":"Point"}
}