{
  "type": "Feature",
  "properties": {
    "iso:country":"DE",
    "sg:address":"Harbernusstr. 1 c",
    "sg:city":"Neuss",
    "sg:phone":"+49 2182/6392",
    "sg:postcode":"41472",
    "sg:province":"Nordrhein-Westfalen",
    "wof:name":"Helpensteiner Bau Gmbh",
    "wof:placetype":"venue"
},
  "geometry": {"coordinates":[6.6700701714,51.1422615051],"type":"Point"}
}