{
  "type": "Feature",
  "properties": {
    "iso:country":"DE",
    "sg:address":"Ledastr. 3",
    "sg:city":"Rhauderfehn",
    "sg:phone":"+49 4955/1611",
    "sg:postcode":"26817",
    "sg:province":"Niedersachsen",
    "wof:name":"Wilhelm Gr\u00fcnefeld",
    "wof:placetype":"venue"
},
  "geometry": {"coordinates":[7.527003,53.19146],"type":"Point"}
}