{
  "type": "Feature",
  "properties": {
    "iso:country":"DE",
    "sg:address":"Am R\u00e4tschenbach 27",
    "sg:city":"Erding",
    "sg:phone":"+49 8122",
    "sg:postcode":"85435",
    "sg:province":"Bayern",
    "wof:name":"Extra-immobilien",
    "wof:placetype":"venue"
},
  "geometry": {"coordinates":[11.9088859558,48.3080482483],"type":"Point"}
}