{
  "type": "Feature",
  "properties": {
    "iso:country":"DE",
    "sg:address":"Altk\u00f6nigstr 4",
    "sg:city":"Niederdorfelden",
    "sg:phone":"+49 6101/6090",
    "sg:postcode":"61138",
    "sg:province":"Hessen",
    "wof:name":"Aquatec Engeneering Gmbh",
    "wof:placetype":"venue"
},
  "geometry": {"coordinates":[8.7957620621,50.190071106],"type":"Point"}
}