{
  "type": "Feature",
  "properties": {
    "iso:country":"DE",
    "sg:address":"Am Falltor 38",
    "sg:city":"Bensheim",
    "sg:phone":"+49 6251/79955",
    "sg:postcode":"64625",
    "sg:province":"Hessen",
    "wof:name":"Ulrich Heinecker",
    "wof:placetype":"venue"
},
  "geometry": {"coordinates":[8.5699205399,49.6987266541],"type":"Point"}
}