{
  "type": "Feature",
  "properties": {
    "iso:country":"DE",
    "sg:address":"Gotenweg 51",
    "sg:city":"Wetzlar",
    "sg:phone":"+49 6441/926682",
    "sg:postcode":"35578",
    "sg:province":"Hessen",
    "wof:name":"Med Tec Gmbh",
    "wof:placetype":"venue"
},
  "geometry": {"coordinates":[8.506636,50.545502],"type":"Point"}
}