{
  "type": "Feature",
  "properties": {
    "iso:country":"DE",
    "sg:address":"Graf-Konrad-Str. 47",
    "sg:city":"Ehingen",
    "sg:phone":"+49 7391/8720",
    "sg:postcode":"89584",
    "sg:province":"Baden-W\u00fcrttemberg",
    "wof:name":"Bruno Kloos",
    "wof:placetype":"venue"
},
  "geometry": {"coordinates":[9.737416,48.260803],"type":"Point"}
}