{
  "type": "Feature",
  "properties": {
    "iso:country":"DE",
    "sg:address":"Bahnhofstra\u00dfe 47",
    "sg:city":"Saarbr\u00fccken",
    "sg:phone":"+49 681/36051",
    "sg:postcode":"66111",
    "sg:province":"Saarland",
    "wof:name":"Dema-zeitarbeit Gmbh (personaldienstleistung,- Leasing)",
    "wof:placetype":"venue"
},
  "geometry": {"coordinates":[6.993503,49.235516],"type":"Point"}
}