{
  "type": "Feature",
  "properties": {
    "iso:country":"DE",
    "sg:address":"Altenwahlingen 30",
    "sg:city":"B\u00f6hme",
    "sg:phone":"+49 5165/1863",
    "sg:postcode":"29693",
    "sg:province":"Niedersachsen",
    "wof:name":"F. Bernholz",
    "wof:placetype":"venue"
},
  "geometry": {"coordinates":[9.4303541183,52.7962913513],"type":"Point"}
}