{
  "type": "Feature",
  "properties": {
    "iso:country":"DE",
    "sg:address":"Friedhofstr. 7",
    "sg:city":"Denkingen",
    "sg:phone":"+49 7424/85882",
    "sg:postcode":"78588",
    "sg:province":"Baden-W\u00fcrttemberg",
    "wof:name":"Gastst\u00e4tte Z\u00fcchterheim",
    "wof:placetype":"venue"
},
  "geometry": {"coordinates":[8.734457016,48.1094703674],"type":"Point"}
}