{
  "type": "Feature",
  "properties": {
    "iso:country":"DE",
    "sg:address":"Brunnenstr. 91",
    "sg:city":"L\u00fcnen",
    "sg:phone":"+49 2306/12192",
    "sg:postcode":"44536",
    "sg:province":"Nordrhein-Westfalen",
    "wof:name":"Restaurant L\u00fcner Brunnen",
    "wof:placetype":"venue"
},
  "geometry": {"coordinates":[7.4764518738,51.6143722534],"type":"Point"}
}