{
  "type": "Feature",
  "properties": {
    "iso:country":"DE",
    "sg:address":"Admiralstr. 21",
    "sg:city":"Berlin",
    "sg:phone":"+49 30/6149112",
    "sg:postcode":"10999",
    "sg:province":"Berlin",
    "wof:name":"Gerd Hahn",
    "wof:placetype":"venue"
},
  "geometry": {"coordinates":[13.415728569,52.4958648682],"type":"Point"}
}