{
  "type": "Feature",
  "properties": {
    "iso:country":"DE",
    "sg:address":"Schulkamp 4",
    "sg:city":"Westerstede",
    "sg:phone":"+49 4409/371",
    "sg:postcode":"26655",
    "sg:province":"Niedersachsen",
    "wof:name":"August Krieger Inh. Detlef",
    "wof:placetype":"venue"
},
  "geometry": {"coordinates":[7.8971858025,53.2010917664],"type":"Point"}
}