{
  "type": "Feature",
  "properties": {
    "iso:country":"DE",
    "sg:address":"Gro\u00dfenhainer Str. 16",
    "sg:city":"Sch\u00f6nfeld",
    "sg:phone":"+49 35248/81274",
    "sg:postcode":"01561",
    "sg:province":"Sachsen",
    "wof:name":"G\u00fcnter Scholz",
    "wof:placetype":"venue"
},
  "geometry": {"coordinates":[13.70126,51.302563],"type":"Point"}
}