{
  "type": "Feature",
  "properties": {
    "iso:country":"DE",
    "sg:address":"Am Riddershof 2",
    "sg:city":"Krefeld",
    "sg:phone":"+49 4962/8152010",
    "sg:postcode":"47805",
    "sg:province":"Nordrhein-Westfalen",
    "wof:name":"J\u00dcrgen Erhardt E. K.",
    "wof:placetype":"venue"
},
  "geometry": {"coordinates":[9.340494,49.528915],"type":"Point"}
}