{
  "type": "Feature",
  "properties": {
    "iso:country":"DE",
    "sg:address":"Mandelring 19",
    "sg:city":"Neustadt",
    "sg:phone":"+49 6321/355501",
    "sg:postcode":"67433",
    "sg:province":"Rheinland-Pfalz",
    "wof:name":"Pizzeria Haardt",
    "wof:placetype":"venue"
},
  "geometry": {"coordinates":[8.1377687454,49.3613739014],"type":"Point"}
}