{
  "type": "Feature",
  "properties": {
    "iso:country":"DE",
    "sg:address":"Am Spielmannsfalter 19",
    "sg:city":"Kaarst",
    "sg:phone":"+49 2131/519553",
    "sg:postcode":"41564",
    "sg:province":"Nordrhein-Westfalen",
    "wof:name":"F. Reichel Steuerberater",
    "wof:placetype":"venue"
},
  "geometry": {"coordinates":[6.57411623,51.2140541077],"type":"Point"}
}