{
  "type": "Feature",
  "properties": {
    "iso:country":"DE",
    "sg:address":"Silvesterweg 31 A",
    "sg:city":"Berlin",
    "sg:phone":"+49 30/4041099",
    "sg:postcode":"13467",
    "sg:province":"Berlin",
    "wof:name":"Bauland-verwertungs- Und Verwaltungsgesellschaft Mbh",
    "wof:placetype":"venue"
},
  "geometry": {"coordinates":[13.308842659,52.6219444275],"type":"Point"}
}