{
  "type": "Feature",
  "properties": {
    "iso:country":"DE",
    "sg:address":"K\u00f6nigstr. 4",
    "sg:city":"Rottenburg",
    "sg:phone":"+49 7472/1849",
    "sg:postcode":"72108",
    "sg:province":"Baden-W\u00fcrttemberg",
    "wof:name":"Falken",
    "wof:placetype":"venue"
},
  "geometry": {"coordinates":[8.9356946945,48.4786338806],"type":"Point"}
}