{
  "type": "Feature",
  "properties": {
    "iso:country":"DE",
    "sg:address":"Ihringsh\u00e4user Str. 3",
    "sg:city":"Kassel",
    "sg:phone":"+49 561/874221",
    "sg:postcode":"34125",
    "sg:province":"Hessen",
    "wof:name":"Katholische Pfarrgemeinde St Bonifatius Kassel",
    "wof:placetype":"venue"
},
  "geometry": {"coordinates":[9.51279,51.32439],"type":"Point"}
}