{
  "type": "Feature",
  "properties": {
    "iso:country":"DE",
    "sg:address":"Hans-Gr\u00fcninger-Weg 6",
    "sg:city":"Markgr\u00f6ningen",
    "sg:phone":"+49 7145/923006",
    "sg:postcode":"71706",
    "sg:province":"Baden-W\u00fcrttemberg",
    "wof:name":"Dentir B\u00e4ckerei-gmbh",
    "wof:placetype":"venue"
},
  "geometry": {"coordinates":[9.077623,48.902218],"type":"Point"}
}