{
  "type": "Feature",
  "properties": {
    "iso:country":"DE",
    "sg:address":"St.-Vither-Str.",
    "sg:city":"Pr\u00fcm",
    "sg:phone":"+49 6551/851",
    "sg:postcode":"54595",
    "sg:province":"Rheinland-Pfalz",
    "wof:name":"Kath. Pfarramt St. Gordian Und Epimachus",
    "wof:placetype":"venue"
},
  "geometry": {"coordinates":[6.4008779526,50.1915435791],"type":"Point"}
}