{
  "type": "Feature",
  "properties": {
    "iso:country":"DE",
    "sg:address":"Dorfring 2",
    "sg:city":"Laasdorf",
    "sg:phone":"+49 36428/40748",
    "sg:postcode":"07646",
    "sg:province":"Th\u00fcringen",
    "wof:name":"Pro Reha Handel Gmbh",
    "wof:placetype":"venue"
},
  "geometry": {"coordinates":[11.6732320786,50.8720283508],"type":"Point"}
}