{
  "type": "Feature",
  "properties": {
    "iso:country":"DE",
    "sg:address":"Gottwollsh\u00e4user Steige 6",
    "sg:city":"Schw\u00e4bisch Hall",
    "sg:phone":"+49 791/54126",
    "sg:postcode":"74523",
    "sg:province":"Baden-W\u00fcrttemberg",
    "wof:name":"S. Schramm",
    "wof:placetype":"venue"
},
  "geometry": {"coordinates":[9.7322263718,49.1155281067],"type":"Point"}
}