{
  "type": "Feature",
  "properties": {
    "iso:country":"DE",
    "sg:address":"Thierlsteiner Str. 5",
    "sg:city":"Cham",
    "sg:phone":"+49 9944/244",
    "sg:postcode":"93413",
    "sg:province":"Bayern",
    "wof:name":"Bayerwald Aulfes Kg",
    "wof:placetype":"venue"
},
  "geometry": {"coordinates":[12.6265907288,49.2087249756],"type":"Point"}
}