{
  "type": "Feature",
  "properties": {
    "iso:country":"DE",
    "sg:address":"Josef-Landes-Str. 44",
    "sg:city":"Kaufbeuren",
    "sg:phone":"+49 8341/2827",
    "sg:postcode":"87600",
    "sg:province":"Bayern",
    "wof:name":"T\u00e4nzelfestverein E. V.",
    "wof:placetype":"venue"
},
  "geometry": {"coordinates":[10.6239299774,47.8793106079],"type":"Point"}
}