{
  "type": "Feature",
  "properties": {
    "iso:country":"DE",
    "sg:address":"Am W\u00e4cker 20",
    "sg:city":"Bergneustadt",
    "sg:phone":"+49 2261/41394",
    "sg:postcode":"51702",
    "sg:province":"Nordrhein-Westfalen",
    "wof:name":"Restaurant Zum Krug",
    "wof:placetype":"venue"
},
  "geometry": {"coordinates":[7.6380667686,51.018081665],"type":"Point"}
}