{
  "type": "Feature",
  "properties": {
    "iso:country":"DE",
    "sg:address":"Friedrich-Engels-Str. 15",
    "sg:city":"Seehausen",
    "sg:phone":"+49 39407/5000",
    "sg:postcode":"39365",
    "sg:province":"Sachsen-Anhalt",
    "wof:name":"Hotel-restaurant Seehausen",
    "wof:placetype":"venue"
},
  "geometry": {"coordinates":[11.2935428619,52.1021232605],"type":"Point"}
}