{
  "type": "Feature",
  "properties": {
    "iso:country":"DE",
    "sg:address":"Klingengasse 14",
    "sg:city":"Rothenburg",
    "sg:phone":"+49 9861/2474",
    "sg:postcode":"91541",
    "sg:province":"Bayern",
    "wof:name":"Guckloch",
    "wof:placetype":"venue"
},
  "geometry": {"coordinates":[10.177173,49.379074],"type":"Point"}
}