{
  "type": "Feature",
  "properties": {
    "iso:country":"DE",
    "sg:address":"Lauterhofener Str. 5",
    "sg:city":"Kirchberg",
    "sg:phone":"+49 37602/64295",
    "sg:postcode":"08107",
    "sg:province":"Sachsen",
    "wof:name":"A. Wolf",
    "wof:placetype":"venue"
},
  "geometry": {"coordinates":[12.517065,50.615849],"type":"Point"}
}