{
  "type": "Feature",
  "properties": {
    "iso:country":"DE",
    "sg:address":"Gabelsbergerstr. 16",
    "sg:city":"Hannover",
    "sg:phone":"+49 511/8700011",
    "sg:postcode":"30163",
    "sg:province":"Niedersachsen",
    "wof:name":"In Wo",
    "wof:placetype":"venue"
},
  "geometry": {"coordinates":[9.746447,52.390671],"type":"Point"}
}