{
  "type": "Feature",
  "properties": {
    "iso:country":"DE",
    "sg:address":"An der Saline 2",
    "sg:city":"B\u00fcdingen",
    "sg:phone":"+49 6042/810",
    "sg:postcode":"63654",
    "sg:province":"Hessen",
    "wof:name":"Sonnenschein Internat. Gmbh",
    "wof:placetype":"venue"
},
  "geometry": {"coordinates":[9.109093,50.284863],"type":"Point"}
}