{
  "type": "Feature",
  "properties": {
    "iso:country":"DE",
    "sg:address":"Levinstr. 103",
    "sg:city":"Essen",
    "sg:phone":"+49 201/665176",
    "sg:postcode":"45356",
    "sg:province":"Nordrhein-Westfalen",
    "wof:name":"Gerhard Gohlke",
    "wof:placetype":"venue"
},
  "geometry": {"coordinates":[6.944049,51.491329],"type":"Point"}
}