{
  "type": "Feature",
  "properties": {
    "iso:country":"DE",
    "sg:address":"Thierseestr. 24a",
    "sg:city":"Kiefersfelden",
    "sg:phone":"+49 8033/8150",
    "sg:postcode":"83088",
    "sg:province":"Bayern",
    "wof:name":"Hella Systeme F\u00fcr Laden- Und Messebau Vertriebsge-",
    "wof:placetype":"venue"
},
  "geometry": {"coordinates":[12.1838960648,47.6189613342],"type":"Point"}
}