{
  "type": "Feature",
  "properties": {
    "iso:country":"DE",
    "sg:address":"Stresemannstr. 1",
    "sg:city":"Schweinfurt",
    "sg:phone":"+49 9721/805399",
    "sg:postcode":"97424",
    "sg:province":"Bayern",
    "wof:name":"O. Krohe",
    "wof:placetype":"venue"
},
  "geometry": {"coordinates":[10.2104663849,50.0368461609],"type":"Point"}
}