{
  "type": "Feature",
  "properties": {
    "iso:country":"DE",
    "sg:address":"Hauptstr. 59",
    "sg:city":"Altenbamberg",
    "sg:phone":"+49 6708/3965",
    "sg:postcode":"55585",
    "sg:province":"Rheinland-Pfalz",
    "wof:name":"Friedrich Reichard",
    "wof:placetype":"venue"
},
  "geometry": {"coordinates":[7.83147192,49.7849159241],"type":"Point"}
}