{
  "type": "Feature",
  "properties": {
    "iso:country":"DE",
    "sg:address":"Flinger Str. 40",
    "sg:city":"D\u00fcsseldorf",
    "sg:phone":"+49 211/133123",
    "sg:postcode":"40213",
    "sg:province":"Nordrhein-Westfalen",
    "wof:name":"Queen Bar",
    "wof:placetype":"venue"
},
  "geometry": {"coordinates":[6.774558,51.225471],"type":"Point"}
}