{
  "type": "Feature",
  "properties": {
    "iso:country":"DE",
    "sg:address":"K\u00f6hlerbarg 8",
    "sg:city":"Quarnbek",
    "sg:phone":"+49 4340/8083",
    "sg:postcode":"24107",
    "sg:province":"Schleswig-Holstein",
    "wof:name":"Autovermietung Schoer Gmbh",
    "wof:placetype":"venue"
},
  "geometry": {"coordinates":[9.984738,54.330849],"type":"Point"}
}