{
  "type": "Feature",
  "properties": {
    "iso:country":"DE",
    "sg:address":"Hammerschmiedstr. 15 A",
    "sg:city":"Egling",
    "sg:phone":"+49 8206/96010",
    "sg:postcode":"86492",
    "sg:province":"Bayern",
    "wof:name":"Blauhut & Partner Informationssysteme Gmbh",
    "wof:placetype":"venue"
},
  "geometry": {"coordinates":[10.9729318619,48.1854553223],"type":"Point"}
}