{
  "type": "Feature",
  "properties": {
    "iso:country":"DE",
    "sg:address":"Werkstr. 27",
    "sg:city":"Bad K\u00f6nig",
    "sg:phone":"+49 6063/95940",
    "sg:postcode":"64732",
    "sg:province":"Hessen",
    "wof:name":"Seniorenresidenz Am Kurpark Gmbh",
    "wof:placetype":"venue"
},
  "geometry": {"coordinates":[9.0003843307,49.736831665],"type":"Point"}
}