{
  "type": "Feature",
  "properties": {
    "iso:country":"DE",
    "sg:address":"Schillerstr. 9",
    "sg:city":"Oedheim",
    "sg:phone":"+49 7136/910184",
    "sg:postcode":"74229",
    "sg:province":"Baden-W\u00fcrttemberg",
    "wof:name":"Marwen Tours Markus Wende",
    "wof:placetype":"venue"
},
  "geometry": {"coordinates":[9.2454795837,49.2435264587],"type":"Point"}
}