{
  "type": "Feature",
  "properties": {
    "iso:country":"DE",
    "sg:address":"Vogelheimer Str. 133",
    "sg:city":"Essen",
    "sg:phone":"+49 201/368751",
    "sg:postcode":"45329",
    "sg:province":"Nordrhein-Westfalen",
    "wof:name":"Tinas K\u00fcche I.g.",
    "wof:placetype":"venue"
},
  "geometry": {"coordinates":[6.9952502251,51.4919815063],"type":"Point"}
}