{
  "type": "Feature",
  "properties": {
    "iso:country":"DE",
    "sg:address":"Rathausgasse 1",
    "sg:city":"Staufen",
    "sg:phone":"+49 7633/6136",
    "sg:postcode":"79219",
    "sg:province":"Baden-W\u00fcrttemberg",
    "wof:name":"Herbert Erler",
    "wof:placetype":"venue"
},
  "geometry": {"coordinates":[7.732154,47.882336],"type":"Point"}
}