{
  "type": "Feature",
  "properties": {
    "iso:country":"DE",
    "sg:address":"M\u00fchlstr. 17",
    "sg:city":"Mespelbrunn",
    "sg:phone":"+49 6092/7159",
    "sg:postcode":"63875",
    "sg:province":"Bayern",
    "wof:name":"Fine Kunkel",
    "wof:placetype":"venue"
},
  "geometry": {"coordinates":[9.2882728577,49.9292945862],"type":"Point"}
}