{
  "type": "Feature",
  "properties": {
    "iso:country":"DE",
    "sg:address":"Bodelschwinghstr. 2",
    "sg:city":"Traunreut",
    "sg:phone":"+49 8669/861340",
    "sg:postcode":"83301",
    "sg:province":"Bayern",
    "wof:name":"Chiemgau-lebenshilfe- Werkst\u00e4tten Gmbh",
    "wof:placetype":"venue"
},
  "geometry": {"coordinates":[12.6024084091,47.9684295654],"type":"Point"}
}