{
  "type": "Feature",
  "properties": {
    "iso:country":"DE",
    "sg:address":"Tondernweg 6",
    "sg:city":"Ellerau",
    "sg:phone":"+49 4106/72418",
    "sg:postcode":"25479",
    "sg:province":"Schleswig-Holstein",
    "wof:name":"B\u00e4rbel Rudtke Immobilienmaklerin",
    "wof:placetype":"venue"
},
  "geometry": {"coordinates":[9.9234237671,53.752620697],"type":"Point"}
}