{
  "type": "Feature",
  "properties": {
    "iso:country":"DE",
    "sg:address":"Hawermannweg 16",
    "sg:city":"Rostock",
    "sg:phone":"+49 381/890024",
    "sg:postcode":"18069",
    "sg:province":"Mecklenburg-Vorpommern",
    "wof:name":"Itz Informationstechnologie- Zentrum Rostock Gmbh",
    "wof:placetype":"venue"
},
  "geometry": {"coordinates":[12.080713,54.105385],"type":"Point"}
}