{
  "type": "Feature",
  "properties": {
    "iso:country":"DE",
    "sg:address":"Alte Bismarckstr. 13",
    "sg:city":"Remscheid",
    "sg:phone":"+49 2191/23925",
    "sg:postcode":"42853",
    "sg:province":"Nordrhein-Westfalen",
    "wof:name":"La Gondola",
    "wof:placetype":"venue"
},
  "geometry": {"coordinates":[7.1966490746,51.1792030334],"type":"Point"}
}