{
  "type": "Feature",
  "properties": {
    "iso:country":"DE",
    "sg:address":"Eichenstr. 15",
    "sg:city":"Neuried",
    "sg:phone":"+49 89/7592252",
    "sg:postcode":"82061",
    "sg:province":"Bayern",
    "wof:name":"Quintenz Handelsgesellschaft F\u00fcr Microelektronik Mbh",
    "wof:placetype":"venue"
},
  "geometry": {"coordinates":[11.4537000656,48.0861816406],"type":"Point"}
}