{
  "type": "Feature",
  "properties": {
    "iso:country":"DE",
    "sg:address":"Hartwigstr. 14",
    "sg:city":"Ruhland",
    "sg:phone":"+49 35752/2218",
    "sg:postcode":"01945",
    "sg:province":"Brandenburg",
    "wof:name":"H. Biesold",
    "wof:placetype":"venue"
},
  "geometry": {"coordinates":[13.860574,51.456799],"type":"Point"}
}