{
  "type": "Feature",
  "properties": {
    "iso:country":"DE",
    "sg:address":"Steinh\u00e4ulesweg 9",
    "sg:city":"Neu-Ulm",
    "sg:phone":"+49 731/7253045",
    "sg:postcode":"89233",
    "sg:province":"Bayern",
    "wof:name":"Vereinsgastst\u00e4tte Tennisrestaurant Blau-wei\u00df",
    "wof:placetype":"venue"
},
  "geometry": {"coordinates":[10.0180034637,48.4110221863],"type":"Point"}
}