{
  "type": "Feature",
  "properties": {
    "iso:country":"DE",
    "sg:address":"Hochdorfer Str. 6",
    "sg:city":"Althegnenberg",
    "sg:phone":"+49 8202/8226",
    "sg:postcode":"82278",
    "sg:province":"Bayern",
    "wof:name":"Franz Gaier Gmbh",
    "wof:placetype":"venue"
},
  "geometry": {"coordinates":[11.064384,48.23521],"type":"Point"}
}