{
  "type": "Feature",
  "properties": {
    "iso:country":"DE",
    "sg:address":"Dorfstr. 2",
    "sg:city":"Neuenmarkt",
    "sg:phone":"+49 9227/376",
    "sg:postcode":"95339",
    "sg:province":"Bayern",
    "wof:name":"G\u00fcnter Oertel",
    "wof:placetype":"venue"
},
  "geometry": {"coordinates":[11.584787,50.095798],"type":"Point"}
}