{
  "type": "Feature",
  "properties": {
    "iso:country":"DE",
    "sg:address":"Huffelsheck 1",
    "sg:city":"Leidenborn",
    "sg:phone":"+49 6559/467",
    "sg:postcode":"54619",
    "sg:province":"Rheinland-Pfalz",
    "wof:name":"Judith Bossert",
    "wof:placetype":"venue"
},
  "geometry": {"coordinates":[6.2362599373,50.1397285461],"type":"Point"}
}