{
  "type": "Feature",
  "properties": {
    "iso:country":"DE",
    "sg:address":"Rathausstr. 14",
    "sg:city":"Stolberg",
    "sg:phone":"+49 2402/25000",
    "sg:postcode":"52222",
    "sg:province":"Nordrhein-Westfalen",
    "wof:name":"Rathaus-apotheke",
    "wof:placetype":"venue"
},
  "geometry": {"coordinates":[6.228702,50.770599],"type":"Point"}
}