{
  "type": "Feature",
  "properties": {
    "iso:country":"DE",
    "sg:address":"Hasseler Str. 99a",
    "sg:city":"Gelsenkirchen",
    "sg:phone":"+49 209/66091",
    "sg:postcode":"45896",
    "sg:province":"Nordrhein-Westfalen",
    "wof:name":"Hasseler St\u00fcbchen",
    "wof:placetype":"venue"
},
  "geometry": {"coordinates":[7.0599799156,51.6067390442],"type":"Point"}
}