{
  "type": "Feature",
  "properties": {
    "iso:country":"DE",
    "sg:address":"Horschelweg 5",
    "sg:city":"Oberrot",
    "sg:phone":"+49 7977/89056",
    "sg:postcode":"74420",
    "sg:province":"Baden-W\u00fcrttemberg",
    "wof:name":"Riek",
    "wof:placetype":"venue"
},
  "geometry": {"coordinates":[9.6794309616,49.0061264038],"type":"Point"}
}