{
  "type": "Feature",
  "properties": {
    "iso:country":"DE",
    "sg:address":"Am Bahnhof 14",
    "sg:city":"Malching",
    "sg:postcode":"94094",
    "sg:province":"Bayern",
    "wof:name":"J. Oberlechner Lagerhaus",
    "wof:placetype":"venue"
},
  "geometry": {"coordinates":[13.186433,48.309917],"type":"Point"}
}