{
  "type": "Feature",
  "properties": {
    "iso:country":"DE",
    "sg:address":"Am Rondell 14",
    "sg:city":"Aurich",
    "sg:phone":"+49 4941/71623",
    "sg:postcode":"26607",
    "sg:province":"Niedersachsen",
    "wof:name":"A. Zacherl",
    "wof:placetype":"venue"
},
  "geometry": {"coordinates":[7.4670758247,53.5152168274],"type":"Point"}
}