{
  "type": "Feature",
  "properties": {
    "iso:country":"DE",
    "sg:address":"Naumburger Str. 19",
    "sg:city":"Kassel",
    "sg:phone":"+49 561/83363",
    "sg:postcode":"34127",
    "sg:province":"Hessen",
    "wof:name":"Ernst Aschenbrandt",
    "wof:placetype":"venue"
},
  "geometry": {"coordinates":[9.4763851166,51.3244857788],"type":"Point"}
}