{
  "type": "Feature",
  "properties": {
    "iso:country":"DE",
    "sg:address":"Laubenzedel 57",
    "sg:city":"Gunzenhausen",
    "sg:phone":"+49 9831/8600",
    "sg:postcode":"91710",
    "sg:province":"Bayern",
    "wof:name":"K. Bachschuster",
    "wof:placetype":"venue"
},
  "geometry": {"coordinates":[10.7494478226,49.1444778442],"type":"Point"}
}