{
  "type": "Feature",
  "properties": {
    "iso:country":"DE",
    "sg:address":"Markt 10",
    "sg:city":"W\u00fcrselen",
    "sg:phone":"+49 2405/93841",
    "sg:postcode":"52146",
    "sg:province":"Nordrhein-Westfalen",
    "wof:name":"Casa Verde",
    "wof:placetype":"venue"
},
  "geometry": {"coordinates":[6.13294,50.818268],"type":"Point"}
}