{
  "type": "Feature",
  "properties": {
    "iso:country":"DE",
    "sg:address":"Werner-Hilpert-Str. 129",
    "sg:city":"Wiesbaden",
    "sg:phone":"+49 611/467985",
    "sg:postcode":"65197",
    "sg:province":"Hessen",
    "wof:name":"Ha-ra",
    "wof:placetype":"venue"
},
  "geometry": {"coordinates":[8.194951,50.088879],"type":"Point"}
}