{
  "type": "Feature",
  "properties": {
    "iso:country":"DE",
    "sg:address":"Eimsb\u00fctteler Str. 113",
    "sg:city":"Hamburg",
    "sg:phone":"+49 40/85322116",
    "sg:postcode":"22769",
    "sg:province":"Hamburg",
    "wof:name":"His Hamburger Immobilien Service Gmbh",
    "wof:placetype":"venue"
},
  "geometry": {"coordinates":[9.9508686066,53.5678215027],"type":"Point"}
}