{
  "type": "Feature",
  "properties": {
    "iso:country":"DE",
    "sg:address":"Heidh\u00f6hn 13",
    "sg:city":"Cuxhaven",
    "sg:phone":"+49 4721/29673",
    "sg:postcode":"27476",
    "sg:province":"Niedersachsen",
    "wof:name":"Flying Fish Grote & P\u00fcrschel Gmbh",
    "wof:placetype":"venue"
},
  "geometry": {"coordinates":[8.60567379,53.8606872559],"type":"Point"}
}