{
  "type": "Feature",
  "properties": {
    "iso:country":"DE",
    "sg:address":"Schmid\u00e4ckerstr. 13",
    "sg:city":"Salach",
    "sg:phone":"+49 7162/44064",
    "sg:postcode":"73084",
    "sg:province":"Baden-W\u00fcrttemberg",
    "wof:name":"Holographie Hofmann",
    "wof:placetype":"venue"
},
  "geometry": {"coordinates":[9.7443475723,48.6987228394],"type":"Point"}
}