{
  "type": "Feature",
  "properties": {
    "iso:country":"DE",
    "sg:address":"Am Anger 36",
    "sg:city":"Neulingen",
    "sg:phone":"+49 7237/246",
    "sg:postcode":"75245",
    "sg:province":"Baden-W\u00fcrttemberg",
    "wof:name":"Edmund Jahn Elektroanl.",
    "wof:placetype":"venue"
},
  "geometry": {"coordinates":[8.724338,48.970268],"type":"Point"}
}