{
  "type": "Feature",
  "properties": {
    "iso:country":"DE",
    "sg:address":"Panoramastr. 10",
    "sg:city":"Uhingen",
    "sg:phone":"+49 7161/9387140",
    "sg:postcode":"73066",
    "sg:province":"Baden-W\u00fcrttemberg",
    "wof:name":"Hallenbad Uhingen",
    "wof:placetype":"venue"
},
  "geometry": {"coordinates":[9.5864677429,48.7125396729],"type":"Point"}
}