{
  "type": "Feature",
  "properties": {
    "iso:country":"DE",
    "sg:address":"Lohhof",
    "sg:city":"Tiefenbach",
    "sg:phone":"+49 8509/820",
    "sg:postcode":"94113",
    "sg:province":"Bayern",
    "wof:name":"Profap Vogl Gmbh",
    "wof:placetype":"venue"
},
  "geometry": {"coordinates":[13.4138441086,48.6372261047],"type":"Point"}
}