{
  "type": "Feature",
  "properties": {
    "iso:country":"DE",
    "sg:address":"Rheinuferstr. 74a",
    "sg:city":"Kamp-Bornhofen",
    "sg:phone":"+49 6773/919005",
    "sg:postcode":"56341",
    "sg:province":"Rheinland-Pfalz",
    "wof:name":"R. Schowald",
    "wof:placetype":"venue"
},
  "geometry": {"coordinates":[7.621497,50.221149],"type":"Point"}
}