{
  "type": "Feature",
  "properties": {
    "iso:country":"DE",
    "sg:address":"Zimmergasse 26",
    "sg:city":"Hetzerath",
    "sg:phone":"+49 6508/7280",
    "sg:postcode":"54523",
    "sg:province":"Rheinland-Pfalz",
    "wof:name":"Arno Haas",
    "wof:placetype":"venue"
},
  "geometry": {"coordinates":[6.7948508263,49.8900909424],"type":"Point"}
}