{
  "type": "Feature",
  "properties": {
    "iso:country":"DE",
    "sg:address":"Biggenhammer 1",
    "sg:city":"Diemelstadt",
    "sg:phone":"+49 5694",
    "sg:postcode":"34474",
    "sg:province":"Hessen",
    "wof:name":"Hundemarkt.com",
    "wof:placetype":"venue"
},
  "geometry": {"coordinates":[8.9677085876,51.5009384155],"type":"Point"}
}