{
  "type": "Feature",
  "properties": {
    "iso:country":"DE",
    "sg:address":"Sinnersdorferstr. 173",
    "sg:city":"K\u00f6ln",
    "sg:postcode":"50769",
    "sg:province":"Nordrhein-Westfalen",
    "wof:name":"Duo Piasso",
    "wof:placetype":"venue"
},
  "geometry": {"coordinates":[6.8413,51.043461],"type":"Point"}
}