{
  "type": "Feature",
  "properties": {
    "iso:country":"DE",
    "sg:address":"Waldbleeke 50",
    "sg:city":"M\u00fclheim",
    "sg:phone":"+49 208/486131",
    "sg:postcode":"45481",
    "sg:province":"Nordrhein-Westfalen",
    "wof:name":"Hans Moes",
    "wof:placetype":"venue"
},
  "geometry": {"coordinates":[6.855426,51.403996],"type":"Point"}
}