{
  "type": "Feature",
  "properties": {
    "iso:country":"DE",
    "sg:address":"Markt 11",
    "sg:city":"J\u00fcchen",
    "sg:phone":"+49 2165/1601",
    "sg:postcode":"41363",
    "sg:province":"Nordrhein-Westfalen",
    "wof:name":"Raiffeisenbank Grevenbroich Eg",
    "wof:placetype":"venue"
},
  "geometry": {"coordinates":[6.503832,51.10051],"type":"Point"}
}