{
  "type": "Feature",
  "properties": {
    "iso:country":"DE",
    "sg:address":"Fritz-Weidner-Str. 12",
    "sg:city":"N\u00fcrnberg",
    "sg:phone":"+49 911/646489",
    "sg:postcode":"90451",
    "sg:province":"Bayern",
    "wof:name":"Rainer Netter",
    "wof:placetype":"venue"
},
  "geometry": {"coordinates":[11.0342006683,49.4011611938],"type":"Point"}
}