{
  "type": "Feature",
  "properties": {
    "iso:country":"DE",
    "sg:address":"Keplerstr. 108",
    "sg:city":"Essen",
    "sg:phone":"+49 201/707466",
    "sg:postcode":"45147",
    "sg:province":"Nordrhein-Westfalen",
    "wof:name":"Paul H\u00f6lscher Buch- Und Zeitschriften-",
    "wof:placetype":"venue"
},
  "geometry": {"coordinates":[6.9793839455,51.4432792664],"type":"Point"}
}