{
  "type": "Feature",
  "properties": {
    "iso:country":"DE",
    "sg:address":"Modering 3",
    "sg:city":"Hamburg",
    "sg:phone":"+49 40/5591588",
    "sg:postcode":"22457",
    "sg:province":"Hamburg",
    "wof:name":"Chadha Gmbh",
    "wof:placetype":"venue"
},
  "geometry": {"coordinates":[9.9227323532,53.6376876831],"type":"Point"}
}