{
  "type": "Feature",
  "properties": {
    "iso:country":"DE",
    "sg:address":"Dachsbergstr. 16",
    "sg:city":"Schauenburg",
    "sg:phone":"+49 5601/2084",
    "sg:postcode":"34270",
    "sg:province":"Hessen",
    "wof:name":"Werner Hempel Ingenieur",
    "wof:placetype":"venue"
},
  "geometry": {"coordinates":[9.3818912506,51.2751617432],"type":"Point"}
}