{
  "type": "Feature",
  "properties": {
    "iso:country":"DE",
    "sg:address":"Hintere Bleiche 8",
    "sg:city":"Mainz",
    "sg:phone":"+49 6131/223910",
    "sg:postcode":"55116",
    "sg:province":"Rheinland-Pfalz",
    "wof:name":"Weinhaus Weinel",
    "wof:placetype":"venue"
},
  "geometry": {"coordinates":[8.2635087967,50.0014228821],"type":"Point"}
}