{
  "type": "Feature",
  "properties": {
    "iso:country":"DE",
    "sg:address":"Zeller Str. 14",
    "sg:city":"Biberach",
    "sg:phone":"+49 7835/7820",
    "sg:postcode":"77781",
    "sg:province":"Baden-W\u00fcrttemberg",
    "wof:name":"Knauer-druck Verwaltungs- Gmbh",
    "wof:placetype":"venue"
},
  "geometry": {"coordinates":[8.037781,48.335819],"type":"Point"}
}