{
  "type": "Feature",
  "properties": {
    "iso:country":"DE",
    "sg:address":"Gehrbusch 53",
    "sg:city":"Salzgitter",
    "sg:phone":"+49 5341/50445",
    "sg:postcode":"38228",
    "sg:province":"Niedersachsen",
    "wof:name":"E.-frido Gaus",
    "wof:placetype":"venue"
},
  "geometry": {"coordinates":[10.298988,52.124844],"type":"Point"}
}