{
  "type": "Feature",
  "properties": {
    "iso:country":"DE",
    "sg:address":"Bendorfer Str.",
    "sg:city":"Bendorf",
    "sg:phone":"+49 2622/10440",
    "sg:postcode":"56170",
    "sg:province":"Rheinland-Pfalz",
    "wof:name":"Bio-tech-sportger\u00e4te Manfred Nitsch",
    "wof:placetype":"venue"
},
  "geometry": {"coordinates":[7.555698,50.423386],"type":"Point"}
}