{
  "type": "Feature",
  "properties": {
    "iso:country":"DE",
    "sg:address":"Kurgartenstr. 109",
    "sg:city":"L\u00fcbeck",
    "sg:phone":"+49 4502/302727",
    "sg:postcode":"23570",
    "sg:province":"Schleswig-Holstein",
    "wof:name":"Pension Bastian",
    "wof:placetype":"venue"
},
  "geometry": {"coordinates":[10.8713264465,53.9588165283],"type":"Point"}
}