{
  "type": "Feature",
  "properties": {
    "iso:country":"DE",
    "sg:address":"Marxstr. 77",
    "sg:city":"Hattingen",
    "sg:phone":"+49 2324/67575",
    "sg:postcode":"45527",
    "sg:province":"Nordrhein-Westfalen",
    "wof:name":"Hasebrink Und D\u00fcbbers Rechtsanw\u00e4lte Und Notare",
    "wof:placetype":"venue"
},
  "geometry": {"coordinates":[7.2129640579,51.4118804932],"type":"Point"}
}