{
  "type": "Feature",
  "properties": {
    "iso:country":"DE",
    "sg:address":"Dammstr. 4",
    "sg:city":"Sonneberg",
    "sg:phone":"+49 3675/464233",
    "sg:postcode":"96515",
    "sg:province":"Th\u00fcringen",
    "wof:name":"Multi M\u00f6bel Handelsges. Mbh",
    "wof:placetype":"venue"
},
  "geometry": {"coordinates":[11.167844,50.353848],"type":"Point"}
}