{
  "type": "Feature",
  "properties": {
    "iso:country":"DE",
    "sg:address":"Carl-Zei\u00df-Str 2",
    "sg:city":"Wagh\u00e4usel",
    "sg:phone":"+49 7254/93360",
    "sg:postcode":"68753",
    "sg:province":"Baden-W\u00fcrttemberg",
    "wof:name":"Sitec-glas Gmbh",
    "wof:placetype":"venue"
},
  "geometry": {"coordinates":[8.5453910828,49.2507247925],"type":"Point"}
}