{
  "type": "Feature",
  "properties": {
    "iso:country":"DE",
    "sg:address":"Wiesbadener Str. 58",
    "sg:city":"Idstein",
    "sg:phone":"+49 6126/93550",
    "sg:postcode":"65510",
    "sg:province":"Hessen",
    "wof:name":"Grosso",
    "wof:placetype":"venue"
},
  "geometry": {"coordinates":[8.2621870041,50.2175636292],"type":"Point"}
}