{
  "type": "Feature",
  "properties": {
    "iso:country":"DE",
    "sg:address":"Uhlandstr. 81",
    "sg:city":"Berlin",
    "sg:phone":"+49 30/860158",
    "sg:postcode":"10717",
    "sg:province":"Berlin",
    "wof:name":"Vero Handels Gmbh",
    "wof:placetype":"venue"
},
  "geometry": {"coordinates":[13.3227138519,52.4899177551],"type":"Point"}
}