{
  "type": "Feature",
  "properties": {
    "iso:country":"DE",
    "sg:address":"Am Sophienhof 3",
    "sg:city":"Flensburg",
    "sg:phone":"+49 6894/9610",
    "sg:postcode":"24941",
    "sg:province":"Schleswig-Holstein",
    "wof:name":"Saar Pr\u00e4zision Gmbh",
    "wof:placetype":"venue"
},
  "geometry": {"coordinates":[7.1010890007,49.2722854614],"type":"Point"}
}