{
  "type": "Feature",
  "properties": {
    "iso:country":"DE",
    "sg:address":"Helmpertstr. 2",
    "sg:city":"M\u00fcnchen",
    "sg:phone":"+49 89/566484",
    "sg:postcode":"80687",
    "sg:province":"Bayern",
    "wof:name":"Engl Gmbh",
    "wof:placetype":"venue"
},
  "geometry": {"coordinates":[11.5025587082,48.140914917],"type":"Point"}
}