{
  "type": "Feature",
  "properties": {
    "iso:country":"DE",
    "sg:address":"W\u00fcrzburger Str. 10",
    "sg:city":"Burgebrach",
    "sg:phone":"+49 9546/92250",
    "sg:postcode":"96138",
    "sg:province":"Bayern",
    "wof:name":"Sch\u00fctz Kg",
    "wof:placetype":"venue"
},
  "geometry": {"coordinates":[10.7378635406,49.8277702332],"type":"Point"}
}