{
  "type": "Feature",
  "properties": {
    "iso:country":"DE",
    "sg:address":"Theresienstr. 73",
    "sg:city":"M\u00fcnchen",
    "sg:phone":"+49 89/5234039",
    "sg:postcode":"80333",
    "sg:province":"Bayern",
    "wof:name":"Ulrich Traude",
    "wof:placetype":"venue"
},
  "geometry": {"coordinates":[11.562824,48.15136],"type":"Point"}
}