{
  "type": "Feature",
  "properties": {
    "iso:country":"DE",
    "sg:address":"Starenstr. 50",
    "sg:city":"Kelheim",
    "sg:phone":"+49 9441/70000",
    "sg:postcode":"93309",
    "sg:province":"Bayern",
    "wof:name":"Devappa Dr. R. Zinsser Gmbh",
    "wof:placetype":"venue"
},
  "geometry": {"coordinates":[11.8929576874,48.9141464233],"type":"Point"}
}