{
  "type": "Feature",
  "properties": {
    "iso:country":"DE",
    "sg:address":"Zesenstr. 2",
    "sg:city":"Hamburg",
    "sg:phone":"+49 40/2700743",
    "sg:postcode":"22301",
    "sg:province":"Hamburg",
    "wof:name":"Kurt Kamma Heilpraktiker",
    "wof:placetype":"venue"
},
  "geometry": {"coordinates":[10.0052537918,53.5877418518],"type":"Point"}
}