{
  "type": "Feature",
  "properties": {
    "iso:country":"DE",
    "sg:address":"L\u00f6fflerstr. 1",
    "sg:city":"Freyung",
    "sg:phone":"+49 8551/9750",
    "sg:postcode":"94078",
    "sg:province":"Bayern",
    "wof:name":"Seaquist-l\u00f6ffler Kunststoffwerk Gmbh",
    "wof:placetype":"venue"
},
  "geometry": {"coordinates":[13.56854,48.822327],"type":"Point"}
}