{
  "type": "Feature",
  "properties": {
    "iso:country":"DE",
    "sg:address":"Goldbergweg 6-1",
    "sg:city":"Remseck",
    "sg:phone":"+49 7146/89410",
    "sg:postcode":"71686",
    "sg:province":"Baden-W\u00fcrttemberg",
    "wof:name":"B\u00e4rbel Bauknecht-feik Steuerberater",
    "wof:placetype":"venue"
},
  "geometry": {"coordinates":[9.2489700317,48.8675689697],"type":"Point"}
}