{
  "type": "Feature",
  "properties": {
    "iso:country":"DE",
    "sg:address":"Hauptstr. 103",
    "sg:city":"Langenfeld",
    "sg:phone":"+49 2173/17847",
    "sg:postcode":"40764",
    "sg:province":"Nordrhein-Westfalen",
    "wof:name":"Hans W. Backeshoff",
    "wof:placetype":"venue"
},
  "geometry": {"coordinates":[6.9489860535,51.1067962646],"type":"Point"}
}