{
  "type": "Feature",
  "properties": {
    "iso:country":"DE",
    "sg:address":"Schlo\u00dfberg 1",
    "sg:city":"Herrenberg",
    "sg:phone":"+49 7032/920777",
    "sg:postcode":"71083",
    "sg:province":"Baden-W\u00fcrttemberg",
    "wof:name":"Gastst\u00e4tte Schlo\u00dfkeller",
    "wof:placetype":"venue"
},
  "geometry": {"coordinates":[8.8738307953,48.597454071],"type":"Point"}
}