{
  "type": "Feature",
  "properties": {
    "iso:country":"DE",
    "sg:address":"Vaalser Str. 164d",
    "sg:city":"Aachen",
    "sg:phone":"+49 241/874761",
    "sg:postcode":"52074",
    "sg:province":"Nordrhein-Westfalen",
    "wof:name":"Goertz & Sch\u00f6nfeld",
    "wof:placetype":"venue"
},
  "geometry": {"coordinates":[6.064354,50.770336],"type":"Point"}
}