{
  "type": "Feature",
  "properties": {
    "iso:country":"DE",
    "sg:address":"M\u00fcnsterstr. 135",
    "sg:city":"D\u00fclmen",
    "sg:phone":"+49 2594/94760",
    "sg:postcode":"48249",
    "sg:province":"Nordrhein-Westfalen",
    "wof:name":"G\u00fcnter Wiesel",
    "wof:placetype":"venue"
},
  "geometry": {"coordinates":[7.286758,51.83884],"type":"Point"}
}