{
  "type": "Feature",
  "properties": {
    "iso:country":"DE",
    "sg:address":"Schlitzer Str. 17",
    "sg:city":"Niederaula",
    "sg:phone":"+49 6625/5170",
    "sg:postcode":"36272",
    "sg:province":"Hessen",
    "wof:name":"Heinz Spohr Elektro",
    "wof:placetype":"venue"
},
  "geometry": {"coordinates":[9.602730751,50.7990608215],"type":"Point"}
}