{
  "type": "Feature",
  "properties": {
    "iso:country":"DE",
    "sg:address":"Ahornstr. 2",
    "sg:city":"Neustadt",
    "sg:phone":"+49 8402/930030",
    "sg:postcode":"93333",
    "sg:province":"Bayern",
    "wof:name":"Evr S\u00fcd Entsorgungs- Und Verwertungs Gmbh",
    "wof:placetype":"venue"
},
  "geometry": {"coordinates":[13.7533998489,51.0747718811],"type":"Point"}
}