{
  "type": "Feature",
  "properties": {
    "iso:country":"DE",
    "sg:address":"Paulinenstr. 43",
    "sg:city":"Detmold",
    "sg:phone":"+49 5231/24637",
    "sg:postcode":"32756",
    "sg:province":"Nordrhein-Westfalen",
    "wof:name":"Redaktion Die M\u00fchle Und Mischfuttertechnik",
    "wof:placetype":"venue"
},
  "geometry": {"coordinates":[8.8748569489,51.9374809265],"type":"Point"}
}