{
  "type": "Feature",
  "properties": {
    "iso:country":"DE",
    "sg:address":"Hauptstr. 12",
    "sg:city":"Wallhalben",
    "sg:phone":"+49 6375/242",
    "sg:postcode":"66917",
    "sg:province":"Rheinland-Pfalz",
    "wof:name":"Hummel-apotheke",
    "wof:placetype":"venue"
},
  "geometry": {"coordinates":[7.523548,49.316082],"type":"Point"}
}