{
  "type": "Feature",
  "properties": {
    "iso:country":"DE",
    "sg:address":"Osthofener Str. 99",
    "sg:city":"Eich",
    "sg:phone":"+49 6246/363",
    "sg:postcode":"67575",
    "sg:province":"Rheinland-Pfalz",
    "wof:name":"Bernhard Arnt",
    "wof:placetype":"venue"
},
  "geometry": {"coordinates":[8.3873510361,49.7449836731],"type":"Point"}
}