{
  "type": "Feature",
  "properties": {
    "iso:country":"DE",
    "sg:address":"Luisenstr. 52",
    "sg:city":"Nordenham",
    "sg:phone":"+49 4731/7688",
    "sg:postcode":"26954",
    "sg:province":"Niedersachsen",
    "wof:name":"J\u00fcrgen Berner Steinmetzmeister",
    "wof:placetype":"venue"
},
  "geometry": {"coordinates":[8.4757413864,53.4963684082],"type":"Point"}
}