{
  "type": "Feature",
  "properties": {
    "iso:country":"DE",
    "sg:address":"Lausicker Str. 3",
    "sg:city":"Borna",
    "sg:phone":"+49 3433/851821",
    "sg:postcode":"04552",
    "sg:province":"Sachsen",
    "wof:name":"Sachsenst\u00fcbl",
    "wof:placetype":"venue"
},
  "geometry": {"coordinates":[12.4874305725,51.1206130981],"type":"Point"}
}