{
  "type": "Feature",
  "properties": {
    "iso:country":"DE",
    "sg:address":"Alte Schlo\u00dfstr. 2",
    "sg:city":"Neuwied",
    "sg:postcode":"56566",
    "sg:province":"Rheinland-Pfalz",
    "wof:name":"Schlo\u00dfkeller Engers",
    "wof:placetype":"venue"
},
  "geometry": {"coordinates":[7.5439929962,50.423210144],"type":"Point"}
}