{
  "type": "Feature",
  "properties": {
    "iso:country":"DE",
    "sg:address":"Georg-Schwarz-Str. 159",
    "sg:city":"Leipzig",
    "sg:phone":"+49 341/4426410",
    "sg:postcode":"04179",
    "sg:province":"Sachsen",
    "wof:name":"Die Drei Pflegedienst",
    "wof:placetype":"venue"
},
  "geometry": {"coordinates":[12.308379,51.35014],"type":"Point"}
}