{
  "type": "Feature",
  "properties": {
    "iso:country":"DE",
    "sg:address":"Bahnhofstr. 86",
    "sg:city":"Deggendorf",
    "sg:phone":"+49 991/8820",
    "sg:postcode":"94469",
    "sg:province":"Bayern",
    "wof:name":"Dr. Med. Manfred Leubner Arzt F\u00fcr Allgemeinmedizin",
    "wof:placetype":"venue"
},
  "geometry": {"coordinates":[12.9522590637,48.8378181458],"type":"Point"}
}