{
  "type": "Feature",
  "properties": {
    "iso:country":"DE",
    "sg:city":"Buxtehude",
    "sg:phone":"+49 6109/50510",
    "sg:postcode":"21614",
    "sg:province":"Niedersachsen",
    "wof:name":"Anlageberatung , Steueroptimierung Und Fonds - Mira Gmbh",
    "wof:placetype":"venue"
},
  "geometry": {"coordinates":[9.703144,53.477165],"type":"Point"}
}