{
  "type": "Feature",
  "properties": {
    "iso:country":"DE",
    "sg:city":"Mirskofen",
    "sg:phone":"+49 8703/2051",
    "sg:postcode":"84051",
    "sg:province":"Bayern",
    "wof:name":"Raiffeisenbank Essenbach Eg",
    "wof:placetype":"venue"
},
  "geometry": {"coordinates":[12.192305,48.612411],"type":"Point"}
}