{
  "type": "Feature",
  "properties": {
    "iso:country":"DE",
    "sg:address":"Gutenbergstr. 18",
    "sg:city":"Marburg",
    "sg:phone":"+49 6421/23690",
    "sg:postcode":"35037",
    "sg:province":"Hessen",
    "wof:name":"Collegium Gentium",
    "wof:placetype":"venue"
},
  "geometry": {"coordinates":[8.7693986893,50.8043518066],"type":"Point"}
}