{
  "type": "Feature",
  "properties": {
    "iso:country":"DE",
    "sg:address":"Trollingerstr. 4",
    "sg:city":"Stuttgart",
    "sg:phone":"+49 711/3260322",
    "sg:postcode":"70329",
    "sg:province":"Baden-W\u00fcrttemberg",
    "wof:name":"Weinstube-cafe L\u00f6wen",
    "wof:placetype":"venue"
},
  "geometry": {"coordinates":[9.2789115906,48.7768821716],"type":"Point"}
}