{
  "type": "Feature",
  "properties": {
    "iso:country":"DE",
    "sg:address":"Bahnhofstr. 33",
    "sg:city":"Mittenwald",
    "sg:phone":"+49 8823/8222",
    "sg:postcode":"82481",
    "sg:province":"Bayern",
    "wof:name":"Hallenbad",
    "wof:placetype":"venue"
},
  "geometry": {"coordinates":[11.2627897263,47.4411888123],"type":"Point"}
}