{
  "type": "Feature",
  "properties": {
    "iso:country":"DE",
    "sg:address":"Herzogenbuscher Str. 1",
    "sg:city":"Trier",
    "sg:phone":"+49 651/29900",
    "sg:postcode":"54292",
    "sg:province":"Rheinland-Pfalz",
    "wof:name":"Postillion Karin Thull & Sohn Ohg",
    "wof:placetype":"venue"
},
  "geometry": {"coordinates":[6.6552500725,49.7661247253],"type":"Point"}
}