{
  "type": "Feature",
  "properties": {
    "iso:country":"DE",
    "sg:address":"Tornescher Weg 140",
    "sg:city":"Uetersen",
    "sg:phone":"+49 4122/95230",
    "sg:postcode":"25436",
    "sg:province":"Schleswig-Holstein",
    "wof:name":"Osbahr Gmbh",
    "wof:placetype":"venue"
},
  "geometry": {"coordinates":[9.6989383698,53.6900787354],"type":"Point"}
}