{
  "type": "Feature",
  "properties": {
    "iso:country":"DE",
    "sg:address":"Walther-Rathenau-Str. 20",
    "sg:city":"Wurzen",
    "sg:phone":"+49 3425/814987",
    "sg:postcode":"04808",
    "sg:province":"Sachsen",
    "wof:name":"Gerhard Ober",
    "wof:placetype":"venue"
},
  "geometry": {"coordinates":[12.742469,51.366825],"type":"Point"}
}