{
  "type": "Feature",
  "properties": {
    "iso:country":"DE",
    "sg:address":"Goethestr. 13",
    "sg:city":"B\u00f6blingen",
    "sg:phone":"+49 7031/673011",
    "sg:postcode":"71034",
    "sg:province":"Baden-W\u00fcrttemberg",
    "wof:name":"Spedition Erhardt Inh. Kurt Erhardt",
    "wof:placetype":"venue"
},
  "geometry": {"coordinates":[8.9596004486,48.6936454773],"type":"Point"}
}