{
  "type": "Feature",
  "properties": {
    "iso:country":"DE",
    "sg:address":"Burgstr. 8",
    "sg:city":"Haibach",
    "sg:phone":"+49 6021/60858",
    "sg:postcode":"63808",
    "sg:province":"Bayern",
    "wof:name":"Burgkindergarten Und Krankenpflege",
    "wof:placetype":"venue"
},
  "geometry": {"coordinates":[9.2035093307,49.9674453735],"type":"Point"}
}