{
  "type": "Feature",
  "properties": {
    "iso:country":"DE",
    "sg:address":"Adolf-Hetzler-Str. 1",
    "sg:city":"Saarlouis",
    "sg:phone":"+49 6831/43366",
    "sg:postcode":"66740",
    "sg:province":"Saarland",
    "wof:name":"Dr. Med. Peter Kiefer",
    "wof:placetype":"venue"
},
  "geometry": {"coordinates":[6.7547020912,49.3144493103],"type":"Point"}
}