{
  "type": "Feature",
  "properties": {
    "iso:country":"DE",
    "sg:address":"Langstr. 46-48",
    "sg:city":"M\u00f6rfelden-Walldorf",
    "sg:phone":"+49 6105/5368",
    "sg:postcode":"64546",
    "sg:province":"Hessen",
    "wof:name":"K. Und M. K\u00fcchler Ohg",
    "wof:placetype":"venue"
},
  "geometry": {"coordinates":[8.577266,50.001034],"type":"Point"}
}