{
  "type": "Feature",
  "properties": {
    "iso:country":"DE",
    "sg:address":"Mittelweg 7",
    "sg:city":"Frankfurt",
    "sg:phone":"+49 69/95530749",
    "sg:postcode":"60318",
    "sg:province":"Hessen",
    "wof:name":"S&p Softwaredesign Und Platinenentwicklung Sascha Nitsch",
    "wof:placetype":"venue"
},
  "geometry": {"coordinates":[8.6845912933,50.1210289001],"type":"Point"}
}