{
  "type": "Feature",
  "properties": {
    "iso:country":"DE",
    "sg:address":"Odenthalstr. 32",
    "sg:city":"Krefeld",
    "sg:phone":"+49 2151/300465",
    "sg:postcode":"47807",
    "sg:province":"Nordrhein-Westfalen",
    "wof:name":"Magdalene Witten",
    "wof:placetype":"venue"
},
  "geometry": {"coordinates":[6.5899062157,51.3008537292],"type":"Point"}
}