{
  "type": "Feature",
  "properties": {
    "iso:country":"DE",
    "sg:address":"Sonnenstr. 18",
    "sg:city":"Butjadingen",
    "sg:phone":"+49 4736/102258",
    "sg:postcode":"26969",
    "sg:province":"Niedersachsen",
    "wof:name":"J\u00fcrgen Krummheuer",
    "wof:placetype":"venue"
},
  "geometry": {"coordinates":[8.2779684067,53.5886001587],"type":"Point"}
}