{
  "type": "Feature",
  "properties": {
    "iso:country":"DE",
    "sg:address":"Gestringer Str. 30",
    "sg:city":"Espelkamp",
    "sg:phone":"+49 5743/1437",
    "sg:postcode":"32339",
    "sg:province":"Nordrhein-Westfalen",
    "wof:name":"Kamps Bierstuben",
    "wof:placetype":"venue"
},
  "geometry": {"coordinates":[8.6089200974,52.352104187],"type":"Point"}
}