{
  "type": "Feature",
  "properties": {
    "iso:country":"DE",
    "sg:address":"Kunigundenruhstr. 27",
    "sg:city":"Bamberg",
    "sg:phone":"+49 951/27631",
    "sg:postcode":"96050",
    "sg:province":"Bayern",
    "wof:name":"Andreas Und Adam Emmerling",
    "wof:placetype":"venue"
},
  "geometry": {"coordinates":[10.900581,49.897881],"type":"Point"}
}