{
  "type": "Feature",
  "properties": {
    "iso:country":"DE",
    "sg:address":"Prinzenstr. 49",
    "sg:city":"Duisburg",
    "sg:phone":"+49 203/338960",
    "sg:postcode":"47058",
    "sg:province":"Nordrhein-Westfalen",
    "wof:name":"Immekus Der Fitnessclub",
    "wof:placetype":"venue"
},
  "geometry": {"coordinates":[6.791601181,51.4357757568],"type":"Point"}
}