{
  "type": "Feature",
  "properties": {
    "iso:country":"DE",
    "sg:address":"Hauptstr. 11",
    "sg:city":"Brielow",
    "sg:phone":"+49 33837/42034",
    "sg:postcode":"14778",
    "sg:province":"Brandenburg",
    "wof:name":"R. Schniete Immobilienmakler",
    "wof:placetype":"venue"
},
  "geometry": {"coordinates":[12.5414237976,52.461315155],"type":"Point"}
}