{
  "type": "Feature",
  "properties": {
    "iso:country":"DE",
    "sg:address":"Dechant-Wolfgarten-Str. 85",
    "sg:city":"Euskirchen",
    "sg:phone":"+49 2251/94850",
    "sg:postcode":"53881",
    "sg:province":"Nordrhein-Westfalen",
    "wof:name":"Kalff Vliesstoffe Gmbh",
    "wof:placetype":"venue"
},
  "geometry": {"coordinates":[6.812101841,50.6312789917],"type":"Point"}
}