{
  "type": "Feature",
  "properties": {
    "iso:country":"DE",
    "sg:address":"Appenrother Weg 2",
    "sg:city":"Bad Emstal",
    "sg:phone":"+49 5624/1555",
    "sg:postcode":"34308",
    "sg:province":"Hessen",
    "wof:name":"R-kauf",
    "wof:placetype":"venue"
},
  "geometry": {"coordinates":[9.2590389252,51.2466888428],"type":"Point"}
}