{
  "type": "Feature",
  "properties": {
    "iso:country":"DE",
    "sg:address":"Friedrichring 33",
    "sg:city":"Freiburg",
    "sg:phone":"+49 761/272013",
    "sg:postcode":"79098",
    "sg:province":"Baden-W\u00fcrttemberg",
    "wof:name":"M\u00fcnchener Verein Allgemeine Versicherungs-ag",
    "wof:placetype":"venue"
},
  "geometry": {"coordinates":[7.849571228,47.9986877441],"type":"Point"}
}