{
  "type": "Feature",
  "properties": {
    "iso:country":"DE",
    "sg:address":"Oberstdorfer Str. 18",
    "sg:city":"Stuttgart",
    "sg:phone":"+49 711/3369350",
    "sg:postcode":"70327",
    "sg:province":"Baden-W\u00fcrttemberg",
    "wof:name":"Dees Gmbh",
    "wof:placetype":"venue"
},
  "geometry": {"coordinates":[9.2524328232,48.7821235657],"type":"Point"}
}