{
  "type": "Feature",
  "properties": {
    "iso:country":"DE",
    "sg:address":"Am Arzberg 7",
    "sg:city":"Steinbach-Hallenberg",
    "sg:phone":"+49 36847/31771",
    "sg:postcode":"98587",
    "sg:province":"Th\u00fcringen",
    "wof:name":"K. Burkhardt",
    "wof:placetype":"venue"
},
  "geometry": {"coordinates":[10.565249,50.702312],"type":"Point"}
}