{
  "type": "Feature",
  "properties": {
    "iso:country":"DE",
    "sg:address":"Hauptstr. 34",
    "sg:city":"Erfurt",
    "sg:phone":"+49 361/7968079",
    "sg:postcode":"99094",
    "sg:province":"Th\u00fcringen",
    "wof:name":"Gr\u00fcnes Tal",
    "wof:placetype":"venue"
},
  "geometry": {"coordinates":[10.9920539856,50.9213867188],"type":"Point"}
}