{
  "type": "Feature",
  "properties": {
    "iso:country":"DE",
    "sg:address":"Poststr. 20",
    "sg:city":"Hessisch Lichtenau",
    "sg:phone":"+49 5602/2167",
    "sg:postcode":"37235",
    "sg:province":"Hessen",
    "wof:name":"Elvira Stumm-kruch",
    "wof:placetype":"venue"
},
  "geometry": {"coordinates":[9.7258529663,51.1981964111],"type":"Point"}
}