{
  "type": "Feature",
  "properties": {
    "iso:country":"DE",
    "sg:address":"Keltenstr. 23",
    "sg:city":"Sauerlach",
    "sg:phone":"+49 8104/1856",
    "sg:postcode":"82054",
    "sg:province":"Bayern",
    "wof:name":"Eleonore Dinius",
    "wof:placetype":"venue"
},
  "geometry": {"coordinates":[11.6400184631,47.9692268372],"type":"Point"}
}