{
  "type": "Feature",
  "properties": {
    "iso:country":"DE",
    "sg:address":"Pfluggasse 14",
    "sg:city":"Biberach",
    "sg:phone":"+49 7351/34170",
    "sg:postcode":"88400",
    "sg:province":"Baden-W\u00fcrttemberg",
    "wof:name":"G\u00fcnter Schmitt Und Partner Architekten",
    "wof:placetype":"venue"
},
  "geometry": {"coordinates":[9.79109,48.098511],"type":"Point"}
}