{
  "type": "Feature",
  "properties": {
    "iso:country":"DE",
    "sg:address":"Wilhelmstr. 25",
    "sg:city":"Balingen",
    "sg:phone":"+49 7433/170349",
    "sg:postcode":"72336",
    "sg:province":"Baden-W\u00fcrttemberg",
    "wof:name":"Stadtb\u00fccherei",
    "wof:placetype":"venue"
},
  "geometry": {"coordinates":[8.849815,48.273682],"type":"Point"}
}