{
  "type": "Feature",
  "properties": {
    "iso:country":"DE",
    "sg:address":"Rathausstr. 4",
    "sg:city":"Achern",
    "sg:phone":"+49 7841/4105",
    "sg:postcode":"77855",
    "sg:province":"Baden-W\u00fcrttemberg",
    "wof:name":"Peter",
    "wof:placetype":"venue"
},
  "geometry": {"coordinates":[8.034505,48.605274],"type":"Point"}
}