{
  "type": "Feature",
  "properties": {
    "iso:country":"DE",
    "sg:address":"Nordstr. 16",
    "sg:city":"Nentershausen",
    "sg:phone":"+49 6485/1345",
    "sg:postcode":"56412",
    "sg:province":"Rheinland-Pfalz",
    "wof:name":"Reinhard Laux",
    "wof:placetype":"venue"
},
  "geometry": {"coordinates":[7.9340500832,50.4243278503],"type":"Point"}
}