{
  "type": "Feature",
  "properties": {
    "iso:country":"DE",
    "sg:address":"Kolinscher Weg 10",
    "sg:city":"Kerken",
    "sg:phone":"+49 2833/57290",
    "sg:postcode":"47647",
    "sg:province":"Nordrhein-Westfalen",
    "wof:name":"Posnet Gbr",
    "wof:placetype":"venue"
},
  "geometry": {"coordinates":[6.4191980362,51.4441757202],"type":"Point"}
}