{
  "type": "Feature",
  "properties": {
    "iso:country":"DE",
    "sg:address":"Itzbachweg 12",
    "sg:city":"Idstein",
    "sg:phone":"+49 6126/70228",
    "sg:postcode":"65510",
    "sg:province":"Hessen",
    "wof:name":"Frank Schmidt",
    "wof:placetype":"venue"
},
  "geometry": {"coordinates":[8.25547,50.23991],"type":"Point"}
}