{
  "type": "Feature",
  "properties": {
    "iso:country":"DE",
    "sg:address":"Friedrich-Ebert-Str. 18",
    "sg:city":"Datteln",
    "sg:phone":"+49 2363/34851",
    "sg:postcode":"45711",
    "sg:province":"Nordrhein-Westfalen",
    "wof:name":"Ewert Naturmarkt Inh. Vera Ewert E. Kfr.",
    "wof:placetype":"venue"
},
  "geometry": {"coordinates":[7.3363370895,51.6517829895],"type":"Point"}
}