{
  "type": "Feature",
  "properties": {
    "iso:country":"DE",
    "sg:address":"Schleinufer 14",
    "sg:city":"Magdeburg",
    "sg:phone":"+49 391/5440966",
    "sg:postcode":"39104",
    "sg:province":"Sachsen-Anhalt",
    "wof:name":"Restaurant Athen Inh. Joannis Gkinis",
    "wof:placetype":"venue"
},
  "geometry": {"coordinates":[11.6323537827,52.1205596924],"type":"Point"}
}