{
  "type": "Feature",
  "properties": {
    "iso:country":"DE",
    "sg:address":"Fifaweg 1",
    "sg:city":"Pfullingen",
    "sg:phone":"+49 115464",
    "sg:postcode":"72793",
    "sg:province":"Baden-W\u00fcrttemberg",
    "wof:name":"Www.fifamafia.de.vu - Fifamafia Online",
    "wof:placetype":"venue"
},
  "geometry": {"coordinates":[9.226949,48.465744],"type":"Point"}
}