{
  "type": "Feature",
  "properties": {
    "iso:country":"DE",
    "sg:address":"Benderstr. 95",
    "sg:city":"D\u00fcsseldorf",
    "sg:phone":"+49 211/283544",
    "sg:postcode":"40625",
    "sg:province":"Nordrhein-Westfalen",
    "wof:name":"Inas-industrie-assekuranz Vermittlungsgesellschaft Mbh",
    "wof:placetype":"venue"
},
  "geometry": {"coordinates":[6.8502540588,51.2385749817],"type":"Point"}
}