{
  "type": "Feature",
  "properties": {
    "iso:country":"DE",
    "sg:address":"Greimelscheider Str. 1",
    "sg:city":"Lambertsberg",
    "sg:phone":"+49 6554/573",
    "sg:postcode":"54649",
    "sg:province":"Rheinland-Pfalz",
    "wof:name":"W. Weber",
    "wof:placetype":"venue"
},
  "geometry": {"coordinates":[6.3969540596,50.092010498],"type":"Point"}
}