{
  "type": "Feature",
  "properties": {
    "iso:country":"DE",
    "sg:address":"Im Siebengehege 15",
    "sg:city":"G\u00fcnthersleben",
    "sg:phone":"+49 36256/21434",
    "sg:postcode":"99869",
    "sg:province":"Th\u00fcringen",
    "wof:name":"Bernd Bauer",
    "wof:placetype":"venue"
},
  "geometry": {"coordinates":[10.7681779861,50.9000816345],"type":"Point"}
}