{
  "type": "Feature",
  "properties": {
    "iso:country":"DE",
    "sg:address":"Puschkinplatz 7",
    "sg:city":"Gera",
    "sg:postcode":"07545",
    "sg:province":"Th\u00fcringen",
    "wof:name":"Wissenschaftliche Allgemeinbibliothek",
    "wof:placetype":"venue"
},
  "geometry": {"coordinates":[12.0789,50.879391],"type":"Point"}
}