{
  "type": "Feature",
  "properties": {
    "iso:country":"DE",
    "sg:address":"Leonhard-Tietz-Str. 1",
    "sg:city":"K\u00f6ln",
    "sg:postcode":"50676",
    "sg:province":"Nordrhein-Westfalen",
    "wof:name":"Cibi Beteiligungsges.mbh & Co. Objekt Frankfurt Zeil",
    "wof:placetype":"venue"
},
  "geometry": {"coordinates":[6.951558,50.933895],"type":"Point"}
}