{
  "type": "Feature",
  "properties": {
    "iso:country":"DE",
    "sg:address":"H\u00fclhovener Str. 92",
    "sg:city":"Heinsberg",
    "sg:phone":"+49 2452/62530",
    "sg:postcode":"52525",
    "sg:province":"Nordrhein-Westfalen",
    "wof:name":"Dohmen",
    "wof:placetype":"venue"
},
  "geometry": {"coordinates":[6.123925209,51.047832489],"type":"Point"}
}