{
  "type": "Feature",
  "properties": {
    "iso:country":"DE",
    "sg:address":"Lange Str. 17",
    "sg:city":"Reinhardshagen",
    "sg:phone":"+49 5544/509",
    "sg:postcode":"34359",
    "sg:province":"Hessen",
    "wof:name":"F. Und M. Lind",
    "wof:placetype":"venue"
},
  "geometry": {"coordinates":[9.6023845673,51.4942932129],"type":"Point"}
}