{
  "type": "Feature",
  "properties": {
    "iso:country":"DE",
    "sg:address":"Simbacher Str. 40",
    "sg:city":"Rotthalm\u00fcnster",
    "sg:phone":"+49 8533/438",
    "sg:postcode":"94094",
    "sg:province":"Bayern",
    "wof:name":"W. Hallhuber Kunstmaler",
    "wof:placetype":"venue"
},
  "geometry": {"coordinates":[13.200856,48.35445],"type":"Point"}
}