{
  "type": "Feature",
  "properties": {
    "iso:country":"DE",
    "sg:address":"Bahnhofstr. 22",
    "sg:city":"Thannhausen",
    "sg:phone":"+49 8281/4080",
    "sg:postcode":"86470",
    "sg:province":"Bayern",
    "wof:name":"Martina Gr\u00f6nda Rechtsanw\u00e4ltin",
    "wof:placetype":"venue"
},
  "geometry": {"coordinates":[10.4694623947,48.2839927673],"type":"Point"}
}