{
  "type": "Feature",
  "properties": {
    "iso:country":"DE",
    "sg:address":"Hauptstr. 13",
    "sg:city":"Mengkofen",
    "sg:phone":"+49 8733/930917",
    "sg:postcode":"84152",
    "sg:province":"Bayern",
    "wof:name":"X. Buchner",
    "wof:placetype":"venue"
},
  "geometry": {"coordinates":[12.4436044693,48.7214393616],"type":"Point"}
}