{
  "type": "Feature",
  "properties": {
    "iso:country":"DE",
    "sg:address":"Burgstr. 14",
    "sg:city":"Beverungen",
    "sg:phone":"+49 5273/32000",
    "sg:postcode":"37688",
    "sg:province":"Nordrhein-Westfalen",
    "wof:name":"Klaus Feldhaus",
    "wof:placetype":"venue"
},
  "geometry": {"coordinates":[9.373611,51.662514],"type":"Point"}
}