{
  "type": "Feature",
  "properties": {
    "iso:country":"DE",
    "sg:address":"Langensteiner Str. 2",
    "sg:city":"Stadtallendorf",
    "sg:phone":"+49 6428/1609",
    "sg:postcode":"35260",
    "sg:province":"Hessen",
    "wof:name":"Hans Henkel",
    "wof:placetype":"venue"
},
  "geometry": {"coordinates":[9.021074,50.859158],"type":"Point"}
}