{
  "type": "Feature",
  "properties": {
    "iso:country":"DE",
    "sg:address":"Wallensteinstr. 47",
    "sg:city":"Hannover",
    "sg:phone":"+49 511/425349",
    "sg:postcode":"30459",
    "sg:province":"Niedersachsen",
    "wof:name":"R. Und V. D\u00f6ring",
    "wof:placetype":"venue"
},
  "geometry": {"coordinates":[9.709869,52.341793],"type":"Point"}
}