{
  "type": "Feature",
  "properties": {
    "iso:country":"DE",
    "sg:address":"Hauptstr. 138",
    "sg:city":"V\u00f6lklingen",
    "sg:phone":"+49 6802/1373",
    "sg:postcode":"66333",
    "sg:province":"Saarland",
    "wof:name":"S. Benzm\u00fcller",
    "wof:placetype":"venue"
},
  "geometry": {"coordinates":[6.74548,49.184673],"type":"Point"}
}