{
  "type": "Feature",
  "properties": {
    "iso:country":"DE",
    "sg:address":"Friedrich-Ebert-Str. 15",
    "sg:city":"Michelstadt",
    "sg:phone":"+49 6061/94270",
    "sg:postcode":"64720",
    "sg:province":"Hessen",
    "wof:name":"Kaufhalle Ag",
    "wof:placetype":"venue"
},
  "geometry": {"coordinates":[9.00166,49.676003],"type":"Point"}
}