{
  "type": "Feature",
  "properties": {
    "iso:country":"DE",
    "sg:address":"Jahnstr. 20",
    "sg:city":"Stra\u00dfkirchen",
    "sg:phone":"+49 9424/714",
    "sg:postcode":"94342",
    "sg:province":"Bayern",
    "wof:name":"Georg Wax",
    "wof:placetype":"venue"
},
  "geometry": {"coordinates":[12.717383,48.835011],"type":"Point"}
}