{
  "type": "Feature",
  "properties": {
    "iso:country":"DE",
    "sg:address":"Friedrich-Loose-Str. 8",
    "sg:city":"Dortmund",
    "sg:phone":"+49 231/733346",
    "sg:postcode":"44229",
    "sg:province":"Nordrhein-Westfalen",
    "wof:name":"J\u00fcrgen Schweins Ingenieur",
    "wof:placetype":"venue"
},
  "geometry": {"coordinates":[7.4671092033,51.4540252686],"type":"Point"}
}