{
  "type": "Feature",
  "properties": {
    "iso:country":"DE",
    "sg:address":"Bundesstr.18 - 20a",
    "sg:city":"Th\u00fcr",
    "sg:phone":"+49 4926/5297960",
    "sg:postcode":"56743",
    "sg:province":"Rheinland-Pfalz",
    "wof:name":"Druckerei Kr\u00c4mer Gmbh",
    "wof:placetype":"venue"
},
  "geometry": {"coordinates":[7.2801661491,50.3557777405],"type":"Point"}
}