{
  "type": "Feature",
  "properties": {
    "iso:country":"DE",
    "sg:address":"Pr\u00f6llerstr. 10",
    "sg:city":"Kollnburg",
    "sg:phone":"+49 9942/8394",
    "sg:postcode":"94262",
    "sg:province":"Bayern",
    "wof:name":"Hermann Wieser",
    "wof:placetype":"venue"
},
  "geometry": {"coordinates":[12.8605222702,49.0439949036],"type":"Point"}
}