{
  "type": "Feature",
  "properties": {
    "iso:country":"DE",
    "sg:address":"Hans-Lingl-Str. 17",
    "sg:city":"Krumbach",
    "sg:phone":"+49 8282/88980",
    "sg:postcode":"86381",
    "sg:province":"Bayern",
    "wof:name":"Quabi Garten- Und Heimwerkermarkt Ag",
    "wof:placetype":"venue"
},
  "geometry": {"coordinates":[10.3629417419,48.2554855347],"type":"Point"}
}