{
  "type": "Feature",
  "properties": {
    "iso:country":"DE",
    "sg:address":"Denisstr. 28",
    "sg:city":"Kaiserslautern",
    "sg:phone":"+49 631/357100",
    "sg:postcode":"67663",
    "sg:province":"Rheinland-Pfalz",
    "wof:name":"Backhaus Klein Gmbh",
    "wof:placetype":"venue"
},
  "geometry": {"coordinates":[7.71925,49.443867],"type":"Point"}
}