{
  "type": "Feature",
  "properties": {
    "iso:country":"DE",
    "sg:address":"Bahnhofstr. 5",
    "sg:city":"Mellrichstadt",
    "sg:phone":"+49 9776/9192",
    "sg:postcode":"97638",
    "sg:province":"Bayern",
    "wof:name":"G. Bieber",
    "wof:placetype":"venue"
},
  "geometry": {"coordinates":[10.306,50.424591],"type":"Point"}
}