{
  "type": "Feature",
  "properties": {
    "iso:country":"DE",
    "sg:address":"Kaiserstr. 32",
    "sg:city":"Rastatt",
    "sg:phone":"+49 7222/30783",
    "sg:postcode":"76437",
    "sg:province":"Baden-W\u00fcrttemberg",
    "wof:name":"Men Style",
    "wof:placetype":"venue"
},
  "geometry": {"coordinates":[8.2028045654,48.8577613831],"type":"Point"}
}