{
  "type": "Feature",
  "properties": {
    "iso:country":"DE",
    "sg:address":"Kampstr. 26",
    "sg:city":"Hamburg",
    "sg:phone":"+49 40/436788",
    "sg:postcode":"20357",
    "sg:province":"Hamburg",
    "wof:name":"Walter Schock",
    "wof:placetype":"venue"
},
  "geometry": {"coordinates":[9.9668521881,53.5609970093],"type":"Point"}
}