{
  "type": "Feature",
  "properties": {
    "iso:country":"DE",
    "sg:address":"Fronhofstr. 38",
    "sg:city":"J\u00fclich",
    "sg:phone":"+49 2461/2994",
    "sg:postcode":"52428",
    "sg:province":"Nordrhein-Westfalen",
    "wof:name":"Josef Spohr",
    "wof:placetype":"venue"
},
  "geometry": {"coordinates":[6.350853,50.897461],"type":"Point"}
}