{
  "type": "Feature",
  "properties": {
    "iso:country":"DE",
    "sg:address":"Elsterstr. 63",
    "sg:city":"Leipzig",
    "sg:phone":"+49 341/4794821",
    "sg:postcode":"04109",
    "sg:province":"Sachsen",
    "wof:name":"Wolfgang Such Rechtsanwalt",
    "wof:placetype":"venue"
},
  "geometry": {"coordinates":[12.3603668213,51.3418312073],"type":"Point"}
}