{
  "type": "Feature",
  "properties": {
    "iso:country":"DE",
    "sg:address":"Casinostr. 35",
    "sg:city":"Koblenz",
    "sg:phone":"+49 261/15020",
    "sg:postcode":"56068",
    "sg:province":"Rheinland-Pfalz",
    "wof:name":"Lux Gmbh",
    "wof:placetype":"venue"
},
  "geometry": {"coordinates":[7.5970950127,50.357334137],"type":"Point"}
}