{
  "type": "Feature",
  "properties": {
    "iso:country":"DE",
    "sg:address":"Hainh\u00e4user Str. 74",
    "sg:city":"Rodgau",
    "sg:phone":"+49 6106/5590",
    "sg:postcode":"63110",
    "sg:province":"Hessen",
    "wof:name":"Jakob Faust",
    "wof:placetype":"venue"
},
  "geometry": {"coordinates":[8.8860311508,50.0475959778],"type":"Point"}
}