{
  "type": "Feature",
  "properties": {
    "iso:country":"DE",
    "sg:address":"Schmalbachstr. 18",
    "sg:city":"Bretzfeld",
    "sg:phone":"+49 7946/91170",
    "sg:postcode":"74626",
    "sg:province":"Baden-W\u00fcrttemberg",
    "wof:name":"Markisenbau M\u00fcller Gmbh",
    "wof:placetype":"venue"
},
  "geometry": {"coordinates":[9.4124746323,49.1821022034],"type":"Point"}
}