{
  "type": "Feature",
  "properties": {
    "iso:country":"DE",
    "sg:address":"Waldmannshofen 32",
    "sg:city":"Creglingen",
    "sg:postcode":"97993",
    "sg:province":"Baden-W\u00fcrttemberg",
    "wof:name":"Fr. Albrecht",
    "wof:placetype":"venue"
},
  "geometry": {"coordinates":[10.066397,49.531971],"type":"Point"}
}