{
  "type": "Feature",
  "properties": {
    "iso:country":"DE",
    "sg:address":"Peheimer Str. 39",
    "sg:city":"Vrees",
    "sg:phone":"+49 4479/94800",
    "sg:postcode":"49757",
    "sg:province":"Niedersachsen",
    "wof:name":"Maschinen- Und M\u00fchlenbau Benker & Voet Gmbh",
    "wof:placetype":"venue"
},
  "geometry": {"coordinates":[7.782165,52.887615],"type":"Point"}
}