{
  "type": "Feature",
  "properties": {
    "iso:country":"DE",
    "sg:address":"Albtorplatz 13",
    "sg:city":"Reutlingen",
    "sg:phone":"+49 7121/338344",
    "sg:postcode":"72764",
    "sg:province":"Baden-W\u00fcrttemberg",
    "wof:name":"Citibank Privatkunden Ag",
    "wof:placetype":"venue"
},
  "geometry": {"coordinates":[9.21599,48.490261],"type":"Point"}
}