{
  "type": "Feature",
  "properties": {
    "iso:country":"DE",
    "sg:address":"Sanktjohanserstr. 85",
    "sg:city":"Bad Wiessee",
    "sg:phone":"+49 8022/83513",
    "sg:postcode":"83707",
    "sg:province":"Bayern",
    "wof:name":"Anton Grauvogl Metallbau Gmbh",
    "wof:placetype":"venue"
},
  "geometry": {"coordinates":[11.727013,47.703171],"type":"Point"}
}