{
  "type": "Feature",
  "properties": {
    "iso:country":"DE",
    "sg:address":"Konsulplatz 6",
    "sg:city":"G\u00f6rlitz",
    "sg:phone":"+49 3581/407242",
    "sg:postcode":"02826",
    "sg:province":"Sachsen",
    "wof:name":"K\u00fchn Und Bracke Rechtsanw\u00e4ltinnen",
    "wof:placetype":"venue"
},
  "geometry": {"coordinates":[14.9892683029,51.1498680115],"type":"Point"}
}