{
  "type": "Feature",
  "properties": {
    "iso:country":"DE",
    "sg:address":"Frankfurter Str. 21",
    "sg:city":"Darmstadt",
    "sg:phone":"+49 6151/74511",
    "sg:postcode":"64293",
    "sg:province":"Hessen",
    "wof:name":"S. T\u00f6rk",
    "wof:placetype":"venue"
},
  "geometry": {"coordinates":[8.651078,49.881195],"type":"Point"}
}