{
  "type": "Feature",
  "properties": {
    "iso:country":"DE",
    "sg:address":"Dresdner Str 30",
    "sg:city":"D\u00f6beln",
    "sg:phone":"+49 3431/577913",
    "sg:postcode":"04720",
    "sg:province":"Sachsen",
    "wof:name":"Tecklenborg Gmbh Nutzfahrzeuge Und Gabelstapler",
    "wof:placetype":"venue"
},
  "geometry": {"coordinates":[13.1422653198,51.1209449768],"type":"Point"}
}