{
  "type": "Feature",
  "properties": {
    "iso:country":"DE",
    "sg:address":"Albstr. 163",
    "sg:city":"Eislingen",
    "sg:postcode":"73054",
    "sg:province":"Baden-W\u00fcrttemberg",
    "wof:name":"Eins-a-warenhaus",
    "wof:placetype":"venue"
},
  "geometry": {"coordinates":[9.6913604736,48.6922798157],"type":"Point"}
}