{
  "type": "Feature",
  "properties": {
    "iso:country":"DE",
    "sg:address":"Anton-Jaumann-Industriepark 1",
    "sg:city":"N\u00f6rdlingen",
    "sg:phone":"+49 9081/2120",
    "sg:postcode":"86720",
    "sg:province":"Bayern",
    "wof:name":"Engelhardt Druck Gmbh",
    "wof:placetype":"venue"
},
  "geometry": {"coordinates":[10.503478,48.842468],"type":"Point"}
}