{
  "type": "Feature",
  "properties": {
    "iso:country":"DE",
    "sg:address":"Hauptstr. 1",
    "sg:city":"Lindow",
    "sg:phone":"+49 38828/21652",
    "sg:postcode":"23923",
    "sg:province":"Mecklenburg-Vorpommern",
    "wof:name":"Manfred Meinke",
    "wof:placetype":"venue"
},
  "geometry": {"coordinates":[10.92733,53.795921],"type":"Point"}
}