{
  "type": "Feature",
  "properties": {
    "iso:country":"DE",
    "sg:address":"Niersstr. 6",
    "sg:city":"Kevelaer",
    "sg:phone":"+49 2832/80555",
    "sg:postcode":"47626",
    "sg:province":"Nordrhein-Westfalen",
    "wof:name":"Elisabeth Schumacher",
    "wof:placetype":"venue"
},
  "geometry": {"coordinates":[6.287567,51.596287],"type":"Point"}
}