{
  "type": "Feature",
  "properties": {
    "iso:country":"DE",
    "sg:address":"Schulterblatt 51",
    "sg:city":"Hamburg",
    "sg:phone":"+49 40/436595",
    "sg:postcode":"20357",
    "sg:province":"Hamburg",
    "wof:name":"Gust. Ehrhorn Nachf. Inh. Peter Emmerling",
    "wof:placetype":"venue"
},
  "geometry": {"coordinates":[9.9625301361,53.5610084534],"type":"Point"}
}