{
  "type": "Feature",
  "properties": {
    "iso:country":"DE",
    "sg:address":"Broichstr. 76",
    "sg:city":"Bonn",
    "sg:postcode":"53227",
    "sg:province":"Nordrhein-Westfalen",
    "wof:name":"Sita Hw Umweltservice Gmbh",
    "wof:placetype":"venue"
},
  "geometry": {"coordinates":[7.1435937881,50.7336463928],"type":"Point"}
}