{
  "type": "Feature",
  "properties": {
    "iso:country":"DE",
    "sg:address":"Friedrichstr. 27",
    "sg:city":"Bonn",
    "sg:phone":"+49 228/638555",
    "sg:postcode":"53111",
    "sg:province":"Nordrhein-Westfalen",
    "wof:name":"Opatija Grillgastst\u00e4tten Gmbh",
    "wof:placetype":"venue"
},
  "geometry": {"coordinates":[7.1003489494,50.7368125916],"type":"Point"}
}