{
  "type": "Feature",
  "properties": {
    "iso:country":"DE",
    "sg:address":"Ottostr. 9-11",
    "sg:city":"Heusenstamm",
    "sg:postcode":"63150",
    "sg:province":"Hessen",
    "wof:name":"Stahl Becker Gmbh",
    "wof:placetype":"venue"
},
  "geometry": {"coordinates":[8.799675,50.046974],"type":"Point"}
}