{
  "type": "Feature",
  "properties": {
    "iso:country":"DE",
    "sg:address":"Frankfurter Str. 239",
    "sg:city":"Kassel",
    "sg:phone":"+49 561/473439",
    "sg:postcode":"34134",
    "sg:province":"Hessen",
    "wof:name":"Kago-kamine-kachelofen Gmbh & Co.-deutsche",
    "wof:placetype":"venue"
},
  "geometry": {"coordinates":[9.4717235565,51.2887611389],"type":"Point"}
}