{
  "type": "Feature",
  "properties": {
    "iso:country":"DE",
    "sg:address":"Friedrich-Ebert-Str. 110",
    "sg:city":"Solingen",
    "sg:phone":"+49 212/318484",
    "sg:postcode":"42719",
    "sg:province":"Nordrhein-Westfalen",
    "wof:name":"C. Thrun",
    "wof:placetype":"venue"
},
  "geometry": {"coordinates":[7.044128,51.184628],"type":"Point"}
}