{
  "type": "Feature",
  "properties": {
    "iso:country":"DE",
    "sg:address":"Brackweder Str. 42",
    "sg:city":"Halle",
    "sg:phone":"+49 5201/70669",
    "sg:postcode":"33790",
    "sg:province":"Nordrhein-Westfalen",
    "wof:name":"Verein Jugendzentrum Halle Anke Venohr",
    "wof:placetype":"venue"
},
  "geometry": {"coordinates":[8.398846,52.031826],"type":"Point"}
}