{
  "type": "Feature",
  "properties": {
    "iso:country":"DE",
    "sg:address":"Hauptstr. 48",
    "sg:city":"Sch\u00f6ppingen",
    "sg:phone":"+49 2555/1241",
    "sg:postcode":"48624",
    "sg:province":"Nordrhein-Westfalen",
    "wof:name":"B. Mensing",
    "wof:placetype":"venue"
},
  "geometry": {"coordinates":[7.237526,52.092133],"type":"Point"}
}