{
  "type": "Feature",
  "properties": {
    "iso:country":"DE",
    "sg:address":"In der Barlage 112",
    "sg:city":"Osnabr\u00fcck",
    "sg:phone":"+49 541/43800",
    "sg:postcode":"49078",
    "sg:province":"Niedersachsen",
    "wof:name":"Wilhelm Beckmann Taxi-service Gmbh",
    "wof:placetype":"venue"
},
  "geometry": {"coordinates":[8.0088033676,52.2730484009],"type":"Point"}
}