{
  "type": "Feature",
  "properties": {
    "iso:country":"DE",
    "sg:address":"Oldenburger Str. 51",
    "sg:city":"Edewecht",
    "sg:phone":"+49 4405/6566",
    "sg:postcode":"26188",
    "sg:province":"Niedersachsen",
    "wof:name":"Silke Rippen",
    "wof:placetype":"venue"
},
  "geometry": {"coordinates":[7.99295,53.124786],"type":"Point"}
}