{
  "type": "Feature",
  "properties": {
    "iso:country":"DE",
    "sg:address":"Am Hain 13",
    "sg:city":"Wunstorf",
    "sg:phone":"+49 5031/72228",
    "sg:postcode":"31515",
    "sg:province":"Niedersachsen",
    "wof:name":"Reinhard Wolf",
    "wof:placetype":"venue"
},
  "geometry": {"coordinates":[9.4665307999,52.4254074097],"type":"Point"}
}