{
  "type": "Feature",
  "properties": {
    "iso:country":"DE",
    "sg:address":"Leonhardtstr. 4",
    "sg:city":"Hannover",
    "sg:postcode":"30175",
    "sg:province":"Niedersachsen",
    "wof:name":"Hzi Hannover Zement Gmbh",
    "wof:placetype":"venue"
},
  "geometry": {"coordinates":[9.7480669022,52.3776054382],"type":"Point"}
}