{
  "type": "Feature",
  "properties": {
    "iso:country":"DE",
    "sg:address":"Cottbuser Str. 11",
    "sg:city":"Tschernitz",
    "sg:phone":"+49 35600/7045",
    "sg:postcode":"03130",
    "sg:province":"Brandenburg",
    "wof:name":"H. G\u00fcrbig",
    "wof:placetype":"venue"
},
  "geometry": {"coordinates":[14.6149768829,51.5764312744],"type":"Point"}
}