{
  "type": "Feature",
  "properties": {
    "iso:country":"DE",
    "sg:address":"Schillerstr. 44",
    "sg:city":"Ehrenfriedersdorf",
    "sg:postcode":"09427",
    "sg:province":"Sachsen",
    "wof:name":"Sepa Gmbh",
    "wof:placetype":"venue"
},
  "geometry": {"coordinates":[12.96438,50.644379],"type":"Point"}
}