{
  "type": "Feature",
  "properties": {
    "iso:country":"DE",
    "sg:address":"Michaelstr. 79",
    "sg:city":"Neuss",
    "sg:phone":"+49 2131/24275",
    "sg:postcode":"41460",
    "sg:province":"Nordrhein-Westfalen",
    "wof:name":"W. Hartmann",
    "wof:placetype":"venue"
},
  "geometry": {"coordinates":[6.693447,51.196144],"type":"Point"}
}