{
  "type": "Feature",
  "properties": {
    "iso:country":"DE",
    "sg:address":"Von-Behring-Str 3",
    "sg:city":"Stutensee",
    "sg:phone":"+49 7244/607635",
    "sg:postcode":"76297",
    "sg:province":"Baden-W\u00fcrttemberg",
    "wof:name":"Herrmann & Kutscher Gmbh",
    "wof:placetype":"venue"
},
  "geometry": {"coordinates":[8.461075,49.076466],"type":"Point"}
}