{
  "type": "Feature",
  "properties": {
    "iso:country":"DE",
    "sg:address":"Ostenallee 72",
    "sg:city":"Hamm",
    "sg:phone":"+49 2381/29243",
    "sg:postcode":"59063",
    "sg:province":"Nordrhein-Westfalen",
    "wof:name":"Prof. Dr. Hermann Bauer Ingenieur",
    "wof:placetype":"venue"
},
  "geometry": {"coordinates":[7.8386540413,51.686832428],"type":"Point"}
}