{
  "type": "Feature",
  "properties": {
    "iso:country":"DE",
    "sg:address":"Kunigundenberg 6",
    "sg:city":"Panschwitz-Kuckau",
    "sg:phone":"+49 35796/96297",
    "sg:postcode":"01920",
    "sg:province":"Sachsen",
    "wof:name":"Klaus Schuster",
    "wof:placetype":"venue"
},
  "geometry": {"coordinates":[14.201581955,51.2341537476],"type":"Point"}
}