{
  "type": "Feature",
  "properties": {
    "iso:country":"DE",
    "sg:address":"Hindenburgstr. 30",
    "sg:city":"Bondorf",
    "sg:phone":"+49 7457/8942",
    "sg:postcode":"71149",
    "sg:province":"Baden-W\u00fcrttemberg",
    "wof:name":"F. Mast",
    "wof:placetype":"venue"
},
  "geometry": {"coordinates":[8.83143,48.520935],"type":"Point"}
}