{
  "type": "Feature",
  "properties": {
    "iso:country":"DE",
    "sg:address":"Bochumer Str. 325",
    "sg:city":"Dorsten",
    "sg:phone":"+49 2362/41652",
    "sg:postcode":"46282",
    "sg:province":"Nordrhein-Westfalen",
    "wof:name":"Karl-heinz Tripp",
    "wof:placetype":"venue"
},
  "geometry": {"coordinates":[7.0054798126,51.6294517517],"type":"Point"}
}