{
  "type": "Feature",
  "properties": {
    "iso:country":"DE",
    "sg:address":"Schillerstr. 10",
    "sg:city":"Haiterbach",
    "sg:postcode":"72221",
    "sg:province":"Baden-W\u00fcrttemberg",
    "wof:name":"Cylox Systems Gmbh",
    "wof:placetype":"venue"
},
  "geometry": {"coordinates":[8.6424703598,48.5220108032],"type":"Point"}
}