{
  "type": "Feature",
  "properties": {
    "iso:country":"DE",
    "sg:address":"Ruhhecke 30",
    "sg:city":"Speyer",
    "sg:phone":"+49 6232/33283",
    "sg:postcode":"67346",
    "sg:province":"Rheinland-Pfalz",
    "wof:name":"Johann Schmitt Ingenieur",
    "wof:placetype":"venue"
},
  "geometry": {"coordinates":[8.4358167648,49.3507614136],"type":"Point"}
}