{
  "type": "Feature",
  "properties": {
    "iso:country":"DE",
    "sg:address":"Dunlopstr. 40",
    "sg:city":"Bielefeld",
    "sg:phone":"+49 4977/3256956",
    "sg:postcode":"33689",
    "sg:province":"Nordrhein-Westfalen",
    "wof:name":"Neptun Bootspflege-service Gmbh",
    "wof:placetype":"venue"
},
  "geometry": {"coordinates":[8.984819,47.736614],"type":"Point"}
}