{
  "type": "Feature",
  "properties": {
    "iso:country":"DE",
    "sg:address":"Elisabethenstr. 51",
    "sg:city":"Darmstadt",
    "sg:phone":"+49 6151/17540",
    "sg:postcode":"64283",
    "sg:province":"Hessen",
    "wof:name":"Evangelisches Amt F\u00fcr Jugendarbeit",
    "wof:placetype":"venue"
},
  "geometry": {"coordinates":[8.6460008621,49.8696899414],"type":"Point"}
}