{
  "type": "Feature",
  "properties": {
    "iso:country":"DE",
    "sg:address":"Hessenweg 41",
    "sg:city":"Sch\u00fcttorf",
    "sg:phone":"+49 5923/990598",
    "sg:postcode":"48465",
    "sg:province":"Niedersachsen",
    "wof:name":"Fbs Metalltechnik Gmbh",
    "wof:placetype":"venue"
},
  "geometry": {"coordinates":[7.21849,52.321739],"type":"Point"}
}