{
  "type": "Feature",
  "properties": {
    "iso:country":"DE",
    "sg:address":"Pfungst\u00e4dter Str. 35",
    "sg:city":"Griesheim",
    "sg:phone":"+49 6155/5342",
    "sg:postcode":"64347",
    "sg:province":"Hessen",
    "wof:name":"Kurt H\u00f6hl",
    "wof:placetype":"venue"
},
  "geometry": {"coordinates":[8.556983,49.856838],"type":"Point"}
}