{
  "type": "Feature",
  "properties": {
    "iso:country":"DE",
    "sg:address":"Alte Tauchaer Str. 56",
    "sg:city":"Leipzig",
    "sg:postcode":"04288",
    "sg:province":"Sachsen",
    "wof:name":"Dr. Med. Hans-j\u00fcrgen Fritsche",
    "wof:placetype":"venue"
},
  "geometry": {"coordinates":[12.459826,51.289059],"type":"Point"}
}