{
  "type": "Feature",
  "properties": {
    "iso:country":"DE",
    "sg:address":"Kalkhain 23",
    "sg:city":"Wilnsdorf",
    "sg:phone":"+49 2739/89690",
    "sg:postcode":"57234",
    "sg:province":"Nordrhein-Westfalen",
    "wof:name":"G\u00e4stehaus Wilgersdorf Gmbh",
    "wof:placetype":"venue"
},
  "geometry": {"coordinates":[8.1485319138,50.8067207336],"type":"Point"}
}