{
  "type": "Feature",
  "properties": {
    "iso:country":"DE",
    "sg:address":"Lindenstr. 4",
    "sg:city":"Philippsthal",
    "sg:phone":"+49 6620/7465",
    "sg:postcode":"36269",
    "sg:province":"Hessen",
    "wof:name":"C. Sippel Masseur",
    "wof:placetype":"venue"
},
  "geometry": {"coordinates":[9.954364,50.852554],"type":"Point"}
}