{
  "type": "Feature",
  "properties": {
    "iso:country":"DE",
    "sg:address":"Otto-Wiegand-Str. 5",
    "sg:city":"Steinbach",
    "sg:phone":"+49 9263/595",
    "sg:postcode":"96361",
    "sg:province":"Bayern",
    "wof:name":"Roland Richter Steuerberater",
    "wof:placetype":"venue"
},
  "geometry": {"coordinates":[11.3813323975,50.4414176941],"type":"Point"}
}