{
  "type": "Feature",
  "properties": {
    "iso:country":"DE",
    "sg:address":"Fu\u00dfg\u00e4ngerzone",
    "sg:city":"Simbach",
    "sg:phone":"+49 8571/2346",
    "sg:postcode":"84359",
    "sg:province":"Bayern",
    "wof:name":"Schlattl",
    "wof:placetype":"venue"
},
  "geometry": {"coordinates":[13.02768,48.26738],"type":"Point"}
}