{
  "type": "Feature",
  "properties": {
    "iso:country":"DE",
    "sg:address":"Schwetzingerstr. 145",
    "sg:city":"Mannheim",
    "sg:phone":"+49 6201/404094",
    "sg:postcode":"68165",
    "sg:province":"Baden-W\u00fcrttemberg",
    "wof:name":"Us Sports-fanshop",
    "wof:placetype":"venue"
},
  "geometry": {"coordinates":[8.4806432724,49.4760437012],"type":"Point"}
}