{
  "type": "Feature",
  "properties": {
    "iso:country":"DE",
    "sg:address":"Sonnenstr. 30",
    "sg:city":"Heigenbr\u00fccken",
    "sg:postcode":"63869",
    "sg:province":"Bayern",
    "wof:name":"Mitterle Paletten-express",
    "wof:placetype":"venue"
},
  "geometry": {"coordinates":[9.38193,50.025131],"type":"Point"}
}