{
  "type": "Feature",
  "properties": {
    "iso:country":"DE",
    "sg:address":"Heerstr. 182",
    "sg:city":"Boppard",
    "sg:phone":"+49 6742/4289",
    "sg:postcode":"56154",
    "sg:province":"Rheinland-Pfalz",
    "wof:name":"Klaus-peter Forneck",
    "wof:placetype":"venue"
},
  "geometry": {"coordinates":[7.5841040611,50.2322158813],"type":"Point"}
}