{
  "type": "Feature",
  "properties": {
    "iso:country":"DE",
    "sg:address":"Dorfstr. 1",
    "sg:city":"Schmilau",
    "sg:phone":"+49 4541/82271",
    "sg:postcode":"23911",
    "sg:province":"Schleswig-Holstein",
    "wof:name":"Hotel Ulmenhof",
    "wof:placetype":"venue"
},
  "geometry": {"coordinates":[10.7583093643,53.6635475159],"type":"Point"}
}