{
  "type": "Feature",
  "properties": {
    "iso:country":"DE",
    "sg:address":"Bachwiesenstr. 2",
    "sg:city":"M\u00fcnsingen",
    "sg:phone":"+49 7381/929733",
    "sg:postcode":"72525",
    "sg:province":"Baden-W\u00fcrttemberg",
    "wof:name":"Eiscafe Pinocchio",
    "wof:placetype":"venue"
},
  "geometry": {"coordinates":[9.493105,48.412682],"type":"Point"}
}