{
  "type": "Feature",
  "properties": {
    "iso:country":"DE",
    "sg:address":"M\u00fchlenstr. 33",
    "sg:city":"Pulheim",
    "sg:phone":"+49 2234/81879",
    "sg:postcode":"50259",
    "sg:province":"Nordrhein-Westfalen",
    "wof:name":"Hans Horst Ley Rechtsanwalt",
    "wof:placetype":"venue"
},
  "geometry": {"coordinates":[6.7817668915,50.9548301697],"type":"Point"}
}