{
  "type": "Feature",
  "properties": {
    "iso:country":"DE",
    "sg:address":"Bismarckstr. 8",
    "sg:city":"Friedrichshafen",
    "sg:phone":"+49 7541/23570",
    "sg:postcode":"88045",
    "sg:province":"Baden-W\u00fcrttemberg",
    "wof:name":"H. Maier Immobilienmakler Rdm",
    "wof:placetype":"venue"
},
  "geometry": {"coordinates":[9.4778642654,47.653553009],"type":"Point"}
}