{
  "type": "Feature",
  "properties": {
    "iso:country":"DE",
    "sg:address":"Auf dem Stift 16",
    "sg:city":"Havixbeck",
    "sg:phone":"+49 2507/572241",
    "sg:postcode":"48329",
    "sg:province":"Nordrhein-Westfalen",
    "wof:name":"Klaus Karwatzki Seminare",
    "wof:placetype":"venue"
},
  "geometry": {"coordinates":[7.461409,51.99641],"type":"Point"}
}