{
  "type": "Feature",
  "properties": {
    "iso:country":"DE",
    "sg:address":"Lietzenburger Str. 91",
    "sg:city":"Berlin",
    "sg:phone":"+49 30/88430410",
    "sg:postcode":"10719",
    "sg:province":"Berlin",
    "wof:name":"Consens And Friends Baukoordinierung Und",
    "wof:placetype":"venue"
},
  "geometry": {"coordinates":[13.3218126297,52.4997024536],"type":"Point"}
}