{
  "type": "Feature",
  "properties": {
    "iso:country":"DE",
    "sg:address":"Rathausstr. 52",
    "sg:city":"Alsdorf",
    "sg:phone":"+49 2404/23102",
    "sg:postcode":"52477",
    "sg:province":"Nordrhein-Westfalen",
    "wof:name":"Gabriela Ablasser",
    "wof:placetype":"venue"
},
  "geometry": {"coordinates":[6.1638898849,50.8761482239],"type":"Point"}
}