{
  "type": "Feature",
  "properties": {
    "iso:country":"DE",
    "sg:address":"Hein-Hoyer-Str. 3",
    "sg:city":"Hamburg",
    "sg:postcode":"20359",
    "sg:province":"Hamburg",
    "wof:name":"San De Trade Gmbh",
    "wof:placetype":"venue"
},
  "geometry": {"coordinates":[9.9620800018,53.5498886108],"type":"Point"}
}