{
  "type": "Feature",
  "properties": {
    "iso:country":"DE",
    "sg:address":"Hannoversche Str. 24",
    "sg:city":"Einbeck",
    "sg:postcode":"37574",
    "sg:province":"Niedersachsen",
    "wof:name":"Autohaus Siebrecht Gmbh",
    "wof:placetype":"venue"
},
  "geometry": {"coordinates":[9.8515024185,51.8206748962],"type":"Point"}
}