{
  "type": "Feature",
  "properties": {
    "iso:country":"DE",
    "sg:address":"Waldheimer Str. 2",
    "sg:city":"Tiefenbach",
    "sg:postcode":"09661",
    "sg:province":"Sachsen",
    "wof:name":"Gemeindeschwesterstation",
    "wof:placetype":"venue"
},
  "geometry": {"coordinates":[13.184921,51.051018],"type":"Point"}
}