{
  "type": "Feature",
  "properties": {
    "iso:country":"DE",
    "sg:address":"Schmachtendorfer Str. 78",
    "sg:city":"Oberhausen",
    "sg:phone":"+49 208/682079",
    "sg:postcode":"46147",
    "sg:province":"Nordrhein-Westfalen",
    "wof:name":"Heinrich Stratmann",
    "wof:placetype":"venue"
},
  "geometry": {"coordinates":[6.8168859482,51.5388832092],"type":"Point"}
}