{
  "type": "Feature",
  "properties": {
    "iso:country":"DE",
    "sg:address":"Viktoriastr. 6",
    "sg:city":"Castrop-Rauxel",
    "sg:phone":"+49 2305/29045",
    "sg:postcode":"44575",
    "sg:province":"Nordrhein-Westfalen",
    "wof:name":"Jarzina Und Winkelmann Architekten",
    "wof:placetype":"venue"
},
  "geometry": {"coordinates":[7.313429,51.547413],"type":"Point"}
}