{
  "type": "Feature",
  "properties": {
    "iso:country":"DE",
    "sg:address":"Zum Marktplatz 11",
    "sg:city":"Marienheide",
    "sg:phone":"+49 2264/28444",
    "sg:postcode":"51709",
    "sg:province":"Nordrhein-Westfalen",
    "wof:name":"Willkommen In Der Braut-galerie Ody !",
    "wof:placetype":"venue"
},
  "geometry": {"coordinates":[7.529733,51.083366],"type":"Point"}
}