{
  "type": "Feature",
  "properties": {
    "iso:country":"DE",
    "sg:address":"Develangring 2",
    "sg:city":"Dannenberg",
    "sg:phone":"+49 5861/2491",
    "sg:postcode":"29451",
    "sg:province":"Niedersachsen",
    "wof:name":"Horst Wenau",
    "wof:placetype":"venue"
},
  "geometry": {"coordinates":[11.0888566971,53.0906715393],"type":"Point"}
}