{
  "type": "Feature",
  "properties": {
    "iso:country":"DE",
    "sg:address":"Zum Mindelsee 1",
    "sg:city":"Allensbach",
    "sg:phone":"+49 7533/7503",
    "sg:postcode":"78476",
    "sg:province":"Baden-W\u00fcrttemberg",
    "wof:name":"Studienzentrum Schlo\u00df Langenrain Gmbh",
    "wof:placetype":"venue"
},
  "geometry": {"coordinates":[9.0751667023,47.7627410889],"type":"Point"}
}