{
  "type": "Feature",
  "properties": {
    "iso:country":"DE",
    "sg:address":"M\u00fcndener Str. 8",
    "sg:city":"Staufenberg",
    "sg:phone":"+49 5543/47268",
    "sg:postcode":"34355",
    "sg:province":"Niedersachsen",
    "wof:name":"J. M\u00f6ller",
    "wof:placetype":"venue"
},
  "geometry": {"coordinates":[9.6183624268,51.331199646],"type":"Point"}
}