{
  "type": "Feature",
  "properties": {
    "iso:country":"DE",
    "sg:address":"Friedenstr. 1",
    "sg:city":"Wiernsheim",
    "sg:phone":"+49 7044/6177",
    "sg:postcode":"75446",
    "sg:province":"Baden-W\u00fcrttemberg",
    "wof:name":"R. Heilmann",
    "wof:placetype":"venue"
},
  "geometry": {"coordinates":[8.872418,48.893932],"type":"Point"}
}