{
  "type": "Feature",
  "properties": {
    "iso:country":"DE",
    "sg:address":"Alter Schulweg 4",
    "sg:city":"Rhade",
    "sg:phone":"+49 4285/278",
    "sg:postcode":"27404",
    "sg:province":"Niedersachsen",
    "wof:name":"Helmut Harms",
    "wof:placetype":"venue"
},
  "geometry": {"coordinates":[9.1132526398,53.3272476196],"type":"Point"}
}