{
  "type": "Feature",
  "properties": {
    "iso:country":"DE",
    "sg:address":"Bismarckstr. 3",
    "sg:city":"Braunlage",
    "sg:phone":"+49 5520/586",
    "sg:postcode":"38700",
    "sg:province":"Niedersachsen",
    "wof:name":"Hotel Waldfrieden",
    "wof:placetype":"venue"
},
  "geometry": {"coordinates":[10.6098184586,51.7291793823],"type":"Point"}
}