{
  "type": "Feature",
  "properties": {
    "iso:country":"DE",
    "sg:address":"Schlo\u00dfhalde 18",
    "sg:city":"Erbach",
    "sg:phone":"+49 7305/7470",
    "sg:postcode":"89155",
    "sg:province":"Baden-W\u00fcrttemberg",
    "wof:name":"R. Und G. Westernberger",
    "wof:placetype":"venue"
},
  "geometry": {"coordinates":[9.888914,48.322968],"type":"Point"}
}