{
  "type": "Feature",
  "properties": {
    "iso:country":"DE",
    "sg:address":"Bahnhofstr. 15",
    "sg:city":"Lachendorf",
    "sg:phone":"+49 5145/8330",
    "sg:postcode":"29331",
    "sg:province":"Niedersachsen",
    "wof:name":"Renate Drangmeister",
    "wof:placetype":"venue"
},
  "geometry": {"coordinates":[10.24491,52.622631],"type":"Point"}
}