{
  "type": "Feature",
  "properties": {
    "iso:country":"DE",
    "sg:address":"Rothigweg 55b",
    "sg:city":"P\u00f6\u00dfneck",
    "sg:phone":"+49 3647/414020",
    "sg:postcode":"07381",
    "sg:province":"Th\u00fcringen",
    "wof:name":"Burkhardt Franz",
    "wof:placetype":"venue"
},
  "geometry": {"coordinates":[11.589454,50.708637],"type":"Point"}
}