{
  "type": "Feature",
  "properties": {
    "iso:country":"DE",
    "sg:address":"August-Thyssen-Str. 129",
    "sg:city":"M\u00fclheim Ruhr",
    "sg:phone":"+49 2054/95950",
    "sg:postcode":"45481",
    "sg:province":"Nordrhein-Westfalen",
    "wof:name":"Hotel Mintarder Wasserbahnhof",
    "wof:placetype":"venue"
},
  "geometry": {"coordinates":[6.904327,51.376152],"type":"Point"}
}