{
  "type": "Feature",
  "properties": {
    "iso:country":"DE",
    "sg:address":"Bahnhofstr. 57",
    "sg:city":"Voerde",
    "sg:phone":"+49 2855/81572",
    "sg:postcode":"46562",
    "sg:province":"Nordrhein-Westfalen",
    "wof:name":"Rolf Jakobs",
    "wof:placetype":"venue"
},
  "geometry": {"coordinates":[6.68052,51.596458],"type":"Point"}
}