{
  "type": "Feature",
  "properties": {
    "iso:country":"DE",
    "sg:address":"Stresemannstr. 2",
    "sg:city":"D\u00fcsseldorf",
    "sg:postcode":"40210",
    "sg:province":"Nordrhein-Westfalen",
    "wof:name":"Sor Ma\u00dfschneiderei Nic. Reuter D\u00fcsseldorf Zweigniederlassung",
    "wof:placetype":"venue"
},
  "geometry": {"coordinates":[6.7828598022,51.2217597961],"type":"Point"}
}