{
  "type": "Feature",
  "properties": {
    "iso:country":"DE",
    "sg:address":"Bahnhofstr. 30",
    "sg:city":"Sonthofen",
    "sg:phone":"+49 8321/88020",
    "sg:postcode":"87527",
    "sg:province":"Bayern",
    "wof:name":"Pizzeria Capri",
    "wof:placetype":"venue"
},
  "geometry": {"coordinates":[10.2734527588,47.5134735107],"type":"Point"}
}