{
  "type": "Feature",
  "properties": {
    "iso:country":"DE",
    "sg:address":"Schreberstrasse 6a",
    "sg:city":"Ludwigshafen",
    "sg:phone":"+49 621/557902",
    "sg:postcode":"67065",
    "sg:province":"Rheinland-Pfalz",
    "wof:name":"Grafik-design-weber",
    "wof:placetype":"venue"
},
  "geometry": {"coordinates":[8.409508,49.472103],"type":"Point"}
}