{
  "type": "Feature",
  "properties": {
    "iso:country":"DE",
    "sg:address":"Am Graben 30",
    "sg:city":"Fl\u00f6rsheim",
    "sg:phone":"+49 6145/2366",
    "sg:postcode":"65439",
    "sg:province":"Hessen",
    "wof:name":"Gustav Niedermeier Architekt",
    "wof:placetype":"venue"
},
  "geometry": {"coordinates":[8.402129,50.02898],"type":"Point"}
}