{
  "type": "Feature",
  "properties": {
    "iso:country":"DE",
    "sg:address":"Zum Furtfeld 5",
    "sg:city":"March",
    "sg:phone":"+49 7665/40406",
    "sg:postcode":"79232",
    "sg:province":"Baden-W\u00fcrttemberg",
    "wof:name":"Media Norm Gesellschaft F\u00fcr Elektron. Datentechn. Me\u00dftech-",
    "wof:placetype":"venue"
},
  "geometry": {"coordinates":[7.77858,48.056374],"type":"Point"}
}