{
  "type": "Feature",
  "properties": {
    "iso:country":"DE",
    "sg:address":"Ernst-Th\u00e4lmann-Str. 8a",
    "sg:city":"L\u00f6cknitz",
    "sg:phone":"+49 39754/20322",
    "sg:postcode":"17321",
    "sg:province":"Mecklenburg-Vorpommern",
    "wof:name":"Dr. Alice Fr\u00f6hlich Zahn\u00e4rztin",
    "wof:placetype":"venue"
},
  "geometry": {"coordinates":[14.215261,53.453636],"type":"Point"}
}