{
  "type": "Feature",
  "properties": {
    "iso:country":"DE",
    "sg:address":"Hauptstr. 7",
    "sg:city":"Wei\u00dfenhorn",
    "sg:phone":"+49 4973/092082",
    "sg:postcode":"89264",
    "sg:province":"Bayern",
    "wof:name":"Sparkasse",
    "wof:placetype":"venue"
},
  "geometry": {"coordinates":[10.158346,48.30489],"type":"Point"}
}