{
  "type": "Feature",
  "properties": {
    "iso:country":"DE",
    "sg:address":"Marktplatz 13",
    "sg:city":"Eppelborn",
    "sg:phone":"+49 6827/3416",
    "sg:postcode":"66571",
    "sg:province":"Saarland",
    "wof:name":"Werner Bost M\u00fchlenb\u00e4ckerei Gmbh",
    "wof:placetype":"venue"
},
  "geometry": {"coordinates":[6.96799,49.407722],"type":"Point"}
}