{
  "type": "Feature",
  "properties": {
    "iso:country":"DE",
    "sg:address":"Westheimer Str. 5",
    "sg:city":"Neus\u00e4\u00df",
    "sg:phone":"+49 821/481793",
    "sg:postcode":"86356",
    "sg:province":"Bayern",
    "wof:name":"Leis-massivbau Schl\u00fcsselfertiges Bauen",
    "wof:placetype":"venue"
},
  "geometry": {"coordinates":[10.8215665817,48.3868408203],"type":"Point"}
}