{
  "type": "Feature",
  "properties": {
    "iso:country":"DE",
    "sg:address":"Lauffener Str. 23",
    "sg:city":"Kirchheim",
    "sg:phone":"+49 7143/91842",
    "sg:postcode":"74366",
    "sg:province":"Baden-W\u00fcrttemberg",
    "wof:name":"Erich Schneider",
    "wof:placetype":"venue"
},
  "geometry": {"coordinates":[9.144027,49.04546],"type":"Point"}
}