{
  "type": "Feature",
  "properties": {
    "iso:country":"DE",
    "sg:address":"H\u00f6felinger Weg 11",
    "sg:city":"Uchte",
    "sg:phone":"+49 5763/2319",
    "sg:postcode":"31600",
    "sg:province":"Niedersachsen",
    "wof:name":"Dieter Klante",
    "wof:placetype":"venue"
},
  "geometry": {"coordinates":[8.900559,52.494781],"type":"Point"}
}