{
  "type": "Feature",
  "properties": {
    "iso:country":"DE",
    "sg:address":"Diebacher Weg 24",
    "sg:city":"Waldsolms",
    "sg:phone":"+49 6085/970166",
    "sg:postcode":"35647",
    "sg:province":"Hessen",
    "wof:name":"Graf Sport Marketing Gmbh",
    "wof:placetype":"venue"
},
  "geometry": {"coordinates":[8.4901065826,50.4369468689],"type":"Point"}
}