{
  "type": "Feature",
  "properties": {
    "iso:country":"DE",
    "sg:address":"Langstr. 3",
    "sg:city":"Landau",
    "sg:phone":"+49 6341/89564",
    "sg:postcode":"76829",
    "sg:province":"Rheinland-Pfalz",
    "wof:name":"Gregor Arnold Immobilienmakler",
    "wof:placetype":"venue"
},
  "geometry": {"coordinates":[8.1083936691,49.1985397339],"type":"Point"}
}