{
  "type": "Feature",
  "properties": {
    "iso:country":"DE",
    "sg:address":"Schlagbaum 2",
    "sg:city":"Wermelskirchen",
    "sg:phone":"+49 2193/2975",
    "sg:postcode":"42929",
    "sg:province":"Nordrhein-Westfalen",
    "wof:name":"Helm Grossgloss",
    "wof:placetype":"venue"
},
  "geometry": {"coordinates":[7.211438,51.085674],"type":"Point"}
}