{
  "type": "Feature",
  "properties": {
    "iso:country":"DE",
    "sg:address":"Saudengasse 14",
    "sg:city":"Biberach",
    "sg:phone":"+49 7351/9791",
    "sg:postcode":"88400",
    "sg:province":"Baden-W\u00fcrttemberg",
    "wof:name":"Artur Sontheimer Masseur",
    "wof:placetype":"venue"
},
  "geometry": {"coordinates":[9.790913,48.09584],"type":"Point"}
}