{
  "type": "Feature",
  "properties": {
    "iso:country":"DE",
    "sg:address":"Marienstr. 29",
    "sg:city":"Ellwangen",
    "sg:phone":"+49 7961/53786",
    "sg:postcode":"73479",
    "sg:province":"Baden-W\u00fcrttemberg",
    "wof:name":"Christoph Langkau Krankengymnast",
    "wof:placetype":"venue"
},
  "geometry": {"coordinates":[10.1300878525,48.9595527649],"type":"Point"}
}