{
  "type": "Feature",
  "properties": {
    "iso:country":"DE",
    "sg:address":"Wissinghauser Str. 22",
    "sg:city":"Medebach",
    "sg:phone":"+49 5632/7361",
    "sg:postcode":"59964",
    "sg:province":"Nordrhein-Westfalen",
    "wof:name":"Hubertus Lange",
    "wof:placetype":"venue"
},
  "geometry": {"coordinates":[8.704677,51.198196],"type":"Point"}
}