{
  "type": "Feature",
  "properties": {
    "iso:country":"DE",
    "sg:address":"Isarstr. 2",
    "sg:city":"Berlin",
    "sg:postcode":"12053",
    "sg:province":"Berlin",
    "wof:name":"Valuna Beteiligungs- Gesellschaft Mbh",
    "wof:placetype":"venue"
},
  "geometry": {"coordinates":[13.43161,52.481213],"type":"Point"}
}