{
  "type": "Feature",
  "properties": {
    "iso:country":"DE",
    "sg:address":"Homburger Landstr. 746",
    "sg:city":"Frankfurt",
    "sg:phone":"+49 69/5075763",
    "sg:postcode":"60437",
    "sg:province":"Hessen",
    "wof:name":"F. Weih Holzbildhauer",
    "wof:placetype":"venue"
},
  "geometry": {"coordinates":[8.666818,50.190701],"type":"Point"}
}