{
  "type": "Feature",
  "properties": {
    "iso:country":"DE",
    "sg:address":"Lortzingstr. 7",
    "sg:city":"L\u00fcnen",
    "sg:phone":"+49 2306/44111",
    "sg:postcode":"44534",
    "sg:province":"Nordrhein-Westfalen",
    "wof:name":"Giesbert Laakmann",
    "wof:placetype":"venue"
},
  "geometry": {"coordinates":[7.5119137764,51.6315536499],"type":"Point"}
}