{
  "type": "Feature",
  "properties": {
    "iso:country":"DE",
    "sg:address":"Hengsbecke 19-29",
    "sg:city":"Medebach",
    "sg:phone":"+49 2982/4070",
    "sg:postcode":"59964",
    "sg:province":"Nordrhein-Westfalen",
    "wof:name":"Paul Schmidt",
    "wof:placetype":"venue"
},
  "geometry": {"coordinates":[8.7009887695,51.2046661377],"type":"Point"}
}