{
  "type": "Feature",
  "properties": {
    "iso:country":"DE",
    "sg:address":"Mathias-Marx-Str. 7",
    "sg:city":"Kevelaer",
    "sg:phone":"+49 2832/5726",
    "sg:postcode":"47623",
    "sg:province":"Nordrhein-Westfalen",
    "wof:name":"Annemarie Gerke Steuerberaterin",
    "wof:placetype":"venue"
},
  "geometry": {"coordinates":[6.2340707779,51.5905532837],"type":"Point"}
}