{
  "type": "Feature",
  "properties": {
    "iso:country":"DE",
    "sg:address":"Holbeinstr. 6",
    "sg:city":"K\u00f6ln",
    "sg:phone":"+49 221/97312810",
    "sg:postcode":"50733",
    "sg:province":"Nordrhein-Westfalen",
    "wof:name":"Petra Ladenburger Rechtsanw\u00e4ltin",
    "wof:placetype":"venue"
},
  "geometry": {"coordinates":[6.9538350105,50.9595794678],"type":"Point"}
}