{
  "type": "Feature",
  "properties": {
    "iso:country":"DE",
    "sg:address":"L\u00fctersheimer Str. 19",
    "sg:city":"Volkmarsen",
    "sg:phone":"+49 5693/822",
    "sg:postcode":"34471",
    "sg:province":"Hessen",
    "wof:name":"Stadtwerke Volkmarsen",
    "wof:placetype":"venue"
},
  "geometry": {"coordinates":[9.118944,51.404541],"type":"Point"}
}