{
  "type": "Feature",
  "properties": {
    "iso:country":"DE",
    "sg:address":"Forsthausstr. 3",
    "sg:city":"Haar",
    "sg:postcode":"85540",
    "sg:province":"Bayern",
    "wof:name":"Msi Fertighausbau Gmbh",
    "wof:placetype":"venue"
},
  "geometry": {"coordinates":[11.735291,48.103912],"type":"Point"}
}