{
  "type": "Feature",
  "properties": {
    "iso:country":"DE",
    "sg:address":"Ellerkirchstr. 27",
    "sg:city":"D\u00fcsseldorf",
    "sg:phone":"+49 4921/1218039",
    "sg:postcode":"40229",
    "sg:province":"Nordrhein-Westfalen",
    "wof:name":"Siegfried Br\u00dcckner",
    "wof:placetype":"venue"
},
  "geometry": {"coordinates":[6.8445692062,51.2016906738],"type":"Point"}
}