{
  "type": "Feature",
  "properties": {
    "iso:country":"DE",
    "sg:address":"Hohenkamp 18",
    "sg:city":"Geesthacht",
    "sg:phone":"+49 4152/842226",
    "sg:postcode":"21502",
    "sg:province":"Schleswig-Holstein",
    "wof:name":"Monika Klatt Rechtsanw\u00e4ltin",
    "wof:placetype":"venue"
},
  "geometry": {"coordinates":[10.3764810562,53.4475212097],"type":"Point"}
}