{
  "type": "Feature",
  "properties": {
    "iso:country":"DE",
    "sg:address":"Immenklint",
    "sg:city":"Boostedt",
    "sg:phone":"+49 4393/3386",
    "sg:postcode":"24598",
    "sg:province":"Schleswig-Holstein",
    "wof:name":"Horn Ingenieur",
    "wof:placetype":"venue"
},
  "geometry": {"coordinates":[10.0312147141,53.9989318848],"type":"Point"}
}