{
  "type": "Feature",
  "properties": {
    "iso:country":"DE",
    "sg:address":"Steinmerschweg 1",
    "sg:city":"G\u00fctersloh",
    "sg:phone":"+49 5241/948080",
    "sg:postcode":"33332",
    "sg:province":"Nordrhein-Westfalen",
    "wof:name":"Franz M\u00fcterthies Inh. Irmgard Schulte-lindhorst",
    "wof:placetype":"venue"
},
  "geometry": {"coordinates":[8.39467,51.879009],"type":"Point"}
}