{
  "type": "Feature",
  "properties": {
    "iso:country":"DE",
    "sg:address":"Burgwedeler Str. 33",
    "sg:city":"Isernhagen",
    "sg:phone":"+49 511/973900",
    "sg:postcode":"30916",
    "sg:province":"Niedersachsen",
    "wof:name":"Gasthaus Sievers",
    "wof:placetype":"venue"
},
  "geometry": {"coordinates":[9.7888946533,52.460849762],"type":"Point"}
}