{
  "type": "Feature",
  "properties": {
    "iso:country":"DE",
    "sg:address":"Neesbacher Str. 17",
    "sg:city":"H\u00fcnfelden",
    "sg:phone":"+49 6438/4490",
    "sg:postcode":"65597",
    "sg:province":"Hessen",
    "wof:name":"Alex Pfeiffer Gmbh",
    "wof:placetype":"venue"
},
  "geometry": {"coordinates":[8.17390728,50.3305892944],"type":"Point"}
}