{
  "type": "Feature",
  "properties": {
    "iso:country":"DE",
    "sg:address":"P\u00f6ltnerstr. 6",
    "sg:city":"Weilheim",
    "sg:phone":"+49 881/6694",
    "sg:postcode":"82362",
    "sg:province":"Bayern",
    "wof:name":"Furore Jeans",
    "wof:placetype":"venue"
},
  "geometry": {"coordinates":[11.141617775,47.838508606],"type":"Point"}
}