{
  "type": "Feature",
  "properties": {
    "iso:country":"DE",
    "sg:address":"Tunnelstr. 38",
    "sg:city":"Berlin",
    "sg:phone":"+49 30/2965946",
    "sg:postcode":"10245",
    "sg:province":"Berlin",
    "wof:name":"Trepte Gmbh",
    "wof:placetype":"venue"
},
  "geometry": {"coordinates":[13.480474472,52.4909095764],"type":"Point"}
}