{
  "type": "Feature",
  "properties": {
    "iso:country":"DE",
    "sg:address":"Hollergasse 20",
    "sg:city":"Trebur",
    "sg:phone":"+49 6147/8323",
    "sg:postcode":"65468",
    "sg:province":"Hessen",
    "wof:name":"Gisela Hanke",
    "wof:placetype":"venue"
},
  "geometry": {"coordinates":[8.4042901993,49.9228515625],"type":"Point"}
}