{
  "type": "Feature",
  "properties": {
    "iso:country":"DE",
    "sg:address":"Martinstr. 17",
    "sg:city":"Halle",
    "sg:phone":"+49 345/501029",
    "sg:postcode":"06108",
    "sg:province":"Sachsen-Anhalt",
    "wof:name":"Asia Restaurant",
    "wof:placetype":"venue"
},
  "geometry": {"coordinates":[11.9799871445,51.4793548584],"type":"Point"}
}