{
  "type": "Feature",
  "properties": {
    "iso:country":"DE",
    "sg:address":"R\u00f6merstr. 10",
    "sg:city":"M\u00fcnster-Sarmsheim",
    "sg:phone":"+49 6721/41081",
    "sg:postcode":"55424",
    "sg:province":"Rheinland-Pfalz",
    "wof:name":"Albert Schmitt",
    "wof:placetype":"venue"
},
  "geometry": {"coordinates":[7.8976588249,49.9467468262],"type":"Point"}
}