{
  "type": "Feature",
  "properties": {
    "iso:country":"DE",
    "sg:address":"Hilgersh\u00e4user Str. 1 a",
    "sg:city":"Felsberg",
    "sg:phone":"+49 5662/5176",
    "sg:postcode":"34587",
    "sg:province":"Hessen",
    "wof:name":"Karl Ackermann",
    "wof:placetype":"venue"
},
  "geometry": {"coordinates":[9.4695234299,51.1150856018],"type":"Point"}
}