{
  "type": "Feature",
  "properties": {
    "iso:country":"DE",
    "sg:address":"Lindenhofstr. 47",
    "sg:city":"Saarbr\u00fccken",
    "sg:phone":"+49 681/78441",
    "sg:postcode":"66115",
    "sg:province":"Saarland",
    "wof:name":"Dieter M\u00fcller",
    "wof:placetype":"venue"
},
  "geometry": {"coordinates":[6.9409389496,49.2509002686],"type":"Point"}
}