{
  "type": "Feature",
  "properties": {
    "iso:country":"DE",
    "sg:address":"Poststr. 18",
    "sg:city":"Lehrte",
    "sg:postcode":"31275",
    "sg:province":"Niedersachsen",
    "wof:name":"Wilhelm B\u00e4lz & Sohn Gmbh & Co. Kg",
    "wof:placetype":"venue"
},
  "geometry": {"coordinates":[9.9730453491,52.3793945312],"type":"Point"}
}