{
  "type": "Feature",
  "properties": {
    "iso:country":"DE",
    "sg:address":"Buchenstr. 5",
    "sg:city":"Aachen",
    "sg:phone":"+49 2408/5115",
    "sg:postcode":"52076",
    "sg:province":"Nordrhein-Westfalen",
    "wof:name":"Peter Nysten Ingenieur",
    "wof:placetype":"venue"
},
  "geometry": {"coordinates":[6.1711540222,50.7017440796],"type":"Point"}
}