{
  "type": "Feature",
  "properties": {
    "iso:country":"DE",
    "sg:address":"Rathausstr. 43",
    "sg:city":"Alsdorf",
    "sg:phone":"+49 2404/21215",
    "sg:postcode":"52477",
    "sg:province":"Nordrhein-Westfalen",
    "wof:name":"Peter H\u00f6ppener",
    "wof:placetype":"venue"
},
  "geometry": {"coordinates":[6.162702,50.87529],"type":"Point"}
}