{
  "type": "Feature",
  "properties": {
    "iso:country":"DE",
    "sg:address":"Fruchtmarktstr. 26",
    "sg:city":"Zweibr\u00fccken",
    "sg:phone":"+49 6332/73263",
    "sg:postcode":"66482",
    "sg:province":"Rheinland-Pfalz",
    "wof:name":"Spielothek-automaten- Freizeit-center",
    "wof:placetype":"venue"
},
  "geometry": {"coordinates":[7.3641519547,49.245967865],"type":"Point"}
}