{
  "type": "Feature",
  "properties": {
    "iso:country":"DE",
    "sg:address":"Hauptstr. 80",
    "sg:city":"Br\u00f6ckel",
    "sg:phone":"+49 5144/92746",
    "sg:postcode":"29356",
    "sg:province":"Niedersachsen",
    "wof:name":"Reise - Treff Eva Berkhan",
    "wof:placetype":"venue"
},
  "geometry": {"coordinates":[10.2157068253,52.5244255066],"type":"Point"}
}