{
  "type": "Feature",
  "properties": {
    "iso:country":"DE",
    "sg:address":"Delsterner Str. 147",
    "sg:city":"Hagen",
    "sg:phone":"+49 2331/973284",
    "sg:postcode":"58091",
    "sg:province":"Nordrhein-Westfalen",
    "wof:name":"Schneider Grosshandel Gmbh",
    "wof:placetype":"venue"
},
  "geometry": {"coordinates":[7.5209331512,51.3317146301],"type":"Point"}
}