{
  "type": "Feature",
  "properties": {
    "iso:country":"DE",
    "sg:address":"An Haus Behr 2",
    "sg:city":"Titz",
    "sg:phone":"+49 2463/905227",
    "sg:postcode":"52445",
    "sg:province":"Nordrhein-Westfalen",
    "wof:name":"H. Schmidt & S. Windolph",
    "wof:placetype":"venue"
},
  "geometry": {"coordinates":[6.3635950089,50.9825439453],"type":"Point"}
}