{
  "type": "Feature",
  "properties": {
    "iso:country":"DE",
    "sg:address":"Immengarten 54",
    "sg:city":"Hildesheim",
    "sg:phone":"+49 5121/37212",
    "sg:postcode":"31134",
    "sg:province":"Niedersachsen",
    "wof:name":"Hans Bloch Farben Und Tapeten",
    "wof:placetype":"venue"
},
  "geometry": {"coordinates":[9.9619140625,52.148651123],"type":"Point"}
}