{
  "type": "Feature",
  "properties": {
    "iso:country":"DE",
    "sg:address":"Reinekestr. 3",
    "sg:city":"Hemmingen",
    "sg:phone":"+49 511/2344733",
    "sg:postcode":"30966",
    "sg:province":"Niedersachsen",
    "wof:name":"Stella Automaten- Betriebe- Gmbh",
    "wof:placetype":"venue"
},
  "geometry": {"coordinates":[9.7216472626,52.3259277344],"type":"Point"}
}