{
  "type": "Feature",
  "properties": {
    "iso:country":"DE",
    "sg:address":"Weststr. 12",
    "sg:city":"Brackenheim",
    "sg:phone":"+49 7135/15004",
    "sg:postcode":"74336",
    "sg:province":"Baden-W\u00fcrttemberg",
    "wof:name":"Ivcic Gmbh",
    "wof:placetype":"venue"
},
  "geometry": {"coordinates":[9.076887,49.08757],"type":"Point"}
}