{
  "type": "Feature",
  "properties": {
    "iso:country":"DE",
    "sg:address":"Am M\u00fchlberg 22a",
    "sg:city":"Ober-Ramstadt",
    "sg:postcode":"64372",
    "sg:province":"Hessen",
    "wof:name":"Dawel German Trading Ag",
    "wof:placetype":"venue"
},
  "geometry": {"coordinates":[8.7366542816,49.8019676208],"type":"Point"}
}