{
  "type": "Feature",
  "properties": {
    "iso:country":"DE",
    "sg:address":"H\u00f6henweg 8",
    "sg:city":"Bad M\u00fcnstereifel",
    "sg:phone":"+49 2257/605",
    "sg:postcode":"53902",
    "sg:province":"Nordrhein-Westfalen",
    "wof:name":"Pension B\u00e4renbrinker",
    "wof:placetype":"venue"
},
  "geometry": {"coordinates":[6.8547639847,50.5036392212],"type":"Point"}
}