{
  "type": "Feature",
  "properties": {
    "iso:country":"DE",
    "sg:address":"Alte Dorfstr. 18",
    "sg:city":"Barntrup",
    "sg:phone":"+49 5263/2457",
    "sg:postcode":"32683",
    "sg:province":"Nordrhein-Westfalen",
    "wof:name":"Brunhild L\u00e4ger",
    "wof:placetype":"venue"
},
  "geometry": {"coordinates":[9.1690196991,52.0088195801],"type":"Point"}
}