{
  "type": "Feature",
  "properties": {
    "iso:country":"DE",
    "sg:address":"Wylichstr. 9",
    "sg:city":"Ostseebad Binz",
    "sg:postcode":"18609",
    "sg:province":"Mecklenburg-Vorpommern",
    "wof:name":"K & B Bautr\u00e4gerges. Mbh",
    "wof:placetype":"venue"
},
  "geometry": {"coordinates":[13.608567,54.402363],"type":"Point"}
}