{
  "type": "Feature",
  "properties": {
    "iso:country":"DE",
    "sg:address":"Kruppstr. 6",
    "sg:city":"Nordhorn",
    "sg:phone":"+49 5921/35155",
    "sg:postcode":"48531",
    "sg:province":"Niedersachsen",
    "wof:name":"Anton Scholle",
    "wof:placetype":"venue"
},
  "geometry": {"coordinates":[7.1575899124,52.4616470337],"type":"Point"}
}