{
  "type": "Feature",
  "properties": {
    "iso:country":"DE",
    "sg:address":"Hechelfurt 1",
    "sg:city":"Meckenbeuren",
    "sg:phone":"+49 7541/53278",
    "sg:postcode":"88074",
    "sg:province":"Baden-W\u00fcrttemberg",
    "wof:name":"Franz Mayer",
    "wof:placetype":"venue"
},
  "geometry": {"coordinates":[9.5326309204,47.6634597778],"type":"Point"}
}