{
  "type": "Feature",
  "properties": {
    "iso:country":"DE",
    "sg:address":"Rembrandtstr. 14",
    "sg:city":"Potsdam",
    "sg:postcode":"14467",
    "sg:province":"Brandenburg",
    "wof:name":"Versicherungsagentur Fuchs E. K.",
    "wof:placetype":"venue"
},
  "geometry": {"coordinates":[13.0816574097,52.4144515991],"type":"Point"}
}