{
  "type": "Feature",
  "properties": {
    "iso:country":"DE",
    "sg:address":"Alte Handelsstr. 1",
    "sg:city":"Judenbach",
    "sg:phone":"+49 3675/742146",
    "sg:postcode":"96515",
    "sg:province":"Th\u00fcringen",
    "wof:name":"Steiner Heizungs- Und Sanit\u00e4rtechnik Gmbh",
    "wof:placetype":"venue"
},
  "geometry": {"coordinates":[11.215456,50.385822],"type":"Point"}
}