{
  "type": "Feature",
  "properties": {
    "iso:country":"DE",
    "sg:address":"Leipziger Str. 13 e",
    "sg:city":"Colditz",
    "sg:postcode":"04680",
    "sg:province":"Sachsen",
    "wof:name":"Eckel & Schmidt Gmbh",
    "wof:placetype":"venue"
},
  "geometry": {"coordinates":[12.8180198669,51.1270103455],"type":"Point"}
}