{
  "type": "Feature",
  "properties": {
    "iso:country":"DE",
    "sg:address":"Hartmannstr. 22a",
    "sg:city":"Ludwigshafen",
    "sg:phone":"+49 621/523703",
    "sg:postcode":"67063",
    "sg:province":"Rheinland-Pfalz",
    "wof:name":"Wilhelm P\u00fclz",
    "wof:placetype":"venue"
},
  "geometry": {"coordinates":[8.439314,49.486862],"type":"Point"}
}