{
  "type": "Feature",
  "properties": {
    "iso:country":"DE",
    "sg:address":"Emmentaler Str. 114",
    "sg:city":"Berlin",
    "sg:phone":"+49 30/49861440",
    "sg:postcode":"13409",
    "sg:province":"Berlin",
    "wof:name":"W. Bohm",
    "wof:placetype":"venue"
},
  "geometry": {"coordinates":[13.364192,52.571568],"type":"Point"}
}