{
  "type": "Feature",
  "properties": {
    "iso:country":"DE",
    "sg:address":"Celler Str. 65",
    "sg:city":"Braunschweig",
    "sg:phone":"+49 531/53245",
    "sg:postcode":"38114",
    "sg:province":"Niedersachsen",
    "wof:name":"Shell-tankstelle",
    "wof:placetype":"venue"
},
  "geometry": {"coordinates":[10.5053539276,52.2796783447],"type":"Point"}
}