{
  "type": "Feature",
  "properties": {
    "iso:country":"DE",
    "sg:address":"B\u00e4ckerstr. 3",
    "sg:city":"Hameln",
    "sg:phone":"+49 5151/95180",
    "sg:postcode":"31785",
    "sg:province":"Niedersachsen",
    "wof:name":"Tutis Shop",
    "wof:placetype":"venue"
},
  "geometry": {"coordinates":[9.3566017151,52.1039352417],"type":"Point"}
}