{
  "type": "Feature",
  "properties": {
    "iso:country":"DE",
    "sg:address":"Wischhofstr. 1-3",
    "sg:city":"Kiel",
    "sg:phone":"+49 431/729485",
    "sg:postcode":"24148",
    "sg:province":"Schleswig-Holstein",
    "wof:name":"Gebr. Schr\u00f6der Gmbh",
    "wof:placetype":"venue"
},
  "geometry": {"coordinates":[10.1769132614,54.3276557922],"type":"Point"}
}