{
  "type": "Feature",
  "properties": {
    "iso:country":"DE",
    "sg:address":"Bergfriedhof 8",
    "sg:city":"T\u00fcbingen",
    "sg:phone":"+49 7071/32745",
    "sg:postcode":"72072",
    "sg:province":"Baden-W\u00fcrttemberg",
    "wof:name":"Krau\u00df Ges. F\u00fcr Grabmale Und Natursteinarbeiten Mbh",
    "wof:placetype":"venue"
},
  "geometry": {"coordinates":[9.0695724487,48.5039901733],"type":"Point"}
}