{
  "type": "Feature",
  "properties": {
    "iso:country":"DE",
    "sg:address":"Mainzer Str. 119",
    "sg:city":"Wiesbaden",
    "sg:phone":"+49 611/721879",
    "sg:postcode":"65189",
    "sg:province":"Hessen",
    "wof:name":"Holzwerkstatt Gie\u00df",
    "wof:placetype":"venue"
},
  "geometry": {"coordinates":[8.25388,50.059738],"type":"Point"}
}