{
  "type": "Feature",
  "properties": {
    "iso:country":"DE",
    "sg:address":"Hirtenstr. 17",
    "sg:city":"Ronnenberg",
    "sg:phone":"+49 511/462620",
    "sg:postcode":"30952",
    "sg:province":"Niedersachsen",
    "wof:name":"Hermann M\u00fcller Nachf. Gmbh",
    "wof:placetype":"venue"
},
  "geometry": {"coordinates":[9.665394,52.339207],"type":"Point"}
}