{
  "type": "Feature",
  "properties": {
    "iso:country":"DE",
    "sg:address":"Schuhmachers Weg 19",
    "sg:city":"Garbsen",
    "sg:phone":"+49 5131/54542",
    "sg:postcode":"30826",
    "sg:province":"Niedersachsen",
    "wof:name":"M. Freyer",
    "wof:placetype":"venue"
},
  "geometry": {"coordinates":[9.5501737595,52.4590072632],"type":"Point"}
}