{
  "type": "Feature",
  "properties": {
    "iso:country":"DE",
    "sg:address":"Frankfurter Str. 4 a",
    "sg:city":"Maintal",
    "sg:phone":"+49 6181/48497",
    "sg:postcode":"63477",
    "sg:province":"Hessen",
    "wof:name":"Dagmar Schr\u00f6der Steuerberaterin",
    "wof:placetype":"venue"
},
  "geometry": {"coordinates":[8.8410491943,50.1322364807],"type":"Point"}
}