{
  "type": "Feature",
  "properties": {
    "iso:country":"DE",
    "sg:address":"Heidestr. 11",
    "sg:city":"L\u00fcnen",
    "sg:phone":"+49 2306/53681",
    "sg:postcode":"44534",
    "sg:province":"Nordrhein-Westfalen",
    "wof:name":"Heinz Medaljon Architekt",
    "wof:placetype":"venue"
},
  "geometry": {"coordinates":[7.529602,51.628468],"type":"Point"}
}