{
  "type": "Feature",
  "properties": {
    "iso:country":"DE",
    "sg:address":"Bergsh\u00e4user Str.",
    "sg:city":"Lohfelden",
    "sg:phone":"+49 561/95980",
    "sg:postcode":"34253",
    "sg:province":"Hessen",
    "wof:name":"Hotel Autobahnrasthaus",
    "wof:placetype":"venue"
},
  "geometry": {"coordinates":[9.5351486206,51.2714996338],"type":"Point"}
}