{
  "type": "Feature",
  "properties": {
    "iso:country":"DE",
    "sg:address":"Volmarsteiner Str. 26",
    "sg:city":"Hagen",
    "sg:phone":"+49 2331/301001",
    "sg:postcode":"58089",
    "sg:province":"Nordrhein-Westfalen",
    "wof:name":"Raskopf Gesch\u00e4ftsf\u00fchrungs Gmbh",
    "wof:placetype":"venue"
},
  "geometry": {"coordinates":[7.400685,51.370323],"type":"Point"}
}