{
  "type": "Feature",
  "properties": {
    "iso:country":"DE",
    "sg:address":"Kirchplatz 3",
    "sg:city":"Sendenhorst",
    "sg:phone":"+49 2535/223",
    "sg:postcode":"48324",
    "sg:province":"Nordrhein-Westfalen",
    "wof:name":"Gasthof-hotel Zur Post",
    "wof:placetype":"venue"
},
  "geometry": {"coordinates":[7.7333722115,51.8683891296],"type":"Point"}
}