{
  "type": "Feature",
  "properties": {
    "iso:country":"DE",
    "sg:address":"Hauptstr. 108",
    "sg:city":"Langenwetzendorf",
    "sg:phone":"+49 36625/20288",
    "sg:postcode":"07957",
    "sg:province":"Th\u00fcringen",
    "wof:name":"K. Zschiegner",
    "wof:placetype":"venue"
},
  "geometry": {"coordinates":[12.0897426605,50.6830863953],"type":"Point"}
}