{
  "type": "Feature",
  "properties": {
    "iso:country":"DE",
    "sg:address":"Windische Gasse 112",
    "sg:city":"Heilbad Heiligenstadt",
    "sg:phone":"+49 3606/604554",
    "sg:postcode":"37308",
    "sg:province":"Th\u00fcringen",
    "wof:name":"Hsmt Handel U. Service Mit Me- Dizinprodukten U. Technik Gmbh",
    "wof:placetype":"venue"
},
  "geometry": {"coordinates":[10.141465,51.376888],"type":"Point"}
}