{
  "type": "Feature",
  "properties": {
    "iso:country":"DE",
    "sg:address":"Kleiststr. 29",
    "sg:city":"Wolfsburg",
    "sg:phone":"+49 5361/16267",
    "sg:postcode":"38440",
    "sg:province":"Niedersachsen",
    "wof:name":"Jeremias Gmbh",
    "wof:placetype":"venue"
},
  "geometry": {"coordinates":[10.7836704254,52.4250030518],"type":"Point"}
}