{
  "type": "Feature",
  "properties": {
    "iso:country":"DE",
    "sg:address":"Rembrandtstr. 9",
    "sg:city":"Heddesheim",
    "sg:phone":"+49 6203/41437",
    "sg:postcode":"68542",
    "sg:province":"Baden-W\u00fcrttemberg",
    "wof:name":"Peter G\u00e4ckle",
    "wof:placetype":"venue"
},
  "geometry": {"coordinates":[8.5947370529,49.5037498474],"type":"Point"}
}