{
  "type": "Feature",
  "properties": {
    "iso:country":"DE",
    "sg:address":"Hans-B\u00f6ckler-Str. 11",
    "sg:city":"Bergisch Gladbach",
    "sg:phone":"+49 2204/56690",
    "sg:postcode":"51429",
    "sg:province":"Nordrhein-Westfalen",
    "wof:name":"H. Alberti Und M. Wildenauer",
    "wof:placetype":"venue"
},
  "geometry": {"coordinates":[7.1433491707,50.9658737183],"type":"Point"}
}