{
  "type": "Feature",
  "properties": {
    "iso:country":"DE",
    "sg:address":"Alfelder Str. 98",
    "sg:city":"Hildesheim",
    "sg:phone":"+49 5121/44545",
    "sg:postcode":"31139",
    "sg:province":"Niedersachsen",
    "wof:name":"Bonnfinanz Ag",
    "wof:placetype":"venue"
},
  "geometry": {"coordinates":[9.9387493134,52.146648407],"type":"Point"}
}