{
  "type": "Feature",
  "properties": {
    "iso:country":"DE",
    "sg:address":"Bergstr. 1",
    "sg:city":"Hohwald",
    "sg:phone":"+49 3596/603321",
    "sg:postcode":"01844",
    "sg:province":"Sachsen",
    "wof:name":"G\u00fcnter Wulschner",
    "wof:placetype":"venue"
},
  "geometry": {"coordinates":[14.216246,51.03014],"type":"Point"}
}