{
  "type": "Feature",
  "properties": {
    "iso:country":"DE",
    "sg:address":"Schlo\u00dfstr. 1",
    "sg:city":"Schwarzenfeld",
    "sg:phone":"+49 9435/3236",
    "sg:postcode":"92521",
    "sg:province":"Bayern",
    "wof:name":"Pizzeria La Gondola",
    "wof:placetype":"venue"
},
  "geometry": {"coordinates":[12.1397800446,49.3886833191],"type":"Point"}
}