{
  "type": "Feature",
  "properties": {
    "iso:country":"DE",
    "sg:address":"Ave-Maria-Weg",
    "sg:city":"Deggingen",
    "sg:phone":"+49 7334/3640",
    "sg:postcode":"73326",
    "sg:province":"Baden-W\u00fcrttemberg",
    "wof:name":"P. Hinderer",
    "wof:placetype":"venue"
},
  "geometry": {"coordinates":[9.728495,48.598289],"type":"Point"}
}