{
  "type": "Feature",
  "properties": {
    "iso:country":"DE",
    "sg:address":"Am Katterbach 14b",
    "sg:city":"Bergisch Gladbach",
    "sg:phone":"+49 2202/84825",
    "sg:postcode":"51467",
    "sg:province":"Nordrhein-Westfalen",
    "wof:name":"G\u00fcnter Sch\u00f6nenborn",
    "wof:placetype":"venue"
},
  "geometry": {"coordinates":[7.078511,51.008636],"type":"Point"}
}