{
  "type": "Feature",
  "properties": {
    "iso:country":"DE",
    "sg:address":"Weismainer Str.",
    "sg:city":"Altenkunstadt",
    "sg:phone":"+49 9572/1269",
    "sg:postcode":"96264",
    "sg:province":"Bayern",
    "wof:name":"Erika Schamburek",
    "wof:placetype":"venue"
},
  "geometry": {"coordinates":[11.2379903793,50.1263694763],"type":"Point"}
}