{
  "type": "Feature",
  "properties": {
    "iso:country":"DE",
    "sg:address":"Maximilian-Kolbe-Str. 12",
    "sg:city":"L\u00fcdinghausen",
    "sg:phone":"+49 2591/78333",
    "sg:postcode":"59348",
    "sg:province":"Nordrhein-Westfalen",
    "wof:name":"Radu Stefanescu-gross Dipl.-ing. Architekt",
    "wof:placetype":"venue"
},
  "geometry": {"coordinates":[7.455142,51.772823],"type":"Point"}
}