{
  "type": "Feature",
  "properties": {
    "iso:country":"DE",
    "sg:address":"Schmiedestr. 23",
    "sg:city":"Wetter",
    "sg:phone":"+49 2335/973887",
    "sg:postcode":"58300",
    "sg:province":"Nordrhein-Westfalen",
    "wof:name":"Ernst Graumann",
    "wof:placetype":"venue"
},
  "geometry": {"coordinates":[7.34288311,51.4006690979],"type":"Point"}
}