{
  "type": "Feature",
  "properties": {
    "iso:country":"DE",
    "sg:address":"Kaiserstr. 98",
    "sg:city":"M\u00f6nchengladbach",
    "sg:phone":"+49 2161/17022",
    "sg:postcode":"41061",
    "sg:province":"Nordrhein-Westfalen",
    "wof:name":"Ermert Und Engel Rechtsanw\u00e4lte",
    "wof:placetype":"venue"
},
  "geometry": {"coordinates":[6.4415001869,51.1987571716],"type":"Point"}
}