{
  "type": "Feature",
  "properties": {
    "iso:country":"DE",
    "sg:address":"Schulstr. 50",
    "sg:city":"Stockstadt",
    "sg:phone":"+49 6027/7690",
    "sg:postcode":"63811",
    "sg:province":"Bayern",
    "wof:name":"Pizzeria Paradise",
    "wof:placetype":"venue"
},
  "geometry": {"coordinates":[9.0574092865,49.9775161743],"type":"Point"}
}