{
  "type": "Feature",
  "properties": {
    "iso:country":"DE",
    "sg:address":"Sch\u00f6nlinder Str. 1",
    "sg:city":"Schongau",
    "sg:postcode":"86956",
    "sg:province":"Bayern",
    "wof:name":"V2 Gmbh",
    "wof:placetype":"venue"
},
  "geometry": {"coordinates":[10.884013,47.819679],"type":"Point"}
}