{
  "type": "Feature",
  "properties": {
    "iso:country":"DE",
    "sg:address":"Siemensstr 13",
    "sg:city":"Rosenfeld",
    "sg:phone":"+49 7428/93840",
    "sg:postcode":"72348",
    "sg:province":"Baden-W\u00fcrttemberg",
    "wof:name":"Martin H\u00f6hn Gmbh",
    "wof:placetype":"venue"
},
  "geometry": {"coordinates":[8.7116241455,48.2843132019],"type":"Point"}
}