{
  "type": "Feature",
  "properties": {
    "iso:country":"DE",
    "sg:address":"Langenreem 43",
    "sg:city":"L\u00fcbeck",
    "sg:phone":"+49 451/3939",
    "sg:postcode":"23569",
    "sg:province":"Schleswig-Holstein",
    "wof:name":"Truckstop",
    "wof:placetype":"venue"
},
  "geometry": {"coordinates":[10.7431201935,53.9132118225],"type":"Point"}
}