{
  "type": "Feature",
  "properties": {
    "iso:country":"DE",
    "sg:address":"Lotharstr. 7",
    "sg:city":"Mainz",
    "sg:phone":"+49 6131/232494",
    "sg:postcode":"55116",
    "sg:province":"Rheinland-Pfalz",
    "wof:name":"Tui",
    "wof:placetype":"venue"
},
  "geometry": {"coordinates":[8.2669858932,50.0014915466],"type":"Point"}
}