{
  "type": "Feature",
  "properties": {
    "iso:country":"DE",
    "sg:address":"Dr.-Wimmer-Ring 12",
    "sg:city":"Bad Griesbach",
    "sg:phone":"+49 8532/2625",
    "sg:postcode":"94086",
    "sg:province":"Bayern",
    "wof:name":"Hubert Bichler Rechtsanwalt",
    "wof:placetype":"venue"
},
  "geometry": {"coordinates":[13.2024183273,48.4474067688],"type":"Point"}
}