{
  "type": "Feature",
  "properties": {
    "iso:country":"DE",
    "sg:address":"Hanauer Landstr. 568",
    "sg:city":"Frankfurt",
    "sg:phone":"+49 69/412890",
    "sg:postcode":"60386",
    "sg:province":"Hessen",
    "wof:name":"Bier-hannes",
    "wof:placetype":"venue"
},
  "geometry": {"coordinates":[8.7686109543,50.1335067749],"type":"Point"}
}