{
  "type": "Feature",
  "properties": {
    "iso:country":"DE",
    "sg:address":"Achillesstr. 14",
    "sg:city":"H\u00f6hr-Grenzhausen",
    "sg:phone":"+49 2624/7611",
    "sg:postcode":"56203",
    "sg:province":"Rheinland-Pfalz",
    "wof:name":"Horst Stein",
    "wof:placetype":"venue"
},
  "geometry": {"coordinates":[7.66257,50.429722],"type":"Point"}
}