{
  "type": "Feature",
  "properties": {
    "iso:country":"DE",
    "sg:address":"Hugenottenallee 168",
    "sg:city":"Neu-Isenburg",
    "sg:phone":"+49 6102/22553",
    "sg:postcode":"63263",
    "sg:province":"Hessen",
    "wof:name":"Rockmann Gmbh Transportvermittlung",
    "wof:placetype":"venue"
},
  "geometry": {"coordinates":[8.6898975372,50.0447921753],"type":"Point"}
}