{
  "type": "Feature",
  "properties": {
    "iso:country":"DE",
    "sg:address":"Beckumer Str. 91",
    "sg:city":"Ahlen",
    "sg:phone":"+49 2382/63506",
    "sg:postcode":"59229",
    "sg:province":"Nordrhein-Westfalen",
    "wof:name":"Restaurant Franz Kr\u00e4mer",
    "wof:placetype":"venue"
},
  "geometry": {"coordinates":[7.9092450142,51.7645072937],"type":"Point"}
}