{
  "type": "Feature",
  "properties": {
    "iso:country":"DE",
    "sg:address":"Lankwitzer Str. 7",
    "sg:city":"Berlin",
    "sg:phone":"+49 30/76802923",
    "sg:postcode":"12209",
    "sg:province":"Berlin",
    "wof:name":"Foto-raab Gmbh",
    "wof:placetype":"venue"
},
  "geometry": {"coordinates":[13.3307743073,52.4291801453],"type":"Point"}
}