{
  "type": "Feature",
  "properties": {
    "iso:country":"DE",
    "sg:address":"Tiefer Weg 99",
    "sg:city":"Hopfgarten",
    "sg:postcode":"99428",
    "sg:province":"Th\u00fcringen",
    "wof:name":"Ev.-luth. Kirche Hopfgarten",
    "wof:placetype":"venue"
},
  "geometry": {"coordinates":[11.2224617004,50.9869117737],"type":"Point"}
}