{
  "type": "Feature",
  "properties": {
    "iso:country":"DE",
    "sg:address":"Markelstr. 4",
    "sg:city":"Berlin",
    "sg:phone":"+49 30/7915807",
    "sg:postcode":"12163",
    "sg:province":"Berlin",
    "wof:name":"Heinz Stahl Elektromeister",
    "wof:placetype":"venue"
},
  "geometry": {"coordinates":[13.3245267868,52.4643249512],"type":"Point"}
}