{
  "type": "Feature",
  "properties": {
    "iso:country":"DE",
    "sg:address":"Am Vierrutenberg 30",
    "sg:city":"Berlin",
    "sg:phone":"+49 30/4025644",
    "sg:postcode":"13469",
    "sg:province":"Berlin",
    "wof:name":"Apotheke L\u00fcbars",
    "wof:placetype":"venue"
},
  "geometry": {"coordinates":[13.341691,52.6157],"type":"Point"}
}