{
  "type": "Feature",
  "properties": {
    "iso:country":"DE",
    "sg:address":"Tersteegenstr. 21",
    "sg:city":"Remscheid",
    "sg:phone":"+49 2191/790373",
    "sg:postcode":"42857",
    "sg:province":"Nordrhein-Westfalen",
    "wof:name":"Kremenholler Kopf",
    "wof:placetype":"venue"
},
  "geometry": {"coordinates":[7.1725201607,51.1699295044],"type":"Point"}
}