{
  "type": "Feature",
  "properties": {
    "iso:country":"DE",
    "sg:address":"Marktstr. 80",
    "sg:city":"Tiefenort",
    "sg:phone":"+49 3695/824296",
    "sg:postcode":"36469",
    "sg:province":"Th\u00fcringen",
    "wof:name":"Helmut Schellentr\u00e4ger",
    "wof:placetype":"venue"
},
  "geometry": {"coordinates":[10.166009,50.840107],"type":"Point"}
}