{
  "type": "Feature",
  "properties": {
    "iso:country":"DE",
    "sg:address":"Berliner Str. 5",
    "sg:city":"Berlin",
    "sg:phone":"+49 30/4050880",
    "sg:postcode":"13467",
    "sg:province":"Berlin",
    "wof:name":"Katthaen",
    "wof:placetype":"venue"
},
  "geometry": {"coordinates":[13.3156642914,52.6128807068],"type":"Point"}
}