{
  "type": "Feature",
  "properties": {
    "iso:country":"DE",
    "sg:address":"Gro\u00dfe Forststr. 189",
    "sg:city":"Niederzier",
    "sg:phone":"+49 2428/4261",
    "sg:postcode":"52382",
    "sg:province":"Nordrhein-Westfalen",
    "wof:name":"Pier Gmbh",
    "wof:placetype":"venue"
},
  "geometry": {"coordinates":[6.446051,50.899136],"type":"Point"}
}