{
  "type": "Feature",
  "properties": {
    "iso:country":"DE",
    "sg:address":"Winzerstr. 7-9",
    "sg:city":"Oestrich-Winkel",
    "sg:phone":"+49 6723/7753",
    "sg:postcode":"65375",
    "sg:province":"Hessen",
    "wof:name":"Hartex Industrie- Anlagentechnik Gmbh",
    "wof:placetype":"venue"
},
  "geometry": {"coordinates":[8.0331344604,50.0090637207],"type":"Point"}
}