{
  "type": "Feature",
  "properties": {
    "iso:country":"DE",
    "sg:address":"Dorfstr. 6",
    "sg:city":"Reichenberg",
    "sg:phone":"+49 9333/1494",
    "sg:postcode":"97234",
    "sg:province":"Bayern",
    "wof:name":"Br\u00e4ustube",
    "wof:placetype":"venue"
},
  "geometry": {"coordinates":[9.9699211121,49.6985206604],"type":"Point"}
}