{
  "type": "Feature",
  "properties": {
    "iso:country":"DE",
    "sg:address":"Plessenstr. 28",
    "sg:city":"Schleswig",
    "sg:phone":"+49 4621/21851",
    "sg:postcode":"24837",
    "sg:province":"Schleswig-Holstein",
    "wof:name":"Christels N\u00e4hstube",
    "wof:placetype":"venue"
},
  "geometry": {"coordinates":[9.566641,54.515892],"type":"Point"}
}