{
  "type": "Feature",
  "properties": {
    "iso:country":"DE",
    "sg:address":"Schlei\u00dfheimer Str. 426",
    "sg:city":"M\u00fcnchen",
    "sg:postcode":"80935",
    "sg:province":"Bayern",
    "wof:name":"R & G Holzhandels Gmbh",
    "wof:placetype":"venue"
},
  "geometry": {"coordinates":[11.5533847809,48.1995887756],"type":"Point"}
}