{
  "type": "Feature",
  "properties": {
    "iso:country":"DE",
    "sg:address":"H\u00f6pingen 80",
    "sg:city":"Rosendahl",
    "sg:phone":"+49 2545/1617",
    "sg:postcode":"48720",
    "sg:province":"Nordrhein-Westfalen",
    "wof:name":"D. M\u00e4nnl",
    "wof:placetype":"venue"
},
  "geometry": {"coordinates":[7.311143,52.024357],"type":"Point"}
}