{
  "type": "Feature",
  "properties": {
    "iso:country":"DE",
    "sg:address":"Hauptstr. 29",
    "sg:city":"Lehnin",
    "sg:phone":"+49 3382/700561",
    "sg:postcode":"14797",
    "sg:province":"Brandenburg",
    "wof:name":"Wendler Und Walter Masseure",
    "wof:placetype":"venue"
},
  "geometry": {"coordinates":[12.7454099655,52.3195304871],"type":"Point"}
}