{
  "type": "Feature",
  "properties": {
    "iso:country":"DE",
    "sg:address":"Quellenstr. 91",
    "sg:city":"Remagen",
    "sg:phone":"+49 2642/44589",
    "sg:postcode":"53424",
    "sg:province":"Rheinland-Pfalz",
    "wof:name":"G. Schumacher",
    "wof:placetype":"venue"
},
  "geometry": {"coordinates":[7.267950058,50.5593986511],"type":"Point"}
}