{
  "type": "Feature",
  "properties": {
    "iso:country":"DE",
    "sg:address":"Wieblingerstra\u00dfe 51",
    "sg:city":"Eppelheim",
    "sg:phone":"+49 6221/767833",
    "sg:postcode":"69214",
    "sg:province":"Baden-W\u00fcrttemberg",
    "wof:name":"Iip - Internet Information Project",
    "wof:placetype":"venue"
},
  "geometry": {"coordinates":[8.6348466873,49.4042015076],"type":"Point"}
}