{
  "type": "Feature",
  "properties": {
    "iso:country":"DE",
    "sg:address":"Nibelungenstr. 7",
    "sg:city":"Berlin",
    "sg:phone":"+49 30/4013784",
    "sg:postcode":"13465",
    "sg:province":"Berlin",
    "wof:name":"G\u00fcnter Thorwest",
    "wof:placetype":"venue"
},
  "geometry": {"coordinates":[13.2817049026,52.6347808838],"type":"Point"}
}