{
  "type": "Feature",
  "properties": {
    "iso:country":"DE",
    "sg:address":"Karl-Frey-Weg 11",
    "sg:city":"Baiersbronn",
    "sg:phone":"+49 7447/733",
    "sg:postcode":"72270",
    "sg:province":"Baden-W\u00fcrttemberg",
    "wof:name":"J\u00e4gerst\u00fcble Gastst\u00e4tte",
    "wof:placetype":"venue"
},
  "geometry": {"coordinates":[8.3881616592,48.6021461487],"type":"Point"}
}