{
  "type": "Feature",
  "properties": {
    "iso:country":"DE",
    "sg:address":"Schachtstr. 2",
    "sg:city":"L\u00fcdersfeld",
    "sg:phone":"+49 5725/915390",
    "sg:postcode":"31702",
    "sg:province":"Niedersachsen",
    "wof:name":"Skt Schm\u00e4deke Kommunaltechnik Gmbh",
    "wof:placetype":"venue"
},
  "geometry": {"coordinates":[9.245813,52.360012],"type":"Point"}
}