{
  "type": "Feature",
  "properties": {
    "iso:country":"DE",
    "sg:address":"Metgesheide 36",
    "sg:city":"Nettetal",
    "sg:phone":"+49 2153/72870",
    "sg:postcode":"41334",
    "sg:province":"Nordrhein-Westfalen",
    "wof:name":"Widuckel Gesellschaft Mbh",
    "wof:placetype":"venue"
},
  "geometry": {"coordinates":[6.2433037758,51.2889099121],"type":"Point"}
}