{
  "type": "Feature",
  "properties": {
    "iso:country":"DE",
    "sg:address":"Amalienstr. 10",
    "sg:city":"Oberhausen-Rheinhausen",
    "sg:phone":"+49 7254/2155",
    "sg:postcode":"68794",
    "sg:province":"Baden-W\u00fcrttemberg",
    "wof:name":"Spargel-absatzgenossen- Schaft Egmbh",
    "wof:placetype":"venue"
},
  "geometry": {"coordinates":[8.4835195541,49.2591323853],"type":"Point"}
}