{
  "type": "Feature",
  "properties": {
    "iso:country":"DE",
    "sg:address":"Baumeisterallee 29",
    "sg:city":"Schwedt",
    "sg:phone":"+49 3332/475327",
    "sg:postcode":"16303",
    "sg:province":"Brandenburg",
    "wof:name":"Abm Agrar Gmbh",
    "wof:placetype":"venue"
},
  "geometry": {"coordinates":[14.27239,53.049492],"type":"Point"}
}