{
  "type": "Feature",
  "properties": {
    "iso:country":"DE",
    "sg:address":"August-Bebel-Str. 199",
    "sg:city":"Hamburg",
    "sg:phone":"+49 40/7204055",
    "sg:postcode":"21029",
    "sg:province":"Hamburg",
    "wof:name":"Gerhard Nierlich Bildhauerei",
    "wof:placetype":"venue"
},
  "geometry": {"coordinates":[10.243702,53.481365],"type":"Point"}
}