{
  "type": "Feature",
  "properties": {
    "iso:country":"DE",
    "sg:address":"Gabrielistr. 5",
    "sg:city":"Eichst\u00e4tt",
    "sg:phone":"+49 8421/6040",
    "sg:postcode":"85072",
    "sg:province":"Bayern",
    "wof:name":"Sparkasse Eichst\u00c4tt",
    "wof:placetype":"venue"
},
  "geometry": {"coordinates":[11.184907,48.893482],"type":"Point"}
}