{
  "type": "Feature",
  "properties": {
    "iso:country":"DE",
    "sg:address":"K\u00f6niginstr. 23",
    "sg:city":"M\u00fcnchen",
    "sg:phone":"+49 89/3604990",
    "sg:postcode":"80539",
    "sg:province":"Bayern",
    "wof:name":"Abold B\u00dcro F. Marketingkommunikation Gmbh",
    "wof:placetype":"venue"
},
  "geometry": {"coordinates":[11.584666,48.147564],"type":"Point"}
}