{
  "type": "Feature",
  "properties": {
    "iso:country":"DE",
    "sg:address":"Kirchstr. 17",
    "sg:city":"Winterberg",
    "sg:phone":"+49 2981/1247",
    "sg:postcode":"59955",
    "sg:province":"Nordrhein-Westfalen",
    "wof:name":"Pension Renate Jung",
    "wof:placetype":"venue"
},
  "geometry": {"coordinates":[8.5378189087,51.1950721741],"type":"Point"}
}