{
  "type": "Feature",
  "properties": {
    "iso:country":"DE",
    "sg:address":"Weinbergstr. 25",
    "sg:city":"Holleben",
    "sg:phone":"+49 345/6130248",
    "sg:postcode":"06179",
    "sg:province":"Sachsen-Anhalt",
    "wof:name":"Agrargenossenschaft Holleben Eg",
    "wof:placetype":"venue"
},
  "geometry": {"coordinates":[11.89392,51.444695],"type":"Point"}
}