{
  "type": "Feature",
  "properties": {
    "iso:country":"DE",
    "sg:address":"Z\u00fcricher Str. 20",
    "sg:city":"N\u00fcrnberg",
    "sg:phone":"+49 911/608040",
    "sg:postcode":"90431",
    "sg:province":"Bayern",
    "wof:name":"Hopak-planungsges. F\u00fcr Hoch- Und Tiefbau Mbh",
    "wof:placetype":"venue"
},
  "geometry": {"coordinates":[11.026109,49.440266],"type":"Point"}
}