{
  "type": "Feature",
  "properties": {
    "iso:country":"DE",
    "sg:address":"Goethestr. 40",
    "sg:city":"P\u00fcttlingen",
    "sg:phone":"+49 6898/66049",
    "sg:postcode":"66346",
    "sg:province":"Saarland",
    "wof:name":"Helmut Texter",
    "wof:placetype":"venue"
},
  "geometry": {"coordinates":[6.879986,49.29266],"type":"Point"}
}