{
  "type": "Feature",
  "properties": {
    "iso:country":"DE",
    "sg:address":"Obereichhofen 12",
    "sg:city":"A\u00dfling",
    "sg:postcode":"85617",
    "sg:province":"Bayern",
    "wof:name":"Cramer Gmbh",
    "wof:placetype":"venue"
},
  "geometry": {"coordinates":[11.95426,48.004238],"type":"Point"}
}