{
  "type": "Feature",
  "properties": {
    "iso:country":"DE",
    "sg:address":"Birkheckenstr. 5",
    "sg:city":"Stuttgart",
    "sg:phone":"+49 711/4560313",
    "sg:postcode":"70599",
    "sg:province":"Baden-W\u00fcrttemberg",
    "wof:name":"G\u00fcnther Kauffmann",
    "wof:placetype":"venue"
},
  "geometry": {"coordinates":[9.2084665298,48.7223892212],"type":"Point"}
}