{
  "type": "Feature",
  "properties": {
    "iso:country":"DE",
    "sg:address":"Sprenger Weg 10",
    "sg:city":"Hoisdorf",
    "sg:phone":"+49 4107/5763",
    "sg:postcode":"22955",
    "sg:province":"Schleswig-Holstein",
    "wof:name":"M & T Grafik Design Electronic Publishing Gmbh",
    "wof:placetype":"venue"
},
  "geometry": {"coordinates":[10.3414697647,53.6588478088],"type":"Point"}
}