{
  "type": "Feature",
  "properties": {
    "iso:country":"DE",
    "sg:address":"Christopherusstr. 1",
    "sg:city":"Marburg",
    "sg:phone":"+49 6421/81886",
    "sg:postcode":"35041",
    "sg:province":"Hessen",
    "wof:name":"Ev. Pfarramt Trinitatiskirche Wehrda",
    "wof:placetype":"venue"
},
  "geometry": {"coordinates":[8.7539148331,50.8432273865],"type":"Point"}
}