{
  "type": "Feature",
  "properties": {
    "iso:country":"DE",
    "sg:address":"Negeleinstr. 2",
    "sg:city":"Kulmbach",
    "sg:phone":"+49 9221/1202",
    "sg:postcode":"95326",
    "sg:province":"Bayern",
    "wof:name":"B\u00fcrgerstube",
    "wof:placetype":"venue"
},
  "geometry": {"coordinates":[11.4491643906,50.1114883423],"type":"Point"}
}