{
  "type": "Feature",
  "properties": {
    "iso:country":"DE",
    "sg:address":"Heubnerstr. 4",
    "sg:city":"Lutherstadt Wittenberg",
    "sg:phone":"+49 3491/410832",
    "sg:postcode":"06886",
    "sg:province":"Sachsen-Anhalt",
    "wof:name":"M\u00f6belhaus Wittenberg D\u00fcmichen & Schr\u00f6dter",
    "wof:placetype":"venue"
},
  "geometry": {"coordinates":[12.6512842178,51.8689117432],"type":"Point"}
}