{
  "type": "Feature",
  "properties": {
    "iso:country":"DE",
    "sg:address":"Niebuhrstr. 78",
    "sg:city":"Berlin",
    "sg:phone":"+49 30/8847030",
    "sg:postcode":"10629",
    "sg:province":"Berlin",
    "wof:name":"Creativ Berlin Filmpartner Gmbh & Co.",
    "wof:placetype":"venue"
},
  "geometry": {"coordinates":[13.3191699982,52.5039672852],"type":"Point"}
}