{
  "type": "Feature",
  "properties": {
    "iso:country":"DE",
    "sg:address":"Ringstr. 15",
    "sg:city":"Sch\u00f6mberg",
    "sg:phone":"+49 7084/4248",
    "sg:postcode":"75328",
    "sg:province":"Baden-W\u00fcrttemberg",
    "wof:name":"Erwin Walz",
    "wof:placetype":"venue"
},
  "geometry": {"coordinates":[8.63355,48.803459],"type":"Point"}
}