{
  "type": "Feature",
  "properties": {
    "iso:country":"DE",
    "sg:address":"Diekstraat 11",
    "sg:city":"Norderfriedrichskoog",
    "sg:postcode":"25870",
    "sg:province":"Schleswig-Holstein",
    "wof:name":"Schmul Immobilien Beratungs- Und Organisations Gmbh",
    "wof:placetype":"venue"
},
  "geometry": {"coordinates":[8.8894748688,54.4034996033],"type":"Point"}
}