{
  "type": "Feature",
  "properties": {
    "iso:country":"DE",
    "sg:address":"Theodor-Heuss-Allee 2",
    "sg:city":"Frankfurt",
    "sg:classifiers":[
        {
            "category":"Professional",
            "subcategory":"Computer Services",
            "type":"Services"
        }
    ],
    "sg:postcode":"60486",
    "sg:tags":[
        "structure",
        "skyscraper",
        "building",
        "firm",
        "company",
        "enterprise",
        "database",
        "heights",
        "floors",
        "portal",
        "architectural",
        "corporation",
        "construction",
        "tower",
        "tall",
        "high",
        "wide",
        "architecture",
        "skyscrapers",
        "statistics",
        "commercial",
        "great-buildings",
        "tall-building",
        "real-estat"
    ],
    "sg:website":"http://corporate.emporis.com/",
    "wof:name":"Emporis",
    "wof:placetype":"venue"
},
  "geometry": {"coordinates":[8.6503108,50.1136964],"type":"Point"}
}