{
  "type": "Feature",
  "properties": {
    "iso:country":"DE",
    "sg:address":"Burscheider Str. 71",
    "sg:city":"D\u00fcsseldorf",
    "sg:phone":"+49 211/764959",
    "sg:postcode":"40591",
    "sg:province":"Nordrhein-Westfalen",
    "wof:name":"Reifen Biesenbach Gmbh",
    "wof:placetype":"venue"
},
  "geometry": {"coordinates":[6.821583,51.186161],"type":"Point"}
}