{
  "type": "Feature",
  "properties": {
    "iso:country":"DE",
    "sg:address":"Berliner Str. 21",
    "sg:city":"\u00d6hringen",
    "sg:phone":"+49 4975/4396250",
    "sg:postcode":"74613",
    "sg:province":"Baden-W\u00fcrttemberg",
    "wof:name":"Wlz Raiffeisen Ag",
    "wof:placetype":"venue"
},
  "geometry": {"coordinates":[9.597386,47.604897],"type":"Point"}
}