{
  "type": "Feature",
  "properties": {
    "iso:country":"DE",
    "sg:address":"Ahrensburger Str. 152",
    "sg:city":"Hamburg",
    "sg:phone":"+49 40/6695208",
    "sg:postcode":"22045",
    "sg:province":"Hamburg",
    "wof:name":"G\u00fcnther Ahlrep",
    "wof:placetype":"venue"
},
  "geometry": {"coordinates":[10.1080436707,53.5816116333],"type":"Point"}
}