{
  "type": "Feature",
  "properties": {
    "iso:country":"DE",
    "sg:address":"Fr\u00fchlingstr. 2",
    "sg:city":"Sonthofen",
    "sg:postcode":"87527",
    "sg:province":"Bayern",
    "wof:name":"Vdk Sonthofen Verband Der Kriegs- Und Wehrdienstopfer",
    "wof:placetype":"venue"
},
  "geometry": {"coordinates":[10.2804689407,47.5092849731],"type":"Point"}
}