{
  "type": "Feature",
  "properties": {
    "iso:country":"DE",
    "sg:address":"Birkenstr. 50",
    "sg:city":"Heimsheim",
    "sg:phone":"+49 7033/390293",
    "sg:postcode":"71296",
    "sg:province":"Baden-W\u00fcrttemberg",
    "wof:name":"Barnabas Wolf Gmbh",
    "wof:placetype":"venue"
},
  "geometry": {"coordinates":[8.874476,48.808136],"type":"Point"}
}