{
  "type": "Feature",
  "properties": {
    "iso:country":"DE",
    "sg:address":"Hildegardisstr. 1",
    "sg:city":"Bingen",
    "sg:phone":"+49 6721/32289",
    "sg:postcode":"55411",
    "sg:province":"Rheinland-Pfalz",
    "wof:name":"Kath. Pfarramt St. Rupert Und St. Hildegart",
    "wof:placetype":"venue"
},
  "geometry": {"coordinates":[7.8864011765,49.9644432068],"type":"Point"}
}