{
  "type": "Feature",
  "properties": {
    "iso:country":"DE",
    "sg:address":"Oldenburger Str. 37",
    "sg:city":"Berlin",
    "sg:phone":"+49 30/3952654",
    "sg:postcode":"10551",
    "sg:province":"Berlin",
    "wof:name":"Oldenburger Apotheke",
    "wof:placetype":"venue"
},
  "geometry": {"coordinates":[13.335879,52.530125],"type":"Point"}
}