{
  "type": "Feature",
  "properties": {
    "iso:country":"DE",
    "sg:address":"Ummelner Str. 10",
    "sg:city":"G\u00fctersloh",
    "sg:phone":"+49 5241/67203",
    "sg:postcode":"33334",
    "sg:province":"Nordrhein-Westfalen",
    "wof:name":"Wilhelm Sch\u00f6ning",
    "wof:placetype":"venue"
},
  "geometry": {"coordinates":[8.4148101807,51.9521789551],"type":"Point"}
}