{
  "type": "Feature",
  "properties": {
    "iso:country":"DE",
    "sg:address":"Herner Str. 79",
    "sg:city":"Bochum",
    "sg:phone":"+49 234/9409120",
    "sg:postcode":"44791",
    "sg:province":"Nordrhein-Westfalen",
    "wof:name":"Arex Industrieservice Gmbh",
    "wof:placetype":"venue"
},
  "geometry": {"coordinates":[7.2132849693,51.4905967712],"type":"Point"}
}