{
  "type": "Feature",
  "properties": {
    "iso:country":"DE",
    "sg:address":"Ortsstr. 14",
    "sg:city":"W\u00fclfershausen",
    "sg:phone":"+49 9762/9230",
    "sg:postcode":"97618",
    "sg:province":"Bayern",
    "wof:name":"Joachim Seifert Finanzberater",
    "wof:placetype":"venue"
},
  "geometry": {"coordinates":[10.304649353,50.3247795105],"type":"Point"}
}