{
  "type": "Feature",
  "properties": {
    "iso:country":"DE",
    "sg:address":"Lerchenplatz 2",
    "sg:city":"Neckarsulm",
    "sg:phone":"+49 7132/37296",
    "sg:postcode":"74172",
    "sg:province":"Baden-W\u00fcrttemberg",
    "wof:name":"Rudolf Keicher",
    "wof:placetype":"venue"
},
  "geometry": {"coordinates":[9.225748,49.187572],"type":"Point"}
}