{
  "type": "Feature",
  "properties": {
    "iso:country":"DE",
    "sg:address":"Martinistr. 19",
    "sg:city":"Greven",
    "sg:phone":"+49 2571/6884",
    "sg:postcode":"48268",
    "sg:province":"Nordrhein-Westfalen",
    "wof:name":"Ludwig Winninghoff Rechtsanwalt",
    "wof:placetype":"venue"
},
  "geometry": {"coordinates":[7.6104841232,52.0926551819],"type":"Point"}
}