{
  "type": "Feature",
  "properties": {
    "iso:country":"DE",
    "sg:address":"Am Gr\u00fcbchen 5a",
    "sg:city":"H\u00f6hr-Grenzhausen",
    "sg:phone":"+49 2624/4809",
    "sg:postcode":"56203",
    "sg:province":"Rheinland-Pfalz",
    "wof:name":"P\u00fcsch-immobilien",
    "wof:placetype":"venue"
},
  "geometry": {"coordinates":[7.6661930084,50.4341125488],"type":"Point"}
}