{
  "type": "Feature",
  "properties": {
    "iso:country":"DE",
    "sg:address":"M\u00fclheimer Str. 109",
    "sg:city":"Oberhausen",
    "sg:phone":"+49 208/23077",
    "sg:postcode":"46045",
    "sg:province":"Nordrhein-Westfalen",
    "wof:name":"A. Preusker",
    "wof:placetype":"venue"
},
  "geometry": {"coordinates":[6.863557,51.47538],"type":"Point"}
}