{
  "type": "Feature",
  "properties": {
    "iso:country":"DE",
    "sg:address":"Hauptstr. 60",
    "sg:city":"Barwedel",
    "sg:phone":"+49 5366/280",
    "sg:postcode":"38476",
    "sg:province":"Niedersachsen",
    "wof:name":"Adolf Kage",
    "wof:placetype":"venue"
},
  "geometry": {"coordinates":[10.767931,52.525475],"type":"Point"}
}