{
  "type": "Feature",
  "properties": {
    "iso:country":"DE",
    "sg:address":"Essener Str. 32",
    "sg:city":"Bakum",
    "sg:phone":"+49 5438/227",
    "sg:postcode":"49456",
    "sg:province":"Niedersachsen",
    "wof:name":"Hubert Ruhe",
    "wof:placetype":"venue"
},
  "geometry": {"coordinates":[8.076987,52.732338],"type":"Point"}
}