{
  "type": "Feature",
  "properties": {
    "iso:country":"DE",
    "sg:address":"Am Eichhof 2",
    "sg:city":"Hohne",
    "sg:phone":"+49 5083/1707",
    "sg:postcode":"29362",
    "sg:province":"Niedersachsen",
    "wof:name":"Rolf-j\u00fcrgen Oppermann",
    "wof:placetype":"venue"
},
  "geometry": {"coordinates":[10.385757,52.596901],"type":"Point"}
}