{
  "type": "Feature",
  "properties": {
    "iso:country":"DE",
    "sg:address":"Klopstockstr. 17",
    "sg:city":"Hamburg",
    "sg:phone":"+49 40/3903906",
    "sg:postcode":"22765",
    "sg:province":"Hamburg",
    "wof:name":"Dr. Jan Sorth Rechtsanwalt",
    "wof:placetype":"venue"
},
  "geometry": {"coordinates":[9.9331979752,53.5464057922],"type":"Point"}
}