{
  "type": "Feature",
  "properties": {
    "iso:country":"DE",
    "sg:address":"Findorffstr.85",
    "sg:city":"Bremen",
    "sg:postcode":"28215",
    "sg:province":"Bremen",
    "wof:name":"Findorffer Schachfreunde",
    "wof:placetype":"venue"
},
  "geometry": {"coordinates":[8.8101243973,53.0887527466],"type":"Point"}
}