{
  "type": "Feature",
  "properties": {
    "iso:country":"DE",
    "sg:address":"Bachstr. 5",
    "sg:city":"Lutter",
    "sg:phone":"+49 5383/450",
    "sg:postcode":"38729",
    "sg:province":"Niedersachsen",
    "wof:name":"A. Ahrens",
    "wof:placetype":"venue"
},
  "geometry": {"coordinates":[10.26478,51.988838],"type":"Point"}
}