{
  "type": "Feature",
  "properties": {
    "iso:country":"DE",
    "sg:address":"Sch\u00fclestr. 13",
    "sg:city":"Kirchheim",
    "sg:phone":"+49 7021/97530",
    "sg:postcode":"73230",
    "sg:province":"Baden-W\u00fcrttemberg",
    "wof:name":"Heudorfer Gmbh & Co.",
    "wof:placetype":"venue"
},
  "geometry": {"coordinates":[9.4472665787,48.647567749],"type":"Point"}
}