{
  "type": "Feature",
  "properties": {
    "iso:country":"DE",
    "sg:address":"Greifensteiner Str. 1",
    "sg:city":"Greifenstein",
    "sg:phone":"+49 2779/448",
    "sg:postcode":"35753",
    "sg:province":"Hessen",
    "wof:name":"Bronko Penezic",
    "wof:placetype":"venue"
},
  "geometry": {"coordinates":[8.2460222244,50.5880279541],"type":"Point"}
}