{
  "type": "Feature",
  "properties": {
    "iso:country":"DE",
    "sg:address":"Geschwister-Scholl-Str. 4",
    "sg:city":"Blankenhain",
    "sg:postcode":"99444",
    "sg:province":"Th\u00fcringen",
    "wof:name":"Deckenbach Reisen Gmbh & Co.",
    "wof:placetype":"venue"
},
  "geometry": {"coordinates":[11.347784996,50.8632850647],"type":"Point"}
}