{
  "type": "Feature",
  "properties": {
    "iso:country":"DE",
    "sg:address":"Balthasarstr. 53",
    "sg:city":"K\u00f6ln",
    "sg:phone":"+49 221/725301",
    "sg:postcode":"50670",
    "sg:province":"Nordrhein-Westfalen",
    "wof:name":"Fritz Winter",
    "wof:placetype":"venue"
},
  "geometry": {"coordinates":[6.95632,50.952991],"type":"Point"}
}