{
  "type": "Feature",
  "properties": {
    "iso:country":"DE",
    "sg:address":"Lisztstr. 4",
    "sg:city":"Singen",
    "sg:phone":"+49 7731/42715",
    "sg:postcode":"78224",
    "sg:province":"Baden-W\u00fcrttemberg",
    "wof:name":"Eberhard Spohn",
    "wof:placetype":"venue"
},
  "geometry": {"coordinates":[8.839766,47.768444],"type":"Point"}
}