{
  "type": "Feature",
  "properties": {
    "iso:country":"DE",
    "sg:address":"Hauptstr. 30",
    "sg:city":"M\u00f6nchengladbach",
    "sg:phone":"+49 2166/94730",
    "sg:postcode":"41236",
    "sg:province":"Nordrhein-Westfalen",
    "wof:name":"Touristik-service Radermacher Ohg",
    "wof:placetype":"venue"
},
  "geometry": {"coordinates":[6.4432020187,51.1678543091],"type":"Point"}
}