{
  "type": "Feature",
  "properties": {
    "iso:country":"DE",
    "sg:address":"Achenfeldstr. 21",
    "sg:city":"Garmisch-Partenkirchen",
    "sg:phone":"+49 8821/9150",
    "sg:postcode":"82467",
    "sg:province":"Bayern",
    "wof:name":"Krankenanstalt Massagen Und Med. B\u00e4der",
    "wof:placetype":"venue"
},
  "geometry": {"coordinates":[11.092608,47.492138],"type":"Point"}
}