{
  "type": "Feature",
  "properties": {
    "iso:country":"DE",
    "sg:address":"Harthausenstr. 2",
    "sg:city":"Zorneding",
    "sg:phone":"+49 8106/24210",
    "sg:postcode":"85604",
    "sg:province":"Bayern",
    "wof:name":"Ruderer Klebetechnik Gmbh",
    "wof:placetype":"venue"
},
  "geometry": {"coordinates":[11.822076,48.083164],"type":"Point"}
}