{
  "type": "Feature",
  "properties": {
    "iso:country":"DE",
    "sg:address":"Frauenberg",
    "sg:city":"Haidm\u00fchle",
    "sg:phone":"+49 8556/1055",
    "sg:postcode":"94145",
    "sg:province":"Bayern",
    "wof:name":"Gudrun Wei\u00df",
    "wof:placetype":"venue"
},
  "geometry": {"coordinates":[13.7473258972,48.7902641296],"type":"Point"}
}