{
  "type": "Feature",
  "properties": {
    "iso:country":"DE",
    "sg:address":"Dorfstr. 1",
    "sg:city":"Keller",
    "sg:phone":"+49 33083/80449",
    "sg:postcode":"16775",
    "sg:province":"Brandenburg",
    "wof:name":"Wolfgang Hohn",
    "wof:placetype":"venue"
},
  "geometry": {"coordinates":[13.031227,52.981304],"type":"Point"}
}