{
  "type": "Feature",
  "properties": {
    "iso:country":"DE",
    "sg:address":"Postfach 800405:: 45504 Hattingen:: Germany.^^Roonstr 1::",
    "sg:city":"Hattingen",
    "sg:phone":"+49 2324/2030",
    "sg:postcode":"45525",
    "sg:province":"Nordrhein-Westfalen",
    "wof:name":"Sparkasse Hattingen",
    "wof:placetype":"venue"
},
  "geometry": {"coordinates":[7.181681,51.396957],"type":"Point"}
}