{
  "type": "Feature",
  "properties": {
    "iso:country":"DE",
    "sg:address":"Donatusstr. 4",
    "sg:city":"K\u00f6ln",
    "sg:phone":"+49 221/5902964",
    "sg:postcode":"50767",
    "sg:province":"Nordrhein-Westfalen",
    "wof:name":"Harald Paproth",
    "wof:placetype":"venue"
},
  "geometry": {"coordinates":[6.8796229362,51.0000839233],"type":"Point"}
}