{
  "type": "Feature",
  "properties": {
    "iso:country":"DE",
    "sg:city":"K\u00f6ln",
    "sg:phone":"+49 221/9862742",
    "sg:postcode":"51107",
    "sg:province":"Nordrhein-Westfalen",
    "wof:name":"Acd-press K\u00f6ln",
    "wof:placetype":"venue"
},
  "geometry": {"coordinates":[7.081296,50.92165],"type":"Point"}
}