{
  "type": "Feature",
  "properties": {
    "iso:country":"DE",
    "sg:address":"Am Consrader Berg 8",
    "sg:city":"Plate",
    "sg:phone":"+49 385/208020",
    "sg:postcode":"19086",
    "sg:province":"Mecklenburg-Vorpommern",
    "wof:name":"Amwe-asphaltmischwerke Gmbh & Co. Kg N Schwerin",
    "wof:placetype":"venue"
},
  "geometry": {"coordinates":[11.4664745331,53.576675415],"type":"Point"}
}