{
  "type": "Feature",
  "properties": {
    "iso:country":"DE",
    "sg:address":"Hoherainstr. 49",
    "sg:city":"Gladenbach",
    "sg:phone":"+49 6462/6078",
    "sg:postcode":"35075",
    "sg:province":"Hessen",
    "wof:name":"Hotel-restaurant Zur Hinterl\u00e4nder Schweiz",
    "wof:placetype":"venue"
},
  "geometry": {"coordinates":[8.5790195465,50.7756271362],"type":"Point"}
}