{
  "type": "Feature",
  "properties": {
    "iso:country":"DE",
    "sg:address":"Ebersbacher Str. 36",
    "sg:city":"Aschaffenburg",
    "sg:phone":"+49 6021/94400",
    "sg:postcode":"63743",
    "sg:province":"Bayern",
    "wof:name":"Ludwig B\u00e4rschneider Farben Und Tapeten",
    "wof:placetype":"venue"
},
  "geometry": {"coordinates":[9.164412,49.952881],"type":"Point"}
}