{
  "type": "Feature",
  "properties": {
    "iso:country":"DE",
    "sg:address":"Mannheimer Str. 229",
    "sg:city":"Heidelberg",
    "sg:phone":"+49 6221/834488",
    "sg:postcode":"69123",
    "sg:province":"Baden-W\u00fcrttemberg",
    "wof:name":"Georg L. Ziegle Elektroinstallation",
    "wof:placetype":"venue"
},
  "geometry": {"coordinates":[8.649143,49.423695],"type":"Point"}
}