{
  "type": "Feature",
  "properties": {
    "iso:country":"DE",
    "sg:address":"Levinstr. 156",
    "sg:city":"Essen",
    "sg:postcode":"45356",
    "sg:province":"Nordrhein-Westfalen",
    "wof:name":"Janssen Gmbh & Co. Mobil Kg",
    "wof:placetype":"venue"
},
  "geometry": {"coordinates":[6.9424471855,51.4942131042],"type":"Point"}
}