{
  "type": "Feature",
  "properties": {
    "iso:country":"DE",
    "sg:address":"Riedstr. 4",
    "sg:city":"Geldersheim",
    "sg:phone":"+49 9721/87497",
    "sg:postcode":"97505",
    "sg:province":"Bayern",
    "wof:name":"Dieter Ziegler",
    "wof:placetype":"venue"
},
  "geometry": {"coordinates":[10.154067,50.04604],"type":"Point"}
}