{
  "type": "Feature",
  "properties": {
    "iso:country":"DE",
    "sg:address":"Otto-Hahn-Str. 17",
    "sg:city":"Kitzingen",
    "sg:phone":"+49 9321/385532",
    "sg:postcode":"97318",
    "sg:province":"Bayern",
    "wof:name":"Nightrockcafe",
    "wof:placetype":"venue"
},
  "geometry": {"coordinates":[10.194128,49.734196],"type":"Point"}
}