{
  "type": "Feature",
  "properties": {
    "iso:country":"DE",
    "sg:address":"Herzogstr. 61",
    "sg:city":"Neu-Isenburg",
    "sg:phone":"+49 6102/320028",
    "sg:postcode":"63263",
    "sg:province":"Hessen",
    "wof:name":"Dieter Michaelis Steuerberater",
    "wof:placetype":"venue"
},
  "geometry": {"coordinates":[8.7007389069,50.0502548218],"type":"Point"}
}