{
  "type": "Feature",
  "properties": {
    "iso:country":"DE",
    "sg:address":"Klausenhofstr. 100",
    "sg:city":"Hamminkeln",
    "sg:phone":"+49 2852/890",
    "sg:postcode":"46499",
    "sg:province":"Nordrhein-Westfalen",
    "wof:name":"Akademie Klausenhof Gmbh",
    "wof:placetype":"venue"
},
  "geometry": {"coordinates":[6.633616,51.773182],"type":"Point"}
}