{
  "type": "Feature",
  "properties": {
    "iso:country":"DE",
    "sg:address":"Kirchdorfer Str. 75",
    "sg:city":"Bad W\u00f6rishofen",
    "sg:phone":"+49 8247/96770",
    "sg:postcode":"86825",
    "sg:province":"Bayern",
    "wof:name":"Auto Waibl Verwaltungs Gmbh",
    "wof:placetype":"venue"
},
  "geometry": {"coordinates":[10.5956106186,48.0192070007],"type":"Point"}
}