{
  "type": "Feature",
  "properties": {
    "iso:country":"DE",
    "sg:address":"Schachener Str. 40",
    "sg:city":"Gersfeld",
    "sg:phone":"+49 6654/7158",
    "sg:postcode":"36129",
    "sg:province":"Hessen",
    "wof:name":"G\u00fcnther Niebling",
    "wof:placetype":"venue"
},
  "geometry": {"coordinates":[9.9274053574,50.4545249939],"type":"Point"}
}