{
  "type": "Feature",
  "properties": {
    "iso:country":"DE",
    "sg:address":"Timmerhellstr. 26",
    "sg:city":"M\u00fclheim",
    "sg:phone":"+49 208/593047",
    "sg:postcode":"45478",
    "sg:province":"Nordrhein-Westfalen",
    "wof:name":"Seifert Autogentechnik Gmbh",
    "wof:placetype":"venue"
},
  "geometry": {"coordinates":[6.851666,51.434921],"type":"Point"}
}