{
  "type": "Feature",
  "properties": {
    "iso:country":"DE",
    "sg:address":"Alt Bischofsheim 4",
    "sg:city":"Maintal",
    "sg:phone":"+49 6109/69091",
    "sg:postcode":"63477",
    "sg:province":"Hessen",
    "wof:name":"Dieter Philips Rechtsanwalt",
    "wof:placetype":"venue"
},
  "geometry": {"coordinates":[8.8031330109,50.1521263123],"type":"Point"}
}