{
  "type": "Feature",
  "properties": {
    "iso:country":"DE",
    "sg:address":"Weinbrennerstr. 3",
    "sg:city":"Karlsbad",
    "sg:phone":"+49 7202/5961",
    "sg:postcode":"76307",
    "sg:province":"Baden-W\u00fcrttemberg",
    "wof:name":"Hans-gerhard Kleiner Rechtsanwalt",
    "wof:placetype":"venue"
},
  "geometry": {"coordinates":[8.5054254532,48.9172096252],"type":"Point"}
}