{
  "type": "Feature",
  "properties": {
    "iso:country":"DE",
    "sg:address":"Scharnhorststr. 38",
    "sg:city":"Leverkusen",
    "sg:phone":"+49 214/75634",
    "sg:postcode":"51377",
    "sg:province":"Nordrhein-Westfalen",
    "wof:name":"Ev. Pfarramt Johanneskirche",
    "wof:placetype":"venue"
},
  "geometry": {"coordinates":[7.0196518898,51.0315742493],"type":"Point"}
}