{
  "type": "Feature",
  "properties": {
    "iso:country":"DE",
    "sg:address":"Leipziger Str. 19",
    "sg:city":"Eilenburg",
    "sg:phone":"+49 3423/2093",
    "sg:postcode":"04838",
    "sg:province":"Sachsen",
    "wof:name":"Schubert & Schneider",
    "wof:placetype":"venue"
},
  "geometry": {"coordinates":[12.629843,51.459312],"type":"Point"}
}