{
  "type": "Feature",
  "properties": {
    "iso:country":"DE",
    "sg:address":"Frohnhauser Weg 295",
    "sg:city":"M\u00fclheim",
    "sg:phone":"+49 208/497628",
    "sg:postcode":"45472",
    "sg:province":"Nordrhein-Westfalen",
    "wof:name":"Frohnhauser Gartenhof Beate Funkenberg Kg",
    "wof:placetype":"venue"
},
  "geometry": {"coordinates":[6.950691,51.44775],"type":"Point"}
}