{
  "type": "Feature",
  "properties": {
    "iso:country":"DE",
    "sg:address":"Lorenzstr. 11",
    "sg:city":"Stutensee",
    "sg:phone":"+49 7244/94383",
    "sg:postcode":"76297",
    "sg:province":"Baden-W\u00fcrttemberg",
    "wof:name":"J\u00fcrgen Hausberger",
    "wof:placetype":"venue"
},
  "geometry": {"coordinates":[8.456847,49.074062],"type":"Point"}
}