{
  "type": "Feature",
  "properties": {
    "iso:country":"DE",
    "sg:address":"Heinrich-Zille-Weg 22",
    "sg:city":"Freiberg",
    "sg:phone":"+49 3731/31640",
    "sg:postcode":"09599",
    "sg:province":"Sachsen",
    "wof:name":"Brigitte Heynert",
    "wof:placetype":"venue"
},
  "geometry": {"coordinates":[13.3570566177,50.9094009399],"type":"Point"}
}