{
  "type": "Feature",
  "properties": {
    "iso:country":"DE",
    "sg:address":"Rosentorstr. 32",
    "sg:city":"Goslar",
    "sg:phone":"+49 5321/26277",
    "sg:postcode":"38640",
    "sg:province":"Niedersachsen",
    "wof:name":"Augenoptik Friedrich H\u00f6rger\u00e4te Gmbh",
    "wof:placetype":"venue"
},
  "geometry": {"coordinates":[10.4272842407,51.9078369141],"type":"Point"}
}