{
  "type": "Feature",
  "properties": {
    "iso:country":"DE",
    "sg:address":"Benzstra\u00dfe 17",
    "sg:city":"Regensburg",
    "sg:phone":"+49 941/789154",
    "sg:postcode":"93053",
    "sg:province":"Bayern",
    "wof:name":"Dhs Vision Of Colour",
    "wof:placetype":"venue"
},
  "geometry": {"coordinates":[12.126801,48.997162],"type":"Point"}
}