{
  "type": "Feature",
  "properties": {
    "iso:country":"DE",
    "sg:address":"Steinstr. 16",
    "sg:city":"Teningen",
    "sg:phone":"+49 7641/3511",
    "sg:postcode":"79331",
    "sg:province":"Baden-W\u00fcrttemberg",
    "wof:name":"Richard Gro\u00df",
    "wof:placetype":"venue"
},
  "geometry": {"coordinates":[7.807427,48.125484],"type":"Point"}
}