{
  "type": "Feature",
  "properties": {
    "iso:country":"DE",
    "sg:address":"Am Horster Felde 5",
    "sg:city":"Bleckede",
    "sg:phone":"+49 5854/1051",
    "sg:postcode":"21354",
    "sg:province":"Niedersachsen",
    "wof:name":"Jagd Und Tour Reisevermittlungs Gmbh",
    "wof:placetype":"venue"
},
  "geometry": {"coordinates":[10.8007926941,53.2697486877],"type":"Point"}
}