{
  "type": "Feature",
  "properties": {
    "iso:country":"DE",
    "sg:address":"Ruprechtstr. 51",
    "sg:city":"Edesheim",
    "sg:phone":"+49 6323/2859",
    "sg:postcode":"67483",
    "sg:province":"Rheinland-Pfalz",
    "wof:name":"Karl Mentz Weinanbau",
    "wof:placetype":"venue"
},
  "geometry": {"coordinates":[8.1263132095,49.2589912415],"type":"Point"}
}