{
  "type": "Feature",
  "properties": {
    "iso:country":"DE",
    "sg:address":"Rollnerstr. 8",
    "sg:city":"N\u00fcrnberg",
    "sg:phone":"+49 911/393640",
    "sg:postcode":"90408",
    "sg:province":"Bayern",
    "wof:name":"Opinion Market Research & Consulting Gmbh",
    "wof:placetype":"venue"
},
  "geometry": {"coordinates":[11.081981,49.459934],"type":"Point"}
}