{
  "type": "Feature",
  "properties": {
    "iso:country":"DE",
    "sg:address":"B\u00f6rder Str. 3",
    "sg:city":"Bassum",
    "sg:phone":"+49 4241/7711",
    "sg:postcode":"27211",
    "sg:province":"Niedersachsen",
    "wof:name":"Flying Pizza",
    "wof:placetype":"venue"
},
  "geometry": {"coordinates":[8.71902,52.849861],"type":"Point"}
}