{
  "type": "Feature",
  "properties": {
    "iso:country":"DE",
    "sg:address":"Hilzweg 33",
    "sg:city":"Heidelberg",
    "sg:phone":"+49 6221/470212",
    "sg:postcode":"69121",
    "sg:province":"Baden-W\u00fcrttemberg",
    "wof:name":"Hans-peter Pollich Architekt",
    "wof:placetype":"venue"
},
  "geometry": {"coordinates":[8.684548,49.433582],"type":"Point"}
}