{
  "type": "Feature",
  "properties": {
    "iso:country":"DE",
    "sg:address":"Schuhgasse 1",
    "sg:city":"P\u00f6\u00dfneck",
    "sg:phone":"+49 3647/412509",
    "sg:postcode":"07381",
    "sg:province":"Th\u00fcringen",
    "wof:name":"Curt G\u00f6schel",
    "wof:placetype":"venue"
},
  "geometry": {"coordinates":[11.594534874,50.6942863464],"type":"Point"}
}