{
  "type": "Feature",
  "properties": {
    "iso:country":"DE",
    "sg:address":"Am Alten Forsthaus 8",
    "sg:city":"St. Ingbert",
    "sg:phone":"+49 6894/51241",
    "sg:postcode":"66386",
    "sg:province":"Saarland",
    "wof:name":"W. Fu\u00df",
    "wof:placetype":"venue"
},
  "geometry": {"coordinates":[7.1699938774,49.2802886963],"type":"Point"}
}