{
  "type": "Feature",
  "properties": {
    "iso:country":"DE",
    "sg:address":"Gustav-Bastert-Str. 17",
    "sg:city":"Bielefeld",
    "sg:phone":"+49 521/336686",
    "sg:postcode":"33719",
    "sg:province":"Nordrhein-Westfalen",
    "wof:name":"Schneider Food Gmbh & Co. Kg",
    "wof:placetype":"venue"
},
  "geometry": {"coordinates":[8.6099338531,52.0267791748],"type":"Point"}
}