{
  "type": "Feature",
  "properties": {
    "iso:country":"DE",
    "sg:address":"Unterer Marktplatz 3",
    "sg:city":"Dorfen",
    "sg:phone":"+49 8081/2538",
    "sg:postcode":"84405",
    "sg:province":"Bayern",
    "wof:name":"Hans-werner Hartl Rechtsanwalt",
    "wof:placetype":"venue"
},
  "geometry": {"coordinates":[12.1510801315,48.2732467651],"type":"Point"}
}