{
  "type": "Feature",
  "properties": {
    "iso:country":"DE",
    "sg:address":"Zeven",
    "sg:city":"Zeven",
    "sg:phone":"+49 4281/5990",
    "sg:postcode":"27404",
    "sg:province":"Niedersachsen",
    "wof:name":"All-for-eyes - Der Kontaklinsenversand -",
    "wof:placetype":"venue"
},
  "geometry": {"coordinates":[9.26132,53.281559],"type":"Point"}
}