{
  "type": "Feature",
  "properties": {
    "iso:country":"DE",
    "sg:address":"Zum Moor 2",
    "sg:city":"Handeloh",
    "sg:postcode":"21256",
    "sg:province":"Niedersachsen",
    "wof:name":"Quait Gmbh",
    "wof:placetype":"venue"
},
  "geometry": {"coordinates":[9.8591251373,53.268409729],"type":"Point"}
}