{
  "type": "Feature",
  "properties": {
    "iso:country":"DE",
    "sg:address":"Fritz-Buddin-Ring 6",
    "sg:city":"Sch\u00f6nberg",
    "sg:phone":"+49 38828/21365",
    "sg:postcode":"23923",
    "sg:province":"Mecklenburg-Vorpommern",
    "wof:name":"G\u00fcnter Stickel Gmbh",
    "wof:placetype":"venue"
},
  "geometry": {"coordinates":[10.918627,53.848969],"type":"Point"}
}