{
  "type": "Feature",
  "properties": {
    "iso:country":"DE",
    "sg:address":"Amalienstr. 53",
    "sg:city":"F\u00fcrth",
    "sg:phone":"+49 911/774443",
    "sg:postcode":"90763",
    "sg:province":"Bayern",
    "wof:name":"Hermetico Laborbedarf",
    "wof:placetype":"venue"
},
  "geometry": {"coordinates":[10.990564,49.467793],"type":"Point"}
}