{
  "type": "Feature",
  "properties": {
    "iso:country":"DE",
    "sg:city":"Gartow",
    "sg:phone":"+49 4958/46565",
    "sg:postcode":"29471",
    "sg:province":"Niedersachsen",
    "wof:name":"Volksbank Dannenberg Eg",
    "wof:placetype":"venue"
},
  "geometry": {"coordinates":[11.449335,53.022209],"type":"Point"}
}