{
  "type": "Feature",
  "properties": {
    "iso:country":"DE",
    "sg:address":"Alte Wache 6",
    "sg:city":"Lauenburg",
    "sg:phone":"+49 4153/52277",
    "sg:postcode":"21481",
    "sg:province":"Schleswig-Holstein",
    "wof:name":"Bernd Hofmann",
    "wof:placetype":"venue"
},
  "geometry": {"coordinates":[10.5567750931,53.3731956482],"type":"Point"}
}