{
  "type": "Feature",
  "properties": {
    "iso:country":"DE",
    "sg:address":"Kirchstr. 13",
    "sg:city":"Brinkum",
    "sg:phone":"+49 4950/444",
    "sg:postcode":"26835",
    "sg:province":"Niedersachsen",
    "wof:name":"J\u00e4gerst\u00fcbchen",
    "wof:placetype":"venue"
},
  "geometry": {"coordinates":[7.561319828,53.2688446045],"type":"Point"}
}