{
  "type": "Feature",
  "properties": {
    "iso:country":"DE",
    "sg:address":"Wasserschiederstr. 16",
    "sg:city":"Birkenfeld",
    "sg:phone":"+49 6782/2413",
    "sg:postcode":"55765",
    "sg:province":"Rheinland-Pfalz",
    "wof:name":"Alt Birkenfeld",
    "wof:placetype":"venue"
},
  "geometry": {"coordinates":[7.171172142,49.649181366],"type":"Point"}
}