{
  "type": "Feature",
  "properties": {
    "iso:country":"DE",
    "sg:address":"Schottjer Str. 50",
    "sg:city":"Upgant-Schott",
    "sg:phone":"+49 4934/1325",
    "sg:postcode":"26529",
    "sg:province":"Niedersachsen",
    "wof:name":"Imbi\u00df Hansgeorg Pohl",
    "wof:placetype":"venue"
},
  "geometry": {"coordinates":[7.2634191513,53.5091094971],"type":"Point"}
}