{
  "type": "Feature",
  "properties": {
    "iso:country":"DE",
    "sg:address":"Gotmarstr. 4",
    "sg:city":"G\u00f6ttingen",
    "sg:phone":"+49 551/44645",
    "sg:postcode":"37073",
    "sg:province":"Niedersachsen",
    "wof:name":"G. Becker",
    "wof:placetype":"venue"
},
  "geometry": {"coordinates":[9.933744,51.534],"type":"Point"}
}