{
  "type": "Feature",
  "properties": {
    "iso:country":"DE",
    "sg:address":"Spreenende 38",
    "sg:city":"Hamburg",
    "sg:phone":"+49 40/5536612",
    "sg:postcode":"22453",
    "sg:province":"Hamburg",
    "wof:name":"Werner Kalisch",
    "wof:placetype":"venue"
},
  "geometry": {"coordinates":[9.978115,53.613117],"type":"Point"}
}