{
  "type": "Feature",
  "properties": {
    "iso:country":"DE",
    "sg:address":"Industriestr.30-34",
    "sg:city":"Eschborn",
    "sg:phone":"+49 4961/9695560",
    "sg:postcode":"65760",
    "sg:province":"Hessen",
    "wof:name":"Novartis Tiergesundheit Gmbh",
    "wof:placetype":"venue"
},
  "geometry": {"coordinates":[8.55138,50.146111],"type":"Point"}
}