{
  "type": "Feature",
  "properties": {
    "iso:country":"DE",
    "sg:address":"Tannenweg 7",
    "sg:city":"Hallbergmoos",
    "sg:phone":"+49 811/93717",
    "sg:postcode":"85399",
    "sg:province":"Bayern",
    "wof:name":"G. Agola-comel",
    "wof:placetype":"venue"
},
  "geometry": {"coordinates":[11.740964,48.311359],"type":"Point"}
}