{
  "type": "Feature",
  "properties": {
    "iso:country":"DE",
    "sg:address":"Halderstr. 3-5",
    "sg:city":"Augsburg",
    "sg:phone":"+49 821/3255510",
    "sg:postcode":"86150",
    "sg:province":"Bayern",
    "wof:name":"Aufwind",
    "wof:placetype":"venue"
},
  "geometry": {"coordinates":[10.8922357559,48.364906311],"type":"Point"}
}