{
  "type": "Feature",
  "properties": {
    "iso:country":"DE",
    "sg:address":"Kadettenweg 61",
    "sg:city":"Berlin",
    "sg:phone":"+49 30/8331120",
    "sg:postcode":"12205",
    "sg:province":"Berlin",
    "wof:name":"Sylvia-carmen Tanz-rutz Steuerberaterin",
    "wof:placetype":"venue"
},
  "geometry": {"coordinates":[13.2992124557,52.4354667664],"type":"Point"}
}