{
  "type": "Feature",
  "properties": {
    "iso:country":"DE",
    "sg:address":"Klosterbergstr. 42",
    "sg:city":"Vaihingen",
    "sg:phone":"+49 7042/3058",
    "sg:postcode":"71665",
    "sg:province":"Baden-W\u00fcrttemberg",
    "wof:name":"Kloster-apotheke",
    "wof:placetype":"venue"
},
  "geometry": {"coordinates":[8.989002,48.978806],"type":"Point"}
}