{
  "type": "Feature",
  "properties": {
    "iso:country":"DE",
    "sg:address":"Am Krekel 55",
    "sg:city":"Marburg",
    "sg:phone":"+49 6421/91110",
    "sg:postcode":"35039",
    "sg:province":"Hessen",
    "wof:name":"Gewobau",
    "wof:placetype":"venue"
},
  "geometry": {"coordinates":[8.7574920654,50.7891426086],"type":"Point"}
}