{
  "type": "Feature",
  "properties": {
    "iso:country":"DE",
    "sg:address":"Gro\u00dfer Anger 33",
    "sg:city":"Ha\u00dffurt",
    "sg:phone":"+49 9521/5131",
    "sg:postcode":"97437",
    "sg:province":"Bayern",
    "wof:name":"Freizeit- Und Erlebnisbad",
    "wof:placetype":"venue"
},
  "geometry": {"coordinates":[10.5039758682,50.0368614197],"type":"Point"}
}