{
  "type": "Feature",
  "properties": {
    "iso:country":"DE",
    "sg:address":"K\u00f6nigstrasse 20",
    "sg:city":"Rosenheim",
    "sg:phone":"+49 8031/31029",
    "sg:postcode":"83022",
    "sg:province":"Bayern",
    "wof:name":"Die Schoene Wohnung Einrichtungs Gmbh",
    "wof:placetype":"venue"
},
  "geometry": {"coordinates":[12.1293506622,47.8540725708],"type":"Point"}
}