{
  "type": "Feature",
  "properties": {
    "iso:country":"DE",
    "sg:address":"Heidestr. 1",
    "sg:city":"Oberasbach",
    "sg:phone":"+49 911/9699256",
    "sg:postcode":"90522",
    "sg:province":"Bayern",
    "wof:name":"Spitzbart Treppenbau Gmbh",
    "wof:placetype":"venue"
},
  "geometry": {"coordinates":[10.9896,49.414085],"type":"Point"}
}