{
  "type": "Feature",
  "properties": {
    "iso:country":"DE",
    "sg:address":"J\u00e4gerweg 3",
    "sg:city":"Bad F\u00fcssing",
    "sg:phone":"+49 8531/24692",
    "sg:postcode":"94072",
    "sg:province":"Bayern",
    "wof:name":"G\u00e4stehaus Brigitte",
    "wof:placetype":"venue"
},
  "geometry": {"coordinates":[13.3093328476,48.3452606201],"type":"Point"}
}