{
  "type": "Feature",
  "properties": {
    "iso:country":"DE",
    "sg:address":"Marcobrunnerstr. 15",
    "sg:city":"Wiesbaden",
    "sg:postcode":"65197",
    "sg:province":"Hessen",
    "wof:name":"Promedium Gmbh",
    "wof:placetype":"venue"
},
  "geometry": {"coordinates":[8.2256031036,50.0765190125],"type":"Point"}
}