{
  "type": "Feature",
  "properties": {
    "iso:country":"DE",
    "sg:address":"Innere Zwickauer Str. 112",
    "sg:city":"Zwickau",
    "sg:phone":"+49 375/785382",
    "sg:postcode":"08064",
    "sg:province":"Sachsen",
    "wof:name":"J. Fischer",
    "wof:placetype":"venue"
},
  "geometry": {"coordinates":[12.48306,50.673489],"type":"Point"}
}