{
  "type": "Feature",
  "properties": {
    "iso:country":"DE",
    "sg:address":"Rainwaldstr. 6",
    "sg:city":"Oberstaufen",
    "sg:phone":"+49 8386/558",
    "sg:postcode":"87534",
    "sg:province":"Bayern",
    "wof:name":"Katholisches Pfarramt St. Peter Und Paul",
    "wof:placetype":"venue"
},
  "geometry": {"coordinates":[10.0241680145,47.5535011292],"type":"Point"}
}