{
  "type": "Feature",
  "properties": {
    "iso:country":"DE",
    "sg:address":"Blumenstr. 21",
    "sg:city":"Stuttgart",
    "sg:phone":"+49 711/244866",
    "sg:postcode":"70182",
    "sg:province":"Baden-W\u00fcrttemberg",
    "wof:name":"Der Raum",
    "wof:placetype":"venue"
},
  "geometry": {"coordinates":[9.187374,48.774353],"type":"Point"}
}