{
  "type": "Feature",
  "properties": {
    "iso:country":"DE",
    "sg:address":"Steinbeisstr. 1",
    "sg:city":"Urbach",
    "sg:phone":"+49 7181/45044",
    "sg:postcode":"73660",
    "sg:province":"Baden-W\u00fcrttemberg",
    "wof:name":"Sksf Steuerungstechnik Gmbh",
    "wof:placetype":"venue"
},
  "geometry": {"coordinates":[9.565633,48.809223],"type":"Point"}
}