{
  "type": "Feature",
  "properties": {
    "iso:country":"DE",
    "sg:address":"Dringenberger Str. 24",
    "sg:city":"Bad Driburg",
    "sg:phone":"+49 5253/3305",
    "sg:postcode":"33014",
    "sg:province":"Nordrhein-Westfalen",
    "wof:name":"Tanzcafe Harlekin",
    "wof:placetype":"venue"
},
  "geometry": {"coordinates":[9.018549,51.732616],"type":"Point"}
}