{
  "type": "Feature",
  "properties": {
    "iso:country":"DE",
    "sg:address":"Farbgasse 6",
    "sg:city":"Lichtenfels",
    "sg:phone":"+49 9571/759870",
    "sg:postcode":"96215",
    "sg:province":"Bayern",
    "wof:name":"Pierce Things Piercings And More",
    "wof:placetype":"venue"
},
  "geometry": {"coordinates":[11.0619735718,50.1460876465],"type":"Point"}
}