{
  "type": "Feature",
  "properties": {
    "iso:country":"DE",
    "sg:address":"Haydnstr. 1",
    "sg:city":"Ostrhauderfehn",
    "sg:phone":"+49 4952/6481",
    "sg:postcode":"26842",
    "sg:province":"Niedersachsen",
    "wof:name":"L. Trey",
    "wof:placetype":"venue"
},
  "geometry": {"coordinates":[7.612207,53.132057],"type":"Point"}
}