{
  "type": "Feature",
  "properties": {
    "iso:country":"DE",
    "sg:address":"M\u00fchlweg 29",
    "sg:city":"Murr",
    "sg:phone":"+49 7144/2873",
    "sg:postcode":"71711",
    "sg:province":"Baden-W\u00fcrttemberg",
    "wof:name":"Huf Werbeartikel-reklamez\u00fcndh\u00f6lzer",
    "wof:placetype":"venue"
},
  "geometry": {"coordinates":[9.2586479187,48.9591407776],"type":"Point"}
}