{
  "type": "Feature",
  "properties": {
    "iso:country":"DE",
    "sg:address":"Opelstr. 14",
    "sg:city":"M\u00f6rfelden-Walldorf",
    "sg:phone":"+49 6105/23051",
    "sg:postcode":"64546",
    "sg:province":"Hessen",
    "wof:name":"Bs Treuhand Steuerberatungsges. Mbh",
    "wof:placetype":"venue"
},
  "geometry": {"coordinates":[8.5651397705,49.9668083191],"type":"Point"}
}