{
  "type": "Feature",
  "properties": {
    "iso:country":"DE",
    "sg:address":"Jengerstr. 6",
    "sg:city":"Ehrenkirchen",
    "sg:phone":"+49 4976/336866",
    "sg:postcode":"79238",
    "sg:province":"Baden-W\u00fcrttemberg",
    "wof:name":"Volksbank Staufen Eg",
    "wof:placetype":"venue"
},
  "geometry": {"coordinates":[7.745691,47.917942],"type":"Point"}
}