{
  "type": "Feature",
  "properties": {
    "iso:country":"DE",
    "sg:address":"Walther-Rathenau-Str. 2",
    "sg:city":"Heppenheim",
    "sg:phone":"+49 4962/52171",
    "sg:postcode":"64646",
    "sg:province":"Hessen",
    "wof:name":"Bezirkssparkasse, Heppenheim (bergstr.)",
    "wof:placetype":"venue"
},
  "geometry": {"coordinates":[8.639968,49.639385],"type":"Point"}
}