{
  "type": "Feature",
  "properties": {
    "iso:country":"DE",
    "sg:address":"Hochschulstr. 1",
    "sg:city":"Darmstadt",
    "sg:postcode":"64289",
    "sg:province":"Hessen",
    "wof:name":"Fachbereich Rechts- Und Wirtschaftswissenschaften",
    "wof:placetype":"venue"
},
  "geometry": {"coordinates":[8.656281,49.877316],"type":"Point"}
}