{
  "type": "Feature",
  "properties": {
    "iso:country":"DE",
    "sg:address":"Arberstr. 26",
    "sg:city":"Schwandorf",
    "sg:phone":"+49 9431/3129",
    "sg:postcode":"92421",
    "sg:province":"Bayern",
    "wof:name":"S. Mickisch",
    "wof:placetype":"venue"
},
  "geometry": {"coordinates":[12.1232509613,49.3210411072],"type":"Point"}
}