{
  "type": "Feature",
  "properties": {
    "iso:country":"DE",
    "sg:address":"Rathausplatz 4",
    "sg:city":"Wilhelmshaven",
    "sg:phone":"+49 4421/34088",
    "sg:postcode":"26382",
    "sg:province":"Niedersachsen",
    "wof:name":"Dagmar Ottens Masseurin",
    "wof:placetype":"venue"
},
  "geometry": {"coordinates":[8.110615,53.52758],"type":"Point"}
}