{
  "type": "Feature",
  "properties": {
    "iso:country":"DE",
    "sg:address":"Schwieberdinger Str. 44",
    "sg:city":"Ludwigsburg",
    "sg:postcode":"71636",
    "sg:province":"Baden-W\u00fcrttemberg",
    "wof:name":"Groger Automation Gmbh",
    "wof:placetype":"venue"
},
  "geometry": {"coordinates":[9.177432,48.89056],"type":"Point"}
}