{
  "type": "Feature",
  "properties": {
    "iso:country":"DE",
    "sg:address":"Reimersstr. 36",
    "sg:city":"Leer",
    "sg:postcode":"26789",
    "sg:province":"Niedersachsen",
    "wof:name":"M\u00f6schle Zerkleinerungs- Systeme Gmbh & Co. Kg",
    "wof:placetype":"venue"
},
  "geometry": {"coordinates":[7.466109,53.226597],"type":"Point"}
}