{
  "type": "Feature",
  "properties": {
    "iso:country":"DE",
    "sg:address":"Schwachhauser Ring 2",
    "sg:city":"Bremen",
    "sg:phone":"+49 421/344496",
    "sg:postcode":"28209",
    "sg:province":"Bremen",
    "wof:name":"M. Meier-klages",
    "wof:placetype":"venue"
},
  "geometry": {"coordinates":[8.8492698669,53.0862083435],"type":"Point"}
}