{
  "type": "Feature",
  "properties": {
    "iso:country":"DE",
    "sg:address":"Hauptstr. 4",
    "sg:city":"L\u00fcbbow",
    "sg:phone":"+49 4958/437101",
    "sg:postcode":"29488",
    "sg:province":"Niedersachsen",
    "wof:name":"Volksbank Wendland Eg",
    "wof:placetype":"venue"
},
  "geometry": {"coordinates":[11.181034,52.911228],"type":"Point"}
}