{
  "type": "Feature",
  "properties": {
    "iso:country":"DE",
    "sg:address":"Pfeuferstr. 8",
    "sg:city":"M\u00fcnchen",
    "sg:phone":"+49 89/776660",
    "sg:postcode":"81373",
    "sg:province":"Bayern",
    "wof:name":"Alfred Baumg\u00e4rtner Ingenieur",
    "wof:placetype":"venue"
},
  "geometry": {"coordinates":[11.5400257111,48.1262550354],"type":"Point"}
}