{
  "type": "Feature",
  "properties": {
    "iso:country":"DE",
    "sg:address":"Neckarstr. 2",
    "sg:city":"Dietzenbach",
    "sg:phone":"+49 6074/32822",
    "sg:postcode":"63128",
    "sg:province":"Hessen",
    "wof:name":"Heil Gmbh Hausverwaltung",
    "wof:placetype":"venue"
},
  "geometry": {"coordinates":[8.790804863,50.0278396606],"type":"Point"}
}