{
  "type": "Feature",
  "properties": {
    "iso:country":"DE",
    "sg:address":"Kirchstr. 13",
    "sg:city":"Bad Kreuznach",
    "sg:phone":"+49 671/43030",
    "sg:postcode":"55545",
    "sg:province":"Rheinland-Pfalz",
    "wof:name":"Steffen Meinhard",
    "wof:placetype":"venue"
},
  "geometry": {"coordinates":[7.8654198647,49.8714370728],"type":"Point"}
}