{
  "type": "Feature",
  "properties": {
    "iso:country":"DE",
    "sg:address":"Schlo\u00dfstr. 22",
    "sg:city":"Borken",
    "sg:postcode":"34582",
    "sg:province":"Hessen",
    "wof:name":"Rehm Grundst\u00fccks Gmbh & Co. Kg",
    "wof:placetype":"venue"
},
  "geometry": {"coordinates":[9.2460584641,51.0539970398],"type":"Point"}
}