{
  "type": "Feature",
  "properties": {
    "iso:country":"DE",
    "sg:address":"Bad Sodener Str. 11",
    "sg:city":"Bad Soden-Salm\u00fcnster",
    "sg:phone":"+49 6056/2566",
    "sg:postcode":"63628",
    "sg:province":"Hessen",
    "wof:name":"Martin May Augenoptiker",
    "wof:placetype":"venue"
},
  "geometry": {"coordinates":[9.3683481216,50.2789764404],"type":"Point"}
}