{
  "type": "Feature",
  "properties": {
    "iso:country":"DE",
    "sg:address":"Dorf Zellhub 48",
    "sg:city":"Eggenfelden",
    "sg:phone":"+49 8721/1805",
    "sg:postcode":"84307",
    "sg:province":"Bayern",
    "wof:name":"Bauturm Peter W. Michalski",
    "wof:placetype":"venue"
},
  "geometry": {"coordinates":[12.786572,48.411625],"type":"Point"}
}