{
  "type": "Feature",
  "properties": {
    "iso:country":"DE",
    "sg:address":"Am Steinbrink 35",
    "sg:city":"Hasbergen",
    "sg:phone":"+49 5405/2278",
    "sg:postcode":"49205",
    "sg:province":"Niedersachsen",
    "wof:name":"Wilhelm B\u00fcker",
    "wof:placetype":"venue"
},
  "geometry": {"coordinates":[7.970198,52.22908],"type":"Point"}
}