{
  "type": "Feature",
  "properties": {
    "iso:country":"DE",
    "sg:address":"Hauptstr. 82",
    "sg:city":"Eibau",
    "sg:phone":"+49 3586/702535",
    "sg:postcode":"02739",
    "sg:province":"Sachsen",
    "wof:name":"Lutz Stolle",
    "wof:placetype":"venue"
},
  "geometry": {"coordinates":[14.664393,50.981453],"type":"Point"}
}