{
  "type": "Feature",
  "properties": {
    "iso:country":"DE",
    "sg:address":"Viehhofstra\u00dfe 125",
    "sg:city":"Wuppertal",
    "sg:phone":"+49 202/2427150",
    "sg:postcode":"42117",
    "sg:province":"Nordrhein-Westfalen",
    "wof:name":"Spitzlicht Fotografie",
    "wof:placetype":"venue"
},
  "geometry": {"coordinates":[7.131677,51.245403],"type":"Point"}
}