{
  "type": "Feature",
  "properties": {
    "iso:country":"DE",
    "sg:address":"Stollberger Str 55",
    "sg:city":"Jahnsdorf",
    "sg:phone":"+49 37296/7620",
    "sg:postcode":"09387",
    "sg:province":"Sachsen",
    "wof:name":"Leistritz Abgastechnik Stollberg Gmbh",
    "wof:placetype":"venue"
},
  "geometry": {"coordinates":[12.8203926086,50.7484664917],"type":"Point"}
}