{
  "type": "Feature",
  "properties": {
    "iso:country":"DE",
    "sg:address":"Oberst\u00fcterstr. 6",
    "sg:city":"Hattingen",
    "sg:phone":"+49 2324/78988",
    "sg:postcode":"45527",
    "sg:province":"Nordrhein-Westfalen",
    "wof:name":"H\u00fcgelland",
    "wof:placetype":"venue"
},
  "geometry": {"coordinates":[7.1947088242,51.3483543396],"type":"Point"}
}