{
  "type": "Feature",
  "properties": {
    "iso:country":"DE",
    "sg:address":"Maschm\u00fchlenweg 50",
    "sg:city":"G\u00f6ttingen",
    "sg:phone":"+49 551/34034",
    "sg:postcode":"37081",
    "sg:province":"Niedersachsen",
    "wof:name":"City-taxi G\u00f6ttingen Taxibetriebs- Und Service Gmbh",
    "wof:placetype":"venue"
},
  "geometry": {"coordinates":[9.9230537415,51.5483665466],"type":"Point"}
}