{
  "type": "Feature",
  "properties": {
    "iso:country":"DE",
    "sg:address":"Rotkreuzstr. 5",
    "sg:city":"Bad Mergentheim",
    "sg:phone":"+49 7931/45855",
    "sg:postcode":"97980",
    "sg:province":"Baden-W\u00fcrttemberg",
    "wof:name":"T. Schmei\u00dfer",
    "wof:placetype":"venue"
},
  "geometry": {"coordinates":[9.7682609558,49.4897956848],"type":"Point"}
}