{
  "type": "Feature",
  "properties": {
    "iso:country":"DE",
    "sg:address":"Veringstr. 21",
    "sg:city":"Hamburg",
    "sg:phone":"+49 40/757125",
    "sg:postcode":"21107",
    "sg:province":"Hamburg",
    "wof:name":"Optiker Kranaster Gmbh",
    "wof:placetype":"venue"
},
  "geometry": {"coordinates":[9.9872169495,53.5164833069],"type":"Point"}
}