{
  "type": "Feature",
  "properties": {
    "iso:country":"DE",
    "sg:address":"Schlo\u00dfgartenstr. 15",
    "sg:city":"Bad M\u00fcnster-Ebernburg",
    "sg:phone":"+49 6708/2453",
    "sg:postcode":"55583",
    "sg:province":"Rheinland-Pfalz",
    "wof:name":"Nahe-alsenz-eck",
    "wof:placetype":"venue"
},
  "geometry": {"coordinates":[7.838453,49.809174],"type":"Point"}
}