{
  "type": "Feature",
  "properties": {
    "iso:country":"DE",
    "sg:address":"Altmarkt 2",
    "sg:city":"Schmalkalden",
    "sg:phone":"+49 3683/402742",
    "sg:postcode":"98574",
    "sg:province":"Th\u00fcringen",
    "wof:name":"Ratskeller",
    "wof:placetype":"venue"
},
  "geometry": {"coordinates":[10.4511575699,50.7213516235],"type":"Point"}
}