{
  "type": "Feature",
  "properties": {
    "iso:country":"DE",
    "sg:address":"Heedfelder Str. 51",
    "sg:city":"L\u00fcdenscheid",
    "sg:phone":"+49 2351/61114",
    "sg:postcode":"58509",
    "sg:province":"Nordrhein-Westfalen",
    "wof:name":"Thietmar Wolski",
    "wof:placetype":"venue"
},
  "geometry": {"coordinates":[7.6152739525,51.2257232666],"type":"Point"}
}