{
  "type": "Feature",
  "properties": {
    "iso:country":"DE",
    "sg:address":"Im Gartenfeld 10",
    "sg:city":"Dreis",
    "sg:phone":"+49 6578/98110",
    "sg:postcode":"54518",
    "sg:province":"Rheinland-Pfalz",
    "wof:name":"Friedrich Fensterbau Gmbh",
    "wof:placetype":"venue"
},
  "geometry": {"coordinates":[6.81891,49.940212],"type":"Point"}
}