{
  "type": "Feature",
  "properties": {
    "iso:country":"DE",
    "sg:address":"In Der Masch 21",
    "sg:city":"Herford",
    "sg:phone":"+49 7907/941685",
    "sg:postcode":"32049",
    "sg:province":"Nordrhein-Westfalen",
    "wof:name":"Hans-j\u00dcrgen G\u00c4rtling",
    "wof:placetype":"venue"
},
  "geometry": {"coordinates":[9.8296165466,49.1005058289],"type":"Point"}
}