{
  "type": "Feature",
  "properties": {
    "iso:country":"DE",
    "sg:address":"Lerchenweg 23",
    "sg:city":"Walheim",
    "sg:phone":"+49 7143/34117",
    "sg:postcode":"74399",
    "sg:province":"Baden-W\u00fcrttemberg",
    "wof:name":"Hilmar K. Klages Steuerberater Und",
    "wof:placetype":"venue"
},
  "geometry": {"coordinates":[9.1486558914,49.0112380981],"type":"Point"}
}