{
  "type": "Feature",
  "properties": {
    "iso:country":"DE",
    "sg:address":"Oberdiensdorf",
    "sg:city":"Hauzenberg",
    "sg:phone":"+49 8586/1033",
    "sg:postcode":"94051",
    "sg:province":"Bayern",
    "wof:name":"Gasthaus Stern",
    "wof:placetype":"venue"
},
  "geometry": {"coordinates":[13.6251316071,48.6493759155],"type":"Point"}
}