{
  "type": "Feature",
  "properties": {
    "iso:country":"DE",
    "sg:address":"Steinbergstr. 14",
    "sg:city":"Erfurt",
    "sg:phone":"+49 361/6439099",
    "sg:postcode":"99099",
    "sg:province":"Th\u00fcringen",
    "wof:name":"Phv-erfurt Assekurenzmakler Gmbh",
    "wof:placetype":"venue"
},
  "geometry": {"coordinates":[11.0757017136,50.9657325745],"type":"Point"}
}