{
  "type": "Feature",
  "properties": {
    "iso:country":"DE",
    "sg:address":"Dipbacher Str. 18",
    "sg:city":"Bergtheim",
    "sg:phone":"+49 9367/99250",
    "sg:postcode":"97241",
    "sg:province":"Bayern",
    "wof:name":"Hans Pr\u00f6tzel",
    "wof:placetype":"venue"
},
  "geometry": {"coordinates":[10.07636,49.897228],"type":"Point"}
}