{
  "type": "Feature",
  "properties": {
    "iso:country":"DE",
    "sg:address":"Nicolaistr. 7",
    "sg:city":"L\u00f6bau",
    "sg:phone":"+49 3585/401962",
    "sg:postcode":"02708",
    "sg:province":"Sachsen",
    "wof:name":"Kraatz Inh. Heinz Thomas",
    "wof:placetype":"venue"
},
  "geometry": {"coordinates":[14.6664628983,51.0960464478],"type":"Point"}
}