{
  "type": "Feature",
  "properties": {
    "iso:country":"DE",
    "sg:address":"Fischhausstr. 2",
    "sg:city":"Lauter",
    "sg:phone":"+49 3771/552011",
    "sg:postcode":"08312",
    "sg:province":"Sachsen",
    "wof:name":"Gerd Kubitschek Rechtsanwalt",
    "wof:placetype":"venue"
},
  "geometry": {"coordinates":[12.7444000244,50.5609855652],"type":"Point"}
}