{
  "type": "Feature",
  "properties": {
    "iso:country":"DE",
    "sg:address":"Winnender 43",
    "sg:city":"Affalterbach",
    "sg:phone":"+49 7144/38774",
    "sg:postcode":"71563",
    "sg:province":"Baden-W\u00fcrttemberg",
    "wof:name":"Wollwaescherei",
    "wof:placetype":"venue"
},
  "geometry": {"coordinates":[9.328593,48.922455],"type":"Point"}
}