{
  "type": "Feature",
  "properties": {
    "iso:country":"DE",
    "sg:address":"Hude 6",
    "sg:city":"Bad Oldesloe",
    "sg:phone":"+49 4531/5208",
    "sg:postcode":"23843",
    "sg:province":"Schleswig-Holstein",
    "wof:name":"Ln Und Hapag-lloyd Reiseb\u00fcro Gmbh",
    "wof:placetype":"venue"
},
  "geometry": {"coordinates":[10.3766326904,53.8091697693],"type":"Point"}
}