{
  "type": "Feature",
  "properties": {
    "iso:country":"DE",
    "sg:address":"Rottweiler Str. 12",
    "sg:city":"Villingendorf",
    "sg:phone":"+49 741/34232",
    "sg:postcode":"78667",
    "sg:province":"Baden-W\u00fcrttemberg",
    "wof:name":"Dieter Und Gabi Kr\u00fcger Massage- Und",
    "wof:placetype":"venue"
},
  "geometry": {"coordinates":[8.590814,48.201202],"type":"Point"}
}