{
  "type": "Feature",
  "properties": {
    "iso:country":"DE",
    "sg:address":"Tannenbergstr. 34",
    "sg:city":"Remscheid",
    "sg:phone":"+49 2191/590831",
    "sg:postcode":"42899",
    "sg:province":"Nordrhein-Westfalen",
    "wof:name":"C. Und H. -w. Bauss Ingenieure",
    "wof:placetype":"venue"
},
  "geometry": {"coordinates":[7.2336821556,51.2107963562],"type":"Point"}
}