{
  "type": "Feature",
  "properties": {
    "iso:country":"DE",
    "sg:address":"B\u00f6ckersstr. 24",
    "sg:city":"Rietberg",
    "sg:phone":"+49 5244/10509",
    "sg:postcode":"33397",
    "sg:province":"Nordrhein-Westfalen",
    "wof:name":"Fachwerkstatt Dr\u00fccker & Schnitger Gmbh",
    "wof:placetype":"venue"
},
  "geometry": {"coordinates":[8.4375400543,51.8203697205],"type":"Point"}
}