{
  "type": "Feature",
  "properties": {
    "iso:country":"DE",
    "sg:address":"Capeller Str. 150",
    "sg:city":"Werne",
    "sg:phone":"+49 2389/79700",
    "sg:postcode":"59368",
    "sg:province":"Nordrhein-Westfalen",
    "wof:name":"Icopal Holding Deutschland Gmbh",
    "wof:placetype":"venue"
},
  "geometry": {"coordinates":[7.620925,51.682114],"type":"Point"}
}