{
  "type": "Feature",
  "properties": {
    "iso:country":"DE",
    "sg:address":"Hintergasse 1",
    "sg:city":"Walluf",
    "sg:phone":"+49 6123/72312",
    "sg:postcode":"65396",
    "sg:province":"Hessen",
    "wof:name":"Klerner Erben Inh. Ullrich Bertel",
    "wof:placetype":"venue"
},
  "geometry": {"coordinates":[8.1611537933,50.0346031189],"type":"Point"}
}