{
  "type": "Feature",
  "properties": {
    "iso:country":"DE",
    "sg:address":"Glemsgaustr. 14",
    "sg:city":"Stuttgart",
    "sg:phone":"+49 711/8873270",
    "sg:postcode":"70499",
    "sg:province":"Baden-W\u00fcrttemberg",
    "wof:name":"Robert Sauter",
    "wof:placetype":"venue"
},
  "geometry": {"coordinates":[9.1115589142,48.8151473999],"type":"Point"}
}