{
  "type": "Feature",
  "properties": {
    "iso:country":"DE",
    "sg:address":"Kieler Str. 44",
    "sg:city":"Eckernf\u00f6rde",
    "sg:phone":"+49 4351/2190",
    "sg:postcode":"24340",
    "sg:province":"Schleswig-Holstein",
    "wof:name":"Ihr Platz Drogeriemarkt",
    "wof:placetype":"venue"
},
  "geometry": {"coordinates":[9.836997,54.470451],"type":"Point"}
}