{
  "type": "Feature",
  "properties": {
    "iso:country":"DE",
    "sg:address":"Gewerbepark BWB 13",
    "sg:city":"Bruckm\u00fchl",
    "sg:phone":"+49 8062/708940",
    "sg:postcode":"83052",
    "sg:province":"Bayern",
    "wof:name":"Endo Produktionsges. F\u00fcr Medical- Und",
    "wof:placetype":"venue"
},
  "geometry": {"coordinates":[11.9338626862,47.876537323],"type":"Point"}
}