{
  "type": "Feature",
  "properties": {
    "iso:country":"DE",
    "sg:address":"Am Siebenstein 2",
    "sg:city":"Dreieich",
    "sg:phone":"+49 6103/62061",
    "sg:postcode":"63303",
    "sg:province":"Hessen",
    "wof:name":"Scharpf Alarmsysteme Gmbh",
    "wof:placetype":"venue"
},
  "geometry": {"coordinates":[8.659935,50.019016],"type":"Point"}
}