{
  "type": "Feature",
  "properties": {
    "iso:country":"DE",
    "sg:address":"Rathausplatz 1",
    "sg:city":"Landau",
    "sg:postcode":"76829",
    "sg:province":"Rheinland-Pfalz",
    "wof:name":"Landauer Entsorgungsbetriebe Gmbh",
    "wof:placetype":"venue"
},
  "geometry": {"coordinates":[8.11231,49.198689],"type":"Point"}
}