{
  "type": "Feature",
  "properties": {
    "iso:country":"DE",
    "sg:address":"Hauptstr. 15",
    "sg:city":"Ortenberg",
    "sg:phone":"+49 781/9483640",
    "sg:postcode":"77799",
    "sg:province":"Baden-W\u00fcrttemberg",
    "wof:name":"H. W\u00f6hrle",
    "wof:placetype":"venue"
},
  "geometry": {"coordinates":[7.9696969986,48.4453315735],"type":"Point"}
}