{
  "type": "Feature",
  "properties": {
    "iso:country":"DE",
    "sg:address":"Kegelstr. 34",
    "sg:city":"Duisburg",
    "sg:phone":"+49 203/782352",
    "sg:postcode":"47259",
    "sg:province":"Nordrhein-Westfalen",
    "wof:name":"Johannes Lachnitt",
    "wof:placetype":"venue"
},
  "geometry": {"coordinates":[6.6811389923,51.3558425903],"type":"Point"}
}