{
  "type": "Feature",
  "properties": {
    "iso:country":"DE",
    "sg:address":"Postfach 100665:: 93042 Regensburg:: Germany.^^Dr Theobald Schrems Str 3::",
    "sg:city":"Regensburg",
    "sg:phone":"+49 941/40950",
    "sg:postcode":"93055",
    "sg:province":"Bayern",
    "wof:name":"Liga Bank Eg Regensburg",
    "wof:placetype":"venue"
},
  "geometry": {"coordinates":[12.142273,48.987244],"type":"Point"}
}