{
  "type": "Feature",
  "properties": {
    "iso:country":"DE",
    "sg:address":"Auf dem Sandhof 9",
    "sg:city":"Limbach",
    "sg:phone":"+49 6757/393",
    "sg:postcode":"55606",
    "sg:province":"Rheinland-Pfalz",
    "wof:name":"Adolf Herrmann",
    "wof:placetype":"venue"
},
  "geometry": {"coordinates":[7.544901,49.742672],"type":"Point"}
}