{
  "type": "Feature",
  "properties": {
    "iso:country":"DE",
    "sg:address":"Leipziger Str. 44a",
    "sg:city":"Chemnitz",
    "sg:phone":"+49 3722/502784",
    "sg:postcode":"09113",
    "sg:province":"Sachsen",
    "wof:name":"Mode Art Gmbh",
    "wof:placetype":"venue"
},
  "geometry": {"coordinates":[12.9064941406,50.8415527344],"type":"Point"}
}