{
  "type": "Feature",
  "properties": {
    "iso:country":"DE",
    "sg:address":"Sommerauer Str. 4",
    "sg:city":"Feuchtwangen",
    "sg:phone":"+49 4960/3171730",
    "sg:postcode":"91555",
    "sg:province":"Bayern",
    "wof:name":"Wetterauer Druckerei Und Verlag",
    "wof:placetype":"venue"
},
  "geometry": {"coordinates":[8.7699947357,50.3308372498],"type":"Point"}
}