{
  "type": "Feature",
  "properties": {
    "iso:country":"DE",
    "sg:address":"Rohrbachstr. 19",
    "sg:city":"Frankfurt",
    "sg:postcode":"60389",
    "sg:province":"Hessen",
    "wof:name":"Jutta Fink Gmbh",
    "wof:placetype":"venue"
},
  "geometry": {"coordinates":[8.697825,50.128319],"type":"Point"}
}