{
  "type": "Feature",
  "properties": {
    "iso:country":"DE",
    "sg:address":"Scheideweg 27",
    "sg:city":"Oldenburg",
    "sg:phone":"+49 441/980680",
    "sg:postcode":"26121",
    "sg:province":"Niedersachsen",
    "wof:name":"Prull-druck Gmbh & Co. Kg",
    "wof:placetype":"venue"
},
  "geometry": {"coordinates":[8.219836,53.161182],"type":"Point"}
}