{
  "type": "Feature",
  "properties": {
    "iso:country":"DE",
    "sg:address":"Dachauer Str. 10 a",
    "sg:city":"Erdweg",
    "sg:postcode":"85253",
    "sg:province":"Bayern",
    "wof:name":"D-q-b Donau-quarz Baustoff- Handels- Gmbh",
    "wof:placetype":"venue"
},
  "geometry": {"coordinates":[11.3161211014,48.3208389282],"type":"Point"}
}