{
  "type": "Feature",
  "properties": {
    "iso:country":"DE",
    "sg:address":"Weiherstr. 25",
    "sg:city":"Hochheim",
    "sg:phone":"+49 6146/3377",
    "sg:postcode":"65239",
    "sg:province":"Hessen",
    "wof:name":"Paracelsus-apotheke",
    "wof:placetype":"venue"
},
  "geometry": {"coordinates":[8.352307,50.013294],"type":"Point"}
}