{
  "type": "Feature",
  "properties": {
    "iso:country":"DE",
    "sg:address":"Walkersaich 39",
    "sg:city":"Schwindegg",
    "sg:phone":"+49 8092/946479",
    "sg:postcode":"84419",
    "sg:province":"Bayern",
    "wof:name":"Ulrich Niemeier",
    "wof:placetype":"venue"
},
  "geometry": {"coordinates":[12.3038492203,48.2779884338],"type":"Point"}
}