{
  "type": "Feature",
  "properties": {
    "iso:country":"DE",
    "sg:address":"Seegefelder Str. 60",
    "sg:city":"Berlin",
    "sg:phone":"+49 30/3332690",
    "sg:postcode":"13583",
    "sg:province":"Berlin",
    "wof:name":"West-apotheke",
    "wof:placetype":"venue"
},
  "geometry": {"coordinates":[13.188648,52.537365],"type":"Point"}
}