{
  "type": "Feature",
  "properties": {
    "iso:country":"DE",
    "sg:address":"Langgasse 37",
    "sg:city":"Nordheim",
    "sg:phone":"+49 9381/1436",
    "sg:postcode":"97334",
    "sg:province":"Bayern",
    "wof:name":"Felix Braun Weinanbau",
    "wof:placetype":"venue"
},
  "geometry": {"coordinates":[10.1814203262,49.8581314087],"type":"Point"}
}