{
  "type": "Feature",
  "properties": {
    "iso:country":"DE",
    "sg:address":"Friedrich-Engels-Allee 216",
    "sg:city":"Wuppertal",
    "sg:phone":"+49 202/84848",
    "sg:postcode":"42285",
    "sg:province":"Nordrhein-Westfalen",
    "wof:name":"Rolf Lange Rechtsanwalt",
    "wof:placetype":"venue"
},
  "geometry": {"coordinates":[7.1757040024,51.2623443604],"type":"Point"}
}