{
  "type": "Feature",
  "properties": {
    "iso:country":"DE",
    "sg:address":"Albert-Ludwig-Grimm-Str. 16 /2",
    "sg:city":"Weinheim",
    "sg:phone":"+49 6201/64285",
    "sg:postcode":"69469",
    "sg:province":"Baden-W\u00fcrttemberg",
    "wof:name":"Dr. P. Thomsen Rechtsanwalt",
    "wof:placetype":"venue"
},
  "geometry": {"coordinates":[8.6680040359,49.5474395752],"type":"Point"}
}