{
  "type": "Feature",
  "properties": {
    "iso:country":"DE",
    "sg:address":"Plutostr. 85",
    "sg:city":"Herne",
    "sg:phone":"+49 2325/60153",
    "sg:postcode":"44651",
    "sg:province":"Nordrhein-Westfalen",
    "wof:name":"Thessaloniki",
    "wof:placetype":"venue"
},
  "geometry": {"coordinates":[7.1588749886,51.5167121887],"type":"Point"}
}