{
  "type": "Feature",
  "properties": {
    "iso:country":"DE",
    "sg:address":"Hans-B\u00f6heim-Str. 4",
    "sg:city":"Dresden",
    "sg:postcode":"01309",
    "sg:province":"Sachsen",
    "wof:name":"Registra Geb\u00e4udedienste Gmbh",
    "wof:placetype":"venue"
},
  "geometry": {"coordinates":[13.776283,51.045975],"type":"Point"}
}