{
  "type": "Feature",
  "properties": {
    "iso:country":"DE",
    "sg:address":"Darmst\u00e4dter Str. 20",
    "sg:city":"Hanau",
    "sg:phone":"+49 6181/65322",
    "sg:postcode":"63456",
    "sg:province":"Hessen",
    "wof:name":"Pizzeria Turnerschaft 1874",
    "wof:placetype":"venue"
},
  "geometry": {"coordinates":[8.9059495926,50.1040306091],"type":"Point"}
}