{
  "type": "Feature",
  "properties": {
    "iso:country":"DE",
    "sg:address":"Rothsal 2",
    "sg:city":"Roding",
    "sg:phone":"+49 9465/382",
    "sg:postcode":"93426",
    "sg:province":"Bayern",
    "wof:name":"P. Griesbeck",
    "wof:placetype":"venue"
},
  "geometry": {"coordinates":[12.4286832809,49.2661132812],"type":"Point"}
}