{
  "type": "Feature",
  "properties": {
    "iso:country":"DE",
    "sg:address":"Unter Taschenmacher 10",
    "sg:city":"K\u00f6ln",
    "sg:phone":"+49 221/9259670",
    "sg:postcode":"50667",
    "sg:province":"Nordrhein-Westfalen",
    "wof:name":"Usit Connections Gmbh",
    "wof:placetype":"venue"
},
  "geometry": {"coordinates":[6.9596710205,50.9394493103],"type":"Point"}
}