{
  "type": "Feature",
  "properties": {
    "iso:country":"DE",
    "sg:address":"W\u00fclfingstr. 6",
    "sg:city":"Radevormwald",
    "sg:phone":"+49 2191/666945",
    "sg:postcode":"42477",
    "sg:province":"Nordrhein-Westfalen",
    "wof:name":"Dahlerauer Effektzwirn Gmbh",
    "wof:placetype":"venue"
},
  "geometry": {"coordinates":[7.312055,51.220776],"type":"Point"}
}