{
  "type": "Feature",
  "properties": {
    "iso:country":"DE",
    "sg:address":"Zahnrad 2",
    "sg:city":"Essen",
    "sg:phone":"+49 201/407957",
    "sg:postcode":"45239",
    "sg:province":"Nordrhein-Westfalen",
    "wof:name":"Michael Schmitz Architekt",
    "wof:placetype":"venue"
},
  "geometry": {"coordinates":[7.021495,51.386379],"type":"Point"}
}