{
  "type": "Feature",
  "properties": {
    "iso:country":"DE",
    "sg:address":"Frankenstr. 3",
    "sg:city":"Herford",
    "sg:phone":"+49 5221/51882",
    "sg:postcode":"32052",
    "sg:province":"Nordrhein-Westfalen",
    "wof:name":"H\u00f6cker Polytechnik Gmbh",
    "wof:placetype":"venue"
},
  "geometry": {"coordinates":[8.6776180267,52.1105537415],"type":"Point"}
}