{
  "type": "Feature",
  "properties": {
    "iso:country":"DE",
    "sg:address":"Neum\u00fchle 1",
    "sg:city":"Schwieberdingen",
    "sg:phone":"+49 7150/31247",
    "sg:postcode":"71701",
    "sg:province":"Baden-W\u00fcrttemberg",
    "wof:name":"Thomas Cantz",
    "wof:placetype":"venue"
},
  "geometry": {"coordinates":[9.0670585632,48.8848457336],"type":"Point"}
}