{
  "type": "Feature",
  "properties": {
    "iso:country":"DE",
    "sg:address":"Parkstr. 4",
    "sg:city":"M\u00f6rfelden-Walldorf",
    "sg:phone":"+49 6105/278280",
    "sg:postcode":"64546",
    "sg:province":"Hessen",
    "wof:name":"F. H. W. Winkler Gmbh",
    "wof:placetype":"venue"
},
  "geometry": {"coordinates":[8.564498,49.973202],"type":"Point"}
}