{
  "type": "Feature",
  "properties": {
    "iso:country":"DE",
    "sg:address":"M\u00e4scher Weg 1",
    "sg:city":"Bad Iburg",
    "sg:phone":"+49 5403/2433",
    "sg:postcode":"49186",
    "sg:province":"Niedersachsen",
    "wof:name":"Heinz Tepe",
    "wof:placetype":"venue"
},
  "geometry": {"coordinates":[8.0283517838,52.1640472412],"type":"Point"}
}