{
  "type": "Feature",
  "properties": {
    "iso:country":"DE",
    "sg:address":"Hochstr. 21",
    "sg:city":"Bochum",
    "sg:postcode":"44866",
    "sg:province":"Nordrhein-Westfalen",
    "wof:name":"Gw Druck Gmbh",
    "wof:placetype":"venue"
},
  "geometry": {"coordinates":[7.1398410797,51.4802360535],"type":"Point"}
}