{
  "type": "Feature",
  "properties": {
    "iso:country":"DE",
    "sg:address":"Rheinbabenallee 29",
    "sg:city":"Berlin",
    "sg:postcode":"14199",
    "sg:province":"Berlin",
    "wof:name":"Stefan Stift Gmbh",
    "wof:placetype":"venue"
},
  "geometry": {"coordinates":[13.285493,52.473118],"type":"Point"}
}