{
  "type": "Feature",
  "properties": {
    "iso:country":"DE",
    "sg:address":"Regensburger Str. 10",
    "sg:city":"W\u00f6rth",
    "sg:phone":"+49 9482/2948",
    "sg:postcode":"93086",
    "sg:province":"Bayern",
    "wof:name":"Bestattungen Piet\u00e4t",
    "wof:placetype":"venue"
},
  "geometry": {"coordinates":[12.398587,48.999928],"type":"Point"}
}