{
  "type": "Feature",
  "properties": {
    "iso:country":"DE",
    "sg:address":"Havelstr. 18",
    "sg:city":"Berlin",
    "sg:postcode":"13597",
    "sg:province":"Berlin",
    "wof:name":"Sch\u00f6nnagel Handelsges. Mbh",
    "wof:placetype":"venue"
},
  "geometry": {"coordinates":[13.2059679031,52.5386695862],"type":"Point"}
}