{
  "type": "Feature",
  "properties": {
    "iso:country":"DE",
    "sg:address":"Ludowicistr. 30",
    "sg:city":"Ludwigshafen",
    "sg:phone":"+49 6237/6415",
    "sg:postcode":"67071",
    "sg:province":"Rheinland-Pfalz",
    "wof:name":"Werner P\u00f6sel",
    "wof:placetype":"venue"
},
  "geometry": {"coordinates":[8.3257446289,49.4762382507],"type":"Point"}
}