{
  "type": "Feature",
  "properties": {
    "iso:country":"DE",
    "sg:address":"Fr\u00fchlingstr. 3",
    "sg:city":"Traunstein",
    "sg:postcode":"83278",
    "sg:province":"Bayern",
    "wof:name":"Emco Maier Gmbh",
    "wof:placetype":"venue"
},
  "geometry": {"coordinates":[12.64223,47.872265],"type":"Point"}
}