{
  "type": "Feature",
  "properties": {
    "iso:country":"DE",
    "sg:address":"Im Saun 19",
    "sg:city":"Herbrechtingen",
    "sg:phone":"+49 7324/2021",
    "sg:postcode":"89542",
    "sg:province":"Baden-W\u00fcrttemberg",
    "wof:name":"Ernst Wirth",
    "wof:placetype":"venue"
},
  "geometry": {"coordinates":[10.1827421188,48.6237564087],"type":"Point"}
}