{
  "type": "Feature",
  "properties": {
    "iso:country":"DE",
    "sg:address":"Molkereistr. 8",
    "sg:city":"Elster",
    "sg:phone":"+49 35383/20308",
    "sg:postcode":"06918",
    "sg:province":"Sachsen-Anhalt",
    "wof:name":"Anker Apotheke Britta Hoffmann",
    "wof:placetype":"venue"
},
  "geometry": {"coordinates":[12.824354,51.830402],"type":"Point"}
}