{
  "type": "Feature",
  "properties": {
    "iso:country":"DE",
    "sg:address":"Tal 8a",
    "sg:city":"Durbach",
    "sg:phone":"+49 781/9482173",
    "sg:postcode":"77770",
    "sg:province":"Baden-W\u00fcrttemberg",
    "wof:name":"Krieger Gmbh",
    "wof:placetype":"venue"
},
  "geometry": {"coordinates":[8.017172,48.493942],"type":"Point"}
}