{
  "type": "Feature",
  "properties": {
    "iso:country":"DE",
    "sg:address":"Heidelberger Str. 19",
    "sg:city":"Oranienburg",
    "sg:phone":"+49 3301/526691",
    "sg:postcode":"16515",
    "sg:province":"Brandenburg",
    "wof:name":"Christa Kirchhoff",
    "wof:placetype":"venue"
},
  "geometry": {"coordinates":[13.258266,52.756561],"type":"Point"}
}