{
  "type": "Feature",
  "properties": {
    "iso:country":"DE",
    "sg:address":"Hedwigstr. 9",
    "sg:city":"Kassel",
    "sg:phone":"+49 561/7075510",
    "sg:postcode":"34117",
    "sg:province":"Hessen",
    "wof:name":"Neckermann Reiseb\u00fcro",
    "wof:placetype":"venue"
},
  "geometry": {"coordinates":[9.4997930527,51.3170471191],"type":"Point"}
}