{
  "type": "Feature",
  "properties": {
    "iso:country":"DE",
    "sg:address":"Am Burghof 2",
    "sg:city":"M\u00fclverstedt",
    "sg:phone":"+49 36022/90791",
    "sg:postcode":"99947",
    "sg:province":"Th\u00fcringen",
    "wof:name":"Deutsche Verm\u00f6gensberatung Ag",
    "wof:placetype":"venue"
},
  "geometry": {"coordinates":[10.5066480637,51.1193122864],"type":"Point"}
}