{
  "type": "Feature",
  "properties": {
    "iso:country":"DE",
    "sg:address":"Polthierstr. 29",
    "sg:city":"Wittstock",
    "sg:postcode":"16909",
    "sg:province":"Brandenburg",
    "wof:name":"Schacht & Otto Ohg",
    "wof:placetype":"venue"
},
  "geometry": {"coordinates":[12.479525,53.153278],"type":"Point"}
}