{
  "type": "Feature",
  "properties": {
    "iso:country":"DE",
    "sg:address":"Lohkoppel 35",
    "sg:city":"Winsen",
    "sg:phone":"+49 4171/780205",
    "sg:postcode":"21423",
    "sg:province":"Niedersachsen",
    "wof:name":"Burghard H. Quast Versicherungsmakler Gmbh",
    "wof:placetype":"venue"
},
  "geometry": {"coordinates":[10.2413759232,53.3460197449],"type":"Point"}
}