{
  "type": "Feature",
  "properties": {
    "iso:country":"DE",
    "sg:address":"Brembach 4",
    "sg:city":"Gersfeld",
    "sg:phone":"+49 6654/7064",
    "sg:postcode":"36129",
    "sg:province":"Hessen",
    "wof:name":"Ernst Richter",
    "wof:placetype":"venue"
},
  "geometry": {"coordinates":[9.920609,50.461803],"type":"Point"}
}