{
  "type": "Feature",
  "properties": {
    "iso:country":"DE",
    "sg:address":"Spindelstr. 71 B",
    "sg:city":"Bielefeld",
    "sg:phone":"+49 521/299060",
    "sg:postcode":"33604",
    "sg:province":"Nordrhein-Westfalen",
    "wof:name":"Gehring Beteiligungs Gmbh",
    "wof:placetype":"venue"
},
  "geometry": {"coordinates":[8.554859,52.016773],"type":"Point"}
}