{
  "type": "Feature",
  "properties": {
    "iso:country":"DE",
    "sg:address":"Westendorf 34",
    "sg:city":"Sch\u00f6ningen",
    "sg:phone":"+49 5352/2216",
    "sg:postcode":"38364",
    "sg:province":"Niedersachsen",
    "wof:name":"Joachim Horn",
    "wof:placetype":"venue"
},
  "geometry": {"coordinates":[10.963814,52.139297],"type":"Point"}
}