{
  "type": "Feature",
  "properties": {
    "iso:country":"DE",
    "sg:address":"Siemensstr. 14",
    "sg:city":"Hildesheim",
    "sg:phone":"+49 5121/78130",
    "sg:postcode":"31135",
    "sg:province":"Niedersachsen",
    "wof:name":"Teppichland W. Heineking",
    "wof:placetype":"venue"
},
  "geometry": {"coordinates":[9.9709310532,52.1627426147],"type":"Point"}
}