{
  "type": "Feature",
  "properties": {
    "iso:country":"DE",
    "sg:address":"Mathildenstr. 9",
    "sg:city":"Hallbergmoos",
    "sg:postcode":"85399",
    "sg:province":"Bayern",
    "wof:name":"Malereibetrieb Robert Gr\u00fcnwald, Landkreis Freising, M\u00fcnchen",
    "wof:placetype":"venue"
},
  "geometry": {"coordinates":[11.7526512146,48.3236656189],"type":"Point"}
}