{
  "type": "Feature",
  "properties": {
    "iso:country":"DE",
    "sg:address":"Gro\u00dffeld 4",
    "sg:city":"Wermelskirchen",
    "sg:phone":"+49 2193/963",
    "sg:postcode":"42929",
    "sg:province":"Nordrhein-Westfalen",
    "wof:name":"Imc Maschinen Vertriebsgesellschaft Mbh",
    "wof:placetype":"venue"
},
  "geometry": {"coordinates":[7.20179,51.094425],"type":"Point"}
}