{
  "type": "Feature",
  "properties": {
    "iso:country":"DE",
    "sg:address":"Sandstr. 5",
    "sg:city":"Wittenberge",
    "sg:phone":"+49 3877/403993",
    "sg:postcode":"19322",
    "sg:province":"Brandenburg",
    "wof:name":"G\u00fcnter Katzur",
    "wof:placetype":"venue"
},
  "geometry": {"coordinates":[11.7542963028,52.9922676086],"type":"Point"}
}