{
  "type": "Feature",
  "properties": {
    "iso:country":"DE",
    "sg:address":"Burgstallstr. 10",
    "sg:city":"Adelsheim",
    "sg:phone":"+49 6291/1476",
    "sg:postcode":"74740",
    "sg:province":"Baden-W\u00fcrttemberg",
    "wof:name":"Gastst\u00e4tte Sportheim",
    "wof:placetype":"venue"
},
  "geometry": {"coordinates":[9.3865823746,49.3825492859],"type":"Point"}
}