{
  "type": "Feature",
  "properties": {
    "iso:country":"DE",
    "sg:address":"Sandgasse 13",
    "sg:city":"Hanau",
    "sg:phone":"+49 6181/55613",
    "sg:postcode":"63457",
    "sg:province":"Hessen",
    "wof:name":"Roberts Bike-shop",
    "wof:placetype":"venue"
},
  "geometry": {"coordinates":[8.947133,50.102558],"type":"Point"}
}