{
  "type": "Feature",
  "properties": {
    "iso:country":"DE",
    "sg:address":"K\u00f6nigstr. 35",
    "sg:city":"Rottweil",
    "sg:phone":"+49 741/13890",
    "sg:postcode":"78628",
    "sg:province":"Baden-W\u00fcrttemberg",
    "wof:name":"Med-bett D. Schwalb",
    "wof:placetype":"venue"
},
  "geometry": {"coordinates":[8.6314077377,48.1624145508],"type":"Point"}
}