{
  "type": "Feature",
  "properties": {
    "iso:country":"DE",
    "sg:address":"Marienplatz 3",
    "sg:city":"M\u00fcnchen",
    "sg:phone":"+49 89/294770",
    "sg:postcode":"80331",
    "sg:province":"Bayern",
    "wof:name":"Redaktion Naturamed",
    "wof:placetype":"venue"
},
  "geometry": {"coordinates":[11.5748567581,48.1374778748],"type":"Point"}
}