{
  "type": "Feature",
  "properties": {
    "iso:country":"DE",
    "sg:address":"Marktstr. 15",
    "sg:city":"Neuenb\u00fcrg",
    "sg:phone":"+49 7082/50730",
    "sg:postcode":"75305",
    "sg:province":"Baden-W\u00fcrttemberg",
    "wof:name":"Rall",
    "wof:placetype":"venue"
},
  "geometry": {"coordinates":[8.5887975693,48.8459434509],"type":"Point"}
}