{
  "type": "Feature",
  "properties": {
    "iso:country":"DE",
    "sg:address":"Kapellenstr. 41",
    "sg:city":"Meerbusch",
    "sg:phone":"+49 2159/2417",
    "sg:postcode":"40670",
    "sg:province":"Nordrhein-Westfalen",
    "wof:name":"Marmor May Gmbh",
    "wof:placetype":"venue"
},
  "geometry": {"coordinates":[6.6239900589,51.2751426697],"type":"Point"}
}