{
  "type": "Feature",
  "properties": {
    "iso:country":"DE",
    "sg:address":"C/San Antonio 18",
    "sg:city":"Marbella",
    "sg:phone":"+49 34952/868769",
    "sg:postcode":"29600",
    "wof:name":"Ross Peluquer\u00eda - Marbella - Malaga - Spain",
    "wof:placetype":"venue"
},
  "geometry": {"coordinates":[-4.881745,36.512886],"type":"Point"}
}