{
  "type": "Feature",
  "properties": {
    "iso:country":"DE",
    "sg:address":"Seilerstr. 6",
    "sg:city":"M\u00fclheim",
    "sg:postcode":"45473",
    "sg:province":"Nordrhein-Westfalen",
    "wof:name":"Teppichhof Nadine Trei\u00df",
    "wof:placetype":"venue"
},
  "geometry": {"coordinates":[6.8816962242,51.4365844727],"type":"Point"}
}