{
  "type": "Feature",
  "properties": {
    "iso:country":"DE",
    "sg:address":"Marchioninistr. 15",
    "sg:city":"M\u00fcnchen",
    "sg:phone":"+49 89/70954587",
    "sg:postcode":"81377",
    "sg:province":"Bayern",
    "wof:name":"Institut F\u00fcr An\u00e4sthesiologie Der Ludw.-maxim.-universit\u00e4t",
    "wof:placetype":"venue"
},
  "geometry": {"coordinates":[11.4751167297,48.1118965149],"type":"Point"}
}