{
  "type": "Feature",
  "properties": {
    "iso:country":"DE",
    "sg:address":"Rigipsstr. 6",
    "sg:city":"Herrenberg",
    "sg:phone":"+49 7032/75339",
    "sg:postcode":"71083",
    "sg:province":"Baden-W\u00fcrttemberg",
    "wof:name":"Bistro Paradise",
    "wof:placetype":"venue"
},
  "geometry": {"coordinates":[8.8859081268,48.576625824],"type":"Point"}
}