{
  "type": "Feature",
  "properties": {
    "iso:country":"DE",
    "sg:address":"K\u00f6nigsforster Str. 10",
    "sg:city":"R\u00f6srath",
    "sg:phone":"+49 2205/2644",
    "sg:postcode":"51503",
    "sg:province":"Nordrhein-Westfalen",
    "wof:name":"P. Karla Finanzberater",
    "wof:placetype":"venue"
},
  "geometry": {"coordinates":[7.1744937897,50.9265327454],"type":"Point"}
}