{
  "type": "Feature",
  "properties": {
    "iso:country":"DE",
    "sg:address":"H\u00f6henweg 19",
    "sg:city":"Niederhofen",
    "sg:phone":"+49 2684/5133",
    "sg:postcode":"56316",
    "sg:province":"Rheinland-Pfalz",
    "wof:name":"Bernhard Heck",
    "wof:placetype":"venue"
},
  "geometry": {"coordinates":[7.6068768501,50.5598373413],"type":"Point"}
}