{
  "type": "Feature",
  "properties": {
    "iso:country":"DE",
    "sg:address":"N\u00fcrnberger Str. 234",
    "sg:city":"Regensburg",
    "sg:phone":"+49 941/892103",
    "sg:postcode":"93059",
    "sg:province":"Bayern",
    "wof:name":"Gerhard Reichert Sabine Reichert",
    "wof:placetype":"venue"
},
  "geometry": {"coordinates":[12.0633525848,49.0329856873],"type":"Point"}
}