{
  "type": "Feature",
  "properties": {
    "iso:country":"DE",
    "sg:address":"Niendorfer Str. 4",
    "sg:city":"Burg",
    "sg:postcode":"23769",
    "sg:province":"Schleswig-Holstein",
    "wof:name":"Schuhhaus Herta Wilken",
    "wof:placetype":"venue"
},
  "geometry": {"coordinates":[11.1970186234,54.4404067993],"type":"Point"}
}