{
  "type": "Feature",
  "properties": {
    "iso:country":"DE",
    "sg:address":"Ahmser Str. 1",
    "sg:city":"Herford",
    "sg:postcode":"32052",
    "sg:province":"Nordrhein-Westfalen",
    "wof:name":"Andr\u00e8 Przybilla E. K.",
    "wof:placetype":"venue"
},
  "geometry": {"coordinates":[8.6741533279,52.1109275818],"type":"Point"}
}