{
  "type": "Feature",
  "properties": {
    "iso:country":"DE",
    "sg:address":"Hauptstr. 150",
    "sg:city":"Lohmar",
    "sg:phone":"+49 2246/120",
    "sg:postcode":"53797",
    "sg:province":"Nordrhein-Westfalen",
    "wof:name":"Walterscheid Rohrver- Bindungstechnik Gmbh",
    "wof:placetype":"venue"
},
  "geometry": {"coordinates":[7.2055301666,50.8313446045],"type":"Point"}
}