{
  "type": "Feature",
  "properties": {
    "iso:country":"DE",
    "sg:address":"Marktplatz 5",
    "sg:city":"Altenberge",
    "sg:phone":"+49 2505/949424",
    "sg:postcode":"48341",
    "sg:province":"Nordrhein-Westfalen",
    "wof:name":"Die Olive",
    "wof:placetype":"venue"
},
  "geometry": {"coordinates":[7.4691200256,52.0456161499],"type":"Point"}
}