{
  "type": "Feature",
  "properties": {
    "iso:country":"DE",
    "sg:address":"Geschwisterstr. 3",
    "sg:city":"Herten",
    "sg:phone":"+49 209/3594161",
    "sg:postcode":"45701",
    "sg:province":"Nordrhein-Westfalen",
    "wof:name":"Exclusiv-reisen Krause & Ceylan Ohg",
    "wof:placetype":"venue"
},
  "geometry": {"coordinates":[7.0849270821,51.6055030823],"type":"Point"}
}