{
  "type": "Feature",
  "properties": {
    "iso:country":"DE",
    "sg:address":"Wolfhartsgasse 1",
    "sg:city":"W\u00fcrzburg",
    "sg:phone":"+49 931/50016",
    "sg:postcode":"97070",
    "sg:province":"Bayern",
    "wof:name":"Ru\u00df",
    "wof:placetype":"venue"
},
  "geometry": {"coordinates":[9.9289388657,49.7926139832],"type":"Point"}
}