{
  "type": "Feature",
  "properties": {
    "iso:country":"DE",
    "sg:address":"Lerchenweg 11",
    "sg:city":"Asperg",
    "sg:phone":"+49 7141/661801",
    "sg:postcode":"71679",
    "sg:province":"Baden-W\u00fcrttemberg",
    "wof:name":"Willi Bufe",
    "wof:placetype":"venue"
},
  "geometry": {"coordinates":[9.1445436478,48.9038734436],"type":"Point"}
}