{
  "type": "Feature",
  "properties": {
    "iso:country":"DE",
    "sg:address":"Sigmund-Stammler-Str. 1",
    "sg:city":"Wei\u00dfenhorn",
    "sg:phone":"+49 7306/6286",
    "sg:postcode":"89264",
    "sg:province":"Bayern",
    "wof:name":"W. Blum Gmbh",
    "wof:placetype":"venue"
},
  "geometry": {"coordinates":[10.124921,48.270775],"type":"Point"}
}