{
  "type": "Feature",
  "properties": {
    "iso:country":"DE",
    "sg:address":"Breite Str. 42",
    "sg:city":"Karlsruhe",
    "sg:phone":"+49 721/31326",
    "sg:postcode":"76135",
    "sg:province":"Baden-W\u00fcrttemberg",
    "wof:name":"Zelch-haus Baubetreuungs Gmbh",
    "wof:placetype":"venue"
},
  "geometry": {"coordinates":[8.3904743195,48.9914855957],"type":"Point"}
}