{
  "type": "Feature",
  "properties": {
    "iso:country":"DE",
    "sg:address":"Meisenring 45",
    "sg:city":"Nienhagen",
    "sg:phone":"+49 5144/970852",
    "sg:postcode":"29336",
    "sg:province":"Niedersachsen",
    "wof:name":"E. Wilke",
    "wof:placetype":"venue"
},
  "geometry": {"coordinates":[10.090388298,52.5594062805],"type":"Point"}
}