{
  "type": "Feature",
  "properties": {
    "iso:country":"DE",
    "sg:address":"Reinh\u00e4user Landstr. 22",
    "sg:city":"G\u00f6ttingen",
    "sg:phone":"+49 551/703710",
    "sg:postcode":"37083",
    "sg:province":"Niedersachsen",
    "wof:name":"Gastst\u00e4tte Sportpalast",
    "wof:placetype":"venue"
},
  "geometry": {"coordinates":[9.9393043518,51.5264320374],"type":"Point"}
}