{
  "type": "Feature",
  "properties": {
    "iso:country":"DE",
    "sg:address":"Wilhelm-Haspel-Str. 5",
    "sg:city":"Sindelfingen",
    "sg:postcode":"71065",
    "sg:province":"Baden-W\u00fcrttemberg",
    "wof:name":"P\u00fcls",
    "wof:placetype":"venue"
},
  "geometry": {"coordinates":[9.01858,48.712681],"type":"Point"}
}