{
  "type": "Feature",
  "properties": {
    "iso:country":"DE",
    "sg:address":"Wailandtstr 4",
    "sg:city":"Aschaffenburg",
    "sg:phone":"+49 6021/84450",
    "sg:postcode":"63741",
    "sg:province":"Bayern",
    "wof:name":"Aschaffenburger Maschinenfabrik Johann Modler Gmbh",
    "wof:placetype":"venue"
},
  "geometry": {"coordinates":[9.097717,49.945374],"type":"Point"}
}