{
  "type": "Feature",
  "properties": {
    "iso:country":"DE",
    "sg:address":"Im Hinterfeld 13",
    "sg:city":"B\u00fcdingen",
    "sg:phone":"+49 6041/5285",
    "sg:postcode":"63654",
    "sg:province":"Hessen",
    "wof:name":"Eugen M\u00fcller",
    "wof:placetype":"venue"
},
  "geometry": {"coordinates":[9.0327148438,50.2882575989],"type":"Point"}
}