{
  "type": "Feature",
  "properties": {
    "iso:country":"DE",
    "sg:address":"Zehntwall 64",
    "sg:city":"Erftstadt",
    "sg:phone":"+49 2235/72200",
    "sg:postcode":"50374",
    "sg:province":"Nordrhein-Westfalen",
    "wof:name":"Klaus Reiner Esser",
    "wof:placetype":"venue"
},
  "geometry": {"coordinates":[6.7647900581,50.7987785339],"type":"Point"}
}