{
  "type": "Feature",
  "properties": {
    "iso:country":"DE",
    "sg:address":"Uhlandstr. 35",
    "sg:city":"Backnang",
    "sg:postcode":"71522",
    "sg:province":"Baden-W\u00fcrttemberg",
    "wof:name":"Gewerbeverein Backnang Otto Baur",
    "wof:placetype":"venue"
},
  "geometry": {"coordinates":[9.4303865433,48.9478340149],"type":"Point"}
}