{
  "type": "Feature",
  "properties": {
    "iso:country":"DE",
    "sg:address":"Darmst\u00e4dter Str. 22",
    "sg:city":"M\u00fcnster",
    "sg:postcode":"64839",
    "sg:province":"Hessen",
    "wof:name":"Jacob Fenster Und T\u00fcren Gmbh",
    "wof:placetype":"venue"
},
  "geometry": {"coordinates":[8.858636,49.922718],"type":"Point"}
}