{
  "type": "Feature",
  "properties": {
    "iso:country":"DE",
    "sg:address":"Lingener Str. 51",
    "sg:city":"Nordhorn",
    "sg:phone":"+49 5921/34668",
    "sg:postcode":"48531",
    "sg:province":"Niedersachsen",
    "wof:name":"Erich Beltle",
    "wof:placetype":"venue"
},
  "geometry": {"coordinates":[7.0838499069,52.4407310486],"type":"Point"}
}