{
  "type": "Feature",
  "properties": {
    "iso:country":"DE",
    "sg:address":"Am Bogen 3",
    "sg:city":"Wilstedt",
    "sg:phone":"+49 4283/5215",
    "sg:postcode":"27412",
    "sg:province":"Niedersachsen",
    "wof:name":"Arthur Lemmermann",
    "wof:placetype":"venue"
},
  "geometry": {"coordinates":[9.096427,53.195717],"type":"Point"}
}