{
  "type": "Feature",
  "properties": {
    "iso:country":"DE",
    "sg:address":"Zur H\u00fcllbuche 2",
    "sg:city":"Daaden",
    "sg:phone":"+49 2743/720",
    "sg:postcode":"57567",
    "sg:province":"Rheinland-Pfalz",
    "wof:name":"Helmut Grisse",
    "wof:placetype":"venue"
},
  "geometry": {"coordinates":[7.9736990929,50.7409515381],"type":"Point"}
}