{
  "type": "Feature",
  "properties": {
    "iso:country":"DE",
    "sg:address":"Henschelring 10",
    "sg:city":"Kirchheim",
    "sg:postcode":"85551",
    "sg:province":"Bayern",
    "wof:name":"Obermaier Metallbau Gmbh",
    "wof:placetype":"venue"
},
  "geometry": {"coordinates":[11.768591,48.175014],"type":"Point"}
}