{
  "type": "Feature",
  "properties": {
    "iso:country":"DE",
    "sg:address":"F\u00e4hrstr. 8",
    "sg:city":"Brunsb\u00fcttel",
    "sg:phone":"+49 4948/5287166",
    "sg:postcode":"25541",
    "sg:province":"Schleswig-Holstein",
    "wof:name":"Elektro- Marzok Ohg",
    "wof:placetype":"venue"
},
  "geometry": {"coordinates":[9.158893,53.895927],"type":"Point"}
}