{
  "type": "Feature",
  "properties": {
    "iso:country":"DE",
    "sg:address":"Thorwaldsenstr. 7",
    "sg:city":"M\u00fcnchen",
    "sg:postcode":"80335",
    "sg:province":"Bayern",
    "wof:name":"Rudolf Otto Grundst\u00fccks- Verwaltungs Gmbh & Co. Kg",
    "wof:placetype":"venue"
},
  "geometry": {"coordinates":[11.5501804352,48.1503829956],"type":"Point"}
}