{
  "type": "Feature",
  "properties": {
    "iso:country":"DE",
    "sg:address":"Pestalozzistr. 75",
    "sg:city":"Eisenberg",
    "sg:phone":"+49 6351/43994",
    "sg:postcode":"67304",
    "sg:province":"Rheinland-Pfalz",
    "wof:name":"Edmund Maltry Architekt",
    "wof:placetype":"venue"
},
  "geometry": {"coordinates":[8.079978,49.562878],"type":"Point"}
}