{
  "type": "Feature",
  "properties": {
    "iso:country":"DE",
    "sg:address":"am listholze 10",
    "sg:city":"Hannover",
    "sg:phone":"+49 511/666666",
    "sg:postcode":"30177",
    "sg:province":"Niedersachsen",
    "wof:name":"Hartmann & Franke Gbr",
    "wof:placetype":"venue"
},
  "geometry": {"coordinates":[9.7643489838,52.3966407776],"type":"Point"}
}