{
  "type": "Feature",
  "properties": {
    "iso:country":"DE",
    "sg:address":"Eisenbahnstr. 47",
    "sg:city":"St. Ingbert",
    "sg:phone":"+49 6894/580887",
    "sg:postcode":"66386",
    "sg:province":"Saarland",
    "wof:name":"K.-h. Grund-b\u00fcromaschinen Geldz\u00e4hlsysteme Gmbh",
    "wof:placetype":"venue"
},
  "geometry": {"coordinates":[7.1686830521,49.2642059326],"type":"Point"}
}