{
  "type": "Feature",
  "properties": {
    "iso:country":"DE",
    "sg:address":"Dammhaststr. 64",
    "sg:city":"Zehdenick",
    "sg:phone":"+49 3307/2635",
    "sg:postcode":"16792",
    "sg:province":"Brandenburg",
    "wof:name":"G & S Gmbh",
    "wof:placetype":"venue"
},
  "geometry": {"coordinates":[13.339615,52.984642],"type":"Point"}
}