{
  "type": "Feature",
  "properties": {
    "iso:country":"DE",
    "sg:address":"Industriestr. 9",
    "sg:city":"Bad Laasphe",
    "sg:phone":"+49 2752/9283",
    "sg:postcode":"57334",
    "sg:province":"Nordrhein-Westfalen",
    "wof:name":"Ludwig Fischer",
    "wof:placetype":"venue"
},
  "geometry": {"coordinates":[8.433073,50.927048],"type":"Point"}
}