{
  "type": "Feature",
  "properties": {
    "iso:country":"DE",
    "sg:address":"Markt 3",
    "sg:city":"Bad Oldesloe",
    "sg:phone":"+49 4531/2317",
    "sg:postcode":"23843",
    "sg:province":"Schleswig-Holstein",
    "wof:name":"G\u00fcnther Brall & Sohn Ohg",
    "wof:placetype":"venue"
},
  "geometry": {"coordinates":[10.3731079102,53.8098373413],"type":"Point"}
}