{
  "type": "Feature",
  "properties": {
    "iso:country":"DE",
    "sg:address":"Kiefholzstr. 400",
    "sg:city":"Berlin",
    "sg:phone":"+49 30/5337505",
    "sg:postcode":"12435",
    "sg:province":"Berlin",
    "wof:name":"W. Stephan E. K.",
    "wof:placetype":"venue"
},
  "geometry": {"coordinates":[13.456793,52.487152],"type":"Point"}
}