{
  "type": "Feature",
  "properties": {
    "iso:country":"DE",
    "sg:address":"Espenweg 1",
    "sg:city":"Lingen",
    "sg:phone":"+49 591/47045",
    "sg:postcode":"49808",
    "sg:province":"Niedersachsen",
    "wof:name":"Wein-willenbrock",
    "wof:placetype":"venue"
},
  "geometry": {"coordinates":[7.3103852272,52.5327949524],"type":"Point"}
}