{
  "type": "Feature",
  "properties": {
    "iso:country":"DE",
    "sg:address":"Trothaer Str. 54",
    "sg:city":"Halle",
    "sg:phone":"+49 345/5234429",
    "sg:postcode":"06118",
    "sg:province":"Sachsen-Anhalt",
    "wof:name":"Barbara Kr\u00f6ner",
    "wof:placetype":"venue"
},
  "geometry": {"coordinates":[11.9560403824,51.5190086365],"type":"Point"}
}