{
  "type": "Feature",
  "properties": {
    "iso:country":"DE",
    "sg:address":"Am Teiche 6",
    "sg:city":"Stotternheim",
    "sg:postcode":"99195",
    "sg:province":"Th\u00fcringen",
    "wof:name":"Suntextil Gmbh & Co. Kg",
    "wof:placetype":"venue"
},
  "geometry": {"coordinates":[11.048032,51.061008],"type":"Point"}
}