{
  "type": "Feature",
  "properties": {
    "iso:country":"DE",
    "sg:address":"Christoph-Probst-Weg 3",
    "sg:city":"Hamburg",
    "sg:classifiers":[
        {
            "category":"Professional",
            "subcategory":"Computer Services",
            "type":"Services"
        }
    ],
    "sg:postcode":"20251",
    "sg:tags":[
        "online-games",
        "browser-games",
        "browsergames",
        "browser-based-online-games",
        "free-to-play",
        "game-portal",
        "publisher",
        "content-provider",
        "developer",
        "games",
        "mmo",
        "mmog"
    ],
    "sg:website":"http://www.bigpoint.com",
    "wof:name":"Bigpoint",
    "wof:placetype":"venue"
},
  "geometry": {"coordinates":[9.9762519,53.5973055],"type":"Point"}
}