{
  "type": "Feature",
  "properties": {
    "iso:country":"DE",
    "sg:address":"Mittelgasse 4",
    "sg:city":"Br\u00e4unlingen",
    "sg:phone":"+49 771/62151",
    "sg:postcode":"78199",
    "sg:province":"Baden-W\u00fcrttemberg",
    "wof:name":"G. Gro\u00dfholz",
    "wof:placetype":"venue"
},
  "geometry": {"coordinates":[8.447012,47.929726],"type":"Point"}
}