{
  "type": "Feature",
  "properties": {
    "iso:country":"DE",
    "sg:address":"Sperberweg 13",
    "sg:city":"Gr\u00f6benzell",
    "sg:phone":"+49 8142/7187",
    "sg:postcode":"82194",
    "sg:province":"Bayern",
    "wof:name":"B. Schrader-volbeding \u00dcbersetzungsb\u00fcro",
    "wof:placetype":"venue"
},
  "geometry": {"coordinates":[11.381085,48.184746],"type":"Point"}
}