{
  "type": "Feature",
  "properties": {
    "iso:country":"DE",
    "sg:address":"Oranienburger Chaussee 52",
    "sg:city":"Berlin",
    "sg:phone":"+49 30/4051197",
    "sg:postcode":"13465",
    "sg:province":"Berlin",
    "wof:name":"Anhold Immobilien Gmbh",
    "wof:placetype":"venue"
},
  "geometry": {"coordinates":[13.3014497757,52.6433181763],"type":"Point"}
}