{
  "type": "Feature",
  "properties": {
    "iso:country":"DE",
    "sg:address":"Lange-Feld-Str. 29",
    "sg:city":"Seelze",
    "sg:phone":"+49 511/407710",
    "sg:postcode":"30926",
    "sg:province":"Niedersachsen",
    "wof:name":"Bierbar Blues Brothers",
    "wof:placetype":"venue"
},
  "geometry": {"coordinates":[9.642124176,52.3968505859],"type":"Point"}
}