{
  "type": "Feature",
  "properties": {
    "iso:country":"DE",
    "sg:address":"Bahnhofstr. 17",
    "sg:city":"Bad Friedrichshall",
    "sg:phone":"+49 7136/23275",
    "sg:postcode":"74177",
    "sg:province":"Baden-W\u00fcrttemberg",
    "wof:name":"Hans Schmidt",
    "wof:placetype":"venue"
},
  "geometry": {"coordinates":[9.213684082,49.2199020386],"type":"Point"}
}