{
  "type": "Feature",
  "properties": {
    "iso:country":"DE",
    "sg:address":"Fuggerstr. 16",
    "sg:city":"Korschenbroich",
    "sg:phone":"+49 4921/6167498",
    "sg:postcode":"41352",
    "sg:province":"Nordrhein-Westfalen",
    "wof:name":"Maschinenfabrik Hermann Franz Gmbh",
    "wof:placetype":"venue"
},
  "geometry": {"coordinates":[6.5409340858,51.1987609863],"type":"Point"}
}