{
  "type": "Feature",
  "properties": {
    "iso:country":"DE",
    "sg:address":"Magdeburger Str. 13",
    "sg:city":"Genthin",
    "sg:phone":"+49 3933/3724",
    "sg:postcode":"39307",
    "sg:province":"Sachsen-Anhalt",
    "wof:name":"Seelig Und Beuermann Rechtsanw\u00e4lte",
    "wof:placetype":"venue"
},
  "geometry": {"coordinates":[12.1524324417,52.4040374756],"type":"Point"}
}