{
  "type": "Feature",
  "properties": {
    "iso:country":"DE",
    "sg:address":"Altenh\u00e4ger Str. 10",
    "sg:city":"Hagenburg",
    "sg:phone":"+49 5033/6224",
    "sg:postcode":"31558",
    "sg:province":"Niedersachsen",
    "wof:name":"Hans-otto Seegers E. K.",
    "wof:placetype":"venue"
},
  "geometry": {"coordinates":[9.3273515701,52.4338874817],"type":"Point"}
}