{
  "type": "Feature",
  "properties": {
    "iso:country":"DE",
    "sg:address":"Thalheimer Str. 29",
    "sg:city":"Jahnsdorf",
    "sg:phone":"+49 3721/3582",
    "sg:postcode":"09387",
    "sg:province":"Sachsen",
    "wof:name":"Agrargenossenschaft Eg",
    "wof:placetype":"venue"
},
  "geometry": {"coordinates":[12.842246,50.733768],"type":"Point"}
}