{
  "type": "Feature",
  "properties": {
    "iso:country":"DE",
    "sg:address":"Wiesenweg 1b",
    "sg:city":"Barsb\u00fcttel",
    "sg:phone":"+49 40/7108137",
    "sg:postcode":"22885",
    "sg:province":"Schleswig-Holstein",
    "wof:name":"J\u00fcrgen Schmans",
    "wof:placetype":"venue"
},
  "geometry": {"coordinates":[10.238837,53.588226],"type":"Point"}
}