{
  "type": "Feature",
  "properties": {
    "iso:country":"DE",
    "sg:address":"Friemersheimer Str 18",
    "sg:city":"Moers",
    "sg:phone":"+49 2841/507569",
    "sg:postcode":"47441",
    "sg:province":"Nordrhein-Westfalen",
    "wof:name":"Audiob\u00fcro Gmbh",
    "wof:placetype":"venue"
},
  "geometry": {"coordinates":[6.6685199738,51.4356193542],"type":"Point"}
}