{
  "type": "Feature",
  "properties": {
    "iso:country":"DE",
    "sg:address":"Hinsbecker Weg 1",
    "sg:city":"Meerbusch",
    "sg:phone":"+49 2159/1041",
    "sg:postcode":"40670",
    "sg:province":"Nordrhein-Westfalen",
    "wof:name":"Friedrich Ossendot Rechtsanwalt",
    "wof:placetype":"venue"
},
  "geometry": {"coordinates":[6.6130871773,51.270942688],"type":"Point"}
}