{
  "type": "Feature",
  "properties": {
    "iso:country":"DE",
    "sg:address":"Br\u00fcckenstr. 9",
    "sg:city":"Zittau",
    "sg:phone":"+49 3583/703915",
    "sg:postcode":"02763",
    "sg:province":"Sachsen",
    "wof:name":"Wolfgang Gredy",
    "wof:placetype":"venue"
},
  "geometry": {"coordinates":[14.8190107346,50.8967971802],"type":"Point"}
}