{
  "type": "Feature",
  "properties": {
    "iso:country":"DE",
    "sg:address":"Halskestr 23",
    "sg:city":"Ratingen",
    "sg:phone":"+49 2102/997570",
    "sg:postcode":"40880",
    "sg:province":"Nordrhein-Westfalen",
    "wof:name":"Junckers Parkett Gmbh",
    "wof:placetype":"venue"
},
  "geometry": {"coordinates":[6.835049,51.305241],"type":"Point"}
}