{
  "type": "Feature",
  "properties": {
    "iso:country":"DE",
    "sg:address":"Bensberger Str. 102",
    "sg:city":"Bergisch Gladbach",
    "sg:phone":"+49 2202/242835",
    "sg:postcode":"51469",
    "sg:province":"Nordrhein-Westfalen",
    "wof:name":"Eggemann Verwaltungs Gmbh",
    "wof:placetype":"venue"
},
  "geometry": {"coordinates":[7.13502,50.984261],"type":"Point"}
}