{
  "type": "Feature",
  "properties": {
    "iso:country":"DE",
    "sg:address":"N\u00fcrtinger Str. 39",
    "sg:city":"Waldenbuch",
    "sg:postcode":"71111",
    "sg:province":"Baden-W\u00fcrttemberg",
    "wof:name":"Ta Engineering E. K.",
    "wof:placetype":"venue"
},
  "geometry": {"coordinates":[9.135588,48.6366],"type":"Point"}
}