{
  "type": "Feature",
  "properties": {
    "iso:country":"DE",
    "sg:address":"Schinkelstr. 8",
    "sg:city":"Holzminden",
    "sg:phone":"+49 5531/4538",
    "sg:postcode":"37603",
    "sg:province":"Niedersachsen",
    "wof:name":"Karl Klages Architekt",
    "wof:placetype":"venue"
},
  "geometry": {"coordinates":[9.461546,51.818371],"type":"Point"}
}