{
  "type": "Feature",
  "properties": {
    "iso:country":"DE",
    "sg:address":"Fitzgasse 10",
    "sg:city":"Waldkappel",
    "sg:phone":"+49 5658/1096",
    "sg:postcode":"37284",
    "sg:province":"Hessen",
    "wof:name":"Helmut Riemann Elektroinstallation",
    "wof:placetype":"venue"
},
  "geometry": {"coordinates":[9.932617,51.137478],"type":"Point"}
}