{
  "type": "Feature",
  "properties": {
    "iso:country":"DE",
    "sg:address":"Blankenseer Flughafen",
    "sg:city":"L\u00fcbeck",
    "sg:phone":"+49 451/583730",
    "sg:postcode":"23560",
    "sg:province":"Schleswig-Holstein",
    "wof:name":"Aviatec Avjonik Und Flugtechnik Gmbh",
    "wof:placetype":"venue"
},
  "geometry": {"coordinates":[10.632272,53.840908],"type":"Point"}
}