{
  "type": "Feature",
  "properties": {
    "iso:country":"DE",
    "sg:address":"An Der Amtmannsm\u00fchle 10",
    "sg:city":"Biebertal",
    "sg:phone":"+49 4964/091790",
    "sg:postcode":"35444",
    "sg:province":"Hessen",
    "wof:name":"R & S Gmbh",
    "wof:placetype":"venue"
},
  "geometry": {"coordinates":[8.614731,50.612728],"type":"Point"}
}