{
  "type": "Feature",
  "properties": {
    "iso:country":"DE",
    "sg:address":"B\u00f6singh\u00e4user Weg",
    "sg:city":"Waake",
    "sg:phone":"+49 5507/414",
    "sg:postcode":"37136",
    "sg:province":"Niedersachsen",
    "wof:name":"Gastst\u00e4tte Alwin Drechsler",
    "wof:placetype":"venue"
},
  "geometry": {"coordinates":[10.0566244125,51.5594100952],"type":"Point"}
}