{
  "type": "Feature",
  "properties": {
    "iso:country":"DE",
    "sg:address":"Biermannstr. 34",
    "sg:city":"Spenge",
    "sg:phone":"+49 5225/9946",
    "sg:postcode":"32139",
    "sg:province":"Nordrhein-Westfalen",
    "wof:name":"Adler Apotheke Marlies Kiel",
    "wof:placetype":"venue"
},
  "geometry": {"coordinates":[8.48763,52.139839],"type":"Point"}
}