{
  "type": "Feature",
  "properties": {
    "iso:country":"DE",
    "sg:address":"Ernst-Th\u00e4lmann-Str. 41",
    "sg:city":"Reitzenhain",
    "sg:postcode":"09496",
    "sg:province":"Sachsen",
    "wof:name":"W. Meyer",
    "wof:placetype":"venue"
},
  "geometry": {"coordinates":[13.2193145752,50.5612487793],"type":"Point"}
}