{
  "type": "Feature",
  "properties": {
    "iso:country":"DE",
    "sg:address":"Meergartenweg 21 b",
    "sg:city":"Frankenthal",
    "sg:phone":"+49 6233/66439",
    "sg:postcode":"67227",
    "sg:province":"Rheinland-Pfalz",
    "wof:name":"Herbert Schwab Augenoptiker",
    "wof:placetype":"venue"
},
  "geometry": {"coordinates":[8.3676300049,49.5322914124],"type":"Point"}
}