{
  "type": "Feature",
  "properties": {
    "iso:country":"DE",
    "sg:address":"Waldshuter Str. 20",
    "sg:city":"Bad S\u00e4ckingen",
    "sg:postcode":"79713",
    "sg:province":"Baden-W\u00fcrttemberg",
    "wof:name":"Tennis-center Kurverwalt. Gmbh Bad S\u00e4ckingen & Co. Kg",
    "wof:placetype":"venue"
},
  "geometry": {"coordinates":[7.9491658211,47.555141449],"type":"Point"}
}