{
  "type": "Feature",
  "properties": {
    "iso:country":"DE",
    "sg:address":"Gartenstr. 3",
    "sg:city":"Neumarkt",
    "sg:postcode":"92318",
    "sg:province":"Bayern",
    "wof:name":"Artex International Gmbh",
    "wof:placetype":"venue"
},
  "geometry": {"coordinates":[11.457512,49.276299],"type":"Point"}
}