{
  "type": "Feature",
  "properties": {
    "iso:country":"DE",
    "sg:address":"Stuttgarter Str. 79",
    "sg:city":"Reichenbach",
    "sg:phone":"+49 7153/98460",
    "sg:postcode":"73262",
    "sg:province":"Baden-W\u00fcrttemberg",
    "wof:name":"Ez Ziegler Products Gmbh",
    "wof:placetype":"venue"
},
  "geometry": {"coordinates":[9.4540958405,48.7081604004],"type":"Point"}
}