{
  "type": "Feature",
  "properties": {
    "iso:country":"DE",
    "sg:address":"Nollenkamp 3",
    "sg:city":"Hoffeld",
    "sg:phone":"+49 4322/6632",
    "sg:postcode":"24582",
    "sg:province":"Schleswig-Holstein",
    "wof:name":"Wilhelm Tank",
    "wof:placetype":"venue"
},
  "geometry": {"coordinates":[9.9920930862,54.1762428284],"type":"Point"}
}