{
  "type": "Feature",
  "properties": {
    "iso:country":"DE",
    "sg:address":"Werkstrasse 7",
    "sg:city":"Enger",
    "sg:phone":"+49 4966/931810",
    "sg:postcode":"32130",
    "sg:province":"Nordrhein-Westfalen",
    "wof:name":"Elektrische Licht-und Kraftanlagen Ag",
    "wof:placetype":"venue"
},
  "geometry": {"coordinates":[9.285695076,51.0006332397],"type":"Point"}
}