{
  "type": "Feature",
  "properties": {
    "iso:country":"DE",
    "sg:address":"Ludwig-Ganghofer-Str. 29",
    "sg:city":"Berchtesgaden",
    "sg:phone":"+49 8652/948431",
    "sg:postcode":"83471",
    "sg:province":"Bayern",
    "wof:name":"Petra Felder Ergotherapeutin",
    "wof:placetype":"venue"
},
  "geometry": {"coordinates":[12.998783,47.629333],"type":"Point"}
}