{
  "type": "Feature",
  "properties": {
    "iso:country":"DE",
    "sg:address":"Durlacher Str. 12",
    "sg:city":"Pforzheim",
    "sg:phone":"+49 7231/32507",
    "sg:postcode":"75172",
    "sg:province":"Baden-W\u00fcrttemberg",
    "wof:name":"Arthur Helbig",
    "wof:placetype":"venue"
},
  "geometry": {"coordinates":[8.693776,48.89275],"type":"Point"}
}