{
  "type": "Feature",
  "properties": {
    "iso:country":"DE",
    "sg:address":"Kiebitzstr. 22",
    "sg:city":"W\u00f6rthsee",
    "sg:phone":"+49 8153/8044",
    "sg:postcode":"82237",
    "sg:province":"Bayern",
    "wof:name":"Gerhard Hugel",
    "wof:placetype":"venue"
},
  "geometry": {"coordinates":[11.2013225555,48.0594520569],"type":"Point"}
}