{
  "type": "Feature",
  "properties": {
    "iso:country":"DE",
    "sg:address":"Neustr. 43 a",
    "sg:city":"Dinslaken",
    "sg:phone":"+49 2064/777347",
    "sg:postcode":"46535",
    "sg:province":"Nordrhein-Westfalen",
    "wof:name":"Sonnen-apotheke Birte Van Staa E. Kfr.",
    "wof:placetype":"venue"
},
  "geometry": {"coordinates":[6.736509,51.562401],"type":"Point"}
}