{
  "type": "Feature",
  "properties": {
    "iso:country":"DE",
    "sg:address":"Schlo\u00dfstr. 4",
    "sg:city":"Naumburg",
    "sg:phone":"+49 5625/862",
    "sg:postcode":"34311",
    "sg:province":"Hessen",
    "wof:name":"Heinz Herzog Steinmetzbetrieb",
    "wof:placetype":"venue"
},
  "geometry": {"coordinates":[9.2088384628,51.2307739258],"type":"Point"}
}