{
  "type": "Feature",
  "properties": {
    "iso:country":"DE",
    "sg:address":"Im Gewerbegebiet 6",
    "sg:city":"Bad Endorf",
    "sg:postcode":"83093",
    "sg:province":"Bayern",
    "wof:name":"Holzmaier Verwaltungs Gmbh",
    "wof:placetype":"venue"
},
  "geometry": {"coordinates":[12.2940759659,47.9155006409],"type":"Point"}
}