{
  "type": "Feature",
  "properties": {
    "iso:country":"DE",
    "sg:address":"Fuggerstr 20",
    "sg:city":"Gessertshausen",
    "sg:phone":"+49 8238/2267",
    "sg:postcode":"86459",
    "sg:province":"Bayern",
    "wof:name":"Steiger Gmbh",
    "wof:placetype":"venue"
},
  "geometry": {"coordinates":[10.711023,48.313656],"type":"Point"}
}