{
  "type": "Feature",
  "properties": {
    "iso:country":"DE",
    "sg:address":"Falkstr. 7",
    "sg:city":"Essen",
    "sg:phone":"+49 201/793940",
    "sg:postcode":"45147",
    "sg:province":"Nordrhein-Westfalen",
    "wof:name":"Horst Goller Ingenieur",
    "wof:placetype":"venue"
},
  "geometry": {"coordinates":[6.9992289543,51.4427909851],"type":"Point"}
}