{
  "type": "Feature",
  "properties": {
    "iso:country":"DE",
    "sg:address":"Donnerschweer Str. 372",
    "sg:city":"Oldenburg",
    "sg:phone":"+49 441/34020",
    "sg:postcode":"26123",
    "sg:province":"Niedersachsen",
    "wof:name":"Van Der Linden Gmbh & Co.",
    "wof:placetype":"venue"
},
  "geometry": {"coordinates":[8.2498083115,53.1619224548],"type":"Point"}
}