{
  "type": "Feature",
  "properties": {
    "iso:country":"DE",
    "sg:address":"Siegelsberg 1",
    "sg:city":"Hallenberg",
    "sg:phone":"+49 2984/462",
    "sg:postcode":"59969",
    "sg:province":"Nordrhein-Westfalen",
    "wof:name":"Sgv Hallenberg Hans Sandbrink",
    "wof:placetype":"venue"
},
  "geometry": {"coordinates":[8.6207618713,51.1184577942],"type":"Point"}
}