{
  "type": "Feature",
  "properties": {
    "iso:country":"DE",
    "sg:address":"Auf der Ley 14",
    "sg:city":"Hennef",
    "sg:phone":"+49 2248/798",
    "sg:postcode":"53773",
    "sg:province":"Nordrhein-Westfalen",
    "wof:name":"Intercem Engineering Gmbh",
    "wof:placetype":"venue"
},
  "geometry": {"coordinates":[7.3543171883,50.7602119446],"type":"Point"}
}