{
  "type": "Feature",
  "properties": {
    "iso:country":"DE",
    "sg:address":"Kirchplatz 3",
    "sg:city":"Calw",
    "sg:postcode":"75365",
    "sg:province":"Baden-W\u00fcrttemberg",
    "wof:name":"Marketing- Und Veranstaltungs- Gmbh",
    "wof:placetype":"venue"
},
  "geometry": {"coordinates":[8.7377796173,48.7140960693],"type":"Point"}
}