{
  "type": "Feature",
  "properties": {
    "iso:country":"DE",
    "sg:address":"Bauerstr. 22",
    "sg:city":"M\u00fcnchen",
    "sg:phone":"+49 89/2731186",
    "sg:postcode":"80796",
    "sg:province":"Bayern",
    "wof:name":"Christoph Lay Innenarchitekt",
    "wof:placetype":"venue"
},
  "geometry": {"coordinates":[11.571504,48.159649],"type":"Point"}
}