{
  "type": "Feature",
  "properties": {
    "iso:country":"DE",
    "sg:address":"Daimlerstr 56",
    "sg:city":"Goch",
    "sg:phone":"+49 2823/97690",
    "sg:postcode":"47574",
    "sg:province":"Nordrhein-Westfalen",
    "wof:name":"Wienstroth W\u00e4rmebehandlungstechnik Gmbh",
    "wof:placetype":"venue"
},
  "geometry": {"coordinates":[6.1353449821,51.6874504089],"type":"Point"}
}