{
  "type": "Feature",
  "properties": {
    "iso:country":"DE",
    "sg:address":"Schlo\u00dfallee 7",
    "sg:city":"Niederwiesa",
    "sg:postcode":"09577",
    "sg:province":"Sachsen",
    "wof:name":"Color-web Gmbh",
    "wof:placetype":"venue"
},
  "geometry": {"coordinates":[13.0074472427,50.8832244873],"type":"Point"}
}