{
  "type": "Feature",
  "properties": {
    "iso:country":"DE",
    "sg:address":"Schillerstr. 20",
    "sg:city":"Heidelberg",
    "sg:phone":"+49 6221/24328",
    "sg:postcode":"69115",
    "sg:province":"Baden-W\u00fcrttemberg",
    "wof:name":"Le Visage C. K\u00fcnnemann",
    "wof:placetype":"venue"
},
  "geometry": {"coordinates":[8.687239,49.399982],"type":"Point"}
}