{
  "type": "Feature",
  "properties": {
    "iso:country":"DE",
    "sg:address":"Waaghausstr. 12",
    "sg:city":"Tuttlingen",
    "sg:phone":"+49 7461/8956",
    "sg:postcode":"78532",
    "sg:province":"Baden-W\u00fcrttemberg",
    "wof:name":"Ellinor B\u00e4slack",
    "wof:placetype":"venue"
},
  "geometry": {"coordinates":[8.8181838989,47.9849739075],"type":"Point"}
}