{
  "type": "Feature",
  "properties": {
    "iso:country":"DE",
    "sg:address":"Rosenh\u00fcgel 8",
    "sg:city":"Ritterhude",
    "sg:phone":"+49 421/6360606",
    "sg:postcode":"27721",
    "sg:province":"Niedersachsen",
    "wof:name":"Alpha Gesellschaft F\u00fcr Reiseb\u00fcros Mbh",
    "wof:placetype":"venue"
},
  "geometry": {"coordinates":[8.7066202164,53.1805801392],"type":"Point"}
}