{
  "type": "Feature",
  "properties": {
    "iso:country":"DE",
    "sg:address":"Potsdamer Str. 160",
    "sg:city":"Bielefeld",
    "sg:phone":"+49 521/20930",
    "sg:postcode":"33719",
    "sg:province":"Nordrhein-Westfalen",
    "wof:name":"Jab Anstoetz International Beteiligungsges. Mbh",
    "wof:placetype":"venue"
},
  "geometry": {"coordinates":[8.599884,52.009701],"type":"Point"}
}