{
  "type": "Feature",
  "properties": {
    "iso:country":"DE",
    "sg:address":"Gerberstr. 37",
    "sg:city":"Winnenden",
    "sg:phone":"+49 7195/63336",
    "sg:postcode":"71364",
    "sg:province":"Baden-W\u00fcrttemberg",
    "wof:name":"Franz Schuster",
    "wof:placetype":"venue"
},
  "geometry": {"coordinates":[9.4003162384,48.8775482178],"type":"Point"}
}