{
  "type": "Feature",
  "properties": {
    "iso:country":"DE",
    "sg:address":"Brabanter Str. 41",
    "sg:city":"Wassenberg",
    "sg:phone":"+49 2432/6002",
    "sg:postcode":"41849",
    "sg:province":"Nordrhein-Westfalen",
    "wof:name":"Wilhelm Wilms Gmbh & Co.",
    "wof:placetype":"venue"
},
  "geometry": {"coordinates":[6.18332,51.101318],"type":"Point"}
}