{
  "type": "Feature",
  "properties": {
    "iso:country":"DE",
    "sg:address":"Benzstr. 33",
    "sg:city":"Renningen",
    "sg:phone":"+49 4971/5993120",
    "sg:postcode":"71272",
    "sg:province":"Baden-W\u00fcrttemberg",
    "wof:name":"Clean-tek Gmbh",
    "wof:placetype":"venue"
},
  "geometry": {"coordinates":[8.923982,48.776649],"type":"Point"}
}