{
  "type": "Feature",
  "properties": {
    "iso:country":"DE",
    "sg:address":"Maxstr. 22",
    "sg:city":"Scheibenhardt",
    "sg:phone":"+49 7277/391",
    "sg:postcode":"76779",
    "sg:province":"Rheinland-Pfalz",
    "wof:name":"Nikolaus Bayer",
    "wof:placetype":"venue"
},
  "geometry": {"coordinates":[8.136608,48.982639],"type":"Point"}
}