{
  "type": "Feature",
  "properties": {
    "iso:country":"DE",
    "sg:address":"Wilhelm-Heinrich-Str. 18",
    "sg:city":"Saarbr\u00fccken",
    "sg:phone":"+49 681/51181",
    "sg:postcode":"66117",
    "sg:province":"Saarland",
    "wof:name":"Fritz Anspach",
    "wof:placetype":"venue"
},
  "geometry": {"coordinates":[6.9903979301,49.2322463989],"type":"Point"}
}