{
  "type": "Feature",
  "properties": {
    "iso:country":"DE",
    "sg:address":"Kapellenstr. 27",
    "sg:city":"Lennestadt",
    "sg:phone":"+49 2721/2965",
    "sg:postcode":"57368",
    "sg:province":"Nordrhein-Westfalen",
    "wof:name":"B. Hettmann",
    "wof:placetype":"venue"
},
  "geometry": {"coordinates":[8.0412302017,51.1532440186],"type":"Point"}
}