{
  "type": "Feature",
  "properties": {
    "iso:country":"DE",
    "sg:address":"Wacholderberg 2a",
    "sg:city":"Wetzlar",
    "sg:phone":"+49 6441/43667",
    "sg:postcode":"35583",
    "sg:province":"Hessen",
    "wof:name":"Ekf Einkaufs- Service Und Dienstleistungen",
    "wof:placetype":"venue"
},
  "geometry": {"coordinates":[8.527505,50.563213],"type":"Point"}
}