{
  "type": "Feature",
  "properties": {
    "iso:country":"DE",
    "sg:address":"Melanchthonstr. 9",
    "sg:city":"Jena",
    "sg:postcode":"07743",
    "sg:province":"Th\u00fcringen",
    "wof:name":"Jk Bau Gmbh",
    "wof:placetype":"venue"
},
  "geometry": {"coordinates":[11.5729484558,50.929599762],"type":"Point"}
}