{
  "type": "Feature",
  "properties": {
    "iso:country":"DE",
    "sg:address":"Hauptstr. 82",
    "sg:city":"Boll",
    "sg:phone":"+49 7164/14040",
    "sg:postcode":"73087",
    "sg:province":"Baden-W\u00fcrttemberg",
    "wof:name":"Harald Finkbeiner Heilpraktiker",
    "wof:placetype":"venue"
},
  "geometry": {"coordinates":[9.6155700684,48.6407966614],"type":"Point"}
}