{
  "type": "Feature",
  "properties": {
    "iso:country":"DE",
    "sg:address":"Burgstallstr. 122",
    "sg:city":"Stuttgart",
    "sg:phone":"+49 711/6498183",
    "sg:postcode":"70199",
    "sg:province":"Baden-W\u00fcrttemberg",
    "wof:name":"Dea Tankstelle",
    "wof:placetype":"venue"
},
  "geometry": {"coordinates":[9.1413373947,48.7551193237],"type":"Point"}
}