{
  "type": "Feature",
  "properties": {
    "iso:country":"DE",
    "sg:address":"Jung-Jochen-Weg 12",
    "sg:city":"Rostock",
    "sg:phone":"+49 381/82253",
    "sg:postcode":"18069",
    "sg:province":"Mecklenburg-Vorpommern",
    "wof:name":"H. Kentzler",
    "wof:placetype":"venue"
},
  "geometry": {"coordinates":[12.083650589,54.1037597656],"type":"Point"}
}