{
  "type": "Feature",
  "properties": {
    "iso:country":"DE",
    "sg:address":"Im Hitzbach 13",
    "sg:city":"Breitenbach",
    "sg:phone":"+49 6675/919437",
    "sg:postcode":"36287",
    "sg:province":"Hessen",
    "wof:name":"Gerst Massivhaus Gmbh & Co. Kg",
    "wof:placetype":"venue"
},
  "geometry": {"coordinates":[9.5176801682,50.7747612],"type":"Point"}
}