{
  "type": "Feature",
  "properties": {
    "iso:country":"DE",
    "sg:address":"Liebigstr. 13",
    "sg:city":"Bad D\u00fcrrenberg",
    "sg:phone":"+49 3462/83008",
    "sg:postcode":"06231",
    "sg:province":"Sachsen-Anhalt",
    "wof:name":"Wolfgang Gerner",
    "wof:placetype":"venue"
},
  "geometry": {"coordinates":[12.0676422119,51.28490448],"type":"Point"}
}