{
  "type": "Feature",
  "properties": {
    "iso:country":"DE",
    "sg:address":"Alt Prester 46",
    "sg:city":"Magdeburg",
    "sg:phone":"+49 391/8116967",
    "sg:postcode":"39114",
    "sg:province":"Sachsen-Anhalt",
    "wof:name":"W. Mund",
    "wof:placetype":"venue"
},
  "geometry": {"coordinates":[11.673447,52.107113],"type":"Point"}
}