{
  "type": "Feature",
  "properties": {
    "iso:country":"DE",
    "sg:address":"Gr\u00fcnbacher Str. 38",
    "sg:city":"Falkenstein",
    "sg:phone":"+49 3745/6701",
    "sg:postcode":"08223",
    "sg:province":"Sachsen",
    "wof:name":"Norbert Gr\u00fcner Steuerberater",
    "wof:placetype":"venue"
},
  "geometry": {"coordinates":[12.3673601151,50.4686508179],"type":"Point"}
}