{
  "type": "Feature",
  "properties": {
    "iso:country":"DE",
    "sg:address":"Hauptstr. 17",
    "sg:city":"Herschbach",
    "sg:phone":"+49 6435/2567",
    "sg:postcode":"56414",
    "sg:province":"Rheinland-Pfalz",
    "wof:name":"Achim Jung",
    "wof:placetype":"venue"
},
  "geometry": {"coordinates":[7.7368988991,50.5734138489],"type":"Point"}
}