{
  "type": "Feature",
  "properties": {
    "iso:country":"DE",
    "sg:address":"Beusenstr. 9b",
    "sg:city":"Ostbevern",
    "sg:phone":"+49 2532/90504",
    "sg:postcode":"48346",
    "sg:province":"Nordrhein-Westfalen",
    "wof:name":"E. Ruhe",
    "wof:placetype":"venue"
},
  "geometry": {"coordinates":[7.8369541168,52.0371360779],"type":"Point"}
}