{
  "type": "Feature",
  "properties": {
    "iso:country":"DE",
    "sg:address":"Heidelberger Str. 17",
    "sg:city":"Gundelsheim",
    "sg:phone":"+49 7136/5193",
    "sg:postcode":"74831",
    "sg:province":"Baden-W\u00fcrttemberg",
    "wof:name":"Karl Krauth",
    "wof:placetype":"venue"
},
  "geometry": {"coordinates":[9.201921,49.264137],"type":"Point"}
}