{
  "type": "Feature",
  "properties": {
    "iso:country":"DE",
    "sg:address":"Marquardstr. 21",
    "sg:city":"L\u00fcbeck",
    "sg:phone":"+49 451/42467",
    "sg:postcode":"23554",
    "sg:province":"Schleswig-Holstein",
    "wof:name":"G. Scharnberg",
    "wof:placetype":"venue"
},
  "geometry": {"coordinates":[10.6696214676,53.8712615967],"type":"Point"}
}