{
  "type": "Feature",
  "properties": {
    "iso:country":"DE",
    "sg:address":"Bahnhofstr. 23",
    "sg:city":"K\u00f6nigswinter",
    "sg:phone":"+49 2223/24056",
    "sg:postcode":"53639",
    "sg:province":"Nordrhein-Westfalen",
    "wof:name":"Pizzeria Romino",
    "wof:placetype":"venue"
},
  "geometry": {"coordinates":[7.1931328773,50.6774864197],"type":"Point"}
}