{
  "type": "Feature",
  "properties": {
    "iso:country":"DE",
    "sg:address":"Wendelsteinstr. 2",
    "sg:city":"Rosenheim",
    "sg:phone":"+49 8031/43068",
    "sg:postcode":"83026",
    "sg:province":"Bayern",
    "wof:name":"Walter Michel Steuerberater",
    "wof:placetype":"venue"
},
  "geometry": {"coordinates":[12.1036186218,47.8524513245],"type":"Point"}
}