{
  "type": "Feature",
  "properties": {
    "iso:country":"DE",
    "sg:address":"Dachauer Str. 14",
    "sg:city":"Markt Indersdorf",
    "sg:phone":"+49 8136/366",
    "sg:postcode":"85229",
    "sg:province":"Bayern",
    "wof:name":"Kloster-apotheke",
    "wof:placetype":"venue"
},
  "geometry": {"coordinates":[11.377026,48.360905],"type":"Point"}
}