{
  "type": "Feature",
  "properties": {
    "iso:country":"DE",
    "sg:address":"Neustr. 58",
    "sg:city":"Winningen",
    "sg:phone":"+49 2606/756",
    "sg:postcode":"56333",
    "sg:province":"Rheinland-Pfalz",
    "wof:name":"Manfred M\u00f6lich Weinanbau",
    "wof:placetype":"venue"
},
  "geometry": {"coordinates":[7.5140109062,50.313747406],"type":"Point"}
}