{
  "type": "Feature",
  "properties": {
    "iso:country":"DE",
    "sg:address":"Hofer Str 48",
    "sg:city":"Berg",
    "sg:phone":"+49 9293/8080",
    "sg:postcode":"95180",
    "sg:province":"Bayern",
    "wof:name":"Spedition Lauterbach Gmbh & Co Kg",
    "wof:placetype":"venue"
},
  "geometry": {"coordinates":[11.7790546417,50.3748550415],"type":"Point"}
}