{
  "type": "Feature",
  "properties": {
    "iso:country":"DE",
    "sg:address":"Friesenstr. 22",
    "sg:city":"Berlin",
    "sg:phone":"+49 30/69507333",
    "sg:postcode":"10965",
    "sg:province":"Berlin",
    "wof:name":"Sarods Than Restaurant",
    "wof:placetype":"venue"
},
  "geometry": {"coordinates":[13.394657135,52.4878959656],"type":"Point"}
}