{
  "type": "Feature",
  "properties": {
    "iso:country":"DE",
    "sg:address":"Hauptstr. 26",
    "sg:city":"Wermelskirchen",
    "sg:phone":"+49 2196/80726",
    "sg:postcode":"42929",
    "sg:province":"Nordrhein-Westfalen",
    "wof:name":"H. W. Und G. Steinhaus",
    "wof:placetype":"venue"
},
  "geometry": {"coordinates":[7.25684,51.108585],"type":"Point"}
}