{
  "type": "Feature",
  "properties": {
    "iso:country":"DE",
    "sg:address":"Nauwieser Str. 22",
    "sg:city":"Saarbr\u00fccken",
    "sg:phone":"+49 681/35743",
    "sg:postcode":"66111",
    "sg:province":"Saarland",
    "wof:name":"Uff De Nauwies",
    "wof:placetype":"venue"
},
  "geometry": {"coordinates":[6.9992017746,49.2351303101],"type":"Point"}
}