{
  "type": "Feature",
  "properties": {
    "iso:country":"DE",
    "sg:address":"Bornstr. 136",
    "sg:city":"Dortmund",
    "sg:phone":"+49 231/813837",
    "sg:postcode":"44145",
    "sg:province":"Nordrhein-Westfalen",
    "wof:name":"Michael Nachbar Und Larissa Davidovskaja",
    "wof:placetype":"venue"
},
  "geometry": {"coordinates":[7.4708838463,51.5260772705],"type":"Point"}
}