{
  "type": "Feature",
  "properties": {
    "iso:country":"DE",
    "sg:address":"Birkenhofstr. 10",
    "sg:city":"Stuttgart",
    "sg:phone":"+49 711/4569465",
    "sg:postcode":"70599",
    "sg:province":"Baden-W\u00fcrttemberg",
    "wof:name":"Syntax",
    "wof:placetype":"venue"
},
  "geometry": {"coordinates":[9.2091350555,48.7186546326],"type":"Point"}
}