{
  "type": "Feature",
  "properties": {
    "iso:country":"DE",
    "sg:address":"Br\u00fcckenstr. 9",
    "sg:city":"Mayen",
    "sg:phone":"+49 2651/6249",
    "sg:postcode":"56727",
    "sg:province":"Rheinland-Pfalz",
    "wof:name":"M\u00fcller-johnston Antiquit\u00e4ten",
    "wof:placetype":"venue"
},
  "geometry": {"coordinates":[7.223928,50.330086],"type":"Point"}
}