{
  "type": "Feature",
  "properties": {
    "iso:country":"DE",
    "sg:address":"Kreuzstr. 14",
    "sg:city":"Ingolstadt",
    "sg:phone":"+49 841/35933",
    "sg:postcode":"85049",
    "sg:province":"Bayern",
    "wof:name":"Wein In",
    "wof:placetype":"venue"
},
  "geometry": {"coordinates":[11.4187202454,48.76404953],"type":"Point"}
}