{
  "type": "Feature",
  "properties": {
    "iso:country":"DE",
    "sg:address":"Heisenbergstr. 2-4",
    "sg:city":"Eching",
    "sg:phone":"+49 8165/95350",
    "sg:postcode":"85386",
    "sg:province":"Bayern",
    "wof:name":"Wickenh\u00e4user Verwaltungs- Gmbh",
    "wof:placetype":"venue"
},
  "geometry": {"coordinates":[11.63123,48.304668],"type":"Point"}
}