{
  "type": "Feature",
  "properties": {
    "iso:country":"DE",
    "sg:address":"Am Fischerbichl 1",
    "sg:city":"Berchtesgaden",
    "sg:phone":"+49 8652/2557",
    "sg:postcode":"83471",
    "sg:province":"Bayern",
    "wof:name":"Oskar Filip",
    "wof:placetype":"venue"
},
  "geometry": {"coordinates":[13.0028429031,47.632522583],"type":"Point"}
}