{
  "type": "Feature",
  "properties": {
    "iso:country":"DE",
    "sg:address":"Wilhelmstr 59",
    "sg:city":"Muggensturm",
    "sg:phone":"+49 800 1811184",
    "sg:postcode":"76461",
    "sg:province":"Baden-W\u00fcrttemberg",
    "wof:name":"Bachem Distributions Services Gmbh",
    "wof:placetype":"venue"
},
  "geometry": {"coordinates":[7.597634,47.604973],"type":"Point"}
}