{
  "type": "Feature",
  "properties": {
    "iso:country":"DE",
    "sg:address":"Tolstoistr. 7",
    "sg:city":"Dresden",
    "sg:phone":"+49 351/2679968",
    "sg:postcode":"01326",
    "sg:province":"Sachsen",
    "wof:name":"Ring Deutscher Makler Landesverband Sachsen E. V.",
    "wof:placetype":"venue"
},
  "geometry": {"coordinates":[13.8072290421,51.0625686646],"type":"Point"}
}