{
  "type": "Feature",
  "properties": {
    "iso:country":"DE",
    "sg:address":"Gartenweg 2",
    "sg:city":"S\u00fcplingen",
    "sg:postcode":"39343",
    "sg:province":"Sachsen-Anhalt",
    "wof:name":"Rieke Massivhaus Gmbh",
    "wof:placetype":"venue"
},
  "geometry": {"coordinates":[11.326728,52.285633],"type":"Point"}
}