{
  "type": "Feature",
  "properties": {
    "iso:country":"DE",
    "sg:address":"Alter Markt 9",
    "sg:city":"Parchim",
    "sg:phone":"+49 3871/264666",
    "sg:postcode":"19370",
    "sg:province":"Mecklenburg-Vorpommern",
    "wof:name":"G. Staeck",
    "wof:placetype":"venue"
},
  "geometry": {"coordinates":[11.848690033,53.4277954102],"type":"Point"}
}