{
  "type": "Feature",
  "properties": {
    "iso:country":"DE",
    "sg:address":"Alte Chaussee 27",
    "sg:city":"Hadamar",
    "sg:phone":"+49 6433/943726",
    "sg:postcode":"65589",
    "sg:province":"Hessen",
    "wof:name":"Christiane Klein-de Meulenaer Masseurin",
    "wof:placetype":"venue"
},
  "geometry": {"coordinates":[8.041613,50.445587],"type":"Point"}
}