{
  "type": "Feature",
  "properties": {
    "iso:country":"DE",
    "sg:address":"Otto-von-Guericke-Str. 4",
    "sg:city":"Rotenburg",
    "sg:phone":"+49 4261/2025",
    "sg:postcode":"27356",
    "sg:province":"Niedersachsen",
    "wof:name":"Oetjen Rohstoffhandel Gmbh",
    "wof:placetype":"venue"
},
  "geometry": {"coordinates":[9.3847293854,53.1155929565],"type":"Point"}
}