{
  "type": "Feature",
  "properties": {
    "iso:country":"DE",
    "sg:address":"Am Altenroth 8",
    "sg:city":"Hosenfeld",
    "sg:phone":"+49 6669/1599",
    "sg:postcode":"36154",
    "sg:province":"Hessen",
    "wof:name":"Manfred Zipper",
    "wof:placetype":"venue"
},
  "geometry": {"coordinates":[9.450276,50.490803],"type":"Point"}
}