{
  "type": "Feature",
  "properties": {
    "iso:country":"DE",
    "sg:address":"Sohra 26 d",
    "sg:city":"Bobritzsch",
    "sg:phone":"+49 37325/7265",
    "sg:postcode":"09627",
    "sg:province":"Sachsen",
    "wof:name":"Sohratal",
    "wof:placetype":"venue"
},
  "geometry": {"coordinates":[13.4305896759,50.9024810791],"type":"Point"}
}