{
  "type": "Feature",
  "properties": {
    "iso:country":"DE",
    "sg:address":"Schwartower Str. 43",
    "sg:city":"Boizenburg",
    "sg:phone":"+49 38847/53341",
    "sg:postcode":"19258",
    "sg:province":"Mecklenburg-Vorpommern",
    "wof:name":"Lindenhof",
    "wof:placetype":"venue"
},
  "geometry": {"coordinates":[10.726776123,53.3795166016],"type":"Point"}
}