{
  "type": "Feature",
  "properties": {
    "iso:country":"DE",
    "sg:address":"Kaiser-Wilhelm-Str. 24-26",
    "sg:city":"Berlin",
    "sg:phone":"+49 30/7417067",
    "sg:postcode":"12247",
    "sg:province":"Berlin",
    "wof:name":"Hako Immobilien Inh. Claudia Ludwig",
    "wof:placetype":"venue"
},
  "geometry": {"coordinates":[13.3367052078,52.4312820435],"type":"Point"}
}