{
  "type": "Feature",
  "properties": {
    "iso:country":"DE",
    "sg:address":"Osterkamp 10",
    "sg:city":"Seedorf",
    "sg:phone":"+49 4555/465",
    "sg:postcode":"23823",
    "sg:province":"Schleswig-Holstein",
    "wof:name":"Gerhard W. H\u00fcgle",
    "wof:placetype":"venue"
},
  "geometry": {"coordinates":[10.3661546707,54.0733947754],"type":"Point"}
}