{
  "type": "Feature",
  "properties": {
    "iso:country":"DE",
    "sg:address":"Ganghoferstr. 5",
    "sg:city":"Altom\u00fcnster",
    "sg:phone":"+49 8254/8315",
    "sg:postcode":"85250",
    "sg:province":"Bayern",
    "wof:name":"Dr. Walter Meyer Tierarzt",
    "wof:placetype":"venue"
},
  "geometry": {"coordinates":[11.2500810623,48.3848381042],"type":"Point"}
}