{
  "type": "Feature",
  "properties": {
    "iso:country":"DE",
    "sg:address":"Pfarrfeldstr. 1",
    "sg:city":"Lauingen",
    "sg:phone":"+49 9072/95360",
    "sg:postcode":"89415",
    "sg:province":"Bayern",
    "wof:name":"Lut Gmbh Lauinger Umwelttechnik",
    "wof:placetype":"venue"
},
  "geometry": {"coordinates":[10.4242677689,48.5662117004],"type":"Point"}
}