{
  "type": "Feature",
  "properties": {
    "iso:country":"DE",
    "sg:address":"Sandstr. 17",
    "sg:city":"Wassenberg",
    "sg:phone":"+49 2432/20830",
    "sg:postcode":"41849",
    "sg:province":"Nordrhein-Westfalen",
    "wof:name":"Heribert Winkens",
    "wof:placetype":"venue"
},
  "geometry": {"coordinates":[6.16047,51.118359],"type":"Point"}
}