{
  "type": "Feature",
  "properties": {
    "iso:country":"DE",
    "sg:address":"Hauptstr. 5",
    "sg:city":"Zell",
    "sg:phone":"+49 6542/2589",
    "sg:postcode":"56856",
    "sg:province":"Rheinland-Pfalz",
    "wof:name":"J\u00fcrgen Klaus",
    "wof:placetype":"venue"
},
  "geometry": {"coordinates":[9.502961,48.202919],"type":"Point"}
}