{
  "type": "Feature",
  "properties": {
    "iso:country":"DE",
    "sg:address":"St.-Martin-Str. 12",
    "sg:city":"Beltheim",
    "sg:phone":"+49 6762/6624",
    "sg:postcode":"56290",
    "sg:province":"Rheinland-Pfalz",
    "wof:name":"Martin Kr\u00e4mer",
    "wof:placetype":"venue"
},
  "geometry": {"coordinates":[7.4353289604,50.1104125977],"type":"Point"}
}