{
  "type": "Feature",
  "properties": {
    "iso:country":"DE",
    "sg:address":"Holzgraben 5",
    "sg:city":"Aachen",
    "sg:phone":"+49 241/28238",
    "sg:postcode":"52062",
    "sg:province":"Nordrhein-Westfalen",
    "wof:name":"Ca Bu Chon",
    "wof:placetype":"venue"
},
  "geometry": {"coordinates":[6.08725,50.774792],"type":"Point"}
}