{
  "type": "Feature",
  "properties": {
    "iso:country":"DE",
    "sg:address":"Am Horn 4",
    "sg:city":"Bad Harzburg",
    "sg:phone":"+49 5322/86611",
    "sg:postcode":"38667",
    "sg:province":"Niedersachsen",
    "wof:name":"Hackbeil Dachdeckermeister Gmbh",
    "wof:placetype":"venue"
},
  "geometry": {"coordinates":[10.549675,51.895348],"type":"Point"}
}