{
  "type": "Feature",
  "properties": {
    "iso:country":"DE",
    "sg:address":"Odenwaldstr. 10",
    "sg:city":"Ettlingen",
    "sg:phone":"+49 7243/2199700",
    "sg:postcode":"76275",
    "sg:province":"Baden-W\u00fcrttemberg",
    "wof:name":"Stentec Kg",
    "wof:placetype":"venue"
},
  "geometry": {"coordinates":[8.430846,48.914108],"type":"Point"}
}