{
  "type": "Feature",
  "properties": {
    "iso:country":"DE",
    "sg:address":"Rohrbacher Str. 45",
    "sg:city":"Heidelberg",
    "sg:phone":"+49 6221/25275",
    "sg:postcode":"69115",
    "sg:province":"Baden-W\u00fcrttemberg",
    "wof:name":"H. Lott",
    "wof:placetype":"venue"
},
  "geometry": {"coordinates":[8.6922931671,49.4037132263],"type":"Point"}
}