{
  "type": "Feature",
  "properties": {
    "iso:country":"DE",
    "sg:address":"Konrad-Adenauer-Platz 23",
    "sg:city":"Bonn",
    "sg:phone":"+49 228/461489",
    "sg:postcode":"53225",
    "sg:province":"Nordrhein-Westfalen",
    "wof:name":"Raimund Schmitz-reinhard Schmitz-reinhard",
    "wof:placetype":"venue"
},
  "geometry": {"coordinates":[7.1177420616,50.739616394],"type":"Point"}
}