{
  "type": "Feature",
  "properties": {
    "iso:country":"DE",
    "sg:address":"Sulzbacher Str. 43",
    "sg:city":"Schwalbach",
    "sg:phone":"+49 4961/961244",
    "sg:postcode":"65824",
    "sg:province":"Hessen",
    "wof:name":"Gebr. Steier Ohg",
    "wof:placetype":"venue"
},
  "geometry": {"coordinates":[8.533662796,50.1436958313],"type":"Point"}
}