{
  "type": "Feature",
  "properties": {
    "iso:country":"DE",
    "sg:address":"Teichstr. 2",
    "sg:city":"Crimmitschau",
    "sg:postcode":"08451",
    "sg:province":"Sachsen",
    "wof:name":"Aee Aktiengesellschaft F\u00fcr Erneuerbare Energien & Co.",
    "wof:placetype":"venue"
},
  "geometry": {"coordinates":[12.380489,50.816257],"type":"Point"}
}