{
  "type": "Feature",
  "properties": {
    "iso:country":"DE",
    "sg:address":"Eisenbahnstr. 8",
    "sg:city":"Nerchau",
    "sg:phone":"+49 34382/41222",
    "sg:postcode":"04685",
    "sg:province":"Sachsen",
    "wof:name":"G\u00fcttner Sicherheitstechnik Und Systembau Gmbh",
    "wof:placetype":"venue"
},
  "geometry": {"coordinates":[12.7946929932,51.27734375],"type":"Point"}
}