{
  "type": "Feature",
  "properties": {
    "iso:country":"DE",
    "sg:address":"Goethestr. 33",
    "sg:city":"Worms",
    "sg:postcode":"67547",
    "sg:province":"Rheinland-Pfalz",
    "wof:name":"Bvg Baustoff-vertriebs Gmbh & Co.",
    "wof:placetype":"venue"
},
  "geometry": {"coordinates":[8.35828,49.635925],"type":"Point"}
}