{
  "type": "Feature",
  "properties": {
    "iso:country":"DE",
    "sg:address":"Saarbr\u00fccker Str. 25",
    "sg:city":"Riegelsberg",
    "sg:phone":"+49 6806/490316",
    "sg:postcode":"66292",
    "sg:province":"Saarland",
    "wof:name":"Kebapgrill",
    "wof:placetype":"venue"
},
  "geometry": {"coordinates":[6.9460110664,49.3008537292],"type":"Point"}
}