{
  "type": "Feature",
  "properties": {
    "iso:country":"DE",
    "sg:address":"Hauptstr. 4",
    "sg:city":"Linden",
    "sg:phone":"+49 6403/95050",
    "sg:postcode":"35440",
    "sg:province":"Hessen",
    "wof:name":"Moderne Bauelemente Schmidt Gesch\u00e4ftsf\u00fchrungs Gmbh",
    "wof:placetype":"venue"
},
  "geometry": {"coordinates":[8.686322,50.529827],"type":"Point"}
}