{
  "type": "Feature",
  "properties": {
    "iso:country":"DE",
    "sg:address":"Alte Landstr. 3",
    "sg:city":"Griesingen",
    "sg:phone":"+49 7391/6652",
    "sg:postcode":"89608",
    "sg:province":"Baden-W\u00fcrttemberg",
    "wof:name":"Gasthaus Maria Staudenrausch",
    "wof:placetype":"venue"
},
  "geometry": {"coordinates":[9.7857513428,48.2678718567],"type":"Point"}
}