{
  "type": "Feature",
  "properties": {
    "iso:country":"DE",
    "sg:address":"H\u00f6ckinger Str. 2",
    "sg:city":"Landau",
    "sg:phone":"+49 9951/8373",
    "sg:postcode":"94405",
    "sg:province":"Bayern",
    "wof:name":"Sergey Barawikow",
    "wof:placetype":"venue"
},
  "geometry": {"coordinates":[12.693817,48.672756],"type":"Point"}
}