{
  "type": "Feature",
  "properties": {
    "iso:country":"DE",
    "sg:address":"Virchowstr. 43",
    "sg:city":"Leverkusen",
    "sg:postcode":"51375",
    "sg:province":"Nordrhein-Westfalen",
    "wof:name":"Helmut Nowak Gmbh",
    "wof:placetype":"venue"
},
  "geometry": {"coordinates":[7.0274548531,51.0330467224],"type":"Point"}
}