{
  "type": "Feature",
  "properties": {
    "iso:country":"DE",
    "sg:address":"Am Fronhof 1",
    "sg:city":"Bonn",
    "sg:phone":"+49 228/357628",
    "sg:postcode":"53177",
    "sg:province":"Nordrhein-Westfalen",
    "wof:name":"R. Kocks",
    "wof:placetype":"venue"
},
  "geometry": {"coordinates":[7.1526517868,50.6826515198],"type":"Point"}
}