{
  "type": "Feature",
  "properties": {
    "iso:country":"DE",
    "sg:address":"Mariendorfer Damm 149",
    "sg:city":"Berlin",
    "sg:phone":"+49 30/7055226",
    "sg:postcode":"12107",
    "sg:province":"Berlin",
    "wof:name":"Georg Orphall",
    "wof:placetype":"venue"
},
  "geometry": {"coordinates":[13.3881244659,52.438079834],"type":"Point"}
}