{
  "type": "Feature",
  "properties": {
    "iso:country":"DE",
    "sg:address":"Dorfstr. 66",
    "sg:city":"Felde",
    "sg:phone":"+49 4340/775",
    "sg:postcode":"24242",
    "sg:province":"Schleswig-Holstein",
    "wof:name":"Edeltraut Heinrich",
    "wof:placetype":"venue"
},
  "geometry": {"coordinates":[9.9361944199,54.3028106689],"type":"Point"}
}