{
  "type": "Feature",
  "properties": {
    "iso:country":"DE",
    "sg:address":"Am Wei\u00dfen Stein 3",
    "sg:city":"Frankfurt",
    "sg:phone":"+49 69/515003",
    "sg:postcode":"60431",
    "sg:province":"Hessen",
    "wof:name":"Eva-maria Blanco",
    "wof:placetype":"venue"
},
  "geometry": {"coordinates":[8.657041,50.156097],"type":"Point"}
}