{
  "type": "Feature",
  "properties": {
    "iso:country":"DE",
    "sg:address":"Bahnhofstr 22",
    "sg:city":"Westoverledingen",
    "sg:phone":"+49 4955/4456",
    "sg:postcode":"26810",
    "sg:province":"Niedersachsen",
    "wof:name":"Sparkasse Leer-weener",
    "wof:placetype":"venue"
},
  "geometry": {"coordinates":[7.453528,53.166626],"type":"Point"}
}