{
  "type": "Feature",
  "properties": {
    "iso:country":"DE",
    "sg:address":"Bruchhausen 3",
    "sg:city":"Erkrath",
    "sg:postcode":"40699",
    "sg:province":"Nordrhein-Westfalen",
    "wof:name":"Exim Export- Und Import- Gesellschaft F\u00fcr Industrie-",
    "wof:placetype":"venue"
},
  "geometry": {"coordinates":[6.9263429642,51.1979637146],"type":"Point"}
}