{
  "type": "Feature",
  "properties": {
    "iso:country":"DE",
    "sg:address":"Meesmannstr. 54",
    "sg:city":"Witten",
    "sg:phone":"+49 2302/71363",
    "sg:postcode":"58456",
    "sg:province":"Nordrhein-Westfalen",
    "wof:name":"Stadtsch\u00e4nke",
    "wof:placetype":"venue"
},
  "geometry": {"coordinates":[7.2814459801,51.4220809937],"type":"Point"}
}