{
  "type": "Feature",
  "properties": {
    "iso:country":"DE",
    "sg:address":"Sch\u00f6ppinger Str.",
    "sg:city":"Ahaus",
    "sg:postcode":"48683",
    "sg:province":"Nordrhein-Westfalen",
    "wof:name":"Baumarkt Hellweg Gmbh",
    "wof:placetype":"venue"
},
  "geometry": {"coordinates":[7.0343379974,52.0744628906],"type":"Point"}
}