{
  "type": "Feature",
  "properties": {
    "iso:country":"DE",
    "sg:address":"Gro\u00df Aschen 65",
    "sg:city":"Melle",
    "sg:phone":"+49 5226/5203",
    "sg:postcode":"49328",
    "sg:province":"Niedersachsen",
    "wof:name":"Karl Blume Architekten",
    "wof:placetype":"venue"
},
  "geometry": {"coordinates":[8.49671,52.176971],"type":"Point"}
}