{
  "type": "Feature",
  "properties": {
    "iso:country":"DE",
    "sg:address":"Johannes-M\u00fcller-Str. 7",
    "sg:city":"Koblenz",
    "sg:postcode":"56068",
    "sg:province":"Rheinland-Pfalz",
    "wof:name":"Mcc Medcare Contraol Ggmbh",
    "wof:placetype":"venue"
},
  "geometry": {"coordinates":[7.593961,50.348831],"type":"Point"}
}