{
  "type": "Feature",
  "properties": {
    "iso:country":"DE",
    "sg:address":"K\u00f6lner Str. 3",
    "sg:city":"Lindlar",
    "sg:phone":"+49 2266/477800",
    "sg:postcode":"51789",
    "sg:province":"Nordrhein-Westfalen",
    "wof:name":"Gondolf & Partner Gmbh",
    "wof:placetype":"venue"
},
  "geometry": {"coordinates":[7.3747601509,51.0191192627],"type":"Point"}
}