{
  "type": "Feature",
  "properties": {
    "iso:country":"DE",
    "sg:address":"Parkstr. 44",
    "sg:city":"Kronberg",
    "sg:phone":"+49 6173/68222",
    "sg:postcode":"61476",
    "sg:province":"Hessen",
    "wof:name":"Edith Hammer Heilpraktikerin",
    "wof:placetype":"venue"
},
  "geometry": {"coordinates":[8.5199460983,50.187625885],"type":"Point"}
}