{
  "type": "Feature",
  "properties": {
    "iso:country":"DE",
    "sg:address":"Grabengasse 2",
    "sg:city":"Passau",
    "sg:phone":"+49 851/33466",
    "sg:postcode":"94032",
    "sg:province":"Bayern",
    "wof:name":"Wilhelm Simader",
    "wof:placetype":"venue"
},
  "geometry": {"coordinates":[13.460395813,48.5746955872],"type":"Point"}
}