{
  "type": "Feature",
  "properties": {
    "iso:country":"DE",
    "sg:address":"Seestr. 12",
    "sg:city":"Niederlehme",
    "sg:phone":"+49 3375/501676",
    "sg:postcode":"15751",
    "sg:province":"Brandenburg",
    "wof:name":"Sporthaus",
    "wof:placetype":"venue"
},
  "geometry": {"coordinates":[13.6504068375,52.3177528381],"type":"Point"}
}