{
  "type": "Feature",
  "properties": {
    "iso:country":"DE",
    "sg:address":"Brustertkirchpfad 2-6",
    "sg:city":"Krefeld",
    "sg:phone":"+49 2151/732528",
    "sg:postcode":"47839",
    "sg:province":"Nordrhein-Westfalen",
    "wof:name":"Karin Strumpen Immobilienmaklerin",
    "wof:placetype":"venue"
},
  "geometry": {"coordinates":[6.5089578629,51.3779258728],"type":"Point"}
}