{
  "type": "Feature",
  "properties": {
    "iso:country":"DE",
    "sg:address":"Erkelenzer Str. 45",
    "sg:city":"Wassenberg",
    "sg:phone":"+49 2432/3161",
    "sg:postcode":"41849",
    "sg:province":"Nordrhein-Westfalen",
    "wof:name":"Eiscafe Kohlens",
    "wof:placetype":"venue"
},
  "geometry": {"coordinates":[6.170308,51.103333],"type":"Point"}
}