{
  "type": "Feature",
  "properties": {
    "iso:country":"DE",
    "sg:address":"Schlo\u00dfstr. 14",
    "sg:city":"Potsdam",
    "sg:phone":"+49 331/291506",
    "sg:postcode":"14467",
    "sg:province":"Brandenburg",
    "wof:name":"Pegasus",
    "wof:placetype":"venue"
},
  "geometry": {"coordinates":[13.0565299988,52.3947868347],"type":"Point"}
}