{
  "type": "Feature",
  "properties": {
    "iso:country":"DE",
    "sg:address":"Am Bahnhof 14",
    "sg:city":"Handewitt",
    "sg:phone":"+49 4639/7119",
    "sg:postcode":"24983",
    "sg:province":"Schleswig-Holstein",
    "wof:name":"Elektro Ehrhardt Johannes Ehrhardt",
    "wof:placetype":"venue"
},
  "geometry": {"coordinates":[9.326809,54.773018],"type":"Point"}
}