{
  "type": "Feature",
  "properties": {
    "iso:country":"DE",
    "sg:address":"B\u00f6tticherstr. 9",
    "sg:city":"Westerland",
    "sg:phone":"+49 4651/927024",
    "sg:postcode":"25980",
    "sg:province":"Schleswig-Holstein",
    "wof:name":"Rainer Heiliger",
    "wof:placetype":"venue"
},
  "geometry": {"coordinates":[8.3034238815,54.906124115],"type":"Point"}
}