{
  "type": "Feature",
  "properties": {
    "iso:country":"DE",
    "sg:address":"Hauptstr. 39 Menteroda",
    "sg:city":"Urbach",
    "sg:phone":"+49 36029/84485",
    "sg:postcode":"99996",
    "sg:province":"Th\u00fcringen",
    "wof:name":"Agrargenossenschaft Urbach Eg",
    "wof:placetype":"venue"
},
  "geometry": {"coordinates":[10.560794,51.30518],"type":"Point"}
}