{
  "type": "Feature",
  "properties": {
    "iso:country":"DE",
    "sg:address":"Molsberger Str. 2",
    "sg:city":"Wallmerod",
    "sg:phone":"+49 6435/1205",
    "sg:postcode":"56414",
    "sg:province":"Rheinland-Pfalz",
    "wof:name":"Pension St. Hubertus",
    "wof:placetype":"venue"
},
  "geometry": {"coordinates":[7.9547119141,50.4839401245],"type":"Point"}
}