{
  "type": "Feature",
  "properties": {
    "iso:country":"DE",
    "sg:address":"M\u00fcnstererstr. 5",
    "sg:city":"Abensberg",
    "sg:phone":"+49 9443/5204",
    "sg:postcode":"93326",
    "sg:province":"Bayern",
    "wof:name":"M. Gammel Ingenieur",
    "wof:placetype":"venue"
},
  "geometry": {"coordinates":[11.8480453491,48.8164978027],"type":"Point"}
}