{
  "type": "Feature",
  "properties": {
    "iso:country":"DE",
    "sg:address":"Bremer Str. 323 a",
    "sg:city":"Delmenhorst",
    "sg:phone":"+49 4221/978294",
    "sg:postcode":"27751",
    "sg:province":"Niedersachsen",
    "wof:name":"Schmitz",
    "wof:placetype":"venue"
},
  "geometry": {"coordinates":[8.6787519455,53.055847168],"type":"Point"}
}