{
  "type": "Feature",
  "properties": {
    "iso:country":"DE",
    "sg:address":"Roteb\u00fchlstr. 20",
    "sg:city":"Stuttgart",
    "sg:phone":"+49 4971/1225043",
    "sg:postcode":"70178",
    "sg:province":"Baden-W\u00fcrttemberg",
    "wof:name":"Deutsche Centralbodenkredit Ag",
    "wof:placetype":"venue"
},
  "geometry": {"coordinates":[9.16887,48.773571],"type":"Point"}
}