{
  "type": "Feature",
  "properties": {
    "iso:country":"DE",
    "sg:address":"Heidemannstr. 31",
    "sg:city":"M\u00fcnchen",
    "sg:phone":"+49 89/3164137",
    "sg:postcode":"80939",
    "sg:province":"Bayern",
    "wof:name":"Theaterkunst Gmbh",
    "wof:placetype":"venue"
},
  "geometry": {"coordinates":[11.590261,48.201534],"type":"Point"}
}