{
  "type": "Feature",
  "properties": {
    "iso:country":"DE",
    "sg:address":"Innstr. 12",
    "sg:city":"Rott",
    "sg:phone":"+49 8039/1021",
    "sg:postcode":"83543",
    "sg:province":"Bayern",
    "wof:name":"Ernst Huber W\u00e4rmetechnik Gmbh",
    "wof:placetype":"venue"
},
  "geometry": {"coordinates":[12.134512,47.98568],"type":"Point"}
}