{
  "type": "Feature",
  "properties": {
    "iso:country":"DE",
    "sg:address":"Buscherkamp 36",
    "sg:city":"Erkelenz",
    "sg:phone":"+49 2431/4620",
    "sg:postcode":"41812",
    "sg:province":"Nordrhein-Westfalen",
    "wof:name":"S. Erksen",
    "wof:placetype":"venue"
},
  "geometry": {"coordinates":[6.3149819374,51.0874176025],"type":"Point"}
}