{
  "type": "Feature",
  "properties": {
    "iso:country":"DE",
    "sg:address":"In Rieda 51",
    "sg:city":"Verden",
    "sg:phone":"+49 4231/83584",
    "sg:postcode":"27283",
    "sg:province":"Niedersachsen",
    "wof:name":"Wilhelm Br\u00fcmmer",
    "wof:placetype":"venue"
},
  "geometry": {"coordinates":[9.1983509064,52.883392334],"type":"Point"}
}