{
  "type": "Feature",
  "properties": {
    "iso:country":"DE",
    "sg:address":"Hauptstr. 27",
    "sg:city":"B\u00e4rnsdorf",
    "sg:phone":"+49 35207/81481",
    "sg:postcode":"01471",
    "sg:province":"Sachsen",
    "wof:name":"L. Kie\u00dfling",
    "wof:placetype":"venue"
},
  "geometry": {"coordinates":[13.726401329,51.165473938],"type":"Point"}
}