{
  "type": "Feature",
  "properties": {
    "iso:country":"DE",
    "sg:address":"Kapit\u00e4n-von-Schiller-Str. 18",
    "sg:city":"Neu-Isenburg",
    "sg:phone":"+49 69/691625",
    "sg:postcode":"63263",
    "sg:province":"Hessen",
    "wof:name":"I.-v. Tomberg Heilpraktiker",
    "wof:placetype":"venue"
},
  "geometry": {"coordinates":[8.6088018417,50.0334510803],"type":"Point"}
}