{
  "type": "Feature",
  "properties": {
    "iso:country":"DE",
    "sg:address":"Hans-Sachs-Str. 10",
    "sg:city":"Hilden",
    "sg:phone":"+49 2103/36880",
    "sg:postcode":"40721",
    "sg:province":"Nordrhein-Westfalen",
    "wof:name":"Notifier Sicherungs- Systeme Gmbh",
    "wof:placetype":"venue"
},
  "geometry": {"coordinates":[6.919915,51.173504],"type":"Point"}
}