{
  "type": "Feature",
  "properties": {
    "iso:country":"DE",
    "sg:address":"Waldallee 57",
    "sg:city":"Eppstein",
    "sg:phone":"+49 6198/2944",
    "sg:postcode":"65817",
    "sg:province":"Hessen",
    "wof:name":"Comm-soft Gmbh",
    "wof:placetype":"venue"
},
  "geometry": {"coordinates":[8.357339859,50.1350097656],"type":"Point"}
}