{
  "type": "Feature",
  "properties": {
    "iso:country":"DE",
    "sg:address":"Kr\u00e4melweg 9a",
    "sg:city":"Steinen",
    "sg:phone":"+49 7627/8410",
    "sg:postcode":"79585",
    "sg:province":"Baden-W\u00fcrttemberg",
    "wof:name":"W. L\u00e4uger Jun.",
    "wof:placetype":"venue"
},
  "geometry": {"coordinates":[7.739669,47.691044],"type":"Point"}
}