{
  "type": "Feature",
  "properties": {
    "iso:country":"DE",
    "sg:address":"B\u00fcrgerstr. 1",
    "sg:city":"Hannover",
    "sg:phone":"+49 511/664444",
    "sg:postcode":"30161",
    "sg:province":"Niedersachsen",
    "wof:name":"Artur Brandt",
    "wof:placetype":"venue"
},
  "geometry": {"coordinates":[9.748796463,52.3872375488],"type":"Point"}
}