{
  "type": "Feature",
  "properties": {
    "iso:country":"DE",
    "sg:address":"Moosstr. 2",
    "sg:city":"Windach",
    "sg:phone":"+49 8193/8044",
    "sg:postcode":"86949",
    "sg:province":"Bayern",
    "wof:name":"Hans Schmidkonz Steuerberater",
    "wof:placetype":"venue"
},
  "geometry": {"coordinates":[11.0347661972,48.0693778992],"type":"Point"}
}