{
  "type": "Feature",
  "properties": {
    "iso:country":"DE",
    "sg:address":"Tulpenweg 18",
    "sg:city":"Gotha",
    "sg:postcode":"99867",
    "sg:province":"Th\u00fcringen",
    "wof:name":"Treff-vertriebs Gmbh",
    "wof:placetype":"venue"
},
  "geometry": {"coordinates":[10.673091,50.934345],"type":"Point"}
}