{
  "type": "Feature",
  "properties": {
    "iso:country":"DE",
    "sg:address":"Vorschlehern 1",
    "sg:city":"Bammental",
    "sg:phone":"+49 6223/95240",
    "sg:postcode":"69245",
    "sg:province":"Baden-W\u00fcrttemberg",
    "wof:name":"Friedrich B\u00e4hr Baustoffe Und Fliesen",
    "wof:placetype":"venue"
},
  "geometry": {"coordinates":[8.7685613632,49.3485717773],"type":"Point"}
}