{
  "type": "Feature",
  "properties": {
    "iso:country":"DE",
    "sg:address":"Klein-Laudenbach",
    "sg:city":"Karlstadt",
    "sg:phone":"+49 9353/7479",
    "sg:postcode":"97753",
    "sg:province":"Bayern",
    "wof:name":"B. Mehling",
    "wof:placetype":"venue"
},
  "geometry": {"coordinates":[9.763756,49.950249],"type":"Point"}
}