{
  "type": "Feature",
  "properties": {
    "iso:country":"DE",
    "sg:address":"Hansastr 6",
    "sg:city":"Dresden",
    "sg:phone":"+49 351/5023823",
    "sg:postcode":"01097",
    "sg:province":"Sachsen",
    "wof:name":"Deutsche Verkehrs-bank Ag",
    "wof:placetype":"venue"
},
  "geometry": {"coordinates":[13.739499,51.067066],"type":"Point"}
}