{
  "type": "Feature",
  "properties": {
    "iso:country":"DE",
    "sg:address":"Langenhorner Chaussee 137",
    "sg:city":"Hamburg",
    "sg:phone":"+49 40/5317962",
    "sg:postcode":"22415",
    "sg:province":"Hamburg",
    "wof:name":"Helmut Axtner",
    "wof:placetype":"venue"
},
  "geometry": {"coordinates":[10.012839,53.643967],"type":"Point"}
}