{
  "type": "Feature",
  "properties": {
    "iso:country":"DE",
    "sg:address":"Kirchstr. 16",
    "sg:city":"Rosbach",
    "sg:phone":"+49 6003/3817",
    "sg:postcode":"61191",
    "sg:province":"Hessen",
    "wof:name":"Daniela Meuer U. Renate M\u00fcller",
    "wof:placetype":"venue"
},
  "geometry": {"coordinates":[8.688998,50.304695],"type":"Point"}
}