{
  "type": "Feature",
  "properties": {
    "iso:country":"DE",
    "sg:address":"Dr.-Alfred-Herrhausen-Allee 32",
    "sg:city":"Duisburg",
    "sg:postcode":"47228",
    "sg:province":"Nordrhein-Westfalen",
    "wof:name":"Zukunft Industrie- Und Werkzeugmaschinen Handels Gmbh",
    "wof:placetype":"venue"
},
  "geometry": {"coordinates":[6.6982998848,51.43019104],"type":"Point"}
}