{
  "type": "Feature",
  "properties": {
    "iso:country":"DE",
    "sg:address":"Br\u00fcckenstr. 13",
    "sg:city":"Eitorf",
    "sg:phone":"+49 2243/2786",
    "sg:postcode":"53783",
    "sg:province":"Nordrhein-Westfalen",
    "wof:name":"Robert Auth",
    "wof:placetype":"venue"
},
  "geometry": {"coordinates":[7.449827,50.771709],"type":"Point"}
}