{
  "type": "Feature",
  "properties": {
    "iso:country":"DE",
    "sg:address":"Herrenberger Str. 14",
    "sg:city":"Nufringen",
    "sg:phone":"+49 7032/83745",
    "sg:postcode":"71154",
    "sg:province":"Baden-W\u00fcrttemberg",
    "wof:name":"Doc Computer Gmbh",
    "wof:placetype":"venue"
},
  "geometry": {"coordinates":[8.887339592,48.6213684082],"type":"Point"}
}