{
  "type": "Feature",
  "properties": {
    "iso:country":"DE",
    "sg:address":"Buchbichl 52",
    "sg:city":"Irschenberg",
    "sg:phone":"+49 8020/281042",
    "sg:postcode":"83737",
    "sg:province":"Bayern",
    "wof:name":"Holistic Diagcenter",
    "wof:placetype":"venue"
},
  "geometry": {"coordinates":[11.892131,47.819283],"type":"Point"}
}