{
  "type": "Feature",
  "properties": {
    "iso:country":"DE",
    "sg:address":"Hauptstr. 6",
    "sg:city":"Leck",
    "sg:phone":"+49 4662/2665",
    "sg:postcode":"25917",
    "sg:province":"Schleswig-Holstein",
    "wof:name":"Helmut Sch\u00fctt",
    "wof:placetype":"venue"
},
  "geometry": {"coordinates":[8.975822,54.771301],"type":"Point"}
}