{
  "type": "Feature",
  "properties": {
    "iso:country":"DE",
    "sg:address":"Oberer B\u00fcrgla\u00df 21",
    "sg:city":"Coburg",
    "sg:postcode":"96450",
    "sg:province":"Bayern",
    "wof:name":"Auslandskorrespondenten-schule Coburg",
    "wof:placetype":"venue"
},
  "geometry": {"coordinates":[10.966468,50.261711],"type":"Point"}
}