{
  "type": "Feature",
  "properties": {
    "iso:country":"DE",
    "sg:address":"Mentiner Str. 12",
    "sg:city":"Suckow",
    "sg:phone":"+49 38729/20144",
    "sg:postcode":"19376",
    "sg:province":"Mecklenburg-Vorpommern",
    "wof:name":"Dur\u00c4umat Stall-einrichtungen Gmbh & Co. Kg",
    "wof:placetype":"venue"
},
  "geometry": {"coordinates":[11.89395,53.351574],"type":"Point"}
}