{
  "type": "Feature",
  "properties": {
    "iso:country":"DE",
    "sg:address":"Am Backhaus 1",
    "sg:city":"Rheine",
    "sg:phone":"+49 5459/7622",
    "sg:postcode":"48432",
    "sg:province":"Nordrhein-Westfalen",
    "wof:name":"Leo Plenter",
    "wof:placetype":"venue"
},
  "geometry": {"coordinates":[7.533237,52.285172],"type":"Point"}
}