{
  "type": "Feature",
  "properties": {
    "iso:country":"DE",
    "sg:address":"Lotzenweg 38",
    "sg:city":"Wald-Michelbach",
    "sg:phone":"+49 6207/29880",
    "sg:postcode":"69483",
    "sg:province":"Hessen",
    "wof:name":"G\u00e4stehaus Waldfrieden",
    "wof:placetype":"venue"
},
  "geometry": {"coordinates":[8.85665,49.545563],"type":"Point"}
}