{
  "type": "Feature",
  "properties": {
    "iso:country":"DE",
    "sg:address":"Askanierring 40-41",
    "sg:city":"Berlin",
    "sg:phone":"+49 30/3755055",
    "sg:postcode":"13585",
    "sg:province":"Berlin",
    "wof:name":"Helmut Glander Gmbh",
    "wof:placetype":"venue"
},
  "geometry": {"coordinates":[13.193982,52.547791],"type":"Point"}
}