{
  "type": "Feature",
  "properties": {
    "iso:country":"DE",
    "sg:address":"Eckstr. 9",
    "sg:city":"Bad Saulgau",
    "sg:phone":"+49 7371/961510",
    "sg:postcode":"88348",
    "sg:province":"Baden-W\u00fcrttemberg",
    "wof:name":"Communix Informations- Und Datentechnik Gmbh",
    "wof:placetype":"venue"
},
  "geometry": {"coordinates":[9.4993524551,48.0161094666],"type":"Point"}
}