{
  "type": "Feature",
  "properties": {
    "iso:country":"DE",
    "sg:address":"Friedrich-Ebert-Str. 15",
    "sg:city":"F\u00fcrth",
    "sg:phone":"+49 911/7593023",
    "sg:postcode":"90766",
    "sg:province":"Bayern",
    "wof:name":"Star Car",
    "wof:placetype":"venue"
},
  "geometry": {"coordinates":[10.970381,49.483536],"type":"Point"}
}