{
  "type": "Feature",
  "properties": {
    "iso:country":"DE",
    "sg:address":"Offlum",
    "sg:city":"Neuenkirchen",
    "sg:phone":"+49 5973/3469",
    "sg:postcode":"48485",
    "sg:province":"Nordrhein-Westfalen",
    "wof:name":"Gastst\u00e4tte Siegfried Diefenbach",
    "wof:placetype":"venue"
},
  "geometry": {"coordinates":[7.332005024,52.2526931763],"type":"Point"}
}