{
  "type": "Feature",
  "properties": {
    "iso:country":"DE",
    "sg:address":"Reichsstr. 19",
    "sg:city":"D\u00fcsseldorf",
    "sg:phone":"+49 211/392751",
    "sg:postcode":"40217",
    "sg:province":"Nordrhein-Westfalen",
    "wof:name":"Creson & Weber",
    "wof:placetype":"venue"
},
  "geometry": {"coordinates":[6.7708759308,51.2165184021],"type":"Point"}
}