{
  "type": "Feature",
  "properties": {
    "iso:country":"DE",
    "sg:address":"Kurt-Schumacher-Str. 58",
    "sg:city":"Augsburg",
    "sg:phone":"+49 821/720130",
    "sg:postcode":"86165",
    "sg:province":"Bayern",
    "wof:name":"Horle & B\u00f6swillibald Bau- Unternehmung Gmbh & Co. Kg",
    "wof:placetype":"venue"
},
  "geometry": {"coordinates":[10.9286050797,48.3802375793],"type":"Point"}
}