{
  "type": "Feature",
  "properties": {
    "iso:country":"DE",
    "sg:address":"Schlernweg 10",
    "sg:city":"Friedberg",
    "sg:phone":"+49 821/603414",
    "sg:postcode":"86316",
    "sg:province":"Bayern",
    "wof:name":"R. Herr Freizeitbetrieb",
    "wof:placetype":"venue"
},
  "geometry": {"coordinates":[10.994805,48.364586],"type":"Point"}
}