{
  "type": "Feature",
  "properties": {
    "iso:country":"DE",
    "sg:address":"Nelkenstr. 9 a",
    "sg:city":"Rheinm\u00fcnster",
    "sg:phone":"+49 7229/2519",
    "sg:postcode":"77836",
    "sg:province":"Baden-W\u00fcrttemberg",
    "wof:name":"Franz Zimmermann Schiffahrt",
    "wof:placetype":"venue"
},
  "geometry": {"coordinates":[8.003574,48.750027],"type":"Point"}
}