{
  "type": "Feature",
  "properties": {
    "iso:country":"DE",
    "sg:address":"Kranichstr. 15",
    "sg:city":"Butjadingen",
    "sg:phone":"+49 231/814394",
    "sg:postcode":"26969",
    "sg:province":"Niedersachsen",
    "wof:name":"G\u00fcnter Rosendahl",
    "wof:placetype":"venue"
},
  "geometry": {"coordinates":[8.365275,53.572826],"type":"Point"}
}