{
  "type": "Feature",
  "properties": {
    "iso:country":"DE",
    "sg:address":"Markt 3",
    "sg:city":"Tangerm\u00fcnde",
    "sg:phone":"+49 39322/3696",
    "sg:postcode":"39590",
    "sg:province":"Sachsen-Anhalt",
    "wof:name":"M. Wegler",
    "wof:placetype":"venue"
},
  "geometry": {"coordinates":[11.9706439972,52.5408172607],"type":"Point"}
}