{
  "type": "Feature",
  "properties": {
    "iso:country":"DE",
    "sg:address":"Einsteinstr. 12-14",
    "sg:city":"Mannheim",
    "sg:postcode":"68169",
    "sg:province":"Baden-W\u00fcrttemberg",
    "wof:name":"Schweissring Handels Gmbh",
    "wof:placetype":"venue"
},
  "geometry": {"coordinates":[8.457971,49.517586],"type":"Point"}
}