{
  "type": "Feature",
  "properties": {
    "iso:country":"DE",
    "sg:address":"Kaiserstr. 79",
    "sg:city":"Radevormwald",
    "sg:phone":"+49 2195/1050",
    "sg:postcode":"42477",
    "sg:province":"Nordrhein-Westfalen",
    "wof:name":"Hotel-restaurant Zur Post",
    "wof:placetype":"venue"
},
  "geometry": {"coordinates":[7.3579778671,51.202835083],"type":"Point"}
}