{
  "type": "Feature",
  "properties": {
    "iso:country":"DE",
    "sg:address":"H\u00f6henstr. 13",
    "sg:city":"Roth",
    "sg:phone":"+49 6772/2501",
    "sg:postcode":"56368",
    "sg:province":"Rheinland-Pfalz",
    "wof:name":"Ursula Amend Steuerberaterin",
    "wof:placetype":"venue"
},
  "geometry": {"coordinates":[7.8951301575,50.2688598633],"type":"Point"}
}