{
  "type": "Feature",
  "properties": {
    "iso:country":"DE",
    "sg:address":"Schlo\u00dfstr. 31-33",
    "sg:city":"Neuwied",
    "sg:phone":"+49 2631/358486",
    "sg:postcode":"56564",
    "sg:province":"Rheinland-Pfalz",
    "wof:name":"Privaphone Shop Gmbh",
    "wof:placetype":"venue"
},
  "geometry": {"coordinates":[7.4578518867,50.4296226501],"type":"Point"}
}