{
  "type": "Feature",
  "properties": {
    "iso:country":"DE",
    "sg:address":"Hauptstr. 12",
    "sg:city":"Gro\u00dfharthau-B\u00fchlau",
    "sg:phone":"+49 35954/50231",
    "sg:postcode":"01909",
    "sg:province":"Sachsen",
    "wof:name":"Uwe H\u00e4ntzschel",
    "wof:placetype":"venue"
},
  "geometry": {"coordinates":[14.1070041656,51.1308746338],"type":"Point"}
}