{
  "type": "Feature",
  "properties": {
    "iso:country":"DE",
    "sg:address":"Crimmitschauer Str. 3",
    "sg:city":"Schm\u00f6lln",
    "sg:phone":"+49 34491/83232",
    "sg:postcode":"04626",
    "sg:province":"Th\u00fcringen",
    "wof:name":"Inge Wittig",
    "wof:placetype":"venue"
},
  "geometry": {"coordinates":[12.351258,50.894459],"type":"Point"}
}