{
  "type": "Feature",
  "properties": {
    "iso:country":"DE",
    "sg:address":"-K.A.",
    "sg:city":"Kaltenkirchen",
    "sg:postcode":"24568",
    "sg:province":"Schleswig-Holstein",
    "wof:name":"Olymp Immobilien Gmbh",
    "wof:placetype":"venue"
},
  "geometry": {"coordinates":[9.9597969055,53.8381271362],"type":"Point"}
}