{
  "type": "Feature",
  "properties": {
    "iso:country":"DE",
    "sg:address":"An der Trift 1",
    "sg:city":"Weimar",
    "sg:phone":"+49 3643/59624",
    "sg:postcode":"99425",
    "sg:province":"Th\u00fcringen",
    "wof:name":"W. Luley",
    "wof:placetype":"venue"
},
  "geometry": {"coordinates":[11.346089,50.957432],"type":"Point"}
}