{
  "type": "Feature",
  "properties": {
    "iso:country":"DE",
    "sg:address":"Burgstr. 11",
    "sg:city":"Kempen",
    "sg:phone":"+49 2152/3451",
    "sg:postcode":"47906",
    "sg:province":"Nordrhein-Westfalen",
    "wof:name":"G. Kaatz",
    "wof:placetype":"venue"
},
  "geometry": {"coordinates":[6.4212040901,51.3648681641],"type":"Point"}
}