{
  "type": "Feature",
  "properties": {
    "iso:country":"DE",
    "sg:address":"Gau\u00dfstr. 194",
    "sg:city":"Hamburg",
    "sg:phone":"+49 40/397729",
    "sg:postcode":"22765",
    "sg:province":"Hamburg",
    "wof:name":"Hans R\u00f6pcke Grundst\u00fccksverwaltung Gmbh",
    "wof:placetype":"venue"
},
  "geometry": {"coordinates":[9.9229640961,53.5587348938],"type":"Point"}
}