{
  "type": "Feature",
  "properties": {
    "iso:country":"DE",
    "sg:address":"Hermannplatz 9",
    "sg:city":"Berlin",
    "sg:phone":"+49 30/6237046",
    "sg:postcode":"10967",
    "sg:province":"Berlin",
    "wof:name":"Apotheke Am Hermannplatz P\u00e4chter Frank Noetzel",
    "wof:placetype":"venue"
},
  "geometry": {"coordinates":[13.425509,52.487434],"type":"Point"}
}