{
  "type": "Feature",
  "properties": {
    "iso:country":"DE",
    "sg:address":"Auricher Str. 150",
    "sg:city":"Emden",
    "sg:phone":"+49 4921/8960",
    "sg:postcode":"26721",
    "sg:province":"Niedersachsen",
    "wof:name":"Daimler-benz Ag",
    "wof:placetype":"venue"
},
  "geometry": {"coordinates":[7.2079668045,53.3864364624],"type":"Point"}
}