{
  "type": "Feature",
  "properties": {
    "iso:country":"DE",
    "sg:address":"G\u00e4rtnerstr. 6",
    "sg:city":"Ammerbuch",
    "sg:postcode":"72119",
    "sg:province":"Baden-W\u00fcrttemberg",
    "wof:name":"Welte Druckereitechnik Gmbh",
    "wof:placetype":"venue"
},
  "geometry": {"coordinates":[8.9670448303,48.5520553589],"type":"Point"}
}