{
  "type": "Feature",
  "properties": {
    "iso:country":"DE",
    "sg:address":"Allmendstr. 13 Mietersheim",
    "sg:city":"Lahr",
    "sg:phone":"+49 4978/2158060",
    "sg:postcode":"77933",
    "sg:province":"Baden-W\u00fcrttemberg",
    "wof:name":"M\u00d6belhaus Des Schreinerhandwerks Gmbh & Co Kg",
    "wof:placetype":"venue"
},
  "geometry": {"coordinates":[7.876033783,48.3401756287],"type":"Point"}
}