{
  "type": "Feature",
  "properties": {
    "iso:country":"DE",
    "sg:address":"Friedensstr. 43",
    "sg:city":"Reichenbach",
    "sg:phone":"+49 3765/78880",
    "sg:postcode":"08468",
    "sg:province":"Sachsen",
    "wof:name":"Reichenbach Gmbh",
    "wof:placetype":"venue"
},
  "geometry": {"coordinates":[12.658382,50.835976],"type":"Point"}
}