{
  "type": "Feature",
  "properties": {
    "iso:country":"DE",
    "sg:address":"Wiltmann-Kleine-Str. 16",
    "sg:city":"Versmold",
    "sg:phone":"+49 5423/170",
    "sg:postcode":"33775",
    "sg:province":"Nordrhein-Westfalen",
    "wof:name":"Archiv Der Franz Wiltmann Gmbh & Co.",
    "wof:placetype":"venue"
},
  "geometry": {"coordinates":[8.142969,52.038177],"type":"Point"}
}