{
  "type": "Feature",
  "properties": {
    "iso:country":"DE",
    "sg:address":"An der Aue 10",
    "sg:city":"Ellerbek",
    "sg:postcode":"25474",
    "sg:province":"Schleswig-Holstein",
    "wof:name":"Bsh Marketing Kg",
    "wof:placetype":"venue"
},
  "geometry": {"coordinates":[9.9005670547,53.6509170532],"type":"Point"}
}