{
  "type": "Feature",
  "properties": {
    "iso:country":"DE",
    "sg:address":"Dorfstr. 52a",
    "sg:city":"Laasdorf",
    "sg:phone":"+49 36428/40719",
    "sg:postcode":"07646",
    "sg:province":"Th\u00fcringen",
    "wof:name":"Laasdorfer Gem\u00fcse",
    "wof:placetype":"venue"
},
  "geometry": {"coordinates":[11.669960022,50.8704414368],"type":"Point"}
}