{
  "type": "Feature",
  "properties": {
    "iso:country":"DE",
    "sg:address":"Langemarckstr. 32",
    "sg:city":"Essen",
    "sg:phone":"+49 201/294000",
    "sg:postcode":"45141",
    "sg:province":"Nordrhein-Westfalen",
    "wof:name":"Fritz Berger Gmbh",
    "wof:placetype":"venue"
},
  "geometry": {"coordinates":[7.0557751656,51.473449707],"type":"Point"}
}