{
  "type": "Feature",
  "properties": {
    "iso:country":"DE",
    "sg:address":"Wolfener Str. 68",
    "sg:city":"Greppin",
    "sg:phone":"+49 3493/20107",
    "sg:postcode":"06803",
    "sg:province":"Sachsen-Anhalt",
    "wof:name":"Kramer & W\u00fcnsch Gbr",
    "wof:placetype":"venue"
},
  "geometry": {"coordinates":[12.298665,51.643101],"type":"Point"}
}