{
  "type": "Feature",
  "properties": {
    "iso:country":"DE",
    "sg:address":"Adelsreute 10",
    "sg:city":"Ravensburg",
    "sg:phone":"+49 751/93623",
    "sg:postcode":"88213",
    "sg:province":"Baden-W\u00fcrttemberg",
    "wof:name":"Hermann Brugger",
    "wof:placetype":"venue"
},
  "geometry": {"coordinates":[9.539433,47.740578],"type":"Point"}
}