{
  "type": "Feature",
  "properties": {
    "iso:country":"DE",
    "sg:address":"Lindenstr. 24",
    "sg:city":"Kleinbodungen",
    "sg:phone":"+49 36338/41579",
    "sg:postcode":"99752",
    "sg:province":"Th\u00fcringen",
    "wof:name":"Friedrich Lange",
    "wof:placetype":"venue"
},
  "geometry": {"coordinates":[10.53008,51.468525],"type":"Point"}
}