{
  "type": "Feature",
  "properties": {
    "iso:country":"DE",
    "sg:address":"Darmst\u00e4dter Landstr. 11",
    "sg:city":"Weiterstadt",
    "sg:phone":"+49 6150/51025",
    "sg:postcode":"64331",
    "sg:province":"Hessen",
    "wof:name":"Hotel-restaurant Zum L\u00f6wen",
    "wof:placetype":"venue"
},
  "geometry": {"coordinates":[8.5808668137,49.9055137634],"type":"Point"}
}