{
  "type": "Feature",
  "properties": {
    "iso:country":"DE",
    "sg:address":"Schneppenhorststr. 65",
    "sg:city":"N\u00fcrnberg",
    "sg:phone":"+49 911/652710",
    "sg:postcode":"90439",
    "sg:province":"Bayern",
    "wof:name":"R. K\u00f6hler",
    "wof:placetype":"venue"
},
  "geometry": {"coordinates":[11.040468,49.438347],"type":"Point"}
}