{
  "type": "Feature",
  "properties": {
    "iso:country":"DE",
    "sg:address":"Am F\u00f6rsterberg 4",
    "sg:city":"Neusch\u00f6nau",
    "sg:phone":"+49 8552/920412",
    "sg:postcode":"94556",
    "sg:province":"Bayern",
    "wof:name":"Gasthaus-pension Bl\u00f6chinger",
    "wof:placetype":"venue"
},
  "geometry": {"coordinates":[13.4649782181,48.9062271118],"type":"Point"}
}