{
  "type": "Feature",
  "properties": {
    "iso:country":"DE",
    "sg:address":"Prenzlauer Str. 21",
    "sg:city":"Neubrandenburg",
    "sg:phone":"+49 395/4225426",
    "sg:postcode":"17034",
    "sg:province":"Mecklenburg-Vorpommern",
    "wof:name":"Monika Olbrich",
    "wof:placetype":"venue"
},
  "geometry": {"coordinates":[13.275843,53.566769],"type":"Point"}
}