{
  "type": "Feature",
  "properties": {
    "iso:country":"DE",
    "sg:address":"Hugo-Keller-Str. 15-16",
    "sg:city":"G\u00f6rlitz",
    "sg:phone":"+49 3581/48490",
    "sg:postcode":"02826",
    "sg:province":"Sachsen",
    "wof:name":"Srg Stadtreinigungs G\u00f6rlitz Gmbh",
    "wof:placetype":"venue"
},
  "geometry": {"coordinates":[14.987512,51.157307],"type":"Point"}
}