{
  "type": "Feature",
  "properties": {
    "iso:country":"DE",
    "sg:address":"Beuerlbacher Str. 39",
    "sg:city":"Crailsheim",
    "sg:postcode":"74564",
    "sg:province":"Baden-W\u00fcrttemberg",
    "wof:name":"Kath. \u00d6ffentliche B\u00fccherei St. Bonifatius",
    "wof:placetype":"venue"
},
  "geometry": {"coordinates":[10.076872,49.141369],"type":"Point"}
}