{
  "type": "Feature",
  "properties": {
    "iso:country":"DE",
    "sg:address":"Metzer Str. 112",
    "sg:city":"Saarbr\u00fccken",
    "sg:phone":"+49 681/52475",
    "sg:postcode":"66117",
    "sg:province":"Saarland",
    "wof:name":"Total Tankstelle",
    "wof:placetype":"venue"
},
  "geometry": {"coordinates":[6.97062397,49.2202148438],"type":"Point"}
}