{
  "type": "Feature",
  "properties": {
    "iso:country":"DE",
    "sg:address":"Rheindorfer Str. 7-11",
    "sg:city":"Bonn",
    "sg:phone":"+49 228/466681",
    "sg:postcode":"53225",
    "sg:province":"Nordrhein-Westfalen",
    "wof:name":"Heinrich Ludwig Gmbh",
    "wof:placetype":"venue"
},
  "geometry": {"coordinates":[7.1180491447,50.740196228],"type":"Point"}
}