{
  "type": "Feature",
  "properties": {
    "iso:country":"DE",
    "sg:address":"D\u00fcnenstr. 1",
    "sg:city":"Seebad Ahlbeck",
    "sg:postcode":"17419",
    "sg:province":"Mecklenburg-Vorpommern",
    "wof:name":"Bau- Und Verwaltungsges. Insel Usedom Gmbh",
    "wof:placetype":"venue"
},
  "geometry": {"coordinates":[14.0651,53.886711],"type":"Point"}
}