{
  "type": "Feature",
  "properties": {
    "iso:country":"DE",
    "sg:address":"Stuckbergstr. 2a",
    "sg:city":"Bayreuth",
    "sg:phone":"+49 921/21345",
    "sg:postcode":"95448",
    "sg:province":"Bayern",
    "wof:name":"Renate Semmler Krankengymnastin",
    "wof:placetype":"venue"
},
  "geometry": {"coordinates":[11.587209,49.950863],"type":"Point"}
}