{
  "type": "Feature",
  "properties": {
    "iso:country":"DE",
    "sg:address":"Bergstr. 23",
    "sg:city":"Zehren",
    "sg:postcode":"01665",
    "sg:province":"Sachsen",
    "wof:name":"Evangelisches Pfarramt",
    "wof:placetype":"venue"
},
  "geometry": {"coordinates":[13.4051303864,51.2000389099],"type":"Point"}
}