{
  "type": "Feature",
  "properties": {
    "iso:country":"DE",
    "sg:address":"Sonnenstr. 2 b",
    "sg:city":"Karlsruhe",
    "sg:phone":"+49 721/593342",
    "sg:postcode":"76185",
    "sg:province":"Baden-W\u00fcrttemberg",
    "wof:name":"Ernst Sonner",
    "wof:placetype":"venue"
},
  "geometry": {"coordinates":[8.359458,49.01469],"type":"Point"}
}