{
  "type": "Feature",
  "properties": {
    "iso:country":"DE",
    "sg:address":"R\u00fcckertstr. 30",
    "sg:city":"Neustadt",
    "sg:phone":"+49 9161/3563",
    "sg:postcode":"91413",
    "sg:province":"Bayern",
    "wof:name":"Dr. Ottmar Fick Tierarzt",
    "wof:placetype":"venue"
},
  "geometry": {"coordinates":[8.7996425629,53.0708808899],"type":"Point"}
}