{
  "type": "Feature",
  "properties": {
    "iso:country":"DE",
    "sg:address":"Schubertstr. 3",
    "sg:city":"M\u00f6rlenbach",
    "sg:phone":"+49 6209/5720",
    "sg:postcode":"69509",
    "sg:province":"Hessen",
    "wof:name":"Christine Lange",
    "wof:placetype":"venue"
},
  "geometry": {"coordinates":[8.7394742966,49.6051864624],"type":"Point"}
}