{
  "type": "Feature",
  "properties": {
    "iso:country":"DE",
    "sg:address":"Bardroffstr. 1",
    "sg:city":"Aschaffenburg",
    "sg:phone":"+49 6021/24456",
    "sg:postcode":"63739",
    "sg:province":"Bayern",
    "wof:name":"Radio Namyslo Service Gmbh",
    "wof:placetype":"venue"
},
  "geometry": {"coordinates":[9.151696,49.96991],"type":"Point"}
}