{
  "type": "Feature",
  "properties": {
    "iso:country":"DE",
    "sg:address":"Friedhofstr. 9",
    "sg:city":"Witten",
    "sg:postcode":"58453",
    "sg:province":"Nordrhein-Westfalen",
    "wof:name":"Djk Blau-wei\u00df Annen Ursula Hoffmeister",
    "wof:placetype":"venue"
},
  "geometry": {"coordinates":[7.3676538467,51.4506835938],"type":"Point"}
}