{
  "type": "Feature",
  "properties": {
    "iso:country":"DE",
    "sg:address":"Farrenstr. 41",
    "sg:city":"Stuttgart",
    "sg:phone":"+49 711/465071",
    "sg:postcode":"70186",
    "sg:province":"Baden-W\u00fcrttemberg",
    "wof:name":"Richard Kr\u00fcger",
    "wof:placetype":"venue"
},
  "geometry": {"coordinates":[9.2002048492,48.7723121643],"type":"Point"}
}