{
  "type": "Feature",
  "properties": {
    "iso:country":"DE",
    "sg:address":"Bonnstr. 453 A",
    "sg:city":"Br\u00fchl",
    "sg:phone":"+49 2232/31894",
    "sg:postcode":"50321",
    "sg:province":"Nordrhein-Westfalen",
    "wof:name":"Petra Piche",
    "wof:placetype":"venue"
},
  "geometry": {"coordinates":[6.914836,50.800877],"type":"Point"}
}