{
  "type": "Feature",
  "properties": {
    "iso:country":"DE",
    "sg:address":"Bremer Weg 160",
    "sg:city":"Celle",
    "sg:phone":"+49 5141/950400",
    "sg:postcode":"29223",
    "sg:province":"Niedersachsen",
    "wof:name":"Deutsche Bp Gmbh",
    "wof:placetype":"venue"
},
  "geometry": {"coordinates":[10.0566310883,52.6358566284],"type":"Point"}
}