{
  "type": "Feature",
  "properties": {
    "iso:country":"DE",
    "sg:address":"Steinstr. 28",
    "sg:city":"Herford",
    "sg:phone":"+49 5221/51644",
    "sg:postcode":"32052",
    "sg:province":"Nordrhein-Westfalen",
    "wof:name":"Pianka",
    "wof:placetype":"venue"
},
  "geometry": {"coordinates":[8.665479,52.11594],"type":"Point"}
}