{
  "type": "Feature",
  "properties": {
    "iso:country":"DE",
    "sg:address":"Hegelstr. 11a",
    "sg:city":"Bamberg",
    "sg:phone":"+49 951/34097",
    "sg:postcode":"96052",
    "sg:province":"Bayern",
    "wof:name":"E. Bail",
    "wof:placetype":"venue"
},
  "geometry": {"coordinates":[10.9064331055,49.9055252075],"type":"Point"}
}