{
  "type": "Feature",
  "properties": {
    "iso:country":"DE",
    "sg:address":"Am Markt 2",
    "sg:city":"Wilster",
    "sg:phone":"+49 4823/8244",
    "sg:postcode":"25554",
    "sg:province":"Schleswig-Holstein",
    "wof:name":"Klaus K\u00fchl Elektroinstallation",
    "wof:placetype":"venue"
},
  "geometry": {"coordinates":[9.374433,53.922123],"type":"Point"}
}