{
  "type": "Feature",
  "properties": {
    "iso:country":"DE",
    "sg:address":"Dorfstr. 114",
    "sg:city":"H\u00e4melhausen",
    "sg:phone":"+49 4254/691",
    "sg:postcode":"27324",
    "sg:province":"Niedersachsen",
    "wof:name":"Heinrich Seegelke",
    "wof:placetype":"venue"
},
  "geometry": {"coordinates":[9.27595,52.780998],"type":"Point"}
}