{
  "type": "Feature",
  "properties": {
    "iso:country":"DE",
    "sg:address":"Hohe Str. 33",
    "sg:city":"Zeulenroda",
    "sg:phone":"+49 36628/82345",
    "sg:postcode":"07937",
    "sg:province":"Th\u00fcringen",
    "wof:name":"Dietmar Perzel",
    "wof:placetype":"venue"
},
  "geometry": {"coordinates":[11.984886,50.646618],"type":"Point"}
}