{
  "type": "Feature",
  "properties": {
    "iso:country":"DE",
    "sg:address":"Kahlenstr. 31-33",
    "sg:city":"Lippstadt",
    "sg:phone":"+49 2941/59676",
    "sg:postcode":"59555",
    "sg:province":"Nordrhein-Westfalen",
    "wof:name":"Fachner In Lippstadt - B\u00fccher Und Kunsthandwerk",
    "wof:placetype":"venue"
},
  "geometry": {"coordinates":[8.343955,51.673363],"type":"Point"}
}