{
  "type": "Feature",
  "properties": {
    "iso:country":"DE",
    "sg:address":"Westerstr. 7",
    "sg:city":"Dornum",
    "sg:phone":"+49 4933/914096",
    "sg:postcode":"26553",
    "sg:province":"Niedersachsen",
    "wof:name":"Ambulanter Alten- Und Kranken- Pfegedienst In Ostfriesland",
    "wof:placetype":"venue"
},
  "geometry": {"coordinates":[7.42633,53.646999],"type":"Point"}
}