{
  "type": "Feature",
  "properties": {
    "iso:country":"DE",
    "sg:address":"Ernst-Ludwig-Str. 26",
    "sg:city":"Breuberg",
    "sg:phone":"+49 6163/2285",
    "sg:postcode":"64747",
    "sg:province":"Hessen",
    "wof:name":"Heinrich Heusel",
    "wof:placetype":"venue"
},
  "geometry": {"coordinates":[9.016740799,49.8202133179],"type":"Point"}
}