{
  "type": "Feature",
  "properties": {
    "iso:country":"DE",
    "sg:address":"Hohenst\u00e4dter Str. 53",
    "sg:city":"Happurg",
    "sg:postcode":"91230",
    "sg:province":"Bayern",
    "wof:name":"Sybille K\u00fchnlein Gmbh",
    "wof:placetype":"venue"
},
  "geometry": {"coordinates":[11.4681806564,49.4983673096],"type":"Point"}
}