{
  "type": "Feature",
  "properties": {
    "iso:country":"DE",
    "sg:address":"Gutenbergstr. 42",
    "sg:city":"Ingolstadt",
    "sg:phone":"+49 841/58026",
    "sg:postcode":"85055",
    "sg:province":"Bayern",
    "wof:name":"Restaurant Mandarin",
    "wof:placetype":"venue"
},
  "geometry": {"coordinates":[11.4569320679,48.7724685669],"type":"Point"}
}