{
  "type": "Feature",
  "properties": {
    "iso:country":"DE",
    "sg:address":"Kaulberg 35",
    "sg:city":"Rattelsdorf",
    "sg:phone":"+49 9547/1725",
    "sg:postcode":"96179",
    "sg:province":"Bayern",
    "wof:name":"Georg Ritzer",
    "wof:placetype":"venue"
},
  "geometry": {"coordinates":[10.8896303177,50.0165214539],"type":"Point"}
}