{
  "type": "Feature",
  "properties": {
    "iso:country":"DE",
    "sg:address":"Feldstr. 11",
    "sg:city":"Putbus",
    "sg:phone":"+49 38301/391",
    "sg:postcode":"18581",
    "sg:province":"Mecklenburg-Vorpommern",
    "wof:name":"Dr. Dietmar Schneider Rechtsanwalt",
    "wof:placetype":"venue"
},
  "geometry": {"coordinates":[13.4881238937,54.3694343567],"type":"Point"}
}