{
  "type": "Feature",
  "properties": {
    "iso:country":"DE",
    "sg:address":"Gutenbergstr. 10",
    "sg:city":"Weiterstadt",
    "sg:phone":"+49 6151/537063",
    "sg:postcode":"64331",
    "sg:province":"Hessen",
    "wof:name":"Reiner Hoffmann Rechtsanwalt",
    "wof:placetype":"venue"
},
  "geometry": {"coordinates":[8.6075248718,49.8906555176],"type":"Point"}
}