{
  "type": "Feature",
  "properties": {
    "iso:country":"DE",
    "sg:address":"Rudolf-Diesel-Str. 52",
    "sg:city":"Walldorf",
    "sg:postcode":"69190",
    "sg:province":"Baden-W\u00fcrttemberg",
    "wof:name":"Rast Ges. F. Rohrleitungsbau",
    "wof:placetype":"venue"
},
  "geometry": {"coordinates":[8.6472911835,49.2896575928],"type":"Point"}
}