{
  "type": "Feature",
  "properties": {
    "iso:country":"DE",
    "sg:address":"Im Schulw\u00e4ldchen 10",
    "sg:city":"Niederfischbach",
    "sg:phone":"+49 2734/61905",
    "sg:postcode":"57572",
    "sg:province":"Rheinland-Pfalz",
    "wof:name":"Rosenthal Holz- Und Bautenschutz Gmbh",
    "wof:placetype":"venue"
},
  "geometry": {"coordinates":[7.8809299469,50.8610916138],"type":"Point"}
}