{
  "type": "Feature",
  "properties": {
    "iso:country":"DE",
    "sg:address":"Kettelerstrasse 23",
    "sg:city":"Stockstadt",
    "sg:phone":"+49 6027/401894",
    "sg:postcode":"63811",
    "sg:province":"Bayern",
    "wof:name":"Digitalwerbung Scherer",
    "wof:placetype":"venue"
},
  "geometry": {"coordinates":[9.060446,49.976601],"type":"Point"}
}