{
  "type": "Feature",
  "properties": {
    "iso:country":"DE",
    "sg:address":"Gustav-Mahler-Str. 29",
    "sg:city":"Stuttgart",
    "sg:phone":"+49 711/698065",
    "sg:postcode":"70195",
    "sg:province":"Baden-W\u00fcrttemberg",
    "wof:name":"Bahnm\u00fcller Gmbh",
    "wof:placetype":"venue"
},
  "geometry": {"coordinates":[9.122171402,48.7752456665],"type":"Point"}
}