{
  "type": "Feature",
  "properties": {
    "iso:country":"DE",
    "sg:address":"Reichenberger Str 6",
    "sg:city":"Waldkraiburg",
    "sg:phone":"+49 8638/60030",
    "sg:postcode":"84478",
    "sg:province":"Bayern",
    "wof:name":"Renolit Ag",
    "wof:placetype":"venue"
},
  "geometry": {"coordinates":[12.394164,48.206783],"type":"Point"}
}