{
  "type": "Feature",
  "properties": {
    "iso:country":"DE",
    "sg:address":"Schleusenstr. 4a",
    "sg:city":"Hattingen",
    "sg:phone":"+49 2324/24852",
    "sg:postcode":"45525",
    "sg:province":"Nordrhein-Westfalen",
    "wof:name":"Dichte Gmbh",
    "wof:placetype":"venue"
},
  "geometry": {"coordinates":[7.1705150604,51.4038276672],"type":"Point"}
}