{
  "type": "Feature",
  "properties": {
    "iso:country":"DE",
    "sg:address":"Daimlerstr. 2",
    "sg:city":"Alth\u00fctte",
    "sg:phone":"+49 7183/958580",
    "sg:postcode":"71566",
    "sg:province":"Baden-W\u00fcrttemberg",
    "wof:name":"Mat Maschinen- & Anlagentechnik Gmbh",
    "wof:placetype":"venue"
},
  "geometry": {"coordinates":[9.5777082443,48.9091873169],"type":"Point"}
}