{
  "type": "Feature",
  "properties": {
    "iso:country":"DE",
    "sg:address":"Saalstr. 4",
    "sg:city":"Saalfeld",
    "sg:postcode":"07318",
    "sg:province":"Th\u00fcringen",
    "wof:name":"K. Fankh\u00e4nel",
    "wof:placetype":"venue"
},
  "geometry": {"coordinates":[11.3615074158,50.6483154297],"type":"Point"}
}