{
  "type": "Feature",
  "properties": {
    "iso:country":"DE",
    "sg:address":"Lange Str. 29",
    "sg:city":"Nienburg",
    "sg:phone":"+49 5021/63596",
    "sg:postcode":"31582",
    "sg:province":"Niedersachsen",
    "wof:name":"Chapeau Claque",
    "wof:placetype":"venue"
},
  "geometry": {"coordinates":[9.2069396973,52.6427459717],"type":"Point"}
}