{
  "type": "Feature",
  "properties": {
    "iso:country":"DE",
    "sg:address":"Max-Prinstner-Str. 2",
    "sg:city":"Beilngries",
    "sg:postcode":"92339",
    "sg:province":"Bayern",
    "wof:name":"Bertex Berchinger Textilvertr. Willax & Co. Inh. Hans Willax",
    "wof:placetype":"venue"
},
  "geometry": {"coordinates":[11.4694824219,49.0338973999],"type":"Point"}
}