{
  "type": "Feature",
  "properties": {
    "iso:country":"DE",
    "sg:address":"Bahnhofstr. 68",
    "sg:city":"Chemnitz",
    "sg:phone":"+49 371/643751",
    "sg:postcode":"09111",
    "sg:province":"Sachsen",
    "wof:name":"Rainer Wentzel",
    "wof:placetype":"venue"
},
  "geometry": {"coordinates":[12.918021,50.829994],"type":"Point"}
}