{
  "type": "Feature",
  "properties": {
    "iso:country":"DE",
    "sg:address":"Dornhaldenstr. 10",
    "sg:city":"Stuttgart",
    "sg:phone":"+49 711/6491215",
    "sg:postcode":"70199",
    "sg:province":"Baden-W\u00fcrttemberg",
    "wof:name":"Bruno Haag",
    "wof:placetype":"venue"
},
  "geometry": {"coordinates":[9.1614742279,48.7604637146],"type":"Point"}
}