{
  "type": "Feature",
  "properties": {
    "iso:country":"DE",
    "sg:address":"Scheffelstr. 21",
    "sg:city":"Leipzig",
    "sg:postcode":"04277",
    "sg:province":"Sachsen",
    "wof:name":"Dr. Med. Renate Stolle",
    "wof:placetype":"venue"
},
  "geometry": {"coordinates":[12.369979,51.311661],"type":"Point"}
}