{
  "type": "Feature",
  "properties": {
    "iso:country":"DE",
    "sg:address":"Birkenweg 6",
    "sg:city":"Melsdorf",
    "sg:phone":"+49 4340/9159",
    "sg:postcode":"24109",
    "sg:province":"Schleswig-Holstein",
    "wof:name":"Heike Und Peter Zogs Architekten",
    "wof:placetype":"venue"
},
  "geometry": {"coordinates":[10.026203,54.314102],"type":"Point"}
}