{
  "type": "Feature",
  "properties": {
    "iso:country":"DE",
    "sg:address":"Radldorf 50",
    "sg:city":"Perkam",
    "sg:phone":"+49 9429/490",
    "sg:postcode":"94368",
    "sg:province":"Bayern",
    "wof:name":"H\u00fcttenwirtschaft",
    "wof:placetype":"venue"
},
  "geometry": {"coordinates":[12.4401226044,48.8541107178],"type":"Point"}
}