{
  "type": "Feature",
  "properties": {
    "iso:country":"DE",
    "sg:address":"Kronenweg 81",
    "sg:city":"Wesseling",
    "sg:phone":"+49 2236/45720",
    "sg:postcode":"50389",
    "sg:province":"Nordrhein-Westfalen",
    "wof:name":"Bernd Clemens",
    "wof:placetype":"venue"
},
  "geometry": {"coordinates":[6.9803528786,50.813129425],"type":"Point"}
}