{
  "type": "Feature",
  "properties": {
    "iso:country":"DE",
    "sg:address":"Nettelbeckstr. 8",
    "sg:city":"D\u00fcsseldorf",
    "sg:phone":"+49 211/494111",
    "sg:postcode":"40477",
    "sg:province":"Nordrhein-Westfalen",
    "wof:name":"Eurospar",
    "wof:placetype":"venue"
},
  "geometry": {"coordinates":[6.7832927704,51.2364730835],"type":"Point"}
}