{
  "type": "Feature",
  "properties": {
    "iso:country":"DE",
    "sg:address":"Dekan-Maier-Str. 14 b",
    "sg:city":"Velden",
    "sg:postcode":"84149",
    "sg:province":"Bayern",
    "wof:name":"Plieninger Gmbh",
    "wof:placetype":"venue"
},
  "geometry": {"coordinates":[12.2511081696,48.3635864258],"type":"Point"}
}