{
  "type": "Feature",
  "properties": {
    "iso:country":"DE",
    "sg:address":"Arnheimer Str. 31",
    "sg:city":"D\u00fcsseldorf",
    "sg:phone":"+49 211/403934",
    "sg:postcode":"40489",
    "sg:province":"Nordrhein-Westfalen",
    "wof:name":"M. Erlat",
    "wof:placetype":"venue"
},
  "geometry": {"coordinates":[6.74072,51.303059],"type":"Point"}
}