{
  "type": "Feature",
  "properties": {
    "iso:country":"DE",
    "sg:address":"Feldstr. 273",
    "sg:city":"Herten",
    "sg:phone":"+49 2366/54629",
    "sg:postcode":"45701",
    "sg:province":"Nordrhein-Westfalen",
    "wof:name":"Bauernstube",
    "wof:placetype":"venue"
},
  "geometry": {"coordinates":[7.1171598434,51.6131515503],"type":"Point"}
}