{
  "type": "Feature",
  "properties": {
    "iso:country":"DE",
    "sg:address":"Erlenbachhof 1",
    "sg:city":"Rosenfeld",
    "sg:phone":"+49 7428",
    "sg:postcode":"72348",
    "sg:province":"Baden-W\u00fcrttemberg",
    "wof:name":"Ferienhausvermietung Huonker",
    "wof:placetype":"venue"
},
  "geometry": {"coordinates":[8.7324447632,48.2635803223],"type":"Point"}
}