{
  "type": "Feature",
  "properties": {
    "iso:country":"DE",
    "sg:address":"Fritz-Reuter-Str. 66",
    "sg:city":"Rostock",
    "sg:postcode":"18057",
    "sg:province":"Mecklenburg-Vorpommern",
    "wof:name":"Mecks Verlag Und Marketing Gmbh",
    "wof:placetype":"venue"
},
  "geometry": {"coordinates":[12.1135282516,54.0892868042],"type":"Point"}
}