{
  "type": "Feature",
  "properties": {
    "iso:country":"DE",
    "sg:address":"Heldmanstr. 14",
    "sg:city":"Bad Salzuflen",
    "sg:phone":"+49 5222/81204",
    "sg:postcode":"32108",
    "sg:province":"Nordrhein-Westfalen",
    "wof:name":"Wilhelm Peter Brennstoff- Handlung Ohg",
    "wof:placetype":"venue"
},
  "geometry": {"coordinates":[8.7694101334,52.0754394531],"type":"Point"}
}