{
  "type": "Feature",
  "properties": {
    "iso:country":"DE",
    "sg:address":"Montanusstr. 39",
    "sg:city":"K\u00f6ln",
    "sg:phone":"+49 221/626106",
    "sg:postcode":"51065",
    "sg:province":"Nordrhein-Westfalen",
    "wof:name":"Grund",
    "wof:placetype":"venue"
},
  "geometry": {"coordinates":[7.0126280785,50.9591598511],"type":"Point"}
}