{
  "type": "Feature",
  "properties": {
    "iso:country":"DE",
    "sg:address":"Rosengasse 351-352",
    "sg:city":"Landshut",
    "sg:phone":"+49 871/22990",
    "sg:postcode":"84028",
    "sg:province":"Bayern",
    "wof:name":"Buchhandlung Jos.hochnedersche Johann Von Weitl",
    "wof:placetype":"venue"
},
  "geometry": {"coordinates":[12.1536273956,48.5368537903],"type":"Point"}
}