{
  "type": "Feature",
  "properties": {
    "iso:country":"DE",
    "sg:address":"Untere Hauptstr. 47a",
    "sg:city":"Weiden",
    "sg:phone":"+49 961/44596",
    "sg:postcode":"92637",
    "sg:province":"Bayern",
    "wof:name":"Hefa Inh. Anton Heining",
    "wof:placetype":"venue"
},
  "geometry": {"coordinates":[12.1383361816,49.6268577576],"type":"Point"}
}