{
  "type": "Feature",
  "properties": {
    "iso:country":"DE",
    "sg:address":"Rothenburg 45",
    "sg:city":"M\u00fcnster",
    "sg:postcode":"48143",
    "sg:province":"Nordrhein-Westfalen",
    "wof:name":"M. F. Ehring Zweignieder- Lassung Der N & K Bielefelder",
    "wof:placetype":"venue"
},
  "geometry": {"coordinates":[7.6263008118,51.9607963562],"type":"Point"}
}