{
  "type": "Feature",
  "properties": {
    "iso:country":"DE",
    "sg:address":"Parkstr. 63",
    "sg:city":"G\u00fctersloh",
    "sg:phone":"+49 5241/57049",
    "sg:postcode":"33332",
    "sg:province":"Nordrhein-Westfalen",
    "wof:name":"Kle\u00dfmann Verwaltungs Gmbh",
    "wof:placetype":"venue"
},
  "geometry": {"coordinates":[8.395763,51.896549],"type":"Point"}
}