{
  "type": "Feature",
  "properties": {
    "iso:country":"DE",
    "sg:address":"Feldstr. 36",
    "sg:city":"Siegen",
    "sg:phone":"+49 271/43431",
    "sg:postcode":"57076",
    "sg:province":"Nordrhein-Westfalen",
    "wof:name":"Schneider Drehtechnik",
    "wof:placetype":"venue"
},
  "geometry": {"coordinates":[8.0279798508,50.895690918],"type":"Point"}
}