{
  "type": "Feature",
  "properties": {
    "iso:country":"DE",
    "sg:address":"Schulstr.",
    "sg:city":"Neckarzimmern",
    "sg:phone":"+49 6261/2579",
    "sg:postcode":"74865",
    "sg:province":"Baden-W\u00fcrttemberg",
    "wof:name":"Gemeindebibliothek",
    "wof:placetype":"venue"
},
  "geometry": {"coordinates":[9.132468,49.320881],"type":"Point"}
}