{
  "type": "Feature",
  "properties": {
    "iso:country":"DE",
    "sg:address":"Hechlinger Str.",
    "sg:city":"Heidenheim",
    "sg:phone":"+49 9833/1696",
    "sg:postcode":"91719",
    "sg:province":"Bayern",
    "wof:name":"Camping Hasenm\u00fchle",
    "wof:placetype":"venue"
},
  "geometry": {"coordinates":[10.740528,49.014553],"type":"Point"}
}