{
  "type": "Feature",
  "properties": {
    "iso:country":"DE",
    "sg:address":"Heidstr. 12",
    "sg:city":"Weyhe",
    "sg:phone":"+49 4203/9942",
    "sg:postcode":"28844",
    "sg:province":"Niedersachsen",
    "wof:name":"Diedrich Kuhlmann Architekt",
    "wof:placetype":"venue"
},
  "geometry": {"coordinates":[8.876084,52.976204],"type":"Point"}
}