{
  "type": "Feature",
  "properties": {
    "iso:country":"DE",
    "sg:address":"Bahnhofstr. 39",
    "sg:city":"Rhede",
    "sg:phone":"+49 2872/2384",
    "sg:postcode":"46414",
    "sg:province":"Nordrhein-Westfalen",
    "wof:name":"Blumenhaus Sindermann E. Kfr.",
    "wof:placetype":"venue"
},
  "geometry": {"coordinates":[6.698209,51.836819],"type":"Point"}
}