{
  "type": "Feature",
  "properties": {
    "iso:country":"DE",
    "sg:address":"R\u00f6merstr. 10",
    "sg:city":"Bad Friedrichshall",
    "sg:phone":"+49 7136/8419",
    "sg:postcode":"74177",
    "sg:province":"Baden-W\u00fcrttemberg",
    "wof:name":"L. Grammling Heissmangel",
    "wof:placetype":"venue"
},
  "geometry": {"coordinates":[9.1931085587,49.2340354919],"type":"Point"}
}