{
  "type": "Feature",
  "properties": {
    "iso:country":"DE",
    "sg:address":"Fabrikstr. 15",
    "sg:city":"Singen",
    "sg:phone":"+49 7731/23783",
    "sg:postcode":"78224",
    "sg:province":"Baden-W\u00fcrttemberg",
    "wof:name":"Elektro-gn\u00e4dinger Gmbh",
    "wof:placetype":"venue"
},
  "geometry": {"coordinates":[8.897439,47.718468],"type":"Point"}
}