{
  "type": "Feature",
  "properties": {
    "iso:country":"DE",
    "sg:address":"Rothenkirchener Str. 49",
    "sg:city":"Hartmannsdorf",
    "sg:phone":"+49 37602/66578",
    "sg:postcode":"08107",
    "sg:province":"Sachsen",
    "wof:name":"Landhof Hartmannsdorf Eg",
    "wof:placetype":"venue"
},
  "geometry": {"coordinates":[12.546743,50.592644],"type":"Point"}
}