{
  "type": "Feature",
  "properties": {
    "iso:country":"DE",
    "sg:address":"Vierlander Str. 11a",
    "sg:city":"Geesthacht",
    "sg:phone":"+49 4152/84590",
    "sg:postcode":"21502",
    "sg:province":"Schleswig-Holstein",
    "wof:name":"Mantis Ulv Spr\u00fchger\u00e4te Gmbh",
    "wof:placetype":"venue"
},
  "geometry": {"coordinates":[10.328137,53.436565],"type":"Point"}
}