{
  "type": "Feature",
  "properties": {
    "iso:country":"DE",
    "sg:address":"Vo\u00dfstr. 219",
    "sg:city":"Gladbeck",
    "sg:phone":"+49 2043/293140",
    "sg:postcode":"45966",
    "sg:province":"Nordrhein-Westfalen",
    "wof:name":"E. J\u00fcnger",
    "wof:placetype":"venue"
},
  "geometry": {"coordinates":[6.998779,51.58934],"type":"Point"}
}