{
  "type": "Feature",
  "properties": {
    "iso:country":"DE",
    "sg:address":"Bramfelder Chaussee 197a",
    "sg:city":"Hamburg",
    "sg:phone":"+49 40/6417417",
    "sg:postcode":"22177",
    "sg:province":"Hamburg",
    "wof:name":"Yours Handels Gmbh",
    "wof:placetype":"venue"
},
  "geometry": {"coordinates":[10.07330513,53.6101074219],"type":"Point"}
}