{
  "type": "Feature",
  "properties": {
    "iso:country":"DE",
    "sg:address":"Am Bahnhof 20",
    "sg:city":"Traben-Trarbach",
    "sg:phone":"+49 6541/4235",
    "sg:postcode":"56841",
    "sg:province":"Rheinland-Pfalz",
    "wof:name":"Riemann",
    "wof:placetype":"venue"
},
  "geometry": {"coordinates":[7.119642,49.95113],"type":"Point"}
}