{
  "type": "Feature",
  "properties": {
    "iso:country":"DE",
    "sg:address":"J\u00e4gerweg 46",
    "sg:city":"Nittenau",
    "sg:postcode":"93149",
    "sg:province":"Bayern",
    "wof:name":"T. E. R. -technologie F\u00fcr Entsorgung Und",
    "wof:placetype":"venue"
},
  "geometry": {"coordinates":[12.2902202606,49.2019348145],"type":"Point"}
}