{
  "type": "Feature",
  "properties": {
    "iso:country":"DE",
    "sg:address":"Bachstr. 2",
    "sg:city":"Gro\u00dfwechsungen",
    "sg:phone":"+49 36335/40076",
    "sg:postcode":"99735",
    "sg:province":"Th\u00fcringen",
    "wof:name":"Elke Rothhagen",
    "wof:placetype":"venue"
},
  "geometry": {"coordinates":[10.691072,51.49268],"type":"Point"}
}