{
  "type": "Feature",
  "properties": {
    "iso:country":"DE",
    "sg:address":"Pfaffenhofen",
    "sg:city":"Pfaffenhofen",
    "sg:phone":"+49 7046/344",
    "sg:postcode":"74397",
    "sg:province":"Baden-W\u00fcrttemberg",
    "wof:name":"Kreissparkasse Heilbronn",
    "wof:placetype":"venue"
},
  "geometry": {"coordinates":[8.977104,49.064011],"type":"Point"}
}