{
  "type": "Feature",
  "properties": {
    "iso:country":"DE",
    "sg:address":"Herzog-Georg-Str. 30",
    "sg:city":"Bad Liebenstein",
    "sg:phone":"+49 36961/31593",
    "sg:postcode":"36448",
    "sg:province":"Th\u00fcringen",
    "wof:name":"Brenn Und Hillmann",
    "wof:placetype":"venue"
},
  "geometry": {"coordinates":[10.3528347015,50.8153839111],"type":"Point"}
}