{
  "type": "Feature",
  "properties": {
    "iso:country":"DE",
    "sg:address":"Am M\u00fchlberg 15",
    "sg:city":"Langg\u00f6ns",
    "sg:phone":"+49 6403/3636",
    "sg:postcode":"35428",
    "sg:province":"Hessen",
    "wof:name":"Martin R\u00fcb Rechtsanwalt",
    "wof:placetype":"venue"
},
  "geometry": {"coordinates":[8.6661634445,50.4964561462],"type":"Point"}
}