{
  "type": "Feature",
  "properties": {
    "iso:country":"DE",
    "sg:address":"Marktstr 83",
    "sg:city":"Neuwied",
    "sg:phone":"+49 2631/999777",
    "sg:postcode":"56564",
    "sg:province":"Rheinland-Pfalz",
    "wof:name":"Thielker & Team Werbeagentur Gmbh",
    "wof:placetype":"venue"
},
  "geometry": {"coordinates":[7.45775,50.426025],"type":"Point"}
}