{
  "type": "Feature",
  "properties": {
    "iso:country":"DE",
    "sg:address":"Sch\u00fctzenstr. 1",
    "sg:city":"Immenstadt",
    "sg:postcode":"87509",
    "sg:province":"Bayern",
    "wof:name":"Bpr-richtmann- Ag",
    "wof:placetype":"venue"
},
  "geometry": {"coordinates":[10.219333,47.561371],"type":"Point"}
}