{
  "type": "Feature",
  "properties": {
    "iso:country":"DE",
    "sg:address":"Naruto-Str. 82",
    "sg:city":"L\u00fcneburg",
    "sg:phone":"+49 4131/66142",
    "sg:postcode":"21339",
    "sg:province":"Niedersachsen",
    "wof:name":"Terwort-transporte",
    "wof:placetype":"venue"
},
  "geometry": {"coordinates":[10.3837709427,53.270488739],"type":"Point"}
}