{
  "type": "Feature",
  "properties": {
    "iso:country":"DE",
    "sg:address":"Bahnhofstra\u00dfe 45",
    "sg:city":"hagen",
    "sg:phone":"+49 2331/9219119",
    "sg:postcode":"58095",
    "sg:province":"Nordrhein-Westfalen",
    "wof:name":"Viag Interkom -partnershop- Hagen-menden-schwerte",
    "wof:placetype":"venue"
},
  "geometry": {"coordinates":[7.463116,51.361156],"type":"Point"}
}