{
  "type": "Feature",
  "properties": {
    "iso:country":"DE",
    "sg:address":"Gr\u00fcnthalstr. 19",
    "sg:city":"Raubling",
    "sg:phone":"+49 8035/5778",
    "sg:postcode":"83064",
    "sg:province":"Bayern",
    "wof:name":"Helako Elektrotechnik Gmbh",
    "wof:placetype":"venue"
},
  "geometry": {"coordinates":[12.1009378433,47.7894554138],"type":"Point"}
}