{
  "type": "Feature",
  "properties": {
    "iso:country":"DE",
    "sg:address":"Walther-Rathenau-Str. 42",
    "sg:city":"Magdeburg",
    "sg:postcode":"39106",
    "sg:province":"Sachsen-Anhalt",
    "wof:name":"Verband Der Kaufleute Sachsen-anhalt E. V.",
    "wof:placetype":"venue"
},
  "geometry": {"coordinates":[11.647082,52.145409],"type":"Point"}
}