{
  "type": "Feature",
  "properties": {
    "iso:country":"DE",
    "sg:address":"Einsteinstr. 25",
    "sg:city":"Geilenkirchen",
    "sg:phone":"+49 2451/959230",
    "sg:postcode":"52511",
    "sg:province":"Nordrhein-Westfalen",
    "wof:name":"W. Wolff Betonsteinwerk Kg",
    "wof:placetype":"venue"
},
  "geometry": {"coordinates":[6.0974059105,50.9803161621],"type":"Point"}
}