{
  "type": "Feature",
  "properties": {
    "iso:country":"DE",
    "sg:address":"Kaiserstr. 20",
    "sg:city":"D\u00fcsseldorf",
    "sg:phone":"+49 211/49590",
    "sg:postcode":"40479",
    "sg:province":"Nordrhein-Westfalen",
    "wof:name":"Saga Hotels Gmbh",
    "wof:placetype":"venue"
},
  "geometry": {"coordinates":[6.7789368629,51.2342681885],"type":"Point"}
}