{
  "type": "Feature",
  "properties": {
    "iso:country":"DE",
    "sg:address":"Hauptstr. 61a",
    "sg:city":"Steinpleis",
    "sg:postcode":"08432",
    "wof:name":"Bm Handel Und Gastro Gmbh",
    "wof:placetype":"venue"
},
  "geometry": {"coordinates":[12.395534,50.713329],"type":"Point"}
}