{
  "type": "Feature",
  "properties": {
    "iso:country":"DE",
    "sg:address":"In der Steintormasch 43c",
    "sg:city":"Hannover",
    "sg:phone":"+49 511/7010656",
    "sg:postcode":"30167",
    "sg:province":"Niedersachsen",
    "wof:name":"Ernst Hansmann",
    "wof:placetype":"venue"
},
  "geometry": {"coordinates":[9.699907,52.382111],"type":"Point"}
}