{
  "type": "Feature",
  "properties": {
    "iso:country":"DE",
    "sg:address":"Werner-von-Siemens-Str. 16",
    "sg:city":"Forst",
    "sg:phone":"+49 7251/17926",
    "sg:postcode":"76694",
    "sg:province":"Baden-W\u00fcrttemberg",
    "wof:name":"Fernmeldebau Gmbh",
    "wof:placetype":"venue"
},
  "geometry": {"coordinates":[8.5775098801,49.1562309265],"type":"Point"}
}