{
  "type": "Feature",
  "properties": {
    "iso:country":"DE",
    "sg:address":"Marienstr. 7",
    "sg:city":"Detmold",
    "sg:phone":"+49 5231/26475",
    "sg:postcode":"32756",
    "sg:province":"Nordrhein-Westfalen",
    "wof:name":"Petra Bork",
    "wof:placetype":"venue"
},
  "geometry": {"coordinates":[8.879687,51.943169],"type":"Point"}
}