{
  "type": "Feature",
  "properties": {
    "iso:country":"DE",
    "sg:address":"Parkstr. 1",
    "sg:city":"F\u00fcrstenau",
    "sg:phone":"+49 5901/3963",
    "sg:postcode":"49584",
    "sg:province":"Niedersachsen",
    "wof:name":"Grill-center",
    "wof:placetype":"venue"
},
  "geometry": {"coordinates":[7.67517519,52.5133132935],"type":"Point"}
}