{
  "type": "Feature",
  "properties": {
    "iso:country":"DE",
    "sg:address":"Muggenthaler Str. 2",
    "sg:city":"Krailling",
    "sg:phone":"+49 89/565861",
    "sg:postcode":"82152",
    "sg:province":"Bayern",
    "wof:name":"Hans Weidl Import - Vertretungen",
    "wof:placetype":"venue"
},
  "geometry": {"coordinates":[11.4132976532,48.0930213928],"type":"Point"}
}