{
  "type": "Feature",
  "properties": {
    "iso:country":"DE",
    "sg:address":"Schillerstr. 16",
    "sg:city":"Winterbach",
    "sg:phone":"+49 7181/73771",
    "sg:postcode":"73650",
    "sg:province":"Baden-W\u00fcrttemberg",
    "wof:name":"Friedrich Wagner",
    "wof:placetype":"venue"
},
  "geometry": {"coordinates":[9.4730606079,48.797328949],"type":"Point"}
}