{
  "type": "Feature",
  "properties": {
    "iso:country":"DE",
    "sg:address":"Hauptstra\u00dfe 141",
    "sg:city":"M\u00fcllheim",
    "sg:phone":"+49 7631",
    "sg:postcode":"79379",
    "sg:province":"Baden-W\u00fcrttemberg",
    "wof:name":"Markgr\u00e4fler Zooshop Rabe",
    "wof:placetype":"venue"
},
  "geometry": {"coordinates":[7.6269459724,47.8061141968],"type":"Point"}
}