{
  "type": "Feature",
  "properties": {
    "iso:country":"DE",
    "sg:address":"Hauptstr. 10",
    "sg:city":"Pfaffenhausen",
    "sg:phone":"+49 8265/7026",
    "sg:postcode":"87772",
    "sg:province":"Bayern",
    "wof:name":"Raiffeisenbank Hausen-salgen Eg",
    "wof:placetype":"venue"
},
  "geometry": {"coordinates":[10.452697,48.118793],"type":"Point"}
}