{
  "type": "Feature",
  "properties": {
    "iso:country":"DE",
    "sg:address":"Am Bahnhof 7",
    "sg:city":"Bad Doberan",
    "sg:phone":"+49 38203/12630",
    "sg:postcode":"18209",
    "sg:province":"Mecklenburg-Vorpommern",
    "wof:name":"Holger Prause Rechtsanwalt",
    "wof:placetype":"venue"
},
  "geometry": {"coordinates":[11.9032001495,54.0998001099],"type":"Point"}
}