{
  "type": "Feature",
  "properties": {
    "iso:country":"DE",
    "sg:address":"Schweizer Str. 11",
    "sg:city":"Bad Neuenahr-Ahrweiler",
    "sg:phone":"+49 2641/25336",
    "sg:postcode":"53474",
    "sg:province":"Rheinland-Pfalz",
    "wof:name":"Rolf M\u00fcller",
    "wof:placetype":"venue"
},
  "geometry": {"coordinates":[7.139729,50.539146],"type":"Point"}
}