{
  "type": "Feature",
  "properties": {
    "iso:country":"DE",
    "sg:address":"Place d'Epouville 1",
    "sg:city":"Dinklage",
    "sg:phone":"+49 4443/3755",
    "sg:postcode":"49413",
    "sg:province":"Niedersachsen",
    "wof:name":"Boulevard",
    "wof:placetype":"venue"
},
  "geometry": {"coordinates":[8.10478,52.651001],"type":"Point"}
}