{
  "type": "Feature",
  "properties": {
    "iso:country":"DE",
    "sg:address":"Martinsriether Weg",
    "sg:city":"Sangerhausen",
    "sg:phone":"+49 3464/612505",
    "sg:postcode":"06526",
    "sg:province":"Sachsen-Anhalt",
    "wof:name":"Am Darrweg",
    "wof:placetype":"venue"
},
  "geometry": {"coordinates":[11.2691230774,51.4682846069],"type":"Point"}
}