{
  "type": "Feature",
  "properties": {
    "iso:country":"DE",
    "sg:address":"Auf dem Kamp 10",
    "sg:city":"Kleve",
    "sg:phone":"+49 2821/49533",
    "sg:postcode":"47533",
    "sg:province":"Nordrhein-Westfalen",
    "wof:name":"F. Derksen",
    "wof:placetype":"venue"
},
  "geometry": {"coordinates":[6.096313,51.75816],"type":"Point"}
}