{
  "type": "Feature",
  "properties": {
    "iso:country":"DE",
    "sg:address":"Hauptstr. 23",
    "sg:city":"Etzelwang",
    "sg:phone":"+49 9663/519",
    "sg:postcode":"92268",
    "sg:province":"Bayern",
    "wof:name":"Andreas Schierl",
    "wof:placetype":"venue"
},
  "geometry": {"coordinates":[11.5853977203,49.5265808105],"type":"Point"}
}