{
  "type": "Feature",
  "properties": {
    "iso:country":"DE",
    "sg:address":"Goldammerweg 7 b",
    "sg:city":"Leipzig",
    "sg:phone":"+49 341/5210374",
    "sg:postcode":"04159",
    "sg:province":"Sachsen",
    "wof:name":"Richter Holzbauelemente Gmbh",
    "wof:placetype":"venue"
},
  "geometry": {"coordinates":[12.325064,51.382133],"type":"Point"}
}