{
  "type": "Feature",
  "properties": {
    "iso:country":"DE",
    "sg:address":"Schmiedestr. 1-9a",
    "sg:city":"Schwarzenbek",
    "sg:postcode":"21493",
    "sg:province":"Schleswig-Holstein",
    "wof:name":"Budnikowsky Drogeriemarkt",
    "wof:placetype":"venue"
},
  "geometry": {"coordinates":[10.480598,53.501385],"type":"Point"}
}