{
  "type": "Feature",
  "properties": {
    "iso:country":"DE",
    "sg:address":"Dreitorspitzstr. 23",
    "sg:city":"Garmisch-Partenkirchen",
    "sg:phone":"+49 8821/2331",
    "sg:postcode":"82467",
    "sg:province":"Bayern",
    "wof:name":"Ebinger & Klipphahn",
    "wof:placetype":"venue"
},
  "geometry": {"coordinates":[11.112321,47.488049],"type":"Point"}
}