{
  "type": "Feature",
  "properties": {
    "iso:country":"DE",
    "sg:address":"Bad Meinberger Str. 1",
    "sg:city":"Detmold",
    "sg:phone":"+49 5231/95100",
    "sg:postcode":"32760",
    "sg:province":"Nordrhein-Westfalen",
    "wof:name":"Sander & Hilker Gmbh",
    "wof:placetype":"venue"
},
  "geometry": {"coordinates":[8.92185,51.93203],"type":"Point"}
}