{
  "type": "Feature",
  "properties": {
    "iso:country":"DE",
    "sg:address":"Wiederleiten 12",
    "sg:city":"Tiefenbach",
    "sg:phone":"+49 8546/1453",
    "sg:postcode":"94113",
    "sg:province":"Bayern",
    "wof:name":"Wolfgang Zehntner",
    "wof:placetype":"venue"
},
  "geometry": {"coordinates":[13.3291654587,48.644947052],"type":"Point"}
}