{
  "type": "Feature",
  "properties": {
    "iso:country":"DE",
    "sg:address":"Ulmer Str. 25",
    "sg:city":"Leonberg",
    "sg:phone":"+49 7152/48585",
    "sg:postcode":"71229",
    "sg:province":"Baden-W\u00fcrttemberg",
    "wof:name":"Ingo Vinnai Architekt",
    "wof:placetype":"venue"
},
  "geometry": {"coordinates":[9.02808,48.788139],"type":"Point"}
}