{
  "type": "Feature",
  "properties": {
    "iso:country":"DE",
    "sg:address":"Battenberger Str. 15",
    "sg:city":"Frankenberg",
    "sg:phone":"+49 6451/3502",
    "sg:postcode":"35066",
    "sg:province":"Hessen",
    "wof:name":"Gernot Neuhaus",
    "wof:placetype":"venue"
},
  "geometry": {"coordinates":[8.7495260239,51.0459022522],"type":"Point"}
}