{
  "type": "Feature",
  "properties": {
    "iso:country":"DE",
    "sg:address":"Albert-Schweitzer-Str. 23",
    "sg:city":"Bretzfeld",
    "sg:phone":"+49 7946/6355",
    "sg:postcode":"74626",
    "sg:province":"Baden-W\u00fcrttemberg",
    "wof:name":"Viktor Bonetti",
    "wof:placetype":"venue"
},
  "geometry": {"coordinates":[9.431473732,49.1765632629],"type":"Point"}
}