{
  "type": "Feature",
  "properties": {
    "iso:country":"DE",
    "sg:address":"Anton-Dr\u00e4xl-Str. 20",
    "sg:city":"Lenggries",
    "sg:phone":"+49 8042/8789",
    "sg:postcode":"83661",
    "sg:province":"Bayern",
    "wof:name":"Kath. \u00d6ffentl. Bibliothek Im Pfarramt",
    "wof:placetype":"venue"
},
  "geometry": {"coordinates":[11.575651,47.674828],"type":"Point"}
}