{
  "type": "Feature",
  "properties": {
    "iso:country":"DE",
    "sg:address":"Seminarstrasse 2",
    "sg:city":"Naumburg/S.",
    "sg:postcode":"06618",
    "sg:province":"Sachsen-Anhalt",
    "wof:name":"Ostsibirische Schnarchschnecken",
    "wof:placetype":"venue"
},
  "geometry": {"coordinates":[11.79809,51.150501],"type":"Point"}
}