{
  "type": "Feature",
  "properties": {
    "iso:country":"DE",
    "sg:address":"Walzenweg 29",
    "sg:city":"Siegen",
    "sg:phone":"+49 271/370275",
    "sg:postcode":"57072",
    "sg:province":"Nordrhein-Westfalen",
    "wof:name":"Deimel Bauunternehmung Gmbh",
    "wof:placetype":"venue"
},
  "geometry": {"coordinates":[7.988378,50.890244],"type":"Point"}
}