{
  "type": "Feature",
  "properties": {
    "iso:country":"DE",
    "sg:address":"Georg-Gr\u00f6ning-Str. 31a",
    "sg:city":"Bremen",
    "sg:phone":"+49 421/344400",
    "sg:postcode":"28209",
    "sg:province":"Bremen",
    "wof:name":"Hildegard Esch-kobs Regieassistentin",
    "wof:placetype":"venue"
},
  "geometry": {"coordinates":[8.8307571411,53.0834884644],"type":"Point"}
}