{
  "type": "Feature",
  "properties": {
    "iso:country":"DE",
    "sg:address":"Schillerstr. 4-5",
    "sg:city":"Berlin",
    "sg:postcode":"10625",
    "sg:province":"Berlin",
    "wof:name":"Sdvv Datenverarbeituns- Service Gmbh",
    "wof:placetype":"venue"
},
  "geometry": {"coordinates":[13.32114,52.511292],"type":"Point"}
}