{
  "type": "Feature",
  "properties": {
    "iso:country":"DE",
    "sg:address":"Schulstr. 4",
    "sg:city":"Lissendorf",
    "sg:postcode":"54587",
    "sg:province":"Rheinland-Pfalz",
    "wof:name":"Hannelore Vetter Briefmarken",
    "wof:placetype":"venue"
},
  "geometry": {"coordinates":[6.6116900444,50.317653656],"type":"Point"}
}