{
  "type": "Feature",
  "properties": {
    "iso:country":"DE",
    "sg:address":"Kranoldplatz 3",
    "sg:city":"Berlin",
    "sg:phone":"+49 30/7733613",
    "sg:postcode":"12209",
    "sg:province":"Berlin",
    "wof:name":"Karin Wilhelm",
    "wof:placetype":"venue"
},
  "geometry": {"coordinates":[13.327734,52.428589],"type":"Point"}
}