{
  "type": "Feature",
  "properties": {
    "iso:country":"DE",
    "sg:address":"Finkenweg 15",
    "sg:city":"Spaichingen",
    "sg:phone":"+49 7424/2913",
    "sg:postcode":"78549",
    "sg:province":"Baden-W\u00fcrttemberg",
    "wof:name":"Joachim Wolfrum Architekt",
    "wof:placetype":"venue"
},
  "geometry": {"coordinates":[8.717653,48.074665],"type":"Point"}
}