{
  "type": "Feature",
  "properties": {
    "iso:country":"DE",
    "sg:address":"Willy-Messerschmitt-Str.",
    "sg:city":"Ottobrunn",
    "sg:postcode":"85521",
    "sg:province":"Bayern",
    "wof:name":"Et Gmbh",
    "wof:placetype":"venue"
},
  "geometry": {"coordinates":[11.6538133621,48.0754585266],"type":"Point"}
}