{
  "type": "Feature",
  "properties": {
    "iso:country":"DE",
    "sg:address":"Aachener Str. 102",
    "sg:city":"Stolberg",
    "sg:phone":"+49 2402/81318",
    "sg:postcode":"52223",
    "sg:province":"Nordrhein-Westfalen",
    "wof:name":"Nikolaus-grill",
    "wof:placetype":"venue"
},
  "geometry": {"coordinates":[6.2178192139,50.7590713501],"type":"Point"}
}