{
  "type": "Feature",
  "properties": {
    "iso:country":"DE",
    "sg:address":"Am Hafen 1",
    "sg:city":"Bramsche",
    "sg:phone":"+49 5461/5138",
    "sg:postcode":"49565",
    "sg:province":"Niedersachsen",
    "wof:name":"Rolf Poske",
    "wof:placetype":"venue"
},
  "geometry": {"coordinates":[8.0040378571,52.4011878967],"type":"Point"}
}