{
  "type": "Feature",
  "properties": {
    "iso:country":"DE",
    "sg:address":"Kreiler Weg 3",
    "sg:city":"Velen",
    "sg:phone":"+49 2863/2841",
    "sg:postcode":"46342",
    "sg:province":"Nordrhein-Westfalen",
    "wof:name":"Blumenhaus M. Dahlke",
    "wof:placetype":"venue"
},
  "geometry": {"coordinates":[6.996014,51.892475],"type":"Point"}
}