{
  "type": "Feature",
  "properties": {
    "iso:country":"DE",
    "sg:address":"Zeughausstr. 9",
    "sg:city":"Meschede",
    "sg:phone":"+49 291/7424",
    "sg:postcode":"59872",
    "sg:province":"Nordrhein-Westfalen",
    "wof:name":"Ulrich Weber",
    "wof:placetype":"venue"
},
  "geometry": {"coordinates":[8.2849330902,51.3461914062],"type":"Point"}
}