{
  "type": "Feature",
  "properties": {
    "iso:country":"DE",
    "sg:address":"Postfach 1138",
    "sg:city":"Dettingen",
    "sg:postcode":"72575",
    "wof:name":"Die Backstube B\u00e4ckerei",
    "wof:placetype":"venue"
},
  "geometry": {"coordinates":[9.34467,48.526669],"type":"Point"}
}