{
  "type": "Feature",
  "properties": {
    "iso:country":"DE",
    "sg:address":"Kurze Str. 42",
    "sg:city":"Pfullingen",
    "sg:phone":"+49 7121/798194",
    "sg:postcode":"72793",
    "sg:province":"Baden-W\u00fcrttemberg",
    "wof:name":"E. Friese",
    "wof:placetype":"venue"
},
  "geometry": {"coordinates":[9.22195,48.468372],"type":"Point"}
}