{
  "type": "Feature",
  "properties": {
    "iso:country":"DE",
    "sg:address":"Gutenbergstr. 2",
    "sg:city":"Gau-Algesheim",
    "sg:phone":"+49 6725/4481",
    "sg:postcode":"55435",
    "sg:province":"Rheinland-Pfalz",
    "wof:name":"Metalltechnik Menges Gmbh",
    "wof:placetype":"venue"
},
  "geometry": {"coordinates":[8.02012,49.963219],"type":"Point"}
}