{
  "type": "Feature",
  "properties": {
    "iso:country":"DE",
    "sg:address":"Spiekerweg 7",
    "sg:city":"M\u00fcden",
    "sg:phone":"+49 5375/2600",
    "sg:postcode":"38539",
    "sg:province":"Niedersachsen",
    "wof:name":"Wilfried Meier",
    "wof:placetype":"venue"
},
  "geometry": {"coordinates":[10.3543777466,52.5280570984],"type":"Point"}
}