{
  "type": "Feature",
  "properties": {
    "iso:country":"DE",
    "sg:address":"Langernstr 60",
    "sg:city":"Werne",
    "sg:phone":"+49 2389/959768",
    "sg:postcode":"59368",
    "sg:province":"Nordrhein-Westfalen",
    "wof:name":"E. Westrup Gbr",
    "wof:placetype":"venue"
},
  "geometry": {"coordinates":[7.561483,51.646713],"type":"Point"}
}