{
  "type": "Feature",
  "properties": {
    "iso:country":"DE",
    "sg:address":"Gescherer Str. 13",
    "sg:city":"Rosendahl",
    "sg:phone":"+49 2566/972888",
    "sg:postcode":"48720",
    "sg:province":"Nordrhein-Westfalen",
    "wof:name":"Heinz Volkmer Architekt",
    "wof:placetype":"venue"
},
  "geometry": {"coordinates":[7.126079,52.004871],"type":"Point"}
}