{
  "type": "Feature",
  "properties": {
    "iso:country":"DE",
    "sg:address":"Odenwaldstr. 12",
    "sg:city":"Bensheim",
    "sg:phone":"+49 6251/4749",
    "sg:postcode":"64625",
    "sg:province":"Hessen",
    "wof:name":"Georg Kindinger",
    "wof:placetype":"venue"
},
  "geometry": {"coordinates":[8.6118507385,49.6833496094],"type":"Point"}
}