{
  "type": "Feature",
  "properties": {
    "iso:country":"DE",
    "sg:address":"Dammtorstr. 7",
    "sg:city":"Hamburg",
    "sg:phone":"+49 40/344872",
    "sg:postcode":"20354",
    "sg:province":"Hamburg",
    "wof:name":"Moeller Am Dammtor Georg Und Ruth Moeller",
    "wof:placetype":"venue"
},
  "geometry": {"coordinates":[9.987942,53.55661],"type":"Point"}
}