{
  "type": "Feature",
  "properties": {
    "iso:country":"DE",
    "sg:address":"Hauptstr. 8",
    "sg:city":"M\u00fcnsterappel",
    "sg:phone":"+49 4963/623180",
    "sg:postcode":"67822",
    "sg:province":"Rheinland-Pfalz",
    "wof:name":"Jutta U. Elmar Graf",
    "wof:placetype":"venue"
},
  "geometry": {"coordinates":[7.876414,49.733826],"type":"Point"}
}