{
  "type": "Feature",
  "properties": {
    "iso:country":"DE",
    "sg:address":"Am Markt 4",
    "sg:city":"Harrislee",
    "sg:phone":"+49 461/71677",
    "sg:postcode":"24955",
    "sg:province":"Schleswig-Holstein",
    "wof:name":"Restaurant Am Markt",
    "wof:placetype":"venue"
},
  "geometry": {"coordinates":[9.3956308365,54.7997436523],"type":"Point"}
}