{
  "type": "Feature",
  "properties": {
    "iso:country":"DE",
    "sg:address":"Am Joseph 8-10",
    "sg:city":"Wehrheim",
    "sg:phone":"+49 6081/943050",
    "sg:postcode":"61273",
    "sg:province":"Hessen",
    "wof:name":"Transatlantic Handelsges. Stolpe & Co Mbh",
    "wof:placetype":"venue"
},
  "geometry": {"coordinates":[8.570402,50.295563],"type":"Point"}
}