{
  "type": "Feature",
  "properties": {
    "iso:country":"DE",
    "sg:address":"Breite Str. 5",
    "sg:city":"Stapelburg",
    "sg:phone":"+49 39452/9121",
    "sg:postcode":"38871",
    "sg:province":"Sachsen-Anhalt",
    "wof:name":"Udo Kerwel Ingenieur",
    "wof:placetype":"venue"
},
  "geometry": {"coordinates":[10.6630687714,51.9001159668],"type":"Point"}
}