{
  "type": "Feature",
  "properties": {
    "iso:country":"DE",
    "sg:address":"Zeppelinstr. 12",
    "sg:city":"Sersheim",
    "sg:postcode":"74372",
    "sg:province":"Baden-W\u00fcrttemberg",
    "wof:name":"Stahl-rohr-technik Ohg Bauer Blumenthal",
    "wof:placetype":"venue"
},
  "geometry": {"coordinates":[9.0029678345,48.9567146301],"type":"Point"}
}