{
  "type": "Feature",
  "properties": {
    "iso:country":"DE",
    "sg:address":"Teichstr. 24",
    "sg:city":"Kassel",
    "sg:phone":"+49 561/67767",
    "sg:postcode":"34130",
    "sg:province":"Hessen",
    "wof:name":"Moet Hennessy Deutschland Gmbh",
    "wof:placetype":"venue"
},
  "geometry": {"coordinates":[9.4498806,51.322101593],"type":"Point"}
}