{
  "type": "Feature",
  "properties": {
    "iso:country":"DE",
    "sg:address":"Lo\u00dfburger Str. 15",
    "sg:city":"Freudenstadt",
    "sg:phone":"+49 7441/4154",
    "sg:postcode":"72250",
    "sg:province":"Baden-W\u00fcrttemberg",
    "wof:name":"Anuschka-grill",
    "wof:placetype":"venue"
},
  "geometry": {"coordinates":[8.4128017426,48.4617843628],"type":"Point"}
}