{
  "type": "Feature",
  "properties": {
    "iso:country":"DE",
    "sg:address":"Poststr. 28 POSTFACH 1568",
    "sg:city":"Lengerich",
    "sg:phone":"+49 4954/8194500",
    "sg:postcode":"49515",
    "sg:province":"Niedersachsen",
    "wof:name":"Gustav Schmidt Ohg",
    "wof:placetype":"venue"
},
  "geometry": {"coordinates":[7.8736209869,52.1722373962],"type":"Point"}
}