{
  "type": "Feature",
  "properties": {
    "iso:country":"DE",
    "sg:address":"K\u00f6nigsbr\u00fccker Str. 22",
    "sg:city":"Oberlichtenau",
    "sg:phone":"+49 35795/2588",
    "sg:postcode":"01936",
    "sg:province":"Sachsen",
    "wof:name":"Heimatmuseum Reichenau",
    "wof:placetype":"venue"
},
  "geometry": {"coordinates":[13.990222,51.233124],"type":"Point"}
}