{
  "type": "Feature",
  "properties": {
    "iso:country":"DE",
    "sg:address":"Fasanenweg 6-8",
    "sg:city":"Leinfelden-Echterdingen",
    "sg:phone":"+49 711/759030",
    "sg:postcode":"70771",
    "sg:province":"Baden-W\u00fcrttemberg",
    "wof:name":"August Heine Kg",
    "wof:placetype":"venue"
},
  "geometry": {"coordinates":[9.143967,48.707294],"type":"Point"}
}