{
  "type": "Feature",
  "properties": {
    "iso:country":"DE",
    "sg:address":"Weinstr. 7 a",
    "sg:city":"M\u00fcnchen",
    "sg:phone":"+49 89/298481",
    "sg:postcode":"80333",
    "sg:province":"Bayern",
    "wof:name":"Andechser Am Dom",
    "wof:placetype":"venue"
},
  "geometry": {"coordinates":[11.5751495361,48.1382865906],"type":"Point"}
}