{
  "type": "Feature",
  "properties": {
    "iso:country":"DE",
    "sg:address":"Hagenhiller Str. 25",
    "sg:city":"Altmannstein",
    "sg:postcode":"93336",
    "sg:province":"Bayern",
    "wof:name":"Schels Holzbau - Zimmerei Gmbh",
    "wof:placetype":"venue"
},
  "geometry": {"coordinates":[11.6604938507,48.8951225281],"type":"Point"}
}