{
  "type": "Feature",
  "properties": {
    "iso:country":"DE",
    "sg:address":"Ostbeverner Str. 50",
    "sg:city":"Greven",
    "sg:phone":"+49 5485/1844",
    "sg:postcode":"48268",
    "sg:province":"Nordrhein-Westfalen",
    "wof:name":"Paul Wichmar",
    "wof:placetype":"venue"
},
  "geometry": {"coordinates":[7.736223,52.091408],"type":"Point"}
}