{
  "type": "Feature",
  "properties": {
    "iso:country":"DE",
    "sg:address":"Helmersh\u00e4user Str. 28",
    "sg:city":"Altenstadt",
    "sg:phone":"+49 6047/68161",
    "sg:postcode":"63674",
    "sg:province":"Hessen",
    "wof:name":"Lovatex Industrie-service Gmbh",
    "wof:placetype":"venue"
},
  "geometry": {"coordinates":[8.965684,50.275482],"type":"Point"}
}