{
  "type": "Feature",
  "properties": {
    "iso:country":"DE",
    "sg:address":"Cotheniusstr. 8",
    "sg:city":"Berlin",
    "sg:phone":"+49 30/4248225",
    "sg:postcode":"10407",
    "sg:province":"Berlin",
    "wof:name":"Onkel Mirko",
    "wof:placetype":"venue"
},
  "geometry": {"coordinates":[13.4484348297,52.5283622742],"type":"Point"}
}