{
  "type": "Feature",
  "properties": {
    "iso:country":"DE",
    "sg:address":"Goldbecker Str. 21",
    "sg:city":"Regesbostel",
    "sg:phone":"+49 4165/97210",
    "sg:postcode":"21649",
    "sg:province":"Niedersachsen",
    "wof:name":"Lafarge Roofing Europe Gmbh",
    "wof:placetype":"venue"
},
  "geometry": {"coordinates":[9.653419,53.404579],"type":"Point"}
}