{
  "type": "Feature",
  "properties": {
    "iso:country":"DE",
    "sg:address":"Am Herrenberg 1",
    "sg:city":"Weinsberg",
    "sg:phone":"+49 7134/9900",
    "sg:postcode":"74189",
    "sg:province":"Baden-W\u00fcrttemberg",
    "wof:name":"Stark S. Gmbh",
    "wof:placetype":"venue"
},
  "geometry": {"coordinates":[9.3522386551,49.1651344299],"type":"Point"}
}