{
  "type": "Feature",
  "properties": {
    "iso:country":"DE",
    "sg:address":"Schippelsweg 12",
    "sg:city":"Hamburg",
    "sg:phone":"+49 40/5517762",
    "sg:postcode":"22455",
    "sg:province":"Hamburg",
    "wof:name":"M. V. Kohten",
    "wof:placetype":"venue"
},
  "geometry": {"coordinates":[9.9609003067,53.6338348389],"type":"Point"}
}