{
  "type": "Feature",
  "properties": {
    "iso:country":"DE",
    "sg:address":"Am Bannholz 5-3",
    "sg:city":"Weinheim",
    "sg:phone":"+49 6201/60040",
    "sg:postcode":"69469",
    "sg:province":"Baden-W\u00fcrttemberg",
    "wof:name":"Cdm Conventz Direct Marketing Gmbh",
    "wof:placetype":"venue"
},
  "geometry": {"coordinates":[8.6885128021,49.5409393311],"type":"Point"}
}