{
  "type": "Feature",
  "properties": {
    "iso:country":"DE",
    "sg:address":"Klosterstr. 30",
    "sg:city":"W\u00fcrselen",
    "sg:phone":"+49 2405/4570",
    "sg:postcode":"52146",
    "sg:province":"Nordrhein-Westfalen",
    "wof:name":"Alten- Und Pflegeheim St. Antonius",
    "wof:placetype":"venue"
},
  "geometry": {"coordinates":[6.129454,50.820415],"type":"Point"}
}