{
  "type": "Feature",
  "properties": {
    "iso:country":"DE",
    "sg:address":"Bundesstr.16",
    "sg:city":"Hamburg",
    "sg:phone":"+49 40/55773370",
    "sg:postcode":"20146",
    "sg:province":"Hamburg",
    "wof:name":"Die-mucke, Das Forum F\u00fcr S\u00e4nger Und S\u00e4ngerinnen",
    "wof:placetype":"venue"
},
  "geometry": {"coordinates":[9.98192,53.564568],"type":"Point"}
}