{
  "type": "Feature",
  "properties": {
    "iso:country":"DE",
    "sg:address":"Josefstra\u00dfe 15",
    "sg:city":"Goch",
    "sg:phone":"+49 2827/9315",
    "sg:postcode":"47574",
    "sg:province":"Nordrhein-Westfalen",
    "wof:name":"Hotel Villa Fiore C/o Klaus R\u00f6ntgen - Online-mareting",
    "wof:placetype":"venue"
},
  "geometry": {"coordinates":[6.0788521767,51.7068977356],"type":"Point"}
}