{
  "type": "Feature",
  "properties": {
    "iso:country":"DE",
    "sg:address":"Neue Weing\u00e4rten 8",
    "sg:city":"Ludwigsburg",
    "sg:phone":"+49 7141/220221",
    "sg:postcode":"71634",
    "sg:province":"Baden-W\u00fcrttemberg",
    "wof:name":"C. E. S.",
    "wof:placetype":"venue"
},
  "geometry": {"coordinates":[9.1618499756,48.908000946],"type":"Point"}
}