{
  "type": "Feature",
  "properties": {
    "iso:country":"DE",
    "sg:address":"Wirthfeldweg 10",
    "sg:city":"Sauerlach",
    "sg:phone":"+49 8104/1608",
    "sg:postcode":"82054",
    "sg:province":"Bayern",
    "wof:name":"Christeva Sonnenenergie- Technik Gmbh",
    "wof:placetype":"venue"
},
  "geometry": {"coordinates":[11.65358,47.97723],"type":"Point"}
}