{
  "type": "Feature",
  "properties": {
    "iso:country":"DE",
    "sg:address":"Lange Str. 20",
    "sg:city":"Warin",
    "sg:phone":"+49 38482/60244",
    "sg:postcode":"19417",
    "sg:province":"Mecklenburg-Vorpommern",
    "wof:name":"Horst Kruse",
    "wof:placetype":"venue"
},
  "geometry": {"coordinates":[11.704165,53.800709],"type":"Point"}
}