{
  "type": "Feature",
  "properties": {
    "iso:country":"DE",
    "sg:address":"Wangener Str. 121",
    "sg:city":"Ravensburg",
    "sg:phone":"+49 751/362520",
    "sg:postcode":"88212",
    "sg:province":"Baden-W\u00fcrttemberg",
    "wof:name":"Thomas Bihler Gmbh",
    "wof:placetype":"venue"
},
  "geometry": {"coordinates":[9.6210699081,47.7696762085],"type":"Point"}
}