{
  "type": "Feature",
  "properties": {
    "iso:country":"DE",
    "sg:address":"Zeppelinstra\u00dfe 10",
    "sg:city":"Saarlouis",
    "sg:phone":"+49 6831/123282",
    "sg:postcode":"66740",
    "sg:province":"Saarland",
    "wof:name":"Scissor Lift System Gmbh",
    "wof:placetype":"venue"
},
  "geometry": {"coordinates":[6.732531,49.313026],"type":"Point"}
}