{
  "type": "Feature",
  "properties": {
    "iso:country":"DE",
    "sg:address":"Rosenheimer Str. 108i",
    "sg:city":"M\u00fcnchen",
    "sg:phone":"+49 89/4484948",
    "sg:postcode":"81669",
    "sg:province":"Bayern",
    "wof:name":"Treu Concept Gmbh",
    "wof:placetype":"venue"
},
  "geometry": {"coordinates":[11.5990905762,48.1252861023],"type":"Point"}
}