{
  "type": "Feature",
  "properties": {
    "iso:country":"DE",
    "sg:address":"Hauptstr. 65",
    "sg:city":"Oberthal",
    "sg:phone":"+49 6854/8349",
    "sg:postcode":"66649",
    "sg:province":"Saarland",
    "wof:name":"G\u00fcnther Schwingel",
    "wof:placetype":"venue"
},
  "geometry": {"coordinates":[7.0901799202,49.5089683533],"type":"Point"}
}