{
  "type": "Feature",
  "properties": {
    "iso:country":"DE",
    "sg:address":"Bismarckstr. 39",
    "sg:city":"V\u00f6lklingen",
    "sg:phone":"+49 6898/22694",
    "sg:postcode":"66333",
    "sg:province":"Saarland",
    "wof:name":"W. Merches",
    "wof:placetype":"venue"
},
  "geometry": {"coordinates":[6.8528327942,49.2514610291],"type":"Point"}
}