{
  "type": "Feature",
  "properties": {
    "iso:country":"DE",
    "sg:address":"Hersbrucker Str. 49",
    "sg:city":"Lauf",
    "sg:phone":"+49 9123/988578",
    "sg:postcode":"91207",
    "sg:province":"Bayern",
    "wof:name":"Cinemathek",
    "wof:placetype":"venue"
},
  "geometry": {"coordinates":[11.287446022,49.5154075623],"type":"Point"}
}