{
  "type": "Feature",
  "properties": {
    "iso:country":"DE",
    "sg:address":"M\u00fcnsterplatz 24",
    "sg:city":"Ulm",
    "sg:phone":"+49 731/619995",
    "sg:postcode":"89073",
    "sg:province":"Baden-W\u00fcrttemberg",
    "wof:name":"S. Kopp",
    "wof:placetype":"venue"
},
  "geometry": {"coordinates":[9.993527,48.398163],"type":"Point"}
}