{
  "type": "Feature",
  "properties": {
    "iso:country":"DE",
    "sg:address":"H\u00f6henstr 7",
    "sg:city":"Eisingen",
    "sg:phone":"+49 7232/38400",
    "sg:postcode":"75239",
    "sg:province":"Baden-W\u00fcrttemberg",
    "wof:name":"Wegoma",
    "wof:placetype":"venue"
},
  "geometry": {"coordinates":[8.671848,48.945305],"type":"Point"}
}