{
  "type": "Feature",
  "properties": {
    "iso:country":"DE",
    "sg:address":"Hopfenstr. 5",
    "sg:city":"H\u00f6rgertshausen",
    "sg:phone":"+49 8764/920336",
    "sg:postcode":"85413",
    "sg:province":"Bayern",
    "wof:name":"Schleibinger Office-line Gmbh",
    "wof:placetype":"venue"
},
  "geometry": {"coordinates":[11.868254,48.551208],"type":"Point"}
}