{
  "type": "Feature",
  "properties": {
    "iso:country":"DE",
    "sg:city":"Hannover",
    "sg:postcode":"30163",
    "sg:province":"Niedersachsen",
    "wof:name":"Traderscorner",
    "wof:placetype":"venue"
},
  "geometry": {"coordinates":[9.751327,52.389111],"type":"Point"}
}