{
  "type": "Feature",
  "properties": {
    "iso:country":"DE",
    "sg:address":"Dresdner Str. 5",
    "sg:city":"Stolpen",
    "sg:phone":"+49 35973/26593",
    "sg:postcode":"01833",
    "sg:province":"Sachsen",
    "wof:name":"Brigitte Kreft",
    "wof:placetype":"venue"
},
  "geometry": {"coordinates":[14.0816431046,51.0491600037],"type":"Point"}
}