{
  "type": "Feature",
  "properties": {
    "iso:country":"DE",
    "sg:address":"Schillerstr. 25",
    "sg:city":"Burgst\u00e4dt",
    "sg:phone":"+49 3724/2616",
    "sg:postcode":"09217",
    "sg:province":"Sachsen",
    "wof:name":"J\u00fcrgen Krabisch Ingenieur",
    "wof:placetype":"venue"
},
  "geometry": {"coordinates":[12.8061800003,50.916229248],"type":"Point"}
}