{
  "type": "Feature",
  "properties": {
    "iso:country":"DE",
    "sg:address":"Seesener Str. 21",
    "sg:city":"Salzgitter",
    "sg:phone":"+49 5341/25795",
    "sg:postcode":"38239",
    "sg:province":"Niedersachsen",
    "wof:name":"Restaurant Kammerkrug",
    "wof:placetype":"venue"
},
  "geometry": {"coordinates":[10.4458189011,52.1448974609],"type":"Point"}
}