{
  "type": "Feature",
  "properties": {
    "iso:country":"DE",
    "sg:address":"Weinbergstr. 14",
    "sg:city":"Mesenich",
    "sg:phone":"+49 2673/4626",
    "sg:postcode":"56820",
    "sg:province":"Rheinland-Pfalz",
    "wof:name":"Josef Schneiders Weinanbau",
    "wof:placetype":"venue"
},
  "geometry": {"coordinates":[7.1978111267,50.0967254639],"type":"Point"}
}