{
  "type": "Feature",
  "properties": {
    "iso:country":"DE",
    "sg:address":"Felkestra\u00dfe 46",
    "sg:city":"Diez",
    "sg:phone":"+49 4906/4322679",
    "sg:postcode":"65582",
    "sg:province":"Rheinland-Pfalz",
    "wof:name":"Cheops Cornerstone Webservices",
    "wof:placetype":"venue"
},
  "geometry": {"coordinates":[8.0235319138,50.3738250732],"type":"Point"}
}