{
  "type": "Feature",
  "properties": {
    "iso:country":"DE",
    "sg:address":"West 14",
    "sg:city":"Neuenbrook",
    "sg:phone":"+49 4824/1881",
    "sg:postcode":"25578",
    "sg:province":"Schleswig-Holstein",
    "wof:name":"Niese & Niese Bauunternehmung Gmbh",
    "wof:placetype":"venue"
},
  "geometry": {"coordinates":[9.5303,53.86145],"type":"Point"}
}