{
  "type": "Feature",
  "properties": {
    "iso:country":"DE",
    "sg:address":"Jahnstr. 3",
    "sg:city":"Dargun",
    "sg:phone":"+49 39959/20238",
    "sg:postcode":"17159",
    "sg:province":"Mecklenburg-Vorpommern",
    "wof:name":"Gerd-eberhard Plautz",
    "wof:placetype":"venue"
},
  "geometry": {"coordinates":[12.858939,53.898441],"type":"Point"}
}