{
  "type": "Feature",
  "properties": {
    "iso:country":"DE",
    "sg:address":"Kantstr. 35",
    "sg:city":"W\u00fcrzburg",
    "sg:phone":"+49 931/284170",
    "sg:postcode":"97074",
    "sg:province":"Bayern",
    "wof:name":"Hap Ges. F\u00fcr Planung Analyse Und Innov. Gest. Mbh",
    "wof:placetype":"venue"
},
  "geometry": {"coordinates":[9.9433288574,49.7761611938],"type":"Point"}
}