{
  "type": "Feature",
  "properties": {
    "iso:country":"DE",
    "sg:address":"Liebfrauenstr. 1",
    "sg:city":"Bad Bevensen",
    "sg:phone":"+49 5821/98080",
    "sg:postcode":"29549",
    "sg:province":"Niedersachsen",
    "wof:name":"Mesch Dental Gmbh Zahn\u00e4rztebedarf",
    "wof:placetype":"venue"
},
  "geometry": {"coordinates":[10.5716934204,53.0834617615],"type":"Point"}
}