{
  "type": "Feature",
  "properties": {
    "iso:country":"DE",
    "sg:address":"Eisenbahnstr. 5",
    "sg:city":"Gera",
    "sg:phone":"+49 365/8001159",
    "sg:postcode":"07545",
    "sg:province":"Th\u00fcringen",
    "wof:name":"Arbeitsf\u00f6rderungsagentur Des Freistaates Th\u00fcringen",
    "wof:placetype":"venue"
},
  "geometry": {"coordinates":[12.076902,50.871292],"type":"Point"}
}