{
  "type": "Feature",
  "properties": {
    "iso:country":"DE",
    "sg:address":"Goslarsche Str. 54",
    "sg:city":"Clausthal-Zellerfeld",
    "sg:phone":"+49 5323/82661",
    "sg:postcode":"38678",
    "sg:province":"Niedersachsen",
    "wof:name":"Schremer-wahrhusen Inh. Claudia Wahrhusen",
    "wof:placetype":"venue"
},
  "geometry": {"coordinates":[10.3403902054,51.8200721741],"type":"Point"}
}