{
  "type": "Feature",
  "properties": {
    "iso:country":"DE",
    "sg:address":"Schulstr. 5",
    "sg:city":"Triberg",
    "sg:phone":"+49 7722/920323",
    "sg:postcode":"78098",
    "sg:province":"Baden-W\u00fcrttemberg",
    "wof:name":"Plus-warenhandels- Gmbh & Co.",
    "wof:placetype":"venue"
},
  "geometry": {"coordinates":[8.2331542969,48.1305580139],"type":"Point"}
}