{
  "type": "Feature",
  "properties": {
    "iso:country":"DE",
    "sg:address":"Schlacker Weg 9",
    "sg:city":"Herzogenrath",
    "sg:phone":"+49 2406/929044",
    "sg:postcode":"52134",
    "sg:province":"Nordrhein-Westfalen",
    "wof:name":"Hermann Grever Steuerberater",
    "wof:placetype":"venue"
},
  "geometry": {"coordinates":[6.1114029884,50.8692016602],"type":"Point"}
}