{
  "type": "Feature",
  "properties": {
    "iso:country":"DE",
    "sg:address":"Hugo-von-Eltz-Str. 26",
    "sg:city":"Hattersheim",
    "sg:phone":"+49 6145/31727",
    "sg:postcode":"65795",
    "sg:province":"Hessen",
    "wof:name":"Susanne Pregitzer",
    "wof:placetype":"venue"
},
  "geometry": {"coordinates":[8.4866542816,50.0685043335],"type":"Point"}
}