{
  "type": "Feature",
  "properties": {
    "iso:country":"DE",
    "sg:address":"Lange Str. 9",
    "sg:city":"Obernkirchen",
    "sg:phone":"+49 5724/2328",
    "sg:postcode":"31683",
    "sg:province":"Niedersachsen",
    "wof:name":"Reinland Textilpflege Gmbh",
    "wof:placetype":"venue"
},
  "geometry": {"coordinates":[9.127676,52.271511],"type":"Point"}
}