{
  "type": "Feature",
  "properties": {
    "iso:country":"DE",
    "sg:address":"73119",
    "sg:city":"Zell",
    "sg:phone":"+49 7164/7333",
    "sg:postcode":"73119",
    "sg:province":"Baden-W\u00fcrttemberg",
    "wof:name":"Gemeindehalle",
    "wof:placetype":"venue"
},
  "geometry": {"coordinates":[9.5749397278,48.6505813599],"type":"Point"}
}