{
  "type": "Feature",
  "properties": {
    "iso:country":"DE",
    "sg:address":"Bahnhofstr. 26 A",
    "sg:city":"B\u00f6nningstedt",
    "sg:phone":"+49 40/55693835",
    "sg:postcode":"25474",
    "sg:province":"Schleswig-Holstein",
    "wof:name":"P. C. Partner Daten- Und Kommuni- B\u00f6nningstedt Gmbh",
    "wof:placetype":"venue"
},
  "geometry": {"coordinates":[9.9094676971,53.6644515991],"type":"Point"}
}