{
  "type": "Feature",
  "properties": {
    "iso:country":"DE",
    "sg:address":"Loderm\u00fchl 4",
    "sg:city":"Tirschenreuth",
    "sg:phone":"+49 9631/1305",
    "sg:postcode":"95643",
    "sg:province":"Bayern",
    "wof:name":"Wilh. Anton Ziegler Kg",
    "wof:placetype":"venue"
},
  "geometry": {"coordinates":[12.3534603119,49.8575210571],"type":"Point"}
}