{
  "type": "Feature",
  "properties": {
    "iso:country":"DE",
    "sg:address":"Erbachstr. 27",
    "sg:city":"Magstadt",
    "sg:phone":"+49 7159/42557",
    "sg:postcode":"71106",
    "sg:province":"Baden-W\u00fcrttemberg",
    "wof:name":"Erbachst\u00fcble",
    "wof:placetype":"venue"
},
  "geometry": {"coordinates":[8.9673709869,48.7385597229],"type":"Point"}
}