{
  "type": "Feature",
  "properties": {
    "iso:country":"DE",
    "sg:address":"Gundelfinger Str. 7",
    "sg:city":"Freiburg",
    "sg:phone":"+49 761/552637",
    "sg:postcode":"79108",
    "sg:province":"Baden-W\u00fcrttemberg",
    "wof:name":"M\u00f6bel- Fakler Gmbh",
    "wof:placetype":"venue"
},
  "geometry": {"coordinates":[7.860841,48.028297],"type":"Point"}
}