{
  "type": "Feature",
  "properties": {
    "iso:country":"DE",
    "sg:address":"Stader Str. 2",
    "sg:city":"Cadenberge",
    "sg:phone":"+49 4777/93410",
    "sg:postcode":"21781",
    "sg:province":"Niedersachsen",
    "wof:name":"Herbert Zeeck Steuerberater",
    "wof:placetype":"venue"
},
  "geometry": {"coordinates":[9.0566072464,53.7719306946],"type":"Point"}
}