{
  "type": "Feature",
  "properties": {
    "iso:country":"DE",
    "sg:address":"Heisfelder Str. 263",
    "sg:city":"Leer",
    "sg:phone":"+49 491/3584",
    "sg:postcode":"26789",
    "sg:province":"Niedersachsen",
    "wof:name":"Aral Ag",
    "wof:placetype":"venue"
},
  "geometry": {"coordinates":[7.457930088,53.2496986389],"type":"Point"}
}