{
  "type": "Feature",
  "properties": {
    "iso:country":"DE",
    "sg:address":"K\u00f6rtestr. 10",
    "sg:city":"Berlin",
    "sg:phone":"+49 30/6944433",
    "sg:postcode":"10967",
    "sg:province":"Berlin",
    "wof:name":"Intermezzo Peter D\u00fctzer",
    "wof:placetype":"venue"
},
  "geometry": {"coordinates":[13.411076,52.491219],"type":"Point"}
}