{
  "type": "Feature",
  "properties": {
    "iso:country":"DE",
    "sg:address":"Hintergasse 38",
    "sg:city":"Hofheim",
    "sg:phone":"+49 6192/39681",
    "sg:postcode":"65719",
    "sg:province":"Hessen",
    "wof:name":"F. Und E. Zink Restauratoren",
    "wof:placetype":"venue"
},
  "geometry": {"coordinates":[8.4191179276,50.0619354248],"type":"Point"}
}