{
  "type": "Feature",
  "properties": {
    "iso:country":"DE",
    "sg:address":"Bismarckstr. 56",
    "sg:city":"Krefeld",
    "sg:postcode":"47799",
    "sg:province":"Nordrhein-Westfalen",
    "wof:name":"Q-in Media Gmbh",
    "wof:placetype":"venue"
},
  "geometry": {"coordinates":[6.574718,51.340004],"type":"Point"}
}