{
  "type": "Feature",
  "properties": {
    "iso:country":"DE",
    "sg:address":"Niederhabbach 18",
    "sg:city":"Lindlar",
    "sg:postcode":"51789",
    "sg:province":"Nordrhein-Westfalen",
    "wof:name":"Poli Mat Handelsgesellschaft F\u00fcr Poligraphische Materialien",
    "wof:placetype":"venue"
},
  "geometry": {"coordinates":[7.4235582352,51.0554161072],"type":"Point"}
}