{
  "type": "Feature",
  "properties": {
    "iso:country":"DE",
    "sg:address":"Plattenstr. 7/1",
    "sg:city":"Wiernsheim",
    "sg:phone":"+49 7041/7245",
    "sg:postcode":"75446",
    "sg:province":"Baden-W\u00fcrttemberg",
    "wof:name":"Helmut Buikat",
    "wof:placetype":"venue"
},
  "geometry": {"coordinates":[8.8475370407,48.9103507996],"type":"Point"}
}