{
  "type": "Feature",
  "properties": {
    "iso:country":"DE",
    "sg:address":"Herbert-Kadner-Str. 10",
    "sg:city":"M\u00fcnchen",
    "sg:phone":"+49 89/3133353",
    "sg:postcode":"80995",
    "sg:province":"Bayern",
    "wof:name":"Anton Frankl Gmbh",
    "wof:placetype":"venue"
},
  "geometry": {"coordinates":[11.5336837769,48.2168998718],"type":"Point"}
}