{
  "type": "Feature",
  "properties": {
    "iso:country":"DE",
    "sg:address":"Mewesstr. 30",
    "sg:city":"Berlin",
    "sg:phone":"+49 30/9413227",
    "sg:postcode":"13125",
    "sg:province":"Berlin",
    "wof:name":"Doris Winter",
    "wof:placetype":"venue"
},
  "geometry": {"coordinates":[13.5044298172,52.6479225159],"type":"Point"}
}