{
  "type": "Feature",
  "properties": {
    "iso:country":"DE",
    "sg:address":"Basteigasse 4",
    "sg:city":"Kaiserslautern",
    "sg:phone":"+49 631/93330",
    "sg:postcode":"67655",
    "sg:province":"Rheinland-Pfalz",
    "wof:name":"J\u00fcdische Gemeinde",
    "wof:placetype":"venue"
},
  "geometry": {"coordinates":[7.7717089653,49.4422416687],"type":"Point"}
}