{
  "type": "Feature",
  "properties": {
    "iso:country":"DE",
    "sg:address":"Virchowstr. 4",
    "sg:city":"Neuss",
    "sg:phone":"+49 2131/8808120",
    "sg:postcode":"41464",
    "sg:province":"Nordrhein-Westfalen",
    "wof:name":"Helga Henneberg Steuerberaterin",
    "wof:placetype":"venue"
},
  "geometry": {"coordinates":[6.674601078,51.1898612976],"type":"Point"}
}