{
  "type": "Feature",
  "properties": {
    "iso:country":"DE",
    "sg:address":"Im Grund 4",
    "sg:city":"Heiligkreuzsteinach",
    "sg:phone":"+49 6220/8611",
    "sg:postcode":"69253",
    "sg:province":"Baden-W\u00fcrttemberg",
    "wof:name":"Karl Hei\u00df",
    "wof:placetype":"venue"
},
  "geometry": {"coordinates":[8.7657461166,49.4986801147],"type":"Point"}
}