{
  "type": "Feature",
  "properties": {
    "iso:country":"DE",
    "sg:address":"Weng 5",
    "sg:city":"Griesst\u00e4tt",
    "sg:phone":"+49 8038/765",
    "sg:postcode":"83556",
    "sg:province":"Bayern",
    "wof:name":"Peterhof Antiquit\u00e4ten Gmbh",
    "wof:placetype":"venue"
},
  "geometry": {"coordinates":[12.174024,47.976852],"type":"Point"}
}