{
  "type": "Feature",
  "properties": {
    "iso:country":"DE",
    "sg:address":"Eschollbr\u00fccker Str. 42",
    "sg:city":"Darmstadt",
    "sg:phone":"+49 6151/317046",
    "sg:postcode":"64295",
    "sg:province":"Hessen",
    "wof:name":"Nova Videothek Gmbh",
    "wof:placetype":"venue"
},
  "geometry": {"coordinates":[8.634147644,49.8582878113],"type":"Point"}
}