{
  "type": "Feature",
  "properties": {
    "iso:country":"DE",
    "sg:address":"Theoderichstr. 2",
    "sg:city":"Bochum",
    "sg:phone":"+49 234/504025",
    "sg:postcode":"44803",
    "sg:province":"Nordrhein-Westfalen",
    "wof:name":"G. Bertling",
    "wof:placetype":"venue"
},
  "geometry": {"coordinates":[7.252301,51.469093],"type":"Point"}
}