{
  "type": "Feature",
  "properties": {
    "iso:country":"DE",
    "sg:address":"Schuhstr. 17",
    "sg:city":"Celle",
    "sg:phone":"+49 5141/21110",
    "sg:postcode":"29221",
    "sg:province":"Niedersachsen",
    "wof:name":"Margits Magazin Verlags-gmbh",
    "wof:placetype":"venue"
},
  "geometry": {"coordinates":[10.0836439133,52.6256866455],"type":"Point"}
}