{
  "type": "Feature",
  "properties": {
    "iso:country":"DE",
    "sg:address":"Sutthauser Str. 47",
    "sg:city":"Georgsmarienh\u00fctte",
    "sg:phone":"+49 5401/30660",
    "sg:postcode":"49124",
    "sg:province":"Niedersachsen",
    "wof:name":"Pizzeria Le Journal",
    "wof:placetype":"venue"
},
  "geometry": {"coordinates":[8.0153064728,52.2294883728],"type":"Point"}
}