{
  "type": "Feature",
  "properties": {
    "iso:country":"DE",
    "sg:address":"Weckmarkt 11",
    "sg:city":"Frankfurt",
    "sg:phone":"+49 69/292081",
    "sg:postcode":"60311",
    "sg:province":"Hessen",
    "wof:name":"Drabert Michael Fuchs",
    "wof:placetype":"venue"
},
  "geometry": {"coordinates":[8.685969,50.110245],"type":"Point"}
}