{
  "type": "Feature",
  "properties": {
    "iso:country":"DE",
    "sg:address":"Goethestr. 12",
    "sg:city":"Polch",
    "sg:phone":"+49 2654/6035",
    "sg:postcode":"56751",
    "sg:province":"Rheinland-Pfalz",
    "wof:name":"Manfred M\u00f6sch Steinmetzbetrieb",
    "wof:placetype":"venue"
},
  "geometry": {"coordinates":[7.3138771057,50.3029136658],"type":"Point"}
}