{
  "type": "Feature",
  "properties": {
    "iso:country":"DE",
    "sg:address":"Dieselstr. 10",
    "sg:city":"Ilvesheim",
    "sg:phone":"+49 621/493169",
    "sg:postcode":"68549",
    "sg:province":"Baden-W\u00fcrttemberg",
    "wof:name":"Joh. Und Aug. Haun",
    "wof:placetype":"venue"
},
  "geometry": {"coordinates":[8.566419,49.480881],"type":"Point"}
}