{
  "type": "Feature",
  "properties": {
    "iso:country":"DE",
    "sg:address":"Gildenstr. 13",
    "sg:city":"Bochum",
    "sg:phone":"+49 2327/18506",
    "sg:postcode":"44866",
    "sg:province":"Nordrhein-Westfalen",
    "wof:name":"A. Leyerer-m\u00fcller",
    "wof:placetype":"venue"
},
  "geometry": {"coordinates":[7.154068,51.488007],"type":"Point"}
}