{
  "type": "Feature",
  "properties": {
    "iso:country":"DE",
    "sg:address":"Am Westheck 96",
    "sg:city":"Dortmund",
    "sg:phone":"+49 231/202153",
    "sg:postcode":"44309",
    "sg:province":"Nordrhein-Westfalen",
    "wof:name":"Esra Partnerschaft F\u00fcr Freie Parit\u00e4tische Sozialpflege-",
    "wof:placetype":"venue"
},
  "geometry": {"coordinates":[7.53757,51.531898],"type":"Point"}
}