{
  "type": "Feature",
  "properties": {
    "iso:country":"DE",
    "sg:address":"Zur Langen Br\u00fccke 42",
    "sg:city":"H\u00fcnxe",
    "sg:phone":"+49 2858/2060",
    "sg:postcode":"46569",
    "sg:province":"Nordrhein-Westfalen",
    "wof:name":"Johann Welter",
    "wof:placetype":"venue"
},
  "geometry": {"coordinates":[6.771166,51.644512],"type":"Point"}
}