{
  "type": "Feature",
  "properties": {
    "iso:country":"DE",
    "sg:address":"Siedlung 4 a",
    "sg:city":"Telz",
    "sg:phone":"+49 3377/301618",
    "sg:postcode":"15806",
    "sg:province":"Brandenburg",
    "wof:name":"Lv-landwirtschaftliche Produktions-verm\u00f6gens- Und",
    "wof:placetype":"venue"
},
  "geometry": {"coordinates":[13.44803,52.215515],"type":"Point"}
}