{
  "type": "Feature",
  "properties": {
    "iso:country":"DE",
    "sg:address":"Am Waisenhausplatz 26",
    "sg:city":"Pforzheim",
    "sg:phone":"+49 7231/359466",
    "sg:postcode":"75172",
    "sg:province":"Baden-W\u00fcrttemberg",
    "wof:name":"Goldstadt-immobilien Gmbh",
    "wof:placetype":"venue"
},
  "geometry": {"coordinates":[8.7002372742,48.8900222778],"type":"Point"}
}