{
  "type": "Feature",
  "properties": {
    "iso:country":"DE",
    "sg:address":"Diekstraat 1",
    "sg:city":"Norderfriedrichskoog",
    "sg:postcode":"25870",
    "sg:province":"Schleswig-Holstein",
    "wof:name":"Lilly Gmbh",
    "wof:placetype":"venue"
},
  "geometry": {"coordinates":[8.90525,54.405521],"type":"Point"}
}