{
  "type": "Feature",
  "properties": {
    "iso:country":"DE",
    "sg:address":"Kutusowstr. 44",
    "sg:city":"Chemnitz",
    "sg:phone":"+49 371/73390",
    "sg:postcode":"09130",
    "sg:province":"Sachsen",
    "wof:name":"Frank Drobniewski",
    "wof:placetype":"venue"
},
  "geometry": {"coordinates":[12.9680767059,50.8335494995],"type":"Point"}
}