{
  "type": "Feature",
  "properties": {
    "iso:country":"DE",
    "sg:address":"Dahlemer Weg 73",
    "sg:city":"Berlin",
    "sg:phone":"+49 30/8174972",
    "sg:postcode":"14167",
    "sg:province":"Berlin",
    "wof:name":"Hans Sch\u00fcttler",
    "wof:placetype":"venue"
},
  "geometry": {"coordinates":[13.27955,52.431538],"type":"Point"}
}