{
  "type": "Feature",
  "properties": {
    "iso:country":"DE",
    "sg:address":"Rentzelstr. 16",
    "sg:city":"Hamburg",
    "sg:phone":"+49 40/447548",
    "sg:postcode":"20146",
    "sg:province":"Hamburg",
    "wof:name":"Niels Hansen Architekt",
    "wof:placetype":"venue"
},
  "geometry": {"coordinates":[9.9796,53.566402],"type":"Point"}
}