{
  "type": "Feature",
  "properties": {
    "iso:country":"DE",
    "sg:address":"Olandsweg 27",
    "sg:city":"Bad Malente-Grevesm\u00fchlen",
    "sg:phone":"+49 4523/99230",
    "sg:postcode":"23714",
    "sg:province":"Schleswig-Holstein",
    "wof:name":"Appartmenthotel Garni Dieksee-h\u00f6rn",
    "wof:placetype":"venue"
},
  "geometry": {"coordinates":[10.548459053,54.1617393494],"type":"Point"}
}