{
  "type": "Feature",
  "properties": {
    "iso:country":"DE",
    "sg:address":"Humboldtstr. 6",
    "sg:city":"Wuppertal",
    "sg:phone":"+49 202/280360",
    "sg:postcode":"42283",
    "sg:province":"Nordrhein-Westfalen",
    "wof:name":"Pro Parkett Gro\u00df- Und Einzelhandel Gmbh",
    "wof:placetype":"venue"
},
  "geometry": {"coordinates":[7.1774811745,51.2733573914],"type":"Point"}
}