{
  "type": "Feature",
  "properties": {
    "iso:country":"DE",
    "sg:address":"Liebensteiner Str. 7",
    "sg:city":"Moorgrund",
    "sg:phone":"+49 3695/84691",
    "sg:postcode":"36433",
    "sg:province":"Th\u00fcringen",
    "wof:name":"Kurt Malsch",
    "wof:placetype":"venue"
},
  "geometry": {"coordinates":[10.3011636734,50.8338241577],"type":"Point"}
}