{
  "type": "Feature",
  "properties": {
    "iso:country":"DE",
    "sg:address":"Nerscheider Weg 56",
    "sg:city":"Aachen",
    "sg:phone":"+49 2408/930153",
    "sg:postcode":"52076",
    "sg:province":"Nordrhein-Westfalen",
    "wof:name":"H. Begas Rechtsanwalt",
    "wof:placetype":"venue"
},
  "geometry": {"coordinates":[6.1419391632,50.716342926],"type":"Point"}
}