{
  "type": "Feature",
  "properties": {
    "iso:country":"DE",
    "sg:address":"Altenburger Str 7",
    "sg:city":"Meuselwitz",
    "sg:phone":"+49 3448/4460",
    "sg:postcode":"04610",
    "sg:province":"Th\u00fcringen",
    "wof:name":"Hanns Glass Gmbh & Co. Kg Niederlassung Meuselwitz/werk Ii",
    "wof:placetype":"venue"
},
  "geometry": {"coordinates":[12.299363,51.045746],"type":"Point"}
}