{
  "type": "Feature",
  "properties": {
    "iso:country":"DE",
    "sg:address":"Ebersbacher Str. 4",
    "sg:city":"K\u00f6tz",
    "sg:phone":"+49 8221/32014",
    "sg:postcode":"89359",
    "sg:province":"Bayern",
    "wof:name":"R\u00c4dler Eiprodukte Gmbh",
    "wof:placetype":"venue"
},
  "geometry": {"coordinates":[10.30048,48.41016],"type":"Point"}
}