{
  "type": "Feature",
  "properties": {
    "iso:country":"DE",
    "sg:address":"Schubertstr. 54",
    "sg:city":"Frankfurt",
    "sg:postcode":"15234",
    "sg:province":"Brandenburg",
    "wof:name":"Will Frischdienst Vertriebs- Und Handels Gmbh",
    "wof:placetype":"venue"
},
  "geometry": {"coordinates":[14.4846286774,52.3573951721],"type":"Point"}
}