{
  "type": "Feature",
  "properties": {
    "iso:country":"DE",
    "sg:address":"Theaterring 4",
    "sg:city":"Zittau",
    "sg:postcode":"02763",
    "sg:province":"Sachsen",
    "wof:name":"Presswerk Ottendorf-okrilla Gmbh",
    "wof:placetype":"venue"
},
  "geometry": {"coordinates":[14.8114881516,50.8983078003],"type":"Point"}
}