{
  "type": "Feature",
  "properties": {
    "iso:country":"DE",
    "sg:address":"Steinstr. 21",
    "sg:city":"Gotha",
    "sg:phone":"+49 3621/405948",
    "sg:postcode":"99867",
    "sg:province":"Th\u00fcringen",
    "wof:name":"Restaurant Zur Kugel",
    "wof:placetype":"venue"
},
  "geometry": {"coordinates":[10.7115497589,50.9580116272],"type":"Point"}
}