{
  "type": "Feature",
  "properties": {
    "iso:country":"DE",
    "sg:address":"Herrnsheimer Hauptstr. 30",
    "sg:city":"Worms",
    "sg:phone":"+49 6241/58133",
    "sg:postcode":"67550",
    "sg:province":"Rheinland-Pfalz",
    "wof:name":"Willi Kercher",
    "wof:placetype":"venue"
},
  "geometry": {"coordinates":[8.3305864334,49.6570243835],"type":"Point"}
}