{
  "type": "Feature",
  "properties": {
    "iso:country":"DE",
    "sg:address":"Feldstr. 5",
    "sg:city":"Worbis",
    "sg:phone":"+49 36074/93956",
    "sg:postcode":"37339",
    "sg:province":"Th\u00fcringen",
    "wof:name":"Michael Kaiser",
    "wof:placetype":"venue"
},
  "geometry": {"coordinates":[10.3596506119,51.427898407],"type":"Point"}
}