{
  "type": "Feature",
  "properties": {
    "iso:country":"DE",
    "sg:address":"L\u00fcttelforst 137",
    "sg:city":"Schwalmtal",
    "sg:phone":"+49 2163/49697",
    "sg:postcode":"41366",
    "sg:province":"Nordrhein-Westfalen",
    "wof:name":"Karl Wiater Garten- Und",
    "wof:placetype":"venue"
},
  "geometry": {"coordinates":[6.25711,51.190411],"type":"Point"}
}