{
  "type": "Feature",
  "properties": {
    "iso:country":"DE",
    "sg:address":"Eppendorfer Weg 99",
    "sg:city":"Hamburg",
    "sg:phone":"+49 40/404180",
    "sg:postcode":"20259",
    "sg:province":"Hamburg",
    "wof:name":"Edith Dohmann",
    "wof:placetype":"venue"
},
  "geometry": {"coordinates":[9.960812,53.573757],"type":"Point"}
}