{
  "type": "Feature",
  "properties": {
    "iso:country":"DE",
    "sg:address":"Am Bahnhof",
    "sg:city":"Rangsdorf",
    "sg:phone":"+49 33708/20210",
    "sg:postcode":"15834",
    "sg:province":"Brandenburg",
    "wof:name":"Blumen & Geschenke Manfred Boden",
    "wof:placetype":"venue"
},
  "geometry": {"coordinates":[13.430348,52.29388],"type":"Point"}
}