{
  "type": "Feature",
  "properties": {
    "iso:country":"DE",
    "sg:address":"Ludwigstr. 93",
    "sg:city":"Oer-Erkenschwick",
    "sg:phone":"+49 2368/6287",
    "sg:postcode":"45739",
    "sg:province":"Nordrhein-Westfalen",
    "wof:name":"W. Pennekamp",
    "wof:placetype":"venue"
},
  "geometry": {"coordinates":[7.275902,51.639694],"type":"Point"}
}