{
  "type": "Feature",
  "properties": {
    "iso:country":"DE",
    "sg:address":"Nikolausstr. 4",
    "sg:city":"Berg",
    "sg:phone":"+49 8151/95715",
    "sg:postcode":"82335",
    "sg:province":"Bayern",
    "wof:name":"Schreinerei Pfisterer Gmbh",
    "wof:placetype":"venue"
},
  "geometry": {"coordinates":[11.382479,47.962418],"type":"Point"}
}