{
  "type": "Feature",
  "properties": {
    "iso:country":"DE",
    "sg:address":"Nr. 14 a",
    "sg:city":"Gera",
    "sg:postcode":"07554",
    "sg:province":"Th\u00fcringen",
    "wof:name":"Tietz Dach Gmbh",
    "wof:placetype":"venue"
},
  "geometry": {"coordinates":[-83.738464,43.38332],"type":"Point"}
}