{
  "type": "Feature",
  "properties": {
    "iso:country":"DE",
    "sg:address":"Karl-Marx-Platz 2",
    "sg:city":"Oelsnitz",
    "sg:phone":"+49 37421/24888",
    "sg:postcode":"08606",
    "sg:province":"Sachsen",
    "wof:name":"Fkw-steuerberatungsges. Mbh",
    "wof:placetype":"venue"
},
  "geometry": {"coordinates":[12.1734399796,50.4144058228],"type":"Point"}
}