{
  "type": "Feature",
  "properties": {
    "iso:country":"DE",
    "sg:address":"Osnabr\u00fccker Str. 32",
    "sg:city":"Rheine",
    "sg:phone":"+49 5971/71101",
    "sg:postcode":"48429",
    "sg:province":"Nordrhein-Westfalen",
    "wof:name":"Karl Hopster Inh. Georg Rabert",
    "wof:placetype":"venue"
},
  "geometry": {"coordinates":[7.447872,52.281567],"type":"Point"}
}