{
  "type": "Feature",
  "properties": {
    "iso:country":"DE",
    "sg:address":"Bischofstr. 2",
    "sg:city":"Stolberg",
    "sg:phone":"+49 2402/25319",
    "sg:postcode":"52223",
    "sg:province":"Nordrhein-Westfalen",
    "wof:name":"Bestattungen Deussen Stolberg Vormals Jakob Averdieck Zwdl.",
    "wof:placetype":"venue"
},
  "geometry": {"coordinates":[6.217111,50.755566],"type":"Point"}
}