{
  "type": "Feature",
  "properties": {
    "iso:country":"DE",
    "sg:address":"Hauptstr. 37",
    "sg:city":"B\u00fchlertal",
    "sg:phone":"+49 7223/72185",
    "sg:postcode":"77830",
    "sg:province":"Baden-W\u00fcrttemberg",
    "wof:name":"Deutscher Kaiser",
    "wof:placetype":"venue"
},
  "geometry": {"coordinates":[8.1796350479,48.6931228638],"type":"Point"}
}