{
  "type": "Feature",
  "properties": {
    "iso:country":"DE",
    "sg:address":"Am Blumenacker 13",
    "sg:city":"Eschenburg",
    "sg:phone":"+49 2774/71561",
    "sg:postcode":"35713",
    "sg:province":"Hessen",
    "wof:name":"Karle Concept",
    "wof:placetype":"venue"
},
  "geometry": {"coordinates":[8.344881,50.819935],"type":"Point"}
}