{
  "type": "Feature",
  "properties": {
    "iso:country":"DE",
    "sg:address":"Becker-G\u00f6ring-Str. 15",
    "sg:city":"Karlsbad",
    "sg:phone":"+49 7248/91790",
    "sg:postcode":"76307",
    "sg:province":"Baden-W\u00fcrttemberg",
    "wof:name":"Hago Druck Und Medien Gmbh",
    "wof:placetype":"venue"
},
  "geometry": {"coordinates":[8.5053911209,48.8800849915],"type":"Point"}
}