{
  "type": "Feature",
  "properties": {
    "iso:country":"DE",
    "sg:address":"Am Bahnhof 6",
    "sg:city":"Schee\u00dfel",
    "sg:phone":"+49 4263/1210",
    "sg:postcode":"27383",
    "sg:province":"Niedersachsen",
    "wof:name":"Deutsche Bahn Ag",
    "wof:placetype":"venue"
},
  "geometry": {"coordinates":[9.4963779449,53.1657104492],"type":"Point"}
}