{
  "type": "Feature",
  "properties": {
    "iso:country":"DE",
    "sg:address":"Zum Osterberg 13",
    "sg:city":"Dederstedt",
    "sg:phone":"+49 34773/20493",
    "sg:postcode":"06295",
    "sg:province":"Sachsen-Anhalt",
    "wof:name":"P. H\u00f6hne",
    "wof:placetype":"venue"
},
  "geometry": {"coordinates":[11.6926822662,51.5435638428],"type":"Point"}
}