{
  "type": "Feature",
  "properties": {
    "iso:country":"DE",
    "sg:address":"Hirtenwiesen 156",
    "sg:city":"Sachsenheim",
    "sg:phone":"+49 7147/6865",
    "sg:postcode":"74343",
    "sg:province":"Baden-W\u00fcrttemberg",
    "wof:name":"Bp-baugesellschaft Mbh",
    "wof:placetype":"venue"
},
  "geometry": {"coordinates":[9.058313,48.954277],"type":"Point"}
}