{
  "type": "Feature",
  "properties": {
    "iso:country":"DE",
    "sg:address":"Bahnhofsplatz 3",
    "sg:city":"Ottobrunn",
    "sg:phone":"+49 89/6014032",
    "sg:postcode":"85521",
    "sg:province":"Bayern",
    "wof:name":"Kreissparkasse M\u00fcnchen",
    "wof:placetype":"venue"
},
  "geometry": {"coordinates":[11.657192,48.070751],"type":"Point"}
}