{
  "type": "Feature",
  "properties": {
    "iso:country":"DE",
    "sg:address":"Dudweiler Landstr. 151",
    "sg:city":"Saarbr\u00fccken",
    "sg:phone":"+49 681/371570",
    "sg:postcode":"66123",
    "sg:province":"Saarland",
    "wof:name":"Helmut Schreiner Metallbau Gmbh",
    "wof:placetype":"venue"
},
  "geometry": {"coordinates":[7.005799,49.250507],"type":"Point"}
}