{
  "type": "Feature",
  "properties": {
    "iso:country":"DE",
    "sg:address":"Weinbergstr. 30",
    "sg:city":"Potsdam",
    "sg:postcode":"14469",
    "sg:province":"Brandenburg",
    "wof:name":"Stefan Gro\u00dfmann",
    "wof:placetype":"venue"
},
  "geometry": {"coordinates":[13.048159,52.403732],"type":"Point"}
}