{
  "type": "Feature",
  "properties": {
    "iso:country":"DE",
    "sg:address":"Schleitstr. 5",
    "sg:city":"Schmelz",
    "sg:phone":"+49 6887/5992",
    "sg:postcode":"66839",
    "sg:province":"Saarland",
    "wof:name":"H.w. Matzak",
    "wof:placetype":"venue"
},
  "geometry": {"coordinates":[6.896088,49.471485],"type":"Point"}
}