{
  "type": "Feature",
  "properties": {
    "iso:country":"DE",
    "sg:address":"M\u00fchlwiesenstr. 35",
    "sg:city":"St. Georgen",
    "sg:phone":"+49 7724/3487",
    "sg:postcode":"78112",
    "sg:province":"Baden-W\u00fcrttemberg",
    "wof:name":"Hans Besch Architekt",
    "wof:placetype":"venue"
},
  "geometry": {"coordinates":[8.370877,48.135326],"type":"Point"}
}