{
  "type": "Feature",
  "properties": {
    "iso:country":"DE",
    "sg:address":"Hauptstr. 84",
    "sg:city":"Voigtsdorf",
    "sg:phone":"+49 4937/3651819",
    "sg:postcode":"09619",
    "sg:province":"Sachsen",
    "wof:name":"Polsterm\u00d6bel Geschw. B\u00dcschel Kg",
    "wof:placetype":"venue"
},
  "geometry": {"coordinates":[13.3948488235,50.7478179932],"type":"Point"}
}