{
  "type": "Feature",
  "properties": {
    "iso:country":"DE",
    "sg:address":"J\u00f6\u00dfnitzer Str. 64",
    "sg:city":"Plauen",
    "sg:phone":"+49 3741/225306",
    "sg:postcode":"08525",
    "sg:province":"Sachsen",
    "wof:name":"Hut-zeune",
    "wof:placetype":"venue"
},
  "geometry": {"coordinates":[12.140924,50.504368],"type":"Point"}
}