{
  "type": "Feature",
  "properties": {
    "iso:country":"DE",
    "sg:address":"Robbenplate 9",
    "sg:city":"Bremen",
    "sg:phone":"+49 421/571122",
    "sg:postcode":"28259",
    "sg:province":"Bremen",
    "wof:name":"Ddhb Dachdiscount Handels- Und Beteiligungs Gmbh",
    "wof:placetype":"venue"
},
  "geometry": {"coordinates":[8.736934,53.051243],"type":"Point"}
}