{
  "type": "Feature",
  "properties": {
    "iso:country":"DE",
    "sg:address":"Reutersbrunnenstr. 34",
    "sg:city":"N\u00fcrnberg",
    "sg:phone":"+49 911/2312425",
    "sg:postcode":"90429",
    "sg:province":"Bayern",
    "wof:name":"Kinder- Und Jugendheim",
    "wof:placetype":"venue"
},
  "geometry": {"coordinates":[11.0542898178,49.4547157288],"type":"Point"}
}