{
  "type": "Feature",
  "properties": {
    "iso:country":"DE",
    "sg:address":"An der Abens 20",
    "sg:city":"Neustadt",
    "sg:phone":"+49 9445/21132",
    "sg:postcode":"93333",
    "sg:province":"Bayern",
    "wof:name":"Ino Immobilienvermittlung In Nieder- Und Oberbayern",
    "wof:placetype":"venue"
},
  "geometry": {"coordinates":[11.7793207169,48.8236618042],"type":"Point"}
}