{
  "type": "Feature",
  "properties": {
    "iso:country":"DE",
    "sg:address":"Ingerslebener Weg 6",
    "sg:city":"Erfurt",
    "sg:phone":"+49 361/7969170",
    "sg:postcode":"99094",
    "sg:province":"Th\u00fcringen",
    "wof:name":"Becker & Sch\u00f6n Gmbh",
    "wof:placetype":"venue"
},
  "geometry": {"coordinates":[10.988034,50.920631],"type":"Point"}
}