{
  "type": "Feature",
  "properties": {
    "iso:country":"DE",
    "sg:address":"Kleiststr. 7",
    "sg:city":"Berlin",
    "sg:phone":"+49 30/2117702",
    "sg:postcode":"10787",
    "sg:province":"Berlin",
    "wof:name":"Pragers",
    "wof:placetype":"venue"
},
  "geometry": {"coordinates":[13.349627,52.500668],"type":"Point"}
}