{
  "type": "Feature",
  "properties": {
    "iso:country":"DE",
    "sg:address":"K\u00f6nigstr. 62",
    "sg:city":"Duisburg",
    "sg:phone":"+49 2066/8159",
    "sg:postcode":"47198",
    "sg:province":"Nordrhein-Westfalen",
    "wof:name":"Brigitta B\u00fcchele Immobilienmaklerin",
    "wof:placetype":"venue"
},
  "geometry": {"coordinates":[6.7171878815,51.4518318176],"type":"Point"}
}