{
  "type": "Feature",
  "properties": {
    "iso:country":"DE",
    "sg:address":"Erfurter Str. 25",
    "sg:city":"Eching",
    "sg:phone":"+49 89/3191903",
    "sg:postcode":"85386",
    "sg:province":"Bayern",
    "wof:name":"Spedition Fritzner Gmbh",
    "wof:placetype":"venue"
},
  "geometry": {"coordinates":[11.6223249435,48.3062324524],"type":"Point"}
}