{
  "type": "Feature",
  "properties": {
    "iso:country":"DE",
    "sg:address":"Probst Jesar 16",
    "sg:city":"Probst Jesar",
    "sg:phone":"+49 38855/51550",
    "sg:postcode":"19249",
    "sg:province":"Mecklenburg-Vorpommern",
    "wof:name":"Restaurant Waldbaude",
    "wof:placetype":"venue"
},
  "geometry": {"coordinates":[11.1179895401,53.3012084961],"type":"Point"}
}