{
  "type": "Feature",
  "properties": {
    "iso:country":"DE",
    "sg:address":"Willibrordusstr. 70",
    "sg:city":"Grevenbroich",
    "sg:phone":"+49 2181/3598",
    "sg:postcode":"41517",
    "sg:province":"Nordrhein-Westfalen",
    "wof:name":"Michael Z\u00f6lling Architekt",
    "wof:placetype":"venue"
},
  "geometry": {"coordinates":[6.591115,51.066273],"type":"Point"}
}