{
  "type": "Feature",
  "properties": {
    "iso:country":"DE",
    "sg:address":"S\u00e4lzerweg 8",
    "sg:city":"Soest",
    "sg:postcode":"59494",
    "sg:province":"Nordrhein-Westfalen",
    "wof:name":"Franz Schreiber Gmbh",
    "wof:placetype":"venue"
},
  "geometry": {"coordinates":[8.1461639404,51.5537567139],"type":"Point"}
}