{
  "type": "Feature",
  "properties": {
    "iso:country":"DE",
    "sg:address":"Oberwalting 17",
    "sg:city":"Leiblfing",
    "sg:phone":"+49 9427/230",
    "sg:postcode":"94339",
    "sg:province":"Bayern",
    "wof:name":"Josef Lermer",
    "wof:placetype":"venue"
},
  "geometry": {"coordinates":[12.5150337219,48.7778701782],"type":"Point"}
}