{
  "type": "Feature",
  "properties": {
    "iso:country":"DE",
    "sg:address":"Heggelbach 43",
    "sg:city":"Leutkirch",
    "sg:postcode":"88299",
    "sg:province":"Baden-W\u00fcrttemberg",
    "wof:name":"Marzari Technik Gmbh",
    "wof:placetype":"venue"
},
  "geometry": {"coordinates":[9.98208,47.818737],"type":"Point"}
}