{
  "type": "Feature",
  "properties": {
    "iso:country":"DE",
    "sg:address":"Leostr. 13",
    "sg:city":"\u00dcbach-Palenberg",
    "sg:phone":"+49 2404/82213",
    "sg:postcode":"52531",
    "sg:province":"Nordrhein-Westfalen",
    "wof:name":"Bau Form Bauunternehmung Gmbh",
    "wof:placetype":"venue"
},
  "geometry": {"coordinates":[6.119494,50.919815],"type":"Point"}
}