{
  "type": "Feature",
  "properties": {
    "iso:country":"DE",
    "sg:address":"Steinstr. 45",
    "sg:city":"Gadebusch",
    "sg:phone":"+49 3886/35333",
    "sg:postcode":"19205",
    "sg:province":"Mecklenburg-Vorpommern",
    "wof:name":"E.-j. Heller",
    "wof:placetype":"venue"
},
  "geometry": {"coordinates":[11.115172,53.704876],"type":"Point"}
}