{
  "type": "Feature",
  "properties": {
    "iso:country":"DE",
    "sg:address":"Am Sperlingsberge 56 c",
    "sg:city":"Nohra",
    "sg:phone":"+49 3643/825296",
    "sg:postcode":"99428",
    "sg:province":"Th\u00fcringen",
    "wof:name":"Profund-nohra Helmut Geyer",
    "wof:placetype":"venue"
},
  "geometry": {"coordinates":[11.233146,50.960175],"type":"Point"}
}