{
  "type": "Feature",
  "properties": {
    "iso:country":"DE",
    "sg:address":"Gerberweg 10",
    "sg:city":"Preetz",
    "sg:phone":"+49 4342/5362",
    "sg:postcode":"24211",
    "sg:province":"Schleswig-Holstein",
    "wof:name":"Herbert Meyer",
    "wof:placetype":"venue"
},
  "geometry": {"coordinates":[10.269381,54.219997],"type":"Point"}
}