{
  "type": "Feature",
  "properties": {
    "iso:country":"DE",
    "sg:address":"Kaulbachstr. 21",
    "sg:city":"M\u00fcnchen",
    "sg:phone":"+49 89/28787766",
    "sg:postcode":"80539",
    "sg:province":"Bayern",
    "wof:name":"Susanne Brandl Rechtsanw\u00e4ltin",
    "wof:placetype":"venue"
},
  "geometry": {"coordinates":[11.5831832886,48.1482048035],"type":"Point"}
}