{
  "type": "Feature",
  "properties": {
    "iso:country":"DE",
    "sg:address":"Burgstr. 22",
    "sg:city":"Filderstadt",
    "sg:phone":"+49 711/7079250",
    "sg:postcode":"70794",
    "sg:province":"Baden-W\u00fcrttemberg",
    "wof:name":"Harald Schr\u00f6der Steuerberater",
    "wof:placetype":"venue"
},
  "geometry": {"coordinates":[9.2142457962,48.6791419983],"type":"Point"}
}