{
  "type": "Feature",
  "properties": {
    "iso:country":"DE",
    "sg:address":"Hauptstr. 126",
    "sg:city":"Frechen",
    "sg:phone":"+49 2234/17720",
    "sg:postcode":"50226",
    "sg:province":"Nordrhein-Westfalen",
    "wof:name":"Eiscafe Bistro Dolomiti",
    "wof:placetype":"venue"
},
  "geometry": {"coordinates":[6.807183,50.909389],"type":"Point"}
}