{
  "type": "Feature",
  "properties": {
    "iso:country":"DE",
    "sg:address":"Grabenstr. 4",
    "sg:city":"Wallhausen",
    "sg:phone":"+49 6706/1432",
    "sg:postcode":"55595",
    "sg:province":"Rheinland-Pfalz",
    "wof:name":"Heinz Schmitt Ingenieur",
    "wof:placetype":"venue"
},
  "geometry": {"coordinates":[7.7643461227,49.8902778625],"type":"Point"}
}