{
  "type": "Feature",
  "properties": {
    "iso:country":"DE",
    "sg:address":"Samentalweg 17",
    "sg:city":"Aalen",
    "sg:phone":"+49 7361/8640",
    "sg:postcode":"73432",
    "sg:province":"Baden-W\u00fcrttemberg",
    "wof:name":"Willi Hopfensitz Architekt",
    "wof:placetype":"venue"
},
  "geometry": {"coordinates":[10.123977,48.814316],"type":"Point"}
}