{
  "type": "Feature",
  "properties": {
    "iso:country":"DE",
    "sg:address":"Postfach 5143:: 71376 Weinstadt:: Germany.^^Theodor Heuss Str 18::",
    "sg:city":"Weinstadt",
    "sg:phone":"+49 7151/96400",
    "sg:postcode":"71384",
    "sg:province":"Baden-W\u00fcrttemberg",
    "wof:name":"Raiffeisenbank Weinstadt Eg",
    "wof:placetype":"venue"
},
  "geometry": {"coordinates":[9.365385,48.812263],"type":"Point"}
}