{
  "type": "Feature",
  "properties": {
    "iso:country":"DE",
    "sg:address":"Meindlstr. 25",
    "sg:city":"M\u00fcnchen",
    "sg:phone":"+49 89/74790004",
    "sg:postcode":"81373",
    "sg:province":"Bayern",
    "wof:name":"Gabriele Grundl Steuerberater",
    "wof:placetype":"venue"
},
  "geometry": {"coordinates":[11.5383338928,48.117351532],"type":"Point"}
}