{
  "type": "Feature",
  "properties": {
    "iso:country":"DE",
    "sg:city":"Weitefeld",
    "sg:phone":"+49 2743/4260",
    "sg:postcode":"57586",
    "sg:province":"Rheinland-Pfalz",
    "wof:name":"Kurt Nagel B\u00e4ckerei",
    "wof:placetype":"venue"
},
  "geometry": {"coordinates":[7.925693,50.724525],"type":"Point"}
}