{
  "type": "Feature",
  "properties": {
    "iso:country":"DE",
    "sg:address":"Ilzweg 3",
    "sg:city":"Olching",
    "sg:phone":"+49 8142/13891",
    "sg:postcode":"82140",
    "sg:province":"Bayern",
    "wof:name":"Scherb Gmbh",
    "wof:placetype":"venue"
},
  "geometry": {"coordinates":[11.3333425522,48.2112197876],"type":"Point"}
}