{
  "type": "Feature",
  "properties": {
    "iso:country":"DE",
    "sg:address":"Niederwald 7",
    "sg:city":"Asendorf",
    "sg:phone":"+49 4253/517",
    "sg:postcode":"27330",
    "sg:province":"Niedersachsen",
    "wof:name":"E. Wehrhahn",
    "wof:placetype":"venue"
},
  "geometry": {"coordinates":[8.9837856293,52.7736816406],"type":"Point"}
}