{
  "type": "Feature",
  "properties": {
    "iso:country":"DE",
    "sg:address":"Wastelbauerstr. 5",
    "sg:city":"M\u00fcnchen",
    "sg:phone":"+49 89/8113409",
    "sg:postcode":"81247",
    "sg:province":"Bayern",
    "wof:name":"Detlev Richter",
    "wof:placetype":"venue"
},
  "geometry": {"coordinates":[11.4821557999,48.1684303284],"type":"Point"}
}