{
  "type": "Feature",
  "properties": {
    "iso:country":"DE",
    "sg:address":"Bornstr. 25",
    "sg:city":"Rodenbach",
    "sg:phone":"+49 6184/51566",
    "sg:postcode":"63517",
    "sg:province":"Hessen",
    "wof:name":"Ev. Pfarramt Rodenbach Iii",
    "wof:placetype":"venue"
},
  "geometry": {"coordinates":[9.0631732941,50.1386985779],"type":"Point"}
}