{
  "type": "Feature",
  "properties": {
    "iso:country":"DE",
    "sg:address":"Tolle Stra\u00dfe",
    "sg:city":"Buchshausen",
    "sg:phone":"+49 15353153",
    "sg:postcode":"15464",
    "wof:name":"Bc Bliesheim Tischtennis",
    "wof:placetype":"venue"
},
  "geometry": {"coordinates":[-79.434578,39.923481],"type":"Point"}
}