{
  "type": "Feature",
  "properties": {
    "iso:country":"DE",
    "sg:address":"Waldhornstr. 12",
    "sg:city":"Memmingen",
    "sg:phone":"+49 8331/3454",
    "sg:postcode":"87700",
    "sg:province":"Bayern",
    "wof:name":"Axel Haupt",
    "wof:placetype":"venue"
},
  "geometry": {"coordinates":[10.184997,47.984226],"type":"Point"}
}