{
  "type": "Feature",
  "properties": {
    "iso:country":"DE",
    "sg:address":"Stiermannstr. 5",
    "sg:city":"Augsburg",
    "sg:phone":"+49 821/411957",
    "sg:postcode":"86154",
    "sg:province":"Bayern",
    "wof:name":"Goldener Falke",
    "wof:placetype":"venue"
},
  "geometry": {"coordinates":[10.8750524521,48.3823013306],"type":"Point"}
}