{
  "type": "Feature",
  "properties": {
    "iso:country":"DE",
    "sg:address":"Flachsb\u00fchlstr. 1 A",
    "sg:city":"Taunusstein",
    "sg:phone":"+49 6128/43967",
    "sg:postcode":"65232",
    "sg:province":"Hessen",
    "wof:name":"Johannes W. Balzer",
    "wof:placetype":"venue"
},
  "geometry": {"coordinates":[8.1375741959,50.1322631836],"type":"Point"}
}