{
  "type": "Feature",
  "properties": {
    "iso:country":"DE",
    "sg:address":"Am Stadtbruch 14 A",
    "sg:city":"Volkmarsen",
    "sg:phone":"+49 5693/5191",
    "sg:postcode":"34471",
    "sg:province":"Hessen",
    "wof:name":"J\u00fcrgen Dallig",
    "wof:placetype":"venue"
},
  "geometry": {"coordinates":[9.107549,51.404198],"type":"Point"}
}