{
  "type": "Feature",
  "properties": {
    "iso:country":"DE",
    "sg:address":"Am Eisenwerk 51",
    "sg:city":"Hannover",
    "sg:phone":"+49 511/9286106",
    "sg:postcode":"30519",
    "sg:province":"Niedersachsen",
    "wof:name":"Multidata Service Gmbh",
    "wof:placetype":"venue"
},
  "geometry": {"coordinates":[9.78558,52.327312],"type":"Point"}
}