{
  "type": "Feature",
  "properties": {
    "iso:country":"DE",
    "sg:address":"Dorfstr. 31",
    "sg:city":"Unterleinleiter",
    "sg:phone":"+49 9198/997770",
    "sg:postcode":"91364",
    "sg:province":"Bayern",
    "wof:name":"Matthias Ottis",
    "wof:placetype":"venue"
},
  "geometry": {"coordinates":[11.1589679718,49.8383293152],"type":"Point"}
}