{
  "type": "Feature",
  "properties": {
    "iso:country":"DE",
    "sg:address":"August-Bebel-Str. 29",
    "sg:city":"Naumburg",
    "sg:postcode":"06618",
    "sg:province":"Sachsen-Anhalt",
    "wof:name":"Wespita Handels-gmbh",
    "wof:placetype":"venue"
},
  "geometry": {"coordinates":[11.8169059753,51.1539916992],"type":"Point"}
}