{
  "type": "Feature",
  "properties": {
    "iso:country":"DE",
    "sg:address":"Warnsdorfer Str. 4",
    "sg:city":"Seifhennersdorf",
    "sg:phone":"+49 3586/404747",
    "sg:postcode":"02782",
    "sg:province":"Sachsen",
    "wof:name":"Schiffner Haustechnik Gmbh",
    "wof:placetype":"venue"
},
  "geometry": {"coordinates":[14.6194496155,50.9319000244],"type":"Point"}
}