{
  "type": "Feature",
  "properties": {
    "iso:country":"DE",
    "sg:address":"Kadener Str. 1",
    "sg:city":"Alveslohe",
    "sg:phone":"+49 4193/2042",
    "sg:postcode":"25486",
    "sg:province":"Schleswig-Holstein",
    "wof:name":"Behnke Nah- Und Ferntransporte Gmbh",
    "wof:placetype":"venue"
},
  "geometry": {"coordinates":[9.926399231,53.7895927429],"type":"Point"}
}