{
  "type": "Feature",
  "properties": {
    "iso:country":"DE",
    "sg:address":"Naabgasse 35",
    "sg:city":"Burglengenfeld",
    "sg:phone":"+49 9471/1289",
    "sg:postcode":"93133",
    "sg:province":"Bayern",
    "wof:name":"J. Schwingl",
    "wof:placetype":"venue"
},
  "geometry": {"coordinates":[12.036613,49.214149],"type":"Point"}
}