{
  "type": "Feature",
  "properties": {
    "iso:country":"DE",
    "sg:address":"Alter Heerweg 22",
    "sg:city":"Aurich",
    "sg:phone":"+49 4947/912040",
    "sg:postcode":"26607",
    "sg:province":"Niedersachsen",
    "wof:name":"Sobottka",
    "wof:placetype":"venue"
},
  "geometry": {"coordinates":[7.6191248894,53.5362091064],"type":"Point"}
}