{
  "type": "Feature",
  "properties": {
    "iso:country":"DE",
    "sg:address":"Brink 33",
    "sg:city":"Ahaus",
    "sg:phone":"+49 2567/1477",
    "sg:postcode":"48683",
    "sg:province":"Nordrhein-Westfalen",
    "wof:name":"Hermann Weitkamp",
    "wof:placetype":"venue"
},
  "geometry": {"coordinates":[6.954696,52.128971],"type":"Point"}
}