{
  "type": "Feature",
  "properties": {
    "iso:country":"DE",
    "sg:address":"Reitweg 2",
    "sg:city":"Bernried",
    "sg:phone":"+49 8158/3709",
    "sg:postcode":"82347",
    "sg:province":"Bayern",
    "wof:name":"August Melf",
    "wof:placetype":"venue"
},
  "geometry": {"coordinates":[11.2943172455,47.8657188416],"type":"Point"}
}