{
  "type": "Feature",
  "properties": {
    "iso:country":"DE",
    "sg:address":"Remsstr. 1",
    "sg:city":"Kornwestheim",
    "sg:phone":"+49 7154/13020",
    "sg:postcode":"70806",
    "sg:province":"Baden-W\u00fcrttemberg",
    "wof:name":"Deckel-gildemeister Stuttgart Vertriebs Gmbh",
    "wof:placetype":"venue"
},
  "geometry": {"coordinates":[9.205351,48.862309],"type":"Point"}
}