{
  "type": "Feature",
  "properties": {
    "iso:country":"DE",
    "sg:address":"R\u00f6dingsmarkt 33",
    "sg:city":"Hamburg",
    "sg:phone":"+49 40/3256270",
    "sg:postcode":"20459",
    "sg:province":"Hamburg",
    "wof:name":"Boeckel & Co Gmbh & Co",
    "wof:placetype":"venue"
},
  "geometry": {"coordinates":[9.985802,53.546524],"type":"Point"}
}