{
  "type": "Feature",
  "properties": {
    "iso:country":"DE",
    "sg:address":"Kirchplatz 1",
    "sg:city":"Selbitz",
    "sg:phone":"+49 9280/202",
    "sg:postcode":"95152",
    "sg:province":"Bayern",
    "wof:name":"Jugendb\u00fccherei Des Evang.- Luth. Pfarramtes Selbitz",
    "wof:placetype":"venue"
},
  "geometry": {"coordinates":[11.74946,50.315372],"type":"Point"}
}