{
  "type": "Feature",
  "properties": {
    "iso:country":"DE",
    "sg:address":"Kalktal 1",
    "sg:city":"Wiehl",
    "sg:phone":"+49 2262/68001",
    "sg:postcode":"51674",
    "sg:province":"Nordrhein-Westfalen",
    "wof:name":"A. Schreiber",
    "wof:placetype":"venue"
},
  "geometry": {"coordinates":[7.5110459328,50.9678459167],"type":"Point"}
}