{
  "type": "Feature",
  "properties": {
    "iso:country":"DE",
    "sg:address":"Lusenstr. 12",
    "sg:city":"Obertraubling",
    "sg:postcode":"93083",
    "sg:province":"Bayern",
    "wof:name":"Deiminger Gmbh & Co. Kg",
    "wof:placetype":"venue"
},
  "geometry": {"coordinates":[12.1548404694,48.9654693604],"type":"Point"}
}