{
  "type": "Feature",
  "properties": {
    "iso:country":"DE",
    "sg:address":"Hochstr. 26",
    "sg:city":"Nettetal",
    "sg:phone":"+49 2153/2363",
    "sg:postcode":"41334",
    "sg:province":"Nordrhein-Westfalen",
    "wof:name":"Monique Lederwaren Erich Bauer",
    "wof:placetype":"venue"
},
  "geometry": {"coordinates":[6.276146,51.305897],"type":"Point"}
}