{
  "type": "Feature",
  "properties": {
    "iso:country":"DE",
    "sg:address":"Pater-Otto-Hopfenm\u00fcller-Str. 3",
    "sg:city":"Weismain",
    "sg:phone":"+49 9575/563",
    "sg:postcode":"96260",
    "sg:province":"Bayern",
    "wof:name":"Berthold D\u00fcck",
    "wof:placetype":"venue"
},
  "geometry": {"coordinates":[11.248759,50.085968],"type":"Point"}
}