{
  "type": "Feature",
  "properties": {
    "iso:country":"DE",
    "sg:address":"Auf der Au 16",
    "sg:city":"Obernburg",
    "sg:phone":"+49 6022/31486",
    "sg:postcode":"63785",
    "sg:province":"Bayern",
    "wof:name":"Heinrich Kreher",
    "wof:placetype":"venue"
},
  "geometry": {"coordinates":[9.11799,49.834419],"type":"Point"}
}