{
  "type": "Feature",
  "properties": {
    "iso:country":"DE",
    "sg:address":"Kleine Wassergasse 6",
    "sg:city":"Mainz",
    "sg:phone":"+49 6131/831651",
    "sg:postcode":"55130",
    "sg:province":"Rheinland-Pfalz",
    "wof:name":"Bernd Endlich",
    "wof:placetype":"venue"
},
  "geometry": {"coordinates":[8.3020238876,49.9823608398],"type":"Point"}
}