{
  "type": "Feature",
  "properties": {
    "iso:country":"DE",
    "sg:address":"Kronenweg 15",
    "sg:city":"Minden",
    "sg:postcode":"32423",
    "sg:province":"Nordrhein-Westfalen",
    "wof:name":"Trim-line Autodesign",
    "wof:placetype":"venue"
},
  "geometry": {"coordinates":[8.947149,52.284332],"type":"Point"}
}