{
  "type": "Feature",
  "properties": {
    "iso:country":"DE",
    "sg:address":"Rathausstr. 3",
    "sg:city":"H\u00f6hr-Grenzhausen",
    "sg:phone":"+49 2624/6279",
    "sg:postcode":"56203",
    "sg:province":"Rheinland-Pfalz",
    "wof:name":"Norma Gmbh & Co. Kg",
    "wof:placetype":"venue"
},
  "geometry": {"coordinates":[7.6714777946,50.4331817627],"type":"Point"}
}