{
  "type": "Feature",
  "properties": {
    "iso:country":"DE",
    "sg:address":"Hochstr. 30",
    "sg:city":"Lahnstein",
    "sg:phone":"+49 2621/3674",
    "sg:postcode":"56112",
    "sg:province":"Rheinland-Pfalz",
    "wof:name":"M. Sturm",
    "wof:placetype":"venue"
},
  "geometry": {"coordinates":[7.6051778793,50.2997817993],"type":"Point"}
}