{
  "type": "Feature",
  "properties": {
    "iso:country":"DE",
    "sg:address":"Milbinger Str. 46",
    "sg:city":"Brannenburg",
    "sg:phone":"+49 8034/3392",
    "sg:postcode":"83098",
    "sg:province":"Bayern",
    "wof:name":"Martin Astner",
    "wof:placetype":"venue"
},
  "geometry": {"coordinates":[12.1012,47.726089],"type":"Point"}
}