{
  "type": "Feature",
  "properties": {
    "iso:country":"DE",
    "sg:address":"Postfach 1152:: 27613 Beverstedt:: Germany.^^Hindenburgstr 10::",
    "sg:city":"Beverstedt",
    "sg:phone":"+49 4747/94980",
    "sg:postcode":"27616",
    "sg:province":"Niedersachsen",
    "wof:name":"Volksbank Eg Im Landkreis Cuxhaven",
    "wof:placetype":"venue"
},
  "geometry": {"coordinates":[8.819085,53.434593],"type":"Point"}
}