{
  "type": "Feature",
  "properties": {
    "iso:country":"DE",
    "sg:address":"Am W\u00f6llershof 2",
    "sg:city":"Koblenz",
    "sg:phone":"+49 261/31350",
    "sg:postcode":"56068",
    "sg:province":"Rheinland-Pfalz",
    "wof:name":"Nagelstudio Wirtgen",
    "wof:placetype":"venue"
},
  "geometry": {"coordinates":[7.593624,50.359802],"type":"Point"}
}