{
  "type": "Feature",
  "properties": {
    "iso:country":"DE",
    "sg:address":"Breitscheidstr. 72",
    "sg:city":"Kassel",
    "sg:phone":"+49 561/38112",
    "sg:postcode":"34119",
    "sg:province":"Hessen",
    "wof:name":"Witzel Heissmangel",
    "wof:placetype":"venue"
},
  "geometry": {"coordinates":[9.4589529037,51.3188438416],"type":"Point"}
}