{
  "type": "Feature",
  "properties": {
    "iso:country":"DE",
    "sg:address":"Friedensstr. 4",
    "sg:city":"Heppenheim",
    "sg:phone":"+49 6252/77882",
    "sg:postcode":"64646",
    "sg:province":"Hessen",
    "wof:name":"Gwh Gmbh",
    "wof:placetype":"venue"
},
  "geometry": {"coordinates":[8.6335229874,49.6454467773],"type":"Point"}
}