{
  "type": "Feature",
  "properties": {
    "iso:country":"DE",
    "sg:address":"Fronstr. 26",
    "sg:city":"Worms",
    "sg:phone":"+49 6242/1577",
    "sg:postcode":"67550",
    "sg:province":"Rheinland-Pfalz",
    "wof:name":"Helmut B\u00e4rsch",
    "wof:placetype":"venue"
},
  "geometry": {"coordinates":[8.2807750702,49.6759223938],"type":"Point"}
}