{
  "type": "Feature",
  "properties": {
    "iso:country":"DE",
    "sg:address":"Herrnstr 13",
    "sg:city":"Hanau",
    "sg:phone":"+49 6181/20110",
    "sg:postcode":"63450",
    "sg:province":"Hessen",
    "wof:name":"Friedrich Wilhelm Lenz Gmbh & Co Kg",
    "wof:placetype":"venue"
},
  "geometry": {"coordinates":[8.9118385315,50.1335754395],"type":"Point"}
}