{
  "type": "Feature",
  "properties": {
    "iso:country":"DE",
    "sg:address":"An der Stadtmauer 10",
    "sg:city":"Ornbau",
    "sg:postcode":"91737",
    "sg:province":"Bayern",
    "wof:name":"Bastei Waltz E. K.",
    "wof:placetype":"venue"
},
  "geometry": {"coordinates":[10.654024,49.175659],"type":"Point"}
}