{
  "type": "Feature",
  "properties": {
    "iso:country":"DE",
    "sg:address":"Seedammweg 55",
    "sg:city":"Bad Homburg",
    "sg:postcode":"61352",
    "sg:province":"Hessen",
    "wof:name":"Homotoxin Gmbh",
    "wof:placetype":"venue"
},
  "geometry": {"coordinates":[8.639682,50.229218],"type":"Point"}
}