{
  "type": "Feature",
  "properties": {
    "iso:country":"DE",
    "sg:address":"Max-Planck-Str. 34",
    "sg:city":"Spaichingen",
    "sg:phone":"+49 7424/93150",
    "sg:postcode":"78549",
    "sg:province":"Baden-W\u00fcrttemberg",
    "wof:name":"Pr\u00e4zis Gmbh",
    "wof:placetype":"venue"
},
  "geometry": {"coordinates":[8.7508420944,48.0655288696],"type":"Point"}
}