{
  "type": "Feature",
  "properties": {
    "iso:country":"DE",
    "sg:address":"Alte Potsdamer Str. 41",
    "sg:city":"Brandenburg",
    "sg:phone":"+49 3381/727172",
    "sg:postcode":"14776",
    "sg:province":"Brandenburg",
    "wof:name":"Schewski Immobilienmakler",
    "wof:placetype":"venue"
},
  "geometry": {"coordinates":[12.5729255676,52.4062309265],"type":"Point"}
}