{
  "type": "Feature",
  "properties": {
    "iso:country":"DE",
    "sg:address":"Dr.-Eduard-Stadler-Str. 11",
    "sg:city":"Plauen",
    "sg:phone":"+49 3741/446632",
    "sg:postcode":"08529",
    "sg:province":"Sachsen",
    "wof:name":"Vvs Holding Vertriebs- Verwaltungs- Und Service Gmbh",
    "wof:placetype":"venue"
},
  "geometry": {"coordinates":[12.1683387756,50.4973754883],"type":"Point"}
}