{
  "type": "Feature",
  "properties": {
    "iso:country":"DE",
    "sg:address":"Heeresstr. 24",
    "sg:city":"Lebach",
    "sg:phone":"+49 6881/9362100",
    "sg:postcode":"66822",
    "sg:province":"Saarland",
    "wof:name":"Elisabeth Schober Gmbh",
    "wof:placetype":"venue"
},
  "geometry": {"coordinates":[6.8946709633,49.4132537842],"type":"Point"}
}