{
  "type": "Feature",
  "properties": {
    "iso:country":"DE",
    "sg:address":"Prinzenstr. 81",
    "sg:city":"Kamp-Lintfort",
    "sg:phone":"+49 2842/91776",
    "sg:postcode":"47475",
    "sg:province":"Nordrhein-Westfalen",
    "wof:name":"Jet Tankstelle",
    "wof:placetype":"venue"
},
  "geometry": {"coordinates":[6.5444469452,51.5082588196],"type":"Point"}
}