{
  "type": "Feature",
  "properties": {
    "iso:country":"DE",
    "sg:address":"Kieler Str. 90",
    "sg:city":"Eckernf\u00f6rde",
    "sg:postcode":"24340",
    "sg:province":"Schleswig-Holstein",
    "wof:name":"Flienert Und Runge",
    "wof:placetype":"venue"
},
  "geometry": {"coordinates":[9.8373937607,54.467010498],"type":"Point"}
}