{
  "type": "Feature",
  "properties": {
    "iso:country":"DE",
    "sg:address":"Altenzeller Str. 2/13",
    "sg:city":"Dresden",
    "sg:phone":"+49 351/4726392",
    "sg:postcode":"01069",
    "sg:province":"Sachsen",
    "wof:name":"Manfred Henkel",
    "wof:placetype":"venue"
},
  "geometry": {"coordinates":[13.7185649872,51.0384368896],"type":"Point"}
}