{
  "type": "Feature",
  "properties": {
    "iso:country":"DE",
    "sg:address":"Helmerner Str. 8",
    "sg:city":"Bad W\u00fcnnenberg",
    "sg:phone":"+49 2957/1076",
    "sg:postcode":"33181",
    "sg:province":"Nordrhein-Westfalen",
    "wof:name":"Josef M\u00fcnster",
    "wof:placetype":"venue"
},
  "geometry": {"coordinates":[8.730231,51.565815],"type":"Point"}
}