{
  "type": "Feature",
  "properties": {
    "iso:country":"DE",
    "sg:address":"Eschenweg 4 B",
    "sg:city":"Dinslaken",
    "sg:phone":"+49 2064/95615",
    "sg:postcode":"46539",
    "sg:province":"Nordrhein-Westfalen",
    "wof:name":"Andre Schmidt",
    "wof:placetype":"venue"
},
  "geometry": {"coordinates":[6.7638459206,51.5660591125],"type":"Point"}
}