{
  "type": "Feature",
  "properties": {
    "iso:country":"DE",
    "sg:address":"Kaiserswerther Str. 20",
    "sg:city":"Ratingen",
    "sg:phone":"+49 2102/26466",
    "sg:postcode":"40878",
    "sg:province":"Nordrhein-Westfalen",
    "wof:name":"Hans Herbertz",
    "wof:placetype":"venue"
},
  "geometry": {"coordinates":[6.844523,51.30006],"type":"Point"}
}