{
  "type": "Feature",
  "properties": {
    "iso:country":"DE",
    "sg:address":"Lange Str. 76",
    "sg:city":"L\u00fcnen",
    "sg:phone":"+49 2306/21331",
    "sg:postcode":"44532",
    "sg:province":"Nordrhein-Westfalen",
    "wof:name":"R. Lehmann",
    "wof:placetype":"venue"
},
  "geometry": {"coordinates":[7.5240750313,51.6115112305],"type":"Point"}
}