{
  "type": "Feature",
  "properties": {
    "iso:country":"DE",
    "sg:address":"an der kuppe 23",
    "sg:city":"berlin",
    "sg:phone":"+49 30/38208045454",
    "sg:postcode":"13581",
    "sg:province":"Berlin",
    "wof:name":"Sex, Cam, Erotik, Porno, Bilder,nackt,pictures,xxx",
    "wof:placetype":"venue"
},
  "geometry": {"coordinates":[13.189157,52.538776],"type":"Point"}
}