{
  "type": "Feature",
  "properties": {
    "iso:country":"DE",
    "sg:address":"Max-Wenzel-Str. 7",
    "sg:city":"Ehrenfriedersdorf",
    "sg:phone":"+49 37341/48880",
    "sg:postcode":"09427",
    "sg:province":"Sachsen",
    "wof:name":"Steffi Ahnert Ergotherapie",
    "wof:placetype":"venue"
},
  "geometry": {"coordinates":[12.967203,50.648186],"type":"Point"}
}