{
  "type": "Feature",
  "properties": {
    "iso:country":"DE",
    "sg:address":"Zugspitzstr. 33",
    "sg:city":"Garmisch-Partenkirchen",
    "sg:phone":"+49 8821/50042",
    "sg:postcode":"82467",
    "sg:province":"Bayern",
    "wof:name":"Dr. E. Heiss Steuerberater",
    "wof:placetype":"venue"
},
  "geometry": {"coordinates":[11.0806903839,47.4909896851],"type":"Point"}
}