{
  "type": "Feature",
  "properties": {
    "iso:country":"DE",
    "sg:address":"Fontanestr. 4",
    "sg:city":"Sch\u00f6nhausen",
    "sg:phone":"+49 39323/38261",
    "sg:postcode":"39524",
    "sg:province":"Sachsen-Anhalt",
    "wof:name":"Fritz Krueger",
    "wof:placetype":"venue"
},
  "geometry": {"coordinates":[12.03592,52.579903],"type":"Point"}
}