{
  "type": "Feature",
  "properties": {
    "iso:country":"DE",
    "sg:address":"Alst\u00e4tter Str. 12",
    "sg:city":"Gronau",
    "sg:phone":"+49 2562/5605",
    "sg:postcode":"48599",
    "sg:province":"Nordrhein-Westfalen",
    "wof:name":"Ev. Pfarramt Ii",
    "wof:placetype":"venue"
},
  "geometry": {"coordinates":[7.0183830261,52.2108268738],"type":"Point"}
}