{
  "type": "Feature",
  "properties": {
    "iso:country":"DE",
    "sg:address":"Bleichstr. 57",
    "sg:city":"Pforzheim",
    "sg:phone":"+49 7231/24516",
    "sg:postcode":"75173",
    "sg:province":"Baden-W\u00fcrttemberg",
    "wof:name":"G. Frank",
    "wof:placetype":"venue"
},
  "geometry": {"coordinates":[8.695568,48.88517],"type":"Point"}
}