{
  "type": "Feature",
  "properties": {
    "iso:country":"DE",
    "sg:address":"Mohnweg 7",
    "sg:city":"Helmstedt",
    "sg:phone":"+49 5351/37459",
    "sg:postcode":"38350",
    "sg:province":"Niedersachsen",
    "wof:name":"Hernier",
    "wof:placetype":"venue"
},
  "geometry": {"coordinates":[10.9669113159,52.2443466187],"type":"Point"}
}