{
  "type": "Feature",
  "properties": {
    "iso:country":"DE",
    "sg:address":"St.-Anna-Str. 16",
    "sg:city":"M\u00fcnchen",
    "sg:phone":"+49 89/296995",
    "sg:postcode":"80538",
    "sg:province":"Bayern",
    "wof:name":"Ascot Filmverleih Gmbh",
    "wof:placetype":"venue"
},
  "geometry": {"coordinates":[11.5871896744,48.1393585205],"type":"Point"}
}