{
  "type": "Feature",
  "properties": {
    "iso:country":"DE",
    "sg:address":"Grabenstr. 1",
    "sg:city":"Heimsheim",
    "sg:phone":"+49 7033/13339",
    "sg:postcode":"71296",
    "sg:province":"Baden-W\u00fcrttemberg",
    "wof:name":"Rowa Labortechnische Anlagen Gmbh",
    "wof:placetype":"venue"
},
  "geometry": {"coordinates":[8.863331,48.806114],"type":"Point"}
}