{
  "type": "Feature",
  "properties": {
    "iso:country":"DE",
    "sg:address":"Krommerter Weg 31",
    "sg:city":"Rhede",
    "sg:phone":"+49 2872/92640",
    "sg:postcode":"46414",
    "sg:province":"Nordrhein-Westfalen",
    "wof:name":"Helmut Krasemann Gmbh",
    "wof:placetype":"venue"
},
  "geometry": {"coordinates":[6.7030601501,51.8316993713],"type":"Point"}
}