{
  "type": "Feature",
  "properties": {
    "iso:country":"DE",
    "sg:address":"Kuhlenstr. 3",
    "sg:city":"Uetersen",
    "sg:phone":"+49 4122/3279",
    "sg:postcode":"25436",
    "sg:province":"Schleswig-Holstein",
    "wof:name":"Helmut Raabe Inh. Ingo Matthiessen",
    "wof:placetype":"venue"
},
  "geometry": {"coordinates":[9.65205,53.682442],"type":"Point"}
}