{
  "type": "Feature",
  "properties": {
    "iso:country":"DE",
    "sg:address":"Bleiwaesche 10",
    "sg:city":"Wuelfrath",
    "sg:phone":"+49 4902/058",
    "sg:postcode":"42489",
    "sg:province":"Nordrhein-Westfalen",
    "wof:name":"Ingenieurbuero Duenckel",
    "wof:placetype":"venue"
},
  "geometry": {"coordinates":[7.020668,51.273632],"type":"Point"}
}