{
  "type": "Feature",
  "properties": {
    "iso:country":"DE",
    "sg:address":"Stockacher Str. 83",
    "sg:city":"Tuttlingen",
    "sg:phone":"+49 7461/2507",
    "sg:postcode":"78532",
    "sg:province":"Baden-W\u00fcrttemberg",
    "wof:name":"Herbert Bucher",
    "wof:placetype":"venue"
},
  "geometry": {"coordinates":[8.823179,47.976036],"type":"Point"}
}