{
  "type": "Feature",
  "properties": {
    "iso:country":"DE",
    "sg:city":"Nordermeldorf",
    "sg:phone":"+49 4832/2224",
    "sg:postcode":"25704",
    "sg:province":"Schleswig-Holstein",
    "wof:name":"Norddeutscher Ladenbau",
    "wof:placetype":"venue"
},
  "geometry": {"coordinates":[9.015304,54.119308],"type":"Point"}
}