{
  "type": "Feature",
  "properties": {
    "iso:country":"DE",
    "sg:address":"Helmstedter Str. 1 a",
    "sg:city":"Braunschweig",
    "sg:phone":"+49 531/73206",
    "sg:postcode":"38102",
    "sg:province":"Niedersachsen",
    "wof:name":"Apotheke Am Steintor",
    "wof:placetype":"venue"
},
  "geometry": {"coordinates":[10.535707,52.262817],"type":"Point"}
}