{
  "type": "Feature",
  "properties": {
    "iso:country":"DE",
    "sg:address":"Rhein-Mosel-Str. 49",
    "sg:city":"Emmelshausen",
    "sg:phone":"+49 6747/6848",
    "sg:postcode":"56281",
    "sg:province":"Rheinland-Pfalz",
    "wof:name":"Franz Schneberger",
    "wof:placetype":"venue"
},
  "geometry": {"coordinates":[7.5548801422,50.1557312012],"type":"Point"}
}