{
  "type": "Feature",
  "properties": {
    "iso:country":"DE",
    "sg:address":"Reichsstr. 100",
    "sg:city":"Berlin",
    "sg:phone":"+49 30/3053004",
    "sg:postcode":"14052",
    "sg:province":"Berlin",
    "wof:name":"Hermann Kiepe Rechtsanwalt Und Notar",
    "wof:placetype":"venue"
},
  "geometry": {"coordinates":[13.2679958344,52.5116653442],"type":"Point"}
}