{
  "type": "Feature",
  "properties": {
    "iso:country":"DE",
    "sg:address":"Faustm\u00fchlenweg 45",
    "sg:city":"Kassel",
    "sg:phone":"+49 561/513733",
    "sg:postcode":"34123",
    "sg:province":"Hessen",
    "wof:name":"Otto Werner",
    "wof:placetype":"venue"
},
  "geometry": {"coordinates":[9.5481462479,51.2895050049],"type":"Point"}
}