{
  "type": "Feature",
  "properties": {
    "iso:country":"DE",
    "sg:address":"Bastei 9",
    "sg:city":"Amberg",
    "sg:postcode":"92224",
    "sg:province":"Bayern",
    "wof:name":"Die Hausmeisterin Inh. Angelika Graf E. K.",
    "wof:placetype":"venue"
},
  "geometry": {"coordinates":[11.8598117828,49.4435997009],"type":"Point"}
}