{
  "type": "Feature",
  "properties": {
    "iso:country":"DE",
    "sg:address":"Karl-Marx-Str. 7",
    "sg:city":"Ilfeld",
    "sg:phone":"+49 36331/30333",
    "sg:postcode":"99768",
    "sg:province":"Th\u00fcringen",
    "wof:name":"A. Schubotz",
    "wof:placetype":"venue"
},
  "geometry": {"coordinates":[10.787618,51.572704],"type":"Point"}
}