{
  "type": "Feature",
  "properties": {
    "iso:country":"DE",
    "sg:address":"Bokeloher Str. 26",
    "sg:city":"Wunstorf",
    "sg:phone":"+49 5031/3988",
    "sg:postcode":"31515",
    "sg:province":"Niedersachsen",
    "wof:name":"Willi Freise",
    "wof:placetype":"venue"
},
  "geometry": {"coordinates":[9.3608350754,52.413269043],"type":"Point"}
}