{
  "type": "Feature",
  "properties": {
    "iso:country":"DE",
    "sg:address":"Dorfstr. 29",
    "sg:city":"Ilmm\u00fcnster",
    "sg:phone":"+49 8441/3861",
    "sg:postcode":"85304",
    "sg:province":"Bayern",
    "wof:name":"Franz Aigner",
    "wof:placetype":"venue"
},
  "geometry": {"coordinates":[11.485107,48.478207],"type":"Point"}
}