{
  "type": "Feature",
  "properties": {
    "iso:country":"DE",
    "sg:address":"K\u00f6nig-Ludwig-Str. 50",
    "sg:city":"Recklinghausen",
    "sg:phone":"+49 2361/34413",
    "sg:postcode":"45663",
    "sg:province":"Nordrhein-Westfalen",
    "wof:name":"Southern",
    "wof:placetype":"venue"
},
  "geometry": {"coordinates":[7.220539093,51.578453064],"type":"Point"}
}