{
  "type": "Feature",
  "properties": {
    "iso:country":"DE",
    "sg:address":"Gro\u00dfe Kirchenstr. 13",
    "sg:city":"Rheinstetten",
    "sg:phone":"+49 7242/3193",
    "sg:postcode":"76287",
    "sg:province":"Baden-W\u00fcrttemberg",
    "wof:name":"Pizzeria Altona",
    "wof:placetype":"venue"
},
  "geometry": {"coordinates":[8.2900075912,48.9615364075],"type":"Point"}
}