{
  "type": "Feature",
  "properties": {
    "iso:country":"DE",
    "sg:address":"An der Rellau 21",
    "sg:city":"Rellingen",
    "sg:phone":"+49 4101/24435",
    "sg:postcode":"25462",
    "sg:province":"Schleswig-Holstein",
    "wof:name":"Horst Federmann",
    "wof:placetype":"venue"
},
  "geometry": {"coordinates":[9.8366355896,53.6537857056],"type":"Point"}
}