{
  "type": "Feature",
  "properties": {
    "iso:country":"DE",
    "sg:address":"Rittershausstr. 18",
    "sg:city":"Bonn",
    "sg:postcode":"53113",
    "sg:province":"Nordrhein-Westfalen",
    "wof:name":"Med-3-concept Gmbh",
    "wof:placetype":"venue"
},
  "geometry": {"coordinates":[7.105547905,50.7217254639],"type":"Point"}
}