{
  "type": "Feature",
  "properties": {
    "iso:country":"DE",
    "sg:address":"Am Kratt 10",
    "sg:city":"Ahrensburg",
    "sg:phone":"+49 4102/1748",
    "sg:postcode":"22926",
    "sg:province":"Schleswig-Holstein",
    "wof:name":"Kroschke Stiftung F\u00fcr Kinder",
    "wof:placetype":"venue"
},
  "geometry": {"coordinates":[10.207983017,53.6392593384],"type":"Point"}
}