{
  "type": "Feature",
  "properties": {
    "iso:country":"DE",
    "sg:address":"Brinckmannstr. 13",
    "sg:city":"Husum",
    "sg:phone":"+49 4841/61001",
    "sg:postcode":"25813",
    "sg:province":"Schleswig-Holstein",
    "wof:name":"Dr. Hansj\u00f6rg Andresen Dr. Uwe Ladda Horst Bl\u00fcmel",
    "wof:placetype":"venue"
},
  "geometry": {"coordinates":[9.0561990738,54.4806480408],"type":"Point"}
}