{
  "type": "Feature",
  "properties": {
    "iso:country":"DE",
    "sg:address":"Kleinreinsdorf 62",
    "sg:city":"Teichwolframsdorf",
    "sg:phone":"+49 36624/4000",
    "sg:postcode":"07989",
    "sg:province":"Th\u00fcringen",
    "wof:name":"Asfil Isolations- & Filtermaterial Gmbh",
    "wof:placetype":"venue"
},
  "geometry": {"coordinates":[12.2169208527,50.7205886841],"type":"Point"}
}