{
  "type": "Feature",
  "properties": {
    "iso:country":"DE",
    "sg:address":"Kaiser-Friedrich-Str 5",
    "sg:city":"Berlin",
    "sg:phone":"+49 30/34703087",
    "sg:postcode":"10585",
    "sg:province":"Berlin",
    "wof:name":"Krawattenzwang Angelika Holz",
    "wof:placetype":"venue"
},
  "geometry": {"coordinates":[13.299967,52.517963],"type":"Point"}
}