{
  "type": "Feature",
  "properties": {
    "iso:country":"DE",
    "sg:address":"Franz-Schubert-Str. 38",
    "sg:city":"Stuttgart",
    "sg:phone":"+49 711/691095",
    "sg:postcode":"70195",
    "sg:province":"Baden-W\u00fcrttemberg",
    "wof:name":"August H\u00e4bich",
    "wof:placetype":"venue"
},
  "geometry": {"coordinates":[9.12829,48.778168],"type":"Point"}
}