{
  "type": "Feature",
  "properties": {
    "iso:country":"DE",
    "sg:address":"Dr.-Ricken-Str. 8",
    "sg:city":"Tann",
    "sg:phone":"+49 6682/1487",
    "sg:postcode":"36142",
    "sg:province":"Hessen",
    "wof:name":"Josef M\u00fcller",
    "wof:placetype":"venue"
},
  "geometry": {"coordinates":[10.0071363449,50.621383667],"type":"Point"}
}