{
  "type": "Feature",
  "properties": {
    "iso:country":"DE",
    "sg:address":"Christine-Englerth-Str. 7",
    "sg:city":"Recklinghausen",
    "sg:postcode":"45665",
    "sg:province":"Nordrhein-Westfalen",
    "wof:name":"Bett & Co. Gmbh",
    "wof:placetype":"venue"
},
  "geometry": {"coordinates":[7.2474331856,51.6056442261],"type":"Point"}
}