{
  "type": "Feature",
  "properties": {
    "iso:country":"DE",
    "sg:address":"Kaiserstr. 27",
    "sg:city":"Reil",
    "sg:phone":"+49 6542/21727",
    "sg:postcode":"56861",
    "sg:province":"Rheinland-Pfalz",
    "wof:name":"Karl-e. Barzen",
    "wof:placetype":"venue"
},
  "geometry": {"coordinates":[7.1164669991,50.0224494934],"type":"Point"}
}