{
  "type": "Feature",
  "properties": {
    "iso:country":"DE",
    "sg:address":"Randersackerer Str. 46 a",
    "sg:city":"W\u00fcrzburg",
    "sg:phone":"+49 931/7841900",
    "sg:postcode":"97072",
    "sg:province":"Bayern",
    "wof:name":"H & S Kraftfahrzeuge Gmbh",
    "wof:placetype":"venue"
},
  "geometry": {"coordinates":[9.9392528534,49.7771568298],"type":"Point"}
}