{
  "type": "Feature",
  "properties": {
    "iso:country":"DE",
    "sg:address":"Schlehenweg 4a",
    "sg:city":"Ochtendung",
    "sg:postcode":"56299",
    "sg:province":"Rheinland-Pfalz",
    "wof:name":"Kostenverwaltung F\u00fcr Privat Krankenversicherte",
    "wof:placetype":"venue"
},
  "geometry": {"coordinates":[7.383013,50.343262],"type":"Point"}
}