{
  "type": "Feature",
  "properties": {
    "iso:country":"DE",
    "sg:address":"Segitzdamm 2",
    "sg:city":"Berlin",
    "sg:phone":"+49 30/6153091",
    "sg:postcode":"10969",
    "sg:province":"Berlin",
    "wof:name":"European Film Academy E. V.",
    "wof:placetype":"venue"
},
  "geometry": {"coordinates":[13.4146976471,52.5016136169],"type":"Point"}
}