{
  "type": "Feature",
  "properties": {
    "iso:country":"DE",
    "sg:address":"Kiffward 26",
    "sg:city":"Duisburg",
    "sg:phone":"+49 203/446135",
    "sg:postcode":"47138",
    "sg:province":"Nordrhein-Westfalen",
    "wof:name":"J\u00fcrgen Freiwald",
    "wof:placetype":"venue"
},
  "geometry": {"coordinates":[6.776438,51.454273],"type":"Point"}
}