{
  "type": "Feature",
  "properties": {
    "iso:country":"DE",
    "sg:address":"Mellinghofer Str. 136",
    "sg:city":"Oberhausen",
    "sg:phone":"+49 208/872490",
    "sg:postcode":"46047",
    "sg:province":"Nordrhein-Westfalen",
    "wof:name":"A-z Waschmaschinen-service Gmbh",
    "wof:placetype":"venue"
},
  "geometry": {"coordinates":[6.8865141869,51.4759216309],"type":"Point"}
}