{
  "type": "Feature",
  "properties": {
    "iso:country":"DE",
    "sg:address":"Wolfgangstr. 29",
    "sg:city":"Rodenbach",
    "sg:phone":"+49 6184/50255",
    "sg:postcode":"63517",
    "sg:province":"Hessen",
    "wof:name":"Werner Kirschstein Architekt",
    "wof:placetype":"venue"
},
  "geometry": {"coordinates":[9.014946,50.14238],"type":"Point"}
}