{
  "type": "Feature",
  "properties": {
    "iso:country":"DE",
    "sg:address":"Robert-Blum-Str. 57",
    "sg:city":"Leverkusen",
    "sg:postcode":"51373",
    "sg:province":"Nordrhein-Westfalen",
    "wof:name":"Gts Gesellschaft Technischer Service Mbh",
    "wof:placetype":"venue"
},
  "geometry": {"coordinates":[6.981745,51.033192],"type":"Point"}
}