{
  "type": "Feature",
  "properties": {
    "iso:country":"DE",
    "sg:address":"Bahnhofstr. 17",
    "sg:city":"Thalm\u00e4ssing",
    "sg:phone":"+49 9173/243",
    "sg:postcode":"91177",
    "sg:province":"Bayern",
    "wof:name":"Anton Schieferdecker",
    "wof:placetype":"venue"
},
  "geometry": {"coordinates":[11.215215,49.087952],"type":"Point"}
}