{
  "type": "Feature",
  "properties": {
    "iso:country":"DE",
    "sg:address":"Reichenstr. 33",
    "sg:city":"F\u00fcssen",
    "sg:phone":"+49 8362/7680",
    "sg:postcode":"87629",
    "sg:province":"Bayern",
    "wof:name":"Roseng\u00e4rtchen Cafe",
    "wof:placetype":"venue"
},
  "geometry": {"coordinates":[10.700188,47.569256],"type":"Point"}
}