{
  "type": "Feature",
  "properties": {
    "iso:country":"DE",
    "sg:address":"Rudolst\u00e4dter Str. 39",
    "sg:city":"Jena",
    "sg:phone":"+49 3641/20190",
    "sg:postcode":"07745",
    "sg:province":"Th\u00fcringen",
    "wof:name":"Job Jenaer Objektmanagement- Und Betriebsgesellschaft Mbh",
    "wof:placetype":"venue"
},
  "geometry": {"coordinates":[11.5802516937,50.8987159729],"type":"Point"}
}