{
  "type": "Feature",
  "properties": {
    "iso:country":"DE",
    "sg:address":"Merowingerstr. 12",
    "sg:city":"Br\u00e4unlingen",
    "sg:phone":"+49 771/8969026",
    "sg:postcode":"78199",
    "sg:province":"Baden-W\u00fcrttemberg",
    "wof:name":"Handwerkerkreis Gmbh",
    "wof:placetype":"venue"
},
  "geometry": {"coordinates":[8.442294,47.924191],"type":"Point"}
}