{
  "type": "Feature",
  "properties": {
    "iso:country":"DE",
    "sg:address":"Pliezh\u00e4user Str. 21",
    "sg:city":"Reutlingen",
    "sg:phone":"+49 7121/963009",
    "sg:postcode":"72768",
    "sg:province":"Baden-W\u00fcrttemberg",
    "wof:name":"Walter H\u00e4u\u00dfler Steuerberater",
    "wof:placetype":"venue"
},
  "geometry": {"coordinates":[9.2029428482,48.5494384766],"type":"Point"}
}