{
  "type": "Feature",
  "properties": {
    "iso:country":"DE",
    "sg:address":"Hof Lauterbach 1",
    "sg:city":"V\u00f6hl",
    "sg:phone":"+49 5635/9237",
    "sg:postcode":"34516",
    "sg:province":"Hessen",
    "wof:name":"Karl Eigenbrodt Nachf. Inh. K. W. Wittmer-eigenbrodt",
    "wof:placetype":"venue"
},
  "geometry": {"coordinates":[8.930729866,51.2304611206],"type":"Point"}
}