{
  "type": "Feature",
  "properties": {
    "iso:country":"DE",
    "sg:address":"An den Reesenbetten 4",
    "sg:city":"B\u00fcdelsdorf",
    "sg:phone":"+49 4331/359610",
    "sg:postcode":"24782",
    "sg:province":"Schleswig-Holstein",
    "wof:name":"Fast Forward Medien Verwaltungsgesellschaft Mbh",
    "wof:placetype":"venue"
},
  "geometry": {"coordinates":[9.6974143982,54.3220405579],"type":"Point"}
}