{
  "type": "Feature",
  "properties": {
    "iso:country":"DE",
    "sg:address":"Chemnitzer Str. 72",
    "sg:city":"Meerane",
    "sg:phone":"+49 3764/4541",
    "sg:postcode":"08393",
    "sg:province":"Sachsen",
    "wof:name":"Restaurant Rhodos",
    "wof:placetype":"venue"
},
  "geometry": {"coordinates":[12.4763584137,50.8454780579],"type":"Point"}
}