{
  "type": "Feature",
  "properties": {
    "iso:country":"DE",
    "sg:address":"Wiesenstr. 99",
    "sg:city":"St. Ingbert",
    "sg:postcode":"66386",
    "sg:province":"Saarland",
    "wof:name":"Hans Jung Gmbh",
    "wof:placetype":"venue"
},
  "geometry": {"coordinates":[7.118035,49.271725],"type":"Point"}
}