{
  "type": "Feature",
  "properties": {
    "iso:country":"DE",
    "sg:address":"Auf der Jenseite 15",
    "sg:city":"Lennestadt",
    "sg:phone":"+49 2723/8364",
    "sg:postcode":"57368",
    "sg:province":"Nordrhein-Westfalen",
    "wof:name":"Toni B\u00f6rger",
    "wof:placetype":"venue"
},
  "geometry": {"coordinates":[8.171406,51.115368],"type":"Point"}
}