{
  "type": "Feature",
  "properties": {
    "iso:country":"DE",
    "sg:address":"Mathias-Br\u00fcggen-Str. 166",
    "sg:city":"K\u00f6ln",
    "sg:phone":"+49 221/594228",
    "sg:postcode":"50829",
    "sg:province":"Nordrhein-Westfalen",
    "wof:name":"Bistro Im Park",
    "wof:placetype":"venue"
},
  "geometry": {"coordinates":[6.881595,50.986679],"type":"Point"}
}