{
  "type": "Feature",
  "properties": {
    "iso:country":"DE",
    "sg:address":"Karl-Marx-Str. 33",
    "sg:city":"Hartha",
    "sg:phone":"+49 34328/38653",
    "sg:postcode":"04746",
    "sg:province":"Sachsen",
    "wof:name":"Heike Paletzki Agentur",
    "wof:placetype":"venue"
},
  "geometry": {"coordinates":[12.9715662003,51.0977096558],"type":"Point"}
}