{
  "type": "Feature",
  "properties": {
    "iso:country":"DE",
    "sg:address":"Heusweilerstr. 58a",
    "sg:city":"Eppelborn",
    "sg:phone":"+49 6806/81327",
    "sg:postcode":"66571",
    "sg:province":"Saarland",
    "wof:name":"Bauelemente Straub Gmbh",
    "wof:placetype":"venue"
},
  "geometry": {"coordinates":[6.981,49.361408],"type":"Point"}
}