{
  "type": "Feature",
  "properties": {
    "iso:country":"DE",
    "sg:address":"Holthauser Str. 13",
    "sg:city":"Bochum",
    "sg:phone":"+49 234/851226",
    "sg:postcode":"44805",
    "sg:province":"Nordrhein-Westfalen",
    "wof:name":"Harry Palm",
    "wof:placetype":"venue"
},
  "geometry": {"coordinates":[7.2793240547,51.5238227844],"type":"Point"}
}