{
  "type": "Feature",
  "properties": {
    "iso:country":"DE",
    "sg:address":"Max-Planck-Str. 38",
    "sg:city":"K\u00f6ln",
    "sg:phone":"+49 2234/270641",
    "sg:postcode":"50858",
    "sg:province":"Nordrhein-Westfalen",
    "wof:name":"Lbb Immobilien Beteiligungs- Und",
    "wof:placetype":"venue"
},
  "geometry": {"coordinates":[6.8466448784,50.9226074219],"type":"Point"}
}