{
  "type": "Feature",
  "properties": {
    "iso:country":"DE",
    "sg:address":"Stra\u00dfe am Orte 153",
    "sg:city":"Mellingen",
    "sg:postcode":"99441",
    "sg:province":"Th\u00fcringen",
    "wof:name":"Big Facility Management Geb\u00e4udetechnik Gmbh",
    "wof:placetype":"venue"
},
  "geometry": {"coordinates":[11.3892879486,50.9395179749],"type":"Point"}
}