{
  "type": "Feature",
  "properties": {
    "iso:country":"DE",
    "sg:address":"Kanalstr. 63",
    "sg:city":"Kiel",
    "sg:phone":"+49 431/36847",
    "sg:postcode":"24159",
    "sg:province":"Schleswig-Holstein",
    "wof:name":"Restaurant Kanal-packhaus",
    "wof:placetype":"venue"
},
  "geometry": {"coordinates":[10.1502399445,54.3695487976],"type":"Point"}
}