{
  "type": "Feature",
  "properties": {
    "iso:country":"DE",
    "sg:address":"Stra\u00dfe 26",
    "sg:city":"Berlin",
    "sg:postcode":"13129",
    "sg:province":"Berlin",
    "wof:name":"Devantier Ingenieurb\u00fcro Gmbh",
    "wof:placetype":"venue"
},
  "geometry": {"coordinates":[13.4685640335,52.5967102051],"type":"Point"}
}