{
  "type": "Feature",
  "properties": {
    "iso:country":"DE",
    "sg:address":"Gerberstr. 2",
    "sg:city":"Heilbronn",
    "sg:phone":"+49 7131/87582",
    "sg:postcode":"74072",
    "sg:province":"Baden-W\u00fcrttemberg",
    "wof:name":"Jerichow Hess Vetter Rechtsanw\u00e4lte",
    "wof:placetype":"venue"
},
  "geometry": {"coordinates":[9.2171669006,49.1423988342],"type":"Point"}
}