{
  "type": "Feature",
  "properties": {
    "iso:country":"DE",
    "sg:address":"M\u00fchlstr. 4",
    "sg:city":"Pilsting",
    "sg:phone":"+49 9953/757",
    "sg:postcode":"94431",
    "sg:province":"Bayern",
    "wof:name":"Bajog Electronic Gmbh",
    "wof:placetype":"venue"
},
  "geometry": {"coordinates":[12.657181,48.702042],"type":"Point"}
}