{
  "type": "Feature",
  "properties": {
    "iso:country":"DE",
    "sg:address":"Poppenb\u00fctteler Chaussee 28",
    "sg:city":"Hamburg",
    "sg:phone":"+49 40/60566561",
    "sg:postcode":"22397",
    "sg:province":"Hamburg",
    "wof:name":"Hamburg Relocation",
    "wof:placetype":"venue"
},
  "geometry": {"coordinates":[10.1027011871,53.7058639526],"type":"Point"}
}