{
  "type": "Feature",
  "properties": {
    "iso:country":"DE",
    "sg:address":"Halener Str. 17",
    "sg:city":"Emstek",
    "sg:postcode":"49685",
    "sg:province":"Niedersachsen",
    "wof:name":"Voba Immobilien Gmbh",
    "wof:placetype":"venue"
},
  "geometry": {"coordinates":[8.1549491882,52.8360366821],"type":"Point"}
}