{
  "type": "Feature",
  "properties": {
    "iso:country":"DE",
    "sg:address":"Seltersweg 7",
    "sg:city":"Gie\u00dfen",
    "sg:phone":"+49 641/76644",
    "sg:postcode":"35390",
    "sg:province":"Hessen",
    "wof:name":"I. Tank Reiseb\u00fcro Gmbh & Co. Kg",
    "wof:placetype":"venue"
},
  "geometry": {"coordinates":[8.6740837097,50.5846405029],"type":"Point"}
}