{
  "type": "Feature",
  "properties": {
    "iso:country":"DE",
    "sg:address":"Gr\u00fcnberger Str. 41",
    "sg:city":"Gie\u00dfen",
    "sg:phone":"+49 641/9460130",
    "sg:postcode":"35394",
    "sg:province":"Hessen",
    "wof:name":"Steinbrecher Gmbh & Co. Kg",
    "wof:placetype":"venue"
},
  "geometry": {"coordinates":[8.6869697571,50.5842933655],"type":"Point"}
}