{
  "type": "Feature",
  "properties": {
    "iso:country":"DE",
    "sg:address":"Feldstr. 19",
    "sg:city":"Tangerh\u00fctte",
    "sg:phone":"+49 3935/28278",
    "sg:postcode":"39517",
    "sg:province":"Sachsen-Anhalt",
    "wof:name":"G. Lukas",
    "wof:placetype":"venue"
},
  "geometry": {"coordinates":[11.795267,52.437431],"type":"Point"}
}