{
  "type": "Feature",
  "properties": {
    "iso:country":"DE",
    "sg:address":"Dorfstr. 13",
    "sg:city":"V\u00f6gelsen",
    "sg:phone":"+49 4131/120789",
    "sg:postcode":"21360",
    "sg:province":"Niedersachsen",
    "wof:name":"Dirk Brodersen",
    "wof:placetype":"venue"
},
  "geometry": {"coordinates":[10.350402832,53.2781562805],"type":"Point"}
}