{
  "type": "Feature",
  "properties": {
    "iso:country":"DE",
    "sg:address":"Martin-Luther-Str. 1",
    "sg:city":"Bad Schwalbach",
    "sg:phone":"+49 6124/12286",
    "sg:postcode":"65307",
    "sg:province":"Hessen",
    "wof:name":"Ev. Pfarramt Gem. Bad Schwalbach Ii",
    "wof:placetype":"venue"
},
  "geometry": {"coordinates":[8.0765113831,50.1462783813],"type":"Point"}
}