{
  "type": "Feature",
  "properties": {
    "iso:country":"DE",
    "sg:address":"Hornusstr. 16",
    "sg:city":"Freiburg",
    "sg:phone":"+49 761/807394",
    "sg:postcode":"79108",
    "sg:province":"Baden-W\u00fcrttemberg",
    "wof:name":"Dr. Manfred K\u00f6hler Gmbh",
    "wof:placetype":"venue"
},
  "geometry": {"coordinates":[7.854165,48.015244],"type":"Point"}
}