{
  "type": "Feature",
  "properties": {
    "iso:country":"DE",
    "sg:address":"Pappelweg 74",
    "sg:city":"K\u00f6ln",
    "sg:phone":"+49 221/794769",
    "sg:postcode":"50767",
    "sg:province":"Nordrhein-Westfalen",
    "wof:name":"Powernet Informationssysteme Gmbh",
    "wof:placetype":"venue"
},
  "geometry": {"coordinates":[6.9054608345,51.0088424683],"type":"Point"}
}