{
  "type": "Feature",
  "properties": {
    "iso:country":"DE",
    "sg:address":"Seestr.",
    "sg:city":"Waabs",
    "sg:phone":"+49 4352/2311",
    "sg:postcode":"24369",
    "sg:province":"Schleswig-Holstein",
    "wof:name":"Ostsee-freizeitpark Booknis",
    "wof:placetype":"venue"
},
  "geometry": {"coordinates":[10.001531,54.552265],"type":"Point"}
}