{
  "type": "Feature",
  "properties": {
    "iso:country":"DE",
    "sg:address":"Britzer Damm 107",
    "sg:city":"Berlin",
    "sg:phone":"+49 30/6008640",
    "sg:postcode":"12347",
    "sg:province":"Berlin",
    "wof:name":"Luisen-apotheke",
    "wof:placetype":"venue"
},
  "geometry": {"coordinates":[13.43855,52.453358],"type":"Point"}
}