{
  "type": "Feature",
  "properties": {
    "iso:country":"DE",
    "sg:address":"Biesenstr. 45",
    "sg:city":"Duisburg",
    "sg:phone":"+49 203/445153",
    "sg:postcode":"47137",
    "sg:province":"Nordrhein-Westfalen",
    "wof:name":"Franz Steines Ingenieur",
    "wof:placetype":"venue"
},
  "geometry": {"coordinates":[6.7718868256,51.4699287415],"type":"Point"}
}