{
  "type": "Feature",
  "properties": {
    "iso:country":"DE",
    "sg:address":"Tilsiter Str. 24",
    "sg:city":"Augsburg",
    "sg:phone":"+49 821/708601",
    "sg:postcode":"86167",
    "sg:province":"Bayern",
    "wof:name":"I. Tausch",
    "wof:placetype":"venue"
},
  "geometry": {"coordinates":[10.919459343,48.3901634216],"type":"Point"}
}