{
  "type": "Feature",
  "properties": {
    "iso:country":"DE",
    "sg:address":"Grumbachweg 15",
    "sg:city":"St. Ingbert",
    "sg:phone":"+49 6894/8343",
    "sg:postcode":"66386",
    "sg:province":"Saarland",
    "wof:name":"Norbert Wei\u00df Rechtsanwalt",
    "wof:placetype":"venue"
},
  "geometry": {"coordinates":[7.0978631973,49.2552452087],"type":"Point"}
}