{
  "type": "Feature",
  "properties": {
    "iso:country":"DE",
    "sg:address":"Kurpfalzstr. 6",
    "sg:city":"Freckenfeld",
    "sg:phone":"+49 6340/8232",
    "sg:postcode":"76872",
    "sg:province":"Rheinland-Pfalz",
    "wof:name":"Heinrich Renze Kommunikationssysteme Gmbh",
    "wof:placetype":"venue"
},
  "geometry": {"coordinates":[8.1113195419,49.0677833557],"type":"Point"}
}