{
  "type": "Feature",
  "properties": {
    "iso:country":"DE",
    "sg:address":"Kaiserstr. 47",
    "sg:city":"Frankfurt",
    "sg:phone":"+49 69/634095",
    "sg:postcode":"60329",
    "sg:province":"Hessen",
    "wof:name":"Air Niugini",
    "wof:placetype":"venue"
},
  "geometry": {"coordinates":[8.670109,50.108692],"type":"Point"}
}