{
  "type": "Feature",
  "properties": {
    "iso:country":"DE",
    "sg:address":"Marktstr. 1",
    "sg:city":"Horb",
    "sg:phone":"+49 7451/1223",
    "sg:postcode":"72160",
    "sg:province":"Baden-W\u00fcrttemberg",
    "wof:name":"Bruno Raible",
    "wof:placetype":"venue"
},
  "geometry": {"coordinates":[8.689459,48.444859],"type":"Point"}
}