{
  "type": "Feature",
  "properties": {
    "iso:country":"DE",
    "sg:address":"Bornreiher Str. 38",
    "sg:city":"Vollersode",
    "sg:phone":"+49 4793/594",
    "sg:postcode":"27729",
    "sg:province":"Niedersachsen",
    "wof:name":"H. W. Reisedienst Inh. Michael Wrieden E. K.",
    "wof:placetype":"venue"
},
  "geometry": {"coordinates":[8.8934869766,53.3121871948],"type":"Point"}
}