{
  "type": "Feature",
  "properties": {
    "iso:country":"DE",
    "sg:address":"Gneisenaustr. 90",
    "sg:city":"M\u00fclheim",
    "sg:phone":"+49 208/498166",
    "sg:postcode":"45472",
    "sg:province":"Nordrhein-Westfalen",
    "wof:name":"Julia D\u00fcmpel",
    "wof:placetype":"venue"
},
  "geometry": {"coordinates":[6.936555,51.427643],"type":"Point"}
}