{
  "type": "Feature",
  "properties": {
    "iso:country":"DE",
    "sg:address":"Berliner Str. 26",
    "sg:city":"Senden",
    "sg:phone":"+49 7307/32316",
    "sg:postcode":"89250",
    "sg:province":"Bayern",
    "wof:name":"Fitness-center J. Stefanic",
    "wof:placetype":"venue"
},
  "geometry": {"coordinates":[10.0397043228,48.3329963684],"type":"Point"}
}