{
  "type": "Feature",
  "properties": {
    "iso:country":"DE",
    "sg:address":"Schwachhauser Heerstr. 30a",
    "sg:city":"Bremen",
    "sg:phone":"+49 421/949460",
    "sg:postcode":"28209",
    "sg:province":"Bremen",
    "wof:name":"Blanke Meier Und Besch Rechtsanw\u00e4lte",
    "wof:placetype":"venue"
},
  "geometry": {"coordinates":[8.8298692703,53.0808525085],"type":"Point"}
}