{
  "type": "Feature",
  "properties": {
    "iso:country":"DE",
    "sg:address":"Im Polder 2",
    "sg:city":"Offenberg",
    "sg:phone":"+49 991/998000",
    "sg:postcode":"94560",
    "sg:province":"Bayern",
    "wof:name":"Hacker Eps-technik Gmbh",
    "wof:placetype":"venue"
},
  "geometry": {"coordinates":[12.887496,48.859676],"type":"Point"}
}