{
  "type": "Feature",
  "properties": {
    "iso:country":"DE",
    "sg:address":"Sprudelstr. 8",
    "sg:city":"Bad H\u00f6nningen",
    "sg:phone":"+49 2635/2333",
    "sg:postcode":"53557",
    "sg:province":"Rheinland-Pfalz",
    "wof:name":"Pyra Formenbau Gmbh",
    "wof:placetype":"venue"
},
  "geometry": {"coordinates":[7.3109788895,50.5157814026],"type":"Point"}
}