{
  "type": "Feature",
  "properties": {
    "iso:country":"DE",
    "sg:address":"Rohrmooser Str. 9",
    "sg:city":"Oberstdorf",
    "sg:phone":"+49 8322/3662",
    "sg:postcode":"87561",
    "sg:province":"Bayern",
    "wof:name":"E. Wildegger",
    "wof:placetype":"venue"
},
  "geometry": {"coordinates":[10.2378501892,47.4177284241],"type":"Point"}
}