{
  "type": "Feature",
  "properties": {
    "iso:country":"DE",
    "sg:address":"Holzmaarstra\u00dfe 53",
    "sg:city":"Gillenfeld",
    "sg:postcode":"54558",
    "sg:province":"Rheinland-Pfalz",
    "wof:name":"Tierbedarf-rietz",
    "wof:placetype":"venue"
},
  "geometry": {"coordinates":[6.901046,50.125053],"type":"Point"}
}