{
  "type": "Feature",
  "properties": {
    "iso:country":"DE",
    "sg:address":"Braustr. 2",
    "sg:city":"Gera",
    "sg:phone":"+49 365/7303200",
    "sg:postcode":"07551",
    "sg:province":"Th\u00fcringen",
    "wof:name":"Ambo Baumarkt Und Gartencenter",
    "wof:placetype":"venue"
},
  "geometry": {"coordinates":[12.086432457,50.8627281189],"type":"Point"}
}