{
  "type": "Feature",
  "properties": {
    "iso:country":"DE",
    "sg:address":"Im Niesetal 11",
    "sg:city":"Schieder-Schwalenberg",
    "sg:phone":"+49 5282/458",
    "sg:postcode":"32816",
    "sg:province":"Nordrhein-Westfalen",
    "wof:name":"G\u00e4stehaus Zur Papierm\u00fchle",
    "wof:placetype":"venue"
},
  "geometry": {"coordinates":[9.147190094,51.9123497009],"type":"Point"}
}