{
  "type": "Feature",
  "properties": {
    "iso:country":"DE",
    "sg:address":"Friedensstr. 6",
    "sg:city":"Wetzlar",
    "sg:phone":"+49 6441/1314",
    "sg:postcode":"35583",
    "sg:province":"Hessen",
    "wof:name":"Ev. Pfarramt Naunheim",
    "wof:placetype":"venue"
},
  "geometry": {"coordinates":[8.5284824371,50.5650291443],"type":"Point"}
}