{
  "type": "Feature",
  "properties": {
    "iso:country":"DE",
    "sg:address":"Hauptstr. 51",
    "sg:city":"Harnekop",
    "sg:phone":"+49 30/2042704",
    "sg:postcode":"16269",
    "sg:province":"Brandenburg",
    "wof:name":"Rene Enter",
    "wof:placetype":"venue"
},
  "geometry": {"coordinates":[14.009442,52.685642],"type":"Point"}
}