{
  "type": "Feature",
  "properties": {
    "iso:country":"DE",
    "sg:address":"Schlo\u00dfstr. 11",
    "sg:city":"Auerbach",
    "sg:phone":"+49 3744/83550",
    "sg:postcode":"08209",
    "sg:province":"Sachsen",
    "wof:name":"Stadt- Und Kreisbibliothek",
    "wof:placetype":"venue"
},
  "geometry": {"coordinates":[12.403018,50.50753],"type":"Point"}
}