{
  "type": "Feature",
  "properties": {
    "iso:country":"DE",
    "sg:address":"Geschwister-Scholl-Platz 4",
    "sg:city":"Taucha",
    "sg:phone":"+49 34441/92700",
    "sg:postcode":"06679",
    "sg:province":"Sachsen-Anhalt",
    "wof:name":"Axel Markmann M\u00f6belmontage",
    "wof:placetype":"venue"
},
  "geometry": {"coordinates":[12.0785932541,51.1925735474],"type":"Point"}
}