{
  "type": "Feature",
  "properties": {
    "iso:country":"DE",
    "sg:address":"Auf Dem Berg 21",
    "sg:city":"Waldbr\u00f6l",
    "sg:phone":"+49 2291/909612",
    "sg:postcode":"51545",
    "sg:province":"Nordrhein-Westfalen",
    "wof:name":"Umutek Industrieautomation",
    "wof:placetype":"venue"
},
  "geometry": {"coordinates":[7.649881,50.894272],"type":"Point"}
}