{
  "type": "Feature",
  "properties": {
    "iso:country":"DE",
    "sg:address":"Auf Der Huels 183",
    "sg:city":"Aachen",
    "sg:phone":"+49 4955/2185160",
    "sg:postcode":"52068",
    "sg:province":"Nordrhein-Westfalen",
    "wof:name":"Paso Pr\u00c4zisionsmaschinenbau Gmbh",
    "wof:placetype":"venue"
},
  "geometry": {"coordinates":[10.31871,51.641228],"type":"Point"}
}