{
  "type": "Feature",
  "properties": {
    "iso:country":"DE",
    "sg:address":"Friedrich-Ebert-Ring 160",
    "sg:city":"Rheine",
    "sg:phone":"+49 5971/64439",
    "sg:postcode":"48429",
    "sg:province":"Nordrhein-Westfalen",
    "wof:name":"Engelbert Schr\u00e4er",
    "wof:placetype":"venue"
},
  "geometry": {"coordinates":[7.449879,52.293816],"type":"Point"}
}