{
  "type": "Feature",
  "properties": {
    "iso:country":"DE",
    "sg:address":"Josef-Probst-Str. 20",
    "sg:city":"Germersheim",
    "sg:phone":"+49 7274/4043",
    "sg:postcode":"76726",
    "sg:province":"Rheinland-Pfalz",
    "wof:name":"Gerasimos Kokkinis Dolmetscher Und \u00dcbersetzer",
    "wof:placetype":"venue"
},
  "geometry": {"coordinates":[8.36509,49.217384],"type":"Point"}
}