{
  "type": "Feature",
  "properties": {
    "iso:country":"DE",
    "sg:address":"Spradower Weg 101",
    "sg:city":"Kirchlengern",
    "sg:phone":"+49 5223/97220",
    "sg:postcode":"32278",
    "sg:province":"Nordrhein-Westfalen",
    "wof:name":"B. Hempelmann Gmbh Industriemontagen",
    "wof:placetype":"venue"
},
  "geometry": {"coordinates":[8.625587,52.205688],"type":"Point"}
}