{
  "type": "Feature",
  "properties": {
    "iso:country":"DE",
    "sg:address":"Friedrich-Wilhelm-Str. 22",
    "sg:city":"Solingen",
    "sg:phone":"+49 212/223340",
    "sg:postcode":"42655",
    "sg:province":"Nordrhein-Westfalen",
    "wof:name":"Becker Manic\u00fcre Siegfried Becker",
    "wof:placetype":"venue"
},
  "geometry": {"coordinates":[7.062255,51.175591],"type":"Point"}
}