{
  "type": "Feature",
  "properties": {
    "iso:country":"DE",
    "sg:address":"Dorotheenstr. 2",
    "sg:city":"Herford",
    "sg:phone":"+49 5221/54668",
    "sg:postcode":"32051",
    "sg:province":"Nordrhein-Westfalen",
    "wof:name":"Bdp Baudesign Und Projektierungs Gmbh",
    "wof:placetype":"venue"
},
  "geometry": {"coordinates":[8.660734,52.112179],"type":"Point"}
}