{
  "type": "Feature",
  "properties": {
    "iso:country":"DE",
    "sg:address":"Im Felde 31",
    "sg:city":"Neustadt",
    "sg:phone":"+49 4561/537777",
    "sg:postcode":"23730",
    "sg:province":"Schleswig-Holstein",
    "wof:name":"Staudenmaier Import-export Gmbh",
    "wof:placetype":"venue"
},
  "geometry": {"coordinates":[10.8850679398,54.1342926025],"type":"Point"}
}