{
  "type": "Feature",
  "properties": {
    "iso:country":"DE",
    "sg:address":"L\u00fctzelstr. 15",
    "sg:city":"B\u00f6hl-Iggelheim",
    "sg:phone":"+49 6324/979500",
    "sg:postcode":"67459",
    "sg:province":"Rheinland-Pfalz",
    "wof:name":"K\u00fcnstler Gmbh",
    "wof:placetype":"venue"
},
  "geometry": {"coordinates":[8.309544,49.366169],"type":"Point"}
}