{
  "type": "Feature",
  "properties": {
    "iso:country":"DE",
    "sg:address":"Hanauer Str. 77",
    "sg:city":"M\u00fcnchen",
    "sg:phone":"+49 89/142294",
    "sg:postcode":"80993",
    "sg:province":"Bayern",
    "wof:name":"Praktiker Bau- Und Heimwerkermarkt",
    "wof:placetype":"venue"
},
  "geometry": {"coordinates":[11.5305299759,48.183265686],"type":"Point"}
}