{
  "type": "Feature",
  "properties": {
    "iso:country":"DE",
    "sg:address":"Lange Str. 25",
    "sg:city":"Blekendorf",
    "sg:phone":"+49 4381/418700",
    "sg:postcode":"24327",
    "sg:province":"Schleswig-Holstein",
    "wof:name":"Marken-werbeartikel H. Misfeld",
    "wof:placetype":"venue"
},
  "geometry": {"coordinates":[10.6516542435,54.2771759033],"type":"Point"}
}