{
  "type": "Feature",
  "properties": {
    "iso:country":"DE",
    "sg:address":"Sandstr. 7",
    "sg:city":"N\u00fcrnberg",
    "sg:postcode":"90443",
    "sg:province":"Bayern",
    "wof:name":"Neidnig Outdoor Media Gmbh",
    "wof:placetype":"venue"
},
  "geometry": {"coordinates":[11.0694570541,49.446647644],"type":"Point"}
}