{
  "type": "Feature",
  "properties": {
    "iso:country":"DE",
    "sg:address":"In der Luke 13",
    "sg:city":"Hagen",
    "sg:phone":"+49 2331/26979",
    "sg:postcode":"58093",
    "sg:province":"Nordrhein-Westfalen",
    "wof:name":"Blumen Fischbach Gmbh",
    "wof:placetype":"venue"
},
  "geometry": {"coordinates":[7.501022,51.359013],"type":"Point"}
}