{
  "type": "Feature",
  "properties": {
    "iso:country":"DE",
    "sg:address":"Havemannstr. 24",
    "sg:city":"Berlin",
    "sg:phone":"+49 30/93881221",
    "sg:postcode":"12689",
    "sg:province":"Berlin",
    "wof:name":"Sonja Gericke",
    "wof:placetype":"venue"
},
  "geometry": {"coordinates":[13.5727233887,52.5679473877],"type":"Point"}
}