{
  "type": "Feature",
  "properties": {
    "iso:country":"DE",
    "sg:address":"Hubert-von-Herkomer-Str. 24",
    "sg:city":"Landsberg",
    "sg:phone":"+49 8191/50017",
    "sg:postcode":"86899",
    "sg:province":"Bayern",
    "wof:name":"Kornblume Naturkost",
    "wof:placetype":"venue"
},
  "geometry": {"coordinates":[10.8767404556,48.0489997864],"type":"Point"}
}