{
  "type": "Feature",
  "properties": {
    "iso:country":"DE",
    "sg:address":"Lohwiese",
    "sg:city":"Saarwellingen",
    "sg:phone":"+49 6838/6496",
    "sg:postcode":"66793",
    "sg:province":"Saarland",
    "wof:name":"Lohwieshalle Reisbach",
    "wof:placetype":"venue"
},
  "geometry": {"coordinates":[6.881805,49.360474],"type":"Point"}
}