{
  "type": "Feature",
  "properties": {
    "iso:country":"DE",
    "sg:address":"Karl-Marx-Str. 56",
    "sg:city":"Guben",
    "sg:postcode":"03172",
    "sg:province":"Brandenburg",
    "wof:name":"Friedengrenze",
    "wof:placetype":"venue"
},
  "geometry": {"coordinates":[14.703818,51.94725],"type":"Point"}
}