{
  "type": "Feature",
  "properties": {
    "iso:country":"DE",
    "sg:address":"Schwicheldter Str. 25",
    "sg:city":"Peine",
    "sg:phone":"+49 5171/2624",
    "sg:postcode":"31228",
    "sg:province":"Niedersachsen",
    "wof:name":"Wilhelm Lutz",
    "wof:placetype":"venue"
},
  "geometry": {"coordinates":[10.182844162,52.3392181396],"type":"Point"}
}