{
  "type": "Feature",
  "properties": {
    "iso:country":"DE",
    "sg:address":"Hauptstr. 234",
    "sg:city":"Burkau",
    "sg:phone":"+49 35953/5237",
    "sg:postcode":"01906",
    "sg:province":"Sachsen",
    "wof:name":"Burkauer Agrar Gmbh",
    "wof:placetype":"venue"
},
  "geometry": {"coordinates":[14.173019,51.175438],"type":"Point"}
}