{
  "type": "Feature",
  "properties": {
    "iso:country":"DE",
    "sg:address":"Ihringsh\u00e4user Str. 162",
    "sg:city":"Kassel",
    "sg:phone":"+49 561/12610",
    "sg:postcode":"34125",
    "sg:province":"Hessen",
    "wof:name":"Heinrich Gleiser Jr. Elektrof.",
    "wof:placetype":"venue"
},
  "geometry": {"coordinates":[9.515469,51.337452],"type":"Point"}
}