{
  "type": "Feature",
  "properties": {
    "iso:country":"DE",
    "sg:address":"Stadtplatz 4",
    "sg:city":"Freyung",
    "sg:phone":"+49 8551/7048",
    "sg:postcode":"94078",
    "sg:province":"Bayern",
    "wof:name":"Kaufhaus Weber Gmbh & Co. Spielwaren Kg",
    "wof:placetype":"venue"
},
  "geometry": {"coordinates":[13.5472640991,48.8087844849],"type":"Point"}
}