{
  "type": "Feature",
  "properties": {
    "iso:country":"DE",
    "sg:address":"Moselstr. 19",
    "sg:city":"Neuss",
    "sg:phone":"+49 4921/319380",
    "sg:postcode":"41464",
    "sg:province":"Nordrhein-Westfalen",
    "wof:name":"Mg Rover Deutschland Gmbh",
    "wof:placetype":"venue"
},
  "geometry": {"coordinates":[6.6796507835,51.1795158386],"type":"Point"}
}