{
  "type": "Feature",
  "properties": {
    "iso:country":"DE",
    "sg:address":"Egenstr. 33",
    "sg:city":"Wuppertal",
    "sg:phone":"+49 202/763498",
    "sg:postcode":"42113",
    "sg:province":"Nordrhein-Westfalen",
    "wof:name":"Wolfgang Schulze Ingenieur",
    "wof:placetype":"venue"
},
  "geometry": {"coordinates":[7.1211299896,51.2722816467],"type":"Point"}
}