{
  "type": "Feature",
  "properties": {
    "iso:country":"DE",
    "sg:address":"Friedrich-Kirchhoff-Str. 17",
    "sg:city":"Iserlohn",
    "sg:phone":"+49 2371/40275",
    "sg:postcode":"58640",
    "sg:province":"Nordrhein-Westfalen",
    "wof:name":"Tischlerei Jacob Inh. Wolfram Meyer E. K.",
    "wof:placetype":"venue"
},
  "geometry": {"coordinates":[7.695458,51.403439],"type":"Point"}
}