{
  "type": "Feature",
  "properties": {
    "iso:country":"DE",
    "sg:address":"Kapellenweg 12",
    "sg:city":"Freiburg",
    "sg:phone":"+49 761/402212",
    "sg:postcode":"79100",
    "sg:province":"Baden-W\u00fcrttemberg",
    "wof:name":"Dr. Hanns G\u00fcnther Riehle Architekt",
    "wof:placetype":"venue"
},
  "geometry": {"coordinates":[7.837334,47.978607],"type":"Point"}
}