{
  "type": "Feature",
  "properties": {
    "iso:country":"DE",
    "sg:address":"Alexandrinenstr. 68",
    "sg:city":"Rostock",
    "sg:phone":"+49 381/51237",
    "sg:postcode":"18119",
    "sg:province":"Mecklenburg-Vorpommern",
    "wof:name":"Paloma Dessous Und Herrenbekleidung",
    "wof:placetype":"venue"
},
  "geometry": {"coordinates":[12.0861616135,54.179523468],"type":"Point"}
}