{
  "type": "Feature",
  "properties": {
    "iso:country":"DE",
    "sg:address":"Br\u00e4uweg 6",
    "sg:city":"Wenzenbach",
    "sg:phone":"+49 9407/1806",
    "sg:postcode":"93173",
    "sg:province":"Bayern",
    "wof:name":"A. Ernst Mech. Werkstatt",
    "wof:placetype":"venue"
},
  "geometry": {"coordinates":[12.179281,49.076237],"type":"Point"}
}