{
  "type": "Feature",
  "properties": {
    "iso:country":"DE",
    "sg:address":"Hauptstr. 24",
    "sg:city":"Ha\u00dffurt",
    "sg:phone":"+49 9521/2071",
    "sg:postcode":"97437",
    "sg:province":"Bayern",
    "wof:name":"Volksbank Bamberg Eg",
    "wof:placetype":"venue"
},
  "geometry": {"coordinates":[10.508124,50.031544],"type":"Point"}
}