{
  "type": "Feature",
  "properties": {
    "iso:country":"DE",
    "sg:address":"Berger Str. 314",
    "sg:city":"Frankfurt",
    "sg:postcode":"60385",
    "sg:province":"Hessen",
    "wof:name":"Concrete Bautenschutz Gmbh",
    "wof:placetype":"venue"
},
  "geometry": {"coordinates":[8.71115,50.130493],"type":"Point"}
}