{
  "type": "Feature",
  "properties": {
    "iso:country":"DE",
    "sg:address":"Beethovenstr. 21",
    "sg:city":"Cainsdorf",
    "sg:phone":"+49 375/62011",
    "sg:postcode":"08124",
    "wof:name":"S. M\u00f6ckel",
    "wof:placetype":"venue"
},
  "geometry": {"coordinates":[12.49368,50.670269],"type":"Point"}
}