{
  "type": "Feature",
  "properties": {
    "iso:country":"DE",
    "sg:address":"Kanalstr. 8",
    "sg:city":"Marienwerder",
    "sg:phone":"+49 3335/31371",
    "sg:postcode":"16348",
    "sg:province":"Brandenburg",
    "wof:name":"G\u00fcnter Schulz",
    "wof:placetype":"venue"
},
  "geometry": {"coordinates":[13.596444,52.838966],"type":"Point"}
}