{
  "type": "Feature",
  "properties": {
    "iso:country":"DE",
    "sg:address":"Lehbrinksweg 68",
    "sg:city":"Lemgo",
    "sg:phone":"+49 5261/96670",
    "sg:postcode":"32657",
    "sg:province":"Nordrhein-Westfalen",
    "wof:name":"Kracht & Co Gmbh",
    "wof:placetype":"venue"
},
  "geometry": {"coordinates":[8.838113,52.033165],"type":"Point"}
}