{
  "type": "Feature",
  "properties": {
    "iso:country":"DE",
    "sg:address":"Leerer Str. 28",
    "sg:city":"Westerstede",
    "sg:phone":"+49 4488/79513",
    "sg:postcode":"26655",
    "sg:province":"Niedersachsen",
    "wof:name":"Bienenhof Ammerland Kg",
    "wof:placetype":"venue"
},
  "geometry": {"coordinates":[7.8717808723,53.2924842834],"type":"Point"}
}