{
  "type": "Feature",
  "properties": {
    "iso:country":"DE",
    "sg:address":"Kiehlufer 59",
    "sg:city":"Berlin",
    "sg:phone":"+49 30/68809300",
    "sg:postcode":"12059",
    "sg:province":"Berlin",
    "wof:name":"B\u00e4rchen-music-berlin",
    "wof:placetype":"venue"
},
  "geometry": {"coordinates":[13.445591,52.484833],"type":"Point"}
}