{
  "type": "Feature",
  "properties": {
    "iso:country":"DE",
    "sg:address":"Friedrichstr. 84",
    "sg:city":"Kuppenheim",
    "sg:phone":"+49 7222/408333",
    "sg:postcode":"76456",
    "sg:province":"Baden-W\u00fcrttemberg",
    "wof:name":"Stopschild",
    "wof:placetype":"venue"
},
  "geometry": {"coordinates":[8.2539691925,48.8275184631],"type":"Point"}
}