{
  "type": "Feature",
  "properties": {
    "iso:country":"DE",
    "sg:address":"Pfaffenrieder Str. 18::",
    "sg:city":"Wolfratshausen",
    "sg:phone":"+49 8171/91180",
    "sg:postcode":"82515",
    "sg:province":"Bayern",
    "wof:name":"Siebert Werkzeugmaschinen Vertrieb Gmbh",
    "wof:placetype":"venue"
},
  "geometry": {"coordinates":[11.427668,47.903088],"type":"Point"}
}