{
  "type": "Feature",
  "properties": {
    "iso:country":"DE",
    "sg:address":"Birgidstr. 3",
    "sg:city":"Wiesbaden",
    "sg:phone":"+49 611/500760",
    "sg:postcode":"65191",
    "sg:province":"Hessen",
    "wof:name":"Doris Jablonski",
    "wof:placetype":"venue"
},
  "geometry": {"coordinates":[8.2806472778,50.0828094482],"type":"Point"}
}