{
  "type": "Feature",
  "properties": {
    "iso:country":"DE",
    "sg:address":"Abraham-a-Santa-Clara-Str. 9",
    "sg:city":"Leibertingen",
    "sg:phone":"+49 7570/245",
    "sg:postcode":"88637",
    "sg:province":"Baden-W\u00fcrttemberg",
    "wof:name":"Alois Steidle",
    "wof:placetype":"venue"
},
  "geometry": {"coordinates":[9.015516,48.042656],"type":"Point"}
}