{
  "type": "Feature",
  "properties": {
    "iso:country":"DE",
    "sg:address":"Moorstr. 24",
    "sg:city":"Walsrode",
    "sg:phone":"+49 5161/3533",
    "sg:postcode":"29664",
    "sg:province":"Niedersachsen",
    "wof:name":"Gastst\u00e4tte St. Hubertus",
    "wof:placetype":"venue"
},
  "geometry": {"coordinates":[9.593542099,52.8619270325],"type":"Point"}
}