{
  "type": "Feature",
  "properties": {
    "iso:country":"DE",
    "sg:address":"Hansaallee 21",
    "sg:city":"Frankfurt",
    "sg:phone":"+49 69/591429",
    "sg:postcode":"60322",
    "sg:province":"Hessen",
    "wof:name":"Herbert Michel",
    "wof:placetype":"venue"
},
  "geometry": {"coordinates":[8.673275,50.124363],"type":"Point"}
}