{
  "type": "Feature",
  "properties": {
    "iso:country":"DE",
    "sg:address":"F\u00fcrther Str. 184",
    "sg:city":"N\u00fcrnberg",
    "sg:phone":"+49 911/3263089",
    "sg:postcode":"90429",
    "sg:province":"Bayern",
    "wof:name":"Asia-food",
    "wof:placetype":"venue"
},
  "geometry": {"coordinates":[11.038274765,49.4569396973],"type":"Point"}
}