{
  "type": "Feature",
  "properties": {
    "iso:country":"DE",
    "sg:address":"Dickhardtstr. 23",
    "sg:city":"Berlin",
    "sg:phone":"+49 30/85999133",
    "sg:postcode":"12161",
    "sg:province":"Berlin",
    "wof:name":"Jesse Greene",
    "wof:placetype":"venue"
},
  "geometry": {"coordinates":[13.3326931,52.4671020508],"type":"Point"}
}