{
  "type": "Feature",
  "properties": {
    "iso:country":"DE",
    "sg:address":"G\u00f6rresstr. 27",
    "sg:city":"Berlin",
    "sg:phone":"+49 30/4124130",
    "sg:postcode":"12161",
    "sg:province":"Berlin",
    "wof:name":"Dr. Med. Gudrun Schinzel",
    "wof:placetype":"venue"
},
  "geometry": {"coordinates":[13.3248987198,52.4750671387],"type":"Point"}
}