{
  "type": "Feature",
  "properties": {
    "iso:country":"DE",
    "sg:address":"Am Schleierborn 9",
    "sg:city":"Eisenach",
    "sg:postcode":"99817",
    "sg:province":"Th\u00fcringen",
    "wof:name":"Pflegeheim Eisenach-nord",
    "wof:placetype":"venue"
},
  "geometry": {"coordinates":[10.325439,50.97438],"type":"Point"}
}