{
  "type": "Feature",
  "properties": {
    "iso:country":"DE",
    "sg:address":"Am Industriegel\u00e4nde 5",
    "sg:city":"Ludwigslust",
    "sg:postcode":"19288",
    "sg:province":"Mecklenburg-Vorpommern",
    "wof:name":"E. S. Sonderposten Gmbh",
    "wof:placetype":"venue"
},
  "geometry": {"coordinates":[11.511842,53.308239],"type":"Point"}
}