{
  "type": "Feature",
  "properties": {
    "iso:country":"DE",
    "sg:address":"Beerfurther Str. 53",
    "sg:city":"Reichelsheim",
    "sg:phone":"+49 6164/2572",
    "sg:postcode":"64385",
    "sg:province":"Hessen",
    "wof:name":"J. Und K. Pr\u00fcfer Heissmangel",
    "wof:placetype":"venue"
},
  "geometry": {"coordinates":[8.8449697495,49.7136535645],"type":"Point"}
}