{
  "type": "Feature",
  "properties": {
    "iso:country":"DE",
    "sg:address":"In der Krause 59",
    "sg:city":"Eschweiler",
    "sg:phone":"+49 2403/989388",
    "sg:postcode":"52249",
    "sg:province":"Nordrhein-Westfalen",
    "wof:name":"Siegfried Suthau Gmbh",
    "wof:placetype":"venue"
},
  "geometry": {"coordinates":[6.30774,50.82737],"type":"Point"}
}