{
  "type": "Feature",
  "properties": {
    "iso:country":"DE",
    "sg:address":"Unterer Stadtplatz 4",
    "sg:city":"Hemau",
    "sg:phone":"+49 9491/1362",
    "sg:postcode":"93155",
    "sg:province":"Bayern",
    "wof:name":"Pizzeria Dolomiti",
    "wof:placetype":"venue"
},
  "geometry": {"coordinates":[11.7848300934,49.0505599976],"type":"Point"}
}