{
  "type": "Feature",
  "properties": {
    "iso:country":"DE",
    "sg:address":"Rheinhorststr. 21",
    "sg:city":"Ludwigshafen",
    "sg:phone":"+49 621/672022",
    "sg:postcode":"67071",
    "sg:province":"Rheinland-Pfalz",
    "wof:name":"Afk - Hydraulik Karl Kr\u00e4mer Gmbh & Co. Kg",
    "wof:placetype":"venue"
},
  "geometry": {"coordinates":[8.37151,49.499363],"type":"Point"}
}