{
  "type": "Feature",
  "properties": {
    "iso:country":"DE",
    "sg:address":"Kirchstr. 17",
    "sg:city":"N\u00fcrtingen",
    "sg:phone":"+49 7022/932440",
    "sg:postcode":"72622",
    "sg:province":"Baden-W\u00fcrttemberg",
    "wof:name":"Psycho-soz. Beratungsstelle D. Landkreises Und D.",
    "wof:placetype":"venue"
},
  "geometry": {"coordinates":[9.336236,48.627052],"type":"Point"}
}