{
  "type": "Feature",
  "properties": {
    "iso:country":"DE",
    "sg:address":"R\u00f6delheimer Str. 25",
    "sg:city":"Frankfurt",
    "sg:phone":"+49 69/775418",
    "sg:postcode":"60487",
    "sg:province":"Hessen",
    "wof:name":"Kutscherstubb Am Sch\u00f6nhof",
    "wof:placetype":"venue"
},
  "geometry": {"coordinates":[8.6364994049,50.1240844727],"type":"Point"}
}