{
  "type": "Feature",
  "properties": {
    "iso:country":"DE",
    "sg:address":"Hederichweg 27",
    "sg:city":"Menden",
    "sg:phone":"+49 2373/65179",
    "sg:postcode":"58708",
    "sg:province":"Nordrhein-Westfalen",
    "wof:name":"Fritz U. Renate Schroter",
    "wof:placetype":"venue"
},
  "geometry": {"coordinates":[7.753474,51.43298],"type":"Point"}
}