{
  "type": "Feature",
  "properties": {
    "iso:country":"DE",
    "sg:address":"Frohnrather Weg",
    "sg:city":"Aachen",
    "sg:phone":"+49 2407/3375",
    "sg:postcode":"52072",
    "sg:province":"Nordrhein-Westfalen",
    "wof:name":"Hans Hogen",
    "wof:placetype":"venue"
},
  "geometry": {"coordinates":[6.041415,50.835915],"type":"Point"}
}