{
  "type": "Feature",
  "properties": {
    "iso:country":"DE",
    "sg:address":"Am Rathaus 14",
    "sg:city":"Oberasbach",
    "sg:phone":"+49 911/699394",
    "sg:postcode":"90522",
    "sg:province":"Bayern",
    "wof:name":"C. Tr\u00f6ger",
    "wof:placetype":"venue"
},
  "geometry": {"coordinates":[10.970649,49.431519],"type":"Point"}
}