{
  "type": "Feature",
  "properties": {
    "iso:country":"DE",
    "sg:address":"Staudach 14",
    "sg:city":"Massing",
    "sg:phone":"+49 8724/1276",
    "sg:postcode":"84323",
    "sg:province":"Bayern",
    "wof:name":"Johann Schwinghammer",
    "wof:placetype":"venue"
},
  "geometry": {"coordinates":[12.6455278397,48.4280776978],"type":"Point"}
}