{
  "type": "Feature",
  "properties": {
    "iso:country":"DE",
    "sg:address":"R\u00f6dingsmarkt 19",
    "sg:city":"Hamburg",
    "sg:phone":"+49 40/362560",
    "sg:postcode":"20459",
    "sg:province":"Hamburg",
    "wof:name":"B. Machel",
    "wof:placetype":"venue"
},
  "geometry": {"coordinates":[9.986593,53.54726],"type":"Point"}
}