{
  "type": "Feature",
  "properties": {
    "iso:country":"DE",
    "sg:address":"Stadtbahnstr. 21",
    "sg:city":"Hamburg",
    "sg:phone":"+49 40/6017058",
    "sg:postcode":"22393",
    "sg:province":"Hamburg",
    "wof:name":"Karsten Loitz",
    "wof:placetype":"venue"
},
  "geometry": {"coordinates":[10.1066255569,53.6534843445],"type":"Point"}
}