{
  "type": "Feature",
  "properties": {
    "iso:country":"DE",
    "sg:address":"Pelzerstr. 4",
    "sg:city":"Hamburg",
    "sg:phone":"+49 40/3232630",
    "sg:postcode":"20095",
    "sg:province":"Hamburg",
    "wof:name":"Wwk Lebensversicherung A. G.",
    "wof:placetype":"venue"
},
  "geometry": {"coordinates":[9.9946622849,53.549621582],"type":"Point"}
}