{
  "type": "Feature",
  "properties": {
    "iso:country":"DE",
    "sg:address":"Pforzheimer Str. 22",
    "sg:city":"Pforzheim",
    "sg:phone":"+49 7231/75242",
    "sg:postcode":"75180",
    "sg:province":"Baden-W\u00fcrttemberg",
    "wof:name":"A. Heinze",
    "wof:placetype":"venue"
},
  "geometry": {"coordinates":[8.662067,48.85537],"type":"Point"}
}