{
  "type": "Feature",
  "properties": {
    "iso:country":"DE",
    "sg:address":"Olgastr. 120",
    "sg:city":"Stuttgart",
    "sg:phone":"+49 711/6017300",
    "sg:postcode":"70180",
    "sg:province":"Baden-W\u00fcrttemberg",
    "wof:name":"Kottkamp Und Schneider Architekten",
    "wof:placetype":"venue"
},
  "geometry": {"coordinates":[9.178026,48.766918],"type":"Point"}
}