{
  "type": "Feature",
  "properties": {
    "iso:country":"DE",
    "sg:address":"Abtstr. 4",
    "sg:city":"Buxtehude",
    "sg:phone":"+49 4161/2956",
    "sg:postcode":"21614",
    "sg:province":"Niedersachsen",
    "wof:name":"V. Janosevic",
    "wof:placetype":"venue"
},
  "geometry": {"coordinates":[9.7014036179,53.4772644043],"type":"Point"}
}