{
  "type": "Feature",
  "properties": {
    "iso:country":"DE",
    "sg:address":"Gerberstr. 4",
    "sg:city":"Homburg",
    "sg:phone":"+49 6841/4028",
    "sg:postcode":"66424",
    "sg:province":"Saarland",
    "wof:name":"Herbert Eder W. Fredershausen",
    "wof:placetype":"venue"
},
  "geometry": {"coordinates":[7.3390130997,49.3204536438],"type":"Point"}
}