{
  "type": "Feature",
  "properties": {
    "iso:country":"DE",
    "sg:address":"Bernhardstr. 35",
    "sg:city":"Essen",
    "sg:phone":"+49 201/403421",
    "sg:postcode":"45239",
    "sg:province":"Nordrhein-Westfalen",
    "wof:name":"Paul Zeunert Gmbh",
    "wof:placetype":"venue"
},
  "geometry": {"coordinates":[7.023796,51.393635],"type":"Point"}
}