{
  "type": "Feature",
  "properties": {
    "iso:country":"DE",
    "sg:address":"An den H\u00f6fen 3",
    "sg:city":"Seevetal",
    "sg:phone":"+49 40/7688005",
    "sg:postcode":"21217",
    "sg:province":"Niedersachsen",
    "wof:name":"La Trattoria Di Meckelfeld",
    "wof:placetype":"venue"
},
  "geometry": {"coordinates":[10.0215301514,53.4222106934],"type":"Point"}
}