{
  "type": "Feature",
  "properties": {
    "iso:country":"DE",
    "sg:address":"Lilienthal-Str. 41",
    "sg:city":"Ottobrunn",
    "sg:phone":"+49 89/6091135",
    "sg:postcode":"85521",
    "sg:province":"Bayern",
    "wof:name":"Bayerische Vereinsbank Ag",
    "wof:placetype":"venue"
},
  "geometry": {"coordinates":[11.655757,48.05175],"type":"Point"}
}