{
  "type": "Feature",
  "properties": {
    "iso:country":"DE",
    "sg:address":"Im Gef\u00e4lle 3",
    "sg:city":"Marburg",
    "sg:phone":"+49 6421/67161",
    "sg:postcode":"35039",
    "sg:province":"Hessen",
    "wof:name":"Heinrich Schmidt Ohg Lebensmittel Und Feinkost",
    "wof:placetype":"venue"
},
  "geometry": {"coordinates":[8.7781677246,50.8205680847],"type":"Point"}
}