{
  "type": "Feature",
  "properties": {
    "iso:country":"DE",
    "sg:address":"Nombericher Str. 39",
    "sg:city":"Duisburg",
    "sg:postcode":"47137",
    "sg:province":"Nordrhein-Westfalen",
    "wof:name":"Maas Eventservices Gmbh",
    "wof:placetype":"venue"
},
  "geometry": {"coordinates":[6.759384,51.469952],"type":"Point"}
}