{
  "type": "Feature",
  "properties": {
    "iso:country":"DE",
    "sg:address":"Dinnendahlstr. 134",
    "sg:city":"Essen",
    "sg:phone":"+49 201/262109",
    "sg:postcode":"45136",
    "sg:province":"Nordrhein-Westfalen",
    "wof:name":"Wilhelm Hussing & Co. Kg",
    "wof:placetype":"venue"
},
  "geometry": {"coordinates":[7.0559539795,51.4368515015],"type":"Point"}
}