{
  "type": "Feature",
  "properties": {
    "iso:country":"DE",
    "sg:address":"Vordergasse 72",
    "sg:city":"Partenheim",
    "sg:phone":"+49 6732/8811",
    "sg:postcode":"55288",
    "sg:province":"Rheinland-Pfalz",
    "wof:name":"Volker Nehrba\u00df-ahles Und Martina K\u00e4stel-nehrba\u00df-ahles",
    "wof:placetype":"venue"
},
  "geometry": {"coordinates":[8.075921,49.883106],"type":"Point"}
}