{
  "type": "Feature",
  "properties": {
    "iso:country":"DE",
    "sg:address":"Bretthorststr. 130",
    "sg:city":"Vlotho",
    "sg:phone":"+49 5733/3289",
    "sg:postcode":"32602",
    "sg:province":"Nordrhein-Westfalen",
    "wof:name":"Friedhelm Klocke",
    "wof:placetype":"venue"
},
  "geometry": {"coordinates":[8.8665342331,52.1509475708],"type":"Point"}
}