{
  "type": "Feature",
  "properties": {
    "iso:country":"DE",
    "sg:address":"Nagelsweg 37",
    "sg:city":"Hamburg",
    "sg:phone":"+49 40/24864077",
    "sg:postcode":"20097",
    "sg:province":"Hamburg",
    "wof:name":"Hamburgisches Oberverwaltungsgericht-verwal-",
    "wof:placetype":"venue"
},
  "geometry": {"coordinates":[10.019818,53.547039],"type":"Point"}
}