{
  "type": "Feature",
  "properties": {
    "iso:country":"DE",
    "sg:address":"Sternstr. 21",
    "sg:city":"M\u00fcnchen",
    "sg:postcode":"80538",
    "sg:province":"Bayern",
    "wof:name":"Harder Consult Gesellschaft F\u00fcr Design",
    "wof:placetype":"venue"
},
  "geometry": {"coordinates":[11.590970993,48.1405410767],"type":"Point"}
}