{
  "type": "Feature",
  "properties": {
    "iso:country":"DE",
    "sg:address":"Hauptstr. 35",
    "sg:city":"Diedorf",
    "sg:postcode":"86420",
    "sg:province":"Bayern",
    "wof:name":"R. Zangl",
    "wof:placetype":"venue"
},
  "geometry": {"coordinates":[10.7737417221,48.3528442383],"type":"Point"}
}