{
  "type": "Feature",
  "properties": {
    "iso:country":"DE",
    "sg:address":"Recker\u00f6der Str. 10",
    "sg:city":"Kirchheim",
    "sg:phone":"+49 6625/8105",
    "sg:postcode":"36275",
    "sg:province":"Hessen",
    "wof:name":"Reckeroder Hof",
    "wof:placetype":"venue"
},
  "geometry": {"coordinates":[9.596465,50.862019],"type":"Point"}
}