{
  "type": "Feature",
  "properties": {
    "iso:country":"DE",
    "sg:address":"Danziger Str. 5",
    "sg:city":"M\u00fcnchen",
    "sg:phone":"+49 89/3615073",
    "sg:postcode":"80805",
    "sg:province":"Bayern",
    "wof:name":"Franz Kellner Architekt",
    "wof:placetype":"venue"
},
  "geometry": {"coordinates":[11.590941,48.169025],"type":"Point"}
}