{
  "type": "Feature",
  "properties": {
    "iso:country":"DE",
    "sg:address":"Radetzkystr. 19",
    "sg:city":"Augsburg",
    "sg:phone":"+49 821/791376",
    "sg:postcode":"86165",
    "sg:province":"Bayern",
    "wof:name":"Josef Pr\u00f6bstl",
    "wof:placetype":"venue"
},
  "geometry": {"coordinates":[10.916909,48.376106],"type":"Point"}
}