{
  "type": "Feature",
  "properties": {
    "iso:country":"DE",
    "sg:address":"Christhauser Str. 23",
    "sg:city":"Remscheid",
    "sg:phone":"+49 2191/662677",
    "sg:postcode":"42897",
    "sg:province":"Nordrhein-Westfalen",
    "wof:name":"Heinz-j\u00fcrgen Hirschfeld",
    "wof:placetype":"venue"
},
  "geometry": {"coordinates":[7.271189,51.194576],"type":"Point"}
}