{
  "type": "Feature",
  "properties": {
    "iso:country":"DE",
    "sg:address":"Hauptstr. 24",
    "sg:city":"Friesenhagen",
    "sg:phone":"+49 2734/489090",
    "sg:postcode":"51598",
    "sg:province":"Rheinland-Pfalz",
    "wof:name":"Solbach-spitz",
    "wof:placetype":"venue"
},
  "geometry": {"coordinates":[7.8098869324,50.902973175],"type":"Point"}
}