{
  "type": "Feature",
  "properties": {
    "iso:country":"DE",
    "sg:address":"Ringstr. 5",
    "sg:city":"Krogaspe",
    "sg:phone":"+49 4392/5688",
    "sg:postcode":"24644",
    "sg:province":"Schleswig-Holstein",
    "wof:name":"Rolf Behnke",
    "wof:placetype":"venue"
},
  "geometry": {"coordinates":[9.929889,54.133205],"type":"Point"}
}