{
  "type": "Feature",
  "properties": {
    "iso:country":"DE",
    "sg:address":"Espenpark 30",
    "sg:city":"Burgthann",
    "sg:phone":"+49 9188/903903",
    "sg:postcode":"90559",
    "sg:province":"Bayern",
    "wof:name":"D2 Shop Burgthann",
    "wof:placetype":"venue"
},
  "geometry": {"coordinates":[11.3394956589,49.3178596497],"type":"Point"}
}