{
  "type": "Feature",
  "properties": {
    "iso:country":"DE",
    "sg:address":"Kleiststr. 13",
    "sg:city":"Meckenheim",
    "sg:phone":"+49 2225/7712",
    "sg:postcode":"53340",
    "sg:province":"Nordrhein-Westfalen",
    "wof:name":"Peter Kirner",
    "wof:placetype":"venue"
},
  "geometry": {"coordinates":[7.0295801163,50.6274375916],"type":"Point"}
}