{
  "type": "Feature",
  "properties": {
    "iso:country":"DE",
    "sg:address":"Jakobstr. 6",
    "sg:city":"Tamm",
    "sg:phone":"+49 7141/601761",
    "sg:postcode":"71732",
    "sg:province":"Baden-W\u00fcrttemberg",
    "wof:name":"Werner Hagenbucher",
    "wof:placetype":"venue"
},
  "geometry": {"coordinates":[9.121912,48.921207],"type":"Point"}
}