{
  "type": "Feature",
  "properties": {
    "iso:country":"DE",
    "sg:address":"Am Waldrand 97a",
    "sg:city":"H\u00fcckelhoven",
    "sg:phone":"+49 2433/85132",
    "sg:postcode":"41836",
    "sg:province":"Nordrhein-Westfalen",
    "wof:name":"Restaurant Dalmatien",
    "wof:placetype":"venue"
},
  "geometry": {"coordinates":[6.1970000267,51.0664215088],"type":"Point"}
}