{
  "type": "Feature",
  "properties": {
    "iso:country":"DE",
    "sg:address":"B\u00fcchl 1",
    "sg:city":"Waldkirchen",
    "sg:phone":"+49 8581/8613",
    "sg:postcode":"94065",
    "sg:province":"Bayern",
    "wof:name":"Kath. Pfarramt St. Petrus Und Paulus",
    "wof:placetype":"venue"
},
  "geometry": {"coordinates":[13.6010990143,48.7291679382],"type":"Point"}
}