{
  "type": "Feature",
  "properties": {
    "iso:country":"DE",
    "sg:address":"In der Au 21",
    "sg:city":"Langerwehe",
    "sg:phone":"+49 2423/2245",
    "sg:postcode":"52379",
    "sg:province":"Nordrhein-Westfalen",
    "wof:name":"Heinz Horst",
    "wof:placetype":"venue"
},
  "geometry": {"coordinates":[6.40438,50.796158],"type":"Point"}
}