{
  "type": "Feature",
  "properties": {
    "iso:country":"DE",
    "sg:address":"Osterweg 40",
    "sg:city":"Nieb\u00fcll",
    "sg:phone":"+49 4661/20241",
    "sg:postcode":"25899",
    "sg:province":"Schleswig-Holstein",
    "wof:name":"K. H\u00f6hne Steuerberater",
    "wof:placetype":"venue"
},
  "geometry": {"coordinates":[8.8269376755,54.7839813232],"type":"Point"}
}