{
  "type": "Feature",
  "properties": {
    "iso:country":"DE",
    "sg:address":"Am Markt 7",
    "sg:city":"K\u00f6nigslutter",
    "sg:phone":"+49 5353/910819",
    "sg:postcode":"38154",
    "sg:province":"Niedersachsen",
    "wof:name":"Rossmann Drogeriemarkt",
    "wof:placetype":"venue"
},
  "geometry": {"coordinates":[10.818073,52.251026],"type":"Point"}
}