{
  "type": "Feature",
  "properties": {
    "iso:country":"DE",
    "sg:address":"Sudetenstr. 73",
    "sg:city":"Geretsried",
    "sg:phone":"+49 8171/909016",
    "sg:postcode":"82538",
    "sg:province":"Bayern",
    "wof:name":"Aktiv-center Training F. Sport Usw. Gmbh",
    "wof:placetype":"venue"
},
  "geometry": {"coordinates":[11.4962282181,47.8528060913],"type":"Point"}
}