{
  "type": "Feature",
  "properties": {
    "iso:country":"DE",
    "sg:address":"Offenbacher Str. 23",
    "sg:city":"N\u00fcrnberg",
    "sg:phone":"+49 911/301911",
    "sg:postcode":"90427",
    "sg:province":"Bayern",
    "wof:name":"Caroline M\u00fcller Inh. Volker M\u00fcller",
    "wof:placetype":"venue"
},
  "geometry": {"coordinates":[11.006467,49.523674],"type":"Point"}
}