{
  "type": "Feature",
  "properties": {
    "iso:country":"DE",
    "sg:address":"Dossental",
    "sg:city":"Gondelsheim",
    "sg:phone":"+49 7252/974667",
    "sg:postcode":"75053",
    "sg:province":"Baden-W\u00fcrttemberg",
    "wof:name":"Klaus Bittrolff",
    "wof:placetype":"venue"
},
  "geometry": {"coordinates":[8.641246,49.071976],"type":"Point"}
}