{
  "type": "Feature",
  "properties": {
    "iso:country":"DE",
    "sg:address":"Ernst-von-Harnack-Str. 5",
    "sg:city":"Wiesbaden",
    "sg:phone":"+49 611/463622",
    "sg:postcode":"65197",
    "sg:province":"Hessen",
    "wof:name":"Manfred Wich",
    "wof:placetype":"venue"
},
  "geometry": {"coordinates":[8.2047080994,50.083782196],"type":"Point"}
}