{
  "type": "Feature",
  "properties": {
    "iso:country":"DE",
    "sg:address":"Adlerweg 6",
    "sg:city":"Wiesmoor",
    "sg:phone":"+49 4944/7701",
    "sg:postcode":"26639",
    "sg:province":"Niedersachsen",
    "wof:name":"Hermann Grusewski",
    "wof:placetype":"venue"
},
  "geometry": {"coordinates":[7.7468838692,53.410736084],"type":"Point"}
}