{
  "type": "Feature",
  "properties": {
    "iso:country":"DE",
    "sg:address":"Franz-Peter-Sigel-Str. 39",
    "sg:city":"Bad Sch\u00f6nborn",
    "sg:phone":"+49 7253/97700",
    "sg:postcode":"76669",
    "sg:province":"Baden-W\u00fcrttemberg",
    "wof:name":"Hotel Garni Peters",
    "wof:placetype":"venue"
},
  "geometry": {"coordinates":[8.6533670425,49.2019844055],"type":"Point"}
}