{
  "type": "Feature",
  "properties": {
    "iso:country":"DE",
    "sg:address":"Brunnenstr. 69",
    "sg:city":"Bad Wildungen",
    "sg:phone":"+49 5621/6965",
    "sg:postcode":"34537",
    "sg:province":"Hessen",
    "wof:name":"Willy Schulz Krankengymnast",
    "wof:placetype":"venue"
},
  "geometry": {"coordinates":[9.119257,51.117996],"type":"Point"}
}