{
  "type": "Feature",
  "properties": {
    "iso:country":"DE",
    "sg:address":"Mainzer Str. 193",
    "sg:city":"Saarbr\u00fccken",
    "sg:postcode":"66121",
    "sg:province":"Saarland",
    "wof:name":"Ihl Inhouse Logistik Gmbh",
    "wof:placetype":"venue"
},
  "geometry": {"coordinates":[7.019415,49.22731],"type":"Point"}
}