{
  "type": "Feature",
  "properties": {
    "iso:country":"DE",
    "sg:address":"Hans-B\u00f6ckler-Str. 19",
    "sg:city":"Kirchheim",
    "sg:phone":"+49 7021/82877",
    "sg:postcode":"73230",
    "sg:province":"Baden-W\u00fcrttemberg",
    "wof:name":"Guido Layer Architekt",
    "wof:placetype":"venue"
},
  "geometry": {"coordinates":[9.476042,48.639732],"type":"Point"}
}