{
  "type": "Feature",
  "properties": {
    "iso:country":"DE",
    "sg:address":"Hembecker Talstr. 69",
    "sg:city":"Ennepetal",
    "sg:phone":"+49 2333/70531",
    "sg:postcode":"58256",
    "sg:province":"Nordrhein-Westfalen",
    "wof:name":"Paul-august Raabe Mech. Werkstatt",
    "wof:placetype":"venue"
},
  "geometry": {"coordinates":[7.323117,51.302429],"type":"Point"}
}