{
  "type": "Feature",
  "properties": {
    "iso:country":"DE",
    "sg:address":"Forsthausweg 5",
    "sg:city":"Northeim",
    "sg:phone":"+49 5551/911940",
    "sg:postcode":"37154",
    "sg:province":"Niedersachsen",
    "wof:name":"Mitarbeiter Service Pro Gastro Gmbh",
    "wof:placetype":"venue"
},
  "geometry": {"coordinates":[10.01151,51.704632],"type":"Point"}
}