{
  "type": "Feature",
  "properties": {
    "iso:country":"DE",
    "sg:address":"Gr\u00fcnberger Str. 71",
    "sg:city":"Rabenau",
    "sg:phone":"+49 6407/8552",
    "sg:postcode":"35466",
    "sg:province":"Hessen",
    "wof:name":"Buchholz Und Seipp",
    "wof:placetype":"venue"
},
  "geometry": {"coordinates":[8.898859,50.641987],"type":"Point"}
}