{
  "type": "Feature",
  "properties": {
    "iso:country":"DE",
    "sg:address":"Hauptstr. 14",
    "sg:city":"Rauenberg",
    "sg:phone":"+49 6222/94160",
    "sg:postcode":"69231",
    "sg:province":"Baden-W\u00fcrttemberg",
    "wof:name":"Rolf Becker Steuerberater",
    "wof:placetype":"venue"
},
  "geometry": {"coordinates":[8.7065029144,49.2666702271],"type":"Point"}
}