{
  "type": "Feature",
  "properties": {
    "iso:country":"DE",
    "sg:address":"Halbergstr. 58",
    "sg:city":"Saarbr\u00fccken",
    "sg:postcode":"66121",
    "sg:province":"Saarland",
    "wof:name":"Klein & Meyer Beteiligungs Gmbh",
    "wof:placetype":"venue"
},
  "geometry": {"coordinates":[7.008024,49.231873],"type":"Point"}
}