{
  "type": "Feature",
  "properties": {
    "iso:country":"DE",
    "sg:address":"Am Steinkreuz 41",
    "sg:city":"L\u00fcnen",
    "sg:phone":"+49 2407/916362",
    "sg:postcode":"44534",
    "sg:province":"Nordrhein-Westfalen",
    "wof:name":"Nahrungserg\u00e4nzung Und Kosmetik Vom Hersteller",
    "wof:placetype":"venue"
},
  "geometry": {"coordinates":[7.48947,51.634289],"type":"Point"}
}