{
  "type": "Feature",
  "properties": {
    "iso:country":"DE",
    "sg:address":"Kleiberstr. 29",
    "sg:city":"Vaterstetten",
    "sg:phone":"+49 8106/899733",
    "sg:postcode":"85591",
    "sg:province":"Bayern",
    "wof:name":"Harald Richter Rechtsanwalt",
    "wof:placetype":"venue"
},
  "geometry": {"coordinates":[11.7658748627,48.1073379517],"type":"Point"}
}