{
  "type": "Feature",
  "properties": {
    "iso:country":"DE",
    "sg:address":"Jettenburger Str. 20",
    "sg:city":"Kusterdingen",
    "sg:phone":"+49 7071/34575",
    "sg:postcode":"72127",
    "sg:province":"Baden-W\u00fcrttemberg",
    "wof:name":"H. Kasch",
    "wof:placetype":"venue"
},
  "geometry": {"coordinates":[9.113816,48.488064],"type":"Point"}
}