{
  "type": "Feature",
  "properties": {
    "iso:country":"DE",
    "sg:address":"D\u00e4nische Str. 2-6",
    "sg:city":"Kiel",
    "sg:phone":"+49 431/98030",
    "sg:postcode":"24103",
    "sg:province":"Schleswig-Holstein",
    "wof:name":"Gerling Firmen- Und Privat- Service Nord Gmbh",
    "wof:placetype":"venue"
},
  "geometry": {"coordinates":[10.1396818161,54.323551178],"type":"Point"}
}