{
  "type": "Feature",
  "properties": {
    "iso:country":"DE",
    "sg:address":"Breite Str. 74",
    "sg:city":"Karlsruhe",
    "sg:phone":"+49 721/815172",
    "sg:postcode":"76135",
    "sg:province":"Baden-W\u00fcrttemberg",
    "wof:name":"Friedrich Sindermann Innenarchitekt",
    "wof:placetype":"venue"
},
  "geometry": {"coordinates":[8.394693,48.993378],"type":"Point"}
}