{
  "type": "Feature",
  "properties": {
    "iso:country":"DE",
    "sg:address":"Bahnhofstr. 9",
    "sg:city":"Gl\u00fccksburg",
    "sg:phone":"+49 4631/2814",
    "sg:postcode":"24960",
    "sg:province":"Schleswig-Holstein",
    "wof:name":"Co Op",
    "wof:placetype":"venue"
},
  "geometry": {"coordinates":[9.5495147705,54.8335189819],"type":"Point"}
}