{
  "type": "Feature",
  "properties": {
    "iso:country":"DE",
    "sg:address":"Hummelsb\u00fctteler Steindamm 89",
    "sg:city":"Norderstedt",
    "sg:phone":"+49 40/5291717",
    "sg:postcode":"22851",
    "sg:province":"Schleswig-Holstein",
    "wof:name":"W. Schramm",
    "wof:placetype":"venue"
},
  "geometry": {"coordinates":[10.0486898422,53.6933708191],"type":"Point"}
}