{
  "type": "Feature",
  "properties": {
    "iso:country":"DE",
    "sg:address":"Kelterstr. 1",
    "sg:city":"Ispringen",
    "sg:phone":"+49 7231/89143",
    "sg:postcode":"75228",
    "sg:province":"Baden-W\u00fcrttemberg",
    "wof:name":"Gert Nikolaus",
    "wof:placetype":"venue"
},
  "geometry": {"coordinates":[8.664377,48.919376],"type":"Point"}
}