{
  "type": "Feature",
  "properties": {
    "iso:country":"DE",
    "sg:address":"P\u00f6nitzer Weg 7",
    "sg:city":"Taucha",
    "sg:phone":"+49 34298/37868",
    "sg:postcode":"04425",
    "sg:province":"Sachsen",
    "wof:name":"Tura Umwelttechnik Recycling Aufbereitung Gmbh",
    "wof:placetype":"venue"
},
  "geometry": {"coordinates":[12.504201889,51.3875274658],"type":"Point"}
}