{
  "type": "Feature",
  "properties": {
    "iso:country":"DE",
    "sg:address":"Hauptstr. 24",
    "sg:city":"Altenmedingen",
    "sg:phone":"+49 5807/456",
    "sg:postcode":"29575",
    "sg:province":"Niedersachsen",
    "wof:name":"Kurt Reh",
    "wof:placetype":"venue"
},
  "geometry": {"coordinates":[10.605203,53.13187],"type":"Point"}
}