{
  "type": "Feature",
  "properties": {
    "iso:country":"DE",
    "sg:address":"Ochsenwerder Norderdeich 116",
    "sg:city":"Hamburg",
    "sg:phone":"+49 40/7373176",
    "sg:postcode":"21037",
    "sg:province":"Hamburg",
    "wof:name":"H. Buschmann",
    "wof:placetype":"venue"
},
  "geometry": {"coordinates":[10.088356,53.452618],"type":"Point"}
}