{
  "type": "Feature",
  "properties": {
    "iso:country":"DE",
    "sg:address":"Sudetenstr. 56",
    "sg:city":"Hochheim",
    "sg:phone":"+49 6146/84000",
    "sg:postcode":"65239",
    "sg:province":"Hessen",
    "wof:name":"K. Umst\u00e4tter Immobilienmakler",
    "wof:placetype":"venue"
},
  "geometry": {"coordinates":[8.3375701904,50.0180587769],"type":"Point"}
}