{
  "type": "Feature",
  "properties": {
    "iso:country":"DE",
    "sg:address":"Seyfferstr. 12",
    "sg:city":"Stuttgart",
    "sg:phone":"+49 711/626348",
    "sg:postcode":"70197",
    "sg:province":"Baden-W\u00fcrttemberg",
    "wof:name":"Marianne Ruhsam Heilpraktikerin",
    "wof:placetype":"venue"
},
  "geometry": {"coordinates":[9.1558160782,48.7686424255],"type":"Point"}
}