{
  "type": "Feature",
  "properties": {
    "iso:country":"DE",
    "sg:address":"J\u00fcterboger Str. 6",
    "sg:city":"Treuenbrietzen",
    "sg:phone":"+49 33748/13127",
    "sg:postcode":"14929",
    "sg:province":"Brandenburg",
    "wof:name":"Chinagarten",
    "wof:placetype":"venue"
},
  "geometry": {"coordinates":[12.8731384277,52.0923423767],"type":"Point"}
}