{
  "type": "Feature",
  "properties": {
    "iso:country":"DE",
    "sg:address":"Taunusstr. 62",
    "sg:city":"Kelkheim",
    "sg:phone":"+49 6195/63797",
    "sg:postcode":"65779",
    "sg:province":"Hessen",
    "wof:name":"Auto-data Fahrzeughandel Ursula Hornung",
    "wof:placetype":"venue"
},
  "geometry": {"coordinates":[8.4279918671,50.1503982544],"type":"Point"}
}