{
  "type": "Feature",
  "properties": {
    "iso:country":"DE",
    "sg:address":"Martin-Luther-Str. 16",
    "sg:city":"Witzenhausen",
    "sg:phone":"+49 5542/910127",
    "sg:postcode":"37218",
    "sg:province":"Hessen",
    "wof:name":"Torsten Schulz G\u00fcternahverkehr",
    "wof:placetype":"venue"
},
  "geometry": {"coordinates":[9.8099107742,51.3780822754],"type":"Point"}
}