{
  "type": "Feature",
  "properties": {
    "iso:country":"DE",
    "sg:address":"Karlsruher Str. 2",
    "sg:city":"Villingen-Schwenningen",
    "sg:phone":"+49 7721/84630",
    "sg:postcode":"78048",
    "sg:province":"Baden-W\u00fcrttemberg",
    "wof:name":"Schulz Und Sluka Rechtsanw\u00e4lte",
    "wof:placetype":"venue"
},
  "geometry": {"coordinates":[8.4563694,48.0694694519],"type":"Point"}
}