{
  "type": "Feature",
  "properties": {
    "iso:country":"DE",
    "sg:address":"Pr\u00fcllstr. 76",
    "sg:city":"Donaustauf",
    "sg:phone":"+49 9403/1378",
    "sg:postcode":"93093",
    "sg:province":"Bayern",
    "wof:name":"Franz Hornauer",
    "wof:placetype":"venue"
},
  "geometry": {"coordinates":[12.198243,49.034653],"type":"Point"}
}