{
  "type": "Feature",
  "properties": {
    "iso:country":"DE",
    "sg:address":"Gau\u00dfstr. 14",
    "sg:city":"Unterf\u00f6hring",
    "sg:postcode":"85774",
    "sg:province":"Bayern",
    "wof:name":"Xaver Schraufnagel Inh. A. Seitz",
    "wof:placetype":"venue"
},
  "geometry": {"coordinates":[11.64371,48.174629],"type":"Point"}
}