{
  "type": "Feature",
  "properties": {
    "iso:country":"DE",
    "sg:address":"Eselbach 99",
    "sg:city":"Schenkenzell",
    "sg:phone":"+49 4978/36346",
    "sg:postcode":"77773",
    "sg:province":"Baden-W\u00fcrttemberg",
    "wof:name":"Huss-holz Gmbh & Co. Kg",
    "wof:placetype":"venue"
},
  "geometry": {"coordinates":[8.3622617722,48.3144226074],"type":"Point"}
}