{
  "type": "Feature",
  "properties": {
    "iso:country":"DE",
    "sg:address":"Budapester Str 39",
    "sg:city":"Berlin",
    "sg:phone":"+49 30/2647010",
    "sg:postcode":"10787",
    "sg:province":"Berlin",
    "wof:name":"Lohndata Gmbh",
    "wof:placetype":"venue"
},
  "geometry": {"coordinates":[13.3402423859,52.5051116943],"type":"Point"}
}