{
  "type": "Feature",
  "properties": {
    "iso:country":"DE",
    "sg:address":"Altenburger Str. 13",
    "sg:city":"Borna",
    "sg:phone":"+49 3433/204350",
    "sg:postcode":"04552",
    "sg:province":"Sachsen",
    "wof:name":"Lotter Metall Gmbh & Co. Kg",
    "wof:placetype":"venue"
},
  "geometry": {"coordinates":[12.49421,51.120083],"type":"Point"}
}