{
  "type": "Feature",
  "properties": {
    "iso:country":"DE",
    "sg:address":"Am Waldrand 1",
    "sg:city":"Neubrandenburg",
    "sg:phone":"+49 395/3684700",
    "sg:postcode":"17033",
    "sg:province":"Mecklenburg-Vorpommern",
    "wof:name":"Schlo\u00dfsicherungen Vertriebs Gmbh",
    "wof:placetype":"venue"
},
  "geometry": {"coordinates":[13.2602720261,53.516330719],"type":"Point"}
}