{
  "type": "Feature",
  "properties": {
    "iso:country":"DE",
    "sg:address":"Gartenstr 2",
    "sg:city":"Philippsburg",
    "sg:phone":"+49 5207/918990",
    "sg:postcode":"76661",
    "sg:province":"Baden-W\u00fcrttemberg",
    "wof:name":"U.s.h. Innovationen Gmbh",
    "wof:placetype":"venue"
},
  "geometry": {"coordinates":[8.5880537033,51.9167671204],"type":"Point"}
}