{
  "type": "Feature",
  "properties": {
    "iso:country":"DE",
    "sg:address":"Gr\u00fcntenstr. 3",
    "sg:city":"Heimertingen",
    "sg:phone":"+49 8335/986111",
    "sg:postcode":"87751",
    "sg:province":"Bayern",
    "wof:name":"W\u00fcpa Inh. Peter W\u00fcrterle E. K.",
    "wof:placetype":"venue"
},
  "geometry": {"coordinates":[10.151035,48.032078],"type":"Point"}
}