{
  "type": "Feature",
  "properties": {
    "iso:country":"DE",
    "sg:address":"Lindenstr. 52",
    "sg:city":"Oyten",
    "sg:phone":"+49 4207/2307",
    "sg:postcode":"28876",
    "sg:province":"Niedersachsen",
    "wof:name":"Johann Esselmann",
    "wof:placetype":"venue"
},
  "geometry": {"coordinates":[9.014826,53.065319],"type":"Point"}
}