{
  "type": "Feature",
  "properties": {
    "iso:country":"DE",
    "sg:address":"Mittelstr. 20",
    "sg:city":"Alpenrod",
    "sg:phone":"+49 2662/3366",
    "sg:postcode":"57642",
    "sg:province":"Rheinland-Pfalz",
    "wof:name":"Horst Hehn",
    "wof:placetype":"venue"
},
  "geometry": {"coordinates":[7.8664531708,50.6317253113],"type":"Point"}
}