{
  "type": "Feature",
  "properties": {
    "iso:country":"DE",
    "sg:address":"Willhoop 3",
    "sg:city":"Hamburg",
    "sg:phone":"+49 40/3033400",
    "sg:postcode":"22453",
    "sg:province":"Hamburg",
    "wof:name":"Mci Worldcom Deutschland Gmbh",
    "wof:placetype":"venue"
},
  "geometry": {"coordinates":[9.9659690857,53.6123962402],"type":"Point"}
}