{
  "type": "Feature",
  "properties": {
    "iso:country":"DE",
    "sg:address":"Gro\u00dfe Brunnenstr. 38",
    "sg:city":"Hamburg",
    "sg:phone":"+49 40/3909523",
    "sg:postcode":"22763",
    "sg:province":"Hamburg",
    "wof:name":"Hecker",
    "wof:placetype":"venue"
},
  "geometry": {"coordinates":[9.925596,53.549099],"type":"Point"}
}