{
  "type": "Feature",
  "properties": {
    "iso:country":"DE",
    "sg:address":"Hoffmannallee 32",
    "sg:city":"Kleve",
    "sg:phone":"+49 2821/23237",
    "sg:postcode":"47533",
    "sg:province":"Nordrhein-Westfalen",
    "wof:name":"Saccaro Raben Drogerie",
    "wof:placetype":"venue"
},
  "geometry": {"coordinates":[6.127931,51.780643],"type":"Point"}
}