{
  "type": "Feature",
  "properties": {
    "iso:country":"DE",
    "sg:address":"Dagobertstr. 6",
    "sg:city":"Siebeldingen",
    "sg:phone":"+49 6345/2956",
    "sg:postcode":"76833",
    "sg:province":"Rheinland-Pfalz",
    "wof:name":"Ev. Pfarramt Siebeldingen",
    "wof:placetype":"venue"
},
  "geometry": {"coordinates":[8.0487556458,49.2117042542],"type":"Point"}
}