{
  "type": "Feature",
  "properties": {
    "iso:country":"DE",
    "sg:address":"K\u00f6penicker Str. 22-29",
    "sg:city":"Berlin",
    "sg:phone":"+49 30/61076634",
    "sg:postcode":"10997",
    "sg:province":"Berlin",
    "wof:name":"D\u00e4mmisol Baustoffe Gmbh",
    "wof:placetype":"venue"
},
  "geometry": {"coordinates":[13.430983,52.506355],"type":"Point"}
}