{
  "type": "Feature",
  "properties": {
    "iso:country":"DE",
    "sg:address":"Kleine Breite 11",
    "sg:city":"Wolfenb\u00fcttel",
    "sg:phone":"+49 5331/72157",
    "sg:postcode":"38302",
    "sg:province":"Niedersachsen",
    "wof:name":"G\u00fcnther Melchert",
    "wof:placetype":"venue"
},
  "geometry": {"coordinates":[10.5431,52.17178],"type":"Point"}
}