{
  "type": "Feature",
  "properties": {
    "iso:country":"DE",
    "sg:address":"Seifenrand 9",
    "sg:city":"Erlabrunn",
    "sg:phone":"+49 37756/7149",
    "sg:postcode":"08349",
    "sg:province":"Sachsen",
    "wof:name":"Fahsel",
    "wof:placetype":"venue"
},
  "geometry": {"coordinates":[12.70755,50.434151],"type":"Point"}
}