{
  "type": "Feature",
  "properties": {
    "iso:country":"DE",
    "sg:address":"Kugelwasen 4",
    "sg:city":"Rohrdorf",
    "sg:phone":"+49 7452/2555",
    "sg:postcode":"72229",
    "sg:province":"Baden-W\u00fcrttemberg",
    "wof:name":"Gottlob B\u00fcxenstein Elektro-install.",
    "wof:placetype":"venue"
},
  "geometry": {"coordinates":[8.692643,48.569691],"type":"Point"}
}