{
  "type": "Feature",
  "properties": {
    "iso:country":"DE",
    "sg:address":"Zehmeplatz 11",
    "sg:city":"Frankfurt",
    "sg:postcode":"15230",
    "sg:province":"Brandenburg",
    "wof:name":"Hbp Treuhand Gmbh",
    "wof:placetype":"venue"
},
  "geometry": {"coordinates":[14.550110817,52.340877533],"type":"Point"}
}