{
  "type": "Feature",
  "properties": {
    "iso:country":"DE",
    "sg:address":"Adalbert-Stifter-Str. 5",
    "sg:city":"Viernheim",
    "sg:phone":"+49 6204/4131",
    "sg:postcode":"68519",
    "sg:province":"Hessen",
    "wof:name":"Werner M\u00fcller Architekt",
    "wof:placetype":"venue"
},
  "geometry": {"coordinates":[8.562705,49.530651],"type":"Point"}
}