{
  "type": "Feature",
  "properties": {
    "iso:country":"DE",
    "sg:address":"Postfach 220",
    "sg:city":"Sigmaringen",
    "sg:phone":"+49 7571/701",
    "sg:postcode":"72481",
    "sg:province":"Baden-W\u00fcrttemberg",
    "wof:name":"F\u00fcrstlich Hohenzollernsche Werke Laucherthal Gmbh & Co.",
    "wof:placetype":"venue"
},
  "geometry": {"coordinates":[9.2176103592,48.0859832764],"type":"Point"}
}