{
  "type": "Feature",
  "properties": {
    "iso:country":"DE",
    "sg:address":"August-Bebel-Str. 15",
    "sg:city":"Neukieritzsch",
    "sg:phone":"+49 34342/51907",
    "sg:postcode":"04575",
    "sg:province":"Sachsen",
    "wof:name":"Dr. Med. Rainer Stumpf",
    "wof:placetype":"venue"
},
  "geometry": {"coordinates":[12.405829,51.15176],"type":"Point"}
}