{
  "type": "Feature",
  "properties": {
    "iso:country":"DE",
    "sg:address":"Goethestr. 40",
    "sg:city":"Stendal",
    "sg:phone":"+49 3931/212010",
    "sg:postcode":"39576",
    "sg:province":"Sachsen-Anhalt",
    "wof:name":"Willi Peters",
    "wof:placetype":"venue"
},
  "geometry": {"coordinates":[11.8533229828,52.5955314636],"type":"Point"}
}