{
  "type": "Feature",
  "properties": {
    "iso:country":"DE",
    "sg:address":"Moselstr. 20",
    "sg:city":"Piesport",
    "sg:phone":"+49 6507/2421",
    "sg:postcode":"54498",
    "sg:province":"Rheinland-Pfalz",
    "wof:name":"Cafe Moselblick Inh. Monika Und Josef Schl\u00f6der",
    "wof:placetype":"venue"
},
  "geometry": {"coordinates":[6.925898,49.870258],"type":"Point"}
}