{
  "type": "Feature",
  "properties": {
    "iso:country":"DE",
    "sg:address":"Vorgebirgsstr. 43",
    "sg:city":"Bonn",
    "sg:phone":"+49 228/7667290",
    "sg:postcode":"53119",
    "sg:province":"Nordrhein-Westfalen",
    "wof:name":"Gkh-gesellschaft Zur Kooperationsf\u00f6rderung",
    "wof:placetype":"venue"
},
  "geometry": {"coordinates":[7.085050106,50.7397499084],"type":"Point"}
}