{
  "type": "Feature",
  "properties": {
    "iso:country":"DE",
    "sg:address":"Morsestr. 11",
    "sg:city":"K\u00f6ln",
    "sg:phone":"+49 221/394657",
    "sg:postcode":"50769",
    "sg:province":"Nordrhein-Westfalen",
    "wof:name":"Arik-beteiligungsges. Mbh",
    "wof:placetype":"venue"
},
  "geometry": {"coordinates":[6.925602,51.037708],"type":"Point"}
}