{
  "type": "Feature",
  "properties": {
    "iso:country":"DE",
    "sg:address":"Boizenburger Str. 3",
    "sg:city":"Bleckede",
    "sg:phone":"+49 5852/390591",
    "sg:postcode":"21354",
    "sg:province":"Niedersachsen",
    "wof:name":"D & V Druck- Und Verlagsgesellschaft Mbh",
    "wof:placetype":"venue"
},
  "geometry": {"coordinates":[10.736459,53.284527],"type":"Point"}
}