{
  "type": "Feature",
  "properties": {
    "iso:country":"DE",
    "sg:address":"Kaiserstr. 163",
    "sg:city":"Friedberg",
    "sg:phone":"+49 6031/92181",
    "sg:postcode":"61169",
    "sg:province":"Hessen",
    "wof:name":"R. Sautier",
    "wof:placetype":"venue"
},
  "geometry": {"coordinates":[8.7517910004,50.3330841064],"type":"Point"}
}