{
  "type": "Feature",
  "properties": {
    "iso:country":"DE",
    "sg:address":"Bismarkstr. 6",
    "sg:city":"Sonneberg",
    "sg:phone":"+49 3675/2048",
    "sg:postcode":"09130",
    "sg:province":"Sachsen",
    "wof:name":"Raiffeisenbank E. G.",
    "wof:placetype":"venue"
},
  "geometry": {"coordinates":[11.164802,50.360493],"type":"Point"}
}