{
  "type": "Feature",
  "properties": {
    "iso:country":"DE",
    "sg:address":"Kleiner Weg 29",
    "sg:city":"Wertheim",
    "sg:phone":"+49 9342/5803",
    "sg:postcode":"97877",
    "sg:province":"Baden-W\u00fcrttemberg",
    "wof:name":"Erwin Kronm\u00fcller",
    "wof:placetype":"venue"
},
  "geometry": {"coordinates":[9.506092,49.781864],"type":"Point"}
}