{
  "type": "Feature",
  "properties": {
    "iso:country":"DE",
    "sg:address":"Mohrstr. 2",
    "sg:city":"G\u00f6ssenheim",
    "sg:phone":"+49 9358/796",
    "sg:postcode":"97780",
    "sg:province":"Bayern",
    "wof:name":"Vereinsgastst\u00e4tte S\u00e4ngerheim",
    "wof:placetype":"venue"
},
  "geometry": {"coordinates":[9.7809896469,50.0197639465],"type":"Point"}
}