{
  "type": "Feature",
  "properties": {
    "iso:country":"DE",
    "sg:address":"Glasewaldtstr. 22",
    "sg:city":"Dresden",
    "sg:phone":"+49 351/318500",
    "sg:postcode":"01277",
    "sg:province":"Sachsen",
    "wof:name":"Dresden Elektronik Ingenieurtechnik Gmbh",
    "wof:placetype":"venue"
},
  "geometry": {"coordinates":[13.802423,51.044888],"type":"Point"}
}