{
  "type": "Feature",
  "properties": {
    "iso:country":"DE",
    "sg:address":"Am Winterrain",
    "sg:city":"Ispringen",
    "sg:phone":"+49 7231/81018",
    "sg:postcode":"75228",
    "sg:province":"Baden-W\u00fcrttemberg",
    "wof:name":"Waldeck",
    "wof:placetype":"venue"
},
  "geometry": {"coordinates":[8.6607055664,48.918422699],"type":"Point"}
}