{
  "type": "Feature",
  "properties": {
    "iso:country":"DE",
    "sg:address":"Hardtring 8",
    "sg:city":"Stockach",
    "sg:phone":"+49 7771/8090",
    "sg:postcode":"78333",
    "sg:province":"Baden-W\u00fcrttemberg",
    "wof:name":"Eto Beteiligungsges. Mbh",
    "wof:placetype":"venue"
},
  "geometry": {"coordinates":[8.971273,47.837734],"type":"Point"}
}