{
  "type": "Feature",
  "properties": {
    "iso:country":"DE",
    "sg:address":"Auf der Worth 9",
    "sg:city":"Zeven",
    "sg:postcode":"27404",
    "sg:province":"Niedersachsen",
    "wof:name":"Aldi Gmbh & Co. Kg",
    "wof:placetype":"venue"
},
  "geometry": {"coordinates":[9.2796802521,53.2957649231],"type":"Point"}
}