{
  "type": "Feature",
  "properties": {
    "iso:country":"DE",
    "sg:address":"M\u00fcnchnerstr. 64 a",
    "sg:city":"Unterf\u00f6hring",
    "sg:phone":"+49 89/9505882",
    "sg:postcode":"85774",
    "sg:province":"Bayern",
    "wof:name":"Vaitl Verwaltungs- Und Beteiligungsgesellschaft Mbh",
    "wof:placetype":"venue"
},
  "geometry": {"coordinates":[11.639838,48.190895],"type":"Point"}
}