{
  "type": "Feature",
  "properties": {
    "iso:country":"DE",
    "sg:address":"Utenbacher Str. 17",
    "sg:city":"Apolda",
    "sg:postcode":"99510",
    "sg:province":"Th\u00fcringen",
    "wof:name":"Druck U. Verlag Intermedia Kg",
    "wof:placetype":"venue"
},
  "geometry": {"coordinates":[11.521309,51.02375],"type":"Point"}
}