{
  "type": "Feature",
  "properties": {
    "iso:country":"DE",
    "sg:address":"Volkeningstr. 22",
    "sg:city":"H\u00fcllhorst",
    "sg:phone":"+49 5744/2209",
    "sg:postcode":"32609",
    "sg:province":"Nordrhein-Westfalen",
    "wof:name":"Funke Gmbh",
    "wof:placetype":"venue"
},
  "geometry": {"coordinates":[8.7052516937,52.272026062],"type":"Point"}
}