{
  "type": "Feature",
  "properties": {
    "iso:country":"DE",
    "sg:address":"Finkenwerder Norderdeich 133",
    "sg:city":"Hamburg",
    "sg:phone":"+49 40/7429999",
    "sg:postcode":"21129",
    "sg:province":"Hamburg",
    "wof:name":"Luzemann Gmbh",
    "wof:placetype":"venue"
},
  "geometry": {"coordinates":[9.84973526,53.5191230774],"type":"Point"}
}