{
  "type": "Feature",
  "properties": {
    "iso:country":"DE",
    "sg:address":"Dorfstr.",
    "sg:city":"M\u00f6llenhagen",
    "sg:phone":"+49 39928/5912",
    "sg:postcode":"17219",
    "sg:province":"Mecklenburg-Vorpommern",
    "wof:name":"R. Schulz",
    "wof:placetype":"venue"
},
  "geometry": {"coordinates":[12.932299614,53.5285263062],"type":"Point"}
}