{
  "type": "Feature",
  "properties": {
    "iso:country":"DE",
    "sg:address":"Kolpingstr. 5",
    "sg:city":"Hirschberg",
    "sg:postcode":"69493",
    "sg:province":"Baden-W\u00fcrttemberg",
    "wof:name":"Allwo Bautr\u00e4ger- Und Projektierungs Gmbh",
    "wof:placetype":"venue"
},
  "geometry": {"coordinates":[8.658631,49.496574],"type":"Point"}
}