{
  "type": "Feature",
  "properties": {
    "iso:country":"DE",
    "sg:address":"Arnoldstr. 16",
    "sg:city":"D\u00fcsseldorf",
    "sg:phone":"+49 211/4910211",
    "sg:postcode":"40479",
    "sg:province":"Nordrhein-Westfalen",
    "wof:name":"Klaus Breitinger Architekt",
    "wof:placetype":"venue"
},
  "geometry": {"coordinates":[6.776893,51.233826],"type":"Point"}
}