{
  "type": "Feature",
  "properties": {
    "iso:country":"DE",
    "sg:address":"T\u00e4nzelfestweg 7",
    "sg:city":"Kaufbeuren",
    "sg:phone":"+49 8341/3679",
    "sg:postcode":"87600",
    "sg:province":"Bayern",
    "wof:name":"Immobilien Karl Flick Inh. Gabriele Seibold",
    "wof:placetype":"venue"
},
  "geometry": {"coordinates":[10.6268520355,47.8821372986],"type":"Point"}
}