{
  "type": "Feature",
  "properties": {
    "iso:country":"DE",
    "sg:address":"Neuenh\u00f6he 31",
    "sg:city":"Wermelskirchen",
    "sg:phone":"+49 4921/9672240",
    "sg:postcode":"42929",
    "sg:province":"Nordrhein-Westfalen",
    "wof:name":"Friedrich Wilh Betz Gmbh",
    "wof:placetype":"venue"
},
  "geometry": {"coordinates":[7.238887,51.146488],"type":"Point"}
}