{
  "type": "Feature",
  "properties": {
    "iso:country":"DE",
    "sg:address":"Rathausplatz 1",
    "sg:city":"Schmitten",
    "sg:phone":"+49 6084/582",
    "sg:postcode":"61389",
    "sg:province":"Hessen",
    "wof:name":"Museum Im Alten Rathaus",
    "wof:placetype":"venue"
},
  "geometry": {"coordinates":[8.453298,50.260662],"type":"Point"}
}