{
  "type": "Feature",
  "properties": {
    "iso:country":"DE",
    "sg:address":"Eberle-K\u00f6gl-Str. 17",
    "sg:city":"Marktoberdorf",
    "sg:phone":"+49 8342/40926",
    "sg:postcode":"87616",
    "sg:province":"Bayern",
    "wof:name":"J. Niederauer",
    "wof:placetype":"venue"
},
  "geometry": {"coordinates":[10.6212654114,47.7782821655],"type":"Point"}
}