{
  "type": "Feature",
  "properties": {
    "iso:country":"DE",
    "sg:address":"Porschestr. 21",
    "sg:city":"Kaufbeuren",
    "sg:phone":"+49 8341/12787",
    "sg:postcode":"87600",
    "sg:province":"Bayern",
    "wof:name":"Martin Kaufmann",
    "wof:placetype":"venue"
},
  "geometry": {"coordinates":[10.639547,47.893551],"type":"Point"}
}