{
  "type": "Feature",
  "properties": {
    "iso:country":"DE",
    "sg:address":"Raiffeisenstr. 8",
    "sg:city":"L\u00f6bnitz",
    "sg:phone":"+49 34208/72421",
    "sg:postcode":"04509",
    "sg:province":"Sachsen",
    "wof:name":"Fred-bernd Melitz",
    "wof:placetype":"venue"
},
  "geometry": {"coordinates":[12.467433,51.589226],"type":"Point"}
}