{
  "type": "Feature",
  "properties": {
    "iso:country":"DE",
    "sg:address":"Im Fichtenwald 33",
    "sg:city":"Neunkirchen",
    "sg:phone":"+49 6821/32062",
    "sg:postcode":"66539",
    "sg:province":"Saarland",
    "wof:name":"Hermann J. Rhein",
    "wof:placetype":"venue"
},
  "geometry": {"coordinates":[7.2288379669,49.3206710815],"type":"Point"}
}