{
  "type": "Feature",
  "properties": {
    "iso:country":"DE",
    "sg:address":"Arnsdorfer Str. 1",
    "sg:city":"Obergurig",
    "sg:phone":"+49 35938/9556",
    "sg:postcode":"02692",
    "sg:province":"Sachsen",
    "wof:name":"Arnfried Sch\u00fcr",
    "wof:placetype":"venue"
},
  "geometry": {"coordinates":[14.387732,51.129883],"type":"Point"}
}