{
  "type": "Feature",
  "properties": {
    "iso:country":"DE",
    "sg:address":"Stra\u00dfe des Friedens 56",
    "sg:city":"Osterburg",
    "sg:phone":"+49 3937/899999",
    "sg:postcode":"39606",
    "sg:province":"Sachsen-Anhalt",
    "wof:name":"Thorsten Schulz",
    "wof:placetype":"venue"
},
  "geometry": {"coordinates":[11.75427,52.786968],"type":"Point"}
}