{
  "type": "Feature",
  "properties": {
    "iso:country":"DE",
    "sg:address":"Fuhlsb\u00fcttler Str. 269",
    "sg:city":"Hamburg",
    "sg:phone":"+49 40/6928770",
    "sg:postcode":"22307",
    "sg:province":"Hamburg",
    "wof:name":"Graeber-r\u00e4der",
    "wof:placetype":"venue"
},
  "geometry": {"coordinates":[10.042166,53.597839],"type":"Point"}
}