{
  "type": "Feature",
  "properties": {
    "iso:country":"DE",
    "sg:address":"Z\u00e4hringerstr. 14",
    "sg:city":"H\u00fcfingen",
    "sg:phone":"+49 771/63108",
    "sg:postcode":"78183",
    "sg:province":"Baden-W\u00fcrttemberg",
    "wof:name":"A. Gut Mech. Werkstatt",
    "wof:placetype":"venue"
},
  "geometry": {"coordinates":[8.552261,47.891941],"type":"Point"}
}