{
  "type": "Feature",
  "properties": {
    "iso:country":"DE",
    "sg:address":"Dorotheenstr. 18",
    "sg:city":"Dresden",
    "sg:phone":"+49 351/2844587",
    "sg:postcode":"01219",
    "sg:province":"Sachsen",
    "wof:name":"Ingenieurges. System Car Gbr Prof. Uhlmann",
    "wof:placetype":"venue"
},
  "geometry": {"coordinates":[13.7706756592,51.0237007141],"type":"Point"}
}