{
  "type": "Feature",
  "properties": {
    "iso:country":"DE",
    "sg:address":"Rochlitzer Str. 62",
    "sg:city":"Mittweida",
    "sg:postcode":"09648",
    "sg:province":"Sachsen",
    "wof:name":"Raumfahrt Museum",
    "wof:placetype":"venue"
},
  "geometry": {"coordinates":[12.976201,50.986523],"type":"Point"}
}