{
  "type": "Feature",
  "properties": {
    "iso:country":"DE",
    "sg:address":"Lauchst\u00e4dter Str. 6",
    "sg:city":"Angersdorf",
    "sg:phone":"+49 345/613520",
    "sg:postcode":"06179",
    "sg:province":"Sachsen-Anhalt",
    "wof:name":"Praktiker Bau- Und Heimwerkermarkt",
    "wof:placetype":"venue"
},
  "geometry": {"coordinates":[11.9091873169,51.4611740112],"type":"Point"}
}