{
  "type": "Feature",
  "properties": {
    "iso:country":"DE",
    "sg:address":"Marktplatz 2",
    "sg:city":"Gudensberg",
    "sg:phone":"+49 5603/2060",
    "sg:postcode":"34281",
    "sg:province":"Hessen",
    "wof:name":"H\u00f6hmann Und Deuker Rechtsanw\u00e4lte",
    "wof:placetype":"venue"
},
  "geometry": {"coordinates":[9.3652334213,51.1781234741],"type":"Point"}
}