{
  "type": "Feature",
  "properties": {
    "iso:country":"DE",
    "sg:address":"Rintheimer Querallee 4",
    "sg:city":"Karlsruhe",
    "sg:phone":"+49 721/69031",
    "sg:postcode":"76131",
    "sg:province":"Baden-W\u00fcrttemberg",
    "wof:name":"Bundesanstalt F. Flugsicherung",
    "wof:placetype":"venue"
},
  "geometry": {"coordinates":[8.429261,49.023502],"type":"Point"}
}