{
  "type": "Feature",
  "properties": {
    "iso:country":"DE",
    "sg:address":"Adam-Opel-Str 15",
    "sg:city":"Bremen",
    "sg:phone":"+49 421/694600",
    "sg:postcode":"28237",
    "sg:province":"Bremen",
    "wof:name":"Soller Multiservice Gmbh & Co Kg",
    "wof:placetype":"venue"
},
  "geometry": {"coordinates":[8.703647,53.141911],"type":"Point"}
}