{
  "type": "Feature",
  "properties": {
    "iso:country":"DE",
    "sg:address":"Brunnenstr. 12",
    "sg:city":"Niedernhausen",
    "sg:phone":"+49 6127/1822",
    "sg:postcode":"65527",
    "sg:province":"Hessen",
    "wof:name":"Petra Prager-petri Architektin",
    "wof:placetype":"venue"
},
  "geometry": {"coordinates":[8.303481,50.162506],"type":"Point"}
}