{
  "type": "Feature",
  "properties": {
    "iso:country":"DE",
    "sg:address":"Ostpreu\u00dfendamm 65",
    "sg:city":"Berlin",
    "sg:phone":"+49 30/7122008",
    "sg:postcode":"12207",
    "sg:province":"Berlin",
    "wof:name":"Moltke-apotheke",
    "wof:placetype":"venue"
},
  "geometry": {"coordinates":[13.310256,52.421234],"type":"Point"}
}