{
  "type": "Feature",
  "properties": {
    "iso:country":"DE",
    "sg:address":"Pfingstreiterstr. 16",
    "sg:city":"K\u00f6tzting",
    "sg:phone":"+49 9941/1545",
    "sg:postcode":"93444",
    "sg:province":"Bayern",
    "wof:name":"Weigl Konserven Verwaltungs Gmbh",
    "wof:placetype":"venue"
},
  "geometry": {"coordinates":[12.86141,49.172901],"type":"Point"}
}