{
  "type": "Feature",
  "properties": {
    "iso:country":"DE",
    "sg:address":"Theaterstr. 11",
    "sg:city":"W\u00fcrzburg",
    "sg:phone":"+49 931/53685",
    "sg:postcode":"97070",
    "sg:province":"Bayern",
    "wof:name":"Dr. Roland Und Christiane Volk Rechtsanw\u00e4lte",
    "wof:placetype":"venue"
},
  "geometry": {"coordinates":[9.9345569611,49.7965393066],"type":"Point"}
}