{
  "type": "Feature",
  "properties": {
    "iso:country":"DE",
    "sg:address":"Ahornweg 10",
    "sg:city":"Uttenreuth",
    "sg:phone":"+49 9134/1740",
    "sg:postcode":"91080",
    "sg:province":"Bayern",
    "wof:name":"Wolfgang Bader Architekt",
    "wof:placetype":"venue"
},
  "geometry": {"coordinates":[11.100892,49.595249],"type":"Point"}
}