{
  "type": "Feature",
  "properties": {
    "iso:country":"DE",
    "sg:address":"Letznerstr. 8",
    "sg:city":"Einbeck",
    "sg:phone":"+49 5554/1859",
    "sg:postcode":"37574",
    "sg:province":"Niedersachsen",
    "wof:name":"Walter Rische",
    "wof:placetype":"venue"
},
  "geometry": {"coordinates":[9.882582,51.740036],"type":"Point"}
}