{
  "type": "Feature",
  "properties": {
    "iso:country":"DE",
    "sg:address":"Otto-Hahn-Str. 3",
    "sg:city":"Barnstorf",
    "sg:phone":"+49 5442/98750",
    "sg:postcode":"49406",
    "sg:province":"Niedersachsen",
    "wof:name":"Fh Pumpentechnik Gmbh",
    "wof:placetype":"venue"
},
  "geometry": {"coordinates":[8.495804,52.700481],"type":"Point"}
}