{
  "type": "Feature",
  "properties": {
    "iso:country":"DE",
    "sg:address":"Klausenerstr 6",
    "sg:city":"Recklinghausen",
    "sg:phone":"+49 2361/42063",
    "sg:postcode":"45665",
    "sg:province":"Nordrhein-Westfalen",
    "wof:name":"Ibh Ingenieurb\u00fcro Hachmann & Partner Gbr",
    "wof:placetype":"venue"
},
  "geometry": {"coordinates":[7.2165088654,51.6165733337],"type":"Point"}
}