{
  "type": "Feature",
  "properties": {
    "iso:country":"DE",
    "sg:address":"Dalbergstr. 5",
    "sg:city":"Frankfurt",
    "sg:phone":"+49 69/313512",
    "sg:postcode":"65929",
    "sg:province":"Hessen",
    "wof:name":"Elektro-radio Germann Kg",
    "wof:placetype":"venue"
},
  "geometry": {"coordinates":[8.5448312759,50.102016449],"type":"Point"}
}