{
  "type": "Feature",
  "properties": {
    "iso:country":"DE",
    "sg:address":"R\u00fcterweg 69",
    "sg:city":"Herford",
    "sg:phone":"+49 5221/31490",
    "sg:postcode":"32051",
    "sg:province":"Nordrhein-Westfalen",
    "wof:name":"Paul-gerhard Dahlmeier Architekt",
    "wof:placetype":"venue"
},
  "geometry": {"coordinates":[8.61406,52.124142],"type":"Point"}
}