{"geometry":{"type":"Point","coordinates":[7.781208,53.575447]},"type":"Feature","id":102560531,"bbox":[7.781208,53.575447,7.781208,53.575447],"properties":{"sg:province":"Niedersachsen","geom:longitude":7.781208,"wof:breaches":[],"sg:href":"http://api.simplegeo.com/1.0/features/SG_6DQAxqfO4Bo2XrLVim6KQU_53.575447_7.781208@1306268793.json","sg:owner":"simplegeo","sg:postcode":"26409","geom:latitude":53.575447,"sg:classifiers":[],"sg:address":"Drostenstr. 1::","sg:phone":"+49 4944/629140","wof:hierarchy":[{"locality_id":101806513,"venue_id":102560531,"country_id":85633111,"region_id":85682555,"county_id":102064049}],"geom:area":0.000000,"sg:city":"Wittmund","wof:lastmodified":1438093279,"iso:country":"DE","wof:geomhash":"53129948a4f1f232974239571bd4dffc","wof:name":"Raiffeisen-volksbank Aurich-wittmund Eg","wof:belongsto":[101806513,85633111,85682555,102064049],"src:geom":"simplegeo","wof:placetype":"venue","wof:supersedes":[],"wof:id":102560531,"wof:superseded_by":[],"wof:concordances":{"sg:id":"SG_6DQAxqfO4Bo2XrLVim6KQU_53.575447_7.781208@1306268793"},"wof:parent_id":101806513}}