{
  "type": "Feature",
  "properties": {
    "iso:country":"DE",
    "sg:address":"Saargem\u00fcnder Str. 189",
    "sg:city":"Saarbr\u00fccken",
    "sg:phone":"+49 681/871618",
    "sg:postcode":"66130",
    "sg:province":"Saarland",
    "wof:name":"Edith Staude",
    "wof:placetype":"venue"
},
  "geometry": {"coordinates":[7.02921,49.198978],"type":"Point"}
}