{
  "type": "Feature",
  "properties": {
    "iso:country":"DE",
    "sg:address":"S\u00f6mmeringstr. 19",
    "sg:city":"K\u00f6ln",
    "sg:phone":"+49 221/514971",
    "sg:postcode":"50823",
    "sg:province":"Nordrhein-Westfalen",
    "wof:name":"Fethi Karaca",
    "wof:placetype":"venue"
},
  "geometry": {"coordinates":[6.9172501564,50.9488639832],"type":"Point"}
}