{
  "type": "Feature",
  "properties": {
    "iso:country":"DE",
    "sg:address":"Schweinfurter Str. 133",
    "sg:city":"Niederwerrn",
    "sg:phone":"+49 9721/48136",
    "sg:postcode":"97464",
    "sg:province":"Bayern",
    "wof:name":"Imbi\u00df Da Nino",
    "wof:placetype":"venue"
},
  "geometry": {"coordinates":[10.1891031265,50.0584754944],"type":"Point"}
}