{
  "type": "Feature",
  "properties": {
    "iso:country":"DE",
    "sg:address":"Glanzstr. 2",
    "sg:city":"Berlin",
    "sg:phone":"+49 30/53219321",
    "sg:postcode":"12437",
    "sg:province":"Berlin",
    "wof:name":"Karin Radloff",
    "wof:placetype":"venue"
},
  "geometry": {"coordinates":[13.4904079437,52.4676208496],"type":"Point"}
}