{
  "type": "Feature",
  "properties": {
    "iso:country":"DE",
    "sg:address":"Andresenstra\u00dfe 1a",
    "sg:city":"Wolfen",
    "sg:phone":"+49 3494/638300",
    "sg:postcode":"06766",
    "sg:province":"Sachsen-Anhalt",
    "wof:name":"Tgz Technologie- Und Gr\u00fcnderzentrum Bitterfeld-wolfen Gmbh",
    "wof:placetype":"venue"
},
  "geometry": {"coordinates":[12.2533950806,51.6589813232],"type":"Point"}
}