{
  "type": "Feature",
  "properties": {
    "iso:country":"DE",
    "sg:address":"Dorfgarten 8",
    "sg:city":"Driedorf",
    "sg:phone":"+49 2775/445",
    "sg:postcode":"35759",
    "sg:province":"Hessen",
    "wof:name":"Herbert Platte Gmbh Metallverarbeitung",
    "wof:placetype":"venue"
},
  "geometry": {"coordinates":[8.1370401382,50.640460968],"type":"Point"}
}