{
  "type": "Feature",
  "properties": {
    "iso:country":"DE",
    "sg:address":"Fallstr. 27",
    "sg:city":"Rees",
    "sg:phone":"+49 2851/1210",
    "sg:postcode":"46459",
    "sg:province":"Nordrhein-Westfalen",
    "wof:name":"Kirsten Moser Ohg",
    "wof:placetype":"venue"
},
  "geometry": {"coordinates":[6.398706,51.759163],"type":"Point"}
}