{
  "type": "Feature",
  "properties": {
    "iso:country":"DE",
    "sg:address":"Am Kirschgarten 2",
    "sg:city":"Ro\u00dftal",
    "sg:phone":"+49 9127/7452",
    "sg:postcode":"90574",
    "sg:province":"Bayern",
    "wof:name":"Leonhard Weber",
    "wof:placetype":"venue"
},
  "geometry": {"coordinates":[10.912113,49.380402],"type":"Point"}
}