{
  "type": "Feature",
  "properties": {
    "iso:country":"DE",
    "sg:address":"Leipziger Str. 3",
    "sg:city":"F\u00fcrstenau",
    "sg:phone":"+49 5901/2729",
    "sg:postcode":"49584",
    "sg:province":"Niedersachsen",
    "wof:name":"Kolpingfamilie F\u00fcrstenau F. Gerweler",
    "wof:placetype":"venue"
},
  "geometry": {"coordinates":[7.6843299866,52.5184707642],"type":"Point"}
}