{
  "type": "Feature",
  "properties": {
    "iso:country":"DE",
    "sg:address":"Am Ueckerdamm",
    "sg:city":"Ueckerm\u00fcnde",
    "sg:phone":"+49 39771/22630",
    "sg:postcode":"17373",
    "sg:province":"Mecklenburg-Vorpommern",
    "wof:name":"Fischereigenossenschaft Haffk\u00fcste Eg",
    "wof:placetype":"venue"
},
  "geometry": {"coordinates":[14.0482397079,53.7378807068],"type":"Point"}
}