{
  "type": "Feature",
  "properties": {
    "iso:country":"DE",
    "sg:address":"Agricolastr. 26",
    "sg:city":"Berlin",
    "sg:phone":"+49 30/39100320",
    "sg:postcode":"10555",
    "sg:province":"Berlin",
    "wof:name":"Gebra Ges. F\u00fcr Bau Und Raumakustik Mbh",
    "wof:placetype":"venue"
},
  "geometry": {"coordinates":[13.333281,52.520489],"type":"Point"}
}