{
  "type": "Feature",
  "properties": {
    "iso:country":"DE",
    "sg:address":"An der Westspange 1",
    "sg:city":"Gelnhausen",
    "sg:postcode":"63571",
    "sg:province":"Hessen",
    "wof:name":"Goy & Lehnert Fast Food Gmbh",
    "wof:placetype":"venue"
},
  "geometry": {"coordinates":[9.1790246964,50.1896400452],"type":"Point"}
}