{
  "type": "Feature",
  "properties": {
    "iso:country":"DE",
    "sg:address":"Franzh\u00e4uschenstr. 10",
    "sg:city":"Lohmar",
    "sg:phone":"+49 2241/383655",
    "sg:postcode":"53797",
    "sg:province":"Nordrhein-Westfalen",
    "wof:name":"C. Rosauer",
    "wof:placetype":"venue"
},
  "geometry": {"coordinates":[7.2651281357,50.826335907],"type":"Point"}
}