{
  "type": "Feature",
  "properties": {
    "iso:country":"DE",
    "sg:address":"Rheinstr. 23",
    "sg:city":"Horhausen",
    "sg:phone":"+49 2687/921546",
    "sg:postcode":"56593",
    "sg:province":"Rheinland-Pfalz",
    "wof:name":"D. Ecker",
    "wof:placetype":"venue"
},
  "geometry": {"coordinates":[7.504065,50.580383],"type":"Point"}
}