{
  "type": "Feature",
  "properties": {
    "iso:country":"DE",
    "sg:address":"Hamalandstr. 111",
    "sg:city":"Bocholt",
    "sg:phone":"+49 2871/21980",
    "sg:postcode":"46399",
    "sg:province":"Nordrhein-Westfalen",
    "wof:name":"Dibella Gmbh",
    "wof:placetype":"venue"
},
  "geometry": {"coordinates":[6.5858621597,51.8899536133],"type":"Point"}
}