{
  "type": "Feature",
  "properties": {
    "iso:country":"DE",
    "sg:address":"Talstr. 1",
    "sg:city":"Todtmoos",
    "sg:phone":"+49 7674/1222",
    "sg:postcode":"79682",
    "sg:province":"Baden-W\u00fcrttemberg",
    "wof:name":"H. Schmid",
    "wof:placetype":"venue"
},
  "geometry": {"coordinates":[7.99894,47.720329],"type":"Point"}
}