{
  "type": "Feature",
  "properties": {
    "iso:country":"DE",
    "sg:address":"K\u00f6lnstr. 109",
    "sg:city":"D\u00fcren",
    "sg:phone":"+49 2421/13984",
    "sg:postcode":"52351",
    "sg:province":"Nordrhein-Westfalen",
    "wof:name":"Haarhaus Wahlen",
    "wof:placetype":"venue"
},
  "geometry": {"coordinates":[6.4923567772,50.8050231934],"type":"Point"}
}