{
  "type": "Feature",
  "properties": {
    "iso:country":"DE",
    "sg:address":"Gartenstr. 7",
    "sg:city":"Kuhardt",
    "sg:phone":"+49 7272/2491",
    "sg:postcode":"76773",
    "sg:province":"Rheinland-Pfalz",
    "wof:name":"Rudolf Geiger",
    "wof:placetype":"venue"
},
  "geometry": {"coordinates":[8.312711,49.145294],"type":"Point"}
}