{
  "type": "Feature",
  "properties": {
    "iso:country":"DE",
    "sg:address":"Me\u00dfkircher Str. 3",
    "sg:city":"Leibertingen",
    "sg:phone":"+49 7570/474",
    "sg:postcode":"88637",
    "sg:province":"Baden-W\u00fcrttemberg",
    "wof:name":"Janzen-reisen Gmbh",
    "wof:placetype":"venue"
},
  "geometry": {"coordinates":[9.0539541245,48.0534248352],"type":"Point"}
}