{
  "type": "Feature",
  "properties": {
    "iso:country":"DE",
    "sg:address":"Am Wohnheim 2",
    "sg:city":"Dresden",
    "sg:phone":"+49 351/3161769",
    "sg:postcode":"01307",
    "sg:province":"Sachsen",
    "wof:name":"La Nonna",
    "wof:placetype":"venue"
},
  "geometry": {"coordinates":[13.7716798782,51.0524101257],"type":"Point"}
}