{
  "type": "Feature",
  "properties": {
    "iso:country":"DE",
    "sg:address":"Hauptstr. 69",
    "sg:city":"Hahnbach",
    "sg:phone":"+49 9664/252",
    "sg:postcode":"92256",
    "sg:province":"Bayern",
    "wof:name":"Emil Winkler",
    "wof:placetype":"venue"
},
  "geometry": {"coordinates":[11.8035783768,49.5342330933],"type":"Point"}
}