{
  "type": "Feature",
  "properties": {
    "iso:country":"DE",
    "sg:address":"mathias brueggen str. 4a",
    "sg:city":"koeln",
    "sg:phone":"+49 221/9561383",
    "sg:postcode":"50827",
    "sg:province":"Nordrhein-Westfalen",
    "wof:name":"Industrie Und Schiffs Motoren",
    "wof:placetype":"venue"
},
  "geometry": {"coordinates":[6.889191,50.964893],"type":"Point"}
}