{
  "type": "Feature",
  "properties": {
    "iso:country":"DE",
    "sg:address":"Johannisstr 22",
    "sg:city":"M\u00fchlhausen",
    "sg:phone":"+49 36018/13266",
    "sg:postcode":"99974",
    "sg:province":"Th\u00fcringen",
    "wof:name":"W\u00e4rme- Und Klimatechnik M\u00fchlhausen Gmbh",
    "wof:placetype":"venue"
},
  "geometry": {"coordinates":[10.4566164017,51.2364654541],"type":"Point"}
}