{
  "type": "Feature",
  "properties": {
    "iso:country":"DE",
    "sg:address":"Hochstr. 12",
    "sg:city":"B\u00f6r\u00dfum",
    "sg:phone":"+49 5341/268951",
    "sg:postcode":"38312",
    "sg:province":"Niedersachsen",
    "wof:name":"I. K\u00f6chy",
    "wof:placetype":"venue"
},
  "geometry": {"coordinates":[10.597421,52.087639],"type":"Point"}
}