{
  "type": "Feature",
  "properties": {
    "iso:country":"DE",
    "sg:address":"67487",
    "sg:city":"Maikammer",
    "sg:phone":"+49 6321/58634",
    "sg:postcode":"67487",
    "sg:province":"Rheinland-Pfalz",
    "wof:name":"Gastst\u00e4tte Sch\u00fctzenhaus",
    "wof:placetype":"venue"
},
  "geometry": {"coordinates":[8.0623598099,49.3045692444],"type":"Point"}
}