{
  "type": "Feature",
  "properties": {
    "iso:country":"DE",
    "sg:address":"Bruchsaler Str. 30",
    "sg:city":"Graben-Neudorf",
    "sg:postcode":"76676",
    "sg:province":"Baden-W\u00fcrttemberg",
    "wof:name":"Raum Computer Ag",
    "wof:placetype":"venue"
},
  "geometry": {"coordinates":[8.498096,49.171684],"type":"Point"}
}