{
  "type": "Feature",
  "properties": {
    "iso:country":"DE",
    "sg:address":"Asdorfer M\u00fchle 12-24",
    "sg:city":"Freudenberg",
    "sg:phone":"+49 2734/6501",
    "sg:postcode":"57258",
    "sg:province":"Nordrhein-Westfalen",
    "wof:name":"Karl Klos Flanschenfabrik Gmbh & Co. Kg",
    "wof:placetype":"venue"
},
  "geometry": {"coordinates":[7.873295784,50.8764801025],"type":"Point"}
}