{
  "type": "Feature",
  "properties": {
    "iso:country":"DE",
    "sg:address":"Neue Str. 22",
    "sg:city":"Ulm",
    "sg:phone":"+49 731/14480",
    "sg:postcode":"89073",
    "sg:province":"Baden-W\u00fcrttemberg",
    "wof:name":"Alcatel Sel Ag",
    "wof:placetype":"venue"
},
  "geometry": {"coordinates":[9.9855632782,48.3967666626],"type":"Point"}
}