{
  "type": "Feature",
  "properties": {
    "iso:country":"DE",
    "sg:address":"In den H\u00f6fen 3",
    "sg:city":"Melle",
    "sg:phone":"+49 5427/1740",
    "sg:postcode":"49328",
    "sg:province":"Niedersachsen",
    "wof:name":"H.-d. Benz Gmbh",
    "wof:placetype":"venue"
},
  "geometry": {"coordinates":[8.4304189682,52.2481956482],"type":"Point"}
}