{
  "type": "Feature",
  "properties": {
    "iso:country":"DE",
    "sg:address":"Bohmsiel 8",
    "sg:city":"Bremerhaven",
    "sg:phone":"+49 471/74400",
    "sg:postcode":"27572",
    "sg:province":"Bremen",
    "wof:name":"Terminus Gmbh",
    "wof:placetype":"venue"
},
  "geometry": {"coordinates":[8.6001844406,53.4921569824],"type":"Point"}
}