{
  "type": "Feature",
  "properties": {
    "iso:country":"DE",
    "sg:address":"Wurbiser Str. 2",
    "sg:city":"Crostau",
    "sg:phone":"+49 3592/2345",
    "sg:postcode":"02681",
    "sg:province":"Sachsen",
    "wof:name":"Weiterbildungsakademie F\u00fcr F\u00fchrungskr\u00e4fte Der Wirtschaft",
    "wof:placetype":"venue"
},
  "geometry": {"coordinates":[14.4521465302,51.0823135376],"type":"Point"}
}