{
  "type": "Feature",
  "properties": {
    "iso:country":"DE",
    "sg:address":"Gabelsbergerstr. 14",
    "sg:city":"Regensburg",
    "sg:phone":"+49 941/793276",
    "sg:postcode":"93047",
    "sg:province":"Bayern",
    "wof:name":"Osteria D Amore",
    "wof:placetype":"venue"
},
  "geometry": {"coordinates":[12.1066188812,49.0153656006],"type":"Point"}
}