{
  "type": "Feature",
  "properties": {
    "iso:country":"DE",
    "sg:address":"Gierbachstr. 39",
    "sg:city":"Schotten",
    "sg:phone":"+49 6044/8430",
    "sg:postcode":"63679",
    "sg:province":"Hessen",
    "wof:name":"Karl-f. Seibert Markthandlung",
    "wof:placetype":"venue"
},
  "geometry": {"coordinates":[9.1421861649,50.5205039978],"type":"Point"}
}