{
  "type": "Feature",
  "properties": {
    "iso:country":"DE",
    "sg:address":"Wesselinger Str. 23",
    "sg:city":"Br\u00fchl",
    "sg:phone":"+49 2232/42475",
    "sg:postcode":"50321",
    "sg:province":"Nordrhein-Westfalen",
    "wof:name":"K. H. Dyga Metallbau",
    "wof:placetype":"venue"
},
  "geometry": {"coordinates":[6.924478,50.83337],"type":"Point"}
}