{
  "type": "Feature",
  "properties": {
    "iso:country":"DE",
    "sg:address":"Steinkulle 3",
    "sg:city":"Haan",
    "sg:phone":"+49 212/993150",
    "sg:postcode":"42781",
    "sg:province":"Nordrhein-Westfalen",
    "wof:name":"H\u00e4gglunds Drives Gmbh",
    "wof:placetype":"venue"
},
  "geometry": {"coordinates":[6.994701,51.184872],"type":"Point"}
}