{
  "type": "Feature",
  "properties": {
    "iso:country":"DE",
    "sg:address":"Kleine Johannisstr. 6",
    "sg:city":"Hamburg",
    "sg:phone":"+49 40/373193",
    "sg:postcode":"20457",
    "sg:province":"Hamburg",
    "wof:name":"Havarie-sachverst\u00e4ndigen- B\u00fcro R\u00f6hl Gmbh",
    "wof:placetype":"venue"
},
  "geometry": {"coordinates":[9.9936552048,53.5497512817],"type":"Point"}
}