{
  "type": "Feature",
  "properties": {
    "iso:country":"DE",
    "sg:address":"Lutzhorner Landstr. 25",
    "sg:city":"Barmstedt",
    "sg:phone":"+49 4123/85360",
    "sg:postcode":"25355",
    "sg:province":"Schleswig-Holstein",
    "wof:name":"Hans L\u00e4u",
    "wof:placetype":"venue"
},
  "geometry": {"coordinates":[9.768364,53.803112],"type":"Point"}
}