{
  "type": "Feature",
  "properties": {
    "iso:country":"DE",
    "sg:address":"Rosenstr. 6",
    "sg:city":"M\u00fcnchen",
    "sg:phone":"+49 89/26949284",
    "sg:postcode":"80331",
    "sg:province":"Bayern",
    "wof:name":"Bernhard Ruidisch Rechtsanwalt",
    "wof:placetype":"venue"
},
  "geometry": {"coordinates":[11.573843956,48.1364822388],"type":"Point"}
}