{
  "type": "Feature",
  "properties": {
    "iso:country":"DE",
    "sg:address":"Trankgasse 7",
    "sg:city":"K\u00f6ln",
    "sg:phone":"+49 221/133078",
    "sg:postcode":"50667",
    "sg:province":"Nordrhein-Westfalen",
    "wof:name":"Lot Polnische Fluglinien",
    "wof:placetype":"venue"
},
  "geometry": {"coordinates":[6.957004,50.941914],"type":"Point"}
}