{
  "type": "Feature",
  "properties": {
    "iso:country":"DE",
    "sg:address":"D\u00e4nemarkstr. 22",
    "sg:city":"L\u00fcbeck",
    "sg:phone":"+49 4502/72148",
    "sg:postcode":"23570",
    "sg:province":"Schleswig-Holstein",
    "wof:name":"D. Balzer Elektroinstallation",
    "wof:placetype":"venue"
},
  "geometry": {"coordinates":[10.864615,53.965233],"type":"Point"}
}