{
  "type": "Feature",
  "properties": {
    "iso:country":"DE",
    "sg:address":"Schulstr. 24",
    "sg:city":"Westerheim",
    "sg:phone":"+49 7333/922344",
    "sg:postcode":"72589",
    "sg:province":"Baden-W\u00fcrttemberg",
    "wof:name":"Tappe Architekt",
    "wof:placetype":"venue"
},
  "geometry": {"coordinates":[9.628526,48.513233],"type":"Point"}
}