{
  "type": "Feature",
  "properties": {
    "iso:country":"DE",
    "sg:address":"Feithstr. 1",
    "sg:city":"Hagen",
    "sg:phone":"+49 2331/50630",
    "sg:postcode":"58095",
    "sg:province":"Nordrhein-Westfalen",
    "wof:name":"Damiano Russo",
    "wof:placetype":"venue"
},
  "geometry": {"coordinates":[7.5059189796,51.3613090515],"type":"Point"}
}