{
  "type": "Feature",
  "properties": {
    "iso:country":"DE",
    "sg:address":"Hiddenseer Str. 10",
    "sg:city":"Berlin",
    "sg:phone":"+49 30/4458070",
    "sg:postcode":"10437",
    "sg:province":"Berlin",
    "wof:name":"Dr. Med. Lothar Krell",
    "wof:placetype":"venue"
},
  "geometry": {"coordinates":[13.424639,52.542538],"type":"Point"}
}