{
  "type": "Feature",
  "properties": {
    "iso:country":"DE",
    "sg:address":"Indira-Gandhi-Str. 25",
    "sg:city":"Berlin",
    "sg:phone":"+49 30/3269160",
    "sg:postcode":"13088",
    "sg:province":"Berlin",
    "wof:name":"Brau Und Brunnen Ag Berlin Und Dortmund",
    "wof:placetype":"venue"
},
  "geometry": {"coordinates":[13.466799,52.548401],"type":"Point"}
}