{
  "type": "Feature",
  "properties": {
    "iso:country":"DE",
    "sg:address":"Harlesh\u00e4user Str. 64",
    "sg:city":"Kassel",
    "sg:phone":"+49 561/969730",
    "sg:postcode":"34130",
    "sg:province":"Hessen",
    "wof:name":"Delta-markt",
    "wof:placetype":"venue"
},
  "geometry": {"coordinates":[9.4444179535,51.326335907],"type":"Point"}
}