{
  "type": "Feature",
  "properties": {
    "iso:country":"DE",
    "sg:address":"Stolper Str 1",
    "sg:city":"M\u00f6lln",
    "sg:phone":"+49 4542/2818",
    "sg:postcode":"23879",
    "sg:province":"Schleswig-Holstein",
    "wof:name":"Strandkorbfabrik Eggers",
    "wof:placetype":"venue"
},
  "geometry": {"coordinates":[10.6967334747,53.6016273499],"type":"Point"}
}