{
  "type": "Feature",
  "properties": {
    "iso:country":"DE",
    "sg:address":"Victoriastr. 15",
    "sg:city":"K\u00f6ln",
    "sg:postcode":"50668",
    "sg:province":"Nordrhein-Westfalen",
    "wof:name":"Amore Gentle Clothes E. K.",
    "wof:placetype":"venue"
},
  "geometry": {"coordinates":[6.9516201019,50.9449615479],"type":"Point"}
}