{
  "type": "Feature",
  "properties": {
    "iso:country":"DE",
    "sg:address":"Burgmehlstr. 35",
    "sg:city":"Obersontheim",
    "sg:phone":"+49 7973/6763",
    "sg:postcode":"74423",
    "sg:province":"Baden-W\u00fcrttemberg",
    "wof:name":"Hermann Reichert",
    "wof:placetype":"venue"
},
  "geometry": {"coordinates":[9.884943,49.070343],"type":"Point"}
}