{
  "type": "Feature",
  "properties": {
    "iso:country":"DE",
    "sg:address":"Spremberger Str. 10",
    "sg:city":"Gro\u00df-Umstadt",
    "sg:phone":"+49 6078/72618",
    "sg:postcode":"64823",
    "sg:province":"Hessen",
    "wof:name":"K. Kirchmeyer",
    "wof:placetype":"venue"
},
  "geometry": {"coordinates":[8.919455,49.86412],"type":"Point"}
}