{
  "type": "Feature",
  "properties": {
    "iso:country":"DE",
    "sg:address":"Dorfstr. 1",
    "sg:city":"Steinkirchen",
    "sg:phone":"+49 8084/8759",
    "sg:postcode":"84439",
    "sg:province":"Bayern",
    "wof:name":"Fritz Spagl",
    "wof:placetype":"venue"
},
  "geometry": {"coordinates":[12.084613,48.392006],"type":"Point"}
}