{
  "type": "Feature",
  "properties": {
    "iso:country":"DE",
    "sg:address":"Heidenfahrt 52",
    "sg:city":"Heidesheim",
    "sg:phone":"+49 6132/57620",
    "sg:postcode":"55262",
    "sg:province":"Rheinland-Pfalz",
    "wof:name":"Hess Telekommunikation",
    "wof:placetype":"venue"
},
  "geometry": {"coordinates":[8.0957670212,50.0084991455],"type":"Point"}
}