{
  "type": "Feature",
  "properties": {
    "iso:country":"DE",
    "sg:address":"Tilledaer Str. 85",
    "sg:city":"Ichstedt",
    "sg:phone":"+49 3466/320795",
    "sg:postcode":"06556",
    "sg:province":"Th\u00fcringen",
    "wof:name":"Freia Wicht",
    "wof:placetype":"venue"
},
  "geometry": {"coordinates":[11.201848,51.386452],"type":"Point"}
}