{
  "type": "Feature",
  "properties": {
    "iso:country":"DE",
    "sg:address":"K\u00f6nigsbacher Str. 20",
    "sg:city":"Ilvesheim",
    "sg:phone":"+49 621/493204",
    "sg:postcode":"68549",
    "sg:province":"Baden-W\u00fcrttemberg",
    "wof:name":"Helmut Mehren Architekt",
    "wof:placetype":"venue"
},
  "geometry": {"coordinates":[8.566453,49.47834],"type":"Point"}
}