{
  "type": "Feature",
  "properties": {
    "iso:country":"DE",
    "sg:address":"Ulmenweg 24",
    "sg:city":"Stendal",
    "sg:phone":"+49 3931/715263",
    "sg:postcode":"39576",
    "sg:province":"Sachsen-Anhalt",
    "wof:name":"Siegfried Timm Stra\u00dfen- Und Tiefbau",
    "wof:placetype":"venue"
},
  "geometry": {"coordinates":[11.8467998505,52.6249694824],"type":"Point"}
}