{
  "type": "Feature",
  "properties": {
    "iso:country":"DE",
    "sg:address":"Sch\u00e4ferweg 5",
    "sg:city":"H\u00f6sbach",
    "sg:phone":"+49 6024/9989",
    "sg:postcode":"63768",
    "sg:province":"Bayern",
    "wof:name":"Rudolf Groepl",
    "wof:placetype":"venue"
},
  "geometry": {"coordinates":[9.2078323364,50.040725708],"type":"Point"}
}