{
  "type": "Feature",
  "properties": {
    "iso:country":"DE",
    "sg:address":"Hinter den G\u00e4rten 3",
    "sg:city":"Ettlingen",
    "sg:phone":"+49 791/3986",
    "sg:postcode":"76275",
    "sg:province":"Baden-W\u00fcrttemberg",
    "wof:name":"Nagel K\u00e4lte- Und Klimatechnik Gmbh",
    "wof:placetype":"venue"
},
  "geometry": {"coordinates":[9.7460603714,49.1133117676],"type":"Point"}
}