{
  "type": "Feature",
  "properties": {
    "iso:country":"DE",
    "sg:address":"Bismarckstr. 1",
    "sg:city":"Rendsburg",
    "sg:phone":"+49 4331/14310",
    "sg:postcode":"24768",
    "sg:province":"Schleswig-Holstein",
    "wof:name":"Rendsburger Wohnungsgesellschaft Mbh",
    "wof:placetype":"venue"
},
  "geometry": {"coordinates":[9.6729726791,54.3036575317],"type":"Point"}
}