{
  "type": "Feature",
  "properties": {
    "iso:country":"DE",
    "sg:address":"Oelgarten 11",
    "sg:city":"Sonsbeck",
    "sg:phone":"+49 2838/2297",
    "sg:postcode":"47665",
    "sg:province":"Nordrhein-Westfalen",
    "wof:name":"Georg Konetzke",
    "wof:placetype":"venue"
},
  "geometry": {"coordinates":[6.3699331284,51.605884552],"type":"Point"}
}