{
  "type": "Feature",
  "properties": {
    "iso:country":"DE",
    "sg:address":"Hamburger Str. 2",
    "sg:city":"Nauen",
    "sg:phone":"+49 3321/48204",
    "sg:postcode":"14641",
    "sg:province":"Brandenburg",
    "wof:name":"Kfz-sachverst\u00e4ndigenb\u00fcro Miks",
    "wof:placetype":"venue"
},
  "geometry": {"coordinates":[12.8731155396,52.6056404114],"type":"Point"}
}