{
  "type": "Feature",
  "properties": {
    "iso:country":"DE",
    "sg:address":"Am Weendespring 6 a",
    "sg:city":"G\u00f6ttingen",
    "sg:phone":"+49 551/383940",
    "sg:postcode":"37077",
    "sg:province":"Niedersachsen",
    "wof:name":"Seniorenwohnanlage",
    "wof:placetype":"venue"
},
  "geometry": {"coordinates":[9.933072,51.565937],"type":"Point"}
}