{
  "type": "Feature",
  "properties": {
    "iso:country":"DE",
    "sg:address":"R\u00f6merweg 11",
    "sg:city":"Limburgerhof",
    "sg:phone":"+49 6236/48437",
    "sg:postcode":"67117",
    "sg:province":"Rheinland-Pfalz",
    "wof:name":"Brima Wohnbau Gmbh",
    "wof:placetype":"venue"
},
  "geometry": {"coordinates":[8.388964,49.428703],"type":"Point"}
}