{
  "type": "Feature",
  "properties": {
    "iso:country":"DE",
    "sg:address":"Triptiser Str. 35",
    "sg:city":"Auma",
    "sg:phone":"+49 4967/217090",
    "sg:postcode":"07955",
    "sg:province":"Th\u00fcringen",
    "wof:name":"Polyplast M\u00dcller Gmbh",
    "wof:placetype":"venue"
},
  "geometry": {"coordinates":[7.9446902275,49.9662399292],"type":"Point"}
}