{
  "type": "Feature",
  "properties": {
    "iso:country":"DE",
    "sg:address":"Kalchreuther Str. 155",
    "sg:city":"N\u00fcrnberg",
    "sg:postcode":"90411",
    "sg:province":"Bayern",
    "wof:name":"D & L Gmbh",
    "wof:placetype":"venue"
},
  "geometry": {"coordinates":[11.1097993851,49.5063247681],"type":"Point"}
}