{
  "type": "Feature",
  "properties": {
    "iso:country":"DE",
    "sg:address":"Am Stockfeld 23",
    "sg:city":"Viernheim",
    "sg:phone":"+49 6204/79779",
    "sg:postcode":"68519",
    "sg:province":"Hessen",
    "wof:name":"Ccav",
    "wof:placetype":"venue"
},
  "geometry": {"coordinates":[8.570352,49.547565],"type":"Point"}
}