{
  "type": "Feature",
  "properties": {
    "iso:country":"DE",
    "sg:address":"Ilmenauer Str. 4",
    "sg:city":"Berlin",
    "sg:phone":"+49 30/8263807",
    "sg:postcode":"14193",
    "sg:province":"Berlin",
    "wof:name":"Viellechner Dachdecker- Meister Gmbh",
    "wof:placetype":"venue"
},
  "geometry": {"coordinates":[13.287568,52.481941],"type":"Point"}
}