{
  "type": "Feature",
  "properties": {
    "iso:country":"DE",
    "sg:address":"Leimholer Str. 17",
    "sg:city":"Radevormwald",
    "sg:phone":"+49 2195/932148",
    "sg:postcode":"42477",
    "sg:province":"Nordrhein-Westfalen",
    "wof:name":"Ihre Besondere Visitenkarte Im Web",
    "wof:placetype":"venue"
},
  "geometry": {"coordinates":[7.332993,51.20359],"type":"Point"}
}