{
  "type": "Feature",
  "properties": {
    "iso:country":"DE",
    "sg:address":"Tannenstr. 12",
    "sg:city":"Baldham",
    "sg:phone":"+49 8106/31033",
    "sg:postcode":"85598",
    "sg:province":"Bayern",
    "wof:name":"Hans Schlecht Ingenieur",
    "wof:placetype":"venue"
},
  "geometry": {"coordinates":[11.7818098068,48.0945510864],"type":"Point"}
}