{
  "type": "Feature",
  "properties": {
    "iso:country":"DE",
    "sg:address":"Leinstr. 26",
    "sg:city":"Nienburg",
    "sg:phone":"+49 5021/12073",
    "sg:postcode":"31582",
    "sg:province":"Niedersachsen",
    "wof:name":"E. J\u00fcrgens",
    "wof:placetype":"venue"
},
  "geometry": {"coordinates":[9.2089776993,52.6385421753],"type":"Point"}
}