{
  "type": "Feature",
  "properties": {
    "iso:country":"DE",
    "sg:address":"Amselweg 1",
    "sg:city":"Gr\u00e4felfing",
    "sg:phone":"+49 89/8541638",
    "sg:postcode":"82166",
    "sg:province":"Bayern",
    "wof:name":"J. F\u00fchrer",
    "wof:placetype":"venue"
},
  "geometry": {"coordinates":[11.439106,48.116707],"type":"Point"}
}