{
  "type": "Feature",
  "properties": {
    "iso:country":"DE",
    "sg:address":"Curiestr. 11",
    "sg:city":"Lippstadt",
    "sg:postcode":"59557",
    "sg:province":"Nordrhein-Westfalen",
    "wof:name":"Aldi Gmbh & Co. Kg",
    "wof:placetype":"venue"
},
  "geometry": {"coordinates":[8.3291883469,51.6581459045],"type":"Point"}
}