{
  "type": "Feature",
  "properties": {
    "iso:country":"DE",
    "sg:address":"Innl\u00e4nde 20",
    "sg:city":"Rosenheim",
    "sg:phone":"+49 8031/39010",
    "sg:postcode":"83022",
    "sg:province":"Bayern",
    "wof:name":"Hans Holzner Hoch- Tief- Und",
    "wof:placetype":"venue"
},
  "geometry": {"coordinates":[12.143614769,47.8517608643],"type":"Point"}
}