{
  "type": "Feature",
  "properties": {
    "iso:country":"DE",
    "sg:address":"Mommsenstr. 24",
    "sg:city":"K\u00f6ln",
    "sg:phone":"+49 221/4680424",
    "sg:postcode":"50935",
    "sg:province":"Nordrhein-Westfalen",
    "wof:name":"Bavaria 37 Bavariacharter Chartersegeln Portugal",
    "wof:placetype":"venue"
},
  "geometry": {"coordinates":[6.911386,50.919155],"type":"Point"}
}