{
  "type": "Feature",
  "properties": {
    "iso:country":"DE",
    "sg:address":"Wilhelmstr. 2a",
    "sg:city":"Bechhofen",
    "sg:phone":"+49 6372/61427",
    "sg:postcode":"66894",
    "sg:province":"Rheinland-Pfalz",
    "wof:name":"H. Drewes",
    "wof:placetype":"venue"
},
  "geometry": {"coordinates":[7.405242,49.350185],"type":"Point"}
}