{
  "type": "Feature",
  "properties": {
    "iso:country":"DE",
    "sg:address":"Fraunhoferstr. 3",
    "sg:city":"F\u00fcrstenfeldbruck",
    "sg:phone":"+49 8141/31254",
    "sg:postcode":"82256",
    "sg:province":"Bayern",
    "wof:name":"Verzinkerei Sch\u00f6rg Gmbh & Co. Kg",
    "wof:placetype":"venue"
},
  "geometry": {"coordinates":[11.244995,48.200565],"type":"Point"}
}