{
  "type": "Feature",
  "properties": {
    "iso:country":"DE",
    "sg:address":"Garlstorfer Str. 3",
    "sg:city":"Egestorf",
    "sg:phone":"+49 4175/1045",
    "sg:postcode":"21272",
    "sg:province":"Niedersachsen",
    "wof:name":"Hoheneichen Immobilien E. K.",
    "wof:placetype":"venue"
},
  "geometry": {"coordinates":[10.0636749268,53.1959037781],"type":"Point"}
}