{
  "type": "Feature",
  "properties": {
    "iso:country":"DE",
    "sg:address":"Marktplatz 1",
    "sg:city":"R\u00f6hrnbach",
    "sg:phone":"+49 8582/80808",
    "sg:postcode":"94133",
    "sg:province":"Bayern",
    "wof:name":"Hotel Alte Post",
    "wof:placetype":"venue"
},
  "geometry": {"coordinates":[13.5231323242,48.7402763367],"type":"Point"}
}