{
  "type": "Feature",
  "properties": {
    "iso:country":"DE",
    "sg:address":"Emslandstr. 12",
    "sg:city":"Emlichheim",
    "sg:postcode":"49824",
    "sg:province":"Niedersachsen",
    "wof:name":"Grenzlandmarkt Emlichheim",
    "wof:placetype":"venue"
},
  "geometry": {"coordinates":[6.8553071022,52.6098632812],"type":"Point"}
}