{
  "type": "Feature",
  "properties": {
    "iso:country":"DE",
    "sg:address":"Roonstr. 11",
    "sg:city":"Braunschweig",
    "sg:phone":"+49 531/337335",
    "sg:postcode":"38102",
    "sg:province":"Niedersachsen",
    "wof:name":"Leporello Buchhandlung Am Marstall Gmbh",
    "wof:placetype":"venue"
},
  "geometry": {"coordinates":[10.54413414,52.2705497742],"type":"Point"}
}