{
  "type": "Feature",
  "properties": {
    "iso:country":"DE",
    "sg:address":"Engerstr. 5",
    "sg:city":"Kempen",
    "sg:phone":"+49 2152/517424",
    "sg:postcode":"47906",
    "sg:province":"Nordrhein-Westfalen",
    "wof:name":"S. Ermler",
    "wof:placetype":"venue"
},
  "geometry": {"coordinates":[6.420823,51.364422],"type":"Point"}
}