{
  "type": "Feature",
  "properties": {
    "iso:country":"DE",
    "sg:address":"Neuburger Str. 18",
    "sg:city":"K\u00f6nigsmoos",
    "sg:phone":"+49 8433/920800",
    "sg:postcode":"86669",
    "sg:province":"Bayern",
    "wof:name":"Ursula Oppenheimer Rechtsanw\u00e4ltin",
    "wof:placetype":"venue"
},
  "geometry": {"coordinates":[11.214600563,48.6672554016],"type":"Point"}
}