{
  "type": "Feature",
  "properties": {
    "iso:country":"DE",
    "sg:address":"Ahornstr. 4",
    "sg:city":"Ludwigsfelde",
    "sg:postcode":"14974",
    "sg:province":"Brandenburg",
    "wof:name":"Richard Lawson Auto Logistik Gmbh",
    "wof:placetype":"venue"
},
  "geometry": {"coordinates":[13.260925,52.297592],"type":"Point"}
}