{
  "type": "Feature",
  "properties": {
    "iso:country":"DE",
    "sg:address":"Im Altenhof 6",
    "sg:city":"Windeck",
    "sg:phone":"+49 2292/7921",
    "sg:postcode":"51570",
    "sg:province":"Nordrhein-Westfalen",
    "wof:name":"Peter Meurer",
    "wof:placetype":"venue"
},
  "geometry": {"coordinates":[7.647402,50.795322],"type":"Point"}
}