{
  "type": "Feature",
  "properties": {
    "iso:country":"DE",
    "sg:address":"Hauptstr. 13",
    "sg:city":"Wagenfeld",
    "sg:phone":"+49 5444/5853",
    "sg:postcode":"49419",
    "sg:province":"Niedersachsen",
    "wof:name":"Schillmanns Kinderkiste",
    "wof:placetype":"venue"
},
  "geometry": {"coordinates":[8.5841827393,52.5510482788],"type":"Point"}
}