{
  "type": "Feature",
  "properties": {
    "iso:country":"DE",
    "sg:address":"In der Freiheit 31",
    "sg:city":"Sundern",
    "sg:phone":"+49 2933/5257",
    "sg:postcode":"59846",
    "sg:province":"Nordrhein-Westfalen",
    "wof:name":"Restaurant Grillhaus",
    "wof:placetype":"venue"
},
  "geometry": {"coordinates":[8.0019006729,51.3352966309],"type":"Point"}
}