{
  "type": "Feature",
  "properties": {
    "iso:country":"DE",
    "sg:address":"Am Werth 2",
    "sg:city":"Leverkusen",
    "sg:phone":"+49 2173/40240",
    "sg:postcode":"51371",
    "sg:province":"Nordrhein-Westfalen",
    "wof:name":"Sportbootschule H\u00f6tzer",
    "wof:placetype":"venue"
},
  "geometry": {"coordinates":[6.923466,51.057747],"type":"Point"}
}