{
  "type": "Feature",
  "properties": {
    "iso:country":"DE",
    "sg:address":"M\u00f6rnsheim",
    "sg:city":"M\u00f6rnsheim",
    "sg:phone":"+49 9145/7139",
    "sg:postcode":"91804",
    "sg:province":"Bayern",
    "wof:name":"Raiffeisenbank M\u00f6rnsheim-dollnstein",
    "wof:placetype":"venue"
},
  "geometry": {"coordinates":[11.00602,48.869461],"type":"Point"}
}