{
  "type": "Feature",
  "properties": {
    "iso:country":"DE",
    "sg:address":"Ruhesteinstr. 256",
    "sg:city":"Baiersbronn",
    "sg:phone":"+49 7442/3596",
    "sg:postcode":"72270",
    "sg:province":"Baden-W\u00fcrttemberg",
    "wof:name":"Braun-verwaltungs-gmbh",
    "wof:placetype":"venue"
},
  "geometry": {"coordinates":[8.28223,48.536869],"type":"Point"}
}