{
  "type": "Feature",
  "properties": {
    "iso:country":"DE",
    "sg:address":"Hamburger Ring 25",
    "sg:city":"Werder",
    "sg:phone":"+49 3327/43212",
    "sg:postcode":"14542",
    "sg:province":"Brandenburg",
    "wof:name":"Feierabend- Und Pflegeheim Wachtelwinkel",
    "wof:placetype":"venue"
},
  "geometry": {"coordinates":[12.93158,52.373291],"type":"Point"}
}