{
  "type": "Feature",
  "properties": {
    "iso:country":"DE",
    "sg:address":"Von-Galen-Str. 16",
    "sg:city":"Haltern",
    "sg:phone":"+49 2364/68046",
    "sg:postcode":"45721",
    "sg:province":"Nordrhein-Westfalen",
    "wof:name":"Entemeier",
    "wof:placetype":"venue"
},
  "geometry": {"coordinates":[7.2207331657,51.7746047974],"type":"Point"}
}