{
  "type": "Feature",
  "properties": {
    "iso:country":"DE",
    "sg:address":"M\u00fchlental 16",
    "sg:city":"Elbingerode",
    "sg:phone":"+49 39454/41025",
    "sg:postcode":"38875",
    "sg:province":"Sachsen-Anhalt",
    "wof:name":"\u00d6seb \u00d6kologische Sanierungs- Gesellschaft Elbingerode",
    "wof:placetype":"venue"
},
  "geometry": {"coordinates":[10.831856,51.761944],"type":"Point"}
}