{
  "type": "Feature",
  "properties": {
    "iso:country":"DE",
    "sg:address":"Sickingenstr. 1 a",
    "sg:city":"Heidelberg",
    "sg:phone":"+49 6221/34400",
    "sg:postcode":"69126",
    "sg:province":"Baden-W\u00fcrttemberg",
    "wof:name":"Struve & Partner",
    "wof:placetype":"venue"
},
  "geometry": {"coordinates":[8.6897783279,49.3836402893],"type":"Point"}
}