{
  "type": "Feature",
  "properties": {
    "iso:country":"DE",
    "sg:address":"Am Rothenbach 22",
    "sg:city":"Warendorf",
    "sg:phone":"+49 2581/632454",
    "sg:postcode":"48231",
    "sg:province":"Nordrhein-Westfalen",
    "wof:name":"T. H\u00fcsemann",
    "wof:placetype":"venue"
},
  "geometry": {"coordinates":[7.9841399193,51.9342689514],"type":"Point"}
}