{
  "type": "Feature",
  "properties": {
    "iso:country":"DE",
    "sg:address":"Bahnhofstr. 8",
    "sg:city":"Baierbrunn",
    "sg:phone":"+49 89/7930165",
    "sg:postcode":"82065",
    "sg:province":"Bayern",
    "wof:name":"Hans Mayer",
    "wof:placetype":"venue"
},
  "geometry": {"coordinates":[11.483817,48.019196],"type":"Point"}
}