{
  "type": "Feature",
  "properties": {
    "iso:country":"DE",
    "sg:address":"Immenst\u00e4dter Str. 77b",
    "sg:city":"Kempten",
    "sg:phone":"+49 831/10810",
    "sg:postcode":"87435",
    "sg:province":"Bayern",
    "wof:name":"Christina Bach",
    "wof:placetype":"venue"
},
  "geometry": {"coordinates":[10.3113203049,47.7140350342],"type":"Point"}
}