{
  "type": "Feature",
  "properties": {
    "iso:country":"DE",
    "sg:address":"Landwehrstr. 21",
    "sg:city":"Michelau",
    "sg:phone":"+49 9571/8151",
    "sg:postcode":"96247",
    "sg:province":"Bayern",
    "wof:name":"Hans Weisser",
    "wof:placetype":"venue"
},
  "geometry": {"coordinates":[11.1082334518,50.1657104492],"type":"Point"}
}