{
  "type": "Feature",
  "properties": {
    "iso:country":"DE",
    "sg:address":"Harzstr. 9",
    "sg:city":"Rottleberode",
    "sg:phone":"+49 34653/83423",
    "sg:postcode":"06548",
    "sg:province":"Sachsen-Anhalt",
    "wof:name":"Wohnungsbaugenossenschaft",
    "wof:placetype":"venue"
},
  "geometry": {"coordinates":[10.946024,51.523289],"type":"Point"}
}