{
  "type": "Feature",
  "properties": {
    "iso:country":"DE",
    "sg:address":"Dekan-G\u00f6tz-Str. 8",
    "sg:city":"Attenkirchen",
    "sg:phone":"+49 8168/1682",
    "sg:postcode":"85395",
    "sg:province":"Bayern",
    "wof:name":"Manfred Ausfelder Architekt",
    "wof:placetype":"venue"
},
  "geometry": {"coordinates":[11.760943,48.503735],"type":"Point"}
}