{
  "type": "Feature",
  "properties": {
    "iso:country":"DE",
    "sg:address":"Alter Markt",
    "sg:city":"Kiel",
    "sg:phone":"+49 431/93849",
    "sg:postcode":"24103",
    "sg:province":"Schleswig-Holstein",
    "wof:name":"Nordsee Quick",
    "wof:placetype":"venue"
},
  "geometry": {"coordinates":[10.139799118,54.3230285645],"type":"Point"}
}