{
  "type": "Feature",
  "properties": {
    "iso:country":"DE",
    "sg:address":"Oberdahlhausen 2",
    "sg:city":"Radevormwald",
    "sg:phone":"+49 2195/7214",
    "sg:postcode":"42477",
    "sg:province":"Nordrhein-Westfalen",
    "wof:name":"Fritz W. Bergerhoff",
    "wof:placetype":"venue"
},
  "geometry": {"coordinates":[7.314056,51.206787],"type":"Point"}
}