{
  "type": "Feature",
  "properties": {
    "iso:country":"DE",
    "sg:address":"Breite Str. 52",
    "sg:city":"Peine",
    "sg:phone":"+49 5171/17405",
    "sg:postcode":"31224",
    "sg:province":"Niedersachsen",
    "wof:name":"Photo-klimesch Gmbh",
    "wof:placetype":"venue"
},
  "geometry": {"coordinates":[10.2263832092,52.3221893311],"type":"Point"}
}