{
  "type": "Feature",
  "properties": {
    "iso:country":"DE",
    "sg:address":"Herrenstr. 25",
    "sg:city":"Die\u00dfen",
    "sg:phone":"+49 8807/7125",
    "sg:postcode":"86911",
    "sg:province":"Bayern",
    "wof:name":"B. Reinisch",
    "wof:placetype":"venue"
},
  "geometry": {"coordinates":[11.0997409821,47.9481658936],"type":"Point"}
}