{
  "type": "Feature",
  "properties": {
    "iso:country":"DE",
    "sg:address":"Helmernsche Str. 6",
    "sg:city":"Willebadessen",
    "sg:phone":"+49 5644/1212",
    "sg:postcode":"34439",
    "sg:province":"Nordrhein-Westfalen",
    "wof:name":"Hans Weitzenb\u00fcrger",
    "wof:placetype":"venue"
},
  "geometry": {"coordinates":[9.129061,51.600967],"type":"Point"}
}