{
  "type": "Feature",
  "properties": {
    "iso:country":"DE",
    "sg:address":"M\u00fchlweg 2",
    "sg:city":"Siebeldingen",
    "sg:phone":"+49 6345/3311",
    "sg:postcode":"76833",
    "sg:province":"Rheinland-Pfalz",
    "wof:name":"Hotel-restaurant Sonnenhof",
    "wof:placetype":"venue"
},
  "geometry": {"coordinates":[8.0457410812,49.2086143494],"type":"Point"}
}