{
  "type": "Feature",
  "properties": {
    "iso:country":"DE",
    "sg:address":"Nuhnestrasse 2",
    "sg:city":"Winterberg",
    "sg:phone":"+49 2981/908506",
    "sg:postcode":"59955",
    "sg:province":"Nordrhein-Westfalen",
    "wof:name":"Pizzeria I Faraglioni",
    "wof:placetype":"venue"
},
  "geometry": {"coordinates":[8.532692,51.193172],"type":"Point"}
}