{
  "type": "Feature",
  "properties": {
    "iso:country":"DE",
    "sg:address":"Julius-Leber-Ring",
    "sg:city":"Erfurt",
    "sg:postcode":"99087",
    "sg:province":"Th\u00fcringen",
    "wof:name":"Textilhaus Weyrauch Gmbh",
    "wof:placetype":"venue"
},
  "geometry": {"coordinates":[11.0205640793,51.0196495056],"type":"Point"}
}