{
  "type": "Feature",
  "properties": {
    "iso:country":"DE",
    "sg:address":"Wasserburger Str. 37",
    "sg:city":"Kirchseeon",
    "sg:phone":"+49 8091/3681",
    "sg:postcode":"85614",
    "sg:province":"Bayern",
    "wof:name":"Walter Anlauf Ingenieur",
    "wof:placetype":"venue"
},
  "geometry": {"coordinates":[11.8948574066,48.0699081421],"type":"Point"}
}