{
  "type": "Feature",
  "properties": {
    "iso:country":"DE",
    "sg:address":"Vor dem Viehtor 20",
    "sg:city":"Stendal",
    "sg:phone":"+49 3931/213392",
    "sg:postcode":"39576",
    "sg:province":"Sachsen-Anhalt",
    "wof:name":"Konrad M\u00fccke",
    "wof:placetype":"venue"
},
  "geometry": {"coordinates":[11.8650798798,52.6104507446],"type":"Point"}
}