{
  "type": "Feature",
  "properties": {
    "iso:country":"DE",
    "sg:address":"Am Vorwerksbusch 10",
    "sg:city":"Reinbek",
    "sg:postcode":"21465",
    "sg:province":"Schleswig-Holstein",
    "wof:name":"Dr. Jay J. Hanus Gmbh",
    "wof:placetype":"venue"
},
  "geometry": {"coordinates":[10.25952,53.519516],"type":"Point"}
}