{
  "type": "Feature",
  "properties": {
    "iso:country":"DE",
    "sg:address":"Ellhornstr. 35 - 37",
    "sg:city":"Bremen",
    "sg:phone":"+49 421/18323",
    "sg:postcode":"28195",
    "sg:province":"Bremen",
    "wof:name":"Hans-h. Birkholz Und Heinz-o. Elais",
    "wof:placetype":"venue"
},
  "geometry": {"coordinates":[8.8047409058,53.0834197998],"type":"Point"}
}