{
  "type": "Feature",
  "properties": {
    "iso:country":"DE",
    "sg:address":"Rodder Damm 151",
    "sg:city":"Rheine",
    "sg:phone":"+49 5971/71134",
    "sg:postcode":"48429",
    "sg:province":"Nordrhein-Westfalen",
    "wof:name":"Tampico",
    "wof:placetype":"venue"
},
  "geometry": {"coordinates":[7.482555,52.285645],"type":"Point"}
}