{
  "type": "Feature",
  "properties": {
    "iso:country":"DE",
    "sg:address":"Graf-Adolf-Str. 89",
    "sg:city":"D\u00fcsseldorf",
    "sg:phone":"+49 211/382801",
    "sg:postcode":"40210",
    "sg:province":"Nordrhein-Westfalen",
    "wof:name":"Hermann Gr\u00fcne Leihhaus",
    "wof:placetype":"venue"
},
  "geometry": {"coordinates":[6.7901,51.219494],"type":"Point"}
}