{
  "type": "Feature",
  "properties": {
    "iso:country":"DE",
    "sg:address":"Im Vogelsang 3",
    "sg:city":"Allensbach",
    "sg:phone":"+49 7533/5089",
    "sg:postcode":"78476",
    "sg:province":"Baden-W\u00fcrttemberg",
    "wof:name":"Eichkorn Bau Gmbh",
    "wof:placetype":"venue"
},
  "geometry": {"coordinates":[9.05938,47.720432],"type":"Point"}
}