{
  "type": "Feature",
  "properties": {
    "iso:country":"DE",
    "sg:address":"Plinganserstr. 6",
    "sg:city":"M\u00fcnchen",
    "sg:phone":"+49 89/74792735",
    "sg:postcode":"81369",
    "sg:province":"Bayern",
    "wof:name":"Weinprobe Stadel",
    "wof:placetype":"venue"
},
  "geometry": {"coordinates":[11.5409488678,48.1217422485],"type":"Point"}
}