{
  "type": "Feature",
  "properties": {
    "iso:country":"DE",
    "sg:address":"Neuffenstr. 17",
    "sg:city":"Villingen-Schwenningen",
    "sg:phone":"+49 7720/66625",
    "sg:postcode":"78056",
    "sg:province":"Baden-W\u00fcrttemberg",
    "wof:name":"Maier Leuchtfarben Gmbh",
    "wof:placetype":"venue"
},
  "geometry": {"coordinates":[8.554041,48.062687],"type":"Point"}
}