{
  "type": "Feature",
  "properties": {
    "iso:country":"DE",
    "sg:address":"Falkensteinstr. 6",
    "sg:city":"Traunstein",
    "sg:phone":"+49 861/20910",
    "sg:postcode":"83278",
    "sg:province":"Bayern",
    "wof:name":"Buderus Heiztechnik Gmbh",
    "wof:placetype":"venue"
},
  "geometry": {"coordinates":[12.6260099411,47.8560752869],"type":"Point"}
}