{
  "type": "Feature",
  "properties": {
    "iso:country":"DE",
    "sg:address":"Rotenburger Str. 4",
    "sg:city":"Hassendorf",
    "sg:phone":"+49 4264/2987",
    "sg:postcode":"27367",
    "sg:province":"Niedersachsen",
    "wof:name":"Hans Sackmann Elektroinstallation",
    "wof:placetype":"venue"
},
  "geometry": {"coordinates":[9.273616,53.118603],"type":"Point"}
}