{
  "type": "Feature",
  "properties": {
    "iso:country":"DE",
    "sg:address":"Marienstra\u00dfe 27",
    "sg:city":"Stuttgart",
    "sg:phone":"+49 711/96000100",
    "sg:postcode":"70178",
    "sg:province":"Baden-W\u00fcrttemberg",
    "wof:name":"Ecom Service Ag",
    "wof:placetype":"venue"
},
  "geometry": {"coordinates":[9.17092,48.771217],"type":"Point"}
}