{
  "type": "Feature",
  "properties": {
    "iso:country":"DE",
    "sg:address":"Kemnastr. 17",
    "sg:city":"Recklinghausen",
    "sg:postcode":"45657",
    "sg:province":"Nordrhein-Westfalen",
    "wof:name":"Burgerfactory Inh. Ruth Werner E. K.",
    "wof:placetype":"venue"
},
  "geometry": {"coordinates":[7.1928091049,51.6103401184],"type":"Point"}
}