{
  "type": "Feature",
  "properties": {
    "iso:country":"DE",
    "sg:address":"Mutlanger Str. 19",
    "sg:city":"Spraitbach",
    "sg:phone":"+49 7176/868",
    "sg:postcode":"73565",
    "sg:province":"Baden-W\u00fcrttemberg",
    "wof:name":"F. Brenner",
    "wof:placetype":"venue"
},
  "geometry": {"coordinates":[9.7619724274,48.8782691956],"type":"Point"}
}