{
  "type": "Feature",
  "properties": {
    "iso:country":"DE",
    "sg:address":"Wasgenstr. 6",
    "sg:city":"Berlin",
    "sg:phone":"+49 30/8048800",
    "sg:postcode":"14129",
    "sg:province":"Berlin",
    "wof:name":"Heda Kg",
    "wof:placetype":"venue"
},
  "geometry": {"coordinates":[13.2109966278,52.4349212646],"type":"Point"}
}