{
  "type": "Feature",
  "properties": {
    "iso:country":"DE",
    "sg:address":"S\u00fcdanlage 23",
    "sg:city":"Gie\u00dfen",
    "sg:phone":"+49 641/75125",
    "sg:postcode":"35390",
    "sg:province":"Hessen",
    "wof:name":"Rohrbach Verwaltungs-gmbh",
    "wof:placetype":"venue"
},
  "geometry": {"coordinates":[8.67037,50.581741],"type":"Point"}
}