{
  "type": "Feature",
  "properties": {
    "iso:country":"DE",
    "sg:address":"Klosterstr. 13 a",
    "sg:city":"Pocking",
    "sg:phone":"+49 8531/41201",
    "sg:postcode":"94060",
    "sg:province":"Bayern",
    "wof:name":"Hans H\u00f6chtl",
    "wof:placetype":"venue"
},
  "geometry": {"coordinates":[13.3104829788,48.4029273987],"type":"Point"}
}