{
  "type": "Feature",
  "properties": {
    "iso:country":"DE",
    "sg:address":"Brauhausstr. 2",
    "sg:city":"Fulda",
    "sg:phone":"+49 661/21818",
    "sg:postcode":"36037",
    "sg:province":"Hessen",
    "wof:name":"H & H Ihr Reisetreff Gmbh",
    "wof:placetype":"venue"
},
  "geometry": {"coordinates":[9.6770763397,50.5493583679],"type":"Point"}
}