{
  "type": "Feature",
  "properties": {
    "iso:country":"DE",
    "sg:address":"Helmut-Von-Gerlach-Str 3",
    "sg:city":"Halle",
    "sg:phone":"+49 345/5754960",
    "sg:postcode":"06112",
    "sg:province":"Sachsen-Anhalt",
    "wof:name":"Fiba Energieservice Gmbh",
    "wof:placetype":"venue"
},
  "geometry": {"coordinates":[11.997011,51.487946],"type":"Point"}
}