{
  "type": "Feature",
  "properties": {
    "iso:country":"DE",
    "sg:address":"Bettenbach",
    "sg:city":"Geisenhausen",
    "sg:phone":"+49 8743/91191",
    "sg:postcode":"84144",
    "sg:province":"Bayern",
    "wof:name":"Johann Zellhuber Finanzberater",
    "wof:placetype":"venue"
},
  "geometry": {"coordinates":[12.2894802094,48.5031394958],"type":"Point"}
}