{
  "type": "Feature",
  "properties": {
    "iso:country":"DE",
    "sg:address":"Hauptstr. 62",
    "sg:city":"Wildetaube",
    "sg:phone":"+49 36625/20316",
    "sg:postcode":"07980",
    "sg:province":"Th\u00fcringen",
    "wof:name":"Lothar Matthes",
    "wof:placetype":"venue"
},
  "geometry": {"coordinates":[12.111708,50.720188],"type":"Point"}
}