{
  "type": "Feature",
  "properties": {
    "iso:country":"DE",
    "sg:address":"Max-von-M\u00fcller-Str. 33",
    "sg:city":"Rottenburg",
    "sg:phone":"+49 8781/94100",
    "sg:postcode":"84056",
    "sg:province":"Bayern",
    "wof:name":"Dr. E. Steffl Steuerberater",
    "wof:placetype":"venue"
},
  "geometry": {"coordinates":[12.0247325897,48.7062797546],"type":"Point"}
}