{
  "type": "Feature",
  "properties": {
    "iso:country":"DE",
    "sg:address":"K\u00fcppelstr. 1",
    "sg:city":"Frankenberg",
    "sg:phone":"+49 6451/4605",
    "sg:postcode":"35066",
    "sg:province":"Hessen",
    "wof:name":"Karl-heinz Lauckner Ingenieur",
    "wof:placetype":"venue"
},
  "geometry": {"coordinates":[8.7966766357,51.0888824463],"type":"Point"}
}