{
  "type": "Feature",
  "properties": {
    "iso:country":"DE",
    "sg:address":"Steinbruchgasse 1",
    "sg:city":"Niederf\u00fcllbach",
    "sg:phone":"+49 9565/7440",
    "sg:postcode":"96489",
    "sg:province":"Bayern",
    "wof:name":"Vereinigte Coburger Sparkassen",
    "wof:placetype":"venue"
},
  "geometry": {"coordinates":[10.991097,50.219604],"type":"Point"}
}