{
  "type": "Feature",
  "properties": {
    "iso:country":"DE",
    "sg:address":"Arnimstra\u00dfe 58",
    "sg:city":"L\u00fcbeck",
    "sg:postcode":"23566",
    "sg:province":"Schleswig-Holstein",
    "wof:name":"Steuerberater U. Rechtsanwald",
    "wof:placetype":"venue"
},
  "geometry": {"coordinates":[10.720632,53.873894],"type":"Point"}
}