{
  "type": "Feature",
  "properties": {
    "iso:country":"DE",
    "sg:address":"Dornheimstra\u00dfe 62",
    "sg:city":"Erfurt",
    "sg:phone":"+49 171 7213003",
    "sg:postcode":"99099",
    "sg:province":"Th\u00fcringen",
    "wof:name":"Edv-beratung H\u00e4ring",
    "wof:placetype":"venue"
},
  "geometry": {"coordinates":[11.06821,50.956608],"type":"Point"}
}