{
  "type": "Feature",
  "properties": {
    "iso:country":"DE",
    "sg:address":"Hinterm Herrn 3",
    "sg:city":"Strullendorf",
    "sg:phone":"+49 9543/851652",
    "sg:postcode":"96129",
    "sg:province":"Bayern",
    "wof:name":"Karin Mai",
    "wof:placetype":"venue"
},
  "geometry": {"coordinates":[10.968507,49.843704],"type":"Point"}
}