{
  "type": "Feature",
  "properties": {
    "iso:country":"DE",
    "sg:address":"Bornheide 19",
    "sg:city":"Hamburg",
    "sg:phone":"+49 40/8005555",
    "sg:postcode":"22549",
    "sg:province":"Hamburg",
    "wof:name":"Thermosch\u00f6n Glaserei Gmbh",
    "wof:placetype":"venue"
},
  "geometry": {"coordinates":[9.8531608582,53.5838394165],"type":"Point"}
}