{
  "type": "Feature",
  "properties": {
    "iso:country":"DE",
    "sg:address":"Engell\u00e4nderstr. 3",
    "sg:city":"Bernau",
    "sg:phone":"+49 8051/7945",
    "sg:postcode":"83233",
    "sg:province":"Bayern",
    "wof:name":"Kallos Verlag Und Versand Gmbh",
    "wof:placetype":"venue"
},
  "geometry": {"coordinates":[12.3628339767,47.8085289001],"type":"Point"}
}