{
  "type": "Feature",
  "properties": {
    "iso:country":"DE",
    "sg:address":"Jahnstr. 13",
    "sg:city":"Bad K\u00f6nig",
    "sg:phone":"+49 6063/4001",
    "sg:postcode":"64732",
    "sg:province":"Hessen",
    "wof:name":"M. \u00d6z",
    "wof:placetype":"venue"
},
  "geometry": {"coordinates":[9.0045080185,49.7401695251],"type":"Point"}
}