{
  "type": "Feature",
  "properties": {
    "iso:country":"DE",
    "sg:address":"Johannes-Kepler-Str. 4-6",
    "sg:city":"Herrenberg",
    "sg:phone":"+49 7032/932300",
    "sg:postcode":"71083",
    "sg:province":"Baden-W\u00fcrttemberg",
    "wof:name":"Good Buy Eurotel Gmbh",
    "wof:placetype":"venue"
},
  "geometry": {"coordinates":[8.8588018417,48.6008415222],"type":"Point"}
}