{
  "type": "Feature",
  "properties": {
    "iso:country":"DE",
    "sg:address":"Luisenstr. 38",
    "sg:city":"Siegen",
    "sg:phone":"+49 271/4852101",
    "sg:postcode":"57076",
    "sg:province":"Nordrhein-Westfalen",
    "wof:name":"Gerd Grehl Rechtsanwalt",
    "wof:placetype":"venue"
},
  "geometry": {"coordinates":[8.0354003906,50.8926925659],"type":"Point"}
}