{
  "type": "Feature",
  "properties": {
    "iso:country":"DE",
    "sg:address":"Hohenzollernstr. 162",
    "sg:city":"M\u00f6nchengladbach",
    "sg:phone":"+49 2161/22912",
    "sg:postcode":"41063",
    "sg:province":"Nordrhein-Westfalen",
    "wof:name":"Rudolf Ohme Steuerberater",
    "wof:placetype":"venue"
},
  "geometry": {"coordinates":[6.4415397644,51.2042808533],"type":"Point"}
}