{
  "type": "Feature",
  "properties": {
    "iso:country":"DE",
    "sg:address":"Wallweg 19",
    "sg:city":"Fulda",
    "sg:phone":"+49 661/74260",
    "sg:postcode":"36043",
    "sg:province":"Hessen",
    "wof:name":"H. Schiebelhut",
    "wof:placetype":"venue"
},
  "geometry": {"coordinates":[9.678186,50.540073],"type":"Point"}
}