{
  "type": "Feature",
  "properties": {
    "iso:country":"DE",
    "sg:address":"Lothringer Str. 42",
    "sg:city":"K\u00f6ln",
    "sg:postcode":"50677",
    "sg:province":"Nordrhein-Westfalen",
    "wof:name":"Wald Verm\u00f6gensverwaltung Und Beteiligung Gmbh",
    "wof:placetype":"venue"
},
  "geometry": {"coordinates":[6.94906,50.924248],"type":"Point"}
}