{
  "type": "Feature",
  "properties": {
    "iso:country":"DE",
    "sg:address":"C\u00e4cilienstr. 46",
    "sg:city":"K\u00f6ln",
    "sg:postcode":"50667",
    "sg:province":"Nordrhein-Westfalen",
    "wof:name":"Ideal Medical Products Deutschland Gmbh",
    "wof:placetype":"venue"
},
  "geometry": {"coordinates":[6.95032,50.935558],"type":"Point"}
}