{
  "type": "Feature",
  "properties": {
    "iso:country":"DE",
    "sg:address":"Rissener Str. 101",
    "sg:city":"Wedel",
    "sg:phone":"+49 4103/918305",
    "sg:postcode":"22880",
    "sg:province":"Schleswig-Holstein",
    "wof:name":"Jet-tankstelle",
    "wof:placetype":"venue"
},
  "geometry": {"coordinates":[9.7218179703,53.583656311],"type":"Point"}
}