{
  "type": "Feature",
  "properties": {
    "iso:country":"DE",
    "sg:address":"Bahnhofstr. 56",
    "sg:city":"Geraberg",
    "sg:phone":"+49 3677/792259",
    "sg:postcode":"98716",
    "sg:province":"Th\u00fcringen",
    "wof:name":"Oho Baustoffe Gmbh",
    "wof:placetype":"venue"
},
  "geometry": {"coordinates":[10.858112,50.715775],"type":"Point"}
}