{
  "type": "Feature",
  "properties": {
    "iso:country":"DE",
    "sg:address":"Wittensteinstr 200-204",
    "sg:city":"Wuppertal",
    "sg:phone":"+49 202/557036",
    "sg:postcode":"42283",
    "sg:province":"Nordrhein-Westfalen",
    "wof:name":"Josef Jansen & Co",
    "wof:placetype":"venue"
},
  "geometry": {"coordinates":[7.183871,51.263901],"type":"Point"}
}