{
  "type": "Feature",
  "properties": {
    "iso:country":"DE",
    "sg:address":"Hindenburgstr. 13",
    "sg:city":"Langenau",
    "sg:phone":"+49 7345/7571",
    "sg:postcode":"89129",
    "sg:province":"Baden-W\u00fcrttemberg",
    "wof:name":"Hans Bohrmann",
    "wof:placetype":"venue"
},
  "geometry": {"coordinates":[10.1204938889,48.4979438782],"type":"Point"}
}