{
  "type": "Feature",
  "properties": {
    "iso:country":"DE",
    "sg:address":"Hansjakobstr. 9",
    "sg:city":"Hambr\u00fccken",
    "sg:postcode":"76707",
    "sg:province":"Baden-W\u00fcrttemberg",
    "wof:name":"Ssvw Abteilung Schwimmen",
    "wof:placetype":"venue"
},
  "geometry": {"coordinates":[8.541828,49.189648],"type":"Point"}
}