{
  "type": "Feature",
  "properties": {
    "iso:country":"DE",
    "sg:address":"Kirchenstr. 28",
    "sg:city":"Mauer",
    "sg:phone":"+49 6226/3177",
    "sg:postcode":"69256",
    "sg:province":"Baden-W\u00fcrttemberg",
    "wof:name":"Hallenbad",
    "wof:placetype":"venue"
},
  "geometry": {"coordinates":[8.8011302948,49.3374214172],"type":"Point"}
}