{
  "type": "Feature",
  "properties": {
    "iso:country":"DE",
    "sg:address":"Eschenrieder Str. 5a",
    "sg:city":"M\u00fcnchen",
    "sg:phone":"+49 89/8642486",
    "sg:postcode":"81249",
    "sg:province":"Bayern",
    "wof:name":"Verlag F\u00fcr Deutsche Bundesgesetze Gmbh",
    "wof:placetype":"venue"
},
  "geometry": {"coordinates":[11.4087257385,48.1805915833],"type":"Point"}
}