{
  "type": "Feature",
  "properties": {
    "iso:country":"DE",
    "sg:address":"Bergstr. 8",
    "sg:city":"Greven",
    "sg:phone":"+49 2571/2578",
    "sg:postcode":"48268",
    "sg:province":"Nordrhein-Westfalen",
    "wof:name":"E. Gilbert-burgholz",
    "wof:placetype":"venue"
},
  "geometry": {"coordinates":[7.612034,52.093533],"type":"Point"}
}