{
  "type": "Feature",
  "properties": {
    "iso:country":"DE",
    "sg:address":"Obere Sandstr. 4",
    "sg:city":"Bamberg",
    "sg:phone":"+49 951/59192",
    "sg:postcode":"96049",
    "sg:province":"Bayern",
    "wof:name":"Wigwam",
    "wof:placetype":"venue"
},
  "geometry": {"coordinates":[10.884268,49.89188],"type":"Point"}
}