{
  "type": "Feature",
  "properties": {
    "iso:country":"DE",
    "sg:address":"Welchentalstr. 6",
    "sg:city":"Freiburg",
    "sg:phone":"+49 761/65428",
    "sg:postcode":"79117",
    "sg:province":"Baden-W\u00fcrttemberg",
    "wof:name":"Frei-bau Gmbh",
    "wof:placetype":"venue"
},
  "geometry": {"coordinates":[7.9193601608,47.9941101074],"type":"Point"}
}