{
  "type": "Feature",
  "properties": {
    "iso:country":"DE",
    "sg:address":"Salzstr. 6",
    "sg:city":"Thalheim",
    "sg:postcode":"09380",
    "sg:province":"Sachsen",
    "wof:name":"Horst Werzinger",
    "wof:placetype":"venue"
},
  "geometry": {"coordinates":[12.852529,50.7019],"type":"Point"}
}