{
  "type": "Feature",
  "properties": {
    "iso:country":"DE",
    "sg:address":"Blankeneser Chaussee 192",
    "sg:city":"Schenefeld",
    "sg:phone":"+49 40/8406280",
    "sg:postcode":"22869",
    "sg:province":"Schleswig-Holstein",
    "wof:name":"J\u00fcrgen Schmidt",
    "wof:placetype":"venue"
},
  "geometry": {"coordinates":[9.8222370148,53.5848274231],"type":"Point"}
}