{
  "type": "Feature",
  "properties": {
    "iso:country":"DE",
    "sg:address":"Kreuzstr. 21",
    "sg:city":"Braunschweig",
    "sg:phone":"+49 531/85334",
    "sg:postcode":"38118",
    "sg:province":"Niedersachsen",
    "wof:name":"T. Deinert",
    "wof:placetype":"venue"
},
  "geometry": {"coordinates":[10.499109,52.261795],"type":"Point"}
}