{
  "type": "Feature",
  "properties": {
    "iso:country":"DE",
    "sg:address":"F\u00fcrstenwalder Allee 45",
    "sg:city":"Berlin",
    "sg:phone":"+49 30/3311721",
    "sg:postcode":"12589",
    "sg:province":"Berlin",
    "wof:name":"Allcasa Haus- Und Grundst\u00fccks- Verwaltungs Gmbh",
    "wof:placetype":"venue"
},
  "geometry": {"coordinates":[13.6860580444,52.4428062439],"type":"Point"}
}