{
  "type": "Feature",
  "properties": {
    "iso:country":"DE",
    "sg:address":"Grumbach 6",
    "sg:city":"Breitungen",
    "sg:phone":"+49 36848/87428",
    "sg:postcode":"98597",
    "sg:province":"Th\u00fcringen",
    "wof:name":"Schulz",
    "wof:placetype":"venue"
},
  "geometry": {"coordinates":[10.316466,50.772713],"type":"Point"}
}