{
  "type": "Feature",
  "properties": {
    "iso:country":"DE",
    "sg:address":"Beethovenallee 4",
    "sg:city":"Bonn",
    "sg:phone":"+49 228/956750",
    "sg:postcode":"53173",
    "sg:province":"Nordrhein-Westfalen",
    "wof:name":"Taubitz Immobilienpartner Kg",
    "wof:placetype":"venue"
},
  "geometry": {"coordinates":[7.1573400497,50.686088562],"type":"Point"}
}