{
  "type": "Feature",
  "properties": {
    "iso:country":"DE",
    "sg:address":"Kirchstr. 2",
    "sg:city":"Linnich",
    "sg:phone":"+49 2462/1044",
    "sg:postcode":"52441",
    "sg:province":"Nordrhein-Westfalen",
    "wof:name":"J. Steffens",
    "wof:placetype":"venue"
},
  "geometry": {"coordinates":[6.268372,50.978851],"type":"Point"}
}