{
  "type": "Feature",
  "properties": {
    "iso:country":"DE",
    "sg:address":"Eichelstr. 11",
    "sg:city":"Ravensburg",
    "sg:phone":"+49 751/22583",
    "sg:postcode":"88212",
    "sg:province":"Baden-W\u00fcrttemberg",
    "wof:name":"B. Schirl Textilreinigungs Gmbh",
    "wof:placetype":"venue"
},
  "geometry": {"coordinates":[9.614488,47.78056],"type":"Point"}
}