{
  "type": "Feature",
  "properties": {
    "iso:country":"DE",
    "sg:address":"Uwestr. 4",
    "sg:city":"Espelkamp",
    "sg:phone":"+49 5743/1323",
    "sg:postcode":"32339",
    "sg:province":"Nordrhein-Westfalen",
    "wof:name":"Friedr. L\u00fcdtke",
    "wof:placetype":"venue"
},
  "geometry": {"coordinates":[8.573614,52.353203],"type":"Point"}
}