{
  "type": "Feature",
  "properties": {
    "iso:country":"DE",
    "sg:address":"Hechelgasse 6",
    "sg:city":"Mindelheim",
    "sg:phone":"+49 8261",
    "sg:postcode":"87719",
    "sg:province":"Bayern",
    "wof:name":"Rund Um Mindelheim",
    "wof:placetype":"venue"
},
  "geometry": {"coordinates":[10.486957,48.047482],"type":"Point"}
}