{
  "type": "Feature",
  "properties": {
    "iso:country":"DE",
    "sg:address":"Herrendeich 10",
    "sg:city":"Engelbrechtsche Wildnis",
    "sg:phone":"+49 4124/2322",
    "sg:postcode":"25348",
    "sg:province":"Schleswig-Holstein",
    "wof:name":"Fortuna Veranstaltungs- Service Gmbh",
    "wof:placetype":"venue"
},
  "geometry": {"coordinates":[9.454124,53.772488],"type":"Point"}
}