{
  "type": "Feature",
  "properties": {
    "iso:country":"DE",
    "sg:address":"W\u00fcrttemberger Str. 115 b",
    "sg:city":"Bruchsal",
    "sg:phone":"+49 7251/2394",
    "sg:postcode":"76646",
    "sg:province":"Baden-W\u00fcrttemberg",
    "wof:name":"J. U. M. Reindl Ohg",
    "wof:placetype":"venue"
},
  "geometry": {"coordinates":[8.610447,49.119129],"type":"Point"}
}