{
  "type": "Feature",
  "properties": {
    "iso:country":"DE",
    "sg:address":"Isl\u00e4nder Platz 1",
    "sg:city":"Bremerhaven",
    "sg:phone":"+49 471/33310",
    "sg:postcode":"27570",
    "sg:province":"Bremen",
    "wof:name":"Gerhard Heins Gmbh & Co. Kg",
    "wof:placetype":"venue"
},
  "geometry": {"coordinates":[8.596475,53.521221],"type":"Point"}
}