{
  "type": "Feature",
  "properties": {
    "iso:country":"DE",
    "sg:address":"Flurstr. 16",
    "sg:city":"Hohenberg",
    "sg:phone":"+49 9233/4619",
    "sg:postcode":"95691",
    "sg:province":"Bayern",
    "wof:name":"Gemeinn\u00fctziger Bauverein Zu Hohenberg Eg",
    "wof:placetype":"venue"
},
  "geometry": {"coordinates":[12.2193441391,50.0935630798],"type":"Point"}
}