{
  "type": "Feature",
  "properties": {
    "iso:country":"DE",
    "sg:address":"Am Gewerbepark 2",
    "sg:city":"S\u00fcptitz",
    "sg:phone":"+49 3421/708475",
    "sg:postcode":"04860",
    "sg:province":"Sachsen",
    "wof:name":"Ger\u00fcstbau Peter Beier",
    "wof:placetype":"venue"
},
  "geometry": {"coordinates":[12.9239835739,51.5596427917],"type":"Point"}
}