{
  "type": "Feature",
  "properties": {
    "iso:country":"DE",
    "sg:address":"Alte Poststr. 13",
    "sg:city":"Hamminkeln",
    "sg:phone":"+49 2857/2309",
    "sg:postcode":"46499",
    "sg:province":"Nordrhein-Westfalen",
    "wof:name":"Johannes D\u00f6ring",
    "wof:placetype":"venue"
},
  "geometry": {"coordinates":[6.503739,51.723835],"type":"Point"}
}