{
  "type": "Feature",
  "properties": {
    "iso:country":"DE",
    "sg:address":"Neuer H\u00f6ltigbaum 5-7",
    "sg:city":"Hamburg",
    "sg:phone":"+49 40/6828790",
    "sg:postcode":"22143",
    "sg:province":"Hamburg",
    "wof:name":"Johann M\u00dcller Gmbh & Co. Kg",
    "wof:placetype":"venue"
},
  "geometry": {"coordinates":[10.184923172,53.6084213257],"type":"Point"}
}