{
  "type": "Feature",
  "properties": {
    "iso:country":"DE",
    "sg:address":"Unterjettinger Str. 6",
    "sg:city":"M\u00f6tzingen",
    "sg:phone":"+49 7452/740755",
    "sg:postcode":"71159",
    "sg:province":"Baden-W\u00fcrttemberg",
    "wof:name":"Garant Versicherungs- Vermittlung E. K.",
    "wof:placetype":"venue"
},
  "geometry": {"coordinates":[8.7760133743,48.5369606018],"type":"Point"}
}