{
  "type": "Feature",
  "properties": {
    "iso:country":"DE",
    "sg:address":"Schwarzer Weg 70",
    "sg:city":"Peine",
    "sg:phone":"+49 5171/72622",
    "sg:postcode":"31224",
    "sg:province":"Niedersachsen",
    "wof:name":"Olympiade Inh. Konstantinos Zaurelidis",
    "wof:placetype":"venue"
},
  "geometry": {"coordinates":[10.2355899811,52.3304862976],"type":"Point"}
}