{
  "type": "Feature",
  "properties": {
    "iso:country":"DE",
    "sg:address":"Kirchstr. 9",
    "sg:city":"Altheim",
    "sg:phone":"+49 4973/40512",
    "sg:postcode":"89174",
    "sg:province":"Baden-W\u00fcrttemberg",
    "wof:name":"Sparkasse",
    "wof:placetype":"venue"
},
  "geometry": {"coordinates":[10.026163,48.582005],"type":"Point"}
}