{
  "type": "Feature",
  "properties": {
    "iso:country":"DE",
    "sg:address":"Weinholdweg 8",
    "sg:city":"Calw",
    "sg:phone":"+49 7051/79270",
    "sg:postcode":"75365",
    "sg:province":"Baden-W\u00fcrttemberg",
    "wof:name":"Inter-conzept-m\u00fcnz- Beteiligungs- Kg",
    "wof:placetype":"venue"
},
  "geometry": {"coordinates":[8.7599887848,48.7171287537],"type":"Point"}
}