{
  "type": "Feature",
  "properties": {
    "iso:country":"DE",
    "sg:address":"Bahnhofstr. 9",
    "sg:city":"Pforzheim",
    "sg:phone":"+49 7231/101273",
    "sg:postcode":"75172",
    "sg:province":"Baden-W\u00fcrttemberg",
    "wof:name":"H\u00f6rger\u00e4te-ring",
    "wof:placetype":"venue"
},
  "geometry": {"coordinates":[8.7003221512,48.8926315308],"type":"Point"}
}