{
  "type": "Feature",
  "properties": {
    "iso:country":"DE",
    "sg:address":"Gr\u00fcnewalder Str. 62",
    "sg:city":"Solingen",
    "sg:phone":"+49 212/819195",
    "sg:postcode":"42657",
    "sg:province":"Nordrhein-Westfalen",
    "wof:name":"R. W. Loges",
    "wof:placetype":"venue"
},
  "geometry": {"coordinates":[7.0761017799,51.1601448059],"type":"Point"}
}