{
  "type": "Feature",
  "properties": {
    "iso:country":"DE",
    "sg:address":"Gartenfeldweg 1",
    "sg:city":"Lohberg",
    "sg:phone":"+49 9943/1060",
    "sg:postcode":"93470",
    "sg:province":"Bayern",
    "wof:name":"Franz Liebl",
    "wof:placetype":"venue"
},
  "geometry": {"coordinates":[13.089805,49.180771],"type":"Point"}
}