{
  "type": "Feature",
  "properties": {
    "iso:country":"DE",
    "sg:address":"Vehlgast",
    "sg:city":"Vehlgast",
    "sg:postcode":"39539",
    "sg:province":"Sachsen-Anhalt",
    "wof:name":"Gemeinn\u00fctzige Walden Gmbh",
    "wof:placetype":"venue"
},
  "geometry": {"coordinates":[12.202050209,52.800163269],"type":"Point"}
}