{
  "type": "Feature",
  "properties": {
    "iso:country":"DE",
    "sg:address":"Pfaffenherdstr. 39",
    "sg:city":"Burgthann",
    "sg:phone":"+49 9188/1466",
    "sg:postcode":"90559",
    "sg:province":"Bayern",
    "wof:name":"Josef Petter",
    "wof:placetype":"venue"
},
  "geometry": {"coordinates":[11.339425,49.332977],"type":"Point"}
}