{
  "type": "Feature",
  "properties": {
    "iso:country":"DE",
    "sg:address":"T\u00fcbinger Str. 8",
    "sg:city":"Neckartailfingen",
    "sg:phone":"+49 7127/33207",
    "sg:postcode":"72666",
    "sg:province":"Baden-W\u00fcrttemberg",
    "wof:name":"Walter Beutler",
    "wof:placetype":"venue"
},
  "geometry": {"coordinates":[9.263302803,48.6116294861],"type":"Point"}
}