{
  "type": "Feature",
  "properties": {
    "iso:country":"DE",
    "sg:address":"Clausenhof 20",
    "sg:city":"Wuppertal",
    "sg:phone":"+49 202/705780",
    "sg:postcode":"42285",
    "sg:province":"Nordrhein-Westfalen",
    "wof:name":"F. R. Miesel",
    "wof:placetype":"venue"
},
  "geometry": {"coordinates":[7.163615,51.273369],"type":"Point"}
}