{
  "type": "Feature",
  "properties": {
    "iso:country":"DE",
    "sg:address":"Westlicher Stadtgraben 5",
    "sg:city":"Deggendorf",
    "sg:phone":"+49 991/8940",
    "sg:postcode":"94469",
    "sg:province":"Bayern",
    "wof:name":"Scherzo",
    "wof:placetype":"venue"
},
  "geometry": {"coordinates":[12.960294,48.834393],"type":"Point"}
}