{
  "type": "Feature",
  "properties": {
    "iso:country":"DE",
    "sg:address":"Trierer Stra\u00dfe 50",
    "sg:city":"Saarburg",
    "sg:phone":"+49 6581/994172",
    "sg:postcode":"54439",
    "sg:province":"Rheinland-Pfalz",
    "wof:name":"First Choice",
    "wof:placetype":"venue"
},
  "geometry": {"coordinates":[6.560133934,49.6175689697],"type":"Point"}
}