{
  "type": "Feature",
  "properties": {
    "iso:country":"DE",
    "sg:address":"Hauptstr. 43",
    "sg:city":"Ha\u00dffurt",
    "sg:phone":"+49 9521/64431",
    "sg:postcode":"97437",
    "sg:province":"Bayern",
    "wof:name":"Mannl & Hauck Gmbh",
    "wof:placetype":"venue"
},
  "geometry": {"coordinates":[10.5059280396,50.0314178467],"type":"Point"}
}