{
  "type": "Feature",
  "properties": {
    "iso:country":"DE",
    "sg:address":"Pinselstr. 46",
    "sg:city":"Landau",
    "sg:phone":"+49 6341/30931",
    "sg:postcode":"76829",
    "sg:province":"Rheinland-Pfalz",
    "wof:name":"Fritz Born Weinanbau",
    "wof:placetype":"venue"
},
  "geometry": {"coordinates":[8.0836696625,49.1791915894],"type":"Point"}
}