{
  "type": "Feature",
  "properties": {
    "iso:country":"DE",
    "sg:address":"Rosenstr. 27",
    "sg:city":"Denzlingen",
    "sg:phone":"+49 7666/3625",
    "sg:postcode":"79211",
    "sg:province":"Baden-W\u00fcrttemberg",
    "wof:name":"Karl-h. Schmidt",
    "wof:placetype":"venue"
},
  "geometry": {"coordinates":[7.8879990578,48.0690612793],"type":"Point"}
}