{
  "type": "Feature",
  "properties": {
    "iso:country":"DE",
    "sg:address":"Trills 46",
    "sg:city":"Erkrath",
    "sg:phone":"+49 2104/33598",
    "sg:postcode":"40699",
    "sg:province":"Nordrhein-Westfalen",
    "wof:name":"Pizzeria Bella Italia",
    "wof:placetype":"venue"
},
  "geometry": {"coordinates":[6.9480199814,51.2098693848],"type":"Point"}
}