{
  "type": "Feature",
  "properties": {
    "iso:country":"DE",
    "sg:address":"Mei\u00dfnerweg 11",
    "sg:city":"Fuldabr\u00fcck",
    "sg:phone":"+49 561/582986",
    "sg:postcode":"34277",
    "sg:province":"Hessen",
    "wof:name":"Data Point Computer Vertriebs Gmbh",
    "wof:placetype":"venue"
},
  "geometry": {"coordinates":[9.4957971573,51.2683334351],"type":"Point"}
}