{
  "type": "Feature",
  "properties": {
    "iso:country":"DE",
    "sg:address":"M\u00fchltorstr. 13",
    "sg:city":"Lauffen",
    "sg:phone":"+49 7133/8229",
    "sg:postcode":"74348",
    "sg:province":"Baden-W\u00fcrttemberg",
    "wof:name":"Sieglinde Schiedt",
    "wof:placetype":"venue"
},
  "geometry": {"coordinates":[9.15969944,49.075378418],"type":"Point"}
}