{
  "type": "Feature",
  "properties": {
    "iso:country":"DE",
    "sg:address":"Drechslerstr. 6",
    "sg:city":"L\u00fcbeck",
    "sg:phone":"+49 451/8973939",
    "sg:postcode":"23556",
    "sg:province":"Schleswig-Holstein",
    "wof:name":"Gebr. Leu Ohg",
    "wof:placetype":"venue"
},
  "geometry": {"coordinates":[10.609489,53.861427],"type":"Point"}
}