{
  "type": "Feature",
  "properties": {
    "iso:country":"DE",
    "sg:address":"Am Sportplatz 7",
    "sg:city":"M\u00f6nkhagen",
    "sg:postcode":"23619",
    "sg:province":"Schleswig-Holstein",
    "wof:name":"Neubert Pflanzengro\u00df- Handel Gmbh",
    "wof:placetype":"venue"
},
  "geometry": {"coordinates":[10.562074,53.900547],"type":"Point"}
}