{
  "type": "Feature",
  "properties": {
    "iso:country":"DE",
    "sg:address":"Mittelweg 7",
    "sg:city":"Hilders",
    "sg:phone":"+49 6681/601",
    "sg:postcode":"36115",
    "sg:province":"Hessen",
    "wof:name":"Gastst\u00e4tte Wolfgang Glotzbach",
    "wof:placetype":"venue"
},
  "geometry": {"coordinates":[10.0324077606,50.591884613],"type":"Point"}
}