{
  "type": "Feature",
  "properties": {
    "iso:country":"DE",
    "sg:address":"Dieke 20",
    "sg:city":"Harsewinkel",
    "sg:phone":"+49 5247/407254",
    "sg:postcode":"33428",
    "sg:province":"Nordrhein-Westfalen",
    "wof:name":"T. E. M. P. Technische Entwicklungen Maschinen",
    "wof:placetype":"venue"
},
  "geometry": {"coordinates":[8.247323,51.966686],"type":"Point"}
}