{
  "type": "Feature",
  "properties": {
    "iso:country":"DE",
    "sg:address":"Liebigstr. 3",
    "sg:city":"Erlenbach",
    "sg:phone":"+49 9372/5587",
    "sg:postcode":"63906",
    "sg:province":"Bayern",
    "wof:name":"Restaurant Ankara",
    "wof:placetype":"venue"
},
  "geometry": {"coordinates":[9.1517362595,49.8080825806],"type":"Point"}
}