{
  "type": "Feature",
  "properties": {
    "iso:country":"DE",
    "sg:address":"Unterhainstr. 12",
    "sg:city":"Bad Br\u00fcckenau",
    "sg:postcode":"97769",
    "sg:province":"Bayern",
    "wof:name":"M. J.-verwaltungs-gmbh",
    "wof:placetype":"venue"
},
  "geometry": {"coordinates":[9.7889289856,50.3092918396],"type":"Point"}
}