{
  "type": "Feature",
  "properties": {
    "iso:country":"DE",
    "sg:address":"Auestr. 10",
    "sg:city":"Halle",
    "sg:phone":"+49 345/7709513",
    "sg:postcode":"06132",
    "sg:province":"Sachsen-Anhalt",
    "wof:name":"G. Brehm",
    "wof:placetype":"venue"
},
  "geometry": {"coordinates":[11.994316,51.418976],"type":"Point"}
}