{
  "type": "Feature",
  "properties": {
    "iso:country":"DE",
    "sg:address":"Dorfstr. 15b",
    "sg:city":"Gro\u00df Krankow",
    "sg:phone":"+49 38424/4042",
    "sg:postcode":"23966",
    "sg:province":"Mecklenburg-Vorpommern",
    "wof:name":"Karsten Becher Hoch- Und Tiefbau Gmbh",
    "wof:placetype":"venue"
},
  "geometry": {"coordinates":[11.4661464691,53.8910751343],"type":"Point"}
}