{
  "type": "Feature",
  "properties": {
    "iso:country":"DE",
    "sg:address":"Brennerstr. 5",
    "sg:city":"Herne",
    "sg:phone":"+49 2325/41203",
    "sg:postcode":"44652",
    "sg:province":"Nordrhein-Westfalen",
    "wof:name":"Tk Bautr\u00e4ger Gmbh",
    "wof:placetype":"venue"
},
  "geometry": {"coordinates":[7.184407,51.525291],"type":"Point"}
}