{
  "type": "Feature",
  "properties": {
    "iso:country":"DE",
    "sg:address":"Eschborner Landstr. 42-50",
    "sg:city":"Frankfurt",
    "sg:phone":"+49 69/4208060",
    "sg:postcode":"60489",
    "sg:province":"Hessen",
    "wof:name":"Psd Piepenbrock Sicherheitsdienste",
    "wof:placetype":"venue"
},
  "geometry": {"coordinates":[8.603286,50.127651],"type":"Point"}
}