{
  "type": "Feature",
  "properties": {
    "iso:country":"DE",
    "sg:address":"Marktplatz 11",
    "sg:city":"Trossingen",
    "sg:phone":"+49 7425/326326",
    "sg:postcode":"78647",
    "sg:province":"Baden-W\u00fcrttemberg",
    "wof:name":"Moonlight Tanzbar",
    "wof:placetype":"venue"
},
  "geometry": {"coordinates":[8.639380455,48.0769386292],"type":"Point"}
}