{
  "type": "Feature",
  "properties": {
    "iso:country":"DE",
    "sg:address":"Konrad-Adenauer-Str. 53",
    "sg:city":"Dossenheim",
    "sg:phone":"+49 6221/861445",
    "sg:postcode":"69221",
    "sg:province":"Baden-W\u00fcrttemberg",
    "wof:name":"J. A. Claussen",
    "wof:placetype":"venue"
},
  "geometry": {"coordinates":[8.6659240723,49.4433441162],"type":"Point"}
}