{
  "type": "Feature",
  "properties": {
    "iso:country":"DE",
    "sg:address":"Wettringer Str. 26",
    "sg:city":"Steinfurt",
    "sg:phone":"+49 2552/3787",
    "sg:postcode":"48565",
    "sg:province":"Nordrhein-Westfalen",
    "wof:name":"Compuhard Computer Hardware Handels Gmbh",
    "wof:placetype":"venue"
},
  "geometry": {"coordinates":[7.3413658142,52.1515808105],"type":"Point"}
}