{
  "type": "Feature",
  "properties": {
    "iso:country":"DE",
    "sg:address":"Rastatter Str. 13",
    "sg:city":"Rheinm\u00fcnster",
    "sg:phone":"+49 7227/3116",
    "sg:postcode":"77836",
    "sg:province":"Baden-W\u00fcrttemberg",
    "wof:name":"Krone-post",
    "wof:placetype":"venue"
},
  "geometry": {"coordinates":[8.0480852127,48.7648468018],"type":"Point"}
}