{
  "type": "Feature",
  "properties": {
    "iso:country":"DE",
    "sg:address":"Deverweg",
    "sg:city":"Papenburg",
    "sg:phone":"+49 4961/840",
    "sg:postcode":"26871",
    "sg:province":"Niedersachsen",
    "wof:name":"Br\u00fcgmann Verwaltungsges. Mbh",
    "wof:placetype":"venue"
},
  "geometry": {"coordinates":[7.379645,53.0821],"type":"Point"}
}