{
  "type": "Feature",
  "properties": {
    "iso:country":"DE",
    "sg:address":"Unterislinger Weg 22",
    "sg:city":"Regensburg",
    "sg:phone":"+49 941/787880",
    "sg:postcode":"93053",
    "sg:province":"Bayern",
    "wof:name":"Erwin Gmeinwieser Gmbh",
    "wof:placetype":"venue"
},
  "geometry": {"coordinates":[12.1105546951,48.9976806641],"type":"Point"}
}