{
  "type": "Feature",
  "properties": {
    "iso:country":"DE",
    "sg:address":"Kurt-Schumacher-Str. 21",
    "sg:city":"Braunschweig",
    "sg:phone":"+49 531/70010",
    "sg:postcode":"38102",
    "sg:province":"Niedersachsen",
    "wof:name":"Schweitzer & Partner Planungsgruppe Gmbh",
    "wof:placetype":"venue"
},
  "geometry": {"coordinates":[10.533239,52.256542],"type":"Point"}
}