{
  "type": "Feature",
  "properties": {
    "iso:country":"DE",
    "sg:address":"Am Gro\u00dfmarkt 4",
    "sg:city":"Herne",
    "sg:phone":"+49 2323/23826",
    "sg:postcode":"44653",
    "sg:province":"Nordrhein-Westfalen",
    "wof:name":"Heinz-j\u00fcrgen Fischer",
    "wof:placetype":"venue"
},
  "geometry": {"coordinates":[7.1907968521,51.5415115356],"type":"Point"}
}