{
  "type": "Feature",
  "properties": {
    "iso:country":"DE",
    "sg:address":"Am Bergacker 8",
    "sg:city":"Augsburg",
    "sg:phone":"+49 821/451799",
    "sg:postcode":"86156",
    "sg:province":"Bayern",
    "wof:name":"Erich Korn Immobilienmakler",
    "wof:placetype":"venue"
},
  "geometry": {"coordinates":[10.8446540833,48.3895454407],"type":"Point"}
}