{
  "type": "Feature",
  "properties": {
    "iso:country":"DE",
    "sg:address":"Graditzer Str. 81",
    "sg:city":"K\u00f6ln",
    "sg:phone":"+49 221/9714570",
    "sg:postcode":"50735",
    "sg:province":"Nordrhein-Westfalen",
    "wof:name":"Peter Kissel Gmbh & Co. Kg",
    "wof:placetype":"venue"
},
  "geometry": {"coordinates":[6.965031,50.982498],"type":"Point"}
}