{
  "type": "Feature",
  "properties": {
    "iso:country":"DE",
    "sg:address":"Thomas-Mann-Str. 29",
    "sg:city":"Mutterstadt",
    "sg:phone":"+49 6234/1550",
    "sg:postcode":"67112",
    "sg:province":"Rheinland-Pfalz",
    "wof:name":"Bergold Immobilien Gmbh Hausverwaltung",
    "wof:placetype":"venue"
},
  "geometry": {"coordinates":[8.3658008575,49.4402999878],"type":"Point"}
}