{
  "type": "Feature",
  "properties": {
    "iso:country":"DE",
    "sg:address":"Am Mechtenberg 85",
    "sg:city":"Essen",
    "sg:phone":"+49 201/8559730",
    "sg:postcode":"45309",
    "sg:province":"Nordrhein-Westfalen",
    "wof:name":"Bodycote W\u00c4rmebehandlung Gmbh",
    "wof:placetype":"venue"
},
  "geometry": {"coordinates":[7.087174,51.477306],"type":"Point"}
}