{
  "type": "Feature",
  "properties": {
    "iso:country":"DE",
    "sg:address":"Im Winkel 5",
    "sg:city":"Fellheim",
    "sg:phone":"+49 8335/8602",
    "sg:postcode":"87748",
    "sg:province":"Bayern",
    "wof:name":"Erwin B\u00f6ckeler",
    "wof:placetype":"venue"
},
  "geometry": {"coordinates":[10.148424,48.074551],"type":"Point"}
}