{
  "type": "Feature",
  "properties": {
    "iso:country":"DE",
    "sg:address":"Garzweiler Allee 41",
    "sg:city":"J\u00fcchen",
    "sg:phone":"+49 2165/2724",
    "sg:postcode":"41363",
    "sg:province":"Nordrhein-Westfalen",
    "wof:name":"P. Pelzer",
    "wof:placetype":"venue"
},
  "geometry": {"coordinates":[6.5124511719,51.108581543],"type":"Point"}
}