{
  "type": "Feature",
  "properties": {
    "iso:country":"DE",
    "sg:address":"Westenhellweg 3",
    "sg:city":"Dortmund",
    "sg:phone":"+49 231/527275",
    "sg:postcode":"44137",
    "sg:province":"Nordrhein-Westfalen",
    "wof:name":"Modevertriebsgesellschaft Ortner Gmbh",
    "wof:placetype":"venue"
},
  "geometry": {"coordinates":[7.4654998779,51.5142784119],"type":"Point"}
}