{
  "type": "Feature",
  "properties": {
    "iso:country":"DE",
    "sg:address":"Hauptstr. 41",
    "sg:city":"Weinheim",
    "sg:phone":"+49 6201/12738",
    "sg:postcode":"69469",
    "sg:province":"Baden-W\u00fcrttemberg",
    "wof:name":"Hans Engemann",
    "wof:placetype":"venue"
},
  "geometry": {"coordinates":[8.6729478836,49.5514945984],"type":"Point"}
}