{
  "type": "Feature",
  "properties": {
    "iso:country":"DE",
    "sg:address":"Brandenburger Str. 1a",
    "sg:city":"Br\u00fcck",
    "sg:phone":"+49 33844/50937",
    "sg:postcode":"14822",
    "sg:province":"Brandenburg",
    "wof:name":"Peter Balk",
    "wof:placetype":"venue"
},
  "geometry": {"coordinates":[12.7619628906,52.1970024109],"type":"Point"}
}