{
  "type": "Feature",
  "properties": {
    "iso:country":"DE",
    "sg:address":"Bullauer Str. 36",
    "sg:city":"Erbach",
    "sg:phone":"+49 6062/62729",
    "sg:postcode":"64711",
    "sg:province":"Hessen",
    "wof:name":"G. Richter Elektroinstallation",
    "wof:placetype":"venue"
},
  "geometry": {"coordinates":[9.011921,49.645882],"type":"Point"}
}