{
  "type": "Feature",
  "properties": {
    "iso:country":"DE",
    "sg:address":"Bahnhofstr. 36",
    "sg:city":"Vaterstetten",
    "sg:phone":"+49 8106/368590",
    "sg:postcode":"85591",
    "sg:province":"Bayern",
    "wof:name":"American Dental Supplies Vertrieb Von",
    "wof:placetype":"venue"
},
  "geometry": {"coordinates":[11.765721,48.104671],"type":"Point"}
}