{
  "type": "Feature",
  "properties": {
    "iso:country":"DE",
    "sg:address":"Stiftsstr. 31",
    "sg:city":"Kerpen",
    "sg:phone":"+49 2237/52496",
    "sg:postcode":"50171",
    "sg:province":"Nordrhein-Westfalen",
    "wof:name":"Bei Majda",
    "wof:placetype":"venue"
},
  "geometry": {"coordinates":[6.6925120354,50.868637085],"type":"Point"}
}