{
  "type": "Feature",
  "properties": {
    "iso:country":"DE",
    "sg:address":"Ritterstr. 51",
    "sg:city":"L\u00f6rrach",
    "sg:phone":"+49 7621/5045",
    "sg:postcode":"79541",
    "sg:province":"Baden-W\u00fcrttemberg",
    "wof:name":"Siegfried Delzer Ingenieur",
    "wof:placetype":"venue"
},
  "geometry": {"coordinates":[7.6725921631,47.6387214661],"type":"Point"}
}