{
  "type": "Feature",
  "properties": {
    "iso:country":"DE",
    "sg:address":"Rambichler Str. 6",
    "sg:city":"Taching",
    "sg:postcode":"83373",
    "sg:province":"Bayern",
    "wof:name":"Joung Ja Dannhorn Heilpraktikerin",
    "wof:placetype":"venue"
},
  "geometry": {"coordinates":[12.7281112671,47.9589881897],"type":"Point"}
}