{
  "type": "Feature",
  "properties": {
    "iso:country":"DE",
    "sg:address":"Kreuzstr. 11",
    "sg:city":"Neuwied",
    "sg:phone":"+49 2631/352477",
    "sg:postcode":"56564",
    "sg:province":"Rheinland-Pfalz",
    "wof:name":"Bernhard Sch\u00f6lzel Steuerberater",
    "wof:placetype":"venue"
},
  "geometry": {"coordinates":[7.4775700569,50.4264602661],"type":"Point"}
}