{
  "type": "Feature",
  "properties": {
    "iso:country":"DE",
    "sg:address":"Steinweg 8",
    "sg:city":"Halle",
    "sg:phone":"+49 345/503870",
    "sg:postcode":"06110",
    "sg:province":"Sachsen-Anhalt",
    "wof:name":"H\u00e4nschens Reisedienst Gmbh",
    "wof:placetype":"venue"
},
  "geometry": {"coordinates":[11.9705343246,51.4765472412],"type":"Point"}
}