{
  "type": "Feature",
  "properties": {
    "iso:country":"DE",
    "sg:address":"Haus Mariawald",
    "sg:city":"J\u00fclich",
    "sg:phone":"+49 2461/50045",
    "sg:postcode":"52428",
    "sg:province":"Nordrhein-Westfalen",
    "wof:name":"Heinrich Breuer",
    "wof:placetype":"venue"
},
  "geometry": {"coordinates":[6.386535,50.93269],"type":"Point"}
}