{
  "type": "Feature",
  "properties": {
    "iso:country":"DE",
    "sg:address":"Kastanienallee 10",
    "sg:city":"Langenhagen",
    "sg:phone":"+49 511/781113",
    "sg:postcode":"30851",
    "sg:province":"Niedersachsen",
    "wof:name":"Norbert Otte Krankengymnast",
    "wof:placetype":"venue"
},
  "geometry": {"coordinates":[9.731005,52.43742],"type":"Point"}
}