{
  "type": "Feature",
  "properties": {
    "iso:country":"DE",
    "sg:address":"Gro\u00df Liederner Str. 4",
    "sg:city":"Wrestedt",
    "sg:phone":"+49 5825/472",
    "sg:postcode":"29559",
    "sg:province":"Niedersachsen",
    "wof:name":"Ernst Manthei",
    "wof:placetype":"venue"
},
  "geometry": {"coordinates":[10.64284,52.929554],"type":"Point"}
}