{
  "type": "Feature",
  "properties": {
    "iso:country":"DE",
    "sg:address":"Weezer Str. 147",
    "sg:city":"Kevelaer",
    "sg:phone":"+49 2832/6070",
    "sg:postcode":"47623",
    "sg:province":"Nordrhein-Westfalen",
    "wof:name":"Friesen Hochbau- Und Plattierungsgesellschaft",
    "wof:placetype":"venue"
},
  "geometry": {"coordinates":[6.2377347946,51.5914535522],"type":"Point"}
}