{
  "type": "Feature",
  "properties": {
    "iso:country":"DE",
    "sg:address":"Schulstr. 30",
    "sg:city":"Wermelskirchen",
    "sg:phone":"+49 2196/80546",
    "sg:postcode":"42929",
    "sg:province":"Nordrhein-Westfalen",
    "wof:name":"Karl H. Hackl\u00e4nder",
    "wof:placetype":"venue"
},
  "geometry": {"coordinates":[7.2532229424,51.1061973572],"type":"Point"}
}