{
  "type": "Feature",
  "properties": {
    "iso:country":"DE",
    "sg:address":"Rennweg 8",
    "sg:city":"Kulmbach",
    "sg:phone":"+49 9221/76493",
    "sg:postcode":"95326",
    "sg:province":"Bayern",
    "wof:name":"Friedrich Weber",
    "wof:placetype":"venue"
},
  "geometry": {"coordinates":[11.4146299362,50.092048645],"type":"Point"}
}