{
  "type": "Feature",
  "properties": {
    "iso:country":"DE",
    "sg:address":"Tichauer Weg 10",
    "sg:city":"Duesseldorf",
    "sg:phone":"+49 700 4000 7777",
    "sg:postcode":"40231",
    "sg:province":"Nordrhein-Westfalen",
    "wof:name":"Gvb-duesseldorf",
    "wof:placetype":"venue"
},
  "geometry": {"coordinates":[6.8376550674,51.2195968628],"type":"Point"}
}