{
  "type": "Feature",
  "properties": {
    "iso:country":"DE",
    "sg:address":"Gartenfelder Str. 124",
    "sg:city":"Berlin",
    "sg:phone":"+49 30/3348667",
    "sg:postcode":"13599",
    "sg:province":"Berlin",
    "wof:name":"Esigo Eigenheim- Siedlungsgen. Eg",
    "wof:placetype":"venue"
},
  "geometry": {"coordinates":[13.235417366,52.5419044495],"type":"Point"}
}