{
  "type": "Feature",
  "properties": {
    "iso:country":"DE",
    "sg:address":"Auerbacher Str. 58",
    "sg:city":"Crinitzberg",
    "sg:phone":"+49 37462/5410",
    "sg:postcode":"08147",
    "sg:province":"Sachsen",
    "wof:name":"Goldenes Lamm",
    "wof:placetype":"venue"
},
  "geometry": {"coordinates":[12.5285549164,50.5672111511],"type":"Point"}
}