{
  "type": "Feature",
  "properties": {
    "iso:country":"DE",
    "sg:address":"Weinligstr. 18 -20",
    "sg:city":"Soltau",
    "sg:phone":"+49 5191/3944",
    "sg:postcode":"29614",
    "sg:province":"Niedersachsen",
    "wof:name":"Frank Sanowski Heilpraktiker",
    "wof:placetype":"venue"
},
  "geometry": {"coordinates":[9.836807251,52.9797973633],"type":"Point"}
}