{
  "type": "Feature",
  "properties": {
    "iso:country":"DE",
    "sg:address":"Am Scheuelberg 12",
    "sg:city":"Heubach",
    "sg:phone":"+49 7173/2003",
    "sg:postcode":"73540",
    "sg:province":"Baden-W\u00fcrttemberg",
    "wof:name":"Heinz G. M\u00fcller Industrie- Und Handelsver-",
    "wof:placetype":"venue"
},
  "geometry": {"coordinates":[9.9278697968,48.784538269],"type":"Point"}
}