{
  "type": "Feature",
  "properties": {
    "iso:country":"DE",
    "sg:address":"Pascalstr. 71",
    "sg:city":"Aachen",
    "sg:postcode":"52076",
    "sg:province":"Nordrhein-Westfalen",
    "wof:name":"Cycloid Engineering Gmbh",
    "wof:placetype":"venue"
},
  "geometry": {"coordinates":[6.1448202133,50.7149276733],"type":"Point"}
}