{
  "type": "Feature",
  "properties": {
    "iso:country":"DE",
    "sg:address":"Bonner Str. 90",
    "sg:city":"D\u00fcsseldorf",
    "sg:phone":"+49 211/791533",
    "sg:postcode":"40589",
    "sg:province":"Nordrhein-Westfalen",
    "wof:name":"Horst M\u00fcller",
    "wof:placetype":"venue"
},
  "geometry": {"coordinates":[6.8375601768,51.1716346741],"type":"Point"}
}