{
  "type": "Feature",
  "properties": {
    "iso:country":"DE",
    "sg:address":"Theodor-Heuss-Str. 4",
    "sg:city":"Weinheim",
    "sg:phone":"+49 6201/65323",
    "sg:postcode":"69469",
    "sg:province":"Baden-W\u00fcrttemberg",
    "wof:name":"Heinrich Adam Gmbh",
    "wof:placetype":"venue"
},
  "geometry": {"coordinates":[8.6367282867,49.5424499512],"type":"Point"}
}