{
  "type": "Feature",
  "properties": {
    "iso:country":"DE",
    "sg:address":"Marktstr. 41",
    "sg:city":"Essen",
    "sg:phone":"+49 201/677231",
    "sg:postcode":"45355",
    "sg:province":"Nordrhein-Westfalen",
    "wof:name":"Sanit\u00e4tshaus Bach Ohg",
    "wof:placetype":"venue"
},
  "geometry": {"coordinates":[6.952538,51.475555],"type":"Point"}
}