{
  "type": "Feature",
  "properties": {
    "iso:country":"DE",
    "sg:address":"Geschwisterstr. 17",
    "sg:city":"B\u00fcnde",
    "sg:phone":"+49 5223/60104",
    "sg:postcode":"32257",
    "sg:province":"Nordrhein-Westfalen",
    "wof:name":"G\u00fcnter Bollmann Industrievertretungen Gmbh",
    "wof:placetype":"venue"
},
  "geometry": {"coordinates":[8.5102920532,52.2081756592],"type":"Point"}
}