{
  "type": "Feature",
  "properties": {
    "iso:country":"DE",
    "sg:address":"Bauernweg 11",
    "sg:city":"Osterfeld",
    "sg:phone":"+49 34422/21533",
    "sg:postcode":"06721",
    "sg:province":"Sachsen-Anhalt",
    "wof:name":"Dietrich Venus",
    "wof:placetype":"venue"
},
  "geometry": {"coordinates":[11.92472,51.083797],"type":"Point"}
}