{
  "type": "Feature",
  "properties": {
    "iso:country":"DE",
    "sg:address":"Birkenweg 8",
    "sg:city":"Heubach-Buch",
    "sg:phone":"+49 7173",
    "sg:postcode":"73540",
    "sg:province":"Baden-W\u00fcrttemberg",
    "wof:name":"Dipl. Ing. Jochen Biegon",
    "wof:placetype":"venue"
},
  "geometry": {"coordinates":[9.9122104645,48.79347229],"type":"Point"}
}