{
  "type": "Feature",
  "properties": {
    "iso:country":"DE",
    "sg:address":"Sonnenstr. 3",
    "sg:city":"Margetsh\u00f6chheim",
    "sg:phone":"+49 931/461044",
    "sg:postcode":"97276",
    "sg:province":"Bayern",
    "wof:name":"Walter H\u00f6pfinger",
    "wof:placetype":"venue"
},
  "geometry": {"coordinates":[9.8604459763,49.8348426819],"type":"Point"}
}