{
  "type": "Feature",
  "properties": {
    "iso:country":"DE",
    "sg:address":"Zettmannsdorfer Str. 32",
    "sg:city":"Sch\u00f6nbrunn",
    "sg:phone":"+49 9546/1236",
    "sg:postcode":"96185",
    "sg:province":"Bayern",
    "wof:name":"Willi Und Peter Scharf",
    "wof:placetype":"venue"
},
  "geometry": {"coordinates":[10.6896820068,49.8566818237],"type":"Point"}
}