{
  "type": "Feature",
  "properties": {
    "iso:country":"DE",
    "sg:address":"Im Bannholz 8",
    "sg:city":"St Martin",
    "sg:phone":"+49 6323/6698",
    "sg:postcode":"67487",
    "sg:province":"Rheinland-Pfalz",
    "wof:name":"Angler Baustahlarmierungs Gmbh",
    "wof:placetype":"venue"
},
  "geometry": {"coordinates":[8.1079969406,49.3028488159],"type":"Point"}
}