{
  "type": "Feature",
  "properties": {
    "iso:country":"DE",
    "sg:address":"Steinbruch 1",
    "sg:city":"Alzenau",
    "sg:phone":"+49 6023/4538",
    "sg:postcode":"63755",
    "sg:province":"Bayern",
    "wof:name":"Discothek Pan",
    "wof:placetype":"venue"
},
  "geometry": {"coordinates":[9.031874,50.0853],"type":"Point"}
}