{
  "type": "Feature",
  "properties": {
    "iso:country":"DE",
    "sg:address":"Georg-Ohm-Str. 8",
    "sg:city":"Stockelsdorf",
    "sg:phone":"+49 451/491193",
    "sg:postcode":"23617",
    "sg:province":"Schleswig-Holstein",
    "wof:name":"Hans Stutz",
    "wof:placetype":"venue"
},
  "geometry": {"coordinates":[10.64692,53.90583],"type":"Point"}
}