{
  "type": "Feature",
  "properties": {
    "iso:country":"DE",
    "sg:address":"Richard-Strauss-Str. 37 b",
    "sg:city":"Suhl",
    "sg:phone":"+49 3681/721778",
    "sg:postcode":"98529",
    "sg:province":"Th\u00fcringen",
    "wof:name":"Dr. Med. Sigrid Berszin",
    "wof:placetype":"venue"
},
  "geometry": {"coordinates":[10.6685,50.612099],"type":"Point"}
}