{
  "type": "Feature",
  "properties": {
    "iso:country":"DE",
    "sg:address":"Adlerhorst 9",
    "sg:city":"Hamburg",
    "sg:phone":"+49 40/5510031",
    "sg:postcode":"22459",
    "sg:province":"Hamburg",
    "wof:name":"Monika Edeler",
    "wof:placetype":"venue"
},
  "geometry": {"coordinates":[9.954057,53.63126],"type":"Point"}
}