{
  "type": "Feature",
  "properties": {
    "iso:country":"DE",
    "sg:address":"Glockenfeld 24",
    "sg:city":"Herdorf",
    "sg:phone":"+49 2744/6561",
    "sg:postcode":"57562",
    "sg:province":"Rheinland-Pfalz",
    "wof:name":"E. O. Meyer Kunst- Und Bauschlosserei",
    "wof:placetype":"venue"
},
  "geometry": {"coordinates":[7.9444799423,50.7763824463],"type":"Point"}
}