{
  "type": "Feature",
  "properties": {
    "iso:country":"DE",
    "sg:address":"Am Bach 21",
    "sg:city":"Osterwald",
    "sg:phone":"+49 5941/1360",
    "sg:postcode":"49828",
    "sg:province":"Niedersachsen",
    "wof:name":"Jan Zwiens",
    "wof:placetype":"venue"
},
  "geometry": {"coordinates":[7.0267138481,52.5278282166],"type":"Point"}
}