{
  "type": "Feature",
  "properties": {
    "iso:country":"DE",
    "sg:address":"F\u00fcssener Str. 12",
    "sg:city":"Peiting",
    "sg:phone":"+49 8861/59555",
    "sg:postcode":"86971",
    "sg:province":"Bayern",
    "wof:name":"J. Schelkle",
    "wof:placetype":"venue"
},
  "geometry": {"coordinates":[10.9200782776,47.7951469421],"type":"Point"}
}