{
  "type": "Feature",
  "properties": {
    "iso:country":"DE",
    "sg:address":"Berliner Platz 10",
    "sg:city":"W\u00fcrzburg",
    "sg:phone":"+49 931/3555055",
    "sg:postcode":"97080",
    "sg:province":"Bayern",
    "wof:name":"Eureal Treuhand Gmbh",
    "wof:placetype":"venue"
},
  "geometry": {"coordinates":[9.9433193207,49.7996330261],"type":"Point"}
}