{
  "type": "Feature",
  "properties": {
    "iso:country":"DE",
    "sg:address":"Klosterstr. 11",
    "sg:city":"J\u00fclich",
    "sg:phone":"+49 2463/3858",
    "sg:postcode":"52428",
    "sg:province":"Nordrhein-Westfalen",
    "wof:name":"Lina Und Eckart R\u00f6mer",
    "wof:placetype":"venue"
},
  "geometry": {"coordinates":[6.419798,50.951996],"type":"Point"}
}