{
  "type": "Feature",
  "properties": {
    "iso:country":"DE",
    "sg:address":"Kuglmoosstr. 8",
    "sg:city":"Stephanskirchen",
    "sg:phone":"+49 8031/27857",
    "sg:postcode":"83071",
    "sg:province":"Bayern",
    "wof:name":"Georg Weissacher",
    "wof:placetype":"venue"
},
  "geometry": {"coordinates":[12.1484794617,47.856842041],"type":"Point"}
}