{
  "type": "Feature",
  "properties": {
    "iso:country":"DE",
    "sg:address":"Schlott 12",
    "sg:city":"Hollingstedt",
    "sg:postcode":"24876",
    "sg:province":"Schleswig-Holstein",
    "wof:name":"Meltz-bau Gmbh",
    "wof:placetype":"venue"
},
  "geometry": {"coordinates":[9.339105,54.454956],"type":"Point"}
}