{
  "type": "Feature",
  "properties": {
    "iso:country":"DE",
    "sg:address":"Karl-Liebknecht-Str. 9",
    "sg:city":"Nerchau",
    "sg:phone":"+49 34382/41989",
    "sg:postcode":"04685",
    "sg:province":"Sachsen",
    "wof:name":"W. Grimm",
    "wof:placetype":"venue"
},
  "geometry": {"coordinates":[12.8099651337,51.2720375061],"type":"Point"}
}