{
  "type": "Feature",
  "properties": {
    "iso:country":"DE",
    "sg:address":"Hauptstr. 41",
    "sg:city":"Hirschau",
    "sg:phone":"+49 9622/2160",
    "sg:postcode":"92242",
    "sg:province":"Bayern",
    "wof:name":"Schlo\u00df-apotheke Heidi Mauerer E. K.",
    "wof:placetype":"venue"
},
  "geometry": {"coordinates":[11.94753,49.544304],"type":"Point"}
}