{
  "type": "Feature",
  "properties": {
    "iso:country":"DE",
    "sg:address":"Rathenaustr. 13",
    "sg:city":"Neustadt",
    "sg:postcode":"07806",
    "sg:province":"Th\u00fcringen",
    "wof:name":"Smv Sport Marketing Verwaltungs Gmbh",
    "wof:placetype":"venue"
},
  "geometry": {"coordinates":[11.7363653183,50.7240753174],"type":"Point"}
}