{
  "type": "Feature",
  "properties": {
    "iso:country":"DE",
    "sg:address":"Kirchstr. 8",
    "sg:city":"Bad H\u00f6nningen",
    "sg:phone":"+49 2635/2508",
    "sg:postcode":"53557",
    "sg:province":"Rheinland-Pfalz",
    "wof:name":"Hotel K.-j. Elbern",
    "wof:placetype":"venue"
},
  "geometry": {"coordinates":[7.3071060181,50.5147666931],"type":"Point"}
}