{
  "type": "Feature",
  "properties": {
    "iso:country":"DE",
    "sg:address":"Riemsdorf 3",
    "sg:city":"Scharfenberg",
    "sg:postcode":"01665",
    "sg:province":"Sachsen",
    "wof:name":"Mlb Beteiligungsgesellschaft An Landwirtschaftl. Unter-",
    "wof:placetype":"venue"
},
  "geometry": {"coordinates":[13.456019,51.127983],"type":"Point"}
}