{
  "type": "Feature",
  "properties": {
    "iso:country":"DE",
    "sg:address":"Ernst-Th\u00e4lmann-Str. 24",
    "sg:city":"Siggelkow",
    "sg:phone":"+49 38724/20433",
    "sg:postcode":"19376",
    "sg:province":"Mecklenburg-Vorpommern",
    "wof:name":"Hans-werner M\u00fcller",
    "wof:placetype":"venue"
},
  "geometry": {"coordinates":[11.9408121109,53.3865203857],"type":"Point"}
}