{
  "type": "Feature",
  "properties": {
    "iso:country":"DE",
    "sg:address":"Austr. 3",
    "sg:city":"Leinzell",
    "sg:phone":"+49 7175/90054",
    "sg:postcode":"73575",
    "sg:province":"Baden-W\u00fcrttemberg",
    "wof:name":"G\u00fcnther Miller Handelsagentur Gmbh",
    "wof:placetype":"venue"
},
  "geometry": {"coordinates":[9.8736467361,48.848815918],"type":"Point"}
}