{
  "type": "Feature",
  "properties": {
    "iso:country":"DE",
    "sg:address":"Kienh\u00f6fe 8",
    "sg:city":"Pfaffenhofen",
    "sg:postcode":"85276",
    "sg:province":"Bayern",
    "wof:name":"Irchenhauser Bautr\u00e4ger Gmbh",
    "wof:placetype":"venue"
},
  "geometry": {"coordinates":[11.45575,48.544636],"type":"Point"}
}