{
  "type": "Feature",
  "properties": {
    "iso:country":"DE",
    "sg:address":"Schillerstr. 12",
    "sg:city":"Esslingen",
    "sg:phone":"+49 711/312098",
    "sg:postcode":"73728",
    "sg:province":"Baden-W\u00fcrttemberg",
    "wof:name":"W. Fritz Garten- Und Land-",
    "wof:placetype":"venue"
},
  "geometry": {"coordinates":[9.314337,48.734856],"type":"Point"}
}