{
  "type": "Feature",
  "properties": {
    "iso:country":"DE",
    "sg:address":"Adelbyer Kirchenweg 46",
    "sg:city":"Flensburg",
    "sg:phone":"+49 461/144060",
    "sg:postcode":"24943",
    "sg:province":"Schleswig-Holstein",
    "wof:name":"Rainer Gottburg Gmbh",
    "wof:placetype":"venue"
},
  "geometry": {"coordinates":[9.45373,54.790237],"type":"Point"}
}