{
  "type": "Feature",
  "properties": {
    "iso:country":"DE",
    "sg:address":"Leutstettener Str. 9",
    "sg:city":"Starnberg",
    "sg:phone":"+49 8151/73184",
    "sg:postcode":"82319",
    "sg:province":"Bayern",
    "wof:name":"Dr. Med. Albrecht K. Huber Arzt F\u00fcr Allgemeinmedizin",
    "wof:placetype":"venue"
},
  "geometry": {"coordinates":[11.3451919556,48.0017204285],"type":"Point"}
}