{
  "type": "Feature",
  "properties": {
    "iso:country":"DE",
    "sg:address":"Hauptstr. 75",
    "sg:city":"Wiedensahl",
    "sg:phone":"+49 5726/484",
    "sg:postcode":"31719",
    "sg:province":"Niedersachsen",
    "wof:name":"Gerhard Dreyer",
    "wof:placetype":"venue"
},
  "geometry": {"coordinates":[9.119545,52.382008],"type":"Point"}
}