{
  "type": "Feature",
  "properties": {
    "iso:country":"DE",
    "sg:address":"Mathildenstr. 1",
    "sg:city":"Enger",
    "sg:phone":"+49 5224/2258",
    "sg:postcode":"32130",
    "sg:province":"Nordrhein-Westfalen",
    "wof:name":"Wittekind-apotheke Inh. Ursula Knoch",
    "wof:placetype":"venue"
},
  "geometry": {"coordinates":[8.557947,52.138237],"type":"Point"}
}