{
  "type": "Feature",
  "properties": {
    "iso:country":"DE",
    "sg:address":"L\u00f6wensteiner Str. 4",
    "sg:city":"W\u00fcstenrot",
    "sg:phone":"+49 7945/2255",
    "sg:postcode":"71543",
    "sg:province":"Baden-W\u00fcrttemberg",
    "wof:name":"White Horse",
    "wof:placetype":"venue"
},
  "geometry": {"coordinates":[9.4620628357,49.0823707581],"type":"Point"}
}