{
  "type": "Feature",
  "properties": {
    "iso:country":"DE",
    "sg:address":"Katharinenstr. 45 A",
    "sg:city":"Mannheim",
    "sg:phone":"+49 621/8544404",
    "sg:postcode":"68199",
    "sg:province":"Baden-W\u00fcrttemberg",
    "wof:name":"Ges\u00e4nger Rechtsanwalt",
    "wof:placetype":"venue"
},
  "geometry": {"coordinates":[8.4888753891,49.4563713074],"type":"Point"}
}