{
  "type": "Feature",
  "properties": {
    "iso:country":"DE",
    "sg:address":"Schottgasse 21",
    "sg:city":"Bornheim",
    "sg:phone":"+49 2227/924531",
    "sg:postcode":"53332",
    "sg:province":"Nordrhein-Westfalen",
    "wof:name":"Busch Schallschutzisolierung Und Bautenschutz Gmbh",
    "wof:placetype":"venue"
},
  "geometry": {"coordinates":[6.917716,50.779835],"type":"Point"}
}