{
  "type": "Feature",
  "properties": {
    "iso:country":"DE",
    "sg:address":"Hohe Looge 8",
    "sg:city":"Rastede",
    "sg:phone":"+49 4402/9750",
    "sg:postcode":"26180",
    "sg:province":"Niedersachsen",
    "wof:name":"B\u00fcsing & Fasch Gmbh & Co.",
    "wof:placetype":"venue"
},
  "geometry": {"coordinates":[8.172759,53.275753],"type":"Point"}
}