{
  "type": "Feature",
  "properties": {
    "iso:country":"DE",
    "sg:address":"R\u00f6merstr. 129",
    "sg:city":"Lampertheim",
    "sg:phone":"+49 6206/57007",
    "sg:postcode":"68623",
    "sg:province":"Hessen",
    "wof:name":"A & P Steuerberatungsges. Mbh",
    "wof:placetype":"venue"
},
  "geometry": {"coordinates":[8.4630823135,49.5956954956],"type":"Point"}
}