{
  "type": "Feature",
  "properties": {
    "iso:country":"DE",
    "sg:address":"Fuhrenkamp 12",
    "sg:city":"Isernhagen",
    "sg:phone":"+49 5139/6451",
    "sg:postcode":"30916",
    "sg:province":"Niedersachsen",
    "wof:name":"Atk Antennentechnik-und Kabelfernseh Gmbh",
    "wof:placetype":"venue"
},
  "geometry": {"coordinates":[9.882186,52.451855],"type":"Point"}
}