{
  "type": "Feature",
  "properties": {
    "iso:country":"DE",
    "sg:address":"Johann-Kotschwara-Str. 4",
    "sg:city":"Unterschlei\u00dfheim",
    "sg:phone":"+49 89/3740650",
    "sg:postcode":"85716",
    "sg:province":"Bayern",
    "wof:name":"X-fashion Sportbekleidung Gmbh",
    "wof:placetype":"venue"
},
  "geometry": {"coordinates":[11.5778102875,48.2885856628],"type":"Point"}
}