{
  "type": "Feature",
  "properties": {
    "iso:country":"DE",
    "sg:address":"Josefstaler Str. 6",
    "sg:city":"St. Ingbert",
    "sg:phone":"+49 6894/383338",
    "sg:postcode":"66386",
    "sg:province":"Saarland",
    "wof:name":"Hans-dieter Nagel",
    "wof:placetype":"venue"
},
  "geometry": {"coordinates":[7.114933,49.282143],"type":"Point"}
}