{
  "type": "Feature",
  "properties": {
    "iso:country":"DE",
    "sg:address":"Flensburger Str. 4",
    "sg:city":"Leck",
    "sg:phone":"+49 4662/1462",
    "sg:postcode":"25917",
    "sg:province":"Schleswig-Holstein",
    "wof:name":"Anke Gitte-nissen",
    "wof:placetype":"venue"
},
  "geometry": {"coordinates":[8.977437,54.769337],"type":"Point"}
}