{
  "type": "Feature",
  "properties": {
    "iso:country":"DE",
    "sg:address":"Sachsenstr. 40b",
    "sg:city":"Weinheim",
    "sg:phone":"+49 6201/58595",
    "sg:postcode":"69469",
    "sg:province":"Baden-W\u00fcrttemberg",
    "wof:name":"Theresa Stumpe",
    "wof:placetype":"venue"
},
  "geometry": {"coordinates":[8.668754,49.518448],"type":"Point"}
}