{
  "type": "Feature",
  "properties": {
    "iso:country":"DE",
    "sg:address":"N\u00fcrnberger Str. 47",
    "sg:city":"W\u00fcrzburg",
    "sg:phone":"+49 931/250520",
    "sg:postcode":"97076",
    "sg:province":"Bayern",
    "wof:name":"Blue M\u00f6bel Handelsges. Mbh",
    "wof:placetype":"venue"
},
  "geometry": {"coordinates":[9.9619016647,49.7967681885],"type":"Point"}
}