{
  "type": "Feature",
  "properties": {
    "iso:country":"DE",
    "sg:address":"Wirknerstr. 17",
    "sg:city":"Gelsenkirchen",
    "sg:phone":"+49 209/798325",
    "sg:postcode":"45891",
    "sg:province":"Nordrhein-Westfalen",
    "wof:name":"Ingmar Sch\u00e4fer",
    "wof:placetype":"venue"
},
  "geometry": {"coordinates":[7.077146,51.558964],"type":"Point"}
}