{
  "type": "Feature",
  "properties": {
    "iso:country":"DE",
    "sg:address":"Moerser Str. 123",
    "sg:city":"Rheinberg",
    "sg:postcode":"47495",
    "sg:province":"Nordrhein-Westfalen",
    "wof:name":"Landschaftsverband Rheinland Autobahnmeisterei",
    "wof:placetype":"venue"
},
  "geometry": {"coordinates":[6.6048469543,51.5327415466],"type":"Point"}
}