{
  "type": "Feature",
  "properties": {
    "iso:country":"DE",
    "sg:address":"Hepernstr. 8",
    "sg:city":"B\u00fcren",
    "sg:phone":"+49 2958/342",
    "sg:postcode":"33142",
    "sg:province":"Nordrhein-Westfalen",
    "wof:name":"A. H\u00fcpping",
    "wof:placetype":"venue"
},
  "geometry": {"coordinates":[8.5801048279,51.5038719177],"type":"Point"}
}