{
  "type": "Feature",
  "properties": {
    "iso:country":"DE",
    "sg:address":"Schlo\u00dfstr. 33",
    "sg:city":"Koblenz",
    "sg:phone":"+49 261/38466",
    "sg:postcode":"56068",
    "sg:province":"Rheinland-Pfalz",
    "wof:name":"Kodi Diskontl\u00e4den Gmbh",
    "wof:placetype":"venue"
},
  "geometry": {"coordinates":[7.5950908661,50.3565673828],"type":"Point"}
}