{
  "type": "Feature",
  "properties": {
    "iso:country":"DE",
    "sg:address":"Sophie-Immeyer-Str. 56 b",
    "sg:city":"Osnabr\u00fcck",
    "sg:phone":"+49 541/85561",
    "sg:postcode":"49080",
    "sg:province":"Niedersachsen",
    "wof:name":"Klaus Michel",
    "wof:placetype":"venue"
},
  "geometry": {"coordinates":[8.041368,52.253571],"type":"Point"}
}