{
  "type": "Feature",
  "properties": {
    "iso:country":"DE",
    "sg:address":"Felix-Meindl-Weg 8",
    "sg:city":"Landshut",
    "sg:phone":"+49 871/44563",
    "sg:postcode":"84036",
    "sg:province":"Bayern",
    "wof:name":"Ernst Lamprecht",
    "wof:placetype":"venue"
},
  "geometry": {"coordinates":[12.1464796066,48.5244750977],"type":"Point"}
}