{
  "type": "Feature",
  "properties": {
    "iso:country":"DE",
    "sg:address":"Blumenrather Str. 82",
    "sg:city":"Alsdorf",
    "sg:phone":"+49 2404/61590",
    "sg:postcode":"52477",
    "sg:province":"Nordrhein-Westfalen",
    "wof:name":"Karl Heinz Gielen E. K.",
    "wof:placetype":"venue"
},
  "geometry": {"coordinates":[6.186422,50.860184],"type":"Point"}
}