{
  "type": "Feature",
  "properties": {
    "iso:country":"DE",
    "sg:address":"Dorfstr. 63 a",
    "sg:city":"Eineborn",
    "sg:phone":"+49 36426/21391",
    "sg:postcode":"07646",
    "sg:province":"Th\u00fcringen",
    "wof:name":"Hadasch Gmbh",
    "wof:placetype":"venue"
},
  "geometry": {"coordinates":[11.8578367233,50.8306083679],"type":"Point"}
}