{
  "type": "Feature",
  "properties": {
    "iso:country":"DE",
    "sg:address":"Albiger Str 55",
    "sg:city":"Alzey",
    "sg:phone":"+49 6731/7087",
    "sg:postcode":"55232",
    "sg:province":"Rheinland-Pfalz",
    "wof:name":"H. Mann",
    "wof:placetype":"venue"
},
  "geometry": {"coordinates":[8.1184530258,49.7564163208],"type":"Point"}
}