{
  "type": "Feature",
  "properties": {
    "iso:country":"DE",
    "sg:address":"Lange Br\u00fcckstr. 3",
    "sg:city":"Preetz",
    "sg:phone":"+49 4342/1865",
    "sg:postcode":"24211",
    "sg:province":"Schleswig-Holstein",
    "wof:name":"Walter Schnell Drogerie",
    "wof:placetype":"venue"
},
  "geometry": {"coordinates":[10.28226,54.235321],"type":"Point"}
}