{
  "type": "Feature",
  "properties": {
    "iso:country":"DE",
    "sg:address":"Gottlieb-Fecht-Str. 18b",
    "sg:city":"Kehl",
    "sg:phone":"+49 7851/1777",
    "sg:postcode":"77694",
    "sg:province":"Baden-W\u00fcrttemberg",
    "wof:name":"Werner Huck",
    "wof:placetype":"venue"
},
  "geometry": {"coordinates":[7.875886,48.569176],"type":"Point"}
}