{
  "type": "Feature",
  "properties": {
    "iso:country":"DE",
    "sg:address":"Rotdornallee 35a",
    "sg:city":"Michendorf",
    "sg:phone":"+49 33203/79404",
    "sg:postcode":"14552",
    "sg:province":"Brandenburg",
    "wof:name":"A. Schneider",
    "wof:placetype":"venue"
},
  "geometry": {"coordinates":[13.00809,52.311058],"type":"Point"}
}