{
  "type": "Feature",
  "properties": {
    "iso:country":"DE",
    "sg:address":"Br\u00fcckenstr. 1",
    "sg:city":"Mayen",
    "sg:phone":"+49 2651/3334",
    "sg:postcode":"56727",
    "sg:province":"Rheinland-Pfalz",
    "wof:name":"E. Moog Gmbh",
    "wof:placetype":"venue"
},
  "geometry": {"coordinates":[7.2246379852,50.3299102783],"type":"Point"}
}