{
  "type": "Feature",
  "properties": {
    "iso:country":"DE",
    "sg:address":"Bahnhofstr. 95",
    "sg:city":"Gl\u00f6wen",
    "sg:postcode":"19339",
    "sg:province":"Brandenburg",
    "wof:name":"M. Krause",
    "wof:placetype":"venue"
},
  "geometry": {"coordinates":[12.085593,52.911182],"type":"Point"}
}