{
  "type": "Feature",
  "properties": {
    "iso:country":"DE",
    "sg:address":"Bahnhofstr. 34",
    "sg:city":"Cadenberge",
    "sg:postcode":"21781",
    "sg:province":"Niedersachsen",
    "wof:name":"Aromikus Gro\u00dfhandelsges. Mbh",
    "wof:placetype":"venue"
},
  "geometry": {"coordinates":[9.0566396713,53.7692108154],"type":"Point"}
}