{
  "type": "Feature",
  "properties": {
    "iso:country":"DE",
    "sg:address":"Alte Rabenstr. 11",
    "sg:city":"Hamburg",
    "sg:phone":"+49 40/417635",
    "sg:postcode":"20148",
    "sg:province":"Hamburg",
    "wof:name":"Rohstoffhandel Hansa Gmbh",
    "wof:placetype":"venue"
},
  "geometry": {"coordinates":[9.9971570969,53.5667724609],"type":"Point"}
}