{
  "type": "Feature",
  "properties": {
    "iso:country":"DE",
    "sg:address":"Helfendorfer Str. 2",
    "sg:city":"Valley",
    "sg:phone":"+49 8095/1819",
    "sg:postcode":"83626",
    "sg:province":"Bayern",
    "wof:name":"A. Schindler",
    "wof:placetype":"venue"
},
  "geometry": {"coordinates":[11.7862005234,47.9280128479],"type":"Point"}
}