{
  "type": "Feature",
  "properties": {
    "iso:country":"DE",
    "sg:address":"Aichenrain 10",
    "sg:city":"Sulzbach-Laufen",
    "sg:phone":"+49 7976/331",
    "sg:postcode":"74429",
    "sg:province":"Baden-W\u00fcrttemberg",
    "wof:name":"K\u00f6ger Gmbh",
    "wof:placetype":"venue"
},
  "geometry": {"coordinates":[9.8708620071,48.9515533447],"type":"Point"}
}