{
  "type": "Feature",
  "properties": {
    "iso:country":"DE",
    "sg:address":"Poststr. 15",
    "sg:city":"Siegen",
    "sg:phone":"+49 271/4889191",
    "sg:postcode":"57076",
    "sg:province":"Nordrhein-Westfalen",
    "wof:name":"Optik-eckert Gmbh",
    "wof:placetype":"venue"
},
  "geometry": {"coordinates":[8.0252027512,50.8952789307],"type":"Point"}
}