{
  "type": "Feature",
  "properties": {
    "iso:country":"DE",
    "sg:address":"Puschkinstr. 52",
    "sg:city":"Schwerin",
    "sg:postcode":"19055",
    "sg:province":"Mecklenburg-Vorpommern",
    "wof:name":"Spandorf & Partner Kulturradio Gmbh",
    "wof:placetype":"venue"
},
  "geometry": {"coordinates":[11.414919,53.627876],"type":"Point"}
}