{
  "type": "Feature",
  "properties": {
    "iso:country":"DE",
    "sg:address":"Amselweg 2",
    "sg:city":"\u00d6pfingen",
    "sg:phone":"+49 7391/5769",
    "sg:postcode":"89614",
    "sg:province":"Baden-W\u00fcrttemberg",
    "wof:name":"Harald Mooshammer",
    "wof:placetype":"venue"
},
  "geometry": {"coordinates":[9.805841,48.287888],"type":"Point"}
}