{
  "type": "Feature",
  "properties": {
    "iso:country":"DE",
    "sg:address":"Lindenplatz 8",
    "sg:city":"Stendal",
    "sg:phone":"+49 3931/715279",
    "sg:postcode":"39576",
    "sg:province":"Sachsen-Anhalt",
    "wof:name":"Wilfried Schleusner",
    "wof:placetype":"venue"
},
  "geometry": {"coordinates":[11.8487920761,52.6220207214],"type":"Point"}
}