{
  "type": "Feature",
  "properties": {
    "iso:country":"DE",
    "sg:address":"Glockengie\u00dferwall 2",
    "sg:city":"Hamburg",
    "sg:phone":"+49 40/324529",
    "sg:postcode":"20095",
    "sg:province":"Hamburg",
    "wof:name":"Niemann Und H\u00e4nsch Rechtsanw\u00e4lte",
    "wof:placetype":"venue"
},
  "geometry": {"coordinates":[10.0017271042,53.5553665161],"type":"Point"}
}