{
  "type": "Feature",
  "properties": {
    "iso:country":"DE",
    "sg:address":"Eibenstr. 4",
    "sg:city":"Achim",
    "sg:postcode":"28832",
    "sg:province":"Niedersachsen",
    "wof:name":"Betriebsgesellschaft Kompo- Metal Metalltechnik",
    "wof:placetype":"venue"
},
  "geometry": {"coordinates":[9.0557060242,53.0011253357],"type":"Point"}
}