{
  "type": "Feature",
  "properties": {
    "iso:country":"DE",
    "sg:address":"Christian-Kunkel-Str. 3",
    "sg:city":"Haibach",
    "sg:postcode":"63808",
    "sg:province":"Bayern",
    "wof:name":"Sidcom Software Gmbh",
    "wof:placetype":"venue"
},
  "geometry": {"coordinates":[9.1995592117,49.9637832642],"type":"Point"}
}