{
  "type": "Feature",
  "properties": {
    "iso:country":"DE",
    "sg:address":"Zum Naabberg 15",
    "sg:city":"Weiden",
    "sg:phone":"+49 961/42900",
    "sg:postcode":"92637",
    "sg:province":"Bayern",
    "wof:name":"Hans Steinhilber",
    "wof:placetype":"venue"
},
  "geometry": {"coordinates":[12.13668,49.629131],"type":"Point"}
}