{
  "type": "Feature",
  "properties": {
    "iso:country":"DE",
    "sg:address":"Schwangaustra\u00dfe 29",
    "sg:city":"Augsburg",
    "sg:postcode":"86163",
    "sg:province":"Bayern",
    "wof:name":"Klaus Bauunternehmensgruppe (hoch- U.tiefbau, Immobilien)",
    "wof:placetype":"venue"
},
  "geometry": {"coordinates":[10.9431314468,48.3541717529],"type":"Point"}
}