{
  "type": "Feature",
  "properties": {
    "iso:country":"DE",
    "sg:address":"Dorfstr. 4",
    "sg:city":"Wolnzach",
    "sg:phone":"+49 8442/7163",
    "sg:postcode":"85283",
    "sg:province":"Bayern",
    "wof:name":"Josef Werther Elektroinstallation",
    "wof:placetype":"venue"
},
  "geometry": {"coordinates":[11.577755,48.57988],"type":"Point"}
}