{
  "type": "Feature",
  "properties": {
    "iso:country":"DE",
    "sg:address":"Zwieselstr. 3",
    "sg:city":"Teisendorf",
    "sg:phone":"+49 8666/7158",
    "sg:postcode":"83317",
    "sg:province":"Bayern",
    "wof:name":"Peter Dorfleitner",
    "wof:placetype":"venue"
},
  "geometry": {"coordinates":[12.820333,47.847878],"type":"Point"}
}