{
  "type": "Feature",
  "properties": {
    "iso:country":"DE",
    "sg:address":"Freiburger Str. 24",
    "sg:city":"Offenburg",
    "sg:phone":"+49 781/75996",
    "sg:postcode":"77652",
    "sg:province":"Baden-W\u00fcrttemberg",
    "wof:name":"Bernd Sikora",
    "wof:placetype":"venue"
},
  "geometry": {"coordinates":[7.934474,48.474007],"type":"Point"}
}