{
  "type": "Feature",
  "properties": {
    "iso:country":"DE",
    "sg:address":"Treinenfeld 10",
    "sg:city":"Trier",
    "sg:phone":"+49 651/10193",
    "sg:postcode":"54296",
    "sg:province":"Rheinland-Pfalz",
    "wof:name":"Thassilo Haneke Rechtsanwalt",
    "wof:placetype":"venue"
},
  "geometry": {"coordinates":[6.7075371742,49.7342185974],"type":"Point"}
}