{
  "type": "Feature",
  "properties": {
    "iso:country":"DE",
    "sg:address":"Buchenweg 39",
    "sg:city":"Rheinstetten",
    "sg:phone":"+49 721/951650",
    "sg:postcode":"76287",
    "sg:province":"Baden-W\u00fcrttemberg",
    "wof:name":"Mikrotec Mikrocomptersysteme- Automatisierungstechnik Gmbh",
    "wof:placetype":"venue"
},
  "geometry": {"coordinates":[8.288835,48.960033],"type":"Point"}
}