{
  "type": "Feature",
  "properties": {
    "iso:country":"DE",
    "sg:address":"Delmenhorster Str. 2",
    "sg:city":"Lemwerder",
    "sg:phone":"+49 421/671611",
    "sg:postcode":"27809",
    "sg:province":"Niedersachsen",
    "wof:name":"Hans-hinrich Meyer",
    "wof:placetype":"venue"
},
  "geometry": {"coordinates":[8.644879,53.117405],"type":"Point"}
}