{
  "type": "Feature",
  "properties": {
    "iso:country":"DE",
    "sg:address":"Adelheidstr. 2",
    "sg:city":"Augsburg",
    "sg:phone":"+49 821/883485",
    "sg:postcode":"86179",
    "sg:province":"Bayern",
    "wof:name":"W. Mayr",
    "wof:placetype":"venue"
},
  "geometry": {"coordinates":[10.899315834,48.3072242737],"type":"Point"}
}