{
  "type": "Feature",
  "properties": {
    "iso:country":"DE",
    "sg:address":"In Venheyde 4",
    "sg:city":"Wegberg",
    "sg:phone":"+49 2434/4642",
    "sg:postcode":"41844",
    "sg:province":"Nordrhein-Westfalen",
    "wof:name":"Walter Jans",
    "wof:placetype":"venue"
},
  "geometry": {"coordinates":[6.265453,51.176762],"type":"Point"}
}