{
  "type": "Feature",
  "properties": {
    "iso:country":"DE",
    "sg:address":"Rheinstr. 20",
    "sg:city":"Wesseling",
    "sg:phone":"+49 2236/5510",
    "sg:postcode":"50389",
    "sg:province":"Nordrhein-Westfalen",
    "wof:name":"Peter Linden",
    "wof:placetype":"venue"
},
  "geometry": {"coordinates":[7.013031,50.805035],"type":"Point"}
}