{
  "type": "Feature",
  "properties": {
    "iso:country":"DE",
    "sg:address":"Industriestr. 10 a",
    "sg:city":"Germering",
    "sg:phone":"+49 89/841010",
    "sg:postcode":"82110",
    "sg:province":"Bayern",
    "wof:name":"Tronn Direktmarketing Gmbh",
    "wof:placetype":"venue"
},
  "geometry": {"coordinates":[11.375019,48.131214],"type":"Point"}
}