{
  "type": "Feature",
  "properties": {
    "iso:country":"DE",
    "sg:address":"Am Peschkenhof 69",
    "sg:city":"Moers",
    "sg:phone":"+49 2841/22966",
    "sg:postcode":"47441",
    "sg:province":"Nordrhein-Westfalen",
    "wof:name":"Beate Dobrodziej",
    "wof:placetype":"venue"
},
  "geometry": {"coordinates":[6.5958619118,51.4460754395],"type":"Point"}
}