{
  "type": "Feature",
  "properties": {
    "iso:country":"DE",
    "sg:address":"Echternstr. 12",
    "sg:city":"Stadthagen",
    "sg:phone":"+49 5721/6019",
    "sg:postcode":"31655",
    "sg:province":"Niedersachsen",
    "wof:name":"Restaurant Viel-harmonie",
    "wof:placetype":"venue"
},
  "geometry": {"coordinates":[9.2043027878,52.3252906799],"type":"Point"}
}