{
  "type": "Feature",
  "properties": {
    "iso:country":"DE",
    "sg:address":"Luxemburger Str. 6",
    "sg:city":"Gro\u00dfmaischeid",
    "sg:phone":"+49 2689/5340",
    "sg:postcode":"56276",
    "sg:province":"Rheinland-Pfalz",
    "wof:name":"Walter Kern Containerdienst Gmbh",
    "wof:placetype":"venue"
},
  "geometry": {"coordinates":[7.633153,50.504326],"type":"Point"}
}