{
  "type": "Feature",
  "properties": {
    "iso:country":"DE",
    "sg:address":"Westbahnhofstr.",
    "sg:city":"Mayen",
    "sg:phone":"+49 2651/2021",
    "sg:postcode":"56727",
    "sg:province":"Rheinland-Pfalz",
    "wof:name":"Rosenbaum Holz Und Bauelemente Handels Gmbh",
    "wof:placetype":"venue"
},
  "geometry": {"coordinates":[7.2160968781,50.3281288147],"type":"Point"}
}