{
  "type": "Feature",
  "properties": {
    "iso:country":"DE",
    "sg:address":"Danziger Str. 48",
    "sg:city":"Schwaig",
    "sg:postcode":"90571",
    "sg:province":"Bayern",
    "wof:name":"Conetec Gmbh",
    "wof:placetype":"venue"
},
  "geometry": {"coordinates":[11.190162,49.467808],"type":"Point"}
}