{
  "type": "Feature",
  "properties": {
    "iso:country":"DE",
    "sg:address":"Hauptmarkt 1",
    "sg:city":"Trier",
    "sg:phone":"+49 651/48492",
    "sg:postcode":"54290",
    "sg:province":"Rheinland-Pfalz",
    "wof:name":"Richard Becker",
    "wof:placetype":"venue"
},
  "geometry": {"coordinates":[6.6417298317,49.7570152283],"type":"Point"}
}