{
  "type": "Feature",
  "properties": {
    "iso:country":"DE",
    "sg:address":"Bahnstr. 59",
    "sg:city":"M\u00f6rfelden-Walldorf",
    "sg:phone":"+49 6105/41409",
    "sg:postcode":"64546",
    "sg:province":"Hessen",
    "wof:name":"Odzakovic Gmbh",
    "wof:placetype":"venue"
},
  "geometry": {"coordinates":[8.573488,50.000629],"type":"Point"}
}