{
  "type": "Feature",
  "properties": {
    "iso:country":"DE",
    "sg:address":"August-Bebel-Str. 26",
    "sg:city":"Markkleeberg",
    "sg:phone":"+49 341/3585963",
    "sg:postcode":"04416",
    "sg:province":"Sachsen",
    "wof:name":"Dirk Menzel",
    "wof:placetype":"venue"
},
  "geometry": {"coordinates":[12.3635206223,51.277015686],"type":"Point"}
}