{
  "type": "Feature",
  "properties": {
    "iso:country":"DE",
    "sg:address":"Grabenstr. 39",
    "sg:city":"Crailsheim",
    "sg:phone":"+49 7951/7608",
    "sg:postcode":"74564",
    "sg:province":"Baden-W\u00fcrttemberg",
    "wof:name":"Spielhalle",
    "wof:placetype":"venue"
},
  "geometry": {"coordinates":[10.0698261261,49.1374664307],"type":"Point"}
}