{
  "type": "Feature",
  "properties": {
    "iso:country":"DE",
    "sg:address":"Vallstedter Str. 13",
    "sg:city":"Salzgitter",
    "sg:phone":"+49 5341/66165",
    "sg:postcode":"38229",
    "sg:province":"Niedersachsen",
    "wof:name":"Landhaus",
    "wof:placetype":"venue"
},
  "geometry": {"coordinates":[10.3542499542,52.1693954468],"type":"Point"}
}