{
  "type": "Feature",
  "properties": {
    "iso:country":"DE",
    "sg:address":"Wilhelmshavener Heerstr. 9-17",
    "sg:city":"Oldenburg",
    "sg:phone":"+49 441/9360936",
    "sg:postcode":"26125",
    "sg:province":"Niedersachsen",
    "wof:name":"Nord-mobil-leasing Beteiligungs Gmbh",
    "wof:placetype":"venue"
},
  "geometry": {"coordinates":[8.22964,53.1716],"type":"Point"}
}