{
  "type": "Feature",
  "properties": {
    "iso:country":"DE",
    "sg:address":"Dortmunder Str. 2",
    "sg:city":"Hagen",
    "sg:phone":"+49 2331/61986",
    "sg:postcode":"58099",
    "sg:province":"Nordrhein-Westfalen",
    "wof:name":"H. H\u00f6finghoff",
    "wof:placetype":"venue"
},
  "geometry": {"coordinates":[7.4697809219,51.3964538574],"type":"Point"}
}