{
  "type": "Feature",
  "properties": {
    "iso:country":"DE",
    "sg:address":"Gelbehirschstr. 10",
    "sg:city":"Frankfurt",
    "sg:phone":"+49 69/293472",
    "sg:postcode":"60313",
    "sg:province":"Hessen",
    "wof:name":"Little Angel",
    "wof:placetype":"venue"
},
  "geometry": {"coordinates":[8.6872615814,50.1153678894],"type":"Point"}
}