{
  "type": "Feature",
  "properties": {
    "iso:country":"DE",
    "sg:address":"Auer Str. 12",
    "sg:city":"Gr\u00fcnhain",
    "sg:phone":"+49 3774/62549",
    "sg:postcode":"08358",
    "wof:name":"Quelle Agentur Zwicker",
    "wof:placetype":"venue"
},
  "geometry": {"coordinates":[12.807567,50.579025],"type":"Point"}
}