{
  "type": "Feature",
  "properties": {
    "iso:country":"DE",
    "sg:address":"Velaskostr. 10",
    "sg:city":"Feldkirchen",
    "sg:phone":"+49 89/9032173",
    "sg:postcode":"85622",
    "sg:province":"Bayern",
    "wof:name":"Zell Gmbh & Co. Kg",
    "wof:placetype":"venue"
},
  "geometry": {"coordinates":[11.733173,48.151546],"type":"Point"}
}