{
  "type": "Feature",
  "properties": {
    "iso:country":"DE",
    "sg:address":"164er Ring 7",
    "sg:city":"Hameln",
    "sg:postcode":"31785",
    "sg:province":"Niedersachsen",
    "wof:name":"Bellevue Spielcenter Vergn\u00fcgungsst\u00e4tte",
    "wof:placetype":"venue"
},
  "geometry": {"coordinates":[9.362229,52.10704],"type":"Point"}
}