{
  "type": "Feature",
  "properties": {
    "iso:country":"DE",
    "sg:address":"Hintere Gasse 37",
    "sg:city":"Denkendorf",
    "sg:phone":"+49 711/3461204",
    "sg:postcode":"73770",
    "sg:province":"Baden-W\u00fcrttemberg",
    "wof:name":"Helmut Heinrich Kaffeemaschinenkundendienst",
    "wof:placetype":"venue"
},
  "geometry": {"coordinates":[9.3135242462,48.6941184998],"type":"Point"}
}