{
  "type": "Feature",
  "properties": {
    "iso:country":"DE",
    "sg:address":"Bahnhofstr. 63",
    "sg:city":"Renningen",
    "sg:phone":"+49 7159/920593",
    "sg:postcode":"71272",
    "sg:province":"Baden-W\u00fcrttemberg",
    "wof:name":"Hans Krau\u00df",
    "wof:placetype":"venue"
},
  "geometry": {"coordinates":[8.933015,48.773529],"type":"Point"}
}