{
  "type": "Feature",
  "properties": {
    "iso:country":"DE",
    "sg:address":"Pfarrer-Bonhoeffer-Str. 13",
    "sg:city":"Schlotheim",
    "sg:postcode":"99994",
    "sg:province":"Th\u00fcringen",
    "wof:name":"Katholisches Pfarramt Schlotheim",
    "wof:placetype":"venue"
},
  "geometry": {"coordinates":[10.6561822891,51.2401924133],"type":"Point"}
}