{
  "type": "Feature",
  "properties": {
    "iso:country":"DE",
    "sg:address":"Klecker Waldstr. 43",
    "sg:city":"Bendestorf",
    "sg:phone":"+49 4183/6469",
    "sg:postcode":"21227",
    "sg:province":"Niedersachsen",
    "wof:name":"Lissis",
    "wof:placetype":"venue"
},
  "geometry": {"coordinates":[9.966759,53.339401],"type":"Point"}
}