{
  "type": "Feature",
  "properties": {
    "iso:country":"DE",
    "sg:address":"Sch\u00f6nau 3",
    "sg:city":"Inchenhofen",
    "sg:phone":"+49 8257/780",
    "sg:postcode":"86570",
    "sg:province":"Bayern",
    "wof:name":"H. Und M. Zanker",
    "wof:placetype":"venue"
},
  "geometry": {"coordinates":[11.1114301682,48.5318031311],"type":"Point"}
}