{
  "type": "Feature",
  "properties": {
    "iso:country":"DE",
    "sg:address":"Erlenweg 5",
    "sg:city":"Schlier",
    "sg:phone":"+49 4975/2997190",
    "sg:postcode":"88281",
    "sg:province":"Baden-W\u00fcrttemberg",
    "wof:name":"Lippmann Gmbh Fleischwarenvertrieb Gmbh",
    "wof:placetype":"venue"
},
  "geometry": {"coordinates":[9.6933002472,47.8039283752],"type":"Point"}
}