{
  "type": "Feature",
  "properties": {
    "iso:country":"DE",
    "sg:address":"Osselerweg 17",
    "sg:city":"Borken",
    "sg:phone":"+49 2862/2629",
    "sg:postcode":"46325",
    "sg:province":"Nordrhein-Westfalen",
    "wof:name":"Josef Lensing",
    "wof:placetype":"venue"
},
  "geometry": {"coordinates":[6.854292,51.923187],"type":"Point"}
}