{
  "type": "Feature",
  "properties": {
    "iso:country":"DE",
    "sg:address":"Im Klott 6",
    "sg:city":"Oberderdingen",
    "sg:phone":"+49 7045/8690",
    "sg:postcode":"75038",
    "sg:province":"Baden-W\u00fcrttemberg",
    "wof:name":"C. V. Collection Villars Polsterm\u00f6bel-vertriebs Gmbh",
    "wof:placetype":"venue"
},
  "geometry": {"coordinates":[8.7740812302,49.0470046997],"type":"Point"}
}