{
  "type": "Feature",
  "properties": {
    "iso:country":"DE",
    "sg:address":"Dietersdorfer Str. 7",
    "sg:city":"Niedermurach",
    "sg:phone":"+49 9671/91494",
    "sg:postcode":"92545",
    "sg:province":"Bayern",
    "wof:name":"Josef Sch\u00e4ffer",
    "wof:placetype":"venue"
},
  "geometry": {"coordinates":[12.3782587051,49.4494476318],"type":"Point"}
}