{
  "type": "Feature",
  "properties": {
    "iso:country":"DE",
    "sg:address":"Angerstr. 2",
    "sg:city":"Emmerthal",
    "sg:phone":"+49 5286/498",
    "sg:postcode":"31860",
    "sg:province":"Niedersachsen",
    "wof:name":"F. Ilse",
    "wof:placetype":"venue"
},
  "geometry": {"coordinates":[9.372335,51.984001],"type":"Point"}
}