{
  "type": "Feature",
  "properties": {
    "iso:country":"DE",
    "sg:address":"Oststr. 16",
    "sg:city":"Hamm",
    "sg:phone":"+49 2381/20248",
    "sg:postcode":"59065",
    "sg:province":"Nordrhein-Westfalen",
    "wof:name":"I. Eleganz",
    "wof:placetype":"venue"
},
  "geometry": {"coordinates":[7.821274,51.681938],"type":"Point"}
}