{
  "type": "Feature",
  "properties": {
    "iso:country":"DE",
    "sg:address":"Am G\u00e4nsbach 11",
    "sg:city":"Gedern",
    "sg:phone":"+49 6045/1252",
    "sg:postcode":"63688",
    "sg:province":"Hessen",
    "wof:name":"Hermann Meuer & S\u00f6hne Ohg",
    "wof:placetype":"venue"
},
  "geometry": {"coordinates":[9.196783,50.420315],"type":"Point"}
}