{
  "type": "Feature",
  "properties": {
    "iso:country":"DE",
    "sg:address":"Fichtenweg 12",
    "sg:city":"Bad Griesbach",
    "sg:phone":"+49 8532/7688",
    "sg:postcode":"94086",
    "sg:province":"Bayern",
    "wof:name":"Detlef Reb Rechtsanwalt",
    "wof:placetype":"venue"
},
  "geometry": {"coordinates":[13.2051887512,48.4478607178],"type":"Point"}
}