{
  "type": "Feature",
  "properties": {
    "iso:country":"DE",
    "sg:address":"Mittlere Dorfstr. 1",
    "sg:city":"Seelitz",
    "sg:postcode":"09306",
    "sg:province":"Sachsen",
    "wof:name":"Gastronomie Streller Gmbh",
    "wof:placetype":"venue"
},
  "geometry": {"coordinates":[12.8367424011,51.0168609619],"type":"Point"}
}