{
  "type": "Feature",
  "properties": {
    "iso:country":"DE",
    "sg:address":"Ainmillerstr. 33",
    "sg:city":"M\u00fcnchen",
    "sg:phone":"+49 89/36100992",
    "sg:postcode":"80801",
    "sg:province":"Bayern",
    "wof:name":"Reiner Hellmann Rechtsanwalt",
    "wof:placetype":"venue"
},
  "geometry": {"coordinates":[11.5776395798,48.1588554382],"type":"Point"}
}