{
  "type": "Feature",
  "properties": {
    "iso:country":"DE",
    "sg:address":"Forchheimerstr. 2",
    "sg:city":"Passau",
    "sg:phone":"+49 851/94429024",
    "sg:postcode":"94034",
    "sg:province":"Bayern",
    "wof:name":"Die Welt Der Schwingungen",
    "wof:placetype":"venue"
},
  "geometry": {"coordinates":[13.465088,48.587254],"type":"Point"}
}