{
  "type": "Feature",
  "properties": {
    "iso:country":"DE",
    "sg:address":"Jungfernstieg 5",
    "sg:city":"Amelinghausen",
    "sg:phone":"+49 4132/241",
    "sg:postcode":"21385",
    "sg:province":"Niedersachsen",
    "wof:name":"R. Sch\u00fctze",
    "wof:placetype":"venue"
},
  "geometry": {"coordinates":[10.213783,53.126945],"type":"Point"}
}