{
  "type": "Feature",
  "properties": {
    "iso:country":"DE",
    "sg:address":"Kohlenstr. 4",
    "sg:city":"Annarode",
    "sg:phone":"+49 34772/27796",
    "sg:postcode":"06308",
    "sg:province":"Sachsen-Anhalt",
    "wof:name":"Monika Hornung",
    "wof:placetype":"venue"
},
  "geometry": {"coordinates":[11.4003515244,51.5511550903],"type":"Point"}
}