{
  "type": "Feature",
  "properties": {
    "iso:country":"DE",
    "sg:address":"Ruschwedeler Str. 20 a",
    "sg:city":"Harsefeld",
    "sg:phone":"+49 4164/859870",
    "sg:postcode":"21698",
    "sg:province":"Niedersachsen",
    "wof:name":"B\u00e4dorf & B\u00e4dorf Gmbh",
    "wof:placetype":"venue"
},
  "geometry": {"coordinates":[9.5650167465,53.4548149109],"type":"Point"}
}