{
  "type": "Feature",
  "properties": {
    "iso:country":"DE",
    "sg:address":"M\u00fchlberg 18",
    "sg:city":"Rainau",
    "sg:phone":"+49 7961/51750",
    "sg:postcode":"73492",
    "sg:province":"Baden-W\u00fcrttemberg",
    "wof:name":"Goldenes Lamm",
    "wof:placetype":"venue"
},
  "geometry": {"coordinates":[10.1447076797,48.9289321899],"type":"Point"}
}