{
  "type": "Feature",
  "properties": {
    "iso:country":"DE",
    "sg:address":"M\u00fchlenstr. 26",
    "sg:city":"Velten",
    "sg:phone":"+49 3304/502285",
    "sg:postcode":"16727",
    "sg:province":"Brandenburg",
    "wof:name":"Werner Fischer",
    "wof:placetype":"venue"
},
  "geometry": {"coordinates":[13.1701631546,52.6936302185],"type":"Point"}
}