{
  "type": "Feature",
  "properties": {
    "iso:country":"DE",
    "sg:address":"Mertensgasse 27",
    "sg:city":"D\u00fcsseldorf",
    "sg:phone":"+49 211/134294",
    "sg:postcode":"40213",
    "sg:province":"Nordrhein-Westfalen",
    "wof:name":"Schwarzer Peter Gastst\u00e4ttenbetriebs Gmbh",
    "wof:placetype":"venue"
},
  "geometry": {"coordinates":[6.773607,51.22625],"type":"Point"}
}