{
  "type": "Feature",
  "properties": {
    "iso:country":"DE",
    "sg:address":"Finkenweg 14",
    "sg:city":"Dreieich",
    "sg:phone":"+49 6103/87365",
    "sg:postcode":"63303",
    "sg:province":"Hessen",
    "wof:name":"Bernhard Kilb",
    "wof:placetype":"venue"
},
  "geometry": {"coordinates":[8.6981506348,50.0020027161],"type":"Point"}
}