{
  "type": "Feature",
  "properties": {
    "iso:country":"DE",
    "sg:address":"Gro\u00dfenbaumer Weg 6",
    "sg:city":"D\u00fcsseldorf",
    "sg:phone":"+49 211/418620",
    "sg:postcode":"40472",
    "sg:province":"Nordrhein-Westfalen",
    "wof:name":"The Adac Laboratories Gmbh",
    "wof:placetype":"venue"
},
  "geometry": {"coordinates":[6.78936,51.28788],"type":"Point"}
}