{
  "type": "Feature",
  "properties": {
    "iso:country":"DE",
    "sg:address":"Rott am Wald 6",
    "sg:city":"Eggenfelden",
    "sg:phone":"+49 8721/912290",
    "sg:postcode":"84307",
    "sg:province":"Bayern",
    "wof:name":"Apotheke K\u00f6tteritzsch",
    "wof:placetype":"venue"
},
  "geometry": {"coordinates":[12.739364,48.403793],"type":"Point"}
}