{
  "type": "Feature",
  "properties": {
    "iso:country":"DE",
    "sg:address":"Bismarckstr. 100",
    "sg:city":"Aachen",
    "sg:phone":"+49 241/500115",
    "sg:postcode":"52066",
    "sg:province":"Nordrhein-Westfalen",
    "wof:name":"Peter Salvini",
    "wof:placetype":"venue"
},
  "geometry": {"coordinates":[6.1072750092,50.7689361572],"type":"Point"}
}