{
  "type": "Feature",
  "properties": {
    "iso:country":"DE",
    "sg:address":"Tarodunumweg 7",
    "sg:city":"Kirchzarten",
    "sg:postcode":"79199",
    "sg:province":"Baden-W\u00fcrttemberg",
    "wof:name":"G\u00f6tz Handels Gmbh",
    "wof:placetype":"venue"
},
  "geometry": {"coordinates":[7.9811649323,47.9648208618],"type":"Point"}
}