{
  "type": "Feature",
  "properties": {
    "iso:country":"DE",
    "sg:address":"T\u00f6pferstr. 49",
    "sg:city":"Hoehr-Grenzhausen",
    "sg:postcode":"56203",
    "sg:province":"Rheinland-Pfalz",
    "wof:name":"Sybille Letschert Reinigungssysteme",
    "wof:placetype":"venue"
},
  "geometry": {"coordinates":[7.671537,50.437397],"type":"Point"}
}