{
  "type": "Feature",
  "properties": {
    "iso:country":"DE",
    "sg:address":"Paul-Klee-Str. 6",
    "sg:city":"Blankenfelde",
    "sg:phone":"+49 3379/375317",
    "sg:postcode":"15827",
    "sg:province":"Brandenburg",
    "wof:name":"Gartenlaube",
    "wof:placetype":"venue"
},
  "geometry": {"coordinates":[13.3956155777,52.3291091919],"type":"Point"}
}