{
  "type": "Feature",
  "properties": {
    "iso:country":"DE",
    "sg:address":"M\u00fchlenstr. 2",
    "sg:city":"Kipfenberg",
    "sg:phone":"+49 8465/1038",
    "sg:postcode":"85110",
    "sg:province":"Bayern",
    "wof:name":"A. Wagner",
    "wof:placetype":"venue"
},
  "geometry": {"coordinates":[11.3663444519,48.9121780396],"type":"Point"}
}