{
  "type": "Feature",
  "properties": {
    "iso:country":"DE",
    "sg:address":"Apothekerstr. 30",
    "sg:city":"Arnsberg",
    "sg:postcode":"59755",
    "sg:province":"Nordrhein-Westfalen",
    "wof:name":"Buco Mode Gmbh",
    "wof:placetype":"venue"
},
  "geometry": {"coordinates":[7.9655251503,51.451259613],"type":"Point"}
}