{
  "type": "Feature",
  "properties": {
    "iso:country":"DE",
    "sg:address":"Niederbachstr. 34",
    "sg:city":"Oberwesel",
    "sg:phone":"+49 6744/8922",
    "sg:postcode":"55430",
    "sg:province":"Rheinland-Pfalz",
    "wof:name":"Hubert Persch",
    "wof:placetype":"venue"
},
  "geometry": {"coordinates":[7.717818,50.110416],"type":"Point"}
}