{
  "type": "Feature",
  "properties": {
    "iso:country":"DE",
    "sg:address":"D\u00fclmener Str. 48",
    "sg:city":"Dorsten",
    "sg:phone":"+49 2369/4172",
    "sg:postcode":"46286",
    "sg:province":"Nordrhein-Westfalen",
    "wof:name":"Schonebeck Gmbh",
    "wof:placetype":"venue"
},
  "geometry": {"coordinates":[7.019402,51.721348],"type":"Point"}
}