{
  "type": "Feature",
  "properties": {
    "iso:country":"DE",
    "sg:address":"Am Tannenwaeldchen 9",
    "sg:city":"Hungen",
    "sg:phone":"+49 4964/022067",
    "sg:postcode":"35410",
    "sg:province":"Hessen",
    "wof:name":"Baugesellschaft Kroell Mit Beschraenkter Haftung",
    "wof:placetype":"venue"
},
  "geometry": {"coordinates":[8.910746,50.471649],"type":"Point"}
}