{
  "type": "Feature",
  "properties": {
    "iso:country":"DE",
    "sg:address":"K\u00f6lner Str. 145",
    "sg:city":"Neunkirchen",
    "sg:phone":"+49 2735/61467",
    "sg:postcode":"57290",
    "sg:province":"Nordrhein-Westfalen",
    "wof:name":"Andrea Flaschel",
    "wof:placetype":"venue"
},
  "geometry": {"coordinates":[7.9907579422,50.7862434387],"type":"Point"}
}