{
  "type": "Feature",
  "properties": {
    "iso:country":"DE",
    "sg:address":"Auf der H\u00fctung 33",
    "sg:city":"Oberhausen",
    "sg:phone":"+49 208/675427",
    "sg:postcode":"46147",
    "sg:province":"Nordrhein-Westfalen",
    "wof:name":"C. Teschner",
    "wof:placetype":"venue"
},
  "geometry": {"coordinates":[6.8333668709,51.5487442017],"type":"Point"}
}