{
  "type": "Feature",
  "properties": {
    "iso:country":"DE",
    "sg:address":"Hauptstr. 19",
    "sg:city":"Blomberg",
    "sg:phone":"+49 4977/263",
    "sg:postcode":"26487",
    "sg:province":"Niedersachsen",
    "wof:name":"H. Janssen",
    "wof:placetype":"venue"
},
  "geometry": {"coordinates":[7.559764,53.578934],"type":"Point"}
}