{
  "type": "Feature",
  "properties": {
    "iso:country":"DE",
    "sg:address":"Jakob-Degen-Str. 47",
    "sg:city":"Wallenfels",
    "sg:phone":"+49 9262/219",
    "sg:postcode":"96346",
    "sg:province":"Bayern",
    "wof:name":"J. Stumpf",
    "wof:placetype":"venue"
},
  "geometry": {"coordinates":[11.4789772034,50.264919281],"type":"Point"}
}