{
  "type": "Feature",
  "properties": {
    "iso:country":"DE",
    "sg:address":"Benzstr. 23",
    "sg:city":"Renningen",
    "sg:phone":"+49 4971/5916040",
    "sg:postcode":"71272",
    "sg:province":"Baden-W\u00fcrttemberg",
    "wof:name":"Bacher-tische M. + W. Bacher Gmbh",
    "wof:placetype":"venue"
},
  "geometry": {"coordinates":[8.9269180298,48.7768821716],"type":"Point"}
}