{
  "type": "Feature",
  "properties": {
    "iso:country":"DE",
    "sg:address":"Schmeerstr. 3",
    "sg:city":"Halle",
    "sg:phone":"+49 345/5211411",
    "sg:postcode":"06108",
    "sg:province":"Sachsen-Anhalt",
    "wof:name":"Pension Am Alten Markt",
    "wof:placetype":"venue"
},
  "geometry": {"coordinates":[11.9705410004,51.4817199707],"type":"Point"}
}