{
  "type": "Feature",
  "properties": {
    "iso:country":"DE",
    "sg:address":"Sonnemannstr. 50",
    "sg:city":"Uetz",
    "sg:phone":"+49 39366/351",
    "sg:postcode":"39517",
    "sg:province":"Sachsen-Anhalt",
    "wof:name":"Erich Neumann",
    "wof:placetype":"venue"
},
  "geometry": {"coordinates":[11.845721,52.366772],"type":"Point"}
}