{
  "type": "Feature",
  "properties": {
    "iso:country":"DE",
    "sg:address":"Hofstr. 9",
    "sg:city":"Ditzum",
    "sg:phone":"+49 4902/666",
    "sg:postcode":"26844",
    "sg:province":"Niedersachsen",
    "wof:name":"Sparkasse Leer-weener",
    "wof:placetype":"venue"
},
  "geometry": {"coordinates":[7.2787,53.315651],"type":"Point"}
}