{
  "type": "Feature",
  "properties": {
    "iso:country":"DE",
    "sg:address":"Kornwegerstr. 37",
    "sg:city":"M\u00fcnchen",
    "sg:phone":"+49 89/715070",
    "sg:postcode":"81375",
    "sg:province":"Bayern",
    "wof:name":"Aks Hartmann Gmbh",
    "wof:placetype":"venue"
},
  "geometry": {"coordinates":[11.4977169037,48.1149559021],"type":"Point"}
}