{
  "type": "Feature",
  "properties": {
    "iso:country":"DE",
    "sg:address":"Alt-Marienfelde 51 d",
    "sg:city":"Berlin",
    "sg:phone":"+49 30/7214468",
    "sg:postcode":"12277",
    "sg:province":"Berlin",
    "wof:name":"Reinhold Gerstetter",
    "wof:placetype":"venue"
},
  "geometry": {"coordinates":[13.364492,52.412941],"type":"Point"}
}