{
  "type": "Feature",
  "properties": {
    "iso:country":"DE",
    "sg:address":"Gartenweg 21",
    "sg:city":"R\u00fcthen",
    "sg:phone":"+49 2952/3526",
    "sg:postcode":"59602",
    "sg:province":"Nordrhein-Westfalen",
    "wof:name":"Josef Bitter",
    "wof:placetype":"venue"
},
  "geometry": {"coordinates":[8.434393,51.496243],"type":"Point"}
}