{
  "type": "Feature",
  "properties": {
    "iso:country":"DE",
    "sg:address":"Hauptstr. 22",
    "sg:city":"Hohn",
    "sg:phone":"+49 4335/274",
    "sg:postcode":"24806",
    "sg:province":"Schleswig-Holstein",
    "wof:name":"Pflege Lebensnah Ggmbh",
    "wof:placetype":"venue"
},
  "geometry": {"coordinates":[9.50694,54.300804],"type":"Point"}
}