{
  "type": "Feature",
  "properties": {
    "iso:country":"DE",
    "sg:address":"Meiswinkel 1 a",
    "sg:city":"K\u00fcrten",
    "sg:phone":"+49 2207/1832",
    "sg:postcode":"51515",
    "sg:province":"Nordrhein-Westfalen",
    "wof:name":"Hans Heider",
    "wof:placetype":"venue"
},
  "geometry": {"coordinates":[7.223504,51.019981],"type":"Point"}
}