{
  "type": "Feature",
  "properties": {
    "iso:country":"DE",
    "sg:address":"Merkelheider Weg 183",
    "sg:city":"Marl",
    "sg:phone":"+49 2365/923672",
    "sg:postcode":"45772",
    "sg:province":"Nordrhein-Westfalen",
    "wof:name":"Heike Berger Rechtsanw\u00e4ltin",
    "wof:placetype":"venue"
},
  "geometry": {"coordinates":[7.1376681328,51.684211731],"type":"Point"}
}