{
  "type": "Feature",
  "properties": {
    "iso:country":"DE",
    "sg:address":"Bahnhofstr. 30",
    "sg:city":"Immenstadt",
    "sg:phone":"+49 8323/4091",
    "sg:postcode":"87509",
    "sg:province":"Bayern",
    "wof:name":"Bayerische Vereinsbank Ag",
    "wof:placetype":"venue"
},
  "geometry": {"coordinates":[10.215677,47.559475],"type":"Point"}
}