{
  "type": "Feature",
  "properties": {
    "iso:country":"DE",
    "sg:address":"Webergasse 30",
    "sg:city":"Coburg",
    "sg:phone":"+49 9561/95944",
    "sg:postcode":"96450",
    "sg:province":"Bayern",
    "wof:name":"Weberst\u00fcbchen",
    "wof:placetype":"venue"
},
  "geometry": {"coordinates":[10.9641132355,50.2600822449],"type":"Point"}
}