{
  "type": "Feature",
  "properties": {
    "iso:country":"DE",
    "sg:address":"Ritterstr. 98",
    "sg:city":"Brandenburg",
    "sg:phone":"+49 3381/227671",
    "sg:postcode":"14770",
    "sg:province":"Brandenburg",
    "wof:name":"Altstadt Pub",
    "wof:placetype":"venue"
},
  "geometry": {"coordinates":[12.5535211563,52.412612915],"type":"Point"}
}