{
  "type": "Feature",
  "properties": {
    "iso:country":"DE",
    "sg:address":"Dorfstr. 8",
    "sg:city":"Evessen",
    "sg:phone":"+49 5333/8071",
    "sg:postcode":"38173",
    "sg:province":"Niedersachsen",
    "wof:name":"Cleanness And Safety Gmbh",
    "wof:placetype":"venue"
},
  "geometry": {"coordinates":[10.7087907791,52.1880073547],"type":"Point"}
}