{
  "type": "Feature",
  "properties": {
    "iso:country":"DE",
    "sg:address":"Untere M\u00fchlenstr. 14",
    "sg:city":"Bad Salzuflen",
    "sg:phone":"+49 5222/59364",
    "sg:postcode":"32105",
    "sg:province":"Nordrhein-Westfalen",
    "wof:name":"Dr. Gerhard B\u00fcnemann Dipl.-chem.",
    "wof:placetype":"venue"
},
  "geometry": {"coordinates":[8.7470645905,52.0852546692],"type":"Point"}
}