{
  "type": "Feature",
  "properties": {
    "iso:country":"DE",
    "sg:address":"Hexentaufe 3",
    "sg:city":"Essen",
    "sg:phone":"+49 201/440236",
    "sg:postcode":"45134",
    "sg:province":"Nordrhein-Westfalen",
    "wof:name":"Dr. Georg Von Wick",
    "wof:placetype":"venue"
},
  "geometry": {"coordinates":[7.0547509193,51.4279670715],"type":"Point"}
}