{
  "type": "Feature",
  "properties": {
    "iso:country":"DE",
    "sg:address":"Stra\u00dfe der Freundschaft 11",
    "sg:city":"Zella-Mehlis",
    "sg:phone":"+49 3682/40215",
    "sg:postcode":"98544",
    "sg:province":"Th\u00fcringen",
    "wof:name":"Werner & G\u00e4rtner Bau Gmbh",
    "wof:placetype":"venue"
},
  "geometry": {"coordinates":[10.669992,50.65966],"type":"Point"}
}