{
  "type": "Feature",
  "properties": {
    "iso:country":"DE",
    "sg:address":"L\u00fcbbecker Str. 78",
    "sg:city":"L\u00f6hne",
    "sg:phone":"+49 5732/71222",
    "sg:postcode":"32584",
    "sg:province":"Nordrhein-Westfalen",
    "wof:name":"Johannsmeier",
    "wof:placetype":"venue"
},
  "geometry": {"coordinates":[8.7142095566,52.2127990723],"type":"Point"}
}