{
  "type": "Feature",
  "properties": {
    "iso:country":"DE",
    "sg:address":"Aachweg 24",
    "sg:city":"Rielasingen-Worblingen",
    "sg:phone":"+49 7731/918335",
    "sg:postcode":"78239",
    "sg:province":"Baden-W\u00fcrttemberg",
    "wof:name":"Cornelia Leschinski",
    "wof:placetype":"venue"
},
  "geometry": {"coordinates":[8.8401184082,47.7340126038],"type":"Point"}
}