{
  "type": "Feature",
  "properties": {
    "iso:country":"DE",
    "sg:address":"Forggenseestr. 54",
    "sg:city":"M\u00fcnchen",
    "sg:phone":"+49 89/6927247",
    "sg:postcode":"81539",
    "sg:province":"Bayern",
    "wof:name":"Atronik Telekommunikation Vertriebs- Und Service Gmbh",
    "wof:placetype":"venue"
},
  "geometry": {"coordinates":[11.5901203156,48.1075630188],"type":"Point"}
}