{
  "type": "Feature",
  "properties": {
    "iso:country":"DE",
    "sg:address":"Schulzendorfer Str. 17",
    "sg:city":"Berlin",
    "sg:phone":"+49 30/40533561",
    "sg:postcode":"13467",
    "sg:province":"Berlin",
    "wof:name":"Bernd-rainer Hirsch",
    "wof:placetype":"venue"
},
  "geometry": {"coordinates":[13.3094120026,52.6124076843],"type":"Point"}
}