{
  "type": "Feature",
  "properties": {
    "iso:country":"DE",
    "sg:address":"Paschlewer Str. 9",
    "sg:city":"K\u00f6then",
    "sg:phone":"+49 3496/50280",
    "sg:postcode":"06366",
    "sg:province":"Sachsen-Anhalt",
    "wof:name":"Horn Und Schwennen Rechtsanw\u00e4lte Steuerberater",
    "wof:placetype":"venue"
},
  "geometry": {"coordinates":[11.9476890564,51.7572364807],"type":"Point"}
}