{
  "type": "Feature",
  "properties": {
    "iso:country":"DE",
    "sg:address":"Kirchenweg 68",
    "sg:city":"N\u00fcrnberg",
    "sg:phone":"+49 911/3938385",
    "sg:postcode":"90419",
    "sg:province":"Bayern",
    "wof:name":"Stefan Hartmann",
    "wof:placetype":"venue"
},
  "geometry": {"coordinates":[11.0606269836,49.4599685669],"type":"Point"}
}