{
  "type": "Feature",
  "properties": {
    "iso:country":"DE",
    "sg:address":"Am Kirchplatz 5",
    "sg:city":"Neresheim",
    "sg:phone":"+49 7367/7216",
    "sg:postcode":"73450",
    "sg:province":"Baden-W\u00fcrttemberg",
    "wof:name":"Kath. Pfarramt St. Stotmar",
    "wof:placetype":"venue"
},
  "geometry": {"coordinates":[10.2651090622,48.793510437],"type":"Point"}
}