{
  "type": "Feature",
  "properties": {
    "iso:country":"DE",
    "sg:address":"Untere Kampstr. 10",
    "sg:city":"Sundern",
    "sg:phone":"+49 2933/97440",
    "sg:postcode":"59846",
    "sg:province":"Nordrhein-Westfalen",
    "wof:name":"Druckhaus H\u00f6lken Gmbh",
    "wof:placetype":"venue"
},
  "geometry": {"coordinates":[8.006393,51.321098],"type":"Point"}
}