{
  "type": "Feature",
  "properties": {
    "iso:country":"DE",
    "sg:address":"Hauptstr. 47",
    "sg:city":"Lichtenau",
    "sg:phone":"+49 7227/2456",
    "sg:postcode":"77839",
    "sg:province":"Baden-W\u00fcrttemberg",
    "wof:name":"Lamm",
    "wof:placetype":"venue"
},
  "geometry": {"coordinates":[8.0045013428,48.7260437012],"type":"Point"}
}