{
  "type": "Feature",
  "properties": {
    "iso:country":"DE",
    "sg:address":"Hagsche Str. 21",
    "sg:city":"Kleve",
    "sg:phone":"+49 2821/72650",
    "sg:postcode":"47533",
    "sg:province":"Nordrhein-Westfalen",
    "wof:name":"Dr. Erdmann Und Dr.hassenpflug Rechtsanw\u00e4lte",
    "wof:placetype":"venue"
},
  "geometry": {"coordinates":[6.136382103,51.7857246399],"type":"Point"}
}