{
  "type": "Feature",
  "properties": {
    "iso:country":"DE",
    "sg:address":"Achbuchweg 8",
    "sg:city":"Lindau",
    "sg:phone":"+49 8382/3993",
    "sg:postcode":"88131",
    "sg:province":"Bayern",
    "wof:name":"K. Budei Immobilienmakler",
    "wof:placetype":"venue"
},
  "geometry": {"coordinates":[9.6631765366,47.5723228455],"type":"Point"}
}