{
  "type": "Feature",
  "properties": {
    "iso:country":"DE",
    "sg:address":"Hegaustr. 38",
    "sg:city":"Singen",
    "sg:phone":"+49 7731/99650",
    "sg:postcode":"78224",
    "sg:province":"Baden-W\u00fcrttemberg",
    "wof:name":"Karl J\u00f6cker Gmbh",
    "wof:placetype":"venue"
},
  "geometry": {"coordinates":[8.841137886,47.7602424622],"type":"Point"}
}