{
  "type": "Feature",
  "properties": {
    "iso:country":"DE",
    "sg:address":"B\u00e4rensteiner Str. 30",
    "sg:city":"Dresden",
    "sg:postcode":"01277",
    "sg:province":"Sachsen",
    "wof:name":"Dhd-mitarbeiter Beteiligungs Gmbh",
    "wof:placetype":"venue"
},
  "geometry": {"coordinates":[13.800959,51.035152],"type":"Point"}
}