{
  "type": "Feature",
  "properties": {
    "iso:country":"DE",
    "sg:address":"Neuer Graben 3",
    "sg:city":"Dortmund",
    "sg:phone":"+49 231/103557",
    "sg:postcode":"44139",
    "sg:province":"Nordrhein-Westfalen",
    "wof:name":"J\u00fcrgen Schulze",
    "wof:placetype":"venue"
},
  "geometry": {"coordinates":[7.4593110085,51.5055122375],"type":"Point"}
}