{
  "type": "Feature",
  "properties": {
    "iso:country":"DE",
    "sg:address":"Echterdinger Str. 6",
    "sg:city":"Leinfelden-Echterdingen",
    "sg:phone":"+49 711/755175",
    "sg:postcode":"70771",
    "sg:province":"Baden-W\u00fcrttemberg",
    "wof:name":"M. Fichtel",
    "wof:placetype":"venue"
},
  "geometry": {"coordinates":[9.14463,48.692631],"type":"Point"}
}