{
  "type": "Feature",
  "properties": {
    "iso:country":"DE",
    "sg:address":"Josef-Andre-Str. 1",
    "sg:city":"Schramberg",
    "sg:phone":"+49 7422/20337",
    "sg:postcode":"78713",
    "sg:province":"Baden-W\u00fcrttemberg",
    "wof:name":"Kath. Pfarramt Heilig Geist",
    "wof:placetype":"venue"
},
  "geometry": {"coordinates":[8.3877897263,48.2215461731],"type":"Point"}
}