{
  "type": "Feature",
  "properties": {
    "iso:country":"DE",
    "sg:address":"Buchenstr. 5",
    "sg:city":"Pfaffenhofen",
    "sg:phone":"+49 8441/81417",
    "sg:postcode":"85276",
    "sg:province":"Bayern",
    "wof:name":"Inge Und Volker Tscharntke",
    "wof:placetype":"venue"
},
  "geometry": {"coordinates":[11.480345726,48.5168495178],"type":"Point"}
}