{
  "type": "Feature",
  "properties": {
    "iso:country":"DE",
    "sg:address":"Lilienthalallee 40 c",
    "sg:city":"M\u00fcnchen",
    "sg:phone":"+49 89/32369339",
    "sg:postcode":"80939",
    "sg:province":"Bayern",
    "wof:name":"Birnbaum Tragetaschen E. K.",
    "wof:placetype":"venue"
},
  "geometry": {"coordinates":[11.6104536057,48.1977462769],"type":"Point"}
}