{
  "type": "Feature",
  "properties": {
    "iso:country":"DE",
    "sg:address":"Nikolaus-von-Weis-Str. 2",
    "sg:city":"Landstuhl",
    "sg:phone":"+49 6371/9010",
    "sg:postcode":"66849",
    "sg:province":"Rheinland-Pfalz",
    "wof:name":"St. Nikolaus-altenzentrum",
    "wof:placetype":"venue"
},
  "geometry": {"coordinates":[7.56659,49.409283],"type":"Point"}
}