{
  "type": "Feature",
  "properties": {
    "iso:country":"DE",
    "sg:address":"Thuillestr. 67",
    "sg:city":"M\u00fcnchen",
    "sg:phone":"+49 89/6375208",
    "sg:postcode":"81247",
    "sg:province":"Bayern",
    "wof:name":"Gregor Ganz Textilhandels- Und Beteiligungsges. Mbh",
    "wof:placetype":"venue"
},
  "geometry": {"coordinates":[11.469151,48.173546],"type":"Point"}
}