{
  "type": "Feature",
  "properties": {
    "iso:country":"DE",
    "sg:address":"Waldenburger Str. 8",
    "sg:city":"Hessisch Oldendorf",
    "sg:phone":"+49 5152/2916",
    "sg:postcode":"31840",
    "sg:province":"Niedersachsen",
    "wof:name":"Renate Karnau Immobilienmaklerin",
    "wof:placetype":"venue"
},
  "geometry": {"coordinates":[9.2557792664,52.1682739258],"type":"Point"}
}