{
  "type": "Feature",
  "properties": {
    "iso:country":"DE",
    "sg:address":"Weimarische Str. 33",
    "sg:city":"Erfurt",
    "sg:phone":"+49 361/4211911",
    "sg:postcode":"99099",
    "sg:province":"Th\u00fcringen",
    "wof:name":"Xtra Autovermietung Gmbh",
    "wof:placetype":"venue"
},
  "geometry": {"coordinates":[11.060863,50.974594],"type":"Point"}
}