{
  "type": "Feature",
  "properties": {
    "iso:country":"DE",
    "sg:address":"H\u00fcrbelweg",
    "sg:city":"Ilsfeld",
    "sg:phone":"+49 7062/6983",
    "sg:postcode":"74360",
    "sg:province":"Baden-W\u00fcrttemberg",
    "wof:name":"Weima Maschinenbau Gmbh",
    "wof:placetype":"venue"
},
  "geometry": {"coordinates":[9.240895,49.058353],"type":"Point"}
}