{
  "type": "Feature",
  "properties": {
    "iso:country":"DE",
    "sg:address":"Taubenweg 38",
    "sg:city":"F\u00fcrth",
    "sg:phone":"+49 911/772504",
    "sg:postcode":"90766",
    "sg:province":"Bayern",
    "wof:name":"H. B\u00fcrner Elektroinstallation",
    "wof:placetype":"venue"
},
  "geometry": {"coordinates":[10.971675,49.493092],"type":"Point"}
}