{
  "type": "Feature",
  "properties": {
    "iso:country":"DE",
    "sg:address":"Rommerscheider H\u00f6he 25",
    "sg:city":"Bergisch Gladbach",
    "sg:phone":"+49 2202/458899",
    "sg:postcode":"51465",
    "sg:province":"Nordrhein-Westfalen",
    "wof:name":"Korona Haus & Holz Gmbh",
    "wof:placetype":"venue"
},
  "geometry": {"coordinates":[7.148492,50.996887],"type":"Point"}
}