{
  "type": "Feature",
  "properties": {
    "iso:country":"DE",
    "sg:address":"Bei der Neuen M\u00fcnze 3",
    "sg:city":"Hamburg",
    "sg:phone":"+49 40/6782011",
    "sg:postcode":"22145",
    "sg:province":"Hamburg",
    "wof:name":"B\u00f6sche Reisen Gmbh",
    "wof:placetype":"venue"
},
  "geometry": {"coordinates":[10.1508378983,53.6219329834],"type":"Point"}
}