{
  "type": "Feature",
  "properties": {
    "iso:country":"DE",
    "sg:address":"Alt Lorsbach 6",
    "sg:city":"Hofheim",
    "sg:phone":"+49 6192/1399",
    "sg:postcode":"65719",
    "sg:province":"Hessen",
    "wof:name":"Hl-markt",
    "wof:placetype":"venue"
},
  "geometry": {"coordinates":[8.420340538,50.1167678833],"type":"Point"}
}