{
  "type": "Feature",
  "properties": {
    "iso:country":"DE",
    "sg:address":"M\u00fchlgasse 10",
    "sg:city":"Renningen",
    "sg:phone":"+49 7159/2898",
    "sg:postcode":"71272",
    "sg:province":"Baden-W\u00fcrttemberg",
    "wof:name":"Gerhard Beck",
    "wof:placetype":"venue"
},
  "geometry": {"coordinates":[8.938135,48.76506],"type":"Point"}
}