{
  "type": "Feature",
  "properties": {
    "iso:country":"DE",
    "sg:address":"Seerhausener Weg",
    "sg:city":"Mautitz",
    "sg:postcode":"01594",
    "sg:province":"Sachsen",
    "wof:name":"G. Grohmann Gmbh",
    "wof:placetype":"venue"
},
  "geometry": {"coordinates":[13.2267,51.281025],"type":"Point"}
}