{
  "type": "Feature",
  "properties": {
    "iso:country":"DE",
    "sg:address":"Nappianstr. 3 / 4",
    "sg:city":"Lutherstadt Eisleben",
    "sg:phone":"+49 3475/604641",
    "sg:postcode":"06295",
    "sg:province":"Sachsen-Anhalt",
    "wof:name":"Sgv Bau Eisleben Gmbh",
    "wof:placetype":"venue"
},
  "geometry": {"coordinates":[11.5387010574,51.5304679871],"type":"Point"}
}