{
  "type": "Feature",
  "properties": {
    "iso:country":"DE",
    "sg:address":"Bachstr. 54",
    "sg:city":"Geseke",
    "sg:phone":"+49 2942/4585",
    "sg:postcode":"59590",
    "sg:province":"Nordrhein-Westfalen",
    "wof:name":"Blumen Meier Ohg Inh. Theodor Meier",
    "wof:placetype":"venue"
},
  "geometry": {"coordinates":[8.509419,51.638268],"type":"Point"}
}