{
  "type": "Feature",
  "properties": {
    "iso:country":"DE",
    "sg:address":"Rosenhain 4",
    "sg:city":"Bonn",
    "sg:phone":"+49 228/647272",
    "sg:postcode":"53123",
    "sg:province":"Nordrhein-Westfalen",
    "wof:name":"Manfred Schumann",
    "wof:placetype":"venue"
},
  "geometry": {"coordinates":[7.0399260521,50.7182579041],"type":"Point"}
}