{
  "type": "Feature",
  "properties": {
    "iso:country":"DE",
    "sg:address":"Gabriel-Seidl-Str. 2",
    "sg:city":"Bremen",
    "sg:phone":"+49 421/342441",
    "sg:postcode":"28209",
    "sg:province":"Bremen",
    "wof:name":"W. Rieck",
    "wof:placetype":"venue"
},
  "geometry": {"coordinates":[8.831076622,53.0839805603],"type":"Point"}
}