{
  "type": "Feature",
  "properties": {
    "iso:country":"DE",
    "sg:address":"Christophorusstr. 38",
    "sg:city":"Bielefeld",
    "sg:phone":"+49 521/2080888",
    "sg:postcode":"33699",
    "sg:province":"Nordrhein-Westfalen",
    "wof:name":"Robert Schweizer",
    "wof:placetype":"venue"
},
  "geometry": {"coordinates":[8.6113119125,51.9890098572],"type":"Point"}
}