{
  "type": "Feature",
  "properties": {
    "iso:country":"DE",
    "sg:address":"Kurt-Schumacher-Str. 9",
    "sg:city":"Eschweiler",
    "sg:postcode":"52249",
    "sg:province":"Nordrhein-Westfalen",
    "wof:name":"Immolan Gmbh",
    "wof:placetype":"venue"
},
  "geometry": {"coordinates":[6.2820110321,50.8405456543],"type":"Point"}
}