{
  "type": "Feature",
  "properties": {
    "iso:country":"DE",
    "sg:address":"Wachostr. 21",
    "sg:city":"Pfaffenhofen",
    "sg:phone":"+49 8134/6309",
    "sg:postcode":"85235",
    "sg:province":"Bayern",
    "wof:name":"Johann Arzberger Internat. Spedition Und Landwirtschaftl.",
    "wof:placetype":"venue"
},
  "geometry": {"coordinates":[11.174217,48.302361],"type":"Point"}
}