{
  "type": "Feature",
  "properties": {
    "iso:country":"DE",
    "sg:address":"Wittenberger Str. 83",
    "sg:city":"Leipzig",
    "sg:phone":"+49 341/9116715",
    "sg:postcode":"04129",
    "sg:province":"Sachsen",
    "wof:name":"Laumann",
    "wof:placetype":"venue"
},
  "geometry": {"coordinates":[12.3856592178,51.3645973206],"type":"Point"}
}