{
  "type": "Feature",
  "properties": {
    "iso:country":"DE",
    "sg:address":"Im M\u00f6nchgraben 35",
    "sg:city":"Simmozheim",
    "sg:postcode":"75397",
    "sg:province":"Baden-W\u00fcrttemberg",
    "wof:name":"Grama Natursteine Gmbh",
    "wof:placetype":"venue"
},
  "geometry": {"coordinates":[8.8071060181,48.7453117371],"type":"Point"}
}