{
  "type": "Feature",
  "properties": {
    "iso:country":"DE",
    "sg:address":"Kirchstr. 3",
    "sg:city":"Friesoythe",
    "sg:phone":"+49 4491/2243",
    "sg:postcode":"26169",
    "sg:province":"Niedersachsen",
    "wof:name":"G. Und P. Wulfers",
    "wof:placetype":"venue"
},
  "geometry": {"coordinates":[7.8594350815,53.0207366943],"type":"Point"}
}