{
  "type": "Feature",
  "properties": {
    "iso:country":"DE",
    "sg:address":"Reichenstr. 6",
    "sg:city":"Elmshorn",
    "sg:phone":"+49 4121/61457",
    "sg:postcode":"25336",
    "sg:province":"Schleswig-Holstein",
    "wof:name":"Flora-st\u00fcbchen",
    "wof:placetype":"venue"
},
  "geometry": {"coordinates":[9.6561746597,53.7492523193],"type":"Point"}
}