{
  "type": "Feature",
  "properties": {
    "iso:country":"DE",
    "sg:address":"Aichen Schwab",
    "sg:city":"Aichen Schwab",
    "sg:phone":"+49 8284/595",
    "sg:postcode":"86479",
    "sg:province":"Bayern",
    "wof:name":"Raiffeisenbank Ziemetshausen Eg",
    "wof:placetype":"venue"
},
  "geometry": {"coordinates":[10.54042,48.22427],"type":"Point"}
}