{
  "type": "Feature",
  "properties": {
    "iso:country":"DE",
    "sg:address":"Am See 4",
    "sg:city":"Stutensee",
    "sg:phone":"+49 7244/91535",
    "sg:postcode":"76297",
    "sg:province":"Baden-W\u00fcrttemberg",
    "wof:name":"Druckatelier Lenz Gmbh",
    "wof:placetype":"venue"
},
  "geometry": {"coordinates":[8.4640655518,49.0801467896],"type":"Point"}
}