{
  "type": "Feature",
  "properties": {
    "iso:country":"DE",
    "sg:address":"Talstr.",
    "sg:city":"Mettmann",
    "sg:phone":"+49 2104/979797",
    "sg:postcode":"40822",
    "sg:province":"Nordrhein-Westfalen",
    "wof:name":"Neanderthal-museum",
    "wof:placetype":"venue"
},
  "geometry": {"coordinates":[6.972915,51.244171],"type":"Point"}
}