{
  "type": "Feature",
  "properties": {
    "iso:country":"DE",
    "sg:address":"M\u00fcglitztalstr. 17",
    "sg:city":"Dohna",
    "sg:phone":"+49 3529/511760",
    "sg:postcode":"01809",
    "sg:province":"Sachsen",
    "wof:name":"W. Winkler",
    "wof:placetype":"venue"
},
  "geometry": {"coordinates":[13.8549222946,50.9589157104],"type":"Point"}
}