{
  "type": "Feature",
  "properties": {
    "iso:country":"DE",
    "sg:address":"Brauereistr. 2",
    "sg:city":"Worms",
    "sg:phone":"+49 6241/958570",
    "sg:postcode":"67549",
    "sg:province":"Rheinland-Pfalz",
    "wof:name":"Horst Bentz Steuerberatungs Gmbh",
    "wof:placetype":"venue"
},
  "geometry": {"coordinates":[8.3439702988,49.6320037842],"type":"Point"}
}