{
  "type": "Feature",
  "properties": {
    "iso:country":"DE",
    "sg:address":"Griesener Str. 17",
    "sg:city":"Grainau",
    "sg:phone":"+49 8821/58103",
    "sg:postcode":"82491",
    "sg:province":"Bayern",
    "wof:name":"Grill Rustico",
    "wof:placetype":"venue"
},
  "geometry": {"coordinates":[11.0518321991,47.478843689],"type":"Point"}
}