{
  "type": "Feature",
  "properties": {
    "iso:country":"DE",
    "sg:address":"Burgstr. 14",
    "sg:city":"Bensheim",
    "sg:phone":"+49 6251/77513",
    "sg:postcode":"64625",
    "sg:province":"Hessen",
    "wof:name":"Dr. W. Sack Ingenieur",
    "wof:placetype":"venue"
},
  "geometry": {"coordinates":[8.6255064011,49.7069969177],"type":"Point"}
}