{
  "type": "Feature",
  "properties": {
    "iso:country":"DE",
    "sg:city":"H\u00f6chstadt",
    "sg:phone":"+49 9193/2323",
    "sg:postcode":"91315",
    "sg:province":"Bayern",
    "wof:name":"L. Wegel",
    "wof:placetype":"venue"
},
  "geometry": {"coordinates":[10.83926,49.71587],"type":"Point"}
}