{
  "type": "Feature",
  "properties": {
    "iso:country":"DE",
    "sg:address":"Deichstr. 14",
    "sg:city":"Cuxhaven",
    "sg:phone":"+49 4721/53592",
    "sg:postcode":"27472",
    "sg:province":"Niedersachsen",
    "wof:name":"Der Stuhl B. Meier",
    "wof:placetype":"venue"
},
  "geometry": {"coordinates":[8.7015800476,53.8659667969],"type":"Point"}
}