{
  "type": "Feature",
  "properties": {
    "iso:country":"DE",
    "sg:address":"Max-Planck-Str. 20",
    "sg:city":"Saarlouis",
    "sg:phone":"+49 6831/87100",
    "sg:postcode":"66740",
    "sg:province":"Saarland",
    "wof:name":"Hps Hawener & Peter Sarghandel Und Zubeh\u00f6r Gmbh",
    "wof:placetype":"venue"
},
  "geometry": {"coordinates":[6.7727398872,49.3359870911],"type":"Point"}
}