{
  "type": "Feature",
  "properties": {
    "iso:country":"DE",
    "sg:address":"Flomersheimer Str. 10",
    "sg:city":"Frankenthal",
    "sg:phone":"+49 6233/9180",
    "sg:postcode":"67227",
    "sg:province":"Rheinland-Pfalz",
    "wof:name":"E. Bukur",
    "wof:placetype":"venue"
},
  "geometry": {"coordinates":[8.348375,49.527306],"type":"Point"}
}