{
  "type": "Feature",
  "properties": {
    "iso:country":"DE",
    "sg:address":"Kantstr. 12",
    "sg:city":"Peine",
    "sg:phone":"+49 5171/13798",
    "sg:postcode":"31224",
    "sg:province":"Niedersachsen",
    "wof:name":"Bei Tassos",
    "wof:placetype":"venue"
},
  "geometry": {"coordinates":[10.2334337234,52.322845459],"type":"Point"}
}