{
  "type": "Feature",
  "properties": {
    "iso:country":"DE",
    "sg:address":"Rilkestr. 25",
    "sg:city":"N\u00fcrnberg",
    "sg:phone":"+49 911/339528",
    "sg:postcode":"90419",
    "sg:province":"Bayern",
    "wof:name":"Axel Ring",
    "wof:placetype":"venue"
},
  "geometry": {"coordinates":[11.068448,49.46431],"type":"Point"}
}