{
  "type": "Feature",
  "properties": {
    "iso:country":"DE",
    "sg:address":"Bahnstr. 18",
    "sg:city":"Quickborn",
    "sg:phone":"+49 4106/73852",
    "sg:postcode":"25451",
    "sg:province":"Schleswig-Holstein",
    "wof:name":"Mh Videotheken Heidenreich",
    "wof:placetype":"venue"
},
  "geometry": {"coordinates":[9.9222507477,53.7498512268],"type":"Point"}
}