{
  "type": "Feature",
  "properties": {
    "iso:country":"DE",
    "sg:address":"Leutenberger Str. 5",
    "sg:city":"Wurzbach",
    "sg:phone":"+49 36652/22560",
    "sg:postcode":"07343",
    "sg:province":"Th\u00fcringen",
    "wof:name":"Kulturhaus",
    "wof:placetype":"venue"
},
  "geometry": {"coordinates":[11.5383901596,50.4639282227],"type":"Point"}
}