{
  "type": "Feature",
  "properties": {
    "iso:country":"DE",
    "sg:address":"Lange Reihe 48",
    "sg:city":"Hamm",
    "sg:phone":"+49 2381/81140",
    "sg:postcode":"59071",
    "sg:province":"Nordrhein-Westfalen",
    "wof:name":"D. L\u00f6bert",
    "wof:placetype":"venue"
},
  "geometry": {"coordinates":[7.8817439079,51.6780281067],"type":"Point"}
}