{
  "type": "Feature",
  "properties": {
    "iso:country":"DE",
    "sg:address":"Nordstr. 2",
    "sg:city":"Adenstedt",
    "sg:phone":"+49 5060/761",
    "sg:postcode":"31079",
    "sg:province":"Niedersachsen",
    "wof:name":"Heinz Schwertfeger Elektromeister",
    "wof:placetype":"venue"
},
  "geometry": {"coordinates":[9.934248,52.002357],"type":"Point"}
}