{
  "type": "Feature",
  "properties": {
    "iso:country":"DE",
    "sg:address":"Hindenburgstr. 54",
    "sg:city":"Gnarrenburg",
    "sg:phone":"+49 4763/1022",
    "sg:postcode":"27442",
    "sg:province":"Niedersachsen",
    "wof:name":"J\u00f6rg Peters Masseur",
    "wof:placetype":"venue"
},
  "geometry": {"coordinates":[9.004046,53.380795],"type":"Point"}
}