{
  "type": "Feature",
  "properties": {
    "iso:country":"DE",
    "sg:address":"m\u00fchlenbreite 44",
    "sg:city":"schieder-schwalenberg",
    "sg:phone":"+49 5282/6413",
    "sg:postcode":"32816",
    "sg:province":"Nordrhein-Westfalen",
    "wof:name":"Urlaub In Glash\u00fctte Lippe Teutoburgerwald Stausee",
    "wof:placetype":"venue"
},
  "geometry": {"coordinates":[9.152363,51.91],"type":"Point"}
}