{
  "type": "Feature",
  "properties": {
    "iso:country":"DE",
    "sg:address":"Nassauerstr. 14",
    "sg:city":"Saarbr\u00fccken",
    "sg:phone":"+49 681/3908530",
    "sg:postcode":"66111",
    "sg:province":"Saarland",
    "wof:name":"Haifischbar",
    "wof:placetype":"venue"
},
  "geometry": {"coordinates":[6.9985628128,49.2351417542],"type":"Point"}
}