{
  "type": "Feature",
  "properties": {
    "iso:country":"DE",
    "sg:address":"Am Roten Berg 24",
    "sg:city":"Eisenberg",
    "sg:phone":"+49 36691/42363",
    "sg:postcode":"07607",
    "sg:province":"Th\u00fcringen",
    "wof:name":"G. Theil",
    "wof:placetype":"venue"
},
  "geometry": {"coordinates":[11.886385,50.975033],"type":"Point"}
}