{
  "type": "Feature",
  "properties": {
    "iso:country":"DE",
    "sg:address":"Burgdorfer Damm 37",
    "sg:city":"Hannover",
    "sg:phone":"+49 511/562700",
    "sg:postcode":"30625",
    "sg:province":"Niedersachsen",
    "wof:name":"Hans-erich M\u00fcller-baule Rechtanwalt Und Notar",
    "wof:placetype":"venue"
},
  "geometry": {"coordinates":[9.8151683807,52.3804779053],"type":"Point"}
}