{
  "type": "Feature",
  "properties": {
    "iso:country":"DE",
    "sg:address":"Hauptstr 10",
    "sg:city":"Schwanebeck",
    "sg:phone":"+49 33841/6000",
    "sg:postcode":"14806",
    "sg:province":"Brandenburg",
    "wof:name":"Metallbau Stoof Gmbh",
    "wof:placetype":"venue"
},
  "geometry": {"coordinates":[12.625898,52.178104],"type":"Point"}
}