{
  "type": "Feature",
  "properties": {
    "iso:country":"DE",
    "sg:address":"Geismar Landstr. 13",
    "sg:city":"G\u00f6ttingen",
    "sg:phone":"+49 551/547870",
    "sg:postcode":"37083",
    "sg:province":"Niedersachsen",
    "wof:name":"Gro\u00dfmann Planung Gmbh",
    "wof:placetype":"venue"
},
  "geometry": {"coordinates":[9.9435453415,51.528263092],"type":"Point"}
}