{
  "type": "Feature",
  "properties": {
    "iso:country":"DE",
    "sg:address":"Schwarzenbeker Ring 33 c",
    "sg:city":"Hamburg",
    "sg:postcode":"22149",
    "sg:province":"Hamburg",
    "wof:name":"Michael Donges Detektei F\u00fcr Die Wirtschaft-",
    "wof:placetype":"venue"
},
  "geometry": {"coordinates":[10.182584,53.587685],"type":"Point"}
}