{
  "type": "Feature",
  "properties": {
    "iso:country":"DE",
    "sg:address":"Quellenstr. 8",
    "sg:city":"Heidenrod",
    "sg:phone":"+49 6124/721405",
    "sg:postcode":"65321",
    "sg:province":"Hessen",
    "wof:name":"Martin Klyne Rechtsanwalt",
    "wof:placetype":"venue"
},
  "geometry": {"coordinates":[8.0004472733,50.1714172363],"type":"Point"}
}