{
  "type": "Feature",
  "properties": {
    "iso:country":"DE",
    "sg:address":"Hohenstaufenstr. 36",
    "sg:city":"Berlin",
    "sg:phone":"+49 30/2141719",
    "sg:postcode":"10779",
    "sg:province":"Berlin",
    "wof:name":"Steves & Zaun Gesellschaft Von Architekten Mbh",
    "wof:placetype":"venue"
},
  "geometry": {"coordinates":[13.3397836685,52.4944458008],"type":"Point"}
}