{
  "type": "Feature",
  "properties": {
    "iso:country":"DE",
    "sg:address":"Zum Tiefenbach 35",
    "sg:city":"St. Wendel",
    "sg:phone":"+49 6856/239",
    "sg:postcode":"66606",
    "sg:province":"Saarland",
    "wof:name":"L. Morgenstern Gmbh S\u00e4gewerk",
    "wof:placetype":"venue"
},
  "geometry": {"coordinates":[7.2377481461,49.4589500427],"type":"Point"}
}