{
  "type": "Feature",
  "properties": {
    "iso:country":"DE",
    "sg:address":"Isarstr. 29",
    "sg:city":"Wang",
    "sg:phone":"+49 8761/70776",
    "sg:postcode":"85368",
    "sg:province":"Bayern",
    "wof:name":"Reinhold Schorb",
    "wof:placetype":"venue"
},
  "geometry": {"coordinates":[11.96043,48.486462],"type":"Point"}
}