{
  "type": "Feature",
  "properties": {
    "iso:country":"DE",
    "sg:address":"Scheibenm\u00fchlenstr.",
    "sg:city":"Stolpen",
    "sg:phone":"+49 35973/24931",
    "sg:postcode":"01833",
    "sg:province":"Sachsen",
    "wof:name":"Agrargenossenschaft Heeselicht Eg",
    "wof:placetype":"venue"
},
  "geometry": {"coordinates":[14.105044,51.002045],"type":"Point"}
}