{
  "type": "Feature",
  "properties": {
    "iso:country":"DE",
    "sg:address":"Roxheimer Str. 29",
    "sg:city":"Bobenheim-Roxheim",
    "sg:phone":"+49 6239/8627",
    "sg:postcode":"67240",
    "sg:province":"Rheinland-Pfalz",
    "wof:name":"Helga Gr\u00e4f",
    "wof:placetype":"venue"
},
  "geometry": {"coordinates":[8.359505,49.587894],"type":"Point"}
}