{
  "type": "Feature",
  "properties": {
    "iso:country":"DE",
    "sg:address":"Obere Hauptstr. 264",
    "sg:city":"Lustadt",
    "sg:phone":"+49 6347/919079",
    "sg:postcode":"67363",
    "sg:province":"Rheinland-Pfalz",
    "wof:name":"J\u00fcrgen Vollmer",
    "wof:placetype":"venue"
},
  "geometry": {"coordinates":[8.2727174759,49.2445831299],"type":"Point"}
}