{
  "type": "Feature",
  "properties": {
    "iso:country":"DE",
    "sg:address":"Auf der Bins 3",
    "sg:city":"Hechingen",
    "sg:phone":"+49 7471/3063",
    "sg:postcode":"72379",
    "sg:province":"Baden-W\u00fcrttemberg",
    "wof:name":"J. Hakenm\u00fcller Gmbh & Co. Kg",
    "wof:placetype":"venue"
},
  "geometry": {"coordinates":[8.9094152451,48.3516044617],"type":"Point"}
}