{
  "type": "Feature",
  "properties": {
    "iso:country":"DE",
    "sg:address":"B\u00fctteler Str. 1",
    "sg:city":"Bremerhaven",
    "sg:phone":"+49 471/9543140",
    "sg:postcode":"27568",
    "sg:province":"Bremen",
    "wof:name":"Blw Betreutes Leben Und Wohnen Seniorenzentrum Gmbh",
    "wof:placetype":"venue"
},
  "geometry": {"coordinates":[8.584762,53.563332],"type":"Point"}
}