{
  "type": "Feature",
  "properties": {
    "iso:country":"DE",
    "sg:address":"Scharzbergstr 9::",
    "sg:city":"Konz",
    "sg:postcode":"54329",
    "sg:province":"Rheinland-Pfalz",
    "wof:name":"Raiffeisenbank Konz-oberemmel Eg",
    "wof:placetype":"venue"
},
  "geometry": {"coordinates":[6.629841,49.660061],"type":"Point"}
}