{
  "type": "Feature",
  "properties": {
    "iso:country":"DE",
    "sg:address":"Eichholz 5",
    "sg:city":"Extertal",
    "sg:postcode":"32699",
    "sg:province":"Nordrhein-Westfalen",
    "wof:name":"Rehme & Kunz Ohg",
    "wof:placetype":"venue"
},
  "geometry": {"coordinates":[9.1409873962,52.0646209717],"type":"Point"}
}