{
  "type": "Feature",
  "properties": {
    "iso:country":"DE",
    "sg:address":"Bahnhofstr. 17",
    "sg:city":"Bischofsheim",
    "sg:phone":"+49 6144/8180",
    "sg:postcode":"65474",
    "sg:province":"Hessen",
    "wof:name":"Pizzeria-spaghetteria",
    "wof:placetype":"venue"
},
  "geometry": {"coordinates":[8.3609342575,49.9904136658],"type":"Point"}
}