{
  "type": "Feature",
  "properties": {
    "iso:country":"DE",
    "sg:address":"Heckenweg 39",
    "sg:city":"Graal-M\u00fcritz",
    "sg:postcode":"18181",
    "sg:province":"Mecklenburg-Vorpommern",
    "wof:name":"Hans Sachs Schuhservice Gmbh",
    "wof:placetype":"venue"
},
  "geometry": {"coordinates":[12.2379846573,54.249206543],"type":"Point"}
}