{
  "type": "Feature",
  "properties": {
    "iso:country":"DE",
    "sg:address":"Br\u00fcckenstr. 13",
    "sg:city":"Stuttgart",
    "sg:phone":"+49 711/545441",
    "sg:postcode":"70376",
    "sg:province":"Baden-W\u00fcrttemberg",
    "wof:name":"Gastst\u00e4tte Bier-f\u00e4\u00dfle",
    "wof:placetype":"venue"
},
  "geometry": {"coordinates":[9.2110347748,48.8070373535],"type":"Point"}
}