{
  "type": "Feature",
  "properties": {
    "iso:country":"DE",
    "sg:address":"Erich-Garben-Str. 2",
    "sg:city":"Gehrden",
    "sg:phone":"+49 5108/926903",
    "sg:postcode":"30989",
    "sg:province":"Niedersachsen",
    "wof:name":"Rath & Mensing Gmbh",
    "wof:placetype":"venue"
},
  "geometry": {"coordinates":[9.5795297623,52.3327865601],"type":"Point"}
}