{
  "type": "Feature",
  "properties": {
    "iso:country":"DE",
    "sg:address":"Steigerstr. 22",
    "sg:city":"Sulzbach-Rosenberg",
    "sg:phone":"+49 9661/51942",
    "sg:postcode":"92237",
    "sg:province":"Bayern",
    "wof:name":"Helga Ullmann",
    "wof:placetype":"venue"
},
  "geometry": {"coordinates":[11.743188,49.510826],"type":"Point"}
}