{
  "type": "Feature",
  "properties": {
    "iso:country":"DE",
    "sg:address":"Geschwister-Scholl-Str. 27",
    "sg:city":"Dingelst\u00e4dt",
    "sg:phone":"+49 36075/2248",
    "sg:postcode":"37351",
    "sg:province":"Th\u00fcringen",
    "wof:name":"Herfac Gmbh",
    "wof:placetype":"venue"
},
  "geometry": {"coordinates":[10.316197,51.31498],"type":"Point"}
}