{
  "type": "Feature",
  "properties": {
    "iso:country":"DE",
    "sg:address":"Bergstr. 7",
    "sg:city":"T\u00f6pchin",
    "sg:phone":"+49 33769/50253",
    "sg:postcode":"15755",
    "sg:province":"Brandenburg",
    "wof:name":"Pfeffer",
    "wof:placetype":"venue"
},
  "geometry": {"coordinates":[13.6113367081,52.1360702515],"type":"Point"}
}