{
  "type": "Feature",
  "properties": {
    "iso:country":"DE",
    "sg:address":"Walther-Rathenau-Str. 22",
    "sg:city":"Bitterfeld",
    "sg:phone":"+49 3493/24703",
    "sg:postcode":"06749",
    "sg:province":"Sachsen-Anhalt",
    "wof:name":"Walter",
    "wof:placetype":"venue"
},
  "geometry": {"coordinates":[12.3214092255,51.6217536926],"type":"Point"}
}