{
  "type": "Feature",
  "properties": {
    "iso:country":"DE",
    "sg:address":"Tackenweide 31",
    "sg:city":"Emmerich",
    "sg:postcode":"46446",
    "sg:province":"Nordrhein-Westfalen",
    "wof:name":"Siebrecht Backideen Gmbh",
    "wof:placetype":"venue"
},
  "geometry": {"coordinates":[6.2692008018,51.8450965881],"type":"Point"}
}