{
  "type": "Feature",
  "properties": {
    "iso:country":"DE",
    "sg:address":"Hauptstr. 56",
    "sg:city":"P\u00fcttlingen",
    "sg:phone":"+49 6806/920310",
    "sg:postcode":"66346",
    "sg:province":"Saarland",
    "wof:name":"Felix Raber",
    "wof:placetype":"venue"
},
  "geometry": {"coordinates":[6.899235,49.30249],"type":"Point"}
}