{
  "type": "Feature",
  "properties": {
    "iso:country":"DE",
    "sg:address":"\u00d6tisheimer Str. 190",
    "sg:city":"Apolda",
    "sg:phone":"+49 36465/40202",
    "sg:postcode":"99510",
    "sg:province":"Th\u00fcringen",
    "wof:name":"Gastst\u00e4tte Sulzbach",
    "wof:placetype":"venue"
},
  "geometry": {"coordinates":[11.4861822128,51.0024108887],"type":"Point"}
}