{
  "type": "Feature",
  "properties": {
    "iso:country":"DE",
    "sg:address":"Neuen Wall 77",
    "sg:city":"Hamburg",
    "sg:phone":"+49 40/3554220",
    "sg:postcode":"20354",
    "sg:province":"Hamburg",
    "wof:name":"Trans-medica Pharma - Handelsgesellschafts Mbh & Co.kg",
    "wof:placetype":"venue"
},
  "geometry": {"coordinates":[9.992445,53.553345],"type":"Point"}
}