{
  "type": "Feature",
  "properties": {
    "iso:country":"DE",
    "sg:address":"Cranachstr. 15",
    "sg:city":"Reutlingen",
    "sg:phone":"+49 7121/600787",
    "sg:postcode":"72768",
    "sg:province":"Baden-W\u00fcrttemberg",
    "wof:name":"Dr. Werner Futter Rechtsanwalt",
    "wof:placetype":"venue"
},
  "geometry": {"coordinates":[9.1710557938,48.5226554871],"type":"Point"}
}