{
  "type": "Feature",
  "properties": {
    "iso:country":"DE",
    "sg:address":"Zeichaer Str. 5",
    "sg:city":"Naundorf",
    "sg:phone":"+49 3435/920737",
    "sg:postcode":"04769",
    "sg:province":"Sachsen",
    "wof:name":"A. Kasterke",
    "wof:placetype":"venue"
},
  "geometry": {"coordinates":[13.1071529388,51.2552070618],"type":"Point"}
}