{
  "type": "Feature",
  "properties": {
    "iso:country":"DE",
    "sg:address":"Walliser Str. 114",
    "sg:city":"M\u00fcnchen",
    "sg:phone":"+49 89/754982",
    "sg:postcode":"81475",
    "sg:province":"Bayern",
    "wof:name":"Dr. Josef D\u00f6rr Wirtschaftspr\u00fcfer",
    "wof:placetype":"venue"
},
  "geometry": {"coordinates":[11.4837026596,48.0917701721],"type":"Point"}
}