{
  "type": "Feature",
  "properties": {
    "iso:country":"DE",
    "sg:address":"Schie\u00dfst\u00e4ttstr. 35",
    "sg:city":"Wolfratshausen",
    "sg:phone":"+49 8171/20001",
    "sg:postcode":"82515",
    "sg:province":"Bayern",
    "wof:name":"Anne Hahn Littlefair Communication Werbeagentur",
    "wof:placetype":"venue"
},
  "geometry": {"coordinates":[11.4320631027,47.9099769592],"type":"Point"}
}