{
  "type": "Feature",
  "properties": {
    "iso:country":"DE",
    "sg:address":"Gevelsbergstr. 36",
    "sg:city":"Dortmund",
    "sg:phone":"+49 231/453045",
    "sg:postcode":"44269",
    "sg:province":"Nordrhein-Westfalen",
    "wof:name":"Katholisches Pfarramt St. Bonifatius",
    "wof:placetype":"venue"
},
  "geometry": {"coordinates":[7.5375008583,51.4962768555],"type":"Point"}
}