{
  "type": "Feature",
  "properties": {
    "iso:country":"DE",
    "sg:address":"Berliner Str. 38",
    "sg:city":"M\u00fcnchen",
    "sg:phone":"+49 89/369615",
    "sg:postcode":"80805",
    "sg:province":"Bayern",
    "wof:name":"Hans W. Biedermann Rechtsanw\u00e4lte",
    "wof:placetype":"venue"
},
  "geometry": {"coordinates":[11.5878000259,48.172580719],"type":"Point"}
}