{
  "type": "Feature",
  "properties": {
    "iso:country":"DE",
    "sg:address":"Rudelstetten 42",
    "sg:city":"Alerheim",
    "sg:phone":"+49 9085/513",
    "sg:postcode":"86733",
    "sg:province":"Bayern",
    "wof:name":"Rieser Hof",
    "wof:placetype":"venue"
},
  "geometry": {"coordinates":[10.6164340973,48.848274231],"type":"Point"}
}