{
  "type": "Feature",
  "properties": {
    "iso:country":"DE",
    "sg:address":"Zeppelinstr. 14",
    "sg:city":"Jockgrim",
    "sg:phone":"+49 7271/51926",
    "sg:postcode":"76751",
    "sg:province":"Rheinland-Pfalz",
    "wof:name":"G\u00fcnther Krzysewski",
    "wof:placetype":"venue"
},
  "geometry": {"coordinates":[8.2824888229,49.0956382751],"type":"Point"}
}