{
  "type": "Feature",
  "properties": {
    "iso:country":"DE",
    "sg:address":"Albestr. 22",
    "sg:city":"Berlin",
    "sg:phone":"+49 30/8513453",
    "sg:postcode":"12159",
    "sg:province":"Berlin",
    "wof:name":"J\u00fcrgen R\u00fcckert",
    "wof:placetype":"venue"
},
  "geometry": {"coordinates":[13.330621,52.47332],"type":"Point"}
}