{
  "type": "Feature",
  "properties": {
    "iso:country":"DE",
    "sg:address":"Hiltenspergerstr. 15",
    "sg:city":"M\u00fcnchen",
    "sg:phone":"+49 89/2711574",
    "sg:postcode":"80798",
    "sg:province":"Bayern",
    "wof:name":"Peter Porzelt",
    "wof:placetype":"venue"
},
  "geometry": {"coordinates":[11.565685,48.156677],"type":"Point"}
}