{
  "type": "Feature",
  "properties": {
    "iso:country":"DE",
    "sg:address":"Torgauer Str. 20",
    "sg:city":"Gro\u00dfwig",
    "sg:phone":"+49 3421/903123",
    "sg:postcode":"04860",
    "sg:province":"Sachsen",
    "wof:name":"Rainer Richter",
    "wof:placetype":"venue"
},
  "geometry": {"coordinates":[12.890843,51.562092],"type":"Point"}
}