{
  "type": "Feature",
  "properties": {
    "iso:country":"DE",
    "sg:address":"Scheibenstr. 1",
    "sg:city":"Traunstein",
    "sg:phone":"+49 861/5486",
    "sg:postcode":"83278",
    "sg:province":"Bayern",
    "wof:name":"Edeka",
    "wof:placetype":"venue"
},
  "geometry": {"coordinates":[12.6514072418,47.8698272705],"type":"Point"}
}