{
  "type": "Feature",
  "properties": {
    "iso:country":"DE",
    "sg:address":"Max-Eyth-Str. 21",
    "sg:city":"Kirchheim",
    "sg:phone":"+49 7021/2310",
    "sg:postcode":"73230",
    "sg:province":"Baden-W\u00fcrttemberg",
    "wof:name":"En Vogue Chez Geppert",
    "wof:placetype":"venue"
},
  "geometry": {"coordinates":[9.450803,48.648792],"type":"Point"}
}