{
  "type": "Feature",
  "properties": {
    "iso:country":"DE",
    "sg:address":"Alt Schwanheim 56",
    "sg:city":"Frankfurt",
    "sg:phone":"+49 69/358731",
    "sg:postcode":"60529",
    "sg:province":"Hessen",
    "wof:name":"Aldi Gmbh & Co. Kg",
    "wof:placetype":"venue"
},
  "geometry": {"coordinates":[8.5809688568,50.082775116],"type":"Point"}
}