{
  "type": "Feature",
  "properties": {
    "iso:country":"DE",
    "sg:address":"Erlanger Str. 6",
    "sg:city":"Bayreuth",
    "sg:phone":"+49 921/882198",
    "sg:postcode":"95444",
    "sg:province":"Bayern",
    "wof:name":"Volksbank-raiffeisenbank Bayre",
    "wof:placetype":"venue"
},
  "geometry": {"coordinates":[11.568987,49.943417],"type":"Point"}
}