{
  "type": "Feature",
  "properties": {
    "iso:country":"DE",
    "sg:address":"Eichenm\u00fchleweg 14",
    "sg:city":"Friedrichshafen",
    "sg:phone":"+49 7541/41167",
    "sg:postcode":"88048",
    "sg:province":"Baden-W\u00fcrttemberg",
    "wof:name":"Fritz Schmid",
    "wof:placetype":"venue"
},
  "geometry": {"coordinates":[9.408915,47.671661],"type":"Point"}
}