{
  "type": "Feature",
  "properties": {
    "iso:country":"DE",
    "sg:address":"Hauptstr. 2",
    "sg:city":"Bergneustadt",
    "sg:phone":"+49 2261/920900",
    "sg:postcode":"51702",
    "sg:province":"Nordrhein-Westfalen",
    "wof:name":"Hollywood-lieferservice",
    "wof:placetype":"venue"
},
  "geometry": {"coordinates":[7.6492500305,51.0205307007],"type":"Point"}
}