{
  "type": "Feature",
  "properties": {
    "iso:country":"DE",
    "sg:address":"Westlachenb\u00fchl 31",
    "sg:city":"Kaufbeuren",
    "sg:phone":"+49 8341/12505",
    "sg:postcode":"87600",
    "sg:province":"Bayern",
    "wof:name":"Cafe Kraus",
    "wof:placetype":"venue"
},
  "geometry": {"coordinates":[10.606675,47.877869],"type":"Point"}
}