{
  "type": "Feature",
  "properties": {
    "iso:country":"DE",
    "sg:address":"Ulrichstr. 7",
    "sg:city":"G\u00f6ppingen",
    "sg:phone":"+49 7161/73339",
    "sg:postcode":"73033",
    "sg:province":"Baden-W\u00fcrttemberg",
    "wof:name":"Fritz M\u00fcller Jun.",
    "wof:placetype":"venue"
},
  "geometry": {"coordinates":[9.656434,48.707901],"type":"Point"}
}