{
  "type": "Feature",
  "properties": {
    "iso:country":"DE",
    "sg:address":"Gr\u00fcterstr. 19",
    "sg:city":"Rheine",
    "sg:phone":"+49 5971/961980",
    "sg:postcode":"48429",
    "sg:province":"Nordrhein-Westfalen",
    "wof:name":"Ts Monierbau Gmbh",
    "wof:placetype":"venue"
},
  "geometry": {"coordinates":[7.442783,52.283035],"type":"Point"}
}