{
  "type": "Feature",
  "properties": {
    "iso:country":"DE",
    "sg:address":"Oppelner Str. 25",
    "sg:city":"Kaarst",
    "sg:postcode":"41564",
    "sg:province":"Nordrhein-Westfalen",
    "wof:name":"Helmut Achildes",
    "wof:placetype":"venue"
},
  "geometry": {"coordinates":[6.6044330597,51.2198905945],"type":"Point"}
}