{
  "type": "Feature",
  "properties": {
    "iso:country":"DE",
    "sg:address":"K\u00f6lner Str. 358",
    "sg:city":"K\u00fcrten",
    "sg:phone":"+49 2207/910135",
    "sg:postcode":"51515",
    "sg:province":"Nordrhein-Westfalen",
    "wof:name":"Dieter Emunds Rechtsanwalt",
    "wof:placetype":"venue"
},
  "geometry": {"coordinates":[7.2108078003,51.0412445068],"type":"Point"}
}