{
  "type": "Feature",
  "properties": {
    "iso:country":"DE",
    "sg:address":"J\u00f6rgstr. 3",
    "sg:city":"Kempten",
    "sg:phone":"+49 831/71831",
    "sg:postcode":"87437",
    "sg:province":"Bayern",
    "wof:name":"Rainer Zappe",
    "wof:placetype":"venue"
},
  "geometry": {"coordinates":[10.3348941803,47.7293281555],"type":"Point"}
}