{
  "type": "Feature",
  "properties": {
    "iso:country":"DE",
    "sg:address":"Ulmer Str. 47",
    "sg:city":"Weidenstetten",
    "sg:phone":"+49 7340/302",
    "sg:postcode":"89197",
    "sg:province":"Baden-W\u00fcrttemberg",
    "wof:name":"Ev. Pfarramt",
    "wof:placetype":"venue"
},
  "geometry": {"coordinates":[9.9977321625,48.5528297424],"type":"Point"}
}