{
  "type": "Feature",
  "properties": {
    "iso:country":"DE",
    "sg:address":"Lappacher Weg 25",
    "sg:city":"H\u00f6chstadt",
    "sg:phone":"+49 9193/8222",
    "sg:postcode":"91315",
    "sg:province":"Bayern",
    "wof:name":"Lagerhaus Hawel",
    "wof:placetype":"venue"
},
  "geometry": {"coordinates":[10.798002,49.692619],"type":"Point"}
}