{
  "type": "Feature",
  "properties": {
    "iso:country":"DE",
    "sg:address":"Zur Kapelle 4",
    "sg:city":"Morsbach",
    "sg:phone":"+49 2294/1546",
    "sg:postcode":"51597",
    "sg:province":"Nordrhein-Westfalen",
    "wof:name":"Inge Engler Hebamme",
    "wof:placetype":"venue"
},
  "geometry": {"coordinates":[7.690667,50.848858],"type":"Point"}
}