{
  "type": "Feature",
  "properties": {
    "iso:country":"DE",
    "sg:address":"Dorotheenstr. 145",
    "sg:city":"Hamburg",
    "sg:phone":"+49 40/470640",
    "sg:postcode":"22299",
    "sg:province":"Hamburg",
    "wof:name":"Karin Rehder E. K.",
    "wof:placetype":"venue"
},
  "geometry": {"coordinates":[10.001734,53.591732],"type":"Point"}
}