{
  "type": "Feature",
  "properties": {
    "iso:country":"DE",
    "sg:address":"M\u00fchlenweg 10",
    "sg:city":"Hohenkirchen",
    "sg:phone":"+49 36253/25305",
    "sg:postcode":"99887",
    "sg:province":"Th\u00fcringen",
    "wof:name":"Martin Seeber",
    "wof:placetype":"venue"
},
  "geometry": {"coordinates":[10.70962,50.850304],"type":"Point"}
}