{
  "type": "Feature",
  "properties": {
    "iso:country":"DE",
    "sg:address":"Semlower Str. 14",
    "sg:city":"Eixen",
    "sg:phone":"+49 38222/457",
    "sg:postcode":"18334",
    "sg:province":"Mecklenburg-Vorpommern",
    "wof:name":"Landmaschinen Zilian Gbr",
    "wof:placetype":"venue"
},
  "geometry": {"coordinates":[12.714763,54.164707],"type":"Point"}
}