{
  "type": "Feature",
  "properties": {
    "iso:country":"DE",
    "sg:address":"Kirchplatz 4",
    "sg:city":"Auerbach",
    "sg:postcode":"08209",
    "sg:province":"Sachsen",
    "wof:name":"Ev.-luth. Kirche Auerbach",
    "wof:placetype":"venue"
},
  "geometry": {"coordinates":[12.4013175964,50.5088272095],"type":"Point"}
}