{
  "type": "Feature",
  "properties": {
    "iso:country":"DE",
    "sg:address":"Altenburger Str. 30",
    "sg:city":"Mittweida",
    "sg:phone":"+49 3727/92660",
    "sg:postcode":"09648",
    "sg:province":"Sachsen",
    "wof:name":"Fahrrad-g\u00fcnther",
    "wof:placetype":"venue"
},
  "geometry": {"coordinates":[12.952753,50.986416],"type":"Point"}
}