{
  "type": "Feature",
  "properties": {
    "iso:country":"DE",
    "sg:address":"Frankfurter Str. 38",
    "sg:city":"Bad Vilbel",
    "sg:postcode":"61118",
    "sg:province":"Hessen",
    "wof:name":"Mkb Baugesellschaft Mbh",
    "wof:placetype":"venue"
},
  "geometry": {"coordinates":[8.741555,50.181419],"type":"Point"}
}