{
  "type": "Feature",
  "properties": {
    "iso:country":"DE",
    "sg:address":"Krauss-Maffei-Str. 2",
    "sg:city":"M\u00fcnchen",
    "sg:phone":"+49 89/8122641",
    "sg:postcode":"80997",
    "sg:province":"Bayern",
    "wof:name":"Krauss-maffei Kunststofftechnik Gmbh",
    "wof:placetype":"venue"
},
  "geometry": {"coordinates":[11.466465,48.1922],"type":"Point"}
}