{
  "type": "Feature",
  "properties": {
    "iso:country":"DE",
    "sg:address":"Bahnhofstra\u00dfe 3",
    "sg:city":"Lilienthal",
    "sg:phone":"+49 4298",
    "sg:postcode":"28865",
    "sg:province":"Niedersachsen",
    "wof:name":"Seniorenbetreuungsgmbh,seniorenheim,altenheim,pflegeheim",
    "wof:placetype":"venue"
},
  "geometry": {"coordinates":[8.905822,53.141266],"type":"Point"}
}