{
  "type": "Feature",
  "properties": {
    "iso:country":"DE",
    "sg:address":"Vaihinger Str. 20",
    "sg:city":"Stuttgart",
    "sg:phone":"+49 711/714634",
    "sg:postcode":"70567",
    "sg:province":"Baden-W\u00fcrttemberg",
    "wof:name":"Friedrich R\u00f6hm",
    "wof:placetype":"venue"
},
  "geometry": {"coordinates":[9.1500091553,48.7288131714],"type":"Point"}
}