{
  "type": "Feature",
  "properties": {
    "iso:country":"DE",
    "sg:address":"T\u00fcrkisweg 5",
    "sg:city":"L\u00fcbeck",
    "sg:phone":"+49 451/602176",
    "sg:postcode":"23566",
    "sg:province":"Schleswig-Holstein",
    "wof:name":"H. Timmermann",
    "wof:placetype":"venue"
},
  "geometry": {"coordinates":[10.7412910461,53.8648338318],"type":"Point"}
}