{
  "type": "Feature",
  "properties": {
    "iso:country":"DE",
    "sg:address":"Samoborstr. 4-6",
    "sg:city":"Wirges",
    "sg:phone":"+49 4926/0269081",
    "sg:postcode":"56422",
    "sg:province":"Rheinland-Pfalz",
    "wof:name":"Lichtamik Keramik-leuchten Gmbh & Co. Kg",
    "wof:placetype":"venue"
},
  "geometry": {"coordinates":[7.793112,50.47332],"type":"Point"}
}