{
  "type": "Feature",
  "properties": {
    "iso:country":"DE",
    "sg:address":"Kurze Str. 3",
    "sg:city":"Pei\u00dfen",
    "sg:phone":"+49 3471/313418",
    "sg:postcode":"06408",
    "sg:province":"Sachsen-Anhalt",
    "wof:name":"D. Hinze",
    "wof:placetype":"venue"
},
  "geometry": {"coordinates":[11.761327,51.740284],"type":"Point"}
}