{
  "type": "Feature",
  "properties": {
    "iso:country":"DE",
    "sg:address":"Br\u00fcder-Grimm-Str. 50",
    "sg:city":"Steinau",
    "sg:phone":"+49 6663/6693",
    "sg:postcode":"36396",
    "sg:province":"Hessen",
    "wof:name":"C. Hill",
    "wof:placetype":"venue"
},
  "geometry": {"coordinates":[9.462182045,50.3132019043],"type":"Point"}
}