{
  "type": "Feature",
  "properties": {
    "iso:country":"DE",
    "sg:address":"Ferdinand-Miller-Platz 12",
    "sg:city":"M\u00fcnchen",
    "sg:phone":"+49 89/1232274",
    "sg:postcode":"80335",
    "sg:province":"Bayern",
    "wof:name":"Andreas Krau\u00df Hard- Und Soft- Wareservice Gmbh",
    "wof:placetype":"venue"
},
  "geometry": {"coordinates":[11.5530462265,48.1516342163],"type":"Point"}
}