{
  "type": "Feature",
  "properties": {
    "iso:country":"DE",
    "sg:address":"R\u00f6merstr. 18",
    "sg:city":"Worms",
    "sg:phone":"+49 6241/9040",
    "sg:postcode":"67547",
    "sg:province":"Rheinland-Pfalz",
    "wof:name":"Sophienstift",
    "wof:placetype":"venue"
},
  "geometry": {"coordinates":[8.363521,49.628296],"type":"Point"}
}