{
  "type": "Feature",
  "properties": {
    "iso:country":"DE",
    "sg:address":"Morsbacher Str. 13",
    "sg:city":"Titting",
    "sg:phone":"+49 8423/269",
    "sg:postcode":"85135",
    "sg:province":"Bayern",
    "wof:name":"Kath. Pfarramt St. Martin",
    "wof:placetype":"venue"
},
  "geometry": {"coordinates":[11.2109193802,48.9958343506],"type":"Point"}
}