{
  "type": "Feature",
  "properties": {
    "iso:country":"DE",
    "sg:address":"Hospitalstr. 34",
    "sg:city":"Ansbach",
    "sg:phone":"+49 981/9775505",
    "sg:postcode":"91522",
    "sg:province":"Bayern",
    "wof:name":"Prot. Alumneum Ansbach Staatl. Verw. Sch\u00fclerheim",
    "wof:placetype":"venue"
},
  "geometry": {"coordinates":[10.5600786209,49.3035392761],"type":"Point"}
}