{
  "type": "Feature",
  "properties": {
    "iso:country":"DE",
    "sg:address":"Chausseestr. 4",
    "sg:city":"Klostermansfeld",
    "sg:phone":"+49 34772/25213",
    "sg:postcode":"06308",
    "sg:province":"Sachsen-Anhalt",
    "wof:name":"Angela Werner",
    "wof:placetype":"venue"
},
  "geometry": {"coordinates":[11.493558,51.58474],"type":"Point"}
}