{
  "type": "Feature",
  "properties": {
    "iso:country":"DE",
    "sg:address":"Hauptstr. 151",
    "sg:city":"Wiedensahl",
    "sg:phone":"+49 5726/413",
    "sg:postcode":"31719",
    "sg:province":"Niedersachsen",
    "wof:name":"F. Wilkening",
    "wof:placetype":"venue"
},
  "geometry": {"coordinates":[9.118098,52.389973],"type":"Point"}
}