{
  "type": "Feature",
  "properties": {
    "iso:country":"DE",
    "sg:address":"Speckestr. 8",
    "sg:city":"Borgentreich",
    "sg:phone":"+49 5643/1621",
    "sg:postcode":"34434",
    "sg:province":"Nordrhein-Westfalen",
    "wof:name":"Josef Falke",
    "wof:placetype":"venue"
},
  "geometry": {"coordinates":[9.24243,51.567513],"type":"Point"}
}