{
  "type": "Feature",
  "properties": {
    "iso:country":"DE",
    "sg:address":"Bahnhofstr. 5",
    "sg:city":"Cainsdorf",
    "sg:postcode":"08124",
    "wof:name":"Labor Handel Zwickau Gmbh",
    "wof:placetype":"venue"
},
  "geometry": {"coordinates":[12.4948139191,50.6839256287],"type":"Point"}
}