{
  "type": "Feature",
  "properties": {
    "iso:country":"DE",
    "sg:address":"Bahnhofstr. 37-38",
    "sg:city":"Bremen",
    "sg:phone":"+49 421/12210",
    "sg:postcode":"28195",
    "sg:province":"Bremen",
    "wof:name":"Ebo-fachliteratur Ernst-bernhard Orthey",
    "wof:placetype":"venue"
},
  "geometry": {"coordinates":[8.8121137619,53.0818405151],"type":"Point"}
}