{
  "type": "Feature",
  "properties": {
    "iso:country":"DE",
    "sg:address":"Pirolweg 8",
    "sg:city":"M\u00fcnster",
    "sg:phone":"+49 251/61366",
    "sg:postcode":"48167",
    "sg:province":"Nordrhein-Westfalen",
    "wof:name":"Karl Friedrich Bell Verwaltungs Gmbh",
    "wof:placetype":"venue"
},
  "geometry": {"coordinates":[7.6818060875,51.9313621521],"type":"Point"}
}