{
  "type": "Feature",
  "properties": {
    "iso:country":"DE",
    "sg:address":"Ginsterweg 6",
    "sg:city":"Freudenstadt",
    "sg:phone":"+49 7443/5191",
    "sg:postcode":"72250",
    "sg:province":"Baden-W\u00fcrttemberg",
    "wof:name":"Eduard Missal",
    "wof:placetype":"venue"
},
  "geometry": {"coordinates":[8.46217,48.477787],"type":"Point"}
}