{
  "type": "Feature",
  "properties": {
    "iso:country":"DE",
    "sg:address":"Lange Str. 54",
    "sg:city":"Diepholz",
    "sg:phone":"+49 5441/4542",
    "sg:postcode":"49356",
    "sg:province":"Niedersachsen",
    "wof:name":"Grafen-apotheke",
    "wof:placetype":"venue"
},
  "geometry": {"coordinates":[8.369897,52.607765],"type":"Point"}
}