{
  "type": "Feature",
  "properties": {
    "iso:country":"DE",
    "sg:address":"Eilbeker Weg 208",
    "sg:city":"Hamburg",
    "sg:phone":"+49 40/2006161",
    "sg:postcode":"22089",
    "sg:province":"Hamburg",
    "wof:name":"L. Blaudzun & M. Kohlhaus",
    "wof:placetype":"venue"
},
  "geometry": {"coordinates":[10.056211,53.573376],"type":"Point"}
}