{
  "type": "Feature",
  "properties": {
    "iso:country":"DE",
    "sg:address":"Hauptstr. 31",
    "sg:city":"Altmittweida",
    "sg:postcode":"09648",
    "sg:province":"Sachsen",
    "wof:name":"Dachdeckerei Nikoleit Gmbh",
    "wof:placetype":"venue"
},
  "geometry": {"coordinates":[12.966059,50.969727],"type":"Point"}
}