{
  "type": "Feature",
  "properties": {
    "iso:country":"DE",
    "sg:address":"An der Katharinenkirche 12- 15",
    "sg:city":"Braunschweig",
    "sg:postcode":"38100",
    "sg:province":"Niedersachsen",
    "wof:name":"Bsb Bierb\u00f6rse Gmbh",
    "wof:placetype":"venue"
},
  "geometry": {"coordinates":[10.5262842178,52.2674865723],"type":"Point"}
}