{
  "type": "Feature",
  "properties": {
    "iso:country":"DE",
    "sg:address":"M\u00fchlenstr. 7",
    "sg:city":"Stralsund",
    "sg:postcode":"18439",
    "sg:province":"Mecklenburg-Vorpommern",
    "wof:name":"Metis-immobilien Hausmeister Service Gmbh",
    "wof:placetype":"venue"
},
  "geometry": {"coordinates":[13.088785,54.31612],"type":"Point"}
}