{
  "type": "Feature",
  "properties": {
    "iso:country":"DE",
    "sg:address":"Schmerlingstr. 27",
    "sg:city":"Selm",
    "sg:phone":"+49 2592/3328",
    "sg:postcode":"59379",
    "sg:province":"Nordrhein-Westfalen",
    "wof:name":"Hubertus Pohl",
    "wof:placetype":"venue"
},
  "geometry": {"coordinates":[7.4622821808,51.6888427734],"type":"Point"}
}