{
  "type": "Feature",
  "properties": {
    "iso:country":"DE",
    "sg:address":"Herta-Lindner-Str. 8",
    "sg:city":"Bernburg",
    "sg:phone":"+49 3471/350700",
    "sg:postcode":"06406",
    "sg:province":"Sachsen-Anhalt",
    "wof:name":"Michael Schwarz",
    "wof:placetype":"venue"
},
  "geometry": {"coordinates":[11.724527359,51.8119850159],"type":"Point"}
}