{
  "type": "Feature",
  "properties": {
    "iso:country":"DE",
    "sg:address":"Elisabethkirchstr. 7",
    "sg:city":"Berlin",
    "sg:phone":"+49 30/44052440",
    "sg:postcode":"10115",
    "sg:province":"Berlin",
    "wof:name":"Detlef Dornbach Architekt",
    "wof:placetype":"venue"
},
  "geometry": {"coordinates":[13.397782,52.533386],"type":"Point"}
}