{
  "type": "Feature",
  "properties": {
    "iso:country":"DE",
    "sg:address":"Wiebestr. 12-18 Centro Park",
    "sg:city":"Berlin",
    "sg:phone":"+49 30/3497750",
    "sg:postcode":"10553",
    "sg:province":"Berlin",
    "wof:name":"Joh. Peters Sen. Gmbh",
    "wof:placetype":"venue"
},
  "geometry": {"coordinates":[13.3201503754,52.5288505554],"type":"Point"}
}