{
  "type": "Feature",
  "properties": {
    "iso:country":"DE",
    "sg:address":"Dorfstr. 18",
    "sg:city":"Kolochau",
    "sg:phone":"+49 35361/80220",
    "sg:postcode":"04936",
    "sg:province":"Brandenburg",
    "wof:name":"Wolfgang Bommel",
    "wof:placetype":"venue"
},
  "geometry": {"coordinates":[13.3221206665,51.7253723145],"type":"Point"}
}