{
  "type": "Feature",
  "properties": {
    "iso:country":"DE",
    "sg:address":"Bornberg 55",
    "sg:city":"Wuppertal",
    "sg:phone":"+49 202/75709",
    "sg:postcode":"42109",
    "sg:province":"Nordrhein-Westfalen",
    "wof:name":"Ludger M\u00fcller Heilpraktiker",
    "wof:placetype":"venue"
},
  "geometry": {"coordinates":[7.1541018486,51.2741851807],"type":"Point"}
}