{
  "type": "Feature",
  "properties": {
    "iso:country":"DE",
    "sg:address":"Am H\u00fcnenstein 20",
    "sg:city":"Osterholz-Scharmbeck",
    "sg:phone":"+49 4791/7877",
    "sg:postcode":"27711",
    "sg:province":"Niedersachsen",
    "wof:name":"Hannelore B\u00f6ttjer Schilder Vertrieb",
    "wof:placetype":"venue"
},
  "geometry": {"coordinates":[8.796783,53.228596],"type":"Point"}
}