{
  "type": "Feature",
  "properties": {
    "iso:country":"DE",
    "sg:address":"Kurmainzer Str. 6",
    "sg:city":"Bischbrunn",
    "sg:phone":"+49 9394/1447",
    "sg:postcode":"97836",
    "sg:province":"Bayern",
    "wof:name":"J. Schwab",
    "wof:placetype":"venue"
},
  "geometry": {"coordinates":[9.496679306,49.863910675],"type":"Point"}
}