{
  "type": "Feature",
  "properties": {
    "iso:country":"DE",
    "sg:address":"Stuttgarter Str. 10",
    "sg:city":"Fellbach",
    "sg:phone":"+49 711/3260756",
    "sg:postcode":"70736",
    "sg:province":"Baden-W\u00fcrttemberg",
    "wof:name":"Posth\u00f6rnle",
    "wof:placetype":"venue"
},
  "geometry": {"coordinates":[9.2733249664,48.8141860962],"type":"Point"}
}