{
  "type": "Feature",
  "properties": {
    "iso:country":"DE",
    "sg:address":"Fischbacher Str. 45a",
    "sg:city":"Kelkheim",
    "sg:phone":"+49 6195/73983",
    "sg:postcode":"65779",
    "sg:province":"Hessen",
    "wof:name":"L. Walch",
    "wof:placetype":"venue"
},
  "geometry": {"coordinates":[8.4399261475,50.1402053833],"type":"Point"}
}