{
  "type": "Feature",
  "properties": {
    "iso:country":"DE",
    "sg:address":"Poststr. 5",
    "sg:city":"Offenburg",
    "sg:phone":"+49 781/72004",
    "sg:postcode":"77652",
    "sg:province":"Baden-W\u00fcrttemberg",
    "wof:name":"Centralhotel",
    "wof:placetype":"venue"
},
  "geometry": {"coordinates":[7.943543911,48.4740486145],"type":"Point"}
}