{
  "type": "Feature",
  "properties": {
    "iso:country":"DE",
    "sg:address":"Kirchplatz 3",
    "sg:city":"Frauenneuharting",
    "sg:phone":"+49 8092/83273",
    "sg:postcode":"83553",
    "sg:province":"Bayern",
    "wof:name":"Franz Gschwendtner",
    "wof:placetype":"venue"
},
  "geometry": {"coordinates":[12.0482616425,48.0388870239],"type":"Point"}
}