{
  "type": "Feature",
  "properties": {
    "iso:country":"DE",
    "sg:address":"Brauhausstr. 7",
    "sg:city":"R\u00f6ckingen",
    "sg:phone":"+49 9832/67888",
    "sg:postcode":"91740",
    "sg:province":"Bayern",
    "wof:name":"Engelbr\u00e4u Betriebsges. Mbh Wilhelm Teufel",
    "wof:placetype":"venue"
},
  "geometry": {"coordinates":[10.559173,49.056057],"type":"Point"}
}