{
  "type": "Feature",
  "properties": {
    "iso:country":"DE",
    "sg:address":"Hauptstr. 22",
    "sg:city":"Schramberg",
    "sg:phone":"+49 7422/4282",
    "sg:postcode":"78713",
    "sg:province":"Baden-W\u00fcrttemberg",
    "wof:name":"Central-apotheke",
    "wof:placetype":"venue"
},
  "geometry": {"coordinates":[8.38457,48.22578],"type":"Point"}
}