{
  "type": "Feature",
  "properties": {
    "iso:country":"DE",
    "sg:address":"Hafenstr. 58-60",
    "sg:city":"Neuss",
    "sg:phone":"+49 2131/754508",
    "sg:postcode":"41460",
    "sg:province":"Nordrhein-Westfalen",
    "wof:name":"C. E. T. Cingoez",
    "wof:placetype":"venue"
},
  "geometry": {"coordinates":[6.6898207664,51.2021446228],"type":"Point"}
}