{
  "type": "Feature",
  "properties": {
    "iso:country":"DE",
    "sg:address":"Bernhardstr. 111",
    "sg:city":"Chemnitz",
    "sg:postcode":"09126",
    "sg:province":"Sachsen",
    "wof:name":"B\u00e4ckerei Meyer & Meyer Ohg",
    "wof:placetype":"venue"
},
  "geometry": {"coordinates":[12.950256,50.830265],"type":"Point"}
}