{
  "type": "Feature",
  "properties": {
    "iso:country":"DE",
    "sg:address":"Viktoriastr. 26",
    "sg:city":"Minden",
    "sg:phone":"+49 571/30102",
    "sg:postcode":"32423",
    "sg:province":"Nordrhein-Westfalen",
    "wof:name":"Ihr Pflanzencenter Dill Gmbh",
    "wof:placetype":"venue"
},
  "geometry": {"coordinates":[8.93884,52.288837],"type":"Point"}
}