{
  "type": "Feature",
  "properties": {
    "iso:country":"DE",
    "sg:address":"Zusamweg 4",
    "sg:city":"Donauw\u00f6rth",
    "sg:phone":"+49 906/22330",
    "sg:postcode":"86609",
    "sg:province":"Bayern",
    "wof:name":"Softwork Gmbh",
    "wof:placetype":"venue"
},
  "geometry": {"coordinates":[10.7837457657,48.7107467651],"type":"Point"}
}