{
  "type": "Feature",
  "properties": {
    "iso:country":"DE",
    "sg:address":"Am Venusberg 19",
    "sg:city":"Lorch",
    "sg:postcode":"73547",
    "sg:province":"Baden-W\u00fcrttemberg",
    "wof:name":"R\u00f6hr Verwaltungs- Gesellschaft Mbh",
    "wof:placetype":"venue"
},
  "geometry": {"coordinates":[9.694685936,48.7995834351],"type":"Point"}
}