{
  "type": "Feature",
  "properties": {
    "iso:country":"DE",
    "sg:address":"Domstiftstr. 2",
    "sg:city":"Erlangen",
    "sg:phone":"+49 9135/483",
    "sg:postcode":"91056",
    "sg:province":"Bayern",
    "wof:name":"Ewald Schneider",
    "wof:placetype":"venue"
},
  "geometry": {"coordinates":[10.9415836334,49.630695343],"type":"Point"}
}