{
  "type": "Feature",
  "properties": {
    "iso:country":"DE",
    "sg:address":"Bruckner Strasse 2",
    "sg:city":"M\u00fcnchen",
    "sg:phone":"+49 89/41079392",
    "sg:postcode":"81677",
    "sg:province":"Bayern",
    "wof:name":"Job On Ship",
    "wof:placetype":"venue"
},
  "geometry": {"coordinates":[11.612023,48.13855],"type":"Point"}
}