{
  "type": "Feature",
  "properties": {
    "iso:country":"DE",
    "sg:address":"Buschweg 1",
    "sg:city":"Schwalmtal",
    "sg:phone":"+49 2163/1587",
    "sg:postcode":"41366",
    "sg:province":"Nordrhein-Westfalen",
    "wof:name":"B. Jordans",
    "wof:placetype":"venue"
},
  "geometry": {"coordinates":[6.2324857712,51.2217330933],"type":"Point"}
}