{
  "type": "Feature",
  "properties": {
    "iso:country":"DE",
    "sg:address":"Carl-Benz-Str. 4",
    "sg:city":"Hof",
    "sg:phone":"+49 9281/97760",
    "sg:postcode":"95032",
    "sg:province":"Bayern",
    "wof:name":"Autoveri Weissberg Gmbh",
    "wof:placetype":"venue"
},
  "geometry": {"coordinates":[11.9180450439,50.3029823303],"type":"Point"}
}