{
  "type": "Feature",
  "properties": {
    "iso:country":"DE",
    "sg:address":"Wendoche",
    "sg:city":"Belzig",
    "sg:phone":"+49 33846/5990",
    "sg:postcode":"14806",
    "sg:province":"Brandenburg",
    "wof:name":"Fl\u00e4ming Hotel",
    "wof:placetype":"venue"
},
  "geometry": {"coordinates":[12.5992641449,52.1819381714],"type":"Point"}
}