{
  "type": "Feature",
  "properties": {
    "iso:country":"DE",
    "sg:address":"Untere Ein\u00f6de 10",
    "sg:city":"Woringen",
    "sg:phone":"+49 8331/48346",
    "sg:postcode":"87789",
    "sg:province":"Bayern",
    "wof:name":"Ipe Gmbh",
    "wof:placetype":"venue"
},
  "geometry": {"coordinates":[10.194322,47.94529],"type":"Point"}
}