{
  "type": "Feature",
  "properties": {
    "iso:country":"DE",
    "sg:address":"Waldbleeke 3",
    "sg:city":"M\u00fclheim",
    "sg:phone":"+49 208/482946",
    "sg:postcode":"45481",
    "sg:province":"Nordrhein-Westfalen",
    "wof:name":"Klaus B\u00f6llert",
    "wof:placetype":"venue"
},
  "geometry": {"coordinates":[6.851803,51.406761],"type":"Point"}
}