{
  "type": "Feature",
  "properties": {
    "iso:country":"DE",
    "sg:address":"Ludwigstr. 179",
    "sg:city":"M\u00fcnchen",
    "sg:postcode":"80539",
    "sg:province":"Bayern",
    "wof:name":"Bil Beratungsgesellschaft F\u00fcr Investitionsg\u00fcter Leasing Gmbh",
    "wof:placetype":"venue"
},
  "geometry": {"coordinates":[11.58185,48.15221],"type":"Point"}
}