{
  "type": "Feature",
  "properties": {
    "iso:country":"DE",
    "sg:address":"Pannsweg 20",
    "sg:city":"Hamburg",
    "sg:phone":"+49 40/53718003",
    "sg:postcode":"22417",
    "sg:province":"Hamburg",
    "wof:name":"Iwan Verwaltungs- Gesellschaft Mbh",
    "wof:placetype":"venue"
},
  "geometry": {"coordinates":[10.0200643539,53.6803474426],"type":"Point"}
}