{
  "type": "Feature",
  "properties": {
    "iso:country":"DE",
    "sg:address":"Erbacher Str. 65",
    "sg:city":"F\u00fcrth",
    "sg:phone":"+49 6253/84938",
    "sg:postcode":"64658",
    "sg:province":"Hessen",
    "wof:name":"Hhb Hans Helmling Baumaschinen Gmbh & Co. Kg",
    "wof:placetype":"venue"
},
  "geometry": {"coordinates":[8.786245,49.654373],"type":"Point"}
}