{
  "type": "Feature",
  "properties": {
    "iso:country":"DE",
    "sg:address":"Saarlouiser Str. 25",
    "sg:city":"Dillingen",
    "sg:phone":"+49 6831/707023",
    "sg:postcode":"66763",
    "sg:province":"Saarland",
    "wof:name":"Satrans Speditions Gmbh",
    "wof:placetype":"venue"
},
  "geometry": {"coordinates":[6.718629837,49.3581504822],"type":"Point"}
}