{
  "type": "Feature",
  "properties": {
    "iso:country":"DE",
    "sg:address":"Spielbergsweg 34",
    "sg:city":"Velbert",
    "sg:phone":"+49 2052/4081",
    "sg:postcode":"42555",
    "sg:province":"Nordrhein-Westfalen",
    "wof:name":"Gerd Matten",
    "wof:placetype":"venue"
},
  "geometry": {"coordinates":[7.118257,51.340164],"type":"Point"}
}