{
  "type": "Feature",
  "properties": {
    "iso:country":"DE",
    "sg:address":"Triefenbergweg 39",
    "sg:city":"Schlangenbad",
    "sg:phone":"+49 6129/2550",
    "sg:postcode":"65388",
    "sg:province":"Hessen",
    "wof:name":"Pizzeria Alla Pergola",
    "wof:placetype":"venue"
},
  "geometry": {"coordinates":[8.1021203995,50.0929870605],"type":"Point"}
}