{
  "type": "Feature",
  "properties": {
    "iso:country":"DE",
    "sg:address":"Osterstr. 37",
    "sg:city":"Burg",
    "sg:phone":"+49 4371/3333",
    "sg:postcode":"23769",
    "sg:province":"Schleswig-Holstein",
    "wof:name":"Pension P. Und S. Kienzl",
    "wof:placetype":"venue"
},
  "geometry": {"coordinates":[11.1994428635,54.4367485046],"type":"Point"}
}