{
  "type": "Feature",
  "properties": {
    "iso:country":"DE",
    "sg:address":"Groppstr. 9",
    "sg:city":"Bad Kissingen",
    "sg:phone":"+49 971/3378",
    "sg:postcode":"97688",
    "sg:province":"Bayern",
    "wof:name":"Voll",
    "wof:placetype":"venue"
},
  "geometry": {"coordinates":[10.080845,50.203201],"type":"Point"}
}