{
  "type": "Feature",
  "properties": {
    "iso:country":"DE",
    "sg:address":"Werner-Heisenberg-Str. 1",
    "sg:city":"Bexbach",
    "sg:phone":"+49 6826/81311",
    "sg:postcode":"66450",
    "sg:province":"Saarland",
    "wof:name":"P. K\u00f6nsgen Immobilienmakler",
    "wof:placetype":"venue"
},
  "geometry": {"coordinates":[7.2505722046,49.3630218506],"type":"Point"}
}