{
  "type": "Feature",
  "properties": {
    "iso:country":"DE",
    "sg:address":"Eversener Str. 12",
    "sg:city":"Kirchlinteln",
    "sg:phone":"+49 4230/443",
    "sg:postcode":"27308",
    "sg:province":"Niedersachsen",
    "wof:name":"B. Purat",
    "wof:placetype":"venue"
},
  "geometry": {"coordinates":[9.298057,52.997547],"type":"Point"}
}