{
  "type": "Feature",
  "properties": {
    "iso:country":"DE",
    "sg:address":"Dorfstr. 5",
    "sg:city":"Wefensleben",
    "sg:phone":"+49 39400/2392",
    "sg:postcode":"39365",
    "sg:province":"Sachsen-Anhalt",
    "wof:name":"Detlef Brandes",
    "wof:placetype":"venue"
},
  "geometry": {"coordinates":[11.160122,52.184311],"type":"Point"}
}