{
  "type": "Feature",
  "properties": {
    "iso:country":"DE",
    "sg:address":"Donaustaufer Str. 112",
    "sg:city":"Regensburg",
    "sg:postcode":"93059",
    "sg:province":"Bayern",
    "wof:name":"Evr Eisb\u00e4ren Betriebs Gmbh",
    "wof:placetype":"venue"
},
  "geometry": {"coordinates":[12.1187992096,49.0289878845],"type":"Point"}
}