{
  "type": "Feature",
  "properties": {
    "iso:country":"DE",
    "sg:address":"Christine-Englerth-Str. 1",
    "sg:city":"Recklinghausen",
    "sg:phone":"+49 2361/983018",
    "sg:postcode":"45665",
    "sg:province":"Nordrhein-Westfalen",
    "wof:name":"Stork Materieel Gmbh",
    "wof:placetype":"venue"
},
  "geometry": {"coordinates":[7.246628,51.606071],"type":"Point"}
}