{
  "type": "Feature",
  "properties": {
    "iso:country":"DE",
    "sg:address":"Am Bittmorgen 10",
    "sg:city":"Bad Windsheim",
    "sg:phone":"+49 9841/5590",
    "sg:postcode":"91438",
    "sg:province":"Bayern",
    "wof:name":"Richard Wattenbach",
    "wof:placetype":"venue"
},
  "geometry": {"coordinates":[10.3996953964,49.5111999512],"type":"Point"}
}