{
  "type": "Feature",
  "properties": {
    "iso:country":"DE",
    "sg:address":"Rappoltweg 11",
    "sg:city":"Hamburg",
    "sg:phone":"+49 40/7381918",
    "sg:postcode":"21031",
    "sg:province":"Hamburg",
    "wof:name":"I. Hoops",
    "wof:placetype":"venue"
},
  "geometry": {"coordinates":[10.197343,53.510139],"type":"Point"}
}