{
  "type": "Feature",
  "properties": {
    "iso:country":"DE",
    "sg:address":"Mangenberger Str. 180",
    "sg:city":"Solingen",
    "sg:phone":"+49 212/12470",
    "sg:postcode":"42655",
    "sg:province":"Nordrhein-Westfalen",
    "wof:name":"Waldheim",
    "wof:placetype":"venue"
},
  "geometry": {"coordinates":[7.0571689606,51.1683807373],"type":"Point"}
}