{
  "type": "Feature",
  "properties": {
    "iso:country":"DE",
    "sg:address":"L\u00f6wengasse 27c",
    "sg:city":"Frankfurt",
    "sg:phone":"+49 69/4600050",
    "sg:postcode":"60385",
    "sg:province":"Hessen",
    "wof:name":"Stegmeyer - Helker Kommunikation Gmbh",
    "wof:placetype":"venue"
},
  "geometry": {"coordinates":[8.712955,50.12801],"type":"Point"}
}