{
  "type": "Feature",
  "properties": {
    "iso:country":"DE",
    "sg:address":"Landsberger Str. 490",
    "sg:city":"M\u00fcnchen",
    "sg:phone":"+49 89/832127",
    "sg:postcode":"81241",
    "sg:province":"Bayern",
    "wof:name":"Landesbausparkasse Beratungsstelle",
    "wof:placetype":"venue"
},
  "geometry": {"coordinates":[11.461184,48.146755],"type":"Point"}
}