{
  "type": "Feature",
  "properties": {
    "iso:country":"DE",
    "sg:address":"Lindenallee 39",
    "sg:city":"Cloppenburg",
    "sg:phone":"+49 4471/4043",
    "sg:postcode":"49661",
    "sg:province":"Niedersachsen",
    "wof:name":"Schlemmer-grill",
    "wof:placetype":"venue"
},
  "geometry": {"coordinates":[8.0833387375,52.8424072266],"type":"Point"}
}