{
  "type": "Feature",
  "properties": {
    "iso:country":"DE",
    "sg:address":"Schulstr. 36",
    "sg:city":"Leverkusen",
    "sg:phone":"+49 214/46458",
    "sg:postcode":"51373",
    "sg:province":"Nordrhein-Westfalen",
    "wof:name":"Otto Plickert Steuerberater",
    "wof:placetype":"venue"
},
  "geometry": {"coordinates":[6.981388092,51.0301094055],"type":"Point"}
}