{
  "type": "Feature",
  "properties": {
    "iso:country":"DE",
    "sg:address":"F\u00fcrther Str. 60",
    "sg:city":"N\u00fcrnberg",
    "sg:phone":"+49 911/2877410",
    "sg:postcode":"90429",
    "sg:province":"Bayern",
    "wof:name":"Cerovac Nebojsa Anlageberater",
    "wof:placetype":"venue"
},
  "geometry": {"coordinates":[11.0546884537,49.451499939],"type":"Point"}
}