{
  "type": "Feature",
  "properties": {
    "iso:country":"DE",
    "sg:address":"Thiemannstr. 20",
    "sg:city":"Friesack",
    "sg:phone":"+49 33235/1825",
    "sg:postcode":"14662",
    "sg:province":"Brandenburg",
    "wof:name":"I & K Bauelemente Gbr",
    "wof:placetype":"venue"
},
  "geometry": {"coordinates":[12.586232,52.737663],"type":"Point"}
}