{
  "type": "Feature",
  "properties": {
    "iso:country":"DE",
    "sg:address":"Ritterstr. 113",
    "sg:city":"Viersen",
    "sg:phone":"+49 2162/70739",
    "sg:postcode":"41749",
    "sg:province":"Nordrhein-Westfalen",
    "wof:name":"Johannes Erkes",
    "wof:placetype":"venue"
},
  "geometry": {"coordinates":[6.329753,51.305664],"type":"Point"}
}