{
  "type": "Feature",
  "properties": {
    "iso:country":"DE",
    "sg:address":"Neudecker Weg 97",
    "sg:city":"Berlin",
    "sg:phone":"+49 30/6635432",
    "sg:postcode":"12355",
    "sg:province":"Berlin",
    "wof:name":"Walter Glatzel",
    "wof:placetype":"venue"
},
  "geometry": {"coordinates":[13.504784584,52.4182472229],"type":"Point"}
}