{
  "type": "Feature",
  "properties": {
    "iso:country":"DE",
    "sg:address":"Pfeilstr. 37",
    "sg:city":"Solingen",
    "sg:phone":"+49 4921/2331031",
    "sg:postcode":"42699",
    "sg:province":"Nordrhein-Westfalen",
    "wof:name":"Klaas Gmbh & Co Kg, Robert",
    "wof:placetype":"venue"
},
  "geometry": {"coordinates":[7.0199341774,51.1619529724],"type":"Point"}
}