{
  "type": "Feature",
  "properties": {
    "iso:country":"DE",
    "sg:address":"Robert-Koch-Str. 15",
    "sg:city":"Simmerath",
    "sg:phone":"+49 2473/1473",
    "sg:postcode":"52152",
    "sg:province":"Nordrhein-Westfalen",
    "wof:name":"A. B\u00e4hr",
    "wof:placetype":"venue"
},
  "geometry": {"coordinates":[6.3037819862,50.6059570312],"type":"Point"}
}