{
  "type": "Feature",
  "properties": {
    "iso:country":"DE",
    "sg:address":"Steinwinkel 3",
    "sg:city":"Nachrodt-Wiblingwerde",
    "sg:phone":"+49 2334/40624",
    "sg:postcode":"58769",
    "sg:province":"Nordrhein-Westfalen",
    "wof:name":"Gernot Bahr",
    "wof:placetype":"venue"
},
  "geometry": {"coordinates":[7.638176,51.331902],"type":"Point"}
}