{
  "type": "Feature",
  "properties": {
    "iso:country":"DE",
    "sg:address":"Zeppelinstr. 12",
    "sg:city":"D\u00fcren",
    "sg:phone":"+49 2421/54128",
    "sg:postcode":"52351",
    "sg:province":"Nordrhein-Westfalen",
    "wof:name":"Heinz Pesch Immobilienmakler",
    "wof:placetype":"venue"
},
  "geometry": {"coordinates":[6.4903359413,50.7959251404],"type":"Point"}
}