{
  "type": "Feature",
  "properties": {
    "iso:country":"DE",
    "sg:address":"Seewiesenstr. 31",
    "sg:city":"Friedrichshafen",
    "sg:phone":"+49 7541/372987",
    "sg:postcode":"88046",
    "sg:province":"Baden-W\u00fcrttemberg",
    "wof:name":"Schnakencafe",
    "wof:placetype":"venue"
},
  "geometry": {"coordinates":[9.505578,47.643951],"type":"Point"}
}