{
  "type": "Feature",
  "properties": {
    "iso:country":"DE",
    "sg:address":"Postfach 104041:: 50480 Cologne:: Germany.^^Sachsenring 83::",
    "sg:city":"Cologne",
    "sg:phone":"+49 221/20120",
    "sg:postcode":"50677",
    "sg:province":"Nordrhein-Westfalen",
    "wof:name":"Wtb Westdeutsche Kreditbank Gmbh & Co Kg",
    "wof:placetype":"venue"
},
  "geometry": {"coordinates":[6.95989,50.940552],"type":"Point"}
}