{
  "type": "Feature",
  "properties": {
    "iso:country":"DE",
    "sg:address":"Wittbr\u00e4ucker Str. 373",
    "sg:city":"Dortmund",
    "sg:phone":"+49 231/468102",
    "sg:postcode":"44267",
    "sg:province":"Nordrhein-Westfalen",
    "wof:name":"Elke Krane H\u00e4usliche Kranken- Und Altenpflege",
    "wof:placetype":"venue"
},
  "geometry": {"coordinates":[7.523942,51.46566],"type":"Point"}
}