{
  "type": "Feature",
  "properties": {
    "iso:country":"DE",
    "sg:address":"Otto-Hahn-Str. 6",
    "sg:city":"Brake",
    "sg:phone":"+49 4401/81351",
    "sg:postcode":"26919",
    "sg:province":"Niedersachsen",
    "wof:name":"Hermann Sch\u00f6ne Inh. Zimmermann",
    "wof:placetype":"venue"
},
  "geometry": {"coordinates":[8.466176,53.336391],"type":"Point"}
}