{
  "type": "Feature",
  "properties": {
    "iso:country":"DE",
    "sg:address":"Zur Sandkuhle 7",
    "sg:city":"Ostenfeld",
    "sg:phone":"+49 4845/327",
    "sg:postcode":"25872",
    "sg:province":"Schleswig-Holstein",
    "wof:name":"Hermann Thiesen",
    "wof:placetype":"venue"
},
  "geometry": {"coordinates":[9.236869,54.46384],"type":"Point"}
}