{
  "type": "Feature",
  "properties": {
    "iso:country":"DE",
    "sg:address":"In den Schwarzwiesen 22",
    "sg:city":"Oberursel",
    "sg:phone":"+49 6171/85262",
    "sg:postcode":"61440",
    "sg:province":"Hessen",
    "wof:name":"Waldemar E. Winkler",
    "wof:placetype":"venue"
},
  "geometry": {"coordinates":[8.588251,50.187874],"type":"Point"}
}