{
  "type": "Feature",
  "properties": {
    "iso:country":"DE",
    "sg:address":"Katharinenstr. 6",
    "sg:city":"Annaberg-Buchholz",
    "sg:phone":"+49 3733/65323",
    "sg:postcode":"09456",
    "sg:province":"Sachsen",
    "wof:name":"Werner Uhlig",
    "wof:placetype":"venue"
},
  "geometry": {"coordinates":[12.9969587326,50.5693244934],"type":"Point"}
}