{
  "type": "Feature",
  "properties": {
    "iso:country":"DE",
    "sg:address":"Fuchsweg 11",
    "sg:city":"Kirchheim",
    "sg:phone":"+49 7021/6174",
    "sg:postcode":"73230",
    "sg:province":"Baden-W\u00fcrttemberg",
    "wof:name":"I. Nachfolger",
    "wof:placetype":"venue"
},
  "geometry": {"coordinates":[9.4693622589,48.6487388611],"type":"Point"}
}