{
  "type": "Feature",
  "properties": {
    "iso:country":"DE",
    "sg:address":"K\u00f6lner Str. 76",
    "sg:city":"Kierspe",
    "sg:phone":"+49 2359/7001",
    "sg:postcode":"58566",
    "sg:province":"Nordrhein-Westfalen",
    "wof:name":"Provinzial-versicherung Der Sparkassen",
    "wof:placetype":"venue"
},
  "geometry": {"coordinates":[7.6125020981,51.1260261536],"type":"Point"}
}