{
  "type": "Feature",
  "properties": {
    "iso:country":"DE",
    "sg:address":"Hermannsplatz 1",
    "sg:city":"Murr",
    "sg:phone":"+49 7144/25350",
    "sg:postcode":"71711",
    "sg:province":"Baden-W\u00fcrttemberg",
    "wof:name":"Vereinsgastst\u00e4tte Sport- Und Gesangverein E. V.",
    "wof:placetype":"venue"
},
  "geometry": {"coordinates":[9.2625465393,48.962184906],"type":"Point"}
}