{
  "type": "Feature",
  "properties": {
    "iso:country":"DE",
    "sg:address":"J.-B.-Siegfried-Str.",
    "sg:city":"Hochheim",
    "sg:phone":"+49 6146/5749",
    "sg:postcode":"65239",
    "sg:province":"Hessen",
    "wof:name":"A. Mohr",
    "wof:placetype":"venue"
},
  "geometry": {"coordinates":[8.35691,50.014114],"type":"Point"}
}