{
  "type": "Feature",
  "properties": {
    "iso:country":"DE",
    "sg:address":"Lilienstr 35",
    "sg:city":"Renningen",
    "sg:phone":"+49 7159/920430",
    "sg:postcode":"71272",
    "sg:province":"Baden-W\u00fcrttemberg",
    "wof:name":"Wip Gmbh",
    "wof:placetype":"venue"
},
  "geometry": {"coordinates":[8.91228,48.776981],"type":"Point"}
}