{
  "type": "Feature",
  "properties": {
    "iso:country":"DE",
    "sg:address":"G\u00e4rtnerstr. 16",
    "sg:city":"Wallersdorf",
    "sg:phone":"+49 9933/1334",
    "sg:postcode":"94522",
    "sg:province":"Bayern",
    "wof:name":"Josef St\u00f6mmer",
    "wof:placetype":"venue"
},
  "geometry": {"coordinates":[12.748775,48.734203],"type":"Point"}
}