{
  "type": "Feature",
  "properties": {
    "iso:country":"DE",
    "sg:address":"Zimmersm\u00fchlenweg 62",
    "sg:city":"Oberursel",
    "sg:phone":"+49 6171/98670",
    "sg:postcode":"61440",
    "sg:province":"Hessen",
    "wof:name":"Point 2000 Ag",
    "wof:placetype":"venue"
},
  "geometry": {"coordinates":[8.585931,50.188351],"type":"Point"}
}