{
  "type": "Feature",
  "properties": {
    "iso:country":"DE",
    "sg:address":"Wallweg 41",
    "sg:city":"Hanau",
    "sg:postcode":"63450",
    "sg:province":"Hessen",
    "wof:name":"Yazici Flugdienst Gmbh",
    "wof:placetype":"venue"
},
  "geometry": {"coordinates":[8.9183750153,50.1295967102],"type":"Point"}
}