{
  "type": "Feature",
  "properties": {
    "iso:country":"DE",
    "sg:address":"Hauptstr. 55",
    "sg:city":"Kappelrodeck",
    "sg:phone":"+49 7842/555",
    "sg:postcode":"77876",
    "sg:province":"Baden-W\u00fcrttemberg",
    "wof:name":"Hermann Springmann",
    "wof:placetype":"venue"
},
  "geometry": {"coordinates":[8.117284,48.591591],"type":"Point"}
}