{
  "type": "Feature",
  "properties": {
    "iso:country":"DE",
    "sg:address":"Deichstr. 90",
    "sg:city":"Bremerhaven",
    "sg:phone":"+49 471/40044",
    "sg:postcode":"27568",
    "sg:province":"Bremen",
    "wof:name":"Nordsee-taxen E. V.",
    "wof:placetype":"venue"
},
  "geometry": {"coordinates":[8.5812044144,53.5444526672],"type":"Point"}
}