{
  "type": "Feature",
  "properties": {
    "iso:country":"DE",
    "sg:address":"Nernstweg 32-34",
    "sg:city":"Hamburg",
    "sg:postcode":"22765",
    "sg:province":"Hamburg",
    "wof:name":"Abz Abbildungszentrum Ohg",
    "wof:placetype":"venue"
},
  "geometry": {"coordinates":[9.9326295853,53.5563201904],"type":"Point"}
}