{
  "type": "Feature",
  "properties": {
    "iso:country":"DE",
    "sg:address":"Bleichstr. 4",
    "sg:city":"Maintal",
    "sg:phone":"+49 6181/983231",
    "sg:postcode":"63477",
    "sg:province":"Hessen",
    "wof:name":"Marlies Scheerer Briefmarkenversand",
    "wof:placetype":"venue"
},
  "geometry": {"coordinates":[8.8606214523,50.1684875488],"type":"Point"}
}