{
  "type": "Feature",
  "properties": {
    "iso:country":"DE",
    "sg:address":"M\u00e4rkische Str. 1",
    "sg:city":"Engelskirchen",
    "sg:phone":"+49 2263/901797",
    "sg:postcode":"51766",
    "sg:province":"Nordrhein-Westfalen",
    "wof:name":"H. M\u00fcller",
    "wof:placetype":"venue"
},
  "geometry": {"coordinates":[7.4090118408,50.987613678],"type":"Point"}
}