{
  "type": "Feature",
  "properties": {
    "iso:country":"DE",
    "sg:address":"Bergstr. 3",
    "sg:city":"Sommerkahl",
    "sg:postcode":"63825",
    "sg:province":"Bayern",
    "wof:name":"Ba Ro-bautr\u00e4ger Gmbh",
    "wof:placetype":"venue"
},
  "geometry": {"coordinates":[9.26936,50.074841],"type":"Point"}
}