{
  "type": "Feature",
  "properties": {
    "iso:country":"DE",
    "sg:address":"Neuengammer Hausdeich 208",
    "sg:city":"Hamburg",
    "sg:phone":"+49 40/7231158",
    "sg:postcode":"21039",
    "sg:province":"Hamburg",
    "wof:name":"E. H. St\u00fcbe",
    "wof:placetype":"venue"
},
  "geometry": {"coordinates":[10.22013,53.44659],"type":"Point"}
}