{
  "type": "Feature",
  "properties": {
    "iso:country":"DE",
    "sg:address":"Richteweg 23",
    "sg:city":"Bramsche",
    "sg:phone":"+49 5461/3679",
    "sg:postcode":"49565",
    "sg:province":"Niedersachsen",
    "wof:name":"Select Tv Gmbh",
    "wof:placetype":"venue"
},
  "geometry": {"coordinates":[7.92969,52.389751],"type":"Point"}
}