{
  "type": "Feature",
  "properties": {
    "iso:country":"DE",
    "sg:address":"Paulsenstr. 51",
    "sg:city":"Berlin",
    "sg:phone":"+49 30/8232576",
    "sg:postcode":"12163",
    "sg:province":"Berlin",
    "wof:name":"Evamaria Karchow Immobilienmaklerin",
    "wof:placetype":"venue"
},
  "geometry": {"coordinates":[13.3111429214,52.4613037109],"type":"Point"}
}