{
  "type": "Feature",
  "properties": {
    "iso:country":"DE",
    "sg:address":"Louisenstr. 52",
    "sg:city":"Dresden",
    "sg:postcode":"01099",
    "sg:province":"Sachsen",
    "wof:name":"Bms Bautr\u00e4ger Gmbh",
    "wof:placetype":"venue"
},
  "geometry": {"coordinates":[13.754802,51.065987],"type":"Point"}
}