{
  "type": "Feature",
  "properties": {
    "iso:country":"DE",
    "sg:address":"Ortsstr. 26",
    "sg:city":"Gummersbach",
    "sg:phone":"+49 2354/904469",
    "sg:postcode":"51647",
    "sg:province":"Nordrhein-Westfalen",
    "wof:name":"Bettina Rittinghaus",
    "wof:placetype":"venue"
},
  "geometry": {"coordinates":[7.660463,51.070065],"type":"Point"}
}