{
  "type": "Feature",
  "properties": {
    "iso:country":"DE",
    "sg:address":"Piccardstr 10",
    "sg:city":"Augsburg",
    "sg:phone":"+49 821/84015",
    "sg:postcode":"86159",
    "sg:province":"Bayern",
    "wof:name":"Asa Aufzug-service Gmbh",
    "wof:placetype":"venue"
},
  "geometry": {"coordinates":[10.895792,48.340012],"type":"Point"}
}