{
  "type": "Feature",
  "properties": {
    "iso:country":"DE",
    "sg:address":"Breitenbacher Str. 15",
    "sg:city":"Breuberg",
    "sg:phone":"+49 6022/31026",
    "sg:postcode":"64747",
    "sg:province":"Hessen",
    "wof:name":"Hotel-restauant Am K\u00f6nigswald",
    "wof:placetype":"venue"
},
  "geometry": {"coordinates":[9.043047905,49.8130645752],"type":"Point"}
}