{
  "type": "Feature",
  "properties": {
    "iso:country":"DE",
    "sg:address":"Vor dem L\u00fcchower Tor 6",
    "sg:city":"Salzwedel",
    "sg:phone":"+49 3901/422028",
    "sg:postcode":"29410",
    "sg:province":"Sachsen-Anhalt",
    "wof:name":"Horst Stadelmann",
    "wof:placetype":"venue"
},
  "geometry": {"coordinates":[11.1554346085,52.8565177917],"type":"Point"}
}