{
  "type": "Feature",
  "properties": {
    "iso:country":"DE",
    "sg:address":"Daimlerstr 8",
    "sg:city":"Wei\u00dfenhorn",
    "sg:phone":"+49 7309/969015",
    "sg:postcode":"89264",
    "sg:province":"Bayern",
    "wof:name":"Hiller Kg Kunststoffaufbereitung",
    "wof:placetype":"venue"
},
  "geometry": {"coordinates":[10.1422424316,48.3072624207],"type":"Point"}
}