{
  "type": "Feature",
  "properties": {
    "iso:country":"DE",
    "sg:address":"K\u00f6rnerstr. 33",
    "sg:city":"Lauffen",
    "sg:phone":"+49 7133/98700",
    "sg:postcode":"74348",
    "sg:province":"Baden-W\u00fcrttemberg",
    "wof:name":"W. Huber",
    "wof:placetype":"venue"
},
  "geometry": {"coordinates":[9.1529693604,49.0723876953],"type":"Point"}
}