{
  "type": "Feature",
  "properties": {
    "iso:country":"DE",
    "sg:address":"Hainstr. 15",
    "sg:city":"Gr\u00fcnberg",
    "sg:postcode":"35305",
    "sg:province":"Hessen",
    "wof:name":"No-els Gmbh",
    "wof:placetype":"venue"
},
  "geometry": {"coordinates":[8.9438638687,50.6367683411],"type":"Point"}
}