{
  "type": "Feature",
  "properties": {
    "iso:country":"DE",
    "sg:address":"Tillystr. 1",
    "sg:city":"Eslarn",
    "sg:phone":"+49 9653/285",
    "sg:postcode":"92693",
    "sg:province":"Bayern",
    "wof:name":"Herbert Dippl",
    "wof:placetype":"venue"
},
  "geometry": {"coordinates":[12.5232896805,49.5807952881],"type":"Point"}
}