{
  "type": "Feature",
  "properties": {
    "iso:country":"DE",
    "sg:address":"Schulstra\u00dfe 1",
    "sg:city":"Wei\u00dfenhorn",
    "sg:phone":"+49 7309",
    "sg:postcode":"89264",
    "sg:province":"Bayern",
    "wof:name":"Rechtsanwaltskanzlei Helmut Lindner",
    "wof:placetype":"venue"
},
  "geometry": {"coordinates":[10.161236,48.304333],"type":"Point"}
}