{
  "type": "Feature",
  "properties": {
    "iso:country":"DE",
    "sg:address":"Flurstr. 12",
    "sg:city":"Flensburg",
    "sg:phone":"+49 461/56264",
    "sg:postcode":"24939",
    "sg:province":"Schleswig-Holstein",
    "wof:name":"A. Ingwersen",
    "wof:placetype":"venue"
},
  "geometry": {"coordinates":[9.418663,54.792103],"type":"Point"}
}