{
  "type": "Feature",
  "properties": {
    "iso:country":"DE",
    "sg:address":"Wildeshauser Landstr. 69",
    "sg:city":"Ganderkesee",
    "sg:phone":"+49 4222/70101",
    "sg:postcode":"27777",
    "sg:province":"Niedersachsen",
    "wof:name":"Gloth",
    "wof:placetype":"venue"
},
  "geometry": {"coordinates":[8.5690107346,53.0168190002],"type":"Point"}
}