{
  "type": "Feature",
  "properties": {
    "iso:country":"DE",
    "sg:address":"Werkstr. 21",
    "sg:city":"Bocholt",
    "sg:phone":"+49 2871/27680",
    "sg:postcode":"46395",
    "sg:province":"Nordrhein-Westfalen",
    "wof:name":"Stahl-metallverarbeitung Gmbh",
    "wof:placetype":"venue"
},
  "geometry": {"coordinates":[6.582225,51.829468],"type":"Point"}
}