{
  "type": "Feature",
  "properties": {
    "iso:country":"DE",
    "sg:address":"Gr\u00fcnstr. 17",
    "sg:city":"Solingen",
    "sg:phone":"+49 212/79938",
    "sg:postcode":"42697",
    "sg:province":"Nordrhein-Westfalen",
    "wof:name":"Mohr Gmbh",
    "wof:placetype":"venue"
},
  "geometry": {"coordinates":[6.9972882271,51.161239624],"type":"Point"}
}