{
  "type": "Feature",
  "properties": {
    "iso:country":"DE",
    "sg:address":"Die Halde 3",
    "sg:city":"Otzberg",
    "sg:phone":"+49 6162/71131",
    "sg:postcode":"64853",
    "sg:province":"Hessen",
    "wof:name":"R. Hild",
    "wof:placetype":"venue"
},
  "geometry": {"coordinates":[8.8930044174,49.8208045959],"type":"Point"}
}