{
  "type": "Feature",
  "properties": {
    "iso:country":"DE",
    "sg:address":"M\u00fcndener Str. 1",
    "sg:city":"Oberweser",
    "sg:phone":"+49 5574/340",
    "sg:postcode":"34399",
    "sg:province":"Hessen",
    "wof:name":"Walter Itter Inh. Jutta Eisenbraun",
    "wof:placetype":"venue"
},
  "geometry": {"coordinates":[9.5957460403,51.5897941589],"type":"Point"}
}