{
  "type": "Feature",
  "properties": {
    "iso:country":"DE",
    "sg:address":"Pregelstra\u00dfe 18",
    "sg:city":"Ennepetal",
    "sg:phone":"+49 2333",
    "sg:postcode":"58256",
    "sg:province":"Nordrhein-Westfalen",
    "wof:name":"Koeser",
    "wof:placetype":"venue"
},
  "geometry": {"coordinates":[7.3290319443,51.2920303345],"type":"Point"}
}