{
  "type": "Feature",
  "properties": {
    "iso:country":"DE",
    "sg:address":"An der Leutra 2",
    "sg:city":"Jena",
    "sg:phone":"+49 3641/825079",
    "sg:postcode":"07743",
    "sg:province":"Th\u00fcringen",
    "wof:name":"Kess Bau Gmbh",
    "wof:placetype":"venue"
},
  "geometry": {"coordinates":[11.570146,50.932537],"type":"Point"}
}