{
  "type": "Feature",
  "properties": {
    "iso:country":"DE",
    "sg:address":"Anhalter Str. 12",
    "sg:city":"D\u00fcsseldorf",
    "sg:postcode":"40229",
    "sg:province":"Nordrhein-Westfalen",
    "wof:name":"Massivhaus Creativ 2000 Gmbh",
    "wof:placetype":"venue"
},
  "geometry": {"coordinates":[6.836254,51.200947],"type":"Point"}
}