{
  "type": "Feature",
  "properties": {
    "iso:country":"DE",
    "sg:address":"Kuno-Fischer-Str. 22-26",
    "sg:city":"Berlin",
    "sg:phone":"+49 30/34304901",
    "sg:postcode":"14057",
    "sg:province":"Berlin",
    "wof:name":"Max-liebermann-oberschule",
    "wof:placetype":"venue"
},
  "geometry": {"coordinates":[13.290392,52.505428],"type":"Point"}
}