{
  "type": "Feature",
  "properties": {
    "iso:country":"DE",
    "sg:address":"Zietenstr. 12",
    "sg:city":"Augsburg",
    "sg:phone":"+49 821/792498",
    "sg:postcode":"86165",
    "sg:province":"Bayern",
    "wof:name":"Erich Kleinhagauer Masseur",
    "wof:placetype":"venue"
},
  "geometry": {"coordinates":[10.922063,48.374676],"type":"Point"}
}