{
  "type": "Feature",
  "properties": {
    "iso:country":"DE",
    "sg:address":"Am Heiligenhaus 1",
    "sg:city":"Mainz",
    "sg:phone":"+49 6131/371261",
    "sg:postcode":"55116",
    "sg:province":"Rheinland-Pfalz",
    "wof:name":"Mainzer Volksbank Eg",
    "wof:placetype":"venue"
},
  "geometry": {"coordinates":[8.229868,49.996941],"type":"Point"}
}