{
  "type": "Feature",
  "properties": {
    "iso:country":"DE",
    "sg:address":"Hauptstr. 54",
    "sg:city":"Mickhausen",
    "sg:phone":"+49 8204/301",
    "sg:postcode":"86866",
    "sg:province":"Bayern",
    "wof:name":"Kreis- Und Stadtsparkasse",
    "wof:placetype":"venue"
},
  "geometry": {"coordinates":[10.638966,48.237671],"type":"Point"}
}