{
  "type": "Feature",
  "properties": {
    "iso:country":"DE",
    "sg:address":"Beethovenstr. 8",
    "sg:city":"Riesb\u00fcrg",
    "sg:phone":"+49 9081/86427",
    "sg:postcode":"73469",
    "sg:province":"Baden-W\u00fcrttemberg",
    "wof:name":"P.-e. Reinhardt",
    "wof:placetype":"venue"
},
  "geometry": {"coordinates":[10.430398,48.824501],"type":"Point"}
}