{
  "type": "Feature",
  "properties": {
    "iso:country":"DE",
    "sg:address":"Bahnhofstr. 35",
    "sg:city":"Deggendorf",
    "sg:phone":"+49 991/341629",
    "sg:postcode":"94469",
    "sg:province":"Bayern",
    "wof:name":"T. Max",
    "wof:placetype":"venue"
},
  "geometry": {"coordinates":[12.9572343826,48.8341522217],"type":"Point"}
}