{
  "type": "Feature",
  "properties": {
    "iso:country":"DE",
    "sg:address":"Fischerstr. 3",
    "sg:city":"Kempten",
    "sg:phone":"+49 831/22696",
    "sg:postcode":"87435",
    "sg:province":"Bayern",
    "wof:name":"Gisela Rudolph",
    "wof:placetype":"venue"
},
  "geometry": {"coordinates":[10.3155326843,47.7244377136],"type":"Point"}
}