{
  "type": "Feature",
  "properties": {
    "iso:country":"DE",
    "sg:address":"Am Feldrain 18",
    "sg:city":"Cottbus",
    "sg:phone":"+49 355/824221",
    "sg:postcode":"03054",
    "sg:province":"Brandenburg",
    "wof:name":"S. Br\u00fcckner",
    "wof:placetype":"venue"
},
  "geometry": {"coordinates":[14.3457994461,51.8178291321],"type":"Point"}
}