{
  "type": "Feature",
  "properties": {
    "iso:country":"DE",
    "sg:address":"Am Hohen Ufer 2",
    "sg:city":"M\u00fcnster",
    "sg:phone":"+49 2506/6339",
    "sg:postcode":"48167",
    "sg:province":"Nordrhein-Westfalen",
    "wof:name":"Rainer Bohm",
    "wof:placetype":"venue"
},
  "geometry": {"coordinates":[7.695529,51.928276],"type":"Point"}
}