{
  "type": "Feature",
  "properties": {
    "iso:country":"DE",
    "sg:address":"Grund 1",
    "sg:city":"Geisenheim",
    "sg:phone":"+49 6722/50678",
    "sg:postcode":"65366",
    "sg:province":"Hessen",
    "wof:name":"Pvh Weinbau Gmbh",
    "wof:placetype":"venue"
},
  "geometry": {"coordinates":[7.9815211296,49.9953575134],"type":"Point"}
}