{
  "type": "Feature",
  "properties": {
    "iso:country":"DE",
    "sg:address":"Eberswalder Str. 161",
    "sg:city":"Eberswalde",
    "sg:phone":"+49 3334/361200",
    "sg:postcode":"16227",
    "sg:province":"Brandenburg",
    "wof:name":"W. Schumann",
    "wof:placetype":"venue"
},
  "geometry": {"coordinates":[13.723751,52.83952],"type":"Point"}
}