{
  "type": "Feature",
  "properties": {
    "iso:country":"DE",
    "sg:address":"Postfach 1144",
    "sg:city":"Otterberg",
    "sg:postcode":"67694",
    "sg:province":"Rheinland-Pfalz",
    "wof:name":"H. Engelbach",
    "wof:placetype":"venue"
},
  "geometry": {"coordinates":[7.7715849876,49.5040054321],"type":"Point"}
}