{
  "type": "Feature",
  "properties": {
    "iso:country":"DE",
    "sg:address":"Droote 83",
    "sg:city":"Dortmund",
    "sg:phone":"+49 231/234921",
    "sg:postcode":"44328",
    "sg:province":"Nordrhein-Westfalen",
    "wof:name":"Dingsda",
    "wof:placetype":"venue"
},
  "geometry": {"coordinates":[7.5498270988,51.5581970215],"type":"Point"}
}