{
  "type": "Feature",
  "properties": {
    "iso:country":"DE",
    "sg:address":"Mitteltorstr. 14",
    "sg:city":"Marktheidenfeld",
    "sg:phone":"+49 9391/8376",
    "sg:postcode":"97828",
    "sg:province":"Bayern",
    "wof:name":"Kronengarten",
    "wof:placetype":"venue"
},
  "geometry": {"coordinates":[9.6015901566,49.8436355591],"type":"Point"}
}