{
  "type": "Feature",
  "properties": {
    "iso:country":"DE",
    "sg:address":"Im Steinigen Graben 10",
    "sg:city":"Gelnhausen",
    "sg:phone":"+49 6051/96260",
    "sg:postcode":"63571",
    "sg:province":"Hessen",
    "wof:name":"K-tron Deutschland Gmbh Ndl. Gelnhausen",
    "wof:placetype":"venue"
},
  "geometry": {"coordinates":[9.1761922836,50.1863594055],"type":"Point"}
}