{
  "type": "Feature",
  "properties": {
    "iso:country":"DE",
    "sg:address":"Seeshaupter Str 7",
    "sg:city":"Iffeldorf",
    "sg:phone":"+49 8856/2068",
    "sg:postcode":"82393",
    "sg:province":"Bayern",
    "wof:name":"Hagina Gmbh",
    "wof:placetype":"venue"
},
  "geometry": {"coordinates":[11.3277902603,47.7847328186],"type":"Point"}
}