{
  "type": "Feature",
  "properties": {
    "iso:country":"DE",
    "sg:address":"M\u00fchlenstr. 52a",
    "sg:city":"Schellbach",
    "sg:phone":"+49 34423/21348",
    "sg:postcode":"06712",
    "sg:province":"Sachsen-Anhalt",
    "wof:name":"Asa Aechtner & Saubert Beteiligungsges. Mbh",
    "wof:placetype":"venue"
},
  "geometry": {"coordinates":[12.117555,50.975384],"type":"Point"}
}