{
  "type": "Feature",
  "properties": {
    "iso:country":"DE",
    "sg:address":"Kirchstr. 5",
    "sg:city":"Swisttal",
    "sg:phone":"+49 2254/844326",
    "sg:postcode":"53913",
    "sg:province":"Nordrhein-Westfalen",
    "wof:name":"H. Schaaf",
    "wof:placetype":"venue"
},
  "geometry": {"coordinates":[6.9134020805,50.7171440125],"type":"Point"}
}