{
  "type": "Feature",
  "properties": {
    "iso:country":"DE",
    "sg:address":"Aachener Str. 48",
    "sg:city":"H\u00fcckelhoven",
    "sg:phone":"+49 2435/2013",
    "sg:postcode":"41836",
    "sg:province":"Nordrhein-Westfalen",
    "wof:name":"H. Rible Jun. Elektromeisterbetrieb",
    "wof:placetype":"venue"
},
  "geometry": {"coordinates":[6.278051,51.033035],"type":"Point"}
}