{
  "type": "Feature",
  "properties": {
    "iso:country":"DE",
    "sg:address":"Ulmenallee 49",
    "sg:city":"M\u00fclheim",
    "sg:phone":"+49 208/426136",
    "sg:postcode":"45478",
    "sg:province":"Nordrhein-Westfalen",
    "wof:name":"E. R\u00fchl Heissmangelbetrieb",
    "wof:placetype":"venue"
},
  "geometry": {"coordinates":[6.8533301353,51.422416687],"type":"Point"}
}