{
  "type": "Feature",
  "properties": {
    "iso:country":"DE",
    "sg:address":"Malergasse 8",
    "sg:city":"Regensburg",
    "sg:phone":"+49 941/560714",
    "sg:postcode":"93047",
    "sg:province":"Bayern",
    "wof:name":"G\u00fc\u00dfbacher",
    "wof:placetype":"venue"
},
  "geometry": {"coordinates":[12.096493721,49.0172233582],"type":"Point"}
}