{
  "type": "Feature",
  "properties": {
    "iso:country":"DE",
    "sg:address":"L\u00e4rchenstr. 1",
    "sg:city":"Schmidm\u00fchlen",
    "sg:phone":"+49 9474/392",
    "sg:postcode":"92287",
    "sg:province":"Bayern",
    "wof:name":"Erwin Aigner",
    "wof:placetype":"venue"
},
  "geometry": {"coordinates":[11.929485,49.26255],"type":"Point"}
}