{
  "type": "Feature",
  "properties": {
    "iso:country":"DE",
    "sg:address":"Georgenstr. 55",
    "sg:city":"Augsburg",
    "sg:phone":"+49 821/158787",
    "sg:postcode":"86152",
    "sg:province":"Bayern",
    "wof:name":"Online Gmbh",
    "wof:placetype":"venue"
},
  "geometry": {"coordinates":[10.8903770447,48.3757362366],"type":"Point"}
}