{
  "type": "Feature",
  "properties": {
    "iso:country":"DE",
    "sg:address":"Herdestr. 2",
    "sg:city":"Esens",
    "sg:phone":"+49 4971/3230",
    "sg:postcode":"26427",
    "sg:province":"Niedersachsen",
    "wof:name":"Fielmann-optic",
    "wof:placetype":"venue"
},
  "geometry": {"coordinates":[7.6105499268,53.6470146179],"type":"Point"}
}