{
  "type": "Feature",
  "properties": {
    "iso:country":"DE",
    "sg:address":"Daiserstr. 22",
    "sg:city":"M\u00fcnchen",
    "sg:phone":"+49 89/774386",
    "sg:postcode":"81371",
    "sg:province":"Bayern",
    "wof:name":"Paulaner St\u00fcberl",
    "wof:placetype":"venue"
},
  "geometry": {"coordinates":[11.543671608,48.1199188232],"type":"Point"}
}