{
  "type": "Feature",
  "properties": {
    "iso:country":"DE",
    "sg:address":"Heikenbergstr. 30",
    "sg:city":"Bad Lauterberg",
    "sg:phone":"+49 5524/2654",
    "sg:postcode":"37431",
    "sg:province":"Niedersachsen",
    "wof:name":"Heinz Meng",
    "wof:placetype":"venue"
},
  "geometry": {"coordinates":[10.456363,51.626404],"type":"Point"}
}