{
  "type": "Feature",
  "properties": {
    "iso:country":"DE",
    "sg:address":"Salinenweg 2",
    "sg:city":"G\u00f6ttingen",
    "sg:phone":"+49 551/68989",
    "sg:postcode":"37081",
    "sg:province":"Niedersachsen",
    "wof:name":"Volker Schick",
    "wof:placetype":"venue"
},
  "geometry": {"coordinates":[9.9090242386,51.5350265503],"type":"Point"}
}