{
  "type": "Feature",
  "properties": {
    "iso:country":"DE",
    "sg:address":"Weg zur Krumhoffsm\u00fchle",
    "sg:city":"Arnstadt",
    "sg:phone":"+49 3628/70872",
    "sg:postcode":"99310",
    "sg:province":"Th\u00fcringen",
    "wof:name":"Wiesendiele",
    "wof:placetype":"venue"
},
  "geometry": {"coordinates":[10.9432401657,50.8184089661],"type":"Point"}
}