{
  "type": "Feature",
  "properties": {
    "iso:country":"DE",
    "sg:address":"Schaafenstr 47",
    "sg:city":"K\u00f6ln",
    "sg:phone":"+49 221/232839",
    "sg:postcode":"50676",
    "sg:province":"Nordrhein-Westfalen",
    "wof:name":"Kindgen Stempel + Schilder Gmbh",
    "wof:placetype":"venue"
},
  "geometry": {"coordinates":[6.94111,50.934734],"type":"Point"}
}