{
  "type": "Feature",
  "properties": {
    "iso:country":"DE",
    "sg:address":"D\u00fcrn\u00f6derweg 3",
    "sg:city":"Bad F\u00fcssing",
    "sg:phone":"+49 8531/94490",
    "sg:postcode":"94072",
    "sg:province":"Bayern",
    "wof:name":"Rbp Regionalbusverkehr Passau Land Gmbh",
    "wof:placetype":"venue"
},
  "geometry": {"coordinates":[13.3027801514,48.3487167358],"type":"Point"}
}