{
  "type": "Feature",
  "properties": {
    "iso:country":"DE",
    "sg:address":"Wildensee 73",
    "sg:city":"Eschau",
    "sg:phone":"+49 9374/90152",
    "sg:postcode":"63863",
    "sg:province":"Bayern",
    "wof:name":"Pension Tannenhof",
    "wof:placetype":"venue"
},
  "geometry": {"coordinates":[9.3554010391,49.8294029236],"type":"Point"}
}