{
  "type": "Feature",
  "properties": {
    "iso:country":"DE",
    "sg:address":"Reichenstr. 15",
    "sg:city":"F\u00fcssen",
    "sg:postcode":"87629",
    "sg:province":"Bayern",
    "wof:name":"Ostheimer Gmbh",
    "wof:placetype":"venue"
},
  "geometry": {"coordinates":[10.6996212006,47.5681800842],"type":"Point"}
}