{
  "type": "Feature",
  "properties": {
    "iso:country":"DE",
    "sg:address":"Linienstr. 84",
    "sg:city":"Carlsberg",
    "sg:phone":"+49 800255488",
    "sg:postcode":"67316",
    "sg:province":"Rheinland-Pfalz",
    "wof:name":"Allgut Immobilien Gmbh",
    "wof:placetype":"venue"
},
  "geometry": {"coordinates":[8.0319490433,49.5028419495],"type":"Point"}
}