{
  "type": "Feature",
  "properties": {
    "iso:country":"DE",
    "sg:address":"Alter Postweg 52",
    "sg:city":"Stemwede",
    "sg:phone":"+49 5745/500",
    "sg:postcode":"32351",
    "sg:province":"Nordrhein-Westfalen",
    "wof:name":"Hermann Brockschmidt",
    "wof:placetype":"venue"
},
  "geometry": {"coordinates":[8.523753,52.39027],"type":"Point"}
}