{
  "type": "Feature",
  "properties": {
    "iso:country":"DE",
    "sg:address":"Hauptstr. 25",
    "sg:city":"Georgenzell",
    "sg:phone":"+49 36968/60283",
    "sg:postcode":"98590",
    "sg:province":"Th\u00fcringen",
    "wof:name":"Gastst\u00e4tte Frank G\u00f6rting",
    "wof:placetype":"venue"
},
  "geometry": {"coordinates":[10.2620849609,50.7158622742],"type":"Point"}
}