{
  "type": "Feature",
  "properties": {
    "iso:country":"DE",
    "sg:address":"Ballingsh\u00e4user Str. 8",
    "sg:city":"Ma\u00dfbach",
    "sg:phone":"+49 9735/353",
    "sg:postcode":"97711",
    "sg:province":"Bayern",
    "wof:name":"Gartenmann Isolier- Und Terrassenbau Gmbh",
    "wof:placetype":"venue"
},
  "geometry": {"coordinates":[10.275445,50.18446],"type":"Point"}
}