{
  "type": "Feature",
  "properties": {
    "iso:country":"DE",
    "sg:address":"Am Petersberg 8",
    "sg:city":"Marl",
    "sg:phone":"+49 2365/8590",
    "sg:postcode":"45770",
    "sg:province":"Nordrhein-Westfalen",
    "wof:name":"Hamme Anlagenbau Gmbh",
    "wof:placetype":"venue"
},
  "geometry": {"coordinates":[7.173302,51.669415],"type":"Point"}
}