{
  "type": "Feature",
  "properties": {
    "iso:country":"DE",
    "sg:address":"Barbarastr. 18",
    "sg:city":"Langerwehe",
    "sg:phone":"+49 2423/3411",
    "sg:postcode":"52379",
    "sg:province":"Nordrhein-Westfalen",
    "wof:name":"Kunibert Hausmann",
    "wof:placetype":"venue"
},
  "geometry": {"coordinates":[6.369856,50.819408],"type":"Point"}
}