{
  "type": "Feature",
  "properties": {
    "iso:country":"DE",
    "sg:city":"V\u00f6hringen",
    "sg:postcode":"72189",
    "sg:province":"Baden-W\u00fcrttemberg",
    "wof:name":"E. Wegenast",
    "wof:placetype":"venue"
},
  "geometry": {"coordinates":[8.660856,48.33646],"type":"Point"}
}