{
  "type": "Feature",
  "properties": {
    "iso:country":"DE",
    "sg:address":"Elisabethstr. 14",
    "sg:city":"Essen",
    "sg:phone":"+49 201/214836",
    "sg:postcode":"45139",
    "sg:province":"Nordrhein-Westfalen",
    "wof:name":"Walter & Vreden Bedachungen Gmbh",
    "wof:placetype":"venue"
},
  "geometry": {"coordinates":[7.038593,51.462105],"type":"Point"}
}