{
  "type": "Feature",
  "properties": {
    "iso:country":"DE",
    "sg:address":"Hauptstr. 48",
    "sg:city":"Neukirchen-Adorf",
    "sg:phone":"+49 3721/26040",
    "sg:postcode":"09221",
    "sg:province":"Sachsen",
    "wof:name":"Megafunk-sch\u00fctze",
    "wof:placetype":"venue"
},
  "geometry": {"coordinates":[12.8755874634,50.7768058777],"type":"Point"}
}