{
  "type": "Feature",
  "properties": {
    "iso:country":"DE",
    "sg:address":"Hauptstr. 6",
    "sg:city":"Bad Nenndorf",
    "sg:phone":"+49 5723/3426",
    "sg:postcode":"31542",
    "sg:province":"Niedersachsen",
    "wof:name":"Kur-apotheke",
    "wof:placetype":"venue"
},
  "geometry": {"coordinates":[9.377027,52.335674],"type":"Point"}
}