{
  "type": "Feature",
  "properties": {
    "iso:country":"DE",
    "sg:address":"Von-Nagel-Str. 34 a",
    "sg:city":"Oelde",
    "sg:phone":"+49 2522/9313",
    "sg:postcode":"59302",
    "sg:province":"Nordrhein-Westfalen",
    "wof:name":"David Gmbh & Co. Kg",
    "wof:placetype":"venue"
},
  "geometry": {"coordinates":[8.1564683914,51.8342781067],"type":"Point"}
}