{
  "type": "Feature",
  "properties": {
    "iso:country":"DE",
    "sg:address":"Stampfgasse 14",
    "sg:city":"Seefeld",
    "sg:phone":"+49 8152/76448",
    "sg:postcode":"82229",
    "sg:province":"Bayern",
    "wof:name":"Hans Michl",
    "wof:placetype":"venue"
},
  "geometry": {"coordinates":[11.2195930481,48.0377044678],"type":"Point"}
}