{
  "type": "Feature",
  "properties": {
    "iso:country":"DE",
    "sg:address":"Herdestr. 10",
    "sg:city":"Esens",
    "sg:phone":"+49 4971/3351",
    "sg:postcode":"26427",
    "sg:province":"Niedersachsen",
    "wof:name":"E. Janssen",
    "wof:placetype":"venue"
},
  "geometry": {"coordinates":[7.6100420952,53.6468238831],"type":"Point"}
}