{
  "type": "Feature",
  "properties": {
    "iso:country":"DE",
    "sg:address":"Am Schlo\u00df 1",
    "sg:city":"Crimmitschau",
    "sg:phone":"+49 36608/2321",
    "sg:postcode":"08451",
    "sg:province":"Sachsen",
    "wof:name":"Schlo\u00df Blankenhain Agrar- Und Freilichtmuseum",
    "wof:placetype":"venue"
},
  "geometry": {"coordinates":[12.370944,50.813091],"type":"Point"}
}