{
  "type": "Feature",
  "properties": {
    "iso:country":"DE",
    "sg:address":"pfarrstra\u00dfe9",
    "sg:city":"ansbach",
    "sg:phone":"+49 981/9724066",
    "sg:postcode":"91522",
    "sg:province":"Bayern",
    "wof:name":"Sms-dealer.com-intelligente Sms-l\u00f6sungen",
    "wof:placetype":"venue"
},
  "geometry": {"coordinates":[10.572037,49.300686],"type":"Point"}
}