{
  "type": "Feature",
  "properties": {
    "iso:country":"DE",
    "sg:address":"Neuwiesenstr. 5",
    "sg:city":"Geislingen",
    "sg:phone":"+49 7331/95390",
    "sg:postcode":"73312",
    "sg:province":"Baden-W\u00fcrttemberg",
    "wof:name":"Kbm Gussputz-center Gmbh",
    "wof:placetype":"venue"
},
  "geometry": {"coordinates":[9.8094120026,48.6133079529],"type":"Point"}
}