{
  "type": "Feature",
  "properties": {
    "iso:country":"DE",
    "sg:address":"Erlenweg 3",
    "sg:city":"Bad M\u00fcnster-Ebernburg",
    "sg:phone":"+49 6708/3025",
    "sg:postcode":"55583",
    "sg:province":"Rheinland-Pfalz",
    "wof:name":"Lederwaren Scholle Gmbh",
    "wof:placetype":"venue"
},
  "geometry": {"coordinates":[7.832465,49.812859],"type":"Point"}
}