{
  "type": "Feature",
  "properties": {
    "iso:country":"DE",
    "sg:address":"Am Pichelssee 1",
    "sg:city":"Berlin",
    "sg:phone":"+49 30/36282929",
    "sg:postcode":"13595",
    "sg:province":"Berlin",
    "wof:name":"Allround-service",
    "wof:placetype":"venue"
},
  "geometry": {"coordinates":[13.200204,52.510967],"type":"Point"}
}