{
  "type": "Feature",
  "properties": {
    "iso:country":"DE",
    "sg:address":"Rathausplatz 1",
    "sg:city":"Recklinghausen",
    "sg:phone":"+49 2361/26537",
    "sg:postcode":"45657",
    "sg:province":"Nordrhein-Westfalen",
    "wof:name":"Eamail Esmaili Gmbh",
    "wof:placetype":"venue"
},
  "geometry": {"coordinates":[7.2020449638,51.6113052368],"type":"Point"}
}