{
  "type": "Feature",
  "properties": {
    "iso:country":"DE",
    "sg:address":"Holzmarkt 22-24",
    "sg:city":"Arnstadt",
    "sg:phone":"+49 3628/2807",
    "sg:postcode":"99310",
    "sg:province":"Th\u00fcringen",
    "wof:name":"Redaktion Arnst\u00e4dter Allgemeine",
    "wof:placetype":"venue"
},
  "geometry": {"coordinates":[10.948972702,50.8331298828],"type":"Point"}
}