{
  "type": "Feature",
  "properties": {
    "iso:country":"DE",
    "sg:address":"Diekstr. 59",
    "sg:city":"Lingen",
    "sg:phone":"+49 591/76673",
    "sg:postcode":"49809",
    "sg:province":"Niedersachsen",
    "wof:name":"Esli Maschinenfabrik Beteiligungs-gmbh",
    "wof:placetype":"venue"
},
  "geometry": {"coordinates":[7.351735,52.529251],"type":"Point"}
}