{
  "type": "Feature",
  "properties": {
    "iso:country":"DE",
    "sg:address":"Dieselstr. 2",
    "sg:city":"K\u00f6ln",
    "sg:phone":"+49 2234/70110",
    "sg:postcode":"50859",
    "sg:province":"Nordrhein-Westfalen",
    "wof:name":"Medipress Verlags- Gesellschaft Mbh",
    "wof:placetype":"venue"
},
  "geometry": {"coordinates":[6.8406891823,50.9460792542],"type":"Point"}
}