{
  "type": "Feature",
  "properties": {
    "iso:country":"DE",
    "sg:address":"Rathausstr. 1",
    "sg:city":"Dielheim",
    "sg:phone":"+49 6222/75234",
    "sg:postcode":"69234",
    "sg:province":"Baden-W\u00fcrttemberg",
    "wof:name":"Old Cadillac",
    "wof:placetype":"venue"
},
  "geometry": {"coordinates":[8.7356424332,49.2821807861],"type":"Point"}
}