{
  "type": "Feature",
  "properties": {
    "iso:country":"DE",
    "sg:address":"M\u00f6nchw\u00f6rthstr. 111",
    "sg:city":"Mannheim",
    "sg:phone":"+49 621/815518",
    "sg:postcode":"68199",
    "sg:province":"Baden-W\u00fcrttemberg",
    "wof:name":"A. M. Kraft Heilpraktikerin",
    "wof:placetype":"venue"
},
  "geometry": {"coordinates":[8.4852466583,49.4651107788],"type":"Point"}
}