{
  "type": "Feature",
  "properties": {
    "iso:country":"DE",
    "sg:address":"Strandstr. 3 B",
    "sg:city":"Zingst",
    "sg:phone":"+49 38232/16390",
    "sg:postcode":"18374",
    "sg:province":"Mecklenburg-Vorpommern",
    "wof:name":"Cafe Classic Inh. Hentzschel",
    "wof:placetype":"venue"
},
  "geometry": {"coordinates":[12.682157,54.438641],"type":"Point"}
}