{
  "type": "Feature",
  "properties": {
    "iso:country":"DE",
    "sg:address":"B\u00fcrgerm.-Prenn-Str. 12",
    "sg:city":"Unterhaching",
    "sg:phone":"+49 89/61501197",
    "sg:postcode":"82008",
    "sg:province":"Bayern",
    "wof:name":"P. Edlmann Immobilienmakler",
    "wof:placetype":"venue"
},
  "geometry": {"coordinates":[11.6199493408,48.0584182739],"type":"Point"}
}