{
  "type": "Feature",
  "properties": {
    "iso:country":"DE",
    "sg:address":"Beurhausstr. 76",
    "sg:city":"Dortmund",
    "sg:phone":"+49 231/162336",
    "sg:postcode":"44137",
    "sg:province":"Nordrhein-Westfalen",
    "wof:name":"Ursula Zemzycki",
    "wof:placetype":"venue"
},
  "geometry": {"coordinates":[7.452091,51.508736],"type":"Point"}
}