{
  "type": "Feature",
  "properties": {
    "iso:country":"DE",
    "sg:address":"Kransberger Str. 35",
    "sg:city":"Wehrheim",
    "sg:phone":"+49 6081/3181",
    "sg:postcode":"61273",
    "sg:province":"Hessen",
    "wof:name":"Achim Klotsche Gmbh & Co. Gasarmaturen Und Ventile Kg",
    "wof:placetype":"venue"
},
  "geometry": {"coordinates":[8.604571,50.332546],"type":"Point"}
}