{
  "type": "Feature",
  "properties": {
    "iso:country":"DE",
    "sg:address":"Sonnenbichlstr. 59",
    "sg:city":"Nonnenhorn",
    "sg:phone":"+49 8382/8123",
    "sg:postcode":"88149",
    "sg:province":"Bayern",
    "wof:name":"Brunhilde Koeberle-schmidt",
    "wof:placetype":"venue"
},
  "geometry": {"coordinates":[9.619547,47.573898],"type":"Point"}
}