{
  "type": "Feature",
  "properties": {
    "iso:country":"DE",
    "sg:address":"Burgauer Str. 1",
    "sg:city":"Krumbach",
    "sg:phone":"+49 8282/4524",
    "sg:postcode":"86381",
    "sg:province":"Bayern",
    "wof:name":"Fridolin Baum",
    "wof:placetype":"venue"
},
  "geometry": {"coordinates":[10.3701400757,48.2450866699],"type":"Point"}
}