{
  "type": "Feature",
  "properties": {
    "iso:country":"DE",
    "sg:address":"Wriezener Str. 2",
    "sg:city":"Buckow",
    "sg:postcode":"15377",
    "sg:province":"Brandenburg",
    "wof:name":"Clichy Verwaltungs Gmbh",
    "wof:placetype":"venue"
},
  "geometry": {"coordinates":[14.0729932785,52.5687026978],"type":"Point"}
}