{
  "type": "Feature",
  "properties": {
    "iso:country":"DE",
    "sg:address":"Keilkopf 6",
    "sg:city":"Lenggries",
    "sg:phone":"+49 8042/2770",
    "sg:postcode":"83661",
    "sg:province":"Bayern",
    "wof:name":"Denkh\u00fctte",
    "wof:placetype":"venue"
},
  "geometry": {"coordinates":[11.5741195679,47.6899490356],"type":"Point"}
}