{
  "type": "Feature",
  "properties": {
    "iso:country":"DE",
    "sg:address":"Kreuzweg 23",
    "sg:city":"Geisenheim",
    "sg:phone":"+49 6722/7080",
    "sg:postcode":"65366",
    "sg:province":"Hessen",
    "wof:name":"Erbsl\u00f6h Geisenheim Getr\u00e4nke- Technologie Verwaltungs Gmbh",
    "wof:placetype":"venue"
},
  "geometry": {"coordinates":[7.9560599327,49.9864501953],"type":"Point"}
}