{
  "type": "Feature",
  "properties": {
    "iso:country":"DE",
    "sg:address":"In den Benden 8",
    "sg:city":"D\u00fcsseldorf",
    "sg:phone":"+49 211/234675",
    "sg:postcode":"40625",
    "sg:province":"Nordrhein-Westfalen",
    "wof:name":"Jakob Aretz",
    "wof:placetype":"venue"
},
  "geometry": {"coordinates":[6.8452219963,51.2275772095],"type":"Point"}
}