{
  "type": "Feature",
  "properties": {
    "iso:country":"DE",
    "sg:address":"Heidestr. 19",
    "sg:city":"Dessau",
    "sg:phone":"+49 340/8502413",
    "sg:postcode":"06842",
    "sg:province":"Sachsen-Anhalt",
    "wof:name":"Witte",
    "wof:placetype":"venue"
},
  "geometry": {"coordinates":[12.242383,51.822838],"type":"Point"}
}