{
  "type": "Feature",
  "properties": {
    "iso:country":"DE",
    "sg:address":"Berliner Str. 8",
    "sg:city":"Singen",
    "sg:phone":"+49 7731/52529",
    "sg:postcode":"78224",
    "sg:province":"Baden-W\u00fcrttemberg",
    "wof:name":"H. H\u00fcbner",
    "wof:placetype":"venue"
},
  "geometry": {"coordinates":[8.8676204681,47.7571105957],"type":"Point"}
}