{
  "type": "Feature",
  "properties": {
    "iso:country":"DE",
    "sg:address":"Haimburg",
    "sg:city":"Berg",
    "sg:phone":"+49 9189/817",
    "sg:postcode":"92348",
    "sg:province":"Bayern",
    "wof:name":"Arbeitsgemeinschaft Zur F\u00f6rderung Des Umwelt- Und",
    "wof:placetype":"venue"
},
  "geometry": {"coordinates":[11.449634552,49.3538246155],"type":"Point"}
}