{
  "type": "Feature",
  "properties": {
    "iso:country":"DE",
    "sg:address":"Hindenburgstr. 4",
    "sg:city":"Angelburg",
    "sg:phone":"+49 6464/8073",
    "sg:postcode":"35719",
    "sg:province":"Hessen",
    "wof:name":"Engel Immobilienmakler",
    "wof:placetype":"venue"
},
  "geometry": {"coordinates":[8.4509658813,50.8269424438],"type":"Point"}
}