{
  "type": "Feature",
  "properties": {
    "iso:country":"DE",
    "sg:address":"Dreihausen 2",
    "sg:city":"M\u00f6hnesee",
    "sg:phone":"+49 4929/2497050",
    "sg:postcode":"59519",
    "sg:province":"Nordrhein-Westfalen",
    "wof:name":"Hitado Diagnostic Systems",
    "wof:placetype":"venue"
},
  "geometry": {"coordinates":[8.099021,51.495621],"type":"Point"}
}