{
  "type": "Feature",
  "properties": {
    "iso:country":"DE",
    "sg:address":"M\u00fchlstr. 1",
    "sg:city":"Nidda",
    "sg:phone":"+49 6043/2252",
    "sg:postcode":"63667",
    "sg:province":"Hessen",
    "wof:name":"Jordt Kg Inh. Johannes Ludwig Jordt",
    "wof:placetype":"venue"
},
  "geometry": {"coordinates":[9.0086460114,50.4131698608],"type":"Point"}
}