{
  "type": "Feature",
  "properties": {
    "iso:country":"DE",
    "sg:address":"Lerchenstr. 32",
    "sg:city":"Alth\u00fctte",
    "sg:phone":"+49 7183/41706",
    "sg:postcode":"71566",
    "sg:province":"Baden-W\u00fcrttemberg",
    "wof:name":"Wilhelm Wacker",
    "wof:placetype":"venue"
},
  "geometry": {"coordinates":[9.5782213211,48.9188537598],"type":"Point"}
}