{
  "type": "Feature",
  "properties": {
    "iso:country":"DE",
    "sg:address":"St\u00e4tzlinger Str. 22",
    "sg:city":"Augsburg",
    "sg:phone":"+49 821/719905",
    "sg:postcode":"86165",
    "sg:province":"Bayern",
    "wof:name":"Blumen Wirth",
    "wof:placetype":"venue"
},
  "geometry": {"coordinates":[10.925845,48.378895],"type":"Point"}
}