{
  "type": "Feature",
  "properties": {
    "iso:country":"DE",
    "sg:address":"Krummenweg 14",
    "sg:city":"Neu-Ulm",
    "sg:phone":"+49 731/979680",
    "sg:postcode":"89233",
    "sg:province":"Bayern",
    "wof:name":"A. Fischer",
    "wof:placetype":"venue"
},
  "geometry": {"coordinates":[10.026148,48.411686],"type":"Point"}
}