{
  "type": "Feature",
  "properties": {
    "iso:country":"DE",
    "sg:address":"Lehmkuhlenweg 2",
    "sg:city":"Hattstedt",
    "sg:phone":"+49 4846/1407",
    "sg:postcode":"25856",
    "sg:province":"Schleswig-Holstein",
    "wof:name":"Ute Hansen",
    "wof:placetype":"venue"
},
  "geometry": {"coordinates":[9.0299606323,54.5233154297],"type":"Point"}
}