{
  "type": "Feature",
  "properties": {
    "iso:country":"DE",
    "sg:address":"Professor-Wagner-Str. 3",
    "sg:city":"Friedrichsdorf",
    "sg:phone":"+49 6171/637272",
    "sg:postcode":"61381",
    "sg:province":"Hessen",
    "wof:name":"European Digital Telecom Gmbh & Co. Kg",
    "wof:placetype":"venue"
},
  "geometry": {"coordinates":[8.6410093307,50.2557868958],"type":"Point"}
}