{
  "type": "Feature",
  "properties": {
    "iso:country":"DE",
    "sg:address":"Sophienstr. 99",
    "sg:city":"Erbach",
    "sg:phone":"+49 4960/6294090",
    "sg:postcode":"64711",
    "sg:province":"Hessen",
    "wof:name":"Hsi-schreibger\u00c4te Gmbh",
    "wof:placetype":"venue"
},
  "geometry": {"coordinates":[8.9842786789,49.6655921936],"type":"Point"}
}