{
  "type": "Feature",
  "properties": {
    "iso:country":"DE",
    "sg:address":"Ludgeristr. 4",
    "sg:city":"Arnsberg",
    "sg:phone":"+49 2932/36129",
    "sg:postcode":"59759",
    "sg:province":"Nordrhein-Westfalen",
    "wof:name":"Heinz Hermes",
    "wof:placetype":"venue"
},
  "geometry": {"coordinates":[7.992082119,51.4256324768],"type":"Point"}
}