{
  "type": "Feature",
  "properties": {
    "iso:country":"DE",
    "sg:address":"Am Eisenherd 6",
    "sg:city":"Miltenberg",
    "sg:phone":"+49 9371/2586",
    "sg:postcode":"63897",
    "sg:province":"Bayern",
    "wof:name":"Erwin H\u00f6fner",
    "wof:placetype":"venue"
},
  "geometry": {"coordinates":[9.2624893188,49.7017288208],"type":"Point"}
}