{
  "type": "Feature",
  "properties": {
    "iso:country":"DE",
    "sg:address":"Greppiner Str. 19",
    "sg:city":"Wolfen",
    "sg:phone":"+49 3493/72021",
    "sg:postcode":"06766",
    "sg:province":"Sachsen-Anhalt",
    "wof:name":"Cbw Chemie Gmbh",
    "wof:placetype":"venue"
},
  "geometry": {"coordinates":[12.279017,51.656105],"type":"Point"}
}