{
  "type": "Feature",
  "properties": {
    "iso:country":"DE",
    "sg:address":"Schmelenheide 1",
    "sg:city":"Bedburg-Hau",
    "sg:phone":"+49 2821/810",
    "sg:postcode":"47551",
    "sg:province":"Nordrhein-Westfalen",
    "wof:name":"Krankenhausvollapotheke Im Rheinischen Landeskrankenhaus",
    "wof:placetype":"venue"
},
  "geometry": {"coordinates":[6.172699,51.76088],"type":"Point"}
}