{
  "type": "Feature",
  "properties": {
    "iso:country":"DE",
    "sg:address":"Luitpoldstr. 6",
    "sg:city":"Aschaffenburg",
    "sg:phone":"+49 6021/325700",
    "sg:postcode":"63739",
    "sg:province":"Bayern",
    "wof:name":"Argon Software Gmbh",
    "wof:placetype":"venue"
},
  "geometry": {"coordinates":[9.145293,49.976738],"type":"Point"}
}