{
  "type": "Feature",
  "properties": {
    "iso:country":"DE",
    "sg:address":"Amtsstr. 8",
    "sg:city":"Ludwigshafen",
    "sg:phone":"+49 621/512146",
    "sg:postcode":"67059",
    "sg:province":"Rheinland-Pfalz",
    "wof:name":"Franz M\u00fcller",
    "wof:placetype":"venue"
},
  "geometry": {"coordinates":[8.445858,49.481853],"type":"Point"}
}