{
  "type": "Feature",
  "properties": {
    "iso:country":"DE",
    "sg:address":"Bahnhofstr. 1",
    "sg:city":"Detmold",
    "sg:phone":"+49 5231/38430",
    "sg:postcode":"32756",
    "sg:province":"Nordrhein-Westfalen",
    "wof:name":"Pm Gmbh",
    "wof:placetype":"venue"
},
  "geometry": {"coordinates":[8.8750391006,51.9393844604],"type":"Point"}
}