{
  "type": "Feature",
  "properties": {
    "iso:country":"DE",
    "sg:address":"Mozartstr. 17",
    "sg:city":"Heppenheim",
    "sg:phone":"+49 6252/71901",
    "sg:postcode":"64646",
    "sg:province":"Hessen",
    "wof:name":"Herbert Deichert",
    "wof:placetype":"venue"
},
  "geometry": {"coordinates":[8.6296081543,49.6391448975],"type":"Point"}
}