{
  "type": "Feature",
  "properties": {
    "iso:country":"DE",
    "sg:address":"Rotdornweg 12",
    "sg:city":"Zwickau",
    "sg:phone":"+49 375/524737",
    "sg:postcode":"08060",
    "sg:province":"Sachsen",
    "wof:name":"Stefan Queck",
    "wof:placetype":"venue"
},
  "geometry": {"coordinates":[12.4465799332,50.7274551392],"type":"Point"}
}