{
  "type": "Feature",
  "properties": {
    "iso:country":"DE",
    "sg:address":"Waldburgstr. 94",
    "sg:city":"Stuttgart",
    "sg:phone":"+49 711/732616",
    "sg:postcode":"70563",
    "sg:province":"Baden-W\u00fcrttemberg",
    "wof:name":"J\u00fcrgen Mezger",
    "wof:placetype":"venue"
},
  "geometry": {"coordinates":[9.0996789932,48.7251434326],"type":"Point"}
}