{
  "type": "Feature",
  "properties": {
    "iso:country":"DE",
    "sg:address":"Enzianstr. 12",
    "sg:city":"Starnberg",
    "sg:postcode":"82319",
    "sg:province":"Bayern",
    "wof:name":"Pietro Padoan P.r. Reiseservice",
    "wof:placetype":"venue"
},
  "geometry": {"coordinates":[11.3663034439,48.0019950867],"type":"Point"}
}