{
  "type": "Feature",
  "properties": {
    "iso:country":"DE",
    "sg:address":"Schlo\u00dfplatz 7",
    "sg:city":"Saarwellingen",
    "sg:phone":"+49 6838/82073",
    "sg:postcode":"66793",
    "sg:province":"Saarland",
    "wof:name":"Eiscafe Nogara",
    "wof:placetype":"venue"
},
  "geometry": {"coordinates":[6.806697,49.353413],"type":"Point"}
}