{
  "type": "Feature",
  "properties": {
    "iso:country":"DE",
    "sg:address":"Osterberg 1a",
    "sg:city":"Reinstorf",
    "sg:phone":"+49 4137/810151",
    "sg:postcode":"21400",
    "sg:province":"Niedersachsen",
    "wof:name":"Dental Handel Medizintechnik Uwe Sch\u00f6neberg",
    "wof:placetype":"venue"
},
  "geometry": {"coordinates":[10.577029,53.234554],"type":"Point"}
}