{
  "type": "Feature",
  "properties": {
    "iso:country":"DE",
    "sg:address":"Auf der Bredde 33",
    "sg:city":"Wickede",
    "sg:phone":"+49 2922/81501",
    "sg:postcode":"58739",
    "sg:province":"Nordrhein-Westfalen",
    "wof:name":"H.-g. Sporenberg",
    "wof:placetype":"venue"
},
  "geometry": {"coordinates":[7.854359,51.519196],"type":"Point"}
}