{
  "type": "Feature",
  "properties": {
    "iso:country":"DE",
    "sg:address":"Longericher Str. 193",
    "sg:city":"K\u00f6ln",
    "sg:phone":"+49 221/172915",
    "sg:postcode":"50739",
    "sg:province":"Nordrhein-Westfalen",
    "wof:name":"Kosmia Armaturen Gmbh",
    "wof:placetype":"venue"
},
  "geometry": {"coordinates":[6.921781,50.98085],"type":"Point"}
}