{
  "type": "Feature",
  "properties": {
    "iso:country":"DE",
    "sg:address":"Osterstr. 45",
    "sg:city":"Hamburg",
    "sg:phone":"+49 40/40195912",
    "sg:postcode":"20259",
    "sg:province":"Hamburg",
    "wof:name":"Medibay Gmbh",
    "wof:placetype":"venue"
},
  "geometry": {"coordinates":[9.957645,53.574795],"type":"Point"}
}