{
  "type": "Feature",
  "properties": {
    "iso:country":"DE",
    "sg:address":"Bicherouxstr. 91",
    "sg:city":"Herzogenrath",
    "sg:phone":"+49 2406/63000",
    "sg:postcode":"52134",
    "sg:province":"Nordrhein-Westfalen",
    "wof:name":"Walter Olivier",
    "wof:placetype":"venue"
},
  "geometry": {"coordinates":[6.09302,50.877178],"type":"Point"}
}