{
  "type": "Feature",
  "properties": {
    "iso:country":"DE",
    "sg:address":"Hauptstr. 07",
    "sg:city":"Holzhausen",
    "sg:phone":"+49 34297",
    "sg:postcode":"04288",
    "sg:province":"Sachsen",
    "wof:name":"Kfz Markt Holzhausen",
    "wof:placetype":"venue"
},
  "geometry": {"coordinates":[12.464630127,51.3070144653],"type":"Point"}
}