{
  "type": "Feature",
  "properties": {
    "iso:country":"DE",
    "sg:address":"Bahnhofstr. 12",
    "sg:city":"Garmisch-Partenkirchen",
    "sg:phone":"+49 8821/2111",
    "sg:postcode":"82467",
    "sg:province":"Bayern",
    "wof:name":"Reiseb\u00fcro Heinz Karrasch Gmbh",
    "wof:placetype":"venue"
},
  "geometry": {"coordinates":[11.1029529572,47.4933433533],"type":"Point"}
}