{
  "type": "Feature",
  "properties": {
    "iso:country":"DE",
    "sg:address":"Westkotter Str. 87",
    "sg:city":"Wuppertal",
    "sg:phone":"+49 202/501954",
    "sg:postcode":"42277",
    "sg:province":"Nordrhein-Westfalen",
    "wof:name":"Carl Emde",
    "wof:placetype":"venue"
},
  "geometry": {"coordinates":[7.205521,51.279785],"type":"Point"}
}