{
  "type": "Feature",
  "properties": {
    "iso:country":"DE",
    "sg:address":"Bergstr. 17",
    "sg:city":"Wei\u00dfenfels",
    "sg:phone":"+49 3443/300295",
    "sg:postcode":"06667",
    "sg:province":"Sachsen-Anhalt",
    "wof:name":"Pension Am Klemmberg Inh. Grit Eckert",
    "wof:placetype":"venue"
},
  "geometry": {"coordinates":[11.9784421921,51.2015228271],"type":"Point"}
}