{
  "type": "Feature",
  "properties": {
    "iso:country":"DE",
    "sg:address":"Winzelb\u00fcrgstr. 14",
    "sg:city":"N\u00fcrnberg",
    "sg:phone":"+49 911/591710",
    "sg:postcode":"90491",
    "sg:province":"Bayern",
    "wof:name":"Dieter Kastner Steuerberater",
    "wof:placetype":"venue"
},
  "geometry": {"coordinates":[11.1092834473,49.4620819092],"type":"Point"}
}