{
  "type": "Feature",
  "properties": {
    "iso:country":"DE",
    "sg:address":"Bahnhofstr. 34",
    "sg:city":"Dornum",
    "sg:phone":"+49 4933/626",
    "sg:postcode":"26553",
    "sg:province":"Niedersachsen",
    "wof:name":"Rika Beninga Rechtsanw\u00e4ltin",
    "wof:placetype":"venue"
},
  "geometry": {"coordinates":[7.4390478134,53.642162323],"type":"Point"}
}