{
  "type": "Feature",
  "properties": {
    "iso:country":"DE",
    "sg:address":"Hubertusstr. 1",
    "sg:city":"Ehringshausen",
    "sg:phone":"+49 4964/4992280",
    "sg:postcode":"35630",
    "sg:province":"Hessen",
    "wof:name":"Giso Meier Gmbh",
    "wof:placetype":"venue"
},
  "geometry": {"coordinates":[8.3427495956,50.6241149902],"type":"Point"}
}