{
  "type": "Feature",
  "properties": {
    "iso:country":"DE",
    "sg:address":"Amtmannweg 6",
    "sg:city":"Rohrbach",
    "sg:phone":"+49 8442/8560",
    "sg:postcode":"85296",
    "sg:province":"Bayern",
    "wof:name":"Franz Meir",
    "wof:placetype":"venue"
},
  "geometry": {"coordinates":[11.5626583099,48.6145172119],"type":"Point"}
}