{
  "type": "Feature",
  "properties": {
    "iso:country":"DE",
    "sg:address":"Bleicherweg 23",
    "sg:city":"Wismar",
    "sg:phone":"+49 3841/206343",
    "sg:postcode":"23970",
    "sg:province":"Mecklenburg-Vorpommern",
    "wof:name":"R. Hanemann",
    "wof:placetype":"venue"
},
  "geometry": {"coordinates":[11.472692,53.891605],"type":"Point"}
}