{
  "type": "Feature",
  "properties": {
    "iso:country":"DE",
    "sg:address":"Kulmbacher Str. 80",
    "sg:city":"Saalfeld",
    "sg:phone":"+49 3671/555043",
    "sg:postcode":"07318",
    "sg:province":"Th\u00fcringen",
    "wof:name":"Riko Automaten Catering Gmbh",
    "wof:placetype":"venue"
},
  "geometry": {"coordinates":[11.372599,50.645386],"type":"Point"}
}