{
  "type": "Feature",
  "properties": {
    "iso:country":"DE",
    "sg:address":"Hans-Staden-Str. 69",
    "sg:city":"Wolfhagen",
    "sg:phone":"+49 5692/5893",
    "sg:postcode":"34466",
    "sg:province":"Hessen",
    "wof:name":"Erwin Heinemann",
    "wof:placetype":"venue"
},
  "geometry": {"coordinates":[9.1574802399,51.3200683594],"type":"Point"}
}