{
  "type": "Feature",
  "properties": {
    "iso:country":"DE",
    "sg:address":"\u00c4u\u00dfere Sulzbacher Str. 118",
    "sg:city":"N\u00fcrnberg",
    "sg:postcode":"90491",
    "sg:province":"Bayern",
    "wof:name":"John Frieda Gmbh",
    "wof:placetype":"venue"
},
  "geometry": {"coordinates":[11.117829,49.463924],"type":"Point"}
}