{
  "type": "Feature",
  "properties": {
    "iso:country":"DE",
    "sg:address":"Albrechtstr. 31",
    "sg:city":"Schwarzach",
    "sg:phone":"+49 9962/2613",
    "sg:postcode":"94374",
    "sg:province":"Bayern",
    "wof:name":"Weiss Gesellschaft F\u00fcr Das Bauwesen Mbh",
    "wof:placetype":"venue"
},
  "geometry": {"coordinates":[12.8069286346,48.921913147],"type":"Point"}
}