{
  "type": "Feature",
  "properties": {
    "iso:country":"DE",
    "sg:address":"Frankfurter Str. 23",
    "sg:city":"Seligenstadt",
    "sg:phone":"+49 6182/22438",
    "sg:postcode":"63500",
    "sg:province":"Hessen",
    "wof:name":"Pizzeria Puglia",
    "wof:placetype":"venue"
},
  "geometry": {"coordinates":[8.972360611,50.0443267822],"type":"Point"}
}