{
  "type": "Feature",
  "properties": {
    "iso:country":"DE",
    "sg:address":"Krefelder Str. 19",
    "sg:city":"K\u00f6ln",
    "sg:phone":"+49 221/7200809",
    "sg:postcode":"50670",
    "sg:province":"Nordrhein-Westfalen",
    "wof:name":"Italiatravel Reiseb\u00fcro Gmbh",
    "wof:placetype":"venue"
},
  "geometry": {"coordinates":[6.9523091316,50.950553894],"type":"Point"}
}