{
  "type": "Feature",
  "properties": {
    "iso:country":"DE",
    "sg:address":"Ahornweg 26",
    "sg:city":"Lingen",
    "sg:postcode":"49808",
    "sg:province":"Niedersachsen",
    "wof:name":"A. K. Klinkerbau Gmbh",
    "wof:placetype":"venue"
},
  "geometry": {"coordinates":[7.305256,52.535309],"type":"Point"}
}