{
  "type": "Feature",
  "properties": {
    "iso:country":"DE",
    "sg:address":"Bamberger Str. 16",
    "sg:city":"Eckersdorf",
    "sg:phone":"+49 921/7386042",
    "sg:postcode":"95488",
    "sg:province":"Bayern",
    "wof:name":"Helmut Natzi",
    "wof:placetype":"venue"
},
  "geometry": {"coordinates":[11.49985,49.932549],"type":"Point"}
}