{
  "type": "Feature",
  "properties": {
    "iso:country":"DE",
    "sg:address":"Salzburger Str. 15",
    "sg:city":"Bad Reichenhall",
    "sg:phone":"+49 8651/5691",
    "sg:postcode":"83435",
    "sg:province":"Bayern",
    "wof:name":"Dr. Med. Artur Sch\u00f6nach Arzt F\u00fcr Allgemeinmedizin",
    "wof:placetype":"venue"
},
  "geometry": {"coordinates":[12.8843374252,47.7284889221],"type":"Point"}
}