{
  "type": "Feature",
  "properties": {
    "iso:country":"DE",
    "sg:address":"Herborner Str. 36",
    "sg:city":"Weimar",
    "sg:phone":"+49 6421/78811",
    "sg:postcode":"35096",
    "sg:province":"Hessen",
    "wof:name":"Kegelbahn",
    "wof:placetype":"venue"
},
  "geometry": {"coordinates":[8.732591629,50.759349823],"type":"Point"}
}