{
  "type": "Feature",
  "properties": {
    "iso:country":"DE",
    "sg:address":"Liebigstr. 48",
    "sg:city":"Frankfurt",
    "sg:phone":"+49 69/727390",
    "sg:postcode":"60323",
    "sg:province":"Hessen",
    "wof:name":"Exept Verwaltungs- Und Vermietungs-gmbh",
    "wof:placetype":"venue"
},
  "geometry": {"coordinates":[8.6652803421,50.1221694946],"type":"Point"}
}