{
  "type": "Feature",
  "properties": {
    "iso:country":"DE",
    "sg:address":"Giershausener Weg 15a",
    "sg:city":"K\u00f6ln",
    "sg:phone":"+49 221/799343",
    "sg:postcode":"50767",
    "sg:province":"Nordrhein-Westfalen",
    "wof:name":"Verband Der Diplom- Oecotrophologen E. V.",
    "wof:placetype":"venue"
},
  "geometry": {"coordinates":[6.9028968811,51.0074005127],"type":"Point"}
}