{
  "type": "Feature",
  "properties": {
    "iso:country":"DE",
    "sg:address":"Meister-Gerhard-Str. 9",
    "sg:city":"Erkelenz",
    "sg:phone":"+49 2432/80944",
    "sg:postcode":"41812",
    "sg:province":"Nordrhein-Westfalen",
    "wof:name":"Herbert Von Der Forst",
    "wof:placetype":"venue"
},
  "geometry": {"coordinates":[6.22137,51.101475],"type":"Point"}
}