{
  "type": "Feature",
  "properties": {
    "iso:country":"DE",
    "sg:address":"Schulstr 2",
    "sg:city":"Leutenbach",
    "sg:phone":"+49 7195/910966",
    "sg:postcode":"71397",
    "sg:province":"Baden-W\u00fcrttemberg",
    "wof:name":"Walter",
    "wof:placetype":"venue"
},
  "geometry": {"coordinates":[9.404628,48.902935],"type":"Point"}
}