{
  "type": "Feature",
  "properties": {
    "iso:country":"DE",
    "sg:address":"Neuwiedenthaler Str. 135",
    "sg:city":"Hamburg",
    "sg:phone":"+49 40/7965311",
    "sg:postcode":"21147",
    "sg:province":"Hamburg",
    "wof:name":"Siewert Gmbh Vorm. Hugo Wischmeyer Nachf.",
    "wof:placetype":"venue"
},
  "geometry": {"coordinates":[9.88844,53.478203],"type":"Point"}
}