{
  "type": "Feature",
  "properties": {
    "iso:country":"DE",
    "sg:address":"Reithesselstr. 13a",
    "sg:city":"Odernheim",
    "sg:phone":"+49 6755/239",
    "sg:postcode":"55571",
    "sg:province":"Rheinland-Pfalz",
    "wof:name":"Horst Herzog",
    "wof:placetype":"venue"
},
  "geometry": {"coordinates":[7.707424,49.767838],"type":"Point"}
}