{
  "type": "Feature",
  "properties": {
    "iso:country":"DE",
    "sg:address":"Kirchenallee 25",
    "sg:city":"Hamburg",
    "sg:phone":"+49 40/2484460",
    "sg:postcode":"20099",
    "sg:province":"Hamburg",
    "wof:name":"Wilh. Schaumann",
    "wof:placetype":"venue"
},
  "geometry": {"coordinates":[10.007588,53.555332],"type":"Point"}
}