{
  "type": "Feature",
  "properties": {
    "iso:country":"DE",
    "sg:address":"Zur Egge 13",
    "sg:city":"Finnentrop",
    "sg:phone":"+49 2721/70319",
    "sg:postcode":"57413",
    "sg:province":"Nordrhein-Westfalen",
    "wof:name":"Paul Rasche",
    "wof:placetype":"venue"
},
  "geometry": {"coordinates":[7.9986782074,51.1671485901],"type":"Point"}
}