{
  "type": "Feature",
  "properties": {
    "iso:country":"DE",
    "sg:address":"K\u00f6nigsberger Str. 68",
    "sg:city":"Wuppertal",
    "sg:phone":"+49 202/664125",
    "sg:postcode":"42277",
    "sg:province":"Nordrhein-Westfalen",
    "wof:name":"Heinz Scheckermann Architekt",
    "wof:placetype":"venue"
},
  "geometry": {"coordinates":[7.225799,51.287483],"type":"Point"}
}