{
  "type": "Feature",
  "properties": {
    "iso:country":"DE",
    "sg:address":"Ziegeleistr. 18",
    "sg:city":"Langen",
    "sg:phone":"+49 4743/8158",
    "sg:postcode":"27607",
    "sg:province":"Niedersachsen",
    "wof:name":"Speckmann Gardinen Inh. Ursula Speckmann",
    "wof:placetype":"venue"
},
  "geometry": {"coordinates":[8.589468956,53.6029090881],"type":"Point"}
}