{
  "type": "Feature",
  "properties": {
    "iso:country":"DE",
    "sg:address":"Keplerstr. 17",
    "sg:city":"Spaichingen",
    "sg:phone":"+49 7424/3248",
    "sg:postcode":"78549",
    "sg:province":"Baden-W\u00fcrttemberg",
    "wof:name":"Rudolf Grimm",
    "wof:placetype":"venue"
},
  "geometry": {"coordinates":[8.7327880859,48.0671157837],"type":"Point"}
}