{
  "type": "Feature",
  "properties": {
    "iso:country":"DE",
    "sg:address":"St.-J\u00fcrgen-Str. 162",
    "sg:city":"Bremen",
    "sg:phone":"+49 421/74352",
    "sg:postcode":"28203",
    "sg:province":"Bremen",
    "wof:name":"Walther M. Huschke Rechtsanwalt",
    "wof:placetype":"venue"
},
  "geometry": {"coordinates":[8.8374824524,53.0777549744],"type":"Point"}
}