{
  "type": "Feature",
  "properties": {
    "iso:country":"DE",
    "sg:address":"Sponholzstr. 34",
    "sg:city":"Berlin",
    "sg:postcode":"12159",
    "sg:province":"Berlin",
    "wof:name":"Clausing & Seddigh Gmbh",
    "wof:placetype":"venue"
},
  "geometry": {"coordinates":[13.3406162262,52.4721221924],"type":"Point"}
}