{
  "type": "Feature",
  "properties": {
    "iso:country":"DE",
    "sg:address":"Altenberger Str. 35",
    "sg:city":"Altenberg",
    "sg:postcode":"01773",
    "sg:province":"Sachsen",
    "wof:name":"Dr. Siegfried Gerhardt",
    "wof:placetype":"venue"
},
  "geometry": {"coordinates":[13.6757774353,50.8029899597],"type":"Point"}
}