{
  "type": "Feature",
  "properties": {
    "iso:country":"DE",
    "sg:address":"Centrum 11",
    "sg:city":"Postbauer-Heng",
    "sg:phone":"+49 9188/1787",
    "sg:postcode":"92353",
    "sg:province":"Bayern",
    "wof:name":"Naturfreibad",
    "wof:placetype":"venue"
},
  "geometry": {"coordinates":[11.3426246643,49.3027534485],"type":"Point"}
}