{
  "type": "Feature",
  "properties": {
    "iso:country":"DE",
    "sg:address":"Dorfstr. 1a",
    "sg:city":"Audenhain",
    "sg:phone":"+49 34244/51301",
    "sg:postcode":"04838",
    "sg:province":"Sachsen",
    "wof:name":"Agrargenossenschaft Audenhain Eg",
    "wof:placetype":"venue"
},
  "geometry": {"coordinates":[12.626225,51.493671],"type":"Point"}
}