{
  "type": "Feature",
  "properties": {
    "iso:country":"DE",
    "sg:address":"Altes Feld 21",
    "sg:city":"Barsb\u00fcttel",
    "sg:phone":"+49 40/6708890",
    "sg:postcode":"22885",
    "sg:province":"Schleswig-Holstein",
    "wof:name":"Artelli Deutschland Gmbh",
    "wof:placetype":"venue"
},
  "geometry": {"coordinates":[10.182956,53.56781],"type":"Point"}
}