{
  "type": "Feature",
  "properties": {
    "iso:country":"DE",
    "sg:address":"Fichtenweg 19",
    "sg:city":"Kerspleben",
    "sg:phone":"+49 36203/5590",
    "sg:postcode":"99198",
    "sg:province":"Th\u00fcringen",
    "wof:name":"Gk Glaskontor Erfurt Gmbh",
    "wof:placetype":"venue"
},
  "geometry": {"coordinates":[11.095505,50.99929],"type":"Point"}
}