{
  "type": "Feature",
  "properties": {
    "iso:country":"DE",
    "sg:address":"Tuchmacherstr. 48b",
    "sg:city":"Potsdam",
    "sg:phone":"+49 331/7482606",
    "sg:postcode":"14482",
    "sg:province":"Brandenburg",
    "wof:name":"Blickpunkt Werbe- Und Verlagsgesellschaft",
    "wof:placetype":"venue"
},
  "geometry": {"coordinates":[13.0909690857,52.3949775696],"type":"Point"}
}