{
  "type": "Feature",
  "properties": {
    "iso:country":"DE",
    "sg:address":"Bemannsbruch 20",
    "sg:city":"Meckesheim",
    "sg:phone":"+49 6226/92320",
    "sg:postcode":"74909",
    "sg:province":"Baden-W\u00fcrttemberg",
    "wof:name":"Ecotec Kunststoffaufbe- Reitung Verwaltung Gmbh",
    "wof:placetype":"venue"
},
  "geometry": {"coordinates":[8.8055238724,49.3218421936],"type":"Point"}
}