{
  "type": "Feature",
  "properties": {
    "iso:country":"DE",
    "sg:address":"Blomberger Str. 220",
    "sg:city":"Detmold",
    "sg:phone":"+49 5231/5150",
    "sg:postcode":"32760",
    "sg:province":"Nordrhein-Westfalen",
    "wof:name":"U. Heinemann Fotograf Gmbh",
    "wof:placetype":"venue"
},
  "geometry": {"coordinates":[8.9152498245,51.9335594177],"type":"Point"}
}