{
  "type": "Feature",
  "properties": {
    "iso:country":"DE",
    "sg:address":"Westerstr. 10",
    "sg:city":"Bremen",
    "sg:phone":"+49 421/595050",
    "sg:postcode":"28199",
    "sg:province":"Bremen",
    "wof:name":"Thyssen Krupp Materials Und Services Gmbh",
    "wof:placetype":"venue"
},
  "geometry": {"coordinates":[8.798751,53.072983],"type":"Point"}
}