{
  "type": "Feature",
  "properties": {
    "iso:country":"DE",
    "sg:address":"Alte Mainzer Landstr. 9",
    "sg:city":"Dieburg",
    "sg:phone":"+49 6071/22217",
    "sg:postcode":"64807",
    "sg:province":"Hessen",
    "wof:name":"Christ Gmbh",
    "wof:placetype":"venue"
},
  "geometry": {"coordinates":[8.8311910629,49.8961982727],"type":"Point"}
}