{
  "type": "Feature",
  "properties": {
    "iso:country":"DE",
    "sg:address":"Sandstr. 34",
    "sg:city":"Siegen",
    "sg:phone":"+49 271/51345",
    "sg:postcode":"57072",
    "sg:province":"Nordrhein-Westfalen",
    "wof:name":"Gertrud Bockheim Krankengymnastin",
    "wof:placetype":"venue"
},
  "geometry": {"coordinates":[8.022127,50.876831],"type":"Point"}
}