{
  "type": "Feature",
  "properties": {
    "iso:country":"DE",
    "sg:address":"Am Sportplatz 1",
    "sg:city":"Rehling",
    "sg:phone":"+49 8237/6350",
    "sg:postcode":"86508",
    "sg:province":"Bayern",
    "wof:name":"Lechtalstuben",
    "wof:placetype":"venue"
},
  "geometry": {"coordinates":[10.9154100418,48.4828948975],"type":"Point"}
}