{
  "type": "Feature",
  "properties": {
    "iso:country":"DE",
    "sg:address":"Isenbergstr. 12",
    "sg:city":"Essen",
    "sg:phone":"+49 201/775578",
    "sg:postcode":"45130",
    "sg:province":"Nordrhein-Westfalen",
    "wof:name":"De Prins Gastst\u00e4tte",
    "wof:placetype":"venue"
},
  "geometry": {"coordinates":[7.016479969,51.441368103],"type":"Point"}
}