{
  "type": "Feature",
  "properties": {
    "iso:country":"DE",
    "sg:address":"Taunusstr. 67",
    "sg:city":"Wiesbaden",
    "sg:phone":"+49 611/522329",
    "sg:postcode":"65183",
    "sg:province":"Hessen",
    "wof:name":"S. Dietz Rechtsanwalt",
    "wof:placetype":"venue"
},
  "geometry": {"coordinates":[8.2386808395,50.0897102356],"type":"Point"}
}