{
  "type": "Feature",
  "properties": {
    "iso:country":"DE",
    "sg:address":"Ladenstr. 2",
    "sg:city":"Rodenbach",
    "sg:phone":"+49 6184/54754",
    "sg:postcode":"63517",
    "sg:province":"Hessen",
    "wof:name":"Pizzeria Flamingo",
    "wof:placetype":"venue"
},
  "geometry": {"coordinates":[9.0304718018,50.1376533508],"type":"Point"}
}