{
  "type": "Feature",
  "properties": {
    "iso:country":"DE",
    "sg:address":"Br\u00fcckenstr. 1",
    "sg:city":"Niedernhausen",
    "sg:phone":"+49 6127/78551",
    "sg:postcode":"65527",
    "sg:province":"Hessen",
    "wof:name":"P. Roth",
    "wof:placetype":"venue"
},
  "geometry": {"coordinates":[8.284357,50.178612],"type":"Point"}
}