{
  "type": "Feature",
  "properties": {
    "iso:country":"DE",
    "sg:address":"Kleiwellenfeld 25",
    "sg:city":"Ahlen",
    "sg:phone":"+49 2382/766902",
    "sg:postcode":"59229",
    "sg:province":"Nordrhein-Westfalen",
    "wof:name":"Werner Hellmann Speditions Gmbh",
    "wof:placetype":"venue"
},
  "geometry": {"coordinates":[7.8788628578,51.7388458252],"type":"Point"}
}