{
  "type": "Feature",
  "properties": {
    "iso:country":"DE",
    "sg:address":"R\u00f6thstr. 13",
    "sg:city":"Mistelbach",
    "sg:phone":"+49 9201/9370",
    "sg:postcode":"95511",
    "sg:province":"Bayern",
    "wof:name":"Heiko P\u00f6hnl",
    "wof:placetype":"venue"
},
  "geometry": {"coordinates":[11.5107593536,49.9140129089],"type":"Point"}
}