{
  "type": "Feature",
  "properties": {
    "iso:country":"DE",
    "sg:city":"Herschbroich",
    "sg:phone":"+49 2691/2184",
    "sg:postcode":"53518",
    "sg:province":"Rheinland-Pfalz",
    "wof:name":"Alte Burg",
    "wof:placetype":"venue"
},
  "geometry": {"coordinates":[6.96866,50.365913],"type":"Point"}
}