{
  "type": "Feature",
  "properties": {
    "iso:country":"DE",
    "sg:address":"M\u00fchlenweg 1",
    "sg:city":"Trittau",
    "sg:postcode":"22946",
    "sg:province":"Schleswig-Holstein",
    "wof:name":"Hans-j\u00fcrgen Pieper : Steuerberater, Vereidigter Buchpr\u00fcfer",
    "wof:placetype":"venue"
},
  "geometry": {"coordinates":[10.4058580399,53.6016921997],"type":"Point"}
}