{
  "type": "Feature",
  "properties": {
    "iso:country":"DE",
    "sg:address":"Ruselbergstr. 27",
    "sg:city":"Deggendorf",
    "sg:phone":"+49 991/21463",
    "sg:postcode":"94469",
    "sg:province":"Bayern",
    "wof:name":"Joseph Fischl",
    "wof:placetype":"venue"
},
  "geometry": {"coordinates":[12.993511,48.854042],"type":"Point"}
}