{
  "type": "Feature",
  "properties": {
    "iso:country":"DE",
    "sg:address":"Niemetzstr. 41",
    "sg:city":"Berlin",
    "sg:phone":"+49 30/68302066",
    "sg:postcode":"12055",
    "sg:province":"Berlin",
    "wof:name":"Sonne Heizt Energietechnik Gmbh",
    "wof:placetype":"venue"
},
  "geometry": {"coordinates":[13.4535703659,52.4699325562],"type":"Point"}
}