{
  "type": "Feature",
  "properties": {
    "iso:country":"DE",
    "sg:address":"Susannenstr. 23",
    "sg:city":"Hamburg",
    "sg:phone":"+49 40/43290869",
    "sg:postcode":"20357",
    "sg:province":"Hamburg",
    "wof:name":"Onda De Samba",
    "wof:placetype":"venue"
},
  "geometry": {"coordinates":[9.9652633667,53.5630607605],"type":"Point"}
}