{
  "type": "Feature",
  "properties": {
    "iso:country":"DE",
    "sg:address":"Eisenbahnstr. 11",
    "sg:city":"Weil am Rhein",
    "sg:phone":"+49 7621/71166",
    "sg:postcode":"79576",
    "sg:province":"Baden-W\u00fcrttemberg",
    "wof:name":"Jim Knopf",
    "wof:placetype":"venue"
},
  "geometry": {"coordinates":[7.6350507736,47.590877533],"type":"Point"}
}