{
  "type": "Feature",
  "properties": {
    "iso:country":"DE",
    "sg:address":"Kantstr. 35",
    "sg:city":"A\u00dflar",
    "sg:postcode":"35614",
    "sg:province":"Hessen",
    "wof:name":"G\u00fcnter Reuter",
    "wof:placetype":"venue"
},
  "geometry": {"coordinates":[8.458794,50.596146],"type":"Point"}
}