{
  "type": "Feature",
  "properties": {
    "iso:country":"DE",
    "sg:address":"Neufeldstr. 8 a",
    "sg:city":"Karlsruhe",
    "sg:phone":"+49 721/563813",
    "sg:postcode":"76187",
    "sg:province":"Baden-W\u00fcrttemberg",
    "wof:name":"Lammert Immobilienmakler",
    "wof:placetype":"venue"
},
  "geometry": {"coordinates":[8.339468956,49.031337738],"type":"Point"}
}