{
  "type": "Feature",
  "properties": {
    "iso:country":"DE",
    "sg:address":"Bahnhofstr. 5",
    "sg:city":"Baunach",
    "sg:postcode":"96148",
    "sg:province":"Bayern",
    "wof:name":"Mdw Gmbh",
    "wof:placetype":"venue"
},
  "geometry": {"coordinates":[10.851625,49.988194],"type":"Point"}
}