{
  "type": "Feature",
  "properties": {
    "iso:country":"DE",
    "sg:address":"Deidesheimer Str. 27",
    "sg:city":"Berlin",
    "sg:phone":"+49 30/8216959",
    "sg:postcode":"14197",
    "sg:province":"Berlin",
    "wof:name":"Tanja Iboyan Steuerberaterin",
    "wof:placetype":"venue"
},
  "geometry": {"coordinates":[13.3215894699,52.47423172],"type":"Point"}
}