{
  "type": "Feature",
  "properties": {
    "iso:country":"DE",
    "sg:address":"Dreeker Str. 59",
    "sg:city":"Dickel",
    "sg:phone":"+49 5445/771",
    "sg:postcode":"49453",
    "sg:province":"Niedersachsen",
    "wof:name":"Wilhelm Schmidt",
    "wof:placetype":"venue"
},
  "geometry": {"coordinates":[8.487168,52.650425],"type":"Point"}
}