{
  "type": "Feature",
  "properties": {
    "iso:country":"DE",
    "sg:address":"Oberweg 4",
    "sg:city":"Bad Salzschlirf",
    "sg:phone":"+49 6648/2230",
    "sg:postcode":"36364",
    "sg:province":"Hessen",
    "wof:name":"Heinz Brehler",
    "wof:placetype":"venue"
},
  "geometry": {"coordinates":[9.511034,50.621143],"type":"Point"}
}