{
  "type": "Feature",
  "properties": {
    "iso:country":"DE",
    "sg:address":"Giesebrechtstr. 11",
    "sg:city":"Berlin",
    "sg:phone":"+49 30/8825442",
    "sg:postcode":"10629",
    "sg:province":"Berlin",
    "wof:name":"W. Und K.-p. Schumann Rechtsanw\u00e4lte",
    "wof:placetype":"venue"
},
  "geometry": {"coordinates":[13.3114557266,52.5011940002],"type":"Point"}
}