{
  "type": "Feature",
  "properties": {
    "iso:country":"DE",
    "sg:address":"Windstege 5",
    "sg:city":"Wesel",
    "sg:phone":"+49 281/1420",
    "sg:postcode":"46483",
    "sg:province":"Nordrhein-Westfalen",
    "wof:name":"Bauverein Wesel Ag",
    "wof:placetype":"venue"
},
  "geometry": {"coordinates":[6.618111,51.657085],"type":"Point"}
}