{
  "type": "Feature",
  "properties": {
    "iso:country":"DE",
    "sg:address":"Im Spilles 5",
    "sg:city":"Trier",
    "sg:phone":"+49 651/88460",
    "sg:postcode":"54294",
    "sg:province":"Rheinland-Pfalz",
    "wof:name":"Kath. \u00d6ffentliche Bibliothek St. Helena",
    "wof:placetype":"venue"
},
  "geometry": {"coordinates":[6.607603,49.739807],"type":"Point"}
}