{
  "type": "Feature",
  "properties": {
    "iso:country":"DE",
    "sg:address":"L\u00f6ffelstr. 22-24",
    "sg:city":"Stuttgart",
    "sg:phone":"+49 4971/176820",
    "sg:postcode":"70597",
    "sg:province":"Baden-W\u00fcrttemberg",
    "wof:name":"S\u00dcdwestmatall Badenw\u00dcrttenberg E.v.",
    "wof:placetype":"venue"
},
  "geometry": {"coordinates":[9.16693,48.748547],"type":"Point"}
}