{
  "type": "Feature",
  "properties": {
    "iso:country":"DE",
    "sg:address":"Koblenzer Str. 34",
    "sg:city":"Hachenburg",
    "sg:phone":"+49 2662/95540",
    "sg:postcode":"57627",
    "sg:province":"Rheinland-Pfalz",
    "wof:name":"Otto Fischer Ziegelei Bau- Stoff-gro\u00dfhandlung Ohg",
    "wof:placetype":"venue"
},
  "geometry": {"coordinates":[7.8122940063,50.6602020264],"type":"Point"}
}