{
  "type": "Feature",
  "properties": {
    "iso:country":"DE",
    "sg:address":"Fritz-Reuter-Str. 7",
    "sg:city":"Stavenhagen",
    "sg:phone":"+49 39954/39457",
    "sg:postcode":"17153",
    "sg:province":"Mecklenburg-Vorpommern",
    "wof:name":"Eckard Winkler",
    "wof:placetype":"venue"
},
  "geometry": {"coordinates":[12.9704303741,53.7102355957],"type":"Point"}
}