{
  "type": "Feature",
  "properties": {
    "iso:country":"DE",
    "sg:address":"Seehalde 8",
    "sg:city":"Bodman-Ludwigshafen",
    "sg:phone":"+49 7773/5116",
    "sg:postcode":"78351",
    "sg:province":"Baden-W\u00fcrttemberg",
    "wof:name":"Strandbad Ludwigshafen",
    "wof:placetype":"venue"
},
  "geometry": {"coordinates":[9.0615196228,47.8154983521],"type":"Point"}
}