{
  "type": "Feature",
  "properties": {
    "iso:country":"DE",
    "sg:address":"Bitzengarten 28",
    "sg:city":"A\u00dflar",
    "sg:phone":"+49 6440/7221",
    "sg:postcode":"35614",
    "sg:province":"Hessen",
    "wof:name":"H. Krau\u00df Gmbh",
    "wof:placetype":"venue"
},
  "geometry": {"coordinates":[8.43734,50.648022],"type":"Point"}
}