{
  "type": "Feature",
  "properties": {
    "iso:country":"DE",
    "sg:address":"Tornowstr. 73",
    "sg:city":"Frankfurt",
    "sg:phone":"+49 69/772726",
    "sg:postcode":"60486",
    "sg:province":"Hessen",
    "wof:name":"G\u00fcnter Stoy",
    "wof:placetype":"venue"
},
  "geometry": {"coordinates":[8.6289243698,50.1134147644],"type":"Point"}
}