{
  "type": "Feature",
  "properties": {
    "iso:country":"DE",
    "sg:address":"Paul-Motz-Str. 13",
    "sg:city":"Ritschenhausen",
    "sg:phone":"+49 36949/20160",
    "sg:postcode":"98617",
    "sg:province":"Th\u00fcringen",
    "wof:name":"S. Leps",
    "wof:placetype":"venue"
},
  "geometry": {"coordinates":[10.432019,50.510769],"type":"Point"}
}