{
  "type": "Feature",
  "properties": {
    "iso:country":"DE",
    "sg:address":"Frankfurter Str. 193",
    "sg:city":"Kassel",
    "sg:phone":"+49 561/23139",
    "sg:postcode":"34121",
    "sg:province":"Hessen",
    "wof:name":"Reifen Ochs Ohg",
    "wof:placetype":"venue"
},
  "geometry": {"coordinates":[9.4765090942,51.2933120728],"type":"Point"}
}