{
  "type": "Feature",
  "properties": {
    "iso:country":"DE",
    "sg:address":"Hauptstr. 18",
    "sg:city":"Naunhof",
    "sg:phone":"+49 34297/41649",
    "sg:postcode":"04683",
    "sg:province":"Sachsen",
    "wof:name":"Slb Stra\u00dfen-und Landschaftsbauges. Mbh",
    "wof:placetype":"venue"
},
  "geometry": {"coordinates":[12.639198,51.293148],"type":"Point"}
}