{
  "type": "Feature",
  "properties": {
    "iso:country":"DE",
    "sg:address":"M\u00fcnchener Str. 7",
    "sg:city":"Gerolsbach",
    "sg:phone":"+49 8445/259",
    "sg:postcode":"85302",
    "sg:province":"Bayern",
    "wof:name":"J. Salvamoser",
    "wof:placetype":"venue"
},
  "geometry": {"coordinates":[11.364983,48.490532],"type":"Point"}
}