{
  "type": "Feature",
  "properties": {
    "iso:country":"DE",
    "sg:address":"Erlenweg 6",
    "sg:city":"Windeck",
    "sg:postcode":"51570",
    "sg:province":"Nordrhein-Westfalen",
    "wof:name":"M. Hertwig",
    "wof:placetype":"venue"
},
  "geometry": {"coordinates":[7.5685210228,50.8050003052],"type":"Point"}
}