{
  "type": "Feature",
  "properties": {
    "iso:country":"DE",
    "sg:address":"Alte Str.",
    "sg:city":"Immelborn",
    "sg:postcode":"36433",
    "sg:province":"Th\u00fcringen",
    "wof:name":"Kali-werra Ag",
    "wof:placetype":"venue"
},
  "geometry": {"coordinates":[10.2799863815,50.7944107056],"type":"Point"}
}