{
  "type": "Feature",
  "properties": {
    "iso:country":"DE",
    "sg:address":"Fuldastr.",
    "sg:city":"Baunatal",
    "sg:phone":"+49 5665/7631",
    "sg:postcode":"34225",
    "sg:province":"Hessen",
    "wof:name":"R. M\u00fcller Gmbh",
    "wof:placetype":"venue"
},
  "geometry": {"coordinates":[9.4308376312,51.2292022705],"type":"Point"}
}