{
  "type": "Feature",
  "properties": {
    "iso:country":"DE",
    "sg:address":"Lange Str. 40",
    "sg:city":"Castrop-Rauxel",
    "sg:phone":"+49 2305/74469",
    "sg:postcode":"44579",
    "sg:province":"Nordrhein-Westfalen",
    "wof:name":"Eiscafe Florian",
    "wof:placetype":"venue"
},
  "geometry": {"coordinates":[7.310572,51.58408],"type":"Point"}
}