{
  "type": "Feature",
  "properties": {
    "iso:country":"DE",
    "sg:address":"Dorfstr. 51",
    "sg:city":"B\u00fclow",
    "sg:postcode":"17166",
    "sg:province":"Mecklenburg-Vorpommern",
    "wof:name":"Landhotel Schorssow Besitzges. & Co. Kg",
    "wof:placetype":"venue"
},
  "geometry": {"coordinates":[12.572193,53.770733],"type":"Point"}
}