{
  "type": "Feature",
  "properties": {
    "iso:country":"DE",
    "sg:address":"Talstr. 113",
    "sg:city":"Wolfach",
    "sg:phone":"+49 7834/6082",
    "sg:postcode":"77709",
    "sg:province":"Baden-W\u00fcrttemberg",
    "wof:name":"H. Br\u00fcstle Steinmetzbetrieb",
    "wof:placetype":"venue"
},
  "geometry": {"coordinates":[8.2505216599,48.2609138489],"type":"Point"}
}