{
  "type": "Feature",
  "properties": {
    "iso:country":"DE",
    "sg:address":"Humboldtstr. 6 a",
    "sg:city":"Amberg",
    "sg:phone":"+49 9621/74999",
    "sg:postcode":"92224",
    "sg:province":"Bayern",
    "wof:name":"Michael Herrndobler",
    "wof:placetype":"venue"
},
  "geometry": {"coordinates":[11.886828,49.442539],"type":"Point"}
}