{
  "type": "Feature",
  "properties": {
    "iso:country":"DE",
    "sg:address":"Otto-Brenner-Str. 123",
    "sg:city":"Bielefeld",
    "sg:phone":"+49 521/27469",
    "sg:postcode":"33607",
    "sg:province":"Nordrhein-Westfalen",
    "wof:name":"Siekermitte",
    "wof:placetype":"venue"
},
  "geometry": {"coordinates":[8.5652723312,52.0134506226],"type":"Point"}
}