{
  "type": "Feature",
  "properties": {
    "iso:country":"DE",
    "sg:address":"Gartenweg 2",
    "sg:city":"Beilstein",
    "sg:phone":"+49 7062/4310",
    "sg:postcode":"71717",
    "sg:province":"Baden-W\u00fcrttemberg",
    "wof:name":"Hedwig Brixner Gmbh",
    "wof:placetype":"venue"
},
  "geometry": {"coordinates":[9.3131361008,49.0394706726],"type":"Point"}
}