{
  "type": "Feature",
  "properties": {
    "iso:country":"DE",
    "sg:address":"Rudolf-Breitscheid-Str. 29",
    "sg:city":"Potsdam",
    "sg:phone":"+49 331/710337",
    "sg:postcode":"14482",
    "sg:province":"Brandenburg",
    "wof:name":"K\u00fcpper Und Partner Gmbh",
    "wof:placetype":"venue"
},
  "geometry": {"coordinates":[13.0919837952,52.3918037415],"type":"Point"}
}