{
  "type": "Feature",
  "properties": {
    "iso:country":"DE",
    "sg:address":"Frankfurter Str. 13",
    "sg:city":"Kriftel",
    "sg:phone":"+49 6192/42721",
    "sg:postcode":"65830",
    "sg:province":"Hessen",
    "wof:name":"H.-j. Christ",
    "wof:placetype":"venue"
},
  "geometry": {"coordinates":[8.468655,50.083694],"type":"Point"}
}