{
  "type": "Feature",
  "properties": {
    "iso:country":"DE",
    "sg:address":"Schillerstr. 3",
    "sg:city":"Selbitz",
    "sg:phone":"+49 9280/8473",
    "sg:postcode":"95152",
    "sg:province":"Bayern",
    "wof:name":"Avanco Computervertriebsgesellschaft",
    "wof:placetype":"venue"
},
  "geometry": {"coordinates":[11.7484025955,50.3176689148],"type":"Point"}
}