{
  "type": "Feature",
  "properties": {
    "iso:country":"DE",
    "sg:address":"Vorsetzen",
    "sg:city":"Hamburg",
    "sg:phone":"+49 40/362553",
    "sg:postcode":"20459",
    "sg:province":"Hamburg",
    "wof:name":"Das Feuerschiff",
    "wof:placetype":"venue"
},
  "geometry": {"coordinates":[9.975771904,53.5443611145],"type":"Point"}
}