{
  "type": "Feature",
  "properties": {
    "iso:country":"DE",
    "sg:address":"Terhallestr. 37",
    "sg:city":"M\u00fcnchen",
    "sg:phone":"+49 89/6421823",
    "sg:postcode":"81545",
    "sg:province":"Bayern",
    "wof:name":"Claus Danner",
    "wof:placetype":"venue"
},
  "geometry": {"coordinates":[11.566696167,48.0927848816],"type":"Point"}
}