{
  "type": "Feature",
  "properties": {
    "iso:country":"DE",
    "sg:address":"Ulrichsteiner Str. 18",
    "sg:city":"M\u00fccke",
    "sg:phone":"+49 6400/8824",
    "sg:postcode":"35325",
    "sg:province":"Hessen",
    "wof:name":"Erhard Ellrich",
    "wof:placetype":"venue"
},
  "geometry": {"coordinates":[9.0789327621,50.5995979309],"type":"Point"}
}