{
  "type": "Feature",
  "properties": {
    "iso:country":"DE",
    "sg:address":"Promenade 6",
    "sg:city":"Fehrbellin",
    "sg:phone":"+49 33932/9980",
    "sg:postcode":"16833",
    "sg:province":"Brandenburg",
    "wof:name":"Betonwerk Fehrbellin Gmbh & Co Kg",
    "wof:placetype":"venue"
},
  "geometry": {"coordinates":[12.768597,52.811581],"type":"Point"}
}