{
  "type": "Feature",
  "properties": {
    "iso:country":"DE",
    "sg:address":"Kaiser-Friedrich-Str. 41",
    "sg:city":"Pforzheim",
    "sg:phone":"+49 7231/25110",
    "sg:postcode":"75172",
    "sg:province":"Baden-W\u00fcrttemberg",
    "wof:name":"D. W\u00fcst",
    "wof:placetype":"venue"
},
  "geometry": {"coordinates":[8.688446,48.889229],"type":"Point"}
}