{
  "type": "Feature",
  "properties": {
    "iso:country":"DE",
    "sg:address":"Auf der Kanzel 19",
    "sg:city":"Stuttgart",
    "sg:phone":"+49 711/2569312",
    "sg:postcode":"70191",
    "sg:province":"Baden-W\u00fcrttemberg",
    "wof:name":"Dr. Horst Ossenberg Ingenieur",
    "wof:placetype":"venue"
},
  "geometry": {"coordinates":[9.1807250977,48.7999801636],"type":"Point"}
}