{
  "type": "Feature",
  "properties": {
    "iso:country":"DE",
    "sg:address":"D\u00f6rmter Str. 12",
    "sg:city":"Oetzen",
    "sg:phone":"+49 5805/284",
    "sg:postcode":"29588",
    "sg:province":"Niedersachsen",
    "wof:name":"Ernst-august Steinfeld Immobilienmakler",
    "wof:placetype":"venue"
},
  "geometry": {"coordinates":[10.6797199249,53.0219993591],"type":"Point"}
}