{
  "type": "Feature",
  "properties": {
    "iso:country":"DE",
    "sg:address":"Kr\u00fcmpel 4",
    "sg:city":"Mustin",
    "sg:phone":"+49 4546/493",
    "sg:postcode":"23911",
    "sg:province":"Schleswig-Holstein",
    "wof:name":"Schmidt Gbr",
    "wof:placetype":"venue"
},
  "geometry": {"coordinates":[10.884301,53.682297],"type":"Point"}
}