{
  "type": "Feature",
  "properties": {
    "iso:country":"DE",
    "sg:address":"Gluckstr. 3",
    "sg:city":"Regensburg",
    "sg:phone":"+49 941/703198",
    "sg:postcode":"93053",
    "sg:province":"Bayern",
    "wof:name":"Gerold Neumaier Rechtsanwalt",
    "wof:placetype":"venue"
},
  "geometry": {"coordinates":[12.1070394516,49.005443573],"type":"Point"}
}