{
  "type": "Feature",
  "properties": {
    "iso:country":"DE",
    "sg:address":"T\u00fcckelh\u00e4user Str. 10",
    "sg:city":"Ochsenfurt",
    "sg:phone":"+49 9331/7390",
    "sg:postcode":"97199",
    "sg:province":"Bayern",
    "wof:name":"Klingentor-optik Gmbh",
    "wof:placetype":"venue"
},
  "geometry": {"coordinates":[10.058392,49.66515],"type":"Point"}
}