{
  "type": "Feature",
  "properties": {
    "iso:country":"DE",
    "sg:address":"An der Eisenschmelze 16",
    "sg:city":"Sonthofen",
    "sg:phone":"+49 8321/82440",
    "sg:postcode":"87527",
    "sg:province":"Bayern",
    "wof:name":"Gerstmayer Furniere Gmbh",
    "wof:placetype":"venue"
},
  "geometry": {"coordinates":[10.276056,47.520863],"type":"Point"}
}