{
  "type": "Feature",
  "properties": {
    "iso:country":"DE",
    "sg:address":"Marienstr. 17",
    "sg:city":"Weimar",
    "sg:phone":"+49 3643/545300",
    "sg:postcode":"99423",
    "sg:province":"Th\u00fcringen",
    "wof:name":"Liszthaus",
    "wof:placetype":"venue"
},
  "geometry": {"coordinates":[11.329833,50.975075],"type":"Point"}
}