{
  "type": "Feature",
  "properties": {
    "iso:country":"DE",
    "sg:address":"Krofdorfer Str. 136",
    "sg:city":"Gie\u00dfen",
    "sg:phone":"+49 641/83500",
    "sg:postcode":"35398",
    "sg:province":"Hessen",
    "wof:name":"Manfred Sch\u00e4fer",
    "wof:placetype":"venue"
},
  "geometry": {"coordinates":[8.660046,50.596443],"type":"Point"}
}