{
  "type": "Feature",
  "properties": {
    "iso:country":"DE",
    "sg:address":"Schulstra\u00dfe 25",
    "sg:city":"Malchow",
    "sg:postcode":"17213",
    "sg:province":"Mecklenburg-Vorpommern",
    "wof:name":"Tauchen In Malchow",
    "wof:placetype":"venue"
},
  "geometry": {"coordinates":[12.409642,53.468884],"type":"Point"}
}