{
  "type": "Feature",
  "properties": {
    "iso:country":"DE",
    "sg:address":"Feldm\u00fchlenweg 57",
    "sg:city":"Soest",
    "sg:phone":"+49 2921/31457",
    "sg:postcode":"59494",
    "sg:province":"Nordrhein-Westfalen",
    "wof:name":"Freibad Feldm\u00fchlenweg",
    "wof:placetype":"venue"
},
  "geometry": {"coordinates":[8.0968399048,51.57862854],"type":"Point"}
}