{
  "type": "Feature",
  "properties": {
    "iso:country":"DE",
    "sg:address":"Feudenheimer Str. 12",
    "sg:city":"Heidelberg",
    "sg:phone":"+49 6221/833031",
    "sg:postcode":"69123",
    "sg:province":"Baden-W\u00fcrttemberg",
    "wof:name":"Deutscher Telegrafie Club E. V.",
    "wof:placetype":"venue"
},
  "geometry": {"coordinates":[8.6446399689,49.4276351929],"type":"Point"}
}