{
  "type": "Feature",
  "properties": {
    "iso:country":"DE",
    "sg:address":"Asendorfer Str. 2",
    "sg:city":"Asendorf",
    "sg:postcode":"21271",
    "sg:province":"Niedersachsen",
    "wof:name":"Global-vers Gmbh",
    "wof:placetype":"venue"
},
  "geometry": {"coordinates":[9.9789829254,53.2684211731],"type":"Point"}
}