{
  "type": "Feature",
  "properties": {
    "iso:country":"DE",
    "sg:address":"Glasmoorstr. 153",
    "sg:city":"Norderstedt",
    "sg:phone":"+49 40/5243211",
    "sg:postcode":"22851",
    "sg:province":"Schleswig-Holstein",
    "wof:name":"E. Heuchert Immobilienmakler",
    "wof:placetype":"venue"
},
  "geometry": {"coordinates":[10.0299348831,53.7057952881],"type":"Point"}
}