{
  "type": "Feature",
  "properties": {
    "iso:country":"DE",
    "sg:address":"Landwehr 50",
    "sg:city":"Krefeld",
    "sg:phone":"+49 2151/712686",
    "sg:postcode":"47804",
    "sg:province":"Nordrhein-Westfalen",
    "wof:name":"Josephine B\u00fcren Malerbetrieb Inh. Helmut R\u00f6tters H. Bausch",
    "wof:placetype":"venue"
},
  "geometry": {"coordinates":[6.536502,51.317604],"type":"Point"}
}