{
  "type": "Feature",
  "properties": {
    "iso:country":"DE",
    "sg:address":"Mierendorffstr. 33",
    "sg:city":"Weinheim",
    "sg:phone":"+49 6201/66011",
    "sg:postcode":"69469",
    "sg:province":"Baden-W\u00fcrttemberg",
    "wof:name":"Heim Gmbh & Co. Kg",
    "wof:placetype":"venue"
},
  "geometry": {"coordinates":[8.6589956284,49.5418243408],"type":"Point"}
}