{
  "type": "Feature",
  "properties": {
    "iso:country":"DE",
    "sg:address":"Thierlsteiner Str. 14",
    "sg:city":"Cham",
    "sg:phone":"+49 9971/3960",
    "sg:postcode":"93413",
    "sg:province":"Bayern",
    "wof:name":"Ensinger Gmbh",
    "wof:placetype":"venue"
},
  "geometry": {"coordinates":[12.6258840561,49.2095146179],"type":"Point"}
}