{
  "type": "Feature",
  "properties": {
    "iso:country":"DE",
    "sg:address":"T\u00f6lzer Str. 14",
    "sg:city":"Egling",
    "sg:phone":"+49 8176/7474",
    "sg:postcode":"82544",
    "sg:province":"Bayern",
    "wof:name":"Trachten-fr\u00f6stl Vertriebs-gmbh",
    "wof:placetype":"venue"
},
  "geometry": {"coordinates":[11.5118408203,47.9193954468],"type":"Point"}
}