{
  "type": "Feature",
  "properties": {
    "iso:country":"DE",
    "sg:address":"Friedhofstr. 9",
    "sg:city":"Kornwestheim",
    "sg:phone":"+49 7154/26366",
    "sg:postcode":"70806",
    "sg:province":"Baden-W\u00fcrttemberg",
    "wof:name":"Helmut Hubbuch Grabdenkm\u00e4ler",
    "wof:placetype":"venue"
},
  "geometry": {"coordinates":[9.1932163239,48.8674278259],"type":"Point"}
}