{
  "type": "Feature",
  "properties": {
    "iso:country":"DE",
    "sg:address":"Hauptstr. 6",
    "sg:city":"Gundremmingen",
    "sg:phone":"+49 8224/2031",
    "sg:postcode":"89355",
    "sg:province":"Bayern",
    "wof:name":"Hermann Eggenm\u00fcller",
    "wof:placetype":"venue"
},
  "geometry": {"coordinates":[10.3974313736,48.4973297119],"type":"Point"}
}