{
  "type": "Feature",
  "properties": {
    "iso:country":"DE",
    "sg:address":"Am G\u00fcterbahnhof 4",
    "sg:city":"Geldern",
    "sg:phone":"+49 2831/4037",
    "sg:postcode":"47608",
    "sg:province":"Nordrhein-Westfalen",
    "wof:name":"Bernd Dorenkamp Bauunternehmen Kg",
    "wof:placetype":"venue"
},
  "geometry": {"coordinates":[6.3159198761,51.5157814026],"type":"Point"}
}