{
  "type": "Feature",
  "properties": {
    "iso:country":"DE",
    "sg:address":"Industriestr. 34",
    "sg:city":"Backnang",
    "sg:phone":"+49 7191/68126",
    "sg:postcode":"71522",
    "sg:province":"Baden-W\u00fcrttemberg",
    "wof:name":"Werners Bratshop",
    "wof:placetype":"venue"
},
  "geometry": {"coordinates":[9.4430704117,48.9366798401],"type":"Point"}
}