{
  "type": "Feature",
  "properties": {
    "iso:country":"DE",
    "sg:address":"Berliner Str. 1",
    "sg:city":"Finsterwalde",
    "sg:postcode":"03238",
    "sg:province":"Brandenburg",
    "wof:name":"B 2 Mode Gmbh",
    "wof:placetype":"venue"
},
  "geometry": {"coordinates":[13.7083473206,51.6344985962],"type":"Point"}
}