{
  "type": "Feature",
  "properties": {
    "iso:country":"DE",
    "sg:address":"Landmanngassl 16",
    "sg:city":"Grafrath",
    "sg:phone":"+49 8144/7527",
    "sg:postcode":"82284",
    "sg:province":"Bayern",
    "wof:name":"Hans Balazs Architekt",
    "wof:placetype":"venue"
},
  "geometry": {"coordinates":[11.154887,48.127617],"type":"Point"}
}