{
  "type": "Feature",
  "properties": {
    "iso:country":"DE",
    "sg:address":"Annaberger Str. 106a",
    "sg:city":"Raschau",
    "sg:phone":"+49 3774/86355",
    "sg:postcode":"08352",
    "sg:province":"Sachsen",
    "wof:name":"Mrowczynski",
    "wof:placetype":"venue"
},
  "geometry": {"coordinates":[12.821114,50.529827],"type":"Point"}
}