{
  "type": "Feature",
  "properties": {
    "iso:country":"DE",
    "sg:address":"Schlo\u00df Rurich",
    "sg:city":"H\u00fcckelhoven",
    "sg:phone":"+49 2462/7026",
    "sg:postcode":"41836",
    "sg:province":"Nordrhein-Westfalen",
    "wof:name":"Saxony Immobilien Gmbh",
    "wof:placetype":"venue"
},
  "geometry": {"coordinates":[6.2740430832,51.0136642456],"type":"Point"}
}