{
  "type": "Feature",
  "properties": {
    "iso:country":"DE",
    "sg:address":"Jungfernstieg 4",
    "sg:city":"Kiel",
    "sg:phone":"+49 431/93838",
    "sg:postcode":"24103",
    "sg:province":"Schleswig-Holstein",
    "wof:name":"Petersen",
    "wof:placetype":"venue"
},
  "geometry": {"coordinates":[10.1267194748,54.3239250183],"type":"Point"}
}