{
  "type": "Feature",
  "properties": {
    "iso:country":"DE",
    "sg:address":"Essener Str. 22",
    "sg:city":"Gelsenkirchen",
    "sg:phone":"+49 209/52898",
    "sg:postcode":"45899",
    "sg:province":"Nordrhein-Westfalen",
    "wof:name":"Spielothek Automaten-freizeit-center",
    "wof:placetype":"venue"
},
  "geometry": {"coordinates":[7.0225520134,51.5384407043],"type":"Point"}
}