{
  "type": "Feature",
  "properties": {
    "iso:country":"DE",
    "sg:address":"Goethestr. 9",
    "sg:city":"Winterberg",
    "sg:phone":"+49 2983/1541",
    "sg:postcode":"59955",
    "sg:province":"Nordrhein-Westfalen",
    "wof:name":"Norbert Schillings",
    "wof:placetype":"venue"
},
  "geometry": {"coordinates":[8.4716911316,51.2453193665],"type":"Point"}
}