{
  "type": "Feature",
  "properties": {
    "iso:country":"DE",
    "sg:address":"Rundweg 3",
    "sg:city":"Felsberg",
    "sg:postcode":"34587",
    "sg:province":"Hessen",
    "wof:name":"Klasen Internet Business Gmbh",
    "wof:placetype":"venue"
},
  "geometry": {"coordinates":[9.4562091827,51.1130943298],"type":"Point"}
}