{
  "type": "Feature",
  "properties": {
    "iso:country":"DE",
    "sg:address":"Asternweg 16",
    "sg:city":"Burgwedel",
    "sg:phone":"+49 5139/894291",
    "sg:postcode":"30938",
    "sg:province":"Niedersachsen",
    "wof:name":"Sylvia Elkarra",
    "wof:placetype":"venue"
},
  "geometry": {"coordinates":[9.864392,52.49078],"type":"Point"}
}