{
  "type": "Feature",
  "properties": {
    "iso:country":"DE",
    "sg:address":"R\u00f6merstr. 85",
    "sg:city":"Heidenheim",
    "sg:phone":"+49 7321/23384",
    "sg:postcode":"89522",
    "sg:province":"Baden-W\u00fcrttemberg",
    "wof:name":"Rudolf Sch\u00e4fer",
    "wof:placetype":"venue"
},
  "geometry": {"coordinates":[10.174442,48.675858],"type":"Point"}
}