{
  "type": "Feature",
  "properties": {
    "iso:country":"DE",
    "sg:address":"Im Mooshof 3",
    "sg:city":"Aurach",
    "sg:postcode":"91589",
    "sg:province":"Bayern",
    "wof:name":"B\u00fccherei Frau Hillmann",
    "wof:placetype":"venue"
},
  "geometry": {"coordinates":[10.414661,49.244202],"type":"Point"}
}