{
  "type": "Feature",
  "properties": {
    "iso:country":"DE",
    "sg:address":"Bockenheimer Landstr. 21",
    "sg:city":"Frankfurt",
    "sg:phone":"+49 69/710010",
    "sg:postcode":"60325",
    "sg:province":"Hessen",
    "wof:name":"Redaktion Deutsche Handwerks Zeitung",
    "wof:placetype":"venue"
},
  "geometry": {"coordinates":[8.6682529449,50.1159515381],"type":"Point"}
}