{
  "type": "Feature",
  "properties": {
    "iso:country":"DE",
    "sg:address":"Hauptstr. 266",
    "sg:city":"Adenau",
    "sg:phone":"+49 2691/92240",
    "sg:postcode":"53518",
    "sg:province":"Rheinland-Pfalz",
    "wof:name":"Karl Heinz Bell Kg",
    "wof:placetype":"venue"
},
  "geometry": {"coordinates":[6.9435801506,50.3818016052],"type":"Point"}
}