{
  "type": "Feature",
  "properties": {
    "iso:country":"DE",
    "sg:address":"Raiffeisenstr. 6",
    "sg:city":"Remscheid",
    "sg:postcode":"42897",
    "sg:province":"Nordrhein-Westfalen",
    "wof:name":"Meijers Art Antik E. K.",
    "wof:placetype":"venue"
},
  "geometry": {"coordinates":[7.265691,51.159599],"type":"Point"}
}