{
  "type": "Feature",
  "properties": {
    "iso:country":"DE",
    "sg:address":"Kirchgasse 15",
    "sg:city":"Frontenhausen",
    "sg:phone":"+49 8732/370",
    "sg:postcode":"84160",
    "sg:province":"Bayern",
    "wof:name":"Gusti Erl",
    "wof:placetype":"venue"
},
  "geometry": {"coordinates":[12.525246,48.547287],"type":"Point"}
}