{
  "type": "Feature",
  "properties": {
    "iso:country":"DE",
    "sg:address":"Elpersb\u00fcttlerdeich 25",
    "sg:city":"Elpersb\u00fcttel",
    "sg:phone":"+49 171 4930412",
    "sg:postcode":"25704",
    "sg:province":"Schleswig-Holstein",
    "wof:name":"Joachim Witt",
    "wof:placetype":"venue"
},
  "geometry": {"coordinates":[9.01435,54.0686],"type":"Point"}
}