{
  "type": "Feature",
  "properties": {
    "iso:country":"DE",
    "sg:address":"Sporgraben 14",
    "sg:city":"Wittlich",
    "sg:phone":"+49 6571/29440",
    "sg:postcode":"54516",
    "sg:province":"Rheinland-Pfalz",
    "wof:name":"Michael Anker Verwaltungs-gmbh",
    "wof:placetype":"venue"
},
  "geometry": {"coordinates":[6.8880457878,49.990688324],"type":"Point"}
}