{
  "type": "Feature",
  "properties": {
    "iso:country":"DE",
    "sg:address":"Hauptstr. 22",
    "sg:city":"Hirschberg",
    "sg:phone":"+49 6439/57134",
    "sg:postcode":"65558",
    "sg:province":"Rheinland-Pfalz",
    "wof:name":"Pension K\u00e4the K\u00fchr",
    "wof:placetype":"venue"
},
  "geometry": {"coordinates":[7.9270701408,50.3791542053],"type":"Point"}
}