{
  "type": "Feature",
  "properties": {
    "iso:country":"DE",
    "sg:address":"Adolfstr. 39",
    "sg:city":"Lahnstein",
    "sg:phone":"+49 2621/2409",
    "sg:postcode":"56112",
    "sg:province":"Rheinland-Pfalz",
    "wof:name":"W\u00fcstenrot Bausparkasse",
    "wof:placetype":"venue"
},
  "geometry": {"coordinates":[7.605763,50.302261],"type":"Point"}
}