{
  "type": "Feature",
  "properties": {
    "iso:country":"DE",
    "sg:address":"Bergische Str. 48",
    "sg:city":"Engelskirchen",
    "sg:phone":"+49 2263/20031",
    "sg:postcode":"51766",
    "sg:province":"Nordrhein-Westfalen",
    "wof:name":"Ial-institut F\u00fcr Angewandte Logistik",
    "wof:placetype":"venue"
},
  "geometry": {"coordinates":[7.4023709297,50.9894638062],"type":"Point"}
}