{
  "type": "Feature",
  "properties": {
    "iso:country":"DE",
    "sg:address":"Hauptstr. 39",
    "sg:city":"Bad Sch\u00f6nborn",
    "sg:phone":"+49 7253/33979",
    "sg:postcode":"76669",
    "sg:province":"Baden-W\u00fcrttemberg",
    "wof:name":"Ochsen",
    "wof:placetype":"venue"
},
  "geometry": {"coordinates":[8.6480226517,49.2037773132],"type":"Point"}
}