{
  "type": "Feature",
  "properties": {
    "iso:country":"DE",
    "sg:address":"Scharzhofberger Str.9",
    "sg:city":"Berlin",
    "sg:phone":"+49 30/7742238",
    "sg:postcode":"12247",
    "sg:province":"Berlin",
    "wof:name":"Handelswaren",
    "wof:placetype":"venue"
},
  "geometry": {"coordinates":[13.348597,52.438889],"type":"Point"}
}