{
  "type": "Feature",
  "properties": {
    "iso:country":"DE",
    "sg:address":"Von-Weber-Str. 3",
    "sg:city":"Rodgau",
    "sg:phone":"+49 6106/9989",
    "sg:postcode":"63110",
    "sg:province":"Hessen",
    "wof:name":"Karl Ricker",
    "wof:placetype":"venue"
},
  "geometry": {"coordinates":[8.8855228424,50.0516929626],"type":"Point"}
}