{
  "type": "Feature",
  "properties": {
    "iso:country":"DE",
    "sg:address":"Tegernsee",
    "sg:city":"Tegernsee",
    "sg:phone":"+49 8022/3936",
    "sg:postcode":"83684",
    "sg:province":"Bayern",
    "wof:name":"Raiffeisenbank",
    "wof:placetype":"venue"
},
  "geometry": {"coordinates":[11.76594,47.71833],"type":"Point"}
}