{
  "type": "Feature",
  "properties": {
    "iso:country":"DE",
    "sg:address":"Schie\u00dfgasse 19",
    "sg:city":"Butzbach",
    "sg:phone":"+49 6033/2368",
    "sg:postcode":"35510",
    "sg:province":"Hessen",
    "wof:name":"Heinz Wilk Finanzberater",
    "wof:placetype":"venue"
},
  "geometry": {"coordinates":[8.685585022,50.4172286987],"type":"Point"}
}