{
  "type": "Feature",
  "properties": {
    "iso:country":"DE",
    "sg:address":"Oberer Ehweg",
    "sg:city":"Regensburg",
    "sg:phone":"+49 941/700654",
    "sg:postcode":"93055",
    "sg:province":"Bayern",
    "wof:name":"R. Wolf",
    "wof:placetype":"venue"
},
  "geometry": {"coordinates":[12.166225,48.988224],"type":"Point"}
}