{
  "type": "Feature",
  "properties": {
    "iso:country":"DE",
    "sg:address":"Lichtenbergerstr. 10",
    "sg:city":"Ludwigshafen",
    "sg:phone":"+49 621/522048",
    "sg:postcode":"67059",
    "sg:province":"Rheinland-Pfalz",
    "wof:name":"Alster-lichtspielgesellschaft Dr. K\u00fcnzig Kg",
    "wof:placetype":"venue"
},
  "geometry": {"coordinates":[8.451384,49.481319],"type":"Point"}
}