{
  "type": "Feature",
  "properties": {
    "iso:country":"DE",
    "sg:address":"Neue Bergstr. 9",
    "sg:city":"Landsberg am Lech",
    "sg:phone":"+49 8191",
    "sg:postcode":"86899",
    "sg:province":"Bayern",
    "wof:name":"R\u00dctsche - Multimedia",
    "wof:placetype":"venue"
},
  "geometry": {"coordinates":[10.8771085739,48.048122406],"type":"Point"}
}