{
  "type": "Feature",
  "properties": {
    "iso:country":"DE",
    "sg:address":"Rurstr. 16",
    "sg:city":"Simmerath",
    "sg:phone":"+49 2485/213",
    "sg:postcode":"52152",
    "sg:province":"Nordrhein-Westfalen",
    "wof:name":"Hotel Sch\u00fctt",
    "wof:placetype":"venue"
},
  "geometry": {"coordinates":[6.3803920746,50.5831222534],"type":"Point"}
}