{
  "type": "Feature",
  "properties": {
    "iso:country":"DE",
    "sg:address":"Rheinstr. 40",
    "sg:city":"H\u00fcckelhoven",
    "sg:phone":"+49 2433/4777",
    "sg:postcode":"41836",
    "sg:province":"Nordrhein-Westfalen",
    "wof:name":"China-restaurant Kong",
    "wof:placetype":"venue"
},
  "geometry": {"coordinates":[6.2213010788,51.0478744507],"type":"Point"}
}