{
  "type": "Feature",
  "properties": {
    "iso:country":"DE",
    "sg:address":"H\u00f6tzelsdorfer Weg",
    "sg:city":"Attenhofen",
    "sg:phone":"+49 8751/9212",
    "sg:postcode":"84091",
    "sg:province":"Bayern",
    "wof:name":"Gastst\u00e4tte Josef Steiger",
    "wof:placetype":"venue"
},
  "geometry": {"coordinates":[11.8754749298,48.6643180847],"type":"Point"}
}