{
  "type": "Feature",
  "properties": {
    "iso:country":"DE",
    "sg:address":"Hans-Sachs-Str.5b",
    "sg:city":"Potsdam",
    "sg:phone":"+49 331",
    "sg:postcode":"14471",
    "sg:province":"Brandenburg",
    "wof:name":"Pflegeservice Wiku",
    "wof:placetype":"venue"
},
  "geometry": {"coordinates":[13.032694,52.394543],"type":"Point"}
}