{
  "type": "Feature",
  "properties": {
    "iso:country":"DE",
    "sg:address":"Fasanenhofstr. 119",
    "sg:city":"Stuttgart",
    "sg:phone":"+49 711/7155060",
    "sg:postcode":"70565",
    "sg:province":"Baden-W\u00fcrttemberg",
    "wof:name":"Wipa Wilhelm Gmbh",
    "wof:placetype":"venue"
},
  "geometry": {"coordinates":[9.1532859802,48.7090263367],"type":"Point"}
}