{
  "type": "Feature",
  "properties": {
    "iso:country":"DE",
    "sg:address":"Altendorfer Str. 262",
    "sg:city":"Essen",
    "sg:postcode":"45143",
    "sg:province":"Nordrhein-Westfalen",
    "wof:name":"M\u00f6bel Wolter Nachf. J\u00fcrgen Haendschke E. K.",
    "wof:placetype":"venue"
},
  "geometry": {"coordinates":[6.982735,51.459995],"type":"Point"}
}