{
  "type": "Feature",
  "properties": {
    "iso:country":"DE",
    "sg:address":"Fr\u00fchlingstr. 15",
    "sg:city":"Reichenbach",
    "sg:phone":"+49 7153/58120",
    "sg:postcode":"73262",
    "sg:province":"Baden-W\u00fcrttemberg",
    "wof:name":"Thaler Holzbildhauer",
    "wof:placetype":"venue"
},
  "geometry": {"coordinates":[9.465226,48.711346],"type":"Point"}
}