{
  "type": "Feature",
  "properties": {
    "iso:country":"DE",
    "sg:address":"Meersburger Str. 2",
    "sg:city":"K\u00f6ln",
    "sg:phone":"+49 221/432751",
    "sg:postcode":"50935",
    "sg:province":"Nordrhein-Westfalen",
    "wof:name":"Herbert Zangerle",
    "wof:placetype":"venue"
},
  "geometry": {"coordinates":[6.902435,50.92178],"type":"Point"}
}