{
  "type": "Feature",
  "properties": {
    "iso:country":"DE",
    "sg:address":"Feldteichstr. 8",
    "sg:city":"L\u00f6rrach",
    "sg:phone":"+49 7621/591541",
    "sg:postcode":"79541",
    "sg:province":"Baden-W\u00fcrttemberg",
    "wof:name":"Lieselotte Tr\u00f6ndlin Masseurin",
    "wof:placetype":"venue"
},
  "geometry": {"coordinates":[7.696379,47.635399],"type":"Point"}
}