{
  "type": "Feature",
  "properties": {
    "iso:country":"DE",
    "sg:address":"Broitzemer Str. 202",
    "sg:city":"Braunschweig",
    "sg:phone":"+49 531/85353",
    "sg:postcode":"38118",
    "sg:province":"Niedersachsen",
    "wof:name":"Otto Stelzner",
    "wof:placetype":"venue"
},
  "geometry": {"coordinates":[10.4964590073,52.2548446655],"type":"Point"}
}