{
  "type": "Feature",
  "properties": {
    "iso:country":"DE",
    "sg:address":"Hauptstr. 59",
    "sg:city":"Au\u00dfernzell",
    "sg:postcode":"94532",
    "sg:province":"Bayern",
    "wof:name":"Dls E. K.",
    "wof:placetype":"venue"
},
  "geometry": {"coordinates":[13.236967,48.728386],"type":"Point"}
}