{
  "type": "Feature",
  "properties": {
    "iso:country":"DE",
    "sg:address":"W\u00fcrmstr. 7 a",
    "sg:city":"Starnberg",
    "sg:phone":"+49 8151/12474",
    "sg:postcode":"82319",
    "sg:province":"Bayern",
    "wof:name":"Benno Michael Gautner Restaurator",
    "wof:placetype":"venue"
},
  "geometry": {"coordinates":[11.35959,48.000183],"type":"Point"}
}