{
  "type": "Feature",
  "properties": {
    "iso:country":"DE",
    "sg:address":"Hauptstr. 31",
    "sg:city":"Hage",
    "sg:phone":"+49 4931/7898",
    "sg:postcode":"26524",
    "sg:province":"Niedersachsen",
    "wof:name":"Erich Schoolmann Immobilienmakler",
    "wof:placetype":"venue"
},
  "geometry": {"coordinates":[7.2864589691,53.60313797],"type":"Point"}
}