{
  "type": "Feature",
  "properties": {
    "iso:country":"DE",
    "sg:address":"Baumeisterstr. 14",
    "sg:city":"Wuppertal",
    "sg:phone":"+49 202/302393",
    "sg:postcode":"42105",
    "sg:province":"Nordrhein-Westfalen",
    "wof:name":"Dorrenberger Hof",
    "wof:placetype":"venue"
},
  "geometry": {"coordinates":[7.1326270103,51.2654762268],"type":"Point"}
}