{
  "type": "Feature",
  "properties": {
    "iso:country":"DE",
    "sg:address":"Reinekestr. 12",
    "sg:city":"Cuxhaven",
    "sg:phone":"+49 4721/37067",
    "sg:postcode":"27472",
    "sg:province":"Niedersachsen",
    "wof:name":"Paycho-soziale Beratungsstelle",
    "wof:placetype":"venue"
},
  "geometry": {"coordinates":[8.698666,53.869968],"type":"Point"}
}