{
  "type": "Feature",
  "properties": {
    "iso:country":"DE",
    "sg:address":"Fabristr. 10",
    "sg:city":"Ulm",
    "sg:phone":"+49 731/66216",
    "sg:postcode":"89075",
    "sg:province":"Baden-W\u00fcrttemberg",
    "wof:name":"Sidonie Bilger-w\u00f6lpert Architektin",
    "wof:placetype":"venue"
},
  "geometry": {"coordinates":[9.987185,48.409893],"type":"Point"}
}