{
  "type": "Feature",
  "properties": {
    "iso:country":"DE",
    "sg:address":"Lammersdorfer Str.",
    "sg:city":"Hillesheim",
    "sg:phone":"+49 6593/522",
    "sg:postcode":"54576",
    "sg:province":"Rheinland-Pfalz",
    "wof:name":"Ludwig Endres",
    "wof:placetype":"venue"
},
  "geometry": {"coordinates":[6.671119,50.287121],"type":"Point"}
}