{
  "type": "Feature",
  "properties": {
    "iso:country":"DE",
    "sg:address":"Hauptstr. 46",
    "sg:city":"Golzow",
    "sg:postcode":"15328",
    "sg:province":"Brandenburg",
    "wof:name":"Uta Schr\u00f6ter",
    "wof:placetype":"venue"
},
  "geometry": {"coordinates":[14.4907617569,52.5758972168],"type":"Point"}
}