{
  "type": "Feature",
  "properties": {
    "iso:country":"DE",
    "sg:address":"Am Hafensteig 19",
    "sg:city":"Neustadt",
    "sg:phone":"+49 4561/61060",
    "sg:postcode":"23730",
    "sg:province":"Schleswig-Holstein",
    "wof:name":"Princesse De Provence Schiffahrts-gmbh & Co. Kg",
    "wof:placetype":"venue"
},
  "geometry": {"coordinates":[10.885068,54.134293],"type":"Point"}
}