{
  "type": "Feature",
  "properties": {
    "iso:country":"DE",
    "sg:address":"Bachstr 42",
    "sg:city":"Gro\u00dfostheim",
    "sg:phone":"+49 6026/6700",
    "sg:postcode":"63762",
    "sg:province":"Bayern",
    "wof:name":"Hock Repr\u00e4sentanz Der S\u00fcd Leasing Gmbh",
    "wof:placetype":"venue"
},
  "geometry": {"coordinates":[9.075957,49.919216],"type":"Point"}
}