{
  "type": "Feature",
  "properties": {
    "iso:country":"DE",
    "sg:address":"Wupperstr 4",
    "sg:city":"Wiesbaden",
    "sg:phone":"+49 611/271350",
    "sg:postcode":"65201",
    "sg:province":"Hessen",
    "wof:name":"Allround Services Barmeier Gmbh",
    "wof:placetype":"venue"
},
  "geometry": {"coordinates":[8.1893234253,50.0452690125],"type":"Point"}
}