{
  "type": "Feature",
  "properties": {
    "iso:country":"DE",
    "sg:address":"Castroper Str. 263",
    "sg:city":"Bochum",
    "sg:phone":"+49 234/9509000",
    "sg:postcode":"44791",
    "sg:province":"Nordrhein-Westfalen",
    "wof:name":"Drewes & Grunert",
    "wof:placetype":"venue"
},
  "geometry": {"coordinates":[7.249350071,51.4930686951],"type":"Point"}
}