{
  "type": "Feature",
  "properties": {
    "iso:country":"DE",
    "sg:address":"Lindenstr. 10",
    "sg:city":"Trier",
    "sg:phone":"+49 651/970500",
    "sg:postcode":"54292",
    "sg:province":"Rheinland-Pfalz",
    "wof:name":"Bautralux Gmbh",
    "wof:placetype":"venue"
},
  "geometry": {"coordinates":[6.6362838745,49.7628135681],"type":"Point"}
}