{
  "type": "Feature",
  "properties": {
    "iso:country":"DE",
    "sg:address":"Am Schlo\u00dfbach 10",
    "sg:city":"Bonn",
    "sg:phone":"+49 228/252502",
    "sg:postcode":"53125",
    "sg:province":"Nordrhein-Westfalen",
    "wof:name":"Gebr. Kallenberg Gmbh & Co. Kg",
    "wof:placetype":"venue"
},
  "geometry": {"coordinates":[7.0657219887,50.6786499023],"type":"Point"}
}