{
  "type": "Feature",
  "properties": {
    "iso:country":"DE",
    "sg:address":"Gartenstr. 17",
    "sg:city":"Ravensburg",
    "sg:phone":"+49 751/23090",
    "sg:postcode":"88212",
    "sg:province":"Baden-W\u00fcrttemberg",
    "wof:name":"Chris Rohr",
    "wof:placetype":"venue"
},
  "geometry": {"coordinates":[9.616467,47.785423],"type":"Point"}
}