{
  "type": "Feature",
  "properties": {
    "iso:country":"DE",
    "sg:address":"Unsernherrner Str. 31",
    "sg:city":"Ingolstadt",
    "sg:phone":"+49 841/61890",
    "sg:postcode":"85053",
    "sg:province":"Bayern",
    "wof:name":"C. Limmer Drogerie",
    "wof:placetype":"venue"
},
  "geometry": {"coordinates":[11.45865,48.735607],"type":"Point"}
}