{
  "type": "Feature",
  "properties": {
    "iso:country":"DE",
    "sg:address":"Hamburger Str. 30",
    "sg:city":"Lauenburg",
    "sg:phone":"+49 4153/3120",
    "sg:postcode":"21481",
    "sg:province":"Schleswig-Holstein",
    "wof:name":"Aral-tankstelle",
    "wof:placetype":"venue"
},
  "geometry": {"coordinates":[10.5498523712,53.3741188049],"type":"Point"}
}