{
  "type": "Feature",
  "properties": {
    "iso:country":"DE",
    "sg:address":"Igelsburgstr.",
    "sg:city":"Habichtswald",
    "sg:phone":"+49 5606/9014",
    "sg:postcode":"34317",
    "sg:province":"Hessen",
    "wof:name":"Franz Menke Kg",
    "wof:placetype":"venue"
},
  "geometry": {"coordinates":[9.3374052048,51.3355064392],"type":"Point"}
}