{
  "type": "Feature",
  "properties": {
    "iso:country":"DE",
    "sg:address":"Kreuzbergstr. 42",
    "sg:city":"Dessau",
    "sg:phone":"+49 340/8581259",
    "sg:postcode":"06849",
    "sg:province":"Sachsen-Anhalt",
    "wof:name":"Bio Rein-fachgro\u00dfhandel F\u00fcr Reinigungsbedarf Gmbh",
    "wof:placetype":"venue"
},
  "geometry": {"coordinates":[12.2556581497,51.8017425537],"type":"Point"}
}