{
  "type": "Feature",
  "properties": {
    "iso:country":"DE",
    "sg:address":"Rothenbaumchaussee 56",
    "sg:city":"Hamburg",
    "sg:phone":"+49 40/448140",
    "sg:postcode":"20148",
    "sg:province":"Hamburg",
    "wof:name":"Bruno Schr\u00f6der",
    "wof:placetype":"venue"
},
  "geometry": {"coordinates":[9.9885940552,53.5674362183],"type":"Point"}
}