{
  "type": "Feature",
  "properties": {
    "iso:country":"DE",
    "sg:address":"Untere Waldpl\u00e4tze 14",
    "sg:city":"Stuttgart",
    "sg:phone":"+49 711/681617",
    "sg:postcode":"70569",
    "sg:province":"Baden-W\u00fcrttemberg",
    "wof:name":"Phoenix Ag",
    "wof:placetype":"venue"
},
  "geometry": {"coordinates":[9.086462,48.731159],"type":"Point"}
}