{
  "type": "Feature",
  "properties": {
    "iso:country":"DE",
    "sg:address":"Ovendorferredder 5",
    "sg:city":"Schillsdorf",
    "sg:postcode":"24637",
    "sg:province":"Schleswig-Holstein",
    "wof:name":"Jk Holzbauteam Gmbh",
    "wof:placetype":"venue"
},
  "geometry": {"coordinates":[10.1207752228,54.1419868469],"type":"Point"}
}