{
  "type": "Feature",
  "properties": {
    "iso:country":"DE",
    "sg:address":"Bahnhofstr. 14",
    "sg:city":"Bad Soden-Salm\u00fcnster",
    "sg:phone":"+49 6056/2007",
    "sg:postcode":"63628",
    "sg:province":"Hessen",
    "wof:name":"Ekizoglu",
    "wof:placetype":"venue"
},
  "geometry": {"coordinates":[9.3712911606,50.2806167603],"type":"Point"}
}