{
  "type": "Feature",
  "properties": {
    "iso:country":"DE",
    "sg:address":"M\u00fcnstermauer 7",
    "sg:city":"Rheine",
    "sg:phone":"+49 5971/2368",
    "sg:postcode":"48431",
    "sg:province":"Nordrhein-Westfalen",
    "wof:name":"Anno Tobac",
    "wof:placetype":"venue"
},
  "geometry": {"coordinates":[7.4394459724,52.2786560059],"type":"Point"}
}