{
  "type": "Feature",
  "properties": {
    "iso:country":"DE",
    "sg:address":"Babbergerstr. 2",
    "sg:city":"Karlsruhe",
    "sg:phone":"+49 721/912120",
    "sg:postcode":"76189",
    "sg:province":"Baden-W\u00fcrttemberg",
    "wof:name":"Adolf Bach Hoch- Tief- Und Stahlbetonbau Gmbh",
    "wof:placetype":"venue"
},
  "geometry": {"coordinates":[8.3195238113,49.0057411194],"type":"Point"}
}