{
  "type": "Feature",
  "properties": {
    "iso:country":"DE",
    "sg:address":"Esternaystr. 101",
    "sg:city":"Waldbronn",
    "sg:phone":"+49 7243/66971",
    "sg:postcode":"76337",
    "sg:province":"Baden-W\u00fcrttemberg",
    "wof:name":"Renate Wimmer Krankengymnastin",
    "wof:placetype":"venue"
},
  "geometry": {"coordinates":[8.468578,48.90881],"type":"Point"}
}