{
  "type": "Feature",
  "properties": {
    "iso:country":"DE",
    "sg:address":"Carl-von-Ossietzky-Str. 17",
    "sg:city":"Rostock",
    "sg:phone":"+49 381/682592",
    "sg:postcode":"18147",
    "sg:province":"Mecklenburg-Vorpommern",
    "wof:name":"Uwe Kroll",
    "wof:placetype":"venue"
},
  "geometry": {"coordinates":[12.1381,54.113976],"type":"Point"}
}