{
  "type": "Feature",
  "properties": {
    "iso:country":"DE",
    "sg:address":"Rosenstr. 42",
    "sg:city":"Stuttgart",
    "sg:phone":"+49 711/24897130",
    "sg:postcode":"70182",
    "sg:province":"Baden-W\u00fcrttemberg",
    "wof:name":"C. Und K.-p. Goebel Innenarchitekten",
    "wof:placetype":"venue"
},
  "geometry": {"coordinates":[9.184711,48.773884],"type":"Point"}
}