{
  "type": "Feature",
  "properties": {
    "iso:country":"DE",
    "sg:address":"Bergstr. 102",
    "sg:city":"Ahlen",
    "sg:phone":"+49 2382/6884",
    "sg:postcode":"59229",
    "sg:province":"Nordrhein-Westfalen",
    "wof:name":"M. Osthus",
    "wof:placetype":"venue"
},
  "geometry": {"coordinates":[7.9170980453,51.7688522339],"type":"Point"}
}