{
  "type": "Feature",
  "properties": {
    "iso:country":"DE",
    "sg:address":"Ausschl\u00e4ger Allee 48",
    "sg:city":"Hamburg",
    "sg:phone":"+49 40/784971",
    "sg:postcode":"20539",
    "sg:province":"Hamburg",
    "wof:name":"R. Holderbaum",
    "wof:placetype":"venue"
},
  "geometry": {"coordinates":[10.054374,53.531746],"type":"Point"}
}