{
  "type": "Feature",
  "properties": {
    "iso:country":"DE",
    "sg:address":"Altenberger Str. 86",
    "sg:city":"Wermelskirchen",
    "sg:phone":"+49 2193/51020",
    "sg:postcode":"42929",
    "sg:province":"Nordrhein-Westfalen",
    "wof:name":"Busreisen",
    "wof:placetype":"venue"
},
  "geometry": {"coordinates":[7.189834,51.092754],"type":"Point"}
}