{
  "type": "Feature",
  "properties": {
    "iso:country":"DE",
    "sg:address":"Turmhofstr. 45 a",
    "sg:city":"Mechernich",
    "sg:phone":"+49 2443/1207",
    "sg:postcode":"53894",
    "sg:province":"Nordrhein-Westfalen",
    "wof:name":"Spielkisten Automaten- Aufstellungsges. Mbh & Co. Kg",
    "wof:placetype":"venue"
},
  "geometry": {"coordinates":[6.6555509567,50.5915756226],"type":"Point"}
}