{
  "type": "Feature",
  "properties": {
    "iso:country":"DE",
    "sg:address":"Burgfelder Str. 3",
    "sg:city":"Stuttgart",
    "sg:phone":"+49 711/711914",
    "sg:postcode":"70567",
    "sg:province":"Baden-W\u00fcrttemberg",
    "wof:name":"Klaus-walter B\u00f6hringer",
    "wof:placetype":"venue"
},
  "geometry": {"coordinates":[9.1412639618,48.7276268005],"type":"Point"}
}