{
  "type": "Feature",
  "properties": {
    "iso:country":"DE",
    "sg:address":"Gewerbestr. 7",
    "sg:city":"Malterdingen",
    "sg:phone":"+49 7644/913020",
    "sg:postcode":"79364",
    "sg:province":"Baden-W\u00fcrttemberg",
    "wof:name":"B. Kuri Immobilienmakler",
    "wof:placetype":"venue"
},
  "geometry": {"coordinates":[7.7768058777,48.1514701843],"type":"Point"}
}