{
  "type": "Feature",
  "properties": {
    "iso:country":"DE",
    "sg:address":"Kasseler Str. 28",
    "sg:city":"Homberg",
    "sg:phone":"+49 5681/99890",
    "sg:postcode":"34576",
    "sg:province":"Hessen",
    "wof:name":"Raiffeisen-warenzentrale Kurhessen-th\u00fcringen Gmbh",
    "wof:placetype":"venue"
},
  "geometry": {"coordinates":[9.397819,51.038689],"type":"Point"}
}