{
  "type": "Feature",
  "properties": {
    "iso:country":"DE",
    "sg:address":"Silder Moor 9",
    "sg:city":"Kavelstorf",
    "sg:phone":"+49 4938/208660",
    "sg:postcode":"18196",
    "sg:province":"Mecklenburg-Vorpommern",
    "wof:name":"Hermann Stitz & Co Rostock Kg",
    "wof:placetype":"venue"
},
  "geometry": {"coordinates":[12.205148,54.016293],"type":"Point"}
}