{
  "type": "Feature",
  "properties": {
    "iso:country":"DE",
    "sg:address":"Limastr. 2",
    "sg:city":"Berlin",
    "sg:phone":"+49 30/8029799",
    "sg:postcode":"14163",
    "sg:province":"Berlin",
    "wof:name":"Elke Stumpp",
    "wof:placetype":"venue"
},
  "geometry": {"coordinates":[13.231547,52.438225],"type":"Point"}
}