{
  "type": "Feature",
  "properties": {
    "iso:country":"DE",
    "sg:address":"M\u00fchlenstr. 44",
    "sg:city":"Seehausen",
    "sg:phone":"+49 39886/2821",
    "sg:postcode":"39615",
    "sg:province":"Sachsen-Anhalt",
    "wof:name":"Volksbank Seehausen",
    "wof:placetype":"venue"
},
  "geometry": {"coordinates":[11.753577,52.893116],"type":"Point"}
}