{
  "type": "Feature",
  "properties": {
    "iso:country":"DE",
    "sg:address":"Thura-Mark 14",
    "sg:city":"Z\u00f6rbig",
    "sg:phone":"+49 34956/3190",
    "sg:postcode":"06780",
    "sg:province":"Sachsen-Anhalt",
    "wof:name":"Z\u00f6rbiger Konfit\u00fcren Gmbh",
    "wof:placetype":"venue"
},
  "geometry": {"coordinates":[12.1351270676,51.6274375916],"type":"Point"}
}