{
  "type": "Feature",
  "properties": {
    "iso:country":"DE",
    "sg:address":"Innere Plauensche Str. 17",
    "sg:city":"Zwickau",
    "sg:postcode":"08056",
    "sg:province":"Sachsen",
    "wof:name":"Deutsche Telekom T-punkt",
    "wof:placetype":"venue"
},
  "geometry": {"coordinates":[12.4973049164,50.7163658142],"type":"Point"}
}