{
  "type": "Feature",
  "properties": {
    "iso:country":"DE",
    "sg:address":"Stadelner Hauptstr. 170",
    "sg:city":"F\u00fcrth",
    "sg:phone":"+49 911/7659626",
    "sg:postcode":"90765",
    "sg:province":"Bayern",
    "wof:name":"M. Ponkratz",
    "wof:placetype":"venue"
},
  "geometry": {"coordinates":[10.9766969681,49.523109436],"type":"Point"}
}