{
  "type": "Feature",
  "properties": {
    "iso:country":"DE",
    "sg:address":"H\u00f6lderlinstr. 13",
    "sg:city":"B\u00f6blingen",
    "sg:phone":"+49 7031/224417",
    "sg:postcode":"71032",
    "sg:province":"Baden-W\u00fcrttemberg",
    "wof:name":"Ers Electronic Recycle Service E. K.",
    "wof:placetype":"venue"
},
  "geometry": {"coordinates":[9.0236988068,48.6871643066],"type":"Point"}
}