{
  "type": "Feature",
  "properties": {
    "iso:country":"DE",
    "sg:address":"Schornweisach 74 1/2",
    "sg:city":"Uehlfeld",
    "sg:phone":"+49 9163/8282",
    "sg:postcode":"91486",
    "sg:province":"Bayern",
    "wof:name":"Ev. Luth. Pfarramt",
    "wof:placetype":"venue"
},
  "geometry": {"coordinates":[10.7239103317,49.6714706421],"type":"Point"}
}