{
  "type": "Feature",
  "properties": {
    "iso:country":"DE",
    "sg:address":"Karl-Liebknecht-Str. 12",
    "sg:city":"Zwickau",
    "sg:postcode":"08056",
    "sg:province":"Sachsen",
    "wof:name":"F & J Import-export Gmbh",
    "wof:placetype":"venue"
},
  "geometry": {"coordinates":[12.513966,50.699802],"type":"Point"}
}