{
  "type": "Feature",
  "properties": {
    "iso:country":"DE",
    "sg:address":"Z\u00fclpicher Str. 38",
    "sg:city":"D\u00fcren",
    "sg:phone":"+49 2421/51516",
    "sg:postcode":"52349",
    "sg:province":"Nordrhein-Westfalen",
    "wof:name":"Da Nunzia",
    "wof:placetype":"venue"
},
  "geometry": {"coordinates":[6.4911489487,50.794757843],"type":"Point"}
}