{
  "type": "Feature",
  "properties": {
    "iso:country":"DE",
    "sg:address":"Karl-Marx-Str. 5",
    "sg:city":"Schmalkalden",
    "sg:postcode":"98574",
    "sg:province":"Th\u00fcringen",
    "wof:name":"K. Kr\u00fcger Ingenieur",
    "wof:placetype":"venue"
},
  "geometry": {"coordinates":[10.4536237717,50.7205810547],"type":"Point"}
}