{
  "type": "Feature",
  "properties": {
    "iso:country":"DE",
    "sg:address":"Friesoyther Str. 45",
    "sg:city":"Bar\u00dfel",
    "sg:phone":"+49 4499/388",
    "sg:postcode":"26676",
    "sg:province":"Niedersachsen",
    "wof:name":"Gastst\u00e4tte Toni D\u00fcllmann",
    "wof:placetype":"venue"
},
  "geometry": {"coordinates":[7.7545199394,53.1623306274],"type":"Point"}
}