{
  "type": "Feature",
  "properties": {
    "iso:country":"DE",
    "sg:address":"Moerser Str. 229",
    "sg:city":"Kamp-Lintfort",
    "sg:phone":"+49 2842/10577",
    "sg:postcode":"47475",
    "sg:province":"Nordrhein-Westfalen",
    "wof:name":"G. Sieder",
    "wof:placetype":"venue"
},
  "geometry": {"coordinates":[6.545099,51.502968],"type":"Point"}
}