{
  "type": "Feature",
  "properties": {
    "iso:country":"DE",
    "sg:address":"Werzenkamp 35",
    "sg:city":"Dortmund",
    "sg:phone":"+49 231/5899510",
    "sg:postcode":"44329",
    "sg:province":"Nordrhein-Westfalen",
    "wof:name":"Adrian Technologies Gmbh",
    "wof:placetype":"venue"
},
  "geometry": {"coordinates":[7.550447,51.560204],"type":"Point"}
}