{
  "type": "Feature",
  "properties": {
    "iso:country":"DE",
    "sg:address":"Lindenstr.",
    "sg:city":"Saerbeck",
    "sg:phone":"+49 2574/730",
    "sg:postcode":"48369",
    "sg:province":"Nordrhein-Westfalen",
    "wof:name":"Freibad Gemeinde",
    "wof:placetype":"venue"
},
  "geometry": {"coordinates":[7.6407880783,52.1740112305],"type":"Point"}
}