{
  "type": "Feature",
  "properties": {
    "iso:country":"DE",
    "sg:address":"Sundgauallee 35",
    "sg:city":"Freiburg",
    "sg:phone":"+49 761/81180",
    "sg:postcode":"79114",
    "sg:province":"Baden-W\u00fcrttemberg",
    "wof:name":"Waltraud Janz",
    "wof:placetype":"venue"
},
  "geometry": {"coordinates":[7.8134050369,48.0093345642],"type":"Point"}
}