{
  "type": "Feature",
  "properties": {
    "iso:country":"DE",
    "sg:address":"Dorfstr. 92",
    "sg:city":"Neuermark-L\u00fcbars",
    "sg:phone":"+49 39327/41330",
    "sg:postcode":"39524",
    "sg:province":"Sachsen-Anhalt",
    "wof:name":"Pauli",
    "wof:placetype":"venue"
},
  "geometry": {"coordinates":[12.041345,52.654762],"type":"Point"}
}