{
  "type": "Feature",
  "properties": {
    "iso:country":"DE",
    "sg:address":"Martin-Schongauer-Str. 6",
    "sg:city":"Gundelfingen",
    "sg:phone":"+49 761/580294",
    "sg:postcode":"79194",
    "sg:province":"Baden-W\u00fcrttemberg",
    "wof:name":"Eugen Link- Vertrieb Von Roll\u00e4den Und",
    "wof:placetype":"venue"
},
  "geometry": {"coordinates":[7.864237,48.040131],"type":"Point"}
}