{
  "type": "Feature",
  "properties": {
    "iso:country":"DE",
    "sg:address":"Eikbusch 1",
    "sg:city":"Brunsbek",
    "sg:phone":"+49 4107/9844",
    "sg:postcode":"22946",
    "sg:province":"Schleswig-Holstein",
    "wof:name":"G\u00fcternahverkehr Georg Kehnscherper",
    "wof:placetype":"venue"
},
  "geometry": {"coordinates":[10.2933530807,53.5873451233],"type":"Point"}
}