{
  "type": "Feature",
  "properties": {
    "iso:country":"DE",
    "sg:address":"Am Kreuzkamp 5-7",
    "sg:city":"G\u00fctersloh",
    "sg:phone":"+49 5241/96600",
    "sg:postcode":"33334",
    "sg:province":"Nordrhein-Westfalen",
    "wof:name":"Heilpunkt Naturpharma Verwaltungs Gmbh",
    "wof:placetype":"venue"
},
  "geometry": {"coordinates":[8.4053201675,51.9530982971],"type":"Point"}
}