{
  "type": "Feature",
  "properties": {
    "iso:country":"DE",
    "sg:address":"Kirschenweg 9",
    "sg:city":"Butzbach",
    "sg:phone":"+49 6081/14157",
    "sg:postcode":"35510",
    "sg:province":"Hessen",
    "wof:name":"Emil R. Schnorbus Gmbh",
    "wof:placetype":"venue"
},
  "geometry": {"coordinates":[8.5702648163,50.3804893494],"type":"Point"}
}