{
  "type": "Feature",
  "properties": {
    "iso:country":"DE",
    "sg:address":"Quellenstr. 1",
    "sg:city":"Bad Breisig",
    "sg:phone":"+49 2633/9405",
    "sg:postcode":"53498",
    "sg:province":"Rheinland-Pfalz",
    "wof:name":"Elektro-kr\u00e4mer Verwaltungs-gmbh",
    "wof:placetype":"venue"
},
  "geometry": {"coordinates":[7.296020031,50.509021759],"type":"Point"}
}