{
  "type": "Feature",
  "properties": {
    "iso:country":"DE",
    "sg:address":"Parkstr. 27",
    "sg:city":"Karlsruhe",
    "sg:postcode":"76131",
    "sg:province":"Baden-W\u00fcrttemberg",
    "wof:name":"Fleiwex Gmbh & Co. Kg",
    "wof:placetype":"venue"
},
  "geometry": {"coordinates":[8.4233446121,49.0117530823],"type":"Point"}
}