{
  "type": "Feature",
  "properties": {
    "iso:country":"DE",
    "sg:address":"Andreestr. 11",
    "sg:city":"M\u00fcnchen",
    "sg:phone":"+49 89/13998063",
    "sg:postcode":"80634",
    "sg:province":"Bayern",
    "wof:name":"Eva Fleschutz Rechtsanw\u00e4ltin",
    "wof:placetype":"venue"
},
  "geometry": {"coordinates":[11.5299282074,48.1513023376],"type":"Point"}
}