{
  "type": "Feature",
  "properties": {
    "iso:country":"DE",
    "sg:address":"Gartenfeldstr. 20",
    "sg:city":"Mainz",
    "sg:phone":"+49 6131/674160",
    "sg:postcode":"55118",
    "sg:province":"Rheinland-Pfalz",
    "wof:name":"Kurt Bouras",
    "wof:placetype":"venue"
},
  "geometry": {"coordinates":[8.2609128952,50.0051879883],"type":"Point"}
}