{
  "type": "Feature",
  "properties": {
    "iso:country":"DE",
    "sg:address":"Zehntwall 47",
    "sg:city":"Erftstadt",
    "sg:phone":"+49 2235/76999",
    "sg:postcode":"50374",
    "sg:province":"Nordrhein-Westfalen",
    "wof:name":"Schnitzler",
    "wof:placetype":"venue"
},
  "geometry": {"coordinates":[6.767563,50.798347],"type":"Point"}
}