{
  "type": "Feature",
  "properties": {
    "iso:country":"DE",
    "sg:address":"Oderlandstr. 3",
    "sg:city":"Eisenh\u00fcttenstadt",
    "sg:phone":"+49 3364/75390",
    "sg:postcode":"15890",
    "sg:province":"Brandenburg",
    "wof:name":"Heckmann Stahl- Und Metallbau Ost Gmbh",
    "wof:placetype":"venue"
},
  "geometry": {"coordinates":[14.65444,52.151855],"type":"Point"}
}