{
  "type": "Feature",
  "properties": {
    "iso:country":"DE",
    "sg:address":"Seilerstr. 13",
    "sg:city":"Wuppertal",
    "sg:phone":"+49 202/314244",
    "sg:postcode":"42103",
    "sg:province":"Nordrhein-Westfalen",
    "wof:name":"Raymond Machel",
    "wof:placetype":"venue"
},
  "geometry": {"coordinates":[7.1392188072,51.2527008057],"type":"Point"}
}