{
  "type": "Feature",
  "properties": {
    "iso:country":"DE",
    "sg:address":"Clever Landstr. 3 e",
    "sg:city":"Stockelsdorf",
    "sg:postcode":"23617",
    "sg:province":"Schleswig-Holstein",
    "wof:name":"Trave Versicherungs- Vermittlungs- Gmbh",
    "wof:placetype":"venue"
},
  "geometry": {"coordinates":[10.648850441,53.8902435303],"type":"Point"}
}