{
  "type": "Feature",
  "properties": {
    "iso:country":"DE",
    "sg:address":"Eichendorffstr. 62",
    "sg:city":"Esslingen",
    "sg:postcode":"73734",
    "sg:province":"Baden-W\u00fcrttemberg",
    "wof:name":"Aikido-verein-esslingen E.v.",
    "wof:placetype":"venue"
},
  "geometry": {"coordinates":[9.2930488586,48.7268829346],"type":"Point"}
}