{
  "type": "Feature",
  "properties": {
    "iso:country":"DE",
    "sg:address":"Gartenstr. 56",
    "sg:city":"M\u00fclsen",
    "sg:phone":"+49 37601/2399",
    "sg:postcode":"08132",
    "sg:province":"Sachsen",
    "wof:name":"Holzbau Tz M\u00fclsen Gmbh",
    "wof:placetype":"venue"
},
  "geometry": {"coordinates":[12.594902,50.740299],"type":"Point"}
}