{
  "type": "Feature",
  "properties": {
    "iso:country":"DE",
    "sg:address":"Graacher Str. 23",
    "sg:city":"Bernkastel-Kues",
    "sg:phone":"+49 6531/8418",
    "sg:postcode":"54470",
    "sg:province":"Rheinland-Pfalz",
    "wof:name":"Karl-heinz Br\u00fcck",
    "wof:placetype":"venue"
},
  "geometry": {"coordinates":[7.076130867,49.9165039062],"type":"Point"}
}