{
  "type": "Feature",
  "properties": {
    "iso:country":"DE",
    "sg:address":"Sch\u00f6nbergerstr. 2",
    "sg:city":"L\u00fctjenburg",
    "sg:phone":"+49 4381/7701",
    "sg:postcode":"24321",
    "sg:province":"Schleswig-Holstein",
    "wof:name":"Motalia",
    "wof:placetype":"venue"
},
  "geometry": {"coordinates":[10.5829811096,54.2890319824],"type":"Point"}
}