{
  "type": "Feature",
  "properties": {
    "iso:country":"DE",
    "sg:address":"Alfred-Randt-Str. 11",
    "sg:city":"Berlin",
    "sg:postcode":"12559",
    "sg:province":"Berlin",
    "wof:name":"Lutz Manthe",
    "wof:placetype":"venue"
},
  "geometry": {"coordinates":[13.598911,52.439137],"type":"Point"}
}