{
  "type": "Feature",
  "properties": {
    "iso:country":"DE",
    "sg:address":"In der Horst 19a",
    "sg:city":"Bad Zwischenahn",
    "sg:phone":"+49 4403/2703",
    "sg:postcode":"26160",
    "sg:province":"Niedersachsen",
    "wof:name":"M. Rastedt-kutz",
    "wof:placetype":"venue"
},
  "geometry": {"coordinates":[8.01218,53.183006],"type":"Point"}
}