{
  "type": "Feature",
  "properties": {
    "iso:country":"DE",
    "sg:address":"Am Heidekamp 4",
    "sg:city":"Papenburg",
    "sg:phone":"+49 4961/4284",
    "sg:postcode":"26871",
    "sg:province":"Niedersachsen",
    "wof:name":"Heinrich Hillebrand",
    "wof:placetype":"venue"
},
  "geometry": {"coordinates":[7.3954658508,53.0698738098],"type":"Point"}
}