{
  "type": "Feature",
  "properties": {
    "iso:country":"DE",
    "sg:address":"77880",
    "sg:city":"Sasbach",
    "sg:postcode":"77880",
    "sg:province":"Baden-W\u00fcrttemberg",
    "wof:name":"Volksbank Sasbach Eg",
    "wof:placetype":"venue"
},
  "geometry": {"coordinates":[8.09496,48.647831],"type":"Point"}
}