{
  "type": "Feature",
  "properties": {
    "iso:country":"DE",
    "sg:address":"Markt 3",
    "sg:city":"Goslar",
    "sg:phone":"+49 5321/7090",
    "sg:postcode":"38640",
    "sg:province":"Niedersachsen",
    "wof:name":"Hotel Kaiser Worth",
    "wof:placetype":"venue"
},
  "geometry": {"coordinates":[10.4297056198,51.9056854248],"type":"Point"}
}