{
  "type": "Feature",
  "properties": {
    "iso:country":"DE",
    "sg:address":"Albert-Reis-Str. 3",
    "sg:city":"Ostrach",
    "sg:phone":"+49 7585/2600",
    "sg:postcode":"88356",
    "sg:province":"Baden-W\u00fcrttemberg",
    "wof:name":"Ostrachttal-apotheke",
    "wof:placetype":"venue"
},
  "geometry": {"coordinates":[9.380238,47.951263],"type":"Point"}
}