{
  "type": "Feature",
  "properties": {
    "iso:country":"DE",
    "sg:address":"Altendorfer Str. 369",
    "sg:city":"Essen",
    "sg:phone":"+49 201/626087",
    "sg:postcode":"45143",
    "sg:province":"Nordrhein-Westfalen",
    "wof:name":"Karl Gabrys",
    "wof:placetype":"venue"
},
  "geometry": {"coordinates":[6.9712052345,51.4613876343],"type":"Point"}
}