{
  "type": "Feature",
  "properties": {
    "iso:country":"DE",
    "sg:address":"Euelsbruchstr. 3",
    "sg:city":"Freudenberg",
    "sg:phone":"+49 2734/7295",
    "sg:postcode":"57258",
    "sg:province":"Nordrhein-Westfalen",
    "wof:name":"Paul-gerh. Beckmann",
    "wof:placetype":"venue"
},
  "geometry": {"coordinates":[7.869405,50.897434],"type":"Point"}
}