{
  "type": "Feature",
  "properties": {
    "iso:country":"DE",
    "sg:address":"Mariahilfer Str. 36",
    "sg:city":"Eisenberg",
    "sg:phone":"+49 8364/276",
    "sg:postcode":"87637",
    "sg:province":"Bayern",
    "wof:name":"Hotel-pension Freyberg",
    "wof:placetype":"venue"
},
  "geometry": {"coordinates":[10.6124010086,47.6131782532],"type":"Point"}
}