{
  "type": "Feature",
  "properties": {
    "iso:country":"DE",
    "sg:address":"Ellerstr. 50",
    "sg:city":"Bonn",
    "sg:phone":"+49 4922/8982020",
    "sg:postcode":"53119",
    "sg:province":"Nordrhein-Westfalen",
    "wof:name":"Tpg Treuhand Dr. Niederhoff Ortheil Zuttermeister & Partner",
    "wof:placetype":"venue"
},
  "geometry": {"coordinates":[7.083405,50.739075],"type":"Point"}
}