{
  "type": "Feature",
  "properties": {
    "iso:country":"DE",
    "sg:address":"H\u00f6felbeetstr. 4",
    "sg:city":"Heidenheim",
    "sg:phone":"+49 9833/613",
    "sg:postcode":"91719",
    "sg:province":"Bayern",
    "wof:name":"Emil Meyer",
    "wof:placetype":"venue"
},
  "geometry": {"coordinates":[10.7415781021,49.0126075745],"type":"Point"}
}