{
  "type": "Feature",
  "properties": {
    "iso:country":"DE",
    "sg:address":"Breiter Weg 52",
    "sg:city":"Gerwisch",
    "sg:phone":"+49 39292/27208",
    "sg:postcode":"39175",
    "sg:province":"Sachsen-Anhalt",
    "wof:name":"Edelgard K\u00fchntopp",
    "wof:placetype":"venue"
},
  "geometry": {"coordinates":[11.745775,52.172413],"type":"Point"}
}