{
  "type": "Feature",
  "properties": {
    "iso:country":"DE",
    "sg:address":"Paulistr. 9",
    "sg:city":"Alfeld",
    "sg:phone":"+49 5181/1437",
    "sg:postcode":"31061",
    "sg:province":"Niedersachsen",
    "wof:name":"Klaus Reuter E. K.",
    "wof:placetype":"venue"
},
  "geometry": {"coordinates":[9.8253316879,51.9848022461],"type":"Point"}
}