{
  "type": "Feature",
  "properties": {
    "iso:country":"DE",
    "sg:address":"M\u00fchlenweg 1",
    "sg:city":"Bollschweil",
    "sg:phone":"+49 7633/808722",
    "sg:postcode":"79283",
    "sg:province":"Baden-W\u00fcrttemberg",
    "wof:name":"Carl L. Krebs Rechtsanwalt",
    "wof:placetype":"venue"
},
  "geometry": {"coordinates":[7.7792448997,47.9199447632],"type":"Point"}
}