{
  "type": "Feature",
  "properties": {
    "iso:country":"DE",
    "sg:address":"Hauptstr. 92",
    "sg:city":"Siegen",
    "sg:phone":"+49 271/64261",
    "sg:postcode":"57074",
    "sg:province":"Nordrhein-Westfalen",
    "wof:name":"K.-h. Erich",
    "wof:placetype":"venue"
},
  "geometry": {"coordinates":[8.057921,50.871052],"type":"Point"}
}