{
  "type": "Feature",
  "properties": {
    "iso:country":"DE",
    "sg:address":"Gro\u00df-Umst\u00e4dter Str. 20",
    "sg:city":"Gro\u00df-Umstadt",
    "sg:phone":"+49 6078/6148",
    "sg:postcode":"64823",
    "sg:province":"Hessen",
    "wof:name":"Thomas Eidmann",
    "wof:placetype":"venue"
},
  "geometry": {"coordinates":[8.888126,49.874641],"type":"Point"}
}