{
  "type": "Feature",
  "properties": {
    "iso:country":"DE",
    "sg:address":"Gladiolenweg 15a",
    "sg:city":"Bad Lippspringe",
    "sg:phone":"+49 5252/53843",
    "sg:postcode":"33175",
    "sg:province":"Nordrhein-Westfalen",
    "wof:name":"Guido Kleinemeyer",
    "wof:placetype":"venue"
},
  "geometry": {"coordinates":[8.8094520569,51.7736053467],"type":"Point"}
}