{
  "type": "Feature",
  "properties": {
    "iso:country":"DE",
    "sg:address":"Molkereistr 5-7",
    "sg:city":"G\u00fctersloh",
    "sg:phone":"+49 5241/28028",
    "sg:postcode":"33332",
    "sg:province":"Nordrhein-Westfalen",
    "wof:name":"G\u00fctersloher Gew\u00fcrzm\u00fchle Gmbh",
    "wof:placetype":"venue"
},
  "geometry": {"coordinates":[8.3881320953,51.9043579102],"type":"Point"}
}