{
  "type": "Feature",
  "properties": {
    "iso:country":"DE",
    "sg:address":"Zum Frankenbrunnen 1",
    "sg:city":"Bexbach",
    "sg:phone":"+49 6826/800004",
    "sg:postcode":"66450",
    "sg:province":"Saarland",
    "wof:name":"Excalor Hitzeschutz Gmbh",
    "wof:placetype":"venue"
},
  "geometry": {"coordinates":[7.252139,49.380211],"type":"Point"}
}