{
  "type": "Feature",
  "properties": {
    "iso:country":"DE",
    "sg:address":"Steinsmark 1",
    "sg:city":"Meinerzhagen",
    "sg:phone":"+49 2354/3290",
    "sg:postcode":"58540",
    "sg:province":"Nordrhein-Westfalen",
    "wof:name":"Pot Au Feu Inh. C. Stahlhacke",
    "wof:placetype":"venue"
},
  "geometry": {"coordinates":[7.6052908897,51.1002426147],"type":"Point"}
}