{
  "type": "Feature",
  "properties": {
    "iso:country":"DE",
    "sg:address":"Beckumer Str. 2",
    "sg:city":"Welver",
    "sg:phone":"+49 2384/3875",
    "sg:postcode":"59514",
    "sg:province":"Nordrhein-Westfalen",
    "wof:name":"Burghard Bredschneider",
    "wof:placetype":"venue"
},
  "geometry": {"coordinates":[7.966446,51.622662],"type":"Point"}
}