{
  "type": "Feature",
  "properties": {
    "iso:country":"DE",
    "sg:address":"Markt 26",
    "sg:city":"Grimma",
    "sg:phone":"+49 3437/919927",
    "sg:postcode":"04668",
    "sg:province":"Sachsen",
    "wof:name":"Sylvia Weber",
    "wof:placetype":"venue"
},
  "geometry": {"coordinates":[12.729484,51.236206],"type":"Point"}
}