{
  "type": "Feature",
  "properties": {
    "iso:country":"DE",
    "sg:address":"Heddostr. 4",
    "sg:city":"Wilhelmshaven",
    "sg:phone":"+49 4423/2985",
    "sg:postcode":"26388",
    "sg:province":"Niedersachsen",
    "wof:name":"Adolf Tiarks",
    "wof:placetype":"venue"
},
  "geometry": {"coordinates":[8.043847,53.591503],"type":"Point"}
}