{
  "type": "Feature",
  "properties": {
    "iso:country":"DE",
    "sg:address":"Luisenstra\u00dfe 3-5",
    "sg:city":"Bendorf/Rhein",
    "sg:phone":"+49 2622",
    "sg:postcode":"56170",
    "sg:province":"Rheinland-Pfalz",
    "wof:name":"Bomm Gmbh, 56155 Bendorf/rhein",
    "wof:placetype":"venue"
},
  "geometry": {"coordinates":[7.575643,50.423168],"type":"Point"}
}