{
  "type": "Feature",
  "properties": {
    "iso:country":"DE",
    "sg:address":"Heidestr. 15",
    "sg:city":"Schopsdorf",
    "sg:postcode":"39291",
    "sg:province":"Sachsen-Anhalt",
    "wof:name":"Concept Bau-fl\u00e4ming Fiener Gmbh",
    "wof:placetype":"venue"
},
  "geometry": {"coordinates":[12.2469434738,52.2460746765],"type":"Point"}
}