{
  "type": "Feature",
  "properties": {
    "iso:country":"DE",
    "sg:address":"Bahnhofstr. 1",
    "sg:city":"Wolfenb\u00fcttel",
    "sg:phone":"+49 5331/92180",
    "sg:postcode":"38300",
    "sg:province":"Niedersachsen",
    "wof:name":"Bahnhof-apotheke Dr. Ortwin Hantelmann",
    "wof:placetype":"venue"
},
  "geometry": {"coordinates":[10.534006,52.160316],"type":"Point"}
}