{
  "type": "Feature",
  "properties": {
    "iso:country":"DE",
    "sg:address":"Wei\u00dfenburger Str. 2",
    "sg:city":"Landau",
    "sg:phone":"+49 6341/92260",
    "sg:postcode":"76829",
    "sg:province":"Rheinland-Pfalz",
    "wof:name":"Bestattungsinstitut Reber Gmbh",
    "wof:placetype":"venue"
},
  "geometry": {"coordinates":[8.112881,49.192108],"type":"Point"}
}