{
  "type": "Feature",
  "properties": {
    "iso:country":"DE",
    "sg:address":"Schwarzwaldstra\u00dfe 181",
    "sg:city":"Freiburg",
    "sg:postcode":"79117",
    "sg:province":"Baden-W\u00fcrttemberg",
    "wof:name":"Freiburger Turnerschaft 1844 Freiburg",
    "wof:placetype":"venue"
},
  "geometry": {"coordinates":[7.8992500305,47.9877281189],"type":"Point"}
}