{
  "type": "Feature",
  "properties": {
    "iso:country":"DE",
    "sg:address":"Brockzeteler Str. 41",
    "sg:city":"Aurich",
    "sg:phone":"+49 4948/500",
    "sg:postcode":"26605",
    "sg:province":"Niedersachsen",
    "wof:name":"Frerich Post",
    "wof:placetype":"venue"
},
  "geometry": {"coordinates":[7.675898,53.500286],"type":"Point"}
}