{
  "type": "Feature",
  "properties": {
    "iso:country":"DE",
    "sg:address":"Schlo\u00dfstr. 49",
    "sg:city":"Berlin",
    "sg:phone":"+49 30/6211125",
    "sg:postcode":"12165",
    "sg:province":"Berlin",
    "wof:name":"Docupress Sachbuchverlag Produktions- Und Vertriebs",
    "wof:placetype":"venue"
},
  "geometry": {"coordinates":[13.3172826767,52.4541664124],"type":"Point"}
}