{
  "type": "Feature",
  "properties": {
    "iso:country":"DE",
    "sg:address":"Riedweg 4",
    "sg:city":"Hasbergen",
    "sg:postcode":"49205",
    "sg:province":"Niedersachsen",
    "wof:name":"Planungsb\u00fcro Stephan Bolduan Gmbh",
    "wof:placetype":"venue"
},
  "geometry": {"coordinates":[7.9694547653,52.2372512817],"type":"Point"}
}