{
  "type": "Feature",
  "properties": {
    "iso:country":"DE",
    "sg:address":"\u00dcbacher Weg 160",
    "sg:city":"Alsdorf",
    "sg:phone":"+49 2404/22218",
    "sg:postcode":"52477",
    "sg:province":"Nordrhein-Westfalen",
    "wof:name":"Horst Vieting Schilder Stempel",
    "wof:placetype":"venue"
},
  "geometry": {"coordinates":[6.15594,50.879921],"type":"Point"}
}