{
  "type": "Feature",
  "properties": {
    "iso:country":"DE",
    "sg:address":"Chausseestr. 11",
    "sg:city":"Berlin",
    "sg:phone":"+49 30/2828806",
    "sg:postcode":"10115",
    "sg:province":"Berlin",
    "wof:name":"Dr. Med. Brigitte Schiffner",
    "wof:placetype":"venue"
},
  "geometry": {"coordinates":[13.385836,52.528606],"type":"Point"}
}