{
  "type": "Feature",
  "properties": {
    "iso:country":"DE",
    "sg:address":"Im Teich 10",
    "sg:city":"Kirkel",
    "sg:phone":"+49 6841/81172",
    "sg:postcode":"66459",
    "sg:province":"Saarland",
    "wof:name":"Beatrix-blumen Kempf & Slot Gmbh",
    "wof:placetype":"venue"
},
  "geometry": {"coordinates":[7.289698,49.30645],"type":"Point"}
}