{
  "type": "Feature",
  "properties": {
    "iso:country":"DE",
    "sg:address":"Offenburger Str. 22",
    "sg:city":"Lahr",
    "sg:phone":"+49 7821/41395",
    "sg:postcode":"77933",
    "sg:province":"Baden-W\u00fcrttemberg",
    "wof:name":"Manfred Rosskopf",
    "wof:placetype":"venue"
},
  "geometry": {"coordinates":[7.842456,48.345039],"type":"Point"}
}