{
  "type": "Feature",
  "properties": {
    "iso:country":"DE",
    "sg:address":"Inselstr. 6",
    "sg:city":"Bremerhaven",
    "sg:phone":"+49 471/49076",
    "sg:postcode":"27568",
    "sg:province":"Bremen",
    "wof:name":"Maritimer Denkmalschutz F\u00f6rderverein E.v.",
    "wof:placetype":"venue"
},
  "geometry": {"coordinates":[8.5605096817,53.5560760498],"type":"Point"}
}