{
  "type": "Feature",
  "properties": {
    "iso:country":"DE",
    "sg:address":"Friedrich-Ebert-Str. 15",
    "sg:city":"Erlensee",
    "sg:phone":"+49 6183/2295",
    "sg:postcode":"63526",
    "sg:province":"Hessen",
    "wof:name":"E. Erben Piee Ohg",
    "wof:placetype":"venue"
},
  "geometry": {"coordinates":[8.9810171127,50.1691360474],"type":"Point"}
}