{
  "type": "Feature",
  "properties": {
    "iso:country":"DE",
    "sg:address":"Farrenpointstr. 26 A",
    "sg:city":"Kolbermoor",
    "sg:phone":"+49 8031/96880",
    "sg:postcode":"83059",
    "sg:province":"Bayern",
    "wof:name":"J\u00fcrgen K\u00fcppers Ingenieur",
    "wof:placetype":"venue"
},
  "geometry": {"coordinates":[12.0550069809,47.8459472656],"type":"Point"}
}