{
  "type": "Feature",
  "properties": {
    "iso:country":"DE",
    "sg:address":"Haselranken 12",
    "sg:city":"Waldthurn",
    "sg:phone":"+49 9657/261",
    "sg:postcode":"92727",
    "sg:province":"Bayern",
    "wof:name":"Josef Riedl",
    "wof:placetype":"venue"
},
  "geometry": {"coordinates":[12.3249454498,49.6754188538],"type":"Point"}
}