{
  "type": "Feature",
  "properties": {
    "iso:country":"DE",
    "sg:address":"Heilbronner Str. 19",
    "sg:city":"Neckarsulm",
    "sg:phone":"+49 7132/7611",
    "sg:postcode":"74172",
    "sg:province":"Baden-W\u00fcrttemberg",
    "wof:name":"Rainer Frisch",
    "wof:placetype":"venue"
},
  "geometry": {"coordinates":[9.224417,49.188511],"type":"Point"}
}