{
  "type": "Feature",
  "properties": {
    "iso:country":"DE",
    "sg:address":"Cecilienallee 6",
    "sg:city":"D\u00fcsseldorf",
    "sg:postcode":"40474",
    "sg:province":"Nordrhein-Westfalen",
    "wof:name":"Milliken Germany Gmbh",
    "wof:placetype":"venue"
},
  "geometry": {"coordinates":[6.771558,51.240227],"type":"Point"}
}