{
  "type": "Feature",
  "properties": {
    "iso:country":"DE",
    "sg:address":"Obere Kreienbrede 31",
    "sg:city":"Herford",
    "sg:phone":"+49 5221/53353",
    "sg:postcode":"32051",
    "sg:province":"Nordrhein-Westfalen",
    "wof:name":"Positiv Gmbh",
    "wof:placetype":"venue"
},
  "geometry": {"coordinates":[8.6446561813,52.1211585999],"type":"Point"}
}