{
  "type": "Feature",
  "properties": {
    "iso:country":"DE",
    "sg:address":"Pockelsstr. 4",
    "sg:city":"Braunschweig",
    "sg:postcode":"38106",
    "sg:province":"Niedersachsen",
    "wof:name":"Lehrstuhl F\u00fcr Theoretische Chemie",
    "wof:placetype":"venue"
},
  "geometry": {"coordinates":[10.5286273956,52.2734565735],"type":"Point"}
}