{
  "type": "Feature",
  "properties": {
    "iso:country":"DE",
    "sg:address":"Am M\u00fchlgraben 5",
    "sg:city":"Neu-Anspach",
    "sg:phone":"+49 6081/68557",
    "sg:postcode":"61267",
    "sg:province":"Hessen",
    "wof:name":"Sst Sch\u00fcttgut Systemtechnik Gmbh",
    "wof:placetype":"venue"
},
  "geometry": {"coordinates":[8.523730278,50.3096313477],"type":"Point"}
}