{
  "type": "Feature",
  "properties": {
    "iso:country":"DE",
    "sg:address":"Tegernseer Str. 146",
    "sg:city":"Hausham",
    "sg:phone":"+49 8026/5782",
    "sg:postcode":"83734",
    "sg:province":"Bayern",
    "wof:name":"Emil Wimmer Elektroinstallation",
    "wof:placetype":"venue"
},
  "geometry": {"coordinates":[11.82129,47.753933],"type":"Point"}
}