{
  "type": "Feature",
  "properties": {
    "iso:country":"DE",
    "sg:address":"Otto-Brenner-Str. 247",
    "sg:city":"Bielefeld",
    "sg:phone":"+49 521/1450301",
    "sg:postcode":"33604",
    "sg:province":"Nordrhein-Westfalen",
    "wof:name":"Telelogic Gmbh",
    "wof:placetype":"venue"
},
  "geometry": {"coordinates":[8.5598602295,52.0053405762],"type":"Point"}
}