{
  "type": "Feature",
  "properties": {
    "iso:country":"DE",
    "sg:address":"Hegelstr. 30",
    "sg:city":"Magdeburg",
    "sg:phone":"+49 391/5616639",
    "sg:postcode":"39104",
    "sg:province":"Sachsen-Anhalt",
    "wof:name":"Upmann & Partner",
    "wof:placetype":"venue"
},
  "geometry": {"coordinates":[11.6304988861,52.1193885803],"type":"Point"}
}