{
  "type": "Feature",
  "properties": {
    "iso:country":"DE",
    "sg:address":"Heidelbergstr. 10",
    "sg:city":"Herleshausen",
    "sg:phone":"+49 5654/92026",
    "sg:postcode":"37293",
    "sg:province":"Hessen",
    "wof:name":"J. Und W. Ries Verwaltungs- Und Beteiligungs Gmbh",
    "wof:placetype":"venue"
},
  "geometry": {"coordinates":[10.1312503815,51.0515785217],"type":"Point"}
}