{
  "type": "Feature",
  "properties": {
    "iso:country":"DE",
    "sg:address":"Marienstr. 24",
    "sg:city":"Kellinghusen",
    "sg:phone":"+49 4822/6580",
    "sg:postcode":"25548",
    "sg:province":"Schleswig-Holstein",
    "wof:name":"Peter Vollstedt",
    "wof:placetype":"venue"
},
  "geometry": {"coordinates":[9.732228,53.944901],"type":"Point"}
}