{
  "type": "Feature",
  "properties": {
    "iso:country":"DE",
    "sg:address":"Stadtbadstr. 39",
    "sg:city":"Ro\u00dfwein",
    "sg:phone":"+49 34322/5120",
    "sg:postcode":"04741",
    "sg:province":"Sachsen",
    "wof:name":"Ofm Abwasserentsorgung Gmbh",
    "wof:placetype":"venue"
},
  "geometry": {"coordinates":[13.1777496338,51.0636291504],"type":"Point"}
}