{
  "type": "Feature",
  "properties": {
    "iso:country":"DE",
    "sg:address":"Blankenheimer Str. 2-4",
    "sg:city":"Schleiden",
    "sg:phone":"+49 2445/89166",
    "sg:postcode":"53937",
    "sg:province":"Nordrhein-Westfalen",
    "wof:name":"Stadtb\u00fccherei",
    "wof:placetype":"venue"
},
  "geometry": {"coordinates":[6.481353,50.528942],"type":"Point"}
}