{
  "type": "Feature",
  "properties": {
    "iso:country":"DE",
    "sg:address":"Ohmstr. 3",
    "sg:city":"M\u00fcnchen",
    "sg:phone":"+49 89/390929",
    "sg:postcode":"80802",
    "sg:province":"Bayern",
    "wof:name":"Helmut Br\u00fcnner Rechtsanwalt",
    "wof:placetype":"venue"
},
  "geometry": {"coordinates":[11.5839729309,48.1542778015],"type":"Point"}
}