{
  "type": "Feature",
  "properties": {
    "iso:country":"DE",
    "sg:address":"Lintorfer Str. 10",
    "sg:city":"Ratingen",
    "sg:phone":"+49 2102/42370",
    "sg:postcode":"40878",
    "sg:province":"Nordrhein-Westfalen",
    "wof:name":"Fitzner Und M\u00fcnch Patent- Und Rechtsanw\u00e4lte",
    "wof:placetype":"venue"
},
  "geometry": {"coordinates":[6.8482952118,51.2980766296],"type":"Point"}
}