{
  "type": "Feature",
  "properties": {
    "iso:country":"DE",
    "sg:address":"Auf dem Rade 4",
    "sg:city":"Seelze",
    "sg:phone":"+49 5137/92209",
    "sg:postcode":"30926",
    "sg:province":"Niedersachsen",
    "wof:name":"Niermann Gmbh",
    "wof:placetype":"venue"
},
  "geometry": {"coordinates":[9.540957,52.360931],"type":"Point"}
}