{
  "type": "Feature",
  "properties": {
    "iso:country":"DE",
    "sg:address":"Mauerstr. 1-3",
    "sg:city":"Michelstadt",
    "sg:phone":"+49 4922/4284004",
    "sg:postcode":"64720",
    "sg:province":"Hessen",
    "wof:name":"Hausbrennerei Margaretenhof",
    "wof:placetype":"venue"
},
  "geometry": {"coordinates":[7.278073,50.781815],"type":"Point"}
}