{
  "type": "Feature",
  "properties": {
    "iso:country":"DE",
    "sg:address":"Bergstr. 6",
    "sg:city":"D\u00f6hlau",
    "sg:phone":"+49 9281/45738",
    "sg:postcode":"95182",
    "sg:province":"Bayern",
    "wof:name":"A. Und M. Gradl",
    "wof:placetype":"venue"
},
  "geometry": {"coordinates":[11.946535,50.276749],"type":"Point"}
}