{
  "type": "Feature",
  "properties": {
    "iso:country":"DE",
    "sg:address":"Johannes-G\u00f6deritz-Str. 124",
    "sg:city":"Magdeburg",
    "sg:phone":"+49 391/7225126",
    "sg:postcode":"39130",
    "sg:province":"Sachsen-Anhalt",
    "wof:name":"Dr. Med. Christa Weien \u00c4rztin F\u00fcr Augenheilkunde",
    "wof:placetype":"venue"
},
  "geometry": {"coordinates":[11.5877761841,52.1512985229],"type":"Point"}
}