{
  "type": "Feature",
  "properties": {
    "iso:country":"DE",
    "sg:address":"Leipziger Str. 25",
    "sg:city":"Torgau",
    "sg:phone":"+49 3421/712680",
    "sg:postcode":"04860",
    "sg:province":"Sachsen",
    "wof:name":"Sale & Success",
    "wof:placetype":"venue"
},
  "geometry": {"coordinates":[13.0005960464,51.5571365356],"type":"Point"}
}