{
  "type": "Feature",
  "properties": {
    "iso:country":"DE",
    "sg:address":"Rheinbabenstr. 66",
    "sg:city":"Krefeld",
    "sg:phone":"+49 2151/570296",
    "sg:postcode":"47809",
    "sg:province":"Nordrhein-Westfalen",
    "wof:name":"Adi Durst",
    "wof:placetype":"venue"
},
  "geometry": {"coordinates":[6.634342,51.335056],"type":"Point"}
}