{
  "type": "Feature",
  "properties": {
    "iso:country":"DE",
    "sg:address":"Kunstm\u00fchlestr. 43",
    "sg:city":"Pfullingen",
    "sg:phone":"+49 7121/99140",
    "sg:postcode":"72793",
    "sg:province":"Baden-W\u00fcrttemberg",
    "wof:name":"Klass & Gessmann Gmbh",
    "wof:placetype":"venue"
},
  "geometry": {"coordinates":[9.2230100632,48.4725799561],"type":"Point"}
}