{
  "type": "Feature",
  "properties": {
    "iso:country":"DE",
    "sg:address":"Pankerstr. 4",
    "sg:city":"L\u00fctjenburg",
    "sg:phone":"+49 4381/418125",
    "sg:postcode":"24321",
    "sg:province":"Schleswig-Holstein",
    "wof:name":"J\u00f6rg Dohrmann",
    "wof:placetype":"venue"
},
  "geometry": {"coordinates":[10.588603,54.294952],"type":"Point"}
}