{
  "type": "Feature",
  "properties": {
    "iso:country":"DE",
    "sg:address":"Kirchstr. 26",
    "sg:city":"Lorch",
    "sg:phone":"+49 7172/21632",
    "sg:postcode":"73547",
    "sg:province":"Baden-W\u00fcrttemberg",
    "wof:name":"Gabriele Weiler Heilpraktikerin",
    "wof:placetype":"venue"
},
  "geometry": {"coordinates":[9.6881580353,48.7989616394],"type":"Point"}
}