{
  "type": "Feature",
  "properties": {
    "iso:country":"DE",
    "sg:address":"Lange Str. 33",
    "sg:city":"Oebisfelde",
    "sg:phone":"+49 39002/42277",
    "sg:postcode":"39646",
    "sg:province":"Sachsen-Anhalt",
    "wof:name":"H. U. H. Schulz",
    "wof:placetype":"venue"
},
  "geometry": {"coordinates":[10.985162,52.42535],"type":"Point"}
}