{
  "type": "Feature",
  "properties": {
    "iso:country":"DE",
    "sg:address":"Kirchstr. 61",
    "sg:city":"N\u00fcrtingen",
    "sg:phone":"+49 7022/34170",
    "sg:postcode":"72622",
    "sg:province":"Baden-W\u00fcrttemberg",
    "wof:name":"Sieben-schwaben-reiseb\u00fcro Gmbh",
    "wof:placetype":"venue"
},
  "geometry": {"coordinates":[9.3419303894,48.6261291504],"type":"Point"}
}