{
  "type": "Feature",
  "properties": {
    "iso:country":"DE",
    "sg:address":"Crawinkler Str. 10",
    "sg:city":"Oberhof",
    "sg:phone":"+49 36842/22346",
    "sg:postcode":"98559",
    "sg:province":"Th\u00fcringen",
    "wof:name":"Haus Vergi\u00dfmeinnicht",
    "wof:placetype":"venue"
},
  "geometry": {"coordinates":[10.7245941162,50.7081298828],"type":"Point"}
}