{
  "type": "Feature",
  "properties": {
    "iso:country":"DE",
    "sg:address":"Boschstr. 1",
    "sg:city":"Isernhagen",
    "sg:phone":"+49 511/612344",
    "sg:postcode":"30916",
    "sg:province":"Niedersachsen",
    "wof:name":"Gerwin Bleich",
    "wof:placetype":"venue"
},
  "geometry": {"coordinates":[9.8335151672,52.4289665222],"type":"Point"}
}