{
  "type": "Feature",
  "properties": {
    "iso:country":"DE",
    "sg:address":"Bahnweg 3",
    "sg:city":"Goch",
    "sg:phone":"+49 2823/18668",
    "sg:postcode":"47574",
    "sg:province":"Nordrhein-Westfalen",
    "wof:name":"Heinz Gossens",
    "wof:placetype":"venue"
},
  "geometry": {"coordinates":[6.11121,51.68911],"type":"Point"}
}