{
  "type": "Feature",
  "properties": {
    "iso:country":"DE",
    "sg:address":"Vordersteig 14",
    "sg:city":"Ettlingen",
    "sg:phone":"+49 7243/13614",
    "sg:postcode":"76275",
    "sg:province":"Baden-W\u00fcrttemberg",
    "wof:name":"G\u00fcnter Mader Architekt",
    "wof:placetype":"venue"
},
  "geometry": {"coordinates":[8.41598,48.943722],"type":"Point"}
}