{
  "type": "Feature",
  "properties": {
    "iso:country":"DE",
    "sg:address":"Lengmooser Str. 15",
    "sg:city":"Gars",
    "sg:phone":"+49 8073/663",
    "sg:postcode":"83536",
    "sg:province":"Bayern",
    "wof:name":"Maria Groeger Hebamme",
    "wof:placetype":"venue"
},
  "geometry": {"coordinates":[12.271891,48.154026],"type":"Point"}
}