{
  "type": "Feature",
  "properties": {
    "iso:country":"DE",
    "sg:address":"Hochbaumstr. 48",
    "sg:city":"Berlin",
    "sg:phone":"+49 30/7909850",
    "sg:postcode":"14167",
    "sg:province":"Berlin",
    "wof:name":"Dr. H. Joachim Steinig Ingenieur",
    "wof:placetype":"venue"
},
  "geometry": {"coordinates":[13.2820138931,52.4296379089],"type":"Point"}
}