{
  "type": "Feature",
  "properties": {
    "iso:country":"DE",
    "sg:address":"Saarbr\u00fccker Str. 115",
    "sg:city":"Bous",
    "sg:phone":"+49 6834/3710",
    "sg:postcode":"66359",
    "sg:province":"Saarland",
    "wof:name":"Ruhland-kallenborn & Co. Mbh",
    "wof:placetype":"venue"
},
  "geometry": {"coordinates":[6.791858,49.277519],"type":"Point"}
}