{
  "type": "Feature",
  "properties": {
    "iso:country":"DE",
    "sg:address":"Marktstr. 31",
    "sg:city":"Backnang",
    "sg:phone":"+49 7191/83396",
    "sg:postcode":"71522",
    "sg:province":"Baden-W\u00fcrttemberg",
    "wof:name":"Landsiedlung Baden-w\u00fcrttemberg Gmbh",
    "wof:placetype":"venue"
},
  "geometry": {"coordinates":[9.4305124283,48.9466362],"type":"Point"}
}