{
  "type": "Feature",
  "properties": {
    "iso:country":"DE",
    "sg:address":"Bahnhofstr. 17",
    "sg:city":"Immenstadt",
    "sg:phone":"+49 8323/8244",
    "sg:postcode":"87509",
    "sg:province":"Bayern",
    "wof:name":"S. Steiner",
    "wof:placetype":"venue"
},
  "geometry": {"coordinates":[10.217258,47.559589],"type":"Point"}
}