{
  "type": "Feature",
  "properties": {
    "iso:country":"DE",
    "sg:address":"Schillerstr. 12",
    "sg:city":"St. Ingbert",
    "sg:phone":"+49 6894/5512",
    "sg:postcode":"66386",
    "sg:province":"Saarland",
    "wof:name":"A. Schr\u00f6der",
    "wof:placetype":"venue"
},
  "geometry": {"coordinates":[7.1637840271,49.2681350708],"type":"Point"}
}