{
  "type": "Feature",
  "properties": {
    "iso:country":"DE",
    "sg:address":"Weierweg 2",
    "sg:city":"Oberkirch",
    "sg:phone":"+49 7802/50440",
    "sg:postcode":"77704",
    "sg:province":"Baden-W\u00fcrttemberg",
    "wof:name":"Daniela L\u00f6bsack Masseur",
    "wof:placetype":"venue"
},
  "geometry": {"coordinates":[8.080001,48.531727],"type":"Point"}
}