{
  "type": "Feature",
  "properties": {
    "iso:country":"DE",
    "sg:address":"Rehbacher Str. 57",
    "sg:city":"Leipzig",
    "sg:phone":"+49 341/4283541",
    "sg:postcode":"04249",
    "sg:province":"Sachsen",
    "wof:name":"Rolf Spaeth",
    "wof:placetype":"venue"
},
  "geometry": {"coordinates":[12.304151,51.274048],"type":"Point"}
}