{
  "type": "Feature",
  "properties": {
    "iso:country":"DE",
    "sg:address":"Heidenschaftsweg 2",
    "sg:city":"Nieb\u00fcll",
    "sg:phone":"+49 4661/4708",
    "sg:postcode":"25899",
    "sg:province":"Schleswig-Holstein",
    "wof:name":"Reetdachdeckerei Hansen Inh. Hans Martin Hansen",
    "wof:placetype":"venue"
},
  "geometry": {"coordinates":[8.812606,54.771748],"type":"Point"}
}