{
  "type": "Feature",
  "properties": {
    "iso:country":"DE",
    "sg:address":"Eyachstr. 28",
    "sg:city":"Albstadt",
    "sg:phone":"+49 7435/1061",
    "sg:postcode":"72459",
    "sg:province":"Baden-W\u00fcrttemberg",
    "wof:name":"Jumberca Gmbh",
    "wof:placetype":"venue"
},
  "geometry": {"coordinates":[8.9272871017,48.2179107666],"type":"Point"}
}