{
  "type": "Feature",
  "properties": {
    "iso:country":"DE",
    "sg:address":"Wulfener Str. 25",
    "sg:city":"Dorsten",
    "sg:phone":"+49 2369/7138",
    "sg:postcode":"46286",
    "sg:province":"Nordrhein-Westfalen",
    "wof:name":"F.-j. Einhaus",
    "wof:placetype":"venue"
},
  "geometry": {"coordinates":[7.0000090599,51.7569198608],"type":"Point"}
}