{
  "type": "Feature",
  "properties": {
    "iso:country":"DE",
    "sg:address":"Untere Schrangenstr. 4",
    "sg:city":"L\u00fcneburg",
    "sg:phone":"+49 4131/43831",
    "sg:postcode":"21335",
    "sg:province":"Niedersachsen",
    "wof:name":"Stadtflorist Inh. Regine Beushausen",
    "wof:placetype":"venue"
},
  "geometry": {"coordinates":[10.407879,53.248119],"type":"Point"}
}