{
  "type": "Feature",
  "properties": {
    "iso:country":"DE",
    "sg:address":"Friedrich-Ebert-Str. 437-439",
    "sg:city":"Duisburg",
    "sg:phone":"+49 203/471169",
    "sg:postcode":"47178",
    "sg:province":"Nordrhein-Westfalen",
    "wof:name":"Blumen Hoeren Gmbh",
    "wof:placetype":"venue"
},
  "geometry": {"coordinates":[6.737073,51.540691],"type":"Point"}
}