{
  "type": "Feature",
  "properties": {
    "iso:country":"DE",
    "sg:address":"Ortenauer Str. 63",
    "sg:city":"Appenweier",
    "sg:phone":"+49 7805/3458",
    "sg:postcode":"77767",
    "sg:province":"Baden-W\u00fcrttemberg",
    "wof:name":"Badischer Hof",
    "wof:placetype":"venue"
},
  "geometry": {"coordinates":[7.9788389206,48.5413742065],"type":"Point"}
}