{
  "type": "Feature",
  "properties": {
    "iso:country":"DE",
    "sg:address":"Auf Tannerd 15",
    "sg:city":"Alf",
    "sg:phone":"+49 6542/21922",
    "sg:postcode":"56859",
    "sg:province":"Rheinland-Pfalz",
    "wof:name":"Werner Hutter Architekt",
    "wof:placetype":"venue"
},
  "geometry": {"coordinates":[7.125772,50.051289],"type":"Point"}
}