{
  "type": "Feature",
  "properties": {
    "iso:country":"DE",
    "sg:address":"Neue Str. 28",
    "sg:city":"Bremerv\u00f6rde",
    "sg:phone":"+49 4761/2215",
    "sg:postcode":"27432",
    "sg:province":"Niedersachsen",
    "wof:name":"G\u00fcnther Katt",
    "wof:placetype":"venue"
},
  "geometry": {"coordinates":[9.1468229294,53.4870414734],"type":"Point"}
}