{
  "type": "Feature",
  "properties": {
    "iso:country":"DE",
    "sg:address":"Hohenzollernstr. 8f",
    "sg:city":"Berlin",
    "sg:phone":"+49 30/8051754",
    "sg:postcode":"14109",
    "sg:province":"Berlin",
    "wof:name":"Kurt Behrendt Garten- Und",
    "wof:placetype":"venue"
},
  "geometry": {"coordinates":[13.151941,52.41589],"type":"Point"}
}