{
  "type": "Feature",
  "properties": {
    "iso:country":"DE",
    "sg:address":"Muskauer Platz 2",
    "sg:city":"Cottbus",
    "sg:phone":"+49 355/756030",
    "sg:postcode":"03042",
    "sg:province":"Brandenburg",
    "wof:name":"Architektur- Und Ingenieurb\u00fcro Otto-gorn-lehmann Und",
    "wof:placetype":"venue"
},
  "geometry": {"coordinates":[14.348561,51.76059],"type":"Point"}
}