{
  "type": "Feature",
  "properties": {
    "iso:country":"DE",
    "sg:address":"Am Halben Mond 20",
    "sg:city":"Wesel",
    "sg:phone":"+49 281/21522",
    "sg:postcode":"46483",
    "sg:province":"Nordrhein-Westfalen",
    "wof:name":"Dr. Gerhard Sehr Tierarzt",
    "wof:placetype":"venue"
},
  "geometry": {"coordinates":[6.6063580513,51.6573371887],"type":"Point"}
}