{
  "type": "Feature",
  "properties": {
    "iso:country":"DE",
    "sg:address":"Lemf\u00f6rder Str. 4",
    "sg:city":"Rahden",
    "sg:phone":"+49 5771/3033",
    "sg:postcode":"32369",
    "sg:province":"Nordrhein-Westfalen",
    "wof:name":"Auto-plate Autohandels- Gmbh",
    "wof:placetype":"venue"
},
  "geometry": {"coordinates":[8.610188,52.432858],"type":"Point"}
}