{
  "type": "Feature",
  "properties": {
    "iso:country":"DE",
    "sg:address":"Maastrichter Str 24",
    "sg:city":"K\u00f6ln",
    "sg:phone":"+49 221/527981",
    "sg:postcode":"50672",
    "sg:province":"Nordrhein-Westfalen",
    "wof:name":"Edmund Schaefer",
    "wof:placetype":"venue"
},
  "geometry": {"coordinates":[6.93681,50.938538],"type":"Point"}
}