{
  "type": "Feature",
  "properties": {
    "iso:country":"DE",
    "sg:address":"Rehwinkel 33",
    "sg:city":"Saarlouis",
    "sg:phone":"+49 6831/41987",
    "sg:postcode":"66740",
    "sg:province":"Saarland",
    "wof:name":"P. A. Wittig",
    "wof:placetype":"venue"
},
  "geometry": {"coordinates":[6.732373,49.294838],"type":"Point"}
}