{
  "type": "Feature",
  "properties": {
    "iso:country":"DE",
    "sg:address":"Goethestr. 21",
    "sg:city":"Burgau",
    "sg:phone":"+49 8222/2201",
    "sg:postcode":"89331",
    "sg:province":"Bayern",
    "wof:name":"B\u00fchler Gmbh",
    "wof:placetype":"venue"
},
  "geometry": {"coordinates":[10.4060554504,48.4243812561],"type":"Point"}
}