{
  "type": "Feature",
  "properties": {
    "iso:country":"DE",
    "sg:address":"Weidestr. 111b",
    "sg:city":"Hamburg",
    "sg:phone":"+49 40/225843",
    "sg:postcode":"22083",
    "sg:province":"Hamburg",
    "wof:name":"Fast-alles.com",
    "wof:placetype":"venue"
},
  "geometry": {"coordinates":[10.0260887146,53.5804977417],"type":"Point"}
}