{
  "type": "Feature",
  "properties": {
    "iso:country":"DE",
    "sg:address":"Ernst-Th\u00e4lmann-Str. 30",
    "sg:city":"N\u00fcnchritz",
    "sg:postcode":"01612",
    "sg:province":"Sachsen",
    "wof:name":"Gro\u00dfhandel-schreibwaren Und B\u00fcrobedarf",
    "wof:placetype":"venue"
},
  "geometry": {"coordinates":[13.393618,51.298454],"type":"Point"}
}