{
  "type": "Feature",
  "properties": {
    "iso:country":"DE",
    "sg:address":"Schultenallee 11",
    "sg:city":"S\u00fcdlohn",
    "sg:phone":"+49 2862/6319",
    "sg:postcode":"46354",
    "sg:province":"Nordrhein-Westfalen",
    "wof:name":"Willi H\u00f6ing",
    "wof:placetype":"venue"
},
  "geometry": {"coordinates":[6.811334,51.937363],"type":"Point"}
}