{
  "type": "Feature",
  "properties": {
    "iso:country":"DE",
    "sg:address":"Felixstowestr. 3",
    "sg:city":"Wesel",
    "sg:phone":"+49 281/56307",
    "sg:postcode":"46485",
    "sg:province":"Nordrhein-Westfalen",
    "wof:name":"Heinz Gilhaus",
    "wof:placetype":"venue"
},
  "geometry": {"coordinates":[6.647792,51.67498],"type":"Point"}
}