{
  "type": "Feature",
  "properties": {
    "iso:country":"DE",
    "sg:address":"Teplitzerstr. 22",
    "sg:city":"Waldkraiburg",
    "sg:phone":"+49 8638/60060",
    "sg:postcode":"84478",
    "sg:province":"Bayern",
    "wof:name":"Global-guss Gmbh",
    "wof:placetype":"venue"
},
  "geometry": {"coordinates":[12.415453,48.210587],"type":"Point"}
}