{
  "type": "Feature",
  "properties": {
    "iso:country":"DE",
    "sg:address":"Glei\u00dfentalstr. 15",
    "sg:city":"Deisenhofen",
    "sg:postcode":"82041",
    "sg:province":"Bayern",
    "wof:name":"Idl Industrievertretungen S.r.o. & Co. Kg",
    "wof:placetype":"venue"
},
  "geometry": {"coordinates":[11.589525,48.014179],"type":"Point"}
}