{
  "type": "Feature",
  "properties": {
    "iso:country":"DE",
    "sg:address":"Hohes Feld 46",
    "sg:city":"Hann. M\u00fcnden",
    "sg:phone":"+49 5541/4718",
    "sg:postcode":"34346",
    "sg:province":"Niedersachsen",
    "wof:name":"Zf Pr\u00fcftechnik Gmbh",
    "wof:placetype":"venue"
},
  "geometry": {"coordinates":[9.683674,51.416176],"type":"Point"}
}