{
  "type": "Feature",
  "properties": {
    "iso:country":"DE",
    "sg:address":"Neuensteden 37",
    "sg:city":"Freiburg",
    "sg:phone":"+49 4779/273",
    "sg:postcode":"21729",
    "sg:province":"Niedersachsen",
    "wof:name":"Hans-heinrich Tiedemann",
    "wof:placetype":"venue"
},
  "geometry": {"coordinates":[9.279567,53.824142],"type":"Point"}
}