{
  "type": "Feature",
  "properties": {
    "iso:country":"DE",
    "sg:address":"Nordend 2",
    "sg:city":"Hummelfeld",
    "sg:phone":"+49 4353/378",
    "sg:postcode":"24357",
    "sg:province":"Schleswig-Holstein",
    "wof:name":"Harald Gosch Landwirtschaftl. Lohnbetrieb",
    "wof:placetype":"venue"
},
  "geometry": {"coordinates":[9.718445,54.4622],"type":"Point"}
}