{
  "type": "Feature",
  "properties": {
    "iso:country":"DE",
    "sg:address":"Kandelblickstr. 1",
    "sg:city":"Freiburg",
    "sg:phone":"+49 7665/3379",
    "sg:postcode":"79108",
    "sg:province":"Baden-W\u00fcrttemberg",
    "wof:name":"Susanne Hellstab Krankengymnastik",
    "wof:placetype":"venue"
},
  "geometry": {"coordinates":[7.806957,48.048958],"type":"Point"}
}