{
  "type": "Feature",
  "properties": {
    "iso:country":"DE",
    "sg:address":"Hauptstr. 14",
    "sg:city":"Seck",
    "sg:postcode":"56479",
    "sg:province":"Rheinland-Pfalz",
    "wof:name":"Druckerei Tiago Da Silva",
    "wof:placetype":"venue"
},
  "geometry": {"coordinates":[8.04756,50.575287],"type":"Point"}
}