{
  "type": "Feature",
  "properties": {
    "iso:country":"DE",
    "sg:address":"Brandisstr. 8",
    "sg:city":"Merseburg",
    "sg:phone":"+49 3461/77130",
    "sg:postcode":"06217",
    "sg:province":"Sachsen-Anhalt",
    "wof:name":"Dachdecker-einkauf Mitteldeutschland Eg",
    "wof:placetype":"venue"
},
  "geometry": {"coordinates":[11.98477,51.376831],"type":"Point"}
}