{
  "type": "Feature",
  "properties": {
    "iso:country":"DE",
    "sg:address":"Felsenkeller 1a",
    "sg:city":"Feucht",
    "sg:postcode":"90537",
    "sg:province":"Bayern",
    "wof:name":"Innova Wohnungsbau Gmbh & Co. Kg",
    "wof:placetype":"venue"
},
  "geometry": {"coordinates":[11.205445,49.376251],"type":"Point"}
}