{
  "type": "Feature",
  "properties": {
    "iso:country":"DE",
    "sg:address":"Karl-Valentin-Str. 2",
    "sg:city":"Nandlstadt",
    "sg:phone":"+49 8756/388",
    "sg:postcode":"85405",
    "sg:province":"Bayern",
    "wof:name":"Sieglinde Bauer",
    "wof:placetype":"venue"
},
  "geometry": {"coordinates":[11.80949,48.531921],"type":"Point"}
}