{
  "type": "Feature",
  "properties": {
    "iso:country":"DE",
    "sg:address":"Bannenberg 3",
    "sg:city":"B\u00f6ttingen",
    "sg:phone":"+49 7429/91190",
    "sg:postcode":"78583",
    "sg:province":"Baden-W\u00fcrttemberg",
    "wof:name":"Georg Fehrenbach",
    "wof:placetype":"venue"
},
  "geometry": {"coordinates":[8.795064,48.099991],"type":"Point"}
}