{
  "type": "Feature",
  "properties": {
    "iso:country":"DE",
    "sg:address":"Hoetmarer Str. 53",
    "sg:city":"Warendorf",
    "sg:phone":"+49 2581/44527",
    "sg:postcode":"48231",
    "sg:province":"Nordrhein-Westfalen",
    "wof:name":"Hans Braun Drogerie",
    "wof:placetype":"venue"
},
  "geometry": {"coordinates":[7.961859,51.917267],"type":"Point"}
}