{
  "type": "Feature",
  "properties": {
    "iso:country":"DE",
    "sg:address":"Hellmannsberg 1",
    "sg:city":"Hellmannsberg",
    "sg:phone":"+49 8681/9330",
    "sg:postcode":"83329",
    "sg:province":"Bayern",
    "wof:name":"Ludwig Kain Gastst\u00e4tte Schweizerhof",
    "wof:placetype":"venue"
},
  "geometry": {"coordinates":[12.73250103,47.9033126831],"type":"Point"}
}