{
  "type": "Feature",
  "properties": {
    "iso:country":"DE",
    "sg:address":"Bliestalstr. 21",
    "sg:city":"Gersheim",
    "sg:phone":"+49 6843/265",
    "sg:postcode":"66453",
    "sg:province":"Saarland",
    "wof:name":"Ristorante Pizzeria Adria",
    "wof:placetype":"venue"
},
  "geometry": {"coordinates":[7.238093853,49.1742591858],"type":"Point"}
}