{
  "type": "Feature",
  "properties": {
    "iso:country":"DE",
    "sg:address":"Mainzer Landstr. 58",
    "sg:city":"H\u00fcnfelden",
    "sg:phone":"+49 6438/6373",
    "sg:postcode":"65597",
    "sg:province":"Hessen",
    "wof:name":"Heinz-j. Und Ursula St\u00f6rkel",
    "wof:placetype":"venue"
},
  "geometry": {"coordinates":[8.164642334,50.2962875366],"type":"Point"}
}