{
  "type": "Feature",
  "properties": {
    "iso:country":"DE",
    "sg:address":"Pelargonienweg 51",
    "sg:city":"M\u00fcnchen",
    "sg:phone":"+49 89/7194607",
    "sg:postcode":"81377",
    "sg:province":"Bayern",
    "wof:name":"Millennium Grundst\u00fccks Gmbh",
    "wof:placetype":"venue"
},
  "geometry": {"coordinates":[11.488555,48.105873],"type":"Point"}
}