{
  "type": "Feature",
  "properties": {
    "iso:country":"DE",
    "sg:address":"Drakenkamp 5",
    "sg:city":"Steinfurt",
    "sg:phone":"+49 2551/5888",
    "sg:postcode":"48565",
    "sg:province":"Nordrhein-Westfalen",
    "wof:name":"Fiege Gmbh",
    "wof:placetype":"venue"
},
  "geometry": {"coordinates":[7.319535,52.151382],"type":"Point"}
}