{
  "type": "Feature",
  "properties": {
    "iso:country":"DE",
    "sg:address":"Robert-Bosch-Str. 18",
    "sg:city":"Pfungstadt",
    "sg:phone":"+49 6157/80080",
    "sg:postcode":"64319",
    "sg:province":"Hessen",
    "wof:name":"Eltra Heizelemente Gmbh",
    "wof:placetype":"venue"
},
  "geometry": {"coordinates":[8.615695,49.816898],"type":"Point"}
}