{
  "type": "Feature",
  "properties": {
    "iso:country":"DE",
    "sg:address":"Adalbert-Stifter-Str. 34",
    "sg:city":"Albstadt",
    "sg:phone":"+49 7432/98010",
    "sg:postcode":"72461",
    "sg:province":"Baden-W\u00fcrttemberg",
    "wof:name":"Fauler",
    "wof:placetype":"venue"
},
  "geometry": {"coordinates":[9.0067539215,48.2422485352],"type":"Point"}
}