{
  "type": "Feature",
  "properties": {
    "iso:country":"DE",
    "sg:address":"Krahenh\u00f6her Weg 20",
    "sg:city":"Solingen",
    "sg:phone":"+49 212/44422",
    "sg:postcode":"42659",
    "sg:province":"Nordrhein-Westfalen",
    "wof:name":"Christa Saam Gmbh",
    "wof:placetype":"venue"
},
  "geometry": {"coordinates":[7.117621,51.161846],"type":"Point"}
}