{
  "type": "Feature",
  "properties": {
    "iso:country":"DE",
    "sg:address":"Lessingstr 79",
    "sg:city":"Berlin",
    "sg:phone":"+49 30/91770",
    "sg:postcode":"13158",
    "sg:province":"Berlin",
    "wof:name":"Abb Training Center Berlin Gmbh",
    "wof:placetype":"venue"
},
  "geometry": {"coordinates":[13.3591461182,52.5896263123],"type":"Point"}
}