{
  "type": "Feature",
  "properties": {
    "iso:country":"DE",
    "sg:address":"Jenfelder Str. 57 a",
    "sg:city":"Hamburg",
    "sg:phone":"+49 40/6696066",
    "sg:postcode":"22045",
    "sg:province":"Hamburg",
    "wof:name":"Heinz Blechschmidt",
    "wof:placetype":"venue"
},
  "geometry": {"coordinates":[10.113155365,53.5764427185],"type":"Point"}
}