{
  "type": "Feature",
  "properties": {
    "iso:country":"DE",
    "sg:address":"Claudius-Dornier-Str. 3",
    "sg:city":"K\u00f6ln",
    "sg:phone":"+49 221/9564440",
    "sg:postcode":"50829",
    "sg:province":"Nordrhein-Westfalen",
    "wof:name":"Hk Autoteile Gmbh",
    "wof:placetype":"venue"
},
  "geometry": {"coordinates":[6.887689,50.987274],"type":"Point"}
}