{
  "type": "Feature",
  "properties": {
    "iso:country":"DE",
    "sg:address":"Am Pestalozziring 24",
    "sg:city":"Erlangen",
    "sg:phone":"+49 9131/77000",
    "sg:postcode":"91058",
    "sg:province":"Bayern",
    "wof:name":"Ertec Gmbh",
    "wof:placetype":"venue"
},
  "geometry": {"coordinates":[10.996726,49.556305],"type":"Point"}
}