{
  "type": "Feature",
  "properties": {
    "iso:country":"DE",
    "sg:address":"Schlachterstr. 32",
    "sg:city":"Lingen",
    "sg:phone":"+49 591/59624",
    "sg:postcode":"49808",
    "sg:province":"Niedersachsen",
    "wof:name":"Gastst\u00e4tte Phileas Fogg",
    "wof:placetype":"venue"
},
  "geometry": {"coordinates":[7.3146939278,52.5226783752],"type":"Point"}
}