{
  "type": "Feature",
  "properties": {
    "iso:country":"DE",
    "sg:address":"Stockstr. 1",
    "sg:city":"Siegbach",
    "sg:phone":"+49 2778/527",
    "sg:postcode":"35768",
    "sg:province":"Hessen",
    "wof:name":"Weingastst\u00e4tte E. Illner",
    "wof:placetype":"venue"
},
  "geometry": {"coordinates":[8.418170929,50.7364692688],"type":"Point"}
}