{
  "type": "Feature",
  "properties": {
    "iso:country":"DE",
    "sg:address":"Schie\u00dfmauerstr. 8",
    "sg:city":"Stuttgart",
    "sg:phone":"+49 711/7189351",
    "sg:postcode":"70563",
    "sg:province":"Baden-W\u00fcrttemberg",
    "wof:name":"Edwin Hirsch",
    "wof:placetype":"venue"
},
  "geometry": {"coordinates":[9.1068572998,48.7346611023],"type":"Point"}
}