{
  "type": "Feature",
  "properties": {
    "iso:country":"DE",
    "sg:address":"Konitzkyweg 6a",
    "sg:city":"Bad Nauheim",
    "sg:phone":"+49 6032/921370",
    "sg:postcode":"61231",
    "sg:province":"Hessen",
    "wof:name":"Ett Europ Touristik Tours Gmbh",
    "wof:placetype":"venue"
},
  "geometry": {"coordinates":[8.7347288132,50.3569793701],"type":"Point"}
}