{
  "type": "Feature",
  "properties": {
    "iso:country":"DE",
    "sg:address":"Krippenberg 96",
    "sg:city":"Reinhardtsdorf",
    "sg:phone":"+49 35028/80959",
    "sg:postcode":"01814",
    "sg:province":"Sachsen",
    "wof:name":"Frank Fischer",
    "wof:placetype":"venue"
},
  "geometry": {"coordinates":[14.1884145737,50.895236969],"type":"Point"}
}