{
  "type": "Feature",
  "properties": {
    "iso:country":"DE",
    "sg:address":"Hauptstr. 6a",
    "sg:city":"Weiler",
    "sg:phone":"+49 6754/8029",
    "sg:postcode":"55627",
    "sg:province":"Rheinland-Pfalz",
    "wof:name":"Gartenpflege Fr\u00f6hlich",
    "wof:placetype":"venue"
},
  "geometry": {"coordinates":[7.560927,49.807819],"type":"Point"}
}