{
  "type": "Feature",
  "properties": {
    "iso:country":"DE",
    "sg:address":"Goethestr. 21",
    "sg:city":"Hirschberg",
    "sg:phone":"+49 6201/51545",
    "sg:postcode":"69493",
    "sg:province":"Baden-W\u00fcrttemberg",
    "wof:name":"Gerlinde Eger",
    "wof:placetype":"venue"
},
  "geometry": {"coordinates":[8.6593084335,49.4957580566],"type":"Point"}
}