{
  "type": "Feature",
  "properties": {
    "iso:country":"DE",
    "sg:address":"Weideweg 6",
    "sg:city":"Riedenburg",
    "sg:phone":"+49 9442/875",
    "sg:postcode":"93339",
    "sg:province":"Bayern",
    "wof:name":"W. Leixenring",
    "wof:placetype":"venue"
},
  "geometry": {"coordinates":[11.6276493073,48.9556045532],"type":"Point"}
}