{
  "type": "Feature",
  "properties": {
    "iso:country":"DE",
    "sg:address":"Nordwall 4",
    "sg:city":"Menden",
    "sg:phone":"+49 2373/3126",
    "sg:postcode":"58706",
    "sg:province":"Nordrhein-Westfalen",
    "wof:name":"Paul Traulich",
    "wof:placetype":"venue"
},
  "geometry": {"coordinates":[7.7946610451,51.4390602112],"type":"Point"}
}