{
  "type": "Feature",
  "properties": {
    "iso:country":"DE",
    "sg:address":"Wittenburger Str. 7",
    "sg:city":"M\u00f6lln",
    "sg:postcode":"23879",
    "sg:province":"Schleswig-Holstein",
    "wof:name":"Dieter Findeisen Garten- Und",
    "wof:placetype":"venue"
},
  "geometry": {"coordinates":[10.691331,53.610962],"type":"Point"}
}