{
  "type": "Feature",
  "properties": {
    "iso:country":"DE",
    "sg:address":"Schopshofer Weg 30",
    "sg:city":"Heiligenhaus",
    "sg:phone":"+49 2056/4978",
    "sg:postcode":"42579",
    "sg:province":"Nordrhein-Westfalen",
    "wof:name":"Manfred Takkenberg Maschinenvertriebs- Gmbh",
    "wof:placetype":"venue"
},
  "geometry": {"coordinates":[6.9489660263,51.3285293579],"type":"Point"}
}