{
  "type": "Feature",
  "properties": {
    "iso:country":"DE",
    "sg:address":"Unterer Markt 9",
    "sg:city":"Ibbenb\u00fcren",
    "sg:phone":"+49 5451/745460",
    "sg:postcode":"49477",
    "sg:province":"Nordrhein-Westfalen",
    "wof:name":"Anna Ledigs",
    "wof:placetype":"venue"
},
  "geometry": {"coordinates":[7.7157649994,52.272819519],"type":"Point"}
}