{
  "type": "Feature",
  "properties": {
    "iso:country":"DE",
    "sg:address":"Friedrichsorter Str. 22",
    "sg:city":"Kiel",
    "sg:phone":"+49 431/391038",
    "sg:postcode":"24159",
    "sg:province":"Schleswig-Holstein",
    "wof:name":"Ev. Pfarramt Pries",
    "wof:placetype":"venue"
},
  "geometry": {"coordinates":[10.1712779999,54.3976402283],"type":"Point"}
}