{
  "type": "Feature",
  "properties": {
    "iso:country":"DE",
    "sg:address":"Am Waldfriedhof 23",
    "sg:city":"Darmstadt",
    "sg:phone":"+49 6151/891248",
    "sg:postcode":"64293",
    "sg:province":"Hessen",
    "wof:name":"Hermann Speckhardt",
    "wof:placetype":"venue"
},
  "geometry": {"coordinates":[8.6132640839,49.8697776794],"type":"Point"}
}