{
  "type": "Feature",
  "properties": {
    "iso:country":"DE",
    "sg:address":"Am Trappenbruch 24",
    "sg:city":"Pulheim",
    "sg:phone":"+49 2238/925078",
    "sg:postcode":"50259",
    "sg:province":"Nordrhein-Westfalen",
    "wof:name":"Hans-georg Apostel Ingenieur",
    "wof:placetype":"venue"
},
  "geometry": {"coordinates":[6.7669630051,51.0248718262],"type":"Point"}
}