{
  "type": "Feature",
  "properties": {
    "iso:country":"DE",
    "sg:address":"Merkurring 63-65",
    "sg:city":"Hamburg",
    "sg:postcode":"22143",
    "sg:province":"Hamburg",
    "wof:name":"Solar-concept Vertriebsgesellschaft Mbh",
    "wof:placetype":"venue"
},
  "geometry": {"coordinates":[10.188826561,53.6049232483],"type":"Point"}
}