{
  "type": "Feature",
  "properties": {
    "iso:country":"DE",
    "sg:address":"M\u00fcsigen",
    "sg:city":"Newel",
    "sg:phone":"+49 6505/99020",
    "sg:postcode":"54309",
    "sg:province":"Rheinland-Pfalz",
    "wof:name":"G\u00fcnter Loens Gmbh",
    "wof:placetype":"venue"
},
  "geometry": {"coordinates":[6.56816,49.802441],"type":"Point"}
}