{
  "type": "Feature",
  "properties": {
    "iso:country":"DE",
    "sg:address":"Flurstr. 12",
    "sg:city":"Lauf",
    "sg:phone":"+49 9123/3526",
    "sg:postcode":"91207",
    "sg:province":"Bayern",
    "wof:name":"Dr. Med. Gerhard Weinzierl",
    "wof:placetype":"venue"
},
  "geometry": {"coordinates":[11.2854385376,49.5062980652],"type":"Point"}
}