{
  "type": "Feature",
  "properties": {
    "iso:country":"DE",
    "sg:address":"Oberstr. 126",
    "sg:city":"Bochum",
    "sg:phone":"+49 234/294932",
    "sg:postcode":"44892",
    "sg:province":"Nordrhein-Westfalen",
    "wof:name":"Heinz-j\u00fcrgen Beyer",
    "wof:placetype":"venue"
},
  "geometry": {"coordinates":[7.338874,51.477734],"type":"Point"}
}