{
  "type": "Feature",
  "properties": {
    "iso:country":"DE",
    "sg:address":"Sandstr. 27 A",
    "sg:city":"N\u00fcrnberg",
    "sg:postcode":"90443",
    "sg:province":"Bayern",
    "wof:name":"Lopthar Weilepp & Iris Zeisig",
    "wof:placetype":"venue"
},
  "geometry": {"coordinates":[11.0721969604,49.4458961487],"type":"Point"}
}