{
  "type": "Feature",
  "properties": {
    "iso:country":"DE",
    "sg:address":"Stammheimer Str. 112",
    "sg:city":"K\u00f6ln",
    "sg:phone":"+49 221/763934",
    "sg:postcode":"50735",
    "sg:province":"Nordrhein-Westfalen",
    "wof:name":"Heinz Wallraf",
    "wof:placetype":"venue"
},
  "geometry": {"coordinates":[6.976995945,50.9649734497],"type":"Point"}
}