{
  "type": "Feature",
  "properties": {
    "iso:country":"DE",
    "sg:address":"Hertzstr. 12",
    "sg:city":"Ettlingen",
    "sg:phone":"+49 7243/31813",
    "sg:postcode":"76275",
    "sg:province":"Baden-W\u00fcrttemberg",
    "wof:name":"Gabriele Rech Masseurin",
    "wof:placetype":"venue"
},
  "geometry": {"coordinates":[8.38253,48.945221],"type":"Point"}
}