{
  "type": "Feature",
  "properties": {
    "iso:country":"DE",
    "sg:address":"Gildeweg 5",
    "sg:city":"Telgte",
    "sg:phone":"+49 4925/0473500",
    "sg:postcode":"48291",
    "sg:province":"Nordrhein-Westfalen",
    "wof:name":"Jonas Werkzeugbau Stanzerei Gmbh",
    "wof:placetype":"venue"
},
  "geometry": {"coordinates":[7.778588,51.980984],"type":"Point"}
}