{
  "type": "Feature",
  "properties": {
    "iso:country":"DE",
    "sg:address":"Lindenstr. 20",
    "sg:city":"Rennertshofen",
    "sg:phone":"+49 9094/410",
    "sg:postcode":"86643",
    "sg:province":"Bayern",
    "wof:name":"Johann Landes",
    "wof:placetype":"venue"
},
  "geometry": {"coordinates":[10.995996,48.794369],"type":"Point"}
}