{
  "type": "Feature",
  "properties": {
    "iso:country":"DE",
    "sg:address":"Wehrstr 13c",
    "sg:city":"Glauchau",
    "sg:phone":"+49 3763/50850",
    "sg:postcode":"08371",
    "sg:province":"Sachsen",
    "wof:name":"Mh-modevertrieb Hartig & Donner Ohg",
    "wof:placetype":"venue"
},
  "geometry": {"coordinates":[12.5290250778,50.815990448],"type":"Point"}
}