{
  "type": "Feature",
  "properties": {
    "iso:country":"DE",
    "sg:address":"64546",
    "sg:city":"M\u00f6rfelden-Walldorf",
    "sg:phone":"+49 6105/5326",
    "sg:postcode":"64546",
    "sg:province":"Hessen",
    "wof:name":"Deutsche Bahn Ag",
    "wof:placetype":"venue"
},
  "geometry": {"coordinates":[8.5669403076,49.9850616455],"type":"Point"}
}