{
  "type": "Feature",
  "properties": {
    "iso:country":"DE",
    "sg:address":"Halberstaedterstr.12",
    "sg:city":"Halle",
    "sg:phone":"+49 4934/5217780",
    "sg:postcode":"06112",
    "sg:province":"Sachsen-Anhalt",
    "wof:name":"Reprotechnik Halle Gmbh",
    "wof:placetype":"venue"
},
  "geometry": {"coordinates":[11.9831190109,51.4833106995],"type":"Point"}
}