{
  "type": "Feature",
  "properties": {
    "iso:country":"DE",
    "sg:address":"Bisholderweg 9 a",
    "sg:city":"Koblenz",
    "sg:phone":"+49 261/48354",
    "sg:postcode":"56072",
    "sg:province":"Rheinland-Pfalz",
    "wof:name":"Hans Klee",
    "wof:placetype":"venue"
},
  "geometry": {"coordinates":[7.53565979,50.3354682922],"type":"Point"}
}