{
  "type": "Feature",
  "properties": {
    "iso:country":"DE",
    "sg:address":"Burgstr. 14",
    "sg:city":"Bad Mergentheim",
    "sg:phone":"+49 7931/7537",
    "sg:postcode":"97980",
    "sg:province":"Baden-W\u00fcrttemberg",
    "wof:name":"Mittnacht",
    "wof:placetype":"venue"
},
  "geometry": {"coordinates":[9.774226,49.490818],"type":"Point"}
}