{
  "type": "Feature",
  "properties": {
    "iso:country":"DE",
    "sg:address":"Hauptstr. 49",
    "sg:city":"Hohenwarthe",
    "sg:phone":"+49 39222/95625",
    "sg:postcode":"39291",
    "sg:province":"Sachsen-Anhalt",
    "wof:name":"Lkw- Und Baumaschinen- Service Gmbh",
    "wof:placetype":"venue"
},
  "geometry": {"coordinates":[11.7065410614,52.2247467041],"type":"Point"}
}