{
  "type": "Feature",
  "properties": {
    "iso:country":"DE",
    "sg:address":"Querstr. 15",
    "sg:city":"Gladbeck",
    "sg:phone":"+49 2043/66818",
    "sg:postcode":"45964",
    "sg:province":"Nordrhein-Westfalen",
    "wof:name":"Werner Wolff",
    "wof:placetype":"venue"
},
  "geometry": {"coordinates":[6.985326,51.575905],"type":"Point"}
}