{
  "type": "Feature",
  "properties": {
    "iso:country":"DE",
    "sg:address":"Zeilbaumweg 10",
    "sg:city":"\u00d6hringen",
    "sg:phone":"+49 7941/36222",
    "sg:postcode":"74613",
    "sg:province":"Baden-W\u00fcrttemberg",
    "wof:name":"Neubauer Gmbh",
    "wof:placetype":"venue"
},
  "geometry": {"coordinates":[9.491997,49.198673],"type":"Point"}
}