{
  "type": "Feature",
  "properties": {
    "iso:country":"DE",
    "sg:address":"Bramfelder Chaussee 1-3",
    "sg:city":"Hamburg",
    "sg:phone":"+49 40",
    "sg:postcode":"22177",
    "sg:province":"Hamburg",
    "wof:name":"Rechtsanw\u00e4lte Ewald, H\u00e4nel & Baatz",
    "wof:placetype":"venue"
},
  "geometry": {"coordinates":[10.059106,53.593773],"type":"Point"}
}