{
  "type": "Feature",
  "properties": {
    "iso:country":"DE",
    "sg:address":"Englandstr. 9",
    "sg:city":"Hemer",
    "sg:postcode":"58675",
    "sg:province":"Nordrhein-Westfalen",
    "wof:name":"Industrie-kunststoffe Morris & Wroblewski Ohg",
    "wof:placetype":"venue"
},
  "geometry": {"coordinates":[7.799084,51.383709],"type":"Point"}
}