{
  "type": "Feature",
  "properties": {
    "iso:country":"DE",
    "sg:address":"Bahnhofstr. 3",
    "sg:city":"Oberderdingen-Flehingen",
    "sg:phone":"+49 7258",
    "sg:postcode":"75038",
    "sg:province":"Baden-W\u00fcrttemberg",
    "wof:name":"Roland Kraft Elektromotoren Oberderdingen-flehingen",
    "wof:placetype":"venue"
},
  "geometry": {"coordinates":[8.780683,49.086426],"type":"Point"}
}