{
  "type": "Feature",
  "properties": {
    "iso:country":"DE",
    "sg:address":"K\u00fcnzeller Str. 87",
    "sg:city":"Fulda",
    "sg:phone":"+49 661/73448",
    "sg:postcode":"36043",
    "sg:province":"Hessen",
    "wof:name":"August Ziegler",
    "wof:placetype":"venue"
},
  "geometry": {"coordinates":[9.6941490173,50.5453033447],"type":"Point"}
}