{
  "type": "Feature",
  "properties": {
    "iso:country":"DE",
    "sg:address":"Hildesheimer Str. 25",
    "sg:city":"Hannover",
    "sg:phone":"+49 511/285760",
    "sg:postcode":"30169",
    "sg:province":"Niedersachsen",
    "wof:name":"Abb Instalationen",
    "wof:placetype":"venue"
},
  "geometry": {"coordinates":[9.746635,52.3657],"type":"Point"}
}