{
  "type": "Feature",
  "properties": {
    "iso:country":"DE",
    "sg:address":"Heinrichstr",
    "sg:city":"Hildesheim",
    "sg:postcode":"31137",
    "sg:province":"Niedersachsen",
    "wof:name":"Kostenlose Klingelt\u00d6ne & Sms Spr\u00dcche",
    "wof:placetype":"venue"
},
  "geometry": {"coordinates":[9.959661,52.163376],"type":"Point"}
}