{
  "type": "Feature",
  "properties": {
    "iso:country":"DE",
    "sg:address":"Langengasse 27",
    "sg:city":"Altenburg",
    "sg:phone":"+49 3447/4647",
    "sg:postcode":"04600",
    "sg:province":"Th\u00fcringen",
    "wof:name":"Norbert Bertkau",
    "wof:placetype":"venue"
},
  "geometry": {"coordinates":[12.432735,50.981869],"type":"Point"}
}