{
  "type": "Feature",
  "properties": {
    "iso:country":"DE",
    "sg:address":"B\u00fcnder Str. 184",
    "sg:city":"Hiddenhausen",
    "sg:postcode":"32120",
    "sg:province":"Nordrhein-Westfalen",
    "wof:name":"Petrocargo Mineral\u00f6llogistik Gmbh",
    "wof:placetype":"venue"
},
  "geometry": {"coordinates":[8.6494455338,52.1492424011],"type":"Point"}
}