{
  "type": "Feature",
  "properties": {
    "iso:country":"DE",
    "sg:address":"Rainstr. 12",
    "sg:city":"Elkenroth",
    "sg:phone":"+49 2747/7950",
    "sg:postcode":"57578",
    "sg:province":"Rheinland-Pfalz",
    "wof:name":"Weller F\u00f6rdertechnik Gmbh",
    "wof:placetype":"venue"
},
  "geometry": {"coordinates":[7.8873901367,50.7258987427],"type":"Point"}
}