{
  "type": "Feature",
  "properties": {
    "iso:country":"DE",
    "sg:address":"Im Asemwald 48",
    "sg:city":"Stuttgart",
    "sg:phone":"+49 711/7288958",
    "sg:postcode":"70599",
    "sg:province":"Baden-W\u00fcrttemberg",
    "wof:name":"S. Hoffrichter",
    "wof:placetype":"venue"
},
  "geometry": {"coordinates":[9.19252,48.72319],"type":"Point"}
}