{
  "type": "Feature",
  "properties": {
    "iso:country":"DE",
    "sg:address":"Siemensring 118",
    "sg:city":"Willich",
    "sg:phone":"+49 2154/490490",
    "sg:postcode":"47877",
    "sg:province":"Nordrhein-Westfalen",
    "wof:name":"Die Auto-galerie Gmbh",
    "wof:placetype":"venue"
},
  "geometry": {"coordinates":[6.5166950226,51.2666816711],"type":"Point"}
}