{
  "type": "Feature",
  "properties": {
    "iso:country":"DE",
    "sg:address":"Ravensburger Str. 1",
    "sg:city":"Tettnang",
    "sg:phone":"+49 7542/6883",
    "sg:postcode":"88069",
    "sg:province":"Baden-W\u00fcrttemberg",
    "wof:name":"Bus-hotel-ring Bodensee Gmbh",
    "wof:placetype":"venue"
},
  "geometry": {"coordinates":[9.5871124268,47.6745109558],"type":"Point"}
}