{
  "type": "Feature",
  "properties": {
    "iso:country":"DE",
    "sg:address":"Brachter Str. 42",
    "sg:city":"Ratingen",
    "sg:phone":"+49 2102/50126",
    "sg:postcode":"40882",
    "sg:province":"Nordrhein-Westfalen",
    "wof:name":"Karl Kliff",
    "wof:placetype":"venue"
},
  "geometry": {"coordinates":[6.911586,51.295124],"type":"Point"}
}