{
  "type": "Feature",
  "properties": {
    "iso:country":"DE",
    "sg:address":"J\u00e4gerstr. 15",
    "sg:city":"P\u00f6ttmes",
    "sg:phone":"+49 8253/1715",
    "sg:postcode":"86554",
    "sg:province":"Bayern",
    "wof:name":"J. Zettl Jun.",
    "wof:placetype":"venue"
},
  "geometry": {"coordinates":[11.0419950485,48.5407562256],"type":"Point"}
}