{
  "type": "Feature",
  "properties": {
    "iso:country":"DE",
    "sg:address":"Norderende 40",
    "sg:city":"Hollingstedt",
    "sg:phone":"+49 4627/464",
    "sg:postcode":"24876",
    "sg:province":"Schleswig-Holstein",
    "wof:name":"Karl Evers",
    "wof:placetype":"venue"
},
  "geometry": {"coordinates":[9.337727,54.465244],"type":"Point"}
}