{
  "type": "Feature",
  "properties": {
    "iso:country":"DE",
    "sg:address":"Marktstr. 23",
    "sg:city":"Saerbeck",
    "sg:phone":"+49 2574/8109",
    "sg:postcode":"48369",
    "sg:province":"Nordrhein-Westfalen",
    "wof:name":"Gasthaus Winters",
    "wof:placetype":"venue"
},
  "geometry": {"coordinates":[7.6335301399,52.1737861633],"type":"Point"}
}