{
  "type": "Feature",
  "properties": {
    "iso:country":"DE",
    "sg:address":"Karwendelstr. 37",
    "sg:city":"Lenggries",
    "sg:postcode":"83661",
    "sg:province":"Bayern",
    "wof:name":"Josef Ederer",
    "wof:placetype":"venue"
},
  "geometry": {"coordinates":[11.578452,47.67691],"type":"Point"}
}