{
  "type": "Feature",
  "properties": {
    "iso:country":"DE",
    "sg:address":"Hohenzollernstr. 47",
    "sg:city":"Ludwigshafen",
    "sg:phone":"+49 621/695302",
    "sg:postcode":"67063",
    "sg:province":"Rheinland-Pfalz",
    "wof:name":"Rudolf Wieland",
    "wof:placetype":"venue"
},
  "geometry": {"coordinates":[8.4223051071,49.4905662537],"type":"Point"}
}