{
  "type": "Feature",
  "properties": {
    "iso:country":"DE",
    "sg:address":"Th\u00e4lmannstr. 2",
    "sg:city":"Petershagen",
    "sg:phone":"+49 33439/59505",
    "sg:postcode":"15370",
    "sg:province":"Brandenburg",
    "wof:name":"K. Fr\u00e4drich",
    "wof:placetype":"venue"
},
  "geometry": {"coordinates":[13.7748908997,52.5195884705],"type":"Point"}
}