{
  "type": "Feature",
  "properties": {
    "iso:country":"DE",
    "sg:address":"Im Weidchen 20",
    "sg:city":"D\u00fcren",
    "sg:phone":"+49 2421/82299",
    "sg:postcode":"52353",
    "sg:province":"Nordrhein-Westfalen",
    "wof:name":"Egon Tews",
    "wof:placetype":"venue"
},
  "geometry": {"coordinates":[6.443009,50.825611],"type":"Point"}
}