{
  "type": "Feature",
  "properties": {
    "iso:country":"DE",
    "sg:address":"Wunderb\u00fctteler Kirchweg 5",
    "sg:city":"Wittingen",
    "sg:postcode":"29378",
    "sg:province":"Niedersachsen",
    "wof:name":"Otto Heine Immobilien Gmbh & Co. Kg",
    "wof:placetype":"venue"
},
  "geometry": {"coordinates":[10.7266769409,52.7208938599],"type":"Point"}
}