{
  "type": "Feature",
  "properties": {
    "iso:country":"DE",
    "sg:address":"Hauptstr. 17",
    "sg:city":"B\u00f6tzingen",
    "sg:phone":"+49 7663/4542",
    "sg:postcode":"79268",
    "sg:province":"Baden-W\u00fcrttemberg",
    "wof:name":"Anita Martin",
    "wof:placetype":"venue"
},
  "geometry": {"coordinates":[7.7207322121,48.0729293823],"type":"Point"}
}