{
  "type": "Feature",
  "properties": {
    "iso:country":"DE",
    "sg:address":"Am Kuhdamm 8",
    "sg:city":"Esterwegen",
    "sg:phone":"+49 5955/1446",
    "sg:postcode":"26897",
    "sg:province":"Niedersachsen",
    "wof:name":"Putz Und Bau Thomes Gmbh",
    "wof:placetype":"venue"
},
  "geometry": {"coordinates":[7.6564869881,53.0048408508],"type":"Point"}
}