{
  "type": "Feature",
  "properties": {
    "iso:country":"DE",
    "sg:address":"D\u00fcrnbergstr. 14a",
    "sg:city":"Marktredwitz",
    "sg:phone":"+49 9231/660221",
    "sg:postcode":"95615",
    "sg:province":"Bayern",
    "wof:name":"Reinhard Schaller",
    "wof:placetype":"venue"
},
  "geometry": {"coordinates":[12.0877828598,50.0037536621],"type":"Point"}
}