{
  "type": "Feature",
  "properties": {
    "iso:country":"DE",
    "sg:address":"Ossietzkystr. 7",
    "sg:city":"Berlin",
    "sg:postcode":"13187",
    "sg:province":"Berlin",
    "wof:name":"Wohnterrassen Wolfshagener Str. 58 Gmbh",
    "wof:placetype":"venue"
},
  "geometry": {"coordinates":[13.408402,52.57172],"type":"Point"}
}