{
  "type": "Feature",
  "properties": {
    "iso:country":"DE",
    "sg:address":"Tichelweg 3a",
    "sg:city":"Kevelaer",
    "sg:phone":"+49 2832/80484",
    "sg:postcode":"47626",
    "sg:province":"Nordrhein-Westfalen",
    "wof:name":"B. Wolff Rechtsanwalt",
    "wof:placetype":"venue"
},
  "geometry": {"coordinates":[6.2798991203,51.6004600525],"type":"Point"}
}