{
  "type": "Feature",
  "properties": {
    "iso:country":"DE",
    "sg:address":"Marschstr. 53",
    "sg:city":"Meldorf",
    "sg:phone":"+49 4832/8835",
    "sg:postcode":"25704",
    "sg:province":"Schleswig-Holstein",
    "wof:name":"Autokraft Gmbh",
    "wof:placetype":"venue"
},
  "geometry": {"coordinates":[9.0722780228,54.0839347839],"type":"Point"}
}