{
  "type": "Feature",
  "properties": {
    "iso:country":"DE",
    "sg:address":"Dinzling",
    "sg:city":"Traitsching",
    "sg:phone":"+49 9971/30241",
    "sg:postcode":"93455",
    "sg:province":"Bayern",
    "wof:name":"Werner B\u00e4tz",
    "wof:placetype":"venue"
},
  "geometry": {"coordinates":[12.6349229813,49.1338310242],"type":"Point"}
}