{
  "type": "Feature",
  "properties": {
    "iso:country":"DE",
    "sg:address":"Karl-Marx-Str. 12",
    "sg:city":"Schulzendorf",
    "sg:phone":"+49 33762/49820",
    "sg:postcode":"15732",
    "sg:province":"Brandenburg",
    "wof:name":"Lide Lichtdecken-systeme Schulzendorf Gmbh",
    "wof:placetype":"venue"
},
  "geometry": {"coordinates":[13.6032037735,52.3730621338],"type":"Point"}
}