{
  "type": "Feature",
  "properties": {
    "iso:country":"DE",
    "sg:address":"Steilshooper Str 98-100",
    "sg:city":"Hamburg",
    "sg:phone":"+49 40/619206",
    "sg:postcode":"22305",
    "sg:province":"Hamburg",
    "wof:name":"Paul Westphal",
    "wof:placetype":"venue"
},
  "geometry": {"coordinates":[10.050261,53.589745],"type":"Point"}
}