{
  "type": "Feature",
  "properties": {
    "iso:country":"DE",
    "sg:address":"Bielsteiner Str. 135",
    "sg:city":"Wiehl",
    "sg:phone":"+49 2262/2540",
    "sg:postcode":"51674",
    "sg:province":"Nordrhein-Westfalen",
    "wof:name":"Kath. Pfarramt St. Bonifatius",
    "wof:placetype":"venue"
},
  "geometry": {"coordinates":[7.4965047836,50.9624023438],"type":"Point"}
}