{
  "type": "Feature",
  "properties": {
    "iso:country":"DE",
    "sg:address":"Maa\u00dfenstrasse 12",
    "sg:city":"Berlin",
    "sg:phone":"+49 30",
    "sg:postcode":"10777",
    "sg:province":"Berlin",
    "wof:name":"Lenard Mason Promotion Agentur",
    "wof:placetype":"venue"
},
  "geometry": {"coordinates":[13.35422,52.497555],"type":"Point"}
}