{
  "type": "Feature",
  "properties": {
    "iso:country":"DE",
    "sg:address":"Stegemannstr 7",
    "sg:city":"Parchim",
    "sg:phone":"+49 3871/265420",
    "sg:postcode":"19370",
    "sg:province":"Mecklenburg-Vorpommern",
    "wof:name":"Tin Druck Und Verlags Gmbh",
    "wof:placetype":"venue"
},
  "geometry": {"coordinates":[11.8329324722,53.4284477234],"type":"Point"}
}