{
  "type": "Feature",
  "properties": {
    "iso:country":"DE",
    "sg:address":"Maxstr. 16",
    "sg:city":"Zweibr\u00fccken",
    "sg:phone":"+49 6332/74353",
    "sg:postcode":"66482",
    "sg:province":"Rheinland-Pfalz",
    "wof:name":"V 8",
    "wof:placetype":"venue"
},
  "geometry": {"coordinates":[7.3670921326,49.2465820312],"type":"Point"}
}