{
  "type": "Feature",
  "properties": {
    "iso:country":"DE",
    "sg:address":"Freinsheimer Str. 22",
    "sg:city":"Frankenthal",
    "sg:phone":"+49 6233/50024",
    "sg:postcode":"67227",
    "sg:province":"Rheinland-Pfalz",
    "wof:name":"Friedrich Kirstein Fahrr\u00e4der Haushaltswaren",
    "wof:placetype":"venue"
},
  "geometry": {"coordinates":[8.334105,49.515808],"type":"Point"}
}