{
  "type": "Feature",
  "properties": {
    "iso:country":"DE",
    "sg:address":"Fichtenstieg 4",
    "sg:city":"Norderstedt",
    "sg:phone":"+49 40/5226808",
    "sg:postcode":"22844",
    "sg:province":"Schleswig-Holstein",
    "wof:name":"Innova 2000 E. K.",
    "wof:placetype":"venue"
},
  "geometry": {"coordinates":[10.009716,53.735916],"type":"Point"}
}