{
  "type": "Feature",
  "properties": {
    "iso:country":"DE",
    "sg:address":"August-Bebel-Str. 41",
    "sg:city":"Hamburg",
    "sg:phone":"+49 40/7215991",
    "sg:postcode":"21029",
    "sg:province":"Hamburg",
    "wof:name":"W. Van Riesen",
    "wof:placetype":"venue"
},
  "geometry": {"coordinates":[10.223,53.485256],"type":"Point"}
}