{
  "type": "Feature",
  "properties": {
    "iso:country":"DE",
    "sg:address":"Rosentorstr.31",
    "sg:city":"Goslar",
    "sg:phone":"+49 4953/2121141",
    "sg:postcode":"38640",
    "sg:province":"Niedersachsen",
    "wof:name":"Dresdner Bank",
    "wof:placetype":"venue"
},
  "geometry": {"coordinates":[10.426616,51.908615],"type":"Point"}
}