{
  "type": "Feature",
  "properties": {
    "iso:country":"DE",
    "sg:address":"Celler Str. 19",
    "sg:city":"Walsrode",
    "sg:phone":"+49 5161/8225",
    "sg:postcode":"29664",
    "sg:province":"Niedersachsen",
    "wof:name":"Wilhelm Graubohm",
    "wof:placetype":"venue"
},
  "geometry": {"coordinates":[9.6483335495,52.8296852112],"type":"Point"}
}