{
  "type": "Feature",
  "properties": {
    "iso:country":"DE",
    "sg:address":"Penzendorfer Str. 29",
    "sg:city":"Schwabach",
    "sg:phone":"+49 9122/889422",
    "sg:postcode":"91126",
    "sg:province":"Bayern",
    "wof:name":"Doris Engels Ergotherapeutsche Praxis",
    "wof:placetype":"venue"
},
  "geometry": {"coordinates":[11.031001,49.32933],"type":"Point"}
}