{
  "type": "Feature",
  "properties": {
    "iso:country":"DE",
    "sg:address":"Kirchstr. 11",
    "sg:city":"Simonswald",
    "sg:phone":"+49 7683/660",
    "sg:postcode":"79263",
    "sg:province":"Baden-W\u00fcrttemberg",
    "wof:name":"M. Probst",
    "wof:placetype":"venue"
},
  "geometry": {"coordinates":[8.058411,48.101162],"type":"Point"}
}