{
  "type": "Feature",
  "properties": {
    "iso:country":"DE",
    "sg:address":"Gartenstr. 1",
    "sg:city":"Stadtilm",
    "sg:phone":"+49 3629/801312",
    "sg:postcode":"99326",
    "sg:province":"Th\u00fcringen",
    "wof:name":"Christiane Sekienda",
    "wof:placetype":"venue"
},
  "geometry": {"coordinates":[11.0725755692,50.7711029053],"type":"Point"}
}