{
  "type": "Feature",
  "properties": {
    "iso:country":"DE",
    "sg:address":"Landsknechtstr. 83",
    "sg:city":"Hallstadt",
    "sg:phone":"+49 951/70233",
    "sg:postcode":"96103",
    "sg:province":"Bayern",
    "wof:name":"Wolfgang Nehr",
    "wof:placetype":"venue"
},
  "geometry": {"coordinates":[10.883199,49.926826],"type":"Point"}
}