{
  "type": "Feature",
  "properties": {
    "iso:country":"DE",
    "sg:address":"Steinkreuzstr. 37",
    "sg:city":"P\u00fcttlingen",
    "sg:phone":"+49 6898/65823",
    "sg:postcode":"66346",
    "sg:province":"Saarland",
    "wof:name":"M. Valence Farben Und Tapeten",
    "wof:placetype":"venue"
},
  "geometry": {"coordinates":[6.878027916,49.284538269],"type":"Point"}
}