{
  "type": "Feature",
  "properties": {
    "iso:country":"DE",
    "sg:address":"Martin-Luther-Str. 15",
    "sg:city":"Bad Vilbel",
    "sg:phone":"+49 6101/86544",
    "sg:postcode":"61118",
    "sg:province":"Hessen",
    "wof:name":"G. Und R. Reichelt Schaufenstergestaltung",
    "wof:placetype":"venue"
},
  "geometry": {"coordinates":[8.7150068283,50.1747207642],"type":"Point"}
}