{
  "type": "Feature",
  "properties": {
    "iso:country":"DE",
    "sg:address":"Reichsstr. 22",
    "sg:city":"Gera",
    "sg:phone":"+49 365/7106681",
    "sg:postcode":"07545",
    "sg:province":"Th\u00fcringen",
    "wof:name":"M\u00f6bel-schn\u00e4ppchen",
    "wof:placetype":"venue"
},
  "geometry": {"coordinates":[12.084485,50.867764],"type":"Point"}
}