{
  "type": "Feature",
  "properties": {
    "iso:country":"DE",
    "sg:address":"Hauptstr. 32",
    "sg:city":"Drebkau",
    "sg:phone":"+49 35602/21286",
    "sg:postcode":"03116",
    "sg:province":"Brandenburg",
    "wof:name":"I. Kochanski",
    "wof:placetype":"venue"
},
  "geometry": {"coordinates":[14.220126,51.657417],"type":"Point"}
}