{
  "type": "Feature",
  "properties": {
    "iso:country":"DE",
    "sg:address":"Ostseering 11",
    "sg:city":"Graal-M\u00fcritz",
    "sg:phone":"+49 38206/79435",
    "sg:postcode":"18181",
    "sg:province":"Mecklenburg-Vorpommern",
    "wof:name":"Wolf-dieter Schulz",
    "wof:placetype":"venue"
},
  "geometry": {"coordinates":[12.2454338074,54.2511444092],"type":"Point"}
}