{
  "type": "Feature",
  "properties": {
    "iso:country":"DE",
    "sg:address":"M\u00fchlackerstr. 28",
    "sg:city":"Weimar",
    "sg:phone":"+49 4964/26820",
    "sg:postcode":"35096",
    "sg:province":"Hessen",
    "wof:name":"Otto Koch Garten- U. Landschaftsbau Gmbh",
    "wof:placetype":"venue"
},
  "geometry": {"coordinates":[8.695157,50.739719],"type":"Point"}
}