{
  "type": "Feature",
  "properties": {
    "iso:country":"DE",
    "sg:address":"Plochinger Str. 106",
    "sg:city":"Esslingen",
    "sg:phone":"+49 711/3109977",
    "sg:postcode":"73730",
    "sg:province":"Baden-W\u00fcrttemberg",
    "wof:name":"W. Fritsch",
    "wof:placetype":"venue"
},
  "geometry": {"coordinates":[9.329369545,48.7308959961],"type":"Point"}
}