{
  "type": "Feature",
  "properties": {
    "iso:country":"DE",
    "sg:address":"Stra\u00dfe des Friedens 35",
    "sg:city":"Fl\u00f6ha",
    "sg:phone":"+49 3726/723079",
    "sg:postcode":"09557",
    "sg:province":"Sachsen",
    "wof:name":"J\u00f6rg Neudert",
    "wof:placetype":"venue"
},
  "geometry": {"coordinates":[13.0844125748,50.8465232849],"type":"Point"}
}