{
  "type": "Feature",
  "properties": {
    "iso:country":"DE",
    "sg:address":"Weidkamp 121",
    "sg:city":"Essen",
    "sg:phone":"+49 201/686272",
    "sg:postcode":"45355",
    "sg:province":"Nordrhein-Westfalen",
    "wof:name":"Franz-josef Middendorf",
    "wof:placetype":"venue"
},
  "geometry": {"coordinates":[6.947743,51.4813],"type":"Point"}
}