{
  "type": "Feature",
  "properties": {
    "iso:country":"DE",
    "sg:address":"Rethelstr. 47/51",
    "sg:city":"Dresden",
    "sg:phone":"+49 351/851090",
    "sg:postcode":"01139",
    "sg:province":"Sachsen",
    "wof:name":"Ferro W\u00e4rmetechnik Gmbh & Co. Kg",
    "wof:placetype":"venue"
},
  "geometry": {"coordinates":[13.6988515854,51.0699539185],"type":"Point"}
}