{
  "type": "Feature",
  "properties": {
    "iso:country":"DE",
    "sg:address":"Kirchstr. 27",
    "sg:city":"Engstingen",
    "sg:phone":"+49 7129/3143",
    "sg:postcode":"72829",
    "sg:province":"Baden-W\u00fcrttemberg",
    "wof:name":"Siegfried Betzmann",
    "wof:placetype":"venue"
},
  "geometry": {"coordinates":[9.2791900635,48.38671875],"type":"Point"}
}