{
  "type": "Feature",
  "properties": {
    "iso:country":"DE",
    "sg:address":"Am Kaiser 30",
    "sg:city":"W\u00fcrselen",
    "sg:phone":"+49 2405/85235",
    "sg:postcode":"52146",
    "sg:province":"Nordrhein-Westfalen",
    "wof:name":"Josef Becker Sandstrahlarbeiten",
    "wof:placetype":"venue"
},
  "geometry": {"coordinates":[6.10761,50.842644],"type":"Point"}
}