{
  "type": "Feature",
  "properties": {
    "iso:country":"DE",
    "sg:address":"Alpenstr. 8",
    "sg:city":"Owingen",
    "sg:postcode":"88696",
    "sg:province":"Baden-W\u00fcrttemberg",
    "wof:name":"Bernd J. Schweizer",
    "wof:placetype":"venue"
},
  "geometry": {"coordinates":[9.1728553772,47.8074111938],"type":"Point"}
}