{
  "type": "Feature",
  "properties": {
    "iso:country":"DE",
    "sg:address":"Am Werk 9",
    "sg:city":"Hirschfelde",
    "sg:postcode":"02788",
    "sg:province":"Sachsen",
    "wof:name":"Werke Leuna Ag",
    "wof:placetype":"venue"
},
  "geometry": {"coordinates":[14.89021,50.942188],"type":"Point"}
}