{
  "type": "Feature",
  "properties": {
    "iso:country":"DE",
    "sg:address":"Ruhesteinstr. 563",
    "sg:city":"Baiersbronn",
    "sg:phone":"+49 7449/438",
    "sg:postcode":"72270",
    "sg:province":"Baden-W\u00fcrttemberg",
    "wof:name":"Igo Interessengemeinschaft Obertal",
    "wof:placetype":"venue"
},
  "geometry": {"coordinates":[8.2847299576,48.5359077454],"type":"Point"}
}