{
  "type": "Feature",
  "properties": {
    "iso:country":"DE",
    "sg:address":"Poststr. 75",
    "sg:city":"Grevenbroich",
    "sg:phone":"+49 2181/73380",
    "sg:postcode":"41516",
    "sg:province":"Nordrhein-Westfalen",
    "wof:name":"Trattoria Italiana",
    "wof:placetype":"venue"
},
  "geometry": {"coordinates":[6.6214551926,51.1069221497],"type":"Point"}
}