{
  "type": "Feature",
  "properties": {
    "iso:country":"DE",
    "sg:address":"Schwarzwaldstr. 30",
    "sg:city":"Waldkirch",
    "sg:phone":"+49 7681/9467",
    "sg:postcode":"79183",
    "sg:province":"Baden-W\u00fcrttemberg",
    "wof:name":"Kath. Pfarramt St. Pankratius",
    "wof:placetype":"venue"
},
  "geometry": {"coordinates":[7.9259381294,48.0805015564],"type":"Point"}
}