{
  "type": "Feature",
  "properties": {
    "iso:country":"DE",
    "sg:address":"Augsburger Str. 112",
    "sg:city":"Karlshuld",
    "sg:phone":"+49 8454/688",
    "sg:postcode":"86668",
    "sg:province":"Bayern",
    "wof:name":"Siegfried Martin",
    "wof:placetype":"venue"
},
  "geometry": {"coordinates":[11.2705,48.677921],"type":"Point"}
}