{
  "type": "Feature",
  "properties": {
    "iso:country":"DE",
    "sg:address":"Bismarckstr. 21",
    "sg:city":"Baden-Baden",
    "sg:phone":"+49 7221/3690",
    "sg:postcode":"76530",
    "sg:province":"Baden-W\u00fcrttemberg",
    "wof:name":"Privathotel Quisisana Gmbh",
    "wof:placetype":"venue"
},
  "geometry": {"coordinates":[8.232544899,48.7550315857],"type":"Point"}
}