{
  "type": "Feature",
  "properties": {
    "iso:country":"DE",
    "sg:address":"Kleiner Johannes 7",
    "sg:city":"Pegnitz",
    "sg:phone":"+49 9241/1234",
    "sg:postcode":"91257",
    "sg:province":"Bayern",
    "wof:name":"J\u00f6rg Lumpp Kg",
    "wof:placetype":"venue"
},
  "geometry": {"coordinates":[11.5522298813,49.7656097412],"type":"Point"}
}