{
  "type": "Feature",
  "properties": {
    "iso:country":"DE",
    "sg:address":"Hauptstr. 29",
    "sg:city":"Premnitz",
    "sg:phone":"+49 3386/282213",
    "sg:postcode":"14727",
    "sg:province":"Brandenburg",
    "wof:name":"Speisegastst\u00e4tte Zur Bratr\u00f6hre",
    "wof:placetype":"venue"
},
  "geometry": {"coordinates":[12.330450058,52.5321044922],"type":"Point"}
}