{
  "type": "Feature",
  "properties": {
    "iso:country":"DE",
    "sg:address":"Seegatterl 7",
    "sg:city":"Reit im Winkl",
    "sg:phone":"+49 8640/8582",
    "sg:postcode":"83242",
    "sg:province":"Bayern",
    "wof:name":"M\u00fcnster Campingplatz Seegatterl Gmbh",
    "wof:placetype":"venue"
},
  "geometry": {"coordinates":[12.539569,47.658039],"type":"Point"}
}