{
  "type": "Feature",
  "properties": {
    "iso:country":"DE",
    "sg:address":"Steinbruchhaus 6",
    "sg:city":"W\u00fcrselen",
    "sg:phone":"+49 2405/74286",
    "sg:postcode":"52146",
    "sg:province":"Nordrhein-Westfalen",
    "wof:name":"Willi Schornstein",
    "wof:placetype":"venue"
},
  "geometry": {"coordinates":[6.12447,50.820194],"type":"Point"}
}