{
  "type": "Feature",
  "properties": {
    "iso:country":"DE",
    "sg:address":"Schenkstr. 7",
    "sg:city":"Jena",
    "sg:phone":"+49 3641/424327",
    "sg:postcode":"07749",
    "sg:province":"Th\u00fcringen",
    "wof:name":"Bacchus Weinhaus Graf Eltz Gmbh",
    "wof:placetype":"venue"
},
  "geometry": {"coordinates":[11.6017932892,50.930431366],"type":"Point"}
}