{
  "type": "Feature",
  "properties": {
    "iso:country":"DE",
    "sg:address":"Postfach 1246",
    "sg:city":"Burghausen",
    "sg:postcode":"84480",
    "sg:province":"Bayern",
    "wof:name":"W\u00f6hrsee Bootsverleih",
    "wof:placetype":"venue"
},
  "geometry": {"coordinates":[12.8328838348,48.1583557129],"type":"Point"}
}