{
  "type": "Feature",
  "properties": {
    "iso:country":"DE",
    "sg:address":"Hammerg. 5",
    "sg:city":"Olbernhau",
    "sg:phone":"+49 37360/72616",
    "sg:postcode":"09526",
    "sg:province":"Sachsen",
    "wof:name":"Olbenhauer Metallbearbeitung Gmbh",
    "wof:placetype":"venue"
},
  "geometry": {"coordinates":[13.32873,50.657608],"type":"Point"}
}