{
  "type": "Feature",
  "properties": {
    "iso:country":"DE",
    "sg:address":"Schnetter Str. 8",
    "sg:city":"Sch\u00f6nbrunn",
    "sg:phone":"+49 36874/71736",
    "sg:postcode":"98667",
    "sg:province":"Th\u00fcringen",
    "wof:name":"Me\u00dfger\u00c4te Und Umwelttechnik Fischer",
    "wof:placetype":"venue"
},
  "geometry": {"coordinates":[10.874588,50.519367],"type":"Point"}
}