{
  "type": "Feature",
  "properties": {
    "iso:country":"DE",
    "sg:address":"Langgasse 10",
    "sg:city":"Kahl",
    "sg:phone":"+49 6188/81435",
    "sg:postcode":"63796",
    "sg:province":"Bayern",
    "wof:name":"Vereinsgemeinschaft Kahl Peter Emge",
    "wof:placetype":"venue"
},
  "geometry": {"coordinates":[9.0125665665,50.0681991577],"type":"Point"}
}