{
  "type": "Feature",
  "properties": {
    "iso:country":"DE",
    "sg:address":"Harzstr. 37",
    "sg:city":"Niedersachswerfen",
    "sg:phone":"+49 36331/42221",
    "sg:postcode":"99762",
    "sg:province":"Th\u00fcringen",
    "wof:name":"Hans M\u00f6nnich",
    "wof:placetype":"venue"
},
  "geometry": {"coordinates":[10.7693777084,51.5598602295],"type":"Point"}
}