{
  "type": "Feature",
  "properties": {
    "iso:country":"DE",
    "sg:address":"Bonifatiusstr. 35",
    "sg:city":"D\u00fcsseldorf",
    "sg:phone":"+49 211/594402",
    "sg:postcode":"40547",
    "sg:province":"Nordrhein-Westfalen",
    "wof:name":"Hummerst\u00fcbchen",
    "wof:placetype":"venue"
},
  "geometry": {"coordinates":[6.7220277786,51.2515144348],"type":"Point"}
}