{
  "type": "Feature",
  "properties": {
    "iso:country":"DE",
    "sg:address":"Schillerstr. 69",
    "sg:city":"Gerlingen",
    "sg:phone":"+49 7156/22265",
    "sg:postcode":"70839",
    "sg:province":"Baden-W\u00fcrttemberg",
    "wof:name":"Hermann Miller",
    "wof:placetype":"venue"
},
  "geometry": {"coordinates":[9.06971,48.803387],"type":"Point"}
}