{
  "type": "Feature",
  "properties": {
    "iso:country":"DE",
    "sg:address":"Lindenstr. 5",
    "sg:city":"Landau",
    "sg:phone":"+49 9951/98040",
    "sg:postcode":"94405",
    "sg:province":"Bayern",
    "wof:name":"Teba Kreditbank Gmbh & Co Kg",
    "wof:placetype":"venue"
},
  "geometry": {"coordinates":[12.69072,48.669102],"type":"Point"}
}