{
  "type": "Feature",
  "properties": {
    "iso:country":"DE",
    "sg:address":"Bahnhofstr. 110",
    "sg:city":"Borken",
    "sg:phone":"+49 5682/9450",
    "sg:postcode":"34582",
    "sg:province":"Hessen",
    "wof:name":"Walter Makovicka",
    "wof:placetype":"venue"
},
  "geometry": {"coordinates":[9.2851238251,51.045715332],"type":"Point"}
}