{
  "type": "Feature",
  "properties": {
    "iso:country":"DE",
    "sg:address":"Stettiner Str. 24 a",
    "sg:city":"Ibbenb\u00fcren",
    "sg:phone":"+49 5455/1058",
    "sg:postcode":"49479",
    "sg:province":"Nordrhein-Westfalen",
    "wof:name":"Helmut Albers",
    "wof:placetype":"venue"
},
  "geometry": {"coordinates":[7.680339,52.218372],"type":"Point"}
}