{
  "type": "Feature",
  "properties": {
    "iso:country":"DE",
    "sg:address":"Parkstr. 6",
    "sg:city":"Neschwitz",
    "sg:phone":"+49 35933/30331",
    "sg:postcode":"02699",
    "sg:province":"Sachsen",
    "wof:name":"Arnulf Sach\u00dfe",
    "wof:placetype":"venue"
},
  "geometry": {"coordinates":[14.329416,51.271828],"type":"Point"}
}