{
  "type": "Feature",
  "properties": {
    "iso:country":"DE",
    "sg:address":"Thomas-M\u00fcntzer-Str. 51",
    "sg:city":"Ro\u00dfdorf",
    "sg:phone":"+49 3933/87030",
    "sg:postcode":"39307",
    "sg:province":"Sachsen-Anhalt",
    "wof:name":"Fliesen-ernst Gro\u00df- Und Einzelhandel Gmbh",
    "wof:placetype":"venue"
},
  "geometry": {"coordinates":[12.2090854645,52.4277420044],"type":"Point"}
}