{
  "type": "Feature",
  "properties": {
    "iso:country":"DE",
    "sg:address":"Johannes-Gutenberg-Str 4",
    "sg:city":"Ochsenfurt",
    "sg:phone":"+49 9331/4045",
    "sg:postcode":"97199",
    "sg:province":"Bayern",
    "wof:name":"R. & K. Technische Industrieprodukte Gmbh",
    "wof:placetype":"venue"
},
  "geometry": {"coordinates":[10.065990448,49.6634712219],"type":"Point"}
}