{
  "type": "Feature",
  "properties": {
    "iso:country":"DE",
    "sg:address":"Auf der Ebene 10",
    "sg:city":"Gutach",
    "sg:postcode":"77793",
    "sg:province":"Baden-W\u00fcrttemberg",
    "wof:name":"Moser Gmbh",
    "wof:placetype":"venue"
},
  "geometry": {"coordinates":[8.200569,48.269104],"type":"Point"}
}