{
  "type": "Feature",
  "properties": {
    "iso:country":"DE",
    "sg:address":"Markt 7",
    "sg:city":"Br\u00fchl",
    "sg:phone":"+49 2232/42613",
    "sg:postcode":"50321",
    "sg:province":"Nordrhein-Westfalen",
    "wof:name":"Kurf\u00fcrsten Apotheke",
    "wof:placetype":"venue"
},
  "geometry": {"coordinates":[6.904467,50.828438],"type":"Point"}
}