{
  "type": "Feature",
  "properties": {
    "iso:country":"DE",
    "sg:address":"Thomas-M\u00fcntzer-Str. 4",
    "sg:city":"Holleben",
    "sg:phone":"+49 345/6130328",
    "sg:postcode":"06179",
    "sg:province":"Sachsen-Anhalt",
    "wof:name":"Martin Pflock",
    "wof:placetype":"venue"
},
  "geometry": {"coordinates":[11.901886,51.433914],"type":"Point"}
}