{
  "type": "Feature",
  "properties": {
    "iso:country":"DE",
    "sg:address":"Br\u00fcderstr. 13",
    "sg:city":"Lippstadt",
    "sg:phone":"+49 2941/923980",
    "sg:postcode":"59555",
    "sg:province":"Nordrhein-Westfalen",
    "wof:name":"Hoffmann & Partner",
    "wof:placetype":"venue"
},
  "geometry": {"coordinates":[8.3485803604,51.6762619019],"type":"Point"}
}