{
  "type": "Feature",
  "properties": {
    "iso:country":"DE",
    "sg:address":"Kettwiger Str. 39",
    "sg:city":"D\u00fcsseldorf",
    "sg:phone":"+49 211/7334943",
    "sg:postcode":"40233",
    "sg:province":"Nordrhein-Westfalen",
    "wof:name":"Deutsche Shell Ag",
    "wof:placetype":"venue"
},
  "geometry": {"coordinates":[6.8111162186,51.2230644226],"type":"Point"}
}