{
  "type": "Feature",
  "properties": {
    "iso:country":"DE",
    "sg:address":"Kanalstr. II Nr. 1 a",
    "sg:city":"Wiesmoor",
    "sg:phone":"+49 4944/960155",
    "sg:postcode":"26639",
    "sg:province":"Niedersachsen",
    "wof:name":"Bu\u00df Bestattungen Gmbh",
    "wof:placetype":"venue"
},
  "geometry": {"coordinates":[7.733989,53.41354],"type":"Point"}
}