{
  "type": "Feature",
  "properties": {
    "iso:country":"DE",
    "sg:address":"Altenburger Str. 29",
    "sg:city":"Nobitz",
    "sg:phone":"+49 3447/57090",
    "sg:postcode":"04603",
    "sg:province":"Th\u00fcringen",
    "wof:name":"Wohnwelt M\u00f6belzentrum Gmbh",
    "wof:placetype":"venue"
},
  "geometry": {"coordinates":[12.4831972122,50.9801025391],"type":"Point"}
}