{
  "type": "Feature",
  "properties": {
    "iso:country":"DE",
    "sg:address":"Duisburger Str. 78",
    "sg:city":"M\u00fclheim",
    "sg:phone":"+49 208/4510",
    "sg:postcode":"45479",
    "sg:province":"Nordrhein-Westfalen",
    "wof:name":"Betriebe Der Stadt M\u00fclheim",
    "wof:placetype":"venue"
},
  "geometry": {"coordinates":[6.862125,51.426987],"type":"Point"}
}