{
  "type": "Feature",
  "properties": {
    "iso:country":"DE",
    "sg:address":"Joachimstaler Str. 42",
    "sg:city":"Berlin",
    "sg:postcode":"10623",
    "sg:province":"Berlin",
    "wof:name":"Ski-h\u00fctte Invancica Merker-rubcic E.kfr.",
    "wof:placetype":"venue"
},
  "geometry": {"coordinates":[13.33187,52.505005],"type":"Point"}
}