{
  "type": "Feature",
  "properties": {
    "iso:country":"DE",
    "sg:address":"Speicherstr 3-4",
    "sg:city":"Neubrandenburg",
    "sg:phone":"+49 395/55920",
    "sg:postcode":"17033",
    "sg:province":"Mecklenburg-Vorpommern",
    "wof:name":"Webasto Thermosysteme Gmbh",
    "wof:placetype":"venue"
},
  "geometry": {"coordinates":[13.270171,53.560097],"type":"Point"}
}