{
  "type": "Feature",
  "properties": {
    "iso:country":"DE",
    "sg:address":"Schnatweg 15",
    "sg:city":"Bissendorf",
    "sg:phone":"+49 5402/961101",
    "sg:postcode":"49143",
    "sg:province":"Niedersachsen",
    "wof:name":"Martin Kameyer Ingenieur",
    "wof:placetype":"venue"
},
  "geometry": {"coordinates":[8.2232217789,52.2465896606],"type":"Point"}
}