{
  "type": "Feature",
  "properties": {
    "iso:country":"DE",
    "sg:address":"Bahnhofstr. 1",
    "sg:city":"Rackwitz",
    "sg:phone":"+49 34294/70600",
    "sg:postcode":"04519",
    "sg:province":"Sachsen",
    "wof:name":"Agr Aluminium-giesserei Rackwitz Gmbh",
    "wof:placetype":"venue"
},
  "geometry": {"coordinates":[12.375606,51.439735],"type":"Point"}
}