{
  "type": "Feature",
  "properties": {
    "iso:country":"DE",
    "sg:address":"Gr\u00fcner Weg 32",
    "sg:city":"Troisdorf",
    "sg:phone":"+49 2241/400493",
    "sg:postcode":"53842",
    "sg:province":"Nordrhein-Westfalen",
    "wof:name":"K. W. Neunzig",
    "wof:placetype":"venue"
},
  "geometry": {"coordinates":[7.1180791855,50.8232765198],"type":"Point"}
}