{
  "type": "Feature",
  "properties": {
    "iso:country":"DE",
    "sg:address":"Hauptstr. 10",
    "sg:city":"Holm",
    "sg:phone":"+49 4103/17430",
    "sg:postcode":"25488",
    "sg:province":"Schleswig-Holstein",
    "wof:name":"Hans-christian Jessen",
    "wof:placetype":"venue"
},
  "geometry": {"coordinates":[9.674917,53.618553],"type":"Point"}
}