{
  "type": "Feature",
  "properties": {
    "iso:country":"DE",
    "sg:address":"Rudolf-Diesel-Weg 12",
    "sg:city":"M\u00f6lln",
    "sg:phone":"+49 4945/422883",
    "sg:postcode":"23879",
    "sg:province":"Schleswig-Holstein",
    "wof:name":"Nordheim Gmbh",
    "wof:placetype":"venue"
},
  "geometry": {"coordinates":[10.674842,53.602257],"type":"Point"}
}