{
  "type": "Feature",
  "properties": {
    "iso:country":"DE",
    "sg:address":"Fruchtallee 128",
    "sg:city":"Hamburg",
    "sg:phone":"+49 40/496011",
    "sg:postcode":"20259",
    "sg:province":"Hamburg",
    "wof:name":"Barotrauma.de",
    "wof:placetype":"venue"
},
  "geometry": {"coordinates":[9.950498,53.572712],"type":"Point"}
}