{
  "type": "Feature",
  "properties": {
    "iso:country":"DE",
    "sg:address":"Hoffmannallee 19-21",
    "sg:city":"Kleve",
    "sg:phone":"+49 2821/70336",
    "sg:postcode":"47533",
    "sg:province":"Nordrhein-Westfalen",
    "wof:name":"Neukauf",
    "wof:placetype":"venue"
},
  "geometry": {"coordinates":[6.1291160583,51.7810287476],"type":"Point"}
}