{
  "type": "Feature",
  "properties": {
    "iso:country":"DE",
    "sg:address":"Steinhagener Str. 7a",
    "sg:city":"Bielefeld",
    "sg:phone":"+49 521/48677",
    "sg:postcode":"33649",
    "sg:province":"Nordrhein-Westfalen",
    "wof:name":"Hermann Keuch Ingenieur",
    "wof:placetype":"venue"
},
  "geometry": {"coordinates":[8.4558353424,51.9658088684],"type":"Point"}
}