{
  "type": "Feature",
  "properties": {
    "iso:country":"DE",
    "sg:address":"Atzelbergstr.44",
    "sg:city":"Frankfurt/Main",
    "sg:postcode":"60389",
    "sg:province":"Hessen",
    "wof:name":"The Beatles Revival Band",
    "wof:placetype":"venue"
},
  "geometry": {"coordinates":[8.719824,50.14053],"type":"Point"}
}