{
  "type": "Feature",
  "properties": {
    "iso:country":"DE",
    "sg:address":"K\u00f6nigsallee 178 a",
    "sg:city":"Bochum",
    "sg:phone":"+49 234",
    "sg:postcode":"44799",
    "sg:province":"Nordrhein-Westfalen",
    "wof:name":"Bundesverband Selbst\u00e4ndiger Physiotherapeutinnen",
    "wof:placetype":"venue"
},
  "geometry": {"coordinates":[7.22347,51.458336],"type":"Point"}
}