{
  "type": "Feature",
  "properties": {
    "iso:country":"DE",
    "sg:address":"Turbinenstr. 25",
    "sg:city":"Mannheim",
    "sg:phone":"+49 621/727650",
    "sg:postcode":"68309",
    "sg:province":"Baden-W\u00fcrttemberg",
    "wof:name":"Fliesen-oase Fliesen Keramik Gmbh",
    "wof:placetype":"venue"
},
  "geometry": {"coordinates":[8.4982089996,49.5129623413],"type":"Point"}
}