{
  "type": "Feature",
  "properties": {
    "iso:country":"DE",
    "sg:address":"Fichtenstr. 16",
    "sg:city":"Heimsheim",
    "sg:phone":"+49 7033/32746",
    "sg:postcode":"71296",
    "sg:province":"Baden-W\u00fcrttemberg",
    "wof:name":"Heinz R\u00f6ckle",
    "wof:placetype":"venue"
},
  "geometry": {"coordinates":[8.872068,48.807594],"type":"Point"}
}