{
  "type": "Feature",
  "properties": {
    "iso:country":"DE",
    "sg:address":"S\u00fcchtelner Str. 23",
    "sg:city":"T\u00f6nisvorst",
    "sg:phone":"+49 2156/8561",
    "sg:postcode":"47918",
    "sg:province":"Nordrhein-Westfalen",
    "wof:name":"D. Br\u00f6xkes",
    "wof:placetype":"venue"
},
  "geometry": {"coordinates":[6.3892068863,51.3056297302],"type":"Point"}
}