{
  "type": "Feature",
  "properties": {
    "iso:country":"DE",
    "sg:address":"Alte Leipziger Str. 50",
    "sg:city":"Bielen-Nordhausen",
    "sg:phone":"+49 3631",
    "sg:postcode":"99735",
    "sg:province":"Th\u00fcringen",
    "wof:name":"Institut F\u00fcr Neue Basis-technologien",
    "wof:placetype":"venue"
},
  "geometry": {"coordinates":[10.7407264709,51.4831237793],"type":"Point"}
}