{
  "type": "Feature",
  "properties": {
    "iso:country":"DE",
    "sg:address":"Bahnhofstr. 48",
    "sg:city":"Schneverdingen",
    "sg:postcode":"29640",
    "sg:province":"Niedersachsen",
    "wof:name":"Ilses Bioladen",
    "wof:placetype":"venue"
},
  "geometry": {"coordinates":[9.7944498062,53.1136207581],"type":"Point"}
}