{
  "type": "Feature",
  "properties": {
    "iso:country":"DE",
    "sg:address":"Sudetenstr. 1a",
    "sg:city":"Sonthofen",
    "sg:phone":"+49 8321/71963",
    "sg:postcode":"87527",
    "sg:province":"Bayern",
    "wof:name":"A. Und M. Schmid-neugebauer",
    "wof:placetype":"venue"
},
  "geometry": {"coordinates":[10.2760534286,47.5135955811],"type":"Point"}
}