{
  "type": "Feature",
  "properties": {
    "iso:country":"DE",
    "sg:address":"Stakelberg 8",
    "sg:city":"M\u00f6nchengladbach",
    "sg:phone":"+49 2161/87763",
    "sg:postcode":"41063",
    "sg:province":"Nordrhein-Westfalen",
    "wof:name":"Hubert Joeken Architekt",
    "wof:placetype":"venue"
},
  "geometry": {"coordinates":[6.425793,51.209213],"type":"Point"}
}