{
  "type": "Feature",
  "properties": {
    "iso:country":"DE",
    "sg:address":"Daimlerstr. 8",
    "sg:city":"Hilpoltstein",
    "sg:phone":"+49 9174/48945",
    "sg:postcode":"91161",
    "sg:province":"Bayern",
    "wof:name":"H E I K O Gebr. Heimbach Gmbh",
    "wof:placetype":"venue"
},
  "geometry": {"coordinates":[11.1803598404,49.180393219],"type":"Point"}
}