{
  "type": "Feature",
  "properties": {
    "iso:country":"DE",
    "sg:address":"Im Kirchle 13",
    "sg:city":"Kornwestheim",
    "sg:phone":"+49 7154/27777",
    "sg:postcode":"70806",
    "sg:province":"Baden-W\u00fcrttemberg",
    "wof:name":"Reimar Staiger",
    "wof:placetype":"venue"
},
  "geometry": {"coordinates":[9.1895551682,48.8705101013],"type":"Point"}
}