{
  "type": "Feature",
  "properties": {
    "iso:country":"DE",
    "sg:address":"Neufeldstr. 6",
    "sg:city":"R\u00fclzheim",
    "sg:phone":"+49 7272/2523",
    "sg:postcode":"76761",
    "sg:province":"Rheinland-Pfalz",
    "wof:name":"Josef Mrowiec Bauschlosserei",
    "wof:placetype":"venue"
},
  "geometry": {"coordinates":[8.293502,49.151661],"type":"Point"}
}