{
  "type": "Feature",
  "properties": {
    "iso:country":"DE",
    "sg:address":"Lerchenaue 3",
    "sg:city":"Neuenhagen",
    "sg:phone":"+49 3342/201100",
    "sg:postcode":"15366",
    "sg:province":"Brandenburg",
    "wof:name":"H. Bublitz",
    "wof:placetype":"venue"
},
  "geometry": {"coordinates":[13.688965,52.526894],"type":"Point"}
}