{
  "type": "Feature",
  "properties": {
    "iso:country":"DE",
    "sg:address":"Scharnhorststr. 80",
    "sg:city":"Stendal",
    "sg:postcode":"39576",
    "sg:province":"Sachsen-Anhalt",
    "wof:name":"Hgs-hausger\u00e4te Vertrieb Und Service Gmbh",
    "wof:placetype":"venue"
},
  "geometry": {"coordinates":[11.8369102478,52.6041908264],"type":"Point"}
}