{
  "type": "Feature",
  "properties": {
    "iso:country":"DE",
    "sg:address":"Berkeler Feld 28",
    "sg:city":"Hameln",
    "sg:phone":"+49 5151/66207",
    "sg:postcode":"31789",
    "sg:province":"Niedersachsen",
    "wof:name":"Burhenne",
    "wof:placetype":"venue"
},
  "geometry": {"coordinates":[9.344001,52.084778],"type":"Point"}
}