{
  "type": "Feature",
  "properties": {
    "iso:country":"DE",
    "sg:address":"Waldseestr. 31a",
    "sg:city":"Bruchk\u00f6bel",
    "sg:phone":"+49 6181/74361",
    "sg:postcode":"63486",
    "sg:province":"Hessen",
    "wof:name":"H.-j. Von Albrecht",
    "wof:placetype":"venue"
},
  "geometry": {"coordinates":[8.9305076599,50.1758842468],"type":"Point"}
}