{
  "type": "Feature",
  "properties": {
    "iso:country":"DE",
    "sg:address":"Neddener Dorfstr. 47",
    "sg:city":"Kirchlinteln",
    "sg:phone":"+49 4238/222",
    "sg:postcode":"27308",
    "sg:province":"Niedersachsen",
    "wof:name":"Willi Und Christian Oestmann",
    "wof:placetype":"venue"
},
  "geometry": {"coordinates":[9.354139328,52.8851013184],"type":"Point"}
}