{
  "type": "Feature",
  "properties": {
    "iso:country":"DE",
    "sg:address":"Bismarckstr. 9",
    "sg:city":"Bonn",
    "sg:phone":"+49 228/971970",
    "sg:postcode":"53113",
    "sg:province":"Nordrhein-Westfalen",
    "wof:name":"Infodesign Gmbh",
    "wof:placetype":"venue"
},
  "geometry": {"coordinates":[7.10037,50.72644],"type":"Point"}
}