{
  "type": "Feature",
  "properties": {
    "iso:country":"DE",
    "sg:address":"Rosmarinstr. 11 A",
    "sg:city":"Chemnitz",
    "sg:phone":"+49 371/853047",
    "sg:postcode":"09117",
    "sg:province":"Sachsen",
    "wof:name":"E.-m. Ahner",
    "wof:placetype":"venue"
},
  "geometry": {"coordinates":[12.8436403275,50.8186264038],"type":"Point"}
}