{
  "type": "Feature",
  "properties": {
    "iso:country":"DE",
    "sg:address":"Viehmarktstr. 4",
    "sg:city":"Biberach",
    "sg:phone":"+49 7351/9061",
    "sg:postcode":"88400",
    "sg:province":"Baden-W\u00fcrttemberg",
    "wof:name":"Xeller Gmbh",
    "wof:placetype":"venue"
},
  "geometry": {"coordinates":[9.7898674011,48.0971717834],"type":"Point"}
}