{
  "type": "Feature",
  "properties": {
    "iso:country":"DE",
    "sg:address":"Hermann-Muth-Str. 8",
    "sg:city":"Fulda",
    "sg:phone":"+49 661/83840",
    "sg:postcode":"36039",
    "sg:province":"Hessen",
    "wof:name":"Mgf Gutsche Gmbh & Co. Betriebs Kg",
    "wof:placetype":"venue"
},
  "geometry": {"coordinates":[9.6814098358,50.5691490173],"type":"Point"}
}