{
  "type": "Feature",
  "properties": {
    "iso:country":"DE",
    "sg:address":"Kirchstr. 24",
    "sg:city":"Breitenbrunn",
    "sg:phone":"+49 8263/218",
    "sg:postcode":"87739",
    "sg:province":"Bayern",
    "wof:name":"Landsperger Gmbh",
    "wof:placetype":"venue"
},
  "geometry": {"coordinates":[10.4011182785,48.1378822327],"type":"Point"}
}