{
  "type": "Feature",
  "properties": {
    "iso:country":"DE",
    "sg:address":"Hohenzollernstr. 45",
    "sg:city":"M\u00fcnchen",
    "sg:phone":"+49 89/398559",
    "sg:postcode":"80801",
    "sg:province":"Bayern",
    "wof:name":"Strumpftante Ingrid Staab",
    "wof:placetype":"venue"
},
  "geometry": {"coordinates":[11.576179,48.160107],"type":"Point"}
}