{
  "type": "Feature",
  "properties": {
    "iso:country":"DE",
    "sg:address":"Alteburger Str. 87",
    "sg:city":"K\u00f6ln",
    "sg:phone":"+49 221/3761497",
    "sg:postcode":"50678",
    "sg:province":"Nordrhein-Westfalen",
    "wof:name":"Tavernaki",
    "wof:placetype":"venue"
},
  "geometry": {"coordinates":[6.9630279541,50.9181938171],"type":"Point"}
}