{
  "type": "Feature",
  "properties": {
    "iso:country":"DE",
    "sg:address":"Europaallee 115",
    "sg:city":"Frechen",
    "sg:postcode":"50226",
    "sg:province":"Nordrhein-Westfalen",
    "wof:name":"Fahrenkamp & G\u00e4rtner Immo- Bilien Gmbh & Co. Kg West",
    "wof:placetype":"venue"
},
  "geometry": {"coordinates":[6.828339,50.925117],"type":"Point"}
}