{
  "type": "Feature",
  "properties": {
    "iso:country":"DE",
    "sg:address":"Halbergstr 46",
    "sg:city":"Saarbr\u00fccken",
    "sg:phone":"+49 681/967420",
    "sg:postcode":"66121",
    "sg:province":"Saarland",
    "wof:name":"Vds Gesellschaft F\u00fcr Vermessung, Digitalisierung Und Softwareentwicklung Mbh",
    "wof:placetype":"venue"
},
  "geometry": {"coordinates":[7.005566,49.232391],"type":"Point"}
}