{
  "type": "Feature",
  "properties": {
    "iso:country":"DE",
    "sg:address":"Hauptstr. 26",
    "sg:city":"Willst\u00e4tt",
    "sg:phone":"+49 7852/2272",
    "sg:postcode":"77731",
    "sg:province":"Baden-W\u00fcrttemberg",
    "wof:name":"Lichtenberg-apotheke",
    "wof:placetype":"venue"
},
  "geometry": {"coordinates":[7.891594,48.542133],"type":"Point"}
}