{
  "type": "Feature",
  "properties": {
    "iso:country":"DE",
    "sg:address":"Okrifteler Str. 47",
    "sg:city":"Frankfurt",
    "sg:phone":"+49 69/372001",
    "sg:postcode":"65931",
    "sg:province":"Hessen",
    "wof:name":"Ch. Schmitz Gmbh",
    "wof:placetype":"venue"
},
  "geometry": {"coordinates":[8.5178,50.075069],"type":"Point"}
}