{
  "type": "Feature",
  "properties": {
    "iso:country":"DE",
    "sg:address":"Habsburgerstr. 12",
    "sg:city":"Kenzingen",
    "sg:phone":"+49 7644/316",
    "sg:postcode":"79341",
    "sg:province":"Baden-W\u00fcrttemberg",
    "wof:name":"Kath. \u00f6ffentliche Bibliothek St. Laurentius",
    "wof:placetype":"venue"
},
  "geometry": {"coordinates":[7.771377,48.20063],"type":"Point"}
}