{
  "type": "Feature",
  "properties": {
    "iso:country":"DE",
    "sg:address":"Nissensgang 4",
    "sg:city":"Schuby",
    "sg:phone":"+49 4621/4384",
    "sg:postcode":"24850",
    "sg:province":"Schleswig-Holstein",
    "wof:name":"Elfriede Feldhoff",
    "wof:placetype":"venue"
},
  "geometry": {"coordinates":[9.4743423462,54.5122871399],"type":"Point"}
}