{
  "type": "Feature",
  "properties": {
    "iso:country":"DE",
    "sg:address":"Elztalstr. 20",
    "sg:city":"Buchen",
    "sg:phone":"+49 6287/1071",
    "sg:postcode":"74722",
    "sg:province":"Baden-W\u00fcrttemberg",
    "wof:name":"E. Henn",
    "wof:placetype":"venue"
},
  "geometry": {"coordinates":[9.241702,49.484703],"type":"Point"}
}