{
  "type": "Feature",
  "properties": {
    "iso:country":"DE",
    "sg:address":"Burgstr. 17",
    "sg:city":"Falkenberg",
    "sg:phone":"+49 33458/30046",
    "sg:postcode":"16259",
    "sg:province":"Brandenburg",
    "wof:name":"Andre Kosemund",
    "wof:placetype":"venue"
},
  "geometry": {"coordinates":[13.9557285309,52.80052948],"type":"Point"}
}