{
  "type": "Feature",
  "properties": {
    "iso:country":"DE",
    "sg:address":"Pfarrwinkel 2",
    "sg:city":"Oberroth",
    "sg:postcode":"89294",
    "sg:province":"Bayern",
    "wof:name":"Kath. \u00d6ffentliche B\u00fccherei",
    "wof:placetype":"venue"
},
  "geometry": {"coordinates":[10.190444,48.173504],"type":"Point"}
}