{
  "type": "Feature",
  "properties": {
    "iso:country":"DE",
    "sg:address":"Feldwieser Str.",
    "sg:city":"\u00dcbersee",
    "sg:phone":"+49 8642/331",
    "sg:postcode":"83236",
    "sg:province":"Bayern",
    "wof:name":"Sebastian Steffl",
    "wof:placetype":"venue"
},
  "geometry": {"coordinates":[12.485797,47.832249],"type":"Point"}
}