{
  "type": "Feature",
  "properties": {
    "iso:country":"DE",
    "sg:address":"Friedrichstr. 194",
    "sg:city":"Velbert",
    "sg:phone":"+49 2051/53142",
    "sg:postcode":"42551",
    "sg:province":"Nordrhein-Westfalen",
    "wof:name":"W. Bussemas",
    "wof:placetype":"venue"
},
  "geometry": {"coordinates":[7.046899,51.33955],"type":"Point"}
}