{
  "type": "Feature",
  "properties": {
    "iso:country":"DE",
    "sg:address":"Rodaer Dorfstr. 7",
    "sg:city":"Frohburg",
    "sg:postcode":"04654",
    "sg:province":"Sachsen",
    "wof:name":"U. Frohburg",
    "wof:placetype":"venue"
},
  "geometry": {"coordinates":[12.6097564697,51.0475845337],"type":"Point"}
}