{
  "type": "Feature",
  "properties": {
    "iso:country":"DE",
    "sg:address":"Hainweg 21",
    "sg:city":"W\u00f6lfersheim",
    "sg:phone":"+49 6036/981115",
    "sg:postcode":"61200",
    "sg:province":"Hessen",
    "wof:name":"M\u00e4gu Onlineshop",
    "wof:placetype":"venue"
},
  "geometry": {"coordinates":[8.812422,50.39975],"type":"Point"}
}