{
  "type": "Feature",
  "properties": {
    "iso:country":"DE",
    "sg:address":"Industriestr",
    "sg:city":"Pfaffschwende",
    "sg:phone":"+49 36082/4360",
    "sg:postcode":"37308",
    "sg:province":"Th\u00fcringen",
    "wof:name":"Comet-pumpen Systemtechnik Gmbh & Co Kg",
    "wof:placetype":"venue"
},
  "geometry": {"coordinates":[10.09908,51.247799],"type":"Point"}
}