{
  "type": "Feature",
  "properties": {
    "iso:country":"DE",
    "sg:address":"Hauptstr. 81",
    "sg:city":"Sch\u00f6neck",
    "sg:phone":"+49 37464/88388",
    "sg:postcode":"08261",
    "sg:province":"Sachsen",
    "wof:name":"Stadtapotheke",
    "wof:placetype":"venue"
},
  "geometry": {"coordinates":[12.335569,50.395428],"type":"Point"}
}