{
  "type": "Feature",
  "properties": {
    "iso:country":"DE",
    "sg:address":"L\u00e4rchengartenstr. 10",
    "sg:city":"Sch\u00f6nau",
    "sg:postcode":"69250",
    "sg:province":"Baden-W\u00fcrttemberg",
    "wof:name":"Claudia Huber E. K.",
    "wof:placetype":"venue"
},
  "geometry": {"coordinates":[8.8071279526,49.4293212891],"type":"Point"}
}