{
  "type": "Feature",
  "properties": {
    "iso:country":"DE",
    "sg:address":"Garthe",
    "sg:city":"Garthe",
    "sg:phone":"+49 4473/452",
    "sg:postcode":"49685",
    "sg:province":"Niedersachsen",
    "wof:name":"A. Meyer",
    "wof:placetype":"venue"
},
  "geometry": {"coordinates":[8.213303,52.833763],"type":"Point"}
}