{
  "type": "Feature",
  "properties": {
    "iso:country":"DE",
    "sg:address":"Marktstr. 6",
    "sg:city":"Ennepetal",
    "sg:phone":"+49 2333/71574",
    "sg:postcode":"58256",
    "sg:province":"Nordrhein-Westfalen",
    "wof:name":"K. Sch\u00f6ttge",
    "wof:placetype":"venue"
},
  "geometry": {"coordinates":[7.349022,51.299076],"type":"Point"}
}