{
  "type": "Feature",
  "properties": {
    "iso:country":"DE",
    "sg:address":"Teutonenring 11",
    "sg:city":"Rangsdorf",
    "sg:postcode":"15834",
    "sg:province":"Brandenburg",
    "wof:name":"Gemeindeschwesterstation",
    "wof:placetype":"venue"
},
  "geometry": {"coordinates":[13.443324,52.291161],"type":"Point"}
}