{
  "type": "Feature",
  "properties": {
    "iso:country":"DE",
    "sg:address":"Durlacher Str. 24",
    "sg:city":"Pforzheim",
    "sg:phone":"+49 7231/351224",
    "sg:postcode":"75172",
    "sg:province":"Baden-W\u00fcrttemberg",
    "wof:name":"Traude Bischoff",
    "wof:placetype":"venue"
},
  "geometry": {"coordinates":[8.693044,48.892933],"type":"Point"}
}