{
  "type": "Feature",
  "properties": {
    "iso:country":"DE",
    "sg:address":"Provinzialstr. 45",
    "sg:city":"Datteln",
    "sg:phone":"+49 2363/71178",
    "sg:postcode":"45711",
    "sg:province":"Nordrhein-Westfalen",
    "wof:name":"Hermes-m\u00f6belmarkt Gmbh",
    "wof:placetype":"venue"
},
  "geometry": {"coordinates":[7.323637,51.618404],"type":"Point"}
}