{
  "type": "Feature",
  "properties": {
    "iso:country":"DE",
    "sg:address":"Passauer Str. 21",
    "sg:city":"Pocking",
    "sg:phone":"+49 8531/1603",
    "sg:postcode":"94060",
    "sg:province":"Bayern",
    "wof:name":"Jaro Design Gmbh",
    "wof:placetype":"venue"
},
  "geometry": {"coordinates":[13.31295681,48.4041366577],"type":"Point"}
}