{
  "type": "Feature",
  "properties": {
    "iso:country":"DE",
    "sg:address":"Am Ro\u00dftor 8",
    "sg:city":"Wassenberg",
    "sg:phone":"+49 2432/20266",
    "sg:postcode":"41849",
    "sg:province":"Nordrhein-Westfalen",
    "wof:name":"Eiscafe Venezia",
    "wof:placetype":"venue"
},
  "geometry": {"coordinates":[6.154961,51.100224],"type":"Point"}
}