{
  "type": "Feature",
  "properties": {
    "iso:country":"DE",
    "sg:address":"M\u00fchlenfeldstr. 40",
    "sg:city":"Wesel",
    "sg:phone":"+49 2859/380",
    "sg:postcode":"46487",
    "sg:province":"Nordrhein-Westfalen",
    "wof:name":"Theodor Amerkamp",
    "wof:placetype":"venue"
},
  "geometry": {"coordinates":[6.4978342056,51.679851532],"type":"Point"}
}