{
  "type": "Feature",
  "properties": {
    "iso:country":"DE",
    "sg:address":"Aum\u00fchle 1",
    "sg:city":"Kollnburg",
    "sg:phone":"+49 9942/1255",
    "sg:postcode":"94262",
    "sg:province":"Bayern",
    "wof:name":"Otto Fischl X",
    "wof:placetype":"venue"
},
  "geometry": {"coordinates":[12.8848896027,49.0471725464],"type":"Point"}
}