{
  "type": "Feature",
  "properties": {
    "iso:country":"DE",
    "sg:city":"Baden Baden",
    "sg:phone":"+49 4972/235663",
    "sg:postcode":"76532",
    "sg:province":"Baden-W\u00fcrttemberg",
    "wof:name":"Stadtsparkasse Neuweier",
    "wof:placetype":"venue"
},
  "geometry": {"coordinates":[8.19587,48.808556],"type":"Point"}
}