{
  "type": "Feature",
  "properties": {
    "iso:country":"DE",
    "sg:address":"Dorfstr. 20",
    "sg:city":"Selbitz",
    "sg:phone":"+49 34928/20478",
    "sg:postcode":"06773",
    "sg:province":"Sachsen-Anhalt",
    "wof:name":"Hannelore Schellhase",
    "wof:placetype":"venue"
},
  "geometry": {"coordinates":[12.5311717987,51.8147468567],"type":"Point"}
}