{
  "type": "Feature",
  "properties": {
    "iso:country":"DE",
    "sg:address":"Dorfstr. 56",
    "sg:city":"Albersdorf",
    "sg:phone":"+49 36692/22649",
    "sg:postcode":"07646",
    "sg:province":"Th\u00fcringen",
    "wof:name":"A. Hartmann",
    "wof:placetype":"venue"
},
  "geometry": {"coordinates":[11.772425,50.904827],"type":"Point"}
}