{
  "type": "Feature",
  "properties": {
    "iso:country":"DE",
    "sg:address":"Postfach 1765",
    "sg:city":"Soest",
    "sg:phone":"+49 40/6969790",
    "sg:postcode":"59477",
    "sg:province":"Nordrhein-Westfalen",
    "wof:name":"Legrand Gmbh",
    "wof:placetype":"venue"
},
  "geometry": {"coordinates":[8.1082897186,51.5700492859],"type":"Point"}
}