{
  "type": "Feature",
  "properties": {
    "iso:country":"DE",
    "sg:address":"Bahnhofstr. 5",
    "sg:city":"Bruchk\u00f6bel",
    "sg:phone":"+49 6181/71004",
    "sg:postcode":"63486",
    "sg:province":"Hessen",
    "wof:name":"Primus Gold Edelmetallvertrieb Gmbh",
    "wof:placetype":"venue"
},
  "geometry": {"coordinates":[8.923551,50.180233],"type":"Point"}
}