{
  "type": "Feature",
  "properties": {
    "iso:country":"DE",
    "sg:address":"Kirchstr. 17",
    "sg:city":"Wittmund",
    "sg:phone":"+49 4462/7533",
    "sg:postcode":"26409",
    "sg:province":"Niedersachsen",
    "wof:name":"Gastst\u00e4tte Eimer",
    "wof:placetype":"venue"
},
  "geometry": {"coordinates":[7.7811841965,53.5757217407],"type":"Point"}
}