{
  "type": "Feature",
  "properties": {
    "iso:country":"DE",
    "sg:address":"Landsberger Str. 29",
    "sg:city":"Augsburg",
    "sg:phone":"+49 821/8154858",
    "sg:postcode":"86179",
    "sg:province":"Bayern",
    "wof:name":"Cafe Adria",
    "wof:placetype":"venue"
},
  "geometry": {"coordinates":[10.907753,48.313046],"type":"Point"}
}