{
  "type": "Feature",
  "properties": {
    "iso:country":"DE",
    "sg:address":"Irlerhof 14",
    "sg:city":"Burscheid",
    "sg:phone":"+49 2174/8240",
    "sg:postcode":"51399",
    "sg:province":"Nordrhein-Westfalen",
    "wof:name":"Bruno Welisch",
    "wof:placetype":"venue"
},
  "geometry": {"coordinates":[7.099755764,51.0903816223],"type":"Point"}
}