{
  "type": "Feature",
  "properties": {
    "iso:country":"DE",
    "sg:address":"Feldrain 1 a",
    "sg:city":"Itzehoe",
    "sg:phone":"+49 4821/82193",
    "sg:postcode":"25524",
    "sg:province":"Schleswig-Holstein",
    "wof:name":"Horst Voigt",
    "wof:placetype":"venue"
},
  "geometry": {"coordinates":[9.497369,53.907475],"type":"Point"}
}