{
  "type": "Feature",
  "properties": {
    "iso:country":"DE",
    "sg:address":"M\u00e4rkisches Ufer 12",
    "sg:city":"Berlin",
    "sg:phone":"+49 30/2789640",
    "sg:postcode":"10179",
    "sg:province":"Berlin",
    "wof:name":"Markt & Daten",
    "wof:placetype":"venue"
},
  "geometry": {"coordinates":[13.4095134735,52.5125923157],"type":"Point"}
}