{
  "type": "Feature",
  "properties": {
    "iso:country":"DE",
    "sg:address":"Brunckstr 15",
    "sg:city":"Speyer",
    "sg:phone":"+49 6232/5380",
    "sg:postcode":"67346",
    "sg:province":"Rheinland-Pfalz",
    "wof:name":"Mann + Hummel Gmbh",
    "wof:placetype":"venue"
},
  "geometry": {"coordinates":[8.421183,49.33812],"type":"Point"}
}