{
  "type": "Feature",
  "properties": {
    "iso:country":"DE",
    "sg:address":"Wilhelm-Braun-Str. 3",
    "sg:city":"Weingarten",
    "sg:phone":"+49 751/556711",
    "sg:postcode":"88250",
    "sg:province":"Baden-W\u00fcrttemberg",
    "wof:name":"Gr\u00fcninger Gmbh & Co. Kg",
    "wof:placetype":"venue"
},
  "geometry": {"coordinates":[9.6526422501,47.8107910156],"type":"Point"}
}