{
  "type": "Feature",
  "properties": {
    "iso:country":"DE",
    "sg:address":"Badstr. 12",
    "sg:city":"Albbruck",
    "sg:phone":"+49 7753/2907",
    "sg:postcode":"79774",
    "sg:province":"Baden-W\u00fcrttemberg",
    "wof:name":"Schwimmbad",
    "wof:placetype":"venue"
},
  "geometry": {"coordinates":[8.1391687393,47.5972366333],"type":"Point"}
}