{
  "type": "Feature",
  "properties": {
    "iso:country":"DE",
    "sg:address":"Gartenstr. 10",
    "sg:city":"Ehningen",
    "sg:phone":"+49 7034/30580",
    "sg:postcode":"71139",
    "sg:province":"Baden-W\u00fcrttemberg",
    "wof:name":"Gerhard Vogtmann",
    "wof:placetype":"venue"
},
  "geometry": {"coordinates":[8.9430561066,48.659614563],"type":"Point"}
}