{
  "type": "Feature",
  "properties": {
    "iso:country":"DE",
    "sg:address":"Lindauer Str. 1",
    "sg:city":"Loburg",
    "sg:phone":"+49 39245/2625",
    "sg:postcode":"39279",
    "sg:province":"Sachsen-Anhalt",
    "wof:name":"Kooperation Schweinemast Gmbh Kreis Zerbst",
    "wof:placetype":"venue"
},
  "geometry": {"coordinates":[12.075863,52.087795],"type":"Point"}
}