{
  "type": "Feature",
  "properties": {
    "iso:country":"DE",
    "sg:address":"Trierer Str. 10",
    "sg:city":"K\u00f6ln",
    "sg:phone":"+49 221/329177",
    "sg:postcode":"50676",
    "sg:province":"Nordrhein-Westfalen",
    "wof:name":"Billard Cafe",
    "wof:placetype":"venue"
},
  "geometry": {"coordinates":[6.945954,50.927879],"type":"Point"}
}