{
  "type": "Feature",
  "properties": {
    "iso:country":"DE",
    "sg:address":"Ostwall 99",
    "sg:city":"Krefeld",
    "sg:phone":"+49 2151/66903",
    "sg:postcode":"47798",
    "sg:province":"Nordrhein-Westfalen",
    "wof:name":"Malu",
    "wof:placetype":"venue"
},
  "geometry": {"coordinates":[6.5675368309,51.3307113647],"type":"Point"}
}