{
  "type": "Feature",
  "properties": {
    "iso:country":"DE",
    "sg:address":"Lochm\u00fchlenweg 2",
    "sg:city":"Friedrichsdorf",
    "sg:phone":"+49 6172/74003",
    "sg:postcode":"61381",
    "sg:province":"Hessen",
    "wof:name":"Alwine Ickert",
    "wof:placetype":"venue"
},
  "geometry": {"coordinates":[8.6297626495,50.2657470703],"type":"Point"}
}