{
  "type": "Feature",
  "properties": {
    "iso:country":"DE",
    "sg:address":"Erdinger Str. 17",
    "sg:city":"W\u00f6rth",
    "sg:phone":"+49 8122/20594",
    "sg:postcode":"85457",
    "sg:province":"Bayern",
    "wof:name":"Inge Und G\u00fcnther K\u00f6lbl",
    "wof:placetype":"venue"
},
  "geometry": {"coordinates":[11.9366483688,48.2437782288],"type":"Point"}
}