{
  "type": "Feature",
  "properties": {
    "iso:country":"DE",
    "sg:address":"Oldentruper Str. 181a",
    "sg:city":"Bielefeld",
    "sg:phone":"+49 521/296900",
    "sg:postcode":"33605",
    "sg:province":"Nordrhein-Westfalen",
    "wof:name":"Akasya Gmbh",
    "wof:placetype":"venue"
},
  "geometry": {"coordinates":[8.5794868469,52.0111885071],"type":"Point"}
}