{
  "type": "Feature",
  "properties": {
    "iso:country":"DE",
    "sg:address":"Rathausstr. 1",
    "sg:city":"Schwandorf",
    "sg:phone":"+49 9431/41553",
    "sg:postcode":"92421",
    "sg:province":"Bayern",
    "wof:name":"Heimatmuseum Schwandorf",
    "wof:placetype":"venue"
},
  "geometry": {"coordinates":[12.105849,49.329742],"type":"Point"}
}