{
  "type": "Feature",
  "properties": {
    "iso:country":"DE",
    "sg:city":"Ferdinandshof",
    "sg:postcode":"17379",
    "sg:province":"Mecklenburg-Vorpommern",
    "wof:name":"Arbeitsf\u00f6rderungs- Besch\u00e4ftigungs- Und Struktur-",
    "wof:placetype":"venue"
},
  "geometry": {"coordinates":[13.888791,53.664211],"type":"Point"}
}