{
  "type": "Feature",
  "properties": {
    "iso:country":"DE",
    "sg:address":"Hohe Str. 11",
    "sg:city":"Wanzleben",
    "sg:phone":"+49 39209/42179",
    "sg:postcode":"39164",
    "sg:province":"Sachsen-Anhalt",
    "wof:name":"Edeltraut Schramm",
    "wof:placetype":"venue"
},
  "geometry": {"coordinates":[11.435297966,52.0615310669],"type":"Point"}
}