{
  "type": "Feature",
  "properties": {
    "iso:country":"DE",
    "sg:address":"Am Annenried 3",
    "sg:city":"Behringen",
    "sg:phone":"+49 36254/71637",
    "sg:postcode":"99947",
    "sg:province":"Th\u00fcringen",
    "wof:name":"Dieter St\u00fcber",
    "wof:placetype":"venue"
},
  "geometry": {"coordinates":[10.507178,51.023254],"type":"Point"}
}