{
  "type": "Feature",
  "properties": {
    "iso:country":"DE",
    "sg:address":"Keppelstr. 19",
    "sg:city":"Kranenburg",
    "sg:phone":"+49 2826/5670",
    "sg:postcode":"47559",
    "sg:province":"Nordrhein-Westfalen",
    "wof:name":"W. Krebbers Hebamme",
    "wof:placetype":"venue"
},
  "geometry": {"coordinates":[6.014238,51.786411],"type":"Point"}
}