{
  "type": "Feature",
  "properties": {
    "iso:country":"DE",
    "sg:address":"Im Heienbach 55",
    "sg:city":"Rotenburg",
    "sg:phone":"+49 6623/2355",
    "sg:postcode":"36199",
    "sg:province":"Hessen",
    "wof:name":"Hotel G. Berg",
    "wof:placetype":"venue"
},
  "geometry": {"coordinates":[9.7431077957,51.0027236938],"type":"Point"}
}