{
  "type": "Feature",
  "properties": {
    "iso:country":"DE",
    "sg:address":"Bottroper Str. 1",
    "sg:city":"Bottrop",
    "sg:phone":"+49 2045/960278",
    "sg:postcode":"46244",
    "sg:province":"Nordrhein-Westfalen",
    "wof:name":"Plus-warenhandels Gmbh & Co. Ohg",
    "wof:placetype":"venue"
},
  "geometry": {"coordinates":[6.9139509201,51.5892944336],"type":"Point"}
}