{
  "type": "Feature",
  "properties": {
    "iso:country":"DE",
    "sg:address":"Julius-R\u00fctgers-Str. 12",
    "sg:city":"Erkner",
    "sg:postcode":"15537",
    "sg:province":"Brandenburg",
    "wof:name":"Tischlerei R. Busse Gmbh",
    "wof:placetype":"venue"
},
  "geometry": {"coordinates":[13.75492,52.430061],"type":"Point"}
}