{
  "type": "Feature",
  "properties": {
    "iso:country":"DE",
    "sg:address":"Horstring 1-3",
    "sg:city":"Kandel",
    "sg:phone":"+49 7275/95660",
    "sg:postcode":"76870",
    "sg:province":"Rheinland-Pfalz",
    "wof:name":"Bad-rudorf Spedition Gmbh",
    "wof:placetype":"venue"
},
  "geometry": {"coordinates":[8.175579071,49.0987052917],"type":"Point"}
}