{
  "type": "Feature",
  "properties": {
    "iso:country":"DE",
    "sg:address":"Marrensdamm 7",
    "sg:city":"Flensburg",
    "sg:phone":"+49 461/38616",
    "sg:postcode":"24944",
    "sg:province":"Schleswig-Holstein",
    "wof:name":"Co Op-frischmarkt",
    "wof:placetype":"venue"
},
  "geometry": {"coordinates":[9.4739103317,54.8157081604],"type":"Point"}
}