{
  "type": "Feature",
  "properties": {
    "iso:country":"DE",
    "sg:address":"Deutsche Gasse 34",
    "sg:city":"Mannheim",
    "sg:phone":"+49 621/7888322",
    "sg:postcode":"68307",
    "sg:province":"Baden-W\u00fcrttemberg",
    "wof:name":"Hotel Badischer Hof",
    "wof:placetype":"venue"
},
  "geometry": {"coordinates":[8.443901062,49.5439872742],"type":"Point"}
}