{
  "type": "Feature",
  "properties": {
    "iso:country":"DE",
    "sg:address":"Frankfurter Str. 6",
    "sg:city":"Weiterstadt",
    "sg:phone":"+49 6150/53369",
    "sg:postcode":"64331",
    "sg:province":"Hessen",
    "wof:name":"Georg Hamm",
    "wof:placetype":"venue"
},
  "geometry": {"coordinates":[8.594816,49.939323],"type":"Point"}
}