{
  "type": "Feature",
  "properties": {
    "iso:country":"DE",
    "sg:address":"Lindenstr 33",
    "sg:city":"Belm",
    "sg:phone":"+49 5406/899181",
    "sg:postcode":"49191",
    "sg:province":"Niedersachsen",
    "wof:name":"N.i.p. Vertrieb",
    "wof:placetype":"venue"
},
  "geometry": {"coordinates":[8.134681,52.306076],"type":"Point"}
}