{
  "type": "Feature",
  "properties": {
    "iso:country":"DE",
    "sg:address":"B\u00fctzower Str. 13 B",
    "sg:city":"Rostock",
    "sg:phone":"+49 381/7611243",
    "sg:postcode":"18109",
    "sg:province":"Mecklenburg-Vorpommern",
    "wof:name":"Elisabeth Grimm Rechtsanw\u00e4ltin",
    "wof:placetype":"venue"
},
  "geometry": {"coordinates":[12.063129425,54.1559448242],"type":"Point"}
}