{
  "type": "Feature",
  "properties": {
    "iso:country":"DE",
    "sg:address":"Wellum-Weg 31",
    "sg:city":"Friedr-Wilh-L\u00fcbke-Koog",
    "sg:postcode":"25924",
    "sg:province":"Schleswig-Holstein",
    "wof:name":"L\u00fcbke-koog Nord Verwaltungs Gmbh",
    "wof:placetype":"venue"
},
  "geometry": {"coordinates":[4.8108201027,52.4619407654],"type":"Point"}
}