{
  "type": "Feature",
  "properties": {
    "iso:country":"DE",
    "sg:address":"Auf dem Niederberg 13",
    "sg:city":"Sankt Augustin",
    "sg:postcode":"53757",
    "sg:province":"Nordrhein-Westfalen",
    "wof:name":"Vbp Verlag F\u00fcr Betriebliche Praxis Gmbh",
    "wof:placetype":"venue"
},
  "geometry": {"coordinates":[7.1806521416,50.7550735474],"type":"Point"}
}