{
  "type": "Feature",
  "properties": {
    "iso:country":"DE",
    "sg:address":"Holzdamm 53",
    "sg:city":"Hamburg",
    "sg:phone":"+49 40/245962",
    "sg:postcode":"20099",
    "sg:province":"Hamburg",
    "wof:name":"Ungarn Tours Ibusz",
    "wof:placetype":"venue"
},
  "geometry": {"coordinates":[10.0064668655,53.555355072],"type":"Point"}
}