{
  "type": "Feature",
  "properties": {
    "iso:country":"DE",
    "sg:address":"Robert-Schr\u00f6der-Str. 22",
    "sg:city":"Neumark",
    "sg:phone":"+49 37600/722",
    "sg:postcode":"08496",
    "sg:province":"Sachsen",
    "wof:name":"L. Meinhold",
    "wof:placetype":"venue"
},
  "geometry": {"coordinates":[12.350683,50.656937],"type":"Point"}
}