{
  "type": "Feature",
  "properties": {
    "iso:country":"DE",
    "sg:address":"Wagnerstr. 8",
    "sg:city":"Wildau",
    "sg:phone":"+49 3375/554411",
    "sg:postcode":"15745",
    "sg:province":"Brandenburg",
    "wof:name":"Erzeugnisvertrieb Kw - Verteilung Von Drucksachen",
    "wof:placetype":"venue"
},
  "geometry": {"coordinates":[13.619131,52.323303],"type":"Point"}
}