{
  "type": "Feature",
  "properties": {
    "iso:country":"DE",
    "sg:address":"M\u00fchlstr. 1",
    "sg:city":"Holzheim",
    "sg:phone":"+49 6432/63746",
    "sg:postcode":"65558",
    "sg:province":"Rheinland-Pfalz",
    "wof:name":"S. Bruhn-hahn W. Hahn & Partner",
    "wof:placetype":"venue"
},
  "geometry": {"coordinates":[8.0483541489,50.3509979248],"type":"Point"}
}