{
  "type": "Feature",
  "properties": {
    "iso:country":"DE",
    "sg:address":"Dorfstrasse 33a",
    "sg:city":"Possenhain",
    "sg:postcode":"06618",
    "sg:province":"Sachsen-Anhalt",
    "wof:name":"Maschinen & Service Ziemer Gmbh",
    "wof:placetype":"venue"
},
  "geometry": {"coordinates":[11.8986272812,51.1592979431],"type":"Point"}
}