{
  "type": "Feature",
  "properties": {
    "iso:country":"DE",
    "sg:address":"Georg-Strobel-Str. 63",
    "sg:city":"N\u00fcrnberg",
    "sg:phone":"+49 911/553214",
    "sg:postcode":"90489",
    "sg:province":"Bayern",
    "wof:name":"Rollo-beck Inh. Manfred N\u00e4rrisch",
    "wof:placetype":"venue"
},
  "geometry": {"coordinates":[11.099078,49.456898],"type":"Point"}
}