{
  "type": "Feature",
  "properties": {
    "iso:country":"DE",
    "sg:address":"B\u00fcnder Str. 220",
    "sg:city":"Spenge",
    "sg:phone":"+49 5225/2672",
    "sg:postcode":"32139",
    "sg:province":"Nordrhein-Westfalen",
    "wof:name":"August Menke",
    "wof:placetype":"venue"
},
  "geometry": {"coordinates":[8.5046892166,52.1662063599],"type":"Point"}
}