{
  "type": "Feature",
  "properties": {
    "iso:country":"DE",
    "sg:address":"Blumenberg 43",
    "sg:city":"Oschatz",
    "sg:phone":"+49 3435/927754",
    "sg:postcode":"04758",
    "sg:province":"Sachsen",
    "wof:name":"Andreas Ritter",
    "wof:placetype":"venue"
},
  "geometry": {"coordinates":[13.1189479828,51.2902908325],"type":"Point"}
}