{
  "type": "Feature",
  "properties": {
    "iso:country":"DE",
    "sg:address":"Zum Gogericht 15d",
    "sg:city":"Emstek",
    "sg:postcode":"49685",
    "sg:province":"Niedersachsen",
    "wof:name":"V. T\u00fcmer Transport Gmbh",
    "wof:placetype":"venue"
},
  "geometry": {"coordinates":[8.1551647186,52.8344841003],"type":"Point"}
}