{
  "type": "Feature",
  "properties": {
    "iso:country":"DE",
    "sg:address":"Industriestr. 10",
    "sg:city":"Oberstenfeld",
    "sg:phone":"+49 7062/3123",
    "sg:postcode":"71720",
    "sg:province":"Baden-W\u00fcrttemberg",
    "wof:name":"Werner Hansen",
    "wof:placetype":"venue"
},
  "geometry": {"coordinates":[9.327,49.020901],"type":"Point"}
}