{
  "type": "Feature",
  "properties": {
    "iso:country":"DE",
    "sg:address":"Hafenstr. 31",
    "sg:city":"Bergkamen",
    "sg:postcode":"59192",
    "sg:province":"Nordrhein-Westfalen",
    "wof:name":"Htw-yachting Gmbh",
    "wof:placetype":"venue"
},
  "geometry": {"coordinates":[7.5737199783,51.6208305359],"type":"Point"}
}