{
  "type": "Feature",
  "properties": {
    "iso:country":"DE",
    "sg:address":"Weinbergstr. 24",
    "sg:city":"Burtenbach",
    "sg:phone":"+49 8285/1211",
    "sg:postcode":"89349",
    "sg:province":"Bayern",
    "wof:name":"M. Starzinsky Fotofachgesch\u00e4ft",
    "wof:placetype":"venue"
},
  "geometry": {"coordinates":[10.4550886154,48.3437995911],"type":"Point"}
}