{
  "type": "Feature",
  "properties": {
    "iso:country":"DE",
    "sg:address":"Redtenbacher Str. 5",
    "sg:city":"Pforzheim",
    "sg:phone":"+49 4972/3195960",
    "sg:postcode":"75177",
    "sg:province":"Baden-W\u00fcrttemberg",
    "wof:name":"Funk & Eberle Inh J\u00dcrgen Funk",
    "wof:placetype":"venue"
},
  "geometry": {"coordinates":[8.7102556229,48.8991317749],"type":"Point"}
}