{
  "type": "Feature",
  "properties": {
    "iso:country":"DE",
    "sg:address":"C\u00e4cilienstr. 11",
    "sg:city":"Hamburg",
    "sg:phone":"+49 40/2704734",
    "sg:postcode":"22301",
    "sg:province":"Hamburg",
    "wof:name":"Bernd Holldorff",
    "wof:placetype":"venue"
},
  "geometry": {"coordinates":[10.0041303635,53.5865783691],"type":"Point"}
}