{
  "type": "Feature",
  "properties": {
    "iso:country":"DE",
    "sg:address":"N\u00fcrnberger Str. 29 a",
    "sg:city":"Zirndorf",
    "sg:phone":"+49 911/9603150",
    "sg:postcode":"90513",
    "sg:province":"Bayern",
    "wof:name":"Thomas Cook Reiseb\u00fcro",
    "wof:placetype":"venue"
},
  "geometry": {"coordinates":[10.9608983994,49.4403991699],"type":"Point"}
}