{
  "type": "Feature",
  "properties": {
    "iso:country":"DE",
    "sg:address":"Bahnhofsallee 36",
    "sg:city":"Coesfeld",
    "sg:phone":"+49 2546/9100",
    "sg:postcode":"48653",
    "sg:province":"Nordrhein-Westfalen",
    "wof:name":"Voss Verwaltungs- Und Beteiligungs Gmbh & Co. Kg",
    "wof:placetype":"venue"
},
  "geometry": {"coordinates":[7.16786623,51.9401855469],"type":"Point"}
}