{
  "type": "Feature",
  "properties": {
    "iso:country":"DE",
    "sg:address":"Heeder Dorfstr. 45",
    "sg:city":"Diepholz",
    "sg:phone":"+49 5441/2998",
    "sg:postcode":"49356",
    "sg:province":"Niedersachsen",
    "wof:name":"Wilhelm Strangmeyer",
    "wof:placetype":"venue"
},
  "geometry": {"coordinates":[8.381422,52.623749],"type":"Point"}
}