{
  "type": "Feature",
  "properties": {
    "iso:country":"DE",
    "sg:address":"Lohstr. 32",
    "sg:city":"Hemer",
    "sg:phone":"+49 40/7005103",
    "sg:postcode":"58675",
    "sg:province":"Nordrhein-Westfalen",
    "wof:name":"Hermann C Cuhls Inh W Cuhls",
    "wof:placetype":"venue"
},
  "geometry": {"coordinates":[9.7800359726,53.4609222412],"type":"Point"}
}