{
  "type": "Feature",
  "properties": {
    "iso:country":"DE",
    "sg:address":"Erckensstr. 42",
    "sg:city":"Aachen",
    "sg:phone":"+49 241/61709",
    "sg:postcode":"52066",
    "sg:province":"Nordrhein-Westfalen",
    "wof:name":"W. Hirtz",
    "wof:placetype":"venue"
},
  "geometry": {"coordinates":[6.0929031372,50.7557754517],"type":"Point"}
}