{
  "type": "Feature",
  "properties": {
    "iso:country":"DE",
    "sg:address":"S\u00fcdring 26",
    "sg:city":"Emsdetten",
    "sg:phone":"+49 2572/920280",
    "sg:postcode":"48282",
    "sg:province":"Nordrhein-Westfalen",
    "wof:name":"Schallwand-vermietgesellschaft F\u00fcr Veranstaltungstechnik Gmbh",
    "wof:placetype":"venue"
},
  "geometry": {"coordinates":[7.5453281403,52.1547813416],"type":"Point"}
}