{
  "type": "Feature",
  "properties": {
    "iso:country":"DE",
    "sg:address":"Bonhoefferweg 6",
    "sg:city":"Weinheim",
    "sg:phone":"+49 6201/13760",
    "sg:postcode":"69469",
    "sg:province":"Baden-W\u00fcrttemberg",
    "wof:name":"Detlev Bachmann Architekt",
    "wof:placetype":"venue"
},
  "geometry": {"coordinates":[8.656454,49.544685],"type":"Point"}
}