{
  "type": "Feature",
  "properties": {
    "iso:country":"DE",
    "sg:address":"Marienplatz 2-6::",
    "sg:city":"Weilheim",
    "sg:phone":"+49 881/6410",
    "sg:postcode":"82360",
    "sg:province":"Baden-W\u00fcrttemberg",
    "wof:name":"Vereinigte Sparkassen Im Landkreis Weilheim/iob",
    "wof:placetype":"venue"
},
  "geometry": {"coordinates":[11.1422,47.840912],"type":"Point"}
}