{
  "type": "Feature",
  "properties": {
    "iso:country":"DE",
    "sg:address":"Buhlenweg 34a",
    "sg:city":"Konstanz",
    "sg:phone":"+49 7531/78581",
    "sg:postcode":"78467",
    "sg:province":"Baden-W\u00fcrttemberg",
    "wof:name":"P. Aich",
    "wof:placetype":"venue"
},
  "geometry": {"coordinates":[9.1617250443,47.6870536804],"type":"Point"}
}