{
  "type": "Feature",
  "properties": {
    "iso:country":"DE",
    "sg:address":"In der Gerste 4",
    "sg:city":"Ludwigsburg",
    "sg:phone":"+49 7141/462237",
    "sg:postcode":"71636",
    "sg:province":"Baden-W\u00fcrttemberg",
    "wof:name":"Isp Individuelle Software Produkte Gmbh",
    "wof:placetype":"venue"
},
  "geometry": {"coordinates":[9.156124115,48.8887023926],"type":"Point"}
}