{
  "type": "Feature",
  "properties": {
    "iso:country":"DE",
    "sg:address":"Erlanger Str. 21",
    "sg:city":"Uttenreuth",
    "sg:phone":"+49 9131/51138",
    "sg:postcode":"91080",
    "sg:province":"Bayern",
    "wof:name":"Emil Und Herbert Walter",
    "wof:placetype":"venue"
},
  "geometry": {"coordinates":[11.070666,49.596439],"type":"Point"}
}