{
  "type": "Feature",
  "properties": {
    "iso:country":"DE",
    "sg:address":"Blumenstr. 19",
    "sg:city":"Auerbach",
    "sg:phone":"+49 3744/213565",
    "sg:postcode":"08209",
    "sg:province":"Sachsen",
    "wof:name":"Karl-heinz Schr\u00f6der",
    "wof:placetype":"venue"
},
  "geometry": {"coordinates":[12.401601,50.50499],"type":"Point"}
}