{
  "type": "Feature",
  "properties": {
    "iso:country":"DE",
    "sg:address":"Saarlandstr. 5",
    "sg:city":"Rheinzabern",
    "sg:phone":"+49 7272/92210",
    "sg:postcode":"76764",
    "sg:province":"Rheinland-Pfalz",
    "wof:name":"C\u00e4cilie Kiefer",
    "wof:placetype":"venue"
},
  "geometry": {"coordinates":[8.2698659897,49.1156463623],"type":"Point"}
}