{
  "type": "Feature",
  "properties": {
    "iso:country":"DE",
    "sg:address":"Kr\u00fcgersdorfer Chaussee 9",
    "sg:city":"Beeskow",
    "sg:phone":"+49 3366/26141",
    "sg:postcode":"15848",
    "sg:province":"Brandenburg",
    "wof:name":"Faa Bildungsgesellschaft Mbh Zwgndl. Beeskow",
    "wof:placetype":"venue"
},
  "geometry": {"coordinates":[14.233659,52.165409],"type":"Point"}
}