{
  "type": "Feature",
  "properties": {
    "iso:country":"DE",
    "sg:address":"Im Breitspiel 26",
    "sg:city":"Heidelberg",
    "sg:phone":"+49 6221/347600",
    "sg:postcode":"69126",
    "sg:province":"Baden-W\u00fcrttemberg",
    "wof:name":"Oss Consulting Gmbh",
    "wof:placetype":"venue"
},
  "geometry": {"coordinates":[8.686539,49.36343],"type":"Point"}
}