{
  "type": "Feature",
  "properties": {
    "iso:country":"DE",
    "sg:address":"Sch\u00f6nbronner Weg 7",
    "sg:city":"Ehingen",
    "sg:phone":"+49 7391/4250",
    "sg:postcode":"89584",
    "sg:province":"Baden-W\u00fcrttemberg",
    "wof:name":"Rainer Wolf",
    "wof:placetype":"venue"
},
  "geometry": {"coordinates":[9.7295808792,48.287071228],"type":"Point"}
}