{
  "type": "Feature",
  "properties": {
    "iso:country":"DE",
    "sg:address":"Hoopter Elbdeich 70",
    "sg:city":"Winsen",
    "sg:phone":"+49 4171/62969",
    "sg:postcode":"21423",
    "sg:province":"Niedersachsen",
    "wof:name":"Heinrich Giese",
    "wof:placetype":"venue"
},
  "geometry": {"coordinates":[10.16008,53.399075],"type":"Point"}
}