{
  "type": "Feature",
  "properties": {
    "iso:country":"DE",
    "sg:address":"Andersenstr. 5",
    "sg:city":"Albstadt",
    "sg:postcode":"72458",
    "sg:province":"Baden-W\u00fcrttemberg",
    "wof:name":"Textilunion Gmbh",
    "wof:placetype":"venue"
},
  "geometry": {"coordinates":[8.991673,48.214233],"type":"Point"}
}