{
  "type": "Feature",
  "properties": {
    "iso:country":"DE",
    "sg:address":"St. Germanshof 8",
    "sg:city":"Bobenthal",
    "sg:phone":"+49 6394/993088",
    "sg:postcode":"76891",
    "sg:province":"Rheinland-Pfalz",
    "wof:name":"A. H\u00f6hl Parkett",
    "wof:placetype":"venue"
},
  "geometry": {"coordinates":[7.9035601616,49.0456886292],"type":"Point"}
}