{
  "type": "Feature",
  "properties": {
    "iso:country":"DE",
    "sg:address":"Leineweberstr. 49",
    "sg:city":"M\u00fclheim",
    "sg:phone":"+49 208/475114",
    "sg:postcode":"45468",
    "sg:province":"Nordrhein-Westfalen",
    "wof:name":"Peter Wiedemann",
    "wof:placetype":"venue"
},
  "geometry": {"coordinates":[6.881918,51.427479],"type":"Point"}
}