{
  "type": "Feature",
  "properties": {
    "iso:country":"DE",
    "sg:address":"Wendtstr. 19",
    "sg:city":"Karlsruhe",
    "sg:phone":"+49 721/985800",
    "sg:postcode":"76185",
    "sg:province":"Baden-W\u00fcrttemberg",
    "wof:name":"Arcadis Deutschland Gmbh",
    "wof:placetype":"venue"
},
  "geometry": {"coordinates":[8.3729562759,49.0114173889],"type":"Point"}
}