{
  "type": "Feature",
  "properties": {
    "iso:country":"DE",
    "sg:address":"Dortmunder Str. 139",
    "sg:city":"Waltrop",
    "sg:phone":"+49 2309/77410",
    "sg:postcode":"45731",
    "sg:province":"Nordrhein-Westfalen",
    "wof:name":"Eiscafe Rolf Jordan",
    "wof:placetype":"venue"
},
  "geometry": {"coordinates":[7.412882,51.623428],"type":"Point"}
}