{
  "type": "Feature",
  "properties": {
    "iso:country":"DE",
    "sg:address":"Athenslebener Weg 30",
    "sg:city":"Sta\u00dffurt",
    "sg:phone":"+49 3925/625523",
    "sg:postcode":"39418",
    "sg:province":"Sachsen-Anhalt",
    "wof:name":"Pension Brigitte M\u00fcller",
    "wof:placetype":"venue"
},
  "geometry": {"coordinates":[11.5775413513,51.8613166809],"type":"Point"}
}