{
  "type": "Feature",
  "properties": {
    "iso:country":"DE",
    "sg:address":"Beelter Weg 12",
    "sg:city":"Hildesheim",
    "sg:phone":"+49 5121/46832",
    "sg:postcode":"31137",
    "sg:province":"Niedersachsen",
    "wof:name":"Klaus Droste Versicherungen",
    "wof:placetype":"venue"
},
  "geometry": {"coordinates":[9.911108017,52.1674919128],"type":"Point"}
}