{
  "type": "Feature",
  "properties": {
    "iso:country":"DE",
    "sg:address":"Lerchenhaubenweg 3",
    "sg:city":"Wiesent",
    "sg:phone":"+49 9482/2845",
    "sg:postcode":"93109",
    "sg:province":"Bayern",
    "wof:name":"Josef Fichtl",
    "wof:placetype":"venue"
},
  "geometry": {"coordinates":[12.38392,49.005459],"type":"Point"}
}