{
  "type": "Feature",
  "properties": {
    "iso:country":"DE",
    "sg:address":"Wallstr. 78",
    "sg:city":"K\u00f6ln",
    "sg:phone":"+49 221/629864",
    "sg:postcode":"51063",
    "sg:province":"Nordrhein-Westfalen",
    "wof:name":"U. Steinborn",
    "wof:placetype":"venue"
},
  "geometry": {"coordinates":[7.001355,50.964249],"type":"Point"}
}