{
  "type": "Feature",
  "properties": {
    "iso:country":"DE",
    "sg:address":"Hauptstr. 89",
    "sg:city":"Dreikirchen",
    "sg:postcode":"56414",
    "sg:province":"Rheinland-Pfalz",
    "wof:name":"E. C. Team Bau Gmbh",
    "wof:placetype":"venue"
},
  "geometry": {"coordinates":[7.9614830017,50.451374054],"type":"Point"}
}