{
  "type": "Feature",
  "properties": {
    "iso:country":"DE",
    "sg:address":"Waldstr. 92",
    "sg:city":"Hofgeismar",
    "sg:phone":"+49 5671/2287",
    "sg:postcode":"34369",
    "sg:province":"Hessen",
    "wof:name":"Dr. Edeltraut P\u00fcchner Tier\u00e4rztin",
    "wof:placetype":"venue"
},
  "geometry": {"coordinates":[9.467505455,51.4952545166],"type":"Point"}
}