{
  "type": "Feature",
  "properties": {
    "iso:country":"DE",
    "sg:address":"Littersbach",
    "sg:city":"Pirmasens",
    "sg:postcode":"66955",
    "sg:province":"Rheinland-Pfalz",
    "wof:name":"Waldemar Lorenz",
    "wof:placetype":"venue"
},
  "geometry": {"coordinates":[7.596693,49.177193],"type":"Point"}
}