{
  "type": "Feature",
  "properties": {
    "iso:country":"DE",
    "sg:address":"Apfelstr. 7",
    "sg:city":"Halle",
    "sg:phone":"+49 5201/10265",
    "sg:postcode":"33790",
    "sg:province":"Nordrhein-Westfalen",
    "wof:name":"Hagen W. Kaiser Elektroinstallation",
    "wof:placetype":"venue"
},
  "geometry": {"coordinates":[8.376556,52.050716],"type":"Point"}
}