{
  "type": "Feature",
  "properties": {
    "iso:country":"DE",
    "sg:address":"Hagenower Str. 13a",
    "sg:city":"Schwerin",
    "sg:phone":"+49 385/3925655",
    "sg:postcode":"19061",
    "sg:province":"Mecklenburg-Vorpommern",
    "wof:name":"Wohnen & Ideen Einrichtung Licht Accessoires Handels Gmbh",
    "wof:placetype":"venue"
},
  "geometry": {"coordinates":[11.407303,53.591583],"type":"Point"}
}