{
  "type": "Feature",
  "properties": {
    "iso:country":"DE",
    "sg:address":"Taltitzer Str. 2",
    "sg:city":"Weischlitz",
    "sg:phone":"+49 37436/84854",
    "sg:postcode":"08538",
    "sg:province":"Sachsen",
    "wof:name":"R. Und Conny Schmidt",
    "wof:placetype":"venue"
},
  "geometry": {"coordinates":[12.075651,50.461025],"type":"Point"}
}