{
  "type": "Feature",
  "properties": {
    "iso:country":"DE",
    "sg:address":"Wiesenstr. 1",
    "sg:city":"Hagen",
    "sg:phone":"+49 2334/51895",
    "sg:postcode":"58119",
    "sg:province":"Nordrhein-Westfalen",
    "wof:name":"Wienbrauck-weihl Ohg",
    "wof:placetype":"venue"
},
  "geometry": {"coordinates":[7.5678949356,51.3611907959],"type":"Point"}
}