{
  "type": "Feature",
  "properties": {
    "iso:country":"DE",
    "sg:address":"Am Kornberg 48",
    "sg:city":"Siegen",
    "sg:phone":"+49 271/48105",
    "sg:postcode":"57076",
    "sg:province":"Nordrhein-Westfalen",
    "wof:name":"Kora-wohnungsverwaltung",
    "wof:placetype":"venue"
},
  "geometry": {"coordinates":[8.0504579544,50.899356842],"type":"Point"}
}