{
  "type": "Feature",
  "properties": {
    "iso:country":"DE",
    "sg:address":"Untere Schmiedgasse 6",
    "sg:city":"N\u00fcrnberg",
    "sg:phone":"+49 911/2349946",
    "sg:postcode":"90403",
    "sg:province":"Bayern",
    "wof:name":"Nachtw\u00e4chter",
    "wof:placetype":"venue"
},
  "geometry": {"coordinates":[11.0763168335,49.4566688538],"type":"Point"}
}