{
  "type": "Feature",
  "properties": {
    "iso:country":"DE",
    "sg:address":"Am Wellenfeld 4",
    "sg:city":"Bad Salzuflen",
    "sg:phone":"+49 5222/13155",
    "sg:postcode":"32105",
    "sg:province":"Nordrhein-Westfalen",
    "wof:name":"Fremdenheim Ilse Seide",
    "wof:placetype":"venue"
},
  "geometry": {"coordinates":[8.7435894012,52.0890350342],"type":"Point"}
}