{
  "type": "Feature",
  "properties": {
    "iso:country":"DE",
    "sg:address":"Fl\u00f6\u00dflestr. 10",
    "sg:city":"Rottenburg",
    "sg:phone":"+49 7457/1605",
    "sg:postcode":"72108",
    "sg:province":"Baden-W\u00fcrttemberg",
    "wof:name":"Martin Hammer",
    "wof:placetype":"venue"
},
  "geometry": {"coordinates":[8.869973,48.528831],"type":"Point"}
}