{
  "type": "Feature",
  "properties": {
    "iso:country":"DE",
    "sg:address":"Heuweg 4",
    "sg:city":"Graal-M\u00fcritz",
    "sg:phone":"+49 38206/77590",
    "sg:postcode":"18181",
    "sg:province":"Mecklenburg-Vorpommern",
    "wof:name":"Egon Henninger",
    "wof:placetype":"venue"
},
  "geometry": {"coordinates":[12.2228479385,54.2524108887],"type":"Point"}
}