{
  "type": "Feature",
  "properties": {
    "iso:country":"DE",
    "sg:address":"Koppelstr. 3",
    "sg:city":"Horstmar",
    "sg:phone":"+49 2558/355",
    "sg:postcode":"48612",
    "sg:province":"Nordrhein-Westfalen",
    "wof:name":"Theodor Kl\u00e4ver",
    "wof:placetype":"venue"
},
  "geometry": {"coordinates":[7.3088798523,52.082660675],"type":"Point"}
}