{
  "type": "Feature",
  "properties": {
    "iso:country":"DE",
    "sg:address":"Donaustr. 107",
    "sg:city":"N\u00fcrnberg",
    "sg:phone":"+49 911/968350",
    "sg:postcode":"90451",
    "sg:province":"Bayern",
    "wof:name":"Pro St Projekt-team F\u00fcr Edv Beim Steuerberater Gmbh",
    "wof:placetype":"venue"
},
  "geometry": {"coordinates":[11.0560283661,49.4109535217],"type":"Point"}
}