{
  "type": "Feature",
  "properties": {
    "iso:country":"DE",
    "sg:address":"Hans-Schr\u00f6er-Str. 41",
    "sg:city":"R\u00fcdersdorf",
    "sg:phone":"+49 33638/64832",
    "sg:postcode":"15562",
    "sg:province":"Brandenburg",
    "wof:name":"Klaus-dieter Nehrlich Ingenieur",
    "wof:placetype":"venue"
},
  "geometry": {"coordinates":[13.8137149811,52.4693031311],"type":"Point"}
}