{
  "type": "Feature",
  "properties": {
    "iso:country":"DE",
    "sg:address":"B\u00fcrgerstr. 40",
    "sg:city":"Dresden",
    "sg:phone":"+49 351/8435853",
    "sg:postcode":"01127",
    "sg:province":"Sachsen",
    "wof:name":"Hanjochen Langner",
    "wof:placetype":"venue"
},
  "geometry": {"coordinates":[13.7244672775,51.0772514343],"type":"Point"}
}