{
  "type": "Feature",
  "properties": {
    "iso:country":"DE",
    "sg:address":"Jurastr. 6",
    "sg:city":"Asbach-B\u00e4umenheim",
    "sg:postcode":"86663",
    "sg:province":"Bayern",
    "wof:name":"It-service & Support E. K.",
    "wof:placetype":"venue"
},
  "geometry": {"coordinates":[10.8211612701,48.6758232117],"type":"Point"}
}