{
  "type": "Feature",
  "properties": {
    "iso:country":"DE",
    "sg:address":"Scharnhorststr. 3a",
    "sg:city":"Wuppertal",
    "sg:phone":"+49 202/753076",
    "sg:postcode":"42109",
    "sg:province":"Nordrhein-Westfalen",
    "wof:name":"Michael Kosten",
    "wof:placetype":"venue"
},
  "geometry": {"coordinates":[7.1483697891,51.278755188],"type":"Point"}
}