{
  "type": "Feature",
  "properties": {
    "iso:country":"DE",
    "sg:address":"Wichernstr. 28a",
    "sg:city":"Amberg",
    "sg:phone":"+49 9621/81710",
    "sg:postcode":"92224",
    "sg:province":"Bayern",
    "wof:name":"Eckhard Walter Ingenieur",
    "wof:placetype":"venue"
},
  "geometry": {"coordinates":[11.8506240845,49.4304885864],"type":"Point"}
}