{
  "type": "Feature",
  "properties": {
    "iso:country":"DE",
    "sg:address":"M\u00fclheimer Str. 17",
    "sg:city":"Ratingen",
    "sg:postcode":"40878",
    "sg:province":"Nordrhein-Westfalen",
    "wof:name":"Service-center Heiko M. Schulte E. Kfm.",
    "wof:placetype":"venue"
},
  "geometry": {"coordinates":[6.8536782265,51.2997703552],"type":"Point"}
}