{
  "type": "Feature",
  "properties": {
    "iso:country":"DE",
    "sg:address":"Kaarmannweg 27",
    "sg:city":"Essen",
    "sg:phone":"+49 201/405995",
    "sg:postcode":"45239",
    "sg:province":"Nordrhein-Westfalen",
    "wof:name":"Dr. Friedhelm Keppmann Rechtsanwalt",
    "wof:placetype":"venue"
},
  "geometry": {"coordinates":[7.0257458687,51.3885498047],"type":"Point"}
}