{
  "type": "Feature",
  "properties": {
    "iso:country":"DE",
    "sg:address":"Anemonenweg 2",
    "sg:city":"Stuttgart",
    "sg:phone":"+49 711/482947",
    "sg:postcode":"70186",
    "sg:province":"Baden-W\u00fcrttemberg",
    "wof:name":"U.-u. Kampelmann Bildhauer",
    "wof:placetype":"venue"
},
  "geometry": {"coordinates":[9.207945,48.773228],"type":"Point"}
}