{
  "type": "Feature",
  "properties": {
    "iso:country":"DE",
    "sg:address":"Prinzregentenplatz 4",
    "sg:city":"Augsburg",
    "sg:phone":"+49 821/3102278",
    "sg:postcode":"86150",
    "sg:province":"Bayern",
    "wof:name":"Verein Naturpark Augsburg Westl. W\u00e4lder",
    "wof:placetype":"venue"
},
  "geometry": {"coordinates":[10.8891582489,48.3672561646],"type":"Point"}
}