{
  "type": "Feature",
  "properties": {
    "iso:country":"DE",
    "sg:address":"Hallesche Str. 38-40",
    "sg:city":"Lutherstadt Eisleben",
    "sg:postcode":"06295",
    "sg:province":"Sachsen-Anhalt",
    "wof:name":"Feierabendheim Ii",
    "wof:placetype":"venue"
},
  "geometry": {"coordinates":[11.553296,51.525475],"type":"Point"}
}