{
  "type": "Feature",
  "properties": {
    "iso:country":"DE",
    "sg:address":"Albert-Einstein-Str. 23d",
    "sg:city":"Duisburg",
    "sg:phone":"+49 203/581949",
    "sg:postcode":"47167",
    "sg:province":"Nordrhein-Westfalen",
    "wof:name":"Svv Vermietung Und Verwaltung Gmbh",
    "wof:placetype":"venue"
},
  "geometry": {"coordinates":[6.8098859787,51.4968414307],"type":"Point"}
}