{
  "type": "Feature",
  "properties": {
    "iso:country":"DE",
    "sg:address":"Moltkestr. 7",
    "sg:city":"Bad Salzuflen",
    "sg:phone":"+49 5222/12332",
    "sg:postcode":"32105",
    "sg:province":"Nordrhein-Westfalen",
    "wof:name":"Massage Pr. Epmeyer",
    "wof:placetype":"venue"
},
  "geometry": {"coordinates":[8.744584,52.088123],"type":"Point"}
}