{
  "type": "Feature",
  "properties": {
    "iso:country":"DE",
    "sg:city":"Gaildorf",
    "sg:postcode":"74405",
    "sg:province":"Baden-W\u00fcrttemberg",
    "wof:name":"Kulturschmiede Gaildorf E.v.",
    "wof:placetype":"venue"
},
  "geometry": {"coordinates":[9.76995,49.000816],"type":"Point"}
}