{
  "type": "Feature",
  "properties": {
    "iso:country":"DE",
    "sg:address":"Kirdorfer Str. 67",
    "sg:city":"Bad Homburg",
    "sg:phone":"+49 6172/86300",
    "sg:postcode":"61350",
    "sg:province":"Hessen",
    "wof:name":"Marien-apotheke",
    "wof:placetype":"venue"
},
  "geometry": {"coordinates":[8.609142,50.238205],"type":"Point"}
}