{
  "type": "Feature",
  "properties": {
    "iso:country":"DE",
    "sg:address":"Klosterstr. 7",
    "sg:city":"Querfurt",
    "sg:phone":"+49 34771/27923",
    "sg:postcode":"06268",
    "sg:province":"Sachsen-Anhalt",
    "wof:name":"Heinrichs Spielzeug-welt",
    "wof:placetype":"venue"
},
  "geometry": {"coordinates":[11.5983800888,51.3807411194],"type":"Point"}
}