{
  "type": "Feature",
  "properties": {
    "iso:country":"DE",
    "sg:address":"Sch\u00f6nbergstr. 7",
    "sg:city":"Felsberg",
    "sg:phone":"+49 4956/6294790",
    "sg:postcode":"34587",
    "sg:province":"Hessen",
    "wof:name":"Sch\u00dcma Maschinen- Und Werkzeug-handels Gmbh",
    "wof:placetype":"venue"
},
  "geometry": {"coordinates":[9.435103,51.125668],"type":"Point"}
}