{
  "type": "Feature",
  "properties": {
    "iso:country":"DE",
    "sg:address":"Sch\u00f6ppenstedter Str. 51",
    "sg:city":"Remlingen",
    "sg:phone":"+49 5336/948222",
    "sg:postcode":"38319",
    "sg:province":"Niedersachsen",
    "wof:name":"Freibad Remlingen",
    "wof:placetype":"venue"
},
  "geometry": {"coordinates":[10.6797523499,52.117061615],"type":"Point"}
}