{
  "type": "Feature",
  "properties": {
    "iso:country":"DE",
    "sg:address":"Fritz-von-Graevenitz-Str. 17",
    "sg:city":"Gerlingen",
    "sg:phone":"+49 7156/21071",
    "sg:postcode":"70839",
    "sg:province":"Baden-W\u00fcrttemberg",
    "wof:name":"H. G. Ellfeldt",
    "wof:placetype":"venue"
},
  "geometry": {"coordinates":[9.0560903549,48.7868270874],"type":"Point"}
}