{
  "type": "Feature",
  "properties": {
    "iso:country":"DE",
    "sg:address":"Am Anger 3",
    "sg:city":"Erdweg",
    "sg:phone":"+49 8135/233",
    "sg:postcode":"85253",
    "sg:province":"Bayern",
    "wof:name":"Albert Loder",
    "wof:placetype":"venue"
},
  "geometry": {"coordinates":[11.27654,48.320866],"type":"Point"}
}