{
  "type": "Feature",
  "properties": {
    "iso:country":"DE",
    "sg:address":"Industriestr. 1",
    "sg:city":"Nast\u00e4tten",
    "sg:phone":"+49 6772/6777",
    "sg:postcode":"56355",
    "sg:province":"Rheinland-Pfalz",
    "wof:name":"Franz-j\u00fcrgen Maus",
    "wof:placetype":"venue"
},
  "geometry": {"coordinates":[7.85028,50.198574],"type":"Point"}
}