{
  "type": "Feature",
  "properties": {
    "iso:country":"DE",
    "sg:address":"Friedrichshagener Str 29-36",
    "sg:city":"Berlin",
    "sg:phone":"+49 30/65485760",
    "sg:postcode":"12555",
    "sg:province":"Berlin",
    "wof:name":"Draka Telekom Gmbh & Co Kg",
    "wof:placetype":"venue"
},
  "geometry": {"coordinates":[13.5844392776,52.4515800476],"type":"Point"}
}