{
  "type": "Feature",
  "properties": {
    "iso:country":"DE",
    "sg:address":"Albertus-Magnus-Str. 28",
    "sg:city":"Leverkusen",
    "sg:phone":"+49 214/53784",
    "sg:postcode":"51375",
    "sg:province":"Nordrhein-Westfalen",
    "wof:name":"J\u00f6rg Lange Rechtsanwalt",
    "wof:placetype":"venue"
},
  "geometry": {"coordinates":[7.0451130867,51.0398406982],"type":"Point"}
}