{
  "type": "Feature",
  "properties": {
    "iso:country":"DE",
    "sg:address":"Am Taubenfeld 43",
    "sg:city":"Heidelberg",
    "sg:phone":"+49 6221/833308",
    "sg:postcode":"69123",
    "sg:province":"Baden-W\u00fcrttemberg",
    "wof:name":"M & O Backwaren Gmbh",
    "wof:placetype":"venue"
},
  "geometry": {"coordinates":[8.63969,49.429153],"type":"Point"}
}