{
  "type": "Feature",
  "properties": {
    "iso:country":"DE",
    "sg:address":"Tegernseer Landstr. 33",
    "sg:city":"M\u00fcnchen",
    "sg:phone":"+49 89/6913437",
    "sg:postcode":"81541",
    "sg:province":"Bayern",
    "wof:name":"Naus Alpen-drogerie Photo-kino-kr\u00e4uterhaus",
    "wof:placetype":"venue"
},
  "geometry": {"coordinates":[11.582005,48.117432],"type":"Point"}
}