{
  "type": "Feature",
  "properties": {
    "iso:country":"DE",
    "sg:address":"Vinckestr. 7",
    "sg:city":"Hemer",
    "sg:phone":"+49 2372/2976",
    "sg:postcode":"58675",
    "sg:province":"Nordrhein-Westfalen",
    "wof:name":"Heinrich Lenberg Gmbh",
    "wof:placetype":"venue"
},
  "geometry": {"coordinates":[7.7454562187,51.3743095398],"type":"Point"}
}