{
  "type": "Feature",
  "properties": {
    "iso:country":"DE",
    "sg:address":"Heidelberger Str. 26",
    "sg:city":"Heidelberg",
    "sg:postcode":"69126",
    "sg:province":"Baden-W\u00fcrttemberg",
    "wof:name":"Uboris Breskvar Tennislehrer",
    "wof:placetype":"venue"
},
  "geometry": {"coordinates":[8.6914596558,49.3813667297],"type":"Point"}
}