{
  "type": "Feature",
  "properties": {
    "iso:country":"DE",
    "sg:address":"Dammer Weg 44",
    "sg:city":"Parchim",
    "sg:phone":"+49 3871/443159",
    "sg:postcode":"19370",
    "sg:province":"Mecklenburg-Vorpommern",
    "wof:name":"Herbert Feddersen",
    "wof:placetype":"venue"
},
  "geometry": {"coordinates":[11.8251657486,53.4321327209],"type":"Point"}
}