{
  "type": "Feature",
  "properties": {
    "iso:country":"DE",
    "sg:address":"Friedrichstr. 69",
    "sg:city":"Eningen",
    "sg:phone":"+49 7121/88656",
    "sg:postcode":"72800",
    "sg:province":"Baden-W\u00fcrttemberg",
    "wof:name":"Dr. R. Und K. Kolbe Immobilienmakler",
    "wof:placetype":"venue"
},
  "geometry": {"coordinates":[9.2544269562,48.4772415161],"type":"Point"}
}