{
  "type": "Feature",
  "properties": {
    "iso:country":"DE",
    "sg:address":"Waldtorstr. 1 a",
    "sg:city":"Waldshut-Tiengen",
    "sg:phone":"+49 7751/83040",
    "sg:postcode":"79761",
    "sg:province":"Baden-W\u00fcrttemberg",
    "wof:name":"Diakonisches Werk",
    "wof:placetype":"venue"
},
  "geometry": {"coordinates":[8.21318,47.624111],"type":"Point"}
}