{
  "type": "Feature",
  "properties": {
    "iso:country":"DE",
    "sg:address":"Leuchtenberger Kirchweg 75 c",
    "sg:city":"D\u00fcsseldorf",
    "sg:phone":"+49 211/479830",
    "sg:postcode":"40474",
    "sg:province":"Nordrhein-Westfalen",
    "wof:name":"Gebr. Holthausen",
    "wof:placetype":"venue"
},
  "geometry": {"coordinates":[6.725801,51.284321],"type":"Point"}
}