{
  "type": "Feature",
  "properties": {
    "iso:country":"DE",
    "sg:address":"Wiesenweg 2",
    "sg:city":"Michelstadt",
    "sg:phone":"+49 6061/12112",
    "sg:postcode":"64720",
    "sg:province":"Hessen",
    "wof:name":"Oft Reise- Und Transportvermittlungs Gmbh",
    "wof:placetype":"venue"
},
  "geometry": {"coordinates":[9.0030527115,49.6804733276],"type":"Point"}
}