{
  "type": "Feature",
  "properties": {
    "iso:country":"DE",
    "sg:address":"Luitpoldstr. 15",
    "sg:city":"Helmbrechts",
    "sg:phone":"+49 9252/91120",
    "sg:postcode":"95233",
    "sg:province":"Bayern",
    "wof:name":"B. E. S. T. Reiseb\u00fcro Hubert Schmidt",
    "wof:placetype":"venue"
},
  "geometry": {"coordinates":[11.7165355682,50.2391433716],"type":"Point"}
}