{
  "type": "Feature",
  "properties": {
    "iso:country":"DE",
    "sg:address":"Sindelfinger Str. 16",
    "sg:city":"Sindelfingen",
    "sg:phone":"+49 7031/386990",
    "sg:postcode":"71069",
    "sg:province":"Baden-W\u00fcrttemberg",
    "wof:name":"Gastst\u00e4tte Maichinger T\u00f6nnle",
    "wof:placetype":"venue"
},
  "geometry": {"coordinates":[8.9645032883,48.7242202759],"type":"Point"}
}