{
  "type": "Feature",
  "properties": {
    "iso:country":"DE",
    "sg:address":"Weiherweg 2",
    "sg:city":"Hauzenberg",
    "sg:phone":"+49 8586/1466",
    "sg:postcode":"94051",
    "sg:province":"Bayern",
    "wof:name":"Anna Schmid",
    "wof:placetype":"venue"
},
  "geometry": {"coordinates":[13.6251964569,48.6594619751],"type":"Point"}
}