{
  "type": "Feature",
  "properties": {
    "iso:country":"DE",
    "sg:address":"Am Barls 260",
    "sg:city":"Hamburg",
    "sg:phone":"+49 40/8315015",
    "sg:postcode":"22549",
    "sg:province":"Hamburg",
    "wof:name":"Pollmer Edv Vertrieb Unternehmensberatungs Gmbh",
    "wof:placetype":"venue"
},
  "geometry": {"coordinates":[9.850771904,53.5960121155],"type":"Point"}
}