{
  "type": "Feature",
  "properties": {
    "iso:country":"DE",
    "sg:address":"Gilmbach",
    "sg:city":"Linnich",
    "sg:phone":"+49 2462/8432",
    "sg:postcode":"52441",
    "sg:province":"Nordrhein-Westfalen",
    "wof:name":"O. R\u00f6mer",
    "wof:placetype":"venue"
},
  "geometry": {"coordinates":[6.2723479271,50.9807434082],"type":"Point"}
}