{
  "type": "Feature",
  "properties": {
    "iso:country":"DE",
    "sg:address":"Bremerstrasse 8A",
    "sg:city":"Ostercappeln",
    "sg:phone":"+49 175 9274426",
    "sg:postcode":"49179",
    "sg:province":"Niedersachsen",
    "wof:name":"Mauring Telecomm",
    "wof:placetype":"venue"
},
  "geometry": {"coordinates":[8.223817,52.343704],"type":"Point"}
}