{
  "type": "Feature",
  "properties": {
    "iso:country":"DE",
    "sg:address":"Rendsburger Str. 125",
    "sg:city":"Eckernf\u00f6rde",
    "sg:postcode":"24340",
    "sg:province":"Schleswig-Holstein",
    "wof:name":"Georg Niemann Gmbh",
    "wof:placetype":"venue"
},
  "geometry": {"coordinates":[9.8320198059,54.4516983032],"type":"Point"}
}