{
  "type": "Feature",
  "properties": {
    "iso:country":"DE",
    "sg:address":"Bochumer Str. 100",
    "sg:city":"Recklinghausen",
    "sg:phone":"+49 2361/32221",
    "sg:postcode":"45661",
    "sg:province":"Nordrhein-Westfalen",
    "wof:name":"Mvs Multi Video Show Gmbh",
    "wof:placetype":"venue"
},
  "geometry": {"coordinates":[7.212643,51.575199],"type":"Point"}
}