{
  "type": "Feature",
  "properties": {
    "iso:country":"DE",
    "sg:address":"Industriestr.-Nord 46",
    "sg:city":"Horn-Bad Meinberg",
    "sg:phone":"+49 5234/1521",
    "sg:postcode":"32805",
    "sg:province":"Nordrhein-Westfalen",
    "wof:name":"Rubart Mineral\u00f6l-vertriebs- U. Speditions Gmbh",
    "wof:placetype":"venue"
},
  "geometry": {"coordinates":[8.9556112289,51.8890266418],"type":"Point"}
}