{
  "type": "Feature",
  "properties": {
    "iso:country":"DE",
    "sg:address":"Fr\u00fchlingstr. 1",
    "sg:city":"Diedorf",
    "sg:phone":"+49 8238/7082",
    "sg:postcode":"86420",
    "sg:province":"Bayern",
    "wof:name":"M. Fischer",
    "wof:placetype":"venue"
},
  "geometry": {"coordinates":[10.778999,48.354691],"type":"Point"}
}