{
  "type": "Feature",
  "properties": {
    "iso:country":"DE",
    "sg:address":"Engelbergstr. 26",
    "sg:city":"Rutesheim",
    "sg:phone":"+49 7152/905067",
    "sg:postcode":"71277",
    "sg:province":"Baden-W\u00fcrttemberg",
    "wof:name":"The Lenki Place",
    "wof:placetype":"venue"
},
  "geometry": {"coordinates":[8.957473,48.793362],"type":"Point"}
}