{
  "type": "Feature",
  "properties": {
    "iso:country":"DE",
    "sg:address":"Mittelgasse 28",
    "sg:city":"Weilm\u00fcnster",
    "sg:phone":"+49 6475/279",
    "sg:postcode":"35789",
    "sg:province":"Hessen",
    "wof:name":"H. Kripp",
    "wof:placetype":"venue"
},
  "geometry": {"coordinates":[8.337129,50.398525],"type":"Point"}
}