{
  "type": "Feature",
  "properties": {
    "iso:country":"DE",
    "sg:address":"Kirchstr. 38",
    "sg:city":"Hochheim",
    "sg:phone":"+49 6146/83860",
    "sg:postcode":"65239",
    "sg:province":"Hessen",
    "wof:name":"Geheimrat Aschrottsche Erben",
    "wof:placetype":"venue"
},
  "geometry": {"coordinates":[8.3517074585,50.0094490051],"type":"Point"}
}