{
  "type": "Feature",
  "properties": {
    "iso:country":"DE",
    "sg:address":"Ernst-Ludwig-Str. 1",
    "sg:city":"Gensingen",
    "sg:phone":"+49 6727/1561",
    "sg:postcode":"55457",
    "sg:province":"Rheinland-Pfalz",
    "wof:name":"Klaus Wilke",
    "wof:placetype":"venue"
},
  "geometry": {"coordinates":[7.9255480766,49.8962173462],"type":"Point"}
}