{
  "type": "Feature",
  "properties": {
    "iso:country":"DE",
    "sg:address":"Kruganger 2",
    "sg:city":"Katlenburg-Lindau",
    "sg:phone":"+49 5552/226",
    "sg:postcode":"37191",
    "sg:province":"Niedersachsen",
    "wof:name":"Wilhelm L\u00fcdeke",
    "wof:placetype":"venue"
},
  "geometry": {"coordinates":[10.096336,51.704887],"type":"Point"}
}