{
  "type": "Feature",
  "properties": {
    "iso:country":"DE",
    "sg:address":"G\u00fctersloher Str. 42",
    "sg:city":"Herzebrock-Clarholz",
    "sg:phone":"+49 5245/4065",
    "sg:postcode":"33442",
    "sg:province":"Nordrhein-Westfalen",
    "wof:name":"Friedrich Pieper",
    "wof:placetype":"venue"
},
  "geometry": {"coordinates":[8.266039,51.885788],"type":"Point"}
}