{
  "type": "Feature",
  "properties": {
    "iso:country":"DE",
    "sg:address":"Steglitzer Damm 32",
    "sg:city":"Berlin",
    "sg:phone":"+49 30/7965032",
    "sg:postcode":"12169",
    "sg:province":"Berlin",
    "wof:name":"Angele Kinscher",
    "wof:placetype":"venue"
},
  "geometry": {"coordinates":[13.341535,52.450485],"type":"Point"}
}