{
  "type": "Feature",
  "properties": {
    "iso:country":"DE",
    "sg:address":"Wormser Landstr. 48-50",
    "sg:city":"Worms",
    "sg:phone":"+49 6241/33034",
    "sg:postcode":"67551",
    "sg:province":"Rheinland-Pfalz",
    "wof:name":"Margit Und Manfred Bechtel",
    "wof:placetype":"venue"
},
  "geometry": {"coordinates":[8.2671432495,49.6057815552],"type":"Point"}
}