{
  "type": "Feature",
  "properties": {
    "iso:country":"DE",
    "sg:address":"Postfach 1101",
    "sg:city":"Sontheim a.d.Brenz",
    "sg:phone":"+49 7325",
    "sg:postcode":"89565",
    "wof:name":"Tooltec M.weimer",
    "wof:placetype":"venue"
},
  "geometry": {"coordinates":[10.2941198349,48.5547714233],"type":"Point"}
}