{
  "type": "Feature",
  "properties": {
    "iso:country":"DE",
    "sg:address":"Merziger Str. 2",
    "sg:city":"Trier",
    "sg:phone":"+49 651/31614",
    "sg:postcode":"54294",
    "sg:province":"Rheinland-Pfalz",
    "wof:name":"Gerhard Kr\u00e4mer",
    "wof:placetype":"venue"
},
  "geometry": {"coordinates":[6.6320228577,49.7339172363],"type":"Point"}
}