{
  "type": "Feature",
  "properties": {
    "iso:country":"DE",
    "sg:address":"Liesel-Waller-Str. 8",
    "sg:city":"Ratingen",
    "sg:phone":"+49 2102/82517",
    "sg:postcode":"40882",
    "sg:province":"Nordrhein-Westfalen",
    "wof:name":"A. Blaich Immobilienmakler",
    "wof:placetype":"venue"
},
  "geometry": {"coordinates":[6.8655309677,51.3035545349],"type":"Point"}
}