{
  "type": "Feature",
  "properties": {
    "iso:country":"DE",
    "sg:address":"Reichhausener Str. 16",
    "sg:city":"Siegsdorf",
    "sg:phone":"+49 8662/7370",
    "sg:postcode":"83313",
    "sg:province":"Bayern",
    "wof:name":"W. Stoiber",
    "wof:placetype":"venue"
},
  "geometry": {"coordinates":[12.630657196,47.8298301697],"type":"Point"}
}