{
  "type": "Feature",
  "properties": {
    "iso:country":"DE",
    "sg:address":"Sch\u00f6nbornring 3",
    "sg:city":"Neu-Isenburg",
    "sg:postcode":"63263",
    "sg:province":"Hessen",
    "wof:name":"Ibv Internet Business Ventures Ag",
    "wof:placetype":"venue"
},
  "geometry": {"coordinates":[8.747995,50.06226],"type":"Point"}
}