{
  "type": "Feature",
  "properties": {
    "iso:country":"DE",
    "sg:address":"Salbergweg 10",
    "sg:city":"Merklingen",
    "sg:phone":"+49 7337/96010",
    "sg:postcode":"89188",
    "sg:province":"Baden-W\u00fcrttemberg",
    "wof:name":"Besemer Bauunternehmung Verwaltungs- Gmbh",
    "wof:placetype":"venue"
},
  "geometry": {"coordinates":[9.7553377151,48.5151443481],"type":"Point"}
}