{
  "type": "Feature",
  "properties": {
    "iso:country":"DE",
    "sg:address":"Marktplatz",
    "sg:city":"Bensheim",
    "sg:phone":"+49 6251",
    "sg:postcode":"64625",
    "sg:province":"Hessen",
    "wof:name":"Pfarrei St. Georg Bensheim",
    "wof:placetype":"venue"
},
  "geometry": {"coordinates":[8.62279,49.680908],"type":"Point"}
}