{
  "type": "Feature",
  "properties": {
    "iso:country":"DE",
    "sg:address":"Kantstr. 30",
    "sg:city":"Pforzheim",
    "sg:phone":"+49 7231/65883",
    "sg:postcode":"75175",
    "sg:province":"Baden-W\u00fcrttemberg",
    "wof:name":"Heike Mummenthey Rechtsanw\u00e4lte",
    "wof:placetype":"venue"
},
  "geometry": {"coordinates":[8.710726738,48.8807144165],"type":"Point"}
}