{
  "type": "Feature",
  "properties": {
    "iso:country":"DE",
    "sg:address":"Kuckelsberg 33",
    "sg:city":"Wuppertal",
    "sg:phone":"+49 202/760908",
    "sg:postcode":"42113",
    "sg:province":"Nordrhein-Westfalen",
    "wof:name":"A. Thiesse Sen.",
    "wof:placetype":"venue"
},
  "geometry": {"coordinates":[7.125527,51.27343],"type":"Point"}
}