{
  "type": "Feature",
  "properties": {
    "iso:country":"DE",
    "sg:address":"Erdmannh\u00e4user Str. 57",
    "sg:city":"Marbach",
    "sg:phone":"+49 4971/449070",
    "sg:postcode":"71672",
    "sg:province":"Baden-W\u00fcrttemberg",
    "wof:name":"Hainbuch Gmbh",
    "wof:placetype":"venue"
},
  "geometry": {"coordinates":[9.276062,48.941963],"type":"Point"}
}