{
  "type": "Feature",
  "properties": {
    "iso:country":"DE",
    "sg:address":"Oskar-Arnold-Str. 14",
    "sg:city":"Zwickau",
    "sg:phone":"+49 375/210070",
    "sg:postcode":"08056",
    "sg:province":"Sachsen",
    "wof:name":"Mc Donalds",
    "wof:placetype":"venue"
},
  "geometry": {"coordinates":[12.501036644,50.7067489624],"type":"Point"}
}