{
  "type": "Feature",
  "properties": {
    "iso:country":"DE",
    "sg:address":"Ha\u00dflinghauser Str. 75",
    "sg:city":"Gevelsberg",
    "sg:phone":"+49 2332/14040",
    "sg:postcode":"58285",
    "sg:province":"Nordrhein-Westfalen",
    "wof:name":"O. Schmidt",
    "wof:placetype":"venue"
},
  "geometry": {"coordinates":[7.321405,51.319836],"type":"Point"}
}