{
  "type": "Feature",
  "properties": {
    "iso:country":"DE",
    "sg:address":"Erzh\u00e4user Str. 12 d",
    "sg:city":"Egelsbach",
    "sg:postcode":"63329",
    "sg:province":"Hessen",
    "wof:name":"Trivet Grundbesitz Und Hausverwaltung Gmbh",
    "wof:placetype":"venue"
},
  "geometry": {"coordinates":[8.658372879,49.9673652649],"type":"Point"}
}