{
  "type": "Feature",
  "properties": {
    "iso:country":"DE",
    "sg:address":"Ro\u00dffelder Str. 63",
    "sg:city":"Crailsheim",
    "sg:phone":"+49 4979/5193720",
    "sg:postcode":"74564",
    "sg:province":"Baden-W\u00fcrttemberg",
    "wof:name":"Peter Heinkel",
    "wof:placetype":"venue"
},
  "geometry": {"coordinates":[10.034337,49.126579],"type":"Point"}
}