{
  "type": "Feature",
  "properties": {
    "iso:country":"DE",
    "sg:address":"Stettiner Str. 20",
    "sg:city":"Dillingen",
    "sg:phone":"+49 6831/976265",
    "sg:postcode":"66763",
    "sg:province":"Saarland",
    "wof:name":"Ks Zahntechnik Gmbh",
    "wof:placetype":"venue"
},
  "geometry": {"coordinates":[6.715896,49.365143],"type":"Point"}
}