{
  "type": "Feature",
  "properties": {
    "iso:country":"DE",
    "sg:address":"Sangerh\u00e4user Str. 42",
    "sg:city":"Lutherstadt Eisleben",
    "sg:phone":"+49 3475/683283",
    "sg:postcode":"06295",
    "sg:province":"Sachsen-Anhalt",
    "wof:name":"Restaurant Zur Kupferklause",
    "wof:placetype":"venue"
},
  "geometry": {"coordinates":[11.5430202484,51.5285224915],"type":"Point"}
}