{
  "type": "Feature",
  "properties": {
    "iso:country":"DE",
    "sg:address":"Severinstr. 17",
    "sg:city":"Aachen",
    "sg:phone":"+49 241/551352",
    "sg:postcode":"52080",
    "sg:province":"Nordrhein-Westfalen",
    "wof:name":"Heinz Salber",
    "wof:placetype":"venue"
},
  "geometry": {"coordinates":[6.1487941742,50.7772331238],"type":"Point"}
}