{
  "type": "Feature",
  "properties": {
    "iso:country":"DE",
    "sg:address":"Otto-Th\u00f6rner-Str. 11",
    "sg:city":"Chemnitz",
    "sg:phone":"+49 371/773424",
    "sg:postcode":"09127",
    "sg:province":"Sachsen",
    "wof:name":"Fritzsch Adelsberg Gmbh",
    "wof:placetype":"venue"
},
  "geometry": {"coordinates":[12.9703407288,50.8087463379],"type":"Point"}
}