{
  "type": "Feature",
  "properties": {
    "iso:country":"DE",
    "sg:address":"Bredde 9",
    "sg:city":"Lennestadt",
    "sg:phone":"+49 2721/81201",
    "sg:postcode":"57368",
    "sg:province":"Nordrhein-Westfalen",
    "wof:name":"Willi Schlabach",
    "wof:placetype":"venue"
},
  "geometry": {"coordinates":[8.05981,51.124908],"type":"Point"}
}