{
  "type": "Feature",
  "properties": {
    "iso:country":"DE",
    "sg:address":"Klostergasse 1",
    "sg:city":"Eberstadt",
    "sg:phone":"+49 7134/4235",
    "sg:postcode":"74246",
    "sg:province":"Baden-W\u00fcrttemberg",
    "wof:name":"Ulrich Hofmann",
    "wof:placetype":"venue"
},
  "geometry": {"coordinates":[9.3217811584,49.1787834167],"type":"Point"}
}