{
  "type": "Feature",
  "properties": {
    "iso:country":"DE",
    "sg:address":"Grenzwall 7",
    "sg:city":"Dassendorf",
    "sg:phone":"+49 4104/3475",
    "sg:postcode":"21521",
    "sg:province":"Schleswig-Holstein",
    "wof:name":"Heinz Rogge Tennislehrer",
    "wof:placetype":"venue"
},
  "geometry": {"coordinates":[10.3486213684,53.4962730408],"type":"Point"}
}