{
  "type": "Feature",
  "properties": {
    "iso:country":"DE",
    "sg:address":"Dr.-Eichinger-Str. 3",
    "sg:city":"Tann",
    "sg:phone":"+49 8572/8794",
    "sg:postcode":"84367",
    "sg:province":"Bayern",
    "wof:name":"Stelzer Textil Gmbh",
    "wof:placetype":"venue"
},
  "geometry": {"coordinates":[12.9216938019,48.3435668945],"type":"Point"}
}