{
  "type": "Feature",
  "properties": {
    "iso:country":"DE",
    "sg:address":"Freiburger Str. 69",
    "sg:city":"Villingen-Schwenningen",
    "sg:phone":"+49 7721/54305",
    "sg:postcode":"78048",
    "sg:province":"Baden-W\u00fcrttemberg",
    "wof:name":"Berthold Und Gisela Bauer Anlageberater",
    "wof:placetype":"venue"
},
  "geometry": {"coordinates":[8.451669693,48.0717277527],"type":"Point"}
}