{
  "type": "Feature",
  "properties": {
    "iso:country":"DE",
    "sg:address":"Rudolf-Diesel-Str 3",
    "sg:city":"Genthin",
    "sg:phone":"+49 3933/804329",
    "sg:postcode":"39307",
    "sg:province":"Sachsen-Anhalt",
    "wof:name":"Dhs Gmbh",
    "wof:placetype":"venue"
},
  "geometry": {"coordinates":[12.1414985657,52.3900184631],"type":"Point"}
}