{
  "type": "Feature",
  "properties": {
    "iso:country":"DE",
    "sg:address":"M\u00f6hringer Str.",
    "sg:city":"Unlingen",
    "sg:phone":"+49 7371/10261",
    "sg:postcode":"88527",
    "sg:province":"Baden-W\u00fcrttemberg",
    "wof:name":"E. Huckle",
    "wof:placetype":"venue"
},
  "geometry": {"coordinates":[9.5261993408,48.1674385071],"type":"Point"}
}