{
  "type": "Feature",
  "properties": {
    "iso:country":"DE",
    "sg:address":"Jakob-Kaiser-Weg 45",
    "sg:city":"Wuppertal",
    "sg:postcode":"42111",
    "sg:province":"Nordrhein-Westfalen",
    "wof:name":"Grundbesitzgesellschaft Sch\u00f6nebecker Strasse",
    "wof:placetype":"venue"
},
  "geometry": {"coordinates":[7.1697268486,51.2877578735],"type":"Point"}
}