{
  "type": "Feature",
  "properties": {
    "iso:country":"DE",
    "sg:address":"M\u00fchlstr. 8",
    "sg:city":"Raguhn",
    "sg:phone":"+49 34906/20211",
    "sg:postcode":"06779",
    "sg:province":"Sachsen-Anhalt",
    "wof:name":"Esra Gmbh",
    "wof:placetype":"venue"
},
  "geometry": {"coordinates":[12.293091,51.711903],"type":"Point"}
}