{
  "type": "Feature",
  "properties": {
    "iso:country":"DE",
    "sg:address":"Klosterstr. 34",
    "sg:city":"Langenfeld",
    "sg:phone":"+49 2173/81835",
    "sg:postcode":"40764",
    "sg:province":"Nordrhein-Westfalen",
    "wof:name":"Harald Pick",
    "wof:placetype":"venue"
},
  "geometry": {"coordinates":[6.941423,51.131065],"type":"Point"}
}