{
  "type": "Feature",
  "properties": {
    "iso:country":"DE",
    "sg:address":"Silcherstr. 20",
    "sg:city":"K\u00f6ln",
    "sg:phone":"+49 221/586469",
    "sg:postcode":"50827",
    "sg:province":"Nordrhein-Westfalen",
    "wof:name":"Martin Sell",
    "wof:placetype":"venue"
},
  "geometry": {"coordinates":[6.895238,50.954807],"type":"Point"}
}