{
  "type": "Feature",
  "properties": {
    "iso:country":"DE",
    "sg:address":"Boppstr. 72",
    "sg:city":"Mainz",
    "sg:phone":"+49 6131/675320",
    "sg:postcode":"55118",
    "sg:province":"Rheinland-Pfalz",
    "wof:name":"E. Sprungk",
    "wof:placetype":"venue"
},
  "geometry": {"coordinates":[8.2551383972,50.0065116882],"type":"Point"}
}