{
  "type": "Feature",
  "properties": {
    "iso:country":"DE",
    "sg:address":"Zollstr. 13",
    "sg:city":"Gottmadingen",
    "sg:phone":"+49 7734/931862",
    "sg:postcode":"78244",
    "sg:province":"Baden-W\u00fcrttemberg",
    "wof:name":"R. Ramisch",
    "wof:placetype":"venue"
},
  "geometry": {"coordinates":[8.7273769379,47.7403488159],"type":"Point"}
}