{
  "type": "Feature",
  "properties": {
    "iso:country":"DE",
    "sg:address":"Gladenbacher Str. 47",
    "sg:city":"Dautphetal",
    "sg:phone":"+49 4964/6691340",
    "sg:postcode":"35232",
    "sg:province":"Hessen",
    "wof:name":"Heck & Becker Gmbh & Co Kg",
    "wof:placetype":"venue"
},
  "geometry": {"coordinates":[8.548221,50.853733],"type":"Point"}
}