{
  "type": "Feature",
  "properties": {
    "iso:country":"DE",
    "sg:address":"Otto-Hahn-Str. 5",
    "sg:city":"Kassel",
    "sg:phone":"+49 4956/1582023",
    "sg:postcode":"34123",
    "sg:province":"Hessen",
    "wof:name":"Heinz Buehl Gmbh Xerox Vertragspartner",
    "wof:placetype":"venue"
},
  "geometry": {"coordinates":[9.5047597885,51.2806053162],"type":"Point"}
}