{
  "type": "Feature",
  "properties": {
    "iso:country":"DE",
    "sg:address":"Hauptstr. 44 a",
    "sg:city":"Brielow",
    "sg:postcode":"14778",
    "sg:province":"Brandenburg",
    "wof:name":"Avb An- Und Verkauf Brielow Gmbh",
    "wof:placetype":"venue"
},
  "geometry": {"coordinates":[12.5445394516,52.4606513977],"type":"Point"}
}