{
  "type": "Feature",
  "properties": {
    "iso:country":"DE",
    "sg:address":"Rohrbacher Str. 1",
    "sg:city":"Lichtenfels",
    "sg:postcode":"96215",
    "sg:province":"Bayern",
    "wof:name":"Kraus & Pabst Beteiligungsgesellschaft",
    "wof:placetype":"venue"
},
  "geometry": {"coordinates":[11.047707,50.136517],"type":"Point"}
}