{
  "type": "Feature",
  "properties": {
    "iso:country":"DE",
    "sg:address":"Hohenzollernstr. 52",
    "sg:city":"Hannover",
    "sg:phone":"+49 511/1694520",
    "sg:postcode":"30161",
    "sg:province":"Niedersachsen",
    "wof:name":"Hawellek & Collegen Wirtschaftsberatungsges. Mbh",
    "wof:placetype":"venue"
},
  "geometry": {"coordinates":[9.7530250549,52.3869781494],"type":"Point"}
}