{
  "type": "Feature",
  "properties": {
    "iso:country":"DE",
    "sg:address":"Hohenhorststr. 1b",
    "sg:city":"L\u00fcneburg",
    "sg:phone":"+49 4131/921312",
    "sg:postcode":"21337",
    "sg:province":"Niedersachsen",
    "wof:name":"Spektrum-raum Dienstleister F\u00fcr Objekt-",
    "wof:placetype":"venue"
},
  "geometry": {"coordinates":[10.4756202698,53.2456283569],"type":"Point"}
}