{
  "type": "Feature",
  "properties": {
    "iso:country":"DE",
    "sg:address":"Eulauer Str. 3",
    "sg:city":"Pegau",
    "sg:phone":"+49 34296/76218",
    "sg:postcode":"04523",
    "sg:province":"Sachsen",
    "wof:name":"Pegauer Fleisch- Und Wurstwaren Gmbh",
    "wof:placetype":"venue"
},
  "geometry": {"coordinates":[12.2479944229,51.1651039124],"type":"Point"}
}