{
  "type": "Feature",
  "properties": {
    "iso:country":"DE",
    "sg:address":"Breslauer Ring 31",
    "sg:city":"B\u00fcchen",
    "sg:phone":"+49 4155/82131",
    "sg:postcode":"21514",
    "sg:province":"Schleswig-Holstein",
    "wof:name":"Ziemba Und Neuziemba Rechtsanw\u00e4lte",
    "wof:placetype":"venue"
},
  "geometry": {"coordinates":[10.5948991776,53.4866371155],"type":"Point"}
}