{
  "type": "Feature",
  "properties": {
    "iso:country":"DE",
    "sg:address":"Kurt-Schumacher-Str. 275",
    "sg:city":"Dinslaken",
    "sg:phone":"+49 2064/96400",
    "sg:postcode":"46539",
    "sg:province":"Nordrhein-Westfalen",
    "wof:name":"Mk Sport-live Gmbh",
    "wof:placetype":"venue"
},
  "geometry": {"coordinates":[6.795794,51.558846],"type":"Point"}
}