{
  "type": "Feature",
  "properties": {
    "iso:country":"DE",
    "sg:address":"Weimarische Str 1a",
    "sg:city":"Rudolstadt",
    "sg:phone":"+49 3672/422487",
    "sg:postcode":"07407",
    "sg:province":"Th\u00fcringen",
    "wof:name":"Gis Gesellschaft F\u00fcr Intelligente Seminar- Und Schulungssysteme Mbh",
    "wof:placetype":"venue"
},
  "geometry": {"coordinates":[11.3362436295,50.7282142639],"type":"Point"}
}