{
  "type": "Feature",
  "properties": {
    "iso:country":"DE",
    "sg:address":"Locherhofer Str. 46",
    "sg:city":"Dunningen",
    "sg:postcode":"78655",
    "sg:province":"Baden-W\u00fcrttemberg",
    "wof:name":"Windkraft Dunningen Gmbh & Co. Kg",
    "wof:placetype":"venue"
},
  "geometry": {"coordinates":[8.5021486282,48.2087898254],"type":"Point"}
}