{
  "type": "Feature",
  "properties": {
    "iso:country":"DE",
    "sg:address":"Albrechtstr. 4",
    "sg:city":"Zeitz",
    "sg:phone":"+49 3441/214050",
    "sg:postcode":"06712",
    "sg:province":"Sachsen-Anhalt",
    "wof:name":"Dietmar H\u00e4hnel Sachverst. F\u00fcr Mineral\u00f6l",
    "wof:placetype":"venue"
},
  "geometry": {"coordinates":[12.1278686523,51.0530395508],"type":"Point"}
}