{
  "type": "Feature",
  "properties": {
    "iso:country":"DE",
    "sg:address":"Rosenheimer Str. 10",
    "sg:city":"Reitmehring",
    "sg:phone":"+49 8071/730",
    "sg:postcode":"83512",
    "sg:province":"Bayern",
    "wof:name":"Inntaler Mischfutter Gmbh & Co. Kg",
    "wof:placetype":"venue"
},
  "geometry": {"coordinates":[12.2331848145,48.0607948303],"type":"Point"}
}