{
  "type": "Feature",
  "properties": {
    "iso:country":"DE",
    "sg:address":"M\u00fchlenkamp 20",
    "sg:city":"Barsbek",
    "sg:phone":"+49 4344/1212",
    "sg:postcode":"24217",
    "sg:province":"Schleswig-Holstein",
    "wof:name":"Karl Meyer Inh. Hans-peter Meyer",
    "wof:placetype":"venue"
},
  "geometry": {"coordinates":[10.3289604187,54.4048728943],"type":"Point"}
}