{
  "type": "Feature",
  "properties": {
    "iso:country":"DE",
    "sg:address":"Elbinsel Krautsand 45",
    "sg:city":"Drochtersen",
    "sg:phone":"+49 4143/5699",
    "sg:postcode":"21706",
    "sg:province":"Niedersachsen",
    "wof:name":"S.-j. Sobolewski",
    "wof:placetype":"venue"
},
  "geometry": {"coordinates":[9.3864049911,53.7495384216],"type":"Point"}
}