{
  "type": "Feature",
  "properties": {
    "iso:country":"DE",
    "sg:address":"Breite Str. 27",
    "sg:city":"Ovelg\u00f6nne",
    "sg:phone":"+49 4401/81780",
    "sg:postcode":"26939",
    "sg:province":"Niedersachsen",
    "wof:name":"Norddeutsches Handwerksmuseum",
    "wof:placetype":"venue"
},
  "geometry": {"coordinates":[8.422225,53.341934],"type":"Point"}
}