{
  "type": "Feature",
  "properties": {
    "iso:country":"DE",
    "sg:address":"Meppener Str. 21",
    "sg:city":"Hasel\u00fcnne",
    "sg:phone":"+49 5961/5539",
    "sg:postcode":"49740",
    "sg:province":"Niedersachsen",
    "wof:name":"Hans Haneklaus",
    "wof:placetype":"venue"
},
  "geometry": {"coordinates":[7.480547,52.67511],"type":"Point"}
}