{
  "type": "Feature",
  "properties": {
    "iso:country":"DE",
    "sg:address":"Posener Str. 20",
    "sg:city":"Straubing",
    "sg:postcode":"94315",
    "sg:province":"Bayern",
    "wof:name":"Str Erlebnisgastronomie- Beteiligungs Gmbh",
    "wof:placetype":"venue"
},
  "geometry": {"coordinates":[12.613429,48.886955],"type":"Point"}
}