{
  "type": "Feature",
  "properties": {
    "iso:country":"DE",
    "sg:address":"Hinter den G\u00e4rten 18",
    "sg:city":"Reiskirchen",
    "sg:phone":"+49 6408/6984",
    "sg:postcode":"35447",
    "sg:province":"Hessen",
    "wof:name":"Reiner Und Brigitte Haschke",
    "wof:placetype":"venue"
},
  "geometry": {"coordinates":[8.8205909729,50.5790176392],"type":"Point"}
}