{
  "type": "Feature",
  "properties": {
    "iso:country":"DE",
    "sg:address":"Viehhofstr. 5",
    "sg:city":"Stuttgart",
    "sg:phone":"+49 711/480520",
    "sg:postcode":"70188",
    "sg:province":"Baden-W\u00fcrttemberg",
    "wof:name":"Adg-steuerberatungsges. Mbh",
    "wof:placetype":"venue"
},
  "geometry": {"coordinates":[9.2189502716,48.7872695923],"type":"Point"}
}