{
  "type": "Feature",
  "properties": {
    "iso:country":"DE",
    "sg:address":"Z\u00f6rgiebelweg 22",
    "sg:city":"Berlin",
    "sg:phone":"+49 30/36710066",
    "sg:postcode":"13591",
    "sg:province":"Berlin",
    "wof:name":"Brigitte Meyer",
    "wof:placetype":"venue"
},
  "geometry": {"coordinates":[13.151386261,52.5385818481],"type":"Point"}
}