{
  "type": "Feature",
  "properties": {
    "iso:country":"DE",
    "sg:address":"Hauptstr. 56",
    "sg:city":"Meinersen",
    "sg:phone":"+49 5372/5238",
    "sg:postcode":"38536",
    "sg:province":"Niedersachsen",
    "wof:name":"Altenpension Erika Heuer",
    "wof:placetype":"venue"
},
  "geometry": {"coordinates":[10.360863,52.474918],"type":"Point"}
}