{
  "type": "Feature",
  "properties": {
    "iso:country":"DE",
    "sg:city":"Burgwald",
    "sg:phone":"+49 4964/578058",
    "sg:postcode":"35099",
    "sg:province":"Hessen",
    "wof:name":"Raiffeisenbank Eg",
    "wof:placetype":"venue"
},
  "geometry": {"coordinates":[8.750599,51.006145],"type":"Point"}
}