{
  "type": "Feature",
  "properties": {
    "iso:country":"DE",
    "sg:address":"Max-Eyth-Str. 16",
    "sg:city":"Lo\u00dfburg",
    "sg:phone":"+49 7446/95150",
    "sg:postcode":"72290",
    "sg:province":"Baden-W\u00fcrttemberg",
    "wof:name":"Schwenk Gmbh",
    "wof:placetype":"venue"
},
  "geometry": {"coordinates":[8.449413,48.405762],"type":"Point"}
}