{
  "type": "Feature",
  "properties": {
    "iso:country":"DE",
    "sg:address":"Ferdinand-Sauerbruch-Str. 17",
    "sg:city":"Koblenz",
    "sg:phone":"+49 261/409799",
    "sg:postcode":"56073",
    "sg:province":"Rheinland-Pfalz",
    "wof:name":"Kasino- Und Party-service Lohmeier & Deimel Ohg",
    "wof:placetype":"venue"
},
  "geometry": {"coordinates":[7.568696022,50.3580055237],"type":"Point"}
}