{
  "type": "Feature",
  "properties": {
    "iso:country":"DE",
    "sg:address":"Karl-Marx-Stra\u00dfe 19",
    "sg:city":"Hochkirch",
    "sg:phone":"+49 35939/88734",
    "sg:postcode":"02627",
    "sg:province":"Sachsen",
    "wof:name":"Historisches Wirtshaus \u00b4alter Fritz\u00b4",
    "wof:placetype":"venue"
},
  "geometry": {"coordinates":[14.5708723068,51.1484146118],"type":"Point"}
}