{
  "type": "Feature",
  "properties": {
    "iso:country":"DE",
    "sg:address":"Hauptstr. 169",
    "sg:city":"Heidelberg",
    "sg:phone":"+49 6221/26903",
    "sg:postcode":"69117",
    "sg:province":"Baden-W\u00fcrttemberg",
    "wof:name":"Atrium H. Baumann",
    "wof:placetype":"venue"
},
  "geometry": {"coordinates":[8.7081184387,49.4118232727],"type":"Point"}
}