{
  "type": "Feature",
  "properties": {
    "iso:country":"DE",
    "sg:address":"Schwachhauser Heerstr. 24",
    "sg:city":"Bremen",
    "sg:phone":"+49 421/340780",
    "sg:postcode":"28209",
    "sg:province":"Bremen",
    "wof:name":"Efk Entwicklungsges. F\u00fcr Kommunikationssysteme Mbh",
    "wof:placetype":"venue"
},
  "geometry": {"coordinates":[8.8283805847,53.0803184509],"type":"Point"}
}