{
  "type": "Feature",
  "properties": {
    "iso:country":"DE",
    "sg:address":"Tulpenweg 10",
    "sg:city":"Friedberg",
    "sg:phone":"+49 821/782505",
    "sg:postcode":"86316",
    "sg:province":"Bayern",
    "wof:name":"Renate Kriener Krankengymnastik",
    "wof:placetype":"venue"
},
  "geometry": {"coordinates":[11.000191,48.393192],"type":"Point"}
}