{
  "type": "Feature",
  "properties": {
    "iso:country":"DE",
    "sg:address":"Im Gr\u00fcndle 1",
    "sg:city":"Winnenden",
    "sg:postcode":"71364",
    "sg:province":"Baden-W\u00fcrttemberg",
    "wof:name":"Servicekontor Gmbh",
    "wof:placetype":"venue"
},
  "geometry": {"coordinates":[9.436122,48.878895],"type":"Point"}
}