{
  "type": "Feature",
  "properties": {
    "iso:country":"DE",
    "sg:address":"Alslebener Str 3a",
    "sg:city":"Gr\u00f6ningen",
    "sg:phone":"+49 39403/94261",
    "sg:postcode":"39397",
    "sg:province":"Sachsen-Anhalt",
    "wof:name":"Mb - Kunststoff Gmbh",
    "wof:placetype":"venue"
},
  "geometry": {"coordinates":[11.2125377655,51.9435424805],"type":"Point"}
}