{
  "type": "Feature",
  "properties": {
    "iso:country":"DE",
    "sg:address":"Wei\u00dfer Weg 26",
    "sg:city":"Kerpen",
    "sg:phone":"+49 2273/1021",
    "sg:postcode":"50169",
    "sg:province":"Nordrhein-Westfalen",
    "wof:name":"Dietrich Reimann",
    "wof:placetype":"venue"
},
  "geometry": {"coordinates":[6.7016692162,50.9161148071],"type":"Point"}
}