{
  "type": "Feature",
  "properties": {
    "iso:country":"DE",
    "sg:address":"Piesbacher Str. 76",
    "sg:city":"Nalbach",
    "sg:phone":"+49 6838/2341",
    "sg:postcode":"66809",
    "sg:province":"Saarland",
    "wof:name":"Heidi Edinger",
    "wof:placetype":"venue"
},
  "geometry": {"coordinates":[6.7954678535,49.3845710754],"type":"Point"}
}