{
  "type": "Feature",
  "properties": {
    "iso:country":"DE",
    "sg:address":"B\u00fcrgerm.-Lienhop-Str. 9",
    "sg:city":"Bassum",
    "sg:phone":"+49 4241/2249",
    "sg:postcode":"27211",
    "sg:province":"Niedersachsen",
    "wof:name":"Walter Scharfe Architekt",
    "wof:placetype":"venue"
},
  "geometry": {"coordinates":[8.736647,52.850544],"type":"Point"}
}