{
  "type": "Feature",
  "properties": {
    "iso:country":"DE",
    "sg:address":"Hewlett-Packard-Str.",
    "sg:city":"Waldbronn",
    "sg:phone":"+49 7243/69051",
    "sg:postcode":"76337",
    "sg:province":"Baden-W\u00fcrttemberg",
    "wof:name":"Minimal",
    "wof:placetype":"venue"
},
  "geometry": {"coordinates":[8.473772049,48.9327697754],"type":"Point"}
}