{
  "type": "Feature",
  "properties": {
    "iso:country":"DE",
    "sg:address":"Platz des Friedens 15",
    "sg:city":"Eibenstock",
    "sg:postcode":"08309",
    "sg:province":"Sachsen",
    "wof:name":"Katholisches Pfarramt Eibensotck",
    "wof:placetype":"venue"
},
  "geometry": {"coordinates":[12.5989332199,50.4975662231],"type":"Point"}
}