{
  "type": "Feature",
  "properties": {
    "iso:country":"DE",
    "sg:address":"Kurstr. 18",
    "sg:city":"Scheidegg",
    "sg:phone":"+49 8381/1584",
    "sg:postcode":"88175",
    "sg:province":"Bayern",
    "wof:name":"Xaver Schenk",
    "wof:placetype":"venue"
},
  "geometry": {"coordinates":[9.8601713181,47.5749015808],"type":"Point"}
}