{
  "type": "Feature",
  "properties": {
    "iso:country":"DE",
    "sg:address":"Mainzer Str. 4",
    "sg:city":"Limburg",
    "sg:phone":"+49 6431/71451",
    "sg:postcode":"65552",
    "sg:province":"Hessen",
    "wof:name":"K. Litzinger",
    "wof:placetype":"venue"
},
  "geometry": {"coordinates":[8.1023597717,50.3930511475],"type":"Point"}
}