{
  "type": "Feature",
  "properties": {
    "iso:country":"DE",
    "sg:address":"Freiwaldauer Weg 28",
    "sg:city":"Berlin",
    "sg:phone":"+49 30/81687680",
    "sg:postcode":"12205",
    "sg:province":"Berlin",
    "wof:name":"Kps Prudentia Gmbh",
    "wof:placetype":"venue"
},
  "geometry": {"coordinates":[13.2874059677,52.4366035461],"type":"Point"}
}