{
  "type": "Feature",
  "properties": {
    "iso:country":"DE",
    "sg:address":"Marienstr. 8",
    "sg:city":"Osnabr\u00fcck",
    "sg:phone":"+49 541/2052062",
    "sg:postcode":"49074",
    "sg:province":"Niedersachsen",
    "wof:name":"Globus Tour Reisen",
    "wof:placetype":"venue"
},
  "geometry": {"coordinates":[8.040596962,52.2767448425],"type":"Point"}
}