{
  "type": "Feature",
  "properties": {
    "iso:country":"DE",
    "sg:address":"Am Bahnhof 13",
    "sg:city":"W\u00e4chtersbach",
    "sg:phone":"+49 6053/2880",
    "sg:postcode":"63607",
    "sg:province":"Hessen",
    "wof:name":"Lidl",
    "wof:placetype":"venue"
},
  "geometry": {"coordinates":[9.2970457077,50.2556381226],"type":"Point"}
}