{
  "type": "Feature",
  "properties": {
    "iso:country":"DE",
    "sg:address":"Prinz-Handjery-Str. 42A",
    "sg:city":"Berlin",
    "sg:phone":"+49 30/8151970",
    "sg:postcode":"14167",
    "sg:province":"Berlin",
    "wof:name":"Apartment No 1 In Berlin",
    "wof:placetype":"venue"
},
  "geometry": {"coordinates":[13.2680492401,52.4229698181],"type":"Point"}
}