{
  "type": "Feature",
  "properties": {
    "iso:country":"DE",
    "sg:address":"Moerser Str. 293",
    "sg:city":"Duisburg",
    "sg:phone":"+49 2066/34420",
    "sg:postcode":"47198",
    "sg:province":"Nordrhein-Westfalen",
    "wof:name":"Kleenothek",
    "wof:placetype":"venue"
},
  "geometry": {"coordinates":[6.68325,51.449669],"type":"Point"}
}