{
  "type": "Feature",
  "properties": {
    "iso:country":"DE",
    "sg:address":"Herdweg 6",
    "sg:city":"Weil im Sch\u00f6nbuch",
    "sg:phone":"+49 7157/61397",
    "sg:postcode":"71093",
    "sg:province":"Baden-W\u00fcrttemberg",
    "wof:name":"Scheuermann & Sohn Bauunternehmung Gmbh",
    "wof:placetype":"venue"
},
  "geometry": {"coordinates":[9.063243,48.626026],"type":"Point"}
}