{
  "type": "Feature",
  "properties": {
    "iso:country":"DE",
    "sg:address":"Kennedyallee 41",
    "sg:city":"Frankfurt",
    "sg:postcode":"60596",
    "sg:province":"Hessen",
    "wof:name":"Baum Immobilien Holding Gmbh",
    "wof:placetype":"venue"
},
  "geometry": {"coordinates":[8.67372,50.099979],"type":"Point"}
}