{
  "type": "Feature",
  "properties": {
    "iso:country":"DE",
    "sg:address":"Wechold 31",
    "sg:city":"Hilgermissen",
    "sg:phone":"+49 4256/272",
    "sg:postcode":"27318",
    "sg:province":"Niedersachsen",
    "wof:name":"Restaurant Zum Goldenen Krug",
    "wof:placetype":"venue"
},
  "geometry": {"coordinates":[9.1129961014,52.8555526733],"type":"Point"}
}