{
  "type": "Feature",
  "properties": {
    "iso:country":"DE",
    "sg:address":"Ohrestr. 19",
    "sg:city":"Magdeburg",
    "sg:phone":"+49 391/31387",
    "sg:postcode":"39124",
    "sg:province":"Sachsen-Anhalt",
    "wof:name":"Niederspannungsschalt Anlagenbau Gmbh",
    "wof:placetype":"venue"
},
  "geometry": {"coordinates":[11.659221,52.159119],"type":"Point"}
}