{
  "type": "Feature",
  "properties": {
    "iso:country":"DE",
    "sg:address":"Hochstr. 2",
    "sg:city":"Schmallenberg",
    "sg:phone":"+49 2974/277",
    "sg:postcode":"57392",
    "sg:province":"Nordrhein-Westfalen",
    "wof:name":"Burg-apotheke",
    "wof:placetype":"venue"
},
  "geometry": {"coordinates":[8.282059,51.157925],"type":"Point"}
}