{
  "type": "Feature",
  "properties": {
    "iso:country":"DE",
    "sg:address":"Eduard-Schmid-Str. 28",
    "sg:city":"M\u00fcnchen",
    "sg:postcode":"81541",
    "sg:province":"Bayern",
    "wof:name":"Ernst M\u00fcssig",
    "wof:placetype":"venue"
},
  "geometry": {"coordinates":[11.575507,48.123825],"type":"Point"}
}