{
  "type": "Feature",
  "properties": {
    "iso:country":"DE",
    "sg:address":"Sonderburger Str. 4",
    "sg:city":"Eckernf\u00f6rde",
    "sg:phone":"+49 4351/83111",
    "sg:postcode":"24340",
    "sg:province":"Schleswig-Holstein",
    "wof:name":"Wolf-r\u00fcdiger M\u00fcller Transportunternehmen Gmbh",
    "wof:placetype":"venue"
},
  "geometry": {"coordinates":[9.8245029449,54.4829216003],"type":"Point"}
}