{
  "type": "Feature",
  "properties": {
    "iso:country":"DE",
    "sg:address":"Eberhardstr. 64",
    "sg:city":"Fellbach",
    "sg:postcode":"70736",
    "sg:province":"Baden-W\u00fcrttemberg",
    "wof:name":"Mediasyn Gmbh",
    "wof:placetype":"venue"
},
  "geometry": {"coordinates":[9.2801847458,48.8164558411],"type":"Point"}
}