{
  "type": "Feature",
  "properties": {
    "iso:country":"DE",
    "sg:address":"An der M\u00e4rchenwiese 28",
    "sg:city":"Leipzig",
    "sg:phone":"+49 341/8773781",
    "sg:postcode":"04277",
    "sg:province":"Sachsen",
    "wof:name":"Berndt Sommer Ingenieur",
    "wof:placetype":"venue"
},
  "geometry": {"coordinates":[12.3996572495,51.3065452576],"type":"Point"}
}