{
  "type": "Feature",
  "properties": {
    "iso:country":"DE",
    "sg:address":"Liebigstr. 1",
    "sg:city":"Aschau",
    "sg:phone":"+49 8638/66666",
    "sg:postcode":"84544",
    "sg:province":"Bayern",
    "wof:name":"Cabaret Monte Christo",
    "wof:placetype":"venue"
},
  "geometry": {"coordinates":[12.374428,48.189919],"type":"Point"}
}