{
  "type": "Feature",
  "properties": {
    "iso:country":"DE",
    "sg:address":"Breslauer Str. 12a",
    "sg:city":"Fronhausen",
    "sg:phone":"+49 6426/966310",
    "sg:postcode":"35112",
    "sg:province":"Hessen",
    "wof:name":"Javier-ernsesto Bielinski Rechtsanw\u00e4lte",
    "wof:placetype":"venue"
},
  "geometry": {"coordinates":[8.7035160065,50.7055358887],"type":"Point"}
}