{
  "type": "Feature",
  "properties": {
    "iso:country":"DE",
    "sg:address":"Klosteracker 6",
    "sg:city":"N\u00f6rten-Hardenberg",
    "sg:postcode":"37176",
    "sg:province":"Niedersachsen",
    "wof:name":"Raith Grundst\u00fccksverwaltungsges.",
    "wof:placetype":"venue"
},
  "geometry": {"coordinates":[9.9351005554,51.622127533],"type":"Point"}
}