{
  "type": "Feature",
  "properties": {
    "iso:country":"DE",
    "sg:address":"Marienbrunnenstr. 1",
    "sg:city":"Leipzig",
    "sg:postcode":"04299",
    "sg:province":"Sachsen",
    "wof:name":"Dr. Med. Almut Lorenz",
    "wof:placetype":"venue"
},
  "geometry": {"coordinates":[12.411008,51.315811],"type":"Point"}
}