{
  "type": "Feature",
  "properties": {
    "iso:country":"DE",
    "sg:address":"Am Pfaffenpfad 30",
    "sg:city":"N\u00fcdlingen",
    "sg:phone":"+49 971/71280",
    "sg:postcode":"97720",
    "sg:province":"Bayern",
    "wof:name":"Klaus Hofmann",
    "wof:placetype":"venue"
},
  "geometry": {"coordinates":[10.1125192642,50.2185516357],"type":"Point"}
}