{
  "type": "Feature",
  "properties": {
    "iso:country":"DE",
    "sg:address":"Vorwerk 2",
    "sg:city":"Sulingen",
    "sg:phone":"+49 4271/3876",
    "sg:postcode":"27232",
    "sg:province":"Niedersachsen",
    "wof:name":"Soziales Hilfswerk Sulinger Land",
    "wof:placetype":"venue"
},
  "geometry": {"coordinates":[8.779335,52.668423],"type":"Point"}
}