{
  "type": "Feature",
  "properties": {
    "iso:country":"DE",
    "sg:address":"Torstr. 4",
    "sg:city":"T\u00fcbingen",
    "sg:phone":"+49 7071/791956",
    "sg:postcode":"72070",
    "sg:province":"Baden-W\u00fcrttemberg",
    "wof:name":"Hartmut Kre\u00df Fotograf",
    "wof:placetype":"venue"
},
  "geometry": {"coordinates":[9.0005464554,48.5009384155],"type":"Point"}
}