{
  "type": "Feature",
  "properties": {
    "iso:country":"DE",
    "sg:address":"Focher Str. 140",
    "sg:city":"Solingen",
    "sg:phone":"+49 212/316688",
    "sg:postcode":"42719",
    "sg:province":"Nordrhein-Westfalen",
    "wof:name":"Pizzeria Bella Italia",
    "wof:placetype":"venue"
},
  "geometry": {"coordinates":[7.0587520599,51.1888465881],"type":"Point"}
}