{
  "type": "Feature",
  "properties": {
    "iso:country":"DE",
    "sg:address":"Panoramastr. 7",
    "sg:city":"R\u00f6merstein",
    "sg:phone":"+49 7382/333",
    "sg:postcode":"72587",
    "sg:province":"Baden-W\u00fcrttemberg",
    "wof:name":"Vereinsgastst\u00e4tte Sportverein Zainingen 1926 E. V.",
    "wof:placetype":"venue"
},
  "geometry": {"coordinates":[9.5483140945,48.4851150513],"type":"Point"}
}