{
  "type": "Feature",
  "properties": {
    "iso:country":"DE",
    "sg:address":"Pognerstr. 6",
    "sg:city":"M\u00fcnchen",
    "sg:phone":"+49 89/7233478",
    "sg:postcode":"81379",
    "sg:province":"Bayern",
    "wof:name":"Hans Kraft Wettannahme",
    "wof:placetype":"venue"
},
  "geometry": {"coordinates":[11.54533,48.104748],"type":"Point"}
}