{
  "type": "Feature",
  "properties": {
    "iso:country":"DE",
    "sg:address":"Bippener Str. 14 a",
    "sg:city":"Eggerm\u00fchlen",
    "sg:phone":"+49 5435/955841",
    "sg:postcode":"49577",
    "sg:province":"Niedersachsen",
    "wof:name":"Wiese Gmbh",
    "wof:placetype":"venue"
},
  "geometry": {"coordinates":[7.7766752243,52.5723953247],"type":"Point"}
}