{
  "type": "Feature",
  "properties": {
    "iso:country":"DE",
    "sg:address":"Ludwigstr. 75/77",
    "sg:city":"Ludwigshafen",
    "sg:phone":"+49 621/525202",
    "sg:postcode":"67059",
    "sg:province":"Rheinland-Pfalz",
    "wof:name":"P 97 Gastst\u00e4ttenbetriebs- Und Verwaltungs Gmbh",
    "wof:placetype":"venue"
},
  "geometry": {"coordinates":[8.447763443,49.4833908081],"type":"Point"}
}