{
  "type": "Feature",
  "properties": {
    "iso:country":"DE",
    "sg:address":"Glambecker Str. 24",
    "sg:city":"Neustrelitz",
    "sg:phone":"+49 3981/24990",
    "sg:postcode":"17235",
    "sg:province":"Mecklenburg-Vorpommern",
    "wof:name":"R. Ocker",
    "wof:placetype":"venue"
},
  "geometry": {"coordinates":[13.0667982101,53.3658027649],"type":"Point"}
}