{
  "type": "Feature",
  "properties": {
    "iso:country":"DE",
    "sg:address":"Tannenweg 12",
    "sg:city":"Friesenheim",
    "sg:phone":"+49 7808/2691",
    "sg:postcode":"77948",
    "sg:province":"Baden-W\u00fcrttemberg",
    "wof:name":"Wolfgang Kupfer Architekt",
    "wof:placetype":"venue"
},
  "geometry": {"coordinates":[7.908147,48.394875],"type":"Point"}
}