{
  "type": "Feature",
  "properties": {
    "iso:country":"DE",
    "sg:address":"Drosselstr. 2b",
    "sg:city":"Neuss",
    "sg:phone":"+49 2131/746990",
    "sg:postcode":"41466",
    "sg:province":"Nordrhein-Westfalen",
    "wof:name":"Germerican Metals Vertriebs-gmbh",
    "wof:placetype":"venue"
},
  "geometry": {"coordinates":[6.681392,51.163235],"type":"Point"}
}