{
  "type": "Feature",
  "properties": {
    "iso:country":"DE",
    "sg:address":"Borsigstr. 19",
    "sg:city":"Reinbek",
    "sg:postcode":"21465",
    "sg:province":"Schleswig-Holstein",
    "wof:name":"Rok Schaltanlagenbau Gmbh",
    "wof:placetype":"venue"
},
  "geometry": {"coordinates":[10.23987,53.526104],"type":"Point"}
}