{
  "type": "Feature",
  "properties": {
    "iso:country":"DE",
    "sg:address":"Kiefernweg 2",
    "sg:city":"Laatzen",
    "sg:phone":"+49 511/827602",
    "sg:postcode":"30880",
    "sg:province":"Niedersachsen",
    "wof:name":"Psycho-soz. Beratungsstelle D. Diak. Werkes",
    "wof:placetype":"venue"
},
  "geometry": {"coordinates":[9.814039,52.302177],"type":"Point"}
}