{
  "type": "Feature",
  "properties": {
    "iso:country":"DE",
    "sg:address":"Binderstr. 9",
    "sg:city":"Hamburg",
    "sg:phone":"+49 40/4107839",
    "sg:postcode":"20148",
    "sg:province":"Hamburg",
    "wof:name":"Uwe Jenzen Handelsvertretung",
    "wof:placetype":"venue"
},
  "geometry": {"coordinates":[9.9884872437,53.5679283142],"type":"Point"}
}