{
  "type": "Feature",
  "properties": {
    "iso:country":"DE",
    "sg:address":"Ulmenweg 22",
    "sg:city":"Merseburg",
    "sg:phone":"+49 3461/503723",
    "sg:postcode":"06217",
    "sg:province":"Sachsen-Anhalt",
    "wof:name":"Bernd Rudloff",
    "wof:placetype":"venue"
},
  "geometry": {"coordinates":[11.981361,51.34726],"type":"Point"}
}