{
  "type": "Feature",
  "properties": {
    "iso:country":"DE",
    "sg:address":"Dickampstr. 5",
    "sg:city":"Gelsenkirchen",
    "sg:phone":"+49 209/170900",
    "sg:postcode":"45879",
    "sg:province":"Nordrhein-Westfalen",
    "wof:name":"Tebodin Consultants & Engineers Gmbh",
    "wof:placetype":"venue"
},
  "geometry": {"coordinates":[7.0964641571,51.5059661865],"type":"Point"}
}