{
  "type": "Feature",
  "properties": {
    "iso:country":"DE",
    "sg:address":"Langenheider Str. 21",
    "sg:city":"Werther",
    "sg:phone":"+49 5203/3266",
    "sg:postcode":"33824",
    "sg:province":"Nordrhein-Westfalen",
    "wof:name":"Hans-heinrich Tremper",
    "wof:placetype":"venue"
},
  "geometry": {"coordinates":[8.383839,52.099464],"type":"Point"}
}