{
  "type": "Feature",
  "properties": {
    "iso:country":"DE",
    "sg:address":"Gr\u00e4wingheide 1",
    "sg:city":"Dorsten",
    "sg:phone":"+49 2362/24400",
    "sg:postcode":"46282",
    "sg:province":"Nordrhein-Westfalen",
    "wof:name":"W. Balster",
    "wof:placetype":"venue"
},
  "geometry": {"coordinates":[7.0111250877,51.6375656128],"type":"Point"}
}