{
  "type": "Feature",
  "properties": {
    "iso:country":"DE",
    "sg:address":"F\u00f6hrenweg 2a",
    "sg:city":"Friedberg",
    "sg:phone":"+49 821/2799187",
    "sg:postcode":"86316",
    "sg:province":"Bayern",
    "wof:name":"Klaus Frank",
    "wof:placetype":"venue"
},
  "geometry": {"coordinates":[10.989708,48.378048],"type":"Point"}
}