{
  "type": "Feature",
  "properties": {
    "iso:country":"DE",
    "sg:address":"Annaberger Str. 81",
    "sg:city":"Kurort Oberwiesenthal",
    "sg:phone":"+49 37348/7225",
    "sg:postcode":"09484",
    "sg:province":"Sachsen",
    "wof:name":"Wiesentholer Hutzenstube",
    "wof:placetype":"venue"
},
  "geometry": {"coordinates":[12.9846038818,50.4246711731],"type":"Point"}
}