{
  "type": "Feature",
  "properties": {
    "iso:country":"DE",
    "sg:address":"Brendelweg 5",
    "sg:city":"Delmenhorst",
    "sg:phone":"+49 4221/21722",
    "sg:postcode":"27755",
    "sg:province":"Niedersachsen",
    "wof:name":"Elan Fris\u00f6r Gmbh",
    "wof:placetype":"venue"
},
  "geometry": {"coordinates":[8.6229887009,53.0324478149],"type":"Point"}
}