{
  "type": "Feature",
  "properties": {
    "iso:country":"DE",
    "sg:address":"Gablenzer Str. 39",
    "sg:city":"Chemnitz",
    "sg:phone":"+49 371/520540",
    "sg:postcode":"09127",
    "sg:province":"Sachsen",
    "wof:name":"Bauhandwerk Aufbau Gmbh & Co. Betriebs Kg",
    "wof:placetype":"venue"
},
  "geometry": {"coordinates":[12.9584827423,50.8292007446],"type":"Point"}
}