{
  "type": "Feature",
  "properties": {
    "iso:country":"DE",
    "sg:address":"Tullaweg 1",
    "sg:city":"Berlin",
    "sg:postcode":"12277",
    "sg:province":"Berlin",
    "wof:name":"Gemerski Beteiligungs Gmbh",
    "wof:placetype":"venue"
},
  "geometry": {"coordinates":[13.3722219467,52.4146842957],"type":"Point"}
}