{
  "type": "Feature",
  "properties": {
    "iso:country":"DE",
    "sg:address":"Maybachstr. 5",
    "sg:city":"Ulm",
    "sg:phone":"+49 731/44120",
    "sg:postcode":"89079",
    "sg:province":"Baden-W\u00fcrttemberg",
    "wof:name":"Fahrzeugrahmen-richtwerk E. Sontag Gmbh & Co. Kg",
    "wof:placetype":"venue"
},
  "geometry": {"coordinates":[9.9447727203,48.361579895],"type":"Point"}
}