{
  "type": "Feature",
  "properties": {
    "iso:country":"DE",
    "sg:address":"Tilsiter Str. 9",
    "sg:city":"Seeheim-Jugenheim",
    "sg:phone":"+49 6257/8979",
    "sg:postcode":"64342",
    "sg:province":"Hessen",
    "wof:name":"G\u00fcnther \u00dcbel",
    "wof:placetype":"venue"
},
  "geometry": {"coordinates":[8.6350736618,49.7758750916],"type":"Point"}
}