{
  "type": "Feature",
  "properties": {
    "iso:country":"DE",
    "sg:address":"Kutusowstr. 4",
    "sg:city":"Chemnitz",
    "sg:phone":"+49 371/724049",
    "sg:postcode":"09130",
    "sg:province":"Sachsen",
    "wof:name":"B. V\u00f6ltzke",
    "wof:placetype":"venue"
},
  "geometry": {"coordinates":[12.968693,50.83395],"type":"Point"}
}