{
  "type": "Feature",
  "properties": {
    "iso:country":"DE",
    "sg:address":"Parlerstr. 42",
    "sg:city":"Schw\u00e4bisch Gm\u00fcnd",
    "sg:phone":"+49 7171/2546",
    "sg:postcode":"73525",
    "sg:province":"Baden-W\u00fcrttemberg",
    "wof:name":"Jos Hoefnagel Krankengymnast",
    "wof:placetype":"venue"
},
  "geometry": {"coordinates":[9.798271,48.7957],"type":"Point"}
}