{
  "type": "Feature",
  "properties": {
    "iso:country":"DE",
    "sg:address":"Kirchstr. 4",
    "sg:city":"Haren",
    "sg:phone":"+49 5932/504996",
    "sg:postcode":"49733",
    "sg:province":"Niedersachsen",
    "wof:name":"M. Wehkamp Mende",
    "wof:placetype":"venue"
},
  "geometry": {"coordinates":[7.2417211533,52.7909355164],"type":"Point"}
}