{
  "type": "Feature",
  "properties": {
    "iso:country":"DE",
    "sg:address":"Schwimmbadstr. 3 Beerfurth",
    "sg:city":"Reichelsheim",
    "sg:phone":"+49 4961/642231",
    "sg:postcode":"64385",
    "sg:province":"Hessen",
    "wof:name":"Wilhelm Eberhardt Back - U. Schokoladenwaren Ohg",
    "wof:placetype":"venue"
},
  "geometry": {"coordinates":[8.840402,49.712505],"type":"Point"}
}