{
  "type": "Feature",
  "properties": {
    "iso:country":"DE",
    "sg:address":"Limbecker Str. 25",
    "sg:city":"Dortmund",
    "sg:phone":"+49 231/632653",
    "sg:postcode":"44388",
    "sg:province":"Nordrhein-Westfalen",
    "wof:name":"Manfred Ortmann",
    "wof:placetype":"venue"
},
  "geometry": {"coordinates":[7.3354148865,51.5004043579],"type":"Point"}
}