{
  "type": "Feature",
  "properties": {
    "iso:country":"DE",
    "sg:address":"Dr.-Rothermel-Str. 6",
    "sg:city":"Krumbach",
    "sg:phone":"+49 8282/4175",
    "sg:postcode":"86381",
    "sg:province":"Bayern",
    "wof:name":"Fritz Konrad",
    "wof:placetype":"venue"
},
  "geometry": {"coordinates":[10.359878,48.244476],"type":"Point"}
}