{
  "type": "Feature",
  "properties": {
    "iso:country":"DE",
    "sg:address":"D\u00fcbener Str. 40",
    "sg:city":"Pressel",
    "sg:postcode":"04849",
    "sg:province":"Sachsen",
    "wof:name":"Chemowerk Gmbh",
    "wof:placetype":"venue"
},
  "geometry": {"coordinates":[12.6970291138,51.5786018372],"type":"Point"}
}