{
  "type": "Feature",
  "properties": {
    "iso:country":"DE",
    "sg:address":"Salzer Weg 1",
    "sg:city":"Weltersburg",
    "sg:phone":"+49 6435/2041",
    "sg:postcode":"56459",
    "sg:province":"Rheinland-Pfalz",
    "wof:name":"Imbi\u00df Heinz W\u00fcst",
    "wof:placetype":"venue"
},
  "geometry": {"coordinates":[7.957654953,50.5213012695],"type":"Point"}
}