{
  "type": "Feature",
  "properties": {
    "iso:country":"DE",
    "sg:address":"Marderstraat 25",
    "sg:city":"Hamburg",
    "sg:phone":"+49 40/6024475",
    "sg:postcode":"22399",
    "sg:province":"Hamburg",
    "wof:name":"Ernst Otto Breudel",
    "wof:placetype":"venue"
},
  "geometry": {"coordinates":[10.0700893402,53.6585845947],"type":"Point"}
}