{
  "type": "Feature",
  "properties": {
    "iso:country":"DE",
    "sg:address":"Kieselstr. 2",
    "sg:city":"D\u00fcsseldorf",
    "sg:phone":"+49 211/684858",
    "sg:postcode":"40235",
    "sg:province":"Nordrhein-Westfalen",
    "wof:name":"Thomas Hauser",
    "wof:placetype":"venue"
},
  "geometry": {"coordinates":[6.8278169632,51.2383422852],"type":"Point"}
}