{
  "type": "Feature",
  "properties": {
    "iso:country":"DE",
    "sg:address":"Rotdornweg 11",
    "sg:city":"Gettorf",
    "sg:phone":"+49 4346/412210",
    "sg:postcode":"24214",
    "sg:province":"Schleswig-Holstein",
    "wof:name":"Ingwer Siewertsen",
    "wof:placetype":"venue"
},
  "geometry": {"coordinates":[9.9863967896,54.4021949768],"type":"Point"}
}