{
  "type": "Feature",
  "properties": {
    "iso:country":"DE",
    "sg:address":"Gro\u00dfe Schm\u00fctzstr.",
    "sg:city":"Oldenburg",
    "sg:phone":"+49 4361/626",
    "sg:postcode":"23758",
    "sg:province":"Schleswig-Holstein",
    "wof:name":"J. Wegner Werkzeuge",
    "wof:placetype":"venue"
},
  "geometry": {"coordinates":[-85.206237793,39.3398132324],"type":"Point"}
}