{
  "type": "Feature",
  "properties": {
    "iso:country":"DE",
    "sg:address":"Hindenburgstr. 151",
    "sg:city":"Wuppertal",
    "sg:phone":"+49 202/742727",
    "sg:postcode":"42117",
    "sg:province":"Nordrhein-Westfalen",
    "wof:name":"Ackermann & Fleck Ohg",
    "wof:placetype":"venue"
},
  "geometry": {"coordinates":[7.1165108681,51.2447319031],"type":"Point"}
}