{
  "type": "Feature",
  "properties": {
    "iso:country":"DE",
    "sg:address":"Amberger Str. 46",
    "sg:city":"Kemnath",
    "sg:phone":"+49 9642/7789",
    "sg:postcode":"95478",
    "sg:province":"Bayern",
    "wof:name":"Norbert Veigl Gmbh",
    "wof:placetype":"venue"
},
  "geometry": {"coordinates":[11.88794,49.863983],"type":"Point"}
}