{
  "type": "Feature",
  "properties": {
    "iso:country":"DE",
    "sg:address":"Robert-Koch-Str. 10",
    "sg:city":"Friedrichshafen",
    "sg:phone":"+49 7541/41670",
    "sg:postcode":"88048",
    "sg:province":"Baden-W\u00fcrttemberg",
    "wof:name":"E. Und M. Wirth",
    "wof:placetype":"venue"
},
  "geometry": {"coordinates":[9.434753418,47.6687049866],"type":"Point"}
}