{
  "type": "Feature",
  "properties": {
    "iso:country":"DE",
    "sg:address":"Sulzburger Str. 37",
    "sg:city":"Freiburg",
    "sg:phone":"+49 761/443799",
    "sg:postcode":"79114",
    "sg:province":"Baden-W\u00fcrttemberg",
    "wof:name":"Reinhard Klingele",
    "wof:placetype":"venue"
},
  "geometry": {"coordinates":[7.8088140488,47.9968147278],"type":"Point"}
}