{
  "type": "Feature",
  "properties": {
    "iso:country":"DE",
    "sg:address":"Markt 10",
    "sg:city":"Kahla",
    "sg:phone":"+49 36424/22617",
    "sg:postcode":"07768",
    "sg:province":"Th\u00fcringen",
    "wof:name":"Ratskeller",
    "wof:placetype":"venue"
},
  "geometry": {"coordinates":[11.5885705948,50.8027572632],"type":"Point"}
}