{
  "type": "Feature",
  "properties": {
    "iso:country":"DE",
    "sg:address":"Sch\u00fctzenstr. 4",
    "sg:city":"Erfurt",
    "sg:phone":"+49 361/3746226",
    "sg:postcode":"99096",
    "sg:province":"Th\u00fcringen",
    "wof:name":"Golf-verband Nordrhein-westfalen",
    "wof:placetype":"venue"
},
  "geometry": {"coordinates":[11.0325126648,50.9571762085],"type":"Point"}
}