{
  "type": "Feature",
  "properties": {
    "iso:country":"DE",
    "sg:address":"Schwarzer Weg 1",
    "sg:city":"Rhede",
    "sg:phone":"+49 4964/377",
    "sg:postcode":"26899",
    "sg:province":"Niedersachsen",
    "wof:name":"R. Und S. Grote",
    "wof:placetype":"venue"
},
  "geometry": {"coordinates":[7.233573,53.068375],"type":"Point"}
}