{
  "type": "Feature",
  "properties": {
    "iso:country":"DE",
    "sg:address":"Dieselstr. 61",
    "sg:city":"Wuppertal",
    "sg:phone":"+49 202/666389",
    "sg:postcode":"42389",
    "sg:province":"Nordrhein-Westfalen",
    "wof:name":"Erich Abshoff Inh. Gerd Abshoff",
    "wof:placetype":"venue"
},
  "geometry": {"coordinates":[7.2581801414,51.2821884155],"type":"Point"}
}