{
  "type": "Feature",
  "properties": {
    "iso:country":"DE",
    "sg:address":"Franz-Mecker-Str. 7a",
    "sg:city":"Bitburg",
    "sg:phone":"+49 6561/67920",
    "sg:postcode":"54634",
    "sg:province":"Rheinland-Pfalz",
    "wof:name":"Rainer Molitor",
    "wof:placetype":"venue"
},
  "geometry": {"coordinates":[6.5206398964,49.9673995972],"type":"Point"}
}