{
  "type": "Feature",
  "properties": {
    "iso:country":"DE",
    "sg:address":"Schlehdornweg 28",
    "sg:city":"Siegen",
    "sg:phone":"+49 271/76442",
    "sg:postcode":"57076",
    "sg:province":"Nordrhein-Westfalen",
    "wof:name":"Ev. Pfarramt I Siegen-weidenau Bz. Ii",
    "wof:placetype":"venue"
},
  "geometry": {"coordinates":[8.0455026627,50.8972587585],"type":"Point"}
}