{
  "type": "Feature",
  "properties": {
    "iso:country":"DE",
    "sg:address":"Hermann-L\u00f6ns-Str. 48",
    "sg:city":"Engen",
    "sg:phone":"+49 7733/2919",
    "sg:postcode":"78234",
    "sg:province":"Baden-W\u00fcrttemberg",
    "wof:name":"Freunde Der Kinderheimat Sonnenuhr E. V.",
    "wof:placetype":"venue"
},
  "geometry": {"coordinates":[8.7633476257,47.8565177917],"type":"Point"}
}