{
  "type": "Feature",
  "properties": {
    "iso:country":"DE",
    "sg:address":"Ringstr. 58",
    "sg:city":"D\u00fcsseldorf",
    "sg:phone":"+49 211/286627",
    "sg:postcode":"40629",
    "sg:province":"Nordrhein-Westfalen",
    "wof:name":"Verlag B. Koch",
    "wof:placetype":"venue"
},
  "geometry": {"coordinates":[6.8867239952,51.2634086609],"type":"Point"}
}