{
  "type": "Feature",
  "properties": {
    "iso:country":"DE",
    "sg:address":"Jahnstr. 60",
    "sg:city":"Hockenheim",
    "sg:phone":"+49 6205/4000",
    "sg:postcode":"68766",
    "sg:province":"Baden-W\u00fcrttemberg",
    "wof:name":"M\u00fcnch",
    "wof:placetype":"venue"
},
  "geometry": {"coordinates":[8.557778,49.317909],"type":"Point"}
}