{
  "type": "Feature",
  "properties": {
    "iso:country":"DE",
    "sg:address":"Moosbergweg 1",
    "sg:city":"Gro\u00dfenkneten",
    "sg:phone":"+49 4435/5950",
    "sg:postcode":"26197",
    "sg:province":"Niedersachsen",
    "wof:name":"Walter Drewes",
    "wof:placetype":"venue"
},
  "geometry": {"coordinates":[8.2952699661,52.9500198364],"type":"Point"}
}