{
  "type": "Feature",
  "properties": {
    "iso:country":"DE",
    "sg:address":"Regensburger Str. 6",
    "sg:city":"Straubing",
    "sg:phone":"+49 9421/81859",
    "sg:postcode":"94315",
    "sg:province":"Bayern",
    "wof:name":"K\u00d6 Spielcaf\u00e9",
    "wof:placetype":"venue"
},
  "geometry": {"coordinates":[12.563796,48.880543],"type":"Point"}
}