{
  "type": "Feature",
  "properties": {
    "iso:country":"DE",
    "sg:address":"Friedrichstr. 42",
    "sg:city":"Haan",
    "sg:phone":"+49 212/91308",
    "sg:postcode":"42781",
    "sg:province":"Nordrhein-Westfalen",
    "wof:name":"Peter Kubisch",
    "wof:placetype":"venue"
},
  "geometry": {"coordinates":[7.0124258995,51.1955680847],"type":"Point"}
}