{
  "type": "Feature",
  "properties": {
    "iso:country":"DE",
    "sg:address":"Dorfstr. 75",
    "sg:city":"Wulfersdorf",
    "sg:phone":"+49 33963/40275",
    "sg:postcode":"16909",
    "sg:province":"Brandenburg",
    "wof:name":"Massey-ferguson-zentrum Landmaschinenhandel Gmbh",
    "wof:placetype":"venue"
},
  "geometry": {"coordinates":[12.415186,53.24527],"type":"Point"}
}