{
  "type": "Feature",
  "properties": {
    "iso:country":"DE",
    "sg:address":"Berliner Platz 13",
    "sg:city":"Hamburg",
    "sg:phone":"+49 40/6791133",
    "sg:postcode":"22045",
    "sg:province":"Hamburg",
    "wof:name":"Christel Jeglinski",
    "wof:placetype":"venue"
},
  "geometry": {"coordinates":[10.141752243,53.5843505859],"type":"Point"}
}