{
  "type": "Feature",
  "properties": {
    "iso:country":"DE",
    "sg:address":"Albstr. 55 b",
    "sg:city":"Stuttgart",
    "sg:phone":"+49 711/7656663",
    "sg:postcode":"70597",
    "sg:province":"Baden-W\u00fcrttemberg",
    "wof:name":"Alfred Koppen Garten- Und",
    "wof:placetype":"venue"
},
  "geometry": {"coordinates":[9.165516,48.743408],"type":"Point"}
}