{
  "type": "Feature",
  "properties": {
    "iso:country":"DE",
    "sg:address":"Gr\u00fcnbacher Str. 27",
    "sg:city":"Falkenstein",
    "sg:postcode":"08223",
    "sg:province":"Sachsen",
    "wof:name":"Dr. Med. Matthias R\u00fchmer",
    "wof:placetype":"venue"
},
  "geometry": {"coordinates":[12.36736,50.468651],"type":"Point"}
}