{
  "type": "Feature",
  "properties": {
    "iso:country":"DE",
    "sg:address":"Dorfkamp 13",
    "sg:city":"Gro\u00dfenkneten",
    "sg:phone":"+49 4435/5502",
    "sg:postcode":"26197",
    "sg:province":"Niedersachsen",
    "wof:name":"Heinz-hermann Abel",
    "wof:placetype":"venue"
},
  "geometry": {"coordinates":[8.21577,52.942688],"type":"Point"}
}