{
  "type": "Feature",
  "properties": {
    "iso:country":"DE",
    "sg:address":"Portenl\u00e4ngerstr. 37",
    "sg:city":"Gr\u00fcnwald",
    "sg:phone":"+49 89/641640",
    "sg:postcode":"82031",
    "sg:province":"Bayern",
    "wof:name":"Ferenczy Publicity Gmbh",
    "wof:placetype":"venue"
},
  "geometry": {"coordinates":[11.534665,48.045521],"type":"Point"}
}