{
  "type": "Feature",
  "properties": {
    "iso:country":"DE",
    "sg:address":"Niederndorf 13",
    "sg:city":"Eggenfelden",
    "sg:phone":"+49 8721/8710",
    "sg:postcode":"84307",
    "sg:province":"Bayern",
    "wof:name":"Josef Winzl Immobilienmakler",
    "wof:placetype":"venue"
},
  "geometry": {"coordinates":[12.7602157593,48.3857345581],"type":"Point"}
}