{
  "type": "Feature",
  "properties": {
    "iso:country":"DE",
    "sg:address":"Lindenstr. 9",
    "sg:city":"Moorenweis",
    "sg:phone":"+49 8146/9162",
    "sg:postcode":"82272",
    "sg:province":"Bayern",
    "wof:name":"A. Kirchner",
    "wof:placetype":"venue"
},
  "geometry": {"coordinates":[11.078619957,48.1553573608],"type":"Point"}
}