{
  "type": "Feature",
  "properties": {
    "iso:country":"DE",
    "sg:address":"Rh\u00f6nhallenstr. 10",
    "sg:city":"Burkardroth",
    "sg:phone":"+49 9734/258",
    "sg:postcode":"97705",
    "sg:province":"Bayern",
    "wof:name":"Katholisches Pfarramt St. Sebastianus",
    "wof:placetype":"venue"
},
  "geometry": {"coordinates":[9.9822492599,50.2868423462],"type":"Point"}
}