{
  "type": "Feature",
  "properties": {
    "iso:country":"DE",
    "sg:address":"Im Uhrengut 1",
    "sg:city":"Rheinau",
    "sg:phone":"+49 7227/1001",
    "sg:postcode":"77866",
    "sg:province":"Baden-W\u00fcrttemberg",
    "wof:name":"Medical Electronics Gmbh",
    "wof:placetype":"venue"
},
  "geometry": {"coordinates":[7.9953651428,48.6870765686],"type":"Point"}
}