{
  "type": "Feature",
  "properties": {
    "iso:country":"DE",
    "sg:address":"Wattenbacher Str. 49",
    "sg:city":"S\u00f6hrewald",
    "sg:phone":"+49 5608/94940",
    "sg:postcode":"34320",
    "sg:province":"Hessen",
    "wof:name":"Planumet Schmidt Gmbh & Co. Kg",
    "wof:placetype":"venue"
},
  "geometry": {"coordinates":[9.578403,51.232674],"type":"Point"}
}