{
  "type": "Feature",
  "properties": {
    "iso:country":"DE",
    "sg:address":"Wiesenstr. 4",
    "sg:city":"Simmerath",
    "sg:phone":"+49 2473/2622",
    "sg:postcode":"52152",
    "sg:province":"Nordrhein-Westfalen",
    "wof:name":"Kurt Nellessen Architekt",
    "wof:placetype":"venue"
},
  "geometry": {"coordinates":[6.380104,50.617264],"type":"Point"}
}