{
  "type": "Feature",
  "properties": {
    "iso:country":"DE",
    "sg:address":"Moissistr. 29",
    "sg:city":"Berlin",
    "sg:phone":"+49 30/6778830",
    "sg:postcode":"12489",
    "sg:province":"Berlin",
    "wof:name":"Btg Arbeit Beratungs- Und Tr\u00e4gergesellschaft F\u00fcr",
    "wof:placetype":"venue"
},
  "geometry": {"coordinates":[13.549133,52.433147],"type":"Point"}
}