{
  "type": "Feature",
  "properties": {
    "iso:country":"DE",
    "sg:address":"Br\u00fcckstr. 46",
    "sg:city":"Erkelenz",
    "sg:phone":"+49 2431/2323",
    "sg:postcode":"41812",
    "sg:province":"Nordrhein-Westfalen",
    "wof:name":"Eva-maria Vieten",
    "wof:placetype":"venue"
},
  "geometry": {"coordinates":[6.31983,51.082088],"type":"Point"}
}