{
  "type": "Feature",
  "properties": {
    "iso:country":"DE",
    "sg:address":"Blockhausstr. 1",
    "sg:city":"Reichshof",
    "sg:phone":"+49 2265/274",
    "sg:postcode":"51580",
    "sg:province":"Nordrhein-Westfalen",
    "wof:name":"Hadamer-sch\u00fcrholz",
    "wof:placetype":"venue"
},
  "geometry": {"coordinates":[7.695358,50.987762],"type":"Point"}
}