{
  "type": "Feature",
  "properties": {
    "iso:country":"DE",
    "sg:address":"Saalower Str. 26",
    "sg:city":"Berlin",
    "sg:phone":"+49 30/7447526",
    "sg:postcode":"12307",
    "sg:province":"Berlin",
    "wof:name":"Werner Leckebusch Kameramann",
    "wof:placetype":"venue"
},
  "geometry": {"coordinates":[13.4091949463,52.3773727417],"type":"Point"}
}