{
  "type": "Feature",
  "properties": {
    "iso:country":"DE",
    "sg:address":"Friedrich-Ebert-Str. 5",
    "sg:city":"Leuna",
    "sg:phone":"+49 3461/813132",
    "sg:postcode":"06237",
    "sg:province":"Sachsen-Anhalt",
    "wof:name":"Michael Roder",
    "wof:placetype":"venue"
},
  "geometry": {"coordinates":[12.0014572144,51.3325004578],"type":"Point"}
}