{
  "type": "Feature",
  "properties": {
    "iso:country":"DE",
    "sg:address":"Rosenstr. 3",
    "sg:city":"Otterndorf",
    "sg:phone":"+49 4751/6518",
    "sg:postcode":"21762",
    "sg:province":"Niedersachsen",
    "wof:name":"T. Lau",
    "wof:placetype":"venue"
},
  "geometry": {"coordinates":[8.9077444077,53.8099060059],"type":"Point"}
}