{
  "type": "Feature",
  "properties": {
    "iso:country":"DE",
    "sg:address":"Schmidtgasse 22",
    "sg:city":"Gelnhausen",
    "sg:phone":"+49 6051/2622",
    "sg:postcode":"63571",
    "sg:province":"Hessen",
    "wof:name":"Betten-schmidt Inh. Hans Ulrich Schmidt",
    "wof:placetype":"venue"
},
  "geometry": {"coordinates":[9.1925897598,50.201210022],"type":"Point"}
}