{
  "type": "Feature",
  "properties": {
    "iso:country":"DE",
    "sg:address":"Markgrafenstr. 3",
    "sg:city":"Bielefeld",
    "sg:phone":"+49 521/172102",
    "sg:postcode":"33602",
    "sg:province":"Nordrhein-Westfalen",
    "wof:name":"Fitness Forum G\u00f6tza Und Pentaiski",
    "wof:placetype":"venue"
},
  "geometry": {"coordinates":[8.5411262512,52.0261192322],"type":"Point"}
}