{
  "type": "Feature",
  "properties": {
    "iso:country":"DE",
    "sg:address":"Dorfstr. 75a",
    "sg:city":"Wulfersdorf",
    "sg:phone":"+49 33963/40267",
    "sg:postcode":"16909",
    "sg:province":"Brandenburg",
    "wof:name":"Wf Immobilien Gmbh",
    "wof:placetype":"venue"
},
  "geometry": {"coordinates":[12.4151859283,53.2452697754],"type":"Point"}
}