{
  "type": "Feature",
  "properties": {
    "iso:country":"DE",
    "sg:address":"Burgstr. 16",
    "sg:city":"Bad K\u00f6sen",
    "sg:phone":"+49 34463/27558",
    "sg:postcode":"06628",
    "sg:province":"Sachsen-Anhalt",
    "wof:name":"B. Tischner",
    "wof:placetype":"venue"
},
  "geometry": {"coordinates":[11.7154531479,51.1309776306],"type":"Point"}
}