{
  "type": "Feature",
  "properties": {
    "iso:country":"DE",
    "sg:address":"Altbuchhorster Str. 43a",
    "sg:city":"Gr\u00fcnheide",
    "sg:postcode":"15537",
    "sg:province":"Brandenburg",
    "wof:name":"Ingenieurb\u00fcro Grosse & Partner",
    "wof:placetype":"venue"
},
  "geometry": {"coordinates":[13.8374767303,52.4346046448],"type":"Point"}
}