{
  "type": "Feature",
  "properties": {
    "iso:country":"DE",
    "sg:address":"Hauptstr. 64",
    "sg:city":"Volkach",
    "sg:phone":"+49 9381/1330",
    "sg:postcode":"97332",
    "sg:province":"Bayern",
    "wof:name":"Hans Neudecker",
    "wof:placetype":"venue"
},
  "geometry": {"coordinates":[10.22521,49.86739],"type":"Point"}
}