{
  "type": "Feature",
  "properties": {
    "iso:country":"DE",
    "sg:address":"Ernst-Reuter-Str. 16",
    "sg:city":"Hof",
    "sg:phone":"+49 9281/92799",
    "sg:postcode":"95032",
    "sg:province":"Bayern",
    "wof:name":"Dieter Spitzbarth",
    "wof:placetype":"venue"
},
  "geometry": {"coordinates":[11.914788,50.30595],"type":"Point"}
}