{
  "type": "Feature",
  "properties": {
    "iso:country":"DE",
    "sg:address":"Otto-Hahn-Str. 10",
    "sg:city":"Dachau",
    "sg:phone":"+49 8131/52483",
    "sg:postcode":"85221",
    "sg:province":"Bayern",
    "wof:name":"Renato Auto Spezialsitze Gmbh",
    "wof:placetype":"venue"
},
  "geometry": {"coordinates":[11.4729013443,48.2677268982],"type":"Point"}
}