{
  "type": "Feature",
  "properties": {
    "iso:country":"DE",
    "sg:address":"Brennickel 4",
    "sg:city":"Coswig",
    "sg:phone":"+49 34903/4190",
    "sg:postcode":"06869",
    "sg:province":"Sachsen-Anhalt",
    "wof:name":"Elektroinstallation Bellrich Gmbh",
    "wof:placetype":"venue"
},
  "geometry": {"coordinates":[12.385796,51.92762],"type":"Point"}
}