{
  "type": "Feature",
  "properties": {
    "iso:country":"DE",
    "sg:address":"Dorfstr. 9",
    "sg:city":"Taucha",
    "sg:postcode":"04425",
    "sg:province":"Sachsen",
    "wof:name":"Mathias Ranz",
    "wof:placetype":"venue"
},
  "geometry": {"coordinates":[12.490562,51.390656],"type":"Point"}
}