{
  "type": "Feature",
  "properties": {
    "iso:country":"DE",
    "sg:address":"Rathausstr. 19",
    "sg:city":"Soest",
    "sg:phone":"+49 2921/15845",
    "sg:postcode":"59494",
    "sg:province":"Nordrhein-Westfalen",
    "wof:name":"Eichhorn & Schipporeit Gmbh",
    "wof:placetype":"venue"
},
  "geometry": {"coordinates":[8.1079626083,51.5708694458],"type":"Point"}
}