{
  "type": "Feature",
  "properties": {
    "iso:country":"DE",
    "sg:address":"Gutenbergweg 7",
    "sg:city":"Delmenhorst",
    "sg:phone":"+49 4221/60158",
    "sg:postcode":"27755",
    "sg:province":"Niedersachsen",
    "wof:name":"Rolf Daut Pharmazeut. Grosshandel",
    "wof:placetype":"venue"
},
  "geometry": {"coordinates":[8.630767,53.036823],"type":"Point"}
}