{
  "type": "Feature",
  "properties": {
    "iso:country":"DE",
    "sg:address":"Chemnitzstr. 2",
    "sg:city":"Barmstedt",
    "sg:phone":"+49 4123/2673",
    "sg:postcode":"25355",
    "sg:province":"Schleswig-Holstein",
    "wof:name":"H. H. Glismann",
    "wof:placetype":"venue"
},
  "geometry": {"coordinates":[9.772477,53.78912],"type":"Point"}
}