{
  "type": "Feature",
  "properties": {
    "iso:country":"DE",
    "sg:address":"Maiergschwendterstr. 11",
    "sg:city":"Ruhpolding",
    "sg:phone":"+49 8663/9572",
    "sg:postcode":"83324",
    "sg:province":"Bayern",
    "wof:name":"G\u00e4stehaus L. Heizinger",
    "wof:placetype":"venue"
},
  "geometry": {"coordinates":[12.6399259567,47.7640075684],"type":"Point"}
}