{
  "type": "Feature",
  "properties": {
    "iso:country":"DE",
    "sg:address":"Markendorfer Str. 142",
    "sg:city":"Melle",
    "sg:phone":"+49 5427/1323",
    "sg:postcode":"49328",
    "sg:province":"Niedersachsen",
    "wof:name":"Ewald Kammann",
    "wof:placetype":"venue"
},
  "geometry": {"coordinates":[8.463539,52.245586],"type":"Point"}
}