{
  "type": "Feature",
  "properties": {
    "iso:country":"DE",
    "sg:address":"Schwalbenweg 2",
    "sg:city":"Rutesheim",
    "sg:phone":"+49 7152/53314",
    "sg:postcode":"71277",
    "sg:province":"Baden-W\u00fcrttemberg",
    "wof:name":"Werner Keppler Mech. Werkstatt",
    "wof:placetype":"venue"
},
  "geometry": {"coordinates":[8.901855,48.813168],"type":"Point"}
}