{
  "type": "Feature",
  "properties": {
    "iso:country":"DE",
    "sg:address":"Siemensstr. 5",
    "sg:city":"Glauchau",
    "sg:phone":"+49 4937/6360960",
    "sg:postcode":"08371",
    "sg:province":"Sachsen",
    "wof:name":"A Kayser Gmbh & Co Kg Glauchau",
    "wof:placetype":"venue"
},
  "geometry": {"coordinates":[12.5202827454,50.8360824585],"type":"Point"}
}