{
  "type": "Feature",
  "properties": {
    "iso:country":"DE",
    "sg:address":"Lange Str. 36",
    "sg:city":"Viersen",
    "sg:phone":"+49 2162/56323",
    "sg:postcode":"41751",
    "sg:province":"Nordrhein-Westfalen",
    "wof:name":"Alibi",
    "wof:placetype":"venue"
},
  "geometry": {"coordinates":[6.3331542015,51.2520828247],"type":"Point"}
}