{
  "type": "Feature",
  "properties": {
    "iso:country":"DE",
    "sg:address":"Wittbr\u00e4ucker Str.1",
    "sg:city":"Dortmund",
    "sg:phone":"+49 231/458592",
    "sg:postcode":"44287",
    "sg:province":"Nordrhein-Westfalen",
    "wof:name":"Dresdner Bank",
    "wof:placetype":"venue"
},
  "geometry": {"coordinates":[7.555155,51.490955],"type":"Point"}
}