{
  "type": "Feature",
  "properties": {
    "iso:country":"DE",
    "sg:address":"Hagener Str. 362",
    "sg:city":"Dortmund",
    "sg:phone":"+49 231/731223",
    "sg:postcode":"44229",
    "sg:province":"Nordrhein-Westfalen",
    "wof:name":"Alfons Bl\u00f6mer",
    "wof:placetype":"venue"
},
  "geometry": {"coordinates":[7.45765,51.450539],"type":"Point"}
}