{
  "type": "Feature",
  "properties": {
    "iso:country":"DE",
    "sg:address":"Betzenstr. 10",
    "sg:city":"Saarbr\u00fccken",
    "sg:postcode":"66111",
    "sg:province":"Saarland",
    "wof:name":"Naturheilpraxis Lenzen Gmbh",
    "wof:placetype":"venue"
},
  "geometry": {"coordinates":[6.9958548546,49.2350730896],"type":"Point"}
}