{
  "type": "Feature",
  "properties": {
    "iso:country":"DE",
    "sg:address":"Ringbahnstr. 13",
    "sg:city":"Berlin",
    "sg:phone":"+49 4930/7526401",
    "sg:postcode":"12099",
    "sg:province":"Berlin",
    "wof:name":"Tischler Wick Gmbh",
    "wof:placetype":"venue"
},
  "geometry": {"coordinates":[13.3935070038,52.4664344788],"type":"Point"}
}