{
  "type": "Feature",
  "properties": {
    "iso:country":"DE",
    "sg:address":"Hindenburgring 16",
    "sg:city":"Espelkamp",
    "sg:phone":"+49 5772/91040",
    "sg:postcode":"32339",
    "sg:province":"Nordrhein-Westfalen",
    "wof:name":"Kadeco Sonnenschutzsysteme Gmbh",
    "wof:placetype":"venue"
},
  "geometry": {"coordinates":[8.631409,52.370716],"type":"Point"}
}