{
  "type": "Feature",
  "properties": {
    "iso:country":"DE",
    "sg:address":"Mittelstr. 1",
    "sg:city":"Daaden",
    "sg:phone":"+49 2743/2054",
    "sg:postcode":"57567",
    "sg:province":"Rheinland-Pfalz",
    "wof:name":"City Reiseb\u00fcro",
    "wof:placetype":"venue"
},
  "geometry": {"coordinates":[7.967086792,50.7379379272],"type":"Point"}
}