{
  "type": "Feature",
  "properties": {
    "iso:country":"DE",
    "sg:address":"Bahnhofstr 1-2",
    "sg:city":"K\u00f6then",
    "sg:phone":"+49 3496/212777",
    "sg:postcode":"06366",
    "sg:province":"Sachsen-Anhalt",
    "wof:name":"Thiele Gmbh",
    "wof:placetype":"venue"
},
  "geometry": {"coordinates":[11.986762,51.750298],"type":"Point"}
}