{
  "type": "Feature",
  "properties": {
    "iso:country":"DE",
    "sg:address":"Farrenstr. 68",
    "sg:city":"Stuttgart",
    "sg:phone":"+49 711/467670",
    "sg:postcode":"70186",
    "sg:province":"Baden-W\u00fcrttemberg",
    "wof:name":"Dr. B. Zilger Steuerberater",
    "wof:placetype":"venue"
},
  "geometry": {"coordinates":[9.1993246078,48.7714958191],"type":"Point"}
}