{
  "type": "Feature",
  "properties": {
    "iso:country":"DE",
    "sg:address":"Neu\u00dfen 41",
    "sg:city":"Belgern",
    "sg:phone":"+49 34224/40174",
    "sg:postcode":"04874",
    "sg:province":"Sachsen",
    "wof:name":"Fuchs Bedachungsges. Mbh",
    "wof:placetype":"venue"
},
  "geometry": {"coordinates":[13.108637,51.448883],"type":"Point"}
}