{
  "type": "Feature",
  "properties": {
    "iso:country":"DE",
    "sg:address":"Lindenstr. 72",
    "sg:city":"Seebad Ahlbeck",
    "sg:phone":"+49 38378/34690",
    "sg:postcode":"17419",
    "sg:province":"Mecklenburg-Vorpommern",
    "wof:name":"S. Rausch Finanzberater",
    "wof:placetype":"venue"
},
  "geometry": {"coordinates":[14.0650997162,53.8867111206],"type":"Point"}
}