{
  "type": "Feature",
  "properties": {
    "iso:country":"DE",
    "sg:address":"Nobelstr. 52",
    "sg:city":"Rostock",
    "sg:postcode":"18059",
    "sg:province":"Mecklenburg-Vorpommern",
    "wof:name":"Hanse-allfinanz Immobilien Gmbh",
    "wof:placetype":"venue"
},
  "geometry": {"coordinates":[12.1168012619,54.0710525513],"type":"Point"}
}