{
  "type": "Feature",
  "properties": {
    "iso:country":"DE",
    "sg:address":"Iggelhorst 23",
    "sg:city":"Dortmund",
    "sg:phone":"+49 231/170053",
    "sg:postcode":"44149",
    "sg:province":"Nordrhein-Westfalen",
    "wof:name":"Dat Kraftfahrzeug- Sch\u00e4tzungs-stelle",
    "wof:placetype":"venue"
},
  "geometry": {"coordinates":[7.4053559303,51.5070266724],"type":"Point"}
}