{
  "type": "Feature",
  "properties": {
    "iso:country":"DE",
    "sg:address":"Brahmsstr. 15",
    "sg:city":"Hagen",
    "sg:phone":"+49 2331/56000",
    "sg:postcode":"58097",
    "sg:province":"Nordrhein-Westfalen",
    "wof:name":"Jan Gollus Architekt",
    "wof:placetype":"venue"
},
  "geometry": {"coordinates":[7.494377,51.369488],"type":"Point"}
}