{
  "type": "Feature",
  "properties": {
    "iso:country":"DE",
    "sg:address":"Lindenburger Allee 19",
    "sg:city":"K\u00f6ln",
    "sg:postcode":"50931",
    "sg:province":"Nordrhein-Westfalen",
    "wof:name":"Bu-vo Mineral\u00f6l Handelsgesellschaft Mbh",
    "wof:placetype":"venue"
},
  "geometry": {"coordinates":[6.9155888557,50.9265441895],"type":"Point"}
}