{
  "type": "Feature",
  "properties": {
    "iso:country":"DE",
    "sg:address":"Klausnerweg 3",
    "sg:city":"Scheyern",
    "sg:phone":"+49 8441/84878",
    "sg:postcode":"85298",
    "sg:province":"Bayern",
    "wof:name":"Josef Zeindl Bauunternehmen Gmbh",
    "wof:placetype":"venue"
},
  "geometry": {"coordinates":[11.4619,48.501057],"type":"Point"}
}