{
  "type": "Feature",
  "properties": {
    "iso:country":"DE",
    "sg:address":"Ludwigstr. 18b",
    "sg:city":"Kempten",
    "sg:phone":"+49 831/561230",
    "sg:postcode":"87437",
    "sg:province":"Bayern",
    "wof:name":"H. Polke Makler",
    "wof:placetype":"venue"
},
  "geometry": {"coordinates":[10.3248262405,47.7119369507],"type":"Point"}
}