{
  "type": "Feature",
  "properties": {
    "iso:country":"DE",
    "sg:address":"Kemnather Str. 16",
    "sg:city":"Mehlmeisel",
    "sg:phone":"+49 9272/6218",
    "sg:postcode":"95694",
    "sg:province":"Bayern",
    "wof:name":"Alois Matt",
    "wof:placetype":"venue"
},
  "geometry": {"coordinates":[11.871116,49.974758],"type":"Point"}
}