{
  "type": "Feature",
  "properties": {
    "iso:country":"DE",
    "sg:address":"Gro\u00df Breesener Str. 18",
    "sg:city":"Guben",
    "sg:phone":"+49 3561/3503",
    "sg:postcode":"03172",
    "sg:province":"Brandenburg",
    "wof:name":"Fischer & Partner Metallbau & Pneumatic Gbr",
    "wof:placetype":"venue"
},
  "geometry": {"coordinates":[14.700924,51.975513],"type":"Point"}
}