{
  "type": "Feature",
  "properties": {
    "iso:country":"DE",
    "sg:address":"Adelzreiterstr 15",
    "sg:city":"Rosenheim",
    "sg:phone":"+49 8031/3589530",
    "sg:postcode":"83022",
    "sg:province":"Bayern",
    "wof:name":"Thieltges, Sell + Partner",
    "wof:placetype":"venue"
},
  "geometry": {"coordinates":[12.1293230057,47.8579444885],"type":"Point"}
}