{
  "type": "Feature",
  "properties": {
    "iso:country":"DE",
    "sg:address":"Hausvogteiplatz 5-7",
    "sg:city":"Berlin",
    "sg:phone":"+49 30/63923980",
    "sg:postcode":"10117",
    "sg:province":"Berlin",
    "wof:name":"Max-planck-institut Ag",
    "wof:placetype":"venue"
},
  "geometry": {"coordinates":[13.3957796097,52.5132064819],"type":"Point"}
}