{
  "type": "Feature",
  "properties": {
    "iso:country":"DE",
    "sg:address":"Friedhofstr. 5",
    "sg:city":"Friesenheim",
    "sg:postcode":"77948",
    "sg:province":"Baden-W\u00fcrttemberg",
    "wof:name":"Frienet Schule Macht Internet Internet Macht Schule Ggmbh",
    "wof:placetype":"venue"
},
  "geometry": {"coordinates":[7.8817300797,48.3742713928],"type":"Point"}
}