{
  "type": "Feature",
  "properties": {
    "iso:country":"DE",
    "sg:address":"Lindenstr. 146",
    "sg:city":"D\u00fcsseldorf",
    "sg:phone":"+49 211/2291343",
    "sg:postcode":"40233",
    "sg:province":"Nordrhein-Westfalen",
    "wof:name":"Saitenwind Co Wolfgang Schmidt",
    "wof:placetype":"venue"
},
  "geometry": {"coordinates":[6.8075251579,51.2286529541],"type":"Point"}
}