{
  "type": "Feature",
  "properties": {
    "iso:country":"DE",
    "sg:address":"Welle 6",
    "sg:city":"Bielefeld",
    "sg:phone":"+49 521/64364",
    "sg:postcode":"33602",
    "sg:province":"Nordrhein-Westfalen",
    "wof:name":"Confetti Bielefeld - Japanische Artikel",
    "wof:placetype":"venue"
},
  "geometry": {"coordinates":[8.531978,52.019722],"type":"Point"}
}