{
  "type": "Feature",
  "properties": {
    "iso:country":"DE",
    "sg:address":"Winfridweg 18e",
    "sg:city":"Hamburg",
    "sg:phone":"+49 40/563344",
    "sg:postcode":"22529",
    "sg:province":"Hamburg",
    "wof:name":"Peter Heerdegen",
    "wof:placetype":"venue"
},
  "geometry": {"coordinates":[9.9544725418,53.5889015198],"type":"Point"}
}