{
  "type": "Feature",
  "properties": {
    "iso:country":"DE",
    "sg:address":"Poststr. 28",
    "sg:city":"Leonberg",
    "sg:phone":"+49 7152/72580",
    "sg:postcode":"71229",
    "sg:province":"Baden-W\u00fcrttemberg",
    "wof:name":"Leo-pizza-service",
    "wof:placetype":"venue"
},
  "geometry": {"coordinates":[9.005588,48.793015],"type":"Point"}
}