{
  "type": "Feature",
  "properties": {
    "iso:country":"DE",
    "sg:address":"Dresdner Str 55",
    "sg:city":"G\u00fctersloh",
    "sg:phone":"+49 5241/33040",
    "sg:postcode":"33330",
    "sg:province":"Nordrhein-Westfalen",
    "wof:name":"Garbalinski Maschinen-fenster- Und T\u00fcrentechnik Gmbh",
    "wof:placetype":"venue"
},
  "geometry": {"coordinates":[8.3660087585,51.9317550659],"type":"Point"}
}