{
  "type": "Feature",
  "properties": {
    "iso:country":"DE",
    "sg:address":"Wiesgarten 121",
    "sg:city":"Westenfeld",
    "sg:phone":"+49 36948/20623",
    "sg:postcode":"98631",
    "sg:province":"Th\u00fcringen",
    "wof:name":"Roswitha Flo\u00dfmann",
    "wof:placetype":"venue"
},
  "geometry": {"coordinates":[10.4942378998,50.4301834106],"type":"Point"}
}