{
  "type": "Feature",
  "properties": {
    "iso:country":"DE",
    "sg:address":"Jakobstr. 4a",
    "sg:city":"G\u00f6rlitz",
    "sg:phone":"+49 3581/403011",
    "sg:postcode":"02826",
    "sg:province":"Sachsen",
    "wof:name":"Thomas W\u00fcnsche",
    "wof:placetype":"venue"
},
  "geometry": {"coordinates":[14.9859056473,51.1505355835],"type":"Point"}
}