{
  "type": "Feature",
  "properties": {
    "iso:country":"DE",
    "sg:address":"Quenstedtstr. 12",
    "sg:city":"T\u00fcbingen",
    "sg:postcode":"72076",
    "sg:province":"Baden-W\u00fcrttemberg",
    "wof:name":"Net Suxxess Infosystems Gmbh",
    "wof:placetype":"venue"
},
  "geometry": {"coordinates":[9.047842,48.530769],"type":"Point"}
}