{
  "type": "Feature",
  "properties": {
    "iso:country":"DE",
    "sg:address":"Up de D\u00fcnen 14",
    "sg:city":"Spiekeroog",
    "sg:phone":"+49 4976/244",
    "sg:postcode":"26474",
    "sg:province":"Niedersachsen",
    "wof:name":"Pension Hilka Kiesow",
    "wof:placetype":"venue"
},
  "geometry": {"coordinates":[7.6882209778,53.7719039917],"type":"Point"}
}