{
  "type": "Feature",
  "properties": {
    "iso:country":"DE",
    "sg:address":"Mittelfeldstr 2",
    "sg:city":"Baden-Baden",
    "sg:phone":"+49 7221/95570",
    "sg:postcode":"76532",
    "sg:province":"Baden-W\u00fcrttemberg",
    "wof:name":"Bold Fertigbau Gmbh & Co Industriebau + Stahlbetonfertigteile",
    "wof:placetype":"venue"
},
  "geometry": {"coordinates":[8.175526619,48.8099555969],"type":"Point"}
}