{
  "type": "Feature",
  "properties": {
    "iso:country":"DE",
    "sg:address":"Grivitenstr. 30",
    "sg:city":"Markdorf",
    "sg:phone":"+49 7544/2264",
    "sg:postcode":"88677",
    "sg:province":"Baden-W\u00fcrttemberg",
    "wof:name":"Helmut Stehle",
    "wof:placetype":"venue"
},
  "geometry": {"coordinates":[9.38224,47.719639],"type":"Point"}
}