{
  "type": "Feature",
  "properties": {
    "iso:country":"DE",
    "sg:address":"Dorfstr. 9",
    "sg:city":"Ballin",
    "sg:phone":"+49 3964/210184",
    "sg:postcode":"17349",
    "sg:province":"Mecklenburg-Vorpommern",
    "wof:name":"Jens-uwe Thamm",
    "wof:placetype":"venue"
},
  "geometry": {"coordinates":[13.428639,53.458881],"type":"Point"}
}