{
  "type": "Feature",
  "properties": {
    "iso:country":"DE",
    "sg:address":"Peter-Paul-Str. 52",
    "sg:city":"Villmar",
    "sg:phone":"+49 6482/4228",
    "sg:postcode":"65606",
    "sg:province":"Hessen",
    "wof:name":"Anna Rosbach",
    "wof:placetype":"venue"
},
  "geometry": {"coordinates":[8.191714,50.391544],"type":"Point"}
}