{
  "type": "Feature",
  "properties": {
    "iso:country":"DE",
    "sg:address":"Leunisweg 11",
    "sg:city":"Hannover",
    "sg:phone":"+49 511/521599",
    "sg:postcode":"30559",
    "sg:province":"Niedersachsen",
    "wof:name":"Helmut Thiemann",
    "wof:placetype":"venue"
},
  "geometry": {"coordinates":[9.8140449524,52.3665351868],"type":"Point"}
}