{
  "type": "Feature",
  "properties": {
    "iso:country":"DE",
    "sg:address":"Herrenhausgasse 9",
    "sg:city":"Laubach",
    "sg:phone":"+49 6405/6823",
    "sg:postcode":"35321",
    "sg:province":"Hessen",
    "wof:name":"Erich Momberger",
    "wof:placetype":"venue"
},
  "geometry": {"coordinates":[8.9574508667,50.5482635498],"type":"Point"}
}