{
  "type": "Feature",
  "properties": {
    "iso:country":"DE",
    "sg:address":"Oststr. 19",
    "sg:city":"Bochum",
    "sg:phone":"+49 2327/88649",
    "sg:postcode":"44866",
    "sg:province":"Nordrhein-Westfalen",
    "wof:name":"Oeben & Thoben Gmbh",
    "wof:placetype":"venue"
},
  "geometry": {"coordinates":[7.1352348328,51.4809989929],"type":"Point"}
}