{
  "type": "Feature",
  "properties": {
    "iso:country":"DE",
    "sg:address":"Leer\u00dfer Str. 13",
    "sg:city":"Syke",
    "sg:phone":"+49 4242/70951",
    "sg:postcode":"28857",
    "sg:province":"Niedersachsen",
    "wof:name":"Erich Uhlenwinkel",
    "wof:placetype":"venue"
},
  "geometry": {"coordinates":[8.782961,52.930668],"type":"Point"}
}