{
  "type": "Feature",
  "properties": {
    "iso:country":"DE",
    "sg:address":"Auf der Dunau 1",
    "sg:city":"Seelze",
    "sg:phone":"+49 5137/3784",
    "sg:postcode":"30926",
    "sg:province":"Niedersachsen",
    "wof:name":"Jobst Von Alten",
    "wof:placetype":"venue"
},
  "geometry": {"coordinates":[9.54978,52.354755],"type":"Point"}
}