{
  "type": "Feature",
  "properties": {
    "iso:country":"DE",
    "sg:address":"Rothschildallee 30",
    "sg:city":"Frankfurt",
    "sg:phone":"+49 69/459530",
    "sg:postcode":"60389",
    "sg:province":"Hessen",
    "wof:name":"Bund Gegen Das Zwangs- Mitrauchen E. V.",
    "wof:placetype":"venue"
},
  "geometry": {"coordinates":[8.69622612,50.1277923584],"type":"Point"}
}