{
  "type": "Feature",
  "properties": {
    "iso:country":"DE",
    "sg:address":"Bahnhofsvorplatz 1a",
    "sg:city":"Grevenbroich",
    "sg:postcode":"41515",
    "sg:province":"Nordrhein-Westfalen",
    "wof:name":"Vicair Gmbh",
    "wof:placetype":"venue"
},
  "geometry": {"coordinates":[6.581,51.092525],"type":"Point"}
}