{
  "type": "Feature",
  "properties": {
    "iso:country":"DE",
    "sg:address":"Neum\u00fchle",
    "sg:city":"Waldenburg",
    "sg:phone":"+49 7942/8042",
    "sg:postcode":"74638",
    "sg:province":"Baden-W\u00fcrttemberg",
    "wof:name":"Campingplatz Neum\u00fchlsee Gmbh & Co.",
    "wof:placetype":"venue"
},
  "geometry": {"coordinates":[9.644825,49.163391],"type":"Point"}
}