{
  "type": "Feature",
  "properties": {
    "iso:country":"DE",
    "sg:address":"Ulmenstr. 32",
    "sg:city":"Ennepetal",
    "sg:phone":"+49 2333/70446",
    "sg:postcode":"58256",
    "sg:province":"Nordrhein-Westfalen",
    "wof:name":"Sebastian Hopff",
    "wof:placetype":"venue"
},
  "geometry": {"coordinates":[7.3275899887,51.2975349426],"type":"Point"}
}