{
  "type": "Feature",
  "properties": {
    "iso:country":"DE",
    "sg:address":"Rudolf-Sendig-Str. 7",
    "sg:city":"Bad Schandau",
    "sg:phone":"+49 35022/42327",
    "sg:postcode":"01814",
    "sg:province":"Sachsen",
    "wof:name":"Am Stadtpark",
    "wof:placetype":"venue"
},
  "geometry": {"coordinates":[14.1561336517,50.9178886414],"type":"Point"}
}