{
  "type": "Feature",
  "properties": {
    "iso:country":"DE",
    "sg:address":"Rudolf-Renner-Stra\u00dfe 33",
    "sg:city":"Dresden",
    "sg:phone":"+49 351/4111179",
    "sg:postcode":"01159",
    "sg:province":"Sachsen",
    "wof:name":"B\u00fcro F. Personal- U. Ingenieurdienstl. Dietmar Knobloch E.k.",
    "wof:placetype":"venue"
},
  "geometry": {"coordinates":[13.6928710938,51.0471534729],"type":"Point"}
}