{
  "type": "Feature",
  "properties": {
    "iso:country":"DE",
    "sg:address":"Ebersteinstr. 22",
    "sg:city":"Rheinstetten",
    "sg:phone":"+49 7242/7367",
    "sg:postcode":"76287",
    "sg:province":"Baden-W\u00fcrttemberg",
    "wof:name":"Else Miemietz Hebamme",
    "wof:placetype":"venue"
},
  "geometry": {"coordinates":[8.264491,48.966736],"type":"Point"}
}