{
  "type": "Feature",
  "properties": {
    "iso:country":"DE",
    "sg:address":"Stettiner Str. 81",
    "sg:city":"Eggesin",
    "sg:phone":"+49 39779/7600",
    "sg:postcode":"17367",
    "sg:province":"Mecklenburg-Vorpommern",
    "wof:name":"Hanseaten Gmbh",
    "wof:placetype":"venue"
},
  "geometry": {"coordinates":[14.0794582367,53.6811904907],"type":"Point"}
}