{
  "type": "Feature",
  "properties": {
    "iso:country":"DE",
    "sg:address":"Burgstr. 99",
    "sg:city":"Veltheim",
    "sg:phone":"+49 39426/313",
    "sg:postcode":"38835",
    "sg:province":"Sachsen-Anhalt",
    "wof:name":"Gastst\u00e4tte Zum Fallstein",
    "wof:placetype":"venue"
},
  "geometry": {"coordinates":[10.7455472946,52.0336341858],"type":"Point"}
}