{
  "type": "Feature",
  "properties": {
    "iso:country":"DE",
    "sg:address":"Kriemhildstr. 9",
    "sg:city":"Bielefeld",
    "sg:phone":"+49 521/132626",
    "sg:postcode":"33615",
    "sg:province":"Nordrhein-Westfalen",
    "wof:name":"Edith Horstmann Verm\u00f6gensverwaltung",
    "wof:placetype":"venue"
},
  "geometry": {"coordinates":[8.5184602737,52.0287971497],"type":"Point"}
}