{
  "type": "Feature",
  "properties": {
    "iso:country":"DE",
    "sg:address":"Ahornstr. 7",
    "sg:city":"Hamburg",
    "sg:phone":"+49 40/6565585",
    "sg:postcode":"22043",
    "sg:province":"Hamburg",
    "wof:name":"Karl-heinz Beese Grundst\u00fccks- Gmbh & Co. Kg",
    "wof:placetype":"venue"
},
  "geometry": {"coordinates":[10.0828504562,53.5658912659],"type":"Point"}
}