{
  "type": "Feature",
  "properties": {
    "iso:country":"DE",
    "sg:address":"Dehmelweg 14",
    "sg:city":"Stuttgart",
    "sg:phone":"+49 711/4760609",
    "sg:postcode":"70619",
    "sg:province":"Baden-W\u00fcrttemberg",
    "wof:name":"Kreutzer & Team Gmbh",
    "wof:placetype":"venue"
},
  "geometry": {"coordinates":[9.210319,48.742283],"type":"Point"}
}