{
  "type": "Feature",
  "properties": {
    "iso:country":"DE",
    "sg:address":"Brunnenstr. 11",
    "sg:city":"Mettlach",
    "sg:phone":"+49 6865/411",
    "sg:postcode":"66693",
    "sg:province":"Saarland",
    "wof:name":"Erich Zimmer Steinbruch",
    "wof:placetype":"venue"
},
  "geometry": {"coordinates":[6.5211548805,49.5034217834],"type":"Point"}
}