{
  "type": "Feature",
  "properties": {
    "iso:country":"DE",
    "sg:address":"S\u00e4ulingstr. 7 a",
    "sg:city":"Rieden",
    "sg:phone":"+49 8362/940600",
    "sg:postcode":"87669",
    "sg:province":"Bayern",
    "wof:name":"Ph Container Import Und Vertrieb Pavel Herbatsch",
    "wof:placetype":"venue"
},
  "geometry": {"coordinates":[10.711476,47.614204],"type":"Point"}
}