{
  "type": "Feature",
  "properties": {
    "iso:country":"DE",
    "sg:address":"Berliner Str. 27",
    "sg:city":"Gro\u00df K\u00f6ris",
    "sg:phone":"+49 33766/62722",
    "sg:postcode":"15746",
    "sg:province":"Brandenburg",
    "wof:name":"D. Roggan",
    "wof:placetype":"venue"
},
  "geometry": {"coordinates":[13.6503505707,52.1590080261],"type":"Point"}
}