{
  "type": "Feature",
  "properties": {
    "iso:country":"DE",
    "sg:address":"Nordhusumer Str. 8",
    "sg:city":"Husum",
    "sg:phone":"+49 4841/62421",
    "sg:postcode":"25813",
    "sg:province":"Schleswig-Holstein",
    "wof:name":"Junghanns Automaten Gmbh",
    "wof:placetype":"venue"
},
  "geometry": {"coordinates":[9.0431861877,54.4776077271],"type":"Point"}
}