{
  "type": "Feature",
  "properties": {
    "iso:country":"DE",
    "sg:address":"Kemptener Str. 69 b",
    "sg:city":"F\u00fcssen",
    "sg:phone":"+49 8362/921100",
    "sg:postcode":"87629",
    "sg:province":"Bayern",
    "wof:name":"Mc Donalds",
    "wof:placetype":"venue"
},
  "geometry": {"coordinates":[10.6812925339,47.5679283142],"type":"Point"}
}