{
  "type": "Feature",
  "properties": {
    "iso:country":"DE",
    "sg:address":"Gebr.-Heyn-Str. 9b",
    "sg:city":"L\u00fcneburg",
    "sg:phone":"+49 4941/3183402",
    "sg:postcode":"21337",
    "sg:province":"Niedersachsen",
    "wof:name":"Helno Maschinenbau Gmbh",
    "wof:placetype":"venue"
},
  "geometry": {"coordinates":[10.468746,53.244083],"type":"Point"}
}