{
  "type": "Feature",
  "properties": {
    "iso:country":"DE",
    "sg:address":"Kaiser-Ludwig-Str. 1",
    "sg:city":"M\u00fchldorf",
    "sg:phone":"+49 8631/12411",
    "sg:postcode":"84453",
    "sg:province":"Bayern",
    "wof:name":"Gebr\u00fcder Glatz Ohg Buch- Und Pressevertrieb",
    "wof:placetype":"venue"
},
  "geometry": {"coordinates":[12.523582,48.246269],"type":"Point"}
}