{
  "type": "Feature",
  "properties": {
    "iso:country":"DE",
    "sg:address":"Schmiedweg 4",
    "sg:city":"Eschlkam",
    "sg:phone":"+49 9948/905015",
    "sg:postcode":"93458",
    "sg:province":"Bayern",
    "wof:name":"F. Breu",
    "wof:placetype":"venue"
},
  "geometry": {"coordinates":[12.953427,49.308483],"type":"Point"}
}