{
  "type": "Feature",
  "properties": {
    "iso:country":"DE",
    "sg:address":"Am Regenstein",
    "sg:city":"Blankenburg",
    "sg:phone":"+49 3944/62615",
    "sg:postcode":"38889",
    "sg:province":"Sachsen-Anhalt",
    "wof:name":"Hasse",
    "wof:placetype":"venue"
},
  "geometry": {"coordinates":[10.94612,51.805351],"type":"Point"}
}