{
  "type": "Feature",
  "properties": {
    "iso:country":"DE",
    "sg:address":"Bamberger Str. 29",
    "sg:city":"Diespeck",
    "sg:phone":"+49 9161/1717",
    "sg:postcode":"91456",
    "sg:province":"Bayern",
    "wof:name":"Hans Helmreich",
    "wof:placetype":"venue"
},
  "geometry": {"coordinates":[10.626543,49.59771],"type":"Point"}
}