{
  "type": "Feature",
  "properties": {
    "iso:country":"DE",
    "sg:address":"Wasserbilliger Str. 2",
    "sg:city":"Trier",
    "sg:phone":"+49 651/85541",
    "sg:postcode":"54294",
    "sg:province":"Rheinland-Pfalz",
    "wof:name":"W. Kirsch",
    "wof:placetype":"venue"
},
  "geometry": {"coordinates":[6.581333,49.719204],"type":"Point"}
}