{
  "type": "Feature",
  "properties": {
    "iso:country":"DE",
    "sg:address":"Sl\u00fcterplatz 9",
    "sg:city":"D\u00f6mitz",
    "sg:postcode":"19303",
    "sg:province":"Mecklenburg-Vorpommern",
    "wof:name":"Evangelisches Pfarramt",
    "wof:placetype":"venue"
},
  "geometry": {"coordinates":[11.24949646,53.141960144],"type":"Point"}
}