{
  "type": "Feature",
  "properties": {
    "iso:country":"DE",
    "sg:address":"Altenbaunaer Str 111",
    "sg:city":"Kassel",
    "sg:phone":"+49 4956/1473268",
    "sg:postcode":"34117",
    "sg:province":"Hessen",
    "wof:name":"Raiffeisenbank Kurhessen Eg",
    "wof:placetype":"venue"
},
  "geometry": {"coordinates":[9.491211,51.311787],"type":"Point"}
}