{
  "type": "Feature",
  "properties": {
    "iso:country":"DE",
    "sg:address":"Marienstr. 51",
    "sg:city":"Hof",
    "sg:phone":"+49 9281/84145",
    "sg:postcode":"95028",
    "sg:province":"Bayern",
    "wof:name":"Heinz Martin",
    "wof:placetype":"venue"
},
  "geometry": {"coordinates":[11.913318634,50.315788269],"type":"Point"}
}