{
  "type": "Feature",
  "properties": {
    "iso:country":"DE",
    "sg:address":"Siemensstr. 20",
    "sg:city":"Rheda-Wiedenbr\u00fcck",
    "sg:phone":"+49 5242/94680",
    "sg:postcode":"33378",
    "sg:province":"Nordrhein-Westfalen",
    "wof:name":"Joachim Kunath",
    "wof:placetype":"venue"
},
  "geometry": {"coordinates":[8.2636194229,51.8583145142],"type":"Point"}
}