{
  "type": "Feature",
  "properties": {
    "iso:country":"DE",
    "sg:address":"K\u00f6nigstor 2 -13",
    "sg:city":"Kassel",
    "sg:phone":"+49 561/4811",
    "sg:postcode":"34117",
    "sg:province":"Hessen",
    "wof:name":"Kraftwerk Kassel Verwaltungsges. Mbh",
    "wof:placetype":"venue"
},
  "geometry": {"coordinates":[9.488507,51.313095],"type":"Point"}
}