{
  "type": "Feature",
  "properties": {
    "iso:country":"DE",
    "sg:address":"Hirschgrundstr. 13",
    "sg:city":"Meerane",
    "sg:phone":"+49 3764/79000",
    "sg:postcode":"08393",
    "sg:province":"Sachsen",
    "wof:name":"Speisenservice Meerane Roy Neupert",
    "wof:placetype":"venue"
},
  "geometry": {"coordinates":[12.4787864685,50.8454322815],"type":"Point"}
}