{
  "type": "Feature",
  "properties": {
    "iso:country":"DE",
    "sg:address":"Friedrich-Engels-Allee 171",
    "sg:city":"Wuppertal",
    "sg:phone":"+49 202/87147",
    "sg:postcode":"42285",
    "sg:province":"Nordrhein-Westfalen",
    "wof:name":"Fr. H. Graumann Farben Und Lacke",
    "wof:placetype":"venue"
},
  "geometry": {"coordinates":[7.172218,51.261536],"type":"Point"}
}