{
  "type": "Feature",
  "properties": {
    "iso:country":"DE",
    "sg:address":"S\u00fcdweg 32",
    "sg:city":"Boxberg",
    "sg:phone":"+49 3576/203655",
    "sg:postcode":"02943",
    "sg:province":"Sachsen",
    "wof:name":"Damen- Und Herrenmode Flair",
    "wof:placetype":"venue"
},
  "geometry": {"coordinates":[14.6016130447,51.4321022034],"type":"Point"}
}