{
  "type": "Feature",
  "properties": {
    "iso:country":"DE",
    "sg:address":"Rohrstr. 64",
    "sg:city":"Offenbach",
    "sg:phone":"+49 69/863903",
    "sg:postcode":"63075",
    "sg:province":"Hessen",
    "wof:name":"Konrad Noll Architekt",
    "wof:placetype":"venue"
},
  "geometry": {"coordinates":[8.799506,50.127552],"type":"Point"}
}