{
  "type": "Feature",
  "properties": {
    "iso:country":"DE",
    "sg:address":"Unterpforte 6",
    "sg:city":"Gabsheim",
    "sg:phone":"+49 6732/4460",
    "sg:postcode":"55288",
    "sg:province":"Rheinland-Pfalz",
    "wof:name":"Elektro-sch\u00e4fer Gmbh",
    "wof:placetype":"venue"
},
  "geometry": {"coordinates":[8.17364,49.845745],"type":"Point"}
}