{
  "type": "Feature",
  "properties": {
    "iso:country":"DE",
    "sg:address":"Postfach 3",
    "sg:city":"Sch\u00f6ffengrund",
    "sg:postcode":"35639",
    "sg:province":"Hessen",
    "wof:name":"Doctor-optic-wetzlar Gmbh",
    "wof:placetype":"venue"
},
  "geometry": {"coordinates":[8.4859199524,50.479888916],"type":"Point"}
}