{
  "type": "Feature",
  "properties": {
    "iso:country":"DE",
    "sg:address":"Stieffring 3-5",
    "sg:city":"Berlin",
    "sg:phone":"+49 30/3441670",
    "sg:postcode":"13627",
    "sg:province":"Berlin",
    "wof:name":"Ultra Tube Ges.f.verfahrens- Technik U. Anlagenbau Mbh",
    "wof:placetype":"venue"
},
  "geometry": {"coordinates":[13.313937,52.54472],"type":"Point"}
}