{
  "type": "Feature",
  "properties": {
    "iso:country":"DE",
    "sg:address":"Am Bildst\u00f6ckle 11",
    "sg:city":"Ichenhausen",
    "sg:phone":"+49 821/579457",
    "sg:postcode":"89335",
    "sg:province":"Bayern",
    "wof:name":"J. Und I. Davidson",
    "wof:placetype":"venue"
},
  "geometry": {"coordinates":[10.310394,48.387428],"type":"Point"}
}