{
  "type": "Feature",
  "properties": {
    "iso:country":"DE",
    "sg:address":"Kirchahorn 37",
    "sg:city":"Ahorntal",
    "sg:phone":"+49 9202/293",
    "sg:postcode":"95491",
    "sg:province":"Bayern",
    "wof:name":"Johann Zellmann",
    "wof:placetype":"venue"
},
  "geometry": {"coordinates":[11.401895,49.832981],"type":"Point"}
}