{
  "type": "Feature",
  "properties": {
    "iso:country":"DE",
    "sg:address":"Friedrichstr. 51",
    "sg:city":"Herdorf",
    "sg:postcode":"57562",
    "sg:province":"Rheinland-Pfalz",
    "wof:name":"Matthias K\u00f6hler Masseur",
    "wof:placetype":"venue"
},
  "geometry": {"coordinates":[7.956191,50.778156],"type":"Point"}
}