{
  "type": "Feature",
  "properties": {
    "iso:country":"DE",
    "sg:address":"Kampstr. 22",
    "sg:city":"Wiehl",
    "sg:phone":"+49 2262/92223",
    "sg:postcode":"51674",
    "sg:province":"Nordrhein-Westfalen",
    "wof:name":"Ruth Merz",
    "wof:placetype":"venue"
},
  "geometry": {"coordinates":[7.579095,50.944374],"type":"Point"}
}