{
  "type": "Feature",
  "properties": {
    "iso:country":"DE",
    "sg:address":"Bad-Tri\u00dfl-Str. 41",
    "sg:city":"Oberaudorf",
    "sg:phone":"+49 8033/1835",
    "sg:postcode":"83080",
    "sg:province":"Bayern",
    "wof:name":"M. Und T. Kolb",
    "wof:placetype":"venue"
},
  "geometry": {"coordinates":[12.162223,47.652889],"type":"Point"}
}