{
  "type": "Feature",
  "properties": {
    "iso:country":"DE",
    "sg:address":"Olgastr. 9",
    "sg:city":"Bad Wildbad",
    "sg:phone":"+49 7081/2191",
    "sg:postcode":"75323",
    "sg:province":"Baden-W\u00fcrttemberg",
    "wof:name":"Rommel-klinik Krankengymnastische Ambulanz",
    "wof:placetype":"venue"
},
  "geometry": {"coordinates":[8.551164,48.748016],"type":"Point"}
}