{
  "type": "Feature",
  "properties": {
    "iso:country":"DE",
    "sg:address":"Islandstr. 46",
    "sg:city":"H\u00fcckeswagen",
    "sg:phone":"+49 2192/2205",
    "sg:postcode":"42499",
    "sg:province":"Nordrhein-Westfalen",
    "wof:name":"H. Ferber",
    "wof:placetype":"venue"
},
  "geometry": {"coordinates":[7.3425159454,51.1498260498],"type":"Point"}
}