{
  "type": "Feature",
  "properties": {
    "iso:country":"DE",
    "sg:address":"Sommerhofenstr.240",
    "sg:city":"Sindelfingen",
    "sg:phone":"+49 7031",
    "sg:postcode":"71067",
    "sg:province":"Baden-W\u00fcrttemberg",
    "wof:name":"Erich Schubert Gmbh",
    "wof:placetype":"venue"
},
  "geometry": {"coordinates":[9.012447,48.725292],"type":"Point"}
}