{
  "type": "Feature",
  "properties": {
    "iso:country":"DE",
    "sg:address":"Aunhamer Weg 48",
    "sg:city":"Bad Griesbach",
    "sg:phone":"+49 8532/3109",
    "sg:postcode":"94086",
    "sg:province":"Bayern",
    "wof:name":"Marion Sigl Masseur",
    "wof:placetype":"venue"
},
  "geometry": {"coordinates":[13.193102,48.442066],"type":"Point"}
}