{
  "type": "Feature",
  "properties": {
    "iso:country":"DE",
    "sg:address":"Mattesstr. 14",
    "sg:city":"Besigheim",
    "sg:phone":"+49 7143/3011",
    "sg:postcode":"74354",
    "sg:province":"Baden-W\u00fcrttemberg",
    "wof:name":"K\u00fcche Bad Hass Gmbh & Co. Kg",
    "wof:placetype":"venue"
},
  "geometry": {"coordinates":[9.1413154602,48.9961662292],"type":"Point"}
}