{
  "type": "Feature",
  "properties": {
    "iso:country":"DE",
    "sg:address":"Beurener Str. 2",
    "sg:city":"Singen",
    "sg:phone":"+49 7731/45186",
    "sg:postcode":"78224",
    "sg:province":"Baden-W\u00fcrttemberg",
    "wof:name":"Bernd Adelmann",
    "wof:placetype":"venue"
},
  "geometry": {"coordinates":[8.8676204681,47.7571105957],"type":"Point"}
}