{
  "type": "Feature",
  "properties": {
    "iso:country":"DE",
    "sg:address":"Grafinger Str. 25",
    "sg:city":"M\u00fcnchen",
    "sg:phone":"+49 89/404021",
    "sg:postcode":"81671",
    "sg:province":"Bayern",
    "wof:name":"Indula Lackfabrik",
    "wof:placetype":"venue"
},
  "geometry": {"coordinates":[11.60918,48.124962],"type":"Point"}
}