{
  "type": "Feature",
  "properties": {
    "iso:country":"DE",
    "sg:address":"Landrichter-Kummer-Str. 20",
    "sg:city":"Eltmann",
    "sg:phone":"+49 9522/5368",
    "sg:postcode":"97483",
    "sg:province":"Bayern",
    "wof:name":"Wolf Gmbh",
    "wof:placetype":"venue"
},
  "geometry": {"coordinates":[10.660914,49.972343],"type":"Point"}
}