{
  "type": "Feature",
  "properties": {
    "iso:country":"DE",
    "sg:address":"Pastor-Schmitz-Str. 4",
    "sg:city":"Wesel",
    "sg:phone":"+49 281/83835",
    "sg:postcode":"46485",
    "sg:province":"Nordrhein-Westfalen",
    "wof:name":"Pizzeria La Prima",
    "wof:placetype":"venue"
},
  "geometry": {"coordinates":[6.6576118469,51.6602058411],"type":"Point"}
}