{
  "type": "Feature",
  "properties": {
    "iso:country":"DE",
    "sg:address":"Dammstr. 6",
    "sg:city":"Gosheim",
    "sg:phone":"+49 7426/7361",
    "sg:postcode":"78559",
    "sg:province":"Baden-W\u00fcrttemberg",
    "wof:name":"Rafael Weber",
    "wof:placetype":"venue"
},
  "geometry": {"coordinates":[8.75554,48.136822],"type":"Point"}
}