{
  "type": "Feature",
  "properties": {
    "iso:country":"DE",
    "sg:address":"Im Heidkamp 20",
    "sg:city":"G\u00fctersloh",
    "sg:phone":"+49 5241/95050",
    "sg:postcode":"33334",
    "sg:province":"Nordrhein-Westfalen",
    "wof:name":"Werkstatt F\u00fcr Behinderte Im Kreis G\u00fctersloh Ggmbh",
    "wof:placetype":"venue"
},
  "geometry": {"coordinates":[8.355203,51.887516],"type":"Point"}
}