{
  "type": "Feature",
  "properties": {
    "iso:country":"DE",
    "sg:address":"Lotter Str. 57",
    "sg:city":"Osnabr\u00fcck",
    "sg:phone":"+49 541/434954",
    "sg:postcode":"49078",
    "sg:province":"Niedersachsen",
    "wof:name":"K\u00fclkens Verwaltungs Gmbh",
    "wof:placetype":"venue"
},
  "geometry": {"coordinates":[8.0249357224,52.2744903564],"type":"Point"}
}