{
  "type": "Feature",
  "properties": {
    "iso:country":"DE",
    "sg:address":"Aichenbachstr. 95",
    "sg:city":"Schorndorf",
    "sg:phone":"+49 7181/63236",
    "sg:postcode":"73614",
    "sg:province":"Baden-W\u00fcrttemberg",
    "wof:name":"Hartmut B\u00fchler Containerdienst",
    "wof:placetype":"venue"
},
  "geometry": {"coordinates":[9.5346069336,48.7974967957],"type":"Point"}
}