{
  "type": "Feature",
  "properties": {
    "iso:country":"DE",
    "sg:address":"Zinkstr. 7",
    "sg:city":"Rheine",
    "sg:phone":"+49 5971/3836",
    "sg:postcode":"48432",
    "sg:province":"Nordrhein-Westfalen",
    "wof:name":"K\u00f6ster Holz Gmbh",
    "wof:placetype":"venue"
},
  "geometry": {"coordinates":[7.4642028809,52.2359962463],"type":"Point"}
}