{
  "type": "Feature",
  "properties": {
    "iso:country":"DE",
    "sg:address":"Siegfriedstr. 20",
    "sg:city":"Worms",
    "sg:phone":"+49 6241/946180",
    "sg:postcode":"67547",
    "sg:province":"Rheinland-Pfalz",
    "wof:name":"Fitness-studio Black & White Gmbh",
    "wof:placetype":"venue"
},
  "geometry": {"coordinates":[8.3608198166,49.6347618103],"type":"Point"}
}