{
  "type": "Feature",
  "properties": {
    "iso:country":"DE",
    "sg:address":"Blutenburgstr. 21",
    "sg:city":"M\u00fcnchen",
    "sg:phone":"+49 89/1266490",
    "sg:postcode":"80636",
    "sg:province":"Bayern",
    "wof:name":"Buchdruckerei Gebr. Bremberger Verlags-gmbh",
    "wof:placetype":"venue"
},
  "geometry": {"coordinates":[11.5442304611,48.1489257812],"type":"Point"}
}