{
  "type": "Feature",
  "properties": {
    "iso:country":"DE",
    "sg:address":"Eibenstr. 18",
    "sg:city":"Erfurt",
    "sg:phone":"+49 361/7968282",
    "sg:postcode":"99094",
    "sg:province":"Th\u00fcringen",
    "wof:name":"Herbert Vogel",
    "wof:placetype":"venue"
},
  "geometry": {"coordinates":[10.985584,50.936783],"type":"Point"}
}