{
  "type": "Feature",
  "properties": {
    "iso:country":"DE",
    "sg:address":"Adolfstr. 7",
    "sg:city":"Schlangen",
    "sg:phone":"+49 5252/81566",
    "sg:postcode":"33189",
    "sg:province":"Nordrhein-Westfalen",
    "wof:name":"Friedrich Ostmann",
    "wof:placetype":"venue"
},
  "geometry": {"coordinates":[8.849928,51.810669],"type":"Point"}
}