{
  "type": "Feature",
  "properties": {
    "iso:country":"DE",
    "sg:address":"Thomas-Mann-Str. 8",
    "sg:city":"Schwedt",
    "sg:postcode":"16303",
    "sg:province":"Brandenburg",
    "wof:name":"Sperner Bauelemente Gmbh",
    "wof:placetype":"venue"
},
  "geometry": {"coordinates":[14.250007,53.069099],"type":"Point"}
}