{
  "type": "Feature",
  "properties": {
    "iso:country":"DE",
    "sg:address":"Rathausstr.",
    "sg:city":"Hamburg",
    "sg:postcode":"20095",
    "sg:province":"Hamburg",
    "wof:name":"Senat Der Freien Und Hansestadt Hamburg",
    "wof:placetype":"venue"
},
  "geometry": {"coordinates":[9.99553,53.549976],"type":"Point"}
}