{
  "type": "Feature",
  "properties": {
    "iso:country":"DE",
    "sg:address":"Beiersdorfstr. 7",
    "sg:city":"Heitersheim",
    "sg:phone":"+49 7634/2135",
    "sg:postcode":"79423",
    "sg:province":"Baden-W\u00fcrttemberg",
    "wof:name":"R. Stockbauer",
    "wof:placetype":"venue"
},
  "geometry": {"coordinates":[7.647368,47.873245],"type":"Point"}
}