{
  "type": "Feature",
  "properties": {
    "iso:country":"DE",
    "sg:address":"Kleinenkneten 50",
    "sg:city":"Wildeshausen",
    "sg:phone":"+49 4431/1719",
    "sg:postcode":"27793",
    "sg:province":"Niedersachsen",
    "wof:name":"Helga Svenson",
    "wof:placetype":"venue"
},
  "geometry": {"coordinates":[8.435088,52.847488],"type":"Point"}
}