{
  "type": "Feature",
  "properties": {
    "iso:country":"DE",
    "sg:address":"Talstr. 31",
    "sg:city":"Hohenstein-Ernstthal",
    "sg:phone":"+49 3723/3456",
    "sg:postcode":"09337",
    "sg:province":"Sachsen",
    "wof:name":"Hans-g\u00fcnter Beyer",
    "wof:placetype":"venue"
},
  "geometry": {"coordinates":[12.690451,50.79734],"type":"Point"}
}