{
  "type": "Feature",
  "properties": {
    "iso:country":"DE",
    "sg:address":"Wiesenstr. 32",
    "sg:city":"D\u00fcsseldorf",
    "sg:phone":"+49 211/5626110",
    "sg:postcode":"40549",
    "sg:province":"Nordrhein-Westfalen",
    "wof:name":"Haus Der Steine Gmbh",
    "wof:placetype":"venue"
},
  "geometry": {"coordinates":[6.709993,51.230076],"type":"Point"}
}