{
  "type": "Feature",
  "properties": {
    "iso:country":"DE",
    "sg:address":"Kreisstr. 134",
    "sg:city":"Saarbr\u00fccken",
    "sg:phone":"+49 681/700803",
    "sg:postcode":"66128",
    "sg:province":"Saarland",
    "wof:name":"W. Wuttke",
    "wof:placetype":"venue"
},
  "geometry": {"coordinates":[6.9037628174,49.245388031],"type":"Point"}
}