{
  "type": "Feature",
  "properties": {
    "iso:country":"DE",
    "sg:address":"Max-Planck-Str. 13",
    "sg:city":"Landsberg",
    "sg:postcode":"86899",
    "sg:province":"Bayern",
    "wof:name":"Czech & Kobert Ohg",
    "wof:placetype":"venue"
},
  "geometry": {"coordinates":[10.856842041,48.0624465942],"type":"Point"}
}