{
  "type": "Feature",
  "properties": {
    "iso:country":"DE",
    "sg:address":"Ernst-Reuter-Str. 28",
    "sg:city":"Hof",
    "sg:phone":"+49 9281/95037",
    "sg:postcode":"95032",
    "sg:province":"Bayern",
    "wof:name":"China-restaurant Lotus",
    "wof:placetype":"venue"
},
  "geometry": {"coordinates":[11.9137210846,50.3070373535],"type":"Point"}
}