{
  "type": "Feature",
  "properties": {
    "iso:country":"DE",
    "sg:address":"Unlandsweg 9",
    "sg:city":"Nenndorf",
    "sg:phone":"+49 4975/327",
    "sg:postcode":"26556",
    "sg:province":"Niedersachsen",
    "wof:name":"Campingplatz Willms",
    "wof:placetype":"venue"
},
  "geometry": {"coordinates":[7.439936,53.592052],"type":"Point"}
}