{
  "type": "Feature",
  "properties": {
    "iso:country":"DE",
    "sg:address":"Warf 23",
    "sg:city":"Reil",
    "sg:phone":"+49 6542/1239",
    "sg:postcode":"56861",
    "sg:province":"Rheinland-Pfalz",
    "wof:name":"Oldie Pub",
    "wof:placetype":"venue"
},
  "geometry": {"coordinates":[7.1171030998,50.0208587646],"type":"Point"}
}