{
  "type": "Feature",
  "properties": {
    "iso:country":"DE",
    "sg:address":"Am Bach 8",
    "sg:city":"Mauern",
    "sg:phone":"+49 8764/524",
    "sg:postcode":"85419",
    "sg:province":"Bayern",
    "wof:name":"C. Plank Elektroinstallation",
    "wof:placetype":"venue"
},
  "geometry": {"coordinates":[11.894891,48.515705],"type":"Point"}
}