{
  "type": "Feature",
  "properties": {
    "iso:country":"DE",
    "sg:address":"Schwartzstr. 11",
    "sg:city":"Bocholt",
    "sg:phone":"+49 2871/998588",
    "sg:postcode":"46397",
    "sg:province":"Nordrhein-Westfalen",
    "wof:name":"Carl Isert Ohg",
    "wof:placetype":"venue"
},
  "geometry": {"coordinates":[6.6234488487,51.8393516541],"type":"Point"}
}