{
  "type": "Feature",
  "properties": {
    "iso:country":"DE",
    "sg:address":"Innere Br\u00fccke 23",
    "sg:city":"Esslingen",
    "sg:phone":"+49 4971/1390000",
    "sg:postcode":"73728",
    "sg:province":"Baden-W\u00fcrttemberg",
    "wof:name":"Bayerishe Hypotheken Bank Ag",
    "wof:placetype":"venue"
},
  "geometry": {"coordinates":[9.305879,48.740334],"type":"Point"}
}