{
  "type": "Feature",
  "properties": {
    "iso:country":"DE",
    "sg:address":"Adjutantenkamp 3-5",
    "sg:city":"Hemer",
    "sg:phone":"+49 2372/6898",
    "sg:postcode":"58675",
    "sg:province":"Nordrhein-Westfalen",
    "wof:name":"Ernst Krieger Nachfolger Gmbh",
    "wof:placetype":"venue"
},
  "geometry": {"coordinates":[7.8011779785,51.3795013428],"type":"Point"}
}