{
  "type": "Feature",
  "properties": {
    "iso:country":"DE",
    "sg:address":"Gehrenseestra\u00dfe",
    "sg:city":"Berlin",
    "sg:phone":"+49 981/14005",
    "sg:postcode":"13053",
    "sg:province":"Berlin",
    "wof:name":"Berlin-hsh.de, Alles \u00fcber Berlin Und Hsh",
    "wof:placetype":"venue"
},
  "geometry": {"coordinates":[13.510875,52.550606],"type":"Point"}
}