{
  "type": "Feature",
  "properties": {
    "iso:country":"DE",
    "sg:address":"Schulthei\u00df-Schneider-Str. 5",
    "sg:city":"Geislingen",
    "sg:phone":"+49 7331/42617",
    "sg:postcode":"73312",
    "sg:province":"Baden-W\u00fcrttemberg",
    "wof:name":"G. Und A. Volk Heissmangel",
    "wof:placetype":"venue"
},
  "geometry": {"coordinates":[9.8295927048,48.6198616028],"type":"Point"}
}