{
  "type": "Feature",
  "properties": {
    "iso:country":"DE",
    "sg:address":"Flagentwiet 54",
    "sg:city":"Hamburg",
    "sg:phone":"+49 40/85158859",
    "sg:postcode":"22457",
    "sg:province":"Hamburg",
    "wof:name":"Hxh Druck, Verlag, Webhosting E.k. Inh. Fatmire Dzaferi",
    "wof:placetype":"venue"
},
  "geometry": {"coordinates":[9.9057836533,53.6361808777],"type":"Point"}
}