{
  "type": "Feature",
  "properties": {
    "iso:country":"DE",
    "sg:address":"Sommerhof",
    "sg:city":"Windeck",
    "sg:phone":"+49 2243/6174",
    "sg:postcode":"51570",
    "sg:province":"Nordrhein-Westfalen",
    "wof:name":"Helmut Ebach",
    "wof:placetype":"venue"
},
  "geometry": {"coordinates":[7.511915,50.772335],"type":"Point"}
}