{
  "type": "Feature",
  "properties": {
    "iso:country":"DE",
    "sg:address":"Igelweg 6",
    "sg:city":"Neum\u00fcnster",
    "sg:phone":"+49 4321/989276",
    "sg:postcode":"24539",
    "sg:province":"Schleswig-Holstein",
    "wof:name":"Wiebke Stange Steuerberaterin",
    "wof:placetype":"venue"
},
  "geometry": {"coordinates":[9.9639997482,54.0493087769],"type":"Point"}
}