{
  "type": "Feature",
  "properties": {
    "iso:country":"DE",
    "sg:address":"Bahnhofstr. 2",
    "sg:city":"Kummersdorf",
    "sg:phone":"+49 33678/2765",
    "sg:postcode":"15859",
    "sg:province":"Brandenburg",
    "wof:name":"B. Grund",
    "wof:placetype":"venue"
},
  "geometry": {"coordinates":[13.867324,52.272324],"type":"Point"}
}