{
  "type": "Feature",
  "properties": {
    "iso:country":"DE",
    "sg:city":"Erbes-B\u00fcdesheim",
    "sg:phone":"+49 6731/41615",
    "sg:postcode":"55234",
    "sg:province":"Rheinland-Pfalz",
    "wof:name":"Hans-dieter Bl\u00e4tz",
    "wof:placetype":"venue"
},
  "geometry": {"coordinates":[8.032475,49.755829],"type":"Point"}
}