{
  "type": "Feature",
  "properties": {
    "iso:country":"DE",
    "sg:address":"Im Heienbach 3",
    "sg:city":"Rotenburg",
    "sg:phone":"+49 6623/919300",
    "sg:postcode":"36199",
    "sg:province":"Hessen",
    "wof:name":"Joh. Gutermuth",
    "wof:placetype":"venue"
},
  "geometry": {"coordinates":[9.7373342514,50.9970664978],"type":"Point"}
}