{
  "type": "Feature",
  "properties": {
    "iso:country":"DE",
    "sg:address":"Landstr. 20",
    "sg:city":"Steinen",
    "sg:postcode":"79585",
    "sg:province":"Baden-W\u00fcrttemberg",
    "wof:name":"Translift Logistik Gmbh",
    "wof:placetype":"venue"
},
  "geometry": {"coordinates":[7.75815,47.6427],"type":"Point"}
}