{
  "type": "Feature",
  "properties": {
    "iso:country":"DE",
    "sg:address":"Industriestr. 30",
    "sg:city":"Neunkirchen",
    "sg:phone":"+49 9134/4847",
    "sg:postcode":"91077",
    "sg:province":"Bayern",
    "wof:name":"Ege Imbi\u00df",
    "wof:placetype":"venue"
},
  "geometry": {"coordinates":[11.1338853836,49.6071586609],"type":"Point"}
}