{
  "type": "Feature",
  "properties": {
    "iso:country":"DE",
    "sg:address":"Kirchgasse 22",
    "sg:city":"Markgr\u00f6ningen",
    "sg:phone":"+49 7145/5390",
    "sg:postcode":"71706",
    "sg:province":"Baden-W\u00fcrttemberg",
    "wof:name":"Rudolf G\u00fcnzler",
    "wof:placetype":"venue"
},
  "geometry": {"coordinates":[9.0815086365,48.9040107727],"type":"Point"}
}