{
  "type": "Feature",
  "properties": {
    "iso:country":"DE",
    "sg:address":"Bochumer Str. 27",
    "sg:city":"Herne",
    "sg:phone":"+49 2323/491990",
    "sg:postcode":"44623",
    "sg:province":"Nordrhein-Westfalen",
    "wof:name":"Engel-apotheke",
    "wof:placetype":"venue"
},
  "geometry": {"coordinates":[7.226196,51.534443],"type":"Point"}
}