{
  "type": "Feature",
  "properties": {
    "iso:country":"DE",
    "sg:address":"Hauptstr. 45a",
    "sg:city":"H\u00fcgelsheim",
    "sg:phone":"+49 7229/30690",
    "sg:postcode":"76549",
    "sg:province":"Baden-W\u00fcrttemberg",
    "wof:name":"Hotel-restaurant Schwan",
    "wof:placetype":"venue"
},
  "geometry": {"coordinates":[8.1113052368,48.7971611023],"type":"Point"}
}