{
  "type": "Feature",
  "properties": {
    "iso:country":"DE",
    "sg:address":"Christine-Englerth-Str. 20",
    "sg:city":"Recklinghausen",
    "sg:phone":"+49 2361/98690",
    "sg:postcode":"45665",
    "sg:province":"Nordrhein-Westfalen",
    "wof:name":"Nem Power-sytems Niederlassung Deutschland Der",
    "wof:placetype":"venue"
},
  "geometry": {"coordinates":[7.248147,51.605663],"type":"Point"}
}