{
  "type": "Feature",
  "properties": {
    "iso:country":"DE",
    "sg:address":"H\u00f6henweg 1",
    "sg:city":"Hagen",
    "sg:phone":"+49 5401/980093",
    "sg:postcode":"49170",
    "sg:province":"Niedersachsen",
    "wof:name":"Wilhelm Bensmann & Sohn Ohg",
    "wof:placetype":"venue"
},
  "geometry": {"coordinates":[7.986992836,52.1985321045],"type":"Point"}
}