{
  "type": "Feature",
  "properties": {
    "iso:country":"DE",
    "sg:address":"Kirchstr 13",
    "sg:city":"Diemelsee",
    "sg:phone":"+49 5633/350",
    "sg:postcode":"34519",
    "sg:province":"Hessen",
    "wof:name":"Pack-holz Gmbh",
    "wof:placetype":"venue"
},
  "geometry": {"coordinates":[8.7277116776,51.3634300232],"type":"Point"}
}