{
  "type": "Feature",
  "properties": {
    "iso:country":"DE",
    "sg:address":"Poststr. 19",
    "sg:city":"Bad Neuenahr-Ahrweiler",
    "sg:phone":"+49 2641/27332",
    "sg:postcode":"53474",
    "sg:province":"Rheinland-Pfalz",
    "wof:name":"Werner M\u00fcnch",
    "wof:placetype":"venue"
},
  "geometry": {"coordinates":[7.1377501488,50.5444641113],"type":"Point"}
}