{
  "type": "Feature",
  "properties": {
    "iso:country":"DE",
    "sg:address":"F\u00fchlingsweg 7",
    "sg:city":"Moringen",
    "sg:phone":"+49 5554/99380",
    "sg:postcode":"37186",
    "sg:province":"Niedersachsen",
    "wof:name":"Bierkamp Gmbh",
    "wof:placetype":"venue"
},
  "geometry": {"coordinates":[9.8677740097,51.6921844482],"type":"Point"}
}