{
  "type": "Feature",
  "properties": {
    "iso:country":"DE",
    "sg:address":"Ortsstr. 73",
    "sg:city":"Heubisch",
    "sg:phone":"+49 36761/305",
    "sg:postcode":"96524",
    "sg:province":"Th\u00fcringen",
    "wof:name":"Horst Motschmann",
    "wof:placetype":"venue"
},
  "geometry": {"coordinates":[11.232925415,50.3403968811],"type":"Point"}
}