{
  "type": "Feature",
  "properties": {
    "iso:country":"DE",
    "sg:address":"Vo\u00dfstr. 2",
    "sg:city":"Sarstedt",
    "sg:phone":"+49 5066/7606",
    "sg:postcode":"31157",
    "sg:province":"Niedersachsen",
    "wof:name":"Kubaschewski",
    "wof:placetype":"venue"
},
  "geometry": {"coordinates":[9.845482,52.231644],"type":"Point"}
}