{
  "type": "Feature",
  "properties": {
    "iso:country":"DE",
    "sg:address":"Traubenstr. 22",
    "sg:city":"Weinstadt",
    "sg:phone":"+49 7151/61203",
    "sg:postcode":"71384",
    "sg:province":"Baden-W\u00fcrttemberg",
    "wof:name":"Alfred Cogo Mech. Werkstatt",
    "wof:placetype":"venue"
},
  "geometry": {"coordinates":[9.363804,48.809731],"type":"Point"}
}