{
  "type": "Feature",
  "properties": {
    "iso:country":"DE",
    "sg:address":"Kratzenbergstr. 1",
    "sg:city":"Helsa",
    "sg:phone":"+49 5605/3904",
    "sg:postcode":"34298",
    "sg:province":"Hessen",
    "wof:name":"J\u00fcrgen Scholz Architekt",
    "wof:placetype":"venue"
},
  "geometry": {"coordinates":[9.70099,51.261009],"type":"Point"}
}