{
  "type": "Feature",
  "properties": {
    "iso:country":"DE",
    "sg:address":"Kaiserstr. 201",
    "sg:city":"Karlsruhe",
    "sg:phone":"+49 721/25476",
    "sg:postcode":"76133",
    "sg:province":"Baden-W\u00fcrttemberg",
    "wof:name":"Schirm-weinig Hannelore Weinig Inh. Rolf Wallbaum Gmbh",
    "wof:placetype":"venue"
},
  "geometry": {"coordinates":[8.3962621689,49.0098571777],"type":"Point"}
}