{
  "type": "Feature",
  "properties": {
    "iso:country":"DE",
    "sg:address":"Wallstr. 12-14",
    "sg:city":"Duisburg",
    "sg:phone":"+49 203/284645",
    "sg:postcode":"47051",
    "sg:province":"Nordrhein-Westfalen",
    "wof:name":"Kr\u00f6mer Und Horn Rechtsanw\u00e4lte",
    "wof:placetype":"venue"
},
  "geometry": {"coordinates":[6.7632761002,51.4319572449],"type":"Point"}
}