{
  "type": "Feature",
  "properties": {
    "iso:country":"DE",
    "sg:address":"Schwalbenweg 12 a",
    "sg:city":"Halle",
    "sg:phone":"+49 345/4449665",
    "sg:postcode":"06110",
    "sg:province":"Sachsen-Anhalt",
    "wof:name":"J\u00fcrgen Pyla",
    "wof:placetype":"venue"
},
  "geometry": {"coordinates":[11.968532,51.460415],"type":"Point"}
}