{
  "type": "Feature",
  "properties": {
    "iso:country":"DE",
    "sg:address":"Vogelheimerstr.208",
    "sg:city":"Essen",
    "sg:phone":"+49 201/369197",
    "sg:postcode":"45329",
    "sg:province":"Nordrhein-Westfalen",
    "wof:name":"Ikc-essen",
    "wof:placetype":"venue"
},
  "geometry": {"coordinates":[6.990567,51.491135],"type":"Point"}
}