{
  "type": "Feature",
  "properties": {
    "iso:country":"DE",
    "sg:address":"H\u00f6lmerweg 2",
    "sg:city":"Versmold",
    "sg:phone":"+49 5423/6342",
    "sg:postcode":"33775",
    "sg:province":"Nordrhein-Westfalen",
    "wof:name":"Ankes Blumenboutique",
    "wof:placetype":"venue"
},
  "geometry": {"coordinates":[8.229166,52.069126],"type":"Point"}
}