{
  "type": "Feature",
  "properties": {
    "iso:country":"DE",
    "sg:address":"Hertefeld 4",
    "sg:city":"Weeze",
    "sg:phone":"+49 2837/7678",
    "sg:postcode":"47652",
    "sg:province":"Nordrhein-Westfalen",
    "wof:name":"Janssen",
    "wof:placetype":"venue"
},
  "geometry": {"coordinates":[6.20436,51.629848],"type":"Point"}
}