{
  "type": "Feature",
  "properties": {
    "iso:country":"DE",
    "sg:address":"Rheinstr. 86",
    "sg:city":"Krefeld",
    "sg:phone":"+49 2151/63210",
    "sg:postcode":"47798",
    "sg:province":"Nordrhein-Westfalen",
    "wof:name":"Halfmann Gmbh & Co. Immobilien Kg",
    "wof:placetype":"venue"
},
  "geometry": {"coordinates":[6.5650548935,51.3334083557],"type":"Point"}
}