{
  "type": "Feature",
  "properties": {
    "iso:country":"DE",
    "sg:address":"Im Band 5",
    "sg:city":"Mendig",
    "sg:phone":"+49 2652/3345",
    "sg:postcode":"56743",
    "sg:province":"Rheinland-Pfalz",
    "wof:name":"Walter Foerster",
    "wof:placetype":"venue"
},
  "geometry": {"coordinates":[7.285354,50.368622],"type":"Point"}
}