{
  "type": "Feature",
  "properties": {
    "iso:country":"DE",
    "sg:address":"Kaiserstr. 12",
    "sg:city":"Salzgitter",
    "sg:phone":"+49 5341/811385",
    "sg:postcode":"38259",
    "sg:province":"Niedersachsen",
    "wof:name":"Kampfkunstschule Taman",
    "wof:placetype":"venue"
},
  "geometry": {"coordinates":[10.3749608994,52.0484580994],"type":"Point"}
}