{
  "type": "Feature",
  "properties": {
    "iso:country":"DE",
    "sg:address":"Habichtsweg 6b",
    "sg:city":"L\u00fcneburg",
    "sg:phone":"+49 4131/42621",
    "sg:postcode":"21337",
    "sg:province":"Niedersachsen",
    "wof:name":"J\u00fcrgen R\u00f6diger Ingenieur",
    "wof:placetype":"venue"
},
  "geometry": {"coordinates":[10.4176883698,53.2318229675],"type":"Point"}
}