{
  "type": "Feature",
  "properties": {
    "iso:country":"DE",
    "sg:address":"Hohe Str. 77",
    "sg:city":"Struppen",
    "sg:phone":"+49 35020/71274",
    "sg:postcode":"01796",
    "sg:province":"Sachsen",
    "wof:name":"S. Und S. Mann",
    "wof:placetype":"venue"
},
  "geometry": {"coordinates":[14.0158319473,50.9334030151],"type":"Point"}
}