{
  "type": "Feature",
  "properties": {
    "iso:country":"DE",
    "sg:address":"Rottstr. 27",
    "sg:city":"Aachen",
    "sg:phone":"+49 4924/1500990",
    "sg:postcode":"52068",
    "sg:province":"Nordrhein-Westfalen",
    "wof:name":"Nobis Gmbh",
    "wof:placetype":"venue"
},
  "geometry": {"coordinates":[6.130152,50.778542],"type":"Point"}
}