{
  "type": "Feature",
  "properties": {
    "iso:country":"DE",
    "sg:address":"Senefelderstr. 12",
    "sg:city":"W\u00fcrzburg",
    "sg:phone":"+49 931/22444",
    "sg:postcode":"97080",
    "sg:province":"Bayern",
    "wof:name":"Aqua Botanica",
    "wof:placetype":"venue"
},
  "geometry": {"coordinates":[9.952042,49.802162],"type":"Point"}
}