{
  "type": "Feature",
  "properties": {
    "iso:country":"DE",
    "sg:address":"Eberhardsbergstr. 22 a",
    "sg:city":"Igensdorf",
    "sg:phone":"+49 9192/558",
    "sg:postcode":"91338",
    "sg:province":"Bayern",
    "wof:name":"Dremo Werkzeugmaschinen Vertriebs Gmbh & Co. Kg",
    "wof:placetype":"venue"
},
  "geometry": {"coordinates":[11.231554985,49.62449646],"type":"Point"}
}