{
  "type": "Feature",
  "properties": {
    "iso:country":"DE",
    "sg:address":"Riedhausen 1",
    "sg:city":"Brunnthal",
    "sg:phone":"+49 8102/3035",
    "sg:postcode":"85649",
    "sg:province":"Bayern",
    "wof:name":"Weigang-werbung",
    "wof:placetype":"venue"
},
  "geometry": {"coordinates":[11.68466,48.006886],"type":"Point"}
}