{
  "type": "Feature",
  "properties": {
    "iso:country":"DE",
    "sg:address":"Am Steinlech 11",
    "sg:city":"Landshut",
    "sg:postcode":"84036",
    "sg:province":"Bayern",
    "wof:name":"H & S Wohnbau Gmbh",
    "wof:placetype":"venue"
},
  "geometry": {"coordinates":[12.152983,48.518421],"type":"Point"}
}