{
  "type": "Feature",
  "properties": {
    "iso:country":"DE",
    "sg:address":"Mittelstr. 6",
    "sg:city":"Gro\u00dftreben-Zwethau",
    "sg:postcode":"04886",
    "sg:province":"Sachsen",
    "wof:name":"S. Heinrich",
    "wof:placetype":"venue"
},
  "geometry": {"coordinates":[12.9871368408,51.6467628479],"type":"Point"}
}