{
  "type": "Feature",
  "properties": {
    "iso:country":"DE",
    "sg:address":"Industriestr. 1",
    "sg:city":"Geisenheim",
    "sg:postcode":"65366",
    "sg:province":"Hessen",
    "wof:name":"Werner Gmbh",
    "wof:placetype":"venue"
},
  "geometry": {"coordinates":[7.975856,49.989441],"type":"Point"}
}