{
  "type": "Feature",
  "properties": {
    "iso:country":"DE",
    "sg:address":"Willibaldstr. 99",
    "sg:city":"M\u00fcnchen",
    "sg:phone":"+49 89/5805538",
    "sg:postcode":"80689",
    "sg:province":"Bayern",
    "wof:name":"Karl Schottenhamel Sportartikel",
    "wof:placetype":"venue"
},
  "geometry": {"coordinates":[11.484509,48.135307],"type":"Point"}
}