{
  "type": "Feature",
  "properties": {
    "iso:country":"DE",
    "sg:address":"Karl-Kellner-Str. 108",
    "sg:city":"Langenhagen",
    "sg:phone":"+49 511/738222",
    "sg:postcode":"30853",
    "sg:province":"Niedersachsen",
    "wof:name":"Lehnardt Transport Gmbh",
    "wof:placetype":"venue"
},
  "geometry": {"coordinates":[9.7384471893,52.4521522522],"type":"Point"}
}