{
  "type": "Feature",
  "properties": {
    "iso:country":"DE",
    "sg:address":"Bookenbusch 25",
    "sg:city":"Ahaus",
    "sg:phone":"+49 2567/476",
    "sg:postcode":"48683",
    "sg:province":"Nordrhein-Westfalen",
    "wof:name":"Hemker & Bekking Gmbh",
    "wof:placetype":"venue"
},
  "geometry": {"coordinates":[6.911375,52.124676],"type":"Point"}
}