{
  "type": "Feature",
  "properties": {
    "iso:country":"DE",
    "sg:address":"Juister Str. 10",
    "sg:city":"Papenburg",
    "sg:phone":"+49 4961/91710",
    "sg:postcode":"26871",
    "sg:province":"Niedersachsen",
    "wof:name":"Berufsbildungs- Und Techno- Logiezentrum Des Aschendorf-",
    "wof:placetype":"venue"
},
  "geometry": {"coordinates":[7.4235401154,53.0728607178],"type":"Point"}
}