{
  "type": "Feature",
  "properties": {
    "iso:country":"DE",
    "sg:address":"Hauptstr. 81",
    "sg:city":"Leinfelden-Echterdingen",
    "sg:phone":"+49 711/793515",
    "sg:postcode":"70771",
    "sg:province":"Baden-W\u00fcrttemberg",
    "wof:name":"Reinhold Haug Gmbh",
    "wof:placetype":"venue"
},
  "geometry": {"coordinates":[9.1667938232,48.6892318726],"type":"Point"}
}