{
  "type": "Feature",
  "properties": {
    "iso:country":"DE",
    "sg:address":"Wulfenauer Mark 5",
    "sg:city":"Dinklage",
    "sg:phone":"+49 5431/2823",
    "sg:postcode":"49413",
    "sg:province":"Niedersachsen",
    "wof:name":"Heinrich Osterhoff",
    "wof:placetype":"venue"
},
  "geometry": {"coordinates":[8.024379,52.685047],"type":"Point"}
}