{
  "type": "Feature",
  "properties": {
    "iso:country":"DE",
    "sg:address":"Rothenburger Str. 167",
    "sg:city":"N\u00fcrnberg",
    "sg:phone":"+49 911/619149",
    "sg:postcode":"90439",
    "sg:province":"Bayern",
    "wof:name":"Klaus Eder",
    "wof:placetype":"venue"
},
  "geometry": {"coordinates":[11.0482292175,49.4420967102],"type":"Point"}
}