{
  "type": "Feature",
  "properties": {
    "iso:country":"DE",
    "sg:address":"Bismarckstr. 10",
    "sg:city":"Hamburg",
    "sg:phone":"+49 40/406195",
    "sg:postcode":"20259",
    "sg:province":"Hamburg",
    "wof:name":"Sweet Virginia",
    "wof:placetype":"venue"
},
  "geometry": {"coordinates":[9.961216,53.572002],"type":"Point"}
}