{
  "type": "Feature",
  "properties": {
    "iso:country":"DE",
    "sg:address":"Gartenstr. 11",
    "sg:city":"Osterburg",
    "sg:phone":"+49 3937/83089",
    "sg:postcode":"39606",
    "sg:province":"Sachsen-Anhalt",
    "wof:name":"Hagemann Gmbh",
    "wof:placetype":"venue"
},
  "geometry": {"coordinates":[11.7569093704,52.7915420532],"type":"Point"}
}