{
  "type": "Feature",
  "properties": {
    "iso:country":"DE",
    "sg:address":"Bartholom\u00e4usstr. 1",
    "sg:city":"Mannheim",
    "sg:phone":"+49 621/771901",
    "sg:postcode":"68307",
    "sg:province":"Baden-W\u00fcrttemberg",
    "wof:name":"Friedrich Mayer",
    "wof:placetype":"venue"
},
  "geometry": {"coordinates":[8.4467897415,49.5462684631],"type":"Point"}
}