{
  "type": "Feature",
  "properties": {
    "iso:country":"DE",
    "sg:address":"Talstr 24",
    "sg:city":"D\u00fcsseldorf",
    "sg:phone":"+49 211/1592340",
    "sg:postcode":"40217",
    "sg:province":"Nordrhein-Westfalen",
    "wof:name":"On Touch Marketing & Communication Gmbh",
    "wof:placetype":"venue"
},
  "geometry": {"coordinates":[6.778977,51.216183],"type":"Point"}
}