{
  "type": "Feature",
  "properties": {
    "iso:country":"DE",
    "sg:address":"Krahestr. 746",
    "sg:city":"D\u00fcsseldorf",
    "sg:postcode":"40233",
    "sg:province":"Nordrhein-Westfalen",
    "wof:name":"Access Schreibb\u00fcro D\u00fcsseldorf, Schreibservice",
    "wof:placetype":"venue"
},
  "geometry": {"coordinates":[6.80337,51.222839],"type":"Point"}
}