{
  "type": "Feature",
  "properties": {
    "iso:country":"DE",
    "sg:address":"Am Hulsberg 3",
    "sg:city":"Bremen",
    "sg:phone":"+49 421/494912",
    "sg:postcode":"28205",
    "sg:province":"Bremen",
    "wof:name":"Eugen Heilmann",
    "wof:placetype":"venue"
},
  "geometry": {"coordinates":[8.842933,53.072178],"type":"Point"}
}