{
  "type": "Feature",
  "properties": {
    "iso:country":"DE",
    "sg:address":"Wilhelmstr. 54",
    "sg:city":"Euskirchen",
    "sg:phone":"+49 2251/74204",
    "sg:postcode":"53879",
    "sg:province":"Nordrhein-Westfalen",
    "wof:name":"Pizza Pfanne",
    "wof:placetype":"venue"
},
  "geometry": {"coordinates":[6.7881169319,50.6583328247],"type":"Point"}
}