{
  "type": "Feature",
  "properties": {
    "iso:country":"DE",
    "sg:address":"Am Ring",
    "sg:city":"Damme",
    "sg:phone":"+49 5491/7184",
    "sg:postcode":"49401",
    "sg:province":"Niedersachsen",
    "wof:name":"Friedrich Rolfsen",
    "wof:placetype":"venue"
},
  "geometry": {"coordinates":[8.280839,52.517082],"type":"Point"}
}