{
  "type": "Feature",
  "properties": {
    "iso:country":"DE",
    "sg:address":"Westliche Ringstr. 2",
    "sg:city":"Karben",
    "sg:postcode":"61184",
    "sg:province":"Hessen",
    "wof:name":"Stadtb\u00fccherei",
    "wof:placetype":"venue"
},
  "geometry": {"coordinates":[8.769837,50.238487],"type":"Point"}
}