{
  "type": "Feature",
  "properties": {
    "iso:country":"DE",
    "sg:address":"Zum Wurmtal 8",
    "sg:city":"W\u00fcrselen",
    "sg:phone":"+49 2405/85515",
    "sg:postcode":"52146",
    "sg:province":"Nordrhein-Westfalen",
    "wof:name":"Hans-josef Schmitt Architekt",
    "wof:placetype":"venue"
},
  "geometry": {"coordinates":[6.103215,50.844376],"type":"Point"}
}