{
  "type": "Feature",
  "properties": {
    "iso:country":"DE",
    "sg:address":"Unterm Hain 16",
    "sg:city":"Bad Berleburg",
    "sg:phone":"+49 2751/2452",
    "sg:postcode":"57319",
    "sg:province":"Nordrhein-Westfalen",
    "wof:name":"Dr. Burkhard M\u00fcller Tierarzt",
    "wof:placetype":"venue"
},
  "geometry": {"coordinates":[8.390542984,51.0515174866],"type":"Point"}
}