{
  "type": "Feature",
  "properties": {
    "iso:country":"DE",
    "sg:address":"Oestinghauser Str. 19",
    "sg:city":"Soest",
    "sg:phone":"+49 2921/80090",
    "sg:postcode":"59494",
    "sg:province":"Nordrhein-Westfalen",
    "wof:name":"Kreis & Schmitz",
    "wof:placetype":"venue"
},
  "geometry": {"coordinates":[8.111483,51.581074],"type":"Point"}
}