{
  "type": "Feature",
  "properties": {
    "iso:country":"DE",
    "sg:address":"Riederbergstr. 1",
    "sg:city":"Wiesbaden",
    "sg:phone":"+49 611/597576",
    "sg:postcode":"65195",
    "sg:province":"Hessen",
    "wof:name":"Acer Garte Design",
    "wof:placetype":"venue"
},
  "geometry": {"coordinates":[8.230461,50.084446],"type":"Point"}
}