{
  "type": "Feature",
  "properties": {
    "iso:country":"DE",
    "sg:address":"Magnolienweg 18",
    "sg:city":"Aschaffenburg",
    "sg:phone":"+49 6021/858155",
    "sg:postcode":"63741",
    "sg:province":"Bayern",
    "wof:name":"Kutzschbach Licht & Ambiente Gmbh",
    "wof:placetype":"venue"
},
  "geometry": {"coordinates":[9.1318902969,49.9654464722],"type":"Point"}
}