{
  "type": "Feature",
  "properties": {
    "iso:country":"DE",
    "sg:address":"Stresemannallee 30",
    "sg:city":"Frankfurt",
    "sg:phone":"+49 69/9636540",
    "sg:postcode":"60596",
    "sg:province":"Hessen",
    "wof:name":"Fire Gmbh",
    "wof:placetype":"venue"
},
  "geometry": {"coordinates":[8.6706371307,50.0960998535],"type":"Point"}
}