{
  "type": "Feature",
  "properties": {
    "iso:country":"DE",
    "sg:address":"Waldstr. 1",
    "sg:city":"Annaberg-Buchholz",
    "sg:phone":"+49 3733/6532",
    "sg:postcode":"09456",
    "sg:province":"Sachsen",
    "wof:name":"Gernot Zimmermann",
    "wof:placetype":"venue"
},
  "geometry": {"coordinates":[12.995193,50.560078],"type":"Point"}
}