{
  "type": "Feature",
  "properties": {
    "iso:country":"DE",
    "sg:address":"Werderstr. 4",
    "sg:city":"Merseburg",
    "sg:postcode":"06217",
    "sg:province":"Sachsen-Anhalt",
    "wof:name":"Aquaterra Gesellschaft F\u00fcr Probleml\u00f6sungen Der Wasser-",
    "wof:placetype":"venue"
},
  "geometry": {"coordinates":[12.01816,51.349121],"type":"Point"}
}