{
  "type": "Feature",
  "properties": {
    "iso:country":"DE",
    "sg:address":"Querstr. 1-3",
    "sg:city":"Gotha",
    "sg:phone":"+49 3621/823980",
    "sg:postcode":"99867",
    "sg:province":"Th\u00fcringen",
    "wof:name":"Klaus-peter Gomon Rechtsanwalt",
    "wof:placetype":"venue"
},
  "geometry": {"coordinates":[10.7037410736,50.9497795105],"type":"Point"}
}