{
  "type": "Feature",
  "properties": {
    "iso:country":"DE",
    "sg:address":"Gl\u00fcck-Auf-Str. 2",
    "sg:city":"Immenhausen",
    "sg:phone":"+49 5673/925340",
    "sg:postcode":"34376",
    "sg:province":"Hessen",
    "wof:name":"Josef Kolar",
    "wof:placetype":"venue"
},
  "geometry": {"coordinates":[9.5377931595,51.423538208],"type":"Point"}
}