{
  "type": "Feature",
  "properties": {
    "iso:country":"DE",
    "sg:address":"Scheibenstr. 40",
    "sg:city":"K\u00f6ln",
    "sg:phone":"+49 221",
    "sg:postcode":"50737",
    "sg:province":"Nordrhein-Westfalen",
    "wof:name":"Gasthaus Rennbahn K\u00f6ln",
    "wof:placetype":"venue"
},
  "geometry": {"coordinates":[6.9496798515,50.9852294922],"type":"Point"}
}