{
  "type": "Feature",
  "properties": {
    "iso:country":"DE",
    "sg:address":"Kaskelstr. 32",
    "sg:city":"Berlin",
    "sg:phone":"+49 30/5536041",
    "sg:postcode":"10317",
    "sg:province":"Berlin",
    "wof:name":"Adler-apotheke Apotheker Peter Heyder",
    "wof:placetype":"venue"
},
  "geometry": {"coordinates":[13.479741,52.50407],"type":"Point"}
}