{
  "type": "Feature",
  "properties": {
    "iso:country":"DE",
    "sg:address":"Abteiberg 2",
    "sg:city":"Oberlungwitz",
    "sg:phone":"+49 3723/681799",
    "sg:postcode":"09353",
    "sg:province":"Sachsen",
    "wof:name":"Automeile Am Sachsenring Gmbh",
    "wof:placetype":"venue"
},
  "geometry": {"coordinates":[12.7342376709,50.7884674072],"type":"Point"}
}