{
  "type": "Feature",
  "properties": {
    "iso:country":"DE",
    "sg:address":"Hauptstr. 118 a",
    "sg:city":"Dietzh\u00f6lztal",
    "sg:phone":"+49 2774/4516",
    "sg:postcode":"35716",
    "sg:province":"Hessen",
    "wof:name":"Dietmar Nassauer Architekt",
    "wof:placetype":"venue"
},
  "geometry": {"coordinates":[8.311154,50.833916],"type":"Point"}
}