{
  "type": "Feature",
  "properties": {
    "iso:country":"DE",
    "sg:address":"H.-H.-Meier-Allee 36",
    "sg:city":"Bremen",
    "sg:phone":"+49 421/215714",
    "sg:postcode":"28213",
    "sg:province":"Bremen",
    "wof:name":"Stichweh Textilreinigung Peter Cienschkowski",
    "wof:placetype":"venue"
},
  "geometry": {"coordinates":[8.845502,53.09166],"type":"Point"}
}