{
  "type": "Feature",
  "properties": {
    "iso:country":"DE",
    "sg:address":"Babenbergerring 171",
    "sg:city":"Bamberg",
    "sg:phone":"+49 951/57621",
    "sg:postcode":"96049",
    "sg:province":"Bayern",
    "wof:name":"Hilde B\u00e4r",
    "wof:placetype":"venue"
},
  "geometry": {"coordinates":[10.8777523041,49.8740158081],"type":"Point"}
}