{
  "type": "Feature",
  "properties": {
    "iso:country":"DE",
    "sg:address":"Am Bierbaum 5",
    "sg:city":"L\u00fcdenscheid",
    "sg:phone":"+49 2351/459028",
    "sg:postcode":"58515",
    "sg:province":"Nordrhein-Westfalen",
    "wof:name":"Cordt",
    "wof:placetype":"venue"
},
  "geometry": {"coordinates":[7.65423,51.203068],"type":"Point"}
}