{
  "type": "Feature",
  "properties": {
    "iso:country":"DE",
    "sg:address":"Hohe Rainstr. 1",
    "sg:city":"Bad Endbach",
    "sg:phone":"+49 6440/1230",
    "sg:postcode":"35080",
    "sg:province":"Hessen",
    "wof:name":"Helma Born",
    "wof:placetype":"venue"
},
  "geometry": {"coordinates":[8.49806,50.75383],"type":"Point"}
}