{
  "type": "Feature",
  "properties": {
    "iso:country":"DE",
    "sg:address":"Langenbacher Str. 11",
    "sg:city":"M\u00fchltroff",
    "sg:phone":"+49 4936/6453010",
    "sg:postcode":"07919",
    "sg:province":"Th\u00fcringen",
    "wof:name":"Kartonagen-und H\u00dclsenfabrik Erich M\u00dcller Gmbh & Co.",
    "wof:placetype":"venue"
},
  "geometry": {"coordinates":[11.9228105545,50.5374794006],"type":"Point"}
}