{
  "type": "Feature",
  "properties": {
    "iso:country":"DE",
    "sg:address":"Wintermoos 45",
    "sg:city":"Tennenbronn",
    "sg:phone":"+49 7729/341",
    "sg:postcode":"78144",
    "sg:province":"Baden-W\u00fcrttemberg",
    "wof:name":"Werner Breithaupt",
    "wof:placetype":"venue"
},
  "geometry": {"coordinates":[8.346881,48.188702],"type":"Point"}
}