{
  "type": "Feature",
  "properties": {
    "iso:country":"DE",
    "sg:address":"Rheinstr. 10",
    "sg:city":"Hachenburg",
    "sg:phone":"+49 2662/5288",
    "sg:postcode":"57627",
    "sg:province":"Rheinland-Pfalz",
    "wof:name":"Matthias Ketz",
    "wof:placetype":"venue"
},
  "geometry": {"coordinates":[7.8149580956,50.6588935852],"type":"Point"}
}