{
  "type": "Feature",
  "properties": {
    "iso:country":"DE",
    "sg:address":"Hannoversche Str. 41",
    "sg:city":"Garbsen",
    "sg:phone":"+49 5137/78258",
    "sg:postcode":"30823",
    "sg:province":"Niedersachsen",
    "wof:name":"Uwe Klein Steuerberater",
    "wof:placetype":"venue"
},
  "geometry": {"coordinates":[9.6114959717,52.405620575],"type":"Point"}
}