{
  "type": "Feature",
  "properties": {
    "iso:country":"DE",
    "sg:address":"Saalstr. 15",
    "sg:city":"Korntal-M\u00fcnchingen",
    "sg:phone":"+49 711/8380882",
    "sg:postcode":"70825",
    "sg:province":"Baden-W\u00fcrttemberg",
    "wof:name":"Restaurant Wirtsch\u00e4ftle",
    "wof:placetype":"venue"
},
  "geometry": {"coordinates":[9.1258611679,48.8315963745],"type":"Point"}
}