{
  "type": "Feature",
  "properties": {
    "iso:country":"DE",
    "sg:address":"Wiener Str. 51",
    "sg:city":"Magdeburg",
    "sg:postcode":"39112",
    "sg:province":"Sachsen-Anhalt",
    "wof:name":"Aengevelt-immobilien Kg",
    "wof:placetype":"venue"
},
  "geometry": {"coordinates":[11.612716,52.110413],"type":"Point"}
}