{
  "type": "Feature",
  "properties": {
    "iso:country":"DE",
    "sg:address":"Friedhofstr. 8",
    "sg:city":"Remscheid",
    "sg:phone":"+49 2191/51412",
    "sg:postcode":"42899",
    "sg:province":"Nordrhein-Westfalen",
    "wof:name":"G\u00fcnter Schaaf",
    "wof:placetype":"venue"
},
  "geometry": {"coordinates":[7.2388892174,51.2068328857],"type":"Point"}
}