{
  "type": "Feature",
  "properties": {
    "iso:country":"DE",
    "sg:address":"Kirchstr. 526",
    "sg:city":"Upgant-Schott",
    "sg:postcode":"26529",
    "sg:province":"Niedersachsen",
    "wof:name":"Upganter Baustoffhandels- Gesellschaft Jungenkr\u00fcger Mbh",
    "wof:placetype":"venue"
},
  "geometry": {"coordinates":[7.293688,53.525429],"type":"Point"}
}