{
  "type": "Feature",
  "properties": {
    "iso:country":"DE",
    "sg:address":"Tropschallee 33",
    "sg:city":"Waldkraiburg",
    "sg:phone":"+49 8638/880803",
    "sg:postcode":"84478",
    "sg:province":"Bayern",
    "wof:name":"Reindl Baubetreuungs Gmbh",
    "wof:placetype":"venue"
},
  "geometry": {"coordinates":[12.4007863998,48.2192649841],"type":"Point"}
}