{
  "type": "Feature",
  "properties": {
    "iso:country":"DE",
    "sg:address":"Boschetsrieder Str. 70",
    "sg:city":"M\u00fcnchen",
    "sg:postcode":"81379",
    "sg:province":"Bayern",
    "wof:name":"Altraglobe Gmbh",
    "wof:placetype":"venue"
},
  "geometry": {"coordinates":[11.5284366608,48.099937439],"type":"Point"}
}