{
  "type": "Feature",
  "properties": {
    "iso:country":"DE",
    "sg:address":"W\u00e4rderstr.1-3",
    "sg:city":"Geesthacht",
    "sg:phone":"+49 4941/5288230",
    "sg:postcode":"21502",
    "sg:province":"Schleswig-Holstein",
    "wof:name":"Josef M\u00d6bius Bau Ag",
    "wof:placetype":"venue"
},
  "geometry": {"coordinates":[10.353394,53.432346],"type":"Point"}
}