{
  "type": "Feature",
  "properties": {
    "iso:country":"DE",
    "sg:address":"Seeheimer Str. 78",
    "sg:city":"Pfungstadt",
    "sg:phone":"+49 6157/3504",
    "sg:postcode":"64319",
    "sg:province":"Hessen",
    "wof:name":"W. Hassenzahl",
    "wof:placetype":"venue"
},
  "geometry": {"coordinates":[8.6032848358,49.7969779968],"type":"Point"}
}