{
  "type": "Feature",
  "properties": {
    "iso:country":"DE",
    "sg:address":"Heinsestr. 38",
    "sg:city":"Berlin",
    "sg:phone":"+49 30/4048607",
    "sg:postcode":"13467",
    "sg:province":"Berlin",
    "wof:name":"Blumenhaus Fiebich",
    "wof:placetype":"venue"
},
  "geometry": {"coordinates":[13.306449,52.617538],"type":"Point"}
}