{
  "type": "Feature",
  "properties": {
    "iso:country":"DE",
    "sg:address":"Hafenstr. 21",
    "sg:city":"Stralsund",
    "sg:phone":"+49 3831/297997",
    "sg:postcode":"18439",
    "sg:province":"Mecklenburg-Vorpommern",
    "wof:name":"Fbn-fahrzeuge Und Baumaschinen",
    "wof:placetype":"venue"
},
  "geometry": {"coordinates":[13.098871,54.314011],"type":"Point"}
}