{
  "type": "Feature",
  "properties": {
    "iso:country":"DE",
    "sg:address":"Schelhornstr. 17",
    "sg:city":"Memmingen",
    "sg:phone":"+49 8331/63167",
    "sg:postcode":"87700",
    "sg:province":"Bayern",
    "wof:name":"Curt Visel",
    "wof:placetype":"venue"
},
  "geometry": {"coordinates":[10.162399292,47.9861373901],"type":"Point"}
}