{
  "type": "Feature",
  "properties": {
    "iso:country":"DE",
    "sg:address":"St\u00fcrmleslochweg 12",
    "sg:city":"Bad Wildbad",
    "sg:phone":"+49 7081/2991",
    "sg:postcode":"75323",
    "sg:province":"Baden-W\u00fcrttemberg",
    "wof:name":"Waltraut R\u00f6ssler Krankengymnastin",
    "wof:placetype":"venue"
},
  "geometry": {"coordinates":[8.540488,48.733742],"type":"Point"}
}