{
  "type": "Feature",
  "properties": {
    "iso:country":"DE",
    "sg:address":"Gr\u00fcner Weg 24",
    "sg:city":"Frankfurt",
    "sg:phone":"+49 335/6850801",
    "sg:postcode":"15230",
    "sg:province":"Brandenburg",
    "wof:name":"Musikbox",
    "wof:placetype":"venue"
},
  "geometry": {"coordinates":[14.5405597687,52.3476867676],"type":"Point"}
}