{
  "type": "Feature",
  "properties": {
    "iso:country":"DE",
    "sg:address":"Marktplatz 7",
    "sg:city":"Neustadt",
    "sg:phone":"+49 9568/5317",
    "sg:postcode":"96465",
    "sg:province":"Bayern",
    "wof:name":"Julius L\u00f6ffler",
    "wof:placetype":"venue"
},
  "geometry": {"coordinates":[9.0350198746,49.8172950745],"type":"Point"}
}