{
  "type": "Feature",
  "properties": {
    "iso:country":"DE",
    "sg:address":"Ruhrstr 62",
    "sg:city":"Hamburg",
    "sg:phone":"+49 40/89070011",
    "sg:postcode":"22761",
    "sg:province":"Hamburg",
    "wof:name":"Dr. Jauss & Partner Hanseatische Unternehmensberatung Gmbh",
    "wof:placetype":"venue"
},
  "geometry": {"coordinates":[9.925712,53.565849],"type":"Point"}
}