{
  "type": "Feature",
  "properties": {
    "iso:country":"DE",
    "sg:address":"Gr\u00fcner Weg 86",
    "sg:city":"Aachen",
    "sg:phone":"+49 4924/1162413",
    "sg:postcode":"52070",
    "sg:province":"Nordrhein-Westfalen",
    "wof:name":"Pries",
    "wof:placetype":"venue"
},
  "geometry": {"coordinates":[6.1075968742,50.7911911011],"type":"Point"}
}