{
  "type": "Feature",
  "properties": {
    "iso:country":"DE",
    "sg:address":"Kraftwerkstr. 5",
    "sg:city":"Rain",
    "sg:phone":"+49 9090/2403",
    "sg:postcode":"86641",
    "sg:province":"Bayern",
    "wof:name":"Josef M\u00fcller Gmbh",
    "wof:placetype":"venue"
},
  "geometry": {"coordinates":[10.9101581573,48.6919364929],"type":"Point"}
}