{
  "type": "Feature",
  "properties": {
    "iso:country":"DE",
    "sg:address":"Oskar von Miller Str. 3",
    "sg:city":"Nabburg",
    "sg:phone":"+49 9433",
    "sg:postcode":"92507",
    "sg:province":"Bayern",
    "wof:name":"Kachel\u00f6fen Und Kamine - Rittmeyer Partner Gmbh 92507 Nab",
    "wof:placetype":"venue"
},
  "geometry": {"coordinates":[12.1985321045,49.4550323486],"type":"Point"}
}