{
  "type": "Feature",
  "properties": {
    "iso:country":"DE",
    "sg:address":"Bahnhofstr. 23",
    "sg:city":"Ottweiler",
    "sg:phone":"+49 6824/4646",
    "sg:postcode":"66564",
    "sg:province":"Saarland",
    "wof:name":"Klein Und Kehe Rechtsanw\u00e4lte",
    "wof:placetype":"venue"
},
  "geometry": {"coordinates":[7.1653428078,49.4031410217],"type":"Point"}
}