{
  "type": "Feature",
  "properties": {
    "iso:country":"DE",
    "sg:address":"Albrecht-Thaer-Str. 6",
    "sg:city":"Bremerv\u00f6rde",
    "sg:postcode":"27432",
    "sg:province":"Niedersachsen",
    "wof:name":"Brela Steuerberat.-gmbh",
    "wof:placetype":"venue"
},
  "geometry": {"coordinates":[9.1347408295,53.4701652527],"type":"Point"}
}