{
  "type": "Feature",
  "properties": {
    "iso:country":"DE",
    "sg:address":"Dettenheimer Str. 9",
    "sg:city":"Wei\u00dfenburg",
    "sg:phone":"+49 9141/86110",
    "sg:postcode":"91781",
    "sg:province":"Bayern",
    "wof:name":"Fliesen-fachmarkt Rauh Inh. Hans-dieter Rauh",
    "wof:placetype":"venue"
},
  "geometry": {"coordinates":[10.9523286819,49.0041770935],"type":"Point"}
}