{
  "type": "Feature",
  "properties": {
    "iso:country":"DE",
    "sg:address":"Schulstr. 1",
    "sg:city":"Stadt Wehlen",
    "sg:phone":"+49 35024/70507",
    "sg:postcode":"01829",
    "sg:province":"Sachsen",
    "wof:name":"Uwe Ehlert",
    "wof:placetype":"venue"
},
  "geometry": {"coordinates":[14.0035257339,50.9626045227],"type":"Point"}
}