{
  "type": "Feature",
  "properties": {
    "iso:country":"DE",
    "sg:address":"Am Berg 5",
    "sg:city":"Gillenbeuren",
    "sg:phone":"+49 2677/574",
    "sg:postcode":"56825",
    "sg:province":"Rheinland-Pfalz",
    "wof:name":"Charlotte Becker Heilpraktikerin",
    "wof:placetype":"venue"
},
  "geometry": {"coordinates":[7.0179710388,50.1593399048],"type":"Point"}
}