{
  "type": "Feature",
  "properties": {
    "iso:country":"DE",
    "sg:address":"Hafenstr. 90",
    "sg:city":"Neuwied",
    "sg:phone":"+49 2631/850",
    "sg:postcode":"56564",
    "sg:province":"Rheinland-Pfalz",
    "wof:name":"Stadtwerke Neuwied Gmbh",
    "wof:placetype":"venue"
},
  "geometry": {"coordinates":[7.484575,50.416637],"type":"Point"}
}