{
  "type": "Feature",
  "properties": {
    "iso:country":"DE",
    "sg:address":"Freudentaler Str. 5",
    "sg:city":"Allensbach",
    "sg:phone":"+49 7533/5374",
    "sg:postcode":"78476",
    "sg:province":"Baden-W\u00fcrttemberg",
    "wof:name":"Hans Erne",
    "wof:placetype":"venue"
},
  "geometry": {"coordinates":[9.078483,47.735104],"type":"Point"}
}