{
  "type": "Feature",
  "properties": {
    "iso:country":"DE",
    "sg:address":"Heimst\u00e4ttenweg 137",
    "sg:city":"Darmstadt",
    "sg:phone":"+49 6151/312361",
    "sg:postcode":"64295",
    "sg:province":"Hessen",
    "wof:name":"Georg Fuchs",
    "wof:placetype":"venue"
},
  "geometry": {"coordinates":[8.622001,49.849792],"type":"Point"}
}