{
  "type": "Feature",
  "properties": {
    "iso:country":"DE",
    "sg:address":"Flamweg 12",
    "sg:city":"Elmshorn",
    "sg:phone":"+49 4121/25262",
    "sg:postcode":"25335",
    "sg:province":"Schleswig-Holstein",
    "wof:name":"Teestube",
    "wof:placetype":"venue"
},
  "geometry": {"coordinates":[9.6501636505,53.7536430359],"type":"Point"}
}