{
  "type": "Feature",
  "properties": {
    "iso:country":"DE",
    "sg:address":"Remser Weg 32",
    "sg:city":"Remse",
    "sg:phone":"+49 3763/15523",
    "sg:postcode":"08373",
    "sg:province":"Sachsen",
    "wof:name":"Ingolf Doberenz",
    "wof:placetype":"venue"
},
  "geometry": {"coordinates":[12.5440607071,50.8494224548],"type":"Point"}
}