{
  "type": "Feature",
  "properties": {
    "iso:country":"DE",
    "sg:address":"Im Ostfeld 5",
    "sg:city":"Schwerte",
    "sg:postcode":"58239",
    "sg:province":"Nordrhein-Westfalen",
    "wof:name":"Risse Grundbesitz Gmbh & Co. Kg",
    "wof:placetype":"venue"
},
  "geometry": {"coordinates":[7.5382947922,51.4237060547],"type":"Point"}
}