{
  "type": "Feature",
  "properties": {
    "iso:country":"DE",
    "sg:address":"Schulstr. 29",
    "sg:city":"Malchin",
    "sg:phone":"+49 3994/223024",
    "sg:postcode":"17139",
    "sg:province":"Mecklenburg-Vorpommern",
    "wof:name":"Friedrich Wulsten",
    "wof:placetype":"venue"
},
  "geometry": {"coordinates":[12.7597179413,53.7396965027],"type":"Point"}
}