{
  "type": "Feature",
  "properties": {
    "iso:country":"DE",
    "sg:address":"Kornblumenstr. 6",
    "sg:city":"Schwabhausen",
    "sg:phone":"+49 8138/9101",
    "sg:postcode":"85247",
    "sg:province":"Bayern",
    "wof:name":"Klaus Gottschalk Rechtsanwalt",
    "wof:placetype":"venue"
},
  "geometry": {"coordinates":[11.3597049713,48.2993240356],"type":"Point"}
}