{
  "type": "Feature",
  "properties": {
    "iso:country":"DE",
    "sg:address":"Horbstr. 8",
    "sg:city":"Ostfildern",
    "sg:phone":"+49 711/4411073",
    "sg:postcode":"73760",
    "sg:province":"Baden-W\u00fcrttemberg",
    "wof:name":"Spiegel",
    "wof:placetype":"venue"
},
  "geometry": {"coordinates":[9.246158,48.729767],"type":"Point"}
}