{
  "type": "Feature",
  "properties": {
    "iso:country":"DE",
    "sg:address":"Sch\u00f6naicher Str 4",
    "sg:city":"Hartmannsdorf",
    "sg:phone":"+49 3722/814666",
    "sg:postcode":"09232",
    "sg:province":"Sachsen",
    "wof:name":"Paul Riedel Nachfolger",
    "wof:placetype":"venue"
},
  "geometry": {"coordinates":[12.791392,50.898617],"type":"Point"}
}