{
  "type": "Feature",
  "properties": {
    "iso:country":"DE",
    "sg:address":"Otto-Schrimpff-Str. 16",
    "sg:city":"Roth",
    "sg:phone":"+49 9171/806108",
    "sg:postcode":"91154",
    "sg:province":"Bayern",
    "wof:name":"Fabrikmuseum Der Leonischen Industrie",
    "wof:placetype":"venue"
},
  "geometry": {"coordinates":[11.094509,49.242336],"type":"Point"}
}