{
  "type": "Feature",
  "properties": {
    "iso:country":"DE",
    "sg:address":"Hofheimer Str. 4",
    "sg:city":"Ha\u00dffurt",
    "sg:phone":"+49 9521/8738",
    "sg:postcode":"97437",
    "sg:province":"Bayern",
    "wof:name":"Dr. Med. Ludwig Feulner",
    "wof:placetype":"venue"
},
  "geometry": {"coordinates":[10.5139875412,50.0331840515],"type":"Point"}
}