{
  "type": "Feature",
  "properties": {
    "iso:country":"DE",
    "sg:address":"Wiesener Str 99",
    "sg:city":"Frammersbach",
    "sg:phone":"+49 9355/99775",
    "sg:postcode":"97833",
    "sg:province":"Bayern",
    "wof:name":"Reber Gmbh",
    "wof:placetype":"venue"
},
  "geometry": {"coordinates":[9.459702,50.061916],"type":"Point"}
}