{
  "type": "Feature",
  "properties": {
    "iso:country":"DE",
    "sg:address":"Kelberger Str. 1",
    "sg:city":"Dreis-Br\u00fcck",
    "sg:phone":"+49 6595/375",
    "sg:postcode":"54552",
    "sg:province":"Rheinland-Pfalz",
    "wof:name":"Winfried Wierz",
    "wof:placetype":"venue"
},
  "geometry": {"coordinates":[6.7943868637,50.2648429871],"type":"Point"}
}