{
  "type": "Feature",
  "properties": {
    "iso:country":"DE",
    "sg:address":"Thumseestr. 21",
    "sg:city":"Bad Reichenhall",
    "sg:phone":"+49 8651/1250",
    "sg:postcode":"83435",
    "sg:province":"Bayern",
    "wof:name":"Rapold Gmbh",
    "wof:placetype":"venue"
},
  "geometry": {"coordinates":[12.8645143509,47.7195358276],"type":"Point"}
}