{
  "type": "Feature",
  "properties": {
    "iso:country":"DE",
    "sg:address":"Alte Dorfstr. 13",
    "sg:city":"Barsb\u00fcttel",
    "sg:phone":"+49 40/7101162",
    "sg:postcode":"22885",
    "sg:province":"Schleswig-Holstein",
    "wof:name":"Uwe Martens & Heinz Hamerich Baugesch\u00e4ft",
    "wof:placetype":"venue"
},
  "geometry": {"coordinates":[10.204255,53.562183],"type":"Point"}
}