{
  "type": "Feature",
  "properties": {
    "iso:country":"DE",
    "sg:address":"Am Dattelner Meer 4",
    "sg:city":"Datteln",
    "sg:phone":"+49 2363/561108",
    "sg:postcode":"45711",
    "sg:province":"Nordrhein-Westfalen",
    "wof:name":"Vst Ingenieur-gmbh",
    "wof:placetype":"venue"
},
  "geometry": {"coordinates":[7.360839,51.661354],"type":"Point"}
}