{
  "type": "Feature",
  "properties": {
    "iso:country":"DE",
    "sg:address":"Industrieweg 17",
    "sg:city":"Sendenhorst",
    "sg:postcode":"48324",
    "sg:province":"Nordrhein-Westfalen",
    "wof:name":"Vaz Video- Und Audio Zubeh\u00f6r Produktions- Und",
    "wof:placetype":"venue"
},
  "geometry": {"coordinates":[7.8427181244,51.8386993408],"type":"Point"}
}