{
  "type": "Feature",
  "properties": {
    "iso:country":"DE",
    "sg:address":"Roschbacher Str. 1",
    "sg:city":"Hainfeld",
    "sg:phone":"+49 6323/2714",
    "sg:postcode":"76835",
    "sg:province":"Rheinland-Pfalz",
    "wof:name":"Ludwig Satter & Sohn Gmbh",
    "wof:placetype":"venue"
},
  "geometry": {"coordinates":[8.1021966934,49.2549057007],"type":"Point"}
}