{
  "type": "Feature",
  "properties": {
    "iso:country":"DE",
    "sg:address":"Friedhofstr. 32",
    "sg:city":"Vlotho",
    "sg:phone":"+49 5733/8434",
    "sg:postcode":"32602",
    "sg:province":"Nordrhein-Westfalen",
    "wof:name":"Hans-heinrich Rinne Rechtsanwalt",
    "wof:placetype":"venue"
},
  "geometry": {"coordinates":[8.8791570663,52.1734275818],"type":"Point"}
}