{
  "type": "Feature",
  "properties": {
    "iso:country":"DE",
    "sg:address":"Goldsternstr. 58",
    "sg:city":"Leipzig",
    "sg:phone":"+49 341/699213",
    "sg:postcode":"04329",
    "sg:province":"Sachsen",
    "wof:name":"Kaufhalle Paunsdorf",
    "wof:placetype":"venue"
},
  "geometry": {"coordinates":[12.459086,51.356564],"type":"Point"}
}