{
  "type": "Feature",
  "properties": {
    "iso:country":"DE",
    "sg:address":"Sch\u00f6nberg 8",
    "sg:city":"Egling",
    "sg:phone":"+49 8170/355",
    "sg:postcode":"82544",
    "sg:province":"Bayern",
    "wof:name":"Strobls Kleinbusse",
    "wof:placetype":"venue"
},
  "geometry": {"coordinates":[11.4842433929,47.9388542175],"type":"Point"}
}