{
  "type": "Feature",
  "properties": {
    "iso:country":"DE",
    "sg:address":"Dorfstr. 9",
    "sg:city":"Colditz",
    "sg:postcode":"04680",
    "sg:province":"Sachsen",
    "wof:name":"Windstromer Gesellschaft F\u00fcr Erneuerbare Energien Mbh",
    "wof:placetype":"venue"
},
  "geometry": {"coordinates":[12.828215,51.09832],"type":"Point"}
}