{
  "type": "Feature",
  "properties": {
    "iso:country":"DE",
    "sg:address":"Zweibr\u00fccker Str. 17",
    "sg:city":"Erdesbach",
    "sg:phone":"+49 6381/1778",
    "sg:postcode":"66887",
    "sg:province":"Rheinland-Pfalz",
    "wof:name":"L. Hein",
    "wof:placetype":"venue"
},
  "geometry": {"coordinates":[7.4440097809,49.5733108521],"type":"Point"}
}