{
  "type": "Feature",
  "properties": {
    "iso:country":"DE",
    "sg:address":"Otto-Hahn-Str. 37",
    "sg:city":"Gundersheim",
    "sg:phone":"+49 6244/5614",
    "sg:postcode":"67598",
    "sg:province":"Rheinland-Pfalz",
    "wof:name":"Hagewe Handelsges. Mbh",
    "wof:placetype":"venue"
},
  "geometry": {"coordinates":[8.193641,49.69566],"type":"Point"}
}