{
  "type": "Feature",
  "properties": {
    "iso:country":"DE",
    "sg:address":"Am Markt 19",
    "sg:city":"Br\u00fchl",
    "sg:phone":"+49 2232/45011",
    "sg:postcode":"50321",
    "sg:province":"Nordrhein-Westfalen",
    "wof:name":"Dresdner Bank",
    "wof:placetype":"venue"
},
  "geometry": {"coordinates":[6.904558,50.828896],"type":"Point"}
}