{
  "type": "Feature",
  "properties": {
    "iso:country":"DE",
    "sg:address":"Alter Markt 10",
    "sg:city":"Kiel",
    "sg:phone":"+49 431/997155",
    "sg:postcode":"24103",
    "sg:province":"Schleswig-Holstein",
    "wof:name":"Check In Inh. Linda Blachewitz",
    "wof:placetype":"venue"
},
  "geometry": {"coordinates":[10.1391086578,54.323589325],"type":"Point"}
}