{
  "type": "Feature",
  "properties": {
    "iso:country":"DE",
    "sg:address":"Falkenstr. 18",
    "sg:city":"Bremen",
    "sg:phone":"+49 421/15877",
    "sg:postcode":"28195",
    "sg:province":"Bremen",
    "wof:name":"Rolf Lehmkuhl",
    "wof:placetype":"venue"
},
  "geometry": {"coordinates":[8.8053979874,53.0833282471],"type":"Point"}
}