{
  "type": "Feature",
  "properties": {
    "iso:country":"DE",
    "sg:address":"An der Bahn 1 - 3",
    "sg:city":"Bergisch Gladbach",
    "sg:phone":"+49 2204/92020",
    "sg:postcode":"51427",
    "sg:province":"Nordrhein-Westfalen",
    "wof:name":"Obi Bau- Und Heimwerkermarkt Bensberg Gmbh",
    "wof:placetype":"venue"
},
  "geometry": {"coordinates":[7.1454601288,50.9580116272],"type":"Point"}
}