{
  "type": "Feature",
  "properties": {
    "iso:country":"DE",
    "sg:address":"Auf der Schanz 34",
    "sg:city":"N\u00fcrnberg",
    "sg:phone":"+49 911/6383302",
    "sg:postcode":"90453",
    "sg:province":"Bayern",
    "wof:name":"Scheufler Kg",
    "wof:placetype":"venue"
},
  "geometry": {"coordinates":[11.0239534378,49.3739814758],"type":"Point"}
}