{
  "type": "Feature",
  "properties": {
    "iso:country":"DE",
    "sg:address":"Wielandstr. 12",
    "sg:city":"Leinfelden-Echterdingen",
    "sg:phone":"+49 711/7544828",
    "sg:postcode":"70771",
    "sg:province":"Baden-W\u00fcrttemberg",
    "wof:name":"Karl Bubser",
    "wof:placetype":"venue"
},
  "geometry": {"coordinates":[9.116502,48.695164],"type":"Point"}
}