{
  "type": "Feature",
  "properties": {
    "iso:country":"DE",
    "sg:address":"Liedbachstr. 10 a",
    "sg:city":"Unna",
    "sg:phone":"+49 2303/86768",
    "sg:postcode":"59427",
    "sg:province":"Nordrhein-Westfalen",
    "wof:name":"Rudolf Betzinger Ingenieur",
    "wof:placetype":"venue"
},
  "geometry": {"coordinates":[7.6681699753,51.5020599365],"type":"Point"}
}