{
  "type": "Feature",
  "properties": {
    "iso:country":"DE",
    "sg:address":"Karlstr. 48",
    "sg:city":"Aachen",
    "sg:phone":"+49 241/551725",
    "sg:postcode":"52080",
    "sg:province":"Nordrhein-Westfalen",
    "wof:name":"Siegfried Kaul",
    "wof:placetype":"venue"
},
  "geometry": {"coordinates":[6.1490221024,50.7799415588],"type":"Point"}
}