{
  "type": "Feature",
  "properties": {
    "iso:country":"DE",
    "sg:address":"Hoyerswerdaer Str. 36",
    "sg:city":"Dresden",
    "sg:phone":"+49 351/8030412",
    "sg:postcode":"01099",
    "sg:province":"Sachsen",
    "wof:name":"Joachim Schiedt",
    "wof:placetype":"venue"
},
  "geometry": {"coordinates":[13.752215,51.062473],"type":"Point"}
}