{
  "type": "Feature",
  "properties": {
    "iso:country":"DE",
    "sg:address":"Rosenkavalierplatz 2",
    "sg:city":"M\u00fcnchen",
    "sg:phone":"+49 89/921400",
    "sg:postcode":"81925",
    "sg:province":"Bayern",
    "wof:name":"Bayerisches Staatsministerium F\u00fcr Landesentwicklung Und",
    "wof:placetype":"venue"
},
  "geometry": {"coordinates":[11.6185,48.152309],"type":"Point"}
}