{
  "type": "Feature",
  "properties": {
    "iso:country":"DE",
    "sg:address":"Froschheide 2A",
    "sg:city":"M\u00fclheim",
    "sg:phone":"+49 208/35786",
    "sg:postcode":"45475",
    "sg:province":"Nordrhein-Westfalen",
    "wof:name":"A. Schumacher",
    "wof:placetype":"venue"
},
  "geometry": {"coordinates":[6.898706,51.45845],"type":"Point"}
}