{
  "type": "Feature",
  "properties": {
    "iso:country":"DE",
    "sg:address":"Hugo-Junkers-Str. 12",
    "sg:city":"K\u00f6ln",
    "sg:postcode":"50739",
    "sg:province":"Nordrhein-Westfalen",
    "wof:name":"Newstyle Clothing Ohg",
    "wof:placetype":"venue"
},
  "geometry": {"coordinates":[6.9107041359,50.9906272888],"type":"Point"}
}