{
  "type": "Feature",
  "properties": {
    "iso:country":"DE",
    "sg:address":"Adenauerstr. 15",
    "sg:city":"Marienfeld",
    "sg:phone":"+49 5247/8960",
    "sg:postcode":"33428",
    "sg:province":"Nordrhein-Westfalen",
    "wof:name":"Marien Apotheke Inh. J\u00f6rn Buttler",
    "wof:placetype":"venue"
},
  "geometry": {"coordinates":[8.273426,51.94965],"type":"Point"}
}