{
  "type": "Feature",
  "properties": {
    "iso:country":"DE",
    "sg:address":"Sonnenweg 2",
    "sg:city":"Sigmaringen",
    "sg:phone":"+49 7570/346",
    "sg:postcode":"72488",
    "sg:province":"Baden-W\u00fcrttemberg",
    "wof:name":"Gasthaus Sonne",
    "wof:placetype":"venue"
},
  "geometry": {"coordinates":[9.1164741516,48.0778846741],"type":"Point"}
}