{
  "type": "Feature",
  "properties": {
    "iso:country":"DE",
    "sg:address":"Venloer Str. 131-133",
    "sg:city":"Wegberg",
    "sg:phone":"+49 2434/928580",
    "sg:postcode":"41844",
    "sg:province":"Nordrhein-Westfalen",
    "wof:name":"Anton R\u00f6ttinger",
    "wof:placetype":"venue"
},
  "geometry": {"coordinates":[6.2733969688,51.15026474],"type":"Point"}
}