{
  "type": "Feature",
  "properties": {
    "iso:country":"DE",
    "sg:address":"Hartmeyerstr. 11",
    "sg:city":"T\u00fcbingen",
    "sg:phone":"+49 7071/61260",
    "sg:postcode":"72076",
    "sg:province":"Baden-W\u00fcrttemberg",
    "wof:name":"J\u00f6rg Und Martin Gauker",
    "wof:placetype":"venue"
},
  "geometry": {"coordinates":[9.045271,48.542412],"type":"Point"}
}