{
  "type": "Feature",
  "properties": {
    "iso:country":"DE",
    "sg:address":"Vater-Jahn-Str.",
    "sg:city":"Ermsleben",
    "sg:postcode":"06463",
    "sg:province":"Sachsen-Anhalt",
    "wof:name":"Abh Ackemann Bauges. Mbh",
    "wof:placetype":"venue"
},
  "geometry": {"coordinates":[11.329116,51.731998],"type":"Point"}
}