{
  "type": "Feature",
  "properties": {
    "iso:country":"DE",
    "sg:address":"Gro\u00dfe Bockenheimer Str. 37",
    "sg:city":"Frankfurt",
    "sg:phone":"+49 69/287528",
    "sg:postcode":"60313",
    "sg:province":"Hessen",
    "wof:name":"China-restaurant Jasmin Gmbh",
    "wof:placetype":"venue"
},
  "geometry": {"coordinates":[8.673997879,50.11460495],"type":"Point"}
}