{
  "type": "Feature",
  "properties": {
    "iso:country":"DE",
    "sg:address":"Leopoldstr. 14",
    "sg:city":"Daun",
    "sg:postcode":"54550",
    "sg:province":"Rheinland-Pfalz",
    "wof:name":"S-finanz-beratungs-center Gmbh",
    "wof:placetype":"venue"
},
  "geometry": {"coordinates":[6.8286399841,50.1986961365],"type":"Point"}
}