{
  "type": "Feature",
  "properties": {
    "iso:country":"DE",
    "sg:address":"Hauptstr. 57",
    "sg:city":"Frankenhain",
    "sg:postcode":"04643",
    "sg:province":"Sachsen",
    "wof:name":"Andreas Wiesenh\u00fcgel",
    "wof:placetype":"venue"
},
  "geometry": {"coordinates":[12.659026,51.081211],"type":"Point"}
}