{
  "type": "Feature",
  "properties": {
    "iso:country":"DE",
    "sg:address":"Blumenau 138",
    "sg:city":"Hamburg",
    "sg:phone":"+49 40/201144",
    "sg:postcode":"22089",
    "sg:province":"Hamburg",
    "wof:name":"Savitor Acrona Handelsgesellschaft Mbh",
    "wof:placetype":"venue"
},
  "geometry": {"coordinates":[10.0425815582,53.5697746277],"type":"Point"}
}