{
  "type": "Feature",
  "properties": {
    "iso:country":"DE",
    "sg:address":"Brandberg 25",
    "sg:city":"Schwanewede",
    "sg:phone":"+49 4209/1328",
    "sg:postcode":"28790",
    "sg:province":"Niedersachsen",
    "wof:name":"Alfred Siemer",
    "wof:placetype":"venue"
},
  "geometry": {"coordinates":[8.609854,53.280193],"type":"Point"}
}