{
  "type": "Feature",
  "properties": {
    "iso:country":"DE",
    "sg:address":"Bahnhofstr. 8",
    "sg:city":"Weidenberg",
    "sg:phone":"+49 9278",
    "sg:postcode":"95466",
    "sg:province":"Bayern",
    "wof:name":"Autohaus Kiessling",
    "wof:placetype":"venue"
},
  "geometry": {"coordinates":[11.7229146957,49.9422111511],"type":"Point"}
}