{
  "type": "Feature",
  "properties": {
    "iso:country":"DE",
    "sg:address":"Am Winkelst\u00fcck 21",
    "sg:city":"Schwerte",
    "sg:phone":"+49 2304/70725",
    "sg:postcode":"58239",
    "sg:province":"Nordrhein-Westfalen",
    "wof:name":"Ggs Stahlhandel Gmbh",
    "wof:placetype":"venue"
},
  "geometry": {"coordinates":[7.600132,51.429981],"type":"Point"}
}