{
  "type": "Feature",
  "properties": {
    "iso:country":"DE",
    "sg:address":"Kirchstr. 19",
    "sg:city":"Lohmar",
    "sg:phone":"+49 2246/5342",
    "sg:postcode":"53797",
    "sg:province":"Nordrhein-Westfalen",
    "wof:name":"Gemeindewasserwerk",
    "wof:placetype":"venue"
},
  "geometry": {"coordinates":[7.2071151733,50.840423584],"type":"Point"}
}