{
  "type": "Feature",
  "properties": {
    "iso:country":"DE",
    "sg:address":"Rheinstr. 7",
    "sg:city":"Friedrichshafen",
    "sg:phone":"+49 7541/57386",
    "sg:postcode":"88046",
    "sg:province":"Baden-W\u00fcrttemberg",
    "wof:name":"Kesba Gmbh",
    "wof:placetype":"venue"
},
  "geometry": {"coordinates":[9.4935503006,47.6708869934],"type":"Point"}
}