{
  "type": "Feature",
  "properties": {
    "iso:country":"DE",
    "sg:address":"Hornbergstr. 16",
    "sg:city":"Backnang",
    "sg:phone":"+49 7191/66146",
    "sg:postcode":"71522",
    "sg:province":"Baden-W\u00fcrttemberg",
    "wof:name":"Ulrich Klenk Architekt",
    "wof:placetype":"venue"
},
  "geometry": {"coordinates":[9.414833,48.949135],"type":"Point"}
}