{
  "type": "Feature",
  "properties": {
    "iso:country":"DE",
    "sg:address":"Benno-Schilde-Str. 6",
    "sg:city":"Bad Hersfeld",
    "sg:phone":"+49 6621/65877",
    "sg:postcode":"36251",
    "sg:province":"Hessen",
    "wof:name":"Willi Krantz Masseur",
    "wof:placetype":"venue"
},
  "geometry": {"coordinates":[9.70892,50.869221],"type":"Point"}
}