{
  "type": "Feature",
  "properties": {
    "iso:country":"DE",
    "sg:address":"Eichendorffstr. 5",
    "sg:city":"Wolfhagen",
    "sg:phone":"+49 5692/995292",
    "sg:postcode":"34466",
    "sg:province":"Hessen",
    "wof:name":"Mehl Immobilien Vermietung Und Vermittlungs Gmbh",
    "wof:placetype":"venue"
},
  "geometry": {"coordinates":[9.1789188385,51.3212547302],"type":"Point"}
}