{
  "type": "Feature",
  "properties": {
    "iso:country":"DE",
    "sg:address":"Erbprinzenstr. 17a",
    "sg:city":"Freiburg",
    "sg:postcode":"79098",
    "sg:province":"Baden-W\u00fcrttemberg",
    "wof:name":"Institut F\u00fcr Kriminologie Und Wirtschaftsrecht",
    "wof:placetype":"venue"
},
  "geometry": {"coordinates":[7.8447918892,47.9922943115],"type":"Point"}
}