{
  "type": "Feature",
  "properties": {
    "iso:country":"DE",
    "sg:address":"Gro\u00dfer Bogen 38",
    "sg:city":"Markkleeberg",
    "sg:phone":"+49 341/3585567",
    "sg:postcode":"04416",
    "sg:province":"Sachsen",
    "wof:name":"Siegfried Plum Gmbh",
    "wof:placetype":"venue"
},
  "geometry": {"coordinates":[12.36208,51.29076],"type":"Point"}
}