{
  "type": "Feature",
  "properties": {
    "iso:country":"DE",
    "sg:address":"Louis-Spohr-Str. 6",
    "sg:city":"Ahlen",
    "sg:phone":"+49 2382/3019",
    "sg:postcode":"59227",
    "sg:province":"Nordrhein-Westfalen",
    "wof:name":"Karl-josef Vau\u00df Architekt",
    "wof:placetype":"venue"
},
  "geometry": {"coordinates":[7.867429,51.767979],"type":"Point"}
}