{
  "type": "Feature",
  "properties": {
    "iso:country":"DE",
    "sg:address":"Hauptstr. 49",
    "sg:city":"St. Leon-Rot",
    "sg:phone":"+49 6227/59437",
    "sg:postcode":"68789",
    "sg:province":"Baden-W\u00fcrttemberg",
    "wof:name":"B. Herrmann",
    "wof:placetype":"venue"
},
  "geometry": {"coordinates":[8.6328382492,49.2625694275],"type":"Point"}
}