{
  "type": "Feature",
  "properties": {
    "iso:country":"DE",
    "sg:address":"Gro\u00dfbeerenstr. 124",
    "sg:city":"Potsdam",
    "sg:phone":"+49 331/7404404",
    "sg:postcode":"14482",
    "sg:province":"Brandenburg",
    "wof:name":"Schulze Haustechnik Gmbh",
    "wof:placetype":"venue"
},
  "geometry": {"coordinates":[13.10836,52.386192],"type":"Point"}
}