{
  "type": "Feature",
  "properties": {
    "iso:country":"DE",
    "sg:address":"Muldensteiner Str. 2",
    "sg:city":"Friedersdorf",
    "sg:phone":"+49 3493/55333",
    "sg:postcode":"06749",
    "sg:province":"Sachsen-Anhalt",
    "wof:name":"Bernd Richter",
    "wof:placetype":"venue"
},
  "geometry": {"coordinates":[12.32869,51.629887],"type":"Point"}
}