{
  "type": "Feature",
  "properties": {
    "iso:country":"DE",
    "sg:address":"Bismarckstr. 33",
    "sg:city":"Berlin",
    "sg:phone":"+49 30/3423234",
    "sg:postcode":"10625",
    "sg:province":"Berlin",
    "wof:name":"Gabriel Daher Anlageberater",
    "wof:placetype":"venue"
},
  "geometry": {"coordinates":[13.3095703125,52.5120124817],"type":"Point"}
}