{
  "type": "Feature",
  "properties": {
    "iso:country":"DE",
    "sg:address":"Saalfelder Str. 3",
    "sg:city":"Gera",
    "sg:phone":"+49 365/7113345",
    "sg:postcode":"07549",
    "sg:province":"Th\u00fcringen",
    "wof:name":"K.-g\u00fcnter Klinger",
    "wof:placetype":"venue"
},
  "geometry": {"coordinates":[12.06057,50.844578],"type":"Point"}
}