{
  "type": "Feature",
  "properties": {
    "iso:country":"DE",
    "sg:address":"Am Springintgut 2",
    "sg:city":"Lueneburg",
    "sg:phone":"+49 4131/380600",
    "sg:postcode":"21337",
    "sg:province":"Niedersachsen",
    "wof:name":"Soltau-therme",
    "wof:placetype":"venue"
},
  "geometry": {"coordinates":[10.4003219604,53.2511520386],"type":"Point"}
}