{
  "type": "Feature",
  "properties": {
    "iso:country":"DE",
    "sg:address":"Perelsplatz 10",
    "sg:city":"Berlin",
    "sg:phone":"+49 30/8516589",
    "sg:postcode":"12159",
    "sg:province":"Berlin",
    "wof:name":"Restaurant Medusa",
    "wof:placetype":"venue"
},
  "geometry": {"coordinates":[13.3331460953,52.4752464294],"type":"Point"}
}