{
  "type": "Feature",
  "properties": {
    "iso:country":"DE",
    "sg:address":"Hoopter Str. 250",
    "sg:city":"Winsen",
    "sg:phone":"+49 4171/3427",
    "sg:postcode":"21423",
    "sg:province":"Niedersachsen",
    "wof:name":"Baugesch\u00e4ft Ruschmeyer Inh. Gertrud Ruschmeyer E. K.",
    "wof:placetype":"venue"
},
  "geometry": {"coordinates":[10.188053,53.387413],"type":"Point"}
}