{
  "type": "Feature",
  "properties": {
    "iso:country":"DE",
    "sg:address":"Brandenburgische Str. 12",
    "sg:city":"Berlin",
    "sg:phone":"+49 30/8616157",
    "sg:postcode":"10713",
    "sg:province":"Berlin",
    "wof:name":"Karl-ludwig Simons",
    "wof:placetype":"venue"
},
  "geometry": {"coordinates":[13.315836,52.489395],"type":"Point"}
}