{
  "type": "Feature",
  "properties": {
    "iso:country":"DE",
    "sg:address":"Ernestinenstr. 1",
    "sg:city":"Essen",
    "sg:phone":"+49 201/212269",
    "sg:postcode":"45141",
    "sg:province":"Nordrhein-Westfalen",
    "wof:name":"Yilmaz Dogan",
    "wof:placetype":"venue"
},
  "geometry": {"coordinates":[7.0383419991,51.4757461548],"type":"Point"}
}