{
  "type": "Feature",
  "properties": {
    "iso:country":"DE",
    "sg:address":"K\u00f6lner Str. 43",
    "sg:city":"D\u00fcsseldorf",
    "sg:phone":"+49 211/357187",
    "sg:postcode":"40211",
    "sg:province":"Nordrhein-Westfalen",
    "wof:name":"Friedrich Weitze",
    "wof:placetype":"venue"
},
  "geometry": {"coordinates":[6.793843,51.226112],"type":"Point"}
}