{
  "type": "Feature",
  "properties": {
    "iso:country":"DE",
    "sg:address":"Gummersbacher Str. 15a",
    "sg:city":"Marienheide",
    "sg:phone":"+49 2264/7905",
    "sg:postcode":"51709",
    "sg:province":"Nordrhein-Westfalen",
    "wof:name":"Manfred Kruse",
    "wof:placetype":"venue"
},
  "geometry": {"coordinates":[7.5539441109,51.0755462646],"type":"Point"}
}