{
  "type": "Feature",
  "properties": {
    "iso:country":"DE",
    "sg:address":"Neubr\u00fcckenstr. 8-11",
    "sg:city":"M\u00fcnster",
    "sg:postcode":"48143",
    "sg:province":"Nordrhein-Westfalen",
    "wof:name":"M\u00fcnstersche Zeitung Verlag Verwaltungsgesellschaft Mbh",
    "wof:placetype":"venue"
},
  "geometry": {"coordinates":[7.6286349297,51.9650650024],"type":"Point"}
}