{
  "type": "Feature",
  "properties": {
    "iso:country":"DE",
    "sg:address":"Alicestr. 5",
    "sg:city":"Bad Nauheim",
    "sg:postcode":"61231",
    "sg:province":"Hessen",
    "wof:name":"Wilberger Hof Gastronomische Betriebs Gmbh",
    "wof:placetype":"venue"
},
  "geometry": {"coordinates":[8.7382202148,50.3646087646],"type":"Point"}
}