{
  "type": "Feature",
  "properties": {
    "iso:country":"DE",
    "sg:address":"Lerchenstr. 22",
    "sg:city":"Freiburg",
    "sg:phone":"+49 761/55011",
    "sg:postcode":"79104",
    "sg:province":"Baden-W\u00fcrttemberg",
    "wof:name":"Partner-immobilien",
    "wof:placetype":"venue"
},
  "geometry": {"coordinates":[7.8595747948,48.0087051392],"type":"Point"}
}