{
  "type": "Feature",
  "properties": {
    "iso:country":"DE",
    "sg:address":"Westerwaldstr.",
    "sg:city":"Vallendar",
    "sg:phone":"+49 261/65800",
    "sg:postcode":"56179",
    "sg:province":"Rheinland-Pfalz",
    "wof:name":"Stadthalle Vallendar",
    "wof:placetype":"venue"
},
  "geometry": {"coordinates":[7.6144800186,50.3978538513],"type":"Point"}
}