{
  "type": "Feature",
  "properties": {
    "iso:country":"DE",
    "sg:address":"Thorwaldsenanlage 9",
    "sg:city":"Wiesbaden",
    "sg:phone":"+49 611/520726",
    "sg:postcode":"65195",
    "sg:province":"Hessen",
    "wof:name":"Karla Gut Heilpraktikerin",
    "wof:placetype":"venue"
},
  "geometry": {"coordinates":[8.2251749039,50.0896911621],"type":"Point"}
}