{
  "type": "Feature",
  "properties": {
    "iso:country":"DE",
    "sg:address":"Doberluger Str. 45",
    "sg:city":"Uebigau",
    "sg:phone":"+49 35365/8422",
    "sg:postcode":"04938",
    "sg:province":"Brandenburg",
    "wof:name":"Max Hellstern Gmbh",
    "wof:placetype":"venue"
},
  "geometry": {"coordinates":[13.306067,51.597301],"type":"Point"}
}