{
  "type": "Feature",
  "properties": {
    "iso:country":"DE",
    "sg:address":"Hauptstr. 12",
    "sg:city":"Dresden",
    "sg:postcode":"01097",
    "sg:province":"Sachsen",
    "wof:name":"J\u00fcrgen Matecki",
    "wof:placetype":"venue"
},
  "geometry": {"coordinates":[13.7426071167,51.05884552],"type":"Point"}
}