{
  "type": "Feature",
  "properties": {
    "iso:country":"DE",
    "sg:address":"Kastanienallee 48",
    "sg:city":"D\u00fcsseldorf",
    "sg:phone":"+49 211/577244",
    "sg:postcode":"40543",
    "sg:province":"Nordrhein-Westfalen",
    "wof:name":"Sex Im Internet Ohne Kreditkarte",
    "wof:placetype":"venue"
},
  "geometry": {"coordinates":[6.846015,51.256134],"type":"Point"}
}