{
  "type": "Feature",
  "properties": {
    "iso:country":"DE",
    "sg:address":"Hangstr. 18",
    "sg:city":"V\u00f6lklingen",
    "sg:phone":"+49 6898/24393",
    "sg:postcode":"66333",
    "sg:province":"Saarland",
    "wof:name":"Anneliese Zorn",
    "wof:placetype":"venue"
},
  "geometry": {"coordinates":[6.821639061,49.2435646057],"type":"Point"}
}