{
  "type": "Feature",
  "properties": {
    "iso:country":"DE",
    "sg:address":"Steg\u00e4ckerstr. 8",
    "sg:city":"Riederich",
    "sg:phone":"+49 7123/934501",
    "sg:postcode":"72585",
    "sg:province":"Baden-W\u00fcrttemberg",
    "wof:name":"Hausverwaltung Bock Gmbh",
    "wof:placetype":"venue"
},
  "geometry": {"coordinates":[9.2640752792,48.5635490417],"type":"Point"}
}