{
  "type": "Feature",
  "properties": {
    "iso:country":"DE",
    "sg:address":"F\u00fcrstenforster Str. 14",
    "sg:city":"Burghaslach",
    "sg:phone":"+49 9552/391",
    "sg:postcode":"96152",
    "sg:province":"Bayern",
    "wof:name":"Ingrid Schl\u00f6singer",
    "wof:placetype":"venue"
},
  "geometry": {"coordinates":[10.6025876999,49.7340126038],"type":"Point"}
}