{
  "type": "Feature",
  "properties": {
    "iso:country":"DE",
    "sg:address":"Nauklerstr. 17",
    "sg:city":"T\u00fcbingen",
    "sg:phone":"+49 7071/52462",
    "sg:postcode":"72074",
    "sg:province":"Baden-W\u00fcrttemberg",
    "wof:name":"Hans Raster",
    "wof:placetype":"venue"
},
  "geometry": {"coordinates":[9.0610723495,48.5270195007],"type":"Point"}
}