{
  "type": "Feature",
  "properties": {
    "iso:country":"DE",
    "sg:address":"Herrengasse 8",
    "sg:city":"Waldstetten",
    "sg:phone":"+49 7162/21202",
    "sg:postcode":"73550",
    "sg:province":"Baden-W\u00fcrttemberg",
    "wof:name":"Franz Zeller Autolackiererei",
    "wof:placetype":"venue"
},
  "geometry": {"coordinates":[9.810108,48.729984],"type":"Point"}
}