{
  "type": "Feature",
  "properties": {
    "iso:country":"DE",
    "sg:address":"Tangersdorf 11b",
    "sg:city":"Lychen",
    "sg:phone":"+49 39888/4011",
    "sg:postcode":"17279",
    "sg:province":"Brandenburg",
    "wof:name":"Dr. Wolfgang Z\u00f6phel Steuerberater",
    "wof:placetype":"venue"
},
  "geometry": {"coordinates":[13.3267726898,53.1608276367],"type":"Point"}
}