{
  "type": "Feature",
  "properties": {
    "iso:country":"DE",
    "sg:city":"Seebad Heringsdorf",
    "sg:postcode":"17424",
    "sg:province":"Mecklenburg-Vorpommern",
    "wof:name":"Heringsdorfer Airport Service Gmbh",
    "wof:placetype":"venue"
},
  "geometry": {"coordinates":[14.153191,53.957695],"type":"Point"}
}