{
  "type": "Feature",
  "properties": {
    "iso:country":"DE",
    "sg:city":"Bad Neustadt",
    "sg:postcode":"97616",
    "sg:province":"Bayern",
    "wof:name":"Clinic-service Gmbh",
    "wof:placetype":"venue"
},
  "geometry": {"coordinates":[10.215092,50.320553],"type":"Point"}
}