{
  "type": "Feature",
  "properties": {
    "iso:country":"DE",
    "sg:address":"Im Hausteile 4",
    "sg:city":"Schramberg",
    "sg:phone":"+49 7422/53670",
    "sg:postcode":"78713",
    "sg:province":"Baden-W\u00fcrttemberg",
    "wof:name":"Eugen Schneider",
    "wof:placetype":"venue"
},
  "geometry": {"coordinates":[8.385613,48.22525],"type":"Point"}
}