{
  "type": "Feature",
  "properties": {
    "iso:country":"DE",
    "sg:address":"M\u00fchlenweg 9",
    "sg:city":"Immenhausen",
    "sg:phone":"+49 5673/7575",
    "sg:postcode":"34376",
    "sg:province":"Hessen",
    "wof:name":"G\u00fcnter Bachmann",
    "wof:placetype":"venue"
},
  "geometry": {"coordinates":[9.488715,51.429504],"type":"Point"}
}