{
  "type": "Feature",
  "properties": {
    "iso:country":"DE",
    "sg:address":"Fuchsstadter Str. 5",
    "sg:city":"Reichenberg",
    "sg:phone":"+49 9366/1545",
    "sg:postcode":"97234",
    "sg:province":"Bayern",
    "wof:name":"Hans Popp",
    "wof:placetype":"venue"
},
  "geometry": {"coordinates":[9.93412,49.693909],"type":"Point"}
}