{
  "type": "Feature",
  "properties": {
    "iso:country":"DE",
    "sg:address":"Waldweg 28",
    "sg:city":"Hamburg",
    "sg:phone":"+49 40/6017874",
    "sg:postcode":"22393",
    "sg:province":"Hamburg",
    "wof:name":"Volker Warnke Immobilienmakler",
    "wof:placetype":"venue"
},
  "geometry": {"coordinates":[10.1175289154,53.6544876099],"type":"Point"}
}