{
  "type": "Feature",
  "properties": {
    "iso:country":"DE",
    "sg:address":"Alemannstr. 11",
    "sg:city":"Magdeburg",
    "sg:phone":"+49 391/5612554",
    "sg:postcode":"39106",
    "sg:province":"Sachsen-Anhalt",
    "wof:name":"Vera Bartl",
    "wof:placetype":"venue"
},
  "geometry": {"coordinates":[11.6386423111,52.1455764771],"type":"Point"}
}