{
  "type": "Feature",
  "properties": {
    "iso:country":"DE",
    "sg:address":"Hafenstr.",
    "sg:city":"Salzgitter",
    "sg:postcode":"38239",
    "sg:province":"Niedersachsen",
    "wof:name":"Winschermann Transport Gmbh Seeschiffaht-u.",
    "wof:placetype":"venue"
},
  "geometry": {"coordinates":[10.417215,52.184902],"type":"Point"}
}