{
  "type": "Feature",
  "properties": {
    "iso:country":"DE",
    "sg:address":"Villastr. 3",
    "sg:city":"Regensburg",
    "sg:phone":"+49 941/791369",
    "sg:postcode":"93055",
    "sg:province":"Bayern",
    "wof:name":"P. G\u00f6tz & H. Blabl",
    "wof:placetype":"venue"
},
  "geometry": {"coordinates":[12.109534,49.018452],"type":"Point"}
}