{
  "type": "Feature",
  "properties": {
    "iso:country":"DE",
    "sg:address":"Marienplatz 49",
    "sg:city":"Ravensburg",
    "sg:phone":"+49 751/363300",
    "sg:postcode":"88212",
    "sg:province":"Baden-W\u00fcrttemberg",
    "wof:name":"Klaus Schoener Steuerberater",
    "wof:placetype":"venue"
},
  "geometry": {"coordinates":[9.6132564545,47.782661438],"type":"Point"}
}