{
  "type": "Feature",
  "properties": {
    "iso:country":"DE",
    "sg:address":"Wischenstr. 29",
    "sg:city":"Edewecht",
    "sg:phone":"+49 4486/408",
    "sg:postcode":"26188",
    "sg:province":"Niedersachsen",
    "wof:name":"Heinz Martens",
    "wof:placetype":"venue"
},
  "geometry": {"coordinates":[8.05243,53.098671],"type":"Point"}
}