{
  "type": "Feature",
  "properties": {
    "iso:country":"DE",
    "sg:address":"Am Ostenteich 2",
    "sg:city":"S\u00f6hlde",
    "sg:phone":"+49 5129/325",
    "sg:postcode":"31185",
    "sg:province":"Niedersachsen",
    "wof:name":"Fritz Beckmann",
    "wof:placetype":"venue"
},
  "geometry": {"coordinates":[10.204534,52.187702],"type":"Point"}
}