{
  "type": "Feature",
  "properties": {
    "iso:country":"DE",
    "sg:address":"Talstr. 37",
    "sg:city":"Bruchsal",
    "sg:phone":"+49 4972/5197540",
    "sg:postcode":"76646",
    "sg:province":"Baden-W\u00fcrttemberg",
    "wof:name":"Bruchsaler Farbenfabrik Gmbh & Co Kg",
    "wof:placetype":"venue"
},
  "geometry": {"coordinates":[8.58824,49.129288],"type":"Point"}
}