{
  "type": "Feature",
  "properties": {
    "iso:country":"DE",
    "sg:address":"Auf der Fahlhorst 5",
    "sg:city":"Wistedt",
    "sg:phone":"+49 4182/3066",
    "sg:postcode":"21255",
    "sg:province":"Niedersachsen",
    "wof:name":"Adolf Rosenbrock Stra\u00dfen- Und Tiefbau Gmbh",
    "wof:placetype":"venue"
},
  "geometry": {"coordinates":[9.6831274033,53.2692680359],"type":"Point"}
}