{
  "type": "Feature",
  "properties": {
    "iso:country":"DE",
    "sg:address":"Luitpoldstr. 64",
    "sg:city":"Neuburg",
    "sg:phone":"+49 8431/42424",
    "sg:postcode":"86633",
    "sg:province":"Bayern",
    "wof:name":"Cafe Castello",
    "wof:placetype":"venue"
},
  "geometry": {"coordinates":[11.182028,48.736652],"type":"Point"}
}