{
  "type": "Feature",
  "properties": {
    "iso:country":"DE",
    "sg:address":"Freunder Str. 2",
    "sg:city":"Aachen",
    "sg:phone":"+49 241/552777",
    "sg:postcode":"52080",
    "sg:province":"Nordrhein-Westfalen",
    "wof:name":"Burghof",
    "wof:placetype":"venue"
},
  "geometry": {"coordinates":[6.1684989929,50.777381897],"type":"Point"}
}