{
  "type": "Feature",
  "properties": {
    "iso:country":"DE",
    "sg:address":"Mitterfeldstr. 13",
    "sg:city":"Garmisch-Partenkirchen",
    "sg:phone":"+49 8821/57425",
    "sg:postcode":"82467",
    "sg:province":"Bayern",
    "wof:name":"Consedes Gmbh",
    "wof:placetype":"venue"
},
  "geometry": {"coordinates":[11.081495285,47.4875106812],"type":"Point"}
}