{
  "type": "Feature",
  "properties": {
    "iso:country":"DE",
    "sg:address":"St\u00fcrtzstr. 16",
    "sg:city":"D\u00fcren",
    "sg:phone":"+49 2421/15616",
    "sg:postcode":"52349",
    "sg:province":"Nordrhein-Westfalen",
    "wof:name":"I. J\u00fcnger-ehlers",
    "wof:placetype":"venue"
},
  "geometry": {"coordinates":[6.4837942123,50.7993812561],"type":"Point"}
}