{
  "type": "Feature",
  "properties": {
    "iso:country":"DE",
    "sg:address":"Windhofstr. 12",
    "sg:city":"Grasellenbach",
    "sg:phone":"+49 4962/076030",
    "sg:postcode":"64689",
    "sg:province":"Hessen",
    "wof:name":"Coronet-kunststoffwerk Gmbh",
    "wof:placetype":"venue"
},
  "geometry": {"coordinates":[8.8526830673,49.6098060608],"type":"Point"}
}