{
  "type": "Feature",
  "properties": {
    "iso:country":"DE",
    "sg:address":"Querstr. 2",
    "sg:city":"Quickborn",
    "sg:phone":"+49 4106/82706",
    "sg:postcode":"25451",
    "sg:province":"Schleswig-Holstein",
    "wof:name":"Thomas Deeken Architekt",
    "wof:placetype":"venue"
},
  "geometry": {"coordinates":[9.90519,53.730869],"type":"Point"}
}