{
  "type": "Feature",
  "properties": {
    "iso:country":"DE",
    "sg:address":"Bachtalstr. 214",
    "sg:city":"Schwalbach",
    "sg:phone":"+49 6834/55527",
    "sg:postcode":"66773",
    "sg:province":"Saarland",
    "wof:name":"Thomas Haas",
    "wof:placetype":"venue"
},
  "geometry": {"coordinates":[6.8431158066,49.2963218689],"type":"Point"}
}