{
  "type": "Feature",
  "properties": {
    "iso:country":"DE",
    "sg:address":"Ziegelweg 4",
    "sg:city":"Irsee",
    "sg:phone":"+49 8341/12030",
    "sg:postcode":"87660",
    "sg:province":"Bayern",
    "wof:name":"Martin Eckloff",
    "wof:placetype":"venue"
},
  "geometry": {"coordinates":[10.58086586,47.908000946],"type":"Point"}
}