{
  "type": "Feature",
  "properties": {
    "iso:country":"DE",
    "sg:address":"Oelerother Str. 40",
    "sg:city":"Ruppichteroth",
    "sg:phone":"+49 2295/2187",
    "sg:postcode":"53809",
    "sg:province":"Nordrhein-Westfalen",
    "wof:name":"Manfred Harscheid Gmbh",
    "wof:placetype":"venue"
},
  "geometry": {"coordinates":[7.497099,50.85265],"type":"Point"}
}