{
  "type": "Feature",
  "properties": {
    "iso:country":"DE",
    "sg:address":"M\u00f6rikestr. 11",
    "sg:city":"Kornwestheim",
    "sg:phone":"+49 7154/3838",
    "sg:postcode":"70806",
    "sg:province":"Baden-W\u00fcrttemberg",
    "wof:name":"Auto-m\u00fcller Gmbh",
    "wof:placetype":"venue"
},
  "geometry": {"coordinates":[9.1850156784,48.8610267639],"type":"Point"}
}