{
  "type": "Feature",
  "properties": {
    "iso:country":"DE",
    "sg:address":"Reichsstr. 102",
    "sg:city":"Berlin",
    "sg:phone":"+49 30/3042044",
    "sg:postcode":"14052",
    "sg:province":"Berlin",
    "wof:name":"Textilhaus Lehmann Inh. Juanita Ernst",
    "wof:placetype":"venue"
},
  "geometry": {"coordinates":[13.2684497833,52.5113945007],"type":"Point"}
}