{
  "type": "Feature",
  "properties": {
    "iso:country":"DE",
    "sg:address":"Im Dausemannstal 2",
    "sg:city":"Rockenhausen",
    "sg:phone":"+49 6361/7777",
    "sg:postcode":"67806",
    "sg:province":"Rheinland-Pfalz",
    "wof:name":"Albert J\u00e4ger",
    "wof:placetype":"venue"
},
  "geometry": {"coordinates":[7.811777,49.628181],"type":"Point"}
}