{
  "type": "Feature",
  "properties": {
    "iso:country":"DE",
    "sg:address":"Domagkstr. 1",
    "sg:city":"M\u00fcnchen",
    "sg:phone":"+49 89/358800",
    "sg:postcode":"80807",
    "sg:province":"Bayern",
    "wof:name":"Bosch",
    "wof:placetype":"venue"
},
  "geometry": {"coordinates":[11.5873308182,48.1845932007],"type":"Point"}
}