{
  "type": "Feature",
  "properties": {
    "iso:country":"DE",
    "sg:address":"Weimarische Str. 24",
    "sg:city":"Buttelstedt",
    "sg:phone":"+49 36451/60370",
    "sg:postcode":"99439",
    "sg:province":"Th\u00fcringen",
    "wof:name":"Herbert Kielmann",
    "wof:placetype":"venue"
},
  "geometry": {"coordinates":[11.341464,51.072639],"type":"Point"}
}