{
  "type": "Feature",
  "properties": {
    "iso:country":"DE",
    "sg:address":"Bahnhofstr. 18",
    "sg:city":"Eiterfeld",
    "sg:phone":"+49 6672/7986",
    "sg:postcode":"36132",
    "sg:province":"Hessen",
    "wof:name":"Futterkiste",
    "wof:placetype":"venue"
},
  "geometry": {"coordinates":[9.7991094589,50.7604408264],"type":"Point"}
}