{
  "type": "Feature",
  "properties": {
    "iso:country":"DE",
    "sg:address":"F\u00fcrstenfelder Str. 13",
    "sg:city":"M\u00fcnchen",
    "sg:phone":"+49 89/26949988",
    "sg:postcode":"80331",
    "sg:province":"Bayern",
    "wof:name":"Abc Telekom Telekommunikations",
    "wof:placetype":"venue"
},
  "geometry": {"coordinates":[11.572511673,48.1370887756],"type":"Point"}
}