{
  "type": "Feature",
  "properties": {
    "iso:country":"DE",
    "sg:address":"Kapellenbrink 1",
    "sg:city":"Seelze",
    "sg:phone":"+49 511/521180",
    "sg:postcode":"30926",
    "sg:province":"Niedersachsen",
    "wof:name":"Ev. Pfarramt St. Johannis",
    "wof:placetype":"venue"
},
  "geometry": {"coordinates":[9.6501903534,52.370098114],"type":"Point"}
}