{
  "type": "Feature",
  "properties": {
    "iso:country":"DE",
    "sg:address":"Am Kral 1",
    "sg:city":"Horn-Bad Meinberg",
    "sg:postcode":"32805",
    "sg:province":"Nordrhein-Westfalen",
    "wof:name":"Teutonenhof Externsteine Verwaltungs-gmbh",
    "wof:placetype":"venue"
},
  "geometry": {"coordinates":[8.903009,51.883183],"type":"Point"}
}