{
  "type": "Feature",
  "properties": {
    "iso:country":"DE",
    "sg:address":"Heinrich-Heine-Weg 16",
    "sg:city":"Pritzwalk",
    "sg:phone":"+49 3395/2317",
    "sg:postcode":"16928",
    "sg:province":"Brandenburg",
    "wof:name":"Produktionsgenossenschaften Bauhandwerk",
    "wof:placetype":"venue"
},
  "geometry": {"coordinates":[12.161418,53.149567],"type":"Point"}
}