{
  "type": "Feature",
  "properties": {
    "iso:country":"DE",
    "sg:address":"Ottostr. 4",
    "sg:city":"Aschersleben",
    "sg:phone":"+49 3473/806958",
    "sg:postcode":"06449",
    "sg:province":"Sachsen-Anhalt",
    "wof:name":"Hartmut K\u00fcmmels Gmbh",
    "wof:placetype":"venue"
},
  "geometry": {"coordinates":[11.4851198196,51.7699165344],"type":"Point"}
}