{
  "type": "Feature",
  "properties": {
    "iso:country":"DE",
    "sg:address":"Reitzensteinstr. 36",
    "sg:city":"Stuttgart",
    "sg:phone":"+49 711/2623771",
    "sg:postcode":"70190",
    "sg:province":"Baden-W\u00fcrttemberg",
    "wof:name":"Taverne Timbales",
    "wof:placetype":"venue"
},
  "geometry": {"coordinates":[9.1984930038,48.7925682068],"type":"Point"}
}