{
  "type": "Feature",
  "properties": {
    "iso:country":"DE",
    "sg:address":"Gottfried-Hagen-Str. 1",
    "sg:city":"K\u00f6ln",
    "sg:phone":"+49 221/832021",
    "sg:postcode":"51105",
    "sg:province":"Nordrhein-Westfalen",
    "wof:name":"Mathilde Menini Ohg",
    "wof:placetype":"venue"
},
  "geometry": {"coordinates":[7.004908,50.931217],"type":"Point"}
}