{
  "type": "Feature",
  "properties": {
    "iso:country":"DE",
    "sg:address":"B\u00fcttnerweg 4",
    "sg:city":"Leipzig",
    "sg:phone":"+49 341/4283326",
    "sg:postcode":"04249",
    "sg:province":"Sachsen",
    "wof:name":"G\u00dcnter Jungk",
    "wof:placetype":"venue"
},
  "geometry": {"coordinates":[12.294417,51.271885],"type":"Point"}
}