{
  "type": "Feature",
  "properties": {
    "iso:country":"DE",
    "sg:address":"Kreuzhalde 7",
    "sg:city":"Abtsgm\u00fcnd",
    "sg:phone":"+49 7366/919110",
    "sg:postcode":"73453",
    "sg:province":"Baden-W\u00fcrttemberg",
    "wof:name":"Pbt Press Bohrtechnik Gmbh",
    "wof:placetype":"venue"
},
  "geometry": {"coordinates":[9.999739,48.886913],"type":"Point"}
}