{
  "type": "Feature",
  "properties": {
    "iso:country":"DE",
    "sg:address":"Im Steinhof 21",
    "sg:city":"Helsa",
    "sg:phone":"+49 5605/2396",
    "sg:postcode":"34298",
    "sg:province":"Hessen",
    "wof:name":"F. Armbr\u00f6ster",
    "wof:placetype":"venue"
},
  "geometry": {"coordinates":[9.6847038269,51.2555999756],"type":"Point"}
}