{
  "type": "Feature",
  "properties": {
    "iso:country":"DE",
    "sg:address":"Blankenburger Str. 8",
    "sg:city":"Rudolstadt",
    "sg:postcode":"07407",
    "sg:province":"Th\u00fcringen",
    "wof:name":"Herger & Perschel Gmbh Pretty Fachbetrieb",
    "wof:placetype":"venue"
},
  "geometry": {"coordinates":[11.314196,50.686066],"type":"Point"}
}