{
  "type": "Feature",
  "properties": {
    "iso:country":"DE",
    "sg:address":"Gartenstr. 13",
    "sg:city":"Aschaffenburg",
    "sg:postcode":"63743",
    "sg:province":"Bayern",
    "wof:name":"Rauch Gmbh",
    "wof:placetype":"venue"
},
  "geometry": {"coordinates":[9.12761,49.937916],"type":"Point"}
}