{
  "type": "Feature",
  "properties": {
    "iso:country":"DE",
    "sg:address":"Hauptstr. 166",
    "sg:city":"Bellheim",
    "sg:phone":"+49 7272/2364",
    "sg:postcode":"76756",
    "sg:province":"Rheinland-Pfalz",
    "wof:name":"Maria Bertlich",
    "wof:placetype":"venue"
},
  "geometry": {"coordinates":[8.28734,49.190731],"type":"Point"}
}