{
  "type": "Feature",
  "properties": {
    "iso:country":"DE",
    "sg:address":"Donaustr. 12",
    "sg:city":"Hengersberg",
    "sg:phone":"+49 9901/1566",
    "sg:postcode":"94491",
    "sg:province":"Bayern",
    "wof:name":"Fahrradstudio",
    "wof:placetype":"venue"
},
  "geometry": {"coordinates":[13.047832,48.765976],"type":"Point"}
}