{
  "type": "Feature",
  "properties": {
    "iso:country":"DE",
    "sg:address":"Azaleenstr. 15",
    "sg:city":"Neuwied",
    "sg:phone":"+49 4926/3183960",
    "sg:postcode":"56566",
    "sg:province":"Rheinland-Pfalz",
    "wof:name":"Geo Ges F Elektronische Datenverarbeitung U Organisation",
    "wof:placetype":"venue"
},
  "geometry": {"coordinates":[7.4922552109,50.4691009521],"type":"Point"}
}