{
  "type": "Feature",
  "properties": {
    "iso:country":"DE",
    "sg:address":"Buchenweg 40",
    "sg:city":"Tirschenreuth",
    "sg:phone":"+49 9631/1660",
    "sg:postcode":"95643",
    "sg:province":"Bayern",
    "wof:name":"Karl Mehler",
    "wof:placetype":"venue"
},
  "geometry": {"coordinates":[12.3268404007,49.8858413696],"type":"Point"}
}