{
  "type": "Feature",
  "properties": {
    "iso:country":"DE",
    "sg:address":"Hauptstr. 40",
    "sg:city":"Rumbach",
    "sg:phone":"+49 6394/5553",
    "sg:postcode":"76891",
    "sg:province":"Rheinland-Pfalz",
    "wof:name":"E. Cornet",
    "wof:placetype":"venue"
},
  "geometry": {"coordinates":[7.787629,49.096016],"type":"Point"}
}