{
  "type": "Feature",
  "properties": {
    "iso:country":"DE",
    "sg:address":"Adlerstr. 15",
    "sg:city":"Geislingen",
    "sg:phone":"+49 7331/42370",
    "sg:postcode":"73312",
    "sg:province":"Baden-W\u00fcrttemberg",
    "wof:name":"Daten-service Geislingen Gmbh",
    "wof:placetype":"venue"
},
  "geometry": {"coordinates":[9.8440542221,48.6118927002],"type":"Point"}
}