{
  "type": "Feature",
  "properties": {
    "iso:country":"DE",
    "sg:address":"Alter Weg 7",
    "sg:city":"Pronsfeld",
    "sg:phone":"+49 6556/7517",
    "sg:postcode":"54597",
    "sg:province":"Rheinland-Pfalz",
    "wof:name":"Hermann Fuchs Frische-service Gmbh",
    "wof:placetype":"venue"
},
  "geometry": {"coordinates":[6.344103,50.161465],"type":"Point"}
}