{
  "type": "Feature",
  "properties": {
    "iso:country":"DE",
    "sg:address":"Hauptstr. 191",
    "sg:city":"Herne",
    "sg:phone":"+49 2325/73878",
    "sg:postcode":"44652",
    "sg:province":"Nordrhein-Westfalen",
    "wof:name":"S\u00fcd-apotheke",
    "wof:placetype":"venue"
},
  "geometry": {"coordinates":[7.16165,51.525406],"type":"Point"}
}