{
  "type": "Feature",
  "properties": {
    "iso:country":"DE",
    "sg:address":"Gewerbestr 8",
    "sg:city":"Fraureuth",
    "sg:phone":"+49 37600/720",
    "sg:postcode":"08427",
    "sg:province":"Sachsen",
    "wof:name":"M\u00fcller Baumontage Gmbh",
    "wof:placetype":"venue"
},
  "geometry": {"coordinates":[12.364591,50.683891],"type":"Point"}
}