{
  "type": "Feature",
  "properties": {
    "iso:country":"DE",
    "sg:address":"Hertingerstr. 190",
    "sg:city":"Unna",
    "sg:phone":"+49 2303/80772",
    "sg:postcode":"59427",
    "sg:province":"Nordrhein-Westfalen",
    "wof:name":"Heinrich Hilleringmann",
    "wof:placetype":"venue"
},
  "geometry": {"coordinates":[7.667252,51.512554],"type":"Point"}
}