{
  "type": "Feature",
  "properties": {
    "iso:country":"DE",
    "sg:address":"S\u00f6gestr. 34",
    "sg:city":"Bremen",
    "sg:phone":"+49 421/171413",
    "sg:postcode":"28195",
    "sg:province":"Bremen",
    "wof:name":"Bremer-schmuck-haus Walther",
    "wof:placetype":"venue"
},
  "geometry": {"coordinates":[8.807434,53.077686],"type":"Point"}
}