{
  "type": "Feature",
  "properties": {
    "iso:country":"DE",
    "sg:address":"Parkstr. 59",
    "sg:city":"Baesweiler",
    "sg:phone":"+49 2401/2507",
    "sg:postcode":"52499",
    "sg:province":"Nordrhein-Westfalen",
    "wof:name":"Dr. H. Johnen-karhoff Architekt",
    "wof:placetype":"venue"
},
  "geometry": {"coordinates":[6.188876,50.905003],"type":"Point"}
}