{
  "type": "Feature",
  "properties": {
    "iso:country":"DE",
    "sg:address":"Bl\u00fctengrund",
    "sg:city":"Kleinjena",
    "sg:phone":"+49 3445/701452",
    "sg:postcode":"06618",
    "sg:province":"Sachsen-Anhalt",
    "wof:name":"Brigitte K\u00fchnert",
    "wof:placetype":"venue"
},
  "geometry": {"coordinates":[11.8205881119,51.144203186],"type":"Point"}
}