{
  "type": "Feature",
  "properties": {
    "iso:country":"DE",
    "sg:address":"Ziolkowskistr. 3",
    "sg:city":"Leipzig",
    "sg:phone":"+49 341/6010955",
    "sg:postcode":"04357",
    "sg:province":"Sachsen",
    "wof:name":"Dr. Med. Ulrike Meyer",
    "wof:placetype":"venue"
},
  "geometry": {"coordinates":[12.41786,51.382267],"type":"Point"}
}