{
  "type": "Feature",
  "properties": {
    "iso:country":"DE",
    "sg:address":"Laugnastra\u00dfe 17-19",
    "sg:city":"Wertingen",
    "sg:phone":"+49 8272/2367",
    "sg:postcode":"86637",
    "sg:province":"Bayern",
    "wof:name":"Deisenhofer Landtechnik",
    "wof:placetype":"venue"
},
  "geometry": {"coordinates":[10.6840820312,48.5577011108],"type":"Point"}
}