{
  "type": "Feature",
  "properties": {
    "iso:country":"DE",
    "sg:address":"Herrnwaldstr. 1",
    "sg:city":"Bensheim",
    "sg:postcode":"64625",
    "sg:province":"Hessen",
    "wof:name":"Perlex Computer Kassen Und Zubeh\u00f6r Handels Gmbh",
    "wof:placetype":"venue"
},
  "geometry": {"coordinates":[8.6478462219,49.7098236084],"type":"Point"}
}