{
  "type": "Feature",
  "properties": {
    "iso:country":"DE",
    "sg:address":"Bielefelder Str. 1",
    "sg:city":"Melle",
    "sg:phone":"+49 5428/540",
    "sg:postcode":"49326",
    "sg:province":"Niedersachsen",
    "wof:name":"Aha Allgemeine Handels- Und Anlagenvermittlungs Gmbh",
    "wof:placetype":"venue"
},
  "geometry": {"coordinates":[8.3901395798,52.13463974],"type":"Point"}
}