{
  "type": "Feature",
  "properties": {
    "iso:country":"DE",
    "sg:address":"Bremer Str. 78-82",
    "sg:city":"Delmenhorst",
    "sg:phone":"+49 4221/91280",
    "sg:postcode":"27751",
    "sg:province":"Niedersachsen",
    "wof:name":"L\u00f6wen-apotheke",
    "wof:placetype":"venue"
},
  "geometry": {"coordinates":[8.646541,53.053089],"type":"Point"}
}