{
  "type": "Feature",
  "properties": {
    "iso:country":"DE",
    "sg:address":"St.-Josef-Str. 1",
    "sg:city":"B\u00fcrstadt",
    "sg:phone":"+49 6206/6187",
    "sg:postcode":"68642",
    "sg:province":"Hessen",
    "wof:name":"Katholisches Pfarramt St. Michael",
    "wof:placetype":"venue"
},
  "geometry": {"coordinates":[8.4441709518,49.6629142761],"type":"Point"}
}