{
  "type": "Feature",
  "properties": {
    "iso:country":"DE",
    "sg:address":"Kempener Str. 11-13",
    "sg:city":"T\u00f6nisvorst",
    "sg:phone":"+49 2156/776483",
    "sg:postcode":"47918",
    "sg:province":"Nordrhein-Westfalen",
    "wof:name":"Extra",
    "wof:placetype":"venue"
},
  "geometry": {"coordinates":[6.4291219711,51.3081512451],"type":"Point"}
}