{
  "type": "Feature",
  "properties": {
    "iso:country":"DE",
    "sg:address":"Marienweg 2a",
    "sg:city":"Neum\u00fcnster",
    "sg:phone":"+49 4321/71671",
    "sg:postcode":"24539",
    "sg:province":"Schleswig-Holstein",
    "wof:name":"Dr. G\u00fcnter Schulze-rehm Tierarzt",
    "wof:placetype":"venue"
},
  "geometry": {"coordinates":[10.0239582062,54.0477485657],"type":"Point"}
}