{
  "type": "Feature",
  "properties": {
    "iso:country":"DE",
    "sg:address":"Flurscheideweg 14",
    "sg:city":"Frankfurt",
    "sg:phone":"+49 69/342022",
    "sg:postcode":"65936",
    "sg:province":"Hessen",
    "wof:name":"Abeka Handels Gmbh",
    "wof:placetype":"venue"
},
  "geometry": {"coordinates":[8.5745620728,50.1249427795],"type":"Point"}
}