{
  "type": "Feature",
  "properties": {
    "iso:country":"DE",
    "sg:address":"Franzstr. 117",
    "sg:city":"Dessau",
    "sg:phone":"+49 340/2215252",
    "sg:postcode":"06842",
    "sg:province":"Sachsen-Anhalt",
    "wof:name":"Enke",
    "wof:placetype":"venue"
},
  "geometry": {"coordinates":[12.242666,51.828739],"type":"Point"}
}