{
  "type": "Feature",
  "properties": {
    "iso:country":"DE",
    "sg:address":"M\u00fchlener Str. 36-42",
    "sg:city":"Wiehl",
    "sg:phone":"+49 4922/62810",
    "sg:postcode":"51674",
    "sg:province":"Nordrhein-Westfalen",
    "wof:name":"Kampf Gmbh & Co",
    "wof:placetype":"venue"
},
  "geometry": {"coordinates":[7.513969,50.947277],"type":"Point"}
}