{
  "type": "Feature",
  "properties": {
    "iso:country":"DE",
    "sg:address":"Dorfstr. Kauern 25a",
    "sg:city":"Tollwitz",
    "sg:phone":"+49 3462/86320",
    "sg:postcode":"06231",
    "sg:province":"Sachsen-Anhalt",
    "wof:name":"Gardinen-mega Markt Gmbh",
    "wof:placetype":"venue"
},
  "geometry": {"coordinates":[12.090130806,51.2906265259],"type":"Point"}
}