{
  "type": "Feature",
  "properties": {
    "iso:country":"DE",
    "sg:address":"Bogenberg",
    "sg:city":"Bogen",
    "sg:phone":"+49 9422/5786",
    "sg:postcode":"94327",
    "sg:province":"Bayern",
    "wof:name":"Kreis- Und Heimatmuseum Auf Dem Bogenberg",
    "wof:placetype":"venue"
},
  "geometry": {"coordinates":[12.698635,48.902332],"type":"Point"}
}