{
  "type": "Feature",
  "properties": {
    "iso:country":"DE",
    "sg:address":"Siemensstra\u00dfe 7",
    "sg:city":"Triefenstein-Lengfurt",
    "sg:phone":"+49 9395/99950",
    "sg:postcode":"97855",
    "sg:province":"Bayern",
    "wof:name":"Fliesen & B\u00e4der",
    "wof:placetype":"venue"
},
  "geometry": {"coordinates":[9.5967521667,49.8198738098],"type":"Point"}
}