{
  "type": "Feature",
  "properties": {
    "iso:country":"DE",
    "sg:address":"Neukolbing 1",
    "sg:city":"Egling",
    "sg:phone":"+49 8176/997144",
    "sg:postcode":"82544",
    "sg:province":"Bayern",
    "wof:name":"Europlast Kunststoff- Verwertung Ag",
    "wof:placetype":"venue"
},
  "geometry": {"coordinates":[11.595817,47.923576],"type":"Point"}
}