{
  "type": "Feature",
  "properties": {
    "iso:country":"DE",
    "sg:address":"Leher Heerstr. 103 a",
    "sg:city":"Bremen",
    "sg:phone":"+49 421/231791",
    "sg:postcode":"28359",
    "sg:province":"Bremen",
    "wof:name":"Max Kossel Gmbh",
    "wof:placetype":"venue"
},
  "geometry": {"coordinates":[8.879974,53.101303],"type":"Point"}
}