{
  "type": "Feature",
  "properties": {
    "iso:country":"DE",
    "sg:address":"Wagnerweg 12",
    "sg:city":"Herdecke",
    "sg:phone":"+49 2330/2663",
    "sg:postcode":"58313",
    "sg:province":"Nordrhein-Westfalen",
    "wof:name":"Gundula Griech Steuerberaterin",
    "wof:placetype":"venue"
},
  "geometry": {"coordinates":[7.431620121,51.4085006714],"type":"Point"}
}