{
  "type": "Feature",
  "properties": {
    "iso:country":"DE",
    "sg:address":"Freiberger Str. 95",
    "sg:city":"Mohorn",
    "sg:phone":"+49 35209/20254",
    "sg:postcode":"01723",
    "sg:province":"Sachsen",
    "wof:name":"Wolfgang W\u00fcstner",
    "wof:placetype":"venue"
},
  "geometry": {"coordinates":[13.456218,50.999668],"type":"Point"}
}