{
  "type": "Feature",
  "properties": {
    "iso:country":"DE",
    "sg:address":"Landauer Str. 12",
    "sg:city":"Bad Bergzabern",
    "sg:phone":"+49 6343/1586",
    "sg:postcode":"76887",
    "sg:province":"Rheinland-Pfalz",
    "wof:name":"Philipp Schwan Gmbh",
    "wof:placetype":"venue"
},
  "geometry": {"coordinates":[8.005563,49.10379],"type":"Point"}
}