{
  "type": "Feature",
  "properties": {
    "iso:country":"DE",
    "sg:address":"Krefelder Str. 19",
    "sg:city":"Neuss",
    "sg:phone":"+49 2131/277531",
    "sg:postcode":"41460",
    "sg:province":"Nordrhein-Westfalen",
    "wof:name":"D\u00fczg\u00fcn",
    "wof:placetype":"venue"
},
  "geometry": {"coordinates":[6.6846861839,51.2023963928],"type":"Point"}
}