{
  "type": "Feature",
  "properties": {
    "iso:country":"DE",
    "sg:address":"Riedweg 2",
    "sg:city":"Frankenberg",
    "sg:phone":"+49 6451/4357",
    "sg:postcode":"35066",
    "sg:province":"Hessen",
    "wof:name":"Friedrich Finger",
    "wof:placetype":"venue"
},
  "geometry": {"coordinates":[8.752862,51.046959],"type":"Point"}
}