{
  "type": "Feature",
  "properties": {
    "iso:country":"DE",
    "sg:address":"Lohmannstr. 10",
    "sg:city":"K\u00f6then",
    "sg:phone":"+49 3496/557977",
    "sg:postcode":"06366",
    "sg:province":"Sachsen-Anhalt",
    "wof:name":"T. Lehmann",
    "wof:placetype":"venue"
},
  "geometry": {"coordinates":[11.9856367111,51.7462654114],"type":"Point"}
}