{
  "type": "Feature",
  "properties": {
    "iso:country":"DE",
    "sg:address":"Herzog-Arenberg-Str. 14 a",
    "sg:city":"Meppen",
    "sg:postcode":"49716",
    "sg:province":"Niedersachsen",
    "wof:name":"Luther-b\u00fccherei",
    "wof:placetype":"venue"
},
  "geometry": {"coordinates":[7.295259,52.696892],"type":"Point"}
}