{
  "type": "Feature",
  "properties": {
    "iso:country":"DE",
    "sg:address":"Pausaer Str. 14",
    "sg:city":"Zeulenroda",
    "sg:phone":"+49 36628/89703",
    "sg:postcode":"07937",
    "sg:province":"Th\u00fcringen",
    "wof:name":"Restaurant Deutsche Eiche",
    "wof:placetype":"venue"
},
  "geometry": {"coordinates":[11.9833469391,50.6450653076],"type":"Point"}
}