{
  "type": "Feature",
  "properties": {
    "iso:country":"DE",
    "sg:address":"Osterstr. 59",
    "sg:city":"Aerzen",
    "sg:phone":"+49 5154/7118",
    "sg:postcode":"31855",
    "sg:province":"Niedersachsen",
    "wof:name":"Meier Antiquit\u00e4ten",
    "wof:placetype":"venue"
},
  "geometry": {"coordinates":[9.261985,52.046627],"type":"Point"}
}