{
  "type": "Feature",
  "properties": {
    "iso:country":"DE",
    "sg:address":"Vor Den Eichen 21",
    "sg:city":"Elz",
    "sg:phone":"+49 4964/3198930",
    "sg:postcode":"65604",
    "sg:province":"Hessen",
    "wof:name":"Wema Gmbh",
    "wof:placetype":"venue"
},
  "geometry": {"coordinates":[8.016960144,50.4250984192],"type":"Point"}
}