{
  "type": "Feature",
  "properties": {
    "iso:country":"DE",
    "sg:address":"Kornweg 24",
    "sg:city":"Bindlach",
    "sg:phone":"+49 9208/57326",
    "sg:postcode":"95463",
    "sg:province":"Bayern",
    "wof:name":"Markus B\u00fcttner",
    "wof:placetype":"venue"
},
  "geometry": {"coordinates":[11.6196203232,49.9790077209],"type":"Point"}
}