{
  "type": "Feature",
  "properties": {
    "iso:country":"DE",
    "sg:address":"Etzwiesenstr. 25",
    "sg:city":"Rottenburg",
    "sg:phone":"+49 7457/1393",
    "sg:postcode":"72108",
    "sg:province":"Baden-W\u00fcrttemberg",
    "wof:name":"Ambacher & Sailer Gmbh",
    "wof:placetype":"venue"
},
  "geometry": {"coordinates":[8.8756628036,48.5283660889],"type":"Point"}
}