{
  "type": "Feature",
  "properties": {
    "iso:country":"DE",
    "sg:address":"K\u00f6nigstr 9",
    "sg:city":"B\u00fcren",
    "sg:phone":"+49 2951/6436",
    "sg:postcode":"33142",
    "sg:province":"Nordrhein-Westfalen",
    "wof:name":"Spar- & Darlehnskasse B\u00fcren & Stein",
    "wof:placetype":"venue"
},
  "geometry": {"coordinates":[8.560207,51.554485],"type":"Point"}
}