{
  "type": "Feature",
  "properties": {
    "iso:country":"DE",
    "sg:address":"M\u00fchldorfer Str. 30",
    "sg:city":"Forstinning",
    "sg:phone":"+49 8121/1247",
    "sg:postcode":"85661",
    "sg:province":"Bayern",
    "wof:name":"J. Eder Immobilienmakler",
    "wof:placetype":"venue"
},
  "geometry": {"coordinates":[11.9164571762,48.1699714661],"type":"Point"}
}