{
  "type": "Feature",
  "properties": {
    "iso:country":"DE",
    "sg:address":"Mittlere-Motsch-Str.",
    "sg:city":"Sonneberg",
    "sg:phone":"+49 3675/89730",
    "sg:postcode":"96515",
    "sg:province":"Th\u00fcringen",
    "wof:name":"Pro Tec Service Gmbh",
    "wof:placetype":"venue"
},
  "geometry": {"coordinates":[11.170904,50.345577],"type":"Point"}
}