{
  "type": "Feature",
  "properties": {
    "iso:country":"DE",
    "sg:address":"Plantage 15",
    "sg:city":"Berlin",
    "sg:phone":"+49 30/3323073",
    "sg:postcode":"13597",
    "sg:province":"Berlin",
    "wof:name":"Aluchrom-markisen Gmbh",
    "wof:placetype":"venue"
},
  "geometry": {"coordinates":[13.203748,52.531902],"type":"Point"}
}