{
  "type": "Feature",
  "properties": {
    "iso:country":"DE",
    "sg:address":"Hauptstr. 21",
    "sg:city":"Eppertshausen",
    "sg:phone":"+49 6071/630846",
    "sg:postcode":"64859",
    "sg:province":"Hessen",
    "wof:name":"Venor Gmbh Nach Polnischem Recht Zweignieder-",
    "wof:placetype":"venue"
},
  "geometry": {"coordinates":[8.847289,49.945107],"type":"Point"}
}