{
  "type": "Feature",
  "properties": {
    "iso:country":"DE",
    "sg:address":"No de Halloh",
    "sg:city":"Ottenb\u00fcttel",
    "sg:postcode":"25591",
    "sg:province":"Schleswig-Holstein",
    "wof:name":"Peter Hopp Gmbh",
    "wof:placetype":"venue"
},
  "geometry": {"coordinates":[9.509547,53.972515],"type":"Point"}
}