{
  "type": "Feature",
  "properties": {
    "iso:country":"DE",
    "sg:address":"Luitpoldstr. 12",
    "sg:city":"Waldsassen",
    "sg:phone":"+49 9632/1278",
    "sg:postcode":"95652",
    "sg:province":"Bayern",
    "wof:name":"Toni Totzauer Kg",
    "wof:placetype":"venue"
},
  "geometry": {"coordinates":[12.3063058853,50.0026702881],"type":"Point"}
}