{
  "type": "Feature",
  "properties": {
    "iso:country":"DE",
    "sg:address":"Heinrich-Imbusch-Str. 18",
    "sg:city":"Herne",
    "sg:phone":"+49 2325/988256",
    "sg:postcode":"44651",
    "sg:province":"Nordrhein-Westfalen",
    "wof:name":"Andreas Langner Gmbh",
    "wof:placetype":"venue"
},
  "geometry": {"coordinates":[7.141816,51.519882],"type":"Point"}
}