{
  "type": "Feature",
  "properties": {
    "iso:country":"DE",
    "sg:address":"Sulzbacher Str. 11",
    "sg:city":"Oberstenfeld",
    "sg:phone":"+49 7062/22241",
    "sg:postcode":"71720",
    "sg:province":"Baden-W\u00fcrttemberg",
    "wof:name":"Kay Sch\u00fc\u00dfler",
    "wof:placetype":"venue"
},
  "geometry": {"coordinates":[9.3233213425,49.0209197998],"type":"Point"}
}