{
  "type": "Feature",
  "properties": {
    "iso:country":"DE",
    "sg:address":"Hildesheimer Str. 314",
    "sg:city":"Laatzen",
    "sg:phone":"+49 5102/3874",
    "sg:postcode":"30880",
    "sg:province":"Niedersachsen",
    "wof:name":"Klaus W. Pacht Gmbh",
    "wof:placetype":"venue"
},
  "geometry": {"coordinates":[9.8109226227,52.2963294983],"type":"Point"}
}