{
  "type": "Feature",
  "properties": {
    "iso:country":"DE",
    "sg:address":"Am Leinewehr 2",
    "sg:city":"Hannover",
    "sg:phone":"+49 511/8489904",
    "sg:postcode":"30519",
    "sg:province":"Niedersachsen",
    "wof:name":"Mediaevo - Webdesign & Werbung",
    "wof:placetype":"venue"
},
  "geometry": {"coordinates":[9.7614059448,52.3330993652],"type":"Point"}
}