{
  "type": "Feature",
  "properties": {
    "iso:country":"DE",
    "sg:address":"Hubertusstr. 33",
    "sg:city":"Rosenheim",
    "sg:phone":"+49 8031/13197",
    "sg:postcode":"83022",
    "sg:province":"Bayern",
    "wof:name":"Praxis Buchheim Und Dr. Med. K\u00e4seberg",
    "wof:placetype":"venue"
},
  "geometry": {"coordinates":[12.1111392975,47.8589859009],"type":"Point"}
}