{
  "type": "Feature",
  "properties": {
    "iso:country":"DE",
    "sg:address":"Grootensweg 1",
    "sg:city":"Sonsbeck",
    "sg:phone":"+49 2838/91818",
    "sg:postcode":"47665",
    "sg:province":"Nordrhein-Westfalen",
    "wof:name":"Hubert Verholen",
    "wof:placetype":"venue"
},
  "geometry": {"coordinates":[6.3795828819,51.6008110046],"type":"Point"}
}