{
  "type": "Feature",
  "properties": {
    "iso:country":"DE",
    "sg:address":"Bahnhofstr. 48",
    "sg:city":"R\u00fcsselsheim",
    "sg:postcode":"65428",
    "sg:province":"Hessen",
    "wof:name":"Schwarzbauer Und Schwind",
    "wof:placetype":"venue"
},
  "geometry": {"coordinates":[8.4138212204,49.9921035767],"type":"Point"}
}