{
  "type": "Feature",
  "properties": {
    "iso:country":"DE",
    "sg:address":"Schwarzburger Str. 47",
    "sg:city":"Katzh\u00fctte",
    "sg:phone":"+49 36781/38313",
    "sg:postcode":"98746",
    "sg:province":"Th\u00fcringen",
    "wof:name":"W. Heinze",
    "wof:placetype":"venue"
},
  "geometry": {"coordinates":[11.03119,50.546295],"type":"Point"}
}