{
  "type": "Feature",
  "properties": {
    "iso:country":"DE",
    "sg:address":"Eichenweg 14",
    "sg:city":"Elmenhorst",
    "sg:phone":"+49 4504/279",
    "sg:postcode":"23869",
    "sg:province":"Schleswig-Holstein",
    "wof:name":"Heinze",
    "wof:placetype":"venue"
},
  "geometry": {"coordinates":[10.2667627335,53.7644424438],"type":"Point"}
}