{
  "type": "Feature",
  "properties": {
    "iso:country":"DE",
    "sg:address":"Speyerer Str. 2",
    "sg:city":"Hockenheim",
    "sg:phone":"+49 6205/15884",
    "sg:postcode":"68766",
    "sg:province":"Baden-W\u00fcrttemberg",
    "wof:name":"Becker",
    "wof:placetype":"venue"
},
  "geometry": {"coordinates":[8.5330905914,49.3378944397],"type":"Point"}
}