{
  "type": "Feature",
  "properties": {
    "iso:country":"DE",
    "sg:address":"Segeberger Stra\u00dfe 23",
    "sg:city":"Krems II",
    "sg:phone":"+49 4557/98202",
    "sg:postcode":"23827",
    "sg:province":"Schleswig-Holstein",
    "wof:name":"Tierpension Und Hundeschule Krems Ii",
    "wof:placetype":"venue"
},
  "geometry": {"coordinates":[10.341388,53.995064],"type":"Point"}
}