{
  "type": "Feature",
  "properties": {
    "iso:country":"DE",
    "sg:address":"Marienstr. 87",
    "sg:city":"Krefeld",
    "sg:phone":"+49 2151/302659",
    "sg:postcode":"47807",
    "sg:province":"Nordrhein-Westfalen",
    "wof:name":"J. Pesch",
    "wof:placetype":"venue"
},
  "geometry": {"coordinates":[6.5854377747,51.3044128418],"type":"Point"}
}