{
  "type": "Feature",
  "properties": {
    "iso:country":"DE",
    "sg:address":"Wilstedter Str. 31",
    "sg:city":"Henstedt-Ulzburg",
    "sg:phone":"+49 4193/78575",
    "sg:postcode":"24558",
    "sg:province":"Schleswig-Holstein",
    "wof:name":"Gerhard Latzke",
    "wof:placetype":"venue"
},
  "geometry": {"coordinates":[9.994921,53.753799],"type":"Point"}
}