{
  "type": "Feature",
  "properties": {
    "iso:country":"DE",
    "sg:address":"Mainzer Ring 64",
    "sg:city":"Offenbach",
    "sg:phone":"+49 69/861146",
    "sg:postcode":"63075",
    "sg:province":"Hessen",
    "wof:name":"F. Diehl",
    "wof:placetype":"venue"
},
  "geometry": {"coordinates":[8.789016,50.114498],"type":"Point"}
}