{
  "type": "Feature",
  "properties": {
    "iso:country":"DE",
    "sg:address":"Konstanzer Str. 57",
    "sg:city":"Berlin",
    "sg:phone":"+49 30/8818890",
    "sg:postcode":"10707",
    "sg:province":"Berlin",
    "wof:name":"Hans O. Bols Architekt",
    "wof:placetype":"venue"
},
  "geometry": {"coordinates":[13.311669,52.496796],"type":"Point"}
}