{
  "type": "Feature",
  "properties": {
    "iso:country":"DE",
    "sg:address":"Paul-Lincke-Ufer 34",
    "sg:city":"Berlin",
    "sg:phone":"+49 30/4469386",
    "sg:postcode":"10999",
    "sg:province":"Berlin",
    "wof:name":"Femto Messtechnik Gmbh",
    "wof:placetype":"venue"
},
  "geometry": {"coordinates":[13.424492836,52.4954414368],"type":"Point"}
}