{
  "type": "Feature",
  "properties": {
    "iso:country":"DE",
    "sg:address":"Nietzschestr. 34",
    "sg:city":"Mannheim",
    "sg:phone":"+49 621/415603",
    "sg:postcode":"68165",
    "sg:province":"Baden-W\u00fcrttemberg",
    "wof:name":"Gert K\u00fcnzler",
    "wof:placetype":"venue"
},
  "geometry": {"coordinates":[8.489891,49.479412],"type":"Point"}
}