{
  "type": "Feature",
  "properties": {
    "iso:country":"DE",
    "sg:address":"Calwer Str. 31",
    "sg:city":"Stuttgart",
    "sg:phone":"+49 711/2261632",
    "sg:postcode":"70173",
    "sg:province":"Baden-W\u00fcrttemberg",
    "wof:name":"Eiscafe",
    "wof:placetype":"venue"
},
  "geometry": {"coordinates":[9.173763,48.775669],"type":"Point"}
}