{
  "type": "Feature",
  "properties": {
    "iso:country":"DE",
    "sg:address":"Otto-Grotewohl-Str. 27",
    "sg:city":"Neuruppin",
    "sg:phone":"+49 3391/5430",
    "sg:postcode":"16816",
    "sg:province":"Brandenburg",
    "wof:name":"C. Traska",
    "wof:placetype":"venue"
},
  "geometry": {"coordinates":[12.78996,52.914497],"type":"Point"}
}