{
  "type": "Feature",
  "properties": {
    "iso:country":"DE",
    "sg:address":"Frohnhauser Str. 95",
    "sg:city":"Essen",
    "sg:phone":"+49 201/10269686",
    "sg:postcode":"45143",
    "sg:province":"Nordrhein-Westfalen",
    "wof:name":"N. Schilling",
    "wof:placetype":"venue"
},
  "geometry": {"coordinates":[6.988762,51.453117],"type":"Point"}
}