{
  "type": "Feature",
  "properties": {
    "iso:country":"DE",
    "sg:address":"Pahlkestr. 46 d",
    "sg:city":"Wuppertal",
    "sg:phone":"+49 202/712505",
    "sg:postcode":"42115",
    "sg:province":"Nordrhein-Westfalen",
    "wof:name":"Aqua Me\u00dftechnik Gmbh",
    "wof:placetype":"venue"
},
  "geometry": {"coordinates":[7.0923042297,51.260219574],"type":"Point"}
}