{
  "type": "Feature",
  "properties": {
    "iso:country":"DE",
    "sg:address":"Surenburgstr. 100",
    "sg:city":"Rheine",
    "sg:phone":"+49 5971/6746",
    "sg:postcode":"48429",
    "sg:province":"Nordrhein-Westfalen",
    "wof:name":"Richard Kohl",
    "wof:placetype":"venue"
},
  "geometry": {"coordinates":[7.462434,52.276997],"type":"Point"}
}