{
  "type": "Feature",
  "properties": {
    "iso:country":"DE",
    "sg:address":"Schwarzwaldstr. 17",
    "sg:city":"Kelkheim",
    "sg:phone":"+49 6195/62708",
    "sg:postcode":"65779",
    "sg:province":"Hessen",
    "wof:name":"Berthold Hillenbrand Steuerberater",
    "wof:placetype":"venue"
},
  "geometry": {"coordinates":[8.4314088821,50.1476325989],"type":"Point"}
}