{
  "type": "Feature",
  "properties": {
    "iso:country":"DE",
    "sg:address":"Priestershof 69",
    "sg:city":"Oberhausen",
    "sg:phone":"+49 208/840432",
    "sg:postcode":"46047",
    "sg:province":"Nordrhein-Westfalen",
    "wof:name":"M. Wawrzyniak",
    "wof:placetype":"venue"
},
  "geometry": {"coordinates":[6.8952980042,51.4704284668],"type":"Point"}
}