{
  "type": "Feature",
  "properties": {
    "iso:country":"DE",
    "sg:address":"Unnaer Str. 7",
    "sg:city":"Hamm",
    "sg:phone":"+49 2385/8017",
    "sg:postcode":"59069",
    "sg:province":"Nordrhein-Westfalen",
    "wof:name":"Paul Helmrich Chemische Reinigung Gmbh & Co. Kg",
    "wof:placetype":"venue"
},
  "geometry": {"coordinates":[7.8499,51.62941],"type":"Point"}
}