{
  "type": "Feature",
  "properties": {
    "iso:country":"DE",
    "sg:address":"Turmstr. 37",
    "sg:city":"L\u00f6rrach",
    "sg:phone":"+49 7621/43637",
    "sg:postcode":"79539",
    "sg:province":"Baden-W\u00fcrttemberg",
    "wof:name":"Eberhard Spaeth",
    "wof:placetype":"venue"
},
  "geometry": {"coordinates":[7.6633148193,47.6133728027],"type":"Point"}
}