{
  "type": "Feature",
  "properties": {
    "iso:country":"DE",
    "sg:address":"Wichnantstr. 19a",
    "sg:city":"M\u00fcnchen",
    "sg:phone":"+49 89/8141470",
    "sg:postcode":"81249",
    "sg:province":"Bayern",
    "wof:name":"J. Schrott Inh. M. Stossberger",
    "wof:placetype":"venue"
},
  "geometry": {"coordinates":[11.3968143463,48.1865997314],"type":"Point"}
}