{
  "type": "Feature",
  "properties": {
    "iso:country":"DE",
    "sg:address":"Coburger Str. 42",
    "sg:city":"Bad Rodach",
    "sg:phone":"+49 9564/4833",
    "sg:postcode":"96476",
    "sg:province":"Bayern",
    "wof:name":"Fina Tankstelle",
    "wof:placetype":"venue"
},
  "geometry": {"coordinates":[10.7838916779,50.3408584595],"type":"Point"}
}