{
  "type": "Feature",
  "properties": {
    "iso:country":"DE",
    "sg:address":"Marienstr. 1",
    "sg:city":"Hamm",
    "sg:phone":"+49 2381/161824",
    "sg:postcode":"59067",
    "sg:province":"Nordrhein-Westfalen",
    "wof:name":"Beratungsstelle F. Eltern Jugendliche Und Kinder",
    "wof:placetype":"venue"
},
  "geometry": {"coordinates":[7.802649,51.673901],"type":"Point"}
}