{
  "type": "Feature",
  "properties": {
    "iso:country":"DE",
    "sg:address":"Siemensstr. 8",
    "sg:city":"Oftersheim",
    "sg:phone":"+49 6202/52831",
    "sg:postcode":"68723",
    "sg:province":"Baden-W\u00fcrttemberg",
    "wof:name":"Harald Helfrich",
    "wof:placetype":"venue"
},
  "geometry": {"coordinates":[8.5814,49.37479],"type":"Point"}
}