{
  "type": "Feature",
  "properties": {
    "iso:country":"DE",
    "sg:address":"Hunteburger Str. 32",
    "sg:city":"Ostercappeln",
    "sg:phone":"+49 5476/393",
    "sg:postcode":"49179",
    "sg:province":"Niedersachsen",
    "wof:name":"August Schr\u00f6der",
    "wof:placetype":"venue"
},
  "geometry": {"coordinates":[8.22465,52.39687],"type":"Point"}
}