{
  "type": "Feature",
  "properties": {
    "iso:country":"DE",
    "sg:address":"Altwahnsdorf 48",
    "sg:city":"Radebeul",
    "sg:phone":"+49 351/8301731",
    "sg:postcode":"01445",
    "sg:province":"Sachsen",
    "wof:name":"Horst Sch\u00fctze",
    "wof:placetype":"venue"
},
  "geometry": {"coordinates":[13.669675,51.119141],"type":"Point"}
}