{
  "type": "Feature",
  "properties": {
    "iso:country":"DE",
    "sg:address":"Peter-Sengl-Str. 9",
    "sg:city":"Aindling",
    "sg:phone":"+49 8237/262",
    "sg:postcode":"86447",
    "sg:province":"Bayern",
    "wof:name":"F. Stevens",
    "wof:placetype":"venue"
},
  "geometry": {"coordinates":[10.95631,48.513325],"type":"Point"}
}