{
  "type": "Feature",
  "properties": {
    "iso:country":"DE",
    "sg:address":"Ruhrstr. 3",
    "sg:city":"Asperg",
    "sg:phone":"+49 7141/62972",
    "sg:postcode":"71679",
    "sg:province":"Baden-W\u00fcrttemberg",
    "wof:name":"J\u00e4kel Gmbh",
    "wof:placetype":"venue"
},
  "geometry": {"coordinates":[9.148972,48.899261],"type":"Point"}
}