{
  "type": "Feature",
  "properties": {
    "iso:country":"DE",
    "sg:address":"Dernauer Str. 25",
    "sg:city":"Grafschaft",
    "sg:phone":"+49 2641/36303",
    "sg:postcode":"53501",
    "sg:province":"Rheinland-Pfalz",
    "wof:name":"Erika Lellmann",
    "wof:placetype":"venue"
},
  "geometry": {"coordinates":[7.0357909203,50.5503692627],"type":"Point"}
}