{
  "type": "Feature",
  "properties": {
    "iso:country":"DE",
    "sg:address":"Elisabethenstr. 34",
    "sg:city":"Langen",
    "sg:phone":"+49 6103/25890",
    "sg:postcode":"63225",
    "sg:province":"Hessen",
    "wof:name":"Waldemar Kachel Rechtsanwalt",
    "wof:placetype":"venue"
},
  "geometry": {"coordinates":[8.6616411209,49.9950332642],"type":"Point"}
}