{
  "type": "Feature",
  "properties": {
    "iso:country":"DE",
    "sg:address":"Schwimmbadstr. 32",
    "sg:city":"Heuchelheim",
    "sg:phone":"+49 641/61844",
    "sg:postcode":"35452",
    "sg:province":"Hessen",
    "wof:name":"Bruno Mandler",
    "wof:placetype":"venue"
},
  "geometry": {"coordinates":[8.618514061,50.582195282],"type":"Point"}
}