{
  "type": "Feature",
  "properties": {
    "iso:country":"DE",
    "sg:address":"Am Eichelberg",
    "sg:city":"Heimbach",
    "sg:phone":"+49 2446/3324",
    "sg:postcode":"52396",
    "sg:province":"Nordrhein-Westfalen",
    "wof:name":"K. H. Kleinschmidt Ingenieur",
    "wof:placetype":"venue"
},
  "geometry": {"coordinates":[6.4741849899,50.6362838745],"type":"Point"}
}