{
  "type": "Feature",
  "properties": {
    "iso:country":"DE",
    "sg:address":"Auwel 1 j",
    "sg:city":"Straelen",
    "sg:phone":"+49 2834/91860",
    "sg:postcode":"47638",
    "sg:province":"Nordrhein-Westfalen",
    "wof:name":"H. H. Servaes",
    "wof:placetype":"venue"
},
  "geometry": {"coordinates":[6.26747,51.447037],"type":"Point"}
}