{
  "type": "Feature",
  "properties": {
    "iso:country":"DE",
    "sg:address":"Brahmsstr. 5",
    "sg:city":"Essen",
    "sg:phone":"+49 201/229170",
    "sg:postcode":"45128",
    "sg:province":"Nordrhein-Westfalen",
    "wof:name":"S. Becker",
    "wof:placetype":"venue"
},
  "geometry": {"coordinates":[7.019466,51.442204],"type":"Point"}
}