{
  "type": "Feature",
  "properties": {
    "iso:country":"DE",
    "sg:address":"Norberstr. 21",
    "sg:city":"Koeln",
    "sg:phone":"+49 221/123460",
    "sg:postcode":"50670",
    "sg:province":"Nordrhein-Westfalen",
    "wof:name":"Benedict International Language And Business School -cologne",
    "wof:placetype":"venue"
},
  "geometry": {"coordinates":[6.944868,50.942177],"type":"Point"}
}