{
  "type": "Feature",
  "properties": {
    "iso:country":"DE",
    "sg:address":"Stra\u00dfe 77 4",
    "sg:city":"Berlin",
    "sg:phone":"+49 30/4742771",
    "sg:postcode":"13127",
    "sg:province":"Berlin",
    "wof:name":"J\u00fcrgen Sonnenberg",
    "wof:placetype":"venue"
},
  "geometry": {"coordinates":[13.442625,52.610493],"type":"Point"}
}