{
  "type": "Feature",
  "properties": {
    "iso:country":"DE",
    "sg:address":"Schmalsteder Weg 28",
    "sg:city":"Br\u00fcgge",
    "sg:phone":"+49 4322/9750",
    "sg:postcode":"24582",
    "sg:province":"Schleswig-Holstein",
    "wof:name":"Ernst Sander",
    "wof:placetype":"venue"
},
  "geometry": {"coordinates":[10.061885,54.177914],"type":"Point"}
}