{
  "type": "Feature",
  "properties": {
    "iso:country":"DE",
    "sg:address":"In Neust\u00fcckern 5",
    "sg:city":"Bodman-Ludwigshafen",
    "sg:phone":"+49 7773/5264",
    "sg:postcode":"78351",
    "sg:province":"Baden-W\u00fcrttemberg",
    "wof:name":"Fritz Winner Bootsbau U. Bootsmotoren-einb.",
    "wof:placetype":"venue"
},
  "geometry": {"coordinates":[9.029183,47.805199],"type":"Point"}
}