{
  "type": "Feature",
  "properties": {
    "iso:country":"DE",
    "sg:address":"Goethestr. 17",
    "sg:city":"Schornsheim",
    "sg:phone":"+49 6732/7364",
    "sg:postcode":"55288",
    "sg:province":"Rheinland-Pfalz",
    "wof:name":"Anja Karau",
    "wof:placetype":"venue"
},
  "geometry": {"coordinates":[8.1677923203,49.8462791443],"type":"Point"}
}