{
  "type": "Feature",
  "properties": {
    "iso:country":"DE",
    "sg:address":"Lilienstr. 24",
    "sg:city":"Neuss",
    "sg:phone":"+49 2131/21374",
    "sg:postcode":"41466",
    "sg:province":"Nordrhein-Westfalen",
    "wof:name":"H. Garenfeld",
    "wof:placetype":"venue"
},
  "geometry": {"coordinates":[6.68322,51.170925],"type":"Point"}
}