{
  "type": "Feature",
  "properties": {
    "iso:country":"DE",
    "sg:address":"Kirchweg 8 b",
    "sg:city":"Bad W\u00fcnnenberg",
    "sg:phone":"+49 2957/348",
    "sg:postcode":"33181",
    "sg:province":"Nordrhein-Westfalen",
    "wof:name":"St. Vitus Apotheke",
    "wof:placetype":"venue"
},
  "geometry": {"coordinates":[8.725857,51.567314],"type":"Point"}
}