{
  "type": "Feature",
  "properties": {
    "iso:country":"DE",
    "sg:address":"Postwiesenstrasse 5 A",
    "sg:city":"STUTTGART",
    "sg:phone":"+49 711/1346614",
    "sg:postcode":"70327",
    "sg:province":"Baden-W\u00fcrttemberg",
    "wof:name":"Cds-verlag",
    "wof:placetype":"venue"
},
  "geometry": {"coordinates":[9.252006,48.777233],"type":"Point"}
}