{
  "type": "Feature",
  "properties": {
    "iso:country":"DE",
    "sg:address":"G\u00fcterstr. 20",
    "sg:city":"Appenweier",
    "sg:phone":"+49 7805/3484",
    "sg:postcode":"77767",
    "sg:province":"Baden-W\u00fcrttemberg",
    "wof:name":"Herbert Burgert",
    "wof:placetype":"venue"
},
  "geometry": {"coordinates":[7.9756407738,48.552570343],"type":"Point"}
}