{
  "type": "Feature",
  "properties": {
    "iso:country":"DE",
    "sg:address":"Pr\u00f6schstr. 3",
    "sg:city":"Schwarzenbek",
    "sg:phone":"+49 4151/82041",
    "sg:postcode":"21493",
    "sg:province":"Schleswig-Holstein",
    "wof:name":"Dr. Med. Hans Woydt",
    "wof:placetype":"venue"
},
  "geometry": {"coordinates":[10.4806632996,53.5036811829],"type":"Point"}
}