{
  "type": "Feature",
  "properties": {
    "iso:country":"DE",
    "sg:address":"Wertachstr. 9",
    "sg:city":"M\u00fchldorf",
    "sg:phone":"+49 8631/7710",
    "sg:postcode":"84453",
    "sg:province":"Bayern",
    "wof:name":"Eva K\u00f6nigsbauer",
    "wof:placetype":"venue"
},
  "geometry": {"coordinates":[12.5316419601,48.2361755371],"type":"Point"}
}