{
  "type": "Feature",
  "properties": {
    "iso:country":"DE",
    "sg:address":"Kirchstr. 35",
    "sg:city":"Bad Segeberg",
    "sg:phone":"+49 4551/2737",
    "sg:postcode":"23795",
    "sg:province":"Schleswig-Holstein",
    "wof:name":"Bernhard Br\u00e4uninger Drogerie",
    "wof:placetype":"venue"
},
  "geometry": {"coordinates":[10.308829,53.9366],"type":"Point"}
}