{
  "type": "Feature",
  "properties": {
    "iso:country":"DE",
    "sg:address":"B\u00f6ckerstr. 13",
    "sg:city":"Hannover",
    "sg:phone":"+49 511/6490043",
    "sg:postcode":"30659",
    "sg:province":"Niedersachsen",
    "wof:name":"Kuhrke & Wisniewski Malerfachbetrieb Gmbh",
    "wof:placetype":"venue"
},
  "geometry": {"coordinates":[9.801984,52.418194],"type":"Point"}
}