{
  "type": "Feature",
  "properties": {
    "iso:country":"DE",
    "sg:address":"Sch\u00f6neberger Str. 30",
    "sg:city":"Pinneberg",
    "sg:phone":"+49 4101/72430",
    "sg:postcode":"25421",
    "sg:province":"Schleswig-Holstein",
    "wof:name":"Acs Pneu Handels Gmbh",
    "wof:placetype":"venue"
},
  "geometry": {"coordinates":[9.7873697281,53.6707191467],"type":"Point"}
}