{
  "type": "Feature",
  "properties": {
    "iso:country":"DE",
    "sg:address":"Brunnh\u00fcgel 8",
    "sg:city":"Neustadt",
    "sg:phone":"+49 9568/2375",
    "sg:postcode":"96465",
    "sg:province":"Bayern",
    "wof:name":"R. B\u00f6hm",
    "wof:placetype":"venue"
},
  "geometry": {"coordinates":[11.0965366364,50.3220291138],"type":"Point"}
}