{
  "type": "Feature",
  "properties": {
    "iso:country":"DE",
    "sg:address":"Markwiesenstr. 37",
    "sg:city":"Reutlingen",
    "sg:phone":"+49 7121/52063",
    "sg:postcode":"72770",
    "sg:province":"Baden-W\u00fcrttemberg",
    "wof:name":"Blumengro\u00dfmarkt Reutlingen",
    "wof:placetype":"venue"
},
  "geometry": {"coordinates":[9.14972,48.495049],"type":"Point"}
}