{
  "type": "Feature",
  "properties": {
    "iso:country":"DE",
    "sg:address":"Am Waltersb\u00fchl 6",
    "sg:city":"Wangen",
    "sg:phone":"+49 7522/21800",
    "sg:postcode":"88239",
    "sg:province":"Baden-W\u00fcrttemberg",
    "wof:name":"Spielhalle Joker",
    "wof:placetype":"venue"
},
  "geometry": {"coordinates":[9.8256731033,47.6977844238],"type":"Point"}
}