{
  "type": "Feature",
  "properties": {
    "iso:country":"DE",
    "sg:address":"Welkaer Str. 4",
    "sg:city":"Bautzen",
    "sg:phone":"+49 3591/275657",
    "sg:postcode":"02625",
    "sg:province":"Sachsen",
    "wof:name":"Stm Stahlmontagen Gmbh",
    "wof:placetype":"venue"
},
  "geometry": {"coordinates":[14.4182481766,51.1889610291],"type":"Point"}
}