{
  "type": "Feature",
  "properties": {
    "iso:country":"DE",
    "sg:address":"Am Ostkamp 25",
    "sg:city":"Wiefelstede",
    "sg:postcode":"26215",
    "sg:province":"Niedersachsen",
    "wof:name":"Zander Gmbh",
    "wof:placetype":"venue"
},
  "geometry": {"coordinates":[8.1694507599,53.1854171753],"type":"Point"}
}