{
  "type": "Feature",
  "properties": {
    "iso:country":"DE",
    "sg:address":"Waldstr. 33",
    "sg:city":"Wachenheim",
    "sg:phone":"+49 6322/988600",
    "sg:postcode":"67157",
    "sg:province":"Rheinland-Pfalz",
    "wof:name":"Persodata Service-gesellschaft F\u00fcr Abrechnungs- Und Kontie-",
    "wof:placetype":"venue"
},
  "geometry": {"coordinates":[8.176035,49.439053],"type":"Point"}
}