{
  "type": "Feature",
  "properties": {
    "iso:country":"DE",
    "sg:address":"Semperstr. 16",
    "sg:city":"Hamburg",
    "sg:phone":"+49 40/27877777",
    "sg:postcode":"22303",
    "sg:province":"Hamburg",
    "wof:name":"Zimmer Frei Hamburg Jens-christian Moos",
    "wof:placetype":"venue"
},
  "geometry": {"coordinates":[10.0128736496,53.5846214294],"type":"Point"}
}