{
  "type": "Feature",
  "properties": {
    "iso:country":"DE",
    "sg:address":"Talstr. 9b",
    "sg:city":"Lauenstein",
    "sg:phone":"+49 35054/25582",
    "sg:postcode":"01778",
    "sg:province":"Sachsen",
    "wof:name":"M\u00fcglitztal",
    "wof:placetype":"venue"
},
  "geometry": {"coordinates":[-71.362877,42.36121],"type":"Point"}
}