{
  "type": "Feature",
  "properties": {
    "iso:country":"DE",
    "sg:address":"Turmstr. 22",
    "sg:city":"Wetzlar",
    "sg:phone":"+49 6441/445386",
    "sg:postcode":"35578",
    "sg:province":"Hessen",
    "wof:name":"Verein F\u00fcr Evangelische Diakonie Wetzlar",
    "wof:placetype":"venue"
},
  "geometry": {"coordinates":[8.5049219131,50.5529823303],"type":"Point"}
}