{
  "type": "Feature",
  "properties": {
    "iso:country":"DE",
    "sg:address":"Heidbraake 6",
    "sg:city":"Neustadt",
    "sg:phone":"+49 5072/349",
    "sg:postcode":"31535",
    "sg:province":"Niedersachsen",
    "wof:name":"K. Hake",
    "wof:placetype":"venue"
},
  "geometry": {"coordinates":[9.589252,52.580513],"type":"Point"}
}