{
  "type": "Feature",
  "properties": {
    "iso:country":"DE",
    "sg:address":"Berkenberg 17",
    "sg:city":"Essen",
    "sg:phone":"+49 201/215461",
    "sg:postcode":"45309",
    "sg:province":"Nordrhein-Westfalen",
    "wof:name":"Wolfgang Fengler Architekt",
    "wof:placetype":"venue"
},
  "geometry": {"coordinates":[7.064313,51.472412],"type":"Point"}
}