{
  "type": "Feature",
  "properties": {
    "iso:country":"DE",
    "sg:address":"Hattinger Str. 758",
    "sg:city":"Bochum",
    "sg:phone":"+49 234/412922",
    "sg:postcode":"44879",
    "sg:province":"Nordrhein-Westfalen",
    "wof:name":"Deutscher Superarkt Handels Gmbh",
    "wof:placetype":"venue"
},
  "geometry": {"coordinates":[7.1669788361,51.4302177429],"type":"Point"}
}