{
  "type": "Feature",
  "properties": {
    "iso:country":"DE",
    "sg:address":"Ottendinger Str. 16",
    "sg:city":"Mengkofen",
    "sg:phone":"+49 8774/701",
    "sg:postcode":"84152",
    "sg:province":"Bayern",
    "wof:name":"A. Braun Gmbh",
    "wof:placetype":"venue"
},
  "geometry": {"coordinates":[12.360538,48.691738],"type":"Point"}
}