{
  "type": "Feature",
  "properties": {
    "iso:country":"DE",
    "sg:address":"Weidenallee 37",
    "sg:city":"Hamburg",
    "sg:phone":"+49 40/4302401",
    "sg:postcode":"20357",
    "sg:province":"Hamburg",
    "wof:name":"Eckart Schacht Architekt",
    "wof:placetype":"venue"
},
  "geometry": {"coordinates":[9.964482,53.567375],"type":"Point"}
}