{
  "type": "Feature",
  "properties": {
    "iso:country":"DE",
    "sg:address":"Sch\u00e4ferkamp 2",
    "sg:city":"Wolfsburg",
    "sg:phone":"+49 5361/71687",
    "sg:postcode":"38444",
    "sg:province":"Niedersachsen",
    "wof:name":"Werner Drechsler",
    "wof:placetype":"venue"
},
  "geometry": {"coordinates":[10.744581,52.390991],"type":"Point"}
}