{
  "type": "Feature",
  "properties": {
    "iso:country":"DE",
    "sg:address":"Wallstr. 49",
    "sg:city":"Remscheid",
    "sg:phone":"+49 2191/668123",
    "sg:postcode":"42897",
    "sg:province":"Nordrhein-Westfalen",
    "wof:name":"Daniel Sch\u00fcrmann Kg",
    "wof:placetype":"venue"
},
  "geometry": {"coordinates":[7.259877,51.192226],"type":"Point"}
}