{
  "type": "Feature",
  "properties": {
    "iso:country":"DE",
    "sg:address":"Heerstr. 2",
    "sg:city":"Algermissen",
    "sg:phone":"+49 5126/1821",
    "sg:postcode":"31191",
    "sg:province":"Niedersachsen",
    "wof:name":"Friedrischak Raumausstattung Gmbh",
    "wof:placetype":"venue"
},
  "geometry": {"coordinates":[9.965767,52.25301],"type":"Point"}
}