{
  "type": "Feature",
  "properties": {
    "iso:country":"DE",
    "sg:address":"Gewerberg. S\u00fcd 1",
    "sg:city":"Bretnig-Hauswalde",
    "sg:phone":"+49 4935/9558390",
    "sg:postcode":"01900",
    "sg:province":"Sachsen",
    "wof:name":"Casco Schutzhelme Gmbh",
    "wof:placetype":"venue"
},
  "geometry": {"coordinates":[14.05285,51.15955],"type":"Point"}
}