{
  "type": "Feature",
  "properties": {
    "iso:country":"DE",
    "sg:address":"Hexenweg 10",
    "sg:city":"Coesfeld",
    "sg:phone":"+49 2541/82878",
    "sg:postcode":"48653",
    "sg:province":"Nordrhein-Westfalen",
    "wof:name":"Norbert Hensel Architekt",
    "wof:placetype":"venue"
},
  "geometry": {"coordinates":[7.180897,51.946201],"type":"Point"}
}