{
  "type": "Feature",
  "properties": {
    "iso:country":"DE",
    "sg:address":"Bahnhofstr. 44",
    "sg:city":"Appenweier",
    "sg:phone":"+49 7805/96760",
    "sg:postcode":"77767",
    "sg:province":"Baden-W\u00fcrttemberg",
    "wof:name":"Jakob Baumann Gmbh & Co.",
    "wof:placetype":"venue"
},
  "geometry": {"coordinates":[7.9742898941,48.5406608582],"type":"Point"}
}