{
  "type": "Feature",
  "properties": {
    "iso:country":"DE",
    "sg:address":"Bolzstr. 4",
    "sg:city":"Stuttgart",
    "sg:phone":"+49 711/228535",
    "sg:postcode":"70173",
    "sg:province":"Baden-W\u00fcrttemberg",
    "wof:name":"Impulse Informations- Technologie Gmbh",
    "wof:placetype":"venue"
},
  "geometry": {"coordinates":[9.179041,48.779736],"type":"Point"}
}