{
  "type": "Feature",
  "properties": {
    "iso:country":"DE",
    "sg:address":"Milchstr. 6",
    "sg:city":"Jever",
    "sg:phone":"+49 4461/5791",
    "sg:postcode":"26441",
    "sg:province":"Niedersachsen",
    "wof:name":"Altenwohnungen",
    "wof:placetype":"venue"
},
  "geometry": {"coordinates":[7.890175,53.569126],"type":"Point"}
}