{
  "type": "Feature",
  "properties": {
    "iso:country":"DE",
    "sg:address":"Rurstr. 9",
    "sg:city":"Erkelenz",
    "sg:phone":"+49 2164/4260",
    "sg:postcode":"41812",
    "sg:province":"Nordrhein-Westfalen",
    "wof:name":"Heinz Goebels",
    "wof:placetype":"venue"
},
  "geometry": {"coordinates":[6.435839,51.051262],"type":"Point"}
}