{
  "type": "Feature",
  "properties": {
    "iso:country":"DE",
    "sg:address":"Hahner Str. 34a",
    "sg:city":"Aachen",
    "sg:phone":"+49 2408/5799",
    "sg:postcode":"52076",
    "sg:province":"Nordrhein-Westfalen",
    "wof:name":"Spronck & Busscher Gmbh",
    "wof:placetype":"venue"
},
  "geometry": {"coordinates":[6.1934199333,50.7097511292],"type":"Point"}
}