{
  "type": "Feature",
  "properties": {
    "iso:country":"DE",
    "sg:address":"Hauptstr. 71",
    "sg:city":"Dunzweiler",
    "sg:phone":"+49 6373/893010",
    "sg:postcode":"66916",
    "sg:province":"Rheinland-Pfalz",
    "wof:name":"Harald Ruffing",
    "wof:placetype":"venue"
},
  "geometry": {"coordinates":[7.3058729172,49.4168624878],"type":"Point"}
}