{
  "type": "Feature",
  "properties": {
    "iso:country":"DE",
    "sg:address":"Oberer Markt 11",
    "sg:city":"Arnstorf",
    "sg:phone":"+49 8723/1575",
    "sg:postcode":"94424",
    "sg:province":"Bayern",
    "wof:name":"Restaurant Etna",
    "wof:placetype":"venue"
},
  "geometry": {"coordinates":[12.8165588379,48.5595588684],"type":"Point"}
}