{
  "type": "Feature",
  "properties": {
    "iso:country":"DE",
    "sg:address":"Hauptstr. 3",
    "sg:city":"Bischoffen",
    "sg:phone":"+49 6444/922710",
    "sg:postcode":"35649",
    "sg:province":"Hessen",
    "wof:name":"Gastst\u00e4tte El Dorado",
    "wof:placetype":"venue"
},
  "geometry": {"coordinates":[8.4775152206,50.703289032],"type":"Point"}
}