{
  "type": "Feature",
  "properties": {
    "iso:country":"DE",
    "sg:address":"Kirchplatz 1",
    "sg:city":"Mayen",
    "sg:phone":"+49 2651/900267",
    "sg:postcode":"56727",
    "sg:province":"Rheinland-Pfalz",
    "wof:name":"Thomas Eulgem",
    "wof:placetype":"venue"
},
  "geometry": {"coordinates":[7.1962208748,50.3478507996],"type":"Point"}
}