{
  "type": "Feature",
  "properties": {
    "iso:country":"DE",
    "sg:address":"Grindelallee 141",
    "sg:city":"Hamburg",
    "sg:phone":"+49 40/41355792",
    "sg:postcode":"20146",
    "sg:province":"Hamburg",
    "wof:name":"Christiane Lange Rechtsanw\u00e4ltin",
    "wof:placetype":"venue"
},
  "geometry": {"coordinates":[9.9787635803,53.5700836182],"type":"Point"}
}