{
  "type": "Feature",
  "properties": {
    "iso:country":"DE",
    "sg:address":"Humboldtstr. 9",
    "sg:city":"Mettmann",
    "sg:phone":"+49 2104/53262",
    "sg:postcode":"40822",
    "sg:province":"Nordrhein-Westfalen",
    "wof:name":"H. Anker",
    "wof:placetype":"venue"
},
  "geometry": {"coordinates":[6.941062,51.267536],"type":"Point"}
}