{
  "type": "Feature",
  "properties": {
    "iso:country":"DE",
    "sg:address":"Siemensring 102a",
    "sg:city":"Willich",
    "sg:phone":"+49 2154/88460",
    "sg:postcode":"47877",
    "sg:province":"Nordrhein-Westfalen",
    "wof:name":"H + H-druck Gmbh",
    "wof:placetype":"venue"
},
  "geometry": {"coordinates":[6.5132517815,51.265838623],"type":"Point"}
}