{
  "type": "Feature",
  "properties": {
    "iso:country":"DE",
    "sg:address":"Milkeler Str. 17",
    "sg:city":"Dresden",
    "sg:phone":"+49 351/2686770",
    "sg:postcode":"01324",
    "sg:province":"Sachsen",
    "wof:name":"Dr. Michael Ziege",
    "wof:placetype":"venue"
},
  "geometry": {"coordinates":[13.8464794159,51.0639076233],"type":"Point"}
}