{
  "type": "Feature",
  "properties": {
    "iso:country":"DE",
    "sg:address":"Schwarzaer Str. 3",
    "sg:city":"Christes",
    "sg:phone":"+49 36844/41130",
    "sg:postcode":"98547",
    "sg:province":"Th\u00fcringen",
    "wof:name":"Kulturgastst\u00e4tte",
    "wof:placetype":"venue"
},
  "geometry": {"coordinates":[10.4800243378,50.6607246399],"type":"Point"}
}