{
  "type": "Feature",
  "properties": {
    "iso:country":"DE",
    "sg:address":"Weideweg 3",
    "sg:city":"Crailsheim",
    "sg:phone":"+49 7951/7184",
    "sg:postcode":"74564",
    "sg:province":"Baden-W\u00fcrttemberg",
    "wof:name":"Horst Kaufmann",
    "wof:placetype":"venue"
},
  "geometry": {"coordinates":[10.1093244553,49.1175918579],"type":"Point"}
}