{
  "type": "Feature",
  "properties": {
    "iso:country":"DE",
    "sg:address":"Westendstr. 125",
    "sg:city":"M\u00fcnchen",
    "sg:phone":"+49 89/65114087",
    "sg:postcode":"80339",
    "sg:province":"Bayern",
    "wof:name":"Bkb Bautr\u00e4ger Und Verwaltungs Gmbh",
    "wof:placetype":"venue"
},
  "geometry": {"coordinates":[11.5331172943,48.1377410889],"type":"Point"}
}