{
  "type": "Feature",
  "properties": {
    "iso:country":"DE",
    "sg:address":"Am Bahnhof",
    "sg:city":"Neustadt",
    "sg:phone":"+49 5032/1258",
    "sg:postcode":"31535",
    "sg:province":"Niedersachsen",
    "wof:name":"Franz Kaspar",
    "wof:placetype":"venue"
},
  "geometry": {"coordinates":[9.456265,52.503777],"type":"Point"}
}