{
  "type": "Feature",
  "properties": {
    "iso:country":"DE",
    "sg:address":"Siedlerstr. 3",
    "sg:city":"Massenhausen",
    "sg:phone":"+49 8165/8281",
    "sg:postcode":"85376",
    "sg:province":"Bayern",
    "wof:name":"Kahlert Malereibetrieb Gmbh",
    "wof:placetype":"venue"
},
  "geometry": {"coordinates":[11.636868,48.346542],"type":"Point"}
}