{
  "type": "Feature",
  "properties": {
    "iso:country":"DE",
    "sg:address":"In der Freiheit 24",
    "sg:city":"Solingen",
    "sg:phone":"+49 212/592786",
    "sg:postcode":"42653",
    "sg:province":"Nordrhein-Westfalen",
    "wof:name":"El Patio",
    "wof:placetype":"venue"
},
  "geometry": {"coordinates":[7.0716061592,51.2072906494],"type":"Point"}
}