{
  "type": "Feature",
  "properties": {
    "iso:country":"DE",
    "sg:address":"Gautinger Str. 19",
    "sg:city":"Krailling",
    "sg:phone":"+49 89/34029737",
    "sg:postcode":"82152",
    "sg:province":"Bayern",
    "wof:name":"Atk Kellermann",
    "wof:placetype":"venue"
},
  "geometry": {"coordinates":[11.417303,48.09761],"type":"Point"}
}