{
  "type": "Feature",
  "properties": {
    "iso:country":"DE",
    "sg:address":"Birenbacher Str. 2",
    "sg:city":"B\u00f6rtlingen",
    "sg:phone":"+49 7161/52820",
    "sg:postcode":"73104",
    "sg:province":"Baden-W\u00fcrttemberg",
    "wof:name":"Zur Rose",
    "wof:placetype":"venue"
},
  "geometry": {"coordinates":[9.6469211578,48.749382019],"type":"Point"}
}