{
  "type": "Feature",
  "properties": {
    "iso:country":"DE",
    "sg:address":"Flinsberger Str. 6",
    "sg:city":"Wachstedt",
    "sg:postcode":"37359",
    "sg:province":"Th\u00fcringen",
    "wof:name":"Solarplan Gmbh",
    "wof:placetype":"venue"
},
  "geometry": {"coordinates":[10.2802143097,51.2750396729],"type":"Point"}
}