{"geometry":{"type":"Point","coordinates":[9.398500,48.876202]},"type":"Feature","id":102560811,"bbox":[9.398500,48.876202,9.398500,48.876202],"properties":{"sg:province":"Baden-W\u00fcrttemberg","geom:longitude":9.398500,"wof:breaches":[],"sg:href":"http://api.simplegeo.com/1.0/features/SG_7kPNAevNjRkh4YKHVpDNln_48.876202_9.398500@1306268793.json","sg:owner":"simplegeo","sg:postcode":"71364","geom:latitude":48.876202,"sg:classifiers":[],"sg:address":"Marktstr. 24::","sg:phone":"+49 4971/956910","wof:hierarchy":[{"locality_id":101828561,"venue_id":102560811,"country_id":85633111,"region_id":85682567,"county_id":102063379}],"geom:area":0.000000,"sg:city":"Winnenden","wof:lastmodified":1438093372,"iso:country":"DE","wof:geomhash":"3a7921e80cfec39149af2b1033a85b9f","wof:name":"Volksbank Winnenden Eingetragenegenossenschaft Eg","wof:belongsto":[101828561,85633111,85682567,102063379],"src:geom":"simplegeo","wof:placetype":"venue","wof:supersedes":[],"wof:id":102560811,"wof:superseded_by":[],"wof:concordances":{"sg:id":"SG_7kPNAevNjRkh4YKHVpDNln_48.876202_9.398500@1306268793"},"wof:parent_id":101828561}}