{
  "type": "Feature",
  "properties": {
    "iso:country":"DE",
    "sg:address":"Bahnhofstr. 80",
    "sg:city":"Cottbus",
    "sg:phone":"+49 355/31116",
    "sg:postcode":"03046",
    "sg:province":"Brandenburg",
    "wof:name":"Die Einrichter Privat- Und Objekt-",
    "wof:placetype":"venue"
},
  "geometry": {"coordinates":[14.3272676468,51.7610588074],"type":"Point"}
}