{
  "type": "Feature",
  "properties": {
    "iso:country":"DE",
    "sg:address":"Porschestr. 8",
    "sg:city":"Marl",
    "sg:phone":"+49 2365/508575",
    "sg:postcode":"45770",
    "sg:province":"Nordrhein-Westfalen",
    "wof:name":"Trendbauhaus Gmbh",
    "wof:placetype":"venue"
},
  "geometry": {"coordinates":[7.1633200645,51.6695556641],"type":"Point"}
}