{
  "type": "Feature",
  "properties": {
    "iso:country":"DE",
    "sg:address":"Nahestr. 18",
    "sg:city":"Hagen",
    "sg:phone":"+49 2331/81412",
    "sg:postcode":"58097",
    "sg:province":"Nordrhein-Westfalen",
    "wof:name":"Ludgera Scheele",
    "wof:placetype":"venue"
},
  "geometry": {"coordinates":[7.472801,51.369652],"type":"Point"}
}