{
  "type": "Feature",
  "properties": {
    "iso:country":"DE",
    "sg:address":"An den Eichen 6",
    "sg:city":"Baiersdorf",
    "sg:phone":"+49 9133/4278",
    "sg:postcode":"91083",
    "sg:province":"Bayern",
    "wof:name":"Dr. Reinhard Glimm Rechtsanwalt",
    "wof:placetype":"venue"
},
  "geometry": {"coordinates":[11.0422716141,49.6446647644],"type":"Point"}
}