{
  "type": "Feature",
  "properties": {
    "iso:country":"DE",
    "sg:address":"Wasserburger Landstr. 178",
    "sg:city":"M\u00fcnchen",
    "sg:phone":"+49 89/4393033",
    "sg:postcode":"81827",
    "sg:province":"Bayern",
    "wof:name":"Karl Bogner U. Erich Hartinger",
    "wof:placetype":"venue"
},
  "geometry": {"coordinates":[11.6936674118,48.1159744263],"type":"Point"}
}