{
  "type": "Feature",
  "properties": {
    "iso:country":"DE",
    "sg:address":"Neue Gr\u00f6ningerstr. 10",
    "sg:city":"Hamburg",
    "sg:phone":"+49 40/337217",
    "sg:postcode":"20457",
    "sg:province":"Hamburg",
    "wof:name":"Wilhelm Fr. Sch\u00fctt",
    "wof:placetype":"venue"
},
  "geometry": {"coordinates":[9.9950838089,53.546421051],"type":"Point"}
}