{
  "type": "Feature",
  "properties": {
    "iso:country":"DE",
    "sg:address":"Unteralleestr. 2",
    "sg:city":"Braubach",
    "sg:phone":"+49 2627/1999",
    "sg:postcode":"56338",
    "sg:province":"Rheinland-Pfalz",
    "wof:name":"Brunnensch\u00e4nke",
    "wof:placetype":"venue"
},
  "geometry": {"coordinates":[7.6462202072,50.273853302],"type":"Point"}
}