{
  "type": "Feature",
  "properties": {
    "iso:country":"DE",
    "sg:address":"In der Dreesbach 24",
    "sg:city":"Hellenthal",
    "sg:postcode":"53940",
    "sg:province":"Nordrhein-Westfalen",
    "wof:name":"Altes Landhaus - Hotel Restaurant Gmbh",
    "wof:placetype":"venue"
},
  "geometry": {"coordinates":[6.4378848076,50.4788017273],"type":"Point"}
}