{
  "type": "Feature",
  "properties": {
    "iso:country":"DE",
    "sg:address":"Im Siek 3",
    "sg:city":"Katlenburg",
    "sg:phone":"+49 4955/56348",
    "sg:postcode":"37191",
    "sg:province":"Niedersachsen",
    "wof:name":"Volksbank Rhumetal Eg",
    "wof:placetype":"venue"
},
  "geometry": {"coordinates":[10.09646,51.633228],"type":"Point"}
}