{
  "type": "Feature",
  "properties": {
    "iso:country":"DE",
    "sg:address":"Pettenhof 4",
    "sg:city":"Schmidm\u00fchlen",
    "sg:phone":"+49 9474/751",
    "sg:postcode":"92287",
    "sg:province":"Bayern",
    "wof:name":"Jakob Lautenschlager",
    "wof:placetype":"venue"
},
  "geometry": {"coordinates":[11.937978,49.223263],"type":"Point"}
}