{
  "type": "Feature",
  "properties": {
    "iso:country":"DE",
    "sg:address":"Neckargasse 5",
    "sg:city":"Benningen",
    "sg:phone":"+49 7144/97290",
    "sg:postcode":"71726",
    "sg:province":"Baden-W\u00fcrttemberg",
    "wof:name":"Friedrich Essig",
    "wof:placetype":"venue"
},
  "geometry": {"coordinates":[9.243267,48.947929],"type":"Point"}
}