{
  "type": "Feature",
  "properties": {
    "iso:country":"DE",
    "sg:address":"Walchnerstr. 16",
    "sg:city":"Radolfzell",
    "sg:phone":"+49 7732/971550",
    "sg:postcode":"78315",
    "sg:province":"Baden-W\u00fcrttemberg",
    "wof:name":"Hanno Kilian Heilpraktiker",
    "wof:placetype":"venue"
},
  "geometry": {"coordinates":[8.966340065,47.7399902344],"type":"Point"}
}