{
  "type": "Feature",
  "properties": {
    "iso:country":"DE",
    "sg:address":"Adolf-Staperfeld-Str. 35a",
    "sg:city":"Osnabr\u00fcck",
    "sg:phone":"+49 541/596360",
    "sg:postcode":"49082",
    "sg:province":"Niedersachsen",
    "wof:name":"Brigitte Jaenisch-r\u00f6mmelt Finanzberaterin",
    "wof:placetype":"venue"
},
  "geometry": {"coordinates":[8.0275144577,52.2432327271],"type":"Point"}
}