{
  "type": "Feature",
  "properties": {
    "iso:country":"DE",
    "sg:address":"Waldweg 27",
    "sg:city":"H\u00fcnxe",
    "sg:phone":"+49 2064/32115",
    "sg:postcode":"46569",
    "sg:province":"Nordrhein-Westfalen",
    "wof:name":"0049 Last Minute Reisen And More .",
    "wof:placetype":"venue"
},
  "geometry": {"coordinates":[6.73932,51.601109],"type":"Point"}
}