{
  "type": "Feature",
  "properties": {
    "iso:country":"DE",
    "sg:address":"Auf der M\u00fchlwiese 17",
    "sg:city":"Bad \u00dcberkingen",
    "sg:phone":"+49 7334",
    "sg:postcode":"73337",
    "sg:province":"Baden-W\u00fcrttemberg",
    "wof:name":"Willkommen Auf Der Geislinger H\u00fctte",
    "wof:placetype":"venue"
},
  "geometry": {"coordinates":[9.761068,48.606396],"type":"Point"}
}