{
  "type": "Feature",
  "properties": {
    "iso:country":"DE",
    "sg:address":"Oberlinweg 7",
    "sg:city":"Hemer",
    "sg:phone":"+49 2372/12301",
    "sg:postcode":"58675",
    "sg:province":"Nordrhein-Westfalen",
    "wof:name":"Gerhard H\u00f6rstemeier",
    "wof:placetype":"venue"
},
  "geometry": {"coordinates":[7.762025,51.40377],"type":"Point"}
}