{
  "type": "Feature",
  "properties": {
    "iso:country":"DE",
    "sg:address":"Steinbrinkstr. 147",
    "sg:city":"Oberhausen",
    "sg:phone":"+49 208/668288",
    "sg:postcode":"46145",
    "sg:province":"Nordrhein-Westfalen",
    "wof:name":"Restaurant Haus Neifer",
    "wof:placetype":"venue"
},
  "geometry": {"coordinates":[6.8507099152,51.5115737915],"type":"Point"}
}