{
  "type": "Feature",
  "properties": {
    "iso:country":"DE",
    "sg:address":"Kaynaer Str. 2",
    "sg:city":"Gro\u00dfkorbetha",
    "sg:phone":"+49 34446/90688",
    "sg:postcode":"06688",
    "sg:province":"Sachsen-Anhalt",
    "wof:name":"Gtm Geb\u00e4udetechnik Mitteldeutschland Gmbh",
    "wof:placetype":"venue"
},
  "geometry": {"coordinates":[12.028039,51.260754],"type":"Point"}
}