{
  "type": "Feature",
  "properties": {
    "iso:country":"DE",
    "sg:address":"Hasel\u00fcnner Str. 17",
    "sg:city":"Meppen",
    "sg:phone":"+49 5931/93910",
    "sg:postcode":"49716",
    "sg:province":"Niedersachsen",
    "wof:name":"Arenberg-nordkirchen Gmbh",
    "wof:placetype":"venue"
},
  "geometry": {"coordinates":[7.2992758751,52.6981658936],"type":"Point"}
}