{
  "type": "Feature",
  "properties": {
    "iso:country":"DE",
    "sg:address":"M\u00fchlenstr. 41",
    "sg:city":"Friesoythe",
    "sg:phone":"+49 4493/1634",
    "sg:postcode":"26169",
    "sg:province":"Niedersachsen",
    "wof:name":"Bauunternehmen Wilfried Breyer Gmbh",
    "wof:placetype":"venue"
},
  "geometry": {"coordinates":[7.86071,53.019421],"type":"Point"}
}