{
  "type": "Feature",
  "properties": {
    "iso:country":"DE",
    "sg:address":"Bismarckstr. 24",
    "sg:city":"Saarbr\u00fccken",
    "sg:phone":"+49 681/9697150",
    "sg:postcode":"66111",
    "sg:province":"Saarland",
    "wof:name":"Schwindt Assekuranz-immobilien",
    "wof:placetype":"venue"
},
  "geometry": {"coordinates":[7.0010228157,49.2304229736],"type":"Point"}
}