{
  "type": "Feature",
  "properties": {
    "iso:country":"DE",
    "sg:address":"Bismarckstr. 11",
    "sg:city":"B\u00fcnde",
    "sg:phone":"+49 5223/2343",
    "sg:postcode":"32257",
    "sg:province":"Nordrhein-Westfalen",
    "wof:name":"Gerold Langer Ingenieur",
    "wof:placetype":"venue"
},
  "geometry": {"coordinates":[8.5848016739,52.2000045776],"type":"Point"}
}