{
  "type": "Feature",
  "properties": {
    "iso:country":"DE",
    "sg:address":"In der Werre 2 B",
    "sg:city":"Stuttgart",
    "sg:phone":"+49 711/4791051",
    "sg:postcode":"70619",
    "sg:province":"Baden-W\u00fcrttemberg",
    "wof:name":"Tillmann Mattes Ingenieur",
    "wof:placetype":"venue"
},
  "geometry": {"coordinates":[9.220916748,48.7504920959],"type":"Point"}
}