{
  "type": "Feature",
  "properties": {
    "iso:country":"DE",
    "sg:address":"Kleutscher Str.",
    "sg:city":"Dessau",
    "sg:phone":"+49 340/218070",
    "sg:postcode":"06842",
    "sg:province":"Sachsen-Anhalt",
    "wof:name":"Hagebaumarkt Dessau Gmbh",
    "wof:placetype":"venue"
},
  "geometry": {"coordinates":[12.2953948975,51.8176879883],"type":"Point"}
}