{
  "type": "Feature",
  "properties": {
    "iso:country":"DE",
    "sg:address":"K\u00f6nigstr. 3",
    "sg:city":"Hameln",
    "sg:phone":"+49 5151/13251",
    "sg:postcode":"31785",
    "sg:province":"Niedersachsen",
    "wof:name":"Helmut Gewohn",
    "wof:placetype":"venue"
},
  "geometry": {"coordinates":[9.3727521896,52.1001396179],"type":"Point"}
}