{
  "type": "Feature",
  "properties": {
    "iso:country":"DE",
    "sg:address":"Kolpingstr. 16",
    "sg:city":"Biberach",
    "sg:phone":"+49 7351/578600",
    "sg:postcode":"88400",
    "sg:province":"Baden-W\u00fcrttemberg",
    "wof:name":"Hans Herre Ingenieur",
    "wof:placetype":"venue"
},
  "geometry": {"coordinates":[9.7866592407,48.095123291],"type":"Point"}
}