{
  "type": "Feature",
  "properties": {
    "iso:country":"DE",
    "sg:address":"Auf der Werthe 4",
    "sg:city":"V\u00f6hrenbach",
    "sg:phone":"+49 7727/91060",
    "sg:postcode":"78147",
    "sg:province":"Baden-W\u00fcrttemberg",
    "wof:name":"Klaus Kracht",
    "wof:placetype":"venue"
},
  "geometry": {"coordinates":[8.304955,48.045189],"type":"Point"}
}