{
  "type": "Feature",
  "properties": {
    "iso:country":"DE",
    "sg:address":"Brunnenstr. 3",
    "sg:city":"Lutzingen",
    "sg:phone":"+49 9074/1371",
    "sg:postcode":"89440",
    "sg:province":"Bayern",
    "wof:name":"Gloco Holzwaren Gmbh",
    "wof:placetype":"venue"
},
  "geometry": {"coordinates":[10.5421581268,48.6465644836],"type":"Point"}
}