{
  "type": "Feature",
  "properties": {
    "iso:country":"DE",
    "sg:address":"Im Br\u00fchl 15",
    "sg:city":"Greifenstein",
    "sg:phone":"+49 2779/91210",
    "sg:postcode":"35753",
    "sg:province":"Hessen",
    "wof:name":"Eastern Granit Gmbh",
    "wof:placetype":"venue"
},
  "geometry": {"coordinates":[8.2464046478,50.6102294922],"type":"Point"}
}