{
  "type": "Feature",
  "properties": {
    "iso:country":"DE",
    "sg:address":"Vogtsgasse",
    "sg:city":"K\u00f6nigswinter",
    "sg:phone":"+49 2244/80847",
    "sg:postcode":"53639",
    "sg:province":"Nordrhein-Westfalen",
    "wof:name":"M. Henseler",
    "wof:placetype":"venue"
},
  "geometry": {"coordinates":[7.2357149124,50.6941108704],"type":"Point"}
}