{
  "type": "Feature",
  "properties": {
    "iso:country":"DE",
    "sg:address":"Waldstr. 10",
    "sg:city":"Bad W\u00f6rishofen",
    "sg:phone":"+49 8247/7712",
    "sg:postcode":"86825",
    "sg:province":"Bayern",
    "wof:name":"Anne Und Helmut J\u00f6rg Massagen Und Naturheilpraxis",
    "wof:placetype":"venue"
},
  "geometry": {"coordinates":[10.621825,48.006248],"type":"Point"}
}