{
  "type": "Feature",
  "properties": {
    "iso:country":"DE",
    "sg:address":"Im Gr\u00fcndchen 6",
    "sg:city":"Bad Camberg",
    "sg:phone":"+49 6434/91460",
    "sg:postcode":"65520",
    "sg:province":"Hessen",
    "wof:name":"Hagebaumarkt Bad Camberg Gmbh",
    "wof:placetype":"venue"
},
  "geometry": {"coordinates":[8.2553710938,50.2929992676],"type":"Point"}
}