{
  "type": "Feature",
  "properties": {
    "iso:country":"DE",
    "sg:address":"Witzheldener Str. 24",
    "sg:city":"Burscheid",
    "sg:phone":"+49 2174/679302",
    "sg:postcode":"51399",
    "sg:province":"Nordrhein-Westfalen",
    "wof:name":"Werner J\u00f6rgens",
    "wof:placetype":"venue"
},
  "geometry": {"coordinates":[7.153236,51.103703],"type":"Point"}
}