{
  "type": "Feature",
  "properties": {
    "iso:country":"DE",
    "sg:address":"Im Wei\u00dfen Bild",
    "sg:city":"Wangen",
    "sg:phone":"+49 7522/9860",
    "sg:postcode":"88239",
    "sg:province":"Baden-W\u00fcrttemberg",
    "wof:name":"Waldner Laboreinrichtungen Verwaltungs-gmbh",
    "wof:placetype":"venue"
},
  "geometry": {"coordinates":[9.81269,47.688381],"type":"Point"}
}