{
  "type": "Feature",
  "properties": {
    "iso:country":"DE",
    "sg:address":"Wiflingshauser Str. 17-1",
    "sg:city":"Esslingen",
    "sg:phone":"+49 711/372024",
    "sg:postcode":"73732",
    "sg:province":"Baden-W\u00fcrttemberg",
    "wof:name":"G. Werner",
    "wof:placetype":"venue"
},
  "geometry": {"coordinates":[9.323986,48.752811],"type":"Point"}
}