{
  "type": "Feature",
  "properties": {
    "iso:country":"DE",
    "sg:address":"Alt Hausen 29",
    "sg:city":"Frankfurt",
    "sg:phone":"+49 69/784639",
    "sg:postcode":"60488",
    "sg:province":"Hessen",
    "wof:name":"Ellerfeldsch\u00e4nke",
    "wof:placetype":"venue"
},
  "geometry": {"coordinates":[8.6253499985,50.1336898804],"type":"Point"}
}