{
  "type": "Feature",
  "properties": {
    "iso:country":"DE",
    "sg:address":"Wettersteinstr. 19",
    "sg:city":"Weilheim",
    "sg:phone":"+49 881/1368",
    "sg:postcode":"82362",
    "sg:province":"Bayern",
    "wof:name":"Hermann Josef R\u00f6hrig",
    "wof:placetype":"venue"
},
  "geometry": {"coordinates":[11.1499900818,47.8426704407],"type":"Point"}
}