{
  "type": "Feature",
  "properties": {
    "iso:country":"DE",
    "sg:address":"Theodor-Fontane-Str. 67",
    "sg:city":"Reutlingen",
    "sg:phone":"+49 7121/311003",
    "sg:postcode":"72760",
    "sg:province":"Baden-W\u00fcrttemberg",
    "wof:name":"Heinrich Seidel Kg",
    "wof:placetype":"venue"
},
  "geometry": {"coordinates":[9.193786,48.507507],"type":"Point"}
}