{
  "type": "Feature",
  "properties": {
    "iso:country":"DE",
    "sg:address":"M\u00fcnsterhalden 7",
    "sg:city":"M\u00fcnstertal",
    "sg:phone":"+49 7636/1300",
    "sg:postcode":"79244",
    "sg:province":"Baden-W\u00fcrttemberg",
    "wof:name":"Hubert Riesterer Holzbildhauer",
    "wof:placetype":"venue"
},
  "geometry": {"coordinates":[7.787568,47.816246],"type":"Point"}
}