{
  "type": "Feature",
  "properties": {
    "iso:country":"DE",
    "sg:address":"Berscheider Str. 28",
    "sg:city":"Geichlingen",
    "sg:phone":"+49 6566/457",
    "sg:postcode":"54675",
    "sg:province":"Rheinland-Pfalz",
    "wof:name":"Peter Streng",
    "wof:placetype":"venue"
},
  "geometry": {"coordinates":[6.263378,49.953445],"type":"Point"}
}