{
  "type": "Feature",
  "properties": {
    "iso:country":"DE",
    "sg:address":"Johannesstr. 13",
    "sg:city":"Kirchentellinsfurt",
    "sg:phone":"+49 7121/90960",
    "sg:postcode":"72138",
    "sg:province":"Baden-W\u00fcrttemberg",
    "wof:name":"Manfred Hafner Steuerberater",
    "wof:placetype":"venue"
},
  "geometry": {"coordinates":[9.1549005508,48.5340766907],"type":"Point"}
}