{
  "type": "Feature",
  "properties": {
    "iso:country":"DE",
    "sg:address":"Buchenstr. 20",
    "sg:city":"Schwalmtal",
    "sg:phone":"+49 2163/45434",
    "sg:postcode":"41366",
    "sg:province":"Nordrhein-Westfalen",
    "wof:name":"Josef Windhausen",
    "wof:placetype":"venue"
},
  "geometry": {"coordinates":[6.267727,51.185932],"type":"Point"}
}