{
  "type": "Feature",
  "properties": {
    "iso:country":"DE",
    "sg:address":"Wurzner Str. 106",
    "sg:city":"Leipzig",
    "sg:postcode":"04315",
    "sg:province":"Sachsen",
    "wof:name":"Xxxhitlist.de Der Ultimative Sexindex",
    "wof:placetype":"venue"
},
  "geometry": {"coordinates":[12.416798,51.343311],"type":"Point"}
}