{
  "type": "Feature",
  "properties": {
    "iso:country":"DE",
    "sg:address":"Tiroler Str. 17",
    "sg:city":"Dortmund",
    "sg:phone":"+49 231/7273001",
    "sg:postcode":"44229",
    "sg:province":"Nordrhein-Westfalen",
    "wof:name":"Bifua Betriebswirtschaftliches Institut F\u00fcr Unternehmens-",
    "wof:placetype":"venue"
},
  "geometry": {"coordinates":[7.4590611458,51.4608268738],"type":"Point"}
}