{
  "type": "Feature",
  "properties": {
    "iso:country":"DE",
    "sg:address":"Klosterstr. 36",
    "sg:city":"Angerm\u00fcnde",
    "sg:phone":"+49 3331/32454",
    "sg:postcode":"16278",
    "sg:province":"Brandenburg",
    "wof:name":"Manfred Bartel",
    "wof:placetype":"venue"
},
  "geometry": {"coordinates":[14.004763,53.016232],"type":"Point"}
}