{
  "type": "Feature",
  "properties": {
    "iso:country":"DE",
    "sg:address":"Ehrenbachstr. 1",
    "sg:city":"St\u00fchlingen",
    "sg:phone":"+49 7744/570",
    "sg:postcode":"79780",
    "sg:province":"Baden-W\u00fcrttemberg",
    "wof:name":"Sto Ag",
    "wof:placetype":"venue"
},
  "geometry": {"coordinates":[8.4726352692,47.7674293518],"type":"Point"}
}