{
  "type": "Feature",
  "properties": {
    "iso:country":"DE",
    "sg:address":"Holzgasse 29",
    "sg:city":"Herxheim",
    "sg:phone":"+49 7276/1234",
    "sg:postcode":"76863",
    "sg:province":"Rheinland-Pfalz",
    "wof:name":"Werner Schumacher",
    "wof:placetype":"venue"
},
  "geometry": {"coordinates":[8.2126750946,49.1442070007],"type":"Point"}
}