{
  "type": "Feature",
  "properties": {
    "iso:country":"DE",
    "sg:address":"Westerwaldstr. 92",
    "sg:city":"Limburg",
    "sg:phone":"+49 6431/6666",
    "sg:postcode":"65549",
    "sg:province":"Hessen",
    "wof:name":"Deutscher Video Ring",
    "wof:placetype":"venue"
},
  "geometry": {"coordinates":[8.059586525,50.3965187073],"type":"Point"}
}