{
  "type": "Feature",
  "properties": {
    "iso:country":"DE",
    "sg:address":"L\u00f6wensteiner Str. 17",
    "sg:city":"Untergruppenbach",
    "sg:postcode":"74199",
    "sg:province":"Baden-W\u00fcrttemberg",
    "wof:name":"Schulze Kaminreparaturen E. K.",
    "wof:placetype":"venue"
},
  "geometry": {"coordinates":[9.3262357712,49.0851554871],"type":"Point"}
}