{
  "type": "Feature",
  "properties": {
    "iso:country":"DE",
    "sg:address":"Holstenstr. 20",
    "sg:city":"L\u00fcbeck",
    "sg:postcode":"23552",
    "sg:province":"Schleswig-Holstein",
    "wof:name":"Ptc Personal Training Coaching Gmbh",
    "wof:placetype":"venue"
},
  "geometry": {"coordinates":[10.6826715469,53.8664894104],"type":"Point"}
}