{
  "type": "Feature",
  "properties": {
    "iso:country":"DE",
    "sg:address":"Zur Centralwerkst\u00e4tte 11",
    "sg:city":"Weiden",
    "sg:phone":"+49 961/88378",
    "sg:postcode":"92637",
    "sg:province":"Bayern",
    "wof:name":"Deutsche Bahn Ag",
    "wof:placetype":"venue"
},
  "geometry": {"coordinates":[12.1614408493,49.6841773987],"type":"Point"}
}