{
  "type": "Feature",
  "properties": {
    "iso:country":"DE",
    "sg:address":"Schwalbenweg 5",
    "sg:city":"Gro\u00dfenkneten",
    "sg:phone":"+49 4435/5636",
    "sg:postcode":"26197",
    "sg:province":"Niedersachsen",
    "wof:name":"Reinhard Pannemann",
    "wof:placetype":"venue"
},
  "geometry": {"coordinates":[8.194074,52.949833],"type":"Point"}
}