{
  "type": "Feature",
  "properties": {
    "iso:country":"DE",
    "sg:address":"Amsterdamer Str. 91",
    "sg:city":"K\u00f6ln",
    "sg:phone":"+49 221/762086",
    "sg:postcode":"50735",
    "sg:province":"Nordrhein-Westfalen",
    "wof:name":"H.o.-computer Software Gmbh",
    "wof:placetype":"venue"
},
  "geometry": {"coordinates":[6.9684529305,50.9656524658],"type":"Point"}
}