{
  "type": "Feature",
  "properties": {
    "iso:country":"DE",
    "sg:address":"Herstallstr. 15",
    "sg:city":"Aschaffenburg",
    "sg:phone":"+49 6021/218141",
    "sg:postcode":"63739",
    "sg:province":"Bayern",
    "wof:name":"R. H\u00e4user",
    "wof:placetype":"venue"
},
  "geometry": {"coordinates":[9.1468839645,49.9752731323],"type":"Point"}
}