{
  "type": "Feature",
  "properties": {
    "iso:country":"DE",
    "sg:address":"Weidachweg 60",
    "sg:city":"Pliening",
    "sg:phone":"+49 8121/81202",
    "sg:postcode":"85652",
    "sg:province":"Bayern",
    "wof:name":"Anton Scheigl",
    "wof:placetype":"venue"
},
  "geometry": {"coordinates":[11.79501,48.199509],"type":"Point"}
}