{
  "type": "Feature",
  "properties": {
    "iso:country":"DE",
    "sg:address":"Kastanienplatz 2",
    "sg:city":"Zeitz",
    "sg:phone":"+49 3441/223891",
    "sg:postcode":"06712",
    "sg:province":"Sachsen-Anhalt",
    "wof:name":"Annemarie Bittner",
    "wof:placetype":"venue"
},
  "geometry": {"coordinates":[12.1507730484,51.0317497253],"type":"Point"}
}