{
  "type": "Feature",
  "properties": {
    "iso:country":"DE",
    "sg:address":"Kiesstr. 11",
    "sg:city":"Neustadt",
    "sg:phone":"+49 6321/84442",
    "sg:postcode":"67434",
    "sg:province":"Rheinland-Pfalz",
    "wof:name":"Erwin Barth-verlag Kg",
    "wof:placetype":"venue"
},
  "geometry": {"coordinates":[8.1403274536,49.3470153809],"type":"Point"}
}