{
  "type": "Feature",
  "properties": {
    "iso:country":"DE",
    "sg:address":"Innstr. 40",
    "sg:city":"Passau",
    "sg:postcode":"94032",
    "sg:province":"Bayern",
    "wof:name":"Rechenzentrum",
    "wof:placetype":"venue"
},
  "geometry": {"coordinates":[13.4572000504,48.5701675415],"type":"Point"}
}