{
  "type": "Feature",
  "properties": {
    "iso:country":"DE",
    "sg:address":"Freiheitstr. 54",
    "sg:city":"Altena",
    "sg:phone":"+49 2352/22151",
    "sg:postcode":"58762",
    "sg:province":"Nordrhein-Westfalen",
    "wof:name":"Rolf Nielsen Inh. Frank Nielsen E. K.",
    "wof:placetype":"venue"
},
  "geometry": {"coordinates":[7.6737089157,51.2908935547],"type":"Point"}
}