{
  "type": "Feature",
  "properties": {
    "iso:country":"DE",
    "sg:address":"Mitterstr. 3",
    "sg:city":"Gstadt",
    "sg:phone":"+49 8054/852",
    "sg:postcode":"83257",
    "sg:province":"Bayern",
    "wof:name":"G\u00fcnther Behrendt Bootshandlung",
    "wof:placetype":"venue"
},
  "geometry": {"coordinates":[12.434717,47.915501],"type":"Point"}
}