{
  "type": "Feature",
  "properties": {
    "iso:country":"DE",
    "sg:address":"Willingen",
    "sg:city":"Willingen",
    "sg:postcode":"34508",
    "sg:province":"Hessen",
    "wof:name":"Biker Toplist - Die Topliste F\u00fcr Alle Bikersites",
    "wof:placetype":"venue"
},
  "geometry": {"coordinates":[8.66889,51.29509],"type":"Point"}
}