{
  "type": "Feature",
  "properties": {
    "iso:country":"DE",
    "sg:address":"Von-Loe-Str. 38",
    "sg:city":"Kempen",
    "sg:phone":"+49 2152/519099",
    "sg:postcode":"47906",
    "sg:province":"Nordrhein-Westfalen",
    "wof:name":"B. R\u00f6se",
    "wof:placetype":"venue"
},
  "geometry": {"coordinates":[6.4206528664,51.3712387085],"type":"Point"}
}