{
  "type": "Feature",
  "properties": {
    "iso:country":"DE",
    "sg:address":"Kaiserstr. 63",
    "sg:city":"Schiffweiler",
    "sg:phone":"+49 6821/69321",
    "sg:postcode":"66578",
    "sg:province":"Saarland",
    "wof:name":"Manfred Kaub",
    "wof:placetype":"venue"
},
  "geometry": {"coordinates":[7.105847,49.355118],"type":"Point"}
}