{
  "type": "Feature",
  "properties": {
    "iso:country":"DE",
    "sg:address":"Possenhofener Str. 53",
    "sg:city":"Starnberg",
    "sg:phone":"+49 8151/89528",
    "sg:postcode":"82319",
    "sg:province":"Bayern",
    "wof:name":"Isar Heimbau Baugesellschaft F\u00fcr",
    "wof:placetype":"venue"
},
  "geometry": {"coordinates":[11.33525,47.989166],"type":"Point"}
}