{
  "type": "Feature",
  "properties": {
    "iso:country":"DE",
    "sg:address":"Hopfenstr. 34",
    "sg:city":"Hanau",
    "sg:phone":"+49 6181/257045",
    "sg:postcode":"63454",
    "sg:province":"Hessen",
    "wof:name":"Theodor Hartwig",
    "wof:placetype":"venue"
},
  "geometry": {"coordinates":[8.8925743103,50.1337547302],"type":"Point"}
}