{
  "type": "Feature",
  "properties": {
    "iso:country":"DE",
    "sg:address":"Hemberger Damm",
    "sg:city":"Emsdetten",
    "sg:phone":"+49 2572/150960",
    "sg:postcode":"48282",
    "sg:province":"Nordrhein-Westfalen",
    "wof:name":"Ferdinand Gier",
    "wof:placetype":"venue"
},
  "geometry": {"coordinates":[7.5555949211,52.1608581543],"type":"Point"}
}