{
  "type": "Feature",
  "properties": {
    "iso:country":"DE",
    "sg:address":"Ostlandstr. 6",
    "sg:city":"Bruchhausen-Vilsen",
    "sg:phone":"+49 4252/1069",
    "sg:postcode":"27305",
    "sg:province":"Niedersachsen",
    "wof:name":"Reinhold Kneifel",
    "wof:placetype":"venue"
},
  "geometry": {"coordinates":[8.989237,52.825439],"type":"Point"}
}