{
  "type": "Feature",
  "properties": {
    "iso:country":"DE",
    "sg:address":"Ziegelstr. 23",
    "sg:city":"Ravensburg",
    "sg:phone":"+49 751/21651",
    "sg:postcode":"88214",
    "sg:province":"Baden-W\u00fcrttemberg",
    "wof:name":"J. Mahler Verm\u00f6gensverwaltung",
    "wof:placetype":"venue"
},
  "geometry": {"coordinates":[9.6070356369,47.7785606384],"type":"Point"}
}