{
  "type": "Feature",
  "properties": {
    "iso:country":"DE",
    "sg:address":"Kanalstr. 20",
    "sg:city":"Neuss",
    "sg:phone":"+49 2131/21844",
    "sg:postcode":"41460",
    "sg:province":"Nordrhein-Westfalen",
    "wof:name":"Schneider Und Wehrmann Ergotherapeutische Praxis",
    "wof:placetype":"venue"
},
  "geometry": {"coordinates":[6.688301,51.196205],"type":"Point"}
}