{
  "type": "Feature",
  "properties": {
    "iso:country":"DE",
    "sg:address":"Robert-Bosch-Str. 23",
    "sg:city":"Hockenheim",
    "sg:phone":"+49 6205/14128",
    "sg:postcode":"68766",
    "sg:province":"Baden-W\u00fcrttemberg",
    "wof:name":"Barbara Hideg",
    "wof:placetype":"venue"
},
  "geometry": {"coordinates":[8.5590324402,49.317779541],"type":"Point"}
}