{
  "type": "Feature",
  "properties": {
    "iso:country":"DE",
    "sg:address":"Pfarrgasse 7",
    "sg:city":"Untersiemau",
    "sg:phone":"+49 9565/6324",
    "sg:postcode":"96253",
    "sg:province":"Bayern",
    "wof:name":"Marienverein Untersiemau Trina Finzel",
    "wof:placetype":"venue"
},
  "geometry": {"coordinates":[10.9748268127,50.1933135986],"type":"Point"}
}