{
  "type": "Feature",
  "properties": {
    "iso:country":"DE",
    "sg:city":"Erden",
    "sg:phone":"+49 6532/4060",
    "sg:postcode":"54492",
    "sg:province":"Rheinland-Pfalz",
    "wof:name":"Camping Erden",
    "wof:placetype":"venue"
},
  "geometry": {"coordinates":[7.02375,49.979015],"type":"Point"}
}