{
  "type": "Feature",
  "properties": {
    "iso:country":"DE",
    "sg:address":"Pfarrer-Jaegers-Str. 1",
    "sg:city":"Everswinkel",
    "sg:postcode":"48351",
    "sg:province":"Nordrhein-Westfalen",
    "wof:name":"Tinnitus-recording Musikproduktion Gmbh",
    "wof:placetype":"venue"
},
  "geometry": {"coordinates":[7.840413,51.926689],"type":"Point"}
}