{
  "type": "Feature",
  "properties": {
    "iso:country":"DE",
    "sg:address":"Horlachen 2",
    "sg:city":"Kronach",
    "sg:phone":"+49 9261/1873",
    "sg:postcode":"96317",
    "sg:province":"Bayern",
    "wof:name":"Autohaus Nohl Gmbh",
    "wof:placetype":"venue"
},
  "geometry": {"coordinates":[11.380979538,50.1991767883],"type":"Point"}
}