{
  "type": "Feature",
  "properties": {
    "iso:country":"DE",
    "sg:address":"Essener Str. 18",
    "sg:city":"Wilnsdorf",
    "sg:postcode":"57234",
    "sg:province":"Nordrhein-Westfalen",
    "wof:name":"Deutscher Paket Dienst Cordes & Simon",
    "wof:placetype":"venue"
},
  "geometry": {"coordinates":[8.07861,50.823936],"type":"Point"}
}