{
  "type": "Feature",
  "properties": {
    "iso:country":"DE",
    "sg:address":"Am Lindenweg 48",
    "sg:city":"K\u00f6ln",
    "sg:phone":"+49 221/9486950",
    "sg:postcode":"50933",
    "sg:province":"Nordrhein-Westfalen",
    "wof:name":"Morawietz Immobilien Verwaltung-vermittlung Gmbh",
    "wof:placetype":"venue"
},
  "geometry": {"coordinates":[6.8624920845,50.9470367432],"type":"Point"}
}