{
  "type": "Feature",
  "properties": {
    "iso:country":"DE",
    "sg:address":"Schottenstr. 73",
    "sg:city":"Konstanz",
    "sg:phone":"+49 7531/916476",
    "sg:postcode":"78462",
    "sg:province":"Baden-W\u00fcrttemberg",
    "wof:name":"Sadeks Treff",
    "wof:placetype":"venue"
},
  "geometry": {"coordinates":[9.1728343964,47.6664733887],"type":"Point"}
}