{
  "type": "Feature",
  "properties": {
    "iso:country":"DE",
    "sg:address":"Volgersweg / Ecke Eichstra\u00dfe",
    "sg:city":"Hannover",
    "sg:phone":"+49 511",
    "sg:postcode":"30175",
    "sg:province":"Niedersachsen",
    "wof:name":"Cappuccino, Espresso- Und Designshop",
    "wof:placetype":"venue"
},
  "geometry": {"coordinates":[9.7683258057,52.376285553],"type":"Point"}
}