{
  "type": "Feature",
  "properties": {
    "iso:country":"DE",
    "sg:address":"Berchtesgadener Str. 25",
    "sg:city":"Ramsau",
    "sg:phone":"+49 8657/453",
    "sg:postcode":"83486",
    "sg:province":"Bayern",
    "wof:name":"Wilhelm H\u00f6gerle",
    "wof:placetype":"venue"
},
  "geometry": {"coordinates":[12.91886,47.604603],"type":"Point"}
}