{
  "type": "Feature",
  "properties": {
    "iso:country":"DE",
    "sg:address":"Aschaffenburger Str. 134",
    "sg:city":"Goldbach",
    "sg:phone":"+49 6021/921060",
    "sg:postcode":"63773",
    "sg:province":"Bayern",
    "wof:name":"Mfk Planungsb\u00fcro F\u00fcr Maschinen- Und Anlagenbau E.k.",
    "wof:placetype":"venue"
},
  "geometry": {"coordinates":[9.189332962,49.9987983704],"type":"Point"}
}