{
  "type": "Feature",
  "properties": {
    "iso:country":"DE",
    "sg:address":"Klobensteiner Str. 23",
    "sg:city":"M\u00fcnchen",
    "sg:phone":"+49 89/643036",
    "sg:postcode":"81547",
    "sg:province":"Bayern",
    "wof:name":"Ing. Grad. Leonhard Kistler Ingenieur Und Architekt",
    "wof:placetype":"venue"
},
  "geometry": {"coordinates":[11.566262,48.098244],"type":"Point"}
}