{
  "type": "Feature",
  "properties": {
    "iso:country":"DE",
    "sg:address":"Schlangenbader Str. 25",
    "sg:city":"Berlin",
    "sg:phone":"+49 30/89702280",
    "sg:postcode":"14197",
    "sg:province":"Berlin",
    "wof:name":"Extra",
    "wof:placetype":"venue"
},
  "geometry": {"coordinates":[13.3078775406,52.4727058411],"type":"Point"}
}