{
  "type": "Feature",
  "properties": {
    "iso:country":"DE",
    "sg:address":"Margot-Kalinke-Str. 9",
    "sg:city":"M\u00fcnchen",
    "sg:phone":"+49 89/318140",
    "sg:postcode":"80939",
    "sg:province":"Bayern",
    "wof:name":"Wilhelm Gienger K\u00fcchen- Und Einrichtungs Gmbh",
    "wof:placetype":"venue"
},
  "geometry": {"coordinates":[11.5960416794,48.1952476501],"type":"Point"}
}