{
  "type": "Feature",
  "properties": {
    "iso:country":"DE",
    "sg:address":"Marktplatz 5",
    "sg:city":"Ochtrup",
    "sg:postcode":"48607",
    "sg:province":"Nordrhein-Westfalen",
    "wof:name":"Extra-markt",
    "wof:placetype":"venue"
},
  "geometry": {"coordinates":[7.1864099503,52.208480835],"type":"Point"}
}