{
  "type": "Feature",
  "properties": {
    "iso:country":"DE",
    "sg:address":"Kirch\u00e4ckerstr. 8",
    "sg:city":"Blaufelden",
    "sg:phone":"+49 7958/98080",
    "sg:postcode":"74572",
    "sg:province":"Baden-W\u00fcrttemberg",
    "wof:name":"Berthold Beierlein Steuerberater",
    "wof:placetype":"venue"
},
  "geometry": {"coordinates":[10.0967845917,49.3106079102],"type":"Point"}
}