{
  "type": "Feature",
  "properties": {
    "iso:country":"DE",
    "sg:address":"Raimundsreut 55",
    "sg:city":"Hohenau",
    "sg:phone":"+49 8558/1023",
    "sg:postcode":"94545",
    "sg:province":"Bayern",
    "wof:name":"Rudolf Peterhansl",
    "wof:placetype":"venue"
},
  "geometry": {"coordinates":[13.542803,48.865986],"type":"Point"}
}