{
  "type": "Feature",
  "properties": {
    "iso:country":"DE",
    "sg:address":"L\u00fcbecker Str. 52",
    "sg:city":"Berlin",
    "sg:phone":"+49 30/3949679",
    "sg:postcode":"10559",
    "sg:province":"Berlin",
    "wof:name":"J. Jung",
    "wof:placetype":"venue"
},
  "geometry": {"coordinates":[13.3452253342,52.5267372131],"type":"Point"}
}