{
  "type": "Feature",
  "properties": {
    "iso:country":"DE",
    "sg:address":"Sotterh\u00e4user Str. 10",
    "sg:city":"Beyernaumburg",
    "sg:phone":"+49 3464/571714",
    "sg:postcode":"06528",
    "sg:province":"Sachsen-Anhalt",
    "wof:name":"Landtechnikservice Und Schlosserei Gmbh",
    "wof:placetype":"venue"
},
  "geometry": {"coordinates":[11.39675,51.469769],"type":"Point"}
}