{
  "type": "Feature",
  "properties": {
    "iso:country":"DE",
    "sg:address":"Landerdamm 4",
    "sg:city":"Schloss Holte",
    "sg:postcode":"33758",
    "sg:province":"Nordrhein-Westfalen",
    "wof:name":"Epilepsie-seminare",
    "wof:placetype":"venue"
},
  "geometry": {"coordinates":[8.607202,51.906429],"type":"Point"}
}