{
  "type": "Feature",
  "properties": {
    "iso:country":"DE",
    "sg:address":"Arweg 37",
    "sg:city":"Bad Breisig",
    "sg:phone":"+49 2633/1748",
    "sg:postcode":"53498",
    "sg:province":"Rheinland-Pfalz",
    "wof:name":"J\u00fcrgen Ennenbach",
    "wof:placetype":"venue"
},
  "geometry": {"coordinates":[7.28984,50.507],"type":"Point"}
}