{
  "type": "Feature",
  "properties": {
    "iso:country":"DE",
    "sg:address":"R\u00fcbenacher Str. 39",
    "sg:city":"M\u00fclheim-K\u00e4rlich",
    "sg:phone":"+49 2630/1300",
    "sg:postcode":"56218",
    "sg:province":"Rheinland-Pfalz",
    "wof:name":"Gerhard Zimmermann",
    "wof:placetype":"venue"
},
  "geometry": {"coordinates":[7.4985389709,50.3841781616],"type":"Point"}
}