{
  "type": "Feature",
  "properties": {
    "iso:country":"DE",
    "sg:address":"Suhlenstr. 4",
    "sg:city":"Barsinghausen",
    "sg:phone":"+49 5105/8766",
    "sg:postcode":"30890",
    "sg:province":"Niedersachsen",
    "wof:name":"I. Peter",
    "wof:placetype":"venue"
},
  "geometry": {"coordinates":[9.5344743729,52.3049850464],"type":"Point"}
}