{
  "type": "Feature",
  "properties": {
    "iso:country":"DE",
    "sg:address":"Scheideweg 33",
    "sg:city":"Hueckeswagen",
    "sg:phone":"+49 2192/932080",
    "sg:postcode":"42499",
    "sg:province":"Nordrhein-Westfalen",
    "wof:name":"Layout",
    "wof:placetype":"venue"
},
  "geometry": {"coordinates":[7.290727,51.135349],"type":"Point"}
}