{
  "type": "Feature",
  "properties": {
    "iso:country":"DE",
    "sg:address":"M\u00fcndener Str. 57",
    "sg:city":"Reinhardshagen",
    "sg:phone":"+49 5544/482",
    "sg:postcode":"34359",
    "sg:province":"Hessen",
    "wof:name":"K. Ude",
    "wof:placetype":"venue"
},
  "geometry": {"coordinates":[9.6178865433,51.4794311523],"type":"Point"}
}