{
  "type": "Feature",
  "properties": {
    "iso:country":"DE",
    "sg:address":"Sonthofener Str. 8",
    "sg:city":"Immenstadt",
    "sg:phone":"+49 8323/7260",
    "sg:postcode":"87509",
    "sg:province":"Bayern",
    "wof:name":"Pilsstube Paulaner",
    "wof:placetype":"venue"
},
  "geometry": {"coordinates":[10.2188453674,47.5616035461],"type":"Point"}
}