{
  "type": "Feature",
  "properties": {
    "iso:country":"DE",
    "sg:address":"Kreuzauer Str. 121",
    "sg:city":"D\u00fcren",
    "sg:phone":"+49 2421/51304",
    "sg:postcode":"52355",
    "sg:province":"Nordrhein-Westfalen",
    "wof:name":"Josef Mattes",
    "wof:placetype":"venue"
},
  "geometry": {"coordinates":[6.49217,50.77076],"type":"Point"}
}