{
  "type": "Feature",
  "properties": {
    "iso:country":"DE",
    "sg:city":"Altlay",
    "sg:phone":"+49 6543/980226",
    "sg:postcode":"56858",
    "sg:province":"Rheinland-Pfalz",
    "wof:name":"Bernd Klein",
    "wof:placetype":"venue"
},
  "geometry": {"coordinates":[7.270191,49.988293],"type":"Point"}
}