{
  "type": "Feature",
  "properties": {
    "iso:country":"DE",
    "sg:address":"Unnauer Weg 25",
    "sg:city":"K\u00f6ln",
    "sg:phone":"+49 221/7901910",
    "sg:postcode":"50767",
    "sg:province":"Nordrhein-Westfalen",
    "wof:name":"Brock Hausverwaltung Gmbh",
    "wof:placetype":"venue"
},
  "geometry": {"coordinates":[6.8952059746,51.0016937256],"type":"Point"}
}