{
  "type": "Feature",
  "properties": {
    "iso:country":"DE",
    "sg:address":"Donaustr. 14",
    "sg:city":"Fridingen",
    "sg:phone":"+49 7463/1772",
    "sg:postcode":"78567",
    "sg:province":"Baden-W\u00fcrttemberg",
    "wof:name":"Herbert Steidle",
    "wof:placetype":"venue"
},
  "geometry": {"coordinates":[8.932277,48.02142],"type":"Point"}
}