{
  "type": "Feature",
  "properties": {
    "iso:country":"DE",
    "sg:address":"Luitgardstr. 23",
    "sg:city":"Pforzheim",
    "sg:phone":"+49 7231/33135",
    "sg:postcode":"75177",
    "sg:province":"Baden-W\u00fcrttemberg",
    "wof:name":"Restaurant Man Wah",
    "wof:placetype":"venue"
},
  "geometry": {"coordinates":[8.6969327927,48.8962898254],"type":"Point"}
}