{
  "type": "Feature",
  "properties": {
    "iso:country":"DE",
    "sg:address":"Stifterstr. 1",
    "sg:city":"Renningen",
    "sg:phone":"+49 7159/2422",
    "sg:postcode":"71272",
    "sg:province":"Baden-W\u00fcrttemberg",
    "wof:name":"Kath. Pfarramt St. Bonifatius",
    "wof:placetype":"venue"
},
  "geometry": {"coordinates":[8.9380531311,48.7717666626],"type":"Point"}
}