{
  "type": "Feature",
  "properties": {
    "iso:country":"DE",
    "sg:address":"Obere G\u00e4rten 10",
    "sg:city":"Buchen-Hollerbach",
    "sg:phone":"+49 6281",
    "sg:postcode":"74722",
    "sg:province":"Baden-W\u00fcrttemberg",
    "wof:name":"Bei Ihrem Stallbau Sollten Sie Uns Dazuholen",
    "wof:placetype":"venue"
},
  "geometry": {"coordinates":[9.278767,49.515434],"type":"Point"}
}