{
  "type": "Feature",
  "properties": {
    "iso:country":"DE",
    "sg:address":"Waldstr.",
    "sg:city":"Ha\u00dfloch",
    "sg:phone":"+49 6324/2868",
    "sg:postcode":"67454",
    "sg:province":"Rheinland-Pfalz",
    "wof:name":"G. Krebs",
    "wof:placetype":"venue"
},
  "geometry": {"coordinates":[8.2488040924,49.3568840027],"type":"Point"}
}