{
  "type": "Feature",
  "properties": {
    "iso:country":"DE",
    "sg:address":"Elisabeth-Anna-Str. 18",
    "sg:city":"Wangerooge",
    "sg:phone":"+49 4469/942229",
    "sg:postcode":"26486",
    "sg:province":"Niedersachsen",
    "wof:name":"Bit Smutje Restaurant",
    "wof:placetype":"venue"
},
  "geometry": {"coordinates":[7.8992180824,53.792224884],"type":"Point"}
}