{
  "type": "Feature",
  "properties": {
    "iso:country":"DE",
    "sg:address":"Bernsteinweg 4",
    "sg:city":"Bad Herrenalb",
    "sg:phone":"+49 7083/3940",
    "sg:postcode":"76332",
    "sg:province":"Baden-W\u00fcrttemberg",
    "wof:name":"Hotel Gaab",
    "wof:placetype":"venue"
},
  "geometry": {"coordinates":[8.4361848831,48.7985534668],"type":"Point"}
}