{
  "type": "Feature",
  "properties": {
    "iso:country":"DE",
    "sg:address":"Mockauer Str. 45",
    "sg:city":"Leipzig",
    "sg:phone":"+49 341/6024700",
    "sg:postcode":"04357",
    "sg:province":"Sachsen",
    "wof:name":"Leipziger Kisten- Und Leistenfabrik Gmbh",
    "wof:placetype":"venue"
},
  "geometry": {"coordinates":[12.405404,51.368076],"type":"Point"}
}