{
  "type": "Feature",
  "properties": {
    "iso:country":"DE",
    "sg:address":"Wenkenstr. 1",
    "sg:city":"Bad Salzuflen",
    "sg:phone":"+49 5222/58833",
    "sg:postcode":"32105",
    "sg:province":"Nordrhein-Westfalen",
    "wof:name":"Fleischerei Franz Owczarek",
    "wof:placetype":"venue"
},
  "geometry": {"coordinates":[8.7469244003,52.0845451355],"type":"Point"}
}