{
  "type": "Feature",
  "properties": {
    "iso:country":"DE",
    "sg:address":"Ludwigstr. 27",
    "sg:city":"Traunstein",
    "sg:phone":"+49 861/166810",
    "sg:postcode":"83278",
    "sg:province":"Bayern",
    "wof:name":"Wilhelm Gienger K\u00fcchen- Und Einrichtungs Gmbh",
    "wof:placetype":"venue"
},
  "geometry": {"coordinates":[12.6426496506,47.8702888489],"type":"Point"}
}