{
  "type": "Feature",
  "properties": {
    "iso:country":"DE",
    "sg:address":"Carl-Zeiss-Rg. 11",
    "sg:city":"Rastenberg",
    "sg:phone":"+49 4936/3777620",
    "sg:postcode":"99636",
    "sg:province":"Th\u00fcringen",
    "wof:name":"Frank Sch\u00c4fer Gmbh Strassen- & Tiefbau",
    "wof:placetype":"venue"
},
  "geometry": {"coordinates":[11.411316,51.173351],"type":"Point"}
}