{
  "type": "Feature",
  "properties": {
    "iso:country":"DE",
    "sg:address":"Schulstr. 50",
    "sg:city":"Reinsb\u00fcttel",
    "sg:phone":"+49 4833/589",
    "sg:postcode":"25764",
    "sg:province":"Schleswig-Holstein",
    "wof:name":"Rolf Lohmeier",
    "wof:placetype":"venue"
},
  "geometry": {"coordinates":[8.91997,54.176262],"type":"Point"}
}