{
  "type": "Feature",
  "properties": {
    "iso:country":"DE",
    "sg:address":"Rotlintstr. 80",
    "sg:city":"Frankfurt",
    "sg:phone":"+49 69/454046",
    "sg:postcode":"60389",
    "sg:province":"Hessen",
    "wof:name":"Rotlint-apotheke B\u00e4hr Und Haas Ohg",
    "wof:placetype":"venue"
},
  "geometry": {"coordinates":[8.695192,50.128315],"type":"Point"}
}