{
  "type": "Feature",
  "properties": {
    "iso:country":"DE",
    "sg:address":"Brauhausstr. 3",
    "sg:city":"Leimbach",
    "sg:phone":"+49 3631/895306",
    "sg:postcode":"99735",
    "sg:province":"Th\u00fcringen",
    "wof:name":"Dietmar Selle",
    "wof:placetype":"venue"
},
  "geometry": {"coordinates":[10.86353302,51.5000343323],"type":"Point"}
}