{
  "type": "Feature",
  "properties": {
    "iso:country":"DE",
    "sg:address":"Grazer Str. 1",
    "sg:city":"Dresden",
    "sg:postcode":"01279",
    "sg:province":"Sachsen",
    "wof:name":"Chorin Grundst\u00fccks- Verwertungsges. Mbh",
    "wof:placetype":"venue"
},
  "geometry": {"coordinates":[13.835214,51.022774],"type":"Point"}
}