{
  "type": "Feature",
  "properties": {
    "iso:country":"DE",
    "sg:address":"Hoorwaldstr. 44a",
    "sg:city":"Burbach",
    "sg:phone":"+49 2736/3325",
    "sg:postcode":"57299",
    "sg:province":"Nordrhein-Westfalen",
    "wof:name":"Oskar Schmenn Gmbh",
    "wof:placetype":"venue"
},
  "geometry": {"coordinates":[8.132016,50.731812],"type":"Point"}
}