{
  "type": "Feature",
  "properties": {
    "iso:country":"DE",
    "sg:address":"Osterstr. 64",
    "sg:city":"Hannover",
    "sg:phone":"+49 511/357980",
    "sg:postcode":"30159",
    "sg:province":"Niedersachsen",
    "wof:name":"Kossmann Und Schuler Rechtsanw\u00e4lte Und Notar",
    "wof:placetype":"venue"
},
  "geometry": {"coordinates":[9.7403526306,52.3684844971],"type":"Point"}
}