{
  "type": "Feature",
  "properties": {
    "iso:country":"DE",
    "sg:address":"Im Kleifeld 23",
    "sg:city":"Lehrte",
    "sg:phone":"+49 5132/87940",
    "sg:postcode":"31275",
    "sg:province":"Niedersachsen",
    "wof:name":"H+s Fahrzeugbau Gmbh & Co",
    "wof:placetype":"venue"
},
  "geometry": {"coordinates":[9.906425,52.36047],"type":"Point"}
}