{
  "type": "Feature",
  "properties": {
    "iso:country":"DE",
    "sg:address":"Hochreuthstr. 17",
    "sg:city":"Abenberg",
    "sg:phone":"+49 9178/274",
    "sg:postcode":"91183",
    "sg:province":"Bayern",
    "wof:name":"Meckert",
    "wof:placetype":"venue"
},
  "geometry": {"coordinates":[10.963055,49.233276],"type":"Point"}
}