{
  "type": "Feature",
  "properties": {
    "iso:country":"DE",
    "sg:address":"Schindbergstr 40",
    "sg:city":"M\u00fcnnerstadt",
    "sg:phone":"+49 9733/782503",
    "sg:postcode":"97702",
    "sg:province":"Bayern",
    "wof:name":"Herrmann",
    "wof:placetype":"venue"
},
  "geometry": {"coordinates":[10.1854410172,50.2425422668],"type":"Point"}
}