{
  "type": "Feature",
  "properties": {
    "iso:country":"DE",
    "sg:address":"Br\u00fcckenweg 5",
    "sg:city":"Meerane",
    "sg:phone":"+49 3764/5020",
    "sg:postcode":"08393",
    "sg:province":"Sachsen",
    "wof:name":"Steinbeis Ibl Gmbh",
    "wof:placetype":"venue"
},
  "geometry": {"coordinates":[12.449717,50.827892],"type":"Point"}
}