{
  "type": "Feature",
  "properties": {
    "iso:country":"DE",
    "sg:address":"Hauptstr. 17",
    "sg:city":"Wolfersdorf",
    "sg:phone":"+49 8168/1801",
    "sg:postcode":"85395",
    "sg:province":"Bayern",
    "wof:name":"Herbert Schweller Gmbh B\u00e4ckerei",
    "wof:placetype":"venue"
},
  "geometry": {"coordinates":[11.706982,48.481098],"type":"Point"}
}