{
  "type": "Feature",
  "properties": {
    "iso:country":"DE",
    "sg:address":"Hofmillerstr. 1",
    "sg:city":"Rosenheim",
    "sg:phone":"+49 8031/85676",
    "sg:postcode":"83024",
    "sg:province":"Bayern",
    "wof:name":"Minimal",
    "wof:placetype":"venue"
},
  "geometry": {"coordinates":[12.1203603745,47.8652915955],"type":"Point"}
}