{
  "type": "Feature",
  "properties": {
    "iso:country":"DE",
    "sg:address":"Sch\u00fctterweg 5",
    "sg:city":"Unna",
    "sg:phone":"+49 2303/82779",
    "sg:postcode":"59423",
    "sg:province":"Nordrhein-Westfalen",
    "wof:name":"Die Mobile Krankenschwester Elke Korten",
    "wof:placetype":"venue"
},
  "geometry": {"coordinates":[7.679605,51.522747],"type":"Point"}
}