{
  "type": "Feature",
  "properties": {
    "iso:country":"DE",
    "sg:address":"J\u00f6llenbecker Str. 565",
    "sg:city":"Bielefeld",
    "sg:phone":"+49 5206/3110",
    "sg:postcode":"33739",
    "sg:province":"Nordrhein-Westfalen",
    "wof:name":"Haselhorst",
    "wof:placetype":"venue"
},
  "geometry": {"coordinates":[8.5136966705,52.0950393677],"type":"Point"}
}