{
  "type": "Feature",
  "properties": {
    "iso:country":"DE",
    "sg:address":"Eching",
    "sg:city":"Eching",
    "sg:phone":"+49 89/3193119",
    "sg:postcode":"85386",
    "sg:province":"Bayern",
    "wof:name":"Raiffeisenbank Eching Eg",
    "wof:placetype":"venue"
},
  "geometry": {"coordinates":[11.63471,48.29874],"type":"Point"}
}