{
  "type": "Feature",
  "properties": {
    "iso:country":"DE",
    "sg:address":"Stra\u00dfe der Jugend 3",
    "sg:city":"Torgau",
    "sg:phone":"+49 3421/903113",
    "sg:postcode":"04860",
    "sg:province":"Sachsen",
    "wof:name":"Br\u00e4ust\u00fcbel",
    "wof:placetype":"venue"
},
  "geometry": {"coordinates":[13.0020513535,51.5555458069],"type":"Point"}
}