{
  "type": "Feature",
  "properties": {
    "iso:country":"DE",
    "sg:address":"Im Langen Feld 10",
    "sg:city":"Alth\u00fctte",
    "sg:phone":"+49 7183/41457",
    "sg:postcode":"71566",
    "sg:province":"Baden-W\u00fcrttemberg",
    "wof:name":"Klaus Tr\u00e4nckler Architekt",
    "wof:placetype":"venue"
},
  "geometry": {"coordinates":[9.579619,48.91259],"type":"Point"}
}