{
  "type": "Feature",
  "properties": {
    "iso:country":"DE",
    "sg:address":"Erste Industriestr. 16",
    "sg:city":"Hockenheim",
    "sg:phone":"+49 6205/7270",
    "sg:postcode":"68766",
    "sg:province":"Baden-W\u00fcrttemberg",
    "wof:name":"Kurt Bayer",
    "wof:placetype":"venue"
},
  "geometry": {"coordinates":[8.5362606049,49.342666626],"type":"Point"}
}