{
  "type": "Feature",
  "properties": {
    "iso:country":"DE",
    "sg:address":"Rheinstr.",
    "sg:city":"Bendorf",
    "sg:phone":"+49 2622/15021",
    "sg:postcode":"56170",
    "sg:province":"Rheinland-Pfalz",
    "wof:name":"Ppp4 Fl\u00fcssiggasvertrieb",
    "wof:placetype":"venue"
},
  "geometry": {"coordinates":[7.5753102303,50.418838501],"type":"Point"}
}