{
  "type": "Feature",
  "properties": {
    "iso:country":"DE",
    "sg:address":"Wehrstr. 4",
    "sg:city":"Bad Oeynhausen",
    "sg:phone":"+49 5731/5619",
    "sg:postcode":"32549",
    "sg:province":"Nordrhein-Westfalen",
    "wof:name":"Willi Flores",
    "wof:placetype":"venue"
},
  "geometry": {"coordinates":[8.810412,52.232185],"type":"Point"}
}