{
  "type": "Feature",
  "properties": {
    "iso:country":"DE",
    "sg:address":"Widukindstr. 12",
    "sg:city":"Ibbenb\u00fcren",
    "sg:phone":"+49 5451/972238",
    "sg:postcode":"49477",
    "sg:province":"Nordrhein-Westfalen",
    "wof:name":"W\u00fcrttemberg. Versicherung",
    "wof:placetype":"venue"
},
  "geometry": {"coordinates":[7.7104530334,52.270904541],"type":"Point"}
}