{
  "type": "Feature",
  "properties": {
    "iso:country":"DE",
    "sg:address":"Wredowstr. 3",
    "sg:city":"Brandenburg",
    "sg:phone":"+49 3381/521265",
    "sg:postcode":"14776",
    "sg:province":"Brandenburg",
    "wof:name":"Dieter H\u00f6hne",
    "wof:placetype":"venue"
},
  "geometry": {"coordinates":[12.550591,52.405754],"type":"Point"}
}