{
  "type": "Feature",
  "properties": {
    "iso:country":"DE",
    "sg:address":"Pfarrgasse 5",
    "sg:city":"Duderstadt",
    "sg:phone":"+49 5527/2611",
    "sg:postcode":"37115",
    "sg:province":"Niedersachsen",
    "wof:name":"Kath. Pfarramt St. Johannes Baptist",
    "wof:placetype":"venue"
},
  "geometry": {"coordinates":[10.2322597504,51.4893989563],"type":"Point"}
}