{
  "type": "Feature",
  "properties": {
    "iso:country":"DE",
    "sg:address":"Dr.-Munderloh-Str. 1",
    "sg:city":"Hude",
    "sg:phone":"+49 4484/945394",
    "sg:postcode":"27798",
    "sg:province":"Niedersachsen",
    "wof:name":"Hergen Bleckwehl",
    "wof:placetype":"venue"
},
  "geometry": {"coordinates":[8.3364963531,53.1168937683],"type":"Point"}
}