{
  "type": "Feature",
  "properties": {
    "iso:country":"DE",
    "sg:address":"Grabenstr. 33",
    "sg:city":"Unterensingen",
    "sg:phone":"+49 7022/6003225",
    "sg:postcode":"72669",
    "sg:province":"Baden-W\u00fcrttemberg",
    "wof:name":"Deutsche Zincolit Gmbh",
    "wof:placetype":"venue"
},
  "geometry": {"coordinates":[9.3620414734,48.6560630798],"type":"Point"}
}