{
  "type": "Feature",
  "properties": {
    "iso:country":"DE",
    "sg:address":"Uracher Str. 36",
    "sg:city":"Dettingen",
    "sg:phone":"+49 7123/97390",
    "sg:postcode":"72581",
    "sg:province":"Baden-W\u00fcrttemberg",
    "wof:name":"Gbi Gmbh Und Ingenieurbau Mbh",
    "wof:placetype":"venue"
},
  "geometry": {"coordinates":[9.347651,48.528397],"type":"Point"}
}