{
  "type": "Feature",
  "properties": {
    "iso:country":"DE",
    "sg:address":"Rosenheimer Str. 3",
    "sg:city":"Bremen",
    "sg:phone":"+49 421/389930",
    "sg:postcode":"28219",
    "sg:province":"Bremen",
    "wof:name":"Timpe & Mock Verwaltungs Gmbh",
    "wof:placetype":"venue"
},
  "geometry": {"coordinates":[8.800081,53.106922],"type":"Point"}
}