{
  "type": "Feature",
  "properties": {
    "iso:country":"DE",
    "sg:address":"Friedrich-Eckardt-Str. 36",
    "sg:city":"Bad Salzungen",
    "sg:phone":"+49 3695/603819",
    "sg:postcode":"36433",
    "sg:province":"Th\u00fcringen",
    "wof:name":"Kurt Robe",
    "wof:placetype":"venue"
},
  "geometry": {"coordinates":[10.2391443253,50.8131446838],"type":"Point"}
}