{
  "type": "Feature",
  "properties": {
    "iso:country":"DE",
    "sg:address":"Beyenburger Str. 67",
    "sg:city":"Schwelm",
    "sg:phone":"+49 2336/15125",
    "sg:postcode":"58332",
    "sg:province":"Nordrhein-Westfalen",
    "wof:name":"Georg Quinke",
    "wof:placetype":"venue"
},
  "geometry": {"coordinates":[7.2980289459,51.2618675232],"type":"Point"}
}