{
  "type": "Feature",
  "properties": {
    "iso:country":"DE",
    "sg:address":"Erfurter Str. 38",
    "sg:city":"Ibbenb\u00fcren",
    "sg:phone":"+49 5451/6178",
    "sg:postcode":"49479",
    "sg:province":"Nordrhein-Westfalen",
    "wof:name":"R. Karisch",
    "wof:placetype":"venue"
},
  "geometry": {"coordinates":[7.6515188217,52.292591095],"type":"Point"}
}