{
  "type": "Feature",
  "properties": {
    "iso:country":"DE",
    "sg:address":"Breslauer Str 8",
    "sg:city":"\u00d6hringen",
    "sg:phone":"+49 7941/649110",
    "sg:postcode":"74613",
    "sg:province":"Baden-W\u00fcrttemberg",
    "wof:name":"Rw-soundsystem Ek",
    "wof:placetype":"venue"
},
  "geometry": {"coordinates":[9.492072,49.200176],"type":"Point"}
}