{
  "type": "Feature",
  "properties": {
    "iso:country":"DE",
    "sg:address":"Burgstr. 9",
    "sg:city":"Warstein",
    "sg:phone":"+49 2902/4576",
    "sg:postcode":"59581",
    "sg:province":"Nordrhein-Westfalen",
    "wof:name":"M. Thielenhaus",
    "wof:placetype":"venue"
},
  "geometry": {"coordinates":[8.2790803909,51.4298934937],"type":"Point"}
}