{
  "type": "Feature",
  "properties": {
    "iso:country":"DE",
    "sg:address":"Baumgartenstr. 13",
    "sg:city":"Schwalmstadt",
    "sg:phone":"+49 6691/2903",
    "sg:postcode":"34613",
    "sg:province":"Hessen",
    "wof:name":"Willi Kl\u00f6s",
    "wof:placetype":"venue"
},
  "geometry": {"coordinates":[9.213959,50.948948],"type":"Point"}
}