{
  "type": "Feature",
  "properties": {
    "iso:country":"DE",
    "sg:address":"Wacholderbergstr. 21",
    "sg:city":"Steinheim",
    "sg:phone":"+49 7144/21465",
    "sg:postcode":"71711",
    "sg:province":"Baden-W\u00fcrttemberg",
    "wof:name":"Heinz Kraft",
    "wof:placetype":"venue"
},
  "geometry": {"coordinates":[9.259047,48.961868],"type":"Point"}
}