{
  "type": "Feature",
  "properties": {
    "iso:country":"DE",
    "sg:address":"Gustav-Freytag-Str. 1",
    "sg:city":"Plauen",
    "sg:postcode":"08525",
    "sg:province":"Sachsen",
    "wof:name":"Bcv Agentur Jens Forberg Gmbh & Co. Kg",
    "wof:placetype":"venue"
},
  "geometry": {"coordinates":[12.1213378906,50.5136146545],"type":"Point"}
}