{
  "type": "Feature",
  "properties": {
    "iso:country":"DE",
    "sg:address":"Schafbergstr. 7",
    "sg:city":"Bautzen",
    "sg:phone":"+49 3591/22537",
    "sg:postcode":"02625",
    "sg:province":"Sachsen",
    "wof:name":"Nadelwitzer Pispub",
    "wof:placetype":"venue"
},
  "geometry": {"coordinates":[14.4588680267,51.1784286499],"type":"Point"}
}