{
  "type": "Feature",
  "properties": {
    "iso:country":"DE",
    "sg:address":"K\u00f6lner Platz 1",
    "sg:city":"M\u00fcnchen",
    "sg:phone":"+49 89/3079310",
    "sg:postcode":"80804",
    "sg:province":"Bayern",
    "wof:name":"Institut F\u00fcr Diabetesforschung",
    "wof:placetype":"venue"
},
  "geometry": {"coordinates":[11.5778627396,48.1701545715],"type":"Point"}
}