{
  "type": "Feature",
  "properties": {
    "iso:country":"DE",
    "sg:address":"Auf den H\u00f6rnern 3",
    "sg:city":"Brandshagen",
    "sg:phone":"+49 38328/80305",
    "sg:postcode":"18519",
    "sg:province":"Mecklenburg-Vorpommern",
    "wof:name":"Versicherungsb\u00fcro Petra B\u00f6ttcher E. K.",
    "wof:placetype":"venue"
},
  "geometry": {"coordinates":[13.1784467697,54.2387504578],"type":"Point"}
}