{
  "type": "Feature",
  "properties": {
    "iso:country":"DE",
    "sg:address":"Zementwerkstr. 3",
    "sg:city":"Burglengenfeld",
    "sg:phone":"+49 9471/7070",
    "sg:postcode":"93133",
    "sg:province":"Bayern",
    "wof:name":"Heidelberger Zement Ag",
    "wof:placetype":"venue"
},
  "geometry": {"coordinates":[12.032959938,49.212928772],"type":"Point"}
}