{
  "type": "Feature",
  "properties": {
    "iso:country":"DE",
    "sg:address":"Promenadenstr. 108",
    "sg:city":"G\u00f6rlitz",
    "sg:postcode":"02827",
    "sg:province":"Sachsen",
    "wof:name":"Handke Bauges. Mbh",
    "wof:placetype":"venue"
},
  "geometry": {"coordinates":[14.943949,51.13316],"type":"Point"}
}