{
  "type": "Feature",
  "properties": {
    "iso:country":"DE",
    "sg:address":"Bauhofstr. 30",
    "sg:city":"Wismar",
    "sg:phone":"+49 3841/213522",
    "sg:postcode":"23966",
    "sg:province":"Mecklenburg-Vorpommern",
    "wof:name":"T. Wenzel",
    "wof:placetype":"venue"
},
  "geometry": {"coordinates":[11.4701356888,53.8939552307],"type":"Point"}
}