{
  "type": "Feature",
  "properties": {
    "iso:country":"DE",
    "sg:address":"An der Lehmkuhl 2a",
    "sg:city":"Rheinberg",
    "sg:phone":"+49 2843/2071",
    "sg:postcode":"47495",
    "sg:province":"Nordrhein-Westfalen",
    "wof:name":"Speditrans Befrachtungs- Schiffahrt Spedition Gmbh",
    "wof:placetype":"venue"
},
  "geometry": {"coordinates":[6.62413311,51.5379371643],"type":"Point"}
}