{
  "type": "Feature",
  "properties": {
    "iso:country":"DE",
    "sg:address":"Freiburger Str. 2 a",
    "sg:city":"Neuenburg",
    "sg:phone":"+49 7631/79090",
    "sg:postcode":"79395",
    "sg:province":"Baden-W\u00fcrttemberg",
    "wof:name":"G\u00e4stehaus Anika Garni",
    "wof:placetype":"venue"
},
  "geometry": {"coordinates":[7.5690498352,47.8128204346],"type":"Point"}
}