{
  "type": "Feature",
  "properties": {
    "iso:country":"DE",
    "sg:address":"D\u00f6nhoffstr. 25",
    "sg:city":"Solingen",
    "sg:phone":"+49 212/205089",
    "sg:postcode":"42655",
    "sg:province":"Nordrhein-Westfalen",
    "wof:name":"Meyer & D\u00f6rner Gmbh",
    "wof:placetype":"venue"
},
  "geometry": {"coordinates":[7.0679659843,51.1745033264],"type":"Point"}
}