{
  "type": "Feature",
  "properties": {
    "iso:country":"DE",
    "sg:address":"Johannes-Palm-Str. 33",
    "sg:city":"Ulm",
    "sg:phone":"+49 731/41290",
    "sg:postcode":"89079",
    "sg:province":"Baden-W\u00fcrttemberg",
    "wof:name":"Robert Kr\u00f6ner",
    "wof:placetype":"venue"
},
  "geometry": {"coordinates":[9.9793548584,48.3608703613],"type":"Point"}
}