{
  "type": "Feature",
  "properties": {
    "iso:country":"DE",
    "sg:address":"Riethornweg 17",
    "sg:city":"Burgdorf",
    "sg:phone":"+49 5136/87197",
    "sg:postcode":"31303",
    "sg:province":"Niedersachsen",
    "wof:name":"K. Biallas Ingenieur",
    "wof:placetype":"venue"
},
  "geometry": {"coordinates":[10.0295743942,52.4589805603],"type":"Point"}
}