{
  "type": "Feature",
  "properties": {
    "iso:country":"DE",
    "sg:address":"Prozessionsweg 12",
    "sg:city":"Neuenkirchen",
    "sg:phone":"+49 5973/2530",
    "sg:postcode":"48485",
    "sg:province":"Nordrhein-Westfalen",
    "wof:name":"Hermann Veltmann",
    "wof:placetype":"venue"
},
  "geometry": {"coordinates":[7.3691310883,52.2452125549],"type":"Point"}
}