{
  "type": "Feature",
  "properties": {
    "iso:country":"DE",
    "sg:address":"Kaiserstr. 14",
    "sg:city":"Ludwigsburg",
    "sg:phone":"+49 7141/24875",
    "sg:postcode":"71636",
    "sg:province":"Baden-W\u00fcrttemberg",
    "wof:name":"Schulbibliothek Im Bildungszentrum West",
    "wof:placetype":"venue"
},
  "geometry": {"coordinates":[9.177399,48.898235],"type":"Point"}
}