{
  "type": "Feature",
  "properties": {
    "iso:country":"DE",
    "sg:address":"Forstmannstr. 81",
    "sg:city":"Essen",
    "sg:phone":"+49 201/406414",
    "sg:postcode":"45239",
    "sg:province":"Nordrhein-Westfalen",
    "wof:name":"M. Meyer",
    "wof:placetype":"venue"
},
  "geometry": {"coordinates":[7.005032,51.396973],"type":"Point"}
}