{
  "type": "Feature",
  "properties": {
    "iso:country":"DE",
    "sg:address":"Frankfurter Landstr. 102",
    "sg:city":"Darmstadt",
    "sg:phone":"+49 6151/375909",
    "sg:postcode":"64291",
    "sg:province":"Hessen",
    "wof:name":"Harry Tack",
    "wof:placetype":"venue"
},
  "geometry": {"coordinates":[8.6565351486,49.9075660706],"type":"Point"}
}