{
  "type": "Feature",
  "properties": {
    "iso:country":"DE",
    "sg:address":"Swinem\u00fcnder Str. 43",
    "sg:city":"Usedom",
    "sg:phone":"+49 38372/70292",
    "sg:postcode":"17406",
    "sg:province":"Mecklenburg-Vorpommern",
    "wof:name":"Gerhard Uecker Gmbh",
    "wof:placetype":"venue"
},
  "geometry": {"coordinates":[13.9213762283,53.8758659363],"type":"Point"}
}