{
  "type": "Feature",
  "properties": {
    "iso:country":"DE",
    "sg:address":"Hohenzollernstr. 43",
    "sg:city":"M\u00fcnchen",
    "sg:phone":"+49 89/33089640",
    "sg:postcode":"80801",
    "sg:province":"Bayern",
    "wof:name":"Prego Leibold Gmbh",
    "wof:placetype":"venue"
},
  "geometry": {"coordinates":[11.5765562057,48.1600799561],"type":"Point"}
}