{
  "type": "Feature",
  "properties": {
    "iso:country":"DE",
    "sg:address":"Schlingstr. 9",
    "sg:city":"Rinteln",
    "sg:phone":"+49 5751/74082",
    "sg:postcode":"31737",
    "sg:province":"Niedersachsen",
    "wof:name":"Heinz Schermer Steuerberater",
    "wof:placetype":"venue"
},
  "geometry": {"coordinates":[9.0791959763,52.1929588318],"type":"Point"}
}