{
  "type": "Feature",
  "properties": {
    "iso:country":"DE",
    "sg:address":"Meringer Str. 1",
    "sg:city":"Friedberg",
    "sg:phone":"+49 821/62051",
    "sg:postcode":"86316",
    "sg:province":"Bayern",
    "wof:name":"F. G. Reithemann",
    "wof:placetype":"venue"
},
  "geometry": {"coordinates":[10.9527044296,48.3552513123],"type":"Point"}
}