{
  "type": "Feature",
  "properties": {
    "iso:country":"DE",
    "sg:address":"Fohlenweide 32",
    "sg:city":"Bremen",
    "sg:phone":"+49 421/25203637",
    "sg:postcode":"28355",
    "sg:province":"Bremen",
    "wof:name":"Hast Stadt & Land Immobilien- Und Baubetreuungs-gmbh",
    "wof:placetype":"venue"
},
  "geometry": {"coordinates":[8.9081611633,53.1083335876],"type":"Point"}
}