{
  "type": "Feature",
  "properties": {
    "iso:country":"DE",
    "sg:address":"Braidbacher Str.",
    "sg:city":"Bastheim",
    "sg:phone":"+49 9773/422",
    "sg:postcode":"97654",
    "sg:province":"Bayern",
    "wof:name":"O. Kirchner",
    "wof:placetype":"venue"
},
  "geometry": {"coordinates":[10.1754245758,50.3945808411],"type":"Point"}
}