{
  "type": "Feature",
  "properties": {
    "iso:country":"DE",
    "sg:address":"Friedensplatz 1",
    "sg:city":"Zuchau",
    "sg:phone":"+49 39295/27231",
    "sg:postcode":"39240",
    "sg:province":"Sachsen-Anhalt",
    "wof:name":"Martin K\u00fchne",
    "wof:placetype":"venue"
},
  "geometry": {"coordinates":[11.85469,51.853718],"type":"Point"}
}