{
  "type": "Feature",
  "properties": {
    "iso:country":"DE",
    "sg:address":"D\u00fcrerstr. 17",
    "sg:city":"Dresden",
    "sg:phone":"+49 351/4421363",
    "sg:postcode":"01069",
    "sg:province":"Sachsen",
    "wof:name":"Ingenieurb\u00fcro Michael Franke",
    "wof:placetype":"venue"
},
  "geometry": {"coordinates":[13.756729126,51.0523948669],"type":"Point"}
}