{
  "type": "Feature",
  "properties": {
    "iso:country":"DE",
    "sg:address":"Obere J\u00e4gergasse 1",
    "sg:city":"Passau",
    "sg:phone":"+49 851/2318",
    "sg:postcode":"94032",
    "sg:province":"Bayern",
    "wof:name":"Sozialberatung F. Werdende M\u00fctter-diak. Werk",
    "wof:placetype":"venue"
},
  "geometry": {"coordinates":[13.460098,48.573654],"type":"Point"}
}