{
  "type": "Feature",
  "properties": {
    "iso:country":"DE",
    "sg:address":"Welschneureuter Str. 18",
    "sg:city":"Karlsruhe",
    "sg:phone":"+49 4972/1706689",
    "sg:postcode":"76149",
    "sg:province":"Baden-W\u00fcrttemberg",
    "wof:name":"G\u00dcnter Weber Gmbh",
    "wof:placetype":"venue"
},
  "geometry": {"coordinates":[8.372379303,49.0451469421],"type":"Point"}
}