{
  "type": "Feature",
  "properties": {
    "iso:country":"DE",
    "sg:address":"L\u00f6wenwall 8",
    "sg:city":"Braunschweig",
    "sg:postcode":"38100",
    "sg:province":"Niedersachsen",
    "wof:name":"Raabe Gesellschaft Braunschweig",
    "wof:placetype":"venue"
},
  "geometry": {"coordinates":[10.5292348862,52.259098053],"type":"Point"}
}