{
  "type": "Feature",
  "properties": {
    "iso:country":"DE",
    "sg:address":"Buchenhagener Str. 4",
    "sg:city":"Baunatal",
    "sg:postcode":"34225",
    "sg:province":"Hessen",
    "wof:name":"Rudolph Verwaltungs Kg",
    "wof:placetype":"venue"
},
  "geometry": {"coordinates":[9.4565868378,51.2346954346],"type":"Point"}
}