{
  "type": "Feature",
  "properties": {
    "iso:country":"DE",
    "sg:address":"Wasserkr\u00fcger Weg 127",
    "sg:city":"M\u00f6lln",
    "sg:phone":"+49 4542/4600",
    "sg:postcode":"23879",
    "sg:province":"Schleswig-Holstein",
    "wof:name":"Dr. Med. Ulrich Geisemeyer Arzt F\u00fcr Sportmedizin",
    "wof:placetype":"venue"
},
  "geometry": {"coordinates":[10.690621376,53.6158981323],"type":"Point"}
}