{
  "type": "Feature",
  "properties": {
    "iso:country":"DE",
    "sg:address":"Hauptstr. 25",
    "sg:city":"M\u00f6nchberg",
    "sg:phone":"+49 9374/99955",
    "sg:postcode":"63933",
    "sg:province":"Bayern",
    "wof:name":"Wa\u00dfmer",
    "wof:placetype":"venue"
},
  "geometry": {"coordinates":[9.2652740479,49.7918739319],"type":"Point"}
}