{
  "type": "Feature",
  "properties": {
    "iso:country":"DE",
    "sg:address":"Kammerhofweg 6",
    "sg:city":"Riedstadt",
    "sg:phone":"+49 6158/71218",
    "sg:postcode":"64560",
    "sg:province":"Hessen",
    "wof:name":"Irmgard Petri",
    "wof:placetype":"venue"
},
  "geometry": {"coordinates":[8.438065,49.855862],"type":"Point"}
}