{
  "type": "Feature",
  "properties": {
    "iso:country":"DE",
    "sg:address":"Sudetenstr. 3",
    "sg:city":"Friedrichsdorf",
    "sg:postcode":"61381",
    "sg:province":"Hessen",
    "wof:name":"Lang Import Gmbh",
    "wof:placetype":"venue"
},
  "geometry": {"coordinates":[8.6474065781,50.2453231812],"type":"Point"}
}