{
  "type": "Feature",
  "properties": {
    "iso:country":"DE",
    "sg:address":"Abnobastrasse 5",
    "sg:city":"Pforzheim",
    "sg:phone":"+49 7231/1559525",
    "sg:postcode":"75175",
    "sg:province":"Baden-W\u00fcrttemberg",
    "wof:name":"Care & Beauty",
    "wof:placetype":"venue"
},
  "geometry": {"coordinates":[8.7136058807,48.8910751343],"type":"Point"}
}