{
  "type": "Feature",
  "properties": {
    "iso:country":"DE",
    "sg:address":"Reuthweg",
    "sg:city":"Hammelburg",
    "sg:postcode":"97762",
    "sg:province":"Bayern",
    "wof:name":"Sc Frankonia 1921 Diebach",
    "wof:placetype":"venue"
},
  "geometry": {"coordinates":[9.8377017975,50.1248970032],"type":"Point"}
}