{
  "type": "Feature",
  "properties": {
    "iso:country":"DE",
    "sg:address":"Am Dorfgarten 1",
    "sg:city":"Frankfurt",
    "sg:phone":"+49 69/5484442",
    "sg:postcode":"60435",
    "sg:province":"Hessen",
    "wof:name":"Sanit\u00e4tshaus Reininger",
    "wof:placetype":"venue"
},
  "geometry": {"coordinates":[8.6923122406,50.154876709],"type":"Point"}
}