{
  "type": "Feature",
  "properties": {
    "iso:country":"DE",
    "sg:address":"Rupbachstr. 23",
    "sg:city":"K\u00f6rdorf",
    "sg:phone":"+49 6486/8450",
    "sg:postcode":"56370",
    "sg:province":"Rheinland-Pfalz",
    "wof:name":"W. Maxeiner",
    "wof:placetype":"venue"
},
  "geometry": {"coordinates":[7.922597,50.288528],"type":"Point"}
}