{
  "type": "Feature",
  "properties": {
    "iso:country":"DE",
    "sg:address":"Barbarakirchgang 6",
    "sg:city":"Essen",
    "sg:phone":"+49 201/234614",
    "sg:postcode":"45139",
    "sg:province":"Nordrhein-Westfalen",
    "wof:name":"Keil Gmbh & Co.",
    "wof:placetype":"venue"
},
  "geometry": {"coordinates":[7.029157,51.460793],"type":"Point"}
}