{
  "type": "Feature",
  "properties": {
    "iso:country":"DE",
    "sg:address":"Alexander-Fleming-Str.",
    "sg:city":"Planegg",
    "sg:phone":"+49 89/8595139",
    "sg:postcode":"82152",
    "sg:province":"Bayern",
    "wof:name":"Franz Dullinger",
    "wof:placetype":"venue"
},
  "geometry": {"coordinates":[11.4495191574,48.104221344],"type":"Point"}
}