{
  "type": "Feature",
  "properties": {
    "iso:country":"DE",
    "sg:address":"Frankfurter Str. 34",
    "sg:city":"Gedern",
    "sg:phone":"+49 6045/1242",
    "sg:postcode":"63688",
    "sg:province":"Hessen",
    "wof:name":"Karl Franz Eisenwaren",
    "wof:placetype":"venue"
},
  "geometry": {"coordinates":[9.1965579987,50.4214706421],"type":"Point"}
}