{
  "type": "Feature",
  "properties": {
    "iso:country":"DE",
    "sg:address":"Marderweg 23",
    "sg:city":"Bielefeld",
    "sg:phone":"+49 5205/7647",
    "sg:postcode":"33689",
    "sg:province":"Nordrhein-Westfalen",
    "wof:name":"Christhard Ehrig Garten- Und Landschafts-",
    "wof:placetype":"venue"
},
  "geometry": {"coordinates":[8.584975,51.937527],"type":"Point"}
}