{
  "type": "Feature",
  "properties": {
    "iso:country":"DE",
    "sg:address":"Bahnhofstr. 13",
    "sg:city":"Westerkappeln",
    "sg:phone":"+49 5404/950810",
    "sg:postcode":"49492",
    "sg:province":"Nordrhein-Westfalen",
    "wof:name":"G\u00f6rtem\u00f6ller",
    "wof:placetype":"venue"
},
  "geometry": {"coordinates":[7.8774237633,52.3160858154],"type":"Point"}
}