{
  "type": "Feature",
  "properties": {
    "iso:country":"DE",
    "sg:address":"Rosenstr. 9",
    "sg:city":"Wagh\u00e4usel",
    "sg:phone":"+49 7254/8631",
    "sg:postcode":"68753",
    "sg:province":"Baden-W\u00fcrttemberg",
    "wof:name":"Karl Bechle",
    "wof:placetype":"venue"
},
  "geometry": {"coordinates":[8.552109,49.241829],"type":"Point"}
}