{
  "type": "Feature",
  "properties": {
    "iso:country":"DE",
    "sg:address":"Leidlinger Str. 13",
    "sg:city":"Oberhausen",
    "sg:phone":"+49 8435/356",
    "sg:postcode":"86697",
    "sg:province":"Bayern",
    "wof:name":"Josef Eubel",
    "wof:placetype":"venue"
},
  "geometry": {"coordinates":[11.102011,48.693192],"type":"Point"}
}