{
  "type": "Feature",
  "properties": {
    "iso:country":"DE",
    "sg:address":"Hauptstr. 65",
    "sg:city":"Bad Saulgau",
    "sg:phone":"+49 7581/4996",
    "sg:postcode":"88348",
    "sg:province":"Baden-W\u00fcrttemberg",
    "wof:name":"H. Sorg",
    "wof:placetype":"venue"
},
  "geometry": {"coordinates":[9.5008115768,48.0165748596],"type":"Point"}
}