{
  "type": "Feature",
  "properties": {
    "iso:country":"DE",
    "sg:address":"Kronprinzstr. 19",
    "sg:city":"Stuttgart",
    "sg:phone":"+49 711/227500",
    "sg:postcode":"70173",
    "sg:province":"Baden-W\u00fcrttemberg",
    "wof:name":"Wkv Leasing Gmbh",
    "wof:placetype":"venue"
},
  "geometry": {"coordinates":[9.1741628647,48.7748413086],"type":"Point"}
}