{
  "type": "Feature",
  "properties": {
    "iso:country":"DE",
    "sg:address":"Venloer Str. 94",
    "sg:city":"Pulheim",
    "sg:phone":"+49 2238/965500",
    "sg:postcode":"50259",
    "sg:province":"Nordrhein-Westfalen",
    "wof:name":"Udo Meuser Steuerberater",
    "wof:placetype":"venue"
},
  "geometry": {"coordinates":[6.8055639267,50.9972419739],"type":"Point"}
}