{
  "type": "Feature",
  "properties": {
    "iso:country":"DE",
    "sg:address":"Bahnhofstr. 21",
    "sg:city":"Eilenburg",
    "sg:phone":"+49 3423/3438",
    "sg:postcode":"04838",
    "sg:province":"Sachsen",
    "wof:name":"Bahnhofsgastst\u00e4tte",
    "wof:placetype":"venue"
},
  "geometry": {"coordinates":[12.6353330612,51.4554748535],"type":"Point"}
}