{
  "type": "Feature",
  "properties": {
    "iso:country":"DE",
    "sg:address":"Kraftwerkstr. 145",
    "sg:city":"Grenzach-Wyhlen",
    "sg:postcode":"79639",
    "sg:province":"Baden-W\u00fcrttemberg",
    "wof:name":"Domizil Bau Gmbh",
    "wof:placetype":"venue"
},
  "geometry": {"coordinates":[7.703705,47.543636],"type":"Point"}
}