{
  "type": "Feature",
  "properties": {
    "iso:country":"DE",
    "sg:address":"Webergasse 6",
    "sg:city":"Aschaffenburg",
    "sg:postcode":"63739",
    "sg:province":"Bayern",
    "wof:name":"Kath. \u00d6ffentliche Bibliothek Unserer Lieben Frau",
    "wof:placetype":"venue"
},
  "geometry": {"coordinates":[9.142963,49.973595],"type":"Point"}
}