{
  "type": "Feature",
  "properties": {
    "iso:country":"DE",
    "sg:address":"Ringstr. 12",
    "sg:city":"Annweiler",
    "sg:phone":"+49 6346/7268",
    "sg:postcode":"76855",
    "sg:province":"Rheinland-Pfalz",
    "wof:name":"Wilhelm Lebk\u00fccher Architekt",
    "wof:placetype":"venue"
},
  "geometry": {"coordinates":[7.993904,49.215366],"type":"Point"}
}