{
  "type": "Feature",
  "properties": {
    "iso:country":"DE",
    "sg:address":"Glatzer Str. 13",
    "sg:city":"Karlsruhe",
    "sg:phone":"+49 721/681817",
    "sg:postcode":"76139",
    "sg:province":"Baden-W\u00fcrttemberg",
    "wof:name":"Gerd K\u00f6hler Ingenieur Architekt",
    "wof:placetype":"venue"
},
  "geometry": {"coordinates":[8.4447145462,49.0289573669],"type":"Point"}
}