{
  "type": "Feature",
  "properties": {
    "iso:country":"DE",
    "sg:address":"H\u00f6rdemannshof 20",
    "sg:city":"Dortmund",
    "sg:phone":"+49 231/352178",
    "sg:postcode":"44359",
    "sg:province":"Nordrhein-Westfalen",
    "wof:name":"Wilhelm Cremer",
    "wof:placetype":"venue"
},
  "geometry": {"coordinates":[7.388942,51.555649],"type":"Point"}
}