{
  "type": "Feature",
  "properties": {
    "iso:country":"DE",
    "sg:address":"Wassersteinchen 10",
    "sg:city":"Wertheim",
    "sg:phone":"+49 9342/7396",
    "sg:postcode":"97877",
    "sg:province":"Baden-W\u00fcrttemberg",
    "wof:name":"E. Oberdorf Landhandel Kg",
    "wof:placetype":"venue"
},
  "geometry": {"coordinates":[9.590643,49.72678],"type":"Point"}
}