{
  "type": "Feature",
  "properties": {
    "iso:country":"DE",
    "sg:address":"Bamberger Str. 22",
    "sg:city":"Untersiemau",
    "sg:phone":"+49 9565/921365",
    "sg:postcode":"96253",
    "sg:province":"Bayern",
    "wof:name":"Apfelbaum Erlebnisgasthof",
    "wof:placetype":"venue"
},
  "geometry": {"coordinates":[10.9727878571,50.2027854919],"type":"Point"}
}