{
  "type": "Feature",
  "properties": {
    "iso:country":"DE",
    "sg:address":"M\u00fcnsterstr. 59",
    "sg:city":"Lienen",
    "sg:phone":"+49 5484/325",
    "sg:postcode":"49536",
    "sg:province":"Nordrhein-Westfalen",
    "wof:name":"August Kiewitt",
    "wof:placetype":"venue"
},
  "geometry": {"coordinates":[7.854557,52.10833],"type":"Point"}
}