{
  "type": "Feature",
  "properties": {
    "iso:country":"DE",
    "sg:address":"Wiesenstr. 5",
    "sg:city":"Hadamar",
    "sg:phone":"+49 6433/2888",
    "sg:postcode":"65589",
    "sg:province":"Hessen",
    "wof:name":"Gerhard Emmelmann",
    "wof:placetype":"venue"
},
  "geometry": {"coordinates":[8.0963916779,50.4563293457],"type":"Point"}
}