{
  "type": "Feature",
  "properties": {
    "iso:country":"DE",
    "sg:address":"Hauptstr. 35",
    "sg:city":"Vollmersbach",
    "sg:phone":"+49 6781/31321",
    "sg:postcode":"55758",
    "sg:province":"Rheinland-Pfalz",
    "wof:name":"Oswald Scholtes Gmbh",
    "wof:placetype":"venue"
},
  "geometry": {"coordinates":[7.3078022003,49.7422447205],"type":"Point"}
}