{
  "type": "Feature",
  "properties": {
    "iso:country":"DE",
    "sg:address":"Am Bergweg 3",
    "sg:city":"Gro\u00dfostheim",
    "sg:phone":"+49 6026/4758",
    "sg:postcode":"63762",
    "sg:province":"Bayern",
    "wof:name":"Forg & Ghezzi",
    "wof:placetype":"venue"
},
  "geometry": {"coordinates":[9.059697,49.906021],"type":"Point"}
}