{
  "type": "Feature",
  "properties": {
    "iso:country":"DE",
    "sg:address":"Strelitzer Str. 21",
    "sg:city":"Feldberg",
    "sg:phone":"+49 39831/20554",
    "sg:postcode":"17258",
    "sg:province":"Mecklenburg-Vorpommern",
    "wof:name":"Horst Berg",
    "wof:placetype":"venue"
},
  "geometry": {"coordinates":[13.4353246689,53.3363723755],"type":"Point"}
}