{
  "type": "Feature",
  "properties": {
    "iso:country":"DE",
    "sg:address":"Ugenhof 1",
    "sg:city":"Herbrechtingen",
    "sg:phone":"+49 7324/981030",
    "sg:postcode":"89542",
    "sg:province":"Baden-W\u00fcrttemberg",
    "wof:name":"Gasthaus Hans Ziegler",
    "wof:placetype":"venue"
},
  "geometry": {"coordinates":[10.1036844254,48.6333007812],"type":"Point"}
}