{
  "type": "Feature",
  "properties": {
    "iso:country":"DE",
    "sg:address":"Josef-Schregel-Str. 9",
    "sg:city":"D\u00fcren",
    "sg:phone":"+49 2421/15543",
    "sg:postcode":"52349",
    "sg:province":"Nordrhein-Westfalen",
    "wof:name":"Ivo Bellenzier",
    "wof:placetype":"venue"
},
  "geometry": {"coordinates":[6.482216,50.805916],"type":"Point"}
}