{
  "type": "Feature",
  "properties": {
    "iso:country":"DE",
    "sg:address":"Fabrikstr. 8",
    "sg:city":"Freising",
    "sg:phone":"+49 8161/50611",
    "sg:postcode":"85354",
    "sg:province":"Bayern",
    "wof:name":"Shin-etsu Handotai Europe Ltd.",
    "wof:placetype":"venue"
},
  "geometry": {"coordinates":[11.742008,48.396297],"type":"Point"}
}