{
  "type": "Feature",
  "properties": {
    "iso:country":"DE",
    "sg:address":"Schiffstr. 2",
    "sg:city":"Freiburg",
    "sg:phone":"+49 761/22558",
    "sg:postcode":"79098",
    "sg:province":"Baden-W\u00fcrttemberg",
    "wof:name":"C. H. K\u00fcnz",
    "wof:placetype":"venue"
},
  "geometry": {"coordinates":[7.8506321907,47.996963501],"type":"Point"}
}