{
  "type": "Feature",
  "properties": {
    "iso:country":"DE",
    "sg:address":"Forststr. 137",
    "sg:city":"Potsdam",
    "sg:phone":"+49 331/964568",
    "sg:postcode":"14471",
    "sg:province":"Brandenburg",
    "wof:name":"Tlm Transport Und Logistik Gmbh",
    "wof:placetype":"venue"
},
  "geometry": {"coordinates":[13.0153865814,52.3814506531],"type":"Point"}
}