{
  "type": "Feature",
  "properties": {
    "iso:country":"DE",
    "sg:address":"Stra\u00dfe der Einheit 106",
    "sg:city":"Heringen",
    "sg:phone":"+49 36333/70591",
    "sg:postcode":"99765",
    "sg:province":"Th\u00fcringen",
    "wof:name":"Brigitte Jendricke",
    "wof:placetype":"venue"
},
  "geometry": {"coordinates":[10.878722,51.446857],"type":"Point"}
}