{
  "type": "Feature",
  "properties": {
    "iso:country":"DE",
    "sg:address":"Postfach 1241",
    "sg:city":"Geilenkirchen",
    "sg:phone":"+31 45 531 2428",
    "sg:postcode":"52502",
    "sg:province":"Nordrhein-Westfalen",
    "wof:name":"Bnl-radio",
    "wof:placetype":"venue"
},
  "geometry": {"coordinates":[6.12211,50.965488],"type":"Point"}
}