{
  "type": "Feature",
  "properties": {
    "iso:country":"DE",
    "sg:address":"Rettenbach 1",
    "sg:city":"Sankt Englmar",
    "sg:phone":"+49 9965/247",
    "sg:postcode":"94379",
    "sg:province":"Bayern",
    "wof:name":"Gasthof Zum Hirschenstein",
    "wof:placetype":"venue"
},
  "geometry": {"coordinates":[12.8423633575,48.9819908142],"type":"Point"}
}