{
  "type": "Feature",
  "properties": {
    "iso:country":"DE",
    "sg:address":"Waldstr. 2",
    "sg:city":"Braunfels",
    "sg:phone":"+49 6442/928723",
    "sg:postcode":"35619",
    "sg:province":"Hessen",
    "wof:name":"P. Neuhaus",
    "wof:placetype":"venue"
},
  "geometry": {"coordinates":[8.422741,50.500813],"type":"Point"}
}