{
  "type": "Feature",
  "properties": {
    "iso:country":"DE",
    "sg:address":"Flundernweg 14",
    "sg:city":"Stuttgart",
    "sg:phone":"+49 711/849090",
    "sg:postcode":"70378",
    "sg:province":"Baden-W\u00fcrttemberg",
    "wof:name":"Deutsches Sozialwerk Altenheim Stuttgart E.v.",
    "wof:placetype":"venue"
},
  "geometry": {"coordinates":[9.212366,48.843414],"type":"Point"}
}