{
  "type": "Feature",
  "properties": {
    "iso:country":"DE",
    "sg:address":"Am Pfarrholz 42",
    "sg:city":"Bielefeld",
    "sg:phone":"+49 4952/063574",
    "sg:postcode":"33739",
    "sg:province":"Nordrhein-Westfalen",
    "wof:name":"Kr\u00c4utica Pharma Gmbh & Co Kg",
    "wof:placetype":"venue"
},
  "geometry": {"coordinates":[8.506785,52.0961],"type":"Point"}
}