{
  "type": "Feature",
  "properties": {
    "iso:country":"DE",
    "sg:address":"Neue Str. 14",
    "sg:city":"Kurtscheid",
    "sg:phone":"+49 2634/2913",
    "sg:postcode":"56581",
    "sg:province":"Rheinland-Pfalz",
    "wof:name":"Via Consult Ing. Georg Schmitt Kg",
    "wof:placetype":"venue"
},
  "geometry": {"coordinates":[7.4650931358,50.5341110229],"type":"Point"}
}