{
  "type": "Feature",
  "properties": {
    "iso:country":"DE",
    "sg:address":"Dimpfelstr. 37",
    "sg:city":"Leipzig",
    "sg:phone":"+49 341/2311635",
    "sg:postcode":"04347",
    "sg:province":"Sachsen",
    "wof:name":"Hans-ernst H\u00e4ussler",
    "wof:placetype":"venue"
},
  "geometry": {"coordinates":[12.408903,51.355034],"type":"Point"}
}