{
  "type": "Feature",
  "properties": {
    "iso:country":"DE",
    "sg:address":"Thomas-M\u00fcntzer-Str. 5",
    "sg:city":"S\u00fcnna",
    "sg:phone":"+49 36962/25977",
    "sg:postcode":"36404",
    "sg:province":"Th\u00fcringen",
    "wof:name":"Limburg Ohg",
    "wof:placetype":"venue"
},
  "geometry": {"coordinates":[9.999659,50.796276],"type":"Point"}
}