{
  "type": "Feature",
  "properties": {
    "iso:country":"DE",
    "sg:address":"Bahnhofstr. 5",
    "sg:city":"Burgst\u00e4dt",
    "sg:phone":"+49 3724/3007",
    "sg:postcode":"09217",
    "sg:province":"Sachsen",
    "wof:name":"Elefanten-apotheke",
    "wof:placetype":"venue"
},
  "geometry": {"coordinates":[12.811923,50.916611],"type":"Point"}
}