{
  "type": "Feature",
  "properties": {
    "iso:country":"DE",
    "sg:address":"Ringstr. 13",
    "sg:city":"Schwendi",
    "sg:phone":"+49 7353/3577",
    "sg:postcode":"88477",
    "sg:province":"Baden-W\u00fcrttemberg",
    "wof:name":"Maier Bautechnik Gmbh",
    "wof:placetype":"venue"
},
  "geometry": {"coordinates":[9.95637,48.198818],"type":"Point"}
}