{
  "type": "Feature",
  "properties": {
    "iso:country":"DE",
    "sg:address":"Bahnhofstr. 18",
    "sg:city":"Ostritz",
    "sg:phone":"+49 35823/86593",
    "sg:postcode":"02899",
    "sg:province":"Sachsen",
    "wof:name":"Rodil Verwaltungs- Dienstleistungen Gmbh",
    "wof:placetype":"venue"
},
  "geometry": {"coordinates":[14.9354953766,51.0164413452],"type":"Point"}
}