{
  "type": "Feature",
  "properties": {
    "iso:country":"DE",
    "sg:address":"Ornachstr. 18",
    "sg:city":"Fischen",
    "sg:phone":"+49 8326/7734",
    "sg:postcode":"87538",
    "sg:province":"Bayern",
    "wof:name":"P. Ott Masseur",
    "wof:placetype":"venue"
},
  "geometry": {"coordinates":[10.233462,47.46067],"type":"Point"}
}