{
  "type": "Feature",
  "properties": {
    "iso:country":"DE",
    "sg:address":"Dr.-Pilet-Spur 7",
    "sg:city":"Feldberg",
    "sg:phone":"+49 7676/180",
    "sg:postcode":"79868",
    "sg:province":"Baden-W\u00fcrttemberg",
    "wof:name":"Hotel Feldberger Hof Banhardt Gmbh",
    "wof:placetype":"venue"
},
  "geometry": {"coordinates":[8.0368499756,47.8607177734],"type":"Point"}
}