{
  "type": "Feature",
  "properties": {
    "iso:country":"DE",
    "sg:address":"Pontivystr. 13",
    "sg:city":"Wesseling",
    "sg:phone":"+49 2236/42447",
    "sg:postcode":"50389",
    "sg:province":"Nordrhein-Westfalen",
    "wof:name":"J\u00f6rg Annas",
    "wof:placetype":"venue"
},
  "geometry": {"coordinates":[6.9812,50.825722],"type":"Point"}
}