{
  "type": "Feature",
  "properties": {
    "iso:country":"DE",
    "sg:address":"Feldmark 9",
    "sg:city":"Neubrandenburg",
    "sg:phone":"+49 395/45340",
    "sg:postcode":"17034",
    "sg:province":"Mecklenburg-Vorpommern",
    "wof:name":"Buderus Heiztechnik Gmbh",
    "wof:placetype":"venue"
},
  "geometry": {"coordinates":[13.2854404449,53.5850715637],"type":"Point"}
}