{
  "type": "Feature",
  "properties": {
    "iso:country":"DE",
    "sg:address":"Schillerstr. 6",
    "sg:city":"Marl",
    "sg:phone":"+49 2365/12311",
    "sg:postcode":"45768",
    "sg:province":"Nordrhein-Westfalen",
    "wof:name":"Haus St\u00fcer Inh. Jutta Richter",
    "wof:placetype":"venue"
},
  "geometry": {"coordinates":[7.0814619064,51.6477661133],"type":"Point"}
}