{
  "type": "Feature",
  "properties": {
    "iso:country":"DE",
    "sg:address":"Carl-von-Ossietzky-Str. 57 a",
    "sg:city":"Weimar",
    "sg:phone":"+49 3643/83630",
    "sg:postcode":"99423",
    "sg:province":"Th\u00fcringen",
    "wof:name":"Corax Marketing E. K.",
    "wof:placetype":"venue"
},
  "geometry": {"coordinates":[11.3282527924,50.9881362915],"type":"Point"}
}