{
  "type": "Feature",
  "properties": {
    "iso:country":"DE",
    "sg:address":"Friedensstr. 39",
    "sg:city":"Hamm",
    "sg:phone":"+49 6246/7390",
    "sg:postcode":"67580",
    "sg:province":"Rheinland-Pfalz",
    "wof:name":"Hanz-peter Blum Rechtsanwalt",
    "wof:placetype":"venue"
},
  "geometry": {"coordinates":[8.4275331497,49.7328224182],"type":"Point"}
}