{
  "type": "Feature",
  "properties": {
    "iso:country":"DE",
    "sg:address":"Unnaer Str. 20",
    "sg:city":"Menden",
    "sg:postcode":"58706",
    "sg:province":"Nordrhein-Westfalen",
    "wof:name":"Medenta Dental Gmbh",
    "wof:placetype":"venue"
},
  "geometry": {"coordinates":[7.791826,51.440178],"type":"Point"}
}