{
  "type": "Feature",
  "properties": {
    "iso:country":"DE",
    "sg:address":"Friedrichstr. 13",
    "sg:city":"Hermaringen",
    "sg:phone":"+49 7322/919183",
    "sg:postcode":"89568",
    "sg:province":"Baden-W\u00fcrttemberg",
    "wof:name":"Wilhelm Brandst\u00e4tter",
    "wof:placetype":"venue"
},
  "geometry": {"coordinates":[10.257399,48.596889],"type":"Point"}
}