{
  "type": "Feature",
  "properties": {
    "iso:country":"DE",
    "sg:address":"Kirchstr. 5",
    "sg:city":"Urspringen",
    "sg:phone":"+49 9396/380",
    "sg:postcode":"97857",
    "sg:province":"Bayern",
    "wof:name":"Kath. Pfarramt",
    "wof:placetype":"venue"
},
  "geometry": {"coordinates":[9.6743412018,49.9032783508],"type":"Point"}
}