{
  "type": "Feature",
  "properties": {
    "iso:country":"DE",
    "sg:address":"Pegnitzweg 1",
    "sg:city":"N\u00fcrnberg",
    "sg:phone":"+49 911/502195",
    "sg:postcode":"90482",
    "sg:province":"Bayern",
    "wof:name":"H. A. Braun",
    "wof:placetype":"venue"
},
  "geometry": {"coordinates":[11.1537189484,49.4659576416],"type":"Point"}
}