{
  "type": "Feature",
  "properties": {
    "iso:country":"DE",
    "sg:address":"In der Ga\u00df 20",
    "sg:city":"Kirchentellinsfurt",
    "sg:phone":"+49 7121/670953",
    "sg:postcode":"72138",
    "sg:province":"Baden-W\u00fcrttemberg",
    "wof:name":"Uwe Steinmetz",
    "wof:placetype":"venue"
},
  "geometry": {"coordinates":[9.1497516632,48.5333862305],"type":"Point"}
}