{
  "type": "Feature",
  "properties": {
    "iso:country":"DE",
    "sg:address":"Droysenstr. 17",
    "sg:city":"Berlin",
    "sg:phone":"+49 4930/3274040",
    "sg:postcode":"10629",
    "sg:province":"Berlin",
    "wof:name":"Westpoint-catering",
    "wof:placetype":"venue"
},
  "geometry": {"coordinates":[13.3008785248,52.5024414062],"type":"Point"}
}