{
  "type": "Feature",
  "properties": {
    "iso:country":"DE",
    "sg:address":"Zum Langenloh 47",
    "sg:city":"Balve",
    "sg:phone":"+49 2375/5123",
    "sg:postcode":"58802",
    "sg:province":"Nordrhein-Westfalen",
    "wof:name":"Angelika Sprenger",
    "wof:placetype":"venue"
},
  "geometry": {"coordinates":[7.896708,51.352676],"type":"Point"}
}