{
  "type": "Feature",
  "properties": {
    "iso:country":"DE",
    "sg:address":"Groner-Tor-Str. 4",
    "sg:city":"G\u00f6ttingen",
    "sg:phone":"+49 551/56605",
    "sg:postcode":"37073",
    "sg:province":"Niedersachsen",
    "wof:name":"Apotheke Am Wall Michael Winkler",
    "wof:placetype":"venue"
},
  "geometry": {"coordinates":[9.927768,51.532715],"type":"Point"}
}