{
  "type": "Feature",
  "properties": {
    "iso:country":"DE",
    "sg:address":"Hasenstr. 39",
    "sg:city":"Merzig",
    "sg:phone":"+49 6861/2021",
    "sg:postcode":"66663",
    "sg:province":"Saarland",
    "wof:name":"Josef Luxemburger",
    "wof:placetype":"venue"
},
  "geometry": {"coordinates":[6.6107058525,49.439868927],"type":"Point"}
}