{
  "type": "Feature",
  "properties": {
    "iso:country":"DE",
    "sg:address":"Kopernikusstr. 3",
    "sg:city":"Ingolstadt",
    "sg:phone":"+49 841/42376",
    "sg:postcode":"85057",
    "sg:province":"Bayern",
    "wof:name":"B. Geiger-thumann",
    "wof:placetype":"venue"
},
  "geometry": {"coordinates":[11.4080400467,48.7749900818],"type":"Point"}
}