{
  "type": "Feature",
  "properties": {
    "iso:country":"DE",
    "sg:address":"Wiesengrund 3",
    "sg:city":"Drebber",
    "sg:phone":"+49 5445/228",
    "sg:postcode":"49457",
    "sg:province":"Niedersachsen",
    "wof:name":"Hildegard Landgraf Kg",
    "wof:placetype":"venue"
},
  "geometry": {"coordinates":[8.4209432602,52.6534500122],"type":"Point"}
}