{
  "type": "Feature",
  "properties": {
    "iso:country":"DE",
    "sg:address":"F\u00fcrther Str. 212",
    "sg:city":"N\u00fcrnberg",
    "sg:postcode":"90429",
    "sg:province":"Bayern",
    "wof:name":"F 1 Communications Center Wolfsburg Gmbh",
    "wof:placetype":"venue"
},
  "geometry": {"coordinates":[11.0345106125,49.4581260681],"type":"Point"}
}