{
  "type": "Feature",
  "properties": {
    "iso:country":"DE",
    "sg:address":"Industriestr. 22",
    "sg:city":"Sch\u00fcttorf",
    "sg:phone":"+49 5923/5086",
    "sg:postcode":"48465",
    "sg:province":"Niedersachsen",
    "wof:name":"Impex Landwirtschaftstechnik Vertriebs- Gmbh",
    "wof:placetype":"venue"
},
  "geometry": {"coordinates":[7.248594,52.338116],"type":"Point"}
}