{
  "type": "Feature",
  "properties": {
    "iso:country":"DE",
    "sg:address":"Freikorpsstr. 5",
    "sg:city":"Oberammergau",
    "sg:phone":"+49 8822/92010",
    "sg:postcode":"82487",
    "sg:province":"Bayern",
    "wof:name":"Hotel Antonia",
    "wof:placetype":"venue"
},
  "geometry": {"coordinates":[11.0607662201,47.5978126526],"type":"Point"}
}