{
  "type": "Feature",
  "properties": {
    "iso:country":"DE",
    "sg:address":"Luisenweg 143",
    "sg:city":"Hamburg",
    "sg:phone":"+49 40/2109670",
    "sg:postcode":"20537",
    "sg:province":"Hamburg",
    "wof:name":"W. Schulz",
    "wof:placetype":"venue"
},
  "geometry": {"coordinates":[10.0451717377,53.5472297668],"type":"Point"}
}