{
  "type": "Feature",
  "properties": {
    "iso:country":"DE",
    "sg:address":"Altmannsberg",
    "sg:city":"Berching",
    "sg:phone":"+49 8460/905010",
    "sg:postcode":"92334",
    "sg:province":"Bayern",
    "wof:name":"J. Hecker",
    "wof:placetype":"venue"
},
  "geometry": {"coordinates":[11.5135202408,49.1275291443],"type":"Point"}
}