{
  "type": "Feature",
  "properties": {
    "iso:country":"DE",
    "sg:address":"Hardstr. 6",
    "sg:city":"Wehr",
    "sg:phone":"+49 7761/6782",
    "sg:postcode":"79664",
    "sg:province":"Baden-W\u00fcrttemberg",
    "wof:name":"Georg Wunderle Ingenieur",
    "wof:placetype":"venue"
},
  "geometry": {"coordinates":[7.9060640335,47.5859794617],"type":"Point"}
}