{
  "type": "Feature",
  "properties": {
    "iso:country":"DE",
    "sg:address":"Anton-Bruckner-Str. 3",
    "sg:city":"Burglengenfeld",
    "sg:phone":"+49 9471/7500",
    "sg:postcode":"93133",
    "sg:province":"Bayern",
    "wof:name":"A. Vogl",
    "wof:placetype":"venue"
},
  "geometry": {"coordinates":[12.034827,49.198475],"type":"Point"}
}