{
  "type": "Feature",
  "properties": {
    "iso:country":"DE",
    "sg:address":"Lindenbergstr. 2",
    "sg:city":"Braunschweig",
    "sg:postcode":"38122",
    "sg:province":"Niedersachsen",
    "wof:name":"Elternhilfsgemeinschaft Grundschule Braunschweig-",
    "wof:placetype":"venue"
},
  "geometry": {"coordinates":[10.48204422,52.2306632996],"type":"Point"}
}