{
  "type": "Feature",
  "properties": {
    "iso:country":"DE",
    "sg:address":"Frankfurt Str. 19",
    "sg:city":"Bad Freienwalde",
    "sg:phone":"+49 3344/32440",
    "sg:postcode":"16259",
    "sg:province":"Brandenburg",
    "wof:name":"Bad Freienwalder M\u00f6bel Gmbh",
    "wof:placetype":"venue"
},
  "geometry": {"coordinates":[14.05494,52.775879],"type":"Point"}
}