{
  "type": "Feature",
  "properties": {
    "iso:country":"DE",
    "sg:address":"Herrenh\u00e4user Str. 63",
    "sg:city":"Hannover",
    "sg:phone":"+49 511/758376",
    "sg:postcode":"30419",
    "sg:province":"Niedersachsen",
    "wof:name":"Klamotte",
    "wof:placetype":"venue"
},
  "geometry": {"coordinates":[9.6853885651,52.3929977417],"type":"Point"}
}