{
  "type": "Feature",
  "properties": {
    "iso:country":"DE",
    "sg:address":"Bachstr. 16",
    "sg:city":"Bad Krozingen",
    "sg:phone":"+49 7633/12471",
    "sg:postcode":"79189",
    "sg:province":"Baden-W\u00fcrttemberg",
    "wof:name":"Eduard Selz",
    "wof:placetype":"venue"
},
  "geometry": {"coordinates":[7.6885528564,47.9408912659],"type":"Point"}
}