{
  "type": "Feature",
  "properties": {
    "iso:country":"DE",
    "sg:address":"Industriestr. 72",
    "sg:city":"Velbert",
    "sg:phone":"+49 2051/23086",
    "sg:postcode":"42551",
    "sg:province":"Nordrhein-Westfalen",
    "wof:name":"G\u00fcnter Brandenbusch Beteiligungs-gmbh",
    "wof:placetype":"venue"
},
  "geometry": {"coordinates":[7.068161,51.348484],"type":"Point"}
}