{
  "type": "Feature",
  "properties": {
    "iso:country":"DE",
    "sg:address":"Salomonsberg 1",
    "sg:city":"Pfarrweisach",
    "sg:phone":"+49 9535/1400",
    "sg:postcode":"96176",
    "sg:province":"Bayern",
    "wof:name":"F. Spitaler Gmbh",
    "wof:placetype":"venue"
},
  "geometry": {"coordinates":[10.743681,50.146049],"type":"Point"}
}