{
  "type": "Feature",
  "properties": {
    "iso:country":"DE",
    "sg:address":"Hasselbrookstr. 25",
    "sg:city":"Hamburg",
    "sg:postcode":"22089",
    "sg:province":"Hamburg",
    "wof:name":"Parcum Ges. F\u00fcr Resourcen- Sparende Bauprojekte Mbh",
    "wof:placetype":"venue"
},
  "geometry": {"coordinates":[10.040216,53.562939],"type":"Point"}
}