{
  "type": "Feature",
  "properties": {
    "iso:country":"DE",
    "sg:address":"Hauptstr. 21",
    "sg:city":"Wolfenb\u00fcttel",
    "sg:phone":"+49 5331/1453",
    "sg:postcode":"38304",
    "sg:province":"Niedersachsen",
    "wof:name":"Heinz Schnur",
    "wof:placetype":"venue"
},
  "geometry": {"coordinates":[10.5167989731,52.1718444824],"type":"Point"}
}