{
  "type": "Feature",
  "properties": {
    "iso:country":"DE",
    "sg:address":"Gereonswall 103",
    "sg:city":"K\u00f6ln",
    "sg:phone":"+49 221/123071",
    "sg:postcode":"50670",
    "sg:province":"Nordrhein-Westfalen",
    "wof:name":"Elektro-innung K\u00f6ln",
    "wof:placetype":"venue"
},
  "geometry": {"coordinates":[6.944961071,50.9449195862],"type":"Point"}
}