{
  "type": "Feature",
  "properties": {
    "iso:country":"DE",
    "sg:address":"Berliner Str. 13",
    "sg:city":"Enger",
    "sg:phone":"+49 5224/7389",
    "sg:postcode":"32130",
    "sg:province":"Nordrhein-Westfalen",
    "wof:name":"Natur Und Gr\u00fcn Enger Beteiligungs Gmbh",
    "wof:placetype":"venue"
},
  "geometry": {"coordinates":[8.55515,52.132622],"type":"Point"}
}