{
  "type": "Feature",
  "properties": {
    "iso:country":"DE",
    "sg:address":"Brunnenstr. 21",
    "sg:city":"Illingen",
    "sg:postcode":"66557",
    "sg:province":"Saarland",
    "wof:name":"Gerd Schneider Bau Gmbh",
    "wof:placetype":"venue"
},
  "geometry": {"coordinates":[7.0539078712,49.373134613],"type":"Point"}
}