{
  "type": "Feature",
  "properties": {
    "iso:country":"DE",
    "sg:address":"Zum Kreuzholz 15",
    "sg:city":"Neustadt",
    "sg:phone":"+49 5036/924131",
    "sg:postcode":"31535",
    "sg:province":"Niedersachsen",
    "wof:name":"Urlaub4me.de - Die Neue Unterkunftssuche",
    "wof:placetype":"venue"
},
  "geometry": {"coordinates":[9.281333,52.489075],"type":"Point"}
}