{
  "type": "Feature",
  "properties": {
    "iso:country":"DE",
    "sg:address":"Hauffstr. 17",
    "sg:city":"\u00d6hringen",
    "sg:phone":"+49 7941/2608",
    "sg:postcode":"74613",
    "sg:province":"Baden-W\u00fcrttemberg",
    "wof:name":"H. H\u00fcbner",
    "wof:placetype":"venue"
},
  "geometry": {"coordinates":[9.5027723312,49.1942024231],"type":"Point"}
}