{
  "type": "Feature",
  "properties": {
    "iso:country":"DE",
    "sg:address":"Hauffstr. 26",
    "sg:city":"Sonnenb\u00fchl",
    "sg:phone":"+49 7128/3992",
    "sg:postcode":"72820",
    "sg:province":"Baden-W\u00fcrttemberg",
    "wof:name":"Sylivia Herrmann Heilpraktikerin",
    "wof:placetype":"venue"
},
  "geometry": {"coordinates":[9.1839199066,48.408290863],"type":"Point"}
}