{
  "type": "Feature",
  "properties": {
    "iso:country":"DE",
    "sg:address":"Gro\u00dfe Str. 61",
    "sg:city":"J\u00fcbek",
    "sg:phone":"+49 4625/467",
    "sg:postcode":"24855",
    "sg:province":"Schleswig-Holstein",
    "wof:name":"Ev. Pfarramt J\u00fcbek",
    "wof:placetype":"venue"
},
  "geometry": {"coordinates":[9.3949165344,54.5565986633],"type":"Point"}
}