{
  "type": "Feature",
  "properties": {
    "iso:country":"DE",
    "sg:address":"Meckelweger Str 13",
    "sg:city":"Lienen",
    "sg:phone":"+49 5483/74570",
    "sg:postcode":"49536",
    "sg:province":"Nordrhein-Westfalen",
    "wof:name":"Wilhelm Voss Gmbh",
    "wof:placetype":"venue"
},
  "geometry": {"coordinates":[7.962876,52.129135],"type":"Point"}
}