{
  "type": "Feature",
  "properties": {
    "iso:country":"DE",
    "sg:address":"Im Park 9",
    "sg:city":"Meerbusch",
    "sg:phone":"+49 2132/4180",
    "sg:postcode":"40667",
    "sg:province":"Nordrhein-Westfalen",
    "wof:name":"Induha Export Handels Gmbh",
    "wof:placetype":"venue"
},
  "geometry": {"coordinates":[6.679309845,51.2623634338],"type":"Point"}
}