{
  "type": "Feature",
  "properties": {
    "iso:country":"DE",
    "sg:address":"Rat-Klingmann-Weg 1",
    "sg:city":"Dirmstein",
    "sg:phone":"+49 6238/2903",
    "sg:postcode":"67246",
    "sg:province":"Rheinland-Pfalz",
    "wof:name":"C. Bechtel-stockinger",
    "wof:placetype":"venue"
},
  "geometry": {"coordinates":[8.250790596,49.5661087036],"type":"Point"}
}