{
  "type": "Feature",
  "properties": {
    "iso:country":"DE",
    "sg:address":"stadthof 2",
    "sg:city":"bergen / r\u00fcgen",
    "sg:phone":"+49 3838/254250",
    "sg:postcode":"18528",
    "sg:province":"Mecklenburg-Vorpommern",
    "wof:name":"Freizeit Ranch R\u00fcgen",
    "wof:placetype":"venue"
},
  "geometry": {"coordinates":[13.3847646713,54.5083999634],"type":"Point"}
}