{
  "type": "Feature",
  "properties": {
    "iso:country":"DE",
    "sg:address":"Bahnhofstr. 28",
    "sg:city":"Bremen",
    "sg:phone":"+49 421/167422",
    "sg:postcode":"28195",
    "sg:province":"Bremen",
    "wof:name":"Garde Der Gute B\u00e4cker Zweigniederlassung Der Achimer",
    "wof:placetype":"venue"
},
  "geometry": {"coordinates":[8.811164,53.08147],"type":"Point"}
}