{
  "type": "Feature",
  "properties": {
    "iso:country":"DE",
    "sg:address":"Siemensstr 8",
    "sg:city":"Rodgau",
    "sg:phone":"+49 6106/28040",
    "sg:postcode":"63110",
    "sg:province":"Hessen",
    "wof:name":"Karl Chmelik Gmbh",
    "wof:placetype":"venue"
},
  "geometry": {"coordinates":[8.88761,50.013908],"type":"Point"}
}