{
  "type": "Feature",
  "properties": {
    "iso:country":"DE",
    "sg:address":"Stra\u00dfe der Freundschaft 9",
    "sg:city":"Neukloster",
    "sg:phone":"+49 38422/20331",
    "sg:postcode":"23992",
    "sg:province":"Mecklenburg-Vorpommern",
    "wof:name":"Textilverkauf Und Reparatur Gmbh",
    "wof:placetype":"venue"
},
  "geometry": {"coordinates":[11.686489,53.866982],"type":"Point"}
}