{
  "type": "Feature",
  "properties": {
    "iso:country":"DE",
    "sg:address":"Taubenweg 5",
    "sg:city":"Nittenau",
    "sg:phone":"+49 9436/437",
    "sg:postcode":"93149",
    "sg:province":"Bayern",
    "wof:name":"Schmidkonz Vertriebs Kg",
    "wof:placetype":"venue"
},
  "geometry": {"coordinates":[12.2887935638,49.2006568909],"type":"Point"}
}