{
  "type": "Feature",
  "properties": {
    "iso:country":"DE",
    "sg:address":"Im Mittelfeld 1",
    "sg:city":"Loitsche",
    "sg:phone":"+49 39208",
    "sg:postcode":"39326",
    "sg:province":"Sachsen-Anhalt",
    "wof:name":"Magna Naturstein Gmbh",
    "wof:placetype":"venue"
},
  "geometry": {"coordinates":[11.6840305328,52.2979164124],"type":"Point"}
}