{
  "type": "Feature",
  "properties": {
    "iso:country":"DE",
    "sg:address":"Sevelter Str. 27",
    "sg:city":"Cloppenburg",
    "sg:phone":"+49 4471/2022",
    "sg:postcode":"49661",
    "sg:province":"Niedersachsen",
    "wof:name":"Gastwirtschaft Ernst Brand",
    "wof:placetype":"venue"
},
  "geometry": {"coordinates":[8.0444173813,52.8423881531],"type":"Point"}
}