{
  "type": "Feature",
  "properties": {
    "iso:country":"DE",
    "sg:address":"Oberpf\u00e4lzerstr. 29",
    "sg:city":"Pegnitz",
    "sg:phone":"+49 9241/2448",
    "sg:postcode":"91257",
    "sg:province":"Bayern",
    "wof:name":"Raiffeisenbank Auerbach/opf Eg",
    "wof:placetype":"venue"
},
  "geometry": {"coordinates":[11.543307,49.756424],"type":"Point"}
}