{
  "type": "Feature",
  "properties": {
    "iso:country":"DE",
    "sg:address":"Auer Gasse 10",
    "sg:city":"Schmalkalden",
    "sg:phone":"+49 3683/403187",
    "sg:postcode":"98574",
    "sg:province":"Th\u00fcringen",
    "wof:name":"Kaufhaus Eckmann Gmbh",
    "wof:placetype":"venue"
},
  "geometry": {"coordinates":[10.4499998093,50.7209205627],"type":"Point"}
}