{
  "type": "Feature",
  "properties": {
    "iso:country":"DE",
    "sg:address":"Rathausplatz 5",
    "sg:city":"Reichelsheim",
    "sg:phone":"+49 6164/1421",
    "sg:postcode":"64385",
    "sg:province":"Hessen",
    "wof:name":"Ev. Pfarramt Ii Gem. Reichelsheim",
    "wof:placetype":"venue"
},
  "geometry": {"coordinates":[8.8400354385,49.71484375],"type":"Point"}
}