{
  "type": "Feature",
  "properties": {
    "iso:country":"DE",
    "sg:city":"Bad Feilnbach",
    "sg:phone":"+49 8066/8031",
    "sg:postcode":"83075",
    "sg:province":"Bayern",
    "wof:name":"Raiffeisenbank Au-feilnbach Eg",
    "wof:placetype":"venue"
},
  "geometry": {"coordinates":[12.008082,47.773361],"type":"Point"}
}