{
  "type": "Feature",
  "properties": {
    "iso:country":"DE",
    "sg:address":"Pl\u00fcckertzstr. 206",
    "sg:city":"Krefeld",
    "sg:postcode":"47804",
    "sg:province":"Nordrhein-Westfalen",
    "wof:name":"Prebau Gmbh",
    "wof:placetype":"venue"
},
  "geometry": {"coordinates":[6.5058298111,51.3010215759],"type":"Point"}
}