{
  "type": "Feature",
  "properties": {
    "iso:country":"DE",
    "sg:address":"Werner-Seelenbinder-Str. 11",
    "sg:city":"Chemnitz",
    "sg:phone":"+49 371/528360",
    "sg:postcode":"09120",
    "sg:province":"Sachsen",
    "wof:name":"Svg Stra\u00dfenverkehrs- Genossenschaft Sachsen Eg",
    "wof:placetype":"venue"
},
  "geometry": {"coordinates":[12.9235219955,50.8063087463],"type":"Point"}
}