{
  "type": "Feature",
  "properties": {
    "iso:country":"DE",
    "sg:address":"Vilsgasse 3",
    "sg:city":"Kallm\u00fcnz",
    "sg:phone":"+49 9473/302",
    "sg:postcode":"93183",
    "sg:province":"Bayern",
    "wof:name":"Maria M\u00fcnz",
    "wof:placetype":"venue"
},
  "geometry": {"coordinates":[11.9530000687,49.1607894897],"type":"Point"}
}