{
  "type": "Feature",
  "properties": {
    "iso:country":"DE",
    "sg:address":"Lerchenstr. 43",
    "sg:city":"Pohlheim",
    "sg:phone":"+49 6404/950936",
    "sg:postcode":"35415",
    "sg:province":"Hessen",
    "wof:name":"Josef Mengeler Rechtsanwalt",
    "wof:placetype":"venue"
},
  "geometry": {"coordinates":[8.7516565323,50.5070953369],"type":"Point"}
}