{
  "type": "Feature",
  "properties": {
    "iso:country":"DE",
    "sg:address":"Ziegelhorststr. 49",
    "sg:city":"Duisburg",
    "sg:phone":"+49 203/5031583",
    "sg:postcode":"47169",
    "sg:province":"Nordrhein-Westfalen",
    "wof:name":"Krankenpflege Pflegeteam- Kroner",
    "wof:placetype":"venue"
},
  "geometry": {"coordinates":[6.773842,51.511719],"type":"Point"}
}