{
  "type": "Feature",
  "properties": {
    "iso:country":"DE",
    "sg:address":"Birkenstr. 11",
    "sg:city":"Tamm",
    "sg:phone":"+49 7141/20510",
    "sg:postcode":"71732",
    "sg:province":"Baden-W\u00fcrttemberg",
    "wof:name":"Gai\u00dfer Av Systeme Gmbh",
    "wof:placetype":"venue"
},
  "geometry": {"coordinates":[9.1317062378,48.9233703613],"type":"Point"}
}