{
  "type": "Feature",
  "properties": {
    "iso:country":"DE",
    "sg:address":"Am Kabelkran 7",
    "sg:city":"Meppen",
    "sg:phone":"+49 5931/93400",
    "sg:postcode":"49716",
    "sg:province":"Niedersachsen",
    "wof:name":"Norbert Jansen Gmbh & Co. Kg",
    "wof:placetype":"venue"
},
  "geometry": {"coordinates":[7.2911400795,52.6899299622],"type":"Point"}
}