{
  "type": "Feature",
  "properties": {
    "iso:country":"DE",
    "sg:address":"Mauthausstr. 10a",
    "sg:city":"Nonnenhorn",
    "sg:phone":"+49 8382/8574",
    "sg:postcode":"88149",
    "sg:province":"Bayern",
    "wof:name":"Gefi Electronic Gmbh",
    "wof:placetype":"venue"
},
  "geometry": {"coordinates":[9.611323,47.577888],"type":"Point"}
}