{
  "type": "Feature",
  "properties": {
    "iso:country":"DE",
    "sg:address":"Altmannweg 10",
    "sg:city":"Hergatz",
    "sg:phone":"+49 8385",
    "sg:postcode":"88145",
    "sg:province":"Bayern",
    "wof:name":"Georg F. Sievers",
    "wof:placetype":"venue"
},
  "geometry": {"coordinates":[9.8765859604,47.6542510986],"type":"Point"}
}