{
  "type": "Feature",
  "properties": {
    "iso:country":"DE",
    "sg:address":"Leerbachstr. 115",
    "sg:city":"Frankfurt",
    "sg:postcode":"60322",
    "sg:province":"Hessen",
    "wof:name":"It Zwei Information Systems Ag",
    "wof:placetype":"venue"
},
  "geometry": {"coordinates":[8.671484,50.124187],"type":"Point"}
}