{
  "type": "Feature",
  "properties": {
    "iso:country":"DE",
    "sg:address":"K\u00f6nigstr. 58",
    "sg:city":"Berlin",
    "sg:phone":"+49 30/80602770",
    "sg:postcode":"14109",
    "sg:province":"Berlin",
    "wof:name":"Bp-tankstelle",
    "wof:placetype":"venue"
},
  "geometry": {"coordinates":[13.144949913,52.3986206055],"type":"Point"}
}