{
  "type": "Feature",
  "properties": {
    "iso:country":"DE",
    "sg:address":"Im Dorffeld 22",
    "sg:city":"Leichlingen",
    "sg:phone":"+49 2175/9404",
    "sg:postcode":"42799",
    "sg:province":"Nordrhein-Westfalen",
    "wof:name":"Picca-trio Leichlingen Hans G\u00fcnter Post",
    "wof:placetype":"venue"
},
  "geometry": {"coordinates":[7.0208749771,51.1052436829],"type":"Point"}
}