{
  "type": "Feature",
  "properties": {
    "iso:country":"DE",
    "sg:address":"Streckerring 16",
    "sg:city":"Collenberg",
    "sg:phone":"+49 9376/331",
    "sg:postcode":"97903",
    "sg:province":"Bayern",
    "wof:name":"Josef Rodenfels",
    "wof:placetype":"venue"
},
  "geometry": {"coordinates":[9.336033,49.771652],"type":"Point"}
}