{
  "type": "Feature",
  "properties": {
    "iso:country":"DE",
    "sg:address":"Hauptstr. 46 a",
    "sg:city":"Gro\u00dfdittmannsdorf",
    "sg:phone":"+49 35208/4477",
    "sg:postcode":"01471",
    "sg:province":"Sachsen",
    "wof:name":"Cornelia Haubold Rechtsanw\u00e4ltin",
    "wof:placetype":"venue"
},
  "geometry": {"coordinates":[13.7722043991,51.1988601685],"type":"Point"}
}