{
  "type": "Feature",
  "properties": {
    "iso:country":"DE",
    "sg:address":"Auf dem Kamp 4",
    "sg:city":"Minden",
    "sg:phone":"+49 571/35213",
    "sg:postcode":"32423",
    "sg:province":"Nordrhein-Westfalen",
    "wof:name":"H. Bernhard Versicherung",
    "wof:placetype":"venue"
},
  "geometry": {"coordinates":[8.9644546509,52.2944641113],"type":"Point"}
}