{
  "type": "Feature",
  "properties": {
    "iso:country":"DE",
    "sg:address":"Kirchweg 3",
    "sg:city":"Kirchbrak",
    "sg:phone":"+49 5533/5205",
    "sg:postcode":"37619",
    "sg:province":"Niedersachsen",
    "wof:name":"Klaus Herrmann",
    "wof:placetype":"venue"
},
  "geometry": {"coordinates":[9.576044,51.964825],"type":"Point"}
}