{
  "type": "Feature",
  "properties": {
    "iso:country":"DE",
    "sg:address":"Neuberg 2",
    "sg:city":"Wiesbaden",
    "sg:phone":"+49 611/529281",
    "sg:postcode":"65193",
    "sg:province":"Hessen",
    "wof:name":"Bernd L. Peter Architekt",
    "wof:placetype":"venue"
},
  "geometry": {"coordinates":[8.243971,50.089878],"type":"Point"}
}