{
  "type": "Feature",
  "properties": {
    "iso:country":"DE",
    "sg:address":"Ohler Weg 12a",
    "sg:city":"Halver",
    "sg:phone":"+49 4923/5197900",
    "sg:postcode":"58553",
    "sg:province":"Nordrhein-Westfalen",
    "wof:name":"Metallwerke Loewen Gmbh",
    "wof:placetype":"venue"
},
  "geometry": {"coordinates":[7.5747179985,51.1942367554],"type":"Point"}
}