{
  "type": "Feature",
  "properties": {
    "iso:country":"DE",
    "sg:address":"M\u00fchlenstr. 4",
    "sg:city":"Tessin",
    "sg:postcode":"18195",
    "sg:province":"Mecklenburg-Vorpommern",
    "wof:name":"G\u00fcnter M\u00fcller",
    "wof:placetype":"venue"
},
  "geometry": {"coordinates":[12.46844,54.02562],"type":"Point"}
}