{
  "type": "Feature",
  "properties": {
    "iso:country":"DE",
    "sg:address":"Point",
    "sg:city":"Kreuth",
    "sg:phone":"+49 8029/495",
    "sg:postcode":"83708",
    "sg:province":"Bayern",
    "wof:name":"Hirschbergliftst\u00fcberl",
    "wof:placetype":"venue"
},
  "geometry": {"coordinates":[11.7524747849,47.6568641663],"type":"Point"}
}