{
  "type": "Feature",
  "properties": {
    "iso:country":"DE",
    "sg:address":"Crimmitschauer Str. 50a",
    "sg:city":"Schm\u00f6lln",
    "sg:phone":"+49 34491/27131",
    "sg:postcode":"04626",
    "sg:province":"Th\u00fcringen",
    "wof:name":"Bws Betonwerk Gmbh",
    "wof:placetype":"venue"
},
  "geometry": {"coordinates":[12.3501653671,50.890296936],"type":"Point"}
}