{
  "type": "Feature",
  "properties": {
    "iso:country":"DE",
    "sg:address":"Lange Reihe 57-59",
    "sg:city":"Hamburg",
    "sg:postcode":"20099",
    "sg:province":"Hamburg",
    "wof:name":"Pastelaria Caravela Ramos E. K.",
    "wof:placetype":"venue"
},
  "geometry": {"coordinates":[10.0111675262,53.557559967],"type":"Point"}
}