{
  "type": "Feature",
  "properties": {
    "iso:country":"DE",
    "sg:address":"Kirchweg 1",
    "sg:city":"Morschen",
    "sg:phone":"+49 5664/1499",
    "sg:postcode":"34326",
    "sg:province":"Hessen",
    "wof:name":"Kurt Fernau",
    "wof:placetype":"venue"
},
  "geometry": {"coordinates":[9.57187,51.071571],"type":"Point"}
}