{
  "type": "Feature",
  "properties": {
    "iso:country":"DE",
    "sg:address":"Nansenstr. 15",
    "sg:city":"Neunkirchen",
    "sg:postcode":"66540",
    "sg:province":"Saarland",
    "wof:name":"Syc Yachtcharter Gmbh",
    "wof:placetype":"venue"
},
  "geometry": {"coordinates":[7.177881,49.375092],"type":"Point"}
}