{
  "type": "Feature",
  "properties": {
    "iso:country":"DE",
    "sg:address":"Rathausstr. 1",
    "sg:city":"Bad Homburg",
    "sg:postcode":"61348",
    "sg:province":"Hessen",
    "wof:name":"Zum Korkenzieher Gmbh",
    "wof:placetype":"venue"
},
  "geometry": {"coordinates":[8.6109981537,50.2294464111],"type":"Point"}
}