{
  "type": "Feature",
  "properties": {
    "iso:country":"DE",
    "sg:address":"Vilbeler Landstr. 204",
    "sg:city":"Frankfurt",
    "sg:phone":"+49 6109/21080",
    "sg:postcode":"60388",
    "sg:province":"Hessen",
    "wof:name":"C. Kleinert",
    "wof:placetype":"venue"
},
  "geometry": {"coordinates":[8.7472505569,50.1538467407],"type":"Point"}
}