{
  "type": "Feature",
  "properties": {
    "iso:country":"DE",
    "sg:address":"Bahnhofstr. 34",
    "sg:city":"H\u00f6chst\u00e4dt",
    "sg:phone":"+49 9074/1331",
    "sg:postcode":"89420",
    "sg:province":"Bayern",
    "wof:name":"Honig-schweier",
    "wof:placetype":"venue"
},
  "geometry": {"coordinates":[10.5668478012,48.6177978516],"type":"Point"}
}