{
  "type": "Feature",
  "properties": {
    "iso:country":"DE",
    "sg:address":"S\u00fcdstr. 44",
    "sg:city":"Kamp-Lintfort",
    "sg:phone":"+49 2842/965930",
    "sg:postcode":"47475",
    "sg:province":"Nordrhein-Westfalen",
    "wof:name":"Kisa Gmbh",
    "wof:placetype":"venue"
},
  "geometry": {"coordinates":[6.54032,51.486061],"type":"Point"}
}