{
  "type": "Feature",
  "properties": {
    "iso:country":"DE",
    "sg:address":"Bahnhofsplatz 8",
    "sg:city":"Ansbach",
    "sg:phone":"+49 981/9097111",
    "sg:postcode":"91522",
    "sg:province":"Bayern",
    "wof:name":"Deutsche Post Ag",
    "wof:placetype":"venue"
},
  "geometry": {"coordinates":[10.579035759,49.2990150452],"type":"Point"}
}