{
  "type": "Feature",
  "properties": {
    "iso:country":"DE",
    "sg:address":"Werner-Gilles-Str. 14",
    "sg:city":"M\u00f6nchengladbach",
    "sg:phone":"+49 2166/40900",
    "sg:postcode":"41236",
    "sg:province":"Nordrhein-Westfalen",
    "wof:name":"Norbert Sch\u00fcnzel Heilpraktiker",
    "wof:placetype":"venue"
},
  "geometry": {"coordinates":[6.4426608086,51.17029953],"type":"Point"}
}