{
  "type": "Feature",
  "properties": {
    "iso:country":"DE",
    "sg:address":"Bleichereistr. 28",
    "sg:city":"Uhingen",
    "sg:phone":"+49 4971/6193840",
    "sg:postcode":"73066",
    "sg:province":"Baden-W\u00fcrttemberg",
    "wof:name":"Thermohauser Erwin Busch Gmbh",
    "wof:placetype":"venue"
},
  "geometry": {"coordinates":[9.5680351257,48.7119407654],"type":"Point"}
}