{
  "type": "Feature",
  "properties": {
    "iso:country":"DE",
    "sg:address":"Dammer Weg 37",
    "sg:city":"Goldbach",
    "sg:phone":"+49 6021/90900",
    "sg:postcode":"63773",
    "sg:province":"Bayern",
    "wof:name":"Tv Touring Sendestudio Aschaffenburg Mbh & Co.",
    "wof:placetype":"venue"
},
  "geometry": {"coordinates":[9.1708173752,49.9940948486],"type":"Point"}
}