{
  "type": "Feature",
  "properties": {
    "iso:country":"DE",
    "sg:address":"M\u00f6rser Str. 54",
    "sg:city":"Wolfsburg",
    "sg:phone":"+49 5362/2008",
    "sg:postcode":"38442",
    "sg:province":"Niedersachsen",
    "wof:name":"Ute Westphal",
    "wof:placetype":"venue"
},
  "geometry": {"coordinates":[10.705835,52.395115],"type":"Point"}
}