{
  "type": "Feature",
  "properties": {
    "iso:country":"DE",
    "sg:address":"Oeseder Str. 8",
    "sg:city":"Georgsmarienh\u00fctte",
    "sg:postcode":"49124",
    "sg:province":"Niedersachsen",
    "wof:name":"Ibo Polymer-anlagentechnik Gmbh & Co. Kg",
    "wof:placetype":"venue"
},
  "geometry": {"coordinates":[8.059943,52.206318],"type":"Point"}
}