{
  "type": "Feature",
  "properties": {
    "iso:country":"DE",
    "sg:address":"An den Burgst\u00fccken 13",
    "sg:city":"Gardelegen",
    "sg:phone":"+49 3907/715601",
    "sg:postcode":"39638",
    "sg:province":"Sachsen-Anhalt",
    "wof:name":"Jastra Jamko Stra\u00dfburg Kg",
    "wof:placetype":"venue"
},
  "geometry": {"coordinates":[11.396916,52.538605],"type":"Point"}
}