{
  "type": "Feature",
  "properties": {
    "iso:country":"DE",
    "sg:address":"Am Richterbusch 27",
    "sg:city":"Sehmatal-Cranzahl",
    "sg:phone":"+49 3733/23280",
    "sg:postcode":"09465",
    "sg:province":"Sachsen",
    "wof:name":"Vereinte Versicherung Ag",
    "wof:placetype":"venue"
},
  "geometry": {"coordinates":[12.9980401993,50.5177688599],"type":"Point"}
}