{
  "type": "Feature",
  "properties": {
    "iso:country":"DE",
    "sg:address":"Am Bahnhof 20",
    "sg:city":"Landscheide",
    "sg:phone":"+49 4858/18000",
    "sg:postcode":"25572",
    "sg:province":"Schleswig-Holstein",
    "wof:name":"Gebr. Sch\u00fctt Gmbh & Co. Kg",
    "wof:placetype":"venue"
},
  "geometry": {"coordinates":[9.249072,53.919781],"type":"Point"}
}