{
  "type": "Feature",
  "properties": {
    "iso:country":"DE",
    "sg:address":"Finkenhof 3 a",
    "sg:city":"Hannover",
    "sg:phone":"+49 511/573132",
    "sg:postcode":"30627",
    "sg:province":"Niedersachsen",
    "wof:name":"Prof. Dr. Otto Anna",
    "wof:placetype":"venue"
},
  "geometry": {"coordinates":[9.8231010437,52.3884277344],"type":"Point"}
}