{
  "type": "Feature",
  "properties": {
    "iso:country":"DE",
    "sg:address":"Goethestr. 52",
    "sg:city":"Ladbergen",
    "sg:postcode":"49549",
    "sg:province":"Nordrhein-Westfalen",
    "wof:name":"Cm Technology Holding Gmbh",
    "wof:placetype":"venue"
},
  "geometry": {"coordinates":[7.73734,52.141689],"type":"Point"}
}