{
  "type": "Feature",
  "properties": {
    "iso:country":"DE",
    "sg:address":"Altendorfer Kirchgasse 21",
    "sg:city":"Nordhausen",
    "sg:phone":"+49 3631/983406",
    "sg:postcode":"99734",
    "sg:province":"Th\u00fcringen",
    "wof:name":"Klaus Neuber",
    "wof:placetype":"venue"
},
  "geometry": {"coordinates":[10.78907,51.507481],"type":"Point"}
}