{
  "type": "Feature",
  "properties": {
    "iso:country":"DE",
    "sg:address":"Kotten B\u00fcsken 25",
    "sg:city":"Borken",
    "sg:phone":"+49 2862/2627",
    "sg:postcode":"46325",
    "sg:province":"Nordrhein-Westfalen",
    "wof:name":"Heinrich Meiering",
    "wof:placetype":"venue"
},
  "geometry": {"coordinates":[6.879587,51.911148],"type":"Point"}
}