{
  "type": "Feature",
  "properties": {
    "iso:country":"DE",
    "sg:address":"Wengertstr. 50",
    "sg:city":"Ha\u00dffurt",
    "sg:phone":"+49 9521/950429",
    "sg:postcode":"97437",
    "sg:province":"Bayern",
    "wof:name":"Febsan Ambulanter Krankenpflegedienst",
    "wof:placetype":"venue"
},
  "geometry": {"coordinates":[10.517259,50.042763],"type":"Point"}
}