{
  "type": "Feature",
  "properties": {
    "iso:country":"DE",
    "sg:address":"Kronenstr. 9",
    "sg:city":"G\u00f6ppingen",
    "sg:phone":"+49 7161/813040",
    "sg:postcode":"73037",
    "sg:province":"Baden-W\u00fcrttemberg",
    "wof:name":"Reinhard Regen",
    "wof:placetype":"venue"
},
  "geometry": {"coordinates":[9.689073,48.684956],"type":"Point"}
}