{
  "type": "Feature",
  "properties": {
    "iso:country":"DE",
    "sg:address":"Postfach",
    "sg:city":"Badenweiler",
    "sg:postcode":"79401",
    "sg:province":"Baden-W\u00fcrttemberg",
    "wof:name":"Golfshop Des Rhein-golf-clubs Badenweiler",
    "wof:placetype":"venue"
},
  "geometry": {"coordinates":[7.67179,47.801781],"type":"Point"}
}