{
  "type": "Feature",
  "properties": {
    "iso:country":"DE",
    "sg:address":"Gutenbergstr. 38-42",
    "sg:city":"Hessisch Lichtenau",
    "sg:phone":"+49 5602/700320",
    "sg:postcode":"37235",
    "sg:province":"Hessen",
    "wof:name":"Sch\u00f6nherr Strick Fashion Gmbh",
    "wof:placetype":"venue"
},
  "geometry": {"coordinates":[9.6980447769,51.2250900269],"type":"Point"}
}