{
  "type": "Feature",
  "properties": {
    "iso:country":"DE",
    "sg:address":"Heuholzstr. 7",
    "sg:city":"\u00d6hringen",
    "sg:postcode":"74613",
    "sg:province":"Baden-W\u00fcrttemberg",
    "wof:name":"Gsp Werbegraphik",
    "wof:placetype":"venue"
},
  "geometry": {"coordinates":[9.4572229385,49.2495346069],"type":"Point"}
}