{
  "type": "Feature",
  "properties": {
    "iso:country":"DE",
    "sg:address":"Seelbuschring 8",
    "sg:city":"Berlin",
    "sg:phone":"+49 30/7062219",
    "sg:postcode":"12105",
    "sg:province":"Berlin",
    "wof:name":"Karl Breuer",
    "wof:placetype":"venue"
},
  "geometry": {"coordinates":[13.371499,52.448334],"type":"Point"}
}