{
  "type": "Feature",
  "properties": {
    "iso:country":"DE",
    "sg:address":"R\u00f6merstra\u00dfe 51",
    "sg:city":"Bad Abbach",
    "sg:phone":"+49 9405",
    "sg:postcode":"93077",
    "sg:province":"Bayern",
    "wof:name":"Facharztpraxis Innere Medizin, Chinesische Medizin Und Akupunktur",
    "wof:placetype":"venue"
},
  "geometry": {"coordinates":[12.05066,48.934814],"type":"Point"}
}