{
  "type": "Feature",
  "properties": {
    "iso:country":"DE",
    "sg:address":"Frankfurter Str. 19",
    "sg:city":"S\u00fcnna",
    "sg:phone":"+49 36962/24269",
    "sg:postcode":"36404",
    "sg:province":"Th\u00fcringen",
    "wof:name":"S. Koch",
    "wof:placetype":"venue"
},
  "geometry": {"coordinates":[9.9990148544,50.7973976135],"type":"Point"}
}