{
  "type": "Feature",
  "properties": {
    "iso:country":"DE",
    "sg:address":"Am Diek 142",
    "sg:city":"Samern",
    "sg:phone":"+49 5923/3995",
    "sg:postcode":"48465",
    "sg:province":"Niedersachsen",
    "wof:name":"H. Wessels",
    "wof:placetype":"venue"
},
  "geometry": {"coordinates":[7.254294,52.314655],"type":"Point"}
}