{
  "type": "Feature",
  "properties": {
    "iso:country":"DE",
    "sg:address":"Gumbertstr. 180-182",
    "sg:city":"D\u00fcsseldorf",
    "sg:phone":"+49 211/221015",
    "sg:postcode":"40229",
    "sg:province":"Nordrhein-Westfalen",
    "wof:name":"Kern Apotheke Wilhelm Kern Apotheker F\u00fcr",
    "wof:placetype":"venue"
},
  "geometry": {"coordinates":[6.843499,51.199722],"type":"Point"}
}