{
  "type": "Feature",
  "properties": {
    "iso:country":"DE",
    "sg:address":"Knappenstr. 108",
    "sg:city":"Oberhausen",
    "sg:postcode":"46047",
    "sg:province":"Nordrhein-Westfalen",
    "wof:name":"Via Moda Gmbh",
    "wof:placetype":"venue"
},
  "geometry": {"coordinates":[6.8799591064,51.4787559509],"type":"Point"}
}