{
  "type": "Feature",
  "properties": {
    "iso:country":"DE",
    "sg:address":"Zeppelinstr. 9",
    "sg:city":"Schwarzenbach a Wald",
    "sg:phone":"+49 9289/303",
    "sg:postcode":"95131",
    "sg:province":"Bayern",
    "wof:name":"Hans Ortlam Fiat-h\u00e4ndler",
    "wof:placetype":"venue"
},
  "geometry": {"coordinates":[11.6288738251,50.2866363525],"type":"Point"}
}