{
  "type": "Feature",
  "properties": {
    "iso:country":"DE",
    "sg:address":"Lindenstr. 36",
    "sg:city":"Idar-Oberstein",
    "sg:phone":"+49 6781/22425",
    "sg:postcode":"55743",
    "sg:province":"Rheinland-Pfalz",
    "wof:name":"Helmut M\u00fcller",
    "wof:placetype":"venue"
},
  "geometry": {"coordinates":[7.2969589233,49.6932792664],"type":"Point"}
}