{
  "type": "Feature",
  "properties": {
    "iso:country":"DE",
    "sg:address":"Wormser Str. 5a",
    "sg:city":"Frankenthal",
    "sg:phone":"+49 6233/27385",
    "sg:postcode":"67227",
    "sg:province":"Rheinland-Pfalz",
    "wof:name":"Nordsee Gmbh",
    "wof:placetype":"venue"
},
  "geometry": {"coordinates":[8.3540754318,49.5360412598],"type":"Point"}
}