{
  "type": "Feature",
  "properties": {
    "iso:country":"DE",
    "sg:address":"Hof Alpenblick 1",
    "sg:city":"M\u00fcnsingen",
    "sg:postcode":"72525",
    "sg:province":"Baden-W\u00fcrttemberg",
    "wof:name":"Schultes Gmbh & Co. Kg",
    "wof:placetype":"venue"
},
  "geometry": {"coordinates":[9.503238678,48.3754844666],"type":"Point"}
}