{
  "type": "Feature",
  "properties": {
    "iso:country":"DE",
    "sg:address":"John-Schehr-Str. 30 Sued",
    "sg:city":"Lauchhammer",
    "sg:phone":"+49 4935/7488670",
    "sg:postcode":"01979",
    "sg:province":"Brandenburg",
    "wof:name":"Meisner Gmbh-bausanierung, Lauchhammer",
    "wof:placetype":"venue"
},
  "geometry": {"coordinates":[13.76404,51.496681],"type":"Point"}
}