{
  "type": "Feature",
  "properties": {
    "iso:country":"DE",
    "sg:address":"Schlo\u00dfstr. 14",
    "sg:city":"Lippetal",
    "sg:phone":"+49 2923/218",
    "sg:postcode":"59510",
    "sg:province":"Nordrhein-Westfalen",
    "wof:name":"J. Michael",
    "wof:placetype":"venue"
},
  "geometry": {"coordinates":[8.1487703323,51.6566505432],"type":"Point"}
}