{
  "type": "Feature",
  "properties": {
    "iso:country":"DE",
    "sg:address":"In den Eschg\u00e4rten 11",
    "sg:city":"Zilshausen",
    "sg:phone":"+49 6762/8920",
    "sg:postcode":"56288",
    "sg:province":"Rheinland-Pfalz",
    "wof:name":"Reiner Hiester Gmbh",
    "wof:placetype":"venue"
},
  "geometry": {"coordinates":[7.3844938278,50.1146965027],"type":"Point"}
}