{
  "type": "Feature",
  "properties": {
    "iso:country":"DE",
    "sg:address":"Fuchsienweg 10",
    "sg:city":"Leer",
    "sg:phone":"+49 491/2843",
    "sg:postcode":"26789",
    "sg:province":"Niedersachsen",
    "wof:name":"Gudrun Knocke",
    "wof:placetype":"venue"
},
  "geometry": {"coordinates":[7.4108438492,53.2172546387],"type":"Point"}
}