{
  "type": "Feature",
  "properties": {
    "iso:country":"DE",
    "sg:address":"Lerchenfeldstr. 35",
    "sg:city":"Kre\u00dfberg",
    "sg:phone":"+49 7957/345",
    "sg:postcode":"74594",
    "sg:province":"Baden-W\u00fcrttemberg",
    "wof:name":"Heinz Beutekamp",
    "wof:placetype":"venue"
},
  "geometry": {"coordinates":[10.239193,49.130501],"type":"Point"}
}