{
  "type": "Feature",
  "properties": {
    "iso:country":"DE",
    "sg:address":"Br\u00fcnnhildestr. 2",
    "sg:city":"Berlin",
    "sg:phone":"+49 30/8526475",
    "sg:postcode":"12159",
    "sg:province":"Berlin",
    "wof:name":"Wilhelm Westphal Malermeister Und Kirchenmaler",
    "wof:placetype":"venue"
},
  "geometry": {"coordinates":[13.330417,52.476608],"type":"Point"}
}