{
  "type": "Feature",
  "properties": {
    "iso:country":"DE",
    "sg:address":"Ehrendorfer Str. 9",
    "sg:city":"Lohne",
    "sg:phone":"+49 5492/2232",
    "sg:postcode":"49393",
    "sg:province":"Niedersachsen",
    "wof:name":"Josef H\u00fcrkamp",
    "wof:placetype":"venue"
},
  "geometry": {"coordinates":[8.22495,52.661289],"type":"Point"}
}