{
  "type": "Feature",
  "properties": {
    "iso:country":"DE",
    "sg:address":"Hagener Str.",
    "sg:city":"Olpe",
    "sg:phone":"+49 2761/41406",
    "sg:postcode":"57462",
    "sg:province":"Nordrhein-Westfalen",
    "wof:name":"Sb-handelshof Gmbh",
    "wof:placetype":"venue"
},
  "geometry": {"coordinates":[7.846036911,51.0285568237],"type":"Point"}
}