{
  "type": "Feature",
  "properties": {
    "iso:country":"DE",
    "sg:address":"Memminger Str. 11 1/2",
    "sg:city":"V\u00f6hringen",
    "sg:phone":"+49 7306/5321",
    "sg:postcode":"89269",
    "sg:province":"Bayern",
    "wof:name":"Schmiede",
    "wof:placetype":"venue"
},
  "geometry": {"coordinates":[10.07873,48.277458],"type":"Point"}
}