{
  "type": "Feature",
  "properties": {
    "iso:country":"DE",
    "sg:address":"Xantener Str. 20",
    "sg:city":"Berlin",
    "sg:phone":"+49 30/8816432",
    "sg:postcode":"10707",
    "sg:province":"Berlin",
    "wof:name":"M. Scheuenstuhl Inh. Rudolf Radloff",
    "wof:placetype":"venue"
},
  "geometry": {"coordinates":[13.309467,52.499203],"type":"Point"}
}