{
  "type": "Feature",
  "properties": {
    "iso:country":"DE",
    "sg:address":"Baumgartsweg 19a",
    "sg:city":"Aachen",
    "sg:phone":"+49 2408/928026",
    "sg:postcode":"52076",
    "sg:province":"Nordrhein-Westfalen",
    "wof:name":"R. Franke Und B. Radtke",
    "wof:placetype":"venue"
},
  "geometry": {"coordinates":[6.1449,50.697872],"type":"Point"}
}