{
  "type": "Feature",
  "properties": {
    "iso:country":"DE",
    "sg:address":"Nickel-Hoffmann-Str. 14",
    "sg:city":"Halle",
    "sg:postcode":"06110",
    "sg:province":"Sachsen-Anhalt",
    "wof:name":"Gebr. Friedrichs B\u00fcrobedarf Gmbh",
    "wof:placetype":"venue"
},
  "geometry": {"coordinates":[11.973204,51.468597],"type":"Point"}
}