{
  "type": "Feature",
  "properties": {
    "iso:country":"DE",
    "sg:address":"Promenade 32",
    "sg:city":"Wei\u00dfenfels",
    "sg:phone":"+49 3443/302000",
    "sg:postcode":"06667",
    "sg:province":"Sachsen-Anhalt",
    "wof:name":"Stil Art Gmbh",
    "wof:placetype":"venue"
},
  "geometry": {"coordinates":[11.9715852737,51.2024307251],"type":"Point"}
}