{
  "type": "Feature",
  "properties": {
    "iso:country":"DE",
    "sg:address":"Auerstr. 8 a",
    "sg:city":"Bad Wiessee",
    "sg:phone":"+49 8022/8773",
    "sg:postcode":"83707",
    "sg:province":"Bayern",
    "wof:name":"G\u00e4stehaus Bildstein Inh. G\u00fcgel",
    "wof:placetype":"venue"
},
  "geometry": {"coordinates":[11.7151632309,47.7184867859],"type":"Point"}
}