{
  "type": "Feature",
  "properties": {
    "iso:country":"DE",
    "sg:address":"Friedrich-Ebert-Ring 170",
    "sg:city":"Rheine",
    "sg:phone":"+49 5971/6266",
    "sg:postcode":"48429",
    "sg:province":"Nordrhein-Westfalen",
    "wof:name":"Del Mundo Reisen Gmbh",
    "wof:placetype":"venue"
},
  "geometry": {"coordinates":[7.4497947693,52.294216156],"type":"Point"}
}