{
  "type": "Feature",
  "properties": {
    "iso:country":"DE",
    "sg:address":"Ahornweg 6",
    "sg:city":"Walldorf",
    "sg:phone":"+49 6227/30468",
    "sg:postcode":"69190",
    "sg:province":"Baden-W\u00fcrttemberg",
    "wof:name":"Ggv-gesellschaft F\u00fcr Grundbesitz- Und",
    "wof:placetype":"venue"
},
  "geometry": {"coordinates":[8.6327028275,49.3113441467],"type":"Point"}
}