{
  "type": "Feature",
  "properties": {
    "iso:country":"DE",
    "sg:address":"Spenting 10",
    "sg:city":"Mohrkirch",
    "sg:postcode":"24405",
    "sg:province":"Schleswig-Holstein",
    "wof:name":"Wasserbeschaffungsverband S\u00f6rup",
    "wof:placetype":"venue"
},
  "geometry": {"coordinates":[9.733829,54.684799],"type":"Point"}
}