{
  "type": "Feature",
  "properties": {
    "iso:country":"DE",
    "sg:address":"Klostergasse 2",
    "sg:city":"Kulmbach",
    "sg:phone":"+49 9221/4481",
    "sg:postcode":"95326",
    "sg:province":"Bayern",
    "wof:name":"Schuhmacherei Roland Baumgartner",
    "wof:placetype":"venue"
},
  "geometry": {"coordinates":[11.456807,50.10807],"type":"Point"}
}