{
  "type": "Feature",
  "properties": {
    "iso:country":"DE",
    "sg:address":"Wilkeplatz 11",
    "sg:city":"Warstein",
    "sg:phone":"+49 2902/97060",
    "sg:postcode":"59581",
    "sg:province":"Nordrhein-Westfalen",
    "wof:name":"Volksbank Immobilien Und Bautr\u00e4ger Gmbh & Co. Kg",
    "wof:placetype":"venue"
},
  "geometry": {"coordinates":[8.3367900848,51.4861526489],"type":"Point"}
}