{
  "type": "Feature",
  "properties": {
    "iso:country":"DE",
    "sg:address":"Kienberger Str. 16",
    "sg:city":"Allershausen",
    "sg:phone":"+49 8166/9517",
    "sg:postcode":"85391",
    "sg:province":"Bayern",
    "wof:name":"Forster",
    "wof:placetype":"venue"
},
  "geometry": {"coordinates":[11.594828,48.433773],"type":"Point"}
}