{
  "type": "Feature",
  "properties": {
    "iso:country":"DE",
    "sg:address":"Feldmochinger Str. 50",
    "sg:city":"M\u00fcnchen",
    "sg:phone":"+49 89/1412670",
    "sg:postcode":"80993",
    "sg:province":"Bayern",
    "wof:name":"G\u00fcnter Stangl",
    "wof:placetype":"venue"
},
  "geometry": {"coordinates":[11.521258,48.183861],"type":"Point"}
}