{
  "type": "Feature",
  "properties": {
    "iso:country":"DE",
    "sg:address":"Marktstr. 20",
    "sg:city":"Hilders",
    "sg:phone":"+49 6681/371",
    "sg:postcode":"36115",
    "sg:province":"Hessen",
    "wof:name":"Eduard Breidung",
    "wof:placetype":"venue"
},
  "geometry": {"coordinates":[10.001042366,50.5715866089],"type":"Point"}
}