{
  "type": "Feature",
  "properties": {
    "iso:country":"DE",
    "sg:address":"Birkenstr. 92",
    "sg:city":"D\u00fcsseldorf",
    "sg:phone":"+49 211/6987830",
    "sg:postcode":"40233",
    "sg:province":"Nordrhein-Westfalen",
    "wof:name":"Canon-hp-scs Kopierer, D\u00fcsseldorf-faxgeraete,usw",
    "wof:placetype":"venue"
},
  "geometry": {"coordinates":[6.807504,51.227127],"type":"Point"}
}