{
  "type": "Feature",
  "properties": {
    "iso:country":"DE",
    "sg:address":"Hindenburgstr. 28",
    "sg:city":"Garmisch-Partenkirchen",
    "sg:phone":"+49 8821/947417",
    "sg:postcode":"82467",
    "sg:province":"Bayern",
    "wof:name":"Bogenrieder Architekt",
    "wof:placetype":"venue"
},
  "geometry": {"coordinates":[11.100809,47.49736],"type":"Point"}
}