{
  "type": "Feature",
  "properties": {
    "iso:country":"DE",
    "sg:address":"Bonifatiusplatz 7",
    "sg:city":"Leinefelde",
    "sg:phone":"+49 3605/518939",
    "sg:postcode":"37327",
    "sg:province":"Th\u00fcringen",
    "wof:name":"Bonifatius-apotheke",
    "wof:placetype":"venue"
},
  "geometry": {"coordinates":[10.320414,51.377396],"type":"Point"}
}