{
  "type": "Feature",
  "properties": {
    "iso:country":"DE",
    "sg:address":"Pinienstr. 10",
    "sg:city":"D\u00fcsseldorf",
    "sg:phone":"+49 211/986880",
    "sg:postcode":"40233",
    "sg:province":"Nordrhein-Westfalen",
    "wof:name":"Hans Meuffels Gmbh",
    "wof:placetype":"venue"
},
  "geometry": {"coordinates":[6.810206,51.217831],"type":"Point"}
}