{
  "type": "Feature",
  "properties": {
    "iso:country":"DE",
    "sg:address":"Edisonstr. 1",
    "sg:city":"Bautzen",
    "sg:phone":"+49 4935/9137880",
    "sg:postcode":"02625",
    "sg:province":"Sachsen",
    "wof:name":"Aft F\u00d6rderanlagen Bautzen Gmbh & Co. Kg",
    "wof:placetype":"venue"
},
  "geometry": {"coordinates":[14.4184417725,51.1644172668],"type":"Point"}
}