{
  "type": "Feature",
  "properties": {
    "iso:country":"DE",
    "sg:address":"Theodor-V\u00f6lker-Str. 12",
    "sg:city":"Lich",
    "sg:postcode":"35423",
    "sg:province":"Hessen",
    "wof:name":"Punkt Eins Organisationsges. Mbh",
    "wof:placetype":"venue"
},
  "geometry": {"coordinates":[8.8209075928,50.5106582642],"type":"Point"}
}