{
  "type": "Feature",
  "properties": {
    "iso:country":"DE",
    "sg:address":"Im Dorf 58",
    "sg:city":"Neusitz",
    "sg:phone":"+49 9861/8951",
    "sg:postcode":"91616",
    "sg:province":"Bayern",
    "wof:name":"Georg Popp",
    "wof:placetype":"venue"
},
  "geometry": {"coordinates":[10.221155,49.373287],"type":"Point"}
}