{
  "type": "Feature",
  "properties": {
    "iso:country":"DE",
    "sg:address":"Sch\u00f6nau",
    "sg:city":"Berchtesgaden",
    "sg:phone":"+49 8652/2117",
    "sg:postcode":"83471",
    "sg:province":"Bayern",
    "wof:name":"Alois Und Johann Kastner",
    "wof:placetype":"venue"
},
  "geometry": {"coordinates":[12.990392,47.590004],"type":"Point"}
}