{
  "type": "Feature",
  "properties": {
    "iso:country":"DE",
    "sg:address":"Gartenheim 2",
    "sg:city":"Neufahrn",
    "sg:phone":"+49 8165/4929",
    "sg:postcode":"85375",
    "sg:province":"Bayern",
    "wof:name":"Hans-christian Preusse",
    "wof:placetype":"venue"
},
  "geometry": {"coordinates":[11.6622495651,48.3169212341],"type":"Point"}
}