{
  "type": "Feature",
  "properties": {
    "iso:country":"DE",
    "sg:address":"Bruckhauser Str. 34",
    "sg:city":"Grefrath",
    "sg:postcode":"47929",
    "sg:province":"Nordrhein-Westfalen",
    "wof:name":"Klaus Sch\u00fcndeln",
    "wof:placetype":"venue"
},
  "geometry": {"coordinates":[6.338916,51.341042],"type":"Point"}
}