{
  "type": "Feature",
  "properties": {
    "iso:country":"DE",
    "sg:address":"Bahnhofstr. 4",
    "sg:city":"Wei\u00dfenhorn",
    "sg:phone":"+49 7309/3758",
    "sg:postcode":"89264",
    "sg:province":"Bayern",
    "wof:name":"Eisdiele Heinrich",
    "wof:placetype":"venue"
},
  "geometry": {"coordinates":[10.157061,48.306293],"type":"Point"}
}