{
  "type": "Feature",
  "properties": {
    "iso:country":"DE",
    "sg:address":"Robert-Bosch-Str. 17",
    "sg:city":"Odelzhausen",
    "sg:phone":"+49 8134/99384",
    "sg:postcode":"85235",
    "sg:province":"Bayern",
    "wof:name":"Kerscher & Sohn Gmbh",
    "wof:placetype":"venue"
},
  "geometry": {"coordinates":[11.208383,48.305241],"type":"Point"}
}