{
  "type": "Feature",
  "properties": {
    "iso:country":"DE",
    "sg:address":"M\u00f6rikestr. 33",
    "sg:city":"Oberderdingen",
    "sg:phone":"+49 7045/636",
    "sg:postcode":"75038",
    "sg:province":"Baden-W\u00fcrttemberg",
    "wof:name":"Josef Krempl Ingenieur",
    "wof:placetype":"venue"
},
  "geometry": {"coordinates":[8.7947540283,49.0621795654],"type":"Point"}
}