{
  "type": "Feature",
  "properties": {
    "iso:country":"DE",
    "sg:address":"Kirchplatz 2",
    "sg:city":"Tr\u00f6stau",
    "sg:phone":"+49 9232/2963",
    "sg:postcode":"95709",
    "sg:province":"Bayern",
    "wof:name":"Ev. Luth. Pfarramt",
    "wof:placetype":"venue"
},
  "geometry": {"coordinates":[11.9425811768,50.0164527893],"type":"Point"}
}