{
  "type": "Feature",
  "properties": {
    "iso:country":"DE",
    "sg:address":"Erlengrund 72",
    "sg:city":"St. Leon-Rot",
    "sg:phone":"+49 6227/59359",
    "sg:postcode":"68789",
    "sg:province":"Baden-W\u00fcrttemberg",
    "wof:name":"J. Bender",
    "wof:placetype":"venue"
},
  "geometry": {"coordinates":[8.6322164536,49.2577095032],"type":"Point"}
}