{
  "type": "Feature",
  "properties": {
    "iso:country":"DE",
    "sg:address":"Hauptstr. 35",
    "sg:city":"Dreieich",
    "sg:phone":"+49 6103/61417",
    "sg:postcode":"63303",
    "sg:province":"Hessen",
    "wof:name":"R. Gerner",
    "wof:placetype":"venue"
},
  "geometry": {"coordinates":[8.695398,50.017239],"type":"Point"}
}