{
  "type": "Feature",
  "properties": {
    "iso:country":"DE",
    "sg:address":"August-Horch-Str. 20",
    "sg:city":"Winningen",
    "sg:phone":"+49 2606/438",
    "sg:postcode":"56333",
    "sg:province":"Rheinland-Pfalz",
    "wof:name":"Martin Hautt",
    "wof:placetype":"venue"
},
  "geometry": {"coordinates":[7.5194001198,50.315120697],"type":"Point"}
}