{
  "type": "Feature",
  "properties": {
    "iso:country":"DE",
    "sg:address":"Marktplatz 23",
    "sg:city":"Aurich",
    "sg:phone":"+49 4941/997979",
    "sg:postcode":"26603",
    "sg:province":"Niedersachsen",
    "wof:name":"Restaurant Knodt'sche Haus",
    "wof:placetype":"venue"
},
  "geometry": {"coordinates":[7.4826340675,53.4702796936],"type":"Point"}
}