{
  "type": "Feature",
  "properties": {
    "iso:country":"DE",
    "sg:address":"Schlo\u00dfstr. 25",
    "sg:city":"Ludwigsburg",
    "sg:phone":"+49 7141/929720",
    "sg:postcode":"71634",
    "sg:province":"Baden-W\u00fcrttemberg",
    "wof:name":"Ursula Krehl Rechtsanw\u00e4ltin",
    "wof:placetype":"venue"
},
  "geometry": {"coordinates":[9.1937837601,48.8986854553],"type":"Point"}
}