{
  "type": "Feature",
  "properties": {
    "iso:country":"DE",
    "sg:address":"Wilhelmstr. 17",
    "sg:city":"Juist",
    "sg:phone":"+49 4935/297",
    "sg:postcode":"26571",
    "sg:province":"Niedersachsen",
    "wof:name":"Pension H. Melching",
    "wof:placetype":"venue"
},
  "geometry": {"coordinates":[6.9966011047,53.6776504517],"type":"Point"}
}