{
  "type": "Feature",
  "properties": {
    "iso:country":"DE",
    "sg:address":"Weilautstr. 1",
    "sg:city":"Ochtrup",
    "sg:phone":"+49 2553/93840",
    "sg:postcode":"48607",
    "sg:province":"Nordrhein-Westfalen",
    "wof:name":"Albers Verwaltungsges. Mbh",
    "wof:placetype":"venue"
},
  "geometry": {"coordinates":[7.185451,52.207348],"type":"Point"}
}