{
  "type": "Feature",
  "properties": {
    "iso:country":"DE",
    "sg:address":"Weildorfer Kreuz 8",
    "sg:city":"Haigerloch",
    "sg:phone":"+49 7474/345",
    "sg:postcode":"72401",
    "sg:province":"Baden-W\u00fcrttemberg",
    "wof:name":"Marita Rentschler Massagepraxis",
    "wof:placetype":"venue"
},
  "geometry": {"coordinates":[8.79372,48.368851],"type":"Point"}
}