{
  "type": "Feature",
  "properties": {
    "iso:country":"DE",
    "sg:address":"Hasenstr. 3",
    "sg:city":"Speyer",
    "sg:phone":"+49 6232/26742",
    "sg:postcode":"67346",
    "sg:province":"Rheinland-Pfalz",
    "wof:name":"Megacor Handel M. Medizin- Technik Und Diagnostika Gmbh",
    "wof:placetype":"venue"
},
  "geometry": {"coordinates":[8.425323,49.316174],"type":"Point"}
}