{
  "type": "Feature",
  "properties": {
    "iso:country":"DE",
    "sg:address":"Franklinstr. 45",
    "sg:city":"Stuttgart",
    "sg:phone":"+49 711/823415",
    "sg:postcode":"70435",
    "sg:province":"Baden-W\u00fcrttemberg",
    "wof:name":"Ev. Pfarramt Pauluskirche Iii",
    "wof:placetype":"venue"
},
  "geometry": {"coordinates":[9.1630163193,48.8288955688],"type":"Point"}
}