{
  "type": "Feature",
  "properties": {
    "iso:country":"DE",
    "sg:address":"Rudolf-Herzog-Str. 16",
    "sg:city":"Wuppertal",
    "sg:phone":"+49 202/2547995",
    "sg:postcode":"42275",
    "sg:province":"Nordrhein-Westfalen",
    "wof:name":"Conrenta Verm\u00f6gensberatungs- Und Vermittlungsgesellschaft",
    "wof:placetype":"venue"
},
  "geometry": {"coordinates":[7.2049331665,51.2716026306],"type":"Point"}
}