{
  "type": "Feature",
  "properties": {
    "iso:country":"DE",
    "sg:address":"Kirchring 1",
    "sg:city":"Ederm\u00fcnde",
    "sg:phone":"+49 5665/6596",
    "sg:postcode":"34295",
    "sg:province":"Hessen",
    "wof:name":"Heinrich Umbach",
    "wof:placetype":"venue"
},
  "geometry": {"coordinates":[9.443717,51.210606],"type":"Point"}
}