{
  "type": "Feature",
  "properties": {
    "iso:country":"DE",
    "sg:address":"Thielestr. 13",
    "sg:city":"Bad Arolsen",
    "sg:postcode":"34454",
    "sg:province":"Hessen",
    "wof:name":"Heinrich Emde",
    "wof:placetype":"venue"
},
  "geometry": {"coordinates":[8.952691,51.38905],"type":"Point"}
}