{
  "type": "Feature",
  "properties": {
    "iso:country":"DE",
    "sg:address":"Hauptstr. 38",
    "sg:city":"Emersacker",
    "sg:phone":"+49 8293/965928",
    "sg:postcode":"86494",
    "sg:province":"Bayern",
    "wof:name":"Pizzeria Im Holzwinkel",
    "wof:placetype":"venue"
},
  "geometry": {"coordinates":[10.6731071472,48.4929199219],"type":"Point"}
}