{
  "type": "Feature",
  "properties": {
    "iso:country":"DE",
    "sg:address":"Rote Str. 27",
    "sg:city":"G\u00f6ttingen",
    "sg:phone":"+49 551/45269",
    "sg:postcode":"37073",
    "sg:province":"Niedersachsen",
    "wof:name":"Gastst\u00e4tte Kamin",
    "wof:placetype":"venue"
},
  "geometry": {"coordinates":[9.9365882874,51.5326881409],"type":"Point"}
}