{
  "type": "Feature",
  "properties": {
    "iso:country":"DE",
    "sg:address":"Ulmenstr. 55",
    "sg:city":"Chemnitz",
    "sg:postcode":"09112",
    "sg:province":"Sachsen",
    "wof:name":"Walter Porstmann",
    "wof:placetype":"venue"
},
  "geometry": {"coordinates":[12.897719,50.83036],"type":"Point"}
}