{
  "type": "Feature",
  "properties": {
    "iso:country":"DE",
    "sg:address":"Schreyerring 11",
    "sg:city":"Hamburg",
    "sg:phone":"+49 40/6315822",
    "sg:postcode":"22309",
    "sg:province":"Hamburg",
    "wof:name":"Gropius-apotheke Ohg",
    "wof:placetype":"venue"
},
  "geometry": {"coordinates":[10.057273,53.610981],"type":"Point"}
}