{
  "type": "Feature",
  "properties": {
    "iso:country":"DE",
    "sg:address":"Loikumer Weg 21",
    "sg:city":"Bocholt",
    "sg:phone":"+49 2871/6836",
    "sg:postcode":"46395",
    "sg:province":"Nordrhein-Westfalen",
    "wof:name":"E. Kinski",
    "wof:placetype":"venue"
},
  "geometry": {"coordinates":[6.5983400345,51.8115997314],"type":"Point"}
}