{
  "type": "Feature",
  "properties": {
    "iso:country":"DE",
    "sg:address":"Brunnenstr. 163",
    "sg:city":"Berlin",
    "sg:phone":"+49 30/4497417",
    "sg:postcode":"10119",
    "sg:province":"Berlin",
    "wof:name":"Wladislaus Wysocki",
    "wof:placetype":"venue"
},
  "geometry": {"coordinates":[13.398067,52.534245],"type":"Point"}
}