{
  "type": "Feature",
  "properties": {
    "iso:country":"DE",
    "sg:address":"Zehdenicker Str. 2",
    "sg:city":"Lychen",
    "sg:phone":"+49 39888/2959",
    "sg:postcode":"17279",
    "sg:province":"Brandenburg",
    "wof:name":"Horst Gladow",
    "wof:placetype":"venue"
},
  "geometry": {"coordinates":[13.3206396103,53.2041854858],"type":"Point"}
}