{
  "type": "Feature",
  "properties": {
    "iso:country":"DE",
    "sg:address":"Ahornstr. 33",
    "sg:city":"Gelsenkirchen",
    "sg:phone":"+49 209/7040",
    "sg:postcode":"45892",
    "sg:province":"Nordrhein-Westfalen",
    "wof:name":"Krankenhausvollapotheke Des St.-hedwig-hospital",
    "wof:placetype":"venue"
},
  "geometry": {"coordinates":[7.106912,51.579048],"type":"Point"}
}