{
  "type": "Feature",
  "properties": {
    "iso:country":"DE",
    "sg:address":"Bismarckstr. 107",
    "sg:city":"Berlin",
    "sg:phone":"+49 30/3125013",
    "sg:postcode":"10625",
    "sg:province":"Berlin",
    "wof:name":"Seidel Und Partner Wirtschaftsberatung Gmbh",
    "wof:placetype":"venue"
},
  "geometry": {"coordinates":[13.3160543442,52.5119972229],"type":"Point"}
}