{
  "type": "Feature",
  "properties": {
    "iso:country":"DE",
    "sg:address":"Schaffhauser Str. 2",
    "sg:city":"V\u00f6lklingen",
    "sg:phone":"+49 6898/21437",
    "sg:postcode":"66333",
    "sg:province":"Saarland",
    "wof:name":"Br\u00fcckenschenke",
    "wof:placetype":"venue"
},
  "geometry": {"coordinates":[6.8377509117,49.2467193604],"type":"Point"}
}