{
  "type": "Feature",
  "properties": {
    "iso:country":"DE",
    "sg:address":"Sch\u00f6ppinger Str. 3",
    "sg:city":"Rosendahl",
    "sg:phone":"+49 2547/7191",
    "sg:postcode":"48720",
    "sg:province":"Nordrhein-Westfalen",
    "wof:name":"Bernhard Gr\u00f6ver",
    "wof:placetype":"venue"
},
  "geometry": {"coordinates":[7.208799839,52.0266304016],"type":"Point"}
}