{
  "type": "Feature",
  "properties": {
    "iso:country":"DE",
    "sg:address":"Ostpreu\u00dfenstr. 56",
    "sg:city":"Regensburg",
    "sg:phone":"+49 941/62105",
    "sg:postcode":"93057",
    "sg:province":"Bayern",
    "wof:name":"Bau- Und Ausbau Gmbh",
    "wof:placetype":"venue"
},
  "geometry": {"coordinates":[12.117043,49.046356],"type":"Point"}
}