{
  "type": "Feature",
  "properties": {
    "iso:country":"DE",
    "sg:address":"Wiesenbrunnenweg 9",
    "sg:city":"Flein",
    "sg:phone":"+49 7131/251968",
    "sg:postcode":"74223",
    "sg:province":"Baden-W\u00fcrttemberg",
    "wof:name":"Hermann Marquardt",
    "wof:placetype":"venue"
},
  "geometry": {"coordinates":[9.2144899368,49.1041946411],"type":"Point"}
}