{
  "type": "Feature",
  "properties": {
    "iso:country":"DE",
    "sg:address":"F\u00f6rsterweg 111 c",
    "sg:city":"Hamburg",
    "sg:phone":"+49 40/545898",
    "sg:postcode":"22525",
    "sg:province":"Hamburg",
    "wof:name":"Hermann Beneke Ingenieur",
    "wof:placetype":"venue"
},
  "geometry": {"coordinates":[9.9223604202,53.5856323242],"type":"Point"}
}