{
  "type": "Feature",
  "properties": {
    "iso:country":"DE",
    "sg:address":"Bochumer Str. 110",
    "sg:city":"Bochum",
    "sg:phone":"+49 2327/15049",
    "sg:postcode":"44866",
    "sg:province":"Nordrhein-Westfalen",
    "wof:name":"Oma H\u00f6lscher",
    "wof:placetype":"venue"
},
  "geometry": {"coordinates":[7.1611537933,51.4797935486],"type":"Point"}
}