{
  "type": "Feature",
  "properties": {
    "iso:country":"DE",
    "sg:address":"Neudorfstr. 6",
    "sg:city":"Mannheim",
    "sg:postcode":"68229",
    "sg:province":"Baden-W\u00fcrttemberg",
    "wof:name":"Verband Deutscher Alten- Und Behindertenhilfe E. V.",
    "wof:placetype":"venue"
},
  "geometry": {"coordinates":[8.5761785507,49.4402160645],"type":"Point"}
}