{
  "type": "Feature",
  "properties": {
    "iso:country":"DE",
    "sg:address":"Kasernenstr. 7",
    "sg:city":"Coburg",
    "sg:phone":"+49 9561/871051",
    "sg:postcode":"96450",
    "sg:province":"Bayern",
    "wof:name":"Sanit\u00e4rtechnik Thomas Gmbh",
    "wof:placetype":"venue"
},
  "geometry": {"coordinates":[10.965107,50.266979],"type":"Point"}
}