{
  "type": "Feature",
  "properties": {
    "iso:country":"DE",
    "sg:address":"Dellplatz 25",
    "sg:city":"Duisburg",
    "sg:phone":"+49 203/22129",
    "sg:postcode":"47051",
    "sg:province":"Nordrhein-Westfalen",
    "wof:name":"Anton Haase",
    "wof:placetype":"venue"
},
  "geometry": {"coordinates":[6.761706,51.429646],"type":"Point"}
}