{
  "type": "Feature",
  "properties": {
    "iso:country":"DE",
    "sg:address":"Brinkstr. 71",
    "sg:city":"Offenbach",
    "sg:phone":"+49 69/83833377",
    "sg:postcode":"63069",
    "sg:province":"Hessen",
    "wof:name":"Atlantis Venture And Products Gmbh",
    "wof:placetype":"venue"
},
  "geometry": {"coordinates":[8.760169,50.090179],"type":"Point"}
}