{
  "type": "Feature",
  "properties": {
    "iso:country":"DE",
    "sg:address":"Buchenweg 14",
    "sg:city":"Heist",
    "sg:phone":"+49 4122/81359",
    "sg:postcode":"25492",
    "sg:province":"Schleswig-Holstein",
    "wof:name":"Uwe L\u00fcck",
    "wof:placetype":"venue"
},
  "geometry": {"coordinates":[9.659702,53.650604],"type":"Point"}
}