{
  "type": "Feature",
  "properties": {
    "iso:country":"DE",
    "sg:address":"Oberwinterbach 7",
    "sg:city":"Vestenbergsgreuth",
    "sg:phone":"+49 9552/7865",
    "sg:postcode":"91487",
    "sg:province":"Bayern",
    "wof:name":"Friedrich Lettenmayer",
    "wof:placetype":"venue"
},
  "geometry": {"coordinates":[10.6492853165,49.704536438],"type":"Point"}
}