{
  "type": "Feature",
  "properties": {
    "iso:country":"DE",
    "sg:address":"Uzstr. 3",
    "sg:city":"Welden",
    "sg:phone":"+49 8293/205",
    "sg:postcode":"86465",
    "sg:province":"Bayern",
    "wof:name":"Demharter",
    "wof:placetype":"venue"
},
  "geometry": {"coordinates":[10.6588363647,48.457233429],"type":"Point"}
}