{
  "type": "Feature",
  "properties": {
    "iso:country":"DE",
    "sg:address":"Obere Dorfstr. 32",
    "sg:city":"Peissen",
    "sg:phone":"+49 4876/301",
    "sg:postcode":"25551",
    "sg:province":"Schleswig-Holstein",
    "wof:name":"R. Schulz",
    "wof:placetype":"venue"
},
  "geometry": {"coordinates":[9.609796,54.023064],"type":"Point"}
}