{
  "type": "Feature",
  "properties": {
    "iso:country":"DE",
    "sg:address":"Heisenbergring 13",
    "sg:city":"Bayreuth",
    "sg:phone":"+49 921/98666",
    "sg:postcode":"95448",
    "sg:province":"Bayern",
    "wof:name":"Wolfgang Jahreis",
    "wof:placetype":"venue"
},
  "geometry": {"coordinates":[11.6077346802,49.9367828369],"type":"Point"}
}