{
  "type": "Feature",
  "properties": {
    "iso:country":"DE",
    "sg:address":"Waldstr. 55",
    "sg:city":"Nauheim",
    "sg:phone":"+49 6152/62938",
    "sg:postcode":"64569",
    "sg:province":"Hessen",
    "wof:name":"Hubert Neuhausen",
    "wof:placetype":"venue"
},
  "geometry": {"coordinates":[8.4579591751,49.9516181946],"type":"Point"}
}