{
  "type": "Feature",
  "properties": {
    "iso:country":"DE",
    "sg:address":"Im Furtsand 10",
    "sg:city":"Segnitz",
    "sg:phone":"+49 9332/1503",
    "sg:postcode":"97340",
    "sg:province":"Bayern",
    "wof:name":"Paul Hofmann",
    "wof:placetype":"venue"
},
  "geometry": {"coordinates":[10.139296,49.670643],"type":"Point"}
}