{
  "type": "Feature",
  "properties": {
    "iso:country":"DE",
    "sg:address":"Bahnhofstr. 12",
    "sg:city":"Brandis",
    "sg:phone":"+49 34292/75155",
    "sg:postcode":"04821",
    "sg:province":"Sachsen",
    "wof:name":"R. Jentzsch",
    "wof:placetype":"venue"
},
  "geometry": {"coordinates":[12.609919548,51.3326072693],"type":"Point"}
}