{
  "type": "Feature",
  "properties": {
    "iso:country":"DE",
    "sg:address":"Ackerstr. 157",
    "sg:city":"Berlin",
    "sg:phone":"+49 30/30871022",
    "sg:postcode":"10115",
    "sg:province":"Berlin",
    "wof:name":"Vostok Reisen E. K.",
    "wof:placetype":"venue"
},
  "geometry": {"coordinates":[13.3966140747,52.5307884216],"type":"Point"}
}