{
  "type": "Feature",
  "properties": {
    "iso:country":"DE",
    "sg:address":"A\u00dfmannstr. 48",
    "sg:city":"Berlin",
    "sg:phone":"+49 30/6452933",
    "sg:postcode":"12587",
    "sg:province":"Berlin",
    "wof:name":"B\u00fcthe-elektro",
    "wof:placetype":"venue"
},
  "geometry": {"coordinates":[13.6250505447,52.4503669739],"type":"Point"}
}