{
  "type": "Feature",
  "properties": {
    "iso:country":"DE",
    "sg:address":"L\u00e4rchenweg 17a",
    "sg:city":"Eitorf",
    "sg:postcode":"53783",
    "sg:province":"Nordrhein-Westfalen",
    "wof:name":"Swiba Versandhandels Gmbh",
    "wof:placetype":"venue"
},
  "geometry": {"coordinates":[7.4538397789,50.7666015625],"type":"Point"}
}