{
  "type": "Feature",
  "properties": {
    "iso:country":"DE",
    "sg:address":"Hauptstr. 11",
    "sg:city":"Stockstadt",
    "sg:phone":"+49 6027/70135",
    "sg:postcode":"63811",
    "sg:province":"Bayern",
    "wof:name":"Bierkeller Windsor",
    "wof:placetype":"venue"
},
  "geometry": {"coordinates":[9.0644750595,49.9787826538],"type":"Point"}
}