{
  "type": "Feature",
  "properties": {
    "iso:country":"DE",
    "sg:address":"Pirnaer Str. 29",
    "sg:city":"Dresden",
    "sg:phone":"+49 35026/91113",
    "sg:postcode":"01328",
    "sg:province":"Sachsen",
    "wof:name":"Holger Bleul",
    "wof:placetype":"venue"
},
  "geometry": {"coordinates":[13.9529733658,51.0316085815],"type":"Point"}
}