{
  "type": "Feature",
  "properties": {
    "iso:country":"DE",
    "sg:city":"essen",
    "sg:postcode":"45136",
    "sg:province":"Nordrhein-Westfalen",
    "wof:name":"Wart.de",
    "wof:placetype":"venue"
},
  "geometry": {"coordinates":[7.035715,51.433174],"type":"Point"}
}