{
  "type": "Feature",
  "properties": {
    "iso:country":"DE",
    "sg:address":"Auf den Bruchswiesen 2 b",
    "sg:city":"Gummersbach",
    "sg:postcode":"51643",
    "sg:province":"Nordrhein-Westfalen",
    "wof:name":"Van Neer Gmbh",
    "wof:placetype":"venue"
},
  "geometry": {"coordinates":[7.5402817726,51.0129814148],"type":"Point"}
}