{
  "type": "Feature",
  "properties": {
    "iso:country":"DE",
    "sg:address":"Dietzgenstr. 31",
    "sg:city":"Berlin",
    "sg:phone":"+49 30/4469320",
    "sg:postcode":"13156",
    "sg:province":"Berlin",
    "wof:name":"Botschaft Der Mongolei",
    "wof:placetype":"venue"
},
  "geometry": {"coordinates":[13.4031839371,52.5830764771],"type":"Point"}
}