{
  "type": "Feature",
  "properties": {
    "iso:country":"DE",
    "sg:address":"Am Fehrborn 20",
    "sg:city":"Lambsborn",
    "sg:phone":"+49 6372/1405",
    "sg:postcode":"66894",
    "sg:province":"Rheinland-Pfalz",
    "wof:name":"Dorfgemeinschaftshaus",
    "wof:placetype":"venue"
},
  "geometry": {"coordinates":[7.431368,49.367897],"type":"Point"}
}