{
  "type": "Feature",
  "properties": {
    "iso:country":"DE",
    "sg:address":"Am Gansacker 10c",
    "sg:city":"Umkirch",
    "sg:phone":"+49 7665/98280",
    "sg:postcode":"79224",
    "sg:province":"Baden-W\u00fcrttemberg",
    "wof:name":"Hans W. Hercher M\u00fcnzen Gmbh",
    "wof:placetype":"venue"
},
  "geometry": {"coordinates":[7.764268,48.038315],"type":"Point"}
}