{
  "type": "Feature",
  "properties": {
    "iso:country":"DE",
    "sg:address":"Harnackstr. 10",
    "sg:city":"Berlin",
    "sg:phone":"+49 30/5598250",
    "sg:postcode":"10365",
    "sg:province":"Berlin",
    "wof:name":"Dr. Med. Fritz Schnell",
    "wof:placetype":"venue"
},
  "geometry": {"coordinates":[13.485232,52.511066],"type":"Point"}
}