{
  "type": "Feature",
  "properties": {
    "iso:country":"DE",
    "sg:address":"H\u00f6nnestra\u00dfe 31",
    "sg:city":"Neuenrade",
    "sg:phone":"+49 2394/180",
    "sg:postcode":"58809",
    "sg:province":"Nordrhein-Westfalen",
    "wof:name":"B\u00dcltmann",
    "wof:placetype":"venue"
},
  "geometry": {"coordinates":[7.8142609596,51.2923088074],"type":"Point"}
}