{
  "type": "Feature",
  "properties": {
    "iso:country":"DE",
    "sg:address":"Erlenweg 12",
    "sg:city":"Cunewalde",
    "sg:phone":"+49 35877/25285",
    "sg:postcode":"02733",
    "sg:province":"Sachsen",
    "wof:name":"Peter Lutze",
    "wof:placetype":"venue"
},
  "geometry": {"coordinates":[14.5050401688,51.0981178284],"type":"Point"}
}