{
  "type": "Feature",
  "properties": {
    "iso:country":"DE",
    "sg:address":"Bonnstr.",
    "sg:city":"Frechen",
    "sg:phone":"+49 2234/1000",
    "sg:postcode":"50226",
    "sg:province":"Nordrhein-Westfalen",
    "wof:name":"Estee Lauder Cosmetics Gmbh",
    "wof:placetype":"venue"
},
  "geometry": {"coordinates":[6.828589,50.912209],"type":"Point"}
}