{
  "type": "Feature",
  "properties": {
    "iso:country":"DE",
    "sg:address":"Schulthei\u00dfenstr. 18",
    "sg:city":"Hameln",
    "sg:phone":"+49 5154/95240",
    "sg:postcode":"31789",
    "sg:province":"Niedersachsen",
    "wof:name":"Genoma Normteile Gmbh",
    "wof:placetype":"venue"
},
  "geometry": {"coordinates":[9.336219,52.082195],"type":"Point"}
}