{
  "type": "Feature",
  "properties": {
    "iso:country":"DE",
    "sg:address":"Kopernikusstr 25",
    "sg:city":"Bergheim",
    "sg:phone":"+49 2271/478710",
    "sg:postcode":"50126",
    "sg:province":"Nordrhein-Westfalen",
    "wof:name":"A&m Labor F\u00fcr Analytik Und Metabolismusforschung Service Gmbh",
    "wof:placetype":"venue"
},
  "geometry": {"coordinates":[6.609878,50.956085],"type":"Point"}
}