{
  "type": "Feature",
  "properties": {
    "iso:country":"DE",
    "sg:address":"Jacob-M\u00f6nch-Str. 5",
    "sg:city":"Offenbach",
    "sg:phone":"+49 69/8901050",
    "sg:postcode":"63073",
    "sg:province":"Hessen",
    "wof:name":"W. Krebs Rohrleitungsbau Gmbh",
    "wof:placetype":"venue"
},
  "geometry": {"coordinates":[8.8402919769,50.081703186],"type":"Point"}
}