{
  "type": "Feature",
  "properties": {
    "iso:country":"DE",
    "sg:address":"Meyenburger Str. 16 a",
    "sg:city":"Parchim",
    "sg:phone":"+49 3871/217808",
    "sg:postcode":"19370",
    "sg:province":"Mecklenburg-Vorpommern",
    "wof:name":"Cross Gmbh & Co. Kg Creative Objekt Service System",
    "wof:placetype":"venue"
},
  "geometry": {"coordinates":[11.8663549423,53.4231071472],"type":"Point"}
}