{
  "type": "Feature",
  "properties": {
    "iso:country":"DE",
    "sg:address":"Platzstr. 16",
    "sg:city":"Ehra-Lessien",
    "sg:phone":"+49 5377/484",
    "sg:postcode":"38468",
    "sg:province":"Niedersachsen",
    "wof:name":"Harald K\u00fchn",
    "wof:placetype":"venue"
},
  "geometry": {"coordinates":[10.756141,52.573563],"type":"Point"}
}