{
  "type": "Feature",
  "properties": {
    "iso:country":"DE",
    "sg:address":"Zehntweg 44",
    "sg:city":"Bergisch Gladbach",
    "sg:phone":"+49 2202/82665",
    "sg:postcode":"51467",
    "sg:province":"Nordrhein-Westfalen",
    "wof:name":"Industrietor M\u00fcller Gmbh",
    "wof:placetype":"venue"
},
  "geometry": {"coordinates":[7.0788397789,51.0197257996],"type":"Point"}
}