{
  "type": "Feature",
  "properties": {
    "iso:country":"DE",
    "sg:address":"Amalienstr. 51",
    "sg:city":"M\u00fcnchen",
    "sg:phone":"+49 89/2809077",
    "sg:postcode":"80799",
    "sg:province":"Bayern",
    "wof:name":"Klaus Tafertshofer",
    "wof:placetype":"venue"
},
  "geometry": {"coordinates":[11.5774650574,48.1491775513],"type":"Point"}
}