{
  "type": "Feature",
  "properties": {
    "iso:country":"DE",
    "sg:address":"Frohsinnstr. 13",
    "sg:city":"Aschaffenburg",
    "sg:phone":"+49 6021/27142",
    "sg:postcode":"63739",
    "sg:province":"Bayern",
    "wof:name":"Frohsinn-apotheke",
    "wof:placetype":"venue"
},
  "geometry": {"coordinates":[9.146263,49.978874],"type":"Point"}
}