{
  "type": "Feature",
  "properties": {
    "iso:country":"DE",
    "sg:address":"Mannheimer Str. 55",
    "sg:city":"Viernheim",
    "sg:phone":"+49 6204/2270",
    "sg:postcode":"68519",
    "sg:province":"Hessen",
    "wof:name":"Hotel Hessischer Hof",
    "wof:placetype":"venue"
},
  "geometry": {"coordinates":[8.5749111176,49.5308761597],"type":"Point"}
}