{
  "type": "Feature",
  "properties": {
    "iso:country":"DE",
    "sg:address":"Charlottenstr. 97",
    "sg:city":"M\u00fclheim",
    "sg:phone":"+49 208/470473",
    "sg:postcode":"45468",
    "sg:province":"Nordrhein-Westfalen",
    "wof:name":"Ulla Heilberg",
    "wof:placetype":"venue"
},
  "geometry": {"coordinates":[6.885732,51.433689],"type":"Point"}
}