{
  "type": "Feature",
  "properties": {
    "iso:country":"DE",
    "sg:address":"Glockhammer 11",
    "sg:city":"Neuss",
    "sg:phone":"+49 2131/276550",
    "sg:postcode":"41460",
    "sg:province":"Nordrhein-Westfalen",
    "wof:name":"M. Schmidt",
    "wof:placetype":"venue"
},
  "geometry": {"coordinates":[6.69281,51.200089],"type":"Point"}
}