{
  "type": "Feature",
  "properties": {
    "iso:country":"DE",
    "sg:address":"Rebenweg 8",
    "sg:city":"Ravensburg",
    "sg:phone":"+49 751/62762",
    "sg:postcode":"88214",
    "sg:province":"Baden-W\u00fcrttemberg",
    "wof:name":"H. Mueller Ingenieur",
    "wof:placetype":"venue"
},
  "geometry": {"coordinates":[9.6063947678,47.7515220642],"type":"Point"}
}