{
  "type": "Feature",
  "properties": {
    "iso:country":"DE",
    "sg:address":"Akazienallee 16",
    "sg:city":"Wandlitz",
    "sg:phone":"+49 33397/21480",
    "sg:postcode":"16348",
    "sg:province":"Brandenburg",
    "wof:name":"Coiffeur Marlies Losansky",
    "wof:placetype":"venue"
},
  "geometry": {"coordinates":[13.4583215714,52.7473449707],"type":"Point"}
}