{
  "type": "Feature",
  "properties": {
    "iso:country":"DE",
    "sg:address":"Berliner Str. 41",
    "sg:city":"Potsdam",
    "sg:postcode":"14467",
    "sg:province":"Brandenburg",
    "wof:name":"K & P Projekt Kg",
    "wof:placetype":"venue"
},
  "geometry": {"coordinates":[13.0756025314,52.4075164795],"type":"Point"}
}