{
  "type": "Feature",
  "properties": {
    "iso:country":"DE",
    "sg:address":"Dorfstr. 12",
    "sg:city":"Brieske",
    "sg:phone":"+49 3573/661811",
    "sg:postcode":"01968",
    "sg:province":"Brandenburg",
    "wof:name":"Andreas Kleiner",
    "wof:placetype":"venue"
},
  "geometry": {"coordinates":[14.00963,51.515202],"type":"Point"}
}