{
  "type": "Feature",
  "properties": {
    "iso:country":"DE",
    "sg:address":"Gewerbestr. 2",
    "sg:city":"Gro\u00dfr\u00e4schen",
    "sg:phone":"+49 35753/2220",
    "sg:postcode":"01983",
    "sg:province":"Brandenburg",
    "wof:name":"M\u00f6bel-zentrum Gro\u00dfr\u00e4schen Gmbh",
    "wof:placetype":"venue"
},
  "geometry": {"coordinates":[14.0312204361,51.5791091919],"type":"Point"}
}