{
  "type": "Feature",
  "properties": {
    "iso:country":"DE",
    "sg:address":"Sch\u00fctzenstr. 20",
    "sg:city":"D\u00fcren",
    "sg:phone":"+49 2421/23983",
    "sg:postcode":"52351",
    "sg:province":"Nordrhein-Westfalen",
    "wof:name":"Bank F\u00fcr Gemeinwirtschaft",
    "wof:placetype":"venue"
},
  "geometry": {"coordinates":[6.486388,50.803898],"type":"Point"}
}