{
  "type": "Feature",
  "properties": {
    "iso:country":"DE",
    "sg:address":"Hauptstr. 40",
    "sg:city":"Berbisdorf",
    "sg:phone":"+49 35208/33551",
    "sg:postcode":"01471",
    "sg:province":"Sachsen",
    "wof:name":"Albrecht Sch\u00f6ne",
    "wof:placetype":"venue"
},
  "geometry": {"coordinates":[13.72448,51.188271],"type":"Point"}
}