{
  "type": "Feature",
  "properties": {
    "iso:country":"DE",
    "sg:address":"Leonhardsgasse 12",
    "sg:city":"Frankfurt",
    "sg:phone":"+49 69/474768",
    "sg:postcode":"60389",
    "sg:province":"Hessen",
    "wof:name":"Glasbau Gleiser Gmbh",
    "wof:placetype":"venue"
},
  "geometry": {"coordinates":[8.728647,50.144951],"type":"Point"}
}