{
  "type": "Feature",
  "properties": {
    "iso:country":"DE",
    "sg:address":"Emstalstr. 9",
    "sg:city":"Felsberg",
    "sg:phone":"+49 5662/2956",
    "sg:postcode":"34587",
    "sg:province":"Hessen",
    "wof:name":"Helmut Hamenst\u00e4dt",
    "wof:placetype":"venue"
},
  "geometry": {"coordinates":[9.41527,51.150547],"type":"Point"}
}