{
  "type": "Feature",
  "properties": {
    "iso:country":"DE",
    "sg:address":"M\u00fchlweg 11",
    "sg:city":"Wiederstedt",
    "sg:postcode":"06333",
    "sg:province":"Sachsen-Anhalt",
    "wof:name":"Evangelische-luth. Kirche",
    "wof:placetype":"venue"
},
  "geometry": {"coordinates":[11.5289716721,51.6658859253],"type":"Point"}
}