{
  "type": "Feature",
  "properties": {
    "iso:country":"DE",
    "sg:address":"Freudenst\u00e4dter Str. 20",
    "sg:city":"Dunningen",
    "sg:phone":"+49 7402/281",
    "sg:postcode":"78655",
    "sg:province":"Baden-W\u00fcrttemberg",
    "wof:name":"Gastst\u00e4tte R\u00f6\u00dfle",
    "wof:placetype":"venue"
},
  "geometry": {"coordinates":[8.4895401001,48.2475547791],"type":"Point"}
}