{
  "type": "Feature",
  "properties": {
    "iso:country":"DE",
    "sg:address":"Cordovastr. 17",
    "sg:city":"Bad Wimpfen",
    "sg:phone":"+49 7063/6503",
    "sg:postcode":"74206",
    "sg:province":"Baden-W\u00fcrttemberg",
    "wof:name":"Gerhard Klein Ingenieur",
    "wof:placetype":"venue"
},
  "geometry": {"coordinates":[9.1594877243,49.2241630554],"type":"Point"}
}