{
  "type": "Feature",
  "properties": {
    "iso:country":"DE",
    "sg:address":"Rosenweg 1",
    "sg:city":"Ockenheim",
    "sg:postcode":"55437",
    "sg:province":"Rheinland-Pfalz",
    "wof:name":"Rabko Handelsgesellschaft Mbh",
    "wof:placetype":"venue"
},
  "geometry": {"coordinates":[7.9677038193,49.9483642578],"type":"Point"}
}