{
  "type": "Feature",
  "properties": {
    "iso:country":"DE",
    "sg:address":"Babelsberger Str. 1",
    "sg:city":"Potsdam",
    "sg:phone":"+49 331/275460",
    "sg:postcode":"14473",
    "sg:province":"Brandenburg",
    "wof:name":"Kaufland Warenhandel Brandenburg Gmbh & Co. Kg",
    "wof:placetype":"venue"
},
  "geometry": {"coordinates":[13.0674600601,52.3927383423],"type":"Point"}
}