{
  "type": "Feature",
  "properties": {
    "iso:country":"DE",
    "sg:address":"Schau-ins-Land 14",
    "sg:city":"Wiesbaden",
    "sg:phone":"+49 611/719685",
    "sg:postcode":"65189",
    "sg:province":"Hessen",
    "wof:name":"Ute Sch\u00f6nfelder Architektin",
    "wof:placetype":"venue"
},
  "geometry": {"coordinates":[8.263963,50.077408],"type":"Point"}
}