{
  "type": "Feature",
  "properties": {
    "iso:country":"DE",
    "sg:address":"Gie\u00dffeldstr. 12",
    "sg:city":"Frankfurt",
    "sg:phone":"+49 69/783435",
    "sg:postcode":"60488",
    "sg:province":"Hessen",
    "wof:name":"Ernst Moch",
    "wof:placetype":"venue"
},
  "geometry": {"coordinates":[8.628603,50.133968],"type":"Point"}
}