{
  "type": "Feature",
  "properties": {
    "iso:country":"DE",
    "sg:address":"Orchheimer Stra\u00dfe 1",
    "sg:city":"Bad M\u00fcnstereifel",
    "sg:phone":"+49 2253/8028",
    "sg:postcode":"53902",
    "sg:province":"Nordrhein-Westfalen",
    "wof:name":"Anwaltskanzlei Nelles",
    "wof:placetype":"venue"
},
  "geometry": {"coordinates":[6.763211,50.553497],"type":"Point"}
}