{
  "type": "Feature",
  "properties": {
    "iso:country":"DE",
    "sg:address":"Talstr. 50",
    "sg:city":"Zella-Mehlis",
    "sg:phone":"+49 3682/46261",
    "sg:postcode":"98544",
    "sg:province":"Th\u00fcringen",
    "wof:name":"M. Rodehau",
    "wof:placetype":"venue"
},
  "geometry": {"coordinates":[10.659074,50.656052],"type":"Point"}
}