{
  "type": "Feature",
  "properties": {
    "iso:country":"DE",
    "sg:address":"Wiebelskircher Weg 18",
    "sg:city":"Berlin",
    "sg:phone":"+49 30/6485833",
    "sg:postcode":"12589",
    "sg:province":"Berlin",
    "wof:name":"Eis-cafe",
    "wof:placetype":"venue"
},
  "geometry": {"coordinates":[13.717796,52.438293],"type":"Point"}
}