{
  "type": "Feature",
  "properties": {
    "iso:country":"DE",
    "sg:address":"Hofackerweg 1",
    "sg:city":"M\u00fcllheim",
    "sg:phone":"+49 7631/5486",
    "sg:postcode":"79379",
    "sg:province":"Baden-W\u00fcrttemberg",
    "wof:name":"Heinrich Birnbreier",
    "wof:placetype":"venue"
},
  "geometry": {"coordinates":[7.6687579155,47.8289108276],"type":"Point"}
}