{
  "type": "Feature",
  "properties": {
    "iso:country":"DE",
    "sg:address":"Frankfurter Str. 17",
    "sg:city":"Bad Rothenfelde",
    "sg:phone":"+49 5424/63158",
    "sg:postcode":"49214",
    "sg:province":"Niedersachsen",
    "wof:name":"Freibad",
    "wof:placetype":"venue"
},
  "geometry": {"coordinates":[8.1624650955,52.1065788269],"type":"Point"}
}