{
  "type": "Feature",
  "properties": {
    "iso:country":"DE",
    "sg:address":"Weinstr. 19",
    "sg:city":"Bad Hersfeld",
    "sg:phone":"+49 6621/2480",
    "sg:postcode":"36251",
    "sg:province":"Hessen",
    "wof:name":"Blumen-bazar",
    "wof:placetype":"venue"
},
  "geometry": {"coordinates":[9.707922,50.868134],"type":"Point"}
}