{
  "type": "Feature",
  "properties": {
    "iso:country":"DE",
    "sg:address":"Taft 15",
    "sg:city":"Norddorf",
    "sg:phone":"+49 4682/949550",
    "sg:postcode":"25946",
    "sg:province":"Schleswig-Holstein",
    "wof:name":"Peter Martinen E. K.",
    "wof:placetype":"venue"
},
  "geometry": {"coordinates":[8.3529310226,54.6505622864],"type":"Point"}
}