{
  "type": "Feature",
  "properties": {
    "iso:country":"DE",
    "sg:address":"Auenweg 6",
    "sg:city":"Schwieberdingen",
    "sg:phone":"+49 7150/31023",
    "sg:postcode":"71701",
    "sg:province":"Baden-W\u00fcrttemberg",
    "wof:name":"Schwebo Stahl Handels-gmbh",
    "wof:placetype":"venue"
},
  "geometry": {"coordinates":[9.072506,48.872414],"type":"Point"}
}