{
  "type": "Feature",
  "properties": {
    "iso:country":"DE",
    "sg:address":"Friedrich-Ebert-Str. 11",
    "sg:city":"Nordhorn",
    "sg:phone":"+49 5921/89110",
    "sg:postcode":"48529",
    "sg:province":"Niedersachsen",
    "wof:name":"Glahe & Stehle Gmbh",
    "wof:placetype":"venue"
},
  "geometry": {"coordinates":[7.063414,52.427738],"type":"Point"}
}