{
  "type": "Feature",
  "properties": {
    "iso:country":"DE",
    "sg:address":"Alte Karlsruher Str. 8",
    "sg:city":"Karlsruhe",
    "sg:postcode":"76227",
    "sg:province":"Baden-W\u00fcrttemberg",
    "wof:name":"Genossenschaft Badischer Friedhofsg\u00e4rtner Eg",
    "wof:placetype":"venue"
},
  "geometry": {"coordinates":[8.4612026215,49.0032539368],"type":"Point"}
}