{
  "type": "Feature",
  "properties": {
    "iso:country":"DE",
    "sg:address":"Paul-Gerhardt-Str. 10",
    "sg:city":"Esslingen",
    "sg:phone":"+49 711/3160980",
    "sg:postcode":"73730",
    "sg:province":"Baden-W\u00fcrttemberg",
    "wof:name":"Rolf Kuch",
    "wof:placetype":"venue"
},
  "geometry": {"coordinates":[9.329426,48.733715],"type":"Point"}
}