{
  "type": "Feature",
  "properties": {
    "iso:country":"DE",
    "sg:address":"Stadtberger Weg 2",
    "sg:city":"Diemelstadt",
    "sg:phone":"+49 2992/2448",
    "sg:postcode":"34474",
    "sg:province":"Hessen",
    "wof:name":"Friedrich-wilh. Schultze",
    "wof:placetype":"venue"
},
  "geometry": {"coordinates":[8.925391,51.470982],"type":"Point"}
}