{
  "type": "Feature",
  "properties": {
    "iso:country":"DE",
    "sg:address":"Porsestr. 37",
    "sg:city":"Ro\u00dflau",
    "sg:phone":"+49 34901/82262",
    "sg:postcode":"06862",
    "sg:province":"Sachsen-Anhalt",
    "wof:name":"Martina Boost",
    "wof:placetype":"venue"
},
  "geometry": {"coordinates":[12.2477703094,51.8875961304],"type":"Point"}
}