{
  "type": "Feature",
  "properties": {
    "iso:country":"DE",
    "sg:address":"Heimchenweg 47",
    "sg:city":"Frankfurt",
    "sg:phone":"+49 69/30039819",
    "sg:postcode":"65929",
    "sg:province":"Hessen",
    "wof:name":"Milly - Bau - Gmbh",
    "wof:placetype":"venue"
},
  "geometry": {"coordinates":[8.5351953506,50.1034889221],"type":"Point"}
}