{
  "type": "Feature",
  "properties": {
    "iso:country":"DE",
    "sg:address":"Forststr. 13",
    "sg:city":"M\u00fcllrose",
    "sg:phone":"+49 33606/880",
    "sg:postcode":"15299",
    "sg:province":"Brandenburg",
    "wof:name":"Hotel Kaiserm\u00fchle Gmbh",
    "wof:placetype":"venue"
},
  "geometry": {"coordinates":[14.451965332,52.2444190979],"type":"Point"}
}