{
  "type": "Feature",
  "properties": {
    "iso:country":"DE",
    "sg:address":"Fichtenstr. 3",
    "sg:city":"Bad Bentheim",
    "sg:phone":"+49 5922/3944",
    "sg:postcode":"48455",
    "sg:province":"Niedersachsen",
    "wof:name":"A. Schr\u00f6er",
    "wof:placetype":"venue"
},
  "geometry": {"coordinates":[7.148916,52.293159],"type":"Point"}
}