{
  "type": "Feature",
  "properties": {
    "iso:country":"DE",
    "sg:address":"Heinrich-Str\u00e4ter-Str. 13",
    "sg:city":"Dortmund",
    "sg:phone":"+49 231/732331",
    "sg:postcode":"44229",
    "sg:province":"Nordrhein-Westfalen",
    "wof:name":"Ulrich Lipke Architekt",
    "wof:placetype":"venue"
},
  "geometry": {"coordinates":[7.466012,51.454227],"type":"Point"}
}