{
  "type": "Feature",
  "properties": {
    "iso:country":"DE",
    "sg:address":"Bergstra\u00dfe 69",
    "sg:city":"Dresden",
    "sg:phone":"+49 351",
    "sg:postcode":"01069",
    "sg:province":"Sachsen",
    "wof:name":"A1 Druck Mit J\u00f6rg\u00b4\u00b4s Atelier",
    "wof:placetype":"venue"
},
  "geometry": {"coordinates":[13.732034,51.025635],"type":"Point"}
}