{
  "type": "Feature",
  "properties": {
    "iso:country":"DE",
    "sg:address":"Egerl\u00e4nder Str. 1",
    "sg:city":"Neumarkt",
    "sg:phone":"+49 9181/41007",
    "sg:postcode":"92318",
    "sg:province":"Bayern",
    "wof:name":"Otto Richter Kg",
    "wof:placetype":"venue"
},
  "geometry": {"coordinates":[11.467854,49.279942],"type":"Point"}
}