{
  "type": "Feature",
  "properties": {
    "iso:country":"DE",
    "sg:address":"Egaustr. 10",
    "sg:city":"Aalen",
    "sg:phone":"+49 7367/7297",
    "sg:postcode":"73432",
    "sg:province":"Baden-W\u00fcrttemberg",
    "wof:name":"Helmut Minder",
    "wof:placetype":"venue"
},
  "geometry": {"coordinates":[10.2068443298,48.8214378357],"type":"Point"}
}