{
  "type": "Feature",
  "properties": {
    "iso:country":"DE",
    "sg:address":"Allg\u00e4uer Str. 36",
    "sg:city":"Pfronten",
    "sg:phone":"+49 8363/5031",
    "sg:postcode":"87459",
    "sg:province":"Bayern",
    "wof:name":"Dr. Med. Dirk Stender",
    "wof:placetype":"venue"
},
  "geometry": {"coordinates":[10.5597877502,47.5847587585],"type":"Point"}
}