{
  "type": "Feature",
  "properties": {
    "iso:country":"DE",
    "sg:address":"Rottstr. 80",
    "sg:city":"Vlotho",
    "sg:phone":"+49 5733/3684",
    "sg:postcode":"32602",
    "sg:province":"Nordrhein-Westfalen",
    "wof:name":"Friedrich Begemann",
    "wof:placetype":"venue"
},
  "geometry": {"coordinates":[8.840553,52.14542],"type":"Point"}
}