{
  "type": "Feature",
  "properties": {
    "iso:country":"DE",
    "sg:address":"Barmstedter Str. 2-4",
    "sg:city":"Kaltenkirchen",
    "sg:phone":"+49 4191/72880",
    "sg:postcode":"24568",
    "sg:province":"Schleswig-Holstein",
    "wof:name":"J. S. Zimmerei Gmbh",
    "wof:placetype":"venue"
},
  "geometry": {"coordinates":[9.9510450363,53.8354377747],"type":"Point"}
}