{
  "type": "Feature",
  "properties": {
    "iso:country":"DE",
    "sg:address":"Nemter Weg 7",
    "sg:city":"Wurzen",
    "sg:phone":"+49 3425/8519776",
    "sg:postcode":"04808",
    "sg:province":"Sachsen",
    "wof:name":"Cannewitzer Bier",
    "wof:placetype":"venue"
},
  "geometry": {"coordinates":[12.7628726959,51.358505249],"type":"Point"}
}