{
  "type": "Feature",
  "properties": {
    "iso:country":"DE",
    "sg:address":"Kurparkstr. 5",
    "sg:city":"Bad Orb",
    "sg:phone":"+49 6052/2805",
    "sg:postcode":"63619",
    "sg:province":"Hessen",
    "wof:name":"Wolfram Hildebrandt Rechtsanwalt Und Notar",
    "wof:placetype":"venue"
},
  "geometry": {"coordinates":[9.3507614136,50.2237586975],"type":"Point"}
}