{
  "type": "Feature",
  "properties": {
    "iso:country":"DE",
    "sg:address":"Markt 5",
    "sg:city":"Radevormwald",
    "sg:phone":"+49 2195/4515",
    "sg:postcode":"42477",
    "sg:province":"Nordrhein-Westfalen",
    "wof:name":"K. Erdmann",
    "wof:placetype":"venue"
},
  "geometry": {"coordinates":[7.3573579788,51.2030601501],"type":"Point"}
}