{
  "type": "Feature",
  "properties": {
    "iso:country":"DE",
    "sg:address":"Kiefernweg 1",
    "sg:city":"Henstedt-Ulzburg",
    "sg:phone":"+49 4193/7890",
    "sg:postcode":"24558",
    "sg:province":"Schleswig-Holstein",
    "wof:name":"Alsterbeton Gmbh",
    "wof:placetype":"venue"
},
  "geometry": {"coordinates":[9.98938,53.764912],"type":"Point"}
}