{
  "type": "Feature",
  "properties": {
    "iso:country":"DE",
    "sg:address":"K\u00f6lner Str. 581",
    "sg:city":"Krefeld",
    "sg:postcode":"47807",
    "sg:province":"Nordrhein-Westfalen",
    "wof:name":"Defacto - Young Fashion- Store Gmbh",
    "wof:placetype":"venue"
},
  "geometry": {"coordinates":[6.5895438194,51.3030128479],"type":"Point"}
}