{
  "type": "Feature",
  "properties": {
    "iso:country":"DE",
    "sg:address":"Streitfeldstr. 17",
    "sg:city":"M\u00fcnchen",
    "sg:phone":"+49 89/4315021",
    "sg:postcode":"81673",
    "sg:province":"Bayern",
    "wof:name":"Kuhn Malereibetrieb Und Werbetechnik Gmbh",
    "wof:placetype":"venue"
},
  "geometry": {"coordinates":[11.618752,48.131771],"type":"Point"}
}