{
  "type": "Feature",
  "properties": {
    "iso:country":"DE",
    "sg:address":"K\u00f6lner Str. 51",
    "sg:city":"Erkelenz",
    "sg:phone":"+49 2431/5372",
    "sg:postcode":"41812",
    "sg:province":"Nordrhein-Westfalen",
    "wof:name":"F. Huybrechts",
    "wof:placetype":"venue"
},
  "geometry": {"coordinates":[6.31914711,51.0770568848],"type":"Point"}
}