{
  "type": "Feature",
  "properties": {
    "iso:country":"DE",
    "sg:address":"M\u00fchltorstr. 4",
    "sg:city":"Velden",
    "sg:phone":"+49 9152/7183",
    "sg:postcode":"91235",
    "sg:province":"Bayern",
    "wof:name":"H.-w. Gerstacker",
    "wof:placetype":"venue"
},
  "geometry": {"coordinates":[11.51060009,49.6137580872],"type":"Point"}
}