{
  "type": "Feature",
  "properties": {
    "iso:country":"DE",
    "sg:address":"Weidachstr. 54",
    "sg:city":"F\u00fcssen",
    "sg:phone":"+49 8362/6464",
    "sg:postcode":"87629",
    "sg:province":"Bayern",
    "wof:name":"Reinhard Kleebauer Berg- U. Skischule",
    "wof:placetype":"venue"
},
  "geometry": {"coordinates":[10.7078208923,47.5754241943],"type":"Point"}
}