{
  "type": "Feature",
  "properties": {
    "iso:country":"DE",
    "sg:address":"Goethestr. 2",
    "sg:city":"Hirschberg",
    "sg:phone":"+49 6201/51015",
    "sg:postcode":"69493",
    "sg:province":"Baden-W\u00fcrttemberg",
    "wof:name":"Hotel Hirschberg",
    "wof:placetype":"venue"
},
  "geometry": {"coordinates":[8.6568803787,49.495464325],"type":"Point"}
}