{
  "type": "Feature",
  "properties": {
    "iso:country":"DE",
    "sg:address":"Benzstr. 22",
    "sg:city":"Goch",
    "sg:phone":"+49 2823/3031",
    "sg:postcode":"47574",
    "sg:province":"Nordrhein-Westfalen",
    "wof:name":"As-leuchten Gmbh",
    "wof:placetype":"venue"
},
  "geometry": {"coordinates":[6.144825,51.685669],"type":"Point"}
}