{
  "type": "Feature",
  "properties": {
    "iso:country":"DE",
    "sg:address":"Freiherr-vom-Stein-Str. 2",
    "sg:city":"Elz",
    "sg:phone":"+49 700 8433 6000",
    "sg:postcode":"65604",
    "sg:province":"Hessen",
    "wof:name":"Gerd C. Meyd Handelsonderneming Gmbh",
    "wof:placetype":"venue"
},
  "geometry": {"coordinates":[8.03625,50.406708],"type":"Point"}
}