{
  "type": "Feature",
  "properties": {
    "iso:country":"DE",
    "sg:address":"Chopinstr. 7",
    "sg:city":"Leipzig",
    "sg:phone":"+49 341/9600014",
    "sg:postcode":"04103",
    "sg:province":"Sachsen",
    "wof:name":"Sinus Werbung Leipzig",
    "wof:placetype":"venue"
},
  "geometry": {"coordinates":[12.38765,51.343391],"type":"Point"}
}