{
  "type": "Feature",
  "properties": {
    "iso:country":"DE",
    "sg:address":"Balthasar-Vitzthum-Str. 23",
    "sg:city":"Gauting",
    "sg:phone":"+49 89/8506251",
    "sg:postcode":"82131",
    "sg:province":"Bayern",
    "wof:name":"Joachim Von Merten Rechtsanwalt",
    "wof:placetype":"venue"
},
  "geometry": {"coordinates":[11.380405426,48.0690002441],"type":"Point"}
}