{
  "type": "Feature",
  "properties": {
    "iso:country":"DE",
    "sg:address":"An der Marsch 2",
    "sg:city":"Gilten",
    "sg:postcode":"29690",
    "sg:province":"Niedersachsen",
    "wof:name":"Konzeptbau F\u00fcnfte Grund- St\u00fccksges. Mbh",
    "wof:placetype":"venue"
},
  "geometry": {"coordinates":[9.58051,52.704826],"type":"Point"}
}