{
  "type": "Feature",
  "properties": {
    "iso:country":"DE",
    "sg:address":"Annabergstr. 30",
    "sg:city":"Haltern",
    "sg:postcode":"45721",
    "sg:province":"Nordrhein-Westfalen",
    "wof:name":"Soester Glasdruck Gmbh",
    "wof:placetype":"venue"
},
  "geometry": {"coordinates":[7.1786828041,51.736831665],"type":"Point"}
}