{
  "type": "Feature",
  "properties": {
    "iso:country":"DE",
    "sg:address":"Jockenstr. 19 b",
    "sg:city":"Moers",
    "sg:phone":"+49 2841/45971",
    "sg:postcode":"47445",
    "sg:province":"Nordrhein-Westfalen",
    "wof:name":"W. Crysandt Ingenieur",
    "wof:placetype":"venue"
},
  "geometry": {"coordinates":[6.6271162033,51.4687538147],"type":"Point"}
}