{
  "type": "Feature",
  "properties": {
    "iso:country":"DE",
    "sg:address":"Hauptstr. 64",
    "sg:city":"Mulda",
    "sg:postcode":"09619",
    "sg:province":"Sachsen",
    "wof:name":"G\u00f6hler-sitzm\u00f6bel Gmbh",
    "wof:placetype":"venue"
},
  "geometry": {"coordinates":[13.4127779007,50.8073158264],"type":"Point"}
}