{
  "type": "Feature",
  "properties": {
    "iso:country":"DE",
    "sg:address":"Karlstr. 61",
    "sg:city":"Karlsruhe",
    "sg:phone":"+49 721/29849",
    "sg:postcode":"76133",
    "sg:province":"Baden-W\u00fcrttemberg",
    "wof:name":"Beratungsstelle Des Badischen Landesverbandes",
    "wof:placetype":"venue"
},
  "geometry": {"coordinates":[8.394665,49.002975],"type":"Point"}
}