{
  "type": "Feature",
  "properties": {
    "iso:country":"DE",
    "sg:address":"Hauptstrasse 9",
    "sg:city":"Naila",
    "sg:phone":"+49 9282/7524",
    "sg:postcode":"95119",
    "sg:province":"Bayern",
    "wof:name":"Leder Ziehr - Service Ist Unsere St\u00e4rke",
    "wof:placetype":"venue"
},
  "geometry": {"coordinates":[11.7078523636,50.3297691345],"type":"Point"}
}