{
  "type": "Feature",
  "properties": {
    "iso:country":"DE",
    "sg:address":"Hermann-B\u00f6ssow-Str. 16",
    "sg:city":"Bad Oldesloe",
    "sg:phone":"+49 4531/81474",
    "sg:postcode":"23843",
    "sg:province":"Schleswig-Holstein",
    "wof:name":"H. Gramkow",
    "wof:placetype":"venue"
},
  "geometry": {"coordinates":[10.4064073563,53.8010978699],"type":"Point"}
}