{
  "type": "Feature",
  "properties": {
    "iso:country":"DE",
    "sg:address":"Gottlieb-Daimler-Str 14",
    "sg:city":"Gera",
    "sg:phone":"+49 365/4208570",
    "sg:postcode":"07552",
    "sg:province":"Th\u00fcringen",
    "wof:name":"Geb Gera Edv Beratungsgesellschaft Mbh",
    "wof:placetype":"venue"
},
  "geometry": {"coordinates":[12.1069450378,50.9005432129],"type":"Point"}
}