{
  "type": "Feature",
  "properties": {
    "iso:country":"DE",
    "sg:address":"Im Schlenk 72",
    "sg:city":"Duisburg",
    "sg:phone":"+49 203/735157",
    "sg:postcode":"47055",
    "sg:province":"Nordrhein-Westfalen",
    "wof:name":"New Art Photography B. Kraft",
    "wof:placetype":"venue"
},
  "geometry": {"coordinates":[6.7696027756,51.4010124207],"type":"Point"}
}