{
  "type": "Feature",
  "properties": {
    "iso:country":"DE",
    "sg:address":"Heimst\u00e4ttenstr. 51",
    "sg:city":"Burgst\u00e4dt",
    "sg:phone":"+49 3724/854949",
    "sg:postcode":"09217",
    "sg:province":"Sachsen",
    "wof:name":"Bremer Kaffeemaschinen",
    "wof:placetype":"venue"
},
  "geometry": {"coordinates":[12.8297996521,50.8941307068],"type":"Point"}
}