{
  "type": "Feature",
  "properties": {
    "iso:country":"DE",
    "sg:address":"Hauptstr. 27",
    "sg:city":"Endingen",
    "sg:phone":"+49 7642/4397",
    "sg:postcode":"79346",
    "sg:province":"Baden-W\u00fcrttemberg",
    "wof:name":"R. R\u00fcsch",
    "wof:placetype":"venue"
},
  "geometry": {"coordinates":[9.1767749786,48.3894500732],"type":"Point"}
}