{
  "type": "Feature",
  "properties": {
    "iso:country":"DE",
    "sg:address":"Memeler Str. 2",
    "sg:city":"Burghaun",
    "sg:phone":"+49 6652/4762",
    "sg:postcode":"36151",
    "sg:province":"Hessen",
    "wof:name":"Franz Kimpel Innenausbau",
    "wof:placetype":"venue"
},
  "geometry": {"coordinates":[9.722263,50.693398],"type":"Point"}
}