{
  "type": "Feature",
  "properties": {
    "iso:country":"DE",
    "sg:address":"Wiegbold 1",
    "sg:city":"Ahaus",
    "sg:phone":"+49 2561/82319",
    "sg:postcode":"48683",
    "sg:province":"Nordrhein-Westfalen",
    "wof:name":"Metallbau H\u00f6lscher Gmbh",
    "wof:placetype":"venue"
},
  "geometry": {"coordinates":[6.9182310104,52.0745506287],"type":"Point"}
}