{
  "type": "Feature",
  "properties": {
    "iso:country":"DE",
    "sg:address":"Saarburger Ring 17",
    "sg:city":"Mannheim",
    "sg:phone":"+49 621/479004",
    "sg:postcode":"68229",
    "sg:province":"Baden-W\u00fcrttemberg",
    "wof:name":"Ts Integra Ges. F\u00fcr Daten- Technik Mbh",
    "wof:placetype":"venue"
},
  "geometry": {"coordinates":[8.5754241943,49.4451904297],"type":"Point"}
}