{
  "type": "Feature",
  "properties": {
    "iso:country":"DE",
    "sg:address":"Hauptstr. 20a",
    "sg:city":"Winterrieden",
    "sg:phone":"+49 8333/7159",
    "sg:postcode":"87785",
    "sg:province":"Bayern",
    "wof:name":"H. P. Mayer",
    "wof:placetype":"venue"
},
  "geometry": {"coordinates":[10.2272148132,48.1203804016],"type":"Point"}
}