{
  "type": "Feature",
  "properties": {
    "iso:country":"DE",
    "sg:address":"Hauptstr. 56",
    "sg:city":"Raumbach",
    "sg:phone":"+49 6753/5311",
    "sg:postcode":"55592",
    "sg:province":"Rheinland-Pfalz",
    "wof:name":"J\u00fcrgen Greulach",
    "wof:placetype":"venue"
},
  "geometry": {"coordinates":[7.6551232338,49.723033905],"type":"Point"}
}