{
  "type": "Feature",
  "properties": {
    "iso:country":"DE",
    "sg:address":"Hauptstr. 2",
    "sg:city":"Grefrath",
    "sg:phone":"+49 2158/5253",
    "sg:postcode":"47929",
    "sg:province":"Nordrhein-Westfalen",
    "wof:name":"Peter Ungerechts",
    "wof:placetype":"venue"
},
  "geometry": {"coordinates":[6.371233,51.336578],"type":"Point"}
}