{
  "type": "Feature",
  "properties": {
    "iso:country":"DE",
    "sg:address":"Brachfeldstr. 3",
    "sg:city":"Offenburg",
    "sg:phone":"+49 781/35553",
    "sg:postcode":"77654",
    "sg:province":"Baden-W\u00fcrttemberg",
    "wof:name":"Blumen-einstein Inh. Hans-martin Einstein",
    "wof:placetype":"venue"
},
  "geometry": {"coordinates":[7.95777,48.470566],"type":"Point"}
}