{
  "type": "Feature",
  "properties": {
    "iso:country":"DE",
    "sg:address":"Zum Kissel 7",
    "sg:city":"Neunkirchen",
    "sg:phone":"+49 6821/41512",
    "sg:postcode":"66539",
    "sg:province":"Saarland",
    "wof:name":"Otto Rebel",
    "wof:placetype":"venue"
},
  "geometry": {"coordinates":[7.207163,49.356636],"type":"Point"}
}