{
  "type": "Feature",
  "properties": {
    "iso:country":"DE",
    "sg:address":"Treskowstr. 10",
    "sg:city":"Berlin",
    "sg:phone":"+49 30/4773794",
    "sg:postcode":"13156",
    "sg:province":"Berlin",
    "wof:name":"Wolfgang Speer",
    "wof:placetype":"venue"
},
  "geometry": {"coordinates":[13.396718,52.582153],"type":"Point"}
}