{
  "type": "Feature",
  "properties": {
    "iso:country":"DE",
    "sg:address":"Parkring 21",
    "sg:city":"Paretz",
    "sg:phone":"+49 33233/80509",
    "sg:postcode":"14669",
    "sg:province":"Brandenburg",
    "wof:name":"Restaurant Gotisches Haus",
    "wof:placetype":"venue"
},
  "geometry": {"coordinates":[12.8774614334,52.4700126648],"type":"Point"}
}