{
  "type": "Feature",
  "properties": {
    "iso:country":"DE",
    "sg:address":"Alstertor",
    "sg:city":"Hamburg",
    "sg:phone":"+49 40/335779",
    "sg:postcode":"20095",
    "sg:province":"Hamburg",
    "wof:name":"Aaa Altstadtblume Am Alstertor",
    "wof:placetype":"venue"
},
  "geometry": {"coordinates":[9.9969596863,53.5527000427],"type":"Point"}
}