{
  "type": "Feature",
  "properties": {
    "iso:country":"DE",
    "sg:address":"Schneidergasse 17",
    "sg:city":"Sch\u00f6nenberg-K\u00fcbelberg",
    "sg:phone":"+49 6373/3717",
    "sg:postcode":"66901",
    "sg:province":"Rheinland-Pfalz",
    "wof:name":"Karl Druck Immobilienmakler",
    "wof:placetype":"venue"
},
  "geometry": {"coordinates":[7.3730478287,49.4100151062],"type":"Point"}
}