{
  "type": "Feature",
  "properties": {
    "iso:country":"DE",
    "sg:address":"Seeburger Chaussee 2",
    "sg:city":"Gro\u00df Glienicke",
    "sg:phone":"+49 33201/31722",
    "sg:postcode":"14476",
    "sg:province":"Brandenburg",
    "wof:name":"Landesentwicklungsgesellschaft F. St\u00e4dtebau Wohnen U. Verkehr",
    "wof:placetype":"venue"
},
  "geometry": {"coordinates":[13.109779,52.472107],"type":"Point"}
}