{
  "type": "Feature",
  "properties": {
    "iso:country":"DE",
    "sg:address":"Bahnhofstr. 67",
    "sg:city":"Neuss",
    "sg:phone":"+49 2131/745410",
    "sg:postcode":"41472",
    "sg:province":"Nordrhein-Westfalen",
    "wof:name":"Kaisers Supermarkt",
    "wof:placetype":"venue"
},
  "geometry": {"coordinates":[6.6651601791,51.1633148193],"type":"Point"}
}