{
  "type": "Feature",
  "properties": {
    "iso:country":"DE",
    "sg:address":"Rudower Stra\u00dfe 60",
    "sg:city":"Berlin",
    "sg:phone":"+49 30",
    "sg:postcode":"12524",
    "sg:province":"Berlin",
    "wof:name":"Hausmann-immobilien Vdm",
    "wof:placetype":"venue"
},
  "geometry": {"coordinates":[13.5378761292,52.4208564758],"type":"Point"}
}