{
  "type": "Feature",
  "properties": {
    "iso:country":"DE",
    "sg:address":"Ringstr. 55",
    "sg:city":"Seevetal",
    "sg:phone":"+49 4105/51743",
    "sg:postcode":"21218",
    "sg:province":"Niedersachsen",
    "wof:name":"Wilfried Diederich",
    "wof:placetype":"venue"
},
  "geometry": {"coordinates":[9.9967184067,53.3724594116],"type":"Point"}
}