{
  "type": "Feature",
  "properties": {
    "iso:country":"DE",
    "sg:address":"Marktplatz 67",
    "sg:city":"Waischenfeld",
    "sg:phone":"+49 9202/203",
    "sg:postcode":"91344",
    "sg:province":"Bayern",
    "wof:name":"H. Und Karin Landmann",
    "wof:placetype":"venue"
},
  "geometry": {"coordinates":[11.3450660706,49.8446807861],"type":"Point"}
}