{
  "type": "Feature",
  "properties": {
    "iso:country":"DE",
    "sg:address":"Schaldingerstrasse 48",
    "sg:city":"Passau",
    "sg:phone":"+49 851/49040",
    "sg:postcode":"94036",
    "sg:province":"Bayern",
    "wof:name":"Lenz & Friends",
    "wof:placetype":"venue"
},
  "geometry": {"coordinates":[13.368886,48.596443],"type":"Point"}
}