{
  "type": "Feature",
  "properties": {
    "iso:country":"DE",
    "sg:address":"Im Taubengrund 31",
    "sg:city":"Kelsterbach",
    "sg:phone":"+49 6107/77080",
    "sg:postcode":"65451",
    "sg:province":"Hessen",
    "wof:name":"Sdv Deutschland Gmbh",
    "wof:placetype":"venue"
},
  "geometry": {"coordinates":[8.5438499451,50.0484886169],"type":"Point"}
}