{
  "type": "Feature",
  "properties": {
    "iso:country":"DE",
    "sg:address":"Heldenbergstr. 28",
    "sg:city":"Donzdorf",
    "sg:phone":"+49 7162/24268",
    "sg:postcode":"73072",
    "sg:province":"Baden-W\u00fcrttemberg",
    "wof:name":"Dieter Deppert Anlageberater",
    "wof:placetype":"venue"
},
  "geometry": {"coordinates":[9.8237428665,48.7125015259],"type":"Point"}
}