{
  "type": "Feature",
  "properties": {
    "iso:country":"DE",
    "sg:address":"Wielandstr. 16",
    "sg:city":"Berlin",
    "sg:phone":"+49 30/3244223",
    "sg:postcode":"10629",
    "sg:province":"Berlin",
    "wof:name":"Prof. Dr. Fritz Neumeyer Architekt",
    "wof:placetype":"venue"
},
  "geometry": {"coordinates":[13.315066,52.502625],"type":"Point"}
}