{
  "type": "Feature",
  "properties": {
    "iso:country":"DE",
    "sg:address":"Hohe Haar 40",
    "sg:city":"Essen",
    "sg:phone":"+49 201/585197",
    "sg:postcode":"45277",
    "sg:province":"Nordrhein-Westfalen",
    "wof:name":"Altfried Beele Komponist",
    "wof:placetype":"venue"
},
  "geometry": {"coordinates":[7.0921578407,51.4223556519],"type":"Point"}
}