{
  "type": "Feature",
  "properties": {
    "iso:country":"DE",
    "sg:address":"Schellingstr. 2",
    "sg:city":"Frankfurt",
    "sg:phone":"+49 69/94419877",
    "sg:postcode":"60316",
    "sg:province":"Hessen",
    "wof:name":"Rmg Publishing Gmbh",
    "wof:placetype":"venue"
},
  "geometry": {"coordinates":[8.700021,50.121189],"type":"Point"}
}