{
  "type": "Feature",
  "properties": {
    "iso:country":"DE",
    "sg:address":"Forlenstr. 5",
    "sg:city":"Karlsbad",
    "sg:phone":"+49 7202/7896",
    "sg:postcode":"76307",
    "sg:province":"Baden-W\u00fcrttemberg",
    "wof:name":"Eve Elektronik-vertriebs- Und Entwicklungs Gmbh",
    "wof:placetype":"venue"
},
  "geometry": {"coordinates":[8.5333299637,48.9168701172],"type":"Point"}
}