{
  "type": "Feature",
  "properties": {
    "iso:country":"DE",
    "sg:address":"Neumannstr. 125",
    "sg:city":"Berlin",
    "sg:postcode":"13189",
    "sg:province":"Berlin",
    "wof:name":"Dr. Med. Annee M\u00fcnchoff",
    "wof:placetype":"venue"
},
  "geometry": {"coordinates":[13.423362,52.554871],"type":"Point"}
}