{
  "type": "Feature",
  "properties": {
    "iso:country":"DE",
    "sg:address":"Penzenhofener Str. 6 A",
    "sg:city":"Winkelhaid",
    "sg:postcode":"90610",
    "sg:province":"Bayern",
    "wof:name":"Edeka Aktiv-markt Manfred Borke",
    "wof:placetype":"venue"
},
  "geometry": {"coordinates":[11.3017911911,49.3871498108],"type":"Point"}
}