{
  "type": "Feature",
  "properties": {
    "iso:country":"DE",
    "sg:address":"Johanniterstr. 6",
    "sg:city":"Dierdorf",
    "sg:phone":"+49 2689/979014",
    "sg:postcode":"56269",
    "sg:province":"Rheinland-Pfalz",
    "wof:name":"Holl & Partner Software Gmbh",
    "wof:placetype":"venue"
},
  "geometry": {"coordinates":[7.659747,50.547062],"type":"Point"}
}