{
  "type": "Feature",
  "properties": {
    "iso:country":"DE",
    "sg:address":"Gunzenhausener Str. 48",
    "sg:city":"Bechhofen",
    "sg:phone":"+49 9822/251",
    "sg:postcode":"91572",
    "sg:province":"Bayern",
    "wof:name":"Alfred Lang",
    "wof:placetype":"venue"
},
  "geometry": {"coordinates":[10.555245,49.158031],"type":"Point"}
}