{
  "type": "Feature",
  "properties": {
    "iso:country":"DE",
    "sg:address":"Tiergartenstr. 66",
    "sg:city":"Hannover",
    "sg:phone":"+49 511/522721",
    "sg:postcode":"30559",
    "sg:province":"Niedersachsen",
    "wof:name":"Helmut Giersberg",
    "wof:placetype":"venue"
},
  "geometry": {"coordinates":[9.820372,52.36232],"type":"Point"}
}