{
  "type": "Feature",
  "properties": {
    "iso:country":"DE",
    "sg:address":"Kirchstr. 199",
    "sg:city":"Ostrhauderfehn",
    "sg:phone":"+49 4952/4482",
    "sg:postcode":"26842",
    "sg:province":"Niedersachsen",
    "wof:name":"Theda Vahl Heilpraktikerin",
    "wof:placetype":"venue"
},
  "geometry": {"coordinates":[7.6193041801,53.1161193848],"type":"Point"}
}