{
  "type": "Feature",
  "properties": {
    "iso:country":"DE",
    "sg:address":"Haushoferstr. 10a",
    "sg:city":"Seebruck",
    "sg:phone":"+49 8667/7339",
    "sg:postcode":"83358",
    "sg:province":"Bayern",
    "wof:name":"Heinz-georg Plikat Steuerberater",
    "wof:placetype":"venue"
},
  "geometry": {"coordinates":[12.4831418991,47.9342842102],"type":"Point"}
}