{
  "type": "Feature",
  "properties": {
    "iso:country":"DE",
    "sg:address":"R\u00fcbezahlweg 82",
    "sg:city":"Leonberg",
    "sg:phone":"+49 7152/949453",
    "sg:postcode":"71229",
    "sg:province":"Baden-W\u00fcrttemberg",
    "wof:name":"M. Naumann",
    "wof:placetype":"venue"
},
  "geometry": {"coordinates":[9.0234556198,48.7921485901],"type":"Point"}
}