{
  "type": "Feature",
  "properties": {
    "iso:country":"DE",
    "sg:address":"Leite 45",
    "sg:city":"Kleinmachnow",
    "sg:phone":"+49 33203/22140",
    "sg:postcode":"14532",
    "sg:province":"Brandenburg",
    "wof:name":"Hans Wolf",
    "wof:placetype":"venue"
},
  "geometry": {"coordinates":[13.2095966339,52.4023513794],"type":"Point"}
}