{
  "type": "Feature",
  "properties": {
    "iso:country":"DE",
    "sg:address":"Wilkeplatz 8",
    "sg:city":"Warstein",
    "sg:phone":"+49 2902/71090",
    "sg:postcode":"59581",
    "sg:province":"Nordrhein-Westfalen",
    "wof:name":"Hotel Joh. R\u00f6ttger",
    "wof:placetype":"venue"
},
  "geometry": {"coordinates":[8.3362970352,51.485584259],"type":"Point"}
}