{
  "type": "Feature",
  "properties": {
    "iso:country":"DE",
    "sg:address":"Im Teelbruch 55",
    "sg:city":"Essen",
    "sg:phone":"+49 2054/928182",
    "sg:postcode":"45219",
    "sg:province":"Nordrhein-Westfalen",
    "wof:name":"Wir - Treuhand Unternehmensberatungsges. Mbh",
    "wof:placetype":"venue"
},
  "geometry": {"coordinates":[6.936644,51.377041],"type":"Point"}
}