{
  "type": "Feature",
  "properties": {
    "iso:country":"DE",
    "sg:address":"Lessingstr. 31",
    "sg:city":"Schwerin",
    "sg:phone":"+49 385/714439",
    "sg:postcode":"19059",
    "sg:province":"Mecklenburg-Vorpommern",
    "wof:name":"J. Wunsch",
    "wof:placetype":"venue"
},
  "geometry": {"coordinates":[11.388735,53.63464],"type":"Point"}
}