{
  "type": "Feature",
  "properties": {
    "iso:country":"DE",
    "sg:address":"Lister Meile 50",
    "sg:city":"Hannover",
    "sg:phone":"+49 531/33652990",
    "sg:postcode":"30161",
    "sg:province":"Niedersachsen",
    "wof:name":"Vdmv Versorgungswerk Der Deutschen Medien- Und",
    "wof:placetype":"venue"
},
  "geometry": {"coordinates":[9.7472667694,52.3851165771],"type":"Point"}
}