{
  "type": "Feature",
  "properties": {
    "iso:country":"DE",
    "sg:address":"Langerfelder Str. 121",
    "sg:city":"Wuppertal",
    "sg:phone":"+49 202/2602549",
    "sg:postcode":"42389",
    "sg:province":"Nordrhein-Westfalen",
    "wof:name":"Bp Tankstelle",
    "wof:placetype":"venue"
},
  "geometry": {"coordinates":[7.2387599945,51.2740592957],"type":"Point"}
}