{
  "type": "Feature",
  "properties": {
    "iso:country":"DE",
    "sg:address":"Essenbach",
    "sg:city":"Essenbach",
    "sg:phone":"+49 8703/9303",
    "sg:postcode":"84051",
    "sg:province":"Bayern",
    "wof:name":"Raiffeisenbank Essenbach Eg",
    "wof:placetype":"venue"
},
  "geometry": {"coordinates":[12.21779,48.619751],"type":"Point"}
}