{
  "type": "Feature",
  "properties": {
    "iso:country":"DE",
    "sg:address":"Schulstr. 6-8",
    "sg:city":"Hilden",
    "sg:postcode":"40721",
    "sg:province":"Nordrhein-Westfalen",
    "wof:name":"Sporthaus Hilden Gmbh",
    "wof:placetype":"venue"
},
  "geometry": {"coordinates":[6.9324469566,51.1677131653],"type":"Point"}
}