{
  "type": "Feature",
  "properties": {
    "iso:country":"DE",
    "sg:address":"Torgauer Platz 3",
    "sg:city":"Leipzig",
    "sg:phone":"+49 341/69710",
    "sg:postcode":"04315",
    "sg:province":"Sachsen",
    "wof:name":"Compunet Computer Vertriebs-gmbh",
    "wof:placetype":"venue"
},
  "geometry": {"coordinates":[12.4153156281,51.3457832336],"type":"Point"}
}