{
  "type": "Feature",
  "properties": {
    "iso:country":"DE",
    "sg:address":"Hag\u00e4ckerstr.",
    "sg:city":"Ostfildern",
    "sg:phone":"+49 711/453808",
    "sg:postcode":"73760",
    "sg:province":"Baden-W\u00fcrttemberg",
    "wof:name":"Hallenbad Kemnat",
    "wof:placetype":"venue"
},
  "geometry": {"coordinates":[9.2259349823,48.7250595093],"type":"Point"}
}