{
  "type": "Feature",
  "properties": {
    "iso:country":"DE",
    "sg:address":"Am Kleink\u00f6riser See 5",
    "sg:city":"Gro\u00df K\u00f6ris",
    "sg:phone":"+49 33766/62730",
    "sg:postcode":"15746",
    "sg:province":"Brandenburg",
    "wof:name":"Jugendherberge Kleink\u00f6ris",
    "wof:placetype":"venue"
},
  "geometry": {"coordinates":[13.6525850296,52.1592292786],"type":"Point"}
}