{
  "type": "Feature",
  "properties": {
    "iso:country":"DE",
    "sg:address":"Alleestr. 13",
    "sg:city":"Norden",
    "sg:phone":"+49 4931/12066",
    "sg:postcode":"26506",
    "sg:province":"Niedersachsen",
    "wof:name":"Thade Gerdes",
    "wof:placetype":"venue"
},
  "geometry": {"coordinates":[7.192819,53.591148],"type":"Point"}
}