{
  "type": "Feature",
  "properties": {
    "iso:country":"DE",
    "sg:address":"Auf'm Hofacker 7",
    "sg:city":"Meckenbach",
    "sg:phone":"+49 6752/2971",
    "sg:postcode":"55606",
    "sg:province":"Rheinland-Pfalz",
    "wof:name":"C. Reich",
    "wof:placetype":"venue"
},
  "geometry": {"coordinates":[7.510619,49.774689],"type":"Point"}
}