{
  "type": "Feature",
  "properties": {
    "iso:country":"DE",
    "sg:address":"Maierstr. 5",
    "sg:city":"Stuttgart",
    "sg:phone":"+49 711/7187630",
    "sg:postcode":"70567",
    "sg:province":"Baden-W\u00fcrttemberg",
    "wof:name":"Ludwig Weipert Ingenieur",
    "wof:placetype":"venue"
},
  "geometry": {"coordinates":[9.1448945999,48.7268447876],"type":"Point"}
}