{
  "type": "Feature",
  "properties": {
    "iso:country":"DE",
    "sg:address":"Pedettistr. 32",
    "sg:city":"Eichst\u00e4tt",
    "sg:phone":"+49 8421/4697",
    "sg:postcode":"85072",
    "sg:province":"Bayern",
    "wof:name":"Konrad Bayer",
    "wof:placetype":"venue"
},
  "geometry": {"coordinates":[11.1835622787,48.8947982788],"type":"Point"}
}