{
  "type": "Feature",
  "properties": {
    "iso:country":"DE",
    "sg:address":"Grethenweg 129",
    "sg:city":"Frankfurt",
    "sg:phone":"+49 69/68608186",
    "sg:postcode":"60598",
    "sg:province":"Hessen",
    "wof:name":"Rhino Linings Produkte Vertriebs Gmbh",
    "wof:placetype":"venue"
},
  "geometry": {"coordinates":[8.6889696121,50.0929756165],"type":"Point"}
}