{
  "type": "Feature",
  "properties": {
    "iso:country":"DE",
    "sg:address":"K\u00f6lner Str. 273",
    "sg:city":"Gummersbach",
    "sg:phone":"+49 2261/22122",
    "sg:postcode":"51645",
    "sg:province":"Nordrhein-Westfalen",
    "wof:name":"Schlachthof Genossenschaft Gummersbach Eg.",
    "wof:placetype":"venue"
},
  "geometry": {"coordinates":[7.5733151436,51.0041351318],"type":"Point"}
}