{
  "type": "Feature",
  "properties": {
    "iso:country":"DE",
    "sg:address":"Oststr. 162",
    "sg:city":"D\u00fcsseldorf",
    "sg:phone":"+49 211/365176",
    "sg:postcode":"40210",
    "sg:province":"Nordrhein-Westfalen",
    "wof:name":"Willi F\u00f6rster Drogerie",
    "wof:placetype":"venue"
},
  "geometry": {"coordinates":[6.784368,51.219494],"type":"Point"}
}