{
  "type": "Feature",
  "properties": {
    "iso:country":"DE",
    "sg:address":"Robert-Bosch-Str. 10",
    "sg:city":"Bretten",
    "sg:phone":"+49 7252/93940",
    "sg:postcode":"75015",
    "sg:province":"Baden-W\u00fcrttemberg",
    "wof:name":"Harald K\u00fcbler Bergungs-und Schleppsysteme Gmbh",
    "wof:placetype":"venue"
},
  "geometry": {"coordinates":[8.674884,49.03801],"type":"Point"}
}