{
  "type": "Feature",
  "properties": {
    "iso:country":"DE",
    "sg:address":"Greifswalder Str. 2",
    "sg:city":"Wolgast",
    "sg:phone":"+49 3836/600382",
    "sg:postcode":"17438",
    "sg:province":"Mecklenburg-Vorpommern",
    "wof:name":"Lothar Fiebow",
    "wof:placetype":"venue"
},
  "geometry": {"coordinates":[13.767589,54.056362],"type":"Point"}
}