{
  "type": "Feature",
  "properties": {
    "iso:country":"DE",
    "sg:address":"Rhodel\u00e4nderweg 24 a",
    "sg:city":"Berlin",
    "sg:postcode":"12355",
    "sg:province":"Berlin",
    "wof:name":"Dr. Peter Hans Hummel Tierarzt",
    "wof:placetype":"venue"
},
  "geometry": {"coordinates":[13.4877519608,52.4091072083],"type":"Point"}
}