{
  "type": "Feature",
  "properties": {
    "iso:country":"DE",
    "sg:address":"Markgrafenstr. 20",
    "sg:city":"Emmendingen",
    "sg:phone":"+49 7641/42831",
    "sg:postcode":"79312",
    "sg:province":"Baden-W\u00fcrttemberg",
    "wof:name":"Markgrafen-apotheke",
    "wof:placetype":"venue"
},
  "geometry": {"coordinates":[7.852243,48.11937],"type":"Point"}
}