{
  "type": "Feature",
  "properties": {
    "iso:country":"DE",
    "sg:address":"Tie 10 a",
    "sg:city":"Aschersleben",
    "sg:postcode":"06449",
    "sg:province":"Sachsen-Anhalt",
    "wof:name":"Drogerie",
    "wof:placetype":"venue"
},
  "geometry": {"coordinates":[11.457351,51.756943],"type":"Point"}
}