{
  "type": "Feature",
  "properties": {
    "iso:country":"DE",
    "sg:address":"Dorotheenstr. 86",
    "sg:city":"D\u00fcsseldorf",
    "sg:phone":"+49 211/6803391",
    "sg:postcode":"40235",
    "sg:province":"Nordrhein-Westfalen",
    "wof:name":"D. Gottschick",
    "wof:placetype":"venue"
},
  "geometry": {"coordinates":[6.812148,51.22699],"type":"Point"}
}