{
  "type": "Feature",
  "properties": {
    "iso:country":"DE",
    "sg:address":"Allg\u00e4uer Str. 37",
    "sg:city":"M\u00fcnchen",
    "sg:phone":"+49 89/750477",
    "sg:postcode":"81475",
    "sg:province":"Bayern",
    "wof:name":"Willy Deppe",
    "wof:placetype":"venue"
},
  "geometry": {"coordinates":[11.4857616425,48.0842666626],"type":"Point"}
}