{
  "type": "Feature",
  "properties": {
    "iso:country":"DE",
    "sg:address":"S\u00fcdallee 98",
    "sg:city":"D\u00fcsseldorf",
    "sg:phone":"+49 211/7005470",
    "sg:postcode":"40593",
    "sg:province":"Nordrhein-Westfalen",
    "wof:name":"Ev. Pfarramt Ii Urdenbach",
    "wof:placetype":"venue"
},
  "geometry": {"coordinates":[6.881000042,51.1543083191],"type":"Point"}
}