{
  "type": "Feature",
  "properties": {
    "iso:country":"DE",
    "sg:address":"Goldbecker Weg 14",
    "sg:city":"Walsleben",
    "sg:phone":"+49 39388/28567",
    "sg:postcode":"39606",
    "sg:province":"Sachsen-Anhalt",
    "wof:name":"B. Und T. Verchow",
    "wof:placetype":"venue"
},
  "geometry": {"coordinates":[11.857832,52.754601],"type":"Point"}
}