{
  "type": "Feature",
  "properties": {
    "iso:country":"DE",
    "sg:address":"Auf der Burg",
    "sg:city":"Plattenburg",
    "sg:postcode":"19336",
    "sg:province":"Brandenburg",
    "wof:name":"Verein Zur F\u00f6rderung Und Erhaltung D. Plattenburg E. V.",
    "wof:placetype":"venue"
},
  "geometry": {"coordinates":[12.0296449661,52.9581947327],"type":"Point"}
}