{
  "type": "Feature",
  "properties": {
    "iso:country":"DE",
    "sg:address":"Hauptstr. 19",
    "sg:city":"B\u00f6bingen",
    "sg:phone":"+49 6327/613",
    "sg:postcode":"67482",
    "sg:province":"Rheinland-Pfalz",
    "wof:name":"Katholisches Pfarramt St. Gallus",
    "wof:placetype":"venue"
},
  "geometry": {"coordinates":[8.2326068878,49.2832336426],"type":"Point"}
}