{
  "type": "Feature",
  "properties": {
    "iso:country":"DE",
    "sg:address":"Marktstr. 3",
    "sg:city":"Weener",
    "sg:phone":"+49 4951/912128",
    "sg:postcode":"26826",
    "sg:province":"Niedersachsen",
    "wof:name":"Lf Protect Inh. Ludwig Freundorfer",
    "wof:placetype":"venue"
},
  "geometry": {"coordinates":[7.3536458015,53.1657752991],"type":"Point"}
}