{
  "type": "Feature",
  "properties": {
    "iso:country":"DE",
    "sg:address":"Alicestr. 21",
    "sg:city":"Bad Nauheim",
    "sg:phone":"+49 6032/4870",
    "sg:postcode":"61231",
    "sg:province":"Hessen",
    "wof:name":"Platz",
    "wof:placetype":"venue"
},
  "geometry": {"coordinates":[8.738824,50.363907],"type":"Point"}
}