{
  "type": "Feature",
  "properties": {
    "iso:country":"DE",
    "sg:address":"Timm-Kr\u00f6ger-Weg 3",
    "sg:city":"Bad Oldesloe",
    "sg:phone":"+49 4531/84190",
    "sg:postcode":"23843",
    "sg:province":"Schleswig-Holstein",
    "wof:name":"Burkhard Von Hennigs Architekt",
    "wof:placetype":"venue"
},
  "geometry": {"coordinates":[10.359839,53.80521],"type":"Point"}
}