{
  "type": "Feature",
  "properties": {
    "iso:country":"DE",
    "sg:address":"Naunburger Str. 22 F",
    "sg:city":"St\u00f6\u00dfen",
    "sg:phone":"+49 34445/20370",
    "sg:postcode":"06667",
    "sg:province":"Sachsen-Anhalt",
    "wof:name":"Krug Transport Gmbh",
    "wof:placetype":"venue"
},
  "geometry": {"coordinates":[11.9519195557,51.1936988831],"type":"Point"}
}