{
  "type": "Feature",
  "properties": {
    "iso:country":"DE",
    "sg:address":"Friedrich-List-Str. 1",
    "sg:city":"Sigmaringen",
    "sg:phone":"+49 7571/4771",
    "sg:postcode":"72488",
    "sg:province":"Baden-W\u00fcrttemberg",
    "wof:name":"H. Schaudt",
    "wof:placetype":"venue"
},
  "geometry": {"coordinates":[9.234516,48.080795],"type":"Point"}
}