{
  "type": "Feature",
  "properties": {
    "iso:country":"DE",
    "sg:address":"Otto-Beck-Str. 38",
    "sg:city":"Mannheim",
    "sg:phone":"+49 621/3285631",
    "sg:postcode":"68165",
    "sg:province":"Baden-W\u00fcrttemberg",
    "wof:name":"Tilman Schilling Rechtsanwalt",
    "wof:placetype":"venue"
},
  "geometry": {"coordinates":[8.4862203598,49.4828948975],"type":"Point"}
}