{
  "type": "Feature",
  "properties": {
    "iso:country":"DE",
    "sg:address":"Kiefernstr. 77",
    "sg:city":"Puchheim",
    "sg:phone":"+49 89/89027403",
    "sg:postcode":"82178",
    "sg:province":"Bayern",
    "wof:name":"E.-w. Winterscheidt",
    "wof:placetype":"venue"
},
  "geometry": {"coordinates":[11.349892,48.177807],"type":"Point"}
}