{
  "type": "Feature",
  "properties": {
    "iso:country":"DE",
    "sg:address":"Theodor-Hoffmann-Platz 15",
    "sg:city":"Boppard",
    "sg:phone":"+49 6742/6254",
    "sg:postcode":"56154",
    "sg:province":"Rheinland-Pfalz",
    "wof:name":"Hotel-bach Gmbh",
    "wof:placetype":"venue"
},
  "geometry": {"coordinates":[7.6310710907,50.2042350769],"type":"Point"}
}