{
  "type": "Feature",
  "properties": {
    "iso:country":"DE",
    "sg:address":"K\u00f6nigsallee 15",
    "sg:city":"D\u00fcsseldorf",
    "sg:phone":"+49 211/80971",
    "sg:postcode":"40212",
    "sg:province":"Nordrhein-Westfalen",
    "wof:name":"Sakura Finanz Gmbh",
    "wof:placetype":"venue"
},
  "geometry": {"coordinates":[6.7783250809,51.2251548767],"type":"Point"}
}