{
  "type": "Feature",
  "properties": {
    "iso:country":"DE",
    "sg:address":"Hauptstr. 23",
    "sg:city":"Wilmersdorf",
    "sg:phone":"+49 4933/3347514",
    "sg:postcode":"16278",
    "sg:province":"Brandenburg",
    "wof:name":"Gut Wilmersdorf Gbr",
    "wof:placetype":"venue"
},
  "geometry": {"coordinates":[14.1382856369,52.2603340149],"type":"Point"}
}