{
  "type": "Feature",
  "properties": {
    "iso:country":"DE",
    "sg:address":"Albert-Niethammer-Str 20",
    "sg:city":"Gr\u00f6ditz",
    "sg:phone":"+49 35263/68007",
    "sg:postcode":"01609",
    "sg:province":"Sachsen",
    "wof:name":"Gud Gr\u00f6ditzer Umwelt Dienst Gmbh",
    "wof:placetype":"venue"
},
  "geometry": {"coordinates":[13.442241,51.417095],"type":"Point"}
}