{
  "type": "Feature",
  "properties": {
    "iso:country":"DE",
    "sg:address":"Weideweg 3",
    "sg:city":"Chemnitz",
    "sg:phone":"+49 371/36640",
    "sg:postcode":"09116",
    "sg:province":"Sachsen",
    "wof:name":"Raab Karcher Baustoffhandel Gmbh",
    "wof:placetype":"venue"
},
  "geometry": {"coordinates":[12.8563632965,50.8315582275],"type":"Point"}
}