{
  "type": "Feature",
  "properties": {
    "iso:country":"DE",
    "sg:address":"Hainanger 23",
    "sg:city":"Schm\u00f6lln",
    "sg:phone":"+49 34491/27506",
    "sg:postcode":"04626",
    "sg:province":"Th\u00fcringen",
    "wof:name":"U. Oelsner",
    "wof:placetype":"venue"
},
  "geometry": {"coordinates":[12.350817,50.902145],"type":"Point"}
}