{
  "type": "Feature",
  "properties": {
    "iso:country":"DE",
    "sg:address":"Poststr. 6",
    "sg:city":"Hohndorf",
    "sg:phone":"+49 37298/94080",
    "sg:postcode":"09394",
    "sg:province":"Sachsen",
    "wof:name":"Tino Sch\u00c4fer",
    "wof:placetype":"venue"
},
  "geometry": {"coordinates":[12.6786651611,50.7419471741],"type":"Point"}
}