{
  "type": "Feature",
  "properties": {
    "iso:country":"DE",
    "sg:address":"T\u00fcnter Heide 37",
    "sg:city":"Rhede",
    "sg:phone":"+49 2872/3388",
    "sg:postcode":"46414",
    "sg:province":"Nordrhein-Westfalen",
    "wof:name":"Restaurant Olympia",
    "wof:placetype":"venue"
},
  "geometry": {"coordinates":[6.7071928978,51.8319244385],"type":"Point"}
}