{
  "type": "Feature",
  "properties": {
    "iso:country":"DE",
    "sg:address":"Carl-Zeiss-Str. 5",
    "sg:city":"Trittau",
    "sg:phone":"+49 4941/543348",
    "sg:postcode":"22946",
    "sg:province":"Schleswig-Holstein",
    "wof:name":"Fellinger Industrieelektronik Gmbh",
    "wof:placetype":"venue"
},
  "geometry": {"coordinates":[10.387430191,53.6159286499],"type":"Point"}
}