{
  "type": "Feature",
  "properties": {
    "iso:country":"DE",
    "sg:address":"Volker-B\u00f6hringer-Weg 18",
    "sg:city":"Esslingen",
    "sg:phone":"+49 711/378844",
    "sg:postcode":"73732",
    "sg:province":"Baden-W\u00fcrttemberg",
    "wof:name":"W. Kanitz",
    "wof:placetype":"venue"
},
  "geometry": {"coordinates":[9.330429,48.753143],"type":"Point"}
}