{
  "type": "Feature",
  "properties": {
    "iso:country":"DE",
    "sg:address":"Gutenbergstr 1",
    "sg:city":"Wittlich",
    "sg:phone":"+49 6571/8384",
    "sg:postcode":"54516",
    "sg:province":"Rheinland-Pfalz",
    "wof:name":"Haft-plastic Gmbh",
    "wof:placetype":"venue"
},
  "geometry": {"coordinates":[6.9011511803,49.9783058167],"type":"Point"}
}