{
  "type": "Feature",
  "properties": {
    "iso:country":"DE",
    "sg:address":"Vardeilser Landstr. 8",
    "sg:city":"Einbeck",
    "sg:phone":"+49 5561/5712",
    "sg:postcode":"37574",
    "sg:province":"Niedersachsen",
    "wof:name":"Erich Schl\u00fcter",
    "wof:placetype":"venue"
},
  "geometry": {"coordinates":[9.851838,51.817677],"type":"Point"}
}