{
  "type": "Feature",
  "properties": {
    "iso:country":"DE",
    "sg:address":"wilhelmm schussentsr. 4",
    "sg:city":"Lichtenstein",
    "sg:phone":"+49 7129",
    "sg:postcode":"72805",
    "sg:province":"Baden-W\u00fcrttemberg",
    "wof:name":"Welcome At Celtic-castle",
    "wof:placetype":"venue"
},
  "geometry": {"coordinates":[9.254775,48.438522],"type":"Point"}
}