{
  "type": "Feature",
  "properties": {
    "iso:country":"DE",
    "sg:address":"Wiegenkamp 10",
    "sg:city":"Rhede",
    "sg:phone":"+49 2872/93830",
    "sg:postcode":"46414",
    "sg:province":"Nordrhein-Westfalen",
    "wof:name":"A & W Albers & Wagener Stahlhandel Und",
    "wof:placetype":"venue"
},
  "geometry": {"coordinates":[6.702269,51.829815],"type":"Point"}
}