{
  "type": "Feature",
  "properties": {
    "iso:country":"DE",
    "sg:address":"Eickwisch 8",
    "sg:city":"Buchholz",
    "sg:phone":"+49 4181/7043",
    "sg:postcode":"21244",
    "sg:province":"Niedersachsen",
    "wof:name":"Gr\u00fctzahn Und Prange Gmbh Rohr- Und Industriehandel",
    "wof:placetype":"venue"
},
  "geometry": {"coordinates":[9.86882,53.344475],"type":"Point"}
}