{
  "type": "Feature",
  "properties": {
    "iso:country":"DE",
    "sg:address":"Theodor-Heuss-Platz 10",
    "sg:city":"Augsburg",
    "sg:phone":"+49 821/571852",
    "sg:postcode":"86150",
    "sg:province":"Bayern",
    "wof:name":"H. Klo\u00df",
    "wof:placetype":"venue"
},
  "geometry": {"coordinates":[10.8983068466,48.359172821],"type":"Point"}
}