{
  "type": "Feature",
  "properties": {
    "iso:country":"DE",
    "sg:address":"Werstener Feld 11",
    "sg:city":"D\u00fcsseldorf",
    "sg:phone":"+49 211/762337",
    "sg:postcode":"40591",
    "sg:province":"Nordrhein-Westfalen",
    "wof:name":"Fortuna Klause",
    "wof:placetype":"venue"
},
  "geometry": {"coordinates":[6.8226251602,51.1841812134],"type":"Point"}
}