{
  "type": "Feature",
  "properties": {
    "iso:country":"DE",
    "sg:address":"Luetzenstrasse 9",
    "sg:city":"Berlin",
    "sg:phone":"+49 30/89092885",
    "sg:postcode":"10711",
    "sg:province":"Berlin",
    "wof:name":"Co&co",
    "wof:placetype":"venue"
},
  "geometry": {"coordinates":[13.288667,52.499138],"type":"Point"}
}