{
  "type": "Feature",
  "properties": {
    "iso:country":"DE",
    "sg:address":"Haferlandweg 18",
    "sg:city":"M\u00fcnster",
    "sg:phone":"+49 251/61830",
    "sg:postcode":"48155",
    "sg:province":"Nordrhein-Westfalen",
    "wof:name":"Selectric Nachrichten Systeme Gmbh",
    "wof:placetype":"venue"
},
  "geometry": {"coordinates":[7.6580138206,51.9374656677],"type":"Point"}
}