{
  "type": "Feature",
  "properties": {
    "iso:country":"DE",
    "sg:address":"Heilbronner Str. 8",
    "sg:city":"Talheim",
    "sg:phone":"+49 4927/4393350",
    "sg:postcode":"74388",
    "sg:province":"Baden-W\u00fcrttemberg",
    "wof:name":"Jumel & Kraft Kunststofftechnik Gmbh",
    "wof:placetype":"venue"
},
  "geometry": {"coordinates":[-81.4354095459,26.5363197327],"type":"Point"}
}