{
  "type": "Feature",
  "properties": {
    "iso:country":"DE",
    "sg:address":"Daimlerstr. 3",
    "sg:city":"Rudersberg",
    "sg:phone":"+49 7183/7301",
    "sg:postcode":"73635",
    "sg:province":"Baden-W\u00fcrttemberg",
    "wof:name":"Manfred Klotz",
    "wof:placetype":"venue"
},
  "geometry": {"coordinates":[9.535831,48.887886],"type":"Point"}
}