{
  "type": "Feature",
  "properties": {
    "iso:country":"DE",
    "sg:address":"Hamburger Str. 208",
    "sg:city":"Ahrensburg",
    "sg:phone":"+49 4102/52947",
    "sg:postcode":"22926",
    "sg:province":"Schleswig-Holstein",
    "wof:name":"Ttn Techniker Team Nord",
    "wof:placetype":"venue"
},
  "geometry": {"coordinates":[10.2104673386,53.6563491821],"type":"Point"}
}