{
  "type": "Feature",
  "properties": {
    "iso:country":"DE",
    "sg:address":"Bismarckallee 10",
    "sg:city":"Bonn",
    "sg:phone":"+49 228/361063",
    "sg:postcode":"53173",
    "sg:province":"Nordrhein-Westfalen",
    "wof:name":"Redaktion Silence-courier Sisu Steinschulte-verlag",
    "wof:placetype":"venue"
},
  "geometry": {"coordinates":[7.1661481857,50.6829490662],"type":"Point"}
}