{
  "type": "Feature",
  "properties": {
    "iso:country":"DE",
    "sg:address":"allende",
    "sg:city":"friville",
    "sg:phone":"+49 32/2301258",
    "sg:postcode":"80130",
    "wof:name":"Vive Le Qu\u00e9bec",
    "wof:placetype":"venue"
},
  "geometry": {"coordinates":[1.517872,50.085037],"type":"Point"}
}