{
  "type": "Feature",
  "properties": {
    "iso:country":"DE",
    "sg:address":"Drostestr. 10",
    "sg:city":"Stuttgart",
    "sg:phone":"+49 711/8385591",
    "sg:postcode":"70499",
    "sg:province":"Baden-W\u00fcrttemberg",
    "wof:name":"Reinhard Schatz Ingenieur",
    "wof:placetype":"venue"
},
  "geometry": {"coordinates":[9.1171960831,48.8236045837],"type":"Point"}
}