{
  "type": "Feature",
  "properties": {
    "iso:country":"DE",
    "sg:address":"Lindholzweg 17a",
    "sg:city":"Berlin",
    "sg:phone":"+49 30/7426530",
    "sg:postcode":"12349",
    "sg:province":"Berlin",
    "wof:name":"Rolf Jeske Ingenieur",
    "wof:placetype":"venue"
},
  "geometry": {"coordinates":[13.4320249557,52.4189033508],"type":"Point"}
}