{
  "type": "Feature",
  "properties": {
    "iso:country":"DE",
    "sg:address":"Gollstr. 20",
    "sg:city":"Hannover",
    "sg:phone":"+49 511/511515",
    "sg:postcode":"30559",
    "sg:province":"Niedersachsen",
    "wof:name":"Hg Haus- Und Grundst\u00fccks- Betreuungs-gmbh",
    "wof:placetype":"venue"
},
  "geometry": {"coordinates":[9.8589057922,52.3608589172],"type":"Point"}
}