{
  "type": "Feature",
  "properties": {
    "iso:country":"DE",
    "sg:address":"Jahnstr. 1",
    "sg:city":"Waldkirch",
    "sg:phone":"+49 7681/7340",
    "sg:postcode":"79183",
    "sg:province":"Baden-W\u00fcrttemberg",
    "wof:name":"Stadiongastst\u00e4tte Des Elzstadion",
    "wof:placetype":"venue"
},
  "geometry": {"coordinates":[7.9550800323,48.0903053284],"type":"Point"}
}