{
  "type": "Feature",
  "properties": {
    "iso:country":"DE",
    "sg:address":"K\u00f6nigsberger Str. 41",
    "sg:city":"M\u00f6nchengladbach",
    "sg:phone":"+49 2161/86259",
    "sg:postcode":"41063",
    "sg:province":"Nordrhein-Westfalen",
    "wof:name":"Hubert Beckers",
    "wof:placetype":"venue"
},
  "geometry": {"coordinates":[6.4169220924,51.2042007446],"type":"Point"}
}