{
  "type": "Feature",
  "properties": {
    "iso:country":"DE",
    "sg:address":"H\u00f6rigstr. 32",
    "sg:city":"Dresden",
    "sg:phone":"+49 351/4212768",
    "sg:postcode":"01157",
    "sg:province":"Sachsen",
    "wof:name":"J. Sch\u00f6nbach",
    "wof:placetype":"venue"
},
  "geometry": {"coordinates":[13.680284,51.051598],"type":"Point"}
}