{
  "type": "Feature",
  "properties": {
    "iso:country":"DE",
    "sg:address":"Justus-von-Liebig-Str 6",
    "sg:city":"\u00d6stringen",
    "sg:phone":"+49 7253/92560",
    "sg:postcode":"76684",
    "sg:province":"Baden-W\u00fcrttemberg",
    "wof:name":"Edgar Rothermel Internationale Spedition Gmbh",
    "wof:placetype":"venue"
},
  "geometry": {"coordinates":[8.697492,49.21582],"type":"Point"}
}