{
  "type": "Feature",
  "properties": {
    "iso:country":"DE",
    "sg:address":"Lucas-Cranach-Str. 21",
    "sg:city":"Kronach",
    "sg:postcode":"96317",
    "sg:province":"Bayern",
    "wof:name":"Modehaus K\u00f6nig Gmbh",
    "wof:placetype":"venue"
},
  "geometry": {"coordinates":[11.325159,50.241684],"type":"Point"}
}