{
  "type": "Feature",
  "properties": {
    "iso:country":"DE",
    "sg:address":"Tucholskystr. 41",
    "sg:city":"Berlin",
    "sg:phone":"+49 30/2828602",
    "sg:postcode":"10117",
    "sg:province":"Berlin",
    "wof:name":"Reiseb\u00fcro Durchblick",
    "wof:placetype":"venue"
},
  "geometry": {"coordinates":[13.3929853439,52.5269775391],"type":"Point"}
}