{
  "type": "Feature",
  "properties": {
    "iso:country":"DE",
    "sg:address":"Graf-Kirchberg-Str. 11",
    "sg:city":"Illertissen",
    "sg:phone":"+49 7303/7232",
    "sg:postcode":"89257",
    "sg:province":"Bayern",
    "wof:name":"Franz Zahner",
    "wof:placetype":"venue"
},
  "geometry": {"coordinates":[10.1215667725,48.2525291443],"type":"Point"}
}