{
  "type": "Feature",
  "properties": {
    "iso:country":"DE",
    "sg:address":"Hauptstr. 3",
    "sg:city":"Nittenau",
    "sg:phone":"+49 9436/576",
    "sg:postcode":"93149",
    "sg:province":"Bayern",
    "wof:name":"Stadtb\u00fccherei Haus Des Gastes",
    "wof:placetype":"venue"
},
  "geometry": {"coordinates":[12.272357,49.197544],"type":"Point"}
}