{
  "type": "Feature",
  "properties": {
    "iso:country":"DE",
    "sg:address":"Butzbacher Str. 4",
    "sg:city":"Butzbach",
    "sg:phone":"+49 6033/66521",
    "sg:postcode":"35510",
    "sg:province":"Hessen",
    "wof:name":"Armin Br\u00fcckel",
    "wof:placetype":"venue"
},
  "geometry": {"coordinates":[8.68316,50.420559],"type":"Point"}
}