{
  "type": "Feature",
  "properties": {
    "iso:country":"DE",
    "sg:address":"D\u00f6llingerstr. 17",
    "sg:city":"M\u00fcnchen",
    "sg:postcode":"80639",
    "sg:province":"Bayern",
    "wof:name":"Europatent Gesellschaft F\u00fcr Europ\u00e4ischen Patentdienst",
    "wof:placetype":"venue"
},
  "geometry": {"coordinates":[11.514515,48.155159],"type":"Point"}
}