{
  "type": "Feature",
  "properties": {
    "iso:country":"DE",
    "sg:address":"Kaimling",
    "sg:city":"Vohenstrau\u00df",
    "sg:phone":"+49 9651/232",
    "sg:postcode":"92648",
    "sg:province":"Bayern",
    "wof:name":"Pension Am Sonnenhang",
    "wof:placetype":"venue"
},
  "geometry": {"coordinates":[12.3416996002,49.6236381531],"type":"Point"}
}