{
  "type": "Feature",
  "properties": {
    "iso:country":"DE",
    "sg:address":"Traminer Str. 24",
    "sg:city":"R\u00f6dermark",
    "sg:phone":"+49 6074/61586",
    "sg:postcode":"63322",
    "sg:province":"Hessen",
    "wof:name":"Gerhard Frank",
    "wof:placetype":"venue"
},
  "geometry": {"coordinates":[8.809378624,49.9649543762],"type":"Point"}
}