{
  "type": "Feature",
  "properties": {
    "iso:country":"DE",
    "sg:address":"Industriestr 10",
    "sg:city":"Herne",
    "sg:phone":"+49 2323/911111",
    "sg:postcode":"44628",
    "sg:province":"Nordrhein-Westfalen",
    "wof:name":"Noise-ex International Gmbh",
    "wof:placetype":"venue"
},
  "geometry": {"coordinates":[7.24592,51.54776],"type":"Point"}
}