{
  "type": "Feature",
  "properties": {
    "iso:country":"DE",
    "sg:address":"Enge Str. 3",
    "sg:city":"Rinteln",
    "sg:phone":"+49 5751/41969",
    "sg:postcode":"31737",
    "sg:province":"Niedersachsen",
    "wof:name":"Manfred Krasovic",
    "wof:placetype":"venue"
},
  "geometry": {"coordinates":[9.081651,52.189068],"type":"Point"}
}