{
  "type": "Feature",
  "properties": {
    "iso:country":"DE",
    "sg:address":"Am Kirschberg 33",
    "sg:city":"Weimar",
    "sg:phone":"+49 3643/53604",
    "sg:postcode":"99423",
    "sg:province":"Th\u00fcringen",
    "wof:name":"Weimarplan Architektur- Und Ingenieurb\u00fcro Gmbh",
    "wof:placetype":"venue"
},
  "geometry": {"coordinates":[11.332166,50.985767],"type":"Point"}
}