{
  "type": "Feature",
  "properties": {
    "iso:country":"DE",
    "sg:address":"Poststr. 53",
    "sg:city":"Wippra",
    "sg:phone":"+49 34775/20443",
    "sg:postcode":"06543",
    "sg:province":"Sachsen-Anhalt",
    "wof:name":"Ute Elster",
    "wof:placetype":"venue"
},
  "geometry": {"coordinates":[11.272881,51.57262],"type":"Point"}
}