{
  "type": "Feature",
  "properties": {
    "iso:country":"DE",
    "sg:address":"Friedrich-Engels-Str. 3",
    "sg:city":"L\u00fctzen",
    "sg:phone":"+49 34444/20255",
    "sg:postcode":"06686",
    "sg:province":"Sachsen-Anhalt",
    "wof:name":"Gisela Joost",
    "wof:placetype":"venue"
},
  "geometry": {"coordinates":[12.1420974731,51.2571144104],"type":"Point"}
}