{
  "type": "Feature",
  "properties": {
    "iso:country":"DE",
    "sg:address":"Hauptstr. 46",
    "sg:city":"Pegnitz",
    "sg:phone":"+49 9241/2520",
    "sg:postcode":"91257",
    "sg:province":"Bayern",
    "wof:name":"Werner Brand",
    "wof:placetype":"venue"
},
  "geometry": {"coordinates":[11.540417,49.75679],"type":"Point"}
}