{
  "type": "Feature",
  "properties": {
    "iso:country":"DE",
    "sg:address":"Goethestr. 5",
    "sg:city":"Stockach",
    "sg:phone":"+49 7771/929325",
    "sg:postcode":"78333",
    "sg:province":"Baden-W\u00fcrttemberg",
    "wof:name":"J. Jerg",
    "wof:placetype":"venue"
},
  "geometry": {"coordinates":[9.0101308823,47.8509025574],"type":"Point"}
}