{
  "type": "Feature",
  "properties": {
    "iso:country":"DE",
    "sg:address":"Am Stadion 52",
    "sg:city":"Papenburg",
    "sg:phone":"+49 4961/76757",
    "sg:postcode":"26871",
    "sg:province":"Niedersachsen",
    "wof:name":"Emil Meiners",
    "wof:placetype":"venue"
},
  "geometry": {"coordinates":[7.417192,53.068314],"type":"Point"}
}