{
  "type": "Feature",
  "properties": {
    "iso:country":"DE",
    "sg:address":"Gr\u00fcntenstr. 4",
    "sg:city":"Kissing",
    "sg:postcode":"86438",
    "sg:province":"Bayern",
    "wof:name":"Ggv - Grund Geb\u00e4ude Verwaltungs Gmbh",
    "wof:placetype":"venue"
},
  "geometry": {"coordinates":[10.972984314,48.3013801575],"type":"Point"}
}