{
  "type": "Feature",
  "properties": {
    "iso:country":"DE",
    "sg:address":"Mittelstr. 63",
    "sg:city":"D\u00f6rentrup",
    "sg:phone":"+49 5265/378",
    "sg:postcode":"32694",
    "sg:province":"Nordrhein-Westfalen",
    "wof:name":"Werner Freitag",
    "wof:placetype":"venue"
},
  "geometry": {"coordinates":[9.0056,52.032028],"type":"Point"}
}