{
  "type": "Feature",
  "properties": {
    "iso:country":"DE",
    "sg:address":"Europaallee 12",
    "sg:city":"F\u00fcrth",
    "sg:phone":"+49 911/705544",
    "sg:postcode":"90763",
    "sg:province":"Bayern",
    "wof:name":"Eberhard Meyer Gmbh",
    "wof:placetype":"venue"
},
  "geometry": {"coordinates":[10.99836,49.45084],"type":"Point"}
}