{
  "type": "Feature",
  "properties": {
    "iso:country":"DE",
    "sg:address":"Am Kniep 15",
    "sg:city":"Korbach",
    "sg:phone":"+49 5631/7073",
    "sg:postcode":"34497",
    "sg:province":"Hessen",
    "wof:name":"Herbert Kuhaupt Architekt",
    "wof:placetype":"venue"
},
  "geometry": {"coordinates":[8.866859,51.275429],"type":"Point"}
}