{
  "type": "Feature",
  "properties": {
    "iso:country":"DE",
    "sg:address":"Sprockh\u00f6veler Str. 121",
    "sg:city":"Witten",
    "sg:phone":"+49 2302/54465",
    "sg:postcode":"58455",
    "sg:province":"Nordrhein-Westfalen",
    "wof:name":"Leonhard Jaschke Gmbh",
    "wof:placetype":"venue"
},
  "geometry": {"coordinates":[7.3227338791,51.4404220581],"type":"Point"}
}