{
  "type": "Feature",
  "properties": {
    "iso:country":"DE",
    "sg:address":"Albulaweg 14 A",
    "sg:city":"Berlin",
    "sg:phone":"+49 4930/7418010",
    "sg:postcode":"12107",
    "sg:province":"Berlin",
    "wof:name":"Trans-medical Gmbh",
    "wof:placetype":"venue"
},
  "geometry": {"coordinates":[13.4009160995,52.4233283997],"type":"Point"}
}