{
  "type": "Feature",
  "properties": {
    "iso:country":"DE",
    "sg:address":"Rathausstr. 20",
    "sg:city":"Pfaffenhausen",
    "sg:postcode":"87772",
    "sg:province":"Bayern",
    "wof:name":"Kr\u00e4uterhaus Wagener Gmbh",
    "wof:placetype":"venue"
},
  "geometry": {"coordinates":[10.45666,48.117592],"type":"Point"}
}