{
  "type": "Feature",
  "properties": {
    "iso:country":"DE",
    "sg:address":"Stieberstr. 5",
    "sg:city":"Roth",
    "sg:phone":"+49 9171/87017",
    "sg:postcode":"91154",
    "sg:province":"Bayern",
    "wof:name":"Kb Kabel Beteiligungs-gmbh",
    "wof:placetype":"venue"
},
  "geometry": {"coordinates":[11.089073,49.24519],"type":"Point"}
}