{
  "type": "Feature",
  "properties": {
    "iso:country":"DE",
    "sg:address":"Kappelweg 23",
    "sg:city":"Unterammergau",
    "sg:phone":"+49 8822/94200",
    "sg:postcode":"82497",
    "sg:province":"Bayern",
    "wof:name":"Vision Production",
    "wof:placetype":"venue"
},
  "geometry": {"coordinates":[11.032681,47.620804],"type":"Point"}
}