{
  "type": "Feature",
  "properties": {
    "iso:country":"DE",
    "sg:address":"Vorderer Flo\u00dfanger 10",
    "sg:city":"Coburg",
    "sg:phone":"+49 9561/5150",
    "sg:postcode":"96450",
    "sg:province":"Bayern",
    "wof:name":"F. Und H. Schumann Kunststoffwaren-gh.",
    "wof:placetype":"venue"
},
  "geometry": {"coordinates":[10.9701976776,50.2701148987],"type":"Point"}
}