{
  "type": "Feature",
  "properties": {
    "iso:country":"DE",
    "sg:address":"Frankfurter Str. 31",
    "sg:city":"Offenbach",
    "sg:phone":"+49 69/881112",
    "sg:postcode":"63065",
    "sg:province":"Hessen",
    "wof:name":"Michael Zwilling",
    "wof:placetype":"venue"
},
  "geometry": {"coordinates":[8.7613773346,50.1050338745],"type":"Point"}
}