{
  "type": "Feature",
  "properties": {
    "iso:country":"DE",
    "sg:address":"Wiedenbr\u00fccker Str. 6",
    "sg:city":"Langenberg",
    "sg:postcode":"33449",
    "sg:province":"Nordrhein-Westfalen",
    "wof:name":"Menze Gmbh",
    "wof:placetype":"venue"
},
  "geometry": {"coordinates":[8.323228,51.776596],"type":"Point"}
}