{
  "type": "Feature",
  "properties": {
    "iso:country":"DE",
    "sg:address":"Nunsdorfer Ring 19",
    "sg:city":"Berlin",
    "sg:phone":"+49 30/7211014",
    "sg:postcode":"12277",
    "sg:province":"Berlin",
    "wof:name":"Chemoport Johannes Schuppan & Co. Kg",
    "wof:placetype":"venue"
},
  "geometry": {"coordinates":[13.3832187653,52.4070281982],"type":"Point"}
}