{
  "type": "Feature",
  "properties": {
    "iso:country":"DE",
    "sg:address":"Am K\u00fcmmerling 35",
    "sg:city":"Bodenheim",
    "sg:phone":"+49 6135/92440",
    "sg:postcode":"55294",
    "sg:province":"Rheinland-Pfalz",
    "wof:name":"Isochem Und Datenverarbeitung Gmbh",
    "wof:placetype":"venue"
},
  "geometry": {"coordinates":[8.3212776184,49.924571991],"type":"Point"}
}