{
  "type": "Feature",
  "properties": {
    "iso:country":"DE",
    "sg:address":"Zellerstr. 16",
    "sg:city":"Berglen",
    "sg:phone":"+49 7195/71770",
    "sg:postcode":"73663",
    "sg:province":"Baden-W\u00fcrttemberg",
    "wof:name":"Doris Kuhlmann Steuerberaterin",
    "wof:placetype":"venue"
},
  "geometry": {"coordinates":[9.4675836563,48.8609085083],"type":"Point"}
}