{
  "type": "Feature",
  "properties": {
    "iso:country":"DE",
    "sg:address":"Kaiserplatz 18",
    "sg:city":"Bonn",
    "sg:phone":"+49 228/653776",
    "sg:postcode":"53113",
    "sg:province":"Nordrhein-Westfalen",
    "wof:name":"Mediterrano",
    "wof:placetype":"venue"
},
  "geometry": {"coordinates":[7.1008272171,50.7321090698],"type":"Point"}
}