{
  "type": "Feature",
  "properties": {
    "iso:country":"DE",
    "sg:address":"Meisenweg 2",
    "sg:city":"Nagold",
    "sg:phone":"+49 7452/4544",
    "sg:postcode":"72202",
    "sg:province":"Baden-W\u00fcrttemberg",
    "wof:name":"Dhk Dorner Heuser Kempf Architekten",
    "wof:placetype":"venue"
},
  "geometry": {"coordinates":[8.716117,48.544922],"type":"Point"}
}