{
  "type": "Feature",
  "properties": {
    "iso:country":"DE",
    "sg:address":"Karl-Wilhelm-Str. 1a",
    "sg:city":"Karlsruhe",
    "sg:phone":"+49 721/606603",
    "sg:postcode":"76131",
    "sg:province":"Baden-W\u00fcrttemberg",
    "wof:name":"Dr. Anneli Und Peter Muser Tier\u00e4rzte",
    "wof:placetype":"venue"
},
  "geometry": {"coordinates":[8.4194021225,49.0100097656],"type":"Point"}
}