{
  "type": "Feature",
  "properties": {
    "iso:country":"DE",
    "sg:address":"Edelwei\u00dfstr. 7",
    "sg:city":"Oberstdorf",
    "sg:phone":"+49 8322/8282",
    "sg:postcode":"87561",
    "sg:province":"Bayern",
    "wof:name":"G. & B. Hahn",
    "wof:placetype":"venue"
},
  "geometry": {"coordinates":[10.2896757126,47.4108657837],"type":"Point"}
}