{
  "type": "Feature",
  "properties": {
    "iso:country":"DE",
    "sg:address":"Schlo\u00dfstr. 4",
    "sg:city":"Berg",
    "sg:phone":"+49 9189/307",
    "sg:postcode":"92348",
    "sg:province":"Bayern",
    "wof:name":"Willibald Nie\u00dflbeck",
    "wof:placetype":"venue"
},
  "geometry": {"coordinates":[11.4414978027,49.3306770325],"type":"Point"}
}