{
  "type": "Feature",
  "properties": {
    "iso:country":"DE",
    "sg:address":"Bahnhofstr 1",
    "sg:city":"Rackwitz",
    "sg:phone":"+49 34294/8270",
    "sg:postcode":"04519",
    "sg:province":"Sachsen",
    "wof:name":"Rackwitz Industrieanlagen Gmbh",
    "wof:placetype":"venue"
},
  "geometry": {"coordinates":[12.3756055832,51.4397354126],"type":"Point"}
}