{
  "type": "Feature",
  "properties": {
    "iso:country":"DE",
    "sg:address":"J.-G.-Nathusius-Str. 24",
    "sg:city":"Haldensleben",
    "sg:phone":"+49 4939/0466180",
    "sg:postcode":"39340",
    "sg:province":"Sachsen-Anhalt",
    "wof:name":"Kaiser Gmbh",
    "wof:placetype":"venue"
},
  "geometry": {"coordinates":[11.427972,52.282066],"type":"Point"}
}