{
  "type": "Feature",
  "properties": {
    "iso:country":"DE",
    "sg:address":"Unterdietfurter Str. 1",
    "sg:city":"Massing",
    "sg:phone":"+49 8724/1799",
    "sg:postcode":"84323",
    "sg:province":"Bayern",
    "wof:name":"Walter Hirsch",
    "wof:placetype":"venue"
},
  "geometry": {"coordinates":[12.648771286,48.3909873962],"type":"Point"}
}