{
  "type": "Feature",
  "properties": {
    "iso:country":"DE",
    "sg:address":"Lipper Weg 181",
    "sg:city":"Marl",
    "sg:phone":"+49 2365/63745",
    "sg:postcode":"45772",
    "sg:province":"Nordrhein-Westfalen",
    "wof:name":"Sternschn\u00fcppchen",
    "wof:placetype":"venue"
},
  "geometry": {"coordinates":[7.1090388298,51.6737060547],"type":"Point"}
}