{
  "type": "Feature",
  "properties": {
    "iso:country":"DE",
    "sg:address":"Gustav-Heinemann-Str. 2",
    "sg:city":"Erftstadt",
    "sg:phone":"+49 2235/461296",
    "sg:postcode":"50374",
    "sg:province":"Nordrhein-Westfalen",
    "wof:name":"Restaurant Pi-pa-po",
    "wof:placetype":"venue"
},
  "geometry": {"coordinates":[6.8155560493,50.8006706238],"type":"Point"}
}