{
  "type": "Feature",
  "properties": {
    "iso:country":"DE",
    "sg:address":"Ziegelstr. 24",
    "sg:city":"Schm\u00f6lln",
    "sg:phone":"+49 34491/82492",
    "sg:postcode":"04626",
    "sg:province":"Th\u00fcringen",
    "wof:name":"Heinz Teichmann Immobilienmakler",
    "wof:placetype":"venue"
},
  "geometry": {"coordinates":[12.3526687622,50.8882446289],"type":"Point"}
}