{
  "type": "Feature",
  "properties": {
    "iso:country":"DE",
    "sg:address":"Halverstr. 30",
    "sg:city":"L\u00fcdenscheid",
    "sg:phone":"+49 2351/78030",
    "sg:postcode":"58515",
    "sg:province":"Nordrhein-Westfalen",
    "wof:name":"Wilfried Gottwald",
    "wof:placetype":"venue"
},
  "geometry": {"coordinates":[7.558744,51.208874],"type":"Point"}
}