{
  "type": "Feature",
  "properties": {
    "iso:country":"DE",
    "sg:address":"B\u00e4rnfels 79",
    "sg:city":"Obertrubach",
    "sg:phone":"+49 9245/297",
    "sg:postcode":"91286",
    "sg:province":"Bayern",
    "wof:name":"Beate Vogler",
    "wof:placetype":"venue"
},
  "geometry": {"coordinates":[11.3456964493,49.7150421143],"type":"Point"}
}