{
  "type": "Feature",
  "properties": {
    "iso:country":"DE",
    "sg:address":"Max-Born-Str. 8",
    "sg:city":"Mannheim",
    "sg:phone":"+49 621/313233",
    "sg:postcode":"68169",
    "sg:province":"Baden-W\u00fcrttemberg",
    "wof:name":"Edgar K\u00f6rber Gmbh",
    "wof:placetype":"venue"
},
  "geometry": {"coordinates":[8.457579,49.523159],"type":"Point"}
}