{
  "type": "Feature",
  "properties": {
    "iso:country":"DE",
    "sg:address":"Agathastr. 15",
    "sg:city":"Werl",
    "sg:phone":"+49 2922/2924",
    "sg:postcode":"59457",
    "sg:province":"Nordrhein-Westfalen",
    "wof:name":"Eberhard Kipp",
    "wof:placetype":"venue"
},
  "geometry": {"coordinates":[7.8575549126,51.5492744446],"type":"Point"}
}