{
  "type": "Feature",
  "properties": {
    "iso:country":"DE",
    "sg:address":"Im Ostpark 23",
    "sg:city":"Wettenberg",
    "sg:postcode":"35435",
    "sg:province":"Hessen",
    "wof:name":"Bauer Blumenvertriebs- Gmbh & Co. Kg",
    "wof:placetype":"venue"
},
  "geometry": {"coordinates":[8.655466,50.609112],"type":"Point"}
}