{
  "type": "Feature",
  "properties": {
    "iso:country":"DE",
    "sg:address":"Elsterwerdaer Str.",
    "sg:city":"Gro\u00dfenhain",
    "sg:postcode":"01558",
    "sg:province":"Sachsen",
    "wof:name":"Schell & Puffler Flugservice Gmbh",
    "wof:placetype":"venue"
},
  "geometry": {"coordinates":[13.5346632004,51.295249939],"type":"Point"}
}