{
  "type": "Feature",
  "properties": {
    "iso:country":"DE",
    "sg:address":"Rheinaustr. 38",
    "sg:city":"Bonn",
    "sg:phone":"+49 228/460243",
    "sg:postcode":"53225",
    "sg:province":"Nordrhein-Westfalen",
    "wof:name":"Gerd R\u00f6ser Masseur",
    "wof:placetype":"venue"
},
  "geometry": {"coordinates":[7.112798,50.744381],"type":"Point"}
}