{
  "type": "Feature",
  "properties": {
    "iso:country":"DE",
    "sg:address":"Bongardstr. 21",
    "sg:city":"Bochum",
    "sg:phone":"+49 234/17087",
    "sg:postcode":"44787",
    "sg:province":"Nordrhein-Westfalen",
    "wof:name":"Ross Cosmetik Gmbh",
    "wof:placetype":"venue"
},
  "geometry": {"coordinates":[7.218407,51.482029],"type":"Point"}
}