{
  "type": "Feature",
  "properties": {
    "iso:country":"DE",
    "sg:address":"Bullspecken 1",
    "sg:city":"Basdahl",
    "sg:postcode":"27432",
    "sg:province":"Niedersachsen",
    "wof:name":"Aee Alternative Energie- Und Elektrik-systeme Gmbh",
    "wof:placetype":"venue"
},
  "geometry": {"coordinates":[8.9529047012,53.4364852905],"type":"Point"}
}