{
  "type": "Feature",
  "properties": {
    "iso:country":"DE",
    "sg:address":"Manchinger Str. 128",
    "sg:city":"Ingolstadt",
    "sg:phone":"+49 841/65075",
    "sg:postcode":"85053",
    "sg:province":"Bayern",
    "wof:name":"Seba Ohg",
    "wof:placetype":"venue"
},
  "geometry": {"coordinates":[11.4698057175,48.7451057434],"type":"Point"}
}