{
  "type": "Feature",
  "properties": {
    "iso:country":"DE",
    "sg:address":"Am K\u00f6ppelplatz 5",
    "sg:city":"Pottenstein",
    "sg:phone":"+49 9243/263",
    "sg:postcode":"91278",
    "sg:province":"Bayern",
    "wof:name":"Pension Hans Und Juliane Haber",
    "wof:placetype":"venue"
},
  "geometry": {"coordinates":[11.40391922,49.7740211487],"type":"Point"}
}