{
  "type": "Feature",
  "properties": {
    "iso:country":"DE",
    "sg:address":"M\u00fchlbachstr. 1",
    "sg:city":"R\u00fcsselsheim",
    "sg:phone":"+49 6142/67939",
    "sg:postcode":"65428",
    "sg:province":"Hessen",
    "wof:name":"Klaus Schindel",
    "wof:placetype":"venue"
},
  "geometry": {"coordinates":[8.4057655334,49.9943466187],"type":"Point"}
}