{
  "type": "Feature",
  "properties": {
    "iso:country":"DE",
    "sg:address":"D\u00fcsseldorfer Ring 12",
    "sg:city":"Amorbach",
    "sg:phone":"+49 9373/99102",
    "sg:postcode":"63916",
    "sg:province":"Bayern",
    "wof:name":"Bernd Ballweg Anlageberater",
    "wof:placetype":"venue"
},
  "geometry": {"coordinates":[9.2131052017,49.6466636658],"type":"Point"}
}