{
  "type": "Feature",
  "properties": {
    "iso:country":"DE",
    "sg:address":"Schanzenstr. 17",
    "sg:city":"Hamm",
    "sg:phone":"+49 2381/71867",
    "sg:postcode":"59075",
    "sg:province":"Nordrhein-Westfalen",
    "wof:name":"G\u00fcnter Heldt",
    "wof:placetype":"venue"
},
  "geometry": {"coordinates":[7.749691,51.691578],"type":"Point"}
}