{
  "type": "Feature",
  "properties": {
    "iso:country":"DE",
    "sg:address":"Westring 3",
    "sg:city":"Leopoldsh\u00f6he",
    "sg:postcode":"33818",
    "sg:province":"Nordrhein-Westfalen",
    "wof:name":"Autohaus Heinrich Freitag Gmbh & Co. Kg",
    "wof:placetype":"venue"
},
  "geometry": {"coordinates":[8.656088829,51.9798965454],"type":"Point"}
}