{
  "type": "Feature",
  "properties": {
    "iso:country":"DE",
    "sg:address":"He\u00dfloher Str. 139",
    "sg:city":"Lage",
    "sg:phone":"+49 5232/3995",
    "sg:postcode":"32791",
    "sg:province":"Nordrhein-Westfalen",
    "wof:name":"Hotel-restaurant Landhaus J\u00e4gerhof",
    "wof:placetype":"venue"
},
  "geometry": {"coordinates":[8.8392601013,51.9937286377],"type":"Point"}
}