{
  "type": "Feature",
  "properties": {
    "iso:country":"DE",
    "sg:address":"Reutestr. 129",
    "sg:city":"Villingen-Schwenningen",
    "sg:phone":"+49 7720/7016",
    "sg:postcode":"78056",
    "sg:province":"Baden-W\u00fcrttemberg",
    "wof:name":"Hakos Pr\u00e4zisionswerkzeuge Hakenjos Gmbh",
    "wof:placetype":"venue"
},
  "geometry": {"coordinates":[8.5364990234,48.0553512573],"type":"Point"}
}