{
  "type": "Feature",
  "properties": {
    "iso:country":"DE",
    "sg:address":"Winsstra\u00dfe 1",
    "sg:city":"Berlin",
    "sg:phone":"+49 30/4427335",
    "sg:postcode":"10405",
    "sg:province":"Berlin",
    "wof:name":"Th-net P.burkhardt U. Jochen Loesdau Gbr",
    "wof:placetype":"venue"
},
  "geometry": {"coordinates":[13.422842,52.530918],"type":"Point"}
}