{
  "type": "Feature",
  "properties": {
    "iso:country":"DE",
    "sg:address":"Weststr. 3",
    "sg:city":"Gevelsberg",
    "sg:postcode":"58285",
    "sg:province":"Nordrhein-Westfalen",
    "wof:name":"Arbeitsamt Hagen Dst. Gevelsberg",
    "wof:placetype":"venue"
},
  "geometry": {"coordinates":[7.332969,51.318439],"type":"Point"}
}