{
  "type": "Feature",
  "properties": {
    "iso:country":"DE",
    "sg:address":"Hickengrundstr. 62",
    "sg:city":"Burbach",
    "sg:phone":"+49 2736/3066",
    "sg:postcode":"57299",
    "sg:province":"Nordrhein-Westfalen",
    "wof:name":"Volksbank S\u00fcd-siegerland Eg",
    "wof:placetype":"venue"
},
  "geometry": {"coordinates":[8.141874,50.736744],"type":"Point"}
}