{
  "type": "Feature",
  "properties": {
    "iso:country":"DE",
    "sg:address":"Ahrberger Weg 1",
    "sg:city":"Sarstedt",
    "sg:phone":"+49 5066/61099",
    "sg:postcode":"31157",
    "sg:province":"Niedersachsen",
    "wof:name":"J\u00fcrgen Dismer",
    "wof:placetype":"venue"
},
  "geometry": {"coordinates":[9.834675,52.213989],"type":"Point"}
}