{
  "type": "Feature",
  "properties": {
    "iso:country":"DE",
    "sg:address":"Holunderweg 16",
    "sg:city":"Obrigheim",
    "sg:phone":"+49 6261/64830",
    "sg:postcode":"74847",
    "sg:province":"Baden-W\u00fcrttemberg",
    "wof:name":"Hemamed Medizintechnik Gmbh",
    "wof:placetype":"venue"
},
  "geometry": {"coordinates":[9.0774297714,49.3488082886],"type":"Point"}
}