{
  "type": "Feature",
  "properties": {
    "iso:country":"DE",
    "sg:address":"Gerdauer Str. 30",
    "sg:city":"Uelzen",
    "sg:phone":"+49 581/5213",
    "sg:postcode":"29525",
    "sg:province":"Niedersachsen",
    "wof:name":"Richard Winkelmann",
    "wof:placetype":"venue"
},
  "geometry": {"coordinates":[10.480615,52.954693],"type":"Point"}
}