{
  "type": "Feature",
  "properties": {
    "iso:country":"DE",
    "sg:address":"Nauener Str. 52 A",
    "sg:city":"Linum",
    "sg:phone":"+49 33922/50245",
    "sg:postcode":"16833",
    "sg:province":"Brandenburg",
    "wof:name":"Horst Voigt Bauschlosserei Gmbh",
    "wof:placetype":"venue"
},
  "geometry": {"coordinates":[12.879049,52.758736],"type":"Point"}
}