{
  "type": "Feature",
  "properties": {
    "iso:country":"DE",
    "sg:address":"Freier Grunder Str. 135",
    "sg:city":"Wilnsdorf",
    "sg:phone":"+49 2739/7424",
    "sg:postcode":"57234",
    "sg:province":"Nordrhein-Westfalen",
    "wof:name":"Renate Stolz Heilpraktikerin",
    "wof:placetype":"venue"
},
  "geometry": {"coordinates":[8.0539903641,50.8032875061],"type":"Point"}
}