{
  "type": "Feature",
  "properties": {
    "iso:country":"DE",
    "sg:address":"Leipziger Str. 7",
    "sg:city":"Syke",
    "sg:phone":"+49 4242/4251",
    "sg:postcode":"28857",
    "sg:province":"Niedersachsen",
    "wof:name":"Ev. Pfarramt Auferstehungsgemeinde Bremen",
    "wof:placetype":"venue"
},
  "geometry": {"coordinates":[8.8195400238,52.903503418],"type":"Point"}
}