{
  "type": "Feature",
  "properties": {
    "iso:country":"DE",
    "sg:address":"Arrach",
    "sg:city":"Falkenstein",
    "sg:phone":"+49 9462/242",
    "sg:postcode":"93167",
    "sg:province":"Bayern",
    "wof:name":"A. Weinzierl",
    "wof:placetype":"venue"
},
  "geometry": {"coordinates":[12.484424,49.093632],"type":"Point"}
}