{
  "type": "Feature",
  "properties": {
    "iso:country":"DE",
    "sg:address":"Siemensweg 5",
    "sg:city":"Wadersloh",
    "sg:phone":"+49 2520/93030",
    "sg:postcode":"59329",
    "sg:province":"Nordrhein-Westfalen",
    "wof:name":"Wilco Wilken Lasertechnik Verwaltungsges. Mbh",
    "wof:placetype":"venue"
},
  "geometry": {"coordinates":[8.175687,51.734333],"type":"Point"}
}