{
  "type": "Feature",
  "properties": {
    "iso:country":"DE",
    "sg:address":"Goslarer Str.",
    "sg:city":"Vienenburg",
    "sg:phone":"+49 5324/1884",
    "sg:postcode":"38690",
    "sg:province":"Niedersachsen",
    "wof:name":"A. Oppermann",
    "wof:placetype":"venue"
},
  "geometry": {"coordinates":[10.5585613251,51.9539794922],"type":"Point"}
}