{
  "type": "Feature",
  "properties": {
    "iso:country":"DE",
    "sg:address":"Jahnstr. 25",
    "sg:city":"Gundersheim",
    "sg:phone":"+49 6244/7542",
    "sg:postcode":"67598",
    "sg:province":"Rheinland-Pfalz",
    "wof:name":"Karl Jansohn",
    "wof:placetype":"venue"
},
  "geometry": {"coordinates":[8.2043228149,49.6957588196],"type":"Point"}
}