{
  "type": "Feature",
  "properties": {
    "iso:country":"DE",
    "sg:address":"B\u00f6rsenstr. 119",
    "sg:city":"Wilhelmshaven",
    "sg:phone":"+49 4421/21449",
    "sg:postcode":"26382",
    "sg:province":"Niedersachsen",
    "wof:name":"Farben-jan\u00dfen Ohg",
    "wof:placetype":"venue"
},
  "geometry": {"coordinates":[8.100315,53.520592],"type":"Point"}
}