{
  "type": "Feature",
  "properties": {
    "iso:country":"DE",
    "sg:address":"Alt Schwanheim 40",
    "sg:city":"Frankfurt",
    "sg:phone":"+49 69/357272",
    "sg:postcode":"60529",
    "sg:province":"Hessen",
    "wof:name":"Heuser Gmbh",
    "wof:placetype":"venue"
},
  "geometry": {"coordinates":[8.5811090469,50.0839118958],"type":"Point"}
}