{
  "type": "Feature",
  "properties": {
    "iso:country":"DE",
    "sg:address":"Friedrich-R\u00f6mer-Str. 29",
    "sg:city":"Erkenbrechtsweiler",
    "sg:phone":"+49 7026/2978",
    "sg:postcode":"73268",
    "sg:province":"Baden-W\u00fcrttemberg",
    "wof:name":"Silvia Kuder",
    "wof:placetype":"venue"
},
  "geometry": {"coordinates":[9.425316,48.55743],"type":"Point"}
}