{
  "type": "Feature",
  "properties": {
    "iso:country":"DE",
    "sg:address":"Bl\u00fccherstr. 27",
    "sg:city":"Dortmund",
    "sg:phone":"+49 231/826968",
    "sg:postcode":"44147",
    "sg:province":"Nordrhein-Westfalen",
    "wof:name":"Beratungsstelle F\u00fcr Marokkanische Arbeitnehmer",
    "wof:placetype":"venue"
},
  "geometry": {"coordinates":[7.451181,51.520496],"type":"Point"}
}