{
  "type": "Feature",
  "properties": {
    "iso:country":"DE",
    "sg:address":"In der Krim 26",
    "sg:city":"Wuppertal",
    "sg:phone":"+49 202/460150",
    "sg:postcode":"42369",
    "sg:province":"Nordrhein-Westfalen",
    "wof:name":"Otto Schulte Ohg",
    "wof:placetype":"venue"
},
  "geometry": {"coordinates":[7.20217,51.229248],"type":"Point"}
}