{
  "type": "Feature",
  "properties": {
    "iso:country":"DE",
    "sg:address":"Elzerberg 3",
    "sg:city":"M\u00fcnsing",
    "sg:phone":"+49 8177/1046",
    "sg:postcode":"82541",
    "sg:province":"Bayern",
    "wof:name":"Dorothee Wilcke Rechtsanw\u00e4ltin",
    "wof:placetype":"venue"
},
  "geometry": {"coordinates":[11.3359975815,47.903678894],"type":"Point"}
}