{
  "type": "Feature",
  "properties": {
    "iso:country":"DE",
    "sg:address":"Feldstr. 9",
    "sg:city":"Horneburg",
    "sg:phone":"+49 4163/2149",
    "sg:postcode":"21640",
    "sg:province":"Niedersachsen",
    "wof:name":"J\u00fcrgen Duncker",
    "wof:placetype":"venue"
},
  "geometry": {"coordinates":[9.5708198547,53.5088920593],"type":"Point"}
}