{
  "type": "Feature",
  "properties": {
    "iso:country":"DE",
    "sg:address":"Schulstr. 16",
    "sg:city":"Titz",
    "sg:phone":"+49 2463/1651",
    "sg:postcode":"52445",
    "sg:province":"Nordrhein-Westfalen",
    "wof:name":"Kurt B\u00f6ckels Heissmangel",
    "wof:placetype":"venue"
},
  "geometry": {"coordinates":[6.4284658432,51.0028572083],"type":"Point"}
}