{
  "type": "Feature",
  "properties": {
    "iso:country":"DE",
    "sg:address":"Reinhardsh\u00e4user Str. 3",
    "sg:city":"Bad Wildungen",
    "sg:phone":"+49 5621/2112",
    "sg:postcode":"34537",
    "sg:province":"Hessen",
    "wof:name":"G\u00e4stehaus Reinhold Ulrich",
    "wof:placetype":"venue"
},
  "geometry": {"coordinates":[9.0584592819,51.1154937744],"type":"Point"}
}