{
  "type": "Feature",
  "properties": {
    "iso:country":"DE",
    "sg:address":"Fr\u00f6belstr. 1",
    "sg:city":"Dresden",
    "sg:phone":"+49 351/437547",
    "sg:postcode":"01159",
    "sg:province":"Sachsen",
    "wof:name":"Skoogs Elektrogro\u00dfhandel Dresden Gmbh",
    "wof:placetype":"venue"
},
  "geometry": {"coordinates":[13.7165184021,51.0503120422],"type":"Point"}
}