{
  "type": "Feature",
  "properties": {
    "iso:country":"DE",
    "sg:address":"Alter Gartenweg 14",
    "sg:city":"D\u00fclmen",
    "sg:phone":"+49 2594/94345",
    "sg:postcode":"48249",
    "sg:province":"Nordrhein-Westfalen",
    "wof:name":"Laumann Verwaltungs- Gmbh",
    "wof:placetype":"venue"
},
  "geometry": {"coordinates":[7.283093,51.828609],"type":"Point"}
}