{
  "type": "Feature",
  "properties": {
    "iso:country":"DE",
    "sg:city":"Dauchingen",
    "sg:phone":"+49 7720/64074",
    "sg:postcode":"78083",
    "sg:province":"Baden-W\u00fcrttemberg",
    "wof:name":"A. Benzing",
    "wof:placetype":"venue"
},
  "geometry": {"coordinates":[8.552377,48.090321],"type":"Point"}
}