{
  "type": "Feature",
  "properties": {
    "iso:country":"DE",
    "sg:address":"Albert-Schweitzer-Str. 2",
    "sg:city":"Senftenberg",
    "sg:phone":"+49 3573/791943",
    "sg:postcode":"01968",
    "sg:province":"Brandenburg",
    "wof:name":"Wolfgang Plautz",
    "wof:placetype":"venue"
},
  "geometry": {"coordinates":[13.979531,51.520916],"type":"Point"}
}