{
  "type": "Feature",
  "properties": {
    "iso:country":"DE",
    "sg:address":"Baumgartenstr. 2",
    "sg:city":"Pfungstadt",
    "sg:phone":"+49 6157/6131",
    "sg:postcode":"64319",
    "sg:province":"Hessen",
    "wof:name":"P. Huber",
    "wof:placetype":"venue"
},
  "geometry": {"coordinates":[8.596482,49.800007],"type":"Point"}
}