{
  "type": "Feature",
  "properties": {
    "iso:country":"DE",
    "sg:address":"Am Weidenkamp 7",
    "sg:city":"Rodenberg",
    "sg:phone":"+49 5723/2106",
    "sg:postcode":"31552",
    "sg:province":"Niedersachsen",
    "wof:name":"Konrad Geweke",
    "wof:placetype":"venue"
},
  "geometry": {"coordinates":[9.35336,52.316299],"type":"Point"}
}