{
  "type": "Feature",
  "properties": {
    "iso:country":"DE",
    "sg:address":"Hagener Str. 79",
    "sg:city":"Gevelsberg",
    "sg:phone":"+49 2332/3055",
    "sg:postcode":"58285",
    "sg:province":"Nordrhein-Westfalen",
    "wof:name":"Imcomatex Benkert Gmbh",
    "wof:placetype":"venue"
},
  "geometry": {"coordinates":[7.3485321999,51.3243904114],"type":"Point"}
}