{
  "type": "Feature",
  "properties": {
    "iso:country":"DE",
    "sg:address":"Pestelstr. 7",
    "sg:city":"Saarbr\u00fccken",
    "sg:postcode":"66119",
    "sg:province":"Saarland",
    "wof:name":"Atlas Van Driel Gmbh",
    "wof:placetype":"venue"
},
  "geometry": {"coordinates":[6.9952750206,49.2282104492],"type":"Point"}
}