{
  "type": "Feature",
  "properties": {
    "iso:country":"DE",
    "sg:address":"Adam-M\u00fcller-Str. 68",
    "sg:city":"Pirmasens",
    "sg:phone":"+49 6331/91391",
    "sg:postcode":"66954",
    "sg:province":"Rheinland-Pfalz",
    "wof:name":"Th. Und Fr. Adrian Gmbh",
    "wof:placetype":"venue"
},
  "geometry": {"coordinates":[7.590934,49.20005],"type":"Point"}
}