{
  "type": "Feature",
  "properties": {
    "iso:country":"DE",
    "sg:address":"Dr.-Gartenhof-Str. 2",
    "sg:city":"Bad Br\u00fcckenau",
    "sg:postcode":"97769",
    "sg:province":"Bayern",
    "wof:name":"M. M\u00fcller",
    "wof:placetype":"venue"
},
  "geometry": {"coordinates":[9.78126,50.304245],"type":"Point"}
}