{
  "type": "Feature",
  "properties": {
    "iso:country":"DE",
    "sg:address":"Normannenstr. 11",
    "sg:city":"Berlin",
    "sg:phone":"+49 30/8031938",
    "sg:postcode":"14129",
    "sg:province":"Berlin",
    "wof:name":"Gerd Heiligenst\u00fchler Architekt",
    "wof:placetype":"venue"
},
  "geometry": {"coordinates":[13.196908,52.430531],"type":"Point"}
}