{
  "type": "Feature",
  "properties": {
    "iso:country":"DE",
    "sg:address":"Landstr. 58",
    "sg:city":"Grevenbroich",
    "sg:phone":"+49 2182/1619",
    "sg:postcode":"41516",
    "sg:province":"Nordrhein-Westfalen",
    "wof:name":"Mathias Kremer",
    "wof:placetype":"venue"
},
  "geometry": {"coordinates":[6.593221,51.124199],"type":"Point"}
}