{
  "type": "Feature",
  "properties": {
    "iso:country":"DE",
    "sg:address":"Hungenbach 1 d",
    "sg:city":"K\u00fcrten",
    "sg:phone":"+49 2268/6309",
    "sg:postcode":"51515",
    "sg:province":"Nordrhein-Westfalen",
    "wof:name":"Bad Gruppe Gmbh",
    "wof:placetype":"venue"
},
  "geometry": {"coordinates":[7.2619028091,51.0338020325],"type":"Point"}
}