{
  "type": "Feature",
  "properties": {
    "iso:country":"DE",
    "sg:address":"Im Eickelkamp 162",
    "sg:city":"Duisburg",
    "sg:phone":"+49 203/592762",
    "sg:postcode":"47169",
    "sg:province":"Nordrhein-Westfalen",
    "wof:name":"Hermann Tofahrn",
    "wof:placetype":"venue"
},
  "geometry": {"coordinates":[6.77901,51.526405],"type":"Point"}
}