{
  "type": "Feature",
  "properties": {
    "iso:country":"DE",
    "sg:address":"Friedrichstr. 13",
    "sg:city":"Kamp-Lintfort",
    "sg:phone":"+49 2842/10054",
    "sg:postcode":"47475",
    "sg:province":"Nordrhein-Westfalen",
    "wof:name":"J. Berns Gmbh & Cie. Cafe- Und Backbetriebs-kg",
    "wof:placetype":"venue"
},
  "geometry": {"coordinates":[6.549269,51.500954],"type":"Point"}
}