{
  "type": "Feature",
  "properties": {
    "iso:country":"DE",
    "sg:address":"Oppenheimstr. 9",
    "sg:city":"K\u00f6ln",
    "sg:postcode":"50668",
    "sg:province":"Nordrhein-Westfalen",
    "wof:name":"Mundus Immobilien- Verwaltungsgesellschaft Mbh",
    "wof:placetype":"venue"
},
  "geometry": {"coordinates":[6.969285965,50.9549598694],"type":"Point"}
}