{
  "type": "Feature",
  "properties": {
    "iso:country":"DE",
    "sg:address":"Rethener Str. 29",
    "sg:city":"Sehnde",
    "sg:phone":"+49 5138/616820",
    "sg:postcode":"31319",
    "sg:province":"Niedersachsen",
    "wof:name":"August Rulff",
    "wof:placetype":"venue"
},
  "geometry": {"coordinates":[9.93112,52.320171],"type":"Point"}
}