{
  "type": "Feature",
  "properties": {
    "iso:country":"DE",
    "sg:address":"Auf der Ferlicht 6",
    "sg:city":"Giesen",
    "sg:phone":"+49 5121/770301",
    "sg:postcode":"31180",
    "sg:province":"Niedersachsen",
    "wof:name":"Herbert Bredereck Ingenieur",
    "wof:placetype":"venue"
},
  "geometry": {"coordinates":[9.891503334,52.1998519897],"type":"Point"}
}