{
  "type": "Feature",
  "properties": {
    "iso:country":"DE",
    "sg:address":"Krumbacher Str. 8",
    "sg:city":"Schwabm\u00fcnchen",
    "sg:phone":"+49 8232/4866",
    "sg:postcode":"86830",
    "sg:province":"Bayern",
    "wof:name":"Matthias H\u00f6ld",
    "wof:placetype":"venue"
},
  "geometry": {"coordinates":[10.752458,48.186214],"type":"Point"}
}