{
  "type": "Feature",
  "properties": {
    "iso:country":"DE",
    "sg:address":"Eppendorfer Landstr. 155",
    "sg:city":"Hamburg",
    "sg:phone":"+49 40/48074140",
    "sg:postcode":"20251",
    "sg:province":"Hamburg",
    "wof:name":"Hans-g\u00fcnter H\u00f6rcher Steuerberater",
    "wof:placetype":"venue"
},
  "geometry": {"coordinates":[9.9877986908,53.5954627991],"type":"Point"}
}