{
  "type": "Feature",
  "properties": {
    "iso:country":"DE",
    "sg:address":"Am Lohner Bach 9",
    "sg:city":"Wietmarschen",
    "sg:phone":"+49 5925/1276",
    "sg:postcode":"49835",
    "sg:province":"Niedersachsen",
    "wof:name":"Ulrike Kerstiens Heilpraktikerin",
    "wof:placetype":"venue"
},
  "geometry": {"coordinates":[7.1495938301,52.500869751],"type":"Point"}
}