{
  "type": "Feature",
  "properties": {
    "iso:country":"DE",
    "sg:address":"Siedlung West 1",
    "sg:city":"Lassan",
    "sg:phone":"+49 38374/80239",
    "sg:postcode":"17440",
    "sg:province":"Mecklenburg-Vorpommern",
    "wof:name":"Piehl Transporte",
    "wof:placetype":"venue"
},
  "geometry": {"coordinates":[13.8431615829,53.9476852417],"type":"Point"}
}