{
  "type": "Feature",
  "properties": {
    "iso:country":"DE",
    "sg:address":"Bergholzstr. 9-12",
    "sg:city":"Berlin",
    "sg:phone":"+49 30/6257016",
    "sg:postcode":"12099",
    "sg:province":"Berlin",
    "wof:name":"Verein Der Rheinl\u00e4nder Zu Berlin E. V.",
    "wof:placetype":"venue"
},
  "geometry": {"coordinates":[13.4197273254,52.4585990906],"type":"Point"}
}