{
  "type": "Feature",
  "properties": {
    "iso:country":"DE",
    "sg:address":"Bunnenbergstr. 23",
    "sg:city":"Hannover",
    "sg:phone":"+49 511/393467",
    "sg:postcode":"30165",
    "sg:province":"Niedersachsen",
    "wof:name":"G. Dunker",
    "wof:placetype":"venue"
},
  "geometry": {"coordinates":[9.7215528488,52.3962173462],"type":"Point"}
}