{
  "type": "Feature",
  "properties": {
    "iso:country":"DE",
    "sg:address":"Im Kaltenb\u00e4chel 15 b",
    "sg:city":"Dahn",
    "sg:phone":"+49 6391/3507",
    "sg:postcode":"66994",
    "sg:province":"Rheinland-Pfalz",
    "wof:name":"Heinz Riehm",
    "wof:placetype":"venue"
},
  "geometry": {"coordinates":[7.7792167664,49.1470756531],"type":"Point"}
}