{
  "type": "Feature",
  "properties": {
    "iso:country":"DE",
    "sg:address":"Kurt Keicher 70",
    "sg:city":"Gera",
    "sg:postcode":"07545",
    "sg:province":"Th\u00fcringen",
    "wof:name":"Erik\u00b4s Gera Hp",
    "wof:placetype":"venue"
},
  "geometry": {"coordinates":[12.086189,50.888321],"type":"Point"}
}