{
  "type": "Feature",
  "properties": {
    "iso:country":"DE",
    "sg:address":"Coburger Str. 43",
    "sg:city":"Grub",
    "sg:postcode":"96271",
    "sg:province":"Bayern",
    "wof:name":"Jahn Gmbh",
    "wof:placetype":"venue"
},
  "geometry": {"coordinates":[11.019892,50.227524],"type":"Point"}
}