{
  "type": "Feature",
  "properties": {
    "iso:country":"DE",
    "sg:address":"Schlottergasse 1",
    "sg:city":"Bischofsheim",
    "sg:phone":"+49 9772/360",
    "sg:postcode":"97653",
    "sg:province":"Bayern",
    "wof:name":"Arno Korb Elektroinstallation",
    "wof:placetype":"venue"
},
  "geometry": {"coordinates":[10.032091,50.397125],"type":"Point"}
}