{
  "type": "Feature",
  "properties": {
    "iso:country":"DE",
    "sg:address":"Kirchstr. 10",
    "sg:city":"Greiffenberg",
    "sg:phone":"+49 33334/548",
    "sg:postcode":"16278",
    "sg:province":"Brandenburg",
    "wof:name":"G. H\u00e4usler",
    "wof:placetype":"venue"
},
  "geometry": {"coordinates":[13.954291,53.087902],"type":"Point"}
}