{
  "type": "Feature",
  "properties": {
    "iso:country":"DE",
    "sg:address":"Messenh\u00e4user Str. 42",
    "sg:city":"R\u00f6dermark",
    "sg:phone":"+49 6074/6990",
    "sg:postcode":"63322",
    "sg:province":"Hessen",
    "wof:name":"Peter Ignaz Herdt Kg",
    "wof:placetype":"venue"
},
  "geometry": {"coordinates":[8.803052,49.983772],"type":"Point"}
}