{
  "type": "Feature",
  "properties": {
    "iso:country":"DE",
    "sg:address":"Wintersteinstr.47",
    "sg:city":"Friedberg",
    "sg:phone":"+49 6031/188271",
    "sg:postcode":"61169",
    "sg:province":"Hessen",
    "wof:name":"Home-bau",
    "wof:placetype":"venue"
},
  "geometry": {"coordinates":[8.7415599823,50.3330612183],"type":"Point"}
}