{
  "type": "Feature",
  "properties": {
    "iso:country":"DE",
    "sg:address":"Adlerstr. 17",
    "sg:city":"Oberhausen-Rheinhausen",
    "sg:phone":"+49 7254/2166",
    "sg:postcode":"68794",
    "sg:province":"Baden-W\u00fcrttemberg",
    "wof:name":"M. Rothardt",
    "wof:placetype":"venue"
},
  "geometry": {"coordinates":[8.495983,49.262375],"type":"Point"}
}