{
  "type": "Feature",
  "properties": {
    "iso:country":"DE",
    "sg:address":"Annabergstr. 13",
    "sg:city":"Stuttgart",
    "sg:phone":"+49 711/5282583",
    "sg:postcode":"70374",
    "sg:province":"Baden-W\u00fcrttemberg",
    "wof:name":"Roland Horn Architekt",
    "wof:placetype":"venue"
},
  "geometry": {"coordinates":[9.233456,48.802982],"type":"Point"}
}