{
  "type": "Feature",
  "properties": {
    "iso:country":"DE",
    "sg:address":"Schamerloh 71",
    "sg:city":"Warmsen",
    "sg:phone":"+49 5767/294",
    "sg:postcode":"31606",
    "sg:province":"Niedersachsen",
    "wof:name":"Gasthaus August Kurk",
    "wof:placetype":"venue"
},
  "geometry": {"coordinates":[8.858215332,52.4263877869],"type":"Point"}
}