{
  "type": "Feature",
  "properties": {
    "iso:country":"DE",
    "sg:address":"Grapengie\u00dferstr. 30",
    "sg:city":"L\u00fcbeck",
    "sg:phone":"+49 451/879880",
    "sg:postcode":"23556",
    "sg:province":"Schleswig-Holstein",
    "wof:name":"Steintor-verlag Gmbh",
    "wof:placetype":"venue"
},
  "geometry": {"coordinates":[10.6341495514,53.8620071411],"type":"Point"}
}