{
  "type": "Feature",
  "properties": {
    "iso:country":"DE",
    "sg:address":"Markt 26",
    "sg:city":"Erftstadt",
    "sg:phone":"+49 2235/75986",
    "sg:postcode":"50374",
    "sg:province":"Nordrhein-Westfalen",
    "wof:name":"Wilhelm Heinemann Gmbh & Co. Kg",
    "wof:placetype":"venue"
},
  "geometry": {"coordinates":[6.76602,50.799885],"type":"Point"}
}