{
  "type": "Feature",
  "properties": {
    "iso:country":"DE",
    "sg:address":"Richard-Tauber-Damm 19a",
    "sg:city":"Berlin",
    "sg:phone":"+49 30/7434307",
    "sg:postcode":"12277",
    "sg:province":"Berlin",
    "wof:name":"Gerhard Becker",
    "wof:placetype":"venue"
},
  "geometry": {"coordinates":[13.392437,52.418854],"type":"Point"}
}