{
  "type": "Feature",
  "properties": {
    "iso:country":"DE",
    "sg:address":"Neuhauser Str.",
    "sg:city":"M\u00fcnchen",
    "sg:postcode":"80305",
    "sg:province":"Bayern",
    "wof:name":"Systembetreuer-web",
    "wof:placetype":"venue"
},
  "geometry": {"coordinates":[11.56774,48.138737],"type":"Point"}
}