{
  "type": "Feature",
  "properties": {
    "iso:country":"DE",
    "sg:address":"Steeger Str. 9",
    "sg:city":"Velbert",
    "sg:phone":"+49 2051/84419",
    "sg:postcode":"42551",
    "sg:province":"Nordrhein-Westfalen",
    "wof:name":"H\u00f6lzemann Malerbetrieb Gmbh",
    "wof:placetype":"venue"
},
  "geometry": {"coordinates":[7.05234,51.338821],"type":"Point"}
}