{
  "type": "Feature",
  "properties": {
    "iso:country":"DE",
    "sg:address":"Breniger Str. 36",
    "sg:city":"Swisttal",
    "sg:phone":"+49 2254/5383",
    "sg:postcode":"53913",
    "sg:province":"Nordrhein-Westfalen",
    "wof:name":"Willi Mager",
    "wof:placetype":"venue"
},
  "geometry": {"coordinates":[6.922412,50.722355],"type":"Point"}
}