{
  "type": "Feature",
  "properties": {
    "iso:country":"DE",
    "sg:address":"Rudolf-Diesel Stra\u00dfe 53",
    "sg:city":"Oldenburg",
    "sg:postcode":"26135",
    "sg:province":"Niedersachsen",
    "wof:name":"Futurama",
    "wof:placetype":"venue"
},
  "geometry": {"coordinates":[8.22951,53.12439],"type":"Point"}
}