{
  "type": "Feature",
  "properties": {
    "iso:country":"DE",
    "sg:address":"Schlo\u00dfstr. 12",
    "sg:city":"Staffelstein",
    "sg:phone":"+49 9573/6717",
    "sg:postcode":"96231",
    "sg:province":"Bayern",
    "wof:name":"S. Kraus",
    "wof:placetype":"venue"
},
  "geometry": {"coordinates":[11.012873,50.118584],"type":"Point"}
}