{
  "type": "Feature",
  "properties": {
    "iso:country":"DE",
    "sg:address":"Hafenstr. 187",
    "sg:city":"Bremerhaven",
    "sg:phone":"+49 4947/152591",
    "sg:postcode":"27568",
    "sg:province":"Bremen",
    "wof:name":"B\u00c4ckerei Schulz , Inh. Silvia Kn\u00c4be",
    "wof:placetype":"venue"
},
  "geometry": {"coordinates":[8.586145401,53.5636863708],"type":"Point"}
}