{
  "type": "Feature",
  "properties": {
    "iso:country":"DE",
    "sg:address":"Waldenserstr. 2-4",
    "sg:city":"Berlin",
    "sg:phone":"+49 30/3973840",
    "sg:postcode":"10551",
    "sg:province":"Berlin",
    "wof:name":"Martin Seebauer Karl Wefers Und Partner",
    "wof:placetype":"venue"
},
  "geometry": {"coordinates":[13.337431,52.528564],"type":"Point"}
}