{
  "type": "Feature",
  "properties": {
    "iso:country":"DE",
    "sg:address":"Pfarrgasse 6a",
    "sg:city":"Grettstadt",
    "sg:postcode":"97508",
    "sg:province":"Bayern",
    "wof:name":"D. Barabeisch Bei Stumm",
    "wof:placetype":"venue"
},
  "geometry": {"coordinates":[10.3644933701,50.0021362305],"type":"Point"}
}