{
  "type": "Feature",
  "properties": {
    "iso:country":"DE",
    "sg:address":"Schubertstr. 15",
    "sg:city":"Dortmund",
    "sg:phone":"+49 231/815557",
    "sg:postcode":"44145",
    "sg:province":"Nordrhein-Westfalen",
    "wof:name":"K. H\u00e4ring",
    "wof:placetype":"venue"
},
  "geometry": {"coordinates":[7.4616241455,51.5269432068],"type":"Point"}
}