{
  "type": "Feature",
  "properties": {
    "iso:country":"DE",
    "sg:address":"Mattinger Str. 3",
    "sg:city":"Regensburg",
    "sg:phone":"+49 941/31945",
    "sg:postcode":"93049",
    "sg:province":"Bayern",
    "wof:name":"Albert Wolfram Architekt",
    "wof:placetype":"venue"
},
  "geometry": {"coordinates":[12.033914,49.008667],"type":"Point"}
}