{
  "type": "Feature",
  "properties": {
    "iso:country":"DE",
    "sg:address":"M\u00fchlstr. 29",
    "sg:city":"O\u00dfling",
    "sg:phone":"+49 35792/50341",
    "sg:postcode":"01920",
    "sg:province":"Sachsen",
    "wof:name":"Christian Jurk",
    "wof:placetype":"venue"
},
  "geometry": {"coordinates":[14.173931,51.33197],"type":"Point"}
}