{
  "type": "Feature",
  "properties": {
    "iso:country":"DE",
    "sg:address":"Deichstr. 3",
    "sg:city":"Wangerland",
    "sg:phone":"+49 4426/295",
    "sg:postcode":"26434",
    "sg:province":"Niedersachsen",
    "wof:name":"Strandhotel Heiko Hinrichs",
    "wof:placetype":"venue"
},
  "geometry": {"coordinates":[8.0181798935,53.6896705627],"type":"Point"}
}