{
  "type": "Feature",
  "properties": {
    "iso:country":"DE",
    "sg:address":"Walshauser Str. 9",
    "sg:city":"Kleinsteinhausen",
    "sg:phone":"+49 6339/207",
    "sg:postcode":"66484",
    "sg:province":"Rheinland-Pfalz",
    "wof:name":"Lore Knerr",
    "wof:placetype":"venue"
},
  "geometry": {"coordinates":[7.470485,49.200912],"type":"Point"}
}