{
  "type": "Feature",
  "properties": {
    "iso:country":"DE",
    "sg:address":"Kurf\u00fcrstenstr. 7",
    "sg:city":"Berlin",
    "sg:postcode":"10785",
    "sg:province":"Berlin",
    "wof:name":"Info-agentur Gmbh",
    "wof:placetype":"venue"
},
  "geometry": {"coordinates":[13.367937088,52.4991416931],"type":"Point"}
}