{
  "type": "Feature",
  "properties": {
    "iso:country":"DE",
    "sg:address":"Hasselbrookstr. 1",
    "sg:city":"Hamburg",
    "sg:postcode":"22089",
    "sg:province":"Hamburg",
    "wof:name":"Bardeleben Gmbh",
    "wof:placetype":"venue"
},
  "geometry": {"coordinates":[10.037238,53.561832],"type":"Point"}
}