{
  "type": "Feature",
  "properties": {
    "iso:country":"DE",
    "sg:address":"Im Thomas 5",
    "sg:city":"Borken",
    "sg:phone":"+49 2862/1369",
    "sg:postcode":"46325",
    "sg:province":"Nordrhein-Westfalen",
    "wof:name":"Andreas Bolewski",
    "wof:placetype":"venue"
},
  "geometry": {"coordinates":[6.855133,51.904461],"type":"Point"}
}