{
  "type": "Feature",
  "properties": {
    "iso:country":"DE",
    "sg:address":"Seestr. 4",
    "sg:city":"Uffing",
    "sg:phone":"+49 8846/9320",
    "sg:postcode":"82449",
    "sg:province":"Bayern",
    "wof:name":"Hans-heinz Krau\u00dfe Heilpraktiker",
    "wof:placetype":"venue"
},
  "geometry": {"coordinates":[11.1522512436,47.7137413025],"type":"Point"}
}