{
  "type": "Feature",
  "properties": {
    "iso:country":"DE",
    "sg:address":"M\u00f6llendorffstr. 10",
    "sg:city":"Berlin",
    "sg:phone":"+49 30/5568990",
    "sg:postcode":"10367",
    "sg:province":"Berlin",
    "wof:name":"M\u00fcnzel Bestattungs Gmbh",
    "wof:placetype":"venue"
},
  "geometry": {"coordinates":[13.480068,52.516895],"type":"Point"}
}