{
  "type": "Feature",
  "properties": {
    "iso:country":"DE",
    "sg:address":"Zur Alten M\u00fchle 11",
    "sg:city":"Korbach",
    "sg:phone":"+49 5631/8819",
    "sg:postcode":"34497",
    "sg:province":"Hessen",
    "wof:name":"Martin B\u00f6hmeke",
    "wof:placetype":"venue"
},
  "geometry": {"coordinates":[8.792269,51.287792],"type":"Point"}
}