{
  "type": "Feature",
  "properties": {
    "iso:country":"DE",
    "sg:address":"Martin-Luther-Str. 58",
    "sg:city":"Berlin",
    "sg:phone":"+49 30/2187535",
    "sg:postcode":"10779",
    "sg:province":"Berlin",
    "wof:name":"Regina-apotheke Inh. Gerhard Lippold",
    "wof:placetype":"venue"
},
  "geometry": {"coordinates":[13.344866,52.491257],"type":"Point"}
}