{
  "type": "Feature",
  "properties": {
    "iso:country":"DE",
    "sg:address":"Am Berg 2",
    "sg:city":"Willingshausen",
    "sg:phone":"+49 6691/1592",
    "sg:postcode":"34628",
    "sg:province":"Hessen",
    "wof:name":"Fleischerei Karl Schlein Inh. Dieter Schlein",
    "wof:placetype":"venue"
},
  "geometry": {"coordinates":[9.18708992,50.8731765747],"type":"Point"}
}