{
  "type": "Feature",
  "properties": {
    "iso:country":"DE",
    "sg:address":"Brandstr\u00f6mstr. 6",
    "sg:city":"Meppen",
    "sg:phone":"+49 5931/5510",
    "sg:postcode":"49716",
    "sg:province":"Niedersachsen",
    "wof:name":"K. Conrads Gmbh",
    "wof:placetype":"venue"
},
  "geometry": {"coordinates":[7.3147239685,52.6973686218],"type":"Point"}
}