{
  "type": "Feature",
  "properties": {
    "iso:country":"DE",
    "sg:address":"Kaiser-Wilhelm-Ring 23",
    "sg:city":"Mainz",
    "sg:phone":"+49 6131/616900",
    "sg:postcode":"55118",
    "sg:province":"Rheinland-Pfalz",
    "wof:name":"Pizzeria Bambino",
    "wof:placetype":"venue"
},
  "geometry": {"coordinates":[8.2560796738,50.004940033],"type":"Point"}
}