{
  "type": "Feature",
  "properties": {
    "iso:country":"DE",
    "sg:address":"Grammendorfer Weg",
    "sg:city":"Tribsees",
    "sg:phone":"+49 38320/47927",
    "sg:postcode":"18465",
    "sg:province":"Mecklenburg-Vorpommern",
    "wof:name":"Tankstelle Tribsees",
    "wof:placetype":"venue"
},
  "geometry": {"coordinates":[12.7721691132,54.0921516418],"type":"Point"}
}