{
  "type": "Feature",
  "properties": {
    "iso:country":"DE",
    "sg:address":"Gustav-Mahler-Str. 7",
    "sg:city":"Ratingen",
    "sg:phone":"+49 2102/31492",
    "sg:postcode":"40885",
    "sg:province":"Nordrhein-Westfalen",
    "wof:name":"Korb & Sohn Gmbh",
    "wof:placetype":"venue"
},
  "geometry": {"coordinates":[6.838004,51.33749],"type":"Point"}
}