{
  "type": "Feature",
  "properties": {
    "iso:country":"DE",
    "sg:address":"Weberstr. 6",
    "sg:city":"Ettlingen",
    "sg:phone":"+49 7243/20122",
    "sg:postcode":"76275",
    "sg:province":"Baden-W\u00fcrttemberg",
    "wof:name":"M. Weber",
    "wof:placetype":"venue"
},
  "geometry": {"coordinates":[8.433098793,48.9146652222],"type":"Point"}
}