{
  "type": "Feature",
  "properties": {
    "iso:country":"DE",
    "sg:address":"Schlo\u00dfstr. 8",
    "sg:city":"G\u00fclzow",
    "sg:phone":"+49 4151/82420",
    "sg:postcode":"21483",
    "sg:province":"Schleswig-Holstein",
    "wof:name":"Werner Glabbart",
    "wof:placetype":"venue"
},
  "geometry": {"coordinates":[10.490355,53.442852],"type":"Point"}
}