{
  "type": "Feature",
  "properties": {
    "iso:country":"DE",
    "sg:address":"Kreiensener Str. 1",
    "sg:city":"Bad Gandersheim",
    "sg:phone":"+49 5563/1747",
    "sg:postcode":"37581",
    "sg:province":"Niedersachsen",
    "wof:name":"G. Wiese-g\u00fcnther",
    "wof:placetype":"venue"
},
  "geometry": {"coordinates":[10.024801,51.870716],"type":"Point"}
}