{
  "type": "Feature",
  "properties": {
    "iso:country":"DE",
    "sg:address":"Umgehungsstr. 43",
    "sg:city":"Lauterbach",
    "sg:postcode":"36341",
    "sg:province":"Hessen",
    "wof:name":"Domaschka Verwaltungs Gmbh",
    "wof:placetype":"venue"
},
  "geometry": {"coordinates":[9.3934459686,50.6418075562],"type":"Point"}
}