{
  "type": "Feature",
  "properties": {
    "iso:country":"DE",
    "sg:address":"Nietzschestr. 2",
    "sg:city":"K\u00f6ln",
    "sg:phone":"+49 2203/64035",
    "sg:postcode":"51147",
    "sg:province":"Nordrhein-Westfalen",
    "wof:name":"Weg\u00f6 K\u00f6ln Baubetreuungs Gmbh",
    "wof:placetype":"venue"
},
  "geometry": {"coordinates":[7.097455,50.869766],"type":"Point"}
}