{
  "type": "Feature",
  "properties": {
    "iso:country":"DE",
    "sg:address":"Im S\u00fcdfeld 11",
    "sg:city":"Senden",
    "sg:phone":"+49 2536/99590",
    "sg:postcode":"48308",
    "sg:province":"Nordrhein-Westfalen",
    "wof:name":"M\u00f6ller Import Gmbh & Co. Kg",
    "wof:placetype":"venue"
},
  "geometry": {"coordinates":[7.476614,51.907707],"type":"Point"}
}