{
  "type": "Feature",
  "properties": {
    "iso:country":"DE",
    "sg:address":"G\u00e4rtnerstr. 92",
    "sg:city":"Elmshorn",
    "sg:phone":"+49 4121/42190",
    "sg:postcode":"25335",
    "sg:province":"Schleswig-Holstein",
    "wof:name":"Hotel Drei Kronen Claus Und Hertha Andresen",
    "wof:placetype":"venue"
},
  "geometry": {"coordinates":[9.6469202042,53.7565536499],"type":"Point"}
}