{
  "type": "Feature",
  "properties": {
    "iso:country":"DE",
    "sg:address":"Hohkeppeler Str. 23",
    "sg:city":"Overath",
    "sg:postcode":"51491",
    "sg:province":"Nordrhein-Westfalen",
    "wof:name":"Wib Gmbh",
    "wof:placetype":"venue"
},
  "geometry": {"coordinates":[7.25702,50.940708],"type":"Point"}
}