{
  "type": "Feature",
  "properties": {
    "iso:country":"DE",
    "sg:address":"Akeleiweg 3",
    "sg:city":"Geretsried",
    "sg:phone":"+49 8171/60141",
    "sg:postcode":"82538",
    "sg:province":"Bayern",
    "wof:name":"Alois Plonczek",
    "wof:placetype":"venue"
},
  "geometry": {"coordinates":[11.465833,47.886318],"type":"Point"}
}