{
  "type": "Feature",
  "properties": {
    "iso:country":"DE",
    "sg:address":"Leipziger Str. 18",
    "sg:city":"Crimmitschau",
    "sg:phone":"+49 3762/5327",
    "sg:postcode":"08451",
    "sg:province":"Sachsen",
    "wof:name":"Thomas Sch\u00e4fer",
    "wof:placetype":"venue"
},
  "geometry": {"coordinates":[12.3861646652,50.8181419373],"type":"Point"}
}