{
  "type": "Feature",
  "properties": {
    "iso:country":"DE",
    "sg:address":"Frauentorstr. 8",
    "sg:city":"Augsburg",
    "sg:phone":"+49 821/343930",
    "sg:postcode":"86152",
    "sg:province":"Bayern",
    "wof:name":"Hotel-garni Dom-hotel",
    "wof:placetype":"venue"
},
  "geometry": {"coordinates":[10.8965473175,48.3738861084],"type":"Point"}
}