{
  "type": "Feature",
  "properties": {
    "iso:country":"DE",
    "sg:address":"Adalbert-Stifter-Weg 25",
    "sg:city":"Chemnitz",
    "sg:postcode":"09131",
    "sg:province":"Sachsen",
    "wof:name":"Korte & Mrosek Gmbh",
    "wof:placetype":"venue"
},
  "geometry": {"coordinates":[12.9423923492,50.8681106567],"type":"Point"}
}