{
  "type": "Feature",
  "properties": {
    "iso:country":"DE",
    "sg:address":"Heigenbr\u00fccker Weg 23",
    "sg:city":"Frankfurt",
    "sg:phone":"+49 69/685903",
    "sg:postcode":"60599",
    "sg:province":"Hessen",
    "wof:name":"Robert Pauly Rechtsanwalt",
    "wof:placetype":"venue"
},
  "geometry": {"coordinates":[8.6924438477,50.0941352844],"type":"Point"}
}