{
  "type": "Feature",
  "properties": {
    "iso:country":"DE",
    "sg:address":"Kurzer Ging 116",
    "sg:city":"Springe",
    "sg:phone":"+49 5041/3902",
    "sg:postcode":"31832",
    "sg:province":"Niedersachsen",
    "wof:name":"Dieter Bertram Verlagsvertreter",
    "wof:placetype":"venue"
},
  "geometry": {"coordinates":[9.540439,52.213821],"type":"Point"}
}