{
  "type": "Feature",
  "properties": {
    "iso:country":"DE",
    "sg:address":"Lohbecker Berg 32",
    "sg:city":"M\u00fclheim",
    "sg:phone":"+49 208/360031",
    "sg:postcode":"45470",
    "sg:province":"Nordrhein-Westfalen",
    "wof:name":"Immobilien-bagusat Gmbh",
    "wof:placetype":"venue"
},
  "geometry": {"coordinates":[6.892263,51.412022],"type":"Point"}
}