{
  "type": "Feature",
  "properties": {
    "iso:country":"DE",
    "sg:address":"Thorwaldsenstr. 11",
    "sg:city":"Berlin",
    "sg:phone":"+49 30/6937787",
    "sg:postcode":"12623",
    "sg:province":"Berlin",
    "wof:name":"B & B Buchungs- Und Beratungs- Gmbh",
    "wof:placetype":"venue"
},
  "geometry": {"coordinates":[13.611411,52.471397],"type":"Point"}
}