{
  "type": "Feature",
  "properties": {
    "iso:country":"DE",
    "sg:address":"B\u00f6tzinger Str. 16",
    "sg:city":"Freiburg",
    "sg:phone":"+49 761/472508",
    "sg:postcode":"79111",
    "sg:province":"Baden-W\u00fcrttemberg",
    "wof:name":"Wolfgang Hassler",
    "wof:placetype":"venue"
},
  "geometry": {"coordinates":[7.7884478569,47.993183136],"type":"Point"}
}