{
  "type": "Feature",
  "properties": {
    "iso:country":"DE",
    "sg:address":"Schellingstr. 14",
    "sg:city":"Fellbach",
    "sg:phone":"+49 711/512236",
    "sg:postcode":"70736",
    "sg:province":"Baden-W\u00fcrttemberg",
    "wof:name":"Kurt Ehrhardt Architekt",
    "wof:placetype":"venue"
},
  "geometry": {"coordinates":[9.270249,48.826752],"type":"Point"}
}