{
  "type": "Feature",
  "properties": {
    "iso:country":"DE",
    "sg:address":"Hausheimer Str. 23",
    "sg:city":"Berg",
    "sg:phone":"+49 9189/408000",
    "sg:postcode":"92348",
    "sg:province":"Bayern",
    "wof:name":"D\u00f6rrmann Bau Gmbh",
    "wof:placetype":"venue"
},
  "geometry": {"coordinates":[11.434948,49.329929],"type":"Point"}
}