{
  "type": "Feature",
  "properties": {
    "iso:country":"DE",
    "sg:address":"Hintere Breite 2",
    "sg:city":"Ihringen",
    "sg:phone":"+49 7668/5324",
    "sg:postcode":"79241",
    "sg:province":"Baden-W\u00fcrttemberg",
    "wof:name":"Erich Flubacher",
    "wof:placetype":"venue"
},
  "geometry": {"coordinates":[7.6634039879,48.0535774231],"type":"Point"}
}