{
  "type": "Feature",
  "properties": {
    "iso:country":"DE",
    "sg:address":"Burgstr. 52",
    "sg:city":"Dinklage",
    "sg:phone":"+49 4443/1263",
    "sg:postcode":"49413",
    "sg:province":"Niedersachsen",
    "wof:name":"Gastst\u00e4tte Ottilie L\u00fcers",
    "wof:placetype":"venue"
},
  "geometry": {"coordinates":[8.1290225983,52.6606292725],"type":"Point"}
}