{
  "type": "Feature",
  "properties": {
    "iso:country":"DE",
    "sg:address":"Liebigstr. 40",
    "sg:city":"Hamburg",
    "sg:phone":"+49 40/73670340",
    "sg:postcode":"22113",
    "sg:province":"Schleswig-Holstein",
    "wof:name":"Eugen H\u00f6rner",
    "wof:placetype":"venue"
},
  "geometry": {"coordinates":[10.087948,53.533798],"type":"Point"}
}