{
  "type": "Feature",
  "properties": {
    "iso:country":"DE",
    "sg:address":"Pritzwalker Str 1",
    "sg:city":"Giesensdorf",
    "sg:phone":"+49 3395/700796",
    "sg:postcode":"16928",
    "sg:province":"Brandenburg",
    "wof:name":"Flachshaus Gmbh",
    "wof:placetype":"venue"
},
  "geometry": {"coordinates":[12.1747303009,53.1506195068],"type":"Point"}
}