{
  "type": "Feature",
  "properties": {
    "iso:country":"DE",
    "sg:address":"H\u00f6henweg 31",
    "sg:city":"Thalfang",
    "sg:phone":"+49 6504/609",
    "sg:postcode":"54424",
    "sg:province":"Rheinland-Pfalz",
    "wof:name":"Martha Alt",
    "wof:placetype":"venue"
},
  "geometry": {"coordinates":[6.9841299057,49.7495193481],"type":"Point"}
}