{
  "type": "Feature",
  "properties": {
    "iso:country":"DE",
    "sg:address":"Wilhelmstr. 15",
    "sg:city":"Herten",
    "sg:phone":"+49 2366/81871",
    "sg:postcode":"45699",
    "sg:province":"Nordrhein-Westfalen",
    "wof:name":"Wilhelmschenke",
    "wof:placetype":"venue"
},
  "geometry": {"coordinates":[7.1429748535,51.5921134949],"type":"Point"}
}