{
  "type": "Feature",
  "properties": {
    "iso:country":"DE",
    "sg:address":"Stra\u00dfe der Freiheit 6",
    "sg:city":"Lebus",
    "sg:phone":"+49 33604/5052",
    "sg:postcode":"15326",
    "sg:province":"Brandenburg",
    "wof:name":"Heinz Famulla",
    "wof:placetype":"venue"
},
  "geometry": {"coordinates":[14.53915,52.42617],"type":"Point"}
}