{
  "type": "Feature",
  "properties": {
    "iso:country":"DE",
    "sg:address":"Zentstr. 1",
    "sg:city":"Flieden",
    "sg:phone":"+49 6655/3981",
    "sg:postcode":"36103",
    "sg:province":"Hessen",
    "wof:name":"Annette M\u00f6ller",
    "wof:placetype":"venue"
},
  "geometry": {"coordinates":[9.5671882629,50.4234542847],"type":"Point"}
}