{
  "type": "Feature",
  "properties": {
    "iso:country":"DE",
    "sg:address":"Grombacher Str. 1",
    "sg:city":"Bad Rappenau",
    "sg:phone":"+49 7268/292",
    "sg:postcode":"74906",
    "sg:province":"Baden-W\u00fcrttemberg",
    "wof:name":"G. Steeb",
    "wof:placetype":"venue"
},
  "geometry": {"coordinates":[9.039921,49.255608],"type":"Point"}
}