{
  "type": "Feature",
  "properties": {
    "iso:country":"DE",
    "sg:address":"Heubergstr. 7",
    "sg:city":"Reutlingen",
    "sg:phone":"+49 7121/44482",
    "sg:postcode":"72766",
    "sg:province":"Baden-W\u00fcrttemberg",
    "wof:name":"Gemo Gmbh",
    "wof:placetype":"venue"
},
  "geometry": {"coordinates":[9.218466,48.51284],"type":"Point"}
}