{
  "type": "Feature",
  "properties": {
    "iso:country":"DE",
    "sg:address":"Bahnhofstr. 21 a",
    "sg:city":"Herzberg",
    "sg:postcode":"37412",
    "sg:province":"Niedersachsen",
    "wof:name":"Herzberger Baustoffhandel Gmbh",
    "wof:placetype":"venue"
},
  "geometry": {"coordinates":[10.331897,51.647686],"type":"Point"}
}