{
  "type": "Feature",
  "properties": {
    "iso:country":"DE",
    "sg:address":"Horstweg 32",
    "sg:city":"Bad Oeynhausen",
    "sg:phone":"+49 5731/538868",
    "sg:postcode":"32549",
    "sg:province":"Nordrhein-Westfalen",
    "wof:name":"Pkv-center Gerking Online Versichern!",
    "wof:placetype":"venue"
},
  "geometry": {"coordinates":[8.791473,52.226128],"type":"Point"}
}