{
  "type": "Feature",
  "properties": {
    "iso:country":"DE",
    "sg:address":"Nordstrander Str. 22",
    "sg:city":"Heide",
    "sg:phone":"+49 481/5775",
    "sg:postcode":"25746",
    "sg:province":"Schleswig-Holstein",
    "wof:name":"H. Allwardt",
    "wof:placetype":"venue"
},
  "geometry": {"coordinates":[9.1018600464,54.2056350708],"type":"Point"}
}