{
  "type": "Feature",
  "properties": {
    "iso:country":"DE",
    "sg:address":"Lindenallee 35",
    "sg:city":"Wernigerode",
    "sg:postcode":"38855",
    "sg:province":"Sachsen-Anhalt",
    "wof:name":"Brockenhaus Gmbh",
    "wof:placetype":"venue"
},
  "geometry": {"coordinates":[10.792881012,51.8322715759],"type":"Point"}
}