{
  "type": "Feature",
  "properties": {
    "iso:country":"DE",
    "sg:address":"Ost-West-Str 3",
    "sg:city":"Rostock",
    "sg:phone":"+49 381/6700212",
    "sg:postcode":"18147",
    "sg:province":"Mecklenburg-Vorpommern",
    "wof:name":"Koschellnik + Susemihl Gbr",
    "wof:placetype":"venue"
},
  "geometry": {"coordinates":[12.103427,54.144062],"type":"Point"}
}