{
  "type": "Feature",
  "properties": {
    "iso:country":"DE",
    "sg:address":"Wilhelmsh\u00f6her Allee 137",
    "sg:city":"Kassel",
    "sg:phone":"+49 561/283366",
    "sg:postcode":"34121",
    "sg:province":"Hessen",
    "wof:name":"Yellow Kg",
    "wof:placetype":"venue"
},
  "geometry": {"coordinates":[9.4631519318,51.3124542236],"type":"Point"}
}