{
  "type": "Feature",
  "properties": {
    "iso:country":"DE",
    "sg:address":"Schmiedestr. 9",
    "sg:city":"Senftenberg",
    "sg:phone":"+49 3573/73714",
    "sg:postcode":"01968",
    "sg:province":"Brandenburg",
    "wof:name":"Jeans-house Warenhandels Gmbh",
    "wof:placetype":"venue"
},
  "geometry": {"coordinates":[14.00358,51.518539],"type":"Point"}
}