{
  "type": "Feature",
  "properties": {
    "iso:country":"DE",
    "sg:address":"Barsteder Str. 16",
    "sg:city":"Ihlow",
    "sg:phone":"+49 4928/1817",
    "sg:postcode":"26632",
    "sg:province":"Niedersachsen",
    "wof:name":"Kvhs",
    "wof:placetype":"venue"
},
  "geometry": {"coordinates":[7.368594,53.431602],"type":"Point"}
}