{
  "type": "Feature",
  "properties": {
    "iso:country":"DE",
    "sg:address":"Agnes-Bernauer-Str. 137",
    "sg:city":"M\u00fcnchen",
    "sg:phone":"+49 89/561865",
    "sg:postcode":"80687",
    "sg:province":"Bayern",
    "wof:name":"Aral Ag",
    "wof:placetype":"venue"
},
  "geometry": {"coordinates":[11.4920358658,48.1401138306],"type":"Point"}
}