{
  "type": "Feature",
  "properties": {
    "iso:country":"DE",
    "sg:address":"Treisberger Str. 1",
    "sg:city":"Frankfurt",
    "sg:phone":"+49 69/575354",
    "sg:postcode":"60439",
    "sg:province":"Hessen",
    "wof:name":"Friedrich E. Schmidt Dipl. Kfm.",
    "wof:placetype":"venue"
},
  "geometry": {"coordinates":[8.625831604,50.1547470093],"type":"Point"}
}