{
  "type": "Feature",
  "properties": {
    "iso:country":"DE",
    "sg:address":"Hagenstr. 41",
    "sg:city":"Darmstadt",
    "sg:phone":"+49 6151/51309",
    "sg:postcode":"64297",
    "sg:province":"Hessen",
    "wof:name":"Sandra Pfeiffer",
    "wof:placetype":"venue"
},
  "geometry": {"coordinates":[8.643231,49.822372],"type":"Point"}
}