{
  "type": "Feature",
  "properties": {
    "iso:country":"DE",
    "sg:address":"Bundesstr. 16",
    "sg:city":"Hattstedt",
    "sg:postcode":"25856",
    "sg:province":"Schleswig-Holstein",
    "wof:name":"Erhard Kr\u00f6ger E. K.",
    "wof:placetype":"venue"
},
  "geometry": {"coordinates":[9.0274496078,54.525100708],"type":"Point"}
}