{
  "type": "Feature",
  "properties": {
    "iso:country":"DE",
    "sg:address":"Philipp-M\u00fcller-Str. 28",
    "sg:city":"Stolzenhagen",
    "sg:postcode":"16348",
    "sg:province":"Brandenburg",
    "wof:name":"Turn Key - Bauausf\u00fchrungen Gmbh",
    "wof:placetype":"venue"
},
  "geometry": {"coordinates":[13.4726142883,52.7550354004],"type":"Point"}
}