{
  "type": "Feature",
  "properties": {
    "iso:country":"DE",
    "sg:address":"G\u00e4nseplatz 1",
    "sg:city":"Volkach",
    "sg:phone":"+49 9381/9874",
    "sg:postcode":"97332",
    "sg:province":"Bayern",
    "wof:name":"Virgin Lands Gmbh",
    "wof:placetype":"venue"
},
  "geometry": {"coordinates":[10.2274179459,49.8662261963],"type":"Point"}
}