{
  "type": "Feature",
  "properties": {
    "iso:country":"DE",
    "sg:address":"Ahornweg 101",
    "sg:city":"Ettlingen",
    "sg:phone":"+49 7243/78785",
    "sg:postcode":"76275",
    "sg:province":"Baden-W\u00fcrttemberg",
    "wof:name":"Waldemar Rohrer",
    "wof:placetype":"venue"
},
  "geometry": {"coordinates":[8.3816576004,48.9528121948],"type":"Point"}
}