{
  "type": "Feature",
  "properties": {
    "iso:country":"DE",
    "sg:address":"Karl-Goerdeler-Str. 5",
    "sg:city":"Georgsmarienh\u00fctte",
    "sg:phone":"+49 5401/45055",
    "sg:postcode":"49124",
    "sg:province":"Niedersachsen",
    "wof:name":"Ingrid Wagner E. K.",
    "wof:placetype":"venue"
},
  "geometry": {"coordinates":[8.07218647,52.2002182007],"type":"Point"}
}