{
  "type": "Feature",
  "properties": {
    "iso:country":"DE",
    "sg:address":"Bockenheimer Landstr. 97",
    "sg:city":"Frankfurt",
    "sg:phone":"+49 69/7434920",
    "sg:postcode":"60325",
    "sg:province":"Hessen",
    "wof:name":"Projektgruppe Kompass Gmbh",
    "wof:placetype":"venue"
},
  "geometry": {"coordinates":[8.657375,50.119488],"type":"Point"}
}