{
  "type": "Feature",
  "properties": {
    "iso:country":"DE",
    "sg:address":"Ebstorfer Str. 4",
    "sg:city":"Melbeck",
    "sg:phone":"+49 4134/219",
    "sg:postcode":"21406",
    "sg:province":"Niedersachsen",
    "wof:name":"W. Hagemann",
    "wof:placetype":"venue"
},
  "geometry": {"coordinates":[10.405621,53.179829],"type":"Point"}
}