{
  "type": "Feature",
  "properties": {
    "iso:country":"DE",
    "sg:address":"Bahnhofstr. 27",
    "sg:city":"Erfurt",
    "sg:postcode":"99084",
    "sg:province":"Th\u00fcringen",
    "wof:name":"Rechtsanwaltskammer Th\u00fcringen",
    "wof:placetype":"venue"
},
  "geometry": {"coordinates":[11.036322,50.973297],"type":"Point"}
}