{
  "type": "Feature",
  "properties": {
    "iso:country":"DE",
    "sg:address":"Kaiserstr. 47",
    "sg:city":"Ludwigsburg",
    "sg:phone":"+49 7141/929537",
    "sg:postcode":"71636",
    "sg:province":"Baden-W\u00fcrttemberg",
    "wof:name":"Abs Gmbh",
    "wof:placetype":"venue"
},
  "geometry": {"coordinates":[9.174266,48.897591],"type":"Point"}
}