{
  "type": "Feature",
  "properties": {
    "iso:country":"DE",
    "sg:address":"Krickmarkt 8",
    "sg:city":"Warendorf",
    "sg:phone":"+49 2581/2702",
    "sg:postcode":"48231",
    "sg:province":"Nordrhein-Westfalen",
    "wof:name":"Schwerbrock",
    "wof:placetype":"venue"
},
  "geometry": {"coordinates":[7.989819,51.95187],"type":"Point"}
}