{
  "type": "Feature",
  "properties": {
    "iso:country":"DE",
    "sg:address":"Niebuhrstra\u00dfe 57",
    "sg:city":"Oberhausen",
    "sg:postcode":"46049",
    "sg:province":"Nordrhein-Westfalen",
    "wof:name":"Purmetall Gmbh & Co. Kg - Gesellschaft F\u00fcr Stahlveredlung.",
    "wof:placetype":"venue"
},
  "geometry": {"coordinates":[6.8134098053,51.4725799561],"type":"Point"}
}