{
  "type": "Feature",
  "properties": {
    "iso:country":"DE",
    "sg:address":"Theodor-Heuss-Str. 10",
    "sg:city":"Waiblingen",
    "sg:phone":"+49 7151/20190",
    "sg:postcode":"71336",
    "sg:province":"Baden-W\u00fcrttemberg",
    "wof:name":"Ring-textilservice Gmbh",
    "wof:placetype":"venue"
},
  "geometry": {"coordinates":[9.3222532272,48.8625144958],"type":"Point"}
}