{
  "type": "Feature",
  "properties": {
    "iso:country":"DE",
    "sg:address":"Hauptstr. 78",
    "sg:city":"Hasselroth",
    "sg:phone":"+49 6055/5678",
    "sg:postcode":"63594",
    "sg:province":"Hessen",
    "wof:name":"H. Lotz",
    "wof:placetype":"venue"
},
  "geometry": {"coordinates":[9.1243190765,50.1701965332],"type":"Point"}
}