{
  "type": "Feature",
  "properties": {
    "iso:country":"DE",
    "sg:address":"Stummstr. 62",
    "sg:city":"Dillingen",
    "sg:phone":"+49 6831/703746",
    "sg:postcode":"66763",
    "sg:province":"Saarland",
    "wof:name":"Fashion City",
    "wof:placetype":"venue"
},
  "geometry": {"coordinates":[6.72885,49.354225],"type":"Point"}
}