{
  "type": "Feature",
  "properties": {
    "iso:country":"DE",
    "sg:address":"Industriestr. 13",
    "sg:city":"Saterland",
    "sg:postcode":"26683",
    "sg:province":"Niedersachsen",
    "wof:name":"Spree-elster- Baumaschinenhandel Gmbh",
    "wof:placetype":"venue"
},
  "geometry": {"coordinates":[7.6866788864,53.1020278931],"type":"Point"}
}