{
  "type": "Feature",
  "properties": {
    "iso:country":"DE",
    "sg:address":"K\u00f6feringer Str. 2",
    "sg:city":"M\u00fcnchen",
    "sg:postcode":"81249",
    "sg:province":"Bayern",
    "wof:name":"Andrea Kolmeder",
    "wof:placetype":"venue"
},
  "geometry": {"coordinates":[11.426581,48.137199],"type":"Point"}
}