{
  "type": "Feature",
  "properties": {
    "iso:country":"DE",
    "sg:address":"B\u00e4ckerstr. 6",
    "sg:city":"Torgau",
    "sg:phone":"+49 3421/711375",
    "sg:postcode":"04860",
    "sg:province":"Sachsen",
    "wof:name":"Klaus Georgi",
    "wof:placetype":"venue"
},
  "geometry": {"coordinates":[13.003715,51.559048],"type":"Point"}
}