{
  "type": "Feature",
  "properties": {
    "iso:country":"DE",
    "sg:address":"Von-Siemens-Str. 1",
    "sg:city":"H\u00f6xter",
    "sg:phone":"+49 5271/32972",
    "sg:postcode":"37671",
    "sg:province":"Nordrhein-Westfalen",
    "wof:name":"Valentin Reno Tec Gmbh",
    "wof:placetype":"venue"
},
  "geometry": {"coordinates":[9.395433,51.779812],"type":"Point"}
}