{
  "type": "Feature",
  "properties": {
    "iso:country":"DE",
    "sg:address":"Wettiner Platz 1",
    "sg:city":"L\u00f6bau",
    "sg:phone":"+49 3585/482232",
    "sg:postcode":"02708",
    "sg:province":"Sachsen",
    "wof:name":"Siegfried Hartig",
    "wof:placetype":"venue"
},
  "geometry": {"coordinates":[14.669136,51.098045],"type":"Point"}
}