{
  "type": "Feature",
  "properties": {
    "iso:country":"DE",
    "sg:address":"Denzlinger Str. 13",
    "sg:city":"Emmendingen",
    "sg:phone":"+49 7641/8760",
    "sg:postcode":"79312",
    "sg:province":"Baden-W\u00fcrttemberg",
    "wof:name":"G\u00f6rner",
    "wof:placetype":"venue"
},
  "geometry": {"coordinates":[7.847814,48.114239],"type":"Point"}
}