{
  "type": "Feature",
  "properties": {
    "iso:country":"DE",
    "sg:address":"Kanzleiberg 7",
    "sg:city":"Gie\u00dfen",
    "sg:phone":"+49 641/389736",
    "sg:postcode":"35390",
    "sg:province":"Hessen",
    "wof:name":"Karl-h. Steinbach Steuerberater",
    "wof:placetype":"venue"
},
  "geometry": {"coordinates":[8.6761627197,50.5865325928],"type":"Point"}
}