{
  "type": "Feature",
  "properties": {
    "iso:country":"DE",
    "sg:address":"Brunnenstr. 47",
    "sg:city":"Osann-Monzel",
    "sg:phone":"+49 6535/7182",
    "sg:postcode":"54518",
    "sg:province":"Rheinland-Pfalz",
    "wof:name":"Eduard Schimper",
    "wof:placetype":"venue"
},
  "geometry": {"coordinates":[6.9500508308,49.9129371643],"type":"Point"}
}