{
  "type": "Feature",
  "properties": {
    "iso:country":"DE",
    "sg:address":"Boller Str. 132",
    "sg:city":"G\u00f6ppingen",
    "sg:phone":"+49 7161/40380",
    "sg:postcode":"73035",
    "sg:province":"Baden-W\u00fcrttemberg",
    "wof:name":"G\u00f6ppinger Mineralbrunnen Gmbh Zweigniederlassung",
    "wof:placetype":"venue"
},
  "geometry": {"coordinates":[9.6248598099,48.6802368164],"type":"Point"}
}