{
  "type": "Feature",
  "properties": {
    "iso:country":"DE",
    "sg:address":"Kapellenstr. 1",
    "sg:city":"Merchweiler",
    "sg:phone":"+49 6825/7602",
    "sg:postcode":"66589",
    "sg:province":"Saarland",
    "wof:name":"Couscous Tivoli",
    "wof:placetype":"venue"
},
  "geometry": {"coordinates":[7.0510649681,49.3605232239],"type":"Point"}
}