{
  "type": "Feature",
  "properties": {
    "iso:country":"DE",
    "sg:address":"Kiebitzweg 2",
    "sg:city":"Wasserburg",
    "sg:phone":"+49 8071/2832",
    "sg:postcode":"83512",
    "sg:province":"Bayern",
    "wof:name":"Modul Art Gmbh",
    "wof:placetype":"venue"
},
  "geometry": {"coordinates":[12.2331848145,48.0607948303],"type":"Point"}
}