{
  "type": "Feature",
  "properties": {
    "iso:country":"DE",
    "sg:address":"Am Alten Werk 58",
    "sg:city":"Melbeck",
    "sg:postcode":"21406",
    "sg:province":"Niedersachsen",
    "wof:name":"Frehse Transporte- Rainer Frehse",
    "wof:placetype":"venue"
},
  "geometry": {"coordinates":[10.3733673096,53.190826416],"type":"Point"}
}