{
  "type": "Feature",
  "properties": {
    "iso:country":"DE",
    "sg:address":"Ettlinger Str. 67",
    "sg:city":"Waldbronn",
    "sg:phone":"+49 7243/66064",
    "sg:postcode":"76337",
    "sg:province":"Baden-W\u00fcrttemberg",
    "wof:name":"Dialog Werbeagentur Wilfrid Schroeder",
    "wof:placetype":"venue"
},
  "geometry": {"coordinates":[8.464509964,48.9323120117],"type":"Point"}
}