{
  "type": "Feature",
  "properties": {
    "iso:country":"DE",
    "sg:address":"Sonnhalde 140a",
    "sg:city":"Freiburg",
    "sg:phone":"+49 761/582592",
    "sg:postcode":"79104",
    "sg:province":"Baden-W\u00fcrttemberg",
    "wof:name":"G. Und G. Huber",
    "wof:placetype":"venue"
},
  "geometry": {"coordinates":[7.8623800278,48.0203018188],"type":"Point"}
}