{
  "type": "Feature",
  "properties": {
    "iso:country":"DE",
    "sg:address":"Orffstr. 6",
    "sg:city":"M\u00fcnchen",
    "sg:phone":"+49 89/13039848",
    "sg:postcode":"80634",
    "sg:province":"Bayern",
    "wof:name":"Dr. Wieland Habenicht Patenanwalt",
    "wof:placetype":"venue"
},
  "geometry": {"coordinates":[11.5360202789,48.1563148499],"type":"Point"}
}