{
  "type": "Feature",
  "properties": {
    "iso:country":"DE",
    "sg:address":"Repelener Str. 2",
    "sg:city":"Moers",
    "sg:phone":"+49 2841/25223",
    "sg:postcode":"47441",
    "sg:province":"Nordrhein-Westfalen",
    "wof:name":"M\u00f6belhaus Friedrich Kleier Gmbh & Co. Kg",
    "wof:placetype":"venue"
},
  "geometry": {"coordinates":[6.6214699745,51.453250885],"type":"Point"}
}