{
  "type": "Feature",
  "properties": {
    "iso:country":"DE",
    "sg:address":"Bahnhofplatz 9",
    "sg:city":"Eichst\u00e4tt",
    "sg:phone":"+49 8421/1624",
    "sg:postcode":"85072",
    "sg:province":"Bayern",
    "wof:name":"Peter Spiegl",
    "wof:placetype":"venue"
},
  "geometry": {"coordinates":[11.1805677414,48.8923721313],"type":"Point"}
}