{
  "type": "Feature",
  "properties": {
    "iso:country":"DE",
    "sg:address":"Stadenhauser Str. 45",
    "sg:city":"Lage",
    "sg:phone":"+49 5232/3178419",
    "sg:postcode":"32791",
    "sg:province":"Nordrhein-Westfalen",
    "wof:name":"Gottfried Penning",
    "wof:placetype":"venue"
},
  "geometry": {"coordinates":[8.782765,51.986446],"type":"Point"}
}