{
  "type": "Feature",
  "properties": {
    "iso:country":"DE",
    "sg:address":"Tannenweg 3",
    "sg:city":"Barchfeld",
    "sg:phone":"+49 36961/44337",
    "sg:postcode":"36456",
    "sg:province":"Th\u00fcringen",
    "wof:name":"Werner Patz",
    "wof:placetype":"venue"
},
  "geometry": {"coordinates":[10.312935,50.800507],"type":"Point"}
}