{
  "type": "Feature",
  "properties": {
    "iso:country":"DE",
    "sg:address":"Am Galgenbuckel 10",
    "sg:city":"Sandhausen",
    "sg:phone":"+49 6224/2436",
    "sg:postcode":"69207",
    "sg:province":"Baden-W\u00fcrttemberg",
    "wof:name":"Dr. Annette Menne Tier\u00e4rztin",
    "wof:placetype":"venue"
},
  "geometry": {"coordinates":[8.6479606628,49.3447875977],"type":"Point"}
}