{
  "type": "Feature",
  "properties": {
    "iso:country":"DE",
    "sg:address":"Am H\u00f6llberg 3",
    "sg:city":"Lengenfeld",
    "sg:phone":"+49 37606/34438",
    "sg:postcode":"08485",
    "sg:province":"Sachsen",
    "wof:name":"Frieder Habermann",
    "wof:placetype":"venue"
},
  "geometry": {"coordinates":[12.417951,50.588402],"type":"Point"}
}