{
  "type": "Feature",
  "properties": {
    "iso:country":"DE",
    "sg:address":"Sonsbecker Str. 4",
    "sg:city":"Kevelaer",
    "sg:phone":"+49 2825/6570",
    "sg:postcode":"47626",
    "sg:province":"Nordrhein-Westfalen",
    "wof:name":"H. Tervooren Gmbh",
    "wof:placetype":"venue"
},
  "geometry": {"coordinates":[6.30712,51.597172],"type":"Point"}
}