{
  "type": "Feature",
  "properties": {
    "iso:country":"DE",
    "sg:address":"K\u00f6rnebachstr. 91",
    "sg:city":"Dortmund",
    "sg:phone":"+49 231/5655800",
    "sg:postcode":"44143",
    "sg:province":"Nordrhein-Westfalen",
    "wof:name":"Hartmann & Kroh Gmbh & Co. Kg",
    "wof:placetype":"venue"
},
  "geometry": {"coordinates":[7.489472,51.519665],"type":"Point"}
}