{
  "type": "Feature",
  "properties": {
    "iso:country":"DE",
    "sg:address":"Fuldaer Str. 8",
    "sg:city":"Dipperz",
    "sg:phone":"+49 6657/1864",
    "sg:postcode":"36160",
    "sg:province":"Hessen",
    "wof:name":"Carola Krebs",
    "wof:placetype":"venue"
},
  "geometry": {"coordinates":[9.793284,50.543213],"type":"Point"}
}