{
  "type": "Feature",
  "properties": {
    "iso:country":"DE",
    "sg:address":"Gewerbestr. 13",
    "sg:city":"Bad Orb",
    "sg:phone":"+49 6052/5195",
    "sg:postcode":"63619",
    "sg:province":"Hessen",
    "wof:name":"Anton Schnarr Kg",
    "wof:placetype":"venue"
},
  "geometry": {"coordinates":[9.341415,50.232719],"type":"Point"}
}