{
  "type": "Feature",
  "properties": {
    "iso:country":"DE",
    "sg:address":"Goslarer Str. 81",
    "sg:city":"Stuttgart",
    "sg:phone":"+49 711/886899",
    "sg:postcode":"70499",
    "sg:province":"Baden-W\u00fcrttemberg",
    "wof:name":"Rainer Czychi Masseur",
    "wof:placetype":"venue"
},
  "geometry": {"coordinates":[9.123209,48.816002],"type":"Point"}
}