{
  "type": "Feature",
  "properties": {
    "iso:country":"DE",
    "sg:address":"Herrenstr. 4",
    "sg:city":"Dillingen",
    "sg:phone":"+49 6831/71839",
    "sg:postcode":"66763",
    "sg:province":"Saarland",
    "wof:name":"Kosmetik Kr\u00fcger",
    "wof:placetype":"venue"
},
  "geometry": {"coordinates":[6.728026,49.354252],"type":"Point"}
}