{
  "type": "Feature",
  "properties": {
    "iso:country":"DE",
    "sg:address":"Lindenstr. 42 a",
    "sg:city":"Zembschen",
    "sg:postcode":"06679",
    "sg:province":"Sachsen-Anhalt",
    "wof:name":"Stahlbau Keutschen Gmbh",
    "wof:placetype":"venue"
},
  "geometry": {"coordinates":[12.090943,51.142345],"type":"Point"}
}