{
  "type": "Feature",
  "properties": {
    "iso:country":"DE",
    "sg:address":"M\u00fcnchewiese 4",
    "sg:city":"Hildesheim",
    "sg:phone":"+49 5121/75460",
    "sg:postcode":"31137",
    "sg:province":"Niedersachsen",
    "wof:name":"Bauunternehmung Paul Wiegand Gmbh & Co. Kg",
    "wof:placetype":"venue"
},
  "geometry": {"coordinates":[9.938382,52.162498],"type":"Point"}
}