{
  "type": "Feature",
  "properties": {
    "iso:country":"DE",
    "sg:address":"Auf dem Acker 10",
    "sg:city":"Kalenborn",
    "sg:phone":"+49 2643/900123",
    "sg:postcode":"53505",
    "sg:province":"Rheinland-Pfalz",
    "wof:name":"Ug-tronic Uwe Gorsch\u00fctz",
    "wof:placetype":"venue"
},
  "geometry": {"coordinates":[6.9958348274,50.5476417542],"type":"Point"}
}