{
  "type": "Feature",
  "properties": {
    "iso:country":"DE",
    "sg:address":"Donaustr. 51",
    "sg:city":"Mannheim",
    "sg:phone":"+49 621/851278",
    "sg:postcode":"68199",
    "sg:province":"Baden-W\u00fcrttemberg",
    "wof:name":"E. Welker",
    "wof:placetype":"venue"
},
  "geometry": {"coordinates":[8.507156,49.449368],"type":"Point"}
}