{
  "type": "Feature",
  "properties": {
    "iso:country":"DE",
    "sg:address":"Trift 98",
    "sg:city":"Krefeld",
    "sg:phone":"+49 2151/511284",
    "sg:postcode":"47809",
    "sg:province":"Nordrhein-Westfalen",
    "wof:name":"Trift-st\u00fcbchen",
    "wof:placetype":"venue"
},
  "geometry": {"coordinates":[6.5996999741,51.3289260864],"type":"Point"}
}