{
  "type": "Feature",
  "properties": {
    "iso:country":"DE",
    "sg:address":"Neuenahrer Str. 8",
    "sg:city":"Grafschaft",
    "sg:phone":"+49 4922/254002",
    "sg:postcode":"53501",
    "sg:province":"Rheinland-Pfalz",
    "wof:name":"Hero Sicherheits-service Gmbh",
    "wof:placetype":"venue"
},
  "geometry": {"coordinates":[7.0337109566,50.5826187134],"type":"Point"}
}