{
  "type": "Feature",
  "properties": {
    "iso:country":"DE",
    "sg:address":"Landstr. 14",
    "sg:city":"\u00dcberherrn",
    "sg:phone":"+49 6836/3387",
    "sg:postcode":"66802",
    "sg:province":"Saarland",
    "wof:name":"Verwaltungsgesellschaft Ehl Gmbh",
    "wof:placetype":"venue"
},
  "geometry": {"coordinates":[6.7133579254,49.2739028931],"type":"Point"}
}