{
  "type": "Feature",
  "properties": {
    "iso:country":"DE",
    "sg:address":"Virchowweg 11",
    "sg:city":"Wolfenb\u00fcttel",
    "sg:phone":"+49 5331/73354",
    "sg:postcode":"38302",
    "sg:province":"Niedersachsen",
    "wof:name":"Mondfisch Segelschiff Gmbh",
    "wof:placetype":"venue"
},
  "geometry": {"coordinates":[10.5496578217,52.1707000732],"type":"Point"}
}