{
  "type": "Feature",
  "properties": {
    "iso:country":"DE",
    "sg:address":"Lippestr. 9",
    "sg:city":"Castrop-Rauxel",
    "sg:phone":"+49 2305/973060",
    "sg:postcode":"44579",
    "sg:province":"Nordrhein-Westfalen",
    "wof:name":"Voigt & Schweitzer Beteiligungs Gmbh",
    "wof:placetype":"venue"
},
  "geometry": {"coordinates":[7.300376,51.591343],"type":"Point"}
}