{
  "type": "Feature",
  "properties": {
    "iso:country":"DE",
    "sg:address":"Bessemerstr. 42b",
    "sg:city":"Berlin",
    "sg:phone":"+49 30/754770",
    "sg:postcode":"12103",
    "sg:province":"Berlin",
    "wof:name":"Strabag Hoch-und Ingenieurbau Ag",
    "wof:placetype":"venue"
},
  "geometry": {"coordinates":[13.3667,52.464115],"type":"Point"}
}