{
  "type": "Feature",
  "properties": {
    "iso:country":"DE",
    "sg:address":"Hinter den G\u00e4rten 14",
    "sg:city":"Stuttgart",
    "sg:phone":"+49 711/4560366",
    "sg:postcode":"70599",
    "sg:province":"Baden-W\u00fcrttemberg",
    "wof:name":"Joachim Sautter Ingenieur",
    "wof:placetype":"venue"
},
  "geometry": {"coordinates":[9.2103481293,48.7195968628],"type":"Point"}
}