{
  "type": "Feature",
  "properties": {
    "iso:country":"DE",
    "sg:address":"Am Steintor 5",
    "sg:city":"M\u00fcnster",
    "sg:phone":"+49 2506/2550",
    "sg:postcode":"48167",
    "sg:province":"Nordrhein-Westfalen",
    "wof:name":"Westpreu\u00dfischen Landesmuseum",
    "wof:placetype":"venue"
},
  "geometry": {"coordinates":[7.728934,51.911545],"type":"Point"}
}