{
  "type": "Feature",
  "properties": {
    "iso:country":"DE",
    "sg:address":"Siemensstr.",
    "sg:city":"M\u00fcnster",
    "sg:phone":"+49 251/97870",
    "sg:postcode":"48153",
    "sg:province":"Nordrhein-Westfalen",
    "wof:name":"Hutchison Mobilfunk Gmbh",
    "wof:placetype":"venue"
},
  "geometry": {"coordinates":[7.6325731277,51.9290618896],"type":"Point"}
}