{
  "type": "Feature",
  "properties": {
    "iso:country":"DE",
    "sg:address":"Eisenbahnstr. 3",
    "sg:city":"Achern",
    "sg:phone":"+49 7841/28324",
    "sg:postcode":"77855",
    "sg:province":"Baden-W\u00fcrttemberg",
    "wof:name":"Hi-tec Shop",
    "wof:placetype":"venue"
},
  "geometry": {"coordinates":[8.06793,48.629501],"type":"Point"}
}