{
  "type": "Feature",
  "properties": {
    "iso:country":"DE",
    "sg:address":"Bollenh\u00f6he 5",
    "sg:city":"Mettmann",
    "sg:phone":"+49 2104/91890",
    "sg:postcode":"40822",
    "sg:province":"Nordrhein-Westfalen",
    "wof:name":"Toyocom Europe Gmbh",
    "wof:placetype":"venue"
},
  "geometry": {"coordinates":[7.004702,51.248837],"type":"Point"}
}