{
  "type": "Feature",
  "properties": {
    "iso:country":"DE",
    "sg:address":"Kuckucksbadstr. 15",
    "sg:city":"Bollschweil",
    "sg:phone":"+49 7633/5604",
    "sg:postcode":"79283",
    "sg:province":"Baden-W\u00fcrttemberg",
    "wof:name":"Walter Hermann",
    "wof:placetype":"venue"
},
  "geometry": {"coordinates":[7.77718,47.921822],"type":"Point"}
}