{
  "type": "Feature",
  "properties": {
    "iso:country":"DE",
    "sg:address":"Schenkendorfstr. 21",
    "sg:city":"Frankfurt",
    "sg:phone":"+49 69/524836",
    "sg:postcode":"60431",
    "sg:province":"Hessen",
    "wof:name":"C. K. K\u00f6lling Steuerberater",
    "wof:placetype":"venue"
},
  "geometry": {"coordinates":[8.6574764252,50.1502571106],"type":"Point"}
}