{
  "type": "Feature",
  "properties": {
    "iso:country":"DE",
    "sg:address":"Im Alten Ziel 21",
    "sg:city":"Lenzkirch",
    "sg:phone":"+49 7653/556",
    "sg:postcode":"79853",
    "sg:province":"Baden-W\u00fcrttemberg",
    "wof:name":"Detlev Fischer",
    "wof:placetype":"venue"
},
  "geometry": {"coordinates":[8.223233223,47.8755569458],"type":"Point"}
}