{
  "type": "Feature",
  "properties": {
    "iso:country":"DE",
    "sg:address":"Birkachstr. 13",
    "sg:city":"Albertshofen",
    "sg:phone":"+49 9321/32388",
    "sg:postcode":"97320",
    "sg:province":"Bayern",
    "wof:name":"Hans Ziegler",
    "wof:placetype":"venue"
},
  "geometry": {"coordinates":[10.1624698639,49.7683105469],"type":"Point"}
}