{
  "type": "Feature",
  "properties": {
    "iso:country":"DE",
    "sg:address":"Markt 14",
    "sg:city":"Wolkenstein",
    "sg:phone":"+49 37369/9567",
    "sg:postcode":"09429",
    "sg:province":"Sachsen",
    "wof:name":"Gundula Eger",
    "wof:placetype":"venue"
},
  "geometry": {"coordinates":[13.06645298,50.6558074951],"type":"Point"}
}