{
  "type": "Feature",
  "properties": {
    "iso:country":"DE",
    "sg:address":"Memeler Str. 19",
    "sg:city":"Haan",
    "sg:phone":"+49 212/98477",
    "sg:postcode":"42781",
    "sg:province":"Nordrhein-Westfalen",
    "wof:name":"Chemo-pharm Chemie Grundst. Vertriebsges. Mbh",
    "wof:placetype":"venue"
},
  "geometry": {"coordinates":[7.0143461227,51.201374054],"type":"Point"}
}