{
  "type": "Feature",
  "properties": {
    "iso:country":"DE",
    "sg:address":"Gernr\u00f6der Weg 6",
    "sg:city":"Quedlinburg",
    "sg:phone":"+49 3946/96530",
    "sg:postcode":"06484",
    "sg:province":"Sachsen-Anhalt",
    "wof:name":"August Prelle Baustoffges. Mbh & Co. Kg",
    "wof:placetype":"venue"
},
  "geometry": {"coordinates":[11.143125,51.782398],"type":"Point"}
}