{
  "type": "Feature",
  "properties": {
    "iso:country":"DE",
    "sg:address":"Maiersdorf 9",
    "sg:city":"Velden",
    "sg:phone":"+49 8742/8918",
    "sg:postcode":"84149",
    "sg:province":"Bayern",
    "wof:name":"Hofer",
    "wof:placetype":"venue"
},
  "geometry": {"coordinates":[12.2532587051,48.3659439087],"type":"Point"}
}