{
  "type": "Feature",
  "properties": {
    "iso:country":"DE",
    "sg:address":"Herrschaftsgartenstr. 42",
    "sg:city":"B\u00f6blingen",
    "sg:phone":"+49 7031/229208",
    "sg:postcode":"71032",
    "sg:province":"Baden-W\u00fcrttemberg",
    "wof:name":"Marga Maria Bausch",
    "wof:placetype":"venue"
},
  "geometry": {"coordinates":[9.0196113586,48.6844100952],"type":"Point"}
}