{
  "type": "Feature",
  "properties": {
    "iso:country":"DE",
    "sg:address":"Bachstr. 50",
    "sg:city":"Karlsruhe",
    "sg:phone":"+49 721/552866",
    "sg:postcode":"76185",
    "sg:province":"Baden-W\u00fcrttemberg",
    "wof:name":"Anne Rossney",
    "wof:placetype":"venue"
},
  "geometry": {"coordinates":[8.3641796112,49.0126419067],"type":"Point"}
}