{
  "type": "Feature",
  "properties": {
    "iso:country":"DE",
    "sg:address":"Sch\u00f6nleinstr. 11",
    "sg:city":"Berlin",
    "sg:phone":"+49 30/6945911",
    "sg:postcode":"10967",
    "sg:province":"Berlin",
    "wof:name":"Licht Blick",
    "wof:placetype":"venue"
},
  "geometry": {"coordinates":[13.4201316833,52.4910316467],"type":"Point"}
}