{
  "type": "Feature",
  "properties": {
    "iso:country":"DE",
    "sg:address":"Mommsenstr. 4",
    "sg:city":"Essen",
    "sg:phone":"+49 201/764533",
    "sg:postcode":"45144",
    "sg:province":"Nordrhein-Westfalen",
    "wof:name":"Kraftfahrzeuge Schmitt Gmbh",
    "wof:placetype":"venue"
},
  "geometry": {"coordinates":[6.9744420052,51.4499053955],"type":"Point"}
}