{
  "type": "Feature",
  "properties": {
    "iso:country":"DE",
    "sg:address":"Gutenbergstr. 3",
    "sg:city":"Hagen",
    "sg:phone":"+49 2331/333420",
    "sg:postcode":"58089",
    "sg:province":"Nordrhein-Westfalen",
    "wof:name":"Bauunternehmung Kr\u00e4geloh Gmbh & Co. Kg",
    "wof:placetype":"venue"
},
  "geometry": {"coordinates":[7.454956,51.352604],"type":"Point"}
}