{
  "type": "Feature",
  "properties": {
    "iso:country":"DE",
    "sg:address":"Petzinstr. 23a",
    "sg:city":"Geltow",
    "sg:phone":"+49 3327/56089",
    "sg:postcode":"14542",
    "sg:province":"Brandenburg",
    "wof:name":"Reinhard Fischer Architekt",
    "wof:placetype":"venue"
},
  "geometry": {"coordinates":[12.97921,52.359695],"type":"Point"}
}