{
  "type": "Feature",
  "properties": {
    "iso:country":"DE",
    "sg:address":"Augustenstr. 116",
    "sg:city":"Dessau",
    "sg:phone":"+49 340/8500554",
    "sg:postcode":"06842",
    "sg:province":"Sachsen-Anhalt",
    "wof:name":"Rondo Anhaltino",
    "wof:placetype":"venue"
},
  "geometry": {"coordinates":[12.2480211258,51.8148155212],"type":"Point"}
}