{
  "type": "Feature",
  "properties": {
    "iso:country":"DE",
    "sg:address":"Dorfstr. 28",
    "sg:city":"Rieseby",
    "sg:phone":"+49 4355/1033",
    "sg:postcode":"24354",
    "sg:province":"Schleswig-Holstein",
    "wof:name":"Wieben & Partner",
    "wof:placetype":"venue"
},
  "geometry": {"coordinates":[9.8152351379,54.5418395996],"type":"Point"}
}