{
  "type": "Feature",
  "properties": {
    "iso:country":"DE",
    "sg:address":"Schulweg 1",
    "sg:city":"St. Peter",
    "sg:phone":"+49 7660/236",
    "sg:postcode":"79271",
    "sg:province":"Baden-W\u00fcrttemberg",
    "wof:name":"H. Rohrer",
    "wof:placetype":"venue"
},
  "geometry": {"coordinates":[8.0339345932,48.0173377991],"type":"Point"}
}