{
  "type": "Feature",
  "properties": {
    "iso:country":"DE",
    "sg:address":"Ipfweg 11",
    "sg:city":"Leinfelden-Echterdingen",
    "sg:phone":"+49 711/7546182",
    "sg:postcode":"70771",
    "sg:province":"Baden-W\u00fcrttemberg",
    "wof:name":"Autopan Thomas St\u00e4bler Gmbh",
    "wof:placetype":"venue"
},
  "geometry": {"coordinates":[9.116981,48.703747],"type":"Point"}
}