{
  "type": "Feature",
  "properties": {
    "iso:country":"DE",
    "sg:address":"Heiligenbornstr. 2",
    "sg:city":"Dresden",
    "sg:phone":"+49 351/4706837",
    "sg:postcode":"01219",
    "sg:province":"Sachsen",
    "wof:name":"G\u00e4stehaus C. Ulbrich",
    "wof:placetype":"venue"
},
  "geometry": {"coordinates":[13.7649240494,51.0119972229],"type":"Point"}
}