{
  "type": "Feature",
  "properties": {
    "iso:country":"DE",
    "sg:address":"Elbestrasse 22-28",
    "sg:city":"Krefeld",
    "sg:phone":"+49 2151/477208",
    "sg:postcode":"47800",
    "sg:province":"Nordrhein-Westfalen",
    "wof:name":"Pankow",
    "wof:placetype":"venue"
},
  "geometry": {"coordinates":[6.615207,51.358189],"type":"Point"}
}