{
  "type": "Feature",
  "properties": {
    "iso:country":"DE",
    "sg:address":"F\u00fcrstenbergerhofstr. 21",
    "sg:city":"Mainz",
    "sg:phone":"+49 6131/230304",
    "sg:postcode":"55116",
    "sg:province":"Rheinland-Pfalz",
    "wof:name":"Rudolf Hunold Ingenieur",
    "wof:placetype":"venue"
},
  "geometry": {"coordinates":[8.2710647583,49.9949302673],"type":"Point"}
}