{
  "type": "Feature",
  "properties": {
    "iso:country":"DE",
    "sg:address":"Sehlendorf",
    "sg:city":"Blekendorf",
    "sg:phone":"+49 4382/758",
    "sg:postcode":"24327",
    "sg:province":"Schleswig-Holstein",
    "wof:name":"U. Lindemann Bildhauerei",
    "wof:placetype":"venue"
},
  "geometry": {"coordinates":[10.699416,54.292519],"type":"Point"}
}