{
  "type": "Feature",
  "properties": {
    "iso:country":"DE",
    "sg:address":"M\u00fcrwiker Str. 28",
    "sg:city":"Flensburg",
    "sg:phone":"+49 461/3194319",
    "sg:postcode":"24943",
    "sg:province":"Schleswig-Holstein",
    "wof:name":"Gambrinus",
    "wof:placetype":"venue"
},
  "geometry": {"coordinates":[9.4506130219,54.7960243225],"type":"Point"}
}