{
  "type": "Feature",
  "properties": {
    "iso:country":"DE",
    "sg:address":"Kulmbacher Str. 22",
    "sg:city":"Bayreuth",
    "sg:phone":"+49 921/63926",
    "sg:postcode":"95445",
    "sg:province":"Bayern",
    "wof:name":"Erich H\u00fcbner",
    "wof:placetype":"venue"
},
  "geometry": {"coordinates":[11.5681285858,49.9444541931],"type":"Point"}
}