{
  "type": "Feature",
  "properties": {
    "iso:country":"DE",
    "sg:address":"Grootestr. 97",
    "sg:city":"Bonn",
    "sg:phone":"+49 228/662037",
    "sg:postcode":"53121",
    "sg:province":"Nordrhein-Westfalen",
    "wof:name":"Heribert Kohl Steuerberater",
    "wof:placetype":"venue"
},
  "geometry": {"coordinates":[7.0451049805,50.7400054932],"type":"Point"}
}