{
  "type": "Feature",
  "properties": {
    "iso:country":"DE",
    "sg:address":"Schillerstr 16",
    "sg:city":"Hofheim",
    "sg:phone":"+49 6192/5876",
    "sg:postcode":"65719",
    "sg:province":"Hessen",
    "wof:name":"Eisw\u00fcrfel-service",
    "wof:placetype":"venue"
},
  "geometry": {"coordinates":[8.4193935394,49.6566429138],"type":"Point"}
}