{
  "type": "Feature",
  "properties": {
    "iso:country":"DE",
    "sg:address":"Flattichstr. 35",
    "sg:city":"Ludwigsburg",
    "sg:phone":"+49 7141/51067",
    "sg:postcode":"71642",
    "sg:province":"Baden-W\u00fcrttemberg",
    "wof:name":"Dietmar Ruhle",
    "wof:placetype":"venue"
},
  "geometry": {"coordinates":[9.1984100342,48.9101104736],"type":"Point"}
}