{
  "type": "Feature",
  "properties": {
    "iso:country":"DE",
    "sg:address":"Stuttgarter Stra\u00dfe 30",
    "sg:city":"Ditzingen",
    "sg:phone":"+49 7156/964600",
    "sg:postcode":"71254",
    "sg:province":"Baden-W\u00fcrttemberg",
    "wof:name":"Calimera Aktivhotel Monastir Tunesien",
    "wof:placetype":"venue"
},
  "geometry": {"coordinates":[9.067769,48.824318],"type":"Point"}
}