{
  "type": "Feature",
  "properties": {
    "iso:country":"DE",
    "sg:address":"Flughafenstr. 52a",
    "sg:city":"Hamburg",
    "sg:postcode":"22335",
    "sg:province":"Hamburg",
    "wof:name":"Kintana Gmbh",
    "wof:placetype":"venue"
},
  "geometry": {"coordinates":[10.015002,53.640041],"type":"Point"}
}