{
  "type": "Feature",
  "properties": {
    "iso:country":"DE",
    "sg:address":"Scheuerm\u00fchlenstr. 36",
    "sg:city":"K\u00f6ln",
    "sg:phone":"+49 2203/67229",
    "sg:postcode":"51147",
    "sg:province":"Nordrhein-Westfalen",
    "wof:name":"St. Lauer",
    "wof:placetype":"venue"
},
  "geometry": {"coordinates":[7.105654,50.857502],"type":"Point"}
}