{
  "type": "Feature",
  "properties": {
    "iso:country":"DE",
    "sg:address":"Graurheindorfer Str. 79",
    "sg:city":"Bonn",
    "sg:phone":"+49 228/697146",
    "sg:postcode":"53111",
    "sg:province":"Nordrhein-Westfalen",
    "wof:name":"Medienb\u00fcro Ulrich Dold",
    "wof:placetype":"venue"
},
  "geometry": {"coordinates":[7.0952019691,50.7453384399],"type":"Point"}
}