{
  "type": "Feature",
  "properties": {
    "iso:country":"DE",
    "sg:address":"Emil-Wolff-Str. 17",
    "sg:city":"Bad Berleburg",
    "sg:phone":"+49 2751/7081",
    "sg:postcode":"57319",
    "sg:province":"Nordrhein-Westfalen",
    "wof:name":"Aletter B\u00fcroorganisation Gmbh",
    "wof:placetype":"venue"
},
  "geometry": {"coordinates":[8.391707,51.046246],"type":"Point"}
}