{
  "type": "Feature",
  "properties": {
    "iso:country":"DE",
    "sg:address":"Raiffeisenstr. 24",
    "sg:city":"Felsberg",
    "sg:phone":"+49 5662/4422",
    "sg:postcode":"34587",
    "sg:province":"Hessen",
    "wof:name":"Waldemar Sinning",
    "wof:placetype":"venue"
},
  "geometry": {"coordinates":[9.46813,51.10368],"type":"Point"}
}