{
  "type": "Feature",
  "properties": {
    "iso:country":"DE",
    "sg:address":"Kleikstr. 77",
    "sg:city":"Herzogenrath",
    "sg:phone":"+49 2406/4536",
    "sg:postcode":"52134",
    "sg:province":"Nordrhein-Westfalen",
    "wof:name":"Johannes Ziefle",
    "wof:placetype":"venue"
},
  "geometry": {"coordinates":[6.091287,50.86694],"type":"Point"}
}