{
  "type": "Feature",
  "properties": {
    "iso:country":"DE",
    "sg:address":"Nibelungenstr. 20a",
    "sg:city":"Passau",
    "sg:phone":"+49 851/73973",
    "sg:postcode":"94032",
    "sg:province":"Bayern",
    "wof:name":"Poseidon-sub",
    "wof:placetype":"venue"
},
  "geometry": {"coordinates":[13.449474,48.572014],"type":"Point"}
}