{
  "type": "Feature",
  "properties": {
    "iso:country":"DE",
    "sg:address":"Gewerbepark 19",
    "sg:city":"L\u00fcbbenau",
    "sg:phone":"+49 3542/3293",
    "sg:postcode":"03222",
    "sg:province":"Brandenburg",
    "wof:name":"Heisa-heizung-sanit\u00e4r- Installation Und Service Gmbh",
    "wof:placetype":"venue"
},
  "geometry": {"coordinates":[13.950559,51.853249],"type":"Point"}
}