{
  "type": "Feature",
  "properties": {
    "iso:country":"DE",
    "sg:address":"Anne-Frank-Weg 9",
    "sg:city":"Hemmingen",
    "sg:phone":"+49 7150/5330",
    "sg:postcode":"71282",
    "sg:province":"Baden-W\u00fcrttemberg",
    "wof:name":"Reiner N\u00e4gele Architekt",
    "wof:placetype":"venue"
},
  "geometry": {"coordinates":[9.025116,48.868217],"type":"Point"}
}