{
  "type": "Feature",
  "properties": {
    "iso:country":"DE",
    "sg:address":"Hermannstr. 186",
    "sg:city":"Dortmund",
    "sg:phone":"+49 231/4271814",
    "sg:postcode":"44263",
    "sg:province":"Nordrhein-Westfalen",
    "wof:name":"Dsi Ind. Daten & Steuerungstechnik Gmbh",
    "wof:placetype":"venue"
},
  "geometry": {"coordinates":[7.518233,51.48505],"type":"Point"}
}