{
  "type": "Feature",
  "properties": {
    "iso:country":"DE",
    "sg:address":"Frankfurter Str. 72",
    "sg:city":"Dreieich",
    "sg:phone":"+49 6103/64065",
    "sg:postcode":"63303",
    "sg:province":"Hessen",
    "wof:name":"Franz Spindler Edv-beratung Gmbh",
    "wof:placetype":"venue"
},
  "geometry": {"coordinates":[8.6822290421,50.0021514893],"type":"Point"}
}