{
  "type": "Feature",
  "properties": {
    "iso:country":"DE",
    "sg:address":"Lustgarten 10",
    "sg:city":"Oldenburg",
    "sg:postcode":"26135",
    "sg:province":"Niedersachsen",
    "wof:name":"Ev.-luth. Kirchengemeinde Osternburg",
    "wof:placetype":"venue"
},
  "geometry": {"coordinates":[8.2231054306,53.1294364929],"type":"Point"}
}