{
  "type": "Feature",
  "properties": {
    "iso:country":"DE",
    "sg:address":"Am Langenhorster Bahnhof 22",
    "sg:city":"Ochtrup",
    "sg:phone":"+49 2553/93990",
    "sg:postcode":"48607",
    "sg:province":"Nordrhein-Westfalen",
    "wof:name":"Alfred Woltering Gmbh & Co Kg",
    "wof:placetype":"venue"
},
  "geometry": {"coordinates":[7.219119072,52.2058982849],"type":"Point"}
}