{
  "type": "Feature",
  "properties": {
    "iso:country":"DE",
    "sg:address":"In der Heide 20",
    "sg:city":"Harsewinkel",
    "sg:phone":"+49 2588/93000",
    "sg:postcode":"33428",
    "sg:province":"Nordrhein-Westfalen",
    "wof:name":"S & W Gmbh Fleischwarenfabrikation",
    "wof:placetype":"venue"
},
  "geometry": {"coordinates":[8.1695785522,51.9840354919],"type":"Point"}
}