{
  "type": "Feature",
  "properties": {
    "iso:country":"DE",
    "sg:address":"Niederkasseler Str 63",
    "sg:city":"D\u00fcsseldorf",
    "sg:phone":"+49 211/954400",
    "sg:postcode":"40547",
    "sg:province":"Nordrhein-Westfalen",
    "wof:name":"Huster Promotion Gmbh",
    "wof:placetype":"venue"
},
  "geometry": {"coordinates":[6.752869,51.238167],"type":"Point"}
}