{
  "type": "Feature",
  "properties": {
    "iso:country":"DE",
    "sg:address":"Weinsberger Str. 11",
    "sg:city":"Heilbronn",
    "sg:phone":"+49 7131/164739",
    "sg:postcode":"74072",
    "sg:province":"Baden-W\u00fcrttemberg",
    "wof:name":"Heinz Zimmermann",
    "wof:placetype":"venue"
},
  "geometry": {"coordinates":[9.222990036,49.1464042664],"type":"Point"}
}