{
  "type": "Feature",
  "properties": {
    "iso:country":"DE",
    "sg:address":"Glash\u00fctter Damm 210 a",
    "sg:city":"Norderstedt",
    "sg:phone":"+49 40/5293521",
    "sg:postcode":"22851",
    "sg:province":"Schleswig-Holstein",
    "wof:name":"Klaus Imhof",
    "wof:placetype":"venue"
},
  "geometry": {"coordinates":[10.0299329758,53.6936759949],"type":"Point"}
}