{
  "type": "Feature",
  "properties": {
    "iso:country":"DE",
    "sg:address":"Beutenbergstr. 6",
    "sg:city":"Chemnitz",
    "sg:phone":"+49 371/73634",
    "sg:postcode":"09128",
    "sg:province":"Sachsen",
    "wof:name":"Lackiererei Gross Gmbh",
    "wof:placetype":"venue"
},
  "geometry": {"coordinates":[13.010387,50.845901],"type":"Point"}
}