{
  "type": "Feature",
  "properties": {
    "iso:country":"DE",
    "sg:address":"Hartwaldstr. 72",
    "sg:city":"Stuttgart",
    "sg:phone":"+49 711/535684",
    "sg:postcode":"70378",
    "sg:province":"Baden-W\u00fcrttemberg",
    "wof:name":"Krone",
    "wof:placetype":"venue"
},
  "geometry": {"coordinates":[9.2256965637,48.8360862732],"type":"Point"}
}