{
  "type": "Feature",
  "properties": {
    "iso:country":"DE",
    "sg:address":"Engelbertstr. 25",
    "sg:city":"D\u00fcsseldorf",
    "sg:phone":"+49 211/7335190",
    "sg:postcode":"40233",
    "sg:province":"Nordrhein-Westfalen",
    "wof:name":"Edith Koop Bildhauerin",
    "wof:placetype":"venue"
},
  "geometry": {"coordinates":[6.809038,51.222454],"type":"Point"}
}