{
  "type": "Feature",
  "properties": {
    "iso:country":"DE",
    "sg:address":"Hardt 45",
    "sg:city":"Willich",
    "sg:phone":"+49 2159/2427",
    "sg:postcode":"47877",
    "sg:province":"Nordrhein-Westfalen",
    "wof:name":"Karl Bahners",
    "wof:placetype":"venue"
},
  "geometry": {"coordinates":[6.616043,51.249836],"type":"Point"}
}