{
  "type": "Feature",
  "properties": {
    "iso:country":"DE",
    "sg:address":"B\u00fcrgermeister-Rox-Platz 6",
    "sg:city":"Beverungen",
    "sg:phone":"+49 5273/88500",
    "sg:postcode":"37688",
    "sg:province":"Nordrhein-Westfalen",
    "wof:name":"F. Meijer",
    "wof:placetype":"venue"
},
  "geometry": {"coordinates":[9.409125,51.641819],"type":"Point"}
}