{
  "type": "Feature",
  "properties": {
    "iso:country":"DE",
    "sg:address":"Totenh\u00e4user Weg 30",
    "sg:city":"Allendorf",
    "sg:phone":"+49 6407/7953",
    "sg:postcode":"35469",
    "sg:province":"Hessen",
    "wof:name":"Gerold Alswede Rechtsanwalt Und Notar",
    "wof:placetype":"venue"
},
  "geometry": {"coordinates":[8.813249588,50.6781730652],"type":"Point"}
}