{
  "type": "Feature",
  "properties": {
    "iso:country":"DE",
    "sg:address":"E\u00dfbaum 6a",
    "sg:city":"Samerberg",
    "sg:phone":"+49 8032/8445",
    "sg:postcode":"83122",
    "sg:province":"Bayern",
    "wof:name":"Wimmer Baugesch\u00e4ft Gmbh",
    "wof:placetype":"venue"
},
  "geometry": {"coordinates":[12.197852,47.764671],"type":"Point"}
}