{
  "type": "Feature",
  "properties": {
    "iso:country":"DE",
    "sg:address":"Mainzer Landstr. 268",
    "sg:city":"Frankfurt",
    "sg:postcode":"60326",
    "sg:province":"Hessen",
    "wof:name":"Cdk Import-export Handels Gmbh",
    "wof:placetype":"venue"
},
  "geometry": {"coordinates":[8.640392,50.102829],"type":"Point"}
}