{
  "type": "Feature",
  "properties": {
    "iso:country":"DE",
    "sg:address":"Ilsestr. 38",
    "sg:city":"Berlin",
    "sg:phone":"+49 30/5086327",
    "sg:postcode":"10318",
    "sg:province":"Berlin",
    "wof:name":"Horst Krause Ingenieur",
    "wof:placetype":"venue"
},
  "geometry": {"coordinates":[13.5178956985,52.4898109436],"type":"Point"}
}