{
  "type": "Feature",
  "properties": {
    "iso:country":"DE",
    "sg:address":"Nordstr.",
    "sg:city":"Langendorf",
    "sg:phone":"+49 3443/84194",
    "sg:postcode":"06667",
    "sg:province":"Sachsen-Anhalt",
    "wof:name":"Lange & Sohn",
    "wof:placetype":"venue"
},
  "geometry": {"coordinates":[11.964753,51.186279],"type":"Point"}
}