{
  "type": "Feature",
  "properties": {
    "iso:country":"DE",
    "sg:address":"S\u00fcdring 19",
    "sg:city":"Aschaffenburg",
    "sg:phone":"+49 6021/22453",
    "sg:postcode":"63739",
    "sg:province":"Bayern",
    "wof:name":"Rainer F\u00f6rtig Gmbh & Co. Kg",
    "wof:placetype":"venue"
},
  "geometry": {"coordinates":[9.1548643112,49.9690322876],"type":"Point"}
}