{
  "type": "Feature",
  "properties": {
    "iso:country":"DE",
    "sg:address":"Rei\u00dfiger Gewerbering 51",
    "sg:city":"Plauen",
    "sg:phone":"+49 3741/55800",
    "sg:postcode":"08525",
    "sg:province":"Sachsen",
    "wof:name":"Dental-labor Handrich & Ebert Gmbh",
    "wof:placetype":"venue"
},
  "geometry": {"coordinates":[12.150097847,50.5253868103],"type":"Point"}
}