{
  "type": "Feature",
  "properties": {
    "iso:country":"DE",
    "sg:address":"Wickrather Str. 78",
    "sg:city":"M\u00f6nchengladbach",
    "sg:phone":"+49 2166/42332",
    "sg:postcode":"41236",
    "sg:province":"Nordrhein-Westfalen",
    "wof:name":"Hermann-josef Feser",
    "wof:placetype":"venue"
},
  "geometry": {"coordinates":[6.4396128654,51.1594543457],"type":"Point"}
}