{
  "type": "Feature",
  "properties": {
    "iso:country":"DE",
    "sg:address":"Schussenstr. 5",
    "sg:city":"Fronreute",
    "sg:phone":"+49 7502/2764",
    "sg:postcode":"88273",
    "sg:province":"Baden-W\u00fcrttemberg",
    "wof:name":"Otto L\u00e4mmle",
    "wof:placetype":"venue"
},
  "geometry": {"coordinates":[9.604747,47.85146],"type":"Point"}
}