{
  "type": "Feature",
  "properties": {
    "iso:country":"DE",
    "sg:address":"Brockmann-Meyerhof-Str. 46",
    "sg:city":"Schneverdingen",
    "sg:phone":"+49 5193/6996",
    "sg:postcode":"29640",
    "sg:province":"Niedersachsen",
    "wof:name":"Manfred Stelter",
    "wof:placetype":"venue"
},
  "geometry": {"coordinates":[9.812388,53.10696],"type":"Point"}
}