{
  "type": "Feature",
  "properties": {
    "iso:country":"DE",
    "sg:address":"H\u00fcttenweg 15",
    "sg:city":"Meinhard",
    "sg:phone":"+49 5651/5661",
    "sg:postcode":"37276",
    "sg:province":"Hessen",
    "wof:name":"E. Meier",
    "wof:placetype":"venue"
},
  "geometry": {"coordinates":[10.05089,51.220795],"type":"Point"}
}