{
  "type": "Feature",
  "properties": {
    "iso:country":"DE",
    "sg:address":"Saseler Chaussee 44",
    "sg:city":"Hamburg",
    "sg:phone":"+49 40/6400874",
    "sg:postcode":"22391",
    "sg:province":"Hamburg",
    "wof:name":"C A M\u00fcggenburg Makler",
    "wof:placetype":"venue"
},
  "geometry": {"coordinates":[10.0941371918,53.6378936768],"type":"Point"}
}