{
  "type": "Feature",
  "properties": {
    "iso:country":"DE",
    "sg:address":"Lauchaer Str. 31",
    "sg:city":"Langenhain",
    "sg:phone":"+49 3622/67135",
    "sg:postcode":"99880",
    "sg:province":"Th\u00fcringen",
    "wof:name":"Steffen Stiebling",
    "wof:placetype":"venue"
},
  "geometry": {"coordinates":[10.523708,50.904095],"type":"Point"}
}