{
  "type": "Feature",
  "properties": {
    "iso:country":"DE",
    "sg:address":"Hauptstr. 29",
    "sg:city":"Heltersberg",
    "sg:phone":"+49 6333/63072",
    "sg:postcode":"67716",
    "sg:province":"Rheinland-Pfalz",
    "wof:name":"Music Pub Merlin",
    "wof:placetype":"venue"
},
  "geometry": {"coordinates":[7.7124071121,49.3129882812],"type":"Point"}
}