{
  "type": "Feature",
  "properties": {
    "iso:country":"DE",
    "sg:address":"Kettelerstr. 4",
    "sg:city":"Bochum",
    "sg:phone":"+49 177 3162676",
    "sg:postcode":"44803",
    "sg:province":"Nordrhein-Westfalen",
    "wof:name":"Ruhr Universit\u00e4t Bochum",
    "wof:placetype":"venue"
},
  "geometry": {"coordinates":[7.2450990677,51.4691772461],"type":"Point"}
}