{
  "type": "Feature",
  "properties": {
    "iso:country":"DE",
    "sg:address":"Untere Au 41",
    "sg:city":"Sachsenheim",
    "sg:phone":"+49 7147/6091",
    "sg:postcode":"74343",
    "sg:province":"Baden-W\u00fcrttemberg",
    "wof:name":"Redaktion Cjd Mitteilungen Burg Verlag",
    "wof:placetype":"venue"
},
  "geometry": {"coordinates":[9.0159788132,48.9985694885],"type":"Point"}
}