{
  "type": "Feature",
  "properties": {
    "iso:country":"DE",
    "sg:address":"W\u00f6rthstr. 15",
    "sg:city":"M\u00fcnchen",
    "sg:phone":"+49 89/3617594",
    "sg:postcode":"81667",
    "sg:province":"Bayern",
    "wof:name":"Christian Lindner",
    "wof:placetype":"venue"
},
  "geometry": {"coordinates":[11.5993728638,48.1312217712],"type":"Point"}
}