{
  "type": "Feature",
  "properties": {
    "iso:country":"DE",
    "sg:address":"Grimms Weg 2",
    "sg:city":"B\u00fccken",
    "sg:postcode":"27333",
    "sg:province":"Niedersachsen",
    "wof:name":"La Gereta-cosmetique E. K.",
    "wof:placetype":"venue"
},
  "geometry": {"coordinates":[9.1203098297,52.7809143066],"type":"Point"}
}