{
  "type": "Feature",
  "properties": {
    "iso:country":"DE",
    "sg:address":"Ettmannsdorfer Str. 21",
    "sg:city":"Schwandorf",
    "sg:postcode":"92421",
    "sg:province":"Bayern",
    "wof:name":"Caritas Verband Schwandorf",
    "wof:placetype":"venue"
},
  "geometry": {"coordinates":[12.102619,49.329021],"type":"Point"}
}