{
  "type": "Feature",
  "properties": {
    "iso:country":"DE",
    "sg:address":"In der Heeb 6",
    "sg:city":"Gladenbach",
    "sg:postcode":"35075",
    "sg:province":"Hessen",
    "wof:name":"Immobilienverwaltungs- Gmbh",
    "wof:placetype":"venue"
},
  "geometry": {"coordinates":[8.5320386887,50.7740974426],"type":"Point"}
}