{
  "type": "Feature",
  "properties": {
    "iso:country":"DE",
    "sg:address":"Paracelsusstr. 41",
    "sg:city":"Worms",
    "sg:phone":"+49 6241/592253",
    "sg:postcode":"67550",
    "sg:province":"Rheinland-Pfalz",
    "wof:name":"Musik Wenninger Juri Wenninger",
    "wof:placetype":"venue"
},
  "geometry": {"coordinates":[8.3261499405,49.6504096985],"type":"Point"}
}