{
  "type": "Feature",
  "properties": {
    "iso:country":"DE",
    "sg:address":"R\u00f6merstr. 37",
    "sg:city":"Neumagen-Dhron",
    "sg:phone":"+49 6507/5235",
    "sg:postcode":"54347",
    "sg:province":"Rheinland-Pfalz",
    "wof:name":"Herbert Schneider",
    "wof:placetype":"venue"
},
  "geometry": {"coordinates":[6.8956031799,49.8549041748],"type":"Point"}
}