{
  "type": "Feature",
  "properties": {
    "iso:country":"DE",
    "sg:address":"Domerschulstr. 9",
    "sg:city":"W\u00fcrzburg",
    "sg:phone":"+49 931/53744",
    "sg:postcode":"97070",
    "sg:province":"Bayern",
    "wof:name":"Norma Lebensmittelfilial- Betrieb Gmbh & Co. Kg",
    "wof:placetype":"venue"
},
  "geometry": {"coordinates":[9.9323568344,49.7913703918],"type":"Point"}
}