{
  "type": "Feature",
  "properties": {
    "iso:country":"DE",
    "sg:address":"Harmoniestr. 26",
    "sg:city":"Eitorf",
    "sg:phone":"+49 2243/7806",
    "sg:postcode":"53783",
    "sg:province":"Nordrhein-Westfalen",
    "wof:name":"P. Und W. Hildebrandt",
    "wof:placetype":"venue"
},
  "geometry": {"coordinates":[7.4279131889,50.7763214111],"type":"Point"}
}