{
  "type": "Feature",
  "properties": {
    "iso:country":"DE",
    "sg:address":"Max-Planck-Str. 9-13",
    "sg:city":"Ditzingen",
    "sg:postcode":"71254",
    "sg:province":"Baden-W\u00fcrttemberg",
    "wof:name":"Wws Druckvorstufen- Und Medientechnik",
    "wof:placetype":"venue"
},
  "geometry": {"coordinates":[8.9946498871,48.8555183411],"type":"Point"}
}