{
  "type": "Feature",
  "properties": {
    "iso:country":"DE",
    "sg:address":"R\u00e4dereichen 8",
    "sg:city":"Radevormwald",
    "sg:phone":"+49 2195/8198",
    "sg:postcode":"42477",
    "sg:province":"Nordrhein-Westfalen",
    "wof:name":"Albrecht Pempeit",
    "wof:placetype":"venue"
},
  "geometry": {"coordinates":[7.3830060959,51.1983261108],"type":"Point"}
}