{
  "type": "Feature",
  "properties": {
    "iso:country":"DE",
    "sg:address":"Am Sportplatz 12",
    "sg:city":"Vienenburg",
    "sg:phone":"+49 5324/2274",
    "sg:postcode":"38690",
    "sg:province":"Niedersachsen",
    "wof:name":"Kbb Holzbau Und Innenausbau Lochtum Gmbh",
    "wof:placetype":"venue"
},
  "geometry": {"coordinates":[10.596669,51.928082],"type":"Point"}
}