{
  "type": "Feature",
  "properties": {
    "iso:country":"DE",
    "sg:address":"Ritterkaut 5",
    "sg:city":"Wetzlar",
    "sg:phone":"+49 6441/46139",
    "sg:postcode":"35583",
    "sg:province":"Hessen",
    "wof:name":"Kleintierzuchtverein Walter Koob",
    "wof:placetype":"venue"
},
  "geometry": {"coordinates":[8.532500267,50.5638885498],"type":"Point"}
}