{
  "type": "Feature",
  "properties": {
    "iso:country":"DE",
    "sg:address":"Talsperrenstr. 4-6",
    "sg:city":"Reichshof",
    "sg:phone":"+49 4922/968020",
    "sg:postcode":"51580",
    "sg:province":"Nordrhein-Westfalen",
    "wof:name":"Hans Berg Gmbh & Co Kg",
    "wof:placetype":"venue"
},
  "geometry": {"coordinates":[7.652291,50.931301],"type":"Point"}
}