{
  "type": "Feature",
  "properties": {
    "iso:country":"DE",
    "sg:address":"Meierhof 10",
    "sg:city":"Diemelsee",
    "sg:phone":"+49 5633/91120",
    "sg:postcode":"34519",
    "sg:province":"Hessen",
    "wof:name":"W. Hillebrand",
    "wof:placetype":"venue"
},
  "geometry": {"coordinates":[8.7717666626,51.3589820862],"type":"Point"}
}