{
  "type": "Feature",
  "properties": {
    "iso:country":"DE",
    "sg:address":"Sch\u00f6nebergstr. 15",
    "sg:city":"Aachen",
    "sg:phone":"+49 241/968880",
    "sg:postcode":"52068",
    "sg:province":"Nordrhein-Westfalen",
    "wof:name":"Ise Informatikgesellschaft F\u00fcr Software-entwicklung Mbh",
    "wof:placetype":"venue"
},
  "geometry": {"coordinates":[6.1376109123,50.7900276184],"type":"Point"}
}