{
  "type": "Feature",
  "properties": {
    "iso:country":"DE",
    "sg:address":"Candidplatz 15",
    "sg:city":"M\u00fcnchen",
    "sg:phone":"+49 89/6242930",
    "sg:postcode":"81543",
    "sg:province":"Bayern",
    "wof:name":"Solf Und Zapf Patentanw\u00e4lte",
    "wof:placetype":"venue"
},
  "geometry": {"coordinates":[11.5700063705,48.1114959717],"type":"Point"}
}