{
  "type": "Feature",
  "properties": {
    "iso:country":"DE",
    "sg:address":"Oberlemper Str. 38",
    "sg:city":"Ehringshausen",
    "sg:phone":"+49 6440/362",
    "sg:postcode":"35630",
    "sg:province":"Hessen",
    "wof:name":"Hans Stingl",
    "wof:placetype":"venue"
},
  "geometry": {"coordinates":[8.4216995239,50.6458854675],"type":"Point"}
}