{
  "type": "Feature",
  "properties": {
    "iso:country":"DE",
    "sg:address":"R\u00f6merstr. 96",
    "sg:city":"Heidelberg",
    "sg:phone":"+49 6221/21182",
    "sg:postcode":"69115",
    "sg:province":"Baden-W\u00fcrttemberg",
    "wof:name":"Huth Fu\u00dfb\u00f6den Inh. G. Bremer Und",
    "wof:placetype":"venue"
},
  "geometry": {"coordinates":[8.6851396561,49.3987388611],"type":"Point"}
}