{
  "type": "Feature",
  "properties": {
    "iso:country":"DE",
    "sg:address":"Tennisplatzweg 4",
    "sg:city":"Fluorn-Winzeln",
    "sg:phone":"+49 7402/92040",
    "sg:postcode":"78737",
    "sg:province":"Baden-W\u00fcrttemberg",
    "wof:name":"Staiger Hm-werkzeuge Gmbh",
    "wof:placetype":"venue"
},
  "geometry": {"coordinates":[8.493723,48.296925],"type":"Point"}
}