{
  "type": "Feature",
  "properties": {
    "iso:country":"DE",
    "sg:address":"Hauptstr. 18",
    "sg:city":"B\u00f6hmfeld",
    "sg:phone":"+49 8406/239",
    "sg:postcode":"85113",
    "sg:province":"Bayern",
    "wof:name":"Peter Herschke",
    "wof:placetype":"venue"
},
  "geometry": {"coordinates":[11.367299,48.860512],"type":"Point"}
}