{
  "type": "Feature",
  "properties": {
    "iso:country":"DE",
    "sg:address":"Schuhmarktplatz 4",
    "sg:city":"Oberndorf",
    "sg:phone":"+49 7423/2318",
    "sg:postcode":"78727",
    "sg:province":"Baden-W\u00fcrttemberg",
    "wof:name":"Kurt Bippus Installationen",
    "wof:placetype":"venue"
},
  "geometry": {"coordinates":[8.5699930191,48.2905578613],"type":"Point"}
}