{
  "type": "Feature",
  "properties": {
    "iso:country":"DE",
    "sg:address":"Werderplatz 40-44",
    "sg:city":"Karlsruhe",
    "sg:phone":"+49 721/74680",
    "sg:postcode":"76137",
    "sg:province":"Baden-W\u00fcrttemberg",
    "wof:name":"Hno-praxis Dr. Med. Goldschmidt // Herzlich Willko",
    "wof:placetype":"venue"
},
  "geometry": {"coordinates":[8.406916,49.00132],"type":"Point"}
}