{
  "type": "Feature",
  "properties": {
    "iso:country":"DE",
    "sg:address":"Steinbacher Str. 8",
    "sg:city":"Johannesberg",
    "sg:phone":"+49 6021/450574",
    "sg:postcode":"63867",
    "sg:province":"Bayern",
    "wof:name":"Dr. Hans-georg Florig Rechtsanwalt",
    "wof:placetype":"venue"
},
  "geometry": {"coordinates":[9.1177759171,50.0134887695],"type":"Point"}
}