{
  "type": "Feature",
  "properties": {
    "iso:country":"DE",
    "sg:address":"Hauptstr. 95",
    "sg:city":"Offenburg",
    "sg:phone":"+49 781/92620",
    "sg:postcode":"77652",
    "sg:province":"Baden-W\u00fcrttemberg",
    "wof:name":"Redaktion Badische Zeitung",
    "wof:placetype":"venue"
},
  "geometry": {"coordinates":[7.9427552223,48.4682273865],"type":"Point"}
}