{
  "type": "Feature",
  "properties": {
    "iso:country":"DE",
    "sg:address":"Schlo\u00dfstr. 27",
    "sg:city":"Ansbach",
    "sg:phone":"+49 981/87294",
    "sg:postcode":"91522",
    "sg:province":"Bayern",
    "wof:name":"Kaiserh\u00f6he",
    "wof:placetype":"venue"
},
  "geometry": {"coordinates":[10.5773477554,49.3054351807],"type":"Point"}
}