{
  "type": "Feature",
  "properties": {
    "iso:country":"DE",
    "sg:address":"Lankwitzweg 50",
    "sg:city":"Hannover",
    "sg:phone":"+49 511/6041076",
    "sg:postcode":"30179",
    "sg:province":"Niedersachsen",
    "wof:name":"Aspendos Grill-imbi\u00df",
    "wof:placetype":"venue"
},
  "geometry": {"coordinates":[9.7660446167,52.4191703796],"type":"Point"}
}