{
  "type": "Feature",
  "properties": {
    "iso:country":"DE",
    "sg:address":"Kernerstr. 19",
    "sg:city":"Weinsberg",
    "sg:phone":"+49 4971/345020",
    "sg:postcode":"74189",
    "sg:province":"Baden-W\u00fcrttemberg",
    "wof:name":"Kreissparkasse Heilbronn",
    "wof:placetype":"venue"
},
  "geometry": {"coordinates":[9.286687,49.149162],"type":"Point"}
}