{
  "type": "Feature",
  "properties": {
    "iso:country":"DE",
    "sg:address":"An der Markuskirche 5",
    "sg:city":"Hannover",
    "sg:phone":"+49 4905/113948",
    "sg:postcode":"30163",
    "sg:province":"Niedersachsen",
    "wof:name":"Classical Leader",
    "wof:placetype":"venue"
},
  "geometry": {"coordinates":[9.752649,52.388882],"type":"Point"}
}