{
  "type": "Feature",
  "properties": {
    "iso:country":"DE",
    "sg:address":"Fuchsbergstr. 15",
    "sg:city":"Eching",
    "sg:phone":"+49 8133/9147",
    "sg:postcode":"85386",
    "sg:province":"Bayern",
    "wof:name":"Manfred Wilhelm Handels- Vertretungen Gmbh",
    "wof:placetype":"venue"
},
  "geometry": {"coordinates":[11.6053104401,48.3225975037],"type":"Point"}
}