{
  "type": "Feature",
  "properties": {
    "iso:country":"DE",
    "sg:address":"Alter Postweg 14",
    "sg:city":"L\u00f6ningen",
    "sg:phone":"+49 5432/2945",
    "sg:postcode":"49624",
    "sg:province":"Niedersachsen",
    "wof:name":"Marta Spieker",
    "wof:placetype":"venue"
},
  "geometry": {"coordinates":[7.7606730461,52.7401275635],"type":"Point"}
}