{
  "type": "Feature",
  "properties": {
    "iso:country":"DE",
    "sg:address":"Burghauser Str. 11",
    "sg:city":"Marktl",
    "sg:phone":"+49 8678/98860",
    "sg:postcode":"84533",
    "sg:province":"Bayern",
    "wof:name":"Karl Beck Beteiligungs Gmbh",
    "wof:placetype":"venue"
},
  "geometry": {"coordinates":[12.843089,48.25243],"type":"Point"}
}