{
  "type": "Feature",
  "properties": {
    "iso:country":"DE",
    "sg:address":"Bahnhofstr. 34",
    "sg:city":"Gie\u00dfen",
    "sg:phone":"+49 641/72108",
    "sg:postcode":"35390",
    "sg:province":"Hessen",
    "wof:name":"Kino-center Kino 14",
    "wof:placetype":"venue"
},
  "geometry": {"coordinates":[8.670464,50.584641],"type":"Point"}
}