{
  "type": "Feature",
  "properties": {
    "iso:country":"DE",
    "sg:address":"Georgskommende 19",
    "sg:city":"M\u00fcnster",
    "sg:phone":"+49 251/495518",
    "sg:postcode":"48143",
    "sg:province":"Nordrhein-Westfalen",
    "wof:name":"Bistumsarchiv Des Bistums M\u00fcnster",
    "wof:placetype":"venue"
},
  "geometry": {"coordinates":[7.619467,51.960327],"type":"Point"}
}