{
  "type": "Feature",
  "properties": {
    "iso:country":"DE",
    "sg:address":"Hindenburgstr. 24",
    "sg:city":"Langenau",
    "sg:postcode":"89129",
    "sg:province":"Baden-W\u00fcrttemberg",
    "wof:name":"S. G\u00f6ttle",
    "wof:placetype":"venue"
},
  "geometry": {"coordinates":[10.119957,48.497551],"type":"Point"}
}