{
  "type": "Feature",
  "properties": {
    "iso:country":"DE",
    "sg:address":"Bahnhofstr. 104",
    "sg:city":"L\u00f6hne",
    "sg:phone":"+49 5732/2980",
    "sg:postcode":"32584",
    "sg:province":"Nordrhein-Westfalen",
    "wof:name":"Haus Der V\u00e4ter",
    "wof:placetype":"venue"
},
  "geometry": {"coordinates":[8.6989679337,52.2075195312],"type":"Point"}
}