{
  "type": "Feature",
  "properties": {
    "iso:country":"DE",
    "sg:address":"Am Tannenw\u00e4ldchen 2",
    "sg:city":"Kusel",
    "sg:phone":"+49 6381/47688",
    "sg:postcode":"66869",
    "sg:province":"Rheinland-Pfalz",
    "wof:name":"Brunhild Von Steinaecker",
    "wof:placetype":"venue"
},
  "geometry": {"coordinates":[7.3993349075,49.5431556702],"type":"Point"}
}