{
  "type": "Feature",
  "properties": {
    "iso:country":"DE",
    "sg:address":"Gro\u00dfenbucher Str. 2",
    "sg:city":"Neunkirchen",
    "sg:phone":"+49 9134/5403",
    "sg:postcode":"91077",
    "sg:province":"Bayern",
    "wof:name":"Horst Wagner Steuerberater",
    "wof:placetype":"venue"
},
  "geometry": {"coordinates":[11.1320886612,49.6129646301],"type":"Point"}
}