{
  "type": "Feature",
  "properties": {
    "iso:country":"DE",
    "sg:address":"H\u00f6llochstrasse 4-6",
    "sg:city":"Lenningen",
    "sg:phone":"+49 7026",
    "sg:postcode":"73252",
    "sg:province":"Baden-W\u00fcrttemberg",
    "wof:name":"Gs Electronic Lenningen",
    "wof:placetype":"venue"
},
  "geometry": {"coordinates":[9.4679403305,48.5564651489],"type":"Point"}
}