{
  "type": "Feature",
  "properties": {
    "iso:country":"DE",
    "sg:address":"Hessenstr. 10",
    "sg:city":"Merenberg",
    "sg:phone":"+49 6471/52431",
    "sg:postcode":"35799",
    "sg:province":"Hessen",
    "wof:name":"Klaus Unkelbach",
    "wof:placetype":"venue"
},
  "geometry": {"coordinates":[8.1869535446,50.5047302246],"type":"Point"}
}