{
  "type": "Feature",
  "properties": {
    "iso:country":"DE",
    "sg:address":"Am Brestenberg 2",
    "sg:city":"Schramberg",
    "sg:phone":"+49 7422/3134",
    "sg:postcode":"78713",
    "sg:province":"Baden-W\u00fcrttemberg",
    "wof:name":"Sozialstation",
    "wof:placetype":"venue"
},
  "geometry": {"coordinates":[8.384369,48.22673],"type":"Point"}
}