{
  "type": "Feature",
  "properties": {
    "iso:country":"DE",
    "sg:address":"Elisabethstr. 5",
    "sg:city":"Westerland",
    "sg:phone":"+49 4651/28448",
    "sg:postcode":"25980",
    "sg:province":"Schleswig-Holstein",
    "wof:name":"Traumfoto Sylt Inh. J\u00f6rg Br\u00fcggemann",
    "wof:placetype":"venue"
},
  "geometry": {"coordinates":[8.3013153076,54.908416748],"type":"Point"}
}