{
  "type": "Feature",
  "properties": {
    "iso:country":"DE",
    "sg:address":"Abteistr. 9",
    "sg:city":"Bendorf",
    "sg:phone":"+49 2622/10652",
    "sg:postcode":"56170",
    "sg:province":"Rheinland-Pfalz",
    "wof:name":"Planen Und Bauen Elke Feustel",
    "wof:placetype":"venue"
},
  "geometry": {"coordinates":[7.578009,50.438358],"type":"Point"}
}