{
  "type": "Feature",
  "properties": {
    "iso:country":"DE",
    "sg:address":"Schlehdornweg 9",
    "sg:city":"Odenthal",
    "sg:postcode":"51519",
    "sg:province":"Nordrhein-Westfalen",
    "wof:name":"Bau Und Boden Ges. F\u00fcr Baubetreuung, Ver-",
    "wof:placetype":"venue"
},
  "geometry": {"coordinates":[7.108268,51.052166],"type":"Point"}
}