{
  "type": "Feature",
  "properties": {
    "iso:country":"DE",
    "sg:address":"Gerokstr 22",
    "sg:city":"Illingen",
    "sg:phone":"+49 7042/82220",
    "sg:postcode":"75428",
    "sg:province":"Baden-W\u00fcrttemberg",
    "wof:name":"Pewetool Zerspanungswerkzeuge Gmbh",
    "wof:placetype":"venue"
},
  "geometry": {"coordinates":[8.931809,48.955826],"type":"Point"}
}