{
  "type": "Feature",
  "properties": {
    "iso:country":"DE",
    "sg:address":"J\u00e4gerstr. 28a",
    "sg:city":"R\u00f6srath",
    "sg:phone":"+49 2205/3769",
    "sg:postcode":"51503",
    "sg:province":"Nordrhein-Westfalen",
    "wof:name":"Pmv Produkt-management",
    "wof:placetype":"venue"
},
  "geometry": {"coordinates":[7.1679868698,50.9193878174],"type":"Point"}
}