{
  "type": "Feature",
  "properties": {
    "iso:country":"DE",
    "sg:address":"Kraftwerkstr. 13",
    "sg:city":"Zschornewitz",
    "sg:postcode":"06791",
    "sg:province":"Sachsen-Anhalt",
    "wof:name":"Abfallwirtschaftsgesellschaft Zschornewitz Mbh",
    "wof:placetype":"venue"
},
  "geometry": {"coordinates":[12.399451,51.716496],"type":"Point"}
}