{
  "type": "Feature",
  "properties": {
    "iso:country":"DE",
    "sg:address":"Dietrich-Bonhoeffer-Str. 27",
    "sg:city":"Frankenthal",
    "sg:phone":"+49 6233/40287",
    "sg:postcode":"67227",
    "sg:province":"Rheinland-Pfalz",
    "wof:name":"Haker Consulting Gmbh",
    "wof:placetype":"venue"
},
  "geometry": {"coordinates":[8.359251976,49.5069541931],"type":"Point"}
}