{
  "type": "Feature",
  "properties": {
    "iso:country":"DE",
    "sg:address":"Heinestr. 5-7",
    "sg:city":"Frankfurt",
    "sg:postcode":"60322",
    "sg:province":"Hessen",
    "wof:name":"Chaloupka Gmbh",
    "wof:placetype":"venue"
},
  "geometry": {"coordinates":[8.6771421432,50.1233062744],"type":"Point"}
}