{
  "type": "Feature",
  "properties": {
    "iso:country":"DE",
    "sg:address":"Boschetsrieder Str. 71",
    "sg:city":"M\u00fcnchen",
    "sg:phone":"+49 89/786003",
    "sg:postcode":"81379",
    "sg:province":"Bayern",
    "wof:name":"Bayerische Vereinsbank Ag",
    "wof:placetype":"venue"
},
  "geometry": {"coordinates":[11.5293,48.099632],"type":"Point"}
}