{
  "type": "Feature",
  "properties": {
    "iso:country":"DE",
    "sg:address":"Saarbr\u00fccker Str. 145",
    "sg:city":"Saarbr\u00fccken",
    "sg:phone":"+49 4968/977011",
    "sg:postcode":"66125",
    "sg:province":"Saarland",
    "wof:name":"Armbrust Getr\u00c4nke Gmbh",
    "wof:placetype":"venue"
},
  "geometry": {"coordinates":[7.0277938843,49.274055481],"type":"Point"}
}