{
  "type": "Feature",
  "properties": {
    "iso:country":"DE",
    "sg:address":"Grabensprung 174",
    "sg:city":"Berlin",
    "sg:phone":"+49 30/5146305",
    "sg:postcode":"12683",
    "sg:province":"Berlin",
    "wof:name":"Auto-schmidt Gmbh",
    "wof:placetype":"venue"
},
  "geometry": {"coordinates":[13.554926,52.495857],"type":"Point"}
}