{
  "type": "Feature",
  "properties": {
    "iso:country":"DE",
    "sg:address":"Heschredder 90",
    "sg:city":"Hamburg",
    "sg:phone":"+49 40/599552",
    "sg:postcode":"22335",
    "sg:province":"Hamburg",
    "wof:name":"Omnibus",
    "wof:placetype":"venue"
},
  "geometry": {"coordinates":[10.0166826248,53.6308174133],"type":"Point"}
}