{
  "type": "Feature",
  "properties": {
    "iso:country":"DE",
    "sg:address":"Hohetorwall 4",
    "sg:city":"Braunschweig",
    "sg:postcode":"38118",
    "sg:province":"Niedersachsen",
    "wof:name":"Intrust Gmbh",
    "wof:placetype":"venue"
},
  "geometry": {"coordinates":[10.5106592178,52.2628364563],"type":"Point"}
}