{
  "type": "Feature",
  "properties": {
    "iso:country":"DE",
    "sg:address":"Otto-Hahn-Str. 26",
    "sg:city":"D\u00fcsseldorf",
    "sg:phone":"+49 211/750843",
    "sg:postcode":"40591",
    "sg:province":"Nordrhein-Westfalen",
    "wof:name":"H. Obiegio",
    "wof:placetype":"venue"
},
  "geometry": {"coordinates":[6.8095259666,51.178691864],"type":"Point"}
}