{
  "type": "Feature",
  "properties": {
    "iso:country":"DE",
    "sg:address":"Steinsiek 5",
    "sg:city":"L\u00f6hne",
    "sg:phone":"+49 5732/3205",
    "sg:postcode":"32584",
    "sg:province":"Nordrhein-Westfalen",
    "wof:name":"Heinz Johannsmeier Elektroinstallation",
    "wof:placetype":"venue"
},
  "geometry": {"coordinates":[8.712112,52.191738],"type":"Point"}
}