{
  "type": "Feature",
  "properties": {
    "iso:country":"DE",
    "sg:address":"Grapengie\u00dferstr. 26",
    "sg:city":"L\u00fcneburg",
    "sg:phone":"+49 4131/46041",
    "sg:postcode":"21335",
    "sg:province":"Niedersachsen",
    "wof:name":"Gutschmidt-gossen Und Mertens Rechtsanw\u00e4lte Und Notare",
    "wof:placetype":"venue"
},
  "geometry": {"coordinates":[10.4045095444,53.2474212646],"type":"Point"}
}