{
  "type": "Feature",
  "properties": {
    "iso:country":"DE",
    "sg:address":"Hartmann-von-der-Aue-Str. 1",
    "sg:city":"Wolframs-Eschenbach",
    "sg:phone":"+49 9875/281",
    "sg:postcode":"91639",
    "sg:province":"Bayern",
    "wof:name":"Wilfried Barwig",
    "wof:placetype":"venue"
},
  "geometry": {"coordinates":[10.7254705429,49.2227478027],"type":"Point"}
}