{
  "type": "Feature",
  "properties": {
    "iso:country":"DE",
    "sg:address":"Greutterstr. 12",
    "sg:city":"Stuttgart",
    "sg:phone":"+49 711/832535",
    "sg:postcode":"70499",
    "sg:province":"Baden-W\u00fcrttemberg",
    "wof:name":"Herbert Meier",
    "wof:placetype":"venue"
},
  "geometry": {"coordinates":[9.1191911697,48.82213974],"type":"Point"}
}