{
  "type": "Feature",
  "properties": {
    "iso:country":"DE",
    "sg:address":"Gautinger Str. 53",
    "sg:city":"Krailling",
    "sg:phone":"+49 89/8994870",
    "sg:postcode":"82152",
    "sg:province":"Bayern",
    "wof:name":"Card Tronic Pro Net Gmbh",
    "wof:placetype":"venue"
},
  "geometry": {"coordinates":[11.41127,48.094051],"type":"Point"}
}