{
  "type": "Feature",
  "properties": {
    "iso:country":"DE",
    "sg:address":"Windhukstr. 21",
    "sg:city":"Hamburg",
    "sg:phone":"+49 40/8806894",
    "sg:postcode":"22763",
    "sg:province":"Hamburg",
    "wof:name":"Kl\u00e4jus Ingenieur",
    "wof:placetype":"venue"
},
  "geometry": {"coordinates":[9.9154787064,53.5557289124],"type":"Point"}
}