{
  "type": "Feature",
  "properties": {
    "iso:country":"DE",
    "sg:address":"Eickumer Str. 6",
    "sg:city":"Bielefeld",
    "sg:phone":"+49 5206/3704",
    "sg:postcode":"33739",
    "sg:province":"Nordrhein-Westfalen",
    "wof:name":"Dirk Wollnik Rechtsanwalt",
    "wof:placetype":"venue"
},
  "geometry": {"coordinates":[8.5424890518,52.0977478027],"type":"Point"}
}