{
  "type": "Feature",
  "properties": {
    "iso:country":"DE",
    "sg:address":"Friedrich-Engels-Str. 13",
    "sg:city":"Seehausen",
    "sg:phone":"+49 39407/5514",
    "sg:postcode":"39365",
    "sg:province":"Sachsen-Anhalt",
    "wof:name":"Fiedlers Blumenparadies",
    "wof:placetype":"venue"
},
  "geometry": {"coordinates":[11.29397,52.102097],"type":"Point"}
}