{
  "type": "Feature",
  "properties": {
    "iso:country":"DE",
    "sg:address":"Sandgasse 64",
    "sg:city":"Griesheim",
    "sg:phone":"+49 6155/2752",
    "sg:postcode":"64347",
    "sg:province":"Hessen",
    "wof:name":"Charlotte Merker",
    "wof:placetype":"venue"
},
  "geometry": {"coordinates":[8.5580654144,49.8645133972],"type":"Point"}
}