{
  "type": "Feature",
  "properties": {
    "iso:country":"DE",
    "sg:address":"Hauptstr. 15 a",
    "sg:city":"Schopp",
    "sg:phone":"+49 6307/92150",
    "sg:postcode":"67707",
    "sg:province":"Rheinland-Pfalz",
    "wof:name":"Nahlenz Immobilien- Verwaltung Gmbh",
    "wof:placetype":"venue"
},
  "geometry": {"coordinates":[7.6874132156,49.3517951965],"type":"Point"}
}