{
  "type": "Feature",
  "properties": {
    "iso:country":"DE",
    "sg:address":"Ostrowskistr. 19",
    "sg:city":"Magdeburg",
    "sg:phone":"+49 391/7221081",
    "sg:postcode":"39128",
    "sg:province":"Sachsen-Anhalt",
    "wof:name":"U. Machner",
    "wof:placetype":"venue"
},
  "geometry": {"coordinates":[11.5997676849,52.1460266113],"type":"Point"}
}