{
  "type": "Feature",
  "properties": {
    "iso:country":"DE",
    "sg:address":"Jacobstr. 12",
    "sg:city":"Sangerhausen",
    "sg:phone":"+49 3464/572803",
    "sg:postcode":"06526",
    "sg:province":"Sachsen-Anhalt",
    "wof:name":"Werner Dienemann",
    "wof:placetype":"venue"
},
  "geometry": {"coordinates":[11.2967748642,51.4742279053],"type":"Point"}
}