{
  "type": "Feature",
  "properties": {
    "iso:country":"DE",
    "sg:address":"Wilhelmstr. 70",
    "sg:city":"Lampertheim",
    "sg:phone":"+49 6206/3798",
    "sg:postcode":"68623",
    "sg:province":"Hessen",
    "wof:name":"Die Besondere K\u00fcche Konnerth E. K.",
    "wof:placetype":"venue"
},
  "geometry": {"coordinates":[8.465669632,49.5959777832],"type":"Point"}
}