{
  "type": "Feature",
  "properties": {
    "iso:country":"DE",
    "sg:address":"Ahornstr. 13",
    "sg:city":"Pentling",
    "sg:phone":"+49 941/92916",
    "sg:postcode":"93080",
    "sg:province":"Bayern",
    "wof:name":"G\u00fcnter Wei\u00df Steuerberater",
    "wof:placetype":"venue"
},
  "geometry": {"coordinates":[12.0555610657,48.9866027832],"type":"Point"}
}