{
  "type": "Feature",
  "properties": {
    "iso:country":"DE",
    "sg:address":"B\u00e4umlstr. 17",
    "sg:city":"M\u00fcnchen",
    "sg:postcode":"80638",
    "sg:province":"Bayern",
    "wof:name":"C. V. B. Eine Wohnidee Gmbh",
    "wof:placetype":"venue"
},
  "geometry": {"coordinates":[11.5060148239,48.1617164612],"type":"Point"}
}