{
  "type": "Feature",
  "properties": {
    "iso:country":"DE",
    "sg:address":"Am R\u00f6hrig 3",
    "sg:city":"Gro\u00dfostheim",
    "sg:postcode":"63762",
    "sg:province":"Bayern",
    "wof:name":"Arkkon Gmbh",
    "wof:placetype":"venue"
},
  "geometry": {"coordinates":[9.0483360291,49.8977928162],"type":"Point"}
}