{
  "type": "Feature",
  "properties": {
    "iso:country":"DE",
    "sg:address":"Unterer Schachenm\u00fchlenweg 22 b",
    "sg:city":"Ober-Ramstadt",
    "sg:phone":"+49 6154/1347",
    "sg:postcode":"64372",
    "sg:province":"Hessen",
    "wof:name":"H\u00e4mmer",
    "wof:placetype":"venue"
},
  "geometry": {"coordinates":[8.7173938751,49.8286361694],"type":"Point"}
}