{
  "type": "Feature",
  "properties": {
    "iso:country":"DE",
    "sg:address":"St. Georg",
    "sg:city":"Neubrandenburg",
    "sg:phone":"+49 395/2636",
    "sg:postcode":"17033",
    "sg:province":"Mecklenburg-Vorpommern",
    "wof:name":"Ulrich Kutzner",
    "wof:placetype":"venue"
},
  "geometry": {"coordinates":[13.2467451096,53.5578842163],"type":"Point"}
}