{
  "type": "Feature",
  "properties": {
    "iso:country":"DE",
    "sg:address":"Schinnaer Landstr. 63",
    "sg:city":"Stolzenau",
    "sg:phone":"+49 5765/7190",
    "sg:postcode":"31592",
    "sg:province":"Niedersachsen",
    "wof:name":"Br\u00fcggemann Spedition Und Logistik Verwaltungs Gmbh",
    "wof:placetype":"venue"
},
  "geometry": {"coordinates":[9.0756053925,52.5224113464],"type":"Point"}
}