{
  "type": "Feature",
  "properties": {
    "iso:country":"DE",
    "sg:address":"Zweibr\u00fccker Str. 3",
    "sg:city":"Neunkirchen",
    "sg:phone":"+49 6821/982840",
    "sg:postcode":"66538",
    "sg:province":"Saarland",
    "wof:name":"Klaus Kliebenstein Ingenieur",
    "wof:placetype":"venue"
},
  "geometry": {"coordinates":[7.1836948395,49.3374214172],"type":"Point"}
}