{
  "type": "Feature",
  "properties": {
    "iso:country":"DE",
    "sg:address":"Zeppelinstr. 4",
    "sg:city":"Erlangen",
    "sg:phone":"+49 9131/76200",
    "sg:postcode":"91052",
    "sg:province":"Bayern",
    "wof:name":"Encad Ingenieurges. Mbh F\u00fcr Den Anlagen- Und",
    "wof:placetype":"venue"
},
  "geometry": {"coordinates":[11.0120582581,49.5893135071],"type":"Point"}
}