{
  "type": "Feature",
  "properties": {
    "iso:country":"DE",
    "sg:address":"Schlo\u00dfweg 36",
    "sg:city":"Remseck",
    "sg:phone":"+49 7146/821748",
    "sg:postcode":"71686",
    "sg:province":"Baden-W\u00fcrttemberg",
    "wof:name":"Prof. A. Ade",
    "wof:placetype":"venue"
},
  "geometry": {"coordinates":[9.2717733383,48.8700447083],"type":"Point"}
}