{
  "type": "Feature",
  "properties": {
    "iso:country":"DE",
    "sg:address":"Truderinger Str. 275",
    "sg:city":"M\u00fcnchen",
    "sg:phone":"+49 89/425724",
    "sg:postcode":"81825",
    "sg:province":"Bayern",
    "wof:name":"Gerd Nast & S\u00f6hne Gmbh",
    "wof:placetype":"venue"
},
  "geometry": {"coordinates":[11.6674470901,48.1237297058],"type":"Point"}
}