{
  "type": "Feature",
  "properties": {
    "iso:country":"DE",
    "sg:address":"Wellenbergstr. 2",
    "sg:city":"Tauberbischofsheim",
    "sg:phone":"+49 9341/7526",
    "sg:postcode":"97941",
    "sg:province":"Baden-W\u00fcrttemberg",
    "wof:name":"Gottfried Fleck Bildhauer",
    "wof:placetype":"venue"
},
  "geometry": {"coordinates":[9.657428,49.623112],"type":"Point"}
}