{
  "type": "Feature",
  "properties": {
    "iso:country":"DE",
    "sg:address":"Hausener Str. 2",
    "sg:city":"Kirchardt",
    "sg:phone":"+49 7266/8997",
    "sg:postcode":"74912",
    "sg:province":"Baden-W\u00fcrttemberg",
    "wof:name":"Hubert Geiger",
    "wof:placetype":"venue"
},
  "geometry": {"coordinates":[8.981069,49.183704],"type":"Point"}
}