{
  "type": "Feature",
  "properties": {
    "iso:country":"DE",
    "sg:address":"Winkelstr. 6",
    "sg:city":"Hannover",
    "sg:phone":"+49 511/526960",
    "sg:postcode":"30559",
    "sg:province":"Niedersachsen",
    "wof:name":"B\u00e4rbel Orga\u00df",
    "wof:placetype":"venue"
},
  "geometry": {"coordinates":[9.8546581268,52.3593902588],"type":"Point"}
}