{
  "type": "Feature",
  "properties": {
    "iso:country":"DE",
    "sg:address":"Jugendherbergstr. 2",
    "sg:city":"Bad Sachsa",
    "sg:phone":"+49 5523/3544",
    "sg:postcode":"37441",
    "sg:province":"Niedersachsen",
    "wof:name":"Horst Renschin Rechtsanw\u00e4lte",
    "wof:placetype":"venue"
},
  "geometry": {"coordinates":[10.5572385788,51.5940742493],"type":"Point"}
}