{
  "type": "Feature",
  "properties": {
    "iso:country":"DE",
    "sg:address":"Waldhaus Fr\u00f6hne 22",
    "sg:city":"Hartha",
    "sg:phone":"+49 34328/39304",
    "sg:postcode":"04746",
    "sg:province":"Sachsen",
    "wof:name":"Nauhain Inh. Enrico Windler",
    "wof:placetype":"venue"
},
  "geometry": {"coordinates":[12.9693078995,51.1056938171],"type":"Point"}
}