{
  "type": "Feature",
  "properties": {
    "iso:country":"DE",
    "sg:address":"Weserstr. 6",
    "sg:city":"Petershagen",
    "sg:phone":"+49 5705/658",
    "sg:postcode":"32469",
    "sg:province":"Nordrhein-Westfalen",
    "wof:name":"Wilhelm David",
    "wof:placetype":"venue"
},
  "geometry": {"coordinates":[9.011016,52.41647],"type":"Point"}
}