{
  "type": "Feature",
  "properties": {
    "iso:country":"DE",
    "sg:address":"Sutnerstr. 2",
    "sg:city":"M\u00fcnchen",
    "sg:phone":"+49 89/640358",
    "sg:postcode":"81545",
    "sg:province":"Bayern",
    "wof:name":"Inter Fashion Holding",
    "wof:placetype":"venue"
},
  "geometry": {"coordinates":[11.543628,48.077831],"type":"Point"}
}