{
  "type": "Feature",
  "properties": {
    "iso:country":"DE",
    "sg:address":"Schlo\u00dfgasse 20",
    "sg:city":"Heilbronn",
    "sg:phone":"+49 7131/571328",
    "sg:postcode":"74081",
    "sg:province":"Baden-W\u00fcrttemberg",
    "wof:name":"J. Knauer",
    "wof:placetype":"venue"
},
  "geometry": {"coordinates":[9.1660041809,49.1158294678],"type":"Point"}
}