{
  "type": "Feature",
  "properties": {
    "iso:country":"DE",
    "sg:address":"Heidestr. 22",
    "sg:city":"Altenstadt",
    "sg:phone":"+49 6047/2483",
    "sg:postcode":"63674",
    "sg:province":"Hessen",
    "wof:name":"Bulka Gmbh",
    "wof:placetype":"venue"
},
  "geometry": {"coordinates":[8.9572000504,50.3047981262],"type":"Point"}
}