{
  "type": "Feature",
  "properties": {
    "iso:country":"DE",
    "sg:address":"Vorm Eichholz 2 Elberfeld",
    "sg:city":"Wuppertal",
    "sg:phone":"+49 4920/240400",
    "sg:postcode":"42119",
    "sg:province":"Nordrhein-Westfalen",
    "wof:name":"Keller Gmbh",
    "wof:placetype":"venue"
},
  "geometry": {"coordinates":[7.1589198112,51.2436103821],"type":"Point"}
}