{
  "type": "Feature",
  "properties": {
    "iso:country":"DE",
    "sg:address":"Emil-Rittershaus-Str. 7a",
    "sg:city":"Remscheid",
    "sg:phone":"+49 2191/71021",
    "sg:postcode":"42853",
    "sg:province":"Nordrhein-Westfalen",
    "wof:name":"Alwema Werkzeug- Und Maschinen Handelsgesellschaft Mbh",
    "wof:placetype":"venue"
},
  "geometry": {"coordinates":[7.175745,51.182709],"type":"Point"}
}