{
  "type": "Feature",
  "properties": {
    "iso:country":"DE",
    "sg:address":"Ringstr. 27",
    "sg:city":"M\u00fclheim-K\u00e4rlich",
    "sg:phone":"+49 2630/3703",
    "sg:postcode":"56218",
    "sg:province":"Rheinland-Pfalz",
    "wof:name":"Zerwas-aurass",
    "wof:placetype":"venue"
},
  "geometry": {"coordinates":[7.499649,50.388184],"type":"Point"}
}