{
  "type": "Feature",
  "properties": {
    "iso:country":"DE",
    "sg:address":"L\u00f6sm\u00fchle 2",
    "sg:city":"Roth",
    "sg:phone":"+49 9171/2370",
    "sg:postcode":"91154",
    "sg:province":"Bayern",
    "wof:name":"Keller & Beck Gmbh",
    "wof:placetype":"venue"
},
  "geometry": {"coordinates":[11.0905752182,49.2462043762],"type":"Point"}
}