{
  "type": "Feature",
  "properties": {
    "iso:country":"DE",
    "sg:address":"Bruchweg 22",
    "sg:city":"Eschershausen",
    "sg:phone":"+49 4955/3499030",
    "sg:postcode":"37632",
    "sg:province":"Niedersachsen",
    "wof:name":"Texcon Gmbh",
    "wof:placetype":"venue"
},
  "geometry": {"coordinates":[9.652076,51.927708],"type":"Point"}
}