{
  "type": "Feature",
  "properties": {
    "iso:country":"DE",
    "sg:address":"Ernst-Th\u00e4lmann-Str. 25",
    "sg:city":"B\u00f6hlen",
    "sg:phone":"+49 34206/51814",
    "sg:postcode":"04564",
    "sg:province":"Sachsen",
    "wof:name":"Andreas Zipfel",
    "wof:placetype":"venue"
},
  "geometry": {"coordinates":[12.3859119415,51.2106781006],"type":"Point"}
}