{
  "type": "Feature",
  "properties": {
    "iso:country":"DE",
    "sg:address":"Paulinenstr. 9",
    "sg:city":"Bad Soden",
    "sg:phone":"+49 6196/25555",
    "sg:postcode":"65812",
    "sg:province":"Hessen",
    "wof:name":"Dr. Clemens Broer Rechtsanwalt",
    "wof:placetype":"venue"
},
  "geometry": {"coordinates":[8.4976911545,50.1458129883],"type":"Point"}
}