{
  "type": "Feature",
  "properties": {
    "iso:country":"DE",
    "sg:address":"Neuer Kamp 1",
    "sg:city":"Nienhagen",
    "sg:phone":"+49 5144/2280",
    "sg:postcode":"29336",
    "sg:province":"Niedersachsen",
    "wof:name":"Dv Beratung Bruckhoff Gmbh",
    "wof:placetype":"venue"
},
  "geometry": {"coordinates":[10.083805,52.558182],"type":"Point"}
}