{
  "type": "Feature",
  "properties": {
    "iso:country":"DE",
    "sg:address":"Alte Stra\u00dfe 74-75",
    "sg:city":"Bremerv\u00f6rde",
    "sg:phone":"+49 4761/3185",
    "sg:postcode":"27432",
    "sg:province":"Niedersachsen",
    "wof:name":"Facktor",
    "wof:placetype":"venue"
},
  "geometry": {"coordinates":[9.143737793,53.4857559204],"type":"Point"}
}