{
  "type": "Feature",
  "properties": {
    "iso:country":"DE",
    "sg:address":"Maasstr. 22",
    "sg:city":"Goch",
    "sg:phone":"+49 2823/3021",
    "sg:postcode":"47574",
    "sg:province":"Nordrhein-Westfalen",
    "wof:name":"Karl Rosenbaum",
    "wof:placetype":"venue"
},
  "geometry": {"coordinates":[6.117895,51.702469],"type":"Point"}
}