{
  "type": "Feature",
  "properties": {
    "iso:country":"DE",
    "sg:address":"Br\u00fcckenstrasse 28",
    "sg:city":"Neuenkirchen",
    "sg:phone":"+49 5973",
    "sg:postcode":"48485",
    "sg:province":"Nordrhein-Westfalen",
    "wof:name":"Alph-for-web",
    "wof:placetype":"venue"
},
  "geometry": {"coordinates":[7.373117,52.248894],"type":"Point"}
}