{
  "type": "Feature",
  "properties": {
    "iso:country":"DE",
    "sg:address":"Friedrichstr. 8",
    "sg:city":"Fellbach",
    "sg:postcode":"70736",
    "sg:province":"Baden-W\u00fcrttemberg",
    "wof:name":"Omt Holding Gmbh",
    "wof:placetype":"venue"
},
  "geometry": {"coordinates":[9.260758,48.830517],"type":"Point"}
}