{
  "type": "Feature",
  "properties": {
    "iso:country":"DE",
    "sg:address":"Gasthauskanal 15",
    "sg:city":"Papenburg",
    "sg:phone":"+49 4961/5078",
    "sg:postcode":"26871",
    "sg:province":"Niedersachsen",
    "wof:name":"Johannesstift",
    "wof:placetype":"venue"
},
  "geometry": {"coordinates":[7.409369,53.075554],"type":"Point"}
}