{
  "type": "Feature",
  "properties": {
    "iso:country":"DE",
    "sg:address":"Moselstr. 33",
    "sg:city":"Niederfell",
    "sg:phone":"+49 2607/1068",
    "sg:postcode":"56332",
    "sg:province":"Rheinland-Pfalz",
    "wof:name":"Wwe. Peter Dany Gmbh",
    "wof:placetype":"venue"
},
  "geometry": {"coordinates":[7.4624261856,50.2911643982],"type":"Point"}
}