{
  "type": "Feature",
  "properties": {
    "iso:country":"DE",
    "sg:address":"Kreftenscheerstr. 101",
    "sg:city":"M\u00fclheim",
    "sg:phone":"+49 208/998211",
    "sg:postcode":"45472",
    "sg:province":"Nordrhein-Westfalen",
    "wof:name":"Areal Grund- Und Boden-",
    "wof:placetype":"venue"
},
  "geometry": {"coordinates":[6.921476841,51.4274215698],"type":"Point"}
}