{
  "type": "Feature",
  "properties": {
    "iso:country":"DE",
    "sg:address":"Mannheimer Str. 114",
    "sg:city":"Bad Kreuznach",
    "sg:phone":"+49 671/2111",
    "sg:postcode":"55543",
    "sg:province":"Rheinland-Pfalz",
    "wof:name":"Cafe Kiefer",
    "wof:placetype":"venue"
},
  "geometry": {"coordinates":[7.859165,49.843849],"type":"Point"}
}