{
  "type": "Feature",
  "properties": {
    "iso:country":"DE",
    "sg:address":"Lederecke 4",
    "sg:city":"Nentershausen",
    "sg:phone":"+49 6627/770",
    "sg:postcode":"36214",
    "sg:province":"Hessen",
    "wof:name":"D. Lehmann",
    "wof:placetype":"venue"
},
  "geometry": {"coordinates":[9.938025,51.012085],"type":"Point"}
}