{
  "type": "Feature",
  "properties": {
    "iso:country":"DE",
    "sg:address":"Wangener Str. 101-1",
    "sg:city":"Leutkirch",
    "sg:phone":"+49 7561/2515",
    "sg:postcode":"88299",
    "sg:province":"Baden-W\u00fcrttemberg",
    "wof:name":"Krieger- Und Kameradenverein E. V.",
    "wof:placetype":"venue"
},
  "geometry": {"coordinates":[10.0010881424,47.8208580017],"type":"Point"}
}