{
  "type": "Feature",
  "properties": {
    "iso:country":"DE",
    "sg:address":"Lehnstedter Str. 46",
    "sg:city":"Bremen",
    "sg:postcode":"28201",
    "sg:province":"Bremen",
    "wof:name":"H. Dreyer Beerdigungsinstitut Ndl. Der Norddeutschen",
    "wof:placetype":"venue"
},
  "geometry": {"coordinates":[8.797891,53.066036],"type":"Point"}
}