{
  "type": "Feature",
  "properties": {
    "iso:country":"DE",
    "sg:address":"Hausmannstr. 23",
    "sg:city":"Hanau",
    "sg:phone":"+49 6181/85764",
    "sg:postcode":"63452",
    "sg:province":"Hessen",
    "wof:name":"Helmut Sulzmann Architekt",
    "wof:placetype":"venue"
},
  "geometry": {"coordinates":[8.904058,50.14185],"type":"Point"}
}