{
  "type": "Feature",
  "properties": {
    "iso:country":"DE",
    "sg:address":"Thann",
    "sg:city":"Neunburg",
    "sg:postcode":"92431",
    "sg:province":"Bayern",
    "wof:name":"R. Blab",
    "wof:placetype":"venue"
},
  "geometry": {"coordinates":[12.471280098,49.3246154785],"type":"Point"}
}