{
  "type": "Feature",
  "properties": {
    "iso:country":"DE",
    "sg:address":"Kastanienallee 5",
    "sg:city":"Tostedt",
    "sg:phone":"+49 4182/70167",
    "sg:postcode":"21255",
    "sg:province":"Niedersachsen",
    "wof:name":"Schr\u00f6ders Foto Express",
    "wof:placetype":"venue"
},
  "geometry": {"coordinates":[9.7139835358,53.2821121216],"type":"Point"}
}