{
  "type": "Feature",
  "properties": {
    "iso:country":"DE",
    "sg:address":"Borschemicher Str. 6",
    "sg:city":"Erkelenz",
    "sg:phone":"+49 2164/949256",
    "sg:postcode":"41812",
    "sg:province":"Nordrhein-Westfalen",
    "wof:name":"Dirk Koster",
    "wof:placetype":"venue"
},
  "geometry": {"coordinates":[6.4139890671,51.0835533142],"type":"Point"}
}