{
  "type": "Feature",
  "properties": {
    "iso:country":"DE",
    "sg:address":"Hauptstr. 5",
    "sg:city":"Meerbeck",
    "sg:phone":"+49 5721/1220",
    "sg:postcode":"31715",
    "sg:province":"Niedersachsen",
    "wof:name":"Restaurant Alter Krug",
    "wof:placetype":"venue"
},
  "geometry": {"coordinates":[9.1514167786,52.3479270935],"type":"Point"}
}