{
  "type": "Feature",
  "properties": {
    "iso:country":"DE",
    "sg:address":"Hermann-B\u00f6se-Str. 15",
    "sg:city":"Bremen",
    "sg:phone":"+49 421/3469008",
    "sg:postcode":"28209",
    "sg:province":"Bremen",
    "wof:name":"L. Piasecka Immobilien",
    "wof:placetype":"venue"
},
  "geometry": {"coordinates":[8.8195800781,53.0837669373],"type":"Point"}
}