{
  "type": "Feature",
  "properties": {
    "iso:country":"DE",
    "sg:address":"Bruchwiesenstr. 5",
    "sg:city":"Ludwigshafen",
    "sg:phone":"+49 621/579050",
    "sg:postcode":"67059",
    "sg:province":"Rheinland-Pfalz",
    "wof:name":"Siemens Ag",
    "wof:placetype":"venue"
},
  "geometry": {"coordinates":[8.4179906845,49.4629058838],"type":"Point"}
}