{
  "type": "Feature",
  "properties": {
    "iso:country":"DE",
    "sg:address":"H\u00fcnger 33",
    "sg:city":"Wermelskirchen",
    "sg:phone":"+49 2196/2226",
    "sg:postcode":"42929",
    "sg:province":"Nordrhein-Westfalen",
    "wof:name":"Hsb Harald Schneider Bauelemente",
    "wof:placetype":"venue"
},
  "geometry": {"coordinates":[7.1869988441,51.1383361816],"type":"Point"}
}