{
  "type": "Feature",
  "properties": {
    "iso:country":"DE",
    "sg:address":"Rinklinger Str. 7",
    "sg:city":"Bretten",
    "sg:phone":"+49 7252/2991",
    "sg:postcode":"75015",
    "sg:province":"Baden-W\u00fcrttemberg",
    "wof:name":"Kraichgau Beton-gmbh & Co. Kg",
    "wof:placetype":"venue"
},
  "geometry": {"coordinates":[8.6941022873,49.0361099243],"type":"Point"}
}