{
  "type": "Feature",
  "properties": {
    "iso:country":"DE",
    "sg:address":"Marburger Str. 14",
    "sg:city":"Siegen",
    "sg:phone":"+49 271/55455",
    "sg:postcode":"57072",
    "sg:province":"Nordrhein-Westfalen",
    "wof:name":"Reimar Richter",
    "wof:placetype":"venue"
},
  "geometry": {"coordinates":[8.026836,50.875607],"type":"Point"}
}