{
  "type": "Feature",
  "properties": {
    "iso:country":"DE",
    "sg:address":"Karl-Wiechert-Allee 1D",
    "sg:city":"Hannover",
    "sg:phone":"+49 511/340150",
    "sg:postcode":"30625",
    "sg:province":"Niedersachsen",
    "wof:name":"Steinke Haas Und Partner Gbr",
    "wof:placetype":"venue"
},
  "geometry": {"coordinates":[9.8057079315,52.3716468811],"type":"Point"}
}