{
  "type": "Feature",
  "properties": {
    "iso:country":"DE",
    "sg:address":"Sexauerstr. 3",
    "sg:city":"M\u00fcnchen",
    "sg:phone":"+49 89/4307148",
    "sg:postcode":"81827",
    "sg:province":"Bayern",
    "wof:name":"Anja Von Morenhoffen Immobilienmaklerin",
    "wof:placetype":"venue"
},
  "geometry": {"coordinates":[11.6972360611,48.1165161133],"type":"Point"}
}