{
  "type": "Feature",
  "properties": {
    "iso:country":"DE",
    "sg:address":"Babostr. 13",
    "sg:city":"Abensberg",
    "sg:phone":"+49 9443/1260",
    "sg:postcode":"93326",
    "sg:province":"Bayern",
    "wof:name":"Franz Schwarz",
    "wof:placetype":"venue"
},
  "geometry": {"coordinates":[11.84489,48.814808],"type":"Point"}
}