{
  "type": "Feature",
  "properties": {
    "iso:country":"DE",
    "sg:address":"Hauptstr 107b",
    "sg:city":"Herzogenrath",
    "sg:phone":"+49 2406/80990",
    "sg:postcode":"52134",
    "sg:province":"Nordrhein-Westfalen",
    "wof:name":"Druckerei Erdtmann",
    "wof:placetype":"venue"
},
  "geometry": {"coordinates":[6.1060328484,50.8866577148],"type":"Point"}
}