{
  "type": "Feature",
  "properties": {
    "iso:country":"DE",
    "sg:address":"Poppelsdorfer All. 25-33",
    "sg:city":"Bonn",
    "sg:phone":"+49 4922/826801",
    "sg:postcode":"53115",
    "sg:province":"Nordrhein-Westfalen",
    "wof:name":"Deutscher Herold Allgemeine Versicherungs Ag",
    "wof:placetype":"venue"
},
  "geometry": {"coordinates":[7.099467,50.730305],"type":"Point"}
}