{
  "type": "Feature",
  "properties": {
    "iso:country":"DE",
    "sg:address":"Pforzheimer Str. 19",
    "sg:city":"Pfinztal",
    "sg:phone":"+49 7240/943400",
    "sg:postcode":"76327",
    "sg:province":"Baden-W\u00fcrttemberg",
    "wof:name":"Dusan Rajic",
    "wof:placetype":"venue"
},
  "geometry": {"coordinates":[8.5548810959,48.9649391174],"type":"Point"}
}