{
  "type": "Feature",
  "properties": {
    "iso:country":"DE",
    "sg:address":"Rolandstr. 6",
    "sg:city":"Celle",
    "sg:phone":"+49 5141/9670",
    "sg:postcode":"29223",
    "sg:province":"Niedersachsen",
    "wof:name":"Wohnpark Rolandstrasse",
    "wof:placetype":"venue"
},
  "geometry": {"coordinates":[10.037294,52.636711],"type":"Point"}
}