{
  "type": "Feature",
  "properties": {
    "iso:country":"DE",
    "sg:address":"Seugast 39",
    "sg:city":"Freihung",
    "sg:phone":"+49 9646/303",
    "sg:postcode":"92271",
    "sg:province":"Bayern",
    "wof:name":"E. Und M. Heuberger",
    "wof:placetype":"venue"
},
  "geometry": {"coordinates":[11.8933897018,49.6007537842],"type":"Point"}
}