{
  "type": "Feature",
  "properties": {
    "iso:country":"DE",
    "sg:address":"Austr. 62",
    "sg:city":"K\u00fcrnbach",
    "sg:phone":"+49 7258/7660",
    "sg:postcode":"75057",
    "sg:province":"Baden-W\u00fcrttemberg",
    "wof:name":"Waldsch\u00e4nke",
    "wof:placetype":"venue"
},
  "geometry": {"coordinates":[8.8621072769,49.0797729492],"type":"Point"}
}