{
  "type": "Feature",
  "properties": {
    "iso:country":"DE",
    "sg:address":"Boy Nielsen 15 Tinnum",
    "sg:city":"Tinnum",
    "sg:phone":"+49 4946/513431",
    "sg:postcode":"25980",
    "sg:province":"Schleswig-Holstein",
    "wof:name":"Pelz Matthiessen Gmbh",
    "wof:placetype":"venue"
},
  "geometry": {"coordinates":[8.373955,54.892746],"type":"Point"}
}