{
  "type": "Feature",
  "properties": {
    "iso:country":"DE",
    "sg:address":"Hauptstr. 10 a",
    "sg:city":"M\u00f6ckm\u00fchl",
    "sg:phone":"+49 6298/7008",
    "sg:postcode":"74219",
    "sg:province":"Baden-W\u00fcrttemberg",
    "wof:name":"Helmut Kraft Und Bruno Spohrer",
    "wof:placetype":"venue"
},
  "geometry": {"coordinates":[9.3616914749,49.3229217529],"type":"Point"}
}