{
  "type": "Feature",
  "properties": {
    "iso:country":"DE",
    "sg:address":"Breitenbachstr. 11-12",
    "sg:city":"Berlin",
    "sg:phone":"+49 30/4148944",
    "sg:postcode":"13509",
    "sg:province":"Berlin",
    "wof:name":"Dirk Niebuhr Wirtschaftspr\u00fcfer",
    "wof:placetype":"venue"
},
  "geometry": {"coordinates":[13.3103408813,52.5777587891],"type":"Point"}
}