{
  "type": "Feature",
  "properties": {
    "iso:country":"DE",
    "sg:address":"D\u00fcsseldorfer Str. 3",
    "sg:city":"Meerbusch",
    "sg:phone":"+49 2132/10375",
    "sg:postcode":"40667",
    "sg:province":"Nordrhein-Westfalen",
    "wof:name":"Ingrid Pezus",
    "wof:placetype":"venue"
},
  "geometry": {"coordinates":[6.689744,51.250751],"type":"Point"}
}