{
  "type": "Feature",
  "properties": {
    "iso:country":"DE",
    "sg:address":"Kapuzinerstr. 8",
    "sg:city":"Bingen",
    "sg:phone":"+49 6721/991448",
    "sg:postcode":"55411",
    "sg:province":"Rheinland-Pfalz",
    "wof:name":"Modissima Handels Gmbh",
    "wof:placetype":"venue"
},
  "geometry": {"coordinates":[7.8958940506,49.9676628113],"type":"Point"}
}