{
  "type": "Feature",
  "properties": {
    "iso:country":"DE",
    "sg:address":"Macherstr. 39",
    "sg:city":"Kamenz",
    "sg:phone":"+49 35783/78490",
    "sg:postcode":"01917",
    "sg:province":"Sachsen",
    "wof:name":"Fundus-cb Treuhand- Und Steuerberatungs Gmbh",
    "wof:placetype":"venue"
},
  "geometry": {"coordinates":[14.10460186,51.2805671692],"type":"Point"}
}