{
  "type": "Feature",
  "properties": {
    "iso:country":"DE",
    "sg:address":"Eichelsdorfer Str. 28",
    "sg:city":"Hofheim",
    "sg:phone":"+49 9523/95300",
    "sg:postcode":"97461",
    "sg:province":"Bayern",
    "wof:name":"Wagenh\u00e4user Erlebnisreisen E. K.",
    "wof:placetype":"venue"
},
  "geometry": {"coordinates":[10.5271472931,50.1437149048],"type":"Point"}
}