{
  "type": "Feature",
  "properties": {
    "iso:country":"DE",
    "sg:address":"B\u00fcltenweg 39- 43",
    "sg:city":"Braunschweig",
    "sg:phone":"+49 531/347887",
    "sg:postcode":"38106",
    "sg:province":"Niedersachsen",
    "wof:name":"Aral-tankstelle",
    "wof:placetype":"venue"
},
  "geometry": {"coordinates":[10.5365562439,52.2807159424],"type":"Point"}
}