{
  "type": "Feature",
  "properties": {
    "iso:country":"DE",
    "sg:address":"In der Reihe 19",
    "sg:city":"Gnarrenburg",
    "sg:phone":"+49 4794/857",
    "sg:postcode":"27442",
    "sg:province":"Niedersachsen",
    "wof:name":"Adolf Stelling",
    "wof:placetype":"venue"
},
  "geometry": {"coordinates":[8.987817,53.332664],"type":"Point"}
}