{
  "type": "Feature",
  "properties": {
    "iso:country":"DE",
    "sg:address":"Goerdelerstr. 11",
    "sg:city":"Solingen",
    "sg:postcode":"42651",
    "sg:province":"Nordrhein-Westfalen",
    "wof:name":"Steeger Und Greiner Rechtsanw\u00e4lte",
    "wof:placetype":"venue"
},
  "geometry": {"coordinates":[7.0860681534,51.1700439453],"type":"Point"}
}