{
  "type": "Feature",
  "properties": {
    "iso:country":"DE",
    "sg:address":"L\u00fcdinghauser Str. 3",
    "sg:city":"Ascheberg",
    "sg:phone":"+49 2593/406",
    "sg:postcode":"59387",
    "sg:province":"Nordrhein-Westfalen",
    "wof:name":"Das Landhaus",
    "wof:placetype":"venue"
},
  "geometry": {"coordinates":[7.622502,51.791836],"type":"Point"}
}