{
  "type": "Feature",
  "properties": {
    "iso:country":"DE",
    "sg:address":"Gluckstr. 7",
    "sg:city":"\u00dcberherrn",
    "sg:phone":"+49 6836/1200",
    "sg:postcode":"66802",
    "sg:province":"Saarland",
    "wof:name":"Ralf-konrad Chytrowski",
    "wof:placetype":"venue"
},
  "geometry": {"coordinates":[6.70381,49.239418],"type":"Point"}
}