{
  "type": "Feature",
  "properties": {
    "iso:country":"DE",
    "sg:address":"Friedrichstr. 7",
    "sg:city":"Kempten",
    "sg:phone":"+49 831/63498",
    "sg:postcode":"87437",
    "sg:province":"Bayern",
    "wof:name":"Carl Baier Gmbh",
    "wof:placetype":"venue"
},
  "geometry": {"coordinates":[10.327340126,47.713848114],"type":"Point"}
}