{
  "type": "Feature",
  "properties": {
    "iso:country":"DE",
    "sg:address":"Meller Str. 27",
    "sg:city":"Borgholzhausen",
    "sg:phone":"+49 5425/94890",
    "sg:postcode":"33829",
    "sg:province":"Nordrhein-Westfalen",
    "wof:name":"Hotel-restaurant Landhaus Uffmann",
    "wof:placetype":"venue"
},
  "geometry": {"coordinates":[8.3204221725,52.1237983704],"type":"Point"}
}