{
  "type": "Feature",
  "properties": {
    "iso:country":"DE",
    "sg:address":"Jebensstr. 3",
    "sg:city":"Berlin",
    "sg:phone":"+49 30/31001107",
    "sg:postcode":"10623",
    "sg:province":"Berlin",
    "wof:name":"Evangelisches Zentralarchiv In Berlin",
    "wof:placetype":"venue"
},
  "geometry": {"coordinates":[13.33187,52.507774],"type":"Point"}
}