{
  "type": "Feature",
  "properties": {
    "iso:country":"DE",
    "sg:address":"K\u00f6nigsbr\u00fccker Str. 58",
    "sg:city":"Dresden",
    "sg:phone":"+49 351/826390",
    "sg:postcode":"01099",
    "sg:province":"Sachsen",
    "wof:name":"Gebr. Forkel Gmbh",
    "wof:placetype":"venue"
},
  "geometry": {"coordinates":[13.7497034073,51.0700645447],"type":"Point"}
}