{
  "type": "Feature",
  "properties": {
    "iso:country":"DE",
    "sg:address":"Stra\u00dfe zum L\u00f6wen 10",
    "sg:city":"Berlin",
    "sg:phone":"+49 30/8054790",
    "sg:postcode":"14109",
    "sg:province":"Berlin",
    "wof:name":"Evelyn Damaschun",
    "wof:placetype":"venue"
},
  "geometry": {"coordinates":[13.159239769,52.4267158508],"type":"Point"}
}