{
  "type": "Feature",
  "properties": {
    "iso:country":"DE",
    "sg:address":"Weseler Str.",
    "sg:city":"Wesel",
    "sg:phone":"+49 281/3009797",
    "sg:postcode":"46487",
    "sg:province":"Nordrhein-Westfalen",
    "wof:name":"Spliethoff",
    "wof:placetype":"venue"
},
  "geometry": {"coordinates":[6.593745,51.638985],"type":"Point"}
}