{
  "type": "Feature",
  "properties": {
    "iso:country":"DE",
    "sg:address":"Lipperoder Str. 71",
    "sg:city":"Lippstadt",
    "sg:phone":"+49 2941/66980",
    "sg:postcode":"59555",
    "sg:province":"Nordrhein-Westfalen",
    "wof:name":"Autohaus Sternpark Verwaltungs Gmbh",
    "wof:placetype":"venue"
},
  "geometry": {"coordinates":[8.363865,51.684509],"type":"Point"}
}