{
  "type": "Feature",
  "properties": {
    "iso:country":"DE",
    "sg:address":"Hauptstr. 45",
    "sg:city":"Waldems",
    "sg:phone":"+49 6126/4792",
    "sg:postcode":"65529",
    "sg:province":"Hessen",
    "wof:name":"Heini Guckes",
    "wof:placetype":"venue"
},
  "geometry": {"coordinates":[8.313699,50.235752],"type":"Point"}
}