{
  "type": "Feature",
  "properties": {
    "iso:country":"DE",
    "sg:address":"Zehnthofstr. 8",
    "sg:city":"Leutesdorf",
    "sg:phone":"+49 2631/72989",
    "sg:postcode":"56599",
    "sg:province":"Rheinland-Pfalz",
    "wof:name":"H. Schneider",
    "wof:placetype":"venue"
},
  "geometry": {"coordinates":[7.3854050636,50.4505958557],"type":"Point"}
}