{
  "type": "Feature",
  "properties": {
    "iso:country":"DE",
    "sg:address":"Bahnhofstr 18",
    "sg:city":"Sch\u00f6nau",
    "sg:phone":"+49 6228/8160",
    "sg:postcode":"69250",
    "sg:province":"Baden-W\u00fcrttemberg",
    "wof:name":"Active Line Gmbh",
    "wof:placetype":"venue"
},
  "geometry": {"coordinates":[8.809089,49.428974],"type":"Point"}
}