{
  "type": "Feature",
  "properties": {
    "iso:country":"DE",
    "sg:address":"Eilenau 33",
    "sg:city":"Hamburg",
    "sg:phone":"+49 40/2501042",
    "sg:postcode":"22089",
    "sg:province":"Hamburg",
    "wof:name":"Baltic Assecuranz Finanzierungs- Und",
    "wof:placetype":"venue"
},
  "geometry": {"coordinates":[10.0332241058,53.5669631958],"type":"Point"}
}