{
  "type": "Feature",
  "properties": {
    "iso:country":"DE",
    "sg:address":"Hirschgartenallee 27",
    "sg:city":"M\u00fcnchen",
    "sg:phone":"+49 89/17809080",
    "sg:postcode":"80639",
    "sg:province":"Bayern",
    "wof:name":"Unterbichler Gbr",
    "wof:placetype":"venue"
},
  "geometry": {"coordinates":[11.5075006485,48.1532173157],"type":"Point"}
}