{
  "type": "Feature",
  "properties": {
    "iso:country":"DE",
    "sg:address":"Bahnhofstr. 6a",
    "sg:city":"Wolfenb\u00fcttel",
    "sg:phone":"+49 4953/3127855",
    "sg:postcode":"38304",
    "sg:province":"Niedersachsen",
    "wof:name":"Begerock Schl\u00dcssel- U. Schlo\u00dfservice",
    "wof:placetype":"venue"
},
  "geometry": {"coordinates":[10.5328102112,52.1583862305],"type":"Point"}
}