{
  "type": "Feature",
  "properties": {
    "iso:country":"DE",
    "sg:address":"Hauptstr. 5",
    "sg:city":"Freiburg",
    "sg:phone":"+49 761/2708270",
    "sg:postcode":"79104",
    "sg:province":"Baden-W\u00fcrttemberg",
    "wof:name":"Psychiatrische Universit\u00e4tsklinik",
    "wof:placetype":"venue"
},
  "geometry": {"coordinates":[7.856873,48.007504],"type":"Point"}
}