{
  "type": "Feature",
  "properties": {
    "iso:country":"DE",
    "sg:address":"In den Waagg\u00e4rten 32",
    "sg:city":"Worms",
    "sg:phone":"+49 6241/28468",
    "sg:postcode":"67547",
    "sg:province":"Rheinland-Pfalz",
    "wof:name":"K. Scheffel",
    "wof:placetype":"venue"
},
  "geometry": {"coordinates":[8.373933,49.621983],"type":"Point"}
}