{
  "type": "Feature",
  "properties": {
    "iso:country":"DE",
    "sg:address":"Lerchenbergh\u00f6fe",
    "sg:city":"Schwaigern",
    "sg:phone":"+49 7138/5228",
    "sg:postcode":"74193",
    "sg:province":"Baden-W\u00fcrttemberg",
    "wof:name":"H. Ebert",
    "wof:placetype":"venue"
},
  "geometry": {"coordinates":[9.064999,49.150532],"type":"Point"}
}