{
  "type": "Feature",
  "properties": {
    "iso:country":"DE",
    "sg:address":"Braunschweiger Str. 9",
    "sg:city":"Salzwedel",
    "sg:phone":"+49 3901/34716",
    "sg:postcode":"29410",
    "sg:province":"Sachsen-Anhalt",
    "wof:name":"Cafeteria Bbs",
    "wof:placetype":"venue"
},
  "geometry": {"coordinates":[11.152212,52.843113],"type":"Point"}
}