{
  "type": "Feature",
  "properties": {
    "iso:country":"DE",
    "sg:address":"M\u00f6hringer Str. 1012",
    "sg:city":"Tuttlingen",
    "sg:phone":"+49 7461/3330",
    "sg:postcode":"78532",
    "sg:province":"Baden-W\u00fcrttemberg",
    "wof:name":"Hermann Martin Inh. Volker Martin",
    "wof:placetype":"venue"
},
  "geometry": {"coordinates":[8.802967,47.980717],"type":"Point"}
}