{
  "type": "Feature",
  "properties": {
    "iso:country":"DE",
    "sg:address":"Heinrich-Dreyer-Str 7",
    "sg:city":"Hude",
    "sg:phone":"+49 5424/8020",
    "sg:postcode":"27798",
    "sg:province":"Niedersachsen",
    "wof:name":"B. Strautmann & S\u00f6hne Gmbh & Co",
    "wof:placetype":"venue"
},
  "geometry": {"coordinates":[8.1029882431,52.1014099121],"type":"Point"}
}