{
  "type": "Feature",
  "properties": {
    "iso:country":"DE",
    "sg:address":"Am Schwarzbach 2",
    "sg:city":"Riedstadt",
    "sg:phone":"+49 6158/1004",
    "sg:postcode":"64560",
    "sg:province":"Hessen",
    "wof:name":"Hellmich Kranservice Gmbh",
    "wof:placetype":"venue"
},
  "geometry": {"coordinates":[8.4810523987,49.8229522705],"type":"Point"}
}