{
  "type": "Feature",
  "properties": {
    "iso:country":"DE",
    "sg:address":"Wundtstr. 15",
    "sg:city":"M\u00fcnchen",
    "sg:phone":"+49 89/31190025",
    "sg:postcode":"80939",
    "sg:province":"Bayern",
    "wof:name":"Holzer & Schweikl Gmbh",
    "wof:placetype":"venue"
},
  "geometry": {"coordinates":[11.5863456726,48.1996955872],"type":"Point"}
}