{
  "type": "Feature",
  "properties": {
    "iso:country":"DE",
    "sg:address":"Stadtplatz 42",
    "sg:city":"M\u00fchldorf",
    "sg:phone":"+49 8631/2670",
    "sg:postcode":"84453",
    "sg:province":"Bayern",
    "wof:name":"Evi Maurer Masseurin",
    "wof:placetype":"venue"
},
  "geometry": {"coordinates":[12.523602,48.241516],"type":"Point"}
}