{
  "type": "Feature",
  "properties": {
    "iso:country":"DE",
    "sg:address":"Westkamp 29",
    "sg:city":"Dortmund",
    "sg:phone":"+49 231/200200",
    "sg:postcode":"44309",
    "sg:province":"Nordrhein-Westfalen",
    "wof:name":"Josef De Almeida",
    "wof:placetype":"venue"
},
  "geometry": {"coordinates":[7.535239,51.524616],"type":"Point"}
}