{
  "type": "Feature",
  "properties": {
    "iso:country":"DE",
    "sg:address":"Friedrich-Engels-Str. 12",
    "sg:city":"Hohenstein-Ernstthal",
    "sg:phone":"+49 3723/3130",
    "sg:postcode":"09337",
    "sg:province":"Sachsen",
    "wof:name":"Bistro F Rizz",
    "wof:placetype":"venue"
},
  "geometry": {"coordinates":[12.704744339,50.8019752502],"type":"Point"}
}