{
  "type": "Feature",
  "properties": {
    "iso:country":"DE",
    "sg:address":"Maximilianstr. 23",
    "sg:city":"Jockgrim",
    "sg:phone":"+49 7271/981602",
    "sg:postcode":"76751",
    "sg:province":"Rheinland-Pfalz",
    "wof:name":"Daniel Tankovic",
    "wof:placetype":"venue"
},
  "geometry": {"coordinates":[8.2813549042,49.0935821533],"type":"Point"}
}