{
  "type": "Feature",
  "properties": {
    "iso:country":"DE",
    "sg:address":"Katharinenfleet 5",
    "sg:city":"Hamburg",
    "sg:phone":"+49 40/37518866",
    "sg:postcode":"20457",
    "sg:province":"Hamburg",
    "wof:name":"Thomas Lorich U. Jens Rettig",
    "wof:placetype":"venue"
},
  "geometry": {"coordinates":[9.989938736,53.545425415],"type":"Point"}
}