{
  "type": "Feature",
  "properties": {
    "iso:country":"DE",
    "sg:address":"Friedenstr. 21",
    "sg:city":"Germering",
    "sg:phone":"+49 89/8412649",
    "sg:postcode":"82110",
    "sg:province":"Bayern",
    "wof:name":"Bingo Inh. Peter Clauss",
    "wof:placetype":"venue"
},
  "geometry": {"coordinates":[11.367184,48.122883],"type":"Point"}
}