{
  "type": "Feature",
  "properties": {
    "iso:country":"DE",
    "sg:address":"Berliner Str. 42",
    "sg:city":"Gro\u00dfalmerode",
    "sg:phone":"+49 5604/6893",
    "sg:postcode":"37247",
    "sg:province":"Hessen",
    "wof:name":"Guido Harms Praxis F\u00fcr Krankengymnastik",
    "wof:placetype":"venue"
},
  "geometry": {"coordinates":[9.789927,51.257545],"type":"Point"}
}