{
  "type": "Feature",
  "properties": {
    "iso:country":"DE",
    "sg:address":"Edelwei\u00dfstr. 8c",
    "sg:city":"Gr\u00f6benzell",
    "sg:phone":"+49 8142",
    "sg:postcode":"82194",
    "sg:province":"Bayern",
    "wof:name":"Beratung F\u00fcr It-projekte : Bl Unternehmensberatung",
    "wof:placetype":"venue"
},
  "geometry": {"coordinates":[11.362438,48.187241],"type":"Point"}
}