{
  "type": "Feature",
  "properties": {
    "iso:country":"DE",
    "sg:address":"Am Markt 10",
    "sg:city":"Warburg",
    "sg:phone":"+49 5641/8780",
    "sg:postcode":"34414",
    "sg:province":"Nordrhein-Westfalen",
    "wof:name":"Felix Moldenhauer",
    "wof:placetype":"venue"
},
  "geometry": {"coordinates":[9.1469402313,51.4853172302],"type":"Point"}
}