{
  "type": "Feature",
  "properties": {
    "iso:country":"DE",
    "sg:address":"Kottsiepen 11",
    "sg:city":"Wuppertal",
    "sg:postcode":"42369",
    "sg:province":"Nordrhein-Westfalen",
    "wof:name":"Kronenberg Verlag",
    "wof:placetype":"venue"
},
  "geometry": {"coordinates":[7.2104468346,51.2229957581],"type":"Point"}
}