{
  "type": "Feature",
  "properties": {
    "iso:country":"DE",
    "sg:address":"Mittelh\u00f6he 53",
    "sg:city":"Schw\u00e4bisch Hall",
    "sg:phone":"+49 791/3535",
    "sg:postcode":"74523",
    "sg:province":"Baden-W\u00fcrttemberg",
    "wof:name":"C. Unser Elektro-inst.",
    "wof:placetype":"venue"
},
  "geometry": {"coordinates":[9.76961,49.107864],"type":"Point"}
}