{
  "type": "Feature",
  "properties": {
    "iso:country":"DE",
    "sg:address":"Am Bahnhof 1",
    "sg:city":"Bad Soden",
    "sg:phone":"+49 6196/2090",
    "sg:postcode":"65812",
    "sg:province":"Hessen",
    "wof:name":"Hotel Concorde",
    "wof:placetype":"venue"
},
  "geometry": {"coordinates":[8.5030498505,50.1431388855],"type":"Point"}
}