{
  "type": "Feature",
  "properties": {
    "iso:country":"DE",
    "sg:address":"Herrenstr. 15",
    "sg:city":"Rastatt",
    "sg:phone":"+49 7222/3810",
    "sg:postcode":"76437",
    "sg:province":"Baden-W\u00fcrttemberg",
    "wof:name":"Landratsamt Rastatt",
    "wof:placetype":"venue"
},
  "geometry": {"coordinates":[8.2031326294,48.8590164185],"type":"Point"}
}