{
  "type": "Feature",
  "properties": {
    "iso:country":"DE",
    "sg:address":"G\u00f6rlitzer Str. 5",
    "sg:city":"Bernstadt",
    "sg:phone":"+49 35874/20579",
    "sg:postcode":"02748",
    "sg:province":"Sachsen",
    "wof:name":"Brigitte Fritsche",
    "wof:placetype":"venue"
},
  "geometry": {"coordinates":[14.8278446198,51.0473213196],"type":"Point"}
}