{
  "type": "Feature",
  "properties": {
    "iso:country":"DE",
    "sg:address":"Blasistr. 9",
    "sg:city":"Schopfheim",
    "sg:phone":"+49 7622/8930",
    "sg:postcode":"79650",
    "sg:province":"Baden-W\u00fcrttemberg",
    "wof:name":"Werner Bockstaller Architekt",
    "wof:placetype":"venue"
},
  "geometry": {"coordinates":[7.83489,47.657108],"type":"Point"}
}