{
  "type": "Feature",
  "properties": {
    "iso:country":"DE",
    "sg:address":"Moorenstr. 80",
    "sg:city":"D\u00fcsseldorf",
    "sg:postcode":"40225",
    "sg:province":"Nordrhein-Westfalen",
    "wof:name":"G\u00fctegemeinschaft Di\u00e4tverpflegung E.v.",
    "wof:placetype":"venue"
},
  "geometry": {"coordinates":[6.789289,51.199329],"type":"Point"}
}