{
  "type": "Feature",
  "properties": {
    "iso:country":"DE",
    "sg:address":"Wampelm\u00fchle",
    "sg:city":"Landshut",
    "sg:phone":"+49 871/63791",
    "sg:postcode":"84034",
    "sg:province":"Bayern",
    "wof:name":"Alfons Golling",
    "wof:placetype":"venue"
},
  "geometry": {"coordinates":[12.096364975,48.5331764221],"type":"Point"}
}