{
  "type": "Feature",
  "properties": {
    "iso:country":"DE",
    "sg:address":"Kirchstr. 31",
    "sg:city":"N\u00fcrtingen",
    "sg:phone":"+49 7022/36366",
    "sg:postcode":"72622",
    "sg:province":"Baden-W\u00fcrttemberg",
    "wof:name":"Vitalis",
    "wof:placetype":"venue"
},
  "geometry": {"coordinates":[9.3467235565,48.6255226135],"type":"Point"}
}