{
  "type": "Feature",
  "properties": {
    "iso:country":"DE",
    "sg:address":"Uthlandstr. 5",
    "sg:city":"Westerland",
    "sg:postcode":"25980",
    "sg:province":"Schleswig-Holstein",
    "wof:name":"Willi Esser Gmbh",
    "wof:placetype":"venue"
},
  "geometry": {"coordinates":[8.3076286316,54.9195594788],"type":"Point"}
}