{
  "type": "Feature",
  "properties": {
    "iso:country":"DE",
    "sg:address":"In der Ohe-Nord 5",
    "sg:city":"Hamburg",
    "sg:phone":"+49 40/7239536",
    "sg:postcode":"21037",
    "sg:province":"Hamburg",
    "wof:name":"Dipl.-ing Andreas Kramer",
    "wof:placetype":"venue"
},
  "geometry": {"coordinates":[10.2068243027,53.4185523987],"type":"Point"}
}