{
  "type": "Feature",
  "properties": {
    "iso:country":"DE",
    "sg:address":"Obere Bahnhofstr. 62",
    "sg:city":"Germering",
    "sg:phone":"+49 89/84058616",
    "sg:postcode":"82110",
    "sg:province":"Bayern",
    "wof:name":"Lhz Lernhilfe-zentrum Gmbh",
    "wof:placetype":"venue"
},
  "geometry": {"coordinates":[11.360329628,48.129699707],"type":"Point"}
}