{
  "type": "Feature",
  "properties": {
    "iso:country":"DE",
    "sg:address":"Zum Wendenkamp 18",
    "sg:city":"Hude",
    "sg:phone":"+49 4408/6888",
    "sg:postcode":"27798",
    "sg:province":"Niedersachsen",
    "wof:name":"Hans Haschen",
    "wof:placetype":"venue"
},
  "geometry": {"coordinates":[8.442654,53.068729],"type":"Point"}
}