{
  "type": "Feature",
  "properties": {
    "iso:country":"DE",
    "sg:address":"Nahmertal 53",
    "sg:city":"Hagen",
    "sg:postcode":"58119",
    "sg:province":"Nordrhein-Westfalen",
    "wof:name":"Polsterm\u00f6bel Wolfgang Stein Inh. Gottfried Pust E. K.",
    "wof:placetype":"venue"
},
  "geometry": {"coordinates":[7.5831928253,51.3048439026],"type":"Point"}
}