{
  "type": "Feature",
  "properties": {
    "iso:country":"DE",
    "sg:address":"Rehhecke 75",
    "sg:city":"Ratingen",
    "sg:phone":"+49 2102/37823",
    "sg:postcode":"40885",
    "sg:province":"Nordrhein-Westfalen",
    "wof:name":"Tengelmann Warenhandelsgesellschaft",
    "wof:placetype":"venue"
},
  "geometry": {"coordinates":[6.8369550705,51.3420028687],"type":"Point"}
}