{
  "type": "Feature",
  "properties": {
    "iso:country":"DE",
    "sg:address":"Hauptstr. 355",
    "sg:city":"K\u00f6nigswinter",
    "sg:phone":"+49 2223/92200",
    "sg:postcode":"53639",
    "sg:province":"Nordrhein-Westfalen",
    "wof:name":"Krahe",
    "wof:placetype":"venue"
},
  "geometry": {"coordinates":[7.191865921,50.6765708923],"type":"Point"}
}