{
  "type": "Feature",
  "properties": {
    "iso:country":"DE",
    "sg:address":"Sch\u00fctzenstr.",
    "sg:city":"Pressig",
    "sg:phone":"+49 9265/8240",
    "sg:postcode":"96332",
    "sg:province":"Bayern",
    "wof:name":"M\u00f6belpassage Gmbh",
    "wof:placetype":"venue"
},
  "geometry": {"coordinates":[11.3199300766,50.3638954163],"type":"Point"}
}