{
  "type": "Feature",
  "properties": {
    "iso:country":"DE",
    "sg:address":"Allg\u00e4uer Str. 1",
    "sg:city":"Kempten",
    "sg:phone":"+49 831/252870",
    "sg:postcode":"87435",
    "sg:province":"Bayern",
    "wof:name":"Sozialbau Kempten Wohnungs- Und St\u00e4dtebau Gmbh",
    "wof:placetype":"venue"
},
  "geometry": {"coordinates":[10.3139047623,47.7208366394],"type":"Point"}
}