{
  "type": "Feature",
  "properties": {
    "iso:country":"DE",
    "sg:address":"Hauptstr. 17",
    "sg:city":"Egenhausen",
    "sg:phone":"+49 7453/6390",
    "sg:postcode":"72227",
    "sg:province":"Baden-W\u00fcrttemberg",
    "wof:name":"Christian Beilharz Inh. Wolfgang Stickel",
    "wof:placetype":"venue"
},
  "geometry": {"coordinates":[8.6185817719,48.5653152466],"type":"Point"}
}