{
  "type": "Feature",
  "properties": {
    "iso:country":"DE",
    "sg:address":"Auf der Hard",
    "sg:city":"Tawern",
    "sg:phone":"+49 6501/17731",
    "sg:postcode":"54456",
    "sg:province":"Rheinland-Pfalz",
    "wof:name":"S. Bock",
    "wof:placetype":"venue"
},
  "geometry": {"coordinates":[6.5274600983,49.66456604],"type":"Point"}
}