{
  "type": "Feature",
  "properties": {
    "iso:country":"DE",
    "sg:address":"Am Grubebach 1",
    "sg:city":"Delbr\u00fcck",
    "sg:phone":"+49 5250/5140",
    "sg:postcode":"33129",
    "sg:province":"Nordrhein-Westfalen",
    "wof:name":"Conditorei Willy Antp\u00f6hler Tiefk\u00fchl-backwaren Gmbh",
    "wof:placetype":"venue"
},
  "geometry": {"coordinates":[8.466849,51.766083],"type":"Point"}
}