{
  "type": "Feature",
  "properties": {
    "iso:country":"DE",
    "sg:address":"Holperdorper Str. 47",
    "sg:city":"Lienen",
    "sg:phone":"+49 5483/8084",
    "sg:postcode":"49536",
    "sg:province":"Nordrhein-Westfalen",
    "wof:name":"Schencking Kalk- Und Sandsteinwerke",
    "wof:placetype":"venue"
},
  "geometry": {"coordinates":[7.970416069,52.1611213684],"type":"Point"}
}