{
  "type": "Feature",
  "properties": {
    "iso:country":"DE",
    "sg:address":"Delitzscher Str. 34",
    "sg:city":"Leipzig",
    "sg:postcode":"04129",
    "sg:province":"Sachsen",
    "wof:name":"K. Paul Winkner",
    "wof:placetype":"venue"
},
  "geometry": {"coordinates":[12.381853,51.362061],"type":"Point"}
}