{
  "type": "Feature",
  "properties": {
    "iso:country":"DE",
    "sg:address":"Ludwigstr. 33",
    "sg:city":"Wunsiedel",
    "sg:phone":"+49 9232/2117",
    "sg:postcode":"95632",
    "sg:province":"Bayern",
    "wof:name":"Buchhandlung B\u00f6hringer Gmbh",
    "wof:placetype":"venue"
},
  "geometry": {"coordinates":[12.002715,50.036831],"type":"Point"}
}