{
  "type": "Feature",
  "properties": {
    "iso:country":"DE",
    "sg:address":"Rosenstr. 8",
    "sg:city":"L\u00f6bau",
    "sg:phone":"+49 3585/404455",
    "sg:postcode":"02708",
    "sg:province":"Sachsen",
    "wof:name":"Werner Schmidt",
    "wof:placetype":"venue"
},
  "geometry": {"coordinates":[14.6670761108,51.0896492004],"type":"Point"}
}