{
  "type": "Feature",
  "properties": {
    "iso:country":"DE",
    "sg:address":"Hauptstr. 4",
    "sg:city":"Nachtsheim",
    "sg:phone":"+49 2656/443",
    "sg:postcode":"56729",
    "sg:province":"Rheinland-Pfalz",
    "wof:name":"Werner Hoffmann",
    "wof:placetype":"venue"
},
  "geometry": {"coordinates":[7.060665,50.320892],"type":"Point"}
}