{
  "type": "Feature",
  "properties": {
    "iso:country":"DE",
    "sg:address":"Osterwiecker Str 51a",
    "sg:city":"Vienenburg",
    "sg:phone":"+49 5324/77070",
    "sg:postcode":"38690",
    "sg:province":"Niedersachsen",
    "wof:name":"August Loose Gmbh & Co Kg",
    "wof:placetype":"venue"
},
  "geometry": {"coordinates":[10.574439,51.952911],"type":"Point"}
}