{
  "type": "Feature",
  "properties": {
    "iso:country":"DE",
    "sg:address":"Peterstor 1c",
    "sg:city":"Bad Hersfeld",
    "sg:phone":"+49 6621/92320",
    "sg:postcode":"36251",
    "sg:province":"Hessen",
    "wof:name":"Rvf Raiffeisen Vieh Und Fleisch Hessen Eg",
    "wof:placetype":"venue"
},
  "geometry": {"coordinates":[9.7149543762,50.8648986816],"type":"Point"}
}