{
  "type": "Feature",
  "properties": {
    "iso:country":"DE",
    "sg:address":"Konrad-Adenauer-Platz 17",
    "sg:city":"Ratingen",
    "sg:postcode":"40885",
    "sg:province":"Nordrhein-Westfalen",
    "wof:name":"Quadric Competence Center Anwendungsberatung F\u00fcr",
    "wof:placetype":"venue"
},
  "geometry": {"coordinates":[6.8291897774,51.3328552246],"type":"Point"}
}