{
  "type": "Feature",
  "properties": {
    "iso:country":"DE",
    "sg:address":"Erlacher Str. 3",
    "sg:city":"Pliezhausen",
    "sg:phone":"+49 7127/71776",
    "sg:postcode":"72124",
    "sg:province":"Baden-W\u00fcrttemberg",
    "wof:name":"Wirsum Gmbh",
    "wof:placetype":"venue"
},
  "geometry": {"coordinates":[9.183732,48.57531],"type":"Point"}
}