{
  "type": "Feature",
  "properties": {
    "iso:country":"DE",
    "sg:address":"Weinstr. 28",
    "sg:city":"Pfaffenweiler",
    "sg:phone":"+49 7664/7980",
    "sg:postcode":"79292",
    "sg:province":"Baden-W\u00fcrttemberg",
    "wof:name":"C. Und W. Scherle",
    "wof:placetype":"venue"
},
  "geometry": {"coordinates":[7.7585468292,47.9398384094],"type":"Point"}
}