{
  "type": "Feature",
  "properties": {
    "iso:country":"DE",
    "sg:address":"Eichh\u00f6lzlesweg 20",
    "sg:city":"Waldstetten",
    "sg:phone":"+49 7171/949393",
    "sg:postcode":"73550",
    "sg:province":"Baden-W\u00fcrttemberg",
    "wof:name":"Karl Baur",
    "wof:placetype":"venue"
},
  "geometry": {"coordinates":[9.826162,48.761913],"type":"Point"}
}