{
  "type": "Feature",
  "properties": {
    "iso:country":"DE",
    "sg:address":"Reutlinger Str. 56",
    "sg:city":"Nehren",
    "sg:phone":"+49 7473/23889",
    "sg:postcode":"72147",
    "sg:province":"Baden-W\u00fcrttemberg",
    "wof:name":"G. Denninger Architekt",
    "wof:placetype":"venue"
},
  "geometry": {"coordinates":[9.066697,48.425503],"type":"Point"}
}