{
  "type": "Feature",
  "properties": {
    "iso:country":"DE",
    "sg:address":"Cranger Str. 79",
    "sg:city":"Gelsenkirchen",
    "sg:phone":"+49 209/31208",
    "sg:postcode":"45894",
    "sg:province":"Nordrhein-Westfalen",
    "wof:name":"K. Oppenberg",
    "wof:placetype":"venue"
},
  "geometry": {"coordinates":[7.072896,51.57296],"type":"Point"}
}