{
  "type": "Feature",
  "properties": {
    "iso:country":"DE",
    "sg:address":"Am Gutshof 3",
    "sg:city":"Werder",
    "sg:phone":"+49 3327/70454",
    "sg:postcode":"14542",
    "sg:province":"Brandenburg",
    "wof:name":"Restaurant Antalya",
    "wof:placetype":"venue"
},
  "geometry": {"coordinates":[12.9365491867,52.375629425],"type":"Point"}
}