{
  "type": "Feature",
  "properties": {
    "iso:country":"DE",
    "sg:address":"Konradstr. 32",
    "sg:city":"Hamm",
    "sg:phone":"+49 2381/402233",
    "sg:postcode":"59067",
    "sg:province":"Nordrhein-Westfalen",
    "wof:name":"Bergschl\u00f6sschen Da Nico",
    "wof:placetype":"venue"
},
  "geometry": {"coordinates":[7.8020482063,51.6487197876],"type":"Point"}
}