{
  "type": "Feature",
  "properties": {
    "iso:country":"DE",
    "sg:address":"Iburger Str. 28",
    "sg:city":"Osnabr\u00fcck",
    "sg:phone":"+49 541/82355",
    "sg:postcode":"49082",
    "sg:province":"Niedersachsen",
    "wof:name":"J. Berning",
    "wof:placetype":"venue"
},
  "geometry": {"coordinates":[8.0551376343,52.2628173828],"type":"Point"}
}