{
  "type": "Feature",
  "properties": {
    "iso:country":"DE",
    "sg:address":"Arndtstr. 24",
    "sg:city":"Bielefeld",
    "sg:phone":"+49 521/5600622",
    "sg:postcode":"33615",
    "sg:province":"Nordrhein-Westfalen",
    "wof:name":"Gaya Natur Und Mode Gabriele Seiger E. K.",
    "wof:placetype":"venue"
},
  "geometry": {"coordinates":[8.5261287689,52.0271339417],"type":"Point"}
}