{
  "type": "Feature",
  "properties": {
    "iso:country":"DE",
    "sg:address":"Lindenstr 90",
    "sg:city":"Zorneding",
    "sg:phone":"+49 8106/248789",
    "sg:postcode":"85604",
    "sg:province":"Bayern",
    "wof:name":"Abofactory-verlagsmarketingberatung",
    "wof:placetype":"venue"
},
  "geometry": {"coordinates":[11.829721,48.08456],"type":"Point"}
}