{
  "type": "Feature",
  "properties": {
    "iso:country":"DE",
    "sg:address":"Marstallstr. 8",
    "sg:city":"M\u00fcnchen",
    "sg:phone":"+49 89/290120",
    "sg:postcode":"80539",
    "sg:province":"Bayern",
    "wof:name":"H. O. T. Home Order Television Europe",
    "wof:placetype":"venue"
},
  "geometry": {"coordinates":[11.582515,48.140038],"type":"Point"}
}