{
  "type": "Feature",
  "properties": {
    "iso:country":"DE",
    "sg:address":"Duissernstr. 3",
    "sg:city":"Duisburg",
    "sg:phone":"+49 203/309390",
    "sg:postcode":"47058",
    "sg:province":"Nordrhein-Westfalen",
    "wof:name":"Ergonomix Software Gmbh",
    "wof:placetype":"venue"
},
  "geometry": {"coordinates":[6.7818899155,51.4379920959],"type":"Point"}
}