{
  "type": "Feature",
  "properties": {
    "iso:country":"DE",
    "sg:address":"Am Solberg 14",
    "sg:city":"B\u00f6ttingen",
    "sg:phone":"+49 7429/2755",
    "sg:postcode":"78583",
    "sg:province":"Baden-W\u00fcrttemberg",
    "wof:name":"Stefan Ballier",
    "wof:placetype":"venue"
},
  "geometry": {"coordinates":[8.8061609268,48.1034622192],"type":"Point"}
}