{
  "type": "Feature",
  "properties": {
    "iso:country":"DE",
    "sg:address":"Vor der Blauen H\u00fctte 1",
    "sg:city":"Sangerhausen",
    "sg:phone":"+49 3464/577341",
    "sg:postcode":"06526",
    "sg:province":"Sachsen-Anhalt",
    "wof:name":"H. Stolze",
    "wof:placetype":"venue"
},
  "geometry": {"coordinates":[11.297916,51.479969],"type":"Point"}
}