{
  "type": "Feature",
  "properties": {
    "iso:country":"DE",
    "sg:address":"K\u00f6lner Landstr. 441",
    "sg:city":"D\u00fcsseldorf",
    "sg:phone":"+49 211",
    "sg:postcode":"40545",
    "sg:province":"Nordrhein-Westfalen",
    "wof:name":"S-online Service D\u00fcsseldorf Gmbh",
    "wof:placetype":"venue"
},
  "geometry": {"coordinates":[6.7518978119,51.23179245],"type":"Point"}
}