{
  "type": "Feature",
  "properties": {
    "iso:country":"DE",
    "sg:address":"Am Fuhrenkamp 3",
    "sg:city":"Weyhe",
    "sg:phone":"+49 4203/6834",
    "sg:postcode":"28844",
    "sg:province":"Niedersachsen",
    "wof:name":"H. Lehrmann Immobilienmakler",
    "wof:placetype":"venue"
},
  "geometry": {"coordinates":[8.8590612411,52.9838485718],"type":"Point"}
}