{
  "type": "Feature",
  "properties": {
    "iso:country":"DE",
    "sg:address":"Gro\u00dfe Str. 2::",
    "sg:city":"Strausberg",
    "sg:phone":"+49 4933/413400",
    "sg:postcode":"15344",
    "sg:province":"Brandenburg",
    "wof:name":"Kreissparkasse Maerkisch-oderland",
    "wof:placetype":"venue"
},
  "geometry": {"coordinates":[13.88162,52.577202],"type":"Point"}
}