{
  "type": "Feature",
  "properties": {
    "iso:country":"DE",
    "sg:address":"Schulstr. 35",
    "sg:city":"Loxstedt",
    "sg:postcode":"27612",
    "sg:province":"Niedersachsen",
    "wof:name":"B\u00fccherei Stotel",
    "wof:placetype":"venue"
},
  "geometry": {"coordinates":[8.599124,53.444],"type":"Point"}
}