{
  "type": "Feature",
  "properties": {
    "iso:country":"DE",
    "sg:address":"Martin-Bauer-Weg 31",
    "sg:city":"Mammendorf",
    "sg:phone":"+49 8145/6364",
    "sg:postcode":"82291",
    "sg:province":"Bayern",
    "wof:name":"Heinz Alscher",
    "wof:placetype":"venue"
},
  "geometry": {"coordinates":[11.179344,48.216003],"type":"Point"}
}