{
  "type": "Feature",
  "properties": {
    "iso:country":"DE",
    "sg:address":"Hirschstr. 22",
    "sg:city":"Ulm",
    "sg:phone":"+49 731/968630",
    "sg:postcode":"89073",
    "sg:province":"Baden-W\u00fcrttemberg",
    "wof:name":"Deutsche Woolworth Gmbh & Co. Ohg",
    "wof:placetype":"venue"
},
  "geometry": {"coordinates":[9.98813,48.398373],"type":"Point"}
}