{
  "type": "Feature",
  "properties": {
    "iso:country":"DE",
    "sg:address":"M\u00fcnzstr. 4",
    "sg:city":"W\u00fcrzburg",
    "sg:phone":"+49 931/15417",
    "sg:postcode":"97070",
    "sg:province":"Bayern",
    "wof:name":"H. Balli",
    "wof:placetype":"venue"
},
  "geometry": {"coordinates":[9.9322156906,49.7885284424],"type":"Point"}
}