{
  "type": "Feature",
  "properties": {
    "iso:country":"DE",
    "sg:address":"Grapengiesserstr. 6",
    "sg:city":"L\u00fcbeck",
    "sg:phone":"+49 4945/1388780",
    "sg:postcode":"23556",
    "sg:province":"Schleswig-Holstein",
    "wof:name":"Paul Weidlich L\u00dcbeck Gmbh",
    "wof:placetype":"venue"
},
  "geometry": {"coordinates":[10.6390247345,53.8586387634],"type":"Point"}
}