{
  "type": "Feature",
  "properties": {
    "iso:country":"DE",
    "sg:address":"Neue Str. 16",
    "sg:city":"Bad Urach",
    "sg:phone":"+49 7125/4277",
    "sg:postcode":"72574",
    "sg:province":"Baden-W\u00fcrttemberg",
    "wof:name":"Bierst\u00fcble",
    "wof:placetype":"venue"
},
  "geometry": {"coordinates":[9.4012823105,48.4926795959],"type":"Point"}
}