{
  "type": "Feature",
  "properties": {
    "iso:country":"DE",
    "sg:address":"Opelstr. 4",
    "sg:city":"M\u00f6rfelden-Walldorf",
    "sg:phone":"+49 6105/24085",
    "sg:postcode":"64546",
    "sg:province":"Hessen",
    "wof:name":"K. D. Liersch Steuerberater",
    "wof:placetype":"venue"
},
  "geometry": {"coordinates":[8.5631933212,49.9664649963],"type":"Point"}
}