{
  "type": "Feature",
  "properties": {
    "iso:country":"DE",
    "sg:city":"Hamburg",
    "sg:phone":"+49 40",
    "sg:postcode":"21035",
    "sg:province":"Hamburg",
    "wof:name":"Image Com Ronald Doll",
    "wof:placetype":"venue"
},
  "geometry": {"coordinates":[10.159323,53.489838],"type":"Point"}
}