{
  "type": "Feature",
  "properties": {
    "iso:country":"DE",
    "sg:address":"Klostersee 1",
    "sg:city":"Gr\u00f6mitz",
    "sg:phone":"+49 4366/517",
    "sg:postcode":"23743",
    "sg:province":"Schleswig-Holstein",
    "wof:name":"Biohof N\u00e4gel U. Marwedel",
    "wof:placetype":"venue"
},
  "geometry": {"coordinates":[11.014987,54.191124],"type":"Point"}
}