{
  "type": "Feature",
  "properties": {
    "iso:country":"DE",
    "sg:address":"Centrumplatz 1",
    "sg:city":"Bochum",
    "sg:phone":"+49 2327/68000",
    "sg:postcode":"44866",
    "sg:province":"Nordrhein-Westfalen",
    "wof:name":"J\u00e4ger Transport Gmbh",
    "wof:placetype":"venue"
},
  "geometry": {"coordinates":[7.160703,51.481037],"type":"Point"}
}