{
  "type": "Feature",
  "properties": {
    "iso:country":"DE",
    "sg:address":"Kandelfeldstr. 12",
    "sg:city":"Aachen",
    "sg:phone":"+49 241/873457",
    "sg:postcode":"52074",
    "sg:province":"Nordrhein-Westfalen",
    "wof:name":"Severt Polska Sp. Zo. O. Zweigniederlassung Aachen",
    "wof:placetype":"venue"
},
  "geometry": {"coordinates":[6.042114,50.768963],"type":"Point"}
}