{
  "type": "Feature",
  "properties": {
    "iso:country":"DE",
    "sg:address":"Leimbacher Str. 84",
    "sg:city":"Wuppertal",
    "sg:phone":"+49 202/508696",
    "sg:postcode":"42281",
    "sg:province":"Nordrhein-Westfalen",
    "wof:name":"H.-p. Und L. Siedenbiedel",
    "wof:placetype":"venue"
},
  "geometry": {"coordinates":[7.193097,51.278324],"type":"Point"}
}