{
  "type": "Feature",
  "properties": {
    "iso:country":"DE",
    "sg:address":"Kapuzinerstr. 11a",
    "sg:city":"Dillingen",
    "sg:phone":"+49 9071/3838",
    "sg:postcode":"89407",
    "sg:province":"Bayern",
    "wof:name":"Hubert Aninger",
    "wof:placetype":"venue"
},
  "geometry": {"coordinates":[10.4953365326,48.5801239014],"type":"Point"}
}