{
  "type": "Feature",
  "properties": {
    "iso:country":"DE",
    "sg:address":"Am Markt 2",
    "sg:city":"B\u00f6nningstedt",
    "sg:phone":"+49 40/5567546",
    "sg:postcode":"25474",
    "sg:province":"Schleswig-Holstein",
    "wof:name":"Apotheke Rugenbergen",
    "wof:placetype":"venue"
},
  "geometry": {"coordinates":[9.905189,53.664776],"type":"Point"}
}