{
  "type": "Feature",
  "properties": {
    "iso:country":"DE",
    "sg:address":"Gro\u00dfe Pagenbergstr. 47",
    "sg:city":"Salzwedel",
    "sg:phone":"+49 3901/27829",
    "sg:postcode":"29410",
    "sg:province":"Sachsen-Anhalt",
    "wof:name":"Meyer Und Demann Rechtsanw\u00e4lte",
    "wof:placetype":"venue"
},
  "geometry": {"coordinates":[11.1475162506,52.8573989868],"type":"Point"}
}