{
  "type": "Feature",
  "properties": {
    "iso:country":"DE",
    "sg:address":"Damaschkestr. 37",
    "sg:city":"Gro\u00dfp\u00f6sna",
    "sg:phone":"+49 34297/42952",
    "sg:postcode":"04463",
    "sg:province":"Sachsen",
    "wof:name":"Gert Schmidt",
    "wof:placetype":"venue"
},
  "geometry": {"coordinates":[12.494577,51.267651],"type":"Point"}
}