{
  "type": "Feature",
  "properties": {
    "iso:country":"DE",
    "sg:address":"Langenrieper Weg 6",
    "sg:city":"Nordenham",
    "sg:phone":"+49 4731/7260",
    "sg:postcode":"26954",
    "sg:province":"Niedersachsen",
    "wof:name":"Theodor B\u00fcsing",
    "wof:placetype":"venue"
},
  "geometry": {"coordinates":[8.439722,53.472466],"type":"Point"}
}