{
  "type": "Feature",
  "properties": {
    "iso:country":"DE",
    "sg:address":"Berliner Damm 197 a",
    "sg:city":"Mahlow",
    "sg:postcode":"15831",
    "sg:province":"Brandenburg",
    "wof:name":"Christian Rohde Elektro- Technik- Und Schaltanlagen",
    "wof:placetype":"venue"
},
  "geometry": {"coordinates":[13.4090366364,52.3560714722],"type":"Point"}
}