{
  "type": "Feature",
  "properties": {
    "iso:country":"DE",
    "sg:address":"Oberfeldstr. 19",
    "sg:city":"Frankfurt",
    "sg:phone":"+49 69/578944",
    "sg:postcode":"60439",
    "sg:province":"Hessen",
    "wof:name":"Walter Hannibal",
    "wof:placetype":"venue"
},
  "geometry": {"coordinates":[8.6244535446,50.1554145813],"type":"Point"}
}