{
  "type": "Feature",
  "properties": {
    "iso:country":"DE",
    "sg:address":"Angerstr. 30",
    "sg:city":"Vilsbiburg",
    "sg:phone":"+49 8741/91623",
    "sg:postcode":"84137",
    "sg:province":"Bayern",
    "wof:name":"F. Pyka",
    "wof:placetype":"venue"
},
  "geometry": {"coordinates":[12.3499689102,48.4532279968],"type":"Point"}
}