{
  "type": "Feature",
  "properties": {
    "iso:country":"DE",
    "sg:address":"Bahnhofsweg 7",
    "sg:city":"Droy\u00dfig",
    "sg:phone":"+49 34425/21415",
    "sg:postcode":"06722",
    "sg:province":"Sachsen-Anhalt",
    "wof:name":"Bahnhofsgastst\u00e4tte",
    "wof:placetype":"venue"
},
  "geometry": {"coordinates":[12.025177002,51.043800354],"type":"Point"}
}