{
  "type": "Feature",
  "properties": {
    "iso:country":"DE",
    "sg:address":"Ferdinand-Sauerbruch-Weg 31",
    "sg:city":"Ulm",
    "sg:phone":"+49 731/57113",
    "sg:postcode":"89075",
    "sg:province":"Baden-W\u00fcrttemberg",
    "wof:name":"Hans-j\u00fcrgen Baron Landschaftsarchitekt",
    "wof:placetype":"venue"
},
  "geometry": {"coordinates":[9.947947,48.412731],"type":"Point"}
}