{
  "type": "Feature",
  "properties": {
    "iso:country":"DE",
    "sg:address":"Bahnhofstr. 45",
    "sg:city":"Torgelow",
    "sg:postcode":"17358",
    "sg:province":"Mecklenburg-Vorpommern",
    "wof:name":"Bcm-bioniklas Collector Management Gmbh",
    "wof:placetype":"venue"
},
  "geometry": {"coordinates":[14.0108118057,53.6307678223],"type":"Point"}
}