{
  "type": "Feature",
  "properties": {
    "iso:country":"DE",
    "sg:address":"Vormbacherweg 3",
    "sg:city":"Grafenau",
    "sg:phone":"+49 8552/96520",
    "sg:postcode":"94481",
    "sg:province":"Bayern",
    "wof:name":"Edwin Sigl Steuerberater",
    "wof:placetype":"venue"
},
  "geometry": {"coordinates":[13.3936977386,48.8604812622],"type":"Point"}
}