{
  "type": "Feature",
  "properties": {
    "iso:country":"DE",
    "sg:address":"Bahnhofstr.",
    "sg:city":"Schweich",
    "sg:phone":"+49 6502/5318",
    "sg:postcode":"54338",
    "sg:province":"Rheinland-Pfalz",
    "wof:name":"Friedhelm Schroeder Ingenieur",
    "wof:placetype":"venue"
},
  "geometry": {"coordinates":[6.7498960495,49.8243713379],"type":"Point"}
}