{
  "type": "Feature",
  "properties": {
    "iso:country":"DE",
    "sg:address":"Am Berge 11",
    "sg:city":"Soltau",
    "sg:phone":"+49 5191/2616",
    "sg:postcode":"29614",
    "sg:province":"Niedersachsen",
    "wof:name":"Karl-heinz Konnopke",
    "wof:placetype":"venue"
},
  "geometry": {"coordinates":[9.8437108994,53.0088577271],"type":"Point"}
}