{
  "type": "Feature",
  "properties": {
    "iso:country":"DE",
    "sg:address":"Markt 7",
    "sg:city":"D\u00fcren",
    "sg:phone":"+49 2421/28060",
    "sg:postcode":"52349",
    "sg:province":"Nordrhein-Westfalen",
    "wof:name":"Quelle Versandhaus",
    "wof:placetype":"venue"
},
  "geometry": {"coordinates":[6.483738,50.802479],"type":"Point"}
}