{
  "type": "Feature",
  "properties": {
    "iso:country":"DE",
    "sg:address":"Ernteweg 5",
    "sg:city":"Homberg",
    "sg:phone":"+49 5681/2792",
    "sg:postcode":"34576",
    "sg:province":"Hessen",
    "wof:name":"Konrad Knorr",
    "wof:placetype":"venue"
},
  "geometry": {"coordinates":[9.423814,51.026844],"type":"Point"}
}