{
  "type": "Feature",
  "properties": {
    "iso:country":"DE",
    "sg:address":"Sch\u00fctzenstr. 15",
    "sg:city":"Gr\u00f6mitz",
    "sg:phone":"+49 4562/4431",
    "sg:postcode":"23743",
    "sg:province":"Schleswig-Holstein",
    "wof:name":"Heidrun Saalmann",
    "wof:placetype":"venue"
},
  "geometry": {"coordinates":[10.9636259079,54.149646759],"type":"Point"}
}