{
  "type": "Feature",
  "properties": {
    "iso:country":"DE",
    "sg:address":"Kirchenstr. 101",
    "sg:city":"Saarwellingen",
    "sg:phone":"+49 6838/3015",
    "sg:postcode":"66793",
    "sg:province":"Saarland",
    "wof:name":"Melanie Feld Heilpraktikerin",
    "wof:placetype":"venue"
},
  "geometry": {"coordinates":[6.8825058937,49.3615074158],"type":"Point"}
}