{
  "type": "Feature",
  "properties": {
    "iso:country":"DE",
    "sg:address":"B\u00e4ckerstr.",
    "sg:city":"D\u00f6beln",
    "sg:phone":"+49 3431/574533",
    "sg:postcode":"04720",
    "sg:province":"Sachsen",
    "wof:name":"Kaufcenter",
    "wof:placetype":"venue"
},
  "geometry": {"coordinates":[13.12057,51.12159],"type":"Point"}
}