{
  "type": "Feature",
  "properties": {
    "iso:country":"DE",
    "sg:address":"Ringstr. 31",
    "sg:city":"Wernigerode",
    "sg:phone":"+49 3943/905205",
    "sg:postcode":"38855",
    "sg:province":"Sachsen-Anhalt",
    "wof:name":"Forum-apotheke Simona Saaber",
    "wof:placetype":"venue"
},
  "geometry": {"coordinates":[10.784272,51.835152],"type":"Point"}
}