{
  "type": "Feature",
  "properties": {
    "iso:country":"DE",
    "sg:address":"Goethestr. 5",
    "sg:city":"Bad Langensalza",
    "sg:postcode":"99947",
    "sg:province":"Th\u00fcringen",
    "wof:name":"Workteam Beteiligungsges. Mbh",
    "wof:placetype":"venue"
},
  "geometry": {"coordinates":[10.642964,51.115067],"type":"Point"}
}