{
  "type": "Feature",
  "properties": {
    "iso:country":"DE",
    "sg:address":"Oberjesinger Str. 42",
    "sg:city":"Herrenberg",
    "sg:phone":"+49 7032/34367",
    "sg:postcode":"71083",
    "sg:province":"Baden-W\u00fcrttemberg",
    "wof:name":"Ristorante-pizzeria La Veranda",
    "wof:placetype":"venue"
},
  "geometry": {"coordinates":[8.8418741226,48.6159515381],"type":"Point"}
}