{
  "type": "Feature",
  "properties": {
    "iso:country":"DE",
    "sg:address":"Griesfeldstr. 23",
    "sg:city":"Bad T\u00f6lz",
    "sg:phone":"+49 8041/77375",
    "sg:postcode":"83646",
    "sg:province":"Bayern",
    "wof:name":"G. Riesch",
    "wof:placetype":"venue"
},
  "geometry": {"coordinates":[11.5621175766,47.7561073303],"type":"Point"}
}