{
  "type": "Feature",
  "properties": {
    "iso:country":"DE",
    "sg:address":"Zum Fuchsstrauch 5",
    "sg:city":"Lich",
    "sg:phone":"+49 6404/2504",
    "sg:postcode":"35423",
    "sg:province":"Hessen",
    "wof:name":"W. Georg Gmbh & Co. Kg",
    "wof:placetype":"venue"
},
  "geometry": {"coordinates":[8.804639,50.516663],"type":"Point"}
}