{
  "type": "Feature",
  "properties": {
    "iso:country":"DE",
    "sg:address":"Moserstr. 24",
    "sg:city":"Stuttgart",
    "sg:phone":"+49 711/247337",
    "sg:postcode":"70182",
    "sg:province":"Baden-W\u00fcrttemberg",
    "wof:name":"Dr. Wagner Und G\u00f6tze-siebrand Rechtsanw\u00e4ltinnen",
    "wof:placetype":"venue"
},
  "geometry": {"coordinates":[9.1877889633,48.7779502869],"type":"Point"}
}