{
  "type": "Feature",
  "properties": {
    "iso:country":"DE",
    "sg:address":"M\u00fchlenredder 23",
    "sg:city":"Fockbek",
    "sg:phone":"+49 4331/61513",
    "sg:postcode":"24787",
    "sg:province":"Schleswig-Holstein",
    "wof:name":"J. Kerath",
    "wof:placetype":"venue"
},
  "geometry": {"coordinates":[9.620251,54.303047],"type":"Point"}
}