{
  "type": "Feature",
  "properties": {
    "iso:country":"DE",
    "sg:address":"In der Galgendell",
    "sg:city":"Saarbr\u00fccken",
    "sg:postcode":"66117",
    "sg:province":"Saarland",
    "wof:name":"Happy Sports Freizeitanlagen Gmbh",
    "wof:placetype":"venue"
},
  "geometry": {"coordinates":[6.972756,49.220615],"type":"Point"}
}