{
  "type": "Feature",
  "properties": {
    "iso:country":"DE",
    "sg:address":"Rittrumer Str. 21",
    "sg:city":"Hatten",
    "sg:phone":"+49 4482/285",
    "sg:postcode":"26209",
    "sg:province":"Niedersachsen",
    "wof:name":"Bernhard M\u00fcller",
    "wof:placetype":"venue"
},
  "geometry": {"coordinates":[8.350264,53.006409],"type":"Point"}
}