{
  "type": "Feature",
  "properties": {
    "iso:country":"DE",
    "sg:address":"M\u00fchlenstr. 14-16",
    "sg:city":"Hilden",
    "sg:postcode":"40721",
    "sg:province":"Nordrhein-Westfalen",
    "wof:name":"Italienisches Zentrum",
    "wof:placetype":"venue"
},
  "geometry": {"coordinates":[6.9419169426,51.1700515747],"type":"Point"}
}