{
  "type": "Feature",
  "properties": {
    "iso:country":"DE",
    "sg:address":"Waldstr. 9",
    "sg:city":"Berlin",
    "sg:phone":"+49 30/4772893",
    "sg:postcode":"13156",
    "sg:province":"Berlin",
    "wof:name":"Detlef B\u00f6hm",
    "wof:placetype":"venue"
},
  "geometry": {"coordinates":[13.399576,52.582172],"type":"Point"}
}