{
  "type": "Feature",
  "properties": {
    "iso:country":"DE",
    "sg:address":"Dorfstr. 26",
    "sg:city":"Fuhlenhagen",
    "sg:phone":"+49 4156/7192",
    "sg:postcode":"21493",
    "sg:province":"Schleswig-Holstein",
    "wof:name":"Lothar Wachholz",
    "wof:placetype":"venue"
},
  "geometry": {"coordinates":[10.527538,53.571621],"type":"Point"}
}