{
  "type": "Feature",
  "properties": {
    "iso:country":"DE",
    "sg:address":"Kirchstr. 13",
    "sg:city":"Oderwitz",
    "sg:postcode":"02791",
    "sg:province":"Sachsen",
    "wof:name":"Evangelisches Pfarramt",
    "wof:placetype":"venue"
},
  "geometry": {"coordinates":[14.7299003601,50.9519081116],"type":"Point"}
}