{
  "type": "Feature",
  "properties": {
    "iso:country":"DE",
    "sg:address":"Holenberger Str. 22",
    "sg:city":"Golmbach",
    "sg:phone":"+49 5532/8291",
    "sg:postcode":"37640",
    "sg:province":"Niedersachsen",
    "wof:name":"Wilhelm M\u00fcller",
    "wof:placetype":"venue"
},
  "geometry": {"coordinates":[9.548879,51.899414],"type":"Point"}
}