{
  "type": "Feature",
  "properties": {
    "iso:country":"DE",
    "sg:address":"Am M\u00fchlenteich 16",
    "sg:city":"Bergheim",
    "sg:phone":"+49 2238/42721",
    "sg:postcode":"50129",
    "sg:province":"Nordrhein-Westfalen",
    "wof:name":"Isolde Hund",
    "wof:placetype":"venue"
},
  "geometry": {"coordinates":[6.750195,50.966751],"type":"Point"}
}