{
  "type": "Feature",
  "properties": {
    "iso:country":"DE",
    "sg:address":"Lehmbrink 13",
    "sg:city":"Blomberg",
    "sg:phone":"+49 5235/96900",
    "sg:postcode":"32825",
    "sg:province":"Nordrhein-Westfalen",
    "wof:name":"Fakta-m\u00f6bel Gmbh & Co. Kg",
    "wof:placetype":"venue"
},
  "geometry": {"coordinates":[9.0976734161,51.9392051697],"type":"Point"}
}