{
  "type": "Feature",
  "properties": {
    "iso:country":"DE",
    "sg:address":"Friedhofstr. 27",
    "sg:city":"Neu-Ulm",
    "sg:postcode":"89233",
    "sg:province":"Bayern",
    "wof:name":"E. M. U. Eventmanagement- Marketing-unternehmens-",
    "wof:placetype":"venue"
},
  "geometry": {"coordinates":[10.0733699799,48.4176216125],"type":"Point"}
}