{
  "type": "Feature",
  "properties": {
    "iso:country":"DE",
    "sg:address":"Gro\u00dfe Ahlm\u00fchle 5",
    "sg:city":"Rohrbach",
    "sg:phone":"+49 4963/4999490",
    "sg:postcode":"76865",
    "sg:province":"Rheinland-Pfalz",
    "wof:name":"Wls-juwel Maschinenfabrik Gmbh",
    "wof:placetype":"venue"
},
  "geometry": {"coordinates":[8.1408348083,49.1332015991],"type":"Point"}
}