{
  "type": "Feature",
  "properties": {
    "iso:country":"DE",
    "sg:address":"Tegernseer Str. 4",
    "sg:city":"Waakirchen",
    "sg:phone":"+49 8022/24334",
    "sg:postcode":"83666",
    "sg:province":"Bayern",
    "wof:name":"Kreissparkasse Tegernsee",
    "wof:placetype":"venue"
},
  "geometry": {"coordinates":[11.675533,47.770222],"type":"Point"}
}