{
  "type": "Feature",
  "properties": {
    "iso:country":"DE",
    "sg:address":"Im Talgarten 23",
    "sg:city":"St. Ingbert",
    "sg:phone":"+49 6894/5507",
    "sg:postcode":"66386",
    "sg:province":"Saarland",
    "wof:name":"Arnold Hermann",
    "wof:placetype":"venue"
},
  "geometry": {"coordinates":[7.168501,49.282898],"type":"Point"}
}