{
  "type": "Feature",
  "properties": {
    "iso:country":"DE",
    "sg:address":"Industriestr. 1",
    "sg:city":"Kastl",
    "sg:phone":"+49 9642/1784",
    "sg:postcode":"95506",
    "sg:province":"Bayern",
    "wof:name":"Ros-rollentechnik Reinhold Schneider Gmbh",
    "wof:placetype":"venue"
},
  "geometry": {"coordinates":[11.897109,49.826939],"type":"Point"}
}