{
  "type": "Feature",
  "properties": {
    "iso:country":"DE",
    "sg:address":"Angelstr. 33",
    "sg:city":"Mannheim",
    "sg:postcode":"68199",
    "sg:province":"Baden-W\u00fcrttemberg",
    "wof:name":"H & S Betriebsgruppe Gmbh",
    "wof:placetype":"venue"
},
  "geometry": {"coordinates":[8.496073,49.44949],"type":"Point"}
}