{
  "type": "Feature",
  "properties": {
    "iso:country":"DE",
    "sg:address":"Max-Eyth-Str. 30",
    "sg:city":"Berlin",
    "sg:postcode":"14195",
    "sg:province":"Berlin",
    "wof:name":"Biotrade Gmbh",
    "wof:placetype":"venue"
},
  "geometry": {"coordinates":[13.284917,52.467892],"type":"Point"}
}