{
  "type": "Feature",
  "properties": {
    "iso:country":"DE",
    "sg:address":"Paulus-Jenisius-Str. 43",
    "sg:city":"Annaberg-Buchholz",
    "sg:phone":"+49 3733/1330",
    "sg:postcode":"09456",
    "sg:province":"Sachsen",
    "wof:name":"Fachvermittlung F\u00fcr Hotel- Und Gastst\u00e4ttenpersonal",
    "wof:placetype":"venue"
},
  "geometry": {"coordinates":[13.009953,50.587421],"type":"Point"}
}