{
  "type": "Feature",
  "properties": {
    "iso:country":"DE",
    "sg:address":"Puschkinstr. 27",
    "sg:city":"Luckenwalde",
    "sg:phone":"+49 3371/610419",
    "sg:postcode":"14943",
    "sg:province":"Brandenburg",
    "wof:name":"Hotel Pelikan Inh. P. G\u00f6tze",
    "wof:placetype":"venue"
},
  "geometry": {"coordinates":[13.166387558,52.0907936096],"type":"Point"}
}