{
  "type": "Feature",
  "properties": {
    "iso:country":"DE",
    "sg:address":"Eisberger Str. 299",
    "sg:city":"Porta Westfalica",
    "sg:phone":"+49 5751/8198",
    "sg:postcode":"32457",
    "sg:province":"Nordrhein-Westfalen",
    "wof:name":"G\u00e4rtner & Stein",
    "wof:placetype":"venue"
},
  "geometry": {"coordinates":[8.995466,52.212639],"type":"Point"}
}