{
  "type": "Feature",
  "properties": {
    "iso:country":"DE",
    "sg:address":"Gillitzerstr. 1",
    "sg:city":"Rosenheim",
    "sg:phone":"+49 8031/357153",
    "sg:postcode":"83022",
    "sg:province":"Bayern",
    "wof:name":"Impuls Fashion Inh. Roswitha Laiminger E. K.",
    "wof:placetype":"venue"
},
  "geometry": {"coordinates":[12.124958,47.855419],"type":"Point"}
}