{
  "type": "Feature",
  "properties": {
    "iso:country":"DE",
    "sg:address":"Bahnstr. 23",
    "sg:city":"Berlin",
    "sg:phone":"+49 30/7211070",
    "sg:postcode":"12277",
    "sg:province":"Berlin",
    "wof:name":"Winfried Mittag",
    "wof:placetype":"venue"
},
  "geometry": {"coordinates":[13.3764152527,52.4203262329],"type":"Point"}
}