{
  "type": "Feature",
  "properties": {
    "iso:country":"DE",
    "sg:address":"Hans-Holbein-Str. 33",
    "sg:city":"Heidenheim",
    "sg:phone":"+49 7321/61712",
    "sg:postcode":"89520",
    "sg:province":"Baden-W\u00fcrttemberg",
    "wof:name":"G\u00fcnter Schnitzer Architekt",
    "wof:placetype":"venue"
},
  "geometry": {"coordinates":[10.136946,48.69698],"type":"Point"}
}