{
  "type": "Feature",
  "properties": {
    "iso:country":"DE",
    "sg:address":"Krampenfeld 56",
    "sg:city":"Dorsten",
    "sg:phone":"+49 2369/7315",
    "sg:postcode":"46286",
    "sg:province":"Nordrhein-Westfalen",
    "wof:name":"Eugen Badura Architekt",
    "wof:placetype":"venue"
},
  "geometry": {"coordinates":[7.004361,51.759544],"type":"Point"}
}