{
  "type": "Feature",
  "properties": {
    "iso:country":"DE",
    "sg:address":"Kepserstr. 19",
    "sg:city":"Freising",
    "sg:phone":"+49 8161/83941",
    "sg:postcode":"85356",
    "sg:province":"Bayern",
    "wof:name":"Gerhard Und Heidi Ollinger",
    "wof:placetype":"venue"
},
  "geometry": {"coordinates":[11.7627439499,48.3951950073],"type":"Point"}
}