{
  "type": "Feature",
  "properties": {
    "iso:country":"DE",
    "sg:address":"Engertstr. 31",
    "sg:city":"Leipzig",
    "sg:phone":"+49 341/4011358",
    "sg:postcode":"04229",
    "sg:province":"Sachsen",
    "wof:name":"Metallbau Walta",
    "wof:placetype":"venue"
},
  "geometry": {"coordinates":[12.32316,51.327896],"type":"Point"}
}