{
  "type": "Feature",
  "properties": {
    "iso:country":"DE",
    "sg:address":"De-la-Chevallerie-Str. 46",
    "sg:city":"Gelsenkirchen",
    "sg:phone":"+49 209/375515",
    "sg:postcode":"45894",
    "sg:province":"Nordrhein-Westfalen",
    "wof:name":"G & O Processing Gmbh",
    "wof:placetype":"venue"
},
  "geometry": {"coordinates":[7.0540628433,51.5809898376],"type":"Point"}
}