{
  "type": "Feature",
  "properties": {
    "iso:country":"DE",
    "sg:address":"Kirchstr. 3",
    "sg:city":"Bad Iburg",
    "sg:phone":"+49 5403/4400",
    "sg:postcode":"49186",
    "sg:province":"Niedersachsen",
    "wof:name":"G\u00fcnther Eggert",
    "wof:placetype":"venue"
},
  "geometry": {"coordinates":[8.054073,52.147198],"type":"Point"}
}