{
  "type": "Feature",
  "properties": {
    "iso:country":"DE",
    "sg:address":"M\u00fcnsterstr. 29",
    "sg:city":"Hamburg",
    "sg:phone":"+49 40/5533652",
    "sg:postcode":"22529",
    "sg:province":"Hamburg",
    "wof:name":"Open Up Gmbh",
    "wof:placetype":"venue"
},
  "geometry": {"coordinates":[9.9746608734,53.5972213745],"type":"Point"}
}