{
  "type": "Feature",
  "properties": {
    "iso:country":"DE",
    "sg:address":"Raiffeisenstr. 24",
    "sg:city":"Bruchk\u00f6bel",
    "sg:phone":"+49 6183/901313",
    "sg:postcode":"63486",
    "sg:province":"Hessen",
    "wof:name":"Thomas Niedermeier Signal Versicherung",
    "wof:placetype":"venue"
},
  "geometry": {"coordinates":[8.9497928619,50.1991615295],"type":"Point"}
}