{
  "type": "Feature",
  "properties": {
    "iso:country":"DE",
    "sg:address":"Springbornstr. 94",
    "sg:city":"Berlin",
    "sg:postcode":"12487",
    "sg:province":"Berlin",
    "wof:name":"Ursula Plauschin",
    "wof:placetype":"venue"
},
  "geometry": {"coordinates":[13.497763,52.438171],"type":"Point"}
}