{
  "type": "Feature",
  "properties": {
    "iso:country":"DE",
    "sg:address":"Bahnhofstr. 22",
    "sg:city":"Eching",
    "sg:phone":"+49 89/3799576",
    "sg:postcode":"85386",
    "sg:province":"Bayern",
    "wof:name":"Ertl &tegtmeyer Gmbh",
    "wof:placetype":"venue"
},
  "geometry": {"coordinates":[11.61815,48.300522],"type":"Point"}
}