{
  "type": "Feature",
  "properties": {
    "iso:country":"DE",
    "sg:address":"Roggensteiner Str. 4",
    "sg:city":"Puchheim",
    "sg:phone":"+49 89/801136",
    "sg:postcode":"82178",
    "sg:province":"Bayern",
    "wof:name":"Stefi F\u00fcll",
    "wof:placetype":"venue"
},
  "geometry": {"coordinates":[11.3520488739,48.1727752686],"type":"Point"}
}