{
  "type": "Feature",
  "properties": {
    "iso:country":"DE",
    "sg:address":"Velauer Str. 130",
    "sg:city":"M\u00fclheim",
    "sg:phone":"+49 208/370423",
    "sg:postcode":"45472",
    "sg:province":"Nordrhein-Westfalen",
    "wof:name":"Heinrich Peters",
    "wof:placetype":"venue"
},
  "geometry": {"coordinates":[6.935395,51.42667],"type":"Point"}
}