{
  "type": "Feature",
  "properties": {
    "iso:country":"DE",
    "sg:address":"Rolandstr. 27 f",
    "sg:city":"Berlin",
    "sg:phone":"+49 30/4762589",
    "sg:postcode":"13156",
    "sg:province":"Berlin",
    "wof:name":"Siegfried Brachhaus",
    "wof:placetype":"venue"
},
  "geometry": {"coordinates":[13.3983097076,52.5814781189],"type":"Point"}
}