{
  "type": "Feature",
  "properties": {
    "iso:country":"DE",
    "sg:address":"Kappenberger Feld 6",
    "sg:city":"Bad Oeynhausen",
    "sg:phone":"+49 5731/866304",
    "sg:postcode":"32547",
    "sg:province":"Nordrhein-Westfalen",
    "wof:name":"Karampour Und Meyer Architekten",
    "wof:placetype":"venue"
},
  "geometry": {"coordinates":[8.8152,52.189331],"type":"Point"}
}