{
  "type": "Feature",
  "properties": {
    "iso:country":"DE",
    "sg:address":"Ulmenweg 3",
    "sg:city":"Dassow",
    "sg:phone":"+49 38826/325",
    "sg:postcode":"23942",
    "sg:province":"Mecklenburg-Vorpommern",
    "wof:name":"B. Pedersen Immobilienmakler",
    "wof:placetype":"venue"
},
  "geometry": {"coordinates":[10.9752206802,53.9017791748],"type":"Point"}
}