{
  "type": "Feature",
  "properties": {
    "iso:country":"DE",
    "sg:address":"Siegener Str. 59",
    "sg:city":"Reichshof",
    "sg:phone":"+49 2297/1880",
    "sg:postcode":"51580",
    "sg:province":"Nordrhein-Westfalen",
    "wof:name":"Die Wurst Gmbh",
    "wof:placetype":"venue"
},
  "geometry": {"coordinates":[7.7568101883,50.9426994324],"type":"Point"}
}