{
  "type": "Feature",
  "properties": {
    "iso:country":"DE",
    "sg:address":"Katharinenstr. 19",
    "sg:city":"Solingen",
    "sg:phone":"+49 212/591946",
    "sg:postcode":"42653",
    "sg:province":"Nordrhein-Westfalen",
    "wof:name":"Hans-joachim Kiene",
    "wof:placetype":"venue"
},
  "geometry": {"coordinates":[7.079214,51.204933],"type":"Point"}
}