{
  "type": "Feature",
  "properties": {
    "iso:country":"DE",
    "sg:address":"Thielenstr. 35",
    "sg:city":"Krefeld",
    "sg:phone":"+49 2151/329057",
    "sg:postcode":"47809",
    "sg:province":"Nordrhein-Westfalen",
    "wof:name":"Attempto E. K.",
    "wof:placetype":"venue"
},
  "geometry": {"coordinates":[6.6106557846,51.331073761],"type":"Point"}
}