{
  "type": "Feature",
  "properties": {
    "iso:country":"DE",
    "sg:address":"Kaiser-Otto-Str. 57",
    "sg:city":"Lennestadt",
    "sg:phone":"+49 2721/3456",
    "sg:postcode":"57368",
    "sg:province":"Nordrhein-Westfalen",
    "wof:name":"W. M\u00fcller",
    "wof:placetype":"venue"
},
  "geometry": {"coordinates":[8.067655,51.121063],"type":"Point"}
}