{
  "type": "Feature",
  "properties": {
    "iso:country":"DE",
    "sg:address":"Ahseufer 3",
    "sg:city":"Hamm",
    "sg:phone":"+49 2381/25253",
    "sg:postcode":"59063",
    "sg:province":"Nordrhein-Westfalen",
    "wof:name":"Werner Hinkelmann Ingenieur",
    "wof:placetype":"venue"
},
  "geometry": {"coordinates":[7.840116024,51.6865158081],"type":"Point"}
}