{
  "type": "Feature",
  "properties": {
    "iso:country":"DE",
    "sg:address":"Blumenstr. 3",
    "sg:city":"Rodgau",
    "sg:phone":"+49 6106/25533",
    "sg:postcode":"63110",
    "sg:province":"Hessen",
    "wof:name":"B. G\u00f6hler",
    "wof:placetype":"venue"
},
  "geometry": {"coordinates":[8.8798465729,50.0248222351],"type":"Point"}
}