{
  "type": "Feature",
  "properties": {
    "iso:country":"DE",
    "sg:address":"Rudolf-Breitscheid-Str. 20",
    "sg:city":"Zschopau",
    "sg:phone":"+49 3725/22231",
    "sg:postcode":"09405",
    "sg:province":"Sachsen",
    "wof:name":"Redaktion Freie Presse",
    "wof:placetype":"venue"
},
  "geometry": {"coordinates":[13.0721073151,50.7474708557],"type":"Point"}
}