{
  "type": "Feature",
  "properties": {
    "iso:country":"DE",
    "sg:address":"Wittenbergstr. 1",
    "sg:city":"Braunschweig",
    "sg:phone":"+49 531/697058",
    "sg:postcode":"38124",
    "sg:province":"Niedersachsen",
    "wof:name":"Rita Lambrecht",
    "wof:placetype":"venue"
},
  "geometry": {"coordinates":[10.537914,52.230713],"type":"Point"}
}