{
  "type": "Feature",
  "properties": {
    "iso:country":"DE",
    "sg:address":"Professorenweg 45",
    "sg:city":"Gie\u00dfen",
    "sg:phone":"+49 641/491491",
    "sg:postcode":"35394",
    "sg:province":"Hessen",
    "wof:name":"Hans-werner Riebel",
    "wof:placetype":"venue"
},
  "geometry": {"coordinates":[8.69435215,50.5901412964],"type":"Point"}
}