{
  "type": "Feature",
  "properties": {
    "iso:country":"DE",
    "sg:address":"An der Pockau 10",
    "sg:city":"Pockau",
    "sg:phone":"+49 37367/9307",
    "sg:postcode":"09509",
    "sg:province":"Sachsen",
    "wof:name":"Turnhalle",
    "wof:placetype":"venue"
},
  "geometry": {"coordinates":[13.2327060699,50.7034759521],"type":"Point"}
}