{
  "type": "Feature",
  "properties": {
    "iso:country":"DE",
    "sg:address":"Neuhauser Str. 16",
    "sg:city":"M\u00fcnchen",
    "sg:phone":"+49 89/263061",
    "sg:postcode":"80331",
    "sg:province":"Bayern",
    "wof:name":"Royal Reisen Gmbh",
    "wof:placetype":"venue"
},
  "geometry": {"coordinates":[11.5676689148,48.1388931274],"type":"Point"}
}