{
  "type": "Feature",
  "properties": {
    "iso:country":"DE",
    "sg:address":"Roggenweg 20 a",
    "sg:city":"K\u00f6ln",
    "sg:phone":"+49 221/4972062",
    "sg:postcode":"50933",
    "sg:province":"Nordrhein-Westfalen",
    "wof:name":"R & K Consult Gmbh",
    "wof:placetype":"venue"
},
  "geometry": {"coordinates":[6.8554120064,50.9478034973],"type":"Point"}
}