{
  "type": "Feature",
  "properties": {
    "iso:country":"DE",
    "sg:address":"Donauw\u00f6rtherstr. 31",
    "sg:city":"Gersthofen",
    "sg:phone":"+49 821/2993077",
    "sg:postcode":"86368",
    "sg:province":"Bayern",
    "wof:name":"Jugendzentrum Gersthofen",
    "wof:placetype":"venue"
},
  "geometry": {"coordinates":[10.8785057068,48.4286003113],"type":"Point"}
}