{
  "type": "Feature",
  "properties": {
    "iso:country":"DE",
    "sg:address":"Altendorfer Tor 24",
    "sg:city":"Einbeck",
    "sg:phone":"+49 5561/4515",
    "sg:postcode":"37574",
    "sg:province":"Niedersachsen",
    "wof:name":"Sauberland Textilpflege",
    "wof:placetype":"venue"
},
  "geometry": {"coordinates":[9.877348,51.814243],"type":"Point"}
}