{
  "type": "Feature",
  "properties": {
    "iso:country":"DE",
    "sg:address":"Bruchbergstr. 66",
    "sg:city":"Berg",
    "sg:phone":"+49 4972/7393470",
    "sg:postcode":"76768",
    "sg:province":"Rheinland-Pfalz",
    "wof:name":"August Berger Metallwarenfabrik Gmbh & Co Kg",
    "wof:placetype":"venue"
},
  "geometry": {"coordinates":[8.2041702271,48.9877853394],"type":"Point"}
}