{
  "type": "Feature",
  "properties": {
    "iso:country":"DE",
    "sg:address":"Willy-Lessing-Str. 16",
    "sg:city":"Bamberg",
    "sg:phone":"+49 951/980770",
    "sg:postcode":"96047",
    "sg:province":"Bayern",
    "wof:name":"Sporthaus Rauh Babette Rauh",
    "wof:placetype":"venue"
},
  "geometry": {"coordinates":[10.893482,49.893684],"type":"Point"}
}