{
  "type": "Feature",
  "properties": {
    "iso:country":"DE",
    "sg:address":"Gutjahrstr. 3b",
    "sg:city":"Dortmund",
    "sg:phone":"+49 231/459528",
    "sg:postcode":"44287",
    "sg:province":"Nordrhein-Westfalen",
    "wof:name":"Kani Gmbh",
    "wof:placetype":"venue"
},
  "geometry": {"coordinates":[7.570972,51.499569],"type":"Point"}
}