{
  "type": "Feature",
  "properties": {
    "iso:country":"DE",
    "sg:address":"Brauereiweg 4",
    "sg:city":"Buxtehude",
    "sg:postcode":"21614",
    "sg:province":"Niedersachsen",
    "wof:name":"Wernst Erste Verwaltungs Gmbh",
    "wof:placetype":"venue"
},
  "geometry": {"coordinates":[9.6863451004,53.4696617126],"type":"Point"}
}