{
  "type": "Feature",
  "properties": {
    "iso:country":"DE",
    "sg:address":"Girlitzweg 30",
    "sg:city":"K\u00f6ln",
    "sg:phone":"+49 221/9498970",
    "sg:postcode":"50829",
    "sg:province":"Nordrhein-Westfalen",
    "wof:name":"Halle Tor 2",
    "wof:placetype":"venue"
},
  "geometry": {"coordinates":[6.8792271614,50.9486122131],"type":"Point"}
}