{
  "type": "Feature",
  "properties": {
    "iso:country":"DE",
    "sg:address":"Filderbahnstr. 43",
    "sg:city":"Stuttgart",
    "sg:phone":"+49 711/716080",
    "sg:postcode":"70567",
    "sg:province":"Baden-W\u00fcrttemberg",
    "wof:name":"Hotel M\u00f6hringen",
    "wof:placetype":"venue"
},
  "geometry": {"coordinates":[9.1462659836,48.72864151],"type":"Point"}
}