{
  "type": "Feature",
  "properties": {
    "iso:country":"DE",
    "sg:address":"Hauptstr.",
    "sg:city":"Bad Teinach",
    "sg:phone":"+49 4970/538902",
    "sg:postcode":"75385",
    "sg:province":"Baden-W\u00fcrttemberg",
    "wof:name":"Raiffeisenbank Altburg Egmbh",
    "wof:placetype":"venue"
},
  "geometry": {"coordinates":[8.655495,48.68166],"type":"Point"}
}