{
  "type": "Feature",
  "properties": {
    "iso:country":"DE",
    "sg:address":"Neustr. 13",
    "sg:city":"M\u00fcnstermaifeld",
    "sg:phone":"+49 2605/952111",
    "sg:postcode":"56294",
    "sg:province":"Rheinland-Pfalz",
    "wof:name":"G\u00fcnter Hemgesberg Gmbh",
    "wof:placetype":"venue"
},
  "geometry": {"coordinates":[7.3691468239,50.2730293274],"type":"Point"}
}