{
  "type": "Feature",
  "properties": {
    "iso:country":"DE",
    "sg:address":"Michaelisstr. 3",
    "sg:city":"Leipzig",
    "sg:phone":"+49 341/5662543",
    "sg:postcode":"04105",
    "sg:province":"Sachsen",
    "wof:name":"Apotheke Am Zoo Inh. Heidrun Eckner E. K.",
    "wof:placetype":"venue"
},
  "geometry": {"coordinates":[12.375788,51.350811],"type":"Point"}
}