{
  "type": "Feature",
  "properties": {
    "iso:country":"DE",
    "sg:address":"Am Kirchberg 1",
    "sg:city":"Oberding",
    "sg:phone":"+49 8122/3262",
    "sg:postcode":"85445",
    "sg:province":"Bayern",
    "wof:name":"Johann Attenberger",
    "wof:placetype":"venue"
},
  "geometry": {"coordinates":[11.863461,48.306973],"type":"Point"}
}