{
  "type": "Feature",
  "properties": {
    "iso:country":"DE",
    "sg:address":"B\u00fcchl 30",
    "sg:city":"Waldkirchen",
    "sg:phone":"+49 8581/1588",
    "sg:postcode":"94065",
    "sg:province":"Bayern",
    "wof:name":"J\u00fcrgen Bergande",
    "wof:placetype":"venue"
},
  "geometry": {"coordinates":[13.6009702682,48.7289886475],"type":"Point"}
}