{
  "type": "Feature",
  "properties": {
    "iso:country":"DE",
    "sg:address":"B\u00fcrgermeister-Haupt-Str. 48",
    "sg:city":"Wismar",
    "sg:phone":"+49 3841/704624",
    "sg:postcode":"23966",
    "sg:province":"Mecklenburg-Vorpommern",
    "wof:name":"Dr. Gerd D\u00fchrkop",
    "wof:placetype":"venue"
},
  "geometry": {"coordinates":[11.4515008926,53.8848609924],"type":"Point"}
}