{
  "type": "Feature",
  "properties": {
    "iso:country":"DE",
    "sg:address":"Amtsbrink 37",
    "sg:city":"Stavenhagen",
    "sg:phone":"+49 39954/21265",
    "sg:postcode":"17153",
    "sg:province":"Mecklenburg-Vorpommern",
    "wof:name":"Alfred Meier",
    "wof:placetype":"venue"
},
  "geometry": {"coordinates":[12.914654,53.691811],"type":"Point"}
}