{
  "type": "Feature",
  "properties": {
    "iso:country":"DE",
    "sg:address":"Hohemarkstr. 110-116",
    "sg:city":"Oberursel",
    "sg:phone":"+49 6171/915100",
    "sg:postcode":"61440",
    "sg:province":"Hessen",
    "wof:name":"Klugkist Und Partner B\u00fcroeinrichtung Gmbh",
    "wof:placetype":"venue"
},
  "geometry": {"coordinates":[8.555403,50.214424],"type":"Point"}
}