{
  "type": "Feature",
  "properties": {
    "iso:country":"DE",
    "sg:address":"Maybachstr. 41",
    "sg:city":"L\u00f6wenstein",
    "sg:phone":"+49 7130/7842",
    "sg:postcode":"74245",
    "sg:province":"Baden-W\u00fcrttemberg",
    "wof:name":"Klaus Hammer",
    "wof:placetype":"venue"
},
  "geometry": {"coordinates":[9.3803749084,49.0945625305],"type":"Point"}
}