{
  "type": "Feature",
  "properties": {
    "iso:country":"DE",
    "sg:address":"Duisburger Str. 35",
    "sg:city":"Braunschweig",
    "sg:phone":"+49 531/371450",
    "sg:postcode":"38108",
    "sg:province":"Niedersachsen",
    "wof:name":"H. Peter",
    "wof:placetype":"venue"
},
  "geometry": {"coordinates":[10.553188,52.288853],"type":"Point"}
}