{
  "type": "Feature",
  "properties": {
    "iso:country":"DE",
    "sg:address":"Zelchstr. 4",
    "sg:city":"M\u00fcnchberg",
    "sg:phone":"+49 9251/1341",
    "sg:postcode":"95213",
    "sg:province":"Bayern",
    "wof:name":"W. Flach",
    "wof:placetype":"venue"
},
  "geometry": {"coordinates":[11.7917070389,50.1909179688],"type":"Point"}
}