{
  "type": "Feature",
  "properties": {
    "iso:country":"DE",
    "sg:address":"Konstanzer Str. 20",
    "sg:city":"Heidelberg",
    "sg:phone":"+49 6221/375777",
    "sg:postcode":"69126",
    "sg:province":"Baden-W\u00fcrttemberg",
    "wof:name":"Renate Rehn",
    "wof:placetype":"venue"
},
  "geometry": {"coordinates":[8.684716,49.372795],"type":"Point"}
}