{
  "type": "Feature",
  "properties": {
    "iso:country":"DE",
    "sg:address":"Kastanienweg 32",
    "sg:city":"Eschenburg",
    "sg:phone":"+49 2774/6032",
    "sg:postcode":"35713",
    "sg:province":"Hessen",
    "wof:name":"Udo Weber Architekt",
    "wof:placetype":"venue"
},
  "geometry": {"coordinates":[8.31617,50.788338],"type":"Point"}
}