{
  "type": "Feature",
  "properties": {
    "iso:country":"DE",
    "sg:address":"Am Hinterrot 2",
    "sg:city":"Hemsbach",
    "sg:phone":"+49 4962/017720",
    "sg:postcode":"69502",
    "sg:province":"Baden-W\u00fcrttemberg",
    "wof:name":"Pagina Media Gmbh",
    "wof:placetype":"venue"
},
  "geometry": {"coordinates":[8.64585495,49.5949325562],"type":"Point"}
}