{
  "type": "Feature",
  "properties": {
    "iso:country":"DE",
    "sg:address":"Neuer Kamp 2",
    "sg:city":"Kellinghusen",
    "sg:phone":"+49 4822/9267",
    "sg:postcode":"25548",
    "sg:province":"Schleswig-Holstein",
    "wof:name":"S. Thie\u00df",
    "wof:placetype":"venue"
},
  "geometry": {"coordinates":[9.72425,53.941261],"type":"Point"}
}