{
  "type": "Feature",
  "properties": {
    "iso:country":"DE",
    "sg:address":"Gauersheimer Str. 1",
    "sg:city":"Ilbesheim",
    "sg:phone":"+49 6355/2169",
    "sg:postcode":"67294",
    "sg:province":"Rheinland-Pfalz",
    "wof:name":"Otto Walldorf",
    "wof:placetype":"venue"
},
  "geometry": {"coordinates":[8.07756,49.688728],"type":"Point"}
}