{
  "type": "Feature",
  "properties": {
    "iso:country":"DE",
    "sg:address":"Alban-Dold-Str. 3",
    "sg:city":"Villingen-Schwenningen",
    "sg:phone":"+49 7721/54667",
    "sg:postcode":"78050",
    "sg:province":"Baden-W\u00fcrttemberg",
    "wof:name":"Siegfried Stockburger",
    "wof:placetype":"venue"
},
  "geometry": {"coordinates":[8.4367837906,48.0589828491],"type":"Point"}
}