{
  "type": "Feature",
  "properties": {
    "iso:country":"DE",
    "sg:address":"Hussenstr. 9",
    "sg:city":"Konstanz",
    "sg:phone":"+49 4975/3121201",
    "sg:postcode":"78462",
    "sg:province":"Baden-W\u00fcrttemberg",
    "wof:name":"Optiker Claudius",
    "wof:placetype":"venue"
},
  "geometry": {"coordinates":[9.1729888916,47.6602554321],"type":"Point"}
}