{
  "type": "Feature",
  "properties": {
    "iso:country":"DE",
    "sg:address":"Trift 100",
    "sg:city":"Krefeld",
    "sg:phone":"+49 2151/541895",
    "sg:postcode":"47809",
    "sg:province":"Nordrhein-Westfalen",
    "wof:name":"Bernhard Hohaus",
    "wof:placetype":"venue"
},
  "geometry": {"coordinates":[6.599796772,51.3289642334],"type":"Point"}
}