{
  "type": "Feature",
  "properties": {
    "iso:country":"DE",
    "sg:address":"Kleiberstr. 11",
    "sg:city":"Erlangen",
    "sg:phone":"+49 9135/728258",
    "sg:postcode":"91056",
    "sg:province":"Bayern",
    "wof:name":"Hans Gumbrecht Inh. G\u00fcnther Wietoska",
    "wof:placetype":"venue"
},
  "geometry": {"coordinates":[10.934425,49.632473],"type":"Point"}
}