{
  "type": "Feature",
  "properties": {
    "iso:country":"DE",
    "sg:address":"Heilbronner Str. 180",
    "sg:city":"Stuttgart",
    "sg:phone":"+49 711/1656260",
    "sg:postcode":"70191",
    "sg:province":"Baden-W\u00fcrttemberg",
    "wof:name":"Albert-maier-stiftung",
    "wof:placetype":"venue"
},
  "geometry": {"coordinates":[9.1835250854,48.8022651672],"type":"Point"}
}