{
  "type": "Feature",
  "properties": {
    "iso:country":"DE",
    "sg:address":"Schmiedstr. 20",
    "sg:city":"Weilheim",
    "sg:phone":"+49 881/3411",
    "sg:postcode":"82362",
    "sg:province":"Bayern",
    "wof:name":"G\u00fcnther Rein Rechtsanwalt",
    "wof:placetype":"venue"
},
  "geometry": {"coordinates":[11.1420841217,47.8405952454],"type":"Point"}
}