{
  "type": "Feature",
  "properties": {
    "iso:country":"DE",
    "sg:address":"Podbielskistr. 311",
    "sg:city":"Hannover",
    "sg:phone":"+49 511/6477747",
    "sg:postcode":"30659",
    "sg:province":"Niedersachsen",
    "wof:name":"Gerhild Und Helmut Bruns",
    "wof:placetype":"venue"
},
  "geometry": {"coordinates":[9.79906,52.40604],"type":"Point"}
}