{
  "type": "Feature",
  "properties": {
    "iso:country":"DE",
    "sg:address":"Konrad-Adenauer-Str. 96",
    "sg:city":"Geilenkirchen",
    "sg:phone":"+49 2451/2877",
    "sg:postcode":"52511",
    "sg:province":"Nordrhein-Westfalen",
    "wof:name":"H. Franzen Haus- Und K\u00fcchenger\u00e4te",
    "wof:placetype":"venue"
},
  "geometry": {"coordinates":[6.1236848831,50.9627914429],"type":"Point"}
}