{
  "type": "Feature",
  "properties": {
    "iso:country":"DE",
    "sg:address":"Gottfried-H\u00f6tzel-Str. 2",
    "sg:city":"D\u00fcsseldorf",
    "sg:phone":"+49 211/502291",
    "sg:postcode":"40549",
    "sg:province":"Nordrhein-Westfalen",
    "wof:name":"Ev. Pfarramt Ii Heerdt",
    "wof:placetype":"venue"
},
  "geometry": {"coordinates":[6.7040791512,51.2310905457],"type":"Point"}
}