{
  "type": "Feature",
  "properties": {
    "iso:country":"DE",
    "sg:address":"Holunderweg 26",
    "sg:city":"Berlin",
    "sg:phone":"+49 30/3367982",
    "sg:postcode":"13587",
    "sg:province":"Berlin",
    "wof:name":"Gurski Heilpraktikerin",
    "wof:placetype":"venue"
},
  "geometry": {"coordinates":[13.2087745667,52.5684051514],"type":"Point"}
}