{
  "type": "Feature",
  "properties": {
    "iso:country":"DE",
    "sg:address":"Weierter Str. 12",
    "sg:city":"Neunkirchen-Seelscheid",
    "sg:phone":"+49 2247/69732",
    "sg:postcode":"53819",
    "sg:province":"Nordrhein-Westfalen",
    "wof:name":"Lorenz Schmidt",
    "wof:placetype":"venue"
},
  "geometry": {"coordinates":[7.3354787827,50.8979225159],"type":"Point"}
}