{
  "type": "Feature",
  "properties": {
    "iso:country":"DE",
    "sg:address":"M\u00fchlwiesenweg 22",
    "sg:city":"Alsfeld",
    "sg:phone":"+49 6639/767",
    "sg:postcode":"36304",
    "sg:province":"Hessen",
    "wof:name":"H.-p. Schwalm",
    "wof:placetype":"venue"
},
  "geometry": {"coordinates":[9.361153,50.772087],"type":"Point"}
}