{
  "type": "Feature",
  "properties": {
    "iso:country":"DE",
    "sg:address":"Langenstr. 6-8",
    "sg:city":"Bremen",
    "sg:phone":"+49 421/325317",
    "sg:postcode":"28195",
    "sg:province":"Bremen",
    "wof:name":"M\u00f6bel-th\u00e4te August Th\u00e4te Gmbh & Co.",
    "wof:placetype":"venue"
},
  "geometry": {"coordinates":[8.805744,53.075974],"type":"Point"}
}