{
  "type": "Feature",
  "properties": {
    "iso:country":"DE",
    "sg:address":"Horpestr. 32",
    "sg:city":"Engelskirchen",
    "sg:phone":"+49 2263/4261",
    "sg:postcode":"51766",
    "sg:province":"Nordrhein-Westfalen",
    "wof:name":"Dr. P. Galuszka Rechtsanwalt",
    "wof:placetype":"venue"
},
  "geometry": {"coordinates":[7.4059500694,50.9907913208],"type":"Point"}
}