{
  "type": "Feature",
  "properties": {
    "iso:country":"DE",
    "sg:address":"Pivitsheider Str. 30",
    "sg:city":"Augustdorf",
    "sg:phone":"+49 5237/7640",
    "sg:postcode":"32832",
    "sg:province":"Nordrhein-Westfalen",
    "wof:name":"Kronengrill",
    "wof:placetype":"venue"
},
  "geometry": {"coordinates":[8.7402963638,51.9087562561],"type":"Point"}
}