{
  "type": "Feature",
  "properties": {
    "iso:country":"DE",
    "sg:address":"Lindenschmitstr. 45",
    "sg:city":"M\u00fcnchen",
    "sg:phone":"+49 89/774865",
    "sg:postcode":"81371",
    "sg:province":"Bayern",
    "wof:name":"C. Caspari Kunstmaler",
    "wof:placetype":"venue"
},
  "geometry": {"coordinates":[11.539315,48.118156],"type":"Point"}
}