{
  "type": "Feature",
  "properties": {
    "iso:country":"DE",
    "sg:address":"Karl-Pfund-Weg 5",
    "sg:city":"Lenggries",
    "sg:phone":"+49 8042/2444",
    "sg:postcode":"83661",
    "sg:province":"Bayern",
    "wof:name":"Gottfried Baumgartner",
    "wof:placetype":"venue"
},
  "geometry": {"coordinates":[11.5756835938,47.6825523376],"type":"Point"}
}