{
  "type": "Feature",
  "properties": {
    "iso:country":"DE",
    "sg:address":"Alte Dorfstr. 2",
    "sg:city":"Nottensdorf",
    "sg:phone":"+49 4163/2377",
    "sg:postcode":"21640",
    "sg:province":"Niedersachsen",
    "wof:name":"Pension Alpers",
    "wof:placetype":"venue"
},
  "geometry": {"coordinates":[9.6032752991,53.4852142334],"type":"Point"}
}