{
  "type": "Feature",
  "properties": {
    "iso:country":"DE",
    "sg:address":"Gr\u00fcneburgweg 124",
    "sg:city":"Frankfurt",
    "sg:phone":"+49 69/5974056",
    "sg:postcode":"60323",
    "sg:province":"Hessen",
    "wof:name":"Gunther Rohrer Lederschutzartikel",
    "wof:placetype":"venue"
},
  "geometry": {"coordinates":[8.662554,50.123367],"type":"Point"}
}