{
  "type": "Feature",
  "properties": {
    "iso:country":"DE",
    "sg:address":"Friedhofstr. 11",
    "sg:city":"Langenfeld",
    "sg:phone":"+49 2173/98445",
    "sg:postcode":"40764",
    "sg:province":"Nordrhein-Westfalen",
    "wof:name":"Reiseb\u00fcro Hebbel Gmbh",
    "wof:placetype":"venue"
},
  "geometry": {"coordinates":[10.2088975906,50.787815094],"type":"Point"}
}