{
  "type": "Feature",
  "properties": {
    "iso:country":"DE",
    "sg:address":"Westring 102",
    "sg:city":"Herne",
    "sg:phone":"+49 2323/12585",
    "sg:postcode":"44623",
    "sg:province":"Nordrhein-Westfalen",
    "wof:name":"Deutsche Shell Ag",
    "wof:placetype":"venue"
},
  "geometry": {"coordinates":[7.2181048393,51.5388908386],"type":"Point"}
}