{
  "type": "Feature",
  "properties": {
    "iso:country":"DE",
    "sg:address":"Adlerstr. 1",
    "sg:city":"Herborn",
    "sg:phone":"+49 2772/63811",
    "sg:postcode":"35745",
    "sg:province":"Hessen",
    "wof:name":"Menger Planungs Gmbh",
    "wof:placetype":"venue"
},
  "geometry": {"coordinates":[8.3399963379,50.7039871216],"type":"Point"}
}