{
  "type": "Feature",
  "properties": {
    "iso:country":"DE",
    "sg:address":"Klebingerstr. 1",
    "sg:city":"Freilassing",
    "sg:phone":"+49 8654/64770",
    "sg:postcode":"83395",
    "sg:province":"Bayern",
    "wof:name":"W. Winter Heiz\u00f6l",
    "wof:placetype":"venue"
},
  "geometry": {"coordinates":[12.9666509628,47.84532547],"type":"Point"}
}