{
  "type": "Feature",
  "properties": {
    "iso:country":"DE",
    "sg:address":"Klosterstr. 62",
    "sg:city":"Frechen",
    "sg:phone":"+49 2234/31334",
    "sg:postcode":"50226",
    "sg:province":"Nordrhein-Westfalen",
    "wof:name":"M\u00fchlenbach-video",
    "wof:placetype":"venue"
},
  "geometry": {"coordinates":[6.7495961189,50.9118232727],"type":"Point"}
}