{
  "type": "Feature",
  "properties": {
    "iso:country":"DE",
    "sg:address":"M\u00fchlenweg 32",
    "sg:city":"Zwickau",
    "sg:phone":"+49 375/7788974",
    "sg:postcode":"08064",
    "sg:province":"Sachsen",
    "wof:name":"Kauer - Bau Gmbh",
    "wof:placetype":"venue"
},
  "geometry": {"coordinates":[12.4771203995,50.6641998291],"type":"Point"}
}