{
  "type": "Feature",
  "properties": {
    "iso:country":"DE",
    "sg:address":"Kohlenweg 18",
    "sg:city":"Stadthagen",
    "sg:phone":"+49 5721/4101",
    "sg:postcode":"31655",
    "sg:province":"Niedersachsen",
    "wof:name":"Gerhard B\u00fcthe Elektromeister",
    "wof:placetype":"venue"
},
  "geometry": {"coordinates":[9.210148,52.297009],"type":"Point"}
}