{
  "type": "Feature",
  "properties": {
    "iso:country":"DE",
    "sg:address":"Bahnhofstr. 8",
    "sg:city":"Bruckm\u00fchl",
    "sg:phone":"+49 8062/1373",
    "sg:postcode":"83052",
    "sg:province":"Bayern",
    "wof:name":"Ludwig Schmid",
    "wof:placetype":"venue"
},
  "geometry": {"coordinates":[11.915271759,47.8816184998],"type":"Point"}
}