{
  "type": "Feature",
  "properties": {
    "iso:country":"DE",
    "sg:address":"kaldenkirchener str. 16",
    "sg:city":"br\u00fcggen",
    "sg:phone":"+49 2157/909994",
    "sg:postcode":"41379",
    "sg:province":"Nordrhein-Westfalen",
    "wof:name":"Paedco Medien Br\u00fcggen",
    "wof:placetype":"venue"
},
  "geometry": {"coordinates":[6.195718,51.286152],"type":"Point"}
}