{
  "type": "Feature",
  "properties": {
    "iso:country":"DE",
    "sg:address":"Kantstr. 73",
    "sg:city":"Leingarten",
    "sg:phone":"+49 7131/401670",
    "sg:postcode":"74211",
    "sg:province":"Baden-W\u00fcrttemberg",
    "wof:name":"Hermann K\u00fchner Rechtsanwalt",
    "wof:placetype":"venue"
},
  "geometry": {"coordinates":[9.1113376617,49.141254425],"type":"Point"}
}