{
  "type": "Feature",
  "properties": {
    "iso:country":"DE",
    "sg:address":"K\u00f6nigsturmstr. 40",
    "sg:city":"Schw\u00e4bisch Gm\u00fcnd",
    "sg:phone":"+49 7171/67483",
    "sg:postcode":"73525",
    "sg:province":"Baden-W\u00fcrttemberg",
    "wof:name":"Josef Str\u00f6bele Rechtsanwalt",
    "wof:placetype":"venue"
},
  "geometry": {"coordinates":[9.8036155701,48.8006019592],"type":"Point"}
}