{
  "type": "Feature",
  "properties": {
    "iso:country":"DE",
    "sg:address":"Trakehner Str. 30",
    "sg:city":"Verl",
    "sg:phone":"+49 5246/83605",
    "sg:postcode":"33415",
    "sg:province":"Nordrhein-Westfalen",
    "wof:name":"Schulenberg Gmbh & Co. Kg",
    "wof:placetype":"venue"
},
  "geometry": {"coordinates":[8.458344,51.892941],"type":"Point"}
}