{
  "type": "Feature",
  "properties": {
    "iso:country":"DE",
    "sg:address":"Nu\u00dfbaumer Stra\u00dfe 19",
    "sg:city":"Bergisch Gladbach",
    "sg:phone":"+49 2202/955200",
    "sg:postcode":"51469",
    "sg:province":"Nordrhein-Westfalen",
    "wof:name":"Comcept Gmbh",
    "wof:placetype":"venue"
},
  "geometry": {"coordinates":[7.10012,51.000069],"type":"Point"}
}