{
  "type": "Feature",
  "properties": {
    "iso:country":"DE",
    "sg:address":"Professor-Mader-Str. 17",
    "sg:city":"Gro\u00dflangheim",
    "sg:phone":"+49 9325/1039",
    "sg:postcode":"97320",
    "sg:province":"Bayern",
    "wof:name":"A. Hetterich Ingenieur",
    "wof:placetype":"venue"
},
  "geometry": {"coordinates":[10.241109848,49.7587432861],"type":"Point"}
}