{
  "type": "Feature",
  "properties": {
    "iso:country":"DE",
    "sg:address":"Industriestr. 35",
    "sg:city":"Meckesheim",
    "sg:phone":"+49 6226/3114",
    "sg:postcode":"74909",
    "sg:province":"Baden-W\u00fcrttemberg",
    "wof:name":"Hans Dellinger",
    "wof:placetype":"venue"
},
  "geometry": {"coordinates":[8.8093690872,49.3236503601],"type":"Point"}
}