{
  "type": "Feature",
  "properties": {
    "iso:country":"DE",
    "sg:address":"Tuchmachergasse 3 A",
    "sg:city":"Stuttgart",
    "sg:phone":"+49 711/562531",
    "sg:postcode":"70372",
    "sg:province":"Baden-W\u00fcrttemberg",
    "wof:name":"Eberhard R\u00fcdt",
    "wof:placetype":"venue"
},
  "geometry": {"coordinates":[9.2168054581,48.8044319153],"type":"Point"}
}