{
  "type": "Feature",
  "properties": {
    "iso:country":"DE",
    "sg:address":"Gewerbering 1",
    "sg:city":"Linkenheim-Hochstetten",
    "sg:phone":"+49 7247/93810",
    "sg:postcode":"76351",
    "sg:province":"Baden-W\u00fcrttemberg",
    "wof:name":"Kother Gmbh",
    "wof:placetype":"venue"
},
  "geometry": {"coordinates":[8.410814,49.143414],"type":"Point"}
}