{
  "type": "Feature",
  "properties": {
    "iso:country":"DE",
    "sg:address":"Am Hirzrain 8",
    "sg:city":"Flieden",
    "sg:postcode":"36103",
    "sg:province":"Hessen",
    "wof:name":"Ips Informations- Und Planungssysteme Gmbh",
    "wof:placetype":"venue"
},
  "geometry": {"coordinates":[9.5134620667,50.4273910522],"type":"Point"}
}