{
  "type": "Feature",
  "properties": {
    "iso:country":"DE",
    "sg:address":"H\u00f6rsterstr. 10",
    "sg:city":"M\u00fcnster",
    "sg:phone":"+49 251/4841448",
    "sg:postcode":"48143",
    "sg:province":"Nordrhein-Westfalen",
    "wof:name":"Pasadena",
    "wof:placetype":"venue"
},
  "geometry": {"coordinates":[7.6303992271,51.9646453857],"type":"Point"}
}