{
  "type": "Feature",
  "properties": {
    "iso:country":"DE",
    "sg:address":"Gustav-Freytagstr. 13",
    "sg:city":"Oelde",
    "sg:phone":"+49 2522",
    "sg:postcode":"59302",
    "sg:province":"Nordrhein-Westfalen",
    "wof:name":"Seppcom Pc- Dienstleistung Rund Um Den Pc",
    "wof:placetype":"venue"
},
  "geometry": {"coordinates":[8.15919,51.837906],"type":"Point"}
}