{
  "type": "Feature",
  "properties": {
    "iso:country":"DE",
    "sg:address":"Oberer Weg 47",
    "sg:city":"Alpirsbach",
    "sg:phone":"+49 7444/2279",
    "sg:postcode":"72275",
    "sg:province":"Baden-W\u00fcrttemberg",
    "wof:name":"Karl Heinzelmann",
    "wof:placetype":"venue"
},
  "geometry": {"coordinates":[8.39589,48.336815],"type":"Point"}
}