{
  "type": "Feature",
  "properties": {
    "iso:country":"DE",
    "sg:address":"Feldstr. 31",
    "sg:city":"Hessisch Oldendorf",
    "sg:phone":"+49 5152/2677",
    "sg:postcode":"31840",
    "sg:province":"Niedersachsen",
    "wof:name":"Walter Vogt",
    "wof:placetype":"venue"
},
  "geometry": {"coordinates":[9.2287883759,52.1752815247],"type":"Point"}
}