{
  "type": "Feature",
  "properties": {
    "iso:country":"DE",
    "sg:address":"Mallwitzstr. 12",
    "sg:city":"Bonn",
    "sg:phone":"+49 228/943310",
    "sg:postcode":"53177",
    "sg:province":"Nordrhein-Westfalen",
    "wof:name":"Kolb Gmbh",
    "wof:placetype":"venue"
},
  "geometry": {"coordinates":[7.175215,50.66798],"type":"Point"}
}