{
  "type": "Feature",
  "properties": {
    "iso:country":"DE",
    "sg:address":"Darmst\u00e4dter Str. 62",
    "sg:city":"B\u00fcttelborn",
    "sg:phone":"+49 6152/54005",
    "sg:postcode":"64572",
    "sg:province":"Hessen",
    "wof:name":"Emig & Schimpf Gbr",
    "wof:placetype":"venue"
},
  "geometry": {"coordinates":[8.5211267471,49.8991775513],"type":"Point"}
}