{
  "type": "Feature",
  "properties": {
    "iso:country":"DE",
    "sg:address":"Leitengasse 2",
    "sg:city":"Weiding",
    "sg:phone":"+49 9971/6337",
    "sg:postcode":"93495",
    "sg:province":"Bayern",
    "wof:name":"Michael Staudner",
    "wof:placetype":"venue"
},
  "geometry": {"coordinates":[12.72461,49.267731],"type":"Point"}
}