{
  "type": "Feature",
  "properties": {
    "iso:country":"DE",
    "sg:address":"Georg-R\u00fcmpler-Weg 1",
    "sg:city":"Leisnig",
    "sg:postcode":"04703",
    "sg:province":"Sachsen",
    "wof:name":"Kraftfahrzeuginstandhaltungs Gmbh",
    "wof:placetype":"venue"
},
  "geometry": {"coordinates":[12.9271116257,51.1503562927],"type":"Point"}
}