{
  "type": "Feature",
  "properties": {
    "iso:country":"DE",
    "sg:address":"Herzog-Otto-Str. 18",
    "sg:city":"Schifferstadt",
    "sg:phone":"+49 6235/6600",
    "sg:postcode":"67105",
    "sg:province":"Rheinland-Pfalz",
    "wof:name":"Helmut Scharnagl",
    "wof:placetype":"venue"
},
  "geometry": {"coordinates":[8.3835659027,49.3722572327],"type":"Point"}
}