{
  "type": "Feature",
  "properties": {
    "iso:country":"DE",
    "sg:address":"Am Fr\u00fchscheid 4",
    "sg:city":"Linz",
    "sg:phone":"+49 2644/2228",
    "sg:postcode":"53545",
    "sg:province":"Rheinland-Pfalz",
    "wof:name":"Karl Bungart",
    "wof:placetype":"venue"
},
  "geometry": {"coordinates":[7.3034110069,50.569896698],"type":"Point"}
}