{
  "type": "Feature",
  "properties": {
    "iso:country":"DE",
    "sg:address":"Pestalozzistr. 11",
    "sg:city":"Vetschau",
    "sg:phone":"+49 35433/2688",
    "sg:postcode":"03226",
    "sg:province":"Brandenburg",
    "wof:name":"Vetschauer Wohnungsgenossenschaft Eg",
    "wof:placetype":"venue"
},
  "geometry": {"coordinates":[14.0882196426,51.7847862244],"type":"Point"}
}