{
  "type": "Feature",
  "properties": {
    "iso:country":"DE",
    "sg:address":"Lange Str. 15 a",
    "sg:city":"Geyer",
    "sg:phone":"+49 37346/6146",
    "sg:postcode":"09468",
    "sg:province":"Sachsen",
    "wof:name":"Berthold Peter",
    "wof:placetype":"venue"
},
  "geometry": {"coordinates":[12.9158773422,50.6278419495],"type":"Point"}
}