{
  "type": "Feature",
  "properties": {
    "iso:country":"DE",
    "sg:address":"Schweinsdorfer Str. 25 B",
    "sg:city":"Rothenburg",
    "sg:phone":"+49 9861/933310",
    "sg:postcode":"91541",
    "sg:province":"Bayern",
    "wof:name":"Molkerei Bistro Musikcafe",
    "wof:placetype":"venue"
},
  "geometry": {"coordinates":[10.1883916855,49.3808135986],"type":"Point"}
}