{
  "type": "Feature",
  "properties": {
    "iso:country":"DE",
    "sg:address":"Mutzer Str. 111",
    "sg:city":"Bergisch Gladbach",
    "sg:phone":"+49 2202/951524",
    "sg:postcode":"51467",
    "sg:province":"Nordrhein-Westfalen",
    "wof:name":"Dietmar Becher",
    "wof:placetype":"venue"
},
  "geometry": {"coordinates":[7.1228680611,51.0109367371],"type":"Point"}
}