{
  "type": "Feature",
  "properties": {
    "iso:country":"DE",
    "sg:address":"Adalbert-Stifter-Str. 1",
    "sg:city":"Eppelheim",
    "sg:phone":"+49 6221/767965",
    "sg:postcode":"69214",
    "sg:province":"Baden-W\u00fcrttemberg",
    "wof:name":"G. Und H. Schuhmacher Transport Gmbh",
    "wof:placetype":"venue"
},
  "geometry": {"coordinates":[8.628610611,49.4033889771],"type":"Point"}
}