{
  "type": "Feature",
  "properties": {
    "iso:country":"DE",
    "sg:address":"Spindlerweg 1",
    "sg:city":"Arberg",
    "sg:phone":"+49 9822/7453",
    "sg:postcode":"91722",
    "sg:province":"Bayern",
    "wof:name":"Konrad Ertl",
    "wof:placetype":"venue"
},
  "geometry": {"coordinates":[10.618242,49.142235],"type":"Point"}
}