{
  "type": "Feature",
  "properties": {
    "iso:country":"DE",
    "sg:address":"Westpreu\u00dfenstr. 14",
    "sg:city":"Lehrte",
    "sg:phone":"+49 5132/86930",
    "sg:postcode":"31275",
    "sg:province":"Niedersachsen",
    "wof:name":"Van Den Berg-w\u00f6bke Zahlungs- Verkehrssysteme Gmbh",
    "wof:placetype":"venue"
},
  "geometry": {"coordinates":[9.9062166214,52.3699111938],"type":"Point"}
}