{
  "type": "Feature",
  "properties": {
    "iso:country":"DE",
    "sg:address":"Westerfeld",
    "sg:city":"Brodersby",
    "sg:phone":"+49 4644/310",
    "sg:postcode":"24398",
    "sg:province":"Schleswig-Holstein",
    "wof:name":"Johannes Wieck",
    "wof:placetype":"venue"
},
  "geometry": {"coordinates":[9.972144,54.628651],"type":"Point"}
}