{
  "type": "Feature",
  "properties": {
    "iso:country":"DE",
    "sg:address":"Pestalozzistr. 78 A",
    "sg:city":"D\u00fcsseldorf",
    "sg:postcode":"40549",
    "sg:province":"Nordrhein-Westfalen",
    "wof:name":"Lignum Beteiligungs-gmbh",
    "wof:placetype":"venue"
},
  "geometry": {"coordinates":[6.718608,51.228855],"type":"Point"}
}