{
  "type": "Feature",
  "properties": {
    "iso:country":"DE",
    "sg:address":"Caspar-Fischer-Str. 13",
    "sg:city":"Kulmbach",
    "sg:phone":"+49 9221/3719",
    "sg:postcode":"95326",
    "sg:province":"Bayern",
    "wof:name":"Wunderlich Ohg",
    "wof:placetype":"venue"
},
  "geometry": {"coordinates":[11.466256,50.114704],"type":"Point"}
}