{
  "type": "Feature",
  "properties": {
    "iso:country":"DE",
    "sg:address":"Bahnhofstr. 42",
    "sg:city":"Helmstadt-Bargen",
    "sg:postcode":"74921",
    "sg:province":"Baden-W\u00fcrttemberg",
    "wof:name":"Edward Leber",
    "wof:placetype":"venue"
},
  "geometry": {"coordinates":[8.9734296799,49.3194084167],"type":"Point"}
}