{
  "type": "Feature",
  "properties": {
    "iso:country":"DE",
    "sg:address":"Hamburger Str. 158",
    "sg:city":"Ahrensburg",
    "sg:phone":"+49 4102/53147",
    "sg:postcode":"22926",
    "sg:province":"Schleswig-Holstein",
    "wof:name":"Restaurant Akropolis",
    "wof:placetype":"venue"
},
  "geometry": {"coordinates":[10.2209939957,53.6641616821],"type":"Point"}
}