{
  "type": "Feature",
  "properties": {
    "iso:country":"DE",
    "sg:address":"Kreisstr. 15",
    "sg:city":"Dortmund",
    "sg:phone":"+49 2304/80426",
    "sg:postcode":"44267",
    "sg:province":"Nordrhein-Westfalen",
    "wof:name":"M. Schnettker",
    "wof:placetype":"venue"
},
  "geometry": {"coordinates":[7.5306959152,51.4439125061],"type":"Point"}
}