{
  "type": "Feature",
  "properties": {
    "iso:country":"DE",
    "sg:address":"M\u00fchlg\u00e4\u00dfle 2",
    "sg:city":"Wain",
    "sg:phone":"+49 7353/3466",
    "sg:postcode":"88489",
    "sg:province":"Baden-W\u00fcrttemberg",
    "wof:name":"Joachim Staigmiller",
    "wof:placetype":"venue"
},
  "geometry": {"coordinates":[10.019464,48.191425],"type":"Point"}
}