{
  "type": "Feature",
  "properties": {
    "iso:country":"DE",
    "sg:address":"Richard-Wagner-Str. 5",
    "sg:city":"Bad F\u00fcssing",
    "sg:phone":"+49 8531/21481",
    "sg:postcode":"94072",
    "sg:province":"Bayern",
    "wof:name":"G. Gessner Masseur",
    "wof:placetype":"venue"
},
  "geometry": {"coordinates":[13.317539,48.34959],"type":"Point"}
}