{
  "type": "Feature",
  "properties": {
    "iso:country":"DE",
    "sg:address":"Hermann-Bohnstedt-Str. 7",
    "sg:city":"Zossen",
    "sg:phone":"+49 3377/334336",
    "sg:postcode":"15806",
    "sg:province":"Brandenburg",
    "wof:name":"Werner Steinberg",
    "wof:placetype":"venue"
},
  "geometry": {"coordinates":[13.44562,52.235252],"type":"Point"}
}