{
  "type": "Feature",
  "properties": {
    "iso:country":"DE",
    "sg:address":"Wiesentalstr. 2",
    "sg:city":"Freiburg",
    "sg:phone":"+49 761/445505",
    "sg:postcode":"79115",
    "sg:province":"Baden-W\u00fcrttemberg",
    "wof:name":"Wiehre 04",
    "wof:placetype":"venue"
},
  "geometry": {"coordinates":[7.8195319176,47.9832649231],"type":"Point"}
}