{
  "type": "Feature",
  "properties": {
    "iso:country":"DE",
    "sg:address":"K\u00f6lnstr. 12",
    "sg:city":"Br\u00fchl",
    "sg:phone":"+49 2232/42524",
    "sg:postcode":"50321",
    "sg:province":"Nordrhein-Westfalen",
    "wof:name":"Paul D\u00fcster Ohg",
    "wof:placetype":"venue"
},
  "geometry": {"coordinates":[6.9054398537,50.8301391602],"type":"Point"}
}