{
  "type": "Feature",
  "properties": {
    "iso:country":"DE",
    "sg:address":"Freib\u00fcrgleweg 10",
    "sg:city":"Konstanz",
    "sg:phone":"+49 7531/77183",
    "sg:postcode":"78467",
    "sg:province":"Baden-W\u00fcrttemberg",
    "wof:name":"Siegfried Pauer",
    "wof:placetype":"venue"
},
  "geometry": {"coordinates":[9.154187,47.684101],"type":"Point"}
}