{
  "type": "Feature",
  "properties": {
    "iso:country":"DE",
    "sg:address":"Ludwigstr. 11",
    "sg:city":"Rudolstadt",
    "sg:phone":"+49 3672/411788",
    "sg:postcode":"07407",
    "sg:province":"Th\u00fcringen",
    "wof:name":"B. Fischer",
    "wof:placetype":"venue"
},
  "geometry": {"coordinates":[11.3436479568,50.7212371826],"type":"Point"}
}