{
  "type": "Feature",
  "properties": {
    "iso:country":"DE",
    "sg:address":"Marienstr. 14",
    "sg:city":"Damme",
    "sg:phone":"+49 5491/2103",
    "sg:postcode":"49401",
    "sg:province":"Niedersachsen",
    "wof:name":"M. Meyer-wessel Hebamme",
    "wof:placetype":"venue"
},
  "geometry": {"coordinates":[8.197528,52.5238],"type":"Point"}
}