{
  "type": "Feature",
  "properties": {
    "iso:country":"DE",
    "sg:address":"Zittauer Str. 02",
    "sg:city":"Hirschfelde",
    "sg:phone":"+49 35843/79020",
    "sg:postcode":"02788",
    "sg:province":"Sachsen",
    "wof:name":"Helga F\u00f6rster",
    "wof:placetype":"venue"
},
  "geometry": {"coordinates":[14.888075,50.945278],"type":"Point"}
}