{
  "type": "Feature",
  "properties": {
    "iso:country":"DE",
    "sg:address":"Unterstr. 8",
    "sg:city":"Warburg",
    "sg:phone":"+49 4956/4190090",
    "sg:postcode":"34414",
    "sg:province":"Nordrhein-Westfalen",
    "wof:name":"Sparkasse H\u00f6xter",
    "wof:placetype":"venue"
},
  "geometry": {"coordinates":[9.152028,51.488762],"type":"Point"}
}