{
  "type": "Feature",
  "properties": {
    "iso:country":"DE",
    "sg:address":"Saalfelder Weg 20",
    "sg:city":"D\u00fcsseldorf",
    "sg:phone":"+49 211/9262626",
    "sg:postcode":"40627",
    "sg:province":"Nordrhein-Westfalen",
    "wof:name":"Wilhelm Haverkamp",
    "wof:placetype":"venue"
},
  "geometry": {"coordinates":[6.859582901,51.216381073],"type":"Point"}
}