{
  "type": "Feature",
  "properties": {
    "iso:country":"DE",
    "sg:address":"Helweg 13",
    "sg:city":"Berlin",
    "sg:phone":"+49 30/4011048",
    "sg:postcode":"13465",
    "sg:province":"Berlin",
    "wof:name":"Edgar Wilhelm Steuerberater",
    "wof:placetype":"venue"
},
  "geometry": {"coordinates":[13.2647285461,52.6282157898],"type":"Point"}
}