{
  "type": "Feature",
  "properties": {
    "iso:country":"DE",
    "sg:address":"Im Schwarzenborn 1",
    "sg:city":"Marburg",
    "sg:postcode":"35041",
    "sg:province":"Hessen",
    "wof:name":"Dr. H. K. M\u00fcller Steuerberater",
    "wof:placetype":"venue"
},
  "geometry": {"coordinates":[8.7566556931,50.8365745544],"type":"Point"}
}