{
  "type": "Feature",
  "properties": {
    "iso:country":"DE",
    "sg:address":"Schellhorner Str. 29",
    "sg:city":"Preetz",
    "sg:phone":"+49 4342/83828",
    "sg:postcode":"24211",
    "sg:province":"Schleswig-Holstein",
    "wof:name":"Rwe Solutions Ag",
    "wof:placetype":"venue"
},
  "geometry": {"coordinates":[10.287776,54.233364],"type":"Point"}
}