{
  "type": "Feature",
  "properties": {
    "iso:country":"DE",
    "sg:address":"S\u00fcdstr. 47",
    "sg:city":"Elsdorf",
    "sg:phone":"+49 2274/2715",
    "sg:postcode":"50189",
    "sg:province":"Nordrhein-Westfalen",
    "wof:name":"Josef Maa\u00dfen",
    "wof:placetype":"venue"
},
  "geometry": {"coordinates":[6.58089,50.926853],"type":"Point"}
}