{
  "type": "Feature",
  "properties": {
    "iso:country":"DE",
    "sg:address":"Bremer Str. 135",
    "sg:city":"Verden",
    "sg:phone":"+49 4231/7660",
    "sg:postcode":"27283",
    "sg:province":"Niedersachsen",
    "wof:name":"Rudolf Und Gerhard Matthaei & Co. Beteiligungs Gmbh",
    "wof:placetype":"venue"
},
  "geometry": {"coordinates":[9.231427,52.938648],"type":"Point"}
}