{
  "type": "Feature",
  "properties": {
    "iso:country":"DE",
    "sg:address":"Bechhofener Weg 35",
    "sg:city":"H\u00f6chstadt",
    "sg:phone":"+49 9193/2378",
    "sg:postcode":"91315",
    "sg:province":"Bayern",
    "wof:name":"Marga Labandowsky Steuerberaterin",
    "wof:placetype":"venue"
},
  "geometry": {"coordinates":[10.8162660599,49.6924972534],"type":"Point"}
}