{
  "type": "Feature",
  "properties": {
    "iso:country":"DE",
    "sg:address":"Zu den Eichen 1",
    "sg:city":"Brandenburg",
    "sg:phone":"+49 3381/714342",
    "sg:postcode":"14772",
    "sg:province":"Brandenburg",
    "wof:name":"Dr. Med. Renate B\u00f6sel",
    "wof:placetype":"venue"
},
  "geometry": {"coordinates":[12.4993438721,52.427406311],"type":"Point"}
}