{
  "type": "Feature",
  "properties": {
    "iso:country":"DE",
    "sg:address":"Breiter Weg 32a",
    "sg:city":"Gerwisch",
    "sg:phone":"+49 39292/27164",
    "sg:postcode":"39175",
    "sg:province":"Sachsen-Anhalt",
    "wof:name":"Susanne Psiorzik",
    "wof:placetype":"venue"
},
  "geometry": {"coordinates":[11.7482,52.174545],"type":"Point"}
}