{
  "type": "Feature",
  "properties": {
    "iso:country":"DE",
    "sg:address":"Russeer Weg 101 -103",
    "sg:city":"Kiel",
    "sg:postcode":"24109",
    "sg:province":"Schleswig-Holstein",
    "wof:name":"New Yorker Nord Gmbh & Co. Kg",
    "wof:placetype":"venue"
},
  "geometry": {"coordinates":[10.0681285858,54.3113365173],"type":"Point"}
}