{
  "type": "Feature",
  "properties": {
    "iso:country":"DE",
    "sg:address":"P\u00f6tschnerstr. 15",
    "sg:city":"M\u00fcnchen",
    "sg:phone":"+49 89/163789",
    "sg:postcode":"80634",
    "sg:province":"Bayern",
    "wof:name":"Immo Scheibel Architekt",
    "wof:placetype":"venue"
},
  "geometry": {"coordinates":[11.532453,48.150894],"type":"Point"}
}