{
  "type": "Feature",
  "properties": {
    "iso:country":"DE",
    "sg:address":"Habsburgerring 57a",
    "sg:city":"Minden",
    "sg:phone":"+49 571/87315",
    "sg:postcode":"32425",
    "sg:province":"Nordrhein-Westfalen",
    "wof:name":"Fonds Agentur B\u00f6ker Gmbh",
    "wof:placetype":"venue"
},
  "geometry": {"coordinates":[8.8969802856,52.2984733582],"type":"Point"}
}