{
  "type": "Feature",
  "properties": {
    "iso:country":"DE",
    "sg:address":"Keibichlstr. 3",
    "sg:city":"M\u00fcnsing",
    "sg:phone":"+49 8177/558",
    "sg:postcode":"82541",
    "sg:province":"Bayern",
    "wof:name":"Gela Baude Rechtsanw\u00e4lte",
    "wof:placetype":"venue"
},
  "geometry": {"coordinates":[11.3502588272,47.8816642761],"type":"Point"}
}