{
  "type": "Feature",
  "properties": {
    "iso:country":"DE",
    "sg:address":"Ekkehardstr. 47",
    "sg:city":"Singen",
    "sg:phone":"+49 7731/64496",
    "sg:postcode":"78224",
    "sg:province":"Baden-W\u00fcrttemberg",
    "wof:name":"Grillimbi\u00df",
    "wof:placetype":"venue"
},
  "geometry": {"coordinates":[8.8419189453,47.7630004883],"type":"Point"}
}