{
  "type": "Feature",
  "properties": {
    "iso:country":"DE",
    "sg:address":"Carl-von-Linde-Weg 1",
    "sg:city":"Herborn",
    "sg:phone":"+49 2772/58000",
    "sg:postcode":"35745",
    "sg:province":"Hessen",
    "wof:name":"Richter F\u00f6rdertechnik Gmbh & Co Kg",
    "wof:placetype":"venue"
},
  "geometry": {"coordinates":[8.28044,50.671684],"type":"Point"}
}