{
  "type": "Feature",
  "properties": {
    "iso:country":"DE",
    "sg:address":"56579",
    "sg:city":"Rengsdorf",
    "sg:phone":"+49 2634/3781",
    "sg:postcode":"56579",
    "sg:province":"Rheinland-Pfalz",
    "wof:name":"Scheffel B\u00e4ckerei",
    "wof:placetype":"venue"
},
  "geometry": {"coordinates":[7.5077,50.51371],"type":"Point"}
}