{
  "type": "Feature",
  "properties": {
    "iso:country":"DE",
    "sg:address":"Innstr. 100",
    "sg:city":"Passau",
    "sg:phone":"+49 851/51783",
    "sg:postcode":"94036",
    "sg:province":"Bayern",
    "wof:name":"Pflasterei & Asphaltbau Hann Von Weihern Gmbh",
    "wof:placetype":"venue"
},
  "geometry": {"coordinates":[13.4377975464,48.5595397949],"type":"Point"}
}