{
  "type": "Feature",
  "properties": {
    "iso:country":"DE",
    "sg:address":"V\u00f6lckers Park 14",
    "sg:city":"Reinbek",
    "sg:phone":"+49 40/7223022",
    "sg:postcode":"21465",
    "sg:province":"Schleswig-Holstein",
    "wof:name":"Dr. Helmut Gantz Gmbh Mark Bric System",
    "wof:placetype":"venue"
},
  "geometry": {"coordinates":[10.249462,53.510242],"type":"Point"}
}