{
  "type": "Feature",
  "properties": {
    "iso:country":"DE",
    "sg:address":"Nr. 17",
    "sg:city":"Altleisnig",
    "sg:phone":"+49 34321",
    "sg:postcode":"04703",
    "sg:province":"Sachsen",
    "wof:name":"Fliesenleger Michael Friedrich",
    "wof:placetype":"venue"
},
  "geometry": {"coordinates":[12.9530696869,51.1720504761],"type":"Point"}
}