{
  "type": "Feature",
  "properties": {
    "iso:country":"DE",
    "sg:address":"Schiffenberger Weg 12",
    "sg:city":"Gie\u00dfen",
    "sg:phone":"+49 641/77470",
    "sg:postcode":"35394",
    "sg:province":"Hessen",
    "wof:name":"Der Regenrinnenmacher Staudt",
    "wof:placetype":"venue"
},
  "geometry": {"coordinates":[8.681536,50.57716],"type":"Point"}
}