{
  "type": "Feature",
  "properties": {
    "iso:country":"DE",
    "sg:address":"Waldeckerh\u00f6he 7",
    "sg:city":"Miesbach",
    "sg:phone":"+49 8025/3822",
    "sg:postcode":"83714",
    "sg:province":"Bayern",
    "wof:name":"Michael Br\u00fcnner Ingenieur",
    "wof:placetype":"venue"
},
  "geometry": {"coordinates":[11.827788353,47.7893981934],"type":"Point"}
}