{
  "type": "Feature",
  "properties": {
    "iso:country":"DE",
    "sg:address":"Ravensberg 6",
    "sg:city":"Gettorf",
    "sg:phone":"+49 4346/9471",
    "sg:postcode":"24214",
    "sg:province":"Schleswig-Holstein",
    "wof:name":"M. Knauer Fleischerei",
    "wof:placetype":"venue"
},
  "geometry": {"coordinates":[9.9831809998,54.4147071838],"type":"Point"}
}