{
  "type": "Feature",
  "properties": {
    "iso:country":"DE",
    "sg:address":"Holtermannstr. 41",
    "sg:city":"Wilhelmshaven",
    "sg:phone":"+49 4421/38386",
    "sg:postcode":"26384",
    "sg:province":"Niedersachsen",
    "wof:name":"Ifas Werksanit\u00e4tsdienste Ingeborg Wiers",
    "wof:placetype":"venue"
},
  "geometry": {"coordinates":[8.1235799789,53.5360298157],"type":"Point"}
}