{
  "type": "Feature",
  "properties": {
    "iso:country":"DE",
    "sg:address":"Erlenweg 16",
    "sg:city":"Saulheim",
    "sg:phone":"+49 6732/65565",
    "sg:postcode":"55291",
    "sg:province":"Rheinland-Pfalz",
    "wof:name":"More Typographie & Layout E. Kfm.",
    "wof:placetype":"venue"
},
  "geometry": {"coordinates":[8.14076,49.865639],"type":"Point"}
}