{
  "type": "Feature",
  "properties": {
    "iso:country":"DE",
    "sg:address":"Glockenstr. 51",
    "sg:city":"Brockscheid",
    "sg:phone":"+49 6573/990330",
    "sg:postcode":"54552",
    "sg:province":"Rheinland-Pfalz",
    "wof:name":"Eifeler Glockengie\u00dferei Hans August Mark",
    "wof:placetype":"venue"
},
  "geometry": {"coordinates":[6.8473,50.132755],"type":"Point"}
}