{
  "type": "Feature",
  "properties": {
    "iso:country":"DE",
    "sg:address":"G\u00f6ckingstr. 8",
    "sg:city":"Ellrich",
    "sg:phone":"+49 36332/70095",
    "sg:postcode":"99755",
    "sg:province":"Th\u00fcringen",
    "wof:name":"S. Zimmer",
    "wof:placetype":"venue"
},
  "geometry": {"coordinates":[10.67347,51.580391],"type":"Point"}
}