{
  "type": "Feature",
  "properties": {
    "iso:country":"DE",
    "sg:address":"Hauptstr 41",
    "sg:city":"Saarbr\u00fccken",
    "sg:phone":"+49 6893/2180",
    "sg:postcode":"66130",
    "sg:province":"Saarland",
    "wof:name":"Metallsch\u00e4rferei Siegfried Fischer",
    "wof:placetype":"venue"
},
  "geometry": {"coordinates":[7.0849928856,49.1880226135],"type":"Point"}
}