{
  "type": "Feature",
  "properties": {
    "iso:country":"DE",
    "sg:address":"Bleichstr. 94",
    "sg:city":"Pforzheim",
    "sg:phone":"+49 7231/25757",
    "sg:postcode":"75173",
    "sg:province":"Baden-W\u00fcrttemberg",
    "wof:name":"B. Heckmann",
    "wof:placetype":"venue"
},
  "geometry": {"coordinates":[8.695575,48.882343],"type":"Point"}
}