{
  "type": "Feature",
  "properties": {
    "iso:country":"DE",
    "sg:address":"Hasenbuckweg 1",
    "sg:city":"Bernau",
    "sg:phone":"+49 7675/424",
    "sg:postcode":"79872",
    "sg:province":"Baden-W\u00fcrttemberg",
    "wof:name":"Restaurant Bergblick",
    "wof:placetype":"venue"
},
  "geometry": {"coordinates":[8.0278596878,47.8110466003],"type":"Point"}
}