{
  "type": "Feature",
  "properties": {
    "iso:country":"DE",
    "sg:address":"Weiselpfad 18",
    "sg:city":"Berlin",
    "sg:phone":"+49 30/6758130",
    "sg:postcode":"12527",
    "sg:province":"Berlin",
    "wof:name":"Bootshaus Krampenblick Inh. Irmgard Hortian",
    "wof:placetype":"venue"
},
  "geometry": {"coordinates":[13.6491975784,52.37940979],"type":"Point"}
}