{
  "type": "Feature",
  "properties": {
    "iso:country":"DE",
    "sg:address":"Frankensteiner Str. 12",
    "sg:city":"Seeheim-Jugenheim",
    "sg:phone":"+49 6151/54949",
    "sg:postcode":"64342",
    "sg:province":"Hessen",
    "wof:name":"Mathomias Sport Gmbh",
    "wof:placetype":"venue"
},
  "geometry": {"coordinates":[8.6528377533,49.7894248962],"type":"Point"}
}