{
  "type": "Feature",
  "properties": {
    "iso:country":"DE",
    "sg:address":"Dormettinger Str. 18",
    "sg:city":"Dotternhausen",
    "sg:phone":"+49 7427/7750",
    "sg:postcode":"72359",
    "sg:province":"Baden-W\u00fcrttemberg",
    "wof:name":"S\u00fcba Bauen Und Wohnen Gmbh",
    "wof:placetype":"venue"
},
  "geometry": {"coordinates":[8.7820463181,48.2284965515],"type":"Point"}
}