{
  "type": "Feature",
  "properties": {
    "iso:country":"DE",
    "sg:address":"Am Markt 1",
    "sg:city":"Bad Bederkesa",
    "sg:phone":"+49 4745/5068",
    "sg:postcode":"27624",
    "sg:province":"Niedersachsen",
    "wof:name":"Ulf M\u00fcgge",
    "wof:placetype":"venue"
},
  "geometry": {"coordinates":[8.8423776627,53.6247901917],"type":"Point"}
}