{
  "type": "Feature",
  "properties": {
    "iso:country":"DE",
    "sg:address":"Friesenstr. 27",
    "sg:city":"Esens",
    "sg:phone":"+49 4971/92900",
    "sg:postcode":"26427",
    "sg:province":"Niedersachsen",
    "wof:name":"Hotel Heinrich Julius",
    "wof:placetype":"venue"
},
  "geometry": {"coordinates":[7.5728869438,53.6709823608],"type":"Point"}
}