{
  "type": "Feature",
  "properties": {
    "iso:country":"DE",
    "sg:address":"Maienweg 43",
    "sg:city":"Murrhardt",
    "sg:phone":"+49 7192/6561",
    "sg:postcode":"71540",
    "sg:province":"Baden-W\u00fcrttemberg",
    "wof:name":"H. D\u00f6z",
    "wof:placetype":"venue"
},
  "geometry": {"coordinates":[9.5849590302,48.9823875427],"type":"Point"}
}