{
  "type": "Feature",
  "properties": {
    "iso:country":"DE",
    "sg:address":"Taunusanlage 11",
    "sg:city":"Frankfurt",
    "sg:postcode":"60329",
    "sg:province":"Hessen",
    "wof:name":"Demedis Dental Depot Gmbh",
    "wof:placetype":"venue"
},
  "geometry": {"coordinates":[8.66861,50.11293],"type":"Point"}
}