{
  "type": "Feature",
  "properties": {
    "iso:country":"DE",
    "sg:address":"Deutsch-Ordens-Str. 18",
    "sg:city":"Westhausen",
    "sg:phone":"+49 4973/635460",
    "sg:postcode":"73463",
    "sg:province":"Baden-W\u00fcrttemberg",
    "wof:name":"Kreissparkasse Ostalb",
    "wof:placetype":"venue"
},
  "geometry": {"coordinates":[10.187509,48.88213],"type":"Point"}
}