{
  "type": "Feature",
  "properties": {
    "iso:country":"DE",
    "sg:address":"Tobelwasenweg 40",
    "sg:city":"Weilheim",
    "sg:phone":"+49 4970/232217",
    "sg:postcode":"73235",
    "sg:province":"Baden-W\u00fcrttemberg",
    "wof:name":"Heinz Elholm",
    "wof:placetype":"venue"
},
  "geometry": {"coordinates":[9.5512104034,48.6196784973],"type":"Point"}
}