{
  "type": "Feature",
  "properties": {
    "iso:country":"DE",
    "sg:address":"Leisenr\u00f6der Str. 1",
    "sg:city":"N\u00f6rten-Hardenberg",
    "sg:phone":"+49 5594/580",
    "sg:postcode":"37176",
    "sg:province":"Niedersachsen",
    "wof:name":"Hotel Restaurant Zur Post",
    "wof:placetype":"venue"
},
  "geometry": {"coordinates":[10.024851799,51.6297302246],"type":"Point"}
}