{
  "type": "Feature",
  "properties": {
    "iso:country":"DE",
    "sg:address":"Rathenaustr. 21",
    "sg:city":"Werdau",
    "sg:phone":"+49 3761/3745",
    "sg:postcode":"08412",
    "sg:province":"Sachsen",
    "wof:name":"Simon Immobilien",
    "wof:placetype":"venue"
},
  "geometry": {"coordinates":[12.37225914,50.7253074646],"type":"Point"}
}