{
  "type": "Feature",
  "properties": {
    "iso:country":"DE",
    "sg:address":"Maienstr. 1",
    "sg:city":"Freiburg",
    "sg:phone":"+49 761/74991",
    "sg:postcode":"79102",
    "sg:province":"Baden-W\u00fcrttemberg",
    "wof:name":"Z\u00fchlke",
    "wof:placetype":"venue"
},
  "geometry": {"coordinates":[7.849341,47.987652],"type":"Point"}
}