{
  "type": "Feature",
  "properties": {
    "iso:country":"DE",
    "sg:address":"Aidenbacher Str. 8",
    "sg:city":"Haarbach",
    "sg:phone":"+49 8535/270",
    "sg:postcode":"94542",
    "sg:province":"Bayern",
    "wof:name":"A. Berger Mech. Werkstatt",
    "wof:placetype":"venue"
},
  "geometry": {"coordinates":[13.143896,48.501369],"type":"Point"}
}