{
  "type": "Feature",
  "properties": {
    "iso:country":"DE",
    "sg:address":"R\u00f6merstr. 21",
    "sg:city":"Walheim",
    "sg:phone":"+49 7143/830149",
    "sg:postcode":"74399",
    "sg:province":"Baden-W\u00fcrttemberg",
    "wof:name":"Teamwork Markus Bachmann",
    "wof:placetype":"venue"
},
  "geometry": {"coordinates":[9.156579,49.013859],"type":"Point"}
}