{
  "type": "Feature",
  "properties": {
    "iso:country":"DE",
    "sg:address":"Im Unteren Angel 19",
    "sg:city":"Offenburg",
    "sg:postcode":"77652",
    "sg:province":"Baden-W\u00fcrttemberg",
    "wof:name":"Reha Werkstatt",
    "wof:placetype":"venue"
},
  "geometry": {"coordinates":[7.9358057976,48.4768981934],"type":"Point"}
}