{
  "type": "Feature",
  "properties": {
    "iso:country":"DE",
    "sg:address":"K\u00e4mmererstr. 15",
    "sg:city":"Speyer",
    "sg:phone":"+49 6232/26060",
    "sg:postcode":"67346",
    "sg:province":"Rheinland-Pfalz",
    "wof:name":"Costa Smeralda Zum Franco",
    "wof:placetype":"venue"
},
  "geometry": {"coordinates":[8.4270944595,49.31483078],"type":"Point"}
}