{
  "type": "Feature",
  "properties": {
    "iso:country":"DE",
    "sg:address":"postbox 1241//besser1eMail+ANRUFEN",
    "sg:city":"peiting",
    "sg:phone":"+49 8861",
    "sg:postcode":"86968",
    "sg:province":"Bayern",
    "wof:name":"Pronto Werbung - Auftragsbeschaffung F\u00fcr Telefonmarketing-",
    "wof:placetype":"venue"
},
  "geometry": {"coordinates":[10.92367,47.7943],"type":"Point"}
}