{
  "type": "Feature",
  "properties": {
    "iso:country":"DE",
    "sg:address":"Marktstr. 7",
    "sg:city":"Homburg",
    "sg:phone":"+49 6841/65188",
    "sg:postcode":"66424",
    "sg:province":"Saarland",
    "wof:name":"Martg\u00e4ssje",
    "wof:placetype":"venue"
},
  "geometry": {"coordinates":[7.3403692245,49.3214950562],"type":"Point"}
}