{
  "type": "Feature",
  "properties": {
    "iso:country":"DE",
    "sg:address":"Dreim\u00fchlenstr. 38",
    "sg:city":"M\u00fcnchen",
    "sg:phone":"+49 89/771317",
    "sg:postcode":"80469",
    "sg:province":"Bayern",
    "wof:name":"M. Klo\u00df",
    "wof:placetype":"venue"
},
  "geometry": {"coordinates":[11.558936,48.12035],"type":"Point"}
}