{
  "type": "Feature",
  "properties": {
    "iso:country":"DE",
    "sg:address":"Dingelst\u00e4dter Str. 70",
    "sg:city":"Berlin",
    "sg:phone":"+49 30/9812552",
    "sg:postcode":"13053",
    "sg:province":"Berlin",
    "wof:name":"J\u00f6rg Mielis",
    "wof:placetype":"venue"
},
  "geometry": {"coordinates":[13.5203952789,52.5377120972],"type":"Point"}
}