{
  "type": "Feature",
  "properties": {
    "iso:country":"DE",
    "sg:address":"Segeberger Str. 10",
    "sg:city":"Schieren",
    "sg:phone":"+49 4551/6906",
    "sg:postcode":"23795",
    "sg:province":"Schleswig-Holstein",
    "wof:name":"Hans-heinrich Hardt",
    "wof:placetype":"venue"
},
  "geometry": {"coordinates":[10.386297,53.944271],"type":"Point"}
}