{
  "type": "Feature",
  "properties": {
    "iso:country":"DE",
    "sg:address":"Naumburger Str.",
    "sg:city":"Grana",
    "sg:phone":"+49 3441/214084",
    "sg:postcode":"06712",
    "sg:province":"Sachsen-Anhalt",
    "wof:name":"Restaurant Peking",
    "wof:placetype":"venue"
},
  "geometry": {"coordinates":[12.1065092087,51.0532684326],"type":"Point"}
}