{
  "type": "Feature",
  "properties": {
    "iso:country":"DE",
    "sg:address":"D\u00fcsseldorferstr. 186",
    "sg:city":"Neuss",
    "sg:phone":"+49 4921/312940",
    "sg:postcode":"41460",
    "sg:province":"Nordrhein-Westfalen",
    "wof:name":"Hendricks Internationale Spedition Gmbh & Co Kg",
    "wof:placetype":"venue"
},
  "geometry": {"coordinates":[6.6932902336,51.2143592834],"type":"Point"}
}