{
  "type": "Feature",
  "properties": {
    "iso:country":"DE",
    "sg:address":"Goldschmidtstr. 18",
    "sg:city":"Neumarkt",
    "sg:phone":"+49 9181/220204",
    "sg:postcode":"92318",
    "sg:province":"Bayern",
    "wof:name":"Jura Wintergarten Bau Gmbh",
    "wof:placetype":"venue"
},
  "geometry": {"coordinates":[11.452648,49.269863],"type":"Point"}
}