{
  "type": "Feature",
  "properties": {
    "iso:country":"DE",
    "sg:address":"Am Kirchberg 12",
    "sg:city":"Hackenheim",
    "sg:phone":"+49 671/62324",
    "sg:postcode":"55546",
    "sg:province":"Rheinland-Pfalz",
    "wof:name":"In Managementberatung Gmbh",
    "wof:placetype":"venue"
},
  "geometry": {"coordinates":[7.899604,49.821499],"type":"Point"}
}