{
  "type": "Feature",
  "properties": {
    "iso:country":"DE",
    "sg:address":"Bahnstr. 7",
    "sg:city":"Dreieich",
    "sg:phone":"+49 6103/81335",
    "sg:postcode":"63303",
    "sg:province":"Hessen",
    "wof:name":"Ilse Dreher",
    "wof:placetype":"venue"
},
  "geometry": {"coordinates":[8.7091608047,50.001285553],"type":"Point"}
}