{
  "type": "Feature",
  "properties": {
    "iso:country":"DE",
    "sg:address":"Im Stadtwald Geb\u00e4ude 30",
    "sg:city":"Saarbr\u00fccken",
    "sg:phone":"+49 681/3026305",
    "sg:postcode":"66123",
    "sg:province":"Saarland",
    "wof:name":"Ciuti Akademie",
    "wof:placetype":"venue"
},
  "geometry": {"coordinates":[7.016635,49.240444],"type":"Point"}
}