{
  "type": "Feature",
  "properties": {
    "iso:country":"DE",
    "sg:address":"Hasklintweg 4",
    "sg:city":"Wathlingen",
    "sg:phone":"+49 5144/4540",
    "sg:postcode":"29339",
    "sg:province":"Niedersachsen",
    "wof:name":"Annette Stemmler",
    "wof:placetype":"venue"
},
  "geometry": {"coordinates":[10.1515159607,52.5404853821],"type":"Point"}
}