{
  "type": "Feature",
  "properties": {
    "iso:country":"DE",
    "sg:address":"Sperberfeld 20",
    "sg:city":"Kleinmachnow",
    "sg:postcode":"14532",
    "sg:province":"Brandenburg",
    "wof:name":"Andrea Brandt Steuerberaterin",
    "wof:placetype":"venue"
},
  "geometry": {"coordinates":[13.2073116302,52.4068374634],"type":"Point"}
}