{
  "type": "Feature",
  "properties": {
    "iso:country":"DE",
    "sg:address":"Berghof",
    "sg:city":"M\u00f6nsheim",
    "sg:phone":"+49 7044/7566",
    "sg:postcode":"71297",
    "sg:province":"Baden-W\u00fcrttemberg",
    "wof:name":"Otto B\u00fcrle",
    "wof:placetype":"venue"
},
  "geometry": {"coordinates":[8.86554,48.871643],"type":"Point"}
}