{
  "type": "Feature",
  "properties": {
    "iso:country":"DE",
    "sg:address":"Am H\u00f6henring 22",
    "sg:city":"Bad Griesbach",
    "sg:phone":"+49 8532/920112",
    "sg:postcode":"94086",
    "sg:province":"Bayern",
    "wof:name":"A. Gurtsching Immobilienmakler",
    "wof:placetype":"venue"
},
  "geometry": {"coordinates":[13.1925144196,48.4401550293],"type":"Point"}
}