{
  "type": "Feature",
  "properties": {
    "iso:country":"DE",
    "sg:address":"Wilhelm-Herbst-Str. 5",
    "sg:city":"Bremen",
    "sg:phone":"+49 421/2187274",
    "sg:postcode":"28359",
    "sg:province":"Bremen",
    "wof:name":"Institut F\u00fcr Konjunktur- Und Strukturforschung (iksf) Bremen",
    "wof:placetype":"venue"
},
  "geometry": {"coordinates":[8.851021,53.112949],"type":"Point"}
}