{
  "type": "Feature",
  "properties": {
    "iso:country":"DE",
    "sg:address":"L\u00fcneburger Str. 157",
    "sg:city":"Winsen",
    "sg:postcode":"21423",
    "sg:province":"Niedersachsen",
    "wof:name":"Babatec Gmbh",
    "wof:placetype":"venue"
},
  "geometry": {"coordinates":[10.232081,53.351967],"type":"Point"}
}