{
  "type": "Feature",
  "properties": {
    "iso:country":"DE",
    "sg:address":"Duracher Str. 11",
    "sg:city":"Kempten",
    "sg:phone":"+49 831/62026",
    "sg:postcode":"87437",
    "sg:province":"Bayern",
    "wof:name":"Hertz Autovermietung",
    "wof:placetype":"venue"
},
  "geometry": {"coordinates":[10.327915,47.714298],"type":"Point"}
}