{
  "type": "Feature",
  "properties": {
    "iso:country":"DE",
    "sg:address":"Dorstener Str. 410",
    "sg:city":"Oberhausen",
    "sg:phone":"+49 208/609752",
    "sg:postcode":"46119",
    "sg:province":"Nordrhein-Westfalen",
    "wof:name":"Almh\u00fctte",
    "wof:placetype":"venue"
},
  "geometry": {"coordinates":[6.8736200333,51.5302734375],"type":"Point"}
}