{
  "type": "Feature",
  "properties": {
    "iso:country":"DE",
    "sg:address":"Werderstr. 3",
    "sg:city":"Hannover",
    "sg:phone":"+49 511/312369",
    "sg:postcode":"30161",
    "sg:province":"Niedersachsen",
    "wof:name":"M & D M\u00f6bel- Und Design Gmbh",
    "wof:placetype":"venue"
},
  "geometry": {"coordinates":[9.7352437973,52.3870048523],"type":"Point"}
}