{
  "type": "Feature",
  "properties": {
    "iso:country":"DE",
    "sg:address":"Rathausstr. 8",
    "sg:city":"Schliersee",
    "sg:phone":"+49 8026/6417",
    "sg:postcode":"83727",
    "sg:province":"Bayern",
    "wof:name":"H. Buresch",
    "wof:placetype":"venue"
},
  "geometry": {"coordinates":[11.8627538681,47.7353744507],"type":"Point"}
}