{
  "type": "Feature",
  "properties": {
    "iso:country":"DE",
    "sg:address":"Arsterdamm 180",
    "sg:city":"Bremen",
    "sg:phone":"+49 421/820919",
    "sg:postcode":"28279",
    "sg:province":"Bremen",
    "wof:name":"Eschi-kaffeer\u00f6sterei Ewald Schieferstein",
    "wof:placetype":"venue"
},
  "geometry": {"coordinates":[8.8448972702,53.0337905884],"type":"Point"}
}