{
  "type": "Feature",
  "properties": {
    "iso:country":"DE",
    "sg:address":"Klosterstr. 24",
    "sg:city":"Krefeld",
    "sg:phone":"+49 2151/67059",
    "sg:postcode":"47798",
    "sg:province":"Nordrhein-Westfalen",
    "wof:name":"Dr. Med. Thomas Schack Arzt F\u00fcr Innere Medizin",
    "wof:placetype":"venue"
},
  "geometry": {"coordinates":[6.5608768463,51.3337364197],"type":"Point"}
}