{
  "type": "Feature",
  "properties": {
    "iso:country":"DE",
    "sg:address":"Lauenburger Str. 34",
    "sg:city":"Schwarzenbek",
    "sg:phone":"+49 4151/89390",
    "sg:postcode":"21493",
    "sg:province":"Schleswig-Holstein",
    "wof:name":"Highcom Mobilfunk U. Computer Inh. Gitta Ribbrock",
    "wof:placetype":"venue"
},
  "geometry": {"coordinates":[10.4852876663,53.5011672974],"type":"Point"}
}