{
  "type": "Feature",
  "properties": {
    "iso:country":"DE",
    "sg:address":"An der R\u00f6merstr. 22",
    "sg:city":"Pfungstadt",
    "sg:phone":"+49 6157/94660",
    "sg:postcode":"64319",
    "sg:province":"Hessen",
    "wof:name":"Erich Bortoli Gmbh Verlagsvertreter",
    "wof:placetype":"venue"
},
  "geometry": {"coordinates":[8.600781,49.795643],"type":"Point"}
}