{
  "type": "Feature",
  "properties": {
    "iso:country":"DE",
    "sg:address":"Marienstr. 29",
    "sg:city":"Eschweiler",
    "sg:phone":"+49 2403/29512",
    "sg:postcode":"52249",
    "sg:province":"Nordrhein-Westfalen",
    "wof:name":"G. Schernich",
    "wof:placetype":"venue"
},
  "geometry": {"coordinates":[6.263261,50.817242],"type":"Point"}
}