{
  "type": "Feature",
  "properties": {
    "iso:country":"DE",
    "sg:address":"Schillerstr. 2",
    "sg:city":"Kirchheimbolanden",
    "sg:phone":"+49 6352/8758",
    "sg:postcode":"67292",
    "sg:province":"Rheinland-Pfalz",
    "wof:name":"K. R\u00f6rich",
    "wof:placetype":"venue"
},
  "geometry": {"coordinates":[8.011351,49.663261],"type":"Point"}
}