{
  "type": "Feature",
  "properties": {
    "iso:country":"DE",
    "sg:address":"Puschkinallee 9 a",
    "sg:city":"Berlin",
    "sg:postcode":"12435",
    "sg:province":"Berlin",
    "wof:name":"Masche & H\u00e4vecker Elektrotechnik Gmbh",
    "wof:placetype":"venue"
},
  "geometry": {"coordinates":[13.457516,52.493839],"type":"Point"}
}