{
  "type": "Feature",
  "properties": {
    "iso:country":"DE",
    "sg:address":"Seugenbergweg 15a",
    "sg:city":"Walderbach",
    "sg:phone":"+49 9464/910654",
    "sg:postcode":"93194",
    "sg:province":"Bayern",
    "wof:name":"Georg Hahn Dieberg",
    "wof:placetype":"venue"
},
  "geometry": {"coordinates":[12.36435,49.192791],"type":"Point"}
}