{
  "type": "Feature",
  "properties": {
    "iso:country":"DE",
    "sg:address":"Friedenstr. 55",
    "sg:city":"Kaiserslautern",
    "sg:phone":"+49 631/43303",
    "sg:postcode":"67657",
    "sg:province":"Rheinland-Pfalz",
    "wof:name":"Marco Dengel",
    "wof:placetype":"venue"
},
  "geometry": {"coordinates":[7.7862391472,49.4490699768],"type":"Point"}
}