{
  "type": "Feature",
  "properties": {
    "iso:country":"DE",
    "sg:address":"L\u00f6schweiler Weg 16",
    "sg:city":"Landau",
    "sg:phone":"+49 6341/960012",
    "sg:postcode":"76829",
    "sg:province":"Rheinland-Pfalz",
    "wof:name":"G. Ellermann Immobilienmakler",
    "wof:placetype":"venue"
},
  "geometry": {"coordinates":[8.0736312866,49.2129135132],"type":"Point"}
}