{
  "type": "Feature",
  "properties": {
    "iso:country":"DE",
    "sg:address":"Wailandtstr. 17",
    "sg:city":"Aschaffenburg",
    "sg:phone":"+49 6021/88338",
    "sg:postcode":"63741",
    "sg:province":"Bayern",
    "wof:name":"Gebr. Wirth Ohg",
    "wof:placetype":"venue"
},
  "geometry": {"coordinates":[9.100875,49.947727],"type":"Point"}
}