{
  "type": "Feature",
  "properties": {
    "iso:country":"DE",
    "sg:address":"Hammerstr. 25",
    "sg:city":"D\u00fcren",
    "sg:phone":"+49 2421/54284",
    "sg:postcode":"52355",
    "sg:province":"Nordrhein-Westfalen",
    "wof:name":"Hammereck",
    "wof:placetype":"venue"
},
  "geometry": {"coordinates":[6.4779491425,50.7719306946],"type":"Point"}
}