{
  "type": "Feature",
  "properties": {
    "iso:country":"DE",
    "sg:address":"F\u00f6hrenstr. 10",
    "sg:city":"Garching",
    "sg:phone":"+49 8634/1874",
    "sg:postcode":"84518",
    "sg:province":"Bayern",
    "wof:name":"Harald Kumpfm\u00fcller",
    "wof:placetype":"venue"
},
  "geometry": {"coordinates":[12.6128664017,48.1483001709],"type":"Point"}
}