{
  "type": "Feature",
  "properties": {
    "iso:country":"DE",
    "sg:address":"Lange Str. 12",
    "sg:city":"Greifswald",
    "sg:postcode":"17489",
    "sg:province":"Mecklenburg-Vorpommern",
    "wof:name":"Mci-management Consult Und Immobilien Gmbh",
    "wof:placetype":"venue"
},
  "geometry": {"coordinates":[13.3722991943,54.0959510803],"type":"Point"}
}