{
  "type": "Feature",
  "properties": {
    "iso:country":"DE",
    "sg:address":"Talstr. 4",
    "sg:city":"Hettstedt",
    "sg:phone":"+49 34742/527",
    "sg:postcode":"06333",
    "sg:province":"Sachsen-Anhalt",
    "wof:name":"E. M\u00e4rtens",
    "wof:placetype":"venue"
},
  "geometry": {"coordinates":[11.5216245651,51.6492729187],"type":"Point"}
}