{
  "type": "Feature",
  "properties": {
    "iso:country":"DE",
    "sg:address":"Trillerstr. 36",
    "sg:city":"Zwickau",
    "sg:phone":"+49 375/475662",
    "sg:postcode":"08066",
    "sg:province":"Sachsen",
    "wof:name":"Horst Fuhrmann",
    "wof:placetype":"venue"
},
  "geometry": {"coordinates":[12.508832,50.725723],"type":"Point"}
}