{
  "type": "Feature",
  "properties": {
    "iso:country":"DE",
    "sg:address":"Lorenzstr. 10",
    "sg:city":"Stuttgart",
    "sg:phone":"+49 711/8210",
    "sg:postcode":"70435",
    "sg:province":"Baden-W\u00fcrttemberg",
    "wof:name":"Alcatel Sel Versicherungsdienst Gmbh",
    "wof:placetype":"venue"
},
  "geometry": {"coordinates":[9.1536006927,48.8316192627],"type":"Point"}
}