{
  "type": "Feature",
  "properties": {
    "iso:country":"DE",
    "sg:address":"Lange Gasse 33",
    "sg:city":"Bernsbach",
    "sg:phone":"+49 3774/645757",
    "sg:postcode":"08315",
    "sg:province":"Sachsen",
    "wof:name":"Billardcafe Manta Bar",
    "wof:placetype":"venue"
},
  "geometry": {"coordinates":[12.7639312744,50.5725402832],"type":"Point"}
}