{
  "type": "Feature",
  "properties": {
    "iso:country":"DE",
    "sg:address":"Hauptstr. 137",
    "sg:city":"Bad Lauterberg im Harz",
    "sg:phone":"+49 5524",
    "sg:postcode":"37431",
    "sg:province":"Niedersachsen",
    "wof:name":"Cafe Und Konditorei, Ferienappartments Schnibbe",
    "wof:placetype":"venue"
},
  "geometry": {"coordinates":[10.4696769714,51.6312904358],"type":"Point"}
}