{
  "type": "Feature",
  "properties": {
    "iso:country":"DE",
    "sg:address":"Natruper Str. 186",
    "sg:city":"Osnabr\u00fcck",
    "sg:phone":"+49 541/128747",
    "sg:postcode":"49090",
    "sg:province":"Niedersachsen",
    "wof:name":"K. H. Weidauer Masseure",
    "wof:placetype":"venue"
},
  "geometry": {"coordinates":[8.017954,52.291935],"type":"Point"}
}