{
  "type": "Feature",
  "properties": {
    "iso:country":"DE",
    "sg:address":"Bernauer Str. 23",
    "sg:city":"Prien",
    "sg:phone":"+49 8051/1083",
    "sg:postcode":"83209",
    "sg:province":"Bayern",
    "wof:name":"Aral Ag",
    "wof:placetype":"venue"
},
  "geometry": {"coordinates":[12.3448524475,47.8523292542],"type":"Point"}
}