{
  "type": "Feature",
  "properties": {
    "iso:country":"DE",
    "sg:address":"Bahnhofstr. 25",
    "sg:city":"R\u00e4tzlingen",
    "sg:phone":"+49 39057/2287",
    "sg:postcode":"39359",
    "sg:province":"Sachsen-Anhalt",
    "wof:name":"Bolle Bauelemente",
    "wof:placetype":"venue"
},
  "geometry": {"coordinates":[11.117689,52.403812],"type":"Point"}
}