{
  "type": "Feature",
  "properties": {
    "iso:country":"DE",
    "sg:address":"Sch\u00f6nauer Str. 5",
    "sg:city":"Freiburg",
    "sg:phone":"+49 761/493793",
    "sg:postcode":"79115",
    "sg:province":"Baden-W\u00fcrttemberg",
    "wof:name":"Richard Hellstern Steinmetzmeister",
    "wof:placetype":"venue"
},
  "geometry": {"coordinates":[7.824215889,47.9796943665],"type":"Point"}
}