{
  "type": "Feature",
  "properties": {
    "iso:country":"DE",
    "sg:address":"Landsbergerstr.484",
    "sg:city":"M\u00fcnchen",
    "sg:phone":"+49 89/8293970",
    "sg:postcode":"81241",
    "sg:province":"Bayern",
    "wof:name":"Jomas Digitale Medien",
    "wof:placetype":"venue"
},
  "geometry": {"coordinates":[11.463421,48.146671],"type":"Point"}
}