{
  "type": "Feature",
  "properties": {
    "iso:country":"DE",
    "sg:address":"Rupprechtstegen",
    "sg:city":"Rupprechtstegen",
    "sg:phone":"+49 9152/8012",
    "sg:postcode":"97294",
    "sg:province":"Bayern",
    "wof:name":"Raiffeisenbank Hersbruck Eg",
    "wof:placetype":"venue"
},
  "geometry": {"coordinates":[-122.675682,45.51181],"type":"Point"}
}