{
  "type": "Feature",
  "properties": {
    "iso:country":"DE",
    "sg:address":"Sauerlacher Str. 27a",
    "sg:city":"Wolfratshausen",
    "sg:phone":"+49 8171/10764",
    "sg:postcode":"82515",
    "sg:province":"Bayern",
    "wof:name":"Isar-apotheke Elvine Engelhardt",
    "wof:placetype":"venue"
},
  "geometry": {"coordinates":[11.428185,47.913509],"type":"Point"}
}