{
  "type": "Feature",
  "properties": {
    "iso:country":"DE",
    "sg:address":"Von-Humboldt-Str. 4",
    "sg:city":"Heppenheim",
    "sg:postcode":"64646",
    "sg:province":"Hessen",
    "wof:name":"Caso Textil-handels Ag",
    "wof:placetype":"venue"
},
  "geometry": {"coordinates":[8.6159057617,49.6423454285],"type":"Point"}
}