{
  "type": "Feature",
  "properties": {
    "iso:country":"DE",
    "sg:address":"Alstertor 18",
    "sg:city":"Hamburg",
    "sg:phone":"+49 40/473296",
    "sg:postcode":"20095",
    "sg:province":"Hamburg",
    "wof:name":"Hup Treuhand- U. Unternehmens- Beratungsgesellschaft Mbh",
    "wof:placetype":"venue"
},
  "geometry": {"coordinates":[9.99705,53.552837],"type":"Point"}
}