{
  "type": "Feature",
  "properties": {
    "iso:country":"DE",
    "sg:address":"Neuendammer Str. 42",
    "sg:city":"Osterholz-Scharmbeck",
    "sg:phone":"+49 4791/57633",
    "sg:postcode":"27711",
    "sg:province":"Niedersachsen",
    "wof:name":"Ludwig Lilienthal",
    "wof:placetype":"venue"
},
  "geometry": {"coordinates":[8.824085,53.24152],"type":"Point"}
}