{
  "type": "Feature",
  "properties": {
    "iso:country":"DE",
    "sg:address":"Hohenkr\u00e4henstr. 35",
    "sg:city":"Singen",
    "sg:phone":"+49 7731/43350",
    "sg:postcode":"78224",
    "sg:province":"Baden-W\u00fcrttemberg",
    "wof:name":"A. Stadelhofer",
    "wof:placetype":"venue"
},
  "geometry": {"coordinates":[8.827998,47.766975],"type":"Point"}
}