{
  "type": "Feature",
  "properties": {
    "iso:country":"DE",
    "sg:address":"Hochburger Str. 7",
    "sg:city":"Emmendingen",
    "sg:phone":"+49 7641/8578",
    "sg:postcode":"79312",
    "sg:province":"Baden-W\u00fcrttemberg",
    "wof:name":"Schirmeier-druck",
    "wof:placetype":"venue"
},
  "geometry": {"coordinates":[7.852319,48.121387],"type":"Point"}
}