{
  "type": "Feature",
  "properties": {
    "iso:country":"DE",
    "sg:address":"Pforzheimer Str. 4",
    "sg:city":"Karlsbad",
    "sg:phone":"+49 7202/2560",
    "sg:postcode":"76307",
    "sg:province":"Baden-W\u00fcrttemberg",
    "wof:name":"Bernfried Pfeil",
    "wof:placetype":"venue"
},
  "geometry": {"coordinates":[8.5067462921,48.9166259766],"type":"Point"}
}