{
  "type": "Feature",
  "properties": {
    "iso:country":"DE",
    "sg:address":"Sandkuhle 27",
    "sg:city":"Itzehoe",
    "sg:phone":"+49 4821/61263",
    "sg:postcode":"25524",
    "sg:province":"Schleswig-Holstein",
    "wof:name":"Wilma Eggert",
    "wof:placetype":"venue"
},
  "geometry": {"coordinates":[9.521246,53.926754],"type":"Point"}
}