{
  "type": "Feature",
  "properties": {
    "iso:country":"DE",
    "sg:address":"Zur Burghart 6",
    "sg:city":"Lohmar",
    "sg:phone":"+49 2246/5482",
    "sg:postcode":"53797",
    "sg:province":"Nordrhein-Westfalen",
    "wof:name":"Walter Knipp Fabrikation Und Verkauf Von",
    "wof:placetype":"venue"
},
  "geometry": {"coordinates":[7.2262878418,50.8523864746],"type":"Point"}
}