{
  "type": "Feature",
  "properties": {
    "iso:country":"DE",
    "sg:address":"R\u00f6ntgenstr. 2",
    "sg:city":"Ehingen",
    "sg:phone":"+49 7391/71322",
    "sg:postcode":"89584",
    "sg:province":"Baden-W\u00fcrttemberg",
    "wof:name":"Positiv Fitness",
    "wof:placetype":"venue"
},
  "geometry": {"coordinates":[9.7230005264,48.2917938232],"type":"Point"}
}