{
  "type": "Feature",
  "properties": {
    "iso:country":"DE",
    "sg:address":"Kappstr. 18",
    "sg:city":"Lindenfels",
    "sg:postcode":"64678",
    "sg:province":"Hessen",
    "wof:name":"Religionsp\u00e4dagogisches Amt Der Ev. Kirche In Hessen",
    "wof:placetype":"venue"
},
  "geometry": {"coordinates":[8.784113,49.681946],"type":"Point"}
}