{
  "type": "Feature",
  "properties": {
    "iso:country":"DE",
    "sg:address":"Donaustr. 29",
    "sg:city":"Memmingen",
    "sg:phone":"+49 8331/85680",
    "sg:postcode":"87700",
    "sg:province":"Bayern",
    "wof:name":"Autohaus K\u00f6hler Gmbh",
    "wof:placetype":"venue"
},
  "geometry": {"coordinates":[10.1799497604,47.9926109314],"type":"Point"}
}