{
  "type": "Feature",
  "properties": {
    "iso:country":"DE",
    "sg:address":"Breitscheidstr. 2",
    "sg:city":"Neustadt-Glewe",
    "sg:phone":"+49 38757/22030",
    "sg:postcode":"19306",
    "sg:province":"Mecklenburg-Vorpommern",
    "wof:name":"Assekuranzkontor Niemeier",
    "wof:placetype":"venue"
},
  "geometry": {"coordinates":[11.5869903564,53.3825111389],"type":"Point"}
}