{
  "type": "Feature",
  "properties": {
    "iso:country":"DE",
    "sg:address":"Z\u00f6rgiebelstr. 10-12",
    "sg:city":"K\u00f6ln",
    "sg:phone":"+49 221/798505",
    "sg:postcode":"50769",
    "sg:province":"Nordrhein-Westfalen",
    "wof:name":"Kath. Pfarramt St. Johannes I. D. N. Stadt",
    "wof:placetype":"venue"
},
  "geometry": {"coordinates":[6.9034981728,51.0181884766],"type":"Point"}
}