{
  "type": "Feature",
  "properties": {
    "iso:country":"DE",
    "sg:address":"Am Hofe 5",
    "sg:city":"Kiel",
    "sg:phone":"+49 431/783875",
    "sg:postcode":"24146",
    "sg:province":"Schleswig-Holstein",
    "wof:name":"Otto Schl\u00fcter & Sohn Gmbh & Co. Kg",
    "wof:placetype":"venue"
},
  "geometry": {"coordinates":[10.174483,54.291271],"type":"Point"}
}