{
  "type": "Feature",
  "properties": {
    "iso:country":"DE",
    "sg:address":"Marktstr. 11",
    "sg:city":"Calw",
    "sg:phone":"+49 7051/2133",
    "sg:postcode":"75365",
    "sg:province":"Baden-W\u00fcrttemberg",
    "wof:name":"Alte Apotheke Calw Apotheker A. Schneider E. K.",
    "wof:placetype":"venue"
},
  "geometry": {"coordinates":[8.74033,48.713875],"type":"Point"}
}