{
  "type": "Feature",
  "properties": {
    "iso:country":"DE",
    "sg:address":"Framstr. 7",
    "sg:city":"Berlin",
    "sg:phone":"+49 4930/6118836",
    "sg:postcode":"12047",
    "sg:province":"Berlin",
    "wof:name":"Green Congress",
    "wof:placetype":"venue"
},
  "geometry": {"coordinates":[13.431748,52.489456],"type":"Point"}
}