{
  "type": "Feature",
  "properties": {
    "iso:country":"DE",
    "sg:city":"Muenchen",
    "sg:postcode":"80804",
    "sg:province":"Bayern",
    "wof:name":"Munich Web Design",
    "wof:placetype":"venue"
},
  "geometry": {"coordinates":[11.5755,48.172371],"type":"Point"}
}