{
  "type": "Feature",
  "properties": {
    "iso:country":"DE",
    "sg:address":"Admiralit\u00e4tstr. 74",
    "sg:city":"Hamburg",
    "sg:phone":"+49 40/37519455",
    "sg:postcode":"20459",
    "sg:province":"Hamburg",
    "wof:name":"N. Herrmann",
    "wof:placetype":"venue"
},
  "geometry": {"coordinates":[9.9847793579,53.5488853455],"type":"Point"}
}