{
  "type": "Feature",
  "properties": {
    "iso:country":"DE",
    "sg:address":"Im Amselbusch 16",
    "sg:city":"Emmelshausen",
    "sg:phone":"+49 6747/6866",
    "sg:postcode":"56281",
    "sg:province":"Rheinland-Pfalz",
    "wof:name":"G\u00fcnter Vogt Architekt",
    "wof:placetype":"venue"
},
  "geometry": {"coordinates":[7.544935,50.152027],"type":"Point"}
}