{
  "type": "Feature",
  "properties": {
    "iso:country":"DE",
    "sg:address":"Kaufbeurer Str. 4",
    "sg:city":"Schwabm\u00fcnchen",
    "sg:phone":"+49 8232/72377",
    "sg:postcode":"86830",
    "sg:province":"Bayern",
    "wof:name":"C. Gro\u00dfmann",
    "wof:placetype":"venue"
},
  "geometry": {"coordinates":[10.7576055527,48.1765365601],"type":"Point"}
}