{
  "type": "Feature",
  "properties": {
    "iso:country":"DE",
    "sg:address":"Storchenstr 2",
    "sg:city":"Aalen",
    "sg:phone":"+49 7361/970120",
    "sg:postcode":"73430",
    "sg:province":"Baden-W\u00fcrttemberg",
    "wof:name":"Sucre Design Factory",
    "wof:placetype":"venue"
},
  "geometry": {"coordinates":[10.092094,48.838623],"type":"Point"}
}