{
  "type": "Feature",
  "properties": {
    "iso:country":"DE",
    "sg:address":"Bonifaciusstr. 10",
    "sg:city":"Erfurt",
    "sg:phone":"+49 361/2225776",
    "sg:postcode":"99084",
    "sg:province":"Th\u00fcringen",
    "wof:name":"Die Pinte",
    "wof:placetype":"venue"
},
  "geometry": {"coordinates":[11.0154485703,50.9708824158],"type":"Point"}
}