{
  "type": "Feature",
  "properties": {
    "iso:country":"DE",
    "sg:address":"Gollierplatz 16",
    "sg:city":"M\u00fcnchen",
    "sg:phone":"+49 89/503265",
    "sg:postcode":"80339",
    "sg:province":"Bayern",
    "wof:name":"Hanns Feil Masseur",
    "wof:placetype":"venue"
},
  "geometry": {"coordinates":[11.53512,48.136677],"type":"Point"}
}