{
  "type": "Feature",
  "properties": {
    "iso:country":"DE",
    "sg:address":"Garstedter Weg 85",
    "sg:city":"Hasloh",
    "sg:phone":"+49 4106/2327",
    "sg:postcode":"25474",
    "sg:province":"Schleswig-Holstein",
    "wof:name":"Frank Reinefeld Gmbh",
    "wof:placetype":"venue"
},
  "geometry": {"coordinates":[9.9321279526,53.6927719116],"type":"Point"}
}