{
  "type": "Feature",
  "properties": {
    "iso:country":"DE",
    "sg:address":"Wei\u00dfestr. 5 c",
    "sg:city":"Leipzig",
    "sg:phone":"+49 341/8621673",
    "sg:postcode":"04299",
    "sg:province":"Sachsen",
    "wof:name":"Siegfried Rink",
    "wof:placetype":"venue"
},
  "geometry": {"coordinates":[12.417246,51.321777],"type":"Point"}
}