{
  "type": "Feature",
  "properties": {
    "iso:country":"DE",
    "sg:address":"Bernsdorfer Str. 51b",
    "sg:city":"Chemnitz",
    "sg:phone":"+49 371/5211382",
    "sg:postcode":"09126",
    "sg:province":"Sachsen",
    "wof:name":"Erika Friede",
    "wof:placetype":"venue"
},
  "geometry": {"coordinates":[12.9352016449,50.8201675415],"type":"Point"}
}