{
  "type": "Feature",
  "properties": {
    "iso:country":"DE",
    "sg:address":"Reetzer Str. 1",
    "sg:city":"Baek",
    "sg:phone":"+49 38782/40216",
    "sg:postcode":"19348",
    "sg:province":"Brandenburg",
    "wof:name":"Detlef Hoppe",
    "wof:placetype":"venue"
},
  "geometry": {"coordinates":[11.911709,53.163815],"type":"Point"}
}