{
  "type": "Feature",
  "properties": {
    "iso:country":"DE",
    "sg:address":"Hauptstr. 103",
    "sg:city":"Herborn",
    "sg:phone":"+49 2772/2556",
    "sg:postcode":"35745",
    "sg:province":"Hessen",
    "wof:name":"Hubert Kuhlmann & Sohn Inh. Friedel Schmidt",
    "wof:placetype":"venue"
},
  "geometry": {"coordinates":[8.3044643402,50.6807975769],"type":"Point"}
}