{
  "type": "Feature",
  "properties": {
    "iso:country":"DE",
    "sg:address":"Huestr. 1",
    "sg:city":"Bochum",
    "sg:postcode":"44787",
    "sg:province":"Nordrhein-Westfalen",
    "wof:name":"Reisewelt Bochum Gmbh",
    "wof:placetype":"venue"
},
  "geometry": {"coordinates":[7.2217421532,51.4793434143],"type":"Point"}
}