{
  "type": "Feature",
  "properties": {
    "iso:country":"DE",
    "sg:address":"Holtenauer Str. 237",
    "sg:city":"Kiel",
    "sg:phone":"+49 431/333140",
    "sg:postcode":"24106",
    "sg:province":"Schleswig-Holstein",
    "wof:name":"Mario Sch\u00e4fer Masseur",
    "wof:placetype":"venue"
},
  "geometry": {"coordinates":[10.132124,54.349483],"type":"Point"}
}