{
  "type": "Feature",
  "properties": {
    "iso:country":"DE",
    "sg:address":"D\u00fcsselburger Str. 11",
    "sg:city":"Rehburg-Loccum",
    "sg:phone":"+49 5037/98081",
    "sg:postcode":"31547",
    "sg:province":"Niedersachsen",
    "wof:name":"Wilhelm Engelke",
    "wof:placetype":"venue"
},
  "geometry": {"coordinates":[9.225179,52.481464],"type":"Point"}
}