{
  "type": "Feature",
  "properties": {
    "iso:country":"DE",
    "sg:address":"Klosterstr. 16",
    "sg:city":"Bad Oeynhausen",
    "sg:phone":"+49 5731/260825",
    "sg:postcode":"32545",
    "sg:province":"Nordrhein-Westfalen",
    "wof:name":"Schormann",
    "wof:placetype":"venue"
},
  "geometry": {"coordinates":[8.797892,52.203632],"type":"Point"}
}