{
  "type": "Feature",
  "properties": {
    "iso:country":"DE",
    "sg:address":"K\u00f6lner Str. 76",
    "sg:city":"Leverkusen",
    "sg:phone":"+49 2171",
    "sg:postcode":"51379",
    "sg:province":"Nordrhein-Westfalen",
    "wof:name":"Creatingart",
    "wof:placetype":"venue"
},
  "geometry": {"coordinates":[7.003656,51.062611],"type":"Point"}
}