{
  "type": "Feature",
  "properties": {
    "iso:country":"DE",
    "sg:address":"Gaustr. 15",
    "sg:city":"Selzen",
    "sg:phone":"+49 6737/229",
    "sg:postcode":"55278",
    "sg:province":"Rheinland-Pfalz",
    "wof:name":"B. Binzel",
    "wof:placetype":"venue"
},
  "geometry": {"coordinates":[8.2531890869,49.8639602661],"type":"Point"}
}