{
  "type": "Feature",
  "properties": {
    "iso:country":"DE",
    "sg:address":"Berkendeich 2",
    "sg:city":"Rietberg",
    "sg:phone":"+49 2944/97980",
    "sg:postcode":"33397",
    "sg:province":"Nordrhein-Westfalen",
    "wof:name":"Kraft Steuerungstechnik Gmbh",
    "wof:placetype":"venue"
},
  "geometry": {"coordinates":[8.398672,51.756683],"type":"Point"}
}