{
  "type": "Feature",
  "properties": {
    "iso:country":"DE",
    "sg:address":"Frankenfurt 1b",
    "sg:city":"Ottendorf-Okrilla",
    "sg:phone":"+49 4935/2054500",
    "sg:postcode":"01458",
    "sg:province":"Sachsen",
    "wof:name":"Ottendorfer M\u00dchlenb\u00c4cker Gmbh",
    "wof:placetype":"venue"
},
  "geometry": {"coordinates":[13.818609,51.183643],"type":"Point"}
}