{
  "type": "Feature",
  "properties": {
    "iso:country":"DE",
    "sg:address":"Hauptstr. 61",
    "sg:city":"Gaggenau",
    "sg:phone":"+49 7225/71649",
    "sg:postcode":"76571",
    "sg:province":"Baden-W\u00fcrttemberg",
    "wof:name":"Marion Rittler",
    "wof:placetype":"venue"
},
  "geometry": {"coordinates":[8.319774,48.803394],"type":"Point"}
}