{
  "type": "Feature",
  "properties": {
    "iso:country":"DE",
    "sg:address":"Otto-Hahn-Str 22",
    "sg:city":"Dachau",
    "sg:phone":"+49 8061/92141",
    "sg:postcode":"85221",
    "sg:province":"Bayern",
    "wof:name":"Walter Werner",
    "wof:placetype":"venue"
},
  "geometry": {"coordinates":[12.00863,47.862041],"type":"Point"}
}