{
  "type": "Feature",
  "properties": {
    "iso:country":"DE",
    "sg:address":"Friedenstr. 7",
    "sg:city":"L\u00fcbeck",
    "sg:postcode":"23554",
    "sg:province":"Schleswig-Holstein",
    "wof:name":"Modeltalk Fotomodell- Vermittlung E. K.",
    "wof:placetype":"venue"
},
  "geometry": {"coordinates":[10.674277,53.873924],"type":"Point"}
}