{
  "type": "Feature",
  "properties": {
    "iso:country":"DE",
    "sg:address":"Neuk\u00f6llnische Allee 156",
    "sg:city":"Berlin",
    "sg:phone":"+49 30/68809887",
    "sg:postcode":"12057",
    "sg:province":"Berlin",
    "wof:name":"Tks Technischer Kundendienst L\u00fcftung Und Service Gmbh",
    "wof:placetype":"venue"
},
  "geometry": {"coordinates":[13.471501,52.461712],"type":"Point"}
}