{
  "type": "Feature",
  "properties": {
    "iso:country":"DE",
    "sg:address":"Konrad-Adenauer-Str. 26",
    "sg:city":"Langenhagen",
    "sg:postcode":"30853",
    "sg:province":"Niedersachsen",
    "wof:name":"Dabag Personenbef\u00f6rderungsges. Mbh",
    "wof:placetype":"venue"
},
  "geometry": {"coordinates":[9.74519,52.439819],"type":"Point"}
}