{
  "type": "Feature",
  "properties": {
    "iso:country":"DE",
    "sg:address":"Eisenh\u00fcttenstr. 12",
    "sg:city":"Siegen",
    "sg:phone":"+49 271/660660",
    "sg:postcode":"57074",
    "sg:province":"Nordrhein-Westfalen",
    "wof:name":"Schneider",
    "wof:placetype":"venue"
},
  "geometry": {"coordinates":[8.0523729324,50.8702011108],"type":"Point"}
}