{
  "type": "Feature",
  "properties": {
    "iso:country":"DE",
    "sg:address":"Scharringhausen 22",
    "sg:city":"Kirchdorf",
    "sg:phone":"+49 4273/252",
    "sg:postcode":"27245",
    "sg:province":"Niedersachsen",
    "wof:name":"Eckhard Henke",
    "wof:placetype":"venue"
},
  "geometry": {"coordinates":[8.799914,52.597565],"type":"Point"}
}