{
  "type": "Feature",
  "properties": {
    "iso:country":"DE",
    "sg:address":"Hanns-Martin-Schleyer-Str 27",
    "sg:city":"Willich",
    "sg:phone":"+49 2154/484876",
    "sg:postcode":"47877",
    "sg:province":"Nordrhein-Westfalen",
    "wof:name":"Plasticmachinery Metzer Gmbh",
    "wof:placetype":"venue"
},
  "geometry": {"coordinates":[6.5147709846,51.2795028687],"type":"Point"}
}