{
  "type": "Feature",
  "properties": {
    "iso:country":"DE",
    "sg:address":"Gerhart-Hauptmann-Str. 20",
    "sg:city":"Greiz",
    "sg:phone":"+49 3661/430654",
    "sg:postcode":"07973",
    "sg:province":"Th\u00fcringen",
    "wof:name":"A. Neudeck",
    "wof:placetype":"venue"
},
  "geometry": {"coordinates":[12.213857,50.664993],"type":"Point"}
}