{
  "type": "Feature",
  "properties": {
    "iso:country":"DE",
    "sg:address":"Am Seedamm 44",
    "sg:city":"Frankfurt",
    "sg:postcode":"60489",
    "sg:province":"Hessen",
    "wof:name":"Rosenthaler Hof Altbau Gmbh",
    "wof:placetype":"venue"
},
  "geometry": {"coordinates":[8.5986528397,50.1266288757],"type":"Point"}
}