{
  "type": "Feature",
  "properties": {
    "iso:country":"DE",
    "sg:address":"Die Reihe 22",
    "sg:city":"Rinteln",
    "sg:phone":"+49 5751/957403",
    "sg:postcode":"31737",
    "sg:province":"Niedersachsen",
    "wof:name":"Manfred Qu\u00e4ck",
    "wof:placetype":"venue"
},
  "geometry": {"coordinates":[9.034627,52.164532],"type":"Point"}
}