{
  "type": "Feature",
  "properties": {
    "iso:country":"DE",
    "sg:address":"Vogelsbergstr. 106",
    "sg:city":"Lauterbach",
    "sg:phone":"+49 6641/3351",
    "sg:postcode":"36341",
    "sg:province":"Hessen",
    "wof:name":"Hans Andert",
    "wof:placetype":"venue"
},
  "geometry": {"coordinates":[9.395767,50.628223],"type":"Point"}
}