{
  "type": "Feature",
  "properties": {
    "iso:country":"DE",
    "sg:address":"Bachstr. 14",
    "sg:city":"M\u00f6nsheim",
    "sg:phone":"+49 4970/447429",
    "sg:postcode":"71297",
    "sg:province":"Baden-W\u00fcrttemberg",
    "wof:name":"Genossenschaftsbank M\u00f6nsheim Eg",
    "wof:placetype":"venue"
},
  "geometry": {"coordinates":[8.863368,48.862324],"type":"Point"}
}