{
  "type": "Feature",
  "properties": {
    "iso:country":"DE",
    "sg:address":"Pflasterstr. 6",
    "sg:city":"Erdmannhausen",
    "sg:phone":"+49 7144/6263",
    "sg:postcode":"71729",
    "sg:province":"Baden-W\u00fcrttemberg",
    "wof:name":"Bernd Frank",
    "wof:placetype":"venue"
},
  "geometry": {"coordinates":[9.2970380783,48.9407424927],"type":"Point"}
}