{
  "type": "Feature",
  "properties": {
    "iso:country":"DE",
    "sg:address":"Hauptstr. 26",
    "sg:city":"Weseram",
    "sg:phone":"+49 33831/30283",
    "sg:postcode":"14778",
    "sg:province":"Brandenburg",
    "wof:name":"D. Michalak",
    "wof:placetype":"venue"
},
  "geometry": {"coordinates":[12.6698865891,52.4631462097],"type":"Point"}
}