{
  "type": "Feature",
  "properties": {
    "iso:country":"DE",
    "sg:address":"Breitenbruch 72",
    "sg:city":"Oberhausen",
    "sg:phone":"+49 208/840346",
    "sg:postcode":"46049",
    "sg:province":"Nordrhein-Westfalen",
    "wof:name":"Erlenkrug",
    "wof:placetype":"venue"
},
  "geometry": {"coordinates":[6.8255739212,51.4616317749],"type":"Point"}
}