{
  "type": "Feature",
  "properties": {
    "iso:country":"DE",
    "sg:address":"Hauptstr. 11",
    "sg:city":"Gifhorn",
    "sg:phone":"+49 5371/728022",
    "sg:postcode":"38518",
    "sg:province":"Niedersachsen",
    "wof:name":"Anjo Fruit Ag",
    "wof:placetype":"venue"
},
  "geometry": {"coordinates":[10.537855,52.520317],"type":"Point"}
}