{
  "type": "Feature",
  "properties": {
    "iso:country":"DE",
    "sg:address":"Hugstrasse 43",
    "sg:city":"Goeppingen",
    "sg:phone":"+49 7161/683599",
    "sg:postcode":"73035",
    "sg:province":"Baden-W\u00fcrttemberg",
    "wof:name":"Fussballcity.de",
    "wof:placetype":"venue"
},
  "geometry": {"coordinates":[9.6375904083,48.6969299316],"type":"Point"}
}