{
  "type": "Feature",
  "properties": {
    "iso:country":"DE",
    "sg:address":"Hahnbrunner Str. 8",
    "sg:city":"Kaiserslautern",
    "sg:phone":"+49 631/77633",
    "sg:postcode":"67659",
    "sg:province":"Rheinland-Pfalz",
    "wof:name":"Klaus H\u00f6hn Masseur",
    "wof:placetype":"venue"
},
  "geometry": {"coordinates":[7.733057,49.458569],"type":"Point"}
}