{
  "type": "Feature",
  "properties": {
    "iso:country":"DE",
    "sg:address":"Wilhelmstr. 30a",
    "sg:city":"Elmshorn",
    "sg:phone":"+49 4121/807480",
    "sg:postcode":"25336",
    "sg:province":"Schleswig-Holstein",
    "wof:name":"Hannemann Und Kr\u00fctzfeldt Architekten",
    "wof:placetype":"venue"
},
  "geometry": {"coordinates":[9.638817,53.740982],"type":"Point"}
}