{
  "type": "Feature",
  "properties": {
    "iso:country":"DE",
    "sg:address":"Schulstr. 22",
    "sg:city":"Wei\u00dfenstadt",
    "sg:phone":"+49 9253/268",
    "sg:postcode":"95163",
    "sg:province":"Bayern",
    "wof:name":"K. H. Kiesling",
    "wof:placetype":"venue"
},
  "geometry": {"coordinates":[11.8877668381,50.1016197205],"type":"Point"}
}