{
  "type": "Feature",
  "properties": {
    "iso:country":"DE",
    "sg:address":"Badstr. 19",
    "sg:city":"Berlin",
    "sg:phone":"+49 30/4936046",
    "sg:postcode":"13357",
    "sg:province":"Berlin",
    "wof:name":"Die Brille Badstr. Gmbh",
    "wof:placetype":"venue"
},
  "geometry": {"coordinates":[13.3833961487,52.5517082214],"type":"Point"}
}