{
  "type": "Feature",
  "properties": {
    "iso:country":"DE",
    "sg:address":"Wetzlarer Str. 7 a",
    "sg:city":"Dietzenbach",
    "sg:phone":"+49 6074/25506",
    "sg:postcode":"63128",
    "sg:province":"Hessen",
    "wof:name":"Die Immobilie E. K.",
    "wof:placetype":"venue"
},
  "geometry": {"coordinates":[8.7729187012,49.9999008179],"type":"Point"}
}