{
  "type": "Feature",
  "properties": {
    "iso:country":"DE",
    "sg:address":"Klever Str. 48",
    "sg:city":"Geldern",
    "sg:phone":"+49 2831/93080",
    "sg:postcode":"47608",
    "sg:province":"Nordrhein-Westfalen",
    "wof:name":"Regent M\u00f6bel Beteiligungs-gmbh & Co. Kg",
    "wof:placetype":"venue"
},
  "geometry": {"coordinates":[6.284118,51.527966],"type":"Point"}
}