{
  "type": "Feature",
  "properties": {
    "iso:country":"DE",
    "sg:address":"Schuckert Str. 6",
    "sg:city":"Gescher",
    "sg:phone":"+49 4925/421001",
    "sg:postcode":"48712",
    "sg:province":"Nordrhein-Westfalen",
    "wof:name":"Aluguss Beulker Gmbh & Co. Kg",
    "wof:placetype":"venue"
},
  "geometry": {"coordinates":[7.028319,51.941978],"type":"Point"}
}