{
  "type": "Feature",
  "properties": {
    "iso:country":"DE",
    "sg:address":"Kilian-Spiegel-Str. 20",
    "sg:city":"Michelstadt",
    "sg:phone":"+49 6061/71420",
    "sg:postcode":"64720",
    "sg:province":"Hessen",
    "wof:name":"Thomas P. Lang Gmbh",
    "wof:placetype":"venue"
},
  "geometry": {"coordinates":[9.0147047043,49.6703491211],"type":"Point"}
}