{
  "type": "Feature",
  "properties": {
    "iso:country":"DE",
    "sg:address":"Am Baum 1",
    "sg:city":"Hamburg",
    "sg:postcode":"21029",
    "sg:province":"Hamburg",
    "wof:name":"St\u00e4dele-immobilien- Gesellschaft Mbh & Co. Kg",
    "wof:placetype":"venue"
},
  "geometry": {"coordinates":[10.2185297012,53.4879188538],"type":"Point"}
}