{
  "type": "Feature",
  "properties": {
    "iso:country":"DE",
    "sg:address":"Hauptstr. 34",
    "sg:city":"Schweinfurt",
    "sg:phone":"+49 9721/88355",
    "sg:postcode":"97424",
    "sg:province":"Bayern",
    "wof:name":"Schwarzer Adler",
    "wof:placetype":"venue"
},
  "geometry": {"coordinates":[10.2013835907,50.027557373],"type":"Point"}
}