{
  "type": "Feature",
  "properties": {
    "iso:country":"DE",
    "sg:address":"Petzvalstr 37",
    "sg:city":"Braunschweig",
    "sg:phone":"+49 531/237280",
    "sg:postcode":"38104",
    "sg:province":"Niedersachsen",
    "wof:name":"Teleplast Gmbh & Co Kg",
    "wof:placetype":"venue"
},
  "geometry": {"coordinates":[10.5749158859,52.2877693176],"type":"Point"}
}