{
  "type": "Feature",
  "properties": {
    "iso:country":"DE",
    "sg:address":"S\u00fcdring 5",
    "sg:city":"Oldenburg",
    "sg:phone":"+49 441/602880",
    "sg:postcode":"26125",
    "sg:province":"Niedersachsen",
    "wof:name":"Dumitru Cibotari",
    "wof:placetype":"venue"
},
  "geometry": {"coordinates":[8.207526,53.198669],"type":"Point"}
}