{
  "type": "Feature",
  "properties": {
    "iso:country":"DE",
    "sg:address":"Harlinger Str. 98",
    "sg:city":"Hitzacker",
    "sg:phone":"+49 5862/6715",
    "sg:postcode":"29456",
    "sg:province":"Niedersachsen",
    "wof:name":"H. Von Houtem",
    "wof:placetype":"venue"
},
  "geometry": {"coordinates":[10.9858388901,53.1512947083],"type":"Point"}
}