{
  "type": "Feature",
  "properties": {
    "iso:country":"DE",
    "sg:address":"Dreiringplatz 10",
    "sg:city":"Essen",
    "sg:phone":"+49 201/8880225",
    "sg:postcode":"45276",
    "sg:province":"Nordrhein-Westfalen",
    "wof:name":"Stadtbibliothek Essen Bezirksbibliothek Steele",
    "wof:placetype":"venue"
},
  "geometry": {"coordinates":[7.080194,51.446163],"type":"Point"}
}