{
  "type": "Feature",
  "properties": {
    "iso:country":"DE",
    "sg:address":"Rimloser Str. 72",
    "sg:city":"Lauterbach",
    "sg:phone":"+49 661/919025",
    "sg:postcode":"36341",
    "sg:province":"Hessen",
    "wof:name":"Z\u00fcrich Agrippina",
    "wof:placetype":"venue"
},
  "geometry": {"coordinates":[9.3844690323,50.6419258118],"type":"Point"}
}