{
  "type": "Feature",
  "properties": {
    "iso:country":"DE",
    "sg:address":"Frankfurter Chaussee 17",
    "sg:city":"Vogelsdorf",
    "sg:phone":"+49 33439/78393",
    "sg:postcode":"15370",
    "sg:province":"Brandenburg",
    "wof:name":"Vogelsdorfer Discotheken Verwaltungs Gmbh",
    "wof:placetype":"venue"
},
  "geometry": {"coordinates":[13.740889,52.499416],"type":"Point"}
}