{
  "type": "Feature",
  "properties": {
    "iso:country":"DE",
    "sg:address":"Hauptstr 46",
    "sg:city":"Lichtenau",
    "sg:phone":"+49 7227/4041",
    "sg:postcode":"77839",
    "sg:province":"Baden-W\u00fcrttemberg",
    "wof:name":"Selection Hotelinterior Vertriebsgesellschaft Mbh",
    "wof:placetype":"venue"
},
  "geometry": {"coordinates":[8.006023407,48.7265892029],"type":"Point"}
}