{
  "type": "Feature",
  "properties": {
    "iso:country":"DE",
    "sg:address":"Kampstr. 23",
    "sg:city":"Hagen",
    "sg:phone":"+49 2331/184112",
    "sg:postcode":"58095",
    "sg:province":"Nordrhein-Westfalen",
    "wof:name":"Ibosonic Waren-handels Gmbh",
    "wof:placetype":"venue"
},
  "geometry": {"coordinates":[7.4708461761,51.3565063477],"type":"Point"}
}