{
  "type": "Feature",
  "properties": {
    "iso:country":"DE",
    "sg:address":"Siedlung 15",
    "sg:city":"Ruppertsgr\u00fcn",
    "sg:phone":"+49 37439/6331",
    "sg:postcode":"08543",
    "sg:province":"Sachsen",
    "wof:name":"Keller Trockenbau Gmbh",
    "wof:placetype":"venue"
},
  "geometry": {"coordinates":[12.18296,50.584881],"type":"Point"}
}