{
  "type": "Feature",
  "properties": {
    "iso:country":"DE",
    "sg:address":"Hirschberger Str. 4",
    "sg:city":"Schee\u00dfel",
    "sg:phone":"+49 4263/1287",
    "sg:postcode":"27383",
    "sg:province":"Niedersachsen",
    "wof:name":"Hermann Nielebock",
    "wof:placetype":"venue"
},
  "geometry": {"coordinates":[9.491841,53.178555],"type":"Point"}
}