{
  "type": "Feature",
  "properties": {
    "iso:country":"DE",
    "sg:address":"Erlenstegenstr. 71 b",
    "sg:city":"N\u00fcrnberg",
    "sg:phone":"+49 911/591081",
    "sg:postcode":"90491",
    "sg:province":"Bayern",
    "wof:name":"Gerhard Wolf",
    "wof:placetype":"venue"
},
  "geometry": {"coordinates":[11.13349,49.471771],"type":"Point"}
}