{
  "type": "Feature",
  "properties": {
    "iso:country":"DE",
    "sg:address":"Eichendorffstr. 7",
    "sg:city":"Ingelfingen",
    "sg:phone":"+49 7940/544059",
    "sg:postcode":"74653",
    "sg:province":"Baden-W\u00fcrttemberg",
    "wof:name":"Target Aktionsm\u00e4rkte Und Warenhandels Gmbh",
    "wof:placetype":"venue"
},
  "geometry": {"coordinates":[9.6599769592,49.2979240417],"type":"Point"}
}