{
  "type": "Feature",
  "properties": {
    "iso:country":"DE",
    "sg:address":"Stadtlohner Str. 41",
    "sg:city":"Ahaus",
    "sg:phone":"+49 2561/81982",
    "sg:postcode":"48683",
    "sg:province":"Nordrhein-Westfalen",
    "wof:name":"J. Leppen",
    "wof:placetype":"venue"
},
  "geometry": {"coordinates":[6.9771909714,52.0665893555],"type":"Point"}
}