{
  "type": "Feature",
  "properties": {
    "iso:country":"DE",
    "sg:address":"Herrenpfad-S\u00fcd 46",
    "sg:city":"Nettetal",
    "sg:postcode":"41334",
    "sg:province":"Nordrhein-Westfalen",
    "wof:name":"Mekkafood Halal Products E. K.",
    "wof:placetype":"venue"
},
  "geometry": {"coordinates":[6.2183198929,51.3244018555],"type":"Point"}
}