{
  "type": "Feature",
  "properties": {
    "iso:country":"DE",
    "sg:address":"Rathausplatz 11",
    "sg:city":"Hemmingen",
    "sg:phone":"+49 511/421132",
    "sg:postcode":"30966",
    "sg:province":"Niedersachsen",
    "wof:name":"Blumen-hesse",
    "wof:placetype":"venue"
},
  "geometry": {"coordinates":[9.725348,52.32584],"type":"Point"}
}