{
  "type": "Feature",
  "properties": {
    "iso:country":"DE",
    "sg:address":"Horber Str. 7",
    "sg:city":"Sulz",
    "sg:phone":"+49 7454/96160",
    "sg:postcode":"72172",
    "sg:province":"Baden-W\u00fcrttemberg",
    "wof:name":"E. Schmid",
    "wof:placetype":"venue"
},
  "geometry": {"coordinates":[8.692433,48.38253],"type":"Point"}
}