{
  "type": "Feature",
  "properties": {
    "iso:country":"DE",
    "sg:address":"Gotenstr. 25",
    "sg:city":"Mannheim",
    "sg:phone":"+49 621/701056",
    "sg:postcode":"68259",
    "sg:province":"Baden-W\u00fcrttemberg",
    "wof:name":"Promarketing Gmbh",
    "wof:placetype":"venue"
},
  "geometry": {"coordinates":[8.5552883148,49.4994392395],"type":"Point"}
}