{
  "type": "Feature",
  "properties": {
    "iso:country":"DE",
    "sg:address":"Auf dem Orth 10",
    "sg:city":"K\u00f6ln",
    "sg:phone":"+49 221/684424",
    "sg:postcode":"51069",
    "sg:province":"Nordrhein-Westfalen",
    "wof:name":"Hans-joachim Wilkens Architekt",
    "wof:placetype":"venue"
},
  "geometry": {"coordinates":[7.067889,50.974354],"type":"Point"}
}