{
  "type": "Feature",
  "properties": {
    "iso:country":"DE",
    "sg:address":"Waisenhausstr. 5",
    "sg:city":"Pirmasens",
    "sg:phone":"+49 6331/21180",
    "sg:postcode":"66954",
    "sg:province":"Rheinland-Pfalz",
    "wof:name":"Die Johanniter",
    "wof:placetype":"venue"
},
  "geometry": {"coordinates":[7.594578,49.194363],"type":"Point"}
}