{
  "type": "Feature",
  "properties": {
    "iso:country":"DE",
    "sg:address":"Karlsbader Str. 2",
    "sg:city":"Rockenberg",
    "sg:phone":"+49 6033/6912",
    "sg:postcode":"35519",
    "sg:province":"Hessen",
    "wof:name":"Kohler Gmbh Prozessautomation",
    "wof:placetype":"venue"
},
  "geometry": {"coordinates":[8.7371912003,50.4330253601],"type":"Point"}
}