{
  "type": "Feature",
  "properties": {
    "iso:country":"DE",
    "sg:address":"Forsthaus Buchenau",
    "sg:city":"Boppard",
    "sg:phone":"+49 6742/3938",
    "sg:postcode":"56154",
    "sg:province":"Rheinland-Pfalz",
    "wof:name":"Hotel Royal Garni",
    "wof:placetype":"venue"
},
  "geometry": {"coordinates":[7.6074390411,50.2063179016],"type":"Point"}
}