{
  "type": "Feature",
  "properties": {
    "iso:country":"DE",
    "sg:address":"Edisonstr. 15",
    "sg:city":"B\u00f6nen",
    "sg:phone":"+49 2383/951154",
    "sg:postcode":"59199",
    "sg:province":"Nordrhein-Westfalen",
    "wof:name":"Wmu- W\u00e4rmebehandlungsanlagen F\u00fcr Industrie Und Umwelt-",
    "wof:placetype":"venue"
},
  "geometry": {"coordinates":[7.7758231163,51.6121635437],"type":"Point"}
}