{
  "type": "Feature",
  "properties": {
    "iso:country":"DE",
    "sg:address":"Marktstr. 68",
    "sg:city":"Klettgau",
    "sg:phone":"+49 7742/6921",
    "sg:postcode":"79771",
    "sg:province":"Baden-W\u00fcrttemberg",
    "wof:name":"Adolf Spitznagel",
    "wof:placetype":"venue"
},
  "geometry": {"coordinates":[8.415867,47.62347],"type":"Point"}
}