{
  "type": "Feature",
  "properties": {
    "iso:country":"DE",
    "sg:address":"Dunkbachstr. 9",
    "sg:city":"Tecklenburg",
    "sg:phone":"+49 4954/051000",
    "sg:postcode":"49545",
    "sg:province":"Nordrhein-Westfalen",
    "wof:name":"Friedrich Brackmann & S\u00d6hne",
    "wof:placetype":"venue"
},
  "geometry": {"coordinates":[7.8822541237,52.2301063538],"type":"Point"}
}