{
  "type": "Feature",
  "properties": {
    "iso:country":"DE",
    "sg:address":"Wildemanner Str. 17",
    "sg:city":"Langelsheim",
    "sg:phone":"+49 5325/6042",
    "sg:postcode":"38685",
    "sg:province":"Niedersachsen",
    "wof:name":"Museumsgastst\u00e4tten",
    "wof:placetype":"venue"
},
  "geometry": {"coordinates":[10.2833747864,51.8645133972],"type":"Point"}
}