{
  "type": "Feature",
  "properties": {
    "iso:country":"DE",
    "sg:address":"Wendenhammer 3",
    "sg:city":"Marktleuthen",
    "sg:phone":"+49 9235/388",
    "sg:postcode":"95168",
    "sg:province":"Bayern",
    "wof:name":"Pecher Kunststoff-technik Gmbh",
    "wof:placetype":"venue"
},
  "geometry": {"coordinates":[12.052122,50.12191],"type":"Point"}
}