{
  "type": "Feature",
  "properties": {
    "iso:country":"DE",
    "sg:address":"Kadettenweg 57",
    "sg:city":"Berlin",
    "sg:phone":"+49 30/67549864",
    "sg:postcode":"12205",
    "sg:province":"Berlin",
    "wof:name":"Gerhard Hildebrandt Architekt",
    "wof:placetype":"venue"
},
  "geometry": {"coordinates":[13.298944,52.435711],"type":"Point"}
}