{
  "type": "Feature",
  "properties": {
    "iso:country":"DE",
    "sg:address":"Friedrichstr. 1",
    "sg:city":"Waibstadt",
    "sg:phone":"+49 7263/5927",
    "sg:postcode":"74915",
    "sg:province":"Baden-W\u00fcrttemberg",
    "wof:name":"Heinz Rieser",
    "wof:placetype":"venue"
},
  "geometry": {"coordinates":[8.9195537567,49.2954216003],"type":"Point"}
}