{
  "type": "Feature",
  "properties": {
    "iso:country":"DE",
    "sg:address":"Falckensteinstr. 42",
    "sg:city":"Berlin",
    "sg:phone":"+49 30/6183420",
    "sg:postcode":"10997",
    "sg:province":"Berlin",
    "wof:name":"Claus Barth",
    "wof:placetype":"venue"
},
  "geometry": {"coordinates":[13.443566,52.499451],"type":"Point"}
}