{
  "type": "Feature",
  "properties": {
    "iso:country":"DE",
    "sg:address":"Wilhelm-Raabe-Str. 13",
    "sg:city":"Bad Pyrmont",
    "sg:phone":"+49 5281/609958",
    "sg:postcode":"31812",
    "sg:province":"Niedersachsen",
    "wof:name":"Rainer Kuntze",
    "wof:placetype":"venue"
},
  "geometry": {"coordinates":[9.2285423279,51.9835205078],"type":"Point"}
}