{
  "type": "Feature",
  "properties": {
    "iso:country":"DE",
    "sg:address":"Schwalbacher Str. 67",
    "sg:city":"Wiesbaden",
    "sg:phone":"+49 611/9518762",
    "sg:postcode":"65183",
    "sg:province":"Hessen",
    "wof:name":"Bestattungen Henrich",
    "wof:placetype":"venue"
},
  "geometry": {"coordinates":[8.236244,50.083607],"type":"Point"}
}