{
  "type": "Feature",
  "properties": {
    "iso:country":"DE",
    "sg:address":"Klafterzeile 7",
    "sg:city":"Berlin",
    "sg:phone":"+49 30/65908201",
    "sg:postcode":"12559",
    "sg:province":"Berlin",
    "wof:name":"Sallmann Holzschutz Gmbh",
    "wof:placetype":"venue"
},
  "geometry": {"coordinates":[13.679054,52.419727],"type":"Point"}
}