{
  "type": "Feature",
  "properties": {
    "iso:country":"DE",
    "sg:address":"Robert-Blum-Str. 31",
    "sg:city":"Annaberg-Buchholz",
    "sg:phone":"+49 3733/289916",
    "sg:postcode":"09456",
    "sg:province":"Sachsen",
    "wof:name":"Pro Dach Gmbh",
    "wof:placetype":"venue"
},
  "geometry": {"coordinates":[13.01466,50.58086],"type":"Point"}
}