{
  "type": "Feature",
  "properties": {
    "iso:country":"DE",
    "sg:address":"L\u00fctzowstr. 249",
    "sg:city":"Solingen",
    "sg:postcode":"42653",
    "sg:province":"Nordrhein-Westfalen",
    "wof:name":"Deutsche Rheuma Liga Arbeitsgemeinsch. Solingen",
    "wof:placetype":"venue"
},
  "geometry": {"coordinates":[7.0866680145,51.2065544128],"type":"Point"}
}