{
  "type": "Feature",
  "properties": {
    "iso:country":"DE",
    "sg:address":"Im Sportzentrum 7",
    "sg:city":"Eppenbrunn",
    "sg:phone":"+49 6335/7300",
    "sg:postcode":"66957",
    "sg:province":"Rheinland-Pfalz",
    "wof:name":"Sportgemeinschaft Fu\u00dfballverein",
    "wof:placetype":"venue"
},
  "geometry": {"coordinates":[7.5703477859,49.1128883362],"type":"Point"}
}