{
  "type": "Feature",
  "properties": {
    "iso:country":"DE",
    "sg:address":"Daimlerstra\u00dfe 10",
    "sg:city":"Hainburg",
    "sg:phone":"+49 6182/95970",
    "sg:postcode":"63512",
    "sg:province":"Hessen",
    "wof:name":"Kfz.-sachverst\u00e4ndigenb\u00fcro Drewes",
    "wof:placetype":"venue"
},
  "geometry": {"coordinates":[8.966406,50.066727],"type":"Point"}
}