{
  "type": "Feature",
  "properties": {
    "iso:country":"DE",
    "sg:address":"Eberhardstr. 9",
    "sg:city":"Backnang",
    "sg:phone":"+49 7191/68605",
    "sg:postcode":"71522",
    "sg:province":"Baden-W\u00fcrttemberg",
    "wof:name":"Bierakademie",
    "wof:placetype":"venue"
},
  "geometry": {"coordinates":[9.4223327637,48.9458007812],"type":"Point"}
}