{
  "type": "Feature",
  "properties": {
    "iso:country":"DE",
    "sg:address":"Kantstr. 54",
    "sg:city":"Berlin",
    "sg:phone":"+49 30/31508476",
    "sg:postcode":"10627",
    "sg:province":"Berlin",
    "wof:name":"Pegasus Dental-technik Gmbh",
    "wof:placetype":"venue"
},
  "geometry": {"coordinates":[13.3084878922,52.5067863464],"type":"Point"}
}