{
  "type": "Feature",
  "properties": {
    "iso:country":"DE",
    "sg:address":"Richthofenstr. 42",
    "sg:city":"Kitzingen",
    "sg:phone":"+49 9321/31404",
    "sg:postcode":"97318",
    "sg:province":"Bayern",
    "wof:name":"Zimmermann-reisen Inh. Hans Zimmermann",
    "wof:placetype":"venue"
},
  "geometry": {"coordinates":[10.1798849106,49.7447662354],"type":"Point"}
}