{
  "type": "Feature",
  "properties": {
    "iso:country":"DE",
    "sg:address":"Graf-Lehndorff-Str. 36",
    "sg:city":"M\u00fcnchen",
    "sg:phone":"+49 89/94500578",
    "sg:postcode":"81929",
    "sg:province":"Bayern",
    "wof:name":"Fisch Web-service Online-shop",
    "wof:placetype":"venue"
},
  "geometry": {"coordinates":[11.672429,48.145393],"type":"Point"}
}