{
  "type": "Feature",
  "properties": {
    "iso:country":"DE",
    "sg:address":"Dr\u00f6genstr. 26",
    "sg:city":"Minden",
    "sg:phone":"+49 571/44445",
    "sg:postcode":"32427",
    "sg:province":"Nordrhein-Westfalen",
    "wof:name":"Wilhelm Riechmann",
    "wof:placetype":"venue"
},
  "geometry": {"coordinates":[8.836839,52.304199],"type":"Point"}
}