{
  "type": "Feature",
  "properties": {
    "iso:country":"DE",
    "sg:address":"Beekebreite 18",
    "sg:city":"Georgsmarienh\u00fctte",
    "sg:phone":"+49 5401/838990",
    "sg:postcode":"49124",
    "sg:province":"Niedersachsen",
    "wof:name":"Hans-georg Buchholz",
    "wof:placetype":"venue"
},
  "geometry": {"coordinates":[8.06804,52.222401],"type":"Point"}
}