{
  "type": "Feature",
  "properties": {
    "iso:country":"DE",
    "sg:address":"Ahsener Str. 3",
    "sg:city":"Datteln",
    "sg:phone":"+49 2363/355345",
    "sg:postcode":"45711",
    "sg:province":"Nordrhein-Westfalen",
    "wof:name":"D. Birol",
    "wof:placetype":"venue"
},
  "geometry": {"coordinates":[7.3385539055,51.653011322],"type":"Point"}
}