{
  "type": "Feature",
  "properties": {
    "iso:country":"DE",
    "sg:address":"Beckergrube 71",
    "sg:city":"L\u00fcbeck",
    "sg:phone":"+49 451/704333",
    "sg:postcode":"23552",
    "sg:province":"Schleswig-Holstein",
    "wof:name":"Restaurant Wullenwever",
    "wof:placetype":"venue"
},
  "geometry": {"coordinates":[10.682258606,53.8695259094],"type":"Point"}
}