{
  "type": "Feature",
  "properties": {
    "iso:country":"DE",
    "sg:address":"Fliederbusch 25",
    "sg:city":"Kreuzau",
    "sg:phone":"+49 2422/7924",
    "sg:postcode":"52372",
    "sg:province":"Nordrhein-Westfalen",
    "wof:name":"Helmut Assenmacher",
    "wof:placetype":"venue"
},
  "geometry": {"coordinates":[6.519384861,50.7273139954],"type":"Point"}
}