{
  "type": "Feature",
  "properties": {
    "iso:country":"DE",
    "sg:address":"Hinterf\u00e4hrnweg",
    "sg:city":"Titisee-Neustadt",
    "sg:postcode":"79822",
    "sg:province":"Baden-W\u00fcrttemberg",
    "wof:name":"Feuerwehrerholungsheim St. Florian Inh. Verein",
    "wof:placetype":"venue"
},
  "geometry": {"coordinates":[8.2032423019,47.9289550781],"type":"Point"}
}