{
  "type": "Feature",
  "properties": {
    "iso:country":"DE",
    "sg:address":"Am Hecklehamm 17",
    "sg:city":"H\u00fcgelsheim",
    "sg:phone":"+49 7229/30360",
    "sg:postcode":"76549",
    "sg:province":"Baden-W\u00fcrttemberg",
    "wof:name":"Befu Gmbh & Co. Kg Peter-estrich",
    "wof:placetype":"venue"
},
  "geometry": {"coordinates":[8.113495,48.800575],"type":"Point"}
}