{
  "type": "Feature",
  "properties": {
    "iso:country":"DE",
    "sg:address":"R\u00fcdesheimer Platz 7",
    "sg:city":"Berlin",
    "sg:phone":"+49 30/8212764",
    "sg:postcode":"14197",
    "sg:province":"Berlin",
    "wof:name":"Dr. Med. Annemarie Nitze",
    "wof:placetype":"venue"
},
  "geometry": {"coordinates":[13.3149452209,52.4727172852],"type":"Point"}
}