{
  "type": "Feature",
  "properties": {
    "iso:country":"DE",
    "sg:address":"Martin-Luther-Str. 2",
    "sg:city":"Dresden",
    "sg:phone":"+49 351/8014810",
    "sg:postcode":"01099",
    "sg:province":"Sachsen",
    "wof:name":"Fma Fernmelde- Und Elektro- Anlagenbau Gmbh",
    "wof:placetype":"venue"
},
  "geometry": {"coordinates":[13.755231,51.06308],"type":"Point"}
}