{
  "type": "Feature",
  "properties": {
    "iso:country":"DE",
    "sg:address":"Klottener Str. 17",
    "sg:city":"Cochem",
    "sg:phone":"+49 2671/97990",
    "sg:postcode":"56812",
    "sg:province":"Rheinland-Pfalz",
    "wof:name":"Camping Am Freizeitzentrum",
    "wof:placetype":"venue"
},
  "geometry": {"coordinates":[7.17149,50.151321],"type":"Point"}
}