{
  "type": "Feature",
  "properties": {
    "iso:country":"DE",
    "sg:address":"Beurenweg 39",
    "sg:city":"Leinefelde",
    "sg:postcode":"37327",
    "sg:province":"Th\u00fcringen",
    "wof:name":"Eichsfeld-einkaufscenter Gmbh",
    "wof:placetype":"venue"
},
  "geometry": {"coordinates":[10.309838,51.387405],"type":"Point"}
}