{
  "type": "Feature",
  "properties": {
    "iso:country":"DE",
    "sg:address":"Detmolder Str. 185",
    "sg:city":"Vlotho",
    "sg:phone":"+49 5228/7197",
    "sg:postcode":"32602",
    "sg:province":"Nordrhein-Westfalen",
    "wof:name":"Theodor Obermowe",
    "wof:placetype":"venue"
},
  "geometry": {"coordinates":[8.78721,52.151642],"type":"Point"}
}