{
  "type": "Feature",
  "properties": {
    "iso:country":"DE",
    "sg:address":"Deisterstr. 69",
    "sg:city":"Hannover",
    "sg:phone":"+49 511/444444",
    "sg:postcode":"30449",
    "sg:province":"Niedersachsen",
    "wof:name":"W. M\u00fcller",
    "wof:placetype":"venue"
},
  "geometry": {"coordinates":[9.7168397903,52.363155365],"type":"Point"}
}