{
  "type": "Feature",
  "properties": {
    "iso:country":"DE",
    "sg:address":"Siegfriedstr. 70",
    "sg:city":"Heppenheim",
    "sg:phone":"+49 6252/67647",
    "sg:postcode":"64646",
    "sg:province":"Hessen",
    "wof:name":"W. F\u00f6rderer",
    "wof:placetype":"venue"
},
  "geometry": {"coordinates":[8.648974,49.642708],"type":"Point"}
}