{
  "type": "Feature",
  "properties": {
    "iso:country":"DE",
    "sg:address":"Mittelstr. 8",
    "sg:city":"Wesenberg",
    "sg:phone":"+49 39832/20728",
    "sg:postcode":"17255",
    "sg:province":"Mecklenburg-Vorpommern",
    "wof:name":"U. Wenzel",
    "wof:placetype":"venue"
},
  "geometry": {"coordinates":[12.969588,53.282101],"type":"Point"}
}