{
  "type": "Feature",
  "properties": {
    "iso:country":"DE",
    "sg:address":"Freisinger Str. 25",
    "sg:city":"Markt Indersdorf",
    "sg:phone":"+49 8136/367",
    "sg:postcode":"85229",
    "sg:province":"Bayern",
    "wof:name":"Heinrich Regenbogen",
    "wof:placetype":"venue"
},
  "geometry": {"coordinates":[11.3764686584,48.3631858826],"type":"Point"}
}