{
  "type": "Feature",
  "properties": {
    "iso:country":"DE",
    "sg:address":"Luitpoldstr. 76",
    "sg:city":"Erlangen",
    "sg:phone":"+49 9131/89240",
    "sg:postcode":"91052",
    "sg:province":"Bayern",
    "wof:name":"W Und F Immobilien Gmbh",
    "wof:placetype":"venue"
},
  "geometry": {"coordinates":[11.0233335495,49.5967330933],"type":"Point"}
}