{
  "type": "Feature",
  "properties": {
    "iso:country":"DE",
    "sg:address":"Bahnhofstr. 94",
    "sg:city":"Bordesholm",
    "sg:phone":"+49 4322/4013",
    "sg:postcode":"24582",
    "sg:province":"Schleswig-Holstein",
    "wof:name":"Kath. Pfarramt Maria-hilfe Der Christen",
    "wof:placetype":"venue"
},
  "geometry": {"coordinates":[10.0310964584,54.1729812622],"type":"Point"}
}