{
  "type": "Feature",
  "properties": {
    "iso:country":"DE",
    "sg:address":"Gebhard-Fugel-Weg 29",
    "sg:city":"Ravensburg",
    "sg:postcode":"88214",
    "sg:province":"Baden-W\u00fcrttemberg",
    "wof:name":"Deutsche Verm\u00f6gensberatung Ag",
    "wof:placetype":"venue"
},
  "geometry": {"coordinates":[9.6056804657,47.7685012817],"type":"Point"}
}