{
  "type": "Feature",
  "properties": {
    "iso:country":"DE",
    "sg:address":"Hombroich",
    "sg:city":"Neuss",
    "sg:phone":"+49 2182/1478",
    "sg:postcode":"41472",
    "sg:province":"Nordrhein-Westfalen",
    "wof:name":"Franz Fleuster",
    "wof:placetype":"venue"
},
  "geometry": {"coordinates":[6.654865,51.14159],"type":"Point"}
}