{
  "type": "Feature",
  "properties": {
    "iso:country":"DE",
    "sg:address":"Bahnhofstr. 36",
    "sg:city":"Krumbach",
    "sg:phone":"+49 8282/81166",
    "sg:postcode":"86381",
    "sg:province":"Bayern",
    "wof:name":"Ludwig Vogt Buchhandlung-schreibwaren",
    "wof:placetype":"venue"
},
  "geometry": {"coordinates":[10.3607635498,48.2452774048],"type":"Point"}
}