{
  "type": "Feature",
  "properties": {
    "iso:country":"DE",
    "sg:address":"Kirchstr. 9",
    "sg:city":"Hann. M\u00fcnden",
    "sg:phone":"+49 5541/4974",
    "sg:postcode":"34346",
    "sg:province":"Niedersachsen",
    "wof:name":"Doris Rech",
    "wof:placetype":"venue"
},
  "geometry": {"coordinates":[9.6525859833,51.4164123535],"type":"Point"}
}