{
  "type": "Feature",
  "properties": {
    "iso:country":"DE",
    "sg:address":"Schwarzer Weg 18",
    "sg:city":"H\u00fcnxe - Bruckhausen",
    "sg:phone":"+49 2064",
    "sg:postcode":"46569",
    "sg:province":"Nordrhein-Westfalen",
    "wof:name":"Gartenbau Niederrhein Heskamp",
    "wof:placetype":"venue"
},
  "geometry": {"coordinates":[6.738383,51.592499],"type":"Point"}
}