{
  "type": "Feature",
  "properties": {
    "iso:country":"DE",
    "sg:address":"Grenzweg 19",
    "sg:city":"Wunstorf",
    "sg:phone":"+49 5033/8644",
    "sg:postcode":"31515",
    "sg:province":"Niedersachsen",
    "wof:name":"Fuhrenklause",
    "wof:placetype":"venue"
},
  "geometry": {"coordinates":[9.373415947,52.4591751099],"type":"Point"}
}