{
  "type": "Feature",
  "properties": {
    "iso:country":"DE",
    "sg:address":"Albrecht-D\u00fcrer-Str. 18",
    "sg:city":"Ludwigsburg",
    "sg:phone":"+49 7141/462728",
    "sg:postcode":"71636",
    "sg:province":"Baden-W\u00fcrttemberg",
    "wof:name":"Erna Nusko",
    "wof:placetype":"venue"
},
  "geometry": {"coordinates":[9.1713418961,48.8985862732],"type":"Point"}
}