{
  "type": "Feature",
  "properties": {
    "iso:country":"DE",
    "sg:address":"Hauptstr. 31",
    "sg:city":"H\u00f6heischweiler",
    "sg:phone":"+49 4963/3395451",
    "sg:postcode":"66989",
    "sg:province":"Rheinland-Pfalz",
    "wof:name":"Raiffeisenbank Rodalben Eg",
    "wof:placetype":"venue"
},
  "geometry": {"coordinates":[7.548303,49.230221],"type":"Point"}
}