{
  "type": "Feature",
  "properties": {
    "iso:country":"DE",
    "sg:address":"Gartenstr. 2",
    "sg:city":"Talheim",
    "sg:phone":"+49 7133/7429",
    "sg:postcode":"74388",
    "sg:province":"Baden-W\u00fcrttemberg",
    "wof:name":"Eberhard Nehr",
    "wof:placetype":"venue"
},
  "geometry": {"coordinates":[9.196149826,49.0833015442],"type":"Point"}
}