{
  "type": "Feature",
  "properties": {
    "iso:country":"DE",
    "sg:address":"Laugasse 34a",
    "sg:city":"Traben-Trarbach",
    "sg:postcode":"56841",
    "sg:province":"Rheinland-Pfalz",
    "wof:name":"Horst Litzenburger",
    "wof:placetype":"venue"
},
  "geometry": {"coordinates":[7.124186039,49.954826355],"type":"Point"}
}