{
  "type": "Feature",
  "properties": {
    "iso:country":"DE",
    "sg:address":"Widmannweg 6",
    "sg:city":"Regensburg",
    "sg:phone":"+49 941/35108",
    "sg:postcode":"93049",
    "sg:province":"Bayern",
    "wof:name":"Landsmann Bauelemente Gmbh",
    "wof:placetype":"venue"
},
  "geometry": {"coordinates":[12.0496816635,49.0158538818],"type":"Point"}
}