{
  "type": "Feature",
  "properties": {
    "iso:country":"DE",
    "sg:address":"Schulstr. 41",
    "sg:city":"Staudernheim",
    "sg:postcode":"55568",
    "sg:province":"Rheinland-Pfalz",
    "wof:name":"Outperformer E. K.",
    "wof:placetype":"venue"
},
  "geometry": {"coordinates":[7.682202,49.776306],"type":"Point"}
}