{
  "type": "Feature",
  "properties": {
    "iso:country":"DE",
    "sg:address":"Brachvogelweg 3",
    "sg:city":"Hannover",
    "sg:phone":"+49 511/480077",
    "sg:postcode":"30455",
    "sg:province":"Niedersachsen",
    "wof:name":"Dieter Schaube",
    "wof:placetype":"venue"
},
  "geometry": {"coordinates":[9.666577,52.369762],"type":"Point"}
}