{
  "type": "Feature",
  "properties": {
    "iso:country":"DE",
    "sg:address":"Hebelstr. 7",
    "sg:city":"Eppelheim",
    "sg:phone":"+49 6221/763810",
    "sg:postcode":"69214",
    "sg:province":"Baden-W\u00fcrttemberg",
    "wof:name":"Bier-b\u00f6rse",
    "wof:placetype":"venue"
},
  "geometry": {"coordinates":[8.6345462799,49.4035072327],"type":"Point"}
}