{
  "type": "Feature",
  "properties": {
    "iso:country":"DE",
    "sg:address":"Mittweidaer Str. 10",
    "sg:city":"Geringswalde",
    "sg:phone":"+49 37382/8796",
    "sg:postcode":"09326",
    "sg:province":"Sachsen",
    "wof:name":"Gastro Profi",
    "wof:placetype":"venue"
},
  "geometry": {"coordinates":[12.908209,51.072102],"type":"Point"}
}