{
  "type": "Feature",
  "properties": {
    "iso:country":"DE",
    "sg:address":"Siethwende 54",
    "sg:city":"Sommerland",
    "sg:phone":"+49 4126/1254",
    "sg:postcode":"25358",
    "sg:province":"Schleswig-Holstein",
    "wof:name":"Hans O. Sch\u00fcmann",
    "wof:placetype":"venue"
},
  "geometry": {"coordinates":[9.5681695938,53.7858886719],"type":"Point"}
}