{
  "type": "Feature",
  "properties": {
    "iso:country":"DE",
    "sg:address":"Hauptstr. 71",
    "sg:city":"Zweibr\u00fccken",
    "sg:phone":"+49 6332/3341",
    "sg:postcode":"66482",
    "sg:province":"Rheinland-Pfalz",
    "wof:name":"Musikhaus M\u00fcller Inh. Karl-heinz M\u00fcller",
    "wof:placetype":"venue"
},
  "geometry": {"coordinates":[7.3618741035,49.2493209839],"type":"Point"}
}