{
  "type": "Feature",
  "properties": {
    "iso:country":"DE",
    "sg:address":"Westheimer Str. 23",
    "sg:city":"Neus\u00e4\u00df",
    "sg:postcode":"86356",
    "sg:province":"Bayern",
    "wof:name":"Augustin Gmbh",
    "wof:placetype":"venue"
},
  "geometry": {"coordinates":[10.8238248825,48.3875389099],"type":"Point"}
}