{
  "type": "Feature",
  "properties": {
    "iso:country":"DE",
    "sg:address":"Lebacher Str. 27",
    "sg:city":"Lebach",
    "sg:phone":"+49 6887/2713",
    "sg:postcode":"66822",
    "sg:province":"Saarland",
    "wof:name":"Automobile Jungblut",
    "wof:placetype":"venue"
},
  "geometry": {"coordinates":[6.8986959457,49.4493293762],"type":"Point"}
}