{
  "type": "Feature",
  "properties": {
    "iso:country":"DE",
    "sg:address":"Bergstr. 14",
    "sg:city":"Gifhorn",
    "sg:postcode":"38518",
    "sg:province":"Niedersachsen",
    "wof:name":"Bosse Bestattungen Ohg",
    "wof:placetype":"venue"
},
  "geometry": {"coordinates":[10.546433,52.478649],"type":"Point"}
}