{
  "type": "Feature",
  "properties": {
    "iso:country":"DE",
    "sg:address":"Burgstr. 7/1",
    "sg:city":"Plochingen",
    "sg:postcode":"73207",
    "sg:province":"Baden-W\u00fcrttemberg",
    "wof:name":"Claudia Fritz Bau Gmbh",
    "wof:placetype":"venue"
},
  "geometry": {"coordinates":[9.4180793762,48.7105827332],"type":"Point"}
}