{
  "type": "Feature",
  "properties": {
    "iso:country":"DE",
    "sg:address":"Am Bahnhof 5",
    "sg:city":"Stadtallendorf",
    "sg:phone":"+49 6428/40297",
    "sg:postcode":"35260",
    "sg:province":"Hessen",
    "wof:name":"Sk Rad Und Freizeit-fashion",
    "wof:placetype":"venue"
},
  "geometry": {"coordinates":[9.015921,50.825932],"type":"Point"}
}