{
  "type": "Feature",
  "properties": {
    "iso:country":"DE",
    "sg:address":"Gasstr. 16",
    "sg:city":"Itzehoe",
    "sg:phone":"+49 4821/74076",
    "sg:postcode":"25524",
    "sg:province":"Schleswig-Holstein",
    "wof:name":"Bassel-scheel Lasergraphics Gmbh",
    "wof:placetype":"venue"
},
  "geometry": {"coordinates":[9.4982414246,53.9306640625],"type":"Point"}
}