{
  "type": "Feature",
  "properties": {
    "iso:country":"DE",
    "sg:address":"Ludwigstr. 5",
    "sg:city":"Cham",
    "sg:phone":"+49 9971/9112",
    "sg:postcode":"93413",
    "sg:province":"Bayern",
    "wof:name":"Herbert Meierhofer Steuerberater",
    "wof:placetype":"venue"
},
  "geometry": {"coordinates":[12.6632232666,49.2202301025],"type":"Point"}
}