{
  "type": "Feature",
  "properties": {
    "iso:country":"DE",
    "sg:address":"Armgartstr. 14 III",
    "sg:city":"Hamburg",
    "sg:phone":"+49 40/2274590",
    "sg:postcode":"22087",
    "sg:province":"Hamburg",
    "wof:name":"Hans W. Wulff",
    "wof:placetype":"venue"
},
  "geometry": {"coordinates":[10.0254297256,53.5639953613],"type":"Point"}
}