{
  "type": "Feature",
  "properties": {
    "iso:country":"DE",
    "sg:address":"Dr.-Friedrichs-Str. 35",
    "sg:city":"M\u00fcgeln",
    "sg:phone":"+49 34362/33383",
    "sg:postcode":"04769",
    "sg:province":"Sachsen",
    "wof:name":"Alfa Bautenschutz Gmbh",
    "wof:placetype":"venue"
},
  "geometry": {"coordinates":[13.051477,51.236656],"type":"Point"}
}