{
  "type": "Feature",
  "properties": {
    "iso:country":"DE",
    "sg:address":"Waldstr. 28",
    "sg:city":"Frankfurt",
    "sg:phone":"+49 69/671526",
    "sg:postcode":"60528",
    "sg:province":"Hessen",
    "wof:name":"W. A. M\u00fcller",
    "wof:placetype":"venue"
},
  "geometry": {"coordinates":[8.6503944397,50.0806465149],"type":"Point"}
}