{
  "type": "Feature",
  "properties": {
    "iso:country":"DE",
    "sg:address":"Robertstr. 44 - 56",
    "sg:city":"Bochum",
    "sg:phone":"+49 4923/4587030",
    "sg:postcode":"44809",
    "sg:province":"Nordrhein-Westfalen",
    "wof:name":"Gallade Alutec Gmbh",
    "wof:placetype":"venue"
},
  "geometry": {"coordinates":[7.2046132088,51.4929924011],"type":"Point"}
}