{
  "type": "Feature",
  "properties": {
    "iso:country":"DE",
    "sg:address":"Bahnhofstr. 16",
    "sg:city":"Kirchen",
    "sg:phone":"+49 2741/61755",
    "sg:postcode":"57548",
    "sg:province":"Rheinland-Pfalz",
    "wof:name":"Gertruden-apotheke",
    "wof:placetype":"venue"
},
  "geometry": {"coordinates":[7.878613,50.81028],"type":"Point"}
}