{
  "type": "Feature",
  "properties": {
    "iso:country":"DE",
    "sg:address":"Roedenbeckstr. 103",
    "sg:city":"Achim",
    "sg:phone":"+49 4202/97610",
    "sg:postcode":"28832",
    "sg:province":"Niedersachsen",
    "wof:name":"M. Pyko Gmbh",
    "wof:placetype":"venue"
},
  "geometry": {"coordinates":[9.10976,53.028301],"type":"Point"}
}