{
  "type": "Feature",
  "properties": {
    "iso:country":"DE",
    "sg:address":"Kaupenweg 5",
    "sg:city":"Dietzenbach",
    "sg:phone":"+49 6074/31604",
    "sg:postcode":"63128",
    "sg:province":"Hessen",
    "wof:name":"Joachim Mitlehner Ingenieur",
    "wof:placetype":"venue"
},
  "geometry": {"coordinates":[8.7733440399,49.993144989],"type":"Point"}
}