{
  "type": "Feature",
  "properties": {
    "iso:country":"DE",
    "sg:address":"Obere Stadt 73a",
    "sg:city":"Weilheim",
    "sg:phone":"+49 881/61444",
    "sg:postcode":"82362",
    "sg:province":"Bayern",
    "wof:name":"Max Schmid",
    "wof:placetype":"venue"
},
  "geometry": {"coordinates":[11.149589,47.838272],"type":"Point"}
}