{
  "type": "Feature",
  "properties": {
    "iso:country":"DE",
    "sg:address":"Olgastr. 25",
    "sg:city":"Deizisau",
    "sg:phone":"+49 4971/5327508",
    "sg:postcode":"73779",
    "sg:province":"Baden-W\u00fcrttemberg",
    "wof:name":"Volksbank Plochingen Eg",
    "wof:placetype":"venue"
},
  "geometry": {"coordinates":[9.385752,48.713017],"type":"Point"}
}