{
  "type": "Feature",
  "properties": {
    "iso:country":"DE",
    "sg:address":"B\u00fcnnerhelfstr. 33",
    "sg:city":"Dortmund",
    "sg:phone":"+49 231/178018",
    "sg:postcode":"44379",
    "sg:province":"Nordrhein-Westfalen",
    "wof:name":"Fritz Rensmann Gmbh & Co.",
    "wof:placetype":"venue"
},
  "geometry": {"coordinates":[7.403441,51.507824],"type":"Point"}
}