{
  "type": "Feature",
  "properties": {
    "iso:country":"DE",
    "sg:address":"Goethestr. 13",
    "sg:city":"Karlskron",
    "sg:phone":"+49 8450/1679",
    "sg:postcode":"85123",
    "sg:province":"Bayern",
    "wof:name":"Ledermoden Wolfgang Schaller",
    "wof:placetype":"venue"
},
  "geometry": {"coordinates":[11.4212150574,48.6818733215],"type":"Point"}
}