{
  "type": "Feature",
  "properties": {
    "iso:country":"DE",
    "sg:address":"Seehofstr. 50",
    "sg:city":"Memmelsdorf",
    "sg:phone":"+49 951/43055",
    "sg:postcode":"96117",
    "sg:province":"Bayern",
    "wof:name":"Holiday Service Wohnungstausch E. V.",
    "wof:placetype":"venue"
},
  "geometry": {"coordinates":[10.9623012543,49.9261627197],"type":"Point"}
}