{
  "type": "Feature",
  "properties": {
    "iso:country":"DE",
    "sg:address":"In den Bergg\u00e4rten 6",
    "sg:city":"Paderborn",
    "sg:phone":"+49 5252/53742",
    "sg:postcode":"33100",
    "sg:province":"Nordrhein-Westfalen",
    "wof:name":"Globalshop - Besonderes F\u00fcr Ambiente Und Freizeit",
    "wof:placetype":"venue"
},
  "geometry": {"coordinates":[8.8441200256,51.746509552],"type":"Point"}
}