{
  "type": "Feature",
  "properties": {
    "iso:country":"DE",
    "sg:address":"Richters Kamp 74",
    "sg:city":"Stadtlohn",
    "sg:phone":"+49 2563/97599",
    "sg:postcode":"48703",
    "sg:province":"Nordrhein-Westfalen",
    "wof:name":"J\u00f6dden-umweltschutz Und Sicherheitstechnik",
    "wof:placetype":"venue"
},
  "geometry": {"coordinates":[6.9287700653,51.9834365845],"type":"Point"}
}