{
  "type": "Feature",
  "properties": {
    "iso:country":"DE",
    "sg:address":"Machandelstieg 7",
    "sg:city":"Hamburg",
    "sg:phone":"+49 40/6402068",
    "sg:postcode":"22175",
    "sg:province":"Hamburg",
    "wof:name":"Joachim Schmidt",
    "wof:placetype":"venue"
},
  "geometry": {"coordinates":[10.0947313309,53.6285438538],"type":"Point"}
}