{
  "type": "Feature",
  "properties": {
    "iso:country":"DE",
    "sg:address":"Hermann-L\u00f6ns-Str. 93",
    "sg:city":"Wesseling",
    "sg:phone":"+49 2236/1212",
    "sg:postcode":"50389",
    "sg:province":"Nordrhein-Westfalen",
    "wof:name":"Franz Sch\u00fctte Taxi",
    "wof:placetype":"venue"
},
  "geometry": {"coordinates":[6.9798331261,50.813911438],"type":"Point"}
}