{
  "type": "Feature",
  "properties": {
    "iso:country":"DE",
    "sg:address":"Synagogenstr. 7",
    "sg:city":"Ibbenb\u00fcren",
    "sg:phone":"+49 5451/49397",
    "sg:postcode":"49477",
    "sg:province":"Nordrhein-Westfalen",
    "wof:name":"Das Haarhaus",
    "wof:placetype":"venue"
},
  "geometry": {"coordinates":[7.7140188217,52.2761878967],"type":"Point"}
}