{
  "type": "Feature",
  "properties": {
    "iso:country":"DE",
    "sg:address":"Im Rosphetal 29",
    "sg:city":"Wetter",
    "sg:phone":"+49 6423/964830",
    "sg:postcode":"35083",
    "sg:province":"Hessen",
    "wof:name":"Klonk & Hartmann Glasmalerei Gmbh",
    "wof:placetype":"venue"
},
  "geometry": {"coordinates":[8.7765016556,50.9103927612],"type":"Point"}
}