{
  "type": "Feature",
  "properties": {
    "iso:country":"DE",
    "sg:address":"Grabmairstr. 2",
    "sg:city":"Scheyern",
    "sg:phone":"+49 8441/5515",
    "sg:postcode":"85298",
    "sg:province":"Bayern",
    "wof:name":"Anton Gabelsberger",
    "wof:placetype":"venue"
},
  "geometry": {"coordinates":[11.456699,48.500996],"type":"Point"}
}