{
  "type": "Feature",
  "properties": {
    "iso:country":"DE",
    "sg:address":"Eckermannstr. 176",
    "sg:city":"Berlin",
    "sg:postcode":"12683",
    "sg:province":"Berlin",
    "wof:name":"Helenes Grundst\u00fccks- Und Dienstleistungsges. Mbh",
    "wof:placetype":"venue"
},
  "geometry": {"coordinates":[13.5561466217,52.5293502808],"type":"Point"}
}