{
  "type": "Feature",
  "properties": {
    "iso:country":"DE",
    "sg:address":"Lerchenweg 7",
    "sg:city":"Neuried",
    "sg:phone":"+49 89/757425",
    "sg:postcode":"82061",
    "sg:province":"Bayern",
    "wof:name":"Richard Mader",
    "wof:placetype":"venue"
},
  "geometry": {"coordinates":[11.4652147293,48.094871521],"type":"Point"}
}