{
  "type": "Feature",
  "properties": {
    "iso:country":"DE",
    "sg:address":"Graf-Wolfegg-Str. 28",
    "sg:city":"Rottenburg",
    "sg:phone":"+49 7472/21904",
    "sg:postcode":"72108",
    "sg:province":"Baden-W\u00fcrttemberg",
    "wof:name":"Manfred Neu",
    "wof:placetype":"venue"
},
  "geometry": {"coordinates":[8.9448900223,48.4796104431],"type":"Point"}
}