{
  "type": "Feature",
  "properties": {
    "iso:country":"DE",
    "sg:address":"Gro\u00dfe Str. 1",
    "sg:city":"Lingen",
    "sg:phone":"+49 591/54742",
    "sg:postcode":"49808",
    "sg:province":"Niedersachsen",
    "wof:name":"Gastst\u00e4tte Alte Posthalterei",
    "wof:placetype":"venue"
},
  "geometry": {"coordinates":[7.3161702156,52.522857666],"type":"Point"}
}