{
  "type": "Feature",
  "properties": {
    "iso:country":"DE",
    "sg:address":"Eichenstr. 22",
    "sg:city":"Cottbus",
    "sg:postcode":"03050",
    "sg:province":"Brandenburg",
    "wof:name":"G\u00fcnter B\u00f6hlke",
    "wof:placetype":"venue"
},
  "geometry": {"coordinates":[14.338253,51.743446],"type":"Point"}
}