{
  "type": "Feature",
  "properties": {
    "iso:country":"DE",
    "sg:address":"Osterlauchdorf 5",
    "sg:city":"Dirlewang",
    "sg:phone":"+49 8267/255",
    "sg:postcode":"87742",
    "sg:province":"Bayern",
    "wof:name":"Cafe Zum Rehwinkel",
    "wof:placetype":"venue"
},
  "geometry": {"coordinates":[10.5418,47.986561],"type":"Point"}
}