{
  "type": "Feature",
  "properties": {
    "iso:country":"DE",
    "sg:address":"Otto-Hahn-Stra\u00dfe 37",
    "sg:city":"Dortmund",
    "sg:postcode":"44227",
    "sg:province":"Nordrhein-Westfalen",
    "wof:name":"Ism-web",
    "wof:placetype":"venue"
},
  "geometry": {"coordinates":[7.401169,51.489281],"type":"Point"}
}