{
  "type": "Feature",
  "properties": {
    "iso:country":"DE",
    "sg:address":"Johannisstr. 1",
    "sg:city":"F\u00fcrth",
    "sg:phone":"+49 911/7499369",
    "sg:postcode":"90763",
    "sg:province":"Bayern",
    "wof:name":"Contry Corner",
    "wof:placetype":"venue"
},
  "geometry": {"coordinates":[10.9862976074,49.4690895081],"type":"Point"}
}