{
  "type": "Feature",
  "properties": {
    "iso:country":"DE",
    "sg:address":"Eichenweg 4",
    "sg:city":"Bad Zwischenahn",
    "sg:phone":"+49 4486/92870",
    "sg:postcode":"26160",
    "sg:province":"Niedersachsen",
    "wof:name":"Abopart Viol & Partner Gmbh & Co. Kg",
    "wof:placetype":"venue"
},
  "geometry": {"coordinates":[8.1218976974,53.1422576904],"type":"Point"}
}