{
  "type": "Feature",
  "properties": {
    "iso:country":"DE",
    "sg:address":"Auguststr. 22",
    "sg:city":"Braunschweig",
    "sg:phone":"+49 531/41286",
    "sg:postcode":"38100",
    "sg:province":"Niedersachsen",
    "wof:name":"Biffar Gmbh & Co. Braunschweig Kg",
    "wof:placetype":"venue"
},
  "geometry": {"coordinates":[10.5266666412,52.2594642639],"type":"Point"}
}