{
  "type": "Feature",
  "properties": {
    "iso:country":"DE",
    "sg:address":"Kesseldorfer Str. 45",
    "sg:city":"Hamminkeln",
    "sg:phone":"+49 2852/2839",
    "sg:postcode":"46499",
    "sg:province":"Nordrhein-Westfalen",
    "wof:name":"Sport Hoffmann Vertriebs Gmbh",
    "wof:placetype":"venue"
},
  "geometry": {"coordinates":[6.580398,51.741707],"type":"Point"}
}