{
  "type": "Feature",
  "properties": {
    "iso:country":"DE",
    "sg:address":"Rittistr. 17",
    "sg:city":"Kappel-Grafenhausen",
    "sg:phone":"+49 7822/6049",
    "sg:postcode":"77966",
    "sg:province":"Baden-W\u00fcrttemberg",
    "wof:name":"Schilli Wohnbau Gmbh",
    "wof:placetype":"venue"
},
  "geometry": {"coordinates":[7.7382769585,48.2946586609],"type":"Point"}
}