{
  "type": "Feature",
  "properties": {
    "iso:country":"DE",
    "sg:address":"Am Hafen 1",
    "sg:city":"Bockhorst",
    "sg:phone":"+49 4967/259",
    "sg:postcode":"26897",
    "sg:province":"Niedersachsen",
    "wof:name":"Fisser & V. Doornum Mineral\u00f6l-grosshandel",
    "wof:placetype":"venue"
},
  "geometry": {"coordinates":[7.6326880455,52.993270874],"type":"Point"}
}