{
  "type": "Feature",
  "properties": {
    "iso:country":"DE",
    "sg:address":"Halbemeiler Str. 2",
    "sg:city":"Breitenbrunn",
    "sg:postcode":"08359",
    "sg:province":"Sachsen",
    "wof:name":"Kurt Keller",
    "wof:placetype":"venue"
},
  "geometry": {"coordinates":[12.814191,50.459808],"type":"Point"}
}