{
  "type": "Feature",
  "properties": {
    "iso:country":"DE",
    "sg:address":"Schweiggerstr. 6",
    "sg:city":"N\u00fcrnberg",
    "sg:phone":"+49 911/5980307",
    "sg:postcode":"90478",
    "sg:province":"Bayern",
    "wof:name":"Pro-han-sa Gmbh",
    "wof:placetype":"venue"
},
  "geometry": {"coordinates":[11.090746,49.441566],"type":"Point"}
}