{
  "type": "Feature",
  "properties": {
    "iso:country":"DE",
    "sg:address":"Elfenallee 5",
    "sg:city":"Berlin",
    "sg:phone":"+49 30/4742703",
    "sg:postcode":"13127",
    "sg:province":"Berlin",
    "wof:name":"Torsten Backhaus",
    "wof:placetype":"venue"
},
  "geometry": {"coordinates":[13.4342565536,52.600276947],"type":"Point"}
}