{
  "type": "Feature",
  "properties": {
    "iso:country":"DE",
    "sg:address":"Kaiserstr. 91",
    "sg:city":"Lahr",
    "sg:phone":"+49 7821/1331",
    "sg:postcode":"77933",
    "sg:province":"Baden-W\u00fcrttemberg",
    "wof:name":"R\u00f6ssle",
    "wof:placetype":"venue"
},
  "geometry": {"coordinates":[7.8662362099,48.3415641785],"type":"Point"}
}