{
  "type": "Feature",
  "properties": {
    "iso:country":"DE",
    "sg:address":"Alverskirchener Str. 9",
    "sg:city":"Everswinkel",
    "sg:phone":"+49 2582/268",
    "sg:postcode":"48351",
    "sg:province":"Nordrhein-Westfalen",
    "wof:name":"Heinrich Kortenjann",
    "wof:placetype":"venue"
},
  "geometry": {"coordinates":[7.842471,51.923931],"type":"Point"}
}