{
  "type": "Feature",
  "properties": {
    "iso:country":"DE",
    "sg:address":"In der Dreesbach 6",
    "sg:city":"Hellenthal",
    "sg:phone":"+49 2482/2683",
    "sg:postcode":"53940",
    "sg:province":"Nordrhein-Westfalen",
    "wof:name":"I. Herrmann Bautr\u00e4ger-gmbh",
    "wof:placetype":"venue"
},
  "geometry": {"coordinates":[6.433989048,50.482421875],"type":"Point"}
}