{
  "type": "Feature",
  "properties": {
    "iso:country":"DE",
    "sg:address":"Pfrondorfer Str. 3",
    "sg:city":"T\u00fcbingen",
    "sg:phone":"+49 7071/81178",
    "sg:postcode":"72074",
    "sg:province":"Baden-W\u00fcrttemberg",
    "wof:name":"Adler-apotheke",
    "wof:placetype":"venue"
},
  "geometry": {"coordinates":[9.078648,48.532078],"type":"Point"}
}