{
  "type": "Feature",
  "properties": {
    "iso:country":"DE",
    "sg:address":"Moselpromenade 9",
    "sg:city":"Trittenheim",
    "sg:postcode":"54349",
    "sg:province":"Rheinland-Pfalz",
    "wof:name":"Ftm Ferienhaus Gmbh",
    "wof:placetype":"venue"
},
  "geometry": {"coordinates":[6.903172,49.822334],"type":"Point"}
}