{
  "type": "Feature",
  "properties": {
    "iso:country":"DE",
    "sg:address":"Saarbr\u00fccker Str. 91",
    "sg:city":"Bous",
    "sg:phone":"+49 6834/3991",
    "sg:postcode":"66359",
    "sg:province":"Saarland",
    "wof:name":"Kino-klause",
    "wof:placetype":"venue"
},
  "geometry": {"coordinates":[6.793982029,49.276058197],"type":"Point"}
}