{
  "type": "Feature",
  "properties": {
    "iso:country":"DE",
    "sg:address":"Angerweidachstr. 7",
    "sg:city":"Prien",
    "sg:phone":"+49 8051/2680",
    "sg:postcode":"83209",
    "sg:province":"Bayern",
    "wof:name":"Dr. V. Iwanoff",
    "wof:placetype":"venue"
},
  "geometry": {"coordinates":[12.351354599,47.8558006287],"type":"Point"}
}