{
  "type": "Feature",
  "properties": {
    "iso:country":"DE",
    "sg:address":"Rosenstr. 1",
    "sg:city":"Bad M\u00fcnder",
    "sg:phone":"+49 5042/989701",
    "sg:postcode":"31848",
    "sg:province":"Niedersachsen",
    "wof:name":"Heinrich Intemann",
    "wof:placetype":"venue"
},
  "geometry": {"coordinates":[9.4166994095,52.236946106],"type":"Point"}
}