{
  "type": "Feature",
  "properties": {
    "iso:country":"DE",
    "sg:address":"Lutherplatz 2",
    "sg:city":"Bad Lauterberg",
    "sg:phone":"+49 5524/5003",
    "sg:postcode":"37431",
    "sg:province":"Niedersachsen",
    "wof:name":"Gothaer Versicherungen",
    "wof:placetype":"venue"
},
  "geometry": {"coordinates":[10.4712753296,51.6307678223],"type":"Point"}
}