{
  "type": "Feature",
  "properties": {
    "iso:country":"DE",
    "sg:address":"Am Gr\u00fcn 58",
    "sg:city":"Marburg",
    "sg:postcode":"35037",
    "sg:province":"Hessen",
    "wof:name":"Telefontest.de - Telefontarife, Internettarife",
    "wof:placetype":"venue"
},
  "geometry": {"coordinates":[8.770972,50.804771],"type":"Point"}
}