{
  "type": "Feature",
  "properties": {
    "iso:country":"DE",
    "sg:address":"Friedrich-Breuer-Str. 26-28",
    "sg:city":"Bonn",
    "sg:phone":"+49 228/476487",
    "sg:postcode":"53225",
    "sg:province":"Nordrhein-Westfalen",
    "wof:name":"M. Scheu",
    "wof:placetype":"venue"
},
  "geometry": {"coordinates":[7.1175742149,50.7386131287],"type":"Point"}
}