{
  "type": "Feature",
  "properties": {
    "iso:country":"DE",
    "sg:address":"Gartenstr. 30",
    "sg:city":"Roth",
    "sg:phone":"+49 9171/9500",
    "sg:postcode":"91154",
    "sg:province":"Bayern",
    "wof:name":"Diakonieverein Roth E. V.",
    "wof:placetype":"venue"
},
  "geometry": {"coordinates":[11.099959,49.244011],"type":"Point"}
}