{
  "type": "Feature",
  "properties": {
    "iso:country":"DE",
    "sg:address":"Orlam\u00fcnder Str. 39",
    "sg:city":"Ludwigsstadt",
    "sg:phone":"+49 9263/215",
    "sg:postcode":"96337",
    "sg:province":"Bayern",
    "wof:name":"Robert Bauer",
    "wof:placetype":"venue"
},
  "geometry": {"coordinates":[11.367494,50.513069],"type":"Point"}
}