{
  "type": "Feature",
  "properties": {
    "iso:country":"DE",
    "sg:address":"Hauptstr. 52",
    "sg:city":"Reichenbach-Steegen",
    "sg:phone":"+49 6385/6446",
    "sg:postcode":"66879",
    "sg:province":"Rheinland-Pfalz",
    "wof:name":"G\u00fcnther Ehlhardt",
    "wof:placetype":"venue"
},
  "geometry": {"coordinates":[7.535646,49.50296],"type":"Point"}
}