{
  "type": "Feature",
  "properties": {
    "iso:country":"DE",
    "sg:address":"M\u00fchlgrabenweg 39",
    "sg:city":"Boxberg",
    "sg:phone":"+49 35774/30934",
    "sg:postcode":"02943",
    "sg:province":"Sachsen",
    "wof:name":"Christian R\u00f6hle",
    "wof:placetype":"venue"
},
  "geometry": {"coordinates":[14.614279,51.464325],"type":"Point"}
}