{
  "type": "Feature",
  "properties": {
    "iso:country":"DE",
    "sg:address":"Bahnhofstr. 34 -36",
    "sg:city":"Pirmasens",
    "sg:phone":"+49 6331/95036",
    "sg:postcode":"66953",
    "sg:province":"Rheinland-Pfalz",
    "wof:name":"Walter H\u00f6h Rechtsanwalt",
    "wof:placetype":"venue"
},
  "geometry": {"coordinates":[7.6015548706,49.2025299072],"type":"Point"}
}