{
  "type": "Feature",
  "properties": {
    "iso:country":"DE",
    "sg:address":"Bahnhofstr. 43",
    "sg:city":"M\u00fchlacker",
    "sg:postcode":"75417",
    "sg:province":"Baden-W\u00fcrttemberg",
    "wof:name":"Arthro-vital Gmbh",
    "wof:placetype":"venue"
},
  "geometry": {"coordinates":[8.840256691,48.9492454529],"type":"Point"}
}