{
  "type": "Feature",
  "properties": {
    "iso:country":"DE",
    "sg:address":"Verbindungschaussee 2 a",
    "sg:city":"G\u00fcstrow",
    "sg:postcode":"18273",
    "sg:province":"Mecklenburg-Vorpommern",
    "wof:name":"Kohlehandel Schwerin Gmbh",
    "wof:placetype":"venue"
},
  "geometry": {"coordinates":[12.201919,53.797596],"type":"Point"}
}