{
  "type": "Feature",
  "properties": {
    "iso:country":"DE",
    "sg:address":"Gerichtsweg 10",
    "sg:city":"Taucha",
    "sg:phone":"+49 34298/68935",
    "sg:postcode":"04425",
    "sg:province":"Sachsen",
    "wof:name":"Beka-pumpenwerk Taucha Gmbh",
    "wof:placetype":"venue"
},
  "geometry": {"coordinates":[12.480225,51.378281],"type":"Point"}
}