{
  "type": "Feature",
  "properties": {
    "iso:country":"DE",
    "sg:address":"Schanzstr. 23",
    "sg:city":"Edenkoben",
    "sg:phone":"+49 4963/232382",
    "sg:postcode":"67480",
    "sg:province":"Rheinland-Pfalz",
    "wof:name":"Raiffeisenbank Eg",
    "wof:placetype":"venue"
},
  "geometry": {"coordinates":[8.136145,49.280037],"type":"Point"}
}