{
  "type": "Feature",
  "properties": {
    "iso:country":"DE",
    "sg:address":"Ferienpark",
    "sg:city":"Ronshausen",
    "sg:phone":"+49 6678/1380",
    "sg:postcode":"36217",
    "sg:province":"Hessen",
    "wof:name":"K.-heinz Holzendorf",
    "wof:placetype":"venue"
},
  "geometry": {"coordinates":[9.8597288132,50.9477539062],"type":"Point"}
}