{
  "type": "Feature",
  "properties": {
    "iso:country":"DE",
    "sg:address":"Jahnstr. 66",
    "sg:city":"Leonberg",
    "sg:phone":"+49 7152/25883",
    "sg:postcode":"71229",
    "sg:province":"Baden-W\u00fcrttemberg",
    "wof:name":"Berthold Schmidt",
    "wof:placetype":"venue"
},
  "geometry": {"coordinates":[9.017029,48.80798],"type":"Point"}
}