{
  "type": "Feature",
  "properties": {
    "iso:country":"DE",
    "sg:address":"Georg-Ledebour-Str. 20",
    "sg:city":"N\u00fcrnberg",
    "sg:phone":"+49 911/804630",
    "sg:postcode":"90473",
    "sg:province":"Bayern",
    "wof:name":"Wolfgang Kretschmer",
    "wof:placetype":"venue"
},
  "geometry": {"coordinates":[11.1519670486,49.402381897],"type":"Point"}
}