{
  "type": "Feature",
  "properties": {
    "iso:country":"DE",
    "sg:address":"Siemensstr 7",
    "sg:city":"Gronau",
    "sg:phone":"+49 2562/7030",
    "sg:postcode":"48599",
    "sg:province":"Nordrhein-Westfalen",
    "wof:name":"T & F Keramikvertriebs-gmbh",
    "wof:placetype":"venue"
},
  "geometry": {"coordinates":[7.056118,52.202339],"type":"Point"}
}