{
  "type": "Feature",
  "properties": {
    "iso:country":"DE",
    "sg:address":"Klosterberg 2",
    "sg:city":"Holzheim",
    "sg:phone":"+49 8296/845",
    "sg:postcode":"89438",
    "sg:province":"Bayern",
    "wof:name":"F. K\u00e4sbohrer",
    "wof:placetype":"venue"
},
  "geometry": {"coordinates":[10.575175,48.489864],"type":"Point"}
}