{
  "type": "Feature",
  "properties": {
    "iso:country":"DE",
    "sg:address":"Hindenburgstr. 8",
    "sg:city":"Fallingbostel",
    "sg:phone":"+49 5162/909660",
    "sg:postcode":"29683",
    "sg:province":"Niedersachsen",
    "wof:name":"Detlef Hendel E. K.",
    "wof:placetype":"venue"
},
  "geometry": {"coordinates":[9.6973438263,52.8643875122],"type":"Point"}
}