{
  "type": "Feature",
  "properties": {
    "iso:country":"DE",
    "sg:address":"Schwabacher Str. 23",
    "sg:city":"F\u00fcrth",
    "sg:phone":"+49 911/7498177",
    "sg:postcode":"90762",
    "sg:province":"Bayern",
    "wof:name":"Kochl\u00f6ffel Gmbh",
    "wof:placetype":"venue"
},
  "geometry": {"coordinates":[10.9887247086,49.4734230042],"type":"Point"}
}