{
  "type": "Feature",
  "properties": {
    "iso:country":"DE",
    "sg:address":"Zur H\u00fctte 66a",
    "sg:city":"Vietgest",
    "sg:phone":"+49 38452/20412",
    "sg:postcode":"18279",
    "sg:province":"Mecklenburg-Vorpommern",
    "wof:name":"Schloss Vietgest",
    "wof:placetype":"venue"
},
  "geometry": {"coordinates":[12.347382,53.764187],"type":"Point"}
}