{
  "type": "Feature",
  "properties": {
    "iso:country":"DE",
    "sg:address":"Leibnizstr. 12",
    "sg:city":"Karlsruhe",
    "sg:phone":"+49 721/821335",
    "sg:postcode":"76137",
    "sg:province":"Baden-W\u00fcrttemberg",
    "wof:name":"I-t\u00fcpfele",
    "wof:placetype":"venue"
},
  "geometry": {"coordinates":[8.39290905,48.9976234436],"type":"Point"}
}