{
  "type": "Feature",
  "properties": {
    "iso:country":"DE",
    "sg:address":"Am Steinbach 9",
    "sg:city":"Bonn",
    "sg:phone":"+49 228/9480504",
    "sg:postcode":"53229",
    "sg:province":"Nordrhein-Westfalen",
    "wof:name":"J. Rolef",
    "wof:placetype":"venue"
},
  "geometry": {"coordinates":[7.1732020378,50.7479133606],"type":"Point"}
}