{
  "type": "Feature",
  "properties": {
    "iso:country":"DE",
    "sg:address":"Am Neptundock",
    "sg:city":"Emden",
    "sg:phone":"+49 4921/22776",
    "sg:postcode":"26723",
    "sg:province":"Niedersachsen",
    "wof:name":"Ernst H\u00d6ppner Gmbh & Co. Kg",
    "wof:placetype":"venue"
},
  "geometry": {"coordinates":[7.201938,53.359509],"type":"Point"}
}