{
  "type": "Feature",
  "properties": {
    "iso:country":"DE",
    "sg:address":"Volmerswerther Str. 417",
    "sg:city":"D\u00fcsseldorf",
    "sg:phone":"+49 211/155683",
    "sg:postcode":"40221",
    "sg:province":"Nordrhein-Westfalen",
    "wof:name":"En De Ehd",
    "wof:placetype":"venue"
},
  "geometry": {"coordinates":[6.7632989883,51.1881599426],"type":"Point"}
}