{
  "type": "Feature",
  "properties": {
    "iso:country":"DE",
    "sg:address":"Bahnhofstr. 100",
    "sg:city":"Schwaigern",
    "sg:phone":"+49 7138/6484",
    "sg:postcode":"74193",
    "sg:province":"Baden-W\u00fcrttemberg",
    "wof:name":"Kurt B\u00fcrger",
    "wof:placetype":"venue"
},
  "geometry": {"coordinates":[9.012869,49.135811],"type":"Point"}
}