{
  "type": "Feature",
  "properties": {
    "iso:country":"DE",
    "sg:address":"Im H\u00f6pen 4",
    "sg:city":"Hanstedt",
    "sg:phone":"+49 4187/445",
    "sg:postcode":"21271",
    "sg:province":"Niedersachsen",
    "wof:name":"Rudolf Vick",
    "wof:placetype":"venue"
},
  "geometry": {"coordinates":[9.93276,53.271221],"type":"Point"}
}