{
  "type": "Feature",
  "properties": {
    "iso:country":"DE",
    "sg:address":"B\u00fcrgermeister-Heine-Str. 26",
    "sg:city":"Celle",
    "sg:phone":"+49 5141/52190",
    "sg:postcode":"29229",
    "sg:province":"Niedersachsen",
    "wof:name":"J\u00fcrgen Heine",
    "wof:placetype":"venue"
},
  "geometry": {"coordinates":[10.057072,52.652191],"type":"Point"}
}