{
  "type": "Feature",
  "properties": {
    "iso:country":"DE",
    "sg:address":"Schmutterstr. 1",
    "sg:city":"Gersthofen",
    "sg:phone":"+49 8230/9190",
    "sg:postcode":"86368",
    "sg:province":"Bayern",
    "wof:name":"Anton Kugelmann",
    "wof:placetype":"venue"
},
  "geometry": {"coordinates":[10.817252,48.430168],"type":"Point"}
}