{
  "type": "Feature",
  "properties": {
    "iso:country":"DE",
    "sg:address":"Rathenauplatz 1a",
    "sg:city":"Frankfurt",
    "sg:phone":"+49 69/290777",
    "sg:postcode":"60313",
    "sg:province":"Hessen",
    "wof:name":"Kosmetik Studio Inh. Christine Herrmann",
    "wof:placetype":"venue"
},
  "geometry": {"coordinates":[14.513715,52.347824],"type":"Point"}
}