{
  "type": "Feature",
  "properties": {
    "iso:country":"DE",
    "sg:address":"H\u00f6henweg 18",
    "sg:city":"Bad Vilbel",
    "sg:phone":"+49 6101/86620",
    "sg:postcode":"61118",
    "sg:province":"Hessen",
    "wof:name":"Helmut Schmidt Steuerberater",
    "wof:placetype":"venue"
},
  "geometry": {"coordinates":[8.7425823212,50.1784133911],"type":"Point"}
}