{
  "type": "Feature",
  "properties": {
    "iso:country":"DE",
    "sg:address":"Br\u00fcckenhofstr. 90",
    "sg:city":"Kassel",
    "sg:phone":"+49 561/405941",
    "sg:postcode":"34132",
    "sg:province":"Hessen",
    "wof:name":"Sch\u00fclertreff",
    "wof:placetype":"venue"
},
  "geometry": {"coordinates":[9.44532,51.28286],"type":"Point"}
}