{
  "type": "Feature",
  "properties": {
    "iso:country":"DE",
    "sg:address":"Jacob-Gottlob-Nathusius-Str. 1",
    "sg:city":"Haldensleben",
    "sg:phone":"+49 3904/45160",
    "sg:postcode":"39340",
    "sg:province":"Sachsen-Anhalt",
    "wof:name":"Gebr\u00fcder Appel Gmbh",
    "wof:placetype":"venue"
},
  "geometry": {"coordinates":[11.4324388504,52.2808036804],"type":"Point"}
}