{
  "type": "Feature",
  "properties": {
    "iso:country":"DE",
    "sg:address":"Steinweg 10",
    "sg:city":"Bad Langensalza",
    "sg:phone":"+49 3603/842010",
    "sg:postcode":"99947",
    "sg:province":"Th\u00fcringen",
    "wof:name":"Dietmar Flachsbarth",
    "wof:placetype":"venue"
},
  "geometry": {"coordinates":[10.6420717239,51.1055221558],"type":"Point"}
}