{
  "type": "Feature",
  "properties": {
    "iso:country":"DE",
    "sg:address":"Hertlehof",
    "sg:city":"Pfaffenhausen",
    "sg:phone":"+49 8265",
    "sg:postcode":"87772",
    "sg:province":"Bayern",
    "wof:name":"Profiseller Multimedia Shop",
    "wof:placetype":"venue"
},
  "geometry": {"coordinates":[10.465658,48.104122],"type":"Point"}
}