{
  "type": "Feature",
  "properties": {
    "iso:country":"DE",
    "sg:address":"Metzinger Str. 11",
    "sg:city":"Riederich",
    "sg:phone":"+49 7123/31713",
    "sg:postcode":"72585",
    "sg:province":"Baden-W\u00fcrttemberg",
    "wof:name":"Restaurant Krone",
    "wof:placetype":"venue"
},
  "geometry": {"coordinates":[9.2687397003,48.5596084595],"type":"Point"}
}