{
  "type": "Feature",
  "properties": {
    "iso:country":"DE",
    "sg:address":"Willemerstr 29",
    "sg:city":"Frankfurt",
    "sg:phone":"+49 69/610284",
    "sg:postcode":"60594",
    "sg:province":"Hessen",
    "wof:name":"K\u00e4lte Steudter Gmbh",
    "wof:placetype":"venue"
},
  "geometry": {"coordinates":[8.694452,50.104622],"type":"Point"}
}