{
  "type": "Feature",
  "properties": {
    "iso:country":"DE",
    "sg:address":"Frauensteiner Str. 9",
    "sg:city":"Obercarsdorf",
    "sg:phone":"+49 35052/65301",
    "sg:postcode":"01762",
    "sg:province":"Sachsen",
    "wof:name":"Agrargenossenschaft Sadisdorf Eg",
    "wof:placetype":"venue"
},
  "geometry": {"coordinates":[13.627671,50.822632],"type":"Point"}
}