{
  "type": "Feature",
  "properties": {
    "iso:country":"DE",
    "sg:address":"Feldbergstr. 46",
    "sg:city":"Singen",
    "sg:phone":"+49 7731/42054",
    "sg:postcode":"78224",
    "sg:province":"Baden-W\u00fcrttemberg",
    "wof:name":"Altenwohnanlage",
    "wof:placetype":"venue"
},
  "geometry": {"coordinates":[8.853197,47.777634],"type":"Point"}
}