{
  "type": "Feature",
  "properties": {
    "iso:country":"DE",
    "sg:address":"Industriestr. 45",
    "sg:city":"Horb",
    "sg:phone":"+49 7451/4634",
    "sg:postcode":"72160",
    "sg:province":"Baden-W\u00fcrttemberg",
    "wof:name":"Secundo-verlag Gmbh",
    "wof:placetype":"venue"
},
  "geometry": {"coordinates":[8.6752300262,48.4646759033],"type":"Point"}
}