{
  "type": "Feature",
  "properties": {
    "iso:country":"DE",
    "sg:address":"Gutenbergstr. 30",
    "sg:city":"Fellbach",
    "sg:phone":"+49 711/513834",
    "sg:postcode":"70736",
    "sg:province":"Baden-W\u00fcrttemberg",
    "wof:name":"Ute Ditz Steuerberaterin",
    "wof:placetype":"venue"
},
  "geometry": {"coordinates":[9.2579097748,48.8292808533],"type":"Point"}
}