{
  "type": "Feature",
  "properties": {
    "iso:country":"DE",
    "sg:address":"Burgstr. 38",
    "sg:city":"Marienhafe",
    "sg:phone":"+49 4934/914847",
    "sg:postcode":"26529",
    "sg:province":"Niedersachsen",
    "wof:name":"Heino Pfropfreis Finanzdienstleistungen E. K.",
    "wof:placetype":"venue"
},
  "geometry": {"coordinates":[7.27178,53.526131],"type":"Point"}
}