{
  "type": "Feature",
  "properties": {
    "iso:country":"DE",
    "sg:address":"Wietmarscher Str. 16",
    "sg:city":"Wietmarschen",
    "sg:phone":"+49 5908/693",
    "sg:postcode":"49835",
    "sg:province":"Niedersachsen",
    "wof:name":"Friedrich Auclair",
    "wof:placetype":"venue"
},
  "geometry": {"coordinates":[7.179066,52.503628],"type":"Point"}
}