{
  "type": "Feature",
  "properties": {
    "iso:country":"DE",
    "sg:address":"In der Reitenwies 19",
    "sg:city":"Tholey",
    "sg:phone":"+49 6853/30901",
    "sg:postcode":"66636",
    "sg:province":"Saarland",
    "wof:name":"Corona Solar Gmbh",
    "wof:placetype":"venue"
},
  "geometry": {"coordinates":[7.027397,49.504597],"type":"Point"}
}