{
  "type": "Feature",
  "properties": {
    "iso:country":"DE",
    "sg:address":"Jakob-Binder-Str. 16",
    "sg:city":"Ludwigshafen",
    "sg:phone":"+49 621/523432",
    "sg:postcode":"67063",
    "sg:province":"Rheinland-Pfalz",
    "wof:name":"B\u00fcrgereck",
    "wof:placetype":"venue"
},
  "geometry": {"coordinates":[8.4399909973,49.4861335754],"type":"Point"}
}