{
  "type": "Feature",
  "properties": {
    "iso:country":"DE",
    "sg:address":"Markdorfer Str. 9",
    "sg:city":"Bermatingen",
    "sg:postcode":"88697",
    "sg:province":"Baden-W\u00fcrttemberg",
    "wof:name":"Vitol Gmbh",
    "wof:placetype":"venue"
},
  "geometry": {"coordinates":[9.3514471054,47.7297515869],"type":"Point"}
}