{
  "type": "Feature",
  "properties": {
    "iso:country":"DE",
    "sg:address":"Elisabethenstr. 27",
    "sg:city":"Bad Vilbel",
    "sg:postcode":"61118",
    "sg:province":"Hessen",
    "wof:name":"Sankt Pirmin Naturprodukte Gmbh",
    "wof:placetype":"venue"
},
  "geometry": {"coordinates":[8.7308177948,50.1751022339],"type":"Point"}
}