{
  "type": "Feature",
  "properties": {
    "iso:country":"DE",
    "sg:address":"Amselweg 31",
    "sg:city":"Halle",
    "sg:phone":"+49 345/4441319",
    "sg:postcode":"06110",
    "sg:province":"Sachsen-Anhalt",
    "wof:name":"Dr. Med. Volker Hofmann",
    "wof:placetype":"venue"
},
  "geometry": {"coordinates":[11.968548,51.459591],"type":"Point"}
}