{
  "type": "Feature",
  "properties": {
    "iso:country":"DE",
    "sg:address":"Heckenh\u00f6fchen 2",
    "sg:city":"Poppenhausen",
    "sg:postcode":"36163",
    "sg:province":"Hessen",
    "wof:name":"Deutsche Jugend In Europa Landesverband Hessen",
    "wof:placetype":"venue"
},
  "geometry": {"coordinates":[9.909693718,50.4886360168],"type":"Point"}
}