{
  "type": "Feature",
  "properties": {
    "iso:country":"DE",
    "sg:address":"Albert-Schweitzer-Str. 19g",
    "sg:city":"Kissing",
    "sg:postcode":"86438",
    "sg:province":"Bayern",
    "wof:name":"Rimar Natursteine Ohg",
    "wof:placetype":"venue"
},
  "geometry": {"coordinates":[10.9755077362,48.3029785156],"type":"Point"}
}