{
  "type": "Feature",
  "properties": {
    "iso:country":"DE",
    "sg:address":"Aschaffenburger Str. 78",
    "sg:city":"Waldaschaff",
    "sg:phone":"+49 6095/4150",
    "sg:postcode":"63857",
    "sg:province":"Bayern",
    "wof:name":"N. \u00d6ner",
    "wof:placetype":"venue"
},
  "geometry": {"coordinates":[9.2925596237,49.9762954712],"type":"Point"}
}