{
  "type": "Feature",
  "properties": {
    "iso:country":"DE",
    "sg:address":"Im Winkel 6-8",
    "sg:city":"Berlin",
    "sg:phone":"+49 30/8390101",
    "sg:postcode":"14195",
    "sg:province":"Berlin",
    "wof:name":"Museum Europ\u00e4ischer Kulturen Prof. Dr. Konrad Vanja",
    "wof:placetype":"venue"
},
  "geometry": {"coordinates":[13.292491,52.460545],"type":"Point"}
}