{
  "type": "Feature",
  "properties": {
    "iso:country":"DE",
    "sg:address":"Grabenallee 22",
    "sg:city":"Offenburg",
    "sg:phone":"+49 781/22577",
    "sg:postcode":"77652",
    "sg:province":"Baden-W\u00fcrttemberg",
    "wof:name":"Jutta Girrbach",
    "wof:placetype":"venue"
},
  "geometry": {"coordinates":[7.9482750893,48.4674758911],"type":"Point"}
}