{
  "type": "Feature",
  "properties": {
    "iso:country":"DE",
    "sg:address":"Wiesdorfer Platz 2",
    "sg:city":"Leverkusen",
    "sg:phone":"+49 214/3290",
    "sg:postcode":"51373",
    "sg:province":"Nordrhein-Westfalen",
    "wof:name":"Bayer-kaufhaus Gmbh",
    "wof:placetype":"venue"
},
  "geometry": {"coordinates":[6.9868621826,51.0325508118],"type":"Point"}
}