{
  "type": "Feature",
  "properties": {
    "iso:country":"DE",
    "sg:address":"Kleppingstr. 10",
    "sg:city":"Dortmund",
    "sg:phone":"+49 231/553303",
    "sg:postcode":"44135",
    "sg:province":"Nordrhein-Westfalen",
    "wof:name":"D\u00f6rthe Kottmann Gmbh",
    "wof:placetype":"venue"
},
  "geometry": {"coordinates":[7.4685149193,51.5134544373],"type":"Point"}
}