{
  "type": "Feature",
  "properties": {
    "iso:country":"DE",
    "sg:address":"K\u00f6nigsberger Str. 4",
    "sg:city":"Rellingen",
    "sg:phone":"+49 4101/23624",
    "sg:postcode":"25462",
    "sg:province":"Schleswig-Holstein",
    "wof:name":"Ingeborg Und Mathias Faber",
    "wof:placetype":"venue"
},
  "geometry": {"coordinates":[9.835513,53.653706],"type":"Point"}
}