{
  "type": "Feature",
  "properties": {
    "iso:country":"DE",
    "sg:address":"Hauptstrasse 28",
    "sg:city":"Coswig",
    "sg:phone":"+49 3523/75393",
    "sg:postcode":"01640",
    "sg:province":"Sachsen",
    "wof:name":"Tapferes Schneiderlein - Schneidereidienstleistungen",
    "wof:placetype":"venue"
},
  "geometry": {"coordinates":[13.58061409,51.1277313232],"type":"Point"}
}