{
  "type": "Feature",
  "properties": {
    "iso:country":"DE",
    "sg:address":"Rethener Str. 2 A",
    "sg:city":"Hannover",
    "sg:phone":"+49 511/792346",
    "sg:postcode":"30519",
    "sg:province":"Niedersachsen",
    "wof:name":"Ev. Pfarramt Gustav-adolf-kirche",
    "wof:placetype":"venue"
},
  "geometry": {"coordinates":[9.79383564,52.3319778442],"type":"Point"}
}