{
  "type": "Feature",
  "properties": {
    "iso:country":"DE",
    "sg:address":"Lynckerstr. 32",
    "sg:city":"Kassel",
    "sg:phone":"+49 561/883424",
    "sg:postcode":"34128",
    "sg:province":"Hessen",
    "wof:name":"Personenbef\u00f6rderungsunter- Nehmen Rolf Freudenstein Gmbh",
    "wof:placetype":"venue"
},
  "geometry": {"coordinates":[9.4541816711,51.3331375122],"type":"Point"}
}