{
  "type": "Feature",
  "properties": {
    "iso:country":"DE",
    "sg:address":"Am Elisabethheim 19 bei Buehn",
    "sg:city":"Wuppertal",
    "sg:postcode":"42111",
    "sg:province":"Nordrhein-Westfalen",
    "wof:name":"L. Benninga",
    "wof:placetype":"venue"
},
  "geometry": {"coordinates":[7.1382398605,51.2955284119],"type":"Point"}
}