{
  "type": "Feature",
  "properties": {
    "iso:country":"DE",
    "sg:address":"Neumarkter Str. 13a",
    "sg:city":"Kastl",
    "sg:phone":"+49 9625/226",
    "sg:postcode":"92280",
    "sg:province":"Bayern",
    "wof:name":"K. Skotner",
    "wof:placetype":"venue"
},
  "geometry": {"coordinates":[11.6779184341,49.3693313599],"type":"Point"}
}