{
  "type": "Feature",
  "properties": {
    "iso:country":"DE",
    "sg:address":"Dr.-Bender-Str. 2",
    "sg:city":"Weinheim",
    "sg:phone":"+49 6201/187248",
    "sg:postcode":"69469",
    "sg:province":"Baden-W\u00fcrttemberg",
    "wof:name":"Monika Baumann",
    "wof:placetype":"venue"
},
  "geometry": {"coordinates":[8.6706676483,49.5489349365],"type":"Point"}
}