{
  "type": "Feature",
  "properties": {
    "iso:country":"DE",
    "sg:address":"Moos\u00e4cker 8",
    "sg:city":"Markt Schwaben",
    "sg:phone":"+49 8121/912375",
    "sg:postcode":"85570",
    "sg:province":"Bayern",
    "wof:name":"Pronto Logistik & Handels Gmbh",
    "wof:placetype":"venue"
},
  "geometry": {"coordinates":[11.8722867966,48.1914176941],"type":"Point"}
}