{
  "type": "Feature",
  "properties": {
    "iso:country":"DE",
    "sg:address":"Lindloher Str. 14",
    "sg:city":"Haren",
    "sg:phone":"+49 5932/2166",
    "sg:postcode":"49733",
    "sg:province":"Niedersachsen",
    "wof:name":"Hubertushof",
    "wof:placetype":"venue"
},
  "geometry": {"coordinates":[7.1997971535,52.7871589661],"type":"Point"}
}