{
  "type": "Feature",
  "properties": {
    "iso:country":"DE",
    "sg:address":"Stuttgarter Str.",
    "sg:city":"W\u00fcrzburg",
    "sg:phone":"+49 931/614000",
    "sg:postcode":"97084",
    "sg:province":"Bayern",
    "wof:name":"Werksteinbetriebe W\u00fcrzburg Gmbh",
    "wof:placetype":"venue"
},
  "geometry": {"coordinates":[9.9430475235,49.7525291443],"type":"Point"}
}