{
  "type": "Feature",
  "properties": {
    "iso:country":"DE",
    "sg:address":"Pauritzer Str. 23",
    "sg:city":"Altenburg",
    "sg:phone":"+49 3447/501019",
    "sg:postcode":"04600",
    "sg:province":"Th\u00fcringen",
    "wof:name":"Victoria Versicherung Ag",
    "wof:placetype":"venue"
},
  "geometry": {"coordinates":[12.4376211166,50.9889678955],"type":"Point"}
}