{
  "type": "Feature",
  "properties": {
    "iso:country":"DE",
    "sg:address":"Heidelberger Str. 85",
    "sg:city":"Darmstadt",
    "sg:phone":"+49 6151/312925",
    "sg:postcode":"64285",
    "sg:province":"Hessen",
    "wof:name":"Frankenstein-apotheke Elisabeth Mattern E. Kfr.",
    "wof:placetype":"venue"
},
  "geometry": {"coordinates":[8.646652,49.858578],"type":"Point"}
}