{
  "type": "Feature",
  "properties": {
    "iso:country":"DE",
    "sg:address":"Lotzfeldchen 44",
    "sg:city":"Eschweiler",
    "sg:phone":"+49 2403/37806",
    "sg:postcode":"52249",
    "sg:province":"Nordrhein-Westfalen",
    "wof:name":"Anna Nieslony",
    "wof:placetype":"venue"
},
  "geometry": {"coordinates":[6.257215023,50.822807312],"type":"Point"}
}