{
  "type": "Feature",
  "properties": {
    "iso:country":"DE",
    "sg:address":"Dorfstr. 31",
    "sg:city":"Halbendorf",
    "sg:phone":"+49 35773/70101",
    "sg:postcode":"02953",
    "sg:province":"Sachsen",
    "wof:name":"Paulos Pension",
    "wof:placetype":"venue"
},
  "geometry": {"coordinates":[14.5758199692,51.5460166931],"type":"Point"}
}