{
  "type": "Feature",
  "properties": {
    "iso:country":"DE",
    "sg:address":"Sch\u00e4fergasse 2",
    "sg:city":"Eppstein",
    "sg:phone":"+49 6198/8621",
    "sg:postcode":"65817",
    "sg:province":"Hessen",
    "wof:name":"Kath. Pfarramt St. Margareta",
    "wof:placetype":"venue"
},
  "geometry": {"coordinates":[8.3597297668,50.1399078369],"type":"Point"}
}