{
  "type": "Feature",
  "properties": {
    "iso:country":"DE",
    "sg:address":"Steingraben 33",
    "sg:city":"Jena",
    "sg:postcode":"07749",
    "sg:province":"Th\u00fcringen",
    "wof:name":"Domani Modevertriebs Gmbh",
    "wof:placetype":"venue"
},
  "geometry": {"coordinates":[11.608441,50.929333],"type":"Point"}
}