{
  "type": "Feature",
  "properties": {
    "iso:country":"DE",
    "sg:address":"Alleenstr. 128",
    "sg:city":"Kirchheim",
    "sg:phone":"+49 7021/3657",
    "sg:postcode":"73230",
    "sg:province":"Baden-W\u00fcrttemberg",
    "wof:name":"Bestattungsinstitut Werner Holt Gmbh",
    "wof:placetype":"venue"
},
  "geometry": {"coordinates":[9.451393,48.649662],"type":"Point"}
}