{
  "type": "Feature",
  "properties": {
    "iso:country":"DE",
    "sg:address":"Schal\u00fcckstr. 10",
    "sg:city":"G\u00fctersloh",
    "sg:phone":"+49 5241/51566",
    "sg:postcode":"33332",
    "sg:province":"Nordrhein-Westfalen",
    "wof:name":"Kintrup",
    "wof:placetype":"venue"
},
  "geometry": {"coordinates":[8.367837,51.892826],"type":"Point"}
}