{
  "type": "Feature",
  "properties": {
    "iso:country":"DE",
    "sg:address":"Farbenweg 10",
    "sg:city":"Helmstedt",
    "sg:phone":"+49 5351/31591",
    "sg:postcode":"38350",
    "sg:province":"Niedersachsen",
    "wof:name":"Ursula Staniek \u00c4rztin F\u00fcr Innere Medizin",
    "wof:placetype":"venue"
},
  "geometry": {"coordinates":[10.9845838547,52.2464370728],"type":"Point"}
}