{
  "type": "Feature",
  "properties": {
    "iso:country":"DE",
    "sg:address":"Lindenthalg\u00fcrtel 61",
    "sg:city":"K\u00f6ln",
    "sg:phone":"+49 221/432047",
    "sg:postcode":"50935",
    "sg:province":"Nordrhein-Westfalen",
    "wof:name":"S. Schmid",
    "wof:placetype":"venue"
},
  "geometry": {"coordinates":[6.91158,50.92461],"type":"Point"}
}