{
  "type": "Feature",
  "properties": {
    "iso:country":"DE",
    "sg:address":"Lange Str. 14",
    "sg:city":"Walsrode",
    "sg:phone":"+49 5161/60050",
    "sg:postcode":"29664",
    "sg:province":"Niedersachsen",
    "wof:name":"Walsroder Zeitung",
    "wof:placetype":"venue"
},
  "geometry": {"coordinates":[9.5936250687,52.8604698181],"type":"Point"}
}