{
  "type": "Feature",
  "properties": {
    "iso:country":"DE",
    "sg:address":"Vaubanstr. 4",
    "sg:city":"Saarlouis",
    "sg:postcode":"66740",
    "sg:province":"Saarland",
    "wof:name":"Dostlar Gmbh D\u00f6nerproduktion",
    "wof:placetype":"venue"
},
  "geometry": {"coordinates":[6.7451272011,49.314655304],"type":"Point"}
}