{
  "type": "Feature",
  "properties": {
    "iso:country":"DE",
    "sg:address":"Bismarckstr 61a",
    "sg:city":"Essen",
    "sg:phone":"+49 201/797914",
    "sg:postcode":"45128",
    "sg:province":"Nordrhein-Westfalen",
    "wof:name":"Gs Trading & Consulting",
    "wof:placetype":"venue"
},
  "geometry": {"coordinates":[7.005433,51.441967],"type":"Point"}
}