{
  "type": "Feature",
  "properties": {
    "iso:country":"DE",
    "sg:address":"Berliner Str. 101",
    "sg:city":"Ratingen",
    "sg:phone":"+49 2102/45230",
    "sg:postcode":"40880",
    "sg:province":"Nordrhein-Westfalen",
    "wof:name":"Klopmann Gmbh",
    "wof:placetype":"venue"
},
  "geometry": {"coordinates":[6.8106079102,51.2928276062],"type":"Point"}
}