{
  "type": "Feature",
  "properties": {
    "iso:country":"DE",
    "sg:address":"Saarlandstr 17",
    "sg:city":"Zweibr\u00fccken",
    "sg:phone":"+49 6332/5699700",
    "sg:postcode":"66482",
    "sg:province":"Rheinland-Pfalz",
    "wof:name":"Psa Wasserarmaturen Gmbh",
    "wof:placetype":"venue"
},
  "geometry": {"coordinates":[7.368350029,49.2537918091],"type":"Point"}
}