{
  "type": "Feature",
  "properties": {
    "iso:country":"DE",
    "sg:address":"Hopfengartenstr. 8",
    "sg:city":"Hasselroth",
    "sg:phone":"+49 6055/81540",
    "sg:postcode":"63594",
    "sg:province":"Hessen",
    "wof:name":"Wolfgang Hartmann",
    "wof:placetype":"venue"
},
  "geometry": {"coordinates":[9.128359,50.170353],"type":"Point"}
}