{
  "type": "Feature",
  "properties": {
    "iso:country":"DE",
    "sg:address":"Steinbeisstr. 13",
    "sg:city":"Waiblingen",
    "sg:phone":"+49 7151/959270",
    "sg:postcode":"71332",
    "sg:province":"Baden-W\u00fcrttemberg",
    "wof:name":"Medizinischer Dienst Der Krankenvers. Bad.-w\u00fcrtt.",
    "wof:placetype":"venue"
},
  "geometry": {"coordinates":[9.298218,48.832222],"type":"Point"}
}