{
  "type": "Feature",
  "properties": {
    "iso:country":"DE",
    "sg:address":"H\u00fclsstr. 1",
    "sg:city":"Herne",
    "sg:phone":"+49 2202/977950",
    "sg:postcode":"44625",
    "sg:province":"Nordrhein-Westfalen",
    "wof:name":"Optenh\u00d6gel Gmbh",
    "wof:placetype":"venue"
},
  "geometry": {"coordinates":[7.1505770683,51.0053672791],"type":"Point"}
}