{
  "type": "Feature",
  "properties": {
    "iso:country":"DE",
    "sg:address":"Loerfeldstr 11a",
    "sg:city":"Herdecke",
    "sg:phone":"+49 2330/764546",
    "sg:postcode":"58313",
    "sg:province":"Nordrhein-Westfalen",
    "wof:name":"Fritz K\u00f6lsche Gmbh",
    "wof:placetype":"venue"
},
  "geometry": {"coordinates":[7.4348402023,51.4226341248],"type":"Point"}
}