{
  "type": "Feature",
  "properties": {
    "iso:country":"DE",
    "sg:address":"Mennrather Str. 100",
    "sg:city":"M\u00f6nchengladbach",
    "sg:phone":"+49 2161/581046",
    "sg:postcode":"41179",
    "sg:province":"Nordrhein-Westfalen",
    "wof:name":"H. J. Dreesen Gmbh & Co.",
    "wof:placetype":"venue"
},
  "geometry": {"coordinates":[6.3705120087,51.1427230835],"type":"Point"}
}