{
  "type": "Feature",
  "properties": {
    "iso:country":"DE",
    "sg:address":"Obere Hauptstr. 70",
    "sg:city":"Lichtenau",
    "sg:phone":"+49 37208/8170",
    "sg:postcode":"09244",
    "sg:province":"Sachsen",
    "wof:name":"Oberlichtenauer Baugesellschaft Mbh",
    "wof:placetype":"venue"
},
  "geometry": {"coordinates":[12.9663944244,50.9047355652],"type":"Point"}
}