{
  "type": "Feature",
  "properties": {
    "iso:country":"DE",
    "sg:address":"An der Kreuzwiese 47",
    "sg:city":"Oberursel",
    "sg:phone":"+49 6171/76271",
    "sg:postcode":"61440",
    "sg:province":"Hessen",
    "wof:name":"U. Burchard Steuerberater",
    "wof:placetype":"venue"
},
  "geometry": {"coordinates":[8.6008462906,50.1821174622],"type":"Point"}
}