{
  "type": "Feature",
  "properties": {
    "iso:country":"DE",
    "sg:address":"Goerdelerstr. 25",
    "sg:city":"Werne",
    "sg:phone":"+49 2389/531848",
    "sg:postcode":"59368",
    "sg:province":"Nordrhein-Westfalen",
    "wof:name":"Vo\u00df",
    "wof:placetype":"venue"
},
  "geometry": {"coordinates":[7.636367,51.670536],"type":"Point"}
}