{
  "type": "Feature",
  "properties": {
    "iso:country":"DE",
    "sg:address":"S\u00f6rmitzer Str. 4",
    "sg:city":"D\u00f6beln",
    "sg:phone":"+49 3431/702705",
    "sg:postcode":"04720",
    "sg:province":"Sachsen",
    "wof:name":"Ingenieurb\u00fcro Klemm & Hensen Gmbh",
    "wof:placetype":"venue"
},
  "geometry": {"coordinates":[13.1291122437,51.1213188171],"type":"Point"}
}