{
  "type": "Feature",
  "properties": {
    "iso:country":"DE",
    "sg:address":"Adlerhorst 17",
    "sg:city":"Hamburg",
    "sg:phone":"+49 40/5524680",
    "sg:postcode":"22459",
    "sg:province":"Hamburg",
    "wof:name":"Milestone Mailorder Gmbh",
    "wof:placetype":"venue"
},
  "geometry": {"coordinates":[9.9548244476,53.6319274902],"type":"Point"}
}