{
  "type": "Feature",
  "properties": {
    "iso:country":"DE",
    "sg:address":"Uferstr. 8",
    "sg:city":"Sch\u00f6neck",
    "sg:phone":"+49 6187/6890",
    "sg:postcode":"61137",
    "sg:province":"Hessen",
    "wof:name":"Sigmund Kantyba",
    "wof:placetype":"venue"
},
  "geometry": {"coordinates":[8.839904,50.202518],"type":"Point"}
}