{
  "type": "Feature",
  "properties": {
    "iso:country":"DE",
    "sg:address":"Graben 7",
    "sg:city":"Waldkirchen",
    "sg:phone":"+49 8581/910800",
    "sg:postcode":"94065",
    "sg:province":"Bayern",
    "wof:name":"Feuchter Gmbh & Co.",
    "wof:placetype":"venue"
},
  "geometry": {"coordinates":[13.601406,48.7281],"type":"Point"}
}