{
  "type": "Feature",
  "properties": {
    "iso:country":"DE",
    "sg:address":"Keltenschanz 9",
    "sg:city":"Otterfing",
    "sg:phone":"+49 8024/6088870",
    "sg:postcode":"83624",
    "sg:province":"Bayern",
    "wof:name":"Elgas Armaturen Gmbh",
    "wof:placetype":"venue"
},
  "geometry": {"coordinates":[11.675782,47.918716],"type":"Point"}
}