{
  "type": "Feature",
  "properties": {
    "iso:country":"DE",
    "sg:city":"St Michaelisdonn",
    "sg:phone":"+49 4853/1357",
    "sg:postcode":"25693",
    "sg:province":"Schleswig-Holstein",
    "wof:name":"Blumenhaus Schwarz",
    "wof:placetype":"venue"
},
  "geometry": {"coordinates":[9.114069,53.98798],"type":"Point"}
}