{
  "type": "Feature",
  "properties": {
    "iso:country":"DE",
    "sg:address":"\u00d6denbach 11",
    "sg:city":"Breitnau",
    "sg:phone":"+49 7652/351",
    "sg:postcode":"79874",
    "sg:province":"Baden-W\u00fcrttemberg",
    "wof:name":"David Kleiser",
    "wof:placetype":"venue"
},
  "geometry": {"coordinates":[8.0973920822,47.9270477295],"type":"Point"}
}