{
  "type": "Feature",
  "properties": {
    "iso:country":"DE",
    "sg:address":"Hasenrachring 39",
    "sg:city":"Saarwellingen",
    "sg:phone":"+49 6838/3884",
    "sg:postcode":"66793",
    "sg:province":"Saarland",
    "wof:name":"Edgar Britz",
    "wof:placetype":"venue"
},
  "geometry": {"coordinates":[6.7977509499,49.3466835022],"type":"Point"}
}