{
  "type": "Feature",
  "properties": {
    "iso:country":"DE",
    "sg:address":"Dorfstr. 1 A",
    "sg:city":"Bucha",
    "sg:phone":"+49 3641/212860",
    "sg:postcode":"07751",
    "sg:province":"Th\u00fcringen",
    "wof:name":"Agrargenossenschaft Bucha Eg",
    "wof:placetype":"venue"
},
  "geometry": {"coordinates":[11.51552,50.882908],"type":"Point"}
}