{
  "type": "Feature",
  "properties": {
    "iso:country":"DE",
    "sg:address":"Kerkenbrock 36",
    "sg:city":"Werther",
    "sg:phone":"+49 5203/6614",
    "sg:postcode":"33824",
    "sg:province":"Nordrhein-Westfalen",
    "wof:name":"Doris Gehring",
    "wof:placetype":"venue"
},
  "geometry": {"coordinates":[8.434748,52.087605],"type":"Point"}
}