{
  "type": "Feature",
  "properties": {
    "iso:country":"DE",
    "sg:address":"Oberstr. 3",
    "sg:city":"Ratingen",
    "sg:phone":"+49 2102/27175",
    "sg:postcode":"40878",
    "sg:province":"Nordrhein-Westfalen",
    "wof:name":"Meeresbuffet Kaspar Gmbh",
    "wof:placetype":"venue"
},
  "geometry": {"coordinates":[6.8503270149,51.2975578308],"type":"Point"}
}