{
  "type": "Feature",
  "properties": {
    "iso:country":"DE",
    "sg:address":"Nordstr. 97",
    "sg:city":"M\u00fclheim",
    "sg:phone":"+49 208/381417",
    "sg:postcode":"45475",
    "sg:province":"Nordrhein-Westfalen",
    "wof:name":"Immopa- Gmbh",
    "wof:placetype":"venue"
},
  "geometry": {"coordinates":[6.901277,51.45182],"type":"Point"}
}