{
  "type": "Feature",
  "properties": {
    "iso:country":"DE",
    "sg:address":"Heimatweg 23",
    "sg:city":"B\u00f6nningstedt",
    "sg:phone":"+49 40/5566573",
    "sg:postcode":"25474",
    "sg:province":"Schleswig-Holstein",
    "wof:name":"Hermann Mohr",
    "wof:placetype":"venue"
},
  "geometry": {"coordinates":[9.905886,53.67635],"type":"Point"}
}