{
  "type": "Feature",
  "properties": {
    "iso:country":"DE",
    "sg:address":"Lindenstr. 83",
    "sg:city":"Siegburg",
    "sg:phone":"+49 2241/66979",
    "sg:postcode":"53721",
    "sg:province":"Nordrhein-Westfalen",
    "wof:name":"Baumaschinen Beckschulte Kg",
    "wof:placetype":"venue"
},
  "geometry": {"coordinates":[7.19373,50.79673],"type":"Point"}
}