{
  "type": "Feature",
  "properties": {
    "iso:country":"DE",
    "sg:address":"Schadowplatz 18",
    "sg:city":"D\u00fcsseldorf",
    "sg:phone":"+49 211/611648",
    "sg:postcode":"40212",
    "sg:province":"Nordrhein-Westfalen",
    "wof:name":"Adrienne Szy Krankengymnastin",
    "wof:placetype":"venue"
},
  "geometry": {"coordinates":[6.781081,51.226112],"type":"Point"}
}