{
  "type": "Feature",
  "properties": {
    "iso:country":"DE",
    "sg:address":"Langenmantelstr. 16",
    "sg:city":"Hurlach",
    "sg:phone":"+49 8248/7532",
    "sg:postcode":"86857",
    "sg:province":"Bayern",
    "wof:name":"Wilhelm Wegele",
    "wof:placetype":"venue"
},
  "geometry": {"coordinates":[10.819226265,48.1234474182],"type":"Point"}
}