{
  "type": "Feature",
  "properties": {
    "iso:country":"DE",
    "sg:address":"Lotzdorfer Str. 5 a",
    "sg:city":"Radeberg",
    "sg:phone":"+49 3528/441932",
    "sg:postcode":"01454",
    "sg:province":"Sachsen",
    "wof:name":"Martina Horn",
    "wof:placetype":"venue"
},
  "geometry": {"coordinates":[13.9121932983,51.1259613037],"type":"Point"}
}