{
  "type": "Feature",
  "properties": {
    "iso:country":"DE",
    "sg:address":"Schmiedeweg 1",
    "sg:city":"Gifhorn",
    "sg:phone":"+49 5371/7021",
    "sg:postcode":"38518",
    "sg:province":"Niedersachsen",
    "wof:name":"M. Und B. Tietge Gmbh",
    "wof:placetype":"venue"
},
  "geometry": {"coordinates":[10.5640230179,52.4869804382],"type":"Point"}
}