{
  "type": "Feature",
  "properties": {
    "iso:country":"DE",
    "sg:address":"Martin-Luther-Str. 10",
    "sg:city":"Kempen",
    "sg:phone":"+49 2152/7086",
    "sg:postcode":"47906",
    "sg:province":"Nordrhein-Westfalen",
    "wof:name":"Theo Schmitt Lebensmittel-e H",
    "wof:placetype":"venue"
},
  "geometry": {"coordinates":[6.4455108643,51.3849716187],"type":"Point"}
}