{
  "type": "Feature",
  "properties": {
    "iso:country":"DE",
    "sg:address":"Egerl\u00e4nder Str. 22",
    "sg:city":"Taunusstein",
    "sg:postcode":"65232",
    "sg:province":"Hessen",
    "wof:name":"Phibonacci Deutschland Informationsgesellschaft F\u00fcr",
    "wof:placetype":"venue"
},
  "geometry": {"coordinates":[8.1950912476,50.1529197693],"type":"Point"}
}