{
  "type": "Feature",
  "properties": {
    "iso:country":"DE",
    "sg:address":"Alfredstr. 26",
    "sg:city":"Essen",
    "sg:phone":"+49 201/781021",
    "sg:postcode":"45130",
    "sg:province":"Nordrhein-Westfalen",
    "wof:name":"W. Kaschlun",
    "wof:placetype":"venue"
},
  "geometry": {"coordinates":[7.0034770966,51.4396743774],"type":"Point"}
}