{
  "type": "Feature",
  "properties": {
    "iso:country":"DE",
    "sg:address":"Theodor-Heuss-Str. 3",
    "sg:city":"Herzogenaurach",
    "sg:phone":"+49 9132/40207",
    "sg:postcode":"91074",
    "sg:province":"Bayern",
    "wof:name":"Good Time Records Gesellschaft F. Tonproduktio-",
    "wof:placetype":"venue"
},
  "geometry": {"coordinates":[10.8734693527,49.5760765076],"type":"Point"}
}