{
  "type": "Feature",
  "properties": {
    "iso:country":"DE",
    "sg:address":"Europark Fichtenhain A9",
    "sg:city":"Krefeld",
    "sg:phone":"+49 4921/5136140",
    "sg:postcode":"47807",
    "sg:province":"Nordrhein-Westfalen",
    "wof:name":"Wacom Europe Gmbh",
    "wof:placetype":"venue"
},
  "geometry": {"coordinates":[6.5876898766,51.3050193787],"type":"Point"}
}