{
  "type": "Feature",
  "properties": {
    "iso:country":"DE",
    "sg:address":"Wagnerstr. 14",
    "sg:city":"Trossingen",
    "sg:phone":"+49 7425/9390",
    "sg:postcode":"78647",
    "sg:province":"Baden-W\u00fcrttemberg",
    "wof:name":"Baugenossenschaft Donau-baar-heuberg Eg",
    "wof:placetype":"venue"
},
  "geometry": {"coordinates":[8.635184288,48.0793609619],"type":"Point"}
}