{
  "type": "Feature",
  "properties": {
    "iso:country":"DE",
    "sg:address":"Wendelsteinweg 6",
    "sg:city":"Taufkirchen",
    "sg:phone":"+49 89/6127043",
    "sg:postcode":"82024",
    "sg:province":"Bayern",
    "wof:name":"Ifa Bilderteam Gmbh",
    "wof:placetype":"venue"
},
  "geometry": {"coordinates":[11.6136026382,48.0349311829],"type":"Point"}
}