{
  "type": "Feature",
  "properties": {
    "iso:country":"DE",
    "sg:address":"Rheinstr. 92",
    "sg:city":"Wesseling",
    "sg:phone":"+49 2236/2064",
    "sg:postcode":"50389",
    "sg:province":"Nordrhein-Westfalen",
    "wof:name":"Euroblitz",
    "wof:placetype":"venue"
},
  "geometry": {"coordinates":[7.020357,50.807007],"type":"Point"}
}