{
  "type": "Feature",
  "properties": {
    "iso:country":"DE",
    "sg:address":"Horststr. 31",
    "sg:city":"Landau",
    "sg:phone":"+49 6341/88597",
    "sg:postcode":"76829",
    "sg:province":"Rheinland-Pfalz",
    "wof:name":"Toom-markt Gmbh",
    "wof:placetype":"venue"
},
  "geometry": {"coordinates":[8.120598793,49.2036552429],"type":"Point"}
}