{
  "type": "Feature",
  "properties": {
    "iso:country":"DE",
    "sg:address":"Frauenrichter Str. 110",
    "sg:city":"Weiden",
    "sg:phone":"+49 961/670700",
    "sg:postcode":"92637",
    "sg:province":"Bayern",
    "wof:name":"Ingenieurb\u00fcro F\u00fcr Kraftfahrzeugtechnik",
    "wof:placetype":"venue"
},
  "geometry": {"coordinates":[12.1442050934,49.67237854],"type":"Point"}
}