{
  "type": "Feature",
  "properties": {
    "iso:country":"DE",
    "sg:address":"S\u00fcdstr. 3",
    "sg:city":"Wietmarschen",
    "sg:phone":"+49 5908/1614",
    "sg:postcode":"49835",
    "sg:province":"Niedersachsen",
    "wof:name":"Bernhard M\u00f6ddel",
    "wof:placetype":"venue"
},
  "geometry": {"coordinates":[7.230207,52.484337],"type":"Point"}
}