{
  "type": "Feature",
  "properties": {
    "iso:country":"DE",
    "sg:address":"Vor dem Peterstor 10",
    "sg:city":"Fulda",
    "sg:phone":"+49 661/21208",
    "sg:postcode":"36037",
    "sg:province":"Hessen",
    "wof:name":"N. Sevim",
    "wof:placetype":"venue"
},
  "geometry": {"coordinates":[9.6820440292,50.5503501892],"type":"Point"}
}