{
  "type": "Feature",
  "properties": {
    "iso:country":"DE",
    "sg:address":"Dycker M\u00fchlenweg 5",
    "sg:city":"Grevenbroich",
    "sg:phone":"+49 2182/2674",
    "sg:postcode":"41516",
    "sg:province":"Nordrhein-Westfalen",
    "wof:name":"Eva Maria Koch",
    "wof:placetype":"venue"
},
  "geometry": {"coordinates":[6.5884408951,51.1243629456],"type":"Point"}
}