{
  "type": "Feature",
  "properties": {
    "iso:country":"DE",
    "sg:address":"Bei der Neuen M\u00fcnze 15",
    "sg:city":"Hamburg",
    "sg:phone":"+49 40/6790950",
    "sg:postcode":"22145",
    "sg:province":"Hamburg",
    "wof:name":"Rauchabzug L\u00fcftungstechnik Dingfelder & Hadler Gmbh",
    "wof:placetype":"venue"
},
  "geometry": {"coordinates":[10.1527147293,53.623626709],"type":"Point"}
}