{
  "type": "Feature",
  "properties": {
    "iso:country":"DE",
    "sg:address":"Lorenzstr. 8",
    "sg:city":"Berlin",
    "sg:phone":"+49 30/7722191",
    "sg:postcode":"12209",
    "sg:province":"Berlin",
    "wof:name":"Manfred Papke",
    "wof:placetype":"venue"
},
  "geometry": {"coordinates":[13.330887,52.427021],"type":"Point"}
}