{
  "type": "Feature",
  "properties": {
    "iso:country":"DE",
    "sg:address":"Grubwaldstr. 15",
    "sg:city":"Singen",
    "sg:phone":"+49 4977/319910",
    "sg:postcode":"78224",
    "sg:province":"Baden-W\u00fcrttemberg",
    "wof:name":"Schwarz & Co",
    "wof:placetype":"venue"
},
  "geometry": {"coordinates":[8.863991,47.756168],"type":"Point"}
}