{
  "type": "Feature",
  "properties": {
    "iso:country":"DE",
    "sg:address":"Voltastr. 28",
    "sg:city":"Hannover",
    "sg:phone":"+49 511/3507865",
    "sg:postcode":"30165",
    "sg:province":"Niedersachsen",
    "wof:name":"Dieter Messerschmidt",
    "wof:placetype":"venue"
},
  "geometry": {"coordinates":[9.733854,52.393581],"type":"Point"}
}