{
  "type": "Feature",
  "properties": {
    "iso:country":"DE",
    "sg:address":"Am Kaiserplatz 3",
    "sg:city":"Neuenhaus",
    "sg:phone":"+49 5941/747",
    "sg:postcode":"49828",
    "sg:province":"Niedersachsen",
    "wof:name":"Heggemanns Grillstube",
    "wof:placetype":"venue"
},
  "geometry": {"coordinates":[6.9972248077,52.5160522461],"type":"Point"}
}