{
  "type": "Feature",
  "properties": {
    "iso:country":"DE",
    "sg:address":"Seidenstr. 70",
    "sg:city":"Krefeld",
    "sg:phone":"+49 2151/800296",
    "sg:postcode":"47799",
    "sg:province":"Nordrhein-Westfalen",
    "wof:name":"Antikhalle Stevens Antiquit\u00e4ten",
    "wof:placetype":"venue"
},
  "geometry": {"coordinates":[6.574522,51.333282],"type":"Point"}
}