{
  "type": "Feature",
  "properties": {
    "iso:country":"DE",
    "sg:address":"Birkenhof 1",
    "sg:city":"Wilnsdorf",
    "sg:phone":"+49 2739/47675",
    "sg:postcode":"57234",
    "sg:province":"Nordrhein-Westfalen",
    "wof:name":"Betriebsgemeinschaft Birkenhof Roth Und Jungclausen",
    "wof:placetype":"venue"
},
  "geometry": {"coordinates":[8.142073,50.826962],"type":"Point"}
}