{
  "type": "Feature",
  "properties": {
    "iso:country":"DE",
    "sg:address":"Talstr 7",
    "sg:city":"Beerfelden",
    "sg:phone":"+49 6068/2155",
    "sg:postcode":"64743",
    "sg:province":"Hessen",
    "wof:name":"Landgraf Gmbh",
    "wof:placetype":"venue"
},
  "geometry": {"coordinates":[8.9647378922,49.5148048401],"type":"Point"}
}