{
  "type": "Feature",
  "properties": {
    "iso:country":"DE",
    "sg:address":"Wendenhof 2",
    "sg:city":"Schwerin",
    "sg:postcode":"19055",
    "sg:province":"Mecklenburg-Vorpommern",
    "wof:name":"Kinderheim Otto Schreiber",
    "wof:placetype":"venue"
},
  "geometry": {"coordinates":[11.423242569,53.6693878174],"type":"Point"}
}