{
  "type": "Feature",
  "properties": {
    "iso:country":"DE",
    "sg:address":"Hauptstr. 26",
    "sg:city":"Heiningen",
    "sg:phone":"+49 7161/42044",
    "sg:postcode":"73092",
    "sg:province":"Baden-W\u00fcrttemberg",
    "wof:name":"Apotheke Heiningen",
    "wof:placetype":"venue"
},
  "geometry": {"coordinates":[9.649085,48.662533],"type":"Point"}
}