{
  "type": "Feature",
  "properties": {
    "iso:country":"DE",
    "sg:address":"Hochstr. 11",
    "sg:city":"Br\u00fcggen",
    "sg:phone":"+49 2163/5555",
    "sg:postcode":"41379",
    "sg:province":"Nordrhein-Westfalen",
    "wof:name":"M. Loibl",
    "wof:placetype":"venue"
},
  "geometry": {"coordinates":[6.1821818352,51.2424621582],"type":"Point"}
}