{
  "type": "Feature",
  "properties": {
    "iso:country":"DE",
    "sg:address":"Bochumer Str 31",
    "sg:city":"Essen",
    "sg:phone":"+49 201/3790420",
    "sg:postcode":"45276",
    "sg:province":"Nordrhein-Westfalen",
    "wof:name":"Kvplan Inh. Volker Tacken",
    "wof:placetype":"venue"
},
  "geometry": {"coordinates":[7.078392,51.446369],"type":"Point"}
}