{
  "type": "Feature",
  "properties": {
    "iso:country":"DE",
    "sg:address":"Marienstr. 1",
    "sg:city":"Selb",
    "sg:phone":"+49 9287/2282",
    "sg:postcode":"95100",
    "sg:province":"Bayern",
    "wof:name":"G. Wolf Rank",
    "wof:placetype":"venue"
},
  "geometry": {"coordinates":[12.12776,50.1698],"type":"Point"}
}