{
  "type": "Feature",
  "properties": {
    "iso:country":"DE",
    "sg:address":"Eugen-Zipperle-Str. 2",
    "sg:city":"Zaberfeld",
    "sg:phone":"+49 7046/7321",
    "sg:postcode":"74374",
    "sg:province":"Baden-W\u00fcrttemberg",
    "wof:name":"Federmann Gmbh",
    "wof:placetype":"venue"
},
  "geometry": {"coordinates":[8.9294490814,49.0644607544],"type":"Point"}
}