{
  "type": "Feature",
  "properties": {
    "iso:country":"DE",
    "sg:city":"Idar-Oberstein",
    "sg:phone":"+49 6781/47681",
    "sg:postcode":"55743",
    "sg:province":"Rheinland-Pfalz",
    "wof:name":"M & R Blumencenter",
    "wof:placetype":"venue"
},
  "geometry": {"coordinates":[7.297686,49.722794],"type":"Point"}
}