{
  "type": "Feature",
  "properties": {
    "iso:country":"DE",
    "sg:address":"Hauptstr. 27",
    "sg:city":"Katzenbach",
    "sg:phone":"+49 6361/993903",
    "sg:postcode":"67806",
    "sg:province":"Rheinland-Pfalz",
    "wof:name":"Alt Schul",
    "wof:placetype":"venue"
},
  "geometry": {"coordinates":[7.8111901283,49.645324707],"type":"Point"}
}