{
  "type": "Feature",
  "properties": {
    "iso:country":"DE",
    "sg:address":"Ziekoer Landstr. 1",
    "sg:city":"Coswig",
    "sg:phone":"+49 34903/66512",
    "sg:postcode":"06869",
    "sg:province":"Sachsen-Anhalt",
    "wof:name":"Wittenberger Argarhandel Gmbh",
    "wof:placetype":"venue"
},
  "geometry": {"coordinates":[12.44622,51.894802],"type":"Point"}
}