{
  "type": "Feature",
  "properties": {
    "iso:country":"DE",
    "sg:address":"Am Hochrain 17",
    "sg:city":"Zwiesel",
    "sg:postcode":"94227",
    "sg:province":"Bayern",
    "wof:name":"Prenissl Grundst\u00fccks- Verwaltung Gmbh & Co. Kg",
    "wof:placetype":"venue"
},
  "geometry": {"coordinates":[13.2354421616,49.0262489319],"type":"Point"}
}