{
  "type": "Feature",
  "properties": {
    "iso:country":"DE",
    "sg:address":"Markt 4",
    "sg:city":"Unna",
    "sg:phone":"+49 2303/21057",
    "sg:postcode":"59423",
    "sg:province":"Nordrhein-Westfalen",
    "wof:name":"Jean Pascale Vertriebs Gmbh & Co.",
    "wof:placetype":"venue"
},
  "geometry": {"coordinates":[7.690269,51.534546],"type":"Point"}
}