{
  "type": "Feature",
  "properties": {
    "iso:country":"DE",
    "sg:address":"Ackerweg 2",
    "sg:city":"M\u00fcnk",
    "sg:phone":"+49 2656/431",
    "sg:postcode":"56729",
    "sg:province":"Rheinland-Pfalz",
    "wof:name":"W. Schmitt",
    "wof:placetype":"venue"
},
  "geometry": {"coordinates":[7.037135,50.306477],"type":"Point"}
}