{
  "type": "Feature",
  "properties": {
    "iso:country":"DE",
    "sg:address":"Burgstr. 1",
    "sg:city":"Hartheim",
    "sg:phone":"+49 7633/15319",
    "sg:postcode":"79258",
    "sg:province":"Baden-W\u00fcrttemberg",
    "wof:name":"K. Licht Immobilienmakler",
    "wof:placetype":"venue"
},
  "geometry": {"coordinates":[7.6229829788,47.9194946289],"type":"Point"}
}