{
  "type": "Feature",
  "properties": {
    "iso:country":"DE",
    "sg:address":"Hofmarkstr. 17",
    "sg:city":"M\u00fcnchen",
    "sg:phone":"+49 89/6351220",
    "sg:postcode":"81737",
    "sg:province":"Bayern",
    "wof:name":"Blitz Handelsgruppe Gmbh",
    "wof:placetype":"venue"
},
  "geometry": {"coordinates":[11.6306695938,48.1022796631],"type":"Point"}
}