{
  "type": "Feature",
  "properties": {
    "iso:country":"DE",
    "sg:address":"Goldbergstr. 17",
    "sg:city":"Homberg",
    "sg:phone":"+49 5681/2134",
    "sg:postcode":"34576",
    "sg:province":"Hessen",
    "wof:name":"Karl Frommann",
    "wof:placetype":"venue"
},
  "geometry": {"coordinates":[9.465201,51.056709],"type":"Point"}
}