{
  "type": "Feature",
  "properties": {
    "iso:country":"DE",
    "sg:address":"Sch\u00f6nhauser Str. 29",
    "sg:city":"K\u00f6ln",
    "sg:phone":"+49 221/384680",
    "sg:postcode":"50968",
    "sg:province":"Nordrhein-Westfalen",
    "wof:name":"Druckerei Josef Kubiak Gmbh",
    "wof:placetype":"venue"
},
  "geometry": {"coordinates":[6.9642491341,50.9113464355],"type":"Point"}
}