{
  "type": "Feature",
  "properties": {
    "iso:country":"DE",
    "sg:address":"Gartenstr. 6",
    "sg:city":"Blaubeuren",
    "sg:phone":"+49 7344/6311",
    "sg:postcode":"89143",
    "sg:province":"Baden-W\u00fcrttemberg",
    "wof:name":"Dieter Haueisen",
    "wof:placetype":"venue"
},
  "geometry": {"coordinates":[9.801125,48.3974],"type":"Point"}
}