{
  "type": "Feature",
  "properties": {
    "iso:country":"DE",
    "sg:address":"Kaiserplatz 18",
    "sg:city":"D\u00fcren",
    "sg:phone":"+49 2421/13288",
    "sg:postcode":"52349",
    "sg:province":"Nordrhein-Westfalen",
    "wof:name":"D\u00fcrener Schl\u00fcssel-express Dieter Menzel Gmbh",
    "wof:placetype":"venue"
},
  "geometry": {"coordinates":[6.4812960625,50.8022117615],"type":"Point"}
}