{
  "type": "Feature",
  "properties": {
    "iso:country":"DE",
    "sg:city":"Obernburg",
    "sg:postcode":"63785",
    "sg:province":"Bayern",
    "wof:name":"Carsten Stelzl",
    "wof:placetype":"venue"
},
  "geometry": {"coordinates":[9.144355,49.839642],"type":"Point"}
}