{
  "type": "Feature",
  "properties": {
    "iso:country":"DE",
    "sg:address":"Unterstr. 31",
    "sg:city":"Bochum",
    "sg:phone":"+49 234/9210444",
    "sg:postcode":"44892",
    "sg:province":"Nordrhein-Westfalen",
    "wof:name":"Ibosan Industrieboden- Sanierung Gmbh",
    "wof:placetype":"venue"
},
  "geometry": {"coordinates":[7.320293,51.473495],"type":"Point"}
}