{
  "type": "Feature",
  "properties": {
    "iso:country":"DE",
    "sg:address":"Ringstr. 11",
    "sg:city":"Bad Oeynhausen",
    "sg:phone":"+49 5731/4573",
    "sg:postcode":"32549",
    "sg:province":"Nordrhein-Westfalen",
    "wof:name":"Karl St\u00fchmeyer",
    "wof:placetype":"venue"
},
  "geometry": {"coordinates":[8.78108,52.216999],"type":"Point"}
}