{
  "type": "Feature",
  "properties": {
    "iso:country":"DE",
    "sg:address":"Schnellerstr 114",
    "sg:city":"Berlin",
    "sg:phone":"+49 30/5337758",
    "sg:postcode":"12439",
    "sg:province":"Berlin",
    "wof:name":"Grafa Gmbh",
    "wof:placetype":"venue"
},
  "geometry": {"coordinates":[13.5157594681,52.454864502],"type":"Point"}
}