{
  "type": "Feature",
  "properties": {
    "iso:country":"DE",
    "sg:address":"Straubinger Str. 60",
    "sg:city":"Mitterfels",
    "sg:phone":"+49 9961/910517",
    "sg:postcode":"94360",
    "sg:province":"Bayern",
    "wof:name":"Hl Markt Warenhandels Gmbh",
    "wof:placetype":"venue"
},
  "geometry": {"coordinates":[12.6714782715,48.9711608887],"type":"Point"}
}