{
  "type": "Feature",
  "properties": {
    "iso:country":"DE",
    "sg:address":"Maurenbrecherstr. 29",
    "sg:city":"D\u00fcsseldorf",
    "sg:phone":"+49 211/6411974",
    "sg:postcode":"40239",
    "sg:province":"Nordrhein-Westfalen",
    "wof:name":"C. Rath",
    "wof:placetype":"venue"
},
  "geometry": {"coordinates":[6.804142952,51.2472572327],"type":"Point"}
}