{
  "type": "Feature",
  "properties": {
    "iso:country":"DE",
    "sg:address":"Vorwerker Str. 65",
    "sg:city":"L\u00fcbeck",
    "sg:phone":"+49 451/40314",
    "sg:postcode":"23554",
    "sg:province":"Schleswig-Holstein",
    "wof:name":"Magnet",
    "wof:placetype":"venue"
},
  "geometry": {"coordinates":[10.6843795776,53.8964118958],"type":"Point"}
}