{
  "type": "Feature",
  "properties": {
    "iso:country":"DE",
    "sg:address":"Wannerspergerstr. 20",
    "sg:city":"Pfaffenhofen",
    "sg:phone":"+49 8441/5888",
    "sg:postcode":"85276",
    "sg:province":"Bayern",
    "wof:name":"Adelheid Herzog-l\u00f6sch Rechtsanw\u00e4ltin",
    "wof:placetype":"venue"
},
  "geometry": {"coordinates":[11.4964141846,48.5374526978],"type":"Point"}
}