{
  "type": "Feature",
  "properties": {
    "iso:country":"DE",
    "sg:address":"Neue Str.9",
    "sg:city":"Schw\u00e4bisch Hall",
    "sg:phone":"+49 4979/16111",
    "sg:postcode":"74523",
    "sg:province":"Baden-W\u00fcrttemberg",
    "wof:name":"Dresdner Bank",
    "wof:placetype":"venue"
},
  "geometry": {"coordinates":[9.735545,49.112881],"type":"Point"}
}