{
  "type": "Feature",
  "properties": {
    "iso:country":"DE",
    "sg:address":"Gm\u00fcnder Str. 19",
    "sg:city":"Mutlangen",
    "sg:phone":"+49 7171/71557",
    "sg:postcode":"73557",
    "sg:province":"Baden-W\u00fcrttemberg",
    "wof:name":"Kassahn Gmbh",
    "wof:placetype":"venue"
},
  "geometry": {"coordinates":[9.795543,48.820885],"type":"Point"}
}