{
  "type": "Feature",
  "properties": {
    "iso:country":"DE",
    "sg:address":"Ravensberger Str.69",
    "sg:city":"Werther",
    "sg:phone":"+49 5203/881125",
    "sg:postcode":"33824",
    "sg:province":"Nordrhein-Westfalen",
    "wof:name":"Wadewitz. -pc Allround-",
    "wof:placetype":"venue"
},
  "geometry": {"coordinates":[8.4199857712,52.076461792],"type":"Point"}
}