{
  "type": "Feature",
  "properties": {
    "iso:country":"DE",
    "sg:address":"Ochsenwerder Norderdeich 314",
    "sg:city":"Hamburg",
    "sg:phone":"+49 40/7372478",
    "sg:postcode":"21037",
    "sg:province":"Hamburg",
    "wof:name":"Werner Z\u00fcchtig",
    "wof:placetype":"venue"
},
  "geometry": {"coordinates":[10.129813,53.461479],"type":"Point"}
}