{
  "type": "Feature",
  "properties": {
    "iso:country":"DE",
    "sg:address":"Lychener Str. 5",
    "sg:city":"Templin",
    "sg:phone":"+49 3987/52220",
    "sg:postcode":"17268",
    "sg:province":"Brandenburg",
    "wof:name":"Norbert Eckardt Ingenieur",
    "wof:placetype":"venue"
},
  "geometry": {"coordinates":[13.493429184,53.1241607666],"type":"Point"}
}