{
  "type": "Feature",
  "properties": {
    "iso:country":"DE",
    "sg:address":"Steinweg 60",
    "sg:city":"Gifhorn",
    "sg:phone":"+49 5371/3066",
    "sg:postcode":"38518",
    "sg:province":"Niedersachsen",
    "wof:name":"Reiseb\u00fcro Reinecke",
    "wof:placetype":"venue"
},
  "geometry": {"coordinates":[10.5468044281,52.4846038818],"type":"Point"}
}