{
  "type": "Feature",
  "properties": {
    "iso:country":"DE",
    "sg:address":"Kurf\u00fcrstendamm 185",
    "sg:city":"Berlin",
    "sg:phone":"+49 30/8857160",
    "sg:postcode":"10707",
    "sg:province":"Berlin",
    "wof:name":"Feddersen Laule Und Scherzberg Rechtsanw\u00e4lte Und Notare",
    "wof:placetype":"venue"
},
  "geometry": {"coordinates":[13.3147029877,52.5006523132],"type":"Point"}
}