{
  "type": "Feature",
  "properties": {
    "iso:country":"DE",
    "sg:address":"Bonner Str. 46",
    "sg:city":"Solingen",
    "sg:phone":"+49 212/72103",
    "sg:postcode":"42697",
    "sg:province":"Nordrhein-Westfalen",
    "wof:name":"Holiday-snack",
    "wof:placetype":"venue"
},
  "geometry": {"coordinates":[6.9943180084,51.1596641541],"type":"Point"}
}