{
  "type": "Feature",
  "properties": {
    "iso:country":"DE",
    "sg:address":"Technikumplatz 17",
    "sg:city":"Mittweida",
    "sg:postcode":"09648",
    "sg:province":"Sachsen",
    "wof:name":"Hochschule F\u00fcr Technik Und Wirtschaft Mittweida (fh)",
    "wof:placetype":"venue"
},
  "geometry": {"coordinates":[12.9730358124,50.9873161316],"type":"Point"}
}