{
  "type": "Feature",
  "properties": {
    "iso:country":"DE",
    "sg:address":"Hoferstr. 29",
    "sg:city":"Zwickau",
    "sg:phone":"+49 375/572087",
    "sg:postcode":"08060",
    "sg:province":"Sachsen",
    "wof:name":"K\u00f6nig",
    "wof:placetype":"venue"
},
  "geometry": {"coordinates":[12.4684820175,50.7186889648],"type":"Point"}
}