{
  "type": "Feature",
  "properties": {
    "iso:country":"DE",
    "sg:address":"Schefflenztalstr. 22",
    "sg:city":"Billigheim",
    "sg:phone":"+49 6265/572",
    "sg:postcode":"74842",
    "sg:province":"Baden-W\u00fcrttemberg",
    "wof:name":"Krone",
    "wof:placetype":"venue"
},
  "geometry": {"coordinates":[9.2555656433,49.3486442566],"type":"Point"}
}