{
  "type": "Feature",
  "properties": {
    "iso:country":"DE",
    "sg:address":"Marktstr. 11-13",
    "sg:city":"Erfurt",
    "sg:postcode":"99084",
    "sg:province":"Th\u00fcringen",
    "wof:name":"Orion Gmbh",
    "wof:placetype":"venue"
},
  "geometry": {"coordinates":[11.0267210007,50.9776954651],"type":"Point"}
}