{
  "type": "Feature",
  "properties": {
    "iso:country":"DE",
    "sg:address":"Carl-Maria-von-Weber-Str. 6",
    "sg:city":"Obertshausen",
    "sg:phone":"+49 6104/41904",
    "sg:postcode":"63179",
    "sg:province":"Hessen",
    "wof:name":"Joachim Schubert",
    "wof:placetype":"venue"
},
  "geometry": {"coordinates":[8.8372678757,50.0675010681],"type":"Point"}
}