{
  "type": "Feature",
  "properties": {
    "iso:country":"DE",
    "sg:address":"Schlossallee 28",
    "sg:city":"Erding",
    "sg:phone":"+49 8122/8920460",
    "sg:postcode":"85435",
    "sg:province":"Bayern",
    "wof:name":"Werbepress Verlags Gmbh",
    "wof:placetype":"venue"
},
  "geometry": {"coordinates":[11.889631,48.270908],"type":"Point"}
}