{
  "type": "Feature",
  "properties": {
    "iso:country":"DE",
    "sg:address":"Rondenbarg 17",
    "sg:city":"Hamburg",
    "sg:postcode":"22525",
    "sg:province":"Hamburg",
    "wof:name":"Meimann & Hoffmann Partnerschaft",
    "wof:placetype":"venue"
},
  "geometry": {"coordinates":[9.923248291,53.575378418],"type":"Point"}
}