{
  "type": "Feature",
  "properties": {
    "iso:country":"DE",
    "sg:address":"Ziegelstr. 6",
    "sg:city":"Hainburg",
    "sg:phone":"+49 6182/68472",
    "sg:postcode":"63512",
    "sg:province":"Hessen",
    "wof:name":"Ks Graphik Studio Gmbh",
    "wof:placetype":"venue"
},
  "geometry": {"coordinates":[8.935024,50.07938],"type":"Point"}
}