{
  "type": "Feature",
  "properties": {
    "iso:country":"DE",
    "sg:address":"Heinrichsdorf 40",
    "sg:city":"Bad Aibling",
    "sg:phone":"+49 8064/906714",
    "sg:postcode":"83043",
    "sg:province":"Bayern",
    "wof:name":"H. Schlemer",
    "wof:placetype":"venue"
},
  "geometry": {"coordinates":[11.9520750046,47.8336410522],"type":"Point"}
}