{
  "type": "Feature",
  "properties": {
    "iso:country":"DE",
    "sg:address":"Neunkirchener Str. 29",
    "sg:city":"Leipzig",
    "sg:phone":"+49 341/8621596",
    "sg:postcode":"04318",
    "sg:province":"Sachsen",
    "wof:name":"H\u00fcnicke & Sohn Gmbh",
    "wof:placetype":"venue"
},
  "geometry": {"coordinates":[12.42648983,51.3295173645],"type":"Point"}
}