{
  "type": "Feature",
  "properties": {
    "iso:country":"DE",
    "sg:address":"Pfauenweg 16",
    "sg:city":"Enger",
    "sg:phone":"+49 5224/978050",
    "sg:postcode":"32130",
    "sg:province":"Nordrhein-Westfalen",
    "wof:name":"Sima Immobilienmakler",
    "wof:placetype":"venue"
},
  "geometry": {"coordinates":[8.5906190872,52.1641311646],"type":"Point"}
}