{
  "type": "Feature",
  "properties": {
    "iso:country":"DE",
    "sg:address":"Lerchenauer Str. 40",
    "sg:city":"M\u00fcnchen",
    "sg:phone":"+49 89/3568108",
    "sg:postcode":"80809",
    "sg:province":"Bayern",
    "wof:name":"Rudolf Hesse",
    "wof:placetype":"venue"
},
  "geometry": {"coordinates":[11.5595359802,48.1753883362],"type":"Point"}
}