{
  "type": "Feature",
  "properties": {
    "iso:country":"DE",
    "sg:address":"Sch\u00fctzenstr. 2",
    "sg:city":"Schwerte",
    "sg:phone":"+49 2304/14019",
    "sg:postcode":"58239",
    "sg:province":"Nordrhein-Westfalen",
    "wof:name":"China Restaurant Bambushof",
    "wof:placetype":"venue"
},
  "geometry": {"coordinates":[7.5745530128,51.4435081482],"type":"Point"}
}