{
  "type": "Feature",
  "properties": {
    "iso:country":"DE",
    "sg:address":"Hermann-L\u00f6ns-Allee 3",
    "sg:city":"Aachen",
    "sg:phone":"+49 241/37422",
    "sg:postcode":"52074",
    "sg:province":"Nordrhein-Westfalen",
    "wof:name":"G\u00fcnter Heinig Gastronomiebetriebe Gmbh",
    "wof:placetype":"venue"
},
  "geometry": {"coordinates":[6.071831,50.761353],"type":"Point"}
}