{
  "type": "Feature",
  "properties": {
    "iso:country":"DE",
    "sg:address":"Z\u00fclpicher Str. 329",
    "sg:city":"K\u00f6ln",
    "sg:phone":"+49 221/416418",
    "sg:postcode":"50937",
    "sg:province":"Nordrhein-Westfalen",
    "wof:name":"Henri Monsieur",
    "wof:placetype":"venue"
},
  "geometry": {"coordinates":[6.9180679321,50.9209022522],"type":"Point"}
}