{
  "type": "Feature",
  "properties": {
    "iso:country":"DE",
    "sg:address":"Am Waidengraben 4",
    "sg:city":"Velen",
    "sg:phone":"+49 2863/760210",
    "sg:postcode":"46342",
    "sg:province":"Nordrhein-Westfalen",
    "wof:name":"Gabriele Nohr Heilpraktikerin",
    "wof:placetype":"venue"
},
  "geometry": {"coordinates":[6.9101758003,51.8877868652],"type":"Point"}
}