{
  "type": "Feature",
  "properties": {
    "iso:country":"DE",
    "sg:address":"Borngasse 33",
    "sg:city":"A\u00dflar",
    "sg:phone":"+49 4964/4188015",
    "sg:postcode":"35614",
    "sg:province":"Hessen",
    "wof:name":"Marc Bender",
    "wof:placetype":"venue"
},
  "geometry": {"coordinates":[8.464502,50.59462],"type":"Point"}
}