{
  "type": "Feature",
  "properties": {
    "iso:country":"DE",
    "sg:address":"Altholzstr. 40",
    "sg:city":"Deggendorf",
    "sg:phone":"+49 991/7733",
    "sg:postcode":"94469",
    "sg:province":"Bayern",
    "wof:name":"Schaller Bau Gmbh",
    "wof:placetype":"venue"
},
  "geometry": {"coordinates":[12.943473,48.807301],"type":"Point"}
}