{
  "type": "Feature",
  "properties": {
    "iso:country":"DE",
    "sg:address":"Goethestr. 44",
    "sg:city":"Holzwickede",
    "sg:phone":"+49 2301/6699",
    "sg:postcode":"59439",
    "sg:province":"Nordrhein-Westfalen",
    "wof:name":"Osu Maschinenbau Gmbh",
    "wof:placetype":"venue"
},
  "geometry": {"coordinates":[7.628995,51.502998],"type":"Point"}
}