{
  "type": "Feature",
  "properties": {
    "iso:country":"DE",
    "sg:address":"Bildst\u00f6ckleweg 7",
    "sg:city":"Baiersbronn",
    "sg:phone":"+49 7442/7075",
    "sg:postcode":"72270",
    "sg:province":"Baden-W\u00fcrttemberg",
    "wof:name":"Wilfried Cl\u00f6dy Rechtsanwalt",
    "wof:placetype":"venue"
},
  "geometry": {"coordinates":[8.369594574,48.5071258545],"type":"Point"}
}