{
  "type": "Feature",
  "properties": {
    "iso:country":"DE",
    "sg:address":"Alstater Str. 35 c",
    "sg:city":"Heidelberg",
    "sg:phone":"+49 6221/788947",
    "sg:postcode":"69124",
    "sg:province":"Baden-W\u00fcrttemberg",
    "wof:name":"Eiling Ingenieure Gmbh",
    "wof:placetype":"venue"
},
  "geometry": {"coordinates":[8.6681785583,49.3809280396],"type":"Point"}
}