{
  "type": "Feature",
  "properties": {
    "iso:country":"DE",
    "sg:address":"Kirchgasse 11",
    "sg:city":"Butzbach",
    "sg:phone":"+49 6033/4305",
    "sg:postcode":"35510",
    "sg:province":"Hessen",
    "wof:name":"Ev. Pfarramt Ostheim",
    "wof:placetype":"venue"
},
  "geometry": {"coordinates":[8.673160553,50.4355354309],"type":"Point"}
}