{
  "type": "Feature",
  "properties": {
    "iso:country":"DE",
    "sg:address":"Hirzensteinstr. 9",
    "sg:city":"Adenau",
    "sg:phone":"+49 2691/659",
    "sg:postcode":"53518",
    "sg:province":"Rheinland-Pfalz",
    "wof:name":"Johannes M\u00fcller",
    "wof:placetype":"venue"
},
  "geometry": {"coordinates":[6.9256410599,50.3794784546],"type":"Point"}
}