{
  "type": "Feature",
  "properties": {
    "iso:country":"DE",
    "sg:address":"Gro\u00dfe Gallusstr. 10",
    "sg:city":"Frankfurt",
    "sg:phone":"+49 69/5961006",
    "sg:postcode":"60311",
    "sg:province":"Hessen",
    "wof:name":"Arogran Verwaltungs-gmbh",
    "wof:placetype":"venue"
},
  "geometry": {"coordinates":[8.674346,50.111748],"type":"Point"}
}