{
  "type": "Feature",
  "properties": {
    "iso:country":"DE",
    "sg:address":"Weissadlergasse 2",
    "sg:city":"Frankfurt a.M.",
    "sg:phone":"+49 511/7245834",
    "sg:postcode":"60311",
    "sg:province":"Hessen",
    "wof:name":"Helvetia Vitafonds - Online Versichern!",
    "wof:placetype":"venue"
},
  "geometry": {"coordinates":[8.678885,50.111828],"type":"Point"}
}