{
  "type": "Feature",
  "properties": {
    "iso:country":"DE",
    "sg:address":"Postfach 1269",
    "sg:city":"Mitwitz",
    "sg:postcode":"96266",
    "sg:province":"Bayern",
    "wof:name":"Neckermann Versand Ag",
    "wof:placetype":"venue"
},
  "geometry": {"coordinates":[11.2097501755,50.2478599548],"type":"Point"}
}