{
  "type": "Feature",
  "properties": {
    "iso:country":"DE",
    "sg:address":"Zum Steinkreuz 10",
    "sg:city":"Reinhardtsgrimma",
    "sg:phone":"+49 35053/48350",
    "sg:postcode":"01768",
    "sg:province":"Sachsen",
    "wof:name":"Hamann Bauunternehmen Gmbh",
    "wof:placetype":"venue"
},
  "geometry": {"coordinates":[13.7539291382,50.8911895752],"type":"Point"}
}