{
  "type": "Feature",
  "properties": {
    "iso:country":"DE",
    "sg:address":"Heestweg 21",
    "sg:city":"Hamburg",
    "sg:phone":"+49 5731/748700",
    "sg:postcode":"22143",
    "sg:province":"Hamburg",
    "wof:name":"Stohlmann Gmbh",
    "wof:placetype":"venue"
},
  "geometry": {"coordinates":[8.774229,52.232407],"type":"Point"}
}