{
  "type": "Feature",
  "properties": {
    "iso:country":"DE",
    "sg:address":"Venloer Str. 301",
    "sg:city":"K\u00f6ln",
    "sg:phone":"+49 221/524001",
    "sg:postcode":"50823",
    "sg:province":"Nordrhein-Westfalen",
    "wof:name":"M\u00f6bel Busch Sparkauf Gmbh",
    "wof:placetype":"venue"
},
  "geometry": {"coordinates":[6.9198951721,50.948348999],"type":"Point"}
}