{
  "type": "Feature",
  "properties": {
    "iso:country":"DE",
    "sg:address":"Hans-Sachs-Str. 26",
    "sg:city":"M\u00fclheim",
    "sg:phone":"+49 208/763885",
    "sg:postcode":"45473",
    "sg:province":"Nordrhein-Westfalen",
    "wof:name":"M. Conzen-mader Und W. Mader Steuerberater",
    "wof:placetype":"venue"
},
  "geometry": {"coordinates":[6.9105949402,51.4449234009],"type":"Point"}
}