{
  "type": "Feature",
  "properties": {
    "iso:country":"DE",
    "sg:address":"Allemannenstr. 7",
    "sg:city":"Gunzenhausen",
    "sg:phone":"+49 9831/4059",
    "sg:postcode":"91710",
    "sg:province":"Bayern",
    "wof:name":"Leberzammer Mineral\u00d6le Gmbh",
    "wof:placetype":"venue"
},
  "geometry": {"coordinates":[10.754282,49.122536],"type":"Point"}
}