{
  "type": "Feature",
  "properties": {
    "iso:country":"DE",
    "sg:address":"Hauptstr. 45",
    "sg:city":"Wietmarschen",
    "sg:phone":"+49 5908/269",
    "sg:postcode":"49835",
    "sg:province":"Niedersachsen",
    "wof:name":"Kath. \u00f6ffentlicher B\u00fccherei Lohne",
    "wof:placetype":"venue"
},
  "geometry": {"coordinates":[7.228575,52.495556],"type":"Point"}
}