{
  "type": "Feature",
  "properties": {
    "iso:country":"DE",
    "sg:address":"Schlo\u00dfstr. 91",
    "sg:city":"Dortmund",
    "sg:postcode":"44357",
    "sg:province":"Nordrhein-Westfalen",
    "wof:name":"Phoenix-data Gmbh",
    "wof:placetype":"venue"
},
  "geometry": {"coordinates":[7.3607001305,51.5499420166],"type":"Point"}
}