{
  "type": "Feature",
  "properties": {
    "iso:country":"DE",
    "sg:address":"Nincoper Str 143",
    "sg:city":"Hamburg",
    "sg:phone":"+49 40/7459246",
    "sg:postcode":"21129",
    "sg:province":"Hamburg",
    "wof:name":"Wilhelm Prigge & Co",
    "wof:placetype":"venue"
},
  "geometry": {"coordinates":[9.770872,53.521133],"type":"Point"}
}