{
  "type": "Feature",
  "properties": {
    "iso:country":"DE",
    "sg:address":"Oehleckerring 4a",
    "sg:city":"Hamburg",
    "sg:phone":"+49 40/53323322",
    "sg:postcode":"22419",
    "sg:province":"Hamburg",
    "wof:name":"August Kahl Brennstoffhandel Inh. Brigitte Billing",
    "wof:placetype":"venue"
},
  "geometry": {"coordinates":[10.0044116974,53.6603927612],"type":"Point"}
}