{
  "type": "Feature",
  "properties": {
    "iso:country":"DE",
    "sg:address":"Eichendorffstr. 25",
    "sg:city":"Leinfelden-Echterdingen",
    "sg:phone":"+49 711/7543636",
    "sg:postcode":"70771",
    "sg:province":"Baden-W\u00fcrttemberg",
    "wof:name":"Manfred Schmauder",
    "wof:placetype":"venue"
},
  "geometry": {"coordinates":[9.1229686737,48.7025184631],"type":"Point"}
}