{
  "type": "Feature",
  "properties": {
    "iso:country":"DE",
    "sg:address":"Berkheimer Str. 24a",
    "sg:city":"Esslingen",
    "sg:phone":"+49 711/382600",
    "sg:postcode":"73734",
    "sg:province":"Baden-W\u00fcrttemberg",
    "wof:name":"Rudolf Brandt Tennislehrer",
    "wof:placetype":"venue"
},
  "geometry": {"coordinates":[9.3041763306,48.7346687317],"type":"Point"}
}