{
  "type": "Feature",
  "properties": {
    "iso:country":"DE",
    "sg:address":"Weiherhofer Str. 52",
    "sg:city":"F\u00fcrth",
    "sg:phone":"+49 911/729727",
    "sg:postcode":"90768",
    "sg:province":"Bayern",
    "wof:name":"G\u00fcnter Litwora",
    "wof:placetype":"venue"
},
  "geometry": {"coordinates":[10.971095,49.46154],"type":"Point"}
}