{
  "type": "Feature",
  "properties": {
    "iso:country":"DE",
    "sg:address":"Hornsche Strasse 38",
    "sg:city":"Detmold",
    "sg:phone":"+49 5231/390603",
    "sg:postcode":"32756",
    "sg:province":"Nordrhein-Westfalen",
    "wof:name":"Literaturbuero Owl In Detmold E.v",
    "wof:placetype":"venue"
},
  "geometry": {"coordinates":[8.880833,51.931622],"type":"Point"}
}