{
  "type": "Feature",
  "properties": {
    "iso:country":"DE",
    "sg:address":"Rheinstr. 48",
    "sg:city":"Dienheim",
    "sg:phone":"+49 6133/1366",
    "sg:postcode":"55276",
    "sg:province":"Rheinland-Pfalz",
    "wof:name":"F. J. Und U. Duttenh\u00f6fer",
    "wof:placetype":"venue"
},
  "geometry": {"coordinates":[8.3499259949,49.8390541077],"type":"Point"}
}