{
  "type": "Feature",
  "properties": {
    "iso:country":"DE",
    "sg:address":"Schachtenstr. 10d",
    "sg:city":"Vilsbiburg",
    "sg:phone":"+49 8741/7220",
    "sg:postcode":"84137",
    "sg:province":"Bayern",
    "wof:name":"P. Kleebauer",
    "wof:placetype":"venue"
},
  "geometry": {"coordinates":[12.3534736633,48.4585037231],"type":"Point"}
}