{
  "type": "Feature",
  "properties": {
    "iso:country":"DE",
    "sg:address":"Goethestr. 6",
    "sg:city":"Radolfzell",
    "sg:phone":"+49 7732/919712",
    "sg:postcode":"78315",
    "sg:province":"Baden-W\u00fcrttemberg",
    "wof:name":"M. Zigrit",
    "wof:placetype":"venue"
},
  "geometry": {"coordinates":[8.9782390594,47.7430152893],"type":"Point"}
}