{
  "type": "Feature",
  "properties": {
    "iso:country":"DE",
    "sg:address":"Friedrich-Koenig-Str. 15",
    "sg:city":"W\u00fcrzburg",
    "sg:phone":"+49 931/900940",
    "sg:postcode":"97080",
    "sg:province":"Bayern",
    "wof:name":"Deutsche Shell Ag",
    "wof:placetype":"venue"
},
  "geometry": {"coordinates":[9.8776197433,49.8094787598],"type":"Point"}
}