{
  "type": "Feature",
  "properties": {
    "iso:country":"DE",
    "sg:address":"Muggensturmer Landstr. 2",
    "sg:city":"Bietigheim",
    "sg:postcode":"76467",
    "sg:province":"Baden-W\u00fcrttemberg",
    "wof:name":"Bie Beteiligungs- Gmbh",
    "wof:placetype":"venue"
},
  "geometry": {"coordinates":[8.266776,48.888268],"type":"Point"}
}