{
  "type": "Feature",
  "properties": {
    "iso:country":"DE",
    "sg:address":"St.-Anna-Platz 2",
    "sg:city":"M\u00fcnchen",
    "sg:phone":"+49 89/2422700",
    "sg:postcode":"80538",
    "sg:province":"Bayern",
    "wof:name":"G\u00fcnther Wagner Rechtsanwalt",
    "wof:placetype":"venue"
},
  "geometry": {"coordinates":[11.5874080658,48.1399765015],"type":"Point"}
}