{
  "type": "Feature",
  "properties": {
    "iso:country":"DE",
    "sg:address":"Sudhoferwg. 99-107",
    "sg:city":"Beckum",
    "sg:phone":"+49 6894/580797",
    "sg:postcode":"59269",
    "sg:province":"Nordrhein-Westfalen",
    "wof:name":"Molter + Pink Gmbh",
    "wof:placetype":"venue"
},
  "geometry": {"coordinates":[7.162878,49.271317],"type":"Point"}
}