{
  "type": "Feature",
  "properties": {
    "iso:country":"DE",
    "sg:address":"Bachanger 14",
    "sg:city":"Ruhstorf",
    "sg:phone":"+49 8531/31223",
    "sg:postcode":"94099",
    "sg:province":"Bayern",
    "wof:name":"Josef Probsteder",
    "wof:placetype":"venue"
},
  "geometry": {"coordinates":[13.3397798538,48.4342384338],"type":"Point"}
}