{
  "type": "Feature",
  "properties": {
    "iso:country":"DE",
    "sg:address":"Hauptstr. 19",
    "sg:city":"Haiger",
    "sg:phone":"+49 2773/1515",
    "sg:postcode":"35708",
    "sg:province":"Hessen",
    "wof:name":"Ingrid Lenz",
    "wof:placetype":"venue"
},
  "geometry": {"coordinates":[8.206016,50.74118],"type":"Point"}
}