{
  "type": "Feature",
  "properties": {
    "iso:country":"DE",
    "sg:address":"Str\u00fcmpfelbacher Str. 1",
    "sg:city":"Weinstadt",
    "sg:phone":"+49 7151/600592",
    "sg:postcode":"71384",
    "sg:province":"Baden-W\u00fcrttemberg",
    "wof:name":"Mehmet Efe",
    "wof:placetype":"venue"
},
  "geometry": {"coordinates":[9.3667726517,48.8133392334],"type":"Point"}
}