{
  "type": "Feature",
  "properties": {
    "iso:country":"DE",
    "sg:address":"Hauptstr. 7",
    "sg:city":"Steigra",
    "sg:phone":"+49 34461/54825",
    "sg:postcode":"06268",
    "sg:province":"Sachsen-Anhalt",
    "wof:name":"S. Fiedler",
    "wof:placetype":"venue"
},
  "geometry": {"coordinates":[11.658361,51.301285],"type":"Point"}
}