{
  "type": "Feature",
  "properties": {
    "iso:country":"DE",
    "sg:address":"Wei\u00dfenthurmer Str. 8",
    "sg:city":"Kettig",
    "sg:phone":"+49 2637/600182",
    "sg:postcode":"56220",
    "sg:province":"Rheinland-Pfalz",
    "wof:name":"Wh Weber - Hermann Ingenieure Gmbh",
    "wof:placetype":"venue"
},
  "geometry": {"coordinates":[7.4625868797,50.3990287781],"type":"Point"}
}