{
  "type": "Feature",
  "properties": {
    "iso:country":"DE",
    "sg:address":"Schwabstr. 36a",
    "sg:city":"Stuttgart",
    "sg:phone":"+49 711/666020",
    "sg:postcode":"70197",
    "sg:province":"Baden-W\u00fcrttemberg",
    "wof:name":"Optiplan Gmbh",
    "wof:placetype":"venue"
},
  "geometry": {"coordinates":[9.157313,48.771931],"type":"Point"}
}