{
  "type": "Feature",
  "properties": {
    "iso:country":"DE",
    "sg:address":"Kanalstr. 12",
    "sg:city":"Mainz",
    "sg:phone":"+49 6131/507389",
    "sg:postcode":"55129",
    "sg:province":"Rheinland-Pfalz",
    "wof:name":"Jakob V. Holz",
    "wof:placetype":"venue"
},
  "geometry": {"coordinates":[8.280223,49.957989],"type":"Point"}
}