{
  "type": "Feature",
  "properties": {
    "iso:country":"DE",
    "sg:address":"Netzeweg 35",
    "sg:city":"Bielefeld",
    "sg:phone":"+49 5205/5379",
    "sg:postcode":"33689",
    "sg:province":"Nordrhein-Westfalen",
    "wof:name":"H. Schleicher Heissmangel",
    "wof:placetype":"venue"
},
  "geometry": {"coordinates":[8.5959510803,51.9487304688],"type":"Point"}
}