{
  "type": "Feature",
  "properties": {
    "iso:country":"DE",
    "sg:address":"Hoyerswerdaer Str. 42",
    "sg:city":"Radibor",
    "sg:phone":"+49 35935/3257",
    "sg:postcode":"02627",
    "sg:province":"Sachsen",
    "wof:name":"Bilk Kapelle Taifun",
    "wof:placetype":"venue"
},
  "geometry": {"coordinates":[14.5417833328,51.1927566528],"type":"Point"}
}