{
  "type": "Feature",
  "properties": {
    "iso:country":"DE",
    "sg:address":"Kulbitzring 27",
    "sg:city":"Marktzeuln",
    "sg:phone":"+49 9574/1777",
    "sg:postcode":"96275",
    "sg:province":"Bayern",
    "wof:name":"Rainer Michel Architekt",
    "wof:placetype":"venue"
},
  "geometry": {"coordinates":[11.164643,50.164505],"type":"Point"}
}