{
  "type": "Feature",
  "properties": {
    "iso:country":"DE",
    "sg:address":"Wiesenstr. 11",
    "sg:city":"Zeuthen",
    "sg:phone":"+49 33762/71439",
    "sg:postcode":"15738",
    "sg:province":"Brandenburg",
    "wof:name":"J. Thomas",
    "wof:placetype":"venue"
},
  "geometry": {"coordinates":[13.615694,52.35561],"type":"Point"}
}