{
  "type": "Feature",
  "properties": {
    "iso:country":"DE",
    "sg:address":"Porschestr. 84",
    "sg:city":"Wolfsburg",
    "sg:phone":"+49 5361/15155",
    "sg:postcode":"38440",
    "sg:province":"Niedersachsen",
    "wof:name":"B. Staats",
    "wof:placetype":"venue"
},
  "geometry": {"coordinates":[10.785626,52.420483],"type":"Point"}
}