{
  "type": "Feature",
  "properties": {
    "iso:country":"DE",
    "sg:address":"Am Bahnhof 12",
    "sg:city":"Olpe",
    "sg:phone":"+49 4927/618080",
    "sg:postcode":"57462",
    "sg:province":"Nordrhein-Westfalen",
    "wof:name":"Sibo-verpackungen Bernd Hesse Gmbh & Co. Kg",
    "wof:placetype":"venue"
},
  "geometry": {"coordinates":[7.8437771797,51.0279579163],"type":"Point"}
}