{
  "type": "Feature",
  "properties": {
    "iso:country":"DE",
    "sg:address":"Auf der Postwacht 4",
    "sg:city":"Nienburg",
    "sg:phone":"+49 5021/912118",
    "sg:postcode":"31582",
    "sg:province":"Niedersachsen",
    "wof:name":"Immobilienmarketing Andreas Thiel",
    "wof:placetype":"venue"
},
  "geometry": {"coordinates":[9.2203760147,52.6270103455],"type":"Point"}
}