{
  "type": "Feature",
  "properties": {
    "iso:country":"DE",
    "sg:address":"B\u00f6blinger Str. 225",
    "sg:city":"Stuttgart",
    "sg:phone":"+49 711/6017390",
    "sg:postcode":"70199",
    "sg:province":"Baden-W\u00fcrttemberg",
    "wof:name":"Marcrist Diamantwerkzeuge Vertriebsgesellschaft Mbh",
    "wof:placetype":"venue"
},
  "geometry": {"coordinates":[9.1431722641,48.7562980652],"type":"Point"}
}