{
  "type": "Feature",
  "properties": {
    "iso:country":"DE",
    "sg:address":"Bergsteinstr. 35",
    "sg:city":"Neustadt",
    "sg:phone":"+49 6321/82290",
    "sg:postcode":"67434",
    "sg:province":"Rheinland-Pfalz",
    "wof:name":"W. Paschek",
    "wof:placetype":"venue"
},
  "geometry": {"coordinates":[8.1196527481,49.337059021],"type":"Point"}
}