{
  "type": "Feature",
  "properties": {
    "iso:country":"DE",
    "sg:address":"Flurstra\u00dfe",
    "sg:city":"Schmalenberg",
    "sg:phone":"+49 6307/4010037",
    "sg:postcode":"67718",
    "sg:province":"Rheinland-Pfalz",
    "wof:name":"Faltenrock",
    "wof:placetype":"venue"
},
  "geometry": {"coordinates":[7.73169,49.331806],"type":"Point"}
}