{
  "type": "Feature",
  "properties": {
    "iso:country":"DE",
    "sg:address":"Berner Str. 23",
    "sg:city":"Frankfurt",
    "sg:phone":"+49 69/500070",
    "sg:postcode":"60437",
    "sg:province":"Hessen",
    "wof:name":"Khk Software Gmbh",
    "wof:placetype":"venue"
},
  "geometry": {"coordinates":[8.6640758514,50.1932258606],"type":"Point"}
}