{
  "type": "Feature",
  "properties": {
    "iso:country":"DE",
    "sg:address":"Burghausener Str. 29",
    "sg:city":"Kirchweidach",
    "sg:phone":"+49 8623/224",
    "sg:postcode":"84558",
    "sg:province":"Bayern",
    "wof:name":"Sterflinger & Sohn Inh. Josef Sterflinger E. K.",
    "wof:placetype":"venue"
},
  "geometry": {"coordinates":[12.649171,48.090244],"type":"Point"}
}