{
  "type": "Feature",
  "properties": {
    "iso:country":"DE",
    "sg:address":"Eichh\u00f6rnchenweg 11",
    "sg:city":"Kleinmachnow",
    "sg:phone":"+49 33203/24456",
    "sg:postcode":"14532",
    "sg:province":"Brandenburg",
    "wof:name":"Herbert Wahl",
    "wof:placetype":"venue"
},
  "geometry": {"coordinates":[13.199955,52.399288],"type":"Point"}
}