{
  "type": "Feature",
  "properties": {
    "iso:country":"DE",
    "sg:address":"Karl-Wiechert-Allee 76 A",
    "sg:city":"Hannover",
    "sg:phone":"+49 511/542770",
    "sg:postcode":"30625",
    "sg:province":"Niedersachsen",
    "wof:name":"Cochlear Gmbh",
    "wof:placetype":"venue"
},
  "geometry": {"coordinates":[9.7961406708,52.3943367004],"type":"Point"}
}