{
  "type": "Feature",
  "properties": {
    "iso:country":"DE",
    "sg:address":"Siemensstr. 13",
    "sg:city":"Hainburg",
    "sg:postcode":"63512",
    "sg:province":"Hessen",
    "wof:name":"Baustofflabor Beton- Und Baustoffpr\u00fcfung Gmbh",
    "wof:placetype":"venue"
},
  "geometry": {"coordinates":[8.967594,50.066376],"type":"Point"}
}