{
  "type": "Feature",
  "properties": {
    "iso:country":"DE",
    "sg:address":"Marktstr. 48",
    "sg:city":"Weinstadt",
    "sg:phone":"+49 7151/660770",
    "sg:postcode":"71384",
    "sg:province":"Baden-W\u00fcrttemberg",
    "wof:name":"Erbach",
    "wof:placetype":"venue"
},
  "geometry": {"coordinates":[9.389072,48.804585],"type":"Point"}
}