{
  "type": "Feature",
  "properties": {
    "iso:country":"DE",
    "sg:address":"Gr\u00e4ffstr. 40",
    "sg:city":"Heppenheim",
    "sg:phone":"+49 6252/6599",
    "sg:postcode":"64646",
    "sg:province":"Hessen",
    "wof:name":"Rudolf Prochatschek",
    "wof:placetype":"venue"
},
  "geometry": {"coordinates":[8.6407823563,49.6395454407],"type":"Point"}
}