{
  "type": "Feature",
  "properties": {
    "iso:country":"DE",
    "sg:address":"Holunderweg 4",
    "sg:city":"D\u00fcsseldorf",
    "sg:phone":"+49 203/742817",
    "sg:postcode":"40489",
    "sg:province":"Nordrhein-Westfalen",
    "wof:name":"G. Rohde Rohstoffe Handels-gmbh",
    "wof:placetype":"venue"
},
  "geometry": {"coordinates":[6.7797551155,51.3248062134],"type":"Point"}
}