{
  "type": "Feature",
  "properties": {
    "iso:country":"DE",
    "sg:address":"Zum B\u00f6dden 12",
    "sg:city":"Bakum",
    "sg:phone":"+49 5438/429",
    "sg:postcode":"49456",
    "sg:province":"Niedersachsen",
    "wof:name":"Clemens Ording",
    "wof:placetype":"venue"
},
  "geometry": {"coordinates":[8.063851,52.747375],"type":"Point"}
}