{
  "type": "Feature",
  "properties": {
    "iso:country":"DE",
    "sg:address":"Bergstr. 77",
    "sg:city":"Esslingen",
    "sg:phone":"+49 711/372031",
    "sg:postcode":"73733",
    "sg:province":"Baden-W\u00fcrttemberg",
    "wof:name":"Schrieble & Partner Kg",
    "wof:placetype":"venue"
},
  "geometry": {"coordinates":[9.2927312851,48.7563705444],"type":"Point"}
}