{
  "type": "Feature",
  "properties": {
    "iso:country":"DE",
    "sg:address":"Ah\u00e4user Weg 8-10",
    "sg:city":"Weilburg",
    "sg:phone":"+49 6471/39081",
    "sg:postcode":"35781",
    "sg:province":"Hessen",
    "wof:name":"Brauerei August Helbig Kg",
    "wof:placetype":"venue"
},
  "geometry": {"coordinates":[8.269735,50.486454],"type":"Point"}
}