{
  "type": "Feature",
  "properties": {
    "iso:country":"DE",
    "sg:address":"Weilheimer Str. 15",
    "sg:city":"Murnau",
    "sg:phone":"+49 8841/3045",
    "sg:postcode":"82418",
    "sg:province":"Bayern",
    "wof:name":"Michael Neuhaus",
    "wof:placetype":"venue"
},
  "geometry": {"coordinates":[11.1999454498,47.682598114],"type":"Point"}
}