{
  "type": "Feature",
  "properties": {
    "iso:country":"DE",
    "sg:address":"Ravensburger Ring 10",
    "sg:city":"M\u00fcnchen",
    "sg:phone":"+49 89/8349550",
    "sg:postcode":"81243",
    "sg:province":"Bayern",
    "wof:name":"H.-j. H\u00fcbelmann Immobilienmakler",
    "wof:placetype":"venue"
},
  "geometry": {"coordinates":[11.4403219223,48.150390625],"type":"Point"}
}