{
  "type": "Feature",
  "properties": {
    "iso:country":"DE",
    "sg:address":"Grassistr. 22",
    "sg:city":"Leipzig",
    "sg:phone":"+49 341/566470",
    "sg:postcode":"04107",
    "sg:province":"Sachsen",
    "wof:name":"J. S. Immobilienbeteiligungen E. K.",
    "wof:placetype":"venue"
},
  "geometry": {"coordinates":[12.367744,51.330379],"type":"Point"}
}