{
  "type": "Feature",
  "properties": {
    "iso:country":"DE",
    "sg:address":"Marktstr. 92",
    "sg:city":"Bonn",
    "sg:phone":"+49 228/481924",
    "sg:postcode":"53229",
    "sg:province":"Nordrhein-Westfalen",
    "wof:name":"Annemarie H\u00e4rling",
    "wof:placetype":"venue"
},
  "geometry": {"coordinates":[7.157625,50.746635],"type":"Point"}
}