{
  "type": "Feature",
  "properties": {
    "iso:country":"DE",
    "sg:address":"Morsteiner Weg 3",
    "sg:city":"Gerabronn",
    "sg:phone":"+49 7952/5425",
    "sg:postcode":"74582",
    "sg:province":"Baden-W\u00fcrttemberg",
    "wof:name":"E. Wahle",
    "wof:placetype":"venue"
},
  "geometry": {"coordinates":[9.88559,49.215805],"type":"Point"}
}