{
  "type": "Feature",
  "properties": {
    "iso:country":"DE",
    "sg:address":"John-Graudenz-Str.",
    "sg:city":"Stahnsdorf",
    "sg:phone":"+49 3329/612285",
    "sg:postcode":"14532",
    "sg:province":"Brandenburg",
    "wof:name":"Bernd Nedess",
    "wof:placetype":"venue"
},
  "geometry": {"coordinates":[13.19711,52.392208],"type":"Point"}
}