{
  "type": "Feature",
  "properties": {
    "iso:country":"DE",
    "sg:address":"Alte Gasse 16",
    "sg:city":"Augsburg",
    "sg:phone":"+49 821/514926",
    "sg:postcode":"86152",
    "sg:province":"Bayern",
    "wof:name":"Auskunftei-genossenschaft Eg",
    "wof:placetype":"venue"
},
  "geometry": {"coordinates":[10.892559,48.373528],"type":"Point"}
}