{
  "type": "Feature",
  "properties": {
    "iso:country":"DE",
    "sg:address":"Frankenweg 9",
    "sg:city":"K\u00fcnzelsau",
    "sg:phone":"+49 7940/3691",
    "sg:postcode":"74653",
    "sg:province":"Baden-W\u00fcrttemberg",
    "wof:name":"Tennisst\u00fcble",
    "wof:placetype":"venue"
},
  "geometry": {"coordinates":[9.6979055405,49.2794761658],"type":"Point"}
}