{
  "type": "Feature",
  "properties": {
    "iso:country":"DE",
    "sg:address":"Rotzler Str. 22",
    "sg:city":"Murg",
    "sg:phone":"+49 7763/4662",
    "sg:postcode":"79730",
    "sg:province":"Baden-W\u00fcrttemberg",
    "wof:name":"E. Mutter",
    "wof:placetype":"venue"
},
  "geometry": {"coordinates":[8.041217804,47.5942764282],"type":"Point"}
}