{
  "type": "Feature",
  "properties": {
    "iso:country":"DE",
    "sg:address":"Wingertstr. 2",
    "sg:city":"Schweinfurt",
    "sg:phone":"+49 9721/21158",
    "sg:postcode":"97422",
    "sg:province":"Bayern",
    "wof:name":"Schorsch Pfister Architekt",
    "wof:placetype":"venue"
},
  "geometry": {"coordinates":[10.240842,50.050377],"type":"Point"}
}