{
  "type": "Feature",
  "properties": {
    "iso:country":"DE",
    "sg:address":"Au\u00dferhalb 96",
    "sg:city":"Langen",
    "sg:phone":"+49 6103/71192",
    "sg:postcode":"63225",
    "sg:province":"Hessen",
    "wof:name":"Vereinsgastst\u00e4tte Waldstadion 1. Fc Oberlinden",
    "wof:placetype":"venue"
},
  "geometry": {"coordinates":[8.6520662308,49.9796257019],"type":"Point"}
}