{
  "type": "Feature",
  "properties": {
    "iso:country":"DE",
    "sg:address":"Paul-Spindler-Str. 4",
    "sg:city":"Nast\u00e4tten",
    "sg:phone":"+49 6772/8309",
    "sg:postcode":"56355",
    "sg:province":"Rheinland-Pfalz",
    "wof:name":"Ev. Pfarramt Nast\u00e4tten",
    "wof:placetype":"venue"
},
  "geometry": {"coordinates":[7.8535819054,50.2007980347],"type":"Point"}
}