{
  "type": "Feature",
  "properties": {
    "iso:country":"DE",
    "sg:address":"Elberfelder Str. 35",
    "sg:city":"Velbert",
    "sg:phone":"+49 2053/40178",
    "sg:postcode":"42553",
    "sg:province":"Nordrhein-Westfalen",
    "wof:name":"Eiscafe Friuli",
    "wof:placetype":"venue"
},
  "geometry": {"coordinates":[7.089233,51.311485],"type":"Point"}
}