{
  "type": "Feature",
  "properties": {
    "iso:country":"DE",
    "sg:address":"Oberhausener Str. 177",
    "sg:city":"M\u00fclheim",
    "sg:phone":"+49 208/992680",
    "sg:postcode":"45476",
    "sg:province":"Nordrhein-Westfalen",
    "wof:name":"Kriemhild Zillig Steuerberaterin",
    "wof:placetype":"venue"
},
  "geometry": {"coordinates":[6.859087944,51.4513320923],"type":"Point"}
}