{
  "type": "Feature",
  "properties": {
    "iso:country":"DE",
    "sg:address":"Breitseeweg 29",
    "sg:city":"Dreieich",
    "sg:phone":"+49 6103/66007",
    "sg:postcode":"63303",
    "sg:province":"Hessen",
    "wof:name":"Georg Gleiser Kg",
    "wof:placetype":"venue"
},
  "geometry": {"coordinates":[8.671959,50.027637],"type":"Point"}
}