{
  "type": "Feature",
  "properties": {
    "iso:country":"DE",
    "sg:address":"Eggenfeldener Str. 4",
    "sg:city":"Geratskirchen",
    "sg:phone":"+49 8728/212",
    "sg:postcode":"84552",
    "sg:province":"Bayern",
    "wof:name":"Johann Hallhuber",
    "wof:placetype":"venue"
},
  "geometry": {"coordinates":[12.6647205353,48.337272644],"type":"Point"}
}