{
  "type": "Feature",
  "properties": {
    "iso:country":"DE",
    "sg:address":"Kindermannstr. 129",
    "sg:city":"Gotha",
    "sg:phone":"+49 3621/704043",
    "sg:postcode":"99867",
    "sg:province":"Th\u00fcringen",
    "wof:name":"L\u00f6ffel Anlageberater",
    "wof:placetype":"venue"
},
  "geometry": {"coordinates":[10.7018060684,50.9340744019],"type":"Point"}
}