{
  "type": "Feature",
  "properties": {
    "iso:country":"DE",
    "sg:address":"Einsteinstr 17",
    "sg:city":"Sersheim",
    "sg:phone":"+49 7042/83610",
    "sg:postcode":"74372",
    "sg:province":"Baden-W\u00fcrttemberg",
    "wof:name":"Wolf + Hekel Gmbh & Co Kg",
    "wof:placetype":"venue"
},
  "geometry": {"coordinates":[9.00229,48.956341],"type":"Point"}
}