{
  "type": "Feature",
  "properties": {
    "iso:country":"DE",
    "sg:address":"Am Rande 20",
    "sg:city":"Kassel",
    "sg:phone":"+49 561/882385",
    "sg:postcode":"34128",
    "sg:province":"Hessen",
    "wof:name":"Hans Rudolf Braun",
    "wof:placetype":"venue"
},
  "geometry": {"coordinates":[9.457461,51.337742],"type":"Point"}
}