{
  "type": "Feature",
  "properties": {
    "iso:country":"DE",
    "sg:address":"Leipziger Str. 6",
    "sg:city":"Unterhaching",
    "sg:phone":"+49 89/6118695",
    "sg:postcode":"82008",
    "sg:province":"Bayern",
    "wof:name":"Altendorf Und Rieger",
    "wof:placetype":"venue"
},
  "geometry": {"coordinates":[11.6155939102,48.0659980774],"type":"Point"}
}