{
  "type": "Feature",
  "properties": {
    "iso:country":"DE",
    "sg:address":"Stahlwerkstr. 35",
    "sg:city":"Mudersbach",
    "sg:phone":"+49 2745/931116",
    "sg:postcode":"57555",
    "sg:province":"Rheinland-Pfalz",
    "wof:name":"Gebr\u00fcder Uebach Mechanische Fertigungs Gmbh",
    "wof:placetype":"venue"
},
  "geometry": {"coordinates":[7.95138,50.830666],"type":"Point"}
}