{
  "type": "Feature",
  "properties": {
    "iso:country":"DE",
    "sg:address":"Neuer weg 7",
    "sg:city":"M\u00fccke",
    "sg:phone":"+49 6400",
    "sg:postcode":"35325",
    "sg:province":"Hessen",
    "wof:name":"Abnehmen",
    "wof:placetype":"venue"
},
  "geometry": {"coordinates":[9.030977,50.608669],"type":"Point"}
}