{
  "type": "Feature",
  "properties": {
    "iso:country":"DE",
    "sg:address":"Hamburger Str. 26",
    "sg:city":"Wuppertal",
    "sg:phone":"+49 202/752325",
    "sg:postcode":"42109",
    "sg:province":"Nordrhein-Westfalen",
    "wof:name":"Willi G\u00f6bbel",
    "wof:placetype":"venue"
},
  "geometry": {"coordinates":[7.147796,51.269821],"type":"Point"}
}