{
  "type": "Feature",
  "properties": {
    "iso:country":"DE",
    "sg:address":"Goethestr. 2",
    "sg:city":"Linsengericht",
    "sg:phone":"+49 6051/73667",
    "sg:postcode":"63589",
    "sg:province":"Hessen",
    "wof:name":"Friedrich Bock",
    "wof:placetype":"venue"
},
  "geometry": {"coordinates":[9.201234,50.186131],"type":"Point"}
}