{
  "type": "Feature",
  "properties": {
    "iso:country":"DE",
    "sg:address":"Sinkelweg 3",
    "sg:city":"Wehringen",
    "sg:phone":"+49 8234/41922",
    "sg:postcode":"86517",
    "sg:province":"Bayern",
    "wof:name":"Schreiber Finanzberater",
    "wof:placetype":"venue"
},
  "geometry": {"coordinates":[10.8028068542,48.2493362427],"type":"Point"}
}