{
  "type": "Feature",
  "properties": {
    "iso:country":"DE",
    "sg:address":"Gleviner Str. 29",
    "sg:city":"G\u00fcstrow",
    "sg:phone":"+49 3843/686733",
    "sg:postcode":"18273",
    "sg:province":"Mecklenburg-Vorpommern",
    "wof:name":"Wiener Cafe",
    "wof:placetype":"venue"
},
  "geometry": {"coordinates":[12.177816391,53.7922782898],"type":"Point"}
}