{
  "type": "Feature",
  "properties": {
    "iso:country":"DE",
    "sg:address":"Ramskamp 65",
    "sg:city":"Elmshorn",
    "sg:phone":"+49 4121/43940",
    "sg:postcode":"25337",
    "sg:province":"Schleswig-Holstein",
    "wof:name":"Mecotec Me\u00df-regel-computer Technologie Gmbh",
    "wof:placetype":"venue"
},
  "geometry": {"coordinates":[9.695571,53.741383],"type":"Point"}
}