{
  "type": "Feature",
  "properties": {
    "iso:country":"DE",
    "sg:address":"Bromergasse 16",
    "sg:city":"Mahlberg",
    "sg:phone":"+49 7825/469",
    "sg:postcode":"77972",
    "sg:province":"Baden-W\u00fcrttemberg",
    "wof:name":"Horst B\u00fcrkle",
    "wof:placetype":"venue"
},
  "geometry": {"coordinates":[7.814116,48.287647],"type":"Point"}
}