{
  "type": "Feature",
  "properties": {
    "iso:country":"DE",
    "sg:address":"Ostrach",
    "sg:city":"Ostrach",
    "sg:phone":"+49 4975/851531",
    "sg:postcode":"88356",
    "sg:province":"Baden-W\u00fcrttemberg",
    "wof:name":"Hohenzollerische Landesbank, Kreissparkasse Burgweiler",
    "wof:placetype":"venue"
},
  "geometry": {"coordinates":[9.3672,47.94846],"type":"Point"}
}