{
  "type": "Feature",
  "properties": {
    "iso:country":"DE",
    "sg:address":"Stefanusstr. 8",
    "sg:city":"Gr\u00e4felfing",
    "sg:postcode":"82166",
    "sg:province":"Bayern",
    "wof:name":"Lehr- Und Versuchsanstalt F. Brauer-institut D. Vereins D.",
    "wof:placetype":"venue"
},
  "geometry": {"coordinates":[11.4356393814,48.1150360107],"type":"Point"}
}