{
  "type": "Feature",
  "properties": {
    "iso:country":"DE",
    "sg:address":"Louisenstr. 131",
    "sg:city":"Bad Homburg",
    "sg:phone":"+49 6172/459016",
    "sg:postcode":"61348",
    "sg:province":"Hessen",
    "wof:name":"Marx",
    "wof:placetype":"venue"
},
  "geometry": {"coordinates":[8.625311,50.222775],"type":"Point"}
}