{
  "type": "Feature",
  "properties": {
    "iso:country":"DE",
    "sg:address":"Jahnstr. 4",
    "sg:city":"Dargun",
    "sg:phone":"+49 39959/20310",
    "sg:postcode":"17159",
    "sg:province":"Mecklenburg-Vorpommern",
    "wof:name":"Bestattungshaus Kolass",
    "wof:placetype":"venue"
},
  "geometry": {"coordinates":[12.856645,53.899021],"type":"Point"}
}