{
  "type": "Feature",
  "properties": {
    "iso:country":"DE",
    "sg:address":"Hefnersplatz 9",
    "sg:city":"N\u00fcrnberg",
    "sg:phone":"+49 911/553541",
    "sg:postcode":"90402",
    "sg:province":"Bayern",
    "wof:name":"Schn\u00fcrch Und Kollegen Rechtsanw\u00e4lte",
    "wof:placetype":"venue"
},
  "geometry": {"coordinates":[11.0720062256,49.4507446289],"type":"Point"}
}