{
  "type": "Feature",
  "properties": {
    "iso:country":"DE",
    "sg:address":"K\u00fcnkelstr. 69",
    "sg:city":"M\u00f6nchengladbach",
    "sg:phone":"+49 2161/92090",
    "sg:postcode":"41063",
    "sg:province":"Nordrhein-Westfalen",
    "wof:name":"Heinrich M\u00fchlen & Co.",
    "wof:placetype":"venue"
},
  "geometry": {"coordinates":[6.453045845,51.2104263306],"type":"Point"}
}