{
  "type": "Feature",
  "properties": {
    "iso:country":"DE",
    "sg:address":"M\u00e4rkische Str. 24a",
    "sg:city":"Schwerte",
    "sg:phone":"+49 2304/21635",
    "sg:postcode":"58239",
    "sg:province":"Nordrhein-Westfalen",
    "wof:name":"Klaus-dieter Schr\u00f6der",
    "wof:placetype":"venue"
},
  "geometry": {"coordinates":[7.566538,51.447735],"type":"Point"}
}