{
  "type": "Feature",
  "properties": {
    "iso:country":"DE",
    "sg:address":"R\u00fcbenkamp 17",
    "sg:city":"Seevetal",
    "sg:phone":"+49 4105/861111",
    "sg:postcode":"21220",
    "sg:province":"Niedersachsen",
    "wof:name":"Laminieren",
    "wof:placetype":"venue"
},
  "geometry": {"coordinates":[10.026763916,53.3903808594],"type":"Point"}
}