{
  "type": "Feature",
  "properties": {
    "iso:country":"DE",
    "sg:address":"Ringstra\u00dfe 4",
    "sg:city":"Hohentengen",
    "sg:phone":"+49 7572/3522",
    "sg:postcode":"88367",
    "sg:province":"Baden-W\u00fcrttemberg",
    "wof:name":"Bauunternehmung",
    "wof:placetype":"venue"
},
  "geometry": {"coordinates":[9.3806467056,48.030921936],"type":"Point"}
}