{
  "type": "Feature",
  "properties": {
    "iso:country":"DE",
    "sg:address":"Himmelreichstr. 26",
    "sg:city":"Schopfheim",
    "sg:phone":"+49 7622/669538",
    "sg:postcode":"79650",
    "sg:province":"Baden-W\u00fcrttemberg",
    "wof:name":"Gustav Anhorn",
    "wof:placetype":"venue"
},
  "geometry": {"coordinates":[7.8274860382,47.6494674683],"type":"Point"}
}