{
  "type": "Feature",
  "properties": {
    "iso:country":"DE",
    "sg:address":"Gr\u00f6bziger Str. 10",
    "sg:city":"Gerlebogk",
    "sg:phone":"+49 34691/20959",
    "sg:postcode":"06420",
    "sg:province":"Sachsen-Anhalt",
    "wof:name":"D. Gro\u00dfhans Gmbh",
    "wof:placetype":"venue"
},
  "geometry": {"coordinates":[11.838125,51.704208],"type":"Point"}
}