{
  "type": "Feature",
  "properties": {
    "iso:country":"DE",
    "sg:address":"Am Allerswald 50",
    "sg:city":"Wallenfels",
    "sg:postcode":"96346",
    "sg:province":"Bayern",
    "wof:name":"Schnabrichsm\u00fchle",
    "wof:placetype":"venue"
},
  "geometry": {"coordinates":[11.4662399292,50.2663803101],"type":"Point"}
}