{
  "type": "Feature",
  "properties": {
    "iso:country":"DE",
    "sg:address":"Wittenweierer Str. 43",
    "sg:city":"Schwanau",
    "sg:phone":"+49 7824/2343",
    "sg:postcode":"77963",
    "sg:province":"Baden-W\u00fcrttemberg",
    "wof:name":"Eduard Gschimailo",
    "wof:placetype":"venue"
},
  "geometry": {"coordinates":[7.7601051331,48.3440704346],"type":"Point"}
}