{
  "type": "Feature",
  "properties": {
    "iso:country":"DE",
    "sg:address":"Kapellstr. 24",
    "sg:city":"Donauw\u00f6rth",
    "sg:phone":"+49 906/23938",
    "sg:postcode":"86609",
    "sg:province":"Bayern",
    "wof:name":"Rudolf Ro\u00dfkopf",
    "wof:placetype":"venue"
},
  "geometry": {"coordinates":[10.7822465897,48.7171592712],"type":"Point"}
}