{
  "type": "Feature",
  "properties": {
    "iso:country":"DE",
    "sg:address":"Sch\u00fctzenweg 10",
    "sg:city":"Verden",
    "sg:postcode":"27283",
    "sg:province":"Niedersachsen",
    "wof:name":"Atelier Nordpfeil Gmbh",
    "wof:placetype":"venue"
},
  "geometry": {"coordinates":[9.227917,52.952217],"type":"Point"}
}