{
  "type": "Feature",
  "properties": {
    "iso:country":"DE",
    "sg:address":"Postfach 2125",
    "sg:city":"Rheinstetten",
    "sg:phone":"+49 7242/1314",
    "sg:postcode":"76281",
    "sg:province":"Baden-W\u00fcrttemberg",
    "wof:name":"Willkommen Bei Antikmessen.com",
    "wof:placetype":"venue"
},
  "geometry": {"coordinates":[8.288835,48.960033],"type":"Point"}
}