{
  "type": "Feature",
  "properties": {
    "iso:country":"DE",
    "sg:address":"Hauptstr. 7",
    "sg:city":"Salach",
    "sg:phone":"+49 7162/44550",
    "sg:postcode":"73084",
    "sg:province":"Baden-W\u00fcrttemberg",
    "wof:name":"Presa Strickwarenfabrik Otto Pre\u00dfmar Kg",
    "wof:placetype":"venue"
},
  "geometry": {"coordinates":[9.7341814041,48.6862831116],"type":"Point"}
}