{
  "type": "Feature",
  "properties": {
    "iso:country":"DE",
    "sg:address":"Rennsteig 7 a",
    "sg:city":"Bamberg",
    "sg:phone":"+49 951/42402",
    "sg:postcode":"96052",
    "sg:province":"Bayern",
    "wof:name":"Bernhard Badum Architekt",
    "wof:placetype":"venue"
},
  "geometry": {"coordinates":[10.91199,49.92548],"type":"Point"}
}