{
  "type": "Feature",
  "properties": {
    "iso:country":"DE",
    "sg:address":"Mathlidenstra\u00dfe 30a",
    "sg:city":"L\u00fcdenscheid",
    "sg:phone":"+49 2351/81136",
    "sg:postcode":"58507",
    "sg:province":"Nordrhein-Westfalen",
    "wof:name":"Cvjm Kreisverband L\u00fcdenscheid",
    "wof:placetype":"venue"
},
  "geometry": {"coordinates":[7.62618,51.23053],"type":"Point"}
}