{
  "type": "Feature",
  "properties": {
    "iso:country":"DE",
    "sg:address":"Monschauerstra\u00dfe 44",
    "sg:city":"M\u00f6nchengladbach",
    "sg:phone":"+49 4902/161",
    "sg:postcode":"41068",
    "sg:province":"Nordrhein-Westfalen",
    "wof:name":"Standardvertr\u00e4ge.de",
    "wof:placetype":"venue"
},
  "geometry": {"coordinates":[6.407271,51.188801],"type":"Point"}
}