{
  "type": "Feature",
  "properties": {
    "iso:country":"DE",
    "sg:address":"Loxstedter Str. 3",
    "sg:city":"Schwaan",
    "sg:phone":"+49 3844/813522",
    "sg:postcode":"18258",
    "sg:province":"Mecklenburg-Vorpommern",
    "wof:name":"Karl-heinz Semrau",
    "wof:placetype":"venue"
},
  "geometry": {"coordinates":[12.110832,53.939659],"type":"Point"}
}