{
  "type": "Feature",
  "properties": {
    "iso:country":"DE",
    "sg:address":"Hartmannstr. 31",
    "sg:city":"Kaiserslautern",
    "sg:phone":"+49 631/13834",
    "sg:postcode":"67655",
    "sg:province":"Rheinland-Pfalz",
    "wof:name":"Mock Und Liebl Wasch- Und Pl\u00e4ttanstalt",
    "wof:placetype":"venue"
},
  "geometry": {"coordinates":[7.7587571144,49.4411430359],"type":"Point"}
}