{
  "type": "Feature",
  "properties": {
    "iso:country":"DE",
    "sg:address":"Bahnhofstr. 9",
    "sg:city":"Briesen",
    "sg:phone":"+49 33607/297",
    "sg:postcode":"15518",
    "sg:province":"Brandenburg",
    "wof:name":"Gastst\u00e4tte Und Pension",
    "wof:placetype":"venue"
},
  "geometry": {"coordinates":[14.2775506973,52.3450965881],"type":"Point"}
}