{
  "type": "Feature",
  "properties": {
    "iso:country":"DE",
    "sg:address":"Weberstr. 20",
    "sg:city":"Belm",
    "sg:phone":"+49 5406/676",
    "sg:postcode":"49191",
    "sg:province":"Niedersachsen",
    "wof:name":"M. Piefke",
    "wof:placetype":"venue"
},
  "geometry": {"coordinates":[8.1126203537,52.3033638],"type":"Point"}
}