{
  "type": "Feature",
  "properties": {
    "iso:country":"DE",
    "sg:address":"Hohe Str. 7",
    "sg:city":"Petershagen",
    "sg:phone":"+49 5761/1521",
    "sg:postcode":"32469",
    "sg:province":"Nordrhein-Westfalen",
    "wof:name":"Heinrich N\u00fclle",
    "wof:placetype":"venue"
},
  "geometry": {"coordinates":[9.066981,52.482212],"type":"Point"}
}