{
  "type": "Feature",
  "properties": {
    "iso:country":"DE",
    "sg:address":"Neunecker Str. 38",
    "sg:city":"Glatten",
    "sg:phone":"+49 7443/6433",
    "sg:postcode":"72293",
    "sg:province":"Baden-W\u00fcrttemberg",
    "wof:name":"Psychiatrisches Pflegeheim Seniorenheim",
    "wof:placetype":"venue"
},
  "geometry": {"coordinates":[8.514814,48.439068],"type":"Point"}
}