{
  "type": "Feature",
  "properties": {
    "iso:country":"DE",
    "sg:address":"Ricarda-Huch-Str. 30",
    "sg:city":"Freiburg",
    "sg:phone":"+49 761/86373",
    "sg:postcode":"79114",
    "sg:province":"Baden-W\u00fcrttemberg",
    "wof:name":"A. Barz Ingenieur",
    "wof:placetype":"venue"
},
  "geometry": {"coordinates":[7.8130698204,48.0045547485],"type":"Point"}
}