{
  "type": "Feature",
  "properties": {
    "iso:country":"DE",
    "sg:address":"Gl\u00fcsing 23",
    "sg:city":"Hohenwestedt",
    "sg:phone":"+49 4871/8638",
    "sg:postcode":"24594",
    "sg:province":"Schleswig-Holstein",
    "wof:name":"Klaus Butensch\u00f6n Elektroinstallation",
    "wof:placetype":"venue"
},
  "geometry": {"coordinates":[9.645667,54.080925],"type":"Point"}
}