{
  "type": "Feature",
  "properties": {
    "iso:country":"DE",
    "sg:address":"Sachsentor 38",
    "sg:city":"Hamburg",
    "sg:phone":"+49 40/331972",
    "sg:postcode":"21029",
    "sg:province":"Hamburg",
    "wof:name":"Chempatex Medizinische Vertriebsges. Mbh",
    "wof:placetype":"venue"
},
  "geometry": {"coordinates":[10.2138118744,53.4872055054],"type":"Point"}
}