{
  "type": "Feature",
  "properties": {
    "iso:country":"DE",
    "sg:address":"Schlo\u00dfbergstr. 91",
    "sg:city":"Albstadt",
    "sg:phone":"+49 7431/3369",
    "sg:postcode":"72458",
    "sg:province":"Baden-W\u00fcrttemberg",
    "wof:name":"Hubert Simmert Ingenieur",
    "wof:placetype":"venue"
},
  "geometry": {"coordinates":[9.033162117,48.222618103],"type":"Point"}
}