{
  "type": "Feature",
  "properties": {
    "iso:country":"DE",
    "sg:address":"Berliner Str. 10",
    "sg:city":"Dillenburg",
    "sg:phone":"+49 2771/24114",
    "sg:postcode":"35683",
    "sg:province":"Hessen",
    "wof:name":"Pizzeria Fantasia",
    "wof:placetype":"venue"
},
  "geometry": {"coordinates":[8.2913599014,50.7293891907],"type":"Point"}
}