{
  "type": "Feature",
  "properties": {
    "iso:country":"DE",
    "sg:address":"In der Krause 72",
    "sg:city":"Eschweiler",
    "sg:phone":"+49 2403/66901",
    "sg:postcode":"52249",
    "sg:province":"Nordrhein-Westfalen",
    "wof:name":"G & A Messebau Gmbh",
    "wof:placetype":"venue"
},
  "geometry": {"coordinates":[6.30567,50.828953],"type":"Point"}
}