{
  "type": "Feature",
  "properties": {
    "iso:country":"DE",
    "sg:address":"Kirchstr. 9",
    "sg:city":"Bassum",
    "sg:phone":"+49 4241/2646",
    "sg:postcode":"27211",
    "sg:province":"Niedersachsen",
    "wof:name":"Otto B\u00f6ning",
    "wof:placetype":"venue"
},
  "geometry": {"coordinates":[8.726659,52.845524],"type":"Point"}
}