{
  "type": "Feature",
  "properties": {
    "iso:country":"DE",
    "sg:address":"Sulgauer Str. 24",
    "sg:city":"Schramberg",
    "sg:phone":"+49 7422/8305",
    "sg:postcode":"78713",
    "sg:province":"Baden-W\u00fcrttemberg",
    "wof:name":"Fader",
    "wof:placetype":"venue"
},
  "geometry": {"coordinates":[8.420641,48.225754],"type":"Point"}
}