{
  "type": "Feature",
  "properties": {
    "iso:country":"DE",
    "sg:address":"In den Bergen 17",
    "sg:city":"D\u00f6tlingen",
    "sg:phone":"+49 4433/1449",
    "sg:postcode":"27801",
    "sg:province":"Niedersachsen",
    "wof:name":"Uwe Buchholz Ingenieur",
    "wof:placetype":"venue"
},
  "geometry": {"coordinates":[8.42370224,52.9407310486],"type":"Point"}
}