{
  "type": "Feature",
  "properties": {
    "iso:country":"DE",
    "sg:address":"Brehmstr. 36",
    "sg:city":"D\u00fcsseldorf",
    "sg:phone":"+49 211/614551",
    "sg:postcode":"40239",
    "sg:province":"Nordrhein-Westfalen",
    "wof:name":"K. Sambaliotis",
    "wof:placetype":"venue"
},
  "geometry": {"coordinates":[6.8014960289,51.2437438965],"type":"Point"}
}