{
  "type": "Feature",
  "properties": {
    "iso:country":"DE",
    "sg:address":"Lindenstr. 112",
    "sg:city":"Wellmitz",
    "sg:phone":"+49 33652/6077",
    "sg:postcode":"15898",
    "sg:province":"Brandenburg",
    "wof:name":"Schlaube Agroservice Gmbh",
    "wof:placetype":"venue"
},
  "geometry": {"coordinates":[14.709827,52.065765],"type":"Point"}
}