{
  "type": "Feature",
  "properties": {
    "iso:country":"DE",
    "sg:address":"Graf-Bentzel-Str. 65",
    "sg:city":"Rottenburg",
    "sg:phone":"+49 7472/98020",
    "sg:postcode":"72108",
    "sg:province":"Baden-W\u00fcrttemberg",
    "wof:name":"Karosserie - Baur",
    "wof:placetype":"venue"
},
  "geometry": {"coordinates":[8.950461,48.477158],"type":"Point"}
}