{
  "type": "Feature",
  "properties": {
    "iso:country":"DE",
    "sg:address":"Perlschneiderstr. 39",
    "sg:city":"M\u00fcnchen",
    "sg:phone":"+49 89/8344978",
    "sg:postcode":"81241",
    "sg:province":"Bayern",
    "wof:name":"Frederiksen Und Weise",
    "wof:placetype":"venue"
},
  "geometry": {"coordinates":[11.4653482437,48.1366958618],"type":"Point"}
}