{
  "type": "Feature",
  "properties": {
    "iso:country":"DE",
    "sg:address":"Fritz-P\u00fctter-Str. 41",
    "sg:city":"M\u00fcnster",
    "sg:phone":"+49 251/7801772",
    "sg:postcode":"48153",
    "sg:province":"Nordrhein-Westfalen",
    "wof:name":"Andreas Krieg",
    "wof:placetype":"venue"
},
  "geometry": {"coordinates":[7.6270070076,51.9349899292],"type":"Point"}
}