{
  "type": "Feature",
  "properties": {
    "iso:country":"DE",
    "sg:address":"Burgweg 45",
    "sg:city":"Hagen",
    "sg:phone":"+49 2334/441279",
    "sg:postcode":"58119",
    "sg:province":"Nordrhein-Westfalen",
    "wof:name":"Marmor Und Fliesen Ademaj Gmbh",
    "wof:placetype":"venue"
},
  "geometry": {"coordinates":[7.5687308311,51.3553733826],"type":"Point"}
}