{
  "type": "Feature",
  "properties": {
    "iso:country":"DE",
    "sg:address":"Kehdenstr. 1",
    "sg:city":"Kiel",
    "sg:phone":"+49 431/675501",
    "sg:postcode":"24103",
    "sg:province":"Schleswig-Holstein",
    "wof:name":"Pizza World System- Vertriebs Gmbh",
    "wof:placetype":"venue"
},
  "geometry": {"coordinates":[10.1383037567,54.3232383728],"type":"Point"}
}