{
  "type": "Feature",
  "properties": {
    "iso:country":"DE",
    "sg:address":"Harburger Str. 4",
    "sg:city":"Jesteburg",
    "sg:postcode":"21266",
    "sg:province":"Niedersachsen",
    "wof:name":"Rudi Gmbh",
    "wof:placetype":"venue"
},
  "geometry": {"coordinates":[9.963677,53.311447],"type":"Point"}
}