{
  "type": "Feature",
  "properties": {
    "iso:country":"DE",
    "sg:address":"Karlstr. 10",
    "sg:city":"Bad Nauheim",
    "sg:phone":"+49 6032/5279",
    "sg:postcode":"61231",
    "sg:province":"Hessen",
    "wof:name":"Postwagen",
    "wof:placetype":"venue"
},
  "geometry": {"coordinates":[8.7395763397,50.3647537231],"type":"Point"}
}