{
  "type": "Feature",
  "properties": {
    "iso:country":"DE",
    "sg:address":"Seidenst\u00fcckerweg 2",
    "sg:city":"Soest",
    "sg:phone":"+49 2921/7050",
    "sg:postcode":"59494",
    "sg:province":"Nordrhein-Westfalen",
    "wof:name":"Holz-schnettler Soest Import-export Gmbh",
    "wof:placetype":"venue"
},
  "geometry": {"coordinates":[8.1336317062,51.5580863953],"type":"Point"}
}