{
  "type": "Feature",
  "properties": {
    "iso:country":"DE",
    "sg:address":"Taunusstr. 100",
    "sg:city":"Gro\u00df-Gerau",
    "sg:postcode":"64521",
    "sg:province":"Hessen",
    "wof:name":"Hessenwasser Gmbh",
    "wof:placetype":"venue"
},
  "geometry": {"coordinates":[8.4743900299,49.8786888123],"type":"Point"}
}