{
  "type": "Feature",
  "properties": {
    "iso:country":"DE",
    "sg:address":"Halverder Str. 23",
    "sg:city":"Recke",
    "sg:phone":"+49 4954/537560",
    "sg:postcode":"49509",
    "sg:province":"Nordrhein-Westfalen",
    "wof:name":"Beckemeier Handels Gmbh",
    "wof:placetype":"venue"
},
  "geometry": {"coordinates":[7.7046570778,52.3847503662],"type":"Point"}
}