{
  "type": "Feature",
  "properties": {
    "iso:country":"DE",
    "sg:address":"Windelsbleicher Str. 15",
    "sg:city":"Bielefeld",
    "sg:phone":"+49 521/442022",
    "sg:postcode":"33647",
    "sg:province":"Nordrhein-Westfalen",
    "wof:name":"Dortschy Verwaltungs Gmbh",
    "wof:placetype":"venue"
},
  "geometry": {"coordinates":[8.5178375244,51.9845085144],"type":"Point"}
}