{
  "type": "Feature",
  "properties": {
    "iso:country":"DE",
    "sg:address":"Z\u00e4hringerplatz 34",
    "sg:city":"Konstanz",
    "sg:phone":"+49 7531/65398",
    "sg:postcode":"78464",
    "sg:province":"Baden-W\u00fcrttemberg",
    "wof:name":"Caprice",
    "wof:placetype":"venue"
},
  "geometry": {"coordinates":[9.1839418411,47.6735458374],"type":"Point"}
}