{
  "type": "Feature",
  "properties": {
    "iso:country":"DE",
    "sg:address":"Freiheitstr. 81",
    "sg:city":"Remscheid",
    "sg:phone":"+49 2191/927391",
    "sg:postcode":"42853",
    "sg:province":"Nordrhein-Westfalen",
    "wof:name":"Horst D\u00f6rschler",
    "wof:placetype":"venue"
},
  "geometry": {"coordinates":[7.1911997795,51.1774597168],"type":"Point"}
}