{
  "type": "Feature",
  "properties": {
    "iso:country":"DE",
    "sg:address":"Berliner Str. 15",
    "sg:city":"Bremen",
    "sg:postcode":"28203",
    "sg:province":"Bremen",
    "wof:name":"Verein F\u00fcr Friedens-und Ent- Wicklungsp\u00e4dagogische \u00f6ffentl.",
    "wof:placetype":"venue"
},
  "geometry": {"coordinates":[8.8282985687,53.0710411072],"type":"Point"}
}