{
  "type": "Feature",
  "properties": {
    "iso:country":"DE",
    "sg:address":"Ahornweg 6",
    "sg:city":"Krauthausen",
    "sg:phone":"+49 3691/629090",
    "sg:postcode":"99819",
    "sg:province":"Th\u00fcringen",
    "wof:name":"Uniwork Gmbh & Co Kg",
    "wof:placetype":"venue"
},
  "geometry": {"coordinates":[10.24758,51.012257],"type":"Point"}
}