{
  "type": "Feature",
  "properties": {
    "iso:country":"DE",
    "sg:address":"Frohmestr. 75",
    "sg:city":"Hamburg",
    "sg:phone":"+49 40/5592838",
    "sg:postcode":"22459",
    "sg:province":"Hamburg",
    "wof:name":"Bobs Music Inh. Robert Hertwig",
    "wof:placetype":"venue"
},
  "geometry": {"coordinates":[9.9252681732,53.6311073303],"type":"Point"}
}