{
  "type": "Feature",
  "properties": {
    "iso:country":"DE",
    "sg:address":"Arolser Str. 1a",
    "sg:city":"V\u00f6hl",
    "sg:phone":"+49 5635/227",
    "sg:postcode":"34516",
    "sg:province":"Hessen",
    "wof:name":"Karl Schneider",
    "wof:placetype":"venue"
},
  "geometry": {"coordinates":[8.9438791275,51.2056045532],"type":"Point"}
}