{
  "type": "Feature",
  "properties": {
    "iso:country":"DE",
    "sg:address":"Arnsberger Str. 12",
    "sg:city":"Berlin",
    "sg:phone":"+49 30/5143834",
    "sg:postcode":"12683",
    "sg:province":"Berlin",
    "wof:name":"Barbara Meyer",
    "wof:placetype":"venue"
},
  "geometry": {"coordinates":[13.5526437759,52.4991188049],"type":"Point"}
}