{
  "type": "Feature",
  "properties": {
    "iso:country":"DE",
    "sg:address":"Im Willenbungert 8",
    "sg:city":"Kinheim",
    "sg:phone":"+49 6532/94040",
    "sg:postcode":"54538",
    "sg:province":"Rheinland-Pfalz",
    "wof:name":"H. Zehnpfund",
    "wof:placetype":"venue"
},
  "geometry": {"coordinates":[7.0524530411,49.9694480896],"type":"Point"}
}