{
  "type": "Feature",
  "properties": {
    "iso:country":"DE",
    "sg:address":"Klammstr. 19",
    "sg:city":"Garmisch-Partenkirchen",
    "sg:phone":"+49 8821/9010",
    "sg:postcode":"82467",
    "sg:province":"Bayern",
    "wof:name":"Hotel Zugspitz Gmbh",
    "wof:placetype":"venue"
},
  "geometry": {"coordinates":[11.0906457901,47.4917030334],"type":"Point"}
}