{
  "type": "Feature",
  "properties": {
    "iso:country":"DE",
    "sg:address":"Pirmasenser Str. 8",
    "sg:city":"Stuttgart",
    "sg:phone":"+49 711/882133",
    "sg:postcode":"70499",
    "sg:province":"Baden-W\u00fcrttemberg",
    "wof:name":"Kath. Pfarramt St. Theresia Vom Kinde Jesu",
    "wof:placetype":"venue"
},
  "geometry": {"coordinates":[9.1154308319,48.8114509583],"type":"Point"}
}