{
  "type": "Feature",
  "properties": {
    "iso:country":"DE",
    "sg:address":"Raiffeisenstr 2",
    "sg:city":"Rodgau",
    "sg:phone":"+49 6106/283703",
    "sg:postcode":"63110",
    "sg:province":"Hessen",
    "wof:name":"Objectsource Software Gmbh",
    "wof:placetype":"venue"
},
  "geometry": {"coordinates":[8.884677887,50.0129928589],"type":"Point"}
}