{
  "type": "Feature",
  "properties": {
    "iso:country":"DE",
    "sg:address":"Postfach 120 142",
    "sg:city":"Euskirchen",
    "sg:phone":"+49 2232/942008",
    "sg:postcode":"53874",
    "sg:province":"Nordrhein-Westfalen",
    "wof:name":"Firmensitz.de",
    "wof:placetype":"venue"
},
  "geometry": {"coordinates":[6.7862901688,50.6621055603],"type":"Point"}
}