{
  "type": "Feature",
  "properties": {
    "iso:country":"DE",
    "sg:address":"Elballee 44",
    "sg:city":"Dessau",
    "sg:phone":"+49 340/611360",
    "sg:postcode":"06846",
    "sg:province":"Sachsen-Anhalt",
    "wof:name":"Thormann",
    "wof:placetype":"venue"
},
  "geometry": {"coordinates":[12.214805,51.848289],"type":"Point"}
}