{
  "type": "Feature",
  "properties": {
    "iso:country":"DE",
    "sg:address":"Am Markt 2",
    "sg:city":"Lauenau",
    "sg:phone":"+49 5043/3298",
    "sg:postcode":"31867",
    "sg:province":"Niedersachsen",
    "wof:name":"A. Lehmann",
    "wof:placetype":"venue"
},
  "geometry": {"coordinates":[9.3698549271,52.2739067078],"type":"Point"}
}