{
  "type": "Feature",
  "properties": {
    "iso:country":"DE",
    "sg:address":"Hermann-L\u00f6ns-Str. 53",
    "sg:city":"Hermannsburg",
    "sg:phone":"+49 5052/978559",
    "sg:postcode":"29320",
    "sg:province":"Niedersachsen",
    "wof:name":"Telepassport-service-center",
    "wof:placetype":"venue"
},
  "geometry": {"coordinates":[10.0916109085,52.8454627991],"type":"Point"}
}