{
  "type": "Feature",
  "properties": {
    "iso:country":"DE",
    "sg:address":"Rhan 9",
    "sg:city":"Sch\u00f6nthal",
    "sg:postcode":"93488",
    "sg:province":"Bayern",
    "wof:name":"Rhanerbr\u00e4u Verwaltungs-gmbh",
    "wof:placetype":"venue"
},
  "geometry": {"coordinates":[12.6172637939,49.3361129761],"type":"Point"}
}