{
  "type": "Feature",
  "properties": {
    "iso:country":"DE",
    "sg:address":"Schlo\u00dfstr. 99",
    "sg:city":"M\u00f6nchengladbach",
    "sg:phone":"+49 2166/249232",
    "sg:postcode":"41238",
    "sg:province":"Nordrhein-Westfalen",
    "wof:name":"R. Heilmann",
    "wof:placetype":"venue"
},
  "geometry": {"coordinates":[6.460865,51.172512],"type":"Point"}
}