{
  "type": "Feature",
  "properties": {
    "iso:country":"DE",
    "sg:address":"Raboisen 16",
    "sg:city":"Hamburg",
    "sg:phone":"+49 40/373238",
    "sg:postcode":"20095",
    "sg:province":"Hamburg",
    "wof:name":"Spedition Freitan Freight Transport Agency",
    "wof:placetype":"venue"
},
  "geometry": {"coordinates":[10.001209259,53.5540084839],"type":"Point"}
}