{
  "type": "Feature",
  "properties": {
    "iso:country":"DE",
    "sg:address":"Burgdorfer Berg 2",
    "sg:city":"Uetze",
    "sg:phone":"+49 5147/436",
    "sg:postcode":"31311",
    "sg:province":"Niedersachsen",
    "wof:name":"H. K\u00f6hne",
    "wof:placetype":"venue"
},
  "geometry": {"coordinates":[10.0871982574,52.4814376831],"type":"Point"}
}