{
  "type": "Feature",
  "properties": {
    "iso:country":"DE",
    "sg:address":"Katharinenstr. 26",
    "sg:city":"Dinslaken",
    "sg:phone":"+49 2064/30463",
    "sg:postcode":"46537",
    "sg:province":"Nordrhein-Westfalen",
    "wof:name":"Thomas Schneider",
    "wof:placetype":"venue"
},
  "geometry": {"coordinates":[6.7401900291,51.5762786865],"type":"Point"}
}