{
  "type": "Feature",
  "properties": {
    "iso:country":"DE",
    "sg:address":"Kap-Horn-Str. 2",
    "sg:city":"Bremen",
    "sg:phone":"+49 421/61040",
    "sg:postcode":"28237",
    "sg:province":"Bremen",
    "wof:name":"Kl\u00f6ckner Stahlhandel Zn Bremen Der Kl\u00f6ckner",
    "wof:placetype":"venue"
},
  "geometry": {"coordinates":[8.748661,53.116005],"type":"Point"}
}