{
  "type": "Feature",
  "properties": {
    "iso:country":"DE",
    "sg:address":"Wellingsb\u00fcttler Weg 115",
    "sg:city":"Hamburg",
    "sg:phone":"+49 40/5361372",
    "sg:postcode":"22391",
    "sg:province":"Hamburg",
    "wof:name":"Alte Apotheke Wellingsb\u00fcttel",
    "wof:placetype":"venue"
},
  "geometry": {"coordinates":[10.079957,53.641293],"type":"Point"}
}