{
  "type": "Feature",
  "properties": {
    "iso:country":"DE",
    "sg:address":"M\u00fcnsterstr. 31",
    "sg:city":"Steinfurt",
    "sg:phone":"+49 2552/2289",
    "sg:postcode":"48565",
    "sg:province":"Nordrhein-Westfalen",
    "wof:name":"Magdalena Betting",
    "wof:placetype":"venue"
},
  "geometry": {"coordinates":[7.394315,52.124012],"type":"Point"}
}