{
  "type": "Feature",
  "properties": {
    "iso:country":"DE",
    "sg:address":"Hauptstr. 49",
    "sg:city":"Remagen",
    "sg:phone":"+49 2642/24188",
    "sg:postcode":"53424",
    "sg:province":"Rheinland-Pfalz",
    "wof:name":"Volksbank Remagen Egmbh",
    "wof:placetype":"venue"
},
  "geometry": {"coordinates":[7.207514,50.613251],"type":"Point"}
}