{
  "type": "Feature",
  "properties": {
    "iso:country":"DE",
    "sg:address":"Lilienweg 10",
    "sg:city":"Wendelstein",
    "sg:phone":"+49 9129/9211",
    "sg:postcode":"90530",
    "sg:province":"Bayern",
    "wof:name":"G\u00fcnter H\u00f6sch Dipl.-ing.",
    "wof:placetype":"venue"
},
  "geometry": {"coordinates":[11.1431007385,49.3490104675],"type":"Point"}
}