{
  "type": "Feature",
  "properties": {
    "iso:country":"DE",
    "sg:address":"Hauptstr. 11",
    "sg:city":"Braunsbedra",
    "sg:phone":"+49 34633/20478",
    "sg:postcode":"06242",
    "sg:province":"Sachsen-Anhalt",
    "wof:name":"Klaus Burbeck",
    "wof:placetype":"venue"
},
  "geometry": {"coordinates":[11.9027414322,51.286895752],"type":"Point"}
}