{
  "type": "Feature",
  "properties": {
    "iso:country":"DE",
    "sg:address":"Geschwister-Scholl-Str. 15",
    "sg:city":"Witzenhausen",
    "sg:phone":"+49 5542/93480",
    "sg:postcode":"37213",
    "sg:province":"Hessen",
    "wof:name":"Walter Witzel Steuerberater",
    "wof:placetype":"venue"
},
  "geometry": {"coordinates":[9.8698797226,51.3407363892],"type":"Point"}
}