{
  "type": "Feature",
  "properties": {
    "iso:country":"DE",
    "sg:address":"Wendenstr. 435",
    "sg:city":"Hamburg",
    "sg:postcode":"20537",
    "sg:province":"Hamburg",
    "wof:name":"Kosmo Vermittlungsges. Mbh",
    "wof:placetype":"venue"
},
  "geometry": {"coordinates":[10.0520963669,53.5503044128],"type":"Point"}
}