{
  "type": "Feature",
  "properties": {
    "iso:country":"DE",
    "sg:address":"Schulstr. 37",
    "sg:city":"Oelsnitz",
    "sg:phone":"+49 37296/2620",
    "sg:postcode":"09376",
    "sg:province":"Sachsen",
    "wof:name":"K. Weigel",
    "wof:placetype":"venue"
},
  "geometry": {"coordinates":[12.7014,50.72168],"type":"Point"}
}