{
  "type": "Feature",
  "properties": {
    "iso:country":"DE",
    "sg:address":"Am Schmiedlacker 36 c",
    "sg:city":"Landshut",
    "sg:phone":"+49 871/44718",
    "sg:postcode":"84028",
    "sg:province":"Bayern",
    "wof:name":"H. Heckmann Ingenieur",
    "wof:placetype":"venue"
},
  "geometry": {"coordinates":[12.1799764633,48.5418052673],"type":"Point"}
}