{
  "type": "Feature",
  "properties": {
    "iso:country":"DE",
    "sg:address":"L\u00fctkerlinde 12",
    "sg:city":"Brakel",
    "sg:postcode":"33034",
    "sg:province":"Nordrhein-Westfalen",
    "wof:name":"Al Eins Metallhandel Gmbh",
    "wof:placetype":"venue"
},
  "geometry": {"coordinates":[9.192355,51.72477],"type":"Point"}
}