{
  "type": "Feature",
  "properties": {
    "iso:country":"DE",
    "sg:address":"Aloysiusstr. 81-83",
    "sg:city":"Rheine",
    "sg:phone":"+49 5971/8660",
    "sg:postcode":"48429",
    "sg:province":"Nordrhein-Westfalen",
    "wof:name":"Altenwohnanlage Marienstift",
    "wof:placetype":"venue"
},
  "geometry": {"coordinates":[7.465362,52.279713],"type":"Point"}
}