{
  "type": "Feature",
  "properties": {
    "iso:country":"DE",
    "sg:address":"Lange Str. 6",
    "sg:city":"Sulingen",
    "sg:phone":"+49 4271/860",
    "sg:postcode":"27232",
    "sg:province":"Niedersachsen",
    "wof:name":"Sparkasse",
    "wof:placetype":"venue"
},
  "geometry": {"coordinates":[8.811166,52.682884],"type":"Point"}
}