{
  "type": "Feature",
  "properties": {
    "iso:country":"DE",
    "sg:address":"Selbitzer Weg 6",
    "sg:city":"Selbitz",
    "sg:phone":"+49 9282/8050",
    "sg:postcode":"95152",
    "sg:province":"Bayern",
    "wof:name":"Gerhard Singer",
    "wof:placetype":"venue"
},
  "geometry": {"coordinates":[11.74154,50.33527],"type":"Point"}
}