{
  "type": "Feature",
  "properties": {
    "iso:country":"DE",
    "sg:address":"Oberh\u00fctzer Str. 22-24",
    "sg:city":"Remscheid",
    "sg:phone":"+49 2191/98850",
    "sg:postcode":"42857",
    "sg:province":"Nordrhein-Westfalen",
    "wof:name":"Winterhoff Beteligungs- Und Verwaltungs-gmbh",
    "wof:placetype":"venue"
},
  "geometry": {"coordinates":[7.1610879898,51.1913604736],"type":"Point"}
}