{
  "type": "Feature",
  "properties": {
    "iso:country":"DE",
    "sg:address":"Carstennstr. 25 g",
    "sg:city":"Berlin",
    "sg:phone":"+49 30/8177042",
    "sg:postcode":"12205",
    "sg:province":"Berlin",
    "wof:name":"Heinz E. Hoffmann Architekt",
    "wof:placetype":"venue"
},
  "geometry": {"coordinates":[13.29659,52.431938],"type":"Point"}
}