{
  "type": "Feature",
  "properties": {
    "iso:country":"DE",
    "sg:address":"Gartenstr. 15a",
    "sg:city":"Nettetal",
    "sg:phone":"+49 2157/4275",
    "sg:postcode":"41334",
    "sg:province":"Nordrhein-Westfalen",
    "wof:name":"Heinz Simonett",
    "wof:placetype":"venue"
},
  "geometry": {"coordinates":[6.1952280998,51.3196678162],"type":"Point"}
}