{
  "type": "Feature",
  "properties": {
    "iso:country":"DE",
    "sg:address":"Barbarastr. 79",
    "sg:city":"Dorsten",
    "sg:postcode":"46282",
    "sg:province":"Nordrhein-Westfalen",
    "wof:name":"B\u00f6cker & Klas-hagemann Gmbh",
    "wof:placetype":"venue"
},
  "geometry": {"coordinates":[6.979976,51.649956],"type":"Point"}
}