{
  "type": "Feature",
  "properties": {
    "iso:country":"DE",
    "sg:address":"Hauserbachstr. 57",
    "sg:city":"Mechernich",
    "sg:phone":"+49 2484/1630",
    "sg:postcode":"53894",
    "sg:province":"Nordrhein-Westfalen",
    "wof:name":"Anneliese Hochg\u00fcrtel",
    "wof:placetype":"venue"
},
  "geometry": {"coordinates":[6.65525,50.559368],"type":"Point"}
}