{
  "type": "Feature",
  "properties": {
    "iso:country":"DE",
    "sg:address":"Neuer Weg 70",
    "sg:city":"Rhauderfehn",
    "sg:phone":"+49 4952/2801",
    "sg:postcode":"26817",
    "sg:province":"Niedersachsen",
    "wof:name":"Friedrich Strenge",
    "wof:placetype":"venue"
},
  "geometry": {"coordinates":[7.57893,53.146061],"type":"Point"}
}