{
  "type": "Feature",
  "properties": {
    "iso:country":"DE",
    "sg:address":"Hindenburgstr. 109",
    "sg:city":"M\u00f6nchengladbach",
    "sg:phone":"+49 2161/26077",
    "sg:postcode":"41061",
    "sg:province":"Nordrhein-Westfalen",
    "wof:name":"Porzellan Tegel\u00e4rs Kg",
    "wof:placetype":"venue"
},
  "geometry": {"coordinates":[6.4395151138,51.1945724487],"type":"Point"}
}