{
  "type": "Feature",
  "properties": {
    "iso:country":"DE",
    "sg:address":"Marburger Str. 2",
    "sg:city":"Darmstadt",
    "sg:phone":"+49 6151/177690",
    "sg:postcode":"64289",
    "sg:province":"Hessen",
    "wof:name":"Emb Ag",
    "wof:placetype":"venue"
},
  "geometry": {"coordinates":[8.6534757614,49.8874816895],"type":"Point"}
}