{
  "type": "Feature",
  "properties": {
    "iso:country":"DE",
    "sg:address":"Bernhard-Schwentner-Str. 16",
    "sg:city":"Schwerin",
    "sg:phone":"+49 385/3975017",
    "sg:postcode":"19061",
    "sg:province":"Mecklenburg-Vorpommern",
    "wof:name":"Schwimmhalle Schwerin",
    "wof:placetype":"venue"
},
  "geometry": {"coordinates":[11.4379463196,53.6034317017],"type":"Point"}
}