{
  "type": "Feature",
  "properties": {
    "iso:country":"DE",
    "sg:address":"Bei der Wette 8",
    "sg:city":"Obersulm",
    "sg:phone":"+49 7130/6448",
    "sg:postcode":"74182",
    "sg:province":"Baden-W\u00fcrttemberg",
    "wof:name":"Ev. Pfarramt Eschenau",
    "wof:placetype":"venue"
},
  "geometry": {"coordinates":[9.4024839401,49.1367492676],"type":"Point"}
}