{
  "type": "Feature",
  "properties": {
    "iso:country":"DE",
    "sg:address":"Sandh\u00f6rn 34",
    "sg:city":"Hollern-Twielenfleth",
    "sg:postcode":"21723",
    "sg:province":"Niedersachsen",
    "wof:name":"Evant Entertainment Gmbh",
    "wof:placetype":"venue"
},
  "geometry": {"coordinates":[9.5700006485,53.5928153992],"type":"Point"}
}