{
  "type": "Feature",
  "properties": {
    "iso:country":"DE",
    "sg:address":"Wei\u00dfer Acker 1",
    "sg:city":"Edemissen",
    "sg:phone":"+49 5372/5336",
    "sg:postcode":"31234",
    "sg:province":"Niedersachsen",
    "wof:name":"Haus Am Schaperberg Alten- Und Pflegeheim Gmbh",
    "wof:placetype":"venue"
},
  "geometry": {"coordinates":[10.285368,52.439819],"type":"Point"}
}