{
  "type": "Feature",
  "properties": {
    "iso:country":"DE",
    "sg:address":"Hauptstr. 4",
    "sg:city":"Oppenau",
    "sg:phone":"+49 7804/633",
    "sg:postcode":"77728",
    "sg:province":"Baden-W\u00fcrttemberg",
    "wof:name":"Emil Maier",
    "wof:placetype":"venue"
},
  "geometry": {"coordinates":[8.170095,48.477474],"type":"Point"}
}