{
  "type": "Feature",
  "properties": {
    "iso:country":"DE",
    "sg:address":"Isarstr 23",
    "sg:city":"Wallgau",
    "sg:phone":"+49 8825/2145",
    "sg:postcode":"82499",
    "sg:province":"Bayern",
    "wof:name":"Neumayr Fwt Ing.-b\u00fcro",
    "wof:placetype":"venue"
},
  "geometry": {"coordinates":[11.29009,47.519241],"type":"Point"}
}