{
  "type": "Feature",
  "properties": {
    "iso:country":"DE",
    "sg:address":"Robert-Koch-Str. 5",
    "sg:city":"Grafschaft",
    "sg:phone":"+49 2225/92380",
    "sg:postcode":"53501",
    "sg:province":"Rheinland-Pfalz",
    "wof:name":"Patrizia Wein- Und Spirituosen Gmbh",
    "wof:placetype":"venue"
},
  "geometry": {"coordinates":[7.0319881439,50.5671920776],"type":"Point"}
}