{
  "type": "Feature",
  "properties": {
    "iso:country":"DE",
    "sg:address":"Sch\u00f6ntaler Weg 24",
    "sg:city":"Neuenrade",
    "sg:phone":"+49 2392/69070",
    "sg:postcode":"58809",
    "sg:province":"Nordrhein-Westfalen",
    "wof:name":"Sauerland Kunststoff Granulate Verm\u00f6gensverwaltung Gmbh",
    "wof:placetype":"venue"
},
  "geometry": {"coordinates":[7.8032970428,51.2879257202],"type":"Point"}
}