{
  "type": "Feature",
  "properties": {
    "iso:country":"DE",
    "sg:address":"Huyssenallee 16",
    "sg:city":"Essen",
    "sg:phone":"+49 201/239153",
    "sg:postcode":"45128",
    "sg:province":"Nordrhein-Westfalen",
    "wof:name":"R\u00fcdiger Abramczik Und Helmut Kremers",
    "wof:placetype":"venue"
},
  "geometry": {"coordinates":[7.011103,51.449001],"type":"Point"}
}