{
  "type": "Feature",
  "properties": {
    "iso:country":"DE",
    "sg:address":"J\u00e4gersteig 4",
    "sg:city":"Kallm\u00fcnz",
    "sg:phone":"+49 9473/278",
    "sg:postcode":"93183",
    "sg:province":"Bayern",
    "wof:name":"Andreas Daxl",
    "wof:placetype":"venue"
},
  "geometry": {"coordinates":[11.959225,49.161903],"type":"Point"}
}