{
  "type": "Feature",
  "properties": {
    "iso:country":"DE",
    "sg:city":"Kleinschmalkalden",
    "sg:postcode":"98593",
    "sg:province":"Th\u00fcringen",
    "wof:name":"G. Wagner",
    "wof:placetype":"venue"
},
  "geometry": {"coordinates":[10.475205,50.796509],"type":"Point"}
}