{
  "type": "Feature",
  "properties": {
    "iso:country":"DE",
    "sg:address":"Alte Renninger Str. 25",
    "sg:city":"Weil der Stadt",
    "sg:phone":"+49 7033/7313",
    "sg:postcode":"71263",
    "sg:province":"Baden-W\u00fcrttemberg",
    "wof:name":"Isolde Eisele-colombo Masseurin",
    "wof:placetype":"venue"
},
  "geometry": {"coordinates":[8.878996,48.753452],"type":"Point"}
}