{
  "type": "Feature",
  "properties": {
    "iso:country":"DE",
    "sg:address":"Dorfstr. 41",
    "sg:city":"Weimar",
    "sg:phone":"+49 3643/418072",
    "sg:postcode":"99427",
    "sg:province":"Th\u00fcringen",
    "wof:name":"Monika Freitag",
    "wof:placetype":"venue"
},
  "geometry": {"coordinates":[11.3532924652,51.0149459839],"type":"Point"}
}