{
  "type": "Feature",
  "properties": {
    "iso:country":"DE",
    "sg:address":"Hopfenhorst",
    "sg:city":"Mieste",
    "sg:phone":"+49 39082/263",
    "sg:postcode":"39649",
    "sg:province":"Sachsen-Anhalt",
    "wof:name":"Tankstelle-minol",
    "wof:placetype":"venue"
},
  "geometry": {"coordinates":[11.1981658936,52.4584503174],"type":"Point"}
}