{
  "type": "Feature",
  "properties": {
    "iso:country":"DE",
    "sg:address":"Emmastr. 270",
    "sg:city":"Bremen",
    "sg:phone":"+49 421/2238070",
    "sg:postcode":"28213",
    "sg:province":"Bremen",
    "wof:name":"Volbert Serviceruf",
    "wof:placetype":"venue"
},
  "geometry": {"coordinates":[8.850183,53.0877],"type":"Point"}
}