{
  "type": "Feature",
  "properties": {
    "iso:country":"DE",
    "sg:address":"Mitscherlichstr. 19",
    "sg:city":"Wilhelmshaven",
    "sg:phone":"+49 4421/12954",
    "sg:postcode":"26382",
    "sg:province":"Niedersachsen",
    "wof:name":"Regina Wallner-rohbeck",
    "wof:placetype":"venue"
},
  "geometry": {"coordinates":[8.108109,53.523613],"type":"Point"}
}