{
  "type": "Feature",
  "properties": {
    "iso:country":"DE",
    "sg:address":"Speyerer Str. 1",
    "sg:city":"Heidelberg",
    "sg:phone":"+49 6221/184310",
    "sg:postcode":"69115",
    "sg:province":"Baden-W\u00fcrttemberg",
    "wof:name":"Mandys Fast Food",
    "wof:placetype":"venue"
},
  "geometry": {"coordinates":[8.6781311035,49.4001426697],"type":"Point"}
}