{
  "type": "Feature",
  "properties": {
    "iso:country":"DE",
    "sg:address":"Staustr. 6",
    "sg:city":"Oldenburg",
    "sg:phone":"+49 441/13472",
    "sg:postcode":"26122",
    "sg:province":"Niedersachsen",
    "wof:name":"Pfaff N\u00e4hzentrum Hutta",
    "wof:placetype":"venue"
},
  "geometry": {"coordinates":[8.2171030045,53.1407585144],"type":"Point"}
}