{
  "type": "Feature",
  "properties": {
    "iso:country":"DE",
    "sg:address":"Vogtsgarten 63",
    "sg:city":"M\u00f6nchengladbach",
    "sg:phone":"+49 2161/580470",
    "sg:postcode":"41179",
    "sg:province":"Nordrhein-Westfalen",
    "wof:name":"Norbert Willimzik Industrievertretungen",
    "wof:placetype":"venue"
},
  "geometry": {"coordinates":[6.3632569313,51.1531143188],"type":"Point"}
}