{
  "type": "Feature",
  "properties": {
    "iso:country":"DE",
    "sg:address":"Carl-Benz-Str. 6",
    "sg:city":"Forst",
    "sg:postcode":"76694",
    "sg:province":"Baden-W\u00fcrttemberg",
    "wof:name":"Delta Inkasso Gmbh",
    "wof:placetype":"venue"
},
  "geometry": {"coordinates":[8.5719165802,49.1559715271],"type":"Point"}
}