{
  "type": "Feature",
  "properties": {
    "iso:country":"DE",
    "sg:address":"Hattinger Str. 77",
    "sg:city":"Bochum",
    "sg:phone":"+49 234/313508",
    "sg:postcode":"44789",
    "sg:province":"Nordrhein-Westfalen",
    "wof:name":"Apotheke Am Bergmannsheil",
    "wof:placetype":"venue"
},
  "geometry": {"coordinates":[7.211035,51.470436],"type":"Point"}
}