{
  "type": "Feature",
  "properties": {
    "iso:country":"DE",
    "sg:address":"Hundebrinkstr. 10",
    "sg:city":"Essen",
    "sg:postcode":"45326",
    "sg:province":"Nordrhein-Westfalen",
    "wof:name":"Bussick Verwaltungs Gmbh",
    "wof:placetype":"venue"
},
  "geometry": {"coordinates":[7.016361,51.476303],"type":"Point"}
}