{
  "type": "Feature",
  "properties": {
    "iso:country":"DE",
    "sg:address":"Wilhelm-Schussen-Str. 3",
    "sg:city":"Bad Schussenried",
    "sg:phone":"+49 7583/2341",
    "sg:postcode":"88427",
    "sg:province":"Baden-W\u00fcrttemberg",
    "wof:name":"Hugo Hammer",
    "wof:placetype":"venue"
},
  "geometry": {"coordinates":[9.6582765579,48.0034370422],"type":"Point"}
}