{
  "type": "Feature",
  "properties": {
    "iso:country":"DE",
    "sg:address":"Hauptstr. 106",
    "sg:city":"Neufahrn",
    "sg:phone":"+49 8773/180",
    "sg:postcode":"84088",
    "sg:province":"Bayern",
    "wof:name":"Erlus Baustoffwerke Ag",
    "wof:placetype":"venue"
},
  "geometry": {"coordinates":[12.1902160645,48.7253799438],"type":"Point"}
}