{
  "type": "Feature",
  "properties": {
    "iso:country":"DE",
    "sg:address":"Erikenstr. 50",
    "sg:city":"Leipzig",
    "sg:phone":"+49 341/4283435",
    "sg:postcode":"04249",
    "sg:province":"Sachsen",
    "wof:name":"Ne\u00dfler & Wellein",
    "wof:placetype":"venue"
},
  "geometry": {"coordinates":[12.302422,51.2584],"type":"Point"}
}