{
  "type": "Feature",
  "properties": {
    "iso:country":"DE",
    "sg:address":"Eichendorffstr. 7",
    "sg:city":"Waldkirchen",
    "sg:phone":"+49 8581/1553",
    "sg:postcode":"94065",
    "sg:province":"Bayern",
    "wof:name":"Josef S\u00fc\u00df",
    "wof:placetype":"venue"
},
  "geometry": {"coordinates":[13.5968255997,48.7324867249],"type":"Point"}
}