{
  "type": "Feature",
  "properties": {
    "iso:country":"DE",
    "sg:address":"Bertholdstr. 15",
    "sg:city":"Pforzheim",
    "sg:phone":"+49 7231/17766",
    "sg:postcode":"75177",
    "sg:province":"Baden-W\u00fcrttemberg",
    "wof:name":"Roland Maier",
    "wof:placetype":"venue"
},
  "geometry": {"coordinates":[8.7055006027,48.8961296082],"type":"Point"}
}