{
  "type": "Feature",
  "properties": {
    "iso:country":"DE",
    "sg:address":"Alte Ixheimer Str. 25",
    "sg:city":"Zweibr\u00fccken",
    "sg:postcode":"66482",
    "sg:province":"Rheinland-Pfalz",
    "wof:name":"Scala Filmtheater",
    "wof:placetype":"venue"
},
  "geometry": {"coordinates":[7.3653120995,49.2456092834],"type":"Point"}
}