{
  "type": "Feature",
  "properties": {
    "iso:country":"DE",
    "sg:address":"M\u00fcllinger Weg 12",
    "sg:city":"Laatzen",
    "sg:phone":"+49 5102/915706",
    "sg:postcode":"30880",
    "sg:province":"Niedersachsen",
    "wof:name":"Gerhard Jaekel Gmbh",
    "wof:placetype":"venue"
},
  "geometry": {"coordinates":[9.829788208,52.2859039307],"type":"Point"}
}