{
  "type": "Feature",
  "properties": {
    "iso:country":"DE",
    "sg:address":"Schillerstr. 33",
    "sg:city":"Bensheim",
    "sg:phone":"+49 6251/787804",
    "sg:postcode":"64625",
    "sg:province":"Hessen",
    "wof:name":"Wolfgang Winkelmann",
    "wof:placetype":"venue"
},
  "geometry": {"coordinates":[8.6165428162,49.699256897],"type":"Point"}
}