{
  "type": "Feature",
  "properties": {
    "iso:country":"DE",
    "sg:address":"Rangstr. 21",
    "sg:city":"Fulda",
    "sg:phone":"+49 661/72827",
    "sg:postcode":"36043",
    "sg:province":"Hessen",
    "wof:name":"Jacques Wein Depot Wein- Einzelhandel",
    "wof:placetype":"venue"
},
  "geometry": {"coordinates":[9.6770877838,50.5463829041],"type":"Point"}
}