{
  "type": "Feature",
  "properties": {
    "iso:country":"DE",
    "sg:address":"Birkenweg 10",
    "sg:city":"Recklinghausen",
    "sg:phone":"+49 2361/34768",
    "sg:postcode":"45659",
    "sg:province":"Nordrhein-Westfalen",
    "wof:name":"U. Gol\u00fcke Heilpraktikerin",
    "wof:placetype":"venue"
},
  "geometry": {"coordinates":[7.2103738785,51.5917396545],"type":"Point"}
}