{
  "type": "Feature",
  "properties": {
    "iso:country":"DE",
    "sg:address":"Karl-Robiczek-Str. 2",
    "sg:city":"F\u00fcrstenfeldbruck",
    "sg:phone":"+49 8141/44525",
    "sg:postcode":"82256",
    "sg:province":"Bayern",
    "wof:name":"Stauden-kraus",
    "wof:placetype":"venue"
},
  "geometry": {"coordinates":[11.265028,48.181786],"type":"Point"}
}