{
  "type": "Feature",
  "properties": {
    "iso:country":"DE",
    "sg:address":"Feldstiege 10",
    "sg:city":"Borken-Gemen",
    "sg:postcode":"46325",
    "sg:province":"Nordrhein-Westfalen",
    "wof:name":"Weddeling-malermeister",
    "wof:placetype":"venue"
},
  "geometry": {"coordinates":[6.8606929779,51.8618164062],"type":"Point"}
}