{
  "type": "Feature",
  "properties": {
    "iso:country":"DE",
    "sg:address":"Hessenring 28",
    "sg:city":"Offenbach",
    "sg:phone":"+49 69/854285",
    "sg:postcode":"63071",
    "sg:province":"Hessen",
    "wof:name":"Boy Productions Gmbh",
    "wof:placetype":"venue"
},
  "geometry": {"coordinates":[8.771438,50.095558],"type":"Point"}
}