{
  "type": "Feature",
  "properties": {
    "iso:country":"DE",
    "sg:address":"Gerlachstr. 25",
    "sg:city":"Hannover",
    "sg:phone":"+49 511/814700",
    "sg:postcode":"30173",
    "sg:province":"Niedersachsen",
    "wof:name":"Karl Schr\u00f6der Steuerberater",
    "wof:placetype":"venue"
},
  "geometry": {"coordinates":[9.772190094,52.3633041382],"type":"Point"}
}