{
  "type": "Feature",
  "properties": {
    "iso:country":"DE",
    "sg:address":"Elsestr. 11",
    "sg:city":"Stahnsdorf",
    "sg:phone":"+49 3329/60570",
    "sg:postcode":"14532",
    "sg:province":"Brandenburg",
    "wof:name":"Protheus Security Gmbh",
    "wof:placetype":"venue"
},
  "geometry": {"coordinates":[13.2161130905,52.3746070862],"type":"Point"}
}