{
  "type": "Feature",
  "properties": {
    "iso:country":"DE",
    "sg:address":"Driescher Str. 33",
    "sg:city":"Kaarst",
    "sg:phone":"+49 2131/989598",
    "sg:postcode":"41564",
    "sg:province":"Nordrhein-Westfalen",
    "wof:name":"Caritas Pflegestation",
    "wof:placetype":"venue"
},
  "geometry": {"coordinates":[6.605201,51.19968],"type":"Point"}
}