{
  "type": "Feature",
  "properties": {
    "iso:country":"DE",
    "sg:address":"Im H\u00e4fl\u00e4 9",
    "sg:city":"Bad S\u00e4ckingen",
    "sg:phone":"+49 7761/1005",
    "sg:postcode":"79713",
    "sg:province":"Baden-W\u00fcrttemberg",
    "wof:name":"Ingenieurb\u00fcro Hochrhein Gmbh",
    "wof:placetype":"venue"
},
  "geometry": {"coordinates":[7.960955,47.560894],"type":"Point"}
}