{
  "type": "Feature",
  "properties": {
    "iso:country":"DE",
    "sg:address":"Bayreuther Str. 1",
    "sg:city":"Heinersreuth",
    "sg:phone":"+49 921",
    "sg:postcode":"95500",
    "sg:province":"Bayern",
    "wof:name":"Hotel-gasthof Opel Bei Bayreuth",
    "wof:placetype":"venue"
},
  "geometry": {"coordinates":[11.5319700241,49.9680213928],"type":"Point"}
}