{
  "type": "Feature",
  "properties": {
    "iso:country":"DE",
    "sg:address":"Im Fl\u00f6schle 38",
    "sg:city":"Wildberg",
    "sg:phone":"+49 7054/5696",
    "sg:postcode":"72218",
    "sg:province":"Baden-W\u00fcrttemberg",
    "wof:name":"W. Und E. R\u00f6hm",
    "wof:placetype":"venue"
},
  "geometry": {"coordinates":[8.777798,48.619625],"type":"Point"}
}