{
  "type": "Feature",
  "properties": {
    "iso:country":"DE",
    "sg:address":"Weststr. 35",
    "sg:city":"Zittau",
    "sg:postcode":"02763",
    "sg:province":"Sachsen",
    "wof:name":"Burgteich",
    "wof:placetype":"venue"
},
  "geometry": {"coordinates":[14.7858314514,50.8962440491],"type":"Point"}
}