{
  "type": "Feature",
  "properties": {
    "iso:country":"DE",
    "sg:address":"Markt 35",
    "sg:city":"Lutherstadt Eisleben",
    "sg:phone":"+49 3475/92530",
    "sg:postcode":"06295",
    "sg:province":"Sachsen-Anhalt",
    "wof:name":"Multi Media Telesat Gmbh",
    "wof:placetype":"venue"
},
  "geometry": {"coordinates":[11.548352,51.528137],"type":"Point"}
}