{
  "type": "Feature",
  "properties": {
    "iso:country":"DE",
    "sg:address":"Bieste",
    "sg:city":"Rieste",
    "sg:phone":"+49 5493/239",
    "sg:postcode":"49597",
    "sg:province":"Niedersachsen",
    "wof:name":"Heinrich Schraad",
    "wof:placetype":"venue"
},
  "geometry": {"coordinates":[8.021041,52.521347],"type":"Point"}
}