{
  "type": "Feature",
  "properties": {
    "iso:country":"DE",
    "sg:address":"Am Bommerichshof",
    "sg:city":"Bergheim",
    "sg:phone":"+49 2238/44019",
    "sg:postcode":"50129",
    "sg:province":"Nordrhein-Westfalen",
    "wof:name":"Johannes Schenk",
    "wof:placetype":"venue"
},
  "geometry": {"coordinates":[6.69517,51.00951],"type":"Point"}
}