{
  "type": "Feature",
  "properties": {
    "iso:country":"DE",
    "sg:address":"Weingartenstr. 28",
    "sg:city":"Nauheim",
    "sg:phone":"+49 6152/63691",
    "sg:postcode":"64569",
    "sg:province":"Hessen",
    "wof:name":"J\u00f6rg P\u00fcchner Rechtsanwalt",
    "wof:placetype":"venue"
},
  "geometry": {"coordinates":[8.4501247406,49.9449920654],"type":"Point"}
}