{
  "type": "Feature",
  "properties": {
    "iso:country":"DE",
    "sg:address":"Kreuzgasse 22-24",
    "sg:city":"Usingen",
    "sg:phone":"+49 6081/10210",
    "sg:postcode":"61250",
    "sg:province":"Hessen",
    "wof:name":"Redaktion Camberger Anzeiger Wagner Druck- Und Verlag",
    "wof:placetype":"venue"
},
  "geometry": {"coordinates":[8.5350074768,50.3354301453],"type":"Point"}
}