{
  "type": "Feature",
  "properties": {
    "iso:country":"DE",
    "sg:address":"B\u00fcnder Str. 53",
    "sg:city":"R\u00f6dinghausen",
    "sg:phone":"+49 5746/8156",
    "sg:postcode":"32289",
    "sg:province":"Nordrhein-Westfalen",
    "wof:name":"Heinrich Lienemann",
    "wof:placetype":"venue"
},
  "geometry": {"coordinates":[8.5092802048,52.2451286316],"type":"Point"}
}