{
  "type": "Feature",
  "properties": {
    "iso:country":"DE",
    "sg:address":"Purschwitzer Str. 17",
    "sg:city":"Malschwitz",
    "sg:phone":"+49 35932/30958",
    "sg:postcode":"02694",
    "sg:province":"Sachsen",
    "wof:name":"Kleinbautzen",
    "wof:placetype":"venue"
},
  "geometry": {"coordinates":[14.5290317535,51.212474823],"type":"Point"}
}