{
  "type": "Feature",
  "properties": {
    "iso:country":"DE",
    "sg:address":"Sterzenbach 4",
    "sg:city":"Hohenfels",
    "sg:phone":"+49 9472/218",
    "sg:postcode":"92366",
    "sg:province":"Bayern",
    "wof:name":"Gastst\u00e4tte Kreszenz Kotzbauer",
    "wof:placetype":"venue"
},
  "geometry": {"coordinates":[11.8486871719,49.2028083801],"type":"Point"}
}