{
  "type": "Feature",
  "properties": {
    "iso:country":"DE",
    "sg:address":"Im Drosselhain 14",
    "sg:city":"Bergisch Gladbach",
    "sg:phone":"+49 2202/57319",
    "sg:postcode":"51467",
    "sg:province":"Nordrhein-Westfalen",
    "wof:name":"Dr. H.-j\u00fcrgen Pokora",
    "wof:placetype":"venue"
},
  "geometry": {"coordinates":[7.1128468513,51.0018501282],"type":"Point"}
}