{
  "type": "Feature",
  "properties": {
    "iso:country":"DE",
    "sg:address":"Am Ziegelturm 4",
    "sg:city":"Gelnhausen",
    "sg:phone":"+49 6051/17058",
    "sg:postcode":"63571",
    "sg:province":"Hessen",
    "wof:name":"Hako Schuh Dietrich Bahner Gmbh & Co. Kg",
    "wof:placetype":"venue"
},
  "geometry": {"coordinates":[9.1915178299,50.1998291016],"type":"Point"}
}