{
  "type": "Feature",
  "properties": {
    "iso:country":"DE",
    "sg:address":"Johannisthaler Chaussee 50",
    "sg:city":"Berlin",
    "sg:phone":"+49 30/30872357",
    "sg:postcode":"12437",
    "sg:province":"Berlin",
    "wof:name":"Vsbg Geb\u00e4ude- Management Gmbh",
    "wof:placetype":"venue"
},
  "geometry": {"coordinates":[13.4837379456,52.4475326538],"type":"Point"}
}