{
  "type": "Feature",
  "properties": {
    "iso:country":"DE",
    "sg:address":"Hauptstr. 5",
    "sg:city":"Meschede",
    "sg:phone":"+49 291/9085316",
    "sg:postcode":"59872",
    "sg:province":"Nordrhein-Westfalen",
    "wof:name":"Mobidoc Pflegedienst & Service Gmbh",
    "wof:placetype":"venue"
},
  "geometry": {"coordinates":[8.171781,51.374817],"type":"Point"}
}