{
  "type": "Feature",
  "properties": {
    "iso:country":"DE",
    "sg:address":"Buchenweg 11",
    "sg:city":"Oberursel",
    "sg:phone":"+49 6172/35719",
    "sg:postcode":"61440",
    "sg:province":"Hessen",
    "wof:name":"Dr. Alfred Fuss Rechtsanwalt",
    "wof:placetype":"venue"
},
  "geometry": {"coordinates":[8.5601825714,50.2204017639],"type":"Point"}
}