{
  "type": "Feature",
  "properties": {
    "iso:country":"DE",
    "sg:address":"Hauptstr. 6",
    "sg:city":"\u00d6tzingen",
    "sg:phone":"+49 2602/70676",
    "sg:postcode":"56244",
    "sg:province":"Rheinland-Pfalz",
    "wof:name":"H. Stein",
    "wof:placetype":"venue"
},
  "geometry": {"coordinates":[7.828854084,50.5016174316],"type":"Point"}
}