{
  "type": "Feature",
  "properties": {
    "iso:country":"DE",
    "sg:address":"Hofstr. 12",
    "sg:city":"Bad Bellingen",
    "sg:phone":"+49 7635/9222",
    "sg:postcode":"79415",
    "sg:province":"Baden-W\u00fcrttemberg",
    "wof:name":"Pension Garni Rheinsberg",
    "wof:placetype":"venue"
},
  "geometry": {"coordinates":[7.5601921082,47.7321853638],"type":"Point"}
}