{
  "type": "Feature",
  "properties": {
    "iso:country":"DE",
    "sg:address":"Kirchstr. 352",
    "sg:city":"Helgoland",
    "sg:phone":"+49 4725/7376",
    "sg:postcode":"27498",
    "sg:province":"Schleswig-Holstein",
    "wof:name":"G\u00e4stehaus Gerda Stavemann",
    "wof:placetype":"venue"
},
  "geometry": {"coordinates":[7.8862128258,54.1828994751],"type":"Point"}
}