{
  "type": "Feature",
  "properties": {
    "iso:country":"DE",
    "sg:address":"Hintere Str. 15",
    "sg:city":"Fellbach",
    "sg:phone":"+49 711/582158",
    "sg:postcode":"70734",
    "sg:province":"Baden-W\u00fcrttemberg",
    "wof:name":"Herrenkommode",
    "wof:placetype":"venue"
},
  "geometry": {"coordinates":[9.2761049271,48.8077774048],"type":"Point"}
}