{
  "type": "Feature",
  "properties": {
    "iso:country":"DE",
    "sg:address":"L\u00f6bleinstr. 56",
    "sg:city":"N\u00fcrnberg",
    "sg:phone":"+49 911/356548",
    "sg:postcode":"90409",
    "sg:province":"Bayern",
    "wof:name":"Wilhelm Felsen",
    "wof:placetype":"venue"
},
  "geometry": {"coordinates":[11.0883693695,49.4654006958],"type":"Point"}
}