{
  "type": "Feature",
  "properties": {
    "iso:country":"DE",
    "sg:address":"Neckarstr. 5",
    "sg:city":"Neckartailfingen",
    "sg:phone":"+49 4971/2731010",
    "sg:postcode":"72666",
    "sg:province":"Baden-W\u00fcrttemberg",
    "wof:name":"Gebr. Greiner Gmbh",
    "wof:placetype":"venue"
},
  "geometry": {"coordinates":[9.26866,48.61375],"type":"Point"}
}