{
  "type": "Feature",
  "properties": {
    "iso:country":"DE",
    "sg:address":"Am Hauptbahnhof 6",
    "sg:city":"Bonn",
    "sg:phone":"+49 228/633637",
    "sg:postcode":"53111",
    "sg:province":"Nordrhein-Westfalen",
    "wof:name":"Knut Fa\u00dfler",
    "wof:placetype":"venue"
},
  "geometry": {"coordinates":[7.0975790024,50.7324409485],"type":"Point"}
}