{
  "type": "Feature",
  "properties": {
    "iso:country":"DE",
    "sg:address":"Deubacher Str. 43",
    "sg:city":"Kutzenhausen",
    "sg:phone":"+49 8294/783",
    "sg:postcode":"86500",
    "sg:province":"Bayern",
    "wof:name":"Josef M. Heinrich",
    "wof:placetype":"venue"
},
  "geometry": {"coordinates":[10.7125091553,48.3653678894],"type":"Point"}
}