{
  "type": "Feature",
  "properties": {
    "iso:country":"DE",
    "sg:address":"Friedrich-Ebert-Str. 50",
    "sg:city":"Mannheim",
    "sg:phone":"+49 621/3392366",
    "sg:postcode":"68167",
    "sg:province":"Baden-W\u00fcrttemberg",
    "wof:name":"Kleine Kaserne",
    "wof:placetype":"venue"
},
  "geometry": {"coordinates":[8.4949998856,49.501411438],"type":"Point"}
}