{
  "type": "Feature",
  "properties": {
    "iso:country":"DE",
    "sg:address":"Friedrichstr 55",
    "sg:city":"Velbert",
    "sg:phone":"+49 2051/54316",
    "sg:postcode":"42551",
    "sg:province":"Nordrhein-Westfalen",
    "wof:name":"Sat Fertigungstechnik Gmbh",
    "wof:placetype":"venue"
},
  "geometry": {"coordinates":[7.037592,51.343021],"type":"Point"}
}