{
  "type": "Feature",
  "properties": {
    "iso:country":"DE",
    "sg:address":"Halberst\u00e4dter Poststr. 4",
    "sg:city":"Schellerten",
    "sg:phone":"+49 5123/8368",
    "sg:postcode":"31174",
    "sg:province":"Niedersachsen",
    "wof:name":"Godehard Fleige",
    "wof:placetype":"venue"
},
  "geometry": {"coordinates":[10.059157,52.167698],"type":"Point"}
}