{
  "type": "Feature",
  "properties": {
    "iso:country":"DE",
    "sg:address":"Weinbergstr.",
    "sg:city":"Holleben",
    "sg:phone":"+49 345/6130248",
    "sg:postcode":"06179",
    "sg:province":"Sachsen-Anhalt",
    "wof:name":"Agrargenossenschaft Holleben E. G.",
    "wof:placetype":"venue"
},
  "geometry": {"coordinates":[11.89391,51.444561],"type":"Point"}
}