{
  "type": "Feature",
  "properties": {
    "iso:country":"DE",
    "sg:address":"Ludolf-van-Ceulen-Str. 3",
    "sg:city":"Hillesheim",
    "sg:phone":"+49 6593/416",
    "sg:postcode":"54576",
    "sg:province":"Rheinland-Pfalz",
    "wof:name":"Ackermann & Br\u00fcggen Keramik- Gmbh",
    "wof:placetype":"venue"
},
  "geometry": {"coordinates":[6.6611142159,50.2926292419],"type":"Point"}
}