{
  "type": "Feature",
  "properties": {
    "iso:country":"DE",
    "sg:address":"Weierstr. 45",
    "sg:city":"H\u00fcrth",
    "sg:phone":"+49 2233/42425",
    "sg:postcode":"50354",
    "sg:province":"Nordrhein-Westfalen",
    "wof:name":"Schlesinger Gmbh",
    "wof:placetype":"venue"
},
  "geometry": {"coordinates":[6.8662228584,50.8684043884],"type":"Point"}
}