{
  "type": "Feature",
  "properties": {
    "iso:country":"DE",
    "sg:address":"Panoramaweg 9",
    "sg:city":"Hohenfurch",
    "sg:phone":"+49 8869/93127",
    "sg:postcode":"86978",
    "sg:province":"Bayern",
    "wof:name":"Wilhelm Passauer Heilpraktiker",
    "wof:placetype":"venue"
},
  "geometry": {"coordinates":[10.8917341232,47.860370636],"type":"Point"}
}