{
  "type": "Feature",
  "properties": {
    "iso:country":"DE",
    "sg:address":"Jean-Bareth-Str. 17",
    "sg:city":"Gro\u00df-Gerau",
    "sg:phone":"+49 6152/55571",
    "sg:postcode":"64521",
    "sg:province":"Hessen",
    "wof:name":"Gudrun Dulies",
    "wof:placetype":"venue"
},
  "geometry": {"coordinates":[8.4813117981,49.9100646973],"type":"Point"}
}