{
  "type": "Feature",
  "properties": {
    "iso:country":"DE",
    "sg:address":"Markstr. 77",
    "sg:city":"Bochum",
    "sg:phone":"+49 4923/4935860",
    "sg:postcode":"44801",
    "sg:province":"Nordrhein-Westfalen",
    "wof:name":"Hauk & Sasko Ingenieurgesellschaft Mbh",
    "wof:placetype":"venue"
},
  "geometry": {"coordinates":[7.257286,51.4599],"type":"Point"}
}