{
  "type": "Feature",
  "properties": {
    "iso:country":"DE",
    "sg:address":"Epprather Weg 5",
    "sg:city":"K\u00f6ln",
    "sg:phone":"+49 221/799745",
    "sg:postcode":"50767",
    "sg:province":"Nordrhein-Westfalen",
    "wof:name":"E. Belen Steuerberater",
    "wof:placetype":"venue"
},
  "geometry": {"coordinates":[6.8978090286,51.0176620483],"type":"Point"}
}