{
  "type": "Feature",
  "properties": {
    "iso:country":"DE",
    "sg:address":"Schulstr 102",
    "sg:city":"Wiesmoor",
    "sg:phone":"+49 4944/92260",
    "sg:postcode":"26639",
    "sg:province":"Niedersachsen",
    "wof:name":"Betonwerk Wiesmoor Gmbh & Co Kg",
    "wof:placetype":"venue"
},
  "geometry": {"coordinates":[7.724170208,53.4371414185],"type":"Point"}
}