{
  "type": "Feature",
  "properties": {
    "iso:country":"DE",
    "sg:address":"Kohlgartenstr. 54",
    "sg:city":"Leipzig",
    "sg:phone":"+49 341/6888277",
    "sg:postcode":"04315",
    "sg:province":"Sachsen",
    "wof:name":"Ralf Wirth Gmbh",
    "wof:placetype":"venue"
},
  "geometry": {"coordinates":[12.401948,51.340034],"type":"Point"}
}