{
  "type": "Feature",
  "properties": {
    "iso:country":"DE",
    "sg:address":"F\u00fcrther Str. 10",
    "sg:city":"N\u00fcrnberg",
    "sg:phone":"+49 911/933440",
    "sg:postcode":"90429",
    "sg:province":"Bayern",
    "wof:name":"M.m.p. Marketing Medien Promotion Service Gmbh",
    "wof:placetype":"venue"
},
  "geometry": {"coordinates":[11.0619096756,49.4496498108],"type":"Point"}
}