{
  "type": "Feature",
  "properties": {
    "iso:country":"DE",
    "sg:address":"Florianstr. 10",
    "sg:city":"H\u00f6chenschwand",
    "sg:postcode":"79862",
    "sg:province":"Baden-W\u00fcrttemberg",
    "wof:name":"Bauunternehmen Schmidt Gmbh",
    "wof:placetype":"venue"
},
  "geometry": {"coordinates":[8.1753902435,47.7317008972],"type":"Point"}
}