{
  "type": "Feature",
  "properties": {
    "iso:country":"DE",
    "sg:address":"Wieslauftalstr. 9",
    "sg:city":"Schorndorf",
    "sg:phone":"+49 7181/24784",
    "sg:postcode":"73614",
    "sg:province":"Baden-W\u00fcrttemberg",
    "wof:name":"Rolf Gl\u00e4\u00dfle",
    "wof:placetype":"venue"
},
  "geometry": {"coordinates":[9.550389,48.83041],"type":"Point"}
}