{
  "type": "Feature",
  "properties": {
    "iso:country":"DE",
    "sg:address":"Eichborndamm 165",
    "sg:city":"Berlin",
    "sg:postcode":"13403",
    "sg:province":"Berlin",
    "wof:name":"Aldi Gmbh & Co. Kg",
    "wof:placetype":"venue"
},
  "geometry": {"coordinates":[13.3190965652,52.5821685791],"type":"Point"}
}