{
  "type": "Feature",
  "properties": {
    "iso:country":"DE",
    "sg:address":"Sulzbacher Str. 70",
    "sg:city":"Lauterbach",
    "sg:phone":"+49 7422/7766",
    "sg:postcode":"78730",
    "sg:province":"Baden-W\u00fcrttemberg",
    "wof:name":"Viktor Neff Gmbh",
    "wof:placetype":"venue"
},
  "geometry": {"coordinates":[8.3270998001,48.2468452454],"type":"Point"}
}