{
  "type": "Feature",
  "properties": {
    "iso:country":"DE",
    "sg:address":"Steinbeisstr. 5",
    "sg:city":"Ilsfeld",
    "sg:phone":"+49 7062/9730810",
    "sg:postcode":"74360",
    "sg:province":"Baden-W\u00fcrttemberg",
    "wof:name":"K\u00f6nig Komfort- Und Rennsitze Gmbh",
    "wof:placetype":"venue"
},
  "geometry": {"coordinates":[9.2602024078,49.0561485291],"type":"Point"}
}