{
  "type": "Feature",
  "properties": {
    "iso:country":"DE",
    "sg:address":"Piesauer Str. 4 g",
    "sg:city":"Lichte",
    "sg:phone":"+49 36701/62800",
    "sg:postcode":"98739",
    "sg:province":"Th\u00fcringen",
    "wof:name":"Privatbrauerei K\u00f6nigsee Gmbh",
    "wof:placetype":"venue"
},
  "geometry": {"coordinates":[11.201915,50.525455],"type":"Point"}
}