{
  "type": "Feature",
  "properties": {
    "iso:country":"DE",
    "sg:address":"Industriestr 1",
    "sg:city":"Olching",
    "sg:phone":"+49 8142/178221",
    "sg:postcode":"82140",
    "sg:province":"Bayern",
    "wof:name":"Elastogran Gmbh",
    "wof:placetype":"venue"
},
  "geometry": {"coordinates":[11.337246,48.222286],"type":"Point"}
}