{
  "type": "Feature",
  "properties": {
    "iso:country":"DE",
    "sg:address":"Berliner Str. 4",
    "sg:city":"Hildesheim",
    "sg:phone":"+49 5121/58131",
    "sg:postcode":"31135",
    "sg:province":"Niedersachsen",
    "wof:name":"H.w.d. Hildesheimer Spezial-werkzeug-dienst Gmbh",
    "wof:placetype":"venue"
},
  "geometry": {"coordinates":[9.969518,52.158318],"type":"Point"}
}