{
  "type": "Feature",
  "properties": {
    "iso:country":"DE",
    "sg:address":"Hallstadter Str. 54",
    "sg:city":"Bamberg",
    "sg:phone":"+49 951/64564",
    "sg:postcode":"96052",
    "sg:province":"Bayern",
    "wof:name":"Paul Braun",
    "wof:placetype":"venue"
},
  "geometry": {"coordinates":[10.884014,49.908627],"type":"Point"}
}