{
  "type": "Feature",
  "properties": {
    "iso:country":"DE",
    "sg:address":"Auf der Bastei 3",
    "sg:city":"Mainz",
    "sg:phone":"+49 6131/995485",
    "sg:postcode":"55131",
    "sg:province":"Rheinland-Pfalz",
    "wof:name":"Villa Musica Stiftung",
    "wof:placetype":"venue"
},
  "geometry": {"coordinates":[8.2619791031,49.9967842102],"type":"Point"}
}