{
  "type": "Feature",
  "properties": {
    "iso:country":"DE",
    "sg:address":"Feldstr. 7",
    "sg:city":"Bockau",
    "sg:phone":"+49 3771/454312",
    "sg:postcode":"08324",
    "sg:province":"Sachsen",
    "wof:name":"Fan Haus Wohnungsverwaltungs- Besitz Und Bautr\u00e4ger Gmbh",
    "wof:placetype":"venue"
},
  "geometry": {"coordinates":[12.685225,50.538067],"type":"Point"}
}