{
  "type": "Feature",
  "properties": {
    "iso:country":"DE",
    "sg:address":"Max-M\u00fcller-Str. 1",
    "sg:city":"Chemnitz",
    "sg:phone":"+49 371/2824100",
    "sg:postcode":"09123",
    "sg:province":"Sachsen",
    "wof:name":"Km-funkelektronik",
    "wof:placetype":"venue"
},
  "geometry": {"coordinates":[12.8969545364,50.7914428711],"type":"Point"}
}