{
  "type": "Feature",
  "properties": {
    "iso:country":"DE",
    "sg:address":"Bahnhofstr.",
    "sg:city":"Sickte",
    "sg:phone":"+49 5305/1698",
    "sg:postcode":"38173",
    "sg:province":"Niedersachsen",
    "wof:name":"Raiffeisen Waren-zentrale Rhein-main Eg",
    "wof:placetype":"venue"
},
  "geometry": {"coordinates":[10.637443,52.215626],"type":"Point"}
}