{
  "type": "Feature",
  "properties": {
    "iso:country":"DE",
    "sg:address":"Abelnkarre 2 a",
    "sg:city":"Braunschweig",
    "sg:postcode":"38100",
    "sg:province":"Niedersachsen",
    "wof:name":"Erc Gmbh",
    "wof:placetype":"venue"
},
  "geometry": {"coordinates":[10.527920723,52.2673339844],"type":"Point"}
}