{
  "type": "Feature",
  "properties": {
    "iso:country":"DE",
    "sg:address":"R\u00f6srather Str. 87",
    "sg:city":"K\u00f6ln",
    "sg:phone":"+49 221/8903662",
    "sg:postcode":"51107",
    "sg:province":"Nordrhein-Westfalen",
    "wof:name":"Franz-josef Oebl",
    "wof:placetype":"venue"
},
  "geometry": {"coordinates":[7.048903,50.929878],"type":"Point"}
}