{
  "type": "Feature",
  "properties": {
    "iso:country":"DE",
    "sg:address":"Raiffeisenstr. 8",
    "sg:city":"Weissach",
    "sg:phone":"+49 7044/31244",
    "sg:postcode":"71287",
    "sg:province":"Baden-W\u00fcrttemberg",
    "wof:name":"Notariat Weissach",
    "wof:placetype":"venue"
},
  "geometry": {"coordinates":[8.9287452698,48.8470077515],"type":"Point"}
}