{
  "type": "Feature",
  "properties": {
    "iso:country":"DE",
    "sg:address":"Kolpingstr.",
    "sg:city":"Beverungen",
    "sg:phone":"+49 5273/6863",
    "sg:postcode":"37688",
    "sg:province":"Nordrhein-Westfalen",
    "wof:name":"Stadthalle Beverungen",
    "wof:placetype":"venue"
},
  "geometry": {"coordinates":[9.374527,51.661503],"type":"Point"}
}