{
  "type": "Feature",
  "properties": {
    "iso:country":"DE",
    "sg:address":"Adolf-Damaschke-Str. 20",
    "sg:city":"Riesa",
    "sg:phone":"+49 3525/731516",
    "sg:postcode":"01591",
    "sg:province":"Sachsen",
    "wof:name":"A & E Energieanlagen Gmbh",
    "wof:placetype":"venue"
},
  "geometry": {"coordinates":[13.25298,51.317989],"type":"Point"}
}