{
  "type": "Feature",
  "properties": {
    "iso:country":"DE",
    "sg:address":"Isaak-Maus-Str. 5",
    "sg:city":"Badenheim",
    "sg:postcode":"55576",
    "sg:province":"Rheinland-Pfalz",
    "wof:name":"Schnelle Partner Gmbh",
    "wof:placetype":"venue"
},
  "geometry": {"coordinates":[7.9865322113,49.8607139587],"type":"Point"}
}