{
  "type": "Feature",
  "properties": {
    "iso:country":"DE",
    "sg:address":"Sonnenweg 4 b",
    "sg:city":"Hamburg",
    "sg:phone":"+49 40/665459",
    "sg:postcode":"22045",
    "sg:province":"Hamburg",
    "wof:name":"Imbi\u00df-stube E. Pakatzki",
    "wof:placetype":"venue"
},
  "geometry": {"coordinates":[10.124920845,53.5868186951],"type":"Point"}
}