{
  "type": "Feature",
  "properties": {
    "iso:country":"DE",
    "sg:address":"Falkenstr. 80",
    "sg:city":"Erkrath",
    "sg:phone":"+49 211/243504",
    "sg:postcode":"40699",
    "sg:province":"Nordrhein-Westfalen",
    "wof:name":"Ev. Pfarramt Iii Erkrath",
    "wof:placetype":"venue"
},
  "geometry": {"coordinates":[6.9177250862,51.216053009],"type":"Point"}
}