{
  "type": "Feature",
  "properties": {
    "iso:country":"DE",
    "sg:address":"Graslitzer Str. 23",
    "sg:city":"Geretsried",
    "sg:phone":"+49 8171/61957",
    "sg:postcode":"82538",
    "sg:province":"Bayern",
    "wof:name":"Walburga Klein",
    "wof:placetype":"venue"
},
  "geometry": {"coordinates":[11.462741,47.876076],"type":"Point"}
}