{
  "type": "Feature",
  "properties": {
    "iso:country":"DE",
    "sg:address":"Kuckelkornweg 8",
    "sg:city":"Aachen",
    "sg:phone":"+49 241/551513",
    "sg:postcode":"52080",
    "sg:province":"Nordrhein-Westfalen",
    "wof:name":"Killian Gmbh",
    "wof:placetype":"venue"
},
  "geometry": {"coordinates":[6.1527619362,50.7858924866],"type":"Point"}
}