{
  "type": "Feature",
  "properties": {
    "iso:country":"DE",
    "sg:address":"Stegersweg 4",
    "sg:city":"Geldern",
    "sg:phone":"+49 2831/2741",
    "sg:postcode":"47608",
    "sg:province":"Nordrhein-Westfalen",
    "wof:name":"W. Rattmann",
    "wof:placetype":"venue"
},
  "geometry": {"coordinates":[6.360022,51.519596],"type":"Point"}
}