{
  "type": "Feature",
  "properties": {
    "iso:country":"DE",
    "sg:address":"Akazienweg 15",
    "sg:city":"Ennepetal",
    "sg:phone":"+49 2333/973585",
    "sg:postcode":"58256",
    "sg:province":"Nordrhein-Westfalen",
    "wof:name":"Die-hand-in-handwerker Gmbh",
    "wof:placetype":"venue"
},
  "geometry": {"coordinates":[7.320249,51.299492],"type":"Point"}
}