{
  "type": "Feature",
  "properties": {
    "iso:country":"DE",
    "sg:address":"Max-Planck-Str. 10",
    "sg:city":"Kempen",
    "sg:phone":"+49 2152/50116",
    "sg:postcode":"47906",
    "sg:province":"Nordrhein-Westfalen",
    "wof:name":"Franz Boge",
    "wof:placetype":"venue"
},
  "geometry": {"coordinates":[6.410851,51.375851],"type":"Point"}
}