{
  "type": "Feature",
  "properties": {
    "iso:country":"DE",
    "sg:address":"Rosenstr. 10",
    "sg:city":"F\u00fcrth",
    "sg:phone":"+49 911/7498973",
    "sg:postcode":"90762",
    "sg:province":"Bayern",
    "wof:name":"Behringer Antiquit\u00e4ten",
    "wof:placetype":"venue"
},
  "geometry": {"coordinates":[10.987324,49.476418],"type":"Point"}
}