{
  "type": "Feature",
  "properties": {
    "iso:country":"DE",
    "sg:address":"Rheinbacher Str. 38",
    "sg:city":"Weilerswist",
    "sg:phone":"+49 2254/4180",
    "sg:postcode":"53919",
    "sg:province":"Nordrhein-Westfalen",
    "wof:name":"Warnecke Gmbh",
    "wof:placetype":"venue"
},
  "geometry": {"coordinates":[6.8760299683,50.7147445679],"type":"Point"}
}