{
  "type": "Feature",
  "properties": {
    "iso:country":"DE",
    "sg:address":"Sch\u00fctzenstr 8",
    "sg:city":"M\u00fcnchen",
    "sg:phone":"+49 89/5003980",
    "sg:postcode":"80335",
    "sg:province":"Bayern",
    "wof:name":"Queen's Auktionshaus Verwaltungs Gmbh",
    "wof:placetype":"venue"
},
  "geometry": {"coordinates":[11.563256,48.139828],"type":"Point"}
}