{
  "type": "Feature",
  "properties": {
    "iso:country":"DE",
    "sg:address":"Nickelstr. 11",
    "sg:city":"Rheda-Wiedenbr\u00fcck",
    "sg:phone":"+49 5242/928585",
    "sg:postcode":"33378",
    "sg:province":"Nordrhein-Westfalen",
    "wof:name":"Bernhard Rosomm",
    "wof:placetype":"venue"
},
  "geometry": {"coordinates":[8.3594322205,51.834312439],"type":"Point"}
}