{
  "type": "Feature",
  "properties": {
    "iso:country":"DE",
    "sg:address":"Liebenwalder Str. 17",
    "sg:city":"Zehdenick",
    "sg:postcode":"16792",
    "sg:province":"Brandenburg",
    "wof:name":"Erwin Breeskow",
    "wof:placetype":"venue"
},
  "geometry": {"coordinates":[13.3514604568,52.9767532349],"type":"Point"}
}