{
  "type": "Feature",
  "properties": {
    "iso:country":"DE",
    "sg:address":"Kuttlerstr. 4",
    "sg:city":"Erlangen",
    "sg:phone":"+49 9131/208955",
    "sg:postcode":"91054",
    "sg:province":"Bayern",
    "wof:name":"St\u00f6phasius",
    "wof:placetype":"venue"
},
  "geometry": {"coordinates":[11.0022621155,49.5994949341],"type":"Point"}
}