{
  "type": "Feature",
  "properties": {
    "iso:country":"DE",
    "sg:address":"Hauptstr. 15",
    "sg:city":"Blaufelden",
    "sg:phone":"+49 7953/1041",
    "sg:postcode":"74572",
    "sg:province":"Baden-W\u00fcrttemberg",
    "wof:name":"Gasthof Hirsch G\u00f6tzenstube",
    "wof:placetype":"venue"
},
  "geometry": {"coordinates":[9.9735097885,49.2964363098],"type":"Point"}
}