{
  "type": "Feature",
  "properties": {
    "iso:country":"DE",
    "sg:address":"Gutenbergstr. 6",
    "sg:city":"Bielefeld",
    "sg:phone":"+49 521/171899",
    "sg:postcode":"33615",
    "sg:province":"Nordrhein-Westfalen",
    "wof:name":"Maria B\u00fcchner",
    "wof:placetype":"venue"
},
  "geometry": {"coordinates":[8.523763,52.032284],"type":"Point"}
}