{
  "type": "Feature",
  "properties": {
    "iso:country":"DE",
    "sg:address":"Glauberger Str. 45",
    "sg:city":"Glauburg",
    "sg:phone":"+49 6041/80060",
    "sg:postcode":"63695",
    "sg:province":"Hessen",
    "wof:name":"Raiffeisen Waren-zentrale Rhein-main Eg",
    "wof:placetype":"venue"
},
  "geometry": {"coordinates":[9.010932,50.320995],"type":"Point"}
}