{
  "type": "Feature",
  "properties": {
    "iso:country":"DE",
    "sg:address":"Robert-Koch-Str 28",
    "sg:city":"Burghausen",
    "sg:phone":"+49 8677/888255",
    "sg:postcode":"84489",
    "sg:province":"Bayern",
    "wof:name":"Volksbank Burghausen Eg",
    "wof:placetype":"venue"
},
  "geometry": {"coordinates":[12.831922,48.172127],"type":"Point"}
}