{
  "type": "Feature",
  "properties": {
    "iso:country":"DE",
    "sg:address":"Hauptstr. 2",
    "sg:city":"Epfenbach",
    "sg:phone":"+49 7263/1504",
    "sg:postcode":"74925",
    "sg:province":"Baden-W\u00fcrttemberg",
    "wof:name":"Hirsch",
    "wof:placetype":"venue"
},
  "geometry": {"coordinates":[8.9131813049,49.3375968933],"type":"Point"}
}