{
  "type": "Feature",
  "properties": {
    "iso:country":"DE",
    "sg:address":"Reiterstr. 29",
    "sg:city":"Landau",
    "sg:phone":"+49 6341/80484",
    "sg:postcode":"76829",
    "sg:province":"Rheinland-Pfalz",
    "wof:name":"Udo Lamek Heilpraktiker",
    "wof:placetype":"venue"
},
  "geometry": {"coordinates":[8.1152334213,49.1950263977],"type":"Point"}
}