{
  "type": "Feature",
  "properties": {
    "iso:country":"DE",
    "sg:address":"Nu\u00dfbergstr. 17",
    "sg:city":"Braunschweig",
    "sg:phone":"+49 531/337565",
    "sg:postcode":"38102",
    "sg:province":"Niedersachsen",
    "wof:name":"Cottonn More Peter Pape",
    "wof:placetype":"venue"
},
  "geometry": {"coordinates":[10.546090126,52.2662734985],"type":"Point"}
}