{
  "type": "Feature",
  "properties": {
    "iso:country":"DE",
    "sg:address":"Neckarauer Str. 136",
    "sg:city":"Mannheim",
    "sg:phone":"+49 621/817901",
    "sg:postcode":"68163",
    "sg:province":"Baden-W\u00fcrttemberg",
    "wof:name":"Neukauf",
    "wof:placetype":"venue"
},
  "geometry": {"coordinates":[8.4876270294,49.464553833],"type":"Point"}
}