{
  "type": "Feature",
  "properties": {
    "iso:country":"DE",
    "sg:address":"Sch\u00fcchtermannstr. 213",
    "sg:city":"Herne",
    "sg:phone":"+49 2323/81819",
    "sg:postcode":"44628",
    "sg:province":"Nordrhein-Westfalen",
    "wof:name":"Mittrop",
    "wof:placetype":"venue"
},
  "geometry": {"coordinates":[7.231584,51.550255],"type":"Point"}
}