{
  "type": "Feature",
  "properties": {
    "iso:country":"DE",
    "sg:address":"Ahornstr. 6",
    "sg:city":"Kolitzheim",
    "sg:phone":"+49 9385/97200",
    "sg:postcode":"97509",
    "sg:province":"Bayern",
    "wof:name":"Ahorn-apotheke",
    "wof:placetype":"venue"
},
  "geometry": {"coordinates":[10.240633,49.918713],"type":"Point"}
}