{
  "type": "Feature",
  "properties": {
    "iso:country":"DE",
    "sg:address":"Daimlerstr. 1 a",
    "sg:city":"Hessisch Lichtenau",
    "sg:phone":"+49 5602/4658",
    "sg:postcode":"37235",
    "sg:province":"Hessen",
    "wof:name":"Wiese",
    "wof:placetype":"venue"
},
  "geometry": {"coordinates":[9.7067632675,51.2251968384],"type":"Point"}
}