{
  "type": "Feature",
  "properties": {
    "iso:country":"DE",
    "sg:address":"K\u00f6nigsplatz 27",
    "sg:city":"Schwabach",
    "sg:phone":"+49 9122/84084",
    "sg:postcode":"91126",
    "sg:province":"Bayern",
    "wof:name":"Commerzbank Ag",
    "wof:placetype":"venue"
},
  "geometry": {"coordinates":[11.021305,49.32869],"type":"Point"}
}