{
  "type": "Feature",
  "properties": {
    "iso:country":"DE",
    "sg:address":"F\u00f6rsterweg 18",
    "sg:city":"Barntrup",
    "sg:phone":"+49 5263/2885",
    "sg:postcode":"32683",
    "sg:province":"Nordrhein-Westfalen",
    "wof:name":"Heinrich Hagemeier M\u00f6bel",
    "wof:placetype":"venue"
},
  "geometry": {"coordinates":[9.131646,51.988186],"type":"Point"}
}