{
  "type": "Feature",
  "properties": {
    "iso:country":"DE",
    "sg:address":"Kardinal-Faulhaber-Str. 2",
    "sg:city":"Planegg",
    "sg:phone":"+49 89/8596797",
    "sg:postcode":"82152",
    "sg:province":"Bayern",
    "wof:name":"J\u00e4ger Wohnbau Gmbh",
    "wof:placetype":"venue"
},
  "geometry": {"coordinates":[11.426697,48.102184],"type":"Point"}
}