{
  "type": "Feature",
  "properties": {
    "iso:country":"DE",
    "sg:address":"Mainzer Landstr. 633",
    "sg:city":"Frankfurt",
    "sg:postcode":"65933",
    "sg:province":"Hessen",
    "wof:name":"Foto Lohmann Gmbh",
    "wof:placetype":"venue"
},
  "geometry": {"coordinates":[8.5915136337,50.099899292],"type":"Point"}
}