{
  "type": "Feature",
  "properties": {
    "iso:country":"DE",
    "sg:address":"Am Bahnhof",
    "sg:city":"Estedt",
    "sg:postcode":"39638",
    "sg:province":"Sachsen-Anhalt",
    "wof:name":"Kraftverkehr Gmbh",
    "wof:placetype":"venue"
},
  "geometry": {"coordinates":[11.357665,52.575142],"type":"Point"}
}