{
  "type": "Feature",
  "properties": {
    "iso:country":"DE",
    "sg:address":"Oststr. 11",
    "sg:city":"Halberstadt",
    "sg:phone":"+49 3941/608090",
    "sg:postcode":"38820",
    "sg:province":"Sachsen-Anhalt",
    "wof:name":"Hydraulikwerkstatt Soyke Gmbh",
    "wof:placetype":"venue"
},
  "geometry": {"coordinates":[11.0644845963,51.8844604492],"type":"Point"}
}