{
  "type": "Feature",
  "properties": {
    "iso:country":"DE",
    "sg:address":"Magdeburger Str. 88 B",
    "sg:city":"Calbe",
    "sg:phone":"+49 39291/4290",
    "sg:postcode":"39240",
    "sg:province":"Sachsen-Anhalt",
    "wof:name":"Industrie- Und Stra\u00dfenbau Calbe Gmbh",
    "wof:placetype":"venue"
},
  "geometry": {"coordinates":[11.8869018555,51.915763855],"type":"Point"}
}