{
  "type": "Feature",
  "properties": {
    "iso:country":"DE",
    "sg:address":"Hauptstr. 120",
    "sg:city":"Rehlingen-Siersburg",
    "sg:phone":"+49 6835/50240",
    "sg:postcode":"66780",
    "sg:province":"Saarland",
    "wof:name":"Knauf Gips Kg",
    "wof:placetype":"venue"
},
  "geometry": {"coordinates":[6.6814551353,49.3769416809],"type":"Point"}
}