{
  "type": "Feature",
  "properties": {
    "iso:country":"DE",
    "sg:address":"G\u00fcldenfeldstr. 39",
    "sg:city":"Harmsdorf",
    "sg:phone":"+49 4363/3101",
    "sg:postcode":"23738",
    "sg:province":"Schleswig-Holstein",
    "wof:name":"Hans-j\u00fcrgen Kolbe",
    "wof:placetype":"venue"
},
  "geometry": {"coordinates":[10.8407621384,54.2385368347],"type":"Point"}
}