{
  "type": "Feature",
  "properties": {
    "iso:country":"DE",
    "sg:address":"Nuhnetalstr. 62",
    "sg:city":"Winterberg",
    "sg:phone":"+49 2981/6194",
    "sg:postcode":"59955",
    "sg:province":"Nordrhein-Westfalen",
    "wof:name":"K.-h. Reinecke",
    "wof:placetype":"venue"
},
  "geometry": {"coordinates":[8.55869,51.16151],"type":"Point"}
}