{
  "type": "Feature",
  "properties": {
    "iso:country":"DE",
    "sg:address":"Maximilianstr. 16",
    "sg:city":"Berchtesgaden",
    "sg:phone":"+49 8652/2384",
    "sg:postcode":"83471",
    "sg:province":"Bayern",
    "wof:name":"Christa Irlinger",
    "wof:placetype":"venue"
},
  "geometry": {"coordinates":[13.0003480911,47.6288299561],"type":"Point"}
}