{
  "type": "Feature",
  "properties": {
    "iso:country":"DE",
    "sg:address":"Blasenbergstr. 28",
    "sg:city":"Ammerbuch",
    "sg:phone":"+49 7073/886",
    "sg:postcode":"72119",
    "sg:province":"Baden-W\u00fcrttemberg",
    "wof:name":"Helmut Flaisch",
    "wof:placetype":"venue"
},
  "geometry": {"coordinates":[8.941413,48.53484],"type":"Point"}
}