{
  "type": "Feature",
  "properties": {
    "iso:country":"DE",
    "sg:address":"W\u00fcstenbrander Str. 7",
    "sg:city":"Oberlungwitz",
    "sg:phone":"+49 3723/69350",
    "sg:postcode":"09353",
    "sg:province":"Sachsen",
    "wof:name":"Htc-f\u00f6rdertechnik- Hebetechnik-handels-gmbh",
    "wof:placetype":"venue"
},
  "geometry": {"coordinates":[12.6865930557,50.7876281738],"type":"Point"}
}