{
  "type": "Feature",
  "properties": {
    "iso:country":"DE",
    "sg:address":"Salierstr. 29",
    "sg:city":"M\u00fchlacker",
    "sg:phone":"+49 7041/2337",
    "sg:postcode":"75417",
    "sg:province":"Baden-W\u00fcrttemberg",
    "wof:name":"Elektro Adolf Lehr",
    "wof:placetype":"venue"
},
  "geometry": {"coordinates":[8.857408,48.974258],"type":"Point"}
}