{
  "type": "Feature",
  "properties": {
    "iso:country":"DE",
    "sg:address":"Eifelstr.23",
    "sg:city":"Aachen",
    "sg:phone":"+49 241/542818",
    "sg:postcode":"52068",
    "sg:province":"Nordrhein-Westfalen",
    "wof:name":"1ac Baubewertung Ruhrmann",
    "wof:placetype":"venue"
},
  "geometry": {"coordinates":[6.1107878685,50.7747306824],"type":"Point"}
}