{
  "type": "Feature",
  "properties": {
    "iso:country":"DE",
    "sg:address":"Hauptstr. 14",
    "sg:city":"Furtwangen",
    "sg:phone":"+49 7723/2489",
    "sg:postcode":"78120",
    "sg:province":"Baden-W\u00fcrttemberg",
    "wof:name":"Wilhelm Kreuz",
    "wof:placetype":"venue"
},
  "geometry": {"coordinates":[8.1755,48.023224],"type":"Point"}
}