{
  "type": "Feature",
  "properties": {
    "iso:country":"DE",
    "sg:address":"Kraibergstr. 4",
    "sg:city":"Baunach",
    "sg:phone":"+49 9544/980681",
    "sg:postcode":"96148",
    "sg:province":"Bayern",
    "wof:name":"Ruh Systeme Gmbh",
    "wof:placetype":"venue"
},
  "geometry": {"coordinates":[10.855298996,49.9916191101],"type":"Point"}
}