{
  "type": "Feature",
  "properties": {
    "iso:country":"DE",
    "sg:address":"Harburger Str. 69",
    "sg:city":"Celle",
    "sg:phone":"+49 5141/33621",
    "sg:postcode":"29223",
    "sg:province":"Niedersachsen",
    "wof:name":"Wilhelm Hundertmark",
    "wof:placetype":"venue"
},
  "geometry": {"coordinates":[10.080316,52.633827],"type":"Point"}
}