{
  "type": "Feature",
  "properties": {
    "iso:country":"DE",
    "sg:address":"Richer Str. 4",
    "sg:city":"Gro\u00df-Umstadt",
    "sg:phone":"+49 6078/73931",
    "sg:postcode":"64823",
    "sg:province":"Hessen",
    "wof:name":"Emma R\u00f6themeyer Ergotherapeutsche Praxis",
    "wof:placetype":"venue"
},
  "geometry": {"coordinates":[8.93222,49.871552],"type":"Point"}
}