{
  "type": "Feature",
  "properties": {
    "iso:country":"DE",
    "sg:address":"Klingener Str.",
    "sg:city":"Billigheim-Ingenheim",
    "sg:phone":"+49 6349/6145",
    "sg:postcode":"76831",
    "sg:province":"Rheinland-Pfalz",
    "wof:name":"Schwimmbad",
    "wof:placetype":"venue"
},
  "geometry": {"coordinates":[8.0769691467,49.1358184814],"type":"Point"}
}