{
  "type": "Feature",
  "properties": {
    "iso:country":"DE",
    "sg:address":"Dierdorfer Stra\u00dfe 93",
    "sg:city":"Neuwied",
    "sg:phone":"+49 2631/23693",
    "sg:postcode":"56564",
    "sg:province":"Rheinland-Pfalz",
    "wof:name":"Orthop\u00e4die-schuhtechnik Bruno Pieper",
    "wof:placetype":"venue"
},
  "geometry": {"coordinates":[7.471387,50.439178],"type":"Point"}
}