{
  "type": "Feature",
  "properties": {
    "iso:country":"DE",
    "sg:address":"Itzelstein 43",
    "sg:city":"Brilon",
    "sg:phone":"+49 2961/3616",
    "sg:postcode":"59929",
    "sg:province":"Nordrhein-Westfalen",
    "wof:name":"J\u00fcrgen Albers Architekt",
    "wof:placetype":"venue"
},
  "geometry": {"coordinates":[8.570079,51.383423],"type":"Point"}
}