{
  "type": "Feature",
  "properties": {
    "iso:country":"DE",
    "sg:address":"Am Kirschberg 36",
    "sg:city":"Dresden",
    "sg:phone":"+49 351/4116130",
    "sg:postcode":"01187",
    "sg:province":"Sachsen",
    "wof:name":"Dr. Med. Brigitte D\u00fcnkel",
    "wof:placetype":"venue"
},
  "geometry": {"coordinates":[13.693161,51.028931],"type":"Point"}
}