{
  "type": "Feature",
  "properties": {
    "iso:country":"DE",
    "sg:address":"Neue Leipziger Str. 18",
    "sg:city":"Leipzig",
    "sg:postcode":"04205",
    "sg:province":"Sachsen",
    "wof:name":"Norbert Schumann",
    "wof:placetype":"venue"
},
  "geometry": {"coordinates":[12.2661180496,51.3183860779],"type":"Point"}
}