{
  "type": "Feature",
  "properties": {
    "iso:country":"DE",
    "sg:address":"Rheingasse 18",
    "sg:city":"Bonn",
    "sg:phone":"+49 228/633460",
    "sg:postcode":"53113",
    "sg:province":"Nordrhein-Westfalen",
    "wof:name":"Cafe Und Konditorei Wilhelm Kleimann",
    "wof:placetype":"venue"
},
  "geometry": {"coordinates":[7.1064591408,50.7359580994],"type":"Point"}
}