{
  "type": "Feature",
  "properties": {
    "iso:country":"DE",
    "sg:address":"Frankensteiner Stra\u00dfe 27",
    "sg:city":"Darmstadt",
    "sg:phone":"+49 6151/943835",
    "sg:postcode":"64297",
    "sg:province":"Hessen",
    "wof:name":"Khb Softwareentwicklungs Gmbh",
    "wof:placetype":"venue"
},
  "geometry": {"coordinates":[8.65731,49.807011],"type":"Point"}
}