{
  "type": "Feature",
  "properties": {
    "iso:country":"DE",
    "sg:address":"Schubertstr. 4",
    "sg:city":"Alzenau",
    "sg:phone":"+49 6023/1631",
    "sg:postcode":"63755",
    "sg:province":"Bayern",
    "wof:name":"Friedrich Gerber Architekt",
    "wof:placetype":"venue"
},
  "geometry": {"coordinates":[9.069244,50.079735],"type":"Point"}
}