{
  "type": "Feature",
  "properties": {
    "iso:country":"DE",
    "sg:address":"Charlottenstr. 79",
    "sg:city":"Berlin",
    "sg:postcode":"10117",
    "sg:province":"Berlin",
    "wof:name":"Inex Industrieservice Gmbh",
    "wof:placetype":"venue"
},
  "geometry": {"coordinates":[13.39201,52.508137],"type":"Point"}
}