{
  "type": "Feature",
  "properties": {
    "iso:country":"DE",
    "sg:address":"Weender Landstr. 25",
    "sg:city":"G\u00f6ttingen",
    "sg:phone":"+49 551/42635",
    "sg:postcode":"37073",
    "sg:province":"Niedersachsen",
    "wof:name":"Hans Rainer Brosselt",
    "wof:placetype":"venue"
},
  "geometry": {"coordinates":[9.932607,51.54163],"type":"Point"}
}