{
  "type": "Feature",
  "properties": {
    "iso:country":"DE",
    "sg:address":"Rosenstr. 40",
    "sg:city":"Magstadt",
    "sg:phone":"+49 7159/42455",
    "sg:postcode":"71106",
    "sg:province":"Baden-W\u00fcrttemberg",
    "wof:name":"Otto Schmidt",
    "wof:placetype":"venue"
},
  "geometry": {"coordinates":[8.9664316177,48.7454147339],"type":"Point"}
}