{
  "type": "Feature",
  "properties": {
    "iso:country":"DE",
    "sg:address":"Pfarrwiese 56",
    "sg:city":"Bad Grund",
    "sg:phone":"+49 5327/83820",
    "sg:postcode":"37539",
    "sg:province":"Niedersachsen",
    "wof:name":"Waldesruh",
    "wof:placetype":"venue"
},
  "geometry": {"coordinates":[10.2520847321,51.80727005],"type":"Point"}
}