{
  "type": "Feature",
  "properties": {
    "iso:country":"DE",
    "sg:address":"Schabbecke 43",
    "sg:city":"Vreden",
    "sg:phone":"+49 2564/31589",
    "sg:postcode":"48691",
    "sg:province":"Nordrhein-Westfalen",
    "wof:name":"Dr. Michael D\u00f6dt Tierarzt",
    "wof:placetype":"venue"
},
  "geometry": {"coordinates":[6.8308868408,52.0310516357],"type":"Point"}
}