{
  "type": "Feature",
  "properties": {
    "iso:country":"DE",
    "sg:address":"Bahnhofstr. 3",
    "sg:city":"Uslar",
    "sg:phone":"+49 5571/2601",
    "sg:postcode":"37170",
    "sg:province":"Niedersachsen",
    "wof:name":"Taxi-j\u00f6rn",
    "wof:placetype":"venue"
},
  "geometry": {"coordinates":[9.6406230927,51.6585884094],"type":"Point"}
}