{
  "type": "Feature",
  "properties": {
    "iso:country":"DE",
    "sg:address":"Maubisstr. 31",
    "sg:city":"Kaarst",
    "sg:phone":"+49 2131/64269",
    "sg:postcode":"41564",
    "sg:province":"Nordrhein-Westfalen",
    "wof:name":"Rudolf Herok Masseur",
    "wof:placetype":"venue"
},
  "geometry": {"coordinates":[6.619993,51.228481],"type":"Point"}
}