{
  "type": "Feature",
  "properties": {
    "iso:country":"DE",
    "sg:address":"Gewerbepark 6",
    "sg:city":"Hamm",
    "sg:phone":"+49 2385/8554",
    "sg:postcode":"59069",
    "sg:province":"Nordrhein-Westfalen",
    "wof:name":"Arnold Scholz",
    "wof:placetype":"venue"
},
  "geometry": {"coordinates":[7.850186,51.623787],"type":"Point"}
}