{
  "type": "Feature",
  "properties": {
    "iso:country":"DE",
    "sg:address":"Hohewartstr 131",
    "sg:city":"Stuttgart",
    "sg:phone":"+49 711/814459",
    "sg:postcode":"70469",
    "sg:province":"Baden-W\u00fcrttemberg",
    "wof:name":"Dr. Kerner Gmbh & Co Kg",
    "wof:placetype":"venue"
},
  "geometry": {"coordinates":[9.138295,48.80283],"type":"Point"}
}