{
  "type": "Feature",
  "properties": {
    "iso:country":"DE",
    "sg:address":"Corbiestr. 23::",
    "sg:city":"Hoexter",
    "sg:phone":"+49 4952/719600",
    "sg:postcode":"37671",
    "sg:province":"Nordrhein-Westfalen",
    "wof:name":"Volksbank Hoexter-beverungen Eg",
    "wof:placetype":"venue"
},
  "geometry": {"coordinates":[9.383883,51.776527],"type":"Point"}
}