{
  "type": "Feature",
  "properties": {
    "iso:country":"DE",
    "sg:address":"Trivastr. 21",
    "sg:city":"M\u00fcnchen",
    "sg:phone":"+49 89/154991",
    "sg:postcode":"80637",
    "sg:province":"Bayern",
    "wof:name":"Asap Software Gmbh",
    "wof:placetype":"venue"
},
  "geometry": {"coordinates":[11.5408296585,48.1614723206],"type":"Point"}
}