{
  "type": "Feature",
  "properties": {
    "iso:country":"DE",
    "sg:address":"Breite Str. 1",
    "sg:city":"Bad Harzburg",
    "sg:phone":"+49 5322/8474",
    "sg:postcode":"38667",
    "sg:province":"Niedersachsen",
    "wof:name":"Heidemarie Puchta Ergotherapiepraxis",
    "wof:placetype":"venue"
},
  "geometry": {"coordinates":[10.537201,51.882069],"type":"Point"}
}