{
  "type": "Feature",
  "properties": {
    "iso:country":"DE",
    "sg:address":"Salzunger Str.",
    "sg:city":"Merkers",
    "sg:phone":"+49 36969/50341",
    "sg:postcode":"36460",
    "sg:province":"Th\u00fcringen",
    "wof:name":"Bahnhof",
    "wof:placetype":"venue"
},
  "geometry": {"coordinates":[10.1154699326,50.8254127502],"type":"Point"}
}