{
  "type": "Feature",
  "properties": {
    "iso:country":"DE",
    "sg:address":"Morsumer Weg 16",
    "sg:city":"Hamburg",
    "sg:phone":"+49 40/7129377",
    "sg:postcode":"22117",
    "sg:province":"Hamburg",
    "wof:name":"Manfred Kaulbarsch Verwaltungsgesellschaft Mbh",
    "wof:placetype":"venue"
},
  "geometry": {"coordinates":[10.1404056549,53.5402297974],"type":"Point"}
}