{
  "type": "Feature",
  "properties": {
    "iso:country":"DE",
    "sg:address":"Pappelallee 18",
    "sg:city":"Karlsruhe",
    "sg:phone":"+49 721/574480",
    "sg:postcode":"76189",
    "sg:province":"Baden-W\u00fcrttemberg",
    "wof:name":"G\u00fcnther Karl Ohg",
    "wof:placetype":"venue"
},
  "geometry": {"coordinates":[8.3358869553,48.9966468811],"type":"Point"}
}