{
  "type": "Feature",
  "properties": {
    "iso:country":"DE",
    "sg:address":"Messinger Str. 4",
    "sg:city":"L\u00fcnne",
    "sg:postcode":"48480",
    "sg:province":"Niedersachsen",
    "wof:name":"Forstreuter Stra\u00dfen- Und Tiefbau Gmbh & Co. Kg",
    "wof:placetype":"venue"
},
  "geometry": {"coordinates":[7.4279379845,52.4360351562],"type":"Point"}
}