{
  "type": "Feature",
  "properties": {
    "iso:country":"DE",
    "sg:address":"Im Thal 10",
    "sg:city":"Penzberg",
    "sg:phone":"+49 8856/7802",
    "sg:postcode":"82377",
    "sg:province":"Bayern",
    "wof:name":"Dr. Med. Christoph Striebeck Arzt F\u00fcr Allgemeinmedizin",
    "wof:placetype":"venue"
},
  "geometry": {"coordinates":[11.3796854019,47.755607605],"type":"Point"}
}