{
  "type": "Feature",
  "properties": {
    "iso:country":"DE",
    "sg:address":"Mindener Str. 13",
    "sg:city":"Petershagen",
    "sg:phone":"+49 5707/307",
    "sg:postcode":"32469",
    "sg:province":"Nordrhein-Westfalen",
    "wof:name":"Griechisches-spezialit\u00e4ten- Restaurant",
    "wof:placetype":"venue"
},
  "geometry": {"coordinates":[8.9707336426,52.3774642944],"type":"Point"}
}