{
  "type": "Feature",
  "properties": {
    "iso:country":"DE",
    "sg:address":"Lange Str. 96c",
    "sg:city":"Sulingen",
    "sg:phone":"+49 4271/4708",
    "sg:postcode":"27232",
    "sg:province":"Niedersachsen",
    "wof:name":"Sb-polsterm\u00f6belhallen Gmbh",
    "wof:placetype":"venue"
},
  "geometry": {"coordinates":[8.795501709,52.6810531616],"type":"Point"}
}