{
  "type": "Feature",
  "properties": {
    "iso:country":"DE",
    "sg:address":"Toyota-Allee 5",
    "sg:city":"K\u00f6ln",
    "sg:phone":"+49 2234/10230",
    "sg:postcode":"50858",
    "sg:province":"Nordrhein-Westfalen",
    "wof:name":"Toyota Informations- Systeme Gmbh",
    "wof:placetype":"venue"
},
  "geometry": {"coordinates":[6.8647379875,50.9157867432],"type":"Point"}
}