{
  "type": "Feature",
  "properties": {
    "iso:country":"DE",
    "sg:address":"Paul-Gerhardt-Str. 11",
    "sg:city":"Wiesbaden",
    "sg:phone":"+49 611/464133",
    "sg:postcode":"65199",
    "sg:province":"Hessen",
    "wof:name":"Heinrich Willer",
    "wof:placetype":"venue"
},
  "geometry": {"coordinates":[8.1967782974,50.0856895447],"type":"Point"}
}