{
  "type": "Feature",
  "properties": {
    "iso:country":"DE",
    "sg:address":"Hermann-Kirchhoff-Str. 2",
    "sg:city":"Paderborn",
    "sg:phone":"+49 5254/940309",
    "sg:postcode":"33102",
    "sg:province":"Nordrhein-Westfalen",
    "wof:name":"Frank Stratmann",
    "wof:placetype":"venue"
},
  "geometry": {"coordinates":[8.7493448257,51.7335090637],"type":"Point"}
}