{
  "type": "Feature",
  "properties": {
    "iso:country":"DE",
    "sg:address":"Angelser Str. 30",
    "sg:city":"Weyhe",
    "sg:phone":"+49 421/807990",
    "sg:postcode":"28844",
    "sg:province":"Niedersachsen",
    "wof:name":"Paul Guse & Sohn Gmbh & Co. Kg",
    "wof:placetype":"venue"
},
  "geometry": {"coordinates":[8.7918252945,52.986541748],"type":"Point"}
}