{
  "type": "Feature",
  "properties": {
    "iso:country":"DE",
    "sg:address":"Friedr-Werthmann-Siedl 19",
    "sg:city":"Hettstedt",
    "sg:phone":"+49 3476/813028",
    "sg:postcode":"06333",
    "sg:province":"Sachsen-Anhalt",
    "wof:name":"Dieter Schalk",
    "wof:placetype":"venue"
},
  "geometry": {"coordinates":[11.5251808167,51.6452903748],"type":"Point"}
}