{
  "type": "Feature",
  "properties": {
    "iso:country":"DE",
    "sg:address":"Zur Gro\u00dfen Heide 22",
    "sg:city":"G\u00fctersloh",
    "sg:phone":"+49 5209/2805",
    "sg:postcode":"33335",
    "sg:province":"Nordrhein-Westfalen",
    "wof:name":"Inn Holsken",
    "wof:placetype":"venue"
},
  "geometry": {"coordinates":[8.4756793976,51.9389762878],"type":"Point"}
}