{
  "type": "Feature",
  "properties": {
    "iso:country":"DE",
    "sg:address":"Kreuzmattstr. 18",
    "sg:city":"Todtnau",
    "sg:phone":"+49 7671/623",
    "sg:postcode":"79674",
    "sg:province":"Baden-W\u00fcrttemberg",
    "wof:name":"Pension H. Schubnell",
    "wof:placetype":"venue"
},
  "geometry": {"coordinates":[7.9407529831,47.850643158],"type":"Point"}
}