{
  "type": "Feature",
  "properties": {
    "iso:country":"DE",
    "sg:address":"Ziegelstr. 14",
    "sg:city":"Dillingen",
    "sg:phone":"+49 9071/9021",
    "sg:postcode":"89407",
    "sg:province":"Bayern",
    "wof:name":"Probst Und Ludwig Rechtsanw\u00e4lte",
    "wof:placetype":"venue"
},
  "geometry": {"coordinates":[10.485502243,48.5772819519],"type":"Point"}
}