{
  "type": "Feature",
  "properties": {
    "iso:country":"DE",
    "sg:address":"Bahnhofstr. 20",
    "sg:city":"Holzminden",
    "sg:phone":"+49 5531/4625",
    "sg:postcode":"37603",
    "sg:province":"Niedersachsen",
    "wof:name":"China-restaurant Hongkong",
    "wof:placetype":"venue"
},
  "geometry": {"coordinates":[9.4518480301,51.8231925964],"type":"Point"}
}