{
  "type": "Feature",
  "properties": {
    "iso:country":"DE",
    "sg:address":"Seedeichstr. 3",
    "sg:city":"Wangerland",
    "sg:phone":"+49 4463/5423",
    "sg:postcode":"26434",
    "sg:province":"Niedersachsen",
    "wof:name":"Wolf-dieter Peters",
    "wof:placetype":"venue"
},
  "geometry": {"coordinates":[7.9011669159,53.6993255615],"type":"Point"}
}