{
  "type": "Feature",
  "properties": {
    "iso:country":"DE",
    "sg:address":"Schmiedeweg 5",
    "sg:city":"Solingen",
    "sg:phone":"+49 212/814064",
    "sg:postcode":"42655",
    "sg:province":"Nordrhein-Westfalen",
    "wof:name":"H. P. Dennerl\u00f6hr Steuerberater",
    "wof:placetype":"venue"
},
  "geometry": {"coordinates":[7.0656528473,51.1645469666],"type":"Point"}
}