{
  "type": "Feature",
  "properties": {
    "iso:country":"DE",
    "sg:address":"Simeonstr. 27",
    "sg:city":"Minden",
    "sg:phone":"+49 571/28839",
    "sg:postcode":"32423",
    "sg:province":"Nordrhein-Westfalen",
    "wof:name":"Mindener Stuben",
    "wof:placetype":"venue"
},
  "geometry": {"coordinates":[8.9132061005,52.285282135],"type":"Point"}
}