{
  "type": "Feature",
  "properties": {
    "iso:country":"DE",
    "sg:address":"Stadtweg 95",
    "sg:city":"Magdeburg",
    "sg:postcode":"39116",
    "sg:province":"Sachsen-Anhalt",
    "wof:name":"Wolfgang Giebel",
    "wof:placetype":"venue"
},
  "geometry": {"coordinates":[11.585938,52.090649],"type":"Point"}
}