{
  "type": "Feature",
  "properties": {
    "iso:country":"DE",
    "sg:address":"Niedersachsenstr 11",
    "sg:city":"Cuxhaven",
    "sg:phone":"+49 4721/21081",
    "sg:postcode":"27472",
    "sg:province":"Niedersachsen",
    "wof:name":"Kutterfisch-zentrale Gmbh",
    "wof:placetype":"venue"
},
  "geometry": {"coordinates":[8.7132511139,53.8594017029],"type":"Point"}
}