{
  "type": "Feature",
  "properties": {
    "iso:country":"DE",
    "sg:address":"Pankstr. 8",
    "sg:city":"Berlin",
    "sg:phone":"+49 30/4742755",
    "sg:postcode":"13127",
    "sg:province":"Berlin",
    "wof:name":"Detlef Teschner Gmbh",
    "wof:placetype":"venue"
},
  "geometry": {"coordinates":[13.439473,52.593452],"type":"Point"}
}