{
  "type": "Feature",
  "properties": {
    "iso:country":"DE",
    "sg:address":"Volksdorfer Damm 2",
    "sg:city":"Hamburg",
    "sg:phone":"+49 40/6034804",
    "sg:postcode":"22359",
    "sg:province":"Hamburg",
    "wof:name":"Eis-gondel",
    "wof:placetype":"venue"
},
  "geometry": {"coordinates":[10.15476,53.661812],"type":"Point"}
}