{
  "type": "Feature",
  "properties": {
    "iso:country":"DE",
    "sg:address":"Schlei\u00dfheimer Str. 437",
    "sg:city":"M\u00fcnchen",
    "sg:phone":"+49 89/3137071",
    "sg:postcode":"80935",
    "sg:province":"Bayern",
    "wof:name":"Gerhard Senge Farben-tapeten-bodenbel\u00e4ge",
    "wof:placetype":"venue"
},
  "geometry": {"coordinates":[11.5630025864,48.2074813843],"type":"Point"}
}