{
  "type": "Feature",
  "properties": {
    "iso:country":"DE",
    "sg:address":"Lauschaer Str. 1 a",
    "sg:city":"Steinach",
    "sg:phone":"+49 36762/32291",
    "sg:postcode":"96523",
    "sg:province":"Th\u00fcringen",
    "wof:name":"W. Fuchs",
    "wof:placetype":"venue"
},
  "geometry": {"coordinates":[11.1550931931,50.4354057312],"type":"Point"}
}