{
  "type": "Feature",
  "properties": {
    "iso:country":"DE",
    "sg:address":"Ringstra\u00dfe 12",
    "sg:city":"Eichenau",
    "sg:phone":"+49 8141/80061",
    "sg:postcode":"82223",
    "sg:province":"Bayern",
    "wof:name":"Leasing S\u00fcd,kehl Und Schu\u00dfmann,berechnung Leasingrate Online",
    "wof:placetype":"venue"
},
  "geometry": {"coordinates":[11.3234224319,48.158618927],"type":"Point"}
}