{
  "type": "Feature",
  "properties": {
    "iso:country":"DE",
    "sg:city":"Stuttgart",
    "sg:phone":"+49 711/3008310",
    "sg:postcode":"70372",
    "sg:province":"Baden-W\u00fcrttemberg",
    "wof:name":"M.i.r.o.",
    "wof:placetype":"venue"
},
  "geometry": {"coordinates":[9.214116,48.805676],"type":"Point"}
}