{
  "type": "Feature",
  "properties": {
    "iso:country":"DE",
    "sg:address":"Traxenberg 2",
    "sg:city":"Thurmansbang",
    "sg:phone":"+49 9907/912",
    "sg:postcode":"94169",
    "sg:province":"Bayern",
    "wof:name":"Hotel Landgut Traxenberg",
    "wof:placetype":"venue"
},
  "geometry": {"coordinates":[13.2980642319,48.7637863159],"type":"Point"}
}