{
  "type": "Feature",
  "properties": {
    "iso:country":"DE",
    "sg:address":"Recklingh\u00e4user Str. 20",
    "sg:city":"Waltrop",
    "sg:phone":"+49 2309/608915",
    "sg:postcode":"45731",
    "sg:province":"Nordrhein-Westfalen",
    "wof:name":"Novum Est Gmbh",
    "wof:placetype":"venue"
},
  "geometry": {"coordinates":[7.3776431084,51.6211967468],"type":"Point"}
}