{
  "type": "Feature",
  "properties": {
    "iso:country":"DE",
    "sg:address":"Bahnhofstr. 1",
    "sg:city":"Pfullendorf",
    "sg:phone":"+49 7552/4673",
    "sg:postcode":"88630",
    "sg:province":"Baden-W\u00fcrttemberg",
    "wof:name":"Langer Inh. Harry Langer",
    "wof:placetype":"venue"
},
  "geometry": {"coordinates":[9.2540531158,47.9256706238],"type":"Point"}
}