{
  "type": "Feature",
  "properties": {
    "iso:country":"DE",
    "sg:address":"Waldweg 7c",
    "sg:city":"Gr\u00fcnwald",
    "sg:phone":"+49 89/6493380",
    "sg:postcode":"82031",
    "sg:province":"Bayern",
    "wof:name":"Wolff-ekkehardt Stein Komponist",
    "wof:placetype":"venue"
},
  "geometry": {"coordinates":[11.5377902985,48.0528030396],"type":"Point"}
}