{
  "type": "Feature",
  "properties": {
    "iso:country":"DE",
    "sg:address":"Schlo\u00dfstr. 6",
    "sg:city":"Gundelsheim",
    "sg:phone":"+49 6269/1591",
    "sg:postcode":"74831",
    "sg:province":"Baden-W\u00fcrttemberg",
    "wof:name":"A. Geudner",
    "wof:placetype":"venue"
},
  "geometry": {"coordinates":[9.159362,49.284832],"type":"Point"}
}