{
  "type": "Feature",
  "properties": {
    "iso:country":"DE",
    "sg:address":"Durchhausen",
    "sg:city":"Durchhausen",
    "sg:phone":"+49 4974/642813",
    "sg:postcode":"78591",
    "sg:province":"Baden-W\u00fcrttemberg",
    "wof:name":"Volksbank Trossingen Eg",
    "wof:placetype":"venue"
},
  "geometry": {"coordinates":[8.675455,48.039055],"type":"Point"}
}