{
  "type": "Feature",
  "properties": {
    "iso:country":"DE",
    "sg:address":"Bertha-Von-Suttner-Str. 9",
    "sg:city":"Bremen",
    "sg:phone":"+49 4942/1499750",
    "sg:postcode":"28207",
    "sg:province":"Bremen",
    "wof:name":"Rifox-hans Richter Gmbh Spezialarmaturen",
    "wof:placetype":"venue"
},
  "geometry": {"coordinates":[8.8631219864,53.0696029663],"type":"Point"}
}