{
  "type": "Feature",
  "properties": {
    "iso:country":"DE",
    "sg:address":"Jakobstr. 57",
    "sg:city":"Bergisch Gladbach",
    "sg:postcode":"51465",
    "sg:province":"Nordrhein-Westfalen",
    "wof:name":"Obi Bau- Und Heimwerkermarkt",
    "wof:placetype":"venue"
},
  "geometry": {"coordinates":[7.1194200516,50.9909095764],"type":"Point"}
}