{
  "type": "Feature",
  "properties": {
    "iso:country":"DE",
    "sg:address":"Albstr. 28",
    "sg:city":"Wendlingen",
    "sg:phone":"+49 7024/500219",
    "sg:postcode":"73240",
    "sg:province":"Baden-W\u00fcrttemberg",
    "wof:name":"Schorsch's Pub",
    "wof:placetype":"venue"
},
  "geometry": {"coordinates":[9.378531456,48.6718330383],"type":"Point"}
}