{
  "type": "Feature",
  "properties": {
    "iso:country":"DE",
    "sg:address":"Wolfskaulstr. 56 a",
    "sg:city":"Riegelsberg",
    "sg:phone":"+49 6806/2668",
    "sg:postcode":"66292",
    "sg:province":"Saarland",
    "wof:name":"Werner Heinz Masseur",
    "wof:placetype":"venue"
},
  "geometry": {"coordinates":[6.937995,49.297195],"type":"Point"}
}