{
  "type": "Feature",
  "properties": {
    "iso:country":"DE",
    "sg:address":"Universit\u00e4tsplatz 7",
    "sg:city":"Fulda",
    "sg:phone":"+49 4966/110901",
    "sg:postcode":"36037",
    "sg:province":"Hessen",
    "wof:name":"Dresdner Bank",
    "wof:placetype":"venue"
},
  "geometry": {"coordinates":[9.679787,50.550945],"type":"Point"}
}