{
  "type": "Feature",
  "properties": {
    "iso:country":"DE",
    "sg:address":"Zeppelinstr. 16",
    "sg:city":"M\u00fclheim",
    "sg:phone":"+49 208/371074",
    "sg:postcode":"45470",
    "sg:province":"Nordrhein-Westfalen",
    "wof:name":"Pizzeria Funghi",
    "wof:placetype":"venue"
},
  "geometry": {"coordinates":[6.900452137,51.4179992676],"type":"Point"}
}