{
  "type": "Feature",
  "properties": {
    "iso:country":"DE",
    "sg:address":"Rayener Str. 56",
    "sg:city":"Neukirchen-Vluyn",
    "sg:phone":"+49 2845/92543",
    "sg:postcode":"47506",
    "sg:province":"Nordrhein-Westfalen",
    "wof:name":"J. Und E. Altrock",
    "wof:placetype":"venue"
},
  "geometry": {"coordinates":[6.5285778046,51.4433517456],"type":"Point"}
}