{
  "type": "Feature",
  "properties": {
    "iso:country":"DE",
    "sg:address":"Bruhnstr. 28",
    "sg:city":"Ingolstadt",
    "sg:phone":"+49 841/87321",
    "sg:postcode":"85053",
    "sg:province":"Bayern",
    "wof:name":"Praxis-design Richard Willert E. K.",
    "wof:placetype":"venue"
},
  "geometry": {"coordinates":[11.479039,48.744946],"type":"Point"}
}