{
  "type": "Feature",
  "properties": {
    "iso:country":"DE",
    "sg:address":"Hirschgraben 7",
    "sg:city":"Wiesbaden",
    "sg:phone":"+49 611/526619",
    "sg:postcode":"65183",
    "sg:province":"Hessen",
    "wof:name":"Werner Kennig",
    "wof:placetype":"venue"
},
  "geometry": {"coordinates":[8.238158226,50.0850830078],"type":"Point"}
}