{
  "type": "Feature",
  "properties": {
    "iso:country":"DE",
    "sg:address":"Schraderstr. 34",
    "sg:city":"Frankenthal",
    "sg:phone":"+49 6233/44911",
    "sg:postcode":"67227",
    "sg:province":"Rheinland-Pfalz",
    "wof:name":"Norma Gmbh & Co. Kg Lebensmittelfilialbetrieb",
    "wof:placetype":"venue"
},
  "geometry": {"coordinates":[8.3513431549,49.5226554871],"type":"Point"}
}