{
  "type": "Feature",
  "properties": {
    "iso:country":"DE",
    "sg:address":"Hauptstr. 116",
    "sg:city":"Alfdorf",
    "sg:phone":"+49 7172/3890",
    "sg:postcode":"73553",
    "sg:province":"Baden-W\u00fcrttemberg",
    "wof:name":"Eugen M\u00fcrdter Inh. J. M\u00fcrdter",
    "wof:placetype":"venue"
},
  "geometry": {"coordinates":[9.7080001831,48.8419265747],"type":"Point"}
}