{
  "type": "Feature",
  "properties": {
    "iso:country":"DE",
    "sg:address":"Wiesenstr. 13",
    "sg:city":"Eichenau",
    "sg:phone":"+49 8141/818423",
    "sg:postcode":"82223",
    "sg:province":"Bayern",
    "wof:name":"Rupert Moll Gmbh",
    "wof:placetype":"venue"
},
  "geometry": {"coordinates":[11.325602,48.170971],"type":"Point"}
}