{
  "type": "Feature",
  "properties": {
    "iso:country":"DE",
    "sg:address":"Ludwigstr. 101",
    "sg:city":"Garmisch-Partenkirchen",
    "sg:phone":"+49 8821/4955",
    "sg:postcode":"82467",
    "sg:province":"Bayern",
    "wof:name":"Dominikus K\u00fcmmerle",
    "wof:placetype":"venue"
},
  "geometry": {"coordinates":[11.1069927216,47.4943466187],"type":"Point"}
}