{
  "type": "Feature",
  "properties": {
    "iso:country":"DE",
    "sg:address":"W\u00f6rg\u00f6tterplatz 2",
    "sg:city":"Bad Reichenhall",
    "sg:phone":"+49 8651/4300",
    "sg:postcode":"83435",
    "sg:province":"Bayern",
    "wof:name":"Roman Dienersberger",
    "wof:placetype":"venue"
},
  "geometry": {"coordinates":[12.875106,47.7229],"type":"Point"}
}