{
  "type": "Feature",
  "properties": {
    "iso:country":"DE",
    "sg:address":"Hargesheimer Landstr. 25",
    "sg:city":"Bad Kreuznach",
    "sg:phone":"+49 671/26194",
    "sg:postcode":"55545",
    "sg:province":"Rheinland-Pfalz",
    "wof:name":"Philipp Gangluff",
    "wof:placetype":"venue"
},
  "geometry": {"coordinates":[7.8277349472,49.8463668823],"type":"Point"}
}