{
  "type": "Feature",
  "properties": {
    "iso:country":"DE",
    "sg:address":"Moorstrich 11",
    "sg:city":"Jade",
    "sg:postcode":"26349",
    "sg:province":"Niedersachsen",
    "wof:name":"Gecoh E. K.",
    "wof:placetype":"venue"
},
  "geometry": {"coordinates":[8.1850404739,53.3297119141],"type":"Point"}
}