{
  "type": "Feature",
  "properties": {
    "iso:country":"DE",
    "sg:address":"Lange Str. 95",
    "sg:city":"Bremerhaven",
    "sg:phone":"+49 471/83823",
    "sg:postcode":"27580",
    "sg:province":"Bremen",
    "wof:name":"Blumenhaus Edda Staack Inh. Gabriele Siedenburg",
    "wof:placetype":"venue"
},
  "geometry": {"coordinates":[8.587642,53.563801],"type":"Point"}
}