{
  "type": "Feature",
  "properties": {
    "iso:country":"DE",
    "sg:address":"Berliner Str. 16",
    "sg:city":"G\u00f6rlitz",
    "sg:phone":"+49 3581/405329",
    "sg:postcode":"02826",
    "sg:province":"Sachsen",
    "wof:name":"Peter Lerche Sachverst\u00e4ndiger",
    "wof:placetype":"venue"
},
  "geometry": {"coordinates":[14.9828224182,51.1499595642],"type":"Point"}
}