{
  "type": "Feature",
  "properties": {
    "iso:country":"DE",
    "sg:address":"An den Teichen",
    "sg:city":"Einbeck",
    "sg:phone":"+49 5561/971171",
    "sg:postcode":"37574",
    "sg:province":"Niedersachsen",
    "wof:name":"Gastst\u00e4tte An Den Teichen",
    "wof:placetype":"venue"
},
  "geometry": {"coordinates":[9.9018239975,51.8330955505],"type":"Point"}
}