{
  "type": "Feature",
  "properties": {
    "iso:country":"DE",
    "sg:address":"Weinstr. 1 a",
    "sg:city":"Vogtsburg",
    "sg:phone":"+49 7662/6904",
    "sg:postcode":"79235",
    "sg:province":"Baden-W\u00fcrttemberg",
    "wof:name":"D. Sacherer",
    "wof:placetype":"venue"
},
  "geometry": {"coordinates":[7.684478,48.092918],"type":"Point"}
}