{
  "type": "Feature",
  "properties": {
    "iso:country":"DE",
    "sg:address":"Henkestra\u00dfe 127",
    "sg:city":"Erlangen",
    "sg:phone":"+49 941/2024700",
    "sg:postcode":"91052",
    "sg:province":"Bayern",
    "wof:name":"Siemens Vdo Automotive",
    "wof:placetype":"venue"
},
  "geometry": {"coordinates":[12.1003503799,49.0165214539],"type":"Point"}
}