{
  "type": "Feature",
  "properties": {
    "iso:country":"DE",
    "sg:address":"Im Langen Feld 25",
    "sg:city":"Halle",
    "sg:phone":"+49 345/4444396",
    "sg:postcode":"06130",
    "sg:province":"Sachsen-Anhalt",
    "wof:name":"Kesch Bau Gmbh",
    "wof:placetype":"venue"
},
  "geometry": {"coordinates":[11.970687,51.447979],"type":"Point"}
}