{
  "type": "Feature",
  "properties": {
    "iso:country":"DE",
    "sg:address":"Wiesenweg 4",
    "sg:city":"Hainewalde",
    "sg:phone":"+49 35841/2249",
    "sg:postcode":"02779",
    "sg:province":"Sachsen",
    "wof:name":"Christian Herfurth",
    "wof:placetype":"venue"
},
  "geometry": {"coordinates":[14.704518,50.909409],"type":"Point"}
}