{
  "type": "Feature",
  "properties": {
    "iso:country":"DE",
    "sg:address":"M\u00fcnstereifeler Str. 40",
    "sg:city":"Euskirchen",
    "sg:phone":"+49 2251/63548",
    "sg:postcode":"53879",
    "sg:province":"Nordrhein-Westfalen",
    "wof:name":"J\u00fcrgen Schwalb",
    "wof:placetype":"venue"
},
  "geometry": {"coordinates":[6.7879872322,50.6538963318],"type":"Point"}
}