{
  "type": "Feature",
  "properties": {
    "iso:country":"DE",
    "sg:address":"Textorstr. 22",
    "sg:city":"W\u00fcrzburg",
    "sg:phone":"+49 931/58333",
    "sg:postcode":"97070",
    "sg:province":"Bayern",
    "wof:name":"Karin Herrle",
    "wof:placetype":"venue"
},
  "geometry": {"coordinates":[9.935114,49.797272],"type":"Point"}
}