{
  "type": "Feature",
  "properties": {
    "iso:country":"DE",
    "sg:address":"Viehtriftstr. 14",
    "sg:city":"Speyer",
    "sg:phone":"+49 6232/36964",
    "sg:postcode":"67346",
    "sg:province":"Rheinland-Pfalz",
    "wof:name":"Erwin Wolf",
    "wof:placetype":"venue"
},
  "geometry": {"coordinates":[8.43237,49.329304],"type":"Point"}
}