{
  "type": "Feature",
  "properties": {
    "iso:country":"DE",
    "sg:address":"Bahnhofstr. 7",
    "sg:city":"G\u00f6ppingen",
    "sg:phone":"+49 7161",
    "sg:postcode":"73033",
    "sg:province":"Baden-W\u00fcrttemberg",
    "wof:name":"Immobilienb\u00fcro Hugo Baumann",
    "wof:placetype":"venue"
},
  "geometry": {"coordinates":[9.6515693665,48.7017059326],"type":"Point"}
}