{
  "type": "Feature",
  "properties": {
    "iso:country":"DE",
    "sg:address":"Schillstr. 7a",
    "sg:city":"Offenbach",
    "sg:postcode":"63067",
    "sg:province":"Hessen",
    "wof:name":"Sypra Systeme F\u00fcr Proze\u00dfauto- Mation Und Informations-",
    "wof:placetype":"venue"
},
  "geometry": {"coordinates":[8.749048233,50.1013031006],"type":"Point"}
}