{
  "type": "Feature",
  "properties": {
    "iso:country":"DE",
    "sg:address":"Die\u00dfemer Str. 137",
    "sg:city":"Krefeld",
    "sg:phone":"+49 2151/20451",
    "sg:postcode":"47799",
    "sg:province":"Nordrhein-Westfalen",
    "wof:name":"Hans Jacobs",
    "wof:placetype":"venue"
},
  "geometry": {"coordinates":[6.5754799843,51.334148407],"type":"Point"}
}