{
  "type": "Feature",
  "properties": {
    "iso:country":"DE",
    "sg:address":"Altperverstr. 88a",
    "sg:city":"Salzwedel",
    "sg:postcode":"29410",
    "sg:province":"Sachsen-Anhalt",
    "wof:name":"Tectum - Service Am Bau Gmbh",
    "wof:placetype":"venue"
},
  "geometry": {"coordinates":[11.158208,52.846989],"type":"Point"}
}