{
  "type": "Feature",
  "properties": {
    "iso:country":"DE",
    "sg:address":"Hauptstr. 66a",
    "sg:city":"Wachau",
    "sg:postcode":"01454",
    "sg:province":"Sachsen",
    "wof:name":"Evangelisches Pfarramt",
    "wof:placetype":"venue"
},
  "geometry": {"coordinates":[13.9043617249,51.1574745178],"type":"Point"}
}