{
  "type": "Feature",
  "properties": {
    "iso:country":"DE",
    "sg:address":"Marcel-Callo-Platz 2",
    "sg:city":"Zella-Mehlis",
    "sg:postcode":"98544",
    "sg:province":"Th\u00fcringen",
    "wof:name":"Katholisches Pfarramt Zella-mehlis",
    "wof:placetype":"venue"
},
  "geometry": {"coordinates":[10.6721105576,50.6541976929],"type":"Point"}
}