{
  "type": "Feature",
  "properties": {
    "iso:country":"DE",
    "sg:address":"Herrngasse 2",
    "sg:city":"Bischofsheim",
    "sg:phone":"+49 9772/231",
    "sg:postcode":"97653",
    "sg:province":"Bayern",
    "wof:name":"Sparkasse",
    "wof:placetype":"venue"
},
  "geometry": {"coordinates":[10.007409,50.401611],"type":"Point"}
}