{
  "type": "Feature",
  "properties": {
    "iso:country":"DE",
    "sg:address":"Kirschbl\u00fctenstr. 87",
    "sg:city":"Wiesbaden",
    "sg:phone":"+49 611/421580",
    "sg:postcode":"65201",
    "sg:province":"Hessen",
    "wof:name":"Michael Carl",
    "wof:placetype":"venue"
},
  "geometry": {"coordinates":[8.172174,50.068886],"type":"Point"}
}