{
  "type": "Feature",
  "properties": {
    "iso:country":"DE",
    "sg:address":"Pfaffenhecke 21",
    "sg:city":"Ramsen",
    "sg:phone":"+49 4963/517317",
    "sg:postcode":"67305",
    "sg:province":"Rheinland-Pfalz",
    "wof:name":"Schreiner Transport Gmbh",
    "wof:placetype":"venue"
},
  "geometry": {"coordinates":[8.0256938934,49.5367774963],"type":"Point"}
}