{
  "type": "Feature",
  "properties": {
    "iso:country":"DE",
    "sg:address":"Hauptstr. 104",
    "sg:city":"Rennerod",
    "sg:phone":"+49 2664/231",
    "sg:postcode":"56477",
    "sg:province":"Rheinland-Pfalz",
    "wof:name":"Herbert Kolb",
    "wof:placetype":"venue"
},
  "geometry": {"coordinates":[8.0673465729,50.6115570068],"type":"Point"}
}