{
  "type": "Feature",
  "properties": {
    "iso:country":"DE",
    "sg:address":"Wardener Str. 10",
    "sg:city":"Alsdorf",
    "sg:phone":"+49 2404/62141",
    "sg:postcode":"52477",
    "sg:province":"Nordrhein-Westfalen",
    "wof:name":"Hubert L\u00fcrkens",
    "wof:placetype":"venue"
},
  "geometry": {"coordinates":[6.21826,50.861126],"type":"Point"}
}