{
  "type": "Feature",
  "properties": {
    "iso:country":"DE",
    "sg:address":"G\u00fcrtelstr. 18",
    "sg:city":"Chemnitz",
    "sg:phone":"+49 371/422147",
    "sg:postcode":"09114",
    "sg:province":"Sachsen",
    "wof:name":"Sandig Speditions- Gmbh",
    "wof:placetype":"venue"
},
  "geometry": {"coordinates":[12.9214792252,50.8751373291],"type":"Point"}
}