{
  "type": "Feature",
  "properties": {
    "iso:country":"DE",
    "sg:address":"Krenmoosstr. 7",
    "sg:city":"Karlsfeld",
    "sg:phone":"+49 8131/91103",
    "sg:postcode":"85757",
    "sg:province":"Bayern",
    "wof:name":"Katholisches Pfarramt St. Anna",
    "wof:placetype":"venue"
},
  "geometry": {"coordinates":[11.4734802246,48.2244186401],"type":"Point"}
}