{
  "type": "Feature",
  "properties": {
    "iso:country":"DE",
    "sg:address":"Riedlinger Str. 28",
    "sg:city":"Uttenweiler",
    "sg:phone":"+49 7374/420",
    "sg:postcode":"88524",
    "sg:province":"Baden-W\u00fcrttemberg",
    "wof:name":"Beurer Kg",
    "wof:placetype":"venue"
},
  "geometry": {"coordinates":[9.6065826416,48.1489334106],"type":"Point"}
}