{
  "type": "Feature",
  "properties": {
    "iso:country":"DE",
    "sg:address":"Hauptstr. 9",
    "sg:city":"Beilngries",
    "sg:phone":"+49 8461/1203",
    "sg:postcode":"92339",
    "sg:province":"Bayern",
    "wof:name":"Gasthof Franz Walthierer",
    "wof:placetype":"venue"
},
  "geometry": {"coordinates":[11.4744577408,49.0338821411],"type":"Point"}
}