{
  "type": "Feature",
  "properties": {
    "iso:country":"DE",
    "sg:address":"Rurdorfer Str. 4",
    "sg:city":"Linnich",
    "sg:phone":"+49 2462/1828",
    "sg:postcode":"52441",
    "sg:province":"Nordrhein-Westfalen",
    "wof:name":"G. Thewissen",
    "wof:placetype":"venue"
},
  "geometry": {"coordinates":[6.2676520348,50.9785728455],"type":"Point"}
}