{
  "type": "Feature",
  "properties": {
    "iso:country":"DE",
    "sg:address":"Eugenstr. 1",
    "sg:city":"Filderstadt",
    "sg:phone":"+49 711/702588",
    "sg:postcode":"70794",
    "sg:province":"Baden-W\u00fcrttemberg",
    "wof:name":"Benno Kott",
    "wof:placetype":"venue"
},
  "geometry": {"coordinates":[9.2205238342,48.6750030518],"type":"Point"}
}