{
  "type": "Feature",
  "properties": {
    "iso:country":"DE",
    "sg:address":"Briloner Str. 21",
    "sg:city":"Warburg",
    "sg:phone":"+49 5642/5305",
    "sg:postcode":"34414",
    "sg:province":"Nordrhein-Westfalen",
    "wof:name":"Spar",
    "wof:placetype":"venue"
},
  "geometry": {"coordinates":[9.0141658783,51.5206413269],"type":"Point"}
}