{
  "type": "Feature",
  "properties": {
    "iso:country":"DE",
    "sg:address":"Bensberger Str. 107",
    "sg:city":"Bergisch Gladbach",
    "sg:phone":"+49 2202/34915",
    "sg:postcode":"51469",
    "sg:province":"Nordrhein-Westfalen",
    "wof:name":"Korten",
    "wof:placetype":"venue"
},
  "geometry": {"coordinates":[7.135025,50.984402],"type":"Point"}
}