{
  "type": "Feature",
  "properties": {
    "iso:country":"DE",
    "sg:address":"Am Kapellengraben 92",
    "sg:city":"Meerbusch",
    "sg:phone":"+49 2159/8584",
    "sg:postcode":"40670",
    "sg:province":"Nordrhein-Westfalen",
    "wof:name":"Herbert Beesen Steuerberater",
    "wof:placetype":"venue"
},
  "geometry": {"coordinates":[6.6520428658,51.2833786011],"type":"Point"}
}