{
  "type": "Feature",
  "properties": {
    "iso:country":"DE",
    "sg:address":"Schellenstr. 3a",
    "sg:city":"Bad Pyrmont",
    "sg:phone":"+49 5281/18687",
    "sg:postcode":"31812",
    "sg:province":"Niedersachsen",
    "wof:name":"Bock",
    "wof:placetype":"venue"
},
  "geometry": {"coordinates":[9.2637729645,51.9861831665],"type":"Point"}
}