{
  "type": "Feature",
  "properties": {
    "iso:country":"DE",
    "sg:address":"Ravenspurgerstr. 38",
    "sg:city":"Augsburg",
    "sg:phone":"+49 821/520041",
    "sg:postcode":"86150",
    "sg:province":"Bayern",
    "wof:name":"K. Schweikle",
    "wof:placetype":"venue"
},
  "geometry": {"coordinates":[10.8819351196,48.3638687134],"type":"Point"}
}