{
  "type": "Feature",
  "properties": {
    "iso:country":"DE",
    "sg:address":"N\u00fcrnberger Str. 14",
    "sg:city":"Hirschau",
    "sg:phone":"+49 9622/2871",
    "sg:postcode":"92242",
    "sg:province":"Bayern",
    "wof:name":"Albert Gallwitzer",
    "wof:placetype":"venue"
},
  "geometry": {"coordinates":[11.941432,49.543133],"type":"Point"}
}