{
  "type": "Feature",
  "properties": {
    "iso:country":"DE",
    "sg:address":"Durlacher Str. 95",
    "sg:city":"Bruchsal",
    "sg:phone":"+49 7251/300063",
    "sg:postcode":"76646",
    "sg:province":"Baden-W\u00fcrttemberg",
    "wof:name":"Truck Rent Gmbh",
    "wof:placetype":"venue"
},
  "geometry": {"coordinates":[8.592852,49.119934],"type":"Point"}
}