{
  "type": "Feature",
  "properties": {
    "iso:country":"DE",
    "sg:address":"Im Feldchen 45",
    "sg:city":"Echzell",
    "sg:phone":"+49 6008/1511",
    "sg:postcode":"61209",
    "sg:province":"Hessen",
    "wof:name":"Ingo Seiff",
    "wof:placetype":"venue"
},
  "geometry": {"coordinates":[8.8795576096,50.3807373047],"type":"Point"}
}