{
  "type": "Feature",
  "properties": {
    "iso:country":"DE",
    "sg:address":"Gartenstr. 29",
    "sg:city":"Hannover",
    "sg:phone":"+49 511/484466",
    "sg:postcode":"30161",
    "sg:province":"Niedersachsen",
    "wof:name":"Renate Althaus",
    "wof:placetype":"venue"
},
  "geometry": {"coordinates":[9.7470502853,52.3797798157],"type":"Point"}
}