{
  "type": "Feature",
  "properties": {
    "iso:country":"DE",
    "sg:address":"Ophofstr. 3",
    "sg:city":"Gelsenkirchen",
    "sg:phone":"+49 209/37204",
    "sg:postcode":"45894",
    "sg:province":"Nordrhein-Westfalen",
    "wof:name":"Ip Inside Partner Werbeagentur Und Verlag Gmbh",
    "wof:placetype":"venue"
},
  "geometry": {"coordinates":[7.0536851883,51.5782814026],"type":"Point"}
}