{
  "type": "Feature",
  "properties": {
    "iso:country":"DE",
    "sg:address":"Traunsteiner Str. 12a",
    "sg:city":"Tittmoning",
    "sg:phone":"+49 8683/473",
    "sg:postcode":"84529",
    "sg:province":"Bayern",
    "wof:name":"Adolf Poller Steuerberater",
    "wof:placetype":"venue"
},
  "geometry": {"coordinates":[12.7643690109,48.0576019287],"type":"Point"}
}