{
  "type": "Feature",
  "properties": {
    "iso:country":"DE",
    "sg:address":"Stedefreunder Str. 15",
    "sg:city":"Bielefeld",
    "sg:phone":"+49 521",
    "sg:postcode":"33729",
    "sg:province":"Nordrhein-Westfalen",
    "wof:name":"Mdp Automobile",
    "wof:placetype":"venue"
},
  "geometry": {"coordinates":[8.6057662964,52.0713348389],"type":"Point"}
}