{
  "type": "Feature",
  "properties": {
    "iso:country":"DE",
    "sg:address":"Herrenleite 8",
    "sg:city":"Waigolshausen",
    "sg:phone":"+49 9722/2037",
    "sg:postcode":"97534",
    "sg:province":"Bayern",
    "wof:name":"K\u00f6hler",
    "wof:placetype":"venue"
},
  "geometry": {"coordinates":[10.155701,49.965183],"type":"Point"}
}