{
  "type": "Feature",
  "properties": {
    "iso:country":"DE",
    "sg:address":"Industriestr. 15",
    "sg:city":"Kaufungen",
    "sg:phone":"+49 4956/058040",
    "sg:postcode":"34260",
    "sg:province":"Hessen",
    "wof:name":"B\u00c4ko Fuldaland Eg",
    "wof:placetype":"venue"
},
  "geometry": {"coordinates":[9.578848,51.285],"type":"Point"}
}