{
  "type": "Feature",
  "properties": {
    "iso:country":"DE",
    "sg:address":"K\u00f6rner Hellweg 36 A",
    "sg:city":"Dortmund",
    "sg:phone":"+49 231/591793",
    "sg:postcode":"44143",
    "sg:province":"Nordrhein-Westfalen",
    "wof:name":"Klaus Pivernetz",
    "wof:placetype":"venue"
},
  "geometry": {"coordinates":[7.5019021034,51.515625],"type":"Point"}
}