{
  "type": "Feature",
  "properties": {
    "iso:country":"DE",
    "sg:address":"Hauptstr. 2",
    "sg:city":"Neuendettelsau",
    "sg:phone":"+49 9874/91180",
    "sg:postcode":"91564",
    "sg:province":"Bayern",
    "wof:name":"Freimund-verlag D. Ges. F. In- Nere U. \u00c4u\u00dfere Mission Im",
    "wof:placetype":"venue"
},
  "geometry": {"coordinates":[10.7875785828,49.2873268127],"type":"Point"}
}