{
  "type": "Feature",
  "properties": {
    "iso:country":"DE",
    "sg:address":"Uhlandstr. 26",
    "sg:city":"Kerpen",
    "sg:phone":"+49 2237/2621",
    "sg:postcode":"50171",
    "sg:province":"Nordrhein-Westfalen",
    "wof:name":"Kl. Perrar Und L. Hembach",
    "wof:placetype":"venue"
},
  "geometry": {"coordinates":[6.7009921074,50.8662147522],"type":"Point"}
}