{
  "type": "Feature",
  "properties": {
    "iso:country":"DE",
    "sg:address":"Uasterjen 7",
    "sg:city":"Sylt-Ost",
    "sg:phone":"+49 4651/890434",
    "sg:postcode":"25980",
    "sg:province":"Schleswig-Holstein",
    "wof:name":"Spielhalle Am Bahnhof Jens M\u00fcller Gmbh",
    "wof:placetype":"venue"
},
  "geometry": {"coordinates":[8.4301347733,54.8592796326],"type":"Point"}
}