{
  "type": "Feature",
  "properties": {
    "iso:country":"DE",
    "sg:address":"Auf dem Berg 19",
    "sg:city":"H\u00fcnfelden-Heringen",
    "sg:phone":"+49 6438/921760",
    "sg:postcode":"65597",
    "sg:province":"Hessen",
    "wof:name":"Werner Dr\u00f6ge Msr",
    "wof:placetype":"venue"
},
  "geometry": {"coordinates":[8.1163988113,50.3189506531],"type":"Point"}
}