{
  "type": "Feature",
  "properties": {
    "iso:country":"DE",
    "sg:address":"St. Johannisstr. 13",
    "sg:city":"Bardowick",
    "sg:phone":"+49 4131/12503",
    "sg:postcode":"21357",
    "sg:province":"Niedersachsen",
    "wof:name":"Ernst Meyer",
    "wof:placetype":"venue"
},
  "geometry": {"coordinates":[10.397744,53.297165],"type":"Point"}
}