{
  "type": "Feature",
  "properties": {
    "iso:country":"DE",
    "sg:address":"Hauptstr. 37",
    "sg:city":"Eitorf",
    "sg:phone":"+49 2243/4825",
    "sg:postcode":"53783",
    "sg:province":"Nordrhein-Westfalen",
    "wof:name":"Fliesen Sieberz Gmbh",
    "wof:placetype":"venue"
},
  "geometry": {"coordinates":[7.4284358025,50.7474441528],"type":"Point"}
}