{
  "type": "Feature",
  "properties": {
    "iso:country":"DE",
    "sg:address":"Bergk\u00e4mpe 4",
    "sg:city":"S\u00fcstedt",
    "sg:phone":"+49 4252/1806",
    "sg:postcode":"27305",
    "sg:province":"Niedersachsen",
    "wof:name":"Pferdez\u00fcchterverein Hoya Und Umgebung",
    "wof:placetype":"venue"
},
  "geometry": {"coordinates":[8.9273643494,52.8258399963],"type":"Point"}
}