{
  "type": "Feature",
  "properties": {
    "iso:country":"DE",
    "sg:address":"Theresienplatz 20",
    "sg:city":"Straubing",
    "sg:phone":"+49 9421/12820",
    "sg:postcode":"94315",
    "sg:province":"Bayern",
    "wof:name":"Helmut Gattermann",
    "wof:placetype":"venue"
},
  "geometry": {"coordinates":[12.569270134,48.8818130493],"type":"Point"}
}