{
  "type": "Feature",
  "properties": {
    "iso:country":"DE",
    "sg:address":"An der grossen Wiese 1",
    "sg:city":"Weimar-Schoendorf",
    "sg:phone":"+49 3643/429910",
    "sg:postcode":"99427",
    "sg:province":"Th\u00fcringen",
    "wof:name":"Ep-vahsholz-internetshop Fuer Elektronikartikel Und Technik",
    "wof:placetype":"venue"
},
  "geometry": {"coordinates":[11.3022851944,51.0235061646],"type":"Point"}
}