{
  "type": "Feature",
  "properties": {
    "iso:country":"DE",
    "sg:address":"Im Br\u00fchl 6",
    "sg:city":"Jossgrund",
    "sg:phone":"+49 6059/745",
    "sg:postcode":"63637",
    "sg:province":"Hessen",
    "wof:name":"Reinhard Christ",
    "wof:placetype":"venue"
},
  "geometry": {"coordinates":[9.4751396179,50.1695899963],"type":"Point"}
}