{
  "type": "Feature",
  "properties": {
    "iso:country":"DE",
    "sg:address":"Hagsche Str. 94",
    "sg:city":"Kleve",
    "sg:phone":"+49 2821/28966",
    "sg:postcode":"47533",
    "sg:province":"Nordrhein-Westfalen",
    "wof:name":"Herbert Peerenboom",
    "wof:placetype":"venue"
},
  "geometry": {"coordinates":[6.1325621605,51.7834663391],"type":"Point"}
}