{
  "type": "Feature",
  "properties": {
    "iso:country":"DE",
    "sg:address":"Marktplatz 36",
    "sg:city":"Aidenbach",
    "sg:phone":"+49 8543/1812",
    "sg:postcode":"94501",
    "sg:province":"Bayern",
    "wof:name":"Klaus Und E. Plattner Eisenwaren",
    "wof:placetype":"venue"
},
  "geometry": {"coordinates":[13.0861654282,48.5682106018],"type":"Point"}
}