{
  "type": "Feature",
  "properties": {
    "iso:country":"DE",
    "sg:address":"Lehmkuhlenweg 8",
    "sg:city":"Tremsb\u00fcttel",
    "sg:phone":"+49 4532/6257",
    "sg:postcode":"22967",
    "sg:province":"Schleswig-Holstein",
    "wof:name":"Gustav-adolf Z\u00f6ftig",
    "wof:placetype":"venue"
},
  "geometry": {"coordinates":[10.295771,53.740887],"type":"Point"}
}