{
  "type": "Feature",
  "properties": {
    "iso:country":"DE",
    "sg:address":"Hamburger Str. 48",
    "sg:city":"Ahrensburg",
    "sg:postcode":"22926",
    "sg:province":"Schleswig-Holstein",
    "wof:name":"Kath. \u00d6ffentliche Bibliothek St. Marien",
    "wof:placetype":"venue"
},
  "geometry": {"coordinates":[10.232277,53.6698],"type":"Point"}
}