{
  "type": "Feature",
  "properties": {
    "iso:country":"DE",
    "sg:address":"Frundsbergstr. 5",
    "sg:city":"M\u00fcnchen",
    "sg:phone":"+49 89/161614",
    "sg:postcode":"80634",
    "sg:province":"Bayern",
    "wof:name":"Lutz Von Der Hellen Architekt Und Ingenieur",
    "wof:placetype":"venue"
},
  "geometry": {"coordinates":[11.5362386703,48.1540145874],"type":"Point"}
}