{
  "type": "Feature",
  "properties": {
    "iso:country":"DE",
    "sg:address":"Graf-von-Luckner-Stieg 1",
    "sg:city":"Scharbeutz",
    "sg:phone":"+49 4503/73232",
    "sg:postcode":"23683",
    "sg:province":"Schleswig-Holstein",
    "wof:name":"Wolfgang Schmidt",
    "wof:placetype":"venue"
},
  "geometry": {"coordinates":[10.755317,54.023144],"type":"Point"}
}