{
  "type": "Feature",
  "properties": {
    "iso:country":"DE",
    "sg:address":"Obere Str. 9",
    "sg:city":"Kiel",
    "sg:postcode":"24159",
    "sg:province":"Schleswig-Holstein",
    "wof:name":"Noisy Gmbh",
    "wof:placetype":"venue"
},
  "geometry": {"coordinates":[10.1730890274,54.4204978943],"type":"Point"}
}