{
  "type": "Feature",
  "properties": {
    "iso:country":"DE",
    "sg:address":"Nagelstr. 14",
    "sg:city":"Trier",
    "sg:phone":"+49 651/76377",
    "sg:postcode":"54290",
    "sg:province":"Rheinland-Pfalz",
    "wof:name":"Becker Reiseb\u00fcro",
    "wof:placetype":"venue"
},
  "geometry": {"coordinates":[6.638712883,49.7536392212],"type":"Point"}
}