{
  "type": "Feature",
  "properties": {
    "iso:country":"DE",
    "sg:address":"Coburger Str. 69",
    "sg:city":"Lichtenfels",
    "sg:phone":"+49 9571/3393",
    "sg:postcode":"96215",
    "sg:province":"Bayern",
    "wof:name":"Automaten-binder",
    "wof:placetype":"venue"
},
  "geometry": {"coordinates":[11.0581512451,50.1532211304],"type":"Point"}
}