{
  "type": "Feature",
  "properties": {
    "iso:country":"DE",
    "sg:address":"Servaisstr 47",
    "sg:city":"Trier",
    "sg:phone":"+49 651/968150",
    "sg:postcode":"54293",
    "sg:province":"Rheinland-Pfalz",
    "wof:name":"Bayer Und Sohn Speditions Gmbh",
    "wof:placetype":"venue"
},
  "geometry": {"coordinates":[6.688135,49.796635],"type":"Point"}
}