{
  "type": "Feature",
  "properties": {
    "iso:country":"DE",
    "sg:address":"Hochschulstr. 50",
    "sg:city":"Dresden",
    "sg:postcode":"01069",
    "sg:province":"Sachsen",
    "wof:name":"Entdecken Sie Bulgarien Ood Zweigniederlassung Dresden",
    "wof:placetype":"venue"
},
  "geometry": {"coordinates":[13.731292,51.030884],"type":"Point"}
}