{
  "type": "Feature",
  "properties": {
    "iso:country":"DE",
    "sg:address":"Schwarzwaldstr.",
    "sg:city":"B\u00fchl",
    "sg:phone":"+49 7226/550",
    "sg:postcode":"77815",
    "sg:province":"Baden-W\u00fcrttemberg",
    "wof:name":"Schlo\u00dfhotel B\u00fchlerh\u00f6he",
    "wof:placetype":"venue"
},
  "geometry": {"coordinates":[8.1595010757,48.6584587097],"type":"Point"}
}