{
  "type": "Feature",
  "properties": {
    "iso:country":"DE",
    "sg:address":"Lindenstr. 1",
    "sg:city":"Altenberge",
    "sg:phone":"+49 2505/2010",
    "sg:postcode":"48341",
    "sg:province":"Nordrhein-Westfalen",
    "wof:name":"Wolfgang De Reuter Ingenieur",
    "wof:placetype":"venue"
},
  "geometry": {"coordinates":[7.4600777626,52.0436477661],"type":"Point"}
}