{
  "type": "Feature",
  "properties": {
    "iso:country":"DE",
    "sg:address":"Rennweg 7-9",
    "sg:city":"N\u00fcrnberg",
    "sg:phone":"+49 911/538530",
    "sg:postcode":"90489",
    "sg:province":"Bayern",
    "wof:name":"Play It Again Sports",
    "wof:placetype":"venue"
},
  "geometry": {"coordinates":[11.092746,49.460938],"type":"Point"}
}