{
  "type": "Feature",
  "properties": {
    "iso:country":"DE",
    "sg:address":"Lilienthalstr 150",
    "sg:city":"Kassel",
    "sg:phone":"+49 561/50700",
    "sg:postcode":"34123",
    "sg:province":"Hessen",
    "wof:name":"Alstom Energietechnik Gmbh",
    "wof:placetype":"venue"
},
  "geometry": {"coordinates":[9.5259876251,51.2967605591],"type":"Point"}
}