{
  "type": "Feature",
  "properties": {
    "iso:country":"DE",
    "sg:address":"Schnaidt",
    "sg:city":"Kressbronn",
    "sg:phone":"+49 7543/96240",
    "sg:postcode":"88079",
    "sg:province":"Baden-W\u00fcrttemberg",
    "wof:name":"Restaurant Schnaidter Hof",
    "wof:placetype":"venue"
},
  "geometry": {"coordinates":[9.5669870377,47.5892486572],"type":"Point"}
}