{
  "type": "Feature",
  "properties": {
    "iso:country":"DE",
    "sg:address":"Wevelinghover Str. 155",
    "sg:city":"Nettetal",
    "sg:phone":"+49 2153/2633",
    "sg:postcode":"41334",
    "sg:province":"Nordrhein-Westfalen",
    "wof:name":"Wenk & Camps Verwaltungsgesellschaft Mbh",
    "wof:placetype":"venue"
},
  "geometry": {"coordinates":[6.270946,51.315201],"type":"Point"}
}