{
  "type": "Feature",
  "properties": {
    "iso:country":"DE",
    "sg:address":"Duttenstedter Str. 13",
    "sg:city":"Peine",
    "sg:phone":"+49 5171/489612",
    "sg:postcode":"31224",
    "sg:province":"Niedersachsen",
    "wof:name":"Stadthotel Inh. W. Maczollek",
    "wof:placetype":"venue"
},
  "geometry": {"coordinates":[10.2321662903,52.3287734985],"type":"Point"}
}