{
  "type": "Feature",
  "properties": {
    "iso:country":"DE",
    "sg:address":"Bahnhofstr. 21",
    "sg:city":"Leutkirch",
    "sg:phone":"+49 7561/98510",
    "sg:postcode":"88299",
    "sg:province":"Baden-W\u00fcrttemberg",
    "wof:name":"Brain At Work Ges. F\u00fcr Kommunikation Mit Neuen",
    "wof:placetype":"venue"
},
  "geometry": {"coordinates":[10.0183582306,47.8260765076],"type":"Point"}
}