{
  "type": "Feature",
  "properties": {
    "iso:country":"DE",
    "sg:address":"Haidfeldstr. 32",
    "sg:city":"Forchheim",
    "sg:phone":"+49 9191/2747",
    "sg:postcode":"91301",
    "sg:province":"Bayern",
    "wof:name":"Georg Fuchs",
    "wof:placetype":"venue"
},
  "geometry": {"coordinates":[11.063347,49.72435],"type":"Point"}
}