{
  "type": "Feature",
  "properties": {
    "iso:country":"DE",
    "sg:address":"R\u00f6merhof",
    "sg:city":"Bad Vilbel",
    "sg:phone":"+49 6101/64953",
    "sg:postcode":"61118",
    "sg:province":"Hessen",
    "wof:name":"Manfred Lanz Beteiligungs- Gesellschaft Mbh & Co. Grund-",
    "wof:placetype":"venue"
},
  "geometry": {"coordinates":[8.748752,50.219482],"type":"Point"}
}