{
  "type": "Feature",
  "properties": {
    "iso:country":"DE",
    "sg:address":"Reitzensteinstr. 41",
    "sg:city":"Recklinghausen",
    "sg:postcode":"45657",
    "sg:province":"Nordrhein-Westfalen",
    "wof:name":"Hardware Kontor Re E. Kfm.",
    "wof:placetype":"venue"
},
  "geometry": {"coordinates":[7.1887331009,51.6160125732],"type":"Point"}
}