{
  "type": "Feature",
  "properties": {
    "iso:country":"DE",
    "sg:address":"Lehrer-Tal-Weg 35",
    "sg:city":"Ulm",
    "sg:phone":"+49 731/59301",
    "sg:postcode":"89075",
    "sg:province":"Baden-W\u00fcrttemberg",
    "wof:name":"Susanne Dufner",
    "wof:placetype":"venue"
},
  "geometry": {"coordinates":[9.9737586975,48.4086952209],"type":"Point"}
}