{
  "type": "Feature",
  "properties": {
    "iso:country":"DE",
    "sg:address":"Walther-Rathenau-Str. 10",
    "sg:city":"Falkenberg",
    "sg:phone":"+49 35365/35327",
    "sg:postcode":"04895",
    "sg:province":"Brandenburg",
    "wof:name":"Rodschinka Fenstertechnik Gmbh",
    "wof:placetype":"venue"
},
  "geometry": {"coordinates":[13.243055,51.585999],"type":"Point"}
}