{
  "type": "Feature",
  "properties": {
    "iso:country":"DE",
    "sg:address":"Jungferngartenstr. 2 b",
    "sg:city":"Wiesbaden",
    "sg:phone":"+49 611/5440974",
    "sg:postcode":"65193",
    "sg:province":"Hessen",
    "wof:name":"Dr. Peter Doetsch Rechtsanwalt",
    "wof:placetype":"venue"
},
  "geometry": {"coordinates":[8.2629919052,50.0993309021],"type":"Point"}
}