{
  "type": "Feature",
  "properties": {
    "iso:country":"DE",
    "sg:address":"Rehgrund 22",
    "sg:city":"Kaufbeuren",
    "sg:phone":"+49 8341/61420",
    "sg:postcode":"87600",
    "sg:province":"Bayern",
    "wof:name":"Sigrun Walter",
    "wof:placetype":"venue"
},
  "geometry": {"coordinates":[10.632062912,47.9053077698],"type":"Point"}
}