{
  "type": "Feature",
  "properties": {
    "iso:country":"DE",
    "sg:address":"Berliner Str.",
    "sg:city":"Welzow",
    "sg:phone":"+49 35751/2100",
    "sg:postcode":"03119",
    "sg:province":"Brandenburg",
    "wof:name":"Minol Zentraltank Gmbh",
    "wof:placetype":"venue"
},
  "geometry": {"coordinates":[14.1716003418,51.5825614929],"type":"Point"}
}