{
  "type": "Feature",
  "properties": {
    "iso:country":"DE",
    "sg:address":"Gro\u00dfe Bahnstr 33",
    "sg:city":"Hamburg",
    "sg:phone":"+49 40/8532680",
    "sg:postcode":"22525",
    "sg:province":"Hamburg",
    "wof:name":"Db Services Nord Gmbh",
    "wof:placetype":"venue"
},
  "geometry": {"coordinates":[9.9361,53.572651],"type":"Point"}
}