{
  "type": "Feature",
  "properties": {
    "iso:country":"DE",
    "sg:address":"M\u00fcnchnerstr. 110",
    "sg:city":"Unterf\u00f6hring",
    "sg:postcode":"85774",
    "sg:province":"Bayern",
    "wof:name":"Cetus Ges. F. Medienbeteilig. Mbh",
    "wof:placetype":"venue"
},
  "geometry": {"coordinates":[11.645996,48.196247],"type":"Point"}
}