{
  "type": "Feature",
  "properties": {
    "iso:country":"DE",
    "sg:address":"Beethovenstr. 2",
    "sg:city":"Bad Soden-Salm\u00fcnster",
    "sg:phone":"+49 6056/8609",
    "sg:postcode":"63628",
    "sg:province":"Hessen",
    "wof:name":"Stadthalle",
    "wof:placetype":"venue"
},
  "geometry": {"coordinates":[9.3717660904,50.269733429],"type":"Point"}
}