{
  "type": "Feature",
  "properties": {
    "iso:country":"DE",
    "sg:address":"Thei\u00dfingstr. 7",
    "sg:city":"M\u00fcnster",
    "sg:phone":"+49 251/531216",
    "sg:postcode":"48153",
    "sg:province":"Nordrhein-Westfalen",
    "wof:name":"T. Schmitz",
    "wof:placetype":"venue"
},
  "geometry": {"coordinates":[7.631313,51.952374],"type":"Point"}
}