{
  "type": "Feature",
  "properties": {
    "iso:country":"DE",
    "sg:address":"Wurster Str. 91",
    "sg:city":"Bremerhaven",
    "sg:phone":"+49 471/81616",
    "sg:postcode":"27580",
    "sg:province":"Bremen",
    "wof:name":"Hans-j\u00fcrgen Thielbar",
    "wof:placetype":"venue"
},
  "geometry": {"coordinates":[8.5916347504,53.5789451599],"type":"Point"}
}