{
  "type": "Feature",
  "properties": {
    "iso:country":"DE",
    "sg:address":"Vechtetalstr. 13",
    "sg:city":"G\u00f6lenkamp",
    "sg:phone":"+49 5941/8566",
    "sg:postcode":"49843",
    "sg:province":"Niedersachsen",
    "wof:name":"Lukas Boers",
    "wof:placetype":"venue"
},
  "geometry": {"coordinates":[6.934148,52.54174],"type":"Point"}
}