{
  "type": "Feature",
  "properties": {
    "iso:country":"DE",
    "sg:address":"Bahnhofstr. 17",
    "sg:city":"Eisenach",
    "sg:phone":"+49 3691/292942",
    "sg:postcode":"99817",
    "sg:province":"Th\u00fcringen",
    "wof:name":"Panasonic Service Center Blitz-elektro Gmbh",
    "wof:placetype":"venue"
},
  "geometry": {"coordinates":[10.3287391663,50.9762153625],"type":"Point"}
}