{
  "type": "Feature",
  "properties": {
    "iso:country":"DE",
    "sg:address":"Hamminkelner Landstr. 22",
    "sg:city":"Wesel",
    "sg:phone":"+49 281/62200",
    "sg:postcode":"46483",
    "sg:province":"Nordrhein-Westfalen",
    "wof:name":"Kupferkanne",
    "wof:placetype":"venue"
},
  "geometry": {"coordinates":[6.6093459129,51.6755332947],"type":"Point"}
}