{
  "type": "Feature",
  "properties": {
    "iso:country":"DE",
    "sg:address":"Oelsnitzer Str. 59",
    "sg:city":"Hof",
    "sg:phone":"+49 9281/73790",
    "sg:postcode":"95028",
    "sg:province":"Bayern",
    "wof:name":"Bosch Telecom Gmbh",
    "wof:placetype":"venue"
},
  "geometry": {"coordinates":[11.9293851852,50.313999176],"type":"Point"}
}