{
  "type": "Feature",
  "properties": {
    "iso:country":"DE",
    "sg:address":"Schillerstr. 8",
    "sg:city":"Lippstadt",
    "sg:phone":"+49 2941/61943",
    "sg:postcode":"59555",
    "sg:province":"Nordrhein-Westfalen",
    "wof:name":"Schwarz-weiss Verwaltungs- Gmbh",
    "wof:placetype":"venue"
},
  "geometry": {"coordinates":[8.3472995758,51.6840171814],"type":"Point"}
}