{
  "type": "Feature",
  "properties": {
    "iso:country":"DE",
    "sg:address":"Gewerbegebiet 10",
    "sg:city":"Bad Bederkesa",
    "sg:phone":"+49 4745/6085",
    "sg:postcode":"27624",
    "sg:province":"Niedersachsen",
    "wof:name":"Griesmann",
    "wof:placetype":"venue"
},
  "geometry": {"coordinates":[8.818295,53.63089],"type":"Point"}
}