{
  "type": "Feature",
  "properties": {
    "iso:country":"DE",
    "sg:address":"Lindenstr. 16",
    "sg:city":"Schwaneberg",
    "sg:phone":"+49 39205/23214",
    "sg:postcode":"39171",
    "sg:province":"Sachsen-Anhalt",
    "wof:name":"Hagedorn Tischlerei Gmbh",
    "wof:placetype":"venue"
},
  "geometry": {"coordinates":[11.470706,51.998795],"type":"Point"}
}