{
  "type": "Feature",
  "properties": {
    "iso:country":"DE",
    "sg:address":"Haufenm\u00fchle 2",
    "sg:city":"Drachselsried",
    "sg:phone":"+49 9945/1047",
    "sg:postcode":"94256",
    "sg:province":"Bayern",
    "wof:name":"Pension Sebastian Maier",
    "wof:placetype":"venue"
},
  "geometry": {"coordinates":[13.0136804581,49.1052932739],"type":"Point"}
}