{
  "type": "Feature",
  "properties": {
    "iso:country":"DE",
    "sg:address":"Meynstr. 28",
    "sg:city":"Rendsburg",
    "sg:phone":"+49 4331/31138",
    "sg:postcode":"24768",
    "sg:province":"Schleswig-Holstein",
    "wof:name":"Imwi Immobilien- Wirtschaftsdienste Gmbh",
    "wof:placetype":"venue"
},
  "geometry": {"coordinates":[9.6601743698,54.310962677],"type":"Point"}
}