{
  "type": "Feature",
  "properties": {
    "iso:country":"DE",
    "sg:address":"Spessartstr. 48-50",
    "sg:city":"Bonn",
    "sg:postcode":"53119",
    "sg:province":"Nordrhein-Westfalen",
    "wof:name":"Brz Serviceb\u00fcro Bonn",
    "wof:placetype":"venue"
},
  "geometry": {"coordinates":[7.08045,50.737808],"type":"Point"}
}