{
  "type": "Feature",
  "properties": {
    "iso:country":"DE",
    "sg:address":"M\u00f6nchgasse 21",
    "sg:city":"Schelklingen",
    "sg:phone":"+49 7384/952316",
    "sg:postcode":"89601",
    "sg:province":"Baden-W\u00fcrttemberg",
    "wof:name":"Rolf Rothenbacher",
    "wof:placetype":"venue"
},
  "geometry": {"coordinates":[9.66087,48.38657],"type":"Point"}
}