{
  "type": "Feature",
  "properties": {
    "iso:country":"DE",
    "sg:address":"Im Sch\u00fctzengrund 48-50",
    "sg:city":"Neuwied",
    "sg:postcode":"56566",
    "sg:province":"Rheinland-Pfalz",
    "wof:name":"Kipping Gmbh & Co. Kg",
    "wof:placetype":"venue"
},
  "geometry": {"coordinates":[7.5331010818,50.4276275635],"type":"Point"}
}