{
  "type": "Feature",
  "properties": {
    "iso:country":"DE",
    "sg:address":"Rosenh\u00fcgel 1",
    "sg:city":"K\u00f6ln",
    "sg:phone":"+49 2203/85514",
    "sg:postcode":"51143",
    "sg:province":"Nordrhein-Westfalen",
    "wof:name":"Em Pitterm\u00e4nnche",
    "wof:placetype":"venue"
},
  "geometry": {"coordinates":[7.0509901047,50.8743896484],"type":"Point"}
}