{
  "type": "Feature",
  "properties": {
    "iso:country":"DE",
    "sg:address":"Am S\u00fclteberg 27",
    "sg:city":"Langelsheim",
    "sg:postcode":"38685",
    "sg:province":"Niedersachsen",
    "wof:name":"Lagerhaus- Und Handels- Gesellschaft Mbh",
    "wof:placetype":"venue"
},
  "geometry": {"coordinates":[10.3314590454,51.9190597534],"type":"Point"}
}