{
  "type": "Feature",
  "properties": {
    "iso:country":"DE",
    "sg:address":"Poststr. 1",
    "sg:city":"D\u00fcsseldorf",
    "sg:phone":"+49 211/89890",
    "sg:postcode":"40213",
    "sg:province":"Nordrhein-Westfalen",
    "wof:name":"Hans-j\u00fcrgen Marquardt Steuerberater",
    "wof:placetype":"venue"
},
  "geometry": {"coordinates":[6.771739006,51.2229156494],"type":"Point"}
}