{
  "type": "Feature",
  "properties": {
    "iso:country":"DE",
    "sg:address":"Carmanstrasse 42",
    "sg:city":"Euskirchen",
    "sg:postcode":"53879",
    "sg:province":"Nordrhein-Westfalen",
    "wof:name":"Srs-projekt Bonn",
    "wof:placetype":"venue"
},
  "geometry": {"coordinates":[6.7845082283,50.6654281616],"type":"Point"}
}