{
  "type": "Feature",
  "properties": {
    "iso:country":"DE",
    "sg:address":"Immanuel-Kant-Str. 26",
    "sg:city":"Hohenstein-Ernstthal",
    "sg:phone":"+49 3723/42482",
    "sg:postcode":"09337",
    "sg:province":"Sachsen",
    "wof:name":"C. Barthel",
    "wof:placetype":"venue"
},
  "geometry": {"coordinates":[12.7059335709,50.7995834351],"type":"Point"}
}