{
  "type": "Feature",
  "properties": {
    "iso:country":"DE",
    "sg:address":"Chausseestr. 15",
    "sg:city":"Sch\u00f6nebeck",
    "sg:phone":"+49 3928/67003",
    "sg:postcode":"39218",
    "sg:province":"Sachsen-Anhalt",
    "wof:name":"Sch\u00f6nebecker Fleisch- Und Wurstwaren Gmbh",
    "wof:placetype":"venue"
},
  "geometry": {"coordinates":[11.715596199,52.0017204285],"type":"Point"}
}