{
  "type": "Feature",
  "properties": {
    "iso:country":"DE",
    "sg:address":"Suhler Str. 32",
    "sg:city":"Schmalkalden",
    "sg:phone":"+49 3683/606329",
    "sg:postcode":"98574",
    "sg:province":"Th\u00fcringen",
    "wof:name":"Wima Werkzeuge Gerhard Mangold",
    "wof:placetype":"venue"
},
  "geometry": {"coordinates":[10.47701,50.712742],"type":"Point"}
}