{
  "type": "Feature",
  "properties": {
    "iso:country":"DE",
    "sg:address":"Eimterstr. 48",
    "sg:city":"Herford",
    "sg:phone":"+49 5221/26777",
    "sg:postcode":"32049",
    "sg:province":"Nordrhein-Westfalen",
    "wof:name":"Deutscher Pokalvertrieb",
    "wof:placetype":"venue"
},
  "geometry": {"coordinates":[8.678895,52.125713],"type":"Point"}
}