{
  "type": "Feature",
  "properties": {
    "iso:country":"DE",
    "sg:address":"Lagerhofstr. 02",
    "sg:city":"Leipzig",
    "sg:postcode":"04103",
    "sg:province":"Sachsen",
    "wof:name":"Leimos Wasserchemie Gmbh",
    "wof:placetype":"venue"
},
  "geometry": {"coordinates":[12.392047,51.346996],"type":"Point"}
}