{
  "type": "Feature",
  "properties": {
    "iso:country":"DE",
    "sg:address":"Schillerstr. 2",
    "sg:city":"Altheim",
    "sg:phone":"+49 7371/3038",
    "sg:postcode":"88499",
    "sg:province":"Baden-W\u00fcrttemberg",
    "wof:name":"Keramail-siebdruck- Technik Gmbh",
    "wof:placetype":"venue"
},
  "geometry": {"coordinates":[9.448417,48.14325],"type":"Point"}
}