{
  "type": "Feature",
  "properties": {
    "iso:country":"DE",
    "sg:address":"Blumlage 23",
    "sg:city":"Celle",
    "sg:postcode":"29221",
    "sg:province":"Niedersachsen",
    "wof:name":"Studio F Gmbh",
    "wof:placetype":"venue"
},
  "geometry": {"coordinates":[10.0907640457,52.6211128235],"type":"Point"}
}