{
  "type": "Feature",
  "properties": {
    "iso:country":"DE",
    "sg:address":"R\u00fcdesheimer Str. 18",
    "sg:city":"Bad Kreuznach",
    "sg:phone":"+49 671/46031",
    "sg:postcode":"55545",
    "sg:province":"Rheinland-Pfalz",
    "wof:name":"Lothar Frank Anlageberater",
    "wof:placetype":"venue"
},
  "geometry": {"coordinates":[7.853126049,49.8484954834],"type":"Point"}
}