{
  "type": "Feature",
  "properties": {
    "iso:country":"DE",
    "sg:address":"Maximilianstr. 54",
    "sg:city":"M\u00fcnchen",
    "sg:postcode":"80538",
    "sg:province":"Bayern",
    "wof:name":"Deltacap Ag",
    "wof:placetype":"venue"
},
  "geometry": {"coordinates":[11.58813,48.137131],"type":"Point"}
}