{
  "type": "Feature",
  "properties": {
    "iso:country":"DE",
    "sg:address":"Hauptstr. 37",
    "sg:city":"Spelle",
    "sg:phone":"+49 5977/8877",
    "sg:postcode":"48480",
    "sg:province":"Niedersachsen",
    "wof:name":"J. Sch\u00fctte Inh. Josef Wiesweg",
    "wof:placetype":"venue"
},
  "geometry": {"coordinates":[7.470744,52.365761],"type":"Point"}
}