{
  "type": "Feature",
  "properties": {
    "iso:country":"DE",
    "sg:address":"Hildesheimer Str. 10",
    "sg:city":"Vechelde",
    "sg:phone":"+49 5302/7106",
    "sg:postcode":"38159",
    "sg:province":"Niedersachsen",
    "wof:name":"F. Sahin",
    "wof:placetype":"venue"
},
  "geometry": {"coordinates":[10.375330925,52.2612457275],"type":"Point"}
}