{
  "type": "Feature",
  "properties": {
    "iso:country":"DE",
    "sg:address":"Gartenweg 7 a",
    "sg:city":"Buxheim",
    "sg:phone":"+49 8458/382303",
    "sg:postcode":"85114",
    "sg:province":"Bayern",
    "wof:name":"Christian Lutz Rechtsanwalt",
    "wof:placetype":"venue"
},
  "geometry": {"coordinates":[11.2902936935,48.8062858582],"type":"Point"}
}