{
  "type": "Feature",
  "properties": {
    "iso:country":"DE",
    "sg:address":"Basler Str. 10",
    "sg:city":"Bad Krozingen",
    "sg:phone":"+49 7633/958050",
    "sg:postcode":"79189",
    "sg:province":"Baden-W\u00fcrttemberg",
    "wof:name":"Hans-eckart Zipfel Ingenieur",
    "wof:placetype":"venue"
},
  "geometry": {"coordinates":[7.699174881,47.9151115417],"type":"Point"}
}