{
  "type": "Feature",
  "properties": {
    "iso:country":"DE",
    "sg:address":"Langgasse 86",
    "sg:city":"Ha\u00dfloch",
    "sg:phone":"+49 6324/3508",
    "sg:postcode":"67454",
    "sg:province":"Rheinland-Pfalz",
    "wof:name":"Sieglinde Stra\u00dfner",
    "wof:placetype":"venue"
},
  "geometry": {"coordinates":[8.257186,49.363354],"type":"Point"}
}