{
  "type": "Feature",
  "properties": {
    "iso:country":"DE",
    "sg:address":"Kaiser-Friedrich-Ring 33",
    "sg:city":"Wiesbaden",
    "sg:phone":"+49 611/846763",
    "sg:postcode":"65185",
    "sg:province":"Hessen",
    "wof:name":"Mephisto",
    "wof:placetype":"venue"
},
  "geometry": {"coordinates":[8.2308864594,50.074798584],"type":"Point"}
}