{
  "type": "Feature",
  "properties": {
    "iso:country":"DE",
    "sg:address":"Ackerrain 12",
    "sg:city":"L\u00fcdinghausen",
    "sg:phone":"+49 2591/21780",
    "sg:postcode":"59348",
    "sg:province":"Nordrhein-Westfalen",
    "wof:name":"Franz Grube Ingenieur",
    "wof:placetype":"venue"
},
  "geometry": {"coordinates":[7.4535508156,51.755859375],"type":"Point"}
}