{
  "type": "Feature",
  "properties": {
    "iso:country":"DE",
    "sg:address":"Anklamer Str. 8",
    "sg:city":"Greifswald",
    "sg:phone":"+49 3834/590550",
    "sg:postcode":"17489",
    "sg:province":"Mecklenburg-Vorpommern",
    "wof:name":"Steffen Pasler Rechtsanwalt",
    "wof:placetype":"venue"
},
  "geometry": {"coordinates":[13.388712883,54.0925598145],"type":"Point"}
}