{
  "type": "Feature",
  "properties": {
    "iso:country":"DE",
    "sg:address":"L\u00fctzelsteiner Weg 5",
    "sg:city":"Berlin",
    "sg:phone":"+49 30/88683088",
    "sg:postcode":"14195",
    "sg:province":"Berlin",
    "wof:name":"Dr. Schuricht Projekt Und Management Gmbh",
    "wof:placetype":"venue"
},
  "geometry": {"coordinates":[13.2724685669,52.4487991333],"type":"Point"}
}