{
  "type": "Feature",
  "properties": {
    "iso:country":"DE",
    "sg:address":"Gebersdorfer Str. 266",
    "sg:city":"N\u00fcrnberg",
    "sg:phone":"+49 911/680020",
    "sg:postcode":"90449",
    "sg:province":"Bayern",
    "wof:name":"Robert Arzmiller",
    "wof:placetype":"venue"
},
  "geometry": {"coordinates":[10.9983682632,49.4343948364],"type":"Point"}
}