{
  "type": "Feature",
  "properties": {
    "iso:country":"DE",
    "sg:address":"Trierer Str. 6",
    "sg:city":"Saarbr\u00fccken",
    "sg:phone":"+49 6897/74246",
    "sg:postcode":"66125",
    "sg:province":"Saarland",
    "wof:name":"Sport Fritsch Gmbh",
    "wof:placetype":"venue"
},
  "geometry": {"coordinates":[7.0348510742,49.2767601013],"type":"Point"}
}