{
  "type": "Feature",
  "properties": {
    "iso:country":"DE",
    "sg:address":"Durlacher Allee 12",
    "sg:city":"Karlsruhe",
    "sg:phone":"+49 721/697875",
    "sg:postcode":"76131",
    "sg:province":"Baden-W\u00fcrttemberg",
    "wof:name":"Br\u00e4dle Friseursalon",
    "wof:placetype":"venue"
},
  "geometry": {"coordinates":[8.4183340073,49.0085105896],"type":"Point"}
}