{
  "type": "Feature",
  "properties": {
    "iso:country":"DE",
    "sg:address":"Franz-Liszt-Str. 10",
    "sg:city":"Lahnau",
    "sg:phone":"+49 6441/61525",
    "sg:postcode":"35633",
    "sg:province":"Hessen",
    "wof:name":"Friedhelm Scheld",
    "wof:placetype":"venue"
},
  "geometry": {"coordinates":[8.577204,50.576508],"type":"Point"}
}