{
  "type": "Feature",
  "properties": {
    "iso:country":"DE",
    "sg:address":"Seelbacher Str. 16",
    "sg:city":"Blieskastel",
    "sg:phone":"+49 6803/582",
    "sg:postcode":"66440",
    "sg:province":"Saarland",
    "wof:name":"Metzgerei Manfred G\u00f6ller Gmbh",
    "wof:placetype":"venue"
},
  "geometry": {"coordinates":[7.1868019104,49.2179069519],"type":"Point"}
}