{
  "type": "Feature",
  "properties": {
    "iso:country":"DE",
    "sg:address":"August-Bebel-Str. 21",
    "sg:city":"Burg",
    "sg:phone":"+49 3921/6625",
    "sg:postcode":"39288",
    "sg:province":"Sachsen-Anhalt",
    "wof:name":"Wolfgang Freitag",
    "wof:placetype":"venue"
},
  "geometry": {"coordinates":[11.842724,52.268932],"type":"Point"}
}