{
  "type": "Feature",
  "properties": {
    "iso:country":"DE",
    "sg:address":"Ketschengasse 54",
    "sg:city":"Coburg",
    "sg:phone":"+49 9561/55450",
    "sg:postcode":"96450",
    "sg:province":"Bayern",
    "wof:name":"Eduard Tauer Steuerberater Und",
    "wof:placetype":"venue"
},
  "geometry": {"coordinates":[10.9641666412,50.2553405762],"type":"Point"}
}