{
  "type": "Feature",
  "properties": {
    "iso:country":"DE",
    "sg:address":"S\u00fcdliche M\u00fcnchner Str. 24",
    "sg:city":"Gr\u00fcnwald",
    "sg:phone":"+49 89/6935130",
    "sg:postcode":"82031",
    "sg:province":"Bayern",
    "wof:name":"Dr. Jung & Partner Gmbh",
    "wof:placetype":"venue"
},
  "geometry": {"coordinates":[11.5280342102,48.0444297791],"type":"Point"}
}