{
  "type": "Feature",
  "properties": {
    "iso:country":"DE",
    "sg:address":"Heinrich-R\u00f6hm-Str. 15",
    "sg:city":"Sontheim",
    "sg:phone":"+49 7325/6708",
    "sg:postcode":"89567",
    "sg:province":"Baden-W\u00fcrttemberg",
    "wof:name":"H. Lindenmaier",
    "wof:placetype":"venue"
},
  "geometry": {"coordinates":[10.2963237762,48.5509033203],"type":"Point"}
}