{
  "type": "Feature",
  "properties": {
    "iso:country":"DE",
    "sg:address":"Klingenhagen 57",
    "sg:city":"Halle",
    "sg:phone":"+49 5201/2075",
    "sg:postcode":"33790",
    "sg:province":"Nordrhein-Westfalen",
    "wof:name":"August Thomas Kg",
    "wof:placetype":"venue"
},
  "geometry": {"coordinates":[8.350584,52.059059],"type":"Point"}
}