{
  "type": "Feature",
  "properties": {
    "iso:country":"DE",
    "sg:address":"Bahnhofsplatz 1",
    "sg:city":"Kassel",
    "sg:phone":"+49 561/710166",
    "sg:postcode":"34117",
    "sg:province":"Hessen",
    "wof:name":"Engelhardt Promotions Gmbh",
    "wof:placetype":"venue"
},
  "geometry": {"coordinates":[9.489606,51.31881],"type":"Point"}
}