{
  "type": "Feature",
  "properties": {
    "iso:country":"DE",
    "sg:address":"Prinzenstr. 1-5",
    "sg:city":"Solingen",
    "sg:phone":"+49 212/330093",
    "sg:postcode":"42697",
    "sg:province":"Nordrhein-Westfalen",
    "wof:name":"Mvl Leuchtenfertigung Gmbh",
    "wof:placetype":"venue"
},
  "geometry": {"coordinates":[7.005453,51.171368],"type":"Point"}
}