{
  "type": "Feature",
  "properties": {
    "iso:country":"DE",
    "sg:address":"Eichenstr. 4",
    "sg:city":"G\u00f6ppingen",
    "sg:phone":"+49 7161/811807",
    "sg:postcode":"73037",
    "sg:province":"Baden-W\u00fcrttemberg",
    "wof:name":"Rad-stube",
    "wof:placetype":"venue"
},
  "geometry": {"coordinates":[9.692694664,48.6668586731],"type":"Point"}
}