{
  "type": "Feature",
  "properties": {
    "iso:country":"DE",
    "sg:address":"Hauptstr. 27",
    "sg:city":"Bad Kleinen",
    "sg:phone":"+49 38423/50217",
    "sg:postcode":"23996",
    "sg:province":"Mecklenburg-Vorpommern",
    "wof:name":"Gerhard Ziebell Baugesch\u00e4ft",
    "wof:placetype":"venue"
},
  "geometry": {"coordinates":[11.471714,53.769711],"type":"Point"}
}