{
  "type": "Feature",
  "properties": {
    "iso:country":"DE",
    "sg:address":"Hauptstr. 30",
    "sg:city":"Besigheim",
    "sg:phone":"+49 7143/35577",
    "sg:postcode":"74354",
    "sg:province":"Baden-W\u00fcrttemberg",
    "wof:name":"Waldhorn",
    "wof:placetype":"venue"
},
  "geometry": {"coordinates":[9.1399021149,49.0011520386],"type":"Point"}
}