{
  "type": "Feature",
  "properties": {
    "iso:country":"DE",
    "sg:address":"Minoritenhof",
    "sg:city":"Sinzing",
    "sg:phone":"+49 941/33181",
    "sg:postcode":"93161",
    "sg:province":"Bayern",
    "wof:name":"I.-c. Von Der Weckl",
    "wof:placetype":"venue"
},
  "geometry": {"coordinates":[12.031945,48.979027],"type":"Point"}
}