{
  "type": "Feature",
  "properties": {
    "iso:country":"DE",
    "sg:address":"Adalbert-Stifter-Str. 26",
    "sg:city":"Gro\u00dfostheim",
    "sg:phone":"+49 6021/423102",
    "sg:postcode":"63762",
    "sg:province":"Bayern",
    "wof:name":"Heiko Zang",
    "wof:placetype":"venue"
},
  "geometry": {"coordinates":[9.0710783005,49.9236717224],"type":"Point"}
}