{
  "type": "Feature",
  "properties": {
    "iso:country":"DE",
    "sg:address":"Parkstr. 1",
    "sg:city":"Altenburg",
    "sg:phone":"+49 3447/500297",
    "sg:postcode":"04600",
    "sg:province":"Th\u00fcringen",
    "wof:name":"Biergarten Am Schlo\u00dfpark",
    "wof:placetype":"venue"
},
  "geometry": {"coordinates":[12.4473514557,50.989780426],"type":"Point"}
}