{
  "type": "Feature",
  "properties": {
    "iso:country":"DE",
    "sg:address":"Marie-Alexandra-Str. 34",
    "sg:city":"Karlsruhe",
    "sg:phone":"+49 721/32481",
    "sg:postcode":"76135",
    "sg:province":"Baden-W\u00fcrttemberg",
    "wof:name":"Franz Lanz",
    "wof:placetype":"venue"
},
  "geometry": {"coordinates":[8.3899316788,48.9929847717],"type":"Point"}
}