{
  "type": "Feature",
  "properties": {
    "iso:country":"DE",
    "sg:address":"Dorfstr. 24",
    "sg:city":"Schmatzin",
    "sg:phone":"+49 39724/22561",
    "sg:postcode":"17390",
    "sg:province":"Mecklenburg-Vorpommern",
    "wof:name":"Bodo Milse",
    "wof:placetype":"venue"
},
  "geometry": {"coordinates":[13.551366,53.922916],"type":"Point"}
}