{
  "type": "Feature",
  "properties": {
    "iso:country":"DE",
    "sg:address":"Sartoriusstr. 30",
    "sg:city":"Hamburg",
    "sg:phone":"+49 40/43270870",
    "sg:postcode":"20257",
    "sg:province":"Hamburg",
    "wof:name":"Docland Non-fiction- Productions E. K.",
    "wof:placetype":"venue"
},
  "geometry": {"coordinates":[9.9431009293,53.5808525085],"type":"Point"}
}