{
  "type": "Feature",
  "properties": {
    "iso:country":"DE",
    "sg:address":"Am Schlo\u00df Walbeck 13",
    "sg:city":"Geldern",
    "sg:phone":"+49 2831/3598",
    "sg:postcode":"47608",
    "sg:province":"Nordrhein-Westfalen",
    "wof:name":"H. A. Poethen",
    "wof:placetype":"venue"
},
  "geometry": {"coordinates":[6.22531,51.50407],"type":"Point"}
}