{
  "type": "Feature",
  "properties": {
    "iso:country":"DE",
    "sg:address":"Hamfhofsweg 33",
    "sg:city":"Bremen",
    "sg:phone":"+49 421/275588",
    "sg:postcode":"28357",
    "sg:province":"Bremen",
    "wof:name":"Herbert Kohlmann Container Transport Und Handel Gmbh",
    "wof:placetype":"venue"
},
  "geometry": {"coordinates":[8.89263,53.129238],"type":"Point"}
}