{
  "type": "Feature",
  "properties": {
    "iso:country":"DE",
    "sg:address":"Mangfallstr. 45",
    "sg:city":"Rosenheim",
    "sg:phone":"+49 8031/609552",
    "sg:postcode":"83026",
    "sg:province":"Bayern",
    "wof:name":"Hermann Slanz Gmbh",
    "wof:placetype":"venue"
},
  "geometry": {"coordinates":[12.112903595,47.8376197815],"type":"Point"}
}