{
  "type": "Feature",
  "properties": {
    "iso:country":"DE",
    "sg:address":"Tuchinger Str. 19",
    "sg:city":"Freising",
    "sg:phone":"+49 8161/62240",
    "sg:postcode":"85356",
    "sg:province":"Bayern",
    "wof:name":"Franz Bauer",
    "wof:placetype":"venue"
},
  "geometry": {"coordinates":[11.768264,48.407993],"type":"Point"}
}