{
  "type": "Feature",
  "properties": {
    "iso:country":"DE",
    "sg:address":"Fuldaer Str 11",
    "sg:city":"N\u00fcrnberg",
    "sg:phone":"+49 911/303040",
    "sg:postcode":"90427",
    "sg:province":"Bayern",
    "wof:name":"Rogg Polycell Kunststoff Technik Gmbh",
    "wof:placetype":"venue"
},
  "geometry": {"coordinates":[11.000749588,49.5144309998],"type":"Point"}
}