{
  "type": "Feature",
  "properties": {
    "iso:country":"DE",
    "sg:address":"Auweg 2",
    "sg:city":"Biedenkopf",
    "sg:phone":"+49 6461/2157",
    "sg:postcode":"35216",
    "sg:province":"Hessen",
    "wof:name":"B. Lapp",
    "wof:placetype":"venue"
},
  "geometry": {"coordinates":[8.531627,50.908878],"type":"Point"}
}