{
  "type": "Feature",
  "properties": {
    "iso:country":"DE",
    "sg:address":"Hauptstr. 18",
    "sg:city":"Lippetal",
    "sg:phone":"+49 2527/325",
    "sg:postcode":"59510",
    "sg:province":"Nordrhein-Westfalen",
    "wof:name":"Hotel-restaurant Lippborger Hof",
    "wof:placetype":"venue"
},
  "geometry": {"coordinates":[8.039440155,51.6643180847],"type":"Point"}
}