{
  "type": "Feature",
  "properties": {
    "iso:country":"DE",
    "sg:address":"Saarbr\u00fccker Str.",
    "sg:city":"Lebach",
    "sg:postcode":"66822",
    "sg:province":"Saarland",
    "wof:name":"Palmeninsel Gmbh",
    "wof:placetype":"venue"
},
  "geometry": {"coordinates":[6.912346,49.407501],"type":"Point"}
}