{
  "type": "Feature",
  "properties": {
    "iso:country":"DE",
    "sg:address":"Wallensteinstr. 7",
    "sg:city":"Stuttgart",
    "sg:phone":"+49 711/842211",
    "sg:postcode":"70437",
    "sg:province":"Baden-W\u00fcrttemberg",
    "wof:name":"Dr. Med. George Petcu",
    "wof:placetype":"venue"
},
  "geometry": {"coordinates":[9.2079696655,48.8418197632],"type":"Point"}
}