{
  "type": "Feature",
  "properties": {
    "iso:country":"DE",
    "sg:address":"An der Fegetasche 10",
    "sg:city":"Coesfeld",
    "sg:phone":"+49 2541/72865",
    "sg:postcode":"48653",
    "sg:province":"Nordrhein-Westfalen",
    "wof:name":"Dr. Friedrich Besselmann Rechtsanwalt Und Notar",
    "wof:placetype":"venue"
},
  "geometry": {"coordinates":[7.1747608185,51.9463272095],"type":"Point"}
}