{
  "type": "Feature",
  "properties": {
    "iso:country":"DE",
    "sg:address":"Stuttgarter Str. 13",
    "sg:city":"Kornwestheim",
    "sg:phone":"+49 7154/27419",
    "sg:postcode":"70806",
    "sg:province":"Baden-W\u00fcrttemberg",
    "wof:name":"Peter Degner",
    "wof:placetype":"venue"
},
  "geometry": {"coordinates":[9.185851,48.864075],"type":"Point"}
}