{
  "type": "Feature",
  "properties": {
    "iso:country":"DE",
    "sg:address":"Fischerstr. 44",
    "sg:city":"Duisburg",
    "sg:phone":"+49 203/776759",
    "sg:postcode":"47055",
    "sg:province":"Nordrhein-Westfalen",
    "wof:name":"Werner Nolte Ingenieur",
    "wof:placetype":"venue"
},
  "geometry": {"coordinates":[6.7549791336,51.4023284912],"type":"Point"}
}