{
  "type": "Feature",
  "properties": {
    "iso:country":"DE",
    "sg:address":"Hauptstr. 27",
    "sg:city":"Kulmbach",
    "sg:phone":"+49 9221/701772",
    "sg:postcode":"95326",
    "sg:province":"Bayern",
    "wof:name":"Wei\u00dfes Ro\u00df",
    "wof:placetype":"venue"
},
  "geometry": {"coordinates":[11.4155702591,50.091632843],"type":"Point"}
}