{
  "type": "Feature",
  "properties": {
    "iso:country":"DE",
    "sg:address":"M\u00fcnchener Str. 71",
    "sg:city":"Freilassing",
    "sg:phone":"+49 8654/1343",
    "sg:postcode":"83395",
    "sg:province":"Bayern",
    "wof:name":"K. Meenen Steuerbevollm\u00e4chtigter",
    "wof:placetype":"venue"
},
  "geometry": {"coordinates":[12.9768753052,47.8422241211],"type":"Point"}
}