{
  "type": "Feature",
  "properties": {
    "iso:country":"DE",
    "sg:address":"Kurt-Pchalek-Str. 33",
    "sg:city":"Bautzen",
    "sg:phone":"+49 3591/37920",
    "sg:postcode":"02625",
    "sg:province":"Sachsen",
    "wof:name":"J. Zschiesche Grundst\u00fccksgesellschaft Kg",
    "wof:placetype":"venue"
},
  "geometry": {"coordinates":[14.430039,51.178204],"type":"Point"}
}