{
  "type": "Feature",
  "properties": {
    "iso:country":"DE",
    "sg:address":"Glockenstr. 16",
    "sg:city":"D\u00fcsseldorf",
    "sg:phone":"+49 211/483069",
    "sg:postcode":"40476",
    "sg:province":"Nordrhein-Westfalen",
    "wof:name":"Eucker Gmbh",
    "wof:placetype":"venue"
},
  "geometry": {"coordinates":[6.785036087,51.2451133728],"type":"Point"}
}