{
  "type": "Feature",
  "properties": {
    "iso:country":"DE",
    "sg:address":"Benzhauser Str. 3",
    "sg:city":"Freiburg",
    "sg:phone":"+49 7665/1705",
    "sg:postcode":"79108",
    "sg:province":"Baden-W\u00fcrttemberg",
    "wof:name":"Kath. Pfarramt St. Martin",
    "wof:placetype":"venue"
},
  "geometry": {"coordinates":[7.8018212318,48.0500564575],"type":"Point"}
}