{
  "type": "Feature",
  "properties": {
    "iso:country":"DE",
    "sg:address":"Seestr. 14",
    "sg:city":"Schliersee",
    "sg:phone":"+49 8026/4167",
    "sg:postcode":"83727",
    "sg:province":"Bayern",
    "wof:name":"Hemo-werbung Und Druck Georg Eckschlager",
    "wof:placetype":"venue"
},
  "geometry": {"coordinates":[11.866792,47.732338],"type":"Point"}
}