{
  "type": "Feature",
  "properties": {
    "iso:country":"DE",
    "sg:address":"Eckermannstr. 19",
    "sg:city":"Bad Bevensen",
    "sg:phone":"+49 5821/98070",
    "sg:postcode":"29549",
    "sg:province":"Niedersachsen",
    "wof:name":"Sommer Und Partner Steuerberatungsgesellschaft",
    "wof:placetype":"venue"
},
  "geometry": {"coordinates":[10.5776166916,53.0844993591],"type":"Point"}
}