{
  "type": "Feature",
  "properties": {
    "iso:country":"DE",
    "sg:address":"Etzenhausener Str. 6",
    "sg:city":"Dachau",
    "sg:phone":"+49 8131/82139",
    "sg:postcode":"85221",
    "sg:province":"Bayern",
    "wof:name":"Ges. F\u00fcr Lagereibetrieb",
    "wof:placetype":"venue"
},
  "geometry": {"coordinates":[11.43831,48.26577],"type":"Point"}
}