{
  "type": "Feature",
  "properties": {
    "iso:country":"DE",
    "sg:address":"H\u00fclser Str. 283",
    "sg:city":"Krefeld",
    "sg:phone":"+49 2151/750115",
    "sg:postcode":"47803",
    "sg:province":"Nordrhein-Westfalen",
    "wof:name":"Club Crawatte Crefeld",
    "wof:placetype":"venue"
},
  "geometry": {"coordinates":[6.545446,51.346741],"type":"Point"}
}