{
  "type": "Feature",
  "properties": {
    "iso:country":"DE",
    "sg:address":"S\u00e4chsische Str. 39",
    "sg:city":"Berlin",
    "sg:phone":"+49 30/8616667",
    "sg:postcode":"10713",
    "sg:province":"Berlin",
    "wof:name":"Bernd Arnhold",
    "wof:placetype":"venue"
},
  "geometry": {"coordinates":[13.316667,52.489872],"type":"Point"}
}