{
  "type": "Feature",
  "properties": {
    "iso:country":"DE",
    "sg:address":"W\u00f6rthstr. 10",
    "sg:city":"M\u00fcnchen",
    "sg:phone":"+49 89/4483617",
    "sg:postcode":"81667",
    "sg:province":"Bayern",
    "wof:name":"Klinger-film-verleih Adalbert Klinger",
    "wof:placetype":"venue"
},
  "geometry": {"coordinates":[11.5989017487,48.1311950684],"type":"Point"}
}