{
  "type": "Feature",
  "properties": {
    "iso:country":"DE",
    "sg:address":"Hauptstr. 7",
    "sg:city":"Fichtenau",
    "sg:phone":"+49 7962/520",
    "sg:postcode":"74579",
    "sg:province":"Baden-W\u00fcrttemberg",
    "wof:name":"Fichtenau-apotheke",
    "wof:placetype":"venue"
},
  "geometry": {"coordinates":[10.208877,49.070911],"type":"Point"}
}