{
  "type": "Feature",
  "properties": {
    "iso:country":"DE",
    "sg:address":"Brunnenstr. 2",
    "sg:city":"Kirchzarten",
    "sg:phone":"+49 7661/1635",
    "sg:postcode":"79199",
    "sg:province":"Baden-W\u00fcrttemberg",
    "wof:name":"C.f. Thomas",
    "wof:placetype":"venue"
},
  "geometry": {"coordinates":[7.954956,47.978085],"type":"Point"}
}