{
  "type": "Feature",
  "properties": {
    "iso:country":"DE",
    "sg:address":"Heinrich-Mann-Ring 41",
    "sg:city":"L\u00fcbeck",
    "sg:phone":"+49 451/65664",
    "sg:postcode":"23566",
    "sg:province":"Schleswig-Holstein",
    "wof:name":"Optic Service Nord - R.m\u00fcnzinger",
    "wof:placetype":"venue"
},
  "geometry": {"coordinates":[10.732048,53.869728],"type":"Point"}
}