{
  "type": "Feature",
  "properties": {
    "iso:country":"DE",
    "sg:address":"S\u00f6hestner Str. 61",
    "sg:city":"Muschwitz",
    "sg:phone":"+49 34441/24824",
    "sg:postcode":"06679",
    "sg:province":"Sachsen-Anhalt",
    "wof:name":"G\u00fcnter Schwenker",
    "wof:placetype":"venue"
},
  "geometry": {"coordinates":[12.121182,51.192551],"type":"Point"}
}