{
  "type": "Feature",
  "properties": {
    "iso:country":"DE",
    "sg:address":"Lehenwiesenweg 31",
    "sg:city":"Wei\u00dfenburg",
    "sg:postcode":"91781",
    "sg:province":"Bayern",
    "wof:name":"K. & R. Grundst\u00fccks Gmbh & Co. Kg",
    "wof:placetype":"venue"
},
  "geometry": {"coordinates":[10.9583559036,49.0351066589],"type":"Point"}
}