{
  "type": "Feature",
  "properties": {
    "iso:country":"DE",
    "sg:address":"J\u00fcthornstr. 49",
    "sg:city":"Hamburg",
    "sg:phone":"+49 40/681447",
    "sg:postcode":"22043",
    "sg:province":"Hamburg",
    "wof:name":"Deutsche Shell Ag",
    "wof:placetype":"venue"
},
  "geometry": {"coordinates":[10.0753660202,53.5667152405],"type":"Point"}
}