{
  "type": "Feature",
  "properties": {
    "iso:country":"DE",
    "sg:address":"Wehrhalden",
    "sg:city":"Herrischried",
    "sg:phone":"+49 7764/378",
    "sg:postcode":"79737",
    "sg:province":"Baden-W\u00fcrttemberg",
    "wof:name":"Pension Rest. Wehrhalder Hof",
    "wof:placetype":"venue"
},
  "geometry": {"coordinates":[8.0038890839,47.7034988403],"type":"Point"}
}