{
  "type": "Feature",
  "properties": {
    "iso:country":"DE",
    "sg:address":"Erwin-Rommel-Str. 15",
    "sg:city":"Paderborn",
    "sg:phone":"+49 5251/49249",
    "sg:postcode":"33102",
    "sg:province":"Nordrhein-Westfalen",
    "wof:name":"Hans Hirschberg",
    "wof:placetype":"venue"
},
  "geometry": {"coordinates":[8.752827,51.741791],"type":"Point"}
}