{
  "type": "Feature",
  "properties": {
    "iso:country":"DE",
    "sg:address":"Wagengasse 26 a",
    "sg:city":"Deesbach",
    "sg:phone":"+49 36705/63163",
    "sg:postcode":"98744",
    "sg:province":"Th\u00fcringen",
    "wof:name":"Wirtshaus Zum Raanzer",
    "wof:placetype":"venue"
},
  "geometry": {"coordinates":[11.147525,50.568886],"type":"Point"}
}