{
  "type": "Feature",
  "properties": {
    "iso:country":"DE",
    "sg:address":"Mursewiek 1",
    "sg:city":"Ummanz",
    "sg:phone":"+49 38305/8130",
    "sg:postcode":"18569",
    "sg:province":"Mecklenburg-Vorpommern",
    "wof:name":"Rassegefl\u00fcgelzuchtverein E. V. H. Kliewe",
    "wof:placetype":"venue"
},
  "geometry": {"coordinates":[13.187256813,54.4481163025],"type":"Point"}
}