{
  "type": "Feature",
  "properties": {
    "iso:country":"DE",
    "sg:address":"Br\u00fcckenstr. 20",
    "sg:city":"Schollene",
    "sg:postcode":"14715",
    "sg:province":"Brandenburg",
    "wof:name":"Feierabend- Und Pflegeheim",
    "wof:placetype":"venue"
},
  "geometry": {"coordinates":[-78.151871,42.072361],"type":"Point"}
}