{
  "type": "Feature",
  "properties": {
    "iso:country":"DE",
    "sg:address":"Ackergarten 17",
    "sg:city":"Laubuseschbach",
    "sg:phone":"+49 6475/912968",
    "sg:postcode":"35789",
    "sg:province":"Hessen",
    "wof:name":"F\u00d6rger Konstruktion",
    "wof:placetype":"venue"
},
  "geometry": {"coordinates":[8.3351402283,50.4002990723],"type":"Point"}
}