{
  "type": "Feature",
  "properties": {
    "iso:country":"DE",
    "sg:address":"Am Schafstall 3",
    "sg:city":"Stemwede",
    "sg:phone":"+49 5773/8720",
    "sg:postcode":"32351",
    "sg:province":"Nordrhein-Westfalen",
    "wof:name":"Helmut Martens",
    "wof:placetype":"venue"
},
  "geometry": {"coordinates":[8.525209,52.500927],"type":"Point"}
}