{
  "type": "Feature",
  "properties": {
    "iso:country":"DE",
    "sg:address":"Ostwall 27",
    "sg:city":"Krefeld",
    "sg:phone":"+49 2151/37670",
    "sg:postcode":"47798",
    "sg:province":"Nordrhein-Westfalen",
    "wof:name":"Bayerische Hypo- Und Vereinsbank Ag",
    "wof:placetype":"venue"
},
  "geometry": {"coordinates":[6.5691218376,51.327495575],"type":"Point"}
}