{
  "type": "Feature",
  "properties": {
    "iso:country":"DE",
    "sg:address":"T\u00f6pferstr. 24",
    "sg:city":"Duingen",
    "sg:phone":"+49 5185/465",
    "sg:postcode":"31089",
    "sg:province":"Niedersachsen",
    "wof:name":"Herbert Kothe Innenarchitekt",
    "wof:placetype":"venue"
},
  "geometry": {"coordinates":[9.702525,52.003574],"type":"Point"}
}