{
  "type": "Feature",
  "properties": {
    "iso:country":"DE",
    "sg:address":"Sperberweg 26",
    "sg:city":"Herzogenrath",
    "sg:phone":"+49 2407/3576",
    "sg:postcode":"52134",
    "sg:province":"Nordrhein-Westfalen",
    "wof:name":"Malerbetrieb Wilhelm Peter Sensen",
    "wof:placetype":"venue"
},
  "geometry": {"coordinates":[6.073918,50.833813],"type":"Point"}
}