{
  "type": "Feature",
  "properties": {
    "iso:country":"DE",
    "sg:address":"Mendelssohnstr. 2",
    "sg:city":"Hildesheim",
    "sg:phone":"+49 5121/85115",
    "sg:postcode":"31141",
    "sg:province":"Niedersachsen",
    "wof:name":"Elan 2000 Gmbh",
    "wof:placetype":"venue"
},
  "geometry": {"coordinates":[9.963555336,52.1450576782],"type":"Point"}
}