{
  "type": "Feature",
  "properties": {
    "iso:country":"DE",
    "sg:address":"Im Kleinen Felde 5/6",
    "sg:city":"Springe",
    "sg:postcode":"31832",
    "sg:province":"Niedersachsen",
    "wof:name":"Willi Heine Dachdeckerei Gmbh",
    "wof:placetype":"venue"
},
  "geometry": {"coordinates":[9.554582,52.212582],"type":"Point"}
}