{
  "type": "Feature",
  "properties": {
    "iso:country":"DE",
    "sg:address":"M\u00fchlegraben 25",
    "sg:city":"St. Peter",
    "sg:phone":"+49 7660/433",
    "sg:postcode":"79271",
    "sg:province":"Baden-W\u00fcrttemberg",
    "wof:name":"Raimund Schreiber",
    "wof:placetype":"venue"
},
  "geometry": {"coordinates":[8.0368652344,48.0195808411],"type":"Point"}
}