{
  "type": "Feature",
  "properties": {
    "iso:country":"DE",
    "sg:address":"Selmer Str. 54",
    "sg:city":"Olfen",
    "sg:phone":"+49 2595/5734",
    "sg:postcode":"59399",
    "sg:province":"Nordrhein-Westfalen",
    "wof:name":"Willi Diekmann",
    "wof:placetype":"venue"
},
  "geometry": {"coordinates":[7.3948588371,51.7053337097],"type":"Point"}
}