{
  "type": "Feature",
  "properties": {
    "iso:country":"DE",
    "sg:address":"Am Handwerkerzentrum 6 Borsd.",
    "sg:city":"Panitzsch",
    "sg:phone":"+49 34291/22350",
    "sg:postcode":"04451",
    "sg:province":"Sachsen",
    "wof:name":"R\u00f6der Landschafts- Tief- Und Rohrleitungsbau Gmbh",
    "wof:placetype":"venue"
},
  "geometry": {"coordinates":[12.5443296432,51.3488502502],"type":"Point"}
}