{
  "type": "Feature",
  "properties": {
    "iso:country":"DE",
    "sg:address":"Papiererweg 12",
    "sg:city":"Dietmannsried",
    "sg:phone":"+49 8374/5760",
    "sg:postcode":"87463",
    "sg:province":"Bayern",
    "wof:name":"K. Und H. Frey",
    "wof:placetype":"venue"
},
  "geometry": {"coordinates":[10.2875328064,47.8052139282],"type":"Point"}
}