{
  "type": "Feature",
  "properties": {
    "iso:country":"DE",
    "sg:address":"Rothenfelder Str 53b",
    "sg:city":"Versmold",
    "sg:phone":"+49 5423/4040",
    "sg:postcode":"33775",
    "sg:province":"Nordrhein-Westfalen",
    "wof:name":"Ahlers Edelstahltechnik Gmbh",
    "wof:placetype":"venue"
},
  "geometry": {"coordinates":[8.1546478271,52.0530204773],"type":"Point"}
}