{
  "type": "Feature",
  "properties": {
    "iso:country":"DE",
    "sg:address":"Amendinger Str. 25",
    "sg:city":"Trunkelsberg",
    "sg:phone":"+49 8331/47287",
    "sg:postcode":"87779",
    "sg:province":"Bayern",
    "wof:name":"Josef M. Kraus",
    "wof:placetype":"venue"
},
  "geometry": {"coordinates":[10.2101621628,48.0031547546],"type":"Point"}
}