{
  "type": "Feature",
  "properties": {
    "iso:country":"DE",
    "sg:address":"Olpketalstr. 160c",
    "sg:city":"Dortmund",
    "sg:phone":"+49 231/4271771",
    "sg:postcode":"44229",
    "sg:province":"Nordrhein-Westfalen",
    "wof:name":"Adk Immobilien Gmbh",
    "wof:placetype":"venue"
},
  "geometry": {"coordinates":[7.47407,51.457161],"type":"Point"}
}