{
  "type": "Feature",
  "properties": {
    "iso:country":"DE",
    "sg:address":"Eyller Str. 11",
    "sg:city":"Kerken",
    "sg:phone":"+49 2833/2280",
    "sg:postcode":"47647",
    "sg:province":"Nordrhein-Westfalen",
    "wof:name":"Heinz Loy Elektroinstallation",
    "wof:placetype":"venue"
},
  "geometry": {"coordinates":[6.373739,51.456554],"type":"Point"}
}