{
  "type": "Feature",
  "properties": {
    "iso:country":"DE",
    "sg:address":"Nikolausstr. 6",
    "sg:city":"Unterpleichfeld",
    "sg:phone":"+49 9367/3980",
    "sg:postcode":"97294",
    "sg:province":"Bayern",
    "wof:name":"Monika Und G\u00fcnther Schierling",
    "wof:placetype":"venue"
},
  "geometry": {"coordinates":[10.0119991302,49.8836097717],"type":"Point"}
}