{
  "type": "Feature",
  "properties": {
    "iso:country":"DE",
    "sg:address":"Golfstr. 3",
    "sg:city":"Norden",
    "sg:phone":"+49 4931/8065",
    "sg:postcode":"26506",
    "sg:province":"Niedersachsen",
    "wof:name":"Hotel Weinhaus P\u00f6tke",
    "wof:placetype":"venue"
},
  "geometry": {"coordinates":[7.1548352242,53.6172523499],"type":"Point"}
}