{
  "type": "Feature",
  "properties": {
    "iso:country":"DE",
    "sg:address":"Helmholtzstr. 16",
    "sg:city":"Ulm",
    "sg:phone":"+49 731/5010",
    "sg:postcode":"89081",
    "sg:province":"Baden-W\u00fcrttemberg",
    "wof:name":"Faw Ulm",
    "wof:placetype":"venue"
},
  "geometry": {"coordinates":[9.9626340866,48.4256477356],"type":"Point"}
}