{
  "type": "Feature",
  "properties": {
    "iso:country":"DE",
    "sg:address":"Clara-Zetkin-Str. 8",
    "sg:city":"Gransch\u00fctz",
    "sg:phone":"+49 34441/93959",
    "sg:postcode":"06679",
    "sg:province":"Sachsen-Anhalt",
    "wof:name":"Arnd Lutsche",
    "wof:placetype":"venue"
},
  "geometry": {"coordinates":[12.094855,51.16877],"type":"Point"}
}