{
  "type": "Feature",
  "properties": {
    "iso:country":"DE",
    "sg:address":"Waldstr. 24a",
    "sg:city":"M\u00f6rfelden-Walldorf",
    "sg:phone":"+49 6105/717712",
    "sg:postcode":"64546",
    "sg:province":"Hessen",
    "wof:name":"Armbrust Organisations-systeme F\u00fcr Das Gesundheitswesen Und",
    "wof:placetype":"venue"
},
  "geometry": {"coordinates":[8.5772,50.002701],"type":"Point"}
}