{
  "type": "Feature",
  "properties": {
    "iso:country":"DE",
    "sg:address":"Marktstr. 25",
    "sg:city":"Lohne",
    "sg:phone":"+49 4442/4094",
    "sg:postcode":"49393",
    "sg:province":"Niedersachsen",
    "wof:name":"Arthur M\u00fcller Optiker",
    "wof:placetype":"venue"
},
  "geometry": {"coordinates":[8.2352304459,52.6652412415],"type":"Point"}
}