{
  "type": "Feature",
  "properties": {
    "iso:country":"DE",
    "sg:address":"Neuenhainer Str. 2",
    "sg:city":"Bad Soden",
    "sg:phone":"+49 6174/4292",
    "sg:postcode":"65812",
    "sg:province":"Hessen",
    "wof:name":"Lazarus Soulis",
    "wof:placetype":"venue"
},
  "geometry": {"coordinates":[8.4732780457,50.1571502686],"type":"Point"}
}