{
  "type": "Feature",
  "properties": {
    "iso:country":"DE",
    "sg:address":"Breite Gasse 4",
    "sg:city":"Vilseck",
    "sg:phone":"+49 9662/329",
    "sg:postcode":"92249",
    "sg:province":"Bayern",
    "wof:name":"Johann Weigert",
    "wof:placetype":"venue"
},
  "geometry": {"coordinates":[11.807970047,49.6120605469],"type":"Point"}
}