{
  "type": "Feature",
  "properties": {
    "iso:country":"DE",
    "sg:address":"Kohlmarkt 12",
    "sg:city":"Wilster",
    "sg:phone":"+49 4823/94940",
    "sg:postcode":"25554",
    "sg:province":"Schleswig-Holstein",
    "wof:name":"Redaktion Wilstersche Zeitung",
    "wof:placetype":"venue"
},
  "geometry": {"coordinates":[9.3762893677,53.9235572815],"type":"Point"}
}