{
  "type": "Feature",
  "properties": {
    "iso:country":"DE",
    "sg:address":"Markt 17",
    "sg:city":"Schwaan",
    "sg:phone":"+49 3844/813510",
    "sg:postcode":"18258",
    "sg:province":"Mecklenburg-Vorpommern",
    "wof:name":"Restaurant Uwes Bauernstube",
    "wof:placetype":"venue"
},
  "geometry": {"coordinates":[12.107629776,53.9398498535],"type":"Point"}
}