{
  "type": "Feature",
  "properties": {
    "iso:country":"DE",
    "sg:address":"Seerandstr. 3",
    "sg:city":"Joachimsthal",
    "sg:phone":"+49 33361/574",
    "sg:postcode":"16247",
    "sg:province":"Brandenburg",
    "wof:name":"G. Wiedenh\u00f6ft",
    "wof:placetype":"venue"
},
  "geometry": {"coordinates":[13.761299,52.978138],"type":"Point"}
}