{
  "type": "Feature",
  "properties": {
    "iso:country":"DE",
    "sg:address":"Nordlandweg 37",
    "sg:city":"Hamburg",
    "sg:phone":"+49 40/6784571",
    "sg:postcode":"22145",
    "sg:province":"Hamburg",
    "wof:name":"Arnold Reimer Ingenieur",
    "wof:placetype":"venue"
},
  "geometry": {"coordinates":[10.1669721603,53.6297950745],"type":"Point"}
}