{
  "type": "Feature",
  "properties": {
    "iso:country":"DE",
    "sg:address":"Seebadstr 18",
    "sg:city":"Berlin",
    "sg:phone":"+49 30/4040177",
    "sg:postcode":"13467",
    "sg:province":"Berlin",
    "wof:name":"Thermotex",
    "wof:placetype":"venue"
},
  "geometry": {"coordinates":[13.326128,52.617165],"type":"Point"}
}