{
  "type": "Feature",
  "properties": {
    "iso:country":"DE",
    "sg:address":"K\u00f6nigsallee 92 A",
    "sg:city":"D\u00fcsseldorf",
    "sg:phone":"+49 211/83870",
    "sg:postcode":"40212",
    "sg:province":"Nordrhein-Westfalen",
    "wof:name":"Wego D\u00fcsseldorfer Finanz- Treuhandgesellschaft Mbh",
    "wof:placetype":"venue"
},
  "geometry": {"coordinates":[6.779433,51.220001],"type":"Point"}
}