{
  "type": "Feature",
  "properties": {
    "iso:country":"DE",
    "sg:address":"Katharinenstr. 61",
    "sg:city":"D\u00fcren",
    "sg:phone":"+49 2421/9830",
    "sg:postcode":"52353",
    "sg:province":"Nordrhein-Westfalen",
    "wof:name":"Cws Technical Coatings Gmbh",
    "wof:placetype":"venue"
},
  "geometry": {"coordinates":[6.431402,50.842926],"type":"Point"}
}