{
  "type": "Feature",
  "properties": {
    "iso:country":"DE",
    "sg:address":"Im Graubad",
    "sg:city":"Neu-Anspach",
    "sg:phone":"+49 6081/41124",
    "sg:postcode":"61267",
    "sg:province":"Hessen",
    "wof:name":"Waldsch\u00e4nke Am Schwimmbad",
    "wof:placetype":"venue"
},
  "geometry": {"coordinates":[8.5108604431,50.2931785583],"type":"Point"}
}