{
  "type": "Feature",
  "properties": {
    "iso:country":"DE",
    "sg:address":"Spittlertorgraben 29",
    "sg:city":"N\u00fcrnberg",
    "sg:phone":"+49 911/2878808",
    "sg:postcode":"90429",
    "sg:province":"Bayern",
    "wof:name":"Tms Development-gesellschaft F\u00fcr Informationssysteme Mbh",
    "wof:placetype":"venue"
},
  "geometry": {"coordinates":[11.066217,49.451626],"type":"Point"}
}