{
  "type": "Feature",
  "properties": {
    "iso:country":"DE",
    "sg:address":"Enneper Str. 38",
    "sg:city":"Hagen",
    "sg:phone":"+49 2331/401961",
    "sg:postcode":"58135",
    "sg:province":"Nordrhein-Westfalen",
    "wof:name":"Udo Gro\u00dfkopf",
    "wof:placetype":"venue"
},
  "geometry": {"coordinates":[7.4069681168,51.3424224854],"type":"Point"}
}