{
  "type": "Feature",
  "properties": {
    "iso:country":"DE",
    "sg:address":"M\u00fchlsteig 25",
    "sg:city":"Langenzenn",
    "sg:postcode":"90579",
    "sg:province":"Bayern",
    "wof:name":"Kellner Reha - Technik Gmbh & Co. Kg",
    "wof:placetype":"venue"
},
  "geometry": {"coordinates":[10.773724556,49.4861869812],"type":"Point"}
}