{
  "type": "Feature",
  "properties": {
    "iso:country":"DE",
    "sg:address":"Magdalenenstr. 48",
    "sg:city":"Bonn",
    "sg:phone":"+49 228/613939",
    "sg:postcode":"53121",
    "sg:province":"Nordrhein-Westfalen",
    "wof:name":"W. Sch\u00f6bel",
    "wof:placetype":"venue"
},
  "geometry": {"coordinates":[7.0759911537,50.7250747681],"type":"Point"}
}