{
  "type": "Feature",
  "properties": {
    "iso:country":"DE",
    "sg:address":"Klausweg 2",
    "sg:city":"Berchtesgaden",
    "sg:phone":"+49 8652/985900",
    "sg:postcode":"83471",
    "sg:province":"Bayern",
    "wof:name":"German Heiduczek",
    "wof:placetype":"venue"
},
  "geometry": {"coordinates":[13.0561723709,47.6304702759],"type":"Point"}
}