{
  "type": "Feature",
  "properties": {
    "iso:country":"DE",
    "sg:address":"Carl-Leverkus-Str. 16",
    "sg:city":"Langenfeld",
    "sg:phone":"+49 2173/72061",
    "sg:postcode":"40764",
    "sg:province":"Nordrhein-Westfalen",
    "wof:name":"Warenhandelsges. Mbh & Co. Kg",
    "wof:placetype":"venue"
},
  "geometry": {"coordinates":[6.965885,51.13237],"type":"Point"}
}