{
  "type": "Feature",
  "properties": {
    "iso:country":"DE",
    "sg:address":"Rendtorffstr. 4",
    "sg:city":"Berlin",
    "sg:phone":"+49 30/84571591",
    "sg:postcode":"14165",
    "sg:province":"Berlin",
    "wof:name":"Karla Schubert-landgraf",
    "wof:placetype":"venue"
},
  "geometry": {"coordinates":[13.2659921646,52.4122009277],"type":"Point"}
}