{
  "type": "Feature",
  "properties": {
    "iso:country":"DE",
    "sg:address":"M\u00fchlenweg 10",
    "sg:city":"Morsum",
    "sg:phone":"+49 4233/1745",
    "sg:postcode":"27321",
    "sg:province":"Niedersachsen",
    "wof:name":"Fantastic Hardware",
    "wof:placetype":"venue"
},
  "geometry": {"coordinates":[9.083674,52.957821],"type":"Point"}
}