{
  "type": "Feature",
  "properties": {
    "iso:country":"DE",
    "sg:address":"Bahnhofstr. 98a",
    "sg:city":"Nidderau",
    "sg:phone":"+49 6187/25937",
    "sg:postcode":"61130",
    "sg:province":"Hessen",
    "wof:name":"Angelika Neubert-reuther Praxis F\u00fcr Krankengymnastik",
    "wof:placetype":"venue"
},
  "geometry": {"coordinates":[8.8745603561,50.2351531982],"type":"Point"}
}