{
  "type": "Feature",
  "properties": {
    "iso:country":"DE",
    "sg:address":"Pfarrstr. 11",
    "sg:city":"V\u00f6hringen",
    "sg:phone":"+49 7454/2625",
    "sg:postcode":"72189",
    "sg:province":"Baden-W\u00fcrttemberg",
    "wof:name":"Ev. Pfarramt",
    "wof:placetype":"venue"
},
  "geometry": {"coordinates":[8.6621427536,48.3340415955],"type":"Point"}
}