{
  "type": "Feature",
  "properties": {
    "iso:country":"DE",
    "sg:address":"An der Burg 1",
    "sg:city":"Baesweiler",
    "sg:phone":"+49 2401/6001",
    "sg:postcode":"52499",
    "sg:province":"Nordrhein-Westfalen",
    "wof:name":"Alten- Und Pflegeheim Burg Setterich",
    "wof:placetype":"venue"
},
  "geometry": {"coordinates":[6.20239,50.923779],"type":"Point"}
}