{
  "type": "Feature",
  "properties": {
    "iso:country":"DE",
    "sg:address":"Am Steinern Kreuz 29",
    "sg:city":"Lengerich",
    "sg:phone":"+49 5482/1036",
    "sg:postcode":"49525",
    "sg:province":"Nordrhein-Westfalen",
    "wof:name":"Hermann Fiegenbaum",
    "wof:placetype":"venue"
},
  "geometry": {"coordinates":[7.79545,52.198215],"type":"Point"}
}