{
  "type": "Feature",
  "properties": {
    "iso:country":"DE",
    "sg:address":"Marktplatz 6",
    "sg:city":"Erpel",
    "sg:phone":"+49 2644/2495",
    "sg:postcode":"53579",
    "sg:province":"Rheinland-Pfalz",
    "wof:name":"Gastst\u00e4tte Om Maat",
    "wof:placetype":"venue"
},
  "geometry": {"coordinates":[7.2390899658,50.5828895569],"type":"Point"}
}