{
  "type": "Feature",
  "properties": {
    "iso:country":"DE",
    "sg:address":"Kurbrunnenstr. 9",
    "sg:city":"Bad D\u00fcrkheim",
    "sg:phone":"+49 6322/981087",
    "sg:postcode":"67098",
    "sg:province":"Rheinland-Pfalz",
    "wof:name":"Wein & Design Claudia Magin",
    "wof:placetype":"venue"
},
  "geometry": {"coordinates":[8.1691627502,49.4639701843],"type":"Point"}
}