{
  "type": "Feature",
  "properties": {
    "iso:country":"DE",
    "sg:address":"Bertolt-Brecht-Str. 2",
    "sg:city":"Unna",
    "sg:phone":"+49 2303/53633",
    "sg:postcode":"59427",
    "sg:province":"Nordrhein-Westfalen",
    "wof:name":"Bk - Promotion Gmbh",
    "wof:placetype":"venue"
},
  "geometry": {"coordinates":[7.6560192108,51.536857605],"type":"Point"}
}