{
  "type": "Feature",
  "properties": {
    "iso:country":"DE",
    "sg:address":"Hardtstr. 2",
    "sg:city":"Neuler",
    "sg:phone":"+49 7961/51263",
    "sg:postcode":"73491",
    "sg:province":"Baden-W\u00fcrttemberg",
    "wof:name":"Franz Emer",
    "wof:placetype":"venue"
},
  "geometry": {"coordinates":[10.071912,48.929115],"type":"Point"}
}