{
  "type": "Feature",
  "properties": {
    "iso:country":"DE",
    "sg:address":"Im Roth 6",
    "sg:city":"Spiesen-Elversberg",
    "sg:phone":"+49 6821/741612",
    "sg:postcode":"66583",
    "sg:province":"Saarland",
    "wof:name":"Z I Consult Gmbh",
    "wof:placetype":"venue"
},
  "geometry": {"coordinates":[7.159891,49.32098],"type":"Point"}
}