{
  "type": "Feature",
  "properties": {
    "iso:country":"DE",
    "sg:address":"Neue Marktstr. 15",
    "sg:city":"Treuenbrietzen",
    "sg:postcode":"14929",
    "sg:province":"Brandenburg",
    "wof:name":"Katholisches Pfarramt Treuenbrietzen",
    "wof:placetype":"venue"
},
  "geometry": {"coordinates":[12.8701448441,52.0950393677],"type":"Point"}
}