{
  "type": "Feature",
  "properties": {
    "iso:country":"DE",
    "sg:address":"Paunsdorfer Allee 1",
    "sg:city":"Leipzig",
    "sg:phone":"+49 341/2518917",
    "sg:postcode":"04329",
    "sg:province":"Sachsen",
    "wof:name":"Orsay Gmbh",
    "wof:placetype":"venue"
},
  "geometry": {"coordinates":[12.47903,51.34877],"type":"Point"}
}