{
  "type": "Feature",
  "properties": {
    "iso:country":"DE",
    "sg:address":"Brandenburger Platz 19",
    "sg:city":"Saarbr\u00fccken",
    "sg:postcode":"66121",
    "sg:province":"Saarland",
    "wof:name":"Gerd Marx Und Partner Architekten Und",
    "wof:placetype":"venue"
},
  "geometry": {"coordinates":[7.04351,49.233219],"type":"Point"}
}