{
  "type": "Feature",
  "properties": {
    "iso:country":"DE",
    "sg:address":"Weserstr. 15",
    "sg:city":"Frankfurt",
    "sg:postcode":"60329",
    "sg:province":"Hessen",
    "wof:name":"Mehanny Gastronomie- Und Hotel-betrieb Verwaltungs",
    "wof:placetype":"venue"
},
  "geometry": {"coordinates":[8.669788,50.10817],"type":"Point"}
}