{
  "type": "Feature",
  "properties": {
    "iso:country":"DE",
    "sg:address":"Georg-Zimmerer-Str. 19",
    "sg:city":"Sigmaringen",
    "sg:phone":"+49 7571/50411",
    "sg:postcode":"72488",
    "sg:province":"Baden-W\u00fcrttemberg",
    "wof:name":"Campingplatz Sigmaringen",
    "wof:placetype":"venue"
},
  "geometry": {"coordinates":[9.211532,48.084927],"type":"Point"}
}