{
  "type": "Feature",
  "properties": {
    "iso:country":"DE",
    "sg:address":"Austr. 11",
    "sg:city":"Lottstetten",
    "sg:phone":"+49 7745/7340",
    "sg:postcode":"79807",
    "sg:province":"Baden-W\u00fcrttemberg",
    "wof:name":"G\u00fcnther Haberstock",
    "wof:placetype":"venue"
},
  "geometry": {"coordinates":[8.571688652,47.6318664551],"type":"Point"}
}