{
  "type": "Feature",
  "properties": {
    "iso:country":"DE",
    "sg:address":"Lauzenstr. 34",
    "sg:city":"Bad Orb",
    "sg:phone":"+49 6052/5672",
    "sg:postcode":"63619",
    "sg:province":"Hessen",
    "wof:name":"Helmut Acker",
    "wof:placetype":"venue"
},
  "geometry": {"coordinates":[9.35365,50.230614],"type":"Point"}
}