{
  "type": "Feature",
  "properties": {
    "iso:country":"DE",
    "sg:address":"Schillerstr.",
    "sg:city":"Taucha",
    "sg:phone":"+49 34298/4000",
    "sg:postcode":"04425",
    "sg:province":"Sachsen",
    "wof:name":"Raab Karcher Baustoffe Gmbh",
    "wof:placetype":"venue"
},
  "geometry": {"coordinates":[12.4855976105,51.380443573],"type":"Point"}
}