{
  "type": "Feature",
  "properties": {
    "iso:country":"DE",
    "sg:address":"Fl\u00f6rkenkamp 3",
    "sg:city":"Lemgo",
    "sg:phone":"+49 5261/17494",
    "sg:postcode":"32657",
    "sg:province":"Nordrhein-Westfalen",
    "wof:name":"Helmut Lentfer Verlagsvertretung",
    "wof:placetype":"venue"
},
  "geometry": {"coordinates":[8.9153308868,52.0411262512],"type":"Point"}
}