{
  "type": "Feature",
  "properties": {
    "iso:country":"DE",
    "sg:address":"August-Bebel-Str. 31",
    "sg:city":"Vacha",
    "sg:phone":"+49 36962/24251",
    "sg:postcode":"36404",
    "sg:province":"Th\u00fcringen",
    "wof:name":"J\u00f6rg Bohn",
    "wof:placetype":"venue"
},
  "geometry": {"coordinates":[10.0184803009,50.8241996765],"type":"Point"}
}