{
  "type": "Feature",
  "properties": {
    "iso:country":"DE",
    "sg:address":"Fritz-Reuter-Str. 38",
    "sg:city":"Dresden",
    "sg:phone":"+49 351/8498823",
    "sg:postcode":"01097",
    "sg:province":"Sachsen",
    "wof:name":"Holztechnik Dresden Gmbh",
    "wof:placetype":"venue"
},
  "geometry": {"coordinates":[13.7393302917,51.0738792419],"type":"Point"}
}