{
  "type": "Feature",
  "properties": {
    "iso:country":"DE",
    "sg:address":"Schillerstr. 20",
    "sg:city":"D\u00fcsseldorf",
    "sg:phone":"+49 211/67020",
    "sg:postcode":"40237",
    "sg:province":"Nordrhein-Westfalen",
    "wof:name":"Eva Eisenbahn-verkehrsmittel- Gesellschaft Mbh",
    "wof:placetype":"venue"
},
  "geometry": {"coordinates":[6.7991781235,51.2340431213],"type":"Point"}
}