{
  "type": "Feature",
  "properties": {
    "iso:country":"DE",
    "sg:address":"Hauffweg 5",
    "sg:city":"Lauchheim",
    "sg:phone":"+49 7363/6214",
    "sg:postcode":"73466",
    "sg:province":"Baden-W\u00fcrttemberg",
    "wof:name":"H. Baumgartner",
    "wof:placetype":"venue"
},
  "geometry": {"coordinates":[10.25102,48.875191],"type":"Point"}
}