{
  "type": "Feature",
  "properties": {
    "iso:country":"DE",
    "sg:address":"Ockersh\u00e4user Allee 13",
    "sg:city":"Marburg",
    "sg:phone":"+49 6421/25242",
    "sg:postcode":"35037",
    "sg:province":"Hessen",
    "wof:name":"Joseph Paffrath",
    "wof:placetype":"venue"
},
  "geometry": {"coordinates":[8.7571382523,50.8043823242],"type":"Point"}
}