{
  "type": "Feature",
  "properties": {
    "iso:country":"DE",
    "sg:address":"Schuhstr. 6",
    "sg:city":"Halberstadt",
    "sg:postcode":"38820",
    "sg:province":"Sachsen-Anhalt",
    "wof:name":"Wenzel Hachmann Gbr",
    "wof:placetype":"venue"
},
  "geometry": {"coordinates":[11.052286,51.896626],"type":"Point"}
}