{
  "type": "Feature",
  "properties": {
    "iso:country":"DE",
    "sg:address":"Bahnhofstr. 72",
    "sg:city":"Herne",
    "sg:phone":"+49 2323/18731",
    "sg:postcode":"44623",
    "sg:province":"Nordrhein-Westfalen",
    "wof:name":"Gro\u00dfb\u00e4ckerei Rokas Gmbh",
    "wof:placetype":"venue"
},
  "geometry": {"coordinates":[7.221531,51.541817],"type":"Point"}
}