{
  "type": "Feature",
  "properties": {
    "iso:country":"DE",
    "sg:address":"M\u00f6rikeweg 1",
    "sg:city":"Spaichingen",
    "sg:phone":"+49 7424/2479",
    "sg:postcode":"78549",
    "sg:province":"Baden-W\u00fcrttemberg",
    "wof:name":"A. J\u00fctzler Ingenieur",
    "wof:placetype":"venue"
},
  "geometry": {"coordinates":[8.7410879135,48.0802993774],"type":"Point"}
}