{
  "type": "Feature",
  "properties": {
    "iso:country":"DE",
    "sg:address":"Untere Bachstr. 31",
    "sg:city":"Wallersdorf",
    "sg:phone":"+49 9933/1209",
    "sg:postcode":"94522",
    "sg:province":"Bayern",
    "wof:name":"Johann Wittmann",
    "wof:placetype":"venue"
},
  "geometry": {"coordinates":[12.706125,48.739296],"type":"Point"}
}