{
  "type": "Feature",
  "properties": {
    "iso:country":"DE",
    "sg:address":"Friedhofstr. 5",
    "sg:city":"Sulzbach",
    "sg:phone":"+49 6028/995868",
    "sg:postcode":"63834",
    "sg:province":"Bayern",
    "wof:name":"Braunwartsm\u00fchle",
    "wof:placetype":"venue"
},
  "geometry": {"coordinates":[9.8468551636,48.967010498],"type":"Point"}
}