{
  "type": "Feature",
  "properties": {
    "iso:country":"DE",
    "sg:address":"Prunn 1",
    "sg:city":"Riedenburg",
    "sg:phone":"+49 9442/3323",
    "sg:postcode":"93339",
    "sg:province":"Bayern",
    "wof:name":"Schloss Prunn Bei Kehlheim Im Altm\u00fchltal",
    "wof:placetype":"venue"
},
  "geometry": {"coordinates":[11.702349,48.959743],"type":"Point"}
}