{
  "type": "Feature",
  "properties": {
    "iso:country":"DE",
    "sg:address":"Hainstr. 17",
    "sg:city":"Leipzig",
    "sg:postcode":"04109",
    "sg:province":"Sachsen",
    "wof:name":"Kinder\u00e4rztliche Praxis Thieme-verlag",
    "wof:placetype":"venue"
},
  "geometry": {"coordinates":[12.3730649948,51.3425102234],"type":"Point"}
}