{
  "type": "Feature",
  "properties": {
    "iso:country":"DE",
    "sg:address":"Bleicherstr. 7",
    "sg:city":"Hildesheim",
    "sg:phone":"+49 5121/41033",
    "sg:postcode":"31137",
    "sg:province":"Niedersachsen",
    "wof:name":"W\u00e4scherei Strube",
    "wof:placetype":"venue"
},
  "geometry": {"coordinates":[9.9384145737,52.1520271301],"type":"Point"}
}