{
  "type": "Feature",
  "properties": {
    "iso:country":"DE",
    "sg:address":"Klosterstr. 11",
    "sg:city":"Bad Oeynhausen",
    "sg:phone":"+49 5731/28307",
    "sg:postcode":"32545",
    "sg:province":"Nordrhein-Westfalen",
    "wof:name":"Ecco",
    "wof:placetype":"venue"
},
  "geometry": {"coordinates":[8.797512,52.203457],"type":"Point"}
}