{
  "type": "Feature",
  "properties": {
    "iso:country":"DE",
    "sg:address":"Leonberger Str. 7",
    "sg:city":"Ditzingen",
    "sg:phone":"+49 7156/34384",
    "sg:postcode":"71254",
    "sg:province":"Baden-W\u00fcrttemberg",
    "wof:name":"Video-aktuell Gmbh",
    "wof:placetype":"venue"
},
  "geometry": {"coordinates":[9.0665597916,48.8260002136],"type":"Point"}
}