{
  "type": "Feature",
  "properties": {
    "iso:country":"DE",
    "sg:address":"Englmannstr. 1",
    "sg:city":"M\u00fcnchen",
    "sg:phone":"+49 89/43109065",
    "sg:postcode":"81673",
    "sg:province":"Bayern",
    "wof:name":"Hans Bl\u00fcmhuber Gmbh",
    "wof:placetype":"venue"
},
  "geometry": {"coordinates":[11.627968,48.130833],"type":"Point"}
}