{
  "type": "Feature",
  "properties": {
    "iso:country":"DE",
    "sg:address":"Mercedesstr. 83",
    "sg:city":"Stuttgart",
    "sg:phone":"+49 711/551543",
    "sg:postcode":"70372",
    "sg:province":"Baden-W\u00fcrttemberg",
    "wof:name":"H. Gerstenh\u00f6fer",
    "wof:placetype":"venue"
},
  "geometry": {"coordinates":[9.230856,48.794052],"type":"Point"}
}