{
  "type": "Feature",
  "properties": {
    "iso:country":"DE",
    "sg:address":"F\u00f6ssestr. 30",
    "sg:city":"Hannover",
    "sg:phone":"+49 511/446603",
    "sg:postcode":"30451",
    "sg:province":"Niedersachsen",
    "wof:name":"Christines Haarstudio",
    "wof:placetype":"venue"
},
  "geometry": {"coordinates":[9.7073659897,52.3703384399],"type":"Point"}
}