{
  "type": "Feature",
  "properties": {
    "iso:country":"DE",
    "sg:address":"Sassestr. 16",
    "sg:city":"Rheinbach",
    "sg:phone":"+49 2226/4295",
    "sg:postcode":"53359",
    "sg:province":"Nordrhein-Westfalen",
    "wof:name":"Joachim Jahnke Architekt",
    "wof:placetype":"venue"
},
  "geometry": {"coordinates":[6.943129,50.632088],"type":"Point"}
}