{
  "type": "Feature",
  "properties": {
    "iso:country":"DE",
    "sg:address":"Langgasse 2",
    "sg:city":"Hattersheim",
    "sg:phone":"+49 6190/6197",
    "sg:postcode":"65795",
    "sg:province":"Hessen",
    "wof:name":"Am Kamin",
    "wof:placetype":"venue"
},
  "geometry": {"coordinates":[8.4996795654,50.0524024963],"type":"Point"}
}