{
  "type": "Feature",
  "properties": {
    "iso:country":"DE",
    "sg:address":"H\u00f6llh\u00e4userweg 43",
    "sg:city":"Baden-Baden",
    "sg:phone":"+49 7221/7901",
    "sg:postcode":"76534",
    "sg:province":"Baden-W\u00fcrttemberg",
    "wof:name":"K. Schulz",
    "wof:placetype":"venue"
},
  "geometry": {"coordinates":[8.2565402985,48.735534668],"type":"Point"}
}