{
  "type": "Feature",
  "properties": {
    "iso:country":"DE",
    "sg:address":"Gr\u00f6nenberger Str. 48",
    "sg:city":"Melle",
    "sg:phone":"+49 5422/45475",
    "sg:postcode":"49324",
    "sg:province":"Niedersachsen",
    "wof:name":"Reinhold Hilker Architekt",
    "wof:placetype":"venue"
},
  "geometry": {"coordinates":[8.329118,52.20319],"type":"Point"}
}