{
  "type": "Feature",
  "properties": {
    "iso:country":"DE",
    "sg:address":"Kulmbacher Str. 27",
    "sg:city":"Hof",
    "sg:phone":"+49 9281/63642",
    "sg:postcode":"95030",
    "sg:province":"Bayern",
    "wof:name":"Heinz-j\u00fcrgen Wenig",
    "wof:placetype":"venue"
},
  "geometry": {"coordinates":[11.9016513824,50.3180160522],"type":"Point"}
}