{
  "type": "Feature",
  "properties": {
    "iso:country":"DE",
    "sg:address":"Neue Str. 2",
    "sg:city":"Berkatal",
    "sg:phone":"+49 5657/1093",
    "sg:postcode":"37297",
    "sg:province":"Hessen",
    "wof:name":"Becker & Sch\u00e4fer Tischlerei Und Fentstebau",
    "wof:placetype":"venue"
},
  "geometry": {"coordinates":[9.9210033417,51.2356491089],"type":"Point"}
}