{
  "type": "Feature",
  "properties": {
    "iso:country":"DE",
    "sg:address":"Herwarthstr. 8",
    "sg:city":"K\u00f6ln",
    "sg:phone":"+49 221/9514980",
    "sg:postcode":"50672",
    "sg:province":"Nordrhein-Westfalen",
    "wof:name":"Codeco Coordinated Design Components Gmbh",
    "wof:placetype":"venue"
},
  "geometry": {"coordinates":[6.939732,50.943329],"type":"Point"}
}