{
  "type": "Feature",
  "properties": {
    "iso:country":"DE",
    "sg:address":"Brunnenstr. 16",
    "sg:city":"Altenstadt",
    "sg:postcode":"63674",
    "sg:province":"Hessen",
    "wof:name":"Lange Leine Nidda Ggmbh",
    "wof:placetype":"venue"
},
  "geometry": {"coordinates":[8.9735937119,50.308216095],"type":"Point"}
}