{
  "type": "Feature",
  "properties": {
    "iso:country":"DE",
    "sg:address":"Tulpenstr. 2",
    "sg:city":"Bad Rappenau",
    "sg:phone":"+49 7264/205150",
    "sg:postcode":"74906",
    "sg:province":"Baden-W\u00fcrttemberg",
    "wof:name":"Dr. Maurischat Gmbh",
    "wof:placetype":"venue"
},
  "geometry": {"coordinates":[9.100936,49.235718],"type":"Point"}
}