{
  "type": "Feature",
  "properties": {
    "iso:country":"DE",
    "sg:address":"Am M\u00fchlberg 33",
    "sg:city":"Reinheim",
    "sg:phone":"+49 6162/83588",
    "sg:postcode":"64354",
    "sg:province":"Hessen",
    "wof:name":"Hannelore Ripper Heilpraktikerin",
    "wof:placetype":"venue"
},
  "geometry": {"coordinates":[8.8237762451,49.8284950256],"type":"Point"}
}