{
  "type": "Feature",
  "properties": {
    "iso:country":"DE",
    "sg:address":"Oststr. 24",
    "sg:city":"H\u00f6rstel",
    "sg:phone":"+49 5459/7104",
    "sg:postcode":"48477",
    "sg:province":"Nordrhein-Westfalen",
    "wof:name":"Rudolf Grotke",
    "wof:placetype":"venue"
},
  "geometry": {"coordinates":[7.6050019264,52.3004417419],"type":"Point"}
}