{
  "type": "Feature",
  "properties": {
    "iso:country":"DE",
    "sg:address":"Am P\u00f6llnitzbach 6",
    "sg:city":"Niederp\u00f6llnitz",
    "sg:phone":"+49 36607/60039",
    "sg:postcode":"07570",
    "sg:province":"Th\u00fcringen",
    "wof:name":"Niederp\u00f6llnitzer Mutterkuh Gmbh",
    "wof:placetype":"venue"
},
  "geometry": {"coordinates":[11.95852,50.756283],"type":"Point"}
}