{
  "type": "Feature",
  "properties": {
    "iso:country":"DE",
    "sg:address":"Kirchstr. 22",
    "sg:city":"Barbing",
    "sg:phone":"+49 9401/2744",
    "sg:postcode":"93092",
    "sg:province":"Bayern",
    "wof:name":"Tennis Und Squash Meier",
    "wof:placetype":"venue"
},
  "geometry": {"coordinates":[12.1968860626,49.0048294067],"type":"Point"}
}