{
  "type": "Feature",
  "properties": {
    "iso:country":"DE",
    "sg:address":"Max-von-M\u00fcller-Weg 4",
    "sg:city":"N\u00fcrnberg",
    "sg:phone":"+49 911/564577",
    "sg:postcode":"90411",
    "sg:province":"Bayern",
    "wof:name":"Karl Lutter Architekt",
    "wof:placetype":"venue"
},
  "geometry": {"coordinates":[11.096728,49.47456],"type":"Point"}
}