{
  "type": "Feature",
  "properties": {
    "iso:country":"DE",
    "sg:address":"Kirchhalde 9",
    "sg:city":"Stockach",
    "sg:phone":"+49 7771/80060",
    "sg:postcode":"78333",
    "sg:province":"Baden-W\u00fcrttemberg",
    "wof:name":"Carl Pfeiffer Gmbh & Co. Kg",
    "wof:placetype":"venue"
},
  "geometry": {"coordinates":[9.0105991364,47.8512916565],"type":"Point"}
}