{
  "type": "Feature",
  "properties": {
    "iso:country":"DE",
    "sg:address":"Danziger Str. 13",
    "sg:city":"Biebertal",
    "sg:phone":"+49 6409/2094",
    "sg:postcode":"35444",
    "sg:province":"Hessen",
    "wof:name":"Reinhardt Und Walter Ges. F\u00fcr Immobilienmanagement Mbh",
    "wof:placetype":"venue"
},
  "geometry": {"coordinates":[8.590393,50.627594],"type":"Point"}
}