{
  "type": "Feature",
  "properties": {
    "iso:country":"DE",
    "sg:address":"Gro\u00dfe Kalandstr. 30",
    "sg:city":"Wei\u00dfenfels",
    "sg:phone":"+49 3443/303725",
    "sg:postcode":"06667",
    "sg:province":"Sachsen-Anhalt",
    "wof:name":"G. Kretschmann",
    "wof:placetype":"venue"
},
  "geometry": {"coordinates":[11.9683656693,51.2015647888],"type":"Point"}
}