{
  "type": "Feature",
  "properties": {
    "iso:country":"DE",
    "sg:address":"Amselring 15",
    "sg:city":"B\u00f6rger",
    "sg:phone":"+49 5953/500",
    "sg:postcode":"26904",
    "sg:province":"Niedersachsen",
    "wof:name":"Hermann Rekers",
    "wof:placetype":"venue"
},
  "geometry": {"coordinates":[7.5399551392,52.9169960022],"type":"Point"}
}