{
  "type": "Feature",
  "properties": {
    "iso:country":"DE",
    "sg:address":"Kaiserstr 70",
    "sg:city":"Rastatt",
    "sg:phone":"+49 7222/103010",
    "sg:postcode":"76437",
    "sg:province":"Baden-W\u00fcrttemberg",
    "wof:name":"Netsurf Edv-betreuungs-gesellschaf Mbh",
    "wof:placetype":"venue"
},
  "geometry": {"coordinates":[8.1987361908,48.8619918823],"type":"Point"}
}