{
  "type": "Feature",
  "properties": {
    "iso:country":"DE",
    "sg:address":"Postf. 1121",
    "sg:city":"Haar",
    "sg:phone":"+49 89",
    "sg:postcode":"85540",
    "sg:province":"Bayern",
    "wof:name":"Dream-woman International",
    "wof:placetype":"venue"
},
  "geometry": {"coordinates":[11.728955,48.110554],"type":"Point"}
}