{
  "type": "Feature",
  "properties": {
    "iso:country":"DE",
    "sg:address":"Reichau 20",
    "sg:city":"Boos",
    "sg:phone":"+49 8333/1478",
    "sg:postcode":"87737",
    "sg:province":"Bayern",
    "wof:name":"L. Pr\u00f6bstl",
    "wof:placetype":"venue"
},
  "geometry": {"coordinates":[10.2221927643,48.0864372253],"type":"Point"}
}