{
  "type": "Feature",
  "properties": {
    "iso:country":"DE",
    "sg:address":"Bauernanger 12",
    "sg:city":"Bodenmais",
    "sg:phone":"+49 9924/408",
    "sg:postcode":"94249",
    "sg:province":"Bayern",
    "wof:name":"Erika Lang",
    "wof:placetype":"venue"
},
  "geometry": {"coordinates":[13.0971031189,49.0686798096],"type":"Point"}
}