{
  "type": "Feature",
  "properties": {
    "iso:country":"DE",
    "sg:address":"An der Burg 14",
    "sg:city":"Loxstedt",
    "sg:phone":"+49 4703/1273",
    "sg:postcode":"27612",
    "sg:province":"Niedersachsen",
    "wof:name":"Werner Neddermann",
    "wof:placetype":"venue"
},
  "geometry": {"coordinates":[8.690645,53.491859],"type":"Point"}
}