{
  "type": "Feature",
  "properties": {
    "iso:country":"DE",
    "sg:address":"Jahnstr. 56",
    "sg:city":"Kassel",
    "sg:phone":"+49 561/571102",
    "sg:postcode":"34123",
    "sg:province":"Hessen",
    "wof:name":"Kurt Heinemann Bootsvermietung",
    "wof:placetype":"venue"
},
  "geometry": {"coordinates":[9.5046367645,51.3091583252],"type":"Point"}
}