{
  "type": "Feature",
  "properties": {
    "iso:country":"DE",
    "sg:address":"Marienthaler Str 63",
    "sg:city":"Zwickau",
    "sg:phone":"+49 375/525496",
    "sg:postcode":"08060",
    "sg:province":"Sachsen",
    "wof:name":"Gefa Tresortechnik G. Gora",
    "wof:placetype":"venue"
},
  "geometry": {"coordinates":[12.4659519196,50.7194709778],"type":"Point"}
}