{
  "type": "Feature",
  "properties": {
    "iso:country":"DE",
    "sg:address":"Flagentwiet 37",
    "sg:city":"Hamburg",
    "sg:phone":"+49 40/55983000",
    "sg:postcode":"22457",
    "sg:province":"Hamburg",
    "wof:name":"Plan Net Service Axel Kayatz",
    "wof:placetype":"venue"
},
  "geometry": {"coordinates":[9.9033031464,53.636051178],"type":"Point"}
}