{
  "type": "Feature",
  "properties": {
    "iso:country":"DE",
    "sg:address":"Fiedlerstr. 30",
    "sg:city":"Kassel",
    "sg:phone":"+49 561/8709393",
    "sg:postcode":"34127",
    "sg:province":"Hessen",
    "wof:name":"Delta-markt",
    "wof:placetype":"venue"
},
  "geometry": {"coordinates":[9.5011329651,51.3309059143],"type":"Point"}
}