{
  "type": "Feature",
  "properties": {
    "iso:country":"DE",
    "sg:address":"Neue Strandstr. 49",
    "sg:city":"Zinnowitz",
    "sg:phone":"+49 38377/42888",
    "sg:postcode":"17454",
    "sg:province":"Mecklenburg-Vorpommern",
    "wof:name":"M. Kr\u00fcger",
    "wof:placetype":"venue"
},
  "geometry": {"coordinates":[13.908678,54.076393],"type":"Point"}
}