{
  "type": "Feature",
  "properties": {
    "iso:country":"DE",
    "sg:address":"Steendiek 30",
    "sg:city":"Hamburg",
    "sg:phone":"+49 40/7425755",
    "sg:postcode":"21129",
    "sg:province":"Hamburg",
    "wof:name":"Sikos Laden",
    "wof:placetype":"venue"
},
  "geometry": {"coordinates":[9.8803358078,53.5322685242],"type":"Point"}
}