{
  "type": "Feature",
  "properties": {
    "iso:country":"DE",
    "sg:address":"Sonnenstr. 40",
    "sg:city":"Wallerfangen",
    "sg:phone":"+49 6831/62241",
    "sg:postcode":"66798",
    "sg:province":"Saarland",
    "wof:name":"Bistro Bajazzo Gmbh",
    "wof:placetype":"venue"
},
  "geometry": {"coordinates":[6.7121357918,49.3310546875],"type":"Point"}
}