{
  "type": "Feature",
  "properties": {
    "iso:country":"DE",
    "sg:address":"Puschkinstr. 3",
    "sg:city":"Schwerin",
    "sg:postcode":"19055",
    "sg:province":"Mecklenburg-Vorpommern",
    "wof:name":"Evangelisch-lutherische St. Nikolai-kirche",
    "wof:placetype":"venue"
},
  "geometry": {"coordinates":[11.4170627594,53.6325912476],"type":"Point"}
}