{
  "type": "Feature",
  "properties": {
    "iso:country":"DE",
    "sg:address":"Bergstr. 1",
    "sg:city":"Greifenstein",
    "sg:phone":"+49 6478/2585",
    "sg:postcode":"35753",
    "sg:province":"Hessen",
    "wof:name":"Bogdan Ulm",
    "wof:placetype":"venue"
},
  "geometry": {"coordinates":[8.303465,50.582943],"type":"Point"}
}