{
  "type": "Feature",
  "properties": {
    "iso:country":"DE",
    "sg:address":"M\u00fchlenstr. 29-31",
    "sg:city":"Gevelsberg",
    "sg:phone":"+49 2332/964406",
    "sg:postcode":"58285",
    "sg:province":"Nordrhein-Westfalen",
    "wof:name":"Bekir Sahin",
    "wof:placetype":"venue"
},
  "geometry": {"coordinates":[7.3471550941,51.3243904114],"type":"Point"}
}