{
  "type": "Feature",
  "properties": {
    "iso:country":"DE",
    "sg:address":"Brunnenbreite 2",
    "sg:city":"Lappersdorf",
    "sg:postcode":"93138",
    "sg:province":"Bayern",
    "wof:name":"Pb Beratung Und Verwaltung Gmbh",
    "wof:placetype":"venue"
},
  "geometry": {"coordinates":[12.073104,49.051373],"type":"Point"}
}