{
  "type": "Feature",
  "properties": {
    "iso:country":"DE",
    "sg:address":"Langenfelde 136",
    "sg:city":"Kiel",
    "sg:phone":"+49 431/3750914",
    "sg:postcode":"24159",
    "sg:province":"Schleswig-Holstein",
    "wof:name":"Klaus-j\u00fcrgen Buck",
    "wof:placetype":"venue"
},
  "geometry": {"coordinates":[10.1711750031,54.4158973694],"type":"Point"}
}