{
  "type": "Feature",
  "properties": {
    "iso:country":"DE",
    "sg:address":"Haarlemer Str. 65",
    "sg:city":"Berlin",
    "sg:phone":"+49 30/6062031",
    "sg:postcode":"12359",
    "sg:province":"Berlin",
    "wof:name":"Abbeizerei",
    "wof:placetype":"venue"
},
  "geometry": {"coordinates":[13.454407692,52.4548988342],"type":"Point"}
}