{
  "type": "Feature",
  "properties": {
    "iso:country":"DE",
    "sg:address":"Burgstr. 22",
    "sg:city":"Herrsching",
    "sg:phone":"+49 8152/969522",
    "sg:postcode":"82211",
    "sg:province":"Bayern",
    "wof:name":"Compulogical Soft- Und Hardware Gmbh",
    "wof:placetype":"venue"
},
  "geometry": {"coordinates":[11.198141,48.020248],"type":"Point"}
}