{
  "type": "Feature",
  "properties": {
    "iso:country":"DE",
    "sg:address":"Damerauer Allee 26",
    "sg:city":"Berlin",
    "sg:phone":"+49 175",
    "sg:postcode":"12621",
    "sg:province":"Berlin",
    "wof:name":"Callfix-callingcards",
    "wof:placetype":"venue"
},
  "geometry": {"coordinates":[13.565036,52.479759],"type":"Point"}
}