{
  "type": "Feature",
  "properties": {
    "iso:country":"DE",
    "sg:address":"Triangeler Hauptstr.",
    "sg:city":"Sassenburg",
    "sg:phone":"+49 5371/6890",
    "sg:postcode":"38524",
    "sg:province":"Niedersachsen",
    "wof:name":"Glunz Ag",
    "wof:placetype":"venue"
},
  "geometry": {"coordinates":[10.5967302322,52.5060386658],"type":"Point"}
}