{
  "type": "Feature",
  "properties": {
    "iso:country":"DE",
    "sg:address":"Oelm\u00fchlenstr. 101",
    "sg:city":"Bielefeld",
    "sg:phone":"+49 521/2700757",
    "sg:postcode":"33604",
    "sg:province":"Nordrhein-Westfalen",
    "wof:name":"A-mode In Pelz Gmbh",
    "wof:placetype":"venue"
},
  "geometry": {"coordinates":[8.550827,52.014488],"type":"Point"}
}