{
  "type": "Feature",
  "properties": {
    "iso:country":"DE",
    "sg:address":"Marktplatz 8",
    "sg:city":"Meersburg",
    "sg:phone":"+49 7532/6087",
    "sg:postcode":"88709",
    "sg:province":"Baden-W\u00fcrttemberg",
    "wof:name":"Fritz Wurster",
    "wof:placetype":"venue"
},
  "geometry": {"coordinates":[9.272966,47.694725],"type":"Point"}
}