{
  "type": "Feature",
  "properties": {
    "iso:country":"DE",
    "sg:address":"Br\u00fcderstr. 2",
    "sg:city":"Zittau",
    "sg:phone":"+49 3583/510185",
    "sg:postcode":"02763",
    "sg:province":"Sachsen",
    "wof:name":"I. Looke",
    "wof:placetype":"venue"
},
  "geometry": {"coordinates":[14.8086652756,50.8964958191],"type":"Point"}
}