{
  "type": "Feature",
  "properties": {
    "iso:country":"DE",
    "sg:address":"Bahnhofstr. 30",
    "sg:city":"Gauting",
    "sg:phone":"+49 89/8502550",
    "sg:postcode":"82131",
    "sg:province":"Bayern",
    "wof:name":"Caf\u00e8 Babylon",
    "wof:placetype":"venue"
},
  "geometry": {"coordinates":[11.377635,48.069317],"type":"Point"}
}