{
  "type": "Feature",
  "properties": {
    "iso:country":"DE",
    "sg:address":"Industriestr. 8",
    "sg:city":"Falkenberg",
    "sg:postcode":"84326",
    "sg:province":"Bayern",
    "wof:name":"Katro Ges.mbh",
    "wof:placetype":"venue"
},
  "geometry": {"coordinates":[12.7229728699,48.4619255066],"type":"Point"}
}