{
  "type": "Feature",
  "properties": {
    "iso:country":"DE",
    "sg:address":"Nordh\u00e4user Str. 1",
    "sg:city":"Erfurt",
    "sg:phone":"+49 361/26544",
    "sg:postcode":"99089",
    "sg:province":"Th\u00fcringen",
    "wof:name":"Ursula Irmer",
    "wof:placetype":"venue"
},
  "geometry": {"coordinates":[11.020183,50.982929],"type":"Point"}
}