{
  "type": "Feature",
  "properties": {
    "iso:country":"DE",
    "sg:address":"Tuckermannstr. 5",
    "sg:city":"Braunschweig",
    "sg:phone":"+49 531/2502778",
    "sg:postcode":"38118",
    "sg:province":"Niedersachsen",
    "wof:name":"Tiabb Handels Gmbh",
    "wof:placetype":"venue"
},
  "geometry": {"coordinates":[10.5055265427,52.264881134],"type":"Point"}
}