{
  "type": "Feature",
  "properties": {
    "iso:country":"DE",
    "sg:address":"Hauptstr. 30",
    "sg:city":"Sankt Johann",
    "sg:phone":"+49 2651/2614",
    "sg:postcode":"56727",
    "sg:province":"Rheinland-Pfalz",
    "wof:name":"Josef Wollenweber",
    "wof:placetype":"venue"
},
  "geometry": {"coordinates":[7.194657,50.348286],"type":"Point"}
}