{
  "type": "Feature",
  "properties": {
    "iso:country":"DE",
    "sg:address":"Venloer Str. 615",
    "sg:city":"Pulheim",
    "sg:phone":"+49 2238/15288",
    "sg:postcode":"50259",
    "sg:province":"Nordrhein-Westfalen",
    "wof:name":"Konstantinidis Kavalla",
    "wof:placetype":"venue"
},
  "geometry": {"coordinates":[6.794875145,51.0006256104],"type":"Point"}
}