{
  "type": "Feature",
  "properties": {
    "iso:country":"DE",
    "sg:address":"Neckarstr. 6 D",
    "sg:city":"Eggenstein-Leopoldshafen",
    "sg:phone":"+49 7247/2361",
    "sg:postcode":"76344",
    "sg:province":"Baden-W\u00fcrttemberg",
    "wof:name":"Franz Prskawetz Steuerberater",
    "wof:placetype":"venue"
},
  "geometry": {"coordinates":[8.4040298462,49.0933303833],"type":"Point"}
}