{
  "type": "Feature",
  "properties": {
    "iso:country":"DE",
    "sg:address":"Albblickweg 5",
    "sg:city":"K\u00f6nigsfeld",
    "sg:phone":"+49 7725/7132",
    "sg:postcode":"78126",
    "sg:province":"Baden-W\u00fcrttemberg",
    "wof:name":"Gabriele Bildhauer",
    "wof:placetype":"venue"
},
  "geometry": {"coordinates":[8.447479248,48.1408996582],"type":"Point"}
}