{
  "type": "Feature",
  "properties": {
    "iso:country":"DE",
    "sg:address":"Nortruper Str. 2",
    "sg:city":"Kettenkamp",
    "sg:phone":"+49 5436/9242",
    "sg:postcode":"49577",
    "sg:province":"Niedersachsen",
    "wof:name":"Dettmer Transport- Und Entsorgungs Gmbh",
    "wof:placetype":"venue"
},
  "geometry": {"coordinates":[7.847410202,52.5936012268],"type":"Point"}
}