{
  "type": "Feature",
  "properties": {
    "iso:country":"DE",
    "sg:address":"Randersackerer Str. 44a",
    "sg:city":"W\u00fcrzburg",
    "sg:phone":"+49 931/870702",
    "sg:postcode":"97072",
    "sg:province":"Bayern",
    "wof:name":"Herbig",
    "wof:placetype":"venue"
},
  "geometry": {"coordinates":[9.938837,49.777542],"type":"Point"}
}