{
  "type": "Feature",
  "properties": {
    "iso:country":"DE",
    "sg:address":"Schleifm\u00fchlestr. 9",
    "sg:city":"Owen",
    "sg:phone":"+49 7021/58463",
    "sg:postcode":"73277",
    "sg:province":"Baden-W\u00fcrttemberg",
    "wof:name":"Ernst Winkler",
    "wof:placetype":"venue"
},
  "geometry": {"coordinates":[9.448713,48.583759],"type":"Point"}
}