{
  "type": "Feature",
  "properties": {
    "iso:country":"DE",
    "sg:address":"Kurpromenade 2",
    "sg:city":"Timmendorfer Strand",
    "sg:phone":"+49 4503/1215",
    "sg:postcode":"23669",
    "sg:province":"Schleswig-Holstein",
    "wof:name":"Restaurant Filou",
    "wof:placetype":"venue"
},
  "geometry": {"coordinates":[10.7799358368,53.9997787476],"type":"Point"}
}