{
  "type": "Feature",
  "properties": {
    "iso:country":"DE",
    "sg:address":"Neheimer Str. 24",
    "sg:city":"Werl",
    "sg:phone":"+49 2922/83644",
    "sg:postcode":"59457",
    "sg:province":"Nordrhein-Westfalen",
    "wof:name":"Wilhelm Koerdt",
    "wof:placetype":"venue"
},
  "geometry": {"coordinates":[7.9200072289,51.5461273193],"type":"Point"}
}