{
  "type": "Feature",
  "properties": {
    "iso:country":"DE",
    "sg:address":"Am Wehberg 8 a",
    "sg:city":"Dorf Mecklenburg",
    "sg:phone":"+49 3841/790010",
    "sg:postcode":"23972",
    "sg:province":"Mecklenburg-Vorpommern",
    "wof:name":"B\u00e4rbel Quade",
    "wof:placetype":"venue"
},
  "geometry": {"coordinates":[11.4663944244,53.8440132141],"type":"Point"}
}