{
  "type": "Feature",
  "properties": {
    "iso:country":"DE",
    "sg:address":"Am Roggenb\u00fchl 22",
    "sg:city":"Schwaig",
    "sg:phone":"+49 911/5074550",
    "sg:postcode":"90571",
    "sg:province":"Bayern",
    "wof:name":"G\u00fcnter B\u00fcttner",
    "wof:placetype":"venue"
},
  "geometry": {"coordinates":[11.1936721802,49.4838600159],"type":"Point"}
}