{
  "type": "Feature",
  "properties": {
    "iso:country":"DE",
    "sg:address":"Hauptstr. 52",
    "sg:city":"Hemmingen",
    "sg:postcode":"71282",
    "sg:province":"Baden-W\u00fcrttemberg",
    "wof:name":"Gasthof Bierakademie",
    "wof:placetype":"venue"
},
  "geometry": {"coordinates":[9.0307922363,48.8643684387],"type":"Point"}
}