{
  "type": "Feature",
  "properties": {
    "iso:country":"DE",
    "sg:address":"Ober-Eschbacher Str. 91",
    "sg:city":"Bad Homburg",
    "sg:phone":"+49 6172/17130",
    "sg:postcode":"61352",
    "sg:province":"Hessen",
    "wof:name":"Dierolf Rechtsanwalt",
    "wof:placetype":"venue"
},
  "geometry": {"coordinates":[8.6524219513,50.2156791687],"type":"Point"}
}