{
  "type": "Feature",
  "properties": {
    "iso:country":"DE",
    "sg:address":"Tischlerstr. 3",
    "sg:city":"Rhauderfehn",
    "sg:phone":"+49 4952/8735",
    "sg:postcode":"26817",
    "sg:province":"Niedersachsen",
    "wof:name":"E. Marks",
    "wof:placetype":"venue"
},
  "geometry": {"coordinates":[7.559849,53.146877],"type":"Point"}
}