{
  "type": "Feature",
  "properties": {
    "iso:country":"DE",
    "sg:address":"Hammerweide 31-33",
    "sg:city":"Arnsberg",
    "sg:postcode":"59821",
    "sg:province":"Nordrhein-Westfalen",
    "wof:name":"Schenk Trockenbau Gmbh",
    "wof:placetype":"venue"
},
  "geometry": {"coordinates":[8.042072,51.413502],"type":"Point"}
}