{
  "type": "Feature",
  "properties": {
    "iso:country":"DE",
    "sg:address":"Max-Herrmann-Str. 6",
    "sg:city":"Berlin",
    "sg:phone":"+49 30/93770022",
    "sg:postcode":"12687",
    "sg:province":"Berlin",
    "wof:name":"Kaisers Verbrauchermarkt",
    "wof:placetype":"venue"
},
  "geometry": {"coordinates":[13.5654640198,52.5543212891],"type":"Point"}
}