{
  "type": "Feature",
  "properties": {
    "iso:country":"DE",
    "sg:address":"Schlesische Str. 40",
    "sg:city":"Hennef",
    "sg:phone":"+49 2242/1803",
    "sg:postcode":"53773",
    "sg:province":"Nordrhein-Westfalen",
    "wof:name":"Marschella Taxen Und Mietwagen E. K.",
    "wof:placetype":"venue"
},
  "geometry": {"coordinates":[7.2534170151,50.7747993469],"type":"Point"}
}