{
  "type": "Feature",
  "properties": {
    "iso:country":"DE",
    "sg:address":"Hohe Str. 65",
    "sg:city":"Herborn",
    "sg:phone":"+49 2772/62824",
    "sg:postcode":"35745",
    "sg:province":"Hessen",
    "wof:name":"Hans J. Goebel",
    "wof:placetype":"venue"
},
  "geometry": {"coordinates":[8.3467445374,50.7050971985],"type":"Point"}
}