{
  "type": "Feature",
  "properties": {
    "iso:country":"DE",
    "sg:address":"Im Dorf 2",
    "sg:city":"L\u00fcneburg",
    "sg:phone":"+49 4131/43745",
    "sg:postcode":"21335",
    "sg:province":"Niedersachsen",
    "wof:name":"C. Voltmer",
    "wof:placetype":"venue"
},
  "geometry": {"coordinates":[10.3910903931,53.212272644],"type":"Point"}
}