{
  "type": "Feature",
  "properties": {
    "iso:country":"DE",
    "sg:address":"Maximilianstr. 11",
    "sg:city":"Bayreuth",
    "sg:phone":"+49 921/64202",
    "sg:postcode":"95444",
    "sg:province":"Bayern",
    "wof:name":"Damen-moden Marta Witzler",
    "wof:placetype":"venue"
},
  "geometry": {"coordinates":[11.5766868591,49.9436950684],"type":"Point"}
}