{
  "type": "Feature",
  "properties": {
    "iso:country":"DE",
    "sg:address":"Moltkestr. 19",
    "sg:city":"Pinneberg",
    "sg:phone":"+49 4101/54990",
    "sg:postcode":"25421",
    "sg:province":"Schleswig-Holstein",
    "wof:name":"Schl\u00fcnzen-immobilien Rdm Inh. Melitta Schl\u00fcnzen",
    "wof:placetype":"venue"
},
  "geometry": {"coordinates":[9.7972183228,53.6584396362],"type":"Point"}
}