{
  "type": "Feature",
  "properties": {
    "iso:country":"DE",
    "sg:address":"Sonnenweg 8",
    "sg:city":"Weimar",
    "sg:phone":"+49 3643/905017",
    "sg:postcode":"99425",
    "sg:province":"Th\u00fcringen",
    "wof:name":"Konrad P\u00fcschel Architekt",
    "wof:placetype":"venue"
},
  "geometry": {"coordinates":[11.324347,50.96656],"type":"Point"}
}