{
  "type": "Feature",
  "properties": {
    "iso:country":"DE",
    "sg:address":"Industriestr. 9",
    "sg:city":"Bramstedt",
    "sg:phone":"+49 4947/461546",
    "sg:postcode":"27628",
    "sg:province":"Niedersachsen",
    "wof:name":"M & P Thermische Spritz-undoberfl\u00c4chentechnik Gmbh",
    "wof:placetype":"venue"
},
  "geometry": {"coordinates":[8.674703,53.365498],"type":"Point"}
}