{
  "type": "Feature",
  "properties": {
    "iso:country":"DE",
    "sg:address":"Blumenstr. 1",
    "sg:city":"Hildrizhausen",
    "sg:phone":"+49 7034/649966",
    "sg:postcode":"71157",
    "sg:province":"Baden-W\u00fcrttemberg",
    "wof:name":"Stefan Gmbh",
    "wof:placetype":"venue"
},
  "geometry": {"coordinates":[8.967033,48.623585],"type":"Point"}
}