{
  "type": "Feature",
  "properties": {
    "iso:country":"DE",
    "sg:address":"Marsstr. 1",
    "sg:city":"Gro\u00dfkarolinenfeld",
    "sg:phone":"+49 8031/5437",
    "sg:postcode":"83109",
    "sg:province":"Bayern",
    "wof:name":"Zachert",
    "wof:placetype":"venue"
},
  "geometry": {"coordinates":[12.0853395462,47.8968887329],"type":"Point"}
}