{
  "type": "Feature",
  "properties": {
    "iso:country":"DE",
    "sg:address":"Prenzlauer Allee 46",
    "sg:city":"Templin",
    "sg:phone":"+49 3987/50731",
    "sg:postcode":"17268",
    "sg:province":"Brandenburg",
    "wof:name":"R. Tarnowski",
    "wof:placetype":"venue"
},
  "geometry": {"coordinates":[13.5206451416,53.1213874817],"type":"Point"}
}