{
  "type": "Feature",
  "properties": {
    "iso:country":"DE",
    "sg:address":"Freisch\u00fctzstr. 55",
    "sg:city":"M\u00fcnchen",
    "sg:phone":"+49 89/956075",
    "sg:postcode":"81927",
    "sg:province":"Bayern",
    "wof:name":"Freisch\u00fctz-apotheke",
    "wof:placetype":"venue"
},
  "geometry": {"coordinates":[11.644875,48.163513],"type":"Point"}
}