{
  "type": "Feature",
  "properties": {
    "iso:country":"DE",
    "sg:address":"Halberst\u00e4dter Str. 29",
    "sg:city":"Magdeburg",
    "sg:phone":"+49 391/6230280",
    "sg:postcode":"39112",
    "sg:province":"Sachsen-Anhalt",
    "wof:name":"Rolf Behrens",
    "wof:placetype":"venue"
},
  "geometry": {"coordinates":[11.6140832901,52.1161727905],"type":"Point"}
}