{
  "type": "Feature",
  "properties": {
    "iso:country":"DE",
    "sg:address":"Reinsburgstr. 186",
    "sg:city":"Stuttgart",
    "sg:phone":"+49 711/6599143",
    "sg:postcode":"70197",
    "sg:province":"Baden-W\u00fcrttemberg",
    "wof:name":"H. J. Krug",
    "wof:placetype":"venue"
},
  "geometry": {"coordinates":[9.1485157013,48.7693099976],"type":"Point"}
}