{
  "type": "Feature",
  "properties": {
    "iso:country":"DE",
    "sg:address":"Salzstr. 7",
    "sg:city":"Marktoberdorf",
    "sg:postcode":"87616",
    "sg:province":"Bayern",
    "wof:name":"Otmarsan Gmbh",
    "wof:placetype":"venue"
},
  "geometry": {"coordinates":[10.6207885742,47.7774276733],"type":"Point"}
}