{
  "type": "Feature",
  "properties": {
    "iso:country":"DE",
    "sg:address":"Rhein-Mosel-Str. 14",
    "sg:city":"Brodenbach",
    "sg:phone":"+49 2605/736",
    "sg:postcode":"56332",
    "sg:province":"Rheinland-Pfalz",
    "wof:name":"Kaufhaus J. C. Wagner Inh. Max R\u00f6\u00dfler",
    "wof:placetype":"venue"
},
  "geometry": {"coordinates":[7.444954,50.226353],"type":"Point"}
}