{
  "type": "Feature",
  "properties": {
    "iso:country":"DE",
    "sg:address":"Bosestr. 3A",
    "sg:city":"Bad Brambach",
    "sg:phone":"+49 37438/20745",
    "sg:postcode":"08648",
    "sg:province":"Sachsen",
    "wof:name":"Friedrich Nierhoff",
    "wof:placetype":"venue"
},
  "geometry": {"coordinates":[12.311975,50.222828],"type":"Point"}
}