{
  "type": "Feature",
  "properties": {
    "iso:country":"DE",
    "sg:address":"Paul - Ehrlich - Str. 10",
    "sg:city":"Leonberg",
    "sg:phone":"+49 4971/5228101",
    "sg:postcode":"71229",
    "sg:province":"Baden-W\u00fcrttemberg",
    "wof:name":"Cem Christian Elbert Gmbh",
    "wof:placetype":"venue"
},
  "geometry": {"coordinates":[9.025324,48.819065],"type":"Point"}
}