{
  "type": "Feature",
  "properties": {
    "iso:country":"DE",
    "sg:address":"Wachbergstr. 7",
    "sg:city":"Ottendorf-Okrilla",
    "sg:phone":"+49 35205/73866",
    "sg:postcode":"01458",
    "sg:province":"Sachsen",
    "wof:name":"Joachim Borchert",
    "wof:placetype":"venue"
},
  "geometry": {"coordinates":[13.808059,51.182835],"type":"Point"}
}