{
  "type": "Feature",
  "properties": {
    "iso:country":"DE",
    "sg:address":"Zur Unteren Leite 3",
    "sg:city":"B\u00fcchenbach",
    "sg:phone":"+49 9178/1717",
    "sg:postcode":"91186",
    "sg:province":"Bayern",
    "wof:name":"Helmut Mitzam",
    "wof:placetype":"venue"
},
  "geometry": {"coordinates":[11.0035648346,49.263343811],"type":"Point"}
}