{
  "type": "Feature",
  "properties": {
    "iso:country":"DE",
    "sg:address":"Unter den Linden 2",
    "sg:city":"Reinbek",
    "sg:phone":"+49 40/7108909",
    "sg:postcode":"21465",
    "sg:province":"Schleswig-Holstein",
    "wof:name":"Dr. Dietrich Janssen",
    "wof:placetype":"venue"
},
  "geometry": {"coordinates":[10.2481355667,53.5523147583],"type":"Point"}
}