{
  "type": "Feature",
  "properties": {
    "iso:country":"DE",
    "sg:address":"Teichstr. 16",
    "sg:city":"Rodewisch",
    "sg:phone":"+49 3744/34162",
    "sg:postcode":"08228",
    "sg:province":"Sachsen",
    "wof:name":"Uwe Odebrecht",
    "wof:placetype":"venue"
},
  "geometry": {"coordinates":[12.4212198257,50.5311813354],"type":"Point"}
}