{
  "type": "Feature",
  "properties": {
    "iso:country":"DE",
    "sg:address":"Erlen 27",
    "sg:city":"Much",
    "sg:phone":"+49 2245/1681",
    "sg:postcode":"53804",
    "sg:province":"Nordrhein-Westfalen",
    "wof:name":"M. Grotkamp",
    "wof:placetype":"venue"
},
  "geometry": {"coordinates":[7.4349,50.87545],"type":"Point"}
}