{
  "type": "Feature",
  "properties": {
    "iso:country":"DE",
    "sg:address":"Aachener Str. 266",
    "sg:city":"Eschweiler",
    "sg:phone":"+49 2403/4294",
    "sg:postcode":"52249",
    "sg:province":"Nordrhein-Westfalen",
    "wof:name":"Kaever Gmbh",
    "wof:placetype":"venue"
},
  "geometry": {"coordinates":[6.2337670326,50.8214607239],"type":"Point"}
}