{
  "type": "Feature",
  "properties": {
    "iso:country":"DE",
    "sg:address":"Anemonenweg 27",
    "sg:city":"Offenburg",
    "sg:phone":"+49 781/59155",
    "sg:postcode":"77656",
    "sg:province":"Baden-W\u00fcrttemberg",
    "wof:name":"Wolfgang Rossi",
    "wof:placetype":"venue"
},
  "geometry": {"coordinates":[7.9222002029,48.455493927],"type":"Point"}
}