{
  "type": "Feature",
  "properties": {
    "iso:country":"DE",
    "sg:address":"Dorfstr. 7",
    "sg:city":"Kochel",
    "sg:phone":"+49 8857/8497",
    "sg:postcode":"82431",
    "sg:province":"Bayern",
    "wof:name":"Josef Zerluth",
    "wof:placetype":"venue"
},
  "geometry": {"coordinates":[11.407143,47.692806],"type":"Point"}
}