{
  "type": "Feature",
  "properties": {
    "iso:country":"DE",
    "sg:address":"Sierichstr. 185",
    "sg:city":"Hamburg",
    "sg:phone":"+49 40/2784820",
    "sg:postcode":"22299",
    "sg:province":"Hamburg",
    "wof:name":"Kraft",
    "wof:placetype":"venue"
},
  "geometry": {"coordinates":[9.996649,53.593307],"type":"Point"}
}