{
  "type": "Feature",
  "properties": {
    "iso:country":"DE",
    "sg:address":"F\u00f6ssestr. 61",
    "sg:city":"Hannover",
    "sg:phone":"+49 511/2109161",
    "sg:postcode":"30451",
    "sg:province":"Niedersachsen",
    "wof:name":"Bei Toto-salerno Antonio Veneziano",
    "wof:placetype":"venue"
},
  "geometry": {"coordinates":[9.7061910629,52.3698387146],"type":"Point"}
}