{
  "type": "Feature",
  "properties": {
    "iso:country":"DE",
    "sg:address":"Mattenm\u00fchle 1",
    "sg:city":"Glottertal",
    "sg:phone":"+49 4976/84225",
    "sg:postcode":"79286",
    "sg:province":"Baden-W\u00fcrttemberg",
    "wof:name":"Glottermetall Gmbh & Co. Kg",
    "wof:placetype":"venue"
},
  "geometry": {"coordinates":[7.9199519157,48.0571212769],"type":"Point"}
}