{
  "type": "Feature",
  "properties": {
    "iso:country":"DE",
    "sg:address":"Br\u00fchlstr. 6-8",
    "sg:city":"Wernau",
    "sg:phone":"+49 7153/305060",
    "sg:postcode":"73249",
    "sg:province":"Baden-W\u00fcrttemberg",
    "wof:name":"Voigt Gmbh",
    "wof:placetype":"venue"
},
  "geometry": {"coordinates":[9.4283895493,48.6810684204],"type":"Point"}
}