{
  "type": "Feature",
  "properties": {
    "iso:country":"DE",
    "sg:address":"Birkenhainer Str. 3",
    "sg:city":"Geiselbach",
    "sg:phone":"+49 6024/3239",
    "sg:postcode":"63826",
    "sg:province":"Bayern",
    "wof:name":"R. Und I. Krebs",
    "wof:placetype":"venue"
},
  "geometry": {"coordinates":[9.192138,50.12674],"type":"Point"}
}