{
  "type": "Feature",
  "properties": {
    "iso:country":"DE",
    "sg:address":"Frankfurter Str. 20",
    "sg:city":"Bad K\u00f6nig",
    "sg:phone":"+49 6063/723",
    "sg:postcode":"64732",
    "sg:province":"Hessen",
    "wof:name":"Hans Koch",
    "wof:placetype":"venue"
},
  "geometry": {"coordinates":[9.0050754547,49.7435874939],"type":"Point"}
}