{
  "type": "Feature",
  "properties": {
    "iso:country":"DE",
    "sg:address":"Frankfurter Str. 93",
    "sg:city":"Offenbach",
    "sg:phone":"+49 69/811648",
    "sg:postcode":"63067",
    "sg:province":"Hessen",
    "wof:name":"Schuh-schultheis Inh. Hans-joachim B\u00e4tz E. K.",
    "wof:placetype":"venue"
},
  "geometry": {"coordinates":[8.7540769577,50.1039009094],"type":"Point"}
}