{
  "type": "Feature",
  "properties": {
    "iso:country":"DE",
    "sg:address":"Paulstr. 21",
    "sg:city":"Speyer",
    "sg:phone":"+49 6232/34716",
    "sg:postcode":"67346",
    "sg:province":"Rheinland-Pfalz",
    "wof:name":"Peter Ziegler Gmbh Estrichbau Und Trocknungs-",
    "wof:placetype":"venue"
},
  "geometry": {"coordinates":[8.4252138138,49.3146972656],"type":"Point"}
}