{
  "type": "Feature",
  "properties": {
    "iso:country":"DE",
    "sg:address":"Wether Str. 99",
    "sg:city":"Drochtersen",
    "sg:phone":"+49 4148/464",
    "sg:postcode":"21706",
    "sg:province":"Niedersachsen",
    "wof:name":"Erich Ropers",
    "wof:placetype":"venue"
},
  "geometry": {"coordinates":[9.4422702789,53.6890983582],"type":"Point"}
}