{
  "type": "Feature",
  "properties": {
    "iso:country":"DE",
    "sg:address":"An der Schwarzbachm\u00fchle 39",
    "sg:city":"Frankfurt",
    "sg:phone":"+49 69/6667345",
    "sg:postcode":"60529",
    "sg:province":"Hessen",
    "wof:name":"Rolf Hahn",
    "wof:placetype":"venue"
},
  "geometry": {"coordinates":[8.5998001099,50.082950592],"type":"Point"}
}