{
  "type": "Feature",
  "properties": {
    "iso:country":"DE",
    "sg:address":"Bekstr. 51",
    "sg:city":"Pforzheim",
    "sg:phone":"+49 7231/23111",
    "sg:postcode":"75180",
    "sg:province":"Baden-W\u00fcrttemberg",
    "wof:name":"Pforzheimer Adre\u00dfbuch Verlag Gmbh & Co. Kg",
    "wof:placetype":"venue"
},
  "geometry": {"coordinates":[8.6670484543,48.8736953735],"type":"Point"}
}