{
  "type": "Feature",
  "properties": {
    "iso:country":"DE",
    "sg:address":"Kapellenstr. 6",
    "sg:city":"Waldkirchen",
    "sg:phone":"+49 8581/3808",
    "sg:postcode":"94065",
    "sg:province":"Bayern",
    "wof:name":"Pilspub Formel 1",
    "wof:placetype":"venue"
},
  "geometry": {"coordinates":[13.6022043228,48.7319412231],"type":"Point"}
}