{
  "type": "Feature",
  "properties": {
    "iso:country":"DE",
    "sg:address":"Kiefernweg 21",
    "sg:city":"Zinnowitz",
    "sg:phone":"+49 38377/40373",
    "sg:postcode":"17454",
    "sg:province":"Mecklenburg-Vorpommern",
    "wof:name":"Heike Usemann",
    "wof:placetype":"venue"
},
  "geometry": {"coordinates":[13.894366,54.080242],"type":"Point"}
}