{
  "type": "Feature",
  "properties": {
    "iso:country":"DE",
    "sg:address":"R\u00fcckershagener Str. 17",
    "sg:city":"Gerabronn",
    "sg:phone":"+49 7952/5278",
    "sg:postcode":"74582",
    "sg:province":"Baden-W\u00fcrttemberg",
    "wof:name":"Biohof Hermann Stirn",
    "wof:placetype":"venue"
},
  "geometry": {"coordinates":[9.93302,49.24955],"type":"Point"}
}