{
  "type": "Feature",
  "properties": {
    "iso:country":"DE",
    "sg:address":"Hans-Warsch-Platz 19",
    "sg:city":"Ludwigshafen",
    "sg:phone":"+49 621/673234",
    "sg:postcode":"67071",
    "sg:province":"Rheinland-Pfalz",
    "wof:name":"Wolfgang Weidemann",
    "wof:placetype":"venue"
},
  "geometry": {"coordinates":[8.375706,49.492809],"type":"Point"}
}