{
  "type": "Feature",
  "properties": {
    "iso:country":"DE",
    "sg:address":"Minheimer Str. 55",
    "sg:city":"Berlin",
    "sg:phone":"+49 30/40632451",
    "sg:postcode":"13465",
    "sg:province":"Berlin",
    "wof:name":"M\u00fclder Massivbau Gmbh",
    "wof:placetype":"venue"
},
  "geometry": {"coordinates":[13.285366,52.638805],"type":"Point"}
}