{
  "type": "Feature",
  "properties": {
    "iso:country":"DE",
    "sg:address":"Hans-Adolf-Krebs-Weg 3",
    "sg:city":"Hildesheim",
    "sg:phone":"+49 5121/878489",
    "sg:postcode":"31141",
    "sg:province":"Niedersachsen",
    "wof:name":"Dirk Stahl Architekt",
    "wof:placetype":"venue"
},
  "geometry": {"coordinates":[9.985289,52.119598],"type":"Point"}
}