{
  "type": "Feature",
  "properties": {
    "iso:country":"DE",
    "sg:address":"Friedrichstr. 4",
    "sg:city":"Rheinfelden",
    "sg:phone":"+49 7623/1206",
    "sg:postcode":"79618",
    "sg:province":"Baden-W\u00fcrttemberg",
    "wof:name":"Kneer",
    "wof:placetype":"venue"
},
  "geometry": {"coordinates":[7.788918,47.559372],"type":"Point"}
}