{
  "type": "Feature",
  "properties": {
    "iso:country":"DE",
    "sg:address":"K\u00f6lnische Str.9-11",
    "sg:city":"Kassel",
    "sg:phone":"+49 4956/11005",
    "sg:postcode":"34117",
    "sg:province":"Hessen",
    "wof:name":"Dresdner Bank",
    "wof:placetype":"venue"
},
  "geometry": {"coordinates":[9.494806,51.316109],"type":"Point"}
}