{
  "type": "Feature",
  "properties": {
    "iso:country":"DE",
    "sg:address":"Neue Str. 3",
    "sg:city":"G\u00fclzow",
    "sg:phone":"+49 3843/686395",
    "sg:postcode":"18276",
    "sg:province":"Mecklenburg-Vorpommern",
    "wof:name":"Bas Baugesellschaft F\u00fcr Sanierungen Und Neubauten",
    "wof:placetype":"venue"
},
  "geometry": {"coordinates":[12.066825,53.819962],"type":"Point"}
}