{
  "type": "Feature",
  "properties": {
    "iso:country":"DE",
    "sg:address":"Horster Str. 204",
    "sg:city":"Gladbeck",
    "sg:phone":"+49 2043/34976",
    "sg:postcode":"45968",
    "sg:province":"Nordrhein-Westfalen",
    "wof:name":"Georg Tix",
    "wof:placetype":"venue"
},
  "geometry": {"coordinates":[7.0018010139,51.555141449],"type":"Point"}
}