{
  "type": "Feature",
  "properties": {
    "iso:country":"DE",
    "sg:address":"Ro\u00dfsteinstr. 9",
    "sg:city":"Weilburg",
    "sg:phone":"+49 6471/1834",
    "sg:postcode":"35781",
    "sg:province":"Hessen",
    "wof:name":"Kirschh\u00f6fer Kuckuck Restaurant",
    "wof:placetype":"venue"
},
  "geometry": {"coordinates":[8.2421131134,50.4742851257],"type":"Point"}
}