{
  "type": "Feature",
  "properties": {
    "iso:country":"DE",
    "sg:address":"Frankensteinstr. 11",
    "sg:city":"B\u00fcrstadt",
    "sg:phone":"+49 6245/4762",
    "sg:postcode":"68642",
    "sg:province":"Hessen",
    "wof:name":"Eduard Lau",
    "wof:placetype":"venue"
},
  "geometry": {"coordinates":[8.4474372864,49.6624069214],"type":"Point"}
}