{
  "type": "Feature",
  "properties": {
    "iso:country":"DE",
    "sg:address":"Schwalbenweg 56",
    "sg:city":"Kempten",
    "sg:phone":"+49 831/93648",
    "sg:postcode":"87439",
    "sg:province":"Bayern",
    "wof:name":"J. J\u00fcnger",
    "wof:placetype":"venue"
},
  "geometry": {"coordinates":[10.2881250381,47.737739563],"type":"Point"}
}