{
  "type": "Feature",
  "properties": {
    "iso:country":"DE",
    "sg:address":"Holzweg 7",
    "sg:city":"Heilbad Heiligenstadt",
    "sg:phone":"+49 3606/619504",
    "sg:postcode":"37308",
    "sg:province":"Th\u00fcringen",
    "wof:name":"Manuela Kruse",
    "wof:placetype":"venue"
},
  "geometry": {"coordinates":[10.130349,51.374413],"type":"Point"}
}