{
  "type": "Feature",
  "properties": {
    "iso:country":"DE",
    "sg:address":"Am Bahnhof 16",
    "sg:city":"Walsrode",
    "sg:phone":"+49 5161/5723",
    "sg:postcode":"29664",
    "sg:province":"Niedersachsen",
    "wof:name":"Verden-walsroder Eisenbahn Gmbh",
    "wof:placetype":"venue"
},
  "geometry": {"coordinates":[9.6005773544,52.8707580566],"type":"Point"}
}