{
  "type": "Feature",
  "properties": {
    "iso:country":"DE",
    "sg:address":"Ronheim 20",
    "sg:city":"Harburg",
    "sg:postcode":"86655",
    "sg:province":"Bayern",
    "wof:name":"Bschor Gmbh",
    "wof:placetype":"venue"
},
  "geometry": {"coordinates":[10.687128067,48.7949867249],"type":"Point"}
}