{
  "type": "Feature",
  "properties": {
    "iso:country":"DE",
    "sg:address":"Alleestr. 75",
    "sg:city":"Riesa",
    "sg:phone":"+49 3525/893000",
    "sg:postcode":"01591",
    "sg:province":"Sachsen",
    "wof:name":"Klaus J\u00e4hnig",
    "wof:placetype":"venue"
},
  "geometry": {"coordinates":[13.263454,51.320305],"type":"Point"}
}