{
  "type": "Feature",
  "properties": {
    "iso:country":"DE",
    "sg:address":"Lichtstr. 15",
    "sg:city":"D\u00fcsseldorf",
    "sg:phone":"+49 211/683050",
    "sg:postcode":"40235",
    "sg:province":"Nordrhein-Westfalen",
    "wof:name":"Simulationsanwendung Schr\u00f6der Gmbh",
    "wof:placetype":"venue"
},
  "geometry": {"coordinates":[6.8165531158,51.2322616577],"type":"Point"}
}