{
  "type": "Feature",
  "properties": {
    "iso:country":"DE",
    "sg:address":"Rudolf-Zorn-Str. 36",
    "sg:city":"M\u00fcnchen",
    "sg:postcode":"81739",
    "sg:province":"Bayern",
    "wof:name":"Becker-innovations Java Consulting Project Support",
    "wof:placetype":"venue"
},
  "geometry": {"coordinates":[11.639867,48.089619],"type":"Point"}
}