{
  "type": "Feature",
  "properties": {
    "iso:country":"DE",
    "sg:address":"Bismarckstr. 19",
    "sg:city":"Berlin",
    "sg:phone":"+49 30/3420665",
    "sg:postcode":"10625",
    "sg:province":"Berlin",
    "wof:name":"Manfred Prietzel Architekt",
    "wof:placetype":"venue"
},
  "geometry": {"coordinates":[13.200664,52.543453],"type":"Point"}
}