{
  "type": "Feature",
  "properties": {
    "iso:country":"DE",
    "sg:address":"Steinkopfstr. 50",
    "sg:city":"K\u00f6ln",
    "sg:phone":"+49 221/612012",
    "sg:postcode":"51065",
    "sg:province":"Nordrhein-Westfalen",
    "wof:name":"Kurt Erler Kartoffelgro\u00dfhandel",
    "wof:placetype":"venue"
},
  "geometry": {"coordinates":[7.0116968155,50.9589347839],"type":"Point"}
}