{
  "type": "Feature",
  "properties": {
    "iso:country":"DE",
    "sg:address":"Breitwiesen 4",
    "sg:city":"Rodenbach",
    "sg:postcode":"67688",
    "sg:province":"Rheinland-Pfalz",
    "wof:name":"Heitzmann Container Und Silo Transport Gmbh & Co. Kg",
    "wof:placetype":"venue"
},
  "geometry": {"coordinates":[7.6674489975,49.4735488892],"type":"Point"}
}