{
  "type": "Feature",
  "properties": {
    "iso:country":"DE",
    "sg:address":"Heideweg 4",
    "sg:city":"Breitenburg",
    "sg:phone":"+49 4821/83608",
    "sg:postcode":"25524",
    "sg:province":"Schleswig-Holstein",
    "wof:name":"Otto Laue Gmbh",
    "wof:placetype":"venue"
},
  "geometry": {"coordinates":[9.503968,53.902016],"type":"Point"}
}