{
  "type": "Feature",
  "properties": {
    "iso:country":"DE",
    "sg:address":"Zum Sportzentrum 3",
    "sg:city":"H\u00fcckeswagen",
    "sg:phone":"+49 2192/4114",
    "sg:postcode":"42499",
    "sg:province":"Nordrhein-Westfalen",
    "wof:name":"Hallenbad-restaurant",
    "wof:placetype":"venue"
},
  "geometry": {"coordinates":[7.3328728676,51.1462974548],"type":"Point"}
}