{
  "type": "Feature",
  "properties": {
    "iso:country":"DE",
    "sg:address":"Arheilger Str. 20",
    "sg:city":"Weiterstadt",
    "sg:phone":"+49 6150/15291",
    "sg:postcode":"64331",
    "sg:province":"Hessen",
    "wof:name":"Bender & K\u00f6rner Verwaltungs Gmbh",
    "wof:placetype":"venue"
},
  "geometry": {"coordinates":[8.590369,49.906155],"type":"Point"}
}