{
  "type": "Feature",
  "properties": {
    "iso:country":"DE",
    "sg:address":"Seehaldenweg 6",
    "sg:city":"Winnenden",
    "sg:phone":"+49 7195/97340",
    "sg:postcode":"71364",
    "sg:province":"Baden-W\u00fcrttemberg",
    "wof:name":"Andress Und Co. Kg Spk-fabrik F\u00fcr",
    "wof:placetype":"venue"
},
  "geometry": {"coordinates":[9.42017,48.873589],"type":"Point"}
}