{
  "type": "Feature",
  "properties": {
    "iso:country":"DE",
    "sg:address":"Magdeburger Chaussee 33",
    "sg:city":"Burg",
    "sg:phone":"+49 3921/989081",
    "sg:postcode":"39288",
    "sg:province":"Sachsen-Anhalt",
    "wof:name":"Silke Michaelis",
    "wof:placetype":"venue"
},
  "geometry": {"coordinates":[11.847263,52.265739],"type":"Point"}
}