{
  "type": "Feature",
  "properties": {
    "iso:country":"DE",
    "sg:address":"Altl\u00e4nder Str. 11",
    "sg:city":"Stade",
    "sg:phone":"+49 4141/44021",
    "sg:postcode":"21680",
    "sg:province":"Niedersachsen",
    "wof:name":"Tobaben Gesellschaft Mit Beschr\u00e4nkter Haftung",
    "wof:placetype":"venue"
},
  "geometry": {"coordinates":[9.4852342606,53.6020469666],"type":"Point"}
}