{
  "type": "Feature",
  "properties": {
    "iso:country":"DE",
    "sg:address":"Bundesstr. 14",
    "sg:city":"Achern",
    "sg:phone":"+49 7841/21517",
    "sg:postcode":"77855",
    "sg:province":"Baden-W\u00fcrttemberg",
    "wof:name":"G\u00fcnther Lang",
    "wof:placetype":"venue"
},
  "geometry": {"coordinates":[8.0517396927,48.6242980957],"type":"Point"}
}