{
  "type": "Feature",
  "properties": {
    "iso:country":"DE",
    "sg:address":"Stettiner Str 134",
    "sg:city":"Hochheim",
    "sg:phone":"+49 6146/835720",
    "sg:postcode":"65239",
    "sg:province":"Hessen",
    "wof:name":"Mic Microconsult Kommunikationssysteme Gmbh",
    "wof:placetype":"venue"
},
  "geometry": {"coordinates":[8.344449,50.012711],"type":"Point"}
}