{
  "type": "Feature",
  "properties": {
    "iso:country":"DE",
    "sg:address":"Einsteinstr. 31",
    "sg:city":"Ulm",
    "sg:phone":"+49 731/936960",
    "sg:postcode":"89077",
    "sg:province":"Baden-W\u00fcrttemberg",
    "wof:name":"W. Lentz Gmbh",
    "wof:placetype":"venue"
},
  "geometry": {"coordinates":[9.9638881683,48.3960342407],"type":"Point"}
}