{
  "type": "Feature",
  "properties": {
    "iso:country":"DE",
    "sg:address":"Kirchplatz 2",
    "sg:city":"Abensberg",
    "sg:phone":"+49 9443/6406",
    "sg:postcode":"93326",
    "sg:province":"Bayern",
    "wof:name":"Kath. Pfarramt St. Vitus",
    "wof:placetype":"venue"
},
  "geometry": {"coordinates":[11.8196649551,48.8389854431],"type":"Point"}
}