{
  "type": "Feature",
  "properties": {
    "iso:country":"DE",
    "sg:address":"Breitgasse 24",
    "sg:city":"Nierstein",
    "sg:phone":"+49 6133/5443",
    "sg:postcode":"55283",
    "sg:province":"Rheinland-Pfalz",
    "wof:name":"Hugo P. Sander",
    "wof:placetype":"venue"
},
  "geometry": {"coordinates":[8.3394050598,49.8768806458],"type":"Point"}
}