{
  "type": "Feature",
  "properties": {
    "iso:country":"DE",
    "sg:address":"Kloster 3",
    "sg:city":"Adelberg",
    "sg:phone":"+49 7166/236",
    "sg:postcode":"73099",
    "sg:province":"Baden-W\u00fcrttemberg",
    "wof:name":"Restaurant-cafe Klosterpark",
    "wof:placetype":"venue"
},
  "geometry": {"coordinates":[9.5977144241,48.7579460144],"type":"Point"}
}