{
  "type": "Feature",
  "properties": {
    "iso:country":"DE",
    "sg:address":"Sandplatte 1",
    "sg:city":"Schnaittach",
    "sg:phone":"+49 9153/8405",
    "sg:postcode":"91220",
    "sg:province":"Bayern",
    "wof:name":"Mathilde Seubert",
    "wof:placetype":"venue"
},
  "geometry": {"coordinates":[11.333987236,49.5589332581],"type":"Point"}
}