{
  "type": "Feature",
  "properties": {
    "iso:country":"DE",
    "sg:address":"Am Stadtpark 23",
    "sg:city":"N\u00fcrnberg",
    "sg:phone":"+49 911/364046",
    "sg:postcode":"90409",
    "sg:province":"Bayern",
    "wof:name":"Isolde Seidel Heilpraktikerin",
    "wof:placetype":"venue"
},
  "geometry": {"coordinates":[11.0890607834,49.4629364014],"type":"Point"}
}