{
  "type": "Feature",
  "properties": {
    "iso:country":"DE",
    "sg:address":"Nr. 8E",
    "sg:city":"Kreischa",
    "sg:postcode":"01731",
    "sg:province":"Sachsen",
    "wof:name":"Dr. Med. Gisela Strauzenberg",
    "wof:placetype":"venue"
},
  "geometry": {"coordinates":[13.760048,50.95047],"type":"Point"}
}