{
  "type": "Feature",
  "properties": {
    "iso:country":"DE",
    "sg:address":"Hochstr. 24",
    "sg:city":"Waldbr\u00f6l",
    "sg:phone":"+49 2291/92170",
    "sg:postcode":"51545",
    "sg:province":"Nordrhein-Westfalen",
    "wof:name":"Norbert Schr\u00f6der",
    "wof:placetype":"venue"
},
  "geometry": {"coordinates":[7.6169309616,50.8751907349],"type":"Point"}
}