{
  "type": "Feature",
  "properties": {
    "iso:country":"DE",
    "sg:address":"K\u00f6lner Str. 17",
    "sg:city":"Netphen",
    "sg:phone":"+49 2737/3615",
    "sg:postcode":"57250",
    "sg:province":"Nordrhein-Westfalen",
    "wof:name":"Wilhelm Schramen",
    "wof:placetype":"venue"
},
  "geometry": {"coordinates":[8.1409721375,50.8835716248],"type":"Point"}
}