{
  "type": "Feature",
  "properties": {
    "iso:country":"DE",
    "sg:address":"Bernardstr. 14",
    "sg:city":"Offenbach",
    "sg:phone":"+49 69/888150",
    "sg:postcode":"63067",
    "sg:province":"Hessen",
    "wof:name":"Gesellschaft F\u00fcr Wirtschafts- Kunde Verein Zur F\u00f6rderung Der",
    "wof:placetype":"venue"
},
  "geometry": {"coordinates":[8.7560501099,50.1078414917],"type":"Point"}
}