{
  "type": "Feature",
  "properties": {
    "iso:country":"DE",
    "sg:address":"Kirchstr. 23",
    "sg:city":"B\u00fchl",
    "sg:postcode":"77815",
    "sg:province":"Baden-W\u00fcrttemberg",
    "wof:name":"Pro-stocks Ges. F\u00fcr Verm\u00f6gens- Anlagenvermittlung Mbh",
    "wof:placetype":"venue"
},
  "geometry": {"coordinates":[8.1263580322,48.7379951477],"type":"Point"}
}