{
  "type": "Feature",
  "properties": {
    "iso:country":"DE",
    "sg:address":"Rosenstr. 23",
    "sg:city":"Besigheim",
    "sg:phone":"+49 7143/58814",
    "sg:postcode":"74354",
    "sg:province":"Baden-W\u00fcrttemberg",
    "wof:name":"J\u00fcrgen Lang Steuerberater",
    "wof:placetype":"venue"
},
  "geometry": {"coordinates":[9.2004051208,49.0197410583],"type":"Point"}
}