{
  "type": "Feature",
  "properties": {
    "iso:country":"DE",
    "sg:address":"Mindener Str. 38",
    "sg:city":"Bremen",
    "sg:phone":"+49 421/493044",
    "sg:postcode":"28205",
    "sg:province":"Bremen",
    "wof:name":"Helmut Lotz",
    "wof:placetype":"venue"
},
  "geometry": {"coordinates":[8.8431720734,53.0708885193],"type":"Point"}
}