{
  "type": "Feature",
  "properties": {
    "iso:country":"DE",
    "sg:address":"Peter-Janssen-Str. 25",
    "sg:city":"D\u00fcsseldorf",
    "sg:phone":"+49 211/683268",
    "sg:postcode":"40237",
    "sg:province":"Nordrhein-Westfalen",
    "wof:name":"Dr. Martin Theisen Immobilienmakler",
    "wof:placetype":"venue"
},
  "geometry": {"coordinates":[6.8096871376,51.2350234985],"type":"Point"}
}