{
  "type": "Feature",
  "properties": {
    "iso:country":"DE",
    "sg:address":"Pongser Str. 203",
    "sg:city":"M\u00f6nchengladbach",
    "sg:phone":"+49 2166/30585",
    "sg:postcode":"41239",
    "sg:province":"Nordrhein-Westfalen",
    "wof:name":"Friedhelm Junkers",
    "wof:placetype":"venue"
},
  "geometry": {"coordinates":[6.413101,51.166058],"type":"Point"}
}