{
  "type": "Feature",
  "properties": {
    "iso:country":"DE",
    "sg:address":"Rumplerweg 3",
    "sg:city":"Waldkraiburg",
    "sg:phone":"+49 8638/4216",
    "sg:postcode":"84478",
    "sg:province":"Bayern",
    "wof:name":"Josef Mark",
    "wof:placetype":"venue"
},
  "geometry": {"coordinates":[12.405267,48.217819],"type":"Point"}
}