{
  "type": "Feature",
  "properties": {
    "iso:country":"DE",
    "sg:address":"Bahnhofstr. 9",
    "sg:city":"Speyer",
    "sg:phone":"+49 6232/75370",
    "sg:postcode":"67346",
    "sg:province":"Rheinland-Pfalz",
    "wof:name":"Fritz Egem",
    "wof:placetype":"venue"
},
  "geometry": {"coordinates":[8.4311437607,49.3183021545],"type":"Point"}
}