{
  "type": "Feature",
  "properties": {
    "iso:country":"DE",
    "sg:address":"Tibarg 1",
    "sg:city":"Hamburg",
    "sg:phone":"+49 40/7337187",
    "sg:postcode":"22459",
    "sg:province":"Hamburg",
    "wof:name":"Manfred Vaqu\u00e9 Stra\u00dfen- Und Tiefbau E. K.",
    "wof:placetype":"venue"
},
  "geometry": {"coordinates":[9.9509305954,53.6188392639],"type":"Point"}
}