{
  "type": "Feature",
  "properties": {
    "iso:country":"DE",
    "sg:address":"Maisweg 10",
    "sg:city":"K\u00f6ln",
    "sg:phone":"+49 221/4912798",
    "sg:postcode":"50933",
    "sg:province":"Nordrhein-Westfalen",
    "wof:name":"Gmk-promotion Veranstaltungen Incentive-reisen Gmbh",
    "wof:placetype":"venue"
},
  "geometry": {"coordinates":[6.860681057,50.950012207],"type":"Point"}
}