{
  "type": "Feature",
  "properties": {
    "iso:country":"DE",
    "sg:address":"Fichtenstr. 6",
    "sg:city":"Niederaula",
    "sg:phone":"+49 6625/1379",
    "sg:postcode":"36272",
    "sg:province":"Hessen",
    "wof:name":"H. Diehl",
    "wof:placetype":"venue"
},
  "geometry": {"coordinates":[9.6500778198,50.8098602295],"type":"Point"}
}