{
  "type": "Feature",
  "properties": {
    "iso:country":"DE",
    "sg:address":"Am Platzl 12a",
    "sg:city":"Straubing",
    "sg:phone":"+49 9421/88770",
    "sg:postcode":"94315",
    "sg:province":"Bayern",
    "wof:name":"Jung",
    "wof:placetype":"venue"
},
  "geometry": {"coordinates":[12.5667266846,48.8800697327],"type":"Point"}
}