{
  "type": "Feature",
  "properties": {
    "iso:country":"DE",
    "sg:address":"Buddenbaum 14",
    "sg:city":"Warendorf",
    "sg:phone":"+49 2585/7453",
    "sg:postcode":"48231",
    "sg:province":"Nordrhein-Westfalen",
    "wof:name":"Alfons Prinz",
    "wof:placetype":"venue"
},
  "geometry": {"coordinates":[7.954091,51.882729],"type":"Point"}
}