{
  "type": "Feature",
  "properties": {
    "iso:country":"DE",
    "sg:address":"Morassistr. 16",
    "sg:city":"M\u00fcnchen",
    "sg:postcode":"80469",
    "sg:province":"Bayern",
    "wof:name":"People4.net Gmbh",
    "wof:placetype":"venue"
},
  "geometry": {"coordinates":[11.5823230743,48.1321296692],"type":"Point"}
}