{
  "type": "Feature",
  "properties": {
    "iso:country":"DE",
    "sg:address":"Sandstr. 32",
    "sg:city":"Monheim",
    "sg:phone":"+49 2173/63535",
    "sg:postcode":"40789",
    "sg:province":"Nordrhein-Westfalen",
    "wof:name":"Franz Schwidden",
    "wof:placetype":"venue"
},
  "geometry": {"coordinates":[6.888051,51.112507],"type":"Point"}
}