{
  "type": "Feature",
  "properties": {
    "iso:country":"DE",
    "sg:address":"Windeckstr. 81",
    "sg:city":"Mannheim",
    "sg:phone":"+49 700 7233 5672",
    "sg:postcode":"68163",
    "sg:province":"Baden-W\u00fcrttemberg",
    "wof:name":"G\u00fcnther K. Delora Rechtsanwalt",
    "wof:placetype":"venue"
},
  "geometry": {"coordinates":[8.4712200165,49.4739303589],"type":"Point"}
}