{
  "type": "Feature",
  "properties": {
    "iso:country":"DE",
    "sg:address":"Dieselstr. 4",
    "sg:city":"Braunschweig",
    "sg:postcode":"38122",
    "sg:province":"Niedersachsen",
    "wof:name":"Peter Salzmann Beteiligungsges. Mbh",
    "wof:placetype":"venue"
},
  "geometry": {"coordinates":[10.498021,52.212692],"type":"Point"}
}