{
  "type": "Feature",
  "properties": {
    "iso:country":"DE",
    "sg:address":"Auf dem Brokamp 9",
    "sg:city":"Herford",
    "sg:phone":"+49 5221/31403",
    "sg:postcode":"32051",
    "sg:province":"Nordrhein-Westfalen",
    "wof:name":"H. M\u00fcller",
    "wof:placetype":"venue"
},
  "geometry": {"coordinates":[8.6046476364,52.1153030396],"type":"Point"}
}