{
  "type": "Feature",
  "properties": {
    "iso:country":"DE",
    "sg:address":"Monrepos 21",
    "sg:city":"Ludwigsburg",
    "sg:phone":"+49 7141/220070",
    "sg:postcode":"71634",
    "sg:province":"Baden-W\u00fcrttemberg",
    "wof:name":"Golfshop Des Golfclubs Schlo\u00df Monrepos",
    "wof:placetype":"venue"
},
  "geometry": {"coordinates":[9.167493,48.922443],"type":"Point"}
}