{
  "type": "Feature",
  "properties": {
    "iso:country":"DE",
    "sg:address":"Hermannstr. 4",
    "sg:city":"MArxen",
    "sg:phone":"+49 511/514718",
    "sg:postcode":"21439",
    "sg:province":"Niedersachsen",
    "wof:name":"Wildniswissen - Das Wissen Der Wildnis",
    "wof:placetype":"venue"
},
  "geometry": {"coordinates":[10.001204,53.311096],"type":"Point"}
}