{
  "type": "Feature",
  "properties": {
    "iso:country":"DE",
    "sg:address":"Br\u00fcckenstr. 1",
    "sg:city":"Schweinfurt",
    "sg:phone":"+49 9721/22956",
    "sg:postcode":"97421",
    "sg:province":"Bayern",
    "wof:name":"Georg Wollner Architekt",
    "wof:placetype":"venue"
},
  "geometry": {"coordinates":[10.235208,50.044968],"type":"Point"}
}