{
  "type": "Feature",
  "properties": {
    "iso:country":"DE",
    "sg:address":"Straizergasse 1",
    "sg:city":"Burgbernheim",
    "sg:phone":"+49 9843/1396",
    "sg:postcode":"91593",
    "sg:province":"Bayern",
    "wof:name":"Gerda Fluhrer Pension",
    "wof:placetype":"venue"
},
  "geometry": {"coordinates":[10.3222351074,49.4492912292],"type":"Point"}
}