{
  "type": "Feature",
  "properties": {
    "iso:country":"DE",
    "sg:address":"M\u00fchlenstr. 4",
    "sg:city":"Erharting",
    "sg:phone":"+49 8631/91750",
    "sg:postcode":"84513",
    "sg:province":"Bayern",
    "wof:name":"Felix Huber",
    "wof:placetype":"venue"
},
  "geometry": {"coordinates":[12.574728,48.28043],"type":"Point"}
}