{
  "type": "Feature",
  "properties": {
    "iso:country":"DE",
    "sg:address":"Zwingenberger Str. 17a",
    "sg:city":"Zwingenberg",
    "sg:phone":"+49 6251/78116",
    "sg:postcode":"64673",
    "sg:province":"Hessen",
    "wof:name":"Klaus Gerhardt Gmbh",
    "wof:placetype":"venue"
},
  "geometry": {"coordinates":[8.593542,49.721546],"type":"Point"}
}