{
  "type": "Feature",
  "properties": {
    "iso:country":"DE",
    "sg:address":"K\u00f6riser Str 5",
    "sg:city":"Bestensee",
    "sg:phone":"+49 33763/61051",
    "sg:postcode":"15741",
    "sg:province":"Brandenburg",
    "wof:name":"Melsa & Hoffmann Gbr",
    "wof:placetype":"venue"
},
  "geometry": {"coordinates":[13.6288938522,52.2336997986],"type":"Point"}
}