{
  "type": "Feature",
  "properties": {
    "iso:country":"DE",
    "sg:city":"Zwingenberg",
    "sg:phone":"+49 6251/77319",
    "sg:postcode":"64673",
    "sg:province":"Hessen",
    "wof:name":"Gottfried Bayer Innenarchitekt",
    "wof:placetype":"venue"
},
  "geometry": {"coordinates":[8.612755,49.724216],"type":"Point"}
}