{
  "type": "Feature",
  "properties": {
    "iso:country":"DE",
    "sg:address":"Hauptstr. 4",
    "sg:city":"Batzlow",
    "sg:phone":"+49 33437/89472",
    "sg:postcode":"15377",
    "sg:province":"Brandenburg",
    "wof:name":"Imbi\u00df Andrea Rothmeier",
    "wof:placetype":"venue"
},
  "geometry": {"coordinates":[14.1185035706,52.6332435608],"type":"Point"}
}