{
  "type": "Feature",
  "properties": {
    "iso:country":"DE",
    "sg:address":"Rappenbergstr. 97",
    "sg:city":"Treuchtlingen",
    "sg:phone":"+49 9142/5148",
    "sg:postcode":"91757",
    "sg:province":"Bayern",
    "wof:name":"Pension E. Schwarz",
    "wof:placetype":"venue"
},
  "geometry": {"coordinates":[10.9053554535,48.9710464478],"type":"Point"}
}