{
  "type": "Feature",
  "properties": {
    "iso:country":"DE",
    "sg:address":"Nebbsallee 5",
    "sg:city":"Varel",
    "sg:phone":"+49 4451/4013",
    "sg:postcode":"26316",
    "sg:province":"Niedersachsen",
    "wof:name":"Stadtb\u00fccherei",
    "wof:placetype":"venue"
},
  "geometry": {"coordinates":[8.139761,53.396362],"type":"Point"}
}