{
  "type": "Feature",
  "properties": {
    "iso:country":"DE",
    "sg:address":"Dorfstr. 16",
    "sg:city":"Jesewitz",
    "sg:phone":"+49 34241/50618",
    "sg:postcode":"04838",
    "sg:province":"Sachsen",
    "wof:name":"Baasch & Schulze",
    "wof:placetype":"venue"
},
  "geometry": {"coordinates":[12.6262254715,51.4936714172],"type":"Point"}
}