{
  "type": "Feature",
  "properties": {
    "iso:country":"DE",
    "sg:address":"Parkhofstr. 76",
    "sg:city":"H\u00fcckelhoven",
    "sg:phone":"+49 2433/82294",
    "sg:postcode":"41836",
    "sg:province":"Nordrhein-Westfalen",
    "wof:name":"Stadtarchiv",
    "wof:placetype":"venue"
},
  "geometry": {"coordinates":[6.223582,51.054935],"type":"Point"}
}