{
  "type": "Feature",
  "properties": {
    "iso:country":"DE",
    "sg:address":"Dorfstr. 11",
    "sg:city":"Gr\u00f6ben",
    "sg:phone":"+49 3378/870197",
    "sg:postcode":"14974",
    "sg:province":"Brandenburg",
    "wof:name":"W. B\u00fcnten Meisterbetrieb F\u00fcr Klempnerei Und Dach-",
    "wof:placetype":"venue"
},
  "geometry": {"coordinates":[13.261506,52.300812],"type":"Point"}
}