{
  "type": "Feature",
  "properties": {
    "iso:country":"DE",
    "sg:address":"Prinzregentenufer 13",
    "sg:city":"N\u00fcrnberg",
    "sg:phone":"+49 911/530000",
    "sg:postcode":"90489",
    "sg:province":"Bayern",
    "wof:name":"G\u00fcnther Morgenweck Rechtsanwalt",
    "wof:placetype":"venue"
},
  "geometry": {"coordinates":[11.0895175934,49.4522094727],"type":"Point"}
}