{
  "type": "Feature",
  "properties": {
    "iso:country":"DE",
    "sg:address":"Hossenhauser Str. 223",
    "sg:city":"Solingen",
    "sg:phone":"+49 212/814702",
    "sg:postcode":"42655",
    "sg:province":"Nordrhein-Westfalen",
    "wof:name":"Walter Lux",
    "wof:placetype":"venue"
},
  "geometry": {"coordinates":[7.038899,51.153126],"type":"Point"}
}