{
  "type": "Feature",
  "properties": {
    "iso:country":"DE",
    "sg:address":"Am Knappenberg 38",
    "sg:city":"Dortmund",
    "sg:phone":"+49 231/572445",
    "sg:postcode":"44139",
    "sg:province":"Nordrhein-Westfalen",
    "wof:name":"Wendelin Saul Ingenieur",
    "wof:placetype":"venue"
},
  "geometry": {"coordinates":[7.4695401192,51.5055541992],"type":"Point"}
}