{
  "type": "Feature",
  "properties": {
    "iso:country":"DE",
    "sg:address":"Schlo\u00dfstr. 1",
    "sg:city":"Kleinwallstadt",
    "sg:phone":"+49 6022/23852",
    "sg:postcode":"63839",
    "sg:province":"Bayern",
    "wof:name":"Gastst\u00e4tte S. Brigante Eiscafe",
    "wof:placetype":"venue"
},
  "geometry": {"coordinates":[9.16887,49.871952],"type":"Point"}
}