{
  "type": "Feature",
  "properties": {
    "iso:country":"DE",
    "sg:address":"Rolandstr. 9",
    "sg:city":"K\u00f6ln",
    "sg:phone":"+49 221/386367",
    "sg:postcode":"50677",
    "sg:province":"Nordrhein-Westfalen",
    "wof:name":"Lemmy",
    "wof:placetype":"venue"
},
  "geometry": {"coordinates":[6.9595041275,50.9183578491],"type":"Point"}
}