{
  "type": "Feature",
  "properties": {
    "iso:country":"DE",
    "sg:address":"H\u00fclsermannshof 11a",
    "sg:city":"Duisburg",
    "sg:phone":"+49 203/490400",
    "sg:postcode":"47179",
    "sg:province":"Nordrhein-Westfalen",
    "wof:name":"Inro Industrie - Rohrleitungsbau Gmbh",
    "wof:placetype":"venue"
},
  "geometry": {"coordinates":[6.7498807907,51.5341529846],"type":"Point"}
}