{
  "type": "Feature",
  "properties": {
    "iso:country":"DE",
    "sg:address":"Talstr. 121",
    "sg:city":"St\u00fctzengr\u00fcn",
    "sg:postcode":"08328",
    "sg:province":"Sachsen",
    "wof:name":"H. Wappler",
    "wof:placetype":"venue"
},
  "geometry": {"coordinates":[12.54376,50.529148],"type":"Point"}
}