{
  "type": "Feature",
  "properties": {
    "iso:country":"DE",
    "sg:address":"Parkstr. 14",
    "sg:city":"Heidenau",
    "sg:phone":"+49 3529/512085",
    "sg:postcode":"01809",
    "sg:province":"Sachsen",
    "wof:name":"Andreas Urbanek",
    "wof:placetype":"venue"
},
  "geometry": {"coordinates":[13.8814182281,50.9588012695],"type":"Point"}
}