{
  "type": "Feature",
  "properties": {
    "iso:country":"DE",
    "sg:address":"Hagebuttenweg 13",
    "sg:city":"Langen",
    "sg:phone":"+49 6103/72401",
    "sg:postcode":"63225",
    "sg:province":"Hessen",
    "wof:name":"Wolfgang D\u00f6lzig",
    "wof:placetype":"venue"
},
  "geometry": {"coordinates":[8.643227,49.991428],"type":"Point"}
}