{
  "type": "Feature",
  "properties": {
    "iso:country":"DE",
    "sg:address":"M\u00f6rikestr 21",
    "sg:city":"Stuttgart",
    "sg:phone":"+49 711/960300",
    "sg:postcode":"70178",
    "sg:province":"Baden-W\u00fcrttemberg",
    "wof:name":"Ats Risk Beratungsgesellschaft F\u00fcr Risikomanagement Gmbh",
    "wof:placetype":"venue"
},
  "geometry": {"coordinates":[9.166771,48.765575],"type":"Point"}
}