{
  "type": "Feature",
  "properties": {
    "iso:country":"DE",
    "sg:address":"K\u00f6nigsberger Str. 26",
    "sg:city":"M\u00fcnchen",
    "sg:phone":"+49 89/93932625",
    "sg:postcode":"81927",
    "sg:province":"Bayern",
    "wof:name":"Tws Treumandat Dienstleistungs Und Unternehmensberatungs Gmbh",
    "wof:placetype":"venue"
},
  "geometry": {"coordinates":[11.640411377,48.151725769],"type":"Point"}
}