{
  "type": "Feature",
  "properties": {
    "iso:country":"DE",
    "sg:address":"Ringstr. 17",
    "sg:city":"Oberriexingen",
    "sg:phone":"+49 7042/4074",
    "sg:postcode":"71739",
    "sg:province":"Baden-W\u00fcrttemberg",
    "wof:name":"Wlz-raiffeisen Ag",
    "wof:placetype":"venue"
},
  "geometry": {"coordinates":[9.021555,48.934261],"type":"Point"}
}