{
  "type": "Feature",
  "properties": {
    "iso:country":"DE",
    "sg:address":"Am Bahnhof 1",
    "sg:city":"Trittau",
    "sg:phone":"+49 4154/3414",
    "sg:postcode":"22946",
    "sg:province":"Schleswig-Holstein",
    "wof:name":"Alter Bahnhof",
    "wof:placetype":"venue"
},
  "geometry": {"coordinates":[10.4043140411,53.6198272705],"type":"Point"}
}