{
  "type": "Feature",
  "properties": {
    "iso:country":"DE",
    "sg:address":"Am S\u00e4gm\u00fchlweiher 2 A",
    "sg:city":"Ludwigswinkel",
    "sg:phone":"+49 6393/1201",
    "sg:postcode":"66996",
    "sg:province":"Rheinland-Pfalz",
    "wof:name":"Kurt Schmitt Gmbh",
    "wof:placetype":"venue"
},
  "geometry": {"coordinates":[7.66017,49.075329],"type":"Point"}
}