{
  "type": "Feature",
  "properties": {
    "iso:country":"DE",
    "sg:address":"Kreetortring 132",
    "sg:city":"Hamburg",
    "sg:phone":"+49 40/7960818",
    "sg:postcode":"21147",
    "sg:province":"Hamburg",
    "wof:name":"Astek Klebstoff-auftrags- Systeme Peter Kainz E. K.",
    "wof:placetype":"venue"
},
  "geometry": {"coordinates":[9.8808717728,53.4821548462],"type":"Point"}
}