{
  "type": "Feature",
  "properties": {
    "iso:country":"DE",
    "sg:address":"Havelstr. 22",
    "sg:city":"Darmstadt",
    "sg:postcode":"64295",
    "sg:province":"Hessen",
    "wof:name":"Marimex Verwaltungs- Gmbh",
    "wof:placetype":"venue"
},
  "geometry": {"coordinates":[8.6367559433,49.8690834045],"type":"Point"}
}