{
  "type": "Feature",
  "properties": {
    "iso:country":"DE",
    "sg:address":"Mittelheimer Str. 13",
    "sg:city":"Ingelheim",
    "sg:phone":"+49 6132/87087",
    "sg:postcode":"55218",
    "sg:province":"Rheinland-Pfalz",
    "wof:name":"S. Bockius Immobilienmakler",
    "wof:placetype":"venue"
},
  "geometry": {"coordinates":[8.0213327408,49.9916419983],"type":"Point"}
}