{
  "type": "Feature",
  "properties": {
    "iso:country":"DE",
    "sg:address":"Stadtweg 3",
    "sg:city":"Berkatal",
    "sg:phone":"+49 5652/917850",
    "sg:postcode":"37297",
    "sg:province":"Hessen",
    "wof:name":"Hoch-montagen E. K.",
    "wof:placetype":"venue"
},
  "geometry": {"coordinates":[9.961648,51.241413],"type":"Point"}
}