{
  "type": "Feature",
  "properties": {
    "iso:country":"DE",
    "sg:address":"Acignering 34",
    "sg:city":"Wachtendonk",
    "sg:phone":"+49 2836/1836",
    "sg:postcode":"47669",
    "sg:province":"Nordrhein-Westfalen",
    "wof:name":"Udo Marschner",
    "wof:placetype":"venue"
},
  "geometry": {"coordinates":[6.339421,51.411205],"type":"Point"}
}