{
  "type": "Feature",
  "properties": {
    "iso:country":"DE",
    "sg:address":"Europastr. 46d",
    "sg:city":"Gladbeck",
    "sg:postcode":"45968",
    "sg:province":"Nordrhein-Westfalen",
    "wof:name":"New Concept Edv Vertriebs Gmbh",
    "wof:placetype":"venue"
},
  "geometry": {"coordinates":[6.98905,51.55357],"type":"Point"}
}