{
  "type": "Feature",
  "properties": {
    "iso:country":"DE",
    "sg:address":"Bahnhofstr 9-15",
    "sg:city":"Tutzing",
    "sg:phone":"+49 8158/90400",
    "sg:postcode":"82327",
    "sg:province":"Bayern",
    "wof:name":"Priaton Gmbh",
    "wof:placetype":"venue"
},
  "geometry": {"coordinates":[11.2775602341,47.9081954956],"type":"Point"}
}