{
  "type": "Feature",
  "properties": {
    "iso:country":"DE",
    "sg:address":"Hauptstr. 84",
    "sg:city":"Kittelsthal",
    "sg:phone":"+49 36929/86464",
    "sg:postcode":"99843",
    "wof:name":"Hoyer Montagetechnik Gmbh & Co. Kg",
    "wof:placetype":"venue"
},
  "geometry": {"coordinates":[10.3859224319,50.9262695312],"type":"Point"}
}