{
  "type": "Feature",
  "properties": {
    "iso:country":"DE",
    "sg:address":"Raiffeisenstr. 23",
    "sg:city":"Rastede",
    "sg:phone":"+49 4402/4272",
    "sg:postcode":"26180",
    "sg:province":"Niedersachsen",
    "wof:name":"I. Stalter",
    "wof:placetype":"venue"
},
  "geometry": {"coordinates":[8.191078,53.24876],"type":"Point"}
}