{
  "type": "Feature",
  "properties": {
    "iso:country":"DE",
    "sg:address":"Waldenburger Str. 8",
    "sg:city":"Spenge",
    "sg:phone":"+49 5225/4420",
    "sg:postcode":"32139",
    "sg:province":"Nordrhein-Westfalen",
    "wof:name":"Bau-team Gesellschaft F\u00fcr Modernes Bauen Mbh",
    "wof:placetype":"venue"
},
  "geometry": {"coordinates":[8.472424,52.13942],"type":"Point"}
}