{
  "type": "Feature",
  "properties": {
    "iso:country":"DE",
    "sg:address":"Johanniterstr. 2-4",
    "sg:city":"Aachen",
    "sg:phone":"+49 611/375175",
    "sg:postcode":"52064",
    "sg:province":"Nordrhein-Westfalen",
    "wof:name":"Schneidereibedarfs-gro\u00dfhandel",
    "wof:placetype":"venue"
},
  "geometry": {"coordinates":[6.0772647858,50.7747993469],"type":"Point"}
}