{
  "type": "Feature",
  "properties": {
    "iso:country":"DE",
    "sg:address":"Kleiststr. 67",
    "sg:city":"Leipzig",
    "sg:phone":"+49 341/9126624",
    "sg:postcode":"04157",
    "sg:province":"Sachsen",
    "wof:name":"Barbara M\u00fcller",
    "wof:placetype":"venue"
},
  "geometry": {"coordinates":[12.3809137344,51.369304657],"type":"Point"}
}