{
  "type": "Feature",
  "properties": {
    "iso:country":"DE",
    "sg:address":"Kluser Str. 3",
    "sg:city":"Wippingen",
    "sg:phone":"+49 4966/497",
    "sg:postcode":"26892",
    "sg:province":"Niedersachsen",
    "wof:name":"Wilhelm Gerdes",
    "wof:placetype":"venue"
},
  "geometry": {"coordinates":[7.399823,52.929798],"type":"Point"}
}