{
  "type": "Feature",
  "properties": {
    "iso:country":"DE",
    "sg:address":"Biedenbach 26",
    "sg:city":"Velden",
    "sg:postcode":"84149",
    "sg:province":"Bayern",
    "wof:name":"M. Lainer",
    "wof:placetype":"venue"
},
  "geometry": {"coordinates":[12.272715,48.376511],"type":"Point"}
}