{
  "type": "Feature",
  "properties": {
    "iso:country":"DE",
    "sg:address":"Bahnhofstr. 35",
    "sg:city":"Krefeld",
    "sg:phone":"+49 2151/480048",
    "sg:postcode":"47829",
    "sg:province":"Nordrhein-Westfalen",
    "wof:name":"Uerdinger Funkwagen Komusiewicz & Nickel Gmbh",
    "wof:placetype":"venue"
},
  "geometry": {"coordinates":[6.6469130516,51.357635498],"type":"Point"}
}