{
  "type": "Feature",
  "properties": {
    "iso:country":"DE",
    "sg:address":"Hauptstr. 110",
    "sg:city":"Kirrweiler",
    "sg:phone":"+49 6321/59568",
    "sg:postcode":"67489",
    "sg:province":"Rheinland-Pfalz",
    "wof:name":"Weinstube St. Urban",
    "wof:placetype":"venue"
},
  "geometry": {"coordinates":[8.1561765671,49.3036994934],"type":"Point"}
}