{
  "type": "Feature",
  "properties": {
    "iso:country":"DE",
    "sg:address":"Ziegelhof 1",
    "sg:city":"Greding",
    "sg:postcode":"91171",
    "sg:province":"Bayern",
    "wof:name":"Ziegelhof Gmbh",
    "wof:placetype":"venue"
},
  "geometry": {"coordinates":[11.321112,49.002533],"type":"Point"}
}