{
  "type": "Feature",
  "properties": {
    "iso:country":"DE",
    "sg:address":"Nibelungenstr. 11",
    "sg:city":"M\u00fcnchen",
    "sg:phone":"+49 89/160295",
    "sg:postcode":"80639",
    "sg:province":"Bayern",
    "wof:name":"Christa Helmschrodt",
    "wof:placetype":"venue"
},
  "geometry": {"coordinates":[11.5289525986,48.1530761719],"type":"Point"}
}