{
  "type": "Feature",
  "properties": {
    "iso:country":"DE",
    "sg:address":"G\u00f6dringer Str. 22B",
    "sg:city":"Sarstedt",
    "sg:postcode":"31157",
    "sg:province":"Niedersachsen",
    "wof:name":"C. Gieseke Gmbh",
    "wof:placetype":"venue"
},
  "geometry": {"coordinates":[9.898957,52.241909],"type":"Point"}
}