{
  "type": "Feature",
  "properties": {
    "iso:country":"DE",
    "sg:address":"Gr\u00fcne Aue 7",
    "sg:city":"Dresden",
    "sg:phone":"+49 351/8906424",
    "sg:postcode":"01109",
    "sg:province":"Sachsen",
    "wof:name":"Bernd Bombach",
    "wof:placetype":"venue"
},
  "geometry": {"coordinates":[13.732649,51.117573],"type":"Point"}
}