{
  "type": "Feature",
  "properties": {
    "iso:country":"DE",
    "sg:address":"Negenbarger Str. 93",
    "sg:city":"Wittmund",
    "sg:phone":"+49 4973/1291",
    "sg:postcode":"26409",
    "sg:province":"Niedersachsen",
    "wof:name":"Cornelius Cornelius",
    "wof:placetype":"venue"
},
  "geometry": {"coordinates":[7.675779,53.574615],"type":"Point"}
}