{
  "type": "Feature",
  "properties": {
    "iso:country":"DE",
    "sg:address":"Obermarkt 20",
    "sg:city":"Worms",
    "sg:phone":"+49 6241/24219",
    "sg:postcode":"67547",
    "sg:province":"Rheinland-Pfalz",
    "wof:name":"Fritz Helmling Metzgerei",
    "wof:placetype":"venue"
},
  "geometry": {"coordinates":[8.3616333008,49.6320457458],"type":"Point"}
}