{
  "type": "Feature",
  "properties": {
    "iso:country":"DE",
    "sg:address":"In den Schwarzwiesen 4",
    "sg:city":"Oberursel",
    "sg:phone":"+49 6171/97270",
    "sg:postcode":"61440",
    "sg:province":"Hessen",
    "wof:name":"Barth Galvanik Gmbh",
    "wof:placetype":"venue"
},
  "geometry": {"coordinates":[8.585291,50.188198],"type":"Point"}
}