{
  "type": "Feature",
  "properties": {
    "iso:country":"DE",
    "sg:address":"Jan-van-Werth-Str. 35",
    "sg:city":"Kaarst",
    "sg:phone":"+49 2131/511747",
    "sg:postcode":"41564",
    "sg:province":"Nordrhein-Westfalen",
    "wof:name":"Canto Und Canto Rechtsanw\u00e4lte",
    "wof:placetype":"venue"
},
  "geometry": {"coordinates":[6.6118121147,51.1926956177],"type":"Point"}
}