{
  "type": "Feature",
  "properties": {
    "iso:country":"DE",
    "sg:address":"Am Burgberg 13",
    "sg:city":"Bergheim",
    "sg:phone":"+49 2271/63840",
    "sg:postcode":"50126",
    "sg:province":"Nordrhein-Westfalen",
    "wof:name":"J\u00fcrgen Bartels Rechtsanwalt",
    "wof:placetype":"venue"
},
  "geometry": {"coordinates":[6.649433136,50.9461746216],"type":"Point"}
}