{
  "type": "Feature",
  "properties": {
    "iso:country":"DE",
    "sg:address":"Am Gewerbegebiet 5",
    "sg:city":"Ebersbach",
    "sg:phone":"+49 4934/3167060",
    "sg:postcode":"04720",
    "sg:province":"Sachsen",
    "wof:name":"Verkehrsgesellschaft D\u00d6beln Gmbh",
    "wof:placetype":"venue"
},
  "geometry": {"coordinates":[13.1017808914,51.1051292419],"type":"Point"}
}