{
  "type": "Feature",
  "properties": {
    "iso:country":"DE",
    "sg:address":"N\u00e4hterstr. 217",
    "sg:city":"Stuttgart",
    "sg:phone":"+49 711/481503",
    "sg:postcode":"70327",
    "sg:province":"Baden-W\u00fcrttemberg",
    "wof:name":"Vereinsheim Kleintierz\u00fcchter Gaisburg",
    "wof:placetype":"venue"
},
  "geometry": {"coordinates":[9.2250995636,48.7805709839],"type":"Point"}
}