{
  "type": "Feature",
  "properties": {
    "iso:country":"DE",
    "sg:address":"Am Bahnhof 1",
    "sg:city":"T\u00fc\u00dfling",
    "sg:phone":"+49 8633/1753",
    "sg:postcode":"84577",
    "sg:province":"Bayern",
    "wof:name":"Discothek Blaues Haus",
    "wof:placetype":"venue"
},
  "geometry": {"coordinates":[12.589408,48.212475],"type":"Point"}
}