{
  "type": "Feature",
  "properties": {
    "iso:country":"DE",
    "sg:address":"Henneberger Str. 29",
    "sg:city":"Sonnefeld",
    "sg:phone":"+49 9562/8330",
    "sg:postcode":"96242",
    "sg:province":"Bayern",
    "wof:name":"Jens G. Hirsch Rechtsanwalt",
    "wof:placetype":"venue"
},
  "geometry": {"coordinates":[11.1274614334,50.2157974243],"type":"Point"}
}