{
  "type": "Feature",
  "properties": {
    "iso:country":"DE",
    "sg:address":"Gewerbegebiet Klinkenthal",
    "sg:city":"Schiffweiler",
    "sg:postcode":"66578",
    "sg:province":"Saarland",
    "wof:name":"C & P Anlagenbau Gmbh",
    "wof:placetype":"venue"
},
  "geometry": {"coordinates":[7.101713,49.35083],"type":"Point"}
}