{
  "type": "Feature",
  "properties": {
    "iso:country":"DE",
    "sg:address":"Kaiser-Joseph-Str. 260",
    "sg:city":"Freiburg",
    "sg:phone":"+49 761/385420",
    "sg:postcode":"79098",
    "sg:province":"Baden-W\u00fcrttemberg",
    "wof:name":"Peter Unkelbach Steuerberater",
    "wof:placetype":"venue"
},
  "geometry": {"coordinates":[7.848637104,47.9931030273],"type":"Point"}
}