{
  "type": "Feature",
  "properties": {
    "iso:country":"DE",
    "sg:address":"Eitzumer Str.",
    "sg:city":"Sch\u00f6ppenstedt",
    "sg:phone":"+49 5332/2464",
    "sg:postcode":"38170",
    "sg:province":"Niedersachsen",
    "wof:name":"Watzumer H\u00e4uschen Inh. Hans J\u00fcrgen Zeiger",
    "wof:placetype":"venue"
},
  "geometry": {"coordinates":[10.8071584702,52.1363067627],"type":"Point"}
}