{
  "type": "Feature",
  "properties": {
    "iso:country":"DE",
    "sg:address":"Am Loh 3",
    "sg:city":"Felsberg",
    "sg:phone":"+49 5662/3198",
    "sg:postcode":"34587",
    "sg:province":"Hessen",
    "wof:name":"Gisela Kerst Architektin",
    "wof:placetype":"venue"
},
  "geometry": {"coordinates":[9.433161,51.120747],"type":"Point"}
}