{
  "type": "Feature",
  "properties": {
    "iso:country":"DE",
    "sg:address":"Sentruper Str. 169",
    "sg:city":"M\u00fcnster",
    "sg:phone":"+49 251/81112",
    "sg:postcode":"48149",
    "sg:province":"Nordrhein-Westfalen",
    "wof:name":"Westfalen-tankstelle",
    "wof:placetype":"venue"
},
  "geometry": {"coordinates":[7.5976910591,51.9537811279],"type":"Point"}
}