{
  "type": "Feature",
  "properties": {
    "iso:country":"DE",
    "sg:address":"Laufer Str. 5",
    "sg:city":"Ottersweier",
    "sg:postcode":"77833",
    "sg:province":"Baden-W\u00fcrttemberg",
    "wof:name":"Pfarrb\u00fccherei Ottersweier",
    "wof:placetype":"venue"
},
  "geometry": {"coordinates":[8.111905,48.667683],"type":"Point"}
}