{
  "type": "Feature",
  "properties": {
    "iso:country":"DE",
    "sg:address":"Gruener Weg 8d",
    "sg:city":"Griesheim",
    "sg:phone":"+49 4961/55",
    "sg:postcode":"64347",
    "sg:province":"Hessen",
    "wof:name":"Osiris (gbr)",
    "wof:placetype":"venue"
},
  "geometry": {"coordinates":[8.5524692535,49.8575286865],"type":"Point"}
}