{
  "type": "Feature",
  "properties": {
    "iso:country":"DE",
    "sg:city":"Misselwarden",
    "sg:phone":"+49 4742/8968",
    "sg:postcode":"27632",
    "sg:province":"Niedersachsen",
    "wof:name":"Hendrik M\u00fcller Diskothek",
    "wof:placetype":"venue"
},
  "geometry": {"coordinates":[8.516905,53.675137],"type":"Point"}
}