{
  "type": "Feature",
  "properties": {
    "iso:country":"DE",
    "sg:address":"Einkaufszentrum",
    "sg:city":"Z\u00f6schen",
    "sg:phone":"+49 34638/20392",
    "sg:postcode":"06254",
    "sg:province":"Sachsen-Anhalt",
    "wof:name":"K. Post",
    "wof:placetype":"venue"
},
  "geometry": {"coordinates":[12.135140419,51.3538894653],"type":"Point"}
}