{
  "type": "Feature",
  "properties": {
    "iso:country":"DE",
    "sg:address":"Schaldinger Str. 27a",
    "sg:city":"Passau",
    "sg:phone":"+49 851/81850",
    "sg:postcode":"94036",
    "sg:province":"Bayern",
    "wof:name":"Schatzl Gmbh",
    "wof:placetype":"venue"
},
  "geometry": {"coordinates":[13.372551,48.594326],"type":"Point"}
}