{
  "type": "Feature",
  "properties": {
    "iso:country":"DE",
    "sg:address":"Obere Beutenbergh\u00e4user 5",
    "sg:city":"Chemnitz",
    "sg:phone":"+49 371/724368",
    "sg:postcode":"09128",
    "sg:province":"Sachsen",
    "wof:name":"A. Renner",
    "wof:placetype":"venue"
},
  "geometry": {"coordinates":[13.00443,50.803791],"type":"Point"}
}