{
  "type": "Feature",
  "properties": {
    "iso:country":"DE",
    "sg:address":"Ziegeleistr 3",
    "sg:city":"Dierdorf",
    "sg:phone":"+49 2689/979307",
    "sg:postcode":"56269",
    "sg:province":"Rheinland-Pfalz",
    "wof:name":"Fan-omenal",
    "wof:placetype":"venue"
},
  "geometry": {"coordinates":[7.65038,50.549538],"type":"Point"}
}