{
  "type": "Feature",
  "properties": {
    "iso:country":"DE",
    "sg:address":"Heerstra\u00dfenbenden 6",
    "sg:city":"Rheinbach",
    "sg:phone":"+49 2226/4091",
    "sg:postcode":"53359",
    "sg:province":"Nordrhein-Westfalen",
    "wof:name":"Zahntechnik Thomas Arlt",
    "wof:placetype":"venue"
},
  "geometry": {"coordinates":[6.951027,50.636448],"type":"Point"}
}