{
  "type": "Feature",
  "properties": {
    "iso:country":"DE",
    "sg:address":"Allee 28",
    "sg:city":"Rodenberg",
    "sg:phone":"+49 5723/4180",
    "sg:postcode":"31552",
    "sg:province":"Niedersachsen",
    "wof:name":"Concept-data Gmbh",
    "wof:placetype":"venue"
},
  "geometry": {"coordinates":[9.3538999557,52.3150100708],"type":"Point"}
}