{
  "type": "Feature",
  "properties": {
    "iso:country":"DE",
    "sg:address":"Dieksbecker Weg 1",
    "sg:city":"Bienenb\u00fcttel",
    "sg:phone":"+49 5823/376",
    "sg:postcode":"29553",
    "sg:province":"Niedersachsen",
    "wof:name":"Sigrid Wischnewski",
    "wof:placetype":"venue"
},
  "geometry": {"coordinates":[10.4822998047,53.1536178589],"type":"Point"}
}