{
  "type": "Feature",
  "properties": {
    "iso:country":"DE",
    "sg:address":"Rudolf-Breitscheid-Str. 24",
    "sg:city":"Eisenach",
    "sg:phone":"+49 3691/872734",
    "sg:postcode":"99817",
    "sg:province":"Th\u00fcringen",
    "wof:name":"K. Ebert",
    "wof:placetype":"venue"
},
  "geometry": {"coordinates":[10.295973,50.990868],"type":"Point"}
}