{
  "type": "Feature",
  "properties": {
    "iso:country":"DE",
    "sg:address":"Wiesestr. 189",
    "sg:city":"Gera",
    "sg:phone":"+49 365/7375730",
    "sg:postcode":"07551",
    "sg:province":"Th\u00fcringen",
    "wof:name":"Network Providing Gmbh",
    "wof:placetype":"venue"
},
  "geometry": {"coordinates":[12.0729598999,50.8533363342],"type":"Point"}
}