{
  "type": "Feature",
  "properties": {
    "iso:country":"DE",
    "sg:address":"Kaiserstr. 117",
    "sg:city":"Karlsruhe",
    "sg:phone":"+49 721/9322311",
    "sg:postcode":"76133",
    "sg:province":"Baden-W\u00fcrttemberg",
    "wof:name":"Gastst\u00e4tte Ursula Brenner",
    "wof:placetype":"venue"
},
  "geometry": {"coordinates":[8.4063711166,49.0093421936],"type":"Point"}
}