{
  "type": "Feature",
  "properties": {
    "iso:country":"DE",
    "sg:address":"Hauptstr. 55",
    "sg:city":"Neub\u00f6rger",
    "sg:phone":"+49 4966/230",
    "sg:postcode":"26909",
    "sg:province":"Niedersachsen",
    "wof:name":"W. Und A. M\u00fcller",
    "wof:placetype":"venue"
},
  "geometry": {"coordinates":[7.4495310783,52.9503936768],"type":"Point"}
}