{
  "type": "Feature",
  "properties": {
    "iso:country":"DE",
    "sg:address":"Friedrichstr. 22",
    "sg:city":"Denkendorf",
    "sg:postcode":"73770",
    "sg:province":"Baden-W\u00fcrttemberg",
    "wof:name":"J\u00e4nchen Verwaltungs Gmbh",
    "wof:placetype":"venue"
},
  "geometry": {"coordinates":[9.315114975,48.695350647],"type":"Point"}
}