{
  "type": "Feature",
  "properties": {
    "iso:country":"DE",
    "sg:address":"Vautswiesenweg 13 a",
    "sg:city":"Kassel",
    "sg:phone":"+49 561/571339",
    "sg:postcode":"34123",
    "sg:province":"Hessen",
    "wof:name":"Dietrich Bedachungs Gmbh",
    "wof:placetype":"venue"
},
  "geometry": {"coordinates":[9.514515,51.292366],"type":"Point"}
}