{
  "type": "Feature",
  "properties": {
    "iso:country":"DE",
    "sg:address":"Jachthafen 9",
    "sg:city":"Bernried",
    "sg:phone":"+49 8158/3259",
    "sg:postcode":"82347",
    "sg:province":"Bayern",
    "wof:name":"Elan Elektro-dienst Gmbh",
    "wof:placetype":"venue"
},
  "geometry": {"coordinates":[11.2924699783,47.8672332764],"type":"Point"}
}