{
  "type": "Feature",
  "properties": {
    "iso:country":"DE",
    "sg:address":"Bruchhausener Str. 30a",
    "sg:city":"Arnsberg",
    "sg:phone":"+49 2932/35708",
    "sg:postcode":"59759",
    "sg:province":"Nordrhein-Westfalen",
    "wof:name":"K.-h. Vo\u00df",
    "wof:placetype":"venue"
},
  "geometry": {"coordinates":[8.023053,51.4245],"type":"Point"}
}