{
  "type": "Feature",
  "properties": {
    "iso:country":"DE",
    "sg:address":"Ravolzh\u00e4user Str. 28",
    "sg:city":"Neuberg",
    "sg:postcode":"63543",
    "sg:province":"Hessen",
    "wof:name":"Dogifood Tierfutter- Und Tierbedarfshandel Sowie Heim-",
    "wof:placetype":"venue"
},
  "geometry": {"coordinates":[8.977356,50.203053],"type":"Point"}
}