{
  "type": "Feature",
  "properties": {
    "iso:country":"DE",
    "sg:address":"Saargem\u00fcnder Str. 161",
    "sg:city":"Saarbr\u00fccken",
    "sg:postcode":"66129",
    "sg:province":"Saarland",
    "wof:name":"Fahrlehrer-service Gmbh",
    "wof:placetype":"venue"
},
  "geometry": {"coordinates":[7.0374908447,49.1795310974],"type":"Point"}
}