{
  "type": "Feature",
  "properties": {
    "iso:country":"DE",
    "sg:address":"Nimrodstr. 26",
    "sg:city":"Germering",
    "sg:postcode":"82110",
    "sg:province":"Bayern",
    "wof:name":"Gieck-verlag Gmbh",
    "wof:placetype":"venue"
},
  "geometry": {"coordinates":[11.3845348358,48.1283836365],"type":"Point"}
}