{
  "type": "Feature",
  "properties": {
    "iso:country":"DE",
    "sg:address":"Sauerlandstr. 55",
    "sg:city":"Marsberg",
    "sg:phone":"+49 2991/6732",
    "sg:postcode":"34431",
    "sg:province":"Nordrhein-Westfalen",
    "wof:name":"Friedhelm Schulz",
    "wof:placetype":"venue"
},
  "geometry": {"coordinates":[8.7669696808,51.4134483337],"type":"Point"}
}