{
  "type": "Feature",
  "properties": {
    "iso:country":"DE",
    "sg:address":"Rechbergstr 1",
    "sg:city":"Denkendorf",
    "sg:phone":"+49 711/9344610",
    "sg:postcode":"73770",
    "sg:province":"Baden-W\u00fcrttemberg",
    "wof:name":"Tecfast Verbindungssysteme Gmbh",
    "wof:placetype":"venue"
},
  "geometry": {"coordinates":[9.310579,48.702],"type":"Point"}
}