{
  "type": "Feature",
  "properties": {
    "iso:country":"DE",
    "sg:address":"Gartenstr. 10",
    "sg:city":"Waldkirchen",
    "sg:phone":"+49 8581/8467",
    "sg:postcode":"94065",
    "sg:province":"Bayern",
    "wof:name":"Helmut Streit",
    "wof:placetype":"venue"
},
  "geometry": {"coordinates":[13.596194,48.72588],"type":"Point"}
}