{
  "type": "Feature",
  "properties": {
    "iso:country":"DE",
    "sg:address":"Hauptstra\u00dfe 15",
    "sg:city":"Goldenstedt",
    "sg:phone":"+49 4444",
    "sg:postcode":"49424",
    "sg:province":"Niedersachsen",
    "wof:name":"Rechtsanwalt Thomas Kr\u00f6ger",
    "wof:placetype":"venue"
},
  "geometry": {"coordinates":[8.430797,52.785172],"type":"Point"}
}