{
  "type": "Feature",
  "properties": {
    "iso:country":"DE",
    "sg:address":"Kaiserstr. 217",
    "sg:city":"Karlsruhe",
    "sg:postcode":"76133",
    "sg:province":"Baden-W\u00fcrttemberg",
    "wof:name":"Ticket Forum Gmbh",
    "wof:placetype":"venue"
},
  "geometry": {"coordinates":[8.394591,49.009895],"type":"Point"}
}