{
  "type": "Feature",
  "properties": {
    "iso:country":"DE",
    "sg:address":"Schillerstr. 77",
    "sg:city":"Neu-Isenburg",
    "sg:phone":"+49 6102/6445",
    "sg:postcode":"63263",
    "sg:province":"Hessen",
    "wof:name":"Marianne Kl\u00fcppel Antiquit\u00e4ten",
    "wof:placetype":"venue"
},
  "geometry": {"coordinates":[8.687054,50.052948],"type":"Point"}
}