{
  "type": "Feature",
  "properties": {
    "iso:country":"DE",
    "sg:address":"Thyssenstr. 7",
    "sg:city":"Berlin",
    "sg:phone":"+49 30/408070",
    "sg:postcode":"13407",
    "sg:province":"Berlin",
    "wof:name":"Janol Gmbh & Co. Kg",
    "wof:placetype":"venue"
},
  "geometry": {"coordinates":[13.3444347382,52.5803260803],"type":"Point"}
}