{
  "type": "Feature",
  "properties": {
    "iso:country":"DE",
    "sg:address":"Obercunnersdorfer Str. 15",
    "sg:city":"Herrnhut",
    "sg:phone":"+49 35873/40556",
    "sg:postcode":"02747",
    "sg:province":"Sachsen",
    "wof:name":"Christian G\u00f6bel",
    "wof:placetype":"venue"
},
  "geometry": {"coordinates":[14.701477,50.999454],"type":"Point"}
}