{
  "type": "Feature",
  "properties": {
    "iso:country":"DE",
    "sg:address":"Kammerloh 9",
    "sg:city":"Henstedt-Ulzburg",
    "sg:postcode":"24558",
    "sg:province":"Schleswig-Holstein",
    "wof:name":"P\u00e4tzel Bautenschutz Gmbh",
    "wof:placetype":"venue"
},
  "geometry": {"coordinates":[9.973862648,53.7950935364],"type":"Point"}
}