{
  "type": "Feature",
  "properties": {
    "iso:country":"DE",
    "sg:address":"N\u00fcrnberger Str. 64",
    "sg:city":"Alheim",
    "sg:phone":"+49 5664/94950",
    "sg:postcode":"36211",
    "sg:province":"Hessen",
    "wof:name":"Heinz Abel Ohg",
    "wof:placetype":"venue"
},
  "geometry": {"coordinates":[9.6703071594,51.0438537598],"type":"Point"}
}