{
  "type": "Feature",
  "properties": {
    "iso:country":"DE",
    "sg:address":"Rombachstr. 82",
    "sg:city":"Neunkirchen",
    "sg:phone":"+49 6821/41757",
    "sg:postcode":"66539",
    "sg:province":"Saarland",
    "wof:name":"Zur Rombach",
    "wof:placetype":"venue"
},
  "geometry": {"coordinates":[7.2146291733,49.3546829224],"type":"Point"}
}