{
  "type": "Feature",
  "properties": {
    "iso:country":"DE",
    "sg:address":"Sellenstr. 14",
    "sg:city":"Schimberg",
    "sg:phone":"+49 36082/45510",
    "sg:postcode":"37308",
    "sg:province":"Th\u00fcringen",
    "wof:name":"W. Sonntag",
    "wof:placetype":"venue"
},
  "geometry": {"coordinates":[10.18073,51.288422],"type":"Point"}
}