{
  "type": "Feature",
  "properties": {
    "iso:country":"DE",
    "sg:address":"Ruhhorn 2",
    "sg:city":"Petershagen",
    "sg:phone":"+49 5707/2260",
    "sg:postcode":"32469",
    "sg:province":"Nordrhein-Westfalen",
    "wof:name":"H. Henken",
    "wof:placetype":"venue"
},
  "geometry": {"coordinates":[8.9309930801,52.3946876526],"type":"Point"}
}