{
  "type": "Feature",
  "properties": {
    "iso:country":"DE",
    "sg:address":"Werner-Heisenberg-Str. 10",
    "sg:city":"Viernheim",
    "sg:phone":"+49 6204/970200",
    "sg:postcode":"68519",
    "sg:province":"Hessen",
    "wof:name":"Die Media Gmbh",
    "wof:placetype":"venue"
},
  "geometry": {"coordinates":[8.593568,49.554245],"type":"Point"}
}