{
  "type": "Feature",
  "properties": {
    "iso:country":"DE",
    "sg:address":"Pirnaer Landstr. 229",
    "sg:city":"Dresden",
    "sg:phone":"+49 351/2231063",
    "sg:postcode":"01259",
    "sg:province":"Sachsen",
    "wof:name":"W. Schmidt Anlageberater",
    "wof:placetype":"venue"
},
  "geometry": {"coordinates":[13.8410797119,51.004234314],"type":"Point"}
}