{
  "type": "Feature",
  "properties": {
    "iso:country":"DE",
    "sg:address":"Badstr. 3",
    "sg:city":"Schwaikheim",
    "sg:phone":"+49 7195/51398",
    "sg:postcode":"71409",
    "sg:province":"Baden-W\u00fcrttemberg",
    "wof:name":"Heinz Wieland",
    "wof:placetype":"venue"
},
  "geometry": {"coordinates":[9.351258,48.876675],"type":"Point"}
}