{
  "type": "Feature",
  "properties": {
    "iso:country":"DE",
    "sg:address":"Ringstra\u00dfe 4",
    "sg:city":"Jettingen",
    "sg:postcode":"71131",
    "sg:province":"Baden-W\u00fcrttemberg",
    "wof:name":"Treppenmeister",
    "wof:placetype":"venue"
},
  "geometry": {"coordinates":[8.7750520706,48.5622177124],"type":"Point"}
}