{
  "type": "Feature",
  "properties": {
    "iso:country":"DE",
    "sg:address":"Panoramastr. 17",
    "sg:city":"Taunusstein",
    "sg:phone":"+49 6128/43601",
    "sg:postcode":"65232",
    "sg:province":"Hessen",
    "wof:name":"Hermann Koch Kg",
    "wof:placetype":"venue"
},
  "geometry": {"coordinates":[8.1376428604,50.1317367554],"type":"Point"}
}