{
  "type": "Feature",
  "properties": {
    "iso:country":"DE",
    "sg:address":"Goethestr. 11",
    "sg:city":"Regis-Breitingen",
    "sg:phone":"+49 34343/51445",
    "sg:postcode":"04565",
    "sg:province":"Sachsen",
    "wof:name":"M\u00f6bel - Zetzsche",
    "wof:placetype":"venue"
},
  "geometry": {"coordinates":[12.4447450638,51.091342926],"type":"Point"}
}