{
  "type": "Feature",
  "properties": {
    "iso:country":"DE",
    "sg:address":"Siebenlindenstra\u00dfe 25",
    "sg:city":"Rottenburg am Neckar",
    "sg:phone":"+49 7472/281799",
    "sg:postcode":"72108",
    "sg:province":"Baden-W\u00fcrttemberg",
    "wof:name":"Geiger & Haas Gmbh Industriewartung Und Service",
    "wof:placetype":"venue"
},
  "geometry": {"coordinates":[8.9511470795,48.4734687805],"type":"Point"}
}