{
  "type": "Feature",
  "properties": {
    "iso:country":"DE",
    "sg:address":"Von-Boch-Str. 24",
    "sg:city":"Losheim",
    "sg:phone":"+49 6872/2261",
    "sg:postcode":"66679",
    "sg:province":"Saarland",
    "wof:name":"Restaurant-pension Zum Jungenwald",
    "wof:placetype":"venue"
},
  "geometry": {"coordinates":[6.6690568924,49.5260314941],"type":"Point"}
}