{
  "type": "Feature",
  "properties": {
    "iso:country":"DE",
    "sg:address":"Weilbachstr. 22",
    "sg:city":"Jungingen",
    "sg:postcode":"72417",
    "sg:province":"Baden-W\u00fcrttemberg",
    "wof:name":"Gebr.pr\u00f6pster Verwaltungs-gmbh",
    "wof:placetype":"venue"
},
  "geometry": {"coordinates":[9.0405321121,48.3307151794],"type":"Point"}
}