{
  "type": "Feature",
  "properties": {
    "iso:country":"DE",
    "sg:address":"Hammerweg 5",
    "sg:city":"Engelskirchen",
    "sg:phone":"+49 2263/969864",
    "sg:postcode":"51766",
    "sg:province":"Nordrhein-Westfalen",
    "wof:name":"Gesundheit Europa",
    "wof:placetype":"venue"
},
  "geometry": {"coordinates":[7.466787,50.997189],"type":"Point"}
}