{
  "type": "Feature",
  "properties": {
    "iso:country":"DE",
    "sg:address":"Josephspitalstr. 12",
    "sg:city":"M\u00fcnchen",
    "sg:phone":"+49 89/594959",
    "sg:postcode":"80331",
    "sg:province":"Bayern",
    "wof:name":"Bernd Groh",
    "wof:placetype":"venue"
},
  "geometry": {"coordinates":[11.566466,48.136677],"type":"Point"}
}