{
  "type": "Feature",
  "properties": {
    "iso:country":"DE",
    "sg:address":"Kleinenwieden 47",
    "sg:city":"Hessisch Oldendorf",
    "sg:phone":"+49 5152/3755",
    "sg:postcode":"31840",
    "sg:province":"Niedersachsen",
    "wof:name":"Frank Meyer",
    "wof:placetype":"venue"
},
  "geometry": {"coordinates":[9.1672916412,52.1757736206],"type":"Point"}
}