{
  "type": "Feature",
  "properties": {
    "iso:country":"DE",
    "sg:address":"Reitfeld 4",
    "sg:city":"W\u00f6rth",
    "sg:phone":"+49 9482/1012",
    "sg:postcode":"93086",
    "sg:province":"Bayern",
    "wof:name":"Konstruktionsb\u00fcro Und Vorrichtungsbau Bredl Gmbh",
    "wof:placetype":"venue"
},
  "geometry": {"coordinates":[12.40402,49.007961],"type":"Point"}
}