{
  "type": "Feature",
  "properties": {
    "iso:country":"DE",
    "sg:address":"Wildberg 62",
    "sg:city":"Wei\u00dfensberg",
    "sg:phone":"+49 8389/722",
    "sg:postcode":"88138",
    "sg:province":"Bayern",
    "wof:name":"Infralet Lampen Gmbh & Co.",
    "wof:placetype":"venue"
},
  "geometry": {"coordinates":[9.7369146347,47.5964012146],"type":"Point"}
}