{
  "type": "Feature",
  "properties": {
    "iso:country":"DE",
    "sg:address":"G\u00f6ddertzgarten 15",
    "sg:city":"Meckenheim",
    "sg:phone":"+49 2225/700049",
    "sg:postcode":"53340",
    "sg:province":"Nordrhein-Westfalen",
    "wof:name":"Praxis Dr. Mooslehner",
    "wof:placetype":"venue"
},
  "geometry": {"coordinates":[7.051981,50.631733],"type":"Point"}
}