{
  "type": "Feature",
  "properties": {
    "iso:country":"DE",
    "sg:address":"Hermann-Fischer-Allee 12",
    "sg:city":"Donaueschingen",
    "sg:phone":"+49 771/2321",
    "sg:postcode":"78166",
    "sg:province":"Baden-W\u00fcrttemberg",
    "wof:name":"Ev. Pfarramt",
    "wof:placetype":"venue"
},
  "geometry": {"coordinates":[8.4929523468,47.9507217407],"type":"Point"}
}