{
  "type": "Feature",
  "properties": {
    "iso:country":"DE",
    "sg:address":"Bleichstr. 28a",
    "sg:city":"Bad Lippspringe",
    "sg:phone":"+49 5252/51629",
    "sg:postcode":"33175",
    "sg:province":"Nordrhein-Westfalen",
    "wof:name":"Willi Rummenie Ingenieur",
    "wof:placetype":"venue"
},
  "geometry": {"coordinates":[8.804145813,51.7790527344],"type":"Point"}
}