{
  "type": "Feature",
  "properties": {
    "iso:country":"DE",
    "sg:address":"Narzissenstr. 8 a",
    "sg:city":"M\u00fcnchen",
    "sg:phone":"+49 89/707949",
    "sg:postcode":"80689",
    "sg:province":"Bayern",
    "wof:name":"Karl Und Beatrix Kovacs",
    "wof:placetype":"venue"
},
  "geometry": {"coordinates":[11.486242,48.124844],"type":"Point"}
}