{
  "type": "Feature",
  "properties": {
    "iso:country":"DE",
    "sg:address":"Hauptstr. 5",
    "sg:city":"Dielmissen",
    "sg:phone":"+49 5534/99250",
    "sg:postcode":"37633",
    "sg:province":"Niedersachsen",
    "wof:name":"Wasserbeschaffungsverband",
    "wof:placetype":"venue"
},
  "geometry": {"coordinates":[9.6036596298,51.9661636353],"type":"Point"}
}