{
  "type": "Feature",
  "properties": {
    "iso:country":"DE",
    "sg:address":"Heimst\u00e4ttenweg 9",
    "sg:city":"Bremen",
    "sg:phone":"+49 421/6090803",
    "sg:postcode":"28779",
    "sg:province":"Bremen",
    "wof:name":"Friedrich Von Rittern Ingenieur",
    "wof:placetype":"venue"
},
  "geometry": {"coordinates":[8.574338913,53.1857261658],"type":"Point"}
}