{
  "type": "Feature",
  "properties": {
    "iso:country":"DE",
    "sg:address":"Wieden\u00e4ckerweg 10",
    "sg:city":"Lenningen",
    "sg:phone":"+49 7026/5242",
    "sg:postcode":"73252",
    "sg:province":"Baden-W\u00fcrttemberg",
    "wof:name":"D. Und K. Beuttel",
    "wof:placetype":"venue"
},
  "geometry": {"coordinates":[9.4737567902,48.5451507568],"type":"Point"}
}