{
  "type": "Feature",
  "properties": {
    "iso:country":"DE",
    "sg:address":"Wunsiedler Str. 24",
    "sg:city":"Nagel",
    "sg:postcode":"95697",
    "sg:province":"Bayern",
    "wof:name":"Nageler Commun-br\u00e4u Gmbh",
    "wof:placetype":"venue"
},
  "geometry": {"coordinates":[11.935498,49.981548],"type":"Point"}
}