{
  "type": "Feature",
  "properties": {
    "iso:country":"DE",
    "sg:address":"Gewerbepark 10",
    "sg:city":"Hatten",
    "sg:phone":"+49 4482/1333",
    "sg:postcode":"26209",
    "sg:province":"Niedersachsen",
    "wof:name":"Hs Handelsagentur Lieferant Von Additiven F\u00fcr Die Lebens-",
    "wof:placetype":"venue"
},
  "geometry": {"coordinates":[8.3561515808,53.0598754883],"type":"Point"}
}