{
  "type": "Feature",
  "properties": {
    "iso:country":"DE",
    "sg:address":"Rodigallee 217",
    "sg:city":"Hamburg",
    "sg:postcode":"22043",
    "sg:province":"Hamburg",
    "wof:name":"Aldi Gmbh & Co. Kg",
    "wof:placetype":"venue"
},
  "geometry": {"coordinates":[10.1231069565,53.5711517334],"type":"Point"}
}