{
  "type": "Feature",
  "properties": {
    "iso:country":"DE",
    "sg:address":"Senefelderstr 58",
    "sg:city":"Offenbach",
    "sg:phone":"+49 69/835028",
    "sg:postcode":"63069",
    "sg:province":"Hessen",
    "wof:name":"Ingenieurb\u00fcro Arndt",
    "wof:placetype":"venue"
},
  "geometry": {"coordinates":[8.762735,50.095783],"type":"Point"}
}