{
  "type": "Feature",
  "properties": {
    "iso:country":"DE",
    "sg:address":"Chausseestr. 16",
    "sg:city":"Berlin",
    "sg:postcode":"10115",
    "sg:province":"Berlin",
    "wof:name":"Arts And Friends Kulturmanagement Gmbh",
    "wof:placetype":"venue"
},
  "geometry": {"coordinates":[13.3843955994,52.5297393799],"type":"Point"}
}