{
  "type": "Feature",
  "properties": {
    "iso:country":"DE",
    "sg:address":"Westfalenstr. 5",
    "sg:city":"Ohrdruf",
    "sg:phone":"+49 3624/313606",
    "sg:postcode":"99885",
    "sg:province":"Th\u00fcringen",
    "wof:name":"Elektroanlagenrolapp & Kr\u00dcger Gmbh",
    "wof:placetype":"venue"
},
  "geometry": {"coordinates":[10.71658,50.83754],"type":"Point"}
}