{
  "type": "Feature",
  "properties": {
    "iso:country":"DE",
    "sg:address":"Adlerstr. 45",
    "sg:city":"Karlsruhe",
    "sg:phone":"+49 721/358404",
    "sg:postcode":"76133",
    "sg:province":"Baden-W\u00fcrttemberg",
    "wof:name":"Klaus Und Michael Maier",
    "wof:placetype":"venue"
},
  "geometry": {"coordinates":[8.4087047577,49.0060386658],"type":"Point"}
}