{
  "type": "Feature",
  "properties": {
    "iso:country":"DE",
    "sg:address":"Vorstadt 11",
    "sg:city":"Sulz",
    "sg:phone":"+49 7454/2309",
    "sg:postcode":"72172",
    "sg:province":"Baden-W\u00fcrttemberg",
    "wof:name":"Walter W\u00f6rner",
    "wof:placetype":"venue"
},
  "geometry": {"coordinates":[8.6330451965,48.3641014099],"type":"Point"}
}