{
  "type": "Feature",
  "properties": {
    "iso:country":"DE",
    "sg:address":"Rothenfelder Str. 13 a",
    "sg:city":"Wolfsburg",
    "sg:postcode":"38440",
    "sg:province":"Niedersachsen",
    "wof:name":"Studio C Inh. Andreas M\u00fcller E. K.",
    "wof:placetype":"venue"
},
  "geometry": {"coordinates":[10.791765,52.424522],"type":"Point"}
}