{
  "type": "Feature",
  "properties": {
    "iso:country":"DE",
    "sg:address":"Johann-Hackl-Ring 35",
    "sg:city":"Grasbrunn",
    "sg:phone":"+49 89/45601010",
    "sg:postcode":"85630",
    "sg:province":"Bayern",
    "wof:name":"G. Thelen Immobilienmakler",
    "wof:placetype":"venue"
},
  "geometry": {"coordinates":[11.7695484161,48.0931091309],"type":"Point"}
}