{
  "type": "Feature",
  "properties": {
    "iso:country":"DE",
    "sg:address":"Gartenstr. 25a",
    "sg:city":"Orsingen-Nenzingen",
    "sg:phone":"+49 7771/4691",
    "sg:postcode":"78359",
    "sg:province":"Baden-W\u00fcrttemberg",
    "wof:name":"Rainer Herzog",
    "wof:placetype":"venue"
},
  "geometry": {"coordinates":[8.9569807053,47.8442649841],"type":"Point"}
}