{
  "type": "Feature",
  "properties": {
    "iso:country":"DE",
    "sg:address":"Josef-Bautz Strasse 20::",
    "sg:city":"Hanau",
    "sg:phone":"+49 4961/8155081",
    "sg:postcode":"63457",
    "sg:province":"Hessen",
    "wof:name":"Dth - Dichtungstechnik Gmbh",
    "wof:placetype":"venue"
},
  "geometry": {"coordinates":[8.926156,50.111038],"type":"Point"}
}