{
  "type": "Feature",
  "properties": {
    "iso:country":"DE",
    "sg:address":"Biegelstr. 2",
    "sg:city":"Weissach",
    "sg:phone":"+49 7044/930393",
    "sg:postcode":"71287",
    "sg:province":"Baden-W\u00fcrttemberg",
    "wof:name":"M. De Rosa Immobilienmakler",
    "wof:placetype":"venue"
},
  "geometry": {"coordinates":[8.9265470505,48.8492240906],"type":"Point"}
}