{
  "type": "Feature",
  "properties": {
    "iso:country":"DE",
    "sg:address":"Reisingerstr. 49",
    "sg:city":"Ismaning",
    "sg:phone":"+49 89/966529",
    "sg:postcode":"85737",
    "sg:province":"Bayern",
    "wof:name":"Musik-management Seelos Franz W. Seelos",
    "wof:placetype":"venue"
},
  "geometry": {"coordinates":[11.6681051254,48.2167015076],"type":"Point"}
}