{
  "type": "Feature",
  "properties": {
    "iso:country":"DE",
    "sg:address":"Innstr. 70",
    "sg:city":"Rosenheim",
    "sg:phone":"+49 8031/16443",
    "sg:postcode":"83022",
    "sg:province":"Bayern",
    "wof:name":"Die Kleine Kneipe",
    "wof:placetype":"venue"
},
  "geometry": {"coordinates":[12.1399383545,47.8547286987],"type":"Point"}
}