{
  "type": "Feature",
  "properties": {
    "iso:country":"DE",
    "sg:address":"N\u00fcrnberger Str. 31 A",
    "sg:city":"Dresden",
    "sg:phone":"+49 351/4721244",
    "sg:postcode":"01187",
    "sg:province":"Sachsen",
    "wof:name":"Steinert & Partner Gmbh",
    "wof:placetype":"venue"
},
  "geometry": {"coordinates":[13.7212705612,51.0346107483],"type":"Point"}
}