{
  "type": "Feature",
  "properties": {
    "iso:country":"DE",
    "sg:address":"Hauptstr. 31",
    "sg:city":"Neukirchen",
    "sg:phone":"+49 9947/539",
    "sg:postcode":"93453",
    "sg:province":"Bayern",
    "wof:name":"Gastst\u00e4tte Ludwig Treml",
    "wof:placetype":"venue"
},
  "geometry": {"coordinates":[13.0465450287,49.2481307983],"type":"Point"}
}