{
  "type": "Feature",
  "properties": {
    "iso:country":"DE",
    "sg:address":"Reichsbahnstra\u00dfe 16",
    "sg:city":"Hagen",
    "sg:phone":"+49 2331/301131",
    "sg:postcode":"58089",
    "sg:province":"Nordrhein-Westfalen",
    "wof:name":"Pvu Service Und Consulting Gmbh",
    "wof:placetype":"venue"
},
  "geometry": {"coordinates":[7.432453,51.386127],"type":"Point"}
}