{
  "type": "Feature",
  "properties": {
    "iso:country":"DE",
    "sg:address":"Freilandstr. 53",
    "sg:city":"Puchheim",
    "sg:phone":"+49 89/804568",
    "sg:postcode":"82178",
    "sg:province":"Bayern",
    "wof:name":"L\u00fcftomatic Ges. F\u00fcr L\u00fcftungs- U. Klimatechnik Mbh",
    "wof:placetype":"venue"
},
  "geometry": {"coordinates":[11.3580789566,48.1784629822],"type":"Point"}
}