{
  "type": "Feature",
  "properties": {
    "iso:country":"DE",
    "sg:address":"Gehrnstr.",
    "sg:city":"Ettlingen",
    "sg:postcode":"76275",
    "sg:province":"Baden-W\u00fcrttemberg",
    "wof:name":"Schneiders\u00f6hne Kuvert Gmbh & Co. Kg",
    "wof:placetype":"venue"
},
  "geometry": {"coordinates":[8.3911828995,48.9488525391],"type":"Point"}
}