{
  "type": "Feature",
  "properties": {
    "iso:country":"DE",
    "sg:address":"Marktstr. 131",
    "sg:city":"Hamburg",
    "sg:phone":"+49 40/4393889",
    "sg:postcode":"20357",
    "sg:province":"Hamburg",
    "wof:name":"Lollo Rossa",
    "wof:placetype":"venue"
},
  "geometry": {"coordinates":[9.9732151031,53.5586013794],"type":"Point"}
}