{
  "type": "Feature",
  "properties": {
    "iso:country":"DE",
    "sg:address":"August-Bebel-Str. 9",
    "sg:city":"Oppach",
    "sg:phone":"+49 35872/32335",
    "sg:postcode":"02736",
    "sg:province":"Sachsen",
    "wof:name":"Drogerie Lehmann",
    "wof:placetype":"venue"
},
  "geometry": {"coordinates":[14.502175,51.058884],"type":"Point"}
}