{
  "type": "Feature",
  "properties": {
    "iso:country":"DE",
    "sg:address":"Kirchberg 28",
    "sg:city":"Overath",
    "sg:phone":"+49 2206/3603",
    "sg:postcode":"51491",
    "sg:province":"Nordrhein-Westfalen",
    "wof:name":"H. Leithe Immobilienmakler",
    "wof:placetype":"venue"
},
  "geometry": {"coordinates":[7.2821550369,50.9357528687],"type":"Point"}
}