{
  "type": "Feature",
  "properties": {
    "iso:country":"DE",
    "sg:address":"Beckstetten 62",
    "sg:city":"Jengen",
    "sg:phone":"+49 8241/1866",
    "sg:postcode":"86860",
    "sg:province":"Bayern",
    "wof:name":"J. Ostenberger",
    "wof:placetype":"venue"
},
  "geometry": {"coordinates":[10.7261953354,47.9999389648],"type":"Point"}
}