{
  "type": "Feature",
  "properties": {
    "iso:country":"DE",
    "sg:address":"Platz des Friedens",
    "sg:city":"Stralsund",
    "sg:postcode":"18437",
    "sg:province":"Mecklenburg-Vorpommern",
    "wof:name":"Dawa Dach Und Wand Baustsoffgro\u00dfhandelsges. Mbh",
    "wof:placetype":"venue"
},
  "geometry": {"coordinates":[13.067715,54.310699],"type":"Point"}
}