{
  "type": "Feature",
  "properties": {
    "iso:country":"DE",
    "sg:address":"Bergstr. 4",
    "sg:city":"Halberstadt",
    "sg:phone":"+49 3941/601381",
    "sg:postcode":"38820",
    "sg:province":"Sachsen-Anhalt",
    "wof:name":"R. Kube",
    "wof:placetype":"venue"
},
  "geometry": {"coordinates":[11.0404777527,51.8901023865],"type":"Point"}
}