{
  "type": "Feature",
  "properties": {
    "iso:country":"DE",
    "sg:address":"Schiffstr. 7",
    "sg:city":"Freiburg",
    "sg:postcode":"79098",
    "sg:province":"Baden-W\u00fcrttemberg",
    "wof:name":"Emidio Verdeccia",
    "wof:placetype":"venue"
},
  "geometry": {"coordinates":[7.850575,47.997208],"type":"Point"}
}