{
  "type": "Feature",
  "properties": {
    "iso:country":"DE",
    "sg:address":"Koloniestr. 61",
    "sg:city":"Duisburg",
    "sg:postcode":"47057",
    "sg:province":"Nordrhein-Westfalen",
    "wof:name":"S & H Autohandelsges. Mbh",
    "wof:placetype":"venue"
},
  "geometry": {"coordinates":[6.779689,51.424416],"type":"Point"}
}