{
  "type": "Feature",
  "properties": {
    "iso:country":"DE",
    "sg:address":"Osloer Str. 116",
    "sg:city":"Berlin",
    "sg:phone":"+49 30/4931003",
    "sg:postcode":"13359",
    "sg:province":"Berlin",
    "wof:name":"Antonio Magro Dolmetscher",
    "wof:placetype":"venue"
},
  "geometry": {"coordinates":[13.386691,52.555389],"type":"Point"}
}