{
  "type": "Feature",
  "properties": {
    "iso:country":"DE",
    "sg:address":"Lichtentaler Str. 37 - 41",
    "sg:city":"Baden-Baden",
    "sg:phone":"+49 7221/31721",
    "sg:postcode":"76530",
    "sg:province":"Baden-W\u00fcrttemberg",
    "wof:name":"Fina Sb-tankstelle",
    "wof:placetype":"venue"
},
  "geometry": {"coordinates":[8.2416038513,48.7582054138],"type":"Point"}
}