{
  "type": "Feature",
  "properties": {
    "iso:country":"DE",
    "sg:address":"Frankenbergstr. 30",
    "sg:city":"Berlin",
    "sg:phone":"+49 30/64849203",
    "sg:postcode":"12589",
    "sg:province":"Berlin",
    "wof:name":"Bioptisches Institut Dr. Med. Ute Seifert",
    "wof:placetype":"venue"
},
  "geometry": {"coordinates":[13.716802597,52.4365959167],"type":"Point"}
}