{
  "type": "Feature",
  "properties": {
    "iso:country":"DE",
    "sg:address":"Hauptstr. 90",
    "sg:city":"Baesweiler",
    "sg:phone":"+49 2401/5853",
    "sg:postcode":"52499",
    "sg:province":"Nordrhein-Westfalen",
    "wof:name":"H. Bially Fussbodenhandlung U. Verleger",
    "wof:placetype":"venue"
},
  "geometry": {"coordinates":[6.2055439949,50.9228973389],"type":"Point"}
}