{
  "type": "Feature",
  "properties": {
    "iso:country":"DE",
    "sg:address":"Limonenstr. 9a",
    "sg:city":"Berlin",
    "sg:phone":"+49 30/8313333",
    "sg:postcode":"12203",
    "sg:province":"Berlin",
    "wof:name":"I. Hummel-liljegren \u00dcbersetzerin",
    "wof:placetype":"venue"
},
  "geometry": {"coordinates":[13.300749,52.452175],"type":"Point"}
}