{
  "type": "Feature",
  "properties": {
    "iso:country":"DE",
    "sg:address":"Wei\u00dfgerberstr. 5",
    "sg:city":"M\u00fchldorf",
    "sg:phone":"+49 8631/8116",
    "sg:postcode":"84453",
    "sg:province":"Bayern",
    "wof:name":"Angelika Kammermeier",
    "wof:placetype":"venue"
},
  "geometry": {"coordinates":[12.522482872,48.2433433533],"type":"Point"}
}