{
  "type": "Feature",
  "properties": {
    "iso:country":"DE",
    "sg:address":"Mittenheimer Str. 23",
    "sg:city":"Eching",
    "sg:phone":"+49 89/3271440",
    "sg:postcode":"85386",
    "sg:province":"Bayern",
    "wof:name":"J. U. D. Schilcher Gmbh & Co. Betriebs Kg",
    "wof:placetype":"venue"
},
  "geometry": {"coordinates":[11.6149635315,48.2948265076],"type":"Point"}
}