{
  "type": "Feature",
  "properties": {
    "iso:country":"DE",
    "sg:address":"Credenstr. 40",
    "sg:city":"Herford",
    "sg:phone":"+49 5221/15595",
    "sg:postcode":"32052",
    "sg:province":"Nordrhein-Westfalen",
    "wof:name":"Pizzeria Vesuvio",
    "wof:placetype":"venue"
},
  "geometry": {"coordinates":[8.6752653122,52.1161499023],"type":"Point"}
}