{
  "type": "Feature",
  "properties": {
    "iso:country":"DE",
    "sg:address":"Am R\u00f6nnebecker Hain 6",
    "sg:city":"Bremen",
    "sg:phone":"+49 421/690560",
    "sg:postcode":"28777",
    "sg:province":"Bremen",
    "wof:name":"Marinetech Edelstahlhandel Gmbh & Co. Kg",
    "wof:placetype":"venue"
},
  "geometry": {"coordinates":[8.552312,53.193443],"type":"Point"}
}