{
  "type": "Feature",
  "properties": {
    "iso:country":"DE",
    "sg:address":"Buchbindergasse 2",
    "sg:city":"Beilngries",
    "sg:phone":"+49 8461/1618",
    "sg:postcode":"92339",
    "sg:province":"Bayern",
    "wof:name":"Altstadt-cafe",
    "wof:placetype":"venue"
},
  "geometry": {"coordinates":[11.472088,49.035816],"type":"Point"}
}