{
  "type": "Feature",
  "properties": {
    "iso:country":"DE",
    "sg:address":"Judithstr. 8",
    "sg:city":"Suhl",
    "sg:postcode":"98527",
    "sg:province":"Th\u00fcringen",
    "wof:name":"Gothaer Versicherungen Stephan He\u00df",
    "wof:placetype":"venue"
},
  "geometry": {"coordinates":[10.6944704056,50.6078491211],"type":"Point"}
}