{
  "type": "Feature",
  "properties": {
    "iso:country":"DE",
    "sg:address":"Motzstr. 34",
    "sg:city":"Berlin",
    "sg:phone":"+49 30/2136453",
    "sg:postcode":"10777",
    "sg:province":"Berlin",
    "wof:name":"Oz\u00fctekin Aksoy",
    "wof:placetype":"venue"
},
  "geometry": {"coordinates":[13.3469314575,52.4975242615],"type":"Point"}
}