{
  "type": "Feature",
  "properties": {
    "iso:country":"DE",
    "sg:address":"Gerolzh\u00f6fer Str.",
    "sg:city":"Grettstadt",
    "sg:phone":"+49 9729/411",
    "sg:postcode":"97508",
    "sg:province":"Bayern",
    "wof:name":"Ezb",
    "wof:placetype":"venue"
},
  "geometry": {"coordinates":[10.30788517,49.9834022522],"type":"Point"}
}