{
  "type": "Feature",
  "properties": {
    "iso:country":"DE",
    "sg:address":"Waldzieststr. 7",
    "sg:city":"Leipzig",
    "sg:phone":"+49 341/2510968",
    "sg:postcode":"04329",
    "sg:province":"Sachsen",
    "wof:name":"Christine Oeffner",
    "wof:placetype":"venue"
},
  "geometry": {"coordinates":[12.4617671967,51.3523712158],"type":"Point"}
}