{
  "type": "Feature",
  "properties": {
    "iso:country":"DE",
    "sg:address":"Marienplatz 11",
    "sg:city":"M\u00fcnchen",
    "sg:phone":"+49 89/23691471",
    "sg:postcode":"80331",
    "sg:province":"Bayern",
    "wof:name":"Schmid Ohg",
    "wof:placetype":"venue"
},
  "geometry": {"coordinates":[11.5765886307,48.1370353699],"type":"Point"}
}