{
  "type": "Feature",
  "properties": {
    "iso:country":"DE",
    "sg:address":"Hafenstr.",
    "sg:city":"Burg",
    "sg:phone":"+49 3921/6819",
    "sg:postcode":"39288",
    "sg:province":"Sachsen-Anhalt",
    "wof:name":"Burger Blumen Und Baumschulen Eg",
    "wof:placetype":"venue"
},
  "geometry": {"coordinates":[11.850582,52.281322],"type":"Point"}
}