{
  "type": "Feature",
  "properties": {
    "iso:country":"DE",
    "sg:address":"Arzbacher Str. 77",
    "sg:city":"Bad Ems",
    "sg:phone":"+49 2603/96060",
    "sg:postcode":"56130",
    "sg:province":"Rheinland-Pfalz",
    "wof:name":"Gerharz Bau Gmbh",
    "wof:placetype":"venue"
},
  "geometry": {"coordinates":[7.7196211815,50.3465538025],"type":"Point"}
}