{
  "type": "Feature",
  "properties": {
    "iso:country":"DE",
    "sg:address":"Markt 15",
    "sg:city":"Straelen",
    "sg:postcode":"47638",
    "sg:province":"Nordrhein-Westfalen",
    "wof:name":"Norwell Trade Im- Und Export Gmbh",
    "wof:placetype":"venue"
},
  "geometry": {"coordinates":[6.2660970688,51.4450912476],"type":"Point"}
}