{
  "type": "Feature",
  "properties": {
    "iso:country":"DE",
    "sg:address":"J\u00e4gerplatz 1",
    "sg:city":"Lingen",
    "sg:phone":"+49 591/9153980",
    "sg:postcode":"49811",
    "sg:province":"Niedersachsen",
    "wof:name":"G. Ehlert",
    "wof:placetype":"venue"
},
  "geometry": {"coordinates":[7.3692097664,52.5291366577],"type":"Point"}
}