{
  "type": "Feature",
  "properties": {
    "iso:country":"DE",
    "sg:address":"Rathausplatz 13",
    "sg:city":"Diedorf",
    "sg:phone":"+49 8238/5025",
    "sg:postcode":"86420",
    "sg:province":"Bayern",
    "wof:name":"B. Storm",
    "wof:placetype":"venue"
},
  "geometry": {"coordinates":[10.785671,48.354919],"type":"Point"}
}