{
  "type": "Feature",
  "properties": {
    "iso:country":"DE",
    "sg:address":"Dutendorfer Str. 5-7",
    "sg:city":"Vestenbergsgreuth",
    "sg:phone":"+49 9163/880",
    "sg:postcode":"91487",
    "sg:province":"Bayern",
    "wof:name":"Martin Bauer Management- Service Gmbh & Co. Kg",
    "wof:placetype":"venue"
},
  "geometry": {"coordinates":[10.6512346268,49.6879920959],"type":"Point"}
}