{
  "type": "Feature",
  "properties": {
    "iso:country":"DE",
    "sg:address":"R\u00f6hrenspring 12",
    "sg:city":"Hagen",
    "sg:phone":"+49 2331/6105850",
    "sg:postcode":"58093",
    "sg:province":"Nordrhein-Westfalen",
    "wof:name":"Gvt - Gesellschaft F\u00fcr Verkehrstechnik Mbh",
    "wof:placetype":"venue"
},
  "geometry": {"coordinates":[7.505481,51.384781],"type":"Point"}
}