{
  "type": "Feature",
  "properties": {
    "iso:country":"DE",
    "sg:address":"Vorstadt 9",
    "sg:city":"Mitterteich",
    "sg:phone":"+49 9633/1241",
    "sg:postcode":"95666",
    "sg:province":"Bayern",
    "wof:name":"Simon Neum\u00fcller",
    "wof:placetype":"venue"
},
  "geometry": {"coordinates":[12.2412233353,49.9500770569],"type":"Point"}
}