{
  "type": "Feature",
  "properties": {
    "iso:country":"DE",
    "sg:address":"Siegener Str. 133",
    "sg:city":"Bad Laasphe",
    "sg:phone":"+49 2754/37490",
    "sg:postcode":"57334",
    "sg:province":"Nordrhein-Westfalen",
    "wof:name":"Hmb-maschinenbau Gmbh",
    "wof:placetype":"venue"
},
  "geometry": {"coordinates":[8.2929754257,50.942150116],"type":"Point"}
}