{
  "type": "Feature",
  "properties": {
    "iso:country":"DE",
    "sg:address":"Fleerstr. 6",
    "sg:city":"Wippingen",
    "sg:phone":"+49 4966/332",
    "sg:postcode":"26892",
    "sg:province":"Niedersachsen",
    "wof:name":"Gerhard Eiken",
    "wof:placetype":"venue"
},
  "geometry": {"coordinates":[7.426601,52.937614],"type":"Point"}
}