{
  "type": "Feature",
  "properties": {
    "iso:country":"DE",
    "sg:address":"Marco-Polo-Str.",
    "sg:city":"Satteldorf",
    "sg:phone":"+49 7951/955217",
    "sg:postcode":"74589",
    "sg:province":"Baden-W\u00fcrttemberg",
    "wof:name":"Mc Donalds",
    "wof:placetype":"venue"
},
  "geometry": {"coordinates":[10.0687732697,49.1817016602],"type":"Point"}
}