{
  "type": "Feature",
  "properties": {
    "iso:country":"DE",
    "sg:address":"Auf dem Oberen Auel 7",
    "sg:city":"K\u00f6nigswinter",
    "sg:postcode":"53639",
    "sg:province":"Nordrhein-Westfalen",
    "wof:name":"Marc Westerhorstmann Beteiligungen Gmbh",
    "wof:placetype":"venue"
},
  "geometry": {"coordinates":[7.26662,50.703968],"type":"Point"}
}