{
  "type": "Feature",
  "properties": {
    "iso:country":"DE",
    "sg:address":"John-Schehr-Str. 6",
    "sg:city":"Riesa",
    "sg:phone":"+49 3525/741411",
    "sg:postcode":"01587",
    "sg:province":"Sachsen",
    "wof:name":"Habetreu & Partner M B H",
    "wof:placetype":"venue"
},
  "geometry": {"coordinates":[13.3032588959,51.3046569824],"type":"Point"}
}