{
  "type": "Feature",
  "properties": {
    "iso:country":"DE",
    "sg:address":"Upp'n Barg 1",
    "sg:city":"Ottersberg",
    "sg:phone":"+49 4205/319011",
    "sg:postcode":"28870",
    "sg:province":"Niedersachsen",
    "wof:name":"Holtmeyer & Sohn Gmbh",
    "wof:placetype":"venue"
},
  "geometry": {"coordinates":[9.169380188,53.1004104614],"type":"Point"}
}