{
  "type": "Feature",
  "properties": {
    "iso:country":"DE",
    "sg:address":"Dorfstr. 37",
    "sg:city":"Ruschberg",
    "sg:phone":"+49 6783/1460",
    "sg:postcode":"55776",
    "sg:province":"Rheinland-Pfalz",
    "wof:name":"O. Kunz",
    "wof:placetype":"venue"
},
  "geometry": {"coordinates":[7.288577,49.61718],"type":"Point"}
}