{
  "type": "Feature",
  "properties": {
    "iso:country":"DE",
    "sg:address":"Wurster Landstr. 52",
    "sg:city":"Langen",
    "sg:phone":"+49 471/84774",
    "sg:postcode":"27607",
    "sg:province":"Niedersachsen",
    "wof:name":"E. Brandt",
    "wof:placetype":"venue"
},
  "geometry": {"coordinates":[8.5381526947,53.6115608215],"type":"Point"}
}