{
  "type": "Feature",
  "properties": {
    "iso:country":"DE",
    "sg:address":"Christian-Blank-Str. 3",
    "sg:city":"Duderstadt",
    "sg:phone":"+49 5527/981919",
    "sg:postcode":"37115",
    "sg:province":"Niedersachsen",
    "wof:name":"Mecke Druck U. Verlag",
    "wof:placetype":"venue"
},
  "geometry": {"coordinates":[10.2567892075,51.5146408081],"type":"Point"}
}