{
  "type": "Feature",
  "properties": {
    "iso:country":"DE",
    "sg:address":"B\u00e4ckerstr. 13",
    "sg:city":"Donauw\u00f6rth",
    "sg:phone":"+49 906/3356",
    "sg:postcode":"86609",
    "sg:province":"Bayern",
    "wof:name":"E. Hodapp",
    "wof:placetype":"venue"
},
  "geometry": {"coordinates":[10.7772245407,48.7205657959],"type":"Point"}
}