{
  "type": "Feature",
  "properties": {
    "iso:country":"DE",
    "sg:address":"Zeppelinstr. 1",
    "sg:city":"Weyhe",
    "sg:phone":"+49 421/8495620",
    "sg:postcode":"28844",
    "sg:province":"Niedersachsen",
    "wof:name":"Reiner Seefried Gmbh",
    "wof:placetype":"venue"
},
  "geometry": {"coordinates":[8.867083,53.020683],"type":"Point"}
}