{
  "type": "Feature",
  "properties": {
    "iso:country":"DE",
    "sg:address":"K\u00f6nigsfelder Weg 4",
    "sg:city":"Hollfeld",
    "sg:phone":"+49 9274/80251",
    "sg:postcode":"96142",
    "sg:province":"Bayern",
    "wof:name":"Renates Heimtierbedarf",
    "wof:placetype":"venue"
},
  "geometry": {"coordinates":[11.284316,49.936096],"type":"Point"}
}