{
  "type": "Feature",
  "properties": {
    "iso:country":"DE",
    "sg:address":"Michlbauerstr. 12",
    "sg:city":"Neuried",
    "sg:phone":"+49 89/7554915",
    "sg:postcode":"82061",
    "sg:province":"Bayern",
    "wof:name":"Fritz Schmid",
    "wof:placetype":"venue"
},
  "geometry": {"coordinates":[11.46901,48.095394],"type":"Point"}
}