{
  "type": "Feature",
  "properties": {
    "iso:country":"DE",
    "sg:address":"Wendelinsweg 6",
    "sg:city":"Offingen",
    "sg:phone":"+49 8224/1855",
    "sg:postcode":"89362",
    "sg:province":"Bayern",
    "wof:name":"S .eberle",
    "wof:placetype":"venue"
},
  "geometry": {"coordinates":[10.3730964661,48.4799194336],"type":"Point"}
}