{
  "type": "Feature",
  "properties": {
    "iso:country":"DE",
    "sg:address":"Kaiser-Wilhelm-Str. 117",
    "sg:city":"Berlin",
    "sg:phone":"+49 30/7741606",
    "sg:postcode":"12247",
    "sg:province":"Berlin",
    "wof:name":"Videoscope",
    "wof:placetype":"venue"
},
  "geometry": {"coordinates":[13.351348877,52.4397354126],"type":"Point"}
}