{
  "type": "Feature",
  "properties": {
    "iso:country":"DE",
    "sg:address":"Friedrich-Ebert-Str. 70",
    "sg:city":"Strausberg",
    "sg:phone":"+49 3341/22669",
    "sg:postcode":"15344",
    "sg:province":"Brandenburg",
    "wof:name":"Dr. Med. J\u00fcrgen Ladisch",
    "wof:placetype":"venue"
},
  "geometry": {"coordinates":[13.873956,52.563805],"type":"Point"}
}