{
  "type": "Feature",
  "properties": {
    "iso:country":"DE",
    "sg:address":"Gnaileser Str. 57",
    "sg:city":"R\u00f6dental",
    "sg:phone":"+49 9563/8246",
    "sg:postcode":"96472",
    "sg:province":"Bayern",
    "wof:name":"Klaus-peter Wiedemann",
    "wof:placetype":"venue"
},
  "geometry": {"coordinates":[11.0381145477,50.2991676331],"type":"Point"}
}