{
  "type": "Feature",
  "properties": {
    "iso:country":"DE",
    "sg:address":"R\u00f6merstr. 17",
    "sg:city":"Winnenden",
    "sg:phone":"+49 7195/2313",
    "sg:postcode":"71364",
    "sg:province":"Baden-W\u00fcrttemberg",
    "wof:name":"Gotthilf Bauder & Co. Inh. Herbert Bauder",
    "wof:placetype":"venue"
},
  "geometry": {"coordinates":[9.420975,48.8871],"type":"Point"}
}