{
  "type": "Feature",
  "properties": {
    "iso:country":"DE",
    "sg:address":"Meerbuscher Str. 273",
    "sg:city":"Meerbusch",
    "sg:phone":"+49 2159/2001",
    "sg:postcode":"40670",
    "sg:province":"Nordrhein-Westfalen",
    "wof:name":"Friedhelm Friederici Ingenieur Und Architekt",
    "wof:placetype":"venue"
},
  "geometry": {"coordinates":[6.648273,51.267357],"type":"Point"}
}