{
  "type": "Feature",
  "properties": {
    "iso:country":"DE",
    "sg:address":"Wei\u00dfenfelser Str. 18",
    "sg:city":"Gr\u00f6bitz",
    "sg:phone":"+49 34445/20556",
    "sg:postcode":"06667",
    "sg:province":"Sachsen-Anhalt",
    "wof:name":"Hans-dieter Ploch",
    "wof:placetype":"venue"
},
  "geometry": {"coordinates":[11.9260873795,51.1313819885],"type":"Point"}
}