{
  "type": "Feature",
  "properties": {
    "iso:country":"DE",
    "sg:address":"Stettiner Str. 4",
    "sg:city":"Bad K\u00f6nig",
    "sg:postcode":"64732",
    "sg:province":"Hessen",
    "wof:name":"Etg-elektronik Gmbh",
    "wof:placetype":"venue"
},
  "geometry": {"coordinates":[9.004785,49.748333],"type":"Point"}
}