{
  "type": "Feature",
  "properties": {
    "iso:country":"DE",
    "sg:address":"Schaezlerstr. 10",
    "sg:city":"Augsburg",
    "sg:phone":"+49 821/38108",
    "sg:postcode":"86150",
    "sg:province":"Bayern",
    "wof:name":"Dr. Peter Kotz Rechtsanwalt",
    "wof:placetype":"venue"
},
  "geometry": {"coordinates":[10.8924808502,48.367729187],"type":"Point"}
}