{
  "type": "Feature",
  "properties": {
    "iso:country":"DE",
    "sg:address":"Jetzendorfer Str. 11",
    "sg:city":"Weichs",
    "sg:phone":"+49 8136/7051",
    "sg:postcode":"85258",
    "sg:province":"Bayern",
    "wof:name":"Jakob Schenkel",
    "wof:placetype":"venue"
},
  "geometry": {"coordinates":[11.395975,48.402962],"type":"Point"}
}