{
  "type": "Feature",
  "properties": {
    "iso:country":"DE",
    "sg:address":"Basler G\u00e4ssle 4",
    "sg:city":"Heitersheim",
    "sg:postcode":"79423",
    "sg:province":"Baden-W\u00fcrttemberg",
    "wof:name":"Fin-holding Gmbh",
    "wof:placetype":"venue"
},
  "geometry": {"coordinates":[7.6578278542,47.8722190857],"type":"Point"}
}