{
  "type": "Feature",
  "properties": {
    "iso:country":"DE",
    "sg:address":"Mappacher Str. 14a",
    "sg:city":"Efringen-Kirchen",
    "sg:phone":"+49 7628/8654",
    "sg:postcode":"79588",
    "sg:province":"Baden-W\u00fcrttemberg",
    "wof:name":"Plus Hochbau Gmbh",
    "wof:placetype":"venue"
},
  "geometry": {"coordinates":[7.6299219131,47.6750335693],"type":"Point"}
}