{
  "type": "Feature",
  "properties": {
    "iso:country":"DE",
    "sg:address":"Elbestr. 12",
    "sg:city":"Frankfurt",
    "sg:phone":"+49 69/231897",
    "sg:postcode":"60329",
    "sg:province":"Hessen",
    "wof:name":"Merkez",
    "wof:placetype":"venue"
},
  "geometry": {"coordinates":[8.669453,50.107365],"type":"Point"}
}