{
  "type": "Feature",
  "properties": {
    "iso:country":"DE",
    "sg:address":"Schluchenhausstr. 17a",
    "sg:city":"Neuss",
    "sg:phone":"+49 2137/70870",
    "sg:postcode":"41469",
    "sg:province":"Nordrhein-Westfalen",
    "wof:name":"Georg Wallraff Lifttechnik & Design E. Kfm.",
    "wof:placetype":"venue"
},
  "geometry": {"coordinates":[6.6980428696,51.1480369568],"type":"Point"}
}