{
  "type": "Feature",
  "properties": {
    "iso:country":"DE",
    "sg:address":"Narzissenweg 3",
    "sg:city":"Renchen",
    "sg:phone":"+49 7843/7144",
    "sg:postcode":"77871",
    "sg:province":"Baden-W\u00fcrttemberg",
    "wof:name":"H. Bartkowiak",
    "wof:placetype":"venue"
},
  "geometry": {"coordinates":[8.0140218735,48.591255188],"type":"Point"}
}