{
  "type": "Feature",
  "properties": {
    "iso:country":"DE",
    "sg:address":"Schlo\u00dfplatz 7",
    "sg:city":"Celle",
    "sg:postcode":"29221",
    "sg:province":"Niedersachsen",
    "wof:name":"Eberhard-schlotter-stiftung",
    "wof:placetype":"venue"
},
  "geometry": {"coordinates":[10.0794219971,52.6238861084],"type":"Point"}
}