{
  "type": "Feature",
  "properties": {
    "iso:country":"DE",
    "sg:address":"Dorotheenplatz 2-4",
    "sg:city":"Leipzig",
    "sg:postcode":"04109",
    "sg:province":"Sachsen",
    "wof:name":"Sal Airlines Gmbh",
    "wof:placetype":"venue"
},
  "geometry": {"coordinates":[12.3684778214,51.3383331299],"type":"Point"}
}