{
  "type": "Feature",
  "properties": {
    "iso:country":"DE",
    "sg:address":"An der M\u00fchlenau 1",
    "sg:city":"Timmendorfer Strand",
    "sg:phone":"+49 4503/2523",
    "sg:postcode":"23669",
    "sg:province":"Schleswig-Holstein",
    "wof:name":"Klaus Str\u00fcmpell",
    "wof:placetype":"venue"
},
  "geometry": {"coordinates":[10.761498,53.993931],"type":"Point"}
}