{
  "type": "Feature",
  "properties": {
    "iso:country":"DE",
    "sg:address":"Heimkehrerweg 26 a",
    "sg:city":"M\u00fcnster",
    "sg:phone":"+49 251/784839",
    "sg:postcode":"48153",
    "sg:province":"Nordrhein-Westfalen",
    "wof:name":"Erich Friedrichs",
    "wof:placetype":"venue"
},
  "geometry": {"coordinates":[7.614388,51.927177],"type":"Point"}
}