{
  "type": "Feature",
  "properties": {
    "iso:country":"DE",
    "sg:address":"Bahnhofstr.",
    "sg:city":"Hainspitz",
    "sg:phone":"+49 36691/54169",
    "sg:postcode":"07607",
    "sg:province":"Th\u00fcringen",
    "wof:name":"Hermann Kost Gmbh",
    "wof:placetype":"venue"
},
  "geometry": {"coordinates":[11.833998,50.964176],"type":"Point"}
}