{
  "type": "Feature",
  "properties": {
    "iso:country":"DE",
    "sg:address":"Blumenfeldstr. 163",
    "sg:city":"Bochum",
    "sg:phone":"+49 2327/97000",
    "sg:postcode":"44869",
    "sg:province":"Nordrhein-Westfalen",
    "wof:name":"Tgp Technische Geb\u00e4ude Planung Gmbh",
    "wof:placetype":"venue"
},
  "geometry": {"coordinates":[7.171428,51.444775],"type":"Point"}
}