{
  "type": "Feature",
  "properties": {
    "iso:country":"DE",
    "sg:address":"Singener Str. 5",
    "sg:city":"Radolfzell",
    "sg:phone":"+49 7732/55290",
    "sg:postcode":"78315",
    "sg:province":"Baden-W\u00fcrttemberg",
    "wof:name":"Hotel Sternen",
    "wof:placetype":"venue"
},
  "geometry": {"coordinates":[8.9336528778,47.7526245117],"type":"Point"}
}