{
  "type": "Feature",
  "properties": {
    "iso:country":"DE",
    "sg:address":"G\u00e4rtnerstr. 32",
    "sg:city":"Hamburg",
    "sg:phone":"+49 40/4225502",
    "sg:postcode":"20253",
    "sg:province":"Hamburg",
    "wof:name":"Wrangel Apotheke Heinrich Rackwitz",
    "wof:placetype":"venue"
},
  "geometry": {"coordinates":[9.967097,53.583027],"type":"Point"}
}