{
  "type": "Feature",
  "properties": {
    "iso:country":"DE",
    "sg:address":"Kampweg 16",
    "sg:city":"Immenhausen",
    "sg:phone":"+49 5673/925350",
    "sg:postcode":"34376",
    "sg:province":"Hessen",
    "wof:name":"Anita Mutke Versandgesch\u00e4ft",
    "wof:placetype":"venue"
},
  "geometry": {"coordinates":[9.4775371552,51.4296112061],"type":"Point"}
}