{
  "type": "Feature",
  "properties": {
    "iso:country":"DE",
    "sg:address":"Rajenstr. 88",
    "sg:city":"Westoverledingen",
    "sg:phone":"+49 4955/7771",
    "sg:postcode":"26810",
    "sg:province":"Niedersachsen",
    "wof:name":"Anita Kesting Heilpraktikerin",
    "wof:placetype":"venue"
},
  "geometry": {"coordinates":[7.4991159439,53.1296653748],"type":"Point"}
}