{
  "type": "Feature",
  "properties": {
    "iso:country":"DE",
    "sg:address":"Friedrich-Ludwig-Jahn-Platz 9",
    "sg:city":"Landshut",
    "sg:phone":"+49 871/43101",
    "sg:postcode":"84036",
    "sg:province":"Bayern",
    "wof:name":"Eva Brennd\u00f6rfer",
    "wof:placetype":"venue"
},
  "geometry": {"coordinates":[12.1515035629,48.5174865723],"type":"Point"}
}