{
  "type": "Feature",
  "properties": {
    "iso:country":"DE",
    "sg:address":"Rheinstr. 200",
    "sg:city":"Wesseling",
    "sg:postcode":"50389",
    "sg:province":"Nordrhein-Westfalen",
    "wof:name":"Kath. \u00d6ffentliche Bibliothek St. Thomas Apostel",
    "wof:placetype":"venue"
},
  "geometry": {"coordinates":[7.026212,50.806816],"type":"Point"}
}