{
  "type": "Feature",
  "properties": {
    "iso:country":"DE",
    "sg:address":"Landenberger Str. 61",
    "sg:city":"Schramberg",
    "sg:phone":"+49 7422/7741",
    "sg:postcode":"78713",
    "sg:province":"Baden-W\u00fcrttemberg",
    "wof:name":"Deutsche Jugendkraft Schramberg",
    "wof:placetype":"venue"
},
  "geometry": {"coordinates":[8.380437851,48.2345848083],"type":"Point"}
}