{
  "type": "Feature",
  "properties": {
    "iso:country":"DE",
    "sg:address":"Bernadottestr. 9",
    "sg:city":"Ansbach",
    "sg:postcode":"91522",
    "sg:province":"Bayern",
    "wof:name":"Zelkom-but Gmbh",
    "wof:placetype":"venue"
},
  "geometry": {"coordinates":[10.5788803101,49.3142051697],"type":"Point"}
}