{
  "type": "Feature",
  "properties": {
    "iso:country":"DE",
    "sg:address":"Maienstr. 1a",
    "sg:city":"Berlin",
    "sg:postcode":"10787",
    "sg:province":"Berlin",
    "wof:name":"Storting Gmbh",
    "wof:placetype":"venue"
},
  "geometry": {"coordinates":[13.3530101776,52.5010375977],"type":"Point"}
}