{
  "type": "Feature",
  "properties": {
    "iso:country":"DE",
    "sg:address":"Reustadt 11/1",
    "sg:city":"Hattenhofen",
    "sg:phone":"+49 7164/4143",
    "sg:postcode":"73110",
    "sg:province":"Baden-W\u00fcrttemberg",
    "wof:name":"Christian Siller Gmbh",
    "wof:placetype":"venue"
},
  "geometry": {"coordinates":[9.5798339844,48.66822052],"type":"Point"}
}