{
  "type": "Feature",
  "properties": {
    "iso:country":"DE",
    "sg:address":"Hauptstr. 112",
    "sg:city":"Gommersheim",
    "sg:phone":"+49 6327/2902",
    "sg:postcode":"67377",
    "sg:province":"Rheinland-Pfalz",
    "wof:name":"Manfred B\u00f6hm",
    "wof:placetype":"venue"
},
  "geometry": {"coordinates":[8.275493,49.291473],"type":"Point"}
}