{
  "type": "Feature",
  "properties": {
    "iso:country":"DE",
    "sg:address":"Mittelweg 35",
    "sg:city":"Blumberg",
    "sg:postcode":"16356",
    "sg:province":"Brandenburg",
    "wof:name":"H\u00f6hne & H\u00f6hne Gmbh",
    "wof:placetype":"venue"
},
  "geometry": {"coordinates":[13.617204,52.603947],"type":"Point"}
}