{
  "type": "Feature",
  "properties": {
    "iso:country":"DE",
    "sg:address":"Markgrafenstr. 21",
    "sg:city":"Essen",
    "sg:phone":"+49 201/285865",
    "sg:postcode":"45138",
    "sg:province":"Nordrhein-Westfalen",
    "wof:name":"Hans He\u00dfbr\u00fcgge",
    "wof:placetype":"venue"
},
  "geometry": {"coordinates":[7.031863,51.452164],"type":"Point"}
}