{
  "type": "Feature",
  "properties": {
    "iso:country":"DE",
    "sg:address":"Hauptstr. 31",
    "sg:city":"Merching",
    "sg:phone":"+49 8233/92348",
    "sg:postcode":"86504",
    "sg:province":"Bayern",
    "wof:name":"H. Teifelhart",
    "wof:placetype":"venue"
},
  "geometry": {"coordinates":[10.988312,48.248398],"type":"Point"}
}