{
  "type": "Feature",
  "properties": {
    "iso:country":"DE",
    "sg:address":"Glenn-Miller-Str. 3",
    "sg:city":"Fulda",
    "sg:phone":"+49 661/928290",
    "sg:postcode":"36041",
    "sg:province":"Hessen",
    "wof:name":"Inform Design Wilhelm & Ziegler Gmbh",
    "wof:placetype":"venue"
},
  "geometry": {"coordinates":[9.6402750015,50.5523796082],"type":"Point"}
}