{
  "type": "Feature",
  "properties": {
    "iso:country":"DE",
    "sg:address":"Am Seitenkanal 8",
    "sg:city":"Lingen",
    "sg:phone":"+49 8104/62950",
    "sg:postcode":"49811",
    "sg:province":"Niedersachsen",
    "wof:name":"Symec System Mechanik Gmbh",
    "wof:placetype":"venue"
},
  "geometry": {"coordinates":[11.707246,47.986366],"type":"Point"}
}