{
  "type": "Feature",
  "properties": {
    "iso:country":"DE",
    "sg:address":"Am Adelsheimer Hof 2",
    "sg:city":"Nassau",
    "sg:phone":"+49 2604/5580",
    "sg:postcode":"56377",
    "sg:province":"Rheinland-Pfalz",
    "wof:name":"J\u00fcrgen Fornoff Masseur",
    "wof:placetype":"venue"
},
  "geometry": {"coordinates":[7.797525,50.31411],"type":"Point"}
}