{
  "type": "Feature",
  "properties": {
    "iso:country":"DE",
    "sg:address":"Friedrich-von-Schiller-Str. 1",
    "sg:city":"Bayreuth",
    "sg:phone":"+49 921/83355",
    "sg:postcode":"95444",
    "sg:province":"Bayern",
    "wof:name":"Andrea Schmeisser Krankengymnastin",
    "wof:placetype":"venue"
},
  "geometry": {"coordinates":[11.578418,49.949337],"type":"Point"}
}