{
  "type": "Feature",
  "properties": {
    "iso:country":"DE",
    "sg:address":"Hauptstr. 177",
    "sg:city":"Heiligenhaus",
    "sg:phone":"+49 2056/6513",
    "sg:postcode":"42579",
    "sg:province":"Nordrhein-Westfalen",
    "wof:name":"Gastst\u00e4tte Z\u00fcrich",
    "wof:placetype":"venue"
},
  "geometry": {"coordinates":[6.969438,51.326244],"type":"Point"}
}