{
  "type": "Feature",
  "properties": {
    "iso:country":"DE",
    "sg:address":"Hauptstr. 28",
    "sg:city":"H\u00f6chberg",
    "sg:phone":"+49 931/49204",
    "sg:postcode":"97204",
    "sg:province":"Bayern",
    "wof:name":"C. Kittler Wettannahme",
    "wof:placetype":"venue"
},
  "geometry": {"coordinates":[9.880169,49.783958],"type":"Point"}
}