{
  "type": "Feature",
  "properties": {
    "iso:country":"DE",
    "sg:address":"Van-Delden-Str. 8",
    "sg:city":"Ahaus",
    "sg:phone":"+49 4972/274417",
    "sg:postcode":"48683",
    "sg:province":"Nordrhein-Westfalen",
    "wof:name":"Naber & Rogge Gmbh",
    "wof:placetype":"venue"
},
  "geometry": {"coordinates":[8.0521383286,48.7661628723],"type":"Point"}
}