{
  "type": "Feature",
  "properties": {
    "iso:country":"DE",
    "sg:address":"Drususallee 22",
    "sg:city":"Neuss",
    "sg:phone":"+49 2131/277812",
    "sg:postcode":"41460",
    "sg:province":"Nordrhein-Westfalen",
    "wof:name":"Piotr Dziamski \u00dcbersetzer",
    "wof:placetype":"venue"
},
  "geometry": {"coordinates":[6.687189,51.197319],"type":"Point"}
}