{
  "type": "Feature",
  "properties": {
    "iso:country":"DE",
    "sg:address":"Wallensteinstr. 33",
    "sg:city":"Erlangen",
    "sg:phone":"+49 9131/990670",
    "sg:postcode":"91056",
    "sg:province":"Bayern",
    "wof:name":"Heinrich Mihlan",
    "wof:placetype":"venue"
},
  "geometry": {"coordinates":[10.953785,49.558475],"type":"Point"}
}