{
  "type": "Feature",
  "properties": {
    "iso:country":"DE",
    "sg:address":"Schwalbacher Str. 91",
    "sg:city":"Wiesbaden",
    "sg:phone":"+49 611/599699",
    "sg:postcode":"65183",
    "sg:province":"Hessen",
    "wof:name":"Gutberlet",
    "wof:placetype":"venue"
},
  "geometry": {"coordinates":[8.235964,50.085991],"type":"Point"}
}