{
  "type": "Feature",
  "properties": {
    "iso:country":"DE",
    "sg:address":"Oststr. 128a",
    "sg:city":"Leipzig",
    "sg:phone":"+49 341/8617532",
    "sg:postcode":"04299",
    "sg:province":"Sachsen",
    "wof:name":"Gartenanlage Flora",
    "wof:placetype":"venue"
},
  "geometry": {"coordinates":[12.4195537567,51.3260154724],"type":"Point"}
}