{
  "type": "Feature",
  "properties": {
    "iso:country":"DE",
    "sg:address":"Paulsdammer Weg 2",
    "sg:city":"Schwerin",
    "sg:phone":"+49 385/561554",
    "sg:postcode":"19055",
    "sg:province":"Mecklenburg-Vorpommern",
    "wof:name":"Seewarte Gmbh",
    "wof:placetype":"venue"
},
  "geometry": {"coordinates":[11.42948246,53.6801605225],"type":"Point"}
}