{
  "type": "Feature",
  "properties": {
    "iso:country":"DE",
    "sg:address":"Hauptstr. 114",
    "sg:city":"Ostrhauderfehn",
    "sg:phone":"+49 4952/942033",
    "sg:postcode":"26842",
    "sg:province":"Niedersachsen",
    "wof:name":"Fleischerei Bernd Johannes Funk Gmbh",
    "wof:placetype":"venue"
},
  "geometry": {"coordinates":[7.6204481125,53.1403770447],"type":"Point"}
}