{
  "type": "Feature",
  "properties": {
    "iso:country":"DE",
    "sg:address":"Gewerbestr. 4",
    "sg:city":"Werdohl",
    "sg:phone":"+49 4923/921644",
    "sg:postcode":"58791",
    "sg:province":"Nordrhein-Westfalen",
    "wof:name":"Ricken - Spaltband Gmbh & Co. Kg",
    "wof:placetype":"venue"
},
  "geometry": {"coordinates":[7.809237,51.257561],"type":"Point"}
}