{
  "type": "Feature",
  "properties": {
    "iso:country":"DE",
    "sg:address":"Dornierstr. 5",
    "sg:city":"K\u00f6nigsbrunn",
    "sg:phone":"+49 8231/6979",
    "sg:postcode":"86343",
    "sg:province":"Bayern",
    "wof:name":"Ristorante Pizzeria Da Mario",
    "wof:placetype":"venue"
},
  "geometry": {"coordinates":[10.8730010986,48.2548713684],"type":"Point"}
}