{
  "type": "Feature",
  "properties": {
    "iso:country":"DE",
    "sg:address":"Wilhelm-Leuschner-Str. 2",
    "sg:city":"Gro\u00df-Zimmern",
    "sg:phone":"+49 6071/41613",
    "sg:postcode":"64846",
    "sg:province":"Hessen",
    "wof:name":"Reinhold Poth",
    "wof:placetype":"venue"
},
  "geometry": {"coordinates":[8.8306179047,49.8744430542],"type":"Point"}
}