{
  "type": "Feature",
  "properties": {
    "iso:country":"DE",
    "sg:address":"Rinnebachstr. 2",
    "sg:city":"H\u00fcrtgenwald",
    "sg:postcode":"52393",
    "sg:province":"Nordrhein-Westfalen",
    "wof:name":"\u00d6ffentliche B\u00fccherei Hauptschule Kleinhau",
    "wof:placetype":"venue"
},
  "geometry": {"coordinates":[6.393721,50.721672],"type":"Point"}
}