{
  "type": "Feature",
  "properties": {
    "iso:country":"DE",
    "sg:address":"Niederhofener Str. 14",
    "sg:city":"Dortmund",
    "sg:phone":"+49 231/437076",
    "sg:postcode":"44263",
    "sg:province":"Nordrhein-Westfalen",
    "wof:name":"Ch. D. Henn",
    "wof:placetype":"venue"
},
  "geometry": {"coordinates":[7.499,51.483379],"type":"Point"}
}