{
  "type": "Feature",
  "properties": {
    "iso:country":"DE",
    "sg:address":"Badstr. 1",
    "sg:city":"Frauenau",
    "sg:phone":"+49 9926/223",
    "sg:postcode":"94258",
    "sg:province":"Bayern",
    "wof:name":"Hugo Wei\u00df",
    "wof:placetype":"venue"
},
  "geometry": {"coordinates":[13.3025350571,48.9922409058],"type":"Point"}
}