{
  "type": "Feature",
  "properties": {
    "iso:country":"DE",
    "sg:address":"Fritz-Erler-Str. 5",
    "sg:city":"Worms",
    "sg:phone":"+49 6247/7719",
    "sg:postcode":"67551",
    "sg:province":"Rheinland-Pfalz",
    "wof:name":"Harald Herr",
    "wof:placetype":"venue"
},
  "geometry": {"coordinates":[8.2673921585,49.6328735352],"type":"Point"}
}