{
  "type": "Feature",
  "properties": {
    "iso:country":"DE",
    "sg:address":"Wilhelm-K\u00fclz-Str. 9",
    "sg:city":"Halberstadt",
    "sg:phone":"+49 3941/68080",
    "sg:postcode":"38820",
    "sg:province":"Sachsen-Anhalt",
    "wof:name":"Hws Steuerberatungsgesellsch. Halberstadt Mbh",
    "wof:placetype":"venue"
},
  "geometry": {"coordinates":[11.0454950333,51.8931045532],"type":"Point"}
}