{
  "type": "Feature",
  "properties": {
    "iso:country":"DE",
    "sg:address":"Hindenburgstr. 88",
    "sg:city":"L\u00fcneburg",
    "sg:phone":"+49 4131/33011",
    "sg:postcode":"21339",
    "sg:province":"Niedersachsen",
    "wof:name":"Peter Herda Steuerberater",
    "wof:placetype":"venue"
},
  "geometry": {"coordinates":[10.3996734619,53.2526779175],"type":"Point"}
}