{
  "type": "Feature",
  "properties": {
    "iso:country":"DE",
    "sg:address":"Georgenstr. 15",
    "sg:city":"M\u00fcnchen",
    "sg:phone":"+49 89/347411",
    "sg:postcode":"80799",
    "sg:province":"Bayern",
    "wof:name":"H. Fritz-denneville",
    "wof:placetype":"venue"
},
  "geometry": {"coordinates":[11.580162,48.154427],"type":"Point"}
}