{
  "type": "Feature",
  "properties": {
    "iso:country":"DE",
    "sg:address":"Wilhelmsh\u00f6her Str. 5",
    "sg:city":"Baunatal",
    "sg:phone":"+49 561/94880",
    "sg:postcode":"34225",
    "sg:province":"Hessen",
    "wof:name":"Hotel Stadt Baunatal Inh. Lutz Und Monika Kirbach",
    "wof:placetype":"venue"
},
  "geometry": {"coordinates":[9.3989267349,51.2611923218],"type":"Point"}
}