{
  "type": "Feature",
  "properties": {
    "iso:country":"DE",
    "sg:address":"W\u00fcrzburger Str. 81",
    "sg:city":"Dresden",
    "sg:phone":"+49 351/4727511",
    "sg:postcode":"01187",
    "sg:province":"Sachsen",
    "wof:name":"Ronald Walter",
    "wof:placetype":"venue"
},
  "geometry": {"coordinates":[13.7189979553,51.0287017822],"type":"Point"}
}