{
  "type": "Feature",
  "properties": {
    "iso:country":"DE",
    "sg:address":"Heidesheimer Str. 16",
    "sg:city":"Budenheim",
    "sg:phone":"+49 6139/1027",
    "sg:postcode":"55257",
    "sg:province":"Rheinland-Pfalz",
    "wof:name":"Jung Malermeisterberieb",
    "wof:placetype":"venue"
},
  "geometry": {"coordinates":[8.152214,50.016785],"type":"Point"}
}