{
  "type": "Feature",
  "properties": {
    "iso:country":"DE",
    "sg:address":"Am Silberhalter 10",
    "sg:city":"Bergneustadt",
    "sg:phone":"+49 2261/42482",
    "sg:postcode":"51702",
    "sg:province":"Nordrhein-Westfalen",
    "wof:name":"L. Sobar",
    "wof:placetype":"venue"
},
  "geometry": {"coordinates":[7.656038,51.008625],"type":"Point"}
}