{
  "type": "Feature",
  "properties": {
    "iso:country":"DE",
    "sg:address":"Kressenstein 15",
    "sg:city":"Kulmbach",
    "sg:phone":"+49 9221/2098",
    "sg:postcode":"95326",
    "sg:province":"Bayern",
    "wof:name":"Bayerische Vereinsbank Ag",
    "wof:placetype":"venue"
},
  "geometry": {"coordinates":[11.453218,50.107513],"type":"Point"}
}