{
  "type": "Feature",
  "properties": {
    "iso:country":"DE",
    "sg:address":"Bremer Str. 5",
    "sg:city":"K\u00f6ln",
    "sg:phone":"+49 221/121550",
    "sg:postcode":"50670",
    "sg:province":"Nordrhein-Westfalen",
    "wof:name":"Fabian V. Massenbach Auktionshaus-kunsthaus",
    "wof:placetype":"venue"
},
  "geometry": {"coordinates":[6.9475889206,50.948009491],"type":"Point"}
}