{
  "type": "Feature",
  "properties": {
    "iso:country":"DE",
    "sg:address":"Hugo-Junkers-Str. 10",
    "sg:city":"K\u00f6ln",
    "sg:postcode":"50739",
    "sg:province":"Nordrhein-Westfalen",
    "wof:name":"Hans Jeschke Gmbh",
    "wof:placetype":"venue"
},
  "geometry": {"coordinates":[6.9116668701,50.9894104004],"type":"Point"}
}