{
  "type": "Feature",
  "properties": {
    "iso:country":"DE",
    "sg:address":"Sch\u00f6nheider Str. 226",
    "sg:city":"Auerbach",
    "sg:phone":"+49 3744/80918",
    "sg:postcode":"08209",
    "sg:province":"Sachsen",
    "wof:name":"Wolfgang E\u00dfbach B\u00e4ckerei",
    "wof:placetype":"venue"
},
  "geometry": {"coordinates":[12.462214,50.507504],"type":"Point"}
}