{
  "type": "Feature",
  "properties": {
    "iso:country":"DE",
    "sg:address":"Neue-Anlage-Str. 30",
    "sg:city":"Karlsruhe",
    "sg:phone":"+49 721/861631",
    "sg:postcode":"76135",
    "sg:province":"Baden-W\u00fcrttemberg",
    "wof:name":"Horst Reinheimer",
    "wof:placetype":"venue"
},
  "geometry": {"coordinates":[8.3805437088,48.9912948608],"type":"Point"}
}