{
  "type": "Feature",
  "properties": {
    "iso:country":"DE",
    "sg:address":"H\u00f6hscheider Weg 39",
    "sg:city":"Solingen",
    "sg:phone":"+49 212/2641555",
    "sg:postcode":"42699",
    "sg:province":"Nordrhein-Westfalen",
    "wof:name":"Joachim Und Warminski",
    "wof:placetype":"venue"
},
  "geometry": {"coordinates":[7.0280342102,51.1476707458],"type":"Point"}
}