{
  "type": "Feature",
  "properties": {
    "iso:country":"DE",
    "sg:address":"Nahestr. 40",
    "sg:city":"R\u00fcdesheim",
    "sg:phone":"+49 671/28352",
    "sg:postcode":"55593",
    "sg:province":"Rheinland-Pfalz",
    "wof:name":"Vieh- Und Fleischgro\u00dfhandel Beisiegel Gmbh & Co. Kg",
    "wof:placetype":"venue"
},
  "geometry": {"coordinates":[7.8141679764,49.8450279236],"type":"Point"}
}