{
  "type": "Feature",
  "properties": {
    "iso:country":"DE",
    "sg:address":"Im Grund 8-1",
    "sg:city":"Leutenbach",
    "sg:phone":"+49 7195/178791",
    "sg:postcode":"71397",
    "sg:province":"Baden-W\u00fcrttemberg",
    "wof:name":"H. Schlenker",
    "wof:placetype":"venue"
},
  "geometry": {"coordinates":[9.3847007751,48.886592865],"type":"Point"}
}