{
  "type": "Feature",
  "properties": {
    "iso:country":"DE",
    "sg:address":"Niddaer Str. 20",
    "sg:city":"Echzell",
    "sg:phone":"+49 6008/460",
    "sg:postcode":"61209",
    "sg:province":"Hessen",
    "wof:name":"Hans M\u00f6schl",
    "wof:placetype":"venue"
},
  "geometry": {"coordinates":[8.902794838,50.3973007202],"type":"Point"}
}