{
  "type": "Feature",
  "properties": {
    "iso:country":"DE",
    "sg:address":"Marktstr. 29",
    "sg:city":"Giengen",
    "sg:phone":"+49 7322/7206",
    "sg:postcode":"89537",
    "sg:province":"Baden-W\u00fcrttemberg",
    "wof:name":"Schuh Und Sport Jentschke Inh. Andreas Jentschke E. K.",
    "wof:placetype":"venue"
},
  "geometry": {"coordinates":[10.2458076477,48.6206130981],"type":"Point"}
}