{
  "type": "Feature",
  "properties": {
    "iso:country":"DE",
    "sg:address":"Carl-Duisberg-Str. 115",
    "sg:city":"Marl",
    "sg:phone":"+49 2365/21925",
    "sg:postcode":"45772",
    "sg:province":"Nordrhein-Westfalen",
    "wof:name":"Rustika-grill",
    "wof:placetype":"venue"
},
  "geometry": {"coordinates":[7.121951,51.680347],"type":"Point"}
}