{
  "type": "Feature",
  "properties": {
    "iso:country":"DE",
    "sg:address":"Industriestr. 4",
    "sg:city":"Ranstadt",
    "sg:phone":"+49 4957/3492101",
    "sg:postcode":"63691",
    "sg:province":"Hessen",
    "wof:name":"Druck Center Drake Huber Gmbh",
    "wof:placetype":"venue"
},
  "geometry": {"coordinates":[8.7477464676,52.2372665405],"type":"Point"}
}