{
  "type": "Feature",
  "properties": {
    "iso:country":"DE",
    "sg:address":"Frohnauer Str. 7",
    "sg:city":"Geesthacht",
    "sg:phone":"+49 4152/2125",
    "sg:postcode":"21502",
    "sg:province":"Schleswig-Holstein",
    "wof:name":"Hermann Schmidt Gmbh",
    "wof:placetype":"venue"
},
  "geometry": {"coordinates":[10.345106,53.433258],"type":"Point"}
}