{
  "type": "Feature",
  "properties": {
    "iso:country":"DE",
    "sg:address":"Gauaschacher Str.",
    "sg:city":"Hammelburg",
    "sg:postcode":"97762",
    "sg:province":"Bayern",
    "wof:name":"Waldgenossenschaft Gauaschach Eg",
    "wof:placetype":"venue"
},
  "geometry": {"coordinates":[9.930165,50.048058],"type":"Point"}
}