{
  "type": "Feature",
  "properties": {
    "iso:country":"DE",
    "sg:address":"Gartenstr. 42",
    "sg:city":"Briedel",
    "sg:phone":"+49 6542/5462",
    "sg:postcode":"56867",
    "sg:province":"Rheinland-Pfalz",
    "wof:name":"Schutzen-erben-simon-mees Weinanbau",
    "wof:placetype":"venue"
},
  "geometry": {"coordinates":[7.1478409767,50.0282821655],"type":"Point"}
}