{
  "type": "Feature",
  "properties": {
    "iso:country":"DE",
    "sg:address":"Augsburger Str. 5",
    "sg:city":"Gersthofen",
    "sg:phone":"+49 821/493949",
    "sg:postcode":"86368",
    "sg:province":"Bayern",
    "wof:name":"W\u00fcstenrot Bausparkasse",
    "wof:placetype":"venue"
},
  "geometry": {"coordinates":[10.878938,48.423847],"type":"Point"}
}