{
  "type": "Feature",
  "properties": {
    "iso:country":"DE",
    "sg:address":"Artur-Neumann-Str. 2",
    "sg:city":"Olbersdorf",
    "sg:phone":"+49 3583/690171",
    "sg:postcode":"02785",
    "sg:province":"Sachsen",
    "wof:name":"Volksbad",
    "wof:placetype":"venue"
},
  "geometry": {"coordinates":[14.7559356689,50.8682365417],"type":"Point"}
}