{
  "type": "Feature",
  "properties": {
    "iso:country":"DE",
    "sg:address":"Hohnerstr 22",
    "sg:city":"Seitingen-Oberflacht",
    "sg:phone":"+49 7464/96145",
    "sg:postcode":"78606",
    "sg:province":"Baden-W\u00fcrttemberg",
    "wof:name":"Rominger Medizintechnik Gmbh",
    "wof:placetype":"venue"
},
  "geometry": {"coordinates":[8.7293634415,48.0149536133],"type":"Point"}
}