{
  "type": "Feature",
  "properties": {
    "iso:country":"DE",
    "sg:address":"K\u00f6nigsbr\u00fccker Str. 30",
    "sg:city":"Radeburg",
    "sg:postcode":"01471",
    "sg:province":"Sachsen",
    "wof:name":"Agro-zent Gmbh",
    "wof:placetype":"venue"
},
  "geometry": {"coordinates":[13.7254400253,51.2200698853],"type":"Point"}
}