{
  "type": "Feature",
  "properties": {
    "iso:country":"DE",
    "sg:address":"Leinestr. 5",
    "sg:city":"Wingerode",
    "sg:phone":"+49 3605/512572",
    "sg:postcode":"37327",
    "sg:province":"Th\u00fcringen",
    "wof:name":"Aloys Sieck",
    "wof:placetype":"venue"
},
  "geometry": {"coordinates":[10.235856,51.393723],"type":"Point"}
}