{
  "type": "Feature",
  "properties": {
    "iso:country":"DE",
    "sg:address":"Bismarckstr. 10",
    "sg:city":"Brake",
    "sg:phone":"+49 4401/977922",
    "sg:postcode":"26919",
    "sg:province":"Niedersachsen",
    "wof:name":"Gerling-konzern J\u00f6rg Lorenz",
    "wof:placetype":"venue"
},
  "geometry": {"coordinates":[8.4764232635,53.3110961914],"type":"Point"}
}