{
  "type": "Feature",
  "properties": {
    "iso:country":"DE",
    "sg:address":"Hauptstr. 72",
    "sg:city":"Glienicke",
    "sg:phone":"+49 33056/77086",
    "sg:postcode":"16548",
    "sg:province":"Brandenburg",
    "wof:name":"Johann Lindner",
    "wof:placetype":"venue"
},
  "geometry": {"coordinates":[13.3126440048,52.6307296753],"type":"Point"}
}