{
  "type": "Feature",
  "properties": {
    "iso:country":"DE",
    "sg:address":"Harthauser Str. 64",
    "sg:city":"M\u00fcnchen",
    "sg:phone":"+49 89/645246",
    "sg:postcode":"81545",
    "sg:province":"Bayern",
    "wof:name":"Elisabeth Noris Krankegymnastin",
    "wof:placetype":"venue"
},
  "geometry": {"coordinates":[11.547092,48.08234],"type":"Point"}
}