{
  "type": "Feature",
  "properties": {
    "iso:country":"DE",
    "sg:address":"Hermann-Kurz-Weg 3",
    "sg:city":"Esslingen",
    "sg:phone":"+49 711/312410",
    "sg:postcode":"73730",
    "sg:province":"Baden-W\u00fcrttemberg",
    "wof:name":"Hans-dieter Schmidt Architekt",
    "wof:placetype":"venue"
},
  "geometry": {"coordinates":[9.335168,48.728313],"type":"Point"}
}