{
  "type": "Feature",
  "properties": {
    "iso:country":"DE",
    "sg:address":"Heger Str. 27",
    "sg:city":"Osnabr\u00fcck",
    "sg:phone":"+49 541/22446",
    "sg:postcode":"49074",
    "sg:province":"Niedersachsen",
    "wof:name":"Schubert Vehling Planen Gestalten",
    "wof:placetype":"venue"
},
  "geometry": {"coordinates":[8.039699,52.276814],"type":"Point"}
}