{
  "type": "Feature",
  "properties": {
    "iso:country":"DE",
    "sg:address":"Birnbaum 50",
    "sg:city":"Gerhardshofen",
    "sg:phone":"+49 9163/641",
    "sg:postcode":"91466",
    "sg:province":"Bayern",
    "wof:name":"Kuusamet Gmbh",
    "wof:placetype":"venue"
},
  "geometry": {"coordinates":[10.719595,49.625027],"type":"Point"}
}