{
  "type": "Feature",
  "properties": {
    "iso:country":"DE",
    "sg:address":"Klingengasse 1",
    "sg:city":"Bad Wimpfen",
    "sg:phone":"+49 7063/1313",
    "sg:postcode":"74206",
    "sg:province":"Baden-W\u00fcrttemberg",
    "wof:name":"B. Axenbeck",
    "wof:placetype":"venue"
},
  "geometry": {"coordinates":[9.16232,49.227295],"type":"Point"}
}