{
  "type": "Feature",
  "properties": {
    "iso:country":"DE",
    "sg:address":"Hans-Bredow-Str. 53",
    "sg:city":"Bremen",
    "sg:phone":"+49 421/4859250",
    "sg:postcode":"28307",
    "sg:province":"Bremen",
    "wof:name":"Neue Igefa E. V.",
    "wof:placetype":"venue"
},
  "geometry": {"coordinates":[8.9531068802,53.0447921753],"type":"Point"}
}