{
  "type": "Feature",
  "properties": {
    "iso:country":"DE",
    "sg:address":"Kempener Str. 21",
    "sg:city":"Wachtendonk",
    "sg:phone":"+49 2836/7118",
    "sg:postcode":"47669",
    "sg:province":"Nordrhein-Westfalen",
    "wof:name":"Heinen & Pot Gmbh",
    "wof:placetype":"venue"
},
  "geometry": {"coordinates":[6.3414092064,51.4086265564],"type":"Point"}
}