{
  "type": "Feature",
  "properties": {
    "iso:country":"DE",
    "sg:address":"Waldstr. 49",
    "sg:city":"Biberach",
    "sg:phone":"+49 7835/7504",
    "sg:postcode":"77781",
    "sg:province":"Baden-W\u00fcrttemberg",
    "wof:name":"Gertrud Sp\u00e4th",
    "wof:placetype":"venue"
},
  "geometry": {"coordinates":[8.0374670029,48.3421783447],"type":"Point"}
}