{
  "type": "Feature",
  "properties": {
    "iso:country":"DE",
    "sg:address":"M\u00fcnsterer Weg 5",
    "sg:city":"Liederbach",
    "sg:phone":"+49 69/313881",
    "sg:postcode":"65835",
    "sg:province":"Hessen",
    "wof:name":"Pfeiffer Elsaba Immobilien",
    "wof:placetype":"venue"
},
  "geometry": {"coordinates":[8.4928531647,50.1167373657],"type":"Point"}
}