{
  "type": "Feature",
  "properties": {
    "iso:country":"DE",
    "sg:address":"Lehmkaute 4",
    "sg:city":"Alsfeld",
    "sg:phone":"+49 6639/423",
    "sg:postcode":"36304",
    "sg:province":"Hessen",
    "wof:name":"Rudolf Vierheller",
    "wof:placetype":"venue"
},
  "geometry": {"coordinates":[9.401986,50.76218],"type":"Point"}
}