{
  "type": "Feature",
  "properties": {
    "iso:country":"DE",
    "sg:address":"Kleine Reichenstr. 1",
    "sg:city":"Hamburg",
    "sg:phone":"+49 40/324108",
    "sg:postcode":"20457",
    "sg:province":"Hamburg",
    "wof:name":"Korte Eich Und Wa\u00dfmann Rechtsanw\u00e4lte",
    "wof:placetype":"venue"
},
  "geometry": {"coordinates":[9.9983444214,53.5482559204],"type":"Point"}
}