{
  "type": "Feature",
  "properties": {
    "iso:country":"DE",
    "sg:address":"Lotharstr. 14",
    "sg:city":"Meerbusch",
    "sg:phone":"+49 2150/1002",
    "sg:postcode":"40668",
    "sg:province":"Nordrhein-Westfalen",
    "wof:name":"Rhein-f\u00e4hrbetrieb Langst- Kaiserswerth Sch\u00e4fer Gmbh",
    "wof:placetype":"venue"
},
  "geometry": {"coordinates":[6.714922905,51.3124771118],"type":"Point"}
}