{
  "type": "Feature",
  "properties": {
    "iso:country":"DE",
    "sg:address":"Kallhardtstr. 31",
    "sg:city":"Pforzheim",
    "sg:phone":"+49 7231/280950",
    "sg:postcode":"75173",
    "sg:province":"Baden-W\u00fcrttemberg",
    "wof:name":"Kupferd\u00e4chle",
    "wof:placetype":"venue"
},
  "geometry": {"coordinates":[8.696797,48.883259],"type":"Point"}
}