{
  "type": "Feature",
  "properties": {
    "iso:country":"DE",
    "sg:address":"Martinistr. 32",
    "sg:city":"Herne",
    "sg:phone":"+49 2325/31424",
    "sg:postcode":"44652",
    "sg:province":"Nordrhein-Westfalen",
    "wof:name":"H. Geisenheiser",
    "wof:placetype":"venue"
},
  "geometry": {"coordinates":[7.1637310982,51.5200576782],"type":"Point"}
}