{
  "type": "Feature",
  "properties": {
    "iso:country":"DE",
    "sg:address":"Hauptstr. 8",
    "sg:city":"Ettinghausen",
    "sg:phone":"+49 6435/2629",
    "sg:postcode":"56244",
    "sg:province":"Rheinland-Pfalz",
    "wof:name":"Werner P\u00fcsch",
    "wof:placetype":"venue"
},
  "geometry": {"coordinates":[7.8726229668,50.5147132874],"type":"Point"}
}