{
  "type": "Feature",
  "properties": {
    "iso:country":"DE",
    "sg:address":"Lindengasse 2",
    "sg:city":"Du\u00dflingen",
    "sg:phone":"+49 7072/7703",
    "sg:postcode":"72144",
    "sg:province":"Baden-W\u00fcrttemberg",
    "wof:name":"G\u00fcnther Klett",
    "wof:placetype":"venue"
},
  "geometry": {"coordinates":[9.0533056259,48.4491043091],"type":"Point"}
}