{
  "type": "Feature",
  "properties": {
    "iso:country":"DE",
    "sg:address":"Rudolf-Breitscheid-Str. 82",
    "sg:city":"Potsdam",
    "sg:phone":"+49 4933/1707282",
    "sg:postcode":"14482",
    "sg:province":"Brandenburg",
    "wof:name":"Bestattungsinstitut Kusche Gmbh",
    "wof:placetype":"venue"
},
  "geometry": {"coordinates":[13.1027669907,52.3925094604],"type":"Point"}
}