{
  "type": "Feature",
  "properties": {
    "iso:country":"DE",
    "sg:address":"Kirchweg 7",
    "sg:city":"\u00dcberlingen",
    "sg:phone":"+49 7553/7525",
    "sg:postcode":"88662",
    "sg:province":"Baden-W\u00fcrttemberg",
    "wof:name":"Kath. Pfarramt Lippersreute",
    "wof:placetype":"venue"
},
  "geometry": {"coordinates":[9.2379159927,47.8042068481],"type":"Point"}
}