{
  "type": "Feature",
  "properties": {
    "iso:country":"DE",
    "sg:address":"Hans-Schrader-Str. 25",
    "sg:city":"Sondershausen",
    "sg:phone":"+49 3632/60630",
    "sg:postcode":"99706",
    "sg:province":"Th\u00fcringen",
    "wof:name":"Flachsbarth Und Schilt Steuerberater",
    "wof:placetype":"venue"
},
  "geometry": {"coordinates":[10.8565940857,51.3665046692],"type":"Point"}
}