{
  "type": "Feature",
  "properties": {
    "iso:country":"DE",
    "sg:address":"Dreifaltigkeitsweg",
    "sg:city":"Sinzig",
    "sg:postcode":"53489",
    "sg:province":"Rheinland-Pfalz",
    "wof:name":"Club Der Ehemaligen Des Rheingymnasiums E. V.",
    "wof:placetype":"venue"
},
  "geometry": {"coordinates":[7.246650219,50.5478935242],"type":"Point"}
}