{
  "type": "Feature",
  "properties": {
    "iso:country":"DE",
    "sg:address":"Heinricht-Geist-Str. 5",
    "sg:city":"Frechen K\u00f6ln",
    "sg:phone":"+49 2234",
    "sg:postcode":"50226",
    "sg:province":"Nordrhein-Westfalen",
    "wof:name":"Alles Rund Um Kabelziehstr\u00fcmpfe Rupi K\u00f6ln",
    "wof:placetype":"venue"
},
  "geometry": {"coordinates":[6.8093,50.910751],"type":"Point"}
}