{
  "type": "Feature",
  "properties": {
    "iso:country":"DE",
    "sg:address":"Hagsche Str. 11",
    "sg:city":"Kleve",
    "sg:phone":"+49 2821/26767",
    "sg:postcode":"47533",
    "sg:province":"Nordrhein-Westfalen",
    "wof:name":"Stechbahn-apotheke",
    "wof:placetype":"venue"
},
  "geometry": {"coordinates":[6.136649,51.786034],"type":"Point"}
}