{
  "type": "Feature",
  "properties": {
    "iso:country":"DE",
    "sg:address":"Reichenbacher Str. 123-125",
    "sg:city":"Greiz",
    "sg:phone":"+49 3661/70570",
    "sg:postcode":"07973",
    "sg:province":"Th\u00fcringen",
    "wof:name":"Hierold",
    "wof:placetype":"venue"
},
  "geometry": {"coordinates":[12.226045,50.652039],"type":"Point"}
}