{
  "type": "Feature",
  "properties": {
    "iso:country":"DE",
    "sg:address":"Friedhofstr. 20",
    "sg:city":"Eschelbronn",
    "sg:phone":"+49 6226/41740",
    "sg:postcode":"74927",
    "sg:province":"Baden-W\u00fcrttemberg",
    "wof:name":"Eugen Wagenbla\u00df",
    "wof:placetype":"venue"
},
  "geometry": {"coordinates":[8.864662,49.317581],"type":"Point"}
}