{
  "type": "Feature",
  "properties": {
    "iso:country":"DE",
    "sg:address":"Seestr. 13",
    "sg:city":"Horn-Bad Meinberg",
    "sg:phone":"+49 5234/98933",
    "sg:postcode":"32805",
    "sg:province":"Nordrhein-Westfalen",
    "wof:name":"Pension Haus Meier-strate",
    "wof:placetype":"venue"
},
  "geometry": {"coordinates":[8.9867391586,51.8940582275],"type":"Point"}
}