{
  "type": "Feature",
  "properties": {
    "iso:country":"DE",
    "sg:address":"Austr.",
    "sg:city":"Weilheim",
    "sg:postcode":"73235",
    "sg:province":"Baden-W\u00fcrttemberg",
    "wof:name":"Barth Logistik Service Gmbh",
    "wof:placetype":"venue"
},
  "geometry": {"coordinates":[9.5044212341,48.6313667297],"type":"Point"}
}