{
  "type": "Feature",
  "properties": {
    "iso:country":"DE",
    "sg:address":"Alt Erlenbach 107",
    "sg:city":"Frankfurt",
    "sg:phone":"+49 6101/47880",
    "sg:postcode":"60437",
    "sg:province":"Hessen",
    "wof:name":"Minimal",
    "wof:placetype":"venue"
},
  "geometry": {"coordinates":[8.7016296387,50.2097511292],"type":"Point"}
}