{
  "type": "Feature",
  "properties": {
    "iso:country":"DE",
    "sg:address":"H\u00f6rmannsdorf",
    "sg:city":"Weng",
    "sg:phone":"+49 8702/1287",
    "sg:postcode":"84187",
    "sg:province":"Bayern",
    "wof:name":"Sebastian Gr\u00fcnbeck",
    "wof:placetype":"venue"
},
  "geometry": {"coordinates":[12.3696928024,48.6616668701],"type":"Point"}
}