{
  "type": "Feature",
  "properties": {
    "iso:country":"DE",
    "sg:address":"Uhlandstr. 184",
    "sg:city":"Berlin",
    "sg:postcode":"10623",
    "sg:province":"Berlin",
    "wof:name":"Pension Flora",
    "wof:placetype":"venue"
},
  "geometry": {"coordinates":[13.3256778717,52.5042037964],"type":"Point"}
}