{
  "type": "Feature",
  "properties": {
    "iso:country":"DE",
    "sg:address":"Erzw\u00e4sche 51",
    "sg:city":"Salzgitter",
    "sg:postcode":"38229",
    "sg:province":"Niedersachsen",
    "wof:name":"Pur-bau- Gmbh",
    "wof:placetype":"venue"
},
  "geometry": {"coordinates":[10.371428,52.093716],"type":"Point"}
}