{
  "type": "Feature",
  "properties": {
    "iso:country":"DE",
    "sg:address":"Kasseler Str. 15",
    "sg:city":"Gudensberg",
    "sg:phone":"+49 5603/1371",
    "sg:postcode":"34281",
    "sg:province":"Hessen",
    "wof:name":"Gastst\u00e4tte Keim",
    "wof:placetype":"venue"
},
  "geometry": {"coordinates":[9.3693132401,51.1784210205],"type":"Point"}
}