{
  "type": "Feature",
  "properties": {
    "iso:country":"DE",
    "sg:address":"Hanauer Str. 59",
    "sg:city":"Berlin",
    "sg:phone":"+49 30/8211313",
    "sg:postcode":"14197",
    "sg:province":"Berlin",
    "wof:name":"Unidaus Universelle Daten Auswertung Gmbh",
    "wof:placetype":"venue"
},
  "geometry": {"coordinates":[13.3134660721,52.4788284302],"type":"Point"}
}