{
  "type": "Feature",
  "properties": {
    "iso:country":"DE",
    "sg:address":"Venloer Str. 241-245",
    "sg:city":"K\u00f6ln",
    "sg:phone":"+49 4922/157280",
    "sg:postcode":"50823",
    "sg:province":"Nordrhein-Westfalen",
    "wof:name":"Muehlens Gmbh & Co Kg",
    "wof:placetype":"venue"
},
  "geometry": {"coordinates":[6.923507,50.946854],"type":"Point"}
}