{
  "type": "Feature",
  "properties": {
    "iso:country":"DE",
    "sg:address":"Eichendorffstr. 2",
    "sg:city":"Baltmannsweiler",
    "sg:phone":"+49 7153/94610",
    "sg:postcode":"73666",
    "sg:province":"Baden-W\u00fcrttemberg",
    "wof:name":"Schreinerei Weber Gmbh",
    "wof:placetype":"venue"
},
  "geometry": {"coordinates":[9.444595,48.750381],"type":"Point"}
}