{
  "type": "Feature",
  "properties": {
    "iso:country":"DE",
    "sg:address":"Stangenr\u00f6der Weg 1",
    "sg:city":"Gr\u00fcnberg",
    "sg:phone":"+49 6401/5764",
    "sg:postcode":"35305",
    "sg:province":"Hessen",
    "wof:name":"Mk-versuchsanlagen",
    "wof:placetype":"venue"
},
  "geometry": {"coordinates":[8.959939,50.596951],"type":"Point"}
}