{
  "type": "Feature",
  "properties": {
    "iso:country":"DE",
    "sg:address":"Hauptstr. 14",
    "sg:city":"Bad Gottleuba",
    "sg:phone":"+49 35023/62529",
    "sg:postcode":"01816",
    "sg:province":"Sachsen",
    "wof:name":"Detlef Schommartz Anlageberater",
    "wof:placetype":"venue"
},
  "geometry": {"coordinates":[13.9422855377,50.8502998352],"type":"Point"}
}