{
  "type": "Feature",
  "properties": {
    "iso:country":"DE",
    "sg:address":"Marktplatz 5",
    "sg:city":"Langenhagen",
    "sg:phone":"+49 511/730833",
    "sg:postcode":"30853",
    "sg:province":"Niedersachsen",
    "wof:name":"J. B\u00fchnemann Strick Und N\u00e4h",
    "wof:placetype":"venue"
},
  "geometry": {"coordinates":[9.739537,52.439423],"type":"Point"}
}