{
  "type": "Feature",
  "properties": {
    "iso:country":"DE",
    "sg:address":"Hupfeldstr. 21",
    "sg:city":"Kassel",
    "sg:phone":"+49 561/22927",
    "sg:postcode":"34121",
    "sg:province":"Hessen",
    "wof:name":"Ev. Pfarramt Wehlheiden",
    "wof:placetype":"venue"
},
  "geometry": {"coordinates":[9.4609107971,51.3104743958],"type":"Point"}
}