{
  "type": "Feature",
  "properties": {
    "iso:country":"DE",
    "sg:address":"Schillerstr. 22",
    "sg:city":"Babenhausen",
    "sg:phone":"+49 8333/3977",
    "sg:postcode":"87727",
    "sg:province":"Bayern",
    "wof:name":"Max Kaifler",
    "wof:placetype":"venue"
},
  "geometry": {"coordinates":[10.248257,48.136589],"type":"Point"}
}