{
  "type": "Feature",
  "properties": {
    "iso:country":"DE",
    "sg:address":"Hofer Str. 9",
    "sg:city":"Kirchenlamitz",
    "sg:phone":"+49 9285/407",
    "sg:postcode":"95158",
    "sg:province":"Bayern",
    "wof:name":"Ev. Pfarramt",
    "wof:placetype":"venue"
},
  "geometry": {"coordinates":[11.9509401321,50.1520996094],"type":"Point"}
}