{
  "type": "Feature",
  "properties": {
    "iso:country":"DE",
    "sg:address":"Oed 3",
    "sg:city":"Teisendorf",
    "sg:postcode":"83317",
    "sg:province":"Bayern",
    "wof:name":"Ernst Reifgerst",
    "wof:placetype":"venue"
},
  "geometry": {"coordinates":[12.825489,47.853886],"type":"Point"}
}