{
  "type": "Feature",
  "properties": {
    "iso:country":"DE",
    "sg:city":"Freilassing",
    "sg:postcode":"83395",
    "sg:province":"Bayern",
    "wof:name":"Stylefactory - Designschmuck In Sterlingsilber",
    "wof:placetype":"venue"
},
  "geometry": {"coordinates":[12.976875,47.842224],"type":"Point"}
}