{
  "type": "Feature",
  "properties": {
    "iso:country":"DE",
    "sg:address":"Lortzingstr. 21",
    "sg:city":"Bad Pyrmont",
    "sg:phone":"+49 5281/608154",
    "sg:postcode":"31812",
    "sg:province":"Niedersachsen",
    "wof:name":"Alt Heidelberg",
    "wof:placetype":"venue"
},
  "geometry": {"coordinates":[9.2643718719,51.9853515625],"type":"Point"}
}