{
  "type": "Feature",
  "properties": {
    "iso:country":"DE",
    "sg:address":"Im Eschig 10",
    "sg:city":"Offenbach",
    "sg:postcode":"63075",
    "sg:province":"Hessen",
    "wof:name":"Herdt Verwaltungsges. Mbh",
    "wof:placetype":"venue"
},
  "geometry": {"coordinates":[8.800605,50.112328],"type":"Point"}
}