{
  "type": "Feature",
  "properties": {
    "iso:country":"DE",
    "sg:address":"Louis-Schuler-Str. 4",
    "sg:city":"G\u00f6ppingen",
    "sg:phone":"+49 7161/72071",
    "sg:postcode":"73033",
    "sg:province":"Baden-W\u00fcrttemberg",
    "wof:name":"Rolf M\u00fcller Farben Und Tapeten",
    "wof:placetype":"venue"
},
  "geometry": {"coordinates":[9.6634836197,48.7085876465],"type":"Point"}
}