{
  "type": "Feature",
  "properties": {
    "iso:country":"DE",
    "sg:address":"Obert\u00fcrkheimer Str. 8",
    "sg:city":"Esslingen",
    "sg:phone":"+49 711/321311",
    "sg:postcode":"73733",
    "sg:province":"Baden-W\u00fcrttemberg",
    "wof:name":"Pilsstern",
    "wof:placetype":"venue"
},
  "geometry": {"coordinates":[9.2762956619,48.7491226196],"type":"Point"}
}