{
  "type": "Feature",
  "properties": {
    "iso:country":"DE",
    "sg:address":"Rinderbachstr. 18",
    "sg:city":"Essen",
    "sg:phone":"+49 2054/86298",
    "sg:postcode":"45219",
    "sg:province":"Nordrhein-Westfalen",
    "wof:name":"Thomas L\u00f6rke Tennislehrer",
    "wof:placetype":"venue"
},
  "geometry": {"coordinates":[6.9333300591,51.3602523804],"type":"Point"}
}