{
  "type": "Feature",
  "properties": {
    "iso:country":"DE",
    "sg:address":"Holzweg 6",
    "sg:city":"S\u00f6gel",
    "sg:phone":"+49 5952/735",
    "sg:postcode":"49751",
    "sg:province":"Niedersachsen",
    "wof:name":"Weser-ems Union Eg",
    "wof:placetype":"venue"
},
  "geometry": {"coordinates":[7.528341,52.845093],"type":"Point"}
}