{
  "type": "Feature",
  "properties": {
    "iso:country":"DE",
    "sg:address":"Barmstedter Str. 1",
    "sg:city":"Kaltenkirchen",
    "sg:phone":"+49 4191/7877",
    "sg:postcode":"24568",
    "sg:province":"Schleswig-Holstein",
    "wof:name":"Raumharmonie Huettmann Kg",
    "wof:placetype":"venue"
},
  "geometry": {"coordinates":[9.9511432648,53.8349838257],"type":"Point"}
}