{
  "type": "Feature",
  "properties": {
    "iso:country":"DE",
    "sg:address":"Gubener Str. 17",
    "sg:city":"L\u00fcbben",
    "sg:postcode":"15907",
    "sg:province":"Brandenburg",
    "wof:name":"Stadtwirtschaftliche Dienstleistungen L\u00fcbben Gmbh",
    "wof:placetype":"venue"
},
  "geometry": {"coordinates":[13.906709671,51.9377403259],"type":"Point"}
}