{
  "type": "Feature",
  "properties": {
    "iso:country":"DE",
    "sg:address":"Breitenfelder Str. 36",
    "sg:city":"Leipzig",
    "sg:phone":"+49 341/5902990",
    "sg:postcode":"04155",
    "sg:province":"Sachsen",
    "wof:name":"Hauskrankenpflege Schwester Sylvia Ohnsorge",
    "wof:placetype":"venue"
},
  "geometry": {"coordinates":[12.362447,51.365635],"type":"Point"}
}