{
  "type": "Feature",
  "properties": {
    "iso:country":"DE",
    "sg:address":"L\u00fcbsche Str. 95",
    "sg:city":"Wismar",
    "sg:phone":"+49 3841/72500",
    "sg:postcode":"23966",
    "sg:province":"Mecklenburg-Vorpommern",
    "wof:name":"We Go Telefone Und Kommunikationssysteme Gmbh",
    "wof:placetype":"venue"
},
  "geometry": {"coordinates":[11.4536781311,53.8926429749],"type":"Point"}
}