{
  "type": "Feature",
  "properties": {
    "iso:country":"DE",
    "sg:address":"Helenenstr. 10",
    "sg:city":"Gotha",
    "sg:phone":"+49 3621/403730",
    "sg:postcode":"99867",
    "sg:province":"Th\u00fcringen",
    "wof:name":"Apotheke An Der Orangerie Beate G\u00fcrtler E. Kfr.",
    "wof:placetype":"venue"
},
  "geometry": {"coordinates":[10.712961,50.946266],"type":"Point"}
}