{
  "type": "Feature",
  "properties": {
    "iso:country":"DE",
    "sg:address":"Auerstr. 203",
    "sg:city":"Coswig",
    "sg:postcode":"01640",
    "sg:province":"Sachsen",
    "wof:name":"Fenstras",
    "wof:placetype":"venue"
},
  "geometry": {"coordinates":[13.5768327713,51.1409454346],"type":"Point"}
}