{
  "type": "Feature",
  "properties": {
    "iso:country":"DE",
    "sg:address":"Samsweger Str. 20",
    "sg:city":"Wolmirstedt",
    "sg:phone":"+49 39201/23000",
    "sg:postcode":"39326",
    "sg:province":"Sachsen-Anhalt",
    "wof:name":"B & S Concept Bau Mirko Bode",
    "wof:placetype":"venue"
},
  "geometry": {"coordinates":[11.624891,52.249722],"type":"Point"}
}