{
  "type": "Feature",
  "properties": {
    "iso:country":"DE",
    "sg:address":"Ernst-Th\u00e4lmann-Str. 11",
    "sg:city":"Templin",
    "sg:postcode":"17268",
    "sg:province":"Brandenburg",
    "wof:name":"Jochen K\u00f6hn",
    "wof:placetype":"venue"
},
  "geometry": {"coordinates":[13.501824379,53.119758606],"type":"Point"}
}