{
  "type": "Feature",
  "properties": {
    "iso:country":"DE",
    "sg:address":"K\u00f6lner Landstr. 239",
    "sg:city":"D\u00fcsseldorf",
    "sg:phone":"+49 211/752370",
    "sg:postcode":"40591",
    "sg:province":"Nordrhein-Westfalen",
    "wof:name":"Restaurant Athen",
    "wof:placetype":"venue"
},
  "geometry": {"coordinates":[6.8199038506,51.1852645874],"type":"Point"}
}