{
  "type": "Feature",
  "properties": {
    "iso:country":"DE",
    "sg:address":"Im Siechengarten",
    "sg:city":"Balingen",
    "sg:phone":"+49 7433/37173",
    "sg:postcode":"72336",
    "sg:province":"Baden-W\u00fcrttemberg",
    "wof:name":"Heliosch",
    "wof:placetype":"venue"
},
  "geometry": {"coordinates":[8.85839,48.278503],"type":"Point"}
}