{
  "type": "Feature",
  "properties": {
    "iso:country":"DE",
    "sg:address":"Josef-Herrmann-Str. 1",
    "sg:city":"Iffezheim",
    "sg:phone":"+49 7229/6000",
    "sg:postcode":"76473",
    "sg:province":"Baden-W\u00fcrttemberg",
    "wof:name":"Sw Kies Gmbh",
    "wof:placetype":"venue"
},
  "geometry": {"coordinates":[8.161856,48.815979],"type":"Point"}
}