{
  "type": "Feature",
  "properties": {
    "iso:country":"DE",
    "sg:address":"W\u00f6rde 10",
    "sg:city":"Leer",
    "sg:phone":"+49 491/63222",
    "sg:postcode":"26789",
    "sg:province":"Niedersachsen",
    "wof:name":"Restaurant Ali Baba",
    "wof:placetype":"venue"
},
  "geometry": {"coordinates":[7.4532089233,53.229133606],"type":"Point"}
}