{
  "type": "Feature",
  "properties": {
    "iso:country":"DE",
    "sg:address":"Rathausplatz 8-10 Haus am Park",
    "sg:city":"Bad Homburg",
    "sg:postcode":"61348",
    "sg:province":"Hessen",
    "wof:name":"Cf Living Office Immobilien Gmbh",
    "wof:placetype":"venue"
},
  "geometry": {"coordinates":[8.6068000793,50.2268714905],"type":"Point"}
}