{
  "type": "Feature",
  "properties": {
    "iso:country":"DE",
    "sg:address":"Am Stadtmuseum 4-8",
    "sg:city":"Oldenburg",
    "sg:phone":"+49 441/2352881",
    "sg:postcode":"26121",
    "sg:province":"Niedersachsen",
    "wof:name":"Stadtmuseum Oldenburg St\u00e4dtische Kunstsammlungen",
    "wof:placetype":"venue"
},
  "geometry": {"coordinates":[8.214436,53.145645],"type":"Point"}
}