{
  "type": "Feature",
  "properties": {
    "iso:country":"DE",
    "sg:address":"S\u00fcderquerweg 224",
    "sg:city":"Hamburg",
    "sg:phone":"+49 40/7238391",
    "sg:postcode":"21037",
    "sg:province":"Hamburg",
    "wof:name":"Biohof Uwe Behnken",
    "wof:placetype":"venue"
},
  "geometry": {"coordinates":[10.160543,53.412014],"type":"Point"}
}