{
  "type": "Feature",
  "properties": {
    "iso:country":"DE",
    "sg:address":"K\u00fchlwetterstr. 16",
    "sg:city":"D\u00fcsseldorf",
    "sg:postcode":"40239",
    "sg:province":"Nordrhein-Westfalen",
    "wof:name":"Vass Immobilien",
    "wof:placetype":"venue"
},
  "geometry": {"coordinates":[6.7993311882,51.2429237366],"type":"Point"}
}