{
  "type": "Feature",
  "properties": {
    "iso:country":"DE",
    "sg:address":"Marienstr. 27",
    "sg:city":"Horb",
    "sg:phone":"+49 7451/8393",
    "sg:postcode":"72160",
    "sg:province":"Baden-W\u00fcrttemberg",
    "wof:name":"Kre\u00df Gmbh",
    "wof:placetype":"venue"
},
  "geometry": {"coordinates":[8.713927269,48.4670333862],"type":"Point"}
}