{
  "type": "Feature",
  "properties": {
    "iso:country":"DE",
    "sg:address":"Barf\u00fc\u00dferstr. 18",
    "sg:city":"G\u00f6ttingen",
    "sg:phone":"+49 551/547340",
    "sg:postcode":"37073",
    "sg:province":"Niedersachsen",
    "wof:name":"O. Fleischmann Gmbh",
    "wof:placetype":"venue"
},
  "geometry": {"coordinates":[9.9370956421,51.5336418152],"type":"Point"}
}