{
  "type": "Feature",
  "properties": {
    "iso:country":"DE",
    "sg:address":"Dorfstr. 4",
    "sg:city":"Wehrbleck",
    "sg:phone":"+49 4274/349",
    "sg:postcode":"27259",
    "sg:province":"Niedersachsen",
    "wof:name":"Filgedamms Gasthaus",
    "wof:placetype":"venue"
},
  "geometry": {"coordinates":[8.6899261475,52.6295890808],"type":"Point"}
}