{
  "type": "Feature",
  "properties": {
    "iso:country":"DE",
    "sg:address":"Auf dem Steinchen 3",
    "sg:city":"Bonn",
    "sg:phone":"+49 228/285180",
    "sg:postcode":"53127",
    "sg:province":"Nordrhein-Westfalen",
    "wof:name":"Dr.med. Martin Zywietz",
    "wof:placetype":"venue"
},
  "geometry": {"coordinates":[7.07921,50.702156],"type":"Point"}
}