{
  "type": "Feature",
  "properties": {
    "iso:country":"DE",
    "sg:address":"M\u00fchlh\u00e4user Str. 47",
    "sg:city":"Kornwestheim",
    "sg:phone":"+49 7154/29261",
    "sg:postcode":"70806",
    "sg:province":"Baden-W\u00fcrttemberg",
    "wof:name":"Alfred Buck Steuerberater",
    "wof:placetype":"venue"
},
  "geometry": {"coordinates":[9.1950616837,48.8631744385],"type":"Point"}
}