{
  "type": "Feature",
  "properties": {
    "iso:country":"DE",
    "sg:address":"Dortmunder Str. 20",
    "sg:city":"Waltrop",
    "sg:phone":"+49 2309/2808",
    "sg:postcode":"45731",
    "sg:province":"Nordrhein-Westfalen",
    "wof:name":"Gastst\u00e4tte H. H\u00f6wer",
    "wof:placetype":"venue"
},
  "geometry": {"coordinates":[7.3984069824,51.6232299805],"type":"Point"}
}