{
  "type": "Feature",
  "properties": {
    "iso:country":"DE",
    "sg:address":"Kuckuckskamp 23",
    "sg:city":"Langenhagen",
    "sg:phone":"+49 511/9783983",
    "sg:postcode":"30855",
    "sg:province":"Niedersachsen",
    "wof:name":"Negelmann Assekuranzb\u00fcro Gmbh",
    "wof:placetype":"venue"
},
  "geometry": {"coordinates":[9.6966838837,52.4404029846],"type":"Point"}
}