{
  "type": "Feature",
  "properties": {
    "iso:country":"DE",
    "sg:address":"Ferdinand-Sauerbruch-Str. 2",
    "sg:city":"Koblenz",
    "sg:phone":"+49 261/94380",
    "sg:postcode":"56073",
    "sg:province":"Rheinland-Pfalz",
    "wof:name":"Sport-toto-gmbh",
    "wof:placetype":"venue"
},
  "geometry": {"coordinates":[7.5713648796,50.3616676331],"type":"Point"}
}