{
  "type": "Feature",
  "properties": {
    "iso:country":"DE",
    "sg:address":"Abersdorf 20",
    "sg:city":"Riedering",
    "sg:postcode":"83083",
    "sg:province":"Bayern",
    "wof:name":"Car-venture Management Gmbh & Co. Kg",
    "wof:placetype":"venue"
},
  "geometry": {"coordinates":[12.245366,47.853008],"type":"Point"}
}