{
  "type": "Feature",
  "properties": {
    "iso:country":"DE",
    "sg:address":"Kramerstr. 44",
    "sg:city":"Memmingen",
    "sg:phone":"+49 8331/2351",
    "sg:postcode":"87700",
    "sg:province":"Bayern",
    "wof:name":"F. Tr\u00f6ger Optiker",
    "wof:placetype":"venue"
},
  "geometry": {"coordinates":[10.1816663742,47.9834098816],"type":"Point"}
}