{
  "type": "Feature",
  "properties": {
    "iso:country":"DE",
    "sg:address":"Schlehweg 2",
    "sg:city":"Kaiserslautern",
    "sg:phone":"+49 631/56680",
    "sg:postcode":"67661",
    "sg:province":"Rheinland-Pfalz",
    "wof:name":"A. Winter",
    "wof:placetype":"venue"
},
  "geometry": {"coordinates":[7.7256350517,49.405128479],"type":"Point"}
}