{
  "type": "Feature",
  "properties": {
    "iso:country":"DE",
    "sg:address":"Hewlett-Packard-Str. 4",
    "sg:city":"Bad Homburg",
    "sg:phone":"+49 6172/49610",
    "sg:postcode":"61352",
    "sg:province":"Hessen",
    "wof:name":"Basler Versicherungs-ges. Direktion F\u00fcr Deutschland",
    "wof:placetype":"venue"
},
  "geometry": {"coordinates":[8.6495685577,50.2120018005],"type":"Point"}
}