{
  "type": "Feature",
  "properties": {
    "iso:country":"DE",
    "sg:address":"Lerchenstr. 6",
    "sg:city":"Eslarn",
    "sg:phone":"+49 9653/92100",
    "sg:postcode":"92693",
    "sg:province":"Bayern",
    "wof:name":"Gerhard Urban Steuerberater",
    "wof:placetype":"venue"
},
  "geometry": {"coordinates":[12.5147275925,49.5782203674],"type":"Point"}
}