{
  "type": "Feature",
  "properties": {
    "iso:country":"DE",
    "sg:address":"Hermannstr. 26",
    "sg:city":"Pulheim",
    "sg:phone":"+49 2234/81414",
    "sg:postcode":"50259",
    "sg:province":"Nordrhein-Westfalen",
    "wof:name":"Anne Brasche",
    "wof:placetype":"venue"
},
  "geometry": {"coordinates":[6.75998,50.957069],"type":"Point"}
}