{
  "type": "Feature",
  "properties": {
    "iso:country":"DE",
    "sg:address":"Georg-Murmann-Str. 6",
    "sg:city":"Erligheim",
    "sg:phone":"+49 7143/883840",
    "sg:postcode":"74391",
    "sg:province":"Baden-W\u00fcrttemberg",
    "wof:name":"Volkhard Schmidt Bedachungen Gmbh",
    "wof:placetype":"venue"
},
  "geometry": {"coordinates":[9.092054,49.023129],"type":"Point"}
}