{
  "type": "Feature",
  "properties": {
    "iso:country":"DE",
    "sg:address":"Arthur-Bretschneider-Str. 14",
    "sg:city":"Chemnitz",
    "sg:phone":"+49 371/3360324",
    "sg:postcode":"09113",
    "sg:province":"Sachsen",
    "wof:name":"Bruno Bennewitz",
    "wof:placetype":"venue"
},
  "geometry": {"coordinates":[12.90236,50.844616],"type":"Point"}
}