{
  "type": "Feature",
  "properties": {
    "iso:country":"DE",
    "sg:address":"He\u00dflocher Str. 9",
    "sg:city":"Wiesbaden",
    "sg:phone":"+49 611/502694",
    "sg:postcode":"65207",
    "sg:province":"Hessen",
    "wof:name":"Bella Vista",
    "wof:placetype":"venue"
},
  "geometry": {"coordinates":[8.305973053,50.0954551697],"type":"Point"}
}