{
  "type": "Feature",
  "properties": {
    "iso:country":"DE",
    "sg:address":"Breiter Gang 10-16",
    "sg:city":"Osnabr\u00fcck",
    "sg:phone":"+49 541/3251",
    "sg:postcode":"49074",
    "sg:province":"Niedersachsen",
    "wof:name":"Neue Osnabr\u00fccker Zeitung Gmbh & Co. Kg",
    "wof:placetype":"venue"
},
  "geometry": {"coordinates":[8.0509700775,52.2772064209],"type":"Point"}
}