{
  "type": "Feature",
  "properties": {
    "iso:country":"DE",
    "sg:address":"Haedenkampstr. 6",
    "sg:city":"Essen",
    "sg:phone":"+49 201/863030",
    "sg:postcode":"45143",
    "sg:province":"Nordrhein-Westfalen",
    "wof:name":"Motoren B\u00fccker & Essing Gmbh & Co. Kg",
    "wof:placetype":"venue"
},
  "geometry": {"coordinates":[6.982785,51.459114],"type":"Point"}
}