{
  "type": "Feature",
  "properties": {
    "iso:country":"DE",
    "sg:address":"Poststr. 4",
    "sg:city":"Wildpoldsried",
    "sg:phone":"+49 8304/5619",
    "sg:postcode":"87499",
    "sg:province":"Bayern",
    "wof:name":"W. Hartmann",
    "wof:placetype":"venue"
},
  "geometry": {"coordinates":[10.400949,47.766239],"type":"Point"}
}