{
  "type": "Feature",
  "properties": {
    "iso:country":"DE",
    "sg:address":"Geestwiesenweg 22",
    "sg:city":"Winsen",
    "sg:phone":"+49 4171/50213",
    "sg:postcode":"21423",
    "sg:province":"Niedersachsen",
    "wof:name":"Zimmerei Cohrs Gmbh",
    "wof:placetype":"venue"
},
  "geometry": {"coordinates":[10.156247139,53.371219635],"type":"Point"}
}