{
  "type": "Feature",
  "properties": {
    "iso:country":"DE",
    "sg:address":"Rennerweg 2",
    "sg:city":"Schrobenhausen",
    "sg:phone":"+49 8252/5095",
    "sg:postcode":"86529",
    "sg:province":"Bayern",
    "wof:name":"Manfred H\u00fcttinger Gmbh",
    "wof:placetype":"venue"
},
  "geometry": {"coordinates":[11.243903,48.570492],"type":"Point"}
}