{
  "type": "Feature",
  "properties": {
    "iso:country":"DE",
    "sg:address":"Bahnhofsplatz",
    "sg:city":"Saarlouis",
    "sg:phone":"+49 6831/84521",
    "sg:postcode":"66740",
    "sg:province":"Saarland",
    "wof:name":"Peter Christmann",
    "wof:placetype":"venue"
},
  "geometry": {"coordinates":[6.7495551109,49.3274688721],"type":"Point"}
}