{
  "type": "Feature",
  "properties": {
    "iso:country":"DE",
    "sg:address":"J\u00e4hndorfstr. 24",
    "sg:city":"Niederorschel",
    "sg:postcode":"37355",
    "sg:province":"Th\u00fcringen",
    "wof:name":"Foesta Consulting Fc Gmbh",
    "wof:placetype":"venue"
},
  "geometry": {"coordinates":[10.428068161,51.3682518005],"type":"Point"}
}