{
  "type": "Feature",
  "properties": {
    "iso:country":"DE",
    "sg:address":"G\u00fcnthersburgallee 88",
    "sg:city":"Frankfurt",
    "sg:phone":"+49 69/456212",
    "sg:postcode":"60389",
    "sg:province":"Hessen",
    "wof:name":"Dr. Med. Karl Bracharz Arzt F\u00fcr Allgemeinmedizin",
    "wof:placetype":"venue"
},
  "geometry": {"coordinates":[8.6996641159,50.1278991699],"type":"Point"}
}