{
  "type": "Feature",
  "properties": {
    "iso:country":"DE",
    "sg:address":"Bert-Brecht-Str. 4",
    "sg:city":"Offenbach",
    "sg:phone":"+49 69/847630",
    "sg:postcode":"63069",
    "sg:province":"Hessen",
    "wof:name":"Werner Und Renate B\u00fcttner",
    "wof:placetype":"venue"
},
  "geometry": {"coordinates":[8.7496442795,50.083278656],"type":"Point"}
}