{
  "type": "Feature",
  "properties": {
    "iso:country":"DE",
    "sg:address":"Mommsenstr. 27",
    "sg:city":"Berlin",
    "sg:phone":"+49 30/3243069",
    "sg:postcode":"10629",
    "sg:province":"Berlin",
    "wof:name":"Claus-dieter Conrad Rechtsanwalt",
    "wof:placetype":"venue"
},
  "geometry": {"coordinates":[13.3090353012,52.5036582947],"type":"Point"}
}