{
  "type": "Feature",
  "properties": {
    "iso:country":"DE",
    "sg:address":"G\u00f6rlinger-Zentrum 29",
    "sg:city":"K\u00f6ln",
    "sg:phone":"+49 221/5001220",
    "sg:postcode":"50829",
    "sg:province":"Nordrhein-Westfalen",
    "wof:name":"Voosen",
    "wof:placetype":"venue"
},
  "geometry": {"coordinates":[6.868344,50.980564],"type":"Point"}
}