{
  "type": "Feature",
  "properties": {
    "iso:country":"DE",
    "sg:address":"Andreas-Passage 1",
    "sg:city":"Hildesheim",
    "sg:phone":"+49 5121/16700",
    "sg:postcode":"31134",
    "sg:province":"Niedersachsen",
    "wof:name":"Gustav L\u00fcder Grundbesitz Gesch\u00e4ftsf\u00fchrungs Gmbh",
    "wof:placetype":"venue"
},
  "geometry": {"coordinates":[9.9490156174,52.1512184143],"type":"Point"}
}