{
  "type": "Feature",
  "properties": {
    "iso:country":"DE",
    "sg:address":"Magdeburger Str. 3",
    "sg:city":"Krefeld",
    "sg:phone":"+49 2151/475500",
    "sg:postcode":"47800",
    "sg:province":"Nordrhein-Westfalen",
    "wof:name":"Siegfried Maier",
    "wof:placetype":"venue"
},
  "geometry": {"coordinates":[6.6235890388,51.3563308716],"type":"Point"}
}