{
  "type": "Feature",
  "properties": {
    "iso:country":"DE",
    "sg:address":"Auf dem Amthaupt 3",
    "sg:city":"H\u00fcnstetten",
    "sg:phone":"+49 6126/56569",
    "sg:postcode":"65510",
    "sg:province":"Hessen",
    "wof:name":"Dieter Nadenau Ingenieur",
    "wof:placetype":"venue"
},
  "geometry": {"coordinates":[8.1966705322,50.2496414185],"type":"Point"}
}