{
  "type": "Feature",
  "properties": {
    "iso:country":"DE",
    "sg:address":"Taunusstr. 30",
    "sg:city":"Kriftel",
    "sg:phone":"+49 6192/911274",
    "sg:postcode":"65830",
    "sg:province":"Hessen",
    "wof:name":"Herbert Leister Obstanbau",
    "wof:placetype":"venue"
},
  "geometry": {"coordinates":[8.4650125504,50.0843009949],"type":"Point"}
}