{
  "type": "Feature",
  "properties": {
    "iso:country":"DE",
    "sg:address":"Deufringer Str. 24",
    "sg:city":"Aidlingen",
    "sg:phone":"+49 7056/8191",
    "sg:postcode":"71134",
    "sg:province":"Baden-W\u00fcrttemberg",
    "wof:name":"W. Wei\u00df",
    "wof:placetype":"venue"
},
  "geometry": {"coordinates":[8.8589096069,48.678478241],"type":"Point"}
}