{
  "type": "Feature",
  "properties": {
    "iso:country":"DE",
    "sg:address":"Paarmanns Weg 4",
    "sg:city":"Hamburg",
    "sg:phone":"+49 40/86663036",
    "sg:postcode":"22587",
    "sg:province":"Hamburg",
    "wof:name":"T. Stoklossa",
    "wof:placetype":"venue"
},
  "geometry": {"coordinates":[9.8079471588,53.5571022034],"type":"Point"}
}