{
  "type": "Feature",
  "properties": {
    "iso:country":"DE",
    "sg:address":"Archivstr. 10",
    "sg:city":"Amberg",
    "sg:phone":"+49 9621/22582",
    "sg:postcode":"92224",
    "sg:province":"Bayern",
    "wof:name":"Dr. O. Duck Rechtsanwalt",
    "wof:placetype":"venue"
},
  "geometry": {"coordinates":[11.8508930206,49.4410934448],"type":"Point"}
}