{
  "type": "Feature",
  "properties": {
    "iso:country":"DE",
    "sg:address":"Gneisenaustr. 14",
    "sg:city":"Stadtlohn",
    "sg:phone":"+49 2563/204205",
    "sg:postcode":"48703",
    "sg:province":"Nordrhein-Westfalen",
    "wof:name":"Jork Br\u00fcske",
    "wof:placetype":"venue"
},
  "geometry": {"coordinates":[6.90422,51.988106],"type":"Point"}
}