{
  "type": "Feature",
  "properties": {
    "iso:country":"DE",
    "sg:address":"Bamberger Str. 10",
    "sg:city":"Ha\u00dffurt",
    "sg:phone":"+49 9521/7561",
    "sg:postcode":"97437",
    "sg:province":"Bayern",
    "wof:name":"Edmund Bendel",
    "wof:placetype":"venue"
},
  "geometry": {"coordinates":[10.547577858,50.0274200439],"type":"Point"}
}