{
  "type": "Feature",
  "properties": {
    "iso:country":"DE",
    "sg:address":"Ebracher Str. 7",
    "sg:city":"M\u00fcnchen",
    "sg:phone":"+49 89/874987",
    "sg:postcode":"81243",
    "sg:province":"Bayern",
    "wof:name":"Gerhard Dietz",
    "wof:placetype":"venue"
},
  "geometry": {"coordinates":[11.432682,48.152458],"type":"Point"}
}