{
  "type": "Feature",
  "properties": {
    "iso:country":"DE",
    "sg:address":"Ridbacher Str. 94",
    "sg:city":"Berlin",
    "sg:phone":"+49 30/5627310",
    "sg:postcode":"12621",
    "sg:province":"Berlin",
    "wof:name":"Frank R\u00f6sler",
    "wof:placetype":"venue"
},
  "geometry": {"coordinates":[13.6063804626,52.5231285095],"type":"Point"}
}