{
  "type": "Feature",
  "properties": {
    "iso:country":"DE",
    "sg:address":"Dresdener Str. 50",
    "sg:city":"Bautzen",
    "sg:phone":"+49 3591/44529",
    "sg:postcode":"02625",
    "sg:province":"Sachsen",
    "wof:name":"Expert Rtv Service Gmbh",
    "wof:placetype":"venue"
},
  "geometry": {"coordinates":[14.4088964462,51.1795768738],"type":"Point"}
}