{
  "type": "Feature",
  "properties": {
    "iso:country":"DE",
    "sg:address":"Aktienstr. 182",
    "sg:city":"M\u00fclheim",
    "sg:phone":"+49 208/764799",
    "sg:postcode":"45473",
    "sg:province":"Nordrhein-Westfalen",
    "wof:name":"Malerbetrieb Dohmen & Fraune Gmbh",
    "wof:placetype":"venue"
},
  "geometry": {"coordinates":[6.900423,51.442657],"type":"Point"}
}