{
  "type": "Feature",
  "properties": {
    "iso:country":"DE",
    "sg:address":"Bremstr. 7",
    "sg:city":"Mainburg",
    "sg:phone":"+49 8751/9821",
    "sg:postcode":"84048",
    "sg:province":"Bayern",
    "wof:name":"Alma Kr\u00e4uter Gmbh",
    "wof:placetype":"venue"
},
  "geometry": {"coordinates":[11.7459802628,48.6149902344],"type":"Point"}
}