{
  "type": "Feature",
  "properties": {
    "iso:country":"DE",
    "sg:address":"Kohleisenstr. 16",
    "sg:city":"Heubach",
    "sg:phone":"+49 7173/12113",
    "sg:postcode":"73540",
    "sg:province":"Baden-W\u00fcrttemberg",
    "wof:name":"Arwid Zander Masseur",
    "wof:placetype":"venue"
},
  "geometry": {"coordinates":[9.919404,48.797558],"type":"Point"}
}