{
  "type": "Feature",
  "properties": {
    "iso:country":"DE",
    "sg:address":"Unterer Marktplatz 35",
    "sg:city":"Dorfen",
    "sg:phone":"+49 8081/512",
    "sg:postcode":"84405",
    "sg:province":"Bayern",
    "wof:name":"Walter Schubert Drogerie-foto",
    "wof:placetype":"venue"
},
  "geometry": {"coordinates":[12.150731,48.273689],"type":"Point"}
}