{
  "type": "Feature",
  "properties": {
    "iso:country":"DE",
    "sg:address":"Schlo\u00dfseeallee 24",
    "sg:city":"Salem",
    "sg:phone":"+49 7553/92300",
    "sg:postcode":"88682",
    "sg:province":"Baden-W\u00fcrttemberg",
    "wof:name":"Groz Elektronic Gmbh",
    "wof:placetype":"venue"
},
  "geometry": {"coordinates":[9.296288,47.767693],"type":"Point"}
}