{
  "type": "Feature",
  "properties": {
    "iso:country":"DE",
    "sg:address":"Nordheim Str. 4",
    "sg:city":"Frankfurt",
    "sg:phone":"+49 69/637144",
    "sg:postcode":"60596",
    "sg:province":"Hessen",
    "wof:name":"H. Kr\u00fcger Steuerberater",
    "wof:placetype":"venue"
},
  "geometry": {"coordinates":[8.6765079498,50.0991630554],"type":"Point"}
}