{
  "type": "Feature",
  "properties": {
    "iso:country":"DE",
    "sg:address":"Menzelstr. 34",
    "sg:city":"Duisburg",
    "sg:phone":"+49 203/284684",
    "sg:postcode":"47053",
    "sg:province":"Nordrhein-Westfalen",
    "wof:name":"R. Matern",
    "wof:placetype":"venue"
},
  "geometry": {"coordinates":[6.7620000839,51.4243469238],"type":"Point"}
}