{
  "type": "Feature",
  "properties": {
    "iso:country":"DE",
    "sg:address":"Oberasbacher Str. 19a",
    "sg:city":"Zirndorf",
    "sg:phone":"+49 911/695046",
    "sg:postcode":"90513",
    "sg:province":"Bayern",
    "wof:name":"Erwin Nickel Reiseb\u00fcro Gmbh",
    "wof:placetype":"venue"
},
  "geometry": {"coordinates":[10.95748806,49.4316177368],"type":"Point"}
}