{
  "type": "Feature",
  "properties": {
    "iso:country":"DE",
    "sg:address":"Antoniusstr. 5",
    "sg:city":"Moers",
    "sg:phone":"+49 2841/58380",
    "sg:postcode":"47441",
    "sg:province":"Nordrhein-Westfalen",
    "wof:name":"Josef Schuh",
    "wof:placetype":"venue"
},
  "geometry": {"coordinates":[6.658595,51.441265],"type":"Point"}
}