{
  "type": "Feature",
  "properties": {
    "iso:country":"DE",
    "sg:address":"Hittastr. 44",
    "sg:city":"M\u00f6nchengladbach",
    "sg:phone":"+49 2161/82570",
    "sg:postcode":"41061",
    "sg:province":"Nordrhein-Westfalen",
    "wof:name":"Debeka Lebensversicherungs- Verein A.g.",
    "wof:placetype":"venue"
},
  "geometry": {"coordinates":[6.425579071,51.1927947998],"type":"Point"}
}