{
  "type": "Feature",
  "properties": {
    "iso:country":"DE",
    "sg:address":"Lotter Str. 118",
    "sg:city":"Osnabr\u00fcck",
    "sg:phone":"+49 541/430897",
    "sg:postcode":"49078",
    "sg:province":"Niedersachsen",
    "wof:name":"J\u00fcrgen Steinigeweg Architekt",
    "wof:placetype":"venue"
},
  "geometry": {"coordinates":[8.034029,52.275047],"type":"Point"}
}