{
  "type": "Feature",
  "properties": {
    "iso:country":"DE",
    "sg:address":"Ocholter Str. 35",
    "sg:city":"Bad Zwischenahn",
    "sg:phone":"+49 4403/972834",
    "sg:postcode":"26160",
    "sg:province":"Niedersachsen",
    "wof:name":"Holderkroog",
    "wof:placetype":"venue"
},
  "geometry": {"coordinates":[7.9533658028,53.185218811],"type":"Point"}
}