{
  "type": "Feature",
  "properties": {
    "iso:country":"DE",
    "sg:address":"R\u00f6merstr. 9",
    "sg:city":"Kissing",
    "sg:phone":"+49 8233/8905",
    "sg:postcode":"86438",
    "sg:province":"Bayern",
    "wof:name":"Maximilian Offner",
    "wof:placetype":"venue"
},
  "geometry": {"coordinates":[10.9625396729,48.2937011719],"type":"Point"}
}