{
  "type": "Feature",
  "properties": {
    "iso:country":"DE",
    "sg:address":"Friedrich-Ebert-Str. 79",
    "sg:city":"Essen",
    "sg:phone":"+49 201/2438842",
    "sg:postcode":"45127",
    "sg:province":"Nordrhein-Westfalen",
    "wof:name":"Cyber Systems Moussa Zias Und",
    "wof:placetype":"venue"
},
  "geometry": {"coordinates":[7.0101327896,51.4610710144],"type":"Point"}
}