{
  "type": "Feature",
  "properties": {
    "iso:country":"DE",
    "sg:address":"Sch\u00f6ne Aussicht 1",
    "sg:city":"Hohenstein",
    "sg:phone":"+49 6120/3331",
    "sg:postcode":"65329",
    "sg:province":"Hessen",
    "wof:name":"C. Ochs",
    "wof:placetype":"venue"
},
  "geometry": {"coordinates":[8.093537,50.19326],"type":"Point"}
}