{
  "type": "Feature",
  "properties": {
    "iso:country":"DE",
    "sg:address":"Scharnstr. 2",
    "sg:city":"Xanten",
    "sg:phone":"+49 2801/3346",
    "sg:postcode":"46509",
    "sg:province":"Nordrhein-Westfalen",
    "wof:name":"Gerhard Tebart",
    "wof:placetype":"venue"
},
  "geometry": {"coordinates":[6.45522,51.661282],"type":"Point"}
}