{
  "type": "Feature",
  "properties": {
    "iso:country":"DE",
    "sg:address":"Blumenthaler Str. 19",
    "sg:city":"Schleiden",
    "sg:phone":"+49 2445/7880",
    "sg:postcode":"53937",
    "sg:province":"Nordrhein-Westfalen",
    "wof:name":"Reidt Und Pelzer Rechtsanw\u00e4lte",
    "wof:placetype":"venue"
},
  "geometry": {"coordinates":[6.4723339081,50.5256538391],"type":"Point"}
}