{
  "type": "Feature",
  "properties": {
    "iso:country":"DE",
    "sg:address":"Starenstr. 24",
    "sg:city":"Versmold",
    "sg:phone":"+49 5423/43441",
    "sg:postcode":"33775",
    "sg:province":"Nordrhein-Westfalen",
    "wof:name":"M. Siekmann",
    "wof:placetype":"venue"
},
  "geometry": {"coordinates":[8.1248512268,52.0184822083],"type":"Point"}
}