{
  "type": "Feature",
  "properties": {
    "iso:country":"DE",
    "sg:address":"Lessingstr. 34",
    "sg:city":"Karlsruhe",
    "sg:phone":"+49 721/844469",
    "sg:postcode":"76135",
    "sg:province":"Baden-W\u00fcrttemberg",
    "wof:name":"Harald Fischer",
    "wof:placetype":"venue"
},
  "geometry": {"coordinates":[8.3850269318,49.0084648132],"type":"Point"}
}