{
  "type": "Feature",
  "properties": {
    "iso:country":"DE",
    "sg:address":"Betziner Weg 13",
    "sg:city":"Fehrbellin",
    "sg:phone":"+49 33932/70247",
    "sg:postcode":"16833",
    "sg:province":"Brandenburg",
    "wof:name":"L\u00e4ndchen Bellin Landtechnik & Service Gmbh",
    "wof:placetype":"venue"
},
  "geometry": {"coordinates":[12.77485,52.803047],"type":"Point"}
}