{
  "type": "Feature",
  "properties": {
    "iso:country":"DE",
    "sg:address":"Neuer Steinweg 7",
    "sg:city":"Gardelegen",
    "sg:phone":"+49 3907/711818",
    "sg:postcode":"39638",
    "sg:province":"Sachsen-Anhalt",
    "wof:name":"Teichmann & Wust Automobile Gmbh",
    "wof:placetype":"venue"
},
  "geometry": {"coordinates":[11.3742637634,52.5258140564],"type":"Point"}
}