{
  "type": "Feature",
  "properties": {
    "iso:country":"DE",
    "sg:address":"Hofmannstr. 22",
    "sg:city":"M\u00fcnchen",
    "sg:postcode":"81379",
    "sg:province":"Bayern",
    "wof:name":"Bettina H\u00e4usler Tennislehrer",
    "wof:placetype":"venue"
},
  "geometry": {"coordinates":[11.5289850235,48.0999794006],"type":"Point"}
}