{
  "type": "Feature",
  "properties": {
    "iso:country":"DE",
    "sg:address":"Asper Str. 21",
    "sg:city":"Bad Salzuflen",
    "sg:phone":"+49 5222/82505",
    "sg:postcode":"32108",
    "sg:province":"Nordrhein-Westfalen",
    "wof:name":"Christiane H\u00f6rbelt",
    "wof:placetype":"venue"
},
  "geometry": {"coordinates":[8.74724,52.068668],"type":"Point"}
}