{
  "type": "Feature",
  "properties": {
    "iso:country":"DE",
    "sg:address":"Im Br\u00fchl 3",
    "sg:city":"N\u00f6rdlingen",
    "sg:phone":"+49 9081/257722",
    "sg:postcode":"86720",
    "sg:province":"Bayern",
    "wof:name":"K-tech Elektronic Vertriebs Gmbh",
    "wof:placetype":"venue"
},
  "geometry": {"coordinates":[10.529978,48.87471],"type":"Point"}
}