{
  "type": "Feature",
  "properties": {
    "iso:country":"DE",
    "sg:address":"Geistbergstr. 23",
    "sg:city":"Buttenwiesen",
    "sg:phone":"+49 8274/92916",
    "sg:postcode":"86647",
    "sg:province":"Bayern",
    "wof:name":"Sylvia Stangl Steuerberaterin",
    "wof:placetype":"venue"
},
  "geometry": {"coordinates":[10.723608017,48.6077537537],"type":"Point"}
}