{
  "type": "Feature",
  "properties": {
    "iso:country":"DE",
    "sg:address":"Hoherodskopfstr. 16",
    "sg:city":"Frankfurt",
    "sg:phone":"+49 69/5484895",
    "sg:postcode":"60435",
    "sg:province":"Hessen",
    "wof:name":"Norbert Krenz Ingenieur",
    "wof:placetype":"venue"
},
  "geometry": {"coordinates":[8.6895589828,50.1519584656],"type":"Point"}
}