{
  "type": "Feature",
  "properties": {
    "iso:country":"DE",
    "sg:address":"Siemensstr. 11",
    "sg:city":"Schlierbach",
    "sg:phone":"+49 7021/71959",
    "sg:postcode":"73278",
    "sg:province":"Baden-W\u00fcrttemberg",
    "wof:name":"Tennishalle Schlierbach",
    "wof:placetype":"venue"
},
  "geometry": {"coordinates":[9.5304117203,48.6750679016],"type":"Point"}
}