{
  "type": "Feature",
  "properties": {
    "iso:country":"DE",
    "sg:address":"Stenzelring 23",
    "sg:city":"Hamburg",
    "sg:postcode":"21107",
    "sg:province":"Hamburg",
    "wof:name":"Setra Spedition Gmbh",
    "wof:placetype":"venue"
},
  "geometry": {"coordinates":[10.0059299469,53.5174636841],"type":"Point"}
}