{
  "type": "Feature",
  "properties": {
    "iso:country":"DE",
    "sg:address":"Oberstenfelder Str. 8",
    "sg:city":"Beilstein",
    "sg:phone":"+49 7062/3777",
    "sg:postcode":"71717",
    "sg:province":"Baden-W\u00fcrttemberg",
    "wof:name":"Ringer Gmbh",
    "wof:placetype":"venue"
},
  "geometry": {"coordinates":[9.316284,49.038231],"type":"Point"}
}