{
  "type": "Feature",
  "properties": {
    "iso:country":"DE",
    "sg:address":"Leopoldstr. 59",
    "sg:city":"M\u00fcnchen",
    "sg:phone":"+49 89/346126",
    "sg:postcode":"80802",
    "sg:province":"Bayern",
    "wof:name":"Dipl.-ing. Dieter Koppe Architekt",
    "wof:placetype":"venue"
},
  "geometry": {"coordinates":[11.585998,48.1614],"type":"Point"}
}