{
  "type": "Feature",
  "properties": {
    "iso:country":"DE",
    "sg:address":"C\u00e4cilienstr. 12",
    "sg:city":"D\u00fcsseldorf",
    "sg:phone":"+49 211/714727",
    "sg:postcode":"40597",
    "sg:province":"Nordrhein-Westfalen",
    "wof:name":"Dragan Dzelajlija",
    "wof:placetype":"venue"
},
  "geometry": {"coordinates":[6.8735928535,51.1645278931],"type":"Point"}
}