{
  "type": "Feature",
  "properties": {
    "iso:country":"DE",
    "sg:address":"Str. d. Pariser Kommune 29/31",
    "sg:city":"Berlin",
    "sg:phone":"+49 30/29049007",
    "sg:postcode":"10243",
    "sg:province":"Berlin",
    "wof:name":"Patchwork Und Quilting",
    "wof:placetype":"venue"
},
  "geometry": {"coordinates":[13.4399,52.515343],"type":"Point"}
}