{
  "type": "Feature",
  "properties": {
    "iso:country":"DE",
    "sg:address":"Leonhardstr. 26",
    "sg:city":"Heilbronn",
    "sg:phone":"+49 7131/31872",
    "sg:postcode":"74080",
    "sg:province":"Baden-W\u00fcrttemberg",
    "wof:name":"K\u00f6hler",
    "wof:placetype":"venue"
},
  "geometry": {"coordinates":[9.1929683685,49.1383972168],"type":"Point"}
}