{
  "type": "Feature",
  "properties": {
    "iso:country":"DE",
    "sg:address":"Steinhof 6",
    "sg:city":"Halberstadt",
    "sg:phone":"+49 3941/611066",
    "sg:postcode":"38820",
    "sg:province":"Sachsen-Anhalt",
    "wof:name":"Holz- Und Restaurations- Werkstatt Holger Vorrath Gmbh",
    "wof:placetype":"venue"
},
  "geometry": {"coordinates":[11.042163,51.895264],"type":"Point"}
}