{
  "type": "Feature",
  "properties": {
    "iso:country":"DE",
    "sg:address":"Pauluskirchstr. 7",
    "sg:city":"Wuppertal",
    "sg:phone":"+49 202/83606",
    "sg:postcode":"42285",
    "sg:province":"Nordrhein-Westfalen",
    "wof:name":"Prof. H. Sch\u00fctz Ingenieur",
    "wof:placetype":"venue"
},
  "geometry": {"coordinates":[7.1674361229,51.2596626282],"type":"Point"}
}