{
  "type": "Feature",
  "properties": {
    "iso:country":"DE",
    "sg:address":"Perfallstr. 1 a",
    "sg:city":"Schliersee",
    "sg:phone":"+49 8026/94819",
    "sg:postcode":"83727",
    "sg:province":"Bayern",
    "wof:name":"Kur-apotheke",
    "wof:placetype":"venue"
},
  "geometry": {"coordinates":[11.86226,47.734356],"type":"Point"}
}