{
  "type": "Feature",
  "properties": {
    "iso:country":"DE",
    "sg:address":"Enger Weg 5",
    "sg:city":"Schotten",
    "sg:phone":"+49 6045/1393",
    "sg:postcode":"63679",
    "sg:province":"Hessen",
    "wof:name":"E. Beuler Inh. Kai John Greene",
    "wof:placetype":"venue"
},
  "geometry": {"coordinates":[9.240281105,50.4791755676],"type":"Point"}
}