{
  "type": "Feature",
  "properties": {
    "iso:country":"DE",
    "sg:address":"Weidenstr. 5",
    "sg:city":"Baienfurt",
    "sg:phone":"+49 751/43464",
    "sg:postcode":"88255",
    "sg:province":"Baden-W\u00fcrttemberg",
    "wof:name":"Benedikt Oberhofer",
    "wof:placetype":"venue"
},
  "geometry": {"coordinates":[9.635251,47.829254],"type":"Point"}
}