{
  "type": "Feature",
  "properties": {
    "iso:country":"DE",
    "sg:address":"Magdeburger Landstr.",
    "sg:city":"Brandenburg",
    "sg:phone":"+49 3381/34040",
    "sg:postcode":"14770",
    "sg:province":"Brandenburg",
    "wof:name":"Itb Industrietransportges. Mbh",
    "wof:placetype":"venue"
},
  "geometry": {"coordinates":[12.5040903091,52.4144325256],"type":"Point"}
}