{
  "type": "Feature",
  "properties": {
    "iso:country":"DE",
    "sg:address":"Schillerstr. 19",
    "sg:city":"Selzen",
    "sg:phone":"+49 6737/352",
    "sg:postcode":"55278",
    "sg:province":"Rheinland-Pfalz",
    "wof:name":"Adolf Heimlich Ingenieur",
    "wof:placetype":"venue"
},
  "geometry": {"coordinates":[8.2535200119,49.8668708801],"type":"Point"}
}