{
  "type": "Feature",
  "properties": {
    "iso:country":"DE",
    "sg:address":"Zehdenicker Strasse 21",
    "sg:city":"Berlin",
    "sg:phone":"+49 30/44350443",
    "sg:postcode":"10119",
    "sg:province":"Berlin",
    "wof:name":"Datenflug",
    "wof:placetype":"venue"
},
  "geometry": {"coordinates":[13.404985,52.53064],"type":"Point"}
}