{
  "type": "Feature",
  "properties": {
    "iso:country":"DE",
    "sg:address":"Borsteler Dorfstr. 82",
    "sg:city":"Verden",
    "sg:phone":"+49 4231/61206",
    "sg:postcode":"27283",
    "sg:province":"Niedersachsen",
    "wof:name":"Joh. Burdorf Ingenieur",
    "wof:placetype":"venue"
},
  "geometry": {"coordinates":[9.2649507523,52.9196891785],"type":"Point"}
}