{
  "type": "Feature",
  "properties": {
    "iso:country":"DE",
    "sg:address":"Bismarckstr. 21",
    "sg:city":"Edingen-Neckarhausen",
    "sg:phone":"+49 6203/83490",
    "sg:postcode":"68535",
    "sg:province":"Baden-W\u00fcrttemberg",
    "wof:name":"Apartment-hotel",
    "wof:placetype":"venue"
},
  "geometry": {"coordinates":[8.6073360443,49.4497032166],"type":"Point"}
}