{
  "type": "Feature",
  "properties": {
    "iso:country":"DE",
    "sg:address":"Erlenweg",
    "sg:city":"Grenzach-Wyhlen",
    "sg:phone":"+49 7624/7602",
    "sg:postcode":"79639",
    "sg:province":"Baden-W\u00fcrttemberg",
    "wof:name":"Fliesenbau G. Stiefvater Und Sohn Gmbh",
    "wof:placetype":"venue"
},
  "geometry": {"coordinates":[7.6648888588,47.5585594177],"type":"Point"}
}