{
  "type": "Feature",
  "properties": {
    "iso:country":"DE",
    "sg:address":"Finkenpfad 2",
    "sg:city":"Bad D\u00fcrkheim",
    "sg:phone":"+49 6322/7458",
    "sg:postcode":"67098",
    "sg:province":"Rheinland-Pfalz",
    "wof:name":"Martin Schatz Weinanbau",
    "wof:placetype":"venue"
},
  "geometry": {"coordinates":[8.1647500992,49.4584579468],"type":"Point"}
}