{
  "type": "Feature",
  "properties": {
    "iso:country":"DE",
    "sg:address":"Petersaurach",
    "sg:city":"Petersaurach",
    "sg:phone":"+49 9872/7746",
    "sg:postcode":"91580",
    "sg:province":"Bayern",
    "wof:name":"Raiffeisenbank Heilsbronn Eg",
    "wof:placetype":"venue"
},
  "geometry": {"coordinates":[10.747345,49.31023],"type":"Point"}
}