{
  "type": "Feature",
  "properties": {
    "iso:country":"DE",
    "sg:address":"Rotzingen 52",
    "sg:city":"G\u00f6rwihl",
    "sg:phone":"+49 4977/547175",
    "sg:postcode":"79733",
    "sg:province":"Baden-W\u00fcrttemberg",
    "wof:name":"Herbert Brugger",
    "wof:placetype":"venue"
},
  "geometry": {"coordinates":[8.074244,47.667622],"type":"Point"}
}