{
  "type": "Feature",
  "properties": {
    "iso:country":"DE",
    "sg:address":"Alter Postweg 2",
    "sg:city":"Borkum",
    "sg:phone":"+49 4922/1001",
    "sg:postcode":"26757",
    "sg:province":"Niedersachsen",
    "wof:name":"Borkumer Taxengemeinschaft",
    "wof:placetype":"venue"
},
  "geometry": {"coordinates":[6.662944,53.588009],"type":"Point"}
}