{
  "type": "Feature",
  "properties": {
    "iso:country":"DE",
    "sg:address":"Leitenweg 12a",
    "sg:city":"Burgthann",
    "sg:phone":"+49 9183/4311",
    "sg:postcode":"90559",
    "sg:province":"Bayern",
    "wof:name":"Helga Worthen",
    "wof:placetype":"venue"
},
  "geometry": {"coordinates":[11.3092508316,49.3216285706],"type":"Point"}
}