{
  "type": "Feature",
  "properties": {
    "iso:country":"DE",
    "sg:address":"Heidstr. 114",
    "sg:city":"Herne",
    "sg:phone":"+49 2325/70630",
    "sg:postcode":"44649",
    "sg:province":"Nordrhein-Westfalen",
    "wof:name":"Karl Nolte",
    "wof:placetype":"venue"
},
  "geometry": {"coordinates":[7.159584,51.539215],"type":"Point"}
}