{
  "type": "Feature",
  "properties": {
    "iso:country":"DE",
    "sg:address":"Dorfstr. 19",
    "sg:city":"Briesen",
    "sg:phone":"+49 35606/225",
    "sg:postcode":"03096",
    "sg:province":"Brandenburg",
    "wof:name":"Wurm",
    "wof:placetype":"venue"
},
  "geometry": {"coordinates":[14.244441,51.815609],"type":"Point"}
}