{
  "type": "Feature",
  "properties": {
    "iso:country":"DE",
    "sg:address":"Sorbenstr 39",
    "sg:city":"Hamburg",
    "sg:phone":"+49 40/25497727",
    "sg:postcode":"20537",
    "sg:province":"Hamburg",
    "wof:name":"Cabao Warenhandels Gmbh",
    "wof:placetype":"venue"
},
  "geometry": {"coordinates":[10.043418,53.550095],"type":"Point"}
}