{
  "type": "Feature",
  "properties": {
    "iso:country":"DE",
    "sg:address":"Zerresweg 3",
    "sg:city":"Viersen",
    "sg:phone":"+49 2162/67722",
    "sg:postcode":"41749",
    "sg:province":"Nordrhein-Westfalen",
    "wof:name":"Hubert L\u00fcngen",
    "wof:placetype":"venue"
},
  "geometry": {"coordinates":[6.336078,51.306843],"type":"Point"}
}