{
  "type": "Feature",
  "properties": {
    "iso:country":"DE",
    "sg:address":"Liebenauer Str. 18",
    "sg:city":"Binnen",
    "sg:phone":"+49 5023/598",
    "sg:postcode":"31619",
    "sg:province":"Niedersachsen",
    "wof:name":"Fritz Sch\u00e4fer",
    "wof:placetype":"venue"
},
  "geometry": {"coordinates":[9.126017,52.625107],"type":"Point"}
}