{
  "type": "Feature",
  "properties": {
    "iso:country":"DE",
    "sg:address":"Alter Stadtweg 3",
    "sg:city":"Ro\u00dfdorf",
    "sg:phone":"+49 6154/9558",
    "sg:postcode":"64380",
    "sg:province":"Hessen",
    "wof:name":"I. Dietz",
    "wof:placetype":"venue"
},
  "geometry": {"coordinates":[8.748708725,49.8589744568],"type":"Point"}
}