{
  "type": "Feature",
  "properties": {
    "iso:country":"DE",
    "sg:address":"Regelsmais",
    "sg:city":"Michelsneukirchen",
    "sg:phone":"+49 9467/268",
    "sg:postcode":"93185",
    "sg:province":"Bayern",
    "wof:name":"Daniel",
    "wof:placetype":"venue"
},
  "geometry": {"coordinates":[12.563949585,49.1109886169],"type":"Point"}
}