{
  "type": "Feature",
  "properties": {
    "iso:country":"DE",
    "sg:address":"Obere Str. 2",
    "sg:city":"Rosdorf",
    "sg:phone":"+49 551/781517",
    "sg:postcode":"37124",
    "sg:province":"Niedersachsen",
    "wof:name":"Athen",
    "wof:placetype":"venue"
},
  "geometry": {"coordinates":[9.8960208893,51.5059432983],"type":"Point"}
}