{
  "type": "Feature",
  "properties": {
    "iso:country":"DE",
    "sg:address":"Wilhelmsh\u00f6her Allee 347",
    "sg:city":"Kassel",
    "sg:postcode":"34131",
    "sg:province":"Hessen",
    "wof:name":"Hessischer Rundfunk Studio Kassel",
    "wof:placetype":"venue"
},
  "geometry": {"coordinates":[9.429895401,51.3132591248],"type":"Point"}
}