{
  "type": "Feature",
  "properties": {
    "iso:country":"DE",
    "sg:address":"Luitpoldstr. 15",
    "sg:city":"Wei\u00dfenburg",
    "sg:phone":"+49 9141/6516",
    "sg:postcode":"91781",
    "sg:province":"Bayern",
    "wof:name":"Erica Moden",
    "wof:placetype":"venue"
},
  "geometry": {"coordinates":[10.974131,49.030869],"type":"Point"}
}