{
  "type": "Feature",
  "properties": {
    "iso:country":"DE",
    "sg:address":"Auerstr. 113",
    "sg:city":"Coswig",
    "sg:phone":"+49 3523/73272",
    "sg:postcode":"01640",
    "sg:province":"Sachsen",
    "wof:name":"Helmut K\u00fchn",
    "wof:placetype":"venue"
},
  "geometry": {"coordinates":[13.564609,51.137932],"type":"Point"}
}