{
  "type": "Feature",
  "properties": {
    "iso:country":"DE",
    "sg:address":"Harrenst\u00e4tter Str. 29",
    "sg:city":"Werlte",
    "sg:phone":"+49 5951/5199",
    "sg:postcode":"49757",
    "sg:province":"Niedersachsen",
    "wof:name":"Walter Flentje",
    "wof:placetype":"venue"
},
  "geometry": {"coordinates":[7.6678080559,52.8556900024],"type":"Point"}
}