{
  "type": "Feature",
  "properties": {
    "iso:country":"DE",
    "sg:address":"K\u00f6nigsh\u00fctter Str. 13",
    "sg:city":"Elbingerode",
    "sg:phone":"+49 39454/4710",
    "sg:postcode":"38875",
    "sg:province":"Sachsen-Anhalt",
    "wof:name":"Borek Harzer Metallbearbeitung Gmbh",
    "wof:placetype":"venue"
},
  "geometry": {"coordinates":[10.785445,51.765789],"type":"Point"}
}