{
  "type": "Feature",
  "properties": {
    "iso:country":"DE",
    "sg:address":"Siemensstr 3",
    "sg:city":"Jettingen-Scheppach",
    "sg:phone":"+49 8225/309060",
    "sg:postcode":"89343",
    "sg:province":"Bayern",
    "wof:name":"Mitrovic",
    "wof:placetype":"venue"
},
  "geometry": {"coordinates":[10.443403,48.410507],"type":"Point"}
}