{
  "type": "Feature",
  "properties": {
    "iso:country":"DE",
    "sg:address":"Lindenstr. 10",
    "sg:city":"Deggendorf",
    "sg:phone":"+49 991/5934",
    "sg:postcode":"94469",
    "sg:province":"Bayern",
    "wof:name":"Rainer Bressler",
    "wof:placetype":"venue"
},
  "geometry": {"coordinates":[12.9654426575,48.8359222412],"type":"Point"}
}