{
  "type": "Feature",
  "properties": {
    "iso:country":"DE",
    "sg:address":"Buchenweg 2",
    "sg:city":"Rockenberg",
    "sg:phone":"+49 6033/970797",
    "sg:postcode":"35519",
    "sg:province":"Hessen",
    "wof:name":"P. Heim Makler",
    "wof:placetype":"venue"
},
  "geometry": {"coordinates":[8.7417497635,50.4209098816],"type":"Point"}
}