{
  "type": "Feature",
  "properties": {
    "iso:country":"DE",
    "sg:address":"Mannheimer Str. 153",
    "sg:city":"Bad Kreuznach",
    "sg:phone":"+49 671/31963",
    "sg:postcode":"55543",
    "sg:province":"Rheinland-Pfalz",
    "wof:name":"Eberhart Grundst\u00fccks- Gmbh & Co. Kg",
    "wof:placetype":"venue"
},
  "geometry": {"coordinates":[7.8615760803,49.8426704407],"type":"Point"}
}