{
  "type": "Feature",
  "properties": {
    "iso:country":"DE",
    "sg:address":"Hauptstr. 53-55",
    "sg:city":"Eppelheim",
    "sg:phone":"+49 6221/764546",
    "sg:postcode":"69214",
    "sg:province":"Baden-W\u00fcrttemberg",
    "wof:name":"Die Brillenmacher Gmbh",
    "wof:placetype":"venue"
},
  "geometry": {"coordinates":[8.6318130493,49.4009857178],"type":"Point"}
}