{
  "type": "Feature",
  "properties": {
    "iso:country":"DE",
    "sg:address":"Im Gewerbegel\u00e4nde 37",
    "sg:city":"Norderney",
    "sg:phone":"+49 4932/491",
    "sg:postcode":"26548",
    "sg:province":"Niedersachsen",
    "wof:name":"E. Und G. Bethke",
    "wof:placetype":"venue"
},
  "geometry": {"coordinates":[7.174783,53.709946],"type":"Point"}
}