{
  "type": "Feature",
  "properties": {
    "iso:country":"DE",
    "sg:address":"Willeberge",
    "sg:city":"Ochtrup",
    "sg:phone":"+49 2553/3487",
    "sg:postcode":"48607",
    "sg:province":"Nordrhein-Westfalen",
    "wof:name":"Alter Posthof",
    "wof:placetype":"venue"
},
  "geometry": {"coordinates":[7.2587890625,52.1991844177],"type":"Point"}
}