{
  "type": "Feature",
  "properties": {
    "iso:country":"DE",
    "sg:address":"Silcherstr. 2",
    "sg:city":"Schn\u00fcrpflingen",
    "sg:phone":"+49 7346/96110",
    "sg:postcode":"89194",
    "sg:province":"Baden-W\u00fcrttemberg",
    "wof:name":"Raiffeisenbank Donau-iller Eg",
    "wof:placetype":"venue"
},
  "geometry": {"coordinates":[9.991915,48.272964],"type":"Point"}
}