{
  "type": "Feature",
  "properties": {
    "iso:country":"DE",
    "sg:address":"Schiffenbergstr. 42",
    "sg:city":"Pohlheim",
    "sg:phone":"+49 6404/5625",
    "sg:postcode":"35415",
    "sg:province":"Hessen",
    "wof:name":"Gerhard G\u00f6rlach",
    "wof:placetype":"venue"
},
  "geometry": {"coordinates":[8.744585,50.541599],"type":"Point"}
}