{
  "type": "Feature",
  "properties": {
    "iso:country":"DE",
    "sg:address":"Brennender Berg Str. 9",
    "sg:city":"Saarbr\u00fccken",
    "sg:phone":"+49 6897/72585",
    "sg:postcode":"66125",
    "sg:province":"Saarland",
    "wof:name":"Helene Braun",
    "wof:placetype":"venue"
},
  "geometry": {"coordinates":[7.0464291573,49.2834014893],"type":"Point"}
}