{
  "type": "Feature",
  "properties": {
    "iso:country":"DE",
    "sg:address":"Altd\u00f6lzschen 32",
    "sg:city":"Dresden",
    "sg:phone":"+49 351/4116434",
    "sg:postcode":"01187",
    "sg:province":"Sachsen",
    "wof:name":"Cdc Intenational Gmbh",
    "wof:placetype":"venue"
},
  "geometry": {"coordinates":[13.6872081757,51.025100708],"type":"Point"}
}