{
  "type": "Feature",
  "properties": {
    "iso:country":"DE",
    "sg:address":"Lange Str. 30",
    "sg:city":"Velen",
    "sg:phone":"+49 2863/923802",
    "sg:postcode":"46342",
    "sg:province":"Nordrhein-Westfalen",
    "wof:name":"S. R\u00f6\u00dfing-witting Rechtsanwalt",
    "wof:placetype":"venue"
},
  "geometry": {"coordinates":[6.9721989632,51.8927536011],"type":"Point"}
}