{
  "type": "Feature",
  "properties": {
    "iso:country":"DE",
    "sg:address":"Adlerstr. 2",
    "sg:city":"Rohrdorf",
    "sg:phone":"+49 8031/72240",
    "sg:postcode":"83101",
    "sg:province":"Bayern",
    "wof:name":"Sengewald Klinikprodukte Verwaltungsges. Mbh",
    "wof:placetype":"venue"
},
  "geometry": {"coordinates":[12.1554441452,47.8280448914],"type":"Point"}
}