{
  "type": "Feature",
  "properties": {
    "iso:country":"DE",
    "sg:address":"Hofstr. 15",
    "sg:city":"M\u00f6nchengladbach",
    "sg:phone":"+49 2161/23291",
    "sg:postcode":"41065",
    "sg:province":"Nordrhein-Westfalen",
    "wof:name":"Kurt Cremer",
    "wof:placetype":"venue"
},
  "geometry": {"coordinates":[6.441757,51.184765],"type":"Point"}
}