{
  "type": "Feature",
  "properties": {
    "iso:country":"DE",
    "sg:address":"Am Steineb\u00fchl 6",
    "sg:city":"Krugzell",
    "sg:postcode":"87452",
    "sg:province":"Bayern",
    "wof:name":"Www.berichts-heft.de",
    "wof:placetype":"venue"
},
  "geometry": {"coordinates":[10.213572,47.80629],"type":"Point"}
}