{
  "type": "Feature",
  "properties": {
    "iso:country":"DE",
    "sg:address":"Max-Eyth-Str. 21",
    "sg:city":"Fellbach",
    "sg:phone":"+49 711/5172452",
    "sg:postcode":"70736",
    "sg:province":"Baden-W\u00fcrttemberg",
    "wof:name":"Atlon Gmbh",
    "wof:placetype":"venue"
},
  "geometry": {"coordinates":[9.252533,48.843296],"type":"Point"}
}