{
  "type": "Feature",
  "properties": {
    "iso:country":"DE",
    "sg:address":"Kreuzbergweg 10",
    "sg:city":"Scheidegg",
    "sg:phone":"+49 8381/82666",
    "sg:postcode":"88175",
    "sg:province":"Bayern",
    "wof:name":"Wolfgang Altmeyer Steuerberater",
    "wof:placetype":"venue"
},
  "geometry": {"coordinates":[9.8497018814,47.5806159973],"type":"Point"}
}