{
  "type": "Feature",
  "properties": {
    "iso:country":"DE",
    "sg:address":"Thyrsusstr. 10",
    "sg:city":"Trier",
    "sg:phone":"+49 651/149276",
    "sg:postcode":"54292",
    "sg:province":"Rheinland-Pfalz",
    "wof:name":"Lvm-versicherungen P. Gebert",
    "wof:placetype":"venue"
},
  "geometry": {"coordinates":[6.655356884,49.7659797668],"type":"Point"}
}