{
  "type": "Feature",
  "properties": {
    "iso:country":"DE",
    "sg:address":"Marktstr. 24",
    "sg:city":"Pritzwalk",
    "sg:phone":"+49 3395/302912",
    "sg:postcode":"16928",
    "sg:province":"Brandenburg",
    "wof:name":"Erika Horstmann",
    "wof:placetype":"venue"
},
  "geometry": {"coordinates":[12.179161,53.149536],"type":"Point"}
}