{
  "type": "Feature",
  "properties": {
    "iso:country":"DE",
    "sg:address":"Buchenweg 10",
    "sg:city":"Altena",
    "sg:phone":"+49 2352/97880",
    "sg:postcode":"58762",
    "sg:province":"Nordrhein-Westfalen",
    "wof:name":"Dtp-studio Rentrop Gmbh",
    "wof:placetype":"venue"
},
  "geometry": {"coordinates":[7.7501220703,51.2953987122],"type":"Point"}
}