{
  "type": "Feature",
  "properties": {
    "iso:country":"DE",
    "sg:address":"Eisbergweg 5",
    "sg:city":"Amberg",
    "sg:phone":"+49 9621/33472",
    "sg:postcode":"92224",
    "sg:province":"Bayern",
    "wof:name":"Peter D\u00fcrr",
    "wof:placetype":"venue"
},
  "geometry": {"coordinates":[11.848132,49.44854],"type":"Point"}
}