{
  "type": "Feature",
  "properties": {
    "iso:country":"DE",
    "sg:address":"Schwenkstr. 2",
    "sg:city":"Dresden",
    "sg:phone":"+49 351/2684108",
    "sg:postcode":"01326",
    "sg:province":"Sachsen",
    "wof:name":"Dipl.-ing. M. Petrow Ingenieur",
    "wof:placetype":"venue"
},
  "geometry": {"coordinates":[13.8305597305,51.0400428772],"type":"Point"}
}