{
  "type": "Feature",
  "properties": {
    "iso:country":"DE",
    "sg:address":"Stargarder Str. 18",
    "sg:city":"Bielefeld",
    "sg:phone":"+49 521/64188",
    "sg:postcode":"33699",
    "sg:province":"Nordrhein-Westfalen",
    "wof:name":"Willi Leisner Gesellschaft Mbh",
    "wof:placetype":"venue"
},
  "geometry": {"coordinates":[8.6062870026,51.9965858459],"type":"Point"}
}