{
  "type": "Feature",
  "properties": {
    "iso:country":"DE",
    "sg:address":"Ortsstrasse 82",
    "sg:city":"Moersdorf",
    "sg:phone":"+49 36428/54741",
    "sg:postcode":"07646",
    "sg:province":"Th\u00fcringen",
    "wof:name":"Willkommen Bei Www.nureinenacht.de",
    "wof:placetype":"venue"
},
  "geometry": {"coordinates":[11.75468,50.847301],"type":"Point"}
}