{
  "type": "Feature",
  "properties": {
    "iso:country":"DE",
    "sg:address":"Berchinger Str. 27",
    "sg:city":"Freystadt",
    "sg:phone":"+49 9179/94910",
    "sg:postcode":"92342",
    "sg:province":"Bayern",
    "wof:name":"Bay-wa-ag Lagerhaus",
    "wof:placetype":"venue"
},
  "geometry": {"coordinates":[11.33369,49.195625],"type":"Point"}
}