{
  "type": "Feature",
  "properties": {
    "iso:country":"DE",
    "sg:address":"Auf dem Knust 25",
    "sg:city":"Bochum",
    "sg:phone":"+49 234/923690",
    "sg:postcode":"44805",
    "sg:province":"Nordrhein-Westfalen",
    "wof:name":"Globoplan Ingenieurgesellschaft Mbh",
    "wof:placetype":"venue"
},
  "geometry": {"coordinates":[7.2773680687,51.497833252],"type":"Point"}
}