{
  "type": "Feature",
  "properties": {
    "iso:country":"DE",
    "sg:address":"Eichstr. 13",
    "sg:city":"Hessisch Oldendorf",
    "sg:phone":"+49 5152/51183",
    "sg:postcode":"31840",
    "sg:province":"Niedersachsen",
    "wof:name":"Inge Szymanski-mentzel",
    "wof:placetype":"venue"
},
  "geometry": {"coordinates":[9.214849472,52.1853408813],"type":"Point"}
}