{
  "type": "Feature",
  "properties": {
    "iso:country":"DE",
    "sg:address":"Br\u00fcckenstr. 2",
    "sg:city":"Neu-Ulm",
    "sg:phone":"+49 731/724022",
    "sg:postcode":"89231",
    "sg:province":"Bayern",
    "wof:name":"Eyermann Und Weinberger",
    "wof:placetype":"venue"
},
  "geometry": {"coordinates":[10.0043096542,48.3980140686],"type":"Point"}
}