{
  "type": "Feature",
  "properties": {
    "iso:country":"DE",
    "sg:address":"Goetheallee 4 a",
    "sg:city":"G\u00f6ttingen",
    "sg:phone":"+49 551/42952",
    "sg:postcode":"37073",
    "sg:province":"Niedersachsen",
    "wof:name":"Sch\u00e4fer-allianz",
    "wof:placetype":"venue"
},
  "geometry": {"coordinates":[9.9302568436,51.5347671509],"type":"Point"}
}