{
  "type": "Feature",
  "properties": {
    "iso:country":"DE",
    "sg:address":"Anton-Gabele-Str. 8",
    "sg:city":"Me\u00dfkirch",
    "sg:phone":"+49 7575/93262",
    "sg:postcode":"88605",
    "sg:province":"Baden-W\u00fcrttemberg",
    "wof:name":"Klaus Klaiber",
    "wof:placetype":"venue"
},
  "geometry": {"coordinates":[9.130273819,48.0035552979],"type":"Point"}
}