{
  "type": "Feature",
  "properties": {
    "iso:country":"DE",
    "sg:address":"Harburger Str. 4",
    "sg:city":"Buxtehude",
    "sg:postcode":"21614",
    "sg:province":"Niedersachsen",
    "wof:name":"Bs Schiffsbeteiligungs- Gesellschaft Mbh",
    "wof:placetype":"venue"
},
  "geometry": {"coordinates":[9.704246,53.477715],"type":"Point"}
}