{
  "type": "Feature",
  "properties": {
    "iso:country":"DE",
    "sg:address":"Kasselerstr.",
    "sg:city":"Dillenburg",
    "sg:phone":"+49 4927/713900",
    "sg:postcode":"35683",
    "sg:province":"Hessen",
    "wof:name":"Thyssenkrupp Nirosta Gmbh",
    "wof:placetype":"venue"
},
  "geometry": {"coordinates":[8.276786,50.748997],"type":"Point"}
}