{
  "type": "Feature",
  "properties": {
    "iso:country":"DE",
    "sg:address":"L\u00fctjenhorner Str. 13",
    "sg:city":"Achtrup",
    "sg:phone":"+49 4662/3296",
    "sg:postcode":"25917",
    "sg:province":"Schleswig-Holstein",
    "wof:name":"Peter Johannsen",
    "wof:placetype":"venue"
},
  "geometry": {"coordinates":[9.090466,54.795311],"type":"Point"}
}