{
  "type": "Feature",
  "properties": {
    "iso:country":"DE",
    "sg:address":"Kurstr. 7",
    "sg:city":"Bad Nauheim",
    "sg:phone":"+49 6032/2578",
    "sg:postcode":"61231",
    "sg:province":"Hessen",
    "wof:name":"Detlev Wegge",
    "wof:placetype":"venue"
},
  "geometry": {"coordinates":[8.74077034,50.3645896912],"type":"Point"}
}