{
  "type": "Feature",
  "properties": {
    "iso:country":"DE",
    "sg:address":"Alt-Hesepertwist 92",
    "sg:city":"Twist",
    "sg:phone":"+49 5936/477",
    "sg:postcode":"49767",
    "sg:province":"Niedersachsen",
    "wof:name":"Heinrich B\u00fcld",
    "wof:placetype":"venue"
},
  "geometry": {"coordinates":[7.117471,52.606422],"type":"Point"}
}