{
  "type": "Feature",
  "properties": {
    "iso:country":"DE",
    "sg:address":"Buchbergstr. 12",
    "sg:city":"Gottmadingen",
    "sg:phone":"+49 761/5950693",
    "sg:postcode":"78244",
    "sg:province":"Baden-W\u00fcrttemberg",
    "wof:name":"Dr. Med. Eberhard Storch Arzt F\u00fcr Allgemeinmedizin",
    "wof:placetype":"venue"
},
  "geometry": {"coordinates":[8.7539577484,47.7504425049],"type":"Point"}
}