{
  "type": "Feature",
  "properties": {
    "iso:country":"DE",
    "sg:address":"Kleine Weilstr. 23",
    "sg:city":"Hattingen",
    "sg:phone":"+49 2324/23377",
    "sg:postcode":"45525",
    "sg:province":"Nordrhein-Westfalen",
    "wof:name":"Stratmann Bestattungen",
    "wof:placetype":"venue"
},
  "geometry": {"coordinates":[7.183567,51.398998],"type":"Point"}
}