{
  "type": "Feature",
  "properties": {
    "iso:country":"DE",
    "sg:address":"Lobitzweg 1",
    "sg:city":"Berlin",
    "sg:phone":"+49 30/9309908",
    "sg:postcode":"12557",
    "sg:province":"Berlin",
    "wof:name":"Biex Handels Gmbh",
    "wof:placetype":"venue"
},
  "geometry": {"coordinates":[13.5865354538,52.4356307983],"type":"Point"}
}