{
  "type": "Feature",
  "properties": {
    "iso:country":"DE",
    "sg:address":"Braunstr. 21",
    "sg:city":"K\u00f6ln",
    "sg:phone":"+49 221/493300",
    "sg:postcode":"50933",
    "sg:province":"Nordrhein-Westfalen",
    "wof:name":"Heinrich Wolf",
    "wof:placetype":"venue"
},
  "geometry": {"coordinates":[6.8983168602,50.9362640381],"type":"Point"}
}