{
  "type": "Feature",
  "properties": {
    "iso:country":"DE",
    "sg:address":"Friesenstr.",
    "sg:city":"Langeoog",
    "sg:phone":"+49 4972/6658",
    "sg:postcode":"26465",
    "sg:province":"Niedersachsen",
    "wof:name":"Gastst\u00e4tte Tagungszentrum",
    "wof:placetype":"venue"
},
  "geometry": {"coordinates":[7.4759697914,53.7448806763],"type":"Point"}
}