{
  "type": "Feature",
  "properties": {
    "iso:country":"DE",
    "sg:address":"Am Hungerberg 16",
    "sg:city":"Niederaula",
    "sg:postcode":"36272",
    "sg:province":"Hessen",
    "wof:name":"Afs Software Beteiligungs Gmbh",
    "wof:placetype":"venue"
},
  "geometry": {"coordinates":[9.606806,50.802849],"type":"Point"}
}