{
  "type": "Feature",
  "properties": {
    "iso:country":"DE",
    "sg:address":"Markt 19",
    "sg:city":"Usedom",
    "sg:phone":"+49 38372/70743",
    "sg:postcode":"17406",
    "sg:province":"Mecklenburg-Vorpommern",
    "wof:name":"H.-g. Sch\u00f6nborn",
    "wof:placetype":"venue"
},
  "geometry": {"coordinates":[13.919796,53.87286],"type":"Point"}
}