{
  "type": "Feature",
  "properties": {
    "iso:country":"DE",
    "sg:address":"Gro\u00dfer Backhorn 20",
    "sg:city":"Ringstedt",
    "sg:phone":"+49 4708/369",
    "sg:postcode":"27624",
    "sg:province":"Niedersachsen",
    "wof:name":"D. Dlppolito",
    "wof:placetype":"venue"
},
  "geometry": {"coordinates":[8.857992,53.560577],"type":"Point"}
}