{
  "type": "Feature",
  "properties": {
    "iso:country":"DE",
    "sg:address":"Kirchstr. 27",
    "sg:city":"Bonn",
    "sg:phone":"+49 228/462554",
    "sg:postcode":"53227",
    "sg:province":"Nordrhein-Westfalen",
    "wof:name":"Christiane Schmitz",
    "wof:placetype":"venue"
},
  "geometry": {"coordinates":[7.1486868858,50.7291069031],"type":"Point"}
}