{
  "type": "Feature",
  "properties": {
    "iso:country":"DE",
    "sg:address":"Dorfstr 37",
    "sg:city":"Liesten",
    "sg:phone":"+49 39032/751",
    "sg:postcode":"29416",
    "sg:province":"Sachsen-Anhalt",
    "wof:name":"Lagertechnik Thilo Simlacher",
    "wof:placetype":"venue"
},
  "geometry": {"coordinates":[11.2903470993,52.7901916504],"type":"Point"}
}