{
  "type": "Feature",
  "properties": {
    "iso:country":"DE",
    "sg:address":"Alte M\u00fchlenstr. 24",
    "sg:city":"Teningen",
    "sg:phone":"+49 7641/43369",
    "sg:postcode":"79331",
    "sg:province":"Baden-W\u00fcrttemberg",
    "wof:name":"T. G\u00e4\u00dfler",
    "wof:placetype":"venue"
},
  "geometry": {"coordinates":[7.828116,48.159988],"type":"Point"}
}