{
  "type": "Feature",
  "properties": {
    "iso:country":"DE",
    "sg:address":"Blanker-Hans-Weg 8",
    "sg:city":"Sankt Peter-Ording",
    "sg:phone":"+49 4863/96600",
    "sg:postcode":"25826",
    "sg:province":"Schleswig-Holstein",
    "wof:name":"Germania Appartements",
    "wof:placetype":"venue"
},
  "geometry": {"coordinates":[8.6069364548,54.3136558533],"type":"Point"}
}