{
  "type": "Feature",
  "properties": {
    "iso:country":"DE",
    "sg:address":"Friedrichstr. 12",
    "sg:city":"Bad Nauheim",
    "sg:phone":"+49 6032/4624",
    "sg:postcode":"61231",
    "sg:province":"Hessen",
    "wof:name":"Gerhard Hachenburger",
    "wof:placetype":"venue"
},
  "geometry": {"coordinates":[8.7359247208,50.3645133972],"type":"Point"}
}