{
  "type": "Feature",
  "properties": {
    "iso:country":"DE",
    "sg:address":"Bahnhofstr. 20",
    "sg:city":"Osternienburg",
    "sg:phone":"+49 34973/21892",
    "sg:postcode":"06386",
    "sg:province":"Sachsen-Anhalt",
    "wof:name":"Fc Hertha",
    "wof:placetype":"venue"
},
  "geometry": {"coordinates":[12.0312242508,51.7908210754],"type":"Point"}
}