{
  "type": "Feature",
  "properties": {
    "iso:country":"DE",
    "sg:address":"Viktoriastr. 23",
    "sg:city":"Bochum",
    "sg:phone":"+49 234/67585",
    "sg:postcode":"44787",
    "sg:province":"Nordrhein-Westfalen",
    "wof:name":"Filmtheater-betriebe Heukeshoven & Co. Kg",
    "wof:placetype":"venue"
},
  "geometry": {"coordinates":[7.2161040306,51.4794158936],"type":"Point"}
}