{
  "type": "Feature",
  "properties": {
    "iso:country":"DE",
    "sg:address":"Gewerbegebiet",
    "sg:city":"Buechenbeuren",
    "sg:phone":"+49 6543",
    "sg:postcode":"55491",
    "sg:province":"Rheinland-Pfalz",
    "wof:name":"Qarp.de",
    "wof:placetype":"venue"
},
  "geometry": {"coordinates":[7.2769198418,49.9199676514],"type":"Point"}
}