{
  "type": "Feature",
  "properties": {
    "iso:country":"DE",
    "sg:address":"Deichstr. 27",
    "sg:city":"Hamburg",
    "sg:phone":"+49 40/36965410",
    "sg:postcode":"20459",
    "sg:province":"Hamburg",
    "wof:name":"Asware Consult Gmbh",
    "wof:placetype":"venue"
},
  "geometry": {"coordinates":[9.987397,53.545944],"type":"Point"}
}