{
  "type": "Feature",
  "properties": {
    "iso:country":"DE",
    "sg:address":"Schifferstr. 18",
    "sg:city":"Magdeburg",
    "sg:phone":"+49 391/5412221",
    "sg:postcode":"39106",
    "sg:province":"Sachsen-Anhalt",
    "wof:name":"China Restaurant Hong Kong Haus",
    "wof:placetype":"venue"
},
  "geometry": {"coordinates":[11.65209198,52.1425704956],"type":"Point"}
}