{
  "type": "Feature",
  "properties": {
    "iso:country":"DE",
    "sg:address":"Feldbergring 51",
    "sg:city":"Langenselbold",
    "sg:phone":"+49 6184/1835",
    "sg:postcode":"63505",
    "sg:province":"Hessen",
    "wof:name":"Otto Zirnzak Tennislehrer",
    "wof:placetype":"venue"
},
  "geometry": {"coordinates":[9.0244064331,50.1832084656],"type":"Point"}
}