{
  "type": "Feature",
  "properties": {
    "iso:country":"DE",
    "sg:address":"Neuh\u00f6ferstra\u00dfe 9",
    "sg:city":"Sulzfeld",
    "sg:phone":"+49 7269",
    "sg:postcode":"75056",
    "sg:province":"Baden-W\u00fcrttemberg",
    "wof:name":"Zweirad Schmidt",
    "wof:placetype":"venue"
},
  "geometry": {"coordinates":[8.859437,49.105297],"type":"Point"}
}