{
  "type": "Feature",
  "properties": {
    "iso:country":"DE",
    "sg:address":"Eldagser Postweg 2",
    "sg:city":"Petershagen",
    "sg:phone":"+49 5707/528",
    "sg:postcode":"32469",
    "sg:province":"Nordrhein-Westfalen",
    "wof:name":"Heinrich Dammeier",
    "wof:placetype":"venue"
},
  "geometry": {"coordinates":[8.948215,52.387764],"type":"Point"}
}