{
  "type": "Feature",
  "properties": {
    "iso:country":"DE",
    "sg:address":"St.-Martinus-Str. 1",
    "sg:city":"Bedburg",
    "sg:phone":"+49 2463/99160",
    "sg:postcode":"50181",
    "sg:province":"Nordrhein-Westfalen",
    "wof:name":"Hotel Deutsches Haus",
    "wof:placetype":"venue"
},
  "geometry": {"coordinates":[6.5427408218,51.0048599243],"type":"Point"}
}