{
  "type": "Feature",
  "properties": {
    "iso:country":"DE",
    "sg:address":"Henningweg 13",
    "sg:city":"Essen",
    "sg:phone":"+49 201/8715074",
    "sg:postcode":"45149",
    "sg:province":"Nordrhein-Westfalen",
    "wof:name":"Helga Blum Steuerberaterin",
    "wof:placetype":"venue"
},
  "geometry": {"coordinates":[6.9534611702,51.4197349548],"type":"Point"}
}