{
  "type": "Feature",
  "properties": {
    "iso:country":"DE",
    "sg:address":"Ahornweg 8",
    "sg:city":"Brackenheim",
    "sg:postcode":"74336",
    "sg:province":"Baden-W\u00fcrttemberg",
    "wof:name":"Linsner Datentechnik Gmbh",
    "wof:placetype":"venue"
},
  "geometry": {"coordinates":[9.0225,49.095268],"type":"Point"}
}