{
  "type": "Feature",
  "properties": {
    "iso:country":"DE",
    "sg:address":"Werner-von-Siemens-Str. 1",
    "sg:city":"Meckenheim",
    "sg:phone":"+49 2225/999980",
    "sg:postcode":"53340",
    "sg:province":"Nordrhein-Westfalen",
    "wof:name":"Linus Gmbh",
    "wof:placetype":"venue"
},
  "geometry": {"coordinates":[7.0153708458,50.6463165283],"type":"Point"}
}