{
  "type": "Feature",
  "properties": {
    "iso:country":"DE",
    "sg:address":"Bundesstr. 5 Nr. 62",
    "sg:city":"Hattstedt",
    "sg:phone":"+49 4846/339",
    "sg:postcode":"25856",
    "sg:province":"Schleswig-Holstein",
    "wof:name":"H. C. L\u00fcneburg",
    "wof:placetype":"venue"
},
  "geometry": {"coordinates":[9.0232801437,54.529499054],"type":"Point"}
}