{
  "type": "Feature",
  "properties": {
    "iso:country":"DE",
    "sg:address":"Geschwister-Scholl-Str. 34a",
    "sg:city":"Dingelst\u00e4dt",
    "sg:phone":"+49 36075/31210",
    "sg:postcode":"37351",
    "sg:province":"Th\u00fcringen",
    "wof:name":"Koch Und Partner Rechtsanw\u00e4lte",
    "wof:placetype":"venue"
},
  "geometry": {"coordinates":[10.3158731461,51.3152198792],"type":"Point"}
}