{
  "type": "Feature",
  "properties": {
    "iso:country":"DE",
    "sg:address":"Kreuznacher Str. 28",
    "sg:city":"Rockenhausen",
    "sg:phone":"+49 6361/7376",
    "sg:postcode":"67806",
    "sg:province":"Rheinland-Pfalz",
    "wof:name":"Ernst Kobelt",
    "wof:placetype":"venue"
},
  "geometry": {"coordinates":[7.8214039803,49.6305389404],"type":"Point"}
}