{
  "type": "Feature",
  "properties": {
    "iso:country":"DE",
    "sg:address":"Dorfstr. 45a",
    "sg:city":"Obercunnersdorf",
    "sg:phone":"+49 35875/209",
    "sg:postcode":"02708",
    "sg:province":"Sachsen",
    "wof:name":"P. Herold",
    "wof:placetype":"venue"
},
  "geometry": {"coordinates":[14.627378,51.030399],"type":"Point"}
}