{
  "type": "Feature",
  "properties": {
    "iso:country":"DE",
    "sg:address":"Otto-Hahn-Str 9",
    "sg:city":"Rodgau",
    "sg:phone":"+49 6106/649666",
    "sg:postcode":"63110",
    "sg:province":"Hessen",
    "wof:name":"Filtec Luftfilter Gmbh",
    "wof:placetype":"venue"
},
  "geometry": {"coordinates":[8.899985,50.023933],"type":"Point"}
}