{
  "type": "Feature",
  "properties": {
    "iso:country":"DE",
    "sg:address":"Anhalter Str. 8a",
    "sg:city":"Wuppertal",
    "sg:phone":"+49 202/660505",
    "sg:postcode":"42389",
    "sg:province":"Nordrhein-Westfalen",
    "wof:name":"Manfred Kumpmann",
    "wof:placetype":"venue"
},
  "geometry": {"coordinates":[7.241454,51.281864],"type":"Point"}
}