{
  "type": "Feature",
  "properties": {
    "iso:country":"DE",
    "sg:address":"Laurentiusstr. 4-12",
    "sg:city":"Bergisch Gladbach",
    "sg:postcode":"51465",
    "sg:province":"Nordrhein-Westfalen",
    "wof:name":"Kath. \u00d6ffent. Bibliothek St. Laurentius",
    "wof:placetype":"venue"
},
  "geometry": {"coordinates":[7.130754,50.99205],"type":"Point"}
}