{
  "type": "Feature",
  "properties": {
    "iso:country":"DE",
    "sg:address":"Lohweg 34",
    "sg:city":"Hannover",
    "sg:phone":"+49 511/5869336",
    "sg:postcode":"30559",
    "sg:province":"Niedersachsen",
    "wof:name":"Deutsche Pectacrete Gmbh",
    "wof:placetype":"venue"
},
  "geometry": {"coordinates":[9.8717393875,52.3743209839],"type":"Point"}
}