{
  "type": "Feature",
  "properties": {
    "iso:country":"DE",
    "sg:address":"Tuchmacherstr. 7",
    "sg:city":"M\u00fchldorf",
    "sg:phone":"+49 8631/2351",
    "sg:postcode":"84453",
    "sg:province":"Bayern",
    "wof:name":"Kreismuseum Im Lodronhaus",
    "wof:placetype":"venue"
},
  "geometry": {"coordinates":[12.526382,48.241455],"type":"Point"}
}