{
  "type": "Feature",
  "properties": {
    "iso:country":"DE",
    "sg:address":"Albert-Heise-Str. 1",
    "sg:city":"Teutschenthal",
    "sg:phone":"+49 34601/22264",
    "sg:postcode":"06179",
    "sg:province":"Sachsen-Anhalt",
    "wof:name":"Linden-apotheke Ohg",
    "wof:placetype":"venue"
},
  "geometry": {"coordinates":[11.81005,51.451618],"type":"Point"}
}