{
  "type": "Feature",
  "properties": {
    "iso:country":"DE",
    "sg:address":"Ortsring 37",
    "sg:city":"Kelheim",
    "sg:phone":"+49 9441/9197",
    "sg:postcode":"93309",
    "sg:province":"Bayern",
    "wof:name":"Heinrich Pr\u00fccklmeier",
    "wof:placetype":"venue"
},
  "geometry": {"coordinates":[11.808269,48.885967],"type":"Point"}
}