{
  "type": "Feature",
  "properties": {
    "iso:country":"DE",
    "sg:address":"Bellerwiese 34",
    "sg:city":"Leimbach",
    "sg:phone":"+49 2691/1206",
    "sg:postcode":"53518",
    "sg:province":"Rheinland-Pfalz",
    "wof:name":"Hermann Scheffold Gmbh",
    "wof:placetype":"venue"
},
  "geometry": {"coordinates":[6.9312591553,50.4022140503],"type":"Point"}
}