{
  "type": "Feature",
  "properties": {
    "iso:country":"DE",
    "sg:address":"Gottfried-Keller-Str. 20",
    "sg:city":"M\u00fcnchen",
    "sg:phone":"+49 89/886169",
    "sg:postcode":"81245",
    "sg:province":"Bayern",
    "wof:name":"Bernd-m. Manthey Rechtsanwalt",
    "wof:placetype":"venue"
},
  "geometry": {"coordinates":[11.4627609253,48.1505851746],"type":"Point"}
}