{
  "type": "Feature",
  "properties": {
    "iso:country":"DE",
    "sg:address":"Feuervogelweg 33",
    "sg:city":"Dortmund",
    "sg:phone":"+49 231/487948",
    "sg:postcode":"44269",
    "sg:province":"Nordrhein-Westfalen",
    "wof:name":"Rm-recycling Management Gmbh",
    "wof:placetype":"venue"
},
  "geometry": {"coordinates":[7.51929,51.47345],"type":"Point"}
}