{
  "type": "Feature",
  "properties": {
    "iso:country":"DE",
    "sg:address":"Oberbilker Allee 115",
    "sg:city":"D\u00fcsseldorf",
    "sg:phone":"+49 211/783115",
    "sg:postcode":"40227",
    "sg:province":"Nordrhein-Westfalen",
    "wof:name":"Bach",
    "wof:placetype":"venue"
},
  "geometry": {"coordinates":[6.7955861092,51.2109451294],"type":"Point"}
}