{
  "type": "Feature",
  "properties": {
    "iso:country":"DE",
    "sg:address":"Curslacker Neuer Deich 44",
    "sg:city":"Hamburg",
    "sg:phone":"+49 40/7269410",
    "sg:postcode":"21029",
    "sg:province":"Hamburg",
    "wof:name":"Redaktion Horner Wochenblatt Hamburger Wochenblatt",
    "wof:placetype":"venue"
},
  "geometry": {"coordinates":[10.2076129913,53.4805984497],"type":"Point"}
}