{
  "type": "Feature",
  "properties": {
    "iso:country":"DE",
    "sg:address":"Pfaffenwaldring 38-40",
    "sg:city":"Stuttgart",
    "sg:phone":"+49 711/6862359",
    "sg:postcode":"70569",
    "sg:province":"Baden-W\u00fcrttemberg",
    "wof:name":"Dlr-institut F\u00fcr Technische Thermodynamik",
    "wof:placetype":"venue"
},
  "geometry": {"coordinates":[9.102,48.748375],"type":"Point"}
}