{
  "type": "Feature",
  "properties": {
    "iso:country":"DE",
    "sg:address":"Schallershofer Str. 86",
    "sg:city":"Erlangen",
    "sg:phone":"+49 9131/758901",
    "sg:postcode":"91056",
    "sg:province":"Bayern",
    "wof:name":"G. Und O. M\u00fchlberger Architekten",
    "wof:placetype":"venue"
},
  "geometry": {"coordinates":[10.974273,49.586273],"type":"Point"}
}