{
  "type": "Feature",
  "properties": {
    "iso:country":"DE",
    "sg:address":"Burggrabenstra\u00dfe 13",
    "sg:city":"Gro\u00df-Rohrheim",
    "sg:phone":"+49 4962/457263",
    "sg:postcode":"68649",
    "sg:province":"Hessen",
    "wof:name":"Backparadies Heinz Krau\u00df",
    "wof:placetype":"venue"
},
  "geometry": {"coordinates":[8.4738483429,49.7161827087],"type":"Point"}
}