{
  "type": "Feature",
  "properties": {
    "iso:country":"DE",
    "sg:address":"Schwedenstr. 37",
    "sg:city":"Kronach",
    "sg:phone":"+49 9261/627500",
    "sg:postcode":"96317",
    "sg:province":"Bayern",
    "wof:name":"Kettelerhaus",
    "wof:placetype":"venue"
},
  "geometry": {"coordinates":[11.3230333328,50.2438278198],"type":"Point"}
}