{
  "type": "Feature",
  "properties": {
    "iso:country":"DE",
    "sg:address":"Talstr 36",
    "sg:city":"Homburg",
    "sg:phone":"+49 6841/9690",
    "sg:postcode":"66424",
    "sg:province":"Saarland",
    "wof:name":"Ermer Gmbh & Co Kg",
    "wof:placetype":"venue"
},
  "geometry": {"coordinates":[7.3380627632,49.3215789795],"type":"Point"}
}