{
  "type": "Feature",
  "properties": {
    "iso:country":"DE",
    "sg:address":"Birkenstr. 2a",
    "sg:city":"Velbert",
    "sg:phone":"+49 2051/251518",
    "sg:postcode":"42549",
    "sg:province":"Nordrhein-Westfalen",
    "wof:name":"Norbert Diegmann",
    "wof:placetype":"venue"
},
  "geometry": {"coordinates":[7.03718,51.331779],"type":"Point"}
}