{
  "type": "Feature",
  "properties": {
    "iso:country":"DE",
    "sg:address":"Zum Ilsetal 34",
    "sg:city":"Bad Laasphe",
    "sg:phone":"+49 2754/8200",
    "sg:postcode":"57334",
    "sg:province":"Nordrhein-Westfalen",
    "wof:name":"Rassegefl\u00fcgelz\u00fcchterverein Feudingen",
    "wof:placetype":"venue"
},
  "geometry": {"coordinates":[8.3340015411,50.9388504028],"type":"Point"}
}