{
  "type": "Feature",
  "properties": {
    "iso:country":"DE",
    "sg:address":"Stieglitzweg 9",
    "sg:city":"Pfullingen",
    "sg:phone":"+49 7121/97560",
    "sg:postcode":"72793",
    "sg:province":"Baden-W\u00fcrttemberg",
    "wof:name":"Hubert Globusch\u00fctz Ingenieur",
    "wof:placetype":"venue"
},
  "geometry": {"coordinates":[9.2166938782,48.46641922],"type":"Point"}
}