{
  "type": "Feature",
  "properties": {
    "iso:country":"DE",
    "sg:address":"Bilhildisstr. 7",
    "sg:city":"Mainz",
    "sg:phone":"+49 6131/224951",
    "sg:postcode":"55116",
    "sg:province":"Rheinland-Pfalz",
    "wof:name":"Renate Sch\u00e4ffer",
    "wof:placetype":"venue"
},
  "geometry": {"coordinates":[8.2625846863,49.9994773865],"type":"Point"}
}