{
  "type": "Feature",
  "properties": {
    "iso:country":"DE",
    "sg:address":"Am Markt 10 -12",
    "sg:city":"Saarburg",
    "sg:phone":"+49 6581/92620",
    "sg:postcode":"54439",
    "sg:province":"Rheinland-Pfalz",
    "wof:name":"Restaurant Meridiana",
    "wof:placetype":"venue"
},
  "geometry": {"coordinates":[6.55037117,49.6082267761],"type":"Point"}
}