{
  "type": "Feature",
  "properties": {
    "iso:country":"DE",
    "sg:address":"Odenwaldstr. 55",
    "sg:city":"Modautal",
    "sg:phone":"+49 6254/942400",
    "sg:postcode":"64397",
    "sg:province":"Hessen",
    "wof:name":"Thomas Roder",
    "wof:placetype":"venue"
},
  "geometry": {"coordinates":[8.738264,49.734955],"type":"Point"}
}