{
  "type": "Feature",
  "properties": {
    "iso:country":"DE",
    "sg:address":"An der Vogelrute 2",
    "sg:city":"Erftstadt",
    "sg:phone":"+49 2235/959101",
    "sg:postcode":"50374",
    "sg:province":"Nordrhein-Westfalen",
    "wof:name":"Pards Finanzcoaching - Online Versichern",
    "wof:placetype":"venue"
},
  "geometry": {"coordinates":[6.775386,50.800312],"type":"Point"}
}