{
  "type": "Feature",
  "properties": {
    "iso:country":"DE",
    "sg:address":"Theatergassen 2",
    "sg:city":"Bamberg",
    "sg:phone":"+49 951/24585",
    "sg:postcode":"96047",
    "sg:province":"Bayern",
    "wof:name":"D. B\u00fcttner",
    "wof:placetype":"venue"
},
  "geometry": {"coordinates":[10.890534,49.891594],"type":"Point"}
}