{
  "type": "Feature",
  "properties": {
    "iso:country":"DE",
    "sg:address":"Rheinallee 162",
    "sg:city":"D\u00fcsseldorf",
    "sg:phone":"+49 211/9544920",
    "sg:postcode":"40545",
    "sg:province":"Nordrhein-Westfalen",
    "wof:name":"Tristano Onofri Moda Italiana Gmbh",
    "wof:placetype":"venue"
},
  "geometry": {"coordinates":[6.753578186,51.2266921997],"type":"Point"}
}