{
  "type": "Feature",
  "properties": {
    "iso:country":"DE",
    "sg:address":"Moritzstr. 2",
    "sg:city":"Berlin",
    "sg:phone":"+49 30/3337670",
    "sg:postcode":"13597",
    "sg:province":"Berlin",
    "wof:name":"Kurbad Spandau W. Neidhardt",
    "wof:placetype":"venue"
},
  "geometry": {"coordinates":[13.203408,52.537819],"type":"Point"}
}