{
  "type": "Feature",
  "properties": {
    "iso:country":"DE",
    "sg:address":"S\u00e4uritzer Str. 3",
    "sg:city":"Burkau",
    "sg:postcode":"01906",
    "sg:province":"Sachsen",
    "wof:name":"Fenster Und Elemente Produktion Vertriebsges. Mbh",
    "wof:placetype":"venue"
},
  "geometry": {"coordinates":[14.172703,51.176422],"type":"Point"}
}