{
  "type": "Feature",
  "properties": {
    "iso:country":"DE",
    "sg:address":"Am Neuen Friedhof 16",
    "sg:city":"Greifswald",
    "sg:phone":"+49 3834/502414",
    "sg:postcode":"17489",
    "sg:province":"Mecklenburg-Vorpommern",
    "wof:name":"U. Dietrich",
    "wof:placetype":"venue"
},
  "geometry": {"coordinates":[13.346012,54.095036],"type":"Point"}
}