{
  "type": "Feature",
  "properties": {
    "iso:country":"DE",
    "sg:address":"Eggenfeldener Str. 46",
    "sg:city":"Falkenberg",
    "sg:postcode":"84326",
    "sg:province":"Bayern",
    "wof:name":"Eba Eigenheimbau Gmbh",
    "wof:placetype":"venue"
},
  "geometry": {"coordinates":[12.7307796478,48.4649467468],"type":"Point"}
}