{
  "type": "Feature",
  "properties": {
    "iso:country":"DE",
    "sg:address":"Dresdner Str. 41",
    "sg:city":"Freital",
    "sg:phone":"+49 351/6494345",
    "sg:postcode":"01705",
    "sg:province":"Sachsen",
    "wof:name":"Eiscafe Sabine Fischer",
    "wof:placetype":"venue"
},
  "geometry": {"coordinates":[13.664785,51.01437],"type":"Point"}
}