{
  "type": "Feature",
  "properties": {
    "iso:country":"DE",
    "sg:address":"Ruwerer Str. 18",
    "sg:city":"Trier",
    "sg:phone":"+49 651/5100",
    "sg:postcode":"54292",
    "sg:province":"Rheinland-Pfalz",
    "wof:name":"Zur Post",
    "wof:placetype":"venue"
},
  "geometry": {"coordinates":[6.7054247856,49.7822685242],"type":"Point"}
}