{
  "type": "Feature",
  "properties": {
    "iso:country":"DE",
    "sg:address":"Johann-Classen-Str. 92",
    "sg:city":"K\u00f6ln",
    "sg:phone":"+49 221/853137",
    "sg:postcode":"51103",
    "sg:province":"Nordrhein-Westfalen",
    "wof:name":"Wilhelm Bauer",
    "wof:placetype":"venue"
},
  "geometry": {"coordinates":[7.011919,50.941509],"type":"Point"}
}