{
  "type": "Feature",
  "properties": {
    "iso:country":"DE",
    "sg:address":"Neuburger Str. 9",
    "sg:city":"Wellheim",
    "sg:phone":"+49 8427/225",
    "sg:postcode":"91809",
    "sg:province":"Bayern",
    "wof:name":"Hermann Schmucker",
    "wof:placetype":"venue"
},
  "geometry": {"coordinates":[11.08253,48.816517],"type":"Point"}
}