{
  "type": "Feature",
  "properties": {
    "iso:country":"DE",
    "sg:address":"Hansastr. 61",
    "sg:city":"Dortmund",
    "sg:phone":"+49 231/16992",
    "sg:postcode":"44137",
    "sg:province":"Nordrhein-Westfalen",
    "wof:name":"Dr. A. Gerling Und K.h. Junker G. Grotefels",
    "wof:placetype":"venue"
},
  "geometry": {"coordinates":[7.4636521339,51.5132484436],"type":"Point"}
}