{
  "type": "Feature",
  "properties": {
    "iso:country":"DE",
    "sg:address":"Darmst\u00e4dter Str. 70",
    "sg:city":"Biblis",
    "sg:phone":"+49 6245/7967",
    "sg:postcode":"68647",
    "sg:province":"Hessen",
    "wof:name":"Alte Post",
    "wof:placetype":"venue"
},
  "geometry": {"coordinates":[8.456376,49.68853],"type":"Point"}
}