{
  "type": "Feature",
  "properties": {
    "iso:country":"DE",
    "sg:address":"Obere Rodstr. 23",
    "sg:city":"Pforzheim",
    "sg:phone":"+49 7231/356636",
    "sg:postcode":"75173",
    "sg:province":"Baden-W\u00fcrttemberg",
    "wof:name":"Kerstin Haase Krankengymnastin",
    "wof:placetype":"venue"
},
  "geometry": {"coordinates":[8.694504,48.881027],"type":"Point"}
}