{
  "type": "Feature",
  "properties": {
    "iso:country":"DE",
    "sg:address":"H\u00f6henstr. 14",
    "sg:city":"Wipperf\u00fcrth",
    "sg:phone":"+49 2267/8496",
    "sg:postcode":"51688",
    "sg:province":"Nordrhein-Westfalen",
    "wof:name":"Willy Dames Masseur",
    "wof:placetype":"venue"
},
  "geometry": {"coordinates":[7.373139,51.081257],"type":"Point"}
}