{
  "type": "Feature",
  "properties": {
    "iso:country":"DE",
    "sg:address":"Am Baackeshof 9",
    "sg:city":"Krefeld",
    "sg:phone":"+49 2151/710510",
    "sg:postcode":"47804",
    "sg:province":"Nordrhein-Westfalen",
    "wof:name":"Hans-georg Fenten",
    "wof:placetype":"venue"
},
  "geometry": {"coordinates":[6.54797,51.324383],"type":"Point"}
}