{
  "type": "Feature",
  "properties": {
    "iso:country":"DE",
    "sg:address":"Olgastr. 6",
    "sg:city":"Heidenheim",
    "sg:phone":"+49 7321/21746",
    "sg:postcode":"89518",
    "sg:province":"Baden-W\u00fcrttemberg",
    "wof:name":"Holland Blumen Matthias Kluge",
    "wof:placetype":"venue"
},
  "geometry": {"coordinates":[10.1526222229,48.6790809631],"type":"Point"}
}