{
  "type": "Feature",
  "properties": {
    "iso:country":"DE",
    "sg:address":"Hintergasse 26",
    "sg:city":"Lohfelden",
    "sg:phone":"+49 5608/91721",
    "sg:postcode":"34253",
    "sg:province":"Hessen",
    "wof:name":"J. Und C. Gundelach",
    "wof:placetype":"venue"
},
  "geometry": {"coordinates":[9.56492,51.260799],"type":"Point"}
}