{
  "type": "Feature",
  "properties": {
    "iso:country":"DE",
    "sg:address":"Robert-Bosch-Str. 9",
    "sg:city":"Wimsheim",
    "sg:phone":"+49 7044/94560",
    "sg:postcode":"71299",
    "sg:province":"Baden-W\u00fcrttemberg",
    "wof:name":"Mori Say Werkzeugmaschinen- Handels-gmbh",
    "wof:placetype":"venue"
},
  "geometry": {"coordinates":[8.8268671036,48.8449287415],"type":"Point"}
}