{
  "type": "Feature",
  "properties": {
    "iso:country":"DE",
    "sg:city":"T\u00d6NISVORST",
    "sg:postcode":"47918",
    "sg:province":"Nordrhein-Westfalen",
    "wof:name":"Leihhaus",
    "wof:placetype":"venue"
},
  "geometry": {"coordinates":[6.49536,51.320625],"type":"Point"}
}