{
  "type": "Feature",
  "properties": {
    "iso:country":"DE",
    "sg:address":"Maximilianstr. 23",
    "sg:city":"Starnberg",
    "sg:phone":"+49 8151/72772",
    "sg:postcode":"82319",
    "sg:province":"Bayern",
    "wof:name":"Hadubrand Walther Rechtsanwalt",
    "wof:placetype":"venue"
},
  "geometry": {"coordinates":[11.3440704346,48.000377655],"type":"Point"}
}