{
  "type": "Feature",
  "properties": {
    "iso:country":"DE",
    "sg:address":"Breslauer Str. 5",
    "sg:city":"Heusenstamm",
    "sg:phone":"+49 6104/65200",
    "sg:postcode":"63150",
    "sg:province":"Hessen",
    "wof:name":"Winterweb Business Publishing Gmbh",
    "wof:placetype":"venue"
},
  "geometry": {"coordinates":[8.7842512131,50.0569801331],"type":"Point"}
}