{
  "type": "Feature",
  "properties": {
    "iso:country":"DE",
    "sg:address":"Dorfanger 37d",
    "sg:city":"Kreblitz",
    "sg:postcode":"15926",
    "sg:province":"Brandenburg",
    "wof:name":"Celhaus-exklusiv Bautr\u00e4gergesellschaft Mbh",
    "wof:placetype":"venue"
},
  "geometry": {"coordinates":[13.712253,51.901459],"type":"Point"}
}