{
  "type": "Feature",
  "properties": {
    "iso:country":"DE",
    "sg:address":"Krayer Str. 230",
    "sg:city":"Essen",
    "sg:phone":"+49 201/555559",
    "sg:postcode":"45307",
    "sg:province":"Nordrhein-Westfalen",
    "wof:name":"Ewald Gmbh",
    "wof:placetype":"venue"
},
  "geometry": {"coordinates":[7.080458,51.46653],"type":"Point"}
}