{
  "type": "Feature",
  "properties": {
    "iso:country":"DE",
    "sg:address":"Unter dem Malesfelsen 18",
    "sg:city":"Albstadt",
    "sg:phone":"+49 7431/3611",
    "sg:postcode":"72458",
    "sg:province":"Baden-W\u00fcrttemberg",
    "wof:name":"Emanuel Schreiber Schilder Und Lichtreklame",
    "wof:placetype":"venue"
},
  "geometry": {"coordinates":[9.02791,48.206181],"type":"Point"}
}