{
  "type": "Feature",
  "properties": {
    "iso:country":"DE",
    "sg:address":"Forststr. 10",
    "sg:city":"Oelsnitz",
    "sg:phone":"+49 37421/4880",
    "sg:postcode":"08606",
    "sg:province":"Sachsen",
    "wof:name":"Schneider Ingenieur Und Architekturb\u00fcro",
    "wof:placetype":"venue"
},
  "geometry": {"coordinates":[12.165527,50.410526],"type":"Point"}
}