{
  "type": "Feature",
  "properties": {
    "iso:country":"DE",
    "sg:address":"Auf dem Nohlenrain 5",
    "sg:city":"Nidda",
    "sg:phone":"+49 6043/1344",
    "sg:postcode":"63667",
    "sg:province":"Hessen",
    "wof:name":"G\u00fcnther Franke",
    "wof:placetype":"venue"
},
  "geometry": {"coordinates":[9.02272892,50.3958129883],"type":"Point"}
}