{
  "type": "Feature",
  "properties": {
    "iso:country":"DE",
    "sg:address":"Ingolst\u00e4dter Str. 31",
    "sg:city":"Frankfurt",
    "sg:phone":"+49 69/443102",
    "sg:postcode":"60316",
    "sg:province":"Hessen",
    "wof:name":"Wilhelm A. J\u00e4ger",
    "wof:placetype":"venue"
},
  "geometry": {"coordinates":[8.7028713226,50.1204528809],"type":"Point"}
}