{
  "type": "Feature",
  "properties": {
    "iso:country":"DE",
    "sg:address":"Badensche Str. 29",
    "sg:city":"Berlin",
    "sg:phone":"+49 30/8732212",
    "sg:postcode":"10715",
    "sg:province":"Berlin",
    "wof:name":"Klaus Rothkegel Ingenieur",
    "wof:placetype":"venue"
},
  "geometry": {"coordinates":[13.3279647827,52.486240387],"type":"Point"}
}