{
  "type": "Feature",
  "properties": {
    "iso:country":"DE",
    "sg:address":"Tuchmacherweg 2 e",
    "sg:city":"Burgdorf",
    "sg:phone":"+49 5136/83888",
    "sg:postcode":"31303",
    "sg:province":"Niedersachsen",
    "wof:name":"Fliesen-wadewitz Gmbh",
    "wof:placetype":"venue"
},
  "geometry": {"coordinates":[10.0055046082,52.4462013245],"type":"Point"}
}