{
  "type": "Feature",
  "properties": {
    "iso:country":"DE",
    "sg:address":"Josef-Knettel-Str. 49a",
    "sg:city":"Bingen",
    "sg:phone":"+49 6721/13848",
    "sg:postcode":"55411",
    "sg:province":"Rheinland-Pfalz",
    "wof:name":"Wahlheim Bautr\u00e4ger Gmbh",
    "wof:placetype":"venue"
},
  "geometry": {"coordinates":[7.918505,49.967693],"type":"Point"}
}