{
  "type": "Feature",
  "properties": {
    "iso:country":"DE",
    "sg:address":"Sonnenstr. 57",
    "sg:city":"Zellingen",
    "sg:phone":"+49 9364/896508",
    "sg:postcode":"97225",
    "sg:province":"Bayern",
    "wof:name":"Norma Gmbh & Co. Kg",
    "wof:placetype":"venue"
},
  "geometry": {"coordinates":[9.8264560699,49.8911514282],"type":"Point"}
}