{
  "type": "Feature",
  "properties": {
    "iso:country":"DE",
    "sg:address":"Norderster Weg 4",
    "sg:city":"Galmsb\u00fcll",
    "sg:phone":"+49 4661/2233",
    "sg:postcode":"25899",
    "sg:province":"Schleswig-Holstein",
    "wof:name":"Kirchner - Hamburg Ute Kirchner E. K.",
    "wof:placetype":"venue"
},
  "geometry": {"coordinates":[8.800755,54.756245],"type":"Point"}
}