{
  "type": "Feature",
  "properties": {
    "iso:country":"DE",
    "sg:address":"Rossertstr. 14",
    "sg:city":"K\u00f6nigstein",
    "sg:phone":"+49 6174/1418",
    "sg:postcode":"61462",
    "sg:province":"Hessen",
    "wof:name":"Roland Bohn",
    "wof:placetype":"venue"
},
  "geometry": {"coordinates":[8.447528,50.173664],"type":"Point"}
}