{
  "type": "Feature",
  "properties": {
    "iso:country":"DE",
    "sg:address":"Sch\u00f6ne Aussicht 41",
    "sg:city":"Wiesbaden",
    "sg:phone":"+49 611/5319053",
    "sg:postcode":"65193",
    "sg:province":"Hessen",
    "wof:name":"Druckkammerzentrum Wiesbaden Gmbh",
    "wof:placetype":"venue"
},
  "geometry": {"coordinates":[8.2500982285,50.0871925354],"type":"Point"}
}