{
  "type": "Feature",
  "properties": {
    "iso:country":"DE",
    "sg:address":"Bendstr. 61",
    "sg:city":"Viersen",
    "sg:phone":"+49 2162/12228",
    "sg:postcode":"41748",
    "sg:province":"Nordrhein-Westfalen",
    "wof:name":"Karl H. Butschen",
    "wof:placetype":"venue"
},
  "geometry": {"coordinates":[6.391013,51.263866],"type":"Point"}
}