{
  "type": "Feature",
  "properties": {
    "iso:country":"DE",
    "sg:address":"Eichenallee 32e",
    "sg:city":"Leegebruch",
    "sg:phone":"+49 3304/250176",
    "sg:postcode":"16767",
    "sg:province":"Brandenburg",
    "wof:name":"Finca-bau Gmbh",
    "wof:placetype":"venue"
},
  "geometry": {"coordinates":[13.196872,52.723045],"type":"Point"}
}