{
  "type": "Feature",
  "properties": {
    "iso:country":"DE",
    "sg:address":"Fliegenberg 16",
    "sg:city":"Stelle",
    "sg:phone":"+49 4174/2532",
    "sg:postcode":"21435",
    "sg:province":"Niedersachsen",
    "wof:name":"Heinrich Schultz Seeschiffahrt-unternehmen",
    "wof:placetype":"venue"
},
  "geometry": {"coordinates":[10.140903,53.415226],"type":"Point"}
}