{
  "type": "Feature",
  "properties": {
    "iso:country":"DE",
    "sg:address":"Marktplatz 14",
    "sg:city":"Boppard",
    "sg:phone":"+49 6742/2318",
    "sg:postcode":"56154",
    "sg:province":"Rheinland-Pfalz",
    "wof:name":"B\u00e4ckerei Martin Nickenig Gmbh",
    "wof:placetype":"venue"
},
  "geometry": {"coordinates":[7.592114,50.232052],"type":"Point"}
}