{
  "type": "Feature",
  "properties": {
    "iso:country":"DE",
    "sg:address":"Kardinalstr. 1",
    "sg:city":"Bernkastel-Kues",
    "sg:phone":"+49 6531/6632",
    "sg:postcode":"54470",
    "sg:province":"Rheinland-Pfalz",
    "wof:name":"Peter Kropf",
    "wof:placetype":"venue"
},
  "geometry": {"coordinates":[7.0628638268,49.9122200012],"type":"Point"}
}