{
  "type": "Feature",
  "properties": {
    "iso:country":"DE",
    "sg:address":"Trierer Str. 29 a",
    "sg:city":"Nohfelden",
    "sg:phone":"+49 6852/244",
    "sg:postcode":"66625",
    "sg:province":"Saarland",
    "wof:name":"Holzvertriebs Gmbh A. Von Hammerstein",
    "wof:placetype":"venue"
},
  "geometry": {"coordinates":[7.0979881287,49.5796089172],"type":"Point"}
}