{
  "type": "Feature",
  "properties": {
    "iso:country":"DE",
    "sg:address":"Dischingerweg 3",
    "sg:city":"T\u00fcbingen",
    "sg:phone":"+49 7071/97660",
    "sg:postcode":"72070",
    "sg:province":"Baden-W\u00fcrttemberg",
    "wof:name":"Sieghard Bartel",
    "wof:placetype":"venue"
},
  "geometry": {"coordinates":[9.003647,48.499401],"type":"Point"}
}