{
  "type": "Feature",
  "properties": {
    "iso:country":"DE",
    "sg:address":"Ringstr. 5",
    "sg:city":"Leverkusen",
    "sg:phone":"+49 2173/41426",
    "sg:postcode":"51371",
    "sg:province":"Nordrhein-Westfalen",
    "wof:name":"Josef Kr\u00e4mer",
    "wof:placetype":"venue"
},
  "geometry": {"coordinates":[6.9076,51.066429],"type":"Point"}
}