{
  "type": "Feature",
  "properties": {
    "iso:country":"DE",
    "sg:address":"Miningstr. 12",
    "sg:city":"Berlin",
    "sg:phone":"+49 30/6234022",
    "sg:postcode":"12359",
    "sg:province":"Berlin",
    "wof:name":"Graphics & Technology Gmbh",
    "wof:placetype":"venue"
},
  "geometry": {"coordinates":[13.4466114044,52.450756073],"type":"Point"}
}