{
  "type": "Feature",
  "properties": {
    "iso:country":"DE",
    "sg:address":"G\u00fcterstr. 25",
    "sg:city":"Pforzheim",
    "sg:phone":"+49 7231/352052",
    "sg:postcode":"75177",
    "sg:province":"Baden-W\u00fcrttemberg",
    "wof:name":"Wilhelm St\u00f6ffler",
    "wof:placetype":"venue"
},
  "geometry": {"coordinates":[8.7002868652,48.8946533203],"type":"Point"}
}