{
  "type": "Feature",
  "properties": {
    "iso:country":"DE",
    "sg:address":"N\u00fcrtinger Str. 32",
    "sg:city":"Filderstadt",
    "sg:phone":"+49 711/703766",
    "sg:postcode":"70794",
    "sg:province":"Baden-W\u00fcrttemberg",
    "wof:name":"G. Und C. Weinmann",
    "wof:placetype":"venue"
},
  "geometry": {"coordinates":[9.2205638885,48.6785697937],"type":"Point"}
}