{
  "type": "Feature",
  "properties": {
    "iso:country":"DE",
    "sg:address":"Sch\u00f6nleinstra\u00dfe 6a",
    "sg:city":"Berlin",
    "sg:phone":"+49 30",
    "sg:postcode":"10967",
    "sg:province":"Berlin",
    "wof:name":"E. M Peine Derivate-verwaltung E.k.",
    "wof:placetype":"venue"
},
  "geometry": {"coordinates":[13.4209070206,52.4922294617],"type":"Point"}
}