{
  "type": "Feature",
  "properties": {
    "iso:country":"DE",
    "sg:address":"Bahnhofstr. 40",
    "sg:city":"Homburg",
    "sg:phone":"+49 6841/777750",
    "sg:postcode":"66424",
    "sg:province":"Saarland",
    "wof:name":"Alois Omlor Gmbh",
    "wof:placetype":"venue"
},
  "geometry": {"coordinates":[7.3306980133,49.3730201721],"type":"Point"}
}