{
  "type": "Feature",
  "properties": {
    "iso:country":"DE",
    "sg:address":"Lindenstr. 1",
    "sg:city":"Bad Salzschlirf",
    "sg:phone":"+49 6648/1229",
    "sg:postcode":"36364",
    "sg:province":"Hessen",
    "wof:name":"Romano",
    "wof:placetype":"venue"
},
  "geometry": {"coordinates":[9.505255,50.625397],"type":"Point"}
}