{
  "type": "Feature",
  "properties": {
    "iso:country":"DE",
    "sg:address":"W\u00f6rmlitzer Weg 2",
    "sg:city":"Ziepel",
    "sg:phone":"+49 39224/315",
    "sg:postcode":"39291",
    "sg:province":"Sachsen-Anhalt",
    "wof:name":"Siegfried Bussmann",
    "wof:placetype":"venue"
},
  "geometry": {"coordinates":[11.86995,52.152306],"type":"Point"}
}