{
  "type": "Feature",
  "properties": {
    "iso:country":"DE",
    "sg:address":"Hauptstr. 22",
    "sg:city":"Neuenkirchen",
    "sg:phone":"+49 5973/3770",
    "sg:postcode":"48485",
    "sg:province":"Nordrhein-Westfalen",
    "wof:name":"Old Pub",
    "wof:placetype":"venue"
},
  "geometry": {"coordinates":[7.3711209297,52.2437019348],"type":"Point"}
}