{
  "type": "Feature",
  "properties": {
    "iso:country":"DE",
    "sg:address":"Bergstr. 153",
    "sg:city":"Heidelberg",
    "sg:phone":"+49 6221/401443",
    "sg:postcode":"69121",
    "sg:province":"Baden-W\u00fcrttemberg",
    "wof:name":"Minitrek Expeditionen Burkhard Schild Gmbh",
    "wof:placetype":"venue"
},
  "geometry": {"coordinates":[8.6905441284,49.4285507202],"type":"Point"}
}