{
  "type": "Feature",
  "properties": {
    "iso:country":"DE",
    "sg:address":"Bonner Str. 178",
    "sg:city":"K\u00f6ln",
    "sg:postcode":"50968",
    "sg:province":"Nordrhein-Westfalen",
    "wof:name":"Simac Ict Gmbh",
    "wof:placetype":"venue"
},
  "geometry": {"coordinates":[6.9619498253,50.9119911194],"type":"Point"}
}