{
  "type": "Feature",
  "properties": {
    "iso:country":"DE",
    "sg:address":"Talweg 6",
    "sg:city":"Roetgen",
    "sg:phone":"+49 2471/990006",
    "sg:postcode":"52159",
    "sg:province":"Nordrhein-Westfalen",
    "wof:name":"Ial Automation Und Logistik Gmbh",
    "wof:placetype":"venue"
},
  "geometry": {"coordinates":[6.2159152031,50.6822013855],"type":"Point"}
}