{
  "type": "Feature",
  "properties": {
    "iso:country":"DE",
    "sg:address":"Siebengebirgsstr. 129",
    "sg:city":"Bonn",
    "sg:phone":"+49 228/430388",
    "sg:postcode":"53229",
    "sg:province":"Nordrhein-Westfalen",
    "wof:name":"Thomas Oyen Gartenarchitekt",
    "wof:placetype":"venue"
},
  "geometry": {"coordinates":[7.18696,50.747829],"type":"Point"}
}