{
  "type": "Feature",
  "properties": {
    "iso:country":"DE",
    "sg:address":"Bahnhofstr.",
    "sg:city":"Chemnitz",
    "sg:phone":"+49 371/61362",
    "sg:postcode":"09111",
    "sg:province":"Sachsen",
    "wof:name":"Kaufhof Reiseb\u00fcro",
    "wof:placetype":"venue"
},
  "geometry": {"coordinates":[12.9286499023,50.8370437622],"type":"Point"}
}