{
  "type": "Feature",
  "properties": {
    "iso:country":"DE",
    "sg:address":"\u00d6lm\u00fchlenweg 4",
    "sg:city":"Hamburg",
    "sg:phone":"+49 40/6561229",
    "sg:postcode":"22047",
    "sg:province":"Hamburg",
    "wof:name":"Textilpflege Siewertsen",
    "wof:placetype":"venue"
},
  "geometry": {"coordinates":[10.102131,53.580887],"type":"Point"}
}