{
  "type": "Feature",
  "properties": {
    "iso:country":"DE",
    "sg:address":"Straubinger Str. 1",
    "sg:city":"Haselbach",
    "sg:phone":"+49 9961/6135",
    "sg:postcode":"94354",
    "sg:province":"Bayern",
    "wof:name":"Alfons Pellkofer",
    "wof:placetype":"venue"
},
  "geometry": {"coordinates":[12.6931600571,49.0045585632],"type":"Point"}
}