{
  "type": "Feature",
  "properties": {
    "iso:country":"DE",
    "sg:address":"Ofener Str. 45",
    "sg:city":"Oldenburg",
    "sg:phone":"+49 441/7779559",
    "sg:postcode":"26121",
    "sg:province":"Niedersachsen",
    "wof:name":"Hanse-merkur Versicherungsgr. R. L\u00fcbbering",
    "wof:placetype":"venue"
},
  "geometry": {"coordinates":[8.1936855316,53.1433296204],"type":"Point"}
}