{
  "type": "Feature",
  "properties": {
    "iso:country":"DE",
    "sg:address":"Blechhammer 1 POSTFACH 100144",
    "sg:city":"Schmalkalden",
    "sg:phone":"+49 3683/402761",
    "sg:postcode":"98561",
    "sg:province":"Th\u00fcringen",
    "wof:name":"A. G. Thorwarthmetallwarenfabrik Gmbh",
    "wof:placetype":"venue"
},
  "geometry": {"coordinates":[10.464109,50.718185],"type":"Point"}
}