{
  "type": "Feature",
  "properties": {
    "iso:country":"DE",
    "sg:address":"Th\u00fcler Str. 1",
    "sg:city":"Friesoythe",
    "sg:postcode":"26169",
    "sg:province":"Niedersachsen",
    "wof:name":"Hansa-friesia Treuhand Gmbh Steuerberatungsges.",
    "wof:placetype":"venue"
},
  "geometry": {"coordinates":[7.85958004,53.0150794983],"type":"Point"}
}