{
  "type": "Feature",
  "properties": {
    "iso:country":"DE",
    "sg:address":"Friedhofsweg 3",
    "sg:city":"Hessisch Oldendorf",
    "sg:phone":"+49 5152/526015",
    "sg:postcode":"31840",
    "sg:province":"Niedersachsen",
    "wof:name":"Taphorn & Gieseking Malergesellschaft Mbh",
    "wof:placetype":"venue"
},
  "geometry": {"coordinates":[9.186334,52.1763],"type":"Point"}
}