{
  "type": "Feature",
  "properties": {
    "iso:country":"DE",
    "sg:address":"Flurstr. 6",
    "sg:city":"Buch",
    "sg:phone":"+49 8709/9140",
    "sg:postcode":"84172",
    "sg:province":"Bayern",
    "wof:name":"Hausmann Und Rieger Ingenieurb\u00fcro",
    "wof:placetype":"venue"
},
  "geometry": {"coordinates":[12.0148267746,48.4581832886],"type":"Point"}
}