{
  "type": "Feature",
  "properties": {
    "iso:country":"DE",
    "sg:address":"Rehbergweg 9",
    "sg:city":"Aschaffenburg",
    "sg:phone":"+49 6021/61880",
    "sg:postcode":"63743",
    "sg:province":"Bayern",
    "wof:name":"Roland Glaab Gmbh",
    "wof:placetype":"venue"
},
  "geometry": {"coordinates":[9.113225,49.98893],"type":"Point"}
}