{
  "type": "Feature",
  "properties": {
    "iso:country":"DE",
    "sg:address":"Hauptstr. 49",
    "sg:city":"Cuxhaven",
    "sg:phone":"+49 4723/71550",
    "sg:postcode":"27478",
    "sg:province":"Niedersachsen",
    "wof:name":"Bestattungsinstitut Ernst Rhode",
    "wof:placetype":"venue"
},
  "geometry": {"coordinates":[8.667403,53.824364],"type":"Point"}
}