{
  "type": "Feature",
  "properties": {
    "iso:country":"DE",
    "sg:address":"Reichenwalder Str. 120",
    "sg:city":"Storkow",
    "sg:phone":"+49 33678/72233",
    "sg:postcode":"15859",
    "sg:province":"Brandenburg",
    "wof:name":"Pension Helga U. Lutz Seehawer",
    "wof:placetype":"venue"
},
  "geometry": {"coordinates":[13.968331337,52.2641983032],"type":"Point"}
}