{
  "type": "Feature",
  "properties": {
    "iso:country":"DE",
    "sg:address":"Rodheimer Str. 83",
    "sg:city":"Heuchelheim",
    "sg:phone":"+49 641/74031",
    "sg:postcode":"35452",
    "sg:province":"Hessen",
    "wof:name":"Verkaufsges. Mittelhess. Betonwerke Mbh",
    "wof:placetype":"venue"
},
  "geometry": {"coordinates":[8.62966,50.595722],"type":"Point"}
}