{
  "type": "Feature",
  "properties": {
    "iso:country":"DE",
    "sg:address":"Neusser Weyhe 90",
    "sg:city":"Neuss",
    "sg:phone":"+49 2131/228090",
    "sg:postcode":"41462",
    "sg:province":"Nordrhein-Westfalen",
    "wof:name":"Vinzenz-gemeinschaft Neuss Altenheim",
    "wof:placetype":"venue"
},
  "geometry": {"coordinates":[6.678,51.214821],"type":"Point"}
}