{
  "type": "Feature",
  "properties": {
    "iso:country":"DE",
    "sg:address":"Steinacher Str. 4",
    "sg:city":"Remshalden",
    "sg:phone":"+49 7151/72001",
    "sg:postcode":"73630",
    "sg:province":"Baden-W\u00fcrttemberg",
    "wof:name":"Tobias Computervertriebs- Gmbh",
    "wof:placetype":"venue"
},
  "geometry": {"coordinates":[9.4223976135,48.8330421448],"type":"Point"}
}