{
  "type": "Feature",
  "properties": {
    "iso:country":"DE",
    "sg:address":"Am Borgberg 3",
    "sg:city":"Hagen",
    "sg:postcode":"49170",
    "sg:province":"Niedersachsen",
    "wof:name":"International Sporthorses Kasselmann Gmbh",
    "wof:placetype":"venue"
},
  "geometry": {"coordinates":[7.9633178711,52.1893768311],"type":"Point"}
}