{
  "type": "Feature",
  "properties": {
    "iso:country":"DE",
    "sg:address":"Pr\u00e4mienstr. 251",
    "sg:city":"Stolberg",
    "sg:phone":"+49 2402/91222",
    "sg:postcode":"52223",
    "sg:province":"Nordrhein-Westfalen",
    "wof:name":"Kiwi Production",
    "wof:placetype":"venue"
},
  "geometry": {"coordinates":[6.2116241455,50.7725830078],"type":"Point"}
}