{
  "type": "Feature",
  "properties": {
    "iso:country":"DE",
    "sg:address":"Niedere Str. 92",
    "sg:city":"Villingen-Schwenningen",
    "sg:phone":"+49 7721/20000",
    "sg:postcode":"78050",
    "sg:province":"Baden-W\u00fcrttemberg",
    "wof:name":"Dr. Peter Bergmann Rechtsanwalt",
    "wof:placetype":"venue"
},
  "geometry": {"coordinates":[8.4611568451,48.0562667847],"type":"Point"}
}