{
  "type": "Feature",
  "properties": {
    "iso:country":"DE",
    "sg:address":"Gottlieb-Daimler-Str. 4",
    "sg:city":"Dietzenbach",
    "sg:phone":"+49 4960/7426233",
    "sg:postcode":"63128",
    "sg:province":"Hessen",
    "wof:name":"Horst M\u00dcller Gmbh",
    "wof:placetype":"venue"
},
  "geometry": {"coordinates":[8.7980194092,50.0192832947],"type":"Point"}
}