{
  "type": "Feature",
  "properties": {
    "iso:country":"DE",
    "sg:address":"Zeppelinstr 146",
    "sg:city":"Pirmasens",
    "sg:phone":"+49 6331/51420",
    "sg:postcode":"66953",
    "sg:province":"Rheinland-Pfalz",
    "wof:name":"Wilhelm Hollinger Gmbh & Co Kg",
    "wof:placetype":"venue"
},
  "geometry": {"coordinates":[7.627233,49.205032],"type":"Point"}
}