{
  "type": "Feature",
  "properties": {
    "iso:country":"DE",
    "sg:address":"Hauptstr. 112",
    "sg:city":"Rimbach",
    "sg:phone":"+49 6253/85578",
    "sg:postcode":"64668",
    "sg:province":"Hessen",
    "wof:name":"Margit Harbich Steuerberaterin",
    "wof:placetype":"venue"
},
  "geometry": {"coordinates":[8.7798576355,49.5980682373],"type":"Point"}
}