{
  "type": "Feature",
  "properties": {
    "iso:country":"DE",
    "sg:address":"Mauseburg 6",
    "sg:city":"Barenburg",
    "sg:phone":"+49 4273/1288",
    "sg:postcode":"27245",
    "sg:province":"Niedersachsen",
    "wof:name":"Friedrich Vorwerk",
    "wof:placetype":"venue"
},
  "geometry": {"coordinates":[8.781235,52.626705],"type":"Point"}
}