{
  "type": "Feature",
  "properties": {
    "iso:country":"DE",
    "sg:address":"Uhlandstr. 4",
    "sg:city":"Gundelsheim",
    "sg:phone":"+49 6269/1404",
    "sg:postcode":"74831",
    "sg:province":"Baden-W\u00fcrttemberg",
    "wof:name":"Anton Baier",
    "wof:placetype":"venue"
},
  "geometry": {"coordinates":[9.163459,49.278641],"type":"Point"}
}