{
  "type": "Feature",
  "properties": {
    "iso:country":"DE",
    "sg:address":"Oststr. 10",
    "sg:city":"Contwig",
    "sg:phone":"+49 6332/5443",
    "sg:postcode":"66497",
    "sg:province":"Rheinland-Pfalz",
    "wof:name":"Form Und Funktion Kopf Wilfried Kopf",
    "wof:placetype":"venue"
},
  "geometry": {"coordinates":[7.438231,49.248821],"type":"Point"}
}