{
  "type": "Feature",
  "properties": {
    "iso:country":"DE",
    "sg:address":"Mauerackerstr. 8",
    "sg:city":"Elfershausen",
    "sg:phone":"+49 9704/387",
    "sg:postcode":"97725",
    "sg:province":"Bayern",
    "wof:name":"Peter L. Emmert Bildhauer",
    "wof:placetype":"venue"
},
  "geometry": {"coordinates":[9.961825,50.148251],"type":"Point"}
}