{
  "type": "Feature",
  "properties": {
    "iso:country":"DE",
    "sg:address":"Gr\u00e4frather Str. 84c",
    "sg:city":"Wuppertal",
    "sg:phone":"+49 202/7387239",
    "sg:postcode":"42329",
    "sg:province":"Nordrhein-Westfalen",
    "wof:name":"Drouven & Fabry Gmbh",
    "wof:placetype":"venue"
},
  "geometry": {"coordinates":[7.0685172081,51.2248840332],"type":"Point"}
}