{
  "type": "Feature",
  "properties": {
    "iso:country":"DE",
    "sg:address":"Wilhelmstr. 20",
    "sg:city":"Oberhausen",
    "sg:phone":"+49 208/633851",
    "sg:postcode":"46145",
    "sg:province":"Nordrhein-Westfalen",
    "wof:name":"E. Bischoff",
    "wof:placetype":"venue"
},
  "geometry": {"coordinates":[6.8455309868,51.5157814026],"type":"Point"}
}