{
  "type": "Feature",
  "properties": {
    "iso:country":"DE",
    "sg:address":"Karl-Stieler-Str. 28",
    "sg:city":"Holzkirchen",
    "sg:phone":"+49 8024/3757",
    "sg:postcode":"83607",
    "sg:province":"Bayern",
    "wof:name":"Jakob Ulrich Heckelsm\u00fcller Rechtsanwalt",
    "wof:placetype":"venue"
},
  "geometry": {"coordinates":[11.703795433,47.8869514465],"type":"Point"}
}