{
  "type": "Feature",
  "properties": {
    "iso:country":"DE",
    "sg:address":"Auenblick 7",
    "sg:city":"Burghausen",
    "sg:phone":"+49 341/4417607",
    "sg:postcode":"04430",
    "sg:province":"Bayern",
    "wof:name":"Dieter Flemming",
    "wof:placetype":"venue"
},
  "geometry": {"coordinates":[12.263415,51.358715],"type":"Point"}
}