{
  "type": "Feature",
  "properties": {
    "iso:country":"DE",
    "sg:address":"Kameralamtsstr. 22",
    "sg:city":"Stuttgart",
    "sg:postcode":"70439",
    "sg:province":"Baden-W\u00fcrttemberg",
    "wof:name":"Brigitte King",
    "wof:placetype":"venue"
},
  "geometry": {"coordinates":[9.162033,48.848637],"type":"Point"}
}