{
  "type": "Feature",
  "properties": {
    "iso:country":"DE",
    "sg:address":"Schwartauer Allee 44/44a",
    "sg:city":"L\u00fcbeck",
    "sg:phone":"+49 451/41220",
    "sg:postcode":"23554",
    "sg:province":"Schleswig-Holstein",
    "wof:name":"Turn- Und Sportbund L\u00fcbeck Gesch\u00e4ftsstelle",
    "wof:placetype":"venue"
},
  "geometry": {"coordinates":[10.6761426926,53.8741912842],"type":"Point"}
}