{
  "type": "Feature",
  "properties": {
    "iso:country":"DE",
    "sg:address":"Mannheimer Str. 213",
    "sg:city":"Bad Kreuznach",
    "sg:phone":"+49 671/65988",
    "sg:postcode":"55543",
    "sg:province":"Rheinland-Pfalz",
    "wof:name":"Eugen Falk",
    "wof:placetype":"venue"
},
  "geometry": {"coordinates":[7.8667178154,49.8386268616],"type":"Point"}
}