{
  "type": "Feature",
  "properties": {
    "iso:country":"DE",
    "sg:address":"Zietenstr. 1",
    "sg:city":"Chemnitz",
    "sg:phone":"+49 371/4012466",
    "sg:postcode":"09130",
    "sg:province":"Sachsen",
    "wof:name":"Sanit\u00c4tshaus",
    "wof:placetype":"venue"
},
  "geometry": {"coordinates":[12.9389047623,50.8311195374],"type":"Point"}
}