{
  "type": "Feature",
  "properties": {
    "iso:country":"DE",
    "sg:address":"Gernsbacher Str. 34",
    "sg:city":"Baden-Baden",
    "sg:phone":"+49 7221/22415",
    "sg:postcode":"76530",
    "sg:province":"Baden-W\u00fcrttemberg",
    "wof:name":"\u00c4rzteverband Baden-baden E. V. Gesch\u00e4ftsstelle",
    "wof:placetype":"venue"
},
  "geometry": {"coordinates":[8.24266,48.762463],"type":"Point"}
}