{
  "type": "Feature",
  "properties": {
    "iso:country":"DE",
    "sg:address":"K\u00f6lner Str. 115",
    "sg:city":"Dormagen",
    "sg:phone":"+49 2133/5436",
    "sg:postcode":"41539",
    "sg:province":"Nordrhein-Westfalen",
    "wof:name":"Freibeuter",
    "wof:placetype":"venue"
},
  "geometry": {"coordinates":[6.8414669037,51.0941886902],"type":"Point"}
}