{
  "type": "Feature",
  "properties": {
    "iso:country":"DE",
    "sg:address":"Essern",
    "sg:city":"Diepenau",
    "sg:phone":"+49 5777/265",
    "sg:postcode":"31603",
    "sg:province":"Niedersachsen",
    "wof:name":"Hermann Dr\u00f6ge",
    "wof:placetype":"venue"
},
  "geometry": {"coordinates":[8.74827,52.462734],"type":"Point"}
}