{
  "type": "Feature",
  "properties": {
    "iso:country":"DE",
    "sg:address":"Butenpa\u00df 3",
    "sg:city":"Rhede",
    "sg:phone":"+49 2872/805479",
    "sg:postcode":"46414",
    "sg:province":"Nordrhein-Westfalen",
    "wof:name":"Automobilzentrum A. Stadt - Rhede E.k.",
    "wof:placetype":"venue"
},
  "geometry": {"coordinates":[6.711507,51.831573],"type":"Point"}
}