{
  "type": "Feature",
  "properties": {
    "iso:country":"DE",
    "sg:address":"Heinrichstr. 17",
    "sg:city":"Bitburg",
    "sg:phone":"+49 6561/3259",
    "sg:postcode":"54634",
    "sg:province":"Rheinland-Pfalz",
    "wof:name":"Wilhelm Notte",
    "wof:placetype":"venue"
},
  "geometry": {"coordinates":[6.519551,49.968067],"type":"Point"}
}