{
  "type": "Feature",
  "properties": {
    "iso:country":"DE",
    "sg:address":"Drehbrunnenstr. 3",
    "sg:city":"Friedrichsthal",
    "sg:postcode":"66299",
    "sg:province":"Saarland",
    "wof:name":"Key-systems Gmbh",
    "wof:placetype":"venue"
},
  "geometry": {"coordinates":[7.0993800163,49.3289413452],"type":"Point"}
}