{
  "type": "Feature",
  "properties": {
    "iso:country":"DE",
    "sg:address":"Kalkofenstr. 19",
    "sg:city":"Villingen-Schwenningen",
    "sg:phone":"+49 7721/98230",
    "sg:postcode":"78050",
    "sg:province":"Baden-W\u00fcrttemberg",
    "wof:name":"Lothar Widmann Glade-beucke & Partner",
    "wof:placetype":"venue"
},
  "geometry": {"coordinates":[8.4535427094,48.0565376282],"type":"Point"}
}