{
  "type": "Feature",
  "properties": {
    "iso:country":"DE",
    "sg:address":"L\u00f6tscher Weg 54",
    "sg:city":"Nettetal",
    "sg:phone":"+49 2153/730716",
    "sg:postcode":"41334",
    "sg:province":"Nordrhein-Westfalen",
    "wof:name":"M.a.i. Norbert Kriegers E. K.",
    "wof:placetype":"venue"
},
  "geometry": {"coordinates":[6.2559337616,51.2897872925],"type":"Point"}
}