{
  "type": "Feature",
  "properties": {
    "iso:country":"DE",
    "sg:address":"Fischbeker Weg 23",
    "sg:city":"Hamburg",
    "sg:phone":"+49 40/7019007",
    "sg:postcode":"21149",
    "sg:province":"Hamburg",
    "wof:name":"Gerhardt M\u00fcller",
    "wof:placetype":"venue"
},
  "geometry": {"coordinates":[9.828913,53.473103],"type":"Point"}
}