{
  "type": "Feature",
  "properties": {
    "iso:country":"DE",
    "sg:address":"Ro\u00dfm\u00e4\u00dflerstr. 23",
    "sg:city":"Tharandt",
    "sg:phone":"+49 35203/2714",
    "sg:postcode":"01737",
    "sg:province":"Sachsen",
    "wof:name":"Kerstin Ehrt Steuerbevollm\u00e4chtigte",
    "wof:placetype":"venue"
},
  "geometry": {"coordinates":[13.5791435242,50.98620224],"type":"Point"}
}