{
  "type": "Feature",
  "properties": {
    "iso:country":"DE",
    "sg:address":"Nadorster Str. 254",
    "sg:city":"Oldenburg",
    "sg:phone":"+49 441/3800334",
    "sg:postcode":"26125",
    "sg:province":"Niedersachsen",
    "wof:name":"Jentson & Eisenhauer",
    "wof:placetype":"venue"
},
  "geometry": {"coordinates":[8.2259063721,53.164390564],"type":"Point"}
}