{
  "type": "Feature",
  "properties": {
    "iso:country":"DE",
    "sg:address":"Im Oberen Tal 18",
    "sg:city":"Aglasterhausen",
    "sg:phone":"+49 6262/2071",
    "sg:postcode":"74858",
    "sg:province":"Baden-W\u00fcrttemberg",
    "wof:name":"Stabilo Werkzeugfachmarkt",
    "wof:placetype":"venue"
},
  "geometry": {"coordinates":[8.983856,49.347439],"type":"Point"}
}