{
  "type": "Feature",
  "properties": {
    "iso:country":"DE",
    "sg:address":"Abt-Rumpler-Str. 11",
    "sg:city":"Neuhaus",
    "sg:phone":"+49 8503/91140",
    "sg:postcode":"94152",
    "sg:province":"Bayern",
    "wof:name":"Andreas Wagner",
    "wof:placetype":"venue"
},
  "geometry": {"coordinates":[13.4372062683,48.4856491089],"type":"Point"}
}