{
  "type": "Feature",
  "properties": {
    "iso:country":"DE",
    "sg:address":"Renneroder Str. 41",
    "sg:city":"Frankfurt",
    "sg:phone":"+49 69/347196",
    "sg:postcode":"65936",
    "sg:province":"Hessen",
    "wof:name":"Kanal-schaupp",
    "wof:placetype":"venue"
},
  "geometry": {"coordinates":[8.5629682541,50.1245727539],"type":"Point"}
}