{
  "type": "Feature",
  "properties": {
    "iso:country":"DE",
    "sg:address":"Diefenbachstr. 29",
    "sg:city":"M\u00fcnchen",
    "sg:phone":"+49 89/74995854",
    "sg:postcode":"81479",
    "sg:province":"Bayern",
    "wof:name":"Fontaine Und Partner Rechtsanw\u00e4lte",
    "wof:placetype":"venue"
},
  "geometry": {"coordinates":[11.5215759277,48.0790672302],"type":"Point"}
}