{
  "type": "Feature",
  "properties": {
    "iso:country":"DE",
    "sg:address":"Gutenbergstr. 33",
    "sg:city":"D\u00fcsseldorf",
    "sg:phone":"+49 211/683270",
    "sg:postcode":"40235",
    "sg:province":"Nordrhein-Westfalen",
    "wof:name":"Manfred Tischer",
    "wof:placetype":"venue"
},
  "geometry": {"coordinates":[6.8260211945,51.2440757751],"type":"Point"}
}