{
  "type": "Feature",
  "properties": {
    "iso:country":"DE",
    "sg:address":"Heiterwanger Str. 30",
    "sg:city":"M\u00fcnchen",
    "sg:phone":"+49 89/7600369",
    "sg:postcode":"81373",
    "sg:province":"Bayern",
    "wof:name":"Armin Oehrlein Rechtsanwalt",
    "wof:placetype":"venue"
},
  "geometry": {"coordinates":[11.5279798508,48.1216392517],"type":"Point"}
}