{
  "type": "Feature",
  "properties": {
    "iso:country":"DE",
    "sg:address":"Richard-Byrd-Str. 35",
    "sg:city":"K\u00f6ln",
    "sg:phone":"+49 221/9174240",
    "sg:postcode":"50829",
    "sg:province":"Nordrhein-Westfalen",
    "wof:name":"Schubert Dienstleistungen K\u00f6ln Verwaltungs- Gmbh",
    "wof:placetype":"venue"
},
  "geometry": {"coordinates":[6.8886442184,50.9894485474],"type":"Point"}
}