{
  "type": "Feature",
  "properties": {
    "iso:country":"DE",
    "sg:address":"Gartenheimallee 20",
    "sg:city":"Dresden",
    "sg:phone":"+49 351/2517922",
    "sg:postcode":"01277",
    "sg:province":"Sachsen",
    "wof:name":"Vat Baustofftechnik Gmbh",
    "wof:placetype":"venue"
},
  "geometry": {"coordinates":[13.791941,51.034088],"type":"Point"}
}