{
  "type": "Feature",
  "properties": {
    "iso:country":"DE",
    "sg:address":"Eisenbahnstr. 21",
    "sg:city":"Waldshut-Tiengen",
    "sg:phone":"+49 7751/4844",
    "sg:postcode":"79761",
    "sg:province":"Baden-W\u00fcrttemberg",
    "wof:name":"O. Maier Steuerberater",
    "wof:placetype":"venue"
},
  "geometry": {"coordinates":[8.2183094025,47.6218070984],"type":"Point"}
}