{
  "type": "Feature",
  "properties": {
    "iso:country":"DE",
    "sg:address":"Mittelweg 177",
    "sg:city":"Hamburg",
    "sg:phone":"+49 40/3805512",
    "sg:postcode":"20148",
    "sg:province":"Hamburg",
    "wof:name":"Lowe Lintas Hamburg Gmbh",
    "wof:placetype":"venue"
},
  "geometry": {"coordinates":[9.9946537018,53.5638656616],"type":"Point"}
}