{
  "type": "Feature",
  "properties": {
    "iso:country":"DE",
    "sg:address":"Rheinstr. 134",
    "sg:city":"Baden-Baden",
    "sg:phone":"+49 7221/62031",
    "sg:postcode":"76532",
    "sg:province":"Baden-W\u00fcrttemberg",
    "wof:name":"Lidl & Schwarz Kg",
    "wof:placetype":"venue"
},
  "geometry": {"coordinates":[8.2082357407,48.7822723389],"type":"Point"}
}