{
  "type": "Feature",
  "properties": {
    "iso:country":"DE",
    "sg:address":"Bismarckplatz 1-4",
    "sg:city":"M\u00f6nchengladbach",
    "sg:postcode":"41061",
    "sg:province":"Nordrhein-Westfalen",
    "wof:name":"Transfer Informations- Technologie Und Services Gmbh",
    "wof:placetype":"venue"
},
  "geometry": {"coordinates":[6.4426851273,51.1954994202],"type":"Point"}
}