{
  "type": "Feature",
  "properties": {
    "iso:country":"DE",
    "sg:address":"Breslauer Str. 20",
    "sg:city":"Winsen",
    "sg:phone":"+49 5143/761",
    "sg:postcode":"29308",
    "sg:province":"Niedersachsen",
    "wof:name":"Max Weishaupt Gmbh",
    "wof:placetype":"venue"
},
  "geometry": {"coordinates":[9.9257135391,52.6788444519],"type":"Point"}
}