{
  "type": "Feature",
  "properties": {
    "iso:country":"DE",
    "sg:address":"Ursulastr. 6",
    "sg:city":"Bochum",
    "sg:postcode":"44793",
    "sg:province":"Nordrhein-Westfalen",
    "wof:name":"Haasen Gmbh",
    "wof:placetype":"venue"
},
  "geometry": {"coordinates":[7.210293,51.475395],"type":"Point"}
}