{
  "type": "Feature",
  "properties": {
    "iso:country":"DE",
    "sg:address":"Werler Landstr. 2",
    "sg:city":"Soest",
    "sg:phone":"+49 2921/67170",
    "sg:postcode":"59494",
    "sg:province":"Nordrhein-Westfalen",
    "wof:name":"Ludewig & Bechheim Verwaltungs Gmbh",
    "wof:placetype":"venue"
},
  "geometry": {"coordinates":[8.088806,51.564526],"type":"Point"}
}