{
  "type": "Feature",
  "properties": {
    "iso:country":"DE",
    "sg:address":"Im Steinach 36",
    "sg:city":"Oberstdorf",
    "sg:phone":"+49 8322/3443",
    "sg:postcode":"87561",
    "sg:province":"Bayern",
    "wof:name":"Hans Bartl",
    "wof:placetype":"venue"
},
  "geometry": {"coordinates":[10.282758,47.415436],"type":"Point"}
}