{
  "type": "Feature",
  "properties": {
    "iso:country":"DE",
    "sg:address":"Sch\u00f6nenberger Str.",
    "sg:city":"\u00d6tisheim",
    "sg:phone":"+49 7041/5227",
    "sg:postcode":"75443",
    "sg:province":"Baden-W\u00fcrttemberg",
    "wof:name":"Lamm",
    "wof:placetype":"venue"
},
  "geometry": {"coordinates":[8.8075609207,48.961151123],"type":"Point"}
}