{
  "type": "Feature",
  "properties": {
    "iso:country":"DE",
    "sg:address":"Hinterer Weiler 1",
    "sg:city":"Pliezhausen",
    "sg:phone":"+49 7127/889659",
    "sg:postcode":"72124",
    "sg:province":"Baden-W\u00fcrttemberg",
    "wof:name":"H. J. Kern Gmbh Werkzeugmaschinen Service",
    "wof:placetype":"venue"
},
  "geometry": {"coordinates":[9.1782264709,48.5767173767],"type":"Point"}
}