{
  "type": "Feature",
  "properties": {
    "iso:country":"DE",
    "sg:address":"Welfenstr",
    "sg:city":"Dillingen",
    "sg:phone":"+49 9071",
    "sg:postcode":"89407",
    "sg:province":"Bayern",
    "wof:name":"Wbv",
    "wof:placetype":"venue"
},
  "geometry": {"coordinates":[10.46747,48.584454],"type":"Point"}
}