{
  "type": "Feature",
  "properties": {
    "iso:country":"DE",
    "sg:address":"Bahnhofstr. 9",
    "sg:city":"Verden",
    "sg:phone":"+49 4231/82176",
    "sg:postcode":"27283",
    "sg:province":"Niedersachsen",
    "wof:name":"Reiner Just",
    "wof:placetype":"venue"
},
  "geometry": {"coordinates":[9.2363672256,52.9214401245],"type":"Point"}
}