{
  "type": "Feature",
  "properties": {
    "iso:country":"DE",
    "sg:address":"Grabastr. 172",
    "sg:city":"Kiel",
    "sg:phone":"+49 431/722320",
    "sg:postcode":"24148",
    "sg:province":"Schleswig-Holstein",
    "wof:name":"Werner N\u00f6renberg Bauingenieur",
    "wof:placetype":"venue"
},
  "geometry": {"coordinates":[10.1685428619,54.3098373413],"type":"Point"}
}