{
  "type": "Feature",
  "properties": {
    "iso:country":"DE",
    "sg:address":"Untere Marktstr. 18",
    "sg:city":"Ludwigsburg",
    "sg:postcode":"71634",
    "sg:province":"Baden-W\u00fcrttemberg",
    "wof:name":"Reis Gmbh",
    "wof:placetype":"venue"
},
  "geometry": {"coordinates":[9.19144,48.898548],"type":"Point"}
}