{
  "type": "Feature",
  "properties": {
    "iso:country":"DE",
    "sg:address":"Untere Hauptstr. 135",
    "sg:city":"Beverungen",
    "sg:phone":"+49 5645/228",
    "sg:postcode":"37688",
    "sg:province":"Nordrhein-Westfalen",
    "wof:name":"Hedwig Groll",
    "wof:placetype":"venue"
},
  "geometry": {"coordinates":[9.2939167023,51.6282653809],"type":"Point"}
}