{
  "type": "Feature",
  "properties": {
    "iso:country":"DE",
    "sg:address":"Mittelstr. 19a",
    "sg:city":"Marienrachdorf",
    "sg:phone":"+49 2626/78707",
    "sg:postcode":"56242",
    "sg:province":"Rheinland-Pfalz",
    "wof:name":"Achim Radermacher Gmbh",
    "wof:placetype":"venue"
},
  "geometry": {"coordinates":[7.7144970894,50.5492630005],"type":"Point"}
}