{
  "type": "Feature",
  "properties": {
    "iso:country":"DE",
    "sg:address":"Schlehenweg 5",
    "sg:city":"Pulheim",
    "sg:postcode":"50259",
    "sg:province":"Nordrhein-Westfalen",
    "wof:name":"Servman Consulting Ohg",
    "wof:placetype":"venue"
},
  "geometry": {"coordinates":[6.7934041023,51.0042953491],"type":"Point"}
}