{
  "type": "Feature",
  "properties": {
    "iso:country":"DE",
    "sg:address":"Bahnhofstr. 35",
    "sg:city":"Edertal",
    "sg:postcode":"34549",
    "sg:province":"Hessen",
    "wof:name":"Bove Bodenveredelungsges. Mbh",
    "wof:placetype":"venue"
},
  "geometry": {"coordinates":[9.13454,51.1604],"type":"Point"}
}