{
  "type": "Feature",
  "properties": {
    "iso:country":"DE",
    "sg:address":"P\u00fcllenweg 33",
    "sg:city":"Korschenbroich",
    "sg:phone":"+49 2161/675949",
    "sg:postcode":"41352",
    "sg:province":"Nordrhein-Westfalen",
    "wof:name":"Sandwich & Co.",
    "wof:placetype":"venue"
},
  "geometry": {"coordinates":[6.5444469452,51.1985740662],"type":"Point"}
}