{
  "type": "Feature",
  "properties": {
    "iso:country":"DE",
    "sg:address":"Am Bermberg 39a",
    "sg:city":"Ruhla",
    "sg:phone":"+49 36929/80066",
    "sg:postcode":"99842",
    "sg:province":"Th\u00fcringen",
    "wof:name":"Judith T\u00fcrk",
    "wof:placetype":"venue"
},
  "geometry": {"coordinates":[10.362469,50.896324],"type":"Point"}
}