{
  "type": "Feature",
  "properties": {
    "iso:country":"DE",
    "sg:address":"Neugasse 13",
    "sg:city":"Mainz",
    "sg:phone":"+49 6136/42291",
    "sg:postcode":"55129",
    "sg:province":"Rheinland-Pfalz",
    "wof:name":"Werner Nauth",
    "wof:placetype":"venue"
},
  "geometry": {"coordinates":[8.2469882965,49.912853241],"type":"Point"}
}