{
  "type": "Feature",
  "properties": {
    "iso:country":"DE",
    "sg:address":"Sandstr. 78",
    "sg:city":"Bergheim",
    "sg:phone":"+49 2271/93697",
    "sg:postcode":"50127",
    "sg:province":"Nordrhein-Westfalen",
    "wof:name":"Maternus Rottland",
    "wof:placetype":"venue"
},
  "geometry": {"coordinates":[6.694032,50.934566],"type":"Point"}
}