{
  "type": "Feature",
  "properties": {
    "iso:country":"DE",
    "sg:address":"Von-Rosenbusch-Str. 8",
    "sg:city":"Nittendorf",
    "sg:phone":"+49 9404/1090",
    "sg:postcode":"93152",
    "sg:province":"Bayern",
    "wof:name":"Schlo\u00dfbrauerei Eichenhofen G\u00fcnther Von Braunbehrens",
    "wof:placetype":"venue"
},
  "geometry": {"coordinates":[11.9261989594,49.0160522461],"type":"Point"}
}