{
  "type": "Feature",
  "properties": {
    "iso:country":"DE",
    "sg:address":"Philipp-Reis-Str. 2",
    "sg:city":"Neu-Anspach",
    "sg:phone":"+49 6081/943715",
    "sg:postcode":"61267",
    "sg:province":"Hessen",
    "wof:name":"F\u00f6lsing Rechtsanw\u00e4lte",
    "wof:placetype":"venue"
},
  "geometry": {"coordinates":[8.510474205,50.3076934814],"type":"Point"}
}