{
  "type": "Feature",
  "properties": {
    "iso:country":"DE",
    "sg:address":"Holzgass\u00e4cker 5",
    "sg:city":"Ehingen",
    "sg:phone":"+49 7391/1656",
    "sg:postcode":"89584",
    "sg:province":"Baden-W\u00fcrttemberg",
    "wof:name":"Dietmar Kammel",
    "wof:placetype":"venue"
},
  "geometry": {"coordinates":[9.7384061813,48.2313270569],"type":"Point"}
}