{
  "type": "Feature",
  "properties": {
    "iso:country":"DE",
    "sg:address":"Oberer Wiesentalweg 10",
    "sg:city":"Hof",
    "sg:phone":"+49 9281/41674",
    "sg:postcode":"95028",
    "sg:province":"Bayern",
    "wof:name":"Iko Immobilien Koordination Inh. Christa K\u00f6ppel",
    "wof:placetype":"venue"
},
  "geometry": {"coordinates":[11.9400682449,50.309463501],"type":"Point"}
}