{
  "type": "Feature",
  "properties": {
    "iso:country":"DE",
    "sg:address":"Rohrweg 3",
    "sg:city":"Borken",
    "sg:phone":"+49 5682/1851",
    "sg:postcode":"34582",
    "sg:province":"Hessen",
    "wof:name":"Peter Otto",
    "wof:placetype":"venue"
},
  "geometry": {"coordinates":[9.346002,51.062447],"type":"Point"}
}