{
  "type": "Feature",
  "properties": {
    "iso:country":"DE",
    "sg:address":"Gecksberg 2a",
    "sg:city":"Rhens",
    "sg:phone":"+49 2628/3011",
    "sg:postcode":"56321",
    "sg:province":"Rheinland-Pfalz",
    "wof:name":"Gries",
    "wof:placetype":"venue"
},
  "geometry": {"coordinates":[7.617253,50.283009],"type":"Point"}
}