{
  "type": "Feature",
  "properties": {
    "iso:country":"DE",
    "sg:address":"Schaumburgstr. 14-16",
    "sg:city":"Recklinghausen",
    "sg:phone":"+49 2361/23415",
    "sg:postcode":"45657",
    "sg:province":"Nordrhein-Westfalen",
    "wof:name":"Kammer-lichtspiele",
    "wof:placetype":"venue"
},
  "geometry": {"coordinates":[7.200704,51.614014],"type":"Point"}
}