{
  "type": "Feature",
  "properties": {
    "iso:country":"DE",
    "sg:address":"Struvestr. 15",
    "sg:city":"G\u00f6rlitz",
    "sg:phone":"+49 3581/422630",
    "sg:postcode":"02826",
    "sg:province":"Sachsen",
    "wof:name":"Ruhland Und Partner Rechtsanw\u00e4lte",
    "wof:placetype":"venue"
},
  "geometry": {"coordinates":[14.9919052124,51.1535835266],"type":"Point"}
}