{
  "type": "Feature",
  "properties": {
    "iso:country":"DE",
    "sg:address":"Fichtenweg 5",
    "sg:city":"Sch\u00f6mberg",
    "sg:phone":"+49 7084/6411",
    "sg:postcode":"75328",
    "sg:province":"Baden-W\u00fcrttemberg",
    "wof:name":"Werner R\u00f6selm\u00fcller",
    "wof:placetype":"venue"
},
  "geometry": {"coordinates":[8.6526975632,48.7849845886],"type":"Point"}
}