{
  "type": "Feature",
  "properties": {
    "iso:country":"DE",
    "sg:address":"Hangstr. 2",
    "sg:city":"Bockenem",
    "sg:phone":"+49 5067/3111",
    "sg:postcode":"31167",
    "sg:province":"Niedersachsen",
    "wof:name":"R. Birkner Steuerberater",
    "wof:placetype":"venue"
},
  "geometry": {"coordinates":[10.0675029755,52.0343208313],"type":"Point"}
}