{
  "type": "Feature",
  "properties": {
    "iso:country":"DE",
    "sg:address":"Neu S\u00fcllitz",
    "sg:city":"Ostseebad Binz",
    "sg:phone":"+49 38393/2753",
    "sg:postcode":"18609",
    "sg:province":"Mecklenburg-Vorpommern",
    "wof:name":"R. H\u00e4ger",
    "wof:placetype":"venue"
},
  "geometry": {"coordinates":[13.6080102921,54.4007606506],"type":"Point"}
}