{
  "type": "Feature",
  "properties": {
    "iso:country":"DE",
    "sg:address":"Uellendahler Str. 27",
    "sg:city":"Wuppertal",
    "sg:phone":"+49 202/2442413",
    "sg:postcode":"42107",
    "sg:province":"Nordrhein-Westfalen",
    "wof:name":"Ludwig Handels-gmbh",
    "wof:placetype":"venue"
},
  "geometry": {"coordinates":[7.1475768089,51.2664756775],"type":"Point"}
}