{
  "type": "Feature",
  "properties": {
    "iso:country":"DE",
    "sg:address":"Meierstr. 4",
    "sg:city":"Giesen",
    "sg:phone":"+49 5121/777251",
    "sg:postcode":"31180",
    "sg:province":"Niedersachsen",
    "wof:name":"Franz Linkogel",
    "wof:placetype":"venue"
},
  "geometry": {"coordinates":[9.919309,52.197079],"type":"Point"}
}