{
  "type": "Feature",
  "properties": {
    "iso:country":"DE",
    "sg:address":"Bildst\u00f6ckleweg 29",
    "sg:city":"Baiersbronn",
    "sg:phone":"+49 7442/6558",
    "sg:postcode":"72270",
    "sg:province":"Baden-W\u00fcrttemberg",
    "wof:name":"R. Becker",
    "wof:placetype":"venue"
},
  "geometry": {"coordinates":[8.3667812347,48.5081748962],"type":"Point"}
}