{
  "type": "Feature",
  "properties": {
    "iso:country":"DE",
    "sg:address":"Furtstr. 14",
    "sg:city":"Bremen",
    "sg:phone":"+49 421/694869",
    "sg:postcode":"28759",
    "sg:province":"Bremen",
    "wof:name":"B & N Wertstoffaufbereitung Bremen Beteiligungs Gmbh",
    "wof:placetype":"venue"
},
  "geometry": {"coordinates":[8.640253,53.169788],"type":"Point"}
}