{
  "type": "Feature",
  "properties": {
    "iso:country":"DE",
    "sg:address":"Andreas-Koch-Str. 9",
    "sg:city":"Trossingen",
    "sg:phone":"+49 7425/200",
    "sg:postcode":"78647",
    "sg:province":"Baden-W\u00fcrttemberg",
    "wof:name":"Hohner Grundst\u00fccksges. Mbh & Co. Kg",
    "wof:placetype":"venue"
},
  "geometry": {"coordinates":[8.6270170212,48.0733795166],"type":"Point"}
}