{
  "type": "Feature",
  "properties": {
    "iso:country":"DE",
    "sg:address":"Hochstiftstr. 24",
    "sg:city":"Regensburg",
    "sg:phone":"+49 941/401467",
    "sg:postcode":"93055",
    "sg:province":"Bayern",
    "wof:name":"Ambulante Krankenpflege",
    "wof:placetype":"venue"
},
  "geometry": {"coordinates":[12.150075,49.024261],"type":"Point"}
}