{
  "type": "Feature",
  "properties": {
    "iso:country":"DE",
    "sg:address":"Holtenauer Str. 152",
    "sg:city":"Kiel",
    "sg:phone":"+49 431/81606",
    "sg:postcode":"24105",
    "sg:province":"Schleswig-Holstein",
    "wof:name":"Restaurant Lammers",
    "wof:placetype":"venue"
},
  "geometry": {"coordinates":[10.1338434219,54.3388748169],"type":"Point"}
}