{
  "type": "Feature",
  "properties": {
    "iso:country":"DE",
    "sg:address":"Robert-Feulgen-Str. 40",
    "sg:city":"Essen",
    "sg:phone":"+49 201/407404",
    "sg:postcode":"45239",
    "sg:province":"Nordrhein-Westfalen",
    "wof:name":"Manfred Stolz Steuerberater",
    "wof:placetype":"venue"
},
  "geometry": {"coordinates":[7.0086240768,51.395198822],"type":"Point"}
}