{
  "type": "Feature",
  "properties": {
    "iso:country":"DE",
    "sg:address":"Zum Nesselberg 27",
    "sg:city":"Springe",
    "sg:phone":"+49 5041/63763",
    "sg:postcode":"31832",
    "sg:province":"Niedersachsen",
    "wof:name":"Heiko Schaper",
    "wof:placetype":"venue"
},
  "geometry": {"coordinates":[9.5189676285,52.1699829102],"type":"Point"}
}