{
  "type": "Feature",
  "properties": {
    "iso:country":"DE",
    "sg:address":"Helmsdorfer Str. 8",
    "sg:city":"Stolpen",
    "sg:phone":"+49 35973/26575",
    "sg:postcode":"01833",
    "sg:province":"Sachsen",
    "wof:name":"J. Thierse",
    "wof:placetype":"venue"
},
  "geometry": {"coordinates":[14.0596,51.056431],"type":"Point"}
}