{
  "type": "Feature",
  "properties": {
    "iso:country":"DE",
    "sg:address":"In der Neuen Welt 8",
    "sg:city":"Memmingen",
    "sg:postcode":"87700",
    "sg:province":"Bayern",
    "wof:name":"Piron Prozesstechnik Gmbh & Co. Kg",
    "wof:placetype":"venue"
},
  "geometry": {"coordinates":[10.186135,47.999325],"type":"Point"}
}