{
  "type": "Feature",
  "properties": {
    "iso:country":"DE",
    "sg:address":"Breite Str. 18",
    "sg:city":"Hosena",
    "sg:phone":"+49 357564031193",
    "sg:postcode":"01996",
    "sg:province":"Brandenburg",
    "wof:name":"Dentalchemie Hohenbocka Dentalgips",
    "wof:placetype":"venue"
},
  "geometry": {"coordinates":[14.0072898865,51.4545135498],"type":"Point"}
}