{
  "type": "Feature",
  "properties": {
    "iso:country":"DE",
    "sg:address":"Mauerstr.5",
    "sg:city":"H\u00fcffler",
    "sg:phone":"+49 6384/6630",
    "sg:postcode":"66909",
    "sg:province":"Rheinland-Pfalz",
    "wof:name":"Kaufhaus 2000",
    "wof:placetype":"venue"
},
  "geometry": {"coordinates":[7.389081955,49.4920425415],"type":"Point"}
}