{
  "type": "Feature",
  "properties": {
    "iso:country":"DE",
    "sg:address":"Albert-Schweitzer-Str. 20 a",
    "sg:city":"Bad Salzungen",
    "sg:phone":"+49 3695/608030",
    "sg:postcode":"36433",
    "sg:province":"Th\u00fcringen",
    "wof:name":"Veronika Lucke",
    "wof:placetype":"venue"
},
  "geometry": {"coordinates":[10.243006,50.806847],"type":"Point"}
}