{
  "type": "Feature",
  "properties": {
    "iso:country":"DE",
    "sg:address":"Wasserburger Landstr. 220",
    "sg:city":"M\u00fcnchen",
    "sg:phone":"+49 89/4392099",
    "sg:postcode":"81827",
    "sg:province":"Bayern",
    "wof:name":"Wilfried Sydow Rechtsanw\u00e4lte",
    "wof:placetype":"venue"
},
  "geometry": {"coordinates":[11.7029676437,48.1125144958],"type":"Point"}
}