{
  "type": "Feature",
  "properties": {
    "iso:country":"DE",
    "sg:address":"Im St\u00f6ckacker 16",
    "sg:city":"Umkirch",
    "sg:phone":"+49 7665/51472",
    "sg:postcode":"79224",
    "sg:province":"Baden-W\u00fcrttemberg",
    "wof:name":"Kurt Hauri Grundst\u00fccksver- Waltungs Gmbh",
    "wof:placetype":"venue"
},
  "geometry": {"coordinates":[7.7648901939,48.0436592102],"type":"Point"}
}