{
  "type": "Feature",
  "properties": {
    "iso:country":"DE",
    "sg:address":"Bergedorfer Schlo\u00dfstr. 33",
    "sg:city":"Hamburg",
    "sg:phone":"+49 40/7211445",
    "sg:postcode":"21029",
    "sg:province":"Hamburg",
    "wof:name":"Pizzeria Vulcanus",
    "wof:placetype":"venue"
},
  "geometry": {"coordinates":[10.2153568268,53.4872245789],"type":"Point"}
}