{
  "type": "Feature",
  "properties": {
    "iso:country":"DE",
    "sg:address":"Gutenbergstr. 1",
    "sg:city":"Hamm",
    "sg:postcode":"59065",
    "sg:province":"Nordrhein-Westfalen",
    "wof:name":"Gvg Gesellschaft F\u00fcr Verlags- Gesch\u00e4fte Ohg",
    "wof:placetype":"venue"
},
  "geometry": {"coordinates":[7.820606,51.680817],"type":"Point"}
}