{
  "type": "Feature",
  "properties": {
    "iso:country":"DE",
    "sg:address":"Lilienthalstr 42",
    "sg:city":"Viersen",
    "sg:phone":"+49 2162/102195",
    "sg:postcode":"41749",
    "sg:province":"Nordrhein-Westfalen",
    "wof:name":"Elfeplastic",
    "wof:placetype":"venue"
},
  "geometry": {"coordinates":[6.3606200218,51.2948493958],"type":"Point"}
}