{
  "type": "Feature",
  "properties": {
    "iso:country":"DE",
    "sg:address":"Wei\u00dfenburger Str. 28",
    "sg:city":"Niederschlettenbach",
    "sg:phone":"+49 6394/465",
    "sg:postcode":"76891",
    "sg:province":"Rheinland-Pfalz",
    "wof:name":"Emil Mertz",
    "wof:placetype":"venue"
},
  "geometry": {"coordinates":[7.8482861519,49.0842170715],"type":"Point"}
}