{
  "type": "Feature",
  "properties": {
    "iso:country":"DE",
    "sg:address":"Leopoldstr. 59",
    "sg:city":"Ludwigshafen",
    "sg:phone":"+49 621/692560",
    "sg:postcode":"67063",
    "sg:province":"Rheinland-Pfalz",
    "wof:name":"Restaurant Sonne",
    "wof:placetype":"venue"
},
  "geometry": {"coordinates":[8.4210147858,49.4986000061],"type":"Point"}
}