{
  "type": "Feature",
  "properties": {
    "iso:country":"DE",
    "sg:address":"Pyrastr. 2",
    "sg:city":"Cottbus",
    "sg:phone":"+49 355/4994290",
    "sg:postcode":"03050",
    "sg:province":"Brandenburg",
    "wof:name":"Ibs Immobilien Vermittlungs- Und",
    "wof:placetype":"venue"
},
  "geometry": {"coordinates":[14.332762,51.74802],"type":"Point"}
}