{
  "type": "Feature",
  "properties": {
    "iso:country":"DE",
    "sg:address":"Hauptstr. 6",
    "sg:city":"Stetten",
    "sg:phone":"+49 7532/47177",
    "sg:postcode":"88719",
    "sg:province":"Baden-W\u00fcrttemberg",
    "wof:name":"Bestattungsdienst Wurm Gmbh",
    "wof:placetype":"venue"
},
  "geometry": {"coordinates":[9.297476,47.690884],"type":"Point"}
}