{
  "type": "Feature",
  "properties": {
    "iso:country":"DE",
    "sg:address":"Schlaa 5",
    "sg:city":"Albersdorf",
    "sg:phone":"+49 4835/625",
    "sg:postcode":"25767",
    "sg:province":"Schleswig-Holstein",
    "wof:name":"Otto Nottelmann",
    "wof:placetype":"venue"
},
  "geometry": {"coordinates":[9.266776,54.130924],"type":"Point"}
}