{
  "type": "Feature",
  "properties": {
    "iso:country":"DE",
    "sg:address":"Markt 5-6",
    "sg:city":"Bad Schwartau",
    "sg:phone":"+49 451/22027",
    "sg:postcode":"23611",
    "sg:province":"Schleswig-Holstein",
    "wof:name":"Brandt Immoiblien- Und Verwaltungsgesellschaft Mbh",
    "wof:placetype":"venue"
},
  "geometry": {"coordinates":[10.6979560852,53.920173645],"type":"Point"}
}