{
  "type": "Feature",
  "properties": {
    "iso:country":"DE",
    "sg:address":"Birkenweg 4",
    "sg:city":"Meitzendorf",
    "sg:phone":"+49 39202/60620",
    "sg:postcode":"39326",
    "sg:province":"Sachsen-Anhalt",
    "wof:name":"I. Grape",
    "wof:placetype":"venue"
},
  "geometry": {"coordinates":[11.562561,52.212696],"type":"Point"}
}