{
  "type": "Feature",
  "properties": {
    "iso:country":"DE",
    "sg:address":"Oberm\u00f6gersheim 21",
    "sg:city":"Wassertr\u00fcdingen",
    "sg:phone":"+49 9836/472",
    "sg:postcode":"91717",
    "sg:province":"Bayern",
    "wof:name":"H. Loacher",
    "wof:placetype":"venue"
},
  "geometry": {"coordinates":[10.6616001129,49.0564117432],"type":"Point"}
}