{
  "type": "Feature",
  "properties": {
    "iso:country":"DE",
    "sg:address":"Sohlweg 75",
    "sg:city":"Niederkr\u00fcchten",
    "sg:phone":"+49 2163/983340",
    "sg:postcode":"41372",
    "sg:province":"Nordrhein-Westfalen",
    "wof:name":"Elbau Gmbh",
    "wof:placetype":"venue"
},
  "geometry": {"coordinates":[6.183273,51.21159],"type":"Point"}
}