{
  "type": "Feature",
  "properties": {
    "iso:country":"DE",
    "sg:address":"Querstr. 2",
    "sg:city":"Neukieritzsch",
    "sg:phone":"+49 34342/51410",
    "sg:postcode":"04575",
    "sg:province":"Sachsen",
    "wof:name":"Annett Roefke",
    "wof:placetype":"venue"
},
  "geometry": {"coordinates":[12.410199,51.151936],"type":"Point"}
}