{
  "type": "Feature",
  "properties": {
    "iso:country":"DE",
    "sg:address":"Rainweg 15",
    "sg:city":"Wilhelmsfeld",
    "sg:phone":"+49 6220/911061",
    "sg:postcode":"69259",
    "sg:province":"Baden-W\u00fcrttemberg",
    "wof:name":"Voice Maze Gmbh",
    "wof:placetype":"venue"
},
  "geometry": {"coordinates":[8.759455,49.472961],"type":"Point"}
}