{
  "type": "Feature",
  "properties": {
    "iso:country":"DE",
    "sg:address":"In der Aue 2",
    "sg:city":"K\u00f6ln",
    "sg:phone":"+49 2236/962640",
    "sg:postcode":"50999",
    "sg:province":"Nordrhein-Westfalen",
    "wof:name":"Gvm Gesellschaft F\u00fcr Vertriebs-marketing Mbh",
    "wof:placetype":"venue"
},
  "geometry": {"coordinates":[6.995511055,50.8538589478],"type":"Point"}
}