{
  "type": "Feature",
  "properties": {
    "iso:country":"DE",
    "sg:address":"Am Schemm 16",
    "sg:city":"Geseke",
    "sg:phone":"+49 2942",
    "sg:postcode":"59590",
    "sg:province":"Nordrhein-Westfalen",
    "wof:name":"Cdu Ortsunion Ehringhausen",
    "wof:placetype":"venue"
},
  "geometry": {"coordinates":[8.4407653809,51.65782547],"type":"Point"}
}