{
  "type": "Feature",
  "properties": {
    "iso:country":"DE",
    "sg:address":"Finkenweg 67",
    "sg:city":"Babenhausen",
    "sg:phone":"+49 6073/63122",
    "sg:postcode":"64832",
    "sg:province":"Hessen",
    "wof:name":"Doris D\u00f6ppes Papiererzeugnisse",
    "wof:placetype":"venue"
},
  "geometry": {"coordinates":[8.967006,49.9725],"type":"Point"}
}