{
  "type": "Feature",
  "properties": {
    "iso:country":"DE",
    "sg:address":"Neusser Str. 2",
    "sg:city":"Bergheim",
    "sg:phone":"+49 2271/41465",
    "sg:postcode":"50126",
    "sg:province":"Nordrhein-Westfalen",
    "wof:name":"M. Endrikat",
    "wof:placetype":"venue"
},
  "geometry": {"coordinates":[6.6362071037,50.9599151611],"type":"Point"}
}