{
  "type": "Feature",
  "properties": {
    "iso:country":"DE",
    "sg:address":"Schlo\u00dfstr. 28",
    "sg:city":"Eppelborn",
    "sg:phone":"+49 6881/6578",
    "sg:postcode":"66571",
    "sg:province":"Saarland",
    "wof:name":"Margit Solander",
    "wof:placetype":"venue"
},
  "geometry": {"coordinates":[6.968475,49.404663],"type":"Point"}
}