{
  "type": "Feature",
  "properties": {
    "iso:country":"DE",
    "sg:address":"Erlenring 13",
    "sg:city":"Bad Vilbel",
    "sg:phone":"+49 6101/4534",
    "sg:postcode":"61118",
    "sg:province":"Hessen",
    "wof:name":"Edgar W. Moog",
    "wof:placetype":"venue"
},
  "geometry": {"coordinates":[8.7197475433,50.185508728],"type":"Point"}
}