{
  "type": "Feature",
  "properties": {
    "iso:country":"DE",
    "sg:address":"Walbergraben 6",
    "sg:city":"A\u00dflar",
    "sg:postcode":"35614",
    "sg:province":"Hessen",
    "wof:name":"Aldi Gmbh & Co. Kg",
    "wof:placetype":"venue"
},
  "geometry": {"coordinates":[8.4801950455,50.5843238831],"type":"Point"}
}