{
  "type": "Feature",
  "properties": {
    "iso:country":"DE",
    "sg:address":"Obertal 15",
    "sg:city":"Nassau",
    "sg:phone":"+49 2604/4090",
    "sg:postcode":"56377",
    "sg:province":"Rheinland-Pfalz",
    "wof:name":"Helmut Bl\u00e4sche",
    "wof:placetype":"venue"
},
  "geometry": {"coordinates":[7.798853,50.314018],"type":"Point"}
}