{
  "type": "Feature",
  "properties": {
    "iso:country":"DE",
    "sg:address":"Ammergauer Str. 16 a",
    "sg:city":"Saulgrub",
    "sg:phone":"+49 8845/8195",
    "sg:postcode":"82442",
    "sg:province":"Bayern",
    "wof:name":"H. Ullsperger",
    "wof:placetype":"venue"
},
  "geometry": {"coordinates":[11.024492,47.666023],"type":"Point"}
}