{
  "type": "Feature",
  "properties": {
    "iso:country":"DE",
    "sg:address":"Brixplatz 4",
    "sg:city":"Berlin",
    "sg:phone":"+49 30/3040886",
    "sg:postcode":"14052",
    "sg:province":"Berlin",
    "wof:name":"Heinz-paul Taeger",
    "wof:placetype":"venue"
},
  "geometry": {"coordinates":[13.255342,52.519726],"type":"Point"}
}