{
  "type": "Feature",
  "properties": {
    "iso:country":"DE",
    "sg:address":"Mittelstr. 7a",
    "sg:city":"Dreisen",
    "sg:phone":"+49 6357/1264",
    "sg:postcode":"67816",
    "sg:province":"Rheinland-Pfalz",
    "wof:name":"Pebetho Metallbau Gmbh",
    "wof:placetype":"venue"
},
  "geometry": {"coordinates":[8.0124359131,49.602432251],"type":"Point"}
}