{
  "type": "Feature",
  "properties": {
    "iso:country":"DE",
    "sg:address":"Josef-Ressel-Str. 32a",
    "sg:city":"M\u00fcnchen",
    "sg:phone":"+49 89/3118813",
    "sg:postcode":"80937",
    "sg:province":"Bayern",
    "wof:name":"Klaus Gerner Gmbh",
    "wof:placetype":"venue"
},
  "geometry": {"coordinates":[11.577233,48.198158],"type":"Point"}
}