{
  "type": "Feature",
  "properties": {
    "iso:country":"DE",
    "sg:address":"Im Tal 70b",
    "sg:city":"Aufse\u00df",
    "sg:phone":"+49 9198/8282",
    "sg:postcode":"91347",
    "sg:province":"Bayern",
    "wof:name":"Aufsesser Premiumbier Frank Rothenbach Gmbh",
    "wof:placetype":"venue"
},
  "geometry": {"coordinates":[11.228148,49.884277],"type":"Point"}
}