{
  "type": "Feature",
  "properties": {
    "iso:country":"DE",
    "sg:address":"Nycolaistr. 12",
    "sg:city":"Paderborn",
    "sg:phone":"+49 5293/1350",
    "sg:postcode":"33100",
    "sg:province":"Nordrhein-Westfalen",
    "wof:name":"G. Dedinski Bauunternehmen",
    "wof:placetype":"venue"
},
  "geometry": {"coordinates":[8.845085,51.69899],"type":"Point"}
}