{
  "type": "Feature",
  "properties": {
    "iso:country":"DE",
    "sg:address":"M\u00fcnchbergstr. 43",
    "sg:city":"Helmbrechts",
    "sg:phone":"+49 9252/99530",
    "sg:postcode":"95233",
    "sg:province":"Bayern",
    "wof:name":"Zipse - Armaturen",
    "wof:placetype":"venue"
},
  "geometry": {"coordinates":[11.721876,50.238205],"type":"Point"}
}