{
  "type": "Feature",
  "properties": {
    "iso:country":"DE",
    "sg:city":"Freiburg",
    "sg:postcode":"79104",
    "sg:province":"Baden-W\u00fcrttemberg",
    "wof:name":"Ulrich Gramm - Supervision",
    "wof:placetype":"venue"
},
  "geometry": {"coordinates":[7.86087,48.008171],"type":"Point"}
}