{
  "type": "Feature",
  "properties": {
    "iso:country":"DE",
    "sg:address":"Berolinastr. 21",
    "sg:city":"Berlin",
    "sg:postcode":"10178",
    "sg:province":"Berlin",
    "wof:name":"Jww Am Alex Werbeservice Und Vertrieb",
    "wof:placetype":"venue"
},
  "geometry": {"coordinates":[13.419711113,52.5221633911],"type":"Point"}
}