{
  "type": "Feature",
  "properties": {
    "iso:country":"DE",
    "sg:address":"Van-der-Upwich-Str 38",
    "sg:city":"Nettetal",
    "sg:phone":"+49 2153/60612",
    "sg:postcode":"41334",
    "sg:province":"Nordrhein-Westfalen",
    "wof:name":"Bootswerft Wefers",
    "wof:placetype":"venue"
},
  "geometry": {"coordinates":[6.286879,51.311314],"type":"Point"}
}