{
  "type": "Feature",
  "properties": {
    "iso:country":"DE",
    "sg:address":"Glogauer Str. 1",
    "sg:city":"H\u00f6chstadt",
    "sg:phone":"+49 9193/1874",
    "sg:postcode":"91315",
    "sg:province":"Bayern",
    "wof:name":"Pauls Keller",
    "wof:placetype":"venue"
},
  "geometry": {"coordinates":[10.8063697815,49.6923751831],"type":"Point"}
}