{
  "type": "Feature",
  "properties": {
    "iso:country":"DE",
    "sg:address":"Am Wasserturm 3",
    "sg:city":"Heusweiler",
    "sg:phone":"+49 6806/98380",
    "sg:postcode":"66265",
    "sg:province":"Saarland",
    "wof:name":"Bla\u00df Gmbh",
    "wof:placetype":"venue"
},
  "geometry": {"coordinates":[7.0087599754,49.3355636597],"type":"Point"}
}