{
  "type": "Feature",
  "properties": {
    "iso:country":"DE",
    "sg:address":"Parkallee 32",
    "sg:city":"Reinbek",
    "sg:phone":"+49 40/7222672",
    "sg:postcode":"21465",
    "sg:province":"Schleswig-Holstein",
    "wof:name":"Klaus-peter Puls Rechtsanwalt",
    "wof:placetype":"venue"
},
  "geometry": {"coordinates":[10.2545509338,53.5126800537],"type":"Point"}
}