{
  "type": "Feature",
  "properties": {
    "iso:country":"DE",
    "sg:address":"Moorburg 13",
    "sg:city":"Marxen",
    "sg:phone":"+49 4185/5253",
    "sg:postcode":"21439",
    "sg:province":"Niedersachsen",
    "wof:name":"Bert Zander",
    "wof:placetype":"venue"
},
  "geometry": {"coordinates":[10.006445,53.311886],"type":"Point"}
}