{
  "type": "Feature",
  "properties": {
    "iso:country":"DE",
    "sg:address":"Emmericher Str. 10",
    "sg:city":"N\u00fcrnberg",
    "sg:phone":"+49 911/52030",
    "sg:postcode":"90411",
    "sg:province":"Bayern",
    "wof:name":"Omnia - Print Gmbh",
    "wof:placetype":"venue"
},
  "geometry": {"coordinates":[11.11078,49.502766],"type":"Point"}
}