{
  "type": "Feature",
  "properties": {
    "iso:country":"DE",
    "sg:address":"Vogtswiesen 60",
    "sg:city":"Schorndorf",
    "sg:phone":"+49 7181/978440",
    "sg:postcode":"73614",
    "sg:province":"Baden-W\u00fcrttemberg",
    "wof:name":"Hesse Gmbh",
    "wof:placetype":"venue"
},
  "geometry": {"coordinates":[9.515954,48.826641],"type":"Point"}
}