{
  "type": "Feature",
  "properties": {
    "iso:country":"DE",
    "sg:address":"K\u00f6nigsberger Str. 15",
    "sg:city":"Biblis",
    "sg:phone":"+49 6245/905190",
    "sg:postcode":"68647",
    "sg:province":"Hessen",
    "wof:name":"Bruno Neumann B\u00fcro F\u00fcr Statik",
    "wof:placetype":"venue"
},
  "geometry": {"coordinates":[8.444331,49.687981],"type":"Point"}
}