{
  "type": "Feature",
  "properties": {
    "iso:country":"DE",
    "sg:address":"Lehrh\u00f6fer Str. 35",
    "sg:city":"Hanau",
    "sg:phone":"+49 6181/257013",
    "sg:postcode":"63457",
    "sg:province":"Hessen",
    "wof:name":"Holger Tretter Finanzberater",
    "wof:placetype":"venue"
},
  "geometry": {"coordinates":[8.954328537,50.1200332642],"type":"Point"}
}