{
  "type": "Feature",
  "properties": {
    "iso:country":"DE",
    "sg:address":"R\u00f6telbachstr. 91",
    "sg:city":"Ulm",
    "sg:phone":"+49 7305/962931",
    "sg:postcode":"89079",
    "sg:province":"Baden-W\u00fcrttemberg",
    "wof:name":"S. A. D. Software Vertriebs- U. Produktions Gmbh",
    "wof:placetype":"venue"
},
  "geometry": {"coordinates":[9.9102802277,48.35364151],"type":"Point"}
}