{
  "type": "Feature",
  "properties": {
    "iso:country":"DE",
    "sg:address":"Behringstrasse 7",
    "sg:city":"Herrenberg",
    "sg:phone":"+49 7032",
    "sg:postcode":"71126",
    "sg:province":"Baden-W\u00fcrttemberg",
    "wof:name":"Aps - Alternative Printing Services",
    "wof:placetype":"venue"
},
  "geometry": {"coordinates":[8.8868808746,48.5767555237],"type":"Point"}
}