{
  "type": "Feature",
  "properties": {
    "iso:country":"DE",
    "sg:address":"Wuhrstr. 2",
    "sg:city":"Bad Buchau",
    "sg:phone":"+49 7582/2155",
    "sg:postcode":"88422",
    "sg:province":"Baden-W\u00fcrttemberg",
    "wof:name":"Kurt Moll",
    "wof:placetype":"venue"
},
  "geometry": {"coordinates":[9.6083431244,48.0632324219],"type":"Point"}
}