{
  "type": "Feature",
  "properties": {
    "iso:country":"DE",
    "sg:address":"Walther-Rathenau-Str. 3",
    "sg:city":"Duisburg",
    "sg:phone":"+49 2065/41394",
    "sg:postcode":"47229",
    "sg:province":"Nordrhein-Westfalen",
    "wof:name":"Adler-apotheke",
    "wof:placetype":"venue"
},
  "geometry": {"coordinates":[6.708044,51.393715],"type":"Point"}
}