{
  "type": "Feature",
  "properties": {
    "iso:country":"DE",
    "sg:address":"Heidestr. 2",
    "sg:city":"Holtland",
    "sg:phone":"+49 4950/1874",
    "sg:postcode":"26835",
    "sg:province":"Niedersachsen",
    "wof:name":"Beate Bohnke-schulze",
    "wof:placetype":"venue"
},
  "geometry": {"coordinates":[7.5760498047,53.2830238342],"type":"Point"}
}