{
  "type": "Feature",
  "properties": {
    "iso:country":"DE",
    "sg:address":"Dorfstr. 41 a",
    "sg:city":"Sch\u00f6ngleina",
    "sg:phone":"+49 36428/40564",
    "sg:postcode":"07646",
    "sg:province":"Th\u00fcringen",
    "wof:name":"Klaus Gr\u00f6bner",
    "wof:placetype":"venue"
},
  "geometry": {"coordinates":[11.731198,50.909973],"type":"Point"}
}