{
  "type": "Feature",
  "properties": {
    "iso:country":"DE",
    "sg:address":"Augartenstr. 28",
    "sg:city":"Zaisenhausen",
    "sg:phone":"+49 7258/347",
    "sg:postcode":"75059",
    "sg:province":"Baden-W\u00fcrttemberg",
    "wof:name":"Reinhold Pfeil",
    "wof:placetype":"venue"
},
  "geometry": {"coordinates":[8.81384,49.107159],"type":"Point"}
}