{
  "type": "Feature",
  "properties": {
    "iso:country":"DE",
    "sg:address":"Wallstr. 1",
    "sg:city":"Nordenham",
    "sg:phone":"+49 4731/923447",
    "sg:postcode":"26954",
    "sg:province":"Niedersachsen",
    "wof:name":"Rademann & Kr\u00fcger Gmbh",
    "wof:placetype":"venue"
},
  "geometry": {"coordinates":[8.4761743546,53.4804496765],"type":"Point"}
}