{
  "type": "Feature",
  "properties": {
    "iso:country":"DE",
    "sg:address":"Gutenbergstr. 1",
    "sg:city":"Pliezhausen",
    "sg:phone":"+49 4971/2797770",
    "sg:postcode":"72124",
    "sg:province":"Baden-W\u00fcrttemberg",
    "wof:name":"Metzgerei Schneider Gmbh",
    "wof:placetype":"venue"
},
  "geometry": {"coordinates":[9.1959104538,48.566570282],"type":"Point"}
}