{
  "type": "Feature",
  "properties": {
    "iso:country":"DE",
    "sg:address":"Leipziger Str. 126 a",
    "sg:city":"Wei\u00dfenfels",
    "sg:phone":"+49 3443/234481",
    "sg:postcode":"06667",
    "sg:province":"Sachsen-Anhalt",
    "wof:name":"Harry Swikle",
    "wof:placetype":"venue"
},
  "geometry": {"coordinates":[11.995276,51.218033],"type":"Point"}
}