{
  "type": "Feature",
  "properties": {
    "iso:country":"DE",
    "sg:address":"Brauereistr. 13",
    "sg:city":"Dessau",
    "sg:phone":"+49 340/266170",
    "sg:postcode":"06847",
    "sg:province":"Sachsen-Anhalt",
    "wof:name":"Creditreform Dessau Balles Noack Kg",
    "wof:placetype":"venue"
},
  "geometry": {"coordinates":[12.222921,51.832287],"type":"Point"}
}