{
  "type": "Feature",
  "properties": {
    "iso:country":"DE",
    "sg:address":"P\u00f6ttcherstr. 10-12",
    "sg:city":"Minden",
    "sg:phone":"+49 571/26883",
    "sg:postcode":"32423",
    "sg:province":"Nordrhein-Westfalen",
    "wof:name":"Optik Schmack Inh. Ingeborg Schmack",
    "wof:placetype":"venue"
},
  "geometry": {"coordinates":[8.9133167267,52.2891845703],"type":"Point"}
}