{
  "type": "Feature",
  "properties": {
    "iso:country":"DE",
    "sg:address":"Obere Hauptstr 22",
    "sg:city":"Seitingen-Oberflacht",
    "sg:phone":"+49 7464/98880",
    "sg:postcode":"78606",
    "sg:province":"Baden-W\u00fcrttemberg",
    "wof:name":"Helmut Zepf Medizintechnik Gmbh",
    "wof:placetype":"venue"
},
  "geometry": {"coordinates":[8.72974,48.020699],"type":"Point"}
}