{
  "type": "Feature",
  "properties": {
    "iso:country":"DE",
    "sg:address":"Markenwaldstr. 1",
    "sg:city":"Rosendahl",
    "sg:phone":"+49 2566/724",
    "sg:postcode":"48720",
    "sg:province":"Nordrhein-Westfalen",
    "wof:name":"Adolf H\u00fcwe",
    "wof:placetype":"venue"
},
  "geometry": {"coordinates":[7.126747,52.011353],"type":"Point"}
}