{
  "type": "Feature",
  "properties": {
    "iso:country":"DE",
    "sg:address":"Kunigundendamm 1 a",
    "sg:city":"Bamberg",
    "sg:phone":"+49 951/26965",
    "sg:postcode":"96050",
    "sg:province":"Bayern",
    "wof:name":"Pizzeria Lorenzo",
    "wof:placetype":"venue"
},
  "geometry": {"coordinates":[10.8944149017,49.8956756592],"type":"Point"}
}