{
  "type": "Feature",
  "properties": {
    "iso:country":"DE",
    "sg:address":"Dr.-Dietz-Str. 6",
    "sg:city":"Fulda",
    "sg:phone":"+49 661/64324",
    "sg:postcode":"36043",
    "sg:province":"Hessen",
    "wof:name":"E. Hahling",
    "wof:placetype":"venue"
},
  "geometry": {"coordinates":[9.7061004639,50.5518035889],"type":"Point"}
}