{
  "type": "Feature",
  "properties": {
    "iso:country":"DE",
    "sg:address":"Rappensberg 1",
    "sg:city":"Landau",
    "sg:postcode":"94405",
    "sg:province":"Bayern",
    "wof:name":"L & T Mineral\u00f6lhandels-gmbh",
    "wof:placetype":"venue"
},
  "geometry": {"coordinates":[12.6831102371,48.632724762],"type":"Point"}
}