{
  "type": "Feature",
  "properties": {
    "iso:country":"DE",
    "sg:address":"Hauptstr. 61",
    "sg:city":"Warstein",
    "sg:phone":"+49 2902/2354",
    "sg:postcode":"59581",
    "sg:province":"Nordrhein-Westfalen",
    "wof:name":"Rautert",
    "wof:placetype":"venue"
},
  "geometry": {"coordinates":[8.35408,51.445107],"type":"Point"}
}