{
  "type": "Feature",
  "properties": {
    "iso:country":"DE",
    "sg:address":"Niederseite 22",
    "sg:city":"Coswig",
    "sg:phone":"+49 3523/71550",
    "sg:postcode":"01640",
    "sg:province":"Sachsen",
    "wof:name":"Kunstglaserei Reinhard Meissner",
    "wof:placetype":"venue"
},
  "geometry": {"coordinates":[13.543162,51.130466],"type":"Point"}
}