{
  "type": "Feature",
  "properties": {
    "iso:country":"DE",
    "sg:address":"Heegestrasse 14",
    "sg:city":"Gelsenkirchen",
    "sg:phone":"+49 209/959760",
    "sg:postcode":"45897",
    "sg:province":"Nordrhein-Westfalen",
    "wof:name":"Fachschule F\u00fcr Technik, Fachrichtung K\u00e4ltetechnik",
    "wof:placetype":"venue"
},
  "geometry": {"coordinates":[7.027712,51.575848],"type":"Point"}
}