{
  "type": "Feature",
  "properties": {
    "iso:country":"DE",
    "sg:address":"Horster Damm 117",
    "sg:city":"Hamburg",
    "sg:postcode":"21039",
    "sg:province":"Hamburg",
    "wof:name":"Lattenkamp - Die Band",
    "wof:placetype":"venue"
},
  "geometry": {"coordinates":[10.2892827988,53.4502410889],"type":"Point"}
}