{
  "type": "Feature",
  "properties": {
    "iso:country":"DE",
    "sg:address":"Lindenstr. 4",
    "sg:city":"St. Egidien",
    "sg:phone":"+49 37204/2963",
    "sg:postcode":"09356",
    "sg:province":"Sachsen",
    "wof:name":"Kommunale Wohnungs Verwaltung",
    "wof:placetype":"venue"
},
  "geometry": {"coordinates":[12.6128740311,50.7880172729],"type":"Point"}
}