{
  "type": "Feature",
  "properties": {
    "iso:country":"DE",
    "sg:address":"Angerstr. 7",
    "sg:city":"Emmerthal",
    "sg:phone":"+49 5286/291",
    "sg:postcode":"31860",
    "sg:province":"Niedersachsen",
    "wof:name":"G\u00fcnther Scheuermann",
    "wof:placetype":"venue"
},
  "geometry": {"coordinates":[9.37321,51.984531],"type":"Point"}
}