{
  "type": "Feature",
  "properties": {
    "iso:country":"DE",
    "sg:address":"Thuiner Str. 20",
    "sg:city":"Messingen",
    "sg:phone":"+49 5905/91234",
    "sg:postcode":"49832",
    "sg:province":"Niedersachsen",
    "wof:name":"Werner Langeborg",
    "wof:placetype":"venue"
},
  "geometry": {"coordinates":[7.45978,52.47171],"type":"Point"}
}