{
  "type": "Feature",
  "properties": {
    "iso:country":"DE",
    "sg:address":"Humboldtstr. 56",
    "sg:city":"Frankfurt",
    "sg:phone":"+49 69/59795022",
    "sg:postcode":"60318",
    "sg:province":"Hessen",
    "wof:name":"Thomas Bode Rechtsanwalt",
    "wof:placetype":"venue"
},
  "geometry": {"coordinates":[8.6841831207,50.1253013611],"type":"Point"}
}