{
  "type": "Feature",
  "properties": {
    "iso:country":"DE",
    "sg:address":"Von-Bodelschwingh-Str. 1",
    "sg:city":"H\u00f6rstel",
    "sg:phone":"+49 5459/7177",
    "sg:postcode":"48477",
    "sg:province":"Nordrhein-Westfalen",
    "wof:name":"Gerhard Bahl",
    "wof:placetype":"venue"
},
  "geometry": {"coordinates":[7.587452,52.296856],"type":"Point"}
}