{
  "type": "Feature",
  "properties": {
    "iso:country":"DE",
    "sg:address":"Altenst\u00e4dter Str. 12",
    "sg:city":"Florstadt",
    "sg:phone":"+49 6035/8303",
    "sg:postcode":"61197",
    "sg:province":"Hessen",
    "wof:name":"Arno Emmerich",
    "wof:placetype":"venue"
},
  "geometry": {"coordinates":[8.861931,50.318111],"type":"Point"}
}