{
  "type": "Feature",
  "properties": {
    "iso:country":"DE",
    "sg:address":"Von-Ellerbach-Str. 20",
    "sg:city":"Burgau",
    "sg:phone":"+49 8222/2683",
    "sg:postcode":"89331",
    "sg:province":"Bayern",
    "wof:name":"Hans G\u00fcnther",
    "wof:placetype":"venue"
},
  "geometry": {"coordinates":[10.3985261917,48.4354667664],"type":"Point"}
}