{
  "type": "Feature",
  "properties": {
    "iso:country":"DE",
    "sg:address":"Paul-Lincke-Str. 4",
    "sg:city":"Bielefeld",
    "sg:phone":"+49 521/49021",
    "sg:postcode":"33659",
    "sg:province":"Nordrhein-Westfalen",
    "wof:name":"Johann Steinbeck Beteiligungs Gmbh",
    "wof:placetype":"venue"
},
  "geometry": {"coordinates":[8.55449,51.963528],"type":"Point"}
}