{
  "type": "Feature",
  "properties": {
    "iso:country":"DE",
    "sg:address":"Edderweg 3",
    "sg:city":"Langenhagen",
    "sg:phone":"+49 511/773209",
    "sg:postcode":"30855",
    "sg:province":"Niedersachsen",
    "wof:name":"Cp Industrievertretungen Gmbh",
    "wof:placetype":"venue"
},
  "geometry": {"coordinates":[9.7667541504,52.4835205078],"type":"Point"}
}