{
  "type": "Feature",
  "properties": {
    "iso:country":"DE",
    "sg:address":"Sch\u00fcruferstr. 29",
    "sg:city":"Dortmund",
    "sg:phone":"+49 231/435152",
    "sg:postcode":"44269",
    "sg:province":"Nordrhein-Westfalen",
    "wof:name":"Kinderlech Co Johannes Schopp",
    "wof:placetype":"venue"
},
  "geometry": {"coordinates":[7.5225310326,51.4842033386],"type":"Point"}
}