{
  "type": "Feature",
  "properties": {
    "iso:country":"DE",
    "sg:address":"Julius-Pintschring 3",
    "sg:city":"F\u00fcrstenwalde",
    "sg:phone":"+49 4933/6135660",
    "sg:postcode":"15517",
    "sg:province":"Brandenburg",
    "wof:name":"Rmg - Gaselan Regel- Und Messtechnik Gmbh",
    "wof:placetype":"venue"
},
  "geometry": {"coordinates":[14.055719,52.368618],"type":"Point"}
}