{
  "type": "Feature",
  "properties": {
    "iso:country":"DE",
    "sg:address":"Selmer Landstr. 85",
    "sg:city":"Werne",
    "sg:phone":"+49 2389/45410",
    "sg:postcode":"59368",
    "sg:province":"Nordrhein-Westfalen",
    "wof:name":"Alfred Kunzig",
    "wof:placetype":"venue"
},
  "geometry": {"coordinates":[7.6079821587,51.6690559387],"type":"Point"}
}