{
  "type": "Feature",
  "properties": {
    "iso:country":"DE",
    "sg:address":"Lindenstr. 1",
    "sg:city":"Kr\u00f6pelin",
    "sg:phone":"+49 38292/695",
    "sg:postcode":"18236",
    "sg:province":"Mecklenburg-Vorpommern",
    "wof:name":"Eleonore Br\u00fcshaber",
    "wof:placetype":"venue"
},
  "geometry": {"coordinates":[11.791768074,54.0708122253],"type":"Point"}
}