{
  "type": "Feature",
  "properties": {
    "iso:country":"DE",
    "sg:address":"Markgrafenstr. 81",
    "sg:city":"M\u00fcnchen",
    "sg:postcode":"81827",
    "sg:province":"Bayern",
    "wof:name":"Nv Trading Gmbh",
    "wof:placetype":"venue"
},
  "geometry": {"coordinates":[11.6778459549,48.1057128906],"type":"Point"}
}