{
  "type": "Feature",
  "properties": {
    "iso:country":"DE",
    "sg:address":"Keiselbergstr. 3",
    "sg:city":"Haibach",
    "sg:phone":"+49 6021/60810",
    "sg:postcode":"63808",
    "sg:province":"Bayern",
    "wof:name":"Club 13 Heiner Weis",
    "wof:placetype":"venue"
},
  "geometry": {"coordinates":[9.2146377563,49.9591140747],"type":"Point"}
}