{
  "type": "Feature",
  "properties": {
    "iso:country":"DE",
    "sg:address":"Augustastr. 65",
    "sg:city":"Eschwege",
    "sg:phone":"+49 5651/70017",
    "sg:postcode":"37269",
    "sg:province":"Hessen",
    "wof:name":"Herkules",
    "wof:placetype":"venue"
},
  "geometry": {"coordinates":[10.0473747253,51.1868591309],"type":"Point"}
}