{
  "type": "Feature",
  "properties": {
    "iso:country":"DE",
    "sg:address":"Friedrichstr. 13",
    "sg:city":"Heppenheim",
    "sg:phone":"+49 6252/913230",
    "sg:postcode":"64646",
    "sg:province":"Hessen",
    "wof:name":"Heinrich Ingenhaag Inh. Ralf-u. Steinmetz",
    "wof:placetype":"venue"
},
  "geometry": {"coordinates":[8.641456604,49.6426429749],"type":"Point"}
}