{
  "type": "Feature",
  "properties": {
    "iso:country":"DE",
    "sg:address":"Am Hallacker 27",
    "sg:city":"Bremen",
    "sg:phone":"+49 421/420737",
    "sg:postcode":"28327",
    "sg:province":"Bremen",
    "wof:name":"Willy Quiel",
    "wof:placetype":"venue"
},
  "geometry": {"coordinates":[8.931552887,53.0686569214],"type":"Point"}
}