{
  "type": "Feature",
  "properties": {
    "iso:country":"DE",
    "sg:address":"Balanstr. 50",
    "sg:city":"M\u00fcnchen",
    "sg:postcode":"81541",
    "sg:province":"Bayern",
    "wof:name":"Berthold Schwarz Automaten-service Gmbh",
    "wof:placetype":"venue"
},
  "geometry": {"coordinates":[11.5984621048,48.1218147278],"type":"Point"}
}