{
  "type": "Feature",
  "properties": {
    "iso:country":"DE",
    "sg:address":"Lindenstr 58",
    "sg:city":"Minden",
    "sg:phone":"+49 571/828790",
    "sg:postcode":"32423",
    "sg:province":"Nordrhein-Westfalen",
    "wof:name":"Teilzeit M. Thiele Gmbh",
    "wof:placetype":"venue"
},
  "geometry": {"coordinates":[8.9138784409,52.284828186],"type":"Point"}
}