{
  "type": "Feature",
  "properties": {
    "iso:country":"DE",
    "sg:address":"Reiherstieg 48-50",
    "sg:city":"L\u00fcbeck",
    "sg:phone":"+49 451/792190",
    "sg:postcode":"23564",
    "sg:province":"Schleswig-Holstein",
    "wof:name":"Domus-immobilien Gmbh",
    "wof:placetype":"venue"
},
  "geometry": {"coordinates":[10.7031621933,53.8664131165],"type":"Point"}
}