{
  "type": "Feature",
  "properties": {
    "iso:country":"DE",
    "sg:address":"Wilhelm-Raabe-Weg 24",
    "sg:city":"Oerlinghausen",
    "sg:phone":"+49 5202/979646",
    "sg:postcode":"33813",
    "sg:province":"Nordrhein-Westfalen",
    "wof:name":"B. Reimann Blumen-e H",
    "wof:placetype":"venue"
},
  "geometry": {"coordinates":[8.662308,51.937328],"type":"Point"}
}