{
  "type": "Feature",
  "properties": {
    "iso:country":"DE",
    "sg:address":"Rathausstr. 24",
    "sg:city":"Bargteheide",
    "sg:phone":"+49 4532/23232",
    "sg:postcode":"22941",
    "sg:province":"Schleswig-Holstein",
    "wof:name":"Crocodile Inh. Lenck",
    "wof:placetype":"venue"
},
  "geometry": {"coordinates":[10.2668409348,53.7297058105],"type":"Point"}
}