{
  "type": "Feature",
  "properties": {
    "iso:country":"DE",
    "sg:address":"Br\u00fcckenstr. 43",
    "sg:city":"Birenbach",
    "sg:phone":"+49 7161/52777",
    "sg:postcode":"73102",
    "sg:province":"Baden-W\u00fcrttemberg",
    "wof:name":"Hans Wei\u00df Ingenieur",
    "wof:placetype":"venue"
},
  "geometry": {"coordinates":[9.6568384171,48.7500648499],"type":"Point"}
}