{
  "type": "Feature",
  "properties": {
    "iso:country":"DE",
    "sg:address":"Bergweg 7",
    "sg:city":"Bar\u00dfel",
    "sg:phone":"+49 4497/1461",
    "sg:postcode":"26676",
    "sg:province":"Niedersachsen",
    "wof:name":"A. Und G. Eilers Ohg",
    "wof:placetype":"venue"
},
  "geometry": {"coordinates":[7.838061,53.114986],"type":"Point"}
}