{
  "type": "Feature",
  "properties": {
    "iso:country":"DE",
    "sg:address":"Wickrather Str. 227",
    "sg:city":"M\u00f6nchengladbach",
    "sg:phone":"+49 2166/17663",
    "sg:postcode":"41236",
    "sg:province":"Nordrhein-Westfalen",
    "wof:name":"Helmut Hermann Holzbearbeitung Gmbh",
    "wof:placetype":"venue"
},
  "geometry": {"coordinates":[6.4353837967,51.1543464661],"type":"Point"}
}