{
  "type": "Feature",
  "properties": {
    "iso:country":"DE",
    "sg:address":"Schmiedendorf 7c",
    "sg:city":"Hohwacht",
    "sg:phone":"+49 4384/5880",
    "sg:postcode":"24321",
    "sg:province":"Schleswig-Holstein",
    "wof:name":"L. Baasch",
    "wof:placetype":"venue"
},
  "geometry": {"coordinates":[10.6071901321,54.2889518738],"type":"Point"}
}