{
  "type": "Feature",
  "properties": {
    "iso:country":"DE",
    "sg:address":"Osthofener Str. 15",
    "sg:city":"Worms",
    "sg:phone":"+49 6242/2863",
    "sg:postcode":"67550",
    "sg:province":"Rheinland-Pfalz",
    "wof:name":"Hans Und Renate B\u00f6nisch",
    "wof:placetype":"venue"
},
  "geometry": {"coordinates":[8.3571186066,49.7027359009],"type":"Point"}
}