{
  "type": "Feature",
  "properties": {
    "iso:country":"DE",
    "sg:address":"Printzstr 15-17",
    "sg:city":"Karlsruhe",
    "sg:phone":"+49 721/962450",
    "sg:postcode":"76139",
    "sg:province":"Baden-W\u00fcrttemberg",
    "wof:name":"Schorn & Groh Gmbh",
    "wof:placetype":"venue"
},
  "geometry": {"coordinates":[8.4630823135,49.0235786438],"type":"Point"}
}