{
  "type": "Feature",
  "properties": {
    "iso:country":"DE",
    "sg:address":"Gelsenkirchener Str. 37",
    "sg:city":"Dorsten",
    "sg:phone":"+49 4923/6245788",
    "sg:postcode":"46282",
    "sg:province":"Nordrhein-Westfalen",
    "wof:name":"B. Voss",
    "wof:placetype":"venue"
},
  "geometry": {"coordinates":[6.972014904,51.6552505493],"type":"Point"}
}