{
  "type": "Feature",
  "properties": {
    "iso:country":"DE",
    "sg:address":"Adelheidstr. 10",
    "sg:city":"M\u00fcnchen",
    "sg:phone":"+49 89/2713290",
    "sg:postcode":"80798",
    "sg:province":"Bayern",
    "wof:name":"R. Van Der Heydt",
    "wof:placetype":"venue"
},
  "geometry": {"coordinates":[11.5674266815,48.1563644409],"type":"Point"}
}