{
  "type": "Feature",
  "properties": {
    "iso:country":"DE",
    "sg:address":"Vaihinger Str. 84",
    "sg:city":"Stuttgart",
    "sg:phone":"+49 711/712654",
    "sg:postcode":"70567",
    "sg:province":"Baden-W\u00fcrttemberg",
    "wof:name":"Eugen Schumacher",
    "wof:placetype":"venue"
},
  "geometry": {"coordinates":[9.140428,48.727669],"type":"Point"}
}