{
  "type": "Feature",
  "properties": {
    "iso:country":"DE",
    "sg:address":"Beate-Paulus-Str. 7",
    "sg:city":"Kornwestheim",
    "sg:postcode":"70806",
    "sg:province":"Baden-W\u00fcrttemberg",
    "wof:name":"Kirchliche Sozialstation",
    "wof:placetype":"venue"
},
  "geometry": {"coordinates":[9.188951,48.855366],"type":"Point"}
}