{
  "type": "Feature",
  "properties": {
    "iso:country":"DE",
    "sg:address":"Herrmannsgr\u00fcner Str. 17",
    "sg:city":"Greiz",
    "sg:phone":"+49 3661/41556",
    "sg:postcode":"07973",
    "sg:province":"Th\u00fcringen",
    "wof:name":"G\u00fcnter Hempel",
    "wof:placetype":"venue"
},
  "geometry": {"coordinates":[12.223566,50.665379],"type":"Point"}
}