{
  "type": "Feature",
  "properties": {
    "iso:country":"DE",
    "sg:address":"Pfarrgasse 97",
    "sg:city":"M\u00e4hring",
    "sg:phone":"+49 9639/1227",
    "sg:postcode":"95695",
    "sg:province":"Bayern",
    "wof:name":"Ip Instaplast Kunststoff Gmbh",
    "wof:placetype":"venue"
},
  "geometry": {"coordinates":[12.5288505554,49.9081878662],"type":"Point"}
}