{
  "type": "Feature",
  "properties": {
    "iso:country":"DE",
    "sg:address":"Im Respel 2",
    "sg:city":"Wittnau",
    "sg:phone":"+49 761/402612",
    "sg:postcode":"79299",
    "sg:province":"Baden-W\u00fcrttemberg",
    "wof:name":"Rolf Kiss Inh. Daniel Kiss",
    "wof:placetype":"venue"
},
  "geometry": {"coordinates":[7.8156700134,47.9475975037],"type":"Point"}
}