{
  "type": "Feature",
  "properties": {
    "iso:country":"DE",
    "sg:address":"Freiligrathstr. 41",
    "sg:city":"Iserlohn",
    "sg:phone":"+49 2371/24288",
    "sg:postcode":"58636",
    "sg:province":"Nordrhein-Westfalen",
    "wof:name":"M. Bruch Steuerberater",
    "wof:placetype":"venue"
},
  "geometry": {"coordinates":[7.7093877792,51.3811836243],"type":"Point"}
}