{
  "type": "Feature",
  "properties": {
    "iso:country":"DE",
    "sg:address":"Dietrichsberg 58",
    "sg:city":"W\u00e4chtersbach",
    "sg:phone":"+49 6053/4122",
    "sg:postcode":"63607",
    "sg:province":"Hessen",
    "wof:name":"H.-j. Knuth Anlagenberater",
    "wof:placetype":"venue"
},
  "geometry": {"coordinates":[9.2954158783,50.264087677],"type":"Point"}
}