{
  "type": "Feature",
  "properties": {
    "iso:country":"DE",
    "sg:address":"Gro\u00df L\u00fcdersh\u00e4ger Weg 31",
    "sg:city":"Stralsund",
    "sg:phone":"+49 3831/497451",
    "sg:postcode":"18437",
    "sg:province":"Mecklenburg-Vorpommern",
    "wof:name":"E. Hoffmann",
    "wof:placetype":"venue"
},
  "geometry": {"coordinates":[13.064827,54.297005],"type":"Point"}
}