{
  "type": "Feature",
  "properties": {
    "iso:country":"DE",
    "sg:address":"Rimbachstr. 30",
    "sg:city":"Suhl",
    "sg:phone":"+49 3681/3750",
    "sg:postcode":"98527",
    "sg:province":"Th\u00fcringen",
    "wof:name":"Amtsgericht Suhl",
    "wof:placetype":"venue"
},
  "geometry": {"coordinates":[10.694560051,50.6093292236],"type":"Point"}
}