{
  "type": "Feature",
  "properties": {
    "iso:country":"DE",
    "sg:address":"Wehrb\u00fcsch 7",
    "sg:city":"\u00dcrzig",
    "sg:phone":"+49 6532/2530",
    "sg:postcode":"54539",
    "sg:province":"Rheinland-Pfalz",
    "wof:name":"Werner Neuhaus Architekt",
    "wof:placetype":"venue"
},
  "geometry": {"coordinates":[6.998074,49.982185],"type":"Point"}
}