{
  "type": "Feature",
  "properties": {
    "iso:country":"DE",
    "sg:address":"Neust\u00e4dter Str. 2",
    "sg:city":"Quakenbr\u00fcck",
    "sg:phone":"+49 5431/2244",
    "sg:postcode":"49610",
    "sg:province":"Niedersachsen",
    "wof:name":"Horst Br\u00fcckner",
    "wof:placetype":"venue"
},
  "geometry": {"coordinates":[7.94024086,52.6731338501],"type":"Point"}
}