{
  "type": "Feature",
  "properties": {
    "iso:country":"DE",
    "sg:address":"Im Reh 2a",
    "sg:city":"Waldbronn",
    "sg:phone":"+49 7243/68834",
    "sg:postcode":"76337",
    "sg:province":"Baden-W\u00fcrttemberg",
    "wof:name":"Erich Und Jutta Kist",
    "wof:placetype":"venue"
},
  "geometry": {"coordinates":[8.464846611,48.9303092957],"type":"Point"}
}