{
  "type": "Feature",
  "properties": {
    "iso:country":"DE",
    "sg:address":"Galgenbergstr. 33",
    "sg:city":"Wei\u00dfenburg",
    "sg:phone":"+49 9141/3140",
    "sg:postcode":"91781",
    "sg:province":"Bayern",
    "wof:name":"Ev. Luth. Pfarramt",
    "wof:placetype":"venue"
},
  "geometry": {"coordinates":[10.9750175476,49.0397491455],"type":"Point"}
}