{
  "type": "Feature",
  "properties": {
    "iso:country":"DE",
    "sg:address":"Hauptstr. 20",
    "sg:city":"Bergheim",
    "sg:phone":"+49 2271/497939",
    "sg:postcode":"50126",
    "sg:province":"Nordrhein-Westfalen",
    "wof:name":"Bergheimer Handy-shop",
    "wof:placetype":"venue"
},
  "geometry": {"coordinates":[6.6425738335,50.9538650513],"type":"Point"}
}