{
  "type": "Feature",
  "properties": {
    "iso:country":"DE",
    "sg:address":"Trotzenburg 1",
    "sg:city":"Meinerzhagen",
    "sg:phone":"+49 2354/91820",
    "sg:postcode":"58540",
    "sg:province":"Nordrhein-Westfalen",
    "wof:name":"Pad Messebau Gmbh",
    "wof:placetype":"venue"
},
  "geometry": {"coordinates":[7.638415,51.098701],"type":"Point"}
}