{
  "type": "Feature",
  "properties": {
    "iso:country":"DE",
    "sg:address":"Deggingstr. 40",
    "sg:city":"Dortmund",
    "sg:postcode":"44141",
    "sg:province":"Nordrhein-Westfalen",
    "wof:name":"Dortmund-m\u00e4rkische Eisenbahn Gmbh",
    "wof:placetype":"venue"
},
  "geometry": {"coordinates":[7.4881410599,51.5053901672],"type":"Point"}
}