{
  "type": "Feature",
  "properties": {
    "iso:country":"DE",
    "sg:address":"Stauffenbergstr. 8",
    "sg:city":"Mettingen",
    "sg:phone":"+49 5452/4350",
    "sg:postcode":"49497",
    "sg:province":"Nordrhein-Westfalen",
    "wof:name":"Heeger Zimmerei Gmbh",
    "wof:placetype":"venue"
},
  "geometry": {"coordinates":[7.7794160843,52.3231697083],"type":"Point"}
}