{
  "type": "Feature",
  "properties": {
    "iso:country":"DE",
    "sg:address":"Wilhelm-Theodor-R\u00f6mheld-Str. 3",
    "sg:city":"Mainz",
    "sg:phone":"+49 6131/8040",
    "sg:postcode":"55130",
    "sg:province":"Rheinland-Pfalz",
    "wof:name":"Kubba Grundst\u00fccks- Verwaltungsges. Mbh",
    "wof:placetype":"venue"
},
  "geometry": {"coordinates":[8.289848,49.980537],"type":"Point"}
}