{
  "type": "Feature",
  "properties": {
    "iso:country":"DE",
    "sg:address":"Ditzinger Str. 91",
    "sg:city":"Stuttgart",
    "sg:phone":"+49 711/8874368",
    "sg:postcode":"70499",
    "sg:province":"Baden-W\u00fcrttemberg",
    "wof:name":"Joachim Ludmann",
    "wof:placetype":"venue"
},
  "geometry": {"coordinates":[9.099963,48.817181],"type":"Point"}
}