{
  "type": "Feature",
  "properties": {
    "iso:country":"DE",
    "sg:address":"Lindenallee 19",
    "sg:city":"Holzminden",
    "sg:postcode":"37603",
    "sg:province":"Niedersachsen",
    "wof:name":"Fitness-world",
    "wof:placetype":"venue"
},
  "geometry": {"coordinates":[9.4506206512,51.8370056152],"type":"Point"}
}