{
  "type": "Feature",
  "properties": {
    "iso:country":"DE",
    "sg:address":"Zur Grafenm\u00fchle 14",
    "sg:city":"Bottrop",
    "sg:phone":"+49 2045/409099",
    "sg:postcode":"46244",
    "sg:province":"Nordrhein-Westfalen",
    "wof:name":"Mobiler Pflegedienst Erika Held Und",
    "wof:placetype":"venue"
},
  "geometry": {"coordinates":[6.894497,51.574722],"type":"Point"}
}