{
  "type": "Feature",
  "properties": {
    "iso:country":"DE",
    "sg:address":"Talquellenweg 15",
    "sg:city":"Bad Wildungen",
    "sg:phone":"+49 5621/4274",
    "sg:postcode":"34537",
    "sg:province":"Hessen",
    "wof:name":"Kurpension G\u00e4stehaus Talquell",
    "wof:placetype":"venue"
},
  "geometry": {"coordinates":[9.1076288223,51.1066818237],"type":"Point"}
}