{
  "type": "Feature",
  "properties": {
    "iso:country":"DE",
    "sg:address":"Hochstr. 41",
    "sg:city":"Bergkamen",
    "sg:phone":"+49 2307/85083",
    "sg:postcode":"59192",
    "sg:province":"Nordrhein-Westfalen",
    "wof:name":"B\u00e4ckerei Schmalenberg Inh. Kay Schmalenberg",
    "wof:placetype":"venue"
},
  "geometry": {"coordinates":[7.648501,51.621414],"type":"Point"}
}