{
  "type": "Feature",
  "properties": {
    "iso:country":"DE",
    "sg:address":"Roermonder Str 145",
    "sg:city":"Aachen",
    "sg:phone":"+49 241/879100",
    "sg:postcode":"52072",
    "sg:province":"Nordrhein-Westfalen",
    "wof:name":"Schilder Bischoff Lichtwerbung Gmbh & Co Kg",
    "wof:placetype":"venue"
},
  "geometry": {"coordinates":[6.068426,50.787823],"type":"Point"}
}