{
  "type": "Feature",
  "properties": {
    "iso:country":"DE",
    "sg:address":"H\u00f6lzelweg 2",
    "sg:city":"Stuttgart",
    "sg:phone":"+49 4971/1255210",
    "sg:postcode":"70191",
    "sg:province":"Baden-W\u00fcrttemberg",
    "wof:name":"Smart Electronic Development Gmbh",
    "wof:placetype":"venue"
},
  "geometry": {"coordinates":[9.17814,48.801483],"type":"Point"}
}