{
  "type": "Feature",
  "properties": {
    "iso:country":"DE",
    "sg:address":"Neunu\u00dfberg 20",
    "sg:city":"Viechtach",
    "sg:phone":"+49 9942/1383",
    "sg:postcode":"94234",
    "sg:province":"Bayern",
    "wof:name":"Gastst\u00e4tte Brandl",
    "wof:placetype":"venue"
},
  "geometry": {"coordinates":[12.9495229721,49.088470459],"type":"Point"}
}