{
  "type": "Feature",
  "properties": {
    "iso:country":"DE",
    "sg:address":"Schulstr. 13",
    "sg:city":"Donaueschingen",
    "sg:phone":"+49 771/15510",
    "sg:postcode":"78166",
    "sg:province":"Baden-W\u00fcrttemberg",
    "wof:name":"Kath. Sozialstation St. Elisabeth E. V.",
    "wof:placetype":"venue"
},
  "geometry": {"coordinates":[8.499171,47.954556],"type":"Point"}
}