{
  "type": "Feature",
  "properties": {
    "iso:country":"DE",
    "sg:address":"Nirmer Str. 47",
    "sg:city":"Aachen",
    "sg:phone":"+49 241/550479",
    "sg:postcode":"52080",
    "sg:province":"Nordrhein-Westfalen",
    "wof:name":"Leo Emonds",
    "wof:placetype":"venue"
},
  "geometry": {"coordinates":[6.160801,50.781891],"type":"Point"}
}