{
  "type": "Feature",
  "properties": {
    "iso:country":"DE",
    "sg:address":"Kasseler Str. 41",
    "sg:city":"Paderborn",
    "sg:phone":"+49 5251/22673",
    "sg:postcode":"33098",
    "sg:province":"Nordrhein-Westfalen",
    "wof:name":"Kasselertor-sch\u00e4nke",
    "wof:placetype":"venue"
},
  "geometry": {"coordinates":[8.7596311569,51.7165718079],"type":"Point"}
}