{
  "type": "Feature",
  "properties": {
    "iso:country":"DE",
    "sg:address":"Am Finkenschlag 19",
    "sg:city":"Ottendorf-Okrilla",
    "sg:phone":"+49 35205/54759",
    "sg:postcode":"01458",
    "sg:province":"Sachsen",
    "wof:name":"Holm-dieter Ulm",
    "wof:placetype":"venue"
},
  "geometry": {"coordinates":[13.828932,51.171963],"type":"Point"}
}