{
  "type": "Feature",
  "properties": {
    "iso:country":"DE",
    "sg:address":"Hesseloherstr. 15",
    "sg:city":"M\u00fcnchen",
    "sg:phone":"+49 89/397612",
    "sg:postcode":"80802",
    "sg:province":"Bayern",
    "wof:name":"Wolfgang Hurmer Architekt",
    "wof:placetype":"venue"
},
  "geometry": {"coordinates":[11.589808,48.162895],"type":"Point"}
}