{
  "type": "Feature",
  "properties": {
    "iso:country":"DE",
    "sg:address":"Fabrikstr. 2",
    "sg:city":"Neum\u00fcnster",
    "sg:phone":"+49 4321/492011",
    "sg:postcode":"24534",
    "sg:province":"Schleswig-Holstein",
    "wof:name":"Norbert Hinderer Hamburg-mannheimer",
    "wof:placetype":"venue"
},
  "geometry": {"coordinates":[9.982334137,54.0740509033],"type":"Point"}
}