{
  "type": "Feature",
  "properties": {
    "iso:country":"DE",
    "sg:address":"Hubertusstr. 15",
    "sg:city":"Herzogenaurach",
    "sg:phone":"+49 9132/9595",
    "sg:postcode":"91074",
    "sg:province":"Bayern",
    "wof:name":"Restaurant G. Seeberger",
    "wof:placetype":"venue"
},
  "geometry": {"coordinates":[10.8948822021,49.5922851562],"type":"Point"}
}