{
  "type": "Feature",
  "properties": {
    "iso:country":"DE",
    "sg:address":"M\u00fchlenbachstr. 10",
    "sg:city":"Sinzig",
    "sg:phone":"+49 2642/43430",
    "sg:postcode":"53489",
    "sg:province":"Rheinland-Pfalz",
    "wof:name":"Barbarossa-apotheke",
    "wof:placetype":"venue"
},
  "geometry": {"coordinates":[7.246967,50.545349],"type":"Point"}
}