{
  "type": "Feature",
  "properties": {
    "iso:country":"DE",
    "sg:address":"Im Gro\u00dfen Ahl 35",
    "sg:city":"Offenbach",
    "sg:phone":"+49 69/868564",
    "sg:postcode":"63075",
    "sg:province":"Hessen",
    "wof:name":"Goab Recycling-zentrum",
    "wof:placetype":"venue"
},
  "geometry": {"coordinates":[8.7963962555,50.1083106995],"type":"Point"}
}