{
  "type": "Feature",
  "properties": {
    "iso:country":"DE",
    "sg:address":"Hospitalstr. 38",
    "sg:city":"D\u00fcren",
    "sg:phone":"+49 2421/86969",
    "sg:postcode":"52353",
    "sg:province":"Nordrhein-Westfalen",
    "wof:name":"St. Schmitz",
    "wof:placetype":"venue"
},
  "geometry": {"coordinates":[6.46585989,50.8232536316],"type":"Point"}
}