{
  "type": "Feature",
  "properties": {
    "iso:country":"DE",
    "sg:address":"Pirnaer Landstr. 217",
    "sg:city":"Dresden",
    "sg:phone":"+49 351/2030956",
    "sg:postcode":"01259",
    "sg:province":"Sachsen",
    "wof:name":"Steffen Paschke Anlageberater",
    "wof:placetype":"venue"
},
  "geometry": {"coordinates":[13.8395881653,51.0053405762],"type":"Point"}
}