{
  "type": "Feature",
  "properties": {
    "iso:country":"DE",
    "sg:address":"Schillerstr. 24",
    "sg:city":"Wellendingen",
    "sg:phone":"+49 7426/8112",
    "sg:postcode":"78669",
    "sg:province":"Baden-W\u00fcrttemberg",
    "wof:name":"E. Zimmerer",
    "wof:placetype":"venue"
},
  "geometry": {"coordinates":[8.7031517029,48.1498756409],"type":"Point"}
}