{
  "type": "Feature",
  "properties": {
    "iso:country":"DE",
    "sg:address":"Mittelstr. 25",
    "sg:city":"Hagen",
    "sg:phone":"+49 2331/89291",
    "sg:postcode":"58095",
    "sg:province":"Nordrhein-Westfalen",
    "wof:name":"Stallmann Gmbh & Co. Kg",
    "wof:placetype":"venue"
},
  "geometry": {"coordinates":[7.4737801552,51.3575325012],"type":"Point"}
}