{
  "type": "Feature",
  "properties": {
    "iso:country":"DE",
    "sg:address":"Ostpreu\u00dfendamm 66",
    "sg:city":"Berlin",
    "sg:postcode":"12207",
    "sg:province":"Berlin",
    "wof:name":"Heiwobau Wohnbau Beteiligungs Gmbh",
    "wof:placetype":"venue"
},
  "geometry": {"coordinates":[13.309407,52.420803],"type":"Point"}
}