{
  "type": "Feature",
  "properties": {
    "iso:country":"DE",
    "sg:address":"G\u00fcndlinger Str. 23",
    "sg:city":"Breisach",
    "sg:phone":"+49 7664/95306",
    "sg:postcode":"79206",
    "sg:province":"Baden-W\u00fcrttemberg",
    "wof:name":"Paul Sch\u00e4chtele Tief- Und Stra\u00dfenbau Gmbh",
    "wof:placetype":"venue"
},
  "geometry": {"coordinates":[7.6662201881,47.9870948792],"type":"Point"}
}