{
  "type": "Feature",
  "properties": {
    "iso:country":"DE",
    "sg:address":"Unter dem Rasenweg 1",
    "sg:city":"Wallhausen",
    "sg:phone":"+49 34656/31107",
    "sg:postcode":"06528",
    "sg:province":"Sachsen-Anhalt",
    "wof:name":"Industrietextilverarbeitung Burkhard Breyer",
    "wof:placetype":"venue"
},
  "geometry": {"coordinates":[11.2058000565,51.4635391235],"type":"Point"}
}