{
  "type": "Feature",
  "properties": {
    "iso:country":"DE",
    "sg:city":"Dillingen",
    "sg:phone":"+49 4968/3173081",
    "sg:postcode":"66763",
    "sg:province":"Saarland",
    "wof:name":"Kreissparkasse Saarlouis",
    "wof:placetype":"venue"
},
  "geometry": {"coordinates":[6.71863,49.35815],"type":"Point"}
}