{
  "type": "Feature",
  "properties": {
    "iso:country":"DE",
    "sg:address":"Imhoffstr. 1A",
    "sg:city":"Langenhagen",
    "sg:phone":"+49 511/721650",
    "sg:postcode":"30853",
    "sg:province":"Niedersachsen",
    "wof:name":"Christoph Meyer Architekt",
    "wof:placetype":"venue"
},
  "geometry": {"coordinates":[9.737842,52.445423],"type":"Point"}
}