{
  "type": "Feature",
  "properties": {
    "iso:country":"DE",
    "sg:address":"Ortsstr. 4",
    "sg:city":"Peuschen",
    "sg:phone":"+49 3647/504388",
    "sg:postcode":"07389",
    "sg:province":"Th\u00fcringen",
    "wof:name":"G. Kienitz",
    "wof:placetype":"venue"
},
  "geometry": {"coordinates":[11.641459465,50.6593933105],"type":"Point"}
}