{
  "type": "Feature",
  "properties": {
    "iso:country":"DE",
    "sg:address":"Frankfurter Str. 154",
    "sg:city":"Bad Camberg",
    "sg:postcode":"65520",
    "sg:province":"Hessen",
    "wof:name":"Treumata-treuhand Main-taunus Gmbh",
    "wof:placetype":"venue"
},
  "geometry": {"coordinates":[8.2751998901,50.2882080078],"type":"Point"}
}