{
  "type": "Feature",
  "properties": {
    "iso:country":"DE",
    "sg:address":"R\u00f6merstr. 69",
    "sg:city":"Bad Ems",
    "sg:phone":"+49 2603/2650",
    "sg:postcode":"56130",
    "sg:province":"Rheinland-Pfalz",
    "wof:name":"Eissalon Luigi Brustolon",
    "wof:placetype":"venue"
},
  "geometry": {"coordinates":[7.7159018517,50.3339881897],"type":"Point"}
}