{
  "type": "Feature",
  "properties": {
    "iso:country":"DE",
    "sg:address":"Dekan-Fellhauer-Str. 23",
    "sg:city":"Marxzell",
    "sg:phone":"+49 7248/932990",
    "sg:postcode":"76359",
    "sg:province":"Baden-W\u00fcrttemberg",
    "wof:name":"M. Schwinda-jetter",
    "wof:placetype":"venue"
},
  "geometry": {"coordinates":[8.435453,48.870251],"type":"Point"}
}