{
  "type": "Feature",
  "properties": {
    "iso:country":"DE",
    "sg:city":"Dissen",
    "sg:phone":"+49 5424/4588",
    "sg:postcode":"49201",
    "sg:province":"Niedersachsen",
    "wof:name":"Dahms Electreonic Edv-anbieter",
    "wof:placetype":"venue"
},
  "geometry": {"coordinates":[8.204799,52.114594],"type":"Point"}
}