{
  "type": "Feature",
  "properties": {
    "iso:country":"DE",
    "sg:address":"B\u00fcltenweg 79 a",
    "sg:city":"Braunschweig",
    "sg:phone":"+49 531/331437",
    "sg:postcode":"38106",
    "sg:province":"Niedersachsen",
    "wof:name":"Arbeitnehmerberatungsb\u00fcro F\u00fcr Informationstechnologie E. V.",
    "wof:placetype":"venue"
},
  "geometry": {"coordinates":[10.534004,52.274818],"type":"Point"}
}