{
  "type": "Feature",
  "properties": {
    "iso:country":"DE",
    "sg:address":"Breitmatten 24",
    "sg:city":"Lahr",
    "sg:phone":"+49 7821/76152",
    "sg:postcode":"77933",
    "sg:province":"Baden-W\u00fcrttemberg",
    "wof:name":"K. Kl\u00e4hr",
    "wof:placetype":"venue"
},
  "geometry": {"coordinates":[7.900218,48.338921],"type":"Point"}
}