{
  "type": "Feature",
  "properties": {
    "iso:country":"DE",
    "sg:address":"Br\u00fcckenstr. 17",
    "sg:city":"Hofheim",
    "sg:phone":"+49 4961/9225079",
    "sg:postcode":"65719",
    "sg:province":"Hessen",
    "wof:name":"Klaus Kr\u00c4ckmann Gmbh",
    "wof:placetype":"venue"
},
  "geometry": {"coordinates":[8.4231863022,50.1180000305],"type":"Point"}
}