{
  "type": "Feature",
  "properties": {
    "iso:country":"DE",
    "sg:address":"Wilhelm-Leuschner-Platz 21",
    "sg:city":"Langen",
    "sg:phone":"+49 6103/928463",
    "sg:postcode":"63225",
    "sg:province":"Hessen",
    "wof:name":"Scandic Exklusiv Gmbh",
    "wof:placetype":"venue"
},
  "geometry": {"coordinates":[8.6797180176,49.9892730713],"type":"Point"}
}