{
  "type": "Feature",
  "properties": {
    "iso:country":"DE",
    "sg:address":"Bismarckstr. 6",
    "sg:city":"Bietigheim-Bissingen",
    "sg:phone":"+49 7142/51127",
    "sg:postcode":"74321",
    "sg:province":"Baden-W\u00fcrttemberg",
    "wof:name":"Wirwas",
    "wof:placetype":"venue"
},
  "geometry": {"coordinates":[9.1362066269,48.9550552368],"type":"Point"}
}