{
  "type": "Feature",
  "properties": {
    "iso:country":"DE",
    "sg:address":"Neu Lohsaer Weg 24",
    "sg:city":"Lohsa",
    "sg:phone":"+49 35724/5410",
    "sg:postcode":"02999",
    "sg:province":"Sachsen",
    "wof:name":"Swanenberg & Bau Gmbh & Co",
    "wof:placetype":"venue"
},
  "geometry": {"coordinates":[14.4012746811,51.379283905],"type":"Point"}
}