{
  "type": "Feature",
  "properties": {
    "iso:country":"DE",
    "sg:address":"Am S\u00fcdkamp 8",
    "sg:city":"Twistringen",
    "sg:phone":"+49 4243/3021",
    "sg:postcode":"27239",
    "sg:province":"Niedersachsen",
    "wof:name":"Riflex Fl\u00e4chentechnik Gmbh",
    "wof:placetype":"venue"
},
  "geometry": {"coordinates":[8.632706,52.78965],"type":"Point"}
}