{
  "type": "Feature",
  "properties": {
    "iso:country":"DE",
    "sg:address":"Rathausplatz 7",
    "sg:city":"Gerbrunn",
    "sg:phone":"+49 931/706794",
    "sg:postcode":"97218",
    "sg:province":"Bayern",
    "wof:name":"Herbert Gschwind Architekt",
    "wof:placetype":"venue"
},
  "geometry": {"coordinates":[9.983692,49.778023],"type":"Point"}
}