{
  "type": "Feature",
  "properties": {
    "iso:country":"DE",
    "sg:address":"Haimhauserstr. 5a",
    "sg:city":"M\u00fcnchen",
    "sg:phone":"+49 89/393110",
    "sg:postcode":"80802",
    "sg:province":"Bayern",
    "wof:name":"Neue Wege Gesellschaft F\u00fcr Jugendhilfe Und",
    "wof:placetype":"venue"
},
  "geometry": {"coordinates":[11.5880937576,48.1624488831],"type":"Point"}
}