{
  "type": "Feature",
  "properties": {
    "iso:country":"DE",
    "sg:address":"Rielasinger Str. 71",
    "sg:city":"Gottmadingen",
    "sg:phone":"+49 7731/71475",
    "sg:postcode":"78244",
    "sg:province":"Baden-W\u00fcrttemberg",
    "wof:name":"K. G\u00fcsewell",
    "wof:placetype":"venue"
},
  "geometry": {"coordinates":[8.7902040482,47.7314186096],"type":"Point"}
}