{
  "type": "Feature",
  "properties": {
    "iso:country":"DE",
    "sg:address":"Altnossener Str. 2",
    "sg:city":"Dresden",
    "sg:phone":"+49 4935/1419090",
    "sg:postcode":"01156",
    "sg:province":"Sachsen",
    "wof:name":"Sanit\u00c4r-heinze Gmbh",
    "wof:placetype":"venue"
},
  "geometry": {"coordinates":[13.614706,51.044659],"type":"Point"}
}