{
  "type": "Feature",
  "properties": {
    "iso:country":"DE",
    "sg:address":"Rohrlochstr. 8 - 10",
    "sg:city":"Balingen",
    "sg:phone":"+49 4974/3390310",
    "sg:postcode":"72336",
    "sg:province":"Baden-W\u00fcrttemberg",
    "wof:name":"Konrad Stautz Gmbh & Co. Kg",
    "wof:placetype":"venue"
},
  "geometry": {"coordinates":[8.83911,48.282597],"type":"Point"}
}