{
  "type": "Feature",
  "properties": {
    "iso:country":"DE",
    "sg:address":"Galileistr. 11",
    "sg:city":"Zwickau",
    "sg:phone":"+49 375/277600",
    "sg:postcode":"08060",
    "sg:province":"Sachsen",
    "wof:name":"Almed Ges. F\u00fcr Handel Und Dienstleistung Mit Medical-",
    "wof:placetype":"venue"
},
  "geometry": {"coordinates":[12.444194,50.722675],"type":"Point"}
}