{
  "type": "Feature",
  "properties": {
    "iso:country":"DE",
    "sg:address":"Vor der Hube 8",
    "sg:city":"B\u00fcttelborn",
    "sg:phone":"+49 6152/81673",
    "sg:postcode":"64572",
    "sg:province":"Hessen",
    "wof:name":"A. Kremer Makler",
    "wof:placetype":"venue"
},
  "geometry": {"coordinates":[8.5512886047,49.9322738647],"type":"Point"}
}