{
  "type": "Feature",
  "properties": {
    "iso:country":"DE",
    "sg:address":"L\u00f6hner Str. 186",
    "sg:city":"H\u00fcllhorst",
    "sg:phone":"+49 5744/2880",
    "sg:postcode":"32609",
    "sg:province":"Nordrhein-Westfalen",
    "wof:name":"Heinrich Jungemeier",
    "wof:placetype":"venue"
},
  "geometry": {"coordinates":[8.696945,52.254414],"type":"Point"}
}