{
  "type": "Feature",
  "properties": {
    "iso:country":"DE",
    "sg:address":"Marktstr. 10",
    "sg:city":"Lahr",
    "sg:phone":"+49 7821/26110",
    "sg:postcode":"77933",
    "sg:province":"Baden-W\u00fcrttemberg",
    "wof:name":"Ufo",
    "wof:placetype":"venue"
},
  "geometry": {"coordinates":[7.872525,48.341377],"type":"Point"}
}