{
  "type": "Feature",
  "properties": {
    "iso:country":"DE",
    "sg:address":"Am Markt 20",
    "sg:city":"Eppelborn",
    "sg:phone":"+49 6881/89469",
    "sg:postcode":"66571",
    "sg:province":"Saarland",
    "wof:name":"Christoffel",
    "wof:placetype":"venue"
},
  "geometry": {"coordinates":[6.968468,49.408195],"type":"Point"}
}