{
  "type": "Feature",
  "properties": {
    "iso:country":"DE",
    "sg:address":"Hanns-Martin-Schleyer-Str. 9A",
    "sg:city":"Willich",
    "sg:phone":"+49 2154/9390",
    "sg:postcode":"47877",
    "sg:province":"Nordrhein-Westfalen",
    "wof:name":"Brightpoint Gmbh",
    "wof:placetype":"venue"
},
  "geometry": {"coordinates":[6.5110001564,51.2756614685],"type":"Point"}
}