{
  "type": "Feature",
  "properties": {
    "iso:country":"DE",
    "sg:address":"Sichelstr 19",
    "sg:city":"Augsburg",
    "sg:phone":"+49 821/880176",
    "sg:postcode":"86179",
    "sg:province":"Bayern",
    "wof:name":"Extra Beschaffungsagentur Marketing-service Horst Von Der Wehd",
    "wof:placetype":"venue"
},
  "geometry": {"coordinates":[10.896904,48.31498],"type":"Point"}
}