{
  "type": "Feature",
  "properties": {
    "iso:country":"DE",
    "sg:address":"Schillerstr. 5",
    "sg:city":"Ostseebad Rerik",
    "sg:postcode":"18230",
    "sg:province":"Mecklenburg-Vorpommern",
    "wof:name":"Ludwig Bunjes Verwaltungs Gmbh",
    "wof:placetype":"venue"
},
  "geometry": {"coordinates":[11.614065,54.105862],"type":"Point"}
}