{
  "type": "Feature",
  "properties": {
    "iso:country":"DE",
    "sg:address":"Erdinger Str. 1",
    "sg:city":"Taufkirchen",
    "sg:phone":"+49 8084/8485",
    "sg:postcode":"84416",
    "sg:province":"Bayern",
    "wof:name":"Hotel-gasthof Zur Post",
    "wof:placetype":"venue"
},
  "geometry": {"coordinates":[12.1291904449,48.3432159424],"type":"Point"}
}