{
  "type": "Feature",
  "properties": {
    "iso:country":"DE",
    "sg:address":"Soonwaldstr. 5",
    "sg:city":"Spall",
    "sg:phone":"+49 6706/94400",
    "sg:postcode":"55595",
    "sg:province":"Rheinland-Pfalz",
    "wof:name":"Toni Zimmermann Gmbh",
    "wof:placetype":"venue"
},
  "geometry": {"coordinates":[7.6801462173,49.8844299316],"type":"Point"}
}