{
  "type": "Feature",
  "properties": {
    "iso:country":"DE",
    "sg:address":"In der B\u00fchl 10",
    "sg:city":"Heimbach",
    "sg:phone":"+49 2446/1218",
    "sg:postcode":"52396",
    "sg:province":"Nordrhein-Westfalen",
    "wof:name":"Josef Cremer",
    "wof:placetype":"venue"
},
  "geometry": {"coordinates":[6.460719,50.640678],"type":"Point"}
}