{
  "type": "Feature",
  "properties": {
    "iso:country":"DE",
    "sg:address":"Van-Eyck-Str. 23",
    "sg:city":"Emmerich",
    "sg:phone":"+49 2822/68061",
    "sg:postcode":"46446",
    "sg:province":"Nordrhein-Westfalen",
    "wof:name":"Daams Kunststoffe Gmbh",
    "wof:placetype":"venue"
},
  "geometry": {"coordinates":[6.254494,51.842274],"type":"Point"}
}