{
  "type": "Feature",
  "properties": {
    "iso:country":"DE",
    "sg:address":"Tiefenbachstr. 85",
    "sg:city":"Stuttgart",
    "sg:phone":"+49 711/426660",
    "sg:postcode":"70329",
    "sg:province":"Baden-W\u00fcrttemberg",
    "wof:name":"Marian Merz Anlageberater",
    "wof:placetype":"venue"
},
  "geometry": {"coordinates":[9.2212905884,48.7552604675],"type":"Point"}
}