{
  "type": "Feature",
  "properties": {
    "iso:country":"DE",
    "sg:address":"Augustastr. 52",
    "sg:city":"Oftersheim",
    "sg:phone":"+49 6202/55260",
    "sg:postcode":"68723",
    "sg:province":"Baden-W\u00fcrttemberg",
    "wof:name":"Hans \u00d6hmig",
    "wof:placetype":"venue"
},
  "geometry": {"coordinates":[8.5845708847,49.37342453],"type":"Point"}
}