{
  "type": "Feature",
  "properties": {
    "iso:country":"DE",
    "sg:address":"M\u00fchltalstr. 34",
    "sg:city":"Klotten",
    "sg:phone":"+49 2671/7040",
    "sg:postcode":"56818",
    "sg:province":"Rheinland-Pfalz",
    "wof:name":"Norbert Panzer",
    "wof:placetype":"venue"
},
  "geometry": {"coordinates":[7.199315,50.163803],"type":"Point"}
}