{
  "type": "Feature",
  "properties": {
    "iso:country":"DE",
    "sg:address":"Lange Str. 118",
    "sg:city":"Bad Driburg",
    "sg:phone":"+49 5253/2463",
    "sg:postcode":"33014",
    "sg:province":"Nordrhein-Westfalen",
    "wof:name":"Alfons L\u00fccking",
    "wof:placetype":"venue"
},
  "geometry": {"coordinates":[9.0228481293,51.7341423035],"type":"Point"}
}