{
  "type": "Feature",
  "properties": {
    "iso:country":"DE",
    "sg:address":"Rothenbaumchaussee 26",
    "sg:city":"Hamburg",
    "sg:phone":"+49 40/452080",
    "sg:postcode":"20148",
    "sg:province":"Hamburg",
    "wof:name":"Maharishi Ayur-ved Ges. Zur Erforschung U. Ver-",
    "wof:placetype":"venue"
},
  "geometry": {"coordinates":[9.9893960953,53.5646934509],"type":"Point"}
}