{
  "type": "Feature",
  "properties": {
    "iso:country":"DE",
    "sg:address":"Remsch\u00fctzer Str. 4",
    "sg:city":"Saalfeld",
    "sg:phone":"+49 3671/55220",
    "sg:postcode":"07318",
    "sg:province":"Th\u00fcringen",
    "wof:name":"Brandhorst Fliesen Und Platten Gmbh",
    "wof:placetype":"venue"
},
  "geometry": {"coordinates":[11.365387,50.657326],"type":"Point"}
}