{
  "type": "Feature",
  "properties": {
    "iso:country":"DE",
    "sg:address":"Stahlstr. 39",
    "sg:city":"Verl",
    "sg:phone":"+49 5246/96000",
    "sg:postcode":"33415",
    "sg:province":"Nordrhein-Westfalen",
    "wof:name":"Katharina Deppe Besitzgesellschaft",
    "wof:placetype":"venue"
},
  "geometry": {"coordinates":[8.4579143524,51.8726768494],"type":"Point"}
}