{
  "type": "Feature",
  "properties": {
    "iso:country":"DE",
    "sg:address":"Grimelsheimer Str. 43",
    "sg:city":"Liebenau",
    "sg:phone":"+49 5676/237",
    "sg:postcode":"34396",
    "sg:province":"Hessen",
    "wof:name":"Perlit-thermoputz-ersen Gmbh",
    "wof:placetype":"venue"
},
  "geometry": {"coordinates":[9.282385,51.496136],"type":"Point"}
}