{
  "type": "Feature",
  "properties": {
    "iso:country":"DE",
    "sg:address":"Jeversche Str. 16",
    "sg:city":"Schortens",
    "sg:phone":"+49 4461/80661",
    "sg:postcode":"26419",
    "sg:province":"Niedersachsen",
    "wof:name":"W. Sch\u00fcnemann",
    "wof:placetype":"venue"
},
  "geometry": {"coordinates":[7.9405817986,53.5441551208],"type":"Point"}
}