{
  "type": "Feature",
  "properties": {
    "iso:country":"DE",
    "sg:address":"Schweinfurter Str. 32",
    "sg:city":"Euerbach",
    "sg:postcode":"97502",
    "sg:province":"Bayern",
    "wof:name":"Gerhard Hub",
    "wof:placetype":"venue"
},
  "geometry": {"coordinates":[10.095827,50.07309],"type":"Point"}
}