{
  "type": "Feature",
  "properties": {
    "iso:country":"DE",
    "sg:address":"Dietrich-Bonhoeffer-Str. 46",
    "sg:city":"Sankt Augustin",
    "sg:phone":"+49 2241/202916",
    "sg:postcode":"53757",
    "sg:province":"Nordrhein-Westfalen",
    "wof:name":"Josefine Dehmel-hofmann",
    "wof:placetype":"venue"
},
  "geometry": {"coordinates":[7.1925749779,50.7821884155],"type":"Point"}
}