{
  "type": "Feature",
  "properties": {
    "iso:country":"DE",
    "sg:address":"Lisztstr. 16",
    "sg:city":"Celle",
    "sg:phone":"+49 5141/53474",
    "sg:postcode":"29223",
    "sg:province":"Niedersachsen",
    "wof:name":"Helmut Wilkert Ingenieur",
    "wof:placetype":"venue"
},
  "geometry": {"coordinates":[10.049369812,52.6320915222],"type":"Point"}
}