{
  "type": "Feature",
  "properties": {
    "iso:country":"DE",
    "sg:address":"Am Osterb\u00e4chel 29",
    "sg:city":"Annweiler",
    "sg:phone":"+49 6346/8446",
    "sg:postcode":"76855",
    "sg:province":"Rheinland-Pfalz",
    "wof:name":"E. S\u00fcss",
    "wof:placetype":"venue"
},
  "geometry": {"coordinates":[7.9698581696,49.2038726807],"type":"Point"}
}