{
  "type": "Feature",
  "properties": {
    "iso:country":"DE",
    "sg:address":"Am Schluff 22",
    "sg:city":"Viersen",
    "sg:phone":"+49 2162/16193",
    "sg:postcode":"41748",
    "sg:province":"Nordrhein-Westfalen",
    "wof:name":"Thea Krause",
    "wof:placetype":"venue"
},
  "geometry": {"coordinates":[6.3916349411,51.2701683044],"type":"Point"}
}