{
  "type": "Feature",
  "properties": {
    "iso:country":"DE",
    "sg:address":"Aufmberg 19",
    "sg:city":"Seeg",
    "sg:phone":"+49 8364/354",
    "sg:postcode":"87637",
    "sg:province":"Bayern",
    "wof:name":"Bert Wahl",
    "wof:placetype":"venue"
},
  "geometry": {"coordinates":[10.6067695618,47.6490707397],"type":"Point"}
}