{
  "type": "Feature",
  "properties": {
    "iso:country":"DE",
    "sg:address":"Hohe Bergstr. 5",
    "sg:city":"D\u00f6bern",
    "sg:postcode":"03159",
    "sg:province":"Brandenburg",
    "wof:name":"Schindler",
    "wof:placetype":"venue"
},
  "geometry": {"coordinates":[14.588341713,51.6127815247],"type":"Point"}
}