{
  "type": "Feature",
  "properties": {
    "iso:country":"DE",
    "sg:address":"Herzog-Max-Str. 5",
    "sg:city":"Bamberg",
    "sg:phone":"+49 951/25353",
    "sg:postcode":"96047",
    "sg:province":"Bayern",
    "wof:name":"Schauer Und Zahn Rechtsanw\u00e4lte",
    "wof:placetype":"venue"
},
  "geometry": {"coordinates":[10.8933000565,49.891746521],"type":"Point"}
}