{
  "type": "Feature",
  "properties": {
    "iso:country":"DE",
    "sg:address":"Taunusstr. 3",
    "sg:city":"Braunfels",
    "sg:phone":"+49 6472/1250",
    "sg:postcode":"35619",
    "sg:province":"Hessen",
    "wof:name":"O. Gath",
    "wof:placetype":"venue"
},
  "geometry": {"coordinates":[8.4075059891,50.4685287476],"type":"Point"}
}