{
  "type": "Feature",
  "properties": {
    "iso:country":"DE",
    "sg:address":"Bahnhofstr. 83",
    "sg:city":"Herne",
    "sg:phone":"+49 2323/50216",
    "sg:postcode":"44623",
    "sg:province":"Nordrhein-Westfalen",
    "wof:name":"Japan Terminal Joachim Selke",
    "wof:placetype":"venue"
},
  "geometry": {"coordinates":[7.219976902,51.5430526733],"type":"Point"}
}