{
  "type": "Feature",
  "properties": {
    "iso:country":"DE",
    "sg:address":"Roggenbeurer Str. 1",
    "sg:city":"Deggenhausertal",
    "sg:phone":"+49 7555/5366",
    "sg:postcode":"88693",
    "sg:province":"Baden-W\u00fcrttemberg",
    "wof:name":"Tal-apotheke",
    "wof:placetype":"venue"
},
  "geometry": {"coordinates":[9.39085,47.781467],"type":"Point"}
}