{
  "type": "Feature",
  "properties": {
    "iso:country":"DE",
    "sg:address":"Goethestr. 2",
    "sg:city":"Sperenberg",
    "sg:postcode":"15838",
    "sg:province":"Brandenburg",
    "wof:name":"L\u00e4ndliche Erwachsenenbildung",
    "wof:placetype":"venue"
},
  "geometry": {"coordinates":[13.3646879196,52.137676239],"type":"Point"}
}