{
  "type": "Feature",
  "properties": {
    "iso:country":"DE",
    "sg:address":"Ludwigsburg 2",
    "sg:city":"Lich",
    "sg:phone":"+49 6404/666854",
    "sg:postcode":"35423",
    "sg:province":"Hessen",
    "wof:name":"Family Medi@ - Hessens Kreative Webagentur",
    "wof:placetype":"venue"
},
  "geometry": {"coordinates":[8.820341,50.520493],"type":"Point"}
}