{
  "type": "Feature",
  "properties": {
    "iso:country":"DE",
    "sg:address":"Hauptstr. 30",
    "sg:city":"Stetten",
    "sg:phone":"+49 7532/43170",
    "sg:postcode":"88719",
    "sg:province":"Baden-W\u00fcrttemberg",
    "wof:name":"P. Schupp",
    "wof:placetype":"venue"
},
  "geometry": {"coordinates":[9.299972,47.692303],"type":"Point"}
}