{
  "type": "Feature",
  "properties": {
    "iso:country":"DE",
    "sg:address":"Mannheimer Str. 44",
    "sg:city":"Oftersheim",
    "sg:phone":"+49 6202/56436",
    "sg:postcode":"68723",
    "sg:province":"Baden-W\u00fcrttemberg",
    "wof:name":"Erika Lochner",
    "wof:placetype":"venue"
},
  "geometry": {"coordinates":[8.5827150345,49.3701133728],"type":"Point"}
}