{
  "type": "Feature",
  "properties": {
    "iso:country":"DE",
    "sg:address":"M\u00fcndelheimer Weg 33",
    "sg:city":"D\u00fcsseldorf",
    "sg:phone":"+49 211/471380",
    "sg:postcode":"40472",
    "sg:province":"Nordrhein-Westfalen",
    "wof:name":"Seatrak Textilvertriebs- Gmbh",
    "wof:placetype":"venue"
},
  "geometry": {"coordinates":[6.7953109741,51.2895393372],"type":"Point"}
}