{
  "type": "Feature",
  "properties": {
    "iso:country":"DE",
    "sg:address":"Sch\u00f6nb\u00f6rnchener Weg 17",
    "sg:city":"Glauchau",
    "sg:phone":"+49 3763/78145",
    "sg:postcode":"08371",
    "sg:province":"Sachsen",
    "wof:name":"Emil Eger & Sohn",
    "wof:placetype":"venue"
},
  "geometry": {"coordinates":[12.518457,50.830635],"type":"Point"}
}