{
  "type": "Feature",
  "properties": {
    "iso:country":"DE",
    "sg:address":"Alt-Moabit 59-60",
    "sg:city":"Berlin",
    "sg:phone":"+49 30/3904850",
    "sg:postcode":"10555",
    "sg:province":"Berlin",
    "wof:name":"Canto Software Ag",
    "wof:placetype":"venue"
},
  "geometry": {"coordinates":[13.3276062012,52.5242004395],"type":"Point"}
}