{
  "type": "Feature",
  "properties": {
    "iso:country":"DE",
    "sg:address":"Jan-Petersen-Str. 16",
    "sg:city":"Berlin",
    "sg:phone":"+49 30/9309854",
    "sg:postcode":"12679",
    "sg:province":"Berlin",
    "wof:name":"Extra",
    "wof:placetype":"venue"
},
  "geometry": {"coordinates":[13.563668251,52.5493621826],"type":"Point"}
}