{
  "type": "Feature",
  "properties": {
    "iso:country":"DE",
    "sg:address":"Rheinstr. 13",
    "sg:city":"Bobenheim-Roxheim",
    "sg:phone":"+49 6239/1295",
    "sg:postcode":"67240",
    "sg:province":"Rheinland-Pfalz",
    "wof:name":"Kath. Pfarramt St. Magdalena",
    "wof:placetype":"venue"
},
  "geometry": {"coordinates":[8.3671455383,49.578918457],"type":"Point"}
}