{
  "type": "Feature",
  "properties": {
    "iso:country":"DE",
    "sg:address":"Erich-Weinert-Stra\u00dfe 01",
    "sg:city":"Ludwigsfelde",
    "sg:phone":"+49 3378",
    "sg:postcode":"14974",
    "sg:province":"Brandenburg",
    "wof:name":"Home24.de/seifert",
    "wof:placetype":"venue"
},
  "geometry": {"coordinates":[13.246553421,52.3063697815],"type":"Point"}
}