{
  "type": "Feature",
  "properties": {
    "iso:country":"DE",
    "sg:address":"Sonnenplatz 2",
    "sg:city":"Hof",
    "sg:phone":"+49 9281/87053",
    "sg:postcode":"95028",
    "sg:province":"Bayern",
    "wof:name":"Franken Wkv Bank Gmbh",
    "wof:placetype":"venue"
},
  "geometry": {"coordinates":[11.914819,50.316669],"type":"Point"}
}