{
  "type": "Feature",
  "properties": {
    "iso:country":"DE",
    "sg:address":"Rappach 2",
    "sg:city":"Landau",
    "sg:phone":"+49 9951/7761",
    "sg:postcode":"94405",
    "sg:province":"Bayern",
    "wof:name":"Tara Golfanlagen Verwaltungs Gmbh",
    "wof:placetype":"venue"
},
  "geometry": {"coordinates":[12.731970787,48.6602783203],"type":"Point"}
}