{
  "type": "Feature",
  "properties": {
    "iso:country":"DE",
    "sg:address":"Lagerstr.",
    "sg:city":"Gr\u00fcnkraut",
    "sg:phone":"+49 751/6961",
    "sg:postcode":"88287",
    "sg:province":"Baden-W\u00fcrttemberg",
    "wof:name":"Lutz Gmbh",
    "wof:placetype":"venue"
},
  "geometry": {"coordinates":[9.657283,47.755234],"type":"Point"}
}