{
  "type": "Feature",
  "properties": {
    "iso:country":"DE",
    "sg:address":"Alte Dorfstr. 6",
    "sg:city":"Hasel\u00fcnne",
    "sg:phone":"+49 5961/5114",
    "sg:postcode":"49740",
    "sg:province":"Niedersachsen",
    "wof:name":"Alter Dorfkrug",
    "wof:placetype":"venue"
},
  "geometry": {"coordinates":[7.5263738632,52.6631965637],"type":"Point"}
}