{
  "type": "Feature",
  "properties": {
    "iso:country":"DE",
    "sg:address":"R\u00fcttenscheider Str. 114",
    "sg:city":"Essen",
    "sg:phone":"+49 201/772848",
    "sg:postcode":"45131",
    "sg:province":"Nordrhein-Westfalen",
    "wof:name":"A. F. Prabucki Steuerberater",
    "wof:placetype":"venue"
},
  "geometry": {"coordinates":[7.0041408539,51.4334182739],"type":"Point"}
}