{
  "type": "Feature",
  "properties": {
    "iso:country":"DE",
    "sg:address":"Ackerstr. 46",
    "sg:city":"Osnabr\u00fcck",
    "sg:phone":"+49 541/907080",
    "sg:postcode":"49084",
    "sg:province":"Niedersachsen",
    "wof:name":"Arnold Leinen Tiefbau Gmbh",
    "wof:placetype":"venue"
},
  "geometry": {"coordinates":[8.0797252655,52.2591972351],"type":"Point"}
}