{
  "type": "Feature",
  "properties": {
    "iso:country":"DE",
    "sg:address":"Bechemer Str. 21",
    "sg:city":"Ratingen",
    "sg:phone":"+49 2102/28989",
    "sg:postcode":"40878",
    "sg:province":"Nordrhein-Westfalen",
    "wof:name":"Trefz",
    "wof:placetype":"venue"
},
  "geometry": {"coordinates":[6.8508892059,51.2964363098],"type":"Point"}
}