{
  "type": "Feature",
  "properties": {
    "iso:country":"DE",
    "sg:address":"Br\u00e4uckenstr. 71",
    "sg:city":"L\u00fcdenscheid",
    "sg:postcode":"58511",
    "sg:province":"Nordrhein-Westfalen",
    "wof:name":"Alu-kokillengu\u00df Gmbh",
    "wof:placetype":"venue"
},
  "geometry": {"coordinates":[7.650329,51.215851],"type":"Point"}
}