{
  "type": "Feature",
  "properties": {
    "iso:country":"DE",
    "sg:address":"Heckacker 20",
    "sg:city":"R\u00fcckersdorf",
    "sg:phone":"+49 911/578437",
    "sg:postcode":"90607",
    "sg:province":"Bayern",
    "wof:name":"Max Kolb Dipl.-phys.",
    "wof:placetype":"venue"
},
  "geometry": {"coordinates":[11.2462234497,49.5008506775],"type":"Point"}
}