{
  "type": "Feature",
  "properties": {
    "iso:country":"DE",
    "sg:address":"Poststr. 2",
    "sg:city":"Rostock",
    "sg:phone":"+49 381/519590",
    "sg:postcode":"18119",
    "sg:province":"Mecklenburg-Vorpommern",
    "wof:name":"Asia Palast",
    "wof:placetype":"venue"
},
  "geometry": {"coordinates":[12.0852508545,54.1762657166],"type":"Point"}
}