{
  "type": "Feature",
  "properties": {
    "iso:country":"DE",
    "sg:address":"Schmittstr. 23",
    "sg:city":"Bingen",
    "sg:phone":"+49 6721/14038",
    "sg:postcode":"55411",
    "sg:province":"Rheinland-Pfalz",
    "wof:name":"Falken-apotheke Ingrid Jansen-pfl\u00fcger E. Kfr.",
    "wof:placetype":"venue"
},
  "geometry": {"coordinates":[7.89445,49.966656],"type":"Point"}
}