{
  "type": "Feature",
  "properties": {
    "iso:country":"DE",
    "sg:address":"Schornweg 5",
    "sg:city":"Kreimbach-Kaulbach",
    "sg:phone":"+49 6308/993390",
    "sg:postcode":"67757",
    "sg:province":"Rheinland-Pfalz",
    "wof:name":"Markus Wolf",
    "wof:placetype":"venue"
},
  "geometry": {"coordinates":[7.6352891922,49.5549087524],"type":"Point"}
}