{
  "type": "Feature",
  "properties": {
    "iso:country":"DE",
    "sg:address":"Luisenstrasse 19",
    "sg:city":"Wiesbaden",
    "sg:phone":"+49 611/9339380",
    "sg:postcode":"65185",
    "sg:province":"Hessen",
    "wof:name":"Vivakom Gmbh",
    "wof:placetype":"venue"
},
  "geometry": {"coordinates":[8.2413425446,50.0792922974],"type":"Point"}
}