{
  "type": "Feature",
  "properties": {
    "iso:country":"DE",
    "sg:address":"Zimmerstr. 11",
    "sg:city":"Berlin",
    "sg:phone":"+49 30/7124972",
    "sg:postcode":"12207",
    "sg:province":"Berlin",
    "wof:name":"Joachim Korff",
    "wof:placetype":"venue"
},
  "geometry": {"coordinates":[13.311424,52.417931],"type":"Point"}
}