{
  "type": "Feature",
  "properties": {
    "iso:country":"DE",
    "sg:address":"Lasurstr. 27",
    "sg:city":"Gera",
    "sg:phone":"+49 365/737420",
    "sg:postcode":"07551",
    "sg:province":"Th\u00fcringen",
    "wof:name":"L\u00f6wen-apotheke Inh. Anneliese Peterh\u00e4nsel",
    "wof:placetype":"venue"
},
  "geometry": {"coordinates":[12.089184,50.852016],"type":"Point"}
}