{
  "type": "Feature",
  "properties": {
    "iso:country":"DE",
    "sg:address":"Gr\u00fcner Weg 9",
    "sg:city":"Lengerich",
    "sg:phone":"+49 5481/38647",
    "sg:postcode":"49525",
    "sg:province":"Nordrhein-Westfalen",
    "wof:name":"Friedrich Kn\u00f6pker",
    "wof:placetype":"venue"
},
  "geometry": {"coordinates":[7.784758,52.147266],"type":"Point"}
}