{
  "type": "Feature",
  "properties": {
    "iso:country":"DE",
    "sg:address":"Ludwigstr. 32",
    "sg:city":"Berg",
    "sg:postcode":"76768",
    "sg:province":"Rheinland-Pfalz",
    "wof:name":"Noblesse T\u00fcrf\u00fcllungen Verwaltungs-gmbh",
    "wof:placetype":"venue"
},
  "geometry": {"coordinates":[8.207618,48.982208],"type":"Point"}
}