{
  "type": "Feature",
  "properties": {
    "iso:country":"DE",
    "sg:address":"Sternbergstr. 15",
    "sg:city":"Karlsruhe",
    "sg:phone":"+49 721/606316",
    "sg:postcode":"76131",
    "sg:province":"Baden-W\u00fcrttemberg",
    "wof:name":"Praxis Tarne",
    "wof:placetype":"venue"
},
  "geometry": {"coordinates":[8.4260320663,49.0096511841],"type":"Point"}
}