{
  "type": "Feature",
  "properties": {
    "iso:country":"DE",
    "sg:address":"Stuttgarter Str. 6",
    "sg:city":"Riederich",
    "sg:phone":"+49 4971/2338010",
    "sg:postcode":"72585",
    "sg:province":"Baden-W\u00fcrttemberg",
    "wof:name":"Baldauf Gmbh",
    "wof:placetype":"venue"
},
  "geometry": {"coordinates":[9.269657,48.56073],"type":"Point"}
}