{
  "type": "Feature",
  "properties": {
    "iso:country":"DE",
    "sg:address":"Deutschherrnstr. 4",
    "sg:city":"Petersdorf",
    "sg:phone":"+49 8237/870",
    "sg:postcode":"86574",
    "sg:province":"Bayern",
    "wof:name":"Andreas Wurzer",
    "wof:placetype":"venue"
},
  "geometry": {"coordinates":[11.0167274475,48.510723114],"type":"Point"}
}