{
  "type": "Feature",
  "properties": {
    "iso:country":"DE",
    "sg:address":"Dorfstr. 37",
    "sg:city":"M\u00fcnchen",
    "sg:phone":"+49 89/8112667",
    "sg:postcode":"81247",
    "sg:province":"Bayern",
    "wof:name":"Peter Fenzl",
    "wof:placetype":"venue"
},
  "geometry": {"coordinates":[11.459307,48.168694],"type":"Point"}
}