{
  "type": "Feature",
  "properties": {
    "iso:country":"DE",
    "sg:address":"Feldbergstr. 2",
    "sg:city":"Waldshut-Tiengen",
    "sg:phone":"+49 7741/83050",
    "sg:postcode":"79761",
    "sg:province":"Baden-W\u00fcrttemberg",
    "wof:name":"Hotel Europa",
    "wof:placetype":"venue"
},
  "geometry": {"coordinates":[8.2686252594,47.632396698],"type":"Point"}
}