{
  "type": "Feature",
  "properties": {
    "iso:country":"DE",
    "sg:address":"Eichkamp 6-16",
    "sg:city":"Kiel",
    "sg:phone":"+49 431/180885",
    "sg:postcode":"24116",
    "sg:province":"Schleswig-Holstein",
    "wof:name":"Ernst Repenning & Sohn Gmbh & Co. Kg",
    "wof:placetype":"venue"
},
  "geometry": {"coordinates":[10.110189,54.332092],"type":"Point"}
}