{
  "type": "Feature",
  "properties": {
    "iso:country":"DE",
    "sg:address":"Bahnhofstr. 8",
    "sg:city":"Greu\u00dfen",
    "sg:phone":"+49 3636/704507",
    "sg:postcode":"99718",
    "sg:province":"Th\u00fcringen",
    "wof:name":"Windisch-haustechnik Gmbh",
    "wof:placetype":"venue"
},
  "geometry": {"coordinates":[10.9450712204,51.228553772],"type":"Point"}
}