{
  "type": "Feature",
  "properties": {
    "iso:country":"DE",
    "sg:address":"Obere Dorfstr. 3",
    "sg:city":"Duingen",
    "sg:phone":"+49 5186/870",
    "sg:postcode":"31089",
    "sg:province":"Niedersachsen",
    "wof:name":"Konrad Wa\u00dfmann",
    "wof:placetype":"venue"
},
  "geometry": {"coordinates":[9.650842,51.991356],"type":"Point"}
}