{
  "type": "Feature",
  "properties": {
    "iso:country":"DE",
    "sg:address":"Schlo\u00dfstr. 25",
    "sg:city":"Herten",
    "sg:phone":"+49 209/612626",
    "sg:postcode":"45701",
    "sg:province":"Nordrhein-Westfalen",
    "wof:name":"Big Fashion Anita Herr",
    "wof:placetype":"venue"
},
  "geometry": {"coordinates":[7.091173,51.600117],"type":"Point"}
}