{
  "type": "Feature",
  "properties": {
    "iso:country":"DE",
    "sg:address":"Elmshorner Str. 29",
    "sg:city":"Pinneberg",
    "sg:phone":"+49 4101/204233",
    "sg:postcode":"25421",
    "sg:province":"Schleswig-Holstein",
    "wof:name":"Lezzet-brot- Gmbh",
    "wof:placetype":"venue"
},
  "geometry": {"coordinates":[9.796525,53.6623],"type":"Point"}
}