{
  "type": "Feature",
  "properties": {
    "iso:country":"DE",
    "sg:address":"Auf dem Flintacker 53",
    "sg:city":"Bremen",
    "sg:phone":"+49 421/654519",
    "sg:postcode":"28755",
    "sg:province":"Bremen",
    "wof:name":"E. Wei\u00dfflog",
    "wof:placetype":"venue"
},
  "geometry": {"coordinates":[8.6349992752,53.1891136169],"type":"Point"}
}