{
  "type": "Feature",
  "properties": {
    "iso:country":"DE",
    "sg:address":"Pf\u00e4lzer Str. 15",
    "sg:city":"Neckarsulm",
    "sg:phone":"+49 7132/980115",
    "sg:postcode":"74172",
    "sg:province":"Baden-W\u00fcrttemberg",
    "wof:name":"Ralf Rie\u00df",
    "wof:placetype":"venue"
},
  "geometry": {"coordinates":[9.244241,49.202831],"type":"Point"}
}