{
  "type": "Feature",
  "properties": {
    "iso:country":"DE",
    "sg:address":"Weststr. 114",
    "sg:city":"Ahlen",
    "sg:phone":"+49 2382/91630",
    "sg:postcode":"59227",
    "sg:province":"Nordrhein-Westfalen",
    "wof:name":"Peter J\u00fcrgens",
    "wof:placetype":"venue"
},
  "geometry": {"coordinates":[7.8834791183,51.7632713318],"type":"Point"}
}