{
  "type": "Feature",
  "properties": {
    "iso:country":"DE",
    "sg:address":"Langemarckstr. 119",
    "sg:city":"Bremen",
    "sg:phone":"+49 421/593540",
    "sg:postcode":"28199",
    "sg:province":"Bremen",
    "wof:name":"R. Berghold",
    "wof:placetype":"venue"
},
  "geometry": {"coordinates":[8.790489,53.071651],"type":"Point"}
}