{
  "type": "Feature",
  "properties": {
    "iso:country":"DE",
    "sg:address":"Bahnhofstr. 2",
    "sg:city":"Oberammergau",
    "sg:phone":"+49 8822/3940",
    "sg:postcode":"82487",
    "sg:province":"Bayern",
    "wof:name":"Rudo Pr\u00e4gert Bildhauer",
    "wof:placetype":"venue"
},
  "geometry": {"coordinates":[11.057037,47.59893],"type":"Point"}
}