{
  "type": "Feature",
  "properties": {
    "iso:country":"DE",
    "sg:address":"Wohlenbergstr 22",
    "sg:city":"Hannover",
    "sg:phone":"+49 511/968760",
    "sg:postcode":"30179",
    "sg:province":"Niedersachsen",
    "wof:name":"Neukirch Spezialtransporte Gmbh & Co Kg",
    "wof:placetype":"venue"
},
  "geometry": {"coordinates":[9.720492363,52.4167861938],"type":"Point"}
}