{
  "type": "Feature",
  "properties": {
    "iso:country":"DE",
    "sg:address":"Freusbergstr. 3",
    "sg:city":"Lennestadt",
    "sg:phone":"+49 2721/81147",
    "sg:postcode":"57368",
    "sg:province":"Nordrhein-Westfalen",
    "wof:name":"K\u00e4lte B\u00e4cker Gmbh",
    "wof:placetype":"venue"
},
  "geometry": {"coordinates":[8.016798,51.094589],"type":"Point"}
}