{
  "type": "Feature",
  "properties": {
    "iso:country":"DE",
    "sg:address":"Schandauer Str. 7",
    "sg:city":"Sebnitz",
    "sg:postcode":"01855",
    "sg:province":"Sachsen",
    "wof:name":"Drogerie",
    "wof:placetype":"venue"
},
  "geometry": {"coordinates":[14.270943,50.971752],"type":"Point"}
}