{
  "type": "Feature",
  "properties": {
    "iso:country":"DE",
    "sg:address":"Im Schwenkenland 8",
    "sg:city":"Umkirch",
    "sg:phone":"+49 7665/98010",
    "sg:postcode":"79224",
    "sg:province":"Baden-W\u00fcrttemberg",
    "wof:name":"Werner Hirzle Ingenieur",
    "wof:placetype":"venue"
},
  "geometry": {"coordinates":[7.7706189156,48.0326080322],"type":"Point"}
}