{
  "type": "Feature",
  "properties": {
    "iso:country":"DE",
    "sg:address":"Wiesenweg 5",
    "sg:city":"Idstein",
    "sg:phone":"+49 6126/2529",
    "sg:postcode":"65510",
    "sg:province":"Hessen",
    "wof:name":"Hans Joachim Koch Elektroinstallation",
    "wof:placetype":"venue"
},
  "geometry": {"coordinates":[8.334015,50.220207],"type":"Point"}
}