{
  "type": "Feature",
  "properties": {
    "iso:country":"DE",
    "sg:address":"Wittekindstr. 17",
    "sg:city":"N\u00fcrnberg",
    "sg:phone":"+49 911/527777",
    "sg:postcode":"90431",
    "sg:province":"Bayern",
    "wof:name":"Pl\u00f6\u00dfl Megerle U. Partner Gmbh",
    "wof:placetype":"venue"
},
  "geometry": {"coordinates":[11.0164375305,49.4578666687],"type":"Point"}
}