{
  "type": "Feature",
  "properties": {
    "iso:country":"DE",
    "sg:address":"Honigbach 18",
    "sg:city":"Bad Salzungen",
    "sg:phone":"+49 3695/622229",
    "sg:postcode":"36433",
    "sg:province":"Th\u00fcringen",
    "wof:name":"J\u00fcrgen Termin",
    "wof:placetype":"venue"
},
  "geometry": {"coordinates":[10.229564,50.803711],"type":"Point"}
}