{
  "type": "Feature",
  "properties": {
    "iso:country":"DE",
    "sg:address":"Am Breitenstock 2",
    "sg:city":"Burgthann",
    "sg:postcode":"90559",
    "sg:province":"Bayern",
    "wof:name":"Bauer-automation Gmbh",
    "wof:placetype":"venue"
},
  "geometry": {"coordinates":[11.337427,49.323006],"type":"Point"}
}