{
  "type": "Feature",
  "properties": {
    "iso:country":"DE",
    "sg:address":"Lerchenstr. 14 Haus 4",
    "sg:city":"M\u00fcnchen",
    "sg:phone":"+49 89/3546371",
    "sg:postcode":"80995",
    "sg:province":"Bayern",
    "wof:name":"Iba Ingenieurb\u00fcro F\u00fcr Aufzugstechnik",
    "wof:placetype":"venue"
},
  "geometry": {"coordinates":[11.5240278244,48.1979637146],"type":"Point"}
}