{
  "type": "Feature",
  "properties": {
    "iso:country":"DE",
    "sg:address":"Karl-Marx-Str. 6",
    "sg:city":"Letschin",
    "sg:postcode":"15324",
    "sg:province":"Brandenburg",
    "wof:name":"Hans-j\u00fcrgen Dresch",
    "wof:placetype":"venue"
},
  "geometry": {"coordinates":[14.359756,52.645504],"type":"Point"}
}