{
  "type": "Feature",
  "properties": {
    "iso:country":"DE",
    "sg:address":"Gartenstr. 51",
    "sg:city":"Rhede",
    "sg:phone":"+49 2871/2381",
    "sg:postcode":"46414",
    "sg:province":"Nordrhein-Westfalen",
    "wof:name":"Bellanet Textil- Und Garnvertriebs Gmbh",
    "wof:placetype":"venue"
},
  "geometry": {"coordinates":[6.7014579773,51.8457374573],"type":"Point"}
}