{
  "type": "Feature",
  "properties": {
    "iso:country":"DE",
    "sg:address":"Sewanstr. 265",
    "sg:city":"Berlin",
    "sg:phone":"+49 30",
    "sg:postcode":"10319",
    "sg:province":"Berlin",
    "wof:name":"Einkaufen Is Cool - Die Besten Shops Im Internet",
    "wof:placetype":"venue"
},
  "geometry": {"coordinates":[13.521482,52.495518],"type":"Point"}
}