{
  "type": "Feature",
  "properties": {
    "iso:country":"DE",
    "sg:address":"Hauptstr. 51",
    "sg:city":"Gefrees",
    "sg:phone":"+49 9254/337",
    "sg:postcode":"95482",
    "sg:province":"Bayern",
    "wof:name":"Hotel Gr\u00fcner Baum",
    "wof:placetype":"venue"
},
  "geometry": {"coordinates":[11.7380361557,50.0949668884],"type":"Point"}
}