{
  "type": "Feature",
  "properties": {
    "iso:country":"DE",
    "sg:address":"Frankenstr. 7",
    "sg:city":"Polch",
    "sg:phone":"+49 2654/1721",
    "sg:postcode":"56751",
    "sg:province":"Rheinland-Pfalz",
    "wof:name":"Hans-joachim Ochotta Steuerberater",
    "wof:placetype":"venue"
},
  "geometry": {"coordinates":[7.3098301888,50.2976875305],"type":"Point"}
}