{
  "type": "Feature",
  "properties": {
    "iso:country":"DE",
    "sg:address":"Frankfurter Str. 24",
    "sg:city":"Gedern",
    "sg:postcode":"63688",
    "sg:province":"Hessen",
    "wof:name":"Gwi Gesellschaft F\u00fcr Gewerbe- Und Immobilienmanagement",
    "wof:placetype":"venue"
},
  "geometry": {"coordinates":[9.1972970963,50.4223327637],"type":"Point"}
}