{
  "type": "Feature",
  "properties": {
    "iso:country":"DE",
    "sg:address":"Bielefelder Str. 115",
    "sg:city":"Rheda-Wiedenbr\u00fcck",
    "sg:phone":"+49 5242/57437",
    "sg:postcode":"33378",
    "sg:province":"Nordrhein-Westfalen",
    "wof:name":"W. Micke",
    "wof:placetype":"venue"
},
  "geometry": {"coordinates":[8.3423576355,51.8685569763],"type":"Point"}
}