{
  "type": "Feature",
  "properties": {
    "iso:country":"DE",
    "sg:address":"Josephsplatz 18",
    "sg:city":"N\u00fcrnberg",
    "sg:phone":"+49 911/22991",
    "sg:postcode":"90403",
    "sg:province":"Bayern",
    "wof:name":"Bauten Und Boden S\u00fcd Gmbh",
    "wof:placetype":"venue"
},
  "geometry": {"coordinates":[11.0730104446,49.4516296387],"type":"Point"}
}