{
  "type": "Feature",
  "properties": {
    "iso:country":"DE",
    "sg:address":"Wandsbeker Chaussee 48",
    "sg:city":"Hamburg",
    "sg:phone":"+49 40/25492644",
    "sg:postcode":"22089",
    "sg:province":"Hamburg",
    "wof:name":"W. Pl\u00e4tow",
    "wof:placetype":"venue"
},
  "geometry": {"coordinates":[10.0378427505,53.5655517578],"type":"Point"}
}