{
  "type": "Feature",
  "properties": {
    "iso:country":"DE",
    "sg:address":"Weender Landstr. 49",
    "sg:city":"G\u00f6ttingen",
    "sg:phone":"+49 551/486413",
    "sg:postcode":"37075",
    "sg:province":"Niedersachsen",
    "wof:name":"Pchouse Gmbh",
    "wof:placetype":"venue"
},
  "geometry": {"coordinates":[9.931901,51.54398],"type":"Point"}
}