{
  "type": "Feature",
  "properties": {
    "iso:country":"DE",
    "sg:address":"L\u00fctzowstr. 44",
    "sg:city":"Leipzig",
    "sg:phone":"+49 341/9012906",
    "sg:postcode":"04157",
    "sg:province":"Sachsen",
    "wof:name":"Delphin-apotheke Inh. Chris Hellinger",
    "wof:placetype":"venue"
},
  "geometry": {"coordinates":[12.376043,51.364552],"type":"Point"}
}