{
  "type": "Feature",
  "properties": {
    "iso:country":"DE",
    "sg:address":"Marktplatz 13",
    "sg:city":"Isny",
    "sg:phone":"+49 7562/4812",
    "sg:postcode":"88316",
    "sg:province":"Baden-W\u00fcrttemberg",
    "wof:name":"Ihr Platz Drogeriemarkt",
    "wof:placetype":"venue"
},
  "geometry": {"coordinates":[10.039206,47.692108],"type":"Point"}
}