{
  "type": "Feature",
  "properties": {
    "iso:country":"DE",
    "sg:address":"Konrad-Adenauer-Str. 80",
    "sg:city":"Salzgitter",
    "sg:phone":"+49 5341/14499",
    "sg:postcode":"38226",
    "sg:province":"Niedersachsen",
    "wof:name":"Nieders\u00e4chsisches Landvolk Salzgitter E. V.",
    "wof:placetype":"venue"
},
  "geometry": {"coordinates":[10.338574,52.152618],"type":"Point"}
}