{
  "type": "Feature",
  "properties": {
    "iso:country":"DE",
    "sg:address":"Dotzheimer Str. 168",
    "sg:city":"Wiesbaden",
    "sg:phone":"+49 611/8840",
    "sg:postcode":"65197",
    "sg:province":"Hessen",
    "wof:name":"Redaktion Neue Solidarit\u00e4t B\u00f6ttiger Verlag",
    "wof:placetype":"venue"
},
  "geometry": {"coordinates":[8.2120046616,50.0764312744],"type":"Point"}
}