{
  "type": "Feature",
  "properties": {
    "iso:country":"DE",
    "sg:address":"Langener Landstr. 226",
    "sg:city":"Bremerhaven",
    "sg:phone":"+49 471/801033",
    "sg:postcode":"27578",
    "sg:province":"Bremen",
    "wof:name":"Transmercant Bodenbelagsgro\u00dfhandel Gmbh",
    "wof:placetype":"venue"
},
  "geometry": {"coordinates":[8.5978517532,53.5874061584],"type":"Point"}
}