{
  "type": "Feature",
  "properties": {
    "iso:country":"DE",
    "sg:address":"Hauptstr. 84",
    "sg:city":"Pockau",
    "sg:phone":"+49 37367/8863",
    "sg:postcode":"09509",
    "sg:province":"Sachsen",
    "wof:name":"Johannes Seifert",
    "wof:placetype":"venue"
},
  "geometry": {"coordinates":[13.27102,50.731709],"type":"Point"}
}