{
  "type": "Feature",
  "properties": {
    "iso:country":"DE",
    "sg:address":"Am B\u00fcrgerteich 4",
    "sg:city":"Schleiz",
    "sg:phone":"+49 3663/428501",
    "sg:postcode":"07907",
    "sg:province":"Th\u00fcringen",
    "wof:name":"Orthop\u00e4die-technik Artur Herbst",
    "wof:placetype":"venue"
},
  "geometry": {"coordinates":[11.8097448349,50.5790863037],"type":"Point"}
}