{
  "type": "Feature",
  "properties": {
    "iso:country":"DE",
    "sg:address":"Landsberger Str 191a",
    "sg:city":"M\u00fcnchen",
    "sg:phone":"+49 89/54779020",
    "sg:postcode":"80687",
    "sg:province":"Bayern",
    "wof:name":"Alu Leitl Gmbh",
    "wof:placetype":"venue"
},
  "geometry": {"coordinates":[11.519764,48.141014],"type":"Point"}
}