{
  "type": "Feature",
  "properties": {
    "iso:country":"DE",
    "sg:address":"Katharina-Heinroth-Ufer 1",
    "sg:city":"Berlin",
    "sg:phone":"+49 30/25411100",
    "sg:postcode":"10787",
    "sg:province":"Berlin",
    "wof:name":"Trigon Grundst\u00fccks Gmbh & Co. Radickestra\u00dfe Kg",
    "wof:placetype":"venue"
},
  "geometry": {"coordinates":[13.3435649872,52.5081825256],"type":"Point"}
}