{
  "type": "Feature",
  "properties": {
    "iso:country":"DE",
    "sg:address":"Milchstr. 10",
    "sg:city":"M\u00fcnchen",
    "sg:phone":"+49 89/4484813",
    "sg:postcode":"81667",
    "sg:province":"Bayern",
    "wof:name":"Schreinerei Robert Glas Gmbh",
    "wof:placetype":"venue"
},
  "geometry": {"coordinates":[11.596764,48.131229],"type":"Point"}
}