{
  "type": "Feature",
  "properties": {
    "iso:country":"DE",
    "sg:address":"Am Haarhaus 6",
    "sg:city":"Ostbevern",
    "sg:phone":"+49 2532/5085",
    "sg:postcode":"48346",
    "sg:province":"Nordrhein-Westfalen",
    "wof:name":"Konrad Laagland",
    "wof:placetype":"venue"
},
  "geometry": {"coordinates":[7.8316888809,52.04296875],"type":"Point"}
}