{
  "type": "Feature",
  "properties": {
    "iso:country":"DE",
    "sg:address":"Friedrich-Ebert-Str. 9",
    "sg:city":"M\u00f6ser",
    "sg:phone":"+49 39222/2223",
    "sg:postcode":"39291",
    "sg:province":"Sachsen-Anhalt",
    "wof:name":"J\u00f6rn B\u00f6ttcher",
    "wof:placetype":"venue"
},
  "geometry": {"coordinates":[11.783804,52.222027],"type":"Point"}
}