{
  "type": "Feature",
  "properties": {
    "iso:country":"DE",
    "sg:address":"Talstr. 8",
    "sg:city":"Bad Saulgau",
    "sg:phone":"+49 7581/4342",
    "sg:postcode":"88348",
    "sg:province":"Baden-W\u00fcrttemberg",
    "wof:name":"Ams Automarkt Verwaltungsges. Mbh",
    "wof:placetype":"venue"
},
  "geometry": {"coordinates":[9.4898948669,48.0219650269],"type":"Point"}
}