{
  "type": "Feature",
  "properties": {
    "iso:country":"DE",
    "sg:address":"Friedhofstr. 25",
    "sg:city":"Nagold",
    "sg:phone":"+49 7452/2320",
    "sg:postcode":"72202",
    "sg:province":"Baden-W\u00fcrttemberg",
    "wof:name":"Ev. Pfarramt Remigiuskirche",
    "wof:placetype":"venue"
},
  "geometry": {"coordinates":[8.7149047852,48.5443954468],"type":"Point"}
}