{
  "type": "Feature",
  "properties": {
    "iso:country":"DE",
    "sg:address":"Scheidertalstr. 1",
    "sg:city":"Taunusstein",
    "sg:phone":"+49 6128/3726",
    "sg:postcode":"65232",
    "sg:province":"Hessen",
    "wof:name":"Restaurant Zum Taunus",
    "wof:placetype":"venue"
},
  "geometry": {"coordinates":[8.1590843201,50.1431312561],"type":"Point"}
}