{
  "type": "Feature",
  "properties": {
    "iso:country":"DE",
    "sg:address":"Am Holzplatz 9",
    "sg:city":"Herne",
    "sg:phone":"+49 2323/963530",
    "sg:postcode":"44627",
    "sg:province":"Nordrhein-Westfalen",
    "wof:name":"Ralf Zinta",
    "wof:placetype":"venue"
},
  "geometry": {"coordinates":[7.2683358192,51.5429954529],"type":"Point"}
}