{
  "type": "Feature",
  "properties": {
    "iso:country":"DE",
    "sg:address":"Hauptstr. 49",
    "sg:city":"Gro\u00dfsch\u00f6nau",
    "sg:phone":"+49 35841/36000",
    "sg:postcode":"02779",
    "sg:province":"Sachsen",
    "wof:name":"Mandau-apotheke Elisabeth Pietschmann",
    "wof:placetype":"venue"
},
  "geometry": {"coordinates":[14.657507,50.897285],"type":"Point"}
}