{
  "type": "Feature",
  "properties": {
    "iso:country":"DE",
    "sg:address":"Osnabr\u00fccker Str. 157",
    "sg:city":"Melle",
    "sg:phone":"+49 5422/8437",
    "sg:postcode":"49324",
    "sg:province":"Niedersachsen",
    "wof:name":"Kallenbach Bestattungen",
    "wof:placetype":"venue"
},
  "geometry": {"coordinates":[8.30172,52.23922],"type":"Point"}
}