{
  "type": "Feature",
  "properties": {
    "iso:country":"DE",
    "sg:address":"Zeisigweg 1",
    "sg:city":"Diedorf",
    "sg:phone":"+49 8238/2815",
    "sg:postcode":"86420",
    "sg:province":"Bayern",
    "wof:name":"R. Dangel",
    "wof:placetype":"venue"
},
  "geometry": {"coordinates":[10.7722072601,48.3414154053],"type":"Point"}
}