{
  "type": "Feature",
  "properties": {
    "iso:country":"DE",
    "sg:address":"Eichenstr. 11",
    "sg:city":"Roetgen",
    "sg:phone":"+49 2471/3344",
    "sg:postcode":"52159",
    "sg:province":"Nordrhein-Westfalen",
    "wof:name":"Marco Maraggia Architekt",
    "wof:placetype":"venue"
},
  "geometry": {"coordinates":[6.213894,50.643616],"type":"Point"}
}