{
  "type": "Feature",
  "properties": {
    "iso:country":"DE",
    "sg:address":"Triebstr. 14",
    "sg:city":"Wagh\u00e4usel",
    "sg:phone":"+49 7254/76300",
    "sg:postcode":"68753",
    "sg:province":"Baden-W\u00fcrttemberg",
    "wof:name":"K. M\u00fcller",
    "wof:placetype":"venue"
},
  "geometry": {"coordinates":[8.5178394318,49.2190093994],"type":"Point"}
}