{
  "type": "Feature",
  "properties": {
    "iso:country":"DE",
    "sg:address":"Bergstr. 10",
    "sg:city":"Darstein",
    "sg:phone":"+49 6398/388",
    "sg:postcode":"76848",
    "sg:province":"Rheinland-Pfalz",
    "wof:name":"M. Demuth Immobilienmakler",
    "wof:placetype":"venue"
},
  "geometry": {"coordinates":[7.8829159737,49.1586990356],"type":"Point"}
}