{
  "type": "Feature",
  "properties": {
    "iso:country":"DE",
    "sg:address":"Lorenzer Str. 33",
    "sg:city":"N\u00fcrnberg",
    "sg:phone":"+49 911/22048",
    "sg:postcode":"90402",
    "sg:province":"Bayern",
    "wof:name":"Zwinger",
    "wof:placetype":"venue"
},
  "geometry": {"coordinates":[11.083016,49.449959],"type":"Point"}
}