{
  "type": "Feature",
  "properties": {
    "iso:country":"DE",
    "sg:address":"Stanzer Zeile 47-49",
    "sg:city":"Berlin",
    "sg:phone":"+49 30/7111834",
    "sg:postcode":"12209",
    "sg:province":"Berlin",
    "wof:name":"Mtd J\u00f6rg Teske",
    "wof:placetype":"venue"
},
  "geometry": {"coordinates":[13.337218,52.413525],"type":"Point"}
}