{
  "type": "Feature",
  "properties": {
    "iso:country":"DE",
    "sg:address":"Gutenbergstr. 33",
    "sg:city":"Illingen",
    "sg:phone":"+49 7042/21220",
    "sg:postcode":"75428",
    "sg:province":"Baden-W\u00fcrttemberg",
    "wof:name":"Winkler",
    "wof:placetype":"venue"
},
  "geometry": {"coordinates":[8.9279308319,48.9576683044],"type":"Point"}
}