{
  "type": "Feature",
  "properties": {
    "iso:country":"DE",
    "sg:address":"Werner-Seelenbinder-Str.",
    "sg:city":"Schwedt",
    "sg:postcode":"16303",
    "sg:province":"Brandenburg",
    "wof:name":"Aldi Gmbh & Co. Kg",
    "wof:placetype":"venue"
},
  "geometry": {"coordinates":[14.2483434677,53.0743904114],"type":"Point"}
}