{
  "type": "Feature",
  "properties": {
    "iso:country":"DE",
    "sg:address":"Strogenstr. 17",
    "sg:city":"Wartenberg",
    "sg:phone":"+49 8762/1231",
    "sg:postcode":"85456",
    "sg:province":"Bayern",
    "wof:name":"Kath. Pfarramt Gem. Wartenberg Strogen",
    "wof:placetype":"venue"
},
  "geometry": {"coordinates":[11.9889955521,48.4031562805],"type":"Point"}
}