{
  "type": "Feature",
  "properties": {
    "iso:country":"DE",
    "sg:address":"Stuttgarter Str. 16",
    "sg:city":"Vaihingen",
    "sg:phone":"+49 7042/6159",
    "sg:postcode":"71665",
    "sg:province":"Baden-W\u00fcrttemberg",
    "wof:name":"Gasthof Traube",
    "wof:placetype":"venue"
},
  "geometry": {"coordinates":[8.9581823349,48.931438446],"type":"Point"}
}