{
  "type": "Feature",
  "properties": {
    "iso:country":"DE",
    "sg:address":"Bismarckstr. 43 b",
    "sg:city":"Moers",
    "sg:phone":"+49 2841/52138",
    "sg:postcode":"47443",
    "sg:province":"Nordrhein-Westfalen",
    "wof:name":"Sonnen-apotheke Dr. Wolfgang Gunder",
    "wof:placetype":"venue"
},
  "geometry": {"coordinates":[6.645655,51.464161],"type":"Point"}
}