{
  "type": "Feature",
  "properties": {
    "iso:country":"DE",
    "sg:address":"Bergstr. 124",
    "sg:city":"Marl",
    "sg:phone":"+49 2365/9249240",
    "sg:postcode":"45770",
    "sg:province":"Nordrhein-Westfalen",
    "wof:name":"Vestax Steuerberatungsges. Mbh",
    "wof:placetype":"venue"
},
  "geometry": {"coordinates":[7.1158819199,51.6620292664],"type":"Point"}
}