{
  "type": "Feature",
  "properties": {
    "iso:country":"DE",
    "sg:address":"Mauritiusweg 1",
    "sg:city":"Rheinfelden",
    "sg:phone":"+49 7622/669609",
    "sg:postcode":"79618",
    "sg:province":"Baden-W\u00fcrttemberg",
    "wof:name":"Katharina Rauch",
    "wof:placetype":"venue"
},
  "geometry": {"coordinates":[7.8206157684,47.6192741394],"type":"Point"}
}