{
  "type": "Feature",
  "properties": {
    "iso:country":"DE",
    "sg:address":"Cleverns",
    "sg:city":"Jever",
    "sg:phone":"+49 4461/3756",
    "sg:postcode":"26441",
    "sg:province":"Niedersachsen",
    "wof:name":"E. Eckstein",
    "wof:placetype":"venue"
},
  "geometry": {"coordinates":[7.8613600731,53.549079895],"type":"Point"}
}