{
  "type": "Feature",
  "properties": {
    "iso:country":"DE",
    "sg:address":"Landzungenstr. 11",
    "sg:city":"Mannheim",
    "sg:phone":"+49 4962/1158060",
    "sg:postcode":"68159",
    "sg:province":"Baden-W\u00fcrttemberg",
    "wof:name":"Schuster & Co Gmbh",
    "wof:placetype":"venue"
},
  "geometry": {"coordinates":[8.452014,49.498241],"type":"Point"}
}