{
  "type": "Feature",
  "properties": {
    "iso:country":"DE",
    "sg:address":"Hutneck 10",
    "sg:city":"Schramberg",
    "sg:phone":"+49 7422/6119",
    "sg:postcode":"78713",
    "sg:province":"Baden-W\u00fcrttemberg",
    "wof:name":"Hutneck",
    "wof:placetype":"venue"
},
  "geometry": {"coordinates":[8.4122552872,48.2138366699],"type":"Point"}
}