{
  "type": "Feature",
  "properties": {
    "iso:country":"DE",
    "sg:address":"Elsassergasse 10",
    "sg:city":"Dinkelsb\u00fchl",
    "sg:phone":"+49 9851/2066",
    "sg:postcode":"91550",
    "sg:province":"Bayern",
    "wof:name":"Reitertruhe",
    "wof:placetype":"venue"
},
  "geometry": {"coordinates":[10.317956,49.07032],"type":"Point"}
}