{
  "type": "Feature",
  "properties": {
    "iso:country":"DE",
    "sg:address":"Gautinger Str. 52",
    "sg:city":"We\u00dfling",
    "sg:phone":"+49 8153/916127",
    "sg:postcode":"82234",
    "sg:province":"Bayern",
    "wof:name":"Plonner",
    "wof:placetype":"venue"
},
  "geometry": {"coordinates":[11.2627744675,48.0743751526],"type":"Point"}
}