{
  "type": "Feature",
  "properties": {
    "iso:country":"DE",
    "sg:address":"Kirchender Dorfweg 14",
    "sg:city":"Herdecke",
    "sg:phone":"+49 2330/80880",
    "sg:postcode":"58313",
    "sg:province":"Nordrhein-Westfalen",
    "wof:name":"Gottschalk Und Wojtys Rechtsanw\u00e4lte",
    "wof:placetype":"venue"
},
  "geometry": {"coordinates":[7.4288859367,51.4186820984],"type":"Point"}
}