{
  "type": "Feature",
  "properties": {
    "iso:country":"DE",
    "sg:address":"Trarbacher Str. 8",
    "sg:city":"Duisburg",
    "sg:phone":"+49 203/7578655",
    "sg:postcode":"47259",
    "sg:province":"Nordrhein-Westfalen",
    "wof:name":"H\u00e4usliche Krankenpflege Akwara",
    "wof:placetype":"venue"
},
  "geometry": {"coordinates":[6.76221,51.36417],"type":"Point"}
}