{
  "type": "Feature",
  "properties": {
    "iso:country":"DE",
    "sg:address":"Bleichenstr 28",
    "sg:city":"Wunstorf",
    "sg:phone":"+49 5033/5225",
    "sg:postcode":"31515",
    "sg:province":"Niedersachsen",
    "wof:name":"Fr. Seegers & Sohn Gmbh",
    "wof:placetype":"venue"
},
  "geometry": {"coordinates":[9.3649263382,52.4583396912],"type":"Point"}
}