{
  "type": "Feature",
  "properties": {
    "iso:country":"DE",
    "sg:address":"Teichstr. 5 b",
    "sg:city":"Panitzsch",
    "sg:phone":"+49 34291/86443",
    "sg:postcode":"04451",
    "sg:province":"Sachsen",
    "wof:name":"Konsumgenoss. Leipzig Eg",
    "wof:placetype":"venue"
},
  "geometry": {"coordinates":[12.529757,51.362572],"type":"Point"}
}