{
  "type": "Feature",
  "properties": {
    "iso:country":"DE",
    "sg:address":"Ziegenhainer Str. 19",
    "sg:city":"Schwalmstadt",
    "sg:phone":"+49 5681/883",
    "sg:postcode":"34613",
    "sg:province":"Hessen",
    "wof:name":"Einkaufszentrum Ziegenhain Heinz Linne Kg",
    "wof:placetype":"venue"
},
  "geometry": {"coordinates":[9.2525672913,50.9142036438],"type":"Point"}
}