{
  "type": "Feature",
  "properties": {
    "iso:country":"DE",
    "sg:address":"Rathenower Str. 6",
    "sg:city":"Rhinow",
    "sg:phone":"+49 33875/30512",
    "sg:postcode":"14728",
    "sg:province":"Brandenburg",
    "wof:name":"Karl-heinz Schnee & Sohn Ohg",
    "wof:placetype":"venue"
},
  "geometry": {"coordinates":[12.347875,52.752289],"type":"Point"}
}