{
  "type": "Feature",
  "properties": {
    "iso:country":"DE",
    "sg:address":"Schwetzinger Str. 9",
    "sg:city":"Ketsch",
    "sg:phone":"+49 6202/68845",
    "sg:postcode":"68775",
    "sg:province":"Baden-W\u00fcrttemberg",
    "wof:name":"Alakart Speisekarten.com Gmbh",
    "wof:placetype":"venue"
},
  "geometry": {"coordinates":[8.5195,49.37402],"type":"Point"}
}