{
  "type": "Feature",
  "properties": {
    "iso:country":"DE",
    "sg:address":"Bergisch Gladbacher Str 1067-1069",
    "sg:city":"K\u00f6ln",
    "sg:phone":"+49 221/689240",
    "sg:postcode":"51069",
    "sg:province":"Nordrhein-Westfalen",
    "wof:name":"K\u00f6lner Marmorwerke H.-j. Engelhardt Gmbh",
    "wof:placetype":"venue"
},
  "geometry": {"coordinates":[7.0759577751,50.9808197021],"type":"Point"}
}