{
  "type": "Feature",
  "properties": {
    "iso:country":"DE",
    "sg:address":"Martinistr. 34",
    "sg:city":"Bremen",
    "sg:phone":"+49 421/302710",
    "sg:postcode":"28195",
    "sg:province":"Bremen",
    "wof:name":"Wohnen Und Ideen Einrichtung- Licht-accessoirs Handels Gmbh",
    "wof:placetype":"venue"
},
  "geometry": {"coordinates":[8.803842,53.07642],"type":"Point"}
}