{
  "type": "Feature",
  "properties": {
    "iso:country":"DE",
    "sg:address":"G\u00fcldenstr. 41",
    "sg:city":"Braunschweig",
    "sg:phone":"+49 531/43603",
    "sg:postcode":"38100",
    "sg:province":"Niedersachsen",
    "wof:name":"Roset-studio",
    "wof:placetype":"venue"
},
  "geometry": {"coordinates":[10.514206,52.266747],"type":"Point"}
}