{
  "type": "Feature",
  "properties": {
    "iso:country":"DE",
    "sg:address":"H\u00f6llmannsried 23",
    "sg:city":"Kirchberg i. Wald",
    "sg:phone":"+49 9927/504",
    "sg:postcode":"94259",
    "sg:province":"Bayern",
    "wof:name":"J. Wengenmayer",
    "wof:placetype":"venue"
},
  "geometry": {"coordinates":[13.169295311,48.8824729919],"type":"Point"}
}