{
  "type": "Feature",
  "properties": {
    "iso:country":"DE",
    "sg:address":"Rosenstr. 12",
    "sg:city":"Iffezheim",
    "sg:phone":"+49 7229/4150",
    "sg:postcode":"76473",
    "sg:province":"Baden-W\u00fcrttemberg",
    "wof:name":"Schock Bauelemente Gmbh",
    "wof:placetype":"venue"
},
  "geometry": {"coordinates":[8.149602,48.821175],"type":"Point"}
}