{
  "type": "Feature",
  "properties": {
    "iso:country":"DE",
    "sg:address":"Hugo-Lang-Bogen 13",
    "sg:city":"M\u00fcnchen",
    "sg:phone":"+49 89/6352565",
    "sg:postcode":"81735",
    "sg:province":"Bayern",
    "wof:name":"Johannes Smuda",
    "wof:placetype":"venue"
},
  "geometry": {"coordinates":[11.6611032486,48.1041984558],"type":"Point"}
}