{
  "type": "Feature",
  "properties": {
    "iso:country":"DE",
    "sg:address":"Karlsruher Str. 23",
    "sg:city":"Heidelberg",
    "sg:phone":"+49 6221/314820",
    "sg:postcode":"69126",
    "sg:province":"Baden-W\u00fcrttemberg",
    "wof:name":"Walter Isele Steuerberater",
    "wof:placetype":"venue"
},
  "geometry": {"coordinates":[8.6907119751,49.3851013184],"type":"Point"}
}