{
  "type": "Feature",
  "properties": {
    "iso:country":"DE",
    "sg:address":"Hansestr. 10a",
    "sg:city":"Sittensen",
    "sg:phone":"+49 4282/4147",
    "sg:postcode":"27419",
    "sg:province":"Niedersachsen",
    "wof:name":"Sittenser Euro-truck-wasch Hans-wilhelm Mahnken",
    "wof:placetype":"venue"
},
  "geometry": {"coordinates":[9.504962,53.29385],"type":"Point"}
}