{
  "type": "Feature",
  "properties": {
    "iso:country":"DE",
    "sg:address":"Schwarzenkopfstr. 5",
    "sg:city":"M\u00fcnchen",
    "sg:phone":"+49 89/428377",
    "sg:postcode":"81825",
    "sg:province":"Bayern",
    "wof:name":"Becker",
    "wof:placetype":"venue"
},
  "geometry": {"coordinates":[11.671620369,48.1166343689],"type":"Point"}
}