{
  "type": "Feature",
  "properties": {
    "iso:country":"DE",
    "sg:address":"Kreutweg 19",
    "sg:city":"Illerrieden",
    "sg:phone":"+49 7306/96230",
    "sg:postcode":"89186",
    "sg:province":"Baden-W\u00fcrttemberg",
    "wof:name":"Eska Peter Scheich",
    "wof:placetype":"venue"
},
  "geometry": {"coordinates":[10.049322,48.251446],"type":"Point"}
}