{
  "type": "Feature",
  "properties": {
    "iso:country":"DE",
    "sg:address":"Stadionstr. 4",
    "sg:city":"Villingendorf",
    "sg:phone":"+49 741/347187",
    "sg:postcode":"78667",
    "sg:province":"Baden-W\u00fcrttemberg",
    "wof:name":"Kehl Wassertechnik Gmbh",
    "wof:placetype":"venue"
},
  "geometry": {"coordinates":[8.586313,48.208973],"type":"Point"}
}