{
  "type": "Feature",
  "properties": {
    "iso:country":"DE",
    "sg:address":"Gotha-Allee 23 c",
    "sg:city":"Berlin",
    "sg:phone":"+49 30/30099149",
    "sg:postcode":"14052",
    "sg:province":"Berlin",
    "wof:name":"J\u00fcrgen Becker",
    "wof:placetype":"venue"
},
  "geometry": {"coordinates":[13.257302,52.520653],"type":"Point"}
}