{
  "type": "Feature",
  "properties": {
    "iso:country":"DE",
    "sg:address":"Stra\u00dfe der Jugend 11 b",
    "sg:city":"Eldena",
    "sg:phone":"+49 38755/20032",
    "sg:postcode":"19294",
    "sg:province":"Mecklenburg-Vorpommern",
    "wof:name":"Eiscafe Cono Gelato",
    "wof:placetype":"venue"
},
  "geometry": {"coordinates":[11.423824,53.228882],"type":"Point"}
}