{
  "type": "Feature",
  "properties": {
    "iso:country":"DE",
    "sg:address":"Siefenfeldchen 141",
    "sg:city":"Bornheim",
    "sg:phone":"+49 2222/64041",
    "sg:postcode":"53332",
    "sg:province":"Nordrhein-Westfalen",
    "wof:name":"Dr. K. Heidenstecker-menke Notar",
    "wof:placetype":"venue"
},
  "geometry": {"coordinates":[7.0016059875,50.7562866211],"type":"Point"}
}