{
  "type": "Feature",
  "properties": {
    "iso:country":"DE",
    "sg:address":"Am Waisenhausplatz 12",
    "sg:city":"Pforzheim",
    "sg:phone":"+49 7231/359348",
    "sg:postcode":"75172",
    "sg:province":"Baden-W\u00fcrttemberg",
    "wof:name":"Pilsstube Dudelsack",
    "wof:placetype":"venue"
},
  "geometry": {"coordinates":[8.7006254196,48.8901863098],"type":"Point"}
}