{
  "type": "Feature",
  "properties": {
    "iso:country":"DE",
    "sg:address":"Limbacher Str. 105",
    "sg:city":"Chemnitz",
    "sg:phone":"+49 371/369090",
    "sg:postcode":"09116",
    "sg:province":"Sachsen",
    "wof:name":"West-apotheke",
    "wof:placetype":"venue"
},
  "geometry": {"coordinates":[12.890101,50.835503],"type":"Point"}
}