{
  "type": "Feature",
  "properties": {
    "iso:country":"DE",
    "sg:address":"Sternstr. 5",
    "sg:city":"Wuppertal",
    "sg:phone":"+49 202/554477",
    "sg:postcode":"42275",
    "sg:province":"Nordrhein-Westfalen",
    "wof:name":"Druckerei Kriegeskorte E. Kfm. Inh. Bernd Mende",
    "wof:placetype":"venue"
},
  "geometry": {"coordinates":[7.208625,51.276482],"type":"Point"}
}