{
  "type": "Feature",
  "properties": {
    "iso:country":"DE",
    "sg:address":"T\u00f6pferstr. 10",
    "sg:city":"Grevenbroich",
    "sg:phone":"+49 2181/1568",
    "sg:postcode":"41515",
    "sg:province":"Nordrhein-Westfalen",
    "wof:name":"Werner Albers Steuerberater",
    "wof:placetype":"venue"
},
  "geometry": {"coordinates":[6.5840501785,51.0953063965],"type":"Point"}
}