{
  "type": "Feature",
  "properties": {
    "iso:country":"DE",
    "sg:address":"Schmiedgasse 8",
    "sg:city":"Gruibingen",
    "sg:phone":"+49 7335/5885",
    "sg:postcode":"73344",
    "sg:province":"Baden-W\u00fcrttemberg",
    "wof:name":"Werner Moll",
    "wof:placetype":"venue"
},
  "geometry": {"coordinates":[9.643339,48.594528],"type":"Point"}
}