{
  "type": "Feature",
  "properties": {
    "iso:country":"DE",
    "sg:address":"Obere Stadt 63",
    "sg:city":"Weilheim",
    "sg:phone":"+49 881/2526",
    "sg:postcode":"82362",
    "sg:province":"Bayern",
    "wof:name":"Rainer Schweiger",
    "wof:placetype":"venue"
},
  "geometry": {"coordinates":[11.148858,47.838303],"type":"Point"}
}