{
  "type": "Feature",
  "properties": {
    "iso:country":"DE",
    "sg:address":"Mardorfer Str. 28",
    "sg:city":"Neustadt",
    "sg:postcode":"31535",
    "sg:province":"Niedersachsen",
    "wof:name":"Shop F\u00fcr Moderne Mundpflegeartikel",
    "wof:placetype":"venue"
},
  "geometry": {"coordinates":[9.294916,52.491695],"type":"Point"}
}