{
  "type": "Feature",
  "properties": {
    "iso:country":"DE",
    "sg:address":"Holl\u00e4nderstr. 9a",
    "sg:city":"Wei\u00dfenfels",
    "sg:phone":"+49 3443/306014",
    "sg:postcode":"06667",
    "sg:province":"Sachsen-Anhalt",
    "wof:name":"Dr. Med. Klaus Heunisch",
    "wof:placetype":"venue"
},
  "geometry": {"coordinates":[11.96946,51.19656],"type":"Point"}
}