{
  "type": "Feature",
  "properties": {
    "iso:country":"DE",
    "sg:address":"Doberaner Str. 50",
    "sg:city":"Rostock",
    "sg:phone":"+49 381/2006770",
    "sg:postcode":"18057",
    "sg:province":"Mecklenburg-Vorpommern",
    "wof:name":"Norbert P\u00e4hlke",
    "wof:placetype":"venue"
},
  "geometry": {"coordinates":[12.113224,54.091503],"type":"Point"}
}