{
  "type": "Feature",
  "properties": {
    "iso:country":"DE",
    "sg:address":"B\u00f6nnigser Str. 1",
    "sg:city":"Wennigsen",
    "sg:phone":"+49 5103/9400",
    "sg:postcode":"30974",
    "sg:province":"Niedersachsen",
    "wof:name":"M\u00f6llerburg",
    "wof:placetype":"venue"
},
  "geometry": {"coordinates":[9.5742721558,52.2828483582],"type":"Point"}
}