{
  "type": "Feature",
  "properties": {
    "iso:country":"DE",
    "sg:address":"Friedrich-Wolf-Str. 48",
    "sg:city":"Lehnitz",
    "sg:postcode":"16565",
    "wof:name":"Evangelische Br\u00fcder-unit\u00e4t",
    "wof:placetype":"venue"
},
  "geometry": {"coordinates":[13.2617397308,52.7417488098],"type":"Point"}
}