{
  "type": "Feature",
  "properties": {
    "iso:country":"DE",
    "sg:address":"Dellbr\u00fccker Str. 264",
    "sg:city":"Bergisch Gladbach",
    "sg:phone":"+49 2202/58161",
    "sg:postcode":"51469",
    "sg:province":"Nordrhein-Westfalen",
    "wof:name":"Hans Eicker",
    "wof:placetype":"venue"
},
  "geometry": {"coordinates":[7.0991902351,50.9979515076],"type":"Point"}
}