{
  "type": "Feature",
  "properties": {
    "iso:country":"DE",
    "sg:address":"Siegfriedstr. 106",
    "sg:city":"Heppenheim",
    "sg:phone":"+49 6252/2529",
    "sg:postcode":"64646",
    "sg:province":"Hessen",
    "wof:name":"Hermann Josef Gies Weinanbau",
    "wof:placetype":"venue"
},
  "geometry": {"coordinates":[8.6507101059,49.6426467896],"type":"Point"}
}