{
  "type": "Feature",
  "properties": {
    "iso:country":"DE",
    "sg:address":"Murrhardter Str. 13",
    "sg:city":"Alth\u00fctte",
    "sg:phone":"+49 7192/3627",
    "sg:postcode":"71566",
    "sg:province":"Baden-W\u00fcrttemberg",
    "wof:name":"Bernd Hanel",
    "wof:placetype":"venue"
},
  "geometry": {"coordinates":[9.5561733246,48.9448204041],"type":"Point"}
}