{
  "type": "Feature",
  "properties": {
    "iso:country":"DE",
    "sg:address":"Hinter der Oberpfarre 3",
    "sg:city":"Wegeleben",
    "sg:phone":"+49 39423/6277",
    "sg:postcode":"38828",
    "sg:province":"Sachsen-Anhalt",
    "wof:name":"R. Kauschus Masseur",
    "wof:placetype":"venue"
},
  "geometry": {"coordinates":[11.172519,51.884876],"type":"Point"}
}