{
  "type": "Feature",
  "properties": {
    "iso:country":"DE",
    "sg:address":"Celler Heerstr. 170",
    "sg:city":"Braunschweig",
    "sg:phone":"+49 531/571023",
    "sg:postcode":"38114",
    "sg:province":"Niedersachsen",
    "wof:name":"Armgart-ingenieurbauges. Mbh",
    "wof:placetype":"venue"
},
  "geometry": {"coordinates":[10.5031814575,52.2832603455],"type":"Point"}
}