{
  "type": "Feature",
  "properties": {
    "iso:country":"DE",
    "sg:address":"Im Strenge 6",
    "sg:city":"Ritterhude",
    "sg:phone":"+49 421/637615",
    "sg:postcode":"27721",
    "sg:province":"Niedersachsen",
    "wof:name":"Stendorfer Maschinenbau Gmbh",
    "wof:placetype":"venue"
},
  "geometry": {"coordinates":[8.703253,53.205505],"type":"Point"}
}