{
  "type": "Feature",
  "properties": {
    "iso:country":"DE",
    "sg:address":"Kaiserstr. 39",
    "sg:city":"Graben-Neudorf",
    "sg:phone":"+49 7255/5688",
    "sg:postcode":"76676",
    "sg:province":"Baden-W\u00fcrttemberg",
    "wof:name":"Walter Wenz",
    "wof:placetype":"venue"
},
  "geometry": {"coordinates":[8.478571,49.157001],"type":"Point"}
}