{
  "type": "Feature",
  "properties": {
    "iso:country":"DE",
    "sg:address":"Vom-Rath-Str. 24",
    "sg:city":"Duisburg",
    "sg:phone":"+49 203/29065",
    "sg:postcode":"47051",
    "sg:province":"Nordrhein-Westfalen",
    "wof:name":"Verm\u00f6gensanlagen Manfred Trojahn Gmbh",
    "wof:placetype":"venue"
},
  "geometry": {"coordinates":[6.767188,51.432007],"type":"Point"}
}