{
  "type": "Feature",
  "properties": {
    "iso:country":"DE",
    "sg:address":"Hasselsstr. 49",
    "sg:city":"D\u00fcsseldorf",
    "sg:phone":"+49 211/998025",
    "sg:postcode":"40599",
    "sg:province":"Nordrhein-Westfalen",
    "wof:name":"Herbert Windsheimer Putz-stuck-akustik Gmbh",
    "wof:placetype":"venue"
},
  "geometry": {"coordinates":[6.872636795,51.1739273071],"type":"Point"}
}