{
  "type": "Feature",
  "properties": {
    "iso:country":"DE",
    "sg:address":"Zschopauer Str. 192",
    "sg:city":"Chemnitz",
    "sg:phone":"+49 371/5308436",
    "sg:postcode":"09126",
    "sg:province":"Sachsen",
    "wof:name":"Arndt M\u00fcller Laden- Und Innenausbau Gmbh",
    "wof:placetype":"venue"
},
  "geometry": {"coordinates":[12.947231,50.817402],"type":"Point"}
}