{
  "type": "Feature",
  "properties": {
    "iso:country":"DE",
    "sg:address":"Hohe Str. 105",
    "sg:city":"Kleve",
    "sg:phone":"+49 2821/3355",
    "sg:postcode":"47533",
    "sg:province":"Nordrhein-Westfalen",
    "wof:name":"Kath. Pfarramt St. Willibord",
    "wof:placetype":"venue"
},
  "geometry": {"coordinates":[6.1271481514,51.8118858337],"type":"Point"}
}