{
  "type": "Feature",
  "properties": {
    "iso:country":"DE",
    "sg:address":"Podbielskistr. 2 a",
    "sg:city":"Bad Nenndorf",
    "sg:phone":"+49 5723/2644",
    "sg:postcode":"31542",
    "sg:province":"Niedersachsen",
    "wof:name":"Horst-dieter Bremer",
    "wof:placetype":"venue"
},
  "geometry": {"coordinates":[9.3665437698,52.3315162659],"type":"Point"}
}