{
  "type": "Feature",
  "properties": {
    "iso:country":"DE",
    "sg:address":"Marktplatz 7 c",
    "sg:city":"Neufahrn",
    "sg:phone":"+49 8165/909595",
    "sg:postcode":"85375",
    "sg:province":"Bayern",
    "wof:name":"Caramed Gmbh",
    "wof:placetype":"venue"
},
  "geometry": {"coordinates":[11.660335,48.316788],"type":"Point"}
}