{
  "type": "Feature",
  "properties": {
    "iso:country":"DE",
    "sg:address":"Unter den Tannen 4",
    "sg:city":"Eime",
    "sg:phone":"+49 5182/7877",
    "sg:postcode":"31036",
    "sg:province":"Niedersachsen",
    "wof:name":"B. Gerlach",
    "wof:placetype":"venue"
},
  "geometry": {"coordinates":[9.7146348953,52.0687866211],"type":"Point"}
}