{
  "type": "Feature",
  "properties": {
    "iso:country":"DE",
    "sg:address":"Paulstr. 20",
    "sg:city":"K\u00f6ln",
    "sg:phone":"+49 221/324863",
    "sg:postcode":"50676",
    "sg:province":"Nordrhein-Westfalen",
    "wof:name":"Dieter C\u00f6llen Gmbh",
    "wof:placetype":"venue"
},
  "geometry": {"coordinates":[6.954071,50.927284],"type":"Point"}
}