{
  "type": "Feature",
  "properties": {
    "iso:country":"DE",
    "sg:address":"Johann-Gerhard-Oncken-Str. 7",
    "sg:city":"Elstal",
    "sg:postcode":"14627",
    "wof:name":"Servicedienste Elstal Gmbh",
    "wof:placetype":"venue"
},
  "geometry": {"coordinates":[12.981481,52.527168],"type":"Point"}
}