{
  "type": "Feature",
  "properties": {
    "iso:country":"DE",
    "sg:address":"Jedelhauserstr. 19",
    "sg:city":"Augsburg",
    "sg:phone":"+49 821/406483",
    "sg:postcode":"86156",
    "sg:province":"Bayern",
    "wof:name":"V. Lang",
    "wof:placetype":"venue"
},
  "geometry": {"coordinates":[10.8668527603,48.3829269409],"type":"Point"}
}