{
  "type": "Feature",
  "properties": {
    "iso:country":"DE",
    "sg:address":"Markersdorfer Str. 40",
    "sg:city":"Chemnitz",
    "sg:phone":"+49 371/2801624",
    "sg:postcode":"09123",
    "sg:province":"Sachsen",
    "wof:name":"Kniewegst\u00fcbl",
    "wof:placetype":"venue"
},
  "geometry": {"coordinates":[12.9036941528,50.7935447693],"type":"Point"}
}