{
  "type": "Feature",
  "properties": {
    "iso:country":"DE",
    "sg:address":"H\u00f6rn 10",
    "sg:city":"Leezen",
    "sg:phone":"+49 4552/1831",
    "sg:postcode":"23816",
    "sg:province":"Schleswig-Holstein",
    "wof:name":"Dirk Hummel Steuerberater",
    "wof:placetype":"venue"
},
  "geometry": {"coordinates":[10.2481718063,53.8715896606],"type":"Point"}
}