{
  "type": "Feature",
  "properties": {
    "iso:country":"DE",
    "sg:address":"Peigertinger Str. 9",
    "sg:city":"F\u00fcrstenstein",
    "sg:phone":"+49 8504/9100",
    "sg:postcode":"94538",
    "sg:province":"Bayern",
    "wof:name":"Dreiburgen-moebel Manfred Krenn",
    "wof:placetype":"venue"
},
  "geometry": {"coordinates":[13.3272809982,48.7164535522],"type":"Point"}
}