{
  "type": "Feature",
  "properties": {
    "iso:country":"DE",
    "sg:address":"Dorfstr. 107",
    "sg:city":"Eppendorf",
    "sg:phone":"+49 37293/70773",
    "sg:postcode":"09575",
    "sg:province":"Sachsen",
    "wof:name":"Armin Hahn",
    "wof:placetype":"venue"
},
  "geometry": {"coordinates":[13.25056,50.808971],"type":"Point"}
}