{
  "type": "Feature",
  "properties": {
    "iso:country":"DE",
    "sg:address":"Kreuzplatz 3",
    "sg:city":"Gie\u00dfen",
    "sg:phone":"+49 641/31095",
    "sg:postcode":"35390",
    "sg:province":"Hessen",
    "wof:name":"Hermann Mettenheimer Gmbh & Co. Kg",
    "wof:placetype":"venue"
},
  "geometry": {"coordinates":[8.6744041443,50.5851821899],"type":"Point"}
}