{
  "type": "Feature",
  "properties": {
    "iso:country":"DE",
    "sg:address":"Hauptstr. 50",
    "sg:city":"Heubach",
    "sg:phone":"+49 7173/4574",
    "sg:postcode":"73540",
    "sg:province":"Baden-W\u00fcrttemberg",
    "wof:name":"Stefan Kn\u00f6pfle",
    "wof:placetype":"venue"
},
  "geometry": {"coordinates":[9.9350919724,48.7881011963],"type":"Point"}
}