{
  "type": "Feature",
  "properties": {
    "iso:country":"DE",
    "sg:address":"Hausbergweg 37",
    "sg:city":"Radebeul",
    "sg:phone":"+49 351/8362330",
    "sg:postcode":"01445",
    "sg:province":"Sachsen",
    "wof:name":"Wolfgang Beger",
    "wof:placetype":"venue"
},
  "geometry": {"coordinates":[13.6034736633,51.1255264282],"type":"Point"}
}