{
  "type": "Feature",
  "properties": {
    "iso:country":"DE",
    "sg:address":"Chemnitzer Str. 1",
    "sg:city":"Lugau",
    "sg:phone":"+49 37295/50510",
    "sg:postcode":"09385",
    "sg:province":"Sachsen",
    "wof:name":"Obi Bau- Und Heimwerkermarkt",
    "wof:placetype":"venue"
},
  "geometry": {"coordinates":[12.7466936111,50.7610778809],"type":"Point"}
}