{
  "type": "Feature",
  "properties": {
    "iso:country":"DE",
    "sg:address":"Aachener Str. 570",
    "sg:city":"Frechen",
    "sg:phone":"+49 2234/966140",
    "sg:postcode":"50226",
    "sg:province":"Nordrhein-Westfalen",
    "wof:name":"Degens & Rummler Gmbh",
    "wof:placetype":"venue"
},
  "geometry": {"coordinates":[6.7750639915,50.9367904663],"type":"Point"}
}