{
  "type": "Feature",
  "properties": {
    "iso:country":"DE",
    "sg:address":"Trayhstr. 19",
    "sg:city":"Bodelshausen",
    "sg:phone":"+49 7471/97364",
    "sg:postcode":"72411",
    "sg:province":"Baden-W\u00fcrttemberg",
    "wof:name":"Zur Rose",
    "wof:placetype":"venue"
},
  "geometry": {"coordinates":[8.9734611511,48.3947715759],"type":"Point"}
}