{
  "type": "Feature",
  "properties": {
    "iso:country":"DE",
    "sg:address":"Alte Schulstr. 11",
    "sg:city":"M\u00f6mlingen",
    "sg:phone":"+49 6022/3331",
    "sg:postcode":"63853",
    "sg:province":"Bayern",
    "wof:name":"Josef Hohm",
    "wof:placetype":"venue"
},
  "geometry": {"coordinates":[9.084851,49.859959],"type":"Point"}
}