{
  "type": "Feature",
  "properties": {
    "iso:country":"DE",
    "sg:address":"Lingnerallee 3",
    "sg:city":"Dresden",
    "sg:postcode":"01069",
    "sg:province":"Sachsen",
    "wof:name":"Verkehrswacht Dresden E.v.",
    "wof:placetype":"venue"
},
  "geometry": {"coordinates":[13.746568,51.046581],"type":"Point"}
}