{
  "type": "Feature",
  "properties": {
    "iso:country":"DE",
    "sg:address":"Repelener Str. 61",
    "sg:city":"Neukirchen-Vluyn",
    "sg:phone":"+49 2845/32377",
    "sg:postcode":"47506",
    "sg:province":"Nordrhein-Westfalen",
    "wof:name":"P. Von Holtum",
    "wof:placetype":"venue"
},
  "geometry": {"coordinates":[6.596371,51.466545],"type":"Point"}
}