{
  "type": "Feature",
  "properties": {
    "iso:country":"DE",
    "sg:address":"Schleichersrain 7",
    "sg:city":"W\u00fcstenrot",
    "sg:phone":"+49 7130/3689",
    "sg:postcode":"71543",
    "sg:province":"Baden-W\u00fcrttemberg",
    "wof:name":"Andrea Meister",
    "wof:placetype":"venue"
},
  "geometry": {"coordinates":[9.4344682693,49.0822792053],"type":"Point"}
}