{
  "type": "Feature",
  "properties": {
    "iso:country":"DE",
    "sg:address":"Aignhof",
    "sg:city":"Eschlkam",
    "sg:phone":"+49 9947/1741",
    "sg:postcode":"93458",
    "sg:province":"Bayern",
    "wof:name":"Anton Pongratz",
    "wof:placetype":"venue"
},
  "geometry": {"coordinates":[12.938216,49.260929],"type":"Point"}
}