{
  "type": "Feature",
  "properties": {
    "iso:country":"DE",
    "sg:address":"St. Benedictstr. 8",
    "sg:city":"Hamburg",
    "sg:postcode":"20149",
    "sg:province":"Hamburg",
    "wof:name":"A@l Asset @ Logistic Ag",
    "wof:placetype":"venue"
},
  "geometry": {"coordinates":[9.9905176163,53.5821380615],"type":"Point"}
}