{
  "type": "Feature",
  "properties": {
    "iso:country":"DE",
    "sg:address":"Hermann-Balk-Str. 109 a",
    "sg:city":"Hamburg",
    "sg:postcode":"22147",
    "sg:province":"Hamburg",
    "wof:name":"B Und W Reinigungen Gmbh",
    "wof:placetype":"venue"
},
  "geometry": {"coordinates":[10.140299,53.623989],"type":"Point"}
}