{
  "type": "Feature",
  "properties": {
    "iso:country":"DE",
    "sg:address":"Oberohe",
    "sg:city":"Fa\u00dfberg",
    "sg:phone":"+49 5827/356",
    "sg:postcode":"29328",
    "sg:province":"Niedersachsen",
    "wof:name":"Georg Von Der Ohe",
    "wof:placetype":"venue"
},
  "geometry": {"coordinates":[10.2258844376,52.8699378967],"type":"Point"}
}