{
  "type": "Feature",
  "properties": {
    "iso:country":"DE",
    "sg:address":"Koopmannstra\u00dfe 59 A",
    "sg:city":"Duisburg",
    "sg:phone":"+49 203/548691",
    "sg:postcode":"47138",
    "sg:province":"Nordrhein-Westfalen",
    "wof:name":"Ifac Colloidtechnologie F\u00fcr Kosmetik Und Pharmazie",
    "wof:placetype":"venue"
},
  "geometry": {"coordinates":[6.800603,51.46825],"type":"Point"}
}