{
  "type": "Feature",
  "properties": {
    "iso:country":"DE",
    "sg:address":"Klosterrain 2",
    "sg:city":"Bessenbach",
    "sg:phone":"+49 6095/567",
    "sg:postcode":"63856",
    "sg:province":"Bayern",
    "wof:name":"Edgar Kunkel",
    "wof:placetype":"venue"
},
  "geometry": {"coordinates":[9.253621,49.95245],"type":"Point"}
}