{
  "type": "Feature",
  "properties": {
    "iso:country":"DE",
    "sg:address":"Falkenberger Landstr. 71",
    "sg:city":"Lilienthal",
    "sg:phone":"+49 4298/3252",
    "sg:postcode":"28865",
    "sg:province":"Niedersachsen",
    "wof:name":"Volksbank Eg",
    "wof:placetype":"venue"
},
  "geometry": {"coordinates":[8.92843,53.154232],"type":"Point"}
}