{
  "type": "Feature",
  "properties": {
    "iso:country":"DE",
    "sg:address":"Pfarrgasse 4",
    "sg:city":"Heidelberg",
    "sg:phone":"+49 6221/475186",
    "sg:postcode":"69121",
    "sg:province":"Baden-W\u00fcrttemberg",
    "wof:name":"Rondo Classico Bernhard Schuh",
    "wof:placetype":"venue"
},
  "geometry": {"coordinates":[8.6881132126,49.4264297485],"type":"Point"}
}