{
  "type": "Feature",
  "properties": {
    "iso:country":"DE",
    "sg:address":"Stauffenbergstr. 5",
    "sg:city":"Trier",
    "sg:phone":"+49 651/32431",
    "sg:postcode":"54295",
    "sg:province":"Rheinland-Pfalz",
    "wof:name":"Guido Becker Steuerberater",
    "wof:placetype":"venue"
},
  "geometry": {"coordinates":[6.6458678246,49.7425308228],"type":"Point"}
}