{
  "type": "Feature",
  "properties": {
    "iso:country":"DE",
    "sg:address":"Ferd.-Aufschl\u00e4gerstr. 42",
    "sg:city":"Simbach",
    "sg:phone":"+49 8571/5162",
    "sg:postcode":"84359",
    "sg:province":"Bayern",
    "wof:name":"Versicherungsagentur Wittmann",
    "wof:placetype":"venue"
},
  "geometry": {"coordinates":[13.027680397,48.2673797607],"type":"Point"}
}