{
  "type": "Feature",
  "properties": {
    "iso:country":"DE",
    "sg:address":"Raiffeisenstr. 12",
    "sg:city":"Rodgau",
    "sg:phone":"+49 6106/826300",
    "sg:postcode":"63110",
    "sg:province":"Hessen",
    "wof:name":"Funk Aluvertriebsgesellschaft Mbh",
    "wof:placetype":"venue"
},
  "geometry": {"coordinates":[8.884027,50.014648],"type":"Point"}
}