{
  "type": "Feature",
  "properties": {
    "iso:country":"DE",
    "sg:address":"Marktstr. 53",
    "sg:city":"Wanfried",
    "sg:phone":"+49 5655/474",
    "sg:postcode":"37281",
    "sg:province":"Hessen",
    "wof:name":"Herbert Dierks",
    "wof:placetype":"venue"
},
  "geometry": {"coordinates":[10.1720695496,51.1805305481],"type":"Point"}
}