{
  "type": "Feature",
  "properties": {
    "iso:country":"DE",
    "sg:address":"Flurstr. 55",
    "sg:city":"Schwandorf",
    "sg:phone":"+49 9431/5827",
    "sg:postcode":"92421",
    "sg:province":"Bayern",
    "wof:name":"Anton Schiessl",
    "wof:placetype":"venue"
},
  "geometry": {"coordinates":[12.1161241531,49.3133201599],"type":"Point"}
}