{
  "type": "Feature",
  "properties": {
    "iso:country":"DE",
    "sg:address":"M\u00fchlentor 13",
    "sg:city":"Borgentreich",
    "sg:phone":"+49 5643/1587",
    "sg:postcode":"34434",
    "sg:province":"Nordrhein-Westfalen",
    "wof:name":"Alfons Watermeier",
    "wof:placetype":"venue"
},
  "geometry": {"coordinates":[9.23781,51.566231],"type":"Point"}
}