{
  "type": "Feature",
  "properties": {
    "iso:country":"DE",
    "sg:address":"Heidenberg 12",
    "sg:city":"Apolda",
    "sg:phone":"+49 3644/542690",
    "sg:postcode":"99510",
    "sg:province":"Th\u00fcringen",
    "wof:name":"Schwarzer Gmbh",
    "wof:placetype":"venue"
},
  "geometry": {"coordinates":[11.5120439529,51.0261955261],"type":"Point"}
}