{
  "type": "Feature",
  "properties": {
    "iso:country":"DE",
    "sg:address":"Nieder-Rosbacher-Str. 11-13",
    "sg:city":"Rosbach",
    "sg:postcode":"61191",
    "sg:province":"Hessen",
    "wof:name":"Risk Consult Group Gmbh",
    "wof:placetype":"venue"
},
  "geometry": {"coordinates":[8.690797,50.301788],"type":"Point"}
}