{
  "type": "Feature",
  "properties": {
    "iso:country":"DE",
    "sg:address":"Moritzstr. 11",
    "sg:city":"Wiesbaden",
    "sg:phone":"+49 611/377436",
    "sg:postcode":"65185",
    "sg:province":"Hessen",
    "wof:name":"Annes Natur-gourmet",
    "wof:placetype":"venue"
},
  "geometry": {"coordinates":[8.2382774353,50.0762786865],"type":"Point"}
}