{
  "type": "Feature",
  "properties": {
    "iso:country":"DE",
    "sg:address":"Menzelstr. 29",
    "sg:city":"Stuttgart",
    "sg:phone":"+49 711/8596470",
    "sg:postcode":"70192",
    "sg:province":"Baden-W\u00fcrttemberg",
    "wof:name":"Architektur Eck Knierim Kr\u00fcger Selz Partnerschaft",
    "wof:placetype":"venue"
},
  "geometry": {"coordinates":[9.1649780273,48.8004646301],"type":"Point"}
}