{
  "type": "Feature",
  "properties": {
    "iso:country":"DE",
    "sg:address":"Cosimastr.306",
    "sg:city":"M\u00fcnchen",
    "sg:phone":"+49 89/9920420",
    "sg:postcode":"81927",
    "sg:province":"Bayern",
    "wof:name":"Vba Veranstaltungs Beratung Amthor Gmbh",
    "wof:placetype":"venue"
},
  "geometry": {"coordinates":[11.63671,48.17355],"type":"Point"}
}