{
  "type": "Feature",
  "properties": {
    "iso:country":"DE",
    "sg:address":"Hallesche Str. 6",
    "sg:city":"Lutherstadt Eisleben",
    "sg:postcode":"06295",
    "sg:province":"Sachsen-Anhalt",
    "wof:name":"Eisleben Information",
    "wof:placetype":"venue"
},
  "geometry": {"coordinates":[11.5505962372,51.5267524719],"type":"Point"}
}