{
  "type": "Feature",
  "properties": {
    "iso:country":"DE",
    "sg:address":"Kleberstr 33a",
    "sg:city":"Bamberg",
    "sg:phone":"+49 951/2087297",
    "sg:postcode":"96047",
    "sg:province":"Bayern",
    "wof:name":"Artmedia Werbeagentur",
    "wof:placetype":"venue"
},
  "geometry": {"coordinates":[10.887327,49.896267],"type":"Point"}
}