{
  "type": "Feature",
  "properties": {
    "iso:country":"DE",
    "sg:address":"Bachstr. 3",
    "sg:city":"Glei\u00dfenberg",
    "sg:phone":"+49 9975/90020",
    "sg:postcode":"93477",
    "sg:province":"Bayern",
    "wof:name":"B. Reitmeier",
    "wof:placetype":"venue"
},
  "geometry": {"coordinates":[12.7395000458,49.316028595],"type":"Point"}
}