{
  "type": "Feature",
  "properties": {
    "iso:country":"DE",
    "sg:address":"Hospitalgasse 14",
    "sg:city":"Friedberg",
    "sg:phone":"+49 6031/9744",
    "sg:postcode":"61169",
    "sg:province":"Hessen",
    "wof:name":"Hans Rolf Binding",
    "wof:placetype":"venue"
},
  "geometry": {"coordinates":[8.752243042,50.3361778259],"type":"Point"}
}