{
  "type": "Feature",
  "properties": {
    "iso:country":"DE",
    "sg:address":"Babenhauser Str. 265",
    "sg:city":"Bielefeld",
    "sg:phone":"+49 521/101444",
    "sg:postcode":"33619",
    "sg:province":"Nordrhein-Westfalen",
    "wof:name":"Siekerkotte",
    "wof:placetype":"venue"
},
  "geometry": {"coordinates":[8.4674186707,52.052406311],"type":"Point"}
}