{
  "type": "Feature",
  "properties": {
    "iso:country":"DE",
    "sg:address":"Rudolf Haym Stra\u00dfe 28",
    "sg:city":"Halle",
    "sg:phone":"+49 345/6782812",
    "sg:postcode":"06110",
    "sg:province":"Sachsen-Anhalt",
    "wof:name":"Starpage Infobroker",
    "wof:placetype":"venue"
},
  "geometry": {"coordinates":[11.975716,51.47263],"type":"Point"}
}