{
  "type": "Feature",
  "properties": {
    "iso:country":"DE",
    "sg:address":"Hornstr. 147",
    "sg:city":"Bergisch Gladbach",
    "sg:phone":"+49 2202/52916",
    "sg:postcode":"51465",
    "sg:province":"Nordrhein-Westfalen",
    "wof:name":"Gasthaus Zum Horn",
    "wof:placetype":"venue"
},
  "geometry": {"coordinates":[7.126871109,50.9979515076],"type":"Point"}
}