{
  "type": "Feature",
  "properties": {
    "iso:country":"DE",
    "sg:address":"Dienersberg",
    "sg:city":"Oberstdorf",
    "sg:phone":"+49 8322/1579",
    "sg:postcode":"87561",
    "sg:province":"Bayern",
    "wof:name":"K. Vogler",
    "wof:placetype":"venue"
},
  "geometry": {"coordinates":[10.2892,47.391953],"type":"Point"}
}