{
  "type": "Feature",
  "properties": {
    "iso:country":"DE",
    "sg:address":"Wiesentalstr. 13",
    "sg:city":"Freiburg",
    "sg:phone":"+49 761/445050",
    "sg:postcode":"79115",
    "sg:province":"Baden-W\u00fcrttemberg",
    "wof:name":"Entenest",
    "wof:placetype":"venue"
},
  "geometry": {"coordinates":[7.8223509789,47.9792747498],"type":"Point"}
}