{
  "type": "Feature",
  "properties": {
    "iso:country":"DE",
    "sg:address":"Karl-L\u00f6we-Str. 1",
    "sg:city":"Frechen",
    "sg:phone":"+49 2234/962128",
    "sg:postcode":"50226",
    "sg:province":"Nordrhein-Westfalen",
    "wof:name":"Restaurant Haus Loewe Inh. M. Langen",
    "wof:placetype":"venue"
},
  "geometry": {"coordinates":[6.7801861763,50.9309921265],"type":"Point"}
}