{
  "type": "Feature",
  "properties": {
    "iso:country":"DE",
    "sg:address":"Finkengrund 11",
    "sg:city":"Leipzig",
    "sg:postcode":"04158",
    "sg:province":"Sachsen",
    "wof:name":"Annemirl Riehl Grafikerin",
    "wof:placetype":"venue"
},
  "geometry": {"coordinates":[12.362049,51.383572],"type":"Point"}
}