{
  "type": "Feature",
  "properties": {
    "iso:country":"DE",
    "sg:address":"Kettenberg 3",
    "sg:city":"L\u00fcdenscheid",
    "sg:phone":"+49 2351/570146",
    "sg:postcode":"58507",
    "sg:province":"Nordrhein-Westfalen",
    "wof:name":"Fritzsch Medizintechnik Gmbh",
    "wof:placetype":"venue"
},
  "geometry": {"coordinates":[7.6151862144,51.2428741455],"type":"Point"}
}