{
  "type": "Feature",
  "properties": {
    "iso:country":"DE",
    "sg:address":"M\u00fcnsterstr. 11",
    "sg:city":"Bad Iburg",
    "sg:phone":"+49 5403/73300",
    "sg:postcode":"49186",
    "sg:province":"Niedersachsen",
    "wof:name":"Heinz Marquard Ingenieur",
    "wof:placetype":"venue"
},
  "geometry": {"coordinates":[8.0423803329,52.1552505493],"type":"Point"}
}