{
  "type": "Feature",
  "properties": {
    "iso:country":"DE",
    "sg:address":"Am Carolapark 6",
    "sg:city":"Glauchau",
    "sg:postcode":"08371",
    "sg:province":"Sachsen",
    "wof:name":"B. Oesterreich",
    "wof:placetype":"venue"
},
  "geometry": {"coordinates":[12.55279,50.820766],"type":"Point"}
}