{
  "type": "Feature",
  "properties": {
    "iso:country":"DE",
    "sg:address":"84048",
    "sg:city":"Mainburg",
    "sg:phone":"+49 8751/865945",
    "sg:postcode":"84048",
    "sg:province":"Bayern",
    "wof:name":"Hallenbad",
    "wof:placetype":"venue"
},
  "geometry": {"coordinates":[11.7600002289,48.6461410522],"type":"Point"}
}