{
  "type": "Feature",
  "properties": {
    "iso:country":"DE",
    "sg:address":"Schmittmannstr. 30",
    "sg:city":"Dernau",
    "sg:phone":"+49 2643/2612",
    "sg:postcode":"53507",
    "sg:province":"Rheinland-Pfalz",
    "wof:name":"Pension Kreuzberg",
    "wof:placetype":"venue"
},
  "geometry": {"coordinates":[7.0453271866,50.5343704224],"type":"Point"}
}