{
  "type": "Feature",
  "properties": {
    "iso:country":"DE",
    "sg:address":"Markscheffelshof 8",
    "sg:city":"Eisenach",
    "sg:phone":"+49 3691/785296",
    "sg:postcode":"99817",
    "sg:province":"Th\u00fcringen",
    "wof:name":"World-of-games Inh. Henry Schneider E. K.",
    "wof:placetype":"venue"
},
  "geometry": {"coordinates":[10.32213974,50.9756355286],"type":"Point"}
}