{
  "type": "Feature",
  "properties": {
    "iso:country":"DE",
    "sg:address":"B\u00fcrener Str. 45",
    "sg:city":"Bad W\u00fcnnenberg",
    "sg:phone":"+49 2957/242",
    "sg:postcode":"33181",
    "sg:province":"Nordrhein-Westfalen",
    "wof:name":"Heinrich Becker",
    "wof:placetype":"venue"
},
  "geometry": {"coordinates":[8.694175,51.51786],"type":"Point"}
}