{
  "type": "Feature",
  "properties": {
    "iso:country":"DE",
    "sg:address":"Rosengarten 66",
    "sg:city":"Bad Bevensen",
    "sg:phone":"+49 5821/2510",
    "sg:postcode":"29549",
    "sg:province":"Niedersachsen",
    "wof:name":"Redaktion Freies Christentum Versandstelle Freies",
    "wof:placetype":"venue"
},
  "geometry": {"coordinates":[10.5728883743,53.0847549438],"type":"Point"}
}