{
  "type": "Feature",
  "properties": {
    "iso:country":"DE",
    "sg:address":"Boxdorfer Str. 8",
    "sg:city":"Fuerth",
    "sg:phone":"+49 911",
    "sg:postcode":"90765",
    "sg:province":"Bayern",
    "wof:name":"Cpw Informationstechnik",
    "wof:placetype":"venue"
},
  "geometry": {"coordinates":[11.021616,49.50613],"type":"Point"}
}