{
  "type": "Feature",
  "properties": {
    "iso:country":"DE",
    "sg:address":"R\u00f6hn 13",
    "sg:city":"Horn-Bad Meinberg",
    "sg:phone":"+49 5234/9274",
    "sg:postcode":"32805",
    "sg:province":"Nordrhein-Westfalen",
    "wof:name":"Zur Waffeloma",
    "wof:placetype":"venue"
},
  "geometry": {"coordinates":[8.995603,51.887379],"type":"Point"}
}