{
  "type": "Feature",
  "properties": {
    "iso:country":"DE",
    "sg:address":"Vangionenstr. 9",
    "sg:city":"Worms",
    "sg:phone":"+49 6241/84080",
    "sg:postcode":"67547",
    "sg:province":"Rheinland-Pfalz",
    "wof:name":"Kl Rohstoffverwertung Gmbh",
    "wof:placetype":"venue"
},
  "geometry": {"coordinates":[8.3747348785,49.6271324158],"type":"Point"}
}