{
  "type": "Feature",
  "properties": {
    "iso:country":"DE",
    "sg:address":"Bechhofer Str. 16",
    "sg:city":"Gro\u00dfenseebach",
    "sg:phone":"+49 9193/3551",
    "sg:postcode":"91091",
    "sg:province":"Bayern",
    "wof:name":"Raiffeisenbank H\u00f6chstadt Eg",
    "wof:placetype":"venue"
},
  "geometry": {"coordinates":[10.87459,49.631355],"type":"Point"}
}