{
  "type": "Feature",
  "properties": {
    "iso:country":"DE",
    "sg:address":"Gebeseer Str.",
    "sg:city":"Herbsleben",
    "sg:postcode":"99955",
    "sg:province":"Th\u00fcringen",
    "wof:name":"Elektro Drey\u00dfe",
    "wof:placetype":"venue"
},
  "geometry": {"coordinates":[10.84545,51.119625],"type":"Point"}
}