{
  "type": "Feature",
  "properties": {
    "iso:country":"DE",
    "sg:address":"Bauerngasse 79",
    "sg:city":"Schweinfurt",
    "sg:phone":"+49 9721/16886",
    "sg:postcode":"97421",
    "sg:province":"Bayern",
    "wof:name":"Ludwig Tully",
    "wof:placetype":"venue"
},
  "geometry": {"coordinates":[10.230604,50.046734],"type":"Point"}
}