{
  "type": "Feature",
  "properties": {
    "iso:country":"DE",
    "sg:address":"H\u00f6rbachstr. 4",
    "sg:city":"Hilchenbach",
    "sg:phone":"+49 2733/51888",
    "sg:postcode":"57271",
    "sg:province":"Nordrhein-Westfalen",
    "wof:name":"Klaus R. Und E. Reis",
    "wof:placetype":"venue"
},
  "geometry": {"coordinates":[8.0672702789,50.9771766663],"type":"Point"}
}