{
  "type": "Feature",
  "properties": {
    "iso:country":"DE",
    "sg:address":"B\u00fcrgermeister-Fuchs-Str. 63",
    "sg:city":"Mannheim",
    "sg:postcode":"68169",
    "sg:province":"Baden-W\u00fcrttemberg",
    "wof:name":"Mb 56 Immobilien Gmbh",
    "wof:placetype":"venue"
},
  "geometry": {"coordinates":[8.465927124,49.5028953552],"type":"Point"}
}