{
  "type": "Feature",
  "properties": {
    "iso:country":"DE",
    "sg:address":"Egelseer Str. 3a",
    "sg:city":"Schwandorf",
    "sg:phone":"+49 9431/51416",
    "sg:postcode":"92421",
    "sg:province":"Bayern",
    "wof:name":"O. Berzl Gmbh",
    "wof:placetype":"venue"
},
  "geometry": {"coordinates":[12.1056880951,49.3237609863],"type":"Point"}
}