{
  "type": "Feature",
  "properties": {
    "iso:country":"DE",
    "sg:address":"Wehrstr. 10",
    "sg:city":"Bad Oeynhausen",
    "sg:phone":"+49 5731/53050",
    "sg:postcode":"32549",
    "sg:province":"Nordrhein-Westfalen",
    "wof:name":"Georg Zopf",
    "wof:placetype":"venue"
},
  "geometry": {"coordinates":[8.7773160934,52.210193634],"type":"Point"}
}