{
  "type": "Feature",
  "properties": {
    "iso:country":"DE",
    "sg:address":"Erikastr. 60",
    "sg:city":"M\u00f6nchengladbach",
    "sg:phone":"+49 2161/633065",
    "sg:postcode":"41066",
    "sg:province":"Nordrhein-Westfalen",
    "wof:name":"Ursula Liefke",
    "wof:placetype":"venue"
},
  "geometry": {"coordinates":[6.458743,51.222488],"type":"Point"}
}