{
  "type": "Feature",
  "properties": {
    "iso:country":"DE",
    "sg:address":"Theisenort 27",
    "sg:city":"Staffelstein",
    "sg:phone":"+49 9573/6592",
    "sg:postcode":"96231",
    "sg:province":"Bayern",
    "wof:name":"Josef H\u00fcls",
    "wof:placetype":"venue"
},
  "geometry": {"coordinates":[11.06398,50.086102],"type":"Point"}
}