{
  "type": "Feature",
  "properties": {
    "iso:country":"DE",
    "sg:address":"K\u00f6lner Landstr. 441",
    "sg:city":"D\u00fcsseldorf",
    "sg:phone":"+49 211/757633",
    "sg:postcode":"40589",
    "sg:province":"Nordrhein-Westfalen",
    "wof:name":"Fischparadies",
    "wof:placetype":"venue"
},
  "geometry": {"coordinates":[6.8322401047,51.1758384705],"type":"Point"}
}