{
  "type": "Feature",
  "properties": {
    "iso:country":"DE",
    "sg:address":"Eichelkopfstr. 3",
    "sg:city":"Gr\u00fcndau",
    "sg:phone":"+49 6058/910447",
    "sg:postcode":"63584",
    "sg:province":"Hessen",
    "wof:name":"Lechleidner Gmbh",
    "wof:placetype":"venue"
},
  "geometry": {"coordinates":[9.1501111984,50.2365226746],"type":"Point"}
}