{
  "type": "Feature",
  "properties": {
    "iso:country":"DE",
    "sg:address":"Havelmatensteig 14 A",
    "sg:city":"Berlin",
    "sg:postcode":"14089",
    "sg:province":"Berlin",
    "wof:name":"Heinzelm\u00e4nner Bauausf\u00fchrungs- Gmbh",
    "wof:placetype":"venue"
},
  "geometry": {"coordinates":[13.17821,52.475025],"type":"Point"}
}