{
  "type": "Feature",
  "properties": {
    "iso:country":"DE",
    "sg:address":"Hauptstr. 36",
    "sg:city":"Appenweier",
    "sg:phone":"+49 7805/910628",
    "sg:postcode":"77767",
    "sg:province":"Baden-W\u00fcrttemberg",
    "wof:name":"Pfarrseppe-wirtsch\u00e4ftl",
    "wof:placetype":"venue"
},
  "geometry": {"coordinates":[7.9692320824,48.5621299744],"type":"Point"}
}