{
  "type": "Feature",
  "properties": {
    "iso:country":"DE",
    "sg:address":"Kirchplatz 3",
    "sg:city":"Forchheim",
    "sg:phone":"+49 9191/4511",
    "sg:postcode":"91301",
    "sg:province":"Bayern",
    "wof:name":"Restaurant Roter Ochs",
    "wof:placetype":"venue"
},
  "geometry": {"coordinates":[8.3078565598,48.9750022888],"type":"Point"}
}