{
  "type": "Feature",
  "properties": {
    "iso:country":"DE",
    "sg:address":"Hauptstr. 20",
    "sg:city":"Schwalmtal",
    "sg:phone":"+49 6638/8182",
    "sg:postcode":"36318",
    "sg:province":"Hessen",
    "wof:name":"Relo Brandschutz Gmbh",
    "wof:placetype":"venue"
},
  "geometry": {"coordinates":[9.3077640533,50.7006797791],"type":"Point"}
}