{
  "type": "Feature",
  "properties": {
    "iso:country":"DE",
    "sg:address":"Hauptst\u00e4tter Str. 99",
    "sg:city":"Stuttgart",
    "sg:phone":"+49 711/6071193",
    "sg:postcode":"70178",
    "sg:province":"Baden-W\u00fcrttemberg",
    "wof:name":"Europa Sachversicherung Ag",
    "wof:placetype":"venue"
},
  "geometry": {"coordinates":[9.1724271774,48.7681770325],"type":"Point"}
}