{
  "type": "Feature",
  "properties": {
    "iso:country":"DE",
    "sg:address":"Beilsteiner Str. 38",
    "sg:city":"Abstatt",
    "sg:phone":"+49 7062/6061",
    "sg:postcode":"74232",
    "sg:province":"Baden-W\u00fcrttemberg",
    "wof:name":"Chemotechnik Abstatt Gmbh",
    "wof:placetype":"venue"
},
  "geometry": {"coordinates":[9.291793,49.065239],"type":"Point"}
}