{
  "type": "Feature",
  "properties": {
    "iso:country":"DE",
    "sg:address":"Kornstr. 78 b",
    "sg:city":"Bremen",
    "sg:phone":"+49 421/500707",
    "sg:postcode":"28201",
    "sg:province":"Bremen",
    "wof:name":"Uwe Mester",
    "wof:placetype":"venue"
},
  "geometry": {"coordinates":[8.8004350662,53.0650024414],"type":"Point"}
}