{
  "type": "Feature",
  "properties": {
    "iso:country":"DE",
    "sg:address":"Werdauer Str. 1-3",
    "sg:city":"Dresden",
    "sg:phone":"+49 351",
    "sg:postcode":"01069",
    "sg:province":"Sachsen",
    "wof:name":"Fairnet Medienagentur",
    "wof:placetype":"venue"
},
  "geometry": {"coordinates":[13.716492,51.039612],"type":"Point"}
}