{
  "type": "Feature",
  "properties": {
    "iso:country":"DE",
    "sg:address":"Unterdorf 33",
    "sg:city":"M\u00fccke",
    "sg:phone":"+49 6400/8860",
    "sg:postcode":"35325",
    "sg:province":"Hessen",
    "wof:name":"Dr. Claus-j\u00f6rg Wiedbrauck Massagen",
    "wof:placetype":"venue"
},
  "geometry": {"coordinates":[9.0836772919,50.6214179993],"type":"Point"}
}