{
  "type": "Feature",
  "properties": {
    "iso:country":"DE",
    "sg:address":"Wilmersdorfer Str. 152",
    "sg:city":"Berlin",
    "sg:phone":"+49 30/3413535",
    "sg:postcode":"10585",
    "sg:province":"Berlin",
    "wof:name":"Klaus Leue",
    "wof:placetype":"venue"
},
  "geometry": {"coordinates":[13.305054,52.51453],"type":"Point"}
}