{
  "type": "Feature",
  "properties": {
    "iso:country":"DE",
    "sg:address":"Alter Postweg 67",
    "sg:city":"Sandhausen",
    "sg:phone":"+49 6224",
    "sg:postcode":"69207",
    "sg:province":"Baden-W\u00fcrttemberg",
    "wof:name":"Christian Jedinat Jonglier- & Zauberartikel",
    "wof:placetype":"venue"
},
  "geometry": {"coordinates":[8.648276329,49.3405914307],"type":"Point"}
}