{
  "type": "Feature",
  "properties": {
    "iso:country":"DE",
    "sg:address":"N\u00fcrtinger Str. 45",
    "sg:city":"Frickenhausen",
    "sg:phone":"+49 7022/46644",
    "sg:postcode":"72636",
    "sg:province":"Baden-W\u00fcrttemberg",
    "wof:name":"Musik-bistro Super M\u00e4x",
    "wof:placetype":"venue"
},
  "geometry": {"coordinates":[9.3531608582,48.5981216431],"type":"Point"}
}