{
  "type": "Feature",
  "properties": {
    "iso:country":"DE",
    "sg:address":"Thomas-Mann-Str. 33",
    "sg:city":"Salzgitter",
    "sg:phone":"+49 5341/264758",
    "sg:postcode":"38239",
    "sg:province":"Niedersachsen",
    "wof:name":"Clean-bau Immobilien- Und Bautr\u00e4gergesellschaft Mbh",
    "wof:placetype":"venue"
},
  "geometry": {"coordinates":[10.476308,52.186607],"type":"Point"}
}