{
  "type": "Feature",
  "properties": {
    "iso:country":"DE",
    "sg:address":"Reinekestr. 31",
    "sg:city":"K\u00f6ln",
    "sg:postcode":"51145",
    "sg:province":"Nordrhein-Westfalen",
    "wof:name":"Bundesverband Der Insulinempf\u00e4nger E. V.",
    "wof:placetype":"venue"
},
  "geometry": {"coordinates":[7.0777420998,50.8766288757],"type":"Point"}
}