{
  "type": "Feature",
  "properties": {
    "iso:country":"DE",
    "sg:address":"Strohgasse 8",
    "sg:city":"Hartenstein",
    "sg:phone":"+49 9152/1297",
    "sg:postcode":"91235",
    "sg:province":"Bayern",
    "wof:name":"Michael Benaburger",
    "wof:placetype":"venue"
},
  "geometry": {"coordinates":[11.5247821808,49.5964202881],"type":"Point"}
}