{
  "type": "Feature",
  "properties": {
    "iso:country":"DE",
    "sg:address":"Schleswiger Str. 45",
    "sg:city":"Flensburg",
    "sg:postcode":"24941",
    "sg:province":"Schleswig-Holstein",
    "wof:name":"J. Lange",
    "wof:placetype":"venue"
},
  "geometry": {"coordinates":[9.4353647232,54.7732849121],"type":"Point"}
}