{
  "type": "Feature",
  "properties": {
    "iso:country":"DE",
    "sg:address":"Hauptstr. 19",
    "sg:city":"Dobel",
    "sg:phone":"+49 7083/8873",
    "sg:postcode":"75335",
    "sg:province":"Baden-W\u00fcrttemberg",
    "wof:name":"Pension Linde",
    "wof:placetype":"venue"
},
  "geometry": {"coordinates":[8.4958353043,48.7982521057],"type":"Point"}
}