{
  "type": "Feature",
  "properties": {
    "iso:country":"DE",
    "sg:address":"Bonner Talweg 180",
    "sg:city":"Bonn",
    "sg:phone":"+49 228/215146",
    "sg:postcode":"53129",
    "sg:province":"Nordrhein-Westfalen",
    "wof:name":"Bioladen Firmenich & Murmann Kg",
    "wof:placetype":"venue"
},
  "geometry": {"coordinates":[7.1042580605,50.720451355],"type":"Point"}
}