{
  "type": "Feature",
  "properties": {
    "iso:country":"DE",
    "sg:address":"Rother Weingartenweg 46",
    "sg:city":"Bad Soden",
    "sg:phone":"+49 6196/528440",
    "sg:postcode":"65812",
    "sg:province":"Hessen",
    "wof:name":"A. Und S. Wilhelm",
    "wof:placetype":"venue"
},
  "geometry": {"coordinates":[8.501762,50.153309],"type":"Point"}
}