{
  "type": "Feature",
  "properties": {
    "iso:country":"DE",
    "sg:address":"Ganswies 4",
    "sg:city":"Eurasburg",
    "sg:phone":"+49 8208/1415",
    "sg:postcode":"86495",
    "sg:province":"Bayern",
    "wof:name":"Hofmann & Echter",
    "wof:placetype":"venue"
},
  "geometry": {"coordinates":[11.1192369461,48.3178024292],"type":"Point"}
}