{
  "type": "Feature",
  "properties": {
    "iso:country":"DE",
    "sg:address":"Heesfeld 1 a",
    "sg:city":"Braunschweig",
    "sg:phone":"+49 531/310310",
    "sg:postcode":"38112",
    "sg:province":"Niedersachsen",
    "wof:name":"Taxi Braunschweig-nord Ohg",
    "wof:placetype":"venue"
},
  "geometry": {"coordinates":[10.4813318253,52.3087615967],"type":"Point"}
}