{
  "type": "Feature",
  "properties": {
    "iso:country":"DE",
    "sg:address":"Schrofenstr. 28",
    "sg:city":"Augsburg",
    "sg:phone":"+49 821/64095",
    "sg:postcode":"86163",
    "sg:province":"Bayern",
    "wof:name":"Manfred Jung",
    "wof:placetype":"venue"
},
  "geometry": {"coordinates":[10.9420289993,48.3460655212],"type":"Point"}
}