{
  "type": "Feature",
  "properties": {
    "iso:country":"DE",
    "sg:address":"Kirchpl. 19",
    "sg:city":"Willich",
    "sg:phone":"+49 2154/49320",
    "sg:postcode":"47877",
    "sg:province":"Nordrhein-Westfalen",
    "wof:name":"Volksbank Willich Eg",
    "wof:placetype":"venue"
},
  "geometry": {"coordinates":[6.462594,51.278183],"type":"Point"}
}