{
  "type": "Feature",
  "properties": {
    "iso:country":"DE",
    "sg:address":"Schulstr. 16",
    "sg:city":"Hohenhameln",
    "sg:phone":"+49 5128/345",
    "sg:postcode":"31249",
    "sg:province":"Niedersachsen",
    "wof:name":"Karl Hahne",
    "wof:placetype":"venue"
},
  "geometry": {"coordinates":[10.119953,52.239922],"type":"Point"}
}