{
  "type": "Feature",
  "properties": {
    "iso:country":"DE",
    "sg:address":"Xantener Str. 27",
    "sg:city":"Alpen",
    "sg:phone":"+49 2802/5384",
    "sg:postcode":"46519",
    "sg:province":"Nordrhein-Westfalen",
    "wof:name":"Hilde Blaschkowitz",
    "wof:placetype":"venue"
},
  "geometry": {"coordinates":[6.5455870628,51.5875091553],"type":"Point"}
}