{
  "type": "Feature",
  "properties": {
    "iso:country":"DE",
    "sg:address":"Zum Nordkai 16",
    "sg:city":"Emden",
    "sg:phone":"+49 4921",
    "sg:postcode":"26725",
    "sg:province":"Niedersachsen",
    "wof:name":"Hameg.net Internetaktualisierungen Einfach Gemacht",
    "wof:placetype":"venue"
},
  "geometry": {"coordinates":[7.214325,53.343712],"type":"Point"}
}