{
  "type": "Feature",
  "properties": {
    "iso:country":"DE",
    "sg:address":"Lehmweg 18",
    "sg:city":"Holm",
    "sg:phone":"+49 4103/7327",
    "sg:postcode":"25488",
    "sg:province":"Schleswig-Holstein",
    "wof:name":"Hans-wilhelm Kruse",
    "wof:placetype":"venue"
},
  "geometry": {"coordinates":[9.677042,53.622662],"type":"Point"}
}