{
  "type": "Feature",
  "properties": {
    "iso:country":"DE",
    "sg:address":"Hauptstr. 71",
    "sg:city":"Hage",
    "sg:phone":"+49 4931/7287",
    "sg:postcode":"26524",
    "sg:province":"Niedersachsen",
    "wof:name":"Gerhard M\u00fcller",
    "wof:placetype":"venue"
},
  "geometry": {"coordinates":[7.281145,53.602901],"type":"Point"}
}