{
  "type": "Feature",
  "properties": {
    "iso:country":"DE",
    "sg:address":"Weinbergstr. 4",
    "sg:city":"Heroldsbach",
    "sg:phone":"+49 9190/379",
    "sg:postcode":"91336",
    "sg:province":"Bayern",
    "wof:name":"Anni B\u00fcttner",
    "wof:placetype":"venue"
},
  "geometry": {"coordinates":[11.0052080154,49.691986084],"type":"Point"}
}