{
  "type": "Feature",
  "properties": {
    "iso:country":"DE",
    "sg:address":"Schlo\u00dfstr. 28",
    "sg:city":"Schwaigern",
    "sg:phone":"+49 7138/5009",
    "sg:postcode":"74193",
    "sg:province":"Baden-W\u00fcrttemberg",
    "wof:name":"Walter Brahner",
    "wof:placetype":"venue"
},
  "geometry": {"coordinates":[9.058005,49.144161],"type":"Point"}
}