{
  "type": "Feature",
  "properties": {
    "iso:country":"DE",
    "sg:address":"Mindener Str. 2",
    "sg:city":"Bad Oeynhausen",
    "sg:phone":"+49 5731/27051",
    "sg:postcode":"32545",
    "sg:province":"Nordrhein-Westfalen",
    "wof:name":"Hilgenb\u00f6ker Gmbh",
    "wof:placetype":"venue"
},
  "geometry": {"coordinates":[8.8014469147,52.2071075439],"type":"Point"}
}