{
  "type": "Feature",
  "properties": {
    "iso:country":"DE",
    "sg:address":"Klosterstr. 6",
    "sg:city":"Kronach",
    "sg:phone":"+49 9261/4292",
    "sg:postcode":"96317",
    "sg:province":"Bayern",
    "wof:name":"Ludwig Barnickel",
    "wof:placetype":"venue"
},
  "geometry": {"coordinates":[11.3228006363,50.243057251],"type":"Point"}
}