{
  "type": "Feature",
  "properties": {
    "iso:country":"DE",
    "sg:address":"R\u00f6merstr. 10",
    "sg:city":"Lorsch",
    "sg:phone":"+49 6251/57184",
    "sg:postcode":"64653",
    "sg:province":"Hessen",
    "wof:name":"T. R\u00fcck",
    "wof:placetype":"venue"
},
  "geometry": {"coordinates":[8.5675172806,49.6526908875],"type":"Point"}
}