{
  "type": "Feature",
  "properties": {
    "iso:country":"DE",
    "sg:address":"Friedensstr. 30",
    "sg:city":"Gro\u00dfkorbetha",
    "sg:phone":"+49 34446/20643",
    "sg:postcode":"06688",
    "sg:province":"Sachsen-Anhalt",
    "wof:name":"Siegmar Eckert",
    "wof:placetype":"venue"
},
  "geometry": {"coordinates":[12.03265,51.265022],"type":"Point"}
}