{
  "type": "Feature",
  "properties": {
    "iso:country":"DE",
    "sg:address":"Klumpbahn 1",
    "sg:city":"Neu L\u00fcblow",
    "sg:phone":"+49 38753/80182",
    "sg:postcode":"19288",
    "sg:province":"Mecklenburg-Vorpommern",
    "wof:name":"Metallbau Hempel Gmbh",
    "wof:placetype":"venue"
},
  "geometry": {"coordinates":[11.461359,53.37915],"type":"Point"}
}