{
  "type": "Feature",
  "properties": {
    "iso:country":"DE",
    "sg:address":"Hegelstr 18",
    "sg:city":"Neunkirchen",
    "sg:phone":"+49 4523/200894",
    "sg:postcode":"57290",
    "sg:province":"Nordrhein-Westfalen",
    "wof:name":"Ralf Harders Container- Und Raumsysteme",
    "wof:placetype":"venue"
},
  "geometry": {"coordinates":[10.679025,54.204201],"type":"Point"}
}