{
  "type": "Feature",
  "properties": {
    "iso:country":"DE",
    "sg:address":"Fraunhoferstr.",
    "sg:city":"Dachau",
    "sg:phone":"+49 8131/15936",
    "sg:postcode":"85221",
    "sg:province":"Bayern",
    "wof:name":"Schr\u00f6der & Weissenbach Kunststoffwaren",
    "wof:placetype":"venue"
},
  "geometry": {"coordinates":[11.475689888,48.2619857788],"type":"Point"}
}