{
  "type": "Feature",
  "properties": {
    "iso:country":"DE",
    "sg:address":"Heinsonweg 27",
    "sg:city":"Hamburg",
    "sg:phone":"+49 40/60911513",
    "sg:postcode":"22359",
    "sg:province":"Hamburg",
    "wof:name":"Hth Hansetravel Gmbh",
    "wof:placetype":"venue"
},
  "geometry": {"coordinates":[10.1767244339,53.6465187073],"type":"Point"}
}