{
  "type": "Feature",
  "properties": {
    "iso:country":"DE",
    "sg:address":"Pforzheimer Str. 351",
    "sg:city":"Stuttgart",
    "sg:phone":"+49 711/8875053",
    "sg:postcode":"70499",
    "sg:province":"Baden-W\u00fcrttemberg",
    "wof:name":"Ralf Kowsky",
    "wof:placetype":"venue"
},
  "geometry": {"coordinates":[9.115698,48.813843],"type":"Point"}
}