{
  "type": "Feature",
  "properties": {
    "iso:country":"DE",
    "sg:address":"Erligheimer Str. 29",
    "sg:city":"L\u00f6chgau",
    "sg:postcode":"74369",
    "sg:province":"Baden-W\u00fcrttemberg",
    "wof:name":"Wlz-raiffeisen Ag",
    "wof:placetype":"venue"
},
  "geometry": {"coordinates":[9.106316,49.001652],"type":"Point"}
}