{
  "type": "Feature",
  "properties": {
    "iso:country":"DE",
    "sg:address":"Hattermannsweg 1",
    "sg:city":"Norden",
    "sg:phone":"+49 4931/8429",
    "sg:postcode":"26506",
    "sg:province":"Niedersachsen",
    "wof:name":"Henno Herlyn",
    "wof:placetype":"venue"
},
  "geometry": {"coordinates":[7.163175,53.616524],"type":"Point"}
}