{
  "type": "Feature",
  "properties": {
    "iso:country":"DE",
    "sg:address":"Hauptstr. 249",
    "sg:city":"Herne",
    "sg:phone":"+49 2325/9810",
    "sg:postcode":"44649",
    "sg:province":"Nordrhein-Westfalen",
    "wof:name":"Stadt-parf\u00fcmerie Pieper Gmbh",
    "wof:placetype":"venue"
},
  "geometry": {"coordinates":[7.158421,51.531666],"type":"Point"}
}