{
  "type": "Feature",
  "properties": {
    "iso:country":"DE",
    "sg:address":"In der Vo\u00dfbank 15",
    "sg:city":"Bochum",
    "sg:phone":"+49 234/534519",
    "sg:postcode":"44809",
    "sg:province":"Nordrhein-Westfalen",
    "wof:name":"K. Grzembowski",
    "wof:placetype":"venue"
},
  "geometry": {"coordinates":[7.2197928429,51.5030899048],"type":"Point"}
}