{
  "type": "Feature",
  "properties": {
    "iso:country":"DE",
    "sg:address":"F\u00fcrst-Johann-Moritz-Str. 1",
    "sg:city":"Siegen",
    "sg:postcode":"57072",
    "sg:province":"Nordrhein-Westfalen",
    "wof:name":"Viterra Ag",
    "wof:placetype":"venue"
},
  "geometry": {"coordinates":[8.0186023712,50.876209259],"type":"Point"}
}