{
  "type": "Feature",
  "properties": {
    "iso:country":"DE",
    "sg:address":"Stubenlohstr. 34",
    "sg:city":"Erlangen",
    "sg:phone":"+49 9131/23093",
    "sg:postcode":"91052",
    "sg:province":"Bayern",
    "wof:name":"Metzner & Mandel",
    "wof:placetype":"venue"
},
  "geometry": {"coordinates":[11.0147562027,49.5948371887],"type":"Point"}
}