{
  "type": "Feature",
  "properties": {
    "iso:country":"DE",
    "sg:address":"Dietlindenstr. 15",
    "sg:city":"Muenchen",
    "sg:phone":"+49 89/3618551",
    "sg:postcode":"80802",
    "sg:province":"Bayern",
    "wof:name":"C.c.t. Combined Container Transport Vermittlungs-gmbh",
    "wof:placetype":"venue"
},
  "geometry": {"coordinates":[11.5929307938,48.1655197144],"type":"Point"}
}