{
  "type": "Feature",
  "properties": {
    "iso:country":"DE",
    "sg:address":"Minervastr. 6",
    "sg:city":"Isselburg",
    "sg:phone":"+49 2874/724",
    "sg:postcode":"46419",
    "sg:province":"Nordrhein-Westfalen",
    "wof:name":"Ev. Pfarramt Anholt",
    "wof:placetype":"venue"
},
  "geometry": {"coordinates":[6.461209774,51.834690094],"type":"Point"}
}