{
  "type": "Feature",
  "properties": {
    "iso:country":"DE",
    "sg:address":"Auf der Klocksborg 16 a",
    "sg:city":"Soest",
    "sg:phone":"+49 2921/4795",
    "sg:postcode":"59494",
    "sg:province":"Nordrhein-Westfalen",
    "wof:name":"Gunnar Schwolle",
    "wof:placetype":"venue"
},
  "geometry": {"coordinates":[8.095459,51.577423],"type":"Point"}
}