{
  "type": "Feature",
  "properties": {
    "iso:country":"DE",
    "sg:address":"Am Stadion 42",
    "sg:city":"Recklinghausen",
    "sg:phone":"+49 2361/21324",
    "sg:postcode":"45659",
    "sg:province":"Nordrhein-Westfalen",
    "wof:name":"Friedhelm Huber Gmbh",
    "wof:placetype":"venue"
},
  "geometry": {"coordinates":[7.189134,51.597912],"type":"Point"}
}