{
  "type": "Feature",
  "properties": {
    "iso:country":"DE",
    "sg:address":"Heedfelder Str. 10",
    "sg:city":"Schalksm\u00fchle",
    "sg:phone":"+49 2351/51181",
    "sg:postcode":"58579",
    "sg:province":"Nordrhein-Westfalen",
    "wof:name":"Bewerunge",
    "wof:placetype":"venue"
},
  "geometry": {"coordinates":[7.5831198692,51.2561836243],"type":"Point"}
}