{
  "type": "Feature",
  "properties": {
    "iso:country":"DE",
    "sg:address":"Durmersheimer Str. 84",
    "sg:city":"Karlsruhe",
    "sg:phone":"+49 721/577287",
    "sg:postcode":"76185",
    "sg:province":"Baden-W\u00fcrttemberg",
    "wof:name":"B\u00e4tz Holzbau Gmbh",
    "wof:placetype":"venue"
},
  "geometry": {"coordinates":[8.3539495468,49.0021743774],"type":"Point"}
}