{
  "type": "Feature",
  "properties": {
    "iso:country":"DE",
    "sg:address":"Ramersbacher Str. 5",
    "sg:city":"Bad Neuenahr-Ahrweiler",
    "sg:phone":"+49 2641/31300",
    "sg:postcode":"53474",
    "sg:province":"Rheinland-Pfalz",
    "wof:name":"Gerd Reuter",
    "wof:placetype":"venue"
},
  "geometry": {"coordinates":[7.0969119072,50.5385398865],"type":"Point"}
}