{
  "type": "Feature",
  "properties": {
    "iso:country":"DE",
    "sg:address":"Dorfstr. 3",
    "sg:city":"Dollern",
    "sg:phone":"+49 4163/6563",
    "sg:postcode":"21739",
    "sg:province":"Niedersachsen",
    "wof:name":"Heinrich M\u00fcller",
    "wof:placetype":"venue"
},
  "geometry": {"coordinates":[9.5478792191,53.5370941162],"type":"Point"}
}