{
  "type": "Feature",
  "properties": {
    "iso:country":"DE",
    "sg:address":"Gieschenhagen 8",
    "sg:city":"Bad Segeberg",
    "sg:phone":"+49 4551/4633",
    "sg:postcode":"23795",
    "sg:province":"Schleswig-Holstein",
    "wof:name":"Blumen-reitt Erwin Reitt E. Kfm.",
    "wof:placetype":"venue"
},
  "geometry": {"coordinates":[10.316089,53.932312],"type":"Point"}
}