{
  "type": "Feature",
  "properties": {
    "iso:country":"DE",
    "sg:address":"Bokeler Weg 5",
    "sg:city":"Nienwohlde",
    "sg:phone":"+49 4958/024560",
    "sg:postcode":"29596",
    "sg:province":"Niedersachsen",
    "wof:name":"Roni Elektroger\u00c4tebau Gmbh",
    "wof:placetype":"venue"
},
  "geometry": {"coordinates":[10.56221,52.846386],"type":"Point"}
}