{
  "type": "Feature",
  "properties": {
    "iso:country":"DE",
    "sg:address":"Brochth\u00e4user Str. 37",
    "sg:city":"Duderstadt",
    "sg:phone":"+49 5529/1343",
    "sg:postcode":"37115",
    "sg:province":"Niedersachsen",
    "wof:name":"Willi Otto",
    "wof:placetype":"venue"
},
  "geometry": {"coordinates":[10.359875679,51.5506477356],"type":"Point"}
}