{
  "type": "Feature",
  "properties": {
    "iso:country":"DE",
    "sg:address":"Lauchst\u00e4dter Str.",
    "sg:city":"Angersdorf",
    "sg:phone":"+49 345/6131922",
    "sg:postcode":"06179",
    "sg:province":"Sachsen-Anhalt",
    "wof:name":"Mc Donalds",
    "wof:placetype":"venue"
},
  "geometry": {"coordinates":[11.9073896408,51.4589004517],"type":"Point"}
}