{
  "type": "Feature",
  "properties": {
    "iso:country":"DE",
    "sg:address":"Gutenbergstr. 26",
    "sg:city":"Berlin",
    "sg:postcode":"12621",
    "sg:province":"Berlin",
    "wof:name":"Tycon Bau Gmbh",
    "wof:placetype":"venue"
},
  "geometry": {"coordinates":[13.5845308304,52.5145072937],"type":"Point"}
}