{
  "type": "Feature",
  "properties": {
    "iso:country":"DE",
    "sg:address":"Am Bahnhof 4a",
    "sg:city":"Gilching",
    "sg:postcode":"82205",
    "sg:province":"Bayern",
    "wof:name":"Joop Systeml\u00f6sungen Gmbh",
    "wof:placetype":"venue"
},
  "geometry": {"coordinates":[11.3012638092,48.1075057983],"type":"Point"}
}