{
  "type": "Feature",
  "properties": {
    "iso:country":"DE",
    "sg:address":"Oberpforte 15",
    "sg:city":"Laubach",
    "sg:postcode":"35321",
    "sg:province":"Hessen",
    "wof:name":"Volksb\u00fccherei",
    "wof:placetype":"venue"
},
  "geometry": {"coordinates":[8.921395,50.552483],"type":"Point"}
}