{
  "type": "Feature",
  "properties": {
    "iso:country":"DE",
    "sg:address":"Ettlinger Str. 19",
    "sg:city":"Karlsruhe",
    "sg:phone":"+49 721/376878",
    "sg:postcode":"76137",
    "sg:province":"Baden-W\u00fcrttemberg",
    "wof:name":"Kohler Immobilienmakler",
    "wof:placetype":"venue"
},
  "geometry": {"coordinates":[8.4032945633,49.0009460449],"type":"Point"}
}