{
  "type": "Feature",
  "properties": {
    "iso:country":"DE",
    "sg:address":"Waldd\u00f6rferstr. 217",
    "sg:city":"Hamburg",
    "sg:phone":"+49 40/6937185",
    "sg:postcode":"22047",
    "sg:province":"Hamburg",
    "wof:name":"Georg Kuchta & Co.",
    "wof:placetype":"venue"
},
  "geometry": {"coordinates":[10.09258461,53.5813484192],"type":"Point"}
}