{
  "type": "Feature",
  "properties": {
    "iso:country":"DE",
    "sg:address":"Hallerweg 9",
    "sg:city":"Gescher",
    "sg:phone":"+49 2542/7718",
    "sg:postcode":"48712",
    "sg:province":"Nordrhein-Westfalen",
    "wof:name":"H. Spicker",
    "wof:placetype":"venue"
},
  "geometry": {"coordinates":[7.0169157982,51.9505386353],"type":"Point"}
}