{
  "type": "Feature",
  "properties": {
    "iso:country":"DE",
    "sg:address":"Villeneuver Str. 5",
    "sg:city":"Rheinbach",
    "sg:phone":"+49 2226/6443",
    "sg:postcode":"53359",
    "sg:province":"Nordrhein-Westfalen",
    "wof:name":"Stadthalle",
    "wof:placetype":"venue"
},
  "geometry": {"coordinates":[6.953603,50.618206],"type":"Point"}
}