{
  "type": "Feature",
  "properties": {
    "iso:country":"DE",
    "sg:address":"Grubenstr. 50",
    "sg:city":"Bonn",
    "sg:phone":"+49 228/347670",
    "sg:postcode":"53179",
    "sg:province":"Nordrhein-Westfalen",
    "wof:name":"Lissy Gernert",
    "wof:placetype":"venue"
},
  "geometry": {"coordinates":[7.16849,50.660118],"type":"Point"}
}