{
  "type": "Feature",
  "properties": {
    "iso:country":"DE",
    "sg:address":"Lend 9",
    "sg:city":"Burgkunstadt",
    "sg:phone":"+49 9572/1575",
    "sg:postcode":"96224",
    "sg:province":"Bayern",
    "wof:name":"Franz Hellmuth",
    "wof:placetype":"venue"
},
  "geometry": {"coordinates":[11.250756,50.140129],"type":"Point"}
}