{
  "type": "Feature",
  "properties": {
    "iso:country":"DE",
    "sg:address":"Peiner Str. 27",
    "sg:city":"Hannover",
    "sg:phone":"+49 511/831014",
    "sg:postcode":"30519",
    "sg:province":"Niedersachsen",
    "wof:name":"Armin Werner Musikinstrumente",
    "wof:placetype":"venue"
},
  "geometry": {"coordinates":[9.7745246887,52.339138031],"type":"Point"}
}