{
  "type": "Feature",
  "properties": {
    "iso:country":"DE",
    "sg:address":"Jakob-Kneip-Str. 112",
    "sg:city":"D\u00fcsseldorf",
    "sg:phone":"+49 211/709163",
    "sg:postcode":"40595",
    "sg:province":"Nordrhein-Westfalen",
    "wof:name":"K. Ginsberg",
    "wof:placetype":"venue"
},
  "geometry": {"coordinates":[6.898145,51.132484],"type":"Point"}
}