{
  "type": "Feature",
  "properties": {
    "iso:country":"DE",
    "sg:address":"Unterer Markt 10",
    "sg:city":"Sonneberg",
    "sg:phone":"+49 3675/703374",
    "sg:postcode":"96515",
    "sg:province":"Th\u00fcringen",
    "wof:name":"Der Brillenladen",
    "wof:placetype":"venue"
},
  "geometry": {"coordinates":[11.174782753,50.3683204651],"type":"Point"}
}