{
  "type": "Feature",
  "properties": {
    "iso:country":"DE",
    "sg:address":"Vorbrucher Str. 33",
    "sg:city":"Schwanewede",
    "sg:phone":"+49 421/68798",
    "sg:postcode":"28790",
    "sg:province":"Niedersachsen",
    "wof:name":"Klaus Morisse",
    "wof:placetype":"venue"
},
  "geometry": {"coordinates":[8.528096,53.238556],"type":"Point"}
}