{
  "type": "Feature",
  "properties": {
    "iso:country":"DE",
    "sg:address":"Pilgramstr. 1",
    "sg:city":"Neuss",
    "sg:phone":"+49 2137/6431",
    "sg:postcode":"41469",
    "sg:province":"Nordrhein-Westfalen",
    "wof:name":"Friedrich-wilhelm Lutter",
    "wof:placetype":"venue"
},
  "geometry": {"coordinates":[6.70515,51.138084],"type":"Point"}
}