{
  "type": "Feature",
  "properties": {
    "iso:country":"DE",
    "sg:address":"Knipfelesweg 5",
    "sg:city":"Brackenheim",
    "sg:phone":"+49 7135/5066",
    "sg:postcode":"74336",
    "sg:province":"Baden-W\u00fcrttemberg",
    "wof:name":"Haus Zaberg\u00e4u",
    "wof:placetype":"venue"
},
  "geometry": {"coordinates":[9.059998,49.073631],"type":"Point"}
}