{
  "type": "Feature",
  "properties": {
    "iso:country":"DE",
    "sg:address":"Hechinger Str. 17",
    "sg:city":"Hirrlingen",
    "sg:phone":"+49 7478/378",
    "sg:postcode":"72145",
    "sg:province":"Baden-W\u00fcrttemberg",
    "wof:name":"J. Kessler Grabdenkm\u00e4ler",
    "wof:placetype":"venue"
},
  "geometry": {"coordinates":[8.8846664429,48.4081764221],"type":"Point"}
}