{
  "type": "Feature",
  "properties": {
    "iso:country":"DE",
    "sg:address":"Scheer",
    "sg:city":"Mengen",
    "sg:phone":"+49 7572/8948",
    "sg:postcode":"88512",
    "sg:province":"Baden-W\u00fcrttemberg",
    "wof:name":"Diana Ils",
    "wof:placetype":"venue"
},
  "geometry": {"coordinates":[9.3163251877,48.0556564331],"type":"Point"}
}