{
  "type": "Feature",
  "properties": {
    "iso:country":"DE",
    "sg:address":"Schwarzwaldstr 16",
    "sg:city":"Wertheim",
    "sg:phone":"+49 9342/96400",
    "sg:postcode":"97877",
    "sg:province":"Baden-W\u00fcrttemberg",
    "wof:name":"Kurt Dinkel Karosserie-fahrzeugbau Gmbh",
    "wof:placetype":"venue"
},
  "geometry": {"coordinates":[9.494089,49.783638],"type":"Point"}
}