{
  "type": "Feature",
  "properties": {
    "iso:country":"DE",
    "sg:address":"Bullenhuser Damm 53",
    "sg:city":"Hamburg",
    "sg:phone":"+49 40/7804630",
    "sg:postcode":"20539",
    "sg:province":"Hamburg",
    "wof:name":"Pfeifer Seil- Und Hebetechnik Gmbh",
    "wof:placetype":"venue"
},
  "geometry": {"coordinates":[10.046159,53.542496],"type":"Point"}
}