{
  "type": "Feature",
  "properties": {
    "iso:country":"DE",
    "sg:address":"Waldnieler Str. 68",
    "sg:city":"Viersen",
    "sg:phone":"+49 2162/52318",
    "sg:postcode":"41751",
    "sg:province":"Nordrhein-Westfalen",
    "wof:name":"Wilh. Fitzen",
    "wof:placetype":"venue"
},
  "geometry": {"coordinates":[6.320485,51.238682],"type":"Point"}
}