{
  "type": "Feature",
  "properties": {
    "iso:country":"DE",
    "sg:address":"Altenberger Str 18",
    "sg:city":"Glash\u00fctte",
    "sg:phone":"+49 35053/48250",
    "sg:postcode":"01768",
    "sg:province":"Sachsen",
    "wof:name":"Schlosserei Ing. Frank Faulhaber",
    "wof:placetype":"venue"
},
  "geometry": {"coordinates":[13.7824172974,50.8485717773],"type":"Point"}
}