{
  "type": "Feature",
  "properties": {
    "iso:country":"DE",
    "sg:address":"Hagenbuchenstr. 14",
    "sg:city":"Stutensee",
    "sg:phone":"+49 7249/8020",
    "sg:postcode":"76297",
    "sg:province":"Baden-W\u00fcrttemberg",
    "wof:name":"Nuraghe Gmbh",
    "wof:placetype":"venue"
},
  "geometry": {"coordinates":[8.4736413956,49.1067008972],"type":"Point"}
}