{
  "type": "Feature",
  "properties": {
    "iso:country":"DE",
    "sg:address":"G\u00fcstener Str. 54",
    "sg:city":"J\u00fclich",
    "sg:phone":"+49 2463/6759",
    "sg:postcode":"52428",
    "sg:province":"Nordrhein-Westfalen",
    "wof:name":"Andreas Havertz Steuerberater",
    "wof:placetype":"venue"
},
  "geometry": {"coordinates":[6.4223470688,50.950969696],"type":"Point"}
}