{
  "type": "Feature",
  "properties": {
    "iso:country":"DE",
    "sg:address":"Kirdorfer Str. 34",
    "sg:city":"Bad Homburg",
    "sg:postcode":"61350",
    "sg:province":"Hessen",
    "wof:name":"Quarzsand- Und Kieswerk Hett Gmbh",
    "wof:placetype":"venue"
},
  "geometry": {"coordinates":[8.6102399826,50.2358093262],"type":"Point"}
}