{
  "type": "Feature",
  "properties": {
    "iso:country":"DE",
    "sg:address":"Hauptstr. 46 a",
    "sg:city":"G\u00f6ssenheim",
    "sg:phone":"+49 9358/315",
    "sg:postcode":"97780",
    "sg:province":"Bayern",
    "wof:name":"G. Henker",
    "wof:placetype":"venue"
},
  "geometry": {"coordinates":[9.782117,50.017529],"type":"Point"}
}