{
  "type": "Feature",
  "properties": {
    "iso:country":"DE",
    "sg:address":"Thundorferstr.",
    "sg:city":"Regensburg",
    "sg:phone":"+49 941/55359",
    "sg:postcode":"93047",
    "sg:province":"Bayern",
    "wof:name":"Regensburger Personen- Schiffahrt Klinger Gmbh",
    "wof:placetype":"venue"
},
  "geometry": {"coordinates":[12.100135,49.02066],"type":"Point"}
}