{
  "type": "Feature",
  "properties": {
    "iso:country":"DE",
    "sg:address":"Wiegerser Str.",
    "sg:city":"Sauensiek",
    "sg:phone":"+49 4169/396",
    "sg:postcode":"21644",
    "sg:province":"Niedersachsen",
    "wof:name":"Heinz Dammann",
    "wof:placetype":"venue"
},
  "geometry": {"coordinates":[9.558205,53.38343],"type":"Point"}
}