{
  "type": "Feature",
  "properties": {
    "iso:country":"DE",
    "sg:address":"Weiherstr. 33",
    "sg:city":"Landstuhl",
    "sg:phone":"+49 6371/64780",
    "sg:postcode":"66849",
    "sg:province":"Rheinland-Pfalz",
    "wof:name":"Ali Baba",
    "wof:placetype":"venue"
},
  "geometry": {"coordinates":[7.5700387955,49.4072914124],"type":"Point"}
}