{
  "type": "Feature",
  "properties": {
    "iso:country":"DE",
    "sg:address":"Augsburger Str. 19",
    "sg:city":"Burgau",
    "sg:phone":"+49 8222/40080",
    "sg:postcode":"89331",
    "sg:province":"Bayern",
    "wof:name":"Vr-banken-g\u00fcnzburg - Die Gro\u00dfe Bankengruppe",
    "wof:placetype":"venue"
},
  "geometry": {"coordinates":[10.410724,48.426361],"type":"Point"}
}