{
  "type": "Feature",
  "properties": {
    "iso:country":"DE",
    "sg:address":"Breitestr. 28",
    "sg:city":"M\u00f6ssingen",
    "sg:phone":"+49 7473/21928",
    "sg:postcode":"72116",
    "sg:province":"Baden-W\u00fcrttemberg",
    "wof:name":"Norbert Saur Architekt",
    "wof:placetype":"venue"
},
  "geometry": {"coordinates":[9.050778,48.404659],"type":"Point"}
}