{
  "type": "Feature",
  "properties": {
    "iso:country":"DE",
    "sg:address":"Weseler Str. 90",
    "sg:city":"Dinslaken",
    "sg:phone":"+49 2064/38718",
    "sg:postcode":"46537",
    "sg:province":"Nordrhein-Westfalen",
    "wof:name":"Hans-joachim Strehlke Rechtsanwalt",
    "wof:placetype":"venue"
},
  "geometry": {"coordinates":[6.7292141914,51.5757026672],"type":"Point"}
}