{
  "type": "Feature",
  "properties": {
    "iso:country":"DE",
    "sg:address":"Im Neyl 30",
    "sg:city":"Arnsberg",
    "sg:phone":"+49 2937/6473",
    "sg:postcode":"59823",
    "sg:province":"Nordrhein-Westfalen",
    "wof:name":"Enno Koch Tankstellenbetriebe",
    "wof:placetype":"venue"
},
  "geometry": {"coordinates":[8.1304311752,51.390712738],"type":"Point"}
}