{
  "type": "Feature",
  "properties": {
    "iso:country":"DE",
    "sg:address":"An Speenbruch 9",
    "sg:city":"Herzogenrath",
    "sg:phone":"+49 241/524552",
    "sg:postcode":"52134",
    "sg:province":"Nordrhein-Westfalen",
    "wof:name":"Jo Maahsen",
    "wof:placetype":"venue"
},
  "geometry": {"coordinates":[6.0743,50.839294],"type":"Point"}
}