{
  "type": "Feature",
  "properties": {
    "iso:country":"DE",
    "sg:address":"Lindenstr. 15 a",
    "sg:city":"Oyten",
    "sg:phone":"+49 4207/91120",
    "sg:postcode":"28876",
    "sg:province":"Niedersachsen",
    "wof:name":"E. & R. Gosch Gmbh",
    "wof:placetype":"venue"
},
  "geometry": {"coordinates":[9.0161590576,53.062374115],"type":"Point"}
}