{
  "type": "Feature",
  "properties": {
    "iso:country":"DE",
    "sg:address":"Max-Planck-Str. 5",
    "sg:city":"N\u00fcrnberg",
    "sg:phone":"+49 911/4249370",
    "sg:postcode":"90443",
    "sg:province":"Bayern",
    "wof:name":"Santec Brandsanierung Gmbh",
    "wof:placetype":"venue"
},
  "geometry": {"coordinates":[11.0639829636,49.4395904541],"type":"Point"}
}