{
  "type": "Feature",
  "properties": {
    "iso:country":"DE",
    "sg:address":"Lindenstr 14",
    "sg:city":"K\u00f6nigsee",
    "sg:phone":"+49 36738/66031",
    "sg:postcode":"07426",
    "sg:province":"Th\u00fcringen",
    "wof:name":"Spefa Kartonagen Inh. Dr. Ernst-josef Str\u00e4tling Ek",
    "wof:placetype":"venue"
},
  "geometry": {"coordinates":[11.103161,50.661182],"type":"Point"}
}