{
  "type": "Feature",
  "properties": {
    "iso:country":"DE",
    "sg:address":"Gro\u00dfe Str. 32",
    "sg:city":"Wallenhorst",
    "sg:phone":"+49 5407/39998",
    "sg:postcode":"49134",
    "sg:province":"Niedersachsen",
    "wof:name":"Adolf Detmer Elektro Mstr.",
    "wof:placetype":"venue"
},
  "geometry": {"coordinates":[8.013883,52.351353],"type":"Point"}
}