{
  "type": "Feature",
  "properties": {
    "iso:country":"DE",
    "sg:address":"Sebastian-M\u00fcnster-Str. 1",
    "sg:city":"Bad Windsheim",
    "sg:phone":"+49 9841/66700",
    "sg:postcode":"91438",
    "sg:province":"Bayern",
    "wof:name":"Offsetdruck W\u00f6rrlein Gmbh",
    "wof:placetype":"venue"
},
  "geometry": {"coordinates":[10.4247169495,49.5104751587],"type":"Point"}
}