{
  "type": "Feature",
  "properties": {
    "iso:country":"DE",
    "sg:address":"Pfeilstr. 37",
    "sg:city":"Gelsenkirchen",
    "sg:phone":"+49 209/9582101",
    "sg:postcode":"45897",
    "sg:province":"Nordrhein-Westfalen",
    "wof:name":"Mimberg Kg",
    "wof:placetype":"venue"
},
  "geometry": {"coordinates":[7.0560588837,51.5437469482],"type":"Point"}
}