{
  "type": "Feature",
  "properties": {
    "iso:country":"DE",
    "sg:address":"Kuckuckstr. 31 A",
    "sg:city":"W\u00f6rthsee",
    "sg:phone":"+49 8153/990205",
    "sg:postcode":"82237",
    "sg:province":"Bayern",
    "wof:name":"Dufter & Partner Immobilien Gmbh",
    "wof:placetype":"venue"
},
  "geometry": {"coordinates":[11.21185112,48.0682525635],"type":"Point"}
}