{
  "type": "Feature",
  "properties": {
    "iso:country":"DE",
    "sg:address":"Am Ringelhain 4",
    "sg:city":"Neustadt",
    "sg:phone":"+49 6692/96080",
    "sg:postcode":"35279",
    "sg:province":"Hessen",
    "wof:name":"Bauscher Baubetriebs Gmbh & Co. Kg",
    "wof:placetype":"venue"
},
  "geometry": {"coordinates":[9.0925073624,50.8455543518],"type":"Point"}
}