{
  "type": "Feature",
  "properties": {
    "iso:country":"DE",
    "sg:address":"Adolfstr. 40",
    "sg:city":"Osnabr\u00fcck",
    "sg:phone":"+49 541/434455",
    "sg:postcode":"49078",
    "sg:province":"Niedersachsen",
    "wof:name":"Gastst\u00e4tte Tatort",
    "wof:placetype":"venue"
},
  "geometry": {"coordinates":[8.0313158035,52.2722129822],"type":"Point"}
}