{
  "type": "Feature",
  "properties": {
    "iso:country":"DE",
    "sg:address":"Alte Dorfstr. 3",
    "sg:city":"Delitzsch",
    "sg:phone":"+49 34202/93765",
    "sg:postcode":"04509",
    "sg:province":"Sachsen",
    "wof:name":"J. Pietsch",
    "wof:placetype":"venue"
},
  "geometry": {"coordinates":[12.4255275726,51.5432167053],"type":"Point"}
}