{
  "type": "Feature",
  "properties": {
    "iso:country":"DE",
    "sg:address":"Industrieweg 43",
    "sg:city":"M\u00fcnster",
    "sg:phone":"+49 4971/7191140",
    "sg:postcode":"48155",
    "sg:province":"Nordrhein-Westfalen",
    "wof:name":"Grau Aromatics Gmbh & Co. Kg",
    "wof:placetype":"venue"
},
  "geometry": {"coordinates":[9.810145,48.802677],"type":"Point"}
}