{
  "type": "Feature",
  "properties": {
    "iso:country":"DE",
    "sg:address":"Driburger Str. 59",
    "sg:city":"Warburg",
    "sg:phone":"+49 5642/6634",
    "sg:postcode":"34414",
    "sg:province":"Nordrhein-Westfalen",
    "wof:name":"Bernhard Hoppe",
    "wof:placetype":"venue"
},
  "geometry": {"coordinates":[9.033012,51.539227],"type":"Point"}
}