{
  "type": "Feature",
  "properties": {
    "iso:country":"DE",
    "sg:address":"Adlerstr. 6",
    "sg:city":"Ravensburg",
    "sg:phone":"+49 751/23212",
    "sg:postcode":"88212",
    "sg:province":"Baden-W\u00fcrttemberg",
    "wof:name":"W. Buchmann",
    "wof:placetype":"venue"
},
  "geometry": {"coordinates":[9.611946106,47.7821998596],"type":"Point"}
}