{
  "type": "Feature",
  "properties": {
    "iso:country":"DE",
    "sg:address":"Im Sonnenschein 13",
    "sg:city":"Konz",
    "sg:phone":"+49 6501/12642",
    "sg:postcode":"54329",
    "sg:province":"Rheinland-Pfalz",
    "wof:name":"Riss Ingenieur",
    "wof:placetype":"venue"
},
  "geometry": {"coordinates":[6.6323838234,49.6929283142],"type":"Point"}
}