{
  "type": "Feature",
  "properties": {
    "iso:country":"DE",
    "sg:address":"Hugenottenstr. 17",
    "sg:city":"Burgwald",
    "sg:phone":"+49 6457/757",
    "sg:postcode":"35099",
    "sg:province":"Hessen",
    "wof:name":"H. Vial",
    "wof:placetype":"venue"
},
  "geometry": {"coordinates":[8.750607,51.006313],"type":"Point"}
}