{
  "type": "Feature",
  "properties": {
    "iso:country":"DE",
    "sg:address":"Rudolf-Renner-Str. 1",
    "sg:city":"Dresden",
    "sg:phone":"+49 351/428050",
    "sg:postcode":"01157",
    "sg:province":"Sachsen",
    "wof:name":"Roth Pahn Und Kollegen Rechtsanw\u00e4lte",
    "wof:placetype":"venue"
},
  "geometry": {"coordinates":[13.6915607452,51.0519218445],"type":"Point"}
}