{
  "type": "Feature",
  "properties": {
    "iso:country":"DE",
    "sg:address":"Neupuschwitz 27",
    "sg:city":"Puschwitz",
    "sg:phone":"+49 35933/5205",
    "sg:postcode":"02699",
    "sg:province":"Sachsen",
    "wof:name":"Vienah",
    "wof:placetype":"venue"
},
  "geometry": {"coordinates":[14.2911558151,51.2607803345],"type":"Point"}
}