{
  "type": "Feature",
  "properties": {
    "iso:country":"DE",
    "sg:address":"B\u00fchlstr. 30",
    "sg:city":"Grafenrheinfeld",
    "sg:phone":"+49 9723/7897",
    "sg:postcode":"97506",
    "sg:province":"Bayern",
    "wof:name":"Bernhard Rumpel",
    "wof:placetype":"venue"
},
  "geometry": {"coordinates":[10.200843,50.000729],"type":"Point"}
}