{
  "type": "Feature",
  "properties": {
    "iso:country":"DE",
    "sg:address":"Heeper Str. 442",
    "sg:city":"Bielefeld",
    "sg:postcode":"33719",
    "sg:province":"Nordrhein-Westfalen",
    "wof:name":"Stadtteilbibliothek E",
    "wof:placetype":"venue"
},
  "geometry": {"coordinates":[8.603396,52.032555],"type":"Point"}
}