{
  "type": "Feature",
  "properties": {
    "iso:country":"DE",
    "sg:address":"Ernst-Reuter-Str. 15",
    "sg:city":"Sehnde",
    "sg:phone":"+49 5138/8947",
    "sg:postcode":"31319",
    "sg:province":"Niedersachsen",
    "wof:name":"Cash Com Gesellschaft F\u00fcr Finanzanalyse Und",
    "wof:placetype":"venue"
},
  "geometry": {"coordinates":[9.9685020447,52.3082237244],"type":"Point"}
}