{
  "type": "Feature",
  "properties": {
    "iso:country":"DE",
    "sg:address":"Hauptstra\u00dfe 46",
    "sg:city":"Linsengericht",
    "sg:phone":"+49 6051/72198",
    "sg:postcode":"63589",
    "sg:province":"Hessen",
    "wof:name":"Tsk Techno Service Krieg",
    "wof:placetype":"venue"
},
  "geometry": {"coordinates":[9.195168,50.188026],"type":"Point"}
}