{
  "type": "Feature",
  "properties": {
    "iso:country":"DE",
    "sg:address":"Am Karrenweg",
    "sg:city":"Waldfeucht",
    "sg:phone":"+49 2455/592",
    "sg:postcode":"52525",
    "sg:province":"Nordrhein-Westfalen",
    "wof:name":"Helmut Von Helden",
    "wof:placetype":"venue"
},
  "geometry": {"coordinates":[6.095342,51.059059],"type":"Point"}
}