{
  "type": "Feature",
  "properties": {
    "iso:country":"DE",
    "sg:address":"L\u00fcbecker Str. 37",
    "sg:city":"Bad Segeberg",
    "sg:phone":"+49 4551/2360",
    "sg:postcode":"23795",
    "sg:province":"Schleswig-Holstein",
    "wof:name":"G. T\u00f6dt",
    "wof:placetype":"venue"
},
  "geometry": {"coordinates":[10.31595,53.936764],"type":"Point"}
}