{
  "type": "Feature",
  "properties": {
    "iso:country":"DE",
    "sg:address":"Wilhelmsplatz 3",
    "sg:city":"Reinhardshagen",
    "sg:phone":"+49 5544/7406",
    "sg:postcode":"34359",
    "sg:province":"Hessen",
    "wof:name":"I. Jerke",
    "wof:placetype":"venue"
},
  "geometry": {"coordinates":[9.601027,51.49604],"type":"Point"}
}