{
  "type": "Feature",
  "properties": {
    "iso:country":"DE",
    "sg:address":"Reisingerstr. 39",
    "sg:city":"Augsburg",
    "sg:phone":"+49 821/582750",
    "sg:postcode":"86159",
    "sg:province":"Bayern",
    "wof:name":"Sisa Gmbh",
    "wof:placetype":"venue"
},
  "geometry": {"coordinates":[10.8783006668,48.3549957275],"type":"Point"}
}