{
  "type": "Feature",
  "properties": {
    "iso:country":"DE",
    "sg:address":"Dieselstr. 13",
    "sg:city":"Neuenkirchen",
    "sg:phone":"+49 4959/7394740",
    "sg:postcode":"48485",
    "sg:province":"Nordrhein-Westfalen",
    "wof:name":"Seli Gmbh",
    "wof:placetype":"venue"
},
  "geometry": {"coordinates":[7.380172,52.252232],"type":"Point"}
}