{
  "type": "Feature",
  "properties": {
    "iso:country":"DE",
    "sg:address":"M\u00fchlenstr. 83",
    "sg:city":"Leer",
    "sg:phone":"+49 491/61177",
    "sg:postcode":"26789",
    "sg:province":"Niedersachsen",
    "wof:name":"Pta-schule Leer Dr. Janssen",
    "wof:placetype":"venue"
},
  "geometry": {"coordinates":[7.4570097923,53.2301483154],"type":"Point"}
}