{
  "type": "Feature",
  "properties": {
    "iso:country":"DE",
    "sg:address":"Friedberger Str. 90",
    "sg:city":"Nidderau",
    "sg:postcode":"61130",
    "sg:province":"Hessen",
    "wof:name":"Fit-inn Heldenbergen Gmbh",
    "wof:placetype":"venue"
},
  "geometry": {"coordinates":[8.858133316,50.2419013977],"type":"Point"}
}