{
  "type": "Feature",
  "properties": {
    "iso:country":"DE",
    "sg:address":"Gro\u00dfer Markt 17",
    "sg:city":"Saarlouis",
    "sg:phone":"+49 6831/43611",
    "sg:postcode":"66740",
    "sg:province":"Saarland",
    "wof:name":"Opticland Die Brille Gmbh",
    "wof:placetype":"venue"
},
  "geometry": {"coordinates":[6.75041008,49.3156204224],"type":"Point"}
}