{
  "type": "Feature",
  "properties": {
    "iso:country":"DE",
    "sg:address":"Ernst-Horn-Str. 17",
    "sg:city":"Hamburg",
    "sg:phone":"+49 40/546217",
    "sg:postcode":"22525",
    "sg:province":"Hamburg",
    "wof:name":"Dieter Sandmann",
    "wof:placetype":"venue"
},
  "geometry": {"coordinates":[9.927859,53.581909],"type":"Point"}
}