{
  "type": "Feature",
  "properties": {
    "iso:country":"DE",
    "sg:address":"Am Wildwechsel 4",
    "sg:city":"Stuttgart",
    "sg:phone":"+49 711/749276",
    "sg:postcode":"70565",
    "sg:province":"Baden-W\u00fcrttemberg",
    "wof:name":"Mkm Segel Sport K. Thomas",
    "wof:placetype":"venue"
},
  "geometry": {"coordinates":[9.089047,48.718281],"type":"Point"}
}