{
  "type": "Feature",
  "properties": {
    "iso:country":"DE",
    "sg:address":"Ahornweg 112",
    "sg:city":"Aschaffenburg",
    "sg:phone":"+49 6021/457070",
    "sg:postcode":"63741",
    "sg:province":"Bayern",
    "wof:name":"Schmitt-maschinen L.r. Schmitt Nachfolger Sondermaschinenbauges. Mbh",
    "wof:placetype":"venue"
},
  "geometry": {"coordinates":[9.12468,49.961441],"type":"Point"}
}