{
  "type": "Feature",
  "properties": {
    "iso:country":"DE",
    "sg:address":"Rundstr. 5",
    "sg:city":"Ingolstadt",
    "sg:phone":"+49 8450/1422",
    "sg:postcode":"85051",
    "sg:province":"Bayern",
    "wof:name":"Hans H\u00e4gele Elektroinstallation",
    "wof:placetype":"venue"
},
  "geometry": {"coordinates":[11.407682,48.714802],"type":"Point"}
}