{
  "type": "Feature",
  "properties": {
    "iso:country":"DE",
    "sg:address":"Sommerdamm 75",
    "sg:city":"Worms",
    "sg:phone":"+49 6242/7801",
    "sg:postcode":"67550",
    "sg:province":"Rheinland-Pfalz",
    "wof:name":"G. Und A. Tils",
    "wof:placetype":"venue"
},
  "geometry": {"coordinates":[8.349319,49.716873],"type":"Point"}
}