{
  "type": "Feature",
  "properties": {
    "iso:country":"DE",
    "sg:address":"Bornkoppelweg 1",
    "sg:city":"Broderstorf",
    "sg:phone":"+49 38204/15244",
    "sg:postcode":"18184",
    "sg:province":"Mecklenburg-Vorpommern",
    "wof:name":"B. R. M. Kartoffelhof Gmbh",
    "wof:placetype":"venue"
},
  "geometry": {"coordinates":[12.2302389145,54.0792045593],"type":"Point"}
}