{
  "type": "Feature",
  "properties": {
    "iso:country":"DE",
    "sg:address":"Nordstr. 1",
    "sg:city":"Flensburg",
    "sg:phone":"+49 461/144350",
    "sg:postcode":"24937",
    "sg:province":"Schleswig-Holstein",
    "wof:name":"Bpn Bauplan Nord Gmbh Projekt M-h-weg 60 & Co. Kg",
    "wof:placetype":"venue"
},
  "geometry": {"coordinates":[9.442509,54.792294],"type":"Point"}
}