{
  "type": "Feature",
  "properties": {
    "iso:country":"DE",
    "sg:address":"Schulstr. 8",
    "sg:city":"Rascheid",
    "sg:phone":"+49 6586/502",
    "sg:postcode":"54413",
    "sg:province":"Rheinland-Pfalz",
    "wof:name":"Ludwig Busreisen Gmbh",
    "wof:placetype":"venue"
},
  "geometry": {"coordinates":[6.9396657944,49.7115783691],"type":"Point"}
}