{
  "type": "Feature",
  "properties": {
    "iso:country":"DE",
    "sg:address":"Kieler Str. 74",
    "sg:city":"Hohenlockstedt",
    "sg:phone":"+49 4826/2256",
    "sg:postcode":"25551",
    "sg:province":"Schleswig-Holstein",
    "wof:name":"Stadt Hamburg",
    "wof:placetype":"venue"
},
  "geometry": {"coordinates":[9.6214799881,53.9641265869],"type":"Point"}
}