{
  "type": "Feature",
  "properties": {
    "iso:country":"DE",
    "sg:address":"In der Worth 6",
    "sg:city":"Gerdau",
    "sg:phone":"+49 5808/338",
    "sg:postcode":"29581",
    "sg:province":"Niedersachsen",
    "wof:name":"Adolf Hilmer Gartenbaubetrieb E. Kfm.",
    "wof:placetype":"venue"
},
  "geometry": {"coordinates":[10.421439,52.96674],"type":"Point"}
}