{
  "type": "Feature",
  "properties": {
    "iso:country":"DE",
    "sg:address":"Bayernstr. 14",
    "sg:city":"Lichtenfels",
    "sg:phone":"+49 9571/2466",
    "sg:postcode":"96215",
    "sg:province":"Bayern",
    "wof:name":"Alfred Raps",
    "wof:placetype":"venue"
},
  "geometry": {"coordinates":[11.078609,50.152061],"type":"Point"}
}