{
  "type": "Feature",
  "properties": {
    "iso:country":"DE",
    "sg:address":"Schillerstr. 11",
    "sg:city":"Wei\u00dfenburg",
    "sg:postcode":"91781",
    "sg:province":"Bayern",
    "wof:name":"Dr. Med. Heinrich Seitzinger",
    "wof:placetype":"venue"
},
  "geometry": {"coordinates":[10.9862003326,49.0302505493],"type":"Point"}
}