{
  "type": "Feature",
  "properties": {
    "iso:country":"DE",
    "sg:address":"Sch\u00f6nsreuther Str. 6",
    "sg:city":"Lichtenfels",
    "sg:postcode":"96215",
    "sg:province":"Bayern",
    "wof:name":"Kellner Gmbh",
    "wof:placetype":"venue"
},
  "geometry": {"coordinates":[11.0128927231,50.1487426758],"type":"Point"}
}