{
  "type": "Feature",
  "properties": {
    "iso:country":"DE",
    "sg:address":"Karl-Ziegler-Str. 52",
    "sg:city":"Waiblingen",
    "sg:phone":"+49 7151/8698",
    "sg:postcode":"71336",
    "sg:province":"Baden-W\u00fcrttemberg",
    "wof:name":"Burg-apotheke",
    "wof:placetype":"venue"
},
  "geometry": {"coordinates":[9.316902,48.864162],"type":"Point"}
}