{"geometry":{"type":"Point","coordinates":[11.559701,48.139088]},"type":"Feature","id":102560449,"bbox":[11.559701,48.139088,11.559701,48.139088],"properties":{"sg:province":"Bayern","geom:longitude":11.559701,"wof:breaches":[],"sg:href":"http://api.simplegeo.com/1.0/features/SG_4w1paS93SLS0bSvdbqIgmT_48.139088_11.559701@1306268793.json","sg:owner":"simplegeo","sg:postcode":"81677","geom:latitude":48.139088,"sg:classifiers":[],"sg:address":"Vogelweidestr. 3::","sg:phone":"+49 89/5515050","wof:hierarchy":[{"venue_id":102560449,"region_id":85682571,"country_id":85633111,"locality_id":101748479,"county_id":102063261,"neighbourhood_id":85900137}],"geom:area":0.000000,"sg:city":"M\u00fcnchen","wof:lastmodified":1438093255,"iso:country":"DE","wof:geomhash":"c0025dfee06b6e752ef7cce24da20d20","wof:name":"Merkur Bank Kg Aa","wof:belongsto":[85682571,85633111,101748479,102063261,85900137],"src:geom":"simplegeo","wof:placetype":"venue","wof:supersedes":[],"wof:id":102560449,"wof:superseded_by":[],"wof:concordances":{"sg:id":"SG_4w1paS93SLS0bSvdbqIgmT_48.139088_11.559701@1306268793"},"wof:parent_id":85900137}}