{
  "type": "Feature",
  "properties": {
    "iso:country":"DE",
    "sg:address":"Am K\u00f6nigsbuckel 12",
    "sg:city":"Wald-Michelbach",
    "sg:phone":"+49 6207/82896",
    "sg:postcode":"69483",
    "sg:province":"Hessen",
    "wof:name":"J. Schaljo",
    "wof:placetype":"venue"
},
  "geometry": {"coordinates":[8.835267,49.566254],"type":"Point"}
}