{
  "type": "Feature",
  "properties": {
    "iso:country":"DE",
    "sg:address":"Matzerather Maar 7",
    "sg:city":"Erkelenz",
    "sg:phone":"+49 2431/73357",
    "sg:postcode":"41812",
    "sg:province":"Nordrhein-Westfalen",
    "wof:name":"Gebr. Gaidzik Gmbh",
    "wof:placetype":"venue"
},
  "geometry": {"coordinates":[6.2829060555,51.0788574219],"type":"Point"}
}