{
  "type": "Feature",
  "properties": {
    "iso:country":"DE",
    "sg:address":"Elberfelder Str. 2",
    "sg:city":"Hagen",
    "sg:phone":"+49 2331/32636",
    "sg:postcode":"58095",
    "sg:province":"Nordrhein-Westfalen",
    "wof:name":"Modehaus Von Drathen Gmbh",
    "wof:placetype":"venue"
},
  "geometry": {"coordinates":[7.474158,51.357174],"type":"Point"}
}