{
  "type": "Feature",
  "properties": {
    "iso:country":"DE",
    "sg:address":"Wintersburgstr. 9",
    "sg:city":"Braunfels",
    "sg:phone":"+49 6442/32788",
    "sg:postcode":"35619",
    "sg:province":"Hessen",
    "wof:name":"Lothar Waltenberg Masseur",
    "wof:placetype":"venue"
},
  "geometry": {"coordinates":[8.389672,50.520103],"type":"Point"}
}