{
  "type": "Feature",
  "properties": {
    "iso:country":"DE",
    "sg:address":"Petscheltweg 437",
    "sg:city":"Oranienburg",
    "sg:postcode":"16515",
    "sg:province":"Brandenburg",
    "wof:name":"Kr\u00fcger-bau Und Bausanierung Gmbh",
    "wof:placetype":"venue"
},
  "geometry": {"coordinates":[13.203666687,52.7457923889],"type":"Point"}
}