{
  "type": "Feature",
  "properties": {
    "iso:country":"DE",
    "sg:address":"Oberensinger Str. 40",
    "sg:city":"N\u00fcrtingen",
    "sg:phone":"+49 7022/502033",
    "sg:postcode":"72622",
    "sg:province":"Baden-W\u00fcrttemberg",
    "wof:name":"Gasthaus Hirsch",
    "wof:placetype":"venue"
},
  "geometry": {"coordinates":[9.3452959061,48.6403083801],"type":"Point"}
}