{
  "type": "Feature",
  "properties": {
    "iso:country":"DE",
    "sg:address":"B\u00f6hmerwaldstr. 30",
    "sg:city":"Regensburg",
    "sg:postcode":"93057",
    "sg:province":"Bayern",
    "wof:name":"Brauerei Hacklberg",
    "wof:placetype":"venue"
},
  "geometry": {"coordinates":[12.10671,49.03722],"type":"Point"}
}