{
  "type": "Feature",
  "properties": {
    "iso:country":"DE",
    "sg:address":"Carumer Str. 1",
    "sg:city":"Bakum",
    "sg:phone":"+49 5438/320",
    "sg:postcode":"49456",
    "sg:province":"Niedersachsen",
    "wof:name":"Alfred Koops",
    "wof:placetype":"venue"
},
  "geometry": {"coordinates":[8.160057,52.713894],"type":"Point"}
}