{
  "type": "Feature",
  "properties": {
    "iso:country":"DE",
    "sg:address":"Wiesenstra\u00dfe 5",
    "sg:city":"Neustadt an der Weinstra\u00dfe",
    "sg:phone":"+49 6321/483649",
    "sg:postcode":"67433",
    "sg:province":"Rheinland-Pfalz",
    "wof:name":"Kunstverein Neustadt An Der Weinstra\u00dfe",
    "wof:placetype":"venue"
},
  "geometry": {"coordinates":[8.146402,49.353222],"type":"Point"}
}