{
  "type": "Feature",
  "properties": {
    "iso:country":"DE",
    "sg:address":"K\u00f6lner Str. 86",
    "sg:city":"Weilerswist",
    "sg:phone":"+49 2254/3165",
    "sg:postcode":"53919",
    "sg:province":"Nordrhein-Westfalen",
    "wof:name":"A. Wechsler",
    "wof:placetype":"venue"
},
  "geometry": {"coordinates":[6.8396449089,50.7549743652],"type":"Point"}
}