{
  "type": "Feature",
  "properties": {
    "iso:country":"DE",
    "sg:address":"Ottostr. 4",
    "sg:city":"M\u00f6nchengladbach",
    "sg:phone":"+49 2166/911940",
    "sg:postcode":"41238",
    "sg:province":"Nordrhein-Westfalen",
    "wof:name":"Jumbo Wash Kraftfahrzeuge Gmbh",
    "wof:placetype":"venue"
},
  "geometry": {"coordinates":[6.4588708878,51.1640090942],"type":"Point"}
}