{
  "type": "Feature",
  "properties": {
    "iso:country":"DE",
    "sg:address":"Hauptstr. 57",
    "sg:city":"Sontheim",
    "sg:phone":"+49 7325/919248",
    "sg:postcode":"89567",
    "sg:province":"Baden-W\u00fcrttemberg",
    "wof:name":"Michael Baumann Praxis F\u00fcr Ergotherapie",
    "wof:placetype":"venue"
},
  "geometry": {"coordinates":[10.290664,48.552628],"type":"Point"}
}