{
  "type": "Feature",
  "properties": {
    "iso:country":"DE",
    "sg:address":"Schanzenstr. 40",
    "sg:city":"Buxtehude",
    "sg:phone":"+49 4161/7060",
    "sg:postcode":"21614",
    "sg:province":"Niedersachsen",
    "wof:name":"Claudius Peters Gmbh",
    "wof:placetype":"venue"
},
  "geometry": {"coordinates":[9.700362,53.465038],"type":"Point"}
}