{
  "type": "Feature",
  "properties": {
    "iso:country":"DE",
    "sg:address":"Sudetenring 70",
    "sg:city":"Mering",
    "sg:phone":"+49 8233/9974",
    "sg:postcode":"86415",
    "sg:province":"Bayern",
    "wof:name":"B. Khodabakhsh Ingenieur",
    "wof:placetype":"venue"
},
  "geometry": {"coordinates":[10.970905304,48.2780456543],"type":"Point"}
}