{
  "type": "Feature",
  "properties": {
    "iso:country":"DE",
    "sg:address":"An der Altnah 16",
    "sg:city":"Langenlonsheim",
    "sg:phone":"+49 6704/960373",
    "sg:postcode":"55450",
    "sg:province":"Rheinland-Pfalz",
    "wof:name":"Daex Bautr\u00e4ger Gmbh",
    "wof:placetype":"venue"
},
  "geometry": {"coordinates":[7.9095258713,49.8970870972],"type":"Point"}
}