{
  "type": "Feature",
  "properties": {
    "iso:country":"DE",
    "sg:address":"Venloer Str. 460",
    "sg:city":"K\u00f6ln",
    "sg:phone":"+49 221/5504823",
    "sg:postcode":"50825",
    "sg:province":"Nordrhein-Westfalen",
    "wof:name":"A. Egitmen",
    "wof:placetype":"venue"
},
  "geometry": {"coordinates":[6.9106078148,50.9543380737],"type":"Point"}
}