{
  "type": "Feature",
  "properties": {
    "iso:country":"DE",
    "sg:address":"Lisa-Meitner-Str. 28",
    "sg:city":"Essen",
    "sg:phone":"+49 201/736061",
    "sg:postcode":"45144",
    "sg:province":"Nordrhein-Westfalen",
    "wof:name":"Hotel / Restaurant Frohnhauser Hof Essen",
    "wof:placetype":"venue"
},
  "geometry": {"coordinates":[6.986606,51.45203],"type":"Point"}
}