{
  "type": "Feature",
  "properties": {
    "iso:country":"DE",
    "sg:address":"Schleswiger Str. 24",
    "sg:city":"B\u00f6klund",
    "sg:phone":"+49 4623/1775",
    "sg:postcode":"24860",
    "sg:province":"Schleswig-Holstein",
    "wof:name":"Provinzial Versicherung Holger Reincke",
    "wof:placetype":"venue"
},
  "geometry": {"coordinates":[9.5839300156,54.6012496948],"type":"Point"}
}