{
  "type": "Feature",
  "properties": {
    "iso:country":"DE",
    "sg:address":"Josef-Baumann-Str. 23",
    "sg:city":"Bochum",
    "sg:postcode":"44805",
    "sg:province":"Nordrhein-Westfalen",
    "wof:name":"Starcore Gmbh",
    "wof:placetype":"venue"
},
  "geometry": {"coordinates":[7.276918,51.508781],"type":"Point"}
}