{
  "type": "Feature",
  "properties": {
    "iso:country":"DE",
    "sg:address":"D\u00fcrener Str. 287",
    "sg:city":"Kerpen",
    "sg:phone":"+49 2275/6168",
    "sg:postcode":"50171",
    "sg:province":"Nordrhein-Westfalen",
    "wof:name":"Gasthaus Kreutz",
    "wof:placetype":"venue"
},
  "geometry": {"coordinates":[6.6320528984,50.8554611206],"type":"Point"}
}