{
  "type": "Feature",
  "properties": {
    "iso:country":"DE",
    "sg:address":"Steinweg 17",
    "sg:city":"Halle",
    "sg:phone":"+49 345/502795",
    "sg:postcode":"06110",
    "sg:province":"Sachsen-Anhalt",
    "wof:name":"Tui-urlaub Center",
    "wof:placetype":"venue"
},
  "geometry": {"coordinates":[11.9705677032,51.4758453369],"type":"Point"}
}