{
  "type": "Feature",
  "properties": {
    "iso:country":"DE",
    "sg:address":"Dietzgenstr. 4",
    "sg:city":"Leipzig",
    "sg:postcode":"04157",
    "sg:province":"Sachsen",
    "wof:name":"Michael & Reiche Gesellschaft F\u00fcr Weiterbildung Und Soft-",
    "wof:placetype":"venue"
},
  "geometry": {"coordinates":[12.3719453812,51.3651313782],"type":"Point"}
}