{
  "type": "Feature",
  "properties": {
    "iso:country":"DE",
    "sg:address":"Bayerwaldstr. 8a",
    "sg:city":"W\u00f6rth",
    "sg:phone":"+49 9482/2484",
    "sg:postcode":"93086",
    "sg:province":"Bayern",
    "wof:name":"Franz Brunner",
    "wof:placetype":"venue"
},
  "geometry": {"coordinates":[12.407386,49.000931],"type":"Point"}
}