{
  "type": "Feature",
  "properties": {
    "iso:country":"DE",
    "sg:address":"Westerstr. 36",
    "sg:city":"St. Michaelisdonn",
    "sg:phone":"+49 4853/80290",
    "sg:postcode":"25693",
    "sg:province":"Schleswig-Holstein",
    "wof:name":"Ugus Und Deniz Sefik",
    "wof:placetype":"venue"
},
  "geometry": {"coordinates":[9.1129703522,53.9837112427],"type":"Point"}
}