{
  "type": "Feature",
  "properties": {
    "iso:country":"DE",
    "sg:address":"Diezer Str. 10+12",
    "sg:city":"Limburg",
    "sg:phone":"+49 6431/27476",
    "sg:postcode":"65549",
    "sg:province":"Hessen",
    "wof:name":"Biwak Trekking Bike",
    "wof:placetype":"venue"
},
  "geometry": {"coordinates":[8.0617256165,50.387928009],"type":"Point"}
}