{
  "type": "Feature",
  "properties": {
    "iso:country":"DE",
    "sg:address":"Alte Rodung 13a",
    "sg:city":"Eschweiler",
    "sg:phone":"+49 2403/35804",
    "sg:postcode":"52249",
    "sg:province":"Nordrhein-Westfalen",
    "wof:name":"Ralf Schaaf",
    "wof:placetype":"venue"
},
  "geometry": {"coordinates":[6.236709,50.796204],"type":"Point"}
}