{
  "type": "Feature",
  "properties": {
    "iso:country":"DE",
    "sg:address":"Kirchenstr. 13",
    "sg:city":"Schwabstedt",
    "sg:phone":"+49 4884/202",
    "sg:postcode":"25876",
    "sg:province":"Schleswig-Holstein",
    "wof:name":"Ernst Dieter Thomsen",
    "wof:placetype":"venue"
},
  "geometry": {"coordinates":[9.187198,54.394527],"type":"Point"}
}