{
  "type": "Feature",
  "properties": {
    "iso:country":"DE",
    "sg:address":"Haselsberger Str. 8",
    "sg:city":"Oberschlei\u00dfheim",
    "sg:phone":"+49 89/3151628",
    "sg:postcode":"85764",
    "sg:province":"Bayern",
    "wof:name":"Ursula Zenz Drogerie",
    "wof:placetype":"venue"
},
  "geometry": {"coordinates":[11.560485,48.251896],"type":"Point"}
}