{
  "type": "Feature",
  "properties": {
    "iso:country":"DE",
    "sg:address":"Marktstr. 19",
    "sg:city":"Rennertshofen",
    "sg:phone":"+49 8434/1771",
    "sg:postcode":"86643",
    "sg:province":"Bayern",
    "wof:name":"Christin",
    "wof:placetype":"venue"
},
  "geometry": {"coordinates":[11.048382,48.756908],"type":"Point"}
}