{
  "type": "Feature",
  "properties": {
    "iso:country":"DE",
    "sg:address":"Unter der Bleiche 36",
    "sg:city":"Bad M\u00fcnder",
    "sg:phone":"+49 5042/3033",
    "sg:postcode":"31848",
    "sg:province":"Niedersachsen",
    "wof:name":"Domus Verwaltungs- Und Beratungs Gmbh",
    "wof:placetype":"venue"
},
  "geometry": {"coordinates":[9.4565181732,52.1956176758],"type":"Point"}
}