{
  "type": "Feature",
  "properties": {
    "iso:country":"DE",
    "sg:address":"Am Bahnhof 1",
    "sg:city":"Westerstede",
    "sg:phone":"+49 4488/71473",
    "sg:postcode":"26655",
    "sg:province":"Niedersachsen",
    "wof:name":"Almuth Bode",
    "wof:placetype":"venue"
},
  "geometry": {"coordinates":[7.9322309494,53.2540283203],"type":"Point"}
}