{
  "type": "Feature",
  "properties": {
    "iso:country":"DE",
    "sg:address":"Bahnhofstr. 17",
    "sg:city":"Nauheim",
    "sg:phone":"+49 4961/526568",
    "sg:postcode":"64569",
    "sg:province":"Hessen",
    "wof:name":"Bischofsheimer Volksbank Eg",
    "wof:placetype":"venue"
},
  "geometry": {"coordinates":[8.451962,49.943779],"type":"Point"}
}