{
  "type": "Feature",
  "properties": {
    "iso:country":"DE",
    "sg:address":"Im Triesch 5",
    "sg:city":"Sinn",
    "sg:phone":"+49 2772/957620",
    "sg:postcode":"35764",
    "sg:province":"Hessen",
    "wof:name":"Elke Fr\u00f6mel",
    "wof:placetype":"venue"
},
  "geometry": {"coordinates":[8.329308,50.653881],"type":"Point"}
}