{
  "type": "Feature",
  "properties": {
    "iso:country":"DE",
    "sg:address":"Am Bahndamm 19",
    "sg:city":"Mauer",
    "sg:phone":"+49 6226/92420",
    "sg:postcode":"69256",
    "sg:province":"Baden-W\u00fcrttemberg",
    "wof:name":"L\u00f6w Gmbh",
    "wof:placetype":"venue"
},
  "geometry": {"coordinates":[8.78848,49.338348],"type":"Point"}
}