{
  "type": "Feature",
  "properties": {
    "iso:country":"DE",
    "sg:address":"Industrieweg",
    "sg:city":"Minden",
    "sg:postcode":"32423",
    "sg:province":"Nordrhein-Westfalen",
    "wof:name":"Hammer Fachm\u00e4rkte F\u00fcr Heim-ausstattung",
    "wof:placetype":"venue"
},
  "geometry": {"coordinates":[8.9432945251,52.2993736267],"type":"Point"}
}