{
  "type": "Feature",
  "properties": {
    "iso:country":"DE",
    "sg:address":"Heusee 11",
    "sg:city":"Pl\u00fcderhausen",
    "sg:phone":"+49 7181/85370",
    "sg:postcode":"73655",
    "sg:province":"Baden-W\u00fcrttemberg",
    "wof:name":"Hannes Gabriel",
    "wof:placetype":"venue"
},
  "geometry": {"coordinates":[9.58791,48.797318],"type":"Point"}
}