{
  "type": "Feature",
  "properties": {
    "iso:country":"DE",
    "sg:address":"Alte Gasse 27",
    "sg:city":"D\u00fcsseldorf",
    "sg:phone":"+49 203/741902",
    "sg:postcode":"40489",
    "sg:province":"Nordrhein-Westfalen",
    "wof:name":"Volker Becher Rechtsanwalt",
    "wof:placetype":"venue"
},
  "geometry": {"coordinates":[6.7893528938,51.3351898193],"type":"Point"}
}