{
  "type": "Feature",
  "properties": {
    "iso:country":"DE",
    "sg:address":"Frankestr. 3",
    "sg:city":"R\u00f6blingen am See",
    "sg:phone":"+49 34774/20342",
    "sg:postcode":"06317",
    "sg:province":"Sachsen-Anhalt",
    "wof:name":"H. Jentsch",
    "wof:placetype":"venue"
},
  "geometry": {"coordinates":[11.67795,51.469276],"type":"Point"}
}