{
  "type": "Feature",
  "properties": {
    "iso:country":"DE",
    "sg:address":"Stephanstr. 21",
    "sg:city":"BERLIN",
    "sg:phone":"+49 30",
    "sg:postcode":"10559",
    "sg:province":"Berlin",
    "wof:name":"Euro Nacomi Trading",
    "wof:placetype":"venue"
},
  "geometry": {"coordinates":[13.3484773636,52.5341033936],"type":"Point"}
}