{
  "type": "Feature",
  "properties": {
    "iso:country":"DE",
    "sg:address":"G\u00e4\u00dflein 9",
    "sg:city":"Altertheim",
    "sg:phone":"+49 9307/449",
    "sg:postcode":"97237",
    "sg:province":"Bayern",
    "wof:name":"Friedrich Bolch",
    "wof:placetype":"venue"
},
  "geometry": {"coordinates":[9.765475,49.72678],"type":"Point"}
}