{
  "type": "Feature",
  "properties": {
    "iso:country":"DE",
    "sg:address":"Zankwaldweg 6",
    "sg:city":"Alpirsbach",
    "sg:phone":"+49 7444/2651",
    "sg:postcode":"72275",
    "sg:province":"Baden-W\u00fcrttemberg",
    "wof:name":"Siegfried Maser",
    "wof:placetype":"venue"
},
  "geometry": {"coordinates":[8.43625,48.335636],"type":"Point"}
}