{
  "type": "Feature",
  "properties": {
    "iso:country":"DE",
    "sg:address":"Bodestr. 2",
    "sg:city":"Hannover",
    "sg:postcode":"30167",
    "sg:province":"Niedersachsen",
    "wof:name":"Erdos Friseurservice Gmbh",
    "wof:placetype":"venue"
},
  "geometry": {"coordinates":[9.7220401764,52.391910553],"type":"Point"}
}