{
  "type": "Feature",
  "properties": {
    "iso:country":"DE",
    "sg:address":"Eckenheimer Landstr. 101",
    "sg:city":"Frankfurt",
    "sg:phone":"+49 69/95529577",
    "sg:postcode":"60318",
    "sg:province":"Hessen",
    "wof:name":"M. Und P. Brusarski Lebensmittel Und Feinkost Gmbh",
    "wof:placetype":"venue"
},
  "geometry": {"coordinates":[8.6855993271,50.1262931824],"type":"Point"}
}