{
  "type": "Feature",
  "properties": {
    "iso:country":"DE",
    "sg:address":"Am Eicherhof 11",
    "sg:city":"M\u00fcnchen",
    "sg:postcode":"81929",
    "sg:province":"Bayern",
    "wof:name":"Elektroanlagen Popp Gmbh",
    "wof:placetype":"venue"
},
  "geometry": {"coordinates":[11.651949,48.140465],"type":"Point"}
}