{
  "type": "Feature",
  "properties": {
    "iso:country":"DE",
    "sg:address":"Marlene-Dietrich-All. 20",
    "sg:city":"Potsdam",
    "sg:phone":"+49 4933/17310",
    "sg:postcode":"14482",
    "sg:province":"Brandenburg",
    "wof:name":"Orb Ostdeutscher Rundfunk Brandenburg",
    "wof:placetype":"venue"
},
  "geometry": {"coordinates":[13.122051,52.390499],"type":"Point"}
}