{
  "type": "Feature",
  "properties": {
    "iso:country":"DE",
    "sg:address":"Lehmweg 107",
    "sg:city":"Gifhorn",
    "sg:phone":"+49 4953/714489",
    "sg:postcode":"38518",
    "sg:province":"Niedersachsen",
    "wof:name":"Frank Kyszkiewicz Gmbh",
    "wof:placetype":"venue"
},
  "geometry": {"coordinates":[10.599477,52.47961],"type":"Point"}
}