{
  "type": "Feature",
  "properties": {
    "iso:country":"DE",
    "sg:address":"Hof\u00fcckerstr. 46::",
    "sg:city":"Karlsruhe",
    "sg:phone":"+49 4972/1680040",
    "sg:postcode":"76139",
    "sg:province":"Baden-W\u00fcrttemberg",
    "wof:name":"Parkwache M Fuchs Gmbh",
    "wof:placetype":"venue"
},
  "geometry": {"coordinates":[8.450339,49.025829],"type":"Point"}
}