{
  "type": "Feature",
  "properties": {
    "iso:country":"DE",
    "sg:address":"Am Wald 15",
    "sg:city":"Karlsruhe",
    "sg:phone":"+49 721/753836",
    "sg:postcode":"76149",
    "sg:province":"Baden-W\u00fcrttemberg",
    "wof:name":"B\u00fcrgerverein Neureut-heide E. V.",
    "wof:placetype":"venue"
},
  "geometry": {"coordinates":[8.3905267715,49.0334396362],"type":"Point"}
}