{
  "type": "Feature",
  "properties": {
    "iso:country":"DE",
    "sg:address":"Graf-Siegfried-Str. 8",
    "sg:city":"Saarburg",
    "sg:phone":"+49 6581/5289",
    "sg:postcode":"54439",
    "sg:province":"Rheinland-Pfalz",
    "wof:name":"W. Junker",
    "wof:placetype":"venue"
},
  "geometry": {"coordinates":[6.5513739586,49.6093292236],"type":"Point"}
}