{
  "type": "Feature",
  "properties": {
    "iso:country":"DE",
    "sg:address":"Marktstr. 28",
    "sg:city":"Leipheim",
    "sg:phone":"+49 8221/273500",
    "sg:postcode":"89340",
    "sg:province":"Bayern",
    "wof:name":"Landb\u00e4ckerei Sch\u00f6ttle",
    "wof:placetype":"venue"
},
  "geometry": {"coordinates":[10.221504,48.446415],"type":"Point"}
}