{
  "type": "Feature",
  "properties": {
    "iso:country":"DE",
    "sg:address":"Chausseehaus 1",
    "sg:city":"Dieskau",
    "sg:phone":"+49 345/580820",
    "sg:postcode":"06184",
    "sg:province":"Sachsen-Anhalt",
    "wof:name":"K\u00f6-ha Automobilhandel Helmut Peters Gmbh & Co. Kg",
    "wof:placetype":"venue"
},
  "geometry": {"coordinates":[12.0981149673,51.4363746643],"type":"Point"}
}