{
  "type": "Feature",
  "properties": {
    "iso:country":"DE",
    "sg:address":"Katzenbuckelstr. 26",
    "sg:city":"Waldbrunn-Waldkatzenbach",
    "sg:phone":"+49 6274/92020",
    "sg:postcode":"69429",
    "sg:province":"Baden-W\u00fcrttemberg",
    "wof:name":"Haus Sonneneck - Das Freundliche G\u00e4stehaus Im Odenwald",
    "wof:placetype":"venue"
},
  "geometry": {"coordinates":[9.0456619263,49.4661216736],"type":"Point"}
}