{
  "type": "Feature",
  "properties": {
    "iso:country":"DE",
    "sg:address":"Unterk\u00fcrnach 2",
    "sg:city":"Wiggensbach",
    "sg:phone":"+49 8370/8070",
    "sg:postcode":"87487",
    "sg:province":"Bayern",
    "wof:name":"Hofgut K\u00fcrnach Club Colombo",
    "wof:placetype":"venue"
},
  "geometry": {"coordinates":[10.1634998322,47.7449951172],"type":"Point"}
}