{
  "type": "Feature",
  "properties": {
    "iso:country":"DE",
    "sg:address":"Sch\u00fctzenstr. 11 B",
    "sg:city":"Weilheim",
    "sg:phone":"+49 881/41519",
    "sg:postcode":"82362",
    "sg:province":"Bayern",
    "wof:name":"Ingrid Eichberger Heilpraktikerin",
    "wof:placetype":"venue"
},
  "geometry": {"coordinates":[11.1499900818,47.8426704407],"type":"Point"}
}