{
  "type": "Feature",
  "properties": {
    "iso:country":"DE",
    "sg:address":"Mathildenstr. 3",
    "sg:city":"Bremen",
    "sg:phone":"+49 421/72974",
    "sg:postcode":"28203",
    "sg:province":"Bremen",
    "wof:name":"S. Schalipp",
    "wof:placetype":"venue"
},
  "geometry": {"coordinates":[8.8246011734,53.0754776001],"type":"Point"}
}