{
  "type": "Feature",
  "properties": {
    "iso:country":"DE",
    "sg:address":"Hofmannstr. 10",
    "sg:city":"Gie\u00dfen",
    "sg:phone":"+49 641/7021",
    "sg:postcode":"35392",
    "sg:province":"Hessen",
    "wof:name":"Institut F. Zuchthygiene Und Veterin\u00e4rmedizinische Genetik",
    "wof:placetype":"venue"
},
  "geometry": {"coordinates":[8.6634693146,50.5775985718],"type":"Point"}
}