{
  "type": "Feature",
  "properties": {
    "iso:country":"DE",
    "sg:address":"Seeuferweg 1",
    "sg:city":"Damp",
    "sg:phone":"+49 4352/5723",
    "sg:postcode":"24351",
    "sg:province":"Schleswig-Holstein",
    "wof:name":"Fahrradverleih Damp",
    "wof:placetype":"venue"
},
  "geometry": {"coordinates":[10.01913,54.581181],"type":"Point"}
}