{
  "type": "Feature",
  "properties": {
    "iso:country":"DE",
    "sg:address":"Weststr. 7 a",
    "sg:city":"D\u00f6lzig",
    "sg:phone":"+49 34205/59606",
    "sg:postcode":"04430",
    "wof:name":"Michelangelo Kg",
    "wof:placetype":"venue"
},
  "geometry": {"coordinates":[12.1984615326,51.3494224548],"type":"Point"}
}