{
  "type": "Feature",
  "properties": {
    "iso:country":"DE",
    "sg:address":"Dankwartstr. 3",
    "sg:city":"Wismar",
    "sg:phone":"+49 3841/258580",
    "sg:postcode":"23966",
    "sg:province":"Mecklenburg-Vorpommern",
    "wof:name":"Gothaer Versicherungen",
    "wof:placetype":"venue"
},
  "geometry": {"coordinates":[11.4646978378,53.8908996582],"type":"Point"}
}