{
  "type": "Feature",
  "properties": {
    "iso:country":"DE",
    "sg:address":"Max-Nonne-Str. 38",
    "sg:city":"Hamburg",
    "sg:phone":"+49 40/5314013",
    "sg:postcode":"22419",
    "sg:province":"Hamburg",
    "wof:name":"Genimex Handels Gmbh",
    "wof:placetype":"venue"
},
  "geometry": {"coordinates":[10.0050067902,53.6613883972],"type":"Point"}
}