{
  "type": "Feature",
  "properties": {
    "iso:country":"DE",
    "sg:address":"Schlo\u00dfplatz 6",
    "sg:city":"Varel",
    "sg:phone":"+49 4451/2223",
    "sg:postcode":"26316",
    "sg:province":"Niedersachsen",
    "wof:name":"Schlo\u00dfcafe Und Konditorei",
    "wof:placetype":"venue"
},
  "geometry": {"coordinates":[8.1376085281,53.3969078064],"type":"Point"}
}