{
  "type": "Feature",
  "properties": {
    "iso:country":"DE",
    "sg:address":"Breslauer Str. 8",
    "sg:city":"Schifferstadt",
    "sg:phone":"+49 6235/959016",
    "sg:postcode":"67105",
    "sg:province":"Rheinland-Pfalz",
    "wof:name":"B\u00f6sling Zeh & Partner Gesellschaft F\u00fcr Management",
    "wof:placetype":"venue"
},
  "geometry": {"coordinates":[8.3833713531,49.39112854],"type":"Point"}
}