{
  "type": "Feature",
  "properties": {
    "iso:country":"DE",
    "sg:address":"Dr.-Jasper-Str. 8",
    "sg:city":"Delligsen",
    "sg:phone":"+49 5187/957478",
    "sg:postcode":"31073",
    "sg:province":"Niedersachsen",
    "wof:name":"Thermotec Fassadensysteme Gmbh & Co. Kg",
    "wof:placetype":"venue"
},
  "geometry": {"coordinates":[9.8178091049,51.9402770996],"type":"Point"}
}