{
  "type": "Feature",
  "properties": {
    "iso:country":"DE",
    "sg:address":"Sittermannstr. 9",
    "sg:city":"Neukirchen-Vluyn",
    "sg:phone":"+49 2845/20594",
    "sg:postcode":"47506",
    "sg:province":"Nordrhein-Westfalen",
    "wof:name":"F. Kreymann Versicherungsvertreter",
    "wof:placetype":"venue"
},
  "geometry": {"coordinates":[6.529074192,51.434425354],"type":"Point"}
}