{
  "type": "Feature",
  "properties": {
    "iso:country":"DE",
    "sg:address":"Schulweg",
    "sg:city":"Oyten",
    "sg:phone":"+49 4207/2770",
    "sg:postcode":"28876",
    "sg:province":"Niedersachsen",
    "wof:name":"Ortsteilb\u00fccherei",
    "wof:placetype":"venue"
},
  "geometry": {"coordinates":[9.052685,53.070644],"type":"Point"}
}