{
  "type": "Feature",
  "properties": {
    "iso:country":"DE",
    "sg:address":"Carsdorfer H\u00f6he 4",
    "sg:city":"Pegau",
    "sg:phone":"+49 34296/76263",
    "sg:postcode":"04523",
    "sg:province":"Sachsen",
    "wof:name":"B\u00e4ckerei Sommer Gmbh",
    "wof:placetype":"venue"
},
  "geometry": {"coordinates":[12.247457,51.175159],"type":"Point"}
}