{
  "type": "Feature",
  "properties": {
    "iso:country":"DE",
    "sg:address":"Rodomstorstr. 72",
    "sg:city":"Pl\u00f6n",
    "sg:phone":"+49 4522/3059",
    "sg:postcode":"24306",
    "sg:province":"Schleswig-Holstein",
    "wof:name":"Klaus Darge Masseur",
    "wof:placetype":"venue"
},
  "geometry": {"coordinates":[10.422068,54.165211],"type":"Point"}
}