{
  "type": "Feature",
  "properties": {
    "iso:country":"DE",
    "sg:address":"Stetteritzring 35",
    "sg:city":"Ro\u00dfdorf",
    "sg:phone":"+49 6071/41483",
    "sg:postcode":"64380",
    "sg:province":"Hessen",
    "wof:name":"Walter Gottstein",
    "wof:placetype":"venue"
},
  "geometry": {"coordinates":[8.7933130264,49.8620948792],"type":"Point"}
}