{
  "type": "Feature",
  "properties": {
    "iso:country":"DE",
    "sg:address":"Am Deepenbrook 31",
    "sg:city":"Neum\u00fcnster",
    "sg:phone":"+49 4321/74744",
    "sg:postcode":"24539",
    "sg:province":"Schleswig-Holstein",
    "wof:name":"H. Lindig",
    "wof:placetype":"venue"
},
  "geometry": {"coordinates":[10.040607,54.050922],"type":"Point"}
}