{
  "type": "Feature",
  "properties": {
    "iso:country":"DE",
    "sg:address":"Detmolder Str. 417",
    "sg:city":"Bielefeld",
    "sg:phone":"+49 521/205636",
    "sg:postcode":"33605",
    "sg:province":"Nordrhein-Westfalen",
    "wof:name":"St. Georg-apotheke",
    "wof:placetype":"venue"
},
  "geometry": {"coordinates":[8.58527,51.998405],"type":"Point"}
}