{
  "type": "Feature",
  "properties": {
    "iso:country":"DE",
    "sg:address":"Rudolf-Diesel-Str. 2",
    "sg:city":"Weingarten",
    "sg:phone":"+49 7244/70260",
    "sg:postcode":"76356",
    "sg:province":"Baden-W\u00fcrttemberg",
    "wof:name":"Alltech Gmbh",
    "wof:placetype":"venue"
},
  "geometry": {"coordinates":[8.519707,49.058159],"type":"Point"}
}