{
  "type": "Feature",
  "properties": {
    "iso:country":"DE",
    "sg:address":"Am Steintor 6",
    "sg:city":"Wittenberge",
    "sg:phone":"+49 3877/403808",
    "sg:postcode":"19322",
    "sg:province":"Brandenburg",
    "wof:name":"Gsw Gesellschaft F\u00fcr Stadterneuerung",
    "wof:placetype":"venue"
},
  "geometry": {"coordinates":[11.751127,52.993366],"type":"Point"}
}