{
  "type": "Feature",
  "properties": {
    "iso:country":"DE",
    "sg:address":"Osterstr. 149",
    "sg:city":"Hamburg",
    "sg:phone":"+49 40/4922347",
    "sg:postcode":"20255",
    "sg:province":"Hamburg",
    "wof:name":"Karl-h. Kramer Ingenieur",
    "wof:placetype":"venue"
},
  "geometry": {"coordinates":[9.9484195709,53.5767669678],"type":"Point"}
}