{
  "type": "Feature",
  "properties": {
    "iso:country":"DE",
    "sg:address":"Friedensaue 22",
    "sg:city":"Saarburg",
    "sg:phone":"+49 6581/2748",
    "sg:postcode":"54439",
    "sg:province":"Rheinland-Pfalz",
    "wof:name":"Modehaus M\u00fcller-hamann E. K.",
    "wof:placetype":"venue"
},
  "geometry": {"coordinates":[6.547904,49.605953],"type":"Point"}
}