{
  "type": "Feature",
  "properties": {
    "iso:country":"DE",
    "sg:address":"Cheruskerstr. 16",
    "sg:city":"Bad Iburg",
    "sg:phone":"+49 5403/8521",
    "sg:postcode":"49186",
    "sg:province":"Niedersachsen",
    "wof:name":"Hermann Und Margot Wiecking- Stiftung",
    "wof:placetype":"venue"
},
  "geometry": {"coordinates":[8.0435600281,52.1636009216],"type":"Point"}
}