{
  "type": "Feature",
  "properties": {
    "iso:country":"DE",
    "sg:address":"Humboldtstr. 24",
    "sg:city":"Ilmenau",
    "sg:phone":"+49 3677/870940",
    "sg:postcode":"98693",
    "sg:province":"Th\u00fcringen",
    "wof:name":"Rainer S\u00fc\u00dfmann",
    "wof:placetype":"venue"
},
  "geometry": {"coordinates":[10.9235134125,50.6972007751],"type":"Point"}
}