{
  "type": "Feature",
  "properties": {
    "iso:country":"DE",
    "sg:address":"Dr.-Kurt-Schumacher-Str.",
    "sg:city":"Oranienburg",
    "sg:phone":"+49 3301/56045",
    "sg:postcode":"16515",
    "sg:province":"Brandenburg",
    "wof:name":"P. Leymann",
    "wof:placetype":"venue"
},
  "geometry": {"coordinates":[13.231,52.749893],"type":"Point"}
}