{
  "type": "Feature",
  "properties": {
    "iso:country":"DE",
    "sg:address":"Wodantal 97",
    "sg:city":"Hattingen",
    "sg:phone":"+49 2324/26433",
    "sg:postcode":"45529",
    "sg:province":"Nordrhein-Westfalen",
    "wof:name":"Alfred Terwei",
    "wof:placetype":"venue"
},
  "geometry": {"coordinates":[7.181585,51.370533],"type":"Point"}
}