{
  "type": "Feature",
  "properties": {
    "iso:country":"DE",
    "sg:address":"Benzweg 6",
    "sg:city":"Geretsried",
    "sg:phone":"+49 8171/52623",
    "sg:postcode":"82538",
    "sg:province":"Bayern",
    "wof:name":"D\u00dcster - Leichtmetallguss Gmbh",
    "wof:placetype":"venue"
},
  "geometry": {"coordinates":[11.490267,47.852707],"type":"Point"}
}