{
  "type": "Feature",
  "properties": {
    "iso:country":"DE",
    "sg:address":"Wittenberger Str. 10",
    "sg:city":"Karlsruhe",
    "sg:postcode":"76139",
    "sg:province":"Baden-W\u00fcrttemberg",
    "wof:name":"Ps B. O. U. L. I. S. Ing. Gmbh",
    "wof:placetype":"venue"
},
  "geometry": {"coordinates":[8.4521713257,49.0298995972],"type":"Point"}
}