{
  "type": "Feature",
  "properties": {
    "iso:country":"DE",
    "sg:address":"Theodor-Fontane-Str. 25",
    "sg:city":"Ludwigsfelde",
    "sg:phone":"+49 3378/874981",
    "sg:postcode":"14974",
    "sg:province":"Brandenburg",
    "wof:name":"Document Centre Druckerei",
    "wof:placetype":"venue"
},
  "geometry": {"coordinates":[13.2614746094,52.301864624],"type":"Point"}
}