{
  "type": "Feature",
  "properties": {
    "iso:country":"DE",
    "sg:address":"Klusetor 2",
    "sg:city":"Lippstadt",
    "sg:phone":"+49 2941/3085",
    "sg:postcode":"59555",
    "sg:province":"Nordrhein-Westfalen",
    "wof:name":"K\u00f6nig & Lex Gmbh",
    "wof:placetype":"venue"
},
  "geometry": {"coordinates":[8.3477077484,51.6737251282],"type":"Point"}
}