{
  "type": "Feature",
  "properties": {
    "iso:country":"DE",
    "sg:address":"Kruppstr. 4",
    "sg:city":"Hildesheim",
    "sg:phone":"+49 5121/511084",
    "sg:postcode":"31135",
    "sg:province":"Niedersachsen",
    "wof:name":"Color. A. Gmbh",
    "wof:placetype":"venue"
},
  "geometry": {"coordinates":[9.975862,52.168346],"type":"Point"}
}