{
  "type": "Feature",
  "properties": {
    "iso:country":"DE",
    "sg:address":"Am Klosterfeld 10",
    "sg:city":"N\u00fcrnberg",
    "sg:phone":"+49 911/306607",
    "sg:postcode":"90427",
    "sg:province":"Bayern",
    "wof:name":"Horst Schmuck Fliesen- Beratungs-service Gmbh",
    "wof:placetype":"venue"
},
  "geometry": {"coordinates":[11.01677,49.530949],"type":"Point"}
}