{
  "type": "Feature",
  "properties": {
    "iso:country":"DE",
    "sg:address":"L\u00fctge Bruch 1a",
    "sg:city":"Herne",
    "sg:phone":"+49 4923/2331265",
    "sg:postcode":"44628",
    "sg:province":"Nordrhein-Westfalen",
    "wof:name":"Steinbergbeschilderungssysteme Gmbh",
    "wof:placetype":"venue"
},
  "geometry": {"coordinates":[7.2616729736,51.5590057373],"type":"Point"}
}