{
  "type": "Feature",
  "properties": {
    "iso:country":"DE",
    "sg:address":"Hagener Str. 5- 7",
    "sg:city":"Iserlohn",
    "sg:phone":"+49 2371/784888",
    "sg:postcode":"58642",
    "sg:province":"Nordrhein-Westfalen",
    "wof:name":"Falkeleuchten E.k.",
    "wof:placetype":"venue"
},
  "geometry": {"coordinates":[7.6174898148,51.3649368286],"type":"Point"}
}