{
  "type": "Feature",
  "properties": {
    "iso:country":"DE",
    "sg:address":"Alleestr. 52",
    "sg:city":"Fr\u00f6ndenberg",
    "sg:phone":"+49 2373/72286",
    "sg:postcode":"58730",
    "sg:province":"Nordrhein-Westfalen",
    "wof:name":"H. Betzinger",
    "wof:placetype":"venue"
},
  "geometry": {"coordinates":[7.7788200378,51.4740104675],"type":"Point"}
}