{
  "type": "Feature",
  "properties": {
    "iso:country":"DE",
    "sg:address":"Fahrgasse 63",
    "sg:city":"Dreieich",
    "sg:phone":"+49 6103/85888",
    "sg:postcode":"63303",
    "sg:province":"Hessen",
    "wof:name":"Restaurant Faselstall",
    "wof:placetype":"venue"
},
  "geometry": {"coordinates":[8.7169723511,50.0011825562],"type":"Point"}
}