{
  "type": "Feature",
  "properties": {
    "iso:country":"DE",
    "sg:address":"Rodung 8",
    "sg:city":"Dresden",
    "sg:phone":"+49 351/8493784",
    "sg:postcode":"01139",
    "sg:province":"Sachsen",
    "wof:name":"Gerd Bochmann Architekt",
    "wof:placetype":"venue"
},
  "geometry": {"coordinates":[13.700214,51.093822],"type":"Point"}
}