{
  "type": "Feature",
  "properties": {
    "iso:country":"DE",
    "sg:address":"Kleiststr. 3",
    "sg:city":"Lippstadt",
    "sg:phone":"+49 2941/60183",
    "sg:postcode":"59555",
    "sg:province":"Nordrhein-Westfalen",
    "wof:name":"Lkl-bau Gmbh",
    "wof:placetype":"venue"
},
  "geometry": {"coordinates":[8.346375,51.680744],"type":"Point"}
}