{
  "type": "Feature",
  "properties": {
    "iso:country":"DE",
    "sg:address":"Weinbergweg 29",
    "sg:city":"Reutlingen",
    "sg:phone":"+49 7121/290240",
    "sg:postcode":"72762",
    "sg:province":"Baden-W\u00fcrttemberg",
    "wof:name":"Winfried Asshoff",
    "wof:placetype":"venue"
},
  "geometry": {"coordinates":[9.2043428421,48.4745483398],"type":"Point"}
}