{
  "type": "Feature",
  "properties": {
    "iso:country":"DE",
    "sg:address":"Am S\u00e4lzerhof 2",
    "sg:city":"Kassel",
    "sg:phone":"+49 561/507490",
    "sg:postcode":"34123",
    "sg:province":"Hessen",
    "wof:name":"Voro Stra\u00dfenfr\u00e4sdienst Gmbh",
    "wof:placetype":"venue"
},
  "geometry": {"coordinates":[9.531083107,51.3105888367],"type":"Point"}
}