{
  "type": "Feature",
  "properties": {
    "iso:country":"DE",
    "sg:address":"Meggener Str. 33",
    "sg:city":"Lennestadt",
    "sg:phone":"+49 2721/84263",
    "sg:postcode":"57368",
    "sg:province":"Nordrhein-Westfalen",
    "wof:name":"Vetter",
    "wof:placetype":"venue"
},
  "geometry": {"coordinates":[8.0678920746,51.1237068176],"type":"Point"}
}