{
  "type": "Feature",
  "properties": {
    "iso:country":"DE",
    "sg:address":"Weststr. 2",
    "sg:city":"Ahlerstedt",
    "sg:phone":"+49 4166/7433",
    "sg:postcode":"21702",
    "sg:province":"Niedersachsen",
    "wof:name":"Heini Alpers",
    "wof:placetype":"venue"
},
  "geometry": {"coordinates":[9.490393,53.398994],"type":"Point"}
}