{
  "type": "Feature",
  "properties": {
    "iso:country":"DE",
    "sg:address":"Schlo\u00dfplatz 8",
    "sg:city":"Berchtesgaden",
    "sg:phone":"+49 8652/2106",
    "sg:postcode":"83471",
    "sg:province":"Bayern",
    "wof:name":"Buchdruckerei Fuchs",
    "wof:placetype":"venue"
},
  "geometry": {"coordinates":[13.0032491684,47.6337280273],"type":"Point"}
}