{
  "type": "Feature",
  "properties": {
    "iso:country":"DE",
    "sg:address":"Amselweg 3",
    "sg:city":"Kirchen",
    "sg:phone":"+49 2741/61120",
    "sg:postcode":"57548",
    "sg:province":"Rheinland-Pfalz",
    "wof:name":"Edmund Bender",
    "wof:placetype":"venue"
},
  "geometry": {"coordinates":[7.887773037,50.8086585999],"type":"Point"}
}