{
  "type": "Feature",
  "properties": {
    "iso:country":"DE",
    "sg:address":"Konrad-Adenauer-Str. 7",
    "sg:city":"Frankfurt",
    "sg:phone":"+49 69/29810",
    "sg:postcode":"60313",
    "sg:province":"Hessen",
    "wof:name":"Restaurant Premiere",
    "wof:placetype":"venue"
},
  "geometry": {"coordinates":[8.6872501373,50.1160125732],"type":"Point"}
}