{
  "type": "Feature",
  "properties": {
    "iso:country":"DE",
    "sg:address":"Mozartstr. 10",
    "sg:city":"Ransbach-Baumbach",
    "sg:phone":"+49 2623/2740",
    "sg:postcode":"56235",
    "sg:province":"Rheinland-Pfalz",
    "wof:name":"Baldus",
    "wof:placetype":"venue"
},
  "geometry": {"coordinates":[7.730593,50.470627],"type":"Point"}
}