{
  "type": "Feature",
  "properties": {
    "iso:country":"DE",
    "sg:address":"Am Forsthaus 1",
    "sg:city":"Riedenburg",
    "sg:phone":"+49 9442/1213",
    "sg:postcode":"93339",
    "sg:province":"Bayern",
    "wof:name":"Erika Gabler Hebamme",
    "wof:placetype":"venue"
},
  "geometry": {"coordinates":[11.624723,48.992207],"type":"Point"}
}