{
  "type": "Feature",
  "properties": {
    "iso:country":"DE",
    "sg:address":"Adalbert-Stifter-Str. 4",
    "sg:city":"Viechtach",
    "sg:phone":"+49 9942/1243",
    "sg:postcode":"94234",
    "sg:province":"Bayern",
    "wof:name":"Hedwig Reil Hebamme",
    "wof:placetype":"venue"
},
  "geometry": {"coordinates":[12.888338,49.073807],"type":"Point"}
}