{
  "type": "Feature",
  "properties": {
    "iso:country":"DE",
    "sg:address":"Lindenstr. 5",
    "sg:city":"Triftern",
    "sg:phone":"+49 8562/438",
    "sg:postcode":"84371",
    "sg:province":"Bayern",
    "wof:name":"Egon Voggenreiter",
    "wof:placetype":"venue"
},
  "geometry": {"coordinates":[13.023805,48.433048],"type":"Point"}
}