{
  "type": "Feature",
  "properties": {
    "iso:country":"DE",
    "sg:address":"Kirchstr. 25",
    "sg:city":"Bergh\u00fclen",
    "sg:phone":"+49 7344/8269",
    "sg:postcode":"89180",
    "sg:province":"Baden-W\u00fcrttemberg",
    "wof:name":"M. Hau\u00dfmann",
    "wof:placetype":"venue"
},
  "geometry": {"coordinates":[9.7572460175,48.4656906128],"type":"Point"}
}