{
  "type": "Feature",
  "properties": {
    "iso:country":"DE",
    "sg:address":"Kleiststr. 9",
    "sg:city":"Bitburg",
    "sg:phone":"+49 6561/17675",
    "sg:postcode":"54634",
    "sg:province":"Rheinland-Pfalz",
    "wof:name":"U. Fabry Hebamme",
    "wof:placetype":"venue"
},
  "geometry": {"coordinates":[6.518963,49.967289],"type":"Point"}
}