{
  "type": "Feature",
  "properties": {
    "iso:country":"DE",
    "sg:address":"Badstr. 1",
    "sg:city":"Neu\u00f6tting",
    "sg:phone":"+49 8671/20111",
    "sg:postcode":"84524",
    "sg:province":"Bayern",
    "wof:name":"Hallenbad Neu\u00f6tting",
    "wof:placetype":"venue"
},
  "geometry": {"coordinates":[12.6894540787,48.2338485718],"type":"Point"}
}