{
  "type": "Feature",
  "properties": {
    "iso:country":"DE",
    "sg:address":"Eibenweg 27",
    "sg:city":"Friedrichsthal",
    "sg:phone":"+49 6897/84974",
    "sg:postcode":"66299",
    "sg:province":"Saarland",
    "wof:name":"Werner Kirsch",
    "wof:placetype":"venue"
},
  "geometry": {"coordinates":[7.1054000854,49.338596344],"type":"Point"}
}