{
  "type": "Feature",
  "properties": {
    "iso:country":"DE",
    "sg:address":"Johann-Sch\u00fctte-Str. 7",
    "sg:city":"Mannheim",
    "sg:phone":"+49 621/786064",
    "sg:postcode":"68307",
    "sg:province":"Baden-W\u00fcrttemberg",
    "wof:name":"Peter Knupfer Gmbh",
    "wof:placetype":"venue"
},
  "geometry": {"coordinates":[8.475108,49.547634],"type":"Point"}
}