{
  "type": "Feature",
  "properties": {
    "iso:country":"DE",
    "sg:address":"Schlo\u00dfhof 17",
    "sg:city":"Aidlingen",
    "sg:phone":"+49 7056/1087",
    "sg:postcode":"71134",
    "sg:province":"Baden-W\u00fcrttemberg",
    "wof:name":"Siegfried Tenczer Ingenieur",
    "wof:placetype":"venue"
},
  "geometry": {"coordinates":[8.8681573868,48.6810340881],"type":"Point"}
}