{
  "type": "Feature",
  "properties": {
    "iso:country":"DE",
    "sg:address":"Im Burgfeld 79",
    "sg:city":"Frankfurt",
    "sg:phone":"+49 69/577517",
    "sg:postcode":"60439",
    "sg:province":"Hessen",
    "wof:name":"Stiebel Eltron Gmbh & Co. Kg",
    "wof:placetype":"venue"
},
  "geometry": {"coordinates":[8.6336803436,50.1514854431],"type":"Point"}
}