{
  "type": "Feature",
  "properties": {
    "iso:country":"DE",
    "sg:address":"Im Weidenfeld 3",
    "sg:city":"Niederzier",
    "sg:phone":"+49 2428/902389",
    "sg:postcode":"52382",
    "sg:province":"Nordrhein-Westfalen",
    "wof:name":"P. Jansen",
    "wof:placetype":"venue"
},
  "geometry": {"coordinates":[6.4483408928,50.8977432251],"type":"Point"}
}