{
  "type": "Feature",
  "properties": {
    "iso:country":"DE",
    "sg:address":"Kerkrader Str. 10",
    "sg:city":"Gie\u00dfen",
    "sg:postcode":"35394",
    "sg:province":"Hessen",
    "wof:name":"Labonova Gmbh",
    "wof:placetype":"venue"
},
  "geometry": {"coordinates":[8.728764534,50.5738868713],"type":"Point"}
}