{
  "type": "Feature",
  "properties": {
    "iso:country":"DE",
    "sg:address":"Mettmanner Str. 120-124",
    "sg:city":"Velbert",
    "sg:postcode":"42549",
    "sg:province":"Nordrhein-Westfalen",
    "wof:name":"Hans Theo Schulte Kg.",
    "wof:placetype":"venue"
},
  "geometry": {"coordinates":[7.048158,51.327061],"type":"Point"}
}