{
  "type": "Feature",
  "properties": {
    "iso:country":"DE",
    "sg:address":"Marienberger Str. 1",
    "sg:city":"Braunschweig",
    "sg:phone":"+49 531/873311",
    "sg:postcode":"38122",
    "sg:province":"Niedersachsen",
    "wof:name":"Momo",
    "wof:placetype":"venue"
},
  "geometry": {"coordinates":[10.501612,52.238186],"type":"Point"}
}