{
  "type": "Feature",
  "properties": {
    "iso:country":"DE",
    "sg:address":"Kirchweg 1",
    "sg:city":"Krombach",
    "sg:phone":"+49 6024/9362",
    "sg:postcode":"63829",
    "sg:province":"Bayern",
    "wof:name":"Benno Bathon",
    "wof:placetype":"venue"
},
  "geometry": {"coordinates":[9.206097,50.080139],"type":"Point"}
}