{
  "type": "Feature",
  "properties": {
    "iso:country":"DE",
    "sg:address":"Limesstr. 91",
    "sg:city":"M\u00fcnchen",
    "sg:phone":"+49 89/8977080",
    "sg:postcode":"81243",
    "sg:province":"Bayern",
    "wof:name":"Klinger & Partner Profilvertrieb Verkaufsges. F.",
    "wof:placetype":"venue"
},
  "geometry": {"coordinates":[11.4228630066,48.1452445984],"type":"Point"}
}