{
  "type": "Feature",
  "properties": {
    "iso:country":"DE",
    "sg:address":"Rothenburger Str. 3",
    "sg:city":"Insingen",
    "sg:postcode":"91610",
    "sg:province":"Bayern",
    "wof:name":"Johann N\u00f6lscher-gmbh",
    "wof:placetype":"venue"
},
  "geometry": {"coordinates":[10.167875,49.327362],"type":"Point"}
}