{
  "type": "Feature",
  "properties": {
    "iso:country":"DE",
    "sg:address":"Ipflerstr. 5",
    "sg:city":"St. Leon-Rot",
    "sg:phone":"+49 6227/50797",
    "sg:postcode":"68789",
    "sg:province":"Baden-W\u00fcrttemberg",
    "wof:name":"Karl Stegm\u00fcller Gmbh",
    "wof:placetype":"venue"
},
  "geometry": {"coordinates":[8.6341905594,49.2594604492],"type":"Point"}
}