{
  "type": "Feature",
  "properties": {
    "iso:country":"DE",
    "sg:address":"Hauptmann-Hoffmann-Str. 24",
    "sg:city":"Erlenbach",
    "sg:phone":"+49 6398/1236",
    "sg:postcode":"76891",
    "sg:province":"Rheinland-Pfalz",
    "wof:name":"Matthias Stadelmann",
    "wof:placetype":"venue"
},
  "geometry": {"coordinates":[7.8297348022,49.1301994324],"type":"Point"}
}