{
  "type": "Feature",
  "properties": {
    "iso:country":"DE",
    "sg:address":"Berliner Str. 48",
    "sg:city":"Gladenbach",
    "sg:phone":"+49 6462/8130",
    "sg:postcode":"35075",
    "sg:province":"Hessen",
    "wof:name":"Edeltraud Und K.-dieter Becker",
    "wof:placetype":"venue"
},
  "geometry": {"coordinates":[8.5818529129,50.7646598816],"type":"Point"}
}