{
  "type": "Feature",
  "properties": {
    "iso:country":"DE",
    "sg:address":"Langgasse 1",
    "sg:city":"Hofheim",
    "sg:phone":"+49 6192/8893",
    "sg:postcode":"65719",
    "sg:province":"Hessen",
    "wof:name":"Sportivo Jeans Und Fashion Gmbh",
    "wof:placetype":"venue"
},
  "geometry": {"coordinates":[8.4444847107,50.0876274109],"type":"Point"}
}