{
  "type": "Feature",
  "properties": {
    "iso:country":"DE",
    "sg:address":"Austr. 2",
    "sg:city":"Wedel",
    "sg:phone":"+49 4103/4229",
    "sg:postcode":"22880",
    "sg:province":"Schleswig-Holstein",
    "wof:name":"Peter Schwarz Architekt",
    "wof:placetype":"venue"
},
  "geometry": {"coordinates":[9.69666,53.583153],"type":"Point"}
}