{
  "type": "Feature",
  "properties": {
    "iso:country":"DE",
    "sg:address":"Fritz-Schwerdtfeger-Weg 1",
    "sg:city":"Hannover",
    "sg:phone":"+49 511/651794",
    "sg:postcode":"30657",
    "sg:province":"Niedersachsen",
    "wof:name":"Dr. Wilfried Bungenstock Rechtsanwalt",
    "wof:placetype":"venue"
},
  "geometry": {"coordinates":[9.7981023788,52.4437599182],"type":"Point"}
}