{
  "type": "Feature",
  "properties": {
    "iso:country":"DE",
    "sg:address":"Sandweierer Str. 43",
    "sg:city":"Baden-Baden",
    "sg:phone":"+49 7221/60242",
    "sg:postcode":"76532",
    "sg:province":"Baden-W\u00fcrttemberg",
    "wof:name":"Sternen",
    "wof:placetype":"venue"
},
  "geometry": {"coordinates":[8.1953239441,48.8109779358],"type":"Point"}
}