{
  "type": "Feature",
  "properties": {
    "iso:country":"DE",
    "sg:address":"Tecklenburger Str. 24",
    "sg:city":"Lengerich",
    "sg:phone":"+49 5481/4051",
    "sg:postcode":"49525",
    "sg:province":"Nordrhein-Westfalen",
    "wof:name":"Martin Klose",
    "wof:placetype":"venue"
},
  "geometry": {"coordinates":[7.843866,52.192753],"type":"Point"}
}