{
  "type": "Feature",
  "properties": {
    "iso:country":"DE",
    "sg:address":"Demminer Str. 5",
    "sg:city":"Neubrandenburg",
    "sg:postcode":"17034",
    "sg:province":"Mecklenburg-Vorpommern",
    "wof:name":"Alpha-bau-controlling Gmbh",
    "wof:placetype":"venue"
},
  "geometry": {"coordinates":[13.269562,53.563019],"type":"Point"}
}