{
  "type": "Feature",
  "properties": {
    "iso:country":"DE",
    "sg:address":"Donizettistr. 5",
    "sg:city":"Stuttgart",
    "sg:postcode":"70195",
    "sg:province":"Baden-W\u00fcrttemberg",
    "wof:name":"Kleintierz\u00fcchter- Verein Botnang E. V.",
    "wof:placetype":"venue"
},
  "geometry": {"coordinates":[9.1205463409,48.7805137634],"type":"Point"}
}