{
  "type": "Feature",
  "properties": {
    "iso:country":"DE",
    "sg:address":"Landstr. 15",
    "sg:city":"Schw\u00f6rstadt",
    "sg:phone":"+49 7762/8755",
    "sg:postcode":"79739",
    "sg:province":"Baden-W\u00fcrttemberg",
    "wof:name":"Karl Asal",
    "wof:placetype":"venue"
},
  "geometry": {"coordinates":[7.8576312065,47.6151313782],"type":"Point"}
}