{
  "type": "Feature",
  "properties": {
    "iso:country":"DE",
    "sg:address":"V\u00f6lklinger Weg 69",
    "sg:city":"Frankfurt",
    "sg:postcode":"60529",
    "sg:province":"Hessen",
    "wof:name":"Auerbacher Gmbh",
    "wof:placetype":"venue"
},
  "geometry": {"coordinates":[8.5731859207,50.0842437744],"type":"Point"}
}