{
  "type": "Feature",
  "properties": {
    "iso:country":"DE",
    "sg:address":"Rosenhagen 18",
    "sg:city":"Hildesheim",
    "sg:phone":"+49 5121/31358",
    "sg:postcode":"31134",
    "sg:province":"Niedersachsen",
    "wof:name":"Dirk Freye Steuerberater",
    "wof:placetype":"venue"
},
  "geometry": {"coordinates":[9.9535360336,52.1546020508],"type":"Point"}
}