{
  "type": "Feature",
  "properties": {
    "iso:country":"DE",
    "sg:address":"Hagenstr. 7-9",
    "sg:city":"Frankfurt",
    "sg:phone":"+49 69/438546",
    "sg:postcode":"60314",
    "sg:province":"Hessen",
    "wof:name":"Erhard Schaller",
    "wof:placetype":"venue"
},
  "geometry": {"coordinates":[8.70971,50.110458],"type":"Point"}
}