{
  "type": "Feature",
  "properties": {
    "iso:country":"DE",
    "sg:address":"Neuenberger Str. 17",
    "sg:city":"Neuss",
    "sg:phone":"+49 2137/76133",
    "sg:postcode":"41470",
    "sg:province":"Nordrhein-Westfalen",
    "wof:name":"Klara Van Heese",
    "wof:placetype":"venue"
},
  "geometry": {"coordinates":[6.733942,51.126762],"type":"Point"}
}