{
  "type": "Feature",
  "properties": {
    "iso:country":"DE",
    "sg:address":"K\u00f6llertalstr. 17",
    "sg:city":"P\u00fcttlingen",
    "sg:phone":"+49 6898/964666",
    "sg:postcode":"66346",
    "sg:province":"Saarland",
    "wof:name":"Restaurant Merlin",
    "wof:placetype":"venue"
},
  "geometry": {"coordinates":[6.8868122101,49.2893562317],"type":"Point"}
}