{
  "type": "Feature",
  "properties": {
    "iso:country":"DE",
    "sg:address":"Marktplatz 15",
    "sg:city":"Bruck",
    "sg:phone":"+49 9434/3892",
    "sg:postcode":"92436",
    "sg:province":"Bayern",
    "wof:name":"Pizzeria San Remo",
    "wof:placetype":"venue"
},
  "geometry": {"coordinates":[12.3084793091,49.2504272461],"type":"Point"}
}