{
  "type": "Feature",
  "properties": {
    "iso:country":"DE",
    "sg:address":"Josephinenstr. 224",
    "sg:city":"Bochum",
    "sg:phone":"+49 234/850151",
    "sg:postcode":"44791",
    "sg:province":"Nordrhein-Westfalen",
    "wof:name":"Herbert Hutmacher",
    "wof:placetype":"venue"
},
  "geometry": {"coordinates":[7.248254776,51.4940872192],"type":"Point"}
}