{
  "type": "Feature",
  "properties": {
    "iso:country":"DE",
    "sg:address":"Westring 232",
    "sg:city":"Castrop-Rauxel",
    "sg:phone":"+49 2305/14952",
    "sg:postcode":"44579",
    "sg:province":"Nordrhein-Westfalen",
    "wof:name":"Lothar Lechleiter Verlags- Auslieferungen E. Kfm.",
    "wof:placetype":"venue"
},
  "geometry": {"coordinates":[7.28779,51.563099],"type":"Point"}
}