{
  "type": "Feature",
  "properties": {
    "iso:country":"DE",
    "sg:address":"Juri-Gagarin-Str. 2",
    "sg:city":"F\u00fcrstenwalde",
    "sg:phone":"+49 3361/33038",
    "sg:postcode":"15517",
    "sg:province":"Brandenburg",
    "wof:name":"Pizzeria Messina",
    "wof:placetype":"venue"
},
  "geometry": {"coordinates":[14.0732336044,52.3705482483],"type":"Point"}
}