{
  "type": "Feature",
  "properties": {
    "iso:country":"DE",
    "sg:address":"Burgenlandstr. 23",
    "sg:city":"Dresden",
    "sg:phone":"+49 351/2510551",
    "sg:postcode":"01279",
    "sg:province":"Sachsen",
    "wof:name":"Isolde Herold",
    "wof:placetype":"venue"
},
  "geometry": {"coordinates":[13.830143,51.025459],"type":"Point"}
}