{
  "type": "Feature",
  "properties": {
    "iso:country":"DE",
    "sg:address":"Schl\u00fcmersweg 19",
    "sg:city":"Hamminkeln",
    "sg:phone":"+49 2856/1226",
    "sg:postcode":"46499",
    "sg:province":"Nordrhein-Westfalen",
    "wof:name":"H. Boland",
    "wof:placetype":"venue"
},
  "geometry": {"coordinates":[6.639993,51.724861],"type":"Point"}
}