{
  "type": "Feature",
  "properties": {
    "iso:country":"DE",
    "sg:address":"Werniger\u00f6der Str.",
    "sg:city":"Benneckenstein",
    "sg:phone":"+49 39457/2264",
    "sg:postcode":"38877",
    "sg:province":"Sachsen-Anhalt",
    "wof:name":"Minol Tankstelle",
    "wof:placetype":"venue"
},
  "geometry": {"coordinates":[10.7160692215,51.6742782593],"type":"Point"}
}