{
  "type": "Feature",
  "properties": {
    "iso:country":"DE",
    "sg:address":"Rabenkamp 30",
    "sg:city":"Dinslaken",
    "sg:phone":"+49 2064/97617",
    "sg:postcode":"46539",
    "sg:province":"Nordrhein-Westfalen",
    "wof:name":"H. Ronig Automobil- Handels Gmbh",
    "wof:placetype":"venue"
},
  "geometry": {"coordinates":[6.7589259148,51.5654335022],"type":"Point"}
}