{
  "type": "Feature",
  "properties": {
    "iso:country":"DE",
    "sg:address":"Waldheimstr. 15",
    "sg:city":"Kierspe",
    "sg:phone":"+49 2359/2152",
    "sg:postcode":"58566",
    "sg:province":"Nordrhein-Westfalen",
    "wof:name":"Bernhard Salmon",
    "wof:placetype":"venue"
},
  "geometry": {"coordinates":[7.591102,51.123058],"type":"Point"}
}