{
  "type": "Feature",
  "properties": {
    "iso:country":"DE",
    "sg:address":"Grenayer Str. 10 a",
    "sg:city":"Glauchau",
    "sg:phone":"+49 3763/15196",
    "sg:postcode":"08371",
    "sg:province":"Sachsen",
    "wof:name":"Toom-baumarkt",
    "wof:placetype":"venue"
},
  "geometry": {"coordinates":[12.5156288147,50.8188514709],"type":"Point"}
}