{
  "type": "Feature",
  "properties": {
    "iso:country":"DE",
    "sg:address":"Residenzstr. 15",
    "sg:city":"Ansbach",
    "sg:phone":"+49 981/9776083",
    "sg:postcode":"91522",
    "sg:province":"Bayern",
    "wof:name":"Mcdonald's",
    "wof:placetype":"venue"
},
  "geometry": {"coordinates":[10.5673666,49.304775238],"type":"Point"}
}