{
  "type": "Feature",
  "properties": {
    "iso:country":"DE",
    "sg:address":"Hagensche Str. 64",
    "sg:city":"Lage",
    "sg:phone":"+49 5232/2610",
    "sg:postcode":"32791",
    "sg:province":"Nordrhein-Westfalen",
    "wof:name":"G. Cruel Inh. Bernd Cruel",
    "wof:placetype":"venue"
},
  "geometry": {"coordinates":[8.7969703674,52.003452301],"type":"Point"}
}