{
  "type": "Feature",
  "properties": {
    "iso:country":"DE",
    "sg:address":"Carl-Zuckmayer-Str. 24",
    "sg:city":"Mannheim",
    "sg:postcode":"68169",
    "sg:province":"Baden-W\u00fcrttemberg",
    "wof:name":"Kowalski-kurierdienst Gmbh",
    "wof:placetype":"venue"
},
  "geometry": {"coordinates":[8.476188,49.510372],"type":"Point"}
}