{
  "type": "Feature",
  "properties": {
    "iso:country":"DE",
    "sg:address":"Dauenser Str. 10c",
    "sg:city":"Varel",
    "sg:phone":"+49 4451/860947",
    "sg:postcode":"26316",
    "sg:province":"Niedersachsen",
    "wof:name":"Karl-heinz Kriesten",
    "wof:placetype":"venue"
},
  "geometry": {"coordinates":[8.1217098236,53.4462623596],"type":"Point"}
}