{
  "type": "Feature",
  "properties": {
    "iso:country":"DE",
    "sg:address":"Kreuzberger Ring 21",
    "sg:city":"Wiesbaden",
    "sg:phone":"+49 611/973300",
    "sg:postcode":"65205",
    "sg:province":"Hessen",
    "wof:name":"Bankbetriebswirtschaft Jacob & Partner",
    "wof:placetype":"venue"
},
  "geometry": {"coordinates":[8.2901229858,50.0547142029],"type":"Point"}
}