{
  "type": "Feature",
  "properties": {
    "iso:country":"DE",
    "sg:address":"Reichstalhalle",
    "sg:city":"Oberharmersbach",
    "sg:phone":"+49 7837",
    "sg:postcode":"77784",
    "sg:province":"Baden-W\u00fcrttemberg",
    "wof:name":"Tourismus E. V. Oberharmersbach",
    "wof:placetype":"venue"
},
  "geometry": {"coordinates":[8.1272392273,48.3738594055],"type":"Point"}
}