{
  "type": "Feature",
  "properties": {
    "iso:country":"DE",
    "sg:address":"Hauptstr. 6",
    "sg:city":"Osterhofen",
    "sg:phone":"+49 9932/95280",
    "sg:postcode":"94486",
    "sg:province":"Bayern",
    "wof:name":"Bay Wa Ag",
    "wof:placetype":"venue"
},
  "geometry": {"coordinates":[13.019036,48.702488],"type":"Point"}
}