{
  "type": "Feature",
  "properties": {
    "iso:country":"DE",
    "sg:address":"Seedorfer Str. 20",
    "sg:city":"Nortorf",
    "sg:phone":"+49 4392/2912",
    "sg:postcode":"24589",
    "sg:province":"Schleswig-Holstein",
    "wof:name":"Ernst Zakzzewski",
    "wof:placetype":"venue"
},
  "geometry": {"coordinates":[9.868716,54.169746],"type":"Point"}
}