{
  "type": "Feature",
  "properties": {
    "iso:country":"DE",
    "sg:address":"Wei\u00dfer Gasse 5",
    "sg:city":"Koblenz",
    "sg:phone":"+49 261/37653",
    "sg:postcode":"56068",
    "sg:province":"Rheinland-Pfalz",
    "wof:name":"Fritz R\u00f6ssel",
    "wof:placetype":"venue"
},
  "geometry": {"coordinates":[7.5926451683,50.3612976074],"type":"Point"}
}