{
  "type": "Feature",
  "properties": {
    "iso:country":"DE",
    "sg:address":"Karrstr. 29",
    "sg:city":"Wittlich",
    "sg:phone":"+49 6571/96286",
    "sg:postcode":"54516",
    "sg:province":"Rheinland-Pfalz",
    "wof:name":"Uwe Lucas",
    "wof:placetype":"venue"
},
  "geometry": {"coordinates":[6.8874588013,49.9847564697],"type":"Point"}
}