{
  "type": "Feature",
  "properties": {
    "iso:country":"DE",
    "sg:address":"Gl\u00fccksburger Str. 5a",
    "sg:city":"Bochum",
    "sg:phone":"+49 234/770303",
    "sg:postcode":"44799",
    "sg:province":"Nordrhein-Westfalen",
    "wof:name":"Industrie Maschinen Support Gmbh",
    "wof:placetype":"venue"
},
  "geometry": {"coordinates":[7.232276,51.451038],"type":"Point"}
}