{
  "type": "Feature",
  "properties": {
    "iso:country":"DE",
    "sg:address":"Querstr. 13",
    "sg:city":"G\u00fcstrow",
    "sg:phone":"+49 3843/211616",
    "sg:postcode":"18273",
    "sg:province":"Mecklenburg-Vorpommern",
    "wof:name":"Siegfried Kainert",
    "wof:placetype":"venue"
},
  "geometry": {"coordinates":[12.180398941,53.7994651794],"type":"Point"}
}