{
  "type": "Feature",
  "properties": {
    "iso:country":"DE",
    "sg:address":"Stolberger Str. 3",
    "sg:city":"K\u00f6ln",
    "sg:phone":"+49 221/9545811",
    "sg:postcode":"50933",
    "sg:province":"Nordrhein-Westfalen",
    "wof:name":"Valve-hearts, Audiophile Tonaufnahmen In R\u00f6hrentechnik",
    "wof:placetype":"venue"
},
  "geometry": {"coordinates":[6.9075160027,50.9416351318],"type":"Point"}
}