{
  "type": "Feature",
  "properties": {
    "iso:country":"DE",
    "sg:address":"Leipziger Str. 187",
    "sg:city":"Kassel",
    "sg:phone":"+49 561/572191",
    "sg:postcode":"34123",
    "sg:province":"Hessen",
    "wof:name":"Elke Dumeier",
    "wof:placetype":"venue"
},
  "geometry": {"coordinates":[9.528995,51.305138],"type":"Point"}
}