{
  "type": "Feature",
  "properties": {
    "iso:country":"DE",
    "sg:address":"Adenauerstr. 21",
    "sg:city":"Altenbeken",
    "sg:phone":"+49 5255/930850",
    "sg:postcode":"33184",
    "sg:province":"Nordrhein-Westfalen",
    "wof:name":"Rewe-markt M\u00fcller Ohg",
    "wof:placetype":"venue"
},
  "geometry": {"coordinates":[8.933008194,51.7644462585],"type":"Point"}
}