{
  "type": "Feature",
  "properties": {
    "iso:country":"DE",
    "sg:address":"Fuststr. 25",
    "sg:city":"M\u00fcnchen",
    "sg:phone":"+49 89/156533",
    "sg:postcode":"80638",
    "sg:province":"Bayern",
    "wof:name":"Rudolf Koch Architekt",
    "wof:placetype":"venue"
},
  "geometry": {"coordinates":[11.51754,48.165237],"type":"Point"}
}