{
  "type": "Feature",
  "properties": {
    "iso:country":"DE",
    "sg:address":"Hartungstr. 1a",
    "sg:city":"Ellrich",
    "sg:phone":"+49 36332/20793",
    "sg:postcode":"99755",
    "sg:province":"Th\u00fcringen",
    "wof:name":"Reiner Schmitt",
    "wof:placetype":"venue"
},
  "geometry": {"coordinates":[10.6690273285,51.5841560364],"type":"Point"}
}