{
  "type": "Feature",
  "properties": {
    "iso:country":"DE",
    "sg:address":"Friedrich-H\u00f6lscher-Str. 450",
    "sg:city":"Dortmund",
    "sg:phone":"+49 231/233053",
    "sg:postcode":"44328",
    "sg:province":"Nordrhein-Westfalen",
    "wof:name":"Manfred Haase",
    "wof:placetype":"venue"
},
  "geometry": {"coordinates":[7.5118298531,51.5449714661],"type":"Point"}
}