{
  "type": "Feature",
  "properties": {
    "iso:country":"DE",
    "sg:address":"Ferdinand-Jost-Str. 54",
    "sg:city":"Leipzig",
    "sg:phone":"+49 341/8622373",
    "sg:postcode":"04299",
    "sg:province":"Sachsen",
    "wof:name":"M\u00e4dison Gmbh",
    "wof:placetype":"venue"
},
  "geometry": {"coordinates":[12.4216880798,51.3209762573],"type":"Point"}
}