{
  "type": "Feature",
  "properties": {
    "iso:country":"DE",
    "sg:address":"Wikingerstr. 49",
    "sg:city":"K\u00f6ln",
    "sg:phone":"+49 221/863382",
    "sg:postcode":"51107",
    "sg:province":"Nordrhein-Westfalen",
    "wof:name":"Malerwerkst\u00e4tte J\u00fcrgen Weber Gmbh",
    "wof:placetype":"venue"
},
  "geometry": {"coordinates":[7.074378,50.917423],"type":"Point"}
}