{
  "type": "Feature",
  "properties": {
    "iso:country":"DE",
    "sg:address":"Lahnweg 3",
    "sg:city":"Fachbach",
    "sg:phone":"+49 2603/13064",
    "sg:postcode":"56133",
    "sg:province":"Rheinland-Pfalz",
    "wof:name":"Maschinenbau Burkhard Gmbh",
    "wof:placetype":"venue"
},
  "geometry": {"coordinates":[7.689515,50.337639],"type":"Point"}
}