{
  "type": "Feature",
  "properties": {
    "iso:country":"DE",
    "sg:address":"Mainzer Str. 27",
    "sg:city":"Worms",
    "sg:phone":"+49 6241/44229",
    "sg:postcode":"67547",
    "sg:province":"Rheinland-Pfalz",
    "wof:name":"Liebfrauen-apotheke",
    "wof:placetype":"venue"
},
  "geometry": {"coordinates":[8.364102,49.637165],"type":"Point"}
}