{
  "type": "Feature",
  "properties": {
    "iso:country":"DE",
    "sg:address":"Manfred-von-Richthofen-Str. 15",
    "sg:city":"Berlin",
    "sg:phone":"+49 30/7866965",
    "sg:postcode":"12101",
    "sg:province":"Berlin",
    "wof:name":"Rex Tier-freund",
    "wof:placetype":"venue"
},
  "geometry": {"coordinates":[13.382533,52.483074],"type":"Point"}
}