{
  "type": "Feature",
  "properties": {
    "iso:country":"DE",
    "sg:address":"Limmerstr. 82",
    "sg:city":"Hannover",
    "sg:phone":"+49 511/2101542",
    "sg:postcode":"30451",
    "sg:province":"Niedersachsen",
    "wof:name":"Rudolf Wedekin",
    "wof:placetype":"venue"
},
  "geometry": {"coordinates":[9.703483,52.374882],"type":"Point"}
}