{
  "type": "Feature",
  "properties": {
    "iso:country":"DE",
    "sg:address":"Malvenweg 9",
    "sg:city":"Gablingen",
    "sg:phone":"+49 8230/1606",
    "sg:postcode":"86456",
    "sg:province":"Bayern",
    "wof:name":"Werma-bautr\u00e4ger Und Baubetreuer",
    "wof:placetype":"venue"
},
  "geometry": {"coordinates":[10.800072,48.442451],"type":"Point"}
}