{
  "type": "Feature",
  "properties": {
    "iso:country":"DE",
    "sg:address":"Hertichstr 37",
    "sg:city":"Leonberg",
    "sg:phone":"+49 7152/358503",
    "sg:postcode":"71229",
    "sg:province":"Baden-W\u00fcrttemberg",
    "wof:name":"Buhl Elektrotechnik Gmbh",
    "wof:placetype":"venue"
},
  "geometry": {"coordinates":[9.000708,48.786427],"type":"Point"}
}