{
  "type": "Feature",
  "properties": {
    "iso:country":"DE",
    "sg:address":"Dr.-Wilhelm-K\u00fclz-Str. 4",
    "sg:city":"Saalfeld",
    "sg:phone":"+49 3671/35397",
    "sg:postcode":"07318",
    "sg:province":"Th\u00fcringen",
    "wof:name":"Rudi Rei\u00dfmann",
    "wof:placetype":"venue"
},
  "geometry": {"coordinates":[11.357008,50.646202],"type":"Point"}
}