{
  "type": "Feature",
  "properties": {
    "iso:country":"DE",
    "sg:address":"Bismarckstr. 16",
    "sg:city":"V\u00f6lklingen",
    "sg:phone":"+49 6898/24131",
    "sg:postcode":"66333",
    "sg:province":"Saarland",
    "wof:name":"M. Schuler",
    "wof:placetype":"venue"
},
  "geometry": {"coordinates":[6.853821,49.251019],"type":"Point"}
}