{
  "type": "Feature",
  "properties": {
    "iso:country":"DE",
    "sg:address":"Sangerhauser Str. 8",
    "sg:city":"Bremen",
    "sg:phone":"+49 421/446641",
    "sg:postcode":"28329",
    "sg:province":"Bremen",
    "wof:name":"Renate Kaminski Immobilien",
    "wof:placetype":"venue"
},
  "geometry": {"coordinates":[8.8899002075,53.08020401],"type":"Point"}
}