{
  "type": "Feature",
  "properties": {
    "iso:country":"DE",
    "sg:address":"Fuchspfad 6",
    "sg:city":"Monheim",
    "sg:phone":"+49 2173/52983",
    "sg:postcode":"40789",
    "sg:province":"Nordrhein-Westfalen",
    "wof:name":"Alfred Skworz",
    "wof:placetype":"venue"
},
  "geometry": {"coordinates":[6.9047818184,51.0956764221],"type":"Point"}
}