{
  "type": "Feature",
  "properties": {
    "iso:country":"DE",
    "sg:address":"Rolandstr. 9",
    "sg:city":"Essen",
    "sg:phone":"+49 201/81004130",
    "sg:postcode":"45128",
    "sg:province":"Nordrhein-Westfalen",
    "wof:name":"Ma- Akademie Verlags Gmbh",
    "wof:placetype":"venue"
},
  "geometry": {"coordinates":[7.0125508308,51.4480400085],"type":"Point"}
}