{
  "type": "Feature",
  "properties": {
    "iso:country":"DE",
    "sg:address":"Itteler Str.",
    "sg:city":"Welschbillig",
    "sg:phone":"+49 6506/268",
    "sg:postcode":"54298",
    "sg:province":"Rheinland-Pfalz",
    "wof:name":"Kath. Pfarramt St. Dionysius",
    "wof:placetype":"venue"
},
  "geometry": {"coordinates":[6.6228499413,49.8675308228],"type":"Point"}
}