{
  "type": "Feature",
  "properties": {
    "iso:country":"DE",
    "sg:address":"Heerenholz 9",
    "sg:city":"Bremen",
    "sg:phone":"+49 421/438780",
    "sg:postcode":"28307",
    "sg:province":"Bremen",
    "wof:name":"Walter Ruff Gmbh",
    "wof:placetype":"venue"
},
  "geometry": {"coordinates":[8.9623985291,53.0451774597],"type":"Point"}
}