{
  "type": "Feature",
  "properties": {
    "iso:country":"DE",
    "sg:address":"In Steckenborn 54",
    "sg:city":"Simmerath",
    "sg:phone":"+49 2473/2986",
    "sg:postcode":"52152",
    "sg:province":"Nordrhein-Westfalen",
    "wof:name":"Emil Jung",
    "wof:placetype":"venue"
},
  "geometry": {"coordinates":[6.353959,50.626453],"type":"Point"}
}