{
  "type": "Feature",
  "properties": {
    "iso:country":"DE",
    "sg:address":"Okenstr. 38",
    "sg:city":"Jena",
    "sg:phone":"+49 3641/616356",
    "sg:postcode":"07745",
    "sg:province":"Th\u00fcringen",
    "wof:name":"Reichmann Vertriebs Gmbh",
    "wof:placetype":"venue"
},
  "geometry": {"coordinates":[11.570619,50.924782],"type":"Point"}
}