{
  "type": "Feature",
  "properties": {
    "iso:country":"DE",
    "sg:address":"Rabelsacker 7",
    "sg:city":"Heiligkreuzsteinach",
    "sg:phone":"+49 6220/8597",
    "sg:postcode":"69253",
    "sg:province":"Baden-W\u00fcrttemberg",
    "wof:name":"Norbert Knorreck Verlagsvertreter",
    "wof:placetype":"venue"
},
  "geometry": {"coordinates":[8.794911,49.488705],"type":"Point"}
}