{
  "type": "Feature",
  "properties": {
    "iso:country":"DE",
    "sg:address":"Waldstr. 3",
    "sg:city":"Walld\u00fcrn",
    "sg:phone":"+49 4962/8292450",
    "sg:postcode":"74731",
    "sg:province":"Baden-W\u00fcrttemberg",
    "wof:name":"Nagel Metallbau Gmbh",
    "wof:placetype":"venue"
},
  "geometry": {"coordinates":[9.362699,49.572922],"type":"Point"}
}