{
  "type": "Feature",
  "properties": {
    "iso:country":"DE",
    "sg:address":"Hofstattstr. 17",
    "sg:city":"Willst\u00e4tt",
    "sg:phone":"+49 7854/980671",
    "sg:postcode":"77731",
    "sg:province":"Baden-W\u00fcrttemberg",
    "wof:name":"S & L Kommunikationstechnik",
    "wof:placetype":"venue"
},
  "geometry": {"coordinates":[7.8567838669,48.5293083191],"type":"Point"}
}