{
  "type": "Feature",
  "properties": {
    "iso:country":"DE",
    "sg:address":"An der K\u00f6hlerei 5",
    "sg:city":"Marktheidenfeld",
    "sg:phone":"+49 9391/5151",
    "sg:postcode":"97828",
    "sg:province":"Bayern",
    "wof:name":"Helmut H\u00e4ufgl\u00f6ckner Ingenieur",
    "wof:placetype":"venue"
},
  "geometry": {"coordinates":[9.6009960175,49.8547286987],"type":"Point"}
}