{
  "type": "Feature",
  "properties": {
    "iso:country":"DE",
    "sg:address":"Staudingerstr. 26",
    "sg:city":"Hamburg",
    "sg:phone":"+49 40/829401",
    "sg:postcode":"22607",
    "sg:province":"Hamburg",
    "wof:name":"Andreas Rischar Rechtsanwalt",
    "wof:placetype":"venue"
},
  "geometry": {"coordinates":[9.8721551895,53.569152832],"type":"Point"}
}