{
  "type": "Feature",
  "properties": {
    "iso:country":"DE",
    "sg:address":"Beethovenstr. 5",
    "sg:city":"Finsterwalde",
    "sg:phone":"+49 3531/3343",
    "sg:postcode":"03238",
    "sg:province":"Brandenburg",
    "wof:name":"Pension-restaurant Die S\u00e4nger Von Finsterwalde",
    "wof:placetype":"venue"
},
  "geometry": {"coordinates":[13.702252388,51.6398963928],"type":"Point"}
}