{
  "type": "Feature",
  "properties": {
    "iso:country":"DE",
    "sg:address":"Kornstr. 2",
    "sg:city":"Helmstedt",
    "sg:phone":"+49 5351",
    "sg:postcode":"38350",
    "sg:province":"Niedersachsen",
    "wof:name":"Volksbank Helmstedt Eg",
    "wof:placetype":"venue"
},
  "geometry": {"coordinates":[11.0103673935,52.2272720337],"type":"Point"}
}