{
  "type": "Feature",
  "properties": {
    "iso:country":"DE",
    "sg:address":"Stettenwinkel 2",
    "sg:city":"H\u00fcfingen",
    "sg:phone":"+49 771/92160",
    "sg:postcode":"78183",
    "sg:province":"Baden-W\u00fcrttemberg",
    "wof:name":"Lidl Gmbh & Co. Kg",
    "wof:placetype":"venue"
},
  "geometry": {"coordinates":[8.4755811691,47.9262390137],"type":"Point"}
}