{
  "type": "Feature",
  "properties": {
    "iso:country":"DE",
    "sg:address":"Amtsfreiheit 6",
    "sg:city":"Moringen",
    "sg:phone":"+49 5554/2445",
    "sg:postcode":"37186",
    "sg:province":"Niedersachsen",
    "wof:name":"Sozialstation Hardegsen Moringen N\u00f6rten Hardenberg",
    "wof:placetype":"venue"
},
  "geometry": {"coordinates":[9.870168,51.69783],"type":"Point"}
}