{
  "type": "Feature",
  "properties": {
    "iso:country":"DE",
    "sg:address":"Cretzschmarstr. 23",
    "sg:city":"Frankfurt",
    "sg:phone":"+49 69/779981",
    "sg:postcode":"60487",
    "sg:province":"Hessen",
    "wof:name":"Robert G\u00f6llner",
    "wof:placetype":"venue"
},
  "geometry": {"coordinates":[8.6530828476,50.1285667419],"type":"Point"}
}