{
  "type": "Feature",
  "properties": {
    "iso:country":"DE",
    "sg:address":"Planie 20",
    "sg:city":"Reutlingen",
    "sg:postcode":"72764",
    "sg:province":"Baden-W\u00fcrttemberg",
    "wof:name":"Deutscher Hausfrauenbund Ortsverband Rtlg.",
    "wof:placetype":"venue"
},
  "geometry": {"coordinates":[9.2182741165,48.4924697876],"type":"Point"}
}