{
  "type": "Feature",
  "properties": {
    "iso:country":"DE",
    "sg:address":"Waldseer Str. 74",
    "sg:city":"Schifferstadt",
    "sg:phone":"+49 6235/3278",
    "sg:postcode":"67105",
    "sg:province":"Rheinland-Pfalz",
    "wof:name":"D. Und W. D\u00fcrphold",
    "wof:placetype":"venue"
},
  "geometry": {"coordinates":[8.386505127,49.3837394714],"type":"Point"}
}