{
  "type": "Feature",
  "properties": {
    "iso:country":"DE",
    "sg:address":"Am Fuchsberg 5-7",
    "sg:city":"Magdeburg",
    "sg:phone":"+49 391/628850",
    "sg:postcode":"39112",
    "sg:province":"Sachsen-Anhalt",
    "wof:name":"Ehle Industrie- Und Fahrzeugtechnik",
    "wof:placetype":"venue"
},
  "geometry": {"coordinates":[11.617799,52.112789],"type":"Point"}
}