{
  "type": "Feature",
  "properties": {
    "iso:country":"DE",
    "sg:address":"Eilendorfer Str. 181",
    "sg:city":"Aachen",
    "sg:phone":"+49 241/928190",
    "sg:postcode":"52078",
    "sg:province":"Nordrhein-Westfalen",
    "wof:name":"Aytex Textil-vertriebs Gmbh",
    "wof:placetype":"venue"
},
  "geometry": {"coordinates":[6.1715831757,50.7594871521],"type":"Point"}
}