{
  "type": "Feature",
  "properties": {
    "iso:country":"DE",
    "sg:address":"Lindenstra\u00dfe 64",
    "sg:city":"Ergolding",
    "sg:postcode":"84030",
    "sg:province":"Bayern",
    "wof:name":"Steuerberater Karlsruhe",
    "wof:placetype":"venue"
},
  "geometry": {"coordinates":[12.165089,48.574638],"type":"Point"}
}