{
  "type": "Feature",
  "properties": {
    "iso:country":"DE",
    "sg:address":"Kulmbacher Str. 5",
    "sg:city":"M\u00fcnchberg",
    "sg:phone":"+49 9251/850870",
    "sg:postcode":"95213",
    "sg:province":"Bayern",
    "wof:name":"Eichh\u00f6rnchen - Naturwaren",
    "wof:placetype":"venue"
},
  "geometry": {"coordinates":[11.7880239487,50.1911277771],"type":"Point"}
}