{
  "type": "Feature",
  "properties": {
    "iso:country":"DE",
    "sg:address":"Max-Adrion-Str. 1",
    "sg:city":"Neubrandenburg",
    "sg:phone":"+49 395/4691873",
    "sg:postcode":"17034",
    "sg:province":"Mecklenburg-Vorpommern",
    "wof:name":"Iris-apotheke B. Kreisel E. K.",
    "wof:placetype":"venue"
},
  "geometry": {"coordinates":[13.280328,53.576477],"type":"Point"}
}