{
  "type": "Feature",
  "properties": {
    "iso:country":"DE",
    "sg:address":"Gr\u00fctenstieg 14",
    "sg:city":"Salzgitter",
    "sg:phone":"+49 5341/91245",
    "sg:postcode":"38259",
    "sg:province":"Niedersachsen",
    "wof:name":"Ernst Dieterich",
    "wof:placetype":"venue"
},
  "geometry": {"coordinates":[10.441217,52.062489],"type":"Point"}
}