{
  "type": "Feature",
  "properties": {
    "iso:country":"DE",
    "sg:address":"Sonnenhalde 8",
    "sg:city":"Isny",
    "sg:phone":"+49 7562/3627",
    "sg:postcode":"88316",
    "sg:province":"Baden-W\u00fcrttemberg",
    "wof:name":"Hans-georg Schmitz Architekt",
    "wof:placetype":"venue"
},
  "geometry": {"coordinates":[10.038677,47.685776],"type":"Point"}
}