{
  "type": "Feature",
  "properties": {
    "iso:country":"DE",
    "sg:address":"Johannes-Scheele-Str 17",
    "sg:city":"Finnentrop",
    "sg:phone":"+49 2721/979121",
    "sg:postcode":"57413",
    "sg:province":"Nordrhein-Westfalen",
    "wof:name":"Ars Zerspanungstechnik Ohg",
    "wof:placetype":"venue"
},
  "geometry": {"coordinates":[7.978432,51.165104],"type":"Point"}
}