{
  "type": "Feature",
  "properties": {
    "iso:country":"DE",
    "sg:address":"Hemmstr. 295",
    "sg:city":"Bremen",
    "sg:phone":"+49 421/351585",
    "sg:postcode":"28215",
    "sg:province":"Bremen",
    "wof:name":"Gastst\u00e4tte D\u00f6ntjes",
    "wof:placetype":"venue"
},
  "geometry": {"coordinates":[8.8116111755,53.0969085693],"type":"Point"}
}