{
  "type": "Feature",
  "properties": {
    "iso:country":"DE",
    "sg:address":"Allewindstr. 7",
    "sg:city":"Gundelfingen",
    "sg:phone":"+49 9073/7086",
    "sg:postcode":"89423",
    "sg:province":"Bayern",
    "wof:name":"Colorado Farben Und Lacke Gmbh",
    "wof:placetype":"venue"
},
  "geometry": {"coordinates":[10.366871,48.546249],"type":"Point"}
}