{
  "type": "Feature",
  "properties": {
    "iso:country":"DE",
    "sg:address":"Dammstr. 12",
    "sg:city":"Ludwigshafen",
    "sg:phone":"+49 621/517272",
    "sg:postcode":"67059",
    "sg:province":"Rheinland-Pfalz",
    "wof:name":"Pf\u00e4lzer Hof",
    "wof:placetype":"venue"
},
  "geometry": {"coordinates":[8.4486131668,49.478187561],"type":"Point"}
}