{
  "type": "Feature",
  "properties": {
    "iso:country":"DE",
    "sg:address":"Markt 21",
    "sg:city":"Sch\u00f6nebeck",
    "sg:phone":"+49 3928/403566",
    "sg:postcode":"39218",
    "sg:province":"Sachsen-Anhalt",
    "wof:name":"Heiko Rosig Notariat",
    "wof:placetype":"venue"
},
  "geometry": {"coordinates":[11.7385931015,52.0213508606],"type":"Point"}
}