{
  "type": "Feature",
  "properties": {
    "iso:country":"DE",
    "sg:address":"Varrentrappstr.",
    "sg:city":"Braunschweig",
    "sg:phone":"+49 931/250270",
    "sg:postcode":"38114",
    "sg:province":"Niedersachsen",
    "wof:name":"Grosse Gmbh",
    "wof:placetype":"venue"
},
  "geometry": {"coordinates":[10.5063495636,52.280380249],"type":"Point"}
}