{
  "type": "Feature",
  "properties": {
    "iso:country":"DE",
    "sg:address":"Aichaer Tal 4",
    "sg:city":"Happurg",
    "sg:phone":"+49 9151/3207",
    "sg:postcode":"91230",
    "sg:province":"Bayern",
    "wof:name":"Albachtaler Hof",
    "wof:placetype":"venue"
},
  "geometry": {"coordinates":[11.5047721863,49.4781684875],"type":"Point"}
}