{
  "type": "Feature",
  "properties": {
    "iso:country":"DE",
    "sg:address":"Dr.-Hans-B\u00f6ckler-Str. 7",
    "sg:city":"Gr\u00fcnstadt",
    "sg:phone":"+49 6359/85177",
    "sg:postcode":"67269",
    "sg:province":"Rheinland-Pfalz",
    "wof:name":"H. R. Ott",
    "wof:placetype":"venue"
},
  "geometry": {"coordinates":[8.168365,49.572327],"type":"Point"}
}