{
  "type": "Feature",
  "properties": {
    "iso:country":"DE",
    "sg:address":"Sandh\u00f6rn 2",
    "sg:city":"Gro\u00dfenkneten",
    "sg:phone":"+49 4435/1383",
    "sg:postcode":"26197",
    "sg:province":"Niedersachsen",
    "wof:name":"W. Br\u00f6mstrup",
    "wof:placetype":"venue"
},
  "geometry": {"coordinates":[8.225262,52.896961],"type":"Point"}
}