{
  "type": "Feature",
  "properties": {
    "iso:country":"DE",
    "sg:address":"Kaiserstr. 92",
    "sg:city":"Kiel",
    "sg:phone":"+49 431/77870",
    "sg:postcode":"24143",
    "sg:province":"Schleswig-Holstein",
    "wof:name":"Intert\u00fcrkspor",
    "wof:placetype":"venue"
},
  "geometry": {"coordinates":[10.1446619034,54.3084182739],"type":"Point"}
}