{
  "type": "Feature",
  "properties": {
    "iso:country":"DE",
    "sg:address":"Bahnhofstr. 5",
    "sg:city":"Laufen",
    "sg:phone":"+49 8682/470",
    "sg:postcode":"83410",
    "sg:province":"Bayern",
    "wof:name":"G. Noppinger",
    "wof:placetype":"venue"
},
  "geometry": {"coordinates":[12.926562,47.935677],"type":"Point"}
}