{
  "type": "Feature",
  "properties": {
    "iso:country":"DE",
    "sg:address":"Hauptstr. 48",
    "sg:city":"Karben",
    "sg:phone":"+49 6039/95820",
    "sg:postcode":"61184",
    "sg:province":"Hessen",
    "wof:name":"Uwe Bieber",
    "wof:placetype":"venue"
},
  "geometry": {"coordinates":[8.757109,50.250923],"type":"Point"}
}