{
  "type": "Feature",
  "properties": {
    "iso:country":"DE",
    "sg:address":"Poststr. 2",
    "sg:city":"Heidelberg",
    "sg:phone":"+49 6221/97990",
    "sg:postcode":"69115",
    "sg:province":"Baden-W\u00fcrttemberg",
    "wof:name":"Bau Und Partner Rechtsanw\u00e4lte",
    "wof:placetype":"venue"
},
  "geometry": {"coordinates":[8.6842803955,49.4077682495],"type":"Point"}
}