{
  "type": "Feature",
  "properties": {
    "iso:country":"DE",
    "sg:address":"K\u00f6lner Str. 45",
    "sg:city":"Essen",
    "sg:phone":"+49 201/756603",
    "sg:postcode":"45145",
    "sg:province":"Nordrhein-Westfalen",
    "wof:name":"Hermann Himmelberg",
    "wof:placetype":"venue"
},
  "geometry": {"coordinates":[6.9720129967,51.4477043152],"type":"Point"}
}