{
  "type": "Feature",
  "properties": {
    "iso:country":"DE",
    "sg:address":"Waldh\u00e4user Str. 112",
    "sg:city":"Aalen",
    "sg:phone":"+49 7361/8600",
    "sg:postcode":"73432",
    "sg:province":"Baden-W\u00fcrttemberg",
    "wof:name":"Vereinsgastst\u00e4tte Miniatur- Golfclub Unterkochen E. V.",
    "wof:placetype":"venue"
},
  "geometry": {"coordinates":[10.1426229477,48.8165054321],"type":"Point"}
}