{
  "type": "Feature",
  "properties": {
    "iso:country":"DE",
    "sg:address":"Wilhelmstr. 55",
    "sg:city":"Altenkirchen",
    "sg:phone":"+49 2681/2611",
    "sg:postcode":"57610",
    "sg:province":"Rheinland-Pfalz",
    "wof:name":"Ringfoto Inh. J\u00fcrgen Klein",
    "wof:placetype":"venue"
},
  "geometry": {"coordinates":[7.6426339149,50.6862640381],"type":"Point"}
}