{
  "type": "Feature",
  "properties": {
    "iso:country":"DE",
    "sg:address":"Waldstr. 30",
    "sg:city":"Aichwald",
    "sg:phone":"+49 711/361466",
    "sg:postcode":"73773",
    "sg:province":"Baden-W\u00fcrttemberg",
    "wof:name":"Albert Fuchs Gmbh",
    "wof:placetype":"venue"
},
  "geometry": {"coordinates":[9.3800516129,48.7494277954],"type":"Point"}
}