{
  "type": "Feature",
  "properties": {
    "iso:country":"DE",
    "sg:address":"Rheinstr. 5",
    "sg:city":"Geilenkirchen",
    "sg:phone":"+49 2451/659960",
    "sg:postcode":"52511",
    "sg:province":"Nordrhein-Westfalen",
    "wof:name":"Bauart Projekt Gmbh",
    "wof:placetype":"venue"
},
  "geometry": {"coordinates":[6.134158,50.961658],"type":"Point"}
}