{
  "type": "Feature",
  "properties": {
    "iso:country":"DE",
    "sg:address":"Rethelstr. 3",
    "sg:city":"W\u00fcrselen",
    "sg:phone":"+49 2405/72123",
    "sg:postcode":"52146",
    "sg:province":"Nordrhein-Westfalen",
    "wof:name":"Georg Keil Ingenieur",
    "wof:placetype":"venue"
},
  "geometry": {"coordinates":[6.1691031456,50.8237113953],"type":"Point"}
}