{
  "type": "Feature",
  "properties": {
    "iso:country":"DE",
    "sg:address":"Beim Steinbruch 3",
    "sg:city":"Altdorf",
    "sg:phone":"+49 9187/5013",
    "sg:postcode":"90518",
    "sg:province":"Bayern",
    "wof:name":"J\u00fcrgen Frauenknecht Gmbh",
    "wof:placetype":"venue"
},
  "geometry": {"coordinates":[11.36174,49.374146],"type":"Point"}
}