{
  "type": "Feature",
  "properties": {
    "iso:country":"DE",
    "sg:address":"Worphauser Landstr. 83",
    "sg:city":"Lilienthal",
    "sg:phone":"+49 4792/310646",
    "sg:postcode":"28865",
    "sg:province":"Niedersachsen",
    "wof:name":"H. Mehrtens",
    "wof:placetype":"venue"
},
  "geometry": {"coordinates":[8.932743,53.202393],"type":"Point"}
}