{
  "type": "Feature",
  "properties": {
    "iso:country":"DE",
    "sg:address":"Ostrower Damm 2",
    "sg:city":"Cottbus",
    "sg:postcode":"03046",
    "sg:province":"Brandenburg",
    "wof:name":"Automatisierungsanlagen",
    "wof:placetype":"venue"
},
  "geometry": {"coordinates":[14.340668,51.754726],"type":"Point"}
}