{
  "type": "Feature",
  "properties": {
    "iso:country":"DE",
    "sg:address":"Gewerbestr 5",
    "sg:city":"Langenhessen",
    "sg:phone":"+49 3761/3587",
    "sg:postcode":"08439",
    "wof:name":"Heine Brunnen Und Rohrleitungsbaugesellschaft Mbh",
    "wof:placetype":"venue"
},
  "geometry": {"coordinates":[12.3690795898,50.7560348511],"type":"Point"}
}