{
  "type": "Feature",
  "properties": {
    "iso:country":"DE",
    "sg:address":"Eutiner Landstra\u00dfe 18",
    "sg:city":"Gro\u00df Meinsdorf",
    "sg:phone":"+49 4521/2842",
    "sg:postcode":"23701",
    "sg:province":"Schleswig-Holstein",
    "wof:name":"Dierk Schlotfeldt - Technik Service F\u00fcr Haus & Bau",
    "wof:placetype":"venue"
},
  "geometry": {"coordinates":[10.6108560562,54.1079521179],"type":"Point"}
}