{
  "type": "Feature",
  "properties": {
    "iso:country":"DE",
    "sg:address":"G\u00fcntzelstr. 55",
    "sg:city":"Berlin",
    "sg:phone":"+49 30/8732700",
    "sg:postcode":"10717",
    "sg:province":"Berlin",
    "wof:name":"Versicherungsagentur Am Adac-haus",
    "wof:placetype":"venue"
},
  "geometry": {"coordinates":[13.3300619125,52.4907112122],"type":"Point"}
}