{
  "type": "Feature",
  "properties": {
    "iso:country":"DE",
    "sg:address":"Hauptstr. 67",
    "sg:city":"Armsheim",
    "sg:phone":"+49 6734/212",
    "sg:postcode":"55288",
    "sg:province":"Rheinland-Pfalz",
    "wof:name":"Bauernverein Armsheim- Schimsheim",
    "wof:placetype":"venue"
},
  "geometry": {"coordinates":[8.0575723648,49.8104019165],"type":"Point"}
}