{
  "type": "Feature",
  "properties": {
    "iso:country":"DE",
    "sg:address":"M\u00fchlenkamp 62",
    "sg:city":"Barsbek",
    "sg:phone":"+49 4344/1366",
    "sg:postcode":"24217",
    "sg:province":"Schleswig-Holstein",
    "wof:name":"A. Schlabritz",
    "wof:placetype":"venue"
},
  "geometry": {"coordinates":[10.322299,54.404312],"type":"Point"}
}