{
  "type": "Feature",
  "properties": {
    "iso:country":"DE",
    "sg:address":"Landsberger Str. 37",
    "sg:city":"Gilching",
    "sg:phone":"+49 8105/25081",
    "sg:postcode":"82205",
    "sg:province":"Bayern",
    "wof:name":"Franz-peter Kiendl",
    "wof:placetype":"venue"
},
  "geometry": {"coordinates":[11.2932710648,48.1008453369],"type":"Point"}
}