{
  "type": "Feature",
  "properties": {
    "iso:country":"DE",
    "sg:address":"Markusstr. 44",
    "sg:city":"Bonn",
    "sg:phone":"+49 228/234908",
    "sg:postcode":"53129",
    "sg:province":"Nordrhein-Westfalen",
    "wof:name":"Carl M\u00fcller Ohg",
    "wof:placetype":"venue"
},
  "geometry": {"coordinates":[7.1115088463,50.7159500122],"type":"Point"}
}