{
  "type": "Feature",
  "properties": {
    "iso:country":"DE",
    "sg:address":"Obere Kaiserstr. 6",
    "sg:city":"Siegen",
    "sg:phone":"+49 271/85091",
    "sg:postcode":"57078",
    "sg:province":"Nordrhein-Westfalen",
    "wof:name":"Panopa Logistik Gmbh & Co. Kg",
    "wof:placetype":"venue"
},
  "geometry": {"coordinates":[8.0142278671,50.9184646606],"type":"Point"}
}