{
  "type": "Feature",
  "properties": {
    "iso:country":"DE",
    "sg:address":"G\u00fctersloher Str. 26",
    "sg:city":"Verl",
    "sg:phone":"+49 5246/925010",
    "sg:postcode":"33415",
    "sg:province":"Nordrhein-Westfalen",
    "wof:name":"Berenbrinker Ohg",
    "wof:placetype":"venue"
},
  "geometry": {"coordinates":[8.5043077469,51.8815841675],"type":"Point"}
}