{
  "type": "Feature",
  "properties": {
    "iso:country":"DE",
    "sg:address":"Hanauer Landstr. 17",
    "sg:city":"Frankfurt",
    "sg:phone":"+49 69/94419890",
    "sg:postcode":"60314",
    "sg:province":"Hessen",
    "wof:name":"Nemec Und Sch\u00fctz Rechtsanw\u00e4lte",
    "wof:placetype":"venue"
},
  "geometry": {"coordinates":[8.6974143982,50.1135101318],"type":"Point"}
}