{
  "type": "Feature",
  "properties": {
    "iso:country":"DE",
    "sg:address":"Hasenstr. 6",
    "sg:city":"Lauenf\u00f6rde",
    "sg:phone":"+49 5273/88199",
    "sg:postcode":"37697",
    "sg:province":"Niedersachsen",
    "wof:name":"R. Externbrink",
    "wof:placetype":"venue"
},
  "geometry": {"coordinates":[9.383454,51.661873],"type":"Point"}
}