{
  "type": "Feature",
  "properties": {
    "iso:country":"DE",
    "sg:address":"Dianastr. 52",
    "sg:city":"N\u00fcrnberg",
    "sg:phone":"+49 911/413900",
    "sg:postcode":"90441",
    "sg:province":"Bayern",
    "wof:name":"Luise Barabas",
    "wof:placetype":"venue"
},
  "geometry": {"coordinates":[11.0650558472,49.4261703491],"type":"Point"}
}