{
  "type": "Feature",
  "properties": {
    "iso:country":"DE",
    "sg:address":"Kronskamp 7",
    "sg:city":"L\u00fcneburg",
    "sg:phone":"+49 4131/681057",
    "sg:postcode":"21339",
    "sg:province":"Niedersachsen",
    "wof:name":"Dmps Software E. K.",
    "wof:placetype":"venue"
},
  "geometry": {"coordinates":[10.3942489624,53.273059845],"type":"Point"}
}