{
  "type": "Feature",
  "properties": {
    "iso:country":"DE",
    "sg:address":"Bergstr. 28",
    "sg:city":"N\u00fcdlingen",
    "sg:phone":"+49 971/67057",
    "sg:postcode":"97720",
    "sg:province":"Bayern",
    "wof:name":"Walter Alberth",
    "wof:placetype":"venue"
},
  "geometry": {"coordinates":[10.121562,50.217785],"type":"Point"}
}