{
  "type": "Feature",
  "properties": {
    "iso:country":"DE",
    "sg:address":"Am Sonnenhang 1",
    "sg:city":"Winnenden",
    "sg:phone":"+49 7195/71927",
    "sg:postcode":"71364",
    "sg:province":"Baden-W\u00fcrttemberg",
    "wof:name":"Hildegard Heinzel Bildhauerin",
    "wof:placetype":"venue"
},
  "geometry": {"coordinates":[9.433839,48.866913],"type":"Point"}
}