{
  "type": "Feature",
  "properties": {
    "iso:country":"DE",
    "sg:address":"Industriehof 3",
    "sg:city":"Oldenburg",
    "sg:phone":"+49 441/42321",
    "sg:postcode":"26133",
    "sg:province":"Niedersachsen",
    "wof:name":"Fitze Inh. D. Meinhardt",
    "wof:placetype":"venue"
},
  "geometry": {"coordinates":[8.212284,53.107594],"type":"Point"}
}