{
  "type": "Feature",
  "properties": {
    "iso:country":"DE",
    "sg:address":"Bachstr. 30",
    "sg:city":"M\u00fcnchhausen",
    "sg:phone":"+49 6423/1741",
    "sg:postcode":"35117",
    "sg:province":"Hessen",
    "wof:name":"Heinrich Trusheim",
    "wof:placetype":"venue"
},
  "geometry": {"coordinates":[8.6646461487,50.9430732727],"type":"Point"}
}