{
  "type": "Feature",
  "properties": {
    "iso:country":"DE",
    "sg:address":"Rekener Str. 24",
    "sg:city":"Haltern",
    "sg:phone":"+49 2364/3254",
    "sg:postcode":"45721",
    "sg:province":"Nordrhein-Westfalen",
    "wof:name":"Haus Eggebrecht",
    "wof:placetype":"venue"
},
  "geometry": {"coordinates":[7.1618390083,51.7790145874],"type":"Point"}
}