{
  "type": "Feature",
  "properties": {
    "iso:country":"DE",
    "sg:address":"Friedensstr. 29",
    "sg:city":"Vielank",
    "sg:phone":"+49 38759/20465",
    "sg:postcode":"19303",
    "sg:province":"Mecklenburg-Vorpommern",
    "wof:name":"Woosmershofer Land- Erzeugergesellschaft Mbh",
    "wof:placetype":"venue"
},
  "geometry": {"coordinates":[11.2080783844,53.2322540283],"type":"Point"}
}