{
  "type": "Feature",
  "properties": {
    "iso:country":"DE",
    "sg:address":"Einbecker Str. 11",
    "sg:city":"Moringen",
    "sg:phone":"+49 5554/2260",
    "sg:postcode":"37186",
    "sg:province":"Niedersachsen",
    "wof:name":"Rudolf B\u00e4ulke",
    "wof:placetype":"venue"
},
  "geometry": {"coordinates":[9.872307,51.704182],"type":"Point"}
}