{
  "type": "Feature",
  "properties": {
    "iso:country":"DE",
    "sg:address":"Hansenweg 6",
    "sg:city":"Soest",
    "sg:phone":"+49 2921/96860",
    "sg:postcode":"59494",
    "sg:province":"Nordrhein-Westfalen",
    "wof:name":"Max & Moritz Gmbh",
    "wof:placetype":"venue"
},
  "geometry": {"coordinates":[8.0967378616,51.5819396973],"type":"Point"}
}