{
  "type": "Feature",
  "properties": {
    "iso:country":"DE",
    "sg:address":"Eisenstr. 21",
    "sg:city":"R\u00fcsselsheim",
    "sg:phone":"+49 6142/61307",
    "sg:postcode":"65428",
    "sg:province":"Hessen",
    "wof:name":"Ulrike Scherbaum Steuerberaterin",
    "wof:placetype":"venue"
},
  "geometry": {"coordinates":[8.4238004684,49.9768066406],"type":"Point"}
}