{
  "type": "Feature",
  "properties": {
    "iso:country":"DE",
    "sg:address":"Quadtstr. 11",
    "sg:city":"M\u00f6nchengladbach",
    "sg:phone":"+49 2166/551321",
    "sg:postcode":"41189",
    "sg:province":"Nordrhein-Westfalen",
    "wof:name":"K.-g. Hain",
    "wof:placetype":"venue"
},
  "geometry": {"coordinates":[6.4126558304,51.1303062439],"type":"Point"}
}