{
  "type": "Feature",
  "properties": {
    "iso:country":"DE",
    "sg:address":"Lange Laube 7",
    "sg:city":"Hannover",
    "sg:phone":"+49 511/27063063",
    "sg:postcode":"30159",
    "sg:province":"Niedersachsen",
    "wof:name":"Friedrich Schnabel Rechtsanwalt",
    "wof:placetype":"venue"
},
  "geometry": {"coordinates":[9.7300548553,52.3761405945],"type":"Point"}
}