{
  "type": "Feature",
  "properties": {
    "iso:country":"DE",
    "sg:address":"Dr.-Avenarius-Herborn-Str. 3",
    "sg:city":"Gau-Algesheim",
    "sg:phone":"+49 6725/2729",
    "sg:postcode":"55435",
    "sg:province":"Rheinland-Pfalz",
    "wof:name":"Anton Obertanner",
    "wof:placetype":"venue"
},
  "geometry": {"coordinates":[8.017731,49.959763],"type":"Point"}
}