{
  "type": "Feature",
  "properties": {
    "iso:country":"DE",
    "sg:address":"Rathausstr. 4",
    "sg:city":"Niederneisen",
    "sg:phone":"+49 6432/61367",
    "sg:postcode":"65629",
    "sg:province":"Rheinland-Pfalz",
    "wof:name":"Werner J\u00fcngst",
    "wof:placetype":"venue"
},
  "geometry": {"coordinates":[8.0556192398,50.3353691101],"type":"Point"}
}