{
  "type": "Feature",
  "properties": {
    "iso:country":"DE",
    "sg:address":"Ulhausgasse 17",
    "sg:city":"Langerwehe",
    "sg:phone":"+49 2423/901316",
    "sg:postcode":"52379",
    "sg:province":"Nordrhein-Westfalen",
    "wof:name":"Mediterran",
    "wof:placetype":"venue"
},
  "geometry": {"coordinates":[6.3581819534,50.817237854],"type":"Point"}
}