{
  "type": "Feature",
  "properties": {
    "iso:country":"DE",
    "sg:address":"K\u00f6nigin-Elisabeth-Str. 57",
    "sg:city":"Berlin",
    "sg:phone":"+49 30/3025097",
    "sg:postcode":"14059",
    "sg:province":"Berlin",
    "wof:name":"Malermeister Ralf Jahnke Gmbh",
    "wof:placetype":"venue"
},
  "geometry": {"coordinates":[13.280045,52.517639],"type":"Point"}
}