{
  "type": "Feature",
  "properties": {
    "iso:country":"DE",
    "sg:address":"Von-Quadt-Str. 18",
    "sg:city":"K\u00f6ln",
    "sg:phone":"+49 221/684132",
    "sg:postcode":"51069",
    "sg:province":"Nordrhein-Westfalen",
    "wof:name":"Wilfried Peters",
    "wof:placetype":"venue"
},
  "geometry": {"coordinates":[7.0694689751,50.9757423401],"type":"Point"}
}