{
  "type": "Feature",
  "properties": {
    "iso:country":"DE",
    "sg:address":"Siemensstr. 2",
    "sg:city":"Waldbronn",
    "sg:phone":"+49 7243/56430",
    "sg:postcode":"76337",
    "sg:province":"Baden-W\u00fcrttemberg",
    "wof:name":"Dr. Busch Elektronik Gmbh",
    "wof:placetype":"venue"
},
  "geometry": {"coordinates":[8.4890317917,48.9264335632],"type":"Point"}
}