{
  "type": "Feature",
  "properties": {
    "iso:country":"DE",
    "sg:address":"Waldheim-Osteufer 53",
    "sg:city":"Sittensen",
    "sg:phone":"+49 4282/2323",
    "sg:postcode":"27419",
    "sg:province":"Niedersachsen",
    "wof:name":"Christa Rathjen Architektin",
    "wof:placetype":"venue"
},
  "geometry": {"coordinates":[9.481918,53.277279],"type":"Point"}
}