{
  "type": "Feature",
  "properties": {
    "iso:country":"DE",
    "sg:address":"91589",
    "sg:city":"Aurach",
    "sg:phone":"+49 9804/244",
    "sg:postcode":"91589",
    "sg:province":"Bayern",
    "wof:name":"Zur Sonne Gastst\u00e4tte",
    "wof:placetype":"venue"
},
  "geometry": {"coordinates":[10.4132385254,49.2447776794],"type":"Point"}
}