{
  "type": "Feature",
  "properties": {
    "iso:country":"DE",
    "sg:address":"Viehofer Str. 25-29",
    "sg:city":"Essen",
    "sg:phone":"+49 201/221366",
    "sg:postcode":"45127",
    "sg:province":"Nordrhein-Westfalen",
    "wof:name":"Hardware Center W & S Essen Handels Gmbh",
    "wof:placetype":"venue"
},
  "geometry": {"coordinates":[7.0132131577,51.4590606689],"type":"Point"}
}