{
  "type": "Feature",
  "properties": {
    "iso:country":"DE",
    "sg:address":"Innere Fr\u00fchlingstr. 22",
    "sg:city":"Straubing",
    "sg:phone":"+49 9421/10877",
    "sg:postcode":"94315",
    "sg:province":"Bayern",
    "wof:name":"Sex-shop Venus",
    "wof:placetype":"venue"
},
  "geometry": {"coordinates":[12.576798,48.879299],"type":"Point"}
}