{
  "type": "Feature",
  "properties": {
    "iso:country":"DE",
    "sg:address":"Stolbergstr. 23",
    "sg:city":"D\u00fclmen",
    "sg:phone":"+49 2594/6725",
    "sg:postcode":"48249",
    "sg:province":"Nordrhein-Westfalen",
    "wof:name":"Gastst\u00e4tte G\u00fcnter Gerdemann",
    "wof:placetype":"venue"
},
  "geometry": {"coordinates":[7.2659192085,51.8391876221],"type":"Point"}
}