{
  "type": "Feature",
  "properties": {
    "iso:country":"DE",
    "sg:address":"S\u00fcd-Nord-Str. 11",
    "sg:city":"Haren",
    "sg:phone":"+49 5935/1286",
    "sg:postcode":"49733",
    "sg:province":"Niedersachsen",
    "wof:name":"Heinrich Br\u00fcmmer",
    "wof:placetype":"venue"
},
  "geometry": {"coordinates":[7.161887,52.749012],"type":"Point"}
}