{
  "type": "Feature",
  "properties": {
    "iso:country":"DE",
    "sg:address":"Steinweg 1",
    "sg:city":"Dederstedt",
    "sg:phone":"+49 34773/20220",
    "sg:postcode":"06295",
    "sg:province":"Sachsen-Anhalt",
    "wof:name":"A. Trillhase",
    "wof:placetype":"venue"
},
  "geometry": {"coordinates":[11.68732,51.544701],"type":"Point"}
}