{
  "type": "Feature",
  "properties": {
    "iso:country":"DE",
    "sg:address":"Forsthofstr. 5",
    "sg:city":"Wadern",
    "sg:phone":"+49 6871/2821",
    "sg:postcode":"66687",
    "sg:province":"Saarland",
    "wof:name":"Erwin Nickels",
    "wof:placetype":"venue"
},
  "geometry": {"coordinates":[6.885382,49.583191],"type":"Point"}
}