{
  "type": "Feature",
  "properties": {
    "iso:country":"DE",
    "sg:address":"Finkensteg 7",
    "sg:city":"Neuenhagen",
    "sg:phone":"+49 3342",
    "sg:postcode":"15366",
    "sg:province":"Brandenburg",
    "wof:name":"Bauplanungsb\u00fcro Architektur Statik J\u00f6rg Schulz",
    "wof:placetype":"venue"
},
  "geometry": {"coordinates":[13.7132377625,52.5112419128],"type":"Point"}
}