{
  "type": "Feature",
  "properties": {
    "iso:country":"DE",
    "sg:address":"Asbacher Str. 9",
    "sg:city":"Helmstadt-Bargen",
    "sg:phone":"+49 7263/5288",
    "sg:postcode":"74921",
    "sg:province":"Baden-W\u00fcrttemberg",
    "wof:name":"W. Seltenreich",
    "wof:placetype":"venue"
},
  "geometry": {"coordinates":[8.9789609909,49.3259887695],"type":"Point"}
}