{
  "type": "Feature",
  "properties": {
    "iso:country":"DE",
    "sg:address":"Schulstr. 12",
    "sg:city":"Wagenfeld",
    "sg:phone":"+49 5444/1920",
    "sg:postcode":"49419",
    "sg:province":"Niedersachsen",
    "wof:name":"Hallenbad Und Freibad",
    "wof:placetype":"venue"
},
  "geometry": {"coordinates":[8.5979099274,52.5457763672],"type":"Point"}
}