{
  "type": "Feature",
  "properties": {
    "iso:country":"DE",
    "sg:address":"Reinhold-Frank-Str. 35",
    "sg:city":"Karlsruhe",
    "sg:phone":"+49 721/848863",
    "sg:postcode":"76133",
    "sg:province":"Baden-W\u00fcrttemberg",
    "wof:name":"Evangelischer Pfarrverein In Baden E. V.",
    "wof:placetype":"venue"
},
  "geometry": {"coordinates":[8.3870391846,49.0083732605],"type":"Point"}
}