{
  "type": "Feature",
  "properties": {
    "iso:country":"DE",
    "sg:address":"Bremer Str. 4",
    "sg:city":"Hamburg",
    "sg:phone":"+49 40/7669080",
    "sg:postcode":"21073",
    "sg:province":"Hamburg",
    "wof:name":"Dr. Nesemann Blum Dr. Nesemann",
    "wof:placetype":"venue"
},
  "geometry": {"coordinates":[9.9348773956,53.436756134],"type":"Point"}
}