{
  "type": "Feature",
  "properties": {
    "iso:country":"DE",
    "sg:address":"Metzinger Str. 59",
    "sg:city":"Metzingen",
    "sg:phone":"+49 7123/969762",
    "sg:postcode":"72555",
    "sg:province":"Baden-W\u00fcrttemberg",
    "wof:name":"Ernst Hettich",
    "wof:placetype":"venue"
},
  "geometry": {"coordinates":[9.300583,48.53091],"type":"Point"}
}