{
  "type": "Feature",
  "properties": {
    "iso:country":"DE",
    "sg:address":"Franz-Josef-von-Wei\u00df-Str. 4",
    "sg:city":"Neuenburg",
    "sg:phone":"+49 7631/72690",
    "sg:postcode":"79395",
    "sg:province":"Baden-W\u00fcrttemberg",
    "wof:name":"T. Dietsche & Doll",
    "wof:placetype":"venue"
},
  "geometry": {"coordinates":[7.5573811531,47.8112945557],"type":"Point"}
}