{
  "type": "Feature",
  "properties": {
    "iso:country":"DE",
    "sg:address":"Holsten-M\u00fcndruper-Str. 46",
    "sg:city":"Osnabr\u00fcck",
    "sg:phone":"+49 541/37307",
    "sg:postcode":"49086",
    "sg:province":"Niedersachsen",
    "wof:name":"Erwin Kr\u00e4mer Verwaltungs- Gmbh",
    "wof:placetype":"venue"
},
  "geometry": {"coordinates":[8.09765625,52.2503623962],"type":"Point"}
}