{
  "type": "Feature",
  "properties": {
    "iso:country":"DE",
    "sg:address":"M\u00f6rfelder Str. 10",
    "sg:city":"Kelsterbach",
    "sg:phone":"+49 6107/991163",
    "sg:postcode":"65451",
    "sg:province":"Hessen",
    "wof:name":"Tengelmann",
    "wof:placetype":"venue"
},
  "geometry": {"coordinates":[8.5310764313,50.0627708435],"type":"Point"}
}