{
  "type": "Feature",
  "properties": {
    "iso:country":"DE",
    "sg:address":"W\u00f6rthstr. 31",
    "sg:city":"Stuttgart",
    "sg:phone":"+49 711/7802764",
    "sg:postcode":"70563",
    "sg:province":"Baden-W\u00fcrttemberg",
    "wof:name":"Werner K\u00fchnly",
    "wof:placetype":"venue"
},
  "geometry": {"coordinates":[9.1236038208,48.7307701111],"type":"Point"}
}