{
  "type": "Feature",
  "properties": {
    "iso:country":"DE",
    "sg:address":"Heinrich-Wieland-Allee 53",
    "sg:city":"Pforzheim",
    "sg:phone":"+49 7231/34545",
    "sg:postcode":"75177",
    "sg:province":"Baden-W\u00fcrttemberg",
    "wof:name":"Foerster Immobilien Gmbh",
    "wof:placetype":"venue"
},
  "geometry": {"coordinates":[8.7072687149,48.9010543823],"type":"Point"}
}