{
  "type": "Feature",
  "properties": {
    "iso:country":"DE",
    "sg:address":"Wei\u00dfenburger Str 17",
    "sg:city":"Treuchtlingen",
    "sg:phone":"+49 9142/96830",
    "sg:postcode":"91757",
    "sg:province":"Bayern",
    "wof:name":"Georg Pledl",
    "wof:placetype":"venue"
},
  "geometry": {"coordinates":[10.9193,48.957577],"type":"Point"}
}