{
  "type": "Feature",
  "properties": {
    "iso:country":"DE",
    "sg:address":"Beekebreite 1",
    "sg:city":"Rinteln",
    "sg:phone":"+49 5751/75252",
    "sg:postcode":"31737",
    "sg:province":"Niedersachsen",
    "wof:name":"F. Buschhorn",
    "wof:placetype":"venue"
},
  "geometry": {"coordinates":[9.1167125702,52.2100334167],"type":"Point"}
}