{
  "type": "Feature",
  "properties": {
    "iso:country":"DE",
    "sg:address":"D\u00fcsseldorfer Str. 90",
    "sg:city":"D\u00fcsseldorf",
    "sg:phone":"+49 211/572121",
    "sg:postcode":"40545",
    "sg:province":"Nordrhein-Westfalen",
    "wof:name":"R. Van Leeuwen",
    "wof:placetype":"venue"
},
  "geometry": {"coordinates":[6.750092,51.228539],"type":"Point"}
}