{
  "type": "Feature",
  "properties": {
    "iso:country":"DE",
    "sg:address":"Gebirgsj\u00e4gerstr. 3",
    "sg:city":"Strub",
    "sg:phone":"+49 8652/2798",
    "sg:postcode":"83489",
    "wof:name":"J. Burghartwieser Bw-kantine",
    "wof:placetype":"venue"
},
  "geometry": {"coordinates":[12.9599962234,47.6314277649],"type":"Point"}
}