{
  "type": "Feature",
  "properties": {
    "iso:country":"DE",
    "sg:address":"Wingertstr. 39-43",
    "sg:city":"Maintal",
    "sg:postcode":"63477",
    "sg:province":"Hessen",
    "wof:name":"Wal-mart Supercenter",
    "wof:placetype":"venue"
},
  "geometry": {"coordinates":[8.8313941956,50.1513519287],"type":"Point"}
}