{
  "type": "Feature",
  "properties": {
    "iso:country":"DE",
    "sg:address":"Zum M\u00f6hnewehr 25",
    "sg:city":"Arnsberg",
    "sg:phone":"+49 2932/97540",
    "sg:postcode":"59755",
    "sg:province":"Nordrhein-Westfalen",
    "wof:name":"Tkt Thermo-kunststoff-trans- Portger\u00e4te-systeme Herstellung",
    "wof:placetype":"venue"
},
  "geometry": {"coordinates":[7.97626,51.46096],"type":"Point"}
}