{
  "type": "Feature",
  "properties": {
    "iso:country":"DE",
    "sg:address":"Paderborner Str. 1",
    "sg:city":"Altenbeken",
    "sg:phone":"+49 5255/6153",
    "sg:postcode":"33184",
    "sg:province":"Nordrhein-Westfalen",
    "wof:name":"Heinrich Lerch",
    "wof:placetype":"venue"
},
  "geometry": {"coordinates":[8.9346189499,51.7140235901],"type":"Point"}
}