{
  "type": "Feature",
  "properties": {
    "iso:country":"DE",
    "sg:address":"Wielandstr. 7",
    "sg:city":"Bonn",
    "sg:phone":"+49 228/19257",
    "sg:postcode":"53173",
    "sg:province":"Nordrhein-Westfalen",
    "wof:name":"Arzt Ruf 19257 Privat\u00e4rztl. Notdienst Gmbh",
    "wof:placetype":"venue"
},
  "geometry": {"coordinates":[7.1673941612,50.6868476868],"type":"Point"}
}