{
  "type": "Feature",
  "properties": {
    "iso:country":"DE",
    "sg:address":"Leutweinstr. 9",
    "sg:city":"Oberhausen",
    "sg:phone":"+49 208/890682",
    "sg:postcode":"46119",
    "sg:province":"Nordrhein-Westfalen",
    "wof:name":"Kroehnert",
    "wof:placetype":"venue"
},
  "geometry": {"coordinates":[6.8883271217,51.5111312866],"type":"Point"}
}