{
  "type": "Feature",
  "properties": {
    "iso:country":"DE",
    "sg:address":"Fuhrtstr. 18",
    "sg:city":"Simmerath",
    "sg:postcode":"52152",
    "sg:province":"Nordrhein-Westfalen",
    "wof:name":"Ftm Formentechnik Und Metallbau Gmbh",
    "wof:placetype":"venue"
},
  "geometry": {"coordinates":[6.3133659363,50.6334495544],"type":"Point"}
}