{
  "type": "Feature",
  "properties": {
    "iso:country":"DE",
    "sg:address":"Hauptstr. 27 /1",
    "sg:city":"Birenbach",
    "sg:phone":"+49 7161/53160",
    "sg:postcode":"73102",
    "sg:province":"Baden-W\u00fcrttemberg",
    "wof:name":"Anton Bader",
    "wof:placetype":"venue"
},
  "geometry": {"coordinates":[9.662504,48.746552],"type":"Point"}
}