{
  "type": "Feature",
  "properties": {
    "iso:country":"DE",
    "sg:address":"Eichhornsgasse 1",
    "sg:city":"Steinach",
    "sg:phone":"+49 36762/32623",
    "sg:postcode":"96523",
    "sg:province":"Th\u00fcringen",
    "wof:name":"Friedel K\u00e4mpf",
    "wof:placetype":"venue"
},
  "geometry": {"coordinates":[11.1556177139,50.4358634949],"type":"Point"}
}