{
  "type": "Feature",
  "properties": {
    "iso:country":"DE",
    "sg:address":"Talangerstr. 3",
    "sg:city":"Krailling",
    "sg:phone":"+49 89/89511010",
    "sg:postcode":"82152",
    "sg:province":"Bayern",
    "wof:name":"Challenge Internetworking Und Computer Consulting E. K.",
    "wof:placetype":"venue"
},
  "geometry": {"coordinates":[11.40955,48.094742],"type":"Point"}
}