{
  "type": "Feature",
  "properties": {
    "iso:country":"DE",
    "sg:address":"Mathildenstr. 1",
    "sg:city":"Gr\u00e4felfing",
    "sg:postcode":"82166",
    "sg:province":"Bayern",
    "wof:name":"Ramses Gmbh",
    "wof:placetype":"venue"
},
  "geometry": {"coordinates":[11.4261817932,48.1268386841],"type":"Point"}
}