{
  "type": "Feature",
  "properties": {
    "iso:country":"DE",
    "sg:address":"Baur 1 a",
    "sg:city":"Wuppertal",
    "sg:phone":"+49 202/465209",
    "sg:postcode":"42369",
    "sg:province":"Nordrhein-Westfalen",
    "wof:name":"Ernst Friedrichs",
    "wof:placetype":"venue"
},
  "geometry": {"coordinates":[7.184603,51.239941],"type":"Point"}
}