{
  "type": "Feature",
  "properties": {
    "iso:country":"DE",
    "sg:address":"Dr.-Hermann-Marcks-Str. 3",
    "sg:city":"Munster",
    "sg:phone":"+49 5192/2243",
    "sg:postcode":"29633",
    "sg:province":"Niedersachsen",
    "wof:name":"Ferdinand Roacke",
    "wof:placetype":"venue"
},
  "geometry": {"coordinates":[10.0976390839,52.9857368469],"type":"Point"}
}