{
  "type": "Feature",
  "properties": {
    "iso:country":"DE",
    "sg:address":"Kyllstr. 62",
    "sg:city":"Trier",
    "sg:postcode":"54293",
    "sg:province":"Rheinland-Pfalz",
    "wof:name":"Der Augenoptiker Roman Wagner + Van Boxem Gmbh",
    "wof:placetype":"venue"
},
  "geometry": {"coordinates":[6.6858291626,49.8081665039],"type":"Point"}
}