{
  "type": "Feature",
  "properties": {
    "iso:country":"DE",
    "sg:address":"Bismarckstr. 47",
    "sg:city":"G\u00f6nnheim",
    "sg:postcode":"67161",
    "sg:province":"Rheinland-Pfalz",
    "wof:name":"Mm-beteiligungs Holding Gmbh",
    "wof:placetype":"venue"
},
  "geometry": {"coordinates":[8.240902,49.44986],"type":"Point"}
}