{
  "type": "Feature",
  "properties": {
    "iso:country":"DE",
    "sg:address":"M\u00fclheimer Ring 6-8",
    "sg:city":"K\u00f6ln",
    "sg:phone":"+49 221/9714000",
    "sg:postcode":"51063",
    "sg:province":"Nordrhein-Westfalen",
    "wof:name":"Am Vermiet & Event Gmbh",
    "wof:placetype":"venue"
},
  "geometry": {"coordinates":[7.021679,50.965965],"type":"Point"}
}