{
  "type": "Feature",
  "properties": {
    "iso:country":"DE",
    "sg:address":"Weinholdstr. 21",
    "sg:city":"Reichenbach",
    "sg:phone":"+49 3765/21138",
    "sg:postcode":"08468",
    "sg:province":"Sachsen",
    "wof:name":"Lothar Krau\u00df",
    "wof:placetype":"venue"
},
  "geometry": {"coordinates":[12.3013706207,50.6246757507],"type":"Point"}
}