{
  "type": "Feature",
  "properties": {
    "iso:country":"DE",
    "sg:address":"Mittelstr. 84",
    "sg:city":"Sprockh\u00f6vel",
    "sg:phone":"+49 2339/912612",
    "sg:postcode":"45549",
    "sg:province":"Nordrhein-Westfalen",
    "wof:name":"Dea",
    "wof:placetype":"venue"
},
  "geometry": {"coordinates":[7.2672548294,51.329750061],"type":"Point"}
}