{
  "type": "Feature",
  "properties": {
    "iso:country":"DE",
    "sg:address":"Basler Str. 9",
    "sg:city":"Bad Krozingen",
    "sg:phone":"+49 7633/150818",
    "sg:postcode":"79189",
    "sg:province":"Baden-W\u00fcrttemberg",
    "wof:name":"P. Machutta",
    "wof:placetype":"venue"
},
  "geometry": {"coordinates":[7.6989941597,47.9153556824],"type":"Point"}
}