{
  "type": "Feature",
  "properties": {
    "iso:country":"DE",
    "sg:address":"Berliner Platz 1",
    "sg:city":"Erfurt",
    "sg:phone":"+49 361/7911256",
    "sg:postcode":"99091",
    "sg:province":"Th\u00fcringen",
    "wof:name":"Erfurter Blumen Gmbh",
    "wof:placetype":"venue"
},
  "geometry": {"coordinates":[11.005023,51.003815],"type":"Point"}
}