{
  "type": "Feature",
  "properties": {
    "iso:country":"DE",
    "sg:address":"Glaner Str. 57 a",
    "sg:city":"Wildeshausen",
    "sg:phone":"+49 4431/5777",
    "sg:postcode":"27793",
    "sg:province":"Niedersachsen",
    "wof:name":"Karl-heinz Neumann",
    "wof:placetype":"venue"
},
  "geometry": {"coordinates":[8.414018631,52.9029655457],"type":"Point"}
}