{
  "type": "Feature",
  "properties": {
    "iso:country":"DE",
    "sg:address":"Maximilianstr.",
    "sg:city":"Hirschaid",
    "sg:phone":"+49 9543/3758",
    "sg:postcode":"96114",
    "sg:province":"Bayern",
    "wof:name":"Georg Fleischmann",
    "wof:placetype":"venue"
},
  "geometry": {"coordinates":[10.9980154037,49.8203735352],"type":"Point"}
}