{
  "type": "Feature",
  "properties": {
    "iso:country":"DE",
    "sg:address":"Gr\u00fcnstr. 45",
    "sg:city":"Pritzwalk",
    "sg:phone":"+49 3395/302008",
    "sg:postcode":"16928",
    "sg:province":"Brandenburg",
    "wof:name":"Oldenburg",
    "wof:placetype":"venue"
},
  "geometry": {"coordinates":[12.177402,53.150284],"type":"Point"}
}