{
  "type": "Feature",
  "properties": {
    "iso:country":"DE",
    "sg:address":"Gabelstr. 1",
    "sg:city":"Fahrenzhausen",
    "sg:phone":"+49 8133/308",
    "sg:postcode":"85777",
    "sg:province":"Bayern",
    "wof:name":"Anton Kratzl",
    "wof:placetype":"venue"
},
  "geometry": {"coordinates":[11.595175,48.33572],"type":"Point"}
}