{
  "type": "Feature",
  "properties": {
    "iso:country":"DE",
    "sg:address":"Br\u00e4uhausstr. 3",
    "sg:city":"Freilassing",
    "sg:postcode":"83395",
    "sg:province":"Bayern",
    "wof:name":"A + G Sicherheitstechnik Gmbh",
    "wof:placetype":"venue"
},
  "geometry": {"coordinates":[12.980964,47.841946],"type":"Point"}
}