{
  "type": "Feature",
  "properties": {
    "iso:country":"DE",
    "sg:address":"Postfach 1417",
    "sg:city":"Bad Homburg",
    "sg:phone":"+49 6172/96280",
    "sg:postcode":"61284",
    "wof:name":"Firmen- & Personal-profil Ohg",
    "wof:placetype":"venue"
},
  "geometry": {"coordinates":[8.6159296036,50.2271499634],"type":"Point"}
}