{
  "type": "Feature",
  "properties": {
    "iso:country":"DE",
    "sg:address":"Fredersdorfer Str. 20d",
    "sg:city":"Fredersdorf",
    "sg:postcode":"15370",
    "sg:province":"Brandenburg",
    "wof:name":"Agrar Online Gmbh",
    "wof:placetype":"venue"
},
  "geometry": {"coordinates":[13.7470445633,52.5427360535],"type":"Point"}
}