{
  "type": "Feature",
  "properties": {
    "iso:country":"DE",
    "sg:address":"Sundremdaer Str. 1",
    "sg:city":"Remda",
    "sg:phone":"+49 36744/203",
    "sg:postcode":"07407",
    "sg:province":"Th\u00fcringen",
    "wof:name":"Kreissparkasse Rudolstadt",
    "wof:placetype":"venue"
},
  "geometry": {"coordinates":[11.228194,50.759251],"type":"Point"}
}