{
  "type": "Feature",
  "properties": {
    "iso:country":"DE",
    "sg:address":"Wessendorfer Str. 2",
    "sg:city":"Vreden",
    "sg:phone":"+49 2564/97590",
    "sg:postcode":"48691",
    "sg:province":"Nordrhein-Westfalen",
    "wof:name":"Buddelei Mode Gmbh",
    "wof:placetype":"venue"
},
  "geometry": {"coordinates":[6.824303,52.036095],"type":"Point"}
}