{
  "type": "Feature",
  "properties": {
    "iso:country":"DE",
    "sg:address":"Ostenhellweg 18",
    "sg:city":"Dortmund",
    "sg:phone":"+49 231/54340",
    "sg:postcode":"44135",
    "sg:province":"Nordrhein-Westfalen",
    "wof:name":"C & A",
    "wof:placetype":"venue"
},
  "geometry": {"coordinates":[7.469236,51.514538],"type":"Point"}
}