{
  "type": "Feature",
  "properties": {
    "iso:country":"DE",
    "sg:address":"W\u00fcrzburger Str. 14",
    "sg:city":"Marktheidenfeld",
    "sg:phone":"+49 9391/4161",
    "sg:postcode":"97828",
    "sg:province":"Bayern",
    "wof:name":"Marxhausen Und Lenzen Rechtsanw\u00e4lte",
    "wof:placetype":"venue"
},
  "geometry": {"coordinates":[9.6044950485,49.8421325684],"type":"Point"}
}