{
  "type": "Feature",
  "properties": {
    "iso:country":"DE",
    "sg:address":"Rosenheimer Str. 5",
    "sg:city":"M\u00fcnchen",
    "sg:phone":"+49 89/48098313",
    "sg:postcode":"81667",
    "sg:province":"Bayern",
    "wof:name":"Bibliothekszentrale Kinder- Und Jugendbibliothek",
    "wof:placetype":"venue"
},
  "geometry": {"coordinates":[11.590768,48.130993],"type":"Point"}
}