{
  "type": "Feature",
  "properties": {
    "iso:country":"DE",
    "sg:address":"Eupener Str. 111",
    "sg:city":"K\u00f6ln",
    "sg:phone":"+49 221/4994771",
    "sg:postcode":"50933",
    "sg:province":"Nordrhein-Westfalen",
    "wof:name":"Werkstatt F\u00dcr Neue M\u00d6bel",
    "wof:placetype":"venue"
},
  "geometry": {"coordinates":[6.889298,50.94257],"type":"Point"}
}