{
  "type": "Feature",
  "properties": {
    "iso:country":"DE",
    "sg:address":"Hamburger Str. 250",
    "sg:city":"Braunschweig",
    "sg:postcode":"38114",
    "sg:province":"Niedersachsen",
    "wof:name":"Real",
    "wof:placetype":"venue"
},
  "geometry": {"coordinates":[10.5187511444,52.2823028564],"type":"Point"}
}