{
  "type": "Feature",
  "properties": {
    "iso:country":"DE",
    "sg:address":"Anne-Frank-Str. 29",
    "sg:city":"Schwerin",
    "sg:phone":"+49 385/3925555",
    "sg:postcode":"19061",
    "sg:province":"Mecklenburg-Vorpommern",
    "wof:name":"Asia Sports Gmbh",
    "wof:placetype":"venue"
},
  "geometry": {"coordinates":[11.436135,53.602505],"type":"Point"}
}