{
  "type": "Feature",
  "properties": {
    "iso:country":"DE",
    "sg:address":"Obere Vorstadt 4 A",
    "sg:city":"Leutershausen",
    "sg:phone":"+49 9823/92000",
    "sg:postcode":"91578",
    "sg:province":"Bayern",
    "wof:name":"Dock-g\u00f6ttsche-hanl-raab Steuerberater Und",
    "wof:placetype":"venue"
},
  "geometry": {"coordinates":[10.4069929123,49.3005561829],"type":"Point"}
}