{
  "type": "Feature",
  "properties": {
    "iso:country":"DE",
    "sg:address":"Pfarrweg 15",
    "sg:city":"Greiz",
    "sg:phone":"+49 3661/2068",
    "sg:postcode":"07973",
    "sg:province":"Th\u00fcringen",
    "wof:name":"Christian H\u00f6fer",
    "wof:placetype":"venue"
},
  "geometry": {"coordinates":[12.175497,50.638878],"type":"Point"}
}