{
  "type": "Feature",
  "properties": {
    "iso:country":"DE",
    "sg:address":"Gerhart-Hauptmann-Str. 6 a",
    "sg:city":"Wei\u00dfenburg",
    "sg:phone":"+49 9141/2046",
    "sg:postcode":"91781",
    "sg:province":"Bayern",
    "wof:name":"Helmut Stigler Notar",
    "wof:placetype":"venue"
},
  "geometry": {"coordinates":[10.9868049622,49.032283783],"type":"Point"}
}