{
  "type": "Feature",
  "properties": {
    "iso:country":"DE",
    "sg:address":"Hauptstr. 13",
    "sg:city":"Braunschweig",
    "sg:phone":"+49 5307/2633",
    "sg:postcode":"38110",
    "sg:province":"Niedersachsen",
    "wof:name":"Reichelt",
    "wof:placetype":"venue"
},
  "geometry": {"coordinates":[10.5147209167,52.3212051392],"type":"Point"}
}