{
  "type": "Feature",
  "properties": {
    "iso:country":"DE",
    "sg:address":"Pfarrgasse 2",
    "sg:city":"Ebern",
    "sg:phone":"+49 9531/206",
    "sg:postcode":"96106",
    "sg:province":"Bayern",
    "wof:name":"Kath. Pfarramt St. Laurentius",
    "wof:placetype":"venue"
},
  "geometry": {"coordinates":[10.7934904099,50.0953903198],"type":"Point"}
}