{
  "type": "Feature",
  "properties": {
    "iso:country":"DE",
    "sg:address":"Kreuzweg 112",
    "sg:city":"Schortens",
    "sg:phone":"+49 4461/80291",
    "sg:postcode":"26419",
    "sg:province":"Niedersachsen",
    "wof:name":"Kath. Pfarramt Hl. Dreifaltigkeit",
    "wof:placetype":"venue"
},
  "geometry": {"coordinates":[7.9501881599,53.533821106],"type":"Point"}
}