{
  "type": "Feature",
  "properties": {
    "iso:country":"DE",
    "sg:address":"Weberkoppel 66",
    "sg:city":"L\u00fcbeck",
    "sg:phone":"+49 451/593469",
    "sg:postcode":"23562",
    "sg:province":"Schleswig-Holstein",
    "wof:name":"Wolfgang Tonne Architekt",
    "wof:placetype":"venue"
},
  "geometry": {"coordinates":[10.719737,53.845921],"type":"Point"}
}