{
  "type": "Feature",
  "properties": {
    "iso:country":"DE",
    "sg:address":"Gro\u00dfheidestr. 4",
    "sg:city":"Hamburg",
    "sg:phone":"+49 40/2708296",
    "sg:postcode":"22303",
    "sg:province":"Hamburg",
    "wof:name":"W. Wolf",
    "wof:placetype":"venue"
},
  "geometry": {"coordinates":[10.027728,53.585274],"type":"Point"}
}