{
  "type": "Feature",
  "properties": {
    "iso:country":"DE",
    "sg:address":"Hopfenweiler",
    "sg:city":"Bad Waldsee",
    "sg:phone":"+49 7524/48778",
    "sg:postcode":"88339",
    "sg:province":"Baden-W\u00fcrttemberg",
    "wof:name":"Golfshop Des Golfclubs Oberschwaben Bad Waldsee",
    "wof:placetype":"venue"
},
  "geometry": {"coordinates":[9.772422,47.932682],"type":"Point"}
}