{
  "type": "Feature",
  "properties": {
    "iso:country":"DE",
    "sg:address":"S\u00fcdring 12",
    "sg:city":"Bochum",
    "sg:phone":"+49 234/683495",
    "sg:postcode":"44787",
    "sg:province":"Nordrhein-Westfalen",
    "wof:name":"Uysuns Haarstudio Gmbh",
    "wof:placetype":"venue"
},
  "geometry": {"coordinates":[7.218432,51.478794],"type":"Point"}
}