{
  "type": "Feature",
  "properties": {
    "iso:country":"DE",
    "sg:address":"Kanalstr. 12/1",
    "sg:city":"Dettingen",
    "sg:phone":"+49 7021/55120",
    "sg:postcode":"73265",
    "sg:province":"Baden-W\u00fcrttemberg",
    "wof:name":"Erich Mann",
    "wof:placetype":"venue"
},
  "geometry": {"coordinates":[9.449677,48.618614],"type":"Point"}
}