{
  "type": "Feature",
  "properties": {
    "iso:country":"DE",
    "sg:address":"Wettersteinstr. 51",
    "sg:city":"N\u00fcrnberg",
    "sg:phone":"+49 911/868724",
    "sg:postcode":"90471",
    "sg:province":"Bayern",
    "wof:name":"Reinhard Knorr Immobilienmakler",
    "wof:placetype":"venue"
},
  "geometry": {"coordinates":[11.1197032928,49.410610199],"type":"Point"}
}