{
  "type": "Feature",
  "properties": {
    "iso:country":"DE",
    "sg:address":"Altenoyther Str. 56",
    "sg:city":"Friesoythe",
    "sg:phone":"+49 4491/2169",
    "sg:postcode":"26169",
    "sg:province":"Niedersachsen",
    "wof:name":"Heinz Speckmann",
    "wof:placetype":"venue"
},
  "geometry": {"coordinates":[7.9184389114,53.0633506775],"type":"Point"}
}