{
  "type": "Feature",
  "properties": {
    "iso:country":"DE",
    "sg:city":"Midlum",
    "sg:phone":"+49 4947/411021",
    "sg:postcode":"27632",
    "sg:province":"Niedersachsen",
    "wof:name":"Volksbank Weserm\u00fcnde-nord Eg",
    "wof:placetype":"venue"
},
  "geometry": {"coordinates":[8.615557,53.730556],"type":"Point"}
}