{
  "type": "Feature",
  "properties": {
    "iso:country":"DE",
    "sg:address":"Scharnhauser Str. 11",
    "sg:city":"Ostfildern",
    "sg:phone":"+49 711/444502",
    "sg:postcode":"73760",
    "sg:province":"Baden-W\u00fcrttemberg",
    "wof:name":"Roland Scheck Ingenieur",
    "wof:placetype":"venue"
},
  "geometry": {"coordinates":[9.2553195953,48.7248001099],"type":"Point"}
}