{
  "type": "Feature",
  "properties": {
    "iso:country":"DE",
    "sg:address":"Linther Str. 1",
    "sg:city":"Linthe",
    "sg:postcode":"14822",
    "sg:province":"Brandenburg",
    "wof:name":"Porta-fenster-t\u00fcren Und Fenster Gmbh & Co. Kg",
    "wof:placetype":"venue"
},
  "geometry": {"coordinates":[12.788186,52.163513],"type":"Point"}
}