{
  "type": "Feature",
  "properties": {
    "iso:country":"DE",
    "sg:address":"Am Goldberg 3",
    "sg:city":"Bendorf",
    "sg:phone":"+49 2622/15900",
    "sg:postcode":"56170",
    "sg:province":"Rheinland-Pfalz",
    "wof:name":"Tischlerei W. Senking E. K. Inh. Andre Iser",
    "wof:placetype":"venue"
},
  "geometry": {"coordinates":[7.579525,50.426338],"type":"Point"}
}