{
  "type": "Feature",
  "properties": {
    "iso:country":"DE",
    "sg:address":"Erlenhofer Str. 2",
    "sg:city":"Fichtenberg",
    "sg:phone":"+49 7971/23777",
    "sg:postcode":"74427",
    "sg:province":"Baden-W\u00fcrttemberg",
    "wof:name":"B\u00fcrobedarf Schuster Inh. Petra Schuster",
    "wof:placetype":"venue"
},
  "geometry": {"coordinates":[9.712911,48.98621],"type":"Point"}
}