{
  "type": "Feature",
  "properties": {
    "iso:country":"DE",
    "sg:address":"Junkersstr. 15",
    "sg:city":"Neu-Ulm",
    "sg:phone":"+49 731/77640",
    "sg:postcode":"89231",
    "sg:province":"Bayern",
    "wof:name":"Vereinigte Blindenwerkst\u00e4tten Schmid & Co. Kg",
    "wof:placetype":"venue"
},
  "geometry": {"coordinates":[10.021454,48.380894],"type":"Point"}
}