{
  "type": "Feature",
  "properties": {
    "iso:country":"DE",
    "sg:address":"Kirchenlamitzer Str. 52",
    "sg:city":"Wei\u00dfenstadt",
    "sg:phone":"+49 9253/1260",
    "sg:postcode":"95163",
    "sg:province":"Bayern",
    "wof:name":"K. Manas",
    "wof:placetype":"venue"
},
  "geometry": {"coordinates":[11.8876256943,50.1042861938],"type":"Point"}
}