{
  "type": "Feature",
  "properties": {
    "iso:country":"DE",
    "sg:address":"B\u00fcttnerstr. 4",
    "sg:city":"Burkardroth",
    "sg:phone":"+49 9734/347",
    "sg:postcode":"97705",
    "sg:province":"Bayern",
    "wof:name":"A. Wehner",
    "wof:placetype":"venue"
},
  "geometry": {"coordinates":[9.9927968979,50.2655754089],"type":"Point"}
}