{
  "type": "Feature",
  "properties": {
    "iso:country":"DE",
    "sg:address":"Coesfelder Berg 21a",
    "sg:city":"Coesfeld",
    "sg:phone":"+49 2541/971873",
    "sg:postcode":"48653",
    "sg:province":"Nordrhein-Westfalen",
    "wof:name":"Lg Metallbau U. Metallgestaltung",
    "wof:placetype":"venue"
},
  "geometry": {"coordinates":[7.216494,51.951157],"type":"Point"}
}