{
  "type": "Feature",
  "properties": {
    "iso:country":"DE",
    "sg:address":"Eufinger Str. 54",
    "sg:city":"H\u00fcnfelden",
    "sg:phone":"+49 6438/6755",
    "sg:postcode":"65597",
    "sg:province":"Hessen",
    "wof:name":"Werner M\u00fcller",
    "wof:placetype":"venue"
},
  "geometry": {"coordinates":[8.189243,50.32584],"type":"Point"}
}