{
  "type": "Feature",
  "properties": {
    "iso:country":"DE",
    "sg:address":"S\u00fcderweg 3",
    "sg:city":"Behrendorf",
    "sg:phone":"+49 4843/1700",
    "sg:postcode":"25850",
    "sg:province":"Schleswig-Holstein",
    "wof:name":"Hans-thomas Jessen",
    "wof:placetype":"venue"
},
  "geometry": {"coordinates":[9.219377,54.560947],"type":"Point"}
}