{
  "type": "Feature",
  "properties": {
    "iso:country":"DE",
    "sg:address":"Hauptstr. 6",
    "sg:city":"Ziegra-Knobelsdorf",
    "sg:phone":"+49 3431/612516",
    "sg:postcode":"04720",
    "sg:province":"Sachsen",
    "wof:name":"Rudolf Gerner",
    "wof:placetype":"venue"
},
  "geometry": {"coordinates":[13.0509519577,51.1177787781],"type":"Point"}
}