{
  "type": "Feature",
  "properties": {
    "iso:country":"DE",
    "sg:address":"Wernauer Weg 14",
    "sg:city":"Ulm",
    "sg:phone":"+49 7305/6516",
    "sg:postcode":"89079",
    "sg:province":"Baden-W\u00fcrttemberg",
    "wof:name":"Hermann Braun",
    "wof:placetype":"venue"
},
  "geometry": {"coordinates":[9.899711,48.352509],"type":"Point"}
}