{
  "type": "Feature",
  "properties": {
    "iso:country":"DE",
    "sg:address":"Rosenbergstr. 16",
    "sg:city":"Daun",
    "sg:phone":"+49 6592/4090",
    "sg:postcode":"54550",
    "sg:province":"Rheinland-Pfalz",
    "wof:name":"Jennys Treff",
    "wof:placetype":"venue"
},
  "geometry": {"coordinates":[6.8263959885,50.1970596313],"type":"Point"}
}