{
  "type": "Feature",
  "properties": {
    "iso:country":"DE",
    "sg:address":"Heiskampstr. 12",
    "sg:city":"Hattingen",
    "sg:phone":"+49 2324/3900",
    "sg:postcode":"45527",
    "sg:province":"Nordrhein-Westfalen",
    "wof:name":"C. E. Pattberg Gmbh & Co.",
    "wof:placetype":"venue"
},
  "geometry": {"coordinates":[7.2180719376,51.3969726562],"type":"Point"}
}