{
  "type": "Feature",
  "properties": {
    "iso:country":"DE",
    "sg:address":"Marktplatz 21-23",
    "sg:city":"Esslingen",
    "sg:phone":"+49 711/359956",
    "sg:postcode":"73728",
    "sg:province":"Baden-W\u00fcrttemberg",
    "wof:name":"G.c. Kessler Gmbh & Co Kg",
    "wof:placetype":"venue"
},
  "geometry": {"coordinates":[9.3069696426,48.7421684265],"type":"Point"}
}