{
  "type": "Feature",
  "properties": {
    "iso:country":"DE",
    "sg:address":"Am Jr\u00f6ne Meerke 38",
    "sg:city":"Neuss",
    "sg:postcode":"41462",
    "sg:province":"Nordrhein-Westfalen",
    "wof:name":"Casa Dos Colibris",
    "wof:placetype":"venue"
},
  "geometry": {"coordinates":[6.656086,51.217564],"type":"Point"}
}