{
  "type": "Feature",
  "properties": {
    "iso:country":"DE",
    "sg:address":"Muchhausener Str. 20",
    "sg:city":"Grevenbroich",
    "sg:phone":"+49 2181/3986",
    "sg:postcode":"41515",
    "sg:province":"Nordrhein-Westfalen",
    "wof:name":"Franz Poschen",
    "wof:placetype":"venue"
},
  "geometry": {"coordinates":[6.640315,51.076168],"type":"Point"}
}