{
  "type": "Feature",
  "properties": {
    "iso:country":"DE",
    "sg:address":"Neuheim 31",
    "sg:city":"M\u00fcnster",
    "sg:postcode":"48155",
    "sg:province":"Nordrhein-Westfalen",
    "wof:name":"Joh. Steffens Verwaltungs- Und Beteiligungs Gmbh",
    "wof:placetype":"venue"
},
  "geometry": {"coordinates":[7.6745638847,51.955165863],"type":"Point"}
}