{
  "type": "Feature",
  "properties": {
    "iso:country":"DE",
    "sg:address":"Bahnhofstr. 24",
    "sg:city":"Steinbach-Hallenberg",
    "sg:phone":"+49 36847/40419",
    "sg:postcode":"98587",
    "sg:province":"Th\u00fcringen",
    "wof:name":"Elisabeth Erkes Masseur",
    "wof:placetype":"venue"
},
  "geometry": {"coordinates":[10.561234,50.694622],"type":"Point"}
}