{
  "type": "Feature",
  "properties": {
    "iso:country":"DE",
    "sg:address":"Grub 110",
    "sg:city":"K\u00f6tzting",
    "sg:phone":"+49 9941/1525",
    "sg:postcode":"93444",
    "sg:province":"Bayern",
    "wof:name":"Gastst\u00e4tte Albert Fechter",
    "wof:placetype":"venue"
},
  "geometry": {"coordinates":[12.8545541763,49.174747467],"type":"Point"}
}