{
  "type": "Feature",
  "properties": {
    "iso:country":"DE",
    "sg:address":"Streiter Str. 2",
    "sg:city":"Elsenfeld",
    "sg:phone":"+49 6022/8212",
    "sg:postcode":"63820",
    "sg:province":"Bayern",
    "wof:name":"Adolf B\u00f6ttiger",
    "wof:placetype":"venue"
},
  "geometry": {"coordinates":[9.16093,49.84568],"type":"Point"}
}