{
  "type": "Feature",
  "properties": {
    "iso:country":"DE",
    "sg:address":"Rottk\u00e4mpe 7",
    "sg:city":"Recklinghausen",
    "sg:phone":"+49 2361/59961",
    "sg:postcode":"45659",
    "sg:province":"Nordrhein-Westfalen",
    "wof:name":"G. G. Gellenbeck Werbeagentur",
    "wof:placetype":"venue"
},
  "geometry": {"coordinates":[7.1774978638,51.6039657593],"type":"Point"}
}