{
  "type": "Feature",
  "properties": {
    "iso:country":"DE",
    "sg:address":"Tauroggener Str. 40",
    "sg:city":"Berlin",
    "sg:phone":"+49 30/3443742",
    "sg:postcode":"10589",
    "sg:province":"Berlin",
    "wof:name":"Gebr\u00fcder Kube Gartenger\u00e4te",
    "wof:placetype":"venue"
},
  "geometry": {"coordinates":[13.3010807037,52.5244903564],"type":"Point"}
}