{
  "type": "Feature",
  "properties": {
    "iso:country":"DE",
    "sg:address":"Chausseestr. 1",
    "sg:city":"Wildau",
    "sg:phone":"+49 3375/21270",
    "sg:postcode":"15745",
    "sg:province":"Brandenburg",
    "wof:name":"Karstadt Warenhaus",
    "wof:placetype":"venue"
},
  "geometry": {"coordinates":[13.603859,52.3162],"type":"Point"}
}