{
  "type": "Feature",
  "properties": {
    "iso:country":"DE",
    "sg:address":"Le Quai des Arts / Ancienne Gare",
    "sg:city":"SOMMIERES",
    "sg:phone":"+49 4667/71027",
    "sg:postcode":"30250",
    "wof:name":"Compagnie Malabar",
    "wof:placetype":"venue"
},
  "geometry": {"coordinates":[4.089205,43.782681],"type":"Point"}
}