{
  "type": "Feature",
  "properties": {
    "iso:country":"DE",
    "sg:address":"Helene-Mayer-Ring 14",
    "sg:city":"M\u00fcnchen",
    "sg:phone":"+49 89/3519081",
    "sg:postcode":"80809",
    "sg:province":"Bayern",
    "wof:name":"Dr. Merk & Dr. Odenthal Apothekenbetriebs Ohg",
    "wof:placetype":"venue"
},
  "geometry": {"coordinates":[11.553006,48.182446],"type":"Point"}
}