{
  "type": "Feature",
  "properties": {
    "iso:country":"DE",
    "sg:address":"Hauptstr. 69",
    "sg:city":"Ginsheim-Gustavsburg",
    "sg:phone":"+49 6144/31752",
    "sg:postcode":"65462",
    "sg:province":"Hessen",
    "wof:name":"O. R. Kuntschik Ingenieur",
    "wof:placetype":"venue"
},
  "geometry": {"coordinates":[8.3472223282,49.9623718262],"type":"Point"}
}