{
  "type": "Feature",
  "properties": {
    "iso:country":"DE",
    "sg:address":"Grimminghausener Weg 3",
    "sg:city":"L\u00f6hne",
    "sg:phone":"+49 5732/7624",
    "sg:postcode":"32584",
    "sg:province":"Nordrhein-Westfalen",
    "wof:name":"Klaus Hammerschmidt",
    "wof:placetype":"venue"
},
  "geometry": {"coordinates":[8.7043457031,52.2306747437],"type":"Point"}
}