{
  "type": "Feature",
  "properties": {
    "iso:country":"DE",
    "sg:address":"Im Moorgrund",
    "sg:city":"Mittelstenahe",
    "sg:phone":"+49 4773/619",
    "sg:postcode":"21770",
    "sg:province":"Niedersachsen",
    "wof:name":"Heinrich Buck",
    "wof:placetype":"venue"
},
  "geometry": {"coordinates":[9.061459,53.662006],"type":"Point"}
}