{
  "type": "Feature",
  "properties": {
    "iso:country":"DE",
    "sg:address":"Segeberger Str. 46",
    "sg:city":"Stockelsdorf",
    "sg:phone":"+49 451/4988656",
    "sg:postcode":"23617",
    "sg:province":"Schleswig-Holstein",
    "wof:name":"Holger Gehrmann",
    "wof:placetype":"venue"
},
  "geometry": {"coordinates":[10.64268,53.888428],"type":"Point"}
}