{
  "type": "Feature",
  "properties": {
    "iso:country":"DE",
    "sg:address":"Morianstr. 32",
    "sg:city":"Wuppertal",
    "sg:phone":"+49 202/550819",
    "sg:postcode":"42103",
    "sg:province":"Nordrhein-Westfalen",
    "wof:name":"Dkv Deutsche Krankenversicherung Ag",
    "wof:placetype":"venue"
},
  "geometry": {"coordinates":[7.1499581337,51.2566452026],"type":"Point"}
}