{
  "type": "Feature",
  "properties": {
    "iso:country":"DE",
    "sg:address":"Elbergen 46",
    "sg:city":"Emsb\u00fcren",
    "sg:phone":"+49 5903/360",
    "sg:postcode":"48488",
    "sg:province":"Niedersachsen",
    "wof:name":"Johann Musekamp",
    "wof:placetype":"venue"
},
  "geometry": {"coordinates":[7.30302,52.443958],"type":"Point"}
}