{
  "type": "Feature",
  "properties": {
    "iso:country":"DE",
    "sg:address":"Scholer S\u00fcnder 13",
    "sg:city":"Engeln",
    "sg:phone":"+49 4252/760",
    "sg:postcode":"27305",
    "sg:province":"Niedersachsen",
    "wof:name":"Ilse Dannemann",
    "wof:placetype":"venue"
},
  "geometry": {"coordinates":[8.9592485428,52.7924346924],"type":"Point"}
}