{
  "type": "Feature",
  "properties": {
    "iso:country":"DE",
    "sg:address":"Ludweilerstr. 209",
    "sg:city":"V\u00f6lklingen",
    "sg:phone":"+49 6898/78709",
    "sg:postcode":"66333",
    "sg:province":"Saarland",
    "wof:name":"G\u00fcnter Calenius",
    "wof:placetype":"venue"
},
  "geometry": {"coordinates":[6.83846,49.243469],"type":"Point"}
}