{
  "type": "Feature",
  "properties": {
    "iso:country":"DE",
    "sg:address":"Postfach 1125",
    "sg:city":"Malsch",
    "sg:phone":"+49 7246",
    "sg:postcode":"76308",
    "sg:province":"Baden-W\u00fcrttemberg",
    "wof:name":"Orientalischer Tanz Mit *ayascha*",
    "wof:placetype":"venue"
},
  "geometry": {"coordinates":[8.3373203278,48.8786811829],"type":"Point"}
}