{
  "type": "Feature",
  "properties": {
    "iso:country":"DE",
    "sg:address":"Dr.-Boecale-Str. 10",
    "sg:city":"Parsberg",
    "sg:phone":"+49 9492/6426",
    "sg:postcode":"92331",
    "sg:province":"Bayern",
    "wof:name":"Dengler",
    "wof:placetype":"venue"
},
  "geometry": {"coordinates":[11.716345787,49.1603317261],"type":"Point"}
}