{
  "type": "Feature",
  "properties": {
    "iso:country":"DE",
    "sg:address":"Im Bantel 7",
    "sg:city":"Altheim",
    "sg:phone":"+49 7340/6383",
    "sg:postcode":"89174",
    "sg:province":"Baden-W\u00fcrttemberg",
    "wof:name":"Ernst Mayer",
    "wof:placetype":"venue"
},
  "geometry": {"coordinates":[10.024704,48.582233],"type":"Point"}
}