{
  "type": "Feature",
  "properties": {
    "iso:country":"DE",
    "sg:address":"Am Apfelberg 18",
    "sg:city":"T\u00fcbingen",
    "sg:phone":"+49 7071/965914",
    "sg:postcode":"72076",
    "sg:province":"Baden-W\u00fcrttemberg",
    "wof:name":"Redaktion Deutschland In Geschichte Und Gegenwart",
    "wof:placetype":"venue"
},
  "geometry": {"coordinates":[9.0522985458,48.5338935852],"type":"Point"}
}