{
  "type": "Feature",
  "properties": {
    "iso:country":"DE",
    "sg:address":"W\u00f6rrst\u00e4dter Str. 31",
    "sg:city":"Schornsheim",
    "sg:phone":"+49 6732/64294",
    "sg:postcode":"55288",
    "sg:province":"Rheinland-Pfalz",
    "wof:name":"Rainer Weifenbach",
    "wof:placetype":"venue"
},
  "geometry": {"coordinates":[8.1730575562,49.8430290222],"type":"Point"}
}