{
  "type": "Feature",
  "properties": {
    "iso:country":"DE",
    "sg:address":"Am Schwaigfeld 5",
    "sg:city":"Neuried",
    "sg:phone":"+49 89/7591567",
    "sg:postcode":"82061",
    "sg:province":"Bayern",
    "wof:name":"Jakob Reiter Gmbh & Co. Kg",
    "wof:placetype":"venue"
},
  "geometry": {"coordinates":[11.4694461823,48.0926704407],"type":"Point"}
}