{
  "type": "Feature",
  "properties": {
    "iso:country":"DE",
    "sg:address":"Saaledamm 2",
    "sg:city":"Elze",
    "sg:phone":"+49 5068/4213",
    "sg:postcode":"31008",
    "sg:province":"Niedersachsen",
    "wof:name":"W. Sch\u00e4fer Gmbh",
    "wof:placetype":"venue"
},
  "geometry": {"coordinates":[9.738177,52.115471],"type":"Point"}
}