{
  "type": "Feature",
  "properties": {
    "iso:country":"DE",
    "sg:address":"Am Holz 20",
    "sg:city":"Dietramszell",
    "sg:phone":"+49 8171/78366",
    "sg:postcode":"83623",
    "sg:province":"Bayern",
    "wof:name":"Holzwirt",
    "wof:placetype":"venue"
},
  "geometry": {"coordinates":[11.4879560471,47.8908882141],"type":"Point"}
}