{
  "type": "Feature",
  "properties": {
    "iso:country":"DE",
    "sg:address":"Bahnhofstr. 11",
    "sg:city":"Geislingen",
    "sg:phone":"+49 7331/43612",
    "sg:postcode":"73312",
    "sg:province":"Baden-W\u00fcrttemberg",
    "wof:name":"Wolfgang Str\u00f6hlen",
    "wof:placetype":"venue"
},
  "geometry": {"coordinates":[9.842614,48.616631],"type":"Point"}
}