{
  "type": "Feature",
  "properties": {
    "iso:country":"DE",
    "sg:address":"Borsigstr. 8",
    "sg:city":"Weil der Stadt",
    "sg:phone":"+49 7033/33796",
    "sg:postcode":"71263",
    "sg:province":"Baden-W\u00fcrttemberg",
    "wof:name":"Klauser Metallwaren Gmbh",
    "wof:placetype":"venue"
},
  "geometry": {"coordinates":[8.826843,48.774857],"type":"Point"}
}