{
  "type": "Feature",
  "properties": {
    "iso:country":"DE",
    "sg:address":"Zum G\u00fcterbahnhof 22",
    "sg:city":"Erfurt",
    "sg:phone":"+49 361/5668101",
    "sg:postcode":"99085",
    "sg:province":"Th\u00fcringen",
    "wof:name":"Gebr. Eisleb Transport Gmbh",
    "wof:placetype":"venue"
},
  "geometry": {"coordinates":[11.044090271,50.974521637],"type":"Point"}
}