{
  "type": "Feature",
  "properties": {
    "iso:country":"DE",
    "sg:address":"Hempenkamp 3",
    "sg:city":"Hamburg",
    "sg:phone":"+49 40/6034236",
    "sg:postcode":"22359",
    "sg:province":"Hamburg",
    "wof:name":"H.-d. Scheube Ingenieur",
    "wof:placetype":"venue"
},
  "geometry": {"coordinates":[10.1790857315,53.650062561],"type":"Point"}
}