{
  "type": "Feature",
  "properties": {
    "iso:country":"DE",
    "sg:address":"Bahnhofstr. 1",
    "sg:city":"Hattorf",
    "sg:phone":"+49 5584/2202",
    "sg:postcode":"37197",
    "sg:province":"Niedersachsen",
    "wof:name":"Bistro Amadeus",
    "wof:placetype":"venue"
},
  "geometry": {"coordinates":[10.2371683121,51.6459732056],"type":"Point"}
}