{
  "type": "Feature",
  "properties": {
    "iso:country":"DE",
    "sg:address":"Z\u00fclpicher Str. 38",
    "sg:city":"K\u00f6ln",
    "sg:phone":"+49 221/239398",
    "sg:postcode":"50674",
    "sg:province":"Nordrhein-Westfalen",
    "wof:name":"Transglobe Richard Helmrich",
    "wof:placetype":"venue"
},
  "geometry": {"coordinates":[6.936996,50.929161],"type":"Point"}
}