{
  "type": "Feature",
  "properties": {
    "iso:country":"DE",
    "sg:address":"Seeseitener Str. 9 b",
    "sg:city":"Seeshaupt",
    "sg:phone":"+49 8801/2960",
    "sg:postcode":"82402",
    "sg:province":"Bayern",
    "wof:name":"Unawave Datentechnik Gmbh",
    "wof:placetype":"venue"
},
  "geometry": {"coordinates":[11.2865619659,47.824848175],"type":"Point"}
}