{
  "type": "Feature",
  "properties": {
    "iso:country":"DE",
    "sg:address":"Augsburger Str. 11/2",
    "sg:city":"Augsburg",
    "sg:phone":"+49 821/529282",
    "sg:postcode":"86157",
    "sg:province":"Bayern",
    "wof:name":"Karl R\u00f6sch",
    "wof:placetype":"venue"
},
  "geometry": {"coordinates":[10.873692,48.363529],"type":"Point"}
}