{
  "type": "Feature",
  "properties": {
    "iso:country":"DE",
    "sg:address":"Goethestr. 19",
    "sg:city":"Ertingen",
    "sg:phone":"+49 7371/6546",
    "sg:postcode":"88521",
    "sg:province":"Baden-W\u00fcrttemberg",
    "wof:name":"Heinrich Klarmann Architekt",
    "wof:placetype":"venue"
},
  "geometry": {"coordinates":[9.467435,48.105408],"type":"Point"}
}