{
  "type": "Feature",
  "properties": {
    "iso:country":"DE",
    "sg:address":"Ludwigstr. 22",
    "sg:city":"Waldsee",
    "sg:phone":"+49 6236/51116",
    "sg:postcode":"67165",
    "sg:province":"Rheinland-Pfalz",
    "wof:name":"Eiscafe Dolomiti",
    "wof:placetype":"venue"
},
  "geometry": {"coordinates":[8.441193,49.394703],"type":"Point"}
}