{
  "type": "Feature",
  "properties": {
    "iso:country":"DE",
    "sg:address":"Oberer Winkel 8",
    "sg:city":"Talheim",
    "sg:phone":"+49 7464/3434",
    "sg:postcode":"78607",
    "sg:province":"Baden-W\u00fcrttemberg",
    "wof:name":"R. Marquardt",
    "wof:placetype":"venue"
},
  "geometry": {"coordinates":[8.6621904373,48.0116958618],"type":"Point"}
}