{
  "type": "Feature",
  "properties": {
    "iso:country":"DE",
    "sg:address":"Pettenkofer Str. 17A",
    "sg:city":"Berlin",
    "sg:phone":"+49 30/422810",
    "sg:postcode":"10247",
    "sg:province":"Berlin",
    "wof:name":"Astron Telemarketing Gmbh",
    "wof:placetype":"venue"
},
  "geometry": {"coordinates":[13.471307,52.518204],"type":"Point"}
}