{
  "type": "Feature",
  "properties": {
    "iso:country":"DE",
    "sg:address":"Vor der Reihe 19",
    "sg:city":"Gro\u00dfenkneten",
    "sg:phone":"+49 4407/368",
    "sg:postcode":"26197",
    "sg:province":"Niedersachsen",
    "wof:name":"Hans-g. Jaeger",
    "wof:placetype":"venue"
},
  "geometry": {"coordinates":[8.14413,52.995232],"type":"Point"}
}