{
  "type": "Feature",
  "properties": {
    "iso:country":"DE",
    "sg:address":"Brinkstr. 25",
    "sg:city":"Offenbach",
    "sg:phone":"+49 69/832245",
    "sg:postcode":"63069",
    "sg:province":"Hessen",
    "wof:name":"Hans Joachim Laun Architekt",
    "wof:placetype":"venue"
},
  "geometry": {"coordinates":[8.759427,50.093327],"type":"Point"}
}