{
  "type": "Feature",
  "properties": {
    "iso:country":"DE",
    "sg:address":"Hagenstr. 33",
    "sg:city":"Nordhorn",
    "sg:phone":"+49 5921/4114",
    "sg:postcode":"48529",
    "sg:province":"Niedersachsen",
    "wof:name":"B\u00e4rlinchen",
    "wof:placetype":"venue"
},
  "geometry": {"coordinates":[7.0711231232,52.4369812012],"type":"Point"}
}