{
  "type": "Feature",
  "properties": {
    "iso:country":"DE",
    "sg:address":"Neupforte 17",
    "sg:city":"Saulheim",
    "sg:phone":"+49 6732/61610",
    "sg:postcode":"55291",
    "sg:province":"Rheinland-Pfalz",
    "wof:name":"Raiffeisen Warengenossenschaft Eg",
    "wof:placetype":"venue"
},
  "geometry": {"coordinates":[8.146609,49.875656],"type":"Point"}
}