{
  "type": "Feature",
  "properties": {
    "iso:country":"DE",
    "sg:address":"Koppelweg 8",
    "sg:city":"Garbsen",
    "sg:phone":"+49 4951/312548",
    "sg:postcode":"30826",
    "sg:province":"Niedersachsen",
    "wof:name":"Karl Heinz Pracht",
    "wof:placetype":"venue"
},
  "geometry": {"coordinates":[9.5521421432,52.466999054],"type":"Point"}
}