{
  "type": "Feature",
  "properties": {
    "iso:country":"DE",
    "sg:address":"Heringer Fahrweg 11",
    "sg:city":"H\u00fcnfelden",
    "sg:phone":"+49 6438/3078",
    "sg:postcode":"65597",
    "sg:province":"Hessen",
    "wof:name":"Hml Multilayerpressen Gmbh",
    "wof:placetype":"venue"
},
  "geometry": {"coordinates":[8.150895,50.311371],"type":"Point"}
}