{
  "type": "Feature",
  "properties": {
    "iso:country":"DE",
    "sg:address":"Am Sch\u00fctthook 137",
    "sg:city":"M\u00fcnster",
    "sg:postcode":"48167",
    "sg:province":"Nordrhein-Westfalen",
    "wof:name":"Yacht Management M\u00fcnster Gmbh & Co. Kg",
    "wof:placetype":"venue"
},
  "geometry": {"coordinates":[7.6951408386,51.9169120789],"type":"Point"}
}