{
  "type": "Feature",
  "properties": {
    "iso:country":"DE",
    "sg:address":"Werftstr. 20-22",
    "sg:city":"D\u00fcsseldorf",
    "sg:phone":"+49 211/5228070",
    "sg:postcode":"40549",
    "sg:province":"Nordrhein-Westfalen",
    "wof:name":"Sompex Handels-gmbh & Co Kg",
    "wof:placetype":"venue"
},
  "geometry": {"coordinates":[6.715959,51.227989],"type":"Point"}
}