{
  "type": "Feature",
  "properties": {
    "iso:country":"DE",
    "sg:address":"An der Malzm\u00fchle 5",
    "sg:city":"Wernigerode",
    "sg:phone":"+49 3943/632463",
    "sg:postcode":"38855",
    "sg:province":"Sachsen-Anhalt",
    "wof:name":"Burkhard Huch",
    "wof:placetype":"venue"
},
  "geometry": {"coordinates":[10.7790403366,51.8311691284],"type":"Point"}
}