{
  "type": "Feature",
  "properties": {
    "iso:country":"DE",
    "sg:address":"M\u00fchlbachstr. 19",
    "sg:city":"Bayerbach",
    "sg:phone":"+49 4971/712467",
    "sg:postcode":"84092",
    "sg:province":"Bayern",
    "wof:name":"Adolf Besson Kg",
    "wof:placetype":"venue"
},
  "geometry": {"coordinates":[9.800811,48.796108],"type":"Point"}
}