{
  "type": "Feature",
  "properties": {
    "iso:country":"DE",
    "sg:address":"Gartenstr. 17",
    "sg:city":"Frankfurt",
    "sg:phone":"+49 69/618062",
    "sg:postcode":"60594",
    "sg:province":"Hessen",
    "wof:name":"Wein-yard",
    "wof:placetype":"venue"
},
  "geometry": {"coordinates":[8.6801586151,50.1034049988],"type":"Point"}
}