{
  "type": "Feature",
  "properties": {
    "iso:country":"DE",
    "sg:address":"Moerser Str. 401",
    "sg:city":"Krefeld",
    "sg:phone":"+49 2151/500019",
    "sg:postcode":"47803",
    "sg:province":"Nordrhein-Westfalen",
    "wof:name":"Enger-commerz Gmbh",
    "wof:placetype":"venue"
},
  "geometry": {"coordinates":[6.575335,51.352306],"type":"Point"}
}