{
  "type": "Feature",
  "properties": {
    "iso:country":"DE",
    "sg:address":"Carl-Sonnenschein Stra\u00dfe 51",
    "sg:city":"Frankfurt",
    "sg:phone":"+49 69",
    "sg:postcode":"65936",
    "sg:province":"Hessen",
    "wof:name":"Pauli Schaltanlagen Gmbh",
    "wof:placetype":"venue"
},
  "geometry": {"coordinates":[8.573703,50.127201],"type":"Point"}
}