{
  "type": "Feature",
  "properties": {
    "iso:country":"DE",
    "sg:address":"Heinrich-Zille-Str. 4",
    "sg:city":"Hanau",
    "sg:phone":"+49 6181/53455",
    "sg:postcode":"63457",
    "sg:province":"Hessen",
    "wof:name":"Dieter Wagner",
    "wof:placetype":"venue"
},
  "geometry": {"coordinates":[8.9562368393,50.1068382263],"type":"Point"}
}