{
  "type": "Feature",
  "properties": {
    "iso:country":"DE",
    "sg:address":"Ottostr 6",
    "sg:city":"Eggenstein-Leopoldshafen",
    "sg:phone":"+49 721/788337",
    "sg:postcode":"76344",
    "sg:province":"Baden-W\u00fcrttemberg",
    "wof:name":"Knobloch Spedition & Logistik Gmbh",
    "wof:placetype":"venue"
},
  "geometry": {"coordinates":[8.380142,49.073238],"type":"Point"}
}