{
  "type": "Feature",
  "properties": {
    "iso:country":"DE",
    "sg:address":"D\u00fcsseldorfer Str. 63",
    "sg:city":"M\u00fclheim",
    "sg:phone":"+49 208/481323",
    "sg:postcode":"45481",
    "sg:province":"Nordrhein-Westfalen",
    "wof:name":"Spitzweg-apotheke",
    "wof:placetype":"venue"
},
  "geometry": {"coordinates":[6.875587,51.404346],"type":"Point"}
}