{
  "type": "Feature",
  "properties": {
    "iso:country":"DE",
    "sg:address":"Friedrich-Ebert-Str. 17-25",
    "sg:city":"M\u00fcnster",
    "sg:phone":"+49 251/520040",
    "sg:postcode":"48153",
    "sg:province":"Nordrhein-Westfalen",
    "wof:name":"H\u00fclskamp Gmbh & Co. Eisenwaren, Baubeschl\u00e4ge",
    "wof:placetype":"venue"
},
  "geometry": {"coordinates":[7.632321,51.952202],"type":"Point"}
}