{
  "type": "Feature",
  "properties": {
    "iso:country":"DE",
    "sg:address":"Berliner Str. 60",
    "sg:city":"Sundern",
    "sg:phone":"+49 2933/4947",
    "sg:postcode":"59846",
    "sg:province":"Nordrhein-Westfalen",
    "wof:name":"Hallenbad",
    "wof:placetype":"venue"
},
  "geometry": {"coordinates":[8.0023298264,51.3198623657],"type":"Point"}
}