{
  "type": "Feature",
  "properties": {
    "iso:country":"DE",
    "sg:address":"Otto-Hahn-Str. 8",
    "sg:city":"Wickede",
    "sg:phone":"+49 2377/92810",
    "sg:postcode":"58739",
    "sg:province":"Nordrhein-Westfalen",
    "wof:name":"Dieter Hermes Metallverarbeitungs Gmbh",
    "wof:placetype":"venue"
},
  "geometry": {"coordinates":[7.8718938828,51.5096168518],"type":"Point"}
}