{
  "type": "Feature",
  "properties": {
    "iso:country":"DE",
    "sg:address":"K\u00f6lner Str. 86",
    "sg:city":"Leverkusen",
    "sg:phone":"+49 2171/47085",
    "sg:postcode":"51379",
    "sg:province":"Nordrhein-Westfalen",
    "wof:name":"Int. Messebau Gmbh",
    "wof:placetype":"venue"
},
  "geometry": {"coordinates":[7.003655,51.062332],"type":"Point"}
}