{
  "type": "Feature",
  "properties": {
    "iso:country":"DE",
    "sg:address":"Tannenweg 12",
    "sg:city":"Herten",
    "sg:phone":"+49 2366/31168",
    "sg:postcode":"45699",
    "sg:province":"Nordrhein-Westfalen",
    "wof:name":"Horst Hapke Ingenieur",
    "wof:placetype":"venue"
},
  "geometry": {"coordinates":[7.1439089775,51.6000289917],"type":"Point"}
}