{
  "type": "Feature",
  "properties": {
    "iso:country":"DE",
    "sg:address":"Habichtsring 9a",
    "sg:city":"Ilmenau",
    "sg:phone":"+49 3677/20703",
    "sg:postcode":"98693",
    "sg:province":"Th\u00fcringen",
    "wof:name":"Sibatec Gmbh",
    "wof:placetype":"venue"
},
  "geometry": {"coordinates":[10.9090642929,50.7006225586],"type":"Point"}
}