{
  "type": "Feature",
  "properties": {
    "iso:country":"DE",
    "sg:address":"Osnabr\u00fccker Str. 29",
    "sg:city":"Bad Iburg",
    "sg:phone":"+49 5403/780123",
    "sg:postcode":"49186",
    "sg:province":"Niedersachsen",
    "wof:name":"Jibi",
    "wof:placetype":"venue"
},
  "geometry": {"coordinates":[8.0501747131,52.1625556946],"type":"Point"}
}