{
  "type": "Feature",
  "properties": {
    "iso:country":"DE",
    "sg:address":"In den Engmatten 4",
    "sg:city":"Glottertal",
    "sg:phone":"+49 7684/353",
    "sg:postcode":"79286",
    "sg:province":"Baden-W\u00fcrttemberg",
    "wof:name":"Omnibus Rieder Gmbh",
    "wof:placetype":"venue"
},
  "geometry": {"coordinates":[7.9345149994,48.0502166748],"type":"Point"}
}