{
  "type": "Feature",
  "properties": {
    "iso:country":"DE",
    "sg:address":"Ulmenstr. 236 b",
    "sg:city":"D\u00fcsseldorf",
    "sg:phone":"+49 211/4220675",
    "sg:postcode":"40468",
    "sg:province":"Nordrhein-Westfalen",
    "wof:name":"Fritz Faltin",
    "wof:placetype":"venue"
},
  "geometry": {"coordinates":[6.777611,51.259621],"type":"Point"}
}