{
  "type": "Feature",
  "properties": {
    "iso:country":"DE",
    "sg:address":"B\u00fcchelstein 8",
    "sg:city":"Grattersdorf",
    "sg:postcode":"94541",
    "sg:province":"Bayern",
    "wof:name":"Waldcafe Pension Kreuzstra\u00dfl Gmbh",
    "wof:placetype":"venue"
},
  "geometry": {"coordinates":[13.186346,48.805622],"type":"Point"}
}