{
  "type": "Feature",
  "properties": {
    "iso:country":"DE",
    "sg:address":"Karlsh\u00f6he 27",
    "sg:city":"Hamburg",
    "sg:phone":"+49 40/6405070",
    "sg:postcode":"22175",
    "sg:province":"Hamburg",
    "wof:name":"Haus Der 131 Biere Inh. Christl Stark",
    "wof:placetype":"venue"
},
  "geometry": {"coordinates":[10.109166,53.62571],"type":"Point"}
}