{
  "type": "Feature",
  "properties": {
    "iso:country":"DE",
    "sg:address":"Hirschstr. 7",
    "sg:city":"K\u00f6ngen",
    "sg:postcode":"73257",
    "sg:province":"Baden-W\u00fcrttemberg",
    "wof:name":"Aem-altlasten- Und Entsorgungsmanagement Gmbh",
    "wof:placetype":"venue"
},
  "geometry": {"coordinates":[9.3630161285,48.6843070984],"type":"Point"}
}