{
  "type": "Feature",
  "properties": {
    "iso:country":"DE",
    "sg:address":"Dorfstr. 32",
    "sg:city":"Glasow",
    "sg:postcode":"17322",
    "sg:province":"Mecklenburg-Vorpommern",
    "wof:name":"Landservice Gmbh",
    "wof:placetype":"venue"
},
  "geometry": {"coordinates":[14.27424,53.379055],"type":"Point"}
}