{
  "type": "Feature",
  "properties": {
    "iso:country":"DE",
    "sg:address":"Am Kirchplatz 7",
    "sg:city":"Feldafing",
    "sg:phone":"+49 8157/1237",
    "sg:postcode":"82340",
    "sg:province":"Bayern",
    "wof:name":"Gisela Hummel",
    "wof:placetype":"venue"
},
  "geometry": {"coordinates":[11.2965421677,47.9501228333],"type":"Point"}
}