{
  "type": "Feature",
  "properties": {
    "iso:country":"DE",
    "sg:address":"Lindenallee 2",
    "sg:city":"Fredersdorf",
    "sg:phone":"+49 33439/80041",
    "sg:postcode":"15370",
    "sg:province":"Brandenburg",
    "wof:name":"Karin Hoppe",
    "wof:placetype":"venue"
},
  "geometry": {"coordinates":[13.754819,52.526917],"type":"Point"}
}