{
  "type": "Feature",
  "properties": {
    "iso:country":"DE",
    "sg:address":"Goethestr. 23",
    "sg:city":"Rathenow",
    "sg:phone":"+49 3385/503602",
    "sg:postcode":"14712",
    "sg:province":"Brandenburg",
    "wof:name":"B. Zick",
    "wof:placetype":"venue"
},
  "geometry": {"coordinates":[12.3452110291,52.6088218689],"type":"Point"}
}