{
  "type": "Feature",
  "properties": {
    "iso:country":"DE",
    "sg:address":"Dorfstr. 17",
    "sg:city":"Freudenberg",
    "sg:phone":"+49 9627/296",
    "sg:postcode":"92272",
    "sg:province":"Bayern",
    "wof:name":"Josef Schlosser",
    "wof:placetype":"venue"
},
  "geometry": {"coordinates":[12.011181,49.442837],"type":"Point"}
}