{
  "type": "Feature",
  "properties": {
    "iso:country":"DE",
    "sg:address":"N\u00f6ckersberg 72a",
    "sg:city":"Essen",
    "sg:phone":"+49 201/485307",
    "sg:postcode":"45257",
    "sg:province":"Nordrhein-Westfalen",
    "wof:name":"Lenk Und Mertens Architekten",
    "wof:placetype":"venue"
},
  "geometry": {"coordinates":[7.096632,51.406021],"type":"Point"}
}