{
  "type": "Feature",
  "properties": {
    "iso:country":"DE",
    "sg:address":"Kirchgasse 10",
    "sg:city":"Wimsheim",
    "sg:phone":"+49 7044/41410",
    "sg:postcode":"71299",
    "sg:province":"Baden-W\u00fcrttemberg",
    "wof:name":"Ev. Pfarramt",
    "wof:placetype":"venue"
},
  "geometry": {"coordinates":[8.8272066116,48.8525505066],"type":"Point"}
}