{
  "type": "Feature",
  "properties": {
    "iso:country":"DE",
    "sg:address":"Sonnensteig 4",
    "sg:city":"Passau",
    "sg:phone":"+49 851/44235",
    "sg:postcode":"94034",
    "sg:province":"Bayern",
    "wof:name":"Herbert Schedina Architekt",
    "wof:placetype":"venue"
},
  "geometry": {"coordinates":[13.477189,48.58337],"type":"Point"}
}