{
  "type": "Feature",
  "properties": {
    "iso:country":"DE",
    "sg:address":"Rietberger Str. 86",
    "sg:city":"Rheda-Wiedenbr\u00fcck",
    "sg:phone":"+49 5242/2008",
    "sg:postcode":"33378",
    "sg:province":"Nordrhein-Westfalen",
    "wof:name":"Altenau Gmbh",
    "wof:placetype":"venue"
},
  "geometry": {"coordinates":[8.362133,51.829056],"type":"Point"}
}