{
  "type": "Feature",
  "properties": {
    "iso:country":"DE",
    "sg:address":"Bachstr. 22",
    "sg:city":"Zahna",
    "sg:phone":"+49 34924/20664",
    "sg:postcode":"06895",
    "sg:province":"Sachsen-Anhalt",
    "wof:name":"Harnisch Messebau",
    "wof:placetype":"venue"
},
  "geometry": {"coordinates":[12.79059,51.923264],"type":"Point"}
}