{
  "type": "Feature",
  "properties": {
    "iso:country":"DE",
    "sg:address":"Karth\u00e4userstr. 8",
    "sg:city":"Saarlouis",
    "sg:phone":"+49 6831/895960",
    "sg:postcode":"66740",
    "sg:province":"Saarland",
    "wof:name":"Karin Betz Steurberater",
    "wof:placetype":"venue"
},
  "geometry": {"coordinates":[6.7644538879,49.327331543],"type":"Point"}
}