{
  "type": "Feature",
  "properties": {
    "iso:country":"DE",
    "sg:address":"W\u00f6lfersheimer Weg 14",
    "sg:city":"Bad Nauheim",
    "sg:phone":"+49 6032/84931",
    "sg:postcode":"61231",
    "sg:province":"Hessen",
    "wof:name":"Birgit Stock",
    "wof:placetype":"venue"
},
  "geometry": {"coordinates":[8.7646532059,50.3781356812],"type":"Point"}
}