{
  "type": "Feature",
  "properties": {
    "iso:country":"DE",
    "sg:address":"Zettlitzer Str. 11",
    "sg:city":"Kulmbach",
    "sg:phone":"+49 9221/64139",
    "sg:postcode":"95326",
    "sg:province":"Bayern",
    "wof:name":"Prestige Werbetechnik Gmbh",
    "wof:placetype":"venue"
},
  "geometry": {"coordinates":[11.41572,50.089886],"type":"Point"}
}