{
  "type": "Feature",
  "properties": {
    "iso:country":"DE",
    "sg:address":"N\u00fcmmener Feld 1",
    "sg:city":"Solingen",
    "sg:phone":"+49 212/546990",
    "sg:postcode":"42719",
    "sg:province":"Nordrhein-Westfalen",
    "wof:name":"Robert M\u00fcllenschl\u00e4der Gmbh",
    "wof:placetype":"venue"
},
  "geometry": {"coordinates":[7.0691199303,51.1925392151],"type":"Point"}
}