{
  "type": "Feature",
  "properties": {
    "iso:country":"DE",
    "sg:address":"Markt 14",
    "sg:city":"Penig",
    "sg:phone":"+49 37381/82330",
    "sg:postcode":"09322",
    "sg:province":"Sachsen",
    "wof:name":"G\u00fcnter Ahnert",
    "wof:placetype":"venue"
},
  "geometry": {"coordinates":[12.7062864304,50.9336357117],"type":"Point"}
}