{
  "type": "Feature",
  "properties": {
    "iso:country":"DE",
    "sg:address":"S\u00fcdstr. 17",
    "sg:city":"Blankenhain",
    "sg:phone":"+49 36459/62657",
    "sg:postcode":"99444",
    "sg:province":"Th\u00fcringen",
    "wof:name":"Waltraud Schmidt",
    "wof:placetype":"venue"
},
  "geometry": {"coordinates":[11.3397865295,50.8568077087],"type":"Point"}
}