{
  "type": "Feature",
  "properties": {
    "iso:country":"DE",
    "sg:address":"Altdorfer Str. 16",
    "sg:city":"Holzgerlingen",
    "sg:phone":"+49 7031/603509",
    "sg:postcode":"71088",
    "sg:province":"Baden-W\u00fcrttemberg",
    "wof:name":"Rainer Schmidt",
    "wof:placetype":"venue"
},
  "geometry": {"coordinates":[9.009368,48.636692],"type":"Point"}
}