{
  "type": "Feature",
  "properties": {
    "iso:country":"DE",
    "sg:address":"Burgstr. 12",
    "sg:city":"Zeltingen-Rachtig",
    "sg:phone":"+49 6532/3426",
    "sg:postcode":"54492",
    "sg:province":"Rheinland-Pfalz",
    "wof:name":"Heribert Glesius Weinanbau",
    "wof:placetype":"venue"
},
  "geometry": {"coordinates":[7.0212578773,49.9523429871],"type":"Point"}
}