{
  "type": "Feature",
  "properties": {
    "iso:country":"DE",
    "sg:address":"Lindenstr. 2",
    "sg:city":"Brunnen",
    "sg:phone":"+49 8454/3330",
    "sg:postcode":"86564",
    "sg:province":"Bayern",
    "wof:name":"Ernst Schwarzbauer",
    "wof:placetype":"venue"
},
  "geometry": {"coordinates":[11.360978,48.632729],"type":"Point"}
}