{
  "type": "Feature",
  "properties": {
    "iso:country":"DE",
    "sg:address":"Goethestr. 87",
    "sg:city":"D\u00fcsseldorf",
    "sg:phone":"+49 211/6914663",
    "sg:postcode":"40237",
    "sg:province":"Nordrhein-Westfalen",
    "wof:name":"K\u00e4mpfe & Gro\u00dfbach",
    "wof:placetype":"venue"
},
  "geometry": {"coordinates":[6.8093690872,51.2339134216],"type":"Point"}
}