{
  "type": "Feature",
  "properties": {
    "iso:country":"DE",
    "sg:address":"Auenweg 4",
    "sg:city":"Erwitte",
    "sg:phone":"+49 2943/870559",
    "sg:postcode":"59597",
    "sg:province":"Nordrhein-Westfalen",
    "wof:name":"I. Mertins",
    "wof:placetype":"venue"
},
  "geometry": {"coordinates":[8.326895,51.616783],"type":"Point"}
}