{
  "type": "Feature",
  "properties": {
    "iso:country":"DE",
    "sg:address":"Ammerl\u00e4nder Str. 2",
    "sg:city":"Brake",
    "sg:phone":"+49 4401/6558",
    "sg:postcode":"26919",
    "sg:province":"Niedersachsen",
    "wof:name":"Sagcob",
    "wof:placetype":"venue"
},
  "geometry": {"coordinates":[8.4776315689,53.3352508545],"type":"Point"}
}