{
  "type": "Feature",
  "properties": {
    "iso:country":"DE",
    "sg:address":"Kaiserstr. 89",
    "sg:city":"Bruchm\u00fchlbach-Miesau",
    "sg:phone":"+49 6372/2469",
    "sg:postcode":"66892",
    "sg:province":"Rheinland-Pfalz",
    "wof:name":"Armin Stenger Rechtsanwalt",
    "wof:placetype":"venue"
},
  "geometry": {"coordinates":[7.4161868095,49.3769226074],"type":"Point"}
}