{
  "type": "Feature",
  "properties": {
    "iso:country":"DE",
    "sg:address":"Walzm\u00fchlenstr. 65",
    "sg:city":"Ludwigshafen",
    "sg:phone":"+49 4906/21",
    "sg:postcode":"67061",
    "sg:province":"Rheinland-Pfalz",
    "wof:name":"Willkommen Im Pflaumenbaum Ludwigshafen, Party",
    "wof:placetype":"venue"
},
  "geometry": {"coordinates":[8.454897,49.479046],"type":"Point"}
}