{
  "type": "Feature",
  "properties": {
    "iso:country":"DE",
    "sg:address":"Auf dem Rain 2",
    "sg:city":"Erndtebr\u00fcck",
    "sg:phone":"+49 2753/2222",
    "sg:postcode":"57339",
    "sg:province":"Nordrhein-Westfalen",
    "wof:name":"O. Und F. Simon",
    "wof:placetype":"venue"
},
  "geometry": {"coordinates":[8.258035,50.989658],"type":"Point"}
}