{
  "type": "Feature",
  "properties": {
    "iso:country":"DE",
    "sg:address":"Doosthof 36",
    "sg:city":"Ahlerstedt",
    "sg:phone":"+49 4166/7657",
    "sg:postcode":"21702",
    "sg:province":"Niedersachsen",
    "wof:name":"Martin Krause Architekt",
    "wof:placetype":"venue"
},
  "geometry": {"coordinates":[9.41878,53.439758],"type":"Point"}
}