{
  "type": "Feature",
  "properties": {
    "iso:country":"DE",
    "sg:address":"Neudammstr. 8",
    "sg:city":"Braunschweig",
    "sg:phone":"+49 531/512272",
    "sg:postcode":"38116",
    "sg:province":"Niedersachsen",
    "wof:name":"Bethge",
    "wof:placetype":"venue"
},
  "geometry": {"coordinates":[10.445103,52.269672],"type":"Point"}
}