{
  "type": "Feature",
  "properties": {
    "iso:country":"DE",
    "sg:address":"L\u00fcneburger Damm 2",
    "sg:city":"Hannover",
    "sg:phone":"+49 511/575703",
    "sg:postcode":"30625",
    "sg:province":"Niedersachsen",
    "wof:name":"Ev. Pfarramt Nikodemus Kirche",
    "wof:placetype":"venue"
},
  "geometry": {"coordinates":[9.8144216537,52.3781547546],"type":"Point"}
}