{
  "type": "Feature",
  "properties": {
    "iso:country":"DE",
    "sg:address":"Ladberger Str. 104",
    "sg:city":"Lengerich",
    "sg:phone":"+49 5481/6900",
    "sg:postcode":"49525",
    "sg:province":"Nordrhein-Westfalen",
    "wof:name":"Friedrich Bl\u00f6mker B\u00e4ckerei",
    "wof:placetype":"venue"
},
  "geometry": {"coordinates":[7.801054,52.161072],"type":"Point"}
}