{
  "type": "Feature",
  "properties": {
    "iso:country":"DE",
    "sg:address":"K\u00f6nigsteiner Str. 13 b",
    "sg:city":"Glash\u00fctten",
    "sg:postcode":"61479",
    "sg:province":"Hessen",
    "wof:name":"Inspiration Gesellschaft F\u00fcr Marketing",
    "wof:placetype":"venue"
},
  "geometry": {"coordinates":[8.3848142624,50.1981163025],"type":"Point"}
}