{
  "type": "Feature",
  "properties": {
    "iso:country":"DE",
    "sg:address":"Lange Str. 64",
    "sg:city":"Worbis",
    "sg:phone":"+49 36074/92333",
    "sg:postcode":"37339",
    "sg:province":"Th\u00fcringen",
    "wof:name":"Wilhelm Hunold",
    "wof:placetype":"venue"
},
  "geometry": {"coordinates":[10.3602581024,51.421913147],"type":"Point"}
}