{
  "type": "Feature",
  "properties": {
    "iso:country":"DE",
    "sg:address":"Sandweg 12",
    "sg:city":"Wettstetten",
    "sg:phone":"+49 841/390157",
    "sg:postcode":"85139",
    "sg:province":"Bayern",
    "wof:name":"Isi-tech Vertriebs Gmbh",
    "wof:placetype":"venue"
},
  "geometry": {"coordinates":[11.4142589569,48.8296089172],"type":"Point"}
}