{
  "type": "Feature",
  "properties": {
    "iso:country":"DE",
    "sg:address":"Weichselstr. 7",
    "sg:city":"B\u00fcdelsdorf",
    "sg:phone":"+49 4331/31314",
    "sg:postcode":"24782",
    "sg:province":"Schleswig-Holstein",
    "wof:name":"Hans Tams",
    "wof:placetype":"venue"
},
  "geometry": {"coordinates":[9.683341,54.315414],"type":"Point"}
}