{
  "type": "Feature",
  "properties": {
    "iso:country":"DE",
    "sg:address":"Rosenstr. 18-28",
    "sg:city":"Marburg",
    "sg:postcode":"35037",
    "sg:province":"Hessen",
    "wof:name":"Rosenpark Med Gmbh",
    "wof:placetype":"venue"
},
  "geometry": {"coordinates":[8.768971,50.819046],"type":"Point"}
}