{
  "type": "Feature",
  "properties": {
    "iso:country":"DE",
    "sg:address":"Sandbergstr. 2",
    "sg:city":"H\u00f6rstel",
    "sg:phone":"+49 5459/8344",
    "sg:postcode":"48477",
    "sg:province":"Nordrhein-Westfalen",
    "wof:name":"Ingrid Seveneick",
    "wof:placetype":"venue"
},
  "geometry": {"coordinates":[7.582285,52.298409],"type":"Point"}
}