{
  "type": "Feature",
  "properties": {
    "iso:country":"DE",
    "sg:address":"J\u00e4gerstr. 11",
    "sg:city":"Celle",
    "sg:phone":"+49 5141/7872",
    "sg:postcode":"29221",
    "sg:province":"Niedersachsen",
    "wof:name":"Hermann Langenheim",
    "wof:placetype":"venue"
},
  "geometry": {"coordinates":[10.071548,52.617348],"type":"Point"}
}