{
  "type": "Feature",
  "properties": {
    "iso:country":"DE",
    "sg:address":"Schillerstr. 13",
    "sg:city":"Halle",
    "sg:phone":"+49 5201/2405",
    "sg:postcode":"33790",
    "sg:province":"Nordrhein-Westfalen",
    "wof:name":"Gerhard Wolf Architekt",
    "wof:placetype":"venue"
},
  "geometry": {"coordinates":[8.354984,52.055588],"type":"Point"}
}