{
  "type": "Feature",
  "properties": {
    "iso:country":"DE",
    "sg:address":"R\u00fcttenscheider Str. 107",
    "sg:city":"Essen",
    "sg:phone":"+49 201/774775",
    "sg:postcode":"45130",
    "sg:province":"Nordrhein-Westfalen",
    "wof:name":"Dorotheen-apotheke",
    "wof:placetype":"venue"
},
  "geometry": {"coordinates":[7.005552,51.436951],"type":"Point"}
}