{
  "type": "Feature",
  "properties": {
    "iso:country":"DE",
    "sg:address":"Friesenweg 1",
    "sg:city":"Gro\u00df Ber\u00dfen",
    "sg:phone":"+49 5965/584",
    "sg:postcode":"49777",
    "sg:province":"Niedersachsen",
    "wof:name":"Josef Ficker",
    "wof:placetype":"venue"
},
  "geometry": {"coordinates":[7.490139,52.765297],"type":"Point"}
}