{
  "type": "Feature",
  "properties": {
    "iso:country":"DE",
    "sg:address":"Hedwigstr. 20",
    "sg:city":"Hannover",
    "sg:phone":"+49 511/322739",
    "sg:postcode":"30159",
    "sg:province":"Niedersachsen",
    "wof:name":"Dr. Ernst Henneberg Rechtsanwalt Und Steuerberater",
    "wof:placetype":"venue"
},
  "geometry": {"coordinates":[9.748257637,52.3722496033],"type":"Point"}
}