{
  "type": "Feature",
  "properties": {
    "iso:country":"DE",
    "sg:address":"Heidturmweg 20",
    "sg:city":"Paderborn",
    "sg:phone":"+49 5251/409732",
    "sg:postcode":"33100",
    "sg:province":"Nordrhein-Westfalen",
    "wof:name":"Heinrich Brechmann",
    "wof:placetype":"venue"
},
  "geometry": {"coordinates":[8.7725553513,51.7411842346],"type":"Point"}
}