{
  "type": "Feature",
  "properties": {
    "iso:country":"DE",
    "sg:address":"Grenzwaldstr. 7",
    "sg:city":"Nettetal",
    "sg:phone":"+49 2157/6678",
    "sg:postcode":"41334",
    "sg:province":"Nordrhein-Westfalen",
    "wof:name":"M. K\u00fcppers",
    "wof:placetype":"venue"
},
  "geometry": {"coordinates":[6.195452,51.31078],"type":"Point"}
}