{
  "type": "Feature",
  "properties": {
    "iso:country":"DE",
    "sg:address":"Steinweg 84",
    "sg:city":"Gifhorn",
    "sg:phone":"+49 5371/50043",
    "sg:postcode":"38518",
    "sg:province":"Niedersachsen",
    "wof:name":"Nesemann-reisen",
    "wof:placetype":"venue"
},
  "geometry": {"coordinates":[10.5455369949,52.4837837219],"type":"Point"}
}