{
  "type": "Feature",
  "properties": {
    "iso:country":"DE",
    "sg:address":"Bismarckstr. 1",
    "sg:city":"Heddesheim",
    "sg:phone":"+49 6203/43712",
    "sg:postcode":"68542",
    "sg:province":"Baden-W\u00fcrttemberg",
    "wof:name":"Gastst\u00e4tte Scheuer",
    "wof:placetype":"venue"
},
  "geometry": {"coordinates":[8.6059188843,49.5078849792],"type":"Point"}
}