{
  "type": "Feature",
  "properties": {
    "iso:country":"DE",
    "sg:address":"Am Neuen Lande 4",
    "sg:city":"Garbsen",
    "sg:phone":"+49 5131/52005",
    "sg:postcode":"30826",
    "sg:province":"Niedersachsen",
    "wof:name":"Walter R\u00fchlicke",
    "wof:placetype":"venue"
},
  "geometry": {"coordinates":[9.6049537659,52.4603843689],"type":"Point"}
}