{
  "type": "Feature",
  "properties": {
    "iso:country":"DE",
    "sg:address":"Kanzleiweg 5",
    "sg:city":"Hohenlinden",
    "sg:phone":"+49 8124/910406",
    "sg:postcode":"85664",
    "sg:province":"Bayern",
    "wof:name":"O. Nagl",
    "wof:placetype":"venue"
},
  "geometry": {"coordinates":[11.997328,48.156059],"type":"Point"}
}