{
  "type": "Feature",
  "properties": {
    "iso:country":"DE",
    "sg:address":"Triebstr. 13",
    "sg:city":"M\u00fcnchen",
    "sg:phone":"+49 89/1491691",
    "sg:postcode":"80993",
    "sg:province":"Bayern",
    "wof:name":"Demel",
    "wof:placetype":"venue"
},
  "geometry": {"coordinates":[11.5314416885,48.1873970032],"type":"Point"}
}