{
  "type": "Feature",
  "properties": {
    "iso:country":"DE",
    "sg:address":"Darmst\u00e4dter Str. 66",
    "sg:city":"Reinheim",
    "sg:phone":"+49 6162/5282",
    "sg:postcode":"64354",
    "sg:province":"Hessen",
    "wof:name":"Jens M\u00f6rsch",
    "wof:placetype":"venue"
},
  "geometry": {"coordinates":[8.833432,49.833012],"type":"Point"}
}