{
  "type": "Feature",
  "properties": {
    "iso:country":"DE",
    "sg:address":"Coloniastr. 29",
    "sg:city":"Kerpen",
    "sg:phone":"+49 2237/7544",
    "sg:postcode":"50169",
    "sg:province":"Nordrhein-Westfalen",
    "wof:name":"J. Schl\u00f6sser",
    "wof:placetype":"venue"
},
  "geometry": {"coordinates":[6.7648649216,50.8547897339],"type":"Point"}
}