{
  "type": "Feature",
  "properties": {
    "iso:country":"DE",
    "sg:address":"Gildemeisterstr. 131",
    "sg:city":"Bielefeld",
    "sg:postcode":"33689",
    "sg:province":"Nordrhein-Westfalen",
    "wof:name":"H. L. Lufttechnik Verwaltungs Gmbh",
    "wof:placetype":"venue"
},
  "geometry": {"coordinates":[8.592233,51.924923],"type":"Point"}
}