{
  "type": "Feature",
  "properties": {
    "iso:country":"DE",
    "sg:address":"M\u00f6nchr\u00f6dener Str. 27",
    "sg:city":"R\u00f6dental",
    "sg:phone":"+49 9563/8204",
    "sg:postcode":"96472",
    "sg:province":"Bayern",
    "wof:name":"Gerhard Deschl",
    "wof:placetype":"venue"
},
  "geometry": {"coordinates":[11.0514593124,50.2987556458],"type":"Point"}
}