{
  "type": "Feature",
  "properties": {
    "iso:country":"DE",
    "sg:address":"Lohrheidestr. 62-66",
    "sg:city":"Bochum",
    "sg:phone":"+49 2327/94730",
    "sg:postcode":"44866",
    "sg:province":"Nordrhein-Westfalen",
    "wof:name":"H\u00f6lter Verwaltungs-gmbh",
    "wof:placetype":"venue"
},
  "geometry": {"coordinates":[7.1232790947,51.4854812622],"type":"Point"}
}