{
  "type": "Feature",
  "properties": {
    "iso:country":"DE",
    "sg:address":"Wolframs-Eschenbacher-Str. 113",
    "sg:city":"N\u00fcrnberg",
    "sg:phone":"+49 911/673113",
    "sg:postcode":"90449",
    "sg:province":"Bayern",
    "wof:name":"Hermann Grimm Ingenieur",
    "wof:placetype":"venue"
},
  "geometry": {"coordinates":[11.023279,49.424877],"type":"Point"}
}