{
  "type": "Feature",
  "properties": {
    "iso:country":"DE",
    "sg:address":"Aderstr.48",
    "sg:city":"D\u00fcsseldorf",
    "sg:phone":"+49 211/373070",
    "sg:postcode":"40215",
    "sg:province":"Nordrhein-Westfalen",
    "wof:name":"Ticketshop Kautz",
    "wof:placetype":"venue"
},
  "geometry": {"coordinates":[6.783049,51.218052],"type":"Point"}
}