{
  "type": "Feature",
  "properties": {
    "iso:country":"DE",
    "sg:address":"Wegscheid 3",
    "sg:city":"Eichst\u00e4tt",
    "sg:phone":"+49 8421/97740",
    "sg:postcode":"85072",
    "sg:province":"Bayern",
    "wof:name":"Karl Wiedmann - Treppen, Naturfarben",
    "wof:placetype":"venue"
},
  "geometry": {"coordinates":[11.184334,48.890629],"type":"Point"}
}