{
  "type": "Feature",
  "properties": {
    "iso:country":"DE",
    "sg:address":"M\u00f6nchshofstr. 37",
    "sg:city":"Viechtach",
    "sg:phone":"+49 9942/8814",
    "sg:postcode":"94234",
    "sg:province":"Bayern",
    "wof:name":"Albert Fischer Metzgerei",
    "wof:placetype":"venue"
},
  "geometry": {"coordinates":[12.8894281387,49.0758209229],"type":"Point"}
}