{
  "type": "Feature",
  "properties": {
    "iso:country":"DE",
    "sg:address":"Bahnstr. 32",
    "sg:city":"Mendig",
    "sg:phone":"+49 2652/2007",
    "sg:postcode":"56743",
    "sg:province":"Rheinland-Pfalz",
    "wof:name":"Klein Und Partner Rechtsanw\u00e4lte",
    "wof:placetype":"venue"
},
  "geometry": {"coordinates":[7.2821211815,50.3710289001],"type":"Point"}
}