{
  "type": "Feature",
  "properties": {
    "iso:country":"DE",
    "sg:address":"Neuschwansteinstr. 20",
    "sg:city":"Schwangau",
    "sg:phone":"+49 8362/81035",
    "sg:postcode":"87645",
    "sg:province":"Bayern",
    "wof:name":"Schlo\u00df Neuschwanstein",
    "wof:placetype":"venue"
},
  "geometry": {"coordinates":[10.748534,47.557693],"type":"Point"}
}