{
  "type": "Feature",
  "properties": {
    "iso:country":"DE",
    "sg:address":"Amselweg 23",
    "sg:city":"Kempten",
    "sg:phone":"+49 831/93109",
    "sg:postcode":"87439",
    "sg:province":"Bayern",
    "wof:name":"Karl Thomas",
    "wof:placetype":"venue"
},
  "geometry": {"coordinates":[10.2900943756,47.733341217],"type":"Point"}
}