{
  "type": "Feature",
  "properties": {
    "iso:country":"DE",
    "sg:address":"Zieglmeierstr. 11",
    "sg:city":"Hohenpei\u00dfenberg",
    "sg:phone":"+49 8805/955137",
    "sg:postcode":"82383",
    "sg:province":"Bayern",
    "wof:name":"Werner Degle",
    "wof:placetype":"venue"
},
  "geometry": {"coordinates":[11.0013608932,47.7891464233],"type":"Point"}
}