{
  "type": "Feature",
  "properties": {
    "iso:country":"DE",
    "sg:address":"Lange Zeile 56",
    "sg:city":"Erlangen",
    "sg:phone":"+49 9131/51332",
    "sg:postcode":"91054",
    "sg:province":"Bayern",
    "wof:name":"Walter Czysch Ingenieur",
    "wof:placetype":"venue"
},
  "geometry": {"coordinates":[11.0367412567,49.6020774841],"type":"Point"}
}