{
  "type": "Feature",
  "properties": {
    "iso:country":"DE",
    "sg:address":"Heimstr. 19",
    "sg:city":"Berlin",
    "sg:phone":"+49 30/6941243",
    "sg:postcode":"10965",
    "sg:province":"Berlin",
    "wof:name":"Verlag Krug Und Schadenberg",
    "wof:placetype":"venue"
},
  "geometry": {"coordinates":[13.397019,52.487701],"type":"Point"}
}