{
  "type": "Feature",
  "properties": {
    "iso:country":"DE",
    "sg:address":"Luisenstr. 20-24",
    "sg:city":"Frankfurt",
    "sg:phone":"+49 335/64623",
    "sg:postcode":"15230",
    "sg:province":"Brandenburg",
    "wof:name":"Gronenfelder Werkst\u00e4tten Ggmbh",
    "wof:placetype":"venue"
},
  "geometry": {"coordinates":[14.535913,52.347065],"type":"Point"}
}