{
  "type": "Feature",
  "properties": {
    "iso:country":"DE",
    "sg:address":"Markt Flamersheim 10",
    "sg:city":"Euskirchen",
    "sg:phone":"+49 2255/2572",
    "sg:postcode":"53881",
    "sg:province":"Nordrhein-Westfalen",
    "wof:name":"Robert Bernads Dentallabor Gmbh",
    "wof:placetype":"venue"
},
  "geometry": {"coordinates":[6.850336,50.623566],"type":"Point"}
}