{
  "type": "Feature",
  "properties": {
    "iso:country":"DE",
    "sg:address":"Schnorrstr. 43",
    "sg:city":"Gelsenkirchen",
    "sg:phone":"+49 209/1656738",
    "sg:postcode":"45892",
    "sg:province":"Nordrhein-Westfalen",
    "wof:name":"Athengrill",
    "wof:placetype":"venue"
},
  "geometry": {"coordinates":[7.1177687645,51.5805244446],"type":"Point"}
}