{
  "type": "Feature",
  "properties": {
    "iso:country":"DE",
    "sg:address":"Borsigstr. 5",
    "sg:city":"Isernhagen",
    "sg:postcode":"30916",
    "sg:province":"Niedersachsen",
    "wof:name":"Mactec Servicezentrale Gmbh",
    "wof:placetype":"venue"
},
  "geometry": {"coordinates":[9.836853,52.430603],"type":"Point"}
}