{
  "type": "Feature",
  "properties": {
    "iso:country":"DE",
    "sg:address":"Heegbarg 32",
    "sg:city":"Hamburg",
    "sg:phone":"+49 40/6020804",
    "sg:postcode":"22391",
    "sg:province":"Hamburg",
    "wof:name":"Restaurant Block House",
    "wof:placetype":"venue"
},
  "geometry": {"coordinates":[10.0932064056,53.6551818848],"type":"Point"}
}