{
  "type": "Feature",
  "properties": {
    "iso:country":"DE",
    "sg:address":"Hermann-Schmid-Str. 4",
    "sg:city":"M\u00fcnchen",
    "sg:phone":"+49 89/48953709",
    "sg:postcode":"80336",
    "sg:province":"Bayern",
    "wof:name":"Dr. J\u00fcrgen Thomas Rechtsanwalt",
    "wof:placetype":"venue"
},
  "geometry": {"coordinates":[11.5536880493,48.127986908],"type":"Point"}
}