{
  "type": "Feature",
  "properties": {
    "iso:country":"DE",
    "sg:address":"Aggertalstr. 4",
    "sg:city":"Gummersbach",
    "sg:phone":"+49 2261/51748",
    "sg:postcode":"51645",
    "sg:province":"Nordrhein-Westfalen",
    "wof:name":"Rudolf Holland Gmbh",
    "wof:placetype":"venue"
},
  "geometry": {"coordinates":[7.615854,51.027565],"type":"Point"}
}