{
  "type": "Feature",
  "properties": {
    "iso:country":"DE",
    "sg:address":"Bachstr. 4",
    "sg:city":"Breidenbach",
    "sg:phone":"+49 6465/91510",
    "sg:postcode":"35236",
    "sg:province":"Hessen",
    "wof:name":"Bfk Bl\u00f6cher & Fischer Gmbh",
    "wof:placetype":"venue"
},
  "geometry": {"coordinates":[8.4549226761,50.8868026733],"type":"Point"}
}