{
  "type": "Feature",
  "properties": {
    "iso:country":"DE",
    "sg:address":"Rheinbabenstr. 105",
    "sg:city":"Krefeld",
    "sg:phone":"+49 2151/570591",
    "sg:postcode":"47809",
    "sg:province":"Nordrhein-Westfalen",
    "wof:name":"Hans Peter Maes",
    "wof:placetype":"venue"
},
  "geometry": {"coordinates":[6.637264,51.334812],"type":"Point"}
}