{
  "type": "Feature",
  "properties": {
    "iso:country":"DE",
    "sg:address":"Bruchweg 10",
    "sg:city":"H\u00fcgelsheim",
    "sg:phone":"+49 7229/5066",
    "sg:postcode":"76549",
    "sg:province":"Baden-W\u00fcrttemberg",
    "wof:name":"H. Walter Immobilienmakler",
    "wof:placetype":"venue"
},
  "geometry": {"coordinates":[8.1093463898,48.7933959961],"type":"Point"}
}