{
  "type": "Feature",
  "properties": {
    "iso:country":"DE",
    "sg:address":"Rudolst\u00e4dter Str. 3",
    "sg:city":"Remda",
    "sg:postcode":"07407",
    "sg:province":"Th\u00fcringen",
    "wof:name":"Hauke Handel Und Vertrieb",
    "wof:placetype":"venue"
},
  "geometry": {"coordinates":[11.2284812927,50.7625350952],"type":"Point"}
}