{
  "type": "Feature",
  "properties": {
    "iso:country":"DE",
    "sg:address":"Gartenstr. 5a",
    "sg:city":"Eschborn",
    "sg:phone":"+49 6173/323675",
    "sg:postcode":"65760",
    "sg:province":"Hessen",
    "wof:name":"Matsushima Trade & Restaurant Gmbh",
    "wof:placetype":"venue"
},
  "geometry": {"coordinates":[8.5448179245,50.1593360901],"type":"Point"}
}