{
  "type": "Feature",
  "properties": {
    "iso:country":"DE",
    "sg:address":"Im Bilskamp 87",
    "sg:city":"M\u00fcnster",
    "sg:phone":"+49 2506/473",
    "sg:postcode":"48167",
    "sg:province":"Nordrhein-Westfalen",
    "wof:name":"Heinz Horsthemke",
    "wof:placetype":"venue"
},
  "geometry": {"coordinates":[7.737142086,51.9183731079],"type":"Point"}
}