{
  "type": "Feature",
  "properties": {
    "iso:country":"DE",
    "sg:address":"Am Bergfried 3",
    "sg:city":"Langen",
    "sg:phone":"+49 6103/23257",
    "sg:postcode":"63225",
    "sg:province":"Hessen",
    "wof:name":"Metabond Molekular-technik Ges. F\u00fcr",
    "wof:placetype":"venue"
},
  "geometry": {"coordinates":[8.689108,49.982307],"type":"Point"}
}