{
  "type": "Feature",
  "properties": {
    "iso:country":"DE",
    "sg:address":"F\u00fcnter Weg 39",
    "sg:city":"M\u00fclheim",
    "sg:phone":"+49 208/431727",
    "sg:postcode":"45472",
    "sg:province":"Nordrhein-Westfalen",
    "wof:name":"Laterne",
    "wof:placetype":"venue"
},
  "geometry": {"coordinates":[6.9245858192,51.4326782227],"type":"Point"}
}