{
  "type": "Feature",
  "properties": {
    "iso:country":"DE",
    "sg:address":"Sonnenstr. 59",
    "sg:city":"Gilching",
    "sg:phone":"+49 8105/9573",
    "sg:postcode":"82205",
    "sg:province":"Bayern",
    "wof:name":"Heinz Nickel Elektroinstallation",
    "wof:placetype":"venue"
},
  "geometry": {"coordinates":[11.28858,48.100052],"type":"Point"}
}