{
  "type": "Feature",
  "properties": {
    "iso:country":"DE",
    "sg:address":"Blankenauer Str. 99",
    "sg:city":"Chemnitz",
    "sg:phone":"+49 371/449840",
    "sg:postcode":"09113",
    "sg:province":"Sachsen",
    "wof:name":"Goetz & Partner Immobilien Und Bautr\u00e4ger Gmbh",
    "wof:placetype":"venue"
},
  "geometry": {"coordinates":[12.9291086197,50.857334137],"type":"Point"}
}