{
  "type": "Feature",
  "properties": {
    "iso:country":"DE",
    "sg:address":"S\u00fcdhemmer Heide 34",
    "sg:city":"Hille",
    "sg:phone":"+49 5703/2439",
    "sg:postcode":"32479",
    "sg:province":"Nordrhein-Westfalen",
    "wof:name":"Wolfgang Fabig",
    "wof:placetype":"venue"
},
  "geometry": {"coordinates":[8.7760467529,52.3196258545],"type":"Point"}
}