{
  "type": "Feature",
  "properties": {
    "iso:country":"DE",
    "sg:address":"Im Paradies 16",
    "sg:city":"Nidda",
    "sg:phone":"+49 6043/8558",
    "sg:postcode":"63667",
    "sg:province":"Hessen",
    "wof:name":"R.-e. Huth",
    "wof:placetype":"venue"
},
  "geometry": {"coordinates":[9.005348,50.421078],"type":"Point"}
}