{
  "type": "Feature",
  "properties": {
    "iso:country":"DE",
    "sg:address":"Marktstr. 44",
    "sg:city":"Gladenbach",
    "sg:phone":"+49 6462/7495",
    "sg:postcode":"35075",
    "sg:province":"Hessen",
    "wof:name":"Pizzeria Marktstube",
    "wof:placetype":"venue"
},
  "geometry": {"coordinates":[8.5823802948,50.7694511414],"type":"Point"}
}