{
  "type": "Feature",
  "properties": {
    "iso:country":"DE",
    "sg:address":"Nibelungenstr. 76",
    "sg:city":"B\u00fcrstadt",
    "sg:phone":"+49 6206/8058",
    "sg:postcode":"68642",
    "sg:province":"Hessen",
    "wof:name":"Karl-heinz Koch",
    "wof:placetype":"venue"
},
  "geometry": {"coordinates":[8.4577131271,49.6425933838],"type":"Point"}
}