{
  "type": "Feature",
  "properties": {
    "iso:country":"DE",
    "sg:address":"Roxeler Str. 6",
    "sg:city":"Havixbeck",
    "sg:phone":"+49 2507/1235",
    "sg:postcode":"48329",
    "sg:province":"Nordrhein-Westfalen",
    "wof:name":"H. Oeding Erdel",
    "wof:placetype":"venue"
},
  "geometry": {"coordinates":[7.4632577896,51.9963912964],"type":"Point"}
}