{
  "type": "Feature",
  "properties": {
    "iso:country":"DE",
    "sg:address":"Wundtstr. 16",
    "sg:city":"Berlin",
    "sg:phone":"+49 30/3221700",
    "sg:postcode":"14059",
    "sg:province":"Berlin",
    "wof:name":"Karlheinz Schie\u00dfler Masseur",
    "wof:placetype":"venue"
},
  "geometry": {"coordinates":[13.293117,52.511803],"type":"Point"}
}