{
  "type": "Feature",
  "properties": {
    "iso:country":"DE",
    "sg:address":"Guggemoosen",
    "sg:city":"R\u00fcckholz",
    "sg:phone":"+49 8369/686",
    "sg:postcode":"87494",
    "sg:province":"Bayern",
    "wof:name":"S. Wigger",
    "wof:placetype":"venue"
},
  "geometry": {"coordinates":[10.561323,47.651089],"type":"Point"}
}