{
  "type": "Feature",
  "properties": {
    "iso:country":"DE",
    "sg:address":"Gelnh\u00e4user Str.",
    "sg:city":"Linsengericht",
    "sg:phone":"+49 6051/6265",
    "sg:postcode":"63589",
    "sg:province":"Hessen",
    "wof:name":"Arche Noah",
    "wof:placetype":"venue"
},
  "geometry": {"coordinates":[9.1934728622,50.1957855225],"type":"Point"}
}