{
  "type": "Feature",
  "properties": {
    "iso:country":"DE",
    "sg:address":"B\u00fcenfeld 1",
    "sg:city":"Eslohe",
    "sg:phone":"+49 2973/3285",
    "sg:postcode":"59889",
    "sg:province":"Nordrhein-Westfalen",
    "wof:name":"Johann Scheele",
    "wof:placetype":"venue"
},
  "geometry": {"coordinates":[8.230269,51.284332],"type":"Point"}
}