{
  "type": "Feature",
  "properties": {
    "iso:country":"DE",
    "sg:address":"Schlo\u00dfstr. 4",
    "sg:city":"Heroldsbach",
    "sg:phone":"+49 9190/998888",
    "sg:postcode":"91336",
    "sg:province":"Bayern",
    "wof:name":"Hermann Kraus",
    "wof:placetype":"venue"
},
  "geometry": {"coordinates":[11.0008268356,49.6883392334],"type":"Point"}
}