{
  "type": "Feature",
  "properties": {
    "iso:country":"DE",
    "sg:address":"Flagentwiet 13",
    "sg:city":"Hamburg",
    "sg:phone":"+49 40/5501011",
    "sg:postcode":"22457",
    "sg:province":"Hamburg",
    "wof:name":"Bin Baumaschinen-instand- Setzung Nord Gmbh",
    "wof:placetype":"venue"
},
  "geometry": {"coordinates":[9.909055,53.636131],"type":"Point"}
}