{
  "type": "Feature",
  "properties": {
    "iso:country":"DE",
    "sg:address":"Hohndorfer Kirchweg 5",
    "sg:city":"Gro\u00dfolbersdorf",
    "sg:postcode":"09432",
    "sg:province":"Sachsen",
    "wof:name":"Gemeindeschwesterstation",
    "wof:placetype":"venue"
},
  "geometry": {"coordinates":[13.088328,50.695885],"type":"Point"}
}