{
  "type": "Feature",
  "properties": {
    "iso:country":"DE",
    "sg:address":"Flandersbacher Str. 116",
    "sg:city":"W\u00fclfrath",
    "sg:phone":"+49 2058/79175",
    "sg:postcode":"42489",
    "sg:province":"Nordrhein-Westfalen",
    "wof:name":"W. Ruhrmann Masseur",
    "wof:placetype":"venue"
},
  "geometry": {"coordinates":[6.995599,51.307835],"type":"Point"}
}