{
  "type": "Feature",
  "properties": {
    "iso:country":"DE",
    "sg:address":"Wieseng\u00e4rten 1",
    "sg:city":"Tachbach",
    "sg:phone":"+49 36873/20328",
    "sg:postcode":"98660",
    "sg:province":"Th\u00fcringen",
    "wof:name":"Schwedenh\u00e4user",
    "wof:placetype":"venue"
},
  "geometry": {"coordinates":[10.614440918,50.5282402039],"type":"Point"}
}