{
  "type": "Feature",
  "properties": {
    "iso:country":"DE",
    "sg:address":"Graf-Engelbert-Str. 72",
    "sg:city":"D\u00fcsseldorf",
    "sg:phone":"+49 203/7480259",
    "sg:postcode":"40489",
    "sg:province":"Nordrhein-Westfalen",
    "wof:name":"Peter Altvater Rechtsanwalt",
    "wof:placetype":"venue"
},
  "geometry": {"coordinates":[6.7954111099,51.329410553],"type":"Point"}
}