{
  "type": "Feature",
  "properties": {
    "iso:country":"DE",
    "sg:address":"M\u00fchlstr. 12",
    "sg:city":"Rheinm\u00fcnster",
    "sg:phone":"+49 7227/4111",
    "sg:postcode":"77836",
    "sg:province":"Baden-W\u00fcrttemberg",
    "wof:name":"Johann Hellgoth",
    "wof:placetype":"venue"
},
  "geometry": {"coordinates":[8.0448551178,48.7652778625],"type":"Point"}
}