{
  "type": "Feature",
  "properties": {
    "iso:country":"DE",
    "sg:address":"Heringstr. 28",
    "sg:city":"Norden",
    "sg:phone":"+49 4931/15991",
    "sg:postcode":"26506",
    "sg:province":"Niedersachsen",
    "wof:name":"China-restaurant Shanghai",
    "wof:placetype":"venue"
},
  "geometry": {"coordinates":[7.2117872238,53.5909347534],"type":"Point"}
}