{
  "type": "Feature",
  "properties": {
    "iso:country":"DE",
    "sg:address":"Clara-Zetkin-Str. 23",
    "sg:city":"Brandenburg",
    "sg:phone":"+49 3381/521541",
    "sg:postcode":"14770",
    "sg:province":"Brandenburg",
    "wof:name":"M. P\u00fcngel",
    "wof:placetype":"venue"
},
  "geometry": {"coordinates":[12.542986,52.406651],"type":"Point"}
}