{
  "type": "Feature",
  "properties": {
    "iso:country":"DE",
    "sg:address":"Im Br\u00fchl 7",
    "sg:city":"Karlsruhe",
    "sg:phone":"+49 721/483054",
    "sg:postcode":"76229",
    "sg:province":"Baden-W\u00fcrttemberg",
    "wof:name":"Biohof Kn\u00f6bl",
    "wof:placetype":"venue"
},
  "geometry": {"coordinates":[8.49133,49.030807],"type":"Point"}
}