{
  "type": "Feature",
  "properties": {
    "iso:country":"DE",
    "sg:address":"Eigenheimstr. 18",
    "sg:city":"Offenbach",
    "sg:postcode":"63071",
    "sg:province":"Hessen",
    "wof:name":"Klaus Bartram Unternehmensberater",
    "wof:placetype":"venue"
},
  "geometry": {"coordinates":[8.7821435928,50.0989379883],"type":"Point"}
}