{
  "type": "Feature",
  "properties": {
    "iso:country":"DE",
    "sg:address":"Schlo\u00dfstr. 41",
    "sg:city":"Bergisch Gladbach",
    "sg:phone":"+49 2204/95000",
    "sg:postcode":"51429",
    "sg:province":"Nordrhein-Westfalen",
    "wof:name":"Reiseb\u00fcro Sonnenschein",
    "wof:placetype":"venue"
},
  "geometry": {"coordinates":[7.159637928,50.9659919739],"type":"Point"}
}