{
  "type": "Feature",
  "properties": {
    "iso:country":"DE",
    "sg:address":"Vehrter Kirchweg 19",
    "sg:city":"Belm",
    "sg:phone":"+49 5406/838211",
    "sg:postcode":"49191",
    "sg:province":"Niedersachsen",
    "wof:name":"S\u00fcntel-apotheke Inh. R. Sch\u00e4fer-wohlers E.kfr.",
    "wof:placetype":"venue"
},
  "geometry": {"coordinates":[8.151367,52.343933],"type":"Point"}
}