{
  "type": "Feature",
  "properties": {
    "iso:country":"DE",
    "sg:address":"Wankelstr. 9",
    "sg:city":"K\u00f6ln",
    "sg:phone":"+49 2236/962970",
    "sg:postcode":"50996",
    "sg:province":"Nordrhein-Westfalen",
    "wof:name":"Nobel Biocare Deutschland Gmbh",
    "wof:placetype":"venue"
},
  "geometry": {"coordinates":[6.989352,50.872017],"type":"Point"}
}