{
  "type": "Feature",
  "properties": {
    "iso:country":"DE",
    "sg:address":"Weender Landstr 3-7",
    "sg:city":"G\u00f6ttingen",
    "sg:phone":"+49 551/521000",
    "sg:postcode":"37073",
    "sg:province":"Niedersachsen",
    "wof:name":"Unic Marketing Gmbh & Co Kg",
    "wof:placetype":"venue"
},
  "geometry": {"coordinates":[9.933318,51.539513],"type":"Point"}
}