{
  "type": "Feature",
  "properties": {
    "iso:country":"DE",
    "sg:address":"Grenzstr.",
    "sg:city":"Eilenburg",
    "sg:phone":"+49 3423/601847",
    "sg:postcode":"04838",
    "sg:province":"Sachsen",
    "wof:name":"Erhard Klein",
    "wof:placetype":"venue"
},
  "geometry": {"coordinates":[12.619835,51.455013],"type":"Point"}
}