{
  "type": "Feature",
  "properties": {
    "iso:country":"DE",
    "sg:address":"Flurstr. 18",
    "sg:city":"Breitscheid",
    "sg:phone":"+49 2777/256",
    "sg:postcode":"35767",
    "sg:province":"Hessen",
    "wof:name":"Otto Metz Installation",
    "wof:placetype":"venue"
},
  "geometry": {"coordinates":[8.1933250427,50.6849632263],"type":"Point"}
}