{
  "type": "Feature",
  "properties": {
    "iso:country":"DE",
    "sg:address":"Aulenbacher Str. 3",
    "sg:city":"Eschau",
    "sg:phone":"+49 9374/2327",
    "sg:postcode":"63863",
    "sg:province":"Bayern",
    "wof:name":"Hannelore Repp Krankengymnastin",
    "wof:placetype":"venue"
},
  "geometry": {"coordinates":[9.277464,49.848358],"type":"Point"}
}