{
  "type": "Feature",
  "properties": {
    "iso:country":"DE",
    "sg:address":"Am Eichenplatz 24",
    "sg:city":"Hamburg",
    "sg:phone":"+49 40/8005353",
    "sg:postcode":"22549",
    "sg:province":"Hamburg",
    "wof:name":"Walter Eggers",
    "wof:placetype":"venue"
},
  "geometry": {"coordinates":[9.84466,53.574715],"type":"Point"}
}