{
  "type": "Feature",
  "properties": {
    "iso:country":"DE",
    "sg:address":"Rathausplatz 3",
    "sg:city":"Traunreut",
    "sg:postcode":"83301",
    "sg:province":"Bayern",
    "wof:name":"Kultur- Und Veranstaltungs Gesellschaft Mbh Der",
    "wof:placetype":"venue"
},
  "geometry": {"coordinates":[12.592896,47.962269],"type":"Point"}
}