{
  "type": "Feature",
  "properties": {
    "iso:country":"DE",
    "sg:address":"Hatzurodestr. 59",
    "sg:city":"Erkelenz",
    "sg:phone":"+49 2433/7970",
    "sg:postcode":"41812",
    "sg:province":"Nordrhein-Westfalen",
    "wof:name":"Karl Peters",
    "wof:placetype":"venue"
},
  "geometry": {"coordinates":[6.283453,51.059624],"type":"Point"}
}