{
  "type": "Feature",
  "properties": {
    "iso:country":"DE",
    "sg:address":"Schulthei\u00dfstr. 56",
    "sg:city":"Bonn",
    "sg:phone":"+49 228/468215",
    "sg:postcode":"53225",
    "sg:province":"Nordrhein-Westfalen",
    "wof:name":"Hildegard Saul",
    "wof:placetype":"venue"
},
  "geometry": {"coordinates":[7.1312851906,50.7519836426],"type":"Point"}
}