{
  "type": "Feature",
  "properties": {
    "iso:country":"DE",
    "sg:address":"K\u00f6hlerstr. 43",
    "sg:city":"Coswig",
    "sg:postcode":"01640",
    "sg:province":"Sachsen",
    "wof:name":"Ambiance Immobilien Und Verm\u00f6gensverwaltung Ag",
    "wof:placetype":"venue"
},
  "geometry": {"coordinates":[13.5342006683,51.1484527588],"type":"Point"}
}