{
  "type": "Feature",
  "properties": {
    "iso:country":"DE",
    "sg:address":"Klarastr. 31",
    "sg:city":"Freiburg",
    "sg:phone":"+49 761/273132",
    "sg:postcode":"79106",
    "sg:province":"Baden-W\u00fcrttemberg",
    "wof:name":"T. Kircher Antiquit\u00e4ten",
    "wof:placetype":"venue"
},
  "geometry": {"coordinates":[7.839441,47.998642],"type":"Point"}
}