{
  "type": "Feature",
  "properties": {
    "iso:country":"DE",
    "sg:address":"Zugspitzstr. 20",
    "sg:city":"Herrsching",
    "sg:phone":"+49 8152/925650",
    "sg:postcode":"82211",
    "sg:province":"Bayern",
    "wof:name":"Ina Verlags Gmbh",
    "wof:placetype":"venue"
},
  "geometry": {"coordinates":[11.1339178085,48.041885376],"type":"Point"}
}