{
  "type": "Feature",
  "properties": {
    "iso:country":"DE",
    "sg:address":"Friedrichstr. 47",
    "sg:city":"Mannheim",
    "sg:phone":"+49 621/8414511",
    "sg:postcode":"68199",
    "sg:province":"Baden-W\u00fcrttemberg",
    "wof:name":"Penny-markt Gmbh",
    "wof:placetype":"venue"
},
  "geometry": {"coordinates":[8.4895095825,49.4525527954],"type":"Point"}
}