{
  "type": "Feature",
  "properties": {
    "iso:country":"DE",
    "sg:address":"Kapellenstr. 8",
    "sg:city":"Altshausen",
    "sg:phone":"+49 7584/2305",
    "sg:postcode":"88361",
    "sg:province":"Baden-W\u00fcrttemberg",
    "wof:name":"Johannes Rimmele",
    "wof:placetype":"venue"
},
  "geometry": {"coordinates":[9.545328,47.927555],"type":"Point"}
}