{
  "type": "Feature",
  "properties": {
    "iso:country":"DE",
    "sg:address":"Lindenackerstr. 7",
    "sg:city":"March",
    "sg:phone":"+49 7665/3036",
    "sg:postcode":"79232",
    "sg:province":"Baden-W\u00fcrttemberg",
    "wof:name":"Fridolin Tr\u00f6ndle",
    "wof:placetype":"venue"
},
  "geometry": {"coordinates":[7.7734260559,48.0703735352],"type":"Point"}
}