{
  "type": "Feature",
  "properties": {
    "iso:country":"DE",
    "sg:address":"Am Ortsring 8",
    "sg:city":"Homberg",
    "sg:postcode":"35315",
    "sg:province":"Hessen",
    "wof:name":"M & V Die Marketing & Vertriebs Gmbh",
    "wof:placetype":"venue"
},
  "geometry": {"coordinates":[8.9671211243,50.7344017029],"type":"Point"}
}