{
  "type": "Feature",
  "properties": {
    "iso:country":"DE",
    "sg:address":"Dorfstr. 19",
    "sg:city":"D\u00fcren",
    "sg:phone":"+49 2421/88608",
    "sg:postcode":"52353",
    "sg:province":"Nordrhein-Westfalen",
    "wof:name":"Eduard Jo\u00dfet Architekt",
    "wof:placetype":"venue"
},
  "geometry": {"coordinates":[6.462544,50.822701],"type":"Point"}
}