{
  "type": "Feature",
  "properties": {
    "iso:country":"DE",
    "sg:address":"St.-Josefs-Platz 6",
    "sg:city":"Herzogenaurach",
    "sg:phone":"+49 9132/2075",
    "sg:postcode":"91074",
    "sg:province":"Bayern",
    "wof:name":"Kath. Pfarramt St. Josef",
    "wof:placetype":"venue"
},
  "geometry": {"coordinates":[10.913854599,49.5627670288],"type":"Point"}
}