{
  "type": "Feature",
  "properties": {
    "iso:country":"DE",
    "sg:address":"Pfingstweidweg 1",
    "sg:city":"Erlensee",
    "sg:phone":"+49 6183/2891",
    "sg:postcode":"63526",
    "sg:province":"Hessen",
    "wof:name":"Ernst Lediger Gmbh",
    "wof:placetype":"venue"
},
  "geometry": {"coordinates":[8.9875631332,50.1682014465],"type":"Point"}
}