{
  "type": "Feature",
  "properties": {
    "iso:country":"DE",
    "sg:address":"Sendling 58",
    "sg:city":"Ramerberg",
    "sg:phone":"+49 8039/3018",
    "sg:postcode":"83561",
    "sg:province":"Bayern",
    "wof:name":"Michael W\u00fchr Gmbh",
    "wof:placetype":"venue"
},
  "geometry": {"coordinates":[12.16761,48.013168],"type":"Point"}
}