{
  "type": "Feature",
  "properties": {
    "iso:country":"DE",
    "sg:address":"Roscherstr. 6",
    "sg:city":"Hannover",
    "sg:phone":"+49 511/315466",
    "sg:postcode":"30161",
    "sg:province":"Niedersachsen",
    "wof:name":"Immobilien-verwaltungs- Gesellschaft Mbh & Co. Kg",
    "wof:placetype":"venue"
},
  "geometry": {"coordinates":[9.748579,52.37656],"type":"Point"}
}