{
  "type": "Feature",
  "properties": {
    "iso:country":"DE",
    "sg:address":"Dingst\u00e4tte 18",
    "sg:city":"Pinneberg",
    "sg:phone":"+49 4101/22464",
    "sg:postcode":"25421",
    "sg:province":"Schleswig-Holstein",
    "wof:name":"Ernst Glindmeyer Kg",
    "wof:placetype":"venue"
},
  "geometry": {"coordinates":[9.7981624603,53.6612663269],"type":"Point"}
}