{
  "type": "Feature",
  "properties": {
    "iso:country":"DE",
    "sg:address":"Auf dem Schiefen Berge 12",
    "sg:city":"Bad Lauterberg",
    "sg:phone":"+49 5524/4213",
    "sg:postcode":"37431",
    "sg:province":"Niedersachsen",
    "wof:name":"Moijn Co Wolfgang David",
    "wof:placetype":"venue"
},
  "geometry": {"coordinates":[10.4646368027,51.6207809448],"type":"Point"}
}