{
  "type": "Feature",
  "properties": {
    "iso:country":"DE",
    "sg:address":"Emsstr. 1c",
    "sg:city":"Rheine",
    "sg:phone":"+49 5971/54990",
    "sg:postcode":"48431",
    "sg:province":"Nordrhein-Westfalen",
    "wof:name":"B. Cramer",
    "wof:placetype":"venue"
},
  "geometry": {"coordinates":[7.4378070831,52.2782821655],"type":"Point"}
}