{
  "type": "Feature",
  "properties": {
    "iso:country":"DE",
    "sg:address":"Ziegelhorststr. 6",
    "sg:city":"Duisburg",
    "sg:phone":"+49 203/592758",
    "sg:postcode":"47169",
    "sg:province":"Nordrhein-Westfalen",
    "wof:name":"Rolf Zagorny",
    "wof:placetype":"venue"
},
  "geometry": {"coordinates":[6.7708721161,51.5078430176],"type":"Point"}
}