{
  "type": "Feature",
  "properties": {
    "iso:country":"DE",
    "sg:address":"Rittergasse 6",
    "sg:city":"Bad Hersfeld",
    "sg:phone":"+49 6621/919439",
    "sg:postcode":"36251",
    "sg:province":"Hessen",
    "wof:name":"Barflay",
    "wof:placetype":"venue"
},
  "geometry": {"coordinates":[9.7094602585,50.8695106506],"type":"Point"}
}