{
  "type": "Feature",
  "properties": {
    "iso:country":"DE",
    "sg:address":"Schneeberger Str. 4",
    "sg:city":"Zschorlau",
    "sg:phone":"+49 3771/458183",
    "sg:postcode":"08321",
    "sg:province":"Sachsen",
    "wof:name":"Dr. Frieder Baumann",
    "wof:placetype":"venue"
},
  "geometry": {"coordinates":[12.6398601532,50.563659668],"type":"Point"}
}