{
  "type": "Feature",
  "properties": {
    "iso:country":"DE",
    "sg:address":"Severinusstr. 65",
    "sg:city":"H\u00fcrth",
    "sg:phone":"+49 2233/77870",
    "sg:postcode":"50354",
    "sg:province":"Nordrhein-Westfalen",
    "wof:name":"G\u00fcnter Heinz Heilpraktiker",
    "wof:placetype":"venue"
},
  "geometry": {"coordinates":[6.8836297989,50.8810195923],"type":"Point"}
}