{
  "type": "Feature",
  "properties": {
    "iso:country":"DE",
    "sg:address":"Cisinskistr 9",
    "sg:city":"Panschwitz-Kuckau",
    "sg:phone":"+49 35796/96215",
    "sg:postcode":"01920",
    "sg:province":"Sachsen",
    "wof:name":"Isenmann Drahtsiebe Gmbh",
    "wof:placetype":"venue"
},
  "geometry": {"coordinates":[14.1925497055,51.2347831726],"type":"Point"}
}