{
  "type": "Feature",
  "properties": {
    "iso:country":"DE",
    "sg:address":"Poststr. 1",
    "sg:city":"Freital",
    "sg:postcode":"01705",
    "sg:province":"Sachsen",
    "wof:name":"Tv-rgfe Gmbh",
    "wof:placetype":"venue"
},
  "geometry": {"coordinates":[13.6455726624,50.9977912903],"type":"Point"}
}