{
  "type": "Feature",
  "properties": {
    "iso:country":"DE",
    "sg:address":"W\u00f6rnersgrund",
    "sg:city":"Neuenstadt",
    "sg:phone":"+49 7139/7798",
    "sg:postcode":"74196",
    "sg:province":"Baden-W\u00fcrttemberg",
    "wof:name":"Willy Ermold",
    "wof:placetype":"venue"
},
  "geometry": {"coordinates":[9.33144,49.224354],"type":"Point"}
}