{
  "type": "Feature",
  "properties": {
    "iso:country":"DE",
    "sg:address":"D\u00fcsseldorfer Str. 47",
    "sg:city":"Grevenbroich",
    "sg:phone":"+49 2181/40061",
    "sg:postcode":"41515",
    "sg:province":"Nordrhein-Westfalen",
    "wof:name":"J\u00e4gerhof",
    "wof:placetype":"venue"
},
  "geometry": {"coordinates":[6.5684142113,51.0954627991],"type":"Point"}
}