{
  "type": "Feature",
  "properties": {
    "iso:country":"DE",
    "sg:address":"Elbinger Str. 20",
    "sg:city":"Heilbronn",
    "sg:phone":"+49 7131/920217",
    "sg:postcode":"74078",
    "sg:province":"Baden-W\u00fcrttemberg",
    "wof:name":"J\u00f6rg Sontopski Ingenieur",
    "wof:placetype":"venue"
},
  "geometry": {"coordinates":[9.1992826462,49.1591262817],"type":"Point"}
}