{
  "type": "Feature",
  "properties": {
    "iso:country":"DE",
    "sg:address":"Am Rittersberg 29",
    "sg:city":"D\u00fcsseldorf",
    "sg:postcode":"40595",
    "sg:province":"Nordrhein-Westfalen",
    "wof:name":"Primus Immobilien Ag",
    "wof:placetype":"venue"
},
  "geometry": {"coordinates":[6.8794159889,51.1456947327],"type":"Point"}
}