{
  "type": "Feature",
  "properties": {
    "iso:country":"DE",
    "sg:address":"Schmalzgasse 14-1",
    "sg:city":"Bisingen",
    "sg:phone":"+49 7476/2773",
    "sg:postcode":"72406",
    "sg:province":"Baden-W\u00fcrttemberg",
    "wof:name":"Enzo Antenucci",
    "wof:placetype":"venue"
},
  "geometry": {"coordinates":[8.916864,48.307537],"type":"Point"}
}