{
  "type": "Feature",
  "properties": {
    "iso:country":"DE",
    "sg:address":"Im Kirchwinkel 12",
    "sg:city":"Otterfing",
    "sg:phone":"+49 8024/2721",
    "sg:postcode":"83624",
    "sg:province":"Bayern",
    "wof:name":"Anton Lehner",
    "wof:placetype":"venue"
},
  "geometry": {"coordinates":[11.6765537262,47.9109649658],"type":"Point"}
}