{
  "type": "Feature",
  "properties": {
    "iso:country":"DE",
    "sg:address":"Langer Markt 17",
    "sg:city":"Hermeskeil",
    "sg:phone":"+49 6503",
    "sg:postcode":"54411",
    "sg:province":"Rheinland-Pfalz",
    "wof:name":"Tourist-information Hermeskeil",
    "wof:placetype":"venue"
},
  "geometry": {"coordinates":[6.9459562302,49.6552429199],"type":"Point"}
}