{
  "type": "Feature",
  "properties": {
    "iso:country":"DE",
    "sg:address":"Rosenheimer Str. 14",
    "sg:city":"Kolbermoor",
    "sg:phone":"+49 8031/91307",
    "sg:postcode":"83059",
    "sg:province":"Bayern",
    "wof:name":"Stadlerbr\u00e4u",
    "wof:placetype":"venue"
},
  "geometry": {"coordinates":[12.0641841888,47.8502044678],"type":"Point"}
}