{
  "type": "Feature",
  "properties": {
    "iso:country":"DE",
    "sg:address":"Raiffeisenstr. 1",
    "sg:city":"W\u00f6llstadt",
    "sg:phone":"+49 6034/4242",
    "sg:postcode":"61206",
    "sg:province":"Hessen",
    "wof:name":"Rainer P\u00e4utz Heilpraktiker",
    "wof:placetype":"venue"
},
  "geometry": {"coordinates":[8.7706842422,50.2770614624],"type":"Point"}
}