{
  "type": "Feature",
  "properties": {
    "iso:country":"DE",
    "sg:address":"In der Sohle 36",
    "sg:city":"Arnsberg",
    "sg:phone":"+49 2932/429108",
    "sg:postcode":"59755",
    "sg:province":"Nordrhein-Westfalen",
    "wof:name":"Christiani Chemie Gmbh",
    "wof:placetype":"venue"
},
  "geometry": {"coordinates":[7.96371,51.443199],"type":"Point"}
}