{
  "type": "Feature",
  "properties": {
    "iso:country":"DE",
    "sg:address":"Oststr. 26",
    "sg:city":"Sendenhorst",
    "sg:phone":"+49 2526/1356",
    "sg:postcode":"48324",
    "sg:province":"Nordrhein-Westfalen",
    "wof:name":"Karl Wessel",
    "wof:placetype":"venue"
},
  "geometry": {"coordinates":[7.8292379379,51.8456764221],"type":"Point"}
}