{
  "type": "Feature",
  "properties": {
    "iso:country":"DE",
    "sg:address":"Nu\u00dfh\u00e4herstr. 39",
    "sg:city":"Berlin",
    "sg:phone":"+49 30/4311386",
    "sg:postcode":"13505",
    "sg:province":"Berlin",
    "wof:name":"Prof. H. Gr\u00e4f Ingenieur",
    "wof:placetype":"venue"
},
  "geometry": {"coordinates":[13.2228727341,52.5822105408],"type":"Point"}
}