{
  "type": "Feature",
  "properties": {
    "iso:country":"DE",
    "sg:address":"Herlesh\u00e4user Str. 4",
    "sg:city":"Sontra",
    "sg:phone":"+49 6627/1222",
    "sg:postcode":"36205",
    "sg:province":"Hessen",
    "wof:name":"Otto Karges",
    "wof:placetype":"venue"
},
  "geometry": {"coordinates":[10.0111074448,51.0212364197],"type":"Point"}
}