{
  "type": "Feature",
  "properties": {
    "iso:country":"DE",
    "sg:address":"Mosbacher Weg 31",
    "sg:city":"Feuchtwangen",
    "sg:phone":"+49 9852/614700",
    "sg:postcode":"91555",
    "sg:province":"Bayern",
    "wof:name":"Dr. Fritz Schweizer Tierarzt",
    "wof:placetype":"venue"
},
  "geometry": {"coordinates":[10.3155374527,49.159954071],"type":"Point"}
}