{
  "type": "Feature",
  "properties": {
    "iso:country":"DE",
    "sg:address":"R\u00f6merstr. 30",
    "sg:city":"Eutingen",
    "sg:phone":"+49 7459/91363",
    "sg:postcode":"72184",
    "sg:province":"Baden-W\u00fcrttemberg",
    "wof:name":"Dreiling Datentechnik Gmbh",
    "wof:placetype":"venue"
},
  "geometry": {"coordinates":[8.750191,48.492702],"type":"Point"}
}