{
  "type": "Feature",
  "properties": {
    "iso:country":"DE",
    "sg:address":"Ostring 18",
    "sg:city":"Holdorf",
    "sg:phone":"+49 5494/261",
    "sg:postcode":"49451",
    "sg:province":"Niedersachsen",
    "wof:name":"Birgits Haarmoden",
    "wof:placetype":"venue"
},
  "geometry": {"coordinates":[8.1267080307,52.5886878967],"type":"Point"}
}