{
  "type": "Feature",
  "properties": {
    "iso:country":"DE",
    "sg:address":"Haingraben 10",
    "sg:city":"Friedberg",
    "sg:phone":"+49 6031/72520",
    "sg:postcode":"61169",
    "sg:province":"Hessen",
    "wof:name":"Psycho-soz. Beratungs- Stelle D. Diak. Werkes",
    "wof:placetype":"venue"
},
  "geometry": {"coordinates":[8.758069,50.334145],"type":"Point"}
}