{
  "type": "Feature",
  "properties": {
    "iso:country":"DE",
    "sg:address":"Dorfstr. 24",
    "sg:city":"Ahlefeld",
    "sg:phone":"+49 4353/268",
    "sg:postcode":"24811",
    "sg:province":"Schleswig-Holstein",
    "wof:name":"Heinrich Hensen-frahm",
    "wof:placetype":"venue"
},
  "geometry": {"coordinates":[9.674997,54.401306],"type":"Point"}
}