{
  "type": "Feature",
  "properties": {
    "iso:country":"DE",
    "sg:address":"Hauptstr. 36",
    "sg:city":"Zarrentin",
    "sg:phone":"+49 38851/25371",
    "sg:postcode":"19246",
    "sg:province":"Mecklenburg-Vorpommern",
    "wof:name":"Ausbauhandwerk Eg",
    "wof:placetype":"venue"
},
  "geometry": {"coordinates":[10.918439,53.547436],"type":"Point"}
}