{
  "type": "Feature",
  "properties": {
    "iso:country":"DE",
    "sg:address":"Am Dorfteich 6 a",
    "sg:city":"Hamburg",
    "sg:phone":"+49 40/5506071",
    "sg:postcode":"22457",
    "sg:province":"Hamburg",
    "wof:name":"Hamburger Immobilien Meincke Ohg",
    "wof:placetype":"venue"
},
  "geometry": {"coordinates":[9.9192056656,53.6357078552],"type":"Point"}
}