{
  "type": "Feature",
  "properties": {
    "iso:country":"DE",
    "sg:address":"Kreuzberg 8",
    "sg:city":"Wernigerode",
    "sg:phone":"+49 3943/47186",
    "sg:postcode":"38855",
    "sg:province":"Sachsen-Anhalt",
    "wof:name":"Bruno Moder",
    "wof:placetype":"venue"
},
  "geometry": {"coordinates":[10.791292,51.827484],"type":"Point"}
}