{
  "type": "Feature",
  "properties": {
    "iso:country":"DE",
    "sg:address":"Niem\u00f6ller Str 13",
    "sg:city":"Ostfildern",
    "sg:phone":"+49 761/383000",
    "sg:postcode":"73760",
    "sg:province":"Baden-W\u00fcrttemberg",
    "wof:name":"Promot Automation Gmbh",
    "wof:placetype":"venue"
},
  "geometry": {"coordinates":[9.271928,48.720299],"type":"Point"}
}