{
  "type": "Feature",
  "properties": {
    "iso:country":"DE",
    "sg:address":"Werftstr. 8",
    "sg:city":"Wasserburg",
    "sg:postcode":"88142",
    "sg:province":"Bayern",
    "wof:name":"Elmar Golz E. K.",
    "wof:placetype":"venue"
},
  "geometry": {"coordinates":[9.6445102692,47.5615196228],"type":"Point"}
}