{
  "type": "Feature",
  "properties": {
    "iso:country":"DE",
    "sg:address":"Campingplatz",
    "sg:city":"Bad H\u00f6nningen",
    "sg:phone":"+49 2635/3199",
    "sg:postcode":"53557",
    "sg:province":"Rheinland-Pfalz",
    "wof:name":"Gastst\u00e4tte Camping-klause",
    "wof:placetype":"venue"
},
  "geometry": {"coordinates":[7.3101458549,50.5141448975],"type":"Point"}
}