{
  "type": "Feature",
  "properties": {
    "iso:country":"DE",
    "sg:address":"Eggensteiner Str. 141",
    "sg:city":"Stutensee",
    "sg:phone":"+49 7244/94034",
    "sg:postcode":"76297",
    "sg:province":"Baden-W\u00fcrttemberg",
    "wof:name":"Sommerlatt-sport Sportartikel",
    "wof:placetype":"venue"
},
  "geometry": {"coordinates":[8.45593,49.066189],"type":"Point"}
}