{
  "type": "Feature",
  "properties": {
    "iso:country":"DE",
    "sg:address":"Zum Jungfernborn 1",
    "sg:city":"Diemelstadt",
    "sg:phone":"+49 5694/97970",
    "sg:postcode":"34474",
    "sg:province":"Hessen",
    "wof:name":"Hotel Montana",
    "wof:placetype":"venue"
},
  "geometry": {"coordinates":[9.0074396133,51.487651825],"type":"Point"}
}