{
  "type": "Feature",
  "properties": {
    "iso:country":"DE",
    "sg:address":"Bahnstr. 81",
    "sg:city":"Grevenbroich",
    "sg:phone":"+49 2181/1205",
    "sg:postcode":"41515",
    "sg:province":"Nordrhein-Westfalen",
    "wof:name":"Ali Ibili",
    "wof:placetype":"venue"
},
  "geometry": {"coordinates":[6.5826258659,51.0918960571],"type":"Point"}
}