{
  "type": "Feature",
  "properties": {
    "iso:country":"DE",
    "sg:address":"Am Kandelborn 26",
    "sg:city":"Brauneberg",
    "sg:phone":"+49 6534/513",
    "sg:postcode":"54472",
    "sg:province":"Rheinland-Pfalz",
    "wof:name":"Ottmar Arnoldi",
    "wof:placetype":"venue"
},
  "geometry": {"coordinates":[6.9829068184,49.906162262],"type":"Point"}
}