{
  "type": "Feature",
  "properties": {
    "iso:country":"DE",
    "sg:address":"Holzener Str. 1",
    "sg:city":"Menden",
    "sg:phone":"+49 2373/394407",
    "sg:postcode":"58708",
    "sg:province":"Nordrhein-Westfalen",
    "wof:name":"Fricke",
    "wof:placetype":"venue"
},
  "geometry": {"coordinates":[7.756898,51.44857],"type":"Point"}
}