{
  "type": "Feature",
  "properties": {
    "iso:country":"DE",
    "sg:address":"Tucherstr. 17",
    "sg:city":"N\u00fcrnberg",
    "sg:phone":"+49 911/2449813",
    "sg:postcode":"90403",
    "sg:province":"Bayern",
    "wof:name":"Birke",
    "wof:placetype":"venue"
},
  "geometry": {"coordinates":[11.0806560516,49.4545936584],"type":"Point"}
}