{
  "type": "Feature",
  "properties": {
    "iso:country":"DE",
    "sg:address":"Hauptstr. 1a",
    "sg:city":"Hohenebra",
    "sg:phone":"+49 36020/72843",
    "sg:postcode":"99713",
    "sg:province":"Th\u00fcringen",
    "wof:name":"Agrarproduktion Hohenebra Gmbh",
    "wof:placetype":"venue"
},
  "geometry": {"coordinates":[10.815044,51.31078],"type":"Point"}
}