{
  "type": "Feature",
  "properties": {
    "iso:country":"DE",
    "sg:address":"Lockhauser Str. 132",
    "sg:city":"Herford",
    "sg:phone":"+49 5221/972572",
    "sg:postcode":"32052",
    "sg:province":"Nordrhein-Westfalen",
    "wof:name":"Profitec Gmbh",
    "wof:placetype":"venue"
},
  "geometry": {"coordinates":[8.6716556549,52.0964317322],"type":"Point"}
}