{
  "type": "Feature",
  "properties": {
    "iso:country":"DE",
    "sg:address":"Holzhofstr. 8",
    "sg:city":"Mainz",
    "sg:phone":"+49 6131/28260",
    "sg:postcode":"55116",
    "sg:province":"Rheinland-Pfalz",
    "wof:name":"Caritas Datenverarbeitung Gmbh",
    "wof:placetype":"venue"
},
  "geometry": {"coordinates":[8.277418,49.994328],"type":"Point"}
}