{
  "type": "Feature",
  "properties": {
    "iso:country":"DE",
    "sg:address":"Rappoltengr\u00fcner Str. 2",
    "sg:city":"Teuschnitz",
    "sg:phone":"+49 9268/237",
    "sg:postcode":"96358",
    "sg:province":"Bayern",
    "wof:name":"B. Jungkunz",
    "wof:placetype":"venue"
},
  "geometry": {"coordinates":[11.3815765381,50.3982582092],"type":"Point"}
}