{
  "type": "Feature",
  "properties": {
    "iso:country":"DE",
    "sg:address":"Kolpingring 3",
    "sg:city":"Kiedrich",
    "sg:phone":"+49 6123/5656",
    "sg:postcode":"65399",
    "sg:province":"Hessen",
    "wof:name":"Klaus Helkenberg",
    "wof:placetype":"venue"
},
  "geometry": {"coordinates":[8.0900936127,50.0385894775],"type":"Point"}
}