{
  "type": "Feature",
  "properties": {
    "iso:country":"DE",
    "sg:address":"Schneckenbergstr. 28",
    "sg:city":"Holzminden",
    "sg:phone":"+49 5531/61451",
    "sg:postcode":"37603",
    "sg:province":"Niedersachsen",
    "wof:name":"Hermann B\u00f6ker",
    "wof:placetype":"venue"
},
  "geometry": {"coordinates":[9.471647,51.82288],"type":"Point"}
}