{
  "type": "Feature",
  "properties": {
    "iso:country":"DE",
    "sg:address":"Saseler M\u00fchlenweg 54 a",
    "sg:city":"Hamburg",
    "sg:phone":"+49 40/6015247",
    "sg:postcode":"22395",
    "sg:province":"Hamburg",
    "wof:name":"Ortlinghaus-werke Gmbh",
    "wof:placetype":"venue"
},
  "geometry": {"coordinates":[10.1072530746,53.6614837646],"type":"Point"}
}