{
  "type": "Feature",
  "properties": {
    "iso:country":"DE",
    "sg:address":"Albert Einstein 3",
    "sg:city":"Kornwestheim",
    "sg:phone":"+49 4971/5482190",
    "sg:postcode":"70806",
    "sg:province":"Baden-W\u00fcrttemberg",
    "wof:name":"Roehren-handelsges. Toedtmann & Birk Gmbh",
    "wof:placetype":"venue"
},
  "geometry": {"coordinates":[9.185025,48.859295],"type":"Point"}
}