{
  "type": "Feature",
  "properties": {
    "iso:country":"DE",
    "sg:address":"Hauptstr. 38",
    "sg:city":"Sch\u00f6nbrunn",
    "sg:phone":"+49 6272/2135",
    "sg:postcode":"69436",
    "sg:province":"Baden-W\u00fcrttemberg",
    "wof:name":"Anton Wiest",
    "wof:placetype":"venue"
},
  "geometry": {"coordinates":[8.9327335358,49.4102401733],"type":"Point"}
}