{
  "type": "Feature",
  "properties": {
    "iso:country":"DE",
    "sg:address":"J\u00e4gerstr. 10",
    "sg:city":"Langenfeld",
    "sg:phone":"+49 2173/18300",
    "sg:postcode":"40764",
    "sg:province":"Nordrhein-Westfalen",
    "wof:name":"Janke Gmbh",
    "wof:placetype":"venue"
},
  "geometry": {"coordinates":[6.9519681931,51.099609375],"type":"Point"}
}