{
  "type": "Feature",
  "properties": {
    "iso:country":"DE",
    "sg:address":"Fallerslebener Str. 15",
    "sg:city":"Ehra-Lessien",
    "sg:phone":"+49 5377/231",
    "sg:postcode":"38468",
    "sg:province":"Niedersachsen",
    "wof:name":"G\u00e4stehaus Behne",
    "wof:placetype":"venue"
},
  "geometry": {"coordinates":[10.7887430191,52.5629272461],"type":"Point"}
}