{
  "type": "Feature",
  "properties": {
    "iso:country":"DE",
    "sg:address":"Esplanade 28",
    "sg:city":"Wesel",
    "sg:phone":"+49 281/21040",
    "sg:postcode":"46483",
    "sg:province":"Nordrhein-Westfalen",
    "wof:name":"Michael Kr\u00e4mer",
    "wof:placetype":"venue"
},
  "geometry": {"coordinates":[6.6164898872,51.6552886963],"type":"Point"}
}