{
  "type": "Feature",
  "properties": {
    "iso:country":"DE",
    "sg:address":"Schaftriebweg 6",
    "sg:city":"Mainz",
    "sg:phone":"+49 6131/572490",
    "sg:postcode":"55131",
    "sg:province":"Rheinland-Pfalz",
    "wof:name":"Eckart Kaunz",
    "wof:placetype":"venue"
},
  "geometry": {"coordinates":[8.2594366074,49.9833755493],"type":"Point"}
}