{
  "type": "Feature",
  "properties": {
    "iso:country":"DE",
    "sg:address":"Friedhofsweg 16",
    "sg:city":"Niestetal",
    "sg:phone":"+49 561/522896",
    "sg:postcode":"34266",
    "sg:province":"Hessen",
    "wof:name":"Willi Rode Grabdenkm\u00e4ler",
    "wof:placetype":"venue"
},
  "geometry": {"coordinates":[9.5529031754,51.3233375549],"type":"Point"}
}