{
  "type": "Feature",
  "properties": {
    "iso:country":"DE",
    "sg:address":"Gerwigstr. 4",
    "sg:city":"Sch\u00f6nwald",
    "sg:phone":"+49 4977/2295060",
    "sg:postcode":"78141",
    "sg:province":"Baden-W\u00fcrttemberg",
    "wof:name":"Hock Gmbh",
    "wof:placetype":"venue"
},
  "geometry": {"coordinates":[8.19503,48.105709],"type":"Point"}
}