{
  "type": "Feature",
  "properties": {
    "iso:country":"DE",
    "sg:address":"Riekenbank 7",
    "sg:city":"Essen",
    "sg:phone":"+49 201/672583",
    "sg:postcode":"45359",
    "sg:province":"Nordrhein-Westfalen",
    "wof:name":"Jaensch Transporte Gmbh",
    "wof:placetype":"venue"
},
  "geometry": {"coordinates":[6.9519839287,51.4622840881],"type":"Point"}
}