{
  "type": "Feature",
  "properties": {
    "iso:country":"DE",
    "sg:address":"Osterloh 32",
    "sg:city":"Hamburg",
    "sg:phone":"+49 40/828826",
    "sg:postcode":"22589",
    "sg:province":"Hamburg",
    "wof:name":"Ihre Polsterwerkstatt Gmbh",
    "wof:placetype":"venue"
},
  "geometry": {"coordinates":[9.828168869,53.5806427002],"type":"Point"}
}