{
  "type": "Feature",
  "properties": {
    "iso:country":"DE",
    "sg:address":"Hauptstr. 17",
    "sg:city":"Marktoffingen",
    "sg:phone":"+49 9087/701",
    "sg:postcode":"86748",
    "sg:province":"Bayern",
    "wof:name":"L. Zeitlmann",
    "wof:placetype":"venue"
},
  "geometry": {"coordinates":[10.469311,48.9259],"type":"Point"}
}