{
  "type": "Feature",
  "properties": {
    "iso:country":"DE",
    "sg:address":"Nincoper Str. 50",
    "sg:city":"Hamburg",
    "sg:phone":"+49 40/7459552",
    "sg:postcode":"21129",
    "sg:province":"Hamburg",
    "wof:name":"Dieter Oben Gmbh",
    "wof:placetype":"venue"
},
  "geometry": {"coordinates":[9.772049,53.52124],"type":"Point"}
}