{
  "type": "Feature",
  "properties": {
    "iso:country":"DE",
    "sg:address":"Kantstr. 24",
    "sg:city":"Cloppenburg",
    "sg:phone":"+49 4471/6480",
    "sg:postcode":"49661",
    "sg:province":"Niedersachsen",
    "wof:name":"H. Fahrenholz Immobilienmakler",
    "wof:placetype":"venue"
},
  "geometry": {"coordinates":[8.0507421494,52.855381012],"type":"Point"}
}