{
  "type": "Feature",
  "properties": {
    "iso:country":"DE",
    "sg:address":"Iltisweg 5",
    "sg:city":"Kleve",
    "sg:phone":"+49 2821/48554",
    "sg:postcode":"47533",
    "sg:province":"Nordrhein-Westfalen",
    "wof:name":"Wolfgang Eis",
    "wof:placetype":"venue"
},
  "geometry": {"coordinates":[6.100265,51.761814],"type":"Point"}
}