{
  "type": "Feature",
  "properties": {
    "iso:country":"DE",
    "sg:address":"Kleeweg 12",
    "sg:city":"Salzkotten",
    "sg:phone":"+49 4902/9557486",
    "sg:postcode":"33154",
    "sg:province":"Nordrhein-Westfalen",
    "wof:name":"Artex-design",
    "wof:placetype":"venue"
},
  "geometry": {"coordinates":[8.670462,51.633724],"type":"Point"}
}