{
  "type": "Feature",
  "properties": {
    "iso:country":"DE",
    "sg:address":"Friedrich-Hebbel-Ring 3",
    "sg:city":"Henstedt-Ulzburg",
    "sg:phone":"+49 4193/77001",
    "sg:postcode":"24558",
    "sg:province":"Schleswig-Holstein",
    "wof:name":"Computer Equipment Edv Anlagen Und Berat. Gmbh",
    "wof:placetype":"venue"
},
  "geometry": {"coordinates":[10.0032958984,53.7505149841],"type":"Point"}
}