{
  "type": "Feature",
  "properties": {
    "iso:country":"DE",
    "sg:address":"Zubermoosstr. 12",
    "sg:city":"Aichhalden",
    "sg:phone":"+49 7444/2038",
    "sg:postcode":"78733",
    "sg:province":"Baden-W\u00fcrttemberg",
    "wof:name":"Eduard Hildbrand",
    "wof:placetype":"venue"
},
  "geometry": {"coordinates":[8.4237766266,48.3020248413],"type":"Point"}
}