{
  "type": "Feature",
  "properties": {
    "iso:country":"DE",
    "sg:address":"Laurentiusstr. 5",
    "sg:city":"Perasdorf",
    "sg:phone":"+49 9962/328",
    "sg:postcode":"94366",
    "sg:province":"Bayern",
    "wof:name":"Gasthaus Karl Barwig",
    "wof:placetype":"venue"
},
  "geometry": {"coordinates":[12.8005456924,48.9497833252],"type":"Point"}
}