{
  "type": "Feature",
  "properties": {
    "iso:country":"DE",
    "sg:address":"Am Sportplatz 1",
    "sg:city":"Stolzenhain a d R\u00f6der",
    "sg:phone":"+49 3533/8328",
    "sg:postcode":"04932",
    "sg:province":"Brandenburg",
    "wof:name":"Hotel-rest. R\u00f6dersch\u00e4nke",
    "wof:placetype":"venue"
},
  "geometry": {"coordinates":[13.4472351074,51.4398841858],"type":"Point"}
}