{
  "type": "Feature",
  "properties": {
    "iso:country":"DE",
    "sg:address":"Oststr. 28",
    "sg:city":"Halver",
    "sg:phone":"+49 2353/3121",
    "sg:postcode":"58553",
    "sg:province":"Nordrhein-Westfalen",
    "wof:name":"Karl-rudolf Bremicker",
    "wof:placetype":"venue"
},
  "geometry": {"coordinates":[7.509718,51.197399],"type":"Point"}
}