{
  "type": "Feature",
  "properties": {
    "iso:country":"DE",
    "sg:address":"Am Ziegelplatz 17",
    "sg:city":"Schutterwald",
    "sg:phone":"+49 781/605780",
    "sg:postcode":"77746",
    "sg:province":"Baden-W\u00fcrttemberg",
    "wof:name":"Teamwerk Andreas Ritter E. K.",
    "wof:placetype":"venue"
},
  "geometry": {"coordinates":[7.90217,48.455414],"type":"Point"}
}