{
  "type": "Feature",
  "properties": {
    "iso:country":"DE",
    "sg:address":"Habenhauser Landstr. 63",
    "sg:city":"Bremen",
    "sg:phone":"+49 421/870032",
    "sg:postcode":"28277",
    "sg:province":"Bremen",
    "wof:name":"Dombrot Backwaren Gmbh",
    "wof:placetype":"venue"
},
  "geometry": {"coordinates":[8.827004,53.050266],"type":"Point"}
}