{
  "type": "Feature",
  "properties": {
    "iso:country":"DE",
    "sg:address":"Berghausstr. 3",
    "sg:city":"Neustadt",
    "sg:phone":"+49 3596/564278",
    "sg:postcode":"01844",
    "sg:province":"Sachsen",
    "wof:name":"Wuk",
    "wof:placetype":"venue"
},
  "geometry": {"coordinates":[14.2149028778,51.020275116],"type":"Point"}
}