{
  "type": "Feature",
  "properties": {
    "iso:country":"DE",
    "sg:address":"02748",
    "sg:city":"Bernstadt",
    "sg:phone":"+49 35874/25336",
    "sg:postcode":"02748",
    "sg:province":"Sachsen",
    "wof:name":"Freibad",
    "wof:placetype":"venue"
},
  "geometry": {"coordinates":[14.8250398636,51.0458602905],"type":"Point"}
}