{
  "type": "Feature",
  "properties": {
    "iso:country":"DE",
    "sg:address":"Drosselweg 14",
    "sg:city":"Geilenkirchen",
    "sg:phone":"+49 2451/66173",
    "sg:postcode":"52511",
    "sg:province":"Nordrhein-Westfalen",
    "wof:name":"Ingeburg Dohlen",
    "wof:placetype":"venue"
},
  "geometry": {"coordinates":[6.12174,50.971611],"type":"Point"}
}