{
  "type": "Feature",
  "properties": {
    "iso:country":"DE",
    "sg:address":"Clarholzer Str. 76",
    "sg:city":"Herzebrock-Clarholz",
    "sg:phone":"+49 5245/44433",
    "sg:postcode":"33442",
    "sg:province":"Nordrhein-Westfalen",
    "wof:name":"Gemeindearchiv",
    "wof:placetype":"venue"
},
  "geometry": {"coordinates":[8.233437,51.883137],"type":"Point"}
}