{
  "type": "Feature",
  "properties": {
    "iso:country":"DE",
    "sg:address":"Hoyerswerdaer Str. 20",
    "sg:city":"Kreba-Neudorf",
    "sg:phone":"+49 35893/840",
    "sg:postcode":"02906",
    "sg:province":"Sachsen",
    "wof:name":"Geocad Beratende Ingenieure Gmbh",
    "wof:placetype":"venue"
},
  "geometry": {"coordinates":[14.6767,51.345901],"type":"Point"}
}