{
  "type": "Feature",
  "properties": {
    "iso:country":"DE",
    "sg:address":"Hildesheimer Str. 17",
    "sg:city":"Holle",
    "sg:phone":"+49 5062/1861",
    "sg:postcode":"31188",
    "sg:province":"Niedersachsen",
    "wof:name":"Kutscherstuben Inh. Fam. Pinkepank",
    "wof:placetype":"venue"
},
  "geometry": {"coordinates":[10.1635503769,52.1077537537],"type":"Point"}
}