{
  "type": "Feature",
  "properties": {
    "iso:country":"DE",
    "sg:address":"Weingartenstr. 14a",
    "sg:city":"Dormagen",
    "sg:phone":"+49 2133/42086",
    "sg:postcode":"41539",
    "sg:province":"Nordrhein-Westfalen",
    "wof:name":"Heinz Greven Architekt",
    "wof:placetype":"venue"
},
  "geometry": {"coordinates":[6.836326,51.096806],"type":"Point"}
}