{
  "type": "Feature",
  "properties": {
    "iso:country":"DE",
    "sg:address":"Hauptstr. 78",
    "sg:city":"Werenzhain",
    "sg:phone":"+49 35322/2735",
    "sg:postcode":"03253",
    "sg:province":"Brandenburg",
    "wof:name":"G. Mahl",
    "wof:placetype":"venue"
},
  "geometry": {"coordinates":[13.536917,51.653397],"type":"Point"}
}