{
  "type": "Feature",
  "properties": {
    "iso:country":"DE",
    "sg:address":"N\u00e4hermemminger Weg 6",
    "sg:city":"N\u00f6rdlingen",
    "sg:phone":"+49 9081/4335",
    "sg:postcode":"86720",
    "sg:province":"Bayern",
    "wof:name":"Rudolf Kling",
    "wof:placetype":"venue"
},
  "geometry": {"coordinates":[10.478014946,48.8491821289],"type":"Point"}
}