{
  "type": "Feature",
  "properties": {
    "iso:country":"DE",
    "sg:address":"Kirchheimer Str. 170",
    "sg:city":"Dettingen",
    "sg:phone":"+49 4970/2150700",
    "sg:postcode":"73265",
    "sg:province":"Baden-W\u00fcrttemberg",
    "wof:name":"Schwabenmobil Gmbh",
    "wof:placetype":"venue"
},
  "geometry": {"coordinates":[9.454120636,48.6242790222],"type":"Point"}
}