{
  "type": "Feature",
  "properties": {
    "iso:country":"DE",
    "sg:address":"Hauptstr. 18",
    "sg:city":"Meitingen",
    "sg:phone":"+49 8271/6744",
    "sg:postcode":"86405",
    "sg:province":"Bayern",
    "wof:name":"L. Beutm\u00fcller & M. Mick",
    "wof:placetype":"venue"
},
  "geometry": {"coordinates":[10.8495149612,48.5457229614],"type":"Point"}
}