{
  "type": "Feature",
  "properties": {
    "iso:country":"DE",
    "sg:address":"Gerbrunner Str. 22",
    "sg:city":"Randersacker",
    "sg:phone":"+49 931/708496",
    "sg:postcode":"97236",
    "sg:province":"Bayern",
    "wof:name":"Gerhard Spatzig",
    "wof:placetype":"venue"
},
  "geometry": {"coordinates":[9.9904413223,49.7658309937],"type":"Point"}
}