{
  "type": "Feature",
  "properties": {
    "iso:country":"DE",
    "sg:address":"beethuvenstr.11",
    "sg:city":"telgte",
    "sg:postcode":"48291",
    "sg:province":"Nordrhein-Westfalen",
    "wof:name":"Forum F\u00fcr Die Gemeindearbeit",
    "wof:placetype":"venue"
},
  "geometry": {"coordinates":[7.787057,51.982235],"type":"Point"}
}