{
  "type": "Feature",
  "properties": {
    "iso:country":"DE",
    "sg:address":"Holmer Weg 7a",
    "sg:city":"Buchholz",
    "sg:phone":"+49 4187/1048",
    "sg:postcode":"21244",
    "sg:province":"Niedersachsen",
    "wof:name":"Decon Systeme Vertriebs- Und Service Gmbh",
    "wof:placetype":"venue"
},
  "geometry": {"coordinates":[9.873381,53.2798],"type":"Point"}
}