{
  "type": "Feature",
  "properties": {
    "iso:country":"DE",
    "sg:address":"Schillerstr. 19",
    "sg:city":"Naumburg",
    "sg:postcode":"06618",
    "sg:province":"Sachsen-Anhalt",
    "wof:name":"Kinderheim Dr. Artur Samter",
    "wof:placetype":"venue"
},
  "geometry": {"coordinates":[11.814499855,51.1434707642],"type":"Point"}
}