{
  "type": "Feature",
  "properties": {
    "iso:country":"DE",
    "sg:address":"Zimmergrundstr. 54",
    "sg:city":"Bad Wildungen",
    "sg:phone":"+49 5621/1523",
    "sg:postcode":"34537",
    "sg:province":"Hessen",
    "wof:name":"J\u00e4gersruh",
    "wof:placetype":"venue"
},
  "geometry": {"coordinates":[9.1028003693,51.1079902649],"type":"Point"}
}