{
  "type": "Feature",
  "properties": {
    "iso:country":"DE",
    "sg:address":"Schierenberg 9",
    "sg:city":"Hamburg",
    "sg:postcode":"22147",
    "sg:province":"Hamburg",
    "wof:name":"Pko Immobilien- Und Verwaltungsges. Mbh",
    "wof:placetype":"venue"
},
  "geometry": {"coordinates":[10.1421546936,53.6235694885],"type":"Point"}
}