{
  "type": "Feature",
  "properties": {
    "iso:country":"DE",
    "sg:address":"Masurenstr. 2",
    "sg:city":"Herzberg",
    "sg:phone":"+49 5521/71922",
    "sg:postcode":"37412",
    "sg:province":"Niedersachsen",
    "wof:name":"Mecklenburger Hof",
    "wof:placetype":"venue"
},
  "geometry": {"coordinates":[10.3155250549,51.6143951416],"type":"Point"}
}