{
  "type": "Feature",
  "properties": {
    "iso:country":"DE",
    "sg:address":"Auf dem Kamp 38",
    "sg:city":"Seevetal",
    "sg:phone":"+49 4105/12118",
    "sg:postcode":"21217",
    "sg:province":"Niedersachsen",
    "wof:name":"Sch\u00f6ttler Akustik- Spezialbau Gmbh",
    "wof:placetype":"venue"
},
  "geometry": {"coordinates":[10.021887,53.403858],"type":"Point"}
}