{
  "type": "Feature",
  "properties": {
    "iso:country":"DE",
    "sg:address":"Westenfelder Str. 114",
    "sg:city":"Bochum",
    "sg:phone":"+49 2327/36337",
    "sg:postcode":"44867",
    "sg:province":"Nordrhein-Westfalen",
    "wof:name":"Westenfelder Grill",
    "wof:placetype":"venue"
},
  "geometry": {"coordinates":[7.1453490257,51.4738845825],"type":"Point"}
}