{
  "type": "Feature",
  "properties": {
    "iso:country":"DE",
    "sg:address":"Quirinstr. 43",
    "sg:city":"D\u00fcsseldorf",
    "sg:phone":"+49 211/554095",
    "sg:postcode":"40545",
    "sg:province":"Nordrhein-Westfalen",
    "wof:name":"Ev. Pfarramt I Auferstehungskirche Oberkassel",
    "wof:placetype":"venue"
},
  "geometry": {"coordinates":[6.7498869896,51.2336273193],"type":"Point"}
}