{
  "type": "Feature",
  "properties": {
    "iso:country":"DE",
    "sg:address":"Gerntkebogen 8",
    "sg:city":"Hamburg",
    "sg:phone":"+49 40/7354353",
    "sg:postcode":"21035",
    "sg:province":"Hamburg",
    "wof:name":"Reiner Fr\u00fchling",
    "wof:placetype":"venue"
},
  "geometry": {"coordinates":[10.1834030151,53.4793930054],"type":"Point"}
}