{
  "type": "Feature",
  "properties": {
    "iso:country":"DE",
    "sg:address":"Eschenauer Hauptstr. 63",
    "sg:city":"Eckental",
    "sg:phone":"+49 9126/281515",
    "sg:postcode":"90542",
    "sg:province":"Bayern",
    "wof:name":"S\u00e4gewerk",
    "wof:placetype":"venue"
},
  "geometry": {"coordinates":[11.202368,49.575413],"type":"Point"}
}