{
  "type": "Feature",
  "properties": {
    "iso:country":"DE",
    "sg:address":"Hofwiesenweg 9::",
    "sg:city":"N\u00fcrnberg-Buch",
    "sg:phone":"+49 911/934350",
    "sg:postcode":"90427",
    "sg:province":"Bayern",
    "wof:name":"Raiffeisenbank Knoblauchsland Eg",
    "wof:placetype":"venue"
},
  "geometry": {"coordinates":[11.045401,49.497963],"type":"Point"}
}