{
  "type": "Feature",
  "properties": {
    "iso:country":"DE",
    "sg:address":"Eduard-Grunow-Str. 24 A",
    "sg:city":"Bremen",
    "sg:phone":"+49 421/76095",
    "sg:postcode":"28203",
    "sg:province":"Bremen",
    "wof:name":"Damas Restaurant Gmbh",
    "wof:placetype":"venue"
},
  "geometry": {"coordinates":[8.8210725784,53.0773048401],"type":"Point"}
}