{
  "type": "Feature",
  "properties": {
    "iso:country":"DE",
    "sg:address":"Schulstr. 3",
    "sg:city":"Owingen",
    "sg:postcode":"88696",
    "sg:province":"Baden-W\u00fcrttemberg",
    "wof:name":"Jugend- Und Gemeindeb\u00fccherei Schulhaus",
    "wof:placetype":"venue"
},
  "geometry": {"coordinates":[9.173184,47.808624],"type":"Point"}
}