{
  "type": "Feature",
  "properties": {
    "iso:country":"DE",
    "sg:address":"Rissener Dorfstr. 11",
    "sg:city":"Hamburg",
    "sg:phone":"+49 40/815093",
    "sg:postcode":"22559",
    "sg:province":"Hamburg",
    "wof:name":"Harald Fredeland",
    "wof:placetype":"venue"
},
  "geometry": {"coordinates":[9.760717392,53.5806045532],"type":"Point"}
}