{
  "type": "Feature",
  "properties": {
    "iso:country":"DE",
    "sg:address":"Reichsstr. 33",
    "sg:city":"Freudenstadt",
    "sg:phone":"+49 7441/7281",
    "sg:postcode":"72250",
    "sg:province":"Baden-W\u00fcrttemberg",
    "wof:name":"O. B\u00e4uerle",
    "wof:placetype":"venue"
},
  "geometry": {"coordinates":[8.413367,48.462452],"type":"Point"}
}