{
  "type": "Feature",
  "properties": {
    "iso:country":"DE",
    "sg:address":"Fritz-Kiehn-Str. 15",
    "sg:city":"Bad D\u00fcrrheim",
    "sg:phone":"+49 7706/5474",
    "sg:postcode":"78073",
    "sg:province":"Baden-W\u00fcrttemberg",
    "wof:name":"Reinhard W\u00f6lfle Architekt",
    "wof:placetype":"venue"
},
  "geometry": {"coordinates":[8.587284,47.99855],"type":"Point"}
}