{
  "type": "Feature",
  "properties": {
    "iso:country":"DE",
    "sg:address":"Berblingerstr. 18",
    "sg:city":"Laupheim",
    "sg:phone":"+49 4973/929780",
    "sg:postcode":"88471",
    "sg:province":"Baden-W\u00fcrttemberg",
    "wof:name":"Fischer Gmbh",
    "wof:placetype":"venue"
},
  "geometry": {"coordinates":[9.8768081665,48.2180900574],"type":"Point"}
}