{
  "type": "Feature",
  "properties": {
    "iso:country":"DE",
    "sg:address":"M\u00fchlh\u00e4user Str. 10",
    "sg:city":"Twistetal",
    "sg:phone":"+49 5695/1338",
    "sg:postcode":"34477",
    "sg:province":"Hessen",
    "wof:name":"Karl Heinemann",
    "wof:placetype":"venue"
},
  "geometry": {"coordinates":[8.930675,51.33131],"type":"Point"}
}