{
  "type": "Feature",
  "properties": {
    "iso:country":"DE",
    "sg:address":"Lichtensteiner Str. 24",
    "sg:city":"Hartenstein",
    "sg:phone":"+49 37605/4250",
    "sg:postcode":"08118",
    "sg:province":"Sachsen",
    "wof:name":"Goldener Stern",
    "wof:placetype":"venue"
},
  "geometry": {"coordinates":[12.6673717499,50.6653366089],"type":"Point"}
}