{
  "type": "Feature",
  "properties": {
    "iso:country":"DE",
    "sg:address":"Graf-Rhena-Str. 2",
    "sg:city":"Karlsruhe",
    "sg:phone":"+49 721/9823972",
    "sg:postcode":"76137",
    "sg:province":"Baden-W\u00fcrttemberg",
    "wof:name":"Alexander Denk",
    "wof:placetype":"venue"
},
  "geometry": {"coordinates":[8.3926382065,48.997341156],"type":"Point"}
}