{
  "type": "Feature",
  "properties": {
    "iso:country":"DE",
    "sg:address":"Ziegeleistr. 1",
    "sg:city":"Genthin",
    "sg:phone":"+49 3933/96900",
    "sg:postcode":"39307",
    "sg:province":"Sachsen-Anhalt",
    "wof:name":"Hotel M\u00fcller",
    "wof:placetype":"venue"
},
  "geometry": {"coordinates":[12.1532659531,52.4116477966],"type":"Point"}
}