{
  "type": "Feature",
  "properties": {
    "iso:country":"DE",
    "sg:address":"Wendenstr. 42",
    "sg:city":"Lichtenfels",
    "sg:postcode":"96215",
    "sg:province":"Bayern",
    "wof:name":"Jahn Verwaltungs Gmbh",
    "wof:placetype":"venue"
},
  "geometry": {"coordinates":[11.0770311356,50.1515235901],"type":"Point"}
}