{
  "type": "Feature",
  "properties": {
    "iso:country":"DE",
    "sg:address":"Mauerstr. 27",
    "sg:city":"Rudolstadt",
    "sg:phone":"+49 3672/422784",
    "sg:postcode":"07407",
    "sg:province":"Th\u00fcringen",
    "wof:name":"Dieter L\u00f6sche",
    "wof:placetype":"venue"
},
  "geometry": {"coordinates":[11.3381614685,50.7195892334],"type":"Point"}
}