{
  "type": "Feature",
  "properties": {
    "iso:country":"DE",
    "sg:address":"Eninger Str. 44",
    "sg:city":"Metzingen",
    "sg:phone":"+49 7123/60059",
    "sg:postcode":"72555",
    "sg:province":"Baden-W\u00fcrttemberg",
    "wof:name":"Michael Koch",
    "wof:placetype":"venue"
},
  "geometry": {"coordinates":[9.3052330017,48.5095710754],"type":"Point"}
}