{
  "type": "Feature",
  "properties": {
    "iso:country":"DE",
    "sg:address":"Weststr. 18",
    "sg:city":"Chemnitz",
    "sg:phone":"+49 371/350391",
    "sg:postcode":"09112",
    "sg:province":"Sachsen",
    "wof:name":"Petra Z\u00e4hringer Rechtsanw\u00e4ltin",
    "wof:placetype":"venue"
},
  "geometry": {"coordinates":[12.9064970016,50.832988739],"type":"Point"}
}