{
  "type": "Feature",
  "properties": {
    "iso:country":"DE",
    "sg:address":"Kapellenstr. 13",
    "sg:city":"Gersthofen",
    "sg:phone":"+49 821/493280",
    "sg:postcode":"86368",
    "sg:province":"Bayern",
    "wof:name":"Walter Rothe Versandgesch\u00e4ft",
    "wof:placetype":"venue"
},
  "geometry": {"coordinates":[10.8797082901,48.4209098816],"type":"Point"}
}