{
  "type": "Feature",
  "properties": {
    "iso:country":"DE",
    "sg:address":"Branderstr. 36",
    "sg:city":"Ruhpolding",
    "sg:phone":"+49 8663/2381",
    "sg:postcode":"83324",
    "sg:province":"Bayern",
    "wof:name":"Werner Kastner Kunst- Und Bauschlosserei",
    "wof:placetype":"venue"
},
  "geometry": {"coordinates":[12.6436185837,47.7586250305],"type":"Point"}
}