{
  "type": "Feature",
  "properties": {
    "iso:country":"DE",
    "sg:address":"Ottilienstr. 10",
    "sg:city":"K\u00f6ln",
    "sg:phone":"+49 221/681317",
    "sg:postcode":"51069",
    "sg:province":"Nordrhein-Westfalen",
    "wof:name":"Heinen M\u00f6beltransporte Gmbh & Co. Kg",
    "wof:placetype":"venue"
},
  "geometry": {"coordinates":[7.0699548721,50.9805755615],"type":"Point"}
}