{
  "type": "Feature",
  "properties": {
    "iso:country":"DE",
    "sg:address":"S\u00f6geler Str. 5",
    "sg:city":"Klein Ber\u00dfen",
    "sg:phone":"+49 5965/251",
    "sg:postcode":"49777",
    "sg:province":"Niedersachsen",
    "wof:name":"H. Hoffmann",
    "wof:placetype":"venue"
},
  "geometry": {"coordinates":[7.458364,52.77039],"type":"Point"}
}