{
  "type": "Feature",
  "properties": {
    "iso:country":"DE",
    "sg:address":"Gartenstr. 50",
    "sg:city":"Gerlingen",
    "sg:phone":"+49 7156/21824",
    "sg:postcode":"70839",
    "sg:province":"Baden-W\u00fcrttemberg",
    "wof:name":"Helmut Rometsch",
    "wof:placetype":"venue"
},
  "geometry": {"coordinates":[9.068081,48.796223],"type":"Point"}
}