{
  "type": "Feature",
  "properties": {
    "iso:country":"DE",
    "sg:address":"Hohenesch 6",
    "sg:city":"Hamburg",
    "sg:phone":"+49 40/393995",
    "sg:postcode":"22765",
    "sg:province":"Hamburg",
    "wof:name":"Hongs",
    "wof:placetype":"venue"
},
  "geometry": {"coordinates":[9.929019928,53.5544662476],"type":"Point"}
}