{
  "type": "Feature",
  "properties": {
    "iso:country":"DE",
    "sg:address":"Waberner Str. 16",
    "sg:city":"Fritzlar",
    "sg:phone":"+49 5622/4063",
    "sg:postcode":"34560",
    "sg:province":"Hessen",
    "wof:name":"W. Fischer Steuerberater",
    "wof:placetype":"venue"
},
  "geometry": {"coordinates":[9.2835578918,51.1269264221],"type":"Point"}
}