{
  "type": "Feature",
  "properties": {
    "iso:country":"DE",
    "sg:address":"Ostlandring 11 a",
    "sg:city":"Burgdorf",
    "sg:phone":"+49 5136/4488",
    "sg:postcode":"31303",
    "sg:province":"Niedersachsen",
    "wof:name":"Peter Weinmann",
    "wof:placetype":"venue"
},
  "geometry": {"coordinates":[10.02737,52.442429],"type":"Point"}
}