{
  "type": "Feature",
  "properties": {
    "iso:country":"DE",
    "sg:address":"Werrastr. 13",
    "sg:city":"Bad Sooden-Allendorf",
    "sg:phone":"+49 5652",
    "sg:postcode":"37242",
    "sg:province":"Hessen",
    "wof:name":"Autohaus Stoeber & Schmidt Gmbh & Co.kg",
    "wof:placetype":"venue"
},
  "geometry": {"coordinates":[9.9767827988,51.2632369995],"type":"Point"}
}