{
  "type": "Feature",
  "properties": {
    "iso:country":"DE",
    "sg:address":"Gelthari-Ring 2",
    "sg:city":"Geldersheim",
    "sg:phone":"+49 9721/88852",
    "sg:postcode":"97505",
    "sg:province":"Bayern",
    "wof:name":"Lutz Gube",
    "wof:placetype":"venue"
},
  "geometry": {"coordinates":[10.151687,50.04958],"type":"Point"}
}