{
  "type": "Feature",
  "properties": {
    "iso:country":"DE",
    "sg:address":"Homburger Str. 141",
    "sg:city":"Bad Vilbel",
    "sg:phone":"+49 6101/42444",
    "sg:postcode":"61118",
    "sg:province":"Hessen",
    "wof:name":"Karl Fischer",
    "wof:placetype":"venue"
},
  "geometry": {"coordinates":[8.7243080139,50.1912269592],"type":"Point"}
}