{
  "type": "Feature",
  "properties": {
    "iso:country":"DE",
    "sg:address":"Luttern 11",
    "sg:city":"Minden",
    "sg:phone":"+49 5734/2134",
    "sg:postcode":"32429",
    "sg:province":"Nordrhein-Westfalen",
    "wof:name":"Heinrich Diekmann",
    "wof:placetype":"venue"
},
  "geometry": {"coordinates":[8.809225,52.265297],"type":"Point"}
}