{
  "type": "Feature",
  "properties": {
    "iso:country":"DE",
    "sg:address":"Friedhofstr. 2",
    "sg:city":"Aschaffenburg",
    "sg:phone":"+49 6021/423235",
    "sg:postcode":"63741",
    "sg:province":"Bayern",
    "wof:name":"Leo Emge",
    "wof:placetype":"venue"
},
  "geometry": {"coordinates":[9.1340227127,49.9842948914],"type":"Point"}
}