{
  "type": "Feature",
  "properties": {
    "iso:country":"DE",
    "sg:address":"Breitscheidstr. 103",
    "sg:city":"Rudolstadt",
    "sg:phone":"+49 3672/52790",
    "sg:postcode":"07407",
    "sg:province":"Th\u00fcringen",
    "wof:name":"Verwaltungsgesellschaft Twa W\u00e4rmeanlagenbau Th\u00fcringen Gmbh",
    "wof:placetype":"venue"
},
  "geometry": {"coordinates":[11.328433,50.701584],"type":"Point"}
}