{
  "type": "Feature",
  "properties": {
    "iso:country":"DE",
    "sg:address":"Julius-Schaxel-Str 19",
    "sg:city":"Jena",
    "sg:phone":"+49 3641/444725",
    "sg:postcode":"07749",
    "sg:province":"Th\u00fcringen",
    "wof:name":"Karl-heinz Zeise",
    "wof:placetype":"venue"
},
  "geometry": {"coordinates":[11.618003,50.931393],"type":"Point"}
}