{
  "type": "Feature",
  "properties": {
    "iso:country":"DE",
    "sg:address":"Brauhof 12 a",
    "sg:city":"Bochum",
    "sg:phone":"+49 2327/86103",
    "sg:postcode":"44866",
    "sg:province":"Nordrhein-Westfalen",
    "wof:name":"Schubert",
    "wof:placetype":"venue"
},
  "geometry": {"coordinates":[7.133935,51.480667],"type":"Point"}
}