{
  "type": "Feature",
  "properties": {
    "iso:country":"DE",
    "sg:address":"Markt",
    "sg:city":"Bonn",
    "sg:phone":"+49 228/651761",
    "sg:postcode":"53111",
    "sg:province":"Nordrhein-Westfalen",
    "wof:name":"Parkhaus Marktgarage",
    "wof:placetype":"venue"
},
  "geometry": {"coordinates":[7.1021900177,50.7351989746],"type":"Point"}
}