{
  "type": "Feature",
  "properties": {
    "iso:country":"DE",
    "sg:address":"Objektstr. 52",
    "sg:city":"Ostseebad Binz",
    "sg:postcode":"18609",
    "sg:province":"Mecklenburg-Vorpommern",
    "wof:name":"Baugesellschaft Gmbh Binz",
    "wof:placetype":"venue"
},
  "geometry": {"coordinates":[13.574337,54.438259],"type":"Point"}
}