{
  "type": "Feature",
  "properties": {
    "iso:country":"DE",
    "sg:address":"Gewerbegebiet",
    "sg:city":"Osburg",
    "sg:phone":"+49 6500/91650",
    "sg:postcode":"54317",
    "sg:province":"Rheinland-Pfalz",
    "wof:name":"Coprex Energiesparsysteme Gmbh",
    "wof:placetype":"venue"
},
  "geometry": {"coordinates":[6.790945,49.714741],"type":"Point"}
}