{
  "type": "Feature",
  "properties": {
    "iso:country":"DE",
    "sg:address":"Frankfurter Str. 4",
    "sg:city":"Essen",
    "sg:postcode":"45145",
    "sg:province":"Nordrhein-Westfalen",
    "wof:name":"Gub Grund Und Boden Immobilienges. Mbh",
    "wof:placetype":"venue"
},
  "geometry": {"coordinates":[6.9763660431,51.4497337341],"type":"Point"}
}