{
  "type": "Feature",
  "properties": {
    "iso:country":"DE",
    "sg:address":"Hans-Tenhaeff-Str. 45",
    "sg:city":"Straelen",
    "sg:phone":"+49 2834/2020",
    "sg:postcode":"47638",
    "sg:province":"Nordrhein-Westfalen",
    "wof:name":"B. Nellesen",
    "wof:placetype":"venue"
},
  "geometry": {"coordinates":[6.269302845,51.4412307739],"type":"Point"}
}