{
  "type": "Feature",
  "properties": {
    "iso:country":"DE",
    "sg:address":"Ant Kruse B\u00f6mken 26",
    "sg:city":"Borken",
    "sg:phone":"+49 2861/61997",
    "sg:postcode":"46325",
    "sg:province":"Nordrhein-Westfalen",
    "wof:name":"Wilhelm Woeste Heilpraktiker",
    "wof:placetype":"venue"
},
  "geometry": {"coordinates":[6.7916989326,51.8480033875],"type":"Point"}
}