{
  "type": "Feature",
  "properties": {
    "iso:country":"DE",
    "sg:address":"Dieselstr. 3a",
    "sg:city":"Darmstadt",
    "sg:phone":"+49 6151/537092",
    "sg:postcode":"64293",
    "sg:province":"Hessen",
    "wof:name":"Wolfgang Schober",
    "wof:placetype":"venue"
},
  "geometry": {"coordinates":[8.633058548,49.8850021362],"type":"Point"}
}