{
  "type": "Feature",
  "properties": {
    "iso:country":"DE",
    "sg:address":"Neuwerk",
    "sg:city":"Solingen",
    "sg:postcode":"42659",
    "sg:province":"Nordrhein-Westfalen",
    "wof:name":"Javo Productions",
    "wof:placetype":"venue"
},
  "geometry": {"coordinates":[7.158447,51.151436],"type":"Point"}
}