{
  "type": "Feature",
  "properties": {
    "iso:country":"DE",
    "sg:address":"Mozartstr. 29",
    "sg:city":"Bopfingen",
    "sg:phone":"+49 7362/96970",
    "sg:postcode":"73441",
    "sg:province":"Baden-W\u00fcrttemberg",
    "wof:name":"Otto Ilk Steuerberater",
    "wof:placetype":"venue"
},
  "geometry": {"coordinates":[10.3632917404,48.8600234985],"type":"Point"}
}