{
  "type": "Feature",
  "properties": {
    "iso:country":"DE",
    "sg:address":"Am Ostbahnhof 32",
    "sg:city":"Ratingen",
    "sg:phone":"+49 2102/844662",
    "sg:postcode":"40878",
    "sg:province":"Nordrhein-Westfalen",
    "wof:name":"H. Und W. Gunkel",
    "wof:placetype":"venue"
},
  "geometry": {"coordinates":[6.861502,51.293064],"type":"Point"}
}