{
  "type": "Feature",
  "properties": {
    "iso:country":"DE",
    "sg:address":"Merkurstr. 9-11",
    "sg:city":"Landstuhl",
    "sg:phone":"+49 6371/937007",
    "sg:postcode":"66849",
    "sg:province":"Rheinland-Pfalz",
    "wof:name":"Broadway Entertainment Gmbh & Co. Kg",
    "wof:placetype":"venue"
},
  "geometry": {"coordinates":[7.57218,49.411766],"type":"Point"}
}