{
  "type": "Feature",
  "properties": {
    "iso:country":"DE",
    "sg:address":"Burgm\u00fcllerstr. 51",
    "sg:city":"D\u00fcsseldorf",
    "sg:phone":"+49 211/662048",
    "sg:postcode":"40235",
    "sg:province":"Nordrhein-Westfalen",
    "wof:name":"Ruhland Immobilien Gmbh",
    "wof:placetype":"venue"
},
  "geometry": {"coordinates":[6.8259239197,51.2424545288],"type":"Point"}
}