{
  "type": "Feature",
  "properties": {
    "iso:country":"DE",
    "sg:address":"Schwerinshorst 1",
    "sg:city":"Spantekow",
    "sg:phone":"+49 39727/20207",
    "sg:postcode":"17392",
    "sg:province":"Mecklenburg-Vorpommern",
    "wof:name":"Forstbaumschule Kraatz Priebe Gbr Gmbh",
    "wof:placetype":"venue"
},
  "geometry": {"coordinates":[13.521009,53.778744],"type":"Point"}
}