{
  "type": "Feature",
  "properties": {
    "iso:country":"DE",
    "sg:address":"Neuenteich 20",
    "sg:city":"Wuppertal",
    "sg:phone":"+49 202/496190",
    "sg:postcode":"42107",
    "sg:province":"Nordrhein-Westfalen",
    "wof:name":"D. Und Hiltrud Gille Steuerberater",
    "wof:placetype":"venue"
},
  "geometry": {"coordinates":[7.1557579041,51.2632141113],"type":"Point"}
}