{
  "type": "Feature",
  "properties": {
    "iso:country":"DE",
    "sg:address":"Schmiedestrang 1",
    "sg:city":"Verl",
    "sg:phone":"+49 9232/6010",
    "sg:postcode":"33415",
    "sg:province":"Nordrhein-Westfalen",
    "wof:name":"Hellbrecht Unternehmerische Planungsmethoden Ag",
    "wof:placetype":"venue"
},
  "geometry": {"coordinates":[12.0154256821,50.0149536133],"type":"Point"}
}