{
  "type": "Feature",
  "properties": {
    "iso:country":"DE",
    "sg:address":"Im Wendischen Dorfe 1-3",
    "sg:city":"L\u00fcneburg",
    "sg:phone":"+49 4131/380888",
    "sg:postcode":"21335",
    "sg:province":"Niedersachsen",
    "wof:name":"Baby-centrum Anker Gmbh",
    "wof:placetype":"venue"
},
  "geometry": {"coordinates":[10.4119052887,53.252407074],"type":"Point"}
}