{
  "type": "Feature",
  "properties": {
    "iso:country":"DE",
    "sg:address":"Neuenhauser Str. 83",
    "sg:city":"Ringe",
    "sg:phone":"+49 5944/93930",
    "sg:postcode":"49824",
    "sg:province":"Niedersachsen",
    "wof:name":"B\u00fcter Bauunternehmen Beteiligungs- Und",
    "wof:placetype":"venue"
},
  "geometry": {"coordinates":[6.935703,52.594254],"type":"Point"}
}