{
  "type": "Feature",
  "properties": {
    "iso:country":"DE",
    "sg:address":"Industriestr. 9",
    "sg:city":"Burscheid",
    "sg:postcode":"51399",
    "sg:province":"Nordrhein-Westfalen",
    "wof:name":"Fietz Verwaltung Gmbh",
    "wof:placetype":"venue"
},
  "geometry": {"coordinates":[7.0977268219,51.0881538391],"type":"Point"}
}