{
  "type": "Feature",
  "properties": {
    "iso:country":"DE",
    "sg:address":"Gadderbaumer Str. 14",
    "sg:city":"Bielefeld",
    "sg:phone":"+49 521/967820",
    "sg:postcode":"33602",
    "sg:province":"Nordrhein-Westfalen",
    "wof:name":"Bodo Thielking Patentanwalt",
    "wof:placetype":"venue"
},
  "geometry": {"coordinates":[8.5237026215,52.0161819458],"type":"Point"}
}