{
  "type": "Feature",
  "properties": {
    "iso:country":"DE",
    "sg:address":"Schillerstr. 79",
    "sg:city":"Cottbus",
    "sg:postcode":"03046",
    "sg:province":"Brandenburg",
    "wof:name":"Fg-bausatzhaus Cottbus Gmbh",
    "wof:placetype":"venue"
},
  "geometry": {"coordinates":[14.3238573074,51.7609138489],"type":"Point"}
}