{
  "type": "Feature",
  "properties": {
    "iso:country":"DE",
    "sg:address":"Im Gr\u00fcn 2",
    "sg:city":"Karlsruhe",
    "sg:phone":"+49 721/887137",
    "sg:postcode":"76199",
    "sg:province":"Baden-W\u00fcrttemberg",
    "wof:name":"Peter Hochmuth",
    "wof:placetype":"venue"
},
  "geometry": {"coordinates":[8.4071760178,48.9760856628],"type":"Point"}
}