{
  "type": "Feature",
  "properties": {
    "iso:country":"DE",
    "sg:address":"Kemnader Str. 40a",
    "sg:city":"Bochum",
    "sg:postcode":"44795",
    "sg:province":"Nordrhein-Westfalen",
    "wof:name":"M\u00fcnzen Sievert",
    "wof:placetype":"venue"
},
  "geometry": {"coordinates":[7.215089798,51.439868927],"type":"Point"}
}