{
  "type": "Feature",
  "properties": {
    "iso:country":"DE",
    "sg:address":"B\u00f6nnier Str. 32",
    "sg:city":"Bockenem",
    "sg:phone":"+49 5067/6463",
    "sg:postcode":"31167",
    "sg:province":"Niedersachsen",
    "wof:name":"Hotel Ambergau",
    "wof:placetype":"venue"
},
  "geometry": {"coordinates":[10.1260375977,52.0094795227],"type":"Point"}
}