{
  "type": "Feature",
  "properties": {
    "iso:country":"DE",
    "sg:address":"Fuchsgrube 4",
    "sg:city":"Traunstein",
    "sg:phone":"+49 861/166770",
    "sg:postcode":"83278",
    "sg:province":"Bayern",
    "wof:name":"Municom Bauelemente F\u00fcr Die Nachrichtentechnik",
    "wof:placetype":"venue"
},
  "geometry": {"coordinates":[12.6492795944,47.8691596985],"type":"Point"}
}