{
  "type": "Feature",
  "properties": {
    "iso:country":"DE",
    "sg:address":"Maria-Theresia-Str. 11",
    "sg:city":"M\u00fcnchen",
    "sg:phone":"+49 89/4152770",
    "sg:postcode":"81675",
    "sg:province":"Bayern",
    "wof:name":"Stern Magazin",
    "wof:placetype":"venue"
},
  "geometry": {"coordinates":[11.5983610153,48.1392784119],"type":"Point"}
}