{
  "type": "Feature",
  "properties": {
    "iso:country":"DE",
    "sg:address":"Hauptstr. 2",
    "sg:city":"R\u00fcmmelsheim",
    "sg:phone":"+49 6721/43027",
    "sg:postcode":"55452",
    "sg:province":"Rheinland-Pfalz",
    "wof:name":"Wein- Und Kulturreisen Gmbh",
    "wof:placetype":"venue"
},
  "geometry": {"coordinates":[7.8598351479,49.933303833],"type":"Point"}
}