{
  "type": "Feature",
  "properties": {
    "iso:country":"DE",
    "sg:address":"Langgasse 28",
    "sg:city":"Karlstadt",
    "sg:phone":"+49 9353/4891",
    "sg:postcode":"97753",
    "sg:province":"Bayern",
    "wof:name":"Hans-joachim Schubert",
    "wof:placetype":"venue"
},
  "geometry": {"coordinates":[9.766374,49.960464],"type":"Point"}
}