{
  "type": "Feature",
  "properties": {
    "iso:country":"DE",
    "sg:address":"Im Gr\u00fcner 7",
    "sg:city":"Bretten",
    "sg:postcode":"75015",
    "sg:province":"Baden-W\u00fcrttemberg",
    "wof:name":"Alfred Aust",
    "wof:placetype":"venue"
},
  "geometry": {"coordinates":[8.716178,49.02969],"type":"Point"}
}