{
  "type": "Feature",
  "properties": {
    "iso:country":"DE",
    "sg:address":"Hauptstr. 45-1",
    "sg:city":"Weilheim",
    "sg:phone":"+49 7023/908770",
    "sg:postcode":"73235",
    "sg:province":"Baden-W\u00fcrttemberg",
    "wof:name":"Stefan Gro\u00dfmann",
    "wof:placetype":"venue"
},
  "geometry": {"coordinates":[9.5382709503,48.5885276794],"type":"Point"}
}