{
  "type": "Feature",
  "properties": {
    "iso:country":"DE",
    "sg:address":"Saerbecker Str. 17",
    "sg:city":"Greven",
    "sg:phone":"+49 2571/6741",
    "sg:postcode":"48268",
    "sg:province":"Nordrhein-Westfalen",
    "wof:name":"Wilhelm Strotmann",
    "wof:placetype":"venue"
},
  "geometry": {"coordinates":[7.611226,52.097149],"type":"Point"}
}