{
  "type": "Feature",
  "properties": {
    "iso:country":"DE",
    "sg:address":"Neustadt 48",
    "sg:city":"Celle",
    "sg:phone":"+49 5141/41326",
    "sg:postcode":"29225",
    "sg:province":"Niedersachsen",
    "wof:name":"Monika Schreier",
    "wof:placetype":"venue"
},
  "geometry": {"coordinates":[10.054276,52.620243],"type":"Point"}
}