{
  "type": "Feature",
  "properties": {
    "iso:country":"DE",
    "sg:address":"An der Kirche 5",
    "sg:city":"Legden",
    "sg:phone":"+49 2566/1612",
    "sg:postcode":"48739",
    "sg:province":"Nordrhein-Westfalen",
    "wof:name":"Kath. Pfarramt St. Margareta",
    "wof:placetype":"venue"
},
  "geometry": {"coordinates":[7.1437039375,52.054145813],"type":"Point"}
}