{
  "type": "Feature",
  "properties": {
    "iso:country":"DE",
    "sg:address":"Im Raidental 4",
    "sg:city":"Albstadt",
    "sg:phone":"+49 7431/3328",
    "sg:postcode":"72458",
    "sg:province":"Baden-W\u00fcrttemberg",
    "wof:name":"Karl Miller",
    "wof:placetype":"venue"
},
  "geometry": {"coordinates":[9.0137357712,48.2164764404],"type":"Point"}
}