{
  "type": "Feature",
  "properties": {
    "iso:country":"DE",
    "sg:address":"Kiesweg 12",
    "sg:city":"Wertheim",
    "sg:phone":"+49 9342/85454",
    "sg:postcode":"97877",
    "sg:province":"Baden-W\u00fcrttemberg",
    "wof:name":"H. Rak",
    "wof:placetype":"venue"
},
  "geometry": {"coordinates":[9.4987010956,49.7857475281],"type":"Point"}
}