{
  "type": "Feature",
  "properties": {
    "iso:country":"DE",
    "sg:address":"Putbuser Str. 2",
    "sg:city":"Ostseebad Binz",
    "sg:phone":"+49 38393/32116",
    "sg:postcode":"18609",
    "sg:province":"Mecklenburg-Vorpommern",
    "wof:name":"Asia Chinarestaurant",
    "wof:placetype":"venue"
},
  "geometry": {"coordinates":[13.6133127213,54.3987846375],"type":"Point"}
}