{
  "type": "Feature",
  "properties": {
    "iso:country":"DE",
    "sg:address":"Andreas-Kratt-Str. 27",
    "sg:city":"Kehl",
    "sg:phone":"+49 7851/71443",
    "sg:postcode":"77694",
    "sg:province":"Baden-W\u00fcrttemberg",
    "wof:name":"Jakob Veid",
    "wof:placetype":"venue"
},
  "geometry": {"coordinates":[7.8705539703,48.5700302124],"type":"Point"}
}