{
  "type": "Feature",
  "properties": {
    "iso:country":"DE",
    "sg:address":"Victor-Slotosch-Str. 11",
    "sg:city":"Frankfurt",
    "sg:phone":"+49 6109/7380",
    "sg:postcode":"60388",
    "sg:province":"Hessen",
    "wof:name":"Ascom Deutschland Gmbh",
    "wof:placetype":"venue"
},
  "geometry": {"coordinates":[8.747575,50.14394],"type":"Point"}
}