{
  "type": "Feature",
  "properties": {
    "iso:country":"DE",
    "sg:address":"Darmst\u00e4dter Str. 59 a",
    "sg:city":"Michelstadt",
    "sg:phone":"+49 6061/72456",
    "sg:postcode":"64720",
    "sg:province":"Hessen",
    "wof:name":"Gerda Reubold",
    "wof:placetype":"venue"
},
  "geometry": {"coordinates":[8.992036,49.685383],"type":"Point"}
}