{
  "type": "Feature",
  "properties": {
    "iso:country":"DE",
    "sg:address":"Edelwei\u00dfstr. 3 B",
    "sg:city":"R\u00f6dermark",
    "sg:phone":"+49 6074/96751",
    "sg:postcode":"63322",
    "sg:province":"Hessen",
    "wof:name":"Ingo Eisenberger Rechtsanwalt",
    "wof:placetype":"venue"
},
  "geometry": {"coordinates":[8.8388824463,49.9653205872],"type":"Point"}
}