{
  "type": "Feature",
  "properties": {
    "iso:country":"DE",
    "sg:address":"Dionysiusstr. 6",
    "sg:city":"H\u00f6xter",
    "sg:phone":"+49 5271/7746",
    "sg:postcode":"37671",
    "sg:province":"Nordrhein-Westfalen",
    "wof:name":"Kath. Pfarramt St. Dionysius",
    "wof:placetype":"venue"
},
  "geometry": {"coordinates":[9.40184021,51.8210792542],"type":"Point"}
}