{
  "type": "Feature",
  "properties": {
    "iso:country":"DE",
    "sg:address":"Am Alten Kanal 9",
    "sg:city":"Bensdorf",
    "sg:phone":"+49 33839/283",
    "sg:postcode":"14789",
    "sg:province":"Brandenburg",
    "wof:name":"Drorotheenhof",
    "wof:placetype":"venue"
},
  "geometry": {"coordinates":[12.3740301132,52.4015846252],"type":"Point"}
}