{
  "type": "Feature",
  "properties": {
    "iso:country":"DE",
    "sg:address":"Nr. 44",
    "sg:city":"Barum",
    "sg:postcode":"29576",
    "sg:province":"Niedersachsen",
    "wof:name":"Gefl\u00fcgelhof Barum Siegfried Schwarz",
    "wof:placetype":"venue"
},
  "geometry": {"coordinates":[10.517058,53.052193],"type":"Point"}
}