{
  "type": "Feature",
  "properties": {
    "iso:country":"DE",
    "sg:address":"Alte Landstr. 23",
    "sg:city":"Engelskirchen",
    "sg:phone":"+49 2263/5596",
    "sg:postcode":"51766",
    "sg:province":"Nordrhein-Westfalen",
    "wof:name":"Helmut Diegel Architekt",
    "wof:placetype":"venue"
},
  "geometry": {"coordinates":[7.451288,51.00573],"type":"Point"}
}