{
  "type": "Feature",
  "properties": {
    "iso:country":"DE",
    "sg:address":"Mittenwalder Str. 36",
    "sg:city":"Garmisch-Partenkirchen",
    "sg:phone":"+49 8821/2389",
    "sg:postcode":"82467",
    "sg:province":"Bayern",
    "wof:name":"Heinz Kiste",
    "wof:placetype":"venue"
},
  "geometry": {"coordinates":[11.118036,47.485886],"type":"Point"}
}