{
  "type": "Feature",
  "properties": {
    "iso:country":"DE",
    "sg:address":"K\u00f6nigstr. 23-25",
    "sg:city":"G\u00fctersloh",
    "sg:phone":"+49 5241/8620",
    "sg:postcode":"33330",
    "sg:province":"Nordrhein-Westfalen",
    "wof:name":"Red. Zeitschrift F\u00fcr Gottesdienst Und Predigt",
    "wof:placetype":"venue"
},
  "geometry": {"coordinates":[8.3750934601,51.9069900513],"type":"Point"}
}