{
  "type": "Feature",
  "properties": {
    "iso:country":"DE",
    "sg:address":"Industrieweg 12",
    "sg:city":"Mittweida",
    "sg:phone":"+49 4937/2794540",
    "sg:postcode":"09648",
    "sg:province":"Sachsen",
    "wof:name":"Erodier- & Galvanotech Gmbh",
    "wof:placetype":"venue"
},
  "geometry": {"coordinates":[12.992515,50.978165],"type":"Point"}
}