{
  "type": "Feature",
  "properties": {
    "iso:country":"DE",
    "sg:address":"Sonnenstr. 9",
    "sg:city":"Garmisch-Partenkirchen",
    "sg:phone":"+49 8821/73460",
    "sg:postcode":"82467",
    "sg:province":"Bayern",
    "wof:name":"Thomas Saller",
    "wof:placetype":"venue"
},
  "geometry": {"coordinates":[11.0844573975,47.493057251],"type":"Point"}
}