{
  "type": "Feature",
  "properties": {
    "iso:country":"DE",
    "sg:address":"Schwarze \u00c4cker 73",
    "sg:city":"K\u00fcrnach",
    "sg:phone":"+49 9367/8820",
    "sg:postcode":"97273",
    "sg:province":"Bayern",
    "wof:name":"G\u00fcnther Und Brigitte Rohracker Steuerberater",
    "wof:placetype":"venue"
},
  "geometry": {"coordinates":[10.043844223,49.8427696228],"type":"Point"}
}