{
  "type": "Feature",
  "properties": {
    "iso:country":"DE",
    "sg:address":"Schlo\u00dfbleiche 40",
    "sg:city":"Wuppertal",
    "sg:phone":"+49 202/444744",
    "sg:postcode":"42103",
    "sg:province":"Nordrhein-Westfalen",
    "wof:name":"M\u00f6bius Gmbh",
    "wof:placetype":"venue"
},
  "geometry": {"coordinates":[7.144939,51.255989],"type":"Point"}
}