{
  "type": "Feature",
  "properties": {
    "iso:country":"DE",
    "sg:address":"Timmerlahstr. 110",
    "sg:city":"Braunschweig",
    "sg:phone":"+49 531/864833",
    "sg:postcode":"38120",
    "sg:province":"Niedersachsen",
    "wof:name":"Alte Dorfschmiede",
    "wof:placetype":"venue"
},
  "geometry": {"coordinates":[10.4536933899,52.2376556396],"type":"Point"}
}