{
  "type": "Feature",
  "properties": {
    "iso:country":"DE",
    "sg:address":"Lollfu\u00df 88",
    "sg:city":"Schleswig",
    "sg:phone":"+49 4621/290371",
    "sg:postcode":"24837",
    "sg:province":"Schleswig-Holstein",
    "wof:name":"Victoria Versicherung",
    "wof:placetype":"venue"
},
  "geometry": {"coordinates":[9.5496473312,54.5134429932],"type":"Point"}
}