{
  "type": "Feature",
  "properties": {
    "iso:country":"DE",
    "sg:address":"Postfach 58:: 06471 Quedlinburg:: Germany.^^Turnstr 8::",
    "sg:city":"Quedlinburg",
    "sg:phone":"+49 3946/9050",
    "sg:postcode":"06484",
    "sg:province":"Sachsen-Anhalt",
    "wof:name":"Kreissparkasse Quedlinburg",
    "wof:placetype":"venue"
},
  "geometry": {"coordinates":[11.203697,51.831375],"type":"Point"}
}