{
  "type": "Feature",
  "properties": {
    "iso:country":"DE",
    "sg:address":"Oedenberger Str. 41",
    "sg:city":"N\u00fcrnberg",
    "sg:phone":"+49 911/435800",
    "sg:postcode":"90491",
    "sg:province":"Bayern",
    "wof:name":"Deutsches Sozialwerk E. V.",
    "wof:placetype":"venue"
},
  "geometry": {"coordinates":[11.1084165573,49.4665222168],"type":"Point"}
}