{
  "type": "Feature",
  "properties": {
    "iso:country":"DE",
    "sg:address":"Marsstr. 1",
    "sg:city":"Dachau",
    "sg:phone":"+49 8131/87581",
    "sg:postcode":"85221",
    "sg:province":"Bayern",
    "wof:name":"C. Czernohorsky",
    "wof:placetype":"venue"
},
  "geometry": {"coordinates":[11.4459924698,48.2656211853],"type":"Point"}
}