{
  "type": "Feature",
  "properties": {
    "iso:country":"DE",
    "sg:address":"Lotjeweg 9",
    "sg:city":"Bremerhaven",
    "sg:phone":"+49 471/982010",
    "sg:postcode":"27578",
    "sg:province":"Bremen",
    "wof:name":"August Reiners Bauunternehmung Gmbh",
    "wof:placetype":"venue"
},
  "geometry": {"coordinates":[8.601877,53.571781],"type":"Point"}
}