{
  "type": "Feature",
  "properties": {
    "iso:country":"DE",
    "sg:address":"Kaiserstr. 34",
    "sg:city":"Siegburg",
    "sg:phone":"+49 2241/63522",
    "sg:postcode":"53721",
    "sg:province":"Nordrhein-Westfalen",
    "wof:name":"Neue Apotheke Apothekerin Martina M\u00fcllenholz E. K.",
    "wof:placetype":"venue"
},
  "geometry": {"coordinates":[7.207999,50.798721],"type":"Point"}
}