{
  "type": "Feature",
  "properties": {
    "iso:country":"DE",
    "sg:address":"Mainzer Str. 1",
    "sg:city":"Saarbr\u00fccken",
    "sg:phone":"+49 681/31426",
    "sg:postcode":"66111",
    "sg:province":"Saarland",
    "wof:name":"Synop",
    "wof:placetype":"venue"
},
  "geometry": {"coordinates":[6.9987502098,49.2317352295],"type":"Point"}
}