{
  "type": "Feature",
  "properties": {
    "iso:country":"DE",
    "sg:address":"Oberpleichfelder Str.",
    "sg:city":"Bergtheim",
    "sg:phone":"+49 9367/3924",
    "sg:postcode":"97241",
    "sg:province":"Bayern",
    "wof:name":"Vereinsgastst\u00e4tte Sv Bergtheim",
    "wof:placetype":"venue"
},
  "geometry": {"coordinates":[10.0675258636,49.895942688],"type":"Point"}
}