{
  "type": "Feature",
  "properties": {
    "iso:country":"DE",
    "sg:address":"Ahornweg 3",
    "sg:city":"Fulda",
    "sg:phone":"+49 661/602771",
    "sg:postcode":"36037",
    "sg:province":"Hessen",
    "wof:name":"Hans Rudolf Knips Ingenieur",
    "wof:placetype":"venue"
},
  "geometry": {"coordinates":[9.6928987503,50.5570793152],"type":"Point"}
}