{
  "type": "Feature",
  "properties": {
    "iso:country":"DE",
    "sg:address":"Danneckerstr. 8-9",
    "sg:city":"Ludwigsburg",
    "sg:phone":"+49 7141/923811",
    "sg:postcode":"71636",
    "sg:province":"Baden-W\u00fcrttemberg",
    "wof:name":"Hanser",
    "wof:placetype":"venue"
},
  "geometry": {"coordinates":[9.179579,48.89896],"type":"Point"}
}