{
  "type": "Feature",
  "properties": {
    "iso:country":"DE",
    "sg:address":"Neudorfstr. 45",
    "sg:city":"Mannheim",
    "sg:phone":"+49 621/472645",
    "sg:postcode":"68229",
    "sg:province":"Baden-W\u00fcrttemberg",
    "wof:name":"Egon Gei\u00dfen",
    "wof:placetype":"venue"
},
  "geometry": {"coordinates":[8.5767173767,49.4377746582],"type":"Point"}
}