{
  "type": "Feature",
  "properties": {
    "iso:country":"DE",
    "sg:address":"Fahrradstr. 11",
    "sg:city":"N\u00fcrnberg",
    "sg:phone":"+49 911/9397643",
    "sg:postcode":"90429",
    "sg:province":"Bayern",
    "wof:name":"Eurokom Media Ohg",
    "wof:placetype":"venue"
},
  "geometry": {"coordinates":[11.0404071808,49.4569396973],"type":"Point"}
}