{
  "type": "Feature",
  "properties": {
    "iso:country":"DE",
    "sg:address":"Bahnhofstr. 25",
    "sg:city":"Mettlach",
    "sg:phone":"+49 6864/682",
    "sg:postcode":"66693",
    "sg:province":"Saarland",
    "wof:name":"Thomas Wolff",
    "wof:placetype":"venue"
},
  "geometry": {"coordinates":[6.5981001854,49.4941596985],"type":"Point"}
}