{
  "type": "Feature",
  "properties": {
    "iso:country":"DE",
    "sg:address":"Br\u00fcderstr. 62",
    "sg:city":"Remscheid",
    "sg:phone":"+49 2191/23048",
    "sg:postcode":"42853",
    "sg:province":"Nordrhein-Westfalen",
    "wof:name":"Jago Verm\u00f6gensverwaltung Gmbh",
    "wof:placetype":"venue"
},
  "geometry": {"coordinates":[7.180574,51.180801],"type":"Point"}
}