{
  "type": "Feature",
  "properties": {
    "iso:country":"DE",
    "sg:address":"Flurstr. 18",
    "sg:city":"Bodolz",
    "sg:phone":"+49 8382/23300",
    "sg:postcode":"88131",
    "sg:province":"Bayern",
    "wof:name":"E. Schenk",
    "wof:placetype":"venue"
},
  "geometry": {"coordinates":[9.661258,47.567486],"type":"Point"}
}