{
  "type": "Feature",
  "properties": {
    "iso:country":"DE",
    "sg:address":"Werner-von-Siemens-Str 29",
    "sg:city":"Heusenstamm",
    "sg:phone":"+49 6104/93430",
    "sg:postcode":"63150",
    "sg:province":"Hessen",
    "wof:name":"Wilhelm & Adam Werbe- Und Verlagsdruck Gmbh",
    "wof:placetype":"venue"
},
  "geometry": {"coordinates":[8.8022975922,50.0471038818],"type":"Point"}
}