{
  "type": "Feature",
  "properties": {
    "iso:country":"DE",
    "sg:address":"Kleppingstr. 28",
    "sg:city":"Dortmund",
    "sg:phone":"+49 231/571155",
    "sg:postcode":"44135",
    "sg:province":"Nordrhein-Westfalen",
    "wof:name":"Elke Otto",
    "wof:placetype":"venue"
},
  "geometry": {"coordinates":[7.468516,51.51096],"type":"Point"}
}