{
  "type": "Feature",
  "properties": {
    "iso:country":"DE",
    "sg:address":"Auf der Bleiche 2a",
    "sg:city":"Troisdorf",
    "sg:phone":"+49 228/454595",
    "sg:postcode":"53844",
    "sg:province":"Nordrhein-Westfalen",
    "wof:name":"Thomas Heil",
    "wof:placetype":"venue"
},
  "geometry": {"coordinates":[7.0980658531,50.7737617493],"type":"Point"}
}