{
  "type": "Feature",
  "properties": {
    "iso:country":"DE",
    "sg:address":"Weinbergstr. 11",
    "sg:city":"Neustadt",
    "sg:phone":"+49 9568/86352",
    "sg:postcode":"96465",
    "sg:province":"Bayern",
    "wof:name":"Irh Designbau Gmbh",
    "wof:placetype":"venue"
},
  "geometry": {"coordinates":[11.121737,50.325062],"type":"Point"}
}