{
  "type": "Feature",
  "properties": {
    "iso:country":"DE",
    "sg:address":"Harle 59",
    "sg:city":"Coesfeld",
    "sg:phone":"+49 2541/72973",
    "sg:postcode":"48653",
    "sg:province":"Nordrhein-Westfalen",
    "wof:name":"J\u00fcrgen Entrup",
    "wof:placetype":"venue"
},
  "geometry": {"coordinates":[7.219903,51.935558],"type":"Point"}
}