{
  "type": "Feature",
  "properties": {
    "iso:country":"DE",
    "sg:address":"Schlo\u00dfstr. 4a",
    "sg:city":"Fensterbach",
    "sg:phone":"+49 9438/1211",
    "sg:postcode":"92269",
    "sg:province":"Bayern",
    "wof:name":"S. Blessing",
    "wof:placetype":"venue"
},
  "geometry": {"coordinates":[12.042355,49.411694],"type":"Point"}
}