{
  "type": "Feature",
  "properties": {
    "iso:country":"DE",
    "sg:address":"Bautzner Strasse 45-47",
    "sg:city":"Dresden",
    "sg:phone":"+49 4969/981904",
    "sg:postcode":"01099",
    "sg:province":"Sachsen",
    "wof:name":"Touristik R.e.p.o.r.t.",
    "wof:placetype":"venue"
},
  "geometry": {"coordinates":[8.7841997147,50.0852813721],"type":"Point"}
}