{
  "type": "Feature",
  "properties": {
    "iso:country":"DE",
    "sg:address":"Linnerheide 7",
    "sg:city":"Bad Essen",
    "sg:phone":"+49 5472/7901",
    "sg:postcode":"49152",
    "sg:province":"Niedersachsen",
    "wof:name":"R. W. Schoster",
    "wof:placetype":"venue"
},
  "geometry": {"coordinates":[8.404873,52.28698],"type":"Point"}
}