{
  "type": "Feature",
  "properties": {
    "iso:country":"DE",
    "sg:address":"Hauptstr. 17",
    "sg:city":"Offenburg",
    "sg:phone":"+49 781/71698",
    "sg:postcode":"77652",
    "sg:province":"Baden-W\u00fcrttemberg",
    "wof:name":"W. Bl\u00e4si",
    "wof:placetype":"venue"
},
  "geometry": {"coordinates":[7.944141,48.473358],"type":"Point"}
}