{
  "type": "Feature",
  "properties": {
    "iso:country":"DE",
    "sg:address":"Kurze Str. 2",
    "sg:city":"Reichenbach",
    "sg:phone":"+49 3765/21103",
    "sg:postcode":"08468",
    "sg:province":"Sachsen",
    "wof:name":"R Und R Bauagentur Gmbh",
    "wof:placetype":"venue"
},
  "geometry": {"coordinates":[10.1877002716,48.8757591248],"type":"Point"}
}