{
  "type": "Feature",
  "properties": {
    "iso:country":"DE",
    "sg:address":"Loschwitzer Str. 41",
    "sg:city":"Dresden",
    "sg:phone":"+49 351/3105468",
    "sg:postcode":"01309",
    "sg:province":"Sachsen",
    "wof:name":"I. Scharf",
    "wof:placetype":"venue"
},
  "geometry": {"coordinates":[13.8005151749,51.0528755188],"type":"Point"}
}