{
  "type": "Feature",
  "properties": {
    "iso:country":"DE",
    "sg:address":"Hannoversche Str. 149",
    "sg:city":"Hannover",
    "sg:phone":"+49 511/5609990",
    "sg:postcode":"30627",
    "sg:province":"Niedersachsen",
    "wof:name":"Teamworks Communikations Systems Ges. F\u00fcr Vernetzte",
    "wof:placetype":"venue"
},
  "geometry": {"coordinates":[9.8255310059,52.3839797974],"type":"Point"}
}