{
  "type": "Feature",
  "properties": {
    "iso:country":"DE",
    "sg:city":"Butzbach",
    "sg:postcode":"35510",
    "sg:province":"Hessen",
    "wof:name":"Autohaus Rover Gmbh",
    "wof:placetype":"venue"
},
  "geometry": {"coordinates":[8.671438,50.435814],"type":"Point"}
}