{
  "type": "Feature",
  "properties": {
    "iso:country":"DE",
    "sg:address":"Nordstr. 52",
    "sg:city":"W\u00fcrselen",
    "sg:phone":"+49 2405/2022",
    "sg:postcode":"52146",
    "sg:province":"Nordrhein-Westfalen",
    "wof:name":"Sobala",
    "wof:placetype":"venue"
},
  "geometry": {"coordinates":[6.13648,50.825497],"type":"Point"}
}