{
  "type": "Feature",
  "properties": {
    "iso:country":"DE",
    "sg:address":"Mainzer Landstr. 59",
    "sg:city":"Gro\u00df-Gerau",
    "sg:phone":"+49 6152/59414",
    "sg:postcode":"64521",
    "sg:province":"Hessen",
    "wof:name":"Willi Frankenberger",
    "wof:placetype":"venue"
},
  "geometry": {"coordinates":[8.48023,49.881332],"type":"Point"}
}