{
  "type": "Feature",
  "properties": {
    "iso:country":"DE",
    "sg:address":"Hauptstr. 5",
    "sg:city":"Hoppegarten b M\u00fcnchebrg",
    "sg:postcode":"15345",
    "sg:province":"Brandenburg",
    "wof:name":"M. Pittelkow",
    "wof:placetype":"venue"
},
  "geometry": {"coordinates":[13.7256040573,52.5652999878],"type":"Point"}
}