{
  "type": "Feature",
  "properties": {
    "iso:country":"DE",
    "sg:address":"Reichpietschstr. 23",
    "sg:city":"Leipzig",
    "sg:postcode":"04317",
    "sg:province":"Sachsen",
    "wof:name":"Ingenieurb\u00fcro F\u00fcr Gefahren",
    "wof:placetype":"venue"
},
  "geometry": {"coordinates":[12.3985824585,51.3352165222],"type":"Point"}
}