{
  "type": "Feature",
  "properties": {
    "iso:country":"DE",
    "sg:address":"Bornaische Str. 45",
    "sg:city":"Markkleeberg",
    "sg:phone":"+49 341/3380276",
    "sg:postcode":"04416",
    "sg:province":"Sachsen",
    "wof:name":"F\u00fcchsel Transport Gmbh",
    "wof:placetype":"venue"
},
  "geometry": {"coordinates":[12.3816051483,51.2727088928],"type":"Point"}
}