{
  "type": "Feature",
  "properties": {
    "iso:country":"DE",
    "sg:address":"Holzweilerstr. 17",
    "sg:city":"Titz",
    "sg:phone":"+49 2164/48828",
    "sg:postcode":"52445",
    "sg:province":"Nordrhein-Westfalen",
    "wof:name":"R. Ramadan",
    "wof:placetype":"venue"
},
  "geometry": {"coordinates":[6.4489150047,51.0350761414],"type":"Point"}
}