{
  "type": "Feature",
  "properties": {
    "iso:country":"DE",
    "sg:address":"G\u00fcterbahnhofstr. 2 b",
    "sg:city":"Lichtenstein",
    "sg:phone":"+49 37204/2881",
    "sg:postcode":"09350",
    "sg:province":"Sachsen",
    "wof:name":"Kommunaler Zweckverband Stadtbeleuchtung",
    "wof:placetype":"venue"
},
  "geometry": {"coordinates":[12.625399,50.756748],"type":"Point"}
}