{
  "type": "Feature",
  "properties": {
    "iso:country":"DE",
    "sg:address":"Hainstr. 14",
    "sg:city":"Erlensee",
    "sg:phone":"+49 6183/3800",
    "sg:postcode":"63526",
    "sg:province":"Hessen",
    "wof:name":"Zur Tankstelle",
    "wof:placetype":"venue"
},
  "geometry": {"coordinates":[8.9847164154,50.1581230164],"type":"Point"}
}