{
  "type": "Feature",
  "properties": {
    "iso:country":"DE",
    "sg:address":"Wedeler Weg 184",
    "sg:city":"Pinneberg",
    "sg:phone":"+49 4101/68834",
    "sg:postcode":"25421",
    "sg:province":"Schleswig-Holstein",
    "wof:name":"Gustav Schulz",
    "wof:placetype":"venue"
},
  "geometry": {"coordinates":[9.7724103928,53.6458358765],"type":"Point"}
}