{
  "type": "Feature",
  "properties": {
    "iso:country":"DE",
    "sg:address":"Gustav-Poensgen-Str 25",
    "sg:city":"D\u00fcsseldorf",
    "sg:phone":"+49 211/5141909",
    "sg:postcode":"40215",
    "sg:province":"Nordrhein-Westfalen",
    "wof:name":"Klaus Federl",
    "wof:placetype":"venue"
},
  "geometry": {"coordinates":[6.789495,51.215073],"type":"Point"}
}