{
  "type": "Feature",
  "properties": {
    "iso:country":"DE",
    "sg:address":"Holster Str. 29",
    "sg:city":"Melle",
    "sg:phone":"+49 5422/8786",
    "sg:postcode":"49324",
    "sg:province":"Niedersachsen",
    "wof:name":"Yvonne Fritsch Innenarchitektin",
    "wof:placetype":"venue"
},
  "geometry": {"coordinates":[8.291026,52.253216],"type":"Point"}
}