{
  "type": "Feature",
  "properties": {
    "iso:country":"DE",
    "sg:address":"Obstmarschenweg 303",
    "sg:city":"Stade",
    "sg:phone":"+49 4146/5496",
    "sg:postcode":"21683",
    "sg:province":"Niedersachsen",
    "wof:name":"F. Nagel",
    "wof:placetype":"venue"
},
  "geometry": {"coordinates":[9.4789800644,53.6374816895],"type":"Point"}
}