{
  "type": "Feature",
  "properties": {
    "iso:country":"DE",
    "sg:address":"Rie\u00dferseestr. 19",
    "sg:city":"Garmisch-Partenkirchen",
    "sg:phone":"+49 8821/1350",
    "sg:postcode":"82467",
    "sg:province":"Bayern",
    "wof:name":"Mws Verwaltungs-vermittlungs- Und Beteiligungs Gmbh",
    "wof:placetype":"venue"
},
  "geometry": {"coordinates":[11.07757,47.488483],"type":"Point"}
}