{
  "type": "Feature",
  "properties": {
    "iso:country":"DE",
    "sg:address":"Elgendorfer Str. 2",
    "sg:city":"Dernbach",
    "sg:phone":"+49 2602/7666",
    "sg:postcode":"56428",
    "sg:province":"Rheinland-Pfalz",
    "wof:name":"Gerhard Wittayer",
    "wof:placetype":"venue"
},
  "geometry": {"coordinates":[7.792001,50.455372],"type":"Point"}
}