{
  "type": "Feature",
  "properties": {
    "iso:country":"DE",
    "sg:address":"Berliner Str. 6",
    "sg:city":"Schmelz",
    "sg:phone":"+49 6887/7785",
    "sg:postcode":"66839",
    "sg:province":"Saarland",
    "wof:name":"Kfz-zulassungs- Versicherungs- Und Schilderdienst Leidinger",
    "wof:placetype":"venue"
},
  "geometry": {"coordinates":[6.8446941376,49.4246673584],"type":"Point"}
}