{
  "type": "Feature",
  "properties": {
    "iso:country":"DE",
    "sg:address":"Karl-Marx-Str 32",
    "sg:city":"Immelborn",
    "sg:phone":"+49 3695/555200",
    "sg:postcode":"36433",
    "sg:province":"Th\u00fcringen",
    "wof:name":"Bauer & Malsch Gmbh",
    "wof:placetype":"venue"
},
  "geometry": {"coordinates":[10.279284,50.792511],"type":"Point"}
}