{
  "type": "Feature",
  "properties": {
    "iso:country":"DE",
    "sg:address":"Mainzer Str. 21",
    "sg:city":"Bitburg",
    "sg:phone":"+49 6561/3950",
    "sg:postcode":"54634",
    "sg:province":"Rheinland-Pfalz",
    "wof:name":"Hotel Turmann",
    "wof:placetype":"venue"
},
  "geometry": {"coordinates":[6.5720691681,49.9986991882],"type":"Point"}
}