{
  "type": "Feature",
  "properties": {
    "iso:country":"DE",
    "sg:address":"Tuttlinger Str. 16",
    "sg:city":"Balgheim",
    "sg:phone":"+49 7424/94970",
    "sg:postcode":"78582",
    "sg:province":"Baden-W\u00fcrttemberg",
    "wof:name":"Psg Presse- Und Verteilservice Baden-w\u00fcrttemberg Gmbh",
    "wof:placetype":"venue"
},
  "geometry": {"coordinates":[8.7638530731,48.0644569397],"type":"Point"}
}