{
  "type": "Feature",
  "properties": {
    "iso:country":"DE",
    "sg:address":"Hemminger Str. 26",
    "sg:city":"Ditzingen",
    "sg:phone":"+49 7152/565670",
    "sg:postcode":"71254",
    "sg:province":"Baden-W\u00fcrttemberg",
    "wof:name":"Gastst\u00e4tte Brauerei",
    "wof:placetype":"venue"
},
  "geometry": {"coordinates":[8.9962692261,48.854927063],"type":"Point"}
}