{
  "type": "Feature",
  "properties": {
    "iso:country":"DE",
    "sg:address":"Kallenfelser Str. 109",
    "sg:city":"Kirn",
    "sg:phone":"+49 6752/2423",
    "sg:postcode":"55606",
    "sg:province":"Rheinland-Pfalz",
    "wof:name":"K. Muser",
    "wof:placetype":"venue"
},
  "geometry": {"coordinates":[7.43803,49.796738],"type":"Point"}
}