{
  "type": "Feature",
  "properties": {
    "iso:country":"DE",
    "sg:address":"Sterntaler 8",
    "sg:city":"Salzgitter",
    "sg:phone":"+49 5341/12838",
    "sg:postcode":"38226",
    "sg:province":"Niedersachsen",
    "wof:name":"Josef Keller Ingenieur",
    "wof:placetype":"venue"
},
  "geometry": {"coordinates":[10.3140068054,52.1623268127],"type":"Point"}
}