{
  "type": "Feature",
  "properties": {
    "iso:country":"DE",
    "sg:address":"Buchener Str. 15",
    "sg:city":"Bad Mergentheim",
    "sg:postcode":"97980",
    "sg:province":"Baden-W\u00fcrttemberg",
    "wof:name":"Vetec Verpflegungstechnik Gmbh",
    "wof:placetype":"venue"
},
  "geometry": {"coordinates":[9.7605819702,49.492767334],"type":"Point"}
}