{
  "type": "Feature",
  "properties": {
    "iso:country":"DE",
    "sg:address":"Obertinsberger Str. 1",
    "sg:city":"L\u00fcdenscheid",
    "sg:phone":"+49 2351/83166",
    "sg:postcode":"58507",
    "sg:province":"Nordrhein-Westfalen",
    "wof:name":"Wilhelm Und M. Amigoni Med. B\u00e4der",
    "wof:placetype":"venue"
},
  "geometry": {"coordinates":[7.640718,51.221012],"type":"Point"}
}