{
  "type": "Feature",
  "properties": {
    "iso:country":"DE",
    "sg:address":"Schwarzenb\u00f6rner Str. 8",
    "sg:city":"Frielendorf",
    "sg:phone":"+49 6691/71322",
    "sg:postcode":"34621",
    "sg:province":"Hessen",
    "wof:name":"G\u00fcnter M\u00fchling",
    "wof:placetype":"venue"
},
  "geometry": {"coordinates":[9.298863,50.917706],"type":"Point"}
}