{
  "type": "Feature",
  "properties": {
    "iso:country":"DE",
    "sg:address":"Mozartstr. 30",
    "sg:city":"Maintal",
    "sg:phone":"+49 6181/497051",
    "sg:postcode":"63477",
    "sg:province":"Hessen",
    "wof:name":"Hotel-restaurant Mozart",
    "wof:placetype":"venue"
},
  "geometry": {"coordinates":[8.8377132416,50.1346359253],"type":"Point"}
}