{
  "type": "Feature",
  "properties": {
    "iso:country":"DE",
    "sg:address":"Alemannenstr. 10",
    "sg:city":"Dresden",
    "sg:phone":"+49 351/3103425",
    "sg:postcode":"01309",
    "sg:province":"Sachsen",
    "wof:name":"Johannes Hanschmann",
    "wof:placetype":"venue"
},
  "geometry": {"coordinates":[13.789889,51.052521],"type":"Point"}
}