{
  "type": "Feature",
  "properties": {
    "iso:country":"DE",
    "sg:address":"Hanaustr. 2",
    "sg:city":"Dreieich",
    "sg:phone":"+49 6103/86864",
    "sg:postcode":"63303",
    "sg:province":"Hessen",
    "wof:name":"Rosen-apotheke",
    "wof:placetype":"venue"
},
  "geometry": {"coordinates":[8.704343,50.001228],"type":"Point"}
}