{
  "type": "Feature",
  "properties": {
    "iso:country":"DE",
    "sg:address":"Rutesheimer Str. 22",
    "sg:city":"Stuttgart",
    "sg:phone":"+49 4971/113880",
    "sg:postcode":"70499",
    "sg:province":"Baden-W\u00fcrttemberg",
    "wof:name":"Otto Roth Gmbh & Co. Kg",
    "wof:placetype":"venue"
},
  "geometry": {"coordinates":[9.100177,48.82196],"type":"Point"}
}