{
  "type": "Feature",
  "properties": {
    "iso:country":"DE",
    "sg:address":"Winkhauser Str. 9",
    "sg:city":"L\u00fcdenscheid",
    "sg:phone":"+49 2351/39795",
    "sg:postcode":"58509",
    "sg:province":"Nordrhein-Westfalen",
    "wof:name":"M. Schneider Immobilienmakler",
    "wof:placetype":"venue"
},
  "geometry": {"coordinates":[7.621088028,51.2214164734],"type":"Point"}
}