{
  "type": "Feature",
  "properties": {
    "iso:country":"DE",
    "sg:address":"Baumschulenstr.71",
    "sg:city":"Berlin",
    "sg:phone":"+49 30",
    "sg:postcode":"12437",
    "sg:province":"Berlin",
    "wof:name":"Blumen Kernchen-lippert",
    "wof:placetype":"venue"
},
  "geometry": {"coordinates":[13.4836101532,52.4629478455],"type":"Point"}
}