{
  "type": "Feature",
  "properties": {
    "iso:country":"DE",
    "sg:address":"Geb\u00e4ude 28 Mensa",
    "sg:city":"Saarbr\u00fccken",
    "sg:phone":"+49 681/3022800",
    "sg:postcode":"66123",
    "sg:province":"Saarland",
    "wof:name":"Studentenwerk Im Saarland Ev",
    "wof:placetype":"venue"
},
  "geometry": {"coordinates":[7.016635,49.240444],"type":"Point"}
}