{
  "type": "Feature",
  "properties": {
    "iso:country":"DE",
    "sg:address":"Ringstr. 36",
    "sg:city":"Otzberg",
    "sg:phone":"+49 6162/72348",
    "sg:postcode":"64853",
    "sg:province":"Hessen",
    "wof:name":"Biohof Fritsch",
    "wof:placetype":"venue"
},
  "geometry": {"coordinates":[8.889056,49.850605],"type":"Point"}
}