{
  "type": "Feature",
  "properties": {
    "iso:country":"DE",
    "sg:address":"Breubergstr. 37",
    "sg:city":"Brensbach",
    "sg:phone":"+49 6161/2061",
    "sg:postcode":"64395",
    "sg:province":"Hessen",
    "wof:name":"Balu Mechanik Gmbh",
    "wof:placetype":"venue"
},
  "geometry": {"coordinates":[8.898754,49.777927],"type":"Point"}
}