{
  "type": "Feature",
  "properties": {
    "iso:country":"DE",
    "sg:address":"Bergstr. 33",
    "sg:city":"Steinheim",
    "sg:phone":"+49 5233/4183",
    "sg:postcode":"32839",
    "sg:province":"Nordrhein-Westfalen",
    "wof:name":"Ute Schmidt",
    "wof:placetype":"venue"
},
  "geometry": {"coordinates":[9.1058006287,51.8764381409],"type":"Point"}
}