{
  "type": "Feature",
  "properties": {
    "iso:country":"DE",
    "sg:address":"Endinger Str. 13",
    "sg:city":"Freiburg",
    "sg:phone":"+49 761/55017",
    "sg:postcode":"79106",
    "sg:province":"Baden-W\u00fcrttemberg",
    "wof:name":"Raiffeisen Warengenossenschaft Eg",
    "wof:placetype":"venue"
},
  "geometry": {"coordinates":[7.836105,48.0019],"type":"Point"}
}