{
  "type": "Feature",
  "properties": {
    "iso:country":"DE",
    "sg:address":"Grote Gert 27",
    "sg:city":"Rheinberg",
    "sg:phone":"+49 2843/60054",
    "sg:postcode":"47495",
    "sg:province":"Nordrhein-Westfalen",
    "wof:name":"S\u00e4misch Bauunternehmung Gmbh",
    "wof:placetype":"venue"
},
  "geometry": {"coordinates":[6.583652,51.541862],"type":"Point"}
}