{
  "type": "Feature",
  "properties": {
    "iso:country":"DE",
    "sg:address":"Kazmairstr. 38",
    "sg:city":"M\u00fcnchen",
    "sg:phone":"+49 89/509370",
    "sg:postcode":"80339",
    "sg:province":"Bayern",
    "wof:name":"Nikos Naturkost G. Nikolaus",
    "wof:placetype":"venue"
},
  "geometry": {"coordinates":[11.5396785736,48.1349105835],"type":"Point"}
}