{
  "type": "Feature",
  "properties": {
    "iso:country":"DE",
    "sg:address":"Klever Str. 22",
    "sg:city":"Xanten",
    "sg:phone":"+49 2801/705020",
    "sg:postcode":"46509",
    "sg:province":"Nordrhein-Westfalen",
    "wof:name":"Restaurant Xiesta",
    "wof:placetype":"venue"
},
  "geometry": {"coordinates":[6.4504928589,51.6622314453],"type":"Point"}
}