{
  "type": "Feature",
  "properties": {
    "iso:country":"DE",
    "sg:address":"Heinrichstr. 5",
    "sg:city":"Braunschweig",
    "sg:phone":"+49 531/238000",
    "sg:postcode":"38106",
    "sg:province":"Niedersachsen",
    "wof:name":"Horst-dieter Schulz Steuerberater",
    "wof:placetype":"venue"
},
  "geometry": {"coordinates":[10.5369653702,52.2695655823],"type":"Point"}
}