{
  "type": "Feature",
  "properties": {
    "iso:country":"DE",
    "sg:address":"B\u00fctersworthstr. 17",
    "sg:city":"Hannover",
    "sg:phone":"+49 511/316336",
    "sg:postcode":"30161",
    "sg:province":"Niedersachsen",
    "wof:name":"Zuttermeister",
    "wof:placetype":"venue"
},
  "geometry": {"coordinates":[9.7517557144,52.3828353882],"type":"Point"}
}