{
  "type": "Feature",
  "properties": {
    "iso:country":"DE",
    "sg:address":"Zur Kettenschmiede 40",
    "sg:city":"Paderborn",
    "sg:phone":"+49 5254",
    "sg:postcode":"33106",
    "sg:province":"Nordrhein-Westfalen",
    "wof:name":"Hdwebservice, Webdesign & Internetservice",
    "wof:placetype":"venue"
},
  "geometry": {"coordinates":[8.677846,51.738647],"type":"Point"}
}