{
  "type": "Feature",
  "properties": {
    "iso:country":"DE",
    "sg:address":"Oberbinge 6",
    "sg:city":"Kassel",
    "sg:phone":"+49 561/61616",
    "sg:postcode":"34130",
    "sg:province":"Hessen",
    "wof:name":"Mediaplan Digitale Medien Gmbh",
    "wof:placetype":"venue"
},
  "geometry": {"coordinates":[9.4434814453,51.3201942444],"type":"Point"}
}