{
  "type": "Feature",
  "properties": {
    "iso:country":"DE",
    "sg:address":"Rathausplatz 3",
    "sg:city":"Neuenmarkt",
    "sg:phone":"+49 9227/6969",
    "sg:postcode":"95339",
    "sg:province":"Bayern",
    "wof:name":"Bella Italia Pizzeria",
    "wof:placetype":"venue"
},
  "geometry": {"coordinates":[11.5830583572,50.0944633484],"type":"Point"}
}