{
  "type": "Feature",
  "properties": {
    "iso:country":"DE",
    "sg:address":"H\u00fclptingser Weg 7",
    "sg:city":"Burgdorf",
    "sg:phone":"+49 5136/880160",
    "sg:postcode":"31303",
    "sg:province":"Niedersachsen",
    "wof:name":"Carl Diewitz Gmbh & Co. Kg",
    "wof:placetype":"venue"
},
  "geometry": {"coordinates":[10.02173,52.443752],"type":"Point"}
}