{
  "type": "Feature",
  "properties": {
    "iso:country":"DE",
    "sg:address":"Inselbogen 1",
    "sg:city":"M\u00fcnster",
    "sg:phone":"+49 251/972500",
    "sg:postcode":"48151",
    "sg:province":"Nordrhein-Westfalen",
    "wof:name":"Ernst-august Schr\u00f6der Inh. Peter Schmidt",
    "wof:placetype":"venue"
},
  "geometry": {"coordinates":[7.6097841263,51.9407615662],"type":"Point"}
}