{
  "type": "Feature",
  "properties": {
    "iso:country":"DE",
    "sg:address":"Volkshof 7",
    "sg:city":"Gutenberg",
    "sg:phone":"+49 34606/20322",
    "sg:postcode":"06193",
    "sg:province":"Sachsen-Anhalt",
    "wof:name":"Hans-georg Exler",
    "wof:placetype":"venue"
},
  "geometry": {"coordinates":[11.972174,51.547852],"type":"Point"}
}