{
  "type": "Feature",
  "properties": {
    "iso:country":"DE",
    "sg:address":"Schlo\u00dfplatz 4",
    "sg:city":"Furth im Wald",
    "sg:phone":"+49 9973/50952",
    "sg:postcode":"93437",
    "sg:province":"Bayern",
    "wof:name":"Landestormuseum",
    "wof:placetype":"venue"
},
  "geometry": {"coordinates":[12.764847,49.307777],"type":"Point"}
}