{
  "type": "Feature",
  "properties": {
    "iso:country":"DE",
    "sg:address":"Okerstr. 4",
    "sg:city":"Berlin",
    "sg:phone":"+49 30/6211035",
    "sg:postcode":"12049",
    "sg:province":"Berlin",
    "wof:name":"R. Stehning",
    "wof:placetype":"venue"
},
  "geometry": {"coordinates":[13.426571846,52.4743385315],"type":"Point"}
}