{
  "type": "Feature",
  "properties": {
    "iso:country":"DE",
    "sg:address":"H\u00f6chster Stra\u00dfe 10",
    "sg:city":"Kelkheim",
    "sg:phone":"+49 6195/900333",
    "sg:postcode":"65779",
    "sg:province":"Hessen",
    "wof:name":"Schl\u00fcssel Barde",
    "wof:placetype":"venue"
},
  "geometry": {"coordinates":[8.453543,50.133175],"type":"Point"}
}