{
  "type": "Feature",
  "properties": {
    "iso:country":"DE",
    "sg:address":"Dr.-August-Stumpf-Str. 28",
    "sg:city":"Walld\u00fcrn",
    "sg:phone":"+49 6282/1790",
    "sg:postcode":"74731",
    "sg:province":"Baden-W\u00fcrttemberg",
    "wof:name":"Kortekamp Anlageberater",
    "wof:placetype":"venue"
},
  "geometry": {"coordinates":[9.3679361343,49.5832290649],"type":"Point"}
}