{
  "type": "Feature",
  "properties": {
    "iso:country":"DE",
    "sg:address":"Gl\u00fcck-Auf-Weg 9",
    "sg:city":"Wenden",
    "sg:phone":"+49 2762/93000",
    "sg:postcode":"57482",
    "sg:province":"Nordrhein-Westfalen",
    "wof:name":"Plitec Pipeline & Armaturen Gmbh",
    "wof:placetype":"venue"
},
  "geometry": {"coordinates":[7.8315620422,50.9836845398],"type":"Point"}
}