{
  "type": "Feature",
  "properties": {
    "iso:country":"DE",
    "sg:address":"Kirchenplatz 1",
    "sg:city":"Norderstedt",
    "sg:phone":"+49 40/5251181",
    "sg:postcode":"22844",
    "sg:province":"Schleswig-Holstein",
    "wof:name":"Ev. Pfarramt Harksheide-falkenberg",
    "wof:placetype":"venue"
},
  "geometry": {"coordinates":[10.0081596375,53.7054214478],"type":"Point"}
}