{
  "type": "Feature",
  "properties": {
    "iso:country":"DE",
    "sg:address":"Hauptstr. 35",
    "sg:city":"Teuschnitz",
    "sg:phone":"+49 9268",
    "sg:postcode":"96358",
    "sg:province":"Bayern",
    "wof:name":"Miquel Schmuck Und Uhren",
    "wof:placetype":"venue"
},
  "geometry": {"coordinates":[11.3803749084,50.3968391418],"type":"Point"}
}