{
  "type": "Feature",
  "properties": {
    "iso:country":"DE",
    "sg:address":"Berliner Str. 12",
    "sg:city":"Herzberg",
    "sg:postcode":"16835",
    "sg:province":"Brandenburg",
    "wof:name":"Al-chrom Nirosta-markt Gmbh",
    "wof:placetype":"venue"
},
  "geometry": {"coordinates":[12.97276,52.899334],"type":"Point"}
}