{
  "type": "Feature",
  "properties": {
    "iso:country":"DE",
    "sg:address":"Birkenweg 12",
    "sg:city":"Seevetal",
    "sg:phone":"+49 40/7684977",
    "sg:postcode":"21217",
    "sg:province":"Niedersachsen",
    "wof:name":"Karl-heinz Kr\u00fcger",
    "wof:placetype":"venue"
},
  "geometry": {"coordinates":[10.023315,53.419514],"type":"Point"}
}