{
  "type": "Feature",
  "properties": {
    "iso:country":"DE",
    "sg:address":"Eckartsbergaer Str. 15",
    "sg:city":"Bad K\u00f6sen",
    "sg:phone":"+49 34463/27579",
    "sg:postcode":"06628",
    "sg:province":"Sachsen-Anhalt",
    "wof:name":"Heinz Klitsch",
    "wof:placetype":"venue"
},
  "geometry": {"coordinates":[11.714468,51.132393],"type":"Point"}
}