{
  "type": "Feature",
  "properties": {
    "iso:country":"DE",
    "sg:address":"Hauptstr. 44",
    "sg:city":"Hambergen",
    "sg:phone":"+49 4793/954092",
    "sg:postcode":"27729",
    "sg:province":"Niedersachsen",
    "wof:name":"Bistro Paris Inh. M. Binder",
    "wof:placetype":"venue"
},
  "geometry": {"coordinates":[8.8383960724,53.3071517944],"type":"Point"}
}