{
  "type": "Feature",
  "properties": {
    "iso:country":"DE",
    "sg:address":"Auflegerstr. 50",
    "sg:city":"M\u00fcnchen",
    "sg:phone":"+49 89/68070740",
    "sg:postcode":"81735",
    "sg:province":"Bayern",
    "wof:name":"Matthias Grill Patentanwalt",
    "wof:placetype":"venue"
},
  "geometry": {"coordinates":[11.6234035492,48.1114273071],"type":"Point"}
}