{
  "type": "Feature",
  "properties": {
    "iso:country":"DE",
    "sg:address":"Bergstr. 46",
    "sg:city":"Wieda",
    "sg:phone":"+49 5586/96610",
    "sg:postcode":"37447",
    "sg:province":"Niedersachsen",
    "wof:name":"Seniorenheim Talblick Alten- Und Pflegeheim",
    "wof:placetype":"venue"
},
  "geometry": {"coordinates":[10.582969,51.63913],"type":"Point"}
}