{
  "type": "Feature",
  "properties": {
    "iso:country":"DE",
    "sg:address":"Weberplatz 22",
    "sg:city":"Potsdam",
    "sg:phone":"+49 331/7480241",
    "sg:postcode":"14482",
    "sg:province":"Brandenburg",
    "wof:name":"Jalousien-m\u00fcller",
    "wof:placetype":"venue"
},
  "geometry": {"coordinates":[13.094278,52.393093],"type":"Point"}
}