{
  "type": "Feature",
  "properties": {
    "iso:country":"DE",
    "sg:address":"Meisenweg 12",
    "sg:city":"Trier",
    "sg:phone":"+49 651/66316",
    "sg:postcode":"54293",
    "sg:province":"Rheinland-Pfalz",
    "wof:name":"G\u00fcnter Hoffmann",
    "wof:placetype":"venue"
},
  "geometry": {"coordinates":[6.6785120964,49.7916908264],"type":"Point"}
}