{
  "type": "Feature",
  "properties": {
    "iso:country":"DE",
    "sg:address":"Stotzstr. 53",
    "sg:city":"Kornwestheim",
    "sg:postcode":"70806",
    "sg:province":"Baden-W\u00fcrttemberg",
    "wof:name":"Eisenkreuz Kornwestheim Hans-michael Gritz",
    "wof:placetype":"venue"
},
  "geometry": {"coordinates":[9.1815977097,48.8597717285],"type":"Point"}
}