{
  "type": "Feature",
  "properties": {
    "iso:country":"DE",
    "sg:address":"Hahnenstr. 10",
    "sg:city":"Waldbr\u00f6l",
    "sg:phone":"+49 2291/92030",
    "sg:postcode":"51545",
    "sg:province":"Nordrhein-Westfalen",
    "wof:name":"Oberbergisches Anzeigenblatt Gmbh & Co. Kg",
    "wof:placetype":"venue"
},
  "geometry": {"coordinates":[7.6172809601,50.8750686646],"type":"Point"}
}