{
  "type": "Feature",
  "properties": {
    "iso:country":"DE",
    "sg:address":"Kirchstr. 5",
    "sg:city":"Horb",
    "sg:phone":"+49 7451/2641",
    "sg:postcode":"72160",
    "sg:province":"Baden-W\u00fcrttemberg",
    "wof:name":"M. G\u00f6ttler",
    "wof:placetype":"venue"
},
  "geometry": {"coordinates":[8.649476,48.439327],"type":"Point"}
}