{
  "type": "Feature",
  "properties": {
    "iso:country":"DE",
    "sg:address":"Erfurter Str. 30",
    "sg:city":"Bad Langensalza",
    "sg:phone":"+49 3603/842319",
    "sg:postcode":"99947",
    "sg:province":"Th\u00fcringen",
    "wof:name":"Brandschutz-technik Th\u00fcringen Gmbh",
    "wof:placetype":"venue"
},
  "geometry": {"coordinates":[10.649731636,51.1067428589],"type":"Point"}
}