{
  "type": "Feature",
  "properties": {
    "iso:country":"DE",
    "sg:address":"Allendorfer Str. 12",
    "sg:city":"Eschwege",
    "sg:phone":"+49 5651/21847",
    "sg:postcode":"37269",
    "sg:province":"Hessen",
    "wof:name":"Asta Baustoffkontor Gmbh",
    "wof:placetype":"venue"
},
  "geometry": {"coordinates":[9.9885826111,51.1770401001],"type":"Point"}
}