{
  "type": "Feature",
  "properties": {
    "iso:country":"DE",
    "sg:address":"Gustav-Freytag-Str. 10",
    "sg:city":"K\u00f6nigswinter",
    "sg:phone":"+49 2244/4769",
    "sg:postcode":"53639",
    "sg:province":"Nordrhein-Westfalen",
    "wof:name":"Meurer Rehatec Gmbh",
    "wof:placetype":"venue"
},
  "geometry": {"coordinates":[7.2714381218,50.7057762146],"type":"Point"}
}