{
  "type": "Feature",
  "properties": {
    "iso:country":"DE",
    "sg:address":"Warnem\u00fcnder Str. 19",
    "sg:city":"Berlin",
    "sg:phone":"+49 30/8233071",
    "sg:postcode":"14199",
    "sg:province":"Berlin",
    "wof:name":"Hotel Sylvia",
    "wof:placetype":"venue"
},
  "geometry": {"coordinates":[13.2893753052,52.4715232849],"type":"Point"}
}