{
  "type": "Feature",
  "properties": {
    "iso:country":"DE",
    "sg:address":"Carl-Benz-Str. 6",
    "sg:city":"Hirschberg",
    "sg:postcode":"69493",
    "sg:province":"Baden-W\u00fcrttemberg",
    "wof:name":"Gis Ges. F\u00fc Integr. Systemplanung Mbh",
    "wof:placetype":"venue"
},
  "geometry": {"coordinates":[8.6458482742,49.5248718262],"type":"Point"}
}