{
  "type": "Feature",
  "properties": {
    "iso:country":"DE",
    "sg:address":"Davenstedter Str. 97",
    "sg:city":"Hannover",
    "sg:phone":"+49 511/21461",
    "sg:postcode":"30453",
    "sg:province":"Niedersachsen",
    "wof:name":"Wilhelm Gruner Gmbh",
    "wof:placetype":"venue"
},
  "geometry": {"coordinates":[9.6978578568,52.3657608032],"type":"Point"}
}