{
  "type": "Feature",
  "properties": {
    "iso:country":"DE",
    "sg:address":"Hauptstr. 50",
    "sg:city":"Besigheim",
    "sg:phone":"+49 7143/80470",
    "sg:postcode":"74354",
    "sg:province":"Baden-W\u00fcrttemberg",
    "wof:name":"Michael Thiele Steuerberater",
    "wof:placetype":"venue"
},
  "geometry": {"coordinates":[9.1413402557,49.0019683838],"type":"Point"}
}