{
  "type": "Feature",
  "properties": {
    "iso:country":"DE",
    "sg:address":"Gerichtstr. 3",
    "sg:city":"Bielefeld",
    "sg:phone":"+49 521/68331",
    "sg:postcode":"33602",
    "sg:province":"Nordrhein-Westfalen",
    "wof:name":"Dr. Horst Rheingans Und Diether Rheingans",
    "wof:placetype":"venue"
},
  "geometry": {"coordinates":[8.5349855423,52.0160064697],"type":"Point"}
}