{
  "type": "Feature",
  "properties": {
    "iso:country":"DE",
    "sg:address":"Hammerstr. 11",
    "sg:city":"Berlin",
    "sg:phone":"+49 30/8183191",
    "sg:postcode":"14167",
    "sg:province":"Berlin",
    "wof:name":"Crescendus Grundst\u00fccks- Verwaltungs Gmbh",
    "wof:placetype":"venue"
},
  "geometry": {"coordinates":[13.275804,52.428986],"type":"Point"}
}