{
  "type": "Feature",
  "properties": {
    "iso:country":"DE",
    "sg:address":"Wilhelmstr. 42",
    "sg:city":"Menden",
    "sg:phone":"+49 2373/2219",
    "sg:postcode":"58706",
    "sg:province":"Nordrhein-Westfalen",
    "wof:name":"Zweirad D\u00fcnnebacke Kg",
    "wof:placetype":"venue"
},
  "geometry": {"coordinates":[7.799478,51.435974],"type":"Point"}
}