{
  "type": "Feature",
  "properties": {
    "iso:country":"DE",
    "sg:address":"Sonthofener Str. 17",
    "sg:city":"Sulzberg",
    "sg:phone":"+49 8376/301",
    "sg:postcode":"87477",
    "sg:province":"Bayern",
    "wof:name":"Landhotel Sulzberger Hof",
    "wof:placetype":"venue"
},
  "geometry": {"coordinates":[10.3494348526,47.6563301086],"type":"Point"}
}