{
  "type": "Feature",
  "properties": {
    "iso:country":"DE",
    "sg:address":"Moosanger 3a",
    "sg:city":"Starnberg",
    "sg:phone":"+49 8151/277681",
    "sg:postcode":"82319",
    "sg:province":"Bayern",
    "wof:name":"K. Luber",
    "wof:placetype":"venue"
},
  "geometry": {"coordinates":[11.365657,48.002407],"type":"Point"}
}