{
  "type": "Feature",
  "properties": {
    "iso:country":"DE",
    "sg:address":"Provinostr. 29",
    "sg:city":"Augsburg",
    "sg:phone":"+49 821/553015",
    "sg:postcode":"86153",
    "sg:province":"Bayern",
    "wof:name":"Manfred Glogger",
    "wof:placetype":"venue"
},
  "geometry": {"coordinates":[10.911292,48.362934],"type":"Point"}
}