{
  "type": "Feature",
  "properties": {
    "iso:country":"DE",
    "sg:address":"Sirius Str. 4",
    "sg:city":"Unterschlei\u00dfheim",
    "sg:phone":"+49 163 3971892",
    "sg:postcode":"85716",
    "sg:province":"Bayern",
    "wof:name":"Zokinet",
    "wof:placetype":"venue"
},
  "geometry": {"coordinates":[11.565778,48.272144],"type":"Point"}
}