{
  "type": "Feature",
  "properties": {
    "iso:country":"DE",
    "sg:address":"Kurzer Graben 3",
    "sg:city":"Schw\u00e4bisch Hall",
    "sg:postcode":"74523",
    "sg:province":"Baden-W\u00fcrttemberg",
    "wof:name":"Kath. \u00d6ffentliche B\u00fccherei St. Josef",
    "wof:placetype":"venue"
},
  "geometry": {"coordinates":[9.739133,49.11388],"type":"Point"}
}