{
  "type": "Feature",
  "properties": {
    "iso:country":"DE",
    "sg:address":"K\u00f6singerstr. 18",
    "sg:city":"Neresheim",
    "sg:phone":"+49 7326/961210",
    "sg:postcode":"73450",
    "sg:province":"Baden-W\u00fcrttemberg",
    "wof:name":"Praxis Dr. Med. Rathgeber Und Dr. Med. Str\u00f6bel",
    "wof:placetype":"venue"
},
  "geometry": {"coordinates":[10.3366088867,48.7568473816],"type":"Point"}
}