{
  "type": "Feature",
  "properties": {
    "iso:country":"DE",
    "sg:address":"In der Steinwiese 70",
    "sg:city":"Siegen",
    "sg:phone":"+49 271/681036",
    "sg:postcode":"57074",
    "sg:province":"Nordrhein-Westfalen",
    "wof:name":"Die Hand In Hand Werker Gmbh",
    "wof:placetype":"venue"
},
  "geometry": {"coordinates":[8.064484,50.868584],"type":"Point"}
}