{
  "type": "Feature",
  "properties": {
    "iso:country":"DE",
    "sg:address":"Fleher Str. 242",
    "sg:city":"D\u00fcsseldorf",
    "sg:phone":"+49 211/902050",
    "sg:postcode":"40223",
    "sg:province":"Nordrhein-Westfalen",
    "wof:name":"Hotel Bl\u00e4ttler Garni",
    "wof:placetype":"venue"
},
  "geometry": {"coordinates":[6.7705559731,51.1921920776],"type":"Point"}
}