{
  "type": "Feature",
  "properties": {
    "iso:country":"DE",
    "sg:address":"Im Weilandmoor 1",
    "sg:city":"Gifhorn",
    "sg:postcode":"38518",
    "sg:province":"Niedersachsen",
    "wof:name":"Ggg Grundst\u00fccksobjekt- Gesellschaft Gmbh & Co. Kg",
    "wof:placetype":"venue"
},
  "geometry": {"coordinates":[10.5296840668,52.4714546204],"type":"Point"}
}