{
  "type": "Feature",
  "properties": {
    "iso:country":"DE",
    "sg:address":"Andreestr. 3",
    "sg:city":"M\u00fcnchen",
    "sg:phone":"+49 89/132744",
    "sg:postcode":"80634",
    "sg:province":"Bayern",
    "wof:name":"Edith Warth",
    "wof:placetype":"venue"
},
  "geometry": {"coordinates":[11.5297136307,48.1519966125],"type":"Point"}
}