{
  "type": "Feature",
  "properties": {
    "iso:country":"DE",
    "sg:address":"Hofaue 73",
    "sg:city":"Wuppertal",
    "sg:phone":"+49 202/444593",
    "sg:postcode":"42103",
    "sg:province":"Nordrhein-Westfalen",
    "wof:name":"G. Frohme Heilpraktiker",
    "wof:placetype":"venue"
},
  "geometry": {"coordinates":[7.1511530876,51.25730896],"type":"Point"}
}