{
  "type": "Feature",
  "properties": {
    "iso:country":"DE",
    "sg:address":"Am Gr\u00fcnen Tor 2",
    "sg:city":"Burow",
    "sg:phone":"+49 3965/421",
    "sg:postcode":"17089",
    "sg:province":"Mecklenburg-Vorpommern",
    "wof:name":"Landapotheke Inh. H. Strauch",
    "wof:placetype":"venue"
},
  "geometry": {"coordinates":[13.272467,53.774017],"type":"Point"}
}