{
  "type": "Feature",
  "properties": {
    "iso:country":"DE",
    "sg:address":"Bahnhofstr. 95",
    "sg:city":"Bad Berneck",
    "sg:phone":"+49 9273/57152",
    "sg:postcode":"95460",
    "sg:province":"Bayern",
    "wof:name":"Diska",
    "wof:placetype":"venue"
},
  "geometry": {"coordinates":[11.6691446304,50.043762207],"type":"Point"}
}