{
  "type": "Feature",
  "properties": {
    "iso:country":"DE",
    "sg:address":"Rothenthaler Str. 6",
    "sg:city":"Olbernhau",
    "sg:phone":"+49 37360/36909",
    "sg:postcode":"09526",
    "sg:province":"Sachsen",
    "wof:name":"Rolf-dieter Preissler",
    "wof:placetype":"venue"
},
  "geometry": {"coordinates":[13.3721036911,50.6377372742],"type":"Point"}
}