{
  "type": "Feature",
  "properties": {
    "iso:country":"DE",
    "sg:address":"Billsbergstr. 1",
    "sg:city":"Pleidelsheim",
    "sg:phone":"+49 7144/29252",
    "sg:postcode":"74385",
    "sg:province":"Baden-W\u00fcrttemberg",
    "wof:name":"G\u00fcnter Scheytt Steuerberater",
    "wof:placetype":"venue"
},
  "geometry": {"coordinates":[9.1951265335,48.9562454224],"type":"Point"}
}