{
  "type": "Feature",
  "properties": {
    "iso:country":"DE",
    "sg:address":"Osterrade 12",
    "sg:city":"Hamburg",
    "sg:phone":"+49 221/9355610",
    "sg:postcode":"21031",
    "sg:province":"Hamburg",
    "wof:name":"Moch-figuren Gmbh",
    "wof:placetype":"venue"
},
  "geometry": {"coordinates":[7.0159687996,50.8854751587],"type":"Point"}
}