{
  "type": "Feature",
  "properties": {
    "iso:country":"DE",
    "sg:address":"Staufenstr. 24",
    "sg:city":"Niederstotzingen",
    "sg:phone":"+49 7325/919266",
    "sg:postcode":"89168",
    "sg:province":"Baden-W\u00fcrttemberg",
    "wof:name":"Wilhelm B\u00f6hm",
    "wof:placetype":"venue"
},
  "geometry": {"coordinates":[10.2389211655,48.5401000977],"type":"Point"}
}