{
  "type": "Feature",
  "properties": {
    "iso:country":"DE",
    "sg:address":"Simonstr. 54",
    "sg:city":"F\u00fcrth",
    "sg:phone":"+49 911/711207",
    "sg:postcode":"90763",
    "sg:province":"Bayern",
    "wof:name":"Dieter Sternberg",
    "wof:placetype":"venue"
},
  "geometry": {"coordinates":[10.9910507202,49.4641685486],"type":"Point"}
}