{
  "type": "Feature",
  "properties": {
    "iso:country":"DE",
    "sg:address":"Stiftsbogen 35",
    "sg:city":"M\u00fcnchen",
    "sg:phone":"+49 89/173819",
    "sg:postcode":"81375",
    "sg:province":"Bayern",
    "wof:name":"Christl Tremel",
    "wof:placetype":"venue"
},
  "geometry": {"coordinates":[11.4919729233,48.1204071045],"type":"Point"}
}