{
  "type": "Feature",
  "properties": {
    "iso:country":"DE",
    "sg:address":"Eislebener Str. 16",
    "sg:city":"Aschersleben",
    "sg:phone":"+49 3473/6571",
    "sg:postcode":"06449",
    "sg:province":"Sachsen-Anhalt",
    "wof:name":"Heinrich Rademacher",
    "wof:placetype":"venue"
},
  "geometry": {"coordinates":[11.44127,51.757141],"type":"Point"}
}