{
  "type": "Feature",
  "properties": {
    "iso:country":"DE",
    "sg:address":"Molkenbornstr. 17",
    "sg:city":"Aschaffenburg",
    "sg:phone":"+49 6021/91718",
    "sg:postcode":"63743",
    "sg:province":"Bayern",
    "wof:name":"Norbert Zahn",
    "wof:placetype":"venue"
},
  "geometry": {"coordinates":[9.1668958664,49.9606056213],"type":"Point"}
}