{
  "type": "Feature",
  "properties": {
    "iso:country":"DE",
    "sg:address":"Kirdorfer Allee 30",
    "sg:city":"Bedburg",
    "sg:phone":"+49 2272/3268",
    "sg:postcode":"50181",
    "sg:province":"Nordrhein-Westfalen",
    "wof:name":"Franz Lipej Architekt",
    "wof:placetype":"venue"
},
  "geometry": {"coordinates":[6.573432,50.97953],"type":"Point"}
}