{
  "type": "Feature",
  "properties": {
    "iso:country":"DE",
    "sg:address":"Azenbergstr. 19",
    "sg:city":"Stuttgart",
    "sg:phone":"+49 711/295875",
    "sg:postcode":"70174",
    "sg:province":"Baden-W\u00fcrttemberg",
    "wof:name":"Klaus-j\u00fcrgen Bauer",
    "wof:placetype":"venue"
},
  "geometry": {"coordinates":[9.1649446487,48.7866287231],"type":"Point"}
}