{
  "type": "Feature",
  "properties": {
    "iso:country":"DE",
    "sg:address":"R\u00f6delheimer Landstr. 75-85",
    "sg:city":"Frankfurt",
    "sg:postcode":"60487",
    "sg:province":"Hessen",
    "wof:name":"B A S Handelsgesellschaft Mbh",
    "wof:placetype":"venue"
},
  "geometry": {"coordinates":[8.622936,50.121002],"type":"Point"}
}