{
  "type": "Feature",
  "properties": {
    "iso:country":"DE",
    "sg:address":"Schlo\u00dfstr. 2",
    "sg:city":"Saarbr\u00fccken",
    "sg:phone":"+49 681/57846",
    "sg:postcode":"66117",
    "sg:province":"Saarland",
    "wof:name":"Restaurant Tomate Gmbh",
    "wof:placetype":"venue"
},
  "geometry": {"coordinates":[6.9907631874,49.2309837341],"type":"Point"}
}