{
  "type": "Feature",
  "properties": {
    "iso:country":"DE",
    "sg:address":"D\u00fcsseldorfer Str. 123",
    "sg:city":"Ratingen",
    "sg:phone":"+49 2102/993897",
    "sg:postcode":"40878",
    "sg:province":"Nordrhein-Westfalen",
    "wof:name":"Walter Aulbach",
    "wof:placetype":"venue"
},
  "geometry": {"coordinates":[6.8407721519,51.2915878296],"type":"Point"}
}