{
  "type": "Feature",
  "properties": {
    "iso:country":"DE",
    "sg:address":"Friedrichstr. 2",
    "sg:city":"Plankstadt",
    "sg:phone":"+49 6202/200643",
    "sg:postcode":"68723",
    "sg:province":"Baden-W\u00fcrttemberg",
    "wof:name":"Schwimmhalle",
    "wof:placetype":"venue"
},
  "geometry": {"coordinates":[8.5962972641,49.3911743164],"type":"Point"}
}