{
  "type": "Feature",
  "properties": {
    "iso:country":"DE",
    "sg:address":"Feringstrasse 6",
    "sg:city":"M\u00fcnchen",
    "sg:phone":"+49 89/99216461",
    "sg:postcode":"85774",
    "sg:province":"Bayern",
    "wof:name":"Shopsuche",
    "wof:placetype":"venue"
},
  "geometry": {"coordinates":[11.6405448914,48.1923942566],"type":"Point"}
}