{
  "type": "Feature",
  "properties": {
    "iso:country":"DE",
    "sg:address":"Lembergstr. 3",
    "sg:city":"Gosheim",
    "sg:phone":"+49 7426/1407",
    "sg:postcode":"78559",
    "sg:province":"Baden-W\u00fcrttemberg",
    "wof:name":"Klaus Weiss",
    "wof:placetype":"venue"
},
  "geometry": {"coordinates":[8.7525959015,48.1356811523],"type":"Point"}
}