{
  "type": "Feature",
  "properties": {
    "iso:country":"DE",
    "sg:address":"Friesenheimer Str. 16",
    "sg:city":"Ludwigshafen",
    "sg:phone":"+49 621/656500",
    "sg:postcode":"67069",
    "sg:province":"Rheinland-Pfalz",
    "wof:name":"Thomas Schr\u00f6der Rechtsanwalt",
    "wof:placetype":"venue"
},
  "geometry": {"coordinates":[8.4069385529,49.5184249878],"type":"Point"}
}