{
  "type": "Feature",
  "properties": {
    "iso:country":"DE",
    "sg:address":"Weinweg 14",
    "sg:city":"Karlsruhe",
    "sg:phone":"+49 721/611156",
    "sg:postcode":"76131",
    "sg:province":"Baden-W\u00fcrttemberg",
    "wof:name":"Otto Katzik Immobilienmakler",
    "wof:placetype":"venue"
},
  "geometry": {"coordinates":[8.4454536438,49.0101928711],"type":"Point"}
}