{
  "type": "Feature",
  "properties": {
    "iso:country":"DE",
    "sg:city":"Darmstadt",
    "sg:postcode":"64295",
    "sg:province":"Hessen",
    "wof:name":"Dbv-winterthur Krankenversicherung",
    "wof:placetype":"venue"
},
  "geometry": {"coordinates":[8.60247,49.850609],"type":"Point"}
}