{
  "type": "Feature",
  "properties": {
    "iso:country":"DE",
    "sg:address":"Krausstr. 21",
    "sg:city":"Duisburg",
    "sg:phone":"+49 203/81084",
    "sg:postcode":"47119",
    "sg:province":"Nordrhein-Westfalen",
    "wof:name":"Kadlec & Br\u00f6dlin Gmbh Elektroinstallation",
    "wof:placetype":"venue"
},
  "geometry": {"coordinates":[6.7337598801,51.4499015808],"type":"Point"}
}