{
  "type": "Feature",
  "properties": {
    "iso:country":"DE",
    "sg:address":"Dietigheimer Str. 2a",
    "sg:city":"Bad Homburg",
    "sg:phone":"+49 6172/82950",
    "sg:postcode":"61350",
    "sg:province":"Hessen",
    "wof:name":"W. Fabel",
    "wof:placetype":"venue"
},
  "geometry": {"coordinates":[8.611882,50.233589],"type":"Point"}
}