{
  "type": "Feature",
  "properties": {
    "iso:country":"DE",
    "sg:address":"Eiserfelder Str. 139",
    "sg:city":"Siegen",
    "sg:postcode":"57072",
    "sg:province":"Nordrhein-Westfalen",
    "wof:name":"Mittelstandsrendite Beteili- Gungsfonds Gmbh & Co. Kg",
    "wof:placetype":"venue"
},
  "geometry": {"coordinates":[8.01136,50.856091],"type":"Point"}
}