{
  "type": "Feature",
  "properties": {
    "iso:country":"DE",
    "sg:address":"Luisental 9",
    "sg:city":"M\u00fclheim",
    "sg:phone":"+49 208/36203",
    "sg:postcode":"45468",
    "sg:province":"Nordrhein-Westfalen",
    "wof:name":"Wolfgang Spies",
    "wof:placetype":"venue"
},
  "geometry": {"coordinates":[6.8773231506,51.4213981628],"type":"Point"}
}