{
  "type": "Feature",
  "properties": {
    "iso:country":"DE",
    "sg:address":"Ahltener Str. 20",
    "sg:city":"Lehrte",
    "sg:phone":"+49 5132/8310",
    "sg:postcode":"31275",
    "sg:province":"Niedersachsen",
    "wof:name":"Seniorenzentrum Lehrte",
    "wof:placetype":"venue"
},
  "geometry": {"coordinates":[9.972452,52.372932],"type":"Point"}
}