{
  "type": "Feature",
  "properties": {
    "iso:country":"DE",
    "sg:address":"Beinsteiner Str. 38",
    "sg:city":"Waiblingen",
    "sg:phone":"+49 7151/23156",
    "sg:postcode":"71334",
    "sg:province":"Baden-W\u00fcrttemberg",
    "wof:name":"Bestattungsunternehmen Golding",
    "wof:placetype":"venue"
},
  "geometry": {"coordinates":[9.327243,48.831089],"type":"Point"}
}