{
  "type": "Feature",
  "properties": {
    "iso:country":"DE",
    "sg:address":"August-Bebel-Str. 70",
    "sg:city":"Beierfeld",
    "sg:phone":"+49 3774/27550",
    "sg:postcode":"08340",
    "sg:province":"Sachsen",
    "wof:name":"M\u00fcller & Kula",
    "wof:placetype":"venue"
},
  "geometry": {"coordinates":[12.78841,50.529518],"type":"Point"}
}