{
  "type": "Feature",
  "properties": {
    "iso:country":"DE",
    "sg:address":"M\u00fcnchener Str. 30 a",
    "sg:city":"Garching",
    "sg:phone":"+49 89/3202512",
    "sg:postcode":"85748",
    "sg:province":"Bayern",
    "wof:name":"Dr. Donderer Hausverwaltungs Gmbh",
    "wof:placetype":"venue"
},
  "geometry": {"coordinates":[-110.7298736572,32.1919593811],"type":"Point"}
}