{
  "type": "Feature",
  "properties": {
    "iso:country":"DE",
    "sg:address":"G\u00fctersloher Str. 27",
    "sg:city":"H\u00f6velhof",
    "sg:phone":"+49 5257/4048",
    "sg:postcode":"33161",
    "sg:province":"Nordrhein-Westfalen",
    "wof:name":"J. Hellmich",
    "wof:placetype":"venue"
},
  "geometry": {"coordinates":[8.65218,51.82518],"type":"Point"}
}