{
  "type": "Feature",
  "properties": {
    "iso:country":"DE",
    "sg:address":"Bayreuther Str. 13",
    "sg:city":"Neusorg",
    "sg:phone":"+49 9234/301",
    "sg:postcode":"95700",
    "sg:province":"Bayern",
    "wof:name":"Neusorger Kalksteinwerk Gmbh",
    "wof:placetype":"venue"
},
  "geometry": {"coordinates":[11.9685401917,49.9308700562],"type":"Point"}
}