{
  "type": "Feature",
  "properties": {
    "iso:country":"DE",
    "sg:address":"Lychener Str. 61",
    "sg:city":"Berlin",
    "sg:postcode":"10437",
    "sg:province":"Berlin",
    "wof:name":"Massen G. Musik-promotion Gmbh",
    "wof:placetype":"venue"
},
  "geometry": {"coordinates":[13.4191160202,52.5453338623],"type":"Point"}
}