{
  "type": "Feature",
  "properties": {
    "iso:country":"DE",
    "sg:address":"Pappenheimer Str. 68",
    "sg:city":"N\u00fcrnberg",
    "sg:phone":"+49 911/644640",
    "sg:postcode":"90451",
    "sg:province":"Bayern",
    "wof:name":"Dr. Bernd Tr\u00f6ger Industrievertretungen Und",
    "wof:placetype":"venue"
},
  "geometry": {"coordinates":[11.0346012115,49.3954315186],"type":"Point"}
}