{
  "type": "Feature",
  "properties": {
    "iso:country":"DE",
    "sg:address":"Luzian-Reich-Str. 9",
    "sg:city":"H\u00fcfingen",
    "sg:phone":"+49 771/61912",
    "sg:postcode":"78183",
    "sg:province":"Baden-W\u00fcrttemberg",
    "wof:name":"Rki Rapp & Kern Immobilienentwicklung Gmbh",
    "wof:placetype":"venue"
},
  "geometry": {"coordinates":[8.493124,47.927139],"type":"Point"}
}