{
  "type": "Feature",
  "properties": {
    "iso:country":"DE",
    "sg:address":"Talackerstr. 21",
    "sg:city":"V\u00f6rstetten",
    "sg:phone":"+49 7666/2394",
    "sg:postcode":"79279",
    "sg:province":"Baden-W\u00fcrttemberg",
    "wof:name":"H. Heim",
    "wof:placetype":"venue"
},
  "geometry": {"coordinates":[7.849187851,48.0615921021],"type":"Point"}
}