{
  "type": "Feature",
  "properties": {
    "iso:country":"DE",
    "sg:address":"Frankenstr. 3",
    "sg:city":"Kreuzwertheim",
    "sg:phone":"+49 9342/8159",
    "sg:postcode":"97892",
    "sg:province":"Bayern",
    "wof:name":"Tischer Gmbh Freizeitfahrzeuge",
    "wof:placetype":"venue"
},
  "geometry": {"coordinates":[9.5243244171,49.790145874],"type":"Point"}
}