{
  "type": "Feature",
  "properties": {
    "iso:country":"DE",
    "sg:address":"Hansastr. 45 a",
    "sg:city":"Osnabr\u00fcck",
    "sg:phone":"+49 541/64386",
    "sg:postcode":"49090",
    "sg:province":"Niedersachsen",
    "wof:name":"Westfalen Tankstelle",
    "wof:placetype":"venue"
},
  "geometry": {"coordinates":[8.0383319855,52.2877006531],"type":"Point"}
}