{
  "type": "Feature",
  "properties": {
    "iso:country":"DE",
    "sg:address":"Bei der Breits\u00fclze 20 c",
    "sg:city":"M\u00fchlhausen",
    "sg:postcode":"99974",
    "sg:province":"Th\u00fcringen",
    "wof:name":"Tupag Bau- Und Heimwerker- Markt Betriebsgesellschaft Mbh",
    "wof:placetype":"venue"
},
  "geometry": {"coordinates":[10.4308614731,51.2241973877],"type":"Point"}
}