{
  "type": "Feature",
  "properties": {
    "iso:country":"DE",
    "sg:address":"fzhh 44",
    "sg:city":"3355dfhdh",
    "sg:phone":"+49 33333/533",
    "sg:postcode":"35533",
    "wof:name":"Soeylemez",
    "wof:placetype":"venue"
},
  "geometry": {"coordinates":[8.50348,50.55098],"type":"Point"}
}