{
  "type": "Feature",
  "properties": {
    "iso:country":"DE",
    "sg:address":"Luisenthaler Str. 153",
    "sg:city":"Saarbr\u00fccken",
    "sg:phone":"+49 681/780870",
    "sg:postcode":"66115",
    "sg:province":"Saarland",
    "wof:name":"Willi Lauer Gmbh",
    "wof:placetype":"venue"
},
  "geometry": {"coordinates":[6.924156,49.244755],"type":"Point"}
}