{
  "type": "Feature",
  "properties": {
    "iso:country":"DE",
    "sg:address":"Brauhausstr. 4",
    "sg:city":"Dortmund",
    "sg:phone":"+49 231/527713",
    "sg:postcode":"44137",
    "sg:province":"Nordrhein-Westfalen",
    "wof:name":"Pro B\u00fcro Und Kopier Gmbh",
    "wof:placetype":"venue"
},
  "geometry": {"coordinates":[7.4665498734,51.5126953125],"type":"Point"}
}