{
  "type": "Feature",
  "properties": {
    "iso:country":"DE",
    "sg:address":"Obergasse 11",
    "sg:city":"W\u00f6rrstadt",
    "sg:phone":"+49 6732/7962",
    "sg:postcode":"55286",
    "sg:province":"Rheinland-Pfalz",
    "wof:name":"Hans-otto Brand",
    "wof:placetype":"venue"
},
  "geometry": {"coordinates":[8.0925989151,49.8223342896],"type":"Point"}
}