{
  "type": "Feature",
  "properties": {
    "iso:country":"DE",
    "sg:address":"Nelkenstr. 18",
    "sg:city":"Hessisch Oldendorf",
    "sg:phone":"+49 5152/3299",
    "sg:postcode":"31840",
    "sg:province":"Niedersachsen",
    "wof:name":"G. Kaese",
    "wof:placetype":"venue"
},
  "geometry": {"coordinates":[9.2438192368,52.1767158508],"type":"Point"}
}