{
  "type": "Feature",
  "properties": {
    "iso:country":"DE",
    "sg:address":"Freesendamm 47",
    "sg:city":"Weyhe",
    "sg:phone":"+49 4203/1817",
    "sg:postcode":"28844",
    "sg:province":"Niedersachsen",
    "wof:name":"Georg Junge",
    "wof:placetype":"venue"
},
  "geometry": {"coordinates":[8.840928,52.971539],"type":"Point"}
}