{
  "type": "Feature",
  "properties": {
    "iso:country":"DE",
    "sg:address":"Gutenbergstr. 21",
    "sg:city":"Lilienthal",
    "sg:phone":"+49 8532/1001",
    "sg:postcode":"28865",
    "sg:province":"Niedersachsen",
    "wof:name":"Klaus M\u00dchlberger",
    "wof:placetype":"venue"
},
  "geometry": {"coordinates":[13.1937246323,48.4526481628],"type":"Point"}
}