{
  "type": "Feature",
  "properties": {
    "iso:country":"DE",
    "sg:address":"Unser Lieben Frauen Kirchhof 1",
    "sg:city":"Bremen",
    "sg:phone":"+49 421/326191",
    "sg:postcode":"28195",
    "sg:province":"Bremen",
    "wof:name":"Walter Lichte",
    "wof:placetype":"venue"
},
  "geometry": {"coordinates":[8.8082733154,53.0766830444],"type":"Point"}
}