{
  "type": "Feature",
  "properties": {
    "iso:country":"DE",
    "sg:address":"Klockenstr. 41",
    "sg:city":"B\u00fcnde",
    "sg:phone":"+49 5223/10833",
    "sg:postcode":"32257",
    "sg:province":"Nordrhein-Westfalen",
    "wof:name":"Heinz-erich H\u00fcffermann",
    "wof:placetype":"venue"
},
  "geometry": {"coordinates":[8.5994520187,52.1900672913],"type":"Point"}
}