{
  "type": "Feature",
  "properties": {
    "iso:country":"DE",
    "sg:address":"Pellheimer Str. 17",
    "sg:city":"Dachau",
    "sg:phone":"+49 8131/5550",
    "sg:postcode":"85221",
    "sg:province":"Bayern",
    "wof:name":"H\u00f6rl Beteiligungs Gmbh",
    "wof:placetype":"venue"
},
  "geometry": {"coordinates":[11.41803,48.292713],"type":"Point"}
}