{
  "type": "Feature",
  "properties": {
    "iso:country":"DE",
    "sg:address":"R\u00f6gen 1",
    "sg:city":"Bad Oldesloe",
    "sg:phone":"+49 4531/17240",
    "sg:postcode":"23843",
    "sg:province":"Schleswig-Holstein",
    "wof:name":"Hage Technik Bad Oldesloe Gmbh",
    "wof:placetype":"venue"
},
  "geometry": {"coordinates":[10.341778,53.799458],"type":"Point"}
}