{
  "type": "Feature",
  "properties": {
    "iso:country":"DE",
    "sg:address":"Hoffmannallee 107-109",
    "sg:city":"Kleve",
    "sg:phone":"+49 2821/72570",
    "sg:postcode":"47533",
    "sg:province":"Nordrhein-Westfalen",
    "wof:name":"Reintjes Graphischer Betrieb Gmbh",
    "wof:placetype":"venue"
},
  "geometry": {"coordinates":[6.121736,51.776512],"type":"Point"}
}