{
  "type": "Feature",
  "properties": {
    "iso:country":"DE",
    "sg:address":"Horstheider Weg 79",
    "sg:city":"Bielefeld",
    "sg:phone":"+49 521/882955",
    "sg:postcode":"33613",
    "sg:province":"Nordrhein-Westfalen",
    "wof:name":"Helmut Biermann",
    "wof:placetype":"venue"
},
  "geometry": {"coordinates":[8.527074,52.054607],"type":"Point"}
}