{
  "type": "Feature",
  "properties": {
    "iso:country":"DE",
    "sg:address":"Ferdinandstr. 14",
    "sg:city":"Berlin",
    "sg:phone":"+49 30/7729034",
    "sg:postcode":"12209",
    "sg:province":"Berlin",
    "wof:name":"Robert Bialk Gmbh",
    "wof:placetype":"venue"
},
  "geometry": {"coordinates":[13.330387,52.424442],"type":"Point"}
}