{
  "type": "Feature",
  "properties": {
    "iso:country":"DE",
    "sg:address":"Breiniger Berg 65",
    "sg:city":"Stolberg",
    "sg:phone":"+49 2402/36675",
    "sg:postcode":"52223",
    "sg:province":"Nordrhein-Westfalen",
    "wof:name":"Go\u00dfen Gmbh",
    "wof:placetype":"venue"
},
  "geometry": {"coordinates":[6.2316842079,50.7355918884],"type":"Point"}
}