{
  "type": "Feature",
  "properties": {
    "iso:country":"DE",
    "sg:address":"Grevener Damm 14",
    "sg:city":"Ostbevern",
    "sg:phone":"+49 2532/5325",
    "sg:postcode":"48346",
    "sg:province":"Nordrhein-Westfalen",
    "wof:name":"Franz Silge",
    "wof:placetype":"venue"
},
  "geometry": {"coordinates":[7.8306851387,52.0421562195],"type":"Point"}
}