{
  "type": "Feature",
  "properties": {
    "iso:country":"DE",
    "sg:address":"Lindenstr. 34 a",
    "sg:city":"Rosdorf",
    "sg:phone":"+49 5509/2091",
    "sg:postcode":"37124",
    "sg:province":"Niedersachsen",
    "wof:name":"P\u00f6stgens Gmbh",
    "wof:placetype":"venue"
},
  "geometry": {"coordinates":[9.8674221039,51.4906539917],"type":"Point"}
}