{
  "type": "Feature",
  "properties": {
    "iso:country":"DE",
    "sg:address":"Kirchengasse 7",
    "sg:city":"Neumarkt",
    "sg:phone":"+49 9181/6084",
    "sg:postcode":"92318",
    "sg:province":"Bayern",
    "wof:name":"Rialto-palast",
    "wof:placetype":"venue"
},
  "geometry": {"coordinates":[11.4582214355,49.2787361145],"type":"Point"}
}