{
  "type": "Feature",
  "properties": {
    "iso:country":"DE",
    "sg:address":"B\u00fcsumer Str. 72",
    "sg:city":"Rendsburg",
    "sg:phone":"+49 4331/44134",
    "sg:postcode":"24768",
    "sg:province":"Schleswig-Holstein",
    "wof:name":"W\u00fcnsch Und Frank",
    "wof:placetype":"venue"
},
  "geometry": {"coordinates":[9.6654157639,54.2996025085],"type":"Point"}
}