{
  "type": "Feature",
  "properties": {
    "iso:country":"DE",
    "sg:address":"Hauptstr. 41",
    "sg:city":"Bensheim",
    "sg:phone":"+49 6251/71077",
    "sg:postcode":"64625",
    "sg:province":"Hessen",
    "wof:name":"Immobiliengesellschaft Der Bergstr\u00e4\u00dfer Volksbanken In",
    "wof:placetype":"venue"
},
  "geometry": {"coordinates":[8.6222467422,49.6803131104],"type":"Point"}
}