{
  "type": "Feature",
  "properties": {
    "iso:country":"DE",
    "sg:address":"Ferienstr. 8",
    "sg:city":"Obernburg",
    "sg:phone":"+49 6022/38717",
    "sg:postcode":"63785",
    "sg:province":"Bayern",
    "wof:name":"Bistro-royal-cafe",
    "wof:placetype":"venue"
},
  "geometry": {"coordinates":[9.1443548203,49.839641571],"type":"Point"}
}