{
  "type": "Feature",
  "properties": {
    "iso:country":"DE",
    "sg:address":"Gschwall 10",
    "sg:city":"Inzell",
    "sg:phone":"+49 8665/288",
    "sg:postcode":"83334",
    "sg:province":"Bayern",
    "wof:name":"Alpenhof",
    "wof:placetype":"venue"
},
  "geometry": {"coordinates":[12.7250747681,47.7834587097],"type":"Point"}
}