{
  "type": "Feature",
  "properties": {
    "iso:country":"DE",
    "sg:address":"Dibberser M\u00fchlenweg 81",
    "sg:city":"Buchholz",
    "sg:postcode":"21244",
    "sg:province":"Niedersachsen",
    "wof:name":"Hans Von Hagen Projekt- Management Hh-p E. K.",
    "wof:placetype":"venue"
},
  "geometry": {"coordinates":[9.87604,53.340107],"type":"Point"}
}