{
  "type": "Feature",
  "properties": {
    "iso:country":"DE",
    "sg:address":"Obergasse 50",
    "sg:city":"Altenstadt",
    "sg:phone":"+49 6047/4860",
    "sg:postcode":"63674",
    "sg:province":"Hessen",
    "wof:name":"Rudolf Hoffmann",
    "wof:placetype":"venue"
},
  "geometry": {"coordinates":[8.9361524582,50.2880744934],"type":"Point"}
}