{
  "type": "Feature",
  "properties": {
    "iso:country":"DE",
    "sg:address":"Schillerstr. 16",
    "sg:city":"Bitterfeld",
    "sg:phone":"+49 3493/41527",
    "sg:postcode":"06749",
    "sg:province":"Sachsen-Anhalt",
    "wof:name":"Willi Busse",
    "wof:placetype":"venue"
},
  "geometry": {"coordinates":[12.324590683,51.6332855225],"type":"Point"}
}