{
  "type": "Feature",
  "properties": {
    "iso:country":"DE",
    "sg:address":"kiesseestr. 33",
    "sg:city":"goettingen",
    "sg:phone":"+49 551/7906916",
    "sg:postcode":"37083",
    "sg:province":"Niedersachsen",
    "wof:name":"Afwk (agentur Fuer Werbung Und Kommunikation)",
    "wof:placetype":"venue"
},
  "geometry": {"coordinates":[9.950356,51.511639],"type":"Point"}
}