{
  "type": "Feature",
  "properties": {
    "iso:country":"DE",
    "sg:address":"Dillinger Str. 3",
    "sg:city":"Dillingen",
    "sg:postcode":"66763",
    "sg:province":"Saarland",
    "wof:name":"Eva P\u00f6nicke",
    "wof:placetype":"venue"
},
  "geometry": {"coordinates":[6.754442215,49.36926651],"type":"Point"}
}