{
  "type": "Feature",
  "properties": {
    "iso:country":"DE",
    "sg:address":"Hauptplatz 10",
    "sg:city":"Landsberg",
    "sg:phone":"+49 8191/92330",
    "sg:postcode":"86899",
    "sg:province":"Bayern",
    "wof:name":"Georg Verza Gmbh",
    "wof:placetype":"venue"
},
  "geometry": {"coordinates":[10.8769388199,48.0493202209],"type":"Point"}
}