{
  "type": "Feature",
  "properties": {
    "iso:country":"DE",
    "sg:address":"Eisenberger Str. 5",
    "sg:city":"Weickelsdorf",
    "sg:phone":"+49 34422/21702",
    "sg:postcode":"06722",
    "sg:province":"Sachsen-Anhalt",
    "wof:name":"Berthold",
    "wof:placetype":"venue"
},
  "geometry": {"coordinates":[11.9966993332,51.0306091309],"type":"Point"}
}