{
  "type": "Feature",
  "properties": {
    "iso:country":"DE",
    "sg:address":"Am Forsthaus 14-18",
    "sg:city":"Geilenkirchen",
    "sg:phone":"+49 2451/2193",
    "sg:postcode":"52511",
    "sg:province":"Nordrhein-Westfalen",
    "wof:name":"Altenheim Am Forsthaus",
    "wof:placetype":"venue"
},
  "geometry": {"coordinates":[6.115184,50.980511],"type":"Point"}
}