{
  "type": "Feature",
  "properties": {
    "iso:country":"DE",
    "sg:address":"Hauptstr. 44",
    "sg:city":"Reckendorf",
    "sg:phone":"+49 9544/302",
    "sg:postcode":"96182",
    "sg:province":"Bayern",
    "wof:name":"Ernst Burkhard Haus- Und K\u00fcchenger\u00e4te",
    "wof:placetype":"venue"
},
  "geometry": {"coordinates":[10.8272123337,50.0206718445],"type":"Point"}
}