{
  "type": "Feature",
  "properties": {
    "iso:country":"DE",
    "sg:address":"R\u00f6merstr. 77",
    "sg:city":"Niedernberg",
    "sg:phone":"+49 6028/1655",
    "sg:postcode":"63843",
    "sg:province":"Bayern",
    "wof:name":"Restaurant Mikes Schnitzelfarm",
    "wof:placetype":"venue"
},
  "geometry": {"coordinates":[9.1314430237,49.91796875],"type":"Point"}
}