{
  "type": "Feature",
  "properties": {
    "iso:country":"DE",
    "sg:address":"Auf dem Berg 1",
    "sg:city":"Herborn",
    "sg:phone":"+49 2772/55198",
    "sg:postcode":"35745",
    "sg:province":"Hessen",
    "wof:name":"Bernd Pfeiffer",
    "wof:placetype":"venue"
},
  "geometry": {"coordinates":[8.2688846588,50.6695747375],"type":"Point"}
}