{
  "type": "Feature",
  "properties": {
    "iso:country":"DE",
    "sg:address":"N\u00fcrnberger Str. 67",
    "sg:city":"Berlin",
    "sg:phone":"+49 30/21477315",
    "sg:postcode":"12309",
    "sg:province":"Berlin",
    "wof:name":"Bundesverband Zur F\u00f6rderung Der Kreislaufwirtschaft E. V.",
    "wof:placetype":"venue"
},
  "geometry": {"coordinates":[13.4124746323,52.3915939331],"type":"Point"}
}