{
  "type": "Feature",
  "properties": {
    "iso:country":"DE",
    "sg:address":"Lange Str. 65",
    "sg:city":"Baden-Baden",
    "sg:postcode":"76530",
    "sg:province":"Baden-W\u00fcrttemberg",
    "wof:name":"Ladr Praxisbetriebsges. Baden-baden Mbh",
    "wof:placetype":"venue"
},
  "geometry": {"coordinates":[8.2340373993,48.7664909363],"type":"Point"}
}