{
  "type": "Feature",
  "properties": {
    "iso:country":"DE",
    "sg:address":"Euskirchener Str. 64",
    "sg:city":"Weilerswist- Hausweiler",
    "sg:phone":"+49 2254/7648",
    "sg:postcode":"53919",
    "sg:province":"Nordrhein-Westfalen",
    "wof:name":"Motorradteam Urban",
    "wof:placetype":"venue"
},
  "geometry": {"coordinates":[6.8158578873,50.7148323059],"type":"Point"}
}