{
  "type": "Feature",
  "properties": {
    "iso:country":"DE",
    "sg:address":"Nenzinger Str. 3",
    "sg:city":"Orsingen-Nenzingen",
    "sg:phone":"+49 7774/6499",
    "sg:postcode":"78359",
    "sg:province":"Baden-W\u00fcrttemberg",
    "wof:name":"Pilsbar Wendeltreppen",
    "wof:placetype":"venue"
},
  "geometry": {"coordinates":[8.9591417313,47.8425674438],"type":"Point"}
}