{
  "type": "Feature",
  "properties": {
    "iso:country":"DE",
    "sg:address":"Scheidinger Str. 2",
    "sg:city":"Welver",
    "sg:phone":"+49 2384/760",
    "sg:postcode":"59514",
    "sg:province":"Nordrhein-Westfalen",
    "wof:name":"Katholisches Pfarramt St. Peter Und Paul",
    "wof:placetype":"venue"
},
  "geometry": {"coordinates":[7.9345149994,51.6008758545],"type":"Point"}
}