{
  "type": "Feature",
  "properties": {
    "iso:country":"DE",
    "sg:address":"Lindenstr. 57",
    "sg:city":"Siegburg",
    "sg:phone":"+49 2241/59450",
    "sg:postcode":"53721",
    "sg:province":"Nordrhein-Westfalen",
    "wof:name":"W. Und K. Wierig Industrie-bedachungsges. Mbh",
    "wof:placetype":"venue"
},
  "geometry": {"coordinates":[7.19654,50.79668],"type":"Point"}
}