{
  "type": "Feature",
  "properties": {
    "iso:country":"DE",
    "sg:address":"Am Dillhof 5",
    "sg:city":"Eschau-Hobbach",
    "sg:phone":"+49 9374/97220",
    "sg:postcode":"63863",
    "sg:province":"Bayern",
    "wof:name":"Kinetics Germany Gmbh",
    "wof:placetype":"venue"
},
  "geometry": {"coordinates":[9.25617,49.820786],"type":"Point"}
}