{
  "type": "Feature",
  "properties": {
    "iso:country":"DE",
    "sg:address":"Marktstr. 38",
    "sg:city":"Nettetal",
    "sg:phone":"+49 2153/8653",
    "sg:postcode":"41334",
    "sg:province":"Nordrhein-Westfalen",
    "wof:name":"Dr. Eckehard Thies Tierarzt",
    "wof:placetype":"venue"
},
  "geometry": {"coordinates":[6.2807202339,51.3333892822],"type":"Point"}
}