{
  "type": "Feature",
  "properties": {
    "iso:country":"DE",
    "sg:address":"Hinterer Markt 29",
    "sg:city":"Allersberg",
    "sg:postcode":"90584",
    "sg:province":"Bayern",
    "wof:name":"Jakob Von Gilardische Stiftung",
    "wof:placetype":"venue"
},
  "geometry": {"coordinates":[11.2337760925,49.2500648499],"type":"Point"}
}