{
  "type": "Feature",
  "properties": {
    "iso:country":"DE",
    "sg:address":"Stadorf 11",
    "sg:city":"Schwienau",
    "sg:phone":"+49 5822/2359",
    "sg:postcode":"29593",
    "sg:province":"Niedersachsen",
    "wof:name":"R\u00fcdiger Niemann",
    "wof:placetype":"venue"
},
  "geometry": {"coordinates":[10.401564,52.994503],"type":"Point"}
}