{
  "type": "Feature",
  "properties": {
    "iso:country":"DE",
    "sg:address":"Steinlachstr. 1",
    "sg:city":"Schwaig",
    "sg:phone":"+49 911/500676",
    "sg:postcode":"90571",
    "sg:province":"Bayern",
    "wof:name":"Wolfgang Keil",
    "wof:placetype":"venue"
},
  "geometry": {"coordinates":[11.200785,49.468395],"type":"Point"}
}