{
  "type": "Feature",
  "properties": {
    "iso:country":"DE",
    "sg:address":"Seeleitn 23",
    "sg:city":"M\u00fcnsing",
    "sg:phone":"+49 8177/1743",
    "sg:postcode":"82541",
    "sg:province":"Bayern",
    "wof:name":"Dr. Ralf Corsten",
    "wof:placetype":"venue"
},
  "geometry": {"coordinates":[11.3334732056,47.8881340027],"type":"Point"}
}