{
  "type": "Feature",
  "properties": {
    "iso:country":"DE",
    "sg:address":"Farbgasse 7",
    "sg:city":"Lichtenfels",
    "sg:phone":"+49 9571/2347",
    "sg:postcode":"96215",
    "sg:province":"Bayern",
    "wof:name":"S. M\u00e4usbacher",
    "wof:placetype":"venue"
},
  "geometry": {"coordinates":[11.0616722107,50.1457710266],"type":"Point"}
}