{
  "type": "Feature",
  "properties": {
    "iso:country":"DE",
    "sg:address":"Ostring 7",
    "sg:city":"Wiesbaden",
    "sg:phone":"+49 6122/6405",
    "sg:postcode":"65205",
    "sg:province":"Hessen",
    "wof:name":"Elektro Cassel Gmbh",
    "wof:placetype":"venue"
},
  "geometry": {"coordinates":[8.3445615768,50.0589332581],"type":"Point"}
}