{
  "type": "Feature",
  "properties": {
    "iso:country":"DE",
    "sg:address":"Schmachtendorfer Str. 104",
    "sg:city":"Oberhausen",
    "sg:phone":"+49 208/682896",
    "sg:postcode":"46147",
    "sg:province":"Nordrhein-Westfalen",
    "wof:name":"Therese Daringhoff Gmbh",
    "wof:placetype":"venue"
},
  "geometry": {"coordinates":[6.817978,51.540348],"type":"Point"}
}