{
  "type": "Feature",
  "properties": {
    "iso:country":"DE",
    "sg:address":"Fasanerie 2",
    "sg:city":"Wallerstein",
    "sg:postcode":"86757",
    "sg:province":"Bayern",
    "wof:name":"Gummitechnik Im Ries Gmbh",
    "wof:placetype":"venue"
},
  "geometry": {"coordinates":[10.487998,48.904774],"type":"Point"}
}