{
  "type": "Feature",
  "properties": {
    "iso:country":"DE",
    "sg:address":"Dorfstra\u00dfe 3",
    "sg:city":"Berlinchen",
    "sg:phone":"+49 33966/60209",
    "sg:postcode":"16609",
    "sg:province":"Brandenburg",
    "wof:name":"Reiterhotel Berlinchen An Der Mecklenburger Seenplatte",
    "wof:placetype":"venue"
},
  "geometry": {"coordinates":[-99.0999984741,19.2667007446],"type":"Point"}
}