{
  "type": "Feature",
  "properties": {
    "iso:country":"DE",
    "sg:address":"Riehlstr. 7",
    "sg:city":"Berlin",
    "sg:phone":"+49 30/3217803",
    "sg:postcode":"14057",
    "sg:province":"Berlin",
    "wof:name":"Eva Nawrotzki",
    "wof:placetype":"venue"
},
  "geometry": {"coordinates":[13.2851896286,52.5083045959],"type":"Point"}
}