{
  "type": "Feature",
  "properties": {
    "iso:country":"DE",
    "sg:address":"Ludwigsplatz 30",
    "sg:city":"Straubing",
    "sg:phone":"+49 9421/9400",
    "sg:postcode":"94315",
    "sg:province":"Bayern",
    "wof:name":"Attenkofer'sche Buch-und Kunstdruckerei Verlagsbuchhandlung Ohg",
    "wof:placetype":"venue"
},
  "geometry": {"coordinates":[12.57188,48.881866],"type":"Point"}
}