{
  "type": "Feature",
  "properties": {
    "iso:country":"DE",
    "sg:address":"Dorfstr. 24",
    "sg:city":"Ofterschwang",
    "sg:phone":"+49 8321/4188",
    "sg:postcode":"87527",
    "sg:province":"Bayern",
    "wof:name":"Pension Haslach",
    "wof:placetype":"venue"
},
  "geometry": {"coordinates":[10.2347803116,47.4935493469],"type":"Point"}
}