{
  "type": "Feature",
  "properties": {
    "iso:country":"DE",
    "sg:address":"Eisenacher Str. 44",
    "sg:city":"K\u00fcnzell",
    "sg:phone":"+49 661/32021",
    "sg:postcode":"36093",
    "sg:province":"Hessen",
    "wof:name":"Winfried Will Gmbh & Co. Kg",
    "wof:placetype":"venue"
},
  "geometry": {"coordinates":[9.7179718018,50.5366401672],"type":"Point"}
}