{
  "type": "Feature",
  "properties": {
    "iso:country":"DE",
    "sg:address":"Ursulastr. 1",
    "sg:city":"Dorsten",
    "sg:phone":"+49 2362/43785",
    "sg:postcode":"46282",
    "sg:province":"Nordrhein-Westfalen",
    "wof:name":"Domsch\u00e4nke",
    "wof:placetype":"venue"
},
  "geometry": {"coordinates":[6.9657292366,51.6609077454],"type":"Point"}
}