{
  "type": "Feature",
  "properties": {
    "iso:country":"DE",
    "sg:address":"Untere Haselstr. 1",
    "sg:city":"Singen",
    "sg:phone":"+49 7731/21889",
    "sg:postcode":"78224",
    "sg:province":"Baden-W\u00fcrttemberg",
    "wof:name":"Fritz Vester",
    "wof:placetype":"venue"
},
  "geometry": {"coordinates":[8.843129,47.744831],"type":"Point"}
}