{
  "type": "Feature",
  "properties": {
    "iso:country":"DE",
    "sg:address":"Eidelstedter Platz 21",
    "sg:city":"Hamburg",
    "sg:phone":"+49 40/5707405",
    "sg:postcode":"22523",
    "sg:province":"Hamburg",
    "wof:name":"Manfred Ihn Steuerberater",
    "wof:placetype":"venue"
},
  "geometry": {"coordinates":[9.905257225,53.6085853577],"type":"Point"}
}