{
  "type": "Feature",
  "properties": {
    "iso:country":"DE",
    "sg:address":"Rheinaustr. 182",
    "sg:city":"Bonn",
    "sg:phone":"+49 228/466416",
    "sg:postcode":"53225",
    "sg:province":"Nordrhein-Westfalen",
    "wof:name":"Linzbach Malerwerkst\u00e4tte Gmbh",
    "wof:placetype":"venue"
},
  "geometry": {"coordinates":[7.115828,50.73296],"type":"Point"}
}