{
  "type": "Feature",
  "properties": {
    "iso:country":"DE",
    "sg:address":"Goldshausener Str. 1 a",
    "sg:city":"Marzling",
    "sg:phone":"+49 8161/65957",
    "sg:postcode":"85417",
    "sg:province":"Bayern",
    "wof:name":"Alois Simlechner",
    "wof:placetype":"venue"
},
  "geometry": {"coordinates":[11.7926607132,48.4104919434],"type":"Point"}
}