{
  "type": "Feature",
  "properties": {
    "iso:country":"DE",
    "sg:address":"Friedemannweg 60",
    "sg:city":"Erfurt",
    "sg:phone":"+49 361/4170060",
    "sg:postcode":"99097",
    "sg:province":"Th\u00fcringen",
    "wof:name":"Rewe Schuster Ohg",
    "wof:placetype":"venue"
},
  "geometry": {"coordinates":[11.0582084656,50.9567718506],"type":"Point"}
}