{
  "type": "Feature",
  "properties": {
    "iso:country":"DE",
    "sg:address":"Marktplatz 18",
    "sg:city":"Waldkirchen",
    "sg:phone":"+49 8581/96030",
    "sg:postcode":"94065",
    "sg:province":"Bayern",
    "wof:name":"Streit Stegschuster Und Partner",
    "wof:placetype":"venue"
},
  "geometry": {"coordinates":[13.601029,48.730286],"type":"Point"}
}