{
  "type": "Feature",
  "properties": {
    "iso:country":"DE",
    "sg:address":"Landweg 14 -15",
    "sg:city":"Kavelstorf",
    "sg:phone":"+49 38208/81210",
    "sg:postcode":"18196",
    "sg:province":"Mecklenburg-Vorpommern",
    "wof:name":"Blaschek Tischlerei Gmbh",
    "wof:placetype":"venue"
},
  "geometry": {"coordinates":[12.196888,54.012283],"type":"Point"}
}