{
  "type": "Feature",
  "properties": {
    "iso:country":"DE",
    "sg:address":"Karl-Valentin-Str. 27",
    "sg:city":"Karlsfeld",
    "sg:phone":"+49 8131/94024",
    "sg:postcode":"85757",
    "sg:province":"Bayern",
    "wof:name":"Wolfgang Seehaus Designer",
    "wof:placetype":"venue"
},
  "geometry": {"coordinates":[11.4756860733,48.2307281494],"type":"Point"}
}