{
  "type": "Feature",
  "properties": {
    "iso:country":"DE",
    "sg:address":"Steinheilstr. 1",
    "sg:city":"M\u00fcnchen",
    "sg:phone":"+49 89/521061",
    "sg:postcode":"80333",
    "sg:province":"Bayern",
    "wof:name":"Institut F\u00fcr St\u00e4dtebau Und Wohnungswesen Dtsch. Akademie",
    "wof:placetype":"venue"
},
  "geometry": {"coordinates":[11.5657434464,48.1492042542],"type":"Point"}
}