{
  "type": "Feature",
  "properties": {
    "iso:country":"DE",
    "sg:address":"Fischachstr. 24",
    "sg:city":"Obersontheim",
    "sg:phone":"+49 7973/266",
    "sg:postcode":"74423",
    "sg:province":"Baden-W\u00fcrttemberg",
    "wof:name":"Ev. Pfarramt Mittelfischach",
    "wof:placetype":"venue"
},
  "geometry": {"coordinates":[9.86241436,49.0432472229],"type":"Point"}
}