{
  "type": "Feature",
  "properties": {
    "iso:country":"DE",
    "sg:address":"Roetgenbachstr. 5",
    "sg:city":"Roetgen",
    "sg:phone":"+49 2471/2307",
    "sg:postcode":"52159",
    "sg:province":"Nordrhein-Westfalen",
    "wof:name":"Kurt Pfeifle",
    "wof:placetype":"venue"
},
  "geometry": {"coordinates":[6.2015209198,50.6490211487],"type":"Point"}
}