{
  "type": "Feature",
  "properties": {
    "iso:country":"DE",
    "sg:address":"Czarnikauer Str. 21",
    "sg:city":"Berlin",
    "sg:phone":"+49 30/4457930",
    "sg:postcode":"10439",
    "sg:province":"Berlin",
    "wof:name":"Barbara Kriegs",
    "wof:placetype":"venue"
},
  "geometry": {"coordinates":[13.40756,52.553169],"type":"Point"}
}