{
  "type": "Feature",
  "properties": {
    "iso:country":"DE",
    "sg:address":"Lindenweg 39",
    "sg:city":"Eppstein",
    "sg:phone":"+49 6198/501620",
    "sg:postcode":"65817",
    "sg:province":"Hessen",
    "wof:name":"Mzf Consulting International Gmbh",
    "wof:placetype":"venue"
},
  "geometry": {"coordinates":[8.3847503662,50.1486434937],"type":"Point"}
}