{
  "type": "Feature",
  "properties": {
    "iso:country":"DE",
    "sg:address":"Hagener Str. 357",
    "sg:city":"Gevelsberg",
    "sg:phone":"+49 2332/6806",
    "sg:postcode":"58285",
    "sg:province":"Nordrhein-Westfalen",
    "wof:name":"Hermann H\u00fchn Gmbh & Co. Kg",
    "wof:placetype":"venue"
},
  "geometry": {"coordinates":[7.3818078041,51.3358955383],"type":"Point"}
}