{
  "type": "Feature",
  "properties": {
    "iso:country":"DE",
    "sg:address":"Kellergasse 28-30",
    "sg:city":"B\u00fcdingen",
    "sg:phone":"+49 6042/4494",
    "sg:postcode":"63654",
    "sg:province":"Hessen",
    "wof:name":"Manfred Meuser",
    "wof:placetype":"venue"
},
  "geometry": {"coordinates":[9.118695,50.290409],"type":"Point"}
}