{
  "type": "Feature",
  "properties": {
    "iso:country":"DE",
    "sg:address":"Am Kruchenhof 2",
    "sg:city":"Grevenbroich",
    "sg:phone":"+49 2181/5081",
    "sg:postcode":"41515",
    "sg:province":"Nordrhein-Westfalen",
    "wof:name":"Manfred Zloty",
    "wof:placetype":"venue"
},
  "geometry": {"coordinates":[6.6257581711,51.0683937073],"type":"Point"}
}