{
  "type": "Feature",
  "properties": {
    "iso:country":"DE",
    "sg:address":"Im Weidchen 18",
    "sg:city":"D\u00fcren",
    "sg:phone":"+49 6894/95340",
    "sg:postcode":"52353",
    "sg:province":"Nordrhein-Westfalen",
    "wof:name":"Omlor Speditions Gmbh",
    "wof:placetype":"venue"
},
  "geometry": {"coordinates":[7.1554059982,49.2891464233],"type":"Point"}
}