{
  "type": "Feature",
  "properties": {
    "iso:country":"DE",
    "sg:address":"Stra\u00dfe der Freundschaft 3",
    "sg:city":"Beesdau",
    "sg:phone":"+49 3544/12050",
    "sg:postcode":"15926",
    "sg:province":"Brandenburg",
    "wof:name":"Hans Giersberg",
    "wof:placetype":"venue"
},
  "geometry": {"coordinates":[13.738421,51.794601],"type":"Point"}
}