{
  "type": "Feature",
  "properties": {
    "iso:country":"DE",
    "sg:address":"Oberdorf 21",
    "sg:city":"Rhumspringe",
    "sg:phone":"+49 5529/1365",
    "sg:postcode":"37434",
    "sg:province":"Niedersachsen",
    "wof:name":"J. W\u00fcstefeld",
    "wof:placetype":"venue"
},
  "geometry": {"coordinates":[10.299805,51.585274],"type":"Point"}
}