{
  "type": "Feature",
  "properties": {
    "iso:country":"DE",
    "sg:address":"Zuffenhauser Str. 67",
    "sg:city":"Korntal-M\u00fcnchingen",
    "sg:phone":"+49 711/837095",
    "sg:postcode":"70825",
    "sg:province":"Baden-W\u00fcrttemberg",
    "wof:name":"Wilhelm Hartmann Kg",
    "wof:placetype":"venue"
},
  "geometry": {"coordinates":[9.131581,48.830399],"type":"Point"}
}