{
  "type": "Feature",
  "properties": {
    "iso:country":"DE",
    "sg:address":"Welle 8",
    "sg:city":"Nordwalde",
    "sg:phone":"+49 2573/532",
    "sg:postcode":"48356",
    "sg:province":"Nordrhein-Westfalen",
    "wof:name":"Karl Heck\u00f6tter",
    "wof:placetype":"venue"
},
  "geometry": {"coordinates":[7.4815721512,52.0840835571],"type":"Point"}
}