{
  "type": "Feature",
  "properties": {
    "iso:country":"DE",
    "sg:address":"Windm\u00fchlenweg 5",
    "sg:city":"Ganderkesee",
    "sg:phone":"+49 4223/8127",
    "sg:postcode":"27777",
    "sg:province":"Niedersachsen",
    "wof:name":"Heinrich Ludvik Masseur",
    "wof:placetype":"venue"
},
  "geometry": {"coordinates":[8.533353,53.094482],"type":"Point"}
}