{
  "type": "Feature",
  "properties": {
    "iso:country":"DE",
    "sg:address":"Kaiserstr. 161",
    "sg:city":"Herten",
    "sg:phone":"+49 2366/35728",
    "sg:postcode":"45699",
    "sg:province":"Nordrhein-Westfalen",
    "wof:name":"Werner Hofer",
    "wof:placetype":"venue"
},
  "geometry": {"coordinates":[7.1499361992,51.6001586914],"type":"Point"}
}