{
  "type": "Feature",
  "properties": {
    "iso:country":"DE",
    "sg:address":"Aichelberger Weg 5-3",
    "sg:city":"Weinstadt",
    "sg:phone":"+49 7151/603176",
    "sg:postcode":"71384",
    "sg:province":"Baden-W\u00fcrttemberg",
    "wof:name":"G\u00e4stehaus Gerhard Zeyher",
    "wof:placetype":"venue"
},
  "geometry": {"coordinates":[9.3730211258,48.7789916992],"type":"Point"}
}