{
  "type": "Feature",
  "properties": {
    "iso:country":"DE",
    "sg:address":"Traber Str. 38",
    "sg:city":"K\u00fcps",
    "sg:phone":"+49 9264/7278",
    "sg:postcode":"96328",
    "sg:province":"Bayern",
    "wof:name":"Ernst Gr\u00e4bner",
    "wof:placetype":"venue"
},
  "geometry": {"coordinates":[11.293458,50.199486],"type":"Point"}
}