{
  "type": "Feature",
  "properties": {
    "iso:country":"DE",
    "sg:address":"Niemannstr 12-14",
    "sg:city":"H\u00f6rstel",
    "sg:phone":"+49 5459/80370",
    "sg:postcode":"48477",
    "sg:province":"Nordrhein-Westfalen",
    "wof:name":"Helmig Marketing Service & Logistik Gmbh & Co Kg",
    "wof:placetype":"venue"
},
  "geometry": {"coordinates":[7.570058,52.274799],"type":"Point"}
}