{
  "type": "Feature",
  "properties": {
    "iso:country":"DE",
    "sg:address":"Weststr. 43",
    "sg:city":"Schmallenberg",
    "sg:phone":"+49 2972/6328",
    "sg:postcode":"57392",
    "sg:province":"Nordrhein-Westfalen",
    "wof:name":"Josef Schuessler Inh. H. Bornemann",
    "wof:placetype":"venue"
},
  "geometry": {"coordinates":[8.284755,51.147068],"type":"Point"}
}