{
  "type": "Feature",
  "properties": {
    "iso:country":"DE",
    "sg:address":"Hermann-Albrecht-Str. 28",
    "sg:city":"\u00d6tisheim",
    "sg:phone":"+49 7041/7134",
    "sg:postcode":"75443",
    "sg:province":"Baden-W\u00fcrttemberg",
    "wof:name":"Oskar Erber Ingenieur",
    "wof:placetype":"venue"
},
  "geometry": {"coordinates":[8.8137931824,48.9691925049],"type":"Point"}
}