{
  "type": "Feature",
  "properties": {
    "iso:country":"DE",
    "sg:address":"Alleenstr. 6",
    "sg:city":"Villingen-Schwenningen",
    "sg:phone":"+49 7720/22891",
    "sg:postcode":"78054",
    "sg:province":"Baden-W\u00fcrttemberg",
    "wof:name":"Software S\u00fcdwest Gmbh",
    "wof:placetype":"venue"
},
  "geometry": {"coordinates":[8.5305175781,48.0614585876],"type":"Point"}
}