{
  "type": "Feature",
  "properties": {
    "iso:country":"DE",
    "sg:address":"Keffelker Str. 13",
    "sg:city":"Brilon",
    "sg:phone":"+49 2961/3507",
    "sg:postcode":"59929",
    "sg:province":"Nordrhein-Westfalen",
    "wof:name":"Hans-gerd Kloke",
    "wof:placetype":"venue"
},
  "geometry": {"coordinates":[8.5768547058,51.3958587646],"type":"Point"}
}