{
  "type": "Feature",
  "properties": {
    "iso:country":"DE",
    "sg:address":"Oststr. 58",
    "sg:city":"Meerbusch",
    "sg:phone":"+49 2132/76161",
    "sg:postcode":"40667",
    "sg:province":"Nordrhein-Westfalen",
    "wof:name":"Boley Gmbh",
    "wof:placetype":"venue"
},
  "geometry": {"coordinates":[6.702924,51.244785],"type":"Point"}
}