{
  "type": "Feature",
  "properties": {
    "iso:country":"DE",
    "sg:address":"Johann-Sebastian-Bach-Str. 42",
    "sg:city":"Kyritz",
    "sg:phone":"+49 33971/56600",
    "sg:postcode":"16866",
    "sg:province":"Brandenburg",
    "wof:name":"Meyer-reisen",
    "wof:placetype":"venue"
},
  "geometry": {"coordinates":[12.3961133957,52.9426841736],"type":"Point"}
}