{
  "type": "Feature",
  "properties": {
    "iso:country":"DE",
    "sg:address":"Martin-Schwantes-Str. 45",
    "sg:city":"Gommern",
    "sg:phone":"+49 39200/51402",
    "sg:postcode":"39245",
    "sg:province":"Sachsen-Anhalt",
    "wof:name":"Gustav Kl\u00f6hn",
    "wof:placetype":"venue"
},
  "geometry": {"coordinates":[11.828042984,52.0728492737],"type":"Point"}
}