{
  "type": "Feature",
  "properties": {
    "iso:country":"DE",
    "sg:address":"Hauptstr. 119",
    "sg:city":"Freigericht",
    "sg:phone":"+49 6055/880833",
    "sg:postcode":"63579",
    "sg:province":"Hessen",
    "wof:name":"Restaurant Hubertus",
    "wof:placetype":"venue"
},
  "geometry": {"coordinates":[9.1458511353,50.1387252808],"type":"Point"}
}