{
  "type": "Feature",
  "properties": {
    "iso:country":"DE",
    "sg:address":"Eisinger Str. 15",
    "sg:city":"K\u00e4mpfelbach",
    "sg:phone":"+49 7231/82711",
    "sg:postcode":"75236",
    "sg:province":"Baden-W\u00fcrttemberg",
    "wof:name":"Dill Wohnbau Gmbh",
    "wof:placetype":"venue"
},
  "geometry": {"coordinates":[8.640516,48.933334],"type":"Point"}
}