{
  "type": "Feature",
  "properties": {
    "iso:country":"DE",
    "sg:address":"Dorfstr. 39",
    "sg:city":"Nienhagen",
    "sg:phone":"+49 5144/93636",
    "sg:postcode":"29336",
    "sg:province":"Niedersachsen",
    "wof:name":"Georg Graf Von Perponcher Rechtsanwalt",
    "wof:placetype":"venue"
},
  "geometry": {"coordinates":[10.1057853699,52.5559005737],"type":"Point"}
}