{
  "type": "Feature",
  "properties": {
    "iso:country":"DE",
    "sg:address":"Auf der Platte 6",
    "sg:city":"Bad Homburg",
    "sg:phone":"+49 6172/31262",
    "sg:postcode":"61350",
    "sg:province":"Hessen",
    "wof:name":"Service- Und Handelsgesell- Schaft F\u00fcr Die Chemische",
    "wof:placetype":"venue"
},
  "geometry": {"coordinates":[8.5896081924,50.2427825928],"type":"Point"}
}