{
  "type": "Feature",
  "properties": {
    "iso:country":"DE",
    "sg:address":"Heegenweg 4",
    "sg:city":"Witzenhausen",
    "sg:phone":"+49 5545/1526",
    "sg:postcode":"37217",
    "sg:province":"Hessen",
    "wof:name":"Willi J\u00fchne",
    "wof:placetype":"venue"
},
  "geometry": {"coordinates":[9.762960434,51.3809013367],"type":"Point"}
}